Compiled from "PrettyPrinter.scala"
public final class scala.xml.PrettyPrinter$$anonfun$traverse$1 extends java.lang.Object implements scala.Function1,scala.ScalaObject,java.io.Serializable
  SourceFile: "PrettyPrinter.scala"
  Scala: length = 0x
   
  InnerClass: 
   public final $anonfun$traverse$1=class scala/xml/PrettyPrinter$$anonfun$traverse$1 of class scala/xml/PrettyPrinter
  minor version: 0
  major version: 49
  Constant pool:
Asciz	SourceFile;
Asciz	PrettyPrinter.scala;
Asciz	<clinit>;
Asciz	()V;
Asciz	Code;
Asciz	serialVersionUID;
Asciz	J;
Asciz	scala/xml/PrettyPrinter$$anonfun$traverse$1;
class	scala/xml/PrettyPrinter$$anonfun$traverse$1
NameAndType	serialVersionUID:J
Field	scala/xml/PrettyPrinter$$anonfun$traverse$1.serialVersionUID:J
Asciz	ind$1;
Asciz	I;
Asciz	scope$1;
Asciz	Lscala/xml/NamespaceBinding;;
Asciz	$outer;
Asciz	Lscala/xml/PrettyPrinter;;
Asciz	<init>;
Asciz	(Lscala/xml/PrettyPrinter;Lscala/xml/NamespaceBinding;I)V;
Asciz	LineNumberTable;
Asciz	java/lang/NullPointerException;
class	java/lang/NullPointerException
NameAndType	"<init>":()V
Method	java/lang/NullPointerException."<init>":()V
NameAndType	$outer:Lscala/xml/PrettyPrinter;
Field	scala/xml/PrettyPrinter$$anonfun$traverse$1.$outer:Lscala/xml/PrettyPrinter;
NameAndType	scope$1:Lscala/xml/NamespaceBinding;
Field	scala/xml/PrettyPrinter$$anonfun$traverse$1.scope$1:Lscala/xml/NamespaceBinding;
NameAndType	ind$1:I
Field	scala/xml/PrettyPrinter$$anonfun$traverse$1.ind$1:I
Asciz	java/lang/Object;
class	java/lang/Object
Method	java/lang/Object."<init>":()V
Asciz	scala/Function1$class;
class	scala/Function1$class
Asciz	$init$;
Asciz	(Lscala/Function1;)V;
NameAndType	$init$:(Lscala/Function1;)V
Method	scala/Function1$class.$init$:(Lscala/Function1;)V
Asciz	this;
Asciz	Lscala/xml/PrettyPrinter$$anonfun$traverse$1;;
Asciz	LocalVariableTable;
Asciz	apply;
Asciz	(Ljava/lang/Object;)Ljava/lang/Object;;
Asciz	scala/xml/Node;
class	scala/xml/Node
Asciz	(Lscala/xml/Node;)V;
NameAndType	apply:(Lscala/xml/Node;)V
Method	scala/xml/PrettyPrinter$$anonfun$traverse$1.apply:(Lscala/xml/Node;)V
Asciz	scala/runtime/BoxedUnit;
class	scala/runtime/BoxedUnit
Asciz	UNIT;
Asciz	Lscala/runtime/BoxedUnit;;
NameAndType	UNIT:Lscala/runtime/BoxedUnit;
Field	scala/runtime/BoxedUnit.UNIT:Lscala/runtime/BoxedUnit;
Asciz	v1;
Asciz	Ljava/lang/Object;;
Asciz	scala/xml/PrettyPrinter;
class	scala/xml/PrettyPrinter
Asciz	traverse;
Asciz	(Lscala/xml/Node;Lscala/xml/NamespaceBinding;I)V;
NameAndType	traverse:(Lscala/xml/Node;Lscala/xml/NamespaceBinding;I)V
Method	scala/xml/PrettyPrinter.traverse:(Lscala/xml/Node;Lscala/xml/NamespaceBinding;I)V
Asciz	makeBreak;
NameAndType	makeBreak:()V
Method	scala/xml/PrettyPrinter.makeBreak:()V
Asciz	c;
Asciz	Lscala/xml/Node;;
Asciz	andThen;
Asciz	(Lscala/Function1;)Lscala/Function1;;
Asciz	(Lscala/Function1;Lscala/Function1;)Lscala/Function1;;
NameAndType	andThen:(Lscala/Function1;Lscala/Function1;)Lscala/Function1;
Method	scala/Function1$class.andThen:(Lscala/Function1;Lscala/Function1;)Lscala/Function1;
Asciz	g;
Asciz	Lscala/Function1;;
Asciz	compose;
NameAndType	compose:(Lscala/Function1;Lscala/Function1;)Lscala/Function1;
Method	scala/Function1$class.compose:(Lscala/Function1;Lscala/Function1;)Lscala/Function1;
Asciz	toString;
Asciz	()Ljava/lang/String;;
Asciz	(Lscala/Function1;)Ljava/lang/String;;
NameAndType	toString:(Lscala/Function1;)Ljava/lang/String;
Method	scala/Function1$class.toString:(Lscala/Function1;)Ljava/lang/String;
Asciz	Scala;
Asciz	InnerClasses;
Asciz	$anonfun$traverse$1;
Asciz	scala/Function1;
class	scala/Function1
Asciz	scala/ScalaObject;
class	scala/ScalaObject
Asciz	java/io/Serializable;
class	java/io/Serializable

{
public static final long serialVersionUID;
  Signature: J

private final int ind$1;
  Signature: I

private final scala.xml.NamespaceBinding scope$1;
  Signature: Lscala/xml/NamespaceBinding;

private final scala.xml.PrettyPrinter $outer;
  Signature: Lscala/xml/PrettyPrinter;

public static {};
  Signature: ()V
  Code:
   Stack=2, Locals=0, Args_size=0
	lconst_0
	putstatic	Field serialVersionUID:J
	return
  Labels:

public scala.xml.PrettyPrinter$$anonfun$traverse$1(scala.xml.PrettyPrinter, scala.xml.NamespaceBinding, int);
  Signature: (Lscala/xml/PrettyPrinter;Lscala/xml/NamespaceBinding;I)V
  Code:
   Stack=2, Locals=4, Args_size=4
	aload_1
	ifnonnull	l1 // aload_0
	new	class java/lang/NullPointerException
	dup
	invokespecial	Method java/lang/NullPointerException."<init>":()V
	athrow
l1	aload_0
	aload_1
	putfield	Field $outer:Lscala/xml/PrettyPrinter;
	aload_0
	aload_2
	putfield	Field scope$1:Lscala/xml/NamespaceBinding;
	aload_0
	iload_3
	putfield	Field ind$1:I
	aload_0
	invokespecial	Method java/lang/Object."<init>":()V
	aload_0
	invokestatic	Method scala/Function1$class.$init$:(Lscala/Function1;)V
	return
  Labels:
   	l1 = 12 // aload_0
  LocalVariableTable: 
   Start  Length  Slot  Name   Signature
   0      36      0    this       Lscala/xml/PrettyPrinter$$anonfun$traverse$1;
   0      36      1    $outer       Lscala/xml/PrettyPrinter;


public final java.lang.Object apply(java.lang.Object);
  Signature: (Ljava/lang/Object;)Ljava/lang/Object;
  Code:
   Stack=2, Locals=3, Args_size=2
	aload_0
	getfield	Field $outer:Lscala/xml/PrettyPrinter;
	astore_2
	aload_0
	aload_1
	checkcast	class scala/xml/Node
	invokevirtual	Method apply:(Lscala/xml/Node;)V
	getstatic	Field scala/runtime/BoxedUnit.UNIT:Lscala/runtime/BoxedUnit;
	areturn
  Labels:
  LocalVariableTable: 
   Start  Length  Slot  Name   Signature
   0      17      0    this       Lscala/xml/PrettyPrinter$$anonfun$traverse$1;
   5      12      1    v1       Ljava/lang/Object;


public final void apply(scala.xml.Node);
  Signature: (Lscala/xml/Node;)V
  Code:
   Stack=4, Locals=3, Args_size=2
	aload_0
	getfield	Field $outer:Lscala/xml/PrettyPrinter;
	astore_2
	aload_0
	getfield	Field $outer:Lscala/xml/PrettyPrinter;
	aload_1
	aload_0
	getfield	Field scope$1:Lscala/xml/NamespaceBinding;
	aload_0
	getfield	Field ind$1:I
	invokevirtual	Method scala/xml/PrettyPrinter.traverse:(Lscala/xml/Node;Lscala/xml/NamespaceBinding;I)V
	aload_0
	getfield	Field $outer:Lscala/xml/PrettyPrinter;
	invokevirtual	Method scala/xml/PrettyPrinter.makeBreak:()V
	return
  Labels:
  LocalVariableTable: 
   Start  Length  Slot  Name   Signature
   0      29      0    this       Lscala/xml/PrettyPrinter$$anonfun$traverse$1;
   5      24      1    c       Lscala/xml/Node;


public scala.Function1 andThen(scala.Function1);
  Signature: (Lscala/Function1;)Lscala/Function1;
  Code:
   Stack=2, Locals=2, Args_size=2
	aload_0
	aload_1
	invokestatic	Method scala/Function1$class.andThen:(Lscala/Function1;Lscala/Function1;)Lscala/Function1;
	areturn
  Labels:
  LocalVariableTable: 
   Start  Length  Slot  Name   Signature
   0      6      0    this       Lscala/xml/PrettyPrinter$$anonfun$traverse$1;
   0      6      1    g       Lscala/Function1;


public scala.Function1 compose(scala.Function1);
  Signature: (Lscala/Function1;)Lscala/Function1;
  Code:
   Stack=2, Locals=2, Args_size=2
	aload_0
	aload_1
	invokestatic	Method scala/Function1$class.compose:(Lscala/Function1;Lscala/Function1;)Lscala/Function1;
	areturn
  Labels:
  LocalVariableTable: 
   Start  Length  Slot  Name   Signature
   0      6      0    this       Lscala/xml/PrettyPrinter$$anonfun$traverse$1;
   0      6      1    g       Lscala/Function1;


public java.lang.String toString();
  Signature: ()Ljava/lang/String;
  Code:
   Stack=1, Locals=1, Args_size=1
	aload_0
	invokestatic	Method scala/Function1$class.toString:(Lscala/Function1;)Ljava/lang/String;
	areturn
  Labels:

}

