Compiled from "PrettyPrinter.scala"
public final class scala.xml.PrettyPrinter$$anonfun$makeBox$1 extends java.lang.Object implements scala.Function1,scala.ScalaObject,java.io.Serializable
  SourceFile: "PrettyPrinter.scala"
  Scala: length = 0x
   
  InnerClass: 
   public Item=class scala/xml/PrettyPrinter$Item of class scala/xml/PrettyPrinter
   public final $anonfun$makeBox$1=class scala/xml/PrettyPrinter$$anonfun$makeBox$1 of class scala/xml/PrettyPrinter
  minor version: 0
  major version: 49
  Constant pool:
Asciz	SourceFile;
Asciz	PrettyPrinter.scala;
Asciz	<clinit>;
Asciz	()V;
Asciz	Code;
Asciz	serialVersionUID;
Asciz	J;
Asciz	scala/xml/PrettyPrinter$$anonfun$makeBox$1;
class	scala/xml/PrettyPrinter$$anonfun$makeBox$1
NameAndType	serialVersionUID:J
Field	scala/xml/PrettyPrinter$$anonfun$makeBox$1.serialVersionUID:J
Asciz	$outer;
Asciz	Lscala/xml/PrettyPrinter;;
Asciz	<init>;
Asciz	(Lscala/xml/PrettyPrinter;)V;
Asciz	LineNumberTable;
Asciz	java/lang/NullPointerException;
class	java/lang/NullPointerException
NameAndType	"<init>":()V
Method	java/lang/NullPointerException."<init>":()V
NameAndType	$outer:Lscala/xml/PrettyPrinter;
Field	scala/xml/PrettyPrinter$$anonfun$makeBox$1.$outer:Lscala/xml/PrettyPrinter;
Asciz	java/lang/Object;
class	java/lang/Object
Method	java/lang/Object."<init>":()V
Asciz	scala/Function1$class;
class	scala/Function1$class
Asciz	$init$;
Asciz	(Lscala/Function1;)V;
NameAndType	$init$:(Lscala/Function1;)V
Method	scala/Function1$class.$init$:(Lscala/Function1;)V
Asciz	this;
Asciz	Lscala/xml/PrettyPrinter$$anonfun$makeBox$1;;
Asciz	LocalVariableTable;
Asciz	apply;
Asciz	(Ljava/lang/Object;)Ljava/lang/Object;;
Asciz	scala/xml/PrettyPrinter$Item;
class	scala/xml/PrettyPrinter$Item
Asciz	(Lscala/xml/PrettyPrinter$Item;)V;
NameAndType	apply:(Lscala/xml/PrettyPrinter$Item;)V
Method	scala/xml/PrettyPrinter$$anonfun$makeBox$1.apply:(Lscala/xml/PrettyPrinter$Item;)V
Asciz	scala/runtime/BoxedUnit;
class	scala/runtime/BoxedUnit
Asciz	UNIT;
Asciz	Lscala/runtime/BoxedUnit;;
NameAndType	UNIT:Lscala/runtime/BoxedUnit;
Field	scala/runtime/BoxedUnit.UNIT:Lscala/runtime/BoxedUnit;
Asciz	v1;
Asciz	Ljava/lang/Object;;
Asciz	scala/xml/PrettyPrinter;
class	scala/xml/PrettyPrinter
Asciz	items;
Asciz	()Lscala/collection/immutable/List;;
NameAndType	items:()Lscala/collection/immutable/List;
Method	scala/xml/PrettyPrinter.items:()Lscala/collection/immutable/List;
Asciz	scala/collection/immutable/List;
class	scala/collection/immutable/List
Asciz	$colon$colon;
Asciz	(Ljava/lang/Object;)Lscala/collection/immutable/List;;
NameAndType	$colon$colon:(Ljava/lang/Object;)Lscala/collection/immutable/List;
Method	scala/collection/immutable/List.$colon$colon:(Ljava/lang/Object;)Lscala/collection/immutable/List;
Asciz	items_$eq;
Asciz	(Lscala/collection/immutable/List;)V;
NameAndType	items_$eq:(Lscala/collection/immutable/List;)V
Method	scala/xml/PrettyPrinter.items_$eq:(Lscala/collection/immutable/List;)V
Asciz	andThen;
Asciz	(Lscala/Function1;)Lscala/Function1;;
Asciz	(Lscala/Function1;Lscala/Function1;)Lscala/Function1;;
NameAndType	andThen:(Lscala/Function1;Lscala/Function1;)Lscala/Function1;
Method	scala/Function1$class.andThen:(Lscala/Function1;Lscala/Function1;)Lscala/Function1;
Asciz	g;
Asciz	Lscala/Function1;;
Asciz	compose;
NameAndType	compose:(Lscala/Function1;Lscala/Function1;)Lscala/Function1;
Method	scala/Function1$class.compose:(Lscala/Function1;Lscala/Function1;)Lscala/Function1;
Asciz	toString;
Asciz	()Ljava/lang/String;;
Asciz	(Lscala/Function1;)Ljava/lang/String;;
NameAndType	toString:(Lscala/Function1;)Ljava/lang/String;
Method	scala/Function1$class.toString:(Lscala/Function1;)Ljava/lang/String;
Asciz	Scala;
Asciz	InnerClasses;
Asciz	Item;
Asciz	$anonfun$makeBox$1;
Asciz	scala/Function1;
class	scala/Function1
Asciz	scala/ScalaObject;
class	scala/ScalaObject
Asciz	java/io/Serializable;
class	java/io/Serializable

{
public static final long serialVersionUID;
  Signature: J

private final scala.xml.PrettyPrinter $outer;
  Signature: Lscala/xml/PrettyPrinter;

public static {};
  Signature: ()V
  Code:
   Stack=2, Locals=0, Args_size=0
	lconst_0
	putstatic	Field serialVersionUID:J
	return
  Labels:

public scala.xml.PrettyPrinter$$anonfun$makeBox$1(scala.xml.PrettyPrinter);
  Signature: (Lscala/xml/PrettyPrinter;)V
  Code:
   Stack=2, Locals=2, Args_size=2
	aload_1
	ifnonnull	l1 // aload_0
	new	class java/lang/NullPointerException
	dup
	invokespecial	Method java/lang/NullPointerException."<init>":()V
	athrow
l1	aload_0
	aload_1
	putfield	Field $outer:Lscala/xml/PrettyPrinter;
	aload_0
	invokespecial	Method java/lang/Object."<init>":()V
	aload_0
	invokestatic	Method scala/Function1$class.$init$:(Lscala/Function1;)V
	return
  Labels:
   	l1 = 12 // aload_0
  LocalVariableTable: 
   Start  Length  Slot  Name   Signature
   0      26      0    this       Lscala/xml/PrettyPrinter$$anonfun$makeBox$1;
   0      26      1    $outer       Lscala/xml/PrettyPrinter;


public final java.lang.Object apply(java.lang.Object);
  Signature: (Ljava/lang/Object;)Ljava/lang/Object;
  Code:
   Stack=2, Locals=3, Args_size=2
	aload_0
	getfield	Field $outer:Lscala/xml/PrettyPrinter;
	astore_2
	aload_0
	aload_1
	checkcast	class scala/xml/PrettyPrinter$Item
	invokevirtual	Method apply:(Lscala/xml/PrettyPrinter$Item;)V
	getstatic	Field scala/runtime/BoxedUnit.UNIT:Lscala/runtime/BoxedUnit;
	areturn
  Labels:
  LocalVariableTable: 
   Start  Length  Slot  Name   Signature
   0      17      0    this       Lscala/xml/PrettyPrinter$$anonfun$makeBox$1;
   5      12      1    v1       Ljava/lang/Object;


public final void apply(scala.xml.PrettyPrinter$Item);
  Signature: (Lscala/xml/PrettyPrinter$Item;)V
  Code:
   Stack=3, Locals=3, Args_size=2
	aload_0
	getfield	Field $outer:Lscala/xml/PrettyPrinter;
	astore_2
	aload_0
	getfield	Field $outer:Lscala/xml/PrettyPrinter;
	aload_0
	getfield	Field $outer:Lscala/xml/PrettyPrinter;
	invokevirtual	Method scala/xml/PrettyPrinter.items:()Lscala/collection/immutable/List;
	aload_1
	invokevirtual	Method scala/collection/immutable/List.$colon$colon:(Ljava/lang/Object;)Lscala/collection/immutable/List;
	invokevirtual	Method scala/xml/PrettyPrinter.items_$eq:(Lscala/collection/immutable/List;)V
	return
  Labels:
  LocalVariableTable: 
   Start  Length  Slot  Name   Signature
   0      24      0    this       Lscala/xml/PrettyPrinter$$anonfun$makeBox$1;


public scala.Function1 andThen(scala.Function1);
  Signature: (Lscala/Function1;)Lscala/Function1;
  Code:
   Stack=2, Locals=2, Args_size=2
	aload_0
	aload_1
	invokestatic	Method scala/Function1$class.andThen:(Lscala/Function1;Lscala/Function1;)Lscala/Function1;
	areturn
  Labels:
  LocalVariableTable: 
   Start  Length  Slot  Name   Signature
   0      6      0    this       Lscala/xml/PrettyPrinter$$anonfun$makeBox$1;
   0      6      1    g       Lscala/Function1;


public scala.Function1 compose(scala.Function1);
  Signature: (Lscala/Function1;)Lscala/Function1;
  Code:
   Stack=2, Locals=2, Args_size=2
	aload_0
	aload_1
	invokestatic	Method scala/Function1$class.compose:(Lscala/Function1;Lscala/Function1;)Lscala/Function1;
	areturn
  Labels:
  LocalVariableTable: 
   Start  Length  Slot  Name   Signature
   0      6      0    this       Lscala/xml/PrettyPrinter$$anonfun$makeBox$1;
   0      6      1    g       Lscala/Function1;


public java.lang.String toString();
  Signature: ()Ljava/lang/String;
  Code:
   Stack=1, Locals=1, Args_size=1
	aload_0
	invokestatic	Method scala/Function1$class.toString:(Lscala/Function1;)Ljava/lang/String;
	areturn
  Labels:

}

