Compiled from "PrettyPrinter.scala"
public class scala.xml.PrettyPrinter$Box extends scala.xml.PrettyPrinter$Item implements scala.ScalaObject,scala.Product,java.io.Serializable
  SourceFile: "PrettyPrinter.scala"
  Scala: length = 0x
   
  InnerClass: 
   public Box=class scala/xml/PrettyPrinter$Box of class scala/xml/PrettyPrinter
   public Item=class scala/xml/PrettyPrinter$Item of class scala/xml/PrettyPrinter
  minor version: 0
  major version: 49
  Constant pool:
Asciz	SourceFile;
Asciz	PrettyPrinter.scala;
Asciz	col;
Asciz	I;
Asciz	s;
Asciz	Ljava/lang/String;;
Asciz	productElementName;
Asciz	(I)Ljava/lang/String;;
Asciz	Code;
Asciz	LineNumberTable;
Asciz	scala/Product$class;
class	scala/Product$class
Asciz	(Lscala/Product;I)Ljava/lang/String;;
NameAndType	productElementName:(Lscala/Product;I)Ljava/lang/String;
Method	scala/Product$class.productElementName:(Lscala/Product;I)Ljava/lang/String;
Asciz	this;
Asciz	Lscala/xml/PrettyPrinter$Box;;
Asciz	n;
Asciz	LocalVariableTable;
Asciz	productIterator;
Asciz	()Lscala/collection/Iterator;;
Asciz	(Lscala/Product;)Lscala/collection/Iterator;;
NameAndType	productIterator:(Lscala/Product;)Lscala/collection/Iterator;
Method	scala/Product$class.productIterator:(Lscala/Product;)Lscala/collection/Iterator;
Asciz	productElements;
NameAndType	productElements:(Lscala/Product;)Lscala/collection/Iterator;
Method	scala/Product$class.productElements:(Lscala/Product;)Lscala/collection/Iterator;
Asciz	Deprecated;
Asciz	copy$default$2;
Asciz	()Ljava/lang/String;;
Asciz	scala/xml/PrettyPrinter$Box;
class	scala/xml/PrettyPrinter$Box
NameAndType	s:()Ljava/lang/String;
Method	scala/xml/PrettyPrinter$Box.s:()Ljava/lang/String;
Asciz	copy$default$1;
Asciz	()I;
NameAndType	col:()I
Method	scala/xml/PrettyPrinter$Box.col:()I
NameAndType	col:I
Field	scala/xml/PrettyPrinter$Box.col:I
NameAndType	s:Ljava/lang/String;
Field	scala/xml/PrettyPrinter$Box.s:Ljava/lang/String;
Asciz	copy;
Asciz	(ILjava/lang/String;)Lscala/xml/PrettyPrinter$Box;;
Asciz	scala$xml$PrettyPrinter$Box$$$outer;
Asciz	()Lscala/xml/PrettyPrinter;;
NameAndType	scala$xml$PrettyPrinter$Box$$$outer:()Lscala/xml/PrettyPrinter;
Method	scala/xml/PrettyPrinter$Box.scala$xml$PrettyPrinter$Box$$$outer:()Lscala/xml/PrettyPrinter;
Asciz	<init>;
Asciz	(Lscala/xml/PrettyPrinter;ILjava/lang/String;)V;
NameAndType	"<init>":(Lscala/xml/PrettyPrinter;ILjava/lang/String;)V
Method	scala/xml/PrettyPrinter$Box."<init>":(Lscala/xml/PrettyPrinter;ILjava/lang/String;)V
Asciz	hashCode;
Asciz	scala/runtime/ScalaRunTime$;
class	scala/runtime/ScalaRunTime$
Asciz	MODULE$;
Asciz	Lscala/runtime/ScalaRunTime$;;
NameAndType	MODULE$:Lscala/runtime/ScalaRunTime$;
Field	scala/runtime/ScalaRunTime$.MODULE$:Lscala/runtime/ScalaRunTime$;
Asciz	_hashCode;
Asciz	(Lscala/Product;)I;
NameAndType	_hashCode:(Lscala/Product;)I
Method	scala/runtime/ScalaRunTime$._hashCode:(Lscala/Product;)I
Asciz	toString;
Asciz	_toString;
Asciz	(Lscala/Product;)Ljava/lang/String;;
NameAndType	_toString:(Lscala/Product;)Ljava/lang/String;
Method	scala/runtime/ScalaRunTime$._toString:(Lscala/Product;)Ljava/lang/String;
Asciz	equals;
Asciz	(Ljava/lang/Object;)Z;
Asciz	gd1$1;
Asciz	(ILjava/lang/String;)Z;
NameAndType	gd1$1:(ILjava/lang/String;)Z
Method	scala/xml/PrettyPrinter$Box.gd1$1:(ILjava/lang/String;)Z
Asciz	scala/Equals;
class	scala/Equals
Asciz	canEqual;
NameAndType	canEqual:(Ljava/lang/Object;)Z
InterfaceMethod	scala/Equals.canEqual:(Ljava/lang/Object;)Z
Asciz	temp3;
Asciz	temp4;
Asciz	temp5;
Asciz	productPrefix;
Asciz	Box;
String	Box
Asciz	productArity;
Asciz	productElement;
Asciz	(I)Ljava/lang/Object;;
Asciz	java/lang/IndexOutOfBoundsException;
class	java/lang/IndexOutOfBoundsException
Asciz	scala/runtime/BoxesRunTime;
class	scala/runtime/BoxesRunTime
Asciz	boxToInteger;
Asciz	(I)Ljava/lang/Integer;;
NameAndType	boxToInteger:(I)Ljava/lang/Integer;
Method	scala/runtime/BoxesRunTime.boxToInteger:(I)Ljava/lang/Integer;
Asciz	java/lang/Object;
class	java/lang/Object
NameAndType	toString:()Ljava/lang/String;
Method	java/lang/Object.toString:()Ljava/lang/String;
Asciz	(Ljava/lang/String;)V;
NameAndType	"<init>":(Ljava/lang/String;)V
Method	java/lang/IndexOutOfBoundsException."<init>":(Ljava/lang/String;)V
Asciz	scala/xml/PrettyPrinter$Item;
class	scala/xml/PrettyPrinter$Item
Asciz	$outer;
Asciz	Lscala/xml/PrettyPrinter;;
NameAndType	$outer:Lscala/xml/PrettyPrinter;
Field	scala/xml/PrettyPrinter$Item.$outer:Lscala/xml/PrettyPrinter;
NameAndType	equals:(Ljava/lang/Object;)Z
Method	java/lang/Object.equals:(Ljava/lang/Object;)Z
Asciz	(Lscala/xml/PrettyPrinter;)V;
NameAndType	"<init>":(Lscala/xml/PrettyPrinter;)V
Method	scala/xml/PrettyPrinter$Item."<init>":(Lscala/xml/PrettyPrinter;)V
Asciz	$init$;
Asciz	(Lscala/Product;)V;
NameAndType	$init$:(Lscala/Product;)V
Method	scala/Product$class.$init$:(Lscala/Product;)V
Asciz	Scala;
Asciz	InnerClasses;
Asciz	scala/xml/PrettyPrinter;
class	scala/xml/PrettyPrinter
Asciz	Item;
Asciz	scala/ScalaObject;
class	scala/ScalaObject
Asciz	scala/Product;
class	scala/Product
Asciz	java/io/Serializable;
class	java/io/Serializable

{
private final int col;
  Signature: I

private final java.lang.String s;
  Signature: Ljava/lang/String;

public java.lang.String productElementName(int);
  Signature: (I)Ljava/lang/String;
  Code:
   Stack=2, Locals=2, Args_size=2
	aload_0
	iload_1
	invokestatic	Method scala/Product$class.productElementName:(Lscala/Product;I)Ljava/lang/String;
	areturn
  Labels:
  LocalVariableTable: 
   Start  Length  Slot  Name   Signature
   0      6      0    this       Lscala/xml/PrettyPrinter$Box;
   0      6      1    n       I


public scala.collection.Iterator productIterator();
  Signature: ()Lscala/collection/Iterator;
  Code:
   Stack=1, Locals=1, Args_size=1
	aload_0
	invokestatic	Method scala/Product$class.productIterator:(Lscala/Product;)Lscala/collection/Iterator;
	areturn
  Labels:

public scala.collection.Iterator productElements();
  Signature: ()Lscala/collection/Iterator;
  Code:
   Stack=1, Locals=1, Args_size=1
	aload_0
	invokestatic	Method scala/Product$class.productElements:(Lscala/Product;)Lscala/collection/Iterator;
	areturn
  Labels:
  Deprecated: true

public java.lang.String copy$default$2();
  Signature: ()Ljava/lang/String;
  Code:
   Stack=1, Locals=1, Args_size=1
	aload_0
	invokevirtual	Method s:()Ljava/lang/String;
	areturn
  Labels:

public int copy$default$1();
  Signature: ()I
  Code:
   Stack=1, Locals=1, Args_size=1
	aload_0
	invokevirtual	Method col:()I
	ireturn
  Labels:

public int col();
  Signature: ()I
  Code:
   Stack=1, Locals=1, Args_size=1
	aload_0
	getfield	Field col:I
	ireturn
  Labels:

public java.lang.String s();
  Signature: ()Ljava/lang/String;
  Code:
   Stack=1, Locals=1, Args_size=1
	aload_0
	getfield	Field s:Ljava/lang/String;
	areturn
  Labels:

public scala.xml.PrettyPrinter$Box copy(int, java.lang.String);
  Signature: (ILjava/lang/String;)Lscala/xml/PrettyPrinter$Box;
  Code:
   Stack=5, Locals=3, Args_size=3
	new	class scala/xml/PrettyPrinter$Box
	dup
	aload_0
	invokevirtual	Method scala$xml$PrettyPrinter$Box$$$outer:()Lscala/xml/PrettyPrinter;
	iload_1
	aload_2
	invokespecial	Method "<init>":(Lscala/xml/PrettyPrinter;ILjava/lang/String;)V
	areturn
  Labels:
  LocalVariableTable: 
   Start  Length  Slot  Name   Signature
   0      14      0    this       Lscala/xml/PrettyPrinter$Box;
   0      14      1    col       I
   0      14      2    s       Ljava/lang/String;


public int hashCode();
  Signature: ()I
  Code:
   Stack=2, Locals=1, Args_size=1
	getstatic	Field scala/runtime/ScalaRunTime$.MODULE$:Lscala/runtime/ScalaRunTime$;
	aload_0
	invokevirtual	Method scala/runtime/ScalaRunTime$._hashCode:(Lscala/Product;)I
	ireturn
  Labels:

public java.lang.String toString();
  Signature: ()Ljava/lang/String;
  Code:
   Stack=2, Locals=1, Args_size=1
	getstatic	Field scala/runtime/ScalaRunTime$.MODULE$:Lscala/runtime/ScalaRunTime$;
	aload_0
	invokevirtual	Method scala/runtime/ScalaRunTime$._toString:(Lscala/Product;)Ljava/lang/String;
	areturn
  Labels:

public boolean equals(java.lang.Object);
  Signature: (Ljava/lang/Object;)Z
  Code:
   Stack=3, Locals=5, Args_size=2
	aload_0
	aload_1
	if_acmpeq	l1 // iconst_1
	aload_1
	instanceof	class scala/xml/PrettyPrinter$Box
	ifeq	l2 // iconst_0
	aload_1
	checkcast	class scala/xml/PrettyPrinter$Box
	invokevirtual	Method scala$xml$PrettyPrinter$Box$$$outer:()Lscala/xml/PrettyPrinter;
	aload_0
	invokevirtual	Method scala$xml$PrettyPrinter$Box$$$outer:()Lscala/xml/PrettyPrinter;
	if_acmpne	l2 // iconst_0
	aload_1
	checkcast	class scala/xml/PrettyPrinter$Box
	astore_2
	aload_2
	invokevirtual	Method col:()I
	istore_3
	aload_2
	invokevirtual	Method s:()Ljava/lang/String;
	astore	4
	aload_0
	iload_3
	aload	4
	invokespecial	Method gd1$1:(ILjava/lang/String;)Z
	ifeq	l3 // iconst_0
	aload_1
	checkcast	class scala/xml/PrettyPrinter$Box
	aload_0
	invokeinterface	InterfaceMethod scala/Equals.canEqual:(Ljava/lang/Object;)Z
	goto	l4 // ifeq
l3	iconst_0
	goto	l4 // ifeq
l2	iconst_0
l4	ifeq	l5 // iconst_0
l1	iconst_1
	goto	l6 // ireturn
l5	iconst_0
l6	ireturn
  Labels:
   	l3 = 65 // iconst_0
   	l2 = 69 // iconst_0
   	l4 = 70 // ifeq
   	l1 = 73 // iconst_1
   	l5 = 77 // iconst_0
   	l6 = 78 // ireturn
  LocalVariableTable: 
   Start  Length  Slot  Name   Signature
   0      79      0    this       Lscala/xml/PrettyPrinter$Box;
   31      38      2    temp3       Lscala/xml/PrettyPrinter$Box;
   36      33      3    temp4       I
   42      27      4    temp5       Ljava/lang/String;


public java.lang.String productPrefix();
  Signature: ()Ljava/lang/String;
  Code:
   Stack=1, Locals=1, Args_size=1
	ldc	String Box
	areturn
  Labels:

public int productArity();
  Signature: ()I
  Code:
   Stack=1, Locals=1, Args_size=1
	iconst_2
	ireturn
  Labels:

public java.lang.Object productElement(int);
  Signature: (I)Ljava/lang/Object;
  Code:
   Stack=3, Locals=3, Args_size=2
	iload_1
	tableswitch{ //0 to 1
		0: 46;
		1: 39;
		default: 24 }
	new	class java/lang/IndexOutOfBoundsException
	dup
	iload_1
	invokestatic	Method scala/runtime/BoxesRunTime.boxToInteger:(I)Ljava/lang/Integer;
	invokevirtual	Method java/lang/Object.toString:()Ljava/lang/String;
	invokespecial	Method java/lang/IndexOutOfBoundsException."<init>":(Ljava/lang/String;)V
	athrow
	aload_0
	invokevirtual	Method s:()Ljava/lang/String;
	goto	l1 // areturn
	aload_0
	invokevirtual	Method col:()I
	istore_2
	iload_2
	invokestatic	Method scala/runtime/BoxesRunTime.boxToInteger:(I)Ljava/lang/Integer;
l1	areturn
  Labels:
   	l1 = 55 // areturn

public boolean canEqual(java.lang.Object);
  Signature: (Ljava/lang/Object;)Z
  Code:
   Stack=1, Locals=2, Args_size=2
	aload_1
	instanceof	class scala/xml/PrettyPrinter$Box
	ireturn
  Labels:

public scala.xml.PrettyPrinter scala$xml$PrettyPrinter$Box$$$outer();
  Signature: ()Lscala/xml/PrettyPrinter;
  Code:
   Stack=1, Locals=1, Args_size=1
	aload_0
	getfield	Field scala/xml/PrettyPrinter$Item.$outer:Lscala/xml/PrettyPrinter;
	areturn
  Labels:

private final boolean gd1$1(int, java.lang.String);
  Signature: (ILjava/lang/String;)Z
  Code:
   Stack=2, Locals=4, Args_size=3
	iload_1
	aload_0
	invokevirtual	Method col:()I
	if_icmpne	l1 // iconst_0
	aload_2
	aload_0
	invokevirtual	Method s:()Ljava/lang/String;
	astore_3
	dup
	ifnonnull	l2 // aload_3
	pop
	aload_3
	ifnull	l3 // iconst_1
	goto	l1 // iconst_0
l2	aload_3
	invokevirtual	Method java/lang/Object.equals:(Ljava/lang/Object;)Z
	ifeq	l1 // iconst_0
l3	iconst_1
	goto	l4 // ireturn
l1	iconst_0
l4	ireturn
  Labels:
   	l2 = 26 // aload_3
   	l3 = 33 // iconst_1
   	l1 = 37 // iconst_0
   	l4 = 38 // ireturn

public scala.xml.PrettyPrinter$Box(scala.xml.PrettyPrinter, int, java.lang.String);
  Signature: (Lscala/xml/PrettyPrinter;ILjava/lang/String;)V
  Code:
   Stack=2, Locals=4, Args_size=4
	aload_0
	iload_2
	putfield	Field col:I
	aload_0
	aload_3
	putfield	Field s:Ljava/lang/String;
	aload_0
	aload_1
	invokespecial	Method scala/xml/PrettyPrinter$Item."<init>":(Lscala/xml/PrettyPrinter;)V
	aload_0
	invokestatic	Method scala/Product$class.$init$:(Lscala/Product;)V
	return
  Labels:
  LocalVariableTable: 
   Start  Length  Slot  Name   Signature
   0      20      0    this       Lscala/xml/PrettyPrinter$Box;
   0      20      1    $outer       Lscala/xml/PrettyPrinter;
   0      20      2    col       I
   0      20      3    s       Ljava/lang/String;


}

