Compiled from "PrettyPrinter.scala"
public final class scala.xml.PrettyPrinter$$anonfun$format$1 extends java.lang.Object implements scala.Function1,scala.ScalaObject,java.io.Serializable
  SourceFile: "PrettyPrinter.scala"
  Scala: length = 0x
   
  InnerClass: 
   public #140= #100 of #57; //Box=class scala/xml/PrettyPrinter$Box of class scala/xml/PrettyPrinter
   public #141= #113 of #57; //Para=class scala/xml/PrettyPrinter$Para of class scala/xml/PrettyPrinter
   public #142= #50 of #57; //Item=class scala/xml/PrettyPrinter$Item of class scala/xml/PrettyPrinter
   public final #143= #9 of #57; //$anonfun$format$1=class scala/xml/PrettyPrinter$$anonfun$format$1 of class scala/xml/PrettyPrinter
  minor version: 0
  major version: 49
  Constant pool:
const #1 = Asciz	SourceFile;
const #2 = Asciz	PrettyPrinter.scala;
const #3 = Asciz	<clinit>;
const #4 = Asciz	()V;
const #5 = Asciz	Code;
const #6 = Asciz	serialVersionUID;
const #7 = Asciz	J;
const #8 = Asciz	scala/xml/PrettyPrinter$$anonfun$format$1;
const #9 = class	#8;	//  scala/xml/PrettyPrinter$$anonfun$format$1
const #10 = NameAndType	#6:#7;//  serialVersionUID:J
const #11 = Field	#9.#10;	//  scala/xml/PrettyPrinter$$anonfun$format$1.serialVersionUID:J
const #12 = Asciz	cur$1;
const #13 = Asciz	Lscala/runtime/IntRef;;
const #14 = Asciz	lastwasbreak$1;
const #15 = Asciz	Lscala/runtime/BooleanRef;;
const #16 = Asciz	sb$1;
const #17 = Asciz	Lscala/collection/mutable/StringBuilder;;
const #18 = Asciz	$outer;
const #19 = Asciz	Lscala/xml/PrettyPrinter;;
const #20 = Asciz	<init>;
const #21 = Asciz	(Lscala/xml/PrettyPrinter;Lscala/collection/mutable/StringBuilder;Lscala/runtime/BooleanRef;Lscala/runtime/IntRef;)V;
const #22 = Asciz	LineNumberTable;
const #23 = Asciz	java/lang/NullPointerException;
const #24 = class	#23;	//  java/lang/NullPointerException
const #25 = NameAndType	#20:#4;//  "<init>":()V
const #26 = Method	#24.#25;	//  java/lang/NullPointerException."<init>":()V
const #27 = NameAndType	#18:#19;//  $outer:Lscala/xml/PrettyPrinter;
const #28 = Field	#9.#27;	//  scala/xml/PrettyPrinter$$anonfun$format$1.$outer:Lscala/xml/PrettyPrinter;
const #29 = NameAndType	#16:#17;//  sb$1:Lscala/collection/mutable/StringBuilder;
const #30 = Field	#9.#29;	//  scala/xml/PrettyPrinter$$anonfun$format$1.sb$1:Lscala/collection/mutable/StringBuilder;
const #31 = NameAndType	#14:#15;//  lastwasbreak$1:Lscala/runtime/BooleanRef;
const #32 = Field	#9.#31;	//  scala/xml/PrettyPrinter$$anonfun$format$1.lastwasbreak$1:Lscala/runtime/BooleanRef;
const #33 = NameAndType	#12:#13;//  cur$1:Lscala/runtime/IntRef;
const #34 = Field	#9.#33;	//  scala/xml/PrettyPrinter$$anonfun$format$1.cur$1:Lscala/runtime/IntRef;
const #35 = Asciz	java/lang/Object;
const #36 = class	#35;	//  java/lang/Object
const #37 = Method	#36.#25;	//  java/lang/Object."<init>":()V
const #38 = Asciz	scala/Function1$class;
const #39 = class	#38;	//  scala/Function1$class
const #40 = Asciz	$init$;
const #41 = Asciz	(Lscala/Function1;)V;
const #42 = NameAndType	#40:#41;//  $init$:(Lscala/Function1;)V
const #43 = Method	#39.#42;	//  scala/Function1$class.$init$:(Lscala/Function1;)V
const #44 = Asciz	this;
const #45 = Asciz	Lscala/xml/PrettyPrinter$$anonfun$format$1;;
const #46 = Asciz	LocalVariableTable;
const #47 = Asciz	apply;
const #48 = Asciz	(Ljava/lang/Object;)Ljava/lang/Object;;
const #49 = Asciz	scala/xml/PrettyPrinter$Item;
const #50 = class	#49;	//  scala/xml/PrettyPrinter$Item
const #51 = Asciz	(Lscala/xml/PrettyPrinter$Item;)Ljava/lang/Object;;
const #52 = NameAndType	#47:#51;//  apply:(Lscala/xml/PrettyPrinter$Item;)Ljava/lang/Object;
const #53 = Method	#9.#52;	//  scala/xml/PrettyPrinter$$anonfun$format$1.apply:(Lscala/xml/PrettyPrinter$Item;)Ljava/lang/Object;
const #54 = Asciz	v1;
const #55 = Asciz	Ljava/lang/Object;;
const #56 = Asciz	scala/xml/PrettyPrinter;
const #57 = class	#56;	//  scala/xml/PrettyPrinter
const #58 = Asciz	Break;
const #59 = Asciz	()Lscala/xml/PrettyPrinter$Break$;;
const #60 = NameAndType	#58:#59;//  Break:()Lscala/xml/PrettyPrinter$Break$;
const #61 = Method	#57.#60;	//  scala/xml/PrettyPrinter.Break:()Lscala/xml/PrettyPrinter$Break$;
const #62 = Asciz	equals;
const #63 = Asciz	(Ljava/lang/Object;)Z;
const #64 = NameAndType	#62:#63;//  equals:(Ljava/lang/Object;)Z
const #65 = Method	#36.#64;	//  java/lang/Object.equals:(Ljava/lang/Object;)Z
const #66 = Asciz	scala/runtime/BooleanRef;
const #67 = class	#66;	//  scala/runtime/BooleanRef
const #68 = Asciz	elem;
const #69 = Asciz	Z;
const #70 = NameAndType	#68:#69;//  elem:Z
const #71 = Field	#67.#70;	//  scala/runtime/BooleanRef.elem:Z
const #72 = Asciz	scala/runtime/BoxedUnit;
const #73 = class	#72;	//  scala/runtime/BoxedUnit
const #74 = Asciz	UNIT;
const #75 = Asciz	Lscala/runtime/BoxedUnit;;
const #76 = NameAndType	#74:#75;//  UNIT:Lscala/runtime/BoxedUnit;
const #77 = Field	#73.#76;	//  scala/runtime/BoxedUnit.UNIT:Lscala/runtime/BoxedUnit;
const #78 = int	10;
const #79 = Asciz	scala/collection/mutable/StringBuilder;
const #80 = class	#79;	//  scala/collection/mutable/StringBuilder
const #81 = Asciz	append;
const #82 = Asciz	(C)Lscala/collection/mutable/StringBuilder;;
const #83 = NameAndType	#81:#82;//  append:(C)Lscala/collection/mutable/StringBuilder;
const #84 = Method	#80.#83;	//  scala/collection/mutable/StringBuilder.append:(C)Lscala/collection/mutable/StringBuilder;
const #85 = Asciz	scala/runtime/IntRef;
const #86 = class	#85;	//  scala/runtime/IntRef
const #87 = Asciz	I;
const #88 = NameAndType	#68:#87;//  elem:I
const #89 = Field	#86.#88;	//  scala/runtime/IntRef.elem:I
const #90 = Asciz	scala/MatchError;
const #91 = class	#90;	//  scala/MatchError
const #92 = Asciz	toString;
const #93 = Asciz	()Ljava/lang/String;;
const #94 = NameAndType	#92:#93;//  toString:()Ljava/lang/String;
const #95 = Method	#50.#94;	//  scala/xml/PrettyPrinter$Item.toString:()Ljava/lang/String;
const #96 = Asciz	(Ljava/lang/String;)V;
const #97 = NameAndType	#20:#96;//  "<init>":(Ljava/lang/String;)V
const #98 = Method	#91.#97;	//  scala/MatchError."<init>":(Ljava/lang/String;)V
const #99 = Asciz	scala/xml/PrettyPrinter$Box;
const #100 = class	#99;	//  scala/xml/PrettyPrinter$Box
const #101 = Asciz	col;
const #102 = Asciz	()I;
const #103 = NameAndType	#101:#102;//  col:()I
const #104 = Method	#100.#103;	//  scala/xml/PrettyPrinter$Box.col:()I
const #105 = Asciz	s;
const #106 = NameAndType	#105:#93;//  s:()Ljava/lang/String;
const #107 = Method	#100.#106;	//  scala/xml/PrettyPrinter$Box.s:()Ljava/lang/String;
const #108 = int	32;
const #109 = Asciz	(Ljava/lang/String;)Lscala/collection/mutable/StringBuilder;;
const #110 = NameAndType	#81:#109;//  append:(Ljava/lang/String;)Lscala/collection/mutable/StringBuilder;
const #111 = Method	#80.#110;	//  scala/collection/mutable/StringBuilder.append:(Ljava/lang/String;)Lscala/collection/mutable/StringBuilder;
const #112 = Asciz	scala/xml/PrettyPrinter$Para;
const #113 = class	#112;	//  scala/xml/PrettyPrinter$Para
const #114 = Method	#113.#106;	//  scala/xml/PrettyPrinter$Para.s:()Ljava/lang/String;
const #115 = Asciz	b;
const #116 = Asciz	Lscala/xml/PrettyPrinter$Item;;
const #117 = Asciz	temp47;
const #118 = Asciz	Lscala/xml/PrettyPrinter$Box;;
const #119 = Asciz	temp48;
const #120 = Asciz	temp49;
const #121 = Asciz	Ljava/lang/String;;
const #122 = Asciz	temp50;
const #123 = Asciz	Lscala/xml/PrettyPrinter$Para;;
const #124 = Asciz	temp51;
const #125 = Asciz	andThen;
const #126 = Asciz	(Lscala/Function1;)Lscala/Function1;;
const #127 = Asciz	(Lscala/Function1;Lscala/Function1;)Lscala/Function1;;
const #128 = NameAndType	#125:#127;//  andThen:(Lscala/Function1;Lscala/Function1;)Lscala/Function1;
const #129 = Method	#39.#128;	//  scala/Function1$class.andThen:(Lscala/Function1;Lscala/Function1;)Lscala/Function1;
const #130 = Asciz	g;
const #131 = Asciz	Lscala/Function1;;
const #132 = Asciz	compose;
const #133 = NameAndType	#132:#127;//  compose:(Lscala/Function1;Lscala/Function1;)Lscala/Function1;
const #134 = Method	#39.#133;	//  scala/Function1$class.compose:(Lscala/Function1;Lscala/Function1;)Lscala/Function1;
const #135 = Asciz	(Lscala/Function1;)Ljava/lang/String;;
const #136 = NameAndType	#92:#135;//  toString:(Lscala/Function1;)Ljava/lang/String;
const #137 = Method	#39.#136;	//  scala/Function1$class.toString:(Lscala/Function1;)Ljava/lang/String;
const #138 = Asciz	Scala;
const #139 = Asciz	InnerClasses;
const #140 = Asciz	Box;
const #141 = Asciz	Para;
const #142 = Asciz	Item;
const #143 = Asciz	$anonfun$format$1;
const #144 = Asciz	scala/Function1;
const #145 = class	#144;	//  scala/Function1
const #146 = Asciz	scala/ScalaObject;
const #147 = class	#146;	//  scala/ScalaObject
const #148 = Asciz	java/io/Serializable;
const #149 = class	#148;	//  java/io/Serializable

{
public static final long serialVersionUID;

public static {};
  Code:
   Stack=2, Locals=0, Args_size=0
   0:	lconst_0
   1:	putstatic	#11; //Field serialVersionUID:J
   4:	return

public scala.xml.PrettyPrinter$$anonfun$format$1(scala.xml.PrettyPrinter, scala.collection.mutable.StringBuilder, scala.runtime.BooleanRef, scala.runtime.IntRef);
  Code:
   Stack=2, Locals=5, Args_size=5
   0:	aload_1
   1:	ifnonnull	12
   4:	new	#24; //class java/lang/NullPointerException
   7:	dup
   8:	invokespecial	#26; //Method java/lang/NullPointerException."<init>":()V
   11:	athrow
   12:	aload_0
   13:	aload_1
   14:	putfield	#28; //Field $outer:Lscala/xml/PrettyPrinter;
   17:	aload_0
   18:	aload_2
   19:	putfield	#30; //Field sb$1:Lscala/collection/mutable/StringBuilder;
   22:	aload_0
   23:	aload_3
   24:	putfield	#32; //Field lastwasbreak$1:Lscala/runtime/BooleanRef;
   27:	aload_0
   28:	aload	4
   30:	putfield	#34; //Field cur$1:Lscala/runtime/IntRef;
   33:	aload_0
   34:	invokespecial	#37; //Method java/lang/Object."<init>":()V
   37:	aload_0
   38:	invokestatic	#43; //Method scala/Function1$class.$init$:(Lscala/Function1;)V
   41:	return
  LineNumberTable: 
   line 229: 0

  LocalVariableTable: 
   Start  Length  Slot  Name   Signature
   0      42      0    this       Lscala/xml/PrettyPrinter$$anonfun$format$1;
   0      42      1    $outer       Lscala/xml/PrettyPrinter;


public final java.lang.Object apply(java.lang.Object);
  Code:
   Stack=2, Locals=3, Args_size=2
   0:	aload_0
   1:	getfield	#28; //Field $outer:Lscala/xml/PrettyPrinter;
   4:	astore_2
   5:	aload_0
   6:	aload_1
   7:	checkcast	#50; //class scala/xml/PrettyPrinter$Item
   10:	invokevirtual	#53; //Method apply:(Lscala/xml/PrettyPrinter$Item;)Ljava/lang/Object;
   13:	areturn
  LineNumberTable: 
   line 229: 0

  LocalVariableTable: 
   Start  Length  Slot  Name   Signature
   0      14      0    this       Lscala/xml/PrettyPrinter$$anonfun$format$1;
   5      9      1    v1       Ljava/lang/Object;


public final java.lang.Object apply(scala.xml.PrettyPrinter$Item);
  Code:
   Stack=3, Locals=9, Args_size=2
   0:	aload_0
   1:	getfield	#28; //Field $outer:Lscala/xml/PrettyPrinter;
   4:	astore	8
   6:	aload_1
   7:	aload_0
   8:	getfield	#28; //Field $outer:Lscala/xml/PrettyPrinter;
   11:	invokevirtual	#61; //Method scala/xml/PrettyPrinter.Break:()Lscala/xml/PrettyPrinter$Break$;
   14:	astore_2
   15:	dup
   16:	ifnonnull	27
   19:	pop
   20:	aload_2
   21:	ifnull	34
   24:	goto	98
   27:	aload_2
   28:	invokevirtual	#65; //Method java/lang/Object.equals:(Ljava/lang/Object;)Z
   31:	ifeq	98
   34:	iconst_1
   35:	ifeq	86
   38:	aload_0
   39:	getfield	#32; //Field lastwasbreak$1:Lscala/runtime/BooleanRef;
   42:	getfield	#71; //Field scala/runtime/BooleanRef.elem:Z
   45:	ifeq	54
   48:	getstatic	#77; //Field scala/runtime/BoxedUnit.UNIT:Lscala/runtime/BoxedUnit;
   51:	goto	63
   54:	aload_0
   55:	getfield	#30; //Field sb$1:Lscala/collection/mutable/StringBuilder;
   58:	ldc	#78; //int 10
   60:	invokevirtual	#84; //Method scala/collection/mutable/StringBuilder.append:(C)Lscala/collection/mutable/StringBuilder;
   63:	pop
   64:	aload_0
   65:	getfield	#32; //Field lastwasbreak$1:Lscala/runtime/BooleanRef;
   68:	iconst_1
   69:	putfield	#71; //Field scala/runtime/BooleanRef.elem:Z
   72:	aload_0
   73:	getfield	#34; //Field cur$1:Lscala/runtime/IntRef;
   76:	iconst_0
   77:	putfield	#89; //Field scala/runtime/IntRef.elem:I
   80:	getstatic	#77; //Field scala/runtime/BoxedUnit.UNIT:Lscala/runtime/BoxedUnit;
   83:	goto	240
   86:	new	#91; //class scala/MatchError
   89:	dup
   90:	aload_1
   91:	invokevirtual	#95; //Method scala/xml/PrettyPrinter$Item.toString:()Ljava/lang/String;
   94:	invokespecial	#98; //Method scala/MatchError."<init>":(Ljava/lang/String;)V
   97:	athrow
   98:	aload_1
   99:	instanceof	#100; //class scala/xml/PrettyPrinter$Box
   102:	ifeq	199
   105:	aload_1
   106:	checkcast	#100; //class scala/xml/PrettyPrinter$Box
   109:	astore_3
   110:	aload_3
   111:	invokevirtual	#104; //Method scala/xml/PrettyPrinter$Box.col:()I
   114:	istore	4
   116:	aload_3
   117:	invokevirtual	#107; //Method scala/xml/PrettyPrinter$Box.s:()Ljava/lang/String;
   120:	astore	5
   122:	iconst_1
   123:	ifeq	187
   126:	aload_0
   127:	getfield	#32; //Field lastwasbreak$1:Lscala/runtime/BooleanRef;
   130:	iconst_0
   131:	putfield	#71; //Field scala/runtime/BooleanRef.elem:Z
   134:	aload_0
   135:	getfield	#34; //Field cur$1:Lscala/runtime/IntRef;
   138:	getfield	#89; //Field scala/runtime/IntRef.elem:I
   141:	iload	4
   143:	if_icmpge	175
   146:	aload_0
   147:	getfield	#30; //Field sb$1:Lscala/collection/mutable/StringBuilder;
   150:	ldc	#108; //int 32
   152:	invokevirtual	#84; //Method scala/collection/mutable/StringBuilder.append:(C)Lscala/collection/mutable/StringBuilder;
   155:	pop
   156:	aload_0
   157:	getfield	#34; //Field cur$1:Lscala/runtime/IntRef;
   160:	aload_0
   161:	getfield	#34; //Field cur$1:Lscala/runtime/IntRef;
   164:	getfield	#89; //Field scala/runtime/IntRef.elem:I
   167:	iconst_1
   168:	iadd
   169:	putfield	#89; //Field scala/runtime/IntRef.elem:I
   172:	goto	134
   175:	aload_0
   176:	getfield	#30; //Field sb$1:Lscala/collection/mutable/StringBuilder;
   179:	aload	5
   181:	invokevirtual	#111; //Method scala/collection/mutable/StringBuilder.append:(Ljava/lang/String;)Lscala/collection/mutable/StringBuilder;
   184:	goto	240
   187:	new	#91; //class scala/MatchError
   190:	dup
   191:	aload_1
   192:	invokevirtual	#95; //Method scala/xml/PrettyPrinter$Item.toString:()Ljava/lang/String;
   195:	invokespecial	#98; //Method scala/MatchError."<init>":(Ljava/lang/String;)V
   198:	athrow
   199:	aload_1
   200:	instanceof	#113; //class scala/xml/PrettyPrinter$Para
   203:	ifeq	253
   206:	aload_1
   207:	checkcast	#113; //class scala/xml/PrettyPrinter$Para
   210:	astore	6
   212:	aload	6
   214:	invokevirtual	#114; //Method scala/xml/PrettyPrinter$Para.s:()Ljava/lang/String;
   217:	astore	7
   219:	iconst_1
   220:	ifeq	241
   223:	aload_0
   224:	getfield	#32; //Field lastwasbreak$1:Lscala/runtime/BooleanRef;
   227:	iconst_0
   228:	putfield	#71; //Field scala/runtime/BooleanRef.elem:Z
   231:	aload_0
   232:	getfield	#30; //Field sb$1:Lscala/collection/mutable/StringBuilder;
   235:	aload	7
   237:	invokevirtual	#111; //Method scala/collection/mutable/StringBuilder.append:(Ljava/lang/String;)Lscala/collection/mutable/StringBuilder;
   240:	areturn
   241:	new	#91; //class scala/MatchError
   244:	dup
   245:	aload_1
   246:	invokevirtual	#95; //Method scala/xml/PrettyPrinter$Item.toString:()Ljava/lang/String;
   249:	invokespecial	#98; //Method scala/MatchError."<init>":(Ljava/lang/String;)V
   252:	athrow
   253:	new	#91; //class scala/MatchError
   256:	dup
   257:	aload_1
   258:	invokevirtual	#95; //Method scala/xml/PrettyPrinter$Item.toString:()Ljava/lang/String;
   261:	invokespecial	#98; //Method scala/MatchError."<init>":(Ljava/lang/String;)V
   264:	athrow
  LineNumberTable: 
   line 229: 0
   line 21: 34
   line 231: 38
   line 232: 64
   line 233: 72
   line 229: 86
   line 21: 122
   line 240: 126
   line 241: 134
   line 242: 146
   line 243: 156
   line 245: 175
   line 229: 187
   line 21: 219
   line 247: 223
   line 248: 231
   line 229: 240

  LocalVariableTable: 
   Start  Length  Slot  Name   Signature
   0      265      0    this       Lscala/xml/PrettyPrinter$$anonfun$format$1;
   6      259      1    b       Lscala/xml/PrettyPrinter$Item;
   110      89      3    temp47       Lscala/xml/PrettyPrinter$Box;
   116      83      4    temp48       I
   122      77      5    temp49       Ljava/lang/String;
   212      28      6    temp50       Lscala/xml/PrettyPrinter$Para;
   241      12      6    temp50       Lscala/xml/PrettyPrinter$Para;
   219      21      7    temp51       Ljava/lang/String;
   241      12      7    temp51       Ljava/lang/String;


public scala.Function1 andThen(scala.Function1);
  Code:
   Stack=2, Locals=2, Args_size=2
   0:	aload_0
   1:	aload_1
   2:	invokestatic	#129; //Method scala/Function1$class.andThen:(Lscala/Function1;Lscala/Function1;)Lscala/Function1;
   5:	areturn
  LineNumberTable: 
   line 229: 0

  LocalVariableTable: 
   Start  Length  Slot  Name   Signature
   0      6      0    this       Lscala/xml/PrettyPrinter$$anonfun$format$1;
   0      6      1    g       Lscala/Function1;


public scala.Function1 compose(scala.Function1);
  Code:
   Stack=2, Locals=2, Args_size=2
   0:	aload_0
   1:	aload_1
   2:	invokestatic	#134; //Method scala/Function1$class.compose:(Lscala/Function1;Lscala/Function1;)Lscala/Function1;
   5:	areturn
  LineNumberTable: 
   line 229: 0

  LocalVariableTable: 
   Start  Length  Slot  Name   Signature
   0      6      0    this       Lscala/xml/PrettyPrinter$$anonfun$format$1;
   0      6      1    g       Lscala/Function1;


public java.lang.String toString();
  Code:
   Stack=1, Locals=1, Args_size=1
   0:	aload_0
   1:	invokestatic	#137; //Method scala/Function1$class.toString:(Lscala/Function1;)Ljava/lang/String;
   4:	areturn
  LineNumberTable: 
   line 229: 0


}

