Compiled from "PrettyPrinter.scala"
public final class scala.xml.PrettyPrinter$Para$ extends java.lang.Object implements scala.Function1,scala.ScalaObject
  SourceFile: "PrettyPrinter.scala"
  Scala: length = 0x
   
  InnerClass: 
   public Para=class scala/xml/PrettyPrinter$Para of class scala/xml/PrettyPrinter
  minor version: 0
  major version: 49
  Constant pool:
Asciz	SourceFile;
Asciz	PrettyPrinter.scala;
Asciz	Scala;
Asciz	$outer;
Asciz	Lscala/xml/PrettyPrinter;;
Asciz	toString;
Asciz	()Ljava/lang/String;;
Asciz	Code;
Asciz	LineNumberTable;
Asciz	scala/Function1$class;
class	scala/Function1$class
Asciz	(Lscala/Function1;)Ljava/lang/String;;
NameAndType	toString:(Lscala/Function1;)Ljava/lang/String;
Method	scala/Function1$class.toString:(Lscala/Function1;)Ljava/lang/String;
Asciz	compose;
Asciz	(Lscala/Function1;)Lscala/Function1;;
Asciz	(Lscala/Function1;Lscala/Function1;)Lscala/Function1;;
NameAndType	compose:(Lscala/Function1;Lscala/Function1;)Lscala/Function1;
Method	scala/Function1$class.compose:(Lscala/Function1;Lscala/Function1;)Lscala/Function1;
Asciz	this;
Asciz	Lscala/xml/PrettyPrinter$Para$;;
Asciz	g;
Asciz	Lscala/Function1;;
Asciz	LocalVariableTable;
Asciz	andThen;
NameAndType	andThen:(Lscala/Function1;Lscala/Function1;)Lscala/Function1;
Method	scala/Function1$class.andThen:(Lscala/Function1;Lscala/Function1;)Lscala/Function1;
Asciz	unapply;
Asciz	(Lscala/xml/PrettyPrinter$Para;)Lscala/Some;;
Asciz	scala/Some;
class	scala/Some
Asciz	scala/xml/PrettyPrinter$Para;
class	scala/xml/PrettyPrinter$Para
Asciz	s;
NameAndType	s:()Ljava/lang/String;
Method	scala/xml/PrettyPrinter$Para.s:()Ljava/lang/String;
Asciz	<init>;
Asciz	(Ljava/lang/Object;)V;
NameAndType	"<init>":(Ljava/lang/Object;)V
Method	scala/Some."<init>":(Ljava/lang/Object;)V
Asciz	x$0;
Asciz	Lscala/xml/PrettyPrinter$Para;;
Asciz	apply;
Asciz	(Ljava/lang/String;)Lscala/xml/PrettyPrinter$Para;;
Asciz	scala/xml/PrettyPrinter$Para$;
class	scala/xml/PrettyPrinter$Para$
NameAndType	$outer:Lscala/xml/PrettyPrinter;
Field	scala/xml/PrettyPrinter$Para$.$outer:Lscala/xml/PrettyPrinter;
Asciz	(Lscala/xml/PrettyPrinter;Ljava/lang/String;)V;
NameAndType	"<init>":(Lscala/xml/PrettyPrinter;Ljava/lang/String;)V
Method	scala/xml/PrettyPrinter$Para."<init>":(Lscala/xml/PrettyPrinter;Ljava/lang/String;)V
Asciz	Ljava/lang/String;;
Asciz	(Ljava/lang/Object;)Ljava/lang/Object;;
Asciz	java/lang/String;
class	java/lang/String
NameAndType	apply:(Ljava/lang/String;)Lscala/xml/PrettyPrinter$Para;
Method	scala/xml/PrettyPrinter$Para$.apply:(Ljava/lang/String;)Lscala/xml/PrettyPrinter$Para;
Asciz	v1;
Asciz	Ljava/lang/Object;;
Asciz	(Lscala/xml/PrettyPrinter;)V;
Asciz	java/lang/NullPointerException;
class	java/lang/NullPointerException
Asciz	()V;
NameAndType	"<init>":()V
Method	java/lang/NullPointerException."<init>":()V
Asciz	java/lang/Object;
class	java/lang/Object
Method	java/lang/Object."<init>":()V
Asciz	$init$;
Asciz	(Lscala/Function1;)V;
NameAndType	$init$:(Lscala/Function1;)V
Method	scala/Function1$class.$init$:(Lscala/Function1;)V
Asciz	InnerClasses;
Asciz	scala/xml/PrettyPrinter;
class	scala/xml/PrettyPrinter
Asciz	Para;
Asciz	scala/Function1;
class	scala/Function1
Asciz	scala/ScalaObject;
class	scala/ScalaObject

{
public final scala.xml.PrettyPrinter $outer;
  Signature: Lscala/xml/PrettyPrinter;

public java.lang.String toString();
  Signature: ()Ljava/lang/String;
  Code:
   Stack=1, Locals=1, Args_size=1
	aload_0
	invokestatic	Method scala/Function1$class.toString:(Lscala/Function1;)Ljava/lang/String;
	areturn
  Labels:

public scala.Function1 compose(scala.Function1);
  Signature: (Lscala/Function1;)Lscala/Function1;
  Code:
   Stack=2, Locals=2, Args_size=2
	aload_0
	aload_1
	invokestatic	Method scala/Function1$class.compose:(Lscala/Function1;Lscala/Function1;)Lscala/Function1;
	areturn
  Labels:
  LocalVariableTable: 
   Start  Length  Slot  Name   Signature
   0      6      0    this       Lscala/xml/PrettyPrinter$Para$;
   0      6      1    g       Lscala/Function1;


public scala.Function1 andThen(scala.Function1);
  Signature: (Lscala/Function1;)Lscala/Function1;
  Code:
   Stack=2, Locals=2, Args_size=2
	aload_0
	aload_1
	invokestatic	Method scala/Function1$class.andThen:(Lscala/Function1;Lscala/Function1;)Lscala/Function1;
	areturn
  Labels:
  LocalVariableTable: 
   Start  Length  Slot  Name   Signature
   0      6      0    this       Lscala/xml/PrettyPrinter$Para$;
   0      6      1    g       Lscala/Function1;


public scala.Some unapply(scala.xml.PrettyPrinter$Para);
  Signature: (Lscala/xml/PrettyPrinter$Para;)Lscala/Some;
  Code:
   Stack=3, Locals=2, Args_size=2
	new	class scala/Some
	dup
	aload_1
	invokevirtual	Method scala/xml/PrettyPrinter$Para.s:()Ljava/lang/String;
	invokespecial	Method scala/Some."<init>":(Ljava/lang/Object;)V
	areturn
  Labels:
  LocalVariableTable: 
   Start  Length  Slot  Name   Signature
   0      12      0    this       Lscala/xml/PrettyPrinter$Para$;
   0      12      1    x$0       Lscala/xml/PrettyPrinter$Para;


public scala.xml.PrettyPrinter$Para apply(java.lang.String);
  Signature: (Ljava/lang/String;)Lscala/xml/PrettyPrinter$Para;
  Code:
   Stack=4, Locals=3, Args_size=2
	aload_0
	getfield	Field $outer:Lscala/xml/PrettyPrinter;
	astore_2
	new	class scala/xml/PrettyPrinter$Para
	dup
	aload_0
	getfield	Field $outer:Lscala/xml/PrettyPrinter;
	aload_1
	invokespecial	Method scala/xml/PrettyPrinter$Para."<init>":(Lscala/xml/PrettyPrinter;Ljava/lang/String;)V
	areturn
  Labels:
  LocalVariableTable: 
   Start  Length  Slot  Name   Signature
   0      18      0    this       Lscala/xml/PrettyPrinter$Para$;
   5      13      1    s       Ljava/lang/String;


public java.lang.Object apply(java.lang.Object);
  Signature: (Ljava/lang/Object;)Ljava/lang/Object;
  Code:
   Stack=2, Locals=3, Args_size=2
	aload_0
	getfield	Field $outer:Lscala/xml/PrettyPrinter;
	astore_2
	aload_0
	aload_1
	checkcast	class java/lang/String
	invokevirtual	Method apply:(Ljava/lang/String;)Lscala/xml/PrettyPrinter$Para;
	areturn
  Labels:
  LocalVariableTable: 
   Start  Length  Slot  Name   Signature
   0      14      0    this       Lscala/xml/PrettyPrinter$Para$;
   5      9      1    v1       Ljava/lang/Object;


public scala.xml.PrettyPrinter$Para$(scala.xml.PrettyPrinter);
  Signature: (Lscala/xml/PrettyPrinter;)V
  Code:
   Stack=2, Locals=2, Args_size=2
	aload_1
	ifnonnull	l1 // aload_0
	new	class java/lang/NullPointerException
	dup
	invokespecial	Method java/lang/NullPointerException."<init>":()V
	athrow
l1	aload_0
	aload_1
	putfield	Field $outer:Lscala/xml/PrettyPrinter;
	aload_0
	invokespecial	Method java/lang/Object."<init>":()V
	aload_0
	invokestatic	Method scala/Function1$class.$init$:(Lscala/Function1;)V
	return
  Labels:
   	l1 = 12 // aload_0
  LocalVariableTable: 
   Start  Length  Slot  Name   Signature
   0      26      0    this       Lscala/xml/PrettyPrinter$Para$;
   0      26      1    $outer       Lscala/xml/PrettyPrinter;


}

