Compiled from "PrettyPrinter.scala"
public final class scala.xml.PrettyPrinter$Box$ extends java.lang.Object implements scala.Function2,scala.ScalaObject
  SourceFile: "PrettyPrinter.scala"
  Scala: length = 0x
   
  InnerClass: 
   public Box=class scala/xml/PrettyPrinter$Box of class scala/xml/PrettyPrinter
  minor version: 0
  major version: 49
  Constant pool:
Asciz	SourceFile;
Asciz	PrettyPrinter.scala;
Asciz	Scala;
Asciz	$outer;
Asciz	Lscala/xml/PrettyPrinter;;
Asciz	toString;
Asciz	()Ljava/lang/String;;
Asciz	Code;
Asciz	LineNumberTable;
Asciz	scala/Function2$class;
class	scala/Function2$class
Asciz	(Lscala/Function2;)Ljava/lang/String;;
NameAndType	toString:(Lscala/Function2;)Ljava/lang/String;
Method	scala/Function2$class.toString:(Lscala/Function2;)Ljava/lang/String;
Asciz	curried;
Asciz	()Lscala/Function1;;
Asciz	(Lscala/Function2;)Lscala/Function1;;
NameAndType	curried:(Lscala/Function2;)Lscala/Function1;
Method	scala/Function2$class.curried:(Lscala/Function2;)Lscala/Function1;
Asciz	curry;
NameAndType	curry:(Lscala/Function2;)Lscala/Function1;
Method	scala/Function2$class.curry:(Lscala/Function2;)Lscala/Function1;
Asciz	Deprecated;
Asciz	tupled;
NameAndType	tupled:(Lscala/Function2;)Lscala/Function1;
Method	scala/Function2$class.tupled:(Lscala/Function2;)Lscala/Function1;
Asciz	unapply;
Asciz	(Lscala/xml/PrettyPrinter$Box;)Lscala/Option;;
Asciz	java/lang/Object;
class	java/lang/Object
Asciz	equals;
Asciz	(Ljava/lang/Object;)Z;
NameAndType	equals:(Ljava/lang/Object;)Z
Method	java/lang/Object.equals:(Ljava/lang/Object;)Z
Asciz	scala/None$;
class	scala/None$
Asciz	MODULE$;
Asciz	Lscala/None$;;
NameAndType	MODULE$:Lscala/None$;
Field	scala/None$.MODULE$:Lscala/None$;
Asciz	scala/Some;
class	scala/Some
Asciz	scala/Tuple2;
class	scala/Tuple2
Asciz	scala/xml/PrettyPrinter$Box;
class	scala/xml/PrettyPrinter$Box
Asciz	col;
Asciz	()I;
NameAndType	col:()I
Method	scala/xml/PrettyPrinter$Box.col:()I
Asciz	scala/runtime/BoxesRunTime;
class	scala/runtime/BoxesRunTime
Asciz	boxToInteger;
Asciz	(I)Ljava/lang/Integer;;
NameAndType	boxToInteger:(I)Ljava/lang/Integer;
Method	scala/runtime/BoxesRunTime.boxToInteger:(I)Ljava/lang/Integer;
Asciz	s;
NameAndType	s:()Ljava/lang/String;
Method	scala/xml/PrettyPrinter$Box.s:()Ljava/lang/String;
Asciz	<init>;
Asciz	(Ljava/lang/Object;Ljava/lang/Object;)V;
NameAndType	"<init>":(Ljava/lang/Object;Ljava/lang/Object;)V
Method	scala/Tuple2."<init>":(Ljava/lang/Object;Ljava/lang/Object;)V
Asciz	(Ljava/lang/Object;)V;
NameAndType	"<init>":(Ljava/lang/Object;)V
Method	scala/Some."<init>":(Ljava/lang/Object;)V
Asciz	this;
Asciz	Lscala/xml/PrettyPrinter$Box$;;
Asciz	x$0;
Asciz	Lscala/xml/PrettyPrinter$Box;;
Asciz	LocalVariableTable;
Asciz	apply;
Asciz	(ILjava/lang/String;)Lscala/xml/PrettyPrinter$Box;;
Asciz	scala/xml/PrettyPrinter$Box$;
class	scala/xml/PrettyPrinter$Box$
NameAndType	$outer:Lscala/xml/PrettyPrinter;
Field	scala/xml/PrettyPrinter$Box$.$outer:Lscala/xml/PrettyPrinter;
Asciz	(Lscala/xml/PrettyPrinter;ILjava/lang/String;)V;
NameAndType	"<init>":(Lscala/xml/PrettyPrinter;ILjava/lang/String;)V
Method	scala/xml/PrettyPrinter$Box."<init>":(Lscala/xml/PrettyPrinter;ILjava/lang/String;)V
Asciz	I;
Asciz	Ljava/lang/String;;
Asciz	(Ljava/lang/Object;Ljava/lang/Object;)Ljava/lang/Object;;
Asciz	unboxToInt;
Asciz	(Ljava/lang/Object;)I;
NameAndType	unboxToInt:(Ljava/lang/Object;)I
Method	scala/runtime/BoxesRunTime.unboxToInt:(Ljava/lang/Object;)I
Asciz	java/lang/String;
class	java/lang/String
NameAndType	apply:(ILjava/lang/String;)Lscala/xml/PrettyPrinter$Box;
Method	scala/xml/PrettyPrinter$Box$.apply:(ILjava/lang/String;)Lscala/xml/PrettyPrinter$Box;
Asciz	v1;
Asciz	Ljava/lang/Object;;
Asciz	v2;
Asciz	(Lscala/xml/PrettyPrinter;)V;
Asciz	java/lang/NullPointerException;
class	java/lang/NullPointerException
Asciz	()V;
NameAndType	"<init>":()V
Method	java/lang/NullPointerException."<init>":()V
Method	java/lang/Object."<init>":()V
Asciz	$init$;
Asciz	(Lscala/Function2;)V;
NameAndType	$init$:(Lscala/Function2;)V
Method	scala/Function2$class.$init$:(Lscala/Function2;)V
Asciz	InnerClasses;
Asciz	scala/xml/PrettyPrinter;
class	scala/xml/PrettyPrinter
Asciz	Box;
Asciz	scala/Function2;
class	scala/Function2
Asciz	scala/ScalaObject;
class	scala/ScalaObject

{
private final scala.xml.PrettyPrinter $outer;
  Signature: Lscala/xml/PrettyPrinter;

public java.lang.String toString();
  Signature: ()Ljava/lang/String;
  Code:
   Stack=1, Locals=1, Args_size=1
	aload_0
	invokestatic	Method scala/Function2$class.toString:(Lscala/Function2;)Ljava/lang/String;
	areturn
  Labels:

public scala.Function1 curried();
  Signature: ()Lscala/Function1;
  Code:
   Stack=1, Locals=1, Args_size=1
	aload_0
	invokestatic	Method scala/Function2$class.curried:(Lscala/Function2;)Lscala/Function1;
	areturn
  Labels:

public scala.Function1 curry();
  Signature: ()Lscala/Function1;
  Code:
   Stack=1, Locals=1, Args_size=1
	aload_0
	invokestatic	Method scala/Function2$class.curry:(Lscala/Function2;)Lscala/Function1;
	areturn
  Labels:
  Deprecated: true

public scala.Function1 tupled();
  Signature: ()Lscala/Function1;
  Code:
   Stack=1, Locals=1, Args_size=1
	aload_0
	invokestatic	Method scala/Function2$class.tupled:(Lscala/Function2;)Lscala/Function1;
	areturn
  Labels:

public scala.Option unapply(scala.xml.PrettyPrinter$Box);
  Signature: (Lscala/xml/PrettyPrinter$Box;)Lscala/Option;
  Code:
   Stack=6, Locals=3, Args_size=2
	aload_1
	dup
	astore_2
	ifnull	l1 // getstatic
	aload_2
	aconst_null
	invokevirtual	Method java/lang/Object.equals:(Ljava/lang/Object;)Z
	ifeq	l2 // new
l1	getstatic	Field scala/None$.MODULE$:Lscala/None$;
	goto	l3 // areturn
l2	new	class scala/Some
	dup
	new	class scala/Tuple2
	dup
	aload_1
	invokevirtual	Method scala/xml/PrettyPrinter$Box.col:()I
	invokestatic	Method scala/runtime/BoxesRunTime.boxToInteger:(I)Ljava/lang/Integer;
	aload_1
	invokevirtual	Method scala/xml/PrettyPrinter$Box.s:()Ljava/lang/String;
	invokespecial	Method scala/Tuple2."<init>":(Ljava/lang/Object;Ljava/lang/Object;)V
	invokespecial	Method scala/Some."<init>":(Ljava/lang/Object;)V
l3	areturn
  Labels:
   	l1 = 14 // getstatic
   	l2 = 20 // new
   	l3 = 45 // areturn
  LocalVariableTable: 
   Start  Length  Slot  Name   Signature
   0      46      0    this       Lscala/xml/PrettyPrinter$Box$;
   0      46      1    x$0       Lscala/xml/PrettyPrinter$Box;


public scala.xml.PrettyPrinter$Box apply(int, java.lang.String);
  Signature: (ILjava/lang/String;)Lscala/xml/PrettyPrinter$Box;
  Code:
   Stack=5, Locals=4, Args_size=3
	aload_0
	getfield	Field $outer:Lscala/xml/PrettyPrinter;
	astore_3
	new	class scala/xml/PrettyPrinter$Box
	dup
	aload_0
	getfield	Field $outer:Lscala/xml/PrettyPrinter;
	iload_1
	aload_2
	invokespecial	Method scala/xml/PrettyPrinter$Box."<init>":(Lscala/xml/PrettyPrinter;ILjava/lang/String;)V
	areturn
  Labels:
  LocalVariableTable: 
   Start  Length  Slot  Name   Signature
   0      19      0    this       Lscala/xml/PrettyPrinter$Box$;
   5      14      1    col       I
   5      14      2    s       Ljava/lang/String;


public java.lang.Object apply(java.lang.Object, java.lang.Object);
  Signature: (Ljava/lang/Object;Ljava/lang/Object;)Ljava/lang/Object;
  Code:
   Stack=3, Locals=4, Args_size=3
	aload_0
	getfield	Field $outer:Lscala/xml/PrettyPrinter;
	astore_3
	aload_0
	aload_1
	invokestatic	Method scala/runtime/BoxesRunTime.unboxToInt:(Ljava/lang/Object;)I
	aload_2
	checkcast	class java/lang/String
	invokevirtual	Method apply:(ILjava/lang/String;)Lscala/xml/PrettyPrinter$Box;
	areturn
  Labels:
  LocalVariableTable: 
   Start  Length  Slot  Name   Signature
   0      18      0    this       Lscala/xml/PrettyPrinter$Box$;
   5      13      1    v1       Ljava/lang/Object;
   5      13      2    v2       Ljava/lang/Object;


public scala.xml.PrettyPrinter$Box$(scala.xml.PrettyPrinter);
  Signature: (Lscala/xml/PrettyPrinter;)V
  Code:
   Stack=2, Locals=2, Args_size=2
	aload_1
	ifnonnull	l1 // aload_0
	new	class java/lang/NullPointerException
	dup
	invokespecial	Method java/lang/NullPointerException."<init>":()V
	athrow
l1	aload_0
	aload_1
	putfield	Field $outer:Lscala/xml/PrettyPrinter;
	aload_0
	invokespecial	Method java/lang/Object."<init>":()V
	aload_0
	invokestatic	Method scala/Function2$class.$init$:(Lscala/Function2;)V
	return
  Labels:
   	l1 = 12 // aload_0
  LocalVariableTable: 
   Start  Length  Slot  Name   Signature
   0      26      0    this       Lscala/xml/PrettyPrinter$Box$;
   0      26      1    $outer       Lscala/xml/PrettyPrinter;


}

