Compiled from "PrettyPrinter.scala"
public final class scala.xml.PrettyPrinter$$anonfun$formatNodes$2 extends java.lang.Object implements scala.Function1,scala.ScalaObject,java.io.Serializable
  SourceFile: "PrettyPrinter.scala"
  Scala: length = 0x
   
  InnerClass: 
   public final $anonfun$formatNodes$2=class scala/xml/PrettyPrinter$$anonfun$formatNodes$2 of class scala/xml/PrettyPrinter
  minor version: 0
  major version: 49
  Constant pool:
Asciz	SourceFile;
Asciz	PrettyPrinter.scala;
Asciz	<clinit>;
Asciz	()V;
Asciz	Code;
Asciz	serialVersionUID;
Asciz	J;
Asciz	scala/xml/PrettyPrinter$$anonfun$formatNodes$2;
class	scala/xml/PrettyPrinter$$anonfun$formatNodes$2
NameAndType	serialVersionUID:J
Field	scala/xml/PrettyPrinter$$anonfun$formatNodes$2.serialVersionUID:J
Asciz	sb$2;
Asciz	Lscala/collection/mutable/StringBuilder;;
Asciz	pscope$4;
Asciz	Lscala/xml/NamespaceBinding;;
Asciz	$outer;
Asciz	Lscala/xml/PrettyPrinter;;
Asciz	<init>;
Asciz	(Lscala/xml/PrettyPrinter;Lscala/xml/NamespaceBinding;Lscala/collection/mutable/StringBuilder;)V;
Asciz	LineNumberTable;
Asciz	java/lang/NullPointerException;
class	java/lang/NullPointerException
NameAndType	"<init>":()V
Method	java/lang/NullPointerException."<init>":()V
NameAndType	$outer:Lscala/xml/PrettyPrinter;
Field	scala/xml/PrettyPrinter$$anonfun$formatNodes$2.$outer:Lscala/xml/PrettyPrinter;
NameAndType	pscope$4:Lscala/xml/NamespaceBinding;
Field	scala/xml/PrettyPrinter$$anonfun$formatNodes$2.pscope$4:Lscala/xml/NamespaceBinding;
NameAndType	sb$2:Lscala/collection/mutable/StringBuilder;
Field	scala/xml/PrettyPrinter$$anonfun$formatNodes$2.sb$2:Lscala/collection/mutable/StringBuilder;
Asciz	java/lang/Object;
class	java/lang/Object
Method	java/lang/Object."<init>":()V
Asciz	scala/Function1$class;
class	scala/Function1$class
Asciz	$init$;
Asciz	(Lscala/Function1;)V;
NameAndType	$init$:(Lscala/Function1;)V
Method	scala/Function1$class.$init$:(Lscala/Function1;)V
Asciz	this;
Asciz	Lscala/xml/PrettyPrinter$$anonfun$formatNodes$2;;
Asciz	LocalVariableTable;
Asciz	apply;
Asciz	(Ljava/lang/Object;)Ljava/lang/Object;;
Asciz	scala/xml/Node;
class	scala/xml/Node
Asciz	(Lscala/xml/Node;)Lscala/collection/mutable/StringBuilder;;
NameAndType	apply:(Lscala/xml/Node;)Lscala/collection/mutable/StringBuilder;
Method	scala/xml/PrettyPrinter$$anonfun$formatNodes$2.apply:(Lscala/xml/Node;)Lscala/collection/mutable/StringBuilder;
Asciz	v1;
Asciz	Ljava/lang/Object;;
Asciz	scala/xml/PrettyPrinter;
class	scala/xml/PrettyPrinter
Asciz	format;
Asciz	(Lscala/xml/Node;Lscala/xml/NamespaceBinding;)Ljava/lang/String;;
NameAndType	format:(Lscala/xml/Node;Lscala/xml/NamespaceBinding;)Ljava/lang/String;
Method	scala/xml/PrettyPrinter.format:(Lscala/xml/Node;Lscala/xml/NamespaceBinding;)Ljava/lang/String;
Asciz	scala/collection/mutable/StringBuilder;
class	scala/collection/mutable/StringBuilder
Asciz	append;
Asciz	(Ljava/lang/String;)Lscala/collection/mutable/StringBuilder;;
NameAndType	append:(Ljava/lang/String;)Lscala/collection/mutable/StringBuilder;
Method	scala/collection/mutable/StringBuilder.append:(Ljava/lang/String;)Lscala/collection/mutable/StringBuilder;
Asciz	n;
Asciz	Lscala/xml/Node;;
Asciz	andThen;
Asciz	(Lscala/Function1;)Lscala/Function1;;
Asciz	(Lscala/Function1;Lscala/Function1;)Lscala/Function1;;
NameAndType	andThen:(Lscala/Function1;Lscala/Function1;)Lscala/Function1;
Method	scala/Function1$class.andThen:(Lscala/Function1;Lscala/Function1;)Lscala/Function1;
Asciz	g;
Asciz	Lscala/Function1;;
Asciz	compose;
NameAndType	compose:(Lscala/Function1;Lscala/Function1;)Lscala/Function1;
Method	scala/Function1$class.compose:(Lscala/Function1;Lscala/Function1;)Lscala/Function1;
Asciz	toString;
Asciz	()Ljava/lang/String;;
Asciz	(Lscala/Function1;)Ljava/lang/String;;
NameAndType	toString:(Lscala/Function1;)Ljava/lang/String;
Method	scala/Function1$class.toString:(Lscala/Function1;)Ljava/lang/String;
Asciz	Scala;
Asciz	InnerClasses;
Asciz	$anonfun$formatNodes$2;
Asciz	scala/Function1;
class	scala/Function1
Asciz	scala/ScalaObject;
class	scala/ScalaObject
Asciz	java/io/Serializable;
class	java/io/Serializable

{
public static final long serialVersionUID;
  Signature: J

private final scala.collection.mutable.StringBuilder sb$2;
  Signature: Lscala/collection/mutable/StringBuilder;

private final scala.xml.NamespaceBinding pscope$4;
  Signature: Lscala/xml/NamespaceBinding;

private final scala.xml.PrettyPrinter $outer;
  Signature: Lscala/xml/PrettyPrinter;

public static {};
  Signature: ()V
  Code:
   Stack=2, Locals=0, Args_size=0
	lconst_0
	putstatic	Field serialVersionUID:J
	return
  Labels:

public scala.xml.PrettyPrinter$$anonfun$formatNodes$2(scala.xml.PrettyPrinter, scala.xml.NamespaceBinding, scala.collection.mutable.StringBuilder);
  Signature: (Lscala/xml/PrettyPrinter;Lscala/xml/NamespaceBinding;Lscala/collection/mutable/StringBuilder;)V
  Code:
   Stack=2, Locals=4, Args_size=4
	aload_1
	ifnonnull	l1 // aload_0
	new	class java/lang/NullPointerException
	dup
	invokespecial	Method java/lang/NullPointerException."<init>":()V
	athrow
l1	aload_0
	aload_1
	putfield	Field $outer:Lscala/xml/PrettyPrinter;
	aload_0
	aload_2
	putfield	Field pscope$4:Lscala/xml/NamespaceBinding;
	aload_0
	aload_3
	putfield	Field sb$2:Lscala/collection/mutable/StringBuilder;
	aload_0
	invokespecial	Method java/lang/Object."<init>":()V
	aload_0
	invokestatic	Method scala/Function1$class.$init$:(Lscala/Function1;)V
	return
  Labels:
   	l1 = 12 // aload_0
  LocalVariableTable: 
   Start  Length  Slot  Name   Signature
   0      36      0    this       Lscala/xml/PrettyPrinter$$anonfun$formatNodes$2;
   0      36      1    $outer       Lscala/xml/PrettyPrinter;


public final java.lang.Object apply(java.lang.Object);
  Signature: (Ljava/lang/Object;)Ljava/lang/Object;
  Code:
   Stack=2, Locals=3, Args_size=2
	aload_0
	getfield	Field $outer:Lscala/xml/PrettyPrinter;
	astore_2
	aload_0
	aload_1
	checkcast	class scala/xml/Node
	invokevirtual	Method apply:(Lscala/xml/Node;)Lscala/collection/mutable/StringBuilder;
	areturn
  Labels:
  LocalVariableTable: 
   Start  Length  Slot  Name   Signature
   0      14      0    this       Lscala/xml/PrettyPrinter$$anonfun$formatNodes$2;
   5      9      1    v1       Ljava/lang/Object;


public final scala.collection.mutable.StringBuilder apply(scala.xml.Node);
  Signature: (Lscala/xml/Node;)Lscala/collection/mutable/StringBuilder;
  Code:
   Stack=4, Locals=3, Args_size=2
	aload_0
	getfield	Field $outer:Lscala/xml/PrettyPrinter;
	astore_2
	aload_0
	getfield	Field sb$2:Lscala/collection/mutable/StringBuilder;
	aload_0
	getfield	Field $outer:Lscala/xml/PrettyPrinter;
	aload_1
	aload_0
	getfield	Field pscope$4:Lscala/xml/NamespaceBinding;
	invokevirtual	Method scala/xml/PrettyPrinter.format:(Lscala/xml/Node;Lscala/xml/NamespaceBinding;)Ljava/lang/String;
	invokevirtual	Method scala/collection/mutable/StringBuilder.append:(Ljava/lang/String;)Lscala/collection/mutable/StringBuilder;
	areturn
  Labels:
  LocalVariableTable: 
   Start  Length  Slot  Name   Signature
   0      25      0    this       Lscala/xml/PrettyPrinter$$anonfun$formatNodes$2;
   5      20      1    n       Lscala/xml/Node;


public scala.Function1 andThen(scala.Function1);
  Signature: (Lscala/Function1;)Lscala/Function1;
  Code:
   Stack=2, Locals=2, Args_size=2
	aload_0
	aload_1
	invokestatic	Method scala/Function1$class.andThen:(Lscala/Function1;Lscala/Function1;)Lscala/Function1;
	areturn
  Labels:
  LocalVariableTable: 
   Start  Length  Slot  Name   Signature
   0      6      0    this       Lscala/xml/PrettyPrinter$$anonfun$formatNodes$2;
   0      6      1    g       Lscala/Function1;


public scala.Function1 compose(scala.Function1);
  Signature: (Lscala/Function1;)Lscala/Function1;
  Code:
   Stack=2, Locals=2, Args_size=2
	aload_0
	aload_1
	invokestatic	Method scala/Function1$class.compose:(Lscala/Function1;Lscala/Function1;)Lscala/Function1;
	areturn
  Labels:
  LocalVariableTable: 
   Start  Length  Slot  Name   Signature
   0      6      0    this       Lscala/xml/PrettyPrinter$$anonfun$formatNodes$2;
   0      6      1    g       Lscala/Function1;


public java.lang.String toString();
  Signature: ()Ljava/lang/String;
  Code:
   Stack=1, Locals=1, Args_size=1
	aload_0
	invokestatic	Method scala/Function1$class.toString:(Lscala/Function1;)Ljava/lang/String;
	areturn
  Labels:

}

