Compiled from "PrettyPrinter.scala"
public final class scala.xml.PrettyPrinter$$anonfun$doPreserve$2 extends java.lang.Object implements scala.Function0,scala.ScalaObject,java.io.Serializable
  SourceFile: "PrettyPrinter.scala"
  Scala: length = 0x
   
  InnerClass: 
   public final $anonfun$doPreserve$2=class scala/xml/PrettyPrinter$$anonfun$doPreserve$2 of class scala/xml/PrettyPrinter
  minor version: 0
  major version: 49
  Constant pool:
Asciz	SourceFile;
Asciz	PrettyPrinter.scala;
Asciz	<clinit>;
Asciz	()V;
Asciz	Code;
Asciz	serialVersionUID;
Asciz	J;
Asciz	scala/xml/PrettyPrinter$$anonfun$doPreserve$2;
class	scala/xml/PrettyPrinter$$anonfun$doPreserve$2
NameAndType	serialVersionUID:J
Field	scala/xml/PrettyPrinter$$anonfun$doPreserve$2.serialVersionUID:J
Asciz	<init>;
Asciz	(Lscala/xml/PrettyPrinter;)V;
Asciz	LineNumberTable;
Asciz	java/lang/Object;
class	java/lang/Object
NameAndType	"<init>":()V
Method	java/lang/Object."<init>":()V
Asciz	scala/Function0$class;
class	scala/Function0$class
Asciz	$init$;
Asciz	(Lscala/Function0;)V;
NameAndType	$init$:(Lscala/Function0;)V
Method	scala/Function0$class.$init$:(Lscala/Function0;)V
Asciz	this;
Asciz	Lscala/xml/PrettyPrinter$$anonfun$doPreserve$2;;
Asciz	$outer;
Asciz	Lscala/xml/PrettyPrinter;;
Asciz	LocalVariableTable;
Asciz	apply;
Asciz	()Ljava/lang/Object;;
Asciz	()Z;
NameAndType	apply:()Z
Method	scala/xml/PrettyPrinter$$anonfun$doPreserve$2.apply:()Z
Asciz	scala/runtime/BoxesRunTime;
class	scala/runtime/BoxesRunTime
Asciz	boxToBoolean;
Asciz	(Z)Ljava/lang/Boolean;;
NameAndType	boxToBoolean:(Z)Ljava/lang/Boolean;
Method	scala/runtime/BoxesRunTime.boxToBoolean:(Z)Ljava/lang/Boolean;
Asciz	toString;
Asciz	()Ljava/lang/String;;
Asciz	(Lscala/Function0;)Ljava/lang/String;;
NameAndType	toString:(Lscala/Function0;)Ljava/lang/String;
Method	scala/Function0$class.toString:(Lscala/Function0;)Ljava/lang/String;
Asciz	Scala;
Asciz	InnerClasses;
Asciz	scala/xml/PrettyPrinter;
class	scala/xml/PrettyPrinter
Asciz	$anonfun$doPreserve$2;
Asciz	scala/Function0;
class	scala/Function0
Asciz	scala/ScalaObject;
class	scala/ScalaObject
Asciz	java/io/Serializable;
class	java/io/Serializable

{
public static final long serialVersionUID;
  Signature: J

public static {};
  Signature: ()V
  Code:
   Stack=2, Locals=0, Args_size=0
	lconst_0
	putstatic	Field serialVersionUID:J
	return
  Labels:

public scala.xml.PrettyPrinter$$anonfun$doPreserve$2(scala.xml.PrettyPrinter);
  Signature: (Lscala/xml/PrettyPrinter;)V
  Code:
   Stack=1, Locals=2, Args_size=2
	aload_0
	invokespecial	Method java/lang/Object."<init>":()V
	aload_0
	invokestatic	Method scala/Function0$class.$init$:(Lscala/Function0;)V
	return
  Labels:
  LocalVariableTable: 
   Start  Length  Slot  Name   Signature
   0      9      0    this       Lscala/xml/PrettyPrinter$$anonfun$doPreserve$2;
   0      9      1    $outer       Lscala/xml/PrettyPrinter;


public final java.lang.Object apply();
  Signature: ()Ljava/lang/Object;
  Code:
   Stack=1, Locals=2, Args_size=1
	aload_0
	invokevirtual	Method apply:()Z
	istore_1
	iload_1
	invokestatic	Method scala/runtime/BoxesRunTime.boxToBoolean:(Z)Ljava/lang/Boolean;
	areturn
  Labels:

public final boolean apply();
  Signature: ()Z
  Code:
   Stack=1, Locals=1, Args_size=1
	iconst_0
	ireturn
  Labels:

public java.lang.String toString();
  Signature: ()Ljava/lang/String;
  Code:
   Stack=1, Locals=1, Args_size=1
	aload_0
	invokestatic	Method scala/Function0$class.toString:(Lscala/Function0;)Ljava/lang/String;
	areturn
  Labels:

}

