Compiled from "PrettyPrinter.scala"
public final class scala.xml.PrettyPrinter$$anonfun$formatNodes$1 extends scala.runtime.AbstractFunction1 implements java.io.Serializable
  SourceFile: "PrettyPrinter.scala"
  Scala: length = 0x
   
  InnerClass: 
   public final $anonfun$formatNodes$1=class scala/xml/PrettyPrinter$$anonfun$formatNodes$1 of class scala/xml/PrettyPrinter
  minor version: 0
  major version: 49
  Constant pool:
Asciz	SourceFile;
Asciz	PrettyPrinter.scala;
Asciz	<clinit>;
Asciz	()V;
Asciz	Code;
Asciz	serialVersionUID;
Asciz	J;
Asciz	scala/xml/PrettyPrinter$$anonfun$formatNodes$1;
class	scala/xml/PrettyPrinter$$anonfun$formatNodes$1
NameAndType	serialVersionUID:J
Field	scala/xml/PrettyPrinter$$anonfun$formatNodes$1.serialVersionUID:J
Asciz	pscope$3;
Asciz	Lscala/xml/NamespaceBinding;;
Asciz	nodes$1;
Asciz	Lscala/collection/Seq;;
Asciz	$outer;
Asciz	Lscala/xml/PrettyPrinter;;
Asciz	<init>;
Asciz	(Lscala/xml/PrettyPrinter;Lscala/collection/Seq;Lscala/xml/NamespaceBinding;)V;
Asciz	LineNumberTable;
Asciz	java/lang/NullPointerException;
class	java/lang/NullPointerException
NameAndType	"<init>":()V
Method	java/lang/NullPointerException."<init>":()V
NameAndType	$outer:Lscala/xml/PrettyPrinter;
Field	scala/xml/PrettyPrinter$$anonfun$formatNodes$1.$outer:Lscala/xml/PrettyPrinter;
NameAndType	nodes$1:Lscala/collection/Seq;
Field	scala/xml/PrettyPrinter$$anonfun$formatNodes$1.nodes$1:Lscala/collection/Seq;
NameAndType	pscope$3:Lscala/xml/NamespaceBinding;
Field	scala/xml/PrettyPrinter$$anonfun$formatNodes$1.pscope$3:Lscala/xml/NamespaceBinding;
Asciz	scala/runtime/AbstractFunction1;
class	scala/runtime/AbstractFunction1
Method	scala/runtime/AbstractFunction1."<init>":()V
Asciz	this;
Asciz	Lscala/xml/PrettyPrinter$$anonfun$formatNodes$1;;
Asciz	LocalVariableTable;
Asciz	apply;
Asciz	(Ljava/lang/Object;)Ljava/lang/Object;;
Asciz	scala/collection/mutable/StringBuilder;
class	scala/collection/mutable/StringBuilder
Asciz	(Lscala/collection/mutable/StringBuilder;)V;
NameAndType	apply:(Lscala/collection/mutable/StringBuilder;)V
Method	scala/xml/PrettyPrinter$$anonfun$formatNodes$1.apply:(Lscala/collection/mutable/StringBuilder;)V
Asciz	scala/runtime/BoxedUnit;
class	scala/runtime/BoxedUnit
Asciz	UNIT;
Asciz	Lscala/runtime/BoxedUnit;;
NameAndType	UNIT:Lscala/runtime/BoxedUnit;
Field	scala/runtime/BoxedUnit.UNIT:Lscala/runtime/BoxedUnit;
Asciz	v1;
Asciz	Ljava/lang/Object;;
Asciz	scala/xml/PrettyPrinter;
class	scala/xml/PrettyPrinter
Asciz	formatNodes;
Asciz	(Lscala/collection/Seq;Lscala/xml/NamespaceBinding;Lscala/collection/mutable/StringBuilder;)V;
NameAndType	formatNodes:(Lscala/collection/Seq;Lscala/xml/NamespaceBinding;Lscala/collection/mutable/StringBuilder;)V
Method	scala/xml/PrettyPrinter.formatNodes:(Lscala/collection/Seq;Lscala/xml/NamespaceBinding;Lscala/collection/mutable/StringBuilder;)V
Asciz	Scala;
Asciz	InnerClasses;
Asciz	$anonfun$formatNodes$1;
Asciz	java/io/Serializable;
class	java/io/Serializable

{
public static final long serialVersionUID;
  Signature: J

public final scala.xml.NamespaceBinding pscope$3;
  Signature: Lscala/xml/NamespaceBinding;

public final scala.collection.Seq nodes$1;
  Signature: Lscala/collection/Seq;

public final scala.xml.PrettyPrinter $outer;
  Signature: Lscala/xml/PrettyPrinter;

public static {};
  Signature: ()V
  Code:
   Stack=2, Locals=0, Args_size=0
	lconst_0
	putstatic	Field serialVersionUID:J
	return
  Labels:

public scala.xml.PrettyPrinter$$anonfun$formatNodes$1(scala.xml.PrettyPrinter, scala.collection.Seq, scala.xml.NamespaceBinding);
  Signature: (Lscala/xml/PrettyPrinter;Lscala/collection/Seq;Lscala/xml/NamespaceBinding;)V
  Code:
   Stack=2, Locals=4, Args_size=4
	aload_1
	ifnonnull	l1 // aload_0
	new	class java/lang/NullPointerException
	dup
	invokespecial	Method java/lang/NullPointerException."<init>":()V
	athrow
l1	aload_0
	aload_1
	putfield	Field $outer:Lscala/xml/PrettyPrinter;
	aload_0
	aload_2
	putfield	Field nodes$1:Lscala/collection/Seq;
	aload_0
	aload_3
	putfield	Field pscope$3:Lscala/xml/NamespaceBinding;
	aload_0
	invokespecial	Method scala/runtime/AbstractFunction1."<init>":()V
	return
  Labels:
   	l1 = 12 // aload_0
  LocalVariableTable: 
   Start  Length  Slot  Name   Signature
   0      32      0    this       Lscala/xml/PrettyPrinter$$anonfun$formatNodes$1;
   0      32      1    $outer       Lscala/xml/PrettyPrinter;


public final java.lang.Object apply(java.lang.Object);
  Signature: (Ljava/lang/Object;)Ljava/lang/Object;
  Code:
   Stack=2, Locals=2, Args_size=2
	aload_0
	aload_1
	checkcast	class scala/collection/mutable/StringBuilder
	invokevirtual	Method apply:(Lscala/collection/mutable/StringBuilder;)V
	getstatic	Field scala/runtime/BoxedUnit.UNIT:Lscala/runtime/BoxedUnit;
	areturn
  Labels:
  LocalVariableTable: 
   Start  Length  Slot  Name   Signature
   0      12      0    this       Lscala/xml/PrettyPrinter$$anonfun$formatNodes$1;
   0      12      1    v1       Ljava/lang/Object;


public final void apply(scala.collection.mutable.StringBuilder);
  Signature: (Lscala/collection/mutable/StringBuilder;)V
  Code:
   Stack=4, Locals=2, Args_size=2
	aload_0
	getfield	Field $outer:Lscala/xml/PrettyPrinter;
	aload_0
	getfield	Field nodes$1:Lscala/collection/Seq;
	aload_0
	getfield	Field pscope$3:Lscala/xml/NamespaceBinding;
	aload_1
	invokevirtual	Method scala/xml/PrettyPrinter.formatNodes:(Lscala/collection/Seq;Lscala/xml/NamespaceBinding;Lscala/collection/mutable/StringBuilder;)V
	return
  Labels:

}

