Compiled from "PrettyPrinter.scala"
public final class scala.xml.PrettyPrinter$$anonfun$format$1 extends java.lang.Object implements scala.Function1,scala.ScalaObject,java.io.Serializable
  SourceFile: "PrettyPrinter.scala"
  Scala: length = 0x
   
  InnerClass: 
   public Box=class scala/xml/PrettyPrinter$Box of class scala/xml/PrettyPrinter
   public Para=class scala/xml/PrettyPrinter$Para of class scala/xml/PrettyPrinter
   public Item=class scala/xml/PrettyPrinter$Item of class scala/xml/PrettyPrinter
   public final $anonfun$format$1=class scala/xml/PrettyPrinter$$anonfun$format$1 of class scala/xml/PrettyPrinter
  minor version: 0
  major version: 49
  Constant pool:
Asciz	SourceFile;
Asciz	PrettyPrinter.scala;
Asciz	<clinit>;
Asciz	()V;
Asciz	Code;
Asciz	serialVersionUID;
Asciz	J;
Asciz	scala/xml/PrettyPrinter$$anonfun$format$1;
class	scala/xml/PrettyPrinter$$anonfun$format$1
NameAndType	serialVersionUID:J
Field	scala/xml/PrettyPrinter$$anonfun$format$1.serialVersionUID:J
Asciz	cur$1;
Asciz	Lscala/runtime/IntRef;;
Asciz	lastwasbreak$1;
Asciz	Lscala/runtime/BooleanRef;;
Asciz	sb$1;
Asciz	Lscala/collection/mutable/StringBuilder;;
Asciz	$outer;
Asciz	Lscala/xml/PrettyPrinter;;
Asciz	<init>;
Asciz	(Lscala/xml/PrettyPrinter;Lscala/collection/mutable/StringBuilder;Lscala/runtime/BooleanRef;Lscala/runtime/IntRef;)V;
Asciz	LineNumberTable;
Asciz	java/lang/NullPointerException;
class	java/lang/NullPointerException
NameAndType	"<init>":()V
Method	java/lang/NullPointerException."<init>":()V
NameAndType	$outer:Lscala/xml/PrettyPrinter;
Field	scala/xml/PrettyPrinter$$anonfun$format$1.$outer:Lscala/xml/PrettyPrinter;
NameAndType	sb$1:Lscala/collection/mutable/StringBuilder;
Field	scala/xml/PrettyPrinter$$anonfun$format$1.sb$1:Lscala/collection/mutable/StringBuilder;
NameAndType	lastwasbreak$1:Lscala/runtime/BooleanRef;
Field	scala/xml/PrettyPrinter$$anonfun$format$1.lastwasbreak$1:Lscala/runtime/BooleanRef;
NameAndType	cur$1:Lscala/runtime/IntRef;
Field	scala/xml/PrettyPrinter$$anonfun$format$1.cur$1:Lscala/runtime/IntRef;
Asciz	java/lang/Object;
class	java/lang/Object
Method	java/lang/Object."<init>":()V
Asciz	scala/Function1$class;
class	scala/Function1$class
Asciz	$init$;
Asciz	(Lscala/Function1;)V;
NameAndType	$init$:(Lscala/Function1;)V
Method	scala/Function1$class.$init$:(Lscala/Function1;)V
Asciz	this;
Asciz	Lscala/xml/PrettyPrinter$$anonfun$format$1;;
Asciz	LocalVariableTable;
Asciz	apply;
Asciz	(Ljava/lang/Object;)Ljava/lang/Object;;
Asciz	scala/xml/PrettyPrinter$Item;
class	scala/xml/PrettyPrinter$Item
Asciz	(Lscala/xml/PrettyPrinter$Item;)Ljava/lang/Object;;
NameAndType	apply:(Lscala/xml/PrettyPrinter$Item;)Ljava/lang/Object;
Method	scala/xml/PrettyPrinter$$anonfun$format$1.apply:(Lscala/xml/PrettyPrinter$Item;)Ljava/lang/Object;
Asciz	v1;
Asciz	Ljava/lang/Object;;
Asciz	scala/xml/PrettyPrinter;
class	scala/xml/PrettyPrinter
Asciz	Break;
Asciz	()Lscala/xml/PrettyPrinter$Break$;;
NameAndType	Break:()Lscala/xml/PrettyPrinter$Break$;
Method	scala/xml/PrettyPrinter.Break:()Lscala/xml/PrettyPrinter$Break$;
Asciz	equals;
Asciz	(Ljava/lang/Object;)Z;
NameAndType	equals:(Ljava/lang/Object;)Z
Method	java/lang/Object.equals:(Ljava/lang/Object;)Z
Asciz	scala/runtime/BooleanRef;
class	scala/runtime/BooleanRef
Asciz	elem;
Asciz	Z;
NameAndType	elem:Z
Field	scala/runtime/BooleanRef.elem:Z
Asciz	scala/runtime/BoxedUnit;
class	scala/runtime/BoxedUnit
Asciz	UNIT;
Asciz	Lscala/runtime/BoxedUnit;;
NameAndType	UNIT:Lscala/runtime/BoxedUnit;
Field	scala/runtime/BoxedUnit.UNIT:Lscala/runtime/BoxedUnit;
int	10;
Asciz	scala/collection/mutable/StringBuilder;
class	scala/collection/mutable/StringBuilder
Asciz	append;
Asciz	(C)Lscala/collection/mutable/StringBuilder;;
NameAndType	append:(C)Lscala/collection/mutable/StringBuilder;
Method	scala/collection/mutable/StringBuilder.append:(C)Lscala/collection/mutable/StringBuilder;
Asciz	scala/runtime/IntRef;
class	scala/runtime/IntRef
Asciz	I;
NameAndType	elem:I
Field	scala/runtime/IntRef.elem:I
Asciz	scala/MatchError;
class	scala/MatchError
Asciz	toString;
Asciz	()Ljava/lang/String;;
NameAndType	toString:()Ljava/lang/String;
Method	scala/xml/PrettyPrinter$Item.toString:()Ljava/lang/String;
Asciz	(Ljava/lang/String;)V;
NameAndType	"<init>":(Ljava/lang/String;)V
Method	scala/MatchError."<init>":(Ljava/lang/String;)V
Asciz	scala/xml/PrettyPrinter$Box;
class	scala/xml/PrettyPrinter$Box
Asciz	col;
Asciz	()I;
NameAndType	col:()I
Method	scala/xml/PrettyPrinter$Box.col:()I
Asciz	s;
NameAndType	s:()Ljava/lang/String;
Method	scala/xml/PrettyPrinter$Box.s:()Ljava/lang/String;
int	32;
Asciz	(Ljava/lang/String;)Lscala/collection/mutable/StringBuilder;;
NameAndType	append:(Ljava/lang/String;)Lscala/collection/mutable/StringBuilder;
Method	scala/collection/mutable/StringBuilder.append:(Ljava/lang/String;)Lscala/collection/mutable/StringBuilder;
Asciz	scala/xml/PrettyPrinter$Para;
class	scala/xml/PrettyPrinter$Para
Method	scala/xml/PrettyPrinter$Para.s:()Ljava/lang/String;
Asciz	b;
Asciz	Lscala/xml/PrettyPrinter$Item;;
Asciz	temp47;
Asciz	Lscala/xml/PrettyPrinter$Box;;
Asciz	temp48;
Asciz	temp49;
Asciz	Ljava/lang/String;;
Asciz	temp50;
Asciz	Lscala/xml/PrettyPrinter$Para;;
Asciz	temp51;
Asciz	andThen;
Asciz	(Lscala/Function1;)Lscala/Function1;;
Asciz	(Lscala/Function1;Lscala/Function1;)Lscala/Function1;;
NameAndType	andThen:(Lscala/Function1;Lscala/Function1;)Lscala/Function1;
Method	scala/Function1$class.andThen:(Lscala/Function1;Lscala/Function1;)Lscala/Function1;
Asciz	g;
Asciz	Lscala/Function1;;
Asciz	compose;
NameAndType	compose:(Lscala/Function1;Lscala/Function1;)Lscala/Function1;
Method	scala/Function1$class.compose:(Lscala/Function1;Lscala/Function1;)Lscala/Function1;
Asciz	(Lscala/Function1;)Ljava/lang/String;;
NameAndType	toString:(Lscala/Function1;)Ljava/lang/String;
Method	scala/Function1$class.toString:(Lscala/Function1;)Ljava/lang/String;
Asciz	Scala;
Asciz	InnerClasses;
Asciz	Box;
Asciz	Para;
Asciz	Item;
Asciz	$anonfun$format$1;
Asciz	scala/Function1;
class	scala/Function1
Asciz	scala/ScalaObject;
class	scala/ScalaObject
Asciz	java/io/Serializable;
class	java/io/Serializable

{
public static final long serialVersionUID;
  Signature: J

private final scala.runtime.IntRef cur$1;
  Signature: Lscala/runtime/IntRef;

private final scala.runtime.BooleanRef lastwasbreak$1;
  Signature: Lscala/runtime/BooleanRef;

private final scala.collection.mutable.StringBuilder sb$1;
  Signature: Lscala/collection/mutable/StringBuilder;

private final scala.xml.PrettyPrinter $outer;
  Signature: Lscala/xml/PrettyPrinter;

public static {};
  Signature: ()V
  Code:
   Stack=2, Locals=0, Args_size=0
	lconst_0
	putstatic	Field serialVersionUID:J
	return
  Labels:

public scala.xml.PrettyPrinter$$anonfun$format$1(scala.xml.PrettyPrinter, scala.collection.mutable.StringBuilder, scala.runtime.BooleanRef, scala.runtime.IntRef);
  Signature: (Lscala/xml/PrettyPrinter;Lscala/collection/mutable/StringBuilder;Lscala/runtime/BooleanRef;Lscala/runtime/IntRef;)V
  Code:
   Stack=2, Locals=5, Args_size=5
	aload_1
	ifnonnull	l1 // aload_0
	new	class java/lang/NullPointerException
	dup
	invokespecial	Method java/lang/NullPointerException."<init>":()V
	athrow
l1	aload_0
	aload_1
	putfield	Field $outer:Lscala/xml/PrettyPrinter;
	aload_0
	aload_2
	putfield	Field sb$1:Lscala/collection/mutable/StringBuilder;
	aload_0
	aload_3
	putfield	Field lastwasbreak$1:Lscala/runtime/BooleanRef;
	aload_0
	aload	4
	putfield	Field cur$1:Lscala/runtime/IntRef;
	aload_0
	invokespecial	Method java/lang/Object."<init>":()V
	aload_0
	invokestatic	Method scala/Function1$class.$init$:(Lscala/Function1;)V
	return
  Labels:
   	l1 = 12 // aload_0
  LocalVariableTable: 
   Start  Length  Slot  Name   Signature
   0      42      0    this       Lscala/xml/PrettyPrinter$$anonfun$format$1;
   0      42      1    $outer       Lscala/xml/PrettyPrinter;


public final java.lang.Object apply(java.lang.Object);
  Signature: (Ljava/lang/Object;)Ljava/lang/Object;
  Code:
   Stack=2, Locals=3, Args_size=2
	aload_0
	getfield	Field $outer:Lscala/xml/PrettyPrinter;
	astore_2
	aload_0
	aload_1
	checkcast	class scala/xml/PrettyPrinter$Item
	invokevirtual	Method apply:(Lscala/xml/PrettyPrinter$Item;)Ljava/lang/Object;
	areturn
  Labels:
  LocalVariableTable: 
   Start  Length  Slot  Name   Signature
   0      14      0    this       Lscala/xml/PrettyPrinter$$anonfun$format$1;
   5      9      1    v1       Ljava/lang/Object;


public final java.lang.Object apply(scala.xml.PrettyPrinter$Item);
  Signature: (Lscala/xml/PrettyPrinter$Item;)Ljava/lang/Object;
  Code:
   Stack=3, Locals=9, Args_size=2
	aload_0
	getfield	Field $outer:Lscala/xml/PrettyPrinter;
	astore	8
	aload_1
	aload_0
	getfield	Field $outer:Lscala/xml/PrettyPrinter;
	invokevirtual	Method scala/xml/PrettyPrinter.Break:()Lscala/xml/PrettyPrinter$Break$;
	astore_2
	dup
	ifnonnull	l1 // aload_2
	pop
	aload_2
	ifnull	l2 // iconst_1
	goto	l3 // aload_1
l1	aload_2
	invokevirtual	Method java/lang/Object.equals:(Ljava/lang/Object;)Z
	ifeq	l3 // aload_1
l2	iconst_1
	ifeq	l4 // new
	aload_0
	getfield	Field lastwasbreak$1:Lscala/runtime/BooleanRef;
	getfield	Field scala/runtime/BooleanRef.elem:Z
	ifeq	l5 // aload_0
	getstatic	Field scala/runtime/BoxedUnit.UNIT:Lscala/runtime/BoxedUnit;
	goto	l6 // pop
l5	aload_0
	getfield	Field sb$1:Lscala/collection/mutable/StringBuilder;
	ldc	int 10
	invokevirtual	Method scala/collection/mutable/StringBuilder.append:(C)Lscala/collection/mutable/StringBuilder;
l6	pop
	aload_0
	getfield	Field lastwasbreak$1:Lscala/runtime/BooleanRef;
	iconst_1
	putfield	Field scala/runtime/BooleanRef.elem:Z
	aload_0
	getfield	Field cur$1:Lscala/runtime/IntRef;
	iconst_0
	putfield	Field scala/runtime/IntRef.elem:I
	getstatic	Field scala/runtime/BoxedUnit.UNIT:Lscala/runtime/BoxedUnit;
	goto	l7 // areturn
l4	new	class scala/MatchError
	dup
	aload_1
	invokevirtual	Method scala/xml/PrettyPrinter$Item.toString:()Ljava/lang/String;
	invokespecial	Method scala/MatchError."<init>":(Ljava/lang/String;)V
	athrow
l3	aload_1
	instanceof	class scala/xml/PrettyPrinter$Box
	ifeq	l8 // aload_1
	aload_1
	checkcast	class scala/xml/PrettyPrinter$Box
	astore_3
	aload_3
	invokevirtual	Method scala/xml/PrettyPrinter$Box.col:()I
	istore	4
	aload_3
	invokevirtual	Method scala/xml/PrettyPrinter$Box.s:()Ljava/lang/String;
	astore	5
	iconst_1
	ifeq	l9 // new
	aload_0
	getfield	Field lastwasbreak$1:Lscala/runtime/BooleanRef;
	iconst_0
	putfield	Field scala/runtime/BooleanRef.elem:Z
l11	aload_0
	getfield	Field cur$1:Lscala/runtime/IntRef;
	getfield	Field scala/runtime/IntRef.elem:I
	iload	4
	if_icmpge	l10 // aload_0
	aload_0
	getfield	Field sb$1:Lscala/collection/mutable/StringBuilder;
	ldc	int 32
	invokevirtual	Method scala/collection/mutable/StringBuilder.append:(C)Lscala/collection/mutable/StringBuilder;
	pop
	aload_0
	getfield	Field cur$1:Lscala/runtime/IntRef;
	aload_0
	getfield	Field cur$1:Lscala/runtime/IntRef;
	getfield	Field scala/runtime/IntRef.elem:I
	iconst_1
	iadd
	putfield	Field scala/runtime/IntRef.elem:I
	goto	l11 // aload_0
l10	aload_0
	getfield	Field sb$1:Lscala/collection/mutable/StringBuilder;
	aload	5
	invokevirtual	Method scala/collection/mutable/StringBuilder.append:(Ljava/lang/String;)Lscala/collection/mutable/StringBuilder;
	goto	l7 // areturn
l9	new	class scala/MatchError
	dup
	aload_1
	invokevirtual	Method scala/xml/PrettyPrinter$Item.toString:()Ljava/lang/String;
	invokespecial	Method scala/MatchError."<init>":(Ljava/lang/String;)V
	athrow
l8	aload_1
	instanceof	class scala/xml/PrettyPrinter$Para
	ifeq	l12 // new
	aload_1
	checkcast	class scala/xml/PrettyPrinter$Para
	astore	6
	aload	6
	invokevirtual	Method scala/xml/PrettyPrinter$Para.s:()Ljava/lang/String;
	astore	7
	iconst_1
	ifeq	l13 // new
	aload_0
	getfield	Field lastwasbreak$1:Lscala/runtime/BooleanRef;
	iconst_0
	putfield	Field scala/runtime/BooleanRef.elem:Z
	aload_0
	getfield	Field sb$1:Lscala/collection/mutable/StringBuilder;
	aload	7
	invokevirtual	Method scala/collection/mutable/StringBuilder.append:(Ljava/lang/String;)Lscala/collection/mutable/StringBuilder;
l7	areturn
l13	new	class scala/MatchError
	dup
	aload_1
	invokevirtual	Method scala/xml/PrettyPrinter$Item.toString:()Ljava/lang/String;
	invokespecial	Method scala/MatchError."<init>":(Ljava/lang/String;)V
	athrow
l12	new	class scala/MatchError
	dup
	aload_1
	invokevirtual	Method scala/xml/PrettyPrinter$Item.toString:()Ljava/lang/String;
	invokespecial	Method scala/MatchError."<init>":(Ljava/lang/String;)V
	athrow
  Labels:
   	l1 = 27 // aload_2
   	l2 = 34 // iconst_1
   	l5 = 54 // aload_0
   	l6 = 63 // pop
   	l4 = 86 // new
   	l3 = 98 // aload_1
   	l11 = 134 // aload_0
   	l10 = 175 // aload_0
   	l9 = 187 // new
   	l8 = 199 // aload_1
   	l7 = 240 // areturn
   	l13 = 241 // new
   	l12 = 253 // new
  LocalVariableTable: 
   Start  Length  Slot  Name   Signature
   0      265      0    this       Lscala/xml/PrettyPrinter$$anonfun$format$1;
   6      259      1    b       Lscala/xml/PrettyPrinter$Item;
   110      89      3    temp47       Lscala/xml/PrettyPrinter$Box;
   116      83      4    temp48       I
   122      77      5    temp49       Ljava/lang/String;
   212      28      6    temp50       Lscala/xml/PrettyPrinter$Para;
   241      12      6    temp50       Lscala/xml/PrettyPrinter$Para;
   219      21      7    temp51       Ljava/lang/String;
   241      12      7    temp51       Ljava/lang/String;


public scala.Function1 andThen(scala.Function1);
  Signature: (Lscala/Function1;)Lscala/Function1;
  Code:
   Stack=2, Locals=2, Args_size=2
	aload_0
	aload_1
	invokestatic	Method scala/Function1$class.andThen:(Lscala/Function1;Lscala/Function1;)Lscala/Function1;
	areturn
  Labels:
  LocalVariableTable: 
   Start  Length  Slot  Name   Signature
   0      6      0    this       Lscala/xml/PrettyPrinter$$anonfun$format$1;
   0      6      1    g       Lscala/Function1;


public scala.Function1 compose(scala.Function1);
  Signature: (Lscala/Function1;)Lscala/Function1;
  Code:
   Stack=2, Locals=2, Args_size=2
	aload_0
	aload_1
	invokestatic	Method scala/Function1$class.compose:(Lscala/Function1;Lscala/Function1;)Lscala/Function1;
	areturn
  Labels:
  LocalVariableTable: 
   Start  Length  Slot  Name   Signature
   0      6      0    this       Lscala/xml/PrettyPrinter$$anonfun$format$1;
   0      6      1    g       Lscala/Function1;


public java.lang.String toString();
  Signature: ()Ljava/lang/String;
  Code:
   Stack=1, Locals=1, Args_size=1
	aload_0
	invokestatic	Method scala/Function1$class.toString:(Lscala/Function1;)Ljava/lang/String;
	areturn
  Labels:

}

