Compiled from "PrettyPrinter.scala"
public final class scala.xml.PrettyPrinter$$anonfun$doPreserve$1 extends java.lang.Object implements scala.Function1,scala.ScalaObject,java.io.Serializable
  SourceFile: "PrettyPrinter.scala"
  Scala: length = 0x
   
  InnerClass: 
   public final $anonfun$doPreserve$1=class scala/xml/PrettyPrinter$$anonfun$doPreserve$1 of class scala/xml/PrettyPrinter
  minor version: 0
  major version: 49
  Constant pool:
Asciz	SourceFile;
Asciz	PrettyPrinter.scala;
Asciz	<clinit>;
Asciz	()V;
Asciz	Code;
Asciz	serialVersionUID;
Asciz	J;
Asciz	scala/xml/PrettyPrinter$$anonfun$doPreserve$1;
class	scala/xml/PrettyPrinter$$anonfun$doPreserve$1
NameAndType	serialVersionUID:J
Field	scala/xml/PrettyPrinter$$anonfun$doPreserve$1.serialVersionUID:J
Asciz	<init>;
Asciz	(Lscala/xml/PrettyPrinter;)V;
Asciz	LineNumberTable;
Asciz	java/lang/Object;
class	java/lang/Object
NameAndType	"<init>":()V
Method	java/lang/Object."<init>":()V
Asciz	scala/Function1$class;
class	scala/Function1$class
Asciz	$init$;
Asciz	(Lscala/Function1;)V;
NameAndType	$init$:(Lscala/Function1;)V
Method	scala/Function1$class.$init$:(Lscala/Function1;)V
Asciz	this;
Asciz	Lscala/xml/PrettyPrinter$$anonfun$doPreserve$1;;
Asciz	$outer;
Asciz	Lscala/xml/PrettyPrinter;;
Asciz	LocalVariableTable;
Asciz	apply;
Asciz	(Ljava/lang/Object;)Ljava/lang/Object;;
Asciz	scala/collection/Seq;
class	scala/collection/Seq
Asciz	(Lscala/collection/Seq;)Z;
NameAndType	apply:(Lscala/collection/Seq;)Z
Method	scala/xml/PrettyPrinter$$anonfun$doPreserve$1.apply:(Lscala/collection/Seq;)Z
Asciz	scala/runtime/BoxesRunTime;
class	scala/runtime/BoxesRunTime
Asciz	boxToBoolean;
Asciz	(Z)Ljava/lang/Boolean;;
NameAndType	boxToBoolean:(Z)Ljava/lang/Boolean;
Method	scala/runtime/BoxesRunTime.boxToBoolean:(Z)Ljava/lang/Boolean;
Asciz	v1;
Asciz	Ljava/lang/Object;;
Asciz	scala/collection/SeqLike;
class	scala/collection/SeqLike
Asciz	toString;
Asciz	()Ljava/lang/String;;
NameAndType	toString:()Ljava/lang/String;
InterfaceMethod	scala/collection/SeqLike.toString:()Ljava/lang/String;
Asciz	scala/xml/XML$;
class	scala/xml/XML$
Asciz	MODULE$;
Asciz	Lscala/xml/XML$;;
NameAndType	MODULE$:Lscala/xml/XML$;
Field	scala/xml/XML$.MODULE$:Lscala/xml/XML$;
Asciz	preserve;
NameAndType	preserve:()Ljava/lang/String;
Method	scala/xml/XML$.preserve:()Ljava/lang/String;
Asciz	equals;
Asciz	(Ljava/lang/Object;)Z;
NameAndType	equals:(Ljava/lang/Object;)Z
Method	java/lang/Object.equals:(Ljava/lang/Object;)Z
Asciz	(Lscala/collection/Seq<Lscala/xml/Node;>;)Z;
Asciz	Signature;
Asciz	andThen;
Asciz	(Lscala/Function1;)Lscala/Function1;;
Asciz	(Lscala/Function1;Lscala/Function1;)Lscala/Function1;;
NameAndType	andThen:(Lscala/Function1;Lscala/Function1;)Lscala/Function1;
Method	scala/Function1$class.andThen:(Lscala/Function1;Lscala/Function1;)Lscala/Function1;
Asciz	g;
Asciz	Lscala/Function1;;
Asciz	compose;
NameAndType	compose:(Lscala/Function1;Lscala/Function1;)Lscala/Function1;
Method	scala/Function1$class.compose:(Lscala/Function1;Lscala/Function1;)Lscala/Function1;
Asciz	(Lscala/Function1;)Ljava/lang/String;;
NameAndType	toString:(Lscala/Function1;)Ljava/lang/String;
Method	scala/Function1$class.toString:(Lscala/Function1;)Ljava/lang/String;
Asciz	Scala;
Asciz	InnerClasses;
Asciz	scala/xml/PrettyPrinter;
class	scala/xml/PrettyPrinter
Asciz	$anonfun$doPreserve$1;
Asciz	scala/Function1;
class	scala/Function1
Asciz	scala/ScalaObject;
class	scala/ScalaObject
Asciz	java/io/Serializable;
class	java/io/Serializable

{
public static final long serialVersionUID;
  Signature: J

public static {};
  Signature: ()V
  Code:
   Stack=2, Locals=0, Args_size=0
	lconst_0
	putstatic	Field serialVersionUID:J
	return
  Labels:

public scala.xml.PrettyPrinter$$anonfun$doPreserve$1(scala.xml.PrettyPrinter);
  Signature: (Lscala/xml/PrettyPrinter;)V
  Code:
   Stack=1, Locals=2, Args_size=2
	aload_0
	invokespecial	Method java/lang/Object."<init>":()V
	aload_0
	invokestatic	Method scala/Function1$class.$init$:(Lscala/Function1;)V
	return
  Labels:
  LocalVariableTable: 
   Start  Length  Slot  Name   Signature
   0      9      0    this       Lscala/xml/PrettyPrinter$$anonfun$doPreserve$1;
   0      9      1    $outer       Lscala/xml/PrettyPrinter;


public final java.lang.Object apply(java.lang.Object);
  Signature: (Ljava/lang/Object;)Ljava/lang/Object;
  Code:
   Stack=2, Locals=3, Args_size=2
	aload_0
	aload_1
	checkcast	class scala/collection/Seq
	invokevirtual	Method apply:(Lscala/collection/Seq;)Z
	istore_2
	iload_2
	invokestatic	Method scala/runtime/BoxesRunTime.boxToBoolean:(Z)Ljava/lang/Boolean;
	areturn
  Labels:
  LocalVariableTable: 
   Start  Length  Slot  Name   Signature
   0      14      0    this       Lscala/xml/PrettyPrinter$$anonfun$doPreserve$1;
   0      14      1    v1       Ljava/lang/Object;


public final boolean apply(scala.collection.Seq);
  Signature: (Lscala/collection/Seq;)Z
  Code:
   Stack=2, Locals=3, Args_size=2
	aload_1
	invokeinterface	InterfaceMethod scala/collection/SeqLike.toString:()Ljava/lang/String;
	getstatic	Field scala/xml/XML$.MODULE$:Lscala/xml/XML$;
	invokevirtual	Method scala/xml/XML$.preserve:()Ljava/lang/String;
	astore_2
	dup
	ifnonnull	l1 // aload_2
	pop
	aload_2
	ifnull	l2 // iconst_1
	goto	l3 // iconst_0
l1	aload_2
	invokevirtual	Method java/lang/Object.equals:(Ljava/lang/Object;)Z
	ifeq	l3 // iconst_0
l2	iconst_1
	goto	l4 // ireturn
l3	iconst_0
l4	ireturn
  Labels:
   	l1 = 25 // aload_2
   	l2 = 32 // iconst_1
   	l3 = 36 // iconst_0
   	l4 = 37 // ireturn
  Signature: length = 0x2
   00 40 

public scala.Function1 andThen(scala.Function1);
  Signature: (Lscala/Function1;)Lscala/Function1;
  Code:
   Stack=2, Locals=2, Args_size=2
	aload_0
	aload_1
	invokestatic	Method scala/Function1$class.andThen:(Lscala/Function1;Lscala/Function1;)Lscala/Function1;
	areturn
  Labels:
  LocalVariableTable: 
   Start  Length  Slot  Name   Signature
   0      6      0    this       Lscala/xml/PrettyPrinter$$anonfun$doPreserve$1;
   0      6      1    g       Lscala/Function1;


public scala.Function1 compose(scala.Function1);
  Signature: (Lscala/Function1;)Lscala/Function1;
  Code:
   Stack=2, Locals=2, Args_size=2
	aload_0
	aload_1
	invokestatic	Method scala/Function1$class.compose:(Lscala/Function1;Lscala/Function1;)Lscala/Function1;
	areturn
  Labels:
  LocalVariableTable: 
   Start  Length  Slot  Name   Signature
   0      6      0    this       Lscala/xml/PrettyPrinter$$anonfun$doPreserve$1;
   0      6      1    g       Lscala/Function1;


public java.lang.String toString();
  Signature: ()Ljava/lang/String;
  Code:
   Stack=1, Locals=1, Args_size=1
	aload_0
	invokestatic	Method scala/Function1$class.toString:(Lscala/Function1;)Ljava/lang/String;
	areturn
  Labels:

}

