Compiled from "PrettyPrinter.scala"
public final class scala.xml.PrettyPrinter$Break$ extends scala.xml.PrettyPrinter$Item implements scala.ScalaObject,scala.Product,java.io.Serializable
  SourceFile: "PrettyPrinter.scala"
  Scala: length = 0x
   
  InnerClass: 
   public Item=class scala/xml/PrettyPrinter$Item of class scala/xml/PrettyPrinter
  minor version: 0
  major version: 49
  Constant pool:
Asciz	SourceFile;
Asciz	PrettyPrinter.scala;
Asciz	Scala;
Asciz	productIterator;
Asciz	()Lscala/collection/Iterator;;
Asciz	Code;
Asciz	LineNumberTable;
Asciz	scala/Product$class;
class	scala/Product$class
Asciz	(Lscala/Product;)Lscala/collection/Iterator;;
NameAndType	productIterator:(Lscala/Product;)Lscala/collection/Iterator;
Method	scala/Product$class.productIterator:(Lscala/Product;)Lscala/collection/Iterator;
Asciz	productElements;
NameAndType	productElements:(Lscala/Product;)Lscala/collection/Iterator;
Method	scala/Product$class.productElements:(Lscala/Product;)Lscala/collection/Iterator;
Asciz	Deprecated;
Asciz	toString;
Asciz	()Ljava/lang/String;;
Asciz	\;
String	\
Asciz	productPrefix;
Asciz	Break;
String	Break
Asciz	productArity;
Asciz	()I;
Asciz	productElement;
Asciz	(I)Ljava/lang/Object;;
Asciz	java/lang/IndexOutOfBoundsException;
class	java/lang/IndexOutOfBoundsException
Asciz	scala/runtime/BoxesRunTime;
class	scala/runtime/BoxesRunTime
Asciz	boxToInteger;
Asciz	(I)Ljava/lang/Integer;;
NameAndType	boxToInteger:(I)Ljava/lang/Integer;
Method	scala/runtime/BoxesRunTime.boxToInteger:(I)Ljava/lang/Integer;
Asciz	java/lang/Object;
class	java/lang/Object
NameAndType	toString:()Ljava/lang/String;
Method	java/lang/Object.toString:()Ljava/lang/String;
Asciz	<init>;
Asciz	(Ljava/lang/String;)V;
NameAndType	"<init>":(Ljava/lang/String;)V
Method	java/lang/IndexOutOfBoundsException."<init>":(Ljava/lang/String;)V
Asciz	productElementName;
Asciz	(I)Ljava/lang/String;;
Asciz	canEqual;
Asciz	(Ljava/lang/Object;)Z;
Asciz	scala/xml/PrettyPrinter$Break$;
class	scala/xml/PrettyPrinter$Break$
Asciz	readResolve;
Asciz	()Ljava/lang/Object;;
Asciz	scala$xml$PrettyPrinter$Break$$$outer;
Asciz	()Lscala/xml/PrettyPrinter;;
NameAndType	scala$xml$PrettyPrinter$Break$$$outer:()Lscala/xml/PrettyPrinter;
Method	scala/xml/PrettyPrinter$Break$.scala$xml$PrettyPrinter$Break$$$outer:()Lscala/xml/PrettyPrinter;
Asciz	scala/xml/PrettyPrinter;
class	scala/xml/PrettyPrinter
Asciz	()Lscala/xml/PrettyPrinter$Break$;;
NameAndType	Break:()Lscala/xml/PrettyPrinter$Break$;
Method	scala/xml/PrettyPrinter.Break:()Lscala/xml/PrettyPrinter$Break$;
Asciz	scala/xml/PrettyPrinter$Item;
class	scala/xml/PrettyPrinter$Item
Asciz	$outer;
Asciz	Lscala/xml/PrettyPrinter;;
NameAndType	$outer:Lscala/xml/PrettyPrinter;
Field	scala/xml/PrettyPrinter$Item.$outer:Lscala/xml/PrettyPrinter;
Asciz	(Lscala/xml/PrettyPrinter;)V;
NameAndType	"<init>":(Lscala/xml/PrettyPrinter;)V
Method	scala/xml/PrettyPrinter$Item."<init>":(Lscala/xml/PrettyPrinter;)V
Asciz	$init$;
Asciz	(Lscala/Product;)V;
NameAndType	$init$:(Lscala/Product;)V
Method	scala/Product$class.$init$:(Lscala/Product;)V
Asciz	this;
Asciz	Lscala/xml/PrettyPrinter$Break$;;
Asciz	LocalVariableTable;
Asciz	InnerClasses;
Asciz	Item;
Asciz	scala/ScalaObject;
class	scala/ScalaObject
Asciz	scala/Product;
class	scala/Product
Asciz	java/io/Serializable;
class	java/io/Serializable

{
public scala.collection.Iterator productIterator();
  Signature: ()Lscala/collection/Iterator;
  Code:
   Stack=1, Locals=1, Args_size=1
	aload_0
	invokestatic	Method scala/Product$class.productIterator:(Lscala/Product;)Lscala/collection/Iterator;
	areturn
  Labels:

public scala.collection.Iterator productElements();
  Signature: ()Lscala/collection/Iterator;
  Code:
   Stack=1, Locals=1, Args_size=1
	aload_0
	invokestatic	Method scala/Product$class.productElements:(Lscala/Product;)Lscala/collection/Iterator;
	areturn
  Labels:
  Deprecated: true

public java.lang.String toString();
  Signature: ()Ljava/lang/String;
  Code:
   Stack=1, Locals=1, Args_size=1
	ldc	String \
	areturn
  Labels:

public java.lang.String productPrefix();
  Signature: ()Ljava/lang/String;
  Code:
   Stack=1, Locals=1, Args_size=1
	ldc	String Break
	areturn
  Labels:

public int productArity();
  Signature: ()I
  Code:
   Stack=1, Locals=1, Args_size=1
	iconst_0
	ireturn
  Labels:

public java.lang.Object productElement(int);
  Signature: (I)Ljava/lang/Object;
  Code:
   Stack=3, Locals=2, Args_size=2
	new	class java/lang/IndexOutOfBoundsException
	dup
	iload_1
	invokestatic	Method scala/runtime/BoxesRunTime.boxToInteger:(I)Ljava/lang/Integer;
	invokevirtual	Method java/lang/Object.toString:()Ljava/lang/String;
	invokespecial	Method java/lang/IndexOutOfBoundsException."<init>":(Ljava/lang/String;)V
	athrow
  Labels:

public java.lang.String productElementName(int);
  Signature: (I)Ljava/lang/String;
  Code:
   Stack=3, Locals=2, Args_size=2
	new	class java/lang/IndexOutOfBoundsException
	dup
	iload_1
	invokestatic	Method scala/runtime/BoxesRunTime.boxToInteger:(I)Ljava/lang/Integer;
	invokevirtual	Method java/lang/Object.toString:()Ljava/lang/String;
	invokespecial	Method java/lang/IndexOutOfBoundsException."<init>":(Ljava/lang/String;)V
	athrow
  Labels:

public boolean canEqual(java.lang.Object);
  Signature: (Ljava/lang/Object;)Z
  Code:
   Stack=1, Locals=2, Args_size=2
	aload_1
	instanceof	class scala/xml/PrettyPrinter$Break$
	ireturn
  Labels:

public java.lang.Object readResolve();
  Signature: ()Ljava/lang/Object;
  Code:
   Stack=1, Locals=1, Args_size=1
	aload_0
	invokevirtual	Method scala$xml$PrettyPrinter$Break$$$outer:()Lscala/xml/PrettyPrinter;
	invokevirtual	Method scala/xml/PrettyPrinter.Break:()Lscala/xml/PrettyPrinter$Break$;
	areturn
  Labels:

public scala.xml.PrettyPrinter scala$xml$PrettyPrinter$Break$$$outer();
  Signature: ()Lscala/xml/PrettyPrinter;
  Code:
   Stack=1, Locals=1, Args_size=1
	aload_0
	getfield	Field scala/xml/PrettyPrinter$Item.$outer:Lscala/xml/PrettyPrinter;
	areturn
  Labels:

public scala.xml.PrettyPrinter$Break$(scala.xml.PrettyPrinter);
  Signature: (Lscala/xml/PrettyPrinter;)V
  Code:
   Stack=2, Locals=2, Args_size=2
	aload_0
	aload_1
	invokespecial	Method scala/xml/PrettyPrinter$Item."<init>":(Lscala/xml/PrettyPrinter;)V
	aload_0
	invokestatic	Method scala/Product$class.$init$:(Lscala/Product;)V
	return
  Labels:
  LocalVariableTable: 
   Start  Length  Slot  Name   Signature
   0      10      0    this       Lscala/xml/PrettyPrinter$Break$;
   0      10      1    $outer       Lscala/xml/PrettyPrinter;


}

