Compiled from "PrettyPrinter.scala"
public class scala.xml.PrettyPrinter$Para extends scala.xml.PrettyPrinter$Item implements scala.ScalaObject,scala.Product,java.io.Serializable
  SourceFile: "PrettyPrinter.scala"
  Scala: length = 0x
   
  InnerClass: 
   public Item=class scala/xml/PrettyPrinter$Item of class scala/xml/PrettyPrinter
   public Para=class scala/xml/PrettyPrinter$Para of class scala/xml/PrettyPrinter
  minor version: 0
  major version: 49
  Constant pool:
Asciz	SourceFile;
Asciz	PrettyPrinter.scala;
Asciz	s;
Asciz	Ljava/lang/String;;
Asciz	productIterator;
Asciz	()Lscala/collection/Iterator;;
Asciz	Code;
Asciz	LineNumberTable;
Asciz	scala/Product$class;
class	scala/Product$class
Asciz	(Lscala/Product;)Lscala/collection/Iterator;;
NameAndType	productIterator:(Lscala/Product;)Lscala/collection/Iterator;
Method	scala/Product$class.productIterator:(Lscala/Product;)Lscala/collection/Iterator;
Asciz	productElements;
NameAndType	productElements:(Lscala/Product;)Lscala/collection/Iterator;
Method	scala/Product$class.productElements:(Lscala/Product;)Lscala/collection/Iterator;
Asciz	Deprecated;
Asciz	copy$default$1;
Asciz	()Ljava/lang/String;;
Asciz	scala/xml/PrettyPrinter$Para;
class	scala/xml/PrettyPrinter$Para
NameAndType	s:()Ljava/lang/String;
Method	scala/xml/PrettyPrinter$Para.s:()Ljava/lang/String;
NameAndType	s:Ljava/lang/String;
Field	scala/xml/PrettyPrinter$Para.s:Ljava/lang/String;
Asciz	copy;
Asciz	(Ljava/lang/String;)Lscala/xml/PrettyPrinter$Para;;
Asciz	scala$xml$PrettyPrinter$Para$$$outer;
Asciz	()Lscala/xml/PrettyPrinter;;
NameAndType	scala$xml$PrettyPrinter$Para$$$outer:()Lscala/xml/PrettyPrinter;
Method	scala/xml/PrettyPrinter$Para.scala$xml$PrettyPrinter$Para$$$outer:()Lscala/xml/PrettyPrinter;
Asciz	<init>;
Asciz	(Lscala/xml/PrettyPrinter;Ljava/lang/String;)V;
NameAndType	"<init>":(Lscala/xml/PrettyPrinter;Ljava/lang/String;)V
Method	scala/xml/PrettyPrinter$Para."<init>":(Lscala/xml/PrettyPrinter;Ljava/lang/String;)V
Asciz	this;
Asciz	Lscala/xml/PrettyPrinter$Para;;
Asciz	LocalVariableTable;
Asciz	hashCode;
Asciz	()I;
Asciz	scala/runtime/ScalaRunTime$;
class	scala/runtime/ScalaRunTime$
Asciz	MODULE$;
Asciz	Lscala/runtime/ScalaRunTime$;;
NameAndType	MODULE$:Lscala/runtime/ScalaRunTime$;
Field	scala/runtime/ScalaRunTime$.MODULE$:Lscala/runtime/ScalaRunTime$;
Asciz	_hashCode;
Asciz	(Lscala/Product;)I;
NameAndType	_hashCode:(Lscala/Product;)I
Method	scala/runtime/ScalaRunTime$._hashCode:(Lscala/Product;)I
Asciz	toString;
Asciz	_toString;
Asciz	(Lscala/Product;)Ljava/lang/String;;
NameAndType	_toString:(Lscala/Product;)Ljava/lang/String;
Method	scala/runtime/ScalaRunTime$._toString:(Lscala/Product;)Ljava/lang/String;
Asciz	equals;
Asciz	(Ljava/lang/Object;)Z;
Asciz	gd2$1;
Asciz	(Ljava/lang/String;)Z;
NameAndType	gd2$1:(Ljava/lang/String;)Z
Method	scala/xml/PrettyPrinter$Para.gd2$1:(Ljava/lang/String;)Z
Asciz	scala/Equals;
class	scala/Equals
Asciz	canEqual;
NameAndType	canEqual:(Ljava/lang/Object;)Z
InterfaceMethod	scala/Equals.canEqual:(Ljava/lang/Object;)Z
Asciz	temp9;
Asciz	Ljava/lang/Object;;
Asciz	temp10;
Asciz	temp11;
Asciz	s$2;
Asciz	productPrefix;
Asciz	Para;
String	Para
Asciz	productArity;
Asciz	productElement;
Asciz	(I)Ljava/lang/Object;;
Asciz	java/lang/IndexOutOfBoundsException;
class	java/lang/IndexOutOfBoundsException
Asciz	scala/runtime/BoxesRunTime;
class	scala/runtime/BoxesRunTime
Asciz	boxToInteger;
Asciz	(I)Ljava/lang/Integer;;
NameAndType	boxToInteger:(I)Ljava/lang/Integer;
Method	scala/runtime/BoxesRunTime.boxToInteger:(I)Ljava/lang/Integer;
Asciz	java/lang/Object;
class	java/lang/Object
NameAndType	toString:()Ljava/lang/String;
Method	java/lang/Object.toString:()Ljava/lang/String;
Asciz	(Ljava/lang/String;)V;
NameAndType	"<init>":(Ljava/lang/String;)V
Method	java/lang/IndexOutOfBoundsException."<init>":(Ljava/lang/String;)V
Asciz	temp12;
Asciz	I;
Asciz	productElementName;
Asciz	(I)Ljava/lang/String;;
String	s
Asciz	temp13;
Asciz	scala/xml/PrettyPrinter$Item;
class	scala/xml/PrettyPrinter$Item
Asciz	$outer;
Asciz	Lscala/xml/PrettyPrinter;;
NameAndType	$outer:Lscala/xml/PrettyPrinter;
Field	scala/xml/PrettyPrinter$Item.$outer:Lscala/xml/PrettyPrinter;
NameAndType	equals:(Ljava/lang/Object;)Z
Method	java/lang/Object.equals:(Ljava/lang/Object;)Z
Asciz	(Lscala/xml/PrettyPrinter;)V;
NameAndType	"<init>":(Lscala/xml/PrettyPrinter;)V
Method	scala/xml/PrettyPrinter$Item."<init>":(Lscala/xml/PrettyPrinter;)V
Asciz	$init$;
Asciz	(Lscala/Product;)V;
NameAndType	$init$:(Lscala/Product;)V
Method	scala/Product$class.$init$:(Lscala/Product;)V
Asciz	Scala;
Asciz	InnerClasses;
Asciz	scala/xml/PrettyPrinter;
class	scala/xml/PrettyPrinter
Asciz	Item;
Asciz	scala/ScalaObject;
class	scala/ScalaObject
Asciz	scala/Product;
class	scala/Product
Asciz	java/io/Serializable;
class	java/io/Serializable

{
private final java.lang.String s;
  Signature: Ljava/lang/String;

public scala.collection.Iterator productIterator();
  Signature: ()Lscala/collection/Iterator;
  Code:
   Stack=1, Locals=1, Args_size=1
	aload_0
	invokestatic	Method scala/Product$class.productIterator:(Lscala/Product;)Lscala/collection/Iterator;
	areturn
  Labels:

public scala.collection.Iterator productElements();
  Signature: ()Lscala/collection/Iterator;
  Code:
   Stack=1, Locals=1, Args_size=1
	aload_0
	invokestatic	Method scala/Product$class.productElements:(Lscala/Product;)Lscala/collection/Iterator;
	areturn
  Labels:
  Deprecated: true

public java.lang.String copy$default$1();
  Signature: ()Ljava/lang/String;
  Code:
   Stack=1, Locals=1, Args_size=1
	aload_0
	invokevirtual	Method s:()Ljava/lang/String;
	areturn
  Labels:

public java.lang.String s();
  Signature: ()Ljava/lang/String;
  Code:
   Stack=1, Locals=1, Args_size=1
	aload_0
	getfield	Field s:Ljava/lang/String;
	areturn
  Labels:

public scala.xml.PrettyPrinter$Para copy(java.lang.String);
  Signature: (Ljava/lang/String;)Lscala/xml/PrettyPrinter$Para;
  Code:
   Stack=4, Locals=2, Args_size=2
	new	class scala/xml/PrettyPrinter$Para
	dup
	aload_0
	invokevirtual	Method scala$xml$PrettyPrinter$Para$$$outer:()Lscala/xml/PrettyPrinter;
	aload_1
	invokespecial	Method "<init>":(Lscala/xml/PrettyPrinter;Ljava/lang/String;)V
	areturn
  Labels:
  LocalVariableTable: 
   Start  Length  Slot  Name   Signature
   0      13      0    this       Lscala/xml/PrettyPrinter$Para;
   0      13      1    s       Ljava/lang/String;


public int hashCode();
  Signature: ()I
  Code:
   Stack=2, Locals=1, Args_size=1
	getstatic	Field scala/runtime/ScalaRunTime$.MODULE$:Lscala/runtime/ScalaRunTime$;
	aload_0
	invokevirtual	Method scala/runtime/ScalaRunTime$._hashCode:(Lscala/Product;)I
	ireturn
  Labels:

public java.lang.String toString();
  Signature: ()Ljava/lang/String;
  Code:
   Stack=2, Locals=1, Args_size=1
	getstatic	Field scala/runtime/ScalaRunTime$.MODULE$:Lscala/runtime/ScalaRunTime$;
	aload_0
	invokevirtual	Method scala/runtime/ScalaRunTime$._toString:(Lscala/Product;)Ljava/lang/String;
	areturn
  Labels:

public boolean equals(java.lang.Object);
  Signature: (Ljava/lang/Object;)Z
  Code:
   Stack=2, Locals=6, Args_size=2
	aload_0
	aload_1
	if_acmpeq	l1 // iconst_1
	aload_1
	astore_2
	aload_2
	instanceof	class scala/xml/PrettyPrinter$Para
	ifeq	l2 // iconst_0
	aload_2
	checkcast	class scala/xml/PrettyPrinter$Para
	invokevirtual	Method scala$xml$PrettyPrinter$Para$$$outer:()Lscala/xml/PrettyPrinter;
	aload_0
	invokevirtual	Method scala$xml$PrettyPrinter$Para$$$outer:()Lscala/xml/PrettyPrinter;
	if_acmpne	l2 // iconst_0
	aload_2
	checkcast	class scala/xml/PrettyPrinter$Para
	astore_3
	aload_3
	invokevirtual	Method s:()Ljava/lang/String;
	astore	4
	aload	4
	astore	5
	aload_0
	aload	5
	invokespecial	Method gd2$1:(Ljava/lang/String;)Z
	ifeq	l3 // iconst_0
	aload_1
	checkcast	class scala/xml/PrettyPrinter$Para
	aload_0
	invokeinterface	InterfaceMethod scala/Equals.canEqual:(Ljava/lang/Object;)Z
	goto	l4 // ifeq
l3	iconst_0
	goto	l4 // ifeq
l2	iconst_0
l4	ifeq	l5 // iconst_0
l1	iconst_1
	goto	l6 // ireturn
l5	iconst_0
l6	ireturn
  Labels:
   	l3 = 65 // iconst_0
   	l2 = 69 // iconst_0
   	l4 = 70 // ifeq
   	l1 = 73 // iconst_1
   	l5 = 77 // iconst_0
   	l6 = 78 // ireturn
  LocalVariableTable: 
   Start  Length  Slot  Name   Signature
   0      79      0    this       Lscala/xml/PrettyPrinter$Para;
   7      66      2    temp9       Ljava/lang/Object;
   33      36      3    temp10       Lscala/xml/PrettyPrinter$Para;
   39      30      4    temp11       Ljava/lang/String;
   43      26      5    s$2       Ljava/lang/String;


public java.lang.String productPrefix();
  Signature: ()Ljava/lang/String;
  Code:
   Stack=1, Locals=1, Args_size=1
	ldc	String Para
	areturn
  Labels:

public int productArity();
  Signature: ()I
  Code:
   Stack=1, Locals=1, Args_size=1
	iconst_1
	ireturn
  Labels:

public java.lang.Object productElement(int);
  Signature: (I)Ljava/lang/Object;
  Code:
   Stack=3, Locals=3, Args_size=2
	iload_1
	istore_2
	iload_2
	iconst_0
	if_icmpne	l1 // new
	aload_0
	invokevirtual	Method s:()Ljava/lang/String;
	areturn
l1	new	class java/lang/IndexOutOfBoundsException
	dup
	iload_1
	invokestatic	Method scala/runtime/BoxesRunTime.boxToInteger:(I)Ljava/lang/Integer;
	invokevirtual	Method java/lang/Object.toString:()Ljava/lang/String;
	invokespecial	Method java/lang/IndexOutOfBoundsException."<init>":(Ljava/lang/String;)V
	athrow
  Labels:
   	l1 = 12 // new
  LocalVariableTable: 
   Start  Length  Slot  Name   Signature
   0      27      0    this       Lscala/xml/PrettyPrinter$Para;
   2      25      2    temp12       I


public java.lang.String productElementName(int);
  Signature: (I)Ljava/lang/String;
  Code:
   Stack=3, Locals=3, Args_size=2
	iload_1
	istore_2
	iload_2
	iconst_0
	if_icmpne	l1 // new
	ldc	String s
	areturn
l1	new	class java/lang/IndexOutOfBoundsException
	dup
	iload_1
	invokestatic	Method scala/runtime/BoxesRunTime.boxToInteger:(I)Ljava/lang/Integer;
	invokevirtual	Method java/lang/Object.toString:()Ljava/lang/String;
	invokespecial	Method java/lang/IndexOutOfBoundsException."<init>":(Ljava/lang/String;)V
	athrow
  Labels:
   	l1 = 10 // new
  LocalVariableTable: 
   Start  Length  Slot  Name   Signature
   0      25      0    this       Lscala/xml/PrettyPrinter$Para;
   2      23      2    temp13       I


public boolean canEqual(java.lang.Object);
  Signature: (Ljava/lang/Object;)Z
  Code:
   Stack=1, Locals=2, Args_size=2
	aload_1
	instanceof	class scala/xml/PrettyPrinter$Para
	ireturn
  Labels:

public scala.xml.PrettyPrinter scala$xml$PrettyPrinter$Para$$$outer();
  Signature: ()Lscala/xml/PrettyPrinter;
  Code:
   Stack=1, Locals=1, Args_size=1
	aload_0
	getfield	Field scala/xml/PrettyPrinter$Item.$outer:Lscala/xml/PrettyPrinter;
	areturn
  Labels:

private final boolean gd2$1(java.lang.String);
  Signature: (Ljava/lang/String;)Z
  Code:
   Stack=2, Locals=3, Args_size=2
	aload_1
	aload_0
	invokevirtual	Method s:()Ljava/lang/String;
	astore_2
	dup
	ifnonnull	l1 // aload_2
	pop
	aload_2
	ifnull	l2 // iconst_1
	goto	l3 // iconst_0
l1	aload_2
	invokevirtual	Method java/lang/Object.equals:(Ljava/lang/Object;)Z
	ifeq	l3 // iconst_0
l2	iconst_1
	goto	l4 // ireturn
l3	iconst_0
l4	ireturn
  Labels:
   	l1 = 18 // aload_2
   	l2 = 25 // iconst_1
   	l3 = 29 // iconst_0
   	l4 = 30 // ireturn

public scala.xml.PrettyPrinter$Para(scala.xml.PrettyPrinter, java.lang.String);
  Signature: (Lscala/xml/PrettyPrinter;Ljava/lang/String;)V
  Code:
   Stack=2, Locals=3, Args_size=3
	aload_0
	aload_2
	putfield	Field s:Ljava/lang/String;
	aload_0
	aload_1
	invokespecial	Method scala/xml/PrettyPrinter$Item."<init>":(Lscala/xml/PrettyPrinter;)V
	aload_0
	invokestatic	Method scala/Product$class.$init$:(Lscala/Product;)V
	return
  Labels:
  LocalVariableTable: 
   Start  Length  Slot  Name   Signature
   0      15      0    this       Lscala/xml/PrettyPrinter$Para;
   0      15      1    $outer       Lscala/xml/PrettyPrinter;
   0      15      2    s       Ljava/lang/String;


}

