Compiled from "ProcInstr.scala"
public class scala.xml.ProcInstr extends scala.xml.SpecialNode implements scala.ScalaObject,scala.Product,java.io.Serializable
  SourceFile: "ProcInstr.scala"
  ScalaSig: length = 0x42E
   05 00 FFFFFF81 1A 06 08 01 02 FFFFFF84 FFFFFF80 FFFFFF80 FFFFFF80 40 07 02 09
   50 72 6F 63 49 6E 73 74 72 0A 02 03 04 01 03 78
   6D 6C 0A 01 05 01 05 73 63 61 6C 61 03 00 13 04
   00 08 0C 10 10 02 09 0A 0D 01 02 09 02 0B 02 02
   0B 53 70 65 63 69 61 6C 4E 6F 64 65 10 02 0D 0E
   0D 01 04 09 02 0F 04 02 0B 53 63 61 6C 61 4F 62
   6A 65 63 74 10 02 0D 11 09 02 12 04 02 07 50 72
   6F 64 75 63 74 08 08 14 00 FFFFFF82 FFFFFFCA FFFFFF80 FFFFFF84 00 15 01
   06 74 61 72 67 65 74 15 01 16 10 02 17 1A 0E 02
   0D 18 09 02 19 04 01 06 50 72 65 64 65 66 09 02
   1B 1C 02 06 53 74 72 69 6E 67 0A 02 19 04 08 08
   1E 00 FFFFFF82 FFFFFF88 FFFFFFA0 FFFFFF80 04 16 01 07 74 61 72 67 65 74
   20 08 08 20 00 FFFFFF82 FFFFFFCA FFFFFF80 FFFFFF84 00 15 01 08 70 72 6F
   63 74 65 78 74 08 08 22 00 FFFFFF82 FFFFFF88 FFFFFFA0 FFFFFF80 04 16 01
   09 70 72 6F 63 74 65 78 74 20 08 05 24 00 FFFFFF84 00
   25 01 06 3C 69 6E 69 74 3E 14 03 26 27 28 10 02
   09 00 08 05 14 23 FFFFFFC0 00 16 08 05 20 23 FFFFFFC0 00 16
   08 05 2A 00 FFFFFF84 22 2B 01 13 64 6F 43 6F 6C 6C 65
   63 74 4E 61 6D 65 73 70 61 63 65 73 15 01 2C 10
   02 0D 2D 09 02 2E 04 02 07 42 6F 6F 6C 65 61 6E
   08 05 30 00 FFFFFF84 22 2B 01 0B 64 6F 54 72 61 6E 73
   66 6F 72 6D 08 05 32 00 FFFFFF84 02 33 01 05 6C 61 62
   65 6C 15 01 34 10 02 35 3A 0D 01 36 0A 02 37 38
   01 04 6C 61 6E 67 0A 01 39 01 04 6A 61 76 61 09
   02 1B 36 08 05 3C 00 FFFFFF84 20 33 01 04 74 65 78 74
   08 05 3E 00 FFFFFF84 20 3F 01 0B 62 75 69 6C 64 53 74
   72 69 6E 67 14 02 40 48 10 02 41 46 0D 01 42 0A
   02 43 44 01 07 6D 75 74 61 62 6C 65 0A 02 45 04
   01 0A 63 6F 6C 6C 65 63 74 69 6F 6E 09 02 47 42
   02 0D 53 74 72 69 6E 67 42 75 69 6C 64 65 72 08
   05 49 3D FFFFFFC0 00 4A 01 02 73 62 10 02 4B 53 0E 02
   4C 51 0E 02 4D 50 0D 01 4E 0A 02 4F 06 01 06 3C
   72 6F 6F 74 3E 09 01 05 09 02 52 04 01 07 70 61
   63 6B 61 67 65 09 02 47 54 0A 02 52 04 08 07 56
   00 FFFFFF81 FFFFFF80 FFFFFF84 00 57 01 04 63 6F 70 79 14 03 26 58
   59 08 07 14 55 FFFFFF90 FFFFFF80 FFFFFFC0 00 16 08 07 20 55 FFFFFF90 FFFFFF80
   FFFFFFC0 00 16 08 07 5B 00 FFFFFF91 FFFFFF80 FFFFFF84 00 5C 01 0E 63 6F
   70 79 24 64 65 66 61 75 6C 74 24 31 15 01 5D 2A
   02 16 5E 2B 01 5F 10 02 60 65 0D 01 61 0A 02 62
   63 01 09 75 6E 63 68 65 63 6B 65 64 0A 02 64 04
   01 0A 61 6E 6E 6F 74 61 74 69 6F 6E 09 02 66 61
   02 11 75 6E 63 68 65 63 6B 65 64 56 61 72 69 61
   6E 63 65 08 07 68 00 FFFFFF91 FFFFFF80 FFFFFF84 00 5C 01 0E 63 6F
   70 79 24 64 65 66 61 75 6C 74 24 32 08 08 6A 00
   FFFFFF84 FFFFFF80 FFFFFF80 FFFFFF84 20 33 01 0D 70 72 6F 64 75 63 74 50
   72 65 66 69 78 08 08 6C 00 FFFFFF84 FFFFFF80 FFFFFF80 FFFFFF84 20 6D 01
   0C 70 72 6F 64 75 63 74 41 72 69 74 79 15 01 6E
   10 02 0D 6F 09 02 70 04 02 03 49 6E 74 08 08 72
   00 FFFFFF84 FFFFFF80 FFFFFF80 FFFFFF84 20 73 01 0E 70 72 6F 64 75 63 74
   45 6C 65 6D 65 6E 74 14 02 74 77 10 02 0D 75 09
   02 76 04 02 03 41 6E 79 08 07 78 71 FFFFFF81 FFFFFF80 FFFFFFC0 00
   6E 01 03 78 24 31 28 02 00 7A 10 02 0D 7B 09 02
   7C 04 02 0C 73 65 72 69 61 6C 69 7A 61 62 6C 65
   07 07 7E 02 FFFFFF81 FFFFFF80 FFFFFF88 02 7F 01 09 50 72 6F 63 49
   6E 73 74 72 10 03 09 FFFFFF81 00 06 09 01 02 FFFFFF84 FFFFFF81 FFFFFF80
   FFFFFF88 02 FFFFFF81 01 13 07 FFFFFF81 00 FFFFFF81 02 FFFFFF81 05 0C 10 03 35
   FFFFFF81 03 09 03 FFFFFF81 04 36 02 06 4F 62 6A 65 63 74 10
   06 0D FFFFFF81 06 16 16 26 09 03 FFFFFF81 07 04 02 09 46 75
   6E 63 74 69 6F 6E 32 08 07 24 FFFFFF81 00 FFFFFF84 00 FFFFFF81 09
   14 01 7F 08 0A FFFFFF81 0B FFFFFF81 00 FFFFFF81 FFFFFF80 FFFFFF84 40 FFFFFF81 0C 01
   05 61 70 70 6C 79 14 05 26 FFFFFF81 0D FFFFFF81 0E 08 06 14
   FFFFFF81 0A FFFFFFC0 00 16 08 06 20 FFFFFF81 0A FFFFFFC0 00 16 08 0A FFFFFF81
   10 FFFFFF81 00 FFFFFF81 FFFFFF80 FFFFFF84 40 FFFFFF81 11 01 07 75 6E 61 70 70
   6C 79 14 04 FFFFFF81 12 FFFFFF81 18 10 05 0D FFFFFF81 13 FFFFFF81 15 09
   03 FFFFFF81 14 04 02 06 4F 70 74 69 6F 6E 10 05 0D FFFFFF81
   16 16 16 09 03 FFFFFF81 17 04 02 06 54 75 70 6C 65 32
   08 07 FFFFFF81 19 FFFFFF81 0F FFFFFFC0 00 26 01 03 78 24 30 
  minor version: 0
  major version: 49
  Constant pool:
Asciz	SourceFile;
Asciz	ProcInstr.scala;
Asciz	tupled;
Asciz	()Lscala/Function1;;
Asciz	Code;
Asciz	scala/xml/ProcInstr$;
class	scala/xml/ProcInstr$
Asciz	MODULE$;
Asciz	Lscala/xml/ProcInstr$;;
NameAndType	MODULE$:Lscala/xml/ProcInstr$;
Field	scala/xml/ProcInstr$.MODULE$:Lscala/xml/ProcInstr$;
NameAndType	tupled:()Lscala/Function1;
Method	scala/xml/ProcInstr$.tupled:()Lscala/Function1;
Asciz	curry;
NameAndType	curry:()Lscala/Function1;
Method	scala/xml/ProcInstr$.curry:()Lscala/Function1;
Asciz	Deprecated;
Asciz	curried;
NameAndType	curried:()Lscala/Function1;
Method	scala/xml/ProcInstr$.curried:()Lscala/Function1;
Asciz	proctext;
Asciz	Ljava/lang/String;;
Asciz	target;
Asciz	productElementName;
Asciz	(I)Ljava/lang/String;;
Asciz	LineNumberTable;
Asciz	scala/Product$class;
class	scala/Product$class
Asciz	(Lscala/Product;I)Ljava/lang/String;;
NameAndType	productElementName:(Lscala/Product;I)Ljava/lang/String;
Method	scala/Product$class.productElementName:(Lscala/Product;I)Ljava/lang/String;
Asciz	this;
Asciz	Lscala/xml/ProcInstr;;
Asciz	n;
Asciz	I;
Asciz	LocalVariableTable;
Asciz	productIterator;
Asciz	()Lscala/collection/Iterator;;
Asciz	(Lscala/Product;)Lscala/collection/Iterator;;
NameAndType	productIterator:(Lscala/Product;)Lscala/collection/Iterator;
Method	scala/Product$class.productIterator:(Lscala/Product;)Lscala/collection/Iterator;
Asciz	productElements;
NameAndType	productElements:(Lscala/Product;)Lscala/collection/Iterator;
Method	scala/Product$class.productElements:(Lscala/Product;)Lscala/collection/Iterator;
Asciz	copy$default$2;
Asciz	()Ljava/lang/String;;
Asciz	scala/xml/ProcInstr;
class	scala/xml/ProcInstr
NameAndType	proctext:()Ljava/lang/String;
Method	scala/xml/ProcInstr.proctext:()Ljava/lang/String;
Asciz	copy$default$1;
NameAndType	target:()Ljava/lang/String;
Method	scala/xml/ProcInstr.target:()Ljava/lang/String;
NameAndType	target:Ljava/lang/String;
Field	scala/xml/ProcInstr.target:Ljava/lang/String;
NameAndType	proctext:Ljava/lang/String;
Field	scala/xml/ProcInstr.proctext:Ljava/lang/String;
Asciz	doCollectNamespaces;
Asciz	()Z;
Asciz	doTransform;
Asciz	label;
Asciz	#PI;
String	#PI
Asciz	text;
Asciz	;
String	
Asciz	buildString;
Asciz	(Lscala/collection/mutable/StringBuilder;)Lscala/collection/mutable/StringBuilder;;
Asciz	<?%s%s?>;
String	<?%s%s?>
Asciz	scala/collection/immutable/StringOps;
class	scala/collection/immutable/StringOps
Asciz	<init>;
Asciz	(Ljava/lang/String;)V;
NameAndType	"<init>":(Ljava/lang/String;)V
Method	scala/collection/immutable/StringOps."<init>":(Ljava/lang/String;)V
Asciz	scala/Predef$;
class	scala/Predef$
Asciz	Lscala/Predef$;;
NameAndType	MODULE$:Lscala/Predef$;
Field	scala/Predef$.MODULE$:Lscala/Predef$;
Asciz	java/lang/Object;
class	java/lang/Object
Asciz	scala/collection/IndexedSeqLike$class;
class	scala/collection/IndexedSeqLike$class
Asciz	isEmpty;
Asciz	(Lscala/collection/IndexedSeqLike;)Z;
NameAndType	isEmpty:(Lscala/collection/IndexedSeqLike;)Z
Method	scala/collection/IndexedSeqLike$class.isEmpty:(Lscala/collection/IndexedSeqLike;)Z
Asciz	scala/collection/mutable/StringBuilder;
class	scala/collection/mutable/StringBuilder
Asciz	()V;
NameAndType	"<init>":()V
Method	scala/collection/mutable/StringBuilder."<init>":()V
Asciz	 ;
String	 
Asciz	append;
Asciz	(Ljava/lang/Object;)Lscala/collection/mutable/StringBuilder;;
NameAndType	append:(Ljava/lang/Object;)Lscala/collection/mutable/StringBuilder;
Method	scala/collection/mutable/StringBuilder.append:(Ljava/lang/Object;)Lscala/collection/mutable/StringBuilder;
Asciz	toString;
NameAndType	toString:()Ljava/lang/String;
Method	scala/collection/mutable/StringBuilder.toString:()Ljava/lang/String;
Asciz	genericWrapArray;
Asciz	(Ljava/lang/Object;)Lscala/collection/mutable/WrappedArray;;
NameAndType	genericWrapArray:(Ljava/lang/Object;)Lscala/collection/mutable/WrappedArray;
Method	scala/Predef$.genericWrapArray:(Ljava/lang/Object;)Lscala/collection/mutable/WrappedArray;
Asciz	scala/collection/immutable/StringLike$class;
class	scala/collection/immutable/StringLike$class
Asciz	format;
Asciz	(Lscala/collection/immutable/StringLike;Lscala/collection/Seq;)Ljava/lang/String;;
NameAndType	format:(Lscala/collection/immutable/StringLike;Lscala/collection/Seq;)Ljava/lang/String;
Method	scala/collection/immutable/StringLike$class.format:(Lscala/collection/immutable/StringLike;Lscala/collection/Seq;)Ljava/lang/String;
Asciz	(Ljava/lang/String;)Lscala/collection/mutable/StringBuilder;;
NameAndType	append:(Ljava/lang/String;)Lscala/collection/mutable/StringBuilder;
Method	scala/collection/mutable/StringBuilder.append:(Ljava/lang/String;)Lscala/collection/mutable/StringBuilder;
Asciz	sb;
Asciz	Lscala/collection/mutable/StringBuilder;;
Asciz	copy;
Asciz	(Ljava/lang/String;Ljava/lang/String;)Lscala/xml/ProcInstr;;
Asciz	(Ljava/lang/String;Ljava/lang/String;)V;
NameAndType	"<init>":(Ljava/lang/String;Ljava/lang/String;)V
Method	scala/xml/ProcInstr."<init>":(Ljava/lang/String;Ljava/lang/String;)V
Asciz	productPrefix;
Asciz	ProcInstr;
String	ProcInstr
Asciz	productArity;
Asciz	()I;
Asciz	productElement;
Asciz	(I)Ljava/lang/Object;;
Asciz	java/lang/IndexOutOfBoundsException;
class	java/lang/IndexOutOfBoundsException
Asciz	scala/runtime/BoxesRunTime;
class	scala/runtime/BoxesRunTime
Asciz	boxToInteger;
Asciz	(I)Ljava/lang/Integer;;
NameAndType	boxToInteger:(I)Ljava/lang/Integer;
Method	scala/runtime/BoxesRunTime.boxToInteger:(I)Ljava/lang/Integer;
Method	java/lang/Object.toString:()Ljava/lang/String;
Method	java/lang/IndexOutOfBoundsException."<init>":(Ljava/lang/String;)V
Asciz	scala/xml/SpecialNode;
class	scala/xml/SpecialNode
Method	scala/xml/SpecialNode."<init>":()V
Asciz	$init$;
Asciz	(Lscala/Product;)V;
NameAndType	$init$:(Lscala/Product;)V
Method	scala/Product$class.$init$:(Lscala/Product;)V
Asciz	scala/xml/Utility$;
class	scala/xml/Utility$
Asciz	Lscala/xml/Utility$;;
NameAndType	MODULE$:Lscala/xml/Utility$;
Field	scala/xml/Utility$.MODULE$:Lscala/xml/Utility$;
Asciz	scala/xml/parsing/TokenTests;
class	scala/xml/parsing/TokenTests
Asciz	isName;
Asciz	(Ljava/lang/String;)Z;
NameAndType	isName:(Ljava/lang/String;)Z
InterfaceMethod	scala/xml/parsing/TokenTests.isName:(Ljava/lang/String;)Z
Asciz	?>;
String	?>
Asciz	java/lang/String;
class	java/lang/String
Asciz	contains;
Asciz	(Ljava/lang/CharSequence;)Z;
NameAndType	contains:(Ljava/lang/CharSequence;)Z
Method	java/lang/String.contains:(Ljava/lang/CharSequence;)Z
Asciz	java/lang/IllegalArgumentException;
class	java/lang/IllegalArgumentException
Asciz	 may not contain \"?>\";
String	 may not contain \"?>\"
Method	java/lang/IllegalArgumentException."<init>":(Ljava/lang/String;)V
Asciz	toLowerCase;
NameAndType	toLowerCase:()Ljava/lang/String;
Method	java/lang/String.toLowerCase:()Ljava/lang/String;
Asciz	xml;
String	xml
Asciz	equals;
Asciz	(Ljava/lang/Object;)Z;
NameAndType	equals:(Ljava/lang/Object;)Z
Method	java/lang/Object.equals:(Ljava/lang/Object;)Z
Asciz	 is reserved;
String	 is reserved
Asciz	 must be an XML Name;
String	 must be an XML Name
Asciz	ScalaSig;
Asciz	scala/ScalaObject;
class	scala/ScalaObject
Asciz	scala/Product;
class	scala/Product
Asciz	java/io/Serializable;
class	java/io/Serializable

{
private final java.lang.String proctext;
  Signature: Ljava/lang/String;

private final java.lang.String target;
  Signature: Ljava/lang/String;

public static final scala.Function1 tupled();
  Signature: ()Lscala/Function1;
  Code:
   Stack=1, Locals=0, Args_size=0
	getstatic	Field scala/xml/ProcInstr$.MODULE$:Lscala/xml/ProcInstr$;
	invokevirtual	Method scala/xml/ProcInstr$.tupled:()Lscala/Function1;
	areturn
  Labels:

public static final scala.Function1 curry();
  Signature: ()Lscala/Function1;
  Code:
   Stack=1, Locals=0, Args_size=0
	getstatic	Field scala/xml/ProcInstr$.MODULE$:Lscala/xml/ProcInstr$;
	invokevirtual	Method scala/xml/ProcInstr$.curry:()Lscala/Function1;
	areturn
  Labels:
  Deprecated: true

public static final scala.Function1 curried();
  Signature: ()Lscala/Function1;
  Code:
   Stack=1, Locals=0, Args_size=0
	getstatic	Field scala/xml/ProcInstr$.MODULE$:Lscala/xml/ProcInstr$;
	invokevirtual	Method scala/xml/ProcInstr$.curried:()Lscala/Function1;
	areturn
  Labels:

public java.lang.String productElementName(int);
  Signature: (I)Ljava/lang/String;
  Code:
   Stack=2, Locals=2, Args_size=2
	aload_0
	iload_1
	invokestatic	Method scala/Product$class.productElementName:(Lscala/Product;I)Ljava/lang/String;
	areturn
  Labels:
  LocalVariableTable: 
   Start  Length  Slot  Name   Signature
   0      6      0    this       Lscala/xml/ProcInstr;
   0      6      1    n       I


public scala.collection.Iterator productIterator();
  Signature: ()Lscala/collection/Iterator;
  Code:
   Stack=1, Locals=1, Args_size=1
	aload_0
	invokestatic	Method scala/Product$class.productIterator:(Lscala/Product;)Lscala/collection/Iterator;
	areturn
  Labels:

public scala.collection.Iterator productElements();
  Signature: ()Lscala/collection/Iterator;
  Code:
   Stack=1, Locals=1, Args_size=1
	aload_0
	invokestatic	Method scala/Product$class.productElements:(Lscala/Product;)Lscala/collection/Iterator;
	areturn
  Labels:
  Deprecated: true

public java.lang.String copy$default$2();
  Signature: ()Ljava/lang/String;
  Code:
   Stack=1, Locals=1, Args_size=1
	aload_0
	invokevirtual	Method proctext:()Ljava/lang/String;
	areturn
  Labels:

public java.lang.String copy$default$1();
  Signature: ()Ljava/lang/String;
  Code:
   Stack=1, Locals=1, Args_size=1
	aload_0
	invokevirtual	Method target:()Ljava/lang/String;
	areturn
  Labels:

public java.lang.String target();
  Signature: ()Ljava/lang/String;
  Code:
   Stack=1, Locals=1, Args_size=1
	aload_0
	getfield	Field target:Ljava/lang/String;
	areturn
  Labels:

public java.lang.String proctext();
  Signature: ()Ljava/lang/String;
  Code:
   Stack=1, Locals=1, Args_size=1
	aload_0
	getfield	Field proctext:Ljava/lang/String;
	areturn
  Labels:

public final boolean doCollectNamespaces();
  Signature: ()Z
  Code:
   Stack=1, Locals=1, Args_size=1
	iconst_0
	ireturn
  Labels:

public final boolean doTransform();
  Signature: ()Z
  Code:
   Stack=1, Locals=1, Args_size=1
	iconst_0
	ireturn
  Labels:

public final java.lang.String label();
  Signature: ()Ljava/lang/String;
  Code:
   Stack=1, Locals=1, Args_size=1
	ldc	String #PI
	areturn
  Labels:

public java.lang.String text();
  Signature: ()Ljava/lang/String;
  Code:
   Stack=1, Locals=1, Args_size=1
	ldc	String 
	areturn
  Labels:

public scala.collection.mutable.StringBuilder buildString(scala.collection.mutable.StringBuilder);
  Signature: (Lscala/collection/mutable/StringBuilder;)Lscala/collection/mutable/StringBuilder;
  Code:
   Stack=9, Locals=7, Args_size=2
	aload_1
	ldc	String <?%s%s?>
	astore_2
	new	class scala/collection/immutable/StringOps
	dup
	aload_2
	invokespecial	Method scala/collection/immutable/StringOps."<init>":(Ljava/lang/String;)V
	getstatic	Field scala/Predef$.MODULE$:Lscala/Predef$;
	iconst_2
	anewarray	class java/lang/Object
	dup
	iconst_0
	aload_0
	invokevirtual	Method target:()Ljava/lang/String;
	aastore
	dup
	iconst_1
	aload_0
	invokevirtual	Method proctext:()Ljava/lang/String;
	astore_3
	new	class scala/collection/immutable/StringOps
	dup
	aload_3
	invokespecial	Method scala/collection/immutable/StringOps."<init>":(Ljava/lang/String;)V
	astore	4
	aload	4
	invokestatic	Method scala/collection/IndexedSeqLike$class.isEmpty:(Lscala/collection/IndexedSeqLike;)Z
	ifeq	l1 // new
	ldc	String 
	goto	l2 // aastore
l1	new	class scala/collection/mutable/StringBuilder
	dup
	invokespecial	Method scala/collection/mutable/StringBuilder."<init>":()V
	ldc	String  
	invokevirtual	Method scala/collection/mutable/StringBuilder.append:(Ljava/lang/Object;)Lscala/collection/mutable/StringBuilder;
	aload_0
	invokevirtual	Method proctext:()Ljava/lang/String;
	invokevirtual	Method scala/collection/mutable/StringBuilder.append:(Ljava/lang/Object;)Lscala/collection/mutable/StringBuilder;
	invokevirtual	Method scala/collection/mutable/StringBuilder.toString:()Ljava/lang/String;
l2	aastore
	invokevirtual	Method scala/Predef$.genericWrapArray:(Ljava/lang/Object;)Lscala/collection/mutable/WrappedArray;
	astore	6
	astore	5
	aload	5
	aload	6
	invokestatic	Method scala/collection/immutable/StringLike$class.format:(Lscala/collection/immutable/StringLike;Lscala/collection/Seq;)Ljava/lang/String;
	invokevirtual	Method scala/collection/mutable/StringBuilder.append:(Ljava/lang/String;)Lscala/collection/mutable/StringBuilder;
	areturn
  Labels:
   	l1 = 56 // new
   	l2 = 78 // aastore
  LocalVariableTable: 
   Start  Length  Slot  Name   Signature
   0      97      0    this       Lscala/xml/ProcInstr;
   0      97      1    sb       Lscala/collection/mutable/StringBuilder;


public scala.xml.ProcInstr copy(java.lang.String, java.lang.String);
  Signature: (Ljava/lang/String;Ljava/lang/String;)Lscala/xml/ProcInstr;
  Code:
   Stack=4, Locals=3, Args_size=3
	new	class scala/xml/ProcInstr
	dup
	aload_1
	aload_2
	invokespecial	Method "<init>":(Ljava/lang/String;Ljava/lang/String;)V
	areturn
  Labels:
  LocalVariableTable: 
   Start  Length  Slot  Name   Signature
   0      10      0    this       Lscala/xml/ProcInstr;
   0      10      1    target       Ljava/lang/String;
   0      10      2    proctext       Ljava/lang/String;


public java.lang.String productPrefix();
  Signature: ()Ljava/lang/String;
  Code:
   Stack=1, Locals=1, Args_size=1
	ldc	String ProcInstr
	areturn
  Labels:

public int productArity();
  Signature: ()I
  Code:
   Stack=1, Locals=1, Args_size=1
	iconst_2
	ireturn
  Labels:

public java.lang.Object productElement(int);
  Signature: (I)Ljava/lang/Object;
  Code:
   Stack=3, Locals=2, Args_size=2
	iload_1
	tableswitch{ //0 to 1
		0: 46;
		1: 39;
		default: 24 }
	new	class java/lang/IndexOutOfBoundsException
	dup
	iload_1
	invokestatic	Method scala/runtime/BoxesRunTime.boxToInteger:(I)Ljava/lang/Integer;
	invokevirtual	Method java/lang/Object.toString:()Ljava/lang/String;
	invokespecial	Method java/lang/IndexOutOfBoundsException."<init>":(Ljava/lang/String;)V
	athrow
	aload_0
	invokevirtual	Method proctext:()Ljava/lang/String;
	goto	l1 // areturn
	aload_0
	invokevirtual	Method target:()Ljava/lang/String;
l1	areturn
  Labels:
   	l1 = 50 // areturn

public scala.xml.ProcInstr(java.lang.String, java.lang.String);
  Signature: (Ljava/lang/String;Ljava/lang/String;)V
  Code:
   Stack=4, Locals=4, Args_size=3
	aload_0
	aload_1
	putfield	Field target:Ljava/lang/String;
	aload_0
	aload_2
	putfield	Field proctext:Ljava/lang/String;
	aload_0
	invokespecial	Method scala/xml/SpecialNode."<init>":()V
	aload_0
	invokestatic	Method scala/Product$class.$init$:(Lscala/Product;)V
	getstatic	Field scala/xml/Utility$.MODULE$:Lscala/xml/Utility$;
	aload_1
	invokeinterface	InterfaceMethod scala/xml/parsing/TokenTests.isName:(Ljava/lang/String;)Z
	ifeq	l1 // new
	aload_2
	ldc	String ?>
	invokevirtual	Method java/lang/String.contains:(Ljava/lang/CharSequence;)Z
	ifeq	l2 // aload_1
	new	class java/lang/IllegalArgumentException
	dup
	new	class scala/collection/mutable/StringBuilder
	dup
	invokespecial	Method scala/collection/mutable/StringBuilder."<init>":()V
	aload_2
	invokevirtual	Method scala/collection/mutable/StringBuilder.append:(Ljava/lang/Object;)Lscala/collection/mutable/StringBuilder;
	ldc	String  may not contain \"?>\"
	invokevirtual	Method scala/collection/mutable/StringBuilder.append:(Ljava/lang/Object;)Lscala/collection/mutable/StringBuilder;
	invokevirtual	Method scala/collection/mutable/StringBuilder.toString:()Ljava/lang/String;
	invokespecial	Method java/lang/IllegalArgumentException."<init>":(Ljava/lang/String;)V
	athrow
l2	aload_1
	invokevirtual	Method java/lang/String.toLowerCase:()Ljava/lang/String;
	ldc	String xml
	astore_3
	dup
	ifnonnull	l3 // aload_3
	pop
	aload_3
	ifnull	l4 // new
	goto	l5 // return
l3	aload_3
	invokevirtual	Method java/lang/Object.equals:(Ljava/lang/Object;)Z
	ifeq	l5 // return
l4	new	class java/lang/IllegalArgumentException
	dup
	new	class scala/collection/mutable/StringBuilder
	dup
	invokespecial	Method scala/collection/mutable/StringBuilder."<init>":()V
	aload_1
	invokevirtual	Method scala/collection/mutable/StringBuilder.append:(Ljava/lang/Object;)Lscala/collection/mutable/StringBuilder;
	ldc	String  is reserved
	invokevirtual	Method scala/collection/mutable/StringBuilder.append:(Ljava/lang/Object;)Lscala/collection/mutable/StringBuilder;
	invokevirtual	Method scala/collection/mutable/StringBuilder.toString:()Ljava/lang/String;
	invokespecial	Method java/lang/IllegalArgumentException."<init>":(Ljava/lang/String;)V
	athrow
l5	return
l1	new	class java/lang/IllegalArgumentException
	dup
	new	class scala/collection/mutable/StringBuilder
	dup
	invokespecial	Method scala/collection/mutable/StringBuilder."<init>":()V
	aload_1
	invokevirtual	Method scala/collection/mutable/StringBuilder.append:(Ljava/lang/Object;)Lscala/collection/mutable/StringBuilder;
	ldc	String  must be an XML Name
	invokevirtual	Method scala/collection/mutable/StringBuilder.append:(Ljava/lang/Object;)Lscala/collection/mutable/StringBuilder;
	invokevirtual	Method scala/collection/mutable/StringBuilder.toString:()Ljava/lang/String;
	invokespecial	Method java/lang/IllegalArgumentException."<init>":(Ljava/lang/String;)V
	athrow
  Labels:
   	l2 = 66 // aload_1
   	l3 = 85 // aload_3
   	l4 = 92 // new
   	l5 = 119 // return
   	l1 = 120 // new
  LocalVariableTable: 
   Start  Length  Slot  Name   Signature
   0      147      0    this       Lscala/xml/ProcInstr;
   0      147      1    target       Ljava/lang/String;
   0      147      2    proctext       Ljava/lang/String;


}

