Compiled from "ProcInstr.scala"
public final class scala.xml.ProcInstr$ extends java.lang.Object implements scala.Function2,scala.ScalaObject
  SourceFile: "ProcInstr.scala"
  Scala: length = 0x
   
  minor version: 0
  major version: 49
  Constant pool:
Asciz	SourceFile;
Asciz	ProcInstr.scala;
Asciz	Scala;
Asciz	MODULE$;
Asciz	Lscala/xml/ProcInstr$;;
Asciz	<clinit>;
Asciz	()V;
Asciz	Code;
Asciz	scala/xml/ProcInstr$;
class	scala/xml/ProcInstr$
Asciz	<init>;
NameAndType	"<init>":()V
Method	scala/xml/ProcInstr$."<init>":()V
Asciz	LineNumberTable;
Asciz	java/lang/Object;
class	java/lang/Object
Method	java/lang/Object."<init>":()V
NameAndType	MODULE$:Lscala/xml/ProcInstr$;
Field	scala/xml/ProcInstr$.MODULE$:Lscala/xml/ProcInstr$;
Asciz	scala/Function2$class;
class	scala/Function2$class
Asciz	$init$;
Asciz	(Lscala/Function2;)V;
NameAndType	$init$:(Lscala/Function2;)V
Method	scala/Function2$class.$init$:(Lscala/Function2;)V
Asciz	apply;
Asciz	(Ljava/lang/Object;Ljava/lang/Object;)Ljava/lang/Object;;
Asciz	java/lang/String;
class	java/lang/String
Asciz	(Ljava/lang/String;Ljava/lang/String;)Lscala/xml/ProcInstr;;
NameAndType	apply:(Ljava/lang/String;Ljava/lang/String;)Lscala/xml/ProcInstr;
Method	scala/xml/ProcInstr$.apply:(Ljava/lang/String;Ljava/lang/String;)Lscala/xml/ProcInstr;
Asciz	this;
Asciz	v1;
Asciz	Ljava/lang/Object;;
Asciz	v2;
Asciz	LocalVariableTable;
Asciz	scala/xml/ProcInstr;
class	scala/xml/ProcInstr
Asciz	(Ljava/lang/String;Ljava/lang/String;)V;
NameAndType	"<init>":(Ljava/lang/String;Ljava/lang/String;)V
Method	scala/xml/ProcInstr."<init>":(Ljava/lang/String;Ljava/lang/String;)V
Asciz	target;
Asciz	Ljava/lang/String;;
Asciz	proctext;
Asciz	unapply;
Asciz	(Lscala/xml/ProcInstr;)Lscala/Some;;
Asciz	scala/Some;
class	scala/Some
Asciz	scala/Tuple2;
class	scala/Tuple2
Asciz	()Ljava/lang/String;;
NameAndType	target:()Ljava/lang/String;
Method	scala/xml/ProcInstr.target:()Ljava/lang/String;
NameAndType	proctext:()Ljava/lang/String;
Method	scala/xml/ProcInstr.proctext:()Ljava/lang/String;
Asciz	(Ljava/lang/Object;Ljava/lang/Object;)V;
NameAndType	"<init>":(Ljava/lang/Object;Ljava/lang/Object;)V
Method	scala/Tuple2."<init>":(Ljava/lang/Object;Ljava/lang/Object;)V
Asciz	(Ljava/lang/Object;)V;
NameAndType	"<init>":(Ljava/lang/Object;)V
Method	scala/Some."<init>":(Ljava/lang/Object;)V
Asciz	x$0;
Asciz	Lscala/xml/ProcInstr;;
Asciz	curry;
Asciz	()Lscala/Function1;;
Asciz	(Lscala/Function2;)Lscala/Function1;;
NameAndType	curry:(Lscala/Function2;)Lscala/Function1;
Method	scala/Function2$class.curry:(Lscala/Function2;)Lscala/Function1;
Asciz	toString;
Asciz	(Lscala/Function2;)Ljava/lang/String;;
NameAndType	toString:(Lscala/Function2;)Ljava/lang/String;
Method	scala/Function2$class.toString:(Lscala/Function2;)Ljava/lang/String;
Asciz	scala/Function2;
class	scala/Function2
Asciz	scala/ScalaObject;
class	scala/ScalaObject

{
public static final scala.xml.ProcInstr$ MODULE$;
  Signature: Lscala/xml/ProcInstr$;

public static {};
  Signature: ()V
  Code:
   Stack=1, Locals=0, Args_size=0
	new	class scala/xml/ProcInstr$
	invokespecial	Method "<init>":()V
	return
  Labels:

private scala.xml.ProcInstr$();
  Signature: ()V
  Code:
   Stack=1, Locals=1, Args_size=1
	aload_0
	invokespecial	Method java/lang/Object."<init>":()V
	aload_0
	putstatic	Field MODULE$:Lscala/xml/ProcInstr$;
	aload_0
	invokestatic	Method scala/Function2$class.$init$:(Lscala/Function2;)V
	return
  Labels:

public java.lang.Object apply(java.lang.Object, java.lang.Object);
  Signature: (Ljava/lang/Object;Ljava/lang/Object;)Ljava/lang/Object;
  Code:
   Stack=3, Locals=3, Args_size=3
	aload_0
	aload_1
	checkcast	class java/lang/String
	aload_2
	checkcast	class java/lang/String
	invokevirtual	Method apply:(Ljava/lang/String;Ljava/lang/String;)Lscala/xml/ProcInstr;
	areturn
  Labels:
  LocalVariableTable: 
   Start  Length  Slot  Name   Signature
   0      13      0    this       Lscala/xml/ProcInstr$;
   0      13      1    v1       Ljava/lang/Object;
   0      13      2    v2       Ljava/lang/Object;


public scala.xml.ProcInstr apply(java.lang.String, java.lang.String);
  Signature: (Ljava/lang/String;Ljava/lang/String;)Lscala/xml/ProcInstr;
  Code:
   Stack=4, Locals=3, Args_size=3
	new	class scala/xml/ProcInstr
	dup
	aload_1
	aload_2
	invokespecial	Method scala/xml/ProcInstr."<init>":(Ljava/lang/String;Ljava/lang/String;)V
	areturn
  Labels:
  LocalVariableTable: 
   Start  Length  Slot  Name   Signature
   0      10      0    this       Lscala/xml/ProcInstr$;
   0      10      1    target       Ljava/lang/String;
   0      10      2    proctext       Ljava/lang/String;


public scala.Some unapply(scala.xml.ProcInstr);
  Signature: (Lscala/xml/ProcInstr;)Lscala/Some;
  Code:
   Stack=6, Locals=2, Args_size=2
	new	class scala/Some
	dup
	new	class scala/Tuple2
	dup
	aload_1
	invokevirtual	Method scala/xml/ProcInstr.target:()Ljava/lang/String;
	aload_1
	invokevirtual	Method scala/xml/ProcInstr.proctext:()Ljava/lang/String;
	invokespecial	Method scala/Tuple2."<init>":(Ljava/lang/Object;Ljava/lang/Object;)V
	invokespecial	Method scala/Some."<init>":(Ljava/lang/Object;)V
	areturn
  Labels:
  LocalVariableTable: 
   Start  Length  Slot  Name   Signature
   0      23      0    this       Lscala/xml/ProcInstr$;
   0      23      1    x$0       Lscala/xml/ProcInstr;


public scala.Function1 curry();
  Signature: ()Lscala/Function1;
  Code:
   Stack=1, Locals=1, Args_size=1
	aload_0
	invokestatic	Method scala/Function2$class.curry:(Lscala/Function2;)Lscala/Function1;
	areturn
  Labels:

public java.lang.String toString();
  Signature: ()Ljava/lang/String;
  Code:
   Stack=1, Locals=1, Args_size=1
	aload_0
	invokestatic	Method scala/Function2$class.toString:(Lscala/Function2;)Ljava/lang/String;
	areturn
  Labels:

}

