Compiled from "QNode.scala"
public final class scala.xml.QNode$ extends java.lang.Object implements scala.ScalaObject
  SourceFile: "QNode.scala"
  Scala: length = 0x
   
  minor version: 0
  major version: 49
  Constant pool:
Asciz	SourceFile;
Asciz	QNode.scala;
Asciz	Scala;
Asciz	MODULE$;
Asciz	Lscala/xml/QNode$;;
Asciz	<clinit>;
Asciz	()V;
Asciz	Code;
Asciz	scala/xml/QNode$;
class	scala/xml/QNode$
Asciz	<init>;
NameAndType	"<init>":()V
Method	scala/xml/QNode$."<init>":()V
Asciz	unapplySeq;
Asciz	(Lscala/xml/Node;)Lscala/Some;;
Asciz	scala/Some;
class	scala/Some
Asciz	LineNumberTable;
Asciz	scala/Tuple4;
class	scala/Tuple4
Asciz	scala/xml/Node;
class	scala/xml/Node
Asciz	scope;
Asciz	()Lscala/xml/NamespaceBinding;;
NameAndType	scope:()Lscala/xml/NamespaceBinding;
Method	scala/xml/Node.scope:()Lscala/xml/NamespaceBinding;
Asciz	prefix;
Asciz	()Ljava/lang/String;;
NameAndType	prefix:()Ljava/lang/String;
Method	scala/xml/Node.prefix:()Ljava/lang/String;
Asciz	scala/xml/NamespaceBinding;
class	scala/xml/NamespaceBinding
Asciz	getURI;
Asciz	(Ljava/lang/String;)Ljava/lang/String;;
NameAndType	getURI:(Ljava/lang/String;)Ljava/lang/String;
Method	scala/xml/NamespaceBinding.getURI:(Ljava/lang/String;)Ljava/lang/String;
Asciz	label;
NameAndType	label:()Ljava/lang/String;
Method	scala/xml/Node.label:()Ljava/lang/String;
Asciz	attributes;
Asciz	()Lscala/xml/MetaData;;
NameAndType	attributes:()Lscala/xml/MetaData;
Method	scala/xml/Node.attributes:()Lscala/xml/MetaData;
Asciz	child;
Asciz	()Lscala/collection/Seq;;
NameAndType	child:()Lscala/collection/Seq;
Method	scala/xml/Node.child:()Lscala/collection/Seq;
Asciz	(Ljava/lang/Object;Ljava/lang/Object;Ljava/lang/Object;Ljava/lang/Object;)V;
NameAndType	"<init>":(Ljava/lang/Object;Ljava/lang/Object;Ljava/lang/Object;Ljava/lang/Object;)V
Method	scala/Tuple4."<init>":(Ljava/lang/Object;Ljava/lang/Object;Ljava/lang/Object;Ljava/lang/Object;)V
Asciz	(Ljava/lang/Object;)V;
NameAndType	"<init>":(Ljava/lang/Object;)V
Method	scala/Some."<init>":(Ljava/lang/Object;)V
Asciz	this;
Asciz	n;
Asciz	Lscala/xml/Node;;
Asciz	LocalVariableTable;
Asciz	(Lscala/xml/Node;)Lscala/Some<Lscala/Tuple4<Ljava/lang/String;Ljava/lang/String;Lscala/xml/MetaData;Lscala/collection/Seq<Lscala/xml/Node;>;>;>;;
Asciz	Signature;
Asciz	java/lang/Object;
class	java/lang/Object
Method	java/lang/Object."<init>":()V
NameAndType	MODULE$:Lscala/xml/QNode$;
Field	scala/xml/QNode$.MODULE$:Lscala/xml/QNode$;
Asciz	scala/ScalaObject;
class	scala/ScalaObject

{
public static final scala.xml.QNode$ MODULE$;
  Signature: Lscala/xml/QNode$;

public static {};
  Signature: ()V
  Code:
   Stack=1, Locals=0, Args_size=0
	new	class scala/xml/QNode$
	invokespecial	Method "<init>":()V
	return
  Labels:

public scala.Some unapplySeq(scala.xml.Node);
  Signature: (Lscala/xml/Node;)Lscala/Some;
  Code:
   Stack=8, Locals=2, Args_size=2
	new	class scala/Some
	dup
	new	class scala/Tuple4
	dup
	aload_1
	invokevirtual	Method scala/xml/Node.scope:()Lscala/xml/NamespaceBinding;
	aload_1
	invokevirtual	Method scala/xml/Node.prefix:()Ljava/lang/String;
	invokevirtual	Method scala/xml/NamespaceBinding.getURI:(Ljava/lang/String;)Ljava/lang/String;
	aload_1
	invokevirtual	Method scala/xml/Node.label:()Ljava/lang/String;
	aload_1
	invokevirtual	Method scala/xml/Node.attributes:()Lscala/xml/MetaData;
	aload_1
	invokevirtual	Method scala/xml/Node.child:()Lscala/collection/Seq;
	invokespecial	Method scala/Tuple4."<init>":(Ljava/lang/Object;Ljava/lang/Object;Ljava/lang/Object;Ljava/lang/Object;)V
	invokespecial	Method scala/Some."<init>":(Ljava/lang/Object;)V
	areturn
  Labels:
  LocalVariableTable: 
   Start  Length  Slot  Name   Signature
   0      38      0    this       Lscala/xml/QNode$;
   0      38      1    n       Lscala/xml/Node;

  Signature: length = 0x2
   00 3A 

private scala.xml.QNode$();
  Signature: ()V
  Code:
   Stack=1, Locals=1, Args_size=1
	aload_0
	invokespecial	Method java/lang/Object."<init>":()V
	aload_0
	putstatic	Field MODULE$:Lscala/xml/QNode$;
	return
  Labels:

}

