Compiled from "XML.scala"
public final class scala.xml.Source extends java.lang.Object
  SourceFile: "XML.scala"
  ScalaSig: length = 0x223
   05 00 5B 07 05 01 02 FFFFFF88 02 07 01 06 53 6F 75 72
   63 65 0A 02 03 04 01 03 78 6D 6C 0A 01 05 01 05
   73 63 61 6C 61 03 00 10 02 08 09 0D 01 02 06 08
   0A 02 FFFFFF84 FFFFFF80 FFFFFF80 FFFFFF88 02 0B 02 06 53 6F 75 72 63 65
   13 03 09 0C 14 10 02 0D 12 0D 01 0E 0A 02 0F 10
   01 04 6C 61 6E 67 0A 01 11 01 04 6A 61 76 61 09
   02 13 0E 02 06 4F 62 6A 65 63 74 10 02 15 16 0D
   01 04 09 02 17 04 02 0B 53 63 61 6C 61 4F 62 6A
   65 63 74 08 05 19 09 FFFFFF84 00 1A 01 06 3C 69 6E 69
   74 3E 14 01 07 08 05 1C 09 FFFFFF84 00 1D 01 08 66 72
   6F 6D 46 69 6C 65 14 02 1E 27 10 02 1F 25 0D 01
   20 0A 02 21 22 01 03 73 61 78 0A 02 03 23 0A 01
   24 01 03 6F 72 67 09 02 26 20 02 0B 49 6E 70 75
   74 53 6F 75 72 63 65 08 05 28 1B FFFFFFC0 00 29 01 04
   66 69 6C 65 10 02 2A 2D 0D 01 2B 0A 02 2C 10 01
   02 69 6F 09 02 2E 2B 02 04 46 69 6C 65 08 05 1C
   09 FFFFFF84 00 30 14 02 1E 31 08 05 32 2F FFFFFFC0 00 33 01
   02 66 64 10 02 2A 34 09 02 35 2B 02 0E 46 69 6C
   65 44 65 73 63 72 69 70 74 6F 72 08 05 1C 09 FFFFFF84
   00 37 14 02 1E 38 08 05 39 36 FFFFFFC0 00 3A 01 04 6E
   61 6D 65 10 02 3B 3E 0E 02 15 3C 09 02 3D 04 01
   06 50 72 65 64 65 66 09 02 3F 40 02 06 53 74 72
   69 6E 67 0A 02 3D 04 08 05 42 09 FFFFFF84 00 43 01 0F
   66 72 6F 6D 49 6E 70 75 74 53 74 72 65 61 6D 14
   02 1E 44 08 05 45 41 FFFFFFC0 00 46 01 02 69 73 10 02
   2A 47 09 02 48 2B 02 0B 49 6E 70 75 74 53 74 72
   65 61 6D 08 05 4A 09 FFFFFF84 00 4B 01 0A 66 72 6F 6D
   52 65 61 64 65 72 14 02 1E 4C 08 05 4D 49 FFFFFFC0 00
   4E 01 06 72 65 61 64 65 72 10 02 2A 4F 09 02 50
   2B 02 06 52 65 61 64 65 72 08 05 52 09 FFFFFF84 00 53
   01 09 66 72 6F 6D 53 79 73 49 64 14 02 1E 54 08
   05 55 51 FFFFFFC0 00 3A 01 05 73 79 73 49 44 08 05 57
   09 FFFFFF84 00 58 01 0A 66 72 6F 6D 53 74 72 69 6E 67
   14 02 1E 59 08 05 5A 56 FFFFFFC0 00 3A 01 06 73 74 72
   69 6E 67 
  minor version: 0
  major version: 49
  Constant pool:
Asciz	SourceFile;
Asciz	XML.scala;
Asciz	fromString;
Asciz	(Ljava/lang/String;)Lorg/xml/sax/InputSource;;
Asciz	Code;
Asciz	scala/xml/Source$;
class	scala/xml/Source$
Asciz	MODULE$;
Asciz	Lscala/xml/Source$;;
NameAndType	MODULE$:Lscala/xml/Source$;
Field	scala/xml/Source$.MODULE$:Lscala/xml/Source$;
NameAndType	fromString:(Ljava/lang/String;)Lorg/xml/sax/InputSource;
Method	scala/xml/Source$.fromString:(Ljava/lang/String;)Lorg/xml/sax/InputSource;
Asciz	fromSysId;
NameAndType	fromSysId:(Ljava/lang/String;)Lorg/xml/sax/InputSource;
Method	scala/xml/Source$.fromSysId:(Ljava/lang/String;)Lorg/xml/sax/InputSource;
Asciz	fromReader;
Asciz	(Ljava/io/Reader;)Lorg/xml/sax/InputSource;;
NameAndType	fromReader:(Ljava/io/Reader;)Lorg/xml/sax/InputSource;
Method	scala/xml/Source$.fromReader:(Ljava/io/Reader;)Lorg/xml/sax/InputSource;
Asciz	fromInputStream;
Asciz	(Ljava/io/InputStream;)Lorg/xml/sax/InputSource;;
NameAndType	fromInputStream:(Ljava/io/InputStream;)Lorg/xml/sax/InputSource;
Method	scala/xml/Source$.fromInputStream:(Ljava/io/InputStream;)Lorg/xml/sax/InputSource;
Asciz	fromFile;
NameAndType	fromFile:(Ljava/lang/String;)Lorg/xml/sax/InputSource;
Method	scala/xml/Source$.fromFile:(Ljava/lang/String;)Lorg/xml/sax/InputSource;
Asciz	(Ljava/io/FileDescriptor;)Lorg/xml/sax/InputSource;;
NameAndType	fromFile:(Ljava/io/FileDescriptor;)Lorg/xml/sax/InputSource;
Method	scala/xml/Source$.fromFile:(Ljava/io/FileDescriptor;)Lorg/xml/sax/InputSource;
Asciz	(Ljava/io/File;)Lorg/xml/sax/InputSource;;
NameAndType	fromFile:(Ljava/io/File;)Lorg/xml/sax/InputSource;
Method	scala/xml/Source$.fromFile:(Ljava/io/File;)Lorg/xml/sax/InputSource;
Asciz	ScalaSig;
Asciz	scala/xml/Source;
class	scala/xml/Source
Asciz	java/lang/Object;
class	java/lang/Object

{
public static final org.xml.sax.InputSource fromString(java.lang.String);
  Signature: (Ljava/lang/String;)Lorg/xml/sax/InputSource;
  Code:
   Stack=2, Locals=1, Args_size=1
	getstatic	Field scala/xml/Source$.MODULE$:Lscala/xml/Source$;
	aload_0
	invokevirtual	Method scala/xml/Source$.fromString:(Ljava/lang/String;)Lorg/xml/sax/InputSource;
	areturn
  Labels:

public static final org.xml.sax.InputSource fromSysId(java.lang.String);
  Signature: (Ljava/lang/String;)Lorg/xml/sax/InputSource;
  Code:
   Stack=2, Locals=1, Args_size=1
	getstatic	Field scala/xml/Source$.MODULE$:Lscala/xml/Source$;
	aload_0
	invokevirtual	Method scala/xml/Source$.fromSysId:(Ljava/lang/String;)Lorg/xml/sax/InputSource;
	areturn
  Labels:

public static final org.xml.sax.InputSource fromReader(java.io.Reader);
  Signature: (Ljava/io/Reader;)Lorg/xml/sax/InputSource;
  Code:
   Stack=2, Locals=1, Args_size=1
	getstatic	Field scala/xml/Source$.MODULE$:Lscala/xml/Source$;
	aload_0
	invokevirtual	Method scala/xml/Source$.fromReader:(Ljava/io/Reader;)Lorg/xml/sax/InputSource;
	areturn
  Labels:

public static final org.xml.sax.InputSource fromInputStream(java.io.InputStream);
  Signature: (Ljava/io/InputStream;)Lorg/xml/sax/InputSource;
  Code:
   Stack=2, Locals=1, Args_size=1
	getstatic	Field scala/xml/Source$.MODULE$:Lscala/xml/Source$;
	aload_0
	invokevirtual	Method scala/xml/Source$.fromInputStream:(Ljava/io/InputStream;)Lorg/xml/sax/InputSource;
	areturn
  Labels:

public static final org.xml.sax.InputSource fromFile(java.lang.String);
  Signature: (Ljava/lang/String;)Lorg/xml/sax/InputSource;
  Code:
   Stack=2, Locals=1, Args_size=1
	getstatic	Field scala/xml/Source$.MODULE$:Lscala/xml/Source$;
	aload_0
	invokevirtual	Method scala/xml/Source$.fromFile:(Ljava/lang/String;)Lorg/xml/sax/InputSource;
	areturn
  Labels:

public static final org.xml.sax.InputSource fromFile(java.io.FileDescriptor);
  Signature: (Ljava/io/FileDescriptor;)Lorg/xml/sax/InputSource;
  Code:
   Stack=2, Locals=1, Args_size=1
	getstatic	Field scala/xml/Source$.MODULE$:Lscala/xml/Source$;
	aload_0
	invokevirtual	Method scala/xml/Source$.fromFile:(Ljava/io/FileDescriptor;)Lorg/xml/sax/InputSource;
	areturn
  Labels:

public static final org.xml.sax.InputSource fromFile(java.io.File);
  Signature: (Ljava/io/File;)Lorg/xml/sax/InputSource;
  Code:
   Stack=2, Locals=1, Args_size=1
	getstatic	Field scala/xml/Source$.MODULE$:Lscala/xml/Source$;
	aload_0
	invokevirtual	Method scala/xml/Source$.fromFile:(Ljava/io/File;)Lorg/xml/sax/InputSource;
	areturn
  Labels:

}

