Compiled from "XML.scala"
public final class scala.xml.Source$ extends java.lang.Object implements scala.ScalaObject
  SourceFile: "XML.scala"
  Scala: length = 0x
   
  minor version: 0
  major version: 49
  Constant pool:
Asciz	SourceFile;
Asciz	XML.scala;
Asciz	Scala;
Asciz	MODULE$;
Asciz	Lscala/xml/Source$;;
Asciz	<clinit>;
Asciz	()V;
Asciz	Code;
Asciz	scala/xml/Source$;
class	scala/xml/Source$
Asciz	<init>;
NameAndType	"<init>":()V
Method	scala/xml/Source$."<init>":()V
Asciz	LineNumberTable;
Asciz	java/lang/Object;
class	java/lang/Object
Method	java/lang/Object."<init>":()V
NameAndType	MODULE$:Lscala/xml/Source$;
Field	scala/xml/Source$.MODULE$:Lscala/xml/Source$;
Asciz	fromString;
Asciz	(Ljava/lang/String;)Lorg/xml/sax/InputSource;;
Asciz	java/io/StringReader;
class	java/io/StringReader
Asciz	(Ljava/lang/String;)V;
NameAndType	"<init>":(Ljava/lang/String;)V
Method	java/io/StringReader."<init>":(Ljava/lang/String;)V
Asciz	fromReader;
Asciz	(Ljava/io/Reader;)Lorg/xml/sax/InputSource;;
NameAndType	fromReader:(Ljava/io/Reader;)Lorg/xml/sax/InputSource;
Method	scala/xml/Source$.fromReader:(Ljava/io/Reader;)Lorg/xml/sax/InputSource;
Asciz	this;
Asciz	string;
Asciz	Ljava/lang/String;;
Asciz	LocalVariableTable;
Asciz	fromSysId;
Asciz	org/xml/sax/InputSource;
class	org/xml/sax/InputSource
Method	org/xml/sax/InputSource."<init>":(Ljava/lang/String;)V
Asciz	sysID;
Asciz	(Ljava/io/Reader;)V;
NameAndType	"<init>":(Ljava/io/Reader;)V
Method	org/xml/sax/InputSource."<init>":(Ljava/io/Reader;)V
Asciz	reader;
Asciz	Ljava/io/Reader;;
Asciz	fromInputStream;
Asciz	(Ljava/io/InputStream;)Lorg/xml/sax/InputSource;;
Asciz	(Ljava/io/InputStream;)V;
NameAndType	"<init>":(Ljava/io/InputStream;)V
Method	org/xml/sax/InputSource."<init>":(Ljava/io/InputStream;)V
Asciz	is;
Asciz	Ljava/io/InputStream;;
Asciz	fromFile;
Asciz	java/io/FileInputStream;
class	java/io/FileInputStream
Method	java/io/FileInputStream."<init>":(Ljava/lang/String;)V
Asciz	name;
Asciz	(Ljava/io/FileDescriptor;)Lorg/xml/sax/InputSource;;
Asciz	(Ljava/io/FileDescriptor;)V;
NameAndType	"<init>":(Ljava/io/FileDescriptor;)V
Method	java/io/FileInputStream."<init>":(Ljava/io/FileDescriptor;)V
Asciz	fd;
Asciz	Ljava/io/FileDescriptor;;
Asciz	(Ljava/io/File;)Lorg/xml/sax/InputSource;;
Asciz	(Ljava/io/File;)V;
NameAndType	"<init>":(Ljava/io/File;)V
Method	java/io/FileInputStream."<init>":(Ljava/io/File;)V
Asciz	file;
Asciz	Ljava/io/File;;
Asciz	scala/ScalaObject;
class	scala/ScalaObject

{
public static final scala.xml.Source$ MODULE$;
  Signature: Lscala/xml/Source$;

public static {};
  Signature: ()V
  Code:
   Stack=1, Locals=0, Args_size=0
	new	class scala/xml/Source$
	invokespecial	Method "<init>":()V
	return
  Labels:

private scala.xml.Source$();
  Signature: ()V
  Code:
   Stack=1, Locals=1, Args_size=1
	aload_0
	invokespecial	Method java/lang/Object."<init>":()V
	aload_0
	putstatic	Field MODULE$:Lscala/xml/Source$;
	return
  Labels:

public org.xml.sax.InputSource fromString(java.lang.String);
  Signature: (Ljava/lang/String;)Lorg/xml/sax/InputSource;
  Code:
   Stack=4, Locals=2, Args_size=2
	aload_0
	new	class java/io/StringReader
	dup
	aload_1
	invokespecial	Method java/io/StringReader."<init>":(Ljava/lang/String;)V
	invokevirtual	Method fromReader:(Ljava/io/Reader;)Lorg/xml/sax/InputSource;
	areturn
  Labels:
  LocalVariableTable: 
   Start  Length  Slot  Name   Signature
   0      13      0    this       Lscala/xml/Source$;
   0      13      1    string       Ljava/lang/String;


public org.xml.sax.InputSource fromSysId(java.lang.String);
  Signature: (Ljava/lang/String;)Lorg/xml/sax/InputSource;
  Code:
   Stack=3, Locals=2, Args_size=2
	new	class org/xml/sax/InputSource
	dup
	aload_1
	invokespecial	Method org/xml/sax/InputSource."<init>":(Ljava/lang/String;)V
	areturn
  Labels:
  LocalVariableTable: 
   Start  Length  Slot  Name   Signature
   0      9      0    this       Lscala/xml/Source$;
   0      9      1    sysID       Ljava/lang/String;


public org.xml.sax.InputSource fromReader(java.io.Reader);
  Signature: (Ljava/io/Reader;)Lorg/xml/sax/InputSource;
  Code:
   Stack=3, Locals=2, Args_size=2
	new	class org/xml/sax/InputSource
	dup
	aload_1
	invokespecial	Method org/xml/sax/InputSource."<init>":(Ljava/io/Reader;)V
	areturn
  Labels:
  LocalVariableTable: 
   Start  Length  Slot  Name   Signature
   0      9      0    this       Lscala/xml/Source$;
   0      9      1    reader       Ljava/io/Reader;


public org.xml.sax.InputSource fromInputStream(java.io.InputStream);
  Signature: (Ljava/io/InputStream;)Lorg/xml/sax/InputSource;
  Code:
   Stack=3, Locals=2, Args_size=2
	new	class org/xml/sax/InputSource
	dup
	aload_1
	invokespecial	Method org/xml/sax/InputSource."<init>":(Ljava/io/InputStream;)V
	areturn
  Labels:
  LocalVariableTable: 
   Start  Length  Slot  Name   Signature
   0      9      0    this       Lscala/xml/Source$;
   0      9      1    is       Ljava/io/InputStream;


public org.xml.sax.InputSource fromFile(java.lang.String);
  Signature: (Ljava/lang/String;)Lorg/xml/sax/InputSource;
  Code:
   Stack=5, Locals=2, Args_size=2
	new	class org/xml/sax/InputSource
	dup
	new	class java/io/FileInputStream
	dup
	aload_1
	invokespecial	Method java/io/FileInputStream."<init>":(Ljava/lang/String;)V
	invokespecial	Method org/xml/sax/InputSource."<init>":(Ljava/io/InputStream;)V
	areturn
  Labels:
  LocalVariableTable: 
   Start  Length  Slot  Name   Signature
   0      16      0    this       Lscala/xml/Source$;
   0      16      1    name       Ljava/lang/String;


public org.xml.sax.InputSource fromFile(java.io.FileDescriptor);
  Signature: (Ljava/io/FileDescriptor;)Lorg/xml/sax/InputSource;
  Code:
   Stack=5, Locals=2, Args_size=2
	new	class org/xml/sax/InputSource
	dup
	new	class java/io/FileInputStream
	dup
	aload_1
	invokespecial	Method java/io/FileInputStream."<init>":(Ljava/io/FileDescriptor;)V
	invokespecial	Method org/xml/sax/InputSource."<init>":(Ljava/io/InputStream;)V
	areturn
  Labels:
  LocalVariableTable: 
   Start  Length  Slot  Name   Signature
   0      16      0    this       Lscala/xml/Source$;
   0      16      1    fd       Ljava/io/FileDescriptor;


public org.xml.sax.InputSource fromFile(java.io.File);
  Signature: (Ljava/io/File;)Lorg/xml/sax/InputSource;
  Code:
   Stack=5, Locals=2, Args_size=2
	new	class org/xml/sax/InputSource
	dup
	new	class java/io/FileInputStream
	dup
	aload_1
	invokespecial	Method java/io/FileInputStream."<init>":(Ljava/io/File;)V
	invokespecial	Method org/xml/sax/InputSource."<init>":(Ljava/io/InputStream;)V
	areturn
  Labels:
  LocalVariableTable: 
   Start  Length  Slot  Name   Signature
   0      16      0    this       Lscala/xml/Source$;
   0      16      1    file       Ljava/io/File;


}

