Compiled from "Text.scala"
public final class scala.xml.Text$ extends java.lang.Object implements scala.ScalaObject
  SourceFile: "Text.scala"
  Scala: length = 0x
   
  minor version: 0
  major version: 49
  Constant pool:
const #1 = Asciz	SourceFile;
const #2 = Asciz	Text.scala;
const #3 = Asciz	Scala;
const #4 = Asciz	MODULE$;
const #5 = Asciz	Lscala/xml/Text$;;
const #6 = Asciz	<clinit>;
const #7 = Asciz	()V;
const #8 = Asciz	Code;
const #9 = Asciz	scala/xml/Text$;
const #10 = class	#9;	//  scala/xml/Text$
const #11 = Asciz	<init>;
const #12 = NameAndType	#11:#7;//  "<init>":()V
const #13 = Method	#10.#12;	//  scala/xml/Text$."<init>":()V
const #14 = Asciz	LineNumberTable;
const #15 = Asciz	java/lang/Object;
const #16 = class	#15;	//  java/lang/Object
const #17 = Method	#16.#12;	//  java/lang/Object."<init>":()V
const #18 = NameAndType	#4:#5;//  MODULE$:Lscala/xml/Text$;
const #19 = Field	#10.#18;	//  scala/xml/Text$.MODULE$:Lscala/xml/Text$;
const #20 = Asciz	unapply;
const #21 = Asciz	(Ljava/lang/Object;)Lscala/Option;;
const #22 = Asciz	scala/xml/Text;
const #23 = class	#22;	//  scala/xml/Text
const #24 = Asciz	scala/Some;
const #25 = class	#24;	//  scala/Some
const #26 = Asciz	data;
const #27 = Asciz	()Ljava/lang/Object;;
const #28 = NameAndType	#26:#27;//  data:()Ljava/lang/Object;
const #29 = Method	#23.#28;	//  scala/xml/Text.data:()Ljava/lang/Object;
const #30 = Asciz	(Ljava/lang/Object;)V;
const #31 = NameAndType	#11:#30;//  "<init>":(Ljava/lang/Object;)V
const #32 = Method	#25.#31;	//  scala/Some."<init>":(Ljava/lang/Object;)V
const #33 = Asciz	scala/MatchError;
const #34 = class	#33;	//  scala/MatchError
const #35 = Asciz	toString;
const #36 = Asciz	()Ljava/lang/String;;
const #37 = NameAndType	#35:#36;//  toString:()Ljava/lang/String;
const #38 = Method	#16.#37;	//  java/lang/Object.toString:()Ljava/lang/String;
const #39 = Asciz	(Ljava/lang/String;)V;
const #40 = NameAndType	#11:#39;//  "<init>":(Ljava/lang/String;)V
const #41 = Method	#34.#40;	//  scala/MatchError."<init>":(Ljava/lang/String;)V
const #42 = Asciz	scala/None$;
const #43 = class	#42;	//  scala/None$
const #44 = Asciz	Lscala/None$;;
const #45 = NameAndType	#4:#44;//  MODULE$:Lscala/None$;
const #46 = Field	#43.#45;	//  scala/None$.MODULE$:Lscala/None$;
const #47 = Asciz	this;
const #48 = Asciz	other;
const #49 = Asciz	Ljava/lang/Object;;
const #50 = Asciz	temp2;
const #51 = Asciz	Lscala/xml/Text;;
const #52 = Asciz	LocalVariableTable;
const #53 = Asciz	(Ljava/lang/Object;)Lscala/Option<Ljava/lang/String;>;;
const #54 = Asciz	Signature;
const #55 = Asciz	apply;
const #56 = Asciz	(Ljava/lang/String;)Lscala/xml/Text;;
const #57 = Asciz	equals;
const #58 = Asciz	(Ljava/lang/Object;)Z;
const #59 = NameAndType	#57:#58;//  equals:(Ljava/lang/Object;)Z
const #60 = Method	#16.#59;	//  java/lang/Object.equals:(Ljava/lang/Object;)Z
const #61 = Asciz	java/lang/IllegalArgumentException;
const #62 = class	#61;	//  java/lang/IllegalArgumentException
const #63 = Asciz	tried to construct Text with null;
const #64 = String	#63;	//  tried to construct Text with null
const #65 = Method	#62.#40;	//  java/lang/IllegalArgumentException."<init>":(Ljava/lang/String;)V
const #66 = Method	#23.#40;	//  scala/xml/Text."<init>":(Ljava/lang/String;)V
const #67 = Asciz	Ljava/lang/String;;
const #68 = Asciz	scala/ScalaObject;
const #69 = class	#68;	//  scala/ScalaObject

{
public static final scala.xml.Text$ MODULE$;

public static {};
  Code:
   Stack=1, Locals=0, Args_size=0
   0:	new	#10; //class scala/xml/Text$
   3:	invokespecial	#13; //Method "<init>":()V
   6:	return

public scala.Option unapply(java.lang.Object);
  Code:
   Stack=3, Locals=3, Args_size=2
   0:	aload_1
   1:	instanceof	#23; //class scala/xml/Text
   4:	ifeq	42
   7:	aload_1
   8:	checkcast	#23; //class scala/xml/Text
   11:	astore_2
   12:	iconst_1
   13:	ifeq	30
   16:	new	#25; //class scala/Some
   19:	dup
   20:	aload_2
   21:	invokevirtual	#29; //Method scala/xml/Text.data:()Ljava/lang/Object;
   24:	invokespecial	#32; //Method scala/Some."<init>":(Ljava/lang/Object;)V
   27:	goto	49
   30:	new	#34; //class scala/MatchError
   33:	dup
   34:	aload_1
   35:	invokevirtual	#38; //Method java/lang/Object.toString:()Ljava/lang/String;
   38:	invokespecial	#41; //Method scala/MatchError."<init>":(Ljava/lang/String;)V
   41:	athrow
   42:	iconst_1
   43:	ifeq	50
   46:	getstatic	#46; //Field scala/None$.MODULE$:Lscala/None$;
   49:	areturn
   50:	new	#34; //class scala/MatchError
   53:	dup
   54:	aload_1
   55:	invokevirtual	#38; //Method java/lang/Object.toString:()Ljava/lang/String;
   58:	invokespecial	#41; //Method scala/MatchError."<init>":(Ljava/lang/String;)V
   61:	athrow
  LineNumberTable: 
   line 21: 0
   line 22: 16
   line 21: 30
   line 23: 46
   line 21: 49

  LocalVariableTable: 
   Start  Length  Slot  Name   Signature
   0      62      0    this       Lscala/xml/Text$;
   0      62      1    other       Ljava/lang/Object;
   12      30      2    temp2       Lscala/xml/Text;

  Signature: length = 0x2
   00 35 

public scala.xml.Text apply(java.lang.String);
  Code:
   Stack=3, Locals=2, Args_size=2
   0:	aload_1
   1:	dup
   2:	pop
   3:	ifnull	14
   6:	aload_1
   7:	aconst_null
   8:	invokevirtual	#60; //Method java/lang/Object.equals:(Ljava/lang/Object;)Z
   11:	ifeq	24
   14:	new	#62; //class java/lang/IllegalArgumentException
   17:	dup
   18:	ldc	#64; //String tried to construct Text with null
   20:	invokespecial	#65; //Method java/lang/IllegalArgumentException."<init>":(Ljava/lang/String;)V
   23:	athrow
   24:	new	#23; //class scala/xml/Text
   27:	dup
   28:	aload_1
   29:	invokespecial	#66; //Method scala/xml/Text."<init>":(Ljava/lang/String;)V
   32:	areturn
  LineNumberTable: 
   line 18: 0
   line 19: 14
   line 18: 24

  LocalVariableTable: 
   Start  Length  Slot  Name   Signature
   0      33      0    this       Lscala/xml/Text$;
   0      33      1    data       Ljava/lang/String;


}

