Compiled from "TextBuffer.scala"
public final class scala.xml.TextBuffer$$anonfun$append$1 extends java.lang.Object implements scala.Function1,scala.ScalaObject,java.io.Serializable
  SourceFile: "TextBuffer.scala"
  Scala: length = 0x
   
  InnerClass: 
   public final $anonfun$append$1=class scala/xml/TextBuffer$$anonfun$append$1 of class scala/xml/TextBuffer
  minor version: 0
  major version: 49
  Constant pool:
Asciz	SourceFile;
Asciz	TextBuffer.scala;
Asciz	<clinit>;
Asciz	()V;
Asciz	Code;
Asciz	serialVersionUID;
Asciz	J;
Asciz	scala/xml/TextBuffer$$anonfun$append$1;
class	scala/xml/TextBuffer$$anonfun$append$1
NameAndType	serialVersionUID:J
Field	scala/xml/TextBuffer$$anonfun$append$1.serialVersionUID:J
Asciz	$outer;
Asciz	Lscala/xml/TextBuffer;;
Asciz	<init>;
Asciz	(Lscala/xml/TextBuffer;)V;
Asciz	LineNumberTable;
Asciz	java/lang/NullPointerException;
class	java/lang/NullPointerException
NameAndType	"<init>":()V
Method	java/lang/NullPointerException."<init>":()V
NameAndType	$outer:Lscala/xml/TextBuffer;
Field	scala/xml/TextBuffer$$anonfun$append$1.$outer:Lscala/xml/TextBuffer;
Asciz	java/lang/Object;
class	java/lang/Object
Method	java/lang/Object."<init>":()V
Asciz	scala/Function1$class;
class	scala/Function1$class
Asciz	$init$;
Asciz	(Lscala/Function1;)V;
NameAndType	$init$:(Lscala/Function1;)V
Method	scala/Function1$class.$init$:(Lscala/Function1;)V
Asciz	this;
Asciz	Lscala/xml/TextBuffer$$anonfun$append$1;;
Asciz	LocalVariableTable;
Asciz	apply;
Asciz	(Ljava/lang/Object;)Ljava/lang/Object;;
Asciz	scala/runtime/BoxesRunTime;
class	scala/runtime/BoxesRunTime
Asciz	unboxToChar;
Asciz	(Ljava/lang/Object;)C;
NameAndType	unboxToChar:(Ljava/lang/Object;)C
Method	scala/runtime/BoxesRunTime.unboxToChar:(Ljava/lang/Object;)C
Asciz	(C)Ljava/lang/Object;;
NameAndType	apply:(C)Ljava/lang/Object;
Method	scala/xml/TextBuffer$$anonfun$append$1.apply:(C)Ljava/lang/Object;
Asciz	v1;
Asciz	Ljava/lang/Object;;
Asciz	scala/xml/Utility$;
class	scala/xml/Utility$
Asciz	MODULE$;
Asciz	Lscala/xml/Utility$;;
NameAndType	MODULE$:Lscala/xml/Utility$;
Field	scala/xml/Utility$.MODULE$:Lscala/xml/Utility$;
Asciz	scala/xml/parsing/TokenTests;
class	scala/xml/parsing/TokenTests
Asciz	isSpace;
Asciz	(C)Z;
NameAndType	isSpace:(C)Z
InterfaceMethod	scala/xml/parsing/TokenTests.isSpace:(C)Z
Asciz	scala/xml/TextBuffer;
class	scala/xml/TextBuffer
Asciz	sb;
Asciz	()Lscala/collection/mutable/StringBuilder;;
NameAndType	sb:()Lscala/collection/mutable/StringBuilder;
Method	scala/xml/TextBuffer.sb:()Lscala/collection/mutable/StringBuilder;
Asciz	scala/collection/IndexedSeqLike$class;
class	scala/collection/IndexedSeqLike$class
Asciz	isEmpty;
Asciz	(Lscala/collection/IndexedSeqLike;)Z;
NameAndType	isEmpty:(Lscala/collection/IndexedSeqLike;)Z
Method	scala/collection/IndexedSeqLike$class.isEmpty:(Lscala/collection/IndexedSeqLike;)Z
Asciz	last;
Asciz	(Lscala/collection/IndexedSeqLike;)Ljava/lang/Object;;
NameAndType	last:(Lscala/collection/IndexedSeqLike;)Ljava/lang/Object;
Method	scala/collection/IndexedSeqLike$class.last:(Lscala/collection/IndexedSeqLike;)Ljava/lang/Object;
Asciz	scala/runtime/BoxedUnit;
class	scala/runtime/BoxedUnit
Asciz	UNIT;
Asciz	Lscala/runtime/BoxedUnit;;
NameAndType	UNIT:Lscala/runtime/BoxedUnit;
Field	scala/runtime/BoxedUnit.UNIT:Lscala/runtime/BoxedUnit;
int	32;
Asciz	scala/collection/mutable/StringBuilder;
class	scala/collection/mutable/StringBuilder
Asciz	append;
Asciz	(C)Lscala/collection/mutable/StringBuilder;;
NameAndType	append:(C)Lscala/collection/mutable/StringBuilder;
Method	scala/collection/mutable/StringBuilder.append:(C)Lscala/collection/mutable/StringBuilder;
Asciz	c;
Asciz	C;
Asciz	andThen;
Asciz	(Lscala/Function1;)Lscala/Function1;;
Asciz	(Lscala/Function1;Lscala/Function1;)Lscala/Function1;;
NameAndType	andThen:(Lscala/Function1;Lscala/Function1;)Lscala/Function1;
Method	scala/Function1$class.andThen:(Lscala/Function1;Lscala/Function1;)Lscala/Function1;
Asciz	g;
Asciz	Lscala/Function1;;
Asciz	compose;
NameAndType	compose:(Lscala/Function1;Lscala/Function1;)Lscala/Function1;
Method	scala/Function1$class.compose:(Lscala/Function1;Lscala/Function1;)Lscala/Function1;
Asciz	toString;
Asciz	()Ljava/lang/String;;
Asciz	(Lscala/Function1;)Ljava/lang/String;;
NameAndType	toString:(Lscala/Function1;)Ljava/lang/String;
Method	scala/Function1$class.toString:(Lscala/Function1;)Ljava/lang/String;
Asciz	Scala;
Asciz	InnerClasses;
Asciz	$anonfun$append$1;
Asciz	scala/Function1;
class	scala/Function1
Asciz	scala/ScalaObject;
class	scala/ScalaObject
Asciz	java/io/Serializable;
class	java/io/Serializable

{
public static final long serialVersionUID;
  Signature: J

private final scala.xml.TextBuffer $outer;
  Signature: Lscala/xml/TextBuffer;

public static {};
  Signature: ()V
  Code:
   Stack=2, Locals=0, Args_size=0
	lconst_0
	putstatic	Field serialVersionUID:J
	return
  Labels:

public scala.xml.TextBuffer$$anonfun$append$1(scala.xml.TextBuffer);
  Signature: (Lscala/xml/TextBuffer;)V
  Code:
   Stack=2, Locals=2, Args_size=2
	aload_1
	ifnonnull	l1 // aload_0
	new	class java/lang/NullPointerException
	dup
	invokespecial	Method java/lang/NullPointerException."<init>":()V
	athrow
l1	aload_0
	aload_1
	putfield	Field $outer:Lscala/xml/TextBuffer;
	aload_0
	invokespecial	Method java/lang/Object."<init>":()V
	aload_0
	invokestatic	Method scala/Function1$class.$init$:(Lscala/Function1;)V
	return
  Labels:
   	l1 = 12 // aload_0
  LocalVariableTable: 
   Start  Length  Slot  Name   Signature
   0      26      0    this       Lscala/xml/TextBuffer$$anonfun$append$1;
   0      26      1    $outer       Lscala/xml/TextBuffer;


public final java.lang.Object apply(java.lang.Object);
  Signature: (Ljava/lang/Object;)Ljava/lang/Object;
  Code:
   Stack=2, Locals=3, Args_size=2
	aload_0
	getfield	Field $outer:Lscala/xml/TextBuffer;
	astore_2
	aload_0
	aload_1
	invokestatic	Method scala/runtime/BoxesRunTime.unboxToChar:(Ljava/lang/Object;)C
	invokevirtual	Method apply:(C)Ljava/lang/Object;
	areturn
  Labels:
  LocalVariableTable: 
   Start  Length  Slot  Name   Signature
   0      14      0    this       Lscala/xml/TextBuffer$$anonfun$append$1;
   5      9      1    v1       Ljava/lang/Object;


public final java.lang.Object apply(char);
  Signature: (C)Ljava/lang/Object;
  Code:
   Stack=2, Locals=5, Args_size=2
	aload_0
	getfield	Field $outer:Lscala/xml/TextBuffer;
	astore	4
	getstatic	Field scala/xml/Utility$.MODULE$:Lscala/xml/Utility$;
	iload_1
	invokeinterface	InterfaceMethod scala/xml/parsing/TokenTests.isSpace:(C)Z
	ifeq	l1 // aload_0
	aload_0
	getfield	Field $outer:Lscala/xml/TextBuffer;
	invokevirtual	Method scala/xml/TextBuffer.sb:()Lscala/collection/mutable/StringBuilder;
	astore_2
	aload_2
	invokestatic	Method scala/collection/IndexedSeqLike$class.isEmpty:(Lscala/collection/IndexedSeqLike;)Z
	ifne	l2 // aload_0
	getstatic	Field scala/xml/Utility$.MODULE$:Lscala/xml/Utility$;
	aload_0
	getfield	Field $outer:Lscala/xml/TextBuffer;
	invokevirtual	Method scala/xml/TextBuffer.sb:()Lscala/collection/mutable/StringBuilder;
	astore_3
	aload_3
	invokestatic	Method scala/collection/IndexedSeqLike$class.last:(Lscala/collection/IndexedSeqLike;)Ljava/lang/Object;
	invokestatic	Method scala/runtime/BoxesRunTime.unboxToChar:(Ljava/lang/Object;)C
	invokeinterface	InterfaceMethod scala/xml/parsing/TokenTests.isSpace:(C)Z
	ifeq	l2 // aload_0
	getstatic	Field scala/runtime/BoxedUnit.UNIT:Lscala/runtime/BoxedUnit;
	goto	l3 // areturn
l2	aload_0
	getfield	Field $outer:Lscala/xml/TextBuffer;
	invokevirtual	Method scala/xml/TextBuffer.sb:()Lscala/collection/mutable/StringBuilder;
	ldc	int 32
	invokevirtual	Method scala/collection/mutable/StringBuilder.append:(C)Lscala/collection/mutable/StringBuilder;
	goto	l3 // areturn
l1	aload_0
	getfield	Field $outer:Lscala/xml/TextBuffer;
	invokevirtual	Method scala/xml/TextBuffer.sb:()Lscala/collection/mutable/StringBuilder;
	iload_1
	invokevirtual	Method scala/collection/mutable/StringBuilder.append:(C)Lscala/collection/mutable/StringBuilder;
l3	areturn
  Labels:
   	l2 = 65 // aload_0
   	l1 = 80 // aload_0
   	l3 = 91 // areturn
  LocalVariableTable: 
   Start  Length  Slot  Name   Signature
   0      92      0    this       Lscala/xml/TextBuffer$$anonfun$append$1;
   6      86      1    c       C


public scala.Function1 andThen(scala.Function1);
  Signature: (Lscala/Function1;)Lscala/Function1;
  Code:
   Stack=2, Locals=2, Args_size=2
	aload_0
	aload_1
	invokestatic	Method scala/Function1$class.andThen:(Lscala/Function1;Lscala/Function1;)Lscala/Function1;
	areturn
  Labels:
  LocalVariableTable: 
   Start  Length  Slot  Name   Signature
   0      6      0    this       Lscala/xml/TextBuffer$$anonfun$append$1;
   0      6      1    g       Lscala/Function1;


public scala.Function1 compose(scala.Function1);
  Signature: (Lscala/Function1;)Lscala/Function1;
  Code:
   Stack=2, Locals=2, Args_size=2
	aload_0
	aload_1
	invokestatic	Method scala/Function1$class.compose:(Lscala/Function1;Lscala/Function1;)Lscala/Function1;
	areturn
  Labels:
  LocalVariableTable: 
   Start  Length  Slot  Name   Signature
   0      6      0    this       Lscala/xml/TextBuffer$$anonfun$append$1;
   0      6      1    g       Lscala/Function1;


public java.lang.String toString();
  Signature: ()Ljava/lang/String;
  Code:
   Stack=1, Locals=1, Args_size=1
	aload_0
	invokestatic	Method scala/Function1$class.toString:(Lscala/Function1;)Ljava/lang/String;
	areturn
  Labels:

}

