Compiled from "Text.scala"
public class scala.xml.Text extends scala.xml.Atom implements scala.ScalaObject,scala.Product,java.io.Serializable
  SourceFile: "Text.scala"
  Signature: length = 0x2
   00 6C 
  ScalaSig: length = 0x364
   05 00 FFFFFF81 05 06 08 01 02 FFFFFF84 FFFFFF80 FFFFFF80 FFFFFF80 40 07 02 04
   54 65 78 74 0A 02 03 04 01 03 78 6D 6C 0A 01 05
   01 05 73 63 61 6C 61 03 00 13 04 00 08 14 17 10
   03 09 0A 0C 0D 01 02 09 02 0B 02 02 04 41 74 6F
   6D 10 02 0D 11 0E 02 0E 0F 0D 01 04 09 02 10 04
   01 06 50 72 65 64 65 66 09 02 12 13 02 06 53 74
   72 69 6E 67 0A 02 10 04 10 02 0E 15 09 02 16 04
   02 0B 53 63 61 6C 61 4F 62 6A 65 63 74 10 02 0E
   18 09 02 19 04 02 07 50 72 6F 64 75 63 74 08 08
   1B 00 FFFFFF82 FFFFFFCA FFFFFF80 FFFFFF84 00 1C 01 05 5F 64 61 74 61 15
   01 0C 08 09 1E 00 FFFFFF82 FFFFFF88 FFFFFFA0 FFFFFF80 04 0C 1F 01 06 5F
   64 61 74 61 20 09 02 20 0A 01 04 64 61 74 61 08
   05 22 00 FFFFFF84 00 23 01 06 3C 69 6E 69 74 3E 14 02
   24 25 10 02 09 00 08 05 1B 21 FFFFFFC0 00 0C 08 05 27
   00 FFFFFF84 22 28 01 06 65 71 75 61 6C 73 14 02 29 2C
   10 02 0E 2A 09 02 2B 04 02 07 42 6F 6F 6C 65 61
   6E 08 05 2D 26 FFFFFFC0 00 2E 01 01 78 10 02 0E 2F 09
   02 30 04 02 03 41 6E 79 08 05 32 00 FFFFFF84 20 33 01
   0B 62 75 69 6C 64 53 74 72 69 6E 67 14 02 34 3C
   10 02 35 3A 0D 01 36 0A 02 37 38 01 07 6D 75 74
   61 62 6C 65 0A 02 39 04 01 0A 63 6F 6C 6C 65 63
   74 69 6F 6E 09 02 3B 36 02 0D 53 74 72 69 6E 67
   42 75 69 6C 64 65 72 08 05 3D 31 FFFFFFC0 00 34 01 02
   73 62 08 07 3F 00 FFFFFF81 FFFFFF80 FFFFFF84 00 40 01 04 63 6F 70
   79 14 02 24 41 08 07 1B 3E FFFFFF90 FFFFFF80 FFFFFFC0 00 0C 08 07
   43 00 FFFFFF91 FFFFFF80 FFFFFF84 00 44 01 0E 63 6F 70 79 24 64 65
   66 61 75 6C 74 24 31 15 01 45 2A 02 0C 46 2B 01
   47 10 02 48 4D 0D 01 49 0A 02 4A 4B 01 09 75 6E
   63 68 65 63 6B 65 64 0A 02 4C 04 01 0A 61 6E 6E
   6F 74 61 74 69 6F 6E 09 02 4E 49 02 11 75 6E 63
   68 65 63 6B 65 64 56 61 72 69 61 6E 63 65 08 08
   50 00 FFFFFF84 FFFFFF80 FFFFFF80 FFFFFF84 20 51 01 0D 70 72 6F 64 75 63
   74 50 72 65 66 69 78 15 01 52 10 02 53 58 0D 01
   54 0A 02 55 56 01 04 6C 61 6E 67 0A 01 57 01 04
   6A 61 76 61 09 02 12 54 08 08 5A 00 FFFFFF84 FFFFFF80 FFFFFF80 FFFFFF84
   20 5B 01 0C 70 72 6F 64 75 63 74 41 72 69 74 79
   15 01 5C 10 02 0E 5D 09 02 5E 04 02 03 49 6E 74
   08 08 60 00 FFFFFF84 FFFFFF80 FFFFFF80 FFFFFF84 20 61 01 0E 70 72 6F 64
   75 63 74 45 6C 65 6D 65 6E 74 14 02 2E 62 08 07
   63 5F FFFFFF81 FFFFFF80 FFFFFFC0 00 5C 01 03 78 24 31 08 08 65 00
   FFFFFF84 FFFFFF80 FFFFFF80 FFFFFF84 20 66 01 12 70 72 6F 64 75 63 74 45
   6C 65 6D 65 6E 74 4E 61 6D 65 14 02 52 67 08 07
   63 64 FFFFFF81 FFFFFF80 FFFFFFC0 00 5C 28 02 00 69 10 02 0E 6A 09
   02 6B 04 02 0C 73 65 72 69 61 6C 69 7A 61 62 6C
   65 07 07 6D 02 FFFFFF81 FFFFFF80 FFFFFF88 02 6E 01 04 54 65 78 74
   10 02 09 6F 06 08 01 02 FFFFFF84 FFFFFF81 FFFFFF80 FFFFFF88 02 70 13 04
   6F 71 74 14 10 02 53 72 09 02 73 54 02 06 4F 62
   6A 65 63 74 10 04 0E 75 0C 24 09 02 76 04 02 09
   46 75 6E 63 74 69 6F 6E 31 08 05 22 6F FFFFFF84 00 78
   14 01 6E 08 07 7A 6F FFFFFF81 FFFFFF80 FFFFFF84 40 7B 01 05 61 70
   70 6C 79 14 02 24 7C 08 05 1B 79 FFFFFFC0 00 0C 08 07
   7E 6F FFFFFF81 FFFFFF80 FFFFFF84 40 7F 01 07 75 6E 61 70 70 6C 79
   14 04 FFFFFF81 00 FFFFFF81 03 10 04 0E FFFFFF81 01 0C 09 03 FFFFFF81 02
   04 02 04 53 6F 6D 65 08 06 FFFFFF81 04 7D FFFFFFC0 00 24 01
   03 78 24 30 
  minor version: 0
  major version: 49
  Constant pool:
Asciz	SourceFile;
Asciz	Text.scala;
Asciz	productIterator;
Asciz	()Lscala/collection/Iterator;;
Asciz	Code;
Asciz	LineNumberTable;
Asciz	scala/Product$class;
class	scala/Product$class
Asciz	(Lscala/Product;)Lscala/collection/Iterator;;
NameAndType	productIterator:(Lscala/Product;)Lscala/collection/Iterator;
Method	scala/Product$class.productIterator:(Lscala/Product;)Lscala/collection/Iterator;
Asciz	productElements;
NameAndType	productElements:(Lscala/Product;)Lscala/collection/Iterator;
Method	scala/Product$class.productElements:(Lscala/Product;)Lscala/collection/Iterator;
Asciz	Deprecated;
Asciz	copy$default$1;
Asciz	()Ljava/lang/String;;
Asciz	scala/xml/Text;
class	scala/xml/Text
Asciz	_data;
NameAndType	_data:()Ljava/lang/String;
Method	scala/xml/Text._data:()Ljava/lang/String;
Asciz	scala/xml/Atom;
class	scala/xml/Atom
Asciz	data;
Asciz	()Ljava/lang/Object;;
NameAndType	data:()Ljava/lang/Object;
Method	scala/xml/Atom.data:()Ljava/lang/Object;
Asciz	java/lang/String;
class	java/lang/String
Asciz	equals;
Asciz	(Ljava/lang/Object;)Z;
Method	scala/xml/Text.data:()Ljava/lang/Object;
Asciz	java/lang/Object;
class	java/lang/Object
NameAndType	equals:(Ljava/lang/Object;)Z
Method	java/lang/Object.equals:(Ljava/lang/Object;)Z
Asciz	java/lang/Number;
class	java/lang/Number
Asciz	java/lang/Character;
class	java/lang/Character
Asciz	scala/runtime/BoxesRunTime;
class	scala/runtime/BoxesRunTime
Asciz	equals2;
Asciz	(Ljava/lang/Object;Ljava/lang/Object;)Z;
NameAndType	equals2:(Ljava/lang/Object;Ljava/lang/Object;)Z
Method	scala/runtime/BoxesRunTime.equals2:(Ljava/lang/Object;Ljava/lang/Object;)Z
Asciz	this;
Asciz	Lscala/xml/Text;;
Asciz	x;
Asciz	Ljava/lang/Object;;
Asciz	x0;
Asciz	y0;
Asciz	LocalVariableTable;
Asciz	buildString;
Asciz	(Lscala/collection/mutable/StringBuilder;)Lscala/collection/mutable/StringBuilder;;
Asciz	scala/xml/Utility$;
class	scala/xml/Utility$
Asciz	MODULE$;
Asciz	Lscala/xml/Utility$;;
NameAndType	MODULE$:Lscala/xml/Utility$;
Field	scala/xml/Utility$.MODULE$:Lscala/xml/Utility$;
Asciz	escape;
Asciz	(Ljava/lang/String;Lscala/collection/mutable/StringBuilder;)Lscala/collection/mutable/StringBuilder;;
NameAndType	escape:(Ljava/lang/String;Lscala/collection/mutable/StringBuilder;)Lscala/collection/mutable/StringBuilder;
Method	scala/xml/Utility$.escape:(Ljava/lang/String;Lscala/collection/mutable/StringBuilder;)Lscala/collection/mutable/StringBuilder;
Asciz	sb;
Asciz	Lscala/collection/mutable/StringBuilder;;
Asciz	copy;
Asciz	(Ljava/lang/String;)Lscala/xml/Text;;
Asciz	<init>;
Asciz	(Ljava/lang/String;)V;
NameAndType	"<init>":(Ljava/lang/String;)V
Method	scala/xml/Text."<init>":(Ljava/lang/String;)V
Asciz	Ljava/lang/String;;
Asciz	productPrefix;
Asciz	Text;
String	Text
Asciz	productArity;
Asciz	()I;
Asciz	productElement;
Asciz	(I)Ljava/lang/Object;;
Asciz	java/lang/IndexOutOfBoundsException;
class	java/lang/IndexOutOfBoundsException
Asciz	boxToInteger;
Asciz	(I)Ljava/lang/Integer;;
NameAndType	boxToInteger:(I)Ljava/lang/Integer;
Method	scala/runtime/BoxesRunTime.boxToInteger:(I)Ljava/lang/Integer;
Asciz	toString;
NameAndType	toString:()Ljava/lang/String;
Method	java/lang/Object.toString:()Ljava/lang/String;
Method	java/lang/IndexOutOfBoundsException."<init>":(Ljava/lang/String;)V
Asciz	productElementName;
Asciz	(I)Ljava/lang/String;;
String	_data
Asciz	(Ljava/lang/Object;)V;
NameAndType	"<init>":(Ljava/lang/Object;)V
Method	scala/xml/Atom."<init>":(Ljava/lang/Object;)V
Asciz	$init$;
Asciz	(Lscala/Product;)V;
NameAndType	$init$:(Lscala/Product;)V
Method	scala/Product$class.$init$:(Lscala/Product;)V
Asciz	java/lang/IllegalArgumentException;
class	java/lang/IllegalArgumentException
Asciz	tried to construct Text with null;
String	tried to construct Text with null
Method	java/lang/IllegalArgumentException."<init>":(Ljava/lang/String;)V
Asciz	Lscala/xml/Atom<Ljava/lang/String;>;Lscala/ScalaObject;Lscala/Product;;
Asciz	Signature;
Asciz	ScalaSig;
Asciz	scala/ScalaObject;
class	scala/ScalaObject
Asciz	scala/Product;
class	scala/Product
Asciz	java/io/Serializable;
class	java/io/Serializable

{
public scala.collection.Iterator productIterator();
  Signature: ()Lscala/collection/Iterator;
  Code:
   Stack=1, Locals=1, Args_size=1
	aload_0
	invokestatic	Method scala/Product$class.productIterator:(Lscala/Product;)Lscala/collection/Iterator;
	areturn
  Labels:

public scala.collection.Iterator productElements();
  Signature: ()Lscala/collection/Iterator;
  Code:
   Stack=1, Locals=1, Args_size=1
	aload_0
	invokestatic	Method scala/Product$class.productElements:(Lscala/Product;)Lscala/collection/Iterator;
	areturn
  Labels:
  Deprecated: true

public java.lang.String copy$default$1();
  Signature: ()Ljava/lang/String;
  Code:
   Stack=1, Locals=1, Args_size=1
	aload_0
	invokevirtual	Method _data:()Ljava/lang/String;
	areturn
  Labels:

public java.lang.String _data();
  Signature: ()Ljava/lang/String;
  Code:
   Stack=1, Locals=1, Args_size=1
	aload_0
	invokespecial	Method scala/xml/Atom.data:()Ljava/lang/Object;
	checkcast	class java/lang/String
	areturn
  Labels:

public final boolean equals(java.lang.Object);
  Signature: (Ljava/lang/Object;)Z
  Code:
   Stack=2, Locals=5, Args_size=2
	aload_1
	instanceof	class java/lang/String
	ifeq	l1 // aload_1
	aload_1
	checkcast	class java/lang/String
	aload_0
	invokevirtual	Method data:()Ljava/lang/Object;
	astore_2
	dup
	ifnonnull	l2 // aload_2
	pop
	aload_2
	ifnull	l3 // iconst_1
	goto	l4 // iconst_0
l2	aload_2
	invokevirtual	Method java/lang/Object.equals:(Ljava/lang/Object;)Z
	ifeq	l4 // iconst_0
l3	iconst_1
	goto	l5 // ireturn
l4	iconst_0
	goto	l5 // ireturn
l1	aload_1
	instanceof	class scala/xml/Atom
	ifeq	l6 // iconst_0
	aload_0
	invokevirtual	Method data:()Ljava/lang/Object;
	aload_1
	checkcast	class scala/xml/Atom
	invokevirtual	Method scala/xml/Atom.data:()Ljava/lang/Object;
	astore	4
	astore_3
	aload_3
	aload	4
	if_acmpne	l7 // aload_3
	iconst_1
	goto	l8 // ifeq
l7	aload_3
	ifnonnull	l9 // aload_3
	iconst_0
	goto	l8 // ifeq
l9	aload_3
	instanceof	class java/lang/Number
	ifne	l10 // aload_3
	aload_3
	instanceof	class java/lang/Character
	ifeq	l11 // aload_3
l10	aload_3
	aload	4
	invokestatic	Method scala/runtime/BoxesRunTime.equals2:(Ljava/lang/Object;Ljava/lang/Object;)Z
	goto	l8 // ifeq
l11	aload_3
	aload	4
	invokevirtual	Method java/lang/Object.equals:(Ljava/lang/Object;)Z
l8	ifeq	l12 // iconst_0
	iconst_1
	goto	l5 // ireturn
l12	iconst_0
	goto	l5 // ireturn
l6	iconst_0
l5	ireturn
  Labels:
   	l2 = 28 // aload_2
   	l3 = 35 // iconst_1
   	l4 = 39 // iconst_0
   	l1 = 43 // aload_1
   	l7 = 74 // aload_3
   	l9 = 82 // aload_3
   	l10 = 96 // aload_3
   	l11 = 105 // aload_3
   	l8 = 111 // ifeq
   	l12 = 118 // iconst_0
   	l6 = 122 // iconst_0
   	l5 = 123 // ireturn
  LocalVariableTable: 
   Start  Length  Slot  Name   Signature
   0      124      0    this       Lscala/xml/Text;
   0      124      1    x       Ljava/lang/Object;
   70      44      3    x0       Ljava/lang/Object;
   70      44      4    y0       Ljava/lang/Object;


public scala.collection.mutable.StringBuilder buildString(scala.collection.mutable.StringBuilder);
  Signature: (Lscala/collection/mutable/StringBuilder;)Lscala/collection/mutable/StringBuilder;
  Code:
   Stack=3, Locals=2, Args_size=2
	getstatic	Field scala/xml/Utility$.MODULE$:Lscala/xml/Utility$;
	aload_0
	invokevirtual	Method data:()Ljava/lang/Object;
	checkcast	class java/lang/String
	aload_1
	invokevirtual	Method scala/xml/Utility$.escape:(Ljava/lang/String;Lscala/collection/mutable/StringBuilder;)Lscala/collection/mutable/StringBuilder;
	areturn
  Labels:
  LocalVariableTable: 
   Start  Length  Slot  Name   Signature
   0      15      0    this       Lscala/xml/Text;
   0      15      1    sb       Lscala/collection/mutable/StringBuilder;


public scala.xml.Text copy(java.lang.String);
  Signature: (Ljava/lang/String;)Lscala/xml/Text;
  Code:
   Stack=3, Locals=2, Args_size=2
	new	class scala/xml/Text
	dup
	aload_1
	invokespecial	Method "<init>":(Ljava/lang/String;)V
	areturn
  Labels:
  LocalVariableTable: 
   Start  Length  Slot  Name   Signature
   0      9      0    this       Lscala/xml/Text;
   0      9      1    _data       Ljava/lang/String;


public java.lang.String productPrefix();
  Signature: ()Ljava/lang/String;
  Code:
   Stack=1, Locals=1, Args_size=1
	ldc	String Text
	areturn
  Labels:

public int productArity();
  Signature: ()I
  Code:
   Stack=1, Locals=1, Args_size=1
	iconst_1
	ireturn
  Labels:

public java.lang.Object productElement(int);
  Signature: (I)Ljava/lang/Object;
  Code:
   Stack=3, Locals=2, Args_size=2
	iload_1
	iconst_0
	if_icmpne	l1 // new
	aload_0
	invokevirtual	Method _data:()Ljava/lang/String;
	areturn
l1	new	class java/lang/IndexOutOfBoundsException
	dup
	iload_1
	invokestatic	Method scala/runtime/BoxesRunTime.boxToInteger:(I)Ljava/lang/Integer;
	invokevirtual	Method java/lang/Object.toString:()Ljava/lang/String;
	invokespecial	Method java/lang/IndexOutOfBoundsException."<init>":(Ljava/lang/String;)V
	athrow
  Labels:
   	l1 = 10 // new

public java.lang.String productElementName(int);
  Signature: (I)Ljava/lang/String;
  Code:
   Stack=3, Locals=2, Args_size=2
	iload_1
	iconst_0
	if_icmpne	l1 // new
	ldc	String _data
	areturn
l1	new	class java/lang/IndexOutOfBoundsException
	dup
	iload_1
	invokestatic	Method scala/runtime/BoxesRunTime.boxToInteger:(I)Ljava/lang/Integer;
	invokevirtual	Method java/lang/Object.toString:()Ljava/lang/String;
	invokespecial	Method java/lang/IndexOutOfBoundsException."<init>":(Ljava/lang/String;)V
	athrow
  Labels:
   	l1 = 8 // new

public scala.xml.Text(java.lang.String);
  Signature: (Ljava/lang/String;)V
  Code:
   Stack=3, Locals=2, Args_size=2
	aload_0
	aload_1
	invokespecial	Method scala/xml/Atom."<init>":(Ljava/lang/Object;)V
	aload_0
	invokestatic	Method scala/Product$class.$init$:(Lscala/Product;)V
	aload_1
	dup
	pop
	ifnull	l1 // new
	aload_1
	aconst_null
	invokevirtual	Method java/lang/Object.equals:(Ljava/lang/Object;)Z
	ifeq	l2 // return
l1	new	class java/lang/IllegalArgumentException
	dup
	ldc	String tried to construct Text with null
	invokespecial	Method java/lang/IllegalArgumentException."<init>":(Ljava/lang/String;)V
	athrow
l2	return
  Labels:
   	l1 = 23 // new
   	l2 = 33 // return
  LocalVariableTable: 
   Start  Length  Slot  Name   Signature
   0      34      0    this       Lscala/xml/Text;
   0      34      1    _data       Ljava/lang/String;


}

