Compiled from "TextBuffer.scala"
public class scala.xml.TextBuffer extends java.lang.Object implements scala.ScalaObject
  SourceFile: "TextBuffer.scala"
  ScalaSig: length = 0x1BA
   05 00 4D 07 05 01 02 FFFFFF88 02 07 01 0A 54 65 78 74
   42 75 66 66 65 72 0A 02 03 04 01 03 78 6D 6C 0A
   01 05 01 05 73 63 61 6C 61 03 00 10 02 08 09 0D
   01 02 06 08 0A 02 FFFFFF84 FFFFFF80 FFFFFF80 FFFFFF88 02 0B 02 0A 54 65
   78 74 42 75 66 66 65 72 13 03 09 0C 14 10 02 0D
   12 0D 01 0E 0A 02 0F 10 01 04 6C 61 6E 67 0A 01
   11 01 04 6A 61 76 61 09 02 13 0E 02 06 4F 62 6A
   65 63 74 10 02 15 16 0D 01 04 09 02 17 04 02 0B
   53 63 61 6C 61 4F 62 6A 65 63 74 08 05 19 09 FFFFFF84
   00 1A 01 06 3C 69 6E 69 74 3E 14 01 07 08 05 1C
   09 FFFFFF84 00 1D 01 0A 66 72 6F 6D 53 74 72 69 6E 67
   14 02 1E 44 10 02 08 1F 06 08 0A 02 FFFFFF84 FFFFFF80 FFFFFF80 FFFFFF80
   00 20 13 03 1F 0C 14 08 05 19 1F FFFFFF84 00 22 14 01
   1E 08 07 24 1F FFFFFFC2 FFFFFF80 FFFFFF84 00 25 01 02 73 62 15 01
   26 10 02 27 2C 0D 01 28 0A 02 29 2A 01 07 6D 75
   74 61 62 6C 65 0A 02 2B 04 01 0A 63 6F 6C 6C 65
   63 74 69 6F 6E 09 02 2D 28 02 0D 53 74 72 69 6E
   67 42 75 69 6C 64 65 72 08 06 2F 1F FFFFFFA0 FFFFFF80 04 26
   01 03 73 62 20 08 05 31 1F FFFFFF84 00 32 01 06 61 70
   70 65 6E 64 14 02 33 34 0D 01 1F 08 05 35 30 FFFFFFC0
   00 36 01 02 63 73 10 03 37 38 3A 0D 01 2A 09 02
   39 2A 02 03 53 65 71 10 02 15 3B 09 02 3C 04 02
   04 43 68 61 72 08 05 3E 1F FFFFFF84 00 3F 01 06 74 6F
   54 65 78 74 15 01 40 10 03 37 38 41 10 02 08 42
   09 02 43 02 02 04 54 65 78 74 08 05 45 1B FFFFFFC0 00
   46 01 03 73 74 72 10 02 47 4A 0E 02 15 48 09 02
   49 04 01 06 50 72 65 64 65 66 09 02 4B 4C 02 06
   53 74 72 69 6E 67 0A 02 49 04 
  InnerClass: 
   public final $anonfun$append$1=class scala/xml/TextBuffer$$anonfun$append$1 of class scala/xml/TextBuffer
  minor version: 0
  major version: 49
  Constant pool:
Asciz	SourceFile;
Asciz	TextBuffer.scala;
Asciz	fromString;
Asciz	(Ljava/lang/String;)Lscala/xml/TextBuffer;;
Asciz	Code;
Asciz	scala/xml/TextBuffer$;
class	scala/xml/TextBuffer$
Asciz	MODULE$;
Asciz	Lscala/xml/TextBuffer$;;
NameAndType	MODULE$:Lscala/xml/TextBuffer$;
Field	scala/xml/TextBuffer$.MODULE$:Lscala/xml/TextBuffer$;
NameAndType	fromString:(Ljava/lang/String;)Lscala/xml/TextBuffer;
Method	scala/xml/TextBuffer$.fromString:(Ljava/lang/String;)Lscala/xml/TextBuffer;
Asciz	sb;
Asciz	Lscala/collection/mutable/StringBuilder;;
Asciz	<init>;
Asciz	()V;
Asciz	LineNumberTable;
Asciz	java/lang/Object;
class	java/lang/Object
NameAndType	"<init>":()V
Method	java/lang/Object."<init>":()V
Asciz	scala/collection/mutable/StringBuilder;
class	scala/collection/mutable/StringBuilder
Method	scala/collection/mutable/StringBuilder."<init>":()V
Asciz	scala/xml/TextBuffer;
class	scala/xml/TextBuffer
NameAndType	sb:Lscala/collection/mutable/StringBuilder;
Field	scala/xml/TextBuffer.sb:Lscala/collection/mutable/StringBuilder;
Asciz	toText;
Asciz	()Lscala/collection/Seq;;
Asciz	()Lscala/collection/mutable/StringBuilder;;
NameAndType	sb:()Lscala/collection/mutable/StringBuilder;
Method	scala/xml/TextBuffer.sb:()Lscala/collection/mutable/StringBuilder;
Asciz	toString;
Asciz	()Ljava/lang/String;;
NameAndType	toString:()Ljava/lang/String;
Method	scala/collection/mutable/StringBuilder.toString:()Ljava/lang/String;
Asciz	java/lang/String;
class	java/lang/String
Asciz	trim;
NameAndType	trim:()Ljava/lang/String;
Method	java/lang/String.trim:()Ljava/lang/String;
Asciz	;
String	
Asciz	equals;
Asciz	(Ljava/lang/Object;)Z;
NameAndType	equals:(Ljava/lang/Object;)Z
Method	java/lang/Object.equals:(Ljava/lang/Object;)Z
Asciz	scala/collection/immutable/Nil$;
class	scala/collection/immutable/Nil$
Asciz	Lscala/collection/immutable/Nil$;;
NameAndType	MODULE$:Lscala/collection/immutable/Nil$;
Field	scala/collection/immutable/Nil$.MODULE$:Lscala/collection/immutable/Nil$;
Asciz	scala/MatchError;
class	scala/MatchError
Method	java/lang/String.toString:()Ljava/lang/String;
Asciz	(Ljava/lang/String;)V;
NameAndType	"<init>":(Ljava/lang/String;)V
Method	scala/MatchError."<init>":(Ljava/lang/String;)V
Asciz	scala/collection/Seq$;
class	scala/collection/Seq$
Asciz	Lscala/collection/Seq$;;
NameAndType	MODULE$:Lscala/collection/Seq$;
Field	scala/collection/Seq$.MODULE$:Lscala/collection/Seq$;
Asciz	scala/Predef$;
class	scala/Predef$
Asciz	Lscala/Predef$;;
NameAndType	MODULE$:Lscala/Predef$;
Field	scala/Predef$.MODULE$:Lscala/Predef$;
Asciz	scala/xml/Text;
class	scala/xml/Text
Asciz	scala/xml/Text$;
class	scala/xml/Text$
Asciz	Lscala/xml/Text$;;
NameAndType	MODULE$:Lscala/xml/Text$;
Field	scala/xml/Text$.MODULE$:Lscala/xml/Text$;
Asciz	apply;
Asciz	(Ljava/lang/String;)Lscala/xml/Text;;
NameAndType	apply:(Ljava/lang/String;)Lscala/xml/Text;
Method	scala/xml/Text$.apply:(Ljava/lang/String;)Lscala/xml/Text;
Asciz	[Ljava/lang/Object;;
class	"[Ljava/lang/Object;"
Asciz	wrapRefArray;
Asciz	([Ljava/lang/Object;)Lscala/collection/mutable/WrappedArray;;
NameAndType	wrapRefArray:([Ljava/lang/Object;)Lscala/collection/mutable/WrappedArray;
Method	scala/Predef$.wrapRefArray:([Ljava/lang/Object;)Lscala/collection/mutable/WrappedArray;
Asciz	(Lscala/collection/Seq;)Lscala/collection/Traversable;;
NameAndType	apply:(Lscala/collection/Seq;)Lscala/collection/Traversable;
Method	scala/collection/Seq$.apply:(Lscala/collection/Seq;)Lscala/collection/Traversable;
Asciz	scala/collection/Seq;
class	scala/collection/Seq
Asciz	this;
Asciz	Lscala/xml/TextBuffer;;
Asciz	temp1;
Asciz	Ljava/lang/String;;
Asciz	LocalVariableTable;
Asciz	()Lscala/collection/Seq<Lscala/xml/Text;>;;
Asciz	Signature;
Asciz	append;
Asciz	(Lscala/collection/Seq;)Lscala/xml/TextBuffer;;
Asciz	scala/xml/TextBuffer$$anonfun$append$1;
class	scala/xml/TextBuffer$$anonfun$append$1
Asciz	(Lscala/xml/TextBuffer;)V;
NameAndType	"<init>":(Lscala/xml/TextBuffer;)V
Method	scala/xml/TextBuffer$$anonfun$append$1."<init>":(Lscala/xml/TextBuffer;)V
Asciz	scala/collection/IterableLike;
class	scala/collection/IterableLike
Asciz	foreach;
Asciz	(Lscala/Function1;)V;
NameAndType	foreach:(Lscala/Function1;)V
InterfaceMethod	scala/collection/IterableLike.foreach:(Lscala/Function1;)V
Asciz	cs;
Asciz	Lscala/collection/Seq;;
Asciz	(Lscala/collection/Seq<Ljava/lang/Character;>;)Lscala/xml/TextBuffer;;
Asciz	ScalaSig;
Asciz	InnerClasses;
Asciz	$anonfun$append$1;
Asciz	scala/ScalaObject;
class	scala/ScalaObject

{
private final scala.collection.mutable.StringBuilder sb;
  Signature: Lscala/collection/mutable/StringBuilder;

public static final scala.xml.TextBuffer fromString(java.lang.String);
  Signature: (Ljava/lang/String;)Lscala/xml/TextBuffer;
  Code:
   Stack=2, Locals=1, Args_size=1
	getstatic	Field scala/xml/TextBuffer$.MODULE$:Lscala/xml/TextBuffer$;
	aload_0
	invokevirtual	Method scala/xml/TextBuffer$.fromString:(Ljava/lang/String;)Lscala/xml/TextBuffer;
	areturn
  Labels:

public scala.xml.TextBuffer();
  Signature: ()V
  Code:
   Stack=3, Locals=1, Args_size=1
	aload_0
	invokespecial	Method java/lang/Object."<init>":()V
	aload_0
	new	class scala/collection/mutable/StringBuilder
	dup
	invokespecial	Method scala/collection/mutable/StringBuilder."<init>":()V
	putfield	Field sb:Lscala/collection/mutable/StringBuilder;
	return
  Labels:

public scala.collection.Seq toText();
  Signature: ()Lscala/collection/Seq;
  Code:
   Stack=7, Locals=3, Args_size=1
	aload_0
	invokevirtual	Method sb:()Lscala/collection/mutable/StringBuilder;
	invokevirtual	Method scala/collection/mutable/StringBuilder.toString:()Ljava/lang/String;
	invokevirtual	Method java/lang/String.trim:()Ljava/lang/String;
	astore_2
	aload_2
	ldc	String 
	astore_1
	dup
	ifnonnull	l1 // aload_1
	pop
	aload_1
	ifnull	l2 // iconst_1
	goto	l3 // iconst_1
l1	aload_1
	invokevirtual	Method java/lang/Object.equals:(Ljava/lang/Object;)Z
	ifeq	l3 // iconst_1
l2	iconst_1
	ifeq	l4 // new
	getstatic	Field scala/collection/immutable/Nil$.MODULE$:Lscala/collection/immutable/Nil$;
	goto	l5 // areturn
l4	new	class scala/MatchError
	dup
	aload_2
	invokevirtual	Method java/lang/String.toString:()Ljava/lang/String;
	invokespecial	Method scala/MatchError."<init>":(Ljava/lang/String;)V
	athrow
l3	iconst_1
	ifeq	l6 // new
	getstatic	Field scala/collection/Seq$.MODULE$:Lscala/collection/Seq$;
	getstatic	Field scala/Predef$.MODULE$:Lscala/Predef$;
	iconst_1
	anewarray	class scala/xml/Text
	dup
	iconst_0
	getstatic	Field scala/xml/Text$.MODULE$:Lscala/xml/Text$;
	aload_2
	invokevirtual	Method scala/xml/Text$.apply:(Ljava/lang/String;)Lscala/xml/Text;
	aastore
	checkcast	class "[Ljava/lang/Object;"
	invokevirtual	Method scala/Predef$.wrapRefArray:([Ljava/lang/Object;)Lscala/collection/mutable/WrappedArray;
	invokevirtual	Method scala/collection/Seq$.apply:(Lscala/collection/Seq;)Lscala/collection/Traversable;
	checkcast	class scala/collection/Seq
l5	areturn
l6	new	class scala/MatchError
	dup
	aload_2
	invokevirtual	Method java/lang/String.toString:()Ljava/lang/String;
	invokespecial	Method scala/MatchError."<init>":(Ljava/lang/String;)V
	athrow
  Labels:
   	l1 = 27 // aload_1
   	l2 = 34 // iconst_1
   	l4 = 44 // new
   	l3 = 56 // iconst_1
   	l5 = 92 // areturn
   	l6 = 93 // new
  LocalVariableTable: 
   Start  Length  Slot  Name   Signature
   0      105      0    this       Lscala/xml/TextBuffer;
   11      94      2    temp1       Ljava/lang/String;

  Signature: length = 0x2
   00 62 

public scala.xml.TextBuffer append(scala.collection.Seq);
  Signature: (Lscala/collection/Seq;)Lscala/xml/TextBuffer;
  Code:
   Stack=4, Locals=2, Args_size=2
	aload_1
	new	class scala/xml/TextBuffer$$anonfun$append$1
	dup
	aload_0
	invokespecial	Method scala/xml/TextBuffer$$anonfun$append$1."<init>":(Lscala/xml/TextBuffer;)V
	invokeinterface	InterfaceMethod scala/collection/IterableLike.foreach:(Lscala/Function1;)V
	aload_0
	areturn
  Labels:
  LocalVariableTable: 
   Start  Length  Slot  Name   Signature
   0      16      0    this       Lscala/xml/TextBuffer;
   0      16      1    cs       Lscala/collection/Seq;

  Signature: length = 0x2
   00 73 

public scala.collection.mutable.StringBuilder sb();
  Signature: ()Lscala/collection/mutable/StringBuilder;
  Code:
   Stack=1, Locals=1, Args_size=1
	aload_0
	getfield	Field sb:Lscala/collection/mutable/StringBuilder;
	areturn
  Labels:

}

