Compiled from "TextBuffer.scala"
public final class scala.xml.TextBuffer$$anonfun$append$1 extends java.lang.Object implements scala.Function1,scala.ScalaObject,java.io.Serializable
  SourceFile: "TextBuffer.scala"
  Scala: length = 0x
   
  InnerClass: 
   public final #108= #9 of #61; //$anonfun$append$1=class scala/xml/TextBuffer$$anonfun$append$1 of class scala/xml/TextBuffer
  minor version: 0
  major version: 49
  Constant pool:
const #1 = Asciz	SourceFile;
const #2 = Asciz	TextBuffer.scala;
const #3 = Asciz	<clinit>;
const #4 = Asciz	()V;
const #5 = Asciz	Code;
const #6 = Asciz	serialVersionUID;
const #7 = Asciz	J;
const #8 = Asciz	scala/xml/TextBuffer$$anonfun$append$1;
const #9 = class	#8;	//  scala/xml/TextBuffer$$anonfun$append$1
const #10 = NameAndType	#6:#7;//  serialVersionUID:J
const #11 = Field	#9.#10;	//  scala/xml/TextBuffer$$anonfun$append$1.serialVersionUID:J
const #12 = Asciz	$outer;
const #13 = Asciz	Lscala/xml/TextBuffer;;
const #14 = Asciz	<init>;
const #15 = Asciz	(Lscala/xml/TextBuffer;)V;
const #16 = Asciz	LineNumberTable;
const #17 = Asciz	java/lang/NullPointerException;
const #18 = class	#17;	//  java/lang/NullPointerException
const #19 = NameAndType	#14:#4;//  "<init>":()V
const #20 = Method	#18.#19;	//  java/lang/NullPointerException."<init>":()V
const #21 = NameAndType	#12:#13;//  $outer:Lscala/xml/TextBuffer;
const #22 = Field	#9.#21;	//  scala/xml/TextBuffer$$anonfun$append$1.$outer:Lscala/xml/TextBuffer;
const #23 = Asciz	java/lang/Object;
const #24 = class	#23;	//  java/lang/Object
const #25 = Method	#24.#19;	//  java/lang/Object."<init>":()V
const #26 = Asciz	scala/Function1$class;
const #27 = class	#26;	//  scala/Function1$class
const #28 = Asciz	$init$;
const #29 = Asciz	(Lscala/Function1;)V;
const #30 = NameAndType	#28:#29;//  $init$:(Lscala/Function1;)V
const #31 = Method	#27.#30;	//  scala/Function1$class.$init$:(Lscala/Function1;)V
const #32 = Asciz	this;
const #33 = Asciz	Lscala/xml/TextBuffer$$anonfun$append$1;;
const #34 = Asciz	LocalVariableTable;
const #35 = Asciz	apply;
const #36 = Asciz	(Ljava/lang/Object;)Ljava/lang/Object;;
const #37 = Asciz	scala/runtime/BoxesRunTime;
const #38 = class	#37;	//  scala/runtime/BoxesRunTime
const #39 = Asciz	unboxToChar;
const #40 = Asciz	(Ljava/lang/Object;)C;
const #41 = NameAndType	#39:#40;//  unboxToChar:(Ljava/lang/Object;)C
const #42 = Method	#38.#41;	//  scala/runtime/BoxesRunTime.unboxToChar:(Ljava/lang/Object;)C
const #43 = Asciz	(C)Ljava/lang/Object;;
const #44 = NameAndType	#35:#43;//  apply:(C)Ljava/lang/Object;
const #45 = Method	#9.#44;	//  scala/xml/TextBuffer$$anonfun$append$1.apply:(C)Ljava/lang/Object;
const #46 = Asciz	v1;
const #47 = Asciz	Ljava/lang/Object;;
const #48 = Asciz	scala/xml/Utility$;
const #49 = class	#48;	//  scala/xml/Utility$
const #50 = Asciz	MODULE$;
const #51 = Asciz	Lscala/xml/Utility$;;
const #52 = NameAndType	#50:#51;//  MODULE$:Lscala/xml/Utility$;
const #53 = Field	#49.#52;	//  scala/xml/Utility$.MODULE$:Lscala/xml/Utility$;
const #54 = Asciz	scala/xml/parsing/TokenTests;
const #55 = class	#54;	//  scala/xml/parsing/TokenTests
const #56 = Asciz	isSpace;
const #57 = Asciz	(C)Z;
const #58 = NameAndType	#56:#57;//  isSpace:(C)Z
const #59 = InterfaceMethod	#55.#58;	//  scala/xml/parsing/TokenTests.isSpace:(C)Z
const #60 = Asciz	scala/xml/TextBuffer;
const #61 = class	#60;	//  scala/xml/TextBuffer
const #62 = Asciz	sb;
const #63 = Asciz	()Lscala/collection/mutable/StringBuilder;;
const #64 = NameAndType	#62:#63;//  sb:()Lscala/collection/mutable/StringBuilder;
const #65 = Method	#61.#64;	//  scala/xml/TextBuffer.sb:()Lscala/collection/mutable/StringBuilder;
const #66 = Asciz	scala/collection/IndexedSeqLike$class;
const #67 = class	#66;	//  scala/collection/IndexedSeqLike$class
const #68 = Asciz	isEmpty;
const #69 = Asciz	(Lscala/collection/IndexedSeqLike;)Z;
const #70 = NameAndType	#68:#69;//  isEmpty:(Lscala/collection/IndexedSeqLike;)Z
const #71 = Method	#67.#70;	//  scala/collection/IndexedSeqLike$class.isEmpty:(Lscala/collection/IndexedSeqLike;)Z
const #72 = Asciz	last;
const #73 = Asciz	(Lscala/collection/IndexedSeqLike;)Ljava/lang/Object;;
const #74 = NameAndType	#72:#73;//  last:(Lscala/collection/IndexedSeqLike;)Ljava/lang/Object;
const #75 = Method	#67.#74;	//  scala/collection/IndexedSeqLike$class.last:(Lscala/collection/IndexedSeqLike;)Ljava/lang/Object;
const #76 = Asciz	scala/runtime/BoxedUnit;
const #77 = class	#76;	//  scala/runtime/BoxedUnit
const #78 = Asciz	UNIT;
const #79 = Asciz	Lscala/runtime/BoxedUnit;;
const #80 = NameAndType	#78:#79;//  UNIT:Lscala/runtime/BoxedUnit;
const #81 = Field	#77.#80;	//  scala/runtime/BoxedUnit.UNIT:Lscala/runtime/BoxedUnit;
const #82 = int	32;
const #83 = Asciz	scala/collection/mutable/StringBuilder;
const #84 = class	#83;	//  scala/collection/mutable/StringBuilder
const #85 = Asciz	append;
const #86 = Asciz	(C)Lscala/collection/mutable/StringBuilder;;
const #87 = NameAndType	#85:#86;//  append:(C)Lscala/collection/mutable/StringBuilder;
const #88 = Method	#84.#87;	//  scala/collection/mutable/StringBuilder.append:(C)Lscala/collection/mutable/StringBuilder;
const #89 = Asciz	c;
const #90 = Asciz	C;
const #91 = Asciz	andThen;
const #92 = Asciz	(Lscala/Function1;)Lscala/Function1;;
const #93 = Asciz	(Lscala/Function1;Lscala/Function1;)Lscala/Function1;;
const #94 = NameAndType	#91:#93;//  andThen:(Lscala/Function1;Lscala/Function1;)Lscala/Function1;
const #95 = Method	#27.#94;	//  scala/Function1$class.andThen:(Lscala/Function1;Lscala/Function1;)Lscala/Function1;
const #96 = Asciz	g;
const #97 = Asciz	Lscala/Function1;;
const #98 = Asciz	compose;
const #99 = NameAndType	#98:#93;//  compose:(Lscala/Function1;Lscala/Function1;)Lscala/Function1;
const #100 = Method	#27.#99;	//  scala/Function1$class.compose:(Lscala/Function1;Lscala/Function1;)Lscala/Function1;
const #101 = Asciz	toString;
const #102 = Asciz	()Ljava/lang/String;;
const #103 = Asciz	(Lscala/Function1;)Ljava/lang/String;;
const #104 = NameAndType	#101:#103;//  toString:(Lscala/Function1;)Ljava/lang/String;
const #105 = Method	#27.#104;	//  scala/Function1$class.toString:(Lscala/Function1;)Ljava/lang/String;
const #106 = Asciz	Scala;
const #107 = Asciz	InnerClasses;
const #108 = Asciz	$anonfun$append$1;
const #109 = Asciz	scala/Function1;
const #110 = class	#109;	//  scala/Function1
const #111 = Asciz	scala/ScalaObject;
const #112 = class	#111;	//  scala/ScalaObject
const #113 = Asciz	java/io/Serializable;
const #114 = class	#113;	//  java/io/Serializable

{
public static final long serialVersionUID;

public static {};
  Code:
   Stack=2, Locals=0, Args_size=0
   0:	lconst_0
   1:	putstatic	#11; //Field serialVersionUID:J
   4:	return

public scala.xml.TextBuffer$$anonfun$append$1(scala.xml.TextBuffer);
  Code:
   Stack=2, Locals=2, Args_size=2
   0:	aload_1
   1:	ifnonnull	12
   4:	new	#18; //class java/lang/NullPointerException
   7:	dup
   8:	invokespecial	#20; //Method java/lang/NullPointerException."<init>":()V
   11:	athrow
   12:	aload_0
   13:	aload_1
   14:	putfield	#22; //Field $outer:Lscala/xml/TextBuffer;
   17:	aload_0
   18:	invokespecial	#25; //Method java/lang/Object."<init>":()V
   21:	aload_0
   22:	invokestatic	#31; //Method scala/Function1$class.$init$:(Lscala/Function1;)V
   25:	return
  LineNumberTable: 
   line 38: 0

  LocalVariableTable: 
   Start  Length  Slot  Name   Signature
   0      26      0    this       Lscala/xml/TextBuffer$$anonfun$append$1;
   0      26      1    $outer       Lscala/xml/TextBuffer;


public final java.lang.Object apply(java.lang.Object);
  Code:
   Stack=2, Locals=3, Args_size=2
   0:	aload_0
   1:	getfield	#22; //Field $outer:Lscala/xml/TextBuffer;
   4:	astore_2
   5:	aload_0
   6:	aload_1
   7:	invokestatic	#42; //Method scala/runtime/BoxesRunTime.unboxToChar:(Ljava/lang/Object;)C
   10:	invokevirtual	#45; //Method apply:(C)Ljava/lang/Object;
   13:	areturn
  LineNumberTable: 
   line 38: 0

  LocalVariableTable: 
   Start  Length  Slot  Name   Signature
   0      14      0    this       Lscala/xml/TextBuffer$$anonfun$append$1;
   5      9      1    v1       Ljava/lang/Object;


public final java.lang.Object apply(char);
  Code:
   Stack=2, Locals=5, Args_size=2
   0:	aload_0
   1:	getfield	#22; //Field $outer:Lscala/xml/TextBuffer;
   4:	astore	4
   6:	getstatic	#53; //Field scala/xml/Utility$.MODULE$:Lscala/xml/Utility$;
   9:	iload_1
   10:	invokeinterface	#59,  2; //InterfaceMethod scala/xml/parsing/TokenTests.isSpace:(C)Z
   15:	ifeq	80
   18:	aload_0
   19:	getfield	#22; //Field $outer:Lscala/xml/TextBuffer;
   22:	invokevirtual	#65; //Method scala/xml/TextBuffer.sb:()Lscala/collection/mutable/StringBuilder;
   25:	astore_2
   26:	aload_2
   27:	invokestatic	#71; //Method scala/collection/IndexedSeqLike$class.isEmpty:(Lscala/collection/IndexedSeqLike;)Z
   30:	ifne	65
   33:	getstatic	#53; //Field scala/xml/Utility$.MODULE$:Lscala/xml/Utility$;
   36:	aload_0
   37:	getfield	#22; //Field $outer:Lscala/xml/TextBuffer;
   40:	invokevirtual	#65; //Method scala/xml/TextBuffer.sb:()Lscala/collection/mutable/StringBuilder;
   43:	astore_3
   44:	aload_3
   45:	invokestatic	#75; //Method scala/collection/IndexedSeqLike$class.last:(Lscala/collection/IndexedSeqLike;)Ljava/lang/Object;
   48:	invokestatic	#42; //Method scala/runtime/BoxesRunTime.unboxToChar:(Ljava/lang/Object;)C
   51:	invokeinterface	#59,  2; //InterfaceMethod scala/xml/parsing/TokenTests.isSpace:(C)Z
   56:	ifeq	65
   59:	getstatic	#81; //Field scala/runtime/BoxedUnit.UNIT:Lscala/runtime/BoxedUnit;
   62:	goto	91
   65:	aload_0
   66:	getfield	#22; //Field $outer:Lscala/xml/TextBuffer;
   69:	invokevirtual	#65; //Method scala/xml/TextBuffer.sb:()Lscala/collection/mutable/StringBuilder;
   72:	ldc	#82; //int 32
   74:	invokevirtual	#88; //Method scala/collection/mutable/StringBuilder.append:(C)Lscala/collection/mutable/StringBuilder;
   77:	goto	91
   80:	aload_0
   81:	getfield	#22; //Field $outer:Lscala/xml/TextBuffer;
   84:	invokevirtual	#65; //Method scala/xml/TextBuffer.sb:()Lscala/collection/mutable/StringBuilder;
   87:	iload_1
   88:	invokevirtual	#88; //Method scala/collection/mutable/StringBuilder.append:(C)Lscala/collection/mutable/StringBuilder;
   91:	areturn
  LineNumberTable: 
   line 39: 0
   line 40: 18
   line 39: 80

  LocalVariableTable: 
   Start  Length  Slot  Name   Signature
   0      92      0    this       Lscala/xml/TextBuffer$$anonfun$append$1;
   6      86      1    c       C


public scala.Function1 andThen(scala.Function1);
  Code:
   Stack=2, Locals=2, Args_size=2
   0:	aload_0
   1:	aload_1
   2:	invokestatic	#95; //Method scala/Function1$class.andThen:(Lscala/Function1;Lscala/Function1;)Lscala/Function1;
   5:	areturn
  LineNumberTable: 
   line 38: 0

  LocalVariableTable: 
   Start  Length  Slot  Name   Signature
   0      6      0    this       Lscala/xml/TextBuffer$$anonfun$append$1;
   0      6      1    g       Lscala/Function1;


public scala.Function1 compose(scala.Function1);
  Code:
   Stack=2, Locals=2, Args_size=2
   0:	aload_0
   1:	aload_1
   2:	invokestatic	#100; //Method scala/Function1$class.compose:(Lscala/Function1;Lscala/Function1;)Lscala/Function1;
   5:	areturn
  LineNumberTable: 
   line 38: 0

  LocalVariableTable: 
   Start  Length  Slot  Name   Signature
   0      6      0    this       Lscala/xml/TextBuffer$$anonfun$append$1;
   0      6      1    g       Lscala/Function1;


public java.lang.String toString();
  Code:
   Stack=1, Locals=1, Args_size=1
   0:	aload_0
   1:	invokestatic	#105; //Method scala/Function1$class.toString:(Lscala/Function1;)Ljava/lang/String;
   4:	areturn
  LineNumberTable: 
   line 38: 0


}

