Compiled from "TopScope.scala"
public final class scala.xml.TopScope extends java.lang.Object
  SourceFile: "TopScope.scala"
  ScalaSig: length = 0x3
   05 00 00 
  RuntimeVisibleAnnotations: length = 0xB
   00 01 00 5F 00 01 00 60 73 00 61 
  minor version: 0
  major version: 49
  Constant pool:
Asciz	SourceFile;
Asciz	TopScope.scala;
Asciz	buildString;
Asciz	(Lscala/collection/mutable/StringBuilder;Lscala/xml/NamespaceBinding;)V;
Asciz	Code;
Asciz	scala/xml/TopScope$;
class	scala/xml/TopScope$
Asciz	MODULE$;
Asciz	Lscala/xml/TopScope$;;
NameAndType	MODULE$:Lscala/xml/TopScope$;
Field	scala/xml/TopScope$.MODULE$:Lscala/xml/TopScope$;
NameAndType	buildString:(Lscala/collection/mutable/StringBuilder;Lscala/xml/NamespaceBinding;)V
Method	scala/xml/TopScope$.buildString:(Lscala/collection/mutable/StringBuilder;Lscala/xml/NamespaceBinding;)V
Asciz	(Lscala/xml/NamespaceBinding;)Ljava/lang/String;;
NameAndType	buildString:(Lscala/xml/NamespaceBinding;)Ljava/lang/String;
Method	scala/xml/TopScope$.buildString:(Lscala/xml/NamespaceBinding;)Ljava/lang/String;
Asciz	getPrefix;
Asciz	(Ljava/lang/String;)Ljava/lang/String;;
NameAndType	getPrefix:(Ljava/lang/String;)Ljava/lang/String;
Method	scala/xml/TopScope$.getPrefix:(Ljava/lang/String;)Ljava/lang/String;
Asciz	getURI;
NameAndType	getURI:(Ljava/lang/String;)Ljava/lang/String;
Method	scala/xml/TopScope$.getURI:(Ljava/lang/String;)Ljava/lang/String;
Asciz	xml_$bang$eq;
Asciz	(Ljava/lang/Object;)Z;
NameAndType	xml_$bang$eq:(Ljava/lang/Object;)Z
Method	scala/xml/TopScope$.xml_$bang$eq:(Ljava/lang/Object;)Z
Asciz	xml_$eq$eq;
NameAndType	xml_$eq$eq:(Ljava/lang/Object;)Z
Method	scala/xml/TopScope$.xml_$eq$eq:(Ljava/lang/Object;)Z
Asciz	strict_$bang$eq;
Asciz	(Lscala/xml/Equality;)Z;
NameAndType	strict_$bang$eq:(Lscala/xml/Equality;)Z
Method	scala/xml/TopScope$.strict_$bang$eq:(Lscala/xml/Equality;)Z
Asciz	productElements;
Asciz	()Lscala/collection/Iterator;;
NameAndType	productElements:()Lscala/collection/Iterator;
Method	scala/xml/TopScope$.productElements:()Lscala/collection/Iterator;
Asciz	Deprecated;
Asciz	productIterator;
NameAndType	productIterator:()Lscala/collection/Iterator;
Method	scala/xml/TopScope$.productIterator:()Lscala/collection/Iterator;
Asciz	productElementName;
Asciz	(I)Ljava/lang/String;;
NameAndType	productElementName:(I)Ljava/lang/String;
Method	scala/xml/TopScope$.productElementName:(I)Ljava/lang/String;
Asciz	productElement;
Asciz	(I)Ljava/lang/Object;;
NameAndType	productElement:(I)Ljava/lang/Object;
Method	scala/xml/TopScope$.productElement:(I)Ljava/lang/Object;
Asciz	productArity;
Asciz	()I;
NameAndType	productArity:()I
Method	scala/xml/TopScope$.productArity:()I
Asciz	productPrefix;
Asciz	()Ljava/lang/String;;
NameAndType	productPrefix:()Ljava/lang/String;
Method	scala/xml/TopScope$.productPrefix:()Ljava/lang/String;
Asciz	copy$default$3;
Asciz	()Lscala/xml/NamespaceBinding;;
NameAndType	copy$default$3:()Lscala/xml/NamespaceBinding;
Method	scala/xml/TopScope$.copy$default$3:()Lscala/xml/NamespaceBinding;
Asciz	copy$default$2;
NameAndType	copy$default$2:()Ljava/lang/String;
Method	scala/xml/TopScope$.copy$default$2:()Ljava/lang/String;
Asciz	copy$default$1;
NameAndType	copy$default$1:()Ljava/lang/String;
Method	scala/xml/TopScope$.copy$default$1:()Ljava/lang/String;
Asciz	copy;
Asciz	(Ljava/lang/String;Ljava/lang/String;Lscala/xml/NamespaceBinding;)Lscala/xml/NamespaceBinding;;
NameAndType	copy:(Ljava/lang/String;Ljava/lang/String;Lscala/xml/NamespaceBinding;)Lscala/xml/NamespaceBinding;
Method	scala/xml/TopScope$.copy:(Ljava/lang/String;Ljava/lang/String;Lscala/xml/NamespaceBinding;)Lscala/xml/NamespaceBinding;
Asciz	basisForHashCode;
Asciz	()Lscala/collection/Seq;;
NameAndType	basisForHashCode:()Lscala/collection/Seq;
Method	scala/xml/TopScope$.basisForHashCode:()Lscala/collection/Seq;
Asciz	()Lscala/collection/Seq<Ljava/lang/Object;>;;
Asciz	Signature;
Asciz	strict_$eq$eq;
NameAndType	strict_$eq$eq:(Lscala/xml/Equality;)Z
Method	scala/xml/TopScope$.strict_$eq$eq:(Lscala/xml/Equality;)Z
Asciz	canEqual;
NameAndType	canEqual:(Ljava/lang/Object;)Z
Method	scala/xml/TopScope$.canEqual:(Ljava/lang/Object;)Z
Asciz	parent;
NameAndType	parent:()Lscala/xml/NamespaceBinding;
Method	scala/xml/TopScope$.parent:()Lscala/xml/NamespaceBinding;
Asciz	uri;
NameAndType	uri:()Ljava/lang/String;
Method	scala/xml/TopScope$.uri:()Ljava/lang/String;
Asciz	prefix;
NameAndType	prefix:()Ljava/lang/String;
Method	scala/xml/TopScope$.prefix:()Ljava/lang/String;
Asciz	ScalaSig;
Asciz	Lscala/reflect/ScalaSignature;;
Asciz	bytes;
Asciz	-;Q!\t\tV8q'|/\t1_7m)!B:dC27\t%iA\t\t!\t!E\tAAk9TG>XmE\n=\"C\n9!(b[/Y2f&tG-8h!\t#D\tBAATGdm2kK$\"\n\t)Aj]&$hF9\"9W\r^+SR\t\t5uq!E\nq!A)sK,g-?\t11:j]T!\t2A\rAXMZ5yc!)1%C!IIq-;Qe43BQA\nAe\tA!:jc!)&C!SAAo\*ue&tw\rF+!\tY'D-\tic&mC:<'\"A\t)g/Y=1BQAMBM\n1BY;jYFO]5oOR!kE\rDgR|C3sF9w%\"E\ni\"!B+oSRDQAu\n!a2y2eBA E\t5)DB\te!=e>|GOP%Q\tBa7.Y4f\t9JATiJLgn\"vS2$WMAQAA1\ta![4o_J,;
Asciz	RuntimeVisibleAnnotations;
Asciz	scala/xml/TopScope;
class	scala/xml/TopScope
Asciz	java/lang/Object;
class	java/lang/Object

{
public static final void buildString(scala.collection.mutable.StringBuilder, scala.xml.NamespaceBinding);
  Signature: (Lscala/collection/mutable/StringBuilder;Lscala/xml/NamespaceBinding;)V
  Code:
   Stack=3, Locals=2, Args_size=2
	getstatic	Field scala/xml/TopScope$.MODULE$:Lscala/xml/TopScope$;
	aload_0
	aload_1
	invokevirtual	Method scala/xml/TopScope$.buildString:(Lscala/collection/mutable/StringBuilder;Lscala/xml/NamespaceBinding;)V
	return
  Labels:

public static final java.lang.String buildString(scala.xml.NamespaceBinding);
  Signature: (Lscala/xml/NamespaceBinding;)Ljava/lang/String;
  Code:
   Stack=2, Locals=1, Args_size=1
	getstatic	Field scala/xml/TopScope$.MODULE$:Lscala/xml/TopScope$;
	aload_0
	invokevirtual	Method scala/xml/TopScope$.buildString:(Lscala/xml/NamespaceBinding;)Ljava/lang/String;
	areturn
  Labels:

public static final java.lang.String getPrefix(java.lang.String);
  Signature: (Ljava/lang/String;)Ljava/lang/String;
  Code:
   Stack=2, Locals=1, Args_size=1
	getstatic	Field scala/xml/TopScope$.MODULE$:Lscala/xml/TopScope$;
	aload_0
	invokevirtual	Method scala/xml/TopScope$.getPrefix:(Ljava/lang/String;)Ljava/lang/String;
	areturn
  Labels:

public static final java.lang.String getURI(java.lang.String);
  Signature: (Ljava/lang/String;)Ljava/lang/String;
  Code:
   Stack=2, Locals=1, Args_size=1
	getstatic	Field scala/xml/TopScope$.MODULE$:Lscala/xml/TopScope$;
	aload_0
	invokevirtual	Method scala/xml/TopScope$.getURI:(Ljava/lang/String;)Ljava/lang/String;
	areturn
  Labels:

public static final boolean xml_$bang$eq(java.lang.Object);
  Signature: (Ljava/lang/Object;)Z
  Code:
   Stack=2, Locals=1, Args_size=1
	getstatic	Field scala/xml/TopScope$.MODULE$:Lscala/xml/TopScope$;
	aload_0
	invokevirtual	Method scala/xml/TopScope$.xml_$bang$eq:(Ljava/lang/Object;)Z
	ireturn
  Labels:

public static final boolean xml_$eq$eq(java.lang.Object);
  Signature: (Ljava/lang/Object;)Z
  Code:
   Stack=2, Locals=1, Args_size=1
	getstatic	Field scala/xml/TopScope$.MODULE$:Lscala/xml/TopScope$;
	aload_0
	invokevirtual	Method scala/xml/TopScope$.xml_$eq$eq:(Ljava/lang/Object;)Z
	ireturn
  Labels:

public static final boolean strict_$bang$eq(scala.xml.Equality);
  Signature: (Lscala/xml/Equality;)Z
  Code:
   Stack=2, Locals=1, Args_size=1
	getstatic	Field scala/xml/TopScope$.MODULE$:Lscala/xml/TopScope$;
	aload_0
	invokevirtual	Method scala/xml/TopScope$.strict_$bang$eq:(Lscala/xml/Equality;)Z
	ireturn
  Labels:

public static final scala.collection.Iterator productElements();
  Signature: ()Lscala/collection/Iterator;
  Code:
   Stack=1, Locals=0, Args_size=0
	getstatic	Field scala/xml/TopScope$.MODULE$:Lscala/xml/TopScope$;
	invokevirtual	Method scala/xml/TopScope$.productElements:()Lscala/collection/Iterator;
	areturn
  Labels:
  Deprecated: true

public static final scala.collection.Iterator productIterator();
  Signature: ()Lscala/collection/Iterator;
  Code:
   Stack=1, Locals=0, Args_size=0
	getstatic	Field scala/xml/TopScope$.MODULE$:Lscala/xml/TopScope$;
	invokevirtual	Method scala/xml/TopScope$.productIterator:()Lscala/collection/Iterator;
	areturn
  Labels:

public static final java.lang.String productElementName(int);
  Signature: (I)Ljava/lang/String;
  Code:
   Stack=2, Locals=1, Args_size=1
	getstatic	Field scala/xml/TopScope$.MODULE$:Lscala/xml/TopScope$;
	iload_0
	invokevirtual	Method scala/xml/TopScope$.productElementName:(I)Ljava/lang/String;
	areturn
  Labels:

public static final java.lang.Object productElement(int);
  Signature: (I)Ljava/lang/Object;
  Code:
   Stack=2, Locals=1, Args_size=1
	getstatic	Field scala/xml/TopScope$.MODULE$:Lscala/xml/TopScope$;
	iload_0
	invokevirtual	Method scala/xml/TopScope$.productElement:(I)Ljava/lang/Object;
	areturn
  Labels:

public static final int productArity();
  Signature: ()I
  Code:
   Stack=1, Locals=0, Args_size=0
	getstatic	Field scala/xml/TopScope$.MODULE$:Lscala/xml/TopScope$;
	invokevirtual	Method scala/xml/TopScope$.productArity:()I
	ireturn
  Labels:

public static final java.lang.String productPrefix();
  Signature: ()Ljava/lang/String;
  Code:
   Stack=1, Locals=0, Args_size=0
	getstatic	Field scala/xml/TopScope$.MODULE$:Lscala/xml/TopScope$;
	invokevirtual	Method scala/xml/TopScope$.productPrefix:()Ljava/lang/String;
	areturn
  Labels:

public static final scala.xml.NamespaceBinding copy$default$3();
  Signature: ()Lscala/xml/NamespaceBinding;
  Code:
   Stack=1, Locals=0, Args_size=0
	getstatic	Field scala/xml/TopScope$.MODULE$:Lscala/xml/TopScope$;
	invokevirtual	Method scala/xml/TopScope$.copy$default$3:()Lscala/xml/NamespaceBinding;
	areturn
  Labels:

public static final java.lang.String copy$default$2();
  Signature: ()Ljava/lang/String;
  Code:
   Stack=1, Locals=0, Args_size=0
	getstatic	Field scala/xml/TopScope$.MODULE$:Lscala/xml/TopScope$;
	invokevirtual	Method scala/xml/TopScope$.copy$default$2:()Ljava/lang/String;
	areturn
  Labels:

public static final java.lang.String copy$default$1();
  Signature: ()Ljava/lang/String;
  Code:
   Stack=1, Locals=0, Args_size=0
	getstatic	Field scala/xml/TopScope$.MODULE$:Lscala/xml/TopScope$;
	invokevirtual	Method scala/xml/TopScope$.copy$default$1:()Ljava/lang/String;
	areturn
  Labels:

public static final scala.xml.NamespaceBinding copy(java.lang.String, java.lang.String, scala.xml.NamespaceBinding);
  Signature: (Ljava/lang/String;Ljava/lang/String;Lscala/xml/NamespaceBinding;)Lscala/xml/NamespaceBinding;
  Code:
   Stack=4, Locals=3, Args_size=3
	getstatic	Field scala/xml/TopScope$.MODULE$:Lscala/xml/TopScope$;
	aload_0
	aload_1
	aload_2
	invokevirtual	Method scala/xml/TopScope$.copy:(Ljava/lang/String;Ljava/lang/String;Lscala/xml/NamespaceBinding;)Lscala/xml/NamespaceBinding;
	areturn
  Labels:

public static final scala.collection.Seq basisForHashCode();
  Signature: ()Lscala/collection/Seq;
  Code:
   Stack=1, Locals=0, Args_size=0
	getstatic	Field scala/xml/TopScope$.MODULE$:Lscala/xml/TopScope$;
	invokevirtual	Method scala/xml/TopScope$.basisForHashCode:()Lscala/collection/Seq;
	areturn
  Labels:
  Signature: length = 0x2
   00 4D 

public static final boolean strict_$eq$eq(scala.xml.Equality);
  Signature: (Lscala/xml/Equality;)Z
  Code:
   Stack=2, Locals=1, Args_size=1
	getstatic	Field scala/xml/TopScope$.MODULE$:Lscala/xml/TopScope$;
	aload_0
	invokevirtual	Method scala/xml/TopScope$.strict_$eq$eq:(Lscala/xml/Equality;)Z
	ireturn
  Labels:

public static final boolean canEqual(java.lang.Object);
  Signature: (Ljava/lang/Object;)Z
  Code:
   Stack=2, Locals=1, Args_size=1
	getstatic	Field scala/xml/TopScope$.MODULE$:Lscala/xml/TopScope$;
	aload_0
	invokevirtual	Method scala/xml/TopScope$.canEqual:(Ljava/lang/Object;)Z
	ireturn
  Labels:

public static final scala.xml.NamespaceBinding parent();
  Signature: ()Lscala/xml/NamespaceBinding;
  Code:
   Stack=1, Locals=0, Args_size=0
	getstatic	Field scala/xml/TopScope$.MODULE$:Lscala/xml/TopScope$;
	invokevirtual	Method scala/xml/TopScope$.parent:()Lscala/xml/NamespaceBinding;
	areturn
  Labels:

public static final java.lang.String uri();
  Signature: ()Ljava/lang/String;
  Code:
   Stack=1, Locals=0, Args_size=0
	getstatic	Field scala/xml/TopScope$.MODULE$:Lscala/xml/TopScope$;
	invokevirtual	Method scala/xml/TopScope$.uri:()Ljava/lang/String;
	areturn
  Labels:

public static final java.lang.String prefix();
  Signature: ()Ljava/lang/String;
  Code:
   Stack=1, Locals=0, Args_size=0
	getstatic	Field scala/xml/TopScope$.MODULE$:Lscala/xml/TopScope$;
	invokevirtual	Method scala/xml/TopScope$.prefix:()Ljava/lang/String;
	areturn
  Labels:

}

