Compiled from "TopScope.scala"
public final class scala.xml.TopScope$ extends scala.xml.NamespaceBinding implements scala.ScalaObject
  SourceFile: "TopScope.scala"
  Scala: length = 0x
   
  minor version: 0
  major version: 49
  Constant pool:
Asciz	SourceFile;
Asciz	TopScope.scala;
Asciz	Scala;
Asciz	MODULE$;
Asciz	Lscala/xml/TopScope$;;
Asciz	<clinit>;
Asciz	()V;
Asciz	Code;
Asciz	scala/xml/TopScope$;
class	scala/xml/TopScope$
Asciz	<init>;
NameAndType	"<init>":()V
Method	scala/xml/TopScope$."<init>":()V
Asciz	getURI;
Asciz	(Ljava/lang/String;)Ljava/lang/String;;
Asciz	LineNumberTable;
Asciz	scala/xml/XML$;
class	scala/xml/XML$
Asciz	Lscala/xml/XML$;;
NameAndType	MODULE$:Lscala/xml/XML$;
Field	scala/xml/XML$.MODULE$:Lscala/xml/XML$;
Asciz	xml;
Asciz	()Ljava/lang/String;;
NameAndType	xml:()Ljava/lang/String;
Method	scala/xml/XML$.xml:()Ljava/lang/String;
Asciz	java/lang/Object;
class	java/lang/Object
Asciz	equals;
Asciz	(Ljava/lang/Object;)Z;
NameAndType	equals:(Ljava/lang/Object;)Z
Method	java/lang/Object.equals:(Ljava/lang/Object;)Z
Asciz	namespace;
NameAndType	namespace:()Ljava/lang/String;
Method	scala/xml/XML$.namespace:()Ljava/lang/String;
Asciz	this;
Asciz	prefix1;
Asciz	Ljava/lang/String;;
Asciz	LocalVariableTable;
Asciz	getPrefix;
Asciz	uri1;
Asciz	toString;
Asciz	;
String	
Asciz	buildString;
Asciz	(Lscala/xml/NamespaceBinding;)Ljava/lang/String;;
Asciz	stop;
Asciz	Lscala/xml/NamespaceBinding;;
Asciz	(Lscala/collection/mutable/StringBuilder;Lscala/xml/NamespaceBinding;)V;
Asciz	sb;
Asciz	Lscala/collection/mutable/StringBuilder;;
Asciz	ignore;
Asciz	scala/xml/NamespaceBinding;
class	scala/xml/NamespaceBinding
Asciz	(Ljava/lang/String;Ljava/lang/String;Lscala/xml/NamespaceBinding;)V;
NameAndType	"<init>":(Ljava/lang/String;Ljava/lang/String;Lscala/xml/NamespaceBinding;)V
Method	scala/xml/NamespaceBinding."<init>":(Ljava/lang/String;Ljava/lang/String;Lscala/xml/NamespaceBinding;)V
NameAndType	MODULE$:Lscala/xml/TopScope$;
Field	scala/xml/TopScope$.MODULE$:Lscala/xml/TopScope$;
Asciz	scala/ScalaObject;
class	scala/ScalaObject

{
public static final scala.xml.TopScope$ MODULE$;
  Signature: Lscala/xml/TopScope$;

public static {};
  Signature: ()V
  Code:
   Stack=1, Locals=0, Args_size=0
	new	class scala/xml/TopScope$
	invokespecial	Method "<init>":()V
	return
  Labels:

public java.lang.String getURI(java.lang.String);
  Signature: (Ljava/lang/String;)Ljava/lang/String;
  Code:
   Stack=2, Locals=3, Args_size=2
	aload_1
	getstatic	Field scala/xml/XML$.MODULE$:Lscala/xml/XML$;
	invokevirtual	Method scala/xml/XML$.xml:()Ljava/lang/String;
	astore_2
	dup
	ifnonnull	l1 // aload_2
	pop
	aload_2
	ifnull	l2 // getstatic
	goto	l3 // aconst_null
l1	aload_2
	invokevirtual	Method java/lang/Object.equals:(Ljava/lang/Object;)Z
	ifeq	l3 // aconst_null
l2	getstatic	Field scala/xml/XML$.MODULE$:Lscala/xml/XML$;
	invokevirtual	Method scala/xml/XML$.namespace:()Ljava/lang/String;
	goto	l4 // areturn
l3	aconst_null
	pop
	aconst_null
l4	areturn
  Labels:
   	l1 = 20 // aload_2
   	l2 = 27 // getstatic
   	l3 = 36 // aconst_null
   	l4 = 39 // areturn
  LocalVariableTable: 
   Start  Length  Slot  Name   Signature
   0      40      0    this       Lscala/xml/TopScope$;
   0      40      1    prefix1       Ljava/lang/String;


public java.lang.String getPrefix(java.lang.String);
  Signature: (Ljava/lang/String;)Ljava/lang/String;
  Code:
   Stack=2, Locals=3, Args_size=2
	aload_1
	getstatic	Field scala/xml/XML$.MODULE$:Lscala/xml/XML$;
	invokevirtual	Method scala/xml/XML$.namespace:()Ljava/lang/String;
	astore_2
	dup
	ifnonnull	l1 // aload_2
	pop
	aload_2
	ifnull	l2 // getstatic
	goto	l3 // aconst_null
l1	aload_2
	invokevirtual	Method java/lang/Object.equals:(Ljava/lang/Object;)Z
	ifeq	l3 // aconst_null
l2	getstatic	Field scala/xml/XML$.MODULE$:Lscala/xml/XML$;
	invokevirtual	Method scala/xml/XML$.xml:()Ljava/lang/String;
	goto	l4 // areturn
l3	aconst_null
	pop
	aconst_null
l4	areturn
  Labels:
   	l1 = 20 // aload_2
   	l2 = 27 // getstatic
   	l3 = 36 // aconst_null
   	l4 = 39 // areturn
  LocalVariableTable: 
   Start  Length  Slot  Name   Signature
   0      40      0    this       Lscala/xml/TopScope$;
   0      40      1    uri1       Ljava/lang/String;


public java.lang.String toString();
  Signature: ()Ljava/lang/String;
  Code:
   Stack=1, Locals=1, Args_size=1
	ldc	String 
	areturn
  Labels:

public java.lang.String buildString(scala.xml.NamespaceBinding);
  Signature: (Lscala/xml/NamespaceBinding;)Ljava/lang/String;
  Code:
   Stack=1, Locals=2, Args_size=2
	ldc	String 
	areturn
  Labels:
  LocalVariableTable: 
   Start  Length  Slot  Name   Signature
   0      3      0    this       Lscala/xml/TopScope$;
   0      3      1    stop       Lscala/xml/NamespaceBinding;


public void buildString(scala.collection.mutable.StringBuilder, scala.xml.NamespaceBinding);
  Signature: (Lscala/collection/mutable/StringBuilder;Lscala/xml/NamespaceBinding;)V
  Code:
   Stack=0, Locals=3, Args_size=3
	return
  Labels:
  LocalVariableTable: 
   Start  Length  Slot  Name   Signature
   0      1      0    this       Lscala/xml/TopScope$;
   0      1      1    sb       Lscala/collection/mutable/StringBuilder;
   0      1      2    ignore       Lscala/xml/NamespaceBinding;


private scala.xml.TopScope$();
  Signature: ()V
  Code:
   Stack=4, Locals=1, Args_size=1
	aload_0
	aconst_null
	pop
	aconst_null
	aconst_null
	pop
	aconst_null
	aconst_null
	pop
	aconst_null
	invokespecial	Method scala/xml/NamespaceBinding."<init>":(Ljava/lang/String;Ljava/lang/String;Lscala/xml/NamespaceBinding;)V
	aload_0
	putstatic	Field MODULE$:Lscala/xml/TopScope$;
	return
  Labels:

}

