Compiled from "Unparsed.scala"
public class scala.xml.Unparsed extends scala.xml.Atom implements scala.ScalaObject
  SourceFile: "Unparsed.scala"
  Signature: length = 0x2
   00 46 
  ScalaSig: length = 0x211
   05 00 5C 06 08 01 02 FFFFFF84 FFFFFF80 FFFFFF80 FFFFFF80 00 07 02 08 55
   6E 70 61 72 73 65 64 0A 02 03 04 01 03 78 6D 6C
   0A 01 05 01 05 73 63 61 6C 61 03 00 13 03 00 08
   14 10 03 09 0A 0C 0D 01 02 09 02 0B 02 02 04 41
   74 6F 6D 10 02 0D 11 0E 02 0E 0F 0D 01 04 09 02
   10 04 01 06 50 72 65 64 65 66 09 02 12 13 02 06
   53 74 72 69 6E 67 0A 02 10 04 10 02 0E 15 09 02
   16 04 02 0B 53 63 61 6C 61 4F 62 6A 65 63 74 08
   09 18 00 FFFFFF82 FFFFFF80 FFFFFFA0 FFFFFF80 04 0C 19 01 04 64 61 74 61
   09 02 18 0A 08 05 1B 00 FFFFFF84 00 1C 01 06 3C 69 6E
   69 74 3E 14 02 1D 1E 10 02 09 00 08 05 18 1A FFFFFFC0
   00 0C 08 05 20 00 FFFFFF84 22 21 01 06 65 71 75 61 6C
   73 14 02 22 25 10 02 0E 23 09 02 24 04 02 07 42
   6F 6F 6C 65 61 6E 08 05 26 1F FFFFFFC0 00 27 01 01 78
   10 02 0E 28 09 02 29 04 02 03 41 6E 79 08 05 2B
   00 FFFFFF84 20 2C 01 0B 62 75 69 6C 64 53 74 72 69 6E
   67 14 02 2D 35 10 02 2E 33 0D 01 2F 0A 02 30 31
   01 07 6D 75 74 61 62 6C 65 0A 02 32 04 01 0A 63
   6F 6C 6C 65 63 74 69 6F 6E 09 02 34 2F 02 0D 53
   74 72 69 6E 67 42 75 69 6C 64 65 72 08 05 36 2A
   FFFFFFC0 00 37 01 02 73 62 10 02 38 40 0E 02 39 3E 0E
   02 3A 3D 0D 01 3B 0A 02 3C 06 01 06 3C 72 6F 6F
   74 3E 09 01 05 09 02 3F 04 01 07 70 61 63 6B 61
   67 65 09 02 34 41 0A 02 3F 04 07 05 43 02 FFFFFF88 02
   44 01 08 55 6E 70 61 72 73 65 64 10 02 09 45 06
   08 01 02 FFFFFF84 FFFFFF80 FFFFFF80 FFFFFF88 02 46 13 03 45 47 14 10 02
   48 4D 0D 01 49 0A 02 4A 4B 01 04 6C 61 6E 67 0A
   01 4C 01 04 6A 61 76 61 09 02 4E 49 02 06 4F 62
   6A 65 63 74 08 05 1B 45 FFFFFF84 00 50 14 01 44 08 05
   52 45 FFFFFF84 00 53 01 05 61 70 70 6C 79 14 02 1D 54
   08 05 18 51 FFFFFFC0 00 0C 08 05 56 45 FFFFFF84 00 57 01 07
   75 6E 61 70 70 6C 79 14 02 58 5B 10 03 0E 59 0C
   09 02 5A 04 02 04 53 6F 6D 65 08 05 26 55 FFFFFFC0 00
   1D 
  minor version: 0
  major version: 49
  Constant pool:
Asciz	SourceFile;
Asciz	Unparsed.scala;
Asciz	unapply;
Asciz	(Lscala/xml/Unparsed;)Lscala/Some;;
Asciz	Code;
Asciz	scala/xml/Unparsed$;
class	scala/xml/Unparsed$
Asciz	MODULE$;
Asciz	Lscala/xml/Unparsed$;;
NameAndType	MODULE$:Lscala/xml/Unparsed$;
Field	scala/xml/Unparsed$.MODULE$:Lscala/xml/Unparsed$;
NameAndType	unapply:(Lscala/xml/Unparsed;)Lscala/Some;
Method	scala/xml/Unparsed$.unapply:(Lscala/xml/Unparsed;)Lscala/Some;
Asciz	(Lscala/xml/Unparsed;)Lscala/Some<Ljava/lang/String;>;;
Asciz	Signature;
Asciz	equals;
Asciz	(Ljava/lang/Object;)Z;
Asciz	LineNumberTable;
Asciz	java/lang/String;
class	java/lang/String
Asciz	scala/xml/Atom;
class	scala/xml/Atom
Asciz	data;
Asciz	()Ljava/lang/Object;;
NameAndType	data:()Ljava/lang/Object;
Method	scala/xml/Atom.data:()Ljava/lang/Object;
Asciz	java/lang/Object;
class	java/lang/Object
NameAndType	equals:(Ljava/lang/Object;)Z
Method	java/lang/Object.equals:(Ljava/lang/Object;)Z
Asciz	java/lang/Number;
class	java/lang/Number
Asciz	java/lang/Character;
class	java/lang/Character
Asciz	scala/runtime/BoxesRunTime;
class	scala/runtime/BoxesRunTime
Asciz	equals2;
Asciz	(Ljava/lang/Object;Ljava/lang/Object;)Z;
NameAndType	equals2:(Ljava/lang/Object;Ljava/lang/Object;)Z
Method	scala/runtime/BoxesRunTime.equals2:(Ljava/lang/Object;Ljava/lang/Object;)Z
Asciz	this;
Asciz	Lscala/xml/Unparsed;;
Asciz	x;
Asciz	Ljava/lang/Object;;
Asciz	x0;
Asciz	y0;
Asciz	LocalVariableTable;
Asciz	buildString;
Asciz	(Lscala/collection/mutable/StringBuilder;)Lscala/collection/mutable/StringBuilder;;
Asciz	scala/collection/mutable/StringBuilder;
class	scala/collection/mutable/StringBuilder
Asciz	append;
Asciz	(Ljava/lang/String;)Lscala/collection/mutable/StringBuilder;;
NameAndType	append:(Ljava/lang/String;)Lscala/collection/mutable/StringBuilder;
Method	scala/collection/mutable/StringBuilder.append:(Ljava/lang/String;)Lscala/collection/mutable/StringBuilder;
Asciz	sb;
Asciz	Lscala/collection/mutable/StringBuilder;;
Asciz	<init>;
Asciz	(Ljava/lang/String;)V;
Asciz	(Ljava/lang/Object;)V;
NameAndType	"<init>":(Ljava/lang/Object;)V
Method	scala/xml/Atom."<init>":(Ljava/lang/Object;)V
Asciz	java/lang/IllegalArgumentException;
class	java/lang/IllegalArgumentException
Asciz	tried to construct Unparsed with null;
String	tried to construct Unparsed with null
NameAndType	"<init>":(Ljava/lang/String;)V
Method	java/lang/IllegalArgumentException."<init>":(Ljava/lang/String;)V
Asciz	Ljava/lang/String;;
Asciz	Lscala/xml/Atom<Ljava/lang/String;>;Lscala/ScalaObject;;
Asciz	ScalaSig;
Asciz	scala/xml/Unparsed;
class	scala/xml/Unparsed
Asciz	scala/ScalaObject;
class	scala/ScalaObject

{
public static final scala.Some unapply(scala.xml.Unparsed);
  Signature: (Lscala/xml/Unparsed;)Lscala/Some;
  Code:
   Stack=2, Locals=1, Args_size=1
	getstatic	Field scala/xml/Unparsed$.MODULE$:Lscala/xml/Unparsed$;
	aload_0
	invokevirtual	Method scala/xml/Unparsed$.unapply:(Lscala/xml/Unparsed;)Lscala/Some;
	areturn
  Labels:
  Signature: length = 0x2
   00 0E 

public final boolean equals(java.lang.Object);
  Signature: (Ljava/lang/Object;)Z
  Code:
   Stack=2, Locals=5, Args_size=2
	aload_1
	instanceof	class java/lang/String
	ifeq	l1 // aload_1
	aload_1
	checkcast	class java/lang/String
	aload_0
	invokespecial	Method scala/xml/Atom.data:()Ljava/lang/Object;
	astore_2
	dup
	ifnonnull	l2 // aload_2
	pop
	aload_2
	ifnull	l3 // iconst_1
	goto	l4 // iconst_0
l2	aload_2
	invokevirtual	Method java/lang/Object.equals:(Ljava/lang/Object;)Z
	ifeq	l4 // iconst_0
l3	iconst_1
	goto	l5 // ireturn
l4	iconst_0
	goto	l5 // ireturn
l1	aload_1
	instanceof	class scala/xml/Atom
	ifeq	l6 // iconst_0
	aload_0
	invokespecial	Method scala/xml/Atom.data:()Ljava/lang/Object;
	aload_1
	checkcast	class scala/xml/Atom
	invokevirtual	Method scala/xml/Atom.data:()Ljava/lang/Object;
	astore	4
	astore_3
	aload_3
	aload	4
	if_acmpne	l7 // aload_3
	iconst_1
	goto	l8 // ifeq
l7	aload_3
	ifnonnull	l9 // aload_3
	iconst_0
	goto	l8 // ifeq
l9	aload_3
	instanceof	class java/lang/Number
	ifne	l10 // aload_3
	aload_3
	instanceof	class java/lang/Character
	ifeq	l11 // aload_3
l10	aload_3
	aload	4
	invokestatic	Method scala/runtime/BoxesRunTime.equals2:(Ljava/lang/Object;Ljava/lang/Object;)Z
	goto	l8 // ifeq
l11	aload_3
	aload	4
	invokevirtual	Method java/lang/Object.equals:(Ljava/lang/Object;)Z
l8	ifeq	l12 // iconst_0
	iconst_1
	goto	l5 // ireturn
l12	iconst_0
	goto	l5 // ireturn
l6	iconst_0
l5	ireturn
  Labels:
   	l2 = 28 // aload_2
   	l3 = 35 // iconst_1
   	l4 = 39 // iconst_0
   	l1 = 43 // aload_1
   	l7 = 74 // aload_3
   	l9 = 82 // aload_3
   	l10 = 96 // aload_3
   	l11 = 105 // aload_3
   	l8 = 111 // ifeq
   	l12 = 118 // iconst_0
   	l6 = 122 // iconst_0
   	l5 = 123 // ireturn
  LocalVariableTable: 
   Start  Length  Slot  Name   Signature
   0      124      0    this       Lscala/xml/Unparsed;
   0      124      1    x       Ljava/lang/Object;
   70      44      3    x0       Ljava/lang/Object;
   70      44      4    y0       Ljava/lang/Object;


public scala.collection.mutable.StringBuilder buildString(scala.collection.mutable.StringBuilder);
  Signature: (Lscala/collection/mutable/StringBuilder;)Lscala/collection/mutable/StringBuilder;
  Code:
   Stack=2, Locals=2, Args_size=2
	aload_1
	aload_0
	invokespecial	Method scala/xml/Atom.data:()Ljava/lang/Object;
	checkcast	class java/lang/String
	invokevirtual	Method scala/collection/mutable/StringBuilder.append:(Ljava/lang/String;)Lscala/collection/mutable/StringBuilder;
	areturn
  Labels:
  LocalVariableTable: 
   Start  Length  Slot  Name   Signature
   0      12      0    this       Lscala/xml/Unparsed;
   0      12      1    sb       Lscala/collection/mutable/StringBuilder;


public scala.xml.Unparsed(java.lang.String);
  Signature: (Ljava/lang/String;)V
  Code:
   Stack=3, Locals=2, Args_size=2
	aload_0
	aload_1
	invokespecial	Method scala/xml/Atom."<init>":(Ljava/lang/Object;)V
	aload_0
	invokespecial	Method scala/xml/Atom.data:()Ljava/lang/Object;
	ifnonnull	l1 // return
	new	class java/lang/IllegalArgumentException
	dup
	ldc	String tried to construct Unparsed with null
	invokespecial	Method java/lang/IllegalArgumentException."<init>":(Ljava/lang/String;)V
	athrow
l1	return
  Labels:
   	l1 = 22 // return
  LocalVariableTable: 
   Start  Length  Slot  Name   Signature
   0      23      0    this       Lscala/xml/Unparsed;
   0      23      1    data       Ljava/lang/String;


}

