Compiled from "UnprefixedAttribute.scala"
public final class scala.xml.UnprefixedAttribute$ extends java.lang.Object implements scala.ScalaObject
  SourceFile: "UnprefixedAttribute.scala"
  Scala: length = 0x
   
  minor version: 0
  major version: 49
  Constant pool:
Asciz	SourceFile;
Asciz	UnprefixedAttribute.scala;
Asciz	MODULE$;
Asciz	Lscala/xml/UnprefixedAttribute$;;
Asciz	<clinit>;
Asciz	()V;
Asciz	Code;
Asciz	scala/xml/UnprefixedAttribute$;
class	scala/xml/UnprefixedAttribute$
Asciz	<init>;
NameAndType	"<init>":()V
Method	scala/xml/UnprefixedAttribute$."<init>":()V
Asciz	unapply;
Asciz	(Lscala/xml/UnprefixedAttribute;)Lscala/Some;;
Asciz	scala/Some;
class	scala/Some
Asciz	LineNumberTable;
Asciz	scala/Tuple3;
class	scala/Tuple3
Asciz	scala/xml/UnprefixedAttribute;
class	scala/xml/UnprefixedAttribute
Asciz	key;
Asciz	()Ljava/lang/String;;
NameAndType	key:()Ljava/lang/String;
Method	scala/xml/UnprefixedAttribute.key:()Ljava/lang/String;
Asciz	value;
Asciz	()Lscala/collection/Seq;;
NameAndType	value:()Lscala/collection/Seq;
Method	scala/xml/UnprefixedAttribute.value:()Lscala/collection/Seq;
Asciz	next;
Asciz	()Lscala/xml/MetaData;;
NameAndType	next:()Lscala/xml/MetaData;
Method	scala/xml/UnprefixedAttribute.next:()Lscala/xml/MetaData;
Asciz	(Ljava/lang/Object;Ljava/lang/Object;Ljava/lang/Object;)V;
NameAndType	"<init>":(Ljava/lang/Object;Ljava/lang/Object;Ljava/lang/Object;)V
Method	scala/Tuple3."<init>":(Ljava/lang/Object;Ljava/lang/Object;Ljava/lang/Object;)V
Asciz	(Ljava/lang/Object;)V;
NameAndType	"<init>":(Ljava/lang/Object;)V
Method	scala/Some."<init>":(Ljava/lang/Object;)V
Asciz	this;
Asciz	x;
Asciz	Lscala/xml/UnprefixedAttribute;;
Asciz	LocalVariableTable;
Asciz	(Lscala/xml/UnprefixedAttribute;)Lscala/Some<Lscala/Tuple3<Ljava/lang/String;Lscala/collection/Seq<Lscala/xml/Node;>;Lscala/xml/MetaData;>;>;;
Asciz	Signature;
Asciz	java/lang/Object;
class	java/lang/Object
Method	java/lang/Object."<init>":()V
NameAndType	MODULE$:Lscala/xml/UnprefixedAttribute$;
Field	scala/xml/UnprefixedAttribute$.MODULE$:Lscala/xml/UnprefixedAttribute$;
Asciz	Scala;
Asciz	scala/ScalaObject;
class	scala/ScalaObject

{
public static final scala.xml.UnprefixedAttribute$ MODULE$;
  Signature: Lscala/xml/UnprefixedAttribute$;

public static {};
  Signature: ()V
  Code:
   Stack=1, Locals=0, Args_size=0
	new	class scala/xml/UnprefixedAttribute$
	invokespecial	Method "<init>":()V
	return
  Labels:

public scala.Some unapply(scala.xml.UnprefixedAttribute);
  Signature: (Lscala/xml/UnprefixedAttribute;)Lscala/Some;
  Code:
   Stack=7, Locals=2, Args_size=2
	new	class scala/Some
	dup
	new	class scala/Tuple3
	dup
	aload_1
	invokevirtual	Method scala/xml/UnprefixedAttribute.key:()Ljava/lang/String;
	aload_1
	invokevirtual	Method scala/xml/UnprefixedAttribute.value:()Lscala/collection/Seq;
	aload_1
	invokevirtual	Method scala/xml/UnprefixedAttribute.next:()Lscala/xml/MetaData;
	invokespecial	Method scala/Tuple3."<init>":(Ljava/lang/Object;Ljava/lang/Object;Ljava/lang/Object;)V
	invokespecial	Method scala/Some."<init>":(Ljava/lang/Object;)V
	areturn
  Labels:
  LocalVariableTable: 
   Start  Length  Slot  Name   Signature
   0      27      0    this       Lscala/xml/UnprefixedAttribute$;
   0      27      1    x       Lscala/xml/UnprefixedAttribute;

  Signature: length = 0x2
   00 2C 

private scala.xml.UnprefixedAttribute$();
  Signature: ()V
  Code:
   Stack=1, Locals=1, Args_size=1
	aload_0
	invokespecial	Method java/lang/Object."<init>":()V
	aload_0
	putstatic	Field MODULE$:Lscala/xml/UnprefixedAttribute$;
	return
  Labels:

}

