Compiled from "Utility.scala"
public final class scala.xml.Utility$$anonfun$collectNamespaces$2 extends java.lang.Object implements scala.Function1,scala.ScalaObject,java.io.Serializable
  SourceFile: "Utility.scala"
  Scala: length = 0x
   
  InnerClass: 
   public final $anonfun$collectNamespaces$2=class scala/xml/Utility$$anonfun$collectNamespaces$2 of class scala/xml/Utility
  minor version: 0
  major version: 49
  Constant pool:
Asciz	SourceFile;
Asciz	Utility.scala;
Asciz	<clinit>;
Asciz	()V;
Asciz	Code;
Asciz	serialVersionUID;
Asciz	J;
Asciz	scala/xml/Utility$$anonfun$collectNamespaces$2;
class	scala/xml/Utility$$anonfun$collectNamespaces$2
NameAndType	serialVersionUID:J
Field	scala/xml/Utility$$anonfun$collectNamespaces$2.serialVersionUID:J
Asciz	set$1;
Asciz	Lscala/collection/mutable/Set;;
Asciz	n$1;
Asciz	Lscala/xml/Node;;
Asciz	<init>;
Asciz	(Lscala/xml/Node;Lscala/collection/mutable/Set;)V;
Asciz	LineNumberTable;
NameAndType	n$1:Lscala/xml/Node;
Field	scala/xml/Utility$$anonfun$collectNamespaces$2.n$1:Lscala/xml/Node;
NameAndType	set$1:Lscala/collection/mutable/Set;
Field	scala/xml/Utility$$anonfun$collectNamespaces$2.set$1:Lscala/collection/mutable/Set;
Asciz	java/lang/Object;
class	java/lang/Object
NameAndType	"<init>":()V
Method	java/lang/Object."<init>":()V
Asciz	scala/Function1$class;
class	scala/Function1$class
Asciz	$init$;
Asciz	(Lscala/Function1;)V;
NameAndType	$init$:(Lscala/Function1;)V
Method	scala/Function1$class.$init$:(Lscala/Function1;)V
Asciz	apply;
Asciz	(Ljava/lang/Object;)Ljava/lang/Object;;
Asciz	scala/xml/MetaData;
class	scala/xml/MetaData
Asciz	(Lscala/xml/MetaData;)Ljava/lang/Object;;
NameAndType	apply:(Lscala/xml/MetaData;)Ljava/lang/Object;
Method	scala/xml/Utility$$anonfun$collectNamespaces$2.apply:(Lscala/xml/MetaData;)Ljava/lang/Object;
Asciz	this;
Asciz	Lscala/xml/Utility$$anonfun$collectNamespaces$2;;
Asciz	v1;
Asciz	Ljava/lang/Object;;
Asciz	LocalVariableTable;
Asciz	scala/xml/PrefixedAttribute;
class	scala/xml/PrefixedAttribute
Asciz	getNamespace;
Asciz	(Lscala/xml/Node;)Ljava/lang/String;;
NameAndType	getNamespace:(Lscala/xml/Node;)Ljava/lang/String;
Method	scala/xml/MetaData.getNamespace:(Lscala/xml/Node;)Ljava/lang/String;
Asciz	scala/collection/mutable/SetLike;
class	scala/collection/mutable/SetLike
Asciz	$plus$eq;
Asciz	(Ljava/lang/Object;)Lscala/collection/mutable/SetLike;;
NameAndType	$plus$eq:(Ljava/lang/Object;)Lscala/collection/mutable/SetLike;
InterfaceMethod	scala/collection/mutable/SetLike.$plus$eq:(Ljava/lang/Object;)Lscala/collection/mutable/SetLike;
Asciz	scala/MatchError;
class	scala/MatchError
Asciz	toString;
Asciz	()Ljava/lang/String;;
NameAndType	toString:()Ljava/lang/String;
Method	scala/xml/MetaData.toString:()Ljava/lang/String;
Asciz	(Ljava/lang/String;)V;
NameAndType	"<init>":(Ljava/lang/String;)V
Method	scala/MatchError."<init>":(Ljava/lang/String;)V
Asciz	scala/runtime/BoxedUnit;
class	scala/runtime/BoxedUnit
Asciz	UNIT;
Asciz	Lscala/runtime/BoxedUnit;;
NameAndType	UNIT:Lscala/runtime/BoxedUnit;
Field	scala/runtime/BoxedUnit.UNIT:Lscala/runtime/BoxedUnit;
Asciz	a;
Asciz	Lscala/xml/MetaData;;
Asciz	andThen;
Asciz	(Lscala/Function1;)Lscala/Function1;;
Asciz	(Lscala/Function1;Lscala/Function1;)Lscala/Function1;;
NameAndType	andThen:(Lscala/Function1;Lscala/Function1;)Lscala/Function1;
Method	scala/Function1$class.andThen:(Lscala/Function1;Lscala/Function1;)Lscala/Function1;
Asciz	g;
Asciz	Lscala/Function1;;
Asciz	compose;
NameAndType	compose:(Lscala/Function1;Lscala/Function1;)Lscala/Function1;
Method	scala/Function1$class.compose:(Lscala/Function1;Lscala/Function1;)Lscala/Function1;
Asciz	(Lscala/Function1;)Ljava/lang/String;;
NameAndType	toString:(Lscala/Function1;)Ljava/lang/String;
Method	scala/Function1$class.toString:(Lscala/Function1;)Ljava/lang/String;
Asciz	Scala;
Asciz	InnerClasses;
Asciz	scala/xml/Utility;
class	scala/xml/Utility
Asciz	$anonfun$collectNamespaces$2;
Asciz	scala/Function1;
class	scala/Function1
Asciz	scala/ScalaObject;
class	scala/ScalaObject
Asciz	java/io/Serializable;
class	java/io/Serializable

{
public static final long serialVersionUID;
  Signature: J

private final scala.collection.mutable.Set set$1;
  Signature: Lscala/collection/mutable/Set;

private final scala.xml.Node n$1;
  Signature: Lscala/xml/Node;

public static {};
  Signature: ()V
  Code:
   Stack=2, Locals=0, Args_size=0
	lconst_0
	putstatic	Field serialVersionUID:J
	return
  Labels:

public scala.xml.Utility$$anonfun$collectNamespaces$2(scala.xml.Node, scala.collection.mutable.Set);
  Signature: (Lscala/xml/Node;Lscala/collection/mutable/Set;)V
  Code:
   Stack=2, Locals=3, Args_size=3
	aload_0
	aload_1
	putfield	Field n$1:Lscala/xml/Node;
	aload_0
	aload_2
	putfield	Field set$1:Lscala/collection/mutable/Set;
	aload_0
	invokespecial	Method java/lang/Object."<init>":()V
	aload_0
	invokestatic	Method scala/Function1$class.$init$:(Lscala/Function1;)V
	return
  Labels:

public final java.lang.Object apply(java.lang.Object);
  Signature: (Ljava/lang/Object;)Ljava/lang/Object;
  Code:
   Stack=2, Locals=2, Args_size=2
	aload_0
	aload_1
	checkcast	class scala/xml/MetaData
	invokevirtual	Method apply:(Lscala/xml/MetaData;)Ljava/lang/Object;
	areturn
  Labels:
  LocalVariableTable: 
   Start  Length  Slot  Name   Signature
   0      9      0    this       Lscala/xml/Utility$$anonfun$collectNamespaces$2;
   0      9      1    v1       Ljava/lang/Object;


public final java.lang.Object apply(scala.xml.MetaData);
  Signature: (Lscala/xml/MetaData;)Ljava/lang/Object;
  Code:
   Stack=3, Locals=2, Args_size=2
	aload_1
	instanceof	class scala/xml/PrefixedAttribute
	ifeq	l1 // iconst_1
	iconst_1
	ifeq	l2 // new
	aload_0
	getfield	Field set$1:Lscala/collection/mutable/Set;
	aload_1
	aload_0
	getfield	Field n$1:Lscala/xml/Node;
	invokevirtual	Method scala/xml/MetaData.getNamespace:(Lscala/xml/Node;)Ljava/lang/String;
	invokeinterface	InterfaceMethod scala/collection/mutable/SetLike.$plus$eq:(Ljava/lang/Object;)Lscala/collection/mutable/SetLike;
	goto	l3 // areturn
l2	new	class scala/MatchError
	dup
	aload_1
	invokevirtual	Method scala/xml/MetaData.toString:()Ljava/lang/String;
	invokespecial	Method scala/MatchError."<init>":(Ljava/lang/String;)V
	athrow
l1	iconst_1
	ifeq	l4 // new
	getstatic	Field scala/runtime/BoxedUnit.UNIT:Lscala/runtime/BoxedUnit;
l3	areturn
l4	new	class scala/MatchError
	dup
	aload_1
	invokevirtual	Method scala/xml/MetaData.toString:()Ljava/lang/String;
	invokespecial	Method scala/MatchError."<init>":(Ljava/lang/String;)V
	athrow
  Labels:
   	l2 = 31 // new
   	l1 = 43 // iconst_1
   	l3 = 50 // areturn
   	l4 = 51 // new
  LocalVariableTable: 
   Start  Length  Slot  Name   Signature
   0      63      0    this       Lscala/xml/Utility$$anonfun$collectNamespaces$2;
   0      63      1    a       Lscala/xml/MetaData;


public scala.Function1 andThen(scala.Function1);
  Signature: (Lscala/Function1;)Lscala/Function1;
  Code:
   Stack=2, Locals=2, Args_size=2
	aload_0
	aload_1
	invokestatic	Method scala/Function1$class.andThen:(Lscala/Function1;Lscala/Function1;)Lscala/Function1;
	areturn
  Labels:
  LocalVariableTable: 
   Start  Length  Slot  Name   Signature
   0      6      0    this       Lscala/xml/Utility$$anonfun$collectNamespaces$2;
   0      6      1    g       Lscala/Function1;


public scala.Function1 compose(scala.Function1);
  Signature: (Lscala/Function1;)Lscala/Function1;
  Code:
   Stack=2, Locals=2, Args_size=2
	aload_0
	aload_1
	invokestatic	Method scala/Function1$class.compose:(Lscala/Function1;Lscala/Function1;)Lscala/Function1;
	areturn
  Labels:
  LocalVariableTable: 
   Start  Length  Slot  Name   Signature
   0      6      0    this       Lscala/xml/Utility$$anonfun$collectNamespaces$2;
   0      6      1    g       Lscala/Function1;


public java.lang.String toString();
  Signature: ()Ljava/lang/String;
  Code:
   Stack=1, Locals=1, Args_size=1
	aload_0
	invokestatic	Method scala/Function1$class.toString:(Lscala/Function1;)Ljava/lang/String;
	areturn
  Labels:

}

