Compiled from "Utility.scala"
public final class scala.xml.Utility$$anonfun$toXML$1 extends java.lang.Object implements scala.Function1,scala.ScalaObject,java.io.Serializable
  SourceFile: "Utility.scala"
  Scala: length = 0x
   
  InnerClass: 
   public final $anonfun$toXML$1=class scala/xml/Utility$$anonfun$toXML$1 of class scala/xml/Utility
  minor version: 0
  major version: 49
  Constant pool:
Asciz	SourceFile;
Asciz	Utility.scala;
Asciz	<clinit>;
Asciz	()V;
Asciz	Code;
Asciz	serialVersionUID;
Asciz	J;
Asciz	scala/xml/Utility$$anonfun$toXML$1;
class	scala/xml/Utility$$anonfun$toXML$1
NameAndType	serialVersionUID:J
Field	scala/xml/Utility$$anonfun$toXML$1.serialVersionUID:J
Asciz	sb$1;
Asciz	Lscala/collection/mutable/StringBuilder;;
Asciz	x$7;
Asciz	Lscala/xml/Node;;
Asciz	<init>;
Asciz	(Lscala/xml/Node;Lscala/collection/mutable/StringBuilder;)V;
Asciz	LineNumberTable;
NameAndType	x$7:Lscala/xml/Node;
Field	scala/xml/Utility$$anonfun$toXML$1.x$7:Lscala/xml/Node;
NameAndType	sb$1:Lscala/collection/mutable/StringBuilder;
Field	scala/xml/Utility$$anonfun$toXML$1.sb$1:Lscala/collection/mutable/StringBuilder;
Asciz	java/lang/Object;
class	java/lang/Object
NameAndType	"<init>":()V
Method	java/lang/Object."<init>":()V
Asciz	scala/Function1$class;
class	scala/Function1$class
Asciz	$init$;
Asciz	(Lscala/Function1;)V;
NameAndType	$init$:(Lscala/Function1;)V
Method	scala/Function1$class.$init$:(Lscala/Function1;)V
Asciz	apply;
Asciz	(Ljava/lang/Object;)Ljava/lang/Object;;
Asciz	scala/xml/Node;
class	scala/xml/Node
Asciz	(Lscala/xml/Node;)Lscala/collection/mutable/StringBuilder;;
NameAndType	apply:(Lscala/xml/Node;)Lscala/collection/mutable/StringBuilder;
Method	scala/xml/Utility$$anonfun$toXML$1.apply:(Lscala/xml/Node;)Lscala/collection/mutable/StringBuilder;
Asciz	this;
Asciz	Lscala/xml/Utility$$anonfun$toXML$1;;
Asciz	v1;
Asciz	Ljava/lang/Object;;
Asciz	LocalVariableTable;
Asciz	scala/xml/Utility$;
class	scala/xml/Utility$
Asciz	MODULE$;
Asciz	Lscala/xml/Utility$;;
NameAndType	MODULE$:Lscala/xml/Utility$;
Field	scala/xml/Utility$.MODULE$:Lscala/xml/Utility$;
Asciz	scope;
Asciz	()Lscala/xml/NamespaceBinding;;
NameAndType	scope:()Lscala/xml/NamespaceBinding;
Method	scala/xml/Node.scope:()Lscala/xml/NamespaceBinding;
Asciz	toXML$default$4;
Asciz	()Z;
NameAndType	toXML$default$4:()Z
Method	scala/xml/Utility$.toXML$default$4:()Z
Asciz	toXML$default$5;
NameAndType	toXML$default$5:()Z
Method	scala/xml/Utility$.toXML$default$5:()Z
Asciz	toXML$default$6;
NameAndType	toXML$default$6:()Z
Method	scala/xml/Utility$.toXML$default$6:()Z
Asciz	toXML$default$7;
NameAndType	toXML$default$7:()Z
Method	scala/xml/Utility$.toXML$default$7:()Z
Asciz	toXML;
Asciz	(Lscala/xml/Node;Lscala/xml/NamespaceBinding;Lscala/collection/mutable/StringBuilder;ZZZZ)Lscala/collection/mutable/StringBuilder;;
NameAndType	toXML:(Lscala/xml/Node;Lscala/xml/NamespaceBinding;Lscala/collection/mutable/StringBuilder;ZZZZ)Lscala/collection/mutable/StringBuilder;
Method	scala/xml/Utility$.toXML:(Lscala/xml/Node;Lscala/xml/NamespaceBinding;Lscala/collection/mutable/StringBuilder;ZZZZ)Lscala/collection/mutable/StringBuilder;
Asciz	c;
Asciz	andThen;
Asciz	(Lscala/Function1;)Lscala/Function1;;
Asciz	(Lscala/Function1;Lscala/Function1;)Lscala/Function1;;
NameAndType	andThen:(Lscala/Function1;Lscala/Function1;)Lscala/Function1;
Method	scala/Function1$class.andThen:(Lscala/Function1;Lscala/Function1;)Lscala/Function1;
Asciz	g;
Asciz	Lscala/Function1;;
Asciz	compose;
NameAndType	compose:(Lscala/Function1;Lscala/Function1;)Lscala/Function1;
Method	scala/Function1$class.compose:(Lscala/Function1;Lscala/Function1;)Lscala/Function1;
Asciz	toString;
Asciz	()Ljava/lang/String;;
Asciz	(Lscala/Function1;)Ljava/lang/String;;
NameAndType	toString:(Lscala/Function1;)Ljava/lang/String;
Method	scala/Function1$class.toString:(Lscala/Function1;)Ljava/lang/String;
Asciz	Scala;
Asciz	InnerClasses;
Asciz	scala/xml/Utility;
class	scala/xml/Utility
Asciz	$anonfun$toXML$1;
Asciz	scala/Function1;
class	scala/Function1
Asciz	scala/ScalaObject;
class	scala/ScalaObject
Asciz	java/io/Serializable;
class	java/io/Serializable

{
public static final long serialVersionUID;
  Signature: J

private final scala.collection.mutable.StringBuilder sb$1;
  Signature: Lscala/collection/mutable/StringBuilder;

private final scala.xml.Node x$7;
  Signature: Lscala/xml/Node;

public static {};
  Signature: ()V
  Code:
   Stack=2, Locals=0, Args_size=0
	lconst_0
	putstatic	Field serialVersionUID:J
	return
  Labels:

public scala.xml.Utility$$anonfun$toXML$1(scala.xml.Node, scala.collection.mutable.StringBuilder);
  Signature: (Lscala/xml/Node;Lscala/collection/mutable/StringBuilder;)V
  Code:
   Stack=2, Locals=3, Args_size=3
	aload_0
	aload_1
	putfield	Field x$7:Lscala/xml/Node;
	aload_0
	aload_2
	putfield	Field sb$1:Lscala/collection/mutable/StringBuilder;
	aload_0
	invokespecial	Method java/lang/Object."<init>":()V
	aload_0
	invokestatic	Method scala/Function1$class.$init$:(Lscala/Function1;)V
	return
  Labels:

public final java.lang.Object apply(java.lang.Object);
  Signature: (Ljava/lang/Object;)Ljava/lang/Object;
  Code:
   Stack=2, Locals=2, Args_size=2
	aload_0
	aload_1
	checkcast	class scala/xml/Node
	invokevirtual	Method apply:(Lscala/xml/Node;)Lscala/collection/mutable/StringBuilder;
	areturn
  Labels:
  LocalVariableTable: 
   Start  Length  Slot  Name   Signature
   0      9      0    this       Lscala/xml/Utility$$anonfun$toXML$1;
   0      9      1    v1       Ljava/lang/Object;


public final scala.collection.mutable.StringBuilder apply(scala.xml.Node);
  Signature: (Lscala/xml/Node;)Lscala/collection/mutable/StringBuilder;
  Code:
   Stack=8, Locals=2, Args_size=2
	getstatic	Field scala/xml/Utility$.MODULE$:Lscala/xml/Utility$;
	aload_1
	aload_0
	getfield	Field x$7:Lscala/xml/Node;
	invokevirtual	Method scala/xml/Node.scope:()Lscala/xml/NamespaceBinding;
	aload_0
	getfield	Field sb$1:Lscala/collection/mutable/StringBuilder;
	getstatic	Field scala/xml/Utility$.MODULE$:Lscala/xml/Utility$;
	invokevirtual	Method scala/xml/Utility$.toXML$default$4:()Z
	getstatic	Field scala/xml/Utility$.MODULE$:Lscala/xml/Utility$;
	invokevirtual	Method scala/xml/Utility$.toXML$default$5:()Z
	getstatic	Field scala/xml/Utility$.MODULE$:Lscala/xml/Utility$;
	invokevirtual	Method scala/xml/Utility$.toXML$default$6:()Z
	getstatic	Field scala/xml/Utility$.MODULE$:Lscala/xml/Utility$;
	invokevirtual	Method scala/xml/Utility$.toXML$default$7:()Z
	invokevirtual	Method scala/xml/Utility$.toXML:(Lscala/xml/Node;Lscala/xml/NamespaceBinding;Lscala/collection/mutable/StringBuilder;ZZZZ)Lscala/collection/mutable/StringBuilder;
	areturn
  Labels:
  LocalVariableTable: 
   Start  Length  Slot  Name   Signature
   0      43      0    this       Lscala/xml/Utility$$anonfun$toXML$1;
   0      43      1    c       Lscala/xml/Node;


public scala.Function1 andThen(scala.Function1);
  Signature: (Lscala/Function1;)Lscala/Function1;
  Code:
   Stack=2, Locals=2, Args_size=2
	aload_0
	aload_1
	invokestatic	Method scala/Function1$class.andThen:(Lscala/Function1;Lscala/Function1;)Lscala/Function1;
	areturn
  Labels:
  LocalVariableTable: 
   Start  Length  Slot  Name   Signature
   0      6      0    this       Lscala/xml/Utility$$anonfun$toXML$1;
   0      6      1    g       Lscala/Function1;


public scala.Function1 compose(scala.Function1);
  Signature: (Lscala/Function1;)Lscala/Function1;
  Code:
   Stack=2, Locals=2, Args_size=2
	aload_0
	aload_1
	invokestatic	Method scala/Function1$class.compose:(Lscala/Function1;Lscala/Function1;)Lscala/Function1;
	areturn
  Labels:
  LocalVariableTable: 
   Start  Length  Slot  Name   Signature
   0      6      0    this       Lscala/xml/Utility$$anonfun$toXML$1;
   0      6      1    g       Lscala/Function1;


public java.lang.String toString();
  Signature: ()Ljava/lang/String;
  Code:
   Stack=1, Locals=1, Args_size=1
	aload_0
	invokestatic	Method scala/Function1$class.toString:(Lscala/Function1;)Ljava/lang/String;
	areturn
  Labels:

}

