Compiled from "Utility.scala"
public final class scala.xml.Utility$$anonfun$1 extends scala.runtime.AbstractFunction0$mcC$sp implements java.io.Serializable
  SourceFile: "Utility.scala"
  Scala: length = 0x
   
  InnerClass: 
   public final $anonfun$1=class scala/xml/Utility$$anonfun$1 of class scala/xml/Utility
  minor version: 0
  major version: 49
  Constant pool:
Asciz	SourceFile;
Asciz	Utility.scala;
Asciz	<clinit>;
Asciz	()V;
Asciz	Code;
Asciz	serialVersionUID;
Asciz	J;
Asciz	scala/xml/Utility$$anonfun$1;
class	scala/xml/Utility$$anonfun$1
NameAndType	serialVersionUID:J
Field	scala/xml/Utility$$anonfun$1.serialVersionUID:J
Asciz	c$1;
Asciz	Lscala/runtime/CharRef;;
Asciz	apply;
Asciz	()C;
Asciz	LineNumberTable;
NameAndType	c$1:Lscala/runtime/CharRef;
Field	scala/xml/Utility$$anonfun$1.c$1:Lscala/runtime/CharRef;
Asciz	scala/runtime/CharRef;
class	scala/runtime/CharRef
Asciz	elem;
Asciz	C;
NameAndType	elem:C
Field	scala/runtime/CharRef.elem:C
Asciz	apply$mcC$sp;
Asciz	()Ljava/lang/Object;;
NameAndType	apply:()C
Method	scala/xml/Utility$$anonfun$1.apply:()C
Asciz	scala/runtime/BoxesRunTime;
class	scala/runtime/BoxesRunTime
Asciz	boxToCharacter;
Asciz	(C)Ljava/lang/Character;;
NameAndType	boxToCharacter:(C)Ljava/lang/Character;
Method	scala/runtime/BoxesRunTime.boxToCharacter:(C)Ljava/lang/Character;
Asciz	<init>;
Asciz	(Lscala/runtime/CharRef;)V;
Asciz	scala/runtime/AbstractFunction0$mcC$sp;
class	scala/runtime/AbstractFunction0$mcC$sp
NameAndType	"<init>":()V
Method	scala/runtime/AbstractFunction0$mcC$sp."<init>":()V
Asciz	Scala;
Asciz	InnerClasses;
Asciz	scala/xml/Utility;
class	scala/xml/Utility
Asciz	$anonfun$1;
Asciz	java/io/Serializable;
class	java/io/Serializable

{
public static final long serialVersionUID;
  Signature: J

public final scala.runtime.CharRef c$1;
  Signature: Lscala/runtime/CharRef;

public static {};
  Signature: ()V
  Code:
   Stack=2, Locals=0, Args_size=0
	lconst_0
	putstatic	Field serialVersionUID:J
	return
  Labels:

public final char apply();
  Signature: ()C
  Code:
   Stack=1, Locals=1, Args_size=1
	aload_0
	getfield	Field c$1:Lscala/runtime/CharRef;
	getfield	Field scala/runtime/CharRef.elem:C
	ireturn
  Labels:

public char apply$mcC$sp();
  Signature: ()C
  Code:
   Stack=1, Locals=1, Args_size=1
	aload_0
	getfield	Field c$1:Lscala/runtime/CharRef;
	getfield	Field scala/runtime/CharRef.elem:C
	ireturn
  Labels:

public final java.lang.Object apply();
  Signature: ()Ljava/lang/Object;
  Code:
   Stack=1, Locals=2, Args_size=1
	aload_0
	invokevirtual	Method apply:()C
	istore_1
	iload_1
	invokestatic	Method scala/runtime/BoxesRunTime.boxToCharacter:(C)Ljava/lang/Character;
	areturn
  Labels:

public scala.xml.Utility$$anonfun$1(scala.runtime.CharRef);
  Signature: (Lscala/runtime/CharRef;)V
  Code:
   Stack=2, Locals=2, Args_size=2
	aload_0
	aload_1
	putfield	Field c$1:Lscala/runtime/CharRef;
	aload_0
	invokespecial	Method scala/runtime/AbstractFunction0$mcC$sp."<init>":()V
	return
  Labels:

}

