Compiled from "Utility.scala"
public final class scala.xml.Utility$ extends java.lang.Object implements scala.xml.parsing.TokenTests,scala.ScalaObject
  SourceFile: "Utility.scala"
  Scala: length = 0x
   
  InnerClass: 
   public final $anon$1=class scala/Predef$$anon$1 of class scala/Predef
   public final $anonfun$6=class scala/xml/Utility$$anonfun$6 of class scala/xml/Utility
   public final $anonfun$5=class scala/xml/Utility$$anonfun$5 of class scala/xml/Utility
   public final $anonfun$4=class scala/xml/Utility$$anonfun$4 of class scala/xml/Utility
   public final $anonfun$2=class scala/xml/Utility$$anonfun$2 of class scala/xml/Utility
   public final $anonfun$1=class scala/xml/Utility$$anonfun$1 of class scala/xml/Utility
   public final $anonfun$apply$6=class scala/Array$$anonfun$apply$6 of class scala/Array
   public abstract $less$colon$less=class scala/Predef$$less$colon$less of class scala/Predef
   public final $anonfun$sort$1=class scala/xml/Utility$$anonfun$sort$1 of class scala/xml/Utility
   public final $anonfun$trim$1=class scala/xml/Utility$$anonfun$trim$1 of class scala/xml/Utility
   public final $anonfun$toXML$1=class scala/xml/Utility$$anonfun$toXML$1 of class scala/xml/Utility
   public final $anonfun$escape$2=class scala/xml/Utility$$anonfun$escape$2 of class scala/xml/Utility
   public final $anonfun$escape$1=class scala/xml/Utility$$anonfun$escape$1 of class scala/xml/Utility
   public final $anonfun$getName$1=class scala/xml/Utility$$anonfun$getName$1 of class scala/xml/Utility
   public final $anonfun$unescape$1=class scala/xml/Utility$$anonfun$unescape$1 of class scala/xml/Utility
   public final $anonfun$trimProper$1=class scala/xml/Utility$$anonfun$trimProper$1 of class scala/xml/Utility
   public final $anonfun$appendQuoted$1=class scala/xml/Utility$$anonfun$appendQuoted$1 of class scala/xml/Utility
   public final $anonfun$sequenceToXML$2=class scala/xml/Utility$$anonfun$sequenceToXML$2 of class scala/xml/Utility
   public final $anonfun$sequenceToXML$1=class scala/xml/Utility$$anonfun$sequenceToXML$1 of class scala/xml/Utility
   public final $anonfun$collectNamespaces$3=class scala/xml/Utility$$anonfun$collectNamespaces$3 of class scala/xml/Utility
   public final $anonfun$collectNamespaces$2=class scala/xml/Utility$$anonfun$collectNamespaces$2 of class scala/xml/Utility
   public final $anonfun$collectNamespaces$1=class scala/xml/Utility$$anonfun$collectNamespaces$1 of class scala/xml/Utility
   public GenericCanBuildFrom=class scala/collection/generic/TraversableFactory$GenericCanBuildFrom of class scala/collection/generic/TraversableFactory
   public final $anonfun$appendEscapedQuoted$1=class scala/xml/Utility$$anonfun$appendEscapedQuoted$1 of class scala/xml/Utility
  minor version: 0
  major version: 49
  Constant pool:
Asciz	SourceFile;
Asciz	Utility.scala;
Asciz	Scala;
Asciz	MODULE$;
Asciz	Lscala/xml/Utility$;;
Asciz	<clinit>;
Asciz	()V;
Asciz	Code;
Asciz	scala/xml/Utility$;
class	scala/xml/Utility$
Asciz	<init>;
NameAndType	"<init>":()V
Method	scala/xml/Utility$."<init>":()V
Asciz	LineNumberTable;
Asciz	java/lang/Object;
class	java/lang/Object
Method	java/lang/Object."<init>":()V
NameAndType	MODULE$:Lscala/xml/Utility$;
Field	scala/xml/Utility$.MODULE$:Lscala/xml/Utility$;
Asciz	scala/xml/parsing/TokenTests$class;
class	scala/xml/parsing/TokenTests$class
Asciz	$init$;
Asciz	(Lscala/xml/parsing/TokenTests;)V;
NameAndType	$init$:(Lscala/xml/parsing/TokenTests;)V
Method	scala/xml/parsing/TokenTests$class.$init$:(Lscala/xml/parsing/TokenTests;)V
Asciz	gd2$1;
Asciz	(CLscala/collection/Seq;)Z;
Asciz	scala/xml/parsing/TokenTests;
class	scala/xml/parsing/TokenTests
Asciz	isNameStart;
Asciz	(C)Z;
NameAndType	isNameStart:(C)Z
InterfaceMethod	scala/xml/parsing/TokenTests.isNameStart:(C)Z
Asciz	gd1$1;
Asciz	(Lscala/xml/Comment;Z)Z;
Asciz	parseCharRef;
Asciz	(Lscala/Function0;Lscala/Function0;Lscala/Function1;)Ljava/lang/String;;
Asciz	scala/Function0;
class	scala/Function0
Asciz	apply;
Asciz	()Ljava/lang/Object;;
NameAndType	apply:()Ljava/lang/Object;
InterfaceMethod	scala/Function0.apply:()Ljava/lang/Object;
Asciz	scala/runtime/BoxesRunTime;
class	scala/runtime/BoxesRunTime
Asciz	unboxToChar;
Asciz	(Ljava/lang/Object;)C;
NameAndType	unboxToChar:(Ljava/lang/Object;)C
Method	scala/runtime/BoxesRunTime.unboxToChar:(Ljava/lang/Object;)C
int	120;
int	16;
int	10;
int	59;
Asciz	scala/collection/mutable/StringBuilder;
class	scala/collection/mutable/StringBuilder
Method	scala/collection/mutable/StringBuilder."<init>":()V
Asciz	character ';
String	character '
Asciz	append;
Asciz	(Ljava/lang/Object;)Lscala/collection/mutable/StringBuilder;;
NameAndType	append:(Ljava/lang/Object;)Lscala/collection/mutable/StringBuilder;
Method	scala/collection/mutable/StringBuilder.append:(Ljava/lang/Object;)Lscala/collection/mutable/StringBuilder;
Asciz	' not allowed in char ref\n;
String	' not allowed in char ref\n
Asciz	toString;
Asciz	()Ljava/lang/String;;
NameAndType	toString:()Ljava/lang/String;
Method	scala/collection/mutable/StringBuilder.toString:()Ljava/lang/String;
Asciz	scala/Function1;
class	scala/Function1
Asciz	(Ljava/lang/Object;)Ljava/lang/Object;;
NameAndType	apply:(Ljava/lang/Object;)Ljava/lang/Object;
InterfaceMethod	scala/Function1.apply:(Ljava/lang/Object;)Ljava/lang/Object;
Asciz	scala/MatchError;
class	scala/MatchError
Asciz	boxToCharacter;
Asciz	(C)Ljava/lang/Character;;
NameAndType	boxToCharacter:(C)Ljava/lang/Character;
Method	scala/runtime/BoxesRunTime.boxToCharacter:(C)Ljava/lang/Character;
Method	java/lang/Object.toString:()Ljava/lang/String;
Asciz	(Ljava/lang/String;)V;
NameAndType	"<init>":(Ljava/lang/String;)V
Method	scala/MatchError."<init>":(Ljava/lang/String;)V
int	36;
Asciz	java/lang/Character;
class	java/lang/Character
Asciz	digit;
Asciz	(CI)I;
NameAndType	digit:(CI)I
Method	java/lang/Character.digit:(CI)I
Asciz	hex char not allowed in decimal char ref\nDid you mean to write &#x ?;
String	hex char not allowed in decimal char ref\nDid you mean to write &#x ?
Asciz	java/lang/String;
class	java/lang/String
Asciz	scala/Predef$;
class	scala/Predef$
Asciz	Lscala/Predef$;;
NameAndType	MODULE$:Lscala/Predef$;
Field	scala/Predef$.MODULE$:Lscala/Predef$;
Asciz	wrapIntArray;
Asciz	([I)Lscala/collection/mutable/WrappedArray;;
NameAndType	wrapIntArray:([I)Lscala/collection/mutable/WrappedArray;
Method	scala/Predef$.wrapIntArray:([I)Lscala/collection/mutable/WrappedArray;
Asciz	scala/collection/SeqLike;
class	scala/collection/SeqLike
Asciz	length;
Asciz	()I;
NameAndType	length:()I
InterfaceMethod	scala/collection/SeqLike.length:()I
Asciz	scala/runtime/IntRef;
class	scala/runtime/IntRef
Asciz	(I)V;
NameAndType	"<init>":(I)V
Method	scala/runtime/IntRef."<init>":(I)V
Asciz	scala/collection/IterableLike;
class	scala/collection/IterableLike
Asciz	iterator;
Asciz	()Lscala/collection/Iterator;;
NameAndType	iterator:()Lscala/collection/Iterator;
InterfaceMethod	scala/collection/IterableLike.iterator:()Lscala/collection/Iterator;
Asciz	scala/Array$$anonfun$apply$6;
class	scala/Array$$anonfun$apply$6
Asciz	([ILscala/runtime/IntRef;)V;
NameAndType	"<init>":([ILscala/runtime/IntRef;)V
Method	scala/Array$$anonfun$apply$6."<init>":([ILscala/runtime/IntRef;)V
Asciz	scala/collection/Iterator;
class	scala/collection/Iterator
Asciz	foreach;
Asciz	(Lscala/Function1;)V;
NameAndType	foreach:(Lscala/Function1;)V
InterfaceMethod	scala/collection/Iterator.foreach:(Lscala/Function1;)V
Asciz	([III)V;
NameAndType	"<init>":([III)V
Method	java/lang/String."<init>":([III)V
Asciz	this;
Asciz	ch;
Asciz	Lscala/Function0;;
Asciz	nextch;
Asciz	reportSyntaxError;
Asciz	Lscala/Function1;;
Asciz	hex;
Asciz	Z;
Asciz	base;
Asciz	I;
Asciz	temp58;
Asciz	C;
Asciz	i;
Asciz	i$60;
Asciz	Lscala/runtime/IntRef;;
Asciz	array$60;
Asciz	[I;
Asciz	LocalVariableTable;
Asciz	(Lscala/Function0<Ljava/lang/Character;>;Lscala/Function0<Ljava/lang/Object;>;Lscala/Function1<Ljava/lang/String;Ljava/lang/Object;>;)Ljava/lang/String;;
Asciz	Signature;
Asciz	parseAttributeValue;
Asciz	(Ljava/lang/String;)Lscala/collection/Seq;;
Method	scala/collection/mutable/StringBuilder."<init>":()V
Asciz	scala/xml/NodeBuffer;
class	scala/xml/NodeBuffer
Method	scala/xml/NodeBuffer."<init>":()V
Asciz	scala/collection/immutable/StringOps;
class	scala/collection/immutable/StringOps
Method	scala/collection/immutable/StringOps."<init>":(Ljava/lang/String;)V
Asciz	scala/collection/IndexedSeqLike;
class	scala/collection/IndexedSeqLike
InterfaceMethod	scala/collection/IndexedSeqLike.iterator:()Lscala/collection/Iterator;
Asciz	hasNext;
Asciz	()Z;
NameAndType	hasNext:()Z
InterfaceMethod	scala/collection/Iterator.hasNext:()Z
Asciz	scala/runtime/CharRef;
class	scala/runtime/CharRef
Asciz	next;
NameAndType	next:()Ljava/lang/Object;
InterfaceMethod	scala/collection/Iterator.next:()Ljava/lang/Object;
Asciz	(C)V;
NameAndType	"<init>":(C)V
Method	scala/runtime/CharRef."<init>":(C)V
Asciz	elem;
NameAndType	elem:C
Field	scala/runtime/CharRef.elem:C
int	38;
int	35;
Asciz	scala/xml/Utility$$anonfun$4;
class	scala/xml/Utility$$anonfun$4
Asciz	(Lscala/runtime/CharRef;)V;
NameAndType	"<init>":(Lscala/runtime/CharRef;)V
Method	scala/xml/Utility$$anonfun$4."<init>":(Lscala/runtime/CharRef;)V
Asciz	scala/xml/Utility$$anonfun$5;
class	scala/xml/Utility$$anonfun$5
Asciz	(Lscala/collection/Iterator;Lscala/runtime/CharRef;)V;
NameAndType	"<init>":(Lscala/collection/Iterator;Lscala/runtime/CharRef;)V
Method	scala/xml/Utility$$anonfun$5."<init>":(Lscala/collection/Iterator;Lscala/runtime/CharRef;)V
Asciz	scala/xml/Utility$$anonfun$6;
class	scala/xml/Utility$$anonfun$6
Method	scala/xml/Utility$$anonfun$6."<init>":()V
NameAndType	parseCharRef:(Lscala/Function0;Lscala/Function0;Lscala/Function1;)Ljava/lang/String;
Method	scala/xml/Utility$.parseCharRef:(Lscala/Function0;Lscala/Function0;Lscala/Function1;)Ljava/lang/String;
Asciz	(Ljava/lang/String;)Lscala/collection/mutable/StringBuilder;;
NameAndType	append:(Ljava/lang/String;)Lscala/collection/mutable/StringBuilder;
Method	scala/collection/mutable/StringBuilder.append:(Ljava/lang/String;)Lscala/collection/mutable/StringBuilder;
Asciz	(C)Lscala/collection/mutable/StringBuilder;;
NameAndType	append:(C)Lscala/collection/mutable/StringBuilder;
Method	scala/collection/mutable/StringBuilder.append:(C)Lscala/collection/mutable/StringBuilder;
Method	scala/collection/mutable/StringBuilder.toString:()Ljava/lang/String;
Asciz	setLength;
NameAndType	setLength:(I)V
Method	scala/collection/mutable/StringBuilder.setLength:(I)V
Asciz	scala/xml/Utility$Escapes$;
class	scala/xml/Utility$Escapes$
Asciz	Lscala/xml/Utility$Escapes$;;
NameAndType	MODULE$:Lscala/xml/Utility$Escapes$;
Field	scala/xml/Utility$Escapes$.MODULE$:Lscala/xml/Utility$Escapes$;
Asciz	unescMap;
Asciz	()Lscala/collection/immutable/Map;;
NameAndType	unescMap:()Lscala/collection/immutable/Map;
Method	scala/xml/Utility$Escapes$.unescMap:()Lscala/collection/immutable/Map;
Asciz	scala/collection/MapLike;
class	scala/collection/MapLike
Asciz	get;
Asciz	(Ljava/lang/Object;)Lscala/Option;;
NameAndType	get:(Ljava/lang/Object;)Lscala/Option;
InterfaceMethod	scala/collection/MapLike.get:(Ljava/lang/Object;)Lscala/Option;
Asciz	scala/xml/Utility$$anonfun$unescape$1;
class	scala/xml/Utility$$anonfun$unescape$1
Asciz	(Lscala/collection/mutable/StringBuilder;)V;
NameAndType	"<init>":(Lscala/collection/mutable/StringBuilder;)V
Method	scala/xml/Utility$$anonfun$unescape$1."<init>":(Lscala/collection/mutable/StringBuilder;)V
Asciz	scala/Option;
class	scala/Option
Asciz	map;
Asciz	(Lscala/Function1;)Lscala/Option;;
NameAndType	map:(Lscala/Function1;)Lscala/Option;
Method	scala/Option.map:(Lscala/Function1;)Lscala/Option;
Asciz	scala/Predef$$anon$1;
class	scala/Predef$$anon$1
Method	scala/Predef$$anon$1."<init>":()V
Asciz	orNull;
Asciz	(Lscala/Predef$$less$colon$less;)Ljava/lang/Object;;
NameAndType	orNull:(Lscala/Predef$$less$colon$less;)Ljava/lang/Object;
Method	scala/Option.orNull:(Lscala/Predef$$less$colon$less;)Ljava/lang/Object;
Method	scala/collection/mutable/StringBuilder.length:()I
Asciz	scala/xml/Text$;
class	scala/xml/Text$
Asciz	Lscala/xml/Text$;;
NameAndType	MODULE$:Lscala/xml/Text$;
Field	scala/xml/Text$.MODULE$:Lscala/xml/Text$;
Asciz	(Ljava/lang/String;)Lscala/xml/Text;;
NameAndType	apply:(Ljava/lang/String;)Lscala/xml/Text;
Method	scala/xml/Text$.apply:(Ljava/lang/String;)Lscala/xml/Text;
Asciz	$plus$eq;
Asciz	(Ljava/lang/Object;)Lscala/collection/mutable/ArrayBuffer;;
NameAndType	$plus$eq:(Ljava/lang/Object;)Lscala/collection/mutable/ArrayBuffer;
Method	scala/xml/NodeBuffer.$plus$eq:(Ljava/lang/Object;)Lscala/collection/mutable/ArrayBuffer;
Asciz	scala/xml/EntityRef;
class	scala/xml/EntityRef
Method	scala/xml/EntityRef."<init>":(Ljava/lang/String;)V
Asciz	scala/runtime/BoxedUnit;
class	scala/runtime/BoxedUnit
Asciz	UNIT;
Asciz	Lscala/runtime/BoxedUnit;;
NameAndType	UNIT:Lscala/runtime/BoxedUnit;
Field	scala/runtime/BoxedUnit.UNIT:Lscala/runtime/BoxedUnit;
Asciz	scala/collection/mutable/ResizableArray;
class	scala/collection/mutable/ResizableArray
InterfaceMethod	scala/collection/mutable/ResizableArray.length:()I
Asciz	value;
Asciz	Ljava/lang/String;;
Asciz	theChar;
Asciz	it$1;
Asciz	Lscala/collection/Iterator;;
Asciz	rfb;
Asciz	Lscala/collection/mutable/StringBuilder;;
Asciz	ref;
Asciz	temp56;
Asciz	c$1;
Asciz	Lscala/runtime/CharRef;;
Asciz	sb;
Asciz	x;
Asciz	Lscala/xml/Text;;
Asciz	nb;
Asciz	Lscala/xml/NodeBuffer;;
Asciz	(Ljava/lang/String;)Lscala/collection/Seq<Lscala/xml/Node;>;;
Asciz	checkAttributeValue;
Asciz	(Ljava/lang/String;)Ljava/lang/String;;
Method	java/lang/String.length:()I
Asciz	charAt;
Asciz	(I)C;
NameAndType	charAt:(I)C
Method	java/lang/String.charAt:(I)C
Asciz	< not allowed in attribute value;
String	< not allowed in attribute value
Asciz	getName;
Asciz	(Ljava/lang/String;I)Ljava/lang/String;;
NameAndType	getName:(Ljava/lang/String;I)Ljava/lang/String;
Method	scala/xml/Utility$.getName:(Ljava/lang/String;I)Ljava/lang/String;
Asciz	malformed entity reference in attribute value [;
String	malformed entity reference in attribute value [
Asciz	];
String	]
Asciz	n;
Asciz	temp55;
Asciz	drop;
Asciz	(I)Ljava/lang/Object;;
NameAndType	drop:(I)Ljava/lang/Object;
InterfaceMethod	scala/collection/IndexedSeqLike.drop:(I)Ljava/lang/Object;
Asciz	scala/collection/Seq;
class	scala/collection/Seq
Asciz	scala/collection/Seq$;
class	scala/collection/Seq$
Asciz	Lscala/collection/Seq$;;
NameAndType	MODULE$:Lscala/collection/Seq$;
Field	scala/collection/Seq$.MODULE$:Lscala/collection/Seq$;
Asciz	unapplySeq;
Asciz	(Lscala/collection/Seq;)Lscala/Some;;
NameAndType	unapplySeq:(Lscala/collection/Seq;)Lscala/Some;
Method	scala/collection/Seq$.unapplySeq:(Lscala/collection/Seq;)Lscala/Some;
Asciz	scala/Some;
class	scala/Some
Asciz	Ljava/lang/Object;;
NameAndType	x:Ljava/lang/Object;
Field	scala/Some.x:Ljava/lang/Object;
Asciz	equals;
Asciz	(Ljava/lang/Object;)Z;
NameAndType	equals:(Ljava/lang/Object;)Z
Method	java/lang/Object.equals:(Ljava/lang/Object;)Z
Asciz	lengthCompare;
Asciz	(I)I;
NameAndType	lengthCompare:(I)I
InterfaceMethod	scala/collection/SeqLike.lengthCompare:(I)I
NameAndType	apply:(I)Ljava/lang/Object;
InterfaceMethod	scala/collection/SeqLike.apply:(I)Ljava/lang/Object;
Asciz	scala/collection/TraversableLike;
class	scala/collection/TraversableLike
InterfaceMethod	scala/collection/TraversableLike.drop:(I)Ljava/lang/Object;
NameAndType	gd2$1:(CLscala/collection/Seq;)Z
Method	scala/xml/Utility$.gd2$1:(CLscala/collection/Seq;)Z
Asciz	scala/xml/Utility$$anonfun$getName$1;
class	scala/xml/Utility$$anonfun$getName$1
Method	scala/xml/Utility$$anonfun$getName$1."<init>":()V
Asciz	takeWhile;
Asciz	(Lscala/Function1;)Ljava/lang/Object;;
NameAndType	takeWhile:(Lscala/Function1;)Ljava/lang/Object;
InterfaceMethod	scala/collection/IterableLike.takeWhile:(Lscala/Function1;)Ljava/lang/Object;
Asciz	mkString;
NameAndType	mkString:()Ljava/lang/String;
InterfaceMethod	scala/collection/TraversableLike.mkString:()Ljava/lang/String;
Asciz	;
String	
Method	java/lang/String.toString:()Ljava/lang/String;
Asciz	s;
Asciz	index;
Asciz	temp50;
Asciz	Lscala/collection/Seq;;
Asciz	temp51;
Asciz	Lscala/Some;;
Asciz	temp52;
Asciz	temp53;
Asciz	temp54;
Asciz	temp49;
Asciz	appendEscapedQuoted;
Asciz	(Ljava/lang/String;Lscala/collection/mutable/StringBuilder;)Lscala/collection/mutable/StringBuilder;;
int	34;
Asciz	augmentString;
Asciz	(Ljava/lang/String;)Lscala/collection/immutable/StringOps;;
NameAndType	augmentString:(Ljava/lang/String;)Lscala/collection/immutable/StringOps;
Method	scala/Predef$.augmentString:(Ljava/lang/String;)Lscala/collection/immutable/StringOps;
Asciz	scala/xml/Utility$$anonfun$appendEscapedQuoted$1;
class	scala/xml/Utility$$anonfun$appendEscapedQuoted$1
Method	scala/xml/Utility$$anonfun$appendEscapedQuoted$1."<init>":(Lscala/collection/mutable/StringBuilder;)V
InterfaceMethod	scala/collection/IndexedSeqLike.foreach:(Lscala/Function1;)V
Asciz	sb$3;
Asciz	appendQuoted;
Asciz	contains;
NameAndType	contains:(Ljava/lang/Object;)Z
InterfaceMethod	scala/collection/SeqLike.contains:(Ljava/lang/Object;)Z
int	39;
NameAndType	appendQuoted:(Ljava/lang/String;Lscala/collection/mutable/StringBuilder;)Lscala/collection/mutable/StringBuilder;
Method	scala/xml/Utility$.appendQuoted:(Ljava/lang/String;Lscala/collection/mutable/StringBuilder;)Lscala/collection/mutable/StringBuilder;
Asciz	s$1;
Asciz	sb0;
Asciz	hashCode;
Asciz	(Ljava/lang/String;Ljava/lang/String;IILscala/collection/Seq;)I;
int	41;
NameAndType	hashCode:()I
Method	java/lang/String.hashCode:()I
int	7;
int	53;
int	31;
Asciz	scala/xml/Node;
class	scala/xml/Node
Method	scala/xml/Node.hashCode:()I
Asciz	pre;
Asciz	label;
Asciz	attribHashCode;
Asciz	scpeHash;
Asciz	children;
Asciz	c;
Asciz	(Ljava/lang/String;Ljava/lang/String;IILscala/collection/Seq<Lscala/xml/Node;>;)I;
Asciz	prefix;
Asciz	(Ljava/lang/String;)Lscala/Option;;
int	58;
Asciz	indexOf;
NameAndType	indexOf:(I)I
Method	java/lang/String.indexOf:(I)I
Asciz	scala/None$;
class	scala/None$
Asciz	Lscala/None$;;
NameAndType	MODULE$:Lscala/None$;
Field	scala/None$.MODULE$:Lscala/None$;
Asciz	boxToInteger;
Asciz	(I)Ljava/lang/Integer;;
NameAndType	boxToInteger:(I)Ljava/lang/Integer;
Method	scala/runtime/BoxesRunTime.boxToInteger:(I)Ljava/lang/Integer;
Asciz	substring;
Asciz	(II)Ljava/lang/String;;
NameAndType	substring:(II)Ljava/lang/String;
Method	java/lang/String.substring:(II)Ljava/lang/String;
Asciz	(Ljava/lang/Object;)V;
NameAndType	"<init>":(Ljava/lang/Object;)V
Method	scala/Some."<init>":(Ljava/lang/Object;)V
Asciz	name;
Asciz	temp47;
Asciz	(Ljava/lang/String;)Lscala/Option<Ljava/lang/String;>;;
Asciz	sequenceToXML;
Asciz	(Lscala/collection/Seq;Lscala/xml/NamespaceBinding;Lscala/collection/mutable/StringBuilder;Z)V;
Asciz	isEmpty;
NameAndType	isEmpty:()Z
InterfaceMethod	scala/collection/IterableLike.isEmpty:()Z
Asciz	scala/xml/Utility$$anonfun$sequenceToXML$1;
class	scala/xml/Utility$$anonfun$sequenceToXML$1
Method	scala/xml/Utility$$anonfun$sequenceToXML$1."<init>":()V
Asciz	forall;
Asciz	(Lscala/Function1;)Z;
NameAndType	forall:(Lscala/Function1;)Z
InterfaceMethod	scala/collection/IterableLike.forall:(Lscala/Function1;)Z
Asciz	toXML;
Asciz	(Lscala/xml/Node;Lscala/xml/NamespaceBinding;Lscala/collection/mutable/StringBuilder;ZZZZ)Lscala/collection/mutable/StringBuilder;;
NameAndType	toXML:(Lscala/xml/Node;Lscala/xml/NamespaceBinding;Lscala/collection/mutable/StringBuilder;ZZZZ)Lscala/collection/mutable/StringBuilder;
Method	scala/xml/Utility$.toXML:(Lscala/xml/Node;Lscala/xml/NamespaceBinding;Lscala/collection/mutable/StringBuilder;ZZZZ)Lscala/collection/mutable/StringBuilder;
int	32;
Asciz	scala/xml/Utility$$anonfun$sequenceToXML$2;
class	scala/xml/Utility$$anonfun$sequenceToXML$2
Asciz	(Lscala/xml/NamespaceBinding;Lscala/collection/mutable/StringBuilder;)V;
NameAndType	"<init>":(Lscala/xml/NamespaceBinding;Lscala/collection/mutable/StringBuilder;)V
Method	scala/xml/Utility$$anonfun$sequenceToXML$2."<init>":(Lscala/xml/NamespaceBinding;Lscala/collection/mutable/StringBuilder;)V
InterfaceMethod	scala/collection/IterableLike.foreach:(Lscala/Function1;)V
Asciz	pscope$1;
Asciz	Lscala/xml/NamespaceBinding;;
Asciz	sb$2;
Asciz	stripComments;
Asciz	f;
Asciz	Lscala/xml/Node;;
Asciz	it;
Asciz	(Lscala/collection/Seq<Lscala/xml/Node;>;Lscala/xml/NamespaceBinding;Lscala/collection/mutable/StringBuilder;Z)V;
Asciz	scala/xml/Comment;
class	scala/xml/Comment
NameAndType	gd1$1:(Lscala/xml/Comment;Z)Z
Method	scala/xml/Utility$.gd1$1:(Lscala/xml/Comment;Z)Z
Asciz	buildString;
Asciz	(Lscala/collection/mutable/StringBuilder;)Lscala/collection/mutable/StringBuilder;;
NameAndType	buildString:(Lscala/collection/mutable/StringBuilder;)Lscala/collection/mutable/StringBuilder;
Method	scala/xml/Comment.buildString:(Lscala/collection/mutable/StringBuilder;)Lscala/collection/mutable/StringBuilder;
Method	scala/xml/Node.toString:()Ljava/lang/String;
Asciz	scala/xml/SpecialNode;
class	scala/xml/SpecialNode
Method	scala/xml/SpecialNode.buildString:(Lscala/collection/mutable/StringBuilder;)Lscala/collection/mutable/StringBuilder;
Asciz	scala/xml/Group;
class	scala/xml/Group
Asciz	nodes;
Asciz	()Lscala/collection/Seq;;
NameAndType	nodes:()Lscala/collection/Seq;
Method	scala/xml/Group.nodes:()Lscala/collection/Seq;
Asciz	scala/xml/Utility$$anonfun$toXML$1;
class	scala/xml/Utility$$anonfun$toXML$1
Asciz	(Lscala/xml/Node;Lscala/collection/mutable/StringBuilder;)V;
NameAndType	"<init>":(Lscala/xml/Node;Lscala/collection/mutable/StringBuilder;)V
Method	scala/xml/Utility$$anonfun$toXML$1."<init>":(Lscala/xml/Node;Lscala/collection/mutable/StringBuilder;)V
int	60;
Asciz	nameToString;
NameAndType	nameToString:(Lscala/collection/mutable/StringBuilder;)Lscala/collection/mutable/StringBuilder;
Method	scala/xml/Node.nameToString:(Lscala/collection/mutable/StringBuilder;)Lscala/collection/mutable/StringBuilder;
Asciz	attributes;
Asciz	()Lscala/xml/MetaData;;
NameAndType	attributes:()Lscala/xml/MetaData;
Method	scala/xml/Node.attributes:()Lscala/xml/MetaData;
Asciz	scala/xml/MetaData;
class	scala/xml/MetaData
Method	scala/xml/MetaData.buildString:(Lscala/collection/mutable/StringBuilder;)Lscala/collection/mutable/StringBuilder;
Asciz	scope;
Asciz	()Lscala/xml/NamespaceBinding;;
NameAndType	scope:()Lscala/xml/NamespaceBinding;
Method	scala/xml/Node.scope:()Lscala/xml/NamespaceBinding;
Asciz	scala/xml/NamespaceBinding;
class	scala/xml/NamespaceBinding
Asciz	(Lscala/collection/mutable/StringBuilder;Lscala/xml/NamespaceBinding;)V;
NameAndType	buildString:(Lscala/collection/mutable/StringBuilder;Lscala/xml/NamespaceBinding;)V
Method	scala/xml/NamespaceBinding.buildString:(Lscala/collection/mutable/StringBuilder;Lscala/xml/NamespaceBinding;)V
Asciz	child;
NameAndType	child:()Lscala/collection/Seq;
Method	scala/xml/Node.child:()Lscala/collection/Seq;
Asciz	 />;
String	 />
int	62;
NameAndType	sequenceToXML:(Lscala/collection/Seq;Lscala/xml/NamespaceBinding;Lscala/collection/mutable/StringBuilder;Z)V
Method	scala/xml/Utility$.sequenceToXML:(Lscala/collection/Seq;Lscala/xml/NamespaceBinding;Lscala/collection/mutable/StringBuilder;Z)V
Asciz	</;
String	</
Asciz	x$7;
Asciz	pscope;
Asciz	sb$1;
Asciz	stripComments$1;
Asciz	decodeEntities;
Asciz	preserveWhitespace;
Asciz	minimizeTags;
Asciz	temp42;
Asciz	Lscala/xml/Comment;;
Asciz	Lscala/xml/SpecialNode;;
Asciz	temp45;
Asciz	Lscala/xml/Group;;
Asciz	collectNamespaces;
Asciz	(Lscala/xml/Node;Lscala/collection/mutable/Set;)V;
Asciz	doCollectNamespaces;
NameAndType	doCollectNamespaces:()Z
Method	scala/xml/Node.doCollectNamespaces:()Z
Asciz	namespace;
NameAndType	namespace:()Ljava/lang/String;
Method	scala/xml/Node.namespace:()Ljava/lang/String;
Asciz	scala/collection/mutable/SetLike;
class	scala/collection/mutable/SetLike
Asciz	(Ljava/lang/Object;)Lscala/collection/mutable/SetLike;;
NameAndType	$plus$eq:(Ljava/lang/Object;)Lscala/collection/mutable/SetLike;
InterfaceMethod	scala/collection/mutable/SetLike.$plus$eq:(Ljava/lang/Object;)Lscala/collection/mutable/SetLike;
Asciz	scala/xml/Utility$$anonfun$collectNamespaces$2;
class	scala/xml/Utility$$anonfun$collectNamespaces$2
NameAndType	"<init>":(Lscala/xml/Node;Lscala/collection/mutable/Set;)V
Method	scala/xml/Utility$$anonfun$collectNamespaces$2."<init>":(Lscala/xml/Node;Lscala/collection/mutable/Set;)V
Asciz	scala/xml/Utility$$anonfun$collectNamespaces$3;
class	scala/xml/Utility$$anonfun$collectNamespaces$3
Asciz	(Lscala/collection/mutable/Set;)V;
NameAndType	"<init>":(Lscala/collection/mutable/Set;)V
Method	scala/xml/Utility$$anonfun$collectNamespaces$3."<init>":(Lscala/collection/mutable/Set;)V
Asciz	n$1;
Asciz	set$1;
Asciz	Lscala/collection/mutable/Set;;
Asciz	(Lscala/xml/Node;Lscala/collection/mutable/Set<Ljava/lang/String;>;)V;
Asciz	(Lscala/collection/Seq;)Lscala/collection/mutable/Set;;
Asciz	scala/collection/mutable/HashSet;
class	scala/collection/mutable/HashSet
Method	scala/collection/mutable/HashSet."<init>":()V
Asciz	scala/xml/Utility$$anonfun$collectNamespaces$1;
class	scala/xml/Utility$$anonfun$collectNamespaces$1
Method	scala/xml/Utility$$anonfun$collectNamespaces$1."<init>":()V
Asciz	foldLeft;
Asciz	(Ljava/lang/Object;Lscala/Function2;)Ljava/lang/Object;;
NameAndType	foldLeft:(Ljava/lang/Object;Lscala/Function2;)Ljava/lang/Object;
InterfaceMethod	scala/collection/TraversableLike.foldLeft:(Ljava/lang/Object;Lscala/Function2;)Ljava/lang/Object;
Asciz	scala/collection/mutable/Set;
class	scala/collection/mutable/Set
Asciz	(Lscala/collection/Seq<Lscala/xml/Node;>;)Lscala/collection/mutable/Set<Ljava/lang/String;>;;
Asciz	unescape;
Asciz	conforms;
Asciz	()Lscala/Predef$$less$colon$less;;
NameAndType	conforms:()Lscala/Predef$$less$colon$less;
Method	scala/Predef$.conforms:()Lscala/Predef$$less$colon$less;
Asciz	s$2;
Asciz	escape;
Asciz	scala/xml/Utility$$anonfun$escape$2;
class	scala/xml/Utility$$anonfun$escape$2
Method	scala/xml/Utility$$anonfun$escape$2."<init>":()V
InterfaceMethod	scala/collection/IndexedSeqLike.foldLeft:(Ljava/lang/Object;Lscala/Function2;)Ljava/lang/Object;
Asciz	text;
Asciz	text$1;
Asciz	sort;
Asciz	(Lscala/xml/Node;)Lscala/xml/Node;;
Asciz	scala/xml/Elem$;
class	scala/xml/Elem$
Asciz	Lscala/xml/Elem$;;
NameAndType	MODULE$:Lscala/xml/Elem$;
Field	scala/xml/Elem$.MODULE$:Lscala/xml/Elem$;
Asciz	(Lscala/xml/Node;)Lscala/Option;;
NameAndType	unapplySeq:(Lscala/xml/Node;)Lscala/Option;
Method	scala/xml/Elem$.unapplySeq:(Lscala/xml/Node;)Lscala/Option;
Method	scala/Option.isEmpty:()Z
NameAndType	get:()Ljava/lang/Object;
Method	scala/Option.get:()Ljava/lang/Object;
Asciz	scala/Tuple5;
class	scala/Tuple5
Asciz	_1;
NameAndType	_1:()Ljava/lang/Object;
Method	scala/Tuple5._1:()Ljava/lang/Object;
Asciz	_2;
NameAndType	_2:()Ljava/lang/Object;
Method	scala/Tuple5._2:()Ljava/lang/Object;
Asciz	_3;
NameAndType	_3:()Ljava/lang/Object;
Method	scala/Tuple5._3:()Ljava/lang/Object;
Asciz	_4;
NameAndType	_4:()Ljava/lang/Object;
Method	scala/Tuple5._4:()Ljava/lang/Object;
Asciz	_5;
NameAndType	_5:()Ljava/lang/Object;
Method	scala/Tuple5._5:()Ljava/lang/Object;
Asciz	(Lscala/xml/MetaData;)Lscala/xml/MetaData;;
NameAndType	sort:(Lscala/xml/MetaData;)Lscala/xml/MetaData;
Method	scala/xml/Utility$.sort:(Lscala/xml/MetaData;)Lscala/xml/MetaData;
Asciz	scala/xml/Utility$$anonfun$sort$1;
class	scala/xml/Utility$$anonfun$sort$1
Method	scala/xml/Utility$$anonfun$sort$1."<init>":()V
Asciz	scala/collection/generic/TraversableFactory$GenericCanBuildFrom;
class	scala/collection/generic/TraversableFactory$GenericCanBuildFrom
Asciz	(Lscala/collection/generic/TraversableFactory;)V;
NameAndType	"<init>":(Lscala/collection/generic/TraversableFactory;)V
Method	scala/collection/generic/TraversableFactory$GenericCanBuildFrom."<init>":(Lscala/collection/generic/TraversableFactory;)V
Asciz	(Lscala/Function1;Lscala/collection/generic/CanBuildFrom;)Ljava/lang/Object;;
NameAndType	map:(Lscala/Function1;Lscala/collection/generic/CanBuildFrom;)Ljava/lang/Object;
InterfaceMethod	scala/collection/TraversableLike.map:(Lscala/Function1;Lscala/collection/generic/CanBuildFrom;)Ljava/lang/Object;
Asciz	scala/xml/Elem;
class	scala/xml/Elem
Asciz	(Ljava/lang/String;Ljava/lang/String;Lscala/xml/MetaData;Lscala/xml/NamespaceBinding;Lscala/collection/Seq;)V;
NameAndType	"<init>":(Ljava/lang/String;Ljava/lang/String;Lscala/xml/MetaData;Lscala/xml/NamespaceBinding;Lscala/collection/Seq;)V
Method	scala/xml/Elem."<init>":(Ljava/lang/String;Ljava/lang/String;Lscala/xml/MetaData;Lscala/xml/NamespaceBinding;Lscala/collection/Seq;)V
Asciz	temp24;
Asciz	Lscala/Option;;
Asciz	temp25;
Asciz	Lscala/Tuple5;;
Asciz	temp28;
Asciz	Lscala/xml/MetaData;;
Asciz	temp30;
Asciz	temp26;
Asciz	temp27;
Asciz	temp29;
Asciz	scala/xml/Null$;
class	scala/xml/Null$
Asciz	Lscala/xml/Null$;;
NameAndType	MODULE$:Lscala/xml/Null$;
Field	scala/xml/Null$.MODULE$:Lscala/xml/Null$;
NameAndType	next:()Lscala/xml/MetaData;
Method	scala/xml/MetaData.next:()Lscala/xml/MetaData;
Asciz	key;
NameAndType	key:()Ljava/lang/String;
Method	scala/xml/MetaData.key:()Ljava/lang/String;
Asciz	scala/xml/Utility$$anonfun$1;
class	scala/xml/Utility$$anonfun$1
Method	scala/xml/Utility$$anonfun$1."<init>":(Ljava/lang/String;)V
Asciz	filter;
Asciz	(Lscala/Function1;)Lscala/xml/MetaData;;
NameAndType	filter:(Lscala/Function1;)Lscala/xml/MetaData;
Method	scala/xml/MetaData.filter:(Lscala/Function1;)Lscala/xml/MetaData;
Asciz	scala/xml/Utility$$anonfun$2;
class	scala/xml/Utility$$anonfun$2
Method	scala/xml/Utility$$anonfun$2."<init>":(Ljava/lang/String;)V
Asciz	append$default$2;
NameAndType	append$default$2:()Lscala/xml/NamespaceBinding;
Method	scala/xml/MetaData.append$default$2:()Lscala/xml/NamespaceBinding;
Asciz	(Lscala/xml/MetaData;Lscala/xml/NamespaceBinding;)Lscala/xml/MetaData;;
NameAndType	append:(Lscala/xml/MetaData;Lscala/xml/NamespaceBinding;)Lscala/xml/MetaData;
Method	scala/xml/MetaData.append:(Lscala/xml/MetaData;Lscala/xml/NamespaceBinding;)Lscala/xml/MetaData;
Asciz	copy;
NameAndType	copy:(Lscala/xml/MetaData;)Lscala/xml/MetaData;
Method	scala/xml/MetaData.copy:(Lscala/xml/MetaData;)Lscala/xml/MetaData;
Asciz	md;
Asciz	key$1;
Asciz	smaller;
Asciz	greater;
Asciz	qual$1;
Asciz	x$5;
Asciz	x$6;
Asciz	trimProper;
Asciz	(Lscala/xml/Node;)Lscala/collection/Seq;;
Asciz	unapply;
NameAndType	unapply:(Ljava/lang/Object;)Lscala/Option;
Method	scala/xml/Text$.unapply:(Ljava/lang/Object;)Lscala/Option;
Asciz	scala/xml/Utility$$anonfun$trimProper$1;
class	scala/xml/Utility$$anonfun$trimProper$1
Method	scala/xml/Utility$$anonfun$trimProper$1."<init>":()V
Asciz	flatMap;
NameAndType	flatMap:(Lscala/Function1;Lscala/collection/generic/CanBuildFrom;)Ljava/lang/Object;
InterfaceMethod	scala/collection/TraversableLike.flatMap:(Lscala/Function1;Lscala/collection/generic/CanBuildFrom;)Ljava/lang/Object;
Asciz	scala/xml/TextBuffer;
class	scala/xml/TextBuffer
Method	scala/xml/TextBuffer."<init>":()V
Asciz	wrapString;
Asciz	(Ljava/lang/String;)Lscala/collection/immutable/WrappedString;;
NameAndType	wrapString:(Ljava/lang/String;)Lscala/collection/immutable/WrappedString;
Method	scala/Predef$.wrapString:(Ljava/lang/String;)Lscala/collection/immutable/WrappedString;
Asciz	(Lscala/collection/Seq;)Lscala/xml/TextBuffer;;
NameAndType	append:(Lscala/collection/Seq;)Lscala/xml/TextBuffer;
Method	scala/xml/TextBuffer.append:(Lscala/collection/Seq;)Lscala/xml/TextBuffer;
Asciz	toText;
NameAndType	toText:()Lscala/collection/Seq;
Method	scala/xml/TextBuffer.toText:()Lscala/collection/Seq;
Asciz	temp21;
Asciz	temp11;
Asciz	temp12;
Asciz	temp17;
Asciz	temp13;
Asciz	temp14;
Asciz	temp15;
Asciz	temp16;
Asciz	temp19;
Asciz	temp20;
Asciz	(Lscala/xml/Node;)Lscala/collection/Seq<Lscala/xml/Node;>;;
Asciz	trim;
Asciz	scala/xml/Utility$$anonfun$trim$1;
class	scala/xml/Utility$$anonfun$trim$1
Method	scala/xml/Utility$$anonfun$trim$1."<init>":()V
Asciz	temp2;
Asciz	temp3;
Asciz	temp8;
Asciz	temp4;
Asciz	temp5;
Asciz	temp6;
Asciz	temp7;
Asciz	isAtomAndNotText;
Asciz	(Lscala/xml/Node;)Z;
Asciz	isAtom;
NameAndType	isAtom:()Z
Method	scala/xml/Node.isAtom:()Z
Asciz	scala/xml/Text;
class	scala/xml/Text
Asciz	sbToString;
Asciz	(Lscala/Function1;)Ljava/lang/String;;
Asciz	(Lscala/Function1<Lscala/collection/mutable/StringBuilder;Ljava/lang/Object;>;)Ljava/lang/String;;
Asciz	implicitSbToString;
Asciz	(Lscala/collection/mutable/StringBuilder;)Ljava/lang/String;;
Asciz	toXML$default$2;
Asciz	scala/xml/TopScope$;
class	scala/xml/TopScope$
Asciz	Lscala/xml/TopScope$;;
NameAndType	MODULE$:Lscala/xml/TopScope$;
Field	scala/xml/TopScope$.MODULE$:Lscala/xml/TopScope$;
Asciz	toXML$default$3;
Asciz	()Lscala/collection/mutable/StringBuilder;;
Asciz	toXML$default$4;
Asciz	toXML$default$5;
Asciz	toXML$default$6;
Asciz	toXML$default$7;
Asciz	sequenceToXML$default$2;
Asciz	sequenceToXML$default$3;
Asciz	sequenceToXML$default$4;
Asciz	checkPubID;
Asciz	(Ljava/lang/String;)Z;
Asciz	(Lscala/xml/parsing/TokenTests;Ljava/lang/String;)Z;
NameAndType	checkPubID:(Lscala/xml/parsing/TokenTests;Ljava/lang/String;)Z
Method	scala/xml/parsing/TokenTests$class.checkPubID:(Lscala/xml/parsing/TokenTests;Ljava/lang/String;)Z
Asciz	checkSysID;
NameAndType	checkSysID:(Lscala/xml/parsing/TokenTests;Ljava/lang/String;)Z
Method	scala/xml/parsing/TokenTests$class.checkSysID:(Lscala/xml/parsing/TokenTests;Ljava/lang/String;)Z
Asciz	isValidIANAEncoding;
Asciz	(Lscala/collection/Seq;)Z;
Asciz	(Lscala/xml/parsing/TokenTests;Lscala/collection/Seq;)Z;
NameAndType	isValidIANAEncoding:(Lscala/xml/parsing/TokenTests;Lscala/collection/Seq;)Z
Method	scala/xml/parsing/TokenTests$class.isValidIANAEncoding:(Lscala/xml/parsing/TokenTests;Lscala/collection/Seq;)Z
Asciz	ianaEncoding;
Asciz	isPubIDChar;
Asciz	(Lscala/xml/parsing/TokenTests;C)Z;
NameAndType	isPubIDChar:(Lscala/xml/parsing/TokenTests;C)Z
Method	scala/xml/parsing/TokenTests$class.isPubIDChar:(Lscala/xml/parsing/TokenTests;C)Z
Asciz	isName;
NameAndType	isName:(Lscala/xml/parsing/TokenTests;Ljava/lang/String;)Z
Method	scala/xml/parsing/TokenTests$class.isName:(Lscala/xml/parsing/TokenTests;Ljava/lang/String;)Z
NameAndType	isNameStart:(Lscala/xml/parsing/TokenTests;C)Z
Method	scala/xml/parsing/TokenTests$class.isNameStart:(Lscala/xml/parsing/TokenTests;C)Z
Asciz	isNameChar;
NameAndType	isNameChar:(Lscala/xml/parsing/TokenTests;C)Z
Method	scala/xml/parsing/TokenTests$class.isNameChar:(Lscala/xml/parsing/TokenTests;C)Z
Asciz	isAlphaDigit;
NameAndType	isAlphaDigit:(Lscala/xml/parsing/TokenTests;C)Z
Method	scala/xml/parsing/TokenTests$class.isAlphaDigit:(Lscala/xml/parsing/TokenTests;C)Z
Asciz	isAlpha;
NameAndType	isAlpha:(Lscala/xml/parsing/TokenTests;C)Z
Method	scala/xml/parsing/TokenTests$class.isAlpha:(Lscala/xml/parsing/TokenTests;C)Z
Asciz	isSpace;
NameAndType	isSpace:(Lscala/xml/parsing/TokenTests;Lscala/collection/Seq;)Z
Method	scala/xml/parsing/TokenTests$class.isSpace:(Lscala/xml/parsing/TokenTests;Lscala/collection/Seq;)Z
Asciz	cs;
NameAndType	isSpace:(Lscala/xml/parsing/TokenTests;C)Z
Method	scala/xml/parsing/TokenTests$class.isSpace:(Lscala/xml/parsing/TokenTests;C)Z
Asciz	InnerClasses;
Asciz	scala/Predef;
class	scala/Predef
Asciz	$anon$1;
Asciz	scala/xml/Utility;
class	scala/xml/Utility
Asciz	$anonfun$6;
Asciz	$anonfun$5;
Asciz	$anonfun$4;
Asciz	$anonfun$2;
Asciz	$anonfun$1;
Asciz	scala/Array;
class	scala/Array
Asciz	$anonfun$apply$6;
Asciz	scala/Predef$$less$colon$less;
class	scala/Predef$$less$colon$less
Asciz	$less$colon$less;
Asciz	$anonfun$sort$1;
Asciz	$anonfun$trim$1;
Asciz	$anonfun$toXML$1;
Asciz	$anonfun$escape$2;
Asciz	scala/xml/Utility$$anonfun$escape$1;
class	scala/xml/Utility$$anonfun$escape$1
Asciz	$anonfun$escape$1;
Asciz	$anonfun$getName$1;
Asciz	$anonfun$unescape$1;
Asciz	$anonfun$trimProper$1;
Asciz	scala/xml/Utility$$anonfun$appendQuoted$1;
class	scala/xml/Utility$$anonfun$appendQuoted$1
Asciz	$anonfun$appendQuoted$1;
Asciz	$anonfun$sequenceToXML$2;
Asciz	$anonfun$sequenceToXML$1;
Asciz	$anonfun$collectNamespaces$3;
Asciz	$anonfun$collectNamespaces$2;
Asciz	$anonfun$collectNamespaces$1;
Asciz	scala/collection/generic/TraversableFactory;
class	scala/collection/generic/TraversableFactory
Asciz	GenericCanBuildFrom;
Asciz	$anonfun$appendEscapedQuoted$1;
Asciz	scala/ScalaObject;
class	scala/ScalaObject

{
public static final scala.xml.Utility$ MODULE$;
  Signature: Lscala/xml/Utility$;

public static {};
  Signature: ()V
  Code:
   Stack=1, Locals=0, Args_size=0
	new	class scala/xml/Utility$
	invokespecial	Method "<init>":()V
	return
  Labels:

private scala.xml.Utility$();
  Signature: ()V
  Code:
   Stack=1, Locals=1, Args_size=1
	aload_0
	invokespecial	Method java/lang/Object."<init>":()V
	aload_0
	putstatic	Field MODULE$:Lscala/xml/Utility$;
	aload_0
	invokestatic	Method scala/xml/parsing/TokenTests$class.$init$:(Lscala/xml/parsing/TokenTests;)V
	return
  Labels:

private final boolean gd2$1(char, scala.collection.Seq);
  Signature: (CLscala/collection/Seq;)Z
  Code:
   Stack=2, Locals=3, Args_size=3
	aload_0
	iload_1
	invokeinterface	InterfaceMethod scala/xml/parsing/TokenTests.isNameStart:(C)Z
	ireturn
  Labels:

private final boolean gd1$1(scala.xml.Comment, boolean);
  Signature: (Lscala/xml/Comment;Z)Z
  Code:
   Stack=1, Locals=3, Args_size=3
	iload_2
	ifeq	l1 // iconst_1
	iconst_0
	goto	l2 // ireturn
l1	iconst_1
l2	ireturn
  Labels:
   	l1 = 8 // iconst_1
   	l2 = 9 // ireturn

public java.lang.String parseCharRef(scala.Function0, scala.Function0, scala.Function1);
  Signature: (Lscala/Function0;Lscala/Function0;Lscala/Function1;)Ljava/lang/String;
  Code:
   Stack=7, Locals=13, Args_size=4
	aload_1
	invokeinterface	InterfaceMethod scala/Function0.apply:()Ljava/lang/Object;
	invokestatic	Method scala/runtime/BoxesRunTime.unboxToChar:(Ljava/lang/Object;)C
	ldc	int 120
	if_icmpne	l1 // iconst_0
	aload_2
	invokeinterface	InterfaceMethod scala/Function0.apply:()Ljava/lang/Object;
	pop
	iconst_1
	ifeq	l1 // iconst_0
	iconst_1
	goto	l2 // istore
l1	iconst_0
l2	istore	4
	iload	4
	ifeq	l3 // ldc
	ldc	int 16
	goto	l4 // istore
l3	ldc	int 10
l4	istore	6
	iconst_0
	istore	9
l13	aload_1
	invokeinterface	InterfaceMethod scala/Function0.apply:()Ljava/lang/Object;
	invokestatic	Method scala/runtime/BoxesRunTime.unboxToChar:(Ljava/lang/Object;)C
	ldc	int 59
	if_icmpeq	l5 // new
	aload_1
	invokeinterface	InterfaceMethod scala/Function0.apply:()Ljava/lang/Object;
	invokestatic	Method scala/runtime/BoxesRunTime.unboxToChar:(Ljava/lang/Object;)C
	istore	8
	iload	8
	lookupswitch{ //22
		48: 789;
		49: 769;
		50: 749;
		51: 729;
		52: 709;
		53: 689;
		54: 669;
		55: 649;
		56: 629;
		57: 609;
		65: 543;
		66: 523;
		67: 503;
		68: 483;
		69: 463;
		70: 443;
		97: 423;
		98: 403;
		99: 383;
		100: 363;
		101: 343;
		102: 323;
		default: 264 }
	iconst_1
	ifeq	l6 // new
	aload_3
	new	class scala/collection/mutable/StringBuilder
	dup
	invokespecial	Method scala/collection/mutable/StringBuilder."<init>":()V
	ldc	String character '
	invokevirtual	Method scala/collection/mutable/StringBuilder.append:(Ljava/lang/Object;)Lscala/collection/mutable/StringBuilder;
	aload_1
	invokeinterface	InterfaceMethod scala/Function0.apply:()Ljava/lang/Object;
	invokevirtual	Method scala/collection/mutable/StringBuilder.append:(Ljava/lang/Object;)Lscala/collection/mutable/StringBuilder;
	ldc	String ' not allowed in char ref\n
	invokevirtual	Method scala/collection/mutable/StringBuilder.append:(Ljava/lang/Object;)Lscala/collection/mutable/StringBuilder;
	invokevirtual	Method scala/collection/mutable/StringBuilder.toString:()Ljava/lang/String;
	invokeinterface	InterfaceMethod scala/Function1.apply:(Ljava/lang/Object;)Ljava/lang/Object;
	pop
	goto	l7 // aload_2
l6	new	class scala/MatchError
	dup
	iload	8
	invokestatic	Method scala/runtime/BoxesRunTime.boxToCharacter:(C)Ljava/lang/Character;
	invokevirtual	Method java/lang/Object.toString:()Ljava/lang/String;
	invokespecial	Method scala/MatchError."<init>":(Ljava/lang/String;)V
	athrow
	iconst_1
	ifne	l8 // iload
	new	class scala/MatchError
	dup
	iload	8
	invokestatic	Method scala/runtime/BoxesRunTime.boxToCharacter:(C)Ljava/lang/Character;
	invokevirtual	Method java/lang/Object.toString:()Ljava/lang/String;
	invokespecial	Method scala/MatchError."<init>":(Ljava/lang/String;)V
	athrow
	iconst_1
	ifne	l8 // iload
	new	class scala/MatchError
	dup
	iload	8
	invokestatic	Method scala/runtime/BoxesRunTime.boxToCharacter:(C)Ljava/lang/Character;
	invokevirtual	Method java/lang/Object.toString:()Ljava/lang/String;
	invokespecial	Method scala/MatchError."<init>":(Ljava/lang/String;)V
	athrow
	iconst_1
	ifne	l8 // iload
	new	class scala/MatchError
	dup
	iload	8
	invokestatic	Method scala/runtime/BoxesRunTime.boxToCharacter:(C)Ljava/lang/Character;
	invokevirtual	Method java/lang/Object.toString:()Ljava/lang/String;
	invokespecial	Method scala/MatchError."<init>":(Ljava/lang/String;)V
	athrow
	iconst_1
	ifne	l8 // iload
	new	class scala/MatchError
	dup
	iload	8
	invokestatic	Method scala/runtime/BoxesRunTime.boxToCharacter:(C)Ljava/lang/Character;
	invokevirtual	Method java/lang/Object.toString:()Ljava/lang/String;
	invokespecial	Method scala/MatchError."<init>":(Ljava/lang/String;)V
	athrow
	iconst_1
	ifne	l8 // iload
	new	class scala/MatchError
	dup
	iload	8
	invokestatic	Method scala/runtime/BoxesRunTime.boxToCharacter:(C)Ljava/lang/Character;
	invokevirtual	Method java/lang/Object.toString:()Ljava/lang/String;
	invokespecial	Method scala/MatchError."<init>":(Ljava/lang/String;)V
	athrow
	iconst_1
	ifne	l8 // iload
	new	class scala/MatchError
	dup
	iload	8
	invokestatic	Method scala/runtime/BoxesRunTime.boxToCharacter:(C)Ljava/lang/Character;
	invokevirtual	Method java/lang/Object.toString:()Ljava/lang/String;
	invokespecial	Method scala/MatchError."<init>":(Ljava/lang/String;)V
	athrow
	iconst_1
	ifne	l8 // iload
	new	class scala/MatchError
	dup
	iload	8
	invokestatic	Method scala/runtime/BoxesRunTime.boxToCharacter:(C)Ljava/lang/Character;
	invokevirtual	Method java/lang/Object.toString:()Ljava/lang/String;
	invokespecial	Method scala/MatchError."<init>":(Ljava/lang/String;)V
	athrow
	iconst_1
	ifne	l8 // iload
	new	class scala/MatchError
	dup
	iload	8
	invokestatic	Method scala/runtime/BoxesRunTime.boxToCharacter:(C)Ljava/lang/Character;
	invokevirtual	Method java/lang/Object.toString:()Ljava/lang/String;
	invokespecial	Method scala/MatchError."<init>":(Ljava/lang/String;)V
	athrow
	iconst_1
	ifne	l8 // iload
	new	class scala/MatchError
	dup
	iload	8
	invokestatic	Method scala/runtime/BoxesRunTime.boxToCharacter:(C)Ljava/lang/Character;
	invokevirtual	Method java/lang/Object.toString:()Ljava/lang/String;
	invokespecial	Method scala/MatchError."<init>":(Ljava/lang/String;)V
	athrow
	iconst_1
	ifne	l8 // iload
	new	class scala/MatchError
	dup
	iload	8
	invokestatic	Method scala/runtime/BoxesRunTime.boxToCharacter:(C)Ljava/lang/Character;
	invokevirtual	Method java/lang/Object.toString:()Ljava/lang/String;
	invokespecial	Method scala/MatchError."<init>":(Ljava/lang/String;)V
	athrow
	iconst_1
	ifne	l8 // iload
	new	class scala/MatchError
	dup
	iload	8
	invokestatic	Method scala/runtime/BoxesRunTime.boxToCharacter:(C)Ljava/lang/Character;
	invokevirtual	Method java/lang/Object.toString:()Ljava/lang/String;
	invokespecial	Method scala/MatchError."<init>":(Ljava/lang/String;)V
	athrow
	iconst_1
	ifeq	l9 // new
l8	iload	4
	ifeq	l10 // aload_3
	iload	9
	iload	6
	imul
	aload_1
	invokeinterface	InterfaceMethod scala/Function0.apply:()Ljava/lang/Object;
	invokestatic	Method scala/runtime/BoxesRunTime.unboxToChar:(Ljava/lang/Object;)C
	istore	5
	iload	5
	ldc	int 36
	invokestatic	Method java/lang/Character.digit:(CI)I
	iadd
	istore	9
	goto	l7 // aload_2
l10	aload_3
	ldc	String hex char not allowed in decimal char ref\nDid you mean to write &#x ?
	invokeinterface	InterfaceMethod scala/Function1.apply:(Ljava/lang/Object;)Ljava/lang/Object;
	pop
	goto	l7 // aload_2
l9	new	class scala/MatchError
	dup
	iload	8
	invokestatic	Method scala/runtime/BoxesRunTime.boxToCharacter:(C)Ljava/lang/Character;
	invokevirtual	Method java/lang/Object.toString:()Ljava/lang/String;
	invokespecial	Method scala/MatchError."<init>":(Ljava/lang/String;)V
	athrow
	iconst_1
	ifne	l11 // iload
	new	class scala/MatchError
	dup
	iload	8
	invokestatic	Method scala/runtime/BoxesRunTime.boxToCharacter:(C)Ljava/lang/Character;
	invokevirtual	Method java/lang/Object.toString:()Ljava/lang/String;
	invokespecial	Method scala/MatchError."<init>":(Ljava/lang/String;)V
	athrow
	iconst_1
	ifne	l11 // iload
	new	class scala/MatchError
	dup
	iload	8
	invokestatic	Method scala/runtime/BoxesRunTime.boxToCharacter:(C)Ljava/lang/Character;
	invokevirtual	Method java/lang/Object.toString:()Ljava/lang/String;
	invokespecial	Method scala/MatchError."<init>":(Ljava/lang/String;)V
	athrow
	iconst_1
	ifne	l11 // iload
	new	class scala/MatchError
	dup
	iload	8
	invokestatic	Method scala/runtime/BoxesRunTime.boxToCharacter:(C)Ljava/lang/Character;
	invokevirtual	Method java/lang/Object.toString:()Ljava/lang/String;
	invokespecial	Method scala/MatchError."<init>":(Ljava/lang/String;)V
	athrow
	iconst_1
	ifne	l11 // iload
	new	class scala/MatchError
	dup
	iload	8
	invokestatic	Method scala/runtime/BoxesRunTime.boxToCharacter:(C)Ljava/lang/Character;
	invokevirtual	Method java/lang/Object.toString:()Ljava/lang/String;
	invokespecial	Method scala/MatchError."<init>":(Ljava/lang/String;)V
	athrow
	iconst_1
	ifne	l11 // iload
	new	class scala/MatchError
	dup
	iload	8
	invokestatic	Method scala/runtime/BoxesRunTime.boxToCharacter:(C)Ljava/lang/Character;
	invokevirtual	Method java/lang/Object.toString:()Ljava/lang/String;
	invokespecial	Method scala/MatchError."<init>":(Ljava/lang/String;)V
	athrow
	iconst_1
	ifne	l11 // iload
	new	class scala/MatchError
	dup
	iload	8
	invokestatic	Method scala/runtime/BoxesRunTime.boxToCharacter:(C)Ljava/lang/Character;
	invokevirtual	Method java/lang/Object.toString:()Ljava/lang/String;
	invokespecial	Method scala/MatchError."<init>":(Ljava/lang/String;)V
	athrow
	iconst_1
	ifne	l11 // iload
	new	class scala/MatchError
	dup
	iload	8
	invokestatic	Method scala/runtime/BoxesRunTime.boxToCharacter:(C)Ljava/lang/Character;
	invokevirtual	Method java/lang/Object.toString:()Ljava/lang/String;
	invokespecial	Method scala/MatchError."<init>":(Ljava/lang/String;)V
	athrow
	iconst_1
	ifne	l11 // iload
	new	class scala/MatchError
	dup
	iload	8
	invokestatic	Method scala/runtime/BoxesRunTime.boxToCharacter:(C)Ljava/lang/Character;
	invokevirtual	Method java/lang/Object.toString:()Ljava/lang/String;
	invokespecial	Method scala/MatchError."<init>":(Ljava/lang/String;)V
	athrow
	iconst_1
	ifne	l11 // iload
	new	class scala/MatchError
	dup
	iload	8
	invokestatic	Method scala/runtime/BoxesRunTime.boxToCharacter:(C)Ljava/lang/Character;
	invokevirtual	Method java/lang/Object.toString:()Ljava/lang/String;
	invokespecial	Method scala/MatchError."<init>":(Ljava/lang/String;)V
	athrow
	iconst_1
	ifeq	l12 // new
l11	iload	9
	iload	6
	imul
	aload_1
	invokeinterface	InterfaceMethod scala/Function0.apply:()Ljava/lang/Object;
	invokestatic	Method scala/runtime/BoxesRunTime.unboxToChar:(Ljava/lang/Object;)C
	istore	7
	iload	7
	ldc	int 36
	invokestatic	Method java/lang/Character.digit:(CI)I
	iadd
	istore	9
l7	aload_2
	invokeinterface	InterfaceMethod scala/Function0.apply:()Ljava/lang/Object;
	pop
	goto	l13 // aload_1
l12	new	class scala/MatchError
	dup
	iload	8
	invokestatic	Method scala/runtime/BoxesRunTime.boxToCharacter:(C)Ljava/lang/Character;
	invokevirtual	Method java/lang/Object.toString:()Ljava/lang/String;
	invokespecial	Method scala/MatchError."<init>":(Ljava/lang/String;)V
	athrow
l5	new	class java/lang/String
	dup
	getstatic	Field scala/Predef$.MODULE$:Lscala/Predef$;
	iconst_0
	newarray int
	invokevirtual	Method scala/Predef$.wrapIntArray:([I)Lscala/collection/mutable/WrappedArray;
	astore	10
	aload	10
	invokeinterface	InterfaceMethod scala/collection/SeqLike.length:()I
	iconst_1
	iadd
	newarray int
	astore	12
	aload	12
	iconst_0
	iload	9
	iastore
	new	class scala/runtime/IntRef
	dup
	iconst_1
	invokespecial	Method scala/runtime/IntRef."<init>":(I)V
	astore	11
	aload	10
	invokeinterface	InterfaceMethod scala/collection/IterableLike.iterator:()Lscala/collection/Iterator;
	new	class scala/Array$$anonfun$apply$6
	dup
	aload	12
	aload	11
	invokespecial	Method scala/Array$$anonfun$apply$6."<init>":([ILscala/runtime/IntRef;)V
	invokeinterface	InterfaceMethod scala/collection/Iterator.foreach:(Lscala/Function1;)V
	aload	12
	iconst_0
	iconst_1
	invokespecial	Method java/lang/String."<init>":([III)V
	areturn
  Labels:
   	l1 = 29 // iconst_0
   	l2 = 30 // istore
   	l3 = 42 // ldc
   	l4 = 44 // istore
   	l13 = 49 // aload_1
   	l6 = 307 // new
   	l8 = 547 // iload
   	l10 = 581 // aload_3
   	l9 = 593 // new
   	l11 = 793 // iload
   	l7 = 819 // aload_2
   	l12 = 829 // new
   	l5 = 845 // new
  LocalVariableTable: 
   Start  Length  Slot  Name   Signature
   0      920      0    this       Lscala/xml/Utility$;
   0      920      1    ch       Lscala/Function0;
   0      920      2    nextch       Lscala/Function0;
   0      920      3    reportSyntaxError       Lscala/Function1;
   32      887      4    hex       Z
   46      873      6    base       I
   74      771      8    temp58       C
   49      870      9    i       I
   889      25      11    i$60       Lscala/runtime/IntRef;
   873      41      12    array$60       [I

  Signature: length = 0x2
   00 FFFFFF99 

public scala.collection.Seq parseAttributeValue(java.lang.String);
  Signature: (Ljava/lang/String;)Lscala/collection/Seq;
  Code:
   Stack=6, Locals=11, Args_size=2
	new	class scala/collection/mutable/StringBuilder
	dup
	invokespecial	Method scala/collection/mutable/StringBuilder."<init>":()V
	astore	8
	aconst_null
	astore	4
	new	class scala/xml/NodeBuffer
	dup
	invokespecial	Method scala/xml/NodeBuffer."<init>":()V
	astore	10
	new	class scala/collection/immutable/StringOps
	dup
	aload_1
	invokespecial	Method scala/collection/immutable/StringOps."<init>":(Ljava/lang/String;)V
	invokeinterface	InterfaceMethod scala/collection/IndexedSeqLike.iterator:()Lscala/collection/Iterator;
	astore_3
l12	aload_3
	invokeinterface	InterfaceMethod scala/collection/Iterator.hasNext:()Z
	ifeq	l1 // aload
	new	class scala/runtime/CharRef
	dup
	aload_3
	invokeinterface	InterfaceMethod scala/collection/Iterator.next:()Ljava/lang/Object;
	invokestatic	Method scala/runtime/BoxesRunTime.unboxToChar:(Ljava/lang/Object;)C
	invokespecial	Method scala/runtime/CharRef."<init>":(C)V
	astore	7
	aload	7
	getfield	Field scala/runtime/CharRef.elem:C
	ldc	int 38
	if_icmpne	l2 // aload
	aload	7
	aload_3
	invokeinterface	InterfaceMethod scala/collection/Iterator.next:()Ljava/lang/Object;
	invokestatic	Method scala/runtime/BoxesRunTime.unboxToChar:(Ljava/lang/Object;)C
	putfield	Field scala/runtime/CharRef.elem:C
	aload	7
	getfield	Field scala/runtime/CharRef.elem:C
	ldc	int 35
	if_icmpne	l3 // aload
	aload	7
	aload_3
	invokeinterface	InterfaceMethod scala/collection/Iterator.next:()Ljava/lang/Object;
	invokestatic	Method scala/runtime/BoxesRunTime.unboxToChar:(Ljava/lang/Object;)C
	putfield	Field scala/runtime/CharRef.elem:C
	aload_0
	new	class scala/xml/Utility$$anonfun$4
	dup
	aload	7
	invokespecial	Method scala/xml/Utility$$anonfun$4."<init>":(Lscala/runtime/CharRef;)V
	new	class scala/xml/Utility$$anonfun$5
	dup
	aload_3
	aload	7
	invokespecial	Method scala/xml/Utility$$anonfun$5."<init>":(Lscala/collection/Iterator;Lscala/runtime/CharRef;)V
	new	class scala/xml/Utility$$anonfun$6
	dup
	invokespecial	Method scala/xml/Utility$$anonfun$6."<init>":()V
	invokevirtual	Method parseCharRef:(Lscala/Function0;Lscala/Function0;Lscala/Function1;)Ljava/lang/String;
	astore_2
	aload	8
	aload_2
	invokevirtual	Method scala/collection/mutable/StringBuilder.append:(Ljava/lang/String;)Lscala/collection/mutable/StringBuilder;
	goto	l4 // pop
l3	aload	4
	ifnonnull	l5 // aload
	new	class scala/collection/mutable/StringBuilder
	dup
	invokespecial	Method scala/collection/mutable/StringBuilder."<init>":()V
	astore	4
l5	aload	4
	aload	7
	getfield	Field scala/runtime/CharRef.elem:C
	invokevirtual	Method scala/collection/mutable/StringBuilder.append:(C)Lscala/collection/mutable/StringBuilder;
	pop
	aload	7
	aload_3
	invokeinterface	InterfaceMethod scala/collection/Iterator.next:()Ljava/lang/Object;
	invokestatic	Method scala/runtime/BoxesRunTime.unboxToChar:(Ljava/lang/Object;)C
	putfield	Field scala/runtime/CharRef.elem:C
l7	aload	7
	getfield	Field scala/runtime/CharRef.elem:C
	ldc	int 59
	if_icmpeq	l6 // aload
	aload	4
	aload	7
	getfield	Field scala/runtime/CharRef.elem:C
	invokevirtual	Method scala/collection/mutable/StringBuilder.append:(C)Lscala/collection/mutable/StringBuilder;
	pop
	aload	7
	aload_3
	invokeinterface	InterfaceMethod scala/collection/Iterator.next:()Ljava/lang/Object;
	invokestatic	Method scala/runtime/BoxesRunTime.unboxToChar:(Ljava/lang/Object;)C
	putfield	Field scala/runtime/CharRef.elem:C
	goto	l7 // aload
l6	aload	4
	invokevirtual	Method scala/collection/mutable/StringBuilder.toString:()Ljava/lang/String;
	astore	5
	aload	4
	iconst_0
	invokevirtual	Method scala/collection/mutable/StringBuilder.setLength:(I)V
	getstatic	Field scala/xml/Utility$Escapes$.MODULE$:Lscala/xml/Utility$Escapes$;
	invokevirtual	Method scala/xml/Utility$Escapes$.unescMap:()Lscala/collection/immutable/Map;
	aload	5
	invokeinterface	InterfaceMethod scala/collection/MapLike.get:(Ljava/lang/Object;)Lscala/Option;
	new	class scala/xml/Utility$$anonfun$unescape$1
	dup
	aload	8
	invokespecial	Method scala/xml/Utility$$anonfun$unescape$1."<init>":(Lscala/collection/mutable/StringBuilder;)V
	invokevirtual	Method scala/Option.map:(Lscala/Function1;)Lscala/Option;
	new	class scala/Predef$$anon$1
	dup
	invokespecial	Method scala/Predef$$anon$1."<init>":()V
	invokevirtual	Method scala/Option.orNull:(Lscala/Predef$$less$colon$less;)Ljava/lang/Object;
	checkcast	class scala/collection/mutable/StringBuilder
	astore	6
	aload	6
	ifnonnull	l8 // iconst_1
	iconst_1
	ifeq	l9 // new
	aload	8
	invokevirtual	Method scala/collection/mutable/StringBuilder.length:()I
	iconst_0
	if_icmple	l10 // aload
	aload	10
	getstatic	Field scala/xml/Text$.MODULE$:Lscala/xml/Text$;
	aload	8
	invokevirtual	Method scala/collection/mutable/StringBuilder.toString:()Ljava/lang/String;
	invokevirtual	Method scala/xml/Text$.apply:(Ljava/lang/String;)Lscala/xml/Text;
	invokevirtual	Method scala/xml/NodeBuffer.$plus$eq:(Ljava/lang/Object;)Lscala/collection/mutable/ArrayBuffer;
	pop
	aload	8
	iconst_0
	invokevirtual	Method scala/collection/mutable/StringBuilder.setLength:(I)V
l10	aload	10
	new	class scala/xml/EntityRef
	dup
	aload	8
	invokevirtual	Method scala/collection/mutable/StringBuilder.toString:()Ljava/lang/String;
	invokespecial	Method scala/xml/EntityRef."<init>":(Ljava/lang/String;)V
	invokevirtual	Method scala/xml/NodeBuffer.$plus$eq:(Ljava/lang/Object;)Lscala/collection/mutable/ArrayBuffer;
	goto	l4 // pop
l9	new	class scala/MatchError
	dup
	aload	6
	invokevirtual	Method scala/collection/mutable/StringBuilder.toString:()Ljava/lang/String;
	invokespecial	Method scala/MatchError."<init>":(Ljava/lang/String;)V
	athrow
l8	iconst_1
	ifeq	l11 // new
	getstatic	Field scala/runtime/BoxedUnit.UNIT:Lscala/runtime/BoxedUnit;
	goto	l4 // pop
l11	new	class scala/MatchError
	dup
	aload	6
	invokevirtual	Method scala/collection/mutable/StringBuilder.toString:()Ljava/lang/String;
	invokespecial	Method scala/MatchError."<init>":(Ljava/lang/String;)V
	athrow
l2	aload	8
	aload	7
	getfield	Field scala/runtime/CharRef.elem:C
	invokevirtual	Method scala/collection/mutable/StringBuilder.append:(C)Lscala/collection/mutable/StringBuilder;
l4	pop
	goto	l12 // aload_3
l1	aload	8
	invokevirtual	Method scala/collection/mutable/StringBuilder.length:()I
	iconst_0
	if_icmple	l13 // getstatic
	getstatic	Field scala/xml/Text$.MODULE$:Lscala/xml/Text$;
	aload	8
	invokevirtual	Method scala/collection/mutable/StringBuilder.toString:()Ljava/lang/String;
	invokevirtual	Method scala/xml/Text$.apply:(Ljava/lang/String;)Lscala/xml/Text;
	astore	9
	aload	10
	invokeinterface	InterfaceMethod scala/collection/mutable/ResizableArray.length:()I
	iconst_0
	if_icmpne	l14 // aload
	aload	9
	areturn
l14	aload	10
	aload	9
	invokevirtual	Method scala/xml/NodeBuffer.$plus$eq:(Ljava/lang/Object;)Lscala/collection/mutable/ArrayBuffer;
	goto	l15 // pop
l13	getstatic	Field scala/runtime/BoxedUnit.UNIT:Lscala/runtime/BoxedUnit;
l15	pop
	aload	10
	areturn
  Labels:
   	l12 = 35 // aload_3
   	l3 = 150 // aload
   	l5 = 164 // aload
   	l7 = 189 // aload
   	l6 = 227 // aload
   	l10 = 321 // aload
   	l9 = 341 // new
   	l8 = 354 // iconst_1
   	l11 = 364 // new
   	l2 = 377 // aload
   	l4 = 387 // pop
   	l1 = 391 // aload
   	l14 = 427 // aload
   	l13 = 437 // getstatic
   	l15 = 440 // pop
  LocalVariableTable: 
   Start  Length  Slot  Name   Signature
   0      444      0    this       Lscala/xml/Utility$;
   0      444      1    value       Ljava/lang/String;
   141      6      2    theChar       Ljava/lang/String;
   35      408      3    it$1       Lscala/collection/Iterator;
   12      431      4    rfb       Lscala/collection/mutable/StringBuilder;
   234      143      5    ref       Ljava/lang/String;
   280      97      6    temp56       Lscala/collection/mutable/StringBuilder;
   62      326      7    c$1       Lscala/runtime/CharRef;
   9      434      8    sb       Lscala/collection/mutable/StringBuilder;
   413      24      9    x       Lscala/xml/Text;
   21      422      10    nb       Lscala/xml/NodeBuffer;

  Signature: length = 0x2
   01 1B 

public java.lang.String checkAttributeValue(java.lang.String);
  Signature: (Ljava/lang/String;)Ljava/lang/String;
  Code:
   Stack=4, Locals=5, Args_size=2
	iconst_0
	istore_3
l7	iload_3
	aload_1
	invokevirtual	Method java/lang/String.length:()I
	if_icmpge	l1 // aconst_null
	aload_1
	iload_3
	invokevirtual	Method java/lang/String.charAt:(I)C
	istore	4
	iload	4
	lookupswitch{ //2
		38: 88;
		60: 64;
		default: 44 }
	iconst_1
	ifne	l2 // iload_3
	new	class scala/MatchError
	dup
	iload	4
	invokestatic	Method scala/runtime/BoxesRunTime.boxToCharacter:(C)Ljava/lang/Character;
	invokevirtual	Method java/lang/Object.toString:()Ljava/lang/String;
	invokespecial	Method scala/MatchError."<init>":(Ljava/lang/String;)V
	athrow
	iconst_1
	ifeq	l3 // new
	ldc_w	String < not allowed in attribute value
	areturn
l3	new	class scala/MatchError
	dup
	iload	4
	invokestatic	Method scala/runtime/BoxesRunTime.boxToCharacter:(C)Ljava/lang/Character;
	invokevirtual	Method java/lang/Object.toString:()Ljava/lang/String;
	invokespecial	Method scala/MatchError."<init>":(Ljava/lang/String;)V
	athrow
	iconst_1
	ifeq	l4 // new
	aload_0
	aload_1
	iload_3
	iconst_1
	iadd
	invokevirtual	Method getName:(Ljava/lang/String;I)Ljava/lang/String;
	astore_2
	aload_2
	ifnonnull	l5 // iload_3
	new	class scala/collection/mutable/StringBuilder
	dup
	invokespecial	Method scala/collection/mutable/StringBuilder."<init>":()V
	ldc_w	String malformed entity reference in attribute value [
	invokevirtual	Method scala/collection/mutable/StringBuilder.append:(Ljava/lang/Object;)Lscala/collection/mutable/StringBuilder;
	aload_1
	invokevirtual	Method scala/collection/mutable/StringBuilder.append:(Ljava/lang/Object;)Lscala/collection/mutable/StringBuilder;
	ldc_w	String ]
	invokevirtual	Method scala/collection/mutable/StringBuilder.append:(Ljava/lang/Object;)Lscala/collection/mutable/StringBuilder;
	invokevirtual	Method scala/collection/mutable/StringBuilder.toString:()Ljava/lang/String;
	areturn
l5	iload_3
	aload_2
	invokevirtual	Method java/lang/String.length:()I
	iadd
	iconst_1
	iadd
	istore_3
	iload_3
	aload_1
	invokevirtual	Method java/lang/String.length:()I
	if_icmpge	l6 // new
	aload_1
	iload_3
	invokevirtual	Method java/lang/String.charAt:(I)C
	ldc	int 59
	if_icmpeq	l2 // iload_3
l6	new	class scala/collection/mutable/StringBuilder
	dup
	invokespecial	Method scala/collection/mutable/StringBuilder."<init>":()V
	ldc_w	String malformed entity reference in attribute value [
	invokevirtual	Method scala/collection/mutable/StringBuilder.append:(Ljava/lang/Object;)Lscala/collection/mutable/StringBuilder;
	aload_1
	invokevirtual	Method scala/collection/mutable/StringBuilder.append:(Ljava/lang/Object;)Lscala/collection/mutable/StringBuilder;
	ldc_w	String ]
	invokevirtual	Method scala/collection/mutable/StringBuilder.append:(Ljava/lang/Object;)Lscala/collection/mutable/StringBuilder;
	invokevirtual	Method scala/collection/mutable/StringBuilder.toString:()Ljava/lang/String;
	areturn
l2	iload_3
	iconst_1
	iadd
	istore_3
	goto	l7 // iload_3
l4	new	class scala/MatchError
	dup
	iload	4
	invokestatic	Method scala/runtime/BoxesRunTime.boxToCharacter:(C)Ljava/lang/Character;
	invokevirtual	Method java/lang/Object.toString:()Ljava/lang/String;
	invokespecial	Method scala/MatchError."<init>":(Ljava/lang/String;)V
	athrow
l1	aconst_null
	areturn
  Labels:
   	l7 = 2 // iload_3
   	l3 = 72 // new
   	l5 = 132 // iload_3
   	l6 = 159 // new
   	l2 = 186 // iload_3
   	l4 = 193 // new
   	l1 = 209 // aconst_null
  LocalVariableTable: 
   Start  Length  Slot  Name   Signature
   0      211      0    this       Lscala/xml/Utility$;
   0      211      1    value       Ljava/lang/String;
   101      85      2    n       Ljava/lang/String;
   2      208      3    i       I
   17      192      4    temp55       C


public java.lang.String getName(java.lang.String, int);
  Signature: (Ljava/lang/String;I)Ljava/lang/String;
  Code:
   Stack=4, Locals=9, Args_size=3
	iload_2
	aload_1
	invokevirtual	Method java/lang/String.length:()I
	if_icmplt	l1 // new
	aconst_null
	goto	l2 // areturn
l1	new	class scala/collection/immutable/StringOps
	dup
	aload_1
	invokespecial	Method scala/collection/immutable/StringOps."<init>":(Ljava/lang/String;)V
	iload_2
	invokeinterface	InterfaceMethod scala/collection/IndexedSeqLike.drop:(I)Ljava/lang/Object;
	checkcast	class java/lang/String
	astore	8
	aload	8
	instanceof	class scala/collection/Seq
	ifeq	l3 // iconst_1
	aload	8
	checkcast	class scala/collection/Seq
	astore_3
	getstatic	Field scala/collection/Seq$.MODULE$:Lscala/collection/Seq$;
	aload_3
	invokevirtual	Method scala/collection/Seq$.unapplySeq:(Lscala/collection/Seq;)Lscala/Some;
	astore	4
	iconst_1
	ifeq	l4 // iconst_1
	aload	4
	getfield	Field scala/Some.x:Ljava/lang/Object;
	checkcast	class scala/collection/Seq
	astore	5
	aload	5
	dup
	pop
	ifnull	l5 // iconst_0
	aload	5
	aconst_null
	invokevirtual	Method java/lang/Object.equals:(Ljava/lang/Object;)Z
	ifeq	l6 // aload
l5	iconst_0
	goto	l7 // ifeq
l6	aload	5
	iconst_1
	invokeinterface	InterfaceMethod scala/collection/SeqLike.lengthCompare:(I)I
	iconst_0
	if_icmplt	l8 // iconst_0
	iconst_1
	goto	l7 // ifeq
l8	iconst_0
l7	ifeq	l9 // iconst_1
	aload	5
	iconst_0
	invokeinterface	InterfaceMethod scala/collection/SeqLike.apply:(I)Ljava/lang/Object;
	invokestatic	Method scala/runtime/BoxesRunTime.unboxToChar:(Ljava/lang/Object;)C
	istore	6
	aload	5
	iconst_1
	invokeinterface	InterfaceMethod scala/collection/TraversableLike.drop:(I)Ljava/lang/Object;
	checkcast	class scala/collection/Seq
	astore	7
	aload_0
	iload	6
	aload	7
	invokespecial	Method gd2$1:(CLscala/collection/Seq;)Z
	ifeq	l10 // iconst_1
	new	class scala/collection/mutable/StringBuilder
	dup
	invokespecial	Method scala/collection/mutable/StringBuilder."<init>":()V
	iload	6
	invokestatic	Method scala/runtime/BoxesRunTime.boxToCharacter:(C)Ljava/lang/Character;
	invokevirtual	Method java/lang/Object.toString:()Ljava/lang/String;
	invokevirtual	Method scala/collection/mutable/StringBuilder.append:(Ljava/lang/Object;)Lscala/collection/mutable/StringBuilder;
	aload	7
	new	class scala/xml/Utility$$anonfun$getName$1
	dup
	invokespecial	Method scala/xml/Utility$$anonfun$getName$1."<init>":()V
	invokeinterface	InterfaceMethod scala/collection/IterableLike.takeWhile:(Lscala/Function1;)Ljava/lang/Object;
	checkcast	class scala/collection/TraversableLike
	invokeinterface	InterfaceMethod scala/collection/TraversableLike.mkString:()Ljava/lang/String;
	invokevirtual	Method scala/collection/mutable/StringBuilder.append:(Ljava/lang/Object;)Lscala/collection/mutable/StringBuilder;
	invokevirtual	Method scala/collection/mutable/StringBuilder.toString:()Ljava/lang/String;
	goto	l2 // areturn
l10	iconst_1
	ifeq	l11 // new
	ldc_w	String 
	goto	l2 // areturn
l11	new	class scala/MatchError
	dup
	aload	8
	invokevirtual	Method java/lang/String.toString:()Ljava/lang/String;
	invokespecial	Method scala/MatchError."<init>":(Ljava/lang/String;)V
	athrow
l9	iconst_1
	ifeq	l12 // new
	ldc_w	String 
	goto	l2 // areturn
l12	new	class scala/MatchError
	dup
	aload	8
	invokevirtual	Method java/lang/String.toString:()Ljava/lang/String;
	invokespecial	Method scala/MatchError."<init>":(Ljava/lang/String;)V
	athrow
l4	iconst_1
	ifeq	l13 // new
	ldc_w	String 
	goto	l2 // areturn
l13	new	class scala/MatchError
	dup
	aload	8
	invokevirtual	Method java/lang/String.toString:()Ljava/lang/String;
	invokespecial	Method scala/MatchError."<init>":(Ljava/lang/String;)V
	athrow
l3	iconst_1
	ifeq	l14 // new
	ldc_w	String 
l2	areturn
l14	new	class scala/MatchError
	dup
	aload	8
	invokevirtual	Method java/lang/String.toString:()Ljava/lang/String;
	invokespecial	Method scala/MatchError."<init>":(Ljava/lang/String;)V
	athrow
  Labels:
   	l1 = 12 // new
   	l5 = 84 // iconst_0
   	l6 = 88 // aload
   	l8 = 104 // iconst_0
   	l7 = 105 // ifeq
   	l10 = 194 // iconst_1
   	l11 = 204 // new
   	l9 = 217 // iconst_1
   	l12 = 227 // new
   	l4 = 240 // iconst_1
   	l13 = 250 // new
   	l3 = 263 // iconst_1
   	l2 = 270 // areturn
   	l14 = 271 // new
  LocalVariableTable: 
   Start  Length  Slot  Name   Signature
   0      284      0    this       Lscala/xml/Utility$;
   0      284      1    s       Ljava/lang/String;
   0      284      2    index       I
   45      218      3    temp50       Lscala/collection/Seq;
   54      209      4    temp51       Lscala/Some;
   68      172      5    temp52       Lscala/collection/Seq;
   121      96      6    temp53       C
   134      83      7    temp54       Lscala/collection/Seq;
   31      239      8    temp49       Ljava/lang/String;
   271      13      8    temp49       Ljava/lang/String;


public scala.collection.mutable.StringBuilder appendEscapedQuoted(java.lang.String, scala.collection.mutable.StringBuilder);
  Signature: (Ljava/lang/String;Lscala/collection/mutable/StringBuilder;)Lscala/collection/mutable/StringBuilder;
  Code:
   Stack=4, Locals=3, Args_size=3
	aload_2
	ldc_w	int 34
	invokevirtual	Method scala/collection/mutable/StringBuilder.append:(C)Lscala/collection/mutable/StringBuilder;
	pop
	getstatic	Field scala/Predef$.MODULE$:Lscala/Predef$;
	aload_1
	invokevirtual	Method scala/Predef$.augmentString:(Ljava/lang/String;)Lscala/collection/immutable/StringOps;
	new	class scala/xml/Utility$$anonfun$appendEscapedQuoted$1
	dup
	aload_2
	invokespecial	Method scala/xml/Utility$$anonfun$appendEscapedQuoted$1."<init>":(Lscala/collection/mutable/StringBuilder;)V
	invokeinterface	InterfaceMethod scala/collection/IndexedSeqLike.foreach:(Lscala/Function1;)V
	aload_2
	ldc_w	int 34
	invokevirtual	Method scala/collection/mutable/StringBuilder.append:(C)Lscala/collection/mutable/StringBuilder;
	areturn
  Labels:
  LocalVariableTable: 
   Start  Length  Slot  Name   Signature
   0      36      0    this       Lscala/xml/Utility$;
   0      36      1    s       Ljava/lang/String;
   0      36      2    sb$3       Lscala/collection/mutable/StringBuilder;


public scala.collection.mutable.StringBuilder appendQuoted(java.lang.String, scala.collection.mutable.StringBuilder);
  Signature: (Ljava/lang/String;Lscala/collection/mutable/StringBuilder;)Lscala/collection/mutable/StringBuilder;
  Code:
   Stack=3, Locals=5, Args_size=3
	new	class scala/collection/immutable/StringOps
	dup
	aload_1
	invokespecial	Method scala/collection/immutable/StringOps."<init>":(Ljava/lang/String;)V
	ldc_w	int 34
	istore_3
	iload_3
	invokestatic	Method scala/runtime/BoxesRunTime.boxToCharacter:(C)Ljava/lang/Character;
	invokeinterface	InterfaceMethod scala/collection/SeqLike.contains:(Ljava/lang/Object;)Z
	ifeq	l1 // ldc_w
	ldc_w	int 39
	goto	l2 // istore
l1	ldc_w	int 34
l2	istore	4
	aload_2
	iload	4
	invokevirtual	Method scala/collection/mutable/StringBuilder.append:(C)Lscala/collection/mutable/StringBuilder;
	aload_1
	invokevirtual	Method scala/collection/mutable/StringBuilder.append:(Ljava/lang/String;)Lscala/collection/mutable/StringBuilder;
	iload	4
	invokevirtual	Method scala/collection/mutable/StringBuilder.append:(C)Lscala/collection/mutable/StringBuilder;
	areturn
  Labels:
   	l1 = 30 // ldc_w
   	l2 = 33 // istore
  LocalVariableTable: 
   Start  Length  Slot  Name   Signature
   0      51      0    this       Lscala/xml/Utility$;
   0      51      1    s       Ljava/lang/String;
   0      51      2    sb       Lscala/collection/mutable/StringBuilder;
   35      15      4    ch       C


public java.lang.String appendQuoted(java.lang.String);
  Signature: (Ljava/lang/String;)Ljava/lang/String;
  Code:
   Stack=3, Locals=4, Args_size=2
	new	class scala/collection/mutable/StringBuilder
	dup
	invokespecial	Method scala/collection/mutable/StringBuilder."<init>":()V
	astore_3
	aload_3
	checkcast	class scala/collection/mutable/StringBuilder
	astore_2
	getstatic	Field MODULE$:Lscala/xml/Utility$;
	aload_1
	aload_2
	invokevirtual	Method appendQuoted:(Ljava/lang/String;Lscala/collection/mutable/StringBuilder;)Lscala/collection/mutable/StringBuilder;
	pop
	aload_3
	invokevirtual	Method scala/collection/mutable/StringBuilder.toString:()Ljava/lang/String;
	areturn
  Labels:
  LocalVariableTable: 
   Start  Length  Slot  Name   Signature
   0      27      0    this       Lscala/xml/Utility$;
   0      27      1    s$1       Ljava/lang/String;
   8      18      3    sb0       Lscala/collection/mutable/StringBuilder;


public int hashCode(java.lang.String, java.lang.String, int, int, scala.collection.Seq);
  Signature: (Ljava/lang/String;Ljava/lang/String;IILscala/collection/Seq;)I
  Code:
   Stack=3, Locals=8, Args_size=6
	aload_1
	ifnull	l1 // iconst_0
	ldc_w	int 41
	aload_1
	invokevirtual	Method java/lang/String.hashCode:()I
	imul
	ldc_w	int 7
	irem
	goto	l2 // aload_2
l1	iconst_0
l2	aload_2
	invokevirtual	Method java/lang/String.hashCode:()I
	ldc_w	int 53
	imul
	iadd
	iload_3
	ldc_w	int 7
	imul
	iadd
	iload	4
	ldc_w	int 31
	imul
	iadd
	iconst_0
	istore	6
	aload	5
	invokeinterface	InterfaceMethod scala/collection/IterableLike.iterator:()Lscala/collection/Iterator;
	astore	7
l4	aload	7
	invokeinterface	InterfaceMethod scala/collection/Iterator.hasNext:()Z
	ifeq	l3 // iload
	iload	6
	ldc_w	int 41
	imul
	aload	7
	invokeinterface	InterfaceMethod scala/collection/Iterator.next:()Ljava/lang/Object;
	checkcast	class scala/xml/Node
	invokevirtual	Method scala/xml/Node.hashCode:()I
	iadd
	istore	6
	goto	l4 // aload
l3	iload	6
	iadd
	ireturn
  Labels:
   	l1 = 19 // iconst_0
   	l2 = 20 // aload_2
   	l4 = 54 // aload
   	l3 = 89 // iload
  LocalVariableTable: 
   Start  Length  Slot  Name   Signature
   0      93      0    this       Lscala/xml/Utility$;
   0      93      1    pre       Ljava/lang/String;
   0      93      2    label       Ljava/lang/String;
   0      93      3    attribHashCode       I
   0      93      4    scpeHash       I
   0      93      5    children       Lscala/collection/Seq;
   45      46      6    c       I
   54      37      7    i       Lscala/collection/Iterator;

  Signature: length = 0x2
   01 FFFFFF8F 

public final scala.Option prefix(java.lang.String);
  Signature: (Ljava/lang/String;)Lscala/Option;
  Code:
   Stack=5, Locals=3, Args_size=2
	aload_1
	ldc_w	int 58
	invokevirtual	Method java/lang/String.indexOf:(I)I
	istore_2
	iload_2
	iconst_m1
	if_icmpne	l1 // iconst_1
	iconst_1
	ifeq	l2 // new
	getstatic	Field scala/None$.MODULE$:Lscala/None$;
	goto	l3 // areturn
l2	new	class scala/MatchError
	dup
	iload_2
	invokestatic	Method scala/runtime/BoxesRunTime.boxToInteger:(I)Ljava/lang/Integer;
	invokevirtual	Method java/lang/Object.toString:()Ljava/lang/String;
	invokespecial	Method scala/MatchError."<init>":(Ljava/lang/String;)V
	athrow
l1	iconst_1
	ifeq	l4 // new
	new	class scala/Some
	dup
	aload_1
	iconst_0
	iload_2
	invokevirtual	Method java/lang/String.substring:(II)Ljava/lang/String;
	invokespecial	Method scala/Some."<init>":(Ljava/lang/Object;)V
l3	areturn
l4	new	class scala/MatchError
	dup
	iload_2
	invokestatic	Method scala/runtime/BoxesRunTime.boxToInteger:(I)Ljava/lang/Integer;
	invokevirtual	Method java/lang/Object.toString:()Ljava/lang/String;
	invokespecial	Method scala/MatchError."<init>":(Ljava/lang/String;)V
	athrow
  Labels:
   	l2 = 23 // new
   	l1 = 38 // iconst_1
   	l3 = 55 // areturn
   	l4 = 56 // new
  LocalVariableTable: 
   Start  Length  Slot  Name   Signature
   0      71      0    this       Lscala/xml/Utility$;
   0      71      1    name       Ljava/lang/String;
   8      63      2    temp47       I

  Signature: length = 0x2
   01 FFFFFFA8 

public void sequenceToXML(scala.collection.Seq, scala.xml.NamespaceBinding, scala.collection.mutable.StringBuilder, boolean);
  Signature: (Lscala/collection/Seq;Lscala/xml/NamespaceBinding;Lscala/collection/mutable/StringBuilder;Z)V
  Code:
   Stack=8, Locals=8, Args_size=5
	aload_1
	invokeinterface	InterfaceMethod scala/collection/IterableLike.isEmpty:()Z
	ifeq	l1 // aload_1
	return
l1	aload_1
	new	class scala/xml/Utility$$anonfun$sequenceToXML$1
	dup
	invokespecial	Method scala/xml/Utility$$anonfun$sequenceToXML$1."<init>":()V
	invokeinterface	InterfaceMethod scala/collection/IterableLike.forall:(Lscala/Function1;)Z
	ifeq	l2 // aload_1
	aload_1
	invokeinterface	InterfaceMethod scala/collection/IterableLike.iterator:()Lscala/collection/Iterator;
	astore	6
	aload	6
	invokeinterface	InterfaceMethod scala/collection/Iterator.next:()Ljava/lang/Object;
	checkcast	class scala/xml/Node
	astore	5
	aload_0
	aload	5
	aload_2
	aload_3
	iconst_0
	iconst_1
	iconst_0
	iconst_0
	invokevirtual	Method toXML:(Lscala/xml/Node;Lscala/xml/NamespaceBinding;Lscala/collection/mutable/StringBuilder;ZZZZ)Lscala/collection/mutable/StringBuilder;
	pop
l4	aload	6
	invokeinterface	InterfaceMethod scala/collection/Iterator.hasNext:()Z
	ifeq	l3 // return
	aload	6
	invokeinterface	InterfaceMethod scala/collection/Iterator.next:()Ljava/lang/Object;
	checkcast	class scala/xml/Node
	astore	7
	aload_3
	ldc_w	int 32
	invokevirtual	Method scala/collection/mutable/StringBuilder.append:(C)Lscala/collection/mutable/StringBuilder;
	pop
	aload_0
	aload	7
	aload_2
	aload_3
	iconst_0
	iconst_1
	iconst_0
	iconst_0
	invokevirtual	Method toXML:(Lscala/xml/Node;Lscala/xml/NamespaceBinding;Lscala/collection/mutable/StringBuilder;ZZZZ)Lscala/collection/mutable/StringBuilder;
	pop
	goto	l4 // aload
l2	aload_1
	new	class scala/xml/Utility$$anonfun$sequenceToXML$2
	dup
	aload_2
	aload_3
	invokespecial	Method scala/xml/Utility$$anonfun$sequenceToXML$2."<init>":(Lscala/xml/NamespaceBinding;Lscala/collection/mutable/StringBuilder;)V
	invokeinterface	InterfaceMethod scala/collection/IterableLike.foreach:(Lscala/Function1;)V
l3	return
  Labels:
   	l1 = 10 // aload_1
   	l4 = 59 // aload
   	l2 = 105 // aload_1
   	l3 = 120 // return
  LocalVariableTable: 
   Start  Length  Slot  Name   Signature
   0      121      0    this       Lscala/xml/Utility$;
   0      121      1    children       Lscala/collection/Seq;
   0      121      2    pscope$1       Lscala/xml/NamespaceBinding;
   0      121      3    sb$2       Lscala/collection/mutable/StringBuilder;
   0      121      4    stripComments       Z
   46      59      5    f       Lscala/xml/Node;
   34      71      6    it       Lscala/collection/Iterator;
   81      21      7    x       Lscala/xml/Node;

  Signature: length = 0x2
   01 FFFFFFC7 

public scala.collection.mutable.StringBuilder toXML(scala.xml.Node, scala.xml.NamespaceBinding, scala.collection.mutable.StringBuilder, boolean, boolean, boolean, boolean);
  Signature: (Lscala/xml/Node;Lscala/xml/NamespaceBinding;Lscala/collection/mutable/StringBuilder;ZZZZ)Lscala/collection/mutable/StringBuilder;
  Code:
   Stack=5, Locals=11, Args_size=8
	aload_1
	instanceof	class scala/xml/Comment
	ifeq	l1 // aload_1
	aload_1
	checkcast	class scala/xml/Comment
	astore	8
	aload_0
	aload	8
	iload	4
	invokespecial	Method gd1$1:(Lscala/xml/Comment;Z)Z
	ifeq	l2 // iconst_1
	aload	8
	aload_3
	invokevirtual	Method scala/xml/Comment.buildString:(Lscala/collection/mutable/StringBuilder;)Lscala/collection/mutable/StringBuilder;
	goto	l3 // areturn
l2	iconst_1
	ifeq	l4 // new
	aload	8
	astore	9
	goto	l5 // aload
l4	new	class scala/MatchError
	dup
	aload_1
	invokevirtual	Method scala/xml/Node.toString:()Ljava/lang/String;
	invokespecial	Method scala/MatchError."<init>":(Ljava/lang/String;)V
	athrow
l1	aload_1
	instanceof	class scala/xml/SpecialNode
	ifeq	l6 // aload_1
	iconst_1
	ifeq	l7 // new
	aload_1
	checkcast	class scala/xml/SpecialNode
	astore	9
l5	aload	9
	aload_3
	invokevirtual	Method scala/xml/SpecialNode.buildString:(Lscala/collection/mutable/StringBuilder;)Lscala/collection/mutable/StringBuilder;
	goto	l3 // areturn
l7	new	class scala/MatchError
	dup
	aload_1
	invokevirtual	Method scala/xml/Node.toString:()Ljava/lang/String;
	invokespecial	Method scala/MatchError."<init>":(Ljava/lang/String;)V
	athrow
l6	aload_1
	instanceof	class scala/xml/Group
	ifeq	l8 // iconst_1
	aload_1
	checkcast	class scala/xml/Group
	astore	10
	iconst_1
	ifeq	l9 // new
	aload	10
	invokevirtual	Method scala/xml/Group.nodes:()Lscala/collection/Seq;
	new	class scala/xml/Utility$$anonfun$toXML$1
	dup
	aload_1
	aload_3
	invokespecial	Method scala/xml/Utility$$anonfun$toXML$1."<init>":(Lscala/xml/Node;Lscala/collection/mutable/StringBuilder;)V
	invokeinterface	InterfaceMethod scala/collection/IterableLike.foreach:(Lscala/Function1;)V
	aload_3
	goto	l3 // areturn
l9	new	class scala/MatchError
	dup
	aload_1
	invokevirtual	Method scala/xml/Node.toString:()Ljava/lang/String;
	invokespecial	Method scala/MatchError."<init>":(Ljava/lang/String;)V
	athrow
l8	iconst_1
	ifeq	l10 // new
	aload_3
	ldc_w	int 60
	invokevirtual	Method scala/collection/mutable/StringBuilder.append:(C)Lscala/collection/mutable/StringBuilder;
	pop
	aload_1
	aload_3
	invokevirtual	Method scala/xml/Node.nameToString:(Lscala/collection/mutable/StringBuilder;)Lscala/collection/mutable/StringBuilder;
	pop
	aload_1
	invokevirtual	Method scala/xml/Node.attributes:()Lscala/xml/MetaData;
	ifnull	l11 // getstatic
	aload_1
	invokevirtual	Method scala/xml/Node.attributes:()Lscala/xml/MetaData;
	aload_3
	invokevirtual	Method scala/xml/MetaData.buildString:(Lscala/collection/mutable/StringBuilder;)Lscala/collection/mutable/StringBuilder;
	goto	l12 // pop
l11	getstatic	Field scala/runtime/BoxedUnit.UNIT:Lscala/runtime/BoxedUnit;
l12	pop
	aload_1
	invokevirtual	Method scala/xml/Node.scope:()Lscala/xml/NamespaceBinding;
	aload_3
	aload_2
	invokevirtual	Method scala/xml/NamespaceBinding.buildString:(Lscala/collection/mutable/StringBuilder;Lscala/xml/NamespaceBinding;)V
	aload_1
	invokevirtual	Method scala/xml/Node.child:()Lscala/collection/Seq;
	invokeinterface	InterfaceMethod scala/collection/IterableLike.isEmpty:()Z
	ifeq	l13 // aload_3
	iload	7
	ifeq	l13 // aload_3
	aload_3
	ldc_w	String  />
	invokevirtual	Method scala/collection/mutable/StringBuilder.append:(Ljava/lang/String;)Lscala/collection/mutable/StringBuilder;
	goto	l3 // areturn
l13	aload_3
	ldc_w	int 62
	invokevirtual	Method scala/collection/mutable/StringBuilder.append:(C)Lscala/collection/mutable/StringBuilder;
	pop
	aload_0
	aload_1
	invokevirtual	Method scala/xml/Node.child:()Lscala/collection/Seq;
	aload_1
	invokevirtual	Method scala/xml/Node.scope:()Lscala/xml/NamespaceBinding;
	aload_3
	iload	4
	invokevirtual	Method sequenceToXML:(Lscala/collection/Seq;Lscala/xml/NamespaceBinding;Lscala/collection/mutable/StringBuilder;Z)V
	aload_3
	ldc_w	String </
	invokevirtual	Method scala/collection/mutable/StringBuilder.append:(Ljava/lang/String;)Lscala/collection/mutable/StringBuilder;
	pop
	aload_1
	aload_3
	invokevirtual	Method scala/xml/Node.nameToString:(Lscala/collection/mutable/StringBuilder;)Lscala/collection/mutable/StringBuilder;
	pop
	aload_3
	ldc_w	int 62
	invokevirtual	Method scala/collection/mutable/StringBuilder.append:(C)Lscala/collection/mutable/StringBuilder;
l3	areturn
l10	new	class scala/MatchError
	dup
	aload_1
	invokevirtual	Method scala/xml/Node.toString:()Ljava/lang/String;
	invokespecial	Method scala/MatchError."<init>":(Ljava/lang/String;)V
	athrow
  Labels:
   	l2 = 33 // iconst_1
   	l4 = 44 // new
   	l1 = 56 // aload_1
   	l5 = 73 // aload
   	l7 = 82 // new
   	l6 = 94 // aload_1
   	l9 = 134 // new
   	l8 = 146 // iconst_1
   	l11 = 182 // getstatic
   	l12 = 185 // pop
   	l13 = 222 // aload_3
   	l3 = 266 // areturn
   	l10 = 267 // new
  LocalVariableTable: 
   Start  Length  Slot  Name   Signature
   0      279      0    this       Lscala/xml/Utility$;
   0      279      1    x$7       Lscala/xml/Node;
   0      279      2    pscope       Lscala/xml/NamespaceBinding;
   0      279      3    sb$1       Lscala/collection/mutable/StringBuilder;
   0      279      4    stripComments$1       Z
   0      279      5    decodeEntities       Z
   0      279      6    preserveWhitespace       Z
   0      279      7    minimizeTags       Z
   13      43      8    temp42       Lscala/xml/Comment;
   73      9      8    temp42       Lscala/xml/Comment;
   33      4      9    x       Lscala/xml/SpecialNode;
   41      3      9    x       Lscala/xml/SpecialNode;
   37      19      9    x       Lscala/xml/SpecialNode;
   73      6      9    x       Lscala/xml/SpecialNode;
   107      39      10    temp45       Lscala/xml/Group;


public void collectNamespaces(scala.xml.Node, scala.collection.mutable.Set);
  Signature: (Lscala/xml/Node;Lscala/collection/mutable/Set;)V
  Code:
   Stack=5, Locals=3, Args_size=3
	aload_1
	invokevirtual	Method scala/xml/Node.doCollectNamespaces:()Z
	ifeq	l1 // return
	aload_2
	aload_1
	invokevirtual	Method scala/xml/Node.namespace:()Ljava/lang/String;
	invokeinterface	InterfaceMethod scala/collection/mutable/SetLike.$plus$eq:(Ljava/lang/Object;)Lscala/collection/mutable/SetLike;
	pop
	aload_1
	invokevirtual	Method scala/xml/Node.attributes:()Lscala/xml/MetaData;
	new	class scala/xml/Utility$$anonfun$collectNamespaces$2
	dup
	aload_1
	aload_2
	invokespecial	Method scala/xml/Utility$$anonfun$collectNamespaces$2."<init>":(Lscala/xml/Node;Lscala/collection/mutable/Set;)V
	invokeinterface	InterfaceMethod scala/collection/IterableLike.foreach:(Lscala/Function1;)V
	aload_1
	invokevirtual	Method scala/xml/Node.child:()Lscala/collection/Seq;
	new	class scala/xml/Utility$$anonfun$collectNamespaces$3
	dup
	aload_2
	invokespecial	Method scala/xml/Utility$$anonfun$collectNamespaces$3."<init>":(Lscala/collection/mutable/Set;)V
	invokeinterface	InterfaceMethod scala/collection/IterableLike.foreach:(Lscala/Function1;)V
l1	return
  Labels:
   	l1 = 53 // return
  LocalVariableTable: 
   Start  Length  Slot  Name   Signature
   0      54      0    this       Lscala/xml/Utility$;
   0      54      1    n$1       Lscala/xml/Node;
   0      54      2    set$1       Lscala/collection/mutable/Set;

  Signature: length = 0x2
   02 22 

public scala.collection.mutable.Set collectNamespaces(scala.collection.Seq);
  Signature: (Lscala/collection/Seq;)Lscala/collection/mutable/Set;
  Code:
   Stack=4, Locals=2, Args_size=2
	aload_1
	new	class scala/collection/mutable/HashSet
	dup
	invokespecial	Method scala/collection/mutable/HashSet."<init>":()V
	new	class scala/xml/Utility$$anonfun$collectNamespaces$1
	dup
	invokespecial	Method scala/xml/Utility$$anonfun$collectNamespaces$1."<init>":()V
	invokeinterface	InterfaceMethod scala/collection/TraversableLike.foldLeft:(Ljava/lang/Object;Lscala/Function2;)Ljava/lang/Object;
	checkcast	class scala/collection/mutable/Set
	areturn
  Labels:
  LocalVariableTable: 
   Start  Length  Slot  Name   Signature
   0      24      0    this       Lscala/xml/Utility$;
   0      24      1    nodes       Lscala/collection/Seq;

  Signature: length = 0x2
   02 30 

public final scala.collection.mutable.StringBuilder unescape(java.lang.String, scala.collection.mutable.StringBuilder);
  Signature: (Ljava/lang/String;Lscala/collection/mutable/StringBuilder;)Lscala/collection/mutable/StringBuilder;
  Code:
   Stack=4, Locals=3, Args_size=3
	getstatic	Field scala/xml/Utility$Escapes$.MODULE$:Lscala/xml/Utility$Escapes$;
	invokevirtual	Method scala/xml/Utility$Escapes$.unescMap:()Lscala/collection/immutable/Map;
	aload_1
	invokeinterface	InterfaceMethod scala/collection/MapLike.get:(Ljava/lang/Object;)Lscala/Option;
	new	class scala/xml/Utility$$anonfun$unescape$1
	dup
	aload_2
	invokespecial	Method scala/xml/Utility$$anonfun$unescape$1."<init>":(Lscala/collection/mutable/StringBuilder;)V
	invokevirtual	Method scala/Option.map:(Lscala/Function1;)Lscala/Option;
	getstatic	Field scala/Predef$.MODULE$:Lscala/Predef$;
	invokevirtual	Method scala/Predef$.conforms:()Lscala/Predef$$less$colon$less;
	invokevirtual	Method scala/Option.orNull:(Lscala/Predef$$less$colon$less;)Ljava/lang/Object;
	checkcast	class scala/collection/mutable/StringBuilder
	areturn
  Labels:
  LocalVariableTable: 
   Start  Length  Slot  Name   Signature
   0      36      0    this       Lscala/xml/Utility$;
   0      36      1    ref       Ljava/lang/String;
   0      36      2    s$2       Lscala/collection/mutable/StringBuilder;


public final scala.collection.mutable.StringBuilder escape(java.lang.String, scala.collection.mutable.StringBuilder);
  Signature: (Ljava/lang/String;Lscala/collection/mutable/StringBuilder;)Lscala/collection/mutable/StringBuilder;
  Code:
   Stack=4, Locals=3, Args_size=3
	getstatic	Field scala/Predef$.MODULE$:Lscala/Predef$;
	aload_1
	invokevirtual	Method scala/Predef$.augmentString:(Ljava/lang/String;)Lscala/collection/immutable/StringOps;
	aload_2
	new	class scala/xml/Utility$$anonfun$escape$2
	dup
	invokespecial	Method scala/xml/Utility$$anonfun$escape$2."<init>":()V
	invokeinterface	InterfaceMethod scala/collection/IndexedSeqLike.foldLeft:(Ljava/lang/Object;Lscala/Function2;)Ljava/lang/Object;
	checkcast	class scala/collection/mutable/StringBuilder
	areturn
  Labels:
  LocalVariableTable: 
   Start  Length  Slot  Name   Signature
   0      24      0    this       Lscala/xml/Utility$;
   0      24      1    text       Ljava/lang/String;
   0      24      2    s       Lscala/collection/mutable/StringBuilder;


public final java.lang.String escape(java.lang.String);
  Signature: (Ljava/lang/String;)Ljava/lang/String;
  Code:
   Stack=4, Locals=5, Args_size=2
	new	class scala/collection/mutable/StringBuilder
	dup
	invokespecial	Method scala/collection/mutable/StringBuilder."<init>":()V
	astore	4
	aload	4
	checkcast	class scala/collection/mutable/StringBuilder
	astore_3
	aload_1
	astore_2
	new	class scala/collection/immutable/StringOps
	dup
	aload_2
	invokespecial	Method scala/collection/immutable/StringOps."<init>":(Ljava/lang/String;)V
	aload_3
	new	class scala/xml/Utility$$anonfun$escape$2
	dup
	invokespecial	Method scala/xml/Utility$$anonfun$escape$2."<init>":()V
	invokeinterface	InterfaceMethod scala/collection/IndexedSeqLike.foldLeft:(Ljava/lang/Object;Lscala/Function2;)Ljava/lang/Object;
	pop
	aload	4
	invokevirtual	Method scala/collection/mutable/StringBuilder.toString:()Ljava/lang/String;
	areturn
  Labels:
  LocalVariableTable: 
   Start  Length  Slot  Name   Signature
   0      45      0    this       Lscala/xml/Utility$;
   0      45      1    text$1       Ljava/lang/String;
   9      35      4    sb0       Lscala/collection/mutable/StringBuilder;


public scala.xml.Node sort(scala.xml.Node);
  Signature: (Lscala/xml/Node;)Lscala/xml/Node;
  Code:
   Stack=7, Locals=12, Args_size=2
	getstatic	Field scala/xml/Elem$.MODULE$:Lscala/xml/Elem$;
	aload_1
	invokevirtual	Method scala/xml/Elem$.unapplySeq:(Lscala/xml/Node;)Lscala/Option;
	astore_2
	aload_2
	invokevirtual	Method scala/Option.isEmpty:()Z
	ifeq	l1 // aload_2
	iconst_1
	ifne	l2 // aload_1
	new	class scala/MatchError
	dup
	aload_1
	invokevirtual	Method scala/xml/Node.toString:()Ljava/lang/String;
	invokespecial	Method scala/MatchError."<init>":(Ljava/lang/String;)V
	athrow
l1	aload_2
	invokevirtual	Method scala/Option.get:()Ljava/lang/Object;
	checkcast	class scala/Tuple5
	astore_3
	aload_3
	invokevirtual	Method scala/Tuple5._1:()Ljava/lang/Object;
	checkcast	class java/lang/String
	astore	7
	aload_3
	invokevirtual	Method scala/Tuple5._2:()Ljava/lang/Object;
	checkcast	class java/lang/String
	astore	8
	aload_3
	invokevirtual	Method scala/Tuple5._3:()Ljava/lang/Object;
	checkcast	class scala/xml/MetaData
	astore	4
	aload_3
	invokevirtual	Method scala/Tuple5._4:()Ljava/lang/Object;
	checkcast	class scala/xml/NamespaceBinding
	astore	10
	aload_3
	invokevirtual	Method scala/Tuple5._5:()Ljava/lang/Object;
	checkcast	class scala/collection/Seq
	astore	5
	aload	5
	dup
	pop
	ifnull	l3 // iconst_0
	aload	5
	aconst_null
	invokevirtual	Method java/lang/Object.equals:(Ljava/lang/Object;)Z
	ifeq	l4 // aload
l3	iconst_0
	goto	l5 // ifeq
l4	aload	5
	iconst_0
	invokeinterface	InterfaceMethod scala/collection/SeqLike.lengthCompare:(I)I
	iconst_0
	if_icmplt	l6 // iconst_0
	iconst_1
	goto	l5 // ifeq
l6	iconst_0
l5	ifeq	l7 // iconst_1
	iconst_1
	ifeq	l8 // new
	aload_0
	aload	4
	invokevirtual	Method sort:(Lscala/xml/MetaData;)Lscala/xml/MetaData;
	aload	5
	new	class scala/xml/Utility$$anonfun$sort$1
	dup
	invokespecial	Method scala/xml/Utility$$anonfun$sort$1."<init>":()V
	getstatic	Field scala/collection/Seq$.MODULE$:Lscala/collection/Seq$;
	astore	6
	new	class scala/collection/generic/TraversableFactory$GenericCanBuildFrom
	dup
	aload	6
	invokespecial	Method scala/collection/generic/TraversableFactory$GenericCanBuildFrom."<init>":(Lscala/collection/generic/TraversableFactory;)V
	invokeinterface	InterfaceMethod scala/collection/TraversableLike.map:(Lscala/Function1;Lscala/collection/generic/CanBuildFrom;)Ljava/lang/Object;
	checkcast	class scala/collection/Seq
	astore	11
	astore	9
	new	class scala/xml/Elem
	dup
	aload	7
	aload	8
	aload	9
	aload	10
	aload	11
	invokespecial	Method scala/xml/Elem."<init>":(Ljava/lang/String;Ljava/lang/String;Lscala/xml/MetaData;Lscala/xml/NamespaceBinding;Lscala/collection/Seq;)V
	goto	l9 // areturn
l8	new	class scala/MatchError
	dup
	aload_1
	invokevirtual	Method scala/xml/Node.toString:()Ljava/lang/String;
	invokespecial	Method scala/MatchError."<init>":(Ljava/lang/String;)V
	athrow
l7	iconst_1
	ifeq	l10 // new
l2	aload_1
l9	areturn
l10	new	class scala/MatchError
	dup
	aload_1
	invokevirtual	Method scala/xml/Node.toString:()Ljava/lang/String;
	invokespecial	Method scala/MatchError."<init>":(Ljava/lang/String;)V
	athrow
  Labels:
   	l1 = 31 // aload_2
   	l3 = 100 // iconst_0
   	l4 = 104 // aload
   	l6 = 120 // iconst_0
   	l5 = 121 // ifeq
   	l8 = 189 // new
   	l7 = 201 // iconst_1
   	l2 = 205 // aload_1
   	l9 = 206 // areturn
   	l10 = 207 // new
  LocalVariableTable: 
   Start  Length  Slot  Name   Signature
   0      219      0    this       Lscala/xml/Utility$;
   0      219      1    n       Lscala/xml/Node;
   8      211      2    temp24       Lscala/Option;
   39      167      3    temp25       Lscala/Tuple5;
   207      12      3    temp25       Lscala/Tuple5;
   66      140      4    temp28       Lscala/xml/MetaData;
   207      12      4    temp28       Lscala/xml/MetaData;
   84      122      5    temp30       Lscala/collection/Seq;
   207      12      5    temp30       Lscala/collection/Seq;
   48      158      7    temp26       Ljava/lang/String;
   207      12      7    temp26       Ljava/lang/String;
   57      149      8    temp27       Ljava/lang/String;
   207      12      8    temp27       Ljava/lang/String;
   75      131      10    temp29       Lscala/xml/NamespaceBinding;
   207      12      10    temp29       Lscala/xml/NamespaceBinding;


public scala.xml.MetaData sort(scala.xml.MetaData);
  Signature: (Lscala/xml/MetaData;)Lscala/xml/MetaData;
  Code:
   Stack=5, Locals=8, Args_size=2
	aload_1
	getstatic	Field scala/xml/Null$.MODULE$:Lscala/xml/Null$;
	if_acmpeq	l1 // aload_1
	aload_1
	invokevirtual	Method scala/xml/MetaData.next:()Lscala/xml/MetaData;
	getstatic	Field scala/xml/Null$.MODULE$:Lscala/xml/Null$;
	if_acmpne	l2 // aload_1
l1	aload_1
	goto	l3 // areturn
l2	aload_1
	invokevirtual	Method scala/xml/MetaData.key:()Ljava/lang/String;
	astore_2
	aload_0
	aload_1
	new	class scala/xml/Utility$$anonfun$1
	dup
	aload_2
	invokespecial	Method scala/xml/Utility$$anonfun$1."<init>":(Ljava/lang/String;)V
	invokevirtual	Method scala/xml/MetaData.filter:(Lscala/Function1;)Lscala/xml/MetaData;
	invokevirtual	Method sort:(Lscala/xml/MetaData;)Lscala/xml/MetaData;
	astore_3
	aload_0
	aload_1
	new	class scala/xml/Utility$$anonfun$2
	dup
	aload_2
	invokespecial	Method scala/xml/Utility$$anonfun$2."<init>":(Ljava/lang/String;)V
	invokevirtual	Method scala/xml/MetaData.filter:(Lscala/Function1;)Lscala/xml/MetaData;
	invokevirtual	Method sort:(Lscala/xml/MetaData;)Lscala/xml/MetaData;
	astore	4
	aload_3
	getstatic	Field scala/xml/Null$.MODULE$:Lscala/xml/Null$;
	aload_3
	invokevirtual	Method scala/xml/MetaData.append$default$2:()Lscala/xml/NamespaceBinding;
	invokevirtual	Method scala/xml/MetaData.append:(Lscala/xml/MetaData;Lscala/xml/NamespaceBinding;)Lscala/xml/MetaData;
	astore	5
	aload_1
	aload	4
	invokevirtual	Method scala/xml/MetaData.copy:(Lscala/xml/MetaData;)Lscala/xml/MetaData;
	astore	6
	aload	5
	invokevirtual	Method scala/xml/MetaData.append$default$2:()Lscala/xml/NamespaceBinding;
	astore	7
	aload	5
	aload	6
	aload	7
	invokevirtual	Method scala/xml/MetaData.append:(Lscala/xml/MetaData;Lscala/xml/NamespaceBinding;)Lscala/xml/MetaData;
l3	areturn
  Labels:
   	l1 = 17 // aload_1
   	l2 = 21 // aload_1
   	l3 = 98 // areturn
  LocalVariableTable: 
   Start  Length  Slot  Name   Signature
   0      99      0    this       Lscala/xml/Utility$;
   0      99      1    md       Lscala/xml/MetaData;
   26      72      2    key$1       Ljava/lang/String;
   43      55      3    smaller       Lscala/xml/MetaData;
   61      37      4    greater       Lscala/xml/MetaData;
   74      24      5    qual$1       Lscala/xml/MetaData;
   82      16      6    x$5       Lscala/xml/MetaData;
   89      9      7    x$6       Lscala/xml/NamespaceBinding;


public scala.collection.Seq trimProper(scala.xml.Node);
  Signature: (Lscala/xml/Node;)Lscala/collection/Seq;
  Code:
   Stack=7, Locals=15, Args_size=2
	getstatic	Field scala/xml/Elem$.MODULE$:Lscala/xml/Elem$;
	aload_1
	invokevirtual	Method scala/xml/Elem$.unapplySeq:(Lscala/xml/Node;)Lscala/Option;
	astore_3
	aload_3
	invokevirtual	Method scala/Option.isEmpty:()Z
	ifeq	l1 // aload_3
	getstatic	Field scala/xml/Text$.MODULE$:Lscala/xml/Text$;
	aload_1
	invokevirtual	Method scala/xml/Text$.unapply:(Ljava/lang/Object;)Lscala/Option;
	astore_2
	aload_2
	invokevirtual	Method scala/Option.isEmpty:()Z
	ifeq	l2 // iconst_1
	iconst_1
	ifne	l3 // aload_1
	new	class scala/MatchError
	dup
	aload_1
	invokevirtual	Method scala/xml/Node.toString:()Ljava/lang/String;
	invokespecial	Method scala/MatchError."<init>":(Ljava/lang/String;)V
	athrow
l2	iconst_1
	ifeq	l4 // new
	aload_2
	invokevirtual	Method scala/Option.get:()Ljava/lang/Object;
	checkcast	class java/lang/String
	astore	14
	goto	l5 // new
l4	new	class scala/MatchError
	dup
	aload_1
	invokevirtual	Method scala/xml/Node.toString:()Ljava/lang/String;
	invokespecial	Method scala/MatchError."<init>":(Ljava/lang/String;)V
	athrow
l1	aload_3
	invokevirtual	Method scala/Option.get:()Ljava/lang/Object;
	checkcast	class scala/Tuple5
	astore	4
	aload	4
	invokevirtual	Method scala/Tuple5._1:()Ljava/lang/Object;
	checkcast	class java/lang/String
	astore	7
	aload	4
	invokevirtual	Method scala/Tuple5._2:()Ljava/lang/Object;
	checkcast	class java/lang/String
	astore	8
	aload	4
	invokevirtual	Method scala/Tuple5._3:()Ljava/lang/Object;
	checkcast	class scala/xml/MetaData
	astore	9
	aload	4
	invokevirtual	Method scala/Tuple5._4:()Ljava/lang/Object;
	checkcast	class scala/xml/NamespaceBinding
	astore	10
	aload	4
	invokevirtual	Method scala/Tuple5._5:()Ljava/lang/Object;
	checkcast	class scala/collection/Seq
	astore	5
	aload	5
	dup
	pop
	ifnull	l6 // iconst_0
	aload	5
	aconst_null
	invokevirtual	Method java/lang/Object.equals:(Ljava/lang/Object;)Z
	ifeq	l7 // aload
l6	iconst_0
	goto	l8 // ifeq
l7	aload	5
	iconst_0
	invokeinterface	InterfaceMethod scala/collection/SeqLike.lengthCompare:(I)I
	iconst_0
	if_icmplt	l9 // iconst_0
	iconst_1
	goto	l8 // ifeq
l9	iconst_0
l8	ifeq	l10 // getstatic
	iconst_1
	ifeq	l11 // new
	aload	5
	new	class scala/xml/Utility$$anonfun$trimProper$1
	dup
	invokespecial	Method scala/xml/Utility$$anonfun$trimProper$1."<init>":()V
	getstatic	Field scala/collection/Seq$.MODULE$:Lscala/collection/Seq$;
	astore	6
	new	class scala/collection/generic/TraversableFactory$GenericCanBuildFrom
	dup
	aload	6
	invokespecial	Method scala/collection/generic/TraversableFactory$GenericCanBuildFrom."<init>":(Lscala/collection/generic/TraversableFactory;)V
	invokeinterface	InterfaceMethod scala/collection/TraversableLike.flatMap:(Lscala/Function1;Lscala/collection/generic/CanBuildFrom;)Ljava/lang/Object;
	checkcast	class scala/collection/Seq
	astore	11
	new	class scala/xml/Elem
	dup
	aload	7
	aload	8
	aload	9
	aload	10
	aload	11
	invokespecial	Method scala/xml/Elem."<init>":(Ljava/lang/String;Ljava/lang/String;Lscala/xml/MetaData;Lscala/xml/NamespaceBinding;Lscala/collection/Seq;)V
	goto	l12 // areturn
l11	new	class scala/MatchError
	dup
	aload_1
	invokevirtual	Method scala/xml/Node.toString:()Ljava/lang/String;
	invokespecial	Method scala/MatchError."<init>":(Ljava/lang/String;)V
	athrow
l10	getstatic	Field scala/xml/Text$.MODULE$:Lscala/xml/Text$;
	aload_1
	invokevirtual	Method scala/xml/Text$.unapply:(Ljava/lang/Object;)Lscala/Option;
	astore	12
	aload	12
	invokevirtual	Method scala/Option.isEmpty:()Z
	ifeq	l13 // aload
	iconst_1
	ifeq	l14 // new
l3	aload_1
	goto	l12 // areturn
l14	new	class scala/MatchError
	dup
	aload_1
	invokevirtual	Method scala/xml/Node.toString:()Ljava/lang/String;
	invokespecial	Method scala/MatchError."<init>":(Ljava/lang/String;)V
	athrow
l13	aload	12
	invokevirtual	Method scala/Option.get:()Ljava/lang/Object;
	checkcast	class java/lang/String
	astore	13
	iconst_1
	ifeq	l15 // new
	aload	13
	astore	14
l5	new	class scala/xml/TextBuffer
	dup
	invokespecial	Method scala/xml/TextBuffer."<init>":()V
	getstatic	Field scala/Predef$.MODULE$:Lscala/Predef$;
	aload	14
	invokevirtual	Method scala/Predef$.wrapString:(Ljava/lang/String;)Lscala/collection/immutable/WrappedString;
	invokevirtual	Method scala/xml/TextBuffer.append:(Lscala/collection/Seq;)Lscala/xml/TextBuffer;
	invokevirtual	Method scala/xml/TextBuffer.toText:()Lscala/collection/Seq;
l12	areturn
l15	new	class scala/MatchError
	dup
	aload_1
	invokevirtual	Method scala/xml/Node.toString:()Ljava/lang/String;
	invokespecial	Method scala/MatchError."<init>":(Ljava/lang/String;)V
	athrow
  Labels:
   	l2 = 46 // iconst_1
   	l4 = 62 // new
   	l1 = 74 // aload_3
   	l6 = 149 // iconst_0
   	l7 = 153 // aload
   	l9 = 169 // iconst_0
   	l8 = 170 // ifeq
   	l11 = 230 // new
   	l10 = 242 // getstatic
   	l3 = 263 // aload_1
   	l14 = 267 // new
   	l13 = 279 // aload
   	l5 = 297 // new
   	l12 = 318 // areturn
   	l15 = 319 // new
  LocalVariableTable: 
   Start  Length  Slot  Name   Signature
   0      331      0    this       Lscala/xml/Utility$;
   0      331      1    x       Lscala/xml/Node;
   23      51      2    temp21       Lscala/Option;
   8      323      3    temp11       Lscala/Option;
   83      235      4    temp12       Lscala/Tuple5;
   319      12      4    temp12       Lscala/Tuple5;
   133      185      5    temp17       Lscala/collection/Seq;
   319      12      5    temp17       Lscala/collection/Seq;
   93      225      7    temp13       Ljava/lang/String;
   319      12      7    temp13       Ljava/lang/String;
   103      215      8    temp14       Ljava/lang/String;
   319      12      8    temp14       Ljava/lang/String;
   113      205      9    temp15       Lscala/xml/MetaData;
   319      12      9    temp15       Lscala/xml/MetaData;
   123      195      10    temp16       Lscala/xml/NamespaceBinding;
   319      12      10    temp16       Lscala/xml/NamespaceBinding;
   251      67      12    temp19       Lscala/Option;
   319      12      12    temp19       Lscala/Option;
   289      29      13    temp20       Ljava/lang/String;
   319      12      13    temp20       Ljava/lang/String;
   289      4      14    s       Ljava/lang/String;
   297      0      14    s       Ljava/lang/String;
   293      25      14    s       Ljava/lang/String;
   319      12      14    s       Ljava/lang/String;

  Signature: length = 0x2
   02 FFFFFFBF 

public scala.xml.Node trim(scala.xml.Node);
  Signature: (Lscala/xml/Node;)Lscala/xml/Node;
  Code:
   Stack=7, Locals=11, Args_size=2
	getstatic	Field scala/xml/Elem$.MODULE$:Lscala/xml/Elem$;
	aload_1
	invokevirtual	Method scala/xml/Elem$.unapplySeq:(Lscala/xml/Node;)Lscala/Option;
	astore_2
	aload_2
	invokevirtual	Method scala/Option.isEmpty:()Z
	ifeq	l1 // aload_2
	new	class scala/MatchError
	dup
	aload_1
	invokevirtual	Method scala/xml/Node.toString:()Ljava/lang/String;
	invokespecial	Method scala/MatchError."<init>":(Ljava/lang/String;)V
	athrow
l1	aload_2
	invokevirtual	Method scala/Option.get:()Ljava/lang/Object;
	checkcast	class scala/Tuple5
	astore_3
	aload_3
	invokevirtual	Method scala/Tuple5._1:()Ljava/lang/Object;
	checkcast	class java/lang/String
	astore	6
	aload_3
	invokevirtual	Method scala/Tuple5._2:()Ljava/lang/Object;
	checkcast	class java/lang/String
	astore	7
	aload_3
	invokevirtual	Method scala/Tuple5._3:()Ljava/lang/Object;
	checkcast	class scala/xml/MetaData
	astore	8
	aload_3
	invokevirtual	Method scala/Tuple5._4:()Ljava/lang/Object;
	checkcast	class scala/xml/NamespaceBinding
	astore	9
	aload_3
	invokevirtual	Method scala/Tuple5._5:()Ljava/lang/Object;
	checkcast	class scala/collection/Seq
	astore	4
	aload	4
	dup
	pop
	ifnull	l2 // iconst_0
	aload	4
	aconst_null
	invokevirtual	Method java/lang/Object.equals:(Ljava/lang/Object;)Z
	ifeq	l3 // aload
l2	iconst_0
	goto	l4 // ifeq
l3	aload	4
	iconst_0
	invokeinterface	InterfaceMethod scala/collection/SeqLike.lengthCompare:(I)I
	iconst_0
	if_icmplt	l5 // iconst_0
	iconst_1
	goto	l4 // ifeq
l5	iconst_0
l4	ifeq	l6 // new
	iconst_1
	ifeq	l7 // new
	aload	4
	new	class scala/xml/Utility$$anonfun$trim$1
	dup
	invokespecial	Method scala/xml/Utility$$anonfun$trim$1."<init>":()V
	getstatic	Field scala/collection/Seq$.MODULE$:Lscala/collection/Seq$;
	astore	5
	new	class scala/collection/generic/TraversableFactory$GenericCanBuildFrom
	dup
	aload	5
	invokespecial	Method scala/collection/generic/TraversableFactory$GenericCanBuildFrom."<init>":(Lscala/collection/generic/TraversableFactory;)V
	invokeinterface	InterfaceMethod scala/collection/TraversableLike.flatMap:(Lscala/Function1;Lscala/collection/generic/CanBuildFrom;)Ljava/lang/Object;
	checkcast	class scala/collection/Seq
	astore	10
	new	class scala/xml/Elem
	dup
	aload	6
	aload	7
	aload	8
	aload	9
	aload	10
	invokespecial	Method scala/xml/Elem."<init>":(Ljava/lang/String;Ljava/lang/String;Lscala/xml/MetaData;Lscala/xml/NamespaceBinding;Lscala/collection/Seq;)V
	areturn
l7	new	class scala/MatchError
	dup
	aload_1
	invokevirtual	Method scala/xml/Node.toString:()Ljava/lang/String;
	invokespecial	Method scala/MatchError."<init>":(Ljava/lang/String;)V
	athrow
l6	new	class scala/MatchError
	dup
	aload_1
	invokevirtual	Method scala/xml/Node.toString:()Ljava/lang/String;
	invokespecial	Method scala/MatchError."<init>":(Ljava/lang/String;)V
	athrow
  Labels:
   	l1 = 27 // aload_2
   	l2 = 96 // iconst_0
   	l3 = 100 // aload
   	l5 = 116 // iconst_0
   	l4 = 117 // ifeq
   	l7 = 175 // new
   	l6 = 187 // new
  LocalVariableTable: 
   Start  Length  Slot  Name   Signature
   0      199      0    this       Lscala/xml/Utility$;
   0      199      1    x       Lscala/xml/Node;
   8      191      2    temp2       Lscala/Option;
   35      164      3    temp3       Lscala/Tuple5;
   80      119      4    temp8       Lscala/collection/Seq;
   44      155      6    temp4       Ljava/lang/String;
   53      146      7    temp5       Ljava/lang/String;
   62      137      8    temp6       Lscala/xml/MetaData;
   71      128      9    temp7       Lscala/xml/NamespaceBinding;


public boolean isAtomAndNotText(scala.xml.Node);
  Signature: (Lscala/xml/Node;)Z
  Code:
   Stack=1, Locals=2, Args_size=2
	aload_1
	invokevirtual	Method scala/xml/Node.isAtom:()Z
	ifeq	l1 // iconst_0
	aload_1
	instanceof	class scala/xml/Text
	ifne	l1 // iconst_0
	iconst_1
	goto	l2 // ireturn
l1	iconst_0
l2	ireturn
  Labels:
   	l1 = 18 // iconst_0
   	l2 = 19 // ireturn
  LocalVariableTable: 
   Start  Length  Slot  Name   Signature
   0      20      0    this       Lscala/xml/Utility$;
   0      20      1    x       Lscala/xml/Node;


public java.lang.String sbToString(scala.Function1);
  Signature: (Lscala/Function1;)Ljava/lang/String;
  Code:
   Stack=2, Locals=3, Args_size=2
	new	class scala/collection/mutable/StringBuilder
	dup
	invokespecial	Method scala/collection/mutable/StringBuilder."<init>":()V
	astore_2
	aload_1
	aload_2
	invokeinterface	InterfaceMethod scala/Function1.apply:(Ljava/lang/Object;)Ljava/lang/Object;
	pop
	aload_2
	invokevirtual	Method scala/collection/mutable/StringBuilder.toString:()Ljava/lang/String;
	areturn
  Labels:
  LocalVariableTable: 
   Start  Length  Slot  Name   Signature
   0      21      0    this       Lscala/xml/Utility$;
   0      21      1    f       Lscala/Function1;
   8      12      2    sb       Lscala/collection/mutable/StringBuilder;

  Signature: length = 0x2
   02 FFFFFFD4 

public java.lang.String implicitSbToString(scala.collection.mutable.StringBuilder);
  Signature: (Lscala/collection/mutable/StringBuilder;)Ljava/lang/String;
  Code:
   Stack=1, Locals=2, Args_size=2
	aload_1
	invokevirtual	Method scala/collection/mutable/StringBuilder.toString:()Ljava/lang/String;
	areturn
  Labels:
  LocalVariableTable: 
   Start  Length  Slot  Name   Signature
   0      5      0    this       Lscala/xml/Utility$;
   0      5      1    sb       Lscala/collection/mutable/StringBuilder;


public scala.xml.NamespaceBinding toXML$default$2();
  Signature: ()Lscala/xml/NamespaceBinding;
  Code:
   Stack=1, Locals=1, Args_size=1
	getstatic	Field scala/xml/TopScope$.MODULE$:Lscala/xml/TopScope$;
	areturn
  Labels:

public scala.collection.mutable.StringBuilder toXML$default$3();
  Signature: ()Lscala/collection/mutable/StringBuilder;
  Code:
   Stack=2, Locals=1, Args_size=1
	new	class scala/collection/mutable/StringBuilder
	dup
	invokespecial	Method scala/collection/mutable/StringBuilder."<init>":()V
	areturn
  Labels:

public boolean toXML$default$4();
  Signature: ()Z
  Code:
   Stack=1, Locals=1, Args_size=1
	iconst_0
	ireturn
  Labels:

public boolean toXML$default$5();
  Signature: ()Z
  Code:
   Stack=1, Locals=1, Args_size=1
	iconst_1
	ireturn
  Labels:

public boolean toXML$default$6();
  Signature: ()Z
  Code:
   Stack=1, Locals=1, Args_size=1
	iconst_0
	ireturn
  Labels:

public boolean toXML$default$7();
  Signature: ()Z
  Code:
   Stack=1, Locals=1, Args_size=1
	iconst_0
	ireturn
  Labels:

public scala.xml.NamespaceBinding sequenceToXML$default$2();
  Signature: ()Lscala/xml/NamespaceBinding;
  Code:
   Stack=1, Locals=1, Args_size=1
	getstatic	Field scala/xml/TopScope$.MODULE$:Lscala/xml/TopScope$;
	areturn
  Labels:

public scala.collection.mutable.StringBuilder sequenceToXML$default$3();
  Signature: ()Lscala/collection/mutable/StringBuilder;
  Code:
   Stack=2, Locals=1, Args_size=1
	new	class scala/collection/mutable/StringBuilder
	dup
	invokespecial	Method scala/collection/mutable/StringBuilder."<init>":()V
	areturn
  Labels:

public boolean sequenceToXML$default$4();
  Signature: ()Z
  Code:
   Stack=1, Locals=1, Args_size=1
	iconst_0
	ireturn
  Labels:

public boolean checkPubID(java.lang.String);
  Signature: (Ljava/lang/String;)Z
  Code:
   Stack=2, Locals=2, Args_size=2
	aload_0
	aload_1
	invokestatic	Method scala/xml/parsing/TokenTests$class.checkPubID:(Lscala/xml/parsing/TokenTests;Ljava/lang/String;)Z
	ireturn
  Labels:
  LocalVariableTable: 
   Start  Length  Slot  Name   Signature
   0      6      0    this       Lscala/xml/Utility$;
   0      6      1    s       Ljava/lang/String;


public boolean checkSysID(java.lang.String);
  Signature: (Ljava/lang/String;)Z
  Code:
   Stack=2, Locals=2, Args_size=2
	aload_0
	aload_1
	invokestatic	Method scala/xml/parsing/TokenTests$class.checkSysID:(Lscala/xml/parsing/TokenTests;Ljava/lang/String;)Z
	ireturn
  Labels:
  LocalVariableTable: 
   Start  Length  Slot  Name   Signature
   0      6      0    this       Lscala/xml/Utility$;
   0      6      1    s       Ljava/lang/String;


public boolean isValidIANAEncoding(scala.collection.Seq);
  Signature: (Lscala/collection/Seq;)Z
  Code:
   Stack=2, Locals=2, Args_size=2
	aload_0
	aload_1
	invokestatic	Method scala/xml/parsing/TokenTests$class.isValidIANAEncoding:(Lscala/xml/parsing/TokenTests;Lscala/collection/Seq;)Z
	ireturn
  Labels:
  LocalVariableTable: 
   Start  Length  Slot  Name   Signature
   0      6      0    this       Lscala/xml/Utility$;
   0      6      1    ianaEncoding       Lscala/collection/Seq;


public boolean isPubIDChar(char);
  Signature: (C)Z
  Code:
   Stack=2, Locals=2, Args_size=2
	aload_0
	iload_1
	invokestatic	Method scala/xml/parsing/TokenTests$class.isPubIDChar:(Lscala/xml/parsing/TokenTests;C)Z
	ireturn
  Labels:
  LocalVariableTable: 
   Start  Length  Slot  Name   Signature
   0      6      0    this       Lscala/xml/Utility$;
   0      6      1    ch       C


public boolean isName(java.lang.String);
  Signature: (Ljava/lang/String;)Z
  Code:
   Stack=2, Locals=2, Args_size=2
	aload_0
	aload_1
	invokestatic	Method scala/xml/parsing/TokenTests$class.isName:(Lscala/xml/parsing/TokenTests;Ljava/lang/String;)Z
	ireturn
  Labels:
  LocalVariableTable: 
   Start  Length  Slot  Name   Signature
   0      6      0    this       Lscala/xml/Utility$;
   0      6      1    s       Ljava/lang/String;


public boolean isNameStart(char);
  Signature: (C)Z
  Code:
   Stack=2, Locals=2, Args_size=2
	aload_0
	iload_1
	invokestatic	Method scala/xml/parsing/TokenTests$class.isNameStart:(Lscala/xml/parsing/TokenTests;C)Z
	ireturn
  Labels:
  LocalVariableTable: 
   Start  Length  Slot  Name   Signature
   0      6      0    this       Lscala/xml/Utility$;
   0      6      1    ch       C


public boolean isNameChar(char);
  Signature: (C)Z
  Code:
   Stack=2, Locals=2, Args_size=2
	aload_0
	iload_1
	invokestatic	Method scala/xml/parsing/TokenTests$class.isNameChar:(Lscala/xml/parsing/TokenTests;C)Z
	ireturn
  Labels:
  LocalVariableTable: 
   Start  Length  Slot  Name   Signature
   0      6      0    this       Lscala/xml/Utility$;
   0      6      1    ch       C


public boolean isAlphaDigit(char);
  Signature: (C)Z
  Code:
   Stack=2, Locals=2, Args_size=2
	aload_0
	iload_1
	invokestatic	Method scala/xml/parsing/TokenTests$class.isAlphaDigit:(Lscala/xml/parsing/TokenTests;C)Z
	ireturn
  Labels:
  LocalVariableTable: 
   Start  Length  Slot  Name   Signature
   0      6      0    this       Lscala/xml/Utility$;
   0      6      1    c       C


public boolean isAlpha(char);
  Signature: (C)Z
  Code:
   Stack=2, Locals=2, Args_size=2
	aload_0
	iload_1
	invokestatic	Method scala/xml/parsing/TokenTests$class.isAlpha:(Lscala/xml/parsing/TokenTests;C)Z
	ireturn
  Labels:
  LocalVariableTable: 
   Start  Length  Slot  Name   Signature
   0      6      0    this       Lscala/xml/Utility$;
   0      6      1    c       C


public final boolean isSpace(scala.collection.Seq);
  Signature: (Lscala/collection/Seq;)Z
  Code:
   Stack=2, Locals=2, Args_size=2
	aload_0
	aload_1
	invokestatic	Method scala/xml/parsing/TokenTests$class.isSpace:(Lscala/xml/parsing/TokenTests;Lscala/collection/Seq;)Z
	ireturn
  Labels:
  LocalVariableTable: 
   Start  Length  Slot  Name   Signature
   0      6      0    this       Lscala/xml/Utility$;
   0      6      1    cs       Lscala/collection/Seq;


public final boolean isSpace(char);
  Signature: (C)Z
  Code:
   Stack=2, Locals=2, Args_size=2
	aload_0
	iload_1
	invokestatic	Method scala/xml/parsing/TokenTests$class.isSpace:(Lscala/xml/parsing/TokenTests;C)Z
	ireturn
  Labels:
  LocalVariableTable: 
   Start  Length  Slot  Name   Signature
   0      6      0    this       Lscala/xml/Utility$;
   0      6      1    ch       C


}

