Compiled from "Utility.scala"
public final class scala.xml.Utility$$anonfun$escape$2 extends java.lang.Object implements scala.Function2,scala.ScalaObject,java.io.Serializable
  SourceFile: "Utility.scala"
  Scala: length = 0x
   
  InnerClass: 
   public final $anonfun$escape$2=class scala/xml/Utility$$anonfun$escape$2 of class scala/xml/Utility
  minor version: 0
  major version: 49
  Constant pool:
Asciz	SourceFile;
Asciz	Utility.scala;
Asciz	<clinit>;
Asciz	()V;
Asciz	Code;
Asciz	serialVersionUID;
Asciz	J;
Asciz	scala/xml/Utility$$anonfun$escape$2;
class	scala/xml/Utility$$anonfun$escape$2
NameAndType	serialVersionUID:J
Field	scala/xml/Utility$$anonfun$escape$2.serialVersionUID:J
Asciz	<init>;
Asciz	LineNumberTable;
Asciz	java/lang/Object;
class	java/lang/Object
NameAndType	"<init>":()V
Method	java/lang/Object."<init>":()V
Asciz	scala/Function2$class;
class	scala/Function2$class
Asciz	$init$;
Asciz	(Lscala/Function2;)V;
NameAndType	$init$:(Lscala/Function2;)V
Method	scala/Function2$class.$init$:(Lscala/Function2;)V
Asciz	apply;
Asciz	(Ljava/lang/Object;Ljava/lang/Object;)Ljava/lang/Object;;
Asciz	scala/collection/mutable/StringBuilder;
class	scala/collection/mutable/StringBuilder
Asciz	scala/runtime/BoxesRunTime;
class	scala/runtime/BoxesRunTime
Asciz	unboxToChar;
Asciz	(Ljava/lang/Object;)C;
NameAndType	unboxToChar:(Ljava/lang/Object;)C
Method	scala/runtime/BoxesRunTime.unboxToChar:(Ljava/lang/Object;)C
Asciz	(Lscala/collection/mutable/StringBuilder;C)Lscala/collection/mutable/StringBuilder;;
NameAndType	apply:(Lscala/collection/mutable/StringBuilder;C)Lscala/collection/mutable/StringBuilder;
Method	scala/xml/Utility$$anonfun$escape$2.apply:(Lscala/collection/mutable/StringBuilder;C)Lscala/collection/mutable/StringBuilder;
Asciz	this;
Asciz	Lscala/xml/Utility$$anonfun$escape$2;;
Asciz	v1;
Asciz	Ljava/lang/Object;;
Asciz	v2;
Asciz	LocalVariableTable;
Asciz	scala/xml/Utility$Escapes$;
class	scala/xml/Utility$Escapes$
Asciz	MODULE$;
Asciz	Lscala/xml/Utility$Escapes$;;
NameAndType	MODULE$:Lscala/xml/Utility$Escapes$;
Field	scala/xml/Utility$Escapes$.MODULE$:Lscala/xml/Utility$Escapes$;
Asciz	escMap;
Asciz	()Lscala/collection/immutable/Map;;
NameAndType	escMap:()Lscala/collection/immutable/Map;
Method	scala/xml/Utility$Escapes$.escMap:()Lscala/collection/immutable/Map;
Asciz	boxToCharacter;
Asciz	(C)Ljava/lang/Character;;
NameAndType	boxToCharacter:(C)Ljava/lang/Character;
Method	scala/runtime/BoxesRunTime.boxToCharacter:(C)Ljava/lang/Character;
Asciz	scala/collection/MapLike;
class	scala/collection/MapLike
Asciz	get;
Asciz	(Ljava/lang/Object;)Lscala/Option;;
NameAndType	get:(Ljava/lang/Object;)Lscala/Option;
InterfaceMethod	scala/collection/MapLike.get:(Ljava/lang/Object;)Lscala/Option;
Asciz	scala/Some;
class	scala/Some
Asciz	x;
NameAndType	x:Ljava/lang/Object;
Field	scala/Some.x:Ljava/lang/Object;
Asciz	java/lang/String;
class	java/lang/String
Asciz	append;
Asciz	(Ljava/lang/String;)Lscala/collection/mutable/StringBuilder;;
NameAndType	append:(Ljava/lang/String;)Lscala/collection/mutable/StringBuilder;
Method	scala/collection/mutable/StringBuilder.append:(Ljava/lang/String;)Lscala/collection/mutable/StringBuilder;
Asciz	scala/MatchError;
class	scala/MatchError
Asciz	scala/Option;
class	scala/Option
Asciz	toString;
Asciz	()Ljava/lang/String;;
NameAndType	toString:()Ljava/lang/String;
Method	scala/Option.toString:()Ljava/lang/String;
Asciz	(Ljava/lang/String;)V;
NameAndType	"<init>":(Ljava/lang/String;)V
Method	scala/MatchError."<init>":(Ljava/lang/String;)V
Asciz	scala/None$;
class	scala/None$
Asciz	Lscala/None$;;
NameAndType	MODULE$:Lscala/None$;
Field	scala/None$.MODULE$:Lscala/None$;
Asciz	equals;
Asciz	(Ljava/lang/Object;)Z;
NameAndType	equals:(Ljava/lang/Object;)Z
Method	java/lang/Object.equals:(Ljava/lang/Object;)Z
Asciz	(C)Lscala/collection/mutable/StringBuilder;;
NameAndType	append:(C)Lscala/collection/mutable/StringBuilder;
Method	scala/collection/mutable/StringBuilder.append:(C)Lscala/collection/mutable/StringBuilder;
Asciz	s;
Asciz	Lscala/collection/mutable/StringBuilder;;
Asciz	c;
Asciz	C;
Asciz	temp36;
Asciz	Lscala/Some;;
Asciz	temp37;
Asciz	Ljava/lang/String;;
Asciz	temp35;
Asciz	Lscala/Option;;
Asciz	curry;
Asciz	()Lscala/Function1;;
Asciz	(Lscala/Function2;)Lscala/Function1;;
NameAndType	curry:(Lscala/Function2;)Lscala/Function1;
Method	scala/Function2$class.curry:(Lscala/Function2;)Lscala/Function1;
Asciz	(Lscala/Function2;)Ljava/lang/String;;
NameAndType	toString:(Lscala/Function2;)Ljava/lang/String;
Method	scala/Function2$class.toString:(Lscala/Function2;)Ljava/lang/String;
Asciz	Scala;
Asciz	InnerClasses;
Asciz	scala/xml/Utility;
class	scala/xml/Utility
Asciz	$anonfun$escape$2;
Asciz	scala/Function2;
class	scala/Function2
Asciz	scala/ScalaObject;
class	scala/ScalaObject
Asciz	java/io/Serializable;
class	java/io/Serializable

{
public static final long serialVersionUID;
  Signature: J

public static {};
  Signature: ()V
  Code:
   Stack=2, Locals=0, Args_size=0
	lconst_0
	putstatic	Field serialVersionUID:J
	return
  Labels:

public scala.xml.Utility$$anonfun$escape$2();
  Signature: ()V
  Code:
   Stack=1, Locals=1, Args_size=1
	aload_0
	invokespecial	Method java/lang/Object."<init>":()V
	aload_0
	invokestatic	Method scala/Function2$class.$init$:(Lscala/Function2;)V
	return
  Labels:

public final java.lang.Object apply(java.lang.Object, java.lang.Object);
  Signature: (Ljava/lang/Object;Ljava/lang/Object;)Ljava/lang/Object;
  Code:
   Stack=3, Locals=3, Args_size=3
	aload_0
	aload_1
	checkcast	class scala/collection/mutable/StringBuilder
	aload_2
	invokestatic	Method scala/runtime/BoxesRunTime.unboxToChar:(Ljava/lang/Object;)C
	invokevirtual	Method apply:(Lscala/collection/mutable/StringBuilder;C)Lscala/collection/mutable/StringBuilder;
	areturn
  Labels:
  LocalVariableTable: 
   Start  Length  Slot  Name   Signature
   0      13      0    this       Lscala/xml/Utility$$anonfun$escape$2;
   0      13      1    v1       Ljava/lang/Object;
   0      13      2    v2       Ljava/lang/Object;


public final scala.collection.mutable.StringBuilder apply(scala.collection.mutable.StringBuilder, char);
  Signature: (Lscala/collection/mutable/StringBuilder;C)Lscala/collection/mutable/StringBuilder;
  Code:
   Stack=3, Locals=6, Args_size=3
	getstatic	Field scala/xml/Utility$Escapes$.MODULE$:Lscala/xml/Utility$Escapes$;
	invokevirtual	Method scala/xml/Utility$Escapes$.escMap:()Lscala/collection/immutable/Map;
	iload_2
	invokestatic	Method scala/runtime/BoxesRunTime.boxToCharacter:(C)Ljava/lang/Character;
	invokeinterface	InterfaceMethod scala/collection/MapLike.get:(Ljava/lang/Object;)Lscala/Option;
	astore	5
	aload	5
	instanceof	class scala/Some
	ifeq	l1 // getstatic
	aload	5
	checkcast	class scala/Some
	astore_3
	aload_3
	getfield	Field scala/Some.x:Ljava/lang/Object;
	checkcast	class java/lang/String
	astore	4
	iconst_1
	ifeq	l2 // new
	aload_1
	aload	4
	invokevirtual	Method scala/collection/mutable/StringBuilder.append:(Ljava/lang/String;)Lscala/collection/mutable/StringBuilder;
	goto	l3 // areturn
l2	new	class scala/MatchError
	dup
	aload	5
	invokevirtual	Method scala/Option.toString:()Ljava/lang/String;
	invokespecial	Method scala/MatchError."<init>":(Ljava/lang/String;)V
	athrow
l1	getstatic	Field scala/None$.MODULE$:Lscala/None$;
	dup
	ifnonnull	l4 // aload
	pop
	aload	5
	ifnull	l5 // iconst_1
	goto	l6 // new
l4	aload	5
	invokevirtual	Method java/lang/Object.equals:(Ljava/lang/Object;)Z
	ifeq	l6 // new
l5	iconst_1
	ifeq	l7 // new
	aload_1
	iload_2
	invokevirtual	Method scala/collection/mutable/StringBuilder.append:(C)Lscala/collection/mutable/StringBuilder;
l3	areturn
l7	new	class scala/MatchError
	dup
	aload	5
	invokevirtual	Method scala/Option.toString:()Ljava/lang/String;
	invokespecial	Method scala/MatchError."<init>":(Ljava/lang/String;)V
	athrow
l6	new	class scala/MatchError
	dup
	aload	5
	invokevirtual	Method scala/Option.toString:()Ljava/lang/String;
	invokespecial	Method scala/MatchError."<init>":(Ljava/lang/String;)V
	athrow
  Labels:
   	l2 = 53 // new
   	l1 = 66 // getstatic
   	l4 = 82 // aload
   	l5 = 90 // iconst_1
   	l3 = 99 // areturn
   	l7 = 100 // new
   	l6 = 113 // new
  LocalVariableTable: 
   Start  Length  Slot  Name   Signature
   0      126      0    this       Lscala/xml/Utility$$anonfun$escape$2;
   0      126      1    s       Lscala/collection/mutable/StringBuilder;
   0      126      2    c       C
   31      35      3    temp36       Lscala/Some;
   40      26      4    temp37       Ljava/lang/String;
   17      109      5    temp35       Lscala/Option;


public scala.Function1 curry();
  Signature: ()Lscala/Function1;
  Code:
   Stack=1, Locals=1, Args_size=1
	aload_0
	invokestatic	Method scala/Function2$class.curry:(Lscala/Function2;)Lscala/Function1;
	areturn
  Labels:

public java.lang.String toString();
  Signature: ()Ljava/lang/String;
  Code:
   Stack=1, Locals=1, Args_size=1
	aload_0
	invokestatic	Method scala/Function2$class.toString:(Lscala/Function2;)Ljava/lang/String;
	areturn
  Labels:

}

