Compiled from "Utility.scala"
public final class scala.xml.Utility$ extends java.lang.Object implements scala.xml.parsing.TokenTests,scala.ScalaObject
  SourceFile: "Utility.scala"
  Scala: length = 0x
   
  InnerClass: 
   public final #789= #236 of #788; //$anon$1=class scala/Predef$$anon$1 of class scala/Predef
   public final #792= #195 of #791; //$anonfun$6=class scala/xml/Utility$$anonfun$6 of class scala/xml/Utility
   public final #793= #190 of #791; //$anonfun$5=class scala/xml/Utility$$anonfun$5 of class scala/xml/Utility
   public final #794= #185 of #791; //$anonfun$4=class scala/xml/Utility$$anonfun$4 of class scala/xml/Utility
   public final #795= #657 of #791; //$anonfun$2=class scala/xml/Utility$$anonfun$2 of class scala/xml/Utility
   public final #796= #650 of #791; //$anonfun$1=class scala/xml/Utility$$anonfun$1 of class scala/xml/Utility
   public final #799= #122 of #798; //$anonfun$apply$6=class scala/Array$$anonfun$apply$6 of class scala/Array
   public abstract #802= #801 of #788; //$less$colon$less=class scala/Predef$$less$colon$less of class scala/Predef
   public final #803= #614 of #791; //$anonfun$sort$1=class scala/xml/Utility$$anonfun$sort$1 of class scala/xml/Utility
   public final #804= #712 of #791; //$anonfun$trim$1=class scala/xml/Utility$$anonfun$trim$1 of class scala/xml/Utility
   public final #805= #478 of #791; //$anonfun$toXML$1=class scala/xml/Utility$$anonfun$toXML$1 of class scala/xml/Utility
   public final #806= #572 of #791; //$anonfun$escape$2=class scala/xml/Utility$$anonfun$escape$2 of class scala/xml/Utility
   public final #807= #577 of #791; //$anonfun$escape$1=class scala/xml/Utility$$anonfun$escape$1 of class scala/xml/Utility
   public final #808= #339 of #791; //$anonfun$getName$1=class scala/xml/Utility$$anonfun$getName$1 of class scala/xml/Utility
   public final #809= #225 of #791; //$anonfun$unescape$1=class scala/xml/Utility$$anonfun$unescape$1 of class scala/xml/Utility
   public final #810= #681 of #791; //$anonfun$trimProper$1=class scala/xml/Utility$$anonfun$trimProper$1 of class scala/xml/Utility
   public final #811= #379 of #791; //$anonfun$appendQuoted$1=class scala/xml/Utility$$anonfun$appendQuoted$1 of class scala/xml/Utility
   public final #812= #446 of #791; //$anonfun$sequenceToXML$2=class scala/xml/Utility$$anonfun$sequenceToXML$2 of class scala/xml/Utility
   public final #813= #434 of #791; //$anonfun$sequenceToXML$1=class scala/xml/Utility$$anonfun$sequenceToXML$1 of class scala/xml/Utility
   public final #814= #542 of #791; //$anonfun$collectNamespaces$3=class scala/xml/Utility$$anonfun$collectNamespaces$3 of class scala/xml/Utility
   public final #815= #538 of #791; //$anonfun$collectNamespaces$2=class scala/xml/Utility$$anonfun$collectNamespaces$2 of class scala/xml/Utility
   public final #816= #555 of #791; //$anonfun$collectNamespaces$1=class scala/xml/Utility$$anonfun$collectNamespaces$1 of class scala/xml/Utility
   public #819= #617 of #818; //GenericCanBuildFrom=class scala/collection/generic/TraversableFactory$GenericCanBuildFrom of class scala/collection/generic/TraversableFactory
   public final #820= #369 of #791; //$anonfun$appendEscapedQuoted$1=class scala/xml/Utility$$anonfun$appendEscapedQuoted$1 of class scala/xml/Utility
  minor version: 0
  major version: 49
  Constant pool:
const #1 = Asciz	SourceFile;
const #2 = Asciz	Utility.scala;
const #3 = Asciz	Scala;
const #4 = Asciz	MODULE$;
const #5 = Asciz	Lscala/xml/Utility$;;
const #6 = Asciz	<clinit>;
const #7 = Asciz	()V;
const #8 = Asciz	Code;
const #9 = Asciz	scala/xml/Utility$;
const #10 = class	#9;	//  scala/xml/Utility$
const #11 = Asciz	<init>;
const #12 = NameAndType	#11:#7;//  "<init>":()V
const #13 = Method	#10.#12;	//  scala/xml/Utility$."<init>":()V
const #14 = Asciz	LineNumberTable;
const #15 = Asciz	java/lang/Object;
const #16 = class	#15;	//  java/lang/Object
const #17 = Method	#16.#12;	//  java/lang/Object."<init>":()V
const #18 = NameAndType	#4:#5;//  MODULE$:Lscala/xml/Utility$;
const #19 = Field	#10.#18;	//  scala/xml/Utility$.MODULE$:Lscala/xml/Utility$;
const #20 = Asciz	scala/xml/parsing/TokenTests$class;
const #21 = class	#20;	//  scala/xml/parsing/TokenTests$class
const #22 = Asciz	$init$;
const #23 = Asciz	(Lscala/xml/parsing/TokenTests;)V;
const #24 = NameAndType	#22:#23;//  $init$:(Lscala/xml/parsing/TokenTests;)V
const #25 = Method	#21.#24;	//  scala/xml/parsing/TokenTests$class.$init$:(Lscala/xml/parsing/TokenTests;)V
const #26 = Asciz	gd2$1;
const #27 = Asciz	(CLscala/collection/Seq;)Z;
const #28 = Asciz	scala/xml/parsing/TokenTests;
const #29 = class	#28;	//  scala/xml/parsing/TokenTests
const #30 = Asciz	isNameStart;
const #31 = Asciz	(C)Z;
const #32 = NameAndType	#30:#31;//  isNameStart:(C)Z
const #33 = InterfaceMethod	#29.#32;	//  scala/xml/parsing/TokenTests.isNameStart:(C)Z
const #34 = Asciz	gd1$1;
const #35 = Asciz	(Lscala/xml/Comment;Z)Z;
const #36 = Asciz	parseCharRef;
const #37 = Asciz	(Lscala/Function0;Lscala/Function0;Lscala/Function1;)Ljava/lang/String;;
const #38 = Asciz	scala/Function0;
const #39 = class	#38;	//  scala/Function0
const #40 = Asciz	apply;
const #41 = Asciz	()Ljava/lang/Object;;
const #42 = NameAndType	#40:#41;//  apply:()Ljava/lang/Object;
const #43 = InterfaceMethod	#39.#42;	//  scala/Function0.apply:()Ljava/lang/Object;
const #44 = Asciz	scala/runtime/BoxesRunTime;
const #45 = class	#44;	//  scala/runtime/BoxesRunTime
const #46 = Asciz	unboxToChar;
const #47 = Asciz	(Ljava/lang/Object;)C;
const #48 = NameAndType	#46:#47;//  unboxToChar:(Ljava/lang/Object;)C
const #49 = Method	#45.#48;	//  scala/runtime/BoxesRunTime.unboxToChar:(Ljava/lang/Object;)C
const #50 = int	120;
const #51 = int	16;
const #52 = int	10;
const #53 = int	59;
const #54 = Asciz	scala/collection/mutable/StringBuilder;
const #55 = class	#54;	//  scala/collection/mutable/StringBuilder
const #56 = Method	#55.#12;	//  scala/collection/mutable/StringBuilder."<init>":()V
const #57 = Asciz	character ';
const #58 = String	#57;	//  character '
const #59 = Asciz	append;
const #60 = Asciz	(Ljava/lang/Object;)Lscala/collection/mutable/StringBuilder;;
const #61 = NameAndType	#59:#60;//  append:(Ljava/lang/Object;)Lscala/collection/mutable/StringBuilder;
const #62 = Method	#55.#61;	//  scala/collection/mutable/StringBuilder.append:(Ljava/lang/Object;)Lscala/collection/mutable/StringBuilder;
const #63 = Asciz	' not allowed in char ref\n;
const #64 = String	#63;	//  ' not allowed in char ref\n
const #65 = Asciz	toString;
const #66 = Asciz	()Ljava/lang/String;;
const #67 = NameAndType	#65:#66;//  toString:()Ljava/lang/String;
const #68 = Method	#55.#67;	//  scala/collection/mutable/StringBuilder.toString:()Ljava/lang/String;
const #69 = Asciz	scala/Function1;
const #70 = class	#69;	//  scala/Function1
const #71 = Asciz	(Ljava/lang/Object;)Ljava/lang/Object;;
const #72 = NameAndType	#40:#71;//  apply:(Ljava/lang/Object;)Ljava/lang/Object;
const #73 = InterfaceMethod	#70.#72;	//  scala/Function1.apply:(Ljava/lang/Object;)Ljava/lang/Object;
const #74 = Asciz	scala/MatchError;
const #75 = class	#74;	//  scala/MatchError
const #76 = Asciz	boxToCharacter;
const #77 = Asciz	(C)Ljava/lang/Character;;
const #78 = NameAndType	#76:#77;//  boxToCharacter:(C)Ljava/lang/Character;
const #79 = Method	#45.#78;	//  scala/runtime/BoxesRunTime.boxToCharacter:(C)Ljava/lang/Character;
const #80 = Method	#16.#67;	//  java/lang/Object.toString:()Ljava/lang/String;
const #81 = Asciz	(Ljava/lang/String;)V;
const #82 = NameAndType	#11:#81;//  "<init>":(Ljava/lang/String;)V
const #83 = Method	#75.#82;	//  scala/MatchError."<init>":(Ljava/lang/String;)V
const #84 = int	36;
const #85 = Asciz	java/lang/Character;
const #86 = class	#85;	//  java/lang/Character
const #87 = Asciz	digit;
const #88 = Asciz	(CI)I;
const #89 = NameAndType	#87:#88;//  digit:(CI)I
const #90 = Method	#86.#89;	//  java/lang/Character.digit:(CI)I
const #91 = Asciz	hex char not allowed in decimal char ref\nDid you mean to write &#x ?;
const #92 = String	#91;	//  hex char not allowed in decimal char ref\nDid you mean to write &#x ?
const #93 = Asciz	java/lang/String;
const #94 = class	#93;	//  java/lang/String
const #95 = Asciz	scala/Predef$;
const #96 = class	#95;	//  scala/Predef$
const #97 = Asciz	Lscala/Predef$;;
const #98 = NameAndType	#4:#97;//  MODULE$:Lscala/Predef$;
const #99 = Field	#96.#98;	//  scala/Predef$.MODULE$:Lscala/Predef$;
const #100 = Asciz	wrapIntArray;
const #101 = Asciz	([I)Lscala/collection/mutable/WrappedArray;;
const #102 = NameAndType	#100:#101;//  wrapIntArray:([I)Lscala/collection/mutable/WrappedArray;
const #103 = Method	#96.#102;	//  scala/Predef$.wrapIntArray:([I)Lscala/collection/mutable/WrappedArray;
const #104 = Asciz	scala/collection/SeqLike;
const #105 = class	#104;	//  scala/collection/SeqLike
const #106 = Asciz	length;
const #107 = Asciz	()I;
const #108 = NameAndType	#106:#107;//  length:()I
const #109 = InterfaceMethod	#105.#108;	//  scala/collection/SeqLike.length:()I
const #110 = Asciz	scala/runtime/IntRef;
const #111 = class	#110;	//  scala/runtime/IntRef
const #112 = Asciz	(I)V;
const #113 = NameAndType	#11:#112;//  "<init>":(I)V
const #114 = Method	#111.#113;	//  scala/runtime/IntRef."<init>":(I)V
const #115 = Asciz	scala/collection/IterableLike;
const #116 = class	#115;	//  scala/collection/IterableLike
const #117 = Asciz	iterator;
const #118 = Asciz	()Lscala/collection/Iterator;;
const #119 = NameAndType	#117:#118;//  iterator:()Lscala/collection/Iterator;
const #120 = InterfaceMethod	#116.#119;	//  scala/collection/IterableLike.iterator:()Lscala/collection/Iterator;
const #121 = Asciz	scala/Array$$anonfun$apply$6;
const #122 = class	#121;	//  scala/Array$$anonfun$apply$6
const #123 = Asciz	([ILscala/runtime/IntRef;)V;
const #124 = NameAndType	#11:#123;//  "<init>":([ILscala/runtime/IntRef;)V
const #125 = Method	#122.#124;	//  scala/Array$$anonfun$apply$6."<init>":([ILscala/runtime/IntRef;)V
const #126 = Asciz	scala/collection/Iterator;
const #127 = class	#126;	//  scala/collection/Iterator
const #128 = Asciz	foreach;
const #129 = Asciz	(Lscala/Function1;)V;
const #130 = NameAndType	#128:#129;//  foreach:(Lscala/Function1;)V
const #131 = InterfaceMethod	#127.#130;	//  scala/collection/Iterator.foreach:(Lscala/Function1;)V
const #132 = Asciz	([III)V;
const #133 = NameAndType	#11:#132;//  "<init>":([III)V
const #134 = Method	#94.#133;	//  java/lang/String."<init>":([III)V
const #135 = Asciz	this;
const #136 = Asciz	ch;
const #137 = Asciz	Lscala/Function0;;
const #138 = Asciz	nextch;
const #139 = Asciz	reportSyntaxError;
const #140 = Asciz	Lscala/Function1;;
const #141 = Asciz	hex;
const #142 = Asciz	Z;
const #143 = Asciz	base;
const #144 = Asciz	I;
const #145 = Asciz	temp58;
const #146 = Asciz	C;
const #147 = Asciz	i;
const #148 = Asciz	i$60;
const #149 = Asciz	Lscala/runtime/IntRef;;
const #150 = Asciz	array$60;
const #151 = Asciz	[I;
const #152 = Asciz	LocalVariableTable;
const #153 = Asciz	(Lscala/Function0<Ljava/lang/Character;>;Lscala/Function0<Ljava/lang/Object;>;Lscala/Function1<Ljava/lang/String;Ljava/lang/Object;>;)Ljava/lang/String;;
const #154 = Asciz	Signature;
const #155 = Asciz	parseAttributeValue;
const #156 = Asciz	(Ljava/lang/String;)Lscala/collection/Seq;;
const #157 = Method	#55.#12;	//  scala/collection/mutable/StringBuilder."<init>":()V
const #158 = Asciz	scala/xml/NodeBuffer;
const #159 = class	#158;	//  scala/xml/NodeBuffer
const #160 = Method	#159.#12;	//  scala/xml/NodeBuffer."<init>":()V
const #161 = Asciz	scala/collection/immutable/StringOps;
const #162 = class	#161;	//  scala/collection/immutable/StringOps
const #163 = Method	#162.#82;	//  scala/collection/immutable/StringOps."<init>":(Ljava/lang/String;)V
const #164 = Asciz	scala/collection/IndexedSeqLike;
const #165 = class	#164;	//  scala/collection/IndexedSeqLike
const #166 = InterfaceMethod	#165.#119;	//  scala/collection/IndexedSeqLike.iterator:()Lscala/collection/Iterator;
const #167 = Asciz	hasNext;
const #168 = Asciz	()Z;
const #169 = NameAndType	#167:#168;//  hasNext:()Z
const #170 = InterfaceMethod	#127.#169;	//  scala/collection/Iterator.hasNext:()Z
const #171 = Asciz	scala/runtime/CharRef;
const #172 = class	#171;	//  scala/runtime/CharRef
const #173 = Asciz	next;
const #174 = NameAndType	#173:#41;//  next:()Ljava/lang/Object;
const #175 = InterfaceMethod	#127.#174;	//  scala/collection/Iterator.next:()Ljava/lang/Object;
const #176 = Asciz	(C)V;
const #177 = NameAndType	#11:#176;//  "<init>":(C)V
const #178 = Method	#172.#177;	//  scala/runtime/CharRef."<init>":(C)V
const #179 = Asciz	elem;
const #180 = NameAndType	#179:#146;//  elem:C
const #181 = Field	#172.#180;	//  scala/runtime/CharRef.elem:C
const #182 = int	38;
const #183 = int	35;
const #184 = Asciz	scala/xml/Utility$$anonfun$4;
const #185 = class	#184;	//  scala/xml/Utility$$anonfun$4
const #186 = Asciz	(Lscala/runtime/CharRef;)V;
const #187 = NameAndType	#11:#186;//  "<init>":(Lscala/runtime/CharRef;)V
const #188 = Method	#185.#187;	//  scala/xml/Utility$$anonfun$4."<init>":(Lscala/runtime/CharRef;)V
const #189 = Asciz	scala/xml/Utility$$anonfun$5;
const #190 = class	#189;	//  scala/xml/Utility$$anonfun$5
const #191 = Asciz	(Lscala/collection/Iterator;Lscala/runtime/CharRef;)V;
const #192 = NameAndType	#11:#191;//  "<init>":(Lscala/collection/Iterator;Lscala/runtime/CharRef;)V
const #193 = Method	#190.#192;	//  scala/xml/Utility$$anonfun$5."<init>":(Lscala/collection/Iterator;Lscala/runtime/CharRef;)V
const #194 = Asciz	scala/xml/Utility$$anonfun$6;
const #195 = class	#194;	//  scala/xml/Utility$$anonfun$6
const #196 = Method	#195.#12;	//  scala/xml/Utility$$anonfun$6."<init>":()V
const #197 = NameAndType	#36:#37;//  parseCharRef:(Lscala/Function0;Lscala/Function0;Lscala/Function1;)Ljava/lang/String;
const #198 = Method	#10.#197;	//  scala/xml/Utility$.parseCharRef:(Lscala/Function0;Lscala/Function0;Lscala/Function1;)Ljava/lang/String;
const #199 = Asciz	(Ljava/lang/String;)Lscala/collection/mutable/StringBuilder;;
const #200 = NameAndType	#59:#199;//  append:(Ljava/lang/String;)Lscala/collection/mutable/StringBuilder;
const #201 = Method	#55.#200;	//  scala/collection/mutable/StringBuilder.append:(Ljava/lang/String;)Lscala/collection/mutable/StringBuilder;
const #202 = Asciz	(C)Lscala/collection/mutable/StringBuilder;;
const #203 = NameAndType	#59:#202;//  append:(C)Lscala/collection/mutable/StringBuilder;
const #204 = Method	#55.#203;	//  scala/collection/mutable/StringBuilder.append:(C)Lscala/collection/mutable/StringBuilder;
const #205 = Method	#55.#67;	//  scala/collection/mutable/StringBuilder.toString:()Ljava/lang/String;
const #206 = Asciz	setLength;
const #207 = NameAndType	#206:#112;//  setLength:(I)V
const #208 = Method	#55.#207;	//  scala/collection/mutable/StringBuilder.setLength:(I)V
const #209 = Asciz	scala/xml/Utility$Escapes$;
const #210 = class	#209;	//  scala/xml/Utility$Escapes$
const #211 = Asciz	Lscala/xml/Utility$Escapes$;;
const #212 = NameAndType	#4:#211;//  MODULE$:Lscala/xml/Utility$Escapes$;
const #213 = Field	#210.#212;	//  scala/xml/Utility$Escapes$.MODULE$:Lscala/xml/Utility$Escapes$;
const #214 = Asciz	unescMap;
const #215 = Asciz	()Lscala/collection/immutable/Map;;
const #216 = NameAndType	#214:#215;//  unescMap:()Lscala/collection/immutable/Map;
const #217 = Method	#210.#216;	//  scala/xml/Utility$Escapes$.unescMap:()Lscala/collection/immutable/Map;
const #218 = Asciz	scala/collection/MapLike;
const #219 = class	#218;	//  scala/collection/MapLike
const #220 = Asciz	get;
const #221 = Asciz	(Ljava/lang/Object;)Lscala/Option;;
const #222 = NameAndType	#220:#221;//  get:(Ljava/lang/Object;)Lscala/Option;
const #223 = InterfaceMethod	#219.#222;	//  scala/collection/MapLike.get:(Ljava/lang/Object;)Lscala/Option;
const #224 = Asciz	scala/xml/Utility$$anonfun$unescape$1;
const #225 = class	#224;	//  scala/xml/Utility$$anonfun$unescape$1
const #226 = Asciz	(Lscala/collection/mutable/StringBuilder;)V;
const #227 = NameAndType	#11:#226;//  "<init>":(Lscala/collection/mutable/StringBuilder;)V
const #228 = Method	#225.#227;	//  scala/xml/Utility$$anonfun$unescape$1."<init>":(Lscala/collection/mutable/StringBuilder;)V
const #229 = Asciz	scala/Option;
const #230 = class	#229;	//  scala/Option
const #231 = Asciz	map;
const #232 = Asciz	(Lscala/Function1;)Lscala/Option;;
const #233 = NameAndType	#231:#232;//  map:(Lscala/Function1;)Lscala/Option;
const #234 = Method	#230.#233;	//  scala/Option.map:(Lscala/Function1;)Lscala/Option;
const #235 = Asciz	scala/Predef$$anon$1;
const #236 = class	#235;	//  scala/Predef$$anon$1
const #237 = Method	#236.#12;	//  scala/Predef$$anon$1."<init>":()V
const #238 = Asciz	orNull;
const #239 = Asciz	(Lscala/Predef$$less$colon$less;)Ljava/lang/Object;;
const #240 = NameAndType	#238:#239;//  orNull:(Lscala/Predef$$less$colon$less;)Ljava/lang/Object;
const #241 = Method	#230.#240;	//  scala/Option.orNull:(Lscala/Predef$$less$colon$less;)Ljava/lang/Object;
const #242 = Method	#55.#108;	//  scala/collection/mutable/StringBuilder.length:()I
const #243 = Asciz	scala/xml/Text$;
const #244 = class	#243;	//  scala/xml/Text$
const #245 = Asciz	Lscala/xml/Text$;;
const #246 = NameAndType	#4:#245;//  MODULE$:Lscala/xml/Text$;
const #247 = Field	#244.#246;	//  scala/xml/Text$.MODULE$:Lscala/xml/Text$;
const #248 = Asciz	(Ljava/lang/String;)Lscala/xml/Text;;
const #249 = NameAndType	#40:#248;//  apply:(Ljava/lang/String;)Lscala/xml/Text;
const #250 = Method	#244.#249;	//  scala/xml/Text$.apply:(Ljava/lang/String;)Lscala/xml/Text;
const #251 = Asciz	$plus$eq;
const #252 = Asciz	(Ljava/lang/Object;)Lscala/collection/mutable/ArrayBuffer;;
const #253 = NameAndType	#251:#252;//  $plus$eq:(Ljava/lang/Object;)Lscala/collection/mutable/ArrayBuffer;
const #254 = Method	#159.#253;	//  scala/xml/NodeBuffer.$plus$eq:(Ljava/lang/Object;)Lscala/collection/mutable/ArrayBuffer;
const #255 = Asciz	scala/xml/EntityRef;
const #256 = class	#255;	//  scala/xml/EntityRef
const #257 = Method	#256.#82;	//  scala/xml/EntityRef."<init>":(Ljava/lang/String;)V
const #258 = Asciz	scala/runtime/BoxedUnit;
const #259 = class	#258;	//  scala/runtime/BoxedUnit
const #260 = Asciz	UNIT;
const #261 = Asciz	Lscala/runtime/BoxedUnit;;
const #262 = NameAndType	#260:#261;//  UNIT:Lscala/runtime/BoxedUnit;
const #263 = Field	#259.#262;	//  scala/runtime/BoxedUnit.UNIT:Lscala/runtime/BoxedUnit;
const #264 = Asciz	scala/collection/mutable/ResizableArray;
const #265 = class	#264;	//  scala/collection/mutable/ResizableArray
const #266 = InterfaceMethod	#265.#108;	//  scala/collection/mutable/ResizableArray.length:()I
const #267 = Asciz	value;
const #268 = Asciz	Ljava/lang/String;;
const #269 = Asciz	theChar;
const #270 = Asciz	it$1;
const #271 = Asciz	Lscala/collection/Iterator;;
const #272 = Asciz	rfb;
const #273 = Asciz	Lscala/collection/mutable/StringBuilder;;
const #274 = Asciz	ref;
const #275 = Asciz	temp56;
const #276 = Asciz	c$1;
const #277 = Asciz	Lscala/runtime/CharRef;;
const #278 = Asciz	sb;
const #279 = Asciz	x;
const #280 = Asciz	Lscala/xml/Text;;
const #281 = Asciz	nb;
const #282 = Asciz	Lscala/xml/NodeBuffer;;
const #283 = Asciz	(Ljava/lang/String;)Lscala/collection/Seq<Lscala/xml/Node;>;;
const #284 = Asciz	checkAttributeValue;
const #285 = Asciz	(Ljava/lang/String;)Ljava/lang/String;;
const #286 = Method	#94.#108;	//  java/lang/String.length:()I
const #287 = Asciz	charAt;
const #288 = Asciz	(I)C;
const #289 = NameAndType	#287:#288;//  charAt:(I)C
const #290 = Method	#94.#289;	//  java/lang/String.charAt:(I)C
const #291 = Asciz	< not allowed in attribute value;
const #292 = String	#291;	//  < not allowed in attribute value
const #293 = Asciz	getName;
const #294 = Asciz	(Ljava/lang/String;I)Ljava/lang/String;;
const #295 = NameAndType	#293:#294;//  getName:(Ljava/lang/String;I)Ljava/lang/String;
const #296 = Method	#10.#295;	//  scala/xml/Utility$.getName:(Ljava/lang/String;I)Ljava/lang/String;
const #297 = Asciz	malformed entity reference in attribute value [;
const #298 = String	#297;	//  malformed entity reference in attribute value [
const #299 = Asciz	];
const #300 = String	#299;	//  ]
const #301 = Asciz	n;
const #302 = Asciz	temp55;
const #303 = Asciz	drop;
const #304 = Asciz	(I)Ljava/lang/Object;;
const #305 = NameAndType	#303:#304;//  drop:(I)Ljava/lang/Object;
const #306 = InterfaceMethod	#165.#305;	//  scala/collection/IndexedSeqLike.drop:(I)Ljava/lang/Object;
const #307 = Asciz	scala/collection/Seq;
const #308 = class	#307;	//  scala/collection/Seq
const #309 = Asciz	scala/collection/Seq$;
const #310 = class	#309;	//  scala/collection/Seq$
const #311 = Asciz	Lscala/collection/Seq$;;
const #312 = NameAndType	#4:#311;//  MODULE$:Lscala/collection/Seq$;
const #313 = Field	#310.#312;	//  scala/collection/Seq$.MODULE$:Lscala/collection/Seq$;
const #314 = Asciz	unapplySeq;
const #315 = Asciz	(Lscala/collection/Seq;)Lscala/Some;;
const #316 = NameAndType	#314:#315;//  unapplySeq:(Lscala/collection/Seq;)Lscala/Some;
const #317 = Method	#310.#316;	//  scala/collection/Seq$.unapplySeq:(Lscala/collection/Seq;)Lscala/Some;
const #318 = Asciz	scala/Some;
const #319 = class	#318;	//  scala/Some
const #320 = Asciz	Ljava/lang/Object;;
const #321 = NameAndType	#279:#320;//  x:Ljava/lang/Object;
const #322 = Field	#319.#321;	//  scala/Some.x:Ljava/lang/Object;
const #323 = Asciz	equals;
const #324 = Asciz	(Ljava/lang/Object;)Z;
const #325 = NameAndType	#323:#324;//  equals:(Ljava/lang/Object;)Z
const #326 = Method	#16.#325;	//  java/lang/Object.equals:(Ljava/lang/Object;)Z
const #327 = Asciz	lengthCompare;
const #328 = Asciz	(I)I;
const #329 = NameAndType	#327:#328;//  lengthCompare:(I)I
const #330 = InterfaceMethod	#105.#329;	//  scala/collection/SeqLike.lengthCompare:(I)I
const #331 = NameAndType	#40:#304;//  apply:(I)Ljava/lang/Object;
const #332 = InterfaceMethod	#105.#331;	//  scala/collection/SeqLike.apply:(I)Ljava/lang/Object;
const #333 = Asciz	scala/collection/TraversableLike;
const #334 = class	#333;	//  scala/collection/TraversableLike
const #335 = InterfaceMethod	#334.#305;	//  scala/collection/TraversableLike.drop:(I)Ljava/lang/Object;
const #336 = NameAndType	#26:#27;//  gd2$1:(CLscala/collection/Seq;)Z
const #337 = Method	#10.#336;	//  scala/xml/Utility$.gd2$1:(CLscala/collection/Seq;)Z
const #338 = Asciz	scala/xml/Utility$$anonfun$getName$1;
const #339 = class	#338;	//  scala/xml/Utility$$anonfun$getName$1
const #340 = Method	#339.#12;	//  scala/xml/Utility$$anonfun$getName$1."<init>":()V
const #341 = Asciz	takeWhile;
const #342 = Asciz	(Lscala/Function1;)Ljava/lang/Object;;
const #343 = NameAndType	#341:#342;//  takeWhile:(Lscala/Function1;)Ljava/lang/Object;
const #344 = InterfaceMethod	#116.#343;	//  scala/collection/IterableLike.takeWhile:(Lscala/Function1;)Ljava/lang/Object;
const #345 = Asciz	mkString;
const #346 = NameAndType	#345:#66;//  mkString:()Ljava/lang/String;
const #347 = InterfaceMethod	#334.#346;	//  scala/collection/TraversableLike.mkString:()Ljava/lang/String;
const #348 = Asciz	;
const #349 = String	#348;	//  
const #350 = Method	#94.#67;	//  java/lang/String.toString:()Ljava/lang/String;
const #351 = Asciz	s;
const #352 = Asciz	index;
const #353 = Asciz	temp50;
const #354 = Asciz	Lscala/collection/Seq;;
const #355 = Asciz	temp51;
const #356 = Asciz	Lscala/Some;;
const #357 = Asciz	temp52;
const #358 = Asciz	temp53;
const #359 = Asciz	temp54;
const #360 = Asciz	temp49;
const #361 = Asciz	appendEscapedQuoted;
const #362 = Asciz	(Ljava/lang/String;Lscala/collection/mutable/StringBuilder;)Lscala/collection/mutable/StringBuilder;;
const #363 = int	34;
const #364 = Asciz	augmentString;
const #365 = Asciz	(Ljava/lang/String;)Lscala/collection/immutable/StringOps;;
const #366 = NameAndType	#364:#365;//  augmentString:(Ljava/lang/String;)Lscala/collection/immutable/StringOps;
const #367 = Method	#96.#366;	//  scala/Predef$.augmentString:(Ljava/lang/String;)Lscala/collection/immutable/StringOps;
const #368 = Asciz	scala/xml/Utility$$anonfun$appendEscapedQuoted$1;
const #369 = class	#368;	//  scala/xml/Utility$$anonfun$appendEscapedQuoted$1
const #370 = Method	#369.#227;	//  scala/xml/Utility$$anonfun$appendEscapedQuoted$1."<init>":(Lscala/collection/mutable/StringBuilder;)V
const #371 = InterfaceMethod	#165.#130;	//  scala/collection/IndexedSeqLike.foreach:(Lscala/Function1;)V
const #372 = Asciz	sb$3;
const #373 = Asciz	appendQuoted;
const #374 = Asciz	contains;
const #375 = NameAndType	#374:#324;//  contains:(Ljava/lang/Object;)Z
const #376 = InterfaceMethod	#105.#375;	//  scala/collection/SeqLike.contains:(Ljava/lang/Object;)Z
const #377 = int	39;
const #378 = Asciz	scala/xml/Utility$$anonfun$appendQuoted$1;
const #379 = class	#378;	//  scala/xml/Utility$$anonfun$appendQuoted$1
const #380 = Method	#379.#82;	//  scala/xml/Utility$$anonfun$appendQuoted$1."<init>":(Ljava/lang/String;)V
const #381 = NameAndType	#373:#362;//  appendQuoted:(Ljava/lang/String;Lscala/collection/mutable/StringBuilder;)Lscala/collection/mutable/StringBuilder;
const #382 = Method	#10.#381;	//  scala/xml/Utility$.appendQuoted:(Ljava/lang/String;Lscala/collection/mutable/StringBuilder;)Lscala/collection/mutable/StringBuilder;
const #383 = Asciz	s$1;
const #384 = Asciz	sb0;
const #385 = Asciz	hashCode;
const #386 = Asciz	(Ljava/lang/String;Ljava/lang/String;IILscala/collection/Seq;)I;
const #387 = int	41;
const #388 = NameAndType	#385:#107;//  hashCode:()I
const #389 = Method	#94.#388;	//  java/lang/String.hashCode:()I
const #390 = int	7;
const #391 = int	53;
const #392 = int	31;
const #393 = Asciz	scala/xml/Node;
const #394 = class	#393;	//  scala/xml/Node
const #395 = Method	#394.#388;	//  scala/xml/Node.hashCode:()I
const #396 = Asciz	pre;
const #397 = Asciz	label;
const #398 = Asciz	attribHashCode;
const #399 = Asciz	scpeHash;
const #400 = Asciz	children;
const #401 = Asciz	c;
const #402 = Asciz	(Ljava/lang/String;Ljava/lang/String;IILscala/collection/Seq<Lscala/xml/Node;>;)I;
const #403 = Asciz	prefix;
const #404 = Asciz	(Ljava/lang/String;)Lscala/Option;;
const #405 = int	58;
const #406 = Asciz	indexOf;
const #407 = NameAndType	#406:#328;//  indexOf:(I)I
const #408 = Method	#94.#407;	//  java/lang/String.indexOf:(I)I
const #409 = Asciz	scala/None$;
const #410 = class	#409;	//  scala/None$
const #411 = Asciz	Lscala/None$;;
const #412 = NameAndType	#4:#411;//  MODULE$:Lscala/None$;
const #413 = Field	#410.#412;	//  scala/None$.MODULE$:Lscala/None$;
const #414 = Asciz	boxToInteger;
const #415 = Asciz	(I)Ljava/lang/Integer;;
const #416 = NameAndType	#414:#415;//  boxToInteger:(I)Ljava/lang/Integer;
const #417 = Method	#45.#416;	//  scala/runtime/BoxesRunTime.boxToInteger:(I)Ljava/lang/Integer;
const #418 = Asciz	substring;
const #419 = Asciz	(II)Ljava/lang/String;;
const #420 = NameAndType	#418:#419;//  substring:(II)Ljava/lang/String;
const #421 = Method	#94.#420;	//  java/lang/String.substring:(II)Ljava/lang/String;
const #422 = Asciz	(Ljava/lang/Object;)V;
const #423 = NameAndType	#11:#422;//  "<init>":(Ljava/lang/Object;)V
const #424 = Method	#319.#423;	//  scala/Some."<init>":(Ljava/lang/Object;)V
const #425 = Asciz	name;
const #426 = Asciz	temp47;
const #427 = Asciz	(Ljava/lang/String;)Lscala/Option<Ljava/lang/String;>;;
const #428 = Asciz	sequenceToXML;
const #429 = Asciz	(Lscala/collection/Seq;Lscala/xml/NamespaceBinding;Lscala/collection/mutable/StringBuilder;Z)V;
const #430 = Asciz	isEmpty;
const #431 = NameAndType	#430:#168;//  isEmpty:()Z
const #432 = InterfaceMethod	#116.#431;	//  scala/collection/IterableLike.isEmpty:()Z
const #433 = Asciz	scala/xml/Utility$$anonfun$sequenceToXML$1;
const #434 = class	#433;	//  scala/xml/Utility$$anonfun$sequenceToXML$1
const #435 = Method	#434.#12;	//  scala/xml/Utility$$anonfun$sequenceToXML$1."<init>":()V
const #436 = Asciz	forall;
const #437 = Asciz	(Lscala/Function1;)Z;
const #438 = NameAndType	#436:#437;//  forall:(Lscala/Function1;)Z
const #439 = InterfaceMethod	#116.#438;	//  scala/collection/IterableLike.forall:(Lscala/Function1;)Z
const #440 = Asciz	toXML;
const #441 = Asciz	(Lscala/xml/Node;Lscala/xml/NamespaceBinding;Lscala/collection/mutable/StringBuilder;ZZZZ)Lscala/collection/mutable/StringBuilder;;
const #442 = NameAndType	#440:#441;//  toXML:(Lscala/xml/Node;Lscala/xml/NamespaceBinding;Lscala/collection/mutable/StringBuilder;ZZZZ)Lscala/collection/mutable/StringBuilder;
const #443 = Method	#10.#442;	//  scala/xml/Utility$.toXML:(Lscala/xml/Node;Lscala/xml/NamespaceBinding;Lscala/collection/mutable/StringBuilder;ZZZZ)Lscala/collection/mutable/StringBuilder;
const #444 = int	32;
const #445 = Asciz	scala/xml/Utility$$anonfun$sequenceToXML$2;
const #446 = class	#445;	//  scala/xml/Utility$$anonfun$sequenceToXML$2
const #447 = Asciz	(Lscala/xml/NamespaceBinding;Lscala/collection/mutable/StringBuilder;)V;
const #448 = NameAndType	#11:#447;//  "<init>":(Lscala/xml/NamespaceBinding;Lscala/collection/mutable/StringBuilder;)V
const #449 = Method	#446.#448;	//  scala/xml/Utility$$anonfun$sequenceToXML$2."<init>":(Lscala/xml/NamespaceBinding;Lscala/collection/mutable/StringBuilder;)V
const #450 = InterfaceMethod	#116.#130;	//  scala/collection/IterableLike.foreach:(Lscala/Function1;)V
const #451 = Asciz	pscope$1;
const #452 = Asciz	Lscala/xml/NamespaceBinding;;
const #453 = Asciz	sb$2;
const #454 = Asciz	stripComments;
const #455 = Asciz	f;
const #456 = Asciz	Lscala/xml/Node;;
const #457 = Asciz	it;
const #458 = Asciz	(Lscala/collection/Seq<Lscala/xml/Node;>;Lscala/xml/NamespaceBinding;Lscala/collection/mutable/StringBuilder;Z)V;
const #459 = Asciz	scala/xml/Comment;
const #460 = class	#459;	//  scala/xml/Comment
const #461 = NameAndType	#34:#35;//  gd1$1:(Lscala/xml/Comment;Z)Z
const #462 = Method	#10.#461;	//  scala/xml/Utility$.gd1$1:(Lscala/xml/Comment;Z)Z
const #463 = Asciz	buildString;
const #464 = Asciz	(Lscala/collection/mutable/StringBuilder;)Lscala/collection/mutable/StringBuilder;;
const #465 = NameAndType	#463:#464;//  buildString:(Lscala/collection/mutable/StringBuilder;)Lscala/collection/mutable/StringBuilder;
const #466 = Method	#460.#465;	//  scala/xml/Comment.buildString:(Lscala/collection/mutable/StringBuilder;)Lscala/collection/mutable/StringBuilder;
const #467 = Method	#394.#67;	//  scala/xml/Node.toString:()Ljava/lang/String;
const #468 = Asciz	scala/xml/SpecialNode;
const #469 = class	#468;	//  scala/xml/SpecialNode
const #470 = Method	#469.#465;	//  scala/xml/SpecialNode.buildString:(Lscala/collection/mutable/StringBuilder;)Lscala/collection/mutable/StringBuilder;
const #471 = Asciz	scala/xml/Group;
const #472 = class	#471;	//  scala/xml/Group
const #473 = Asciz	nodes;
const #474 = Asciz	()Lscala/collection/Seq;;
const #475 = NameAndType	#473:#474;//  nodes:()Lscala/collection/Seq;
const #476 = Method	#472.#475;	//  scala/xml/Group.nodes:()Lscala/collection/Seq;
const #477 = Asciz	scala/xml/Utility$$anonfun$toXML$1;
const #478 = class	#477;	//  scala/xml/Utility$$anonfun$toXML$1
const #479 = Asciz	(Lscala/xml/Node;Lscala/collection/mutable/StringBuilder;)V;
const #480 = NameAndType	#11:#479;//  "<init>":(Lscala/xml/Node;Lscala/collection/mutable/StringBuilder;)V
const #481 = Method	#478.#480;	//  scala/xml/Utility$$anonfun$toXML$1."<init>":(Lscala/xml/Node;Lscala/collection/mutable/StringBuilder;)V
const #482 = int	60;
const #483 = Asciz	nameToString;
const #484 = NameAndType	#483:#464;//  nameToString:(Lscala/collection/mutable/StringBuilder;)Lscala/collection/mutable/StringBuilder;
const #485 = Method	#394.#484;	//  scala/xml/Node.nameToString:(Lscala/collection/mutable/StringBuilder;)Lscala/collection/mutable/StringBuilder;
const #486 = Asciz	attributes;
const #487 = Asciz	()Lscala/xml/MetaData;;
const #488 = NameAndType	#486:#487;//  attributes:()Lscala/xml/MetaData;
const #489 = Method	#394.#488;	//  scala/xml/Node.attributes:()Lscala/xml/MetaData;
const #490 = Asciz	scala/xml/MetaData;
const #491 = class	#490;	//  scala/xml/MetaData
const #492 = Method	#491.#465;	//  scala/xml/MetaData.buildString:(Lscala/collection/mutable/StringBuilder;)Lscala/collection/mutable/StringBuilder;
const #493 = Asciz	scope;
const #494 = Asciz	()Lscala/xml/NamespaceBinding;;
const #495 = NameAndType	#493:#494;//  scope:()Lscala/xml/NamespaceBinding;
const #496 = Method	#394.#495;	//  scala/xml/Node.scope:()Lscala/xml/NamespaceBinding;
const #497 = Asciz	scala/xml/NamespaceBinding;
const #498 = class	#497;	//  scala/xml/NamespaceBinding
const #499 = Asciz	(Lscala/collection/mutable/StringBuilder;Lscala/xml/NamespaceBinding;)V;
const #500 = NameAndType	#463:#499;//  buildString:(Lscala/collection/mutable/StringBuilder;Lscala/xml/NamespaceBinding;)V
const #501 = Method	#498.#500;	//  scala/xml/NamespaceBinding.buildString:(Lscala/collection/mutable/StringBuilder;Lscala/xml/NamespaceBinding;)V
const #502 = Asciz	child;
const #503 = NameAndType	#502:#474;//  child:()Lscala/collection/Seq;
const #504 = Method	#394.#503;	//  scala/xml/Node.child:()Lscala/collection/Seq;
const #505 = Asciz	 />;
const #506 = String	#505;	//   />
const #507 = int	62;
const #508 = NameAndType	#428:#429;//  sequenceToXML:(Lscala/collection/Seq;Lscala/xml/NamespaceBinding;Lscala/collection/mutable/StringBuilder;Z)V
const #509 = Method	#10.#508;	//  scala/xml/Utility$.sequenceToXML:(Lscala/collection/Seq;Lscala/xml/NamespaceBinding;Lscala/collection/mutable/StringBuilder;Z)V
const #510 = Asciz	</;
const #511 = String	#510;	//  </
const #512 = Asciz	x$7;
const #513 = Asciz	pscope;
const #514 = Asciz	sb$1;
const #515 = Asciz	stripComments$1;
const #516 = Asciz	decodeEntities;
const #517 = Asciz	preserveWhitespace;
const #518 = Asciz	minimizeTags;
const #519 = Asciz	temp42;
const #520 = Asciz	Lscala/xml/Comment;;
const #521 = Asciz	Lscala/xml/SpecialNode;;
const #522 = Asciz	temp45;
const #523 = Asciz	Lscala/xml/Group;;
const #524 = Asciz	collectNamespaces;
const #525 = Asciz	(Lscala/xml/Node;Lscala/collection/mutable/Set;)V;
const #526 = Asciz	doCollectNamespaces;
const #527 = NameAndType	#526:#168;//  doCollectNamespaces:()Z
const #528 = Method	#394.#527;	//  scala/xml/Node.doCollectNamespaces:()Z
const #529 = Asciz	namespace;
const #530 = NameAndType	#529:#66;//  namespace:()Ljava/lang/String;
const #531 = Method	#394.#530;	//  scala/xml/Node.namespace:()Ljava/lang/String;
const #532 = Asciz	scala/collection/mutable/SetLike;
const #533 = class	#532;	//  scala/collection/mutable/SetLike
const #534 = Asciz	(Ljava/lang/Object;)Lscala/collection/mutable/SetLike;;
const #535 = NameAndType	#251:#534;//  $plus$eq:(Ljava/lang/Object;)Lscala/collection/mutable/SetLike;
const #536 = InterfaceMethod	#533.#535;	//  scala/collection/mutable/SetLike.$plus$eq:(Ljava/lang/Object;)Lscala/collection/mutable/SetLike;
const #537 = Asciz	scala/xml/Utility$$anonfun$collectNamespaces$2;
const #538 = class	#537;	//  scala/xml/Utility$$anonfun$collectNamespaces$2
const #539 = NameAndType	#11:#525;//  "<init>":(Lscala/xml/Node;Lscala/collection/mutable/Set;)V
const #540 = Method	#538.#539;	//  scala/xml/Utility$$anonfun$collectNamespaces$2."<init>":(Lscala/xml/Node;Lscala/collection/mutable/Set;)V
const #541 = Asciz	scala/xml/Utility$$anonfun$collectNamespaces$3;
const #542 = class	#541;	//  scala/xml/Utility$$anonfun$collectNamespaces$3
const #543 = Asciz	(Lscala/collection/mutable/Set;)V;
const #544 = NameAndType	#11:#543;//  "<init>":(Lscala/collection/mutable/Set;)V
const #545 = Method	#542.#544;	//  scala/xml/Utility$$anonfun$collectNamespaces$3."<init>":(Lscala/collection/mutable/Set;)V
const #546 = Asciz	n$1;
const #547 = Asciz	set$1;
const #548 = Asciz	Lscala/collection/mutable/Set;;
const #549 = Asciz	(Lscala/xml/Node;Lscala/collection/mutable/Set<Ljava/lang/String;>;)V;
const #550 = Asciz	(Lscala/collection/Seq;)Lscala/collection/mutable/Set;;
const #551 = Asciz	scala/collection/mutable/HashSet;
const #552 = class	#551;	//  scala/collection/mutable/HashSet
const #553 = Method	#552.#12;	//  scala/collection/mutable/HashSet."<init>":()V
const #554 = Asciz	scala/xml/Utility$$anonfun$collectNamespaces$1;
const #555 = class	#554;	//  scala/xml/Utility$$anonfun$collectNamespaces$1
const #556 = Method	#555.#12;	//  scala/xml/Utility$$anonfun$collectNamespaces$1."<init>":()V
const #557 = Asciz	foldLeft;
const #558 = Asciz	(Ljava/lang/Object;Lscala/Function2;)Ljava/lang/Object;;
const #559 = NameAndType	#557:#558;//  foldLeft:(Ljava/lang/Object;Lscala/Function2;)Ljava/lang/Object;
const #560 = InterfaceMethod	#334.#559;	//  scala/collection/TraversableLike.foldLeft:(Ljava/lang/Object;Lscala/Function2;)Ljava/lang/Object;
const #561 = Asciz	scala/collection/mutable/Set;
const #562 = class	#561;	//  scala/collection/mutable/Set
const #563 = Asciz	(Lscala/collection/Seq<Lscala/xml/Node;>;)Lscala/collection/mutable/Set<Ljava/lang/String;>;;
const #564 = Asciz	unescape;
const #565 = Asciz	conforms;
const #566 = Asciz	()Lscala/Predef$$less$colon$less;;
const #567 = NameAndType	#565:#566;//  conforms:()Lscala/Predef$$less$colon$less;
const #568 = Method	#96.#567;	//  scala/Predef$.conforms:()Lscala/Predef$$less$colon$less;
const #569 = Asciz	s$2;
const #570 = Asciz	escape;
const #571 = Asciz	scala/xml/Utility$$anonfun$escape$2;
const #572 = class	#571;	//  scala/xml/Utility$$anonfun$escape$2
const #573 = Method	#572.#12;	//  scala/xml/Utility$$anonfun$escape$2."<init>":()V
const #574 = InterfaceMethod	#165.#559;	//  scala/collection/IndexedSeqLike.foldLeft:(Ljava/lang/Object;Lscala/Function2;)Ljava/lang/Object;
const #575 = Asciz	text;
const #576 = Asciz	scala/xml/Utility$$anonfun$escape$1;
const #577 = class	#576;	//  scala/xml/Utility$$anonfun$escape$1
const #578 = Method	#577.#82;	//  scala/xml/Utility$$anonfun$escape$1."<init>":(Ljava/lang/String;)V
const #579 = Asciz	text$1;
const #580 = Asciz	sort;
const #581 = Asciz	(Lscala/xml/Node;)Lscala/xml/Node;;
const #582 = Asciz	scala/xml/Elem$;
const #583 = class	#582;	//  scala/xml/Elem$
const #584 = Asciz	Lscala/xml/Elem$;;
const #585 = NameAndType	#4:#584;//  MODULE$:Lscala/xml/Elem$;
const #586 = Field	#583.#585;	//  scala/xml/Elem$.MODULE$:Lscala/xml/Elem$;
const #587 = Asciz	(Lscala/xml/Node;)Lscala/Option;;
const #588 = NameAndType	#314:#587;//  unapplySeq:(Lscala/xml/Node;)Lscala/Option;
const #589 = Method	#583.#588;	//  scala/xml/Elem$.unapplySeq:(Lscala/xml/Node;)Lscala/Option;
const #590 = Method	#230.#431;	//  scala/Option.isEmpty:()Z
const #591 = NameAndType	#220:#41;//  get:()Ljava/lang/Object;
const #592 = Method	#230.#591;	//  scala/Option.get:()Ljava/lang/Object;
const #593 = Asciz	scala/Tuple5;
const #594 = class	#593;	//  scala/Tuple5
const #595 = Asciz	_1;
const #596 = NameAndType	#595:#41;//  _1:()Ljava/lang/Object;
const #597 = Method	#594.#596;	//  scala/Tuple5._1:()Ljava/lang/Object;
const #598 = Asciz	_2;
const #599 = NameAndType	#598:#41;//  _2:()Ljava/lang/Object;
const #600 = Method	#594.#599;	//  scala/Tuple5._2:()Ljava/lang/Object;
const #601 = Asciz	_3;
const #602 = NameAndType	#601:#41;//  _3:()Ljava/lang/Object;
const #603 = Method	#594.#602;	//  scala/Tuple5._3:()Ljava/lang/Object;
const #604 = Asciz	_4;
const #605 = NameAndType	#604:#41;//  _4:()Ljava/lang/Object;
const #606 = Method	#594.#605;	//  scala/Tuple5._4:()Ljava/lang/Object;
const #607 = Asciz	_5;
const #608 = NameAndType	#607:#41;//  _5:()Ljava/lang/Object;
const #609 = Method	#594.#608;	//  scala/Tuple5._5:()Ljava/lang/Object;
const #610 = Asciz	(Lscala/xml/MetaData;)Lscala/xml/MetaData;;
const #611 = NameAndType	#580:#610;//  sort:(Lscala/xml/MetaData;)Lscala/xml/MetaData;
const #612 = Method	#10.#611;	//  scala/xml/Utility$.sort:(Lscala/xml/MetaData;)Lscala/xml/MetaData;
const #613 = Asciz	scala/xml/Utility$$anonfun$sort$1;
const #614 = class	#613;	//  scala/xml/Utility$$anonfun$sort$1
const #615 = Method	#614.#12;	//  scala/xml/Utility$$anonfun$sort$1."<init>":()V
const #616 = Asciz	scala/collection/generic/TraversableFactory$GenericCanBuildFrom;
const #617 = class	#616;	//  scala/collection/generic/TraversableFactory$GenericCanBuildFrom
const #618 = Asciz	(Lscala/collection/generic/TraversableFactory;)V;
const #619 = NameAndType	#11:#618;//  "<init>":(Lscala/collection/generic/TraversableFactory;)V
const #620 = Method	#617.#619;	//  scala/collection/generic/TraversableFactory$GenericCanBuildFrom."<init>":(Lscala/collection/generic/TraversableFactory;)V
const #621 = Asciz	(Lscala/Function1;Lscala/collection/generic/CanBuildFrom;)Ljava/lang/Object;;
const #622 = NameAndType	#231:#621;//  map:(Lscala/Function1;Lscala/collection/generic/CanBuildFrom;)Ljava/lang/Object;
const #623 = InterfaceMethod	#334.#622;	//  scala/collection/TraversableLike.map:(Lscala/Function1;Lscala/collection/generic/CanBuildFrom;)Ljava/lang/Object;
const #624 = Asciz	scala/xml/Elem;
const #625 = class	#624;	//  scala/xml/Elem
const #626 = Asciz	(Ljava/lang/String;Ljava/lang/String;Lscala/xml/MetaData;Lscala/xml/NamespaceBinding;Lscala/collection/Seq;)V;
const #627 = NameAndType	#11:#626;//  "<init>":(Ljava/lang/String;Ljava/lang/String;Lscala/xml/MetaData;Lscala/xml/NamespaceBinding;Lscala/collection/Seq;)V
const #628 = Method	#625.#627;	//  scala/xml/Elem."<init>":(Ljava/lang/String;Ljava/lang/String;Lscala/xml/MetaData;Lscala/xml/NamespaceBinding;Lscala/collection/Seq;)V
const #629 = Asciz	temp24;
const #630 = Asciz	Lscala/Option;;
const #631 = Asciz	temp25;
const #632 = Asciz	Lscala/Tuple5;;
const #633 = Asciz	temp28;
const #634 = Asciz	Lscala/xml/MetaData;;
const #635 = Asciz	temp30;
const #636 = Asciz	temp26;
const #637 = Asciz	temp27;
const #638 = Asciz	temp29;
const #639 = Asciz	scala/xml/Null$;
const #640 = class	#639;	//  scala/xml/Null$
const #641 = Asciz	Lscala/xml/Null$;;
const #642 = NameAndType	#4:#641;//  MODULE$:Lscala/xml/Null$;
const #643 = Field	#640.#642;	//  scala/xml/Null$.MODULE$:Lscala/xml/Null$;
const #644 = NameAndType	#173:#487;//  next:()Lscala/xml/MetaData;
const #645 = Method	#491.#644;	//  scala/xml/MetaData.next:()Lscala/xml/MetaData;
const #646 = Asciz	key;
const #647 = NameAndType	#646:#66;//  key:()Ljava/lang/String;
const #648 = Method	#491.#647;	//  scala/xml/MetaData.key:()Ljava/lang/String;
const #649 = Asciz	scala/xml/Utility$$anonfun$1;
const #650 = class	#649;	//  scala/xml/Utility$$anonfun$1
const #651 = Method	#650.#82;	//  scala/xml/Utility$$anonfun$1."<init>":(Ljava/lang/String;)V
const #652 = Asciz	filter;
const #653 = Asciz	(Lscala/Function1;)Lscala/xml/MetaData;;
const #654 = NameAndType	#652:#653;//  filter:(Lscala/Function1;)Lscala/xml/MetaData;
const #655 = Method	#491.#654;	//  scala/xml/MetaData.filter:(Lscala/Function1;)Lscala/xml/MetaData;
const #656 = Asciz	scala/xml/Utility$$anonfun$2;
const #657 = class	#656;	//  scala/xml/Utility$$anonfun$2
const #658 = Method	#657.#82;	//  scala/xml/Utility$$anonfun$2."<init>":(Ljava/lang/String;)V
const #659 = Asciz	append$default$2;
const #660 = NameAndType	#659:#494;//  append$default$2:()Lscala/xml/NamespaceBinding;
const #661 = Method	#491.#660;	//  scala/xml/MetaData.append$default$2:()Lscala/xml/NamespaceBinding;
const #662 = Asciz	(Lscala/xml/MetaData;Lscala/xml/NamespaceBinding;)Lscala/xml/MetaData;;
const #663 = NameAndType	#59:#662;//  append:(Lscala/xml/MetaData;Lscala/xml/NamespaceBinding;)Lscala/xml/MetaData;
const #664 = Method	#491.#663;	//  scala/xml/MetaData.append:(Lscala/xml/MetaData;Lscala/xml/NamespaceBinding;)Lscala/xml/MetaData;
const #665 = Asciz	copy;
const #666 = NameAndType	#665:#610;//  copy:(Lscala/xml/MetaData;)Lscala/xml/MetaData;
const #667 = Method	#491.#666;	//  scala/xml/MetaData.copy:(Lscala/xml/MetaData;)Lscala/xml/MetaData;
const #668 = Asciz	md;
const #669 = Asciz	key$1;
const #670 = Asciz	smaller;
const #671 = Asciz	greater;
const #672 = Asciz	qual$1;
const #673 = Asciz	x$5;
const #674 = Asciz	x$6;
const #675 = Asciz	trimProper;
const #676 = Asciz	(Lscala/xml/Node;)Lscala/collection/Seq;;
const #677 = Asciz	unapply;
const #678 = NameAndType	#677:#221;//  unapply:(Ljava/lang/Object;)Lscala/Option;
const #679 = Method	#244.#678;	//  scala/xml/Text$.unapply:(Ljava/lang/Object;)Lscala/Option;
const #680 = Asciz	scala/xml/Utility$$anonfun$trimProper$1;
const #681 = class	#680;	//  scala/xml/Utility$$anonfun$trimProper$1
const #682 = Method	#681.#12;	//  scala/xml/Utility$$anonfun$trimProper$1."<init>":()V
const #683 = Asciz	flatMap;
const #684 = NameAndType	#683:#621;//  flatMap:(Lscala/Function1;Lscala/collection/generic/CanBuildFrom;)Ljava/lang/Object;
const #685 = InterfaceMethod	#334.#684;	//  scala/collection/TraversableLike.flatMap:(Lscala/Function1;Lscala/collection/generic/CanBuildFrom;)Ljava/lang/Object;
const #686 = Asciz	scala/xml/TextBuffer;
const #687 = class	#686;	//  scala/xml/TextBuffer
const #688 = Method	#687.#12;	//  scala/xml/TextBuffer."<init>":()V
const #689 = Asciz	wrapString;
const #690 = Asciz	(Ljava/lang/String;)Lscala/collection/immutable/WrappedString;;
const #691 = NameAndType	#689:#690;//  wrapString:(Ljava/lang/String;)Lscala/collection/immutable/WrappedString;
const #692 = Method	#96.#691;	//  scala/Predef$.wrapString:(Ljava/lang/String;)Lscala/collection/immutable/WrappedString;
const #693 = Asciz	(Lscala/collection/Seq;)Lscala/xml/TextBuffer;;
const #694 = NameAndType	#59:#693;//  append:(Lscala/collection/Seq;)Lscala/xml/TextBuffer;
const #695 = Method	#687.#694;	//  scala/xml/TextBuffer.append:(Lscala/collection/Seq;)Lscala/xml/TextBuffer;
const #696 = Asciz	toText;
const #697 = NameAndType	#696:#474;//  toText:()Lscala/collection/Seq;
const #698 = Method	#687.#697;	//  scala/xml/TextBuffer.toText:()Lscala/collection/Seq;
const #699 = Asciz	temp21;
const #700 = Asciz	temp11;
const #701 = Asciz	temp12;
const #702 = Asciz	temp17;
const #703 = Asciz	temp13;
const #704 = Asciz	temp14;
const #705 = Asciz	temp15;
const #706 = Asciz	temp16;
const #707 = Asciz	temp19;
const #708 = Asciz	temp20;
const #709 = Asciz	(Lscala/xml/Node;)Lscala/collection/Seq<Lscala/xml/Node;>;;
const #710 = Asciz	trim;
const #711 = Asciz	scala/xml/Utility$$anonfun$trim$1;
const #712 = class	#711;	//  scala/xml/Utility$$anonfun$trim$1
const #713 = Method	#712.#12;	//  scala/xml/Utility$$anonfun$trim$1."<init>":()V
const #714 = Asciz	temp2;
const #715 = Asciz	temp3;
const #716 = Asciz	temp8;
const #717 = Asciz	temp4;
const #718 = Asciz	temp5;
const #719 = Asciz	temp6;
const #720 = Asciz	temp7;
const #721 = Asciz	isAtomAndNotText;
const #722 = Asciz	(Lscala/xml/Node;)Z;
const #723 = Asciz	isAtom;
const #724 = NameAndType	#723:#168;//  isAtom:()Z
const #725 = Method	#394.#724;	//  scala/xml/Node.isAtom:()Z
const #726 = Asciz	scala/xml/Text;
const #727 = class	#726;	//  scala/xml/Text
const #728 = Asciz	sbToString;
const #729 = Asciz	(Lscala/Function1;)Ljava/lang/String;;
const #730 = Asciz	(Lscala/Function1<Lscala/collection/mutable/StringBuilder;Ljava/lang/Object;>;)Ljava/lang/String;;
const #731 = Asciz	implicitSbToString;
const #732 = Asciz	(Lscala/collection/mutable/StringBuilder;)Ljava/lang/String;;
const #733 = Asciz	toXML$default$2;
const #734 = Asciz	scala/xml/TopScope$;
const #735 = class	#734;	//  scala/xml/TopScope$
const #736 = Asciz	Lscala/xml/TopScope$;;
const #737 = NameAndType	#4:#736;//  MODULE$:Lscala/xml/TopScope$;
const #738 = Field	#735.#737;	//  scala/xml/TopScope$.MODULE$:Lscala/xml/TopScope$;
const #739 = Asciz	toXML$default$3;
const #740 = Asciz	()Lscala/collection/mutable/StringBuilder;;
const #741 = Asciz	toXML$default$4;
const #742 = Asciz	toXML$default$5;
const #743 = Asciz	toXML$default$6;
const #744 = Asciz	toXML$default$7;
const #745 = Asciz	sequenceToXML$default$2;
const #746 = Asciz	sequenceToXML$default$3;
const #747 = Asciz	sequenceToXML$default$4;
const #748 = Asciz	checkPubID;
const #749 = Asciz	(Ljava/lang/String;)Z;
const #750 = Asciz	(Lscala/xml/parsing/TokenTests;Ljava/lang/String;)Z;
const #751 = NameAndType	#748:#750;//  checkPubID:(Lscala/xml/parsing/TokenTests;Ljava/lang/String;)Z
const #752 = Method	#21.#751;	//  scala/xml/parsing/TokenTests$class.checkPubID:(Lscala/xml/parsing/TokenTests;Ljava/lang/String;)Z
const #753 = Asciz	checkSysID;
const #754 = NameAndType	#753:#750;//  checkSysID:(Lscala/xml/parsing/TokenTests;Ljava/lang/String;)Z
const #755 = Method	#21.#754;	//  scala/xml/parsing/TokenTests$class.checkSysID:(Lscala/xml/parsing/TokenTests;Ljava/lang/String;)Z
const #756 = Asciz	isValidIANAEncoding;
const #757 = Asciz	(Lscala/collection/Seq;)Z;
const #758 = Asciz	(Lscala/xml/parsing/TokenTests;Lscala/collection/Seq;)Z;
const #759 = NameAndType	#756:#758;//  isValidIANAEncoding:(Lscala/xml/parsing/TokenTests;Lscala/collection/Seq;)Z
const #760 = Method	#21.#759;	//  scala/xml/parsing/TokenTests$class.isValidIANAEncoding:(Lscala/xml/parsing/TokenTests;Lscala/collection/Seq;)Z
const #761 = Asciz	ianaEncoding;
const #762 = Asciz	isPubIDChar;
const #763 = Asciz	(Lscala/xml/parsing/TokenTests;C)Z;
const #764 = NameAndType	#762:#763;//  isPubIDChar:(Lscala/xml/parsing/TokenTests;C)Z
const #765 = Method	#21.#764;	//  scala/xml/parsing/TokenTests$class.isPubIDChar:(Lscala/xml/parsing/TokenTests;C)Z
const #766 = Asciz	isName;
const #767 = NameAndType	#766:#750;//  isName:(Lscala/xml/parsing/TokenTests;Ljava/lang/String;)Z
const #768 = Method	#21.#767;	//  scala/xml/parsing/TokenTests$class.isName:(Lscala/xml/parsing/TokenTests;Ljava/lang/String;)Z
const #769 = NameAndType	#30:#763;//  isNameStart:(Lscala/xml/parsing/TokenTests;C)Z
const #770 = Method	#21.#769;	//  scala/xml/parsing/TokenTests$class.isNameStart:(Lscala/xml/parsing/TokenTests;C)Z
const #771 = Asciz	isNameChar;
const #772 = NameAndType	#771:#763;//  isNameChar:(Lscala/xml/parsing/TokenTests;C)Z
const #773 = Method	#21.#772;	//  scala/xml/parsing/TokenTests$class.isNameChar:(Lscala/xml/parsing/TokenTests;C)Z
const #774 = Asciz	isAlphaDigit;
const #775 = NameAndType	#774:#763;//  isAlphaDigit:(Lscala/xml/parsing/TokenTests;C)Z
const #776 = Method	#21.#775;	//  scala/xml/parsing/TokenTests$class.isAlphaDigit:(Lscala/xml/parsing/TokenTests;C)Z
const #777 = Asciz	isAlpha;
const #778 = NameAndType	#777:#763;//  isAlpha:(Lscala/xml/parsing/TokenTests;C)Z
const #779 = Method	#21.#778;	//  scala/xml/parsing/TokenTests$class.isAlpha:(Lscala/xml/parsing/TokenTests;C)Z
const #780 = Asciz	isSpace;
const #781 = NameAndType	#780:#758;//  isSpace:(Lscala/xml/parsing/TokenTests;Lscala/collection/Seq;)Z
const #782 = Method	#21.#781;	//  scala/xml/parsing/TokenTests$class.isSpace:(Lscala/xml/parsing/TokenTests;Lscala/collection/Seq;)Z
const #783 = Asciz	cs;
const #784 = NameAndType	#780:#763;//  isSpace:(Lscala/xml/parsing/TokenTests;C)Z
const #785 = Method	#21.#784;	//  scala/xml/parsing/TokenTests$class.isSpace:(Lscala/xml/parsing/TokenTests;C)Z
const #786 = Asciz	InnerClasses;
const #787 = Asciz	scala/Predef;
const #788 = class	#787;	//  scala/Predef
const #789 = Asciz	$anon$1;
const #790 = Asciz	scala/xml/Utility;
const #791 = class	#790;	//  scala/xml/Utility
const #792 = Asciz	$anonfun$6;
const #793 = Asciz	$anonfun$5;
const #794 = Asciz	$anonfun$4;
const #795 = Asciz	$anonfun$2;
const #796 = Asciz	$anonfun$1;
const #797 = Asciz	scala/Array;
const #798 = class	#797;	//  scala/Array
const #799 = Asciz	$anonfun$apply$6;
const #800 = Asciz	scala/Predef$$less$colon$less;
const #801 = class	#800;	//  scala/Predef$$less$colon$less
const #802 = Asciz	$less$colon$less;
const #803 = Asciz	$anonfun$sort$1;
const #804 = Asciz	$anonfun$trim$1;
const #805 = Asciz	$anonfun$toXML$1;
const #806 = Asciz	$anonfun$escape$2;
const #807 = Asciz	$anonfun$escape$1;
const #808 = Asciz	$anonfun$getName$1;
const #809 = Asciz	$anonfun$unescape$1;
const #810 = Asciz	$anonfun$trimProper$1;
const #811 = Asciz	$anonfun$appendQuoted$1;
const #812 = Asciz	$anonfun$sequenceToXML$2;
const #813 = Asciz	$anonfun$sequenceToXML$1;
const #814 = Asciz	$anonfun$collectNamespaces$3;
const #815 = Asciz	$anonfun$collectNamespaces$2;
const #816 = Asciz	$anonfun$collectNamespaces$1;
const #817 = Asciz	scala/collection/generic/TraversableFactory;
const #818 = class	#817;	//  scala/collection/generic/TraversableFactory
const #819 = Asciz	GenericCanBuildFrom;
const #820 = Asciz	$anonfun$appendEscapedQuoted$1;
const #821 = Asciz	scala/ScalaObject;
const #822 = class	#821;	//  scala/ScalaObject

{
public static final scala.xml.Utility$ MODULE$;

public static {};
  Code:
   Stack=1, Locals=0, Args_size=0
   0:	new	#10; //class scala/xml/Utility$
   3:	invokespecial	#13; //Method "<init>":()V
   6:	return

public java.lang.String parseCharRef(scala.Function0, scala.Function0, scala.Function1);
  Code:
   Stack=7, Locals=13, Args_size=4
   0:	aload_1
   1:	invokeinterface	#43,  1; //InterfaceMethod scala/Function0.apply:()Ljava/lang/Object;
   6:	invokestatic	#49; //Method scala/runtime/BoxesRunTime.unboxToChar:(Ljava/lang/Object;)C
   9:	ldc	#50; //int 120
   11:	if_icmpne	29
   14:	aload_2
   15:	invokeinterface	#43,  1; //InterfaceMethod scala/Function0.apply:()Ljava/lang/Object;
   20:	pop
   21:	iconst_1
   22:	ifeq	29
   25:	iconst_1
   26:	goto	30
   29:	iconst_0
   30:	istore	4
   32:	iload	4
   34:	ifeq	42
   37:	ldc	#51; //int 16
   39:	goto	44
   42:	ldc	#52; //int 10
   44:	istore	6
   46:	iconst_0
   47:	istore	9
   49:	aload_1
   50:	invokeinterface	#43,  1; //InterfaceMethod scala/Function0.apply:()Ljava/lang/Object;
   55:	invokestatic	#49; //Method scala/runtime/BoxesRunTime.unboxToChar:(Ljava/lang/Object;)C
   58:	ldc	#53; //int 59
   60:	if_icmpeq	845
   63:	aload_1
   64:	invokeinterface	#43,  1; //InterfaceMethod scala/Function0.apply:()Ljava/lang/Object;
   69:	invokestatic	#49; //Method scala/runtime/BoxesRunTime.unboxToChar:(Ljava/lang/Object;)C
   72:	istore	8
   74:	iload	8
   76:	lookupswitch{ //22
		48: 789;
		49: 769;
		50: 749;
		51: 729;
		52: 709;
		53: 689;
		54: 669;
		55: 649;
		56: 629;
		57: 609;
		65: 543;
		66: 523;
		67: 503;
		68: 483;
		69: 463;
		70: 443;
		97: 423;
		98: 403;
		99: 383;
		100: 363;
		101: 343;
		102: 323;
		default: 264 }
   264:	iconst_1
   265:	ifeq	307
   268:	aload_3
   269:	new	#55; //class scala/collection/mutable/StringBuilder
   272:	dup
   273:	invokespecial	#56; //Method scala/collection/mutable/StringBuilder."<init>":()V
   276:	ldc	#58; //String character '
   278:	invokevirtual	#62; //Method scala/collection/mutable/StringBuilder.append:(Ljava/lang/Object;)Lscala/collection/mutable/StringBuilder;
   281:	aload_1
   282:	invokeinterface	#43,  1; //InterfaceMethod scala/Function0.apply:()Ljava/lang/Object;
   287:	invokevirtual	#62; //Method scala/collection/mutable/StringBuilder.append:(Ljava/lang/Object;)Lscala/collection/mutable/StringBuilder;
   290:	ldc	#64; //String ' not allowed in char ref\n
   292:	invokevirtual	#62; //Method scala/collection/mutable/StringBuilder.append:(Ljava/lang/Object;)Lscala/collection/mutable/StringBuilder;
   295:	invokevirtual	#68; //Method scala/collection/mutable/StringBuilder.toString:()Ljava/lang/String;
   298:	invokeinterface	#73,  2; //InterfaceMethod scala/Function1.apply:(Ljava/lang/Object;)Ljava/lang/Object;
   303:	pop
   304:	goto	819
   307:	new	#75; //class scala/MatchError
   310:	dup
   311:	iload	8
   313:	invokestatic	#79; //Method scala/runtime/BoxesRunTime.boxToCharacter:(C)Ljava/lang/Character;
   316:	invokevirtual	#80; //Method java/lang/Object.toString:()Ljava/lang/String;
   319:	invokespecial	#83; //Method scala/MatchError."<init>":(Ljava/lang/String;)V
   322:	athrow
   323:	iconst_1
   324:	ifne	547
   327:	new	#75; //class scala/MatchError
   330:	dup
   331:	iload	8
   333:	invokestatic	#79; //Method scala/runtime/BoxesRunTime.boxToCharacter:(C)Ljava/lang/Character;
   336:	invokevirtual	#80; //Method java/lang/Object.toString:()Ljava/lang/String;
   339:	invokespecial	#83; //Method scala/MatchError."<init>":(Ljava/lang/String;)V
   342:	athrow
   343:	iconst_1
   344:	ifne	547
   347:	new	#75; //class scala/MatchError
   350:	dup
   351:	iload	8
   353:	invokestatic	#79; //Method scala/runtime/BoxesRunTime.boxToCharacter:(C)Ljava/lang/Character;
   356:	invokevirtual	#80; //Method java/lang/Object.toString:()Ljava/lang/String;
   359:	invokespecial	#83; //Method scala/MatchError."<init>":(Ljava/lang/String;)V
   362:	athrow
   363:	iconst_1
   364:	ifne	547
   367:	new	#75; //class scala/MatchError
   370:	dup
   371:	iload	8
   373:	invokestatic	#79; //Method scala/runtime/BoxesRunTime.boxToCharacter:(C)Ljava/lang/Character;
   376:	invokevirtual	#80; //Method java/lang/Object.toString:()Ljava/lang/String;
   379:	invokespecial	#83; //Method scala/MatchError."<init>":(Ljava/lang/String;)V
   382:	athrow
   383:	iconst_1
   384:	ifne	547
   387:	new	#75; //class scala/MatchError
   390:	dup
   391:	iload	8
   393:	invokestatic	#79; //Method scala/runtime/BoxesRunTime.boxToCharacter:(C)Ljava/lang/Character;
   396:	invokevirtual	#80; //Method java/lang/Object.toString:()Ljava/lang/String;
   399:	invokespecial	#83; //Method scala/MatchError."<init>":(Ljava/lang/String;)V
   402:	athrow
   403:	iconst_1
   404:	ifne	547
   407:	new	#75; //class scala/MatchError
   410:	dup
   411:	iload	8
   413:	invokestatic	#79; //Method scala/runtime/BoxesRunTime.boxToCharacter:(C)Ljava/lang/Character;
   416:	invokevirtual	#80; //Method java/lang/Object.toString:()Ljava/lang/String;
   419:	invokespecial	#83; //Method scala/MatchError."<init>":(Ljava/lang/String;)V
   422:	athrow
   423:	iconst_1
   424:	ifne	547
   427:	new	#75; //class scala/MatchError
   430:	dup
   431:	iload	8
   433:	invokestatic	#79; //Method scala/runtime/BoxesRunTime.boxToCharacter:(C)Ljava/lang/Character;
   436:	invokevirtual	#80; //Method java/lang/Object.toString:()Ljava/lang/String;
   439:	invokespecial	#83; //Method scala/MatchError."<init>":(Ljava/lang/String;)V
   442:	athrow
   443:	iconst_1
   444:	ifne	547
   447:	new	#75; //class scala/MatchError
   450:	dup
   451:	iload	8
   453:	invokestatic	#79; //Method scala/runtime/BoxesRunTime.boxToCharacter:(C)Ljava/lang/Character;
   456:	invokevirtual	#80; //Method java/lang/Object.toString:()Ljava/lang/String;
   459:	invokespecial	#83; //Method scala/MatchError."<init>":(Ljava/lang/String;)V
   462:	athrow
   463:	iconst_1
   464:	ifne	547
   467:	new	#75; //class scala/MatchError
   470:	dup
   471:	iload	8
   473:	invokestatic	#79; //Method scala/runtime/BoxesRunTime.boxToCharacter:(C)Ljava/lang/Character;
   476:	invokevirtual	#80; //Method java/lang/Object.toString:()Ljava/lang/String;
   479:	invokespecial	#83; //Method scala/MatchError."<init>":(Ljava/lang/String;)V
   482:	athrow
   483:	iconst_1
   484:	ifne	547
   487:	new	#75; //class scala/MatchError
   490:	dup
   491:	iload	8
   493:	invokestatic	#79; //Method scala/runtime/BoxesRunTime.boxToCharacter:(C)Ljava/lang/Character;
   496:	invokevirtual	#80; //Method java/lang/Object.toString:()Ljava/lang/String;
   499:	invokespecial	#83; //Method scala/MatchError."<init>":(Ljava/lang/String;)V
   502:	athrow
   503:	iconst_1
   504:	ifne	547
   507:	new	#75; //class scala/MatchError
   510:	dup
   511:	iload	8
   513:	invokestatic	#79; //Method scala/runtime/BoxesRunTime.boxToCharacter:(C)Ljava/lang/Character;
   516:	invokevirtual	#80; //Method java/lang/Object.toString:()Ljava/lang/String;
   519:	invokespecial	#83; //Method scala/MatchError."<init>":(Ljava/lang/String;)V
   522:	athrow
   523:	iconst_1
   524:	ifne	547
   527:	new	#75; //class scala/MatchError
   530:	dup
   531:	iload	8
   533:	invokestatic	#79; //Method scala/runtime/BoxesRunTime.boxToCharacter:(C)Ljava/lang/Character;
   536:	invokevirtual	#80; //Method java/lang/Object.toString:()Ljava/lang/String;
   539:	invokespecial	#83; //Method scala/MatchError."<init>":(Ljava/lang/String;)V
   542:	athrow
   543:	iconst_1
   544:	ifeq	593
   547:	iload	4
   549:	ifeq	581
   552:	iload	9
   554:	iload	6
   556:	imul
   557:	aload_1
   558:	invokeinterface	#43,  1; //InterfaceMethod scala/Function0.apply:()Ljava/lang/Object;
   563:	invokestatic	#49; //Method scala/runtime/BoxesRunTime.unboxToChar:(Ljava/lang/Object;)C
   566:	istore	5
   568:	iload	5
   570:	ldc	#84; //int 36
   572:	invokestatic	#90; //Method java/lang/Character.digit:(CI)I
   575:	iadd
   576:	istore	9
   578:	goto	819
   581:	aload_3
   582:	ldc	#92; //String hex char not allowed in decimal char ref\nDid you mean to write &#x ?
   584:	invokeinterface	#73,  2; //InterfaceMethod scala/Function1.apply:(Ljava/lang/Object;)Ljava/lang/Object;
   589:	pop
   590:	goto	819
   593:	new	#75; //class scala/MatchError
   596:	dup
   597:	iload	8
   599:	invokestatic	#79; //Method scala/runtime/BoxesRunTime.boxToCharacter:(C)Ljava/lang/Character;
   602:	invokevirtual	#80; //Method java/lang/Object.toString:()Ljava/lang/String;
   605:	invokespecial	#83; //Method scala/MatchError."<init>":(Ljava/lang/String;)V
   608:	athrow
   609:	iconst_1
   610:	ifne	793
   613:	new	#75; //class scala/MatchError
   616:	dup
   617:	iload	8
   619:	invokestatic	#79; //Method scala/runtime/BoxesRunTime.boxToCharacter:(C)Ljava/lang/Character;
   622:	invokevirtual	#80; //Method java/lang/Object.toString:()Ljava/lang/String;
   625:	invokespecial	#83; //Method scala/MatchError."<init>":(Ljava/lang/String;)V
   628:	athrow
   629:	iconst_1
   630:	ifne	793
   633:	new	#75; //class scala/MatchError
   636:	dup
   637:	iload	8
   639:	invokestatic	#79; //Method scala/runtime/BoxesRunTime.boxToCharacter:(C)Ljava/lang/Character;
   642:	invokevirtual	#80; //Method java/lang/Object.toString:()Ljava/lang/String;
   645:	invokespecial	#83; //Method scala/MatchError."<init>":(Ljava/lang/String;)V
   648:	athrow
   649:	iconst_1
   650:	ifne	793
   653:	new	#75; //class scala/MatchError
   656:	dup
   657:	iload	8
   659:	invokestatic	#79; //Method scala/runtime/BoxesRunTime.boxToCharacter:(C)Ljava/lang/Character;
   662:	invokevirtual	#80; //Method java/lang/Object.toString:()Ljava/lang/String;
   665:	invokespecial	#83; //Method scala/MatchError."<init>":(Ljava/lang/String;)V
   668:	athrow
   669:	iconst_1
   670:	ifne	793
   673:	new	#75; //class scala/MatchError
   676:	dup
   677:	iload	8
   679:	invokestatic	#79; //Method scala/runtime/BoxesRunTime.boxToCharacter:(C)Ljava/lang/Character;
   682:	invokevirtual	#80; //Method java/lang/Object.toString:()Ljava/lang/String;
   685:	invokespecial	#83; //Method scala/MatchError."<init>":(Ljava/lang/String;)V
   688:	athrow
   689:	iconst_1
   690:	ifne	793
   693:	new	#75; //class scala/MatchError
   696:	dup
   697:	iload	8
   699:	invokestatic	#79; //Method scala/runtime/BoxesRunTime.boxToCharacter:(C)Ljava/lang/Character;
   702:	invokevirtual	#80; //Method java/lang/Object.toString:()Ljava/lang/String;
   705:	invokespecial	#83; //Method scala/MatchError."<init>":(Ljava/lang/String;)V
   708:	athrow
   709:	iconst_1
   710:	ifne	793
   713:	new	#75; //class scala/MatchError
   716:	dup
   717:	iload	8
   719:	invokestatic	#79; //Method scala/runtime/BoxesRunTime.boxToCharacter:(C)Ljava/lang/Character;
   722:	invokevirtual	#80; //Method java/lang/Object.toString:()Ljava/lang/String;
   725:	invokespecial	#83; //Method scala/MatchError."<init>":(Ljava/lang/String;)V
   728:	athrow
   729:	iconst_1
   730:	ifne	793
   733:	new	#75; //class scala/MatchError
   736:	dup
   737:	iload	8
   739:	invokestatic	#79; //Method scala/runtime/BoxesRunTime.boxToCharacter:(C)Ljava/lang/Character;
   742:	invokevirtual	#80; //Method java/lang/Object.toString:()Ljava/lang/String;
   745:	invokespecial	#83; //Method scala/MatchError."<init>":(Ljava/lang/String;)V
   748:	athrow
   749:	iconst_1
   750:	ifne	793
   753:	new	#75; //class scala/MatchError
   756:	dup
   757:	iload	8
   759:	invokestatic	#79; //Method scala/runtime/BoxesRunTime.boxToCharacter:(C)Ljava/lang/Character;
   762:	invokevirtual	#80; //Method java/lang/Object.toString:()Ljava/lang/String;
   765:	invokespecial	#83; //Method scala/MatchError."<init>":(Ljava/lang/String;)V
   768:	athrow
   769:	iconst_1
   770:	ifne	793
   773:	new	#75; //class scala/MatchError
   776:	dup
   777:	iload	8
   779:	invokestatic	#79; //Method scala/runtime/BoxesRunTime.boxToCharacter:(C)Ljava/lang/Character;
   782:	invokevirtual	#80; //Method java/lang/Object.toString:()Ljava/lang/String;
   785:	invokespecial	#83; //Method scala/MatchError."<init>":(Ljava/lang/String;)V
   788:	athrow
   789:	iconst_1
   790:	ifeq	829
   793:	iload	9
   795:	iload	6
   797:	imul
   798:	aload_1
   799:	invokeinterface	#43,  1; //InterfaceMethod scala/Function0.apply:()Ljava/lang/Object;
   804:	invokestatic	#49; //Method scala/runtime/BoxesRunTime.unboxToChar:(Ljava/lang/Object;)C
   807:	istore	7
   809:	iload	7
   811:	ldc	#84; //int 36
   813:	invokestatic	#90; //Method java/lang/Character.digit:(CI)I
   816:	iadd
   817:	istore	9
   819:	aload_2
   820:	invokeinterface	#43,  1; //InterfaceMethod scala/Function0.apply:()Ljava/lang/Object;
   825:	pop
   826:	goto	49
   829:	new	#75; //class scala/MatchError
   832:	dup
   833:	iload	8
   835:	invokestatic	#79; //Method scala/runtime/BoxesRunTime.boxToCharacter:(C)Ljava/lang/Character;
   838:	invokevirtual	#80; //Method java/lang/Object.toString:()Ljava/lang/String;
   841:	invokespecial	#83; //Method scala/MatchError."<init>":(Ljava/lang/String;)V
   844:	athrow
   845:	new	#94; //class java/lang/String
   848:	dup
   849:	getstatic	#99; //Field scala/Predef$.MODULE$:Lscala/Predef$;
   852:	iconst_0
   853:	newarray int
   855:	invokevirtual	#103; //Method scala/Predef$.wrapIntArray:([I)Lscala/collection/mutable/WrappedArray;
   858:	astore	10
   860:	aload	10
   862:	invokeinterface	#109,  1; //InterfaceMethod scala/collection/SeqLike.length:()I
   867:	iconst_1
   868:	iadd
   869:	newarray int
   871:	astore	12
   873:	aload	12
   875:	iconst_0
   876:	iload	9
   878:	iastore
   879:	new	#111; //class scala/runtime/IntRef
   882:	dup
   883:	iconst_1
   884:	invokespecial	#114; //Method scala/runtime/IntRef."<init>":(I)V
   887:	astore	11
   889:	aload	10
   891:	invokeinterface	#120,  1; //InterfaceMethod scala/collection/IterableLike.iterator:()Lscala/collection/Iterator;
   896:	new	#122; //class scala/Array$$anonfun$apply$6
   899:	dup
   900:	aload	12
   902:	aload	11
   904:	invokespecial	#125; //Method scala/Array$$anonfun$apply$6."<init>":([ILscala/runtime/IntRef;)V
   907:	invokeinterface	#131,  2; //InterfaceMethod scala/collection/Iterator.foreach:(Lscala/Function1;)V
   912:	aload	12
   914:	iconst_0
   915:	iconst_1
   916:	invokespecial	#134; //Method java/lang/String."<init>":([III)V
   919:	areturn
  LineNumberTable: 
   line 395: 0
   line 396: 32
   line 397: 46
   line 398: 49
   line 399: 63
   line 21: 264
   line 410: 268
   line 399: 307
   line 21: 323
   line 399: 327
   line 21: 343
   line 399: 347
   line 21: 363
   line 399: 367
   line 21: 383
   line 399: 387
   line 21: 403
   line 399: 407
   line 21: 423
   line 399: 427
   line 21: 443
   line 399: 447
   line 21: 463
   line 399: 467
   line 21: 483
   line 399: 487
   line 21: 503
   line 399: 507
   line 21: 523
   line 399: 527
   line 21: 543
   line 404: 547
   line 408: 552
   line 404: 578
   line 405: 581
   line 399: 593
   line 21: 609
   line 399: 613
   line 21: 629
   line 399: 633
   line 21: 649
   line 399: 653
   line 21: 669
   line 399: 673
   line 21: 689
   line 399: 693
   line 21: 709
   line 399: 713
   line 21: 729
   line 399: 733
   line 21: 749
   line 399: 753
   line 21: 769
   line 399: 773
   line 21: 789
   line 401: 793
   line 412: 819
   line 399: 829
   line 414: 845

  LocalVariableTable: 
   Start  Length  Slot  Name   Signature
   0      920      0    this       Lscala/xml/Utility$;
   0      920      1    ch       Lscala/Function0;
   0      920      2    nextch       Lscala/Function0;
   0      920      3    reportSyntaxError       Lscala/Function1;
   32      887      4    hex       Z
   46      873      6    base       I
   74      771      8    temp58       C
   49      870      9    i       I
   889      25      11    i$60       Lscala/runtime/IntRef;
   873      41      12    array$60       [I

  Signature: length = 0x2
   00 FFFFFF99 

public scala.collection.Seq parseAttributeValue(java.lang.String);
  Code:
   Stack=6, Locals=11, Args_size=2
   0:	new	#55; //class scala/collection/mutable/StringBuilder
   3:	dup
   4:	invokespecial	#157; //Method scala/collection/mutable/StringBuilder."<init>":()V
   7:	astore	8
   9:	aconst_null
   10:	astore	4
   12:	new	#159; //class scala/xml/NodeBuffer
   15:	dup
   16:	invokespecial	#160; //Method scala/xml/NodeBuffer."<init>":()V
   19:	astore	10
   21:	new	#162; //class scala/collection/immutable/StringOps
   24:	dup
   25:	aload_1
   26:	invokespecial	#163; //Method scala/collection/immutable/StringOps."<init>":(Ljava/lang/String;)V
   29:	invokeinterface	#166,  1; //InterfaceMethod scala/collection/IndexedSeqLike.iterator:()Lscala/collection/Iterator;
   34:	astore_3
   35:	aload_3
   36:	invokeinterface	#170,  1; //InterfaceMethod scala/collection/Iterator.hasNext:()Z
   41:	ifeq	391
   44:	new	#172; //class scala/runtime/CharRef
   47:	dup
   48:	aload_3
   49:	invokeinterface	#175,  1; //InterfaceMethod scala/collection/Iterator.next:()Ljava/lang/Object;
   54:	invokestatic	#49; //Method scala/runtime/BoxesRunTime.unboxToChar:(Ljava/lang/Object;)C
   57:	invokespecial	#178; //Method scala/runtime/CharRef."<init>":(C)V
   60:	astore	7
   62:	aload	7
   64:	getfield	#181; //Field scala/runtime/CharRef.elem:C
   67:	ldc	#182; //int 38
   69:	if_icmpne	377
   72:	aload	7
   74:	aload_3
   75:	invokeinterface	#175,  1; //InterfaceMethod scala/collection/Iterator.next:()Ljava/lang/Object;
   80:	invokestatic	#49; //Method scala/runtime/BoxesRunTime.unboxToChar:(Ljava/lang/Object;)C
   83:	putfield	#181; //Field scala/runtime/CharRef.elem:C
   86:	aload	7
   88:	getfield	#181; //Field scala/runtime/CharRef.elem:C
   91:	ldc	#183; //int 35
   93:	if_icmpne	150
   96:	aload	7
   98:	aload_3
   99:	invokeinterface	#175,  1; //InterfaceMethod scala/collection/Iterator.next:()Ljava/lang/Object;
   104:	invokestatic	#49; //Method scala/runtime/BoxesRunTime.unboxToChar:(Ljava/lang/Object;)C
   107:	putfield	#181; //Field scala/runtime/CharRef.elem:C
   110:	aload_0
   111:	new	#185; //class scala/xml/Utility$$anonfun$4
   114:	dup
   115:	aload	7
   117:	invokespecial	#188; //Method scala/xml/Utility$$anonfun$4."<init>":(Lscala/runtime/CharRef;)V
   120:	new	#190; //class scala/xml/Utility$$anonfun$5
   123:	dup
   124:	aload_3
   125:	aload	7
   127:	invokespecial	#193; //Method scala/xml/Utility$$anonfun$5."<init>":(Lscala/collection/Iterator;Lscala/runtime/CharRef;)V
   130:	new	#195; //class scala/xml/Utility$$anonfun$6
   133:	dup
   134:	invokespecial	#196; //Method scala/xml/Utility$$anonfun$6."<init>":()V
   137:	invokevirtual	#198; //Method parseCharRef:(Lscala/Function0;Lscala/Function0;Lscala/Function1;)Ljava/lang/String;
   140:	astore_2
   141:	aload	8
   143:	aload_2
   144:	invokevirtual	#201; //Method scala/collection/mutable/StringBuilder.append:(Ljava/lang/String;)Lscala/collection/mutable/StringBuilder;
   147:	goto	387
   150:	aload	4
   152:	ifnonnull	164
   155:	new	#55; //class scala/collection/mutable/StringBuilder
   158:	dup
   159:	invokespecial	#157; //Method scala/collection/mutable/StringBuilder."<init>":()V
   162:	astore	4
   164:	aload	4
   166:	aload	7
   168:	getfield	#181; //Field scala/runtime/CharRef.elem:C
   171:	invokevirtual	#204; //Method scala/collection/mutable/StringBuilder.append:(C)Lscala/collection/mutable/StringBuilder;
   174:	pop
   175:	aload	7
   177:	aload_3
   178:	invokeinterface	#175,  1; //InterfaceMethod scala/collection/Iterator.next:()Ljava/lang/Object;
   183:	invokestatic	#49; //Method scala/runtime/BoxesRunTime.unboxToChar:(Ljava/lang/Object;)C
   186:	putfield	#181; //Field scala/runtime/CharRef.elem:C
   189:	aload	7
   191:	getfield	#181; //Field scala/runtime/CharRef.elem:C
   194:	ldc	#53; //int 59
   196:	if_icmpeq	227
   199:	aload	4
   201:	aload	7
   203:	getfield	#181; //Field scala/runtime/CharRef.elem:C
   206:	invokevirtual	#204; //Method scala/collection/mutable/StringBuilder.append:(C)Lscala/collection/mutable/StringBuilder;
   209:	pop
   210:	aload	7
   212:	aload_3
   213:	invokeinterface	#175,  1; //InterfaceMethod scala/collection/Iterator.next:()Ljava/lang/Object;
   218:	invokestatic	#49; //Method scala/runtime/BoxesRunTime.unboxToChar:(Ljava/lang/Object;)C
   221:	putfield	#181; //Field scala/runtime/CharRef.elem:C
   224:	goto	189
   227:	aload	4
   229:	invokevirtual	#205; //Method scala/collection/mutable/StringBuilder.toString:()Ljava/lang/String;
   232:	astore	5
   234:	aload	4
   236:	iconst_0
   237:	invokevirtual	#208; //Method scala/collection/mutable/StringBuilder.setLength:(I)V
   240:	getstatic	#213; //Field scala/xml/Utility$Escapes$.MODULE$:Lscala/xml/Utility$Escapes$;
   243:	invokevirtual	#217; //Method scala/xml/Utility$Escapes$.unescMap:()Lscala/collection/immutable/Map;
   246:	aload	5
   248:	invokeinterface	#223,  2; //InterfaceMethod scala/collection/MapLike.get:(Ljava/lang/Object;)Lscala/Option;
   253:	new	#225; //class scala/xml/Utility$$anonfun$unescape$1
   256:	dup
   257:	aload	8
   259:	invokespecial	#228; //Method scala/xml/Utility$$anonfun$unescape$1."<init>":(Lscala/collection/mutable/StringBuilder;)V
   262:	invokevirtual	#234; //Method scala/Option.map:(Lscala/Function1;)Lscala/Option;
   265:	new	#236; //class scala/Predef$$anon$1
   268:	dup
   269:	invokespecial	#237; //Method scala/Predef$$anon$1."<init>":()V
   272:	invokevirtual	#241; //Method scala/Option.orNull:(Lscala/Predef$$less$colon$less;)Ljava/lang/Object;
   275:	checkcast	#55; //class scala/collection/mutable/StringBuilder
   278:	astore	6
   280:	aload	6
   282:	ifnonnull	354
   285:	iconst_1
   286:	ifeq	341
   289:	aload	8
   291:	invokevirtual	#242; //Method scala/collection/mutable/StringBuilder.length:()I
   294:	iconst_0
   295:	if_icmple	321
   298:	aload	10
   300:	getstatic	#247; //Field scala/xml/Text$.MODULE$:Lscala/xml/Text$;
   303:	aload	8
   305:	invokevirtual	#205; //Method scala/collection/mutable/StringBuilder.toString:()Ljava/lang/String;
   308:	invokevirtual	#250; //Method scala/xml/Text$.apply:(Ljava/lang/String;)Lscala/xml/Text;
   311:	invokevirtual	#254; //Method scala/xml/NodeBuffer.$plus$eq:(Ljava/lang/Object;)Lscala/collection/mutable/ArrayBuffer;
   314:	pop
   315:	aload	8
   317:	iconst_0
   318:	invokevirtual	#208; //Method scala/collection/mutable/StringBuilder.setLength:(I)V
   321:	aload	10
   323:	new	#256; //class scala/xml/EntityRef
   326:	dup
   327:	aload	8
   329:	invokevirtual	#205; //Method scala/collection/mutable/StringBuilder.toString:()Ljava/lang/String;
   332:	invokespecial	#257; //Method scala/xml/EntityRef."<init>":(Ljava/lang/String;)V
   335:	invokevirtual	#254; //Method scala/xml/NodeBuffer.$plus$eq:(Ljava/lang/Object;)Lscala/collection/mutable/ArrayBuffer;
   338:	goto	387
   341:	new	#75; //class scala/MatchError
   344:	dup
   345:	aload	6
   347:	invokevirtual	#205; //Method scala/collection/mutable/StringBuilder.toString:()Ljava/lang/String;
   350:	invokespecial	#83; //Method scala/MatchError."<init>":(Ljava/lang/String;)V
   353:	athrow
   354:	iconst_1
   355:	ifeq	364
   358:	getstatic	#263; //Field scala/runtime/BoxedUnit.UNIT:Lscala/runtime/BoxedUnit;
   361:	goto	387
   364:	new	#75; //class scala/MatchError
   367:	dup
   368:	aload	6
   370:	invokevirtual	#205; //Method scala/collection/mutable/StringBuilder.toString:()Ljava/lang/String;
   373:	invokespecial	#83; //Method scala/MatchError."<init>":(Ljava/lang/String;)V
   376:	athrow
   377:	aload	8
   379:	aload	7
   381:	getfield	#181; //Field scala/runtime/CharRef.elem:C
   384:	invokevirtual	#204; //Method scala/collection/mutable/StringBuilder.append:(C)Lscala/collection/mutable/StringBuilder;
   387:	pop
   388:	goto	35
   391:	aload	8
   393:	invokevirtual	#242; //Method scala/collection/mutable/StringBuilder.length:()I
   396:	iconst_0
   397:	if_icmple	437
   400:	getstatic	#247; //Field scala/xml/Text$.MODULE$:Lscala/xml/Text$;
   403:	aload	8
   405:	invokevirtual	#205; //Method scala/collection/mutable/StringBuilder.toString:()Ljava/lang/String;
   408:	invokevirtual	#250; //Method scala/xml/Text$.apply:(Ljava/lang/String;)Lscala/xml/Text;
   411:	astore	9
   413:	aload	10
   415:	invokeinterface	#266,  1; //InterfaceMethod scala/collection/mutable/ResizableArray.length:()I
   420:	iconst_0
   421:	if_icmpne	427
   424:	aload	9
   426:	areturn
   427:	aload	10
   429:	aload	9
   431:	invokevirtual	#254; //Method scala/xml/NodeBuffer.$plus$eq:(Ljava/lang/Object;)Lscala/collection/mutable/ArrayBuffer;
   434:	goto	440
   437:	getstatic	#263; //Field scala/runtime/BoxedUnit.UNIT:Lscala/runtime/BoxedUnit;
   440:	pop
   441:	aload	10
   443:	areturn
  LineNumberTable: 
   line 332: 0
   line 333: 9
   line 334: 12
   line 336: 21
   line 337: 35
   line 338: 44
   line 340: 62
   line 342: 72
   line 341: 74
   line 342: 86
   line 344: 96
   line 343: 98
   line 344: 110
   line 345: 141
   line 348: 150
   line 349: 164
   line 350: 166
   line 349: 168
   line 350: 175
   line 351: 189
   line 352: 199
   line 353: 201
   line 352: 203
   line 353: 210
   line 355: 227
   line 356: 234
   line 357: 240
   line 21: 285
   line 359: 289
   line 360: 298
   line 361: 303
   line 360: 305
   line 361: 315
   line 363: 321
   line 357: 341
   line 21: 354
   line 357: 358
   line 368: 377
   line 340: 387
   line 370: 391
   line 371: 400
   line 372: 413
   line 373: 424
   line 375: 427
   line 372: 434
   line 370: 437
   line 377: 441

  LocalVariableTable: 
   Start  Length  Slot  Name   Signature
   0      444      0    this       Lscala/xml/Utility$;
   0      444      1    value       Ljava/lang/String;
   141      6      2    theChar       Ljava/lang/String;
   35      408      3    it$1       Lscala/collection/Iterator;
   12      431      4    rfb       Lscala/collection/mutable/StringBuilder;
   234      143      5    ref       Ljava/lang/String;
   280      97      6    temp56       Lscala/collection/mutable/StringBuilder;
   62      326      7    c$1       Lscala/runtime/CharRef;
   9      434      8    sb       Lscala/collection/mutable/StringBuilder;
   413      24      9    x       Lscala/xml/Text;
   21      422      10    nb       Lscala/xml/NodeBuffer;

  Signature: length = 0x2
   01 1B 

public java.lang.String checkAttributeValue(java.lang.String);
  Code:
   Stack=4, Locals=5, Args_size=2
   0:	iconst_0
   1:	istore_3
   2:	iload_3
   3:	aload_1
   4:	invokevirtual	#286; //Method java/lang/String.length:()I
   7:	if_icmpge	209
   10:	aload_1
   11:	iload_3
   12:	invokevirtual	#290; //Method java/lang/String.charAt:(I)C
   15:	istore	4
   17:	iload	4
   19:	lookupswitch{ //2
		38: 88;
		60: 64;
		default: 44 }
   44:	iconst_1
   45:	ifne	186
   48:	new	#75; //class scala/MatchError
   51:	dup
   52:	iload	4
   54:	invokestatic	#79; //Method scala/runtime/BoxesRunTime.boxToCharacter:(C)Ljava/lang/Character;
   57:	invokevirtual	#80; //Method java/lang/Object.toString:()Ljava/lang/String;
   60:	invokespecial	#83; //Method scala/MatchError."<init>":(Ljava/lang/String;)V
   63:	athrow
   64:	iconst_1
   65:	ifeq	72
   68:	ldc_w	#292; //String < not allowed in attribute value
   71:	areturn
   72:	new	#75; //class scala/MatchError
   75:	dup
   76:	iload	4
   78:	invokestatic	#79; //Method scala/runtime/BoxesRunTime.boxToCharacter:(C)Ljava/lang/Character;
   81:	invokevirtual	#80; //Method java/lang/Object.toString:()Ljava/lang/String;
   84:	invokespecial	#83; //Method scala/MatchError."<init>":(Ljava/lang/String;)V
   87:	athrow
   88:	iconst_1
   89:	ifeq	193
   92:	aload_0
   93:	aload_1
   94:	iload_3
   95:	iconst_1
   96:	iadd
   97:	invokevirtual	#296; //Method getName:(Ljava/lang/String;I)Ljava/lang/String;
   100:	astore_2
   101:	aload_2
   102:	ifnonnull	132
   105:	new	#55; //class scala/collection/mutable/StringBuilder
   108:	dup
   109:	invokespecial	#56; //Method scala/collection/mutable/StringBuilder."<init>":()V
   112:	ldc_w	#298; //String malformed entity reference in attribute value [
   115:	invokevirtual	#62; //Method scala/collection/mutable/StringBuilder.append:(Ljava/lang/Object;)Lscala/collection/mutable/StringBuilder;
   118:	aload_1
   119:	invokevirtual	#62; //Method scala/collection/mutable/StringBuilder.append:(Ljava/lang/Object;)Lscala/collection/mutable/StringBuilder;
   122:	ldc_w	#300; //String ]
   125:	invokevirtual	#62; //Method scala/collection/mutable/StringBuilder.append:(Ljava/lang/Object;)Lscala/collection/mutable/StringBuilder;
   128:	invokevirtual	#68; //Method scala/collection/mutable/StringBuilder.toString:()Ljava/lang/String;
   131:	areturn
   132:	iload_3
   133:	aload_2
   134:	invokevirtual	#286; //Method java/lang/String.length:()I
   137:	iadd
   138:	iconst_1
   139:	iadd
   140:	istore_3
   141:	iload_3
   142:	aload_1
   143:	invokevirtual	#286; //Method java/lang/String.length:()I
   146:	if_icmpge	159
   149:	aload_1
   150:	iload_3
   151:	invokevirtual	#290; //Method java/lang/String.charAt:(I)C
   154:	ldc	#53; //int 59
   156:	if_icmpeq	186
   159:	new	#55; //class scala/collection/mutable/StringBuilder
   162:	dup
   163:	invokespecial	#56; //Method scala/collection/mutable/StringBuilder."<init>":()V
   166:	ldc_w	#298; //String malformed entity reference in attribute value [
   169:	invokevirtual	#62; //Method scala/collection/mutable/StringBuilder.append:(Ljava/lang/Object;)Lscala/collection/mutable/StringBuilder;
   172:	aload_1
   173:	invokevirtual	#62; //Method scala/collection/mutable/StringBuilder.append:(Ljava/lang/Object;)Lscala/collection/mutable/StringBuilder;
   176:	ldc_w	#300; //String ]
   179:	invokevirtual	#62; //Method scala/collection/mutable/StringBuilder.append:(Ljava/lang/Object;)Lscala/collection/mutable/StringBuilder;
   182:	invokevirtual	#68; //Method scala/collection/mutable/StringBuilder.toString:()Ljava/lang/String;
   185:	areturn
   186:	iload_3
   187:	iconst_1
   188:	iadd
   189:	istore_3
   190:	goto	2
   193:	new	#75; //class scala/MatchError
   196:	dup
   197:	iload	4
   199:	invokestatic	#79; //Method scala/runtime/BoxesRunTime.boxToCharacter:(C)Ljava/lang/Character;
   202:	invokevirtual	#80; //Method java/lang/Object.toString:()Ljava/lang/String;
   205:	invokespecial	#83; //Method scala/MatchError."<init>":(Ljava/lang/String;)V
   208:	athrow
   209:	aconst_null
   210:	areturn
  LineNumberTable: 
   line 306: 0
   line 307: 2
   line 308: 10
   line 21: 44
   line 308: 48
   line 21: 64
   line 310: 68
   line 308: 72
   line 21: 88
   line 312: 92
   line 313: 101
   line 314: 105
   line 315: 132
   line 316: 141
   line 317: 159
   line 320: 186
   line 308: 193
   line 322: 209

  LocalVariableTable: 
   Start  Length  Slot  Name   Signature
   0      211      0    this       Lscala/xml/Utility$;
   0      211      1    value       Ljava/lang/String;
   101      85      2    n       Ljava/lang/String;
   2      208      3    i       I
   17      192      4    temp55       C


public java.lang.String getName(java.lang.String, int);
  Code:
   Stack=4, Locals=9, Args_size=3
   0:	iload_2
   1:	aload_1
   2:	invokevirtual	#286; //Method java/lang/String.length:()I
   5:	if_icmplt	12
   8:	aconst_null
   9:	goto	270
   12:	new	#162; //class scala/collection/immutable/StringOps
   15:	dup
   16:	aload_1
   17:	invokespecial	#163; //Method scala/collection/immutable/StringOps."<init>":(Ljava/lang/String;)V
   20:	iload_2
   21:	invokeinterface	#306,  2; //InterfaceMethod scala/collection/IndexedSeqLike.drop:(I)Ljava/lang/Object;
   26:	checkcast	#94; //class java/lang/String
   29:	astore	8
   31:	aload	8
   33:	instanceof	#308; //class scala/collection/Seq
   36:	ifeq	263
   39:	aload	8
   41:	checkcast	#308; //class scala/collection/Seq
   44:	astore_3
   45:	getstatic	#313; //Field scala/collection/Seq$.MODULE$:Lscala/collection/Seq$;
   48:	aload_3
   49:	invokevirtual	#317; //Method scala/collection/Seq$.unapplySeq:(Lscala/collection/Seq;)Lscala/Some;
   52:	astore	4
   54:	iconst_1
   55:	ifeq	240
   58:	aload	4
   60:	getfield	#322; //Field scala/Some.x:Ljava/lang/Object;
   63:	checkcast	#308; //class scala/collection/Seq
   66:	astore	5
   68:	aload	5
   70:	dup
   71:	pop
   72:	ifnull	84
   75:	aload	5
   77:	aconst_null
   78:	invokevirtual	#326; //Method java/lang/Object.equals:(Ljava/lang/Object;)Z
   81:	ifeq	88
   84:	iconst_0
   85:	goto	105
   88:	aload	5
   90:	iconst_1
   91:	invokeinterface	#330,  2; //InterfaceMethod scala/collection/SeqLike.lengthCompare:(I)I
   96:	iconst_0
   97:	if_icmplt	104
   100:	iconst_1
   101:	goto	105
   104:	iconst_0
   105:	ifeq	217
   108:	aload	5
   110:	iconst_0
   111:	invokeinterface	#332,  2; //InterfaceMethod scala/collection/SeqLike.apply:(I)Ljava/lang/Object;
   116:	invokestatic	#49; //Method scala/runtime/BoxesRunTime.unboxToChar:(Ljava/lang/Object;)C
   119:	istore	6
   121:	aload	5
   123:	iconst_1
   124:	invokeinterface	#335,  2; //InterfaceMethod scala/collection/TraversableLike.drop:(I)Ljava/lang/Object;
   129:	checkcast	#308; //class scala/collection/Seq
   132:	astore	7
   134:	aload_0
   135:	iload	6
   137:	aload	7
   139:	invokespecial	#337; //Method gd2$1:(CLscala/collection/Seq;)Z
   142:	ifeq	194
   145:	new	#55; //class scala/collection/mutable/StringBuilder
   148:	dup
   149:	invokespecial	#56; //Method scala/collection/mutable/StringBuilder."<init>":()V
   152:	iload	6
   154:	invokestatic	#79; //Method scala/runtime/BoxesRunTime.boxToCharacter:(C)Ljava/lang/Character;
   157:	invokevirtual	#80; //Method java/lang/Object.toString:()Ljava/lang/String;
   160:	invokevirtual	#62; //Method scala/collection/mutable/StringBuilder.append:(Ljava/lang/Object;)Lscala/collection/mutable/StringBuilder;
   163:	aload	7
   165:	new	#339; //class scala/xml/Utility$$anonfun$getName$1
   168:	dup
   169:	invokespecial	#340; //Method scala/xml/Utility$$anonfun$getName$1."<init>":()V
   172:	invokeinterface	#344,  2; //InterfaceMethod scala/collection/IterableLike.takeWhile:(Lscala/Function1;)Ljava/lang/Object;
   177:	checkcast	#334; //class scala/collection/TraversableLike
   180:	invokeinterface	#347,  1; //InterfaceMethod scala/collection/TraversableLike.mkString:()Ljava/lang/String;
   185:	invokevirtual	#62; //Method scala/collection/mutable/StringBuilder.append:(Ljava/lang/Object;)Lscala/collection/mutable/StringBuilder;
   188:	invokevirtual	#68; //Method scala/collection/mutable/StringBuilder.toString:()Ljava/lang/String;
   191:	goto	270
   194:	iconst_1
   195:	ifeq	204
   198:	ldc_w	#349; //String 
   201:	goto	270
   204:	new	#75; //class scala/MatchError
   207:	dup
   208:	aload	8
   210:	invokevirtual	#350; //Method java/lang/String.toString:()Ljava/lang/String;
   213:	invokespecial	#83; //Method scala/MatchError."<init>":(Ljava/lang/String;)V
   216:	athrow
   217:	iconst_1
   218:	ifeq	227
   221:	ldc_w	#349; //String 
   224:	goto	270
   227:	new	#75; //class scala/MatchError
   230:	dup
   231:	aload	8
   233:	invokevirtual	#350; //Method java/lang/String.toString:()Ljava/lang/String;
   236:	invokespecial	#83; //Method scala/MatchError."<init>":(Ljava/lang/String;)V
   239:	athrow
   240:	iconst_1
   241:	ifeq	250
   244:	ldc_w	#349; //String 
   247:	goto	270
   250:	new	#75; //class scala/MatchError
   253:	dup
   254:	aload	8
   256:	invokevirtual	#350; //Method java/lang/String.toString:()Ljava/lang/String;
   259:	invokespecial	#83; //Method scala/MatchError."<init>":(Ljava/lang/String;)V
   262:	athrow
   263:	iconst_1
   264:	ifeq	271
   267:	ldc_w	#349; //String 
   270:	areturn
   271:	new	#75; //class scala/MatchError
   274:	dup
   275:	aload	8
   277:	invokevirtual	#350; //Method java/lang/String.toString:()Ljava/lang/String;
   280:	invokespecial	#83; //Method scala/MatchError."<init>":(Ljava/lang/String;)V
   283:	athrow
  LineNumberTable: 
   line 291: 0
   line 292: 12
   line 290: 39
   line 293: 45
   line 290: 48
   line 21: 54
   line 290: 58
   line 292: 68
   line 228: 84
   line 292: 88
   line 228: 96
   line 292: 100
   line 290: 108
   line 292: 134
   line 293: 145
   line 21: 194
   line 294: 198
   line 292: 204
   line 21: 217
   line 294: 221
   line 292: 227
   line 21: 240
   line 294: 244
   line 292: 250
   line 21: 263
   line 294: 267
   line 291: 270
   line 292: 271

  LocalVariableTable: 
   Start  Length  Slot  Name   Signature
   0      284      0    this       Lscala/xml/Utility$;
   0      284      1    s       Ljava/lang/String;
   0      284      2    index       I
   45      218      3    temp50       Lscala/collection/Seq;
   54      209      4    temp51       Lscala/Some;
   68      172      5    temp52       Lscala/collection/Seq;
   121      96      6    temp53       C
   134      83      7    temp54       Lscala/collection/Seq;
   31      239      8    temp49       Ljava/lang/String;
   271      13      8    temp49       Ljava/lang/String;


public scala.collection.mutable.StringBuilder appendEscapedQuoted(java.lang.String, scala.collection.mutable.StringBuilder);
  Code:
   Stack=4, Locals=3, Args_size=3
   0:	aload_2
   1:	ldc_w	#363; //int 34
   4:	invokevirtual	#204; //Method scala/collection/mutable/StringBuilder.append:(C)Lscala/collection/mutable/StringBuilder;
   7:	pop
   8:	getstatic	#99; //Field scala/Predef$.MODULE$:Lscala/Predef$;
   11:	aload_1
   12:	invokevirtual	#367; //Method scala/Predef$.augmentString:(Ljava/lang/String;)Lscala/collection/immutable/StringOps;
   15:	new	#369; //class scala/xml/Utility$$anonfun$appendEscapedQuoted$1
   18:	dup
   19:	aload_2
   20:	invokespecial	#370; //Method scala/xml/Utility$$anonfun$appendEscapedQuoted$1."<init>":(Lscala/collection/mutable/StringBuilder;)V
   23:	invokeinterface	#371,  2; //InterfaceMethod scala/collection/IndexedSeqLike.foreach:(Lscala/Function1;)V
   28:	aload_2
   29:	ldc_w	#363; //int 34
   32:	invokevirtual	#204; //Method scala/collection/mutable/StringBuilder.append:(C)Lscala/collection/mutable/StringBuilder;
   35:	areturn
  LineNumberTable: 
   line 277: 0
   line 278: 8
   line 282: 28

  LocalVariableTable: 
   Start  Length  Slot  Name   Signature
   0      36      0    this       Lscala/xml/Utility$;
   0      36      1    s       Ljava/lang/String;
   0      36      2    sb$3       Lscala/collection/mutable/StringBuilder;


public scala.collection.mutable.StringBuilder appendQuoted(java.lang.String, scala.collection.mutable.StringBuilder);
  Code:
   Stack=3, Locals=5, Args_size=3
   0:	new	#162; //class scala/collection/immutable/StringOps
   3:	dup
   4:	aload_1
   5:	invokespecial	#163; //Method scala/collection/immutable/StringOps."<init>":(Ljava/lang/String;)V
   8:	ldc_w	#363; //int 34
   11:	istore_3
   12:	iload_3
   13:	invokestatic	#79; //Method scala/runtime/BoxesRunTime.boxToCharacter:(C)Ljava/lang/Character;
   16:	invokeinterface	#376,  2; //InterfaceMethod scala/collection/SeqLike.contains:(Ljava/lang/Object;)Z
   21:	ifeq	30
   24:	ldc_w	#377; //int 39
   27:	goto	33
   30:	ldc_w	#363; //int 34
   33:	istore	4
   35:	aload_2
   36:	iload	4
   38:	invokevirtual	#204; //Method scala/collection/mutable/StringBuilder.append:(C)Lscala/collection/mutable/StringBuilder;
   41:	aload_1
   42:	invokevirtual	#201; //Method scala/collection/mutable/StringBuilder.append:(Ljava/lang/String;)Lscala/collection/mutable/StringBuilder;
   45:	iload	4
   47:	invokevirtual	#204; //Method scala/collection/mutable/StringBuilder.append:(C)Lscala/collection/mutable/StringBuilder;
   50:	areturn
  LineNumberTable: 
   line 265: 0
   line 266: 35

  LocalVariableTable: 
   Start  Length  Slot  Name   Signature
   0      51      0    this       Lscala/xml/Utility$;
   0      51      1    s       Ljava/lang/String;
   0      51      2    sb       Lscala/collection/mutable/StringBuilder;
   35      15      4    ch       C


public java.lang.String appendQuoted(java.lang.String);
  Code:
   Stack=3, Locals=4, Args_size=2
   0:	new	#379; //class scala/xml/Utility$$anonfun$appendQuoted$1
   3:	dup
   4:	pop
   5:	aload_1
   6:	invokespecial	#380; //Method scala/xml/Utility$$anonfun$appendQuoted$1."<init>":(Ljava/lang/String;)V
   9:	new	#55; //class scala/collection/mutable/StringBuilder
   12:	dup
   13:	invokespecial	#157; //Method scala/collection/mutable/StringBuilder."<init>":()V
   16:	astore_3
   17:	aload_3
   18:	checkcast	#55; //class scala/collection/mutable/StringBuilder
   21:	astore_2
   22:	getstatic	#19; //Field MODULE$:Lscala/xml/Utility$;
   25:	aload_1
   26:	aload_2
   27:	invokevirtual	#382; //Method appendQuoted:(Ljava/lang/String;Lscala/collection/mutable/StringBuilder;)Lscala/collection/mutable/StringBuilder;
   30:	pop
   31:	aload_3
   32:	invokevirtual	#205; //Method scala/collection/mutable/StringBuilder.toString:()Ljava/lang/String;
   35:	areturn
  LineNumberTable: 
   line 254: 0

  LocalVariableTable: 
   Start  Length  Slot  Name   Signature
   0      36      0    this       Lscala/xml/Utility$;
   0      36      1    s$1       Ljava/lang/String;
   17      18      3    sb0       Lscala/collection/mutable/StringBuilder;


public int hashCode(java.lang.String, java.lang.String, int, int, scala.collection.Seq);
  Code:
   Stack=3, Locals=8, Args_size=6
   0:	aload_1
   1:	ifnull	19
   4:	ldc_w	#387; //int 41
   7:	aload_1
   8:	invokevirtual	#389; //Method java/lang/String.hashCode:()I
   11:	imul
   12:	ldc_w	#390; //int 7
   15:	irem
   16:	goto	20
   19:	iconst_0
   20:	aload_2
   21:	invokevirtual	#389; //Method java/lang/String.hashCode:()I
   24:	ldc_w	#391; //int 53
   27:	imul
   28:	iadd
   29:	iload_3
   30:	ldc_w	#390; //int 7
   33:	imul
   34:	iadd
   35:	iload	4
   37:	ldc_w	#392; //int 31
   40:	imul
   41:	iadd
   42:	iconst_0
   43:	istore	6
   45:	aload	5
   47:	invokeinterface	#120,  1; //InterfaceMethod scala/collection/IterableLike.iterator:()Lscala/collection/Iterator;
   52:	astore	7
   54:	aload	7
   56:	invokeinterface	#170,  1; //InterfaceMethod scala/collection/Iterator.hasNext:()Z
   61:	ifeq	89
   64:	iload	6
   66:	ldc_w	#387; //int 41
   69:	imul
   70:	aload	7
   72:	invokeinterface	#175,  1; //InterfaceMethod scala/collection/Iterator.next:()Ljava/lang/Object;
   77:	checkcast	#394; //class scala/xml/Node
   80:	invokevirtual	#395; //Method scala/xml/Node.hashCode:()I
   83:	iadd
   84:	istore	6
   86:	goto	54
   89:	iload	6
   91:	iadd
   92:	ireturn
  LineNumberTable: 
   line 242: 0
   line 243: 20
   line 244: 29
   line 245: 35
   line 247: 42
   line 248: 45
   line 249: 54
   line 250: 89
   line 246: 91

  LocalVariableTable: 
   Start  Length  Slot  Name   Signature
   0      93      0    this       Lscala/xml/Utility$;
   0      93      1    pre       Ljava/lang/String;
   0      93      2    label       Ljava/lang/String;
   0      93      3    attribHashCode       I
   0      93      4    scpeHash       I
   0      93      5    children       Lscala/collection/Seq;
   45      46      6    c       I
   54      37      7    i       Lscala/collection/Iterator;

  Signature: length = 0x2
   01 FFFFFF92 

public final scala.Option prefix(java.lang.String);
  Code:
   Stack=5, Locals=3, Args_size=2
   0:	aload_1
   1:	ldc_w	#405; //int 58
   4:	invokevirtual	#408; //Method java/lang/String.indexOf:(I)I
   7:	istore_2
   8:	iload_2
   9:	iconst_m1
   10:	if_icmpne	38
   13:	iconst_1
   14:	ifeq	23
   17:	getstatic	#413; //Field scala/None$.MODULE$:Lscala/None$;
   20:	goto	55
   23:	new	#75; //class scala/MatchError
   26:	dup
   27:	iload_2
   28:	invokestatic	#417; //Method scala/runtime/BoxesRunTime.boxToInteger:(I)Ljava/lang/Integer;
   31:	invokevirtual	#80; //Method java/lang/Object.toString:()Ljava/lang/String;
   34:	invokespecial	#83; //Method scala/MatchError."<init>":(Ljava/lang/String;)V
   37:	athrow
   38:	iconst_1
   39:	ifeq	56
   42:	new	#319; //class scala/Some
   45:	dup
   46:	aload_1
   47:	iconst_0
   48:	iload_2
   49:	invokevirtual	#421; //Method java/lang/String.substring:(II)Ljava/lang/String;
   52:	invokespecial	#424; //Method scala/Some."<init>":(Ljava/lang/Object;)V
   55:	areturn
   56:	new	#75; //class scala/MatchError
   59:	dup
   60:	iload_2
   61:	invokestatic	#417; //Method scala/runtime/BoxesRunTime.boxToInteger:(I)Ljava/lang/Integer;
   64:	invokevirtual	#80; //Method java/lang/Object.toString:()Ljava/lang/String;
   67:	invokespecial	#83; //Method scala/MatchError."<init>":(Ljava/lang/String;)V
   70:	athrow
  LineNumberTable: 
   line 228: 0
   line 21: 13
   line 229: 17
   line 228: 23
   line 21: 38
   line 230: 42
   line 228: 55

  LocalVariableTable: 
   Start  Length  Slot  Name   Signature
   0      71      0    this       Lscala/xml/Utility$;
   0      71      1    name       Ljava/lang/String;
   8      63      2    temp47       I

  Signature: length = 0x2
   01 FFFFFFAB 

public void sequenceToXML(scala.collection.Seq, scala.xml.NamespaceBinding, scala.collection.mutable.StringBuilder, boolean);
  Code:
   Stack=8, Locals=8, Args_size=5
   0:	aload_1
   1:	invokeinterface	#432,  1; //InterfaceMethod scala/collection/IterableLike.isEmpty:()Z
   6:	ifeq	10
   9:	return
   10:	aload_1
   11:	new	#434; //class scala/xml/Utility$$anonfun$sequenceToXML$1
   14:	dup
   15:	invokespecial	#435; //Method scala/xml/Utility$$anonfun$sequenceToXML$1."<init>":()V
   18:	invokeinterface	#439,  2; //InterfaceMethod scala/collection/IterableLike.forall:(Lscala/Function1;)Z
   23:	ifeq	105
   26:	aload_1
   27:	invokeinterface	#120,  1; //InterfaceMethod scala/collection/IterableLike.iterator:()Lscala/collection/Iterator;
   32:	astore	6
   34:	aload	6
   36:	invokeinterface	#175,  1; //InterfaceMethod scala/collection/Iterator.next:()Ljava/lang/Object;
   41:	checkcast	#394; //class scala/xml/Node
   44:	astore	5
   46:	aload_0
   47:	aload	5
   49:	aload_2
   50:	aload_3
   51:	iconst_0
   52:	iconst_1
   53:	iconst_0
   54:	iconst_0
   55:	invokevirtual	#443; //Method toXML:(Lscala/xml/Node;Lscala/xml/NamespaceBinding;Lscala/collection/mutable/StringBuilder;ZZZZ)Lscala/collection/mutable/StringBuilder;
   58:	pop
   59:	aload	6
   61:	invokeinterface	#170,  1; //InterfaceMethod scala/collection/Iterator.hasNext:()Z
   66:	ifeq	120
   69:	aload	6
   71:	invokeinterface	#175,  1; //InterfaceMethod scala/collection/Iterator.next:()Ljava/lang/Object;
   76:	checkcast	#394; //class scala/xml/Node
   79:	astore	7
   81:	aload_3
   82:	ldc_w	#444; //int 32
   85:	invokevirtual	#204; //Method scala/collection/mutable/StringBuilder.append:(C)Lscala/collection/mutable/StringBuilder;
   88:	pop
   89:	aload_0
   90:	aload	7
   92:	aload_2
   93:	aload_3
   94:	iconst_0
   95:	iconst_1
   96:	iconst_0
   97:	iconst_0
   98:	invokevirtual	#443; //Method toXML:(Lscala/xml/Node;Lscala/xml/NamespaceBinding;Lscala/collection/mutable/StringBuilder;ZZZZ)Lscala/collection/mutable/StringBuilder;
   101:	pop
   102:	goto	59
   105:	aload_1
   106:	new	#446; //class scala/xml/Utility$$anonfun$sequenceToXML$2
   109:	dup
   110:	aload_2
   111:	aload_3
   112:	invokespecial	#449; //Method scala/xml/Utility$$anonfun$sequenceToXML$2."<init>":(Lscala/xml/NamespaceBinding;Lscala/collection/mutable/StringBuilder;)V
   115:	invokeinterface	#450,  2; //InterfaceMethod scala/collection/IterableLike.foreach:(Lscala/Function1;)V
   120:	return
  LineNumberTable: 
   line 208: 0
   line 209: 10
   line 210: 26
   line 211: 34
   line 212: 46
   line 213: 59
   line 214: 69
   line 215: 81
   line 216: 89
   line 219: 105
   line 208: 120

  LocalVariableTable: 
   Start  Length  Slot  Name   Signature
   0      121      0    this       Lscala/xml/Utility$;
   0      121      1    children       Lscala/collection/Seq;
   0      121      2    pscope$1       Lscala/xml/NamespaceBinding;
   0      121      3    sb$2       Lscala/collection/mutable/StringBuilder;
   0      121      4    stripComments       Z
   46      59      5    f       Lscala/xml/Node;
   34      71      6    it       Lscala/collection/Iterator;
   81      21      7    x       Lscala/xml/Node;

  Signature: length = 0x2
   01 FFFFFFCA 

public scala.collection.mutable.StringBuilder toXML(scala.xml.Node, scala.xml.NamespaceBinding, scala.collection.mutable.StringBuilder, boolean, boolean, boolean, boolean);
  Code:
   Stack=5, Locals=11, Args_size=8
   0:	aload_1
   1:	instanceof	#460; //class scala/xml/Comment
   4:	ifeq	56
   7:	aload_1
   8:	checkcast	#460; //class scala/xml/Comment
   11:	astore	8
   13:	aload_0
   14:	aload	8
   16:	iload	4
   18:	invokespecial	#462; //Method gd1$1:(Lscala/xml/Comment;Z)Z
   21:	ifeq	33
   24:	aload	8
   26:	aload_3
   27:	invokevirtual	#466; //Method scala/xml/Comment.buildString:(Lscala/collection/mutable/StringBuilder;)Lscala/collection/mutable/StringBuilder;
   30:	goto	266
   33:	iconst_1
   34:	ifeq	44
   37:	aload	8
   39:	astore	9
   41:	goto	73
   44:	new	#75; //class scala/MatchError
   47:	dup
   48:	aload_1
   49:	invokevirtual	#467; //Method scala/xml/Node.toString:()Ljava/lang/String;
   52:	invokespecial	#83; //Method scala/MatchError."<init>":(Ljava/lang/String;)V
   55:	athrow
   56:	aload_1
   57:	instanceof	#469; //class scala/xml/SpecialNode
   60:	ifeq	94
   63:	iconst_1
   64:	ifeq	82
   67:	aload_1
   68:	checkcast	#469; //class scala/xml/SpecialNode
   71:	astore	9
   73:	aload	9
   75:	aload_3
   76:	invokevirtual	#470; //Method scala/xml/SpecialNode.buildString:(Lscala/collection/mutable/StringBuilder;)Lscala/collection/mutable/StringBuilder;
   79:	goto	266
   82:	new	#75; //class scala/MatchError
   85:	dup
   86:	aload_1
   87:	invokevirtual	#467; //Method scala/xml/Node.toString:()Ljava/lang/String;
   90:	invokespecial	#83; //Method scala/MatchError."<init>":(Ljava/lang/String;)V
   93:	athrow
   94:	aload_1
   95:	instanceof	#472; //class scala/xml/Group
   98:	ifeq	146
   101:	aload_1
   102:	checkcast	#472; //class scala/xml/Group
   105:	astore	10
   107:	iconst_1
   108:	ifeq	134
   111:	aload	10
   113:	invokevirtual	#476; //Method scala/xml/Group.nodes:()Lscala/collection/Seq;
   116:	new	#478; //class scala/xml/Utility$$anonfun$toXML$1
   119:	dup
   120:	aload_1
   121:	aload_3
   122:	invokespecial	#481; //Method scala/xml/Utility$$anonfun$toXML$1."<init>":(Lscala/xml/Node;Lscala/collection/mutable/StringBuilder;)V
   125:	invokeinterface	#450,  2; //InterfaceMethod scala/collection/IterableLike.foreach:(Lscala/Function1;)V
   130:	aload_3
   131:	goto	266
   134:	new	#75; //class scala/MatchError
   137:	dup
   138:	aload_1
   139:	invokevirtual	#467; //Method scala/xml/Node.toString:()Ljava/lang/String;
   142:	invokespecial	#83; //Method scala/MatchError."<init>":(Ljava/lang/String;)V
   145:	athrow
   146:	iconst_1
   147:	ifeq	267
   150:	aload_3
   151:	ldc_w	#482; //int 60
   154:	invokevirtual	#204; //Method scala/collection/mutable/StringBuilder.append:(C)Lscala/collection/mutable/StringBuilder;
   157:	pop
   158:	aload_1
   159:	aload_3
   160:	invokevirtual	#485; //Method scala/xml/Node.nameToString:(Lscala/collection/mutable/StringBuilder;)Lscala/collection/mutable/StringBuilder;
   163:	pop
   164:	aload_1
   165:	invokevirtual	#489; //Method scala/xml/Node.attributes:()Lscala/xml/MetaData;
   168:	ifnull	182
   171:	aload_1
   172:	invokevirtual	#489; //Method scala/xml/Node.attributes:()Lscala/xml/MetaData;
   175:	aload_3
   176:	invokevirtual	#492; //Method scala/xml/MetaData.buildString:(Lscala/collection/mutable/StringBuilder;)Lscala/collection/mutable/StringBuilder;
   179:	goto	185
   182:	getstatic	#263; //Field scala/runtime/BoxedUnit.UNIT:Lscala/runtime/BoxedUnit;
   185:	pop
   186:	aload_1
   187:	invokevirtual	#496; //Method scala/xml/Node.scope:()Lscala/xml/NamespaceBinding;
   190:	aload_3
   191:	aload_2
   192:	invokevirtual	#501; //Method scala/xml/NamespaceBinding.buildString:(Lscala/collection/mutable/StringBuilder;Lscala/xml/NamespaceBinding;)V
   195:	aload_1
   196:	invokevirtual	#504; //Method scala/xml/Node.child:()Lscala/collection/Seq;
   199:	invokeinterface	#432,  1; //InterfaceMethod scala/collection/IterableLike.isEmpty:()Z
   204:	ifeq	222
   207:	iload	7
   209:	ifeq	222
   212:	aload_3
   213:	ldc_w	#506; //String  />
   216:	invokevirtual	#201; //Method scala/collection/mutable/StringBuilder.append:(Ljava/lang/String;)Lscala/collection/mutable/StringBuilder;
   219:	goto	266
   222:	aload_3
   223:	ldc_w	#507; //int 62
   226:	invokevirtual	#204; //Method scala/collection/mutable/StringBuilder.append:(C)Lscala/collection/mutable/StringBuilder;
   229:	pop
   230:	aload_0
   231:	aload_1
   232:	invokevirtual	#504; //Method scala/xml/Node.child:()Lscala/collection/Seq;
   235:	aload_1
   236:	invokevirtual	#496; //Method scala/xml/Node.scope:()Lscala/xml/NamespaceBinding;
   239:	aload_3
   240:	iload	4
   242:	invokevirtual	#509; //Method sequenceToXML:(Lscala/collection/Seq;Lscala/xml/NamespaceBinding;Lscala/collection/mutable/StringBuilder;Z)V
   245:	aload_3
   246:	ldc_w	#511; //String </
   249:	invokevirtual	#201; //Method scala/collection/mutable/StringBuilder.append:(Ljava/lang/String;)Lscala/collection/mutable/StringBuilder;
   252:	pop
   253:	aload_1
   254:	aload_3
   255:	invokevirtual	#485; //Method scala/xml/Node.nameToString:(Lscala/collection/mutable/StringBuilder;)Lscala/collection/mutable/StringBuilder;
   258:	pop
   259:	aload_3
   260:	ldc_w	#507; //int 62
   263:	invokevirtual	#204; //Method scala/collection/mutable/StringBuilder.append:(C)Lscala/collection/mutable/StringBuilder;
   266:	areturn
   267:	new	#75; //class scala/MatchError
   270:	dup
   271:	aload_1
   272:	invokevirtual	#467; //Method scala/xml/Node.toString:()Ljava/lang/String;
   275:	invokespecial	#83; //Method scala/MatchError."<init>":(Ljava/lang/String;)V
   278:	athrow
  LineNumberTable: 
   line 178: 0
   line 169: 7
   line 178: 13
   line 179: 24
   line 21: 33
   line 180: 37
   line 178: 44
   line 21: 63
   line 169: 67
   line 180: 73
   line 178: 82
   line 169: 101
   line 21: 107
   line 181: 111
   line 178: 134
   line 21: 146
   line 184: 150
   line 185: 158
   line 186: 164
   line 187: 186
   line 188: 195
   line 190: 212
   line 193: 222
   line 194: 230
   line 195: 245
   line 196: 253
   line 197: 259
   line 178: 266

  LocalVariableTable: 
   Start  Length  Slot  Name   Signature
   0      279      0    this       Lscala/xml/Utility$;
   0      279      1    x$7       Lscala/xml/Node;
   0      279      2    pscope       Lscala/xml/NamespaceBinding;
   0      279      3    sb$1       Lscala/collection/mutable/StringBuilder;
   0      279      4    stripComments$1       Z
   0      279      5    decodeEntities       Z
   0      279      6    preserveWhitespace       Z
   0      279      7    minimizeTags       Z
   13      43      8    temp42       Lscala/xml/Comment;
   73      9      8    temp42       Lscala/xml/Comment;
   33      4      9    x       Lscala/xml/SpecialNode;
   41      3      9    x       Lscala/xml/SpecialNode;
   37      19      9    x       Lscala/xml/SpecialNode;
   73      6      9    x       Lscala/xml/SpecialNode;
   107      39      10    temp45       Lscala/xml/Group;


public void collectNamespaces(scala.xml.Node, scala.collection.mutable.Set);
  Code:
   Stack=5, Locals=3, Args_size=3
   0:	aload_1
   1:	invokevirtual	#528; //Method scala/xml/Node.doCollectNamespaces:()Z
   4:	ifeq	53
   7:	aload_2
   8:	aload_1
   9:	invokevirtual	#531; //Method scala/xml/Node.namespace:()Ljava/lang/String;
   12:	invokeinterface	#536,  2; //InterfaceMethod scala/collection/mutable/SetLike.$plus$eq:(Ljava/lang/Object;)Lscala/collection/mutable/SetLike;
   17:	pop
   18:	aload_1
   19:	invokevirtual	#489; //Method scala/xml/Node.attributes:()Lscala/xml/MetaData;
   22:	new	#538; //class scala/xml/Utility$$anonfun$collectNamespaces$2
   25:	dup
   26:	aload_1
   27:	aload_2
   28:	invokespecial	#540; //Method scala/xml/Utility$$anonfun$collectNamespaces$2."<init>":(Lscala/xml/Node;Lscala/collection/mutable/Set;)V
   31:	invokeinterface	#450,  2; //InterfaceMethod scala/collection/IterableLike.foreach:(Lscala/Function1;)V
   36:	aload_1
   37:	invokevirtual	#504; //Method scala/xml/Node.child:()Lscala/collection/Seq;
   40:	new	#542; //class scala/xml/Utility$$anonfun$collectNamespaces$3
   43:	dup
   44:	aload_2
   45:	invokespecial	#545; //Method scala/xml/Utility$$anonfun$collectNamespaces$3."<init>":(Lscala/collection/mutable/Set;)V
   48:	invokeinterface	#450,  2; //InterfaceMethod scala/collection/IterableLike.foreach:(Lscala/Function1;)V
   53:	return
  LineNumberTable: 
   line 144: 0
   line 145: 7
   line 146: 18
   line 151: 36
   line 144: 53

  LocalVariableTable: 
   Start  Length  Slot  Name   Signature
   0      54      0    this       Lscala/xml/Utility$;
   0      54      1    n$1       Lscala/xml/Node;
   0      54      2    set$1       Lscala/collection/mutable/Set;

  Signature: length = 0x2
   02 25 

public scala.collection.mutable.Set collectNamespaces(scala.collection.Seq);
  Code:
   Stack=4, Locals=2, Args_size=2
   0:	aload_1
   1:	new	#552; //class scala/collection/mutable/HashSet
   4:	dup
   5:	invokespecial	#553; //Method scala/collection/mutable/HashSet."<init>":()V
   8:	new	#555; //class scala/xml/Utility$$anonfun$collectNamespaces$1
   11:	dup
   12:	invokespecial	#556; //Method scala/xml/Utility$$anonfun$collectNamespaces$1."<init>":()V
   15:	invokeinterface	#560,  3; //InterfaceMethod scala/collection/TraversableLike.foldLeft:(Ljava/lang/Object;Lscala/Function2;)Ljava/lang/Object;
   20:	checkcast	#562; //class scala/collection/mutable/Set
   23:	areturn
  LineNumberTable: 
   line 135: 0

  LocalVariableTable: 
   Start  Length  Slot  Name   Signature
   0      24      0    this       Lscala/xml/Utility$;
   0      24      1    nodes       Lscala/collection/Seq;

  Signature: length = 0x2
   02 33 

public final scala.collection.mutable.StringBuilder unescape(java.lang.String, scala.collection.mutable.StringBuilder);
  Code:
   Stack=4, Locals=3, Args_size=3
   0:	getstatic	#213; //Field scala/xml/Utility$Escapes$.MODULE$:Lscala/xml/Utility$Escapes$;
   3:	invokevirtual	#217; //Method scala/xml/Utility$Escapes$.unescMap:()Lscala/collection/immutable/Map;
   6:	aload_1
   7:	invokeinterface	#223,  2; //InterfaceMethod scala/collection/MapLike.get:(Ljava/lang/Object;)Lscala/Option;
   12:	new	#225; //class scala/xml/Utility$$anonfun$unescape$1
   15:	dup
   16:	aload_2
   17:	invokespecial	#228; //Method scala/xml/Utility$$anonfun$unescape$1."<init>":(Lscala/collection/mutable/StringBuilder;)V
   20:	invokevirtual	#234; //Method scala/Option.map:(Lscala/Function1;)Lscala/Option;
   23:	getstatic	#99; //Field scala/Predef$.MODULE$:Lscala/Predef$;
   26:	invokevirtual	#568; //Method scala/Predef$.conforms:()Lscala/Predef$$less$colon$less;
   29:	invokevirtual	#241; //Method scala/Option.orNull:(Lscala/Predef$$less$colon$less;)Ljava/lang/Object;
   32:	checkcast	#55; //class scala/collection/mutable/StringBuilder
   35:	areturn
  LineNumberTable: 
   line 125: 0

  LocalVariableTable: 
   Start  Length  Slot  Name   Signature
   0      36      0    this       Lscala/xml/Utility$;
   0      36      1    ref       Ljava/lang/String;
   0      36      2    s$2       Lscala/collection/mutable/StringBuilder;


public final scala.collection.mutable.StringBuilder escape(java.lang.String, scala.collection.mutable.StringBuilder);
  Code:
   Stack=4, Locals=3, Args_size=3
   0:	getstatic	#99; //Field scala/Predef$.MODULE$:Lscala/Predef$;
   3:	aload_1
   4:	invokevirtual	#367; //Method scala/Predef$.augmentString:(Ljava/lang/String;)Lscala/collection/immutable/StringOps;
   7:	aload_2
   8:	new	#572; //class scala/xml/Utility$$anonfun$escape$2
   11:	dup
   12:	invokespecial	#573; //Method scala/xml/Utility$$anonfun$escape$2."<init>":()V
   15:	invokeinterface	#574,  3; //InterfaceMethod scala/collection/IndexedSeqLike.foldLeft:(Ljava/lang/Object;Lscala/Function2;)Ljava/lang/Object;
   20:	checkcast	#55; //class scala/collection/mutable/StringBuilder
   23:	areturn
  LineNumberTable: 
   line 110: 0

  LocalVariableTable: 
   Start  Length  Slot  Name   Signature
   0      24      0    this       Lscala/xml/Utility$;
   0      24      1    text       Ljava/lang/String;
   0      24      2    s       Lscala/collection/mutable/StringBuilder;


public final java.lang.String escape(java.lang.String);
  Code:
   Stack=4, Locals=5, Args_size=2
   0:	new	#577; //class scala/xml/Utility$$anonfun$escape$1
   3:	dup
   4:	pop
   5:	aload_1
   6:	invokespecial	#578; //Method scala/xml/Utility$$anonfun$escape$1."<init>":(Ljava/lang/String;)V
   9:	new	#55; //class scala/collection/mutable/StringBuilder
   12:	dup
   13:	invokespecial	#157; //Method scala/collection/mutable/StringBuilder."<init>":()V
   16:	astore	4
   18:	aload	4
   20:	checkcast	#55; //class scala/collection/mutable/StringBuilder
   23:	astore_3
   24:	aload_1
   25:	astore_2
   26:	new	#162; //class scala/collection/immutable/StringOps
   29:	dup
   30:	aload_2
   31:	invokespecial	#163; //Method scala/collection/immutable/StringOps."<init>":(Ljava/lang/String;)V
   34:	aload_3
   35:	new	#572; //class scala/xml/Utility$$anonfun$escape$2
   38:	dup
   39:	invokespecial	#573; //Method scala/xml/Utility$$anonfun$escape$2."<init>":()V
   42:	invokeinterface	#574,  3; //InterfaceMethod scala/collection/IndexedSeqLike.foldLeft:(Ljava/lang/Object;Lscala/Function2;)Ljava/lang/Object;
   47:	pop
   48:	aload	4
   50:	invokevirtual	#205; //Method scala/collection/mutable/StringBuilder.toString:()Ljava/lang/String;
   53:	areturn
  LineNumberTable: 
   line 83: 0

  LocalVariableTable: 
   Start  Length  Slot  Name   Signature
   0      54      0    this       Lscala/xml/Utility$;
   0      54      1    text$1       Ljava/lang/String;
   18      35      4    sb0       Lscala/collection/mutable/StringBuilder;


public scala.xml.Node sort(scala.xml.Node);
  Code:
   Stack=7, Locals=12, Args_size=2
   0:	getstatic	#586; //Field scala/xml/Elem$.MODULE$:Lscala/xml/Elem$;
   3:	aload_1
   4:	invokevirtual	#589; //Method scala/xml/Elem$.unapplySeq:(Lscala/xml/Node;)Lscala/Option;
   7:	astore_2
   8:	aload_2
   9:	invokevirtual	#590; //Method scala/Option.isEmpty:()Z
   12:	ifeq	31
   15:	iconst_1
   16:	ifne	205
   19:	new	#75; //class scala/MatchError
   22:	dup
   23:	aload_1
   24:	invokevirtual	#467; //Method scala/xml/Node.toString:()Ljava/lang/String;
   27:	invokespecial	#83; //Method scala/MatchError."<init>":(Ljava/lang/String;)V
   30:	athrow
   31:	aload_2
   32:	invokevirtual	#592; //Method scala/Option.get:()Ljava/lang/Object;
   35:	checkcast	#594; //class scala/Tuple5
   38:	astore_3
   39:	aload_3
   40:	invokevirtual	#597; //Method scala/Tuple5._1:()Ljava/lang/Object;
   43:	checkcast	#94; //class java/lang/String
   46:	astore	7
   48:	aload_3
   49:	invokevirtual	#600; //Method scala/Tuple5._2:()Ljava/lang/Object;
   52:	checkcast	#94; //class java/lang/String
   55:	astore	8
   57:	aload_3
   58:	invokevirtual	#603; //Method scala/Tuple5._3:()Ljava/lang/Object;
   61:	checkcast	#491; //class scala/xml/MetaData
   64:	astore	4
   66:	aload_3
   67:	invokevirtual	#606; //Method scala/Tuple5._4:()Ljava/lang/Object;
   70:	checkcast	#498; //class scala/xml/NamespaceBinding
   73:	astore	10
   75:	aload_3
   76:	invokevirtual	#609; //Method scala/Tuple5._5:()Ljava/lang/Object;
   79:	checkcast	#308; //class scala/collection/Seq
   82:	astore	5
   84:	aload	5
   86:	dup
   87:	pop
   88:	ifnull	100
   91:	aload	5
   93:	aconst_null
   94:	invokevirtual	#326; //Method java/lang/Object.equals:(Ljava/lang/Object;)Z
   97:	ifeq	104
   100:	iconst_0
   101:	goto	121
   104:	aload	5
   106:	iconst_0
   107:	invokeinterface	#330,  2; //InterfaceMethod scala/collection/SeqLike.lengthCompare:(I)I
   112:	iconst_0
   113:	if_icmplt	120
   116:	iconst_1
   117:	goto	121
   120:	iconst_0
   121:	ifeq	201
   124:	iconst_1
   125:	ifeq	189
   128:	aload_0
   129:	aload	4
   131:	invokevirtual	#612; //Method sort:(Lscala/xml/MetaData;)Lscala/xml/MetaData;
   134:	aload	5
   136:	new	#614; //class scala/xml/Utility$$anonfun$sort$1
   139:	dup
   140:	invokespecial	#615; //Method scala/xml/Utility$$anonfun$sort$1."<init>":()V
   143:	getstatic	#313; //Field scala/collection/Seq$.MODULE$:Lscala/collection/Seq$;
   146:	astore	6
   148:	new	#617; //class scala/collection/generic/TraversableFactory$GenericCanBuildFrom
   151:	dup
   152:	aload	6
   154:	invokespecial	#620; //Method scala/collection/generic/TraversableFactory$GenericCanBuildFrom."<init>":(Lscala/collection/generic/TraversableFactory;)V
   157:	invokeinterface	#623,  3; //InterfaceMethod scala/collection/TraversableLike.map:(Lscala/Function1;Lscala/collection/generic/CanBuildFrom;)Ljava/lang/Object;
   162:	checkcast	#308; //class scala/collection/Seq
   165:	astore	11
   167:	astore	9
   169:	new	#625; //class scala/xml/Elem
   172:	dup
   173:	aload	7
   175:	aload	8
   177:	aload	9
   179:	aload	10
   181:	aload	11
   183:	invokespecial	#628; //Method scala/xml/Elem."<init>":(Ljava/lang/String;Ljava/lang/String;Lscala/xml/MetaData;Lscala/xml/NamespaceBinding;Lscala/collection/Seq;)V
   186:	goto	206
   189:	new	#75; //class scala/MatchError
   192:	dup
   193:	aload_1
   194:	invokevirtual	#467; //Method scala/xml/Node.toString:()Ljava/lang/String;
   197:	invokespecial	#83; //Method scala/MatchError."<init>":(Ljava/lang/String;)V
   200:	athrow
   201:	iconst_1
   202:	ifeq	207
   205:	aload_1
   206:	areturn
   207:	new	#75; //class scala/MatchError
   210:	dup
   211:	aload_1
   212:	invokevirtual	#467; //Method scala/xml/Node.toString:()Ljava/lang/String;
   215:	invokespecial	#83; //Method scala/MatchError."<init>":(Ljava/lang/String;)V
   218:	athrow
  LineNumberTable: 
   line 72: 0
   line 71: 3
   line 21: 15
   line 71: 19
   line 228: 100
   line 71: 104
   line 228: 112
   line 71: 116
   line 21: 124
   line 73: 128
   line 71: 189
   line 21: 201
   line 74: 205
   line 71: 206

  LocalVariableTable: 
   Start  Length  Slot  Name   Signature
   0      219      0    this       Lscala/xml/Utility$;
   0      219      1    n       Lscala/xml/Node;
   8      211      2    temp24       Lscala/Option;
   39      167      3    temp25       Lscala/Tuple5;
   207      12      3    temp25       Lscala/Tuple5;
   66      140      4    temp28       Lscala/xml/MetaData;
   207      12      4    temp28       Lscala/xml/MetaData;
   84      122      5    temp30       Lscala/collection/Seq;
   207      12      5    temp30       Lscala/collection/Seq;
   48      158      7    temp26       Ljava/lang/String;
   207      12      7    temp26       Ljava/lang/String;
   57      149      8    temp27       Ljava/lang/String;
   207      12      8    temp27       Ljava/lang/String;
   75      131      10    temp29       Lscala/xml/NamespaceBinding;
   207      12      10    temp29       Lscala/xml/NamespaceBinding;


public scala.xml.MetaData sort(scala.xml.MetaData);
  Code:
   Stack=5, Locals=8, Args_size=2
   0:	aload_1
   1:	getstatic	#643; //Field scala/xml/Null$.MODULE$:Lscala/xml/Null$;
   4:	if_acmpeq	17
   7:	aload_1
   8:	invokevirtual	#645; //Method scala/xml/MetaData.next:()Lscala/xml/MetaData;
   11:	getstatic	#643; //Field scala/xml/Null$.MODULE$:Lscala/xml/Null$;
   14:	if_acmpne	21
   17:	aload_1
   18:	goto	98
   21:	aload_1
   22:	invokevirtual	#648; //Method scala/xml/MetaData.key:()Ljava/lang/String;
   25:	astore_2
   26:	aload_0
   27:	aload_1
   28:	new	#650; //class scala/xml/Utility$$anonfun$1
   31:	dup
   32:	aload_2
   33:	invokespecial	#651; //Method scala/xml/Utility$$anonfun$1."<init>":(Ljava/lang/String;)V
   36:	invokevirtual	#655; //Method scala/xml/MetaData.filter:(Lscala/Function1;)Lscala/xml/MetaData;
   39:	invokevirtual	#612; //Method sort:(Lscala/xml/MetaData;)Lscala/xml/MetaData;
   42:	astore_3
   43:	aload_0
   44:	aload_1
   45:	new	#657; //class scala/xml/Utility$$anonfun$2
   48:	dup
   49:	aload_2
   50:	invokespecial	#658; //Method scala/xml/Utility$$anonfun$2."<init>":(Ljava/lang/String;)V
   53:	invokevirtual	#655; //Method scala/xml/MetaData.filter:(Lscala/Function1;)Lscala/xml/MetaData;
   56:	invokevirtual	#612; //Method sort:(Lscala/xml/MetaData;)Lscala/xml/MetaData;
   59:	astore	4
   61:	aload_3
   62:	getstatic	#643; //Field scala/xml/Null$.MODULE$:Lscala/xml/Null$;
   65:	aload_3
   66:	invokevirtual	#661; //Method scala/xml/MetaData.append$default$2:()Lscala/xml/NamespaceBinding;
   69:	invokevirtual	#664; //Method scala/xml/MetaData.append:(Lscala/xml/MetaData;Lscala/xml/NamespaceBinding;)Lscala/xml/MetaData;
   72:	astore	5
   74:	aload_1
   75:	aload	4
   77:	invokevirtual	#667; //Method scala/xml/MetaData.copy:(Lscala/xml/MetaData;)Lscala/xml/MetaData;
   80:	astore	6
   82:	aload	5
   84:	invokevirtual	#661; //Method scala/xml/MetaData.append$default$2:()Lscala/xml/NamespaceBinding;
   87:	astore	7
   89:	aload	5
   91:	aload	6
   93:	aload	7
   95:	invokevirtual	#664; //Method scala/xml/MetaData.append:(Lscala/xml/MetaData;Lscala/xml/NamespaceBinding;)Lscala/xml/MetaData;
   98:	areturn
  LineNumberTable: 
   line 63: 0
   line 64: 21
   line 65: 26
   line 66: 43
   line 67: 61
   line 63: 98

  LocalVariableTable: 
   Start  Length  Slot  Name   Signature
   0      99      0    this       Lscala/xml/Utility$;
   0      99      1    md       Lscala/xml/MetaData;
   26      72      2    key$1       Ljava/lang/String;
   43      55      3    smaller       Lscala/xml/MetaData;
   61      37      4    greater       Lscala/xml/MetaData;
   74      24      5    qual$1       Lscala/xml/MetaData;
   82      16      6    x$5       Lscala/xml/MetaData;
   89      9      7    x$6       Lscala/xml/NamespaceBinding;


public scala.collection.Seq trimProper(scala.xml.Node);
  Code:
   Stack=7, Locals=15, Args_size=2
   0:	getstatic	#586; //Field scala/xml/Elem$.MODULE$:Lscala/xml/Elem$;
   3:	aload_1
   4:	invokevirtual	#589; //Method scala/xml/Elem$.unapplySeq:(Lscala/xml/Node;)Lscala/Option;
   7:	astore_3
   8:	aload_3
   9:	invokevirtual	#590; //Method scala/Option.isEmpty:()Z
   12:	ifeq	74
   15:	getstatic	#247; //Field scala/xml/Text$.MODULE$:Lscala/xml/Text$;
   18:	aload_1
   19:	invokevirtual	#679; //Method scala/xml/Text$.unapply:(Ljava/lang/Object;)Lscala/Option;
   22:	astore_2
   23:	aload_2
   24:	invokevirtual	#590; //Method scala/Option.isEmpty:()Z
   27:	ifeq	46
   30:	iconst_1
   31:	ifne	263
   34:	new	#75; //class scala/MatchError
   37:	dup
   38:	aload_1
   39:	invokevirtual	#467; //Method scala/xml/Node.toString:()Ljava/lang/String;
   42:	invokespecial	#83; //Method scala/MatchError."<init>":(Ljava/lang/String;)V
   45:	athrow
   46:	iconst_1
   47:	ifeq	62
   50:	aload_2
   51:	invokevirtual	#592; //Method scala/Option.get:()Ljava/lang/Object;
   54:	checkcast	#94; //class java/lang/String
   57:	astore	14
   59:	goto	297
   62:	new	#75; //class scala/MatchError
   65:	dup
   66:	aload_1
   67:	invokevirtual	#467; //Method scala/xml/Node.toString:()Ljava/lang/String;
   70:	invokespecial	#83; //Method scala/MatchError."<init>":(Ljava/lang/String;)V
   73:	athrow
   74:	aload_3
   75:	invokevirtual	#592; //Method scala/Option.get:()Ljava/lang/Object;
   78:	checkcast	#594; //class scala/Tuple5
   81:	astore	4
   83:	aload	4
   85:	invokevirtual	#597; //Method scala/Tuple5._1:()Ljava/lang/Object;
   88:	checkcast	#94; //class java/lang/String
   91:	astore	7
   93:	aload	4
   95:	invokevirtual	#600; //Method scala/Tuple5._2:()Ljava/lang/Object;
   98:	checkcast	#94; //class java/lang/String
   101:	astore	8
   103:	aload	4
   105:	invokevirtual	#603; //Method scala/Tuple5._3:()Ljava/lang/Object;
   108:	checkcast	#491; //class scala/xml/MetaData
   111:	astore	9
   113:	aload	4
   115:	invokevirtual	#606; //Method scala/Tuple5._4:()Ljava/lang/Object;
   118:	checkcast	#498; //class scala/xml/NamespaceBinding
   121:	astore	10
   123:	aload	4
   125:	invokevirtual	#609; //Method scala/Tuple5._5:()Ljava/lang/Object;
   128:	checkcast	#308; //class scala/collection/Seq
   131:	astore	5
   133:	aload	5
   135:	dup
   136:	pop
   137:	ifnull	149
   140:	aload	5
   142:	aconst_null
   143:	invokevirtual	#326; //Method java/lang/Object.equals:(Ljava/lang/Object;)Z
   146:	ifeq	153
   149:	iconst_0
   150:	goto	170
   153:	aload	5
   155:	iconst_0
   156:	invokeinterface	#330,  2; //InterfaceMethod scala/collection/SeqLike.lengthCompare:(I)I
   161:	iconst_0
   162:	if_icmplt	169
   165:	iconst_1
   166:	goto	170
   169:	iconst_0
   170:	ifeq	242
   173:	iconst_1
   174:	ifeq	230
   177:	aload	5
   179:	new	#681; //class scala/xml/Utility$$anonfun$trimProper$1
   182:	dup
   183:	invokespecial	#682; //Method scala/xml/Utility$$anonfun$trimProper$1."<init>":()V
   186:	getstatic	#313; //Field scala/collection/Seq$.MODULE$:Lscala/collection/Seq$;
   189:	astore	6
   191:	new	#617; //class scala/collection/generic/TraversableFactory$GenericCanBuildFrom
   194:	dup
   195:	aload	6
   197:	invokespecial	#620; //Method scala/collection/generic/TraversableFactory$GenericCanBuildFrom."<init>":(Lscala/collection/generic/TraversableFactory;)V
   200:	invokeinterface	#685,  3; //InterfaceMethod scala/collection/TraversableLike.flatMap:(Lscala/Function1;Lscala/collection/generic/CanBuildFrom;)Ljava/lang/Object;
   205:	checkcast	#308; //class scala/collection/Seq
   208:	astore	11
   210:	new	#625; //class scala/xml/Elem
   213:	dup
   214:	aload	7
   216:	aload	8
   218:	aload	9
   220:	aload	10
   222:	aload	11
   224:	invokespecial	#628; //Method scala/xml/Elem."<init>":(Ljava/lang/String;Ljava/lang/String;Lscala/xml/MetaData;Lscala/xml/NamespaceBinding;Lscala/collection/Seq;)V
   227:	goto	318
   230:	new	#75; //class scala/MatchError
   233:	dup
   234:	aload_1
   235:	invokevirtual	#467; //Method scala/xml/Node.toString:()Ljava/lang/String;
   238:	invokespecial	#83; //Method scala/MatchError."<init>":(Ljava/lang/String;)V
   241:	athrow
   242:	getstatic	#247; //Field scala/xml/Text$.MODULE$:Lscala/xml/Text$;
   245:	aload_1
   246:	invokevirtual	#679; //Method scala/xml/Text$.unapply:(Ljava/lang/Object;)Lscala/Option;
   249:	astore	12
   251:	aload	12
   253:	invokevirtual	#590; //Method scala/Option.isEmpty:()Z
   256:	ifeq	279
   259:	iconst_1
   260:	ifeq	267
   263:	aload_1
   264:	goto	318
   267:	new	#75; //class scala/MatchError
   270:	dup
   271:	aload_1
   272:	invokevirtual	#467; //Method scala/xml/Node.toString:()Ljava/lang/String;
   275:	invokespecial	#83; //Method scala/MatchError."<init>":(Ljava/lang/String;)V
   278:	athrow
   279:	aload	12
   281:	invokevirtual	#592; //Method scala/Option.get:()Ljava/lang/Object;
   284:	checkcast	#94; //class java/lang/String
   287:	astore	13
   289:	iconst_1
   290:	ifeq	319
   293:	aload	13
   295:	astore	14
   297:	new	#687; //class scala/xml/TextBuffer
   300:	dup
   301:	invokespecial	#688; //Method scala/xml/TextBuffer."<init>":()V
   304:	getstatic	#99; //Field scala/Predef$.MODULE$:Lscala/Predef$;
   307:	aload	14
   309:	invokevirtual	#692; //Method scala/Predef$.wrapString:(Ljava/lang/String;)Lscala/collection/immutable/WrappedString;
   312:	invokevirtual	#695; //Method scala/xml/TextBuffer.append:(Lscala/collection/Seq;)Lscala/xml/TextBuffer;
   315:	invokevirtual	#698; //Method scala/xml/TextBuffer.toText:()Lscala/collection/Seq;
   318:	areturn
   319:	new	#75; //class scala/MatchError
   322:	dup
   323:	aload_1
   324:	invokevirtual	#467; //Method scala/xml/Node.toString:()Ljava/lang/String;
   327:	invokespecial	#83; //Method scala/MatchError."<init>":(Ljava/lang/String;)V
   330:	athrow
  LineNumberTable: 
   line 55: 0
   line 54: 3
   line 57: 15
   line 54: 18
   line 21: 30
   line 54: 34
   line 21: 46
   line 54: 50
   line 228: 149
   line 54: 153
   line 228: 161
   line 54: 165
   line 21: 173
   line 56: 177
   line 54: 230
   line 57: 242
   line 54: 245
   line 21: 259
   line 60: 263
   line 54: 267
   line 21: 289
   line 57: 293
   line 58: 297
   line 54: 318

  LocalVariableTable: 
   Start  Length  Slot  Name   Signature
   0      331      0    this       Lscala/xml/Utility$;
   0      331      1    x       Lscala/xml/Node;
   23      51      2    temp21       Lscala/Option;
   8      323      3    temp11       Lscala/Option;
   83      235      4    temp12       Lscala/Tuple5;
   319      12      4    temp12       Lscala/Tuple5;
   133      185      5    temp17       Lscala/collection/Seq;
   319      12      5    temp17       Lscala/collection/Seq;
   93      225      7    temp13       Ljava/lang/String;
   319      12      7    temp13       Ljava/lang/String;
   103      215      8    temp14       Ljava/lang/String;
   319      12      8    temp14       Ljava/lang/String;
   113      205      9    temp15       Lscala/xml/MetaData;
   319      12      9    temp15       Lscala/xml/MetaData;
   123      195      10    temp16       Lscala/xml/NamespaceBinding;
   319      12      10    temp16       Lscala/xml/NamespaceBinding;
   251      67      12    temp19       Lscala/Option;
   319      12      12    temp19       Lscala/Option;
   289      29      13    temp20       Ljava/lang/String;
   319      12      13    temp20       Ljava/lang/String;
   289      4      14    s       Ljava/lang/String;
   297      0      14    s       Ljava/lang/String;
   293      25      14    s       Ljava/lang/String;
   319      12      14    s       Ljava/lang/String;

  Signature: length = 0x2
   02 FFFFFFC5 

public scala.xml.Node trim(scala.xml.Node);
  Code:
   Stack=7, Locals=11, Args_size=2
   0:	getstatic	#586; //Field scala/xml/Elem$.MODULE$:Lscala/xml/Elem$;
   3:	aload_1
   4:	invokevirtual	#589; //Method scala/xml/Elem$.unapplySeq:(Lscala/xml/Node;)Lscala/Option;
   7:	astore_2
   8:	aload_2
   9:	invokevirtual	#590; //Method scala/Option.isEmpty:()Z
   12:	ifeq	27
   15:	new	#75; //class scala/MatchError
   18:	dup
   19:	aload_1
   20:	invokevirtual	#467; //Method scala/xml/Node.toString:()Ljava/lang/String;
   23:	invokespecial	#83; //Method scala/MatchError."<init>":(Ljava/lang/String;)V
   26:	athrow
   27:	aload_2
   28:	invokevirtual	#592; //Method scala/Option.get:()Ljava/lang/Object;
   31:	checkcast	#594; //class scala/Tuple5
   34:	astore_3
   35:	aload_3
   36:	invokevirtual	#597; //Method scala/Tuple5._1:()Ljava/lang/Object;
   39:	checkcast	#94; //class java/lang/String
   42:	astore	6
   44:	aload_3
   45:	invokevirtual	#600; //Method scala/Tuple5._2:()Ljava/lang/Object;
   48:	checkcast	#94; //class java/lang/String
   51:	astore	7
   53:	aload_3
   54:	invokevirtual	#603; //Method scala/Tuple5._3:()Ljava/lang/Object;
   57:	checkcast	#491; //class scala/xml/MetaData
   60:	astore	8
   62:	aload_3
   63:	invokevirtual	#606; //Method scala/Tuple5._4:()Ljava/lang/Object;
   66:	checkcast	#498; //class scala/xml/NamespaceBinding
   69:	astore	9
   71:	aload_3
   72:	invokevirtual	#609; //Method scala/Tuple5._5:()Ljava/lang/Object;
   75:	checkcast	#308; //class scala/collection/Seq
   78:	astore	4
   80:	aload	4
   82:	dup
   83:	pop
   84:	ifnull	96
   87:	aload	4
   89:	aconst_null
   90:	invokevirtual	#326; //Method java/lang/Object.equals:(Ljava/lang/Object;)Z
   93:	ifeq	100
   96:	iconst_0
   97:	goto	117
   100:	aload	4
   102:	iconst_0
   103:	invokeinterface	#330,  2; //InterfaceMethod scala/collection/SeqLike.lengthCompare:(I)I
   108:	iconst_0
   109:	if_icmplt	116
   112:	iconst_1
   113:	goto	117
   116:	iconst_0
   117:	ifeq	187
   120:	iconst_1
   121:	ifeq	175
   124:	aload	4
   126:	new	#712; //class scala/xml/Utility$$anonfun$trim$1
   129:	dup
   130:	invokespecial	#713; //Method scala/xml/Utility$$anonfun$trim$1."<init>":()V
   133:	getstatic	#313; //Field scala/collection/Seq$.MODULE$:Lscala/collection/Seq$;
   136:	astore	5
   138:	new	#617; //class scala/collection/generic/TraversableFactory$GenericCanBuildFrom
   141:	dup
   142:	aload	5
   144:	invokespecial	#620; //Method scala/collection/generic/TraversableFactory$GenericCanBuildFrom."<init>":(Lscala/collection/generic/TraversableFactory;)V
   147:	invokeinterface	#685,  3; //InterfaceMethod scala/collection/TraversableLike.flatMap:(Lscala/Function1;Lscala/collection/generic/CanBuildFrom;)Ljava/lang/Object;
   152:	checkcast	#308; //class scala/collection/Seq
   155:	astore	10
   157:	new	#625; //class scala/xml/Elem
   160:	dup
   161:	aload	6
   163:	aload	7
   165:	aload	8
   167:	aload	9
   169:	aload	10
   171:	invokespecial	#628; //Method scala/xml/Elem."<init>":(Ljava/lang/String;Ljava/lang/String;Lscala/xml/MetaData;Lscala/xml/NamespaceBinding;Lscala/collection/Seq;)V
   174:	areturn
   175:	new	#75; //class scala/MatchError
   178:	dup
   179:	aload_1
   180:	invokevirtual	#467; //Method scala/xml/Node.toString:()Ljava/lang/String;
   183:	invokespecial	#83; //Method scala/MatchError."<init>":(Ljava/lang/String;)V
   186:	athrow
   187:	new	#75; //class scala/MatchError
   190:	dup
   191:	aload_1
   192:	invokevirtual	#467; //Method scala/xml/Node.toString:()Ljava/lang/String;
   195:	invokespecial	#83; //Method scala/MatchError."<init>":(Ljava/lang/String;)V
   198:	athrow
  LineNumberTable: 
   line 47: 0
   line 46: 3
   line 228: 96
   line 46: 100
   line 228: 108
   line 46: 112
   line 21: 120
   line 48: 124
   line 46: 174

  LocalVariableTable: 
   Start  Length  Slot  Name   Signature
   0      199      0    this       Lscala/xml/Utility$;
   0      199      1    x       Lscala/xml/Node;
   8      191      2    temp2       Lscala/Option;
   35      164      3    temp3       Lscala/Tuple5;
   80      119      4    temp8       Lscala/collection/Seq;
   44      155      6    temp4       Ljava/lang/String;
   53      146      7    temp5       Ljava/lang/String;
   62      137      8    temp6       Lscala/xml/MetaData;
   71      128      9    temp7       Lscala/xml/NamespaceBinding;


public boolean isAtomAndNotText(scala.xml.Node);
  Code:
   Stack=1, Locals=2, Args_size=2
   0:	aload_1
   1:	invokevirtual	#725; //Method scala/xml/Node.isAtom:()Z
   4:	ifeq	18
   7:	aload_1
   8:	instanceof	#727; //class scala/xml/Text
   11:	ifne	18
   14:	iconst_1
   15:	goto	19
   18:	iconst_0
   19:	ireturn
  LineNumberTable: 
   line 35: 0

  LocalVariableTable: 
   Start  Length  Slot  Name   Signature
   0      20      0    this       Lscala/xml/Utility$;
   0      20      1    x       Lscala/xml/Node;


public java.lang.String sbToString(scala.Function1);
  Code:
   Stack=2, Locals=3, Args_size=2
   0:	new	#55; //class scala/collection/mutable/StringBuilder
   3:	dup
   4:	invokespecial	#157; //Method scala/collection/mutable/StringBuilder."<init>":()V
   7:	astore_2
   8:	aload_1
   9:	aload_2
   10:	invokeinterface	#73,  2; //InterfaceMethod scala/Function1.apply:(Ljava/lang/Object;)Ljava/lang/Object;
   15:	pop
   16:	aload_2
   17:	invokevirtual	#205; //Method scala/collection/mutable/StringBuilder.toString:()Ljava/lang/String;
   20:	areturn
  LineNumberTable: 
   line 31: 0
   line 32: 8
   line 33: 9
   line 32: 10
   line 33: 16

  LocalVariableTable: 
   Start  Length  Slot  Name   Signature
   0      21      0    this       Lscala/xml/Utility$;
   0      21      1    f       Lscala/Function1;
   8      12      2    sb       Lscala/collection/mutable/StringBuilder;

  Signature: length = 0x2
   02 FFFFFFDA 

public java.lang.String implicitSbToString(scala.collection.mutable.StringBuilder);
  Code:
   Stack=1, Locals=2, Args_size=2
   0:	aload_1
   1:	invokevirtual	#205; //Method scala/collection/mutable/StringBuilder.toString:()Ljava/lang/String;
   4:	areturn
  LineNumberTable: 
   line 26: 0

  LocalVariableTable: 
   Start  Length  Slot  Name   Signature
   0      5      0    this       Lscala/xml/Utility$;
   0      5      1    sb       Lscala/collection/mutable/StringBuilder;


public scala.xml.NamespaceBinding toXML$default$2();
  Code:
   Stack=1, Locals=1, Args_size=1
   0:	getstatic	#738; //Field scala/xml/TopScope$.MODULE$:Lscala/xml/TopScope$;
   3:	areturn
  LineNumberTable: 
   line 171: 0


public scala.collection.mutable.StringBuilder toXML$default$3();
  Code:
   Stack=2, Locals=1, Args_size=1
   0:	new	#55; //class scala/collection/mutable/StringBuilder
   3:	dup
   4:	invokespecial	#157; //Method scala/collection/mutable/StringBuilder."<init>":()V
   7:	areturn
  LineNumberTable: 
   line 172: 0


public boolean toXML$default$4();
  Code:
   Stack=1, Locals=1, Args_size=1
   0:	iconst_0
   1:	ireturn
  LineNumberTable: 
   line 173: 0


public boolean toXML$default$5();
  Code:
   Stack=1, Locals=1, Args_size=1
   0:	iconst_1
   1:	ireturn
  LineNumberTable: 
   line 174: 0


public boolean toXML$default$6();
  Code:
   Stack=1, Locals=1, Args_size=1
   0:	iconst_0
   1:	ireturn
  LineNumberTable: 
   line 175: 0


public boolean toXML$default$7();
  Code:
   Stack=1, Locals=1, Args_size=1
   0:	iconst_0
   1:	ireturn
  LineNumberTable: 
   line 176: 0


public scala.xml.NamespaceBinding sequenceToXML$default$2();
  Code:
   Stack=1, Locals=1, Args_size=1
   0:	getstatic	#738; //Field scala/xml/TopScope$.MODULE$:Lscala/xml/TopScope$;
   3:	areturn
  LineNumberTable: 
   line 204: 0


public scala.collection.mutable.StringBuilder sequenceToXML$default$3();
  Code:
   Stack=2, Locals=1, Args_size=1
   0:	new	#55; //class scala/collection/mutable/StringBuilder
   3:	dup
   4:	invokespecial	#157; //Method scala/collection/mutable/StringBuilder."<init>":()V
   7:	areturn
  LineNumberTable: 
   line 205: 0


public boolean sequenceToXML$default$4();
  Code:
   Stack=1, Locals=1, Args_size=1
   0:	iconst_0
   1:	ireturn
  LineNumberTable: 
   line 206: 0


public boolean checkPubID(java.lang.String);
  Code:
   Stack=2, Locals=2, Args_size=2
   0:	aload_0
   1:	aload_1
   2:	invokestatic	#752; //Method scala/xml/parsing/TokenTests$class.checkPubID:(Lscala/xml/parsing/TokenTests;Ljava/lang/String;)Z
   5:	ireturn
  LineNumberTable: 
   line 24: 0

  LocalVariableTable: 
   Start  Length  Slot  Name   Signature
   0      6      0    this       Lscala/xml/Utility$;
   0      6      1    s       Ljava/lang/String;


public boolean checkSysID(java.lang.String);
  Code:
   Stack=2, Locals=2, Args_size=2
   0:	aload_0
   1:	aload_1
   2:	invokestatic	#755; //Method scala/xml/parsing/TokenTests$class.checkSysID:(Lscala/xml/parsing/TokenTests;Ljava/lang/String;)Z
   5:	ireturn
  LineNumberTable: 
   line 24: 0

  LocalVariableTable: 
   Start  Length  Slot  Name   Signature
   0      6      0    this       Lscala/xml/Utility$;
   0      6      1    s       Ljava/lang/String;


public boolean isValidIANAEncoding(scala.collection.Seq);
  Code:
   Stack=2, Locals=2, Args_size=2
   0:	aload_0
   1:	aload_1
   2:	invokestatic	#760; //Method scala/xml/parsing/TokenTests$class.isValidIANAEncoding:(Lscala/xml/parsing/TokenTests;Lscala/collection/Seq;)Z
   5:	ireturn
  LineNumberTable: 
   line 24: 0

  LocalVariableTable: 
   Start  Length  Slot  Name   Signature
   0      6      0    this       Lscala/xml/Utility$;
   0      6      1    ianaEncoding       Lscala/collection/Seq;


public boolean isPubIDChar(char);
  Code:
   Stack=2, Locals=2, Args_size=2
   0:	aload_0
   1:	iload_1
   2:	invokestatic	#765; //Method scala/xml/parsing/TokenTests$class.isPubIDChar:(Lscala/xml/parsing/TokenTests;C)Z
   5:	ireturn
  LineNumberTable: 
   line 24: 0

  LocalVariableTable: 
   Start  Length  Slot  Name   Signature
   0      6      0    this       Lscala/xml/Utility$;
   0      6      1    ch       C


public boolean isName(java.lang.String);
  Code:
   Stack=2, Locals=2, Args_size=2
   0:	aload_0
   1:	aload_1
   2:	invokestatic	#768; //Method scala/xml/parsing/TokenTests$class.isName:(Lscala/xml/parsing/TokenTests;Ljava/lang/String;)Z
   5:	ireturn
  LineNumberTable: 
   line 24: 0

  LocalVariableTable: 
   Start  Length  Slot  Name   Signature
   0      6      0    this       Lscala/xml/Utility$;
   0      6      1    s       Ljava/lang/String;


public boolean isNameStart(char);
  Code:
   Stack=2, Locals=2, Args_size=2
   0:	aload_0
   1:	iload_1
   2:	invokestatic	#770; //Method scala/xml/parsing/TokenTests$class.isNameStart:(Lscala/xml/parsing/TokenTests;C)Z
   5:	ireturn
  LineNumberTable: 
   line 24: 0

  LocalVariableTable: 
   Start  Length  Slot  Name   Signature
   0      6      0    this       Lscala/xml/Utility$;
   0      6      1    ch       C


public boolean isNameChar(char);
  Code:
   Stack=2, Locals=2, Args_size=2
   0:	aload_0
   1:	iload_1
   2:	invokestatic	#773; //Method scala/xml/parsing/TokenTests$class.isNameChar:(Lscala/xml/parsing/TokenTests;C)Z
   5:	ireturn
  LineNumberTable: 
   line 24: 0

  LocalVariableTable: 
   Start  Length  Slot  Name   Signature
   0      6      0    this       Lscala/xml/Utility$;
   0      6      1    ch       C


public boolean isAlphaDigit(char);
  Code:
   Stack=2, Locals=2, Args_size=2
   0:	aload_0
   1:	iload_1
   2:	invokestatic	#776; //Method scala/xml/parsing/TokenTests$class.isAlphaDigit:(Lscala/xml/parsing/TokenTests;C)Z
   5:	ireturn
  LineNumberTable: 
   line 24: 0

  LocalVariableTable: 
   Start  Length  Slot  Name   Signature
   0      6      0    this       Lscala/xml/Utility$;
   0      6      1    c       C


public boolean isAlpha(char);
  Code:
   Stack=2, Locals=2, Args_size=2
   0:	aload_0
   1:	iload_1
   2:	invokestatic	#779; //Method scala/xml/parsing/TokenTests$class.isAlpha:(Lscala/xml/parsing/TokenTests;C)Z
   5:	ireturn
  LineNumberTable: 
   line 24: 0

  LocalVariableTable: 
   Start  Length  Slot  Name   Signature
   0      6      0    this       Lscala/xml/Utility$;
   0      6      1    c       C


public final boolean isSpace(scala.collection.Seq);
  Code:
   Stack=2, Locals=2, Args_size=2
   0:	aload_0
   1:	aload_1
   2:	invokestatic	#782; //Method scala/xml/parsing/TokenTests$class.isSpace:(Lscala/xml/parsing/TokenTests;Lscala/collection/Seq;)Z
   5:	ireturn
  LineNumberTable: 
   line 24: 0

  LocalVariableTable: 
   Start  Length  Slot  Name   Signature
   0      6      0    this       Lscala/xml/Utility$;
   0      6      1    cs       Lscala/collection/Seq;


public final boolean isSpace(char);
  Code:
   Stack=2, Locals=2, Args_size=2
   0:	aload_0
   1:	iload_1
   2:	invokestatic	#785; //Method scala/xml/parsing/TokenTests$class.isSpace:(Lscala/xml/parsing/TokenTests;C)Z
   5:	ireturn
  LineNumberTable: 
   line 24: 0

  LocalVariableTable: 
   Start  Length  Slot  Name   Signature
   0      6      0    this       Lscala/xml/Utility$;
   0      6      1    ch       C


}

