Compiled from "Utility.scala"
public final class scala.xml.Utility$Escapes$ extends java.lang.Object implements scala.ScalaObject
  SourceFile: "Utility.scala"
  Scala: length = 0x
   
  InnerClass: 
   public final ArrowAssoc=class scala/Predef$ArrowAssoc of class scala/Predef
   public final $anonfun$3=class scala/xml/Utility$Escapes$$anonfun$3 of class scala/xml/Utility$Escapes$
  minor version: 0
  major version: 49
  Constant pool:
Asciz	SourceFile;
Asciz	Utility.scala;
Asciz	MODULE$;
Asciz	Lscala/xml/Utility$Escapes$;;
Asciz	<clinit>;
Asciz	()V;
Asciz	Code;
Asciz	scala/xml/Utility$Escapes$;
class	scala/xml/Utility$Escapes$
Asciz	<init>;
NameAndType	"<init>":()V
Method	scala/xml/Utility$Escapes$."<init>":()V
Asciz	pairs;
Asciz	Lscala/collection/immutable/Map;;
Asciz	Lscala/collection/immutable/Map<Ljava/lang/String;Ljava/lang/Character;>;;
Asciz	Signature;
Asciz	escMap;
Asciz	Lscala/collection/immutable/Map<Ljava/lang/Character;Ljava/lang/String;>;;
Asciz	unescMap;
Asciz	()Lscala/collection/immutable/Map;;
Asciz	LineNumberTable;
NameAndType	pairs:Lscala/collection/immutable/Map;
Field	scala/xml/Utility$Escapes$.pairs:Lscala/collection/immutable/Map;
Asciz	()Lscala/collection/immutable/Map<Ljava/lang/String;Ljava/lang/Character;>;;
NameAndType	escMap:Lscala/collection/immutable/Map;
Field	scala/xml/Utility$Escapes$.escMap:Lscala/collection/immutable/Map;
Asciz	()Lscala/collection/immutable/Map<Ljava/lang/Character;Ljava/lang/String;>;;
NameAndType	unescMap:Lscala/collection/immutable/Map;
Field	scala/xml/Utility$Escapes$.unescMap:Lscala/collection/immutable/Map;
Asciz	java/lang/Object;
class	java/lang/Object
Method	java/lang/Object."<init>":()V
NameAndType	MODULE$:Lscala/xml/Utility$Escapes$;
Field	scala/xml/Utility$Escapes$.MODULE$:Lscala/xml/Utility$Escapes$;
Asciz	scala/Predef$;
class	scala/Predef$
Asciz	Lscala/Predef$;;
NameAndType	MODULE$:Lscala/Predef$;
Field	scala/Predef$.MODULE$:Lscala/Predef$;
Asciz	Map;
Asciz	()Lscala/collection/immutable/Map$;;
NameAndType	Map:()Lscala/collection/immutable/Map$;
Method	scala/Predef$.Map:()Lscala/collection/immutable/Map$;
Asciz	scala/Tuple2;
class	scala/Tuple2
Asciz	lt;
String	lt
Asciz	any2ArrowAssoc;
Asciz	(Ljava/lang/Object;)Lscala/Predef$ArrowAssoc;;
NameAndType	any2ArrowAssoc:(Ljava/lang/Object;)Lscala/Predef$ArrowAssoc;
Method	scala/Predef$.any2ArrowAssoc:(Ljava/lang/Object;)Lscala/Predef$ArrowAssoc;
int	60;
Asciz	scala/runtime/BoxesRunTime;
class	scala/runtime/BoxesRunTime
Asciz	boxToCharacter;
Asciz	(C)Ljava/lang/Character;;
NameAndType	boxToCharacter:(C)Ljava/lang/Character;
Method	scala/runtime/BoxesRunTime.boxToCharacter:(C)Ljava/lang/Character;
Asciz	scala/Predef$ArrowAssoc;
class	scala/Predef$ArrowAssoc
Asciz	$minus$greater;
Asciz	(Ljava/lang/Object;)Lscala/Tuple2;;
NameAndType	$minus$greater:(Ljava/lang/Object;)Lscala/Tuple2;
Method	scala/Predef$ArrowAssoc.$minus$greater:(Ljava/lang/Object;)Lscala/Tuple2;
Asciz	gt;
String	gt
int	62;
Asciz	amp;
String	amp
int	38;
Asciz	quot;
String	quot
int	34;
Asciz	[Ljava/lang/Object;;
class	"[Ljava/lang/Object;"
Asciz	wrapRefArray;
Asciz	([Ljava/lang/Object;)Lscala/collection/mutable/WrappedArray;;
NameAndType	wrapRefArray:([Ljava/lang/Object;)Lscala/collection/mutable/WrappedArray;
Method	scala/Predef$.wrapRefArray:([Ljava/lang/Object;)Lscala/collection/mutable/WrappedArray;
Asciz	scala/collection/immutable/Map$;
class	scala/collection/immutable/Map$
Asciz	apply;
Asciz	(Lscala/collection/Seq;)Lscala/collection/Map;;
NameAndType	apply:(Lscala/collection/Seq;)Lscala/collection/Map;
Method	scala/collection/immutable/Map$.apply:(Lscala/collection/Seq;)Lscala/collection/Map;
Asciz	scala/collection/immutable/Map;
class	scala/collection/immutable/Map
NameAndType	pairs:()Lscala/collection/immutable/Map;
Method	scala/xml/Utility$Escapes$.pairs:()Lscala/collection/immutable/Map;
Asciz	scala/xml/Utility$Escapes$$anonfun$3;
class	scala/xml/Utility$Escapes$$anonfun$3
Method	scala/xml/Utility$Escapes$$anonfun$3."<init>":()V
Asciz	Lscala/collection/immutable/Map$;;
NameAndType	MODULE$:Lscala/collection/immutable/Map$;
Field	scala/collection/immutable/Map$.MODULE$:Lscala/collection/immutable/Map$;
Asciz	canBuildFrom;
Asciz	()Lscala/collection/generic/CanBuildFrom;;
NameAndType	canBuildFrom:()Lscala/collection/generic/CanBuildFrom;
Method	scala/collection/immutable/Map$.canBuildFrom:()Lscala/collection/generic/CanBuildFrom;
Asciz	scala/collection/TraversableLike;
class	scala/collection/TraversableLike
Asciz	map;
Asciz	(Lscala/Function1;Lscala/collection/generic/CanBuildFrom;)Ljava/lang/Object;;
NameAndType	map:(Lscala/Function1;Lscala/collection/generic/CanBuildFrom;)Ljava/lang/Object;
InterfaceMethod	scala/collection/TraversableLike.map:(Lscala/Function1;Lscala/collection/generic/CanBuildFrom;)Ljava/lang/Object;
Asciz	apos;
String	apos
int	39;
Asciz	scala/collection/immutable/MapLike;
class	scala/collection/immutable/MapLike
Asciz	$plus$plus;
Asciz	(Lscala/collection/TraversableOnce;)Lscala/collection/immutable/Map;;
NameAndType	$plus$plus:(Lscala/collection/TraversableOnce;)Lscala/collection/immutable/Map;
InterfaceMethod	scala/collection/immutable/MapLike.$plus$plus:(Lscala/collection/TraversableOnce;)Lscala/collection/immutable/Map;
Asciz	Scala;
Asciz	InnerClasses;
Asciz	scala/Predef;
class	scala/Predef
Asciz	ArrowAssoc;
Asciz	$anonfun$3;
Asciz	scala/ScalaObject;
class	scala/ScalaObject

{
public static final scala.xml.Utility$Escapes$ MODULE$;
  Signature: Lscala/xml/Utility$Escapes$;

private final scala.collection.immutable.Map pairs;
  Signature: Lscala/collection/immutable/Map;
  Signature: length = 0x2
   00 0F 

private final scala.collection.immutable.Map escMap;
  Signature: Lscala/collection/immutable/Map;
  Signature: length = 0x2
   00 12 

private final scala.collection.immutable.Map unescMap;
  Signature: Lscala/collection/immutable/Map;
  Signature: length = 0x2
   00 0F 

public static {};
  Signature: ()V
  Code:
   Stack=1, Locals=0, Args_size=0
	new	class scala/xml/Utility$Escapes$
	invokespecial	Method "<init>":()V
	return
  Labels:

public scala.collection.immutable.Map pairs();
  Signature: ()Lscala/collection/immutable/Map;
  Code:
   Stack=1, Locals=1, Args_size=1
	aload_0
	getfield	Field pairs:Lscala/collection/immutable/Map;
	areturn
  Labels:
  Signature: length = 0x2
   00 18 

public scala.collection.immutable.Map escMap();
  Signature: ()Lscala/collection/immutable/Map;
  Code:
   Stack=1, Locals=1, Args_size=1
	aload_0
	getfield	Field escMap:Lscala/collection/immutable/Map;
	areturn
  Labels:
  Signature: length = 0x2
   00 1B 

public scala.collection.immutable.Map unescMap();
  Signature: ()Lscala/collection/immutable/Map;
  Code:
   Stack=1, Locals=1, Args_size=1
	aload_0
	getfield	Field unescMap:Lscala/collection/immutable/Map;
	areturn
  Labels:
  Signature: length = 0x2
   00 18 

public scala.xml.Utility$Escapes$();
  Signature: ()V
  Code:
   Stack=9, Locals=6, Args_size=1
	aload_0
	invokespecial	Method java/lang/Object."<init>":()V
	aload_0
	putstatic	Field MODULE$:Lscala/xml/Utility$Escapes$;
	aload_0
	getstatic	Field scala/Predef$.MODULE$:Lscala/Predef$;
	invokevirtual	Method scala/Predef$.Map:()Lscala/collection/immutable/Map$;
	getstatic	Field scala/Predef$.MODULE$:Lscala/Predef$;
	iconst_4
	anewarray	class scala/Tuple2
	dup
	iconst_0
	getstatic	Field scala/Predef$.MODULE$:Lscala/Predef$;
	ldc	String lt
	invokevirtual	Method scala/Predef$.any2ArrowAssoc:(Ljava/lang/Object;)Lscala/Predef$ArrowAssoc;
	ldc	int 60
	istore_1
	iload_1
	invokestatic	Method scala/runtime/BoxesRunTime.boxToCharacter:(C)Ljava/lang/Character;
	invokevirtual	Method scala/Predef$ArrowAssoc.$minus$greater:(Ljava/lang/Object;)Lscala/Tuple2;
	aastore
	dup
	iconst_1
	getstatic	Field scala/Predef$.MODULE$:Lscala/Predef$;
	ldc	String gt
	invokevirtual	Method scala/Predef$.any2ArrowAssoc:(Ljava/lang/Object;)Lscala/Predef$ArrowAssoc;
	ldc	int 62
	istore_2
	iload_2
	invokestatic	Method scala/runtime/BoxesRunTime.boxToCharacter:(C)Ljava/lang/Character;
	invokevirtual	Method scala/Predef$ArrowAssoc.$minus$greater:(Ljava/lang/Object;)Lscala/Tuple2;
	aastore
	dup
	iconst_2
	getstatic	Field scala/Predef$.MODULE$:Lscala/Predef$;
	ldc	String amp
	invokevirtual	Method scala/Predef$.any2ArrowAssoc:(Ljava/lang/Object;)Lscala/Predef$ArrowAssoc;
	ldc	int 38
	istore_3
	iload_3
	invokestatic	Method scala/runtime/BoxesRunTime.boxToCharacter:(C)Ljava/lang/Character;
	invokevirtual	Method scala/Predef$ArrowAssoc.$minus$greater:(Ljava/lang/Object;)Lscala/Tuple2;
	aastore
	dup
	iconst_3
	getstatic	Field scala/Predef$.MODULE$:Lscala/Predef$;
	ldc	String quot
	invokevirtual	Method scala/Predef$.any2ArrowAssoc:(Ljava/lang/Object;)Lscala/Predef$ArrowAssoc;
	ldc	int 34
	istore	4
	iload	4
	invokestatic	Method scala/runtime/BoxesRunTime.boxToCharacter:(C)Ljava/lang/Character;
	invokevirtual	Method scala/Predef$ArrowAssoc.$minus$greater:(Ljava/lang/Object;)Lscala/Tuple2;
	aastore
	checkcast	class "[Ljava/lang/Object;"
	invokevirtual	Method scala/Predef$.wrapRefArray:([Ljava/lang/Object;)Lscala/collection/mutable/WrappedArray;
	invokevirtual	Method scala/collection/immutable/Map$.apply:(Lscala/collection/Seq;)Lscala/collection/Map;
	checkcast	class scala/collection/immutable/Map
	putfield	Field pairs:Lscala/collection/immutable/Map;
	aload_0
	aload_0
	invokevirtual	Method pairs:()Lscala/collection/immutable/Map;
	new	class scala/xml/Utility$Escapes$$anonfun$3
	dup
	invokespecial	Method scala/xml/Utility$Escapes$$anonfun$3."<init>":()V
	getstatic	Field scala/collection/immutable/Map$.MODULE$:Lscala/collection/immutable/Map$;
	invokevirtual	Method scala/collection/immutable/Map$.canBuildFrom:()Lscala/collection/generic/CanBuildFrom;
	invokeinterface	InterfaceMethod scala/collection/TraversableLike.map:(Lscala/Function1;Lscala/collection/generic/CanBuildFrom;)Ljava/lang/Object;
	checkcast	class scala/collection/immutable/Map
	putfield	Field escMap:Lscala/collection/immutable/Map;
	aload_0
	aload_0
	invokevirtual	Method pairs:()Lscala/collection/immutable/Map;
	getstatic	Field scala/Predef$.MODULE$:Lscala/Predef$;
	invokevirtual	Method scala/Predef$.Map:()Lscala/collection/immutable/Map$;
	getstatic	Field scala/Predef$.MODULE$:Lscala/Predef$;
	iconst_1
	anewarray	class scala/Tuple2
	dup
	iconst_0
	getstatic	Field scala/Predef$.MODULE$:Lscala/Predef$;
	ldc	String apos
	invokevirtual	Method scala/Predef$.any2ArrowAssoc:(Ljava/lang/Object;)Lscala/Predef$ArrowAssoc;
	ldc	int 39
	istore	5
	iload	5
	invokestatic	Method scala/runtime/BoxesRunTime.boxToCharacter:(C)Ljava/lang/Character;
	invokevirtual	Method scala/Predef$ArrowAssoc.$minus$greater:(Ljava/lang/Object;)Lscala/Tuple2;
	aastore
	checkcast	class "[Ljava/lang/Object;"
	invokevirtual	Method scala/Predef$.wrapRefArray:([Ljava/lang/Object;)Lscala/collection/mutable/WrappedArray;
	invokevirtual	Method scala/collection/immutable/Map$.apply:(Lscala/collection/Seq;)Lscala/collection/Map;
	invokeinterface	InterfaceMethod scala/collection/immutable/MapLike.$plus$plus:(Lscala/collection/TraversableOnce;)Lscala/collection/immutable/Map;
	putfield	Field unescMap:Lscala/collection/immutable/Map;
	return
  Labels:

}

