Compiled from "Utility.scala"
public final class scala.xml.Utility$$anonfun$collectNamespaces$3 extends scala.runtime.AbstractFunction1 implements java.io.Serializable
  SourceFile: "Utility.scala"
  Scala: length = 0x
   
  InnerClass: 
   public final $anonfun$collectNamespaces$3=class scala/xml/Utility$$anonfun$collectNamespaces$3 of class scala/xml/Utility
  minor version: 0
  major version: 49
  Constant pool:
Asciz	SourceFile;
Asciz	Utility.scala;
Asciz	<clinit>;
Asciz	()V;
Asciz	Code;
Asciz	serialVersionUID;
Asciz	J;
Asciz	scala/xml/Utility$$anonfun$collectNamespaces$3;
class	scala/xml/Utility$$anonfun$collectNamespaces$3
NameAndType	serialVersionUID:J
Field	scala/xml/Utility$$anonfun$collectNamespaces$3.serialVersionUID:J
Asciz	set$1;
Asciz	Lscala/collection/mutable/Set;;
Asciz	apply;
Asciz	(Lscala/xml/Node;)V;
Asciz	scala/xml/Utility$;
class	scala/xml/Utility$
Asciz	MODULE$;
Asciz	Lscala/xml/Utility$;;
NameAndType	MODULE$:Lscala/xml/Utility$;
Field	scala/xml/Utility$.MODULE$:Lscala/xml/Utility$;
Asciz	LineNumberTable;
NameAndType	set$1:Lscala/collection/mutable/Set;
Field	scala/xml/Utility$$anonfun$collectNamespaces$3.set$1:Lscala/collection/mutable/Set;
Asciz	collectNamespaces;
Asciz	(Lscala/xml/Node;Lscala/collection/mutable/Set;)V;
NameAndType	collectNamespaces:(Lscala/xml/Node;Lscala/collection/mutable/Set;)V
Method	scala/xml/Utility$.collectNamespaces:(Lscala/xml/Node;Lscala/collection/mutable/Set;)V
Asciz	this;
Asciz	Lscala/xml/Utility$$anonfun$collectNamespaces$3;;
Asciz	i;
Asciz	Lscala/xml/Node;;
Asciz	LocalVariableTable;
Asciz	(Ljava/lang/Object;)Ljava/lang/Object;;
Asciz	scala/xml/Node;
class	scala/xml/Node
NameAndType	apply:(Lscala/xml/Node;)V
Method	scala/xml/Utility$$anonfun$collectNamespaces$3.apply:(Lscala/xml/Node;)V
Asciz	scala/runtime/BoxedUnit;
class	scala/runtime/BoxedUnit
Asciz	UNIT;
Asciz	Lscala/runtime/BoxedUnit;;
NameAndType	UNIT:Lscala/runtime/BoxedUnit;
Field	scala/runtime/BoxedUnit.UNIT:Lscala/runtime/BoxedUnit;
Asciz	v1;
Asciz	Ljava/lang/Object;;
Asciz	<init>;
Asciz	(Lscala/collection/mutable/Set;)V;
Asciz	scala/runtime/AbstractFunction1;
class	scala/runtime/AbstractFunction1
NameAndType	"<init>":()V
Method	scala/runtime/AbstractFunction1."<init>":()V
Asciz	Scala;
Asciz	InnerClasses;
Asciz	scala/xml/Utility;
class	scala/xml/Utility
Asciz	$anonfun$collectNamespaces$3;
Asciz	java/io/Serializable;
class	java/io/Serializable

{
public static final long serialVersionUID;
  Signature: J

public final scala.collection.mutable.Set set$1;
  Signature: Lscala/collection/mutable/Set;

public static {};
  Signature: ()V
  Code:
   Stack=2, Locals=0, Args_size=0
	lconst_0
	putstatic	Field serialVersionUID:J
	return
  Labels:

public final void apply(scala.xml.Node);
  Signature: (Lscala/xml/Node;)V
  Code:
   Stack=3, Locals=2, Args_size=2
	getstatic	Field scala/xml/Utility$.MODULE$:Lscala/xml/Utility$;
	aload_1
	aload_0
	getfield	Field set$1:Lscala/collection/mutable/Set;
	invokevirtual	Method scala/xml/Utility$.collectNamespaces:(Lscala/xml/Node;Lscala/collection/mutable/Set;)V
	return
  Labels:
  LocalVariableTable: 
   Start  Length  Slot  Name   Signature
   0      12      0    this       Lscala/xml/Utility$$anonfun$collectNamespaces$3;
   0      12      1    i       Lscala/xml/Node;


public final java.lang.Object apply(java.lang.Object);
  Signature: (Ljava/lang/Object;)Ljava/lang/Object;
  Code:
   Stack=2, Locals=2, Args_size=2
	aload_0
	aload_1
	checkcast	class scala/xml/Node
	invokevirtual	Method apply:(Lscala/xml/Node;)V
	getstatic	Field scala/runtime/BoxedUnit.UNIT:Lscala/runtime/BoxedUnit;
	areturn
  Labels:
  LocalVariableTable: 
   Start  Length  Slot  Name   Signature
   0      12      0    this       Lscala/xml/Utility$$anonfun$collectNamespaces$3;
   0      12      1    v1       Ljava/lang/Object;


public scala.xml.Utility$$anonfun$collectNamespaces$3(scala.collection.mutable.Set);
  Signature: (Lscala/collection/mutable/Set;)V
  Code:
   Stack=2, Locals=2, Args_size=2
	aload_0
	aload_1
	putfield	Field set$1:Lscala/collection/mutable/Set;
	aload_0
	invokespecial	Method scala/runtime/AbstractFunction1."<init>":()V
	return
  Labels:

}

