Compiled from "Utility.scala"
public final class scala.xml.Utility extends java.lang.Object
  SourceFile: "Utility.scala"
  ScalaSig: length = 0x91E
   05 00 FFFFFF82 1F 07 05 01 02 FFFFFF88 02 07 01 07 55 74 69
   6C 69 74 79 0A 02 03 04 01 03 78 6D 6C 0A 01 05
   01 05 73 63 61 6C 61 03 00 10 02 08 09 0D 01 02
   06 08 0A 02 FFFFFF84 FFFFFF80 FFFFFF80 FFFFFF88 02 0B 02 07 55 74 69 6C
   69 74 79 13 04 09 0C 14 1A 10 02 0D 12 0D 01 0E
   0A 02 0F 10 01 04 6C 61 6E 67 0A 01 11 01 04 6A
   61 76 61 09 02 13 0E 02 06 4F 62 6A 65 63 74 10
   02 15 18 0D 01 16 0A 02 17 02 01 07 70 61 72 73
   69 6E 67 09 02 19 16 02 0A 54 6F 6B 65 6E 54 65
   73 74 73 10 02 1B 1C 0D 01 04 09 02 1D 04 02 0B
   53 63 61 6C 61 4F 62 6A 65 63 74 08 05 1F 09 FFFFFF84
   00 20 01 06 3C 69 6E 69 74 3E 14 01 07 08 05 22
   09 FFFFFF84 01 23 01 12 69 6D 70 6C 69 63 69 74 53 62
   54 6F 53 74 72 69 6E 67 14 02 24 2B 10 02 25 28
   0E 02 1B 26 09 02 27 04 01 06 50 72 65 64 65 66
   09 02 29 2A 02 06 53 74 72 69 6E 67 0A 02 27 04
   08 05 2C 21 FFFFFFC0 00 2D 01 02 73 62 10 02 2E 33 0D
   01 2F 0A 02 30 31 01 07 6D 75 74 61 62 6C 65 0A
   02 32 04 01 0A 63 6F 6C 6C 65 63 74 69 6F 6E 09
   02 34 2F 02 0D 53 74 72 69 6E 67 42 75 69 6C 64
   65 72 08 06 36 09 FFFFFF84 00 02 37 01 0A 73 62 54 6F
   53 74 72 69 6E 67 14 02 24 38 08 05 39 35 FFFFFFC0 00
   3A 01 01 66 10 04 1B 3B 2D 3D 09 02 3C 04 02 09
   46 75 6E 63 74 69 6F 6E 31 10 02 1B 3E 09 02 3F
   04 02 04 55 6E 69 74 08 06 41 09 FFFFFF84 00 02 42 01
   10 69 73 41 74 6F 6D 41 6E 64 4E 6F 74 54 65 78
   74 14 02 43 46 10 02 1B 44 09 02 45 04 02 07 42
   6F 6F 6C 65 61 6E 08 05 47 40 FFFFFFC0 00 48 01 01 78
   10 02 08 49 09 02 4A 02 02 04 4E 6F 64 65 08 05
   4C 09 FFFFFF84 00 4D 01 04 74 72 69 6D 14 02 48 4E 08
   05 47 4B FFFFFFC0 00 48 08 05 50 09 FFFFFF84 00 51 01 0A 74
   72 69 6D 50 72 6F 70 65 72 14 02 52 56 10 03 53
   54 48 0D 01 31 09 02 55 31 02 03 53 65 71 08 05
   47 4F FFFFFFC0 00 48 08 05 58 09 FFFFFF84 00 59 01 04 73 6F
   72 74 14 02 5A 5D 10 02 08 5B 09 02 5C 02 02 08
   4D 65 74 61 44 61 74 61 08 05 5E 57 FFFFFFC0 00 5A 01
   02 6D 64 08 05 58 09 FFFFFF84 00 60 14 02 48 61 08 05
   62 5F FFFFFFC0 00 48 01 01 6E 08 05 64 09 FFFFFF84 02 65 01
   06 65 73 63 61 70 65 14 02 24 66 08 05 67 63 FFFFFFC0
   00 24 01 04 74 65 78 74 07 05 69 09 FFFFFF88 02 6A 01
   07 45 73 63 61 70 65 73 10 02 6B 6C 0D 01 09 06
   08 6D 09 FFFFFF84 FFFFFF80 FFFFFF80 FFFFFF88 02 6E 02 07 45 73 63 61 70
   65 73 13 03 6C 0C 1A 08 05 1F 6C FFFFFF84 00 70 14 01
   6A 08 07 72 6C FFFFFFC2 FFFFFF80 FFFFFF84 00 73 01 05 70 61 69 72
   73 15 01 74 10 04 75 78 7A 7C 0D 01 76 0A 02 77
   31 01 09 69 6D 6D 75 74 61 62 6C 65 09 02 79 76
   02 03 4D 61 70 10 02 0D 7B 09 02 29 0E 10 02 1B
   7D 09 02 7E 04 02 04 43 68 61 72 08 07 FFFFFF81 00 6C
   FFFFFFA0 FFFFFF80 04 74 01 06 70 61 69 72 73 20 08 09 FFFFFF81 02
   6C FFFFFFC2 FFFFFF80 FFFFFF84 00 FFFFFF81 03 01 06 65 73 63 4D 61 70 15
   02 FFFFFF81 04 10 04 75 78 7C 24 08 08 FFFFFF81 06 6C FFFFFFA0 FFFFFF80
   04 FFFFFF81 04 01 07 65 73 63 4D 61 70 20 08 08 FFFFFF81 08
   6C FFFFFFC2 FFFFFF80 FFFFFF84 00 73 01 08 75 6E 65 73 63 4D 61 70
   08 07 FFFFFF81 0A 6C FFFFFFA0 FFFFFF80 04 74 01 09 75 6E 65 73 63
   4D 61 70 20 08 06 64 09 FFFFFF84 02 FFFFFF81 0C 14 05 2D FFFFFF81
   0D FFFFFF81 0E 08 06 67 FFFFFF81 0B FFFFFFC0 00 24 08 07 FFFFFF81 0F FFFFFF81
   0B FFFFFFC0 00 2D 01 01 73 08 07 FFFFFF81 11 09 FFFFFF84 02 FFFFFF81 12
   01 08 75 6E 65 73 63 61 70 65 14 05 2D FFFFFF81 13 FFFFFF81
   15 08 07 FFFFFF81 14 FFFFFF81 10 FFFFFFC0 00 24 01 03 72 65 66 08
   07 FFFFFF81 0F FFFFFF81 10 FFFFFFC0 00 2D 08 07 FFFFFF81 17 09 FFFFFF84 00 FFFFFF81
   18 01 11 63 6F 6C 6C 65 63 74 4E 61 6D 65 73 70
   61 63 65 73 14 04 FFFFFF81 19 FFFFFF81 1C 10 04 2E FFFFFF81 1A 24
   09 03 FFFFFF81 1B 2F 02 03 53 65 74 08 07 FFFFFF81 1D FFFFFF81 16
   FFFFFFC0 00 52 01 05 6E 6F 64 65 73 08 07 FFFFFF81 17 09 FFFFFF84
   00 FFFFFF81 1F 14 05 3D FFFFFF81 20 FFFFFF81 21 08 06 62 FFFFFF81 1E FFFFFFC0
   00 48 08 08 FFFFFF81 22 FFFFFF81 1E FFFFFFC0 00 FFFFFF81 19 01 03 73 65
   74 08 07 FFFFFF81 24 09 FFFFFF84 00 FFFFFF81 25 01 05 74 6F 58 4D
   4C 14 0F 2D FFFFFF81 26 FFFFFF81 27 FFFFFF81 39 FFFFFF81 3E FFFFFF81 44 FFFFFF81 48
   FFFFFF81 4C 08 06 47 FFFFFF81 23 FFFFFFC0 00 48 08 0C FFFFFF81 2C FFFFFF81 28
   FFFFFF81 23 FFFFFF90 FFFFFF80 FFFFFFC0 00 FFFFFF81 29 01 06 70 73 63 6F 70 65
   10 03 08 FFFFFF81 2A 09 03 FFFFFF81 2B 02 02 10 4E 61 6D 65
   73 70 61 63 65 42 69 6E 64 69 6E 67 08 09 FFFFFF81 2D
   09 FFFFFF91 FFFFFF80 FFFFFF84 00 FFFFFF81 2E 01 0F 74 6F 58 4D 4C 24 64
   65 66 61 75 6C 74 24 32 15 02 FFFFFF81 2F 2A 04 FFFFFF81 29
   FFFFFF81 30 2B 02 FFFFFF81 31 10 04 FFFFFF81 32 FFFFFF81 37 0D 02 FFFFFF81 33
   0A 04 FFFFFF81 34 FFFFFF81 35 01 09 75 6E 63 68 65 63 6B 65
   64 0A 03 FFFFFF81 36 04 01 0A 61 6E 6E 6F 74 61 74 69
   6F 6E 09 04 FFFFFF81 38 FFFFFF81 33 02 11 75 6E 63 68 65 63
   6B 65 64 56 61 72 69 61 6E 63 65 08 0A FFFFFF81 3A 2C
   FFFFFF81 23 FFFFFF90 FFFFFF80 FFFFFFC0 00 2D 08 09 FFFFFF81 3B 09 FFFFFF91 FFFFFF80 FFFFFF84 00
   FFFFFF81 3C 01 0F 74 6F 58 4D 4C 24 64 65 66 61 75 6C
   74 24 33 15 02 FFFFFF81 3D 2A 03 2D FFFFFF81 30 08 0B FFFFFF81 40
   FFFFFF81 3F FFFFFF81 23 FFFFFF90 FFFFFF80 FFFFFFC0 00 43 01 0D 73 74 72 69 70
   43 6F 6D 6D 65 6E 74 73 08 09 FFFFFF81 41 09 FFFFFF91 FFFFFF80 FFFFFF84
   00 FFFFFF81 42 01 0F 74 6F 58 4D 4C 24 64 65 66 61 75
   6C 74 24 34 15 02 FFFFFF81 43 2A 03 43 FFFFFF81 30 08 0B FFFFFF81
   46 FFFFFF81 45 FFFFFF81 23 FFFFFF90 FFFFFF80 FFFFFFC0 00 43 01 0E 64 65 63 6F
   64 65 45 6E 74 69 74 69 65 73 08 09 FFFFFF81 47 09 FFFFFF91
   FFFFFF80 FFFFFF84 00 FFFFFF81 42 01 0F 74 6F 58 4D 4C 24 64 65 66
   61 75 6C 74 24 35 08 0B FFFFFF81 4A FFFFFF81 49 FFFFFF81 23 FFFFFF90 FFFFFF80
   FFFFFFC0 00 43 01 12 70 72 65 73 65 72 76 65 57 68 69
   74 65 73 70 61 63 65 08 09 FFFFFF81 4B 09 FFFFFF91 FFFFFF80 FFFFFF84 00
   FFFFFF81 42 01 0F 74 6F 58 4D 4C 24 64 65 66 61 75 6C
   74 24 36 08 0B FFFFFF81 4E FFFFFF81 4D FFFFFF81 23 FFFFFF90 FFFFFF80 FFFFFFC0 00 43
   01 0C 6D 69 6E 69 6D 69 7A 65 54 61 67 73 08 09
   FFFFFF81 4F 09 FFFFFF91 FFFFFF80 FFFFFF84 00 FFFFFF81 42 01 0F 74 6F 58 4D 4C
   24 64 65 66 61 75 6C 74 24 37 08 07 FFFFFF81 51 09 FFFFFF84
   00 FFFFFF81 52 01 0D 73 65 71 75 65 6E 63 65 54 6F 58
   4D 4C 14 09 3D FFFFFF81 53 FFFFFF81 55 FFFFFF81 58 FFFFFF81 5B 08 07 FFFFFF81
   54 FFFFFF81 50 FFFFFFC0 00 52 01 08 63 68 69 6C 64 72 65 6E
   08 0C FFFFFF81 56 FFFFFF81 28 FFFFFF81 50 FFFFFF90 FFFFFF80 FFFFFFC0 00 FFFFFF81 29 08 09
   FFFFFF81 57 09 FFFFFF91 FFFFFF80 FFFFFF84 00 FFFFFF81 2E 01 17 73 65 71 75 65
   6E 63 65 54 6F 58 4D 4C 24 64 65 66 61 75 6C 74
   24 32 08 0A FFFFFF81 59 2C FFFFFF81 50 FFFFFF90 FFFFFF80 FFFFFFC0 00 2D 08 09
   FFFFFF81 5A 09 FFFFFF91 FFFFFF80 FFFFFF84 00 FFFFFF81 3C 01 17 73 65 71 75 65
   6E 63 65 54 6F 58 4D 4C 24 64 65 66 61 75 6C 74
   24 33 08 0B FFFFFF81 5C FFFFFF81 3F FFFFFF81 50 FFFFFF90 FFFFFF80 FFFFFFC0 00 43 08
   09 FFFFFF81 5D 09 FFFFFF91 FFFFFF80 FFFFFF84 00 FFFFFF81 42 01 17 73 65 71 75
   65 6E 63 65 54 6F 58 4D 4C 24 64 65 66 61 75 6C
   74 24 34 08 07 FFFFFF81 5F 09 FFFFFF84 02 FFFFFF81 60 01 06 70 72
   65 66 69 78 14 04 FFFFFF81 61 FFFFFF81 64 10 04 1B FFFFFF81 62 24
   09 03 FFFFFF81 63 04 02 06 4F 70 74 69 6F 6E 08 07 FFFFFF81
   65 FFFFFF81 5E FFFFFFC0 00 24 01 04 6E 61 6D 65 08 07 FFFFFF81 67
   09 FFFFFF84 00 FFFFFF81 68 01 08 68 61 73 68 43 6F 64 65 14
   0C FFFFFF81 69 FFFFFF81 6C FFFFFF81 6E FFFFFF81 70 FFFFFF81 72 FFFFFF81 74 10 03 1B
   FFFFFF81 6A 09 03 FFFFFF81 6B 04 02 03 49 6E 74 08 07 FFFFFF81 6D
   FFFFFF81 66 FFFFFFC0 00 24 01 03 70 72 65 08 07 FFFFFF81 6F FFFFFF81 66
   FFFFFFC0 00 24 01 05 6C 61 62 65 6C 08 08 FFFFFF81 71 FFFFFF81 66
   FFFFFFC0 00 FFFFFF81 69 01 0E 61 74 74 72 69 62 48 61 73 68
   43 6F 64 65 08 08 FFFFFF81 73 FFFFFF81 66 FFFFFFC0 00 FFFFFF81 69 01 08
   73 63 70 65 48 61 73 68 08 07 FFFFFF81 54 FFFFFF81 66 FFFFFFC0 00
   52 08 07 FFFFFF81 76 09 FFFFFF84 00 FFFFFF81 77 01 0C 61 70 70 65
   6E 64 51 75 6F 74 65 64 14 03 24 FFFFFF81 78 08 07 FFFFFF81
   0F FFFFFF81 75 FFFFFFC0 00 24 08 07 FFFFFF81 76 09 FFFFFF84 00 FFFFFF81 7A 14
   05 2D FFFFFF81 7B FFFFFF81 7C 08 07 FFFFFF81 0F FFFFFF81 79 FFFFFFC0 00 24 08
   06 2C FFFFFF81 79 FFFFFFC0 00 2D 08 07 FFFFFF81 7E 09 FFFFFF84 00 FFFFFF81 7F
   01 13 61 70 70 65 6E 64 45 73 63 61 70 65 64 51
   75 6F 74 65 64 14 05 2D FFFFFF82 00 FFFFFF82 01 08 07 FFFFFF81 0F
   FFFFFF81 7D FFFFFFC0 00 24 08 06 2C FFFFFF81 7D FFFFFFC0 00 2D 08 07 FFFFFF82
   03 09 FFFFFF84 00 FFFFFF82 04 01 07 67 65 74 4E 61 6D 65 14
   05 24 FFFFFF82 05 FFFFFF82 06 08 07 FFFFFF81 0F FFFFFF82 02 FFFFFFC0 00 24 08
   08 FFFFFF82 07 FFFFFF82 02 FFFFFFC0 00 FFFFFF81 69 01 05 69 6E 64 65 78
   08 07 FFFFFF82 09 09 FFFFFF84 00 FFFFFF82 0A 01 13 63 68 65 63 6B
   41 74 74 72 69 62 75 74 65 56 61 6C 75 65 14 03
   24 FFFFFF82 0B 08 07 FFFFFF82 0C FFFFFF82 08 FFFFFFC0 00 24 01 05 76 61
   6C 75 65 08 07 FFFFFF82 0E 09 FFFFFF84 00 FFFFFF82 0F 01 13 70 61
   72 73 65 41 74 74 72 69 62 75 74 65 56 61 6C 75
   65 14 03 52 FFFFFF82 10 08 07 FFFFFF82 0C FFFFFF82 0D FFFFFFC0 00 24 08
   07 FFFFFF82 12 09 FFFFFF84 00 FFFFFF82 13 01 0C 70 61 72 73 65 43
   68 61 72 52 65 66 14 07 24 FFFFFF82 14 FFFFFF82 19 FFFFFF82 1C 08
   08 FFFFFF82 15 FFFFFF82 11 FFFFFFC0 00 FFFFFF82 16 01 02 63 68 10 04 1B
   FFFFFF82 17 7C 09 03 FFFFFF82 18 04 02 09 46 75 6E 63 74 69
   6F 6E 30 08 08 FFFFFF82 1A FFFFFF82 11 FFFFFFC0 00 FFFFFF82 1B 01 06 6E
   65 78 74 63 68 10 04 1B FFFFFF82 17 3D 08 08 FFFFFF82 1D FFFFFF82
   11 FFFFFFC0 00 FFFFFF82 1E 01 11 72 65 70 6F 72 74 53 79 6E
   74 61 78 45 72 72 6F 72 10 04 1B 3B 24 3D 
  InnerClass: 
   public final $anonfun$6=class scala/xml/Utility$$anonfun$6 of class scala/xml/Utility
   public final $anonfun$5=class scala/xml/Utility$$anonfun$5 of class scala/xml/Utility
   public final $anonfun$4=class scala/xml/Utility$$anonfun$4 of class scala/xml/Utility
   public final $anonfun$2=class scala/xml/Utility$$anonfun$2 of class scala/xml/Utility
   public final $anonfun$1=class scala/xml/Utility$$anonfun$1 of class scala/xml/Utility
   public final $anonfun$sort$1=class scala/xml/Utility$$anonfun$sort$1 of class scala/xml/Utility
   public final $anonfun$trim$1=class scala/xml/Utility$$anonfun$trim$1 of class scala/xml/Utility
   public final $anonfun$toXML$1=class scala/xml/Utility$$anonfun$toXML$1 of class scala/xml/Utility
   public final $anonfun$escape$2=class scala/xml/Utility$$anonfun$escape$2 of class scala/xml/Utility
   public final $anonfun$escape$1=class scala/xml/Utility$$anonfun$escape$1 of class scala/xml/Utility
   public final $anonfun$getName$1=class scala/xml/Utility$$anonfun$getName$1 of class scala/xml/Utility
   public final $anonfun$unescape$1=class scala/xml/Utility$$anonfun$unescape$1 of class scala/xml/Utility
   public final $anonfun$trimProper$1=class scala/xml/Utility$$anonfun$trimProper$1 of class scala/xml/Utility
   public final $anonfun$appendQuoted$1=class scala/xml/Utility$$anonfun$appendQuoted$1 of class scala/xml/Utility
   public final $anonfun$sequenceToXML$2=class scala/xml/Utility$$anonfun$sequenceToXML$2 of class scala/xml/Utility
   public final $anonfun$sequenceToXML$1=class scala/xml/Utility$$anonfun$sequenceToXML$1 of class scala/xml/Utility
   public final $anonfun$collectNamespaces$3=class scala/xml/Utility$$anonfun$collectNamespaces$3 of class scala/xml/Utility
   public final $anonfun$collectNamespaces$2=class scala/xml/Utility$$anonfun$collectNamespaces$2 of class scala/xml/Utility
   public final $anonfun$collectNamespaces$1=class scala/xml/Utility$$anonfun$collectNamespaces$1 of class scala/xml/Utility
   public final $anonfun$appendEscapedQuoted$1=class scala/xml/Utility$$anonfun$appendEscapedQuoted$1 of class scala/xml/Utility
  minor version: 0
  major version: 49
  Constant pool:
Asciz	SourceFile;
Asciz	Utility.scala;
Asciz	checkPubID;
Asciz	(Ljava/lang/String;)Z;
Asciz	Code;
Asciz	scala/xml/Utility$;
class	scala/xml/Utility$
Asciz	MODULE$;
Asciz	Lscala/xml/Utility$;;
NameAndType	MODULE$:Lscala/xml/Utility$;
Field	scala/xml/Utility$.MODULE$:Lscala/xml/Utility$;
NameAndType	checkPubID:(Ljava/lang/String;)Z
Method	scala/xml/Utility$.checkPubID:(Ljava/lang/String;)Z
Asciz	checkSysID;
NameAndType	checkSysID:(Ljava/lang/String;)Z
Method	scala/xml/Utility$.checkSysID:(Ljava/lang/String;)Z
Asciz	isValidIANAEncoding;
Asciz	(Lscala/collection/Seq;)Z;
NameAndType	isValidIANAEncoding:(Lscala/collection/Seq;)Z
Method	scala/xml/Utility$.isValidIANAEncoding:(Lscala/collection/Seq;)Z
Asciz	isPubIDChar;
Asciz	(C)Z;
NameAndType	isPubIDChar:(C)Z
Method	scala/xml/Utility$.isPubIDChar:(C)Z
Asciz	isName;
NameAndType	isName:(Ljava/lang/String;)Z
Method	scala/xml/Utility$.isName:(Ljava/lang/String;)Z
Asciz	isNameStart;
NameAndType	isNameStart:(C)Z
Method	scala/xml/Utility$.isNameStart:(C)Z
Asciz	isNameChar;
NameAndType	isNameChar:(C)Z
Method	scala/xml/Utility$.isNameChar:(C)Z
Asciz	isAlphaDigit;
NameAndType	isAlphaDigit:(C)Z
Method	scala/xml/Utility$.isAlphaDigit:(C)Z
Asciz	isAlpha;
NameAndType	isAlpha:(C)Z
Method	scala/xml/Utility$.isAlpha:(C)Z
Asciz	isSpace;
NameAndType	isSpace:(Lscala/collection/Seq;)Z
Method	scala/xml/Utility$.isSpace:(Lscala/collection/Seq;)Z
NameAndType	isSpace:(C)Z
Method	scala/xml/Utility$.isSpace:(C)Z
Asciz	sequenceToXML$default$4;
Asciz	()Z;
NameAndType	sequenceToXML$default$4:()Z
Method	scala/xml/Utility$.sequenceToXML$default$4:()Z
Asciz	sequenceToXML$default$3;
Asciz	()Lscala/collection/mutable/StringBuilder;;
NameAndType	sequenceToXML$default$3:()Lscala/collection/mutable/StringBuilder;
Method	scala/xml/Utility$.sequenceToXML$default$3:()Lscala/collection/mutable/StringBuilder;
Asciz	sequenceToXML$default$2;
Asciz	()Lscala/xml/NamespaceBinding;;
NameAndType	sequenceToXML$default$2:()Lscala/xml/NamespaceBinding;
Method	scala/xml/Utility$.sequenceToXML$default$2:()Lscala/xml/NamespaceBinding;
Asciz	toXML$default$7;
NameAndType	toXML$default$7:()Z
Method	scala/xml/Utility$.toXML$default$7:()Z
Asciz	toXML$default$6;
NameAndType	toXML$default$6:()Z
Method	scala/xml/Utility$.toXML$default$6:()Z
Asciz	toXML$default$5;
NameAndType	toXML$default$5:()Z
Method	scala/xml/Utility$.toXML$default$5:()Z
Asciz	toXML$default$4;
NameAndType	toXML$default$4:()Z
Method	scala/xml/Utility$.toXML$default$4:()Z
Asciz	toXML$default$3;
NameAndType	toXML$default$3:()Lscala/collection/mutable/StringBuilder;
Method	scala/xml/Utility$.toXML$default$3:()Lscala/collection/mutable/StringBuilder;
Asciz	toXML$default$2;
NameAndType	toXML$default$2:()Lscala/xml/NamespaceBinding;
Method	scala/xml/Utility$.toXML$default$2:()Lscala/xml/NamespaceBinding;
Asciz	parseCharRef;
Asciz	(Lscala/Function0;Lscala/Function0;Lscala/Function1;)Ljava/lang/String;;
NameAndType	parseCharRef:(Lscala/Function0;Lscala/Function0;Lscala/Function1;)Ljava/lang/String;
Method	scala/xml/Utility$.parseCharRef:(Lscala/Function0;Lscala/Function0;Lscala/Function1;)Ljava/lang/String;
Asciz	(Lscala/Function0<Ljava/lang/Character;>;Lscala/Function0<Ljava/lang/Object;>;Lscala/Function1<Ljava/lang/String;Ljava/lang/Object;>;)Ljava/lang/String;;
Asciz	Signature;
Asciz	parseAttributeValue;
Asciz	(Ljava/lang/String;)Lscala/collection/Seq;;
NameAndType	parseAttributeValue:(Ljava/lang/String;)Lscala/collection/Seq;
Method	scala/xml/Utility$.parseAttributeValue:(Ljava/lang/String;)Lscala/collection/Seq;
Asciz	(Ljava/lang/String;)Lscala/collection/Seq<Lscala/xml/Node;>;;
Asciz	checkAttributeValue;
Asciz	(Ljava/lang/String;)Ljava/lang/String;;
NameAndType	checkAttributeValue:(Ljava/lang/String;)Ljava/lang/String;
Method	scala/xml/Utility$.checkAttributeValue:(Ljava/lang/String;)Ljava/lang/String;
Asciz	getName;
Asciz	(Ljava/lang/String;I)Ljava/lang/String;;
NameAndType	getName:(Ljava/lang/String;I)Ljava/lang/String;
Method	scala/xml/Utility$.getName:(Ljava/lang/String;I)Ljava/lang/String;
Asciz	appendEscapedQuoted;
Asciz	(Ljava/lang/String;Lscala/collection/mutable/StringBuilder;)Lscala/collection/mutable/StringBuilder;;
NameAndType	appendEscapedQuoted:(Ljava/lang/String;Lscala/collection/mutable/StringBuilder;)Lscala/collection/mutable/StringBuilder;
Method	scala/xml/Utility$.appendEscapedQuoted:(Ljava/lang/String;Lscala/collection/mutable/StringBuilder;)Lscala/collection/mutable/StringBuilder;
Asciz	appendQuoted;
NameAndType	appendQuoted:(Ljava/lang/String;Lscala/collection/mutable/StringBuilder;)Lscala/collection/mutable/StringBuilder;
Method	scala/xml/Utility$.appendQuoted:(Ljava/lang/String;Lscala/collection/mutable/StringBuilder;)Lscala/collection/mutable/StringBuilder;
NameAndType	appendQuoted:(Ljava/lang/String;)Ljava/lang/String;
Method	scala/xml/Utility$.appendQuoted:(Ljava/lang/String;)Ljava/lang/String;
Asciz	prefix;
Asciz	(Ljava/lang/String;)Lscala/Option;;
NameAndType	prefix:(Ljava/lang/String;)Lscala/Option;
Method	scala/xml/Utility$.prefix:(Ljava/lang/String;)Lscala/Option;
Asciz	(Ljava/lang/String;)Lscala/Option<Ljava/lang/String;>;;
Asciz	sequenceToXML;
Asciz	(Lscala/collection/Seq;Lscala/xml/NamespaceBinding;Lscala/collection/mutable/StringBuilder;Z)V;
NameAndType	sequenceToXML:(Lscala/collection/Seq;Lscala/xml/NamespaceBinding;Lscala/collection/mutable/StringBuilder;Z)V
Method	scala/xml/Utility$.sequenceToXML:(Lscala/collection/Seq;Lscala/xml/NamespaceBinding;Lscala/collection/mutable/StringBuilder;Z)V
Asciz	(Lscala/collection/Seq<Lscala/xml/Node;>;Lscala/xml/NamespaceBinding;Lscala/collection/mutable/StringBuilder;Z)V;
Asciz	toXML;
Asciz	(Lscala/xml/Node;Lscala/xml/NamespaceBinding;Lscala/collection/mutable/StringBuilder;ZZZZ)Lscala/collection/mutable/StringBuilder;;
NameAndType	toXML:(Lscala/xml/Node;Lscala/xml/NamespaceBinding;Lscala/collection/mutable/StringBuilder;ZZZZ)Lscala/collection/mutable/StringBuilder;
Method	scala/xml/Utility$.toXML:(Lscala/xml/Node;Lscala/xml/NamespaceBinding;Lscala/collection/mutable/StringBuilder;ZZZZ)Lscala/collection/mutable/StringBuilder;
Asciz	collectNamespaces;
Asciz	(Lscala/xml/Node;Lscala/collection/mutable/Set;)V;
NameAndType	collectNamespaces:(Lscala/xml/Node;Lscala/collection/mutable/Set;)V
Method	scala/xml/Utility$.collectNamespaces:(Lscala/xml/Node;Lscala/collection/mutable/Set;)V
Asciz	(Lscala/xml/Node;Lscala/collection/mutable/Set<Ljava/lang/String;>;)V;
Asciz	(Lscala/collection/Seq;)Lscala/collection/mutable/Set;;
NameAndType	collectNamespaces:(Lscala/collection/Seq;)Lscala/collection/mutable/Set;
Method	scala/xml/Utility$.collectNamespaces:(Lscala/collection/Seq;)Lscala/collection/mutable/Set;
Asciz	(Lscala/collection/Seq<Lscala/xml/Node;>;)Lscala/collection/mutable/Set<Ljava/lang/String;>;;
Asciz	unescape;
NameAndType	unescape:(Ljava/lang/String;Lscala/collection/mutable/StringBuilder;)Lscala/collection/mutable/StringBuilder;
Method	scala/xml/Utility$.unescape:(Ljava/lang/String;Lscala/collection/mutable/StringBuilder;)Lscala/collection/mutable/StringBuilder;
Asciz	escape;
NameAndType	escape:(Ljava/lang/String;Lscala/collection/mutable/StringBuilder;)Lscala/collection/mutable/StringBuilder;
Method	scala/xml/Utility$.escape:(Ljava/lang/String;Lscala/collection/mutable/StringBuilder;)Lscala/collection/mutable/StringBuilder;
NameAndType	escape:(Ljava/lang/String;)Ljava/lang/String;
Method	scala/xml/Utility$.escape:(Ljava/lang/String;)Ljava/lang/String;
Asciz	sort;
Asciz	(Lscala/xml/Node;)Lscala/xml/Node;;
NameAndType	sort:(Lscala/xml/Node;)Lscala/xml/Node;
Method	scala/xml/Utility$.sort:(Lscala/xml/Node;)Lscala/xml/Node;
Asciz	(Lscala/xml/MetaData;)Lscala/xml/MetaData;;
NameAndType	sort:(Lscala/xml/MetaData;)Lscala/xml/MetaData;
Method	scala/xml/Utility$.sort:(Lscala/xml/MetaData;)Lscala/xml/MetaData;
Asciz	trimProper;
Asciz	(Lscala/xml/Node;)Lscala/collection/Seq;;
NameAndType	trimProper:(Lscala/xml/Node;)Lscala/collection/Seq;
Method	scala/xml/Utility$.trimProper:(Lscala/xml/Node;)Lscala/collection/Seq;
Asciz	(Lscala/xml/Node;)Lscala/collection/Seq<Lscala/xml/Node;>;;
Asciz	trim;
NameAndType	trim:(Lscala/xml/Node;)Lscala/xml/Node;
Method	scala/xml/Utility$.trim:(Lscala/xml/Node;)Lscala/xml/Node;
Asciz	isAtomAndNotText;
Asciz	(Lscala/xml/Node;)Z;
NameAndType	isAtomAndNotText:(Lscala/xml/Node;)Z
Method	scala/xml/Utility$.isAtomAndNotText:(Lscala/xml/Node;)Z
Asciz	sbToString;
Asciz	(Lscala/Function1;)Ljava/lang/String;;
NameAndType	sbToString:(Lscala/Function1;)Ljava/lang/String;
Method	scala/xml/Utility$.sbToString:(Lscala/Function1;)Ljava/lang/String;
Asciz	(Lscala/Function1<Lscala/collection/mutable/StringBuilder;Ljava/lang/Object;>;)Ljava/lang/String;;
Asciz	implicitSbToString;
Asciz	(Lscala/collection/mutable/StringBuilder;)Ljava/lang/String;;
NameAndType	implicitSbToString:(Lscala/collection/mutable/StringBuilder;)Ljava/lang/String;
Method	scala/xml/Utility$.implicitSbToString:(Lscala/collection/mutable/StringBuilder;)Ljava/lang/String;
Asciz	ScalaSig;
Asciz	InnerClasses;
Asciz	scala/xml/Utility$$anonfun$6;
class	scala/xml/Utility$$anonfun$6
Asciz	scala/xml/Utility;
class	scala/xml/Utility
Asciz	$anonfun$6;
Asciz	scala/xml/Utility$$anonfun$5;
class	scala/xml/Utility$$anonfun$5
Asciz	$anonfun$5;
Asciz	scala/xml/Utility$$anonfun$4;
class	scala/xml/Utility$$anonfun$4
Asciz	$anonfun$4;
Asciz	scala/xml/Utility$$anonfun$2;
class	scala/xml/Utility$$anonfun$2
Asciz	$anonfun$2;
Asciz	scala/xml/Utility$$anonfun$1;
class	scala/xml/Utility$$anonfun$1
Asciz	$anonfun$1;
Asciz	scala/xml/Utility$$anonfun$sort$1;
class	scala/xml/Utility$$anonfun$sort$1
Asciz	$anonfun$sort$1;
Asciz	scala/xml/Utility$$anonfun$trim$1;
class	scala/xml/Utility$$anonfun$trim$1
Asciz	$anonfun$trim$1;
Asciz	scala/xml/Utility$$anonfun$toXML$1;
class	scala/xml/Utility$$anonfun$toXML$1
Asciz	$anonfun$toXML$1;
Asciz	scala/xml/Utility$$anonfun$escape$2;
class	scala/xml/Utility$$anonfun$escape$2
Asciz	$anonfun$escape$2;
Asciz	scala/xml/Utility$$anonfun$escape$1;
class	scala/xml/Utility$$anonfun$escape$1
Asciz	$anonfun$escape$1;
Asciz	scala/xml/Utility$$anonfun$getName$1;
class	scala/xml/Utility$$anonfun$getName$1
Asciz	$anonfun$getName$1;
Asciz	scala/xml/Utility$$anonfun$unescape$1;
class	scala/xml/Utility$$anonfun$unescape$1
Asciz	$anonfun$unescape$1;
Asciz	scala/xml/Utility$$anonfun$trimProper$1;
class	scala/xml/Utility$$anonfun$trimProper$1
Asciz	$anonfun$trimProper$1;
Asciz	scala/xml/Utility$$anonfun$appendQuoted$1;
class	scala/xml/Utility$$anonfun$appendQuoted$1
Asciz	$anonfun$appendQuoted$1;
Asciz	scala/xml/Utility$$anonfun$sequenceToXML$2;
class	scala/xml/Utility$$anonfun$sequenceToXML$2
Asciz	$anonfun$sequenceToXML$2;
Asciz	scala/xml/Utility$$anonfun$sequenceToXML$1;
class	scala/xml/Utility$$anonfun$sequenceToXML$1
Asciz	$anonfun$sequenceToXML$1;
Asciz	scala/xml/Utility$$anonfun$collectNamespaces$3;
class	scala/xml/Utility$$anonfun$collectNamespaces$3
Asciz	$anonfun$collectNamespaces$3;
Asciz	scala/xml/Utility$$anonfun$collectNamespaces$2;
class	scala/xml/Utility$$anonfun$collectNamespaces$2
Asciz	$anonfun$collectNamespaces$2;
Asciz	scala/xml/Utility$$anonfun$collectNamespaces$1;
class	scala/xml/Utility$$anonfun$collectNamespaces$1
Asciz	$anonfun$collectNamespaces$1;
Asciz	scala/xml/Utility$$anonfun$appendEscapedQuoted$1;
class	scala/xml/Utility$$anonfun$appendEscapedQuoted$1
Asciz	$anonfun$appendEscapedQuoted$1;
Asciz	java/lang/Object;
class	java/lang/Object

{
public static final boolean checkPubID(java.lang.String);
  Signature: (Ljava/lang/String;)Z
  Code:
   Stack=2, Locals=1, Args_size=1
	getstatic	Field scala/xml/Utility$.MODULE$:Lscala/xml/Utility$;
	aload_0
	invokevirtual	Method scala/xml/Utility$.checkPubID:(Ljava/lang/String;)Z
	ireturn
  Labels:

public static final boolean checkSysID(java.lang.String);
  Signature: (Ljava/lang/String;)Z
  Code:
   Stack=2, Locals=1, Args_size=1
	getstatic	Field scala/xml/Utility$.MODULE$:Lscala/xml/Utility$;
	aload_0
	invokevirtual	Method scala/xml/Utility$.checkSysID:(Ljava/lang/String;)Z
	ireturn
  Labels:

public static final boolean isValidIANAEncoding(scala.collection.Seq);
  Signature: (Lscala/collection/Seq;)Z
  Code:
   Stack=2, Locals=1, Args_size=1
	getstatic	Field scala/xml/Utility$.MODULE$:Lscala/xml/Utility$;
	aload_0
	invokevirtual	Method scala/xml/Utility$.isValidIANAEncoding:(Lscala/collection/Seq;)Z
	ireturn
  Labels:

public static final boolean isPubIDChar(char);
  Signature: (C)Z
  Code:
   Stack=2, Locals=1, Args_size=1
	getstatic	Field scala/xml/Utility$.MODULE$:Lscala/xml/Utility$;
	iload_0
	invokevirtual	Method scala/xml/Utility$.isPubIDChar:(C)Z
	ireturn
  Labels:

public static final boolean isName(java.lang.String);
  Signature: (Ljava/lang/String;)Z
  Code:
   Stack=2, Locals=1, Args_size=1
	getstatic	Field scala/xml/Utility$.MODULE$:Lscala/xml/Utility$;
	aload_0
	invokevirtual	Method scala/xml/Utility$.isName:(Ljava/lang/String;)Z
	ireturn
  Labels:

public static final boolean isNameStart(char);
  Signature: (C)Z
  Code:
   Stack=2, Locals=1, Args_size=1
	getstatic	Field scala/xml/Utility$.MODULE$:Lscala/xml/Utility$;
	iload_0
	invokevirtual	Method scala/xml/Utility$.isNameStart:(C)Z
	ireturn
  Labels:

public static final boolean isNameChar(char);
  Signature: (C)Z
  Code:
   Stack=2, Locals=1, Args_size=1
	getstatic	Field scala/xml/Utility$.MODULE$:Lscala/xml/Utility$;
	iload_0
	invokevirtual	Method scala/xml/Utility$.isNameChar:(C)Z
	ireturn
  Labels:

public static final boolean isAlphaDigit(char);
  Signature: (C)Z
  Code:
   Stack=2, Locals=1, Args_size=1
	getstatic	Field scala/xml/Utility$.MODULE$:Lscala/xml/Utility$;
	iload_0
	invokevirtual	Method scala/xml/Utility$.isAlphaDigit:(C)Z
	ireturn
  Labels:

public static final boolean isAlpha(char);
  Signature: (C)Z
  Code:
   Stack=2, Locals=1, Args_size=1
	getstatic	Field scala/xml/Utility$.MODULE$:Lscala/xml/Utility$;
	iload_0
	invokevirtual	Method scala/xml/Utility$.isAlpha:(C)Z
	ireturn
  Labels:

public static final boolean isSpace(scala.collection.Seq);
  Signature: (Lscala/collection/Seq;)Z
  Code:
   Stack=2, Locals=1, Args_size=1
	getstatic	Field scala/xml/Utility$.MODULE$:Lscala/xml/Utility$;
	aload_0
	invokevirtual	Method scala/xml/Utility$.isSpace:(Lscala/collection/Seq;)Z
	ireturn
  Labels:

public static final boolean isSpace(char);
  Signature: (C)Z
  Code:
   Stack=2, Locals=1, Args_size=1
	getstatic	Field scala/xml/Utility$.MODULE$:Lscala/xml/Utility$;
	iload_0
	invokevirtual	Method scala/xml/Utility$.isSpace:(C)Z
	ireturn
  Labels:

public static final boolean sequenceToXML$default$4();
  Signature: ()Z
  Code:
   Stack=1, Locals=0, Args_size=0
	getstatic	Field scala/xml/Utility$.MODULE$:Lscala/xml/Utility$;
	invokevirtual	Method scala/xml/Utility$.sequenceToXML$default$4:()Z
	ireturn
  Labels:

public static final scala.collection.mutable.StringBuilder sequenceToXML$default$3();
  Signature: ()Lscala/collection/mutable/StringBuilder;
  Code:
   Stack=1, Locals=0, Args_size=0
	getstatic	Field scala/xml/Utility$.MODULE$:Lscala/xml/Utility$;
	invokevirtual	Method scala/xml/Utility$.sequenceToXML$default$3:()Lscala/collection/mutable/StringBuilder;
	areturn
  Labels:

public static final scala.xml.NamespaceBinding sequenceToXML$default$2();
  Signature: ()Lscala/xml/NamespaceBinding;
  Code:
   Stack=1, Locals=0, Args_size=0
	getstatic	Field scala/xml/Utility$.MODULE$:Lscala/xml/Utility$;
	invokevirtual	Method scala/xml/Utility$.sequenceToXML$default$2:()Lscala/xml/NamespaceBinding;
	areturn
  Labels:

public static final boolean toXML$default$7();
  Signature: ()Z
  Code:
   Stack=1, Locals=0, Args_size=0
	getstatic	Field scala/xml/Utility$.MODULE$:Lscala/xml/Utility$;
	invokevirtual	Method scala/xml/Utility$.toXML$default$7:()Z
	ireturn
  Labels:

public static final boolean toXML$default$6();
  Signature: ()Z
  Code:
   Stack=1, Locals=0, Args_size=0
	getstatic	Field scala/xml/Utility$.MODULE$:Lscala/xml/Utility$;
	invokevirtual	Method scala/xml/Utility$.toXML$default$6:()Z
	ireturn
  Labels:

public static final boolean toXML$default$5();
  Signature: ()Z
  Code:
   Stack=1, Locals=0, Args_size=0
	getstatic	Field scala/xml/Utility$.MODULE$:Lscala/xml/Utility$;
	invokevirtual	Method scala/xml/Utility$.toXML$default$5:()Z
	ireturn
  Labels:

public static final boolean toXML$default$4();
  Signature: ()Z
  Code:
   Stack=1, Locals=0, Args_size=0
	getstatic	Field scala/xml/Utility$.MODULE$:Lscala/xml/Utility$;
	invokevirtual	Method scala/xml/Utility$.toXML$default$4:()Z
	ireturn
  Labels:

public static final scala.collection.mutable.StringBuilder toXML$default$3();
  Signature: ()Lscala/collection/mutable/StringBuilder;
  Code:
   Stack=1, Locals=0, Args_size=0
	getstatic	Field scala/xml/Utility$.MODULE$:Lscala/xml/Utility$;
	invokevirtual	Method scala/xml/Utility$.toXML$default$3:()Lscala/collection/mutable/StringBuilder;
	areturn
  Labels:

public static final scala.xml.NamespaceBinding toXML$default$2();
  Signature: ()Lscala/xml/NamespaceBinding;
  Code:
   Stack=1, Locals=0, Args_size=0
	getstatic	Field scala/xml/Utility$.MODULE$:Lscala/xml/Utility$;
	invokevirtual	Method scala/xml/Utility$.toXML$default$2:()Lscala/xml/NamespaceBinding;
	areturn
  Labels:

public static final java.lang.String parseCharRef(scala.Function0, scala.Function0, scala.Function1);
  Signature: (Lscala/Function0;Lscala/Function0;Lscala/Function1;)Ljava/lang/String;
  Code:
   Stack=4, Locals=3, Args_size=3
	getstatic	Field scala/xml/Utility$.MODULE$:Lscala/xml/Utility$;
	aload_0
	aload_1
	aload_2
	invokevirtual	Method scala/xml/Utility$.parseCharRef:(Lscala/Function0;Lscala/Function0;Lscala/Function1;)Ljava/lang/String;
	areturn
  Labels:
  Signature: length = 0x2
   00 4F 

public static final scala.collection.Seq parseAttributeValue(java.lang.String);
  Signature: (Ljava/lang/String;)Lscala/collection/Seq;
  Code:
   Stack=2, Locals=1, Args_size=1
	getstatic	Field scala/xml/Utility$.MODULE$:Lscala/xml/Utility$;
	aload_0
	invokevirtual	Method scala/xml/Utility$.parseAttributeValue:(Ljava/lang/String;)Lscala/collection/Seq;
	areturn
  Labels:
  Signature: length = 0x2
   00 55 

public static final java.lang.String checkAttributeValue(java.lang.String);
  Signature: (Ljava/lang/String;)Ljava/lang/String;
  Code:
   Stack=2, Locals=1, Args_size=1
	getstatic	Field scala/xml/Utility$.MODULE$:Lscala/xml/Utility$;
	aload_0
	invokevirtual	Method scala/xml/Utility$.checkAttributeValue:(Ljava/lang/String;)Ljava/lang/String;
	areturn
  Labels:

public static final java.lang.String getName(java.lang.String, int);
  Signature: (Ljava/lang/String;I)Ljava/lang/String;
  Code:
   Stack=3, Locals=2, Args_size=2
	getstatic	Field scala/xml/Utility$.MODULE$:Lscala/xml/Utility$;
	aload_0
	iload_1
	invokevirtual	Method scala/xml/Utility$.getName:(Ljava/lang/String;I)Ljava/lang/String;
	areturn
  Labels:

public static final scala.collection.mutable.StringBuilder appendEscapedQuoted(java.lang.String, scala.collection.mutable.StringBuilder);
  Signature: (Ljava/lang/String;Lscala/collection/mutable/StringBuilder;)Lscala/collection/mutable/StringBuilder;
  Code:
   Stack=3, Locals=2, Args_size=2
	getstatic	Field scala/xml/Utility$.MODULE$:Lscala/xml/Utility$;
	aload_0
	aload_1
	invokevirtual	Method scala/xml/Utility$.appendEscapedQuoted:(Ljava/lang/String;Lscala/collection/mutable/StringBuilder;)Lscala/collection/mutable/StringBuilder;
	areturn
  Labels:

public static final scala.collection.mutable.StringBuilder appendQuoted(java.lang.String, scala.collection.mutable.StringBuilder);
  Signature: (Ljava/lang/String;Lscala/collection/mutable/StringBuilder;)Lscala/collection/mutable/StringBuilder;
  Code:
   Stack=3, Locals=2, Args_size=2
	getstatic	Field scala/xml/Utility$.MODULE$:Lscala/xml/Utility$;
	aload_0
	aload_1
	invokevirtual	Method scala/xml/Utility$.appendQuoted:(Ljava/lang/String;Lscala/collection/mutable/StringBuilder;)Lscala/collection/mutable/StringBuilder;
	areturn
  Labels:

public static final java.lang.String appendQuoted(java.lang.String);
  Signature: (Ljava/lang/String;)Ljava/lang/String;
  Code:
   Stack=2, Locals=1, Args_size=1
	getstatic	Field scala/xml/Utility$.MODULE$:Lscala/xml/Utility$;
	aload_0
	invokevirtual	Method scala/xml/Utility$.appendQuoted:(Ljava/lang/String;)Ljava/lang/String;
	areturn
  Labels:

public static final scala.Option prefix(java.lang.String);
  Signature: (Ljava/lang/String;)Lscala/Option;
  Code:
   Stack=2, Locals=1, Args_size=1
	getstatic	Field scala/xml/Utility$.MODULE$:Lscala/xml/Utility$;
	aload_0
	invokevirtual	Method scala/xml/Utility$.prefix:(Ljava/lang/String;)Lscala/Option;
	areturn
  Labels:
  Signature: length = 0x2
   00 6B 

public static final void sequenceToXML(scala.collection.Seq, scala.xml.NamespaceBinding, scala.collection.mutable.StringBuilder, boolean);
  Signature: (Lscala/collection/Seq;Lscala/xml/NamespaceBinding;Lscala/collection/mutable/StringBuilder;Z)V
  Code:
   Stack=5, Locals=4, Args_size=4
	getstatic	Field scala/xml/Utility$.MODULE$:Lscala/xml/Utility$;
	aload_0
	aload_1
	aload_2
	iload_3
	invokevirtual	Method scala/xml/Utility$.sequenceToXML:(Lscala/collection/Seq;Lscala/xml/NamespaceBinding;Lscala/collection/mutable/StringBuilder;Z)V
	return
  Labels:
  Signature: length = 0x2
   00 70 

public static final scala.collection.mutable.StringBuilder toXML(scala.xml.Node, scala.xml.NamespaceBinding, scala.collection.mutable.StringBuilder, boolean, boolean, boolean, boolean);
  Signature: (Lscala/xml/Node;Lscala/xml/NamespaceBinding;Lscala/collection/mutable/StringBuilder;ZZZZ)Lscala/collection/mutable/StringBuilder;
  Code:
   Stack=8, Locals=7, Args_size=7
	getstatic	Field scala/xml/Utility$.MODULE$:Lscala/xml/Utility$;
	aload_0
	aload_1
	aload_2
	iload_3
	iload	4
	iload	5
	iload	6
	invokevirtual	Method scala/xml/Utility$.toXML:(Lscala/xml/Node;Lscala/xml/NamespaceBinding;Lscala/collection/mutable/StringBuilder;ZZZZ)Lscala/collection/mutable/StringBuilder;
	areturn
  Labels:

public static final void collectNamespaces(scala.xml.Node, scala.collection.mutable.Set);
  Signature: (Lscala/xml/Node;Lscala/collection/mutable/Set;)V
  Code:
   Stack=3, Locals=2, Args_size=2
	getstatic	Field scala/xml/Utility$.MODULE$:Lscala/xml/Utility$;
	aload_0
	aload_1
	invokevirtual	Method scala/xml/Utility$.collectNamespaces:(Lscala/xml/Node;Lscala/collection/mutable/Set;)V
	return
  Labels:
  Signature: length = 0x2
   00 79 

public static final scala.collection.mutable.Set collectNamespaces(scala.collection.Seq);
  Signature: (Lscala/collection/Seq;)Lscala/collection/mutable/Set;
  Code:
   Stack=2, Locals=1, Args_size=1
	getstatic	Field scala/xml/Utility$.MODULE$:Lscala/xml/Utility$;
	aload_0
	invokevirtual	Method scala/xml/Utility$.collectNamespaces:(Lscala/collection/Seq;)Lscala/collection/mutable/Set;
	areturn
  Labels:
  Signature: length = 0x2
   00 7D 

public static final scala.collection.mutable.StringBuilder unescape(java.lang.String, scala.collection.mutable.StringBuilder);
  Signature: (Ljava/lang/String;Lscala/collection/mutable/StringBuilder;)Lscala/collection/mutable/StringBuilder;
  Code:
   Stack=3, Locals=2, Args_size=2
	getstatic	Field scala/xml/Utility$.MODULE$:Lscala/xml/Utility$;
	aload_0
	aload_1
	invokevirtual	Method scala/xml/Utility$.unescape:(Ljava/lang/String;Lscala/collection/mutable/StringBuilder;)Lscala/collection/mutable/StringBuilder;
	areturn
  Labels:

public static final scala.collection.mutable.StringBuilder escape(java.lang.String, scala.collection.mutable.StringBuilder);
  Signature: (Ljava/lang/String;Lscala/collection/mutable/StringBuilder;)Lscala/collection/mutable/StringBuilder;
  Code:
   Stack=3, Locals=2, Args_size=2
	getstatic	Field scala/xml/Utility$.MODULE$:Lscala/xml/Utility$;
	aload_0
	aload_1
	invokevirtual	Method scala/xml/Utility$.escape:(Ljava/lang/String;Lscala/collection/mutable/StringBuilder;)Lscala/collection/mutable/StringBuilder;
	areturn
  Labels:

public static final java.lang.String escape(java.lang.String);
  Signature: (Ljava/lang/String;)Ljava/lang/String;
  Code:
   Stack=2, Locals=1, Args_size=1
	getstatic	Field scala/xml/Utility$.MODULE$:Lscala/xml/Utility$;
	aload_0
	invokevirtual	Method scala/xml/Utility$.escape:(Ljava/lang/String;)Ljava/lang/String;
	areturn
  Labels:

public static final scala.xml.Node sort(scala.xml.Node);
  Signature: (Lscala/xml/Node;)Lscala/xml/Node;
  Code:
   Stack=2, Locals=1, Args_size=1
	getstatic	Field scala/xml/Utility$.MODULE$:Lscala/xml/Utility$;
	aload_0
	invokevirtual	Method scala/xml/Utility$.sort:(Lscala/xml/Node;)Lscala/xml/Node;
	areturn
  Labels:

public static final scala.xml.MetaData sort(scala.xml.MetaData);
  Signature: (Lscala/xml/MetaData;)Lscala/xml/MetaData;
  Code:
   Stack=2, Locals=1, Args_size=1
	getstatic	Field scala/xml/Utility$.MODULE$:Lscala/xml/Utility$;
	aload_0
	invokevirtual	Method scala/xml/Utility$.sort:(Lscala/xml/MetaData;)Lscala/xml/MetaData;
	areturn
  Labels:

public static final scala.collection.Seq trimProper(scala.xml.Node);
  Signature: (Lscala/xml/Node;)Lscala/collection/Seq;
  Code:
   Stack=2, Locals=1, Args_size=1
	getstatic	Field scala/xml/Utility$.MODULE$:Lscala/xml/Utility$;
	aload_0
	invokevirtual	Method scala/xml/Utility$.trimProper:(Lscala/xml/Node;)Lscala/collection/Seq;
	areturn
  Labels:
  Signature: length = 0x2
   00 FFFFFF91 

public static final scala.xml.Node trim(scala.xml.Node);
  Signature: (Lscala/xml/Node;)Lscala/xml/Node;
  Code:
   Stack=2, Locals=1, Args_size=1
	getstatic	Field scala/xml/Utility$.MODULE$:Lscala/xml/Utility$;
	aload_0
	invokevirtual	Method scala/xml/Utility$.trim:(Lscala/xml/Node;)Lscala/xml/Node;
	areturn
  Labels:

public static final boolean isAtomAndNotText(scala.xml.Node);
  Signature: (Lscala/xml/Node;)Z
  Code:
   Stack=2, Locals=1, Args_size=1
	getstatic	Field scala/xml/Utility$.MODULE$:Lscala/xml/Utility$;
	aload_0
	invokevirtual	Method scala/xml/Utility$.isAtomAndNotText:(Lscala/xml/Node;)Z
	ireturn
  Labels:

public static final java.lang.String sbToString(scala.Function1);
  Signature: (Lscala/Function1;)Ljava/lang/String;
  Code:
   Stack=2, Locals=1, Args_size=1
	getstatic	Field scala/xml/Utility$.MODULE$:Lscala/xml/Utility$;
	aload_0
	invokevirtual	Method scala/xml/Utility$.sbToString:(Lscala/Function1;)Ljava/lang/String;
	areturn
  Labels:
  Signature: length = 0x2
   00 FFFFFF9D 

public static final java.lang.String implicitSbToString(scala.collection.mutable.StringBuilder);
  Signature: (Lscala/collection/mutable/StringBuilder;)Ljava/lang/String;
  Code:
   Stack=2, Locals=1, Args_size=1
	getstatic	Field scala/xml/Utility$.MODULE$:Lscala/xml/Utility$;
	aload_0
	invokevirtual	Method scala/xml/Utility$.implicitSbToString:(Lscala/collection/mutable/StringBuilder;)Ljava/lang/String;
	areturn
  Labels:

}

