Compiled from "Utility.scala"
public final class scala.xml.Utility$$anonfun$escape$1 extends scala.runtime.AbstractFunction1 implements java.io.Serializable
  SourceFile: "Utility.scala"
  Scala: length = 0x
   
  InnerClass: 
   public final $anonfun$escape$1=class scala/xml/Utility$$anonfun$escape$1 of class scala/xml/Utility
  minor version: 0
  major version: 49
  Constant pool:
Asciz	SourceFile;
Asciz	Utility.scala;
Asciz	<clinit>;
Asciz	()V;
Asciz	Code;
Asciz	serialVersionUID;
Asciz	J;
Asciz	scala/xml/Utility$$anonfun$escape$1;
class	scala/xml/Utility$$anonfun$escape$1
NameAndType	serialVersionUID:J
Field	scala/xml/Utility$$anonfun$escape$1.serialVersionUID:J
Asciz	text$1;
Asciz	Ljava/lang/String;;
Asciz	<init>;
Asciz	(Ljava/lang/String;)V;
Asciz	LineNumberTable;
NameAndType	text$1:Ljava/lang/String;
Field	scala/xml/Utility$$anonfun$escape$1.text$1:Ljava/lang/String;
Asciz	scala/runtime/AbstractFunction1;
class	scala/runtime/AbstractFunction1
NameAndType	"<init>":()V
Method	scala/runtime/AbstractFunction1."<init>":()V
Asciz	apply;
Asciz	(Ljava/lang/Object;)Ljava/lang/Object;;
Asciz	scala/collection/mutable/StringBuilder;
class	scala/collection/mutable/StringBuilder
Asciz	(Lscala/collection/mutable/StringBuilder;)V;
NameAndType	apply:(Lscala/collection/mutable/StringBuilder;)V
Method	scala/xml/Utility$$anonfun$escape$1.apply:(Lscala/collection/mutable/StringBuilder;)V
Asciz	scala/runtime/BoxedUnit;
class	scala/runtime/BoxedUnit
Asciz	UNIT;
Asciz	Lscala/runtime/BoxedUnit;;
NameAndType	UNIT:Lscala/runtime/BoxedUnit;
Field	scala/runtime/BoxedUnit.UNIT:Lscala/runtime/BoxedUnit;
Asciz	this;
Asciz	Lscala/xml/Utility$$anonfun$escape$1;;
Asciz	v1;
Asciz	Ljava/lang/Object;;
Asciz	LocalVariableTable;
Asciz	scala/xml/Utility$;
class	scala/xml/Utility$
Asciz	MODULE$;
Asciz	Lscala/xml/Utility$;;
NameAndType	MODULE$:Lscala/xml/Utility$;
Field	scala/xml/Utility$.MODULE$:Lscala/xml/Utility$;
Asciz	escape;
Asciz	(Ljava/lang/String;Lscala/collection/mutable/StringBuilder;)Lscala/collection/mutable/StringBuilder;;
NameAndType	escape:(Ljava/lang/String;Lscala/collection/mutable/StringBuilder;)Lscala/collection/mutable/StringBuilder;
Method	scala/xml/Utility$.escape:(Ljava/lang/String;Lscala/collection/mutable/StringBuilder;)Lscala/collection/mutable/StringBuilder;
Asciz	Scala;
Asciz	InnerClasses;
Asciz	scala/xml/Utility;
class	scala/xml/Utility
Asciz	$anonfun$escape$1;
Asciz	java/io/Serializable;
class	java/io/Serializable

{
public static final long serialVersionUID;
  Signature: J

public final java.lang.String text$1;
  Signature: Ljava/lang/String;

public static {};
  Signature: ()V
  Code:
   Stack=2, Locals=0, Args_size=0
	lconst_0
	putstatic	Field serialVersionUID:J
	return
  Labels:

public scala.xml.Utility$$anonfun$escape$1(java.lang.String);
  Signature: (Ljava/lang/String;)V
  Code:
   Stack=2, Locals=2, Args_size=2
	aload_0
	aload_1
	putfield	Field text$1:Ljava/lang/String;
	aload_0
	invokespecial	Method scala/runtime/AbstractFunction1."<init>":()V
	return
  Labels:

public final java.lang.Object apply(java.lang.Object);
  Signature: (Ljava/lang/Object;)Ljava/lang/Object;
  Code:
   Stack=2, Locals=2, Args_size=2
	aload_0
	aload_1
	checkcast	class scala/collection/mutable/StringBuilder
	invokevirtual	Method apply:(Lscala/collection/mutable/StringBuilder;)V
	getstatic	Field scala/runtime/BoxedUnit.UNIT:Lscala/runtime/BoxedUnit;
	areturn
  Labels:
  LocalVariableTable: 
   Start  Length  Slot  Name   Signature
   0      12      0    this       Lscala/xml/Utility$$anonfun$escape$1;
   0      12      1    v1       Ljava/lang/Object;


public final void apply(scala.collection.mutable.StringBuilder);
  Signature: (Lscala/collection/mutable/StringBuilder;)V
  Code:
   Stack=3, Locals=2, Args_size=2
	getstatic	Field scala/xml/Utility$.MODULE$:Lscala/xml/Utility$;
	aload_0
	getfield	Field text$1:Ljava/lang/String;
	aload_1
	invokevirtual	Method scala/xml/Utility$.escape:(Ljava/lang/String;Lscala/collection/mutable/StringBuilder;)Lscala/collection/mutable/StringBuilder;
	pop
	return
  Labels:

}

