Compiled from "Utility.scala"
public final class scala.xml.Utility$$anonfun$escape$2 extends java.lang.Object implements scala.Function2,scala.ScalaObject,java.io.Serializable
  SourceFile: "Utility.scala"
  Scala: length = 0x
   
  InnerClass: 
   public final #119= #9 of #118; //$anonfun$escape$2=class scala/xml/Utility$$anonfun$escape$2 of class scala/xml/Utility
  minor version: 0
  major version: 49
  Constant pool:
const #1 = Asciz	SourceFile;
const #2 = Asciz	Utility.scala;
const #3 = Asciz	<clinit>;
const #4 = Asciz	()V;
const #5 = Asciz	Code;
const #6 = Asciz	serialVersionUID;
const #7 = Asciz	J;
const #8 = Asciz	scala/xml/Utility$$anonfun$escape$2;
const #9 = class	#8;	//  scala/xml/Utility$$anonfun$escape$2
const #10 = NameAndType	#6:#7;//  serialVersionUID:J
const #11 = Field	#9.#10;	//  scala/xml/Utility$$anonfun$escape$2.serialVersionUID:J
const #12 = Asciz	<init>;
const #13 = Asciz	LineNumberTable;
const #14 = Asciz	java/lang/Object;
const #15 = class	#14;	//  java/lang/Object
const #16 = NameAndType	#12:#4;//  "<init>":()V
const #17 = Method	#15.#16;	//  java/lang/Object."<init>":()V
const #18 = Asciz	scala/Function2$class;
const #19 = class	#18;	//  scala/Function2$class
const #20 = Asciz	$init$;
const #21 = Asciz	(Lscala/Function2;)V;
const #22 = NameAndType	#20:#21;//  $init$:(Lscala/Function2;)V
const #23 = Method	#19.#22;	//  scala/Function2$class.$init$:(Lscala/Function2;)V
const #24 = Asciz	apply;
const #25 = Asciz	(Ljava/lang/Object;Ljava/lang/Object;)Ljava/lang/Object;;
const #26 = Asciz	scala/collection/mutable/StringBuilder;
const #27 = class	#26;	//  scala/collection/mutable/StringBuilder
const #28 = Asciz	scala/runtime/BoxesRunTime;
const #29 = class	#28;	//  scala/runtime/BoxesRunTime
const #30 = Asciz	unboxToChar;
const #31 = Asciz	(Ljava/lang/Object;)C;
const #32 = NameAndType	#30:#31;//  unboxToChar:(Ljava/lang/Object;)C
const #33 = Method	#29.#32;	//  scala/runtime/BoxesRunTime.unboxToChar:(Ljava/lang/Object;)C
const #34 = Asciz	(Lscala/collection/mutable/StringBuilder;C)Lscala/collection/mutable/StringBuilder;;
const #35 = NameAndType	#24:#34;//  apply:(Lscala/collection/mutable/StringBuilder;C)Lscala/collection/mutable/StringBuilder;
const #36 = Method	#9.#35;	//  scala/xml/Utility$$anonfun$escape$2.apply:(Lscala/collection/mutable/StringBuilder;C)Lscala/collection/mutable/StringBuilder;
const #37 = Asciz	this;
const #38 = Asciz	Lscala/xml/Utility$$anonfun$escape$2;;
const #39 = Asciz	v1;
const #40 = Asciz	Ljava/lang/Object;;
const #41 = Asciz	v2;
const #42 = Asciz	LocalVariableTable;
const #43 = Asciz	scala/xml/Utility$Escapes$;
const #44 = class	#43;	//  scala/xml/Utility$Escapes$
const #45 = Asciz	MODULE$;
const #46 = Asciz	Lscala/xml/Utility$Escapes$;;
const #47 = NameAndType	#45:#46;//  MODULE$:Lscala/xml/Utility$Escapes$;
const #48 = Field	#44.#47;	//  scala/xml/Utility$Escapes$.MODULE$:Lscala/xml/Utility$Escapes$;
const #49 = Asciz	escMap;
const #50 = Asciz	()Lscala/collection/immutable/Map;;
const #51 = NameAndType	#49:#50;//  escMap:()Lscala/collection/immutable/Map;
const #52 = Method	#44.#51;	//  scala/xml/Utility$Escapes$.escMap:()Lscala/collection/immutable/Map;
const #53 = Asciz	boxToCharacter;
const #54 = Asciz	(C)Ljava/lang/Character;;
const #55 = NameAndType	#53:#54;//  boxToCharacter:(C)Ljava/lang/Character;
const #56 = Method	#29.#55;	//  scala/runtime/BoxesRunTime.boxToCharacter:(C)Ljava/lang/Character;
const #57 = Asciz	scala/collection/MapLike;
const #58 = class	#57;	//  scala/collection/MapLike
const #59 = Asciz	get;
const #60 = Asciz	(Ljava/lang/Object;)Lscala/Option;;
const #61 = NameAndType	#59:#60;//  get:(Ljava/lang/Object;)Lscala/Option;
const #62 = InterfaceMethod	#58.#61;	//  scala/collection/MapLike.get:(Ljava/lang/Object;)Lscala/Option;
const #63 = Asciz	scala/Some;
const #64 = class	#63;	//  scala/Some
const #65 = Asciz	x;
const #66 = NameAndType	#65:#40;//  x:Ljava/lang/Object;
const #67 = Field	#64.#66;	//  scala/Some.x:Ljava/lang/Object;
const #68 = Asciz	java/lang/String;
const #69 = class	#68;	//  java/lang/String
const #70 = Asciz	append;
const #71 = Asciz	(Ljava/lang/String;)Lscala/collection/mutable/StringBuilder;;
const #72 = NameAndType	#70:#71;//  append:(Ljava/lang/String;)Lscala/collection/mutable/StringBuilder;
const #73 = Method	#27.#72;	//  scala/collection/mutable/StringBuilder.append:(Ljava/lang/String;)Lscala/collection/mutable/StringBuilder;
const #74 = Asciz	scala/MatchError;
const #75 = class	#74;	//  scala/MatchError
const #76 = Asciz	scala/Option;
const #77 = class	#76;	//  scala/Option
const #78 = Asciz	toString;
const #79 = Asciz	()Ljava/lang/String;;
const #80 = NameAndType	#78:#79;//  toString:()Ljava/lang/String;
const #81 = Method	#77.#80;	//  scala/Option.toString:()Ljava/lang/String;
const #82 = Asciz	(Ljava/lang/String;)V;
const #83 = NameAndType	#12:#82;//  "<init>":(Ljava/lang/String;)V
const #84 = Method	#75.#83;	//  scala/MatchError."<init>":(Ljava/lang/String;)V
const #85 = Asciz	scala/None$;
const #86 = class	#85;	//  scala/None$
const #87 = Asciz	Lscala/None$;;
const #88 = NameAndType	#45:#87;//  MODULE$:Lscala/None$;
const #89 = Field	#86.#88;	//  scala/None$.MODULE$:Lscala/None$;
const #90 = Asciz	equals;
const #91 = Asciz	(Ljava/lang/Object;)Z;
const #92 = NameAndType	#90:#91;//  equals:(Ljava/lang/Object;)Z
const #93 = Method	#15.#92;	//  java/lang/Object.equals:(Ljava/lang/Object;)Z
const #94 = Asciz	(C)Lscala/collection/mutable/StringBuilder;;
const #95 = NameAndType	#70:#94;//  append:(C)Lscala/collection/mutable/StringBuilder;
const #96 = Method	#27.#95;	//  scala/collection/mutable/StringBuilder.append:(C)Lscala/collection/mutable/StringBuilder;
const #97 = Asciz	s;
const #98 = Asciz	Lscala/collection/mutable/StringBuilder;;
const #99 = Asciz	c;
const #100 = Asciz	C;
const #101 = Asciz	temp36;
const #102 = Asciz	Lscala/Some;;
const #103 = Asciz	temp37;
const #104 = Asciz	Ljava/lang/String;;
const #105 = Asciz	temp35;
const #106 = Asciz	Lscala/Option;;
const #107 = Asciz	curry;
const #108 = Asciz	()Lscala/Function1;;
const #109 = Asciz	(Lscala/Function2;)Lscala/Function1;;
const #110 = NameAndType	#107:#109;//  curry:(Lscala/Function2;)Lscala/Function1;
const #111 = Method	#19.#110;	//  scala/Function2$class.curry:(Lscala/Function2;)Lscala/Function1;
const #112 = Asciz	(Lscala/Function2;)Ljava/lang/String;;
const #113 = NameAndType	#78:#112;//  toString:(Lscala/Function2;)Ljava/lang/String;
const #114 = Method	#19.#113;	//  scala/Function2$class.toString:(Lscala/Function2;)Ljava/lang/String;
const #115 = Asciz	Scala;
const #116 = Asciz	InnerClasses;
const #117 = Asciz	scala/xml/Utility;
const #118 = class	#117;	//  scala/xml/Utility
const #119 = Asciz	$anonfun$escape$2;
const #120 = Asciz	scala/Function2;
const #121 = class	#120;	//  scala/Function2
const #122 = Asciz	scala/ScalaObject;
const #123 = class	#122;	//  scala/ScalaObject
const #124 = Asciz	java/io/Serializable;
const #125 = class	#124;	//  java/io/Serializable

{
public static final long serialVersionUID;

public static {};
  Code:
   Stack=2, Locals=0, Args_size=0
   0:	lconst_0
   1:	putstatic	#11; //Field serialVersionUID:J
   4:	return

public scala.xml.Utility$$anonfun$escape$2();
  Code:
   Stack=1, Locals=1, Args_size=1
   0:	aload_0
   1:	invokespecial	#17; //Method java/lang/Object."<init>":()V
   4:	aload_0
   5:	invokestatic	#23; //Method scala/Function2$class.$init$:(Lscala/Function2;)V
   8:	return
  LineNumberTable: 
   line 110: 0


public final java.lang.Object apply(java.lang.Object, java.lang.Object);
  Code:
   Stack=3, Locals=3, Args_size=3
   0:	aload_0
   1:	aload_1
   2:	checkcast	#27; //class scala/collection/mutable/StringBuilder
   5:	aload_2
   6:	invokestatic	#33; //Method scala/runtime/BoxesRunTime.unboxToChar:(Ljava/lang/Object;)C
   9:	invokevirtual	#36; //Method apply:(Lscala/collection/mutable/StringBuilder;C)Lscala/collection/mutable/StringBuilder;
   12:	areturn
  LineNumberTable: 
   line 110: 0

  LocalVariableTable: 
   Start  Length  Slot  Name   Signature
   0      13      0    this       Lscala/xml/Utility$$anonfun$escape$2;
   0      13      1    v1       Ljava/lang/Object;
   0      13      2    v2       Ljava/lang/Object;


public final scala.collection.mutable.StringBuilder apply(scala.collection.mutable.StringBuilder, char);
  Code:
   Stack=3, Locals=6, Args_size=3
   0:	getstatic	#48; //Field scala/xml/Utility$Escapes$.MODULE$:Lscala/xml/Utility$Escapes$;
   3:	invokevirtual	#52; //Method scala/xml/Utility$Escapes$.escMap:()Lscala/collection/immutable/Map;
   6:	iload_2
   7:	invokestatic	#56; //Method scala/runtime/BoxesRunTime.boxToCharacter:(C)Ljava/lang/Character;
   10:	invokeinterface	#62,  2; //InterfaceMethod scala/collection/MapLike.get:(Ljava/lang/Object;)Lscala/Option;
   15:	astore	5
   17:	aload	5
   19:	instanceof	#64; //class scala/Some
   22:	ifeq	66
   25:	aload	5
   27:	checkcast	#64; //class scala/Some
   30:	astore_3
   31:	aload_3
   32:	getfield	#67; //Field scala/Some.x:Ljava/lang/Object;
   35:	checkcast	#69; //class java/lang/String
   38:	astore	4
   40:	iconst_1
   41:	ifeq	53
   44:	aload_1
   45:	aload	4
   47:	invokevirtual	#73; //Method scala/collection/mutable/StringBuilder.append:(Ljava/lang/String;)Lscala/collection/mutable/StringBuilder;
   50:	goto	99
   53:	new	#75; //class scala/MatchError
   56:	dup
   57:	aload	5
   59:	invokevirtual	#81; //Method scala/Option.toString:()Ljava/lang/String;
   62:	invokespecial	#84; //Method scala/MatchError."<init>":(Ljava/lang/String;)V
   65:	athrow
   66:	getstatic	#89; //Field scala/None$.MODULE$:Lscala/None$;
   69:	dup
   70:	ifnonnull	82
   73:	pop
   74:	aload	5
   76:	ifnull	90
   79:	goto	113
   82:	aload	5
   84:	invokevirtual	#93; //Method java/lang/Object.equals:(Ljava/lang/Object;)Z
   87:	ifeq	113
   90:	iconst_1
   91:	ifeq	100
   94:	aload_1
   95:	iload_2
   96:	invokevirtual	#96; //Method scala/collection/mutable/StringBuilder.append:(C)Lscala/collection/mutable/StringBuilder;
   99:	areturn
   100:	new	#75; //class scala/MatchError
   103:	dup
   104:	aload	5
   106:	invokevirtual	#81; //Method scala/Option.toString:()Ljava/lang/String;
   109:	invokespecial	#84; //Method scala/MatchError."<init>":(Ljava/lang/String;)V
   112:	athrow
   113:	new	#75; //class scala/MatchError
   116:	dup
   117:	aload	5
   119:	invokevirtual	#81; //Method scala/Option.toString:()Ljava/lang/String;
   122:	invokespecial	#84; //Method scala/MatchError."<init>":(Ljava/lang/String;)V
   125:	athrow
  LineNumberTable: 
   line 110: 0
   line 21: 40
   line 111: 44
   line 110: 53
   line 21: 90
   line 112: 94
   line 110: 99

  LocalVariableTable: 
   Start  Length  Slot  Name   Signature
   0      126      0    this       Lscala/xml/Utility$$anonfun$escape$2;
   0      126      1    s       Lscala/collection/mutable/StringBuilder;
   0      126      2    c       C
   31      35      3    temp36       Lscala/Some;
   40      26      4    temp37       Ljava/lang/String;
   17      109      5    temp35       Lscala/Option;


public scala.Function1 curry();
  Code:
   Stack=1, Locals=1, Args_size=1
   0:	aload_0
   1:	invokestatic	#111; //Method scala/Function2$class.curry:(Lscala/Function2;)Lscala/Function1;
   4:	areturn
  LineNumberTable: 
   line 110: 0


public java.lang.String toString();
  Code:
   Stack=1, Locals=1, Args_size=1
   0:	aload_0
   1:	invokestatic	#114; //Method scala/Function2$class.toString:(Lscala/Function2;)Ljava/lang/String;
   4:	areturn
  LineNumberTable: 
   line 110: 0


}

