Compiled from "Xhtml.scala"
public final class scala.xml.Xhtml$$anonfun$toXhtml$2 extends scala.runtime.AbstractFunction1 implements java.io.Serializable
  SourceFile: "Xhtml.scala"
  Scala: length = 0x
   
  InnerClass: 
   public final $anonfun$toXhtml$2=class scala/xml/Xhtml$$anonfun$toXhtml$2 of class scala/xml/Xhtml
  minor version: 0
  major version: 49
  Constant pool:
Asciz	SourceFile;
Asciz	Xhtml.scala;
Asciz	<clinit>;
Asciz	()V;
Asciz	Code;
Asciz	serialVersionUID;
Asciz	J;
Asciz	scala/xml/Xhtml$$anonfun$toXhtml$2;
class	scala/xml/Xhtml$$anonfun$toXhtml$2
NameAndType	serialVersionUID:J
Field	scala/xml/Xhtml$$anonfun$toXhtml$2.serialVersionUID:J
Asciz	nodeSeq$1;
Asciz	Lscala/xml/NodeSeq;;
Asciz	apply;
Asciz	(Lscala/collection/mutable/StringBuilder;)V;
Asciz	LineNumberTable;
NameAndType	nodeSeq$1:Lscala/xml/NodeSeq;
Field	scala/xml/Xhtml$$anonfun$toXhtml$2.nodeSeq$1:Lscala/xml/NodeSeq;
Asciz	scala/xml/Xhtml$;
class	scala/xml/Xhtml$
Asciz	MODULE$;
Asciz	Lscala/xml/Xhtml$;;
NameAndType	MODULE$:Lscala/xml/Xhtml$;
Field	scala/xml/Xhtml$.MODULE$:Lscala/xml/Xhtml$;
Asciz	sequenceToXML$default$2;
Asciz	()Lscala/xml/NamespaceBinding;;
NameAndType	sequenceToXML$default$2:()Lscala/xml/NamespaceBinding;
Method	scala/xml/Xhtml$.sequenceToXML$default$2:()Lscala/xml/NamespaceBinding;
Asciz	sequenceToXML$default$4;
Asciz	()Z;
NameAndType	sequenceToXML$default$4:()Z
Method	scala/xml/Xhtml$.sequenceToXML$default$4:()Z
Asciz	sequenceToXML$default$5;
NameAndType	sequenceToXML$default$5:()Z
Method	scala/xml/Xhtml$.sequenceToXML$default$5:()Z
Asciz	sequenceToXML$default$6;
NameAndType	sequenceToXML$default$6:()Z
Method	scala/xml/Xhtml$.sequenceToXML$default$6:()Z
Asciz	sequenceToXML$default$7;
NameAndType	sequenceToXML$default$7:()Z
Method	scala/xml/Xhtml$.sequenceToXML$default$7:()Z
Asciz	sequenceToXML;
Asciz	(Lscala/collection/Seq;Lscala/xml/NamespaceBinding;Lscala/collection/mutable/StringBuilder;ZZZZ)V;
NameAndType	sequenceToXML:(Lscala/collection/Seq;Lscala/xml/NamespaceBinding;Lscala/collection/mutable/StringBuilder;ZZZZ)V
Method	scala/xml/Xhtml$.sequenceToXML:(Lscala/collection/Seq;Lscala/xml/NamespaceBinding;Lscala/collection/mutable/StringBuilder;ZZZZ)V
Asciz	this;
Asciz	Lscala/xml/Xhtml$$anonfun$toXhtml$2;;
Asciz	x$11;
Asciz	Lscala/collection/Seq;;
Asciz	x$12;
Asciz	Lscala/collection/mutable/StringBuilder;;
Asciz	x$13;
Asciz	Lscala/xml/NamespaceBinding;;
Asciz	x$14;
Asciz	Z;
Asciz	x$15;
Asciz	x$16;
Asciz	x$17;
Asciz	LocalVariableTable;
Asciz	(Ljava/lang/Object;)Ljava/lang/Object;;
Asciz	scala/collection/mutable/StringBuilder;
class	scala/collection/mutable/StringBuilder
NameAndType	apply:(Lscala/collection/mutable/StringBuilder;)V
Method	scala/xml/Xhtml$$anonfun$toXhtml$2.apply:(Lscala/collection/mutable/StringBuilder;)V
Asciz	scala/runtime/BoxedUnit;
class	scala/runtime/BoxedUnit
Asciz	UNIT;
Asciz	Lscala/runtime/BoxedUnit;;
NameAndType	UNIT:Lscala/runtime/BoxedUnit;
Field	scala/runtime/BoxedUnit.UNIT:Lscala/runtime/BoxedUnit;
Asciz	v1;
Asciz	Ljava/lang/Object;;
Asciz	<init>;
Asciz	(Lscala/xml/NodeSeq;)V;
Asciz	scala/runtime/AbstractFunction1;
class	scala/runtime/AbstractFunction1
NameAndType	"<init>":()V
Method	scala/runtime/AbstractFunction1."<init>":()V
Asciz	Scala;
Asciz	InnerClasses;
Asciz	scala/xml/Xhtml;
class	scala/xml/Xhtml
Asciz	$anonfun$toXhtml$2;
Asciz	java/io/Serializable;
class	java/io/Serializable

{
public static final long serialVersionUID;
  Signature: J

private final scala.xml.NodeSeq nodeSeq$1;
  Signature: Lscala/xml/NodeSeq;

public static {};
  Signature: ()V
  Code:
   Stack=2, Locals=0, Args_size=0
	lconst_0
	putstatic	Field serialVersionUID:J
	return
  Labels:

public final void apply(scala.collection.mutable.StringBuilder);
  Signature: (Lscala/collection/mutable/StringBuilder;)V
  Code:
   Stack=8, Locals=9, Args_size=2
	aload_0
	getfield	Field nodeSeq$1:Lscala/xml/NodeSeq;
	astore_2
	aload_1
	astore_3
	getstatic	Field scala/xml/Xhtml$.MODULE$:Lscala/xml/Xhtml$;
	invokevirtual	Method scala/xml/Xhtml$.sequenceToXML$default$2:()Lscala/xml/NamespaceBinding;
	astore	4
	getstatic	Field scala/xml/Xhtml$.MODULE$:Lscala/xml/Xhtml$;
	invokevirtual	Method scala/xml/Xhtml$.sequenceToXML$default$4:()Z
	istore	5
	getstatic	Field scala/xml/Xhtml$.MODULE$:Lscala/xml/Xhtml$;
	invokevirtual	Method scala/xml/Xhtml$.sequenceToXML$default$5:()Z
	istore	6
	getstatic	Field scala/xml/Xhtml$.MODULE$:Lscala/xml/Xhtml$;
	invokevirtual	Method scala/xml/Xhtml$.sequenceToXML$default$6:()Z
	istore	7
	getstatic	Field scala/xml/Xhtml$.MODULE$:Lscala/xml/Xhtml$;
	invokevirtual	Method scala/xml/Xhtml$.sequenceToXML$default$7:()Z
	istore	8
	getstatic	Field scala/xml/Xhtml$.MODULE$:Lscala/xml/Xhtml$;
	aload_2
	aload	4
	aload_3
	iload	5
	iload	6
	iload	7
	iload	8
	invokevirtual	Method scala/xml/Xhtml$.sequenceToXML:(Lscala/collection/Seq;Lscala/xml/NamespaceBinding;Lscala/collection/mutable/StringBuilder;ZZZZ)V
	return
  Labels:
  LocalVariableTable: 
   Start  Length  Slot  Name   Signature
   0      66      0    this       Lscala/xml/Xhtml$$anonfun$toXhtml$2;
   5      60      2    x$11       Lscala/collection/Seq;
   7      58      3    x$12       Lscala/collection/mutable/StringBuilder;
   15      50      4    x$13       Lscala/xml/NamespaceBinding;
   23      42      5    x$14       Z
   31      34      6    x$15       Z
   39      26      7    x$16       Z
   47      18      8    x$17       Z


public final java.lang.Object apply(java.lang.Object);
  Signature: (Ljava/lang/Object;)Ljava/lang/Object;
  Code:
   Stack=2, Locals=2, Args_size=2
	aload_0
	aload_1
	checkcast	class scala/collection/mutable/StringBuilder
	invokevirtual	Method apply:(Lscala/collection/mutable/StringBuilder;)V
	getstatic	Field scala/runtime/BoxedUnit.UNIT:Lscala/runtime/BoxedUnit;
	areturn
  Labels:
  LocalVariableTable: 
   Start  Length  Slot  Name   Signature
   0      12      0    this       Lscala/xml/Xhtml$$anonfun$toXhtml$2;
   0      12      1    v1       Ljava/lang/Object;


public scala.xml.Xhtml$$anonfun$toXhtml$2(scala.xml.NodeSeq);
  Signature: (Lscala/xml/NodeSeq;)V
  Code:
   Stack=2, Locals=2, Args_size=2
	aload_0
	aload_1
	putfield	Field nodeSeq$1:Lscala/xml/NodeSeq;
	aload_0
	invokespecial	Method scala/runtime/AbstractFunction1."<init>":()V
	return
  Labels:

}

