Compiled from "Xhtml.scala"
public final class scala.xml.Xhtml$$anonfun$sequenceToXML$1 extends java.lang.Object implements scala.Function1,scala.ScalaObject,java.io.Serializable
  SourceFile: "Xhtml.scala"
  Scala: length = 0x
   
  InnerClass: 
   public final $anonfun$sequenceToXML$1=class scala/xml/Xhtml$$anonfun$sequenceToXML$1 of class scala/xml/Xhtml
  minor version: 0
  major version: 49
  Constant pool:
Asciz	SourceFile;
Asciz	Xhtml.scala;
Asciz	<clinit>;
Asciz	()V;
Asciz	Code;
Asciz	serialVersionUID;
Asciz	J;
Asciz	scala/xml/Xhtml$$anonfun$sequenceToXML$1;
class	scala/xml/Xhtml$$anonfun$sequenceToXML$1
NameAndType	serialVersionUID:J
Field	scala/xml/Xhtml$$anonfun$sequenceToXML$1.serialVersionUID:J
Asciz	doSpaces$1;
Asciz	Z;
Asciz	sb$2;
Asciz	Lscala/collection/mutable/StringBuilder;;
Asciz	pscope$1;
Asciz	Lscala/xml/NamespaceBinding;;
Asciz	<init>;
Asciz	(Lscala/xml/NamespaceBinding;Lscala/collection/mutable/StringBuilder;Z)V;
Asciz	LineNumberTable;
NameAndType	pscope$1:Lscala/xml/NamespaceBinding;
Field	scala/xml/Xhtml$$anonfun$sequenceToXML$1.pscope$1:Lscala/xml/NamespaceBinding;
NameAndType	sb$2:Lscala/collection/mutable/StringBuilder;
Field	scala/xml/Xhtml$$anonfun$sequenceToXML$1.sb$2:Lscala/collection/mutable/StringBuilder;
NameAndType	doSpaces$1:Z
Field	scala/xml/Xhtml$$anonfun$sequenceToXML$1.doSpaces$1:Z
Asciz	java/lang/Object;
class	java/lang/Object
NameAndType	"<init>":()V
Method	java/lang/Object."<init>":()V
Asciz	scala/Function1$class;
class	scala/Function1$class
Asciz	$init$;
Asciz	(Lscala/Function1;)V;
NameAndType	$init$:(Lscala/Function1;)V
Method	scala/Function1$class.$init$:(Lscala/Function1;)V
Asciz	apply;
Asciz	(Ljava/lang/Object;)Ljava/lang/Object;;
Asciz	scala/xml/Node;
class	scala/xml/Node
Asciz	(Lscala/xml/Node;)Ljava/lang/Object;;
NameAndType	apply:(Lscala/xml/Node;)Ljava/lang/Object;
Method	scala/xml/Xhtml$$anonfun$sequenceToXML$1.apply:(Lscala/xml/Node;)Ljava/lang/Object;
Asciz	this;
Asciz	Lscala/xml/Xhtml$$anonfun$sequenceToXML$1;;
Asciz	v1;
Asciz	Ljava/lang/Object;;
Asciz	LocalVariableTable;
Asciz	scala/xml/Xhtml$;
class	scala/xml/Xhtml$
Asciz	MODULE$;
Asciz	Lscala/xml/Xhtml$;;
NameAndType	MODULE$:Lscala/xml/Xhtml$;
Field	scala/xml/Xhtml$.MODULE$:Lscala/xml/Xhtml$;
Asciz	toXhtml;
Asciz	(Lscala/xml/Node;Lscala/xml/NamespaceBinding;Lscala/collection/mutable/StringBuilder;ZZZZ)V;
NameAndType	toXhtml:(Lscala/xml/Node;Lscala/xml/NamespaceBinding;Lscala/collection/mutable/StringBuilder;ZZZZ)V
Method	scala/xml/Xhtml$.toXhtml:(Lscala/xml/Node;Lscala/xml/NamespaceBinding;Lscala/collection/mutable/StringBuilder;ZZZZ)V
int	32;
Asciz	scala/collection/mutable/StringBuilder;
class	scala/collection/mutable/StringBuilder
Asciz	append;
Asciz	(C)Lscala/collection/mutable/StringBuilder;;
NameAndType	append:(C)Lscala/collection/mutable/StringBuilder;
Method	scala/collection/mutable/StringBuilder.append:(C)Lscala/collection/mutable/StringBuilder;
Asciz	scala/runtime/BoxedUnit;
class	scala/runtime/BoxedUnit
Asciz	UNIT;
Asciz	Lscala/runtime/BoxedUnit;;
NameAndType	UNIT:Lscala/runtime/BoxedUnit;
Field	scala/runtime/BoxedUnit.UNIT:Lscala/runtime/BoxedUnit;
Asciz	c;
Asciz	Lscala/xml/Node;;
Asciz	andThen;
Asciz	(Lscala/Function1;)Lscala/Function1;;
Asciz	(Lscala/Function1;Lscala/Function1;)Lscala/Function1;;
NameAndType	andThen:(Lscala/Function1;Lscala/Function1;)Lscala/Function1;
Method	scala/Function1$class.andThen:(Lscala/Function1;Lscala/Function1;)Lscala/Function1;
Asciz	g;
Asciz	Lscala/Function1;;
Asciz	compose;
NameAndType	compose:(Lscala/Function1;Lscala/Function1;)Lscala/Function1;
Method	scala/Function1$class.compose:(Lscala/Function1;Lscala/Function1;)Lscala/Function1;
Asciz	toString;
Asciz	()Ljava/lang/String;;
Asciz	(Lscala/Function1;)Ljava/lang/String;;
NameAndType	toString:(Lscala/Function1;)Ljava/lang/String;
Method	scala/Function1$class.toString:(Lscala/Function1;)Ljava/lang/String;
Asciz	Scala;
Asciz	InnerClasses;
Asciz	scala/xml/Xhtml;
class	scala/xml/Xhtml
Asciz	$anonfun$sequenceToXML$1;
Asciz	scala/Function1;
class	scala/Function1
Asciz	scala/ScalaObject;
class	scala/ScalaObject
Asciz	java/io/Serializable;
class	java/io/Serializable

{
public static final long serialVersionUID;
  Signature: J

private final boolean doSpaces$1;
  Signature: Z

private final scala.collection.mutable.StringBuilder sb$2;
  Signature: Lscala/collection/mutable/StringBuilder;

private final scala.xml.NamespaceBinding pscope$1;
  Signature: Lscala/xml/NamespaceBinding;

public static {};
  Signature: ()V
  Code:
   Stack=2, Locals=0, Args_size=0
	lconst_0
	putstatic	Field serialVersionUID:J
	return
  Labels:

public scala.xml.Xhtml$$anonfun$sequenceToXML$1(scala.xml.NamespaceBinding, scala.collection.mutable.StringBuilder, boolean);
  Signature: (Lscala/xml/NamespaceBinding;Lscala/collection/mutable/StringBuilder;Z)V
  Code:
   Stack=2, Locals=4, Args_size=4
	aload_0
	aload_1
	putfield	Field pscope$1:Lscala/xml/NamespaceBinding;
	aload_0
	aload_2
	putfield	Field sb$2:Lscala/collection/mutable/StringBuilder;
	aload_0
	iload_3
	putfield	Field doSpaces$1:Z
	aload_0
	invokespecial	Method java/lang/Object."<init>":()V
	aload_0
	invokestatic	Method scala/Function1$class.$init$:(Lscala/Function1;)V
	return
  Labels:

public final java.lang.Object apply(java.lang.Object);
  Signature: (Ljava/lang/Object;)Ljava/lang/Object;
  Code:
   Stack=2, Locals=2, Args_size=2
	aload_0
	aload_1
	checkcast	class scala/xml/Node
	invokevirtual	Method apply:(Lscala/xml/Node;)Ljava/lang/Object;
	areturn
  Labels:
  LocalVariableTable: 
   Start  Length  Slot  Name   Signature
   0      9      0    this       Lscala/xml/Xhtml$$anonfun$sequenceToXML$1;
   0      9      1    v1       Ljava/lang/Object;


public final java.lang.Object apply(scala.xml.Node);
  Signature: (Lscala/xml/Node;)Ljava/lang/Object;
  Code:
   Stack=8, Locals=2, Args_size=2
	getstatic	Field scala/xml/Xhtml$.MODULE$:Lscala/xml/Xhtml$;
	aload_1
	aload_0
	getfield	Field pscope$1:Lscala/xml/NamespaceBinding;
	aload_0
	getfield	Field sb$2:Lscala/collection/mutable/StringBuilder;
	iconst_0
	iconst_0
	iconst_0
	iconst_1
	invokevirtual	Method scala/xml/Xhtml$.toXhtml:(Lscala/xml/Node;Lscala/xml/NamespaceBinding;Lscala/collection/mutable/StringBuilder;ZZZZ)V
	aload_0
	getfield	Field doSpaces$1:Z
	ifeq	l1 // getstatic
	aload_0
	getfield	Field sb$2:Lscala/collection/mutable/StringBuilder;
	ldc	int 32
	invokevirtual	Method scala/collection/mutable/StringBuilder.append:(C)Lscala/collection/mutable/StringBuilder;
	goto	l2 // areturn
l1	getstatic	Field scala/runtime/BoxedUnit.UNIT:Lscala/runtime/BoxedUnit;
l2	areturn
  Labels:
   	l1 = 38 // getstatic
   	l2 = 41 // areturn
  LocalVariableTable: 
   Start  Length  Slot  Name   Signature
   0      42      0    this       Lscala/xml/Xhtml$$anonfun$sequenceToXML$1;
   0      42      1    c       Lscala/xml/Node;


public scala.Function1 andThen(scala.Function1);
  Signature: (Lscala/Function1;)Lscala/Function1;
  Code:
   Stack=2, Locals=2, Args_size=2
	aload_0
	aload_1
	invokestatic	Method scala/Function1$class.andThen:(Lscala/Function1;Lscala/Function1;)Lscala/Function1;
	areturn
  Labels:
  LocalVariableTable: 
   Start  Length  Slot  Name   Signature
   0      6      0    this       Lscala/xml/Xhtml$$anonfun$sequenceToXML$1;
   0      6      1    g       Lscala/Function1;


public scala.Function1 compose(scala.Function1);
  Signature: (Lscala/Function1;)Lscala/Function1;
  Code:
   Stack=2, Locals=2, Args_size=2
	aload_0
	aload_1
	invokestatic	Method scala/Function1$class.compose:(Lscala/Function1;Lscala/Function1;)Lscala/Function1;
	areturn
  Labels:
  LocalVariableTable: 
   Start  Length  Slot  Name   Signature
   0      6      0    this       Lscala/xml/Xhtml$$anonfun$sequenceToXML$1;
   0      6      1    g       Lscala/Function1;


public java.lang.String toString();
  Signature: ()Ljava/lang/String;
  Code:
   Stack=1, Locals=1, Args_size=1
	aload_0
	invokestatic	Method scala/Function1$class.toString:(Lscala/Function1;)Ljava/lang/String;
	areturn
  Labels:

}

