Compiled from "Xhtml.scala"
public final class scala.xml.Xhtml extends java.lang.Object
  SourceFile: "Xhtml.scala"
  ScalaSig: length = 0x4F9
   05 00 FFFFFF81 1A 07 05 01 02 FFFFFF88 02 07 01 05 58 68 74
   6D 6C 0A 02 03 04 01 03 78 6D 6C 0A 01 05 01 05
   73 63 61 6C 61 03 00 10 02 08 09 0D 01 02 06 08
   0A 02 FFFFFF84 FFFFFF80 FFFFFF80 FFFFFF88 02 0B 02 05 58 68 74 6D 6C 13
   03 09 0C 14 10 02 0D 12 0D 01 0E 0A 02 0F 10 01
   04 6C 61 6E 67 0A 01 11 01 04 6A 61 76 61 09 02
   13 0E 02 06 4F 62 6A 65 63 74 10 02 15 16 0D 01
   04 09 02 17 04 02 0B 53 63 61 6C 61 4F 62 6A 65
   63 74 08 05 19 09 FFFFFF84 00 1A 01 06 3C 69 6E 69 74
   3E 14 01 07 08 05 1C 09 FFFFFF84 00 1D 01 07 74 6F 58
   68 74 6D 6C 14 02 1E 25 10 02 1F 22 0E 02 15 20
   09 02 21 04 01 06 50 72 65 64 65 66 09 02 23 24
   02 06 53 74 72 69 6E 67 0A 02 21 04 08 05 26 1B
   FFFFFFC0 00 27 01 04 6E 6F 64 65 10 02 08 28 09 02 29
   02 02 04 4E 6F 64 65 08 05 1C 09 FFFFFF84 00 2B 14 02
   1E 2C 08 05 2D 2A FFFFFFC0 00 2E 01 07 6E 6F 64 65 53
   65 71 10 02 08 2F 09 02 30 02 02 07 4E 6F 64 65
   53 65 71 08 07 32 09 FFFFFFC2 FFFFFF80 FFFFFF84 04 33 01 13 6D 69
   6E 69 6D 69 7A 61 62 6C 65 45 6C 65 6D 65 6E 74
   73 15 01 34 10 03 35 3A 3C 0D 01 36 0A 02 37 38
   01 09 69 6D 6D 75 74 61 62 6C 65 0A 02 39 04 01
   0A 63 6F 6C 6C 65 63 74 69 6F 6E 09 02 3B 36 02
   04 4C 69 73 74 10 02 0D 3D 09 02 23 0E 08 06 3F
   09 FFFFFFA0 FFFFFF80 04 34 01 14 6D 69 6E 69 6D 69 7A 61 62
   6C 65 45 6C 65 6D 65 6E 74 73 20 08 05 1C 09 FFFFFF84
   00 41 14 08 42 45 47 4C 5A 5F 61 63 10 02 15 43
   09 02 44 04 02 04 55 6E 69 74 08 05 46 40 FFFFFFC0 00
   27 01 01 78 08 07 48 40 FFFFFF90 FFFFFF80 FFFFFFC0 00 49 01 06 70
   73 63 6F 70 65 10 02 08 4A 09 02 4B 02 02 10 4E
   61 6D 65 73 70 61 63 65 42 69 6E 64 69 6E 67 08
   07 4D 40 FFFFFF90 FFFFFF80 FFFFFFC0 00 4E 01 02 73 62 10 02 4F 57
   0E 02 50 55 0E 02 51 54 0D 01 52 0A 02 53 06 01
   06 3C 72 6F 6F 74 3E 09 01 05 09 02 56 04 01 07
   70 61 63 6B 61 67 65 09 02 58 59 02 0D 53 74 72
   69 6E 67 42 75 69 6C 64 65 72 0A 02 56 04 08 07
   5B 40 FFFFFF90 FFFFFF80 FFFFFFC0 00 5C 01 0D 73 74 72 69 70 43 6F
   6D 6D 65 6E 74 73 10 02 15 5D 09 02 5E 04 02 07
   42 6F 6F 6C 65 61 6E 08 07 60 40 FFFFFF90 FFFFFF80 FFFFFFC0 00 5C
   01 0E 64 65 63 6F 64 65 45 6E 74 69 74 69 65 73
   08 07 62 40 FFFFFF90 FFFFFF80 FFFFFFC0 00 5C 01 12 70 72 65 73 65
   72 76 65 57 68 69 74 65 73 70 61 63 65 08 07 64
   40 FFFFFF90 FFFFFF80 FFFFFFC0 00 5C 01 0C 6D 69 6E 69 6D 69 7A 65
   54 61 67 73 08 05 66 09 FFFFFF84 00 67 01 0D 73 65 71
   75 65 6E 63 65 54 6F 58 4D 4C 14 08 42 68 6D 6E
   6F 70 71 72 08 05 69 65 FFFFFFC0 00 6A 01 08 63 68 69
   6C 64 72 65 6E 10 03 4F 6B 27 09 02 6C 59 02 03
   53 65 71 08 07 48 65 FFFFFF90 FFFFFF80 FFFFFFC0 00 49 08 07 4D 65
   FFFFFF90 FFFFFF80 FFFFFFC0 00 4E 08 07 5B 65 FFFFFF90 FFFFFF80 FFFFFFC0 00 5C 08 07
   60 65 FFFFFF90 FFFFFF80 FFFFFFC0 00 5C 08 07 62 65 FFFFFF90 FFFFFF80 FFFFFFC0 00 5C
   08 07 64 65 FFFFFF90 FFFFFF80 FFFFFFC0 00 5C 08 07 74 09 FFFFFF91 FFFFFF80 FFFFFF84
   00 75 01 11 74 6F 58 68 74 6D 6C 24 64 65 66 61
   75 6C 74 24 32 15 01 76 2A 02 49 77 2B 01 78 10
   02 79 7E 0D 01 7A 0A 02 7B 7C 01 09 75 6E 63 68
   65 63 6B 65 64 0A 02 7D 04 01 0A 61 6E 6E 6F 74
   61 74 69 6F 6E 09 02 7F 7A 02 11 75 6E 63 68 65
   63 6B 65 64 56 61 72 69 61 6E 63 65 08 09 FFFFFF81 01
   09 FFFFFF91 FFFFFF80 FFFFFF84 00 FFFFFF81 02 01 11 74 6F 58 68 74 6D 6C
   24 64 65 66 61 75 6C 74 24 33 15 02 FFFFFF81 03 2A 02
   4E 77 08 09 FFFFFF81 05 09 FFFFFF91 FFFFFF80 FFFFFF84 00 FFFFFF81 06 01 11 74
   6F 58 68 74 6D 6C 24 64 65 66 61 75 6C 74 24 34
   15 02 FFFFFF81 07 2A 02 5C 77 08 09 FFFFFF81 09 09 FFFFFF91 FFFFFF80 FFFFFF84
   00 FFFFFF81 06 01 11 74 6F 58 68 74 6D 6C 24 64 65 66
   61 75 6C 74 24 35 08 09 FFFFFF81 0B 09 FFFFFF91 FFFFFF80 FFFFFF84 00 FFFFFF81
   06 01 11 74 6F 58 68 74 6D 6C 24 64 65 66 61 75
   6C 74 24 36 08 09 FFFFFF81 0D 09 FFFFFF91 FFFFFF80 FFFFFF84 00 FFFFFF81 06 01
   11 74 6F 58 68 74 6D 6C 24 64 65 66 61 75 6C 74
   24 37 08 08 FFFFFF81 0F 09 FFFFFF91 FFFFFF80 FFFFFF84 00 75 01 17 73 65
   71 75 65 6E 63 65 54 6F 58 4D 4C 24 64 65 66 61
   75 6C 74 24 32 08 09 FFFFFF81 11 09 FFFFFF91 FFFFFF80 FFFFFF84 00 FFFFFF81 02
   01 17 73 65 71 75 65 6E 63 65 54 6F 58 4D 4C 24
   64 65 66 61 75 6C 74 24 33 08 09 FFFFFF81 13 09 FFFFFF91 FFFFFF80
   FFFFFF84 00 FFFFFF81 06 01 17 73 65 71 75 65 6E 63 65 54 6F
   58 4D 4C 24 64 65 66 61 75 6C 74 24 34 08 09 FFFFFF81
   15 09 FFFFFF91 FFFFFF80 FFFFFF84 00 FFFFFF81 06 01 17 73 65 71 75 65 6E
   63 65 54 6F 58 4D 4C 24 64 65 66 61 75 6C 74 24
   35 08 09 FFFFFF81 17 09 FFFFFF91 FFFFFF80 FFFFFF84 00 FFFFFF81 06 01 17 73 65
   71 75 65 6E 63 65 54 6F 58 4D 4C 24 64 65 66 61
   75 6C 74 24 36 08 09 FFFFFF81 19 09 FFFFFF91 FFFFFF80 FFFFFF84 00 FFFFFF81 06
   01 17 73 65 71 75 65 6E 63 65 54 6F 58 4D 4C 24
   64 65 66 61 75 6C 74 24 37 
  InnerClass: 
   public final $anonfun$1=class scala/xml/Xhtml$$anonfun$1 of class scala/xml/Xhtml
   public final $anonfun$toXhtml$3=class scala/xml/Xhtml$$anonfun$toXhtml$3 of class scala/xml/Xhtml
   public final $anonfun$toXhtml$2=class scala/xml/Xhtml$$anonfun$toXhtml$2 of class scala/xml/Xhtml
   public final $anonfun$toXhtml$1=class scala/xml/Xhtml$$anonfun$toXhtml$1 of class scala/xml/Xhtml
   public final $anonfun$sequenceToXML$1=class scala/xml/Xhtml$$anonfun$sequenceToXML$1 of class scala/xml/Xhtml
  minor version: 0
  major version: 49
  Constant pool:
Asciz	SourceFile;
Asciz	Xhtml.scala;
Asciz	sequenceToXML$default$7;
Asciz	()Z;
Asciz	Code;
Asciz	scala/xml/Xhtml$;
class	scala/xml/Xhtml$
Asciz	MODULE$;
Asciz	Lscala/xml/Xhtml$;;
NameAndType	MODULE$:Lscala/xml/Xhtml$;
Field	scala/xml/Xhtml$.MODULE$:Lscala/xml/Xhtml$;
NameAndType	sequenceToXML$default$7:()Z
Method	scala/xml/Xhtml$.sequenceToXML$default$7:()Z
Asciz	sequenceToXML$default$6;
NameAndType	sequenceToXML$default$6:()Z
Method	scala/xml/Xhtml$.sequenceToXML$default$6:()Z
Asciz	sequenceToXML$default$5;
NameAndType	sequenceToXML$default$5:()Z
Method	scala/xml/Xhtml$.sequenceToXML$default$5:()Z
Asciz	sequenceToXML$default$4;
NameAndType	sequenceToXML$default$4:()Z
Method	scala/xml/Xhtml$.sequenceToXML$default$4:()Z
Asciz	sequenceToXML$default$3;
Asciz	()Lscala/collection/mutable/StringBuilder;;
NameAndType	sequenceToXML$default$3:()Lscala/collection/mutable/StringBuilder;
Method	scala/xml/Xhtml$.sequenceToXML$default$3:()Lscala/collection/mutable/StringBuilder;
Asciz	sequenceToXML$default$2;
Asciz	()Lscala/xml/NamespaceBinding;;
NameAndType	sequenceToXML$default$2:()Lscala/xml/NamespaceBinding;
Method	scala/xml/Xhtml$.sequenceToXML$default$2:()Lscala/xml/NamespaceBinding;
Asciz	toXhtml$default$7;
NameAndType	toXhtml$default$7:()Z
Method	scala/xml/Xhtml$.toXhtml$default$7:()Z
Asciz	toXhtml$default$6;
NameAndType	toXhtml$default$6:()Z
Method	scala/xml/Xhtml$.toXhtml$default$6:()Z
Asciz	toXhtml$default$5;
NameAndType	toXhtml$default$5:()Z
Method	scala/xml/Xhtml$.toXhtml$default$5:()Z
Asciz	toXhtml$default$4;
NameAndType	toXhtml$default$4:()Z
Method	scala/xml/Xhtml$.toXhtml$default$4:()Z
Asciz	toXhtml$default$3;
NameAndType	toXhtml$default$3:()Lscala/collection/mutable/StringBuilder;
Method	scala/xml/Xhtml$.toXhtml$default$3:()Lscala/collection/mutable/StringBuilder;
Asciz	toXhtml$default$2;
NameAndType	toXhtml$default$2:()Lscala/xml/NamespaceBinding;
Method	scala/xml/Xhtml$.toXhtml$default$2:()Lscala/xml/NamespaceBinding;
Asciz	sequenceToXML;
Asciz	(Lscala/collection/Seq;Lscala/xml/NamespaceBinding;Lscala/collection/mutable/StringBuilder;ZZZZ)V;
NameAndType	sequenceToXML:(Lscala/collection/Seq;Lscala/xml/NamespaceBinding;Lscala/collection/mutable/StringBuilder;ZZZZ)V
Method	scala/xml/Xhtml$.sequenceToXML:(Lscala/collection/Seq;Lscala/xml/NamespaceBinding;Lscala/collection/mutable/StringBuilder;ZZZZ)V
Asciz	(Lscala/collection/Seq<Lscala/xml/Node;>;Lscala/xml/NamespaceBinding;Lscala/collection/mutable/StringBuilder;ZZZZ)V;
Asciz	Signature;
Asciz	toXhtml;
Asciz	(Lscala/xml/Node;Lscala/xml/NamespaceBinding;Lscala/collection/mutable/StringBuilder;ZZZZ)V;
NameAndType	toXhtml:(Lscala/xml/Node;Lscala/xml/NamespaceBinding;Lscala/collection/mutable/StringBuilder;ZZZZ)V
Method	scala/xml/Xhtml$.toXhtml:(Lscala/xml/Node;Lscala/xml/NamespaceBinding;Lscala/collection/mutable/StringBuilder;ZZZZ)V
Asciz	(Lscala/xml/NodeSeq;)Ljava/lang/String;;
NameAndType	toXhtml:(Lscala/xml/NodeSeq;)Ljava/lang/String;
Method	scala/xml/Xhtml$.toXhtml:(Lscala/xml/NodeSeq;)Ljava/lang/String;
Asciz	(Lscala/xml/Node;)Ljava/lang/String;;
NameAndType	toXhtml:(Lscala/xml/Node;)Ljava/lang/String;
Method	scala/xml/Xhtml$.toXhtml:(Lscala/xml/Node;)Ljava/lang/String;
Asciz	ScalaSig;
Asciz	InnerClasses;
Asciz	scala/xml/Xhtml$$anonfun$1;
class	scala/xml/Xhtml$$anonfun$1
Asciz	scala/xml/Xhtml;
class	scala/xml/Xhtml
Asciz	$anonfun$1;
Asciz	scala/xml/Xhtml$$anonfun$toXhtml$3;
class	scala/xml/Xhtml$$anonfun$toXhtml$3
Asciz	$anonfun$toXhtml$3;
Asciz	scala/xml/Xhtml$$anonfun$toXhtml$2;
class	scala/xml/Xhtml$$anonfun$toXhtml$2
Asciz	$anonfun$toXhtml$2;
Asciz	scala/xml/Xhtml$$anonfun$toXhtml$1;
class	scala/xml/Xhtml$$anonfun$toXhtml$1
Asciz	$anonfun$toXhtml$1;
Asciz	scala/xml/Xhtml$$anonfun$sequenceToXML$1;
class	scala/xml/Xhtml$$anonfun$sequenceToXML$1
Asciz	$anonfun$sequenceToXML$1;
Asciz	java/lang/Object;
class	java/lang/Object

{
public static final boolean sequenceToXML$default$7();
  Signature: ()Z
  Code:
   Stack=1, Locals=0, Args_size=0
	getstatic	Field scala/xml/Xhtml$.MODULE$:Lscala/xml/Xhtml$;
	invokevirtual	Method scala/xml/Xhtml$.sequenceToXML$default$7:()Z
	ireturn
  Labels:

public static final boolean sequenceToXML$default$6();
  Signature: ()Z
  Code:
   Stack=1, Locals=0, Args_size=0
	getstatic	Field scala/xml/Xhtml$.MODULE$:Lscala/xml/Xhtml$;
	invokevirtual	Method scala/xml/Xhtml$.sequenceToXML$default$6:()Z
	ireturn
  Labels:

public static final boolean sequenceToXML$default$5();
  Signature: ()Z
  Code:
   Stack=1, Locals=0, Args_size=0
	getstatic	Field scala/xml/Xhtml$.MODULE$:Lscala/xml/Xhtml$;
	invokevirtual	Method scala/xml/Xhtml$.sequenceToXML$default$5:()Z
	ireturn
  Labels:

public static final boolean sequenceToXML$default$4();
  Signature: ()Z
  Code:
   Stack=1, Locals=0, Args_size=0
	getstatic	Field scala/xml/Xhtml$.MODULE$:Lscala/xml/Xhtml$;
	invokevirtual	Method scala/xml/Xhtml$.sequenceToXML$default$4:()Z
	ireturn
  Labels:

public static final scala.collection.mutable.StringBuilder sequenceToXML$default$3();
  Signature: ()Lscala/collection/mutable/StringBuilder;
  Code:
   Stack=1, Locals=0, Args_size=0
	getstatic	Field scala/xml/Xhtml$.MODULE$:Lscala/xml/Xhtml$;
	invokevirtual	Method scala/xml/Xhtml$.sequenceToXML$default$3:()Lscala/collection/mutable/StringBuilder;
	areturn
  Labels:

public static final scala.xml.NamespaceBinding sequenceToXML$default$2();
  Signature: ()Lscala/xml/NamespaceBinding;
  Code:
   Stack=1, Locals=0, Args_size=0
	getstatic	Field scala/xml/Xhtml$.MODULE$:Lscala/xml/Xhtml$;
	invokevirtual	Method scala/xml/Xhtml$.sequenceToXML$default$2:()Lscala/xml/NamespaceBinding;
	areturn
  Labels:

public static final boolean toXhtml$default$7();
  Signature: ()Z
  Code:
   Stack=1, Locals=0, Args_size=0
	getstatic	Field scala/xml/Xhtml$.MODULE$:Lscala/xml/Xhtml$;
	invokevirtual	Method scala/xml/Xhtml$.toXhtml$default$7:()Z
	ireturn
  Labels:

public static final boolean toXhtml$default$6();
  Signature: ()Z
  Code:
   Stack=1, Locals=0, Args_size=0
	getstatic	Field scala/xml/Xhtml$.MODULE$:Lscala/xml/Xhtml$;
	invokevirtual	Method scala/xml/Xhtml$.toXhtml$default$6:()Z
	ireturn
  Labels:

public static final boolean toXhtml$default$5();
  Signature: ()Z
  Code:
   Stack=1, Locals=0, Args_size=0
	getstatic	Field scala/xml/Xhtml$.MODULE$:Lscala/xml/Xhtml$;
	invokevirtual	Method scala/xml/Xhtml$.toXhtml$default$5:()Z
	ireturn
  Labels:

public static final boolean toXhtml$default$4();
  Signature: ()Z
  Code:
   Stack=1, Locals=0, Args_size=0
	getstatic	Field scala/xml/Xhtml$.MODULE$:Lscala/xml/Xhtml$;
	invokevirtual	Method scala/xml/Xhtml$.toXhtml$default$4:()Z
	ireturn
  Labels:

public static final scala.collection.mutable.StringBuilder toXhtml$default$3();
  Signature: ()Lscala/collection/mutable/StringBuilder;
  Code:
   Stack=1, Locals=0, Args_size=0
	getstatic	Field scala/xml/Xhtml$.MODULE$:Lscala/xml/Xhtml$;
	invokevirtual	Method scala/xml/Xhtml$.toXhtml$default$3:()Lscala/collection/mutable/StringBuilder;
	areturn
  Labels:

public static final scala.xml.NamespaceBinding toXhtml$default$2();
  Signature: ()Lscala/xml/NamespaceBinding;
  Code:
   Stack=1, Locals=0, Args_size=0
	getstatic	Field scala/xml/Xhtml$.MODULE$:Lscala/xml/Xhtml$;
	invokevirtual	Method scala/xml/Xhtml$.toXhtml$default$2:()Lscala/xml/NamespaceBinding;
	areturn
  Labels:

public static final void sequenceToXML(scala.collection.Seq, scala.xml.NamespaceBinding, scala.collection.mutable.StringBuilder, boolean, boolean, boolean, boolean);
  Signature: (Lscala/collection/Seq;Lscala/xml/NamespaceBinding;Lscala/collection/mutable/StringBuilder;ZZZZ)V
  Code:
   Stack=8, Locals=7, Args_size=7
	getstatic	Field scala/xml/Xhtml$.MODULE$:Lscala/xml/Xhtml$;
	aload_0
	aload_1
	aload_2
	iload_3
	iload	4
	iload	5
	iload	6
	invokevirtual	Method scala/xml/Xhtml$.sequenceToXML:(Lscala/collection/Seq;Lscala/xml/NamespaceBinding;Lscala/collection/mutable/StringBuilder;ZZZZ)V
	return
  Labels:
  Signature: length = 0x2
   00 35 

public static final void toXhtml(scala.xml.Node, scala.xml.NamespaceBinding, scala.collection.mutable.StringBuilder, boolean, boolean, boolean, boolean);
  Signature: (Lscala/xml/Node;Lscala/xml/NamespaceBinding;Lscala/collection/mutable/StringBuilder;ZZZZ)V
  Code:
   Stack=8, Locals=7, Args_size=7
	getstatic	Field scala/xml/Xhtml$.MODULE$:Lscala/xml/Xhtml$;
	aload_0
	aload_1
	aload_2
	iload_3
	iload	4
	iload	5
	iload	6
	invokevirtual	Method scala/xml/Xhtml$.toXhtml:(Lscala/xml/Node;Lscala/xml/NamespaceBinding;Lscala/collection/mutable/StringBuilder;ZZZZ)V
	return
  Labels:

public static final java.lang.String toXhtml(scala.xml.NodeSeq);
  Signature: (Lscala/xml/NodeSeq;)Ljava/lang/String;
  Code:
   Stack=2, Locals=1, Args_size=1
	getstatic	Field scala/xml/Xhtml$.MODULE$:Lscala/xml/Xhtml$;
	aload_0
	invokevirtual	Method scala/xml/Xhtml$.toXhtml:(Lscala/xml/NodeSeq;)Ljava/lang/String;
	areturn
  Labels:

public static final java.lang.String toXhtml(scala.xml.Node);
  Signature: (Lscala/xml/Node;)Ljava/lang/String;
  Code:
   Stack=2, Locals=1, Args_size=1
	getstatic	Field scala/xml/Xhtml$.MODULE$:Lscala/xml/Xhtml$;
	aload_0
	invokevirtual	Method scala/xml/Xhtml$.toXhtml:(Lscala/xml/Node;)Ljava/lang/String;
	areturn
  Labels:

}

