Compiled from "Xhtml.scala"
public final class scala.xml.Xhtml$$anonfun$sequenceToXML$1 extends java.lang.Object implements scala.Function1,scala.ScalaObject,java.io.Serializable
  SourceFile: "Xhtml.scala"
  Scala: length = 0x
   
  InnerClass: 
   public final #101= #14 of #100; //$anonfun$sequenceToXML$1=class scala/xml/Xhtml$$anonfun$sequenceToXML$1 of class scala/xml/Xhtml
  minor version: 0
  major version: 49
  Constant pool:
const #1 = Asciz	SourceFile;
const #2 = Asciz	Xhtml.scala;
const #3 = Asciz	doSpaces$1;
const #4 = Asciz	Z;
const #5 = Asciz	sb$2;
const #6 = Asciz	Lscala/collection/mutable/StringBuilder;;
const #7 = Asciz	pscope$1;
const #8 = Asciz	Lscala/xml/NamespaceBinding;;
const #9 = Asciz	<init>;
const #10 = Asciz	(Lscala/xml/NamespaceBinding;Lscala/collection/mutable/StringBuilder;Z)V;
const #11 = Asciz	Code;
const #12 = Asciz	LineNumberTable;
const #13 = Asciz	scala/xml/Xhtml$$anonfun$sequenceToXML$1;
const #14 = class	#13;	//  scala/xml/Xhtml$$anonfun$sequenceToXML$1
const #15 = NameAndType	#7:#8;//  pscope$1:Lscala/xml/NamespaceBinding;
const #16 = Field	#14.#15;	//  scala/xml/Xhtml$$anonfun$sequenceToXML$1.pscope$1:Lscala/xml/NamespaceBinding;
const #17 = NameAndType	#5:#6;//  sb$2:Lscala/collection/mutable/StringBuilder;
const #18 = Field	#14.#17;	//  scala/xml/Xhtml$$anonfun$sequenceToXML$1.sb$2:Lscala/collection/mutable/StringBuilder;
const #19 = NameAndType	#3:#4;//  doSpaces$1:Z
const #20 = Field	#14.#19;	//  scala/xml/Xhtml$$anonfun$sequenceToXML$1.doSpaces$1:Z
const #21 = Asciz	java/lang/Object;
const #22 = class	#21;	//  java/lang/Object
const #23 = Asciz	()V;
const #24 = NameAndType	#9:#23;//  "<init>":()V
const #25 = Method	#22.#24;	//  java/lang/Object."<init>":()V
const #26 = Asciz	scala/Function1$class;
const #27 = class	#26;	//  scala/Function1$class
const #28 = Asciz	$init$;
const #29 = Asciz	(Lscala/Function1;)V;
const #30 = NameAndType	#28:#29;//  $init$:(Lscala/Function1;)V
const #31 = Method	#27.#30;	//  scala/Function1$class.$init$:(Lscala/Function1;)V
const #32 = Asciz	apply;
const #33 = Asciz	(Ljava/lang/Object;)Ljava/lang/Object;;
const #34 = Asciz	scala/xml/Node;
const #35 = class	#34;	//  scala/xml/Node
const #36 = Asciz	(Lscala/xml/Node;)Ljava/lang/Object;;
const #37 = NameAndType	#32:#36;//  apply:(Lscala/xml/Node;)Ljava/lang/Object;
const #38 = Method	#14.#37;	//  scala/xml/Xhtml$$anonfun$sequenceToXML$1.apply:(Lscala/xml/Node;)Ljava/lang/Object;
const #39 = Asciz	this;
const #40 = Asciz	Lscala/xml/Xhtml$$anonfun$sequenceToXML$1;;
const #41 = Asciz	v1;
const #42 = Asciz	Ljava/lang/Object;;
const #43 = Asciz	LocalVariableTable;
const #44 = Asciz	scala/xml/Xhtml$;
const #45 = class	#44;	//  scala/xml/Xhtml$
const #46 = Asciz	MODULE$;
const #47 = Asciz	Lscala/xml/Xhtml$;;
const #48 = NameAndType	#46:#47;//  MODULE$:Lscala/xml/Xhtml$;
const #49 = Field	#45.#48;	//  scala/xml/Xhtml$.MODULE$:Lscala/xml/Xhtml$;
const #50 = Asciz	toXhtml$default$4;
const #51 = Asciz	()Z;
const #52 = NameAndType	#50:#51;//  toXhtml$default$4:()Z
const #53 = Method	#45.#52;	//  scala/xml/Xhtml$.toXhtml$default$4:()Z
const #54 = Asciz	toXhtml$default$5;
const #55 = NameAndType	#54:#51;//  toXhtml$default$5:()Z
const #56 = Method	#45.#55;	//  scala/xml/Xhtml$.toXhtml$default$5:()Z
const #57 = Asciz	toXhtml$default$6;
const #58 = NameAndType	#57:#51;//  toXhtml$default$6:()Z
const #59 = Method	#45.#58;	//  scala/xml/Xhtml$.toXhtml$default$6:()Z
const #60 = Asciz	toXhtml$default$7;
const #61 = NameAndType	#60:#51;//  toXhtml$default$7:()Z
const #62 = Method	#45.#61;	//  scala/xml/Xhtml$.toXhtml$default$7:()Z
const #63 = Asciz	toXhtml;
const #64 = Asciz	(Lscala/xml/Node;Lscala/xml/NamespaceBinding;Lscala/collection/mutable/StringBuilder;ZZZZ)V;
const #65 = NameAndType	#63:#64;//  toXhtml:(Lscala/xml/Node;Lscala/xml/NamespaceBinding;Lscala/collection/mutable/StringBuilder;ZZZZ)V
const #66 = Method	#45.#65;	//  scala/xml/Xhtml$.toXhtml:(Lscala/xml/Node;Lscala/xml/NamespaceBinding;Lscala/collection/mutable/StringBuilder;ZZZZ)V
const #67 = int	32;
const #68 = Asciz	scala/collection/mutable/StringBuilder;
const #69 = class	#68;	//  scala/collection/mutable/StringBuilder
const #70 = Asciz	append;
const #71 = Asciz	(C)Lscala/collection/mutable/StringBuilder;;
const #72 = NameAndType	#70:#71;//  append:(C)Lscala/collection/mutable/StringBuilder;
const #73 = Method	#69.#72;	//  scala/collection/mutable/StringBuilder.append:(C)Lscala/collection/mutable/StringBuilder;
const #74 = Asciz	scala/runtime/BoxedUnit;
const #75 = class	#74;	//  scala/runtime/BoxedUnit
const #76 = Asciz	UNIT;
const #77 = Asciz	Lscala/runtime/BoxedUnit;;
const #78 = NameAndType	#76:#77;//  UNIT:Lscala/runtime/BoxedUnit;
const #79 = Field	#75.#78;	//  scala/runtime/BoxedUnit.UNIT:Lscala/runtime/BoxedUnit;
const #80 = Asciz	c;
const #81 = Asciz	Lscala/xml/Node;;
const #82 = Asciz	andThen;
const #83 = Asciz	(Lscala/Function1;)Lscala/Function1;;
const #84 = Asciz	(Lscala/Function1;Lscala/Function1;)Lscala/Function1;;
const #85 = NameAndType	#82:#84;//  andThen:(Lscala/Function1;Lscala/Function1;)Lscala/Function1;
const #86 = Method	#27.#85;	//  scala/Function1$class.andThen:(Lscala/Function1;Lscala/Function1;)Lscala/Function1;
const #87 = Asciz	g;
const #88 = Asciz	Lscala/Function1;;
const #89 = Asciz	compose;
const #90 = NameAndType	#89:#84;//  compose:(Lscala/Function1;Lscala/Function1;)Lscala/Function1;
const #91 = Method	#27.#90;	//  scala/Function1$class.compose:(Lscala/Function1;Lscala/Function1;)Lscala/Function1;
const #92 = Asciz	toString;
const #93 = Asciz	()Ljava/lang/String;;
const #94 = Asciz	(Lscala/Function1;)Ljava/lang/String;;
const #95 = NameAndType	#92:#94;//  toString:(Lscala/Function1;)Ljava/lang/String;
const #96 = Method	#27.#95;	//  scala/Function1$class.toString:(Lscala/Function1;)Ljava/lang/String;
const #97 = Asciz	Scala;
const #98 = Asciz	InnerClasses;
const #99 = Asciz	scala/xml/Xhtml;
const #100 = class	#99;	//  scala/xml/Xhtml
const #101 = Asciz	$anonfun$sequenceToXML$1;
const #102 = Asciz	scala/Function1;
const #103 = class	#102;	//  scala/Function1
const #104 = Asciz	scala/ScalaObject;
const #105 = class	#104;	//  scala/ScalaObject
const #106 = Asciz	java/io/Serializable;
const #107 = class	#106;	//  java/io/Serializable

{
public scala.xml.Xhtml$$anonfun$sequenceToXML$1(scala.xml.NamespaceBinding, scala.collection.mutable.StringBuilder, boolean);
  Code:
   Stack=2, Locals=4, Args_size=4
   0:	aload_0
   1:	aload_1
   2:	putfield	#16; //Field pscope$1:Lscala/xml/NamespaceBinding;
   5:	aload_0
   6:	aload_2
   7:	putfield	#18; //Field sb$2:Lscala/collection/mutable/StringBuilder;
   10:	aload_0
   11:	iload_3
   12:	putfield	#20; //Field doSpaces$1:Z
   15:	aload_0
   16:	invokespecial	#25; //Method java/lang/Object."<init>":()V
   19:	aload_0
   20:	invokestatic	#31; //Method scala/Function1$class.$init$:(Lscala/Function1;)V
   23:	return
  LineNumberTable: 
   line 91: 0


public final java.lang.Object apply(java.lang.Object);
  Code:
   Stack=2, Locals=2, Args_size=2
   0:	aload_0
   1:	aload_1
   2:	checkcast	#35; //class scala/xml/Node
   5:	invokevirtual	#38; //Method apply:(Lscala/xml/Node;)Ljava/lang/Object;
   8:	areturn
  LineNumberTable: 
   line 91: 0

  LocalVariableTable: 
   Start  Length  Slot  Name   Signature
   0      9      0    this       Lscala/xml/Xhtml$$anonfun$sequenceToXML$1;
   0      9      1    v1       Ljava/lang/Object;


public final java.lang.Object apply(scala.xml.Node);
  Code:
   Stack=8, Locals=2, Args_size=2
   0:	getstatic	#49; //Field scala/xml/Xhtml$.MODULE$:Lscala/xml/Xhtml$;
   3:	aload_1
   4:	aload_0
   5:	getfield	#16; //Field pscope$1:Lscala/xml/NamespaceBinding;
   8:	aload_0
   9:	getfield	#18; //Field sb$2:Lscala/collection/mutable/StringBuilder;
   12:	getstatic	#49; //Field scala/xml/Xhtml$.MODULE$:Lscala/xml/Xhtml$;
   15:	invokevirtual	#53; //Method scala/xml/Xhtml$.toXhtml$default$4:()Z
   18:	getstatic	#49; //Field scala/xml/Xhtml$.MODULE$:Lscala/xml/Xhtml$;
   21:	invokevirtual	#56; //Method scala/xml/Xhtml$.toXhtml$default$5:()Z
   24:	getstatic	#49; //Field scala/xml/Xhtml$.MODULE$:Lscala/xml/Xhtml$;
   27:	invokevirtual	#59; //Method scala/xml/Xhtml$.toXhtml$default$6:()Z
   30:	getstatic	#49; //Field scala/xml/Xhtml$.MODULE$:Lscala/xml/Xhtml$;
   33:	invokevirtual	#62; //Method scala/xml/Xhtml$.toXhtml$default$7:()Z
   36:	invokevirtual	#66; //Method scala/xml/Xhtml$.toXhtml:(Lscala/xml/Node;Lscala/xml/NamespaceBinding;Lscala/collection/mutable/StringBuilder;ZZZZ)V
   39:	aload_0
   40:	getfield	#20; //Field doSpaces$1:Z
   43:	ifeq	58
   46:	aload_0
   47:	getfield	#18; //Field sb$2:Lscala/collection/mutable/StringBuilder;
   50:	ldc	#67; //int 32
   52:	invokevirtual	#73; //Method scala/collection/mutable/StringBuilder.append:(C)Lscala/collection/mutable/StringBuilder;
   55:	goto	61
   58:	getstatic	#79; //Field scala/runtime/BoxedUnit.UNIT:Lscala/runtime/BoxedUnit;
   61:	areturn
  LineNumberTable: 
   line 92: 0
   line 93: 39
   line 91: 61

  LocalVariableTable: 
   Start  Length  Slot  Name   Signature
   0      62      0    this       Lscala/xml/Xhtml$$anonfun$sequenceToXML$1;
   0      62      1    c       Lscala/xml/Node;


public scala.Function1 andThen(scala.Function1);
  Code:
   Stack=2, Locals=2, Args_size=2
   0:	aload_0
   1:	aload_1
   2:	invokestatic	#86; //Method scala/Function1$class.andThen:(Lscala/Function1;Lscala/Function1;)Lscala/Function1;
   5:	areturn
  LineNumberTable: 
   line 91: 0

  LocalVariableTable: 
   Start  Length  Slot  Name   Signature
   0      6      0    this       Lscala/xml/Xhtml$$anonfun$sequenceToXML$1;
   0      6      1    g       Lscala/Function1;


public scala.Function1 compose(scala.Function1);
  Code:
   Stack=2, Locals=2, Args_size=2
   0:	aload_0
   1:	aload_1
   2:	invokestatic	#91; //Method scala/Function1$class.compose:(Lscala/Function1;Lscala/Function1;)Lscala/Function1;
   5:	areturn
  LineNumberTable: 
   line 91: 0

  LocalVariableTable: 
   Start  Length  Slot  Name   Signature
   0      6      0    this       Lscala/xml/Xhtml$$anonfun$sequenceToXML$1;
   0      6      1    g       Lscala/Function1;


public java.lang.String toString();
  Code:
   Stack=1, Locals=1, Args_size=1
   0:	aload_0
   1:	invokestatic	#96; //Method scala/Function1$class.toString:(Lscala/Function1;)Ljava/lang/String;
   4:	areturn
  LineNumberTable: 
   line 91: 0


}

