Compiled from "Xhtml.scala"
public final class scala.xml.Xhtml$ extends java.lang.Object implements scala.ScalaObject
  SourceFile: "Xhtml.scala"
  Scala: length = 0x
   
  InnerClass: 
   public final $anonfun$1=class scala/xml/Xhtml$$anonfun$1 of class scala/xml/Xhtml
   public final $anonfun$toXhtml$3=class scala/xml/Xhtml$$anonfun$toXhtml$3 of class scala/xml/Xhtml
   public final $anonfun$toXhtml$2=class scala/xml/Xhtml$$anonfun$toXhtml$2 of class scala/xml/Xhtml
   public final $anonfun$toXhtml$1=class scala/xml/Xhtml$$anonfun$toXhtml$1 of class scala/xml/Xhtml
   public final $anonfun$sequenceToXML$1=class scala/xml/Xhtml$$anonfun$sequenceToXML$1 of class scala/xml/Xhtml
  minor version: 0
  major version: 49
  Constant pool:
Asciz	SourceFile;
Asciz	Xhtml.scala;
Asciz	Scala;
Asciz	MODULE$;
Asciz	Lscala/xml/Xhtml$;;
Asciz	<clinit>;
Asciz	()V;
Asciz	Code;
Asciz	scala/xml/Xhtml$;
class	scala/xml/Xhtml$
Asciz	<init>;
NameAndType	"<init>":()V
Method	scala/xml/Xhtml$."<init>":()V
Asciz	minimizableElements;
Asciz	Lscala/collection/immutable/List;;
Asciz	Lscala/collection/immutable/List<Ljava/lang/String;>;;
Asciz	Signature;
Asciz	LineNumberTable;
Asciz	java/lang/Object;
class	java/lang/Object
Method	java/lang/Object."<init>":()V
NameAndType	MODULE$:Lscala/xml/Xhtml$;
Field	scala/xml/Xhtml$.MODULE$:Lscala/xml/Xhtml$;
Asciz	scala/collection/immutable/List$;
class	scala/collection/immutable/List$
Asciz	Lscala/collection/immutable/List$;;
NameAndType	MODULE$:Lscala/collection/immutable/List$;
Field	scala/collection/immutable/List$.MODULE$:Lscala/collection/immutable/List$;
Asciz	scala/Predef$;
class	scala/Predef$
Asciz	Lscala/Predef$;;
NameAndType	MODULE$:Lscala/Predef$;
Field	scala/Predef$.MODULE$:Lscala/Predef$;
int	10;
Asciz	java/lang/String;
class	java/lang/String
Asciz	base;
String	base
Asciz	meta;
String	meta
Asciz	link;
String	link
Asciz	hr;
String	hr
Asciz	br;
String	br
Asciz	param;
String	param
int	6;
Asciz	img;
String	img
int	7;
Asciz	area;
String	area
int	8;
Asciz	input;
String	input
int	9;
Asciz	col;
String	col
Asciz	[Ljava/lang/Object;;
class	"[Ljava/lang/Object;"
Asciz	wrapRefArray;
Asciz	([Ljava/lang/Object;)Lscala/collection/mutable/WrappedArray;;
NameAndType	wrapRefArray:([Ljava/lang/Object;)Lscala/collection/mutable/WrappedArray;
Method	scala/Predef$.wrapRefArray:([Ljava/lang/Object;)Lscala/collection/mutable/WrappedArray;
Asciz	apply;
Asciz	(Lscala/collection/Seq;)Lscala/collection/immutable/List;;
NameAndType	apply:(Lscala/collection/Seq;)Lscala/collection/immutable/List;
Method	scala/collection/immutable/List$.apply:(Lscala/collection/Seq;)Lscala/collection/immutable/List;
NameAndType	minimizableElements:Lscala/collection/immutable/List;
Field	scala/xml/Xhtml$.minimizableElements:Lscala/collection/immutable/List;
Asciz	gd3$1;
Asciz	(Lscala/xml/EntityRef;Z)Z;
Asciz	gd2$1;
Asciz	(Lscala/xml/Comment;Z)Z;
Asciz	shortForm$1;
Asciz	(Lscala/xml/Node;Z)Z;
Asciz	scala/xml/Node;
class	scala/xml/Node
Asciz	child;
Asciz	()Lscala/collection/Seq;;
NameAndType	child:()Lscala/collection/Seq;
Method	scala/xml/Node.child:()Lscala/collection/Seq;
Asciz	equals;
Asciz	(Ljava/lang/Object;)Z;
NameAndType	equals:(Ljava/lang/Object;)Z
Method	java/lang/Object.equals:(Ljava/lang/Object;)Z
Asciz	scala/collection/SeqLike;
class	scala/collection/SeqLike
Asciz	length;
Asciz	()I;
NameAndType	length:()I
InterfaceMethod	scala/collection/SeqLike.length:()I
Asciz	()Lscala/collection/immutable/List;;
NameAndType	minimizableElements:()Lscala/collection/immutable/List;
Method	scala/xml/Xhtml$.minimizableElements:()Lscala/collection/immutable/List;
Asciz	label;
Asciz	()Ljava/lang/String;;
NameAndType	label:()Ljava/lang/String;
Method	scala/xml/Node.label:()Ljava/lang/String;
Asciz	contains;
NameAndType	contains:(Ljava/lang/Object;)Z
InterfaceMethod	scala/collection/SeqLike.contains:(Ljava/lang/Object;)Z
Asciz	decode$1;
Asciz	(Lscala/xml/EntityRef;Lscala/collection/mutable/StringBuilder;)Lscala/collection/mutable/StringBuilder;;
Asciz	scala/xml/parsing/XhtmlEntities$;
class	scala/xml/parsing/XhtmlEntities$
Asciz	Lscala/xml/parsing/XhtmlEntities$;;
NameAndType	MODULE$:Lscala/xml/parsing/XhtmlEntities$;
Field	scala/xml/parsing/XhtmlEntities$.MODULE$:Lscala/xml/parsing/XhtmlEntities$;
Asciz	entMap;
Asciz	()Lscala/collection/immutable/Map;;
NameAndType	entMap:()Lscala/collection/immutable/Map;
Method	scala/xml/parsing/XhtmlEntities$.entMap:()Lscala/collection/immutable/Map;
Asciz	scala/xml/EntityRef;
class	scala/xml/EntityRef
Asciz	entityName;
NameAndType	entityName:()Ljava/lang/String;
Method	scala/xml/EntityRef.entityName:()Ljava/lang/String;
Asciz	scala/collection/MapLike;
class	scala/collection/MapLike
Asciz	get;
Asciz	(Ljava/lang/Object;)Lscala/Option;;
NameAndType	get:(Ljava/lang/Object;)Lscala/Option;
InterfaceMethod	scala/collection/MapLike.get:(Ljava/lang/Object;)Lscala/Option;
Asciz	scala/Some;
class	scala/Some
Asciz	x;
Asciz	Ljava/lang/Object;;
NameAndType	x:Ljava/lang/Object;
Field	scala/Some.x:Ljava/lang/Object;
Asciz	scala/runtime/BoxesRunTime;
class	scala/runtime/BoxesRunTime
Asciz	unboxToChar;
Asciz	(Ljava/lang/Object;)C;
NameAndType	unboxToChar:(Ljava/lang/Object;)C
Method	scala/runtime/BoxesRunTime.unboxToChar:(Ljava/lang/Object;)C
Asciz	gd1$1;
Asciz	(C)Z;
NameAndType	gd1$1:(C)Z
Method	scala/xml/Xhtml$.gd1$1:(C)Z
Asciz	scala/collection/mutable/StringBuilder;
class	scala/collection/mutable/StringBuilder
Asciz	append;
Asciz	(C)Lscala/collection/mutable/StringBuilder;;
NameAndType	append:(C)Lscala/collection/mutable/StringBuilder;
Method	scala/collection/mutable/StringBuilder.append:(C)Lscala/collection/mutable/StringBuilder;
Asciz	scala/MatchError;
class	scala/MatchError
Asciz	scala/Option;
class	scala/Option
Asciz	toString;
NameAndType	toString:()Ljava/lang/String;
Method	scala/Option.toString:()Ljava/lang/String;
Asciz	(Ljava/lang/String;)V;
NameAndType	"<init>":(Ljava/lang/String;)V
Method	scala/MatchError."<init>":(Ljava/lang/String;)V
Asciz	buildString;
Asciz	(Lscala/collection/mutable/StringBuilder;)Lscala/collection/mutable/StringBuilder;;
NameAndType	buildString:(Lscala/collection/mutable/StringBuilder;)Lscala/collection/mutable/StringBuilder;
Method	scala/xml/EntityRef.buildString:(Lscala/collection/mutable/StringBuilder;)Lscala/collection/mutable/StringBuilder;
Asciz	this;
Asciz	er;
Asciz	Lscala/xml/EntityRef;;
Asciz	temp2;
Asciz	Lscala/Some;;
Asciz	temp3;
Asciz	C;
Asciz	temp1;
Asciz	Lscala/Option;;
Asciz	LocalVariableTable;
int	128;
Asciz	sequenceToXML;
Asciz	(Lscala/collection/Seq;Lscala/xml/NamespaceBinding;Lscala/collection/mutable/StringBuilder;ZZZZ)V;
Asciz	scala/collection/IterableLike;
class	scala/collection/IterableLike
Asciz	isEmpty;
Asciz	()Z;
NameAndType	isEmpty:()Z
InterfaceMethod	scala/collection/IterableLike.isEmpty:()Z
Asciz	scala/xml/Xhtml$$anonfun$1;
class	scala/xml/Xhtml$$anonfun$1
Method	scala/xml/Xhtml$$anonfun$1."<init>":()V
Asciz	forall;
Asciz	(Lscala/Function1;)Z;
NameAndType	forall:(Lscala/Function1;)Z
InterfaceMethod	scala/collection/IterableLike.forall:(Lscala/Function1;)Z
Asciz	take;
Asciz	(I)Ljava/lang/Object;;
NameAndType	take:(I)Ljava/lang/Object;
InterfaceMethod	scala/collection/IterableLike.take:(I)Ljava/lang/Object;
Asciz	scala/xml/Xhtml$$anonfun$sequenceToXML$1;
class	scala/xml/Xhtml$$anonfun$sequenceToXML$1
Asciz	(Lscala/xml/NamespaceBinding;Lscala/collection/mutable/StringBuilder;Z)V;
NameAndType	"<init>":(Lscala/xml/NamespaceBinding;Lscala/collection/mutable/StringBuilder;Z)V
Method	scala/xml/Xhtml$$anonfun$sequenceToXML$1."<init>":(Lscala/xml/NamespaceBinding;Lscala/collection/mutable/StringBuilder;Z)V
Asciz	foreach;
Asciz	(Lscala/Function1;)V;
NameAndType	foreach:(Lscala/Function1;)V
InterfaceMethod	scala/collection/IterableLike.foreach:(Lscala/Function1;)V
Asciz	scala/collection/TraversableLike;
class	scala/collection/TraversableLike
Asciz	last;
Asciz	()Ljava/lang/Object;;
NameAndType	last:()Ljava/lang/Object;
InterfaceMethod	scala/collection/TraversableLike.last:()Ljava/lang/Object;
Asciz	toXhtml;
Asciz	(Lscala/xml/Node;Lscala/xml/NamespaceBinding;Lscala/collection/mutable/StringBuilder;ZZZZ)V;
NameAndType	toXhtml:(Lscala/xml/Node;Lscala/xml/NamespaceBinding;Lscala/collection/mutable/StringBuilder;ZZZZ)V
Method	scala/xml/Xhtml$.toXhtml:(Lscala/xml/Node;Lscala/xml/NamespaceBinding;Lscala/collection/mutable/StringBuilder;ZZZZ)V
Asciz	children;
Asciz	Lscala/collection/Seq;;
Asciz	pscope$1;
Asciz	Lscala/xml/NamespaceBinding;;
Asciz	sb$2;
Asciz	Lscala/collection/mutable/StringBuilder;;
Asciz	stripComments;
Asciz	Z;
Asciz	decodeEntities;
Asciz	preserveWhitespace;
Asciz	minimizeTags;
Asciz	doSpaces$1;
Asciz	(Lscala/collection/Seq<Lscala/xml/Node;>;Lscala/xml/NamespaceBinding;Lscala/collection/mutable/StringBuilder;ZZZZ)V;
Asciz	scala/xml/Comment;
class	scala/xml/Comment
NameAndType	gd2$1:(Lscala/xml/Comment;Z)Z
Method	scala/xml/Xhtml$.gd2$1:(Lscala/xml/Comment;Z)Z
Method	scala/xml/Comment.buildString:(Lscala/collection/mutable/StringBuilder;)Lscala/collection/mutable/StringBuilder;
Method	scala/xml/Node.toString:()Ljava/lang/String;
NameAndType	gd3$1:(Lscala/xml/EntityRef;Z)Z
Method	scala/xml/Xhtml$.gd3$1:(Lscala/xml/EntityRef;Z)Z
NameAndType	decode$1:(Lscala/xml/EntityRef;Lscala/collection/mutable/StringBuilder;)Lscala/collection/mutable/StringBuilder;
Method	scala/xml/Xhtml$.decode$1:(Lscala/xml/EntityRef;Lscala/collection/mutable/StringBuilder;)Lscala/collection/mutable/StringBuilder;
Asciz	scala/xml/SpecialNode;
class	scala/xml/SpecialNode
Method	scala/xml/SpecialNode.buildString:(Lscala/collection/mutable/StringBuilder;)Lscala/collection/mutable/StringBuilder;
Asciz	scala/xml/Group;
class	scala/xml/Group
Asciz	nodes;
NameAndType	nodes:()Lscala/collection/Seq;
Method	scala/xml/Group.nodes:()Lscala/collection/Seq;
Asciz	scala/xml/Xhtml$$anonfun$toXhtml$3;
class	scala/xml/Xhtml$$anonfun$toXhtml$3
Asciz	(Lscala/xml/Node;Lscala/collection/mutable/StringBuilder;)V;
NameAndType	"<init>":(Lscala/xml/Node;Lscala/collection/mutable/StringBuilder;)V
Method	scala/xml/Xhtml$$anonfun$toXhtml$3."<init>":(Lscala/xml/Node;Lscala/collection/mutable/StringBuilder;)V
int	60;
Asciz	nameToString;
NameAndType	nameToString:(Lscala/collection/mutable/StringBuilder;)Lscala/collection/mutable/StringBuilder;
Method	scala/xml/Node.nameToString:(Lscala/collection/mutable/StringBuilder;)Lscala/collection/mutable/StringBuilder;
Asciz	attributes;
Asciz	()Lscala/xml/MetaData;;
NameAndType	attributes:()Lscala/xml/MetaData;
Method	scala/xml/Node.attributes:()Lscala/xml/MetaData;
Asciz	scala/xml/MetaData;
class	scala/xml/MetaData
Method	scala/xml/MetaData.buildString:(Lscala/collection/mutable/StringBuilder;)Lscala/collection/mutable/StringBuilder;
Asciz	scala/runtime/BoxedUnit;
class	scala/runtime/BoxedUnit
Asciz	UNIT;
Asciz	Lscala/runtime/BoxedUnit;;
NameAndType	UNIT:Lscala/runtime/BoxedUnit;
Field	scala/runtime/BoxedUnit.UNIT:Lscala/runtime/BoxedUnit;
Asciz	scope;
Asciz	()Lscala/xml/NamespaceBinding;;
NameAndType	scope:()Lscala/xml/NamespaceBinding;
Method	scala/xml/Node.scope:()Lscala/xml/NamespaceBinding;
Asciz	scala/xml/NamespaceBinding;
class	scala/xml/NamespaceBinding
Asciz	(Lscala/collection/mutable/StringBuilder;Lscala/xml/NamespaceBinding;)V;
NameAndType	buildString:(Lscala/collection/mutable/StringBuilder;Lscala/xml/NamespaceBinding;)V
Method	scala/xml/NamespaceBinding.buildString:(Lscala/collection/mutable/StringBuilder;Lscala/xml/NamespaceBinding;)V
NameAndType	shortForm$1:(Lscala/xml/Node;Z)Z
Method	scala/xml/Xhtml$.shortForm$1:(Lscala/xml/Node;Z)Z
Asciz	 />;
String	 />
Asciz	(Ljava/lang/String;)Lscala/collection/mutable/StringBuilder;;
NameAndType	append:(Ljava/lang/String;)Lscala/collection/mutable/StringBuilder;
Method	scala/collection/mutable/StringBuilder.append:(Ljava/lang/String;)Lscala/collection/mutable/StringBuilder;
int	62;
NameAndType	sequenceToXML:(Lscala/collection/Seq;Lscala/xml/NamespaceBinding;Lscala/collection/mutable/StringBuilder;ZZZZ)V
Method	scala/xml/Xhtml$.sequenceToXML:(Lscala/collection/Seq;Lscala/xml/NamespaceBinding;Lscala/collection/mutable/StringBuilder;ZZZZ)V
Asciz	</;
String	</
Asciz	x$18;
Asciz	Lscala/xml/Node;;
Asciz	pscope;
Asciz	sb$1;
Asciz	stripComments$1;
Asciz	decodeEntities$1;
Asciz	minimizeTags$1;
Asciz	temp5;
Asciz	Lscala/xml/Comment;;
Asciz	temp7;
Asciz	Lscala/xml/SpecialNode;;
Asciz	temp10;
Asciz	Lscala/xml/Group;;
Asciz	()Lscala/collection/immutable/List<Ljava/lang/String;>;;
Asciz	(Lscala/xml/NodeSeq;)Ljava/lang/String;;
Asciz	scala/xml/Xhtml$$anonfun$toXhtml$2;
class	scala/xml/Xhtml$$anonfun$toXhtml$2
Asciz	(Lscala/xml/NodeSeq;)V;
NameAndType	"<init>":(Lscala/xml/NodeSeq;)V
Method	scala/xml/Xhtml$$anonfun$toXhtml$2."<init>":(Lscala/xml/NodeSeq;)V
Method	scala/collection/mutable/StringBuilder."<init>":()V
Asciz	scala/xml/TopScope$;
class	scala/xml/TopScope$
Asciz	Lscala/xml/TopScope$;;
NameAndType	MODULE$:Lscala/xml/TopScope$;
Field	scala/xml/TopScope$.MODULE$:Lscala/xml/TopScope$;
Method	scala/collection/mutable/StringBuilder.toString:()Ljava/lang/String;
Asciz	nodeSeq$1;
Asciz	Lscala/xml/NodeSeq;;
Asciz	x$110;
Asciz	x$130;
Asciz	x$140;
Asciz	x$150;
Asciz	x$160;
Asciz	x$170;
Asciz	sb0;
Asciz	(Lscala/xml/Node;)Ljava/lang/String;;
Asciz	scala/xml/Xhtml$$anonfun$toXhtml$1;
class	scala/xml/Xhtml$$anonfun$toXhtml$1
Asciz	(Lscala/xml/Node;)V;
NameAndType	"<init>":(Lscala/xml/Node;)V
Method	scala/xml/Xhtml$$anonfun$toXhtml$1."<init>":(Lscala/xml/Node;)V
Asciz	node$1;
Asciz	x$40;
Asciz	x$60;
Asciz	x$70;
Asciz	x$80;
Asciz	x$90;
Asciz	x$100;
Asciz	toXhtml$default$2;
Asciz	toXhtml$default$3;
Asciz	()Lscala/collection/mutable/StringBuilder;;
Asciz	toXhtml$default$4;
Asciz	toXhtml$default$5;
Asciz	toXhtml$default$6;
Asciz	toXhtml$default$7;
Asciz	sequenceToXML$default$2;
Asciz	sequenceToXML$default$3;
Asciz	sequenceToXML$default$4;
Asciz	sequenceToXML$default$5;
Asciz	sequenceToXML$default$6;
Asciz	sequenceToXML$default$7;
Asciz	InnerClasses;
Asciz	scala/xml/Xhtml;
class	scala/xml/Xhtml
Asciz	$anonfun$1;
Asciz	$anonfun$toXhtml$3;
Asciz	$anonfun$toXhtml$2;
Asciz	$anonfun$toXhtml$1;
Asciz	$anonfun$sequenceToXML$1;
Asciz	scala/ScalaObject;
class	scala/ScalaObject

{
public static final scala.xml.Xhtml$ MODULE$;
  Signature: Lscala/xml/Xhtml$;

private final scala.collection.immutable.List minimizableElements;
  Signature: Lscala/collection/immutable/List;
  Signature: length = 0x2
   00 10 

public static {};
  Signature: ()V
  Code:
   Stack=1, Locals=0, Args_size=0
	new	class scala/xml/Xhtml$
	invokespecial	Method "<init>":()V
	return
  Labels:

private scala.xml.Xhtml$();
  Signature: ()V
  Code:
   Stack=7, Locals=1, Args_size=1
	aload_0
	invokespecial	Method java/lang/Object."<init>":()V
	aload_0
	putstatic	Field MODULE$:Lscala/xml/Xhtml$;
	aload_0
	getstatic	Field scala/collection/immutable/List$.MODULE$:Lscala/collection/immutable/List$;
	getstatic	Field scala/Predef$.MODULE$:Lscala/Predef$;
	ldc	int 10
	anewarray	class java/lang/String
	dup
	iconst_0
	ldc	String base
	aastore
	dup
	iconst_1
	ldc	String meta
	aastore
	dup
	iconst_2
	ldc	String link
	aastore
	dup
	iconst_3
	ldc	String hr
	aastore
	dup
	iconst_4
	ldc	String br
	aastore
	dup
	iconst_5
	ldc	String param
	aastore
	dup
	ldc	int 6
	ldc	String img
	aastore
	dup
	ldc	int 7
	ldc	String area
	aastore
	dup
	ldc	int 8
	ldc	String input
	aastore
	dup
	ldc	int 9
	ldc	String col
	aastore
	checkcast	class "[Ljava/lang/Object;"
	invokevirtual	Method scala/Predef$.wrapRefArray:([Ljava/lang/Object;)Lscala/collection/mutable/WrappedArray;
	invokevirtual	Method scala/collection/immutable/List$.apply:(Lscala/collection/Seq;)Lscala/collection/immutable/List;
	putfield	Field minimizableElements:Lscala/collection/immutable/List;
	return
  Labels:

private final boolean gd3$1(scala.xml.EntityRef, boolean);
  Signature: (Lscala/xml/EntityRef;Z)Z
  Code:
   Stack=1, Locals=3, Args_size=3
	iload_2
	ireturn
  Labels:

private final boolean gd2$1(scala.xml.Comment, boolean);
  Signature: (Lscala/xml/Comment;Z)Z
  Code:
   Stack=1, Locals=3, Args_size=3
	iload_2
	ifeq	l1 // iconst_1
	iconst_0
	goto	l2 // ireturn
l1	iconst_1
l2	ireturn
  Labels:
   	l1 = 8 // iconst_1
   	l2 = 9 // ireturn

private final boolean shortForm$1(scala.xml.Node, boolean);
  Signature: (Lscala/xml/Node;Z)Z
  Code:
   Stack=2, Locals=4, Args_size=3
	iload_2
	ifeq	l1 // iconst_0
	aload_1
	invokevirtual	Method scala/xml/Node.child:()Lscala/collection/Seq;
	dup
	astore_3
	ifnull	l2 // aload_0
	aload_3
	aconst_null
	invokevirtual	Method java/lang/Object.equals:(Ljava/lang/Object;)Z
	ifne	l2 // aload_0
	aload_1
	invokevirtual	Method scala/xml/Node.child:()Lscala/collection/Seq;
	invokeinterface	InterfaceMethod scala/collection/SeqLike.length:()I
	iconst_0
	if_icmpne	l1 // iconst_0
l2	aload_0
	invokespecial	Method minimizableElements:()Lscala/collection/immutable/List;
	aload_1
	invokevirtual	Method scala/xml/Node.label:()Ljava/lang/String;
	invokeinterface	InterfaceMethod scala/collection/SeqLike.contains:(Ljava/lang/Object;)Z
	ifeq	l1 // iconst_0
	iconst_1
	goto	l3 // ireturn
l1	iconst_0
l3	ireturn
  Labels:
   	l2 = 34 // aload_0
   	l1 = 54 // iconst_0
   	l3 = 55 // ireturn

private final scala.collection.mutable.StringBuilder decode$1(scala.xml.EntityRef, scala.collection.mutable.StringBuilder);
  Signature: (Lscala/xml/EntityRef;Lscala/collection/mutable/StringBuilder;)Lscala/collection/mutable/StringBuilder;
  Code:
   Stack=3, Locals=6, Args_size=3
	getstatic	Field scala/xml/parsing/XhtmlEntities$.MODULE$:Lscala/xml/parsing/XhtmlEntities$;
	invokevirtual	Method scala/xml/parsing/XhtmlEntities$.entMap:()Lscala/collection/immutable/Map;
	aload_1
	invokevirtual	Method scala/xml/EntityRef.entityName:()Ljava/lang/String;
	invokeinterface	InterfaceMethod scala/collection/MapLike.get:(Ljava/lang/Object;)Lscala/Option;
	astore	5
	aload	5
	instanceof	class scala/Some
	ifeq	l1 // iconst_1
	aload	5
	checkcast	class scala/Some
	astore_3
	aload_3
	getfield	Field scala/Some.x:Ljava/lang/Object;
	invokestatic	Method scala/runtime/BoxesRunTime.unboxToChar:(Ljava/lang/Object;)C
	istore	4
	aload_0
	iload	4
	invokespecial	Method gd1$1:(C)Z
	ifeq	l2 // iconst_1
	aload_2
	iload	4
	invokevirtual	Method scala/collection/mutable/StringBuilder.append:(C)Lscala/collection/mutable/StringBuilder;
	goto	l3 // areturn
l2	iconst_1
	ifne	l4 // aload_1
	new	class scala/MatchError
	dup
	aload	5
	invokevirtual	Method scala/Option.toString:()Ljava/lang/String;
	invokespecial	Method scala/MatchError."<init>":(Ljava/lang/String;)V
	athrow
l1	iconst_1
	ifeq	l5 // new
l4	aload_1
	aload_2
	invokevirtual	Method scala/xml/EntityRef.buildString:(Lscala/collection/mutable/StringBuilder;)Lscala/collection/mutable/StringBuilder;
l3	areturn
l5	new	class scala/MatchError
	dup
	aload	5
	invokevirtual	Method scala/Option.toString:()Ljava/lang/String;
	invokespecial	Method scala/MatchError."<init>":(Ljava/lang/String;)V
	athrow
  Labels:
   	l2 = 58 // iconst_1
   	l1 = 75 // iconst_1
   	l4 = 79 // aload_1
   	l3 = 84 // areturn
   	l5 = 85 // new
  LocalVariableTable: 
   Start  Length  Slot  Name   Signature
   0      98      0    this       Lscala/xml/Xhtml$;
   0      98      1    er       Lscala/xml/EntityRef;
   31      44      3    temp2       Lscala/Some;
   79      5      3    temp2       Lscala/Some;
   40      35      4    temp3       C
   79      5      4    temp3       C
   17      81      5    temp1       Lscala/Option;


private final boolean gd1$1(char);
  Signature: (C)Z
  Code:
   Stack=2, Locals=2, Args_size=2
	iload_1
	ldc	int 128
	if_icmplt	l1 // iconst_0
	iconst_1
	goto	l2 // ireturn
l1	iconst_0
l2	ireturn
  Labels:
   	l1 = 10 // iconst_0
   	l2 = 11 // ireturn

public void sequenceToXML(scala.collection.Seq, scala.xml.NamespaceBinding, scala.collection.mutable.StringBuilder, boolean, boolean, boolean, boolean);
  Signature: (Lscala/collection/Seq;Lscala/xml/NamespaceBinding;Lscala/collection/mutable/StringBuilder;ZZZZ)V
  Code:
   Stack=8, Locals=9, Args_size=8
	aload_1
	invokeinterface	InterfaceMethod scala/collection/IterableLike.isEmpty:()Z
	ifeq	l1 // aload_1
	return
l1	aload_1
	new	class scala/xml/Xhtml$$anonfun$1
	dup
	invokespecial	Method scala/xml/Xhtml$$anonfun$1."<init>":()V
	invokeinterface	InterfaceMethod scala/collection/IterableLike.forall:(Lscala/Function1;)Z
	istore	8
	aload_1
	aload_1
	invokeinterface	InterfaceMethod scala/collection/SeqLike.length:()I
	iconst_1
	isub
	invokeinterface	InterfaceMethod scala/collection/IterableLike.take:(I)Ljava/lang/Object;
	checkcast	class scala/collection/IterableLike
	new	class scala/xml/Xhtml$$anonfun$sequenceToXML$1
	dup
	aload_2
	aload_3
	iload	8
	invokespecial	Method scala/xml/Xhtml$$anonfun$sequenceToXML$1."<init>":(Lscala/xml/NamespaceBinding;Lscala/collection/mutable/StringBuilder;Z)V
	invokeinterface	InterfaceMethod scala/collection/IterableLike.foreach:(Lscala/Function1;)V
	aload_0
	aload_1
	invokeinterface	InterfaceMethod scala/collection/TraversableLike.last:()Ljava/lang/Object;
	checkcast	class scala/xml/Node
	aload_2
	aload_3
	iconst_0
	iconst_0
	iconst_0
	iconst_1
	invokevirtual	Method toXhtml:(Lscala/xml/Node;Lscala/xml/NamespaceBinding;Lscala/collection/mutable/StringBuilder;ZZZZ)V
	return
  Labels:
   	l1 = 10 // aload_1
  LocalVariableTable: 
   Start  Length  Slot  Name   Signature
   0      78      0    this       Lscala/xml/Xhtml$;
   0      78      1    children       Lscala/collection/Seq;
   0      78      2    pscope$1       Lscala/xml/NamespaceBinding;
   0      78      3    sb$2       Lscala/collection/mutable/StringBuilder;
   0      78      4    stripComments       Z
   0      78      5    decodeEntities       Z
   0      78      6    preserveWhitespace       Z
   0      78      7    minimizeTags       Z
   25      52      8    doSpaces$1       Z

  Signature: length = 0x2
   00 FFFFFFE0 

public void toXhtml(scala.xml.Node, scala.xml.NamespaceBinding, scala.collection.mutable.StringBuilder, boolean, boolean, boolean, boolean);
  Signature: (Lscala/xml/Node;Lscala/xml/NamespaceBinding;Lscala/collection/mutable/StringBuilder;ZZZZ)V
  Code:
   Stack=8, Locals=12, Args_size=8
	aload_1
	instanceof	class scala/xml/Comment
	ifeq	l1 // aload_1
	aload_1
	checkcast	class scala/xml/Comment
	astore	8
	aload_0
	aload	8
	iload	4
	invokespecial	Method gd2$1:(Lscala/xml/Comment;Z)Z
	ifeq	l2 // iconst_1
	aload	8
	aload_3
	invokevirtual	Method scala/xml/Comment.buildString:(Lscala/collection/mutable/StringBuilder;)Lscala/collection/mutable/StringBuilder;
	pop
	goto	l3 // return
l2	iconst_1
	ifeq	l4 // new
	aload	8
	astore	10
	goto	l5 // aload
l4	new	class scala/MatchError
	dup
	aload_1
	invokevirtual	Method scala/xml/Node.toString:()Ljava/lang/String;
	invokespecial	Method scala/MatchError."<init>":(Ljava/lang/String;)V
	athrow
l1	aload_1
	instanceof	class scala/xml/EntityRef
	ifeq	l6 // aload_1
	aload_1
	checkcast	class scala/xml/EntityRef
	astore	9
	aload_0
	aload	9
	iload	5
	invokespecial	Method gd3$1:(Lscala/xml/EntityRef;Z)Z
	ifeq	l7 // iconst_1
	aload_0
	aload	9
	aload_3
	invokespecial	Method decode$1:(Lscala/xml/EntityRef;Lscala/collection/mutable/StringBuilder;)Lscala/collection/mutable/StringBuilder;
	pop
	goto	l3 // return
l7	iconst_1
	ifeq	l8 // new
	aload	9
	astore	10
	goto	l5 // aload
l8	new	class scala/MatchError
	dup
	aload_1
	invokevirtual	Method scala/xml/Node.toString:()Ljava/lang/String;
	invokespecial	Method scala/MatchError."<init>":(Ljava/lang/String;)V
	athrow
l6	aload_1
	instanceof	class scala/xml/SpecialNode
	ifeq	l9 // aload_1
	iconst_1
	ifeq	l10 // new
	aload_1
	checkcast	class scala/xml/SpecialNode
	astore	10
l5	aload	10
	aload_3
	invokevirtual	Method scala/xml/SpecialNode.buildString:(Lscala/collection/mutable/StringBuilder;)Lscala/collection/mutable/StringBuilder;
	pop
	goto	l3 // return
l10	new	class scala/MatchError
	dup
	aload_1
	invokevirtual	Method scala/xml/Node.toString:()Ljava/lang/String;
	invokespecial	Method scala/MatchError."<init>":(Ljava/lang/String;)V
	athrow
l9	aload_1
	instanceof	class scala/xml/Group
	ifeq	l11 // iconst_1
	aload_1
	checkcast	class scala/xml/Group
	astore	11
	iconst_1
	ifeq	l12 // new
	aload	11
	invokevirtual	Method scala/xml/Group.nodes:()Lscala/collection/Seq;
	new	class scala/xml/Xhtml$$anonfun$toXhtml$3
	dup
	aload_1
	aload_3
	invokespecial	Method scala/xml/Xhtml$$anonfun$toXhtml$3."<init>":(Lscala/xml/Node;Lscala/collection/mutable/StringBuilder;)V
	invokeinterface	InterfaceMethod scala/collection/IterableLike.foreach:(Lscala/Function1;)V
	goto	l3 // return
l12	new	class scala/MatchError
	dup
	aload_1
	invokevirtual	Method scala/xml/Node.toString:()Ljava/lang/String;
	invokespecial	Method scala/MatchError."<init>":(Ljava/lang/String;)V
	athrow
l11	iconst_1
	ifeq	l13 // new
	aload_3
	ldc	int 60
	invokevirtual	Method scala/collection/mutable/StringBuilder.append:(C)Lscala/collection/mutable/StringBuilder;
	pop
	aload_1
	aload_3
	invokevirtual	Method scala/xml/Node.nameToString:(Lscala/collection/mutable/StringBuilder;)Lscala/collection/mutable/StringBuilder;
	pop
	aload_1
	invokevirtual	Method scala/xml/Node.attributes:()Lscala/xml/MetaData;
	ifnull	l14 // getstatic
	aload_1
	invokevirtual	Method scala/xml/Node.attributes:()Lscala/xml/MetaData;
	aload_3
	invokevirtual	Method scala/xml/MetaData.buildString:(Lscala/collection/mutable/StringBuilder;)Lscala/collection/mutable/StringBuilder;
	goto	l15 // pop
l14	getstatic	Field scala/runtime/BoxedUnit.UNIT:Lscala/runtime/BoxedUnit;
l15	pop
	aload_1
	invokevirtual	Method scala/xml/Node.scope:()Lscala/xml/NamespaceBinding;
	aload_3
	aload_2
	invokevirtual	Method scala/xml/NamespaceBinding.buildString:(Lscala/collection/mutable/StringBuilder;Lscala/xml/NamespaceBinding;)V
	aload_0
	aload_1
	iload	7
	invokespecial	Method shortForm$1:(Lscala/xml/Node;Z)Z
	ifeq	l16 // aload_3
	aload_3
	ldc_w	String  />
	invokevirtual	Method scala/collection/mutable/StringBuilder.append:(Ljava/lang/String;)Lscala/collection/mutable/StringBuilder;
	pop
	goto	l3 // return
l16	aload_3
	ldc_w	int 62
	invokevirtual	Method scala/collection/mutable/StringBuilder.append:(C)Lscala/collection/mutable/StringBuilder;
	pop
	aload_0
	aload_1
	invokevirtual	Method scala/xml/Node.child:()Lscala/collection/Seq;
	aload_1
	invokevirtual	Method scala/xml/Node.scope:()Lscala/xml/NamespaceBinding;
	aload_3
	iconst_0
	iconst_0
	iconst_0
	iconst_1
	invokevirtual	Method sequenceToXML:(Lscala/collection/Seq;Lscala/xml/NamespaceBinding;Lscala/collection/mutable/StringBuilder;ZZZZ)V
	aload_3
	ldc_w	String </
	invokevirtual	Method scala/collection/mutable/StringBuilder.append:(Ljava/lang/String;)Lscala/collection/mutable/StringBuilder;
	pop
	aload_1
	aload_3
	invokevirtual	Method scala/xml/Node.nameToString:(Lscala/collection/mutable/StringBuilder;)Lscala/collection/mutable/StringBuilder;
	pop
	aload_3
	ldc_w	int 62
	invokevirtual	Method scala/collection/mutable/StringBuilder.append:(C)Lscala/collection/mutable/StringBuilder;
	pop
l3	return
l13	new	class scala/MatchError
	dup
	aload_1
	invokevirtual	Method scala/xml/Node.toString:()Ljava/lang/String;
	invokespecial	Method scala/MatchError."<init>":(Ljava/lang/String;)V
	athrow
  Labels:
   	l2 = 34 // iconst_1
   	l4 = 45 // new
   	l1 = 57 // aload_1
   	l7 = 92 // iconst_1
   	l8 = 103 // new
   	l6 = 115 // aload_1
   	l5 = 132 // aload
   	l10 = 142 // new
   	l9 = 154 // aload_1
   	l12 = 193 // new
   	l11 = 205 // iconst_1
   	l14 = 240 // getstatic
   	l15 = 243 // pop
   	l16 = 274 // aload_3
   	l3 = 321 // return
   	l13 = 322 // new
  LocalVariableTable: 
   Start  Length  Slot  Name   Signature
   0      334      0    this       Lscala/xml/Xhtml$;
   0      334      1    x$18       Lscala/xml/Node;
   0      334      2    pscope       Lscala/xml/NamespaceBinding;
   0      334      3    sb$1       Lscala/collection/mutable/StringBuilder;
   0      334      4    stripComments$1       Z
   0      334      5    decodeEntities$1       Z
   0      334      6    preserveWhitespace       Z
   0      334      7    minimizeTags$1       Z
   13      44      8    temp5       Lscala/xml/Comment;
   132      10      8    temp5       Lscala/xml/Comment;
   70      45      9    temp7       Lscala/xml/EntityRef;
   34      4      10    x       Lscala/xml/SpecialNode;
   42      3      10    x       Lscala/xml/SpecialNode;
   38      19      10    x       Lscala/xml/SpecialNode;
   132      7      10    x       Lscala/xml/SpecialNode;
   167      38      11    temp10       Lscala/xml/Group;


private scala.collection.immutable.List minimizableElements();
  Signature: ()Lscala/collection/immutable/List;
  Code:
   Stack=1, Locals=1, Args_size=1
	aload_0
	getfield	Field minimizableElements:Lscala/collection/immutable/List;
	areturn
  Labels:
  Signature: length = 0x2
   01 2B 

public java.lang.String toXhtml(scala.xml.NodeSeq);
  Signature: (Lscala/xml/NodeSeq;)Ljava/lang/String;
  Code:
   Stack=8, Locals=10, Args_size=2
	new	class scala/xml/Xhtml$$anonfun$toXhtml$2
	dup
	pop
	aload_1
	invokespecial	Method scala/xml/Xhtml$$anonfun$toXhtml$2."<init>":(Lscala/xml/NodeSeq;)V
	new	class scala/collection/mutable/StringBuilder
	dup
	invokespecial	Method scala/collection/mutable/StringBuilder."<init>":()V
	astore	9
	aload	9
	checkcast	class scala/collection/mutable/StringBuilder
	astore	4
	aload_1
	astore_2
	getstatic	Field scala/xml/TopScope$.MODULE$:Lscala/xml/TopScope$;
	astore_3
	iconst_0
	istore	5
	iconst_0
	istore	6
	iconst_0
	istore	7
	iconst_1
	istore	8
	getstatic	Field MODULE$:Lscala/xml/Xhtml$;
	aload_2
	aload_3
	aload	4
	iload	5
	iload	6
	iload	7
	iload	8
	invokevirtual	Method sequenceToXML:(Lscala/collection/Seq;Lscala/xml/NamespaceBinding;Lscala/collection/mutable/StringBuilder;ZZZZ)V
	aload	9
	invokevirtual	Method scala/collection/mutable/StringBuilder.toString:()Ljava/lang/String;
	areturn
  Labels:
  LocalVariableTable: 
   Start  Length  Slot  Name   Signature
   0      67      0    this       Lscala/xml/Xhtml$;
   0      67      1    nodeSeq$1       Lscala/xml/NodeSeq;
   27      34      2    x$110       Lscala/collection/Seq;
   31      30      3    x$130       Lscala/xml/NamespaceBinding;
   34      27      5    x$140       Z
   37      24      6    x$150       Z
   40      21      7    x$160       Z
   43      18      8    x$170       Z
   18      48      9    sb0       Lscala/collection/mutable/StringBuilder;


public java.lang.String toXhtml(scala.xml.Node);
  Signature: (Lscala/xml/Node;)Ljava/lang/String;
  Code:
   Stack=8, Locals=10, Args_size=2
	new	class scala/xml/Xhtml$$anonfun$toXhtml$1
	dup
	pop
	aload_1
	invokespecial	Method scala/xml/Xhtml$$anonfun$toXhtml$1."<init>":(Lscala/xml/Node;)V
	new	class scala/collection/mutable/StringBuilder
	dup
	invokespecial	Method scala/collection/mutable/StringBuilder."<init>":()V
	astore	9
	aload	9
	checkcast	class scala/collection/mutable/StringBuilder
	astore	4
	aload_1
	astore_2
	getstatic	Field scala/xml/TopScope$.MODULE$:Lscala/xml/TopScope$;
	astore_3
	iconst_0
	istore	5
	iconst_0
	istore	6
	iconst_0
	istore	7
	iconst_1
	istore	8
	getstatic	Field MODULE$:Lscala/xml/Xhtml$;
	aload_2
	aload_3
	aload	4
	iload	5
	iload	6
	iload	7
	iload	8
	invokevirtual	Method toXhtml:(Lscala/xml/Node;Lscala/xml/NamespaceBinding;Lscala/collection/mutable/StringBuilder;ZZZZ)V
	aload	9
	invokevirtual	Method scala/collection/mutable/StringBuilder.toString:()Ljava/lang/String;
	areturn
  Labels:
  LocalVariableTable: 
   Start  Length  Slot  Name   Signature
   0      67      0    this       Lscala/xml/Xhtml$;
   0      67      1    node$1       Lscala/xml/Node;
   27      34      2    x$40       Lscala/xml/Node;
   31      30      3    x$60       Lscala/xml/NamespaceBinding;
   34      27      5    x$70       Z
   37      24      6    x$80       Z
   40      21      7    x$90       Z
   43      18      8    x$100       Z
   18      48      9    sb0       Lscala/collection/mutable/StringBuilder;


public scala.xml.NamespaceBinding toXhtml$default$2();
  Signature: ()Lscala/xml/NamespaceBinding;
  Code:
   Stack=1, Locals=1, Args_size=1
	getstatic	Field scala/xml/TopScope$.MODULE$:Lscala/xml/TopScope$;
	areturn
  Labels:

public scala.collection.mutable.StringBuilder toXhtml$default$3();
  Signature: ()Lscala/collection/mutable/StringBuilder;
  Code:
   Stack=2, Locals=1, Args_size=1
	new	class scala/collection/mutable/StringBuilder
	dup
	invokespecial	Method scala/collection/mutable/StringBuilder."<init>":()V
	areturn
  Labels:

public boolean toXhtml$default$4();
  Signature: ()Z
  Code:
   Stack=1, Locals=1, Args_size=1
	iconst_0
	ireturn
  Labels:

public boolean toXhtml$default$5();
  Signature: ()Z
  Code:
   Stack=1, Locals=1, Args_size=1
	iconst_0
	ireturn
  Labels:

public boolean toXhtml$default$6();
  Signature: ()Z
  Code:
   Stack=1, Locals=1, Args_size=1
	iconst_0
	ireturn
  Labels:

public boolean toXhtml$default$7();
  Signature: ()Z
  Code:
   Stack=1, Locals=1, Args_size=1
	iconst_1
	ireturn
  Labels:

public scala.xml.NamespaceBinding sequenceToXML$default$2();
  Signature: ()Lscala/xml/NamespaceBinding;
  Code:
   Stack=1, Locals=1, Args_size=1
	getstatic	Field scala/xml/TopScope$.MODULE$:Lscala/xml/TopScope$;
	areturn
  Labels:

public scala.collection.mutable.StringBuilder sequenceToXML$default$3();
  Signature: ()Lscala/collection/mutable/StringBuilder;
  Code:
   Stack=2, Locals=1, Args_size=1
	new	class scala/collection/mutable/StringBuilder
	dup
	invokespecial	Method scala/collection/mutable/StringBuilder."<init>":()V
	areturn
  Labels:

public boolean sequenceToXML$default$4();
  Signature: ()Z
  Code:
   Stack=1, Locals=1, Args_size=1
	iconst_0
	ireturn
  Labels:

public boolean sequenceToXML$default$5();
  Signature: ()Z
  Code:
   Stack=1, Locals=1, Args_size=1
	iconst_0
	ireturn
  Labels:

public boolean sequenceToXML$default$6();
  Signature: ()Z
  Code:
   Stack=1, Locals=1, Args_size=1
	iconst_0
	ireturn
  Labels:

public boolean sequenceToXML$default$7();
  Signature: ()Z
  Code:
   Stack=1, Locals=1, Args_size=1
	iconst_1
	ireturn
  Labels:

}

