Compiled from "Xhtml.scala"
public final class scala.xml.Xhtml$$anonfun$toXhtml$2 extends java.lang.Object implements scala.Function1,scala.ScalaObject,java.io.Serializable
  SourceFile: "Xhtml.scala"
  Scala: length = 0x
   
  InnerClass: 
   public final #99= #10 of #98; //$anonfun$toXhtml$2=class scala/xml/Xhtml$$anonfun$toXhtml$2 of class scala/xml/Xhtml
  minor version: 0
  major version: 49
  Constant pool:
const #1 = Asciz	SourceFile;
const #2 = Asciz	Xhtml.scala;
const #3 = Asciz	nodeSeq$1;
const #4 = Asciz	Lscala/xml/NodeSeq;;
const #5 = Asciz	<init>;
const #6 = Asciz	(Lscala/xml/NodeSeq;)V;
const #7 = Asciz	Code;
const #8 = Asciz	LineNumberTable;
const #9 = Asciz	scala/xml/Xhtml$$anonfun$toXhtml$2;
const #10 = class	#9;	//  scala/xml/Xhtml$$anonfun$toXhtml$2
const #11 = NameAndType	#3:#4;//  nodeSeq$1:Lscala/xml/NodeSeq;
const #12 = Field	#10.#11;	//  scala/xml/Xhtml$$anonfun$toXhtml$2.nodeSeq$1:Lscala/xml/NodeSeq;
const #13 = Asciz	java/lang/Object;
const #14 = class	#13;	//  java/lang/Object
const #15 = Asciz	()V;
const #16 = NameAndType	#5:#15;//  "<init>":()V
const #17 = Method	#14.#16;	//  java/lang/Object."<init>":()V
const #18 = Asciz	scala/Function1$class;
const #19 = class	#18;	//  scala/Function1$class
const #20 = Asciz	$init$;
const #21 = Asciz	(Lscala/Function1;)V;
const #22 = NameAndType	#20:#21;//  $init$:(Lscala/Function1;)V
const #23 = Method	#19.#22;	//  scala/Function1$class.$init$:(Lscala/Function1;)V
const #24 = Asciz	apply;
const #25 = Asciz	(Ljava/lang/Object;)Ljava/lang/Object;;
const #26 = Asciz	scala/collection/mutable/StringBuilder;
const #27 = class	#26;	//  scala/collection/mutable/StringBuilder
const #28 = Asciz	(Lscala/collection/mutable/StringBuilder;)V;
const #29 = NameAndType	#24:#28;//  apply:(Lscala/collection/mutable/StringBuilder;)V
const #30 = Method	#10.#29;	//  scala/xml/Xhtml$$anonfun$toXhtml$2.apply:(Lscala/collection/mutable/StringBuilder;)V
const #31 = Asciz	scala/runtime/BoxedUnit;
const #32 = class	#31;	//  scala/runtime/BoxedUnit
const #33 = Asciz	UNIT;
const #34 = Asciz	Lscala/runtime/BoxedUnit;;
const #35 = NameAndType	#33:#34;//  UNIT:Lscala/runtime/BoxedUnit;
const #36 = Field	#32.#35;	//  scala/runtime/BoxedUnit.UNIT:Lscala/runtime/BoxedUnit;
const #37 = Asciz	this;
const #38 = Asciz	Lscala/xml/Xhtml$$anonfun$toXhtml$2;;
const #39 = Asciz	v1;
const #40 = Asciz	Ljava/lang/Object;;
const #41 = Asciz	LocalVariableTable;
const #42 = Asciz	scala/xml/Xhtml$;
const #43 = class	#42;	//  scala/xml/Xhtml$
const #44 = Asciz	MODULE$;
const #45 = Asciz	Lscala/xml/Xhtml$;;
const #46 = NameAndType	#44:#45;//  MODULE$:Lscala/xml/Xhtml$;
const #47 = Field	#43.#46;	//  scala/xml/Xhtml$.MODULE$:Lscala/xml/Xhtml$;
const #48 = Asciz	sequenceToXML$default$2;
const #49 = Asciz	()Lscala/xml/NamespaceBinding;;
const #50 = NameAndType	#48:#49;//  sequenceToXML$default$2:()Lscala/xml/NamespaceBinding;
const #51 = Method	#43.#50;	//  scala/xml/Xhtml$.sequenceToXML$default$2:()Lscala/xml/NamespaceBinding;
const #52 = Asciz	sequenceToXML$default$4;
const #53 = Asciz	()Z;
const #54 = NameAndType	#52:#53;//  sequenceToXML$default$4:()Z
const #55 = Method	#43.#54;	//  scala/xml/Xhtml$.sequenceToXML$default$4:()Z
const #56 = Asciz	sequenceToXML$default$5;
const #57 = NameAndType	#56:#53;//  sequenceToXML$default$5:()Z
const #58 = Method	#43.#57;	//  scala/xml/Xhtml$.sequenceToXML$default$5:()Z
const #59 = Asciz	sequenceToXML$default$6;
const #60 = NameAndType	#59:#53;//  sequenceToXML$default$6:()Z
const #61 = Method	#43.#60;	//  scala/xml/Xhtml$.sequenceToXML$default$6:()Z
const #62 = Asciz	sequenceToXML$default$7;
const #63 = NameAndType	#62:#53;//  sequenceToXML$default$7:()Z
const #64 = Method	#43.#63;	//  scala/xml/Xhtml$.sequenceToXML$default$7:()Z
const #65 = Asciz	sequenceToXML;
const #66 = Asciz	(Lscala/collection/Sequence;Lscala/xml/NamespaceBinding;Lscala/collection/mutable/StringBuilder;ZZZZ)V;
const #67 = NameAndType	#65:#66;//  sequenceToXML:(Lscala/collection/Sequence;Lscala/xml/NamespaceBinding;Lscala/collection/mutable/StringBuilder;ZZZZ)V
const #68 = Method	#43.#67;	//  scala/xml/Xhtml$.sequenceToXML:(Lscala/collection/Sequence;Lscala/xml/NamespaceBinding;Lscala/collection/mutable/StringBuilder;ZZZZ)V
const #69 = Asciz	x$11;
const #70 = Asciz	Lscala/collection/Sequence;;
const #71 = Asciz	x$12;
const #72 = Asciz	Lscala/collection/mutable/StringBuilder;;
const #73 = Asciz	x$13;
const #74 = Asciz	Lscala/xml/NamespaceBinding;;
const #75 = Asciz	x$14;
const #76 = Asciz	Z;
const #77 = Asciz	x$15;
const #78 = Asciz	x$16;
const #79 = Asciz	x$17;
const #80 = Asciz	andThen;
const #81 = Asciz	(Lscala/Function1;)Lscala/Function1;;
const #82 = Asciz	(Lscala/Function1;Lscala/Function1;)Lscala/Function1;;
const #83 = NameAndType	#80:#82;//  andThen:(Lscala/Function1;Lscala/Function1;)Lscala/Function1;
const #84 = Method	#19.#83;	//  scala/Function1$class.andThen:(Lscala/Function1;Lscala/Function1;)Lscala/Function1;
const #85 = Asciz	g;
const #86 = Asciz	Lscala/Function1;;
const #87 = Asciz	compose;
const #88 = NameAndType	#87:#82;//  compose:(Lscala/Function1;Lscala/Function1;)Lscala/Function1;
const #89 = Method	#19.#88;	//  scala/Function1$class.compose:(Lscala/Function1;Lscala/Function1;)Lscala/Function1;
const #90 = Asciz	toString;
const #91 = Asciz	()Ljava/lang/String;;
const #92 = Asciz	(Lscala/Function1;)Ljava/lang/String;;
const #93 = NameAndType	#90:#92;//  toString:(Lscala/Function1;)Ljava/lang/String;
const #94 = Method	#19.#93;	//  scala/Function1$class.toString:(Lscala/Function1;)Ljava/lang/String;
const #95 = Asciz	Scala;
const #96 = Asciz	InnerClasses;
const #97 = Asciz	scala/xml/Xhtml;
const #98 = class	#97;	//  scala/xml/Xhtml
const #99 = Asciz	$anonfun$toXhtml$2;
const #100 = Asciz	scala/Function1;
const #101 = class	#100;	//  scala/Function1
const #102 = Asciz	scala/ScalaObject;
const #103 = class	#102;	//  scala/ScalaObject
const #104 = Asciz	java/io/Serializable;
const #105 = class	#104;	//  java/io/Serializable

{
public scala.xml.Xhtml$$anonfun$toXhtml$2(scala.xml.NodeSeq);
  Code:
   Stack=2, Locals=2, Args_size=2
   0:	aload_0
   1:	aload_1
   2:	putfield	#12; //Field nodeSeq$1:Lscala/xml/NodeSeq;
   5:	aload_0
   6:	invokespecial	#17; //Method java/lang/Object."<init>":()V
   9:	aload_0
   10:	invokestatic	#23; //Method scala/Function1$class.$init$:(Lscala/Function1;)V
   13:	return
  LineNumberTable: 
   line 25: 0


public final java.lang.Object apply(java.lang.Object);
  Code:
   Stack=2, Locals=2, Args_size=2
   0:	aload_0
   1:	aload_1
   2:	checkcast	#27; //class scala/collection/mutable/StringBuilder
   5:	invokevirtual	#30; //Method apply:(Lscala/collection/mutable/StringBuilder;)V
   8:	getstatic	#36; //Field scala/runtime/BoxedUnit.UNIT:Lscala/runtime/BoxedUnit;
   11:	areturn
  LineNumberTable: 
   line 25: 0

  LocalVariableTable: 
   Start  Length  Slot  Name   Signature
   0      12      0    this       Lscala/xml/Xhtml$$anonfun$toXhtml$2;
   0      12      1    v1       Ljava/lang/Object;


public final void apply(scala.collection.mutable.StringBuilder);
  Code:
   Stack=8, Locals=9, Args_size=2
   0:	aload_0
   1:	getfield	#12; //Field nodeSeq$1:Lscala/xml/NodeSeq;
   4:	astore_2
   5:	aload_1
   6:	astore_3
   7:	getstatic	#47; //Field scala/xml/Xhtml$.MODULE$:Lscala/xml/Xhtml$;
   10:	invokevirtual	#51; //Method scala/xml/Xhtml$.sequenceToXML$default$2:()Lscala/xml/NamespaceBinding;
   13:	astore	4
   15:	getstatic	#47; //Field scala/xml/Xhtml$.MODULE$:Lscala/xml/Xhtml$;
   18:	invokevirtual	#55; //Method scala/xml/Xhtml$.sequenceToXML$default$4:()Z
   21:	istore	5
   23:	getstatic	#47; //Field scala/xml/Xhtml$.MODULE$:Lscala/xml/Xhtml$;
   26:	invokevirtual	#58; //Method scala/xml/Xhtml$.sequenceToXML$default$5:()Z
   29:	istore	6
   31:	getstatic	#47; //Field scala/xml/Xhtml$.MODULE$:Lscala/xml/Xhtml$;
   34:	invokevirtual	#61; //Method scala/xml/Xhtml$.sequenceToXML$default$6:()Z
   37:	istore	7
   39:	getstatic	#47; //Field scala/xml/Xhtml$.MODULE$:Lscala/xml/Xhtml$;
   42:	invokevirtual	#64; //Method scala/xml/Xhtml$.sequenceToXML$default$7:()Z
   45:	istore	8
   47:	getstatic	#47; //Field scala/xml/Xhtml$.MODULE$:Lscala/xml/Xhtml$;
   50:	aload_2
   51:	aload	4
   53:	aload_3
   54:	iload	5
   56:	iload	6
   58:	iload	7
   60:	iload	8
   62:	invokevirtual	#68; //Method scala/xml/Xhtml$.sequenceToXML:(Lscala/collection/Sequence;Lscala/xml/NamespaceBinding;Lscala/collection/mutable/StringBuilder;ZZZZ)V
   65:	return
  LineNumberTable: 
   line 25: 0

  LocalVariableTable: 
   Start  Length  Slot  Name   Signature
   0      66      0    this       Lscala/xml/Xhtml$$anonfun$toXhtml$2;
   5      60      2    x$11       Lscala/collection/Sequence;
   7      58      3    x$12       Lscala/collection/mutable/StringBuilder;
   15      50      4    x$13       Lscala/xml/NamespaceBinding;
   23      42      5    x$14       Z
   31      34      6    x$15       Z
   39      26      7    x$16       Z
   47      18      8    x$17       Z


public scala.Function1 andThen(scala.Function1);
  Code:
   Stack=2, Locals=2, Args_size=2
   0:	aload_0
   1:	aload_1
   2:	invokestatic	#84; //Method scala/Function1$class.andThen:(Lscala/Function1;Lscala/Function1;)Lscala/Function1;
   5:	areturn
  LineNumberTable: 
   line 25: 0

  LocalVariableTable: 
   Start  Length  Slot  Name   Signature
   0      6      0    this       Lscala/xml/Xhtml$$anonfun$toXhtml$2;
   0      6      1    g       Lscala/Function1;


public scala.Function1 compose(scala.Function1);
  Code:
   Stack=2, Locals=2, Args_size=2
   0:	aload_0
   1:	aload_1
   2:	invokestatic	#89; //Method scala/Function1$class.compose:(Lscala/Function1;Lscala/Function1;)Lscala/Function1;
   5:	areturn
  LineNumberTable: 
   line 25: 0

  LocalVariableTable: 
   Start  Length  Slot  Name   Signature
   0      6      0    this       Lscala/xml/Xhtml$$anonfun$toXhtml$2;
   0      6      1    g       Lscala/Function1;


public java.lang.String toString();
  Code:
   Stack=1, Locals=1, Args_size=1
   0:	aload_0
   1:	invokestatic	#94; //Method scala/Function1$class.toString:(Lscala/Function1;)Ljava/lang/String;
   4:	areturn
  LineNumberTable: 
   line 25: 0


}

