Compiled from "XML.scala"
public final class scala.xml.XML$$anonfun$save$2 extends java.lang.Object implements scala.Function0,scala.ScalaObject,java.io.Serializable
  SourceFile: "XML.scala"
  Scala: length = 0x
   
  InnerClass: 
   public final #74= #9 of #73; //$anonfun$save$2=class scala/xml/XML$$anonfun$save$2 of class scala/xml/XML
  minor version: 0
  major version: 49
  Constant pool:
const #1 = Asciz	SourceFile;
const #2 = Asciz	XML.scala;
const #3 = Asciz	<clinit>;
const #4 = Asciz	()V;
const #5 = Asciz	Code;
const #6 = Asciz	serialVersionUID;
const #7 = Asciz	J;
const #8 = Asciz	scala/xml/XML$$anonfun$save$2;
const #9 = class	#8;	//  scala/xml/XML$$anonfun$save$2
const #10 = NameAndType	#6:#7;//  serialVersionUID:J
const #11 = Field	#9.#10;	//  scala/xml/XML$$anonfun$save$2.serialVersionUID:J
const #12 = Asciz	w$1;
const #13 = Asciz	Ljava/io/Writer;;
const #14 = Asciz	doctype$1;
const #15 = Asciz	Lscala/xml/dtd/DocType;;
const #16 = Asciz	xmlDecl$1;
const #17 = Asciz	Z;
const #18 = Asciz	enc$1;
const #19 = Asciz	Ljava/lang/String;;
const #20 = Asciz	node$1;
const #21 = Asciz	Lscala/xml/Node;;
const #22 = Asciz	<init>;
const #23 = Asciz	(Lscala/xml/Node;Ljava/lang/String;ZLscala/xml/dtd/DocType;Ljava/io/Writer;)V;
const #24 = Asciz	LineNumberTable;
const #25 = NameAndType	#20:#21;//  node$1:Lscala/xml/Node;
const #26 = Field	#9.#25;	//  scala/xml/XML$$anonfun$save$2.node$1:Lscala/xml/Node;
const #27 = NameAndType	#18:#19;//  enc$1:Ljava/lang/String;
const #28 = Field	#9.#27;	//  scala/xml/XML$$anonfun$save$2.enc$1:Ljava/lang/String;
const #29 = NameAndType	#16:#17;//  xmlDecl$1:Z
const #30 = Field	#9.#29;	//  scala/xml/XML$$anonfun$save$2.xmlDecl$1:Z
const #31 = NameAndType	#14:#15;//  doctype$1:Lscala/xml/dtd/DocType;
const #32 = Field	#9.#31;	//  scala/xml/XML$$anonfun$save$2.doctype$1:Lscala/xml/dtd/DocType;
const #33 = NameAndType	#12:#13;//  w$1:Ljava/io/Writer;
const #34 = Field	#9.#33;	//  scala/xml/XML$$anonfun$save$2.w$1:Ljava/io/Writer;
const #35 = Asciz	java/lang/Object;
const #36 = class	#35;	//  java/lang/Object
const #37 = NameAndType	#22:#4;//  "<init>":()V
const #38 = Method	#36.#37;	//  java/lang/Object."<init>":()V
const #39 = Asciz	scala/Function0$class;
const #40 = class	#39;	//  scala/Function0$class
const #41 = Asciz	$init$;
const #42 = Asciz	(Lscala/Function0;)V;
const #43 = NameAndType	#41:#42;//  $init$:(Lscala/Function0;)V
const #44 = Method	#40.#43;	//  scala/Function0$class.$init$:(Lscala/Function0;)V
const #45 = Asciz	apply;
const #46 = Asciz	()Ljava/lang/Object;;
const #47 = NameAndType	#45:#4;//  apply:()V
const #48 = Method	#9.#47;	//  scala/xml/XML$$anonfun$save$2.apply:()V
const #49 = Asciz	scala/runtime/BoxedUnit;
const #50 = class	#49;	//  scala/runtime/BoxedUnit
const #51 = Asciz	UNIT;
const #52 = Asciz	Lscala/runtime/BoxedUnit;;
const #53 = NameAndType	#51:#52;//  UNIT:Lscala/runtime/BoxedUnit;
const #54 = Field	#50.#53;	//  scala/runtime/BoxedUnit.UNIT:Lscala/runtime/BoxedUnit;
const #55 = Asciz	scala/xml/XML$;
const #56 = class	#55;	//  scala/xml/XML$
const #57 = Asciz	MODULE$;
const #58 = Asciz	Lscala/xml/XML$;;
const #59 = NameAndType	#57:#58;//  MODULE$:Lscala/xml/XML$;
const #60 = Field	#56.#59;	//  scala/xml/XML$.MODULE$:Lscala/xml/XML$;
const #61 = Asciz	write;
const #62 = Asciz	(Ljava/io/Writer;Lscala/xml/Node;Ljava/lang/String;ZLscala/xml/dtd/DocType;)V;
const #63 = NameAndType	#61:#62;//  write:(Ljava/io/Writer;Lscala/xml/Node;Ljava/lang/String;ZLscala/xml/dtd/DocType;)V
const #64 = Method	#56.#63;	//  scala/xml/XML$.write:(Ljava/io/Writer;Lscala/xml/Node;Ljava/lang/String;ZLscala/xml/dtd/DocType;)V
const #65 = Asciz	toString;
const #66 = Asciz	()Ljava/lang/String;;
const #67 = Asciz	(Lscala/Function0;)Ljava/lang/String;;
const #68 = NameAndType	#65:#67;//  toString:(Lscala/Function0;)Ljava/lang/String;
const #69 = Method	#40.#68;	//  scala/Function0$class.toString:(Lscala/Function0;)Ljava/lang/String;
const #70 = Asciz	Scala;
const #71 = Asciz	InnerClasses;
const #72 = Asciz	scala/xml/XML;
const #73 = class	#72;	//  scala/xml/XML
const #74 = Asciz	$anonfun$save$2;
const #75 = Asciz	scala/Function0;
const #76 = class	#75;	//  scala/Function0
const #77 = Asciz	scala/ScalaObject;
const #78 = class	#77;	//  scala/ScalaObject
const #79 = Asciz	java/io/Serializable;
const #80 = class	#79;	//  java/io/Serializable

{
public static final long serialVersionUID;

public static {};
  Code:
   Stack=2, Locals=0, Args_size=0
   0:	lconst_0
   1:	putstatic	#11; //Field serialVersionUID:J
   4:	return

public scala.xml.XML$$anonfun$save$2(scala.xml.Node, java.lang.String, boolean, scala.xml.dtd.DocType, java.io.Writer);
  Code:
   Stack=2, Locals=6, Args_size=6
   0:	aload_0
   1:	aload_1
   2:	putfield	#26; //Field node$1:Lscala/xml/Node;
   5:	aload_0
   6:	aload_2
   7:	putfield	#28; //Field enc$1:Ljava/lang/String;
   10:	aload_0
   11:	iload_3
   12:	putfield	#30; //Field xmlDecl$1:Z
   15:	aload_0
   16:	aload	4
   18:	putfield	#32; //Field doctype$1:Lscala/xml/dtd/DocType;
   21:	aload_0
   22:	aload	5
   24:	putfield	#34; //Field w$1:Ljava/io/Writer;
   27:	aload_0
   28:	invokespecial	#38; //Method java/lang/Object."<init>":()V
   31:	aload_0
   32:	invokestatic	#44; //Method scala/Function0$class.$init$:(Lscala/Function0;)V
   35:	return
  LineNumberTable: 
   line 86: 0


public final java.lang.Object apply();
  Code:
   Stack=1, Locals=1, Args_size=1
   0:	aload_0
   1:	invokevirtual	#48; //Method apply:()V
   4:	getstatic	#54; //Field scala/runtime/BoxedUnit.UNIT:Lscala/runtime/BoxedUnit;
   7:	areturn
  LineNumberTable: 
   line 86: 0


public final void apply();
  Code:
   Stack=6, Locals=1, Args_size=1
   0:	getstatic	#60; //Field scala/xml/XML$.MODULE$:Lscala/xml/XML$;
   3:	aload_0
   4:	getfield	#34; //Field w$1:Ljava/io/Writer;
   7:	aload_0
   8:	getfield	#26; //Field node$1:Lscala/xml/Node;
   11:	aload_0
   12:	getfield	#28; //Field enc$1:Ljava/lang/String;
   15:	aload_0
   16:	getfield	#30; //Field xmlDecl$1:Z
   19:	aload_0
   20:	getfield	#32; //Field doctype$1:Lscala/xml/dtd/DocType;
   23:	invokevirtual	#64; //Method scala/xml/XML$.write:(Ljava/io/Writer;Lscala/xml/Node;Ljava/lang/String;ZLscala/xml/dtd/DocType;)V
   26:	return
  LineNumberTable: 
   line 86: 0


public java.lang.String toString();
  Code:
   Stack=1, Locals=1, Args_size=1
   0:	aload_0
   1:	invokestatic	#69; //Method scala/Function0$class.toString:(Lscala/Function0;)Ljava/lang/String;
   4:	areturn
  LineNumberTable: 
   line 86: 0


}

