Compiled from "XML.scala"
public final class scala.xml.XML$$anonfun$save$1 extends java.lang.Object implements scala.Function0,scala.ScalaObject,java.io.Serializable
  SourceFile: "XML.scala"
  Scala: length = 0x
   
  InnerClass: 
   public final $anonfun$save$1=class scala/xml/XML$$anonfun$save$1 of class scala/xml/XML
  minor version: 0
  major version: 49
  Constant pool:
Asciz	SourceFile;
Asciz	XML.scala;
Asciz	<clinit>;
Asciz	()V;
Asciz	Code;
Asciz	serialVersionUID;
Asciz	J;
Asciz	scala/xml/XML$$anonfun$save$1;
class	scala/xml/XML$$anonfun$save$1
NameAndType	serialVersionUID:J
Field	scala/xml/XML$$anonfun$save$1.serialVersionUID:J
Asciz	w$1;
Asciz	Ljava/io/Writer;;
Asciz	fos$1;
Asciz	Ljava/io/FileOutputStream;;
Asciz	<init>;
Asciz	(Ljava/io/FileOutputStream;Ljava/io/Writer;)V;
Asciz	LineNumberTable;
NameAndType	fos$1:Ljava/io/FileOutputStream;
Field	scala/xml/XML$$anonfun$save$1.fos$1:Ljava/io/FileOutputStream;
NameAndType	w$1:Ljava/io/Writer;
Field	scala/xml/XML$$anonfun$save$1.w$1:Ljava/io/Writer;
Asciz	java/lang/Object;
class	java/lang/Object
NameAndType	"<init>":()V
Method	java/lang/Object."<init>":()V
Asciz	scala/Function0$class;
class	scala/Function0$class
Asciz	$init$;
Asciz	(Lscala/Function0;)V;
NameAndType	$init$:(Lscala/Function0;)V
Method	scala/Function0$class.$init$:(Lscala/Function0;)V
Asciz	apply;
Asciz	()Ljava/lang/Object;;
NameAndType	apply:()V
Method	scala/xml/XML$$anonfun$save$1.apply:()V
Asciz	scala/runtime/BoxedUnit;
class	scala/runtime/BoxedUnit
Asciz	UNIT;
Asciz	Lscala/runtime/BoxedUnit;;
NameAndType	UNIT:Lscala/runtime/BoxedUnit;
Field	scala/runtime/BoxedUnit.UNIT:Lscala/runtime/BoxedUnit;
Asciz	java/io/Writer;
class	java/io/Writer
Asciz	close;
NameAndType	close:()V
Method	java/io/Writer.close:()V
Asciz	java/io/FileOutputStream;
class	java/io/FileOutputStream
Method	java/io/FileOutputStream.close:()V
Asciz	toString;
Asciz	()Ljava/lang/String;;
Asciz	(Lscala/Function0;)Ljava/lang/String;;
NameAndType	toString:(Lscala/Function0;)Ljava/lang/String;
Method	scala/Function0$class.toString:(Lscala/Function0;)Ljava/lang/String;
Asciz	Scala;
Asciz	InnerClasses;
Asciz	scala/xml/XML;
class	scala/xml/XML
Asciz	$anonfun$save$1;
Asciz	scala/Function0;
class	scala/Function0
Asciz	scala/ScalaObject;
class	scala/ScalaObject
Asciz	java/io/Serializable;
class	java/io/Serializable

{
public static final long serialVersionUID;
  Signature: J

private final java.io.Writer w$1;
  Signature: Ljava/io/Writer;

private final java.io.FileOutputStream fos$1;
  Signature: Ljava/io/FileOutputStream;

public static {};
  Signature: ()V
  Code:
   Stack=2, Locals=0, Args_size=0
	lconst_0
	putstatic	Field serialVersionUID:J
	return
  Labels:

public scala.xml.XML$$anonfun$save$1(java.io.FileOutputStream, java.io.Writer);
  Signature: (Ljava/io/FileOutputStream;Ljava/io/Writer;)V
  Code:
   Stack=2, Locals=3, Args_size=3
	aload_0
	aload_1
	putfield	Field fos$1:Ljava/io/FileOutputStream;
	aload_0
	aload_2
	putfield	Field w$1:Ljava/io/Writer;
	aload_0
	invokespecial	Method java/lang/Object."<init>":()V
	aload_0
	invokestatic	Method scala/Function0$class.$init$:(Lscala/Function0;)V
	return
  Labels:

public final java.lang.Object apply();
  Signature: ()Ljava/lang/Object;
  Code:
   Stack=1, Locals=1, Args_size=1
	aload_0
	invokevirtual	Method apply:()V
	getstatic	Field scala/runtime/BoxedUnit.UNIT:Lscala/runtime/BoxedUnit;
	areturn
  Labels:

public final void apply();
  Signature: ()V
  Code:
   Stack=1, Locals=1, Args_size=1
	aload_0
	getfield	Field w$1:Ljava/io/Writer;
	invokevirtual	Method java/io/Writer.close:()V
	aload_0
	getfield	Field fos$1:Ljava/io/FileOutputStream;
	invokevirtual	Method java/io/FileOutputStream.close:()V
	return
  Labels:

public java.lang.String toString();
  Signature: ()Ljava/lang/String;
  Code:
   Stack=1, Locals=1, Args_size=1
	aload_0
	invokestatic	Method scala/Function0$class.toString:(Lscala/Function0;)Ljava/lang/String;
	areturn
  Labels:

}

