Compiled from "XML.scala"
public final class scala.xml.XML$$anon$1 extends java.lang.Object implements scala.xml.factory.XMLLoader
  SourceFile: "XML.scala"
  Signature: length = 0x2
   00 60 
  Scala: length = 0x
   
  InnerClass: 
   public final $anon$1=class scala/xml/XML$$anon$1 of class scala/xml/XML
  minor version: 0
  major version: 49
  Constant pool:
Asciz	SourceFile;
Asciz	XML.scala;
Asciz	scala$xml$factory$XMLLoader$$saxFactory;
Asciz	Ljavax/xml/parsers/SAXParserFactory;;
Asciz	parser;
Asciz	Ljavax/xml/parsers/SAXParser;;
Asciz	()Ljavax/xml/parsers/SAXParserFactory;;
Asciz	Code;
Asciz	LineNumberTable;
Asciz	scala/xml/XML$$anon$1;
class	scala/xml/XML$$anon$1
NameAndType	scala$xml$factory$XMLLoader$$saxFactory:Ljavax/xml/parsers/SAXParserFactory;
Field	scala/xml/XML$$anon$1.scala$xml$factory$XMLLoader$$saxFactory:Ljavax/xml/parsers/SAXParserFactory;
Asciz	scala$xml$factory$XMLLoader$_setter_$scala$xml$factory$XMLLoader$$saxFactory_$eq;
Asciz	(Ljavax/xml/parsers/SAXParserFactory;)V;
Asciz	adapter;
Asciz	()Lscala/xml/parsing/FactoryAdapter;;
Asciz	scala/xml/factory/XMLLoader$class;
class	scala/xml/factory/XMLLoader$class
Asciz	(Lscala/xml/factory/XMLLoader;)Lscala/xml/parsing/FactoryAdapter;;
NameAndType	adapter:(Lscala/xml/factory/XMLLoader;)Lscala/xml/parsing/FactoryAdapter;
Method	scala/xml/factory/XMLLoader$class.adapter:(Lscala/xml/factory/XMLLoader;)Lscala/xml/parsing/FactoryAdapter;
Asciz	loadXML;
Asciz	(Lorg/xml/sax/InputSource;Ljavax/xml/parsers/SAXParser;)Lscala/xml/Node;;
Asciz	(Lscala/xml/factory/XMLLoader;Lorg/xml/sax/InputSource;Ljavax/xml/parsers/SAXParser;)Lscala/xml/Node;;
NameAndType	loadXML:(Lscala/xml/factory/XMLLoader;Lorg/xml/sax/InputSource;Ljavax/xml/parsers/SAXParser;)Lscala/xml/Node;
Method	scala/xml/factory/XMLLoader$class.loadXML:(Lscala/xml/factory/XMLLoader;Lorg/xml/sax/InputSource;Ljavax/xml/parsers/SAXParser;)Lscala/xml/Node;
Asciz	this;
Asciz	Lscala/xml/XML$$anon$1;;
Asciz	source;
Asciz	Lorg/xml/sax/InputSource;;
Asciz	LocalVariableTable;
Asciz	loadFile;
Asciz	(Ljava/io/File;)Lscala/xml/Node;;
Asciz	(Lscala/xml/factory/XMLLoader;Ljava/io/File;)Lscala/xml/Node;;
NameAndType	loadFile:(Lscala/xml/factory/XMLLoader;Ljava/io/File;)Lscala/xml/Node;
Method	scala/xml/factory/XMLLoader$class.loadFile:(Lscala/xml/factory/XMLLoader;Ljava/io/File;)Lscala/xml/Node;
Asciz	file;
Asciz	Ljava/io/File;;
Asciz	(Ljava/io/FileDescriptor;)Lscala/xml/Node;;
Asciz	(Lscala/xml/factory/XMLLoader;Ljava/io/FileDescriptor;)Lscala/xml/Node;;
NameAndType	loadFile:(Lscala/xml/factory/XMLLoader;Ljava/io/FileDescriptor;)Lscala/xml/Node;
Method	scala/xml/factory/XMLLoader$class.loadFile:(Lscala/xml/factory/XMLLoader;Ljava/io/FileDescriptor;)Lscala/xml/Node;
Asciz	fd;
Asciz	Ljava/io/FileDescriptor;;
Asciz	(Ljava/lang/String;)Lscala/xml/Node;;
Asciz	(Lscala/xml/factory/XMLLoader;Ljava/lang/String;)Lscala/xml/Node;;
NameAndType	loadFile:(Lscala/xml/factory/XMLLoader;Ljava/lang/String;)Lscala/xml/Node;
Method	scala/xml/factory/XMLLoader$class.loadFile:(Lscala/xml/factory/XMLLoader;Ljava/lang/String;)Lscala/xml/Node;
Asciz	name;
Asciz	Ljava/lang/String;;
Asciz	load;
Asciz	(Ljava/io/InputStream;)Lscala/xml/Node;;
Asciz	(Lscala/xml/factory/XMLLoader;Ljava/io/InputStream;)Lscala/xml/Node;;
NameAndType	load:(Lscala/xml/factory/XMLLoader;Ljava/io/InputStream;)Lscala/xml/Node;
Method	scala/xml/factory/XMLLoader$class.load:(Lscala/xml/factory/XMLLoader;Ljava/io/InputStream;)Lscala/xml/Node;
Asciz	is;
Asciz	Ljava/io/InputStream;;
Asciz	(Ljava/io/Reader;)Lscala/xml/Node;;
Asciz	(Lscala/xml/factory/XMLLoader;Ljava/io/Reader;)Lscala/xml/Node;;
NameAndType	load:(Lscala/xml/factory/XMLLoader;Ljava/io/Reader;)Lscala/xml/Node;
Method	scala/xml/factory/XMLLoader$class.load:(Lscala/xml/factory/XMLLoader;Ljava/io/Reader;)Lscala/xml/Node;
Asciz	reader;
Asciz	Ljava/io/Reader;;
NameAndType	load:(Lscala/xml/factory/XMLLoader;Ljava/lang/String;)Lscala/xml/Node;
Method	scala/xml/factory/XMLLoader$class.load:(Lscala/xml/factory/XMLLoader;Ljava/lang/String;)Lscala/xml/Node;
Asciz	sysID;
Asciz	(Lorg/xml/sax/InputSource;)Lscala/xml/Node;;
Asciz	(Lscala/xml/factory/XMLLoader;Lorg/xml/sax/InputSource;)Lscala/xml/Node;;
NameAndType	load:(Lscala/xml/factory/XMLLoader;Lorg/xml/sax/InputSource;)Lscala/xml/Node;
Method	scala/xml/factory/XMLLoader$class.load:(Lscala/xml/factory/XMLLoader;Lorg/xml/sax/InputSource;)Lscala/xml/Node;
Asciz	(Ljava/net/URL;)Lscala/xml/Node;;
Asciz	(Lscala/xml/factory/XMLLoader;Ljava/net/URL;)Lscala/xml/Node;;
NameAndType	load:(Lscala/xml/factory/XMLLoader;Ljava/net/URL;)Lscala/xml/Node;
Method	scala/xml/factory/XMLLoader$class.load:(Lscala/xml/factory/XMLLoader;Ljava/net/URL;)Lscala/xml/Node;
Asciz	url;
Asciz	Ljava/net/URL;;
Asciz	loadString;
NameAndType	loadString:(Lscala/xml/factory/XMLLoader;Ljava/lang/String;)Lscala/xml/Node;
Method	scala/xml/factory/XMLLoader$class.loadString:(Lscala/xml/factory/XMLLoader;Ljava/lang/String;)Lscala/xml/Node;
Asciz	string;
Asciz	()Ljavax/xml/parsers/SAXParser;;
NameAndType	parser:Ljavax/xml/parsers/SAXParser;
Field	scala/xml/XML$$anon$1.parser:Ljavax/xml/parsers/SAXParser;
Asciz	<init>;
Asciz	(Ljavax/xml/parsers/SAXParser;)V;
Asciz	java/lang/Object;
class	java/lang/Object
Asciz	()V;
NameAndType	"<init>":()V
Method	java/lang/Object."<init>":()V
Asciz	$init$;
Asciz	(Lscala/xml/factory/XMLLoader;)V;
NameAndType	$init$:(Lscala/xml/factory/XMLLoader;)V
Method	scala/xml/factory/XMLLoader$class.$init$:(Lscala/xml/factory/XMLLoader;)V
Asciz	Ljava/lang/Object;Lscala/xml/factory/XMLLoader<Lscala/xml/Elem;>;;
Asciz	Signature;
Asciz	Scala;
Asciz	InnerClasses;
Asciz	scala/xml/XML;
class	scala/xml/XML
Asciz	$anon$1;
Asciz	scala/xml/factory/XMLLoader;
class	scala/xml/factory/XMLLoader

{
private final javax.xml.parsers.SAXParserFactory scala$xml$factory$XMLLoader$$saxFactory;
  Signature: Ljavax/xml/parsers/SAXParserFactory;

private final javax.xml.parsers.SAXParser parser;
  Signature: Ljavax/xml/parsers/SAXParser;

public final javax.xml.parsers.SAXParserFactory scala$xml$factory$XMLLoader$$saxFactory();
  Signature: ()Ljavax/xml/parsers/SAXParserFactory;
  Code:
   Stack=1, Locals=1, Args_size=1
	aload_0
	getfield	Field scala$xml$factory$XMLLoader$$saxFactory:Ljavax/xml/parsers/SAXParserFactory;
	areturn
  Labels:

public void scala$xml$factory$XMLLoader$_setter_$scala$xml$factory$XMLLoader$$saxFactory_$eq(javax.xml.parsers.SAXParserFactory);
  Signature: (Ljavax/xml/parsers/SAXParserFactory;)V
  Code:
   Stack=2, Locals=2, Args_size=2
	aload_0
	aload_1
	putfield	Field scala$xml$factory$XMLLoader$$saxFactory:Ljavax/xml/parsers/SAXParserFactory;
	return
  Labels:

public scala.xml.parsing.FactoryAdapter adapter();
  Signature: ()Lscala/xml/parsing/FactoryAdapter;
  Code:
   Stack=1, Locals=1, Args_size=1
	aload_0
	invokestatic	Method scala/xml/factory/XMLLoader$class.adapter:(Lscala/xml/factory/XMLLoader;)Lscala/xml/parsing/FactoryAdapter;
	areturn
  Labels:

public scala.xml.Node loadXML(org.xml.sax.InputSource, javax.xml.parsers.SAXParser);
  Signature: (Lorg/xml/sax/InputSource;Ljavax/xml/parsers/SAXParser;)Lscala/xml/Node;
  Code:
   Stack=3, Locals=3, Args_size=3
	aload_0
	aload_1
	aload_2
	invokestatic	Method scala/xml/factory/XMLLoader$class.loadXML:(Lscala/xml/factory/XMLLoader;Lorg/xml/sax/InputSource;Ljavax/xml/parsers/SAXParser;)Lscala/xml/Node;
	areturn
  Labels:
  LocalVariableTable: 
   Start  Length  Slot  Name   Signature
   0      7      0    this       Lscala/xml/XML$$anon$1;
   0      7      1    source       Lorg/xml/sax/InputSource;
   0      7      2    parser       Ljavax/xml/parsers/SAXParser;


public scala.xml.Node loadFile(java.io.File);
  Signature: (Ljava/io/File;)Lscala/xml/Node;
  Code:
   Stack=2, Locals=2, Args_size=2
	aload_0
	aload_1
	invokestatic	Method scala/xml/factory/XMLLoader$class.loadFile:(Lscala/xml/factory/XMLLoader;Ljava/io/File;)Lscala/xml/Node;
	areturn
  Labels:
  LocalVariableTable: 
   Start  Length  Slot  Name   Signature
   0      6      0    this       Lscala/xml/XML$$anon$1;
   0      6      1    file       Ljava/io/File;


public scala.xml.Node loadFile(java.io.FileDescriptor);
  Signature: (Ljava/io/FileDescriptor;)Lscala/xml/Node;
  Code:
   Stack=2, Locals=2, Args_size=2
	aload_0
	aload_1
	invokestatic	Method scala/xml/factory/XMLLoader$class.loadFile:(Lscala/xml/factory/XMLLoader;Ljava/io/FileDescriptor;)Lscala/xml/Node;
	areturn
  Labels:
  LocalVariableTable: 
   Start  Length  Slot  Name   Signature
   0      6      0    this       Lscala/xml/XML$$anon$1;
   0      6      1    fd       Ljava/io/FileDescriptor;


public scala.xml.Node loadFile(java.lang.String);
  Signature: (Ljava/lang/String;)Lscala/xml/Node;
  Code:
   Stack=2, Locals=2, Args_size=2
	aload_0
	aload_1
	invokestatic	Method scala/xml/factory/XMLLoader$class.loadFile:(Lscala/xml/factory/XMLLoader;Ljava/lang/String;)Lscala/xml/Node;
	areturn
  Labels:
  LocalVariableTable: 
   Start  Length  Slot  Name   Signature
   0      6      0    this       Lscala/xml/XML$$anon$1;
   0      6      1    name       Ljava/lang/String;


public scala.xml.Node load(java.io.InputStream);
  Signature: (Ljava/io/InputStream;)Lscala/xml/Node;
  Code:
   Stack=2, Locals=2, Args_size=2
	aload_0
	aload_1
	invokestatic	Method scala/xml/factory/XMLLoader$class.load:(Lscala/xml/factory/XMLLoader;Ljava/io/InputStream;)Lscala/xml/Node;
	areturn
  Labels:
  LocalVariableTable: 
   Start  Length  Slot  Name   Signature
   0      6      0    this       Lscala/xml/XML$$anon$1;
   0      6      1    is       Ljava/io/InputStream;


public scala.xml.Node load(java.io.Reader);
  Signature: (Ljava/io/Reader;)Lscala/xml/Node;
  Code:
   Stack=2, Locals=2, Args_size=2
	aload_0
	aload_1
	invokestatic	Method scala/xml/factory/XMLLoader$class.load:(Lscala/xml/factory/XMLLoader;Ljava/io/Reader;)Lscala/xml/Node;
	areturn
  Labels:
  LocalVariableTable: 
   Start  Length  Slot  Name   Signature
   0      6      0    this       Lscala/xml/XML$$anon$1;
   0      6      1    reader       Ljava/io/Reader;


public scala.xml.Node load(java.lang.String);
  Signature: (Ljava/lang/String;)Lscala/xml/Node;
  Code:
   Stack=2, Locals=2, Args_size=2
	aload_0
	aload_1
	invokestatic	Method scala/xml/factory/XMLLoader$class.load:(Lscala/xml/factory/XMLLoader;Ljava/lang/String;)Lscala/xml/Node;
	areturn
  Labels:
  LocalVariableTable: 
   Start  Length  Slot  Name   Signature
   0      6      0    this       Lscala/xml/XML$$anon$1;
   0      6      1    sysID       Ljava/lang/String;


public scala.xml.Node load(org.xml.sax.InputSource);
  Signature: (Lorg/xml/sax/InputSource;)Lscala/xml/Node;
  Code:
   Stack=2, Locals=2, Args_size=2
	aload_0
	aload_1
	invokestatic	Method scala/xml/factory/XMLLoader$class.load:(Lscala/xml/factory/XMLLoader;Lorg/xml/sax/InputSource;)Lscala/xml/Node;
	areturn
  Labels:
  LocalVariableTable: 
   Start  Length  Slot  Name   Signature
   0      6      0    this       Lscala/xml/XML$$anon$1;
   0      6      1    source       Lorg/xml/sax/InputSource;


public scala.xml.Node load(java.net.URL);
  Signature: (Ljava/net/URL;)Lscala/xml/Node;
  Code:
   Stack=2, Locals=2, Args_size=2
	aload_0
	aload_1
	invokestatic	Method scala/xml/factory/XMLLoader$class.load:(Lscala/xml/factory/XMLLoader;Ljava/net/URL;)Lscala/xml/Node;
	areturn
  Labels:
  LocalVariableTable: 
   Start  Length  Slot  Name   Signature
   0      6      0    this       Lscala/xml/XML$$anon$1;
   0      6      1    url       Ljava/net/URL;


public scala.xml.Node loadString(java.lang.String);
  Signature: (Ljava/lang/String;)Lscala/xml/Node;
  Code:
   Stack=2, Locals=2, Args_size=2
	aload_0
	aload_1
	invokestatic	Method scala/xml/factory/XMLLoader$class.loadString:(Lscala/xml/factory/XMLLoader;Ljava/lang/String;)Lscala/xml/Node;
	areturn
  Labels:
  LocalVariableTable: 
   Start  Length  Slot  Name   Signature
   0      6      0    this       Lscala/xml/XML$$anon$1;
   0      6      1    string       Ljava/lang/String;


public javax.xml.parsers.SAXParser parser();
  Signature: ()Ljavax/xml/parsers/SAXParser;
  Code:
   Stack=1, Locals=1, Args_size=1
	aload_0
	getfield	Field parser:Ljavax/xml/parsers/SAXParser;
	areturn
  Labels:

public scala.xml.XML$$anon$1(javax.xml.parsers.SAXParser);
  Signature: (Ljavax/xml/parsers/SAXParser;)V
  Code:
   Stack=2, Locals=2, Args_size=2
	aload_0
	invokespecial	Method java/lang/Object."<init>":()V
	aload_0
	invokestatic	Method scala/xml/factory/XMLLoader$class.$init$:(Lscala/xml/factory/XMLLoader;)V
	aload_0
	aload_1
	putfield	Field parser:Ljavax/xml/parsers/SAXParser;
	return
  Labels:

}

