Compiled from "XML.scala"
public final class scala.xml.XML$ extends java.lang.Object implements scala.xml.factory.XMLLoader,scala.ScalaObject
  SourceFile: "XML.scala"
  Scala: length = 0x
   
  Signature: length = 0x2
   01 03 
  InnerClass: 
   public final $anon$1=class scala/xml/XML$$anon$1 of class scala/xml/XML
   public Catch=class scala/util/control/Exception$Catch of class scala/util/control/Exception
   public final $anonfun$save$2=class scala/xml/XML$$anonfun$save$2 of class scala/xml/XML
   public final $anonfun$save$1=class scala/xml/XML$$anonfun$save$1 of class scala/xml/XML
  minor version: 0
  major version: 49
  Constant pool:
Asciz	SourceFile;
Asciz	XML.scala;
Asciz	Scala;
Asciz	MODULE$;
Asciz	Lscala/xml/XML$;;
Asciz	<clinit>;
Asciz	()V;
Asciz	Code;
Asciz	scala/xml/XML$;
class	scala/xml/XML$
Asciz	<init>;
NameAndType	"<init>":()V
Method	scala/xml/XML$."<init>":()V
Asciz	scala$xml$factory$XMLLoader$$saxFactory;
Asciz	Ljavax/xml/parsers/SAXParserFactory;;
Asciz	encoding;
Asciz	Ljava/lang/String;;
Asciz	lang;
Asciz	space;
Asciz	preserve;
Asciz	namespace;
Asciz	xmlns;
Asciz	xml;
Asciz	LineNumberTable;
Asciz	java/lang/Object;
class	java/lang/Object
Method	java/lang/Object."<init>":()V
NameAndType	MODULE$:Lscala/xml/XML$;
Field	scala/xml/XML$.MODULE$:Lscala/xml/XML$;
Asciz	scala/xml/factory/XMLLoader$class;
class	scala/xml/factory/XMLLoader$class
Asciz	$init$;
Asciz	(Lscala/xml/factory/XMLLoader;)V;
NameAndType	$init$:(Lscala/xml/factory/XMLLoader;)V
Method	scala/xml/factory/XMLLoader$class.$init$:(Lscala/xml/factory/XMLLoader;)V
String	xml
NameAndType	xml:Ljava/lang/String;
Field	scala/xml/XML$.xml:Ljava/lang/String;
String	xmlns
NameAndType	xmlns:Ljava/lang/String;
Field	scala/xml/XML$.xmlns:Ljava/lang/String;
Asciz	http://www.w3.org/XML/1998/namespace;
String	http://www.w3.org/XML/1998/namespace
NameAndType	namespace:Ljava/lang/String;
Field	scala/xml/XML$.namespace:Ljava/lang/String;
String	preserve
NameAndType	preserve:Ljava/lang/String;
Field	scala/xml/XML$.preserve:Ljava/lang/String;
String	space
NameAndType	space:Ljava/lang/String;
Field	scala/xml/XML$.space:Ljava/lang/String;
String	lang
NameAndType	lang:Ljava/lang/String;
Field	scala/xml/XML$.lang:Ljava/lang/String;
Asciz	ISO-8859-1;
String	ISO-8859-1
NameAndType	encoding:Ljava/lang/String;
Field	scala/xml/XML$.encoding:Ljava/lang/String;
Asciz	write;
Asciz	(Ljava/io/Writer;Lscala/xml/Node;Ljava/lang/String;ZLscala/xml/dtd/DocType;)V;
Asciz	scala/collection/mutable/StringBuilder;
class	scala/collection/mutable/StringBuilder
Method	scala/collection/mutable/StringBuilder."<init>":()V
Asciz	<?xml version='1.0' encoding=';
String	<?xml version='1.0' encoding='
Asciz	append;
Asciz	(Ljava/lang/Object;)Lscala/collection/mutable/StringBuilder;;
NameAndType	append:(Ljava/lang/Object;)Lscala/collection/mutable/StringBuilder;
Method	scala/collection/mutable/StringBuilder.append:(Ljava/lang/Object;)Lscala/collection/mutable/StringBuilder;
Asciz	'?>\n;
String	'?>\n
Asciz	toString;
Asciz	()Ljava/lang/String;;
NameAndType	toString:()Ljava/lang/String;
Method	scala/collection/mutable/StringBuilder.toString:()Ljava/lang/String;
Asciz	java/io/Writer;
class	java/io/Writer
Asciz	(Ljava/lang/String;)V;
NameAndType	write:(Ljava/lang/String;)V
Method	java/io/Writer.write:(Ljava/lang/String;)V
Asciz	scala/xml/dtd/DocType;
class	scala/xml/dtd/DocType
Method	scala/xml/dtd/DocType.toString:()Ljava/lang/String;
Asciz	\n;
String	\n
Asciz	scala/xml/Utility$;
class	scala/xml/Utility$
Asciz	Lscala/xml/Utility$;;
NameAndType	MODULE$:Lscala/xml/Utility$;
Field	scala/xml/Utility$.MODULE$:Lscala/xml/Utility$;
Asciz	scala/xml/TopScope$;
class	scala/xml/TopScope$
Asciz	Lscala/xml/TopScope$;;
NameAndType	MODULE$:Lscala/xml/TopScope$;
Field	scala/xml/TopScope$.MODULE$:Lscala/xml/TopScope$;
Method	scala/collection/mutable/StringBuilder."<init>":()V
Asciz	toXML;
Asciz	(Lscala/xml/Node;Lscala/xml/NamespaceBinding;Lscala/collection/mutable/StringBuilder;ZZZZ)Lscala/collection/mutable/StringBuilder;;
NameAndType	toXML:(Lscala/xml/Node;Lscala/xml/NamespaceBinding;Lscala/collection/mutable/StringBuilder;ZZZZ)Lscala/collection/mutable/StringBuilder;
Method	scala/xml/Utility$.toXML:(Lscala/xml/Node;Lscala/xml/NamespaceBinding;Lscala/collection/mutable/StringBuilder;ZZZZ)Lscala/collection/mutable/StringBuilder;
Method	scala/collection/mutable/StringBuilder.toString:()Ljava/lang/String;
Asciz	this;
Asciz	w;
Asciz	Ljava/io/Writer;;
Asciz	node;
Asciz	Lscala/xml/Node;;
Asciz	enc;
Asciz	xmlDecl;
Asciz	Z;
Asciz	doctype;
Asciz	Lscala/xml/dtd/DocType;;
Asciz	LocalVariableTable;
Asciz	save;
Asciz	(Ljava/lang/String;Lscala/xml/Node;Ljava/lang/String;ZLscala/xml/dtd/DocType;)V;
Asciz	java/io/FileOutputStream;
class	java/io/FileOutputStream
NameAndType	"<init>":(Ljava/lang/String;)V
Method	java/io/FileOutputStream."<init>":(Ljava/lang/String;)V
Asciz	getChannel;
Asciz	()Ljava/nio/channels/FileChannel;;
NameAndType	getChannel:()Ljava/nio/channels/FileChannel;
Method	java/io/FileOutputStream.getChannel:()Ljava/nio/channels/FileChannel;
Asciz	java/nio/channels/Channels;
class	java/nio/channels/Channels
Asciz	newWriter;
Asciz	(Ljava/nio/channels/WritableByteChannel;Ljava/lang/String;)Ljava/io/Writer;;
NameAndType	newWriter:(Ljava/nio/channels/WritableByteChannel;Ljava/lang/String;)Ljava/io/Writer;
Method	java/nio/channels/Channels.newWriter:(Ljava/nio/channels/WritableByteChannel;Ljava/lang/String;)Ljava/io/Writer;
Asciz	scala/util/control/Exception$;
class	scala/util/control/Exception$
Asciz	Lscala/util/control/Exception$;;
NameAndType	MODULE$:Lscala/util/control/Exception$;
Field	scala/util/control/Exception$.MODULE$:Lscala/util/control/Exception$;
Asciz	scala/xml/XML$$anonfun$save$1;
class	scala/xml/XML$$anonfun$save$1
Asciz	(Ljava/io/FileOutputStream;Ljava/io/Writer;)V;
NameAndType	"<init>":(Ljava/io/FileOutputStream;Ljava/io/Writer;)V
Method	scala/xml/XML$$anonfun$save$1."<init>":(Ljava/io/FileOutputStream;Ljava/io/Writer;)V
Asciz	noCatch;
Asciz	()Lscala/util/control/Exception$Catch;;
NameAndType	noCatch:()Lscala/util/control/Exception$Catch;
Method	scala/util/control/Exception$.noCatch:()Lscala/util/control/Exception$Catch;
Asciz	scala/util/control/Exception$Catch;
class	scala/util/control/Exception$Catch
Asciz	andFinally;
Asciz	(Lscala/Function0;)Lscala/util/control/Exception$Catch;;
NameAndType	andFinally:(Lscala/Function0;)Lscala/util/control/Exception$Catch;
Method	scala/util/control/Exception$Catch.andFinally:(Lscala/Function0;)Lscala/util/control/Exception$Catch;
Asciz	scala/xml/XML$$anonfun$save$2;
class	scala/xml/XML$$anonfun$save$2
Asciz	(Lscala/xml/Node;Ljava/lang/String;ZLscala/xml/dtd/DocType;Ljava/io/Writer;)V;
NameAndType	"<init>":(Lscala/xml/Node;Ljava/lang/String;ZLscala/xml/dtd/DocType;Ljava/io/Writer;)V
Method	scala/xml/XML$$anonfun$save$2."<init>":(Lscala/xml/Node;Ljava/lang/String;ZLscala/xml/dtd/DocType;Ljava/io/Writer;)V
Asciz	apply;
Asciz	(Lscala/Function0;)Ljava/lang/Object;;
NameAndType	apply:(Lscala/Function0;)Ljava/lang/Object;
Method	scala/util/control/Exception$Catch.apply:(Lscala/Function0;)Ljava/lang/Object;
Asciz	filename;
Asciz	node$1;
Asciz	enc$1;
Asciz	xmlDecl$1;
Asciz	doctype$1;
Asciz	fos$1;
Asciz	Ljava/io/FileOutputStream;;
Asciz	w$1;
Asciz	saveFull;
Asciz	Deprecated;
Asciz	(Ljava/lang/String;Lscala/xml/Node;ZLscala/xml/dtd/DocType;)V;
NameAndType	encoding:()Ljava/lang/String;
Method	scala/xml/XML$.encoding:()Ljava/lang/String;
NameAndType	saveFull:(Ljava/lang/String;Lscala/xml/Node;Ljava/lang/String;ZLscala/xml/dtd/DocType;)V
Method	scala/xml/XML$.saveFull:(Ljava/lang/String;Lscala/xml/Node;Ljava/lang/String;ZLscala/xml/dtd/DocType;)V
Asciz	withSAXParser;
Asciz	(Ljavax/xml/parsers/SAXParser;)Lscala/xml/factory/XMLLoader;;
Asciz	scala/xml/XML$$anon$1;
class	scala/xml/XML$$anon$1
Asciz	(Ljavax/xml/parsers/SAXParser;)V;
NameAndType	"<init>":(Ljavax/xml/parsers/SAXParser;)V
Method	scala/xml/XML$$anon$1."<init>":(Ljavax/xml/parsers/SAXParser;)V
Asciz	p$1;
Asciz	Ljavax/xml/parsers/SAXParser;;
Asciz	(Ljavax/xml/parsers/SAXParser;)Lscala/xml/factory/XMLLoader<Lscala/xml/Elem;>;;
Asciz	Signature;
Asciz	save$default$3;
Asciz	save$default$4;
Asciz	()Z;
Asciz	save$default$5;
Asciz	()Lscala/xml/dtd/DocType;;
Asciz	loadString;
Asciz	(Ljava/lang/String;)Lscala/xml/Node;;
Asciz	(Lscala/xml/factory/XMLLoader;Ljava/lang/String;)Lscala/xml/Node;;
NameAndType	loadString:(Lscala/xml/factory/XMLLoader;Ljava/lang/String;)Lscala/xml/Node;
Method	scala/xml/factory/XMLLoader$class.loadString:(Lscala/xml/factory/XMLLoader;Ljava/lang/String;)Lscala/xml/Node;
Asciz	string;
Asciz	load;
Asciz	(Ljava/net/URL;)Lscala/xml/Node;;
Asciz	(Lscala/xml/factory/XMLLoader;Ljava/net/URL;)Lscala/xml/Node;;
NameAndType	load:(Lscala/xml/factory/XMLLoader;Ljava/net/URL;)Lscala/xml/Node;
Method	scala/xml/factory/XMLLoader$class.load:(Lscala/xml/factory/XMLLoader;Ljava/net/URL;)Lscala/xml/Node;
Asciz	url;
Asciz	Ljava/net/URL;;
Asciz	(Lorg/xml/sax/InputSource;)Lscala/xml/Node;;
Asciz	(Lscala/xml/factory/XMLLoader;Lorg/xml/sax/InputSource;)Lscala/xml/Node;;
NameAndType	load:(Lscala/xml/factory/XMLLoader;Lorg/xml/sax/InputSource;)Lscala/xml/Node;
Method	scala/xml/factory/XMLLoader$class.load:(Lscala/xml/factory/XMLLoader;Lorg/xml/sax/InputSource;)Lscala/xml/Node;
Asciz	source;
Asciz	Lorg/xml/sax/InputSource;;
NameAndType	load:(Lscala/xml/factory/XMLLoader;Ljava/lang/String;)Lscala/xml/Node;
Method	scala/xml/factory/XMLLoader$class.load:(Lscala/xml/factory/XMLLoader;Ljava/lang/String;)Lscala/xml/Node;
Asciz	sysID;
Asciz	(Ljava/io/Reader;)Lscala/xml/Node;;
Asciz	(Lscala/xml/factory/XMLLoader;Ljava/io/Reader;)Lscala/xml/Node;;
NameAndType	load:(Lscala/xml/factory/XMLLoader;Ljava/io/Reader;)Lscala/xml/Node;
Method	scala/xml/factory/XMLLoader$class.load:(Lscala/xml/factory/XMLLoader;Ljava/io/Reader;)Lscala/xml/Node;
Asciz	reader;
Asciz	Ljava/io/Reader;;
Asciz	(Ljava/io/InputStream;)Lscala/xml/Node;;
Asciz	(Lscala/xml/factory/XMLLoader;Ljava/io/InputStream;)Lscala/xml/Node;;
NameAndType	load:(Lscala/xml/factory/XMLLoader;Ljava/io/InputStream;)Lscala/xml/Node;
Method	scala/xml/factory/XMLLoader$class.load:(Lscala/xml/factory/XMLLoader;Ljava/io/InputStream;)Lscala/xml/Node;
Asciz	is;
Asciz	Ljava/io/InputStream;;
Asciz	loadFile;
NameAndType	loadFile:(Lscala/xml/factory/XMLLoader;Ljava/lang/String;)Lscala/xml/Node;
Method	scala/xml/factory/XMLLoader$class.loadFile:(Lscala/xml/factory/XMLLoader;Ljava/lang/String;)Lscala/xml/Node;
Asciz	name;
Asciz	(Ljava/io/FileDescriptor;)Lscala/xml/Node;;
Asciz	(Lscala/xml/factory/XMLLoader;Ljava/io/FileDescriptor;)Lscala/xml/Node;;
NameAndType	loadFile:(Lscala/xml/factory/XMLLoader;Ljava/io/FileDescriptor;)Lscala/xml/Node;
Method	scala/xml/factory/XMLLoader$class.loadFile:(Lscala/xml/factory/XMLLoader;Ljava/io/FileDescriptor;)Lscala/xml/Node;
Asciz	fd;
Asciz	Ljava/io/FileDescriptor;;
Asciz	(Ljava/io/File;)Lscala/xml/Node;;
Asciz	(Lscala/xml/factory/XMLLoader;Ljava/io/File;)Lscala/xml/Node;;
NameAndType	loadFile:(Lscala/xml/factory/XMLLoader;Ljava/io/File;)Lscala/xml/Node;
Method	scala/xml/factory/XMLLoader$class.loadFile:(Lscala/xml/factory/XMLLoader;Ljava/io/File;)Lscala/xml/Node;
Asciz	file;
Asciz	Ljava/io/File;;
Asciz	loadXML;
Asciz	(Lorg/xml/sax/InputSource;Ljavax/xml/parsers/SAXParser;)Lscala/xml/Node;;
Asciz	(Lscala/xml/factory/XMLLoader;Lorg/xml/sax/InputSource;Ljavax/xml/parsers/SAXParser;)Lscala/xml/Node;;
NameAndType	loadXML:(Lscala/xml/factory/XMLLoader;Lorg/xml/sax/InputSource;Ljavax/xml/parsers/SAXParser;)Lscala/xml/Node;
Method	scala/xml/factory/XMLLoader$class.loadXML:(Lscala/xml/factory/XMLLoader;Lorg/xml/sax/InputSource;Ljavax/xml/parsers/SAXParser;)Lscala/xml/Node;
Asciz	parser;
Asciz	()Ljavax/xml/parsers/SAXParser;;
Asciz	(Lscala/xml/factory/XMLLoader;)Ljavax/xml/parsers/SAXParser;;
NameAndType	parser:(Lscala/xml/factory/XMLLoader;)Ljavax/xml/parsers/SAXParser;
Method	scala/xml/factory/XMLLoader$class.parser:(Lscala/xml/factory/XMLLoader;)Ljavax/xml/parsers/SAXParser;
Asciz	adapter;
Asciz	()Lscala/xml/parsing/FactoryAdapter;;
Asciz	(Lscala/xml/factory/XMLLoader;)Lscala/xml/parsing/FactoryAdapter;;
NameAndType	adapter:(Lscala/xml/factory/XMLLoader;)Lscala/xml/parsing/FactoryAdapter;
Method	scala/xml/factory/XMLLoader$class.adapter:(Lscala/xml/factory/XMLLoader;)Lscala/xml/parsing/FactoryAdapter;
Asciz	scala$xml$factory$XMLLoader$_setter_$scala$xml$factory$XMLLoader$$saxFactory_$eq;
Asciz	(Ljavax/xml/parsers/SAXParserFactory;)V;
NameAndType	scala$xml$factory$XMLLoader$$saxFactory:Ljavax/xml/parsers/SAXParserFactory;
Field	scala/xml/XML$.scala$xml$factory$XMLLoader$$saxFactory:Ljavax/xml/parsers/SAXParserFactory;
Asciz	()Ljavax/xml/parsers/SAXParserFactory;;
Asciz	Ljava/lang/Object;Lscala/xml/factory/XMLLoader<Lscala/xml/Elem;>;Lscala/ScalaObject;;
Asciz	InnerClasses;
Asciz	scala/xml/XML;
class	scala/xml/XML
Asciz	$anon$1;
Asciz	scala/util/control/Exception;
class	scala/util/control/Exception
Asciz	Catch;
Asciz	$anonfun$save$2;
Asciz	$anonfun$save$1;
Asciz	scala/xml/factory/XMLLoader;
class	scala/xml/factory/XMLLoader
Asciz	scala/ScalaObject;
class	scala/ScalaObject

{
public static final scala.xml.XML$ MODULE$;
  Signature: Lscala/xml/XML$;

private final javax.xml.parsers.SAXParserFactory scala$xml$factory$XMLLoader$$saxFactory;
  Signature: Ljavax/xml/parsers/SAXParserFactory;

private final java.lang.String encoding;
  Signature: Ljava/lang/String;

private final java.lang.String lang;
  Signature: Ljava/lang/String;

private final java.lang.String space;
  Signature: Ljava/lang/String;

private final java.lang.String preserve;
  Signature: Ljava/lang/String;

private final java.lang.String namespace;
  Signature: Ljava/lang/String;

private final java.lang.String xmlns;
  Signature: Ljava/lang/String;

private final java.lang.String xml;
  Signature: Ljava/lang/String;

public static {};
  Signature: ()V
  Code:
   Stack=1, Locals=0, Args_size=0
	new	class scala/xml/XML$
	invokespecial	Method "<init>":()V
	return
  Labels:

private scala.xml.XML$();
  Signature: ()V
  Code:
   Stack=2, Locals=1, Args_size=1
	aload_0
	invokespecial	Method java/lang/Object."<init>":()V
	aload_0
	putstatic	Field MODULE$:Lscala/xml/XML$;
	aload_0
	invokestatic	Method scala/xml/factory/XMLLoader$class.$init$:(Lscala/xml/factory/XMLLoader;)V
	aload_0
	ldc	String xml
	putfield	Field xml:Ljava/lang/String;
	aload_0
	ldc	String xmlns
	putfield	Field xmlns:Ljava/lang/String;
	aload_0
	ldc	String http://www.w3.org/XML/1998/namespace
	putfield	Field namespace:Ljava/lang/String;
	aload_0
	ldc	String preserve
	putfield	Field preserve:Ljava/lang/String;
	aload_0
	ldc	String space
	putfield	Field space:Ljava/lang/String;
	aload_0
	ldc	String lang
	putfield	Field lang:Ljava/lang/String;
	aload_0
	ldc	String ISO-8859-1
	putfield	Field encoding:Ljava/lang/String;
	return
  Labels:

public final void write(java.io.Writer, scala.xml.Node, java.lang.String, boolean, scala.xml.dtd.DocType);
  Signature: (Ljava/io/Writer;Lscala/xml/Node;Ljava/lang/String;ZLscala/xml/dtd/DocType;)V
  Code:
   Stack=9, Locals=6, Args_size=6
	iload	4
	ifeq	l1 // aload
	aload_1
	new	class scala/collection/mutable/StringBuilder
	dup
	invokespecial	Method scala/collection/mutable/StringBuilder."<init>":()V
	ldc	String <?xml version='1.0' encoding='
	invokevirtual	Method scala/collection/mutable/StringBuilder.append:(Ljava/lang/Object;)Lscala/collection/mutable/StringBuilder;
	aload_3
	invokevirtual	Method scala/collection/mutable/StringBuilder.append:(Ljava/lang/Object;)Lscala/collection/mutable/StringBuilder;
	ldc	String '?>\n
	invokevirtual	Method scala/collection/mutable/StringBuilder.append:(Ljava/lang/Object;)Lscala/collection/mutable/StringBuilder;
	invokevirtual	Method scala/collection/mutable/StringBuilder.toString:()Ljava/lang/String;
	invokevirtual	Method java/io/Writer.write:(Ljava/lang/String;)V
l1	aload	5
	ifnull	l2 // aload_1
	aload_1
	new	class scala/collection/mutable/StringBuilder
	dup
	invokespecial	Method scala/collection/mutable/StringBuilder."<init>":()V
	aload	5
	invokevirtual	Method scala/xml/dtd/DocType.toString:()Ljava/lang/String;
	invokevirtual	Method scala/collection/mutable/StringBuilder.append:(Ljava/lang/Object;)Lscala/collection/mutable/StringBuilder;
	ldc	String \n
	invokevirtual	Method scala/collection/mutable/StringBuilder.append:(Ljava/lang/Object;)Lscala/collection/mutable/StringBuilder;
	invokevirtual	Method scala/collection/mutable/StringBuilder.toString:()Ljava/lang/String;
	invokevirtual	Method java/io/Writer.write:(Ljava/lang/String;)V
l2	aload_1
	getstatic	Field scala/xml/Utility$.MODULE$:Lscala/xml/Utility$;
	aload_2
	getstatic	Field scala/xml/TopScope$.MODULE$:Lscala/xml/TopScope$;
	new	class scala/collection/mutable/StringBuilder
	dup
	invokespecial	Method scala/collection/mutable/StringBuilder."<init>":()V
	iconst_0
	iconst_1
	iconst_0
	iconst_0
	invokevirtual	Method scala/xml/Utility$.toXML:(Lscala/xml/Node;Lscala/xml/NamespaceBinding;Lscala/collection/mutable/StringBuilder;ZZZZ)Lscala/collection/mutable/StringBuilder;
	invokevirtual	Method scala/collection/mutable/StringBuilder.toString:()Ljava/lang/String;
	invokevirtual	Method java/io/Writer.write:(Ljava/lang/String;)V
	return
  Labels:
   	l1 = 33 // aload
   	l2 = 65 // aload_1
  LocalVariableTable: 
   Start  Length  Slot  Name   Signature
   0      94      0    this       Lscala/xml/XML$;
   0      94      1    w       Ljava/io/Writer;
   0      94      2    node       Lscala/xml/Node;
   0      94      3    enc       Ljava/lang/String;
   0      94      4    xmlDecl       Z
   0      94      5    doctype       Lscala/xml/dtd/DocType;


public final void save(java.lang.String, scala.xml.Node, java.lang.String, boolean, scala.xml.dtd.DocType);
  Signature: (Ljava/lang/String;Lscala/xml/Node;Ljava/lang/String;ZLscala/xml/dtd/DocType;)V
  Code:
   Stack=8, Locals=10, Args_size=6
	new	class java/io/FileOutputStream
	dup
	aload_1
	invokespecial	Method java/io/FileOutputStream."<init>":(Ljava/lang/String;)V
	astore	6
	aload	6
	invokevirtual	Method java/io/FileOutputStream.getChannel:()Ljava/nio/channels/FileChannel;
	aload_3
	invokestatic	Method java/nio/channels/Channels.newWriter:(Ljava/nio/channels/WritableByteChannel;Ljava/lang/String;)Ljava/io/Writer;
	astore	9
	getstatic	Field scala/util/control/Exception$.MODULE$:Lscala/util/control/Exception$;
	new	class scala/xml/XML$$anonfun$save$1
	dup
	aload	6
	aload	9
	invokespecial	Method scala/xml/XML$$anonfun$save$1."<init>":(Ljava/io/FileOutputStream;Ljava/io/Writer;)V
	astore	8
	astore	7
	aload	7
	invokevirtual	Method scala/util/control/Exception$.noCatch:()Lscala/util/control/Exception$Catch;
	aload	8
	invokevirtual	Method scala/util/control/Exception$Catch.andFinally:(Lscala/Function0;)Lscala/util/control/Exception$Catch;
	new	class scala/xml/XML$$anonfun$save$2
	dup
	aload_2
	aload_3
	iload	4
	aload	5
	aload	9
	invokespecial	Method scala/xml/XML$$anonfun$save$2."<init>":(Lscala/xml/Node;Ljava/lang/String;ZLscala/xml/dtd/DocType;Ljava/io/Writer;)V
	invokevirtual	Method scala/util/control/Exception$Catch.apply:(Lscala/Function0;)Ljava/lang/Object;
	pop
	return
  Labels:
  LocalVariableTable: 
   Start  Length  Slot  Name   Signature
   0      69      0    this       Lscala/xml/XML$;
   0      69      1    filename       Ljava/lang/String;
   0      69      2    node$1       Lscala/xml/Node;
   0      69      3    enc$1       Ljava/lang/String;
   0      69      4    xmlDecl$1       Z
   0      69      5    doctype$1       Lscala/xml/dtd/DocType;
   10      58      6    fos$1       Ljava/io/FileOutputStream;
   21      47      9    w$1       Ljava/io/Writer;


public final void saveFull(java.lang.String, scala.xml.Node, java.lang.String, boolean, scala.xml.dtd.DocType);
  Signature: (Ljava/lang/String;Lscala/xml/Node;Ljava/lang/String;ZLscala/xml/dtd/DocType;)V
  Code:
   Stack=0, Locals=6, Args_size=6
l1	goto	l1 // goto
  Labels:
   	l1 = 0 // goto
  LocalVariableTable: 
   Start  Length  Slot  Name   Signature
   0      3      0    this       Lscala/xml/XML$;
   0      3      1    filename       Ljava/lang/String;
   0      3      2    node       Lscala/xml/Node;
   0      3      3    enc       Ljava/lang/String;
   0      3      4    xmlDecl       Z
   0      3      5    doctype       Lscala/xml/dtd/DocType;

  Deprecated: true

public final void saveFull(java.lang.String, scala.xml.Node, boolean, scala.xml.dtd.DocType);
  Signature: (Ljava/lang/String;Lscala/xml/Node;ZLscala/xml/dtd/DocType;)V
  Code:
   Stack=6, Locals=5, Args_size=5
	aload_0
	aload_1
	aload_2
	aload_0
	invokevirtual	Method encoding:()Ljava/lang/String;
	iload_3
	aload	4
	invokevirtual	Method saveFull:(Ljava/lang/String;Lscala/xml/Node;Ljava/lang/String;ZLscala/xml/dtd/DocType;)V
	return
  Labels:
  LocalVariableTable: 
   Start  Length  Slot  Name   Signature
   0      14      0    this       Lscala/xml/XML$;
   0      14      1    filename       Ljava/lang/String;
   0      14      2    node       Lscala/xml/Node;
   0      14      3    xmlDecl       Z
   0      14      4    doctype       Lscala/xml/dtd/DocType;

  Deprecated: true

public scala.xml.factory.XMLLoader withSAXParser(javax.xml.parsers.SAXParser);
  Signature: (Ljavax/xml/parsers/SAXParser;)Lscala/xml/factory/XMLLoader;
  Code:
   Stack=3, Locals=2, Args_size=2
	new	class scala/xml/XML$$anon$1
	dup
	aload_1
	invokespecial	Method scala/xml/XML$$anon$1."<init>":(Ljavax/xml/parsers/SAXParser;)V
	areturn
  Labels:
  LocalVariableTable: 
   Start  Length  Slot  Name   Signature
   0      9      0    this       Lscala/xml/XML$;
   0      9      1    p$1       Ljavax/xml/parsers/SAXParser;

  Signature: length = 0x2
   00 FFFFFFB6 

public java.lang.String encoding();
  Signature: ()Ljava/lang/String;
  Code:
   Stack=1, Locals=1, Args_size=1
	aload_0
	getfield	Field encoding:Ljava/lang/String;
	areturn
  Labels:

public java.lang.String lang();
  Signature: ()Ljava/lang/String;
  Code:
   Stack=1, Locals=1, Args_size=1
	aload_0
	getfield	Field lang:Ljava/lang/String;
	areturn
  Labels:

public java.lang.String space();
  Signature: ()Ljava/lang/String;
  Code:
   Stack=1, Locals=1, Args_size=1
	aload_0
	getfield	Field space:Ljava/lang/String;
	areturn
  Labels:

public java.lang.String preserve();
  Signature: ()Ljava/lang/String;
  Code:
   Stack=1, Locals=1, Args_size=1
	aload_0
	getfield	Field preserve:Ljava/lang/String;
	areturn
  Labels:

public java.lang.String namespace();
  Signature: ()Ljava/lang/String;
  Code:
   Stack=1, Locals=1, Args_size=1
	aload_0
	getfield	Field namespace:Ljava/lang/String;
	areturn
  Labels:

public java.lang.String xmlns();
  Signature: ()Ljava/lang/String;
  Code:
   Stack=1, Locals=1, Args_size=1
	aload_0
	getfield	Field xmlns:Ljava/lang/String;
	areturn
  Labels:

public java.lang.String xml();
  Signature: ()Ljava/lang/String;
  Code:
   Stack=1, Locals=1, Args_size=1
	aload_0
	getfield	Field xml:Ljava/lang/String;
	areturn
  Labels:

public final java.lang.String save$default$3();
  Signature: ()Ljava/lang/String;
  Code:
   Stack=1, Locals=1, Args_size=1
	aload_0
	invokevirtual	Method encoding:()Ljava/lang/String;
	areturn
  Labels:

public final boolean save$default$4();
  Signature: ()Z
  Code:
   Stack=1, Locals=1, Args_size=1
	iconst_0
	ireturn
  Labels:

public final scala.xml.dtd.DocType save$default$5();
  Signature: ()Lscala/xml/dtd/DocType;
  Code:
   Stack=1, Locals=1, Args_size=1
	aconst_null
	areturn
  Labels:

public scala.xml.Node loadString(java.lang.String);
  Signature: (Ljava/lang/String;)Lscala/xml/Node;
  Code:
   Stack=2, Locals=2, Args_size=2
	aload_0
	aload_1
	invokestatic	Method scala/xml/factory/XMLLoader$class.loadString:(Lscala/xml/factory/XMLLoader;Ljava/lang/String;)Lscala/xml/Node;
	areturn
  Labels:
  LocalVariableTable: 
   Start  Length  Slot  Name   Signature
   0      6      0    this       Lscala/xml/XML$;
   0      6      1    string       Ljava/lang/String;


public scala.xml.Node load(java.net.URL);
  Signature: (Ljava/net/URL;)Lscala/xml/Node;
  Code:
   Stack=2, Locals=2, Args_size=2
	aload_0
	aload_1
	invokestatic	Method scala/xml/factory/XMLLoader$class.load:(Lscala/xml/factory/XMLLoader;Ljava/net/URL;)Lscala/xml/Node;
	areturn
  Labels:
  LocalVariableTable: 
   Start  Length  Slot  Name   Signature
   0      6      0    this       Lscala/xml/XML$;
   0      6      1    url       Ljava/net/URL;


public scala.xml.Node load(org.xml.sax.InputSource);
  Signature: (Lorg/xml/sax/InputSource;)Lscala/xml/Node;
  Code:
   Stack=2, Locals=2, Args_size=2
	aload_0
	aload_1
	invokestatic	Method scala/xml/factory/XMLLoader$class.load:(Lscala/xml/factory/XMLLoader;Lorg/xml/sax/InputSource;)Lscala/xml/Node;
	areturn
  Labels:
  LocalVariableTable: 
   Start  Length  Slot  Name   Signature
   0      6      0    this       Lscala/xml/XML$;
   0      6      1    source       Lorg/xml/sax/InputSource;


public scala.xml.Node load(java.lang.String);
  Signature: (Ljava/lang/String;)Lscala/xml/Node;
  Code:
   Stack=2, Locals=2, Args_size=2
	aload_0
	aload_1
	invokestatic	Method scala/xml/factory/XMLLoader$class.load:(Lscala/xml/factory/XMLLoader;Ljava/lang/String;)Lscala/xml/Node;
	areturn
  Labels:
  LocalVariableTable: 
   Start  Length  Slot  Name   Signature
   0      6      0    this       Lscala/xml/XML$;
   0      6      1    sysID       Ljava/lang/String;


public scala.xml.Node load(java.io.Reader);
  Signature: (Ljava/io/Reader;)Lscala/xml/Node;
  Code:
   Stack=2, Locals=2, Args_size=2
	aload_0
	aload_1
	invokestatic	Method scala/xml/factory/XMLLoader$class.load:(Lscala/xml/factory/XMLLoader;Ljava/io/Reader;)Lscala/xml/Node;
	areturn
  Labels:
  LocalVariableTable: 
   Start  Length  Slot  Name   Signature
   0      6      0    this       Lscala/xml/XML$;
   0      6      1    reader       Ljava/io/Reader;


public scala.xml.Node load(java.io.InputStream);
  Signature: (Ljava/io/InputStream;)Lscala/xml/Node;
  Code:
   Stack=2, Locals=2, Args_size=2
	aload_0
	aload_1
	invokestatic	Method scala/xml/factory/XMLLoader$class.load:(Lscala/xml/factory/XMLLoader;Ljava/io/InputStream;)Lscala/xml/Node;
	areturn
  Labels:
  LocalVariableTable: 
   Start  Length  Slot  Name   Signature
   0      6      0    this       Lscala/xml/XML$;
   0      6      1    is       Ljava/io/InputStream;


public scala.xml.Node loadFile(java.lang.String);
  Signature: (Ljava/lang/String;)Lscala/xml/Node;
  Code:
   Stack=2, Locals=2, Args_size=2
	aload_0
	aload_1
	invokestatic	Method scala/xml/factory/XMLLoader$class.loadFile:(Lscala/xml/factory/XMLLoader;Ljava/lang/String;)Lscala/xml/Node;
	areturn
  Labels:
  LocalVariableTable: 
   Start  Length  Slot  Name   Signature
   0      6      0    this       Lscala/xml/XML$;
   0      6      1    name       Ljava/lang/String;


public scala.xml.Node loadFile(java.io.FileDescriptor);
  Signature: (Ljava/io/FileDescriptor;)Lscala/xml/Node;
  Code:
   Stack=2, Locals=2, Args_size=2
	aload_0
	aload_1
	invokestatic	Method scala/xml/factory/XMLLoader$class.loadFile:(Lscala/xml/factory/XMLLoader;Ljava/io/FileDescriptor;)Lscala/xml/Node;
	areturn
  Labels:
  LocalVariableTable: 
   Start  Length  Slot  Name   Signature
   0      6      0    this       Lscala/xml/XML$;
   0      6      1    fd       Ljava/io/FileDescriptor;


public scala.xml.Node loadFile(java.io.File);
  Signature: (Ljava/io/File;)Lscala/xml/Node;
  Code:
   Stack=2, Locals=2, Args_size=2
	aload_0
	aload_1
	invokestatic	Method scala/xml/factory/XMLLoader$class.loadFile:(Lscala/xml/factory/XMLLoader;Ljava/io/File;)Lscala/xml/Node;
	areturn
  Labels:
  LocalVariableTable: 
   Start  Length  Slot  Name   Signature
   0      6      0    this       Lscala/xml/XML$;
   0      6      1    file       Ljava/io/File;


public scala.xml.Node loadXML(org.xml.sax.InputSource, javax.xml.parsers.SAXParser);
  Signature: (Lorg/xml/sax/InputSource;Ljavax/xml/parsers/SAXParser;)Lscala/xml/Node;
  Code:
   Stack=3, Locals=3, Args_size=3
	aload_0
	aload_1
	aload_2
	invokestatic	Method scala/xml/factory/XMLLoader$class.loadXML:(Lscala/xml/factory/XMLLoader;Lorg/xml/sax/InputSource;Ljavax/xml/parsers/SAXParser;)Lscala/xml/Node;
	areturn
  Labels:
  LocalVariableTable: 
   Start  Length  Slot  Name   Signature
   0      7      0    this       Lscala/xml/XML$;
   0      7      1    source       Lorg/xml/sax/InputSource;
   0      7      2    parser       Ljavax/xml/parsers/SAXParser;


public javax.xml.parsers.SAXParser parser();
  Signature: ()Ljavax/xml/parsers/SAXParser;
  Code:
   Stack=1, Locals=1, Args_size=1
	aload_0
	invokestatic	Method scala/xml/factory/XMLLoader$class.parser:(Lscala/xml/factory/XMLLoader;)Ljavax/xml/parsers/SAXParser;
	areturn
  Labels:

public scala.xml.parsing.FactoryAdapter adapter();
  Signature: ()Lscala/xml/parsing/FactoryAdapter;
  Code:
   Stack=1, Locals=1, Args_size=1
	aload_0
	invokestatic	Method scala/xml/factory/XMLLoader$class.adapter:(Lscala/xml/factory/XMLLoader;)Lscala/xml/parsing/FactoryAdapter;
	areturn
  Labels:

public void scala$xml$factory$XMLLoader$_setter_$scala$xml$factory$XMLLoader$$saxFactory_$eq(javax.xml.parsers.SAXParserFactory);
  Signature: (Ljavax/xml/parsers/SAXParserFactory;)V
  Code:
   Stack=2, Locals=2, Args_size=2
	aload_0
	aload_1
	putfield	Field scala$xml$factory$XMLLoader$$saxFactory:Ljavax/xml/parsers/SAXParserFactory;
	return
  Labels:

public final javax.xml.parsers.SAXParserFactory scala$xml$factory$XMLLoader$$saxFactory();
  Signature: ()Ljavax/xml/parsers/SAXParserFactory;
  Code:
   Stack=1, Locals=1, Args_size=1
	aload_0
	getfield	Field scala$xml$factory$XMLLoader$$saxFactory:Ljavax/xml/parsers/SAXParserFactory;
	areturn
  Labels:

}

