Compiled from "XML.scala"
public final class scala.xml.XML extends java.lang.Object
  SourceFile: "XML.scala"
  ScalaSig: length = 0x4A1
   05 00 FFFFFF81 2B 07 05 01 02 FFFFFF88 02 07 01 03 58 4D 4C
   0A 02 03 04 01 03 78 6D 6C 0A 01 05 01 05 73 63
   61 6C 61 03 00 10 02 08 09 0D 01 02 06 08 0A 02
   FFFFFF84 FFFFFF80 FFFFFF80 FFFFFF88 02 0B 02 03 58 4D 4C 13 04 09 0C 14
   1D 10 02 0D 12 0D 01 0E 0A 02 0F 10 01 04 6C 61
   6E 67 0A 01 11 01 04 6A 61 76 61 09 02 13 0E 02
   06 4F 62 6A 65 63 74 10 03 15 18 1A 0D 01 16 0A
   02 17 02 01 07 66 61 63 74 6F 72 79 09 02 19 16
   02 09 58 4D 4C 4C 6F 61 64 65 72 10 02 08 1B 09
   02 1C 02 02 04 45 6C 65 6D 10 02 1E 1F 0D 01 04
   09 02 20 04 02 0B 53 63 61 6C 61 4F 62 6A 65 63
   74 08 05 22 09 FFFFFF84 00 23 01 06 3C 69 6E 69 74 3E
   14 01 07 08 07 03 09 FFFFFFC2 FFFFFF80 FFFFFF84 00 25 15 01 26 10
   02 0D 27 09 02 28 0E 02 06 53 74 72 69 6E 67 08
   06 2A 09 FFFFFFA0 FFFFFF80 04 26 01 04 78 6D 6C 20 08 07 2C
   09 FFFFFFC2 FFFFFF80 FFFFFF84 00 25 01 05 78 6D 6C 6E 73 08 06 2E
   09 FFFFFFA0 FFFFFF80 04 26 01 06 78 6D 6C 6E 73 20 08 07 30
   09 FFFFFFC2 FFFFFF80 FFFFFF84 00 25 01 09 6E 61 6D 65 73 70 61 63
   65 08 06 32 09 FFFFFFA0 FFFFFF80 04 26 01 0A 6E 61 6D 65 73
   70 61 63 65 20 08 07 34 09 FFFFFFC2 FFFFFF80 FFFFFF84 00 25 01 08
   70 72 65 73 65 72 76 65 08 06 36 09 FFFFFFA0 FFFFFF80 04 26
   01 09 70 72 65 73 65 72 76 65 20 08 07 38 09 FFFFFFC2
   FFFFFF80 FFFFFF84 00 25 01 05 73 70 61 63 65 08 06 3A 09 FFFFFFA0
   FFFFFF80 04 26 01 06 73 70 61 63 65 20 08 07 0F 09 FFFFFFC2
   FFFFFF80 FFFFFF84 00 25 08 06 3D 09 FFFFFFA0 FFFFFF80 04 26 01 05 6C 61
   6E 67 20 08 07 3F 09 FFFFFFC2 FFFFFF80 FFFFFF84 00 25 01 08 65 6E
   63 6F 64 69 6E 67 08 06 41 09 FFFFFFA0 FFFFFF80 04 26 01 09
   65 6E 63 6F 64 69 6E 67 20 08 05 43 09 FFFFFF84 00 44
   01 0D 77 69 74 68 53 41 58 50 61 72 73 65 72 14
   02 14 45 08 05 46 42 FFFFFFC0 00 47 01 01 70 10 02 48
   4E 0D 01 49 0A 02 4A 4B 01 07 70 61 72 73 65 72
   73 0A 02 03 4C 0A 01 4D 01 05 6A 61 76 61 78 09
   02 4F 49 02 09 53 41 58 50 61 72 73 65 72 08 05
   51 09 FFFFFF84 02 52 01 08 73 61 76 65 46 75 6C 6C 14
   05 53 56 5E 63 68 10 02 1E 54 09 02 55 04 02 04
   55 6E 69 74 08 05 57 50 FFFFFFC0 00 58 01 08 66 69 6C
   65 6E 61 6D 65 10 02 59 5C 0E 02 1E 5A 09 02 5B
   04 01 06 50 72 65 64 65 66 09 02 28 5D 0A 02 5B
   04 08 05 5F 50 FFFFFFC0 00 60 01 04 6E 6F 64 65 10 02
   08 61 09 02 62 02 02 04 4E 6F 64 65 08 05 64 50
   FFFFFFC0 00 65 01 07 78 6D 6C 44 65 63 6C 10 02 1E 66
   09 02 67 04 02 07 42 6F 6F 6C 65 61 6E 08 05 69
   50 FFFFFFC0 00 6A 01 07 64 6F 63 74 79 70 65 10 02 6B
   6E 0D 01 6C 0A 02 6D 02 01 03 64 74 64 09 02 6F
   6C 02 07 44 6F 63 54 79 70 65 28 03 50 71 74 10
   02 1E 72 09 02 73 04 02 0A 64 65 70 72 65 63 61
   74 65 64 21 01 75 01 12 55 73 65 20 73 61 76 65
   28 29 20 69 6E 73 74 65 61 64 08 05 51 09 FFFFFF84 02
   77 14 06 53 78 79 7A 7C 7D 08 05 57 76 FFFFFFC0 00 58
   08 05 5F 76 FFFFFFC0 00 60 08 05 7B 76 FFFFFFC0 00 58 01 03
   65 6E 63 08 05 64 76 FFFFFFC0 00 65 08 05 69 76 FFFFFFC0 00
   6A 28 03 76 71 74 08 07 FFFFFF81 00 09 FFFFFF84 02 FFFFFF81 01 01
   04 73 61 76 65 14 0B 53 FFFFFF81 02 FFFFFF81 03 FFFFFF81 04 FFFFFF81 12
   FFFFFF81 17 08 05 57 7F FFFFFFC0 00 58 08 05 5F 7F FFFFFFC0 00 60
   08 09 FFFFFF81 05 7B 7F FFFFFF90 FFFFFF80 FFFFFFC0 00 58 08 09 FFFFFF81 06 09
   FFFFFF91 FFFFFF80 FFFFFF84 02 FFFFFF81 07 01 0E 73 61 76 65 24 64 65 66
   61 75 6C 74 24 33 15 02 FFFFFF81 08 2A 03 58 FFFFFF81 09 2B
   02 FFFFFF81 0A 10 04 FFFFFF81 0B FFFFFF81 10 0D 02 FFFFFF81 0C 0A 04 FFFFFF81
   0D FFFFFF81 0E 01 09 75 6E 63 68 65 63 6B 65 64 0A 03
   FFFFFF81 0F 04 01 0A 61 6E 6E 6F 74 61 74 69 6F 6E 09
   04 FFFFFF81 11 FFFFFF81 0C 02 11 75 6E 63 68 65 63 6B 65 64
   56 61 72 69 61 6E 63 65 08 09 FFFFFF81 13 64 7F FFFFFF90 FFFFFF80
   FFFFFFC0 00 65 08 09 FFFFFF81 14 09 FFFFFF91 FFFFFF80 FFFFFF84 02 FFFFFF81 15 01 0E
   73 61 76 65 24 64 65 66 61 75 6C 74 24 34 15 02
   FFFFFF81 16 2A 03 65 FFFFFF81 09 08 09 FFFFFF81 18 69 7F FFFFFF90 FFFFFF80 FFFFFFC0
   00 6A 08 09 FFFFFF81 19 09 FFFFFF91 FFFFFF80 FFFFFF84 02 FFFFFF81 1A 01 0E 73
   61 76 65 24 64 65 66 61 75 6C 74 24 35 15 02 FFFFFF81
   1B 2A 03 6A FFFFFF81 09 08 07 FFFFFF81 1D 09 FFFFFF84 02 FFFFFF81 1E 01
   05 77 72 69 74 65 14 0B 53 FFFFFF81 1F FFFFFF81 27 FFFFFF81 28 FFFFFF81
   29 FFFFFF81 2A 08 08 FFFFFF81 20 FFFFFF81 1C FFFFFFC0 00 FFFFFF81 21 01 01 77
   10 04 FFFFFF81 22 FFFFFF81 25 0D 02 FFFFFF81 23 0A 03 FFFFFF81 24 10 01
   02 69 6F 09 04 FFFFFF81 26 FFFFFF81 23 02 06 57 72 69 74 65
   72 08 06 5F FFFFFF81 1C FFFFFFC0 00 60 08 06 7B FFFFFF81 1C FFFFFFC0 00
   58 08 06 64 FFFFFF81 1C FFFFFFC0 00 65 08 06 69 FFFFFF81 1C FFFFFFC0 00
   6A 
  InnerClass: 
   public final $anon$1=class scala/xml/XML$$anon$1 of class scala/xml/XML
   public final $anonfun$save$2=class scala/xml/XML$$anonfun$save$2 of class scala/xml/XML
   public final $anonfun$save$1=class scala/xml/XML$$anonfun$save$1 of class scala/xml/XML
  minor version: 0
  major version: 49
  Constant pool:
Asciz	SourceFile;
Asciz	XML.scala;
Asciz	loadString;
Asciz	(Ljava/lang/String;)Lscala/xml/Node;;
Asciz	Code;
Asciz	scala/xml/XML$;
class	scala/xml/XML$
Asciz	MODULE$;
Asciz	Lscala/xml/XML$;;
NameAndType	MODULE$:Lscala/xml/XML$;
Field	scala/xml/XML$.MODULE$:Lscala/xml/XML$;
NameAndType	loadString:(Ljava/lang/String;)Lscala/xml/Node;
Method	scala/xml/XML$.loadString:(Ljava/lang/String;)Lscala/xml/Node;
Asciz	load;
Asciz	(Ljava/net/URL;)Lscala/xml/Node;;
NameAndType	load:(Ljava/net/URL;)Lscala/xml/Node;
Method	scala/xml/XML$.load:(Ljava/net/URL;)Lscala/xml/Node;
Asciz	(Lorg/xml/sax/InputSource;)Lscala/xml/Node;;
NameAndType	load:(Lorg/xml/sax/InputSource;)Lscala/xml/Node;
Method	scala/xml/XML$.load:(Lorg/xml/sax/InputSource;)Lscala/xml/Node;
NameAndType	load:(Ljava/lang/String;)Lscala/xml/Node;
Method	scala/xml/XML$.load:(Ljava/lang/String;)Lscala/xml/Node;
Asciz	(Ljava/io/Reader;)Lscala/xml/Node;;
NameAndType	load:(Ljava/io/Reader;)Lscala/xml/Node;
Method	scala/xml/XML$.load:(Ljava/io/Reader;)Lscala/xml/Node;
Asciz	(Ljava/io/InputStream;)Lscala/xml/Node;;
NameAndType	load:(Ljava/io/InputStream;)Lscala/xml/Node;
Method	scala/xml/XML$.load:(Ljava/io/InputStream;)Lscala/xml/Node;
Asciz	loadFile;
NameAndType	loadFile:(Ljava/lang/String;)Lscala/xml/Node;
Method	scala/xml/XML$.loadFile:(Ljava/lang/String;)Lscala/xml/Node;
Asciz	(Ljava/io/FileDescriptor;)Lscala/xml/Node;;
NameAndType	loadFile:(Ljava/io/FileDescriptor;)Lscala/xml/Node;
Method	scala/xml/XML$.loadFile:(Ljava/io/FileDescriptor;)Lscala/xml/Node;
Asciz	(Ljava/io/File;)Lscala/xml/Node;;
NameAndType	loadFile:(Ljava/io/File;)Lscala/xml/Node;
Method	scala/xml/XML$.loadFile:(Ljava/io/File;)Lscala/xml/Node;
Asciz	loadXML;
Asciz	(Lorg/xml/sax/InputSource;Ljavax/xml/parsers/SAXParser;)Lscala/xml/Node;;
NameAndType	loadXML:(Lorg/xml/sax/InputSource;Ljavax/xml/parsers/SAXParser;)Lscala/xml/Node;
Method	scala/xml/XML$.loadXML:(Lorg/xml/sax/InputSource;Ljavax/xml/parsers/SAXParser;)Lscala/xml/Node;
Asciz	parser;
Asciz	()Ljavax/xml/parsers/SAXParser;;
NameAndType	parser:()Ljavax/xml/parsers/SAXParser;
Method	scala/xml/XML$.parser:()Ljavax/xml/parsers/SAXParser;
Asciz	adapter;
Asciz	()Lscala/xml/parsing/FactoryAdapter;;
NameAndType	adapter:()Lscala/xml/parsing/FactoryAdapter;
Method	scala/xml/XML$.adapter:()Lscala/xml/parsing/FactoryAdapter;
Asciz	scala$xml$factory$XMLLoader$_setter_$scala$xml$factory$XMLLoader$$saxFactory_$eq;
Asciz	(Ljavax/xml/parsers/SAXParserFactory;)V;
NameAndType	scala$xml$factory$XMLLoader$_setter_$scala$xml$factory$XMLLoader$$saxFactory_$eq:(Ljavax/xml/parsers/SAXParserFactory;)V
Method	scala/xml/XML$.scala$xml$factory$XMLLoader$_setter_$scala$xml$factory$XMLLoader$$saxFactory_$eq:(Ljavax/xml/parsers/SAXParserFactory;)V
Asciz	scala$xml$factory$XMLLoader$$saxFactory;
Asciz	()Ljavax/xml/parsers/SAXParserFactory;;
NameAndType	scala$xml$factory$XMLLoader$$saxFactory:()Ljavax/xml/parsers/SAXParserFactory;
Method	scala/xml/XML$.scala$xml$factory$XMLLoader$$saxFactory:()Ljavax/xml/parsers/SAXParserFactory;
Asciz	save$default$5;
Asciz	()Lscala/xml/dtd/DocType;;
NameAndType	save$default$5:()Lscala/xml/dtd/DocType;
Method	scala/xml/XML$.save$default$5:()Lscala/xml/dtd/DocType;
Asciz	save$default$4;
Asciz	()Z;
NameAndType	save$default$4:()Z
Method	scala/xml/XML$.save$default$4:()Z
Asciz	save$default$3;
Asciz	()Ljava/lang/String;;
NameAndType	save$default$3:()Ljava/lang/String;
Method	scala/xml/XML$.save$default$3:()Ljava/lang/String;
Asciz	write;
Asciz	(Ljava/io/Writer;Lscala/xml/Node;Ljava/lang/String;ZLscala/xml/dtd/DocType;)V;
NameAndType	write:(Ljava/io/Writer;Lscala/xml/Node;Ljava/lang/String;ZLscala/xml/dtd/DocType;)V
Method	scala/xml/XML$.write:(Ljava/io/Writer;Lscala/xml/Node;Ljava/lang/String;ZLscala/xml/dtd/DocType;)V
Asciz	save;
Asciz	(Ljava/lang/String;Lscala/xml/Node;Ljava/lang/String;ZLscala/xml/dtd/DocType;)V;
NameAndType	save:(Ljava/lang/String;Lscala/xml/Node;Ljava/lang/String;ZLscala/xml/dtd/DocType;)V
Method	scala/xml/XML$.save:(Ljava/lang/String;Lscala/xml/Node;Ljava/lang/String;ZLscala/xml/dtd/DocType;)V
Asciz	saveFull;
NameAndType	saveFull:(Ljava/lang/String;Lscala/xml/Node;Ljava/lang/String;ZLscala/xml/dtd/DocType;)V
Method	scala/xml/XML$.saveFull:(Ljava/lang/String;Lscala/xml/Node;Ljava/lang/String;ZLscala/xml/dtd/DocType;)V
Asciz	Deprecated;
Asciz	(Ljava/lang/String;Lscala/xml/Node;ZLscala/xml/dtd/DocType;)V;
NameAndType	saveFull:(Ljava/lang/String;Lscala/xml/Node;ZLscala/xml/dtd/DocType;)V
Method	scala/xml/XML$.saveFull:(Ljava/lang/String;Lscala/xml/Node;ZLscala/xml/dtd/DocType;)V
Asciz	withSAXParser;
Asciz	(Ljavax/xml/parsers/SAXParser;)Lscala/xml/factory/XMLLoader;;
NameAndType	withSAXParser:(Ljavax/xml/parsers/SAXParser;)Lscala/xml/factory/XMLLoader;
Method	scala/xml/XML$.withSAXParser:(Ljavax/xml/parsers/SAXParser;)Lscala/xml/factory/XMLLoader;
Asciz	(Ljavax/xml/parsers/SAXParser;)Lscala/xml/factory/XMLLoader<Lscala/xml/Elem;>;;
Asciz	Signature;
Asciz	encoding;
NameAndType	encoding:()Ljava/lang/String;
Method	scala/xml/XML$.encoding:()Ljava/lang/String;
Asciz	lang;
NameAndType	lang:()Ljava/lang/String;
Method	scala/xml/XML$.lang:()Ljava/lang/String;
Asciz	space;
NameAndType	space:()Ljava/lang/String;
Method	scala/xml/XML$.space:()Ljava/lang/String;
Asciz	preserve;
NameAndType	preserve:()Ljava/lang/String;
Method	scala/xml/XML$.preserve:()Ljava/lang/String;
Asciz	namespace;
NameAndType	namespace:()Ljava/lang/String;
Method	scala/xml/XML$.namespace:()Ljava/lang/String;
Asciz	xmlns;
NameAndType	xmlns:()Ljava/lang/String;
Method	scala/xml/XML$.xmlns:()Ljava/lang/String;
Asciz	xml;
NameAndType	xml:()Ljava/lang/String;
Method	scala/xml/XML$.xml:()Ljava/lang/String;
Asciz	ScalaSig;
Asciz	InnerClasses;
Asciz	scala/xml/XML$$anon$1;
class	scala/xml/XML$$anon$1
Asciz	scala/xml/XML;
class	scala/xml/XML
Asciz	$anon$1;
Asciz	scala/xml/XML$$anonfun$save$2;
class	scala/xml/XML$$anonfun$save$2
Asciz	$anonfun$save$2;
Asciz	scala/xml/XML$$anonfun$save$1;
class	scala/xml/XML$$anonfun$save$1
Asciz	$anonfun$save$1;
Asciz	java/lang/Object;
class	java/lang/Object

{
public static final scala.xml.Node loadString(java.lang.String);
  Signature: (Ljava/lang/String;)Lscala/xml/Node;
  Code:
   Stack=2, Locals=1, Args_size=1
	getstatic	Field scala/xml/XML$.MODULE$:Lscala/xml/XML$;
	aload_0
	invokevirtual	Method scala/xml/XML$.loadString:(Ljava/lang/String;)Lscala/xml/Node;
	areturn
  Labels:

public static final scala.xml.Node load(java.net.URL);
  Signature: (Ljava/net/URL;)Lscala/xml/Node;
  Code:
   Stack=2, Locals=1, Args_size=1
	getstatic	Field scala/xml/XML$.MODULE$:Lscala/xml/XML$;
	aload_0
	invokevirtual	Method scala/xml/XML$.load:(Ljava/net/URL;)Lscala/xml/Node;
	areturn
  Labels:

public static final scala.xml.Node load(org.xml.sax.InputSource);
  Signature: (Lorg/xml/sax/InputSource;)Lscala/xml/Node;
  Code:
   Stack=2, Locals=1, Args_size=1
	getstatic	Field scala/xml/XML$.MODULE$:Lscala/xml/XML$;
	aload_0
	invokevirtual	Method scala/xml/XML$.load:(Lorg/xml/sax/InputSource;)Lscala/xml/Node;
	areturn
  Labels:

public static final scala.xml.Node load(java.lang.String);
  Signature: (Ljava/lang/String;)Lscala/xml/Node;
  Code:
   Stack=2, Locals=1, Args_size=1
	getstatic	Field scala/xml/XML$.MODULE$:Lscala/xml/XML$;
	aload_0
	invokevirtual	Method scala/xml/XML$.load:(Ljava/lang/String;)Lscala/xml/Node;
	areturn
  Labels:

public static final scala.xml.Node load(java.io.Reader);
  Signature: (Ljava/io/Reader;)Lscala/xml/Node;
  Code:
   Stack=2, Locals=1, Args_size=1
	getstatic	Field scala/xml/XML$.MODULE$:Lscala/xml/XML$;
	aload_0
	invokevirtual	Method scala/xml/XML$.load:(Ljava/io/Reader;)Lscala/xml/Node;
	areturn
  Labels:

public static final scala.xml.Node load(java.io.InputStream);
  Signature: (Ljava/io/InputStream;)Lscala/xml/Node;
  Code:
   Stack=2, Locals=1, Args_size=1
	getstatic	Field scala/xml/XML$.MODULE$:Lscala/xml/XML$;
	aload_0
	invokevirtual	Method scala/xml/XML$.load:(Ljava/io/InputStream;)Lscala/xml/Node;
	areturn
  Labels:

public static final scala.xml.Node loadFile(java.lang.String);
  Signature: (Ljava/lang/String;)Lscala/xml/Node;
  Code:
   Stack=2, Locals=1, Args_size=1
	getstatic	Field scala/xml/XML$.MODULE$:Lscala/xml/XML$;
	aload_0
	invokevirtual	Method scala/xml/XML$.loadFile:(Ljava/lang/String;)Lscala/xml/Node;
	areturn
  Labels:

public static final scala.xml.Node loadFile(java.io.FileDescriptor);
  Signature: (Ljava/io/FileDescriptor;)Lscala/xml/Node;
  Code:
   Stack=2, Locals=1, Args_size=1
	getstatic	Field scala/xml/XML$.MODULE$:Lscala/xml/XML$;
	aload_0
	invokevirtual	Method scala/xml/XML$.loadFile:(Ljava/io/FileDescriptor;)Lscala/xml/Node;
	areturn
  Labels:

public static final scala.xml.Node loadFile(java.io.File);
  Signature: (Ljava/io/File;)Lscala/xml/Node;
  Code:
   Stack=2, Locals=1, Args_size=1
	getstatic	Field scala/xml/XML$.MODULE$:Lscala/xml/XML$;
	aload_0
	invokevirtual	Method scala/xml/XML$.loadFile:(Ljava/io/File;)Lscala/xml/Node;
	areturn
  Labels:

public static final scala.xml.Node loadXML(org.xml.sax.InputSource, javax.xml.parsers.SAXParser);
  Signature: (Lorg/xml/sax/InputSource;Ljavax/xml/parsers/SAXParser;)Lscala/xml/Node;
  Code:
   Stack=3, Locals=2, Args_size=2
	getstatic	Field scala/xml/XML$.MODULE$:Lscala/xml/XML$;
	aload_0
	aload_1
	invokevirtual	Method scala/xml/XML$.loadXML:(Lorg/xml/sax/InputSource;Ljavax/xml/parsers/SAXParser;)Lscala/xml/Node;
	areturn
  Labels:

public static final javax.xml.parsers.SAXParser parser();
  Signature: ()Ljavax/xml/parsers/SAXParser;
  Code:
   Stack=1, Locals=0, Args_size=0
	getstatic	Field scala/xml/XML$.MODULE$:Lscala/xml/XML$;
	invokevirtual	Method scala/xml/XML$.parser:()Ljavax/xml/parsers/SAXParser;
	areturn
  Labels:

public static final scala.xml.parsing.FactoryAdapter adapter();
  Signature: ()Lscala/xml/parsing/FactoryAdapter;
  Code:
   Stack=1, Locals=0, Args_size=0
	getstatic	Field scala/xml/XML$.MODULE$:Lscala/xml/XML$;
	invokevirtual	Method scala/xml/XML$.adapter:()Lscala/xml/parsing/FactoryAdapter;
	areturn
  Labels:

public static final void scala$xml$factory$XMLLoader$_setter_$scala$xml$factory$XMLLoader$$saxFactory_$eq(javax.xml.parsers.SAXParserFactory);
  Signature: (Ljavax/xml/parsers/SAXParserFactory;)V
  Code:
   Stack=2, Locals=1, Args_size=1
	getstatic	Field scala/xml/XML$.MODULE$:Lscala/xml/XML$;
	aload_0
	invokevirtual	Method scala/xml/XML$.scala$xml$factory$XMLLoader$_setter_$scala$xml$factory$XMLLoader$$saxFactory_$eq:(Ljavax/xml/parsers/SAXParserFactory;)V
	return
  Labels:

public static final javax.xml.parsers.SAXParserFactory scala$xml$factory$XMLLoader$$saxFactory();
  Signature: ()Ljavax/xml/parsers/SAXParserFactory;
  Code:
   Stack=1, Locals=0, Args_size=0
	getstatic	Field scala/xml/XML$.MODULE$:Lscala/xml/XML$;
	invokevirtual	Method scala/xml/XML$.scala$xml$factory$XMLLoader$$saxFactory:()Ljavax/xml/parsers/SAXParserFactory;
	areturn
  Labels:

public static final scala.xml.dtd.DocType save$default$5();
  Signature: ()Lscala/xml/dtd/DocType;
  Code:
   Stack=1, Locals=0, Args_size=0
	getstatic	Field scala/xml/XML$.MODULE$:Lscala/xml/XML$;
	invokevirtual	Method scala/xml/XML$.save$default$5:()Lscala/xml/dtd/DocType;
	areturn
  Labels:

public static final boolean save$default$4();
  Signature: ()Z
  Code:
   Stack=1, Locals=0, Args_size=0
	getstatic	Field scala/xml/XML$.MODULE$:Lscala/xml/XML$;
	invokevirtual	Method scala/xml/XML$.save$default$4:()Z
	ireturn
  Labels:

public static final java.lang.String save$default$3();
  Signature: ()Ljava/lang/String;
  Code:
   Stack=1, Locals=0, Args_size=0
	getstatic	Field scala/xml/XML$.MODULE$:Lscala/xml/XML$;
	invokevirtual	Method scala/xml/XML$.save$default$3:()Ljava/lang/String;
	areturn
  Labels:

public static final void write(java.io.Writer, scala.xml.Node, java.lang.String, boolean, scala.xml.dtd.DocType);
  Signature: (Ljava/io/Writer;Lscala/xml/Node;Ljava/lang/String;ZLscala/xml/dtd/DocType;)V
  Code:
   Stack=6, Locals=5, Args_size=5
	getstatic	Field scala/xml/XML$.MODULE$:Lscala/xml/XML$;
	aload_0
	aload_1
	aload_2
	iload_3
	aload	4
	invokevirtual	Method scala/xml/XML$.write:(Ljava/io/Writer;Lscala/xml/Node;Ljava/lang/String;ZLscala/xml/dtd/DocType;)V
	return
  Labels:

public static final void save(java.lang.String, scala.xml.Node, java.lang.String, boolean, scala.xml.dtd.DocType);
  Signature: (Ljava/lang/String;Lscala/xml/Node;Ljava/lang/String;ZLscala/xml/dtd/DocType;)V
  Code:
   Stack=6, Locals=5, Args_size=5
	getstatic	Field scala/xml/XML$.MODULE$:Lscala/xml/XML$;
	aload_0
	aload_1
	aload_2
	iload_3
	aload	4
	invokevirtual	Method scala/xml/XML$.save:(Ljava/lang/String;Lscala/xml/Node;Ljava/lang/String;ZLscala/xml/dtd/DocType;)V
	return
  Labels:

public static final void saveFull(java.lang.String, scala.xml.Node, java.lang.String, boolean, scala.xml.dtd.DocType);
  Signature: (Ljava/lang/String;Lscala/xml/Node;Ljava/lang/String;ZLscala/xml/dtd/DocType;)V
  Code:
   Stack=6, Locals=5, Args_size=5
	getstatic	Field scala/xml/XML$.MODULE$:Lscala/xml/XML$;
	aload_0
	aload_1
	aload_2
	iload_3
	aload	4
	invokevirtual	Method scala/xml/XML$.saveFull:(Ljava/lang/String;Lscala/xml/Node;Ljava/lang/String;ZLscala/xml/dtd/DocType;)V
	return
  Labels:
  Deprecated: true

public static final void saveFull(java.lang.String, scala.xml.Node, boolean, scala.xml.dtd.DocType);
  Signature: (Ljava/lang/String;Lscala/xml/Node;ZLscala/xml/dtd/DocType;)V
  Code:
   Stack=5, Locals=4, Args_size=4
	getstatic	Field scala/xml/XML$.MODULE$:Lscala/xml/XML$;
	aload_0
	aload_1
	iload_2
	aload_3
	invokevirtual	Method scala/xml/XML$.saveFull:(Ljava/lang/String;Lscala/xml/Node;ZLscala/xml/dtd/DocType;)V
	return
  Labels:
  Deprecated: true

public static final scala.xml.factory.XMLLoader withSAXParser(javax.xml.parsers.SAXParser);
  Signature: (Ljavax/xml/parsers/SAXParser;)Lscala/xml/factory/XMLLoader;
  Code:
   Stack=2, Locals=1, Args_size=1
	getstatic	Field scala/xml/XML$.MODULE$:Lscala/xml/XML$;
	aload_0
	invokevirtual	Method scala/xml/XML$.withSAXParser:(Ljavax/xml/parsers/SAXParser;)Lscala/xml/factory/XMLLoader;
	areturn
  Labels:
  Signature: length = 0x2
   00 59 

public static final java.lang.String encoding();
  Signature: ()Ljava/lang/String;
  Code:
   Stack=1, Locals=0, Args_size=0
	getstatic	Field scala/xml/XML$.MODULE$:Lscala/xml/XML$;
	invokevirtual	Method scala/xml/XML$.encoding:()Ljava/lang/String;
	areturn
  Labels:

public static final java.lang.String lang();
  Signature: ()Ljava/lang/String;
  Code:
   Stack=1, Locals=0, Args_size=0
	getstatic	Field scala/xml/XML$.MODULE$:Lscala/xml/XML$;
	invokevirtual	Method scala/xml/XML$.lang:()Ljava/lang/String;
	areturn
  Labels:

public static final java.lang.String space();
  Signature: ()Ljava/lang/String;
  Code:
   Stack=1, Locals=0, Args_size=0
	getstatic	Field scala/xml/XML$.MODULE$:Lscala/xml/XML$;
	invokevirtual	Method scala/xml/XML$.space:()Ljava/lang/String;
	areturn
  Labels:

public static final java.lang.String preserve();
  Signature: ()Ljava/lang/String;
  Code:
   Stack=1, Locals=0, Args_size=0
	getstatic	Field scala/xml/XML$.MODULE$:Lscala/xml/XML$;
	invokevirtual	Method scala/xml/XML$.preserve:()Ljava/lang/String;
	areturn
  Labels:

public static final java.lang.String namespace();
  Signature: ()Ljava/lang/String;
  Code:
   Stack=1, Locals=0, Args_size=0
	getstatic	Field scala/xml/XML$.MODULE$:Lscala/xml/XML$;
	invokevirtual	Method scala/xml/XML$.namespace:()Ljava/lang/String;
	areturn
  Labels:

public static final java.lang.String xmlns();
  Signature: ()Ljava/lang/String;
  Code:
   Stack=1, Locals=0, Args_size=0
	getstatic	Field scala/xml/XML$.MODULE$:Lscala/xml/XML$;
	invokevirtual	Method scala/xml/XML$.xmlns:()Ljava/lang/String;
	areturn
  Labels:

public static final java.lang.String xml();
  Signature: ()Ljava/lang/String;
  Code:
   Stack=1, Locals=0, Args_size=0
	getstatic	Field scala/xml/XML$.MODULE$:Lscala/xml/XML$;
	invokevirtual	Method scala/xml/XML$.xml:()Ljava/lang/String;
	areturn
  Labels:

}

