Compiled from "ControlContext.scala"
public final class scala.util.continuations.ControlContext extends java.lang.Object implements scala.ScalaObject,java.io.Serializable
  SourceFile: "ControlContext.scala"
  ScalaSig: length = 0x3
   05 00 00 
  Signature: length = 0x2
   00 7C 
  RuntimeVisibleAnnotations: length = 0xB
   00 01 00 7D 00 01 00 7E 73 00 7F 
  InnerClass: 
   public final $anonfun$3=class scala/util/continuations/ControlContext$$anonfun$3 of class scala/util/continuations/ControlContext
   public final $anonfun$1=class scala/util/continuations/ControlContext$$anonfun$1 of class scala/util/continuations/ControlContext
   public final $anonfun$map$1=class scala/util/continuations/ControlContext$$anonfun$map$1 of class scala/util/continuations/ControlContext
   public final $anonfun$map$2=class scala/util/continuations/ControlContext$$anonfun$map$2 of class scala/util/continuations/ControlContext
   public final $anonfun$foreach$1=class scala/util/continuations/ControlContext$$anonfun$foreach$1 of class scala/util/continuations/ControlContext
   public final $anonfun$flatMap$1=class scala/util/continuations/ControlContext$$anonfun$flatMap$1 of class scala/util/continuations/ControlContext
   public final $anonfun$flatMap$2=class scala/util/continuations/ControlContext$$anonfun$flatMap$2 of class scala/util/continuations/ControlContext
   public final $anonfun$mapFinally$1=class scala/util/continuations/ControlContext$$anonfun$mapFinally$1 of class scala/util/continuations/ControlContext
  minor version: 0
  major version: 49
  Constant pool:
Asciz	SourceFile;
Asciz	ControlContext.scala;
Asciz	fun;
Asciz	Lscala/Function2;;
Asciz	Lscala/Function2<Lscala/Function1<TA;TB;>;Lscala/Function1<Ljava/lang/Exception;TB;>;TC;>;;
Asciz	Signature;
Asciz	x;
Asciz	Ljava/lang/Object;;
Asciz	TA;;
Asciz	()Lscala/Function2;;
Asciz	Code;
Asciz	LineNumberTable;
Asciz	scala/util/continuations/ControlContext;
class	scala/util/continuations/ControlContext
NameAndType	fun:Lscala/Function2;
Field	scala/util/continuations/ControlContext.fun:Lscala/Function2;
Asciz	()Lscala/Function2<Lscala/Function1<TA;TB;>;Lscala/Function1<Ljava/lang/Exception;TB;>;TC;>;;
Asciz	()Ljava/lang/Object;;
NameAndType	x:Ljava/lang/Object;
Field	scala/util/continuations/ControlContext.x:Ljava/lang/Object;
Asciz	()TA;;
Asciz	map;
Asciz	(Lscala/Function1;)Lscala/util/continuations/ControlContext;;
Asciz	scala/Function1;
class	scala/Function1
Asciz	apply;
Asciz	(Ljava/lang/Object;)Ljava/lang/Object;;
NameAndType	apply:(Ljava/lang/Object;)Ljava/lang/Object;
InterfaceMethod	scala/Function1.apply:(Ljava/lang/Object;)Ljava/lang/Object;
Asciz	<init>;
Asciz	(Lscala/Function2;Ljava/lang/Object;)V;
NameAndType	"<init>":(Lscala/Function2;Ljava/lang/Object;)V
Method	scala/util/continuations/ControlContext."<init>":(Lscala/Function2;Ljava/lang/Object;)V
Asciz	scala/util/continuations/ControlContext$$anonfun$map$2;
class	scala/util/continuations/ControlContext$$anonfun$map$2
Asciz	(Lscala/util/continuations/ControlContext;Lscala/Function1;)V;
NameAndType	"<init>":(Lscala/util/continuations/ControlContext;Lscala/Function1;)V
Method	scala/util/continuations/ControlContext$$anonfun$map$2."<init>":(Lscala/util/continuations/ControlContext;Lscala/Function1;)V
Asciz	scala/util/continuations/ControlContext$$anonfun$map$1;
class	scala/util/continuations/ControlContext$$anonfun$map$1
Asciz	(Lscala/util/continuations/ControlContext;Ljava/lang/Exception;)V;
NameAndType	"<init>":(Lscala/util/continuations/ControlContext;Ljava/lang/Exception;)V
Method	scala/util/continuations/ControlContext$$anonfun$map$1."<init>":(Lscala/util/continuations/ControlContext;Ljava/lang/Exception;)V
Asciz	java/lang/Exception;
class	java/lang/Exception
Asciz	this;
Asciz	Lscala/util/continuations/ControlContext;;
Asciz	f$1;
Asciz	Lscala/Function1;;
Asciz	exceptionResult1;
Asciz	LocalVariableTable;
Asciz	<A1:Ljava/lang/Object;>(Lscala/Function1<TA;TA1;>;)Lscala/util/continuations/ControlContext<TA1;TB;TC;>;;
Asciz	flatMap;
Asciz	scala/util/continuations/ControlContext$$anonfun$flatMap$2;
class	scala/util/continuations/ControlContext$$anonfun$flatMap$2
Method	scala/util/continuations/ControlContext$$anonfun$flatMap$2."<init>":(Lscala/util/continuations/ControlContext;Lscala/Function1;)V
Asciz	scala/util/continuations/ControlContext$$anonfun$flatMap$1;
class	scala/util/continuations/ControlContext$$anonfun$flatMap$1
Method	scala/util/continuations/ControlContext$$anonfun$flatMap$1."<init>":(Lscala/util/continuations/ControlContext;Ljava/lang/Exception;)V
Asciz	f$2;
Asciz	exceptionResult2;
Asciz	<A1:Ljava/lang/Object;B1:Ljava/lang/Object;C1:TB;>(Lscala/Function1<TA;Lscala/util/continuations/ControlContext<TA1;TB1;TC1;>;>;)Lscala/util/continuations/ControlContext<TA1;TB1;TC;>;;
Asciz	foreach;
Asciz	(Lscala/Function1;)Ljava/lang/Object;;
Asciz	scala/util/continuations/ControlContext$$anonfun$foreach$1;
class	scala/util/continuations/ControlContext$$anonfun$foreach$1
Asciz	(Lscala/util/continuations/ControlContext;)V;
NameAndType	"<init>":(Lscala/util/continuations/ControlContext;)V
Method	scala/util/continuations/ControlContext$$anonfun$foreach$1."<init>":(Lscala/util/continuations/ControlContext;)V
Asciz	foreachFull;
Asciz	(Lscala/Function1;Lscala/Function1;)Ljava/lang/Object;;
NameAndType	foreachFull:(Lscala/Function1;Lscala/Function1;)Ljava/lang/Object;
Method	scala/util/continuations/ControlContext.foreachFull:(Lscala/Function1;Lscala/Function1;)Ljava/lang/Object;
Asciz	f;
Asciz	(Lscala/Function1<TA;TB;>;)TC;;
Asciz	scala/Function2;
class	scala/Function2
Asciz	(Ljava/lang/Object;Ljava/lang/Object;)Ljava/lang/Object;;
NameAndType	apply:(Ljava/lang/Object;Ljava/lang/Object;)Ljava/lang/Object;
InterfaceMethod	scala/Function2.apply:(Ljava/lang/Object;Ljava/lang/Object;)Ljava/lang/Object;
Asciz	g;
Asciz	(Lscala/Function1<TA;TB;>;Lscala/Function1<Ljava/lang/Exception;TB;>;)TC;;
Asciz	isTrivial;
Asciz	()Z;
Asciz	getTrivialValue;
NameAndType	x:()Ljava/lang/Object;
Method	scala/util/continuations/ControlContext.x:()Ljava/lang/Object;
Asciz	flatMapCatch;
Asciz	(Lscala/PartialFunction;)Lscala/util/continuations/ControlContext;;
Asciz	scala/util/continuations/ControlContext$$anonfun$1;
class	scala/util/continuations/ControlContext$$anonfun$1
Asciz	(Lscala/util/continuations/ControlContext;Lscala/PartialFunction;)V;
NameAndType	"<init>":(Lscala/util/continuations/ControlContext;Lscala/PartialFunction;)V
Method	scala/util/continuations/ControlContext$$anonfun$1."<init>":(Lscala/util/continuations/ControlContext;Lscala/PartialFunction;)V
Asciz	pf$1;
Asciz	Lscala/PartialFunction;;
Asciz	fun1;
Asciz	<A1:Ljava/lang/Object;B1:TB;C1:TB1;>(Lscala/PartialFunction<Ljava/lang/Exception;Lscala/util/continuations/ControlContext<TA1;TB1;TC1;>;>;)Lscala/util/continuations/ControlContext<TA1;TB1;TC1;>;;
Asciz	mapFinally;
Asciz	(Lscala/Function0;)Lscala/util/continuations/ControlContext;;
Asciz	scala/Function0;
class	scala/Function0
NameAndType	apply:()Ljava/lang/Object;
InterfaceMethod	scala/Function0.apply:()Ljava/lang/Object;
Asciz	scala/util/continuations/ControlContext$$anonfun$3;
class	scala/util/continuations/ControlContext$$anonfun$3
Asciz	(Lscala/util/continuations/ControlContext;Lscala/Function0;)V;
NameAndType	"<init>":(Lscala/util/continuations/ControlContext;Lscala/Function0;)V
Method	scala/util/continuations/ControlContext$$anonfun$3."<init>":(Lscala/util/continuations/ControlContext;Lscala/Function0;)V
Asciz	scala/util/continuations/ControlContext$$anonfun$mapFinally$1;
class	scala/util/continuations/ControlContext$$anonfun$mapFinally$1
Method	scala/util/continuations/ControlContext$$anonfun$mapFinally$1."<init>":(Lscala/util/continuations/ControlContext;Ljava/lang/Exception;)V
Asciz	f$3;
Asciz	Lscala/Function0;;
Asciz	exceptionResult3;
Asciz	(Lscala/Function0<Ljava/lang/Object;>;)Lscala/util/continuations/ControlContext<TA;TB;TC;>;;
Asciz	java/lang/Object;
class	java/lang/Object
Asciz	()V;
NameAndType	"<init>":()V
Method	java/lang/Object."<init>":()V
Asciz	(Lscala/Function2<Lscala/Function1<TA;TB;>;Lscala/Function1<Ljava/lang/Exception;TB;>;TC;>;TA;)V;
Asciz	ScalaSig;
Asciz	<A:Ljava/lang/Object;B:Ljava/lang/Object;C:Ljava/lang/Object;>Ljava/lang/Object;Lscala/ScalaObject;;
Asciz	Lscala/reflect/ScalaSignature;;
Asciz	bytes;
Asciz	UbB%abQ8oiJ|GnQ8oiDHO\ti1m8uS:,\r^5p]NT!!\tU$)1oY1mCQ#Yq2A!\ta#D\tqq\"mC:<'\"\t\t)g/Y%5aa2kK$C1B-6-7b\nTWm;\ta!Q1Ae\t1AZ;o+Q#;9ZB%1UO\2uS>t'=ZBA%1UO\2uS>t\"E1AC\t%)\"!\nQ1BAqu5j]\"F\n)2!aA!osB\t[!\t#bI\t\t!\t==ZC9\t\tdG3k5\t1G51AH]8pizJaBo\tq]1dW<W-:u\tIQ\t_2faRLwNo\"!\tuA!CCa\t\t)A5!a-8!!\tA!b\n!=BIIqBQAaP5oSRtDc%KB)\n,w5\t!C!CBCNa*AnCB,\"a*A##B%#.ZCAS\t!F\n\"A!#AA!2)F\n1W1AECQeqA7bi6/[;~+GCA.b!I0<!\t\tST/\tQ1%!\t\tsa/\tQ1%\tCV/!\r=#B%9z#CAf\t!1w\"A9'AA\"2#\t)3Cj!.Ag_J,m5mZ\"B+ii\"B7\tqa4pe7\r$vY2$2aO8q)F1\tH1/9\"B:\t!!C5t)JLg/[1m+)Cw\t9hAAC_>dW-8\teAQ\",G:jm&GNV1mkDQaqAB7bi6oQ1uG\",r!`A\tYFr! \tIE\"!b>\r!aBcAAMCq\rE\"!B>\r!!m\n)Ci\r!aA4#=rbAA\r\ty+:uSdg)8di&|gC!)!!5OR5oC2dFI?Aq!VA\r\t\tEG\t9#C&BR;oGRLwNQ\tI#C,A!8ji\"!aQ\t\t$C4Ab]3sSdN_1cY;
Asciz	RuntimeVisibleAnnotations;
Asciz	InnerClasses;
Asciz	$anonfun$3;
Asciz	$anonfun$1;
Asciz	$anonfun$map$1;
Asciz	$anonfun$map$2;
Asciz	$anonfun$foreach$1;
Asciz	$anonfun$flatMap$1;
Asciz	$anonfun$flatMap$2;
Asciz	$anonfun$mapFinally$1;
Asciz	scala/ScalaObject;
class	scala/ScalaObject
Asciz	java/io/Serializable;
class	java/io/Serializable

{
public final scala.Function2 fun;
  Signature: Lscala/Function2;
  Signature: length = 0x2
   00 05 

public final java.lang.Object x;
  Signature: Ljava/lang/Object;
  Signature: length = 0x2
   00 09 

public scala.Function2 fun();
  Signature: ()Lscala/Function2;
  Code:
   Stack=1, Locals=1, Args_size=1
	aload_0
	getfield	Field fun:Lscala/Function2;
	areturn
  Labels:
  Signature: length = 0x2
   00 11 

public java.lang.Object x();
  Signature: ()Ljava/lang/Object;
  Code:
   Stack=1, Locals=1, Args_size=1
	aload_0
	getfield	Field x:Ljava/lang/Object;
	areturn
  Labels:
  Signature: length = 0x2
   00 15 

public final scala.util.continuations.ControlContext map(scala.Function1);
  Signature: (Lscala/Function1;)Lscala/util/continuations/ControlContext;
  Code:
   Stack=6, Locals=4, Args_size=2
	aload_0
	getfield	Field fun:Lscala/Function2;
	ifnonnull	l1 // new
	new	class scala/util/continuations/ControlContext
	dup
	aconst_null
	aload_1
	aload_0
	getfield	Field x:Ljava/lang/Object;
	invokeinterface	InterfaceMethod scala/Function1.apply:(Ljava/lang/Object;)Ljava/lang/Object;
	invokespecial	Method "<init>":(Lscala/Function2;Ljava/lang/Object;)V
	astore_3
	goto	l2 // aload_3
l1	new	class scala/util/continuations/ControlContext
	dup
	new	class scala/util/continuations/ControlContext$$anonfun$map$2
	dup
	aload_0
	aload_1
	invokespecial	Method scala/util/continuations/ControlContext$$anonfun$map$2."<init>":(Lscala/util/continuations/ControlContext;Lscala/Function1;)V
	aconst_null
	invokespecial	Method "<init>":(Lscala/Function2;Ljava/lang/Object;)V
	goto	l3 // areturn
	astore_2
	new	class scala/util/continuations/ControlContext
	dup
	new	class scala/util/continuations/ControlContext$$anonfun$map$1
	dup
	aload_0
	aload_2
	invokespecial	Method scala/util/continuations/ControlContext$$anonfun$map$1."<init>":(Lscala/util/continuations/ControlContext;Ljava/lang/Exception;)V
	aconst_null
	invokespecial	Method "<init>":(Lscala/Function2;Ljava/lang/Object;)V
	astore_3
l2	aload_3
l3	areturn
  Labels:
   	l1 = 29 // new
   	l2 = 68 // aload_3
   	l3 = 69 // areturn
  Exception table:
   from   to  target type
     7    29    49   Class java/lang/Exception

  LocalVariableTable: 
   Start  Length  Slot  Name   Signature
   0      70      0    this       Lscala/util/continuations/ControlContext;
   0      70      1    f$1       Lscala/Function1;
   7      22      3    exceptionResult1       Lscala/util/continuations/ControlContext;
   49      20      3    exceptionResult1       Lscala/util/continuations/ControlContext;

  Signature: length = 0x2
   00 34 

public final scala.util.continuations.ControlContext flatMap(scala.Function1);
  Signature: (Lscala/Function1;)Lscala/util/continuations/ControlContext;
  Code:
   Stack=6, Locals=4, Args_size=2
	aload_0
	getfield	Field fun:Lscala/Function2;
	ifnonnull	l1 // new
	aload_1
	aload_0
	getfield	Field x:Ljava/lang/Object;
	invokeinterface	InterfaceMethod scala/Function1.apply:(Ljava/lang/Object;)Ljava/lang/Object;
	checkcast	class scala/util/continuations/ControlContext
	astore_3
	goto	l2 // aload_3
l1	new	class scala/util/continuations/ControlContext
	dup
	new	class scala/util/continuations/ControlContext$$anonfun$flatMap$2
	dup
	aload_0
	aload_1
	invokespecial	Method scala/util/continuations/ControlContext$$anonfun$flatMap$2."<init>":(Lscala/util/continuations/ControlContext;Lscala/Function1;)V
	aconst_null
	invokespecial	Method "<init>":(Lscala/Function2;Ljava/lang/Object;)V
	goto	l3 // areturn
	astore_2
	new	class scala/util/continuations/ControlContext
	dup
	new	class scala/util/continuations/ControlContext$$anonfun$flatMap$1
	dup
	aload_0
	aload_2
	invokespecial	Method scala/util/continuations/ControlContext$$anonfun$flatMap$1."<init>":(Lscala/util/continuations/ControlContext;Ljava/lang/Exception;)V
	aconst_null
	invokespecial	Method "<init>":(Lscala/Function2;Ljava/lang/Object;)V
	astore_3
l2	aload_3
l3	areturn
  Labels:
   	l1 = 24 // new
   	l2 = 63 // aload_3
   	l3 = 64 // areturn
  Exception table:
   from   to  target type
     7    24    44   Class java/lang/Exception

  LocalVariableTable: 
   Start  Length  Slot  Name   Signature
   0      65      0    this       Lscala/util/continuations/ControlContext;
   0      65      1    f$2       Lscala/Function1;
   7      17      3    exceptionResult2       Lscala/util/continuations/ControlContext;
   44      20      3    exceptionResult2       Lscala/util/continuations/ControlContext;

  Signature: length = 0x2
   00 3E 

public final java.lang.Object foreach(scala.Function1);
  Signature: (Lscala/Function1;)Ljava/lang/Object;
  Code:
   Stack=5, Locals=2, Args_size=2
	aload_0
	aload_1
	new	class scala/util/continuations/ControlContext$$anonfun$foreach$1
	dup
	aload_0
	invokespecial	Method scala/util/continuations/ControlContext$$anonfun$foreach$1."<init>":(Lscala/util/continuations/ControlContext;)V
	invokevirtual	Method foreachFull:(Lscala/Function1;Lscala/Function1;)Ljava/lang/Object;
	areturn
  Labels:
  LocalVariableTable: 
   Start  Length  Slot  Name   Signature
   0      14      0    this       Lscala/util/continuations/ControlContext;
   0      14      1    f       Lscala/Function1;

  Signature: length = 0x2
   00 4B 

public java.lang.Object foreachFull(scala.Function1, scala.Function1);
  Signature: (Lscala/Function1;Lscala/Function1;)Ljava/lang/Object;
  Code:
   Stack=3, Locals=3, Args_size=3
	aload_0
	getfield	Field fun:Lscala/Function2;
	ifnonnull	l1 // aload_0
	aload_1
	aload_0
	getfield	Field x:Ljava/lang/Object;
	invokeinterface	InterfaceMethod scala/Function1.apply:(Ljava/lang/Object;)Ljava/lang/Object;
	goto	l2 // areturn
l1	aload_0
	getfield	Field fun:Lscala/Function2;
	aload_1
	aload_2
	invokeinterface	InterfaceMethod scala/Function2.apply:(Ljava/lang/Object;Ljava/lang/Object;)Ljava/lang/Object;
l2	areturn
  Labels:
   	l1 = 20 // aload_0
   	l2 = 31 // areturn
  LocalVariableTable: 
   Start  Length  Slot  Name   Signature
   0      32      0    this       Lscala/util/continuations/ControlContext;
   0      32      1    f       Lscala/Function1;
   0      32      2    g       Lscala/Function1;

  Signature: length = 0x2
   00 52 

public final boolean isTrivial();
  Signature: ()Z
  Code:
   Stack=1, Locals=1, Args_size=1
	aload_0
	getfield	Field fun:Lscala/Function2;
	ifnonnull	l1 // iconst_0
	iconst_1
	goto	l2 // ireturn
l1	iconst_0
l2	ireturn
  Labels:
   	l1 = 11 // iconst_0
   	l2 = 12 // ireturn

public final java.lang.Object getTrivialValue();
  Signature: ()Ljava/lang/Object;
  Code:
   Stack=1, Locals=1, Args_size=1
	aload_0
	invokevirtual	Method x:()Ljava/lang/Object;
	areturn
  Labels:
  Signature: length = 0x2
   00 15 

public final scala.util.continuations.ControlContext flatMapCatch(scala.PartialFunction);
  Signature: (Lscala/PartialFunction;)Lscala/util/continuations/ControlContext;
  Code:
   Stack=4, Locals=3, Args_size=2
	aload_0
	getfield	Field fun:Lscala/Function2;
	ifnonnull	l1 // new
	aload_0
	goto	l2 // areturn
l1	new	class scala/util/continuations/ControlContext$$anonfun$1
	dup
	aload_0
	aload_1
	invokespecial	Method scala/util/continuations/ControlContext$$anonfun$1."<init>":(Lscala/util/continuations/ControlContext;Lscala/PartialFunction;)V
	astore_2
	new	class scala/util/continuations/ControlContext
	dup
	aload_2
	aconst_null
	invokespecial	Method "<init>":(Lscala/Function2;Ljava/lang/Object;)V
l2	areturn
  Labels:
   	l1 = 11 // new
   	l2 = 30 // areturn
  LocalVariableTable: 
   Start  Length  Slot  Name   Signature
   0      31      0    this       Lscala/util/continuations/ControlContext;
   0      31      1    pf$1       Lscala/PartialFunction;
   21      9      2    fun1       Lscala/Function2;

  Signature: length = 0x2
   00 62 

public final scala.util.continuations.ControlContext mapFinally(scala.Function0);
  Signature: (Lscala/Function0;)Lscala/util/continuations/ControlContext;
  Code:
   Stack=6, Locals=5, Args_size=2
	aload_0
	getfield	Field fun:Lscala/Function2;
	ifnonnull	l1 // new
	aload_1
	invokeinterface	InterfaceMethod scala/Function0.apply:()Ljava/lang/Object;
	pop
	aload_0
	astore	4
	goto	l2 // aload
l1	new	class scala/util/continuations/ControlContext$$anonfun$3
	dup
	aload_0
	aload_1
	invokespecial	Method scala/util/continuations/ControlContext$$anonfun$3."<init>":(Lscala/util/continuations/ControlContext;Lscala/Function0;)V
	astore_2
	new	class scala/util/continuations/ControlContext
	dup
	aload_2
	aconst_null
	invokespecial	Method "<init>":(Lscala/Function2;Ljava/lang/Object;)V
	goto	l3 // areturn
	astore_3
	new	class scala/util/continuations/ControlContext
	dup
	new	class scala/util/continuations/ControlContext$$anonfun$mapFinally$1
	dup
	aload_0
	aload_3
	invokespecial	Method scala/util/continuations/ControlContext$$anonfun$mapFinally$1."<init>":(Lscala/util/continuations/ControlContext;Ljava/lang/Exception;)V
	aconst_null
	invokespecial	Method "<init>":(Lscala/Function2;Ljava/lang/Object;)V
	astore	4
l2	aload	4
l3	areturn
  Labels:
   	l1 = 20 // new
   	l2 = 62 // aload
   	l3 = 64 // areturn
  Exception table:
   from   to  target type
     7    20    42   Class java/lang/Exception

  LocalVariableTable: 
   Start  Length  Slot  Name   Signature
   0      65      0    this       Lscala/util/continuations/ControlContext;
   0      65      1    f$3       Lscala/Function0;
   30      9      2    fun1       Lscala/Function2;
   7      13      4    exceptionResult3       Lscala/util/continuations/ControlContext;
   42      22      4    exceptionResult3       Lscala/util/continuations/ControlContext;

  Signature: length = 0x2
   00 74 

public scala.util.continuations.ControlContext(scala.Function2, java.lang.Object);
  Signature: (Lscala/Function2;Ljava/lang/Object;)V
  Code:
   Stack=2, Locals=3, Args_size=3
	aload_0
	aload_1
	putfield	Field fun:Lscala/Function2;
	aload_0
	aload_2
	putfield	Field x:Ljava/lang/Object;
	aload_0
	invokespecial	Method java/lang/Object."<init>":()V
	return
  Labels:
  LocalVariableTable: 
   Start  Length  Slot  Name   Signature
   0      15      0    this       Lscala/util/continuations/ControlContext;
   0      15      1    fun       Lscala/Function2;
   0      15      2    x       Ljava/lang/Object;

  Signature: length = 0x2
   00 7A 

}

