Compiled from "ControlContext.scala"
public final class scala.util.continuations.ControlContext$$anonfun$1$$anonfun$2 extends scala.runtime.AbstractFunction1 implements java.io.Serializable
  SourceFile: "ControlContext.scala"
  Scala: length = 0x
   
  InnerClass: 
   public final $anonfun$1=class scala/util/continuations/ControlContext$$anonfun$1 of class scala/util/continuations/ControlContext
   public final $anonfun$2=class scala/util/continuations/ControlContext$$anonfun$1$$anonfun$2 of class scala/util/continuations/ControlContext$$anonfun$1
  minor version: 0
  major version: 49
  Constant pool:
Asciz	SourceFile;
Asciz	ControlContext.scala;
Asciz	<clinit>;
Asciz	()V;
Asciz	Code;
Asciz	serialVersionUID;
Asciz	J;
Asciz	scala/util/continuations/ControlContext$$anonfun$1$$anonfun$2;
class	scala/util/continuations/ControlContext$$anonfun$1$$anonfun$2
NameAndType	serialVersionUID:J
Field	scala/util/continuations/ControlContext$$anonfun$1$$anonfun$2.serialVersionUID:J
Asciz	$outer;
Asciz	Lscala/util/continuations/ControlContext$$anonfun$1;;
Asciz	ret1$1;
Asciz	Lscala/Function1;;
Asciz	thr1$1;
Asciz	apply;
Asciz	(Ljava/lang/Exception;)Ljava/lang/Object;;
Asciz	scala/runtime/BooleanRef;
class	scala/runtime/BooleanRef
Asciz	LineNumberTable;
Asciz	<init>;
Asciz	(Z)V;
NameAndType	"<init>":(Z)V
Method	scala/runtime/BooleanRef."<init>":(Z)V
NameAndType	$outer:Lscala/util/continuations/ControlContext$$anonfun$1;
Field	scala/util/continuations/ControlContext$$anonfun$1$$anonfun$2.$outer:Lscala/util/continuations/ControlContext$$anonfun$1;
Asciz	scala/util/continuations/ControlContext$$anonfun$1;
class	scala/util/continuations/ControlContext$$anonfun$1
Asciz	pf$1;
Asciz	Lscala/PartialFunction;;
NameAndType	pf$1:Lscala/PartialFunction;
Field	scala/util/continuations/ControlContext$$anonfun$1.pf$1:Lscala/PartialFunction;
Asciz	scala/PartialFunction;
class	scala/PartialFunction
Asciz	isDefinedAt;
Asciz	(Ljava/lang/Object;)Z;
NameAndType	isDefinedAt:(Ljava/lang/Object;)Z
InterfaceMethod	scala/PartialFunction.isDefinedAt:(Ljava/lang/Object;)Z
Asciz	scala/Function1;
class	scala/Function1
Asciz	(Ljava/lang/Object;)Ljava/lang/Object;;
NameAndType	apply:(Ljava/lang/Object;)Ljava/lang/Object;
InterfaceMethod	scala/Function1.apply:(Ljava/lang/Object;)Ljava/lang/Object;
Asciz	scala/util/continuations/ControlContext;
class	scala/util/continuations/ControlContext
Asciz	elem;
Asciz	Z;
NameAndType	elem:Z
Field	scala/runtime/BooleanRef.elem:Z
NameAndType	ret1$1:Lscala/Function1;
Field	scala/util/continuations/ControlContext$$anonfun$1$$anonfun$2.ret1$1:Lscala/Function1;
NameAndType	thr1$1:Lscala/Function1;
Field	scala/util/continuations/ControlContext$$anonfun$1$$anonfun$2.thr1$1:Lscala/Function1;
Asciz	fun;
Asciz	Lscala/Function2;;
NameAndType	fun:Lscala/Function2;
Field	scala/util/continuations/ControlContext.fun:Lscala/Function2;
Asciz	x;
Asciz	Ljava/lang/Object;;
NameAndType	x:Ljava/lang/Object;
Field	scala/util/continuations/ControlContext.x:Ljava/lang/Object;
Asciz	scala/Function2;
class	scala/Function2
Asciz	(Ljava/lang/Object;Ljava/lang/Object;)Ljava/lang/Object;;
NameAndType	apply:(Ljava/lang/Object;Ljava/lang/Object;)Ljava/lang/Object;
InterfaceMethod	scala/Function2.apply:(Ljava/lang/Object;Ljava/lang/Object;)Ljava/lang/Object;
Asciz	java/lang/Exception;
class	java/lang/Exception
Asciz	gd3$1;
Asciz	(Ljava/lang/Exception;Lscala/runtime/BooleanRef;)Z;
NameAndType	gd3$1:(Ljava/lang/Exception;Lscala/runtime/BooleanRef;)Z
Method	scala/util/continuations/ControlContext$$anonfun$1$$anonfun$2.gd3$1:(Ljava/lang/Exception;Lscala/runtime/BooleanRef;)Z
Asciz	this;
Asciz	Lscala/util/continuations/ControlContext$$anonfun$1$$anonfun$2;;
Asciz	t;
Asciz	Ljava/lang/Exception;;
Asciz	cc1;
Asciz	Lscala/util/continuations/ControlContext;;
Asciz	f0;
Asciz	g0;
Asciz	captureExceptions$1;
Asciz	Lscala/runtime/BooleanRef;;
Asciz	temp6;
Asciz	exceptionResult6;
Asciz	LocalVariableTable;
Asciz	(Ljava/lang/Exception;)TB1;;
Asciz	Signature;
NameAndType	apply:(Ljava/lang/Exception;)Ljava/lang/Object;
Method	scala/util/continuations/ControlContext$$anonfun$1$$anonfun$2.apply:(Ljava/lang/Exception;)Ljava/lang/Object;
Asciz	v1;
Asciz	(Lscala/util/continuations/ControlContext$$anonfun$1;Lscala/Function1;Lscala/Function1;)V;
Asciz	java/lang/NullPointerException;
class	java/lang/NullPointerException
NameAndType	"<init>":()V
Method	java/lang/NullPointerException."<init>":()V
Asciz	scala/runtime/AbstractFunction1;
class	scala/runtime/AbstractFunction1
Method	scala/runtime/AbstractFunction1."<init>":()V
Asciz	(Lscala/util/continuations/ControlContext<TA;TB;TC;>.$anonfun$1;)V;
Asciz	Scala;
Asciz	InnerClasses;
Asciz	$anonfun$1;
Asciz	$anonfun$2;
Asciz	java/io/Serializable;
class	java/io/Serializable

{
public static final long serialVersionUID;
  Signature: J

private final scala.util.continuations.ControlContext$$anonfun$1 $outer;
  Signature: Lscala/util/continuations/ControlContext$$anonfun$1;

private final scala.Function1 ret1$1;
  Signature: Lscala/Function1;

private final scala.Function1 thr1$1;
  Signature: Lscala/Function1;

public static {};
  Signature: ()V
  Code:
   Stack=2, Locals=0, Args_size=0
	lconst_0
	putstatic	Field serialVersionUID:J
	return
  Labels:

public final java.lang.Object apply(java.lang.Exception);
  Signature: (Ljava/lang/Exception;)Ljava/lang/Object;
  Code:
   Stack=3, Locals=9, Args_size=2
	new	class scala/runtime/BooleanRef
	dup
	iconst_1
	invokespecial	Method scala/runtime/BooleanRef."<init>":(Z)V
	astore	5
	aload_0
	getfield	Field $outer:Lscala/util/continuations/ControlContext$$anonfun$1;
	getfield	Field scala/util/continuations/ControlContext$$anonfun$1.pf$1:Lscala/PartialFunction;
	aload_1
	invokeinterface	InterfaceMethod scala/PartialFunction.isDefinedAt:(Ljava/lang/Object;)Z
	ifeq	l1 // aload
	aload_0
	getfield	Field $outer:Lscala/util/continuations/ControlContext$$anonfun$1;
	getfield	Field scala/util/continuations/ControlContext$$anonfun$1.pf$1:Lscala/PartialFunction;
	aload_1
	invokeinterface	InterfaceMethod scala/Function1.apply:(Ljava/lang/Object;)Ljava/lang/Object;
	checkcast	class scala/util/continuations/ControlContext
	astore_2
	aload	5
	iconst_0
	putfield	Field scala/runtime/BooleanRef.elem:Z
	aload_0
	getfield	Field ret1$1:Lscala/Function1;
	aload_0
	getfield	Field thr1$1:Lscala/Function1;
	astore	4
	astore_3
	aload_2
	getfield	Field scala/util/continuations/ControlContext.fun:Lscala/Function2;
	ifnonnull	l2 // aload_2
	aload_3
	aload_2
	getfield	Field scala/util/continuations/ControlContext.x:Ljava/lang/Object;
	invokeinterface	InterfaceMethod scala/Function1.apply:(Ljava/lang/Object;)Ljava/lang/Object;
	goto	l3 // goto
l2	aload_2
	getfield	Field scala/util/continuations/ControlContext.fun:Lscala/Function2;
	aload_3
	aload	4
	invokeinterface	InterfaceMethod scala/Function2.apply:(Ljava/lang/Object;Ljava/lang/Object;)Ljava/lang/Object;
l3	goto	l4 // astore
l1	aload	5
	iconst_0
	putfield	Field scala/runtime/BooleanRef.elem:Z
	aload_0
	getfield	Field thr1$1:Lscala/Function1;
	aload_1
	invokeinterface	InterfaceMethod scala/Function1.apply:(Ljava/lang/Object;)Ljava/lang/Object;
l4	astore	7
	goto	l5 // aload
	astore	8
	aload	8
	instanceof	class java/lang/Exception
	ifeq	l6 // aload
	aload	8
	checkcast	class java/lang/Exception
	astore	6
	aload_0
	aload	6
	aload	5
	invokespecial	Method gd3$1:(Ljava/lang/Exception;Lscala/runtime/BooleanRef;)Z
	ifeq	l7 // aload
	aload_0
	getfield	Field thr1$1:Lscala/Function1;
	aload	6
	invokeinterface	InterfaceMethod scala/Function1.apply:(Ljava/lang/Object;)Ljava/lang/Object;
	astore	7
l5	aload	7
	areturn
l7	aload	8
	athrow
l6	aload	8
	athrow
  Labels:
   	l2 = 80 // aload_2
   	l3 = 92 // goto
   	l1 = 95 // aload
   	l4 = 111 // astore
   	l5 = 157 // aload
   	l7 = 160 // aload
   	l6 = 163 // aload
  Exception table:
   from   to  target type
    10   116   116   any
  LocalVariableTable: 
   Start  Length  Slot  Name   Signature
   0      166      0    this       Lscala/util/continuations/ControlContext$$anonfun$1$$anonfun$2;
   0      166      1    t       Ljava/lang/Exception;
   43      49      2    cc1       Lscala/util/continuations/ControlContext;
   60      32      3    f0       Lscala/Function1;
   60      32      4    g0       Lscala/Function1;
   10      149      5    captureExceptions$1       Lscala/runtime/BooleanRef;
   160      6      5    captureExceptions$1       Lscala/runtime/BooleanRef;
   133      24      6    temp6       Ljava/lang/Exception;
   160      3      6    temp6       Ljava/lang/Exception;
   10      149      7    exceptionResult6       Ljava/lang/Object;
   160      6      7    exceptionResult6       Ljava/lang/Object;

  Signature: length = 0x2
   00 57 

public final java.lang.Object apply(java.lang.Object);
  Signature: (Ljava/lang/Object;)Ljava/lang/Object;
  Code:
   Stack=2, Locals=2, Args_size=2
	aload_0
	aload_1
	checkcast	class java/lang/Exception
	invokevirtual	Method apply:(Ljava/lang/Exception;)Ljava/lang/Object;
	areturn
  Labels:
  LocalVariableTable: 
   Start  Length  Slot  Name   Signature
   0      9      0    this       Lscala/util/continuations/ControlContext$$anonfun$1$$anonfun$2;
   0      9      1    v1       Ljava/lang/Object;


private final boolean gd3$1(java.lang.Exception, scala.runtime.BooleanRef);
  Signature: (Ljava/lang/Exception;Lscala/runtime/BooleanRef;)Z
  Code:
   Stack=1, Locals=3, Args_size=3
	aload_2
	getfield	Field scala/runtime/BooleanRef.elem:Z
	ireturn
  Labels:

public scala.util.continuations.ControlContext$$anonfun$1$$anonfun$2(scala.util.continuations.ControlContext$$anonfun$1, scala.Function1, scala.Function1);
  Signature: (Lscala/util/continuations/ControlContext$$anonfun$1;Lscala/Function1;Lscala/Function1;)V
  Code:
   Stack=2, Locals=4, Args_size=4
	aload_1
	ifnonnull	l1 // aload_0
	new	class java/lang/NullPointerException
	dup
	invokespecial	Method java/lang/NullPointerException."<init>":()V
	athrow
l1	aload_0
	aload_1
	putfield	Field $outer:Lscala/util/continuations/ControlContext$$anonfun$1;
	aload_0
	aload_2
	putfield	Field ret1$1:Lscala/Function1;
	aload_0
	aload_3
	putfield	Field thr1$1:Lscala/Function1;
	aload_0
	invokespecial	Method scala/runtime/AbstractFunction1."<init>":()V
	return
  Labels:
   	l1 = 12 // aload_0
  LocalVariableTable: 
   Start  Length  Slot  Name   Signature
   0      32      0    this       Lscala/util/continuations/ControlContext$$anonfun$1$$anonfun$2;
   0      32      1    $outer       Lscala/util/continuations/ControlContext$$anonfun$1;

  Signature: length = 0x2
   00 64 

}

