Compiled from "ControlContext.scala"
public final class scala.util.continuations.ControlContext$$anonfun$map$1 extends scala.runtime.AbstractFunction2 implements java.io.Serializable
  SourceFile: "ControlContext.scala"
  Scala: length = 0x
   
  InnerClass: 
   public final $anonfun$map$1=class scala/util/continuations/ControlContext$$anonfun$map$1 of class scala/util/continuations/ControlContext
   public final $anonfun$apply$1=class scala/util/continuations/ControlContext$$anonfun$map$1$$anonfun$apply$1 of class scala/util/continuations/ControlContext$$anonfun$map$1
  minor version: 0
  major version: 49
  Constant pool:
Asciz	SourceFile;
Asciz	ControlContext.scala;
Asciz	<clinit>;
Asciz	()V;
Asciz	Code;
Asciz	serialVersionUID;
Asciz	J;
Asciz	scala/util/continuations/ControlContext$$anonfun$map$1;
class	scala/util/continuations/ControlContext$$anonfun$map$1
NameAndType	serialVersionUID:J
Field	scala/util/continuations/ControlContext$$anonfun$map$1.serialVersionUID:J
Asciz	f$1;
Asciz	Lscala/Function1;;
Asciz	$outer;
Asciz	Lscala/util/continuations/ControlContext;;
Asciz	apply;
Asciz	(Lscala/Function1;Lscala/Function1;)Ljava/lang/Object;;
Asciz	LineNumberTable;
NameAndType	$outer:Lscala/util/continuations/ControlContext;
Field	scala/util/continuations/ControlContext$$anonfun$map$1.$outer:Lscala/util/continuations/ControlContext;
Asciz	scala/util/continuations/ControlContext;
class	scala/util/continuations/ControlContext
Asciz	fun;
Asciz	()Lscala/Function2;;
NameAndType	fun:()Lscala/Function2;
Method	scala/util/continuations/ControlContext.fun:()Lscala/Function2;
Asciz	scala/util/continuations/ControlContext$$anonfun$map$1$$anonfun$apply$1;
class	scala/util/continuations/ControlContext$$anonfun$map$1$$anonfun$apply$1
Asciz	<init>;
Asciz	(Lscala/util/continuations/ControlContext$$anonfun$map$1;Lscala/Function1;Lscala/Function1;)V;
NameAndType	"<init>":(Lscala/util/continuations/ControlContext$$anonfun$map$1;Lscala/Function1;Lscala/Function1;)V
Method	scala/util/continuations/ControlContext$$anonfun$map$1$$anonfun$apply$1."<init>":(Lscala/util/continuations/ControlContext$$anonfun$map$1;Lscala/Function1;Lscala/Function1;)V
Asciz	scala/Function2;
class	scala/Function2
Asciz	(Ljava/lang/Object;Ljava/lang/Object;)Ljava/lang/Object;;
NameAndType	apply:(Ljava/lang/Object;Ljava/lang/Object;)Ljava/lang/Object;
InterfaceMethod	scala/Function2.apply:(Ljava/lang/Object;Ljava/lang/Object;)Ljava/lang/Object;
Asciz	this;
Asciz	Lscala/util/continuations/ControlContext$$anonfun$map$1;;
Asciz	k$1;
Asciz	thr$1;
Asciz	LocalVariableTable;
Asciz	(Lscala/Function1<TA1;TB;>;Lscala/Function1<Ljava/lang/Throwable;TB;>;)TC;;
Asciz	Signature;
Asciz	scala/Function1;
class	scala/Function1
NameAndType	apply:(Lscala/Function1;Lscala/Function1;)Ljava/lang/Object;
Method	scala/util/continuations/ControlContext$$anonfun$map$1.apply:(Lscala/Function1;Lscala/Function1;)Ljava/lang/Object;
Asciz	v1;
Asciz	Ljava/lang/Object;;
Asciz	v2;
Asciz	(Lscala/util/continuations/ControlContext;Lscala/Function1;)V;
Asciz	java/lang/NullPointerException;
class	java/lang/NullPointerException
NameAndType	"<init>":()V
Method	java/lang/NullPointerException."<init>":()V
NameAndType	f$1:Lscala/Function1;
Field	scala/util/continuations/ControlContext$$anonfun$map$1.f$1:Lscala/Function1;
Asciz	scala/runtime/AbstractFunction2;
class	scala/runtime/AbstractFunction2
Method	scala/runtime/AbstractFunction2."<init>":()V
Asciz	(Lscala/util/continuations/ControlContext<TA;TB;TC;>;)V;
Asciz	Scala;
Asciz	InnerClasses;
Asciz	$anonfun$map$1;
Asciz	$anonfun$apply$1;
Asciz	java/io/Serializable;
class	java/io/Serializable

{
public static final long serialVersionUID;
  Signature: J

public final scala.Function1 f$1;
  Signature: Lscala/Function1;

public final scala.util.continuations.ControlContext $outer;
  Signature: Lscala/util/continuations/ControlContext;

public static {};
  Signature: ()V
  Code:
   Stack=2, Locals=0, Args_size=0
	lconst_0
	putstatic	Field serialVersionUID:J
	return
  Labels:

public final java.lang.Object apply(scala.Function1, scala.Function1);
  Signature: (Lscala/Function1;Lscala/Function1;)Ljava/lang/Object;
  Code:
   Stack=6, Locals=3, Args_size=3
	aload_0
	getfield	Field $outer:Lscala/util/continuations/ControlContext;
	invokevirtual	Method scala/util/continuations/ControlContext.fun:()Lscala/Function2;
	new	class scala/util/continuations/ControlContext$$anonfun$map$1$$anonfun$apply$1
	dup
	aload_0
	aload_1
	aload_2
	invokespecial	Method scala/util/continuations/ControlContext$$anonfun$map$1$$anonfun$apply$1."<init>":(Lscala/util/continuations/ControlContext$$anonfun$map$1;Lscala/Function1;Lscala/Function1;)V
	aload_2
	invokeinterface	InterfaceMethod scala/Function2.apply:(Ljava/lang/Object;Ljava/lang/Object;)Ljava/lang/Object;
	areturn
  Labels:
  LocalVariableTable: 
   Start  Length  Slot  Name   Signature
   0      24      0    this       Lscala/util/continuations/ControlContext$$anonfun$map$1;
   0      24      1    k$1       Lscala/Function1;
   0      24      2    thr$1       Lscala/Function1;

  Signature: length = 0x2
   00 2B 

public final java.lang.Object apply(java.lang.Object, java.lang.Object);
  Signature: (Ljava/lang/Object;Ljava/lang/Object;)Ljava/lang/Object;
  Code:
   Stack=3, Locals=3, Args_size=3
	aload_0
	aload_1
	checkcast	class scala/Function1
	aload_2
	checkcast	class scala/Function1
	invokevirtual	Method apply:(Lscala/Function1;Lscala/Function1;)Ljava/lang/Object;
	areturn
  Labels:
  LocalVariableTable: 
   Start  Length  Slot  Name   Signature
   0      13      0    this       Lscala/util/continuations/ControlContext$$anonfun$map$1;
   0      13      1    v1       Ljava/lang/Object;
   0      13      2    v2       Ljava/lang/Object;


public scala.util.continuations.ControlContext$$anonfun$map$1(scala.util.continuations.ControlContext, scala.Function1);
  Signature: (Lscala/util/continuations/ControlContext;Lscala/Function1;)V
  Code:
   Stack=2, Locals=3, Args_size=3
	aload_1
	ifnonnull	l1 // aload_0
	new	class java/lang/NullPointerException
	dup
	invokespecial	Method java/lang/NullPointerException."<init>":()V
	athrow
l1	aload_0
	aload_1
	putfield	Field $outer:Lscala/util/continuations/ControlContext;
	aload_0
	aload_2
	putfield	Field f$1:Lscala/Function1;
	aload_0
	invokespecial	Method scala/runtime/AbstractFunction2."<init>":()V
	return
  Labels:
   	l1 = 12 // aload_0
  LocalVariableTable: 
   Start  Length  Slot  Name   Signature
   0      27      0    this       Lscala/util/continuations/ControlContext$$anonfun$map$1;
   0      27      1    $outer       Lscala/util/continuations/ControlContext;

  Signature: length = 0x2
   00 3E 

}

