Compiled from "ControlContext.scala"
public final class scala.util.continuations.ControlContext$$anonfun$flatMap$1 extends scala.runtime.AbstractFunction2 implements java.io.Serializable
  SourceFile: "ControlContext.scala"
  Scala: length = 0x
   
  InnerClass: 
   public final $anonfun$flatMap$1=class scala/util/continuations/ControlContext$$anonfun$flatMap$1 of class scala/util/continuations/ControlContext
  minor version: 0
  major version: 49
  Constant pool:
Asciz	SourceFile;
Asciz	ControlContext.scala;
Asciz	<clinit>;
Asciz	()V;
Asciz	Code;
Asciz	serialVersionUID;
Asciz	J;
Asciz	scala/util/continuations/ControlContext$$anonfun$flatMap$1;
class	scala/util/continuations/ControlContext$$anonfun$flatMap$1
NameAndType	serialVersionUID:J
Field	scala/util/continuations/ControlContext$$anonfun$flatMap$1.serialVersionUID:J
Asciz	ex$7;
Asciz	Ljava/lang/Exception;;
Asciz	apply;
Asciz	(Lscala/Function1;Lscala/Function1;)Ljava/lang/Object;;
Asciz	LineNumberTable;
NameAndType	ex$7:Ljava/lang/Exception;
Field	scala/util/continuations/ControlContext$$anonfun$flatMap$1.ex$7:Ljava/lang/Exception;
Asciz	scala/Function1;
class	scala/Function1
Asciz	(Ljava/lang/Object;)Ljava/lang/Object;;
NameAndType	apply:(Ljava/lang/Object;)Ljava/lang/Object;
InterfaceMethod	scala/Function1.apply:(Ljava/lang/Object;)Ljava/lang/Object;
Asciz	this;
Asciz	Lscala/util/continuations/ControlContext$$anonfun$flatMap$1;;
Asciz	k;
Asciz	Lscala/Function1;;
Asciz	thr;
Asciz	LocalVariableTable;
Asciz	(Lscala/Function1<TA1;TB1;>;Lscala/Function1<Ljava/lang/Exception;TB1;>;)TC;;
Asciz	Signature;
Asciz	(Ljava/lang/Object;Ljava/lang/Object;)Ljava/lang/Object;;
NameAndType	apply:(Lscala/Function1;Lscala/Function1;)Ljava/lang/Object;
Method	scala/util/continuations/ControlContext$$anonfun$flatMap$1.apply:(Lscala/Function1;Lscala/Function1;)Ljava/lang/Object;
Asciz	v1;
Asciz	Ljava/lang/Object;;
Asciz	v2;
Asciz	<init>;
Asciz	(Lscala/util/continuations/ControlContext;Ljava/lang/Exception;)V;
Asciz	scala/runtime/AbstractFunction2;
class	scala/runtime/AbstractFunction2
NameAndType	"<init>":()V
Method	scala/runtime/AbstractFunction2."<init>":()V
Asciz	$outer;
Asciz	Lscala/util/continuations/ControlContext;;
Asciz	(Lscala/util/continuations/ControlContext<TA;TB;TC;>;)V;
Asciz	Scala;
Asciz	InnerClasses;
Asciz	scala/util/continuations/ControlContext;
class	scala/util/continuations/ControlContext
Asciz	$anonfun$flatMap$1;
Asciz	java/io/Serializable;
class	java/io/Serializable

{
public static final long serialVersionUID;
  Signature: J

public final java.lang.Exception ex$7;
  Signature: Ljava/lang/Exception;

public static {};
  Signature: ()V
  Code:
   Stack=2, Locals=0, Args_size=0
	lconst_0
	putstatic	Field serialVersionUID:J
	return
  Labels:

public final java.lang.Object apply(scala.Function1, scala.Function1);
  Signature: (Lscala/Function1;Lscala/Function1;)Ljava/lang/Object;
  Code:
   Stack=2, Locals=3, Args_size=3
	aload_2
	aload_0
	getfield	Field ex$7:Ljava/lang/Exception;
	invokeinterface	InterfaceMethod scala/Function1.apply:(Ljava/lang/Object;)Ljava/lang/Object;
	areturn
  Labels:
  LocalVariableTable: 
   Start  Length  Slot  Name   Signature
   0      11      0    this       Lscala/util/continuations/ControlContext$$anonfun$flatMap$1;
   0      11      1    k       Lscala/Function1;
   0      11      2    thr       Lscala/Function1;

  Signature: length = 0x2
   00 1E 

public final java.lang.Object apply(java.lang.Object, java.lang.Object);
  Signature: (Ljava/lang/Object;Ljava/lang/Object;)Ljava/lang/Object;
  Code:
   Stack=3, Locals=3, Args_size=3
	aload_0
	aload_1
	checkcast	class scala/Function1
	aload_2
	checkcast	class scala/Function1
	invokevirtual	Method apply:(Lscala/Function1;Lscala/Function1;)Ljava/lang/Object;
	areturn
  Labels:
  LocalVariableTable: 
   Start  Length  Slot  Name   Signature
   0      13      0    this       Lscala/util/continuations/ControlContext$$anonfun$flatMap$1;
   0      13      1    v1       Ljava/lang/Object;
   0      13      2    v2       Ljava/lang/Object;


public scala.util.continuations.ControlContext$$anonfun$flatMap$1(scala.util.continuations.ControlContext, java.lang.Exception);
  Signature: (Lscala/util/continuations/ControlContext;Ljava/lang/Exception;)V
  Code:
   Stack=2, Locals=3, Args_size=3
	aload_0
	aload_2
	putfield	Field ex$7:Ljava/lang/Exception;
	aload_0
	invokespecial	Method scala/runtime/AbstractFunction2."<init>":()V
	return
  Labels:
  LocalVariableTable: 
   Start  Length  Slot  Name   Signature
   0      10      0    this       Lscala/util/continuations/ControlContext$$anonfun$flatMap$1;
   0      10      1    $outer       Lscala/util/continuations/ControlContext;

  Signature: length = 0x2
   00 2E 

}

