Compiled from "package.scala"
public final class scala.util.continuations.package$ extends java.lang.Object implements scala.ScalaObject
  SourceFile: "package.scala"
  Scala: length = 0x
   
  InnerClass: 
   public final $anonfun$run$1=class scala/util/continuations/package$$anonfun$run$1 of class scala/util/continuations/package
   public final $anonfun$reset$1=class scala/util/continuations/package$$anonfun$reset$1 of class scala/util/continuations/package
   public final $anonfun$shiftR$1=class scala/util/continuations/package$$anonfun$shiftR$1 of class scala/util/continuations/package
   public final $anonfun$foreach$1=class scala/util/continuations/ControlContext$$anonfun$foreach$1 of class scala/util/continuations/ControlContext
  minor version: 0
  major version: 49
  Constant pool:
Asciz	SourceFile;
Asciz	package.scala;
Asciz	MODULE$;
Asciz	Lscala/util/continuations/package$;;
Asciz	<clinit>;
Asciz	()V;
Asciz	Code;
Asciz	scala/util/continuations/package$;
class	scala/util/continuations/package$
Asciz	<init>;
NameAndType	"<init>":()V
Method	scala/util/continuations/package$."<init>":()V
Asciz	shift;
Asciz	(Lscala/Function1;)Lscala/util/continuations/ControlContext;;
Asciz	java/lang/NoSuchMethodException;
class	java/lang/NoSuchMethodException
Asciz	LineNumberTable;
Asciz	this code has to be compiled with the Scala continuations plugin enabled;
String	this code has to be compiled with the Scala continuations plugin enabled
Asciz	(Ljava/lang/String;)V;
NameAndType	"<init>":(Ljava/lang/String;)V
Method	java/lang/NoSuchMethodException."<init>":(Ljava/lang/String;)V
Asciz	this;
Asciz	fun;
Asciz	Lscala/Function1;;
Asciz	LocalVariableTable;
Asciz	<A:Ljava/lang/Object;B:Ljava/lang/Object;C:Ljava/lang/Object;>(Lscala/Function1<Lscala/Function1<TA;TB;>;TC;>;)Lscala/util/continuations/ControlContext<TA;TB;TC;>;;
Asciz	Signature;
Asciz	reset;
Asciz	(Lscala/Function0;)Ljava/lang/Object;;
Asciz	scala/Function0;
class	scala/Function0
Asciz	apply;
Asciz	()Ljava/lang/Object;;
NameAndType	apply:()Ljava/lang/Object;
InterfaceMethod	scala/Function0.apply:()Ljava/lang/Object;
Asciz	scala/util/continuations/ControlContext;
class	scala/util/continuations/ControlContext
Asciz	isTrivial;
Asciz	()Z;
NameAndType	isTrivial:()Z
Method	scala/util/continuations/ControlContext.isTrivial:()Z
Asciz	x;
Asciz	Ljava/lang/Object;;
NameAndType	x:Ljava/lang/Object;
Field	scala/util/continuations/ControlContext.x:Ljava/lang/Object;
Asciz	scala/util/continuations/package$$anonfun$reset$1;
class	scala/util/continuations/package$$anonfun$reset$1
Method	scala/util/continuations/package$$anonfun$reset$1."<init>":()V
Asciz	scala/util/continuations/ControlContext$$anonfun$foreach$1;
class	scala/util/continuations/ControlContext$$anonfun$foreach$1
Asciz	(Lscala/util/continuations/ControlContext;)V;
NameAndType	"<init>":(Lscala/util/continuations/ControlContext;)V
Method	scala/util/continuations/ControlContext$$anonfun$foreach$1."<init>":(Lscala/util/continuations/ControlContext;)V
Asciz	Lscala/Function2;;
NameAndType	fun:Lscala/Function2;
Field	scala/util/continuations/ControlContext.fun:Lscala/Function2;
Asciz	scala/Function2;
class	scala/Function2
Asciz	(Ljava/lang/Object;Ljava/lang/Object;)Ljava/lang/Object;;
NameAndType	apply:(Ljava/lang/Object;Ljava/lang/Object;)Ljava/lang/Object;
InterfaceMethod	scala/Function2.apply:(Ljava/lang/Object;Ljava/lang/Object;)Ljava/lang/Object;
Asciz	ctx;
Asciz	Lscala/Function0;;
Asciz	ctxR;
Asciz	Lscala/util/continuations/ControlContext;;
Asciz	f0;
Asciz	g0;
Asciz	<A:Ljava/lang/Object;C:Ljava/lang/Object;>(Lscala/Function0<Lscala/util/continuations/ControlContext<TA;TA;TC;>;>;)TC;;
Asciz	reset0;
NameAndType	reset:(Lscala/Function0;)Ljava/lang/Object;
Method	scala/util/continuations/package$.reset:(Lscala/Function0;)Ljava/lang/Object;
Asciz	<A:Ljava/lang/Object;>(Lscala/Function0<Lscala/util/continuations/ControlContext<TA;TA;TA;>;>;)TA;;
Asciz	run;
Asciz	scala/util/continuations/package$$anonfun$run$1;
class	scala/util/continuations/package$$anonfun$run$1
Method	scala/util/continuations/package$$anonfun$run$1."<init>":()V
Asciz	scala/runtime/BoxedUnit;
class	scala/runtime/BoxedUnit
Asciz	UNIT;
Asciz	Lscala/runtime/BoxedUnit;;
NameAndType	UNIT:Lscala/runtime/BoxedUnit;
Field	scala/runtime/BoxedUnit.UNIT:Lscala/runtime/BoxedUnit;
Asciz	<A:Ljava/lang/Object;>(Lscala/Function0<Lscala/util/continuations/ControlContext<Ljava/lang/Object;Ljava/lang/Object;TA;>;>;)TA;;
Asciz	shiftUnit0;
Asciz	(Ljava/lang/Object;)Lscala/util/continuations/ControlContext;;
Asciz	shiftUnitR;
NameAndType	shiftUnitR:(Ljava/lang/Object;)Lscala/util/continuations/ControlContext;
Method	scala/util/continuations/package$.shiftUnitR:(Ljava/lang/Object;)Lscala/util/continuations/ControlContext;
Asciz	<A:Ljava/lang/Object;B:Ljava/lang/Object;>(TA;)Lscala/util/continuations/ControlContext<TA;TB;TB;>;;
Asciz	shiftUnit;
Asciz	<A:Ljava/lang/Object;B:Ljava/lang/Object;C:Ljava/lang/Object;>(TA;)Lscala/util/continuations/ControlContext<TA;TB;TC;>;;
Asciz	reify;
Asciz	(Lscala/Function0;)Lscala/util/continuations/ControlContext;;
Asciz	<A:Ljava/lang/Object;B:Ljava/lang/Object;C:Ljava/lang/Object;>(Lscala/Function0<Lscala/util/continuations/ControlContext<TA;TB;TC;>;>;)Lscala/util/continuations/ControlContext<TA;TB;TC;>;;
Asciz	(Lscala/Function2;Ljava/lang/Object;)V;
NameAndType	"<init>":(Lscala/Function2;Ljava/lang/Object;)V
Method	scala/util/continuations/ControlContext."<init>":(Lscala/Function2;Ljava/lang/Object;)V
Asciz	shiftR;
Asciz	scala/util/continuations/package$$anonfun$shiftR$1;
class	scala/util/continuations/package$$anonfun$shiftR$1
Asciz	(Lscala/Function1;)V;
NameAndType	"<init>":(Lscala/Function1;)V
Method	scala/util/continuations/package$$anonfun$shiftR$1."<init>":(Lscala/Function1;)V
Asciz	fun$1;
Asciz	reifyR;
Asciz	java/lang/Object;
class	java/lang/Object
Method	java/lang/Object."<init>":()V
NameAndType	MODULE$:Lscala/util/continuations/package$;
Field	scala/util/continuations/package$.MODULE$:Lscala/util/continuations/package$;
Asciz	Scala;
Asciz	InnerClasses;
Asciz	scala/util/continuations/package;
class	scala/util/continuations/package
Asciz	$anonfun$run$1;
Asciz	$anonfun$reset$1;
Asciz	$anonfun$shiftR$1;
Asciz	$anonfun$foreach$1;
Asciz	scala/ScalaObject;
class	scala/ScalaObject

{
public static final scala.util.continuations.package$ MODULE$;
  Signature: Lscala/util/continuations/package$;

public static {};
  Signature: ()V
  Code:
   Stack=1, Locals=0, Args_size=0
	new	class scala/util/continuations/package$
	invokespecial	Method "<init>":()V
	return
  Labels:

public scala.util.continuations.ControlContext shift(scala.Function1);
  Signature: (Lscala/Function1;)Lscala/util/continuations/ControlContext;
  Code:
   Stack=3, Locals=2, Args_size=2
	new	class java/lang/NoSuchMethodException
	dup
	ldc	String this code has to be compiled with the Scala continuations plugin enabled
	invokespecial	Method java/lang/NoSuchMethodException."<init>":(Ljava/lang/String;)V
	athrow
  Labels:
  LocalVariableTable: 
   Start  Length  Slot  Name   Signature
   0      10      0    this       Lscala/util/continuations/package$;
   0      10      1    fun       Lscala/Function1;

  Signature: length = 0x2
   00 1B 

public java.lang.Object reset(scala.Function0);
  Signature: (Lscala/Function0;)Ljava/lang/Object;
  Code:
   Stack=3, Locals=6, Args_size=2
	aload_1
	invokeinterface	InterfaceMethod scala/Function0.apply:()Ljava/lang/Object;
	checkcast	class scala/util/continuations/ControlContext
	astore_3
	aload_3
	invokevirtual	Method scala/util/continuations/ControlContext.isTrivial:()Z
	ifeq	l1 // new
	aload_3
	getfield	Field scala/util/continuations/ControlContext.x:Ljava/lang/Object;
	goto	l2 // areturn
l1	new	class scala/util/continuations/package$$anonfun$reset$1
	dup
	invokespecial	Method scala/util/continuations/package$$anonfun$reset$1."<init>":()V
	astore	4
	new	class scala/util/continuations/ControlContext$$anonfun$foreach$1
	dup
	aload_3
	invokespecial	Method scala/util/continuations/ControlContext$$anonfun$foreach$1."<init>":(Lscala/util/continuations/ControlContext;)V
	astore	5
	aload_3
	getfield	Field scala/util/continuations/ControlContext.fun:Lscala/Function2;
	ifnonnull	l3 // aload_3
	aload_3
	getfield	Field scala/util/continuations/ControlContext.x:Ljava/lang/Object;
	astore_2
	aload_2
	goto	l2 // areturn
l3	aload_3
	getfield	Field scala/util/continuations/ControlContext.fun:Lscala/Function2;
	aload	4
	aload	5
	invokeinterface	InterfaceMethod scala/Function2.apply:(Ljava/lang/Object;Ljava/lang/Object;)Ljava/lang/Object;
l2	areturn
  Labels:
   	l1 = 24 // new
   	l3 = 59 // aload_3
   	l2 = 72 // areturn
  LocalVariableTable: 
   Start  Length  Slot  Name   Signature
   0      73      0    this       Lscala/util/continuations/package$;
   0      73      1    ctx       Lscala/Function0;
   10      63      3    ctxR       Lscala/util/continuations/ControlContext;
   50      22      4    f0       Lscala/Function1;
   50      22      5    g0       Lscala/Function1;

  Signature: length = 0x2
   00 45 

public java.lang.Object reset0(scala.Function0);
  Signature: (Lscala/Function0;)Ljava/lang/Object;
  Code:
   Stack=2, Locals=2, Args_size=2
	aload_0
	aload_1
	invokevirtual	Method reset:(Lscala/Function0;)Ljava/lang/Object;
	areturn
  Labels:
  LocalVariableTable: 
   Start  Length  Slot  Name   Signature
   0      6      0    this       Lscala/util/continuations/package$;
   0      6      1    ctx       Lscala/Function0;

  Signature: length = 0x2
   00 49 

public java.lang.Object run(scala.Function0);
  Signature: (Lscala/Function0;)Ljava/lang/Object;
  Code:
   Stack=3, Locals=5, Args_size=2
	aload_1
	invokeinterface	InterfaceMethod scala/Function0.apply:()Ljava/lang/Object;
	checkcast	class scala/util/continuations/ControlContext
	astore_2
	aload_2
	invokevirtual	Method scala/util/continuations/ControlContext.isTrivial:()Z
	ifeq	l1 // new
	aload_2
	getfield	Field scala/util/continuations/ControlContext.x:Ljava/lang/Object;
	goto	l2 // areturn
l1	new	class scala/util/continuations/package$$anonfun$run$1
	dup
	invokespecial	Method scala/util/continuations/package$$anonfun$run$1."<init>":()V
	astore_3
	new	class scala/util/continuations/ControlContext$$anonfun$foreach$1
	dup
	aload_2
	invokespecial	Method scala/util/continuations/ControlContext$$anonfun$foreach$1."<init>":(Lscala/util/continuations/ControlContext;)V
	astore	4
	aload_2
	getfield	Field scala/util/continuations/ControlContext.fun:Lscala/Function2;
	ifnonnull	l3 // aload_2
	getstatic	Field scala/runtime/BoxedUnit.UNIT:Lscala/runtime/BoxedUnit;
	goto	l2 // areturn
l3	aload_2
	getfield	Field scala/util/continuations/ControlContext.fun:Lscala/Function2;
	aload_3
	aload	4
	invokeinterface	InterfaceMethod scala/Function2.apply:(Ljava/lang/Object;Ljava/lang/Object;)Ljava/lang/Object;
l2	areturn
  Labels:
   	l1 = 24 // new
   	l3 = 55 // aload_2
   	l2 = 67 // areturn
  LocalVariableTable: 
   Start  Length  Slot  Name   Signature
   0      68      0    this       Lscala/util/continuations/package$;
   0      68      1    ctx       Lscala/Function0;
   10      58      2    ctxR       Lscala/util/continuations/ControlContext;
   49      18      3    f0       Lscala/Function1;
   49      18      4    g0       Lscala/Function1;

  Signature: length = 0x2
   00 54 

public scala.util.continuations.ControlContext shiftUnit0(java.lang.Object);
  Signature: (Ljava/lang/Object;)Lscala/util/continuations/ControlContext;
  Code:
   Stack=2, Locals=2, Args_size=2
	aload_0
	aload_1
	invokevirtual	Method shiftUnitR:(Ljava/lang/Object;)Lscala/util/continuations/ControlContext;
	areturn
  Labels:
  LocalVariableTable: 
   Start  Length  Slot  Name   Signature
   0      6      0    this       Lscala/util/continuations/package$;
   0      6      1    x       Ljava/lang/Object;

  Signature: length = 0x2
   00 5A 

public scala.util.continuations.ControlContext shiftUnit(java.lang.Object);
  Signature: (Ljava/lang/Object;)Lscala/util/continuations/ControlContext;
  Code:
   Stack=3, Locals=2, Args_size=2
	new	class java/lang/NoSuchMethodException
	dup
	ldc	String this code has to be compiled with the Scala continuations plugin enabled
	invokespecial	Method java/lang/NoSuchMethodException."<init>":(Ljava/lang/String;)V
	athrow
  Labels:
  LocalVariableTable: 
   Start  Length  Slot  Name   Signature
   0      10      0    this       Lscala/util/continuations/package$;
   0      10      1    x       Ljava/lang/Object;

  Signature: length = 0x2
   00 5C 

public scala.util.continuations.ControlContext reify(scala.Function0);
  Signature: (Lscala/Function0;)Lscala/util/continuations/ControlContext;
  Code:
   Stack=3, Locals=2, Args_size=2
	new	class java/lang/NoSuchMethodException
	dup
	ldc	String this code has to be compiled with the Scala continuations plugin enabled
	invokespecial	Method java/lang/NoSuchMethodException."<init>":(Ljava/lang/String;)V
	athrow
  Labels:
  LocalVariableTable: 
   Start  Length  Slot  Name   Signature
   0      10      0    this       Lscala/util/continuations/package$;
   0      10      1    ctx       Lscala/Function0;

  Signature: length = 0x2
   00 5F 

public scala.util.continuations.ControlContext shiftUnitR(java.lang.Object);
  Signature: (Ljava/lang/Object;)Lscala/util/continuations/ControlContext;
  Code:
   Stack=4, Locals=2, Args_size=2
	new	class scala/util/continuations/ControlContext
	dup
	aconst_null
	aload_1
	invokespecial	Method scala/util/continuations/ControlContext."<init>":(Lscala/Function2;Ljava/lang/Object;)V
	areturn
  Labels:
  LocalVariableTable: 
   Start  Length  Slot  Name   Signature
   0      10      0    this       Lscala/util/continuations/package$;
   0      10      1    x       Ljava/lang/Object;

  Signature: length = 0x2
   00 5A 

public scala.util.continuations.ControlContext shiftR(scala.Function1);
  Signature: (Lscala/Function1;)Lscala/util/continuations/ControlContext;
  Code:
   Stack=5, Locals=2, Args_size=2
	new	class scala/util/continuations/ControlContext
	dup
	new	class scala/util/continuations/package$$anonfun$shiftR$1
	dup
	aload_1
	invokespecial	Method scala/util/continuations/package$$anonfun$shiftR$1."<init>":(Lscala/Function1;)V
	aconst_null
	invokespecial	Method scala/util/continuations/ControlContext."<init>":(Lscala/Function2;Ljava/lang/Object;)V
	areturn
  Labels:
  LocalVariableTable: 
   Start  Length  Slot  Name   Signature
   0      17      0    this       Lscala/util/continuations/package$;
   0      17      1    fun$1       Lscala/Function1;

  Signature: length = 0x2
   00 1B 

public scala.util.continuations.ControlContext reifyR(scala.Function0);
  Signature: (Lscala/Function0;)Lscala/util/continuations/ControlContext;
  Code:
   Stack=1, Locals=2, Args_size=2
	aload_1
	invokeinterface	InterfaceMethod scala/Function0.apply:()Ljava/lang/Object;
	checkcast	class scala/util/continuations/ControlContext
	areturn
  Labels:
  LocalVariableTable: 
   Start  Length  Slot  Name   Signature
   0      10      0    this       Lscala/util/continuations/package$;
   0      10      1    ctx       Lscala/Function0;

  Signature: length = 0x2
   00 5F 

private scala.util.continuations.package$();
  Signature: ()V
  Code:
   Stack=1, Locals=1, Args_size=1
	aload_0
	invokespecial	Method java/lang/Object."<init>":()V
	aload_0
	putstatic	Field MODULE$:Lscala/util/continuations/package$;
	return
  Labels:

}

