Compiled from "package.scala"
public final class scala.util.continuations.package$$anonfun$shiftR$1 extends scala.runtime.AbstractFunction2 implements java.io.Serializable
  SourceFile: "package.scala"
  Scala: length = 0x
   
  InnerClass: 
   public final $anonfun$shiftR$1=class scala/util/continuations/package$$anonfun$shiftR$1 of class scala/util/continuations/package
  minor version: 0
  major version: 49
  Constant pool:
Asciz	SourceFile;
Asciz	package.scala;
Asciz	<clinit>;
Asciz	()V;
Asciz	Code;
Asciz	serialVersionUID;
Asciz	J;
Asciz	scala/util/continuations/package$$anonfun$shiftR$1;
class	scala/util/continuations/package$$anonfun$shiftR$1
NameAndType	serialVersionUID:J
Field	scala/util/continuations/package$$anonfun$shiftR$1.serialVersionUID:J
Asciz	fun$1;
Asciz	Lscala/Function1;;
Asciz	apply;
Asciz	(Lscala/Function1;Lscala/Function1;)Ljava/lang/Object;;
Asciz	LineNumberTable;
NameAndType	fun$1:Lscala/Function1;
Field	scala/util/continuations/package$$anonfun$shiftR$1.fun$1:Lscala/Function1;
Asciz	scala/Function1;
class	scala/Function1
Asciz	(Ljava/lang/Object;)Ljava/lang/Object;;
NameAndType	apply:(Ljava/lang/Object;)Ljava/lang/Object;
InterfaceMethod	scala/Function1.apply:(Ljava/lang/Object;)Ljava/lang/Object;
Asciz	this;
Asciz	Lscala/util/continuations/package$$anonfun$shiftR$1;;
Asciz	f;
Asciz	g;
Asciz	LocalVariableTable;
Asciz	(Lscala/Function1<TA;TB;>;Lscala/Function1<Ljava/lang/Exception;TB;>;)TC;;
Asciz	Signature;
Asciz	(Ljava/lang/Object;Ljava/lang/Object;)Ljava/lang/Object;;
NameAndType	apply:(Lscala/Function1;Lscala/Function1;)Ljava/lang/Object;
Method	scala/util/continuations/package$$anonfun$shiftR$1.apply:(Lscala/Function1;Lscala/Function1;)Ljava/lang/Object;
Asciz	v1;
Asciz	Ljava/lang/Object;;
Asciz	v2;
Asciz	<init>;
Asciz	(Lscala/Function1;)V;
Asciz	scala/runtime/AbstractFunction2;
class	scala/runtime/AbstractFunction2
NameAndType	"<init>":()V
Method	scala/runtime/AbstractFunction2."<init>":()V
Asciz	Scala;
Asciz	InnerClasses;
Asciz	scala/util/continuations/package;
class	scala/util/continuations/package
Asciz	$anonfun$shiftR$1;
Asciz	java/io/Serializable;
class	java/io/Serializable

{
public static final long serialVersionUID;
  Signature: J

public final scala.Function1 fun$1;
  Signature: Lscala/Function1;

public static {};
  Signature: ()V
  Code:
   Stack=2, Locals=0, Args_size=0
	lconst_0
	putstatic	Field serialVersionUID:J
	return
  Labels:

public final java.lang.Object apply(scala.Function1, scala.Function1);
  Signature: (Lscala/Function1;Lscala/Function1;)Ljava/lang/Object;
  Code:
   Stack=2, Locals=3, Args_size=3
	aload_0
	getfield	Field fun$1:Lscala/Function1;
	aload_1
	invokeinterface	InterfaceMethod scala/Function1.apply:(Ljava/lang/Object;)Ljava/lang/Object;
	areturn
  Labels:
  LocalVariableTable: 
   Start  Length  Slot  Name   Signature
   0      11      0    this       Lscala/util/continuations/package$$anonfun$shiftR$1;
   0      11      1    f       Lscala/Function1;
   0      11      2    g       Lscala/Function1;

  Signature: length = 0x2
   00 1D 

public final java.lang.Object apply(java.lang.Object, java.lang.Object);
  Signature: (Ljava/lang/Object;Ljava/lang/Object;)Ljava/lang/Object;
  Code:
   Stack=3, Locals=3, Args_size=3
	aload_0
	aload_1
	checkcast	class scala/Function1
	aload_2
	checkcast	class scala/Function1
	invokevirtual	Method apply:(Lscala/Function1;Lscala/Function1;)Ljava/lang/Object;
	areturn
  Labels:
  LocalVariableTable: 
   Start  Length  Slot  Name   Signature
   0      13      0    this       Lscala/util/continuations/package$$anonfun$shiftR$1;
   0      13      1    v1       Ljava/lang/Object;
   0      13      2    v2       Ljava/lang/Object;


public scala.util.continuations.package$$anonfun$shiftR$1(scala.Function1);
  Signature: (Lscala/Function1;)V
  Code:
   Stack=2, Locals=2, Args_size=2
	aload_0
	aload_1
	putfield	Field fun$1:Lscala/Function1;
	aload_0
	invokespecial	Method scala/runtime/AbstractFunction2."<init>":()V
	return
  Labels:

}

