Compiled from "FactoryAdapter.scala"
public abstract class scala.xml.parsing.ConsoleErrorHandler$class extends java.lang.Object
  SourceFile: "FactoryAdapter.scala"
  Scala: length = 0x
   
  InnerClass: 
   public final $anonfun$printError$1=class scala/xml/parsing/ConsoleErrorHandler$$anonfun$printError$1 of class scala/xml/parsing/ConsoleErrorHandler
  minor version: 0
  major version: 49
  Constant pool:
Asciz	SourceFile;
Asciz	FactoryAdapter.scala;
Asciz	$init$;
Asciz	(Lscala/xml/parsing/ConsoleErrorHandler;)V;
Asciz	Code;
Asciz	LineNumberTable;
Asciz	$this;
Asciz	Lscala/xml/parsing/ConsoleErrorHandler;;
Asciz	LocalVariableTable;
Asciz	printError;
Asciz	(Lscala/xml/parsing/ConsoleErrorHandler;Ljava/lang/String;Lorg/xml/sax/SAXParseException;)V;
Asciz	scala/Console$;
class	scala/Console$
Asciz	MODULE$;
Asciz	Lscala/Console$;;
NameAndType	MODULE$:Lscala/Console$;
Field	scala/Console$.MODULE$:Lscala/Console$;
Asciz	err;
Asciz	()Ljava/io/PrintStream;;
NameAndType	err:()Ljava/io/PrintStream;
Method	scala/Console$.err:()Ljava/io/PrintStream;
Asciz	scala/xml/parsing/ConsoleErrorHandler$$anonfun$printError$1;
class	scala/xml/parsing/ConsoleErrorHandler$$anonfun$printError$1
Asciz	<init>;
NameAndType	"<init>":(Lscala/xml/parsing/ConsoleErrorHandler;Ljava/lang/String;Lorg/xml/sax/SAXParseException;)V
Method	scala/xml/parsing/ConsoleErrorHandler$$anonfun$printError$1."<init>":(Lscala/xml/parsing/ConsoleErrorHandler;Ljava/lang/String;Lorg/xml/sax/SAXParseException;)V
Asciz	withOut;
Asciz	(Ljava/io/PrintStream;Lscala/Function0;)Ljava/lang/Object;;
NameAndType	withOut:(Ljava/io/PrintStream;Lscala/Function0;)Ljava/lang/Object;
Method	scala/Console$.withOut:(Ljava/io/PrintStream;Lscala/Function0;)Ljava/lang/Object;
Asciz	errtype$1;
Asciz	Ljava/lang/String;;
Asciz	ex$1;
Asciz	Lorg/xml/sax/SAXParseException;;
Asciz	fatalError;
Asciz	(Lscala/xml/parsing/ConsoleErrorHandler;Lorg/xml/sax/SAXParseException;)V;
Asciz	Fatal Error;
String	Fatal Error
Asciz	scala/xml/parsing/ConsoleErrorHandler;
class	scala/xml/parsing/ConsoleErrorHandler
Asciz	(Ljava/lang/String;Lorg/xml/sax/SAXParseException;)V;
NameAndType	printError:(Ljava/lang/String;Lorg/xml/sax/SAXParseException;)V
InterfaceMethod	scala/xml/parsing/ConsoleErrorHandler.printError:(Ljava/lang/String;Lorg/xml/sax/SAXParseException;)V
Asciz	ex;
Asciz	error;
Asciz	Error;
String	Error
Asciz	warning;
Asciz	Scala;
Asciz	InnerClasses;
Asciz	$anonfun$printError$1;
Asciz	scala/xml/parsing/ConsoleErrorHandler$class;
class	scala/xml/parsing/ConsoleErrorHandler$class
Asciz	java/lang/Object;
class	java/lang/Object

{
public static void $init$(scala.xml.parsing.ConsoleErrorHandler);
  Signature: (Lscala/xml/parsing/ConsoleErrorHandler;)V
  Code:
   Stack=0, Locals=1, Args_size=1
	return
  Labels:
  LocalVariableTable: 
   Start  Length  Slot  Name   Signature
   0      1      0    $this       Lscala/xml/parsing/ConsoleErrorHandler;


public static void printError(scala.xml.parsing.ConsoleErrorHandler, java.lang.String, org.xml.sax.SAXParseException);
  Signature: (Lscala/xml/parsing/ConsoleErrorHandler;Ljava/lang/String;Lorg/xml/sax/SAXParseException;)V
  Code:
   Stack=7, Locals=3, Args_size=3
	getstatic	Field scala/Console$.MODULE$:Lscala/Console$;
	getstatic	Field scala/Console$.MODULE$:Lscala/Console$;
	invokevirtual	Method scala/Console$.err:()Ljava/io/PrintStream;
	new	class scala/xml/parsing/ConsoleErrorHandler$$anonfun$printError$1
	dup
	aload_0
	aload_1
	aload_2
	invokespecial	Method scala/xml/parsing/ConsoleErrorHandler$$anonfun$printError$1."<init>":(Lscala/xml/parsing/ConsoleErrorHandler;Ljava/lang/String;Lorg/xml/sax/SAXParseException;)V
	invokevirtual	Method scala/Console$.withOut:(Ljava/io/PrintStream;Lscala/Function0;)Ljava/lang/Object;
	pop
	return
  Labels:
  LocalVariableTable: 
   Start  Length  Slot  Name   Signature
   0      24      0    $this       Lscala/xml/parsing/ConsoleErrorHandler;
   0      24      1    errtype$1       Ljava/lang/String;
   0      24      2    ex$1       Lorg/xml/sax/SAXParseException;


public static void fatalError(scala.xml.parsing.ConsoleErrorHandler, org.xml.sax.SAXParseException);
  Signature: (Lscala/xml/parsing/ConsoleErrorHandler;Lorg/xml/sax/SAXParseException;)V
  Code:
   Stack=3, Locals=2, Args_size=2
	aload_0
	ldc	String Fatal Error
	aload_1
	invokeinterface	InterfaceMethod scala/xml/parsing/ConsoleErrorHandler.printError:(Ljava/lang/String;Lorg/xml/sax/SAXParseException;)V
	return
  Labels:
  LocalVariableTable: 
   Start  Length  Slot  Name   Signature
   0      10      0    $this       Lscala/xml/parsing/ConsoleErrorHandler;
   0      10      1    ex       Lorg/xml/sax/SAXParseException;


public static void error(scala.xml.parsing.ConsoleErrorHandler, org.xml.sax.SAXParseException);
  Signature: (Lscala/xml/parsing/ConsoleErrorHandler;Lorg/xml/sax/SAXParseException;)V
  Code:
   Stack=3, Locals=2, Args_size=2
	aload_0
	ldc	String Error
	aload_1
	invokeinterface	InterfaceMethod scala/xml/parsing/ConsoleErrorHandler.printError:(Ljava/lang/String;Lorg/xml/sax/SAXParseException;)V
	return
  Labels:
  LocalVariableTable: 
   Start  Length  Slot  Name   Signature
   0      10      0    $this       Lscala/xml/parsing/ConsoleErrorHandler;
   0      10      1    ex       Lorg/xml/sax/SAXParseException;


public static void warning(scala.xml.parsing.ConsoleErrorHandler, org.xml.sax.SAXParseException);
  Signature: (Lscala/xml/parsing/ConsoleErrorHandler;Lorg/xml/sax/SAXParseException;)V
  Code:
   Stack=0, Locals=2, Args_size=2
	return
  Labels:
  LocalVariableTable: 
   Start  Length  Slot  Name   Signature
   0      1      0    $this       Lscala/xml/parsing/ConsoleErrorHandler;
   0      1      1    ex       Lorg/xml/sax/SAXParseException;


}

