Compiled from "FactoryAdapter.scala"
public final class scala.xml.parsing.ConsoleErrorHandler$$anonfun$printError$1 extends scala.runtime.AbstractFunction0$mcV$sp implements java.io.Serializable
  SourceFile: "FactoryAdapter.scala"
  Scala: length = 0x
   
  InnerClass: 
   public final $anonfun$printError$1=class scala/xml/parsing/ConsoleErrorHandler$$anonfun$printError$1 of class scala/xml/parsing/ConsoleErrorHandler
  minor version: 0
  major version: 49
  Constant pool:
Asciz	SourceFile;
Asciz	FactoryAdapter.scala;
Asciz	<clinit>;
Asciz	()V;
Asciz	Code;
Asciz	serialVersionUID;
Asciz	J;
Asciz	scala/xml/parsing/ConsoleErrorHandler$$anonfun$printError$1;
class	scala/xml/parsing/ConsoleErrorHandler$$anonfun$printError$1
NameAndType	serialVersionUID:J
Field	scala/xml/parsing/ConsoleErrorHandler$$anonfun$printError$1.serialVersionUID:J
Asciz	errtype$1;
Asciz	Ljava/lang/String;;
Asciz	ex$1;
Asciz	Lorg/xml/sax/SAXParseException;;
Asciz	apply;
Asciz	[%s]:%d:%d: %s;
String	[%s]:%d:%d: %s
Asciz	LineNumberTable;
Asciz	scala/collection/immutable/StringOps;
class	scala/collection/immutable/StringOps
Asciz	<init>;
Asciz	(Ljava/lang/String;)V;
NameAndType	"<init>":(Ljava/lang/String;)V
Method	scala/collection/immutable/StringOps."<init>":(Ljava/lang/String;)V
Asciz	scala/Predef$;
class	scala/Predef$
Asciz	MODULE$;
Asciz	Lscala/Predef$;;
NameAndType	MODULE$:Lscala/Predef$;
Field	scala/Predef$.MODULE$:Lscala/Predef$;
Asciz	java/lang/Object;
class	java/lang/Object
NameAndType	errtype$1:Ljava/lang/String;
Field	scala/xml/parsing/ConsoleErrorHandler$$anonfun$printError$1.errtype$1:Ljava/lang/String;
NameAndType	ex$1:Lorg/xml/sax/SAXParseException;
Field	scala/xml/parsing/ConsoleErrorHandler$$anonfun$printError$1.ex$1:Lorg/xml/sax/SAXParseException;
Asciz	org/xml/sax/SAXParseException;
class	org/xml/sax/SAXParseException
Asciz	getLineNumber;
Asciz	()I;
NameAndType	getLineNumber:()I
Method	org/xml/sax/SAXParseException.getLineNumber:()I
Asciz	scala/runtime/BoxesRunTime;
class	scala/runtime/BoxesRunTime
Asciz	boxToInteger;
Asciz	(I)Ljava/lang/Integer;;
NameAndType	boxToInteger:(I)Ljava/lang/Integer;
Method	scala/runtime/BoxesRunTime.boxToInteger:(I)Ljava/lang/Integer;
Asciz	getColumnNumber;
NameAndType	getColumnNumber:()I
Method	org/xml/sax/SAXParseException.getColumnNumber:()I
Asciz	getMessage;
Asciz	()Ljava/lang/String;;
NameAndType	getMessage:()Ljava/lang/String;
Method	org/xml/sax/SAXParseException.getMessage:()Ljava/lang/String;
Asciz	genericWrapArray;
Asciz	(Ljava/lang/Object;)Lscala/collection/mutable/WrappedArray;;
NameAndType	genericWrapArray:(Ljava/lang/Object;)Lscala/collection/mutable/WrappedArray;
Method	scala/Predef$.genericWrapArray:(Ljava/lang/Object;)Lscala/collection/mutable/WrappedArray;
Asciz	scala/collection/immutable/StringLike$class;
class	scala/collection/immutable/StringLike$class
Asciz	format;
Asciz	(Lscala/collection/immutable/StringLike;Lscala/collection/Seq;)Ljava/lang/String;;
NameAndType	format:(Lscala/collection/immutable/StringLike;Lscala/collection/Seq;)Ljava/lang/String;
Method	scala/collection/immutable/StringLike$class.format:(Lscala/collection/immutable/StringLike;Lscala/collection/Seq;)Ljava/lang/String;
Asciz	scala/Console$;
class	scala/Console$
Asciz	Lscala/Console$;;
NameAndType	MODULE$:Lscala/Console$;
Field	scala/Console$.MODULE$:Lscala/Console$;
Asciz	out;
Asciz	()Ljava/io/PrintStream;;
NameAndType	out:()Ljava/io/PrintStream;
Method	scala/Console$.out:()Ljava/io/PrintStream;
Asciz	java/io/PrintStream;
class	java/io/PrintStream
Asciz	println;
Asciz	(Ljava/lang/Object;)V;
NameAndType	println:(Ljava/lang/Object;)V
Method	java/io/PrintStream.println:(Ljava/lang/Object;)V
Asciz	flush;
NameAndType	flush:()V
Method	java/io/PrintStream.flush:()V
Asciz	this;
Asciz	Lscala/xml/parsing/ConsoleErrorHandler$$anonfun$printError$1;;
Asciz	s0;
Asciz	LocalVariableTable;
Asciz	apply$mcV$sp;
Asciz	augmentString;
Asciz	(Ljava/lang/String;)Lscala/collection/immutable/StringOps;;
NameAndType	augmentString:(Ljava/lang/String;)Lscala/collection/immutable/StringOps;
Method	scala/Predef$.augmentString:(Ljava/lang/String;)Lscala/collection/immutable/StringOps;
Asciz	scala/collection/immutable/StringLike;
class	scala/collection/immutable/StringLike
Asciz	(Lscala/collection/Seq;)Ljava/lang/String;;
NameAndType	format:(Lscala/collection/Seq;)Ljava/lang/String;
InterfaceMethod	scala/collection/immutable/StringLike.format:(Lscala/collection/Seq;)Ljava/lang/String;
Method	scala/Console$.println:(Ljava/lang/Object;)V
Method	scala/Console$.flush:()V
Asciz	s;
Asciz	()Ljava/lang/Object;;
NameAndType	apply:()V
Method	scala/xml/parsing/ConsoleErrorHandler$$anonfun$printError$1.apply:()V
Asciz	scala/runtime/BoxedUnit;
class	scala/runtime/BoxedUnit
Asciz	UNIT;
Asciz	Lscala/runtime/BoxedUnit;;
NameAndType	UNIT:Lscala/runtime/BoxedUnit;
Field	scala/runtime/BoxedUnit.UNIT:Lscala/runtime/BoxedUnit;
Asciz	(Lscala/xml/parsing/ConsoleErrorHandler;Ljava/lang/String;Lorg/xml/sax/SAXParseException;)V;
Asciz	scala/runtime/AbstractFunction0$mcV$sp;
class	scala/runtime/AbstractFunction0$mcV$sp
NameAndType	"<init>":()V
Method	scala/runtime/AbstractFunction0$mcV$sp."<init>":()V
Asciz	$outer;
Asciz	Lscala/xml/parsing/ConsoleErrorHandler;;
Asciz	Scala;
Asciz	InnerClasses;
Asciz	scala/xml/parsing/ConsoleErrorHandler;
class	scala/xml/parsing/ConsoleErrorHandler
Asciz	$anonfun$printError$1;
Asciz	java/io/Serializable;
class	java/io/Serializable

{
public static final long serialVersionUID;
  Signature: J

public final java.lang.String errtype$1;
  Signature: Ljava/lang/String;

public final org.xml.sax.SAXParseException ex$1;
  Signature: Lorg/xml/sax/SAXParseException;

public static {};
  Signature: ()V
  Code:
   Stack=2, Locals=0, Args_size=0
	lconst_0
	putstatic	Field serialVersionUID:J
	return
  Labels:

public final void apply();
  Signature: ()V
  Code:
   Stack=6, Locals=9, Args_size=1
	ldc	String [%s]:%d:%d: %s
	astore_1
	new	class scala/collection/immutable/StringOps
	dup
	aload_1
	invokespecial	Method scala/collection/immutable/StringOps."<init>":(Ljava/lang/String;)V
	getstatic	Field scala/Predef$.MODULE$:Lscala/Predef$;
	iconst_4
	anewarray	class java/lang/Object
	dup
	iconst_0
	aload_0
	getfield	Field errtype$1:Ljava/lang/String;
	aastore
	dup
	iconst_1
	aload_0
	getfield	Field ex$1:Lorg/xml/sax/SAXParseException;
	invokevirtual	Method org/xml/sax/SAXParseException.getLineNumber:()I
	istore_2
	iload_2
	invokestatic	Method scala/runtime/BoxesRunTime.boxToInteger:(I)Ljava/lang/Integer;
	aastore
	dup
	iconst_2
	aload_0
	getfield	Field ex$1:Lorg/xml/sax/SAXParseException;
	invokevirtual	Method org/xml/sax/SAXParseException.getColumnNumber:()I
	istore_3
	iload_3
	invokestatic	Method scala/runtime/BoxesRunTime.boxToInteger:(I)Ljava/lang/Integer;
	aastore
	dup
	iconst_3
	aload_0
	getfield	Field ex$1:Lorg/xml/sax/SAXParseException;
	invokevirtual	Method org/xml/sax/SAXParseException.getMessage:()Ljava/lang/String;
	aastore
	invokevirtual	Method scala/Predef$.genericWrapArray:(Ljava/lang/Object;)Lscala/collection/mutable/WrappedArray;
	astore	5
	astore	4
	aload	4
	aload	5
	invokestatic	Method scala/collection/immutable/StringLike$class.format:(Lscala/collection/immutable/StringLike;Lscala/collection/Seq;)Ljava/lang/String;
	astore	7
	getstatic	Field scala/Console$.MODULE$:Lscala/Console$;
	astore	6
	aload	6
	invokevirtual	Method scala/Console$.out:()Ljava/io/PrintStream;
	aload	7
	invokevirtual	Method java/io/PrintStream.println:(Ljava/lang/Object;)V
	getstatic	Field scala/Console$.MODULE$:Lscala/Console$;
	astore	8
	aload	8
	invokevirtual	Method scala/Console$.out:()Ljava/io/PrintStream;
	invokevirtual	Method java/io/PrintStream.flush:()V
	return
  Labels:
  LocalVariableTable: 
   Start  Length  Slot  Name   Signature
   0      110      0    this       Lscala/xml/parsing/ConsoleErrorHandler$$anonfun$printError$1;
   81      28      7    s0       Ljava/lang/String;


public void apply$mcV$sp();
  Signature: ()V
  Code:
   Stack=6, Locals=4, Args_size=1
	getstatic	Field scala/Predef$.MODULE$:Lscala/Predef$;
	ldc	String [%s]:%d:%d: %s
	invokevirtual	Method scala/Predef$.augmentString:(Ljava/lang/String;)Lscala/collection/immutable/StringOps;
	getstatic	Field scala/Predef$.MODULE$:Lscala/Predef$;
	iconst_4
	anewarray	class java/lang/Object
	dup
	iconst_0
	aload_0
	getfield	Field errtype$1:Ljava/lang/String;
	aastore
	dup
	iconst_1
	aload_0
	getfield	Field ex$1:Lorg/xml/sax/SAXParseException;
	invokevirtual	Method org/xml/sax/SAXParseException.getLineNumber:()I
	istore_2
	iload_2
	invokestatic	Method scala/runtime/BoxesRunTime.boxToInteger:(I)Ljava/lang/Integer;
	aastore
	dup
	iconst_2
	aload_0
	getfield	Field ex$1:Lorg/xml/sax/SAXParseException;
	invokevirtual	Method org/xml/sax/SAXParseException.getColumnNumber:()I
	istore_3
	iload_3
	invokestatic	Method scala/runtime/BoxesRunTime.boxToInteger:(I)Ljava/lang/Integer;
	aastore
	dup
	iconst_3
	aload_0
	getfield	Field ex$1:Lorg/xml/sax/SAXParseException;
	invokevirtual	Method org/xml/sax/SAXParseException.getMessage:()Ljava/lang/String;
	aastore
	invokevirtual	Method scala/Predef$.genericWrapArray:(Ljava/lang/Object;)Lscala/collection/mutable/WrappedArray;
	invokeinterface	InterfaceMethod scala/collection/immutable/StringLike.format:(Lscala/collection/Seq;)Ljava/lang/String;
	astore_1
	getstatic	Field scala/Console$.MODULE$:Lscala/Console$;
	aload_1
	invokevirtual	Method scala/Console$.println:(Ljava/lang/Object;)V
	getstatic	Field scala/Console$.MODULE$:Lscala/Console$;
	invokevirtual	Method scala/Console$.flush:()V
	return
  Labels:
  LocalVariableTable: 
   Start  Length  Slot  Name   Signature
   0      85      0    this       Lscala/xml/parsing/ConsoleErrorHandler$$anonfun$printError$1;
   71      13      1    s       Ljava/lang/String;


public final java.lang.Object apply();
  Signature: ()Ljava/lang/Object;
  Code:
   Stack=1, Locals=1, Args_size=1
	aload_0
	invokevirtual	Method apply:()V
	getstatic	Field scala/runtime/BoxedUnit.UNIT:Lscala/runtime/BoxedUnit;
	areturn
  Labels:

public scala.xml.parsing.ConsoleErrorHandler$$anonfun$printError$1(scala.xml.parsing.ConsoleErrorHandler, java.lang.String, org.xml.sax.SAXParseException);
  Signature: (Lscala/xml/parsing/ConsoleErrorHandler;Ljava/lang/String;Lorg/xml/sax/SAXParseException;)V
  Code:
   Stack=2, Locals=4, Args_size=4
	aload_0
	aload_2
	putfield	Field errtype$1:Ljava/lang/String;
	aload_0
	aload_3
	putfield	Field ex$1:Lorg/xml/sax/SAXParseException;
	aload_0
	invokespecial	Method scala/runtime/AbstractFunction0$mcV$sp."<init>":()V
	return
  Labels:
  LocalVariableTable: 
   Start  Length  Slot  Name   Signature
   0      15      0    this       Lscala/xml/parsing/ConsoleErrorHandler$$anonfun$printError$1;
   0      15      1    $outer       Lscala/xml/parsing/ConsoleErrorHandler;


}

