Compiled from "FactoryAdapter.scala"
public final class scala.xml.parsing.ConsoleErrorHandler$$anonfun$printError$1 extends java.lang.Object implements scala.Function0,scala.ScalaObject,java.io.Serializable
  SourceFile: "FactoryAdapter.scala"
  Scala: length = 0x
   
  InnerClass: 
   public final #110= #9 of #109; //$anonfun$printError$1=class scala/xml/parsing/ConsoleErrorHandler$$anonfun$printError$1 of class scala/xml/parsing/ConsoleErrorHandler
  minor version: 0
  major version: 49
  Constant pool:
const #1 = Asciz	SourceFile;
const #2 = Asciz	FactoryAdapter.scala;
const #3 = Asciz	<clinit>;
const #4 = Asciz	()V;
const #5 = Asciz	Code;
const #6 = Asciz	serialVersionUID;
const #7 = Asciz	J;
const #8 = Asciz	scala/xml/parsing/ConsoleErrorHandler$$anonfun$printError$1;
const #9 = class	#8;	//  scala/xml/parsing/ConsoleErrorHandler$$anonfun$printError$1
const #10 = NameAndType	#6:#7;//  serialVersionUID:J
const #11 = Field	#9.#10;	//  scala/xml/parsing/ConsoleErrorHandler$$anonfun$printError$1.serialVersionUID:J
const #12 = Asciz	ex$1;
const #13 = Asciz	Lorg/xml/sax/SAXParseException;;
const #14 = Asciz	errtype$1;
const #15 = Asciz	Ljava/lang/String;;
const #16 = Asciz	<init>;
const #17 = Asciz	(Lscala/xml/parsing/ConsoleErrorHandler;Ljava/lang/String;Lorg/xml/sax/SAXParseException;)V;
const #18 = Asciz	LineNumberTable;
const #19 = NameAndType	#14:#15;//  errtype$1:Ljava/lang/String;
const #20 = Field	#9.#19;	//  scala/xml/parsing/ConsoleErrorHandler$$anonfun$printError$1.errtype$1:Ljava/lang/String;
const #21 = NameAndType	#12:#13;//  ex$1:Lorg/xml/sax/SAXParseException;
const #22 = Field	#9.#21;	//  scala/xml/parsing/ConsoleErrorHandler$$anonfun$printError$1.ex$1:Lorg/xml/sax/SAXParseException;
const #23 = Asciz	java/lang/Object;
const #24 = class	#23;	//  java/lang/Object
const #25 = NameAndType	#16:#4;//  "<init>":()V
const #26 = Method	#24.#25;	//  java/lang/Object."<init>":()V
const #27 = Asciz	scala/Function0$class;
const #28 = class	#27;	//  scala/Function0$class
const #29 = Asciz	$init$;
const #30 = Asciz	(Lscala/Function0;)V;
const #31 = NameAndType	#29:#30;//  $init$:(Lscala/Function0;)V
const #32 = Method	#28.#31;	//  scala/Function0$class.$init$:(Lscala/Function0;)V
const #33 = Asciz	this;
const #34 = Asciz	Lscala/xml/parsing/ConsoleErrorHandler$$anonfun$printError$1;;
const #35 = Asciz	$outer;
const #36 = Asciz	Lscala/xml/parsing/ConsoleErrorHandler;;
const #37 = Asciz	LocalVariableTable;
const #38 = Asciz	apply;
const #39 = Asciz	()Ljava/lang/Object;;
const #40 = NameAndType	#38:#4;//  apply:()V
const #41 = Method	#9.#40;	//  scala/xml/parsing/ConsoleErrorHandler$$anonfun$printError$1.apply:()V
const #42 = Asciz	scala/runtime/BoxedUnit;
const #43 = class	#42;	//  scala/runtime/BoxedUnit
const #44 = Asciz	UNIT;
const #45 = Asciz	Lscala/runtime/BoxedUnit;;
const #46 = NameAndType	#44:#45;//  UNIT:Lscala/runtime/BoxedUnit;
const #47 = Field	#43.#46;	//  scala/runtime/BoxedUnit.UNIT:Lscala/runtime/BoxedUnit;
const #48 = Asciz	scala/Predef$;
const #49 = class	#48;	//  scala/Predef$
const #50 = Asciz	MODULE$;
const #51 = Asciz	Lscala/Predef$;;
const #52 = NameAndType	#50:#51;//  MODULE$:Lscala/Predef$;
const #53 = Field	#49.#52;	//  scala/Predef$.MODULE$:Lscala/Predef$;
const #54 = Asciz	[%s]:%d:%d: %s;
const #55 = String	#54;	//  [%s]:%d:%d: %s
const #56 = Asciz	augmentString;
const #57 = Asciz	(Ljava/lang/String;)Lscala/collection/immutable/StringOps;;
const #58 = NameAndType	#56:#57;//  augmentString:(Ljava/lang/String;)Lscala/collection/immutable/StringOps;
const #59 = Method	#49.#58;	//  scala/Predef$.augmentString:(Ljava/lang/String;)Lscala/collection/immutable/StringOps;
const #60 = Asciz	org/xml/sax/SAXParseException;
const #61 = class	#60;	//  org/xml/sax/SAXParseException
const #62 = Asciz	getLineNumber;
const #63 = Asciz	()I;
const #64 = NameAndType	#62:#63;//  getLineNumber:()I
const #65 = Method	#61.#64;	//  org/xml/sax/SAXParseException.getLineNumber:()I
const #66 = Asciz	scala/runtime/BoxesRunTime;
const #67 = class	#66;	//  scala/runtime/BoxesRunTime
const #68 = Asciz	boxToInteger;
const #69 = Asciz	(I)Ljava/lang/Integer;;
const #70 = NameAndType	#68:#69;//  boxToInteger:(I)Ljava/lang/Integer;
const #71 = Method	#67.#70;	//  scala/runtime/BoxesRunTime.boxToInteger:(I)Ljava/lang/Integer;
const #72 = Asciz	getColumnNumber;
const #73 = NameAndType	#72:#63;//  getColumnNumber:()I
const #74 = Method	#61.#73;	//  org/xml/sax/SAXParseException.getColumnNumber:()I
const #75 = Asciz	getMessage;
const #76 = Asciz	()Ljava/lang/String;;
const #77 = NameAndType	#75:#76;//  getMessage:()Ljava/lang/String;
const #78 = Method	#61.#77;	//  org/xml/sax/SAXParseException.getMessage:()Ljava/lang/String;
const #79 = Asciz	genericWrapArray;
const #80 = Asciz	(Ljava/lang/Object;)Lscala/collection/mutable/WrappedArray;;
const #81 = NameAndType	#79:#80;//  genericWrapArray:(Ljava/lang/Object;)Lscala/collection/mutable/WrappedArray;
const #82 = Method	#49.#81;	//  scala/Predef$.genericWrapArray:(Ljava/lang/Object;)Lscala/collection/mutable/WrappedArray;
const #83 = Asciz	scala/collection/immutable/StringLike;
const #84 = class	#83;	//  scala/collection/immutable/StringLike
const #85 = Asciz	format;
const #86 = Asciz	(Lscala/collection/Seq;)Ljava/lang/String;;
const #87 = NameAndType	#85:#86;//  format:(Lscala/collection/Seq;)Ljava/lang/String;
const #88 = InterfaceMethod	#84.#87;	//  scala/collection/immutable/StringLike.format:(Lscala/collection/Seq;)Ljava/lang/String;
const #89 = Asciz	scala/Console$;
const #90 = class	#89;	//  scala/Console$
const #91 = Asciz	Lscala/Console$;;
const #92 = NameAndType	#50:#91;//  MODULE$:Lscala/Console$;
const #93 = Field	#90.#92;	//  scala/Console$.MODULE$:Lscala/Console$;
const #94 = Asciz	println;
const #95 = Asciz	(Ljava/lang/Object;)V;
const #96 = NameAndType	#94:#95;//  println:(Ljava/lang/Object;)V
const #97 = Method	#90.#96;	//  scala/Console$.println:(Ljava/lang/Object;)V
const #98 = Asciz	flush;
const #99 = NameAndType	#98:#4;//  flush:()V
const #100 = Method	#90.#99;	//  scala/Console$.flush:()V
const #101 = Asciz	s;
const #102 = Asciz	toString;
const #103 = Asciz	(Lscala/Function0;)Ljava/lang/String;;
const #104 = NameAndType	#102:#103;//  toString:(Lscala/Function0;)Ljava/lang/String;
const #105 = Method	#28.#104;	//  scala/Function0$class.toString:(Lscala/Function0;)Ljava/lang/String;
const #106 = Asciz	Scala;
const #107 = Asciz	InnerClasses;
const #108 = Asciz	scala/xml/parsing/ConsoleErrorHandler;
const #109 = class	#108;	//  scala/xml/parsing/ConsoleErrorHandler
const #110 = Asciz	$anonfun$printError$1;
const #111 = Asciz	scala/Function0;
const #112 = class	#111;	//  scala/Function0
const #113 = Asciz	scala/ScalaObject;
const #114 = class	#113;	//  scala/ScalaObject
const #115 = Asciz	java/io/Serializable;
const #116 = class	#115;	//  java/io/Serializable

{
public static final long serialVersionUID;

public static {};
  Code:
   Stack=2, Locals=0, Args_size=0
   0:	lconst_0
   1:	putstatic	#11; //Field serialVersionUID:J
   4:	return

public scala.xml.parsing.ConsoleErrorHandler$$anonfun$printError$1(scala.xml.parsing.ConsoleErrorHandler, java.lang.String, org.xml.sax.SAXParseException);
  Code:
   Stack=2, Locals=4, Args_size=4
   0:	aload_0
   1:	aload_2
   2:	putfield	#20; //Field errtype$1:Ljava/lang/String;
   5:	aload_0
   6:	aload_3
   7:	putfield	#22; //Field ex$1:Lorg/xml/sax/SAXParseException;
   10:	aload_0
   11:	invokespecial	#26; //Method java/lang/Object."<init>":()V
   14:	aload_0
   15:	invokestatic	#32; //Method scala/Function0$class.$init$:(Lscala/Function0;)V
   18:	return
  LineNumberTable: 
   line 35: 0

  LocalVariableTable: 
   Start  Length  Slot  Name   Signature
   0      19      0    this       Lscala/xml/parsing/ConsoleErrorHandler$$anonfun$printError$1;
   0      19      1    $outer       Lscala/xml/parsing/ConsoleErrorHandler;


public final java.lang.Object apply();
  Code:
   Stack=1, Locals=1, Args_size=1
   0:	aload_0
   1:	invokevirtual	#41; //Method apply:()V
   4:	getstatic	#47; //Field scala/runtime/BoxedUnit.UNIT:Lscala/runtime/BoxedUnit;
   7:	areturn
  LineNumberTable: 
   line 35: 0


public final void apply();
  Code:
   Stack=6, Locals=4, Args_size=1
   0:	getstatic	#53; //Field scala/Predef$.MODULE$:Lscala/Predef$;
   3:	ldc	#55; //String [%s]:%d:%d: %s
   5:	invokevirtual	#59; //Method scala/Predef$.augmentString:(Ljava/lang/String;)Lscala/collection/immutable/StringOps;
   8:	getstatic	#53; //Field scala/Predef$.MODULE$:Lscala/Predef$;
   11:	iconst_4
   12:	anewarray	#24; //class java/lang/Object
   15:	dup
   16:	iconst_0
   17:	aload_0
   18:	getfield	#20; //Field errtype$1:Ljava/lang/String;
   21:	aastore
   22:	dup
   23:	iconst_1
   24:	aload_0
   25:	getfield	#22; //Field ex$1:Lorg/xml/sax/SAXParseException;
   28:	invokevirtual	#65; //Method org/xml/sax/SAXParseException.getLineNumber:()I
   31:	istore_2
   32:	iload_2
   33:	invokestatic	#71; //Method scala/runtime/BoxesRunTime.boxToInteger:(I)Ljava/lang/Integer;
   36:	aastore
   37:	dup
   38:	iconst_2
   39:	aload_0
   40:	getfield	#22; //Field ex$1:Lorg/xml/sax/SAXParseException;
   43:	invokevirtual	#74; //Method org/xml/sax/SAXParseException.getColumnNumber:()I
   46:	istore_3
   47:	iload_3
   48:	invokestatic	#71; //Method scala/runtime/BoxesRunTime.boxToInteger:(I)Ljava/lang/Integer;
   51:	aastore
   52:	dup
   53:	iconst_3
   54:	aload_0
   55:	getfield	#22; //Field ex$1:Lorg/xml/sax/SAXParseException;
   58:	invokevirtual	#78; //Method org/xml/sax/SAXParseException.getMessage:()Ljava/lang/String;
   61:	aastore
   62:	invokevirtual	#82; //Method scala/Predef$.genericWrapArray:(Ljava/lang/Object;)Lscala/collection/mutable/WrappedArray;
   65:	invokeinterface	#88,  2; //InterfaceMethod scala/collection/immutable/StringLike.format:(Lscala/collection/Seq;)Ljava/lang/String;
   70:	astore_1
   71:	getstatic	#93; //Field scala/Console$.MODULE$:Lscala/Console$;
   74:	aload_1
   75:	invokevirtual	#97; //Method scala/Console$.println:(Ljava/lang/Object;)V
   78:	getstatic	#93; //Field scala/Console$.MODULE$:Lscala/Console$;
   81:	invokevirtual	#100; //Method scala/Console$.flush:()V
   84:	return
  LineNumberTable: 
   line 36: 0
   line 37: 17
   line 36: 22
   line 37: 24
   line 36: 37
   line 37: 39
   line 36: 52
   line 37: 54
   line 36: 62
   line 38: 71
   line 39: 78

  LocalVariableTable: 
   Start  Length  Slot  Name   Signature
   0      85      0    this       Lscala/xml/parsing/ConsoleErrorHandler$$anonfun$printError$1;
   71      13      1    s       Ljava/lang/String;


public java.lang.String toString();
  Code:
   Stack=1, Locals=1, Args_size=1
   0:	aload_0
   1:	invokestatic	#105; //Method scala/Function0$class.toString:(Lscala/Function0;)Ljava/lang/String;
   4:	areturn
  LineNumberTable: 
   line 35: 0


}

