Compiled from "ConstructingParser.scala"
public final class scala.xml.parsing.ConstructingParser$ extends java.lang.Object implements scala.ScalaObject
  SourceFile: "ConstructingParser.scala"
  Scala: length = 0x
   
  minor version: 0
  major version: 49
  Constant pool:
Asciz	SourceFile;
Asciz	ConstructingParser.scala;
Asciz	Scala;
Asciz	MODULE$;
Asciz	Lscala/xml/parsing/ConstructingParser$;;
Asciz	<clinit>;
Asciz	()V;
Asciz	Code;
Asciz	scala/xml/parsing/ConstructingParser$;
class	scala/xml/parsing/ConstructingParser$
Asciz	<init>;
NameAndType	"<init>":()V
Method	scala/xml/parsing/ConstructingParser$."<init>":()V
Asciz	fromFile;
Asciz	(Ljava/io/File;Z)Lscala/xml/parsing/ConstructingParser;;
Asciz	scala/xml/parsing/ConstructingParser;
class	scala/xml/parsing/ConstructingParser
Asciz	LineNumberTable;
Asciz	scala/io/Source$;
class	scala/io/Source$
Asciz	Lscala/io/Source$;;
NameAndType	MODULE$:Lscala/io/Source$;
Field	scala/io/Source$.MODULE$:Lscala/io/Source$;
Asciz	fromFile$default$2;
Asciz	()I;
NameAndType	fromFile$default$2:()I
Method	scala/io/Source$.fromFile$default$2:()I
Asciz	fromFile$default$3;
Asciz	(Ljava/io/File;I)Lscala/io/Codec;;
NameAndType	fromFile$default$3:(Ljava/io/File;I)Lscala/io/Codec;
Method	scala/io/Source$.fromFile$default$3:(Ljava/io/File;I)Lscala/io/Codec;
Asciz	(Ljava/io/File;ILscala/io/Codec;)Lscala/io/Source;;
NameAndType	fromFile:(Ljava/io/File;ILscala/io/Codec;)Lscala/io/Source;
Method	scala/io/Source$.fromFile:(Ljava/io/File;ILscala/io/Codec;)Lscala/io/Source;
Asciz	(Lscala/io/Source;Z)V;
NameAndType	"<init>":(Lscala/io/Source;Z)V
Method	scala/xml/parsing/ConstructingParser."<init>":(Lscala/io/Source;Z)V
Asciz	scala/xml/parsing/MarkupParser;
class	scala/xml/parsing/MarkupParser
Asciz	initialize;
Asciz	()Lscala/xml/parsing/MarkupHandler;;
NameAndType	initialize:()Lscala/xml/parsing/MarkupHandler;
InterfaceMethod	scala/xml/parsing/MarkupParser.initialize:()Lscala/xml/parsing/MarkupHandler;
Asciz	this;
Asciz	inp;
Asciz	Ljava/io/File;;
Asciz	preserveWS;
Asciz	Z;
Asciz	x$1;
Asciz	x$2;
Asciz	I;
Asciz	x$3;
Asciz	Lscala/io/Codec;;
Asciz	LocalVariableTable;
Asciz	fromSource;
Asciz	(Lscala/io/Source;Z)Lscala/xml/parsing/ConstructingParser;;
Asciz	Lscala/io/Source;;
Asciz	java/lang/Object;
class	java/lang/Object
Method	java/lang/Object."<init>":()V
NameAndType	MODULE$:Lscala/xml/parsing/ConstructingParser$;
Field	scala/xml/parsing/ConstructingParser$.MODULE$:Lscala/xml/parsing/ConstructingParser$;
Asciz	scala/ScalaObject;
class	scala/ScalaObject

{
public static final scala.xml.parsing.ConstructingParser$ MODULE$;
  Signature: Lscala/xml/parsing/ConstructingParser$;

public static {};
  Signature: ()V
  Code:
   Stack=1, Locals=0, Args_size=0
	new	class scala/xml/parsing/ConstructingParser$
	invokespecial	Method "<init>":()V
	return
  Labels:

public scala.xml.parsing.ConstructingParser fromFile(java.io.File, boolean);
  Signature: (Ljava/io/File;Z)Lscala/xml/parsing/ConstructingParser;
  Code:
   Stack=6, Locals=6, Args_size=3
	new	class scala/xml/parsing/ConstructingParser
	dup
	aload_1
	astore_3
	getstatic	Field scala/io/Source$.MODULE$:Lscala/io/Source$;
	invokevirtual	Method scala/io/Source$.fromFile$default$2:()I
	istore	4
	getstatic	Field scala/io/Source$.MODULE$:Lscala/io/Source$;
	aload_3
	iload	4
	invokevirtual	Method scala/io/Source$.fromFile$default$3:(Ljava/io/File;I)Lscala/io/Codec;
	astore	5
	getstatic	Field scala/io/Source$.MODULE$:Lscala/io/Source$;
	aload_3
	iload	4
	aload	5
	invokevirtual	Method scala/io/Source$.fromFile:(Ljava/io/File;ILscala/io/Codec;)Lscala/io/Source;
	iload_2
	invokespecial	Method scala/xml/parsing/ConstructingParser."<init>":(Lscala/io/Source;Z)V
	invokeinterface	InterfaceMethod scala/xml/parsing/MarkupParser.initialize:()Lscala/xml/parsing/MarkupHandler;
	checkcast	class scala/xml/parsing/ConstructingParser
	areturn
  Labels:
  LocalVariableTable: 
   Start  Length  Slot  Name   Signature
   0      49      0    this       Lscala/xml/parsing/ConstructingParser$;
   0      49      1    inp       Ljava/io/File;
   0      49      2    preserveWS       Z
   6      30      3    x$1       Ljava/io/File;
   14      22      4    x$2       I
   25      11      5    x$3       Lscala/io/Codec;


public scala.xml.parsing.ConstructingParser fromSource(scala.io.Source, boolean);
  Signature: (Lscala/io/Source;Z)Lscala/xml/parsing/ConstructingParser;
  Code:
   Stack=4, Locals=3, Args_size=3
	new	class scala/xml/parsing/ConstructingParser
	dup
	aload_1
	iload_2
	invokespecial	Method scala/xml/parsing/ConstructingParser."<init>":(Lscala/io/Source;Z)V
	invokeinterface	InterfaceMethod scala/xml/parsing/MarkupParser.initialize:()Lscala/xml/parsing/MarkupHandler;
	checkcast	class scala/xml/parsing/ConstructingParser
	areturn
  Labels:
  LocalVariableTable: 
   Start  Length  Slot  Name   Signature
   0      18      0    this       Lscala/xml/parsing/ConstructingParser$;
   0      18      1    inp       Lscala/io/Source;
   0      18      2    preserveWS       Z


private scala.xml.parsing.ConstructingParser$();
  Signature: ()V
  Code:
   Stack=1, Locals=1, Args_size=1
	aload_0
	invokespecial	Method java/lang/Object."<init>":()V
	aload_0
	putstatic	Field MODULE$:Lscala/xml/parsing/ConstructingParser$;
	return
  Labels:

}

