Compiled from "ExternalSources.scala"
public class scala.xml.parsing.ExternalSources$MyClass$1 extends scala.io.Source implements scala.ScalaObject
  SourceFile: "ExternalSources.scala"
  Scala: length = 0x
   
  InnerClass: 
   public #72= #21 of #71; //MyClass$1=class scala/xml/parsing/ExternalSources$MyClass$1 of class scala/xml/parsing/ExternalSources
   public final #73= #64 of #21; //$anon$1=class scala/xml/parsing/ExternalSources$MyClass$1$$anon$1 of class scala/xml/parsing/ExternalSources$MyClass$1
  minor version: 0
  major version: 49
  Constant pool:
const #1 = Asciz	SourceFile;
const #2 = Asciz	ExternalSources.scala;
const #3 = Asciz	str$1;
const #4 = Asciz	Lscala/collection/mutable/StringBuilder;;
const #5 = Asciz	url$1;
const #6 = Asciz	Ljava/net/URL;;
const #7 = Asciz	$outer;
const #8 = Asciz	Lscala/xml/parsing/ExternalSources;;
const #9 = Asciz	iter;
const #10 = Asciz	Ljava/lang/Object;;
const #11 = Asciz	<init>;
const #12 = Asciz	(Lscala/xml/parsing/ExternalSources;Ljava/net/URL;Lscala/collection/mutable/StringBuilder;)V;
const #13 = Asciz	Code;
const #14 = Asciz	LineNumberTable;
const #15 = Asciz	java/lang/NullPointerException;
const #16 = class	#15;	//  java/lang/NullPointerException
const #17 = Asciz	()V;
const #18 = NameAndType	#11:#17;//  "<init>":()V
const #19 = Method	#16.#18;	//  java/lang/NullPointerException."<init>":()V
const #20 = Asciz	scala/xml/parsing/ExternalSources$MyClass$1;
const #21 = class	#20;	//  scala/xml/parsing/ExternalSources$MyClass$1
const #22 = NameAndType	#7:#8;//  $outer:Lscala/xml/parsing/ExternalSources;
const #23 = Field	#21.#22;	//  scala/xml/parsing/ExternalSources$MyClass$1.$outer:Lscala/xml/parsing/ExternalSources;
const #24 = NameAndType	#5:#6;//  url$1:Ljava/net/URL;
const #25 = Field	#21.#24;	//  scala/xml/parsing/ExternalSources$MyClass$1.url$1:Ljava/net/URL;
const #26 = NameAndType	#3:#4;//  str$1:Lscala/collection/mutable/StringBuilder;
const #27 = Field	#21.#26;	//  scala/xml/parsing/ExternalSources$MyClass$1.str$1:Lscala/collection/mutable/StringBuilder;
const #28 = Asciz	scala/io/Source;
const #29 = class	#28;	//  scala/io/Source
const #30 = Method	#29.#18;	//  scala/io/Source."<init>":()V
const #31 = Asciz	newIter;
const #32 = Asciz	()Ljava/lang/Object;;
const #33 = NameAndType	#31:#32;//  newIter:()Ljava/lang/Object;
const #34 = Method	#21.#33;	//  scala/xml/parsing/ExternalSources$MyClass$1.newIter:()Ljava/lang/Object;
const #35 = NameAndType	#9:#10;//  iter:Ljava/lang/Object;
const #36 = Field	#21.#35;	//  scala/xml/parsing/ExternalSources$MyClass$1.iter:Ljava/lang/Object;
const #37 = Asciz	java/net/URL;
const #38 = class	#37;	//  java/net/URL
const #39 = Asciz	toExternalForm;
const #40 = Asciz	()Ljava/lang/String;;
const #41 = NameAndType	#39:#40;//  toExternalForm:()Ljava/lang/String;
const #42 = Method	#38.#41;	//  java/net/URL.toExternalForm:()Ljava/lang/String;
const #43 = Asciz	descr_$eq;
const #44 = Asciz	(Ljava/lang/String;)V;
const #45 = NameAndType	#43:#44;//  descr_$eq:(Ljava/lang/String;)V
const #46 = Method	#21.#45;	//  scala/xml/parsing/ExternalSources$MyClass$1.descr_$eq:(Ljava/lang/String;)V
const #47 = Asciz	this;
const #48 = Asciz	Lscala/xml/parsing/ExternalSources$MyClass$1;;
const #49 = Asciz	LocalVariableTable;
const #50 = Asciz	()Lscala/collection/Iterator;;
const #51 = NameAndType	#9:#32;//  iter:()Ljava/lang/Object;
const #52 = Method	#21.#51;	//  scala/xml/parsing/ExternalSources$MyClass$1.iter:()Ljava/lang/Object;
const #53 = Asciz	scala/collection/Iterator;
const #54 = class	#53;	//  scala/collection/Iterator
const #55 = Asciz	scala$xml$parsing$ExternalSources$MyClass$$$outer;
const #56 = Asciz	()Lscala/xml/parsing/ExternalSources;;
const #57 = Asciz	reset;
const #58 = Asciz	()Lscala/io/Source;;
const #59 = NameAndType	#55:#56;//  scala$xml$parsing$ExternalSources$MyClass$$$outer:()Lscala/xml/parsing/ExternalSources;
const #60 = Method	#21.#59;	//  scala/xml/parsing/ExternalSources$MyClass$1.scala$xml$parsing$ExternalSources$MyClass$$$outer:()Lscala/xml/parsing/ExternalSources;
const #61 = NameAndType	#11:#12;//  "<init>":(Lscala/xml/parsing/ExternalSources;Ljava/net/URL;Lscala/collection/mutable/StringBuilder;)V
const #62 = Method	#21.#61;	//  scala/xml/parsing/ExternalSources$MyClass$1."<init>":(Lscala/xml/parsing/ExternalSources;Ljava/net/URL;Lscala/collection/mutable/StringBuilder;)V
const #63 = Asciz	scala/xml/parsing/ExternalSources$MyClass$1$$anon$1;
const #64 = class	#63;	//  scala/xml/parsing/ExternalSources$MyClass$1$$anon$1
const #65 = Asciz	(Lscala/xml/parsing/ExternalSources$MyClass$1;)V;
const #66 = NameAndType	#11:#65;//  "<init>":(Lscala/xml/parsing/ExternalSources$MyClass$1;)V
const #67 = Method	#64.#66;	//  scala/xml/parsing/ExternalSources$MyClass$1$$anon$1."<init>":(Lscala/xml/parsing/ExternalSources$MyClass$1;)V
const #68 = Asciz	Scala;
const #69 = Asciz	InnerClasses;
const #70 = Asciz	scala/xml/parsing/ExternalSources;
const #71 = class	#70;	//  scala/xml/parsing/ExternalSources
const #72 = Asciz	MyClass$1;
const #73 = Asciz	$anon$1;
const #74 = Asciz	scala/ScalaObject;
const #75 = class	#74;	//  scala/ScalaObject

{
public final scala.collection.mutable.StringBuilder str$1;

public final scala.xml.parsing.ExternalSources $outer;

public scala.xml.parsing.ExternalSources$MyClass$1(scala.xml.parsing.ExternalSources, java.net.URL, scala.collection.mutable.StringBuilder);
  Code:
   Stack=2, Locals=4, Args_size=4
   0:	aload_1
   1:	ifnonnull	12
   4:	new	#16; //class java/lang/NullPointerException
   7:	dup
   8:	invokespecial	#19; //Method java/lang/NullPointerException."<init>":()V
   11:	athrow
   12:	aload_0
   13:	aload_1
   14:	putfield	#23; //Field $outer:Lscala/xml/parsing/ExternalSources;
   17:	aload_0
   18:	aload_2
   19:	putfield	#25; //Field url$1:Ljava/net/URL;
   22:	aload_0
   23:	aload_3
   24:	putfield	#27; //Field str$1:Lscala/collection/mutable/StringBuilder;
   27:	aload_0
   28:	invokespecial	#30; //Method scala/io/Source."<init>":()V
   31:	aload_0
   32:	aload_0
   33:	invokevirtual	#34; //Method newIter:()Ljava/lang/Object;
   36:	putfield	#36; //Field iter:Ljava/lang/Object;
   39:	aload_0
   40:	aload_2
   41:	invokevirtual	#42; //Method java/net/URL.toExternalForm:()Ljava/lang/String;
   44:	invokevirtual	#46; //Method descr_$eq:(Ljava/lang/String;)V
   47:	return
  LineNumberTable: 
   line 45: 0
   line 54: 31
   line 58: 39

  LocalVariableTable: 
   Start  Length  Slot  Name   Signature
   0      48      0    this       Lscala/xml/parsing/ExternalSources$MyClass$1;
   0      48      1    $outer       Lscala/xml/parsing/ExternalSources;


public scala.collection.Iterator iter();
  Code:
   Stack=1, Locals=1, Args_size=1
   0:	aload_0
   1:	invokevirtual	#52; //Method iter:()Ljava/lang/Object;
   4:	checkcast	#54; //class scala/collection/Iterator
   7:	areturn
  LineNumberTable: 
   line 45: 0


public scala.xml.parsing.ExternalSources scala$xml$parsing$ExternalSources$MyClass$$$outer();
  Code:
   Stack=1, Locals=1, Args_size=1
   0:	aload_0
   1:	getfield	#23; //Field $outer:Lscala/xml/parsing/ExternalSources;
   4:	areturn
  LineNumberTable: 
   line 45: 0


public scala.io.Source reset();
  Code:
   Stack=5, Locals=1, Args_size=1
   0:	new	#21; //class scala/xml/parsing/ExternalSources$MyClass$1
   3:	dup
   4:	aload_0
   5:	invokevirtual	#60; //Method scala$xml$parsing$ExternalSources$MyClass$$$outer:()Lscala/xml/parsing/ExternalSources;
   8:	aload_0
   9:	getfield	#25; //Field url$1:Ljava/net/URL;
   12:	aload_0
   13:	getfield	#27; //Field str$1:Lscala/collection/mutable/StringBuilder;
   16:	invokespecial	#62; //Method "<init>":(Lscala/xml/parsing/ExternalSources;Ljava/net/URL;Lscala/collection/mutable/StringBuilder;)V
   19:	areturn
  LineNumberTable: 
   line 56: 0


public java.lang.Object iter();
  Code:
   Stack=1, Locals=1, Args_size=1
   0:	aload_0
   1:	getfield	#36; //Field iter:Ljava/lang/Object;
   4:	areturn
  LineNumberTable: 
   line 54: 0


public java.lang.Object newIter();
  Code:
   Stack=3, Locals=1, Args_size=1
   0:	new	#64; //class scala/xml/parsing/ExternalSources$MyClass$1$$anon$1
   3:	dup
   4:	aload_0
   5:	invokespecial	#67; //Method scala/xml/parsing/ExternalSources$MyClass$1$$anon$1."<init>":(Lscala/xml/parsing/ExternalSources$MyClass$1;)V
   8:	areturn
  LineNumberTable: 
   line 47: 0


}

