Compiled from "ExternalSources.scala"
public abstract class scala.xml.parsing.ExternalSources$class extends java.lang.Object
  SourceFile: "ExternalSources.scala"
  Scala: length = 0x
   
  InnerClass: 
   public final $anonfun$1=class scala/io/Source$$anonfun$1 of class scala/io/Source
  minor version: 0
  major version: 49
  Constant pool:
Asciz	SourceFile;
Asciz	ExternalSources.scala;
Asciz	$init$;
Asciz	(Lscala/xml/parsing/MarkupHandler;)V;
Asciz	Code;
Asciz	LineNumberTable;
Asciz	$this;
Asciz	Lscala/xml/parsing/MarkupHandler;;
Asciz	LocalVariableTable;
Asciz	gd1$1;
Asciz	(Lscala/xml/parsing/MarkupHandler;Ljava/lang/String;)Z;
Asciz	file:;
String	file:
Asciz	java/lang/String;
class	java/lang/String
Asciz	startsWith;
Asciz	(Ljava/lang/String;)Z;
NameAndType	startsWith:(Ljava/lang/String;)Z
Method	java/lang/String.startsWith:(Ljava/lang/String;)Z
Asciz	externalSource;
Asciz	(Lscala/xml/parsing/MarkupHandler;Ljava/lang/String;)Lscala/io/Source;;
Asciz	http:;
String	http:
Asciz	java/net/URL;
class	java/net/URL
Asciz	<init>;
Asciz	(Ljava/lang/String;)V;
NameAndType	"<init>":(Ljava/lang/String;)V
Method	java/net/URL."<init>":(Ljava/lang/String;)V
Asciz	java/nio/charset/Charset;
class	java/nio/charset/Charset
Asciz	defaultCharset;
Asciz	()Ljava/nio/charset/Charset;;
NameAndType	defaultCharset:()Ljava/nio/charset/Charset;
Method	java/nio/charset/Charset.defaultCharset:()Ljava/nio/charset/Charset;
Asciz	scala/io/Codec;
class	scala/io/Codec
Asciz	(Ljava/nio/charset/Charset;)V;
NameAndType	"<init>":(Ljava/nio/charset/Charset;)V
Method	scala/io/Codec."<init>":(Ljava/nio/charset/Charset;)V
Asciz	scala/io/Source$;
class	scala/io/Source$
Asciz	MODULE$;
Asciz	Lscala/io/Source$;;
NameAndType	MODULE$:Lscala/io/Source$;
Field	scala/io/Source$.MODULE$:Lscala/io/Source$;
Asciz	openStream;
Asciz	()Ljava/io/InputStream;;
NameAndType	openStream:()Ljava/io/InputStream;
Method	java/net/URL.openStream:()Ljava/io/InputStream;
Asciz	DefaultBufSize;
Asciz	()I;
NameAndType	DefaultBufSize:()I
Method	scala/io/Source$.DefaultBufSize:()I
Asciz	java/lang/Object;
class	java/lang/Object
Asciz	equals;
Asciz	(Ljava/lang/Object;)Z;
NameAndType	equals:(Ljava/lang/Object;)Z
Method	java/lang/Object.equals:(Ljava/lang/Object;)Z
Asciz	scala/io/Source$$anonfun$1;
class	scala/io/Source$$anonfun$1
Asciz	(Ljava/io/InputStream;ILscala/Function0;Lscala/Function0;Lscala/io/Codec;)V;
NameAndType	"<init>":(Ljava/io/InputStream;ILscala/Function0;Lscala/Function0;Lscala/io/Codec;)V
Method	scala/io/Source$$anonfun$1."<init>":(Ljava/io/InputStream;ILscala/Function0;Lscala/Function0;Lscala/io/Codec;)V
Asciz	scala/io/BufferedSource;
class	scala/io/BufferedSource
Asciz	(Ljava/io/InputStream;Lscala/io/Codec;)V;
NameAndType	"<init>":(Ljava/io/InputStream;Lscala/io/Codec;)V
Method	scala/io/BufferedSource."<init>":(Ljava/io/InputStream;Lscala/io/Codec;)V
Asciz	withReset;
Asciz	(Lscala/Function0;)Lscala/io/Source;;
NameAndType	withReset:(Lscala/Function0;)Lscala/io/Source;
Method	scala/io/BufferedSource.withReset:(Lscala/Function0;)Lscala/io/Source;
Asciz	scala/io/Source;
class	scala/io/Source
Asciz	withClose;
NameAndType	withClose:(Lscala/Function0;)Lscala/io/Source;
Method	scala/io/Source.withClose:(Lscala/Function0;)Lscala/io/Source;
Asciz	scala/xml/parsing/MarkupParser;
class	scala/xml/parsing/MarkupParser
Asciz	input;
Asciz	()Lscala/io/Source;;
NameAndType	input:()Lscala/io/Source;
InterfaceMethod	scala/xml/parsing/MarkupParser.input:()Lscala/io/Source;
Asciz	descr;
Asciz	()Ljava/lang/String;;
NameAndType	descr:()Ljava/lang/String;
Method	scala/io/Source.descr:()Ljava/lang/String;
Asciz	scala/xml/parsing/ExternalSources$class;
class	scala/xml/parsing/ExternalSources$class
NameAndType	gd1$1:(Lscala/xml/parsing/MarkupHandler;Ljava/lang/String;)Z
Method	scala/xml/parsing/ExternalSources$class.gd1$1:(Lscala/xml/parsing/MarkupHandler;Ljava/lang/String;)Z
Asciz	scala/collection/immutable/StringOps;
class	scala/collection/immutable/StringOps
Method	scala/collection/immutable/StringOps."<init>":(Ljava/lang/String;)V
Asciz	scala/collection/IndexedSeqLike$class;
class	scala/collection/IndexedSeqLike$class
Asciz	drop;
Asciz	(Lscala/collection/IndexedSeqLike;I)Ljava/lang/Object;;
NameAndType	drop:(Lscala/collection/IndexedSeqLike;I)Ljava/lang/Object;
Method	scala/collection/IndexedSeqLike$class.drop:(Lscala/collection/IndexedSeqLike;I)Ljava/lang/Object;
Asciz	java/io/File;
class	java/io/File
Asciz	separator;
Asciz	Ljava/lang/String;;
NameAndType	separator:Ljava/lang/String;
Field	java/io/File.separator:Ljava/lang/String;
Asciz	lastIndexOf;
Asciz	(Ljava/lang/String;)I;
NameAndType	lastIndexOf:(Ljava/lang/String;)I
Method	java/lang/String.lastIndexOf:(Ljava/lang/String;)I
Asciz	take;
NameAndType	take:(Lscala/collection/IndexedSeqLike;I)Ljava/lang/Object;
Method	scala/collection/IndexedSeqLike$class.take:(Lscala/collection/IndexedSeqLike;I)Ljava/lang/Object;
Asciz	scala/collection/mutable/StringBuilder;
class	scala/collection/mutable/StringBuilder
Asciz	()V;
NameAndType	"<init>":()V
Method	scala/collection/mutable/StringBuilder."<init>":()V
Asciz	append;
Asciz	(Ljava/lang/Object;)Lscala/collection/mutable/StringBuilder;;
NameAndType	append:(Ljava/lang/Object;)Lscala/collection/mutable/StringBuilder;
Method	scala/collection/mutable/StringBuilder.append:(Ljava/lang/Object;)Lscala/collection/mutable/StringBuilder;
Asciz	toString;
NameAndType	toString:()Ljava/lang/String;
Method	scala/collection/mutable/StringBuilder.toString:()Ljava/lang/String;
Asciz	fromPath;
Asciz	(Ljava/lang/String;Lscala/io/Codec;)Lscala/io/Source;;
NameAndType	fromPath:(Ljava/lang/String;Lscala/io/Codec;)Lscala/io/Source;
Method	scala/io/Source$.fromPath:(Ljava/lang/String;Lscala/io/Codec;)Lscala/io/Source;
Asciz	systemId;
Asciz	x$1;
Asciz	Ljava/net/URL;;
Asciz	$inlThis3;
Asciz	Ljava/lang/Object;;
Asciz	bufferSize$10;
Asciz	I;
Asciz	reset$10;
Asciz	Lscala/Function0;;
Asciz	inputStream$10;
Asciz	Ljava/io/InputStream;;
Asciz	x$2;
Asciz	Lscala/io/Codec;;
Asciz	resetFn0;
Asciz	close$10;
Asciz	temp1;
Asciz	fileStr;
Asciz	x$3;
Asciz	x$4;
Asciz	Scala;
Asciz	InnerClasses;
Asciz	$anonfun$1;

{
public static void $init$(scala.xml.parsing.MarkupHandler);
  Signature: (Lscala/xml/parsing/MarkupHandler;)V
  Code:
   Stack=0, Locals=1, Args_size=1
	return
  Labels:
  LocalVariableTable: 
   Start  Length  Slot  Name   Signature
   0      1      0    $this       Lscala/xml/parsing/MarkupHandler;


private static final boolean gd1$1(scala.xml.parsing.MarkupHandler, java.lang.String);
  Signature: (Lscala/xml/parsing/MarkupHandler;Ljava/lang/String;)Z
  Code:
   Stack=2, Locals=2, Args_size=2
	aload_1
	ldc	String file:
	invokevirtual	Method java/lang/String.startsWith:(Ljava/lang/String;)Z
	ireturn
  Labels:
  LocalVariableTable: 
   Start  Length  Slot  Name   Signature
   0      7      0    $this       Lscala/xml/parsing/MarkupHandler;


public static scala.io.Source externalSource(scala.xml.parsing.MarkupHandler, java.lang.String);
  Signature: (Lscala/xml/parsing/MarkupHandler;Ljava/lang/String;)Lscala/io/Source;
  Code:
   Stack=7, Locals=20, Args_size=2
	aload_1
	ldc	String http:
	invokevirtual	Method java/lang/String.startsWith:(Ljava/lang/String;)Z
	ifeq	l1 // aload_0
	new	class java/net/URL
	dup
	aload_1
	invokespecial	Method java/net/URL."<init>":(Ljava/lang/String;)V
	astore_3
	invokestatic	Method java/nio/charset/Charset.defaultCharset:()Ljava/nio/charset/Charset;
	astore_2
	new	class scala/io/Codec
	dup
	aload_2
	invokespecial	Method scala/io/Codec."<init>":(Ljava/nio/charset/Charset;)V
	astore	8
	getstatic	Field scala/io/Source$.MODULE$:Lscala/io/Source$;
	astore	4
	aload_3
	invokevirtual	Method java/net/URL.openStream:()Ljava/io/InputStream;
	aload	4
	invokevirtual	Method scala/io/Source$.DefaultBufSize:()I
	aconst_null
	aconst_null
	astore	10
	astore	6
	istore	5
	astore	7
	aload	6
	dup
	pop
	ifnull	l2 // new
	aload	6
	aconst_null
	invokevirtual	Method java/lang/Object.equals:(Ljava/lang/Object;)Z
	ifeq	l3 // aload
l2	new	class scala/io/Source$$anonfun$1
	dup
	aload	7
	iload	5
	aload	6
	aload	10
	aload	8
	invokespecial	Method scala/io/Source$$anonfun$1."<init>":(Ljava/io/InputStream;ILscala/Function0;Lscala/Function0;Lscala/io/Codec;)V
	goto	l4 // astore
l3	aload	6
l4	astore	9
	new	class scala/io/BufferedSource
	dup
	aload	7
	aload	8
	invokespecial	Method scala/io/BufferedSource."<init>":(Ljava/io/InputStream;Lscala/io/Codec;)V
	aload	9
	invokevirtual	Method scala/io/BufferedSource.withReset:(Lscala/Function0;)Lscala/io/Source;
	aload	10
	invokevirtual	Method scala/io/Source.withClose:(Lscala/Function0;)Lscala/io/Source;
	areturn
l1	aload_0
	checkcast	class scala/xml/parsing/MarkupParser
	invokeinterface	InterfaceMethod scala/xml/parsing/MarkupParser.input:()Lscala/io/Source;
	invokevirtual	Method scala/io/Source.descr:()Ljava/lang/String;
	astore	13
	aload_0
	aload	13
	invokestatic	Method gd1$1:(Lscala/xml/parsing/MarkupHandler;Ljava/lang/String;)Z
	ifeq	l5 // new
	new	class scala/collection/immutable/StringOps
	dup
	aload	13
	invokespecial	Method scala/collection/immutable/StringOps."<init>":(Ljava/lang/String;)V
	iconst_5
	istore	12
	astore	11
	aload	11
	iload	12
	invokestatic	Method scala/collection/IndexedSeqLike$class.drop:(Lscala/collection/IndexedSeqLike;I)Ljava/lang/Object;
	checkcast	class java/lang/String
	goto	l6 // astore
l5	new	class scala/collection/immutable/StringOps
	dup
	aload	13
	invokespecial	Method scala/collection/immutable/StringOps."<init>":(Ljava/lang/String;)V
	aload	13
	getstatic	Field java/io/File.separator:Ljava/lang/String;
	invokevirtual	Method java/lang/String.lastIndexOf:(Ljava/lang/String;)I
	iconst_1
	iadd
	istore	15
	astore	14
	aload	14
	iload	15
	invokestatic	Method scala/collection/IndexedSeqLike$class.take:(Lscala/collection/IndexedSeqLike;I)Ljava/lang/Object;
	checkcast	class java/lang/String
l6	astore	16
	new	class scala/collection/mutable/StringBuilder
	dup
	invokespecial	Method scala/collection/mutable/StringBuilder."<init>":()V
	aload	16
	invokevirtual	Method scala/collection/mutable/StringBuilder.append:(Ljava/lang/Object;)Lscala/collection/mutable/StringBuilder;
	aload_1
	invokevirtual	Method scala/collection/mutable/StringBuilder.append:(Ljava/lang/Object;)Lscala/collection/mutable/StringBuilder;
	invokevirtual	Method scala/collection/mutable/StringBuilder.toString:()Ljava/lang/String;
	astore	18
	invokestatic	Method java/nio/charset/Charset.defaultCharset:()Ljava/nio/charset/Charset;
	astore	17
	new	class scala/io/Codec
	dup
	aload	17
	invokespecial	Method scala/io/Codec."<init>":(Ljava/nio/charset/Charset;)V
	astore	19
	getstatic	Field scala/io/Source$.MODULE$:Lscala/io/Source$;
	aload	18
	aload	19
	invokevirtual	Method scala/io/Source$.fromPath:(Ljava/lang/String;Lscala/io/Codec;)Lscala/io/Source;
	areturn
  Labels:
   	l2 = 72 // new
   	l3 = 92 // aload
   	l4 = 94 // astore
   	l1 = 118 // aload_0
   	l5 = 168 // new
   	l6 = 201 // astore
  LocalVariableTable: 
   Start  Length  Slot  Name   Signature
   0      251      0    $this       Lscala/xml/parsing/MarkupHandler;
   0      251      1    systemId       Ljava/lang/String;
   18      100      3    x$1       Ljava/net/URL;
   63      55      4    $inlThis3       Ljava/lang/Object;
   63      55      5    bufferSize$10       I
   63      55      6    reset$10       Lscala/Function0;
   63      55      7    inputStream$10       Ljava/io/InputStream;
   32      86      8    x$2       Lscala/io/Codec;
   96      21      9    resetFn0       Lscala/Function0;
   63      55      10    close$10       Lscala/Function0;
   132      119      13    temp1       Ljava/lang/String;
   203      47      16    fileStr       Ljava/lang/String;
   224      26      18    x$3       Ljava/lang/String;
   240      10      19    x$4       Lscala/io/Codec;


}

