Compiled from "ExternalSources.scala"
public abstract class scala.xml.parsing.ExternalSources$class extends java.lang.Object
  SourceFile: "ExternalSources.scala"
  Scala: length = 0x
   
  InnerClass: 
   public final #158= #62 of #76; //$anonfun$1=class scala/io/Source$$anonfun$1 of class scala/io/Source
  minor version: 0
  major version: 49
  Constant pool:
const #1 = Asciz	SourceFile;
const #2 = Asciz	ExternalSources.scala;
const #3 = Asciz	$init$;
const #4 = Asciz	(Lscala/xml/parsing/ExternalSources;)V;
const #5 = Asciz	Code;
const #6 = Asciz	LineNumberTable;
const #7 = Asciz	$this;
const #8 = Asciz	Lscala/xml/parsing/ExternalSources;;
const #9 = Asciz	LocalVariableTable;
const #10 = Asciz	gd1$1;
const #11 = Asciz	(Lscala/xml/parsing/ExternalSources;Ljava/lang/String;)Z;
const #12 = Asciz	file:;
const #13 = String	#12;	//  file:
const #14 = Asciz	java/lang/String;
const #15 = class	#14;	//  java/lang/String
const #16 = Asciz	startsWith;
const #17 = Asciz	(Ljava/lang/String;)Z;
const #18 = NameAndType	#16:#17;//  startsWith:(Ljava/lang/String;)Z
const #19 = Method	#15.#18;	//  java/lang/String.startsWith:(Ljava/lang/String;)Z
const #20 = Asciz	externalSource;
const #21 = Asciz	(Lscala/xml/parsing/ExternalSources;Ljava/lang/String;)Lscala/io/Source;;
const #22 = Asciz	http:;
const #23 = String	#22;	//  http:
const #24 = Asciz	java/net/URL;
const #25 = class	#24;	//  java/net/URL
const #26 = Asciz	<init>;
const #27 = Asciz	(Ljava/lang/String;)V;
const #28 = NameAndType	#26:#27;//  "<init>":(Ljava/lang/String;)V
const #29 = Method	#25.#28;	//  java/net/URL."<init>":(Ljava/lang/String;)V
const #30 = Asciz	java/nio/charset/Charset;
const #31 = class	#30;	//  java/nio/charset/Charset
const #32 = Asciz	defaultCharset;
const #33 = Asciz	()Ljava/nio/charset/Charset;;
const #34 = NameAndType	#32:#33;//  defaultCharset:()Ljava/nio/charset/Charset;
const #35 = Method	#31.#34;	//  java/nio/charset/Charset.defaultCharset:()Ljava/nio/charset/Charset;
const #36 = Asciz	scala/io/Codec;
const #37 = class	#36;	//  scala/io/Codec
const #38 = Asciz	(Ljava/nio/charset/Charset;)V;
const #39 = NameAndType	#26:#38;//  "<init>":(Ljava/nio/charset/Charset;)V
const #40 = Method	#37.#39;	//  scala/io/Codec."<init>":(Ljava/nio/charset/Charset;)V
const #41 = Asciz	scala/io/Source$;
const #42 = class	#41;	//  scala/io/Source$
const #43 = Asciz	MODULE$;
const #44 = Asciz	Lscala/io/Source$;;
const #45 = NameAndType	#43:#44;//  MODULE$:Lscala/io/Source$;
const #46 = Field	#42.#45;	//  scala/io/Source$.MODULE$:Lscala/io/Source$;
const #47 = Asciz	openStream;
const #48 = Asciz	()Ljava/io/InputStream;;
const #49 = NameAndType	#47:#48;//  openStream:()Ljava/io/InputStream;
const #50 = Method	#25.#49;	//  java/net/URL.openStream:()Ljava/io/InputStream;
const #51 = Asciz	DefaultBufSize;
const #52 = Asciz	()I;
const #53 = NameAndType	#51:#52;//  DefaultBufSize:()I
const #54 = Method	#42.#53;	//  scala/io/Source$.DefaultBufSize:()I
const #55 = Asciz	java/lang/Object;
const #56 = class	#55;	//  java/lang/Object
const #57 = Asciz	equals;
const #58 = Asciz	(Ljava/lang/Object;)Z;
const #59 = NameAndType	#57:#58;//  equals:(Ljava/lang/Object;)Z
const #60 = Method	#56.#59;	//  java/lang/Object.equals:(Ljava/lang/Object;)Z
const #61 = Asciz	scala/io/Source$$anonfun$1;
const #62 = class	#61;	//  scala/io/Source$$anonfun$1
const #63 = Asciz	(Ljava/io/InputStream;ILscala/Function0;Lscala/Function0;Lscala/io/Codec;)V;
const #64 = NameAndType	#26:#63;//  "<init>":(Ljava/io/InputStream;ILscala/Function0;Lscala/Function0;Lscala/io/Codec;)V
const #65 = Method	#62.#64;	//  scala/io/Source$$anonfun$1."<init>":(Ljava/io/InputStream;ILscala/Function0;Lscala/Function0;Lscala/io/Codec;)V
const #66 = Asciz	scala/io/BufferedSource;
const #67 = class	#66;	//  scala/io/BufferedSource
const #68 = Asciz	(Ljava/io/InputStream;Lscala/io/Codec;)V;
const #69 = NameAndType	#26:#68;//  "<init>":(Ljava/io/InputStream;Lscala/io/Codec;)V
const #70 = Method	#67.#69;	//  scala/io/BufferedSource."<init>":(Ljava/io/InputStream;Lscala/io/Codec;)V
const #71 = Asciz	withReset;
const #72 = Asciz	(Lscala/Function0;)Lscala/io/Source;;
const #73 = NameAndType	#71:#72;//  withReset:(Lscala/Function0;)Lscala/io/Source;
const #74 = Method	#67.#73;	//  scala/io/BufferedSource.withReset:(Lscala/Function0;)Lscala/io/Source;
const #75 = Asciz	scala/io/Source;
const #76 = class	#75;	//  scala/io/Source
const #77 = Asciz	withClose;
const #78 = NameAndType	#77:#72;//  withClose:(Lscala/Function0;)Lscala/io/Source;
const #79 = Method	#76.#78;	//  scala/io/Source.withClose:(Lscala/Function0;)Lscala/io/Source;
const #80 = Asciz	scala/xml/parsing/MarkupParser;
const #81 = class	#80;	//  scala/xml/parsing/MarkupParser
const #82 = Asciz	input;
const #83 = Asciz	()Lscala/io/Source;;
const #84 = NameAndType	#82:#83;//  input:()Lscala/io/Source;
const #85 = InterfaceMethod	#81.#84;	//  scala/xml/parsing/MarkupParser.input:()Lscala/io/Source;
const #86 = Asciz	descr;
const #87 = Asciz	()Ljava/lang/String;;
const #88 = NameAndType	#86:#87;//  descr:()Ljava/lang/String;
const #89 = Method	#76.#88;	//  scala/io/Source.descr:()Ljava/lang/String;
const #90 = Asciz	scala/xml/parsing/ExternalSources$class;
const #91 = class	#90;	//  scala/xml/parsing/ExternalSources$class
const #92 = NameAndType	#10:#11;//  gd1$1:(Lscala/xml/parsing/ExternalSources;Ljava/lang/String;)Z
const #93 = Method	#91.#92;	//  scala/xml/parsing/ExternalSources$class.gd1$1:(Lscala/xml/parsing/ExternalSources;Ljava/lang/String;)Z
const #94 = Asciz	scala/collection/immutable/StringOps;
const #95 = class	#94;	//  scala/collection/immutable/StringOps
const #96 = Method	#95.#28;	//  scala/collection/immutable/StringOps."<init>":(Ljava/lang/String;)V
const #97 = Asciz	scala/collection/IndexedSeqLike;
const #98 = class	#97;	//  scala/collection/IndexedSeqLike
const #99 = Asciz	drop;
const #100 = Asciz	(I)Ljava/lang/Object;;
const #101 = NameAndType	#99:#100;//  drop:(I)Ljava/lang/Object;
const #102 = InterfaceMethod	#98.#101;	//  scala/collection/IndexedSeqLike.drop:(I)Ljava/lang/Object;
const #103 = Asciz	java/io/File;
const #104 = class	#103;	//  java/io/File
const #105 = Asciz	separator;
const #106 = Asciz	Ljava/lang/String;;
const #107 = NameAndType	#105:#106;//  separator:Ljava/lang/String;
const #108 = Field	#104.#107;	//  java/io/File.separator:Ljava/lang/String;
const #109 = Asciz	lastIndexOf;
const #110 = Asciz	(Ljava/lang/String;)I;
const #111 = NameAndType	#109:#110;//  lastIndexOf:(Ljava/lang/String;)I
const #112 = Method	#15.#111;	//  java/lang/String.lastIndexOf:(Ljava/lang/String;)I
const #113 = Asciz	take;
const #114 = NameAndType	#113:#100;//  take:(I)Ljava/lang/Object;
const #115 = InterfaceMethod	#98.#114;	//  scala/collection/IndexedSeqLike.take:(I)Ljava/lang/Object;
const #116 = Asciz	scala/collection/mutable/StringBuilder;
const #117 = class	#116;	//  scala/collection/mutable/StringBuilder
const #118 = Asciz	()V;
const #119 = NameAndType	#26:#118;//  "<init>":()V
const #120 = Method	#117.#119;	//  scala/collection/mutable/StringBuilder."<init>":()V
const #121 = Asciz	append;
const #122 = Asciz	(Ljava/lang/Object;)Lscala/collection/mutable/StringBuilder;;
const #123 = NameAndType	#121:#122;//  append:(Ljava/lang/Object;)Lscala/collection/mutable/StringBuilder;
const #124 = Method	#117.#123;	//  scala/collection/mutable/StringBuilder.append:(Ljava/lang/Object;)Lscala/collection/mutable/StringBuilder;
const #125 = Asciz	toString;
const #126 = NameAndType	#125:#87;//  toString:()Ljava/lang/String;
const #127 = Method	#117.#126;	//  scala/collection/mutable/StringBuilder.toString:()Ljava/lang/String;
const #128 = Method	#104.#28;	//  java/io/File."<init>":(Ljava/lang/String;)V
const #129 = Asciz	fromFile;
const #130 = Asciz	(Ljava/io/File;ILscala/io/Codec;)Lscala/io/Source;;
const #131 = NameAndType	#129:#130;//  fromFile:(Ljava/io/File;ILscala/io/Codec;)Lscala/io/Source;
const #132 = Method	#42.#131;	//  scala/io/Source$.fromFile:(Ljava/io/File;ILscala/io/Codec;)Lscala/io/Source;
const #133 = Asciz	scala/MatchError;
const #134 = class	#133;	//  scala/MatchError
const #135 = Method	#15.#126;	//  java/lang/String.toString:()Ljava/lang/String;
const #136 = Method	#134.#28;	//  scala/MatchError."<init>":(Ljava/lang/String;)V
const #137 = Asciz	systemId;
const #138 = Asciz	x$1;
const #139 = Asciz	Ljava/net/URL;;
const #140 = Asciz	$inlThis3;
const #141 = Asciz	Ljava/lang/Object;;
const #142 = Asciz	bufferSize$10;
const #143 = Asciz	I;
const #144 = Asciz	reset$10;
const #145 = Asciz	Lscala/Function0;;
const #146 = Asciz	inputStream$10;
const #147 = Asciz	Ljava/io/InputStream;;
const #148 = Asciz	x$2;
const #149 = Asciz	Lscala/io/Codec;;
const #150 = Asciz	resetFn0;
const #151 = Asciz	close$10;
const #152 = Asciz	fileStr;
const #153 = Asciz	x$3;
const #154 = Asciz	x$4;
const #155 = Asciz	temp1;
const #156 = Asciz	Scala;
const #157 = Asciz	InnerClasses;
const #158 = Asciz	$anonfun$1;

{
public static void $init$(scala.xml.parsing.ExternalSources);
  Code:
   Stack=0, Locals=1, Args_size=1
   0:	return
  LineNumberTable: 
   line 25: 0

  LocalVariableTable: 
   Start  Length  Slot  Name   Signature
   0      1      0    $this       Lscala/xml/parsing/ExternalSources;


public static scala.io.Source externalSource(scala.xml.parsing.ExternalSources, java.lang.String);
  Code:
   Stack=7, Locals=17, Args_size=2
   0:	aload_1
   1:	ldc	#23; //String http:
   3:	invokevirtual	#19; //Method java/lang/String.startsWith:(Ljava/lang/String;)Z
   6:	ifeq	118
   9:	new	#25; //class java/net/URL
   12:	dup
   13:	aload_1
   14:	invokespecial	#29; //Method java/net/URL."<init>":(Ljava/lang/String;)V
   17:	astore_3
   18:	invokestatic	#35; //Method java/nio/charset/Charset.defaultCharset:()Ljava/nio/charset/Charset;
   21:	astore_2
   22:	new	#37; //class scala/io/Codec
   25:	dup
   26:	aload_2
   27:	invokespecial	#40; //Method scala/io/Codec."<init>":(Ljava/nio/charset/Charset;)V
   30:	astore	8
   32:	getstatic	#46; //Field scala/io/Source$.MODULE$:Lscala/io/Source$;
   35:	astore	4
   37:	aload_3
   38:	invokevirtual	#50; //Method java/net/URL.openStream:()Ljava/io/InputStream;
   41:	aload	4
   43:	invokevirtual	#54; //Method scala/io/Source$.DefaultBufSize:()I
   46:	aconst_null
   47:	aconst_null
   48:	astore	10
   50:	astore	6
   52:	istore	5
   54:	astore	7
   56:	aload	6
   58:	dup
   59:	pop
   60:	ifnull	72
   63:	aload	6
   65:	aconst_null
   66:	invokevirtual	#60; //Method java/lang/Object.equals:(Ljava/lang/Object;)Z
   69:	ifeq	92
   72:	new	#62; //class scala/io/Source$$anonfun$1
   75:	dup
   76:	aload	7
   78:	iload	5
   80:	aload	6
   82:	aload	10
   84:	aload	8
   86:	invokespecial	#65; //Method scala/io/Source$$anonfun$1."<init>":(Ljava/io/InputStream;ILscala/Function0;Lscala/Function0;Lscala/io/Codec;)V
   89:	goto	94
   92:	aload	6
   94:	astore	9
   96:	new	#67; //class scala/io/BufferedSource
   99:	dup
   100:	aload	7
   102:	aload	8
   104:	invokespecial	#70; //Method scala/io/BufferedSource."<init>":(Ljava/io/InputStream;Lscala/io/Codec;)V
   107:	aload	9
   109:	invokevirtual	#74; //Method scala/io/BufferedSource.withReset:(Lscala/Function0;)Lscala/io/Source;
   112:	aload	10
   114:	invokevirtual	#79; //Method scala/io/Source.withClose:(Lscala/Function0;)Lscala/io/Source;
   117:	areturn
   118:	aload_0
   119:	checkcast	#81; //class scala/xml/parsing/MarkupParser
   122:	invokeinterface	#85,  1; //InterfaceMethod scala/xml/parsing/MarkupParser.input:()Lscala/io/Source;
   127:	invokevirtual	#89; //Method scala/io/Source.descr:()Ljava/lang/String;
   130:	astore	16
   132:	aload_0
   133:	aload	16
   135:	invokestatic	#93; //Method gd1$1:(Lscala/xml/parsing/ExternalSources;Ljava/lang/String;)Z
   138:	ifeq	162
   141:	new	#95; //class scala/collection/immutable/StringOps
   144:	dup
   145:	aload	16
   147:	invokespecial	#96; //Method scala/collection/immutable/StringOps."<init>":(Ljava/lang/String;)V
   150:	iconst_5
   151:	invokeinterface	#102,  2; //InterfaceMethod scala/collection/IndexedSeqLike.drop:(I)Ljava/lang/Object;
   156:	checkcast	#15; //class java/lang/String
   159:	goto	193
   162:	iconst_1
   163:	ifeq	259
   166:	new	#95; //class scala/collection/immutable/StringOps
   169:	dup
   170:	aload	16
   172:	invokespecial	#96; //Method scala/collection/immutable/StringOps."<init>":(Ljava/lang/String;)V
   175:	aload	16
   177:	getstatic	#108; //Field java/io/File.separator:Ljava/lang/String;
   180:	invokevirtual	#112; //Method java/lang/String.lastIndexOf:(Ljava/lang/String;)I
   183:	iconst_1
   184:	iadd
   185:	invokeinterface	#115,  2; //InterfaceMethod scala/collection/IndexedSeqLike.take:(I)Ljava/lang/Object;
   190:	checkcast	#15; //class java/lang/String
   193:	astore	11
   195:	new	#117; //class scala/collection/mutable/StringBuilder
   198:	dup
   199:	invokespecial	#120; //Method scala/collection/mutable/StringBuilder."<init>":()V
   202:	aload	11
   204:	invokevirtual	#124; //Method scala/collection/mutable/StringBuilder.append:(Ljava/lang/Object;)Lscala/collection/mutable/StringBuilder;
   207:	aload_1
   208:	invokevirtual	#124; //Method scala/collection/mutable/StringBuilder.append:(Ljava/lang/Object;)Lscala/collection/mutable/StringBuilder;
   211:	invokevirtual	#127; //Method scala/collection/mutable/StringBuilder.toString:()Ljava/lang/String;
   214:	astore	13
   216:	invokestatic	#35; //Method java/nio/charset/Charset.defaultCharset:()Ljava/nio/charset/Charset;
   219:	astore	12
   221:	new	#37; //class scala/io/Codec
   224:	dup
   225:	aload	12
   227:	invokespecial	#40; //Method scala/io/Codec."<init>":(Ljava/nio/charset/Charset;)V
   230:	astore	15
   232:	getstatic	#46; //Field scala/io/Source$.MODULE$:Lscala/io/Source$;
   235:	astore	14
   237:	aload	14
   239:	new	#104; //class java/io/File
   242:	dup
   243:	aload	13
   245:	invokespecial	#128; //Method java/io/File."<init>":(Ljava/lang/String;)V
   248:	aload	14
   250:	invokevirtual	#54; //Method scala/io/Source$.DefaultBufSize:()I
   253:	aload	15
   255:	invokevirtual	#132; //Method scala/io/Source$.fromFile:(Ljava/io/File;ILscala/io/Codec;)Lscala/io/Source;
   258:	areturn
   259:	new	#134; //class scala/MatchError
   262:	dup
   263:	aload	16
   265:	invokevirtual	#135; //Method java/lang/String.toString:()Ljava/lang/String;
   268:	invokespecial	#136; //Method scala/MatchError."<init>":(Ljava/lang/String;)V
   271:	athrow
  LineNumberTable: 
   line 34: 0
   line 35: 9
   line 37: 118
   line 38: 141
   line 21: 162
   line 39: 166
   line 37: 193
   line 42: 195
   line 37: 259

  LocalVariableTable: 
   Start  Length  Slot  Name   Signature
   0      272      0    $this       Lscala/xml/parsing/ExternalSources;
   0      272      1    systemId       Ljava/lang/String;
   18      100      3    x$1       Ljava/net/URL;
   63      55      4    $inlThis3       Ljava/lang/Object;
   63      55      5    bufferSize$10       I
   63      55      6    reset$10       Lscala/Function0;
   63      55      7    inputStream$10       Ljava/io/InputStream;
   32      86      8    x$2       Lscala/io/Codec;
   96      21      9    resetFn0       Lscala/Function0;
   63      55      10    close$10       Lscala/Function0;
   195      63      11    fileStr       Ljava/lang/String;
   216      42      13    x$3       Ljava/lang/String;
   232      26      15    x$4       Lscala/io/Codec;
   132      140      16    temp1       Ljava/lang/String;


}

