Compiled from "FactoryAdapter.scala"
public final class scala.xml.parsing.FactoryAdapter$$anonfun$1 extends scala.runtime.AbstractFunction0 implements java.io.Serializable
  SourceFile: "FactoryAdapter.scala"
  Scala: length = 0x
   
  InnerClass: 
   public final $anonfun$1=class scala/xml/parsing/FactoryAdapter$$anonfun$1 of class scala/xml/parsing/FactoryAdapter
  minor version: 0
  major version: 49
  Constant pool:
Asciz	SourceFile;
Asciz	FactoryAdapter.scala;
Asciz	<clinit>;
Asciz	()V;
Asciz	Code;
Asciz	serialVersionUID;
Asciz	J;
Asciz	scala/xml/parsing/FactoryAdapter$$anonfun$1;
class	scala/xml/parsing/FactoryAdapter$$anonfun$1
NameAndType	serialVersionUID:J
Field	scala/xml/parsing/FactoryAdapter$$anonfun$1.serialVersionUID:J
Asciz	$outer;
Asciz	Lscala/xml/parsing/FactoryAdapter;;
Asciz	<init>;
Asciz	(Lscala/xml/parsing/FactoryAdapter;)V;
Asciz	LineNumberTable;
Asciz	java/lang/NullPointerException;
class	java/lang/NullPointerException
NameAndType	"<init>":()V
Method	java/lang/NullPointerException."<init>":()V
NameAndType	$outer:Lscala/xml/parsing/FactoryAdapter;
Field	scala/xml/parsing/FactoryAdapter$$anonfun$1.$outer:Lscala/xml/parsing/FactoryAdapter;
Asciz	scala/runtime/AbstractFunction0;
class	scala/runtime/AbstractFunction0
Method	scala/runtime/AbstractFunction0."<init>":()V
Asciz	this;
Asciz	Lscala/xml/parsing/FactoryAdapter$$anonfun$1;;
Asciz	LocalVariableTable;
Asciz	apply;
Asciz	()Ljava/lang/Object;;
Asciz	()Lscala/xml/Node;;
NameAndType	apply:()Lscala/xml/Node;
Method	scala/xml/parsing/FactoryAdapter$$anonfun$1.apply:()Lscala/xml/Node;
Asciz	scala/xml/parsing/FactoryAdapter;
class	scala/xml/parsing/FactoryAdapter
Asciz	hStack;
Asciz	()Lscala/collection/mutable/Stack;;
NameAndType	hStack:()Lscala/collection/mutable/Stack;
Method	scala/xml/parsing/FactoryAdapter.hStack:()Lscala/collection/mutable/Stack;
Asciz	scala/collection/mutable/Stack;
class	scala/collection/mutable/Stack
Asciz	pop;
NameAndType	pop:()Ljava/lang/Object;
Method	scala/collection/mutable/Stack.pop:()Ljava/lang/Object;
Asciz	scala/xml/Node;
class	scala/xml/Node
Asciz	Scala;
Asciz	InnerClasses;
Asciz	$anonfun$1;
Asciz	java/io/Serializable;
class	java/io/Serializable

{
public static final long serialVersionUID;
  Signature: J

private final scala.xml.parsing.FactoryAdapter $outer;
  Signature: Lscala/xml/parsing/FactoryAdapter;

public static {};
  Signature: ()V
  Code:
   Stack=2, Locals=0, Args_size=0
	lconst_0
	putstatic	Field serialVersionUID:J
	return
  Labels:

public scala.xml.parsing.FactoryAdapter$$anonfun$1(scala.xml.parsing.FactoryAdapter);
  Signature: (Lscala/xml/parsing/FactoryAdapter;)V
  Code:
   Stack=2, Locals=2, Args_size=2
	aload_1
	ifnonnull	l1 // aload_0
	new	class java/lang/NullPointerException
	dup
	invokespecial	Method java/lang/NullPointerException."<init>":()V
	athrow
l1	aload_0
	aload_1
	putfield	Field $outer:Lscala/xml/parsing/FactoryAdapter;
	aload_0
	invokespecial	Method scala/runtime/AbstractFunction0."<init>":()V
	return
  Labels:
   	l1 = 12 // aload_0
  LocalVariableTable: 
   Start  Length  Slot  Name   Signature
   0      22      0    this       Lscala/xml/parsing/FactoryAdapter$$anonfun$1;
   0      22      1    $outer       Lscala/xml/parsing/FactoryAdapter;


public final java.lang.Object apply();
  Signature: ()Ljava/lang/Object;
  Code:
   Stack=1, Locals=1, Args_size=1
	aload_0
	invokevirtual	Method apply:()Lscala/xml/Node;
	areturn
  Labels:

public final scala.xml.Node apply();
  Signature: ()Lscala/xml/Node;
  Code:
   Stack=1, Locals=1, Args_size=1
	aload_0
	getfield	Field $outer:Lscala/xml/parsing/FactoryAdapter;
	invokevirtual	Method scala/xml/parsing/FactoryAdapter.hStack:()Lscala/collection/mutable/Stack;
	invokevirtual	Method scala/collection/mutable/Stack.pop:()Ljava/lang/Object;
	checkcast	class scala/xml/Node
	areturn
  Labels:

}

