Compiled from "FactoryAdapter.scala"
public final class scala.xml.parsing.FactoryAdapter$$anonfun$startElement$1 extends scala.runtime.AbstractFunction1 implements java.io.Serializable
  SourceFile: "FactoryAdapter.scala"
  Scala: length = 0x
   
  InnerClass: 
   public final $anonfun$startElement$1=class scala/xml/parsing/FactoryAdapter$$anonfun$startElement$1 of class scala/xml/parsing/FactoryAdapter
  minor version: 0
  major version: 49
  Constant pool:
Asciz	SourceFile;
Asciz	FactoryAdapter.scala;
Asciz	<clinit>;
Asciz	()V;
Asciz	Code;
Asciz	serialVersionUID;
Asciz	J;
Asciz	scala/xml/parsing/FactoryAdapter$$anonfun$startElement$1;
class	scala/xml/parsing/FactoryAdapter$$anonfun$startElement$1
NameAndType	serialVersionUID:J
Field	scala/xml/parsing/FactoryAdapter$$anonfun$startElement$1.serialVersionUID:J
Asciz	$outer;
Asciz	Lscala/xml/parsing/FactoryAdapter;;
Asciz	attributes$1;
Asciz	Lorg/xml/sax/Attributes;;
Asciz	m$1;
Asciz	Lscala/runtime/ObjectRef;;
Asciz	scpe$1;
Asciz	apply;
Asciz	(I)V;
Asciz	LineNumberTable;
NameAndType	attributes$1:Lorg/xml/sax/Attributes;
Field	scala/xml/parsing/FactoryAdapter$$anonfun$startElement$1.attributes$1:Lorg/xml/sax/Attributes;
Asciz	org/xml/sax/Attributes;
class	org/xml/sax/Attributes
Asciz	getQName;
Asciz	(I)Ljava/lang/String;;
NameAndType	getQName:(I)Ljava/lang/String;
InterfaceMethod	org/xml/sax/Attributes.getQName:(I)Ljava/lang/String;
Asciz	getValue;
NameAndType	getValue:(I)Ljava/lang/String;
InterfaceMethod	org/xml/sax/Attributes.getValue:(I)Ljava/lang/String;
NameAndType	$outer:Lscala/xml/parsing/FactoryAdapter;
Field	scala/xml/parsing/FactoryAdapter$$anonfun$startElement$1.$outer:Lscala/xml/parsing/FactoryAdapter;
Asciz	scala/xml/parsing/FactoryAdapter;
class	scala/xml/parsing/FactoryAdapter
Asciz	scala$xml$parsing$FactoryAdapter$$splitName;
Asciz	(Ljava/lang/String;)Lscala/Tuple2;;
NameAndType	scala$xml$parsing$FactoryAdapter$$splitName:(Ljava/lang/String;)Lscala/Tuple2;
Method	scala/xml/parsing/FactoryAdapter.scala$xml$parsing$FactoryAdapter$$splitName:(Ljava/lang/String;)Lscala/Tuple2;
Asciz	scala/Tuple2;
class	scala/Tuple2
Asciz	_1;
Asciz	()Ljava/lang/Object;;
NameAndType	_1:()Ljava/lang/Object;
Method	scala/Tuple2._1:()Ljava/lang/Object;
Asciz	_2;
NameAndType	_2:()Ljava/lang/Object;
Method	scala/Tuple2._2:()Ljava/lang/Object;
Asciz	<init>;
Asciz	(Ljava/lang/Object;Ljava/lang/Object;)V;
NameAndType	"<init>":(Ljava/lang/Object;Ljava/lang/Object;)V
Method	scala/Tuple2."<init>":(Ljava/lang/Object;Ljava/lang/Object;)V
Asciz	java/lang/String;
class	java/lang/String
Asciz	xmlns;
String	xmlns
Asciz	java/lang/Object;
class	java/lang/Object
Asciz	equals;
Asciz	(Ljava/lang/Object;)Z;
NameAndType	equals:(Ljava/lang/Object;)Z
Method	java/lang/Object.equals:(Ljava/lang/Object;)Z
NameAndType	scpe$1:Lscala/runtime/ObjectRef;
Field	scala/xml/parsing/FactoryAdapter$$anonfun$startElement$1.scpe$1:Lscala/runtime/ObjectRef;
Asciz	scala/xml/NamespaceBinding;
class	scala/xml/NamespaceBinding
Asciz	nullIfEmpty$1;
Asciz	(Ljava/lang/String;)Ljava/lang/String;;
NameAndType	nullIfEmpty$1:(Ljava/lang/String;)Ljava/lang/String;
Method	scala/xml/parsing/FactoryAdapter$$anonfun$startElement$1.nullIfEmpty$1:(Ljava/lang/String;)Ljava/lang/String;
Asciz	scala/runtime/ObjectRef;
class	scala/runtime/ObjectRef
Asciz	elem;
Asciz	Ljava/lang/Object;;
NameAndType	elem:Ljava/lang/Object;
Field	scala/runtime/ObjectRef.elem:Ljava/lang/Object;
Asciz	(Ljava/lang/String;Ljava/lang/String;Lscala/xml/NamespaceBinding;)V;
NameAndType	"<init>":(Ljava/lang/String;Ljava/lang/String;Lscala/xml/NamespaceBinding;)V
Method	scala/xml/NamespaceBinding."<init>":(Ljava/lang/String;Ljava/lang/String;Lscala/xml/NamespaceBinding;)V
NameAndType	m$1:Lscala/runtime/ObjectRef;
Field	scala/xml/parsing/FactoryAdapter$$anonfun$startElement$1.m$1:Lscala/runtime/ObjectRef;
Asciz	scala/xml/Attribute$;
class	scala/xml/Attribute$
Asciz	MODULE$;
Asciz	Lscala/xml/Attribute$;;
NameAndType	MODULE$:Lscala/xml/Attribute$;
Field	scala/xml/Attribute$.MODULE$:Lscala/xml/Attribute$;
Asciz	scala/Option$;
class	scala/Option$
Asciz	Lscala/Option$;;
NameAndType	MODULE$:Lscala/Option$;
Field	scala/Option$.MODULE$:Lscala/Option$;
Asciz	(Ljava/lang/Object;)Lscala/Option;;
NameAndType	apply:(Ljava/lang/Object;)Lscala/Option;
Method	scala/Option$.apply:(Ljava/lang/Object;)Lscala/Option;
Asciz	scala/xml/Text;
class	scala/xml/Text
Asciz	(Ljava/lang/String;)V;
NameAndType	"<init>":(Ljava/lang/String;)V
Method	scala/xml/Text."<init>":(Ljava/lang/String;)V
Asciz	scala/xml/MetaData;
class	scala/xml/MetaData
Asciz	(Lscala/Option;Ljava/lang/String;Lscala/collection/Seq;Lscala/xml/MetaData;)Lscala/xml/Attribute;;
NameAndType	apply:(Lscala/Option;Ljava/lang/String;Lscala/collection/Seq;Lscala/xml/MetaData;)Lscala/xml/Attribute;
Method	scala/xml/Attribute$.apply:(Lscala/Option;Ljava/lang/String;Lscala/collection/Seq;Lscala/xml/MetaData;)Lscala/xml/Attribute;
Asciz	scala/MatchError;
class	scala/MatchError
Asciz	(Ljava/lang/Object;)V;
NameAndType	"<init>":(Ljava/lang/Object;)V
Method	scala/MatchError."<init>":(Ljava/lang/Object;)V
Asciz	this;
Asciz	Lscala/xml/parsing/FactoryAdapter$$anonfun$startElement$1;;
Asciz	i;
Asciz	I;
Asciz	x$20;
Asciz	Lscala/Tuple2;;
Asciz	qname0;
Asciz	Ljava/lang/String;;
Asciz	arg0;
Asciz	pre0;
Asciz	key0;
Asciz	value0;
Asciz	temp10;
Asciz	LocalVariableTable;
Asciz	apply$mcVI$sp;
Asciz	v1;
Asciz	qname;
Asciz	value;
Asciz	temp1;
Asciz	pre;
Asciz	key;
Asciz	arg;
Asciz	(Ljava/lang/Object;)Ljava/lang/Object;;
Asciz	scala/runtime/BoxesRunTime;
class	scala/runtime/BoxesRunTime
Asciz	unboxToInt;
Asciz	(Ljava/lang/Object;)I;
NameAndType	unboxToInt:(Ljava/lang/Object;)I
Method	scala/runtime/BoxesRunTime.unboxToInt:(Ljava/lang/Object;)I
NameAndType	apply:(I)V
Method	scala/xml/parsing/FactoryAdapter$$anonfun$startElement$1.apply:(I)V
Asciz	scala/runtime/BoxedUnit;
class	scala/runtime/BoxedUnit
Asciz	UNIT;
Asciz	Lscala/runtime/BoxedUnit;;
NameAndType	UNIT:Lscala/runtime/BoxedUnit;
Field	scala/runtime/BoxedUnit.UNIT:Lscala/runtime/BoxedUnit;
Asciz	;
String	
Asciz	s;
Asciz	(Lscala/xml/parsing/FactoryAdapter;Lorg/xml/sax/Attributes;Lscala/runtime/ObjectRef;Lscala/runtime/ObjectRef;)V;
Asciz	java/lang/NullPointerException;
class	java/lang/NullPointerException
NameAndType	"<init>":()V
Method	java/lang/NullPointerException."<init>":()V
Asciz	scala/runtime/AbstractFunction1;
class	scala/runtime/AbstractFunction1
Method	scala/runtime/AbstractFunction1."<init>":()V
Asciz	Scala;
Asciz	InnerClasses;
Asciz	$anonfun$startElement$1;
Asciz	java/io/Serializable;
class	java/io/Serializable

{
public static final long serialVersionUID;
  Signature: J

public final scala.xml.parsing.FactoryAdapter $outer;
  Signature: Lscala/xml/parsing/FactoryAdapter;

public final org.xml.sax.Attributes attributes$1;
  Signature: Lorg/xml/sax/Attributes;

public final scala.runtime.ObjectRef m$1;
  Signature: Lscala/runtime/ObjectRef;

public final scala.runtime.ObjectRef scpe$1;
  Signature: Lscala/runtime/ObjectRef;

public static {};
  Signature: ()V
  Code:
   Stack=2, Locals=0, Args_size=0
	lconst_0
	putstatic	Field serialVersionUID:J
	return
  Labels:

public final void apply(int);
  Signature: (I)V
  Code:
   Stack=7, Locals=11, Args_size=2
	aload_0
	getfield	Field attributes$1:Lorg/xml/sax/Attributes;
	iload_1
	invokeinterface	InterfaceMethod org/xml/sax/Attributes.getQName:(I)Ljava/lang/String;
	astore	4
	aload_0
	getfield	Field attributes$1:Lorg/xml/sax/Attributes;
	iload_1
	invokeinterface	InterfaceMethod org/xml/sax/Attributes.getValue:(I)Ljava/lang/String;
	astore	9
	aload_0
	getfield	Field $outer:Lscala/xml/parsing/FactoryAdapter;
	aload	4
	invokevirtual	Method scala/xml/parsing/FactoryAdapter.scala$xml$parsing$FactoryAdapter$$splitName:(Ljava/lang/String;)Lscala/Tuple2;
	astore	10
	aload	10
	ifnull	l1 // new
	new	class scala/Tuple2
	dup
	aload	10
	invokevirtual	Method scala/Tuple2._1:()Ljava/lang/Object;
	aload	10
	invokevirtual	Method scala/Tuple2._2:()Ljava/lang/Object;
	invokespecial	Method scala/Tuple2."<init>":(Ljava/lang/Object;Ljava/lang/Object;)V
	astore_2
	aload_2
	invokevirtual	Method scala/Tuple2._1:()Ljava/lang/Object;
	checkcast	class java/lang/String
	astore	7
	aload_2
	invokevirtual	Method scala/Tuple2._2:()Ljava/lang/Object;
	checkcast	class java/lang/String
	astore	8
	aload	7
	ldc	String xmlns
	astore_3
	dup
	ifnonnull	l2 // aload_3
	pop
	aload_3
	ifnull	l3 // aload
	goto	l4 // aload
l2	aload_3
	invokevirtual	Method java/lang/Object.equals:(Ljava/lang/Object;)Z
	ifne	l3 // aload
l4	aload	7
	ifnonnull	l5 // aload_0
	aload	4
	ldc	String xmlns
	astore	5
	dup
	ifnonnull	l6 // aload
	pop
	aload	5
	ifnull	l3 // aload
	goto	l5 // aload_0
l6	aload	5
	invokevirtual	Method java/lang/Object.equals:(Ljava/lang/Object;)Z
	ifeq	l5 // aload_0
l3	aload	7
	ifnonnull	l7 // aload
	aconst_null
	goto	l8 // astore
l7	aload	8
l8	astore	6
	aload_0
	getfield	Field scpe$1:Lscala/runtime/ObjectRef;
	new	class scala/xml/NamespaceBinding
	dup
	aload	6
	aload_0
	aload	9
	invokespecial	Method nullIfEmpty$1:(Ljava/lang/String;)Ljava/lang/String;
	aload_0
	getfield	Field scpe$1:Lscala/runtime/ObjectRef;
	getfield	Field scala/runtime/ObjectRef.elem:Ljava/lang/Object;
	checkcast	class scala/xml/NamespaceBinding
	invokespecial	Method scala/xml/NamespaceBinding."<init>":(Ljava/lang/String;Ljava/lang/String;Lscala/xml/NamespaceBinding;)V
	putfield	Field scala/runtime/ObjectRef.elem:Ljava/lang/Object;
	goto	l9 // return
l5	aload_0
	getfield	Field m$1:Lscala/runtime/ObjectRef;
	getstatic	Field scala/xml/Attribute$.MODULE$:Lscala/xml/Attribute$;
	getstatic	Field scala/Option$.MODULE$:Lscala/Option$;
	aload	7
	invokevirtual	Method scala/Option$.apply:(Ljava/lang/Object;)Lscala/Option;
	aload	8
	new	class scala/xml/Text
	dup
	aload	9
	invokespecial	Method scala/xml/Text."<init>":(Ljava/lang/String;)V
	aload_0
	getfield	Field m$1:Lscala/runtime/ObjectRef;
	getfield	Field scala/runtime/ObjectRef.elem:Ljava/lang/Object;
	checkcast	class scala/xml/MetaData
	invokevirtual	Method scala/xml/Attribute$.apply:(Lscala/Option;Ljava/lang/String;Lscala/collection/Seq;Lscala/xml/MetaData;)Lscala/xml/Attribute;
	checkcast	class scala/xml/MetaData
	putfield	Field scala/runtime/ObjectRef.elem:Ljava/lang/Object;
l9	return
l1	new	class scala/MatchError
	dup
	aload	10
	invokespecial	Method scala/MatchError."<init>":(Ljava/lang/Object;)V
	athrow
  Labels:
   	l2 = 93 // aload_3
   	l4 = 100 // aload
   	l6 = 124 // aload
   	l3 = 132 // aload
   	l7 = 141 // aload
   	l8 = 143 // astore
   	l5 = 180 // aload_0
   	l9 = 225 // return
   	l1 = 226 // new
  LocalVariableTable: 
   Start  Length  Slot  Name   Signature
   0      236      0    this       Lscala/xml/parsing/FactoryAdapter$$anonfun$startElement$1;
   0      236      1    i       I
   58      168      2    x$20       Lscala/Tuple2;
   12      224      4    qname0       Ljava/lang/String;
   145      32      6    arg0       Ljava/lang/String;
   67      159      7    pre0       Ljava/lang/String;
   76      150      8    key0       Ljava/lang/String;
   24      212      9    value0       Ljava/lang/String;
   35      50      10    temp10       Lscala/Tuple2;
   226      10      10    temp10       Lscala/Tuple2;


public void apply$mcVI$sp(int);
  Signature: (I)V
  Code:
   Stack=7, Locals=11, Args_size=2
	aload_0
	getfield	Field attributes$1:Lorg/xml/sax/Attributes;
	iload_1
	invokeinterface	InterfaceMethod org/xml/sax/Attributes.getQName:(I)Ljava/lang/String;
	astore_2
	aload_0
	getfield	Field attributes$1:Lorg/xml/sax/Attributes;
	iload_1
	invokeinterface	InterfaceMethod org/xml/sax/Attributes.getValue:(I)Ljava/lang/String;
	astore_3
	aload_0
	getfield	Field $outer:Lscala/xml/parsing/FactoryAdapter;
	aload_2
	invokevirtual	Method scala/xml/parsing/FactoryAdapter.scala$xml$parsing$FactoryAdapter$$splitName:(Ljava/lang/String;)Lscala/Tuple2;
	astore	5
	aload	5
	ifnull	l1 // new
	new	class scala/Tuple2
	dup
	aload	5
	invokevirtual	Method scala/Tuple2._1:()Ljava/lang/Object;
	aload	5
	invokevirtual	Method scala/Tuple2._2:()Ljava/lang/Object;
	invokespecial	Method scala/Tuple2."<init>":(Ljava/lang/Object;Ljava/lang/Object;)V
	astore	4
	aload	4
	invokevirtual	Method scala/Tuple2._1:()Ljava/lang/Object;
	checkcast	class java/lang/String
	astore	6
	aload	4
	invokevirtual	Method scala/Tuple2._2:()Ljava/lang/Object;
	checkcast	class java/lang/String
	astore	7
	aload	6
	ldc	String xmlns
	astore	8
	dup
	ifnonnull	l2 // aload
	pop
	aload	8
	ifnull	l3 // aload
	goto	l4 // aload
l2	aload	8
	invokevirtual	Method java/lang/Object.equals:(Ljava/lang/Object;)Z
	ifne	l3 // aload
l4	aload	6
	ifnonnull	l5 // aload_0
	aload_2
	ldc	String xmlns
	astore	9
	dup
	ifnonnull	l6 // aload
	pop
	aload	9
	ifnull	l3 // aload
	goto	l5 // aload_0
l6	aload	9
	invokevirtual	Method java/lang/Object.equals:(Ljava/lang/Object;)Z
	ifeq	l5 // aload_0
l3	aload	6
	ifnonnull	l7 // aload
	aconst_null
	goto	l8 // astore
l7	aload	7
l8	astore	10
	aload_0
	getfield	Field scpe$1:Lscala/runtime/ObjectRef;
	new	class scala/xml/NamespaceBinding
	dup
	aload	10
	aload_0
	aload_3
	invokespecial	Method nullIfEmpty$1:(Ljava/lang/String;)Ljava/lang/String;
	aload_0
	getfield	Field scpe$1:Lscala/runtime/ObjectRef;
	getfield	Field scala/runtime/ObjectRef.elem:Ljava/lang/Object;
	checkcast	class scala/xml/NamespaceBinding
	invokespecial	Method scala/xml/NamespaceBinding."<init>":(Ljava/lang/String;Ljava/lang/String;Lscala/xml/NamespaceBinding;)V
	putfield	Field scala/runtime/ObjectRef.elem:Ljava/lang/Object;
	goto	l9 // return
l5	aload_0
	getfield	Field m$1:Lscala/runtime/ObjectRef;
	getstatic	Field scala/xml/Attribute$.MODULE$:Lscala/xml/Attribute$;
	getstatic	Field scala/Option$.MODULE$:Lscala/Option$;
	aload	6
	invokevirtual	Method scala/Option$.apply:(Ljava/lang/Object;)Lscala/Option;
	aload	7
	new	class scala/xml/Text
	dup
	aload_3
	invokespecial	Method scala/xml/Text."<init>":(Ljava/lang/String;)V
	aload_0
	getfield	Field m$1:Lscala/runtime/ObjectRef;
	getfield	Field scala/runtime/ObjectRef.elem:Ljava/lang/Object;
	checkcast	class scala/xml/MetaData
	invokevirtual	Method scala/xml/Attribute$.apply:(Lscala/Option;Ljava/lang/String;Lscala/collection/Seq;Lscala/xml/MetaData;)Lscala/xml/Attribute;
	checkcast	class scala/xml/MetaData
	putfield	Field scala/runtime/ObjectRef.elem:Ljava/lang/Object;
l9	return
l1	new	class scala/MatchError
	dup
	aload	5
	invokespecial	Method scala/MatchError."<init>":(Ljava/lang/Object;)V
	athrow
  Labels:
   	l2 = 95 // aload
   	l4 = 103 // aload
   	l6 = 126 // aload
   	l3 = 134 // aload
   	l7 = 143 // aload
   	l8 = 145 // astore
   	l5 = 181 // aload_0
   	l9 = 225 // return
   	l1 = 226 // new
  LocalVariableTable: 
   Start  Length  Slot  Name   Signature
   0      236      0    this       Lscala/xml/parsing/FactoryAdapter$$anonfun$startElement$1;
   0      236      1    v1       I
   11      225      2    qname       Ljava/lang/String;
   22      214      3    value       Ljava/lang/String;
   32      54      5    temp1       Lscala/Tuple2;
   226      10      5    temp1       Lscala/Tuple2;
   66      160      6    pre       Ljava/lang/String;
   76      150      7    key       Ljava/lang/String;
   147      31      10    arg       Ljava/lang/String;


public final java.lang.Object apply(java.lang.Object);
  Signature: (Ljava/lang/Object;)Ljava/lang/Object;
  Code:
   Stack=2, Locals=2, Args_size=2
	aload_0
	aload_1
	invokestatic	Method scala/runtime/BoxesRunTime.unboxToInt:(Ljava/lang/Object;)I
	invokevirtual	Method apply:(I)V
	getstatic	Field scala/runtime/BoxedUnit.UNIT:Lscala/runtime/BoxedUnit;
	areturn
  Labels:
  LocalVariableTable: 
   Start  Length  Slot  Name   Signature
   0      12      0    this       Lscala/xml/parsing/FactoryAdapter$$anonfun$startElement$1;
   0      12      1    v1       Ljava/lang/Object;


private final java.lang.String nullIfEmpty$1(java.lang.String);
  Signature: (Ljava/lang/String;)Ljava/lang/String;
  Code:
   Stack=2, Locals=3, Args_size=2
	aload_1
	ldc	String 
	astore_2
	dup
	ifnonnull	l1 // aload_2
	pop
	aload_2
	ifnull	l2 // aconst_null
	goto	l3 // aload_1
l1	aload_2
	invokevirtual	Method java/lang/Object.equals:(Ljava/lang/Object;)Z
	ifeq	l3 // aload_1
l2	aconst_null
	goto	l4 // areturn
l3	aload_1
l4	areturn
  Labels:
   	l1 = 16 // aload_2
   	l2 = 23 // aconst_null
   	l3 = 27 // aload_1
   	l4 = 28 // areturn
  LocalVariableTable: 
   Start  Length  Slot  Name   Signature
   0      29      0    this       Lscala/xml/parsing/FactoryAdapter$$anonfun$startElement$1;
   0      29      1    s       Ljava/lang/String;


public scala.xml.parsing.FactoryAdapter$$anonfun$startElement$1(scala.xml.parsing.FactoryAdapter, org.xml.sax.Attributes, scala.runtime.ObjectRef, scala.runtime.ObjectRef);
  Signature: (Lscala/xml/parsing/FactoryAdapter;Lorg/xml/sax/Attributes;Lscala/runtime/ObjectRef;Lscala/runtime/ObjectRef;)V
  Code:
   Stack=2, Locals=5, Args_size=5
	aload_1
	ifnonnull	l1 // aload_0
	new	class java/lang/NullPointerException
	dup
	invokespecial	Method java/lang/NullPointerException."<init>":()V
	athrow
l1	aload_0
	aload_1
	putfield	Field $outer:Lscala/xml/parsing/FactoryAdapter;
	aload_0
	aload_2
	putfield	Field attributes$1:Lorg/xml/sax/Attributes;
	aload_0
	aload_3
	putfield	Field m$1:Lscala/runtime/ObjectRef;
	aload_0
	aload	4
	putfield	Field scpe$1:Lscala/runtime/ObjectRef;
	aload_0
	invokespecial	Method scala/runtime/AbstractFunction1."<init>":()V
	return
  Labels:
   	l1 = 12 // aload_0
  LocalVariableTable: 
   Start  Length  Slot  Name   Signature
   0      38      0    this       Lscala/xml/parsing/FactoryAdapter$$anonfun$startElement$1;
   0      38      1    $outer       Lscala/xml/parsing/FactoryAdapter;


}

