Compiled from "FactoryAdapter.scala"
public final class scala.xml.parsing.FactoryAdapter$$anonfun$characters$1 extends scala.runtime.AbstractFunction1 implements java.io.Serializable
  SourceFile: "FactoryAdapter.scala"
  Scala: length = 0x
   
  InnerClass: 
   public final $anonfun$characters$1=class scala/xml/parsing/FactoryAdapter$$anonfun$characters$1 of class scala/xml/parsing/FactoryAdapter
  minor version: 0
  major version: 49
  Constant pool:
Asciz	SourceFile;
Asciz	FactoryAdapter.scala;
Asciz	<clinit>;
Asciz	()V;
Asciz	Code;
Asciz	serialVersionUID;
Asciz	J;
Asciz	scala/xml/parsing/FactoryAdapter$$anonfun$characters$1;
class	scala/xml/parsing/FactoryAdapter$$anonfun$characters$1
NameAndType	serialVersionUID:J
Field	scala/xml/parsing/FactoryAdapter$$anonfun$characters$1.serialVersionUID:J
Asciz	apply;
Asciz	(C)Z;
Asciz	scala/Predef$;
class	scala/Predef$
Asciz	MODULE$;
Asciz	Lscala/Predef$;;
NameAndType	MODULE$:Lscala/Predef$;
Field	scala/Predef$.MODULE$:Lscala/Predef$;
Asciz	LineNumberTable;
Asciz	charWrapper;
Asciz	(C)Lscala/runtime/RichChar;;
NameAndType	charWrapper:(C)Lscala/runtime/RichChar;
Method	scala/Predef$.charWrapper:(C)Lscala/runtime/RichChar;
Asciz	scala/runtime/RichChar;
class	scala/runtime/RichChar
Asciz	isWhitespace;
Asciz	()Z;
NameAndType	isWhitespace:()Z
Method	scala/runtime/RichChar.isWhitespace:()Z
Asciz	(Ljava/lang/Object;)Ljava/lang/Object;;
Asciz	scala/runtime/BoxesRunTime;
class	scala/runtime/BoxesRunTime
Asciz	unboxToChar;
Asciz	(Ljava/lang/Object;)C;
NameAndType	unboxToChar:(Ljava/lang/Object;)C
Method	scala/runtime/BoxesRunTime.unboxToChar:(Ljava/lang/Object;)C
NameAndType	apply:(C)Z
Method	scala/xml/parsing/FactoryAdapter$$anonfun$characters$1.apply:(C)Z
Asciz	boxToBoolean;
Asciz	(Z)Ljava/lang/Boolean;;
NameAndType	boxToBoolean:(Z)Ljava/lang/Boolean;
Method	scala/runtime/BoxesRunTime.boxToBoolean:(Z)Ljava/lang/Boolean;
Asciz	this;
Asciz	Lscala/xml/parsing/FactoryAdapter$$anonfun$characters$1;;
Asciz	v1;
Asciz	Ljava/lang/Object;;
Asciz	LocalVariableTable;
Asciz	<init>;
Asciz	(Lscala/xml/parsing/FactoryAdapter;)V;
Asciz	scala/runtime/AbstractFunction1;
class	scala/runtime/AbstractFunction1
NameAndType	"<init>":()V
Method	scala/runtime/AbstractFunction1."<init>":()V
Asciz	$outer;
Asciz	Lscala/xml/parsing/FactoryAdapter;;
Asciz	Scala;
Asciz	InnerClasses;
Asciz	scala/xml/parsing/FactoryAdapter;
class	scala/xml/parsing/FactoryAdapter
Asciz	$anonfun$characters$1;
Asciz	java/io/Serializable;
class	java/io/Serializable

{
public static final long serialVersionUID;
  Signature: J

public static {};
  Signature: ()V
  Code:
   Stack=2, Locals=0, Args_size=0
	lconst_0
	putstatic	Field serialVersionUID:J
	return
  Labels:

public final boolean apply(char);
  Signature: (C)Z
  Code:
   Stack=2, Locals=2, Args_size=2
	getstatic	Field scala/Predef$.MODULE$:Lscala/Predef$;
	iload_1
	invokevirtual	Method scala/Predef$.charWrapper:(C)Lscala/runtime/RichChar;
	invokevirtual	Method scala/runtime/RichChar.isWhitespace:()Z
	ireturn
  Labels:

public final java.lang.Object apply(java.lang.Object);
  Signature: (Ljava/lang/Object;)Ljava/lang/Object;
  Code:
   Stack=2, Locals=2, Args_size=2
	aload_0
	aload_1
	invokestatic	Method scala/runtime/BoxesRunTime.unboxToChar:(Ljava/lang/Object;)C
	invokevirtual	Method apply:(C)Z
	invokestatic	Method scala/runtime/BoxesRunTime.boxToBoolean:(Z)Ljava/lang/Boolean;
	areturn
  Labels:
  LocalVariableTable: 
   Start  Length  Slot  Name   Signature
   0      12      0    this       Lscala/xml/parsing/FactoryAdapter$$anonfun$characters$1;
   0      12      1    v1       Ljava/lang/Object;


public scala.xml.parsing.FactoryAdapter$$anonfun$characters$1(scala.xml.parsing.FactoryAdapter);
  Signature: (Lscala/xml/parsing/FactoryAdapter;)V
  Code:
   Stack=1, Locals=2, Args_size=2
	aload_0
	invokespecial	Method scala/runtime/AbstractFunction1."<init>":()V
	return
  Labels:
  LocalVariableTable: 
   Start  Length  Slot  Name   Signature
   0      5      0    this       Lscala/xml/parsing/FactoryAdapter$$anonfun$characters$1;
   0      5      1    $outer       Lscala/xml/parsing/FactoryAdapter;


}

