Compiled from "FactoryAdapter.scala"
public final class scala.xml.parsing.FactoryAdapter$$anonfun$startElement$1 extends java.lang.Object implements scala.Function1,scala.ScalaObject,java.io.Serializable
  SourceFile: "FactoryAdapter.scala"
  Scala: length = 0x
   
  InnerClass: 
   public final #180= #9 of #85; //$anonfun$startElement$1=class scala/xml/parsing/FactoryAdapter$$anonfun$startElement$1 of class scala/xml/parsing/FactoryAdapter
  minor version: 0
  major version: 49
  Constant pool:
const #1 = Asciz	SourceFile;
const #2 = Asciz	FactoryAdapter.scala;
const #3 = Asciz	<clinit>;
const #4 = Asciz	()V;
const #5 = Asciz	Code;
const #6 = Asciz	serialVersionUID;
const #7 = Asciz	J;
const #8 = Asciz	scala/xml/parsing/FactoryAdapter$$anonfun$startElement$1;
const #9 = class	#8;	//  scala/xml/parsing/FactoryAdapter$$anonfun$startElement$1
const #10 = NameAndType	#6:#7;//  serialVersionUID:J
const #11 = Field	#9.#10;	//  scala/xml/parsing/FactoryAdapter$$anonfun$startElement$1.serialVersionUID:J
const #12 = Asciz	scpe$1;
const #13 = Asciz	Lscala/runtime/ObjectRef;;
const #14 = Asciz	m$1;
const #15 = Asciz	attributes$1;
const #16 = Asciz	Lorg/xml/sax/Attributes;;
const #17 = Asciz	$outer;
const #18 = Asciz	Lscala/xml/parsing/FactoryAdapter;;
const #19 = Asciz	<init>;
const #20 = Asciz	(Lscala/xml/parsing/FactoryAdapter;Lorg/xml/sax/Attributes;Lscala/runtime/ObjectRef;Lscala/runtime/ObjectRef;)V;
const #21 = Asciz	LineNumberTable;
const #22 = Asciz	java/lang/NullPointerException;
const #23 = class	#22;	//  java/lang/NullPointerException
const #24 = NameAndType	#19:#4;//  "<init>":()V
const #25 = Method	#23.#24;	//  java/lang/NullPointerException."<init>":()V
const #26 = NameAndType	#17:#18;//  $outer:Lscala/xml/parsing/FactoryAdapter;
const #27 = Field	#9.#26;	//  scala/xml/parsing/FactoryAdapter$$anonfun$startElement$1.$outer:Lscala/xml/parsing/FactoryAdapter;
const #28 = NameAndType	#15:#16;//  attributes$1:Lorg/xml/sax/Attributes;
const #29 = Field	#9.#28;	//  scala/xml/parsing/FactoryAdapter$$anonfun$startElement$1.attributes$1:Lorg/xml/sax/Attributes;
const #30 = NameAndType	#14:#13;//  m$1:Lscala/runtime/ObjectRef;
const #31 = Field	#9.#30;	//  scala/xml/parsing/FactoryAdapter$$anonfun$startElement$1.m$1:Lscala/runtime/ObjectRef;
const #32 = NameAndType	#12:#13;//  scpe$1:Lscala/runtime/ObjectRef;
const #33 = Field	#9.#32;	//  scala/xml/parsing/FactoryAdapter$$anonfun$startElement$1.scpe$1:Lscala/runtime/ObjectRef;
const #34 = Asciz	java/lang/Object;
const #35 = class	#34;	//  java/lang/Object
const #36 = Method	#35.#24;	//  java/lang/Object."<init>":()V
const #37 = Asciz	scala/Function1$class;
const #38 = class	#37;	//  scala/Function1$class
const #39 = Asciz	$init$;
const #40 = Asciz	(Lscala/Function1;)V;
const #41 = NameAndType	#39:#40;//  $init$:(Lscala/Function1;)V
const #42 = Method	#38.#41;	//  scala/Function1$class.$init$:(Lscala/Function1;)V
const #43 = Asciz	this;
const #44 = Asciz	Lscala/xml/parsing/FactoryAdapter$$anonfun$startElement$1;;
const #45 = Asciz	LocalVariableTable;
const #46 = Asciz	nullIfEmpty$1;
const #47 = Asciz	(Ljava/lang/String;)Ljava/lang/String;;
const #48 = Asciz	;
const #49 = String	#48;	//  
const #50 = Asciz	equals;
const #51 = Asciz	(Ljava/lang/Object;)Z;
const #52 = NameAndType	#50:#51;//  equals:(Ljava/lang/Object;)Z
const #53 = Method	#35.#52;	//  java/lang/Object.equals:(Ljava/lang/Object;)Z
const #54 = Asciz	s;
const #55 = Asciz	Ljava/lang/String;;
const #56 = Asciz	apply;
const #57 = Asciz	(Ljava/lang/Object;)Ljava/lang/Object;;
const #58 = Asciz	scala/runtime/BoxesRunTime;
const #59 = class	#58;	//  scala/runtime/BoxesRunTime
const #60 = Asciz	unboxToInt;
const #61 = Asciz	(Ljava/lang/Object;)I;
const #62 = NameAndType	#60:#61;//  unboxToInt:(Ljava/lang/Object;)I
const #63 = Method	#59.#62;	//  scala/runtime/BoxesRunTime.unboxToInt:(Ljava/lang/Object;)I
const #64 = Asciz	(I)V;
const #65 = NameAndType	#56:#64;//  apply:(I)V
const #66 = Method	#9.#65;	//  scala/xml/parsing/FactoryAdapter$$anonfun$startElement$1.apply:(I)V
const #67 = Asciz	scala/runtime/BoxedUnit;
const #68 = class	#67;	//  scala/runtime/BoxedUnit
const #69 = Asciz	UNIT;
const #70 = Asciz	Lscala/runtime/BoxedUnit;;
const #71 = NameAndType	#69:#70;//  UNIT:Lscala/runtime/BoxedUnit;
const #72 = Field	#68.#71;	//  scala/runtime/BoxedUnit.UNIT:Lscala/runtime/BoxedUnit;
const #73 = Asciz	v1;
const #74 = Asciz	Ljava/lang/Object;;
const #75 = Asciz	org/xml/sax/Attributes;
const #76 = class	#75;	//  org/xml/sax/Attributes
const #77 = Asciz	getQName;
const #78 = Asciz	(I)Ljava/lang/String;;
const #79 = NameAndType	#77:#78;//  getQName:(I)Ljava/lang/String;
const #80 = InterfaceMethod	#76.#79;	//  org/xml/sax/Attributes.getQName:(I)Ljava/lang/String;
const #81 = Asciz	getValue;
const #82 = NameAndType	#81:#78;//  getValue:(I)Ljava/lang/String;
const #83 = InterfaceMethod	#76.#82;	//  org/xml/sax/Attributes.getValue:(I)Ljava/lang/String;
const #84 = Asciz	scala/xml/parsing/FactoryAdapter;
const #85 = class	#84;	//  scala/xml/parsing/FactoryAdapter
const #86 = Asciz	scala$xml$parsing$FactoryAdapter$$splitName;
const #87 = Asciz	(Ljava/lang/String;)Lscala/Tuple2;;
const #88 = NameAndType	#86:#87;//  scala$xml$parsing$FactoryAdapter$$splitName:(Ljava/lang/String;)Lscala/Tuple2;
const #89 = Method	#85.#88;	//  scala/xml/parsing/FactoryAdapter.scala$xml$parsing$FactoryAdapter$$splitName:(Ljava/lang/String;)Lscala/Tuple2;
const #90 = Asciz	scala/Tuple2;
const #91 = class	#90;	//  scala/Tuple2
const #92 = Asciz	_1;
const #93 = Asciz	()Ljava/lang/Object;;
const #94 = NameAndType	#92:#93;//  _1:()Ljava/lang/Object;
const #95 = Method	#91.#94;	//  scala/Tuple2._1:()Ljava/lang/Object;
const #96 = Asciz	java/lang/String;
const #97 = class	#96;	//  java/lang/String
const #98 = Asciz	_2;
const #99 = NameAndType	#98:#93;//  _2:()Ljava/lang/Object;
const #100 = Method	#91.#99;	//  scala/Tuple2._2:()Ljava/lang/Object;
const #101 = Asciz	(Ljava/lang/Object;Ljava/lang/Object;)V;
const #102 = NameAndType	#19:#101;//  "<init>":(Ljava/lang/Object;Ljava/lang/Object;)V
const #103 = Method	#91.#102;	//  scala/Tuple2."<init>":(Ljava/lang/Object;Ljava/lang/Object;)V
const #104 = Asciz	xmlns;
const #105 = String	#104;	//  xmlns
const #106 = Asciz	scala/xml/NamespaceBinding;
const #107 = class	#106;	//  scala/xml/NamespaceBinding
const #108 = NameAndType	#46:#47;//  nullIfEmpty$1:(Ljava/lang/String;)Ljava/lang/String;
const #109 = Method	#9.#108;	//  scala/xml/parsing/FactoryAdapter$$anonfun$startElement$1.nullIfEmpty$1:(Ljava/lang/String;)Ljava/lang/String;
const #110 = Asciz	scala/runtime/ObjectRef;
const #111 = class	#110;	//  scala/runtime/ObjectRef
const #112 = Asciz	elem;
const #113 = NameAndType	#112:#74;//  elem:Ljava/lang/Object;
const #114 = Field	#111.#113;	//  scala/runtime/ObjectRef.elem:Ljava/lang/Object;
const #115 = Asciz	(Ljava/lang/String;Ljava/lang/String;Lscala/xml/NamespaceBinding;)V;
const #116 = NameAndType	#19:#115;//  "<init>":(Ljava/lang/String;Ljava/lang/String;Lscala/xml/NamespaceBinding;)V
const #117 = Method	#107.#116;	//  scala/xml/NamespaceBinding."<init>":(Ljava/lang/String;Ljava/lang/String;Lscala/xml/NamespaceBinding;)V
const #118 = Asciz	scala/xml/Attribute$;
const #119 = class	#118;	//  scala/xml/Attribute$
const #120 = Asciz	MODULE$;
const #121 = Asciz	Lscala/xml/Attribute$;;
const #122 = NameAndType	#120:#121;//  MODULE$:Lscala/xml/Attribute$;
const #123 = Field	#119.#122;	//  scala/xml/Attribute$.MODULE$:Lscala/xml/Attribute$;
const #124 = Asciz	scala/Option$;
const #125 = class	#124;	//  scala/Option$
const #126 = Asciz	Lscala/Option$;;
const #127 = NameAndType	#120:#126;//  MODULE$:Lscala/Option$;
const #128 = Field	#125.#127;	//  scala/Option$.MODULE$:Lscala/Option$;
const #129 = Asciz	(Ljava/lang/Object;)Lscala/Option;;
const #130 = NameAndType	#56:#129;//  apply:(Ljava/lang/Object;)Lscala/Option;
const #131 = Method	#125.#130;	//  scala/Option$.apply:(Ljava/lang/Object;)Lscala/Option;
const #132 = Asciz	scala/xml/Text$;
const #133 = class	#132;	//  scala/xml/Text$
const #134 = Asciz	Lscala/xml/Text$;;
const #135 = NameAndType	#120:#134;//  MODULE$:Lscala/xml/Text$;
const #136 = Field	#133.#135;	//  scala/xml/Text$.MODULE$:Lscala/xml/Text$;
const #137 = Asciz	(Ljava/lang/String;)Lscala/xml/Text;;
const #138 = NameAndType	#56:#137;//  apply:(Ljava/lang/String;)Lscala/xml/Text;
const #139 = Method	#133.#138;	//  scala/xml/Text$.apply:(Ljava/lang/String;)Lscala/xml/Text;
const #140 = Asciz	scala/xml/MetaData;
const #141 = class	#140;	//  scala/xml/MetaData
const #142 = Asciz	(Lscala/Option;Ljava/lang/String;Lscala/collection/Seq;Lscala/xml/MetaData;)Lscala/xml/Attribute;;
const #143 = NameAndType	#56:#142;//  apply:(Lscala/Option;Ljava/lang/String;Lscala/collection/Seq;Lscala/xml/MetaData;)Lscala/xml/Attribute;
const #144 = Method	#119.#143;	//  scala/xml/Attribute$.apply:(Lscala/Option;Ljava/lang/String;Lscala/collection/Seq;Lscala/xml/MetaData;)Lscala/xml/Attribute;
const #145 = Asciz	scala/MatchError;
const #146 = class	#145;	//  scala/MatchError
const #147 = Asciz	toString;
const #148 = Asciz	()Ljava/lang/String;;
const #149 = NameAndType	#147:#148;//  toString:()Ljava/lang/String;
const #150 = Method	#91.#149;	//  scala/Tuple2.toString:()Ljava/lang/String;
const #151 = Asciz	(Ljava/lang/String;)V;
const #152 = NameAndType	#19:#151;//  "<init>":(Ljava/lang/String;)V
const #153 = Method	#146.#152;	//  scala/MatchError."<init>":(Ljava/lang/String;)V
const #154 = Asciz	i;
const #155 = Asciz	I;
const #156 = Asciz	temp2;
const #157 = Asciz	temp3;
const #158 = Asciz	qname;
const #159 = Asciz	arg;
const #160 = Asciz	pre;
const #161 = Asciz	key;
const #162 = Asciz	value;
const #163 = Asciz	temp1;
const #164 = Asciz	Lscala/Tuple2;;
const #165 = Asciz	andThen;
const #166 = Asciz	(Lscala/Function1;)Lscala/Function1;;
const #167 = Asciz	(Lscala/Function1;Lscala/Function1;)Lscala/Function1;;
const #168 = NameAndType	#165:#167;//  andThen:(Lscala/Function1;Lscala/Function1;)Lscala/Function1;
const #169 = Method	#38.#168;	//  scala/Function1$class.andThen:(Lscala/Function1;Lscala/Function1;)Lscala/Function1;
const #170 = Asciz	g;
const #171 = Asciz	Lscala/Function1;;
const #172 = Asciz	compose;
const #173 = NameAndType	#172:#167;//  compose:(Lscala/Function1;Lscala/Function1;)Lscala/Function1;
const #174 = Method	#38.#173;	//  scala/Function1$class.compose:(Lscala/Function1;Lscala/Function1;)Lscala/Function1;
const #175 = Asciz	(Lscala/Function1;)Ljava/lang/String;;
const #176 = NameAndType	#147:#175;//  toString:(Lscala/Function1;)Ljava/lang/String;
const #177 = Method	#38.#176;	//  scala/Function1$class.toString:(Lscala/Function1;)Ljava/lang/String;
const #178 = Asciz	Scala;
const #179 = Asciz	InnerClasses;
const #180 = Asciz	$anonfun$startElement$1;
const #181 = Asciz	scala/Function1;
const #182 = class	#181;	//  scala/Function1
const #183 = Asciz	scala/ScalaObject;
const #184 = class	#183;	//  scala/ScalaObject
const #185 = Asciz	java/io/Serializable;
const #186 = class	#185;	//  java/io/Serializable

{
public static final long serialVersionUID;

public static {};
  Code:
   Stack=2, Locals=0, Args_size=0
   0:	lconst_0
   1:	putstatic	#11; //Field serialVersionUID:J
   4:	return

public scala.xml.parsing.FactoryAdapter$$anonfun$startElement$1(scala.xml.parsing.FactoryAdapter, org.xml.sax.Attributes, scala.runtime.ObjectRef, scala.runtime.ObjectRef);
  Code:
   Stack=2, Locals=5, Args_size=5
   0:	aload_1
   1:	ifnonnull	12
   4:	new	#23; //class java/lang/NullPointerException
   7:	dup
   8:	invokespecial	#25; //Method java/lang/NullPointerException."<init>":()V
   11:	athrow
   12:	aload_0
   13:	aload_1
   14:	putfield	#27; //Field $outer:Lscala/xml/parsing/FactoryAdapter;
   17:	aload_0
   18:	aload_2
   19:	putfield	#29; //Field attributes$1:Lorg/xml/sax/Attributes;
   22:	aload_0
   23:	aload_3
   24:	putfield	#31; //Field m$1:Lscala/runtime/ObjectRef;
   27:	aload_0
   28:	aload	4
   30:	putfield	#33; //Field scpe$1:Lscala/runtime/ObjectRef;
   33:	aload_0
   34:	invokespecial	#36; //Method java/lang/Object."<init>":()V
   37:	aload_0
   38:	invokestatic	#42; //Method scala/Function1$class.$init$:(Lscala/Function1;)V
   41:	return
  LineNumberTable: 
   line 140: 0

  LocalVariableTable: 
   Start  Length  Slot  Name   Signature
   0      42      0    this       Lscala/xml/parsing/FactoryAdapter$$anonfun$startElement$1;
   0      42      1    $outer       Lscala/xml/parsing/FactoryAdapter;


public final java.lang.Object apply(java.lang.Object);
  Code:
   Stack=2, Locals=3, Args_size=2
   0:	aload_0
   1:	getfield	#27; //Field $outer:Lscala/xml/parsing/FactoryAdapter;
   4:	astore_2
   5:	aload_0
   6:	aload_1
   7:	invokestatic	#63; //Method scala/runtime/BoxesRunTime.unboxToInt:(Ljava/lang/Object;)I
   10:	invokevirtual	#66; //Method apply:(I)V
   13:	getstatic	#72; //Field scala/runtime/BoxedUnit.UNIT:Lscala/runtime/BoxedUnit;
   16:	areturn
  LineNumberTable: 
   line 140: 0

  LocalVariableTable: 
   Start  Length  Slot  Name   Signature
   0      17      0    this       Lscala/xml/parsing/FactoryAdapter$$anonfun$startElement$1;
   5      12      1    v1       Ljava/lang/Object;


public final void apply(int);
  Code:
   Stack=6, Locals=14, Args_size=2
   0:	aload_0
   1:	getfield	#27; //Field $outer:Lscala/xml/parsing/FactoryAdapter;
   4:	astore	13
   6:	aload_0
   7:	getfield	#29; //Field attributes$1:Lorg/xml/sax/Attributes;
   10:	iload_1
   11:	invokeinterface	#80,  2; //InterfaceMethod org/xml/sax/Attributes.getQName:(I)Ljava/lang/String;
   16:	astore	6
   18:	aload_0
   19:	getfield	#29; //Field attributes$1:Lorg/xml/sax/Attributes;
   22:	iload_1
   23:	invokeinterface	#83,  2; //InterfaceMethod org/xml/sax/Attributes.getValue:(I)Ljava/lang/String;
   28:	astore	11
   30:	aload_0
   31:	getfield	#27; //Field $outer:Lscala/xml/parsing/FactoryAdapter;
   34:	aload	6
   36:	invokevirtual	#89; //Method scala/xml/parsing/FactoryAdapter.scala$xml$parsing$FactoryAdapter$$splitName:(Ljava/lang/String;)Lscala/Tuple2;
   39:	astore	12
   41:	aload	12
   43:	ifnull	286
   46:	aload	12
   48:	invokevirtual	#95; //Method scala/Tuple2._1:()Ljava/lang/Object;
   51:	checkcast	#97; //class java/lang/String
   54:	astore_2
   55:	aload	12
   57:	invokevirtual	#100; //Method scala/Tuple2._2:()Ljava/lang/Object;
   60:	checkcast	#97; //class java/lang/String
   63:	astore_3
   64:	iconst_1
   65:	ifeq	273
   68:	new	#91; //class scala/Tuple2
   71:	dup
   72:	aload_2
   73:	aload_3
   74:	invokespecial	#103; //Method scala/Tuple2."<init>":(Ljava/lang/Object;Ljava/lang/Object;)V
   77:	astore	4
   79:	aload	4
   81:	invokevirtual	#95; //Method scala/Tuple2._1:()Ljava/lang/Object;
   84:	checkcast	#97; //class java/lang/String
   87:	astore	9
   89:	aload	4
   91:	invokevirtual	#100; //Method scala/Tuple2._2:()Ljava/lang/Object;
   94:	checkcast	#97; //class java/lang/String
   97:	astore	10
   99:	aload	9
   101:	ldc	#105; //String xmlns
   103:	astore	5
   105:	dup
   106:	ifnonnull	118
   109:	pop
   110:	aload	5
   112:	ifnull	169
   115:	goto	126
   118:	aload	5
   120:	invokevirtual	#53; //Method java/lang/Object.equals:(Ljava/lang/Object;)Z
   123:	ifne	169
   126:	aload	9
   128:	dup
   129:	pop
   130:	ifnull	142
   133:	aload	9
   135:	aconst_null
   136:	invokevirtual	#53; //Method java/lang/Object.equals:(Ljava/lang/Object;)Z
   139:	ifeq	228
   142:	aload	6
   144:	ldc	#105; //String xmlns
   146:	astore	7
   148:	dup
   149:	ifnonnull	161
   152:	pop
   153:	aload	7
   155:	ifnull	169
   158:	goto	228
   161:	aload	7
   163:	invokevirtual	#53; //Method java/lang/Object.equals:(Ljava/lang/Object;)Z
   166:	ifeq	228
   169:	aload	9
   171:	dup
   172:	pop
   173:	ifnull	185
   176:	aload	9
   178:	aconst_null
   179:	invokevirtual	#53; //Method java/lang/Object.equals:(Ljava/lang/Object;)Z
   182:	ifeq	189
   185:	aconst_null
   186:	goto	191
   189:	aload	10
   191:	astore	8
   193:	aload_0
   194:	getfield	#33; //Field scpe$1:Lscala/runtime/ObjectRef;
   197:	new	#107; //class scala/xml/NamespaceBinding
   200:	dup
   201:	aload	8
   203:	aload_0
   204:	aload	11
   206:	invokespecial	#109; //Method nullIfEmpty$1:(Ljava/lang/String;)Ljava/lang/String;
   209:	aload_0
   210:	getfield	#33; //Field scpe$1:Lscala/runtime/ObjectRef;
   213:	getfield	#114; //Field scala/runtime/ObjectRef.elem:Ljava/lang/Object;
   216:	checkcast	#107; //class scala/xml/NamespaceBinding
   219:	invokespecial	#117; //Method scala/xml/NamespaceBinding."<init>":(Ljava/lang/String;Ljava/lang/String;Lscala/xml/NamespaceBinding;)V
   222:	putfield	#114; //Field scala/runtime/ObjectRef.elem:Ljava/lang/Object;
   225:	goto	272
   228:	aload_0
   229:	getfield	#31; //Field m$1:Lscala/runtime/ObjectRef;
   232:	getstatic	#123; //Field scala/xml/Attribute$.MODULE$:Lscala/xml/Attribute$;
   235:	getstatic	#128; //Field scala/Option$.MODULE$:Lscala/Option$;
   238:	aload	9
   240:	invokevirtual	#131; //Method scala/Option$.apply:(Ljava/lang/Object;)Lscala/Option;
   243:	aload	10
   245:	getstatic	#136; //Field scala/xml/Text$.MODULE$:Lscala/xml/Text$;
   248:	aload	11
   250:	invokevirtual	#139; //Method scala/xml/Text$.apply:(Ljava/lang/String;)Lscala/xml/Text;
   253:	aload_0
   254:	getfield	#31; //Field m$1:Lscala/runtime/ObjectRef;
   257:	getfield	#114; //Field scala/runtime/ObjectRef.elem:Ljava/lang/Object;
   260:	checkcast	#141; //class scala/xml/MetaData
   263:	invokevirtual	#144; //Method scala/xml/Attribute$.apply:(Lscala/Option;Ljava/lang/String;Lscala/collection/Seq;Lscala/xml/MetaData;)Lscala/xml/Attribute;
   266:	checkcast	#141; //class scala/xml/MetaData
   269:	putfield	#114; //Field scala/runtime/ObjectRef.elem:Ljava/lang/Object;
   272:	return
   273:	new	#146; //class scala/MatchError
   276:	dup
   277:	aload	12
   279:	invokevirtual	#150; //Method scala/Tuple2.toString:()Ljava/lang/String;
   282:	invokespecial	#153; //Method scala/MatchError."<init>":(Ljava/lang/String;)V
   285:	athrow
   286:	new	#146; //class scala/MatchError
   289:	dup
   290:	aload	12
   292:	invokevirtual	#150; //Method scala/Tuple2.toString:()Ljava/lang/String;
   295:	invokespecial	#153; //Method scala/MatchError."<init>":(Ljava/lang/String;)V
   298:	athrow
  LineNumberTable: 
   line 141: 0
   line 142: 18
   line 143: 30
   line 21: 64
   line 143: 68
   line 146: 99
   line 147: 169
   line 148: 193
   line 151: 228
   line 140: 272
   line 143: 273

  LocalVariableTable: 
   Start  Length  Slot  Name   Signature
   0      299      0    this       Lscala/xml/parsing/FactoryAdapter$$anonfun$startElement$1;
   6      293      1    i       I
   55      54      2    temp2       Ljava/lang/String;
   273      13      2    temp2       Ljava/lang/String;
   64      45      3    temp3       Ljava/lang/String;
   273      13      3    temp3       Ljava/lang/String;
   18      281      6    qname       Ljava/lang/String;
   193      32      8    arg       Ljava/lang/String;
   89      184      9    pre       Ljava/lang/String;
   99      174      10    key       Ljava/lang/String;
   30      269      11    value       Ljava/lang/String;
   41      68      12    temp1       Lscala/Tuple2;
   273      26      12    temp1       Lscala/Tuple2;


public scala.Function1 andThen(scala.Function1);
  Code:
   Stack=2, Locals=2, Args_size=2
   0:	aload_0
   1:	aload_1
   2:	invokestatic	#169; //Method scala/Function1$class.andThen:(Lscala/Function1;Lscala/Function1;)Lscala/Function1;
   5:	areturn
  LineNumberTable: 
   line 140: 0

  LocalVariableTable: 
   Start  Length  Slot  Name   Signature
   0      6      0    this       Lscala/xml/parsing/FactoryAdapter$$anonfun$startElement$1;
   0      6      1    g       Lscala/Function1;


public scala.Function1 compose(scala.Function1);
  Code:
   Stack=2, Locals=2, Args_size=2
   0:	aload_0
   1:	aload_1
   2:	invokestatic	#174; //Method scala/Function1$class.compose:(Lscala/Function1;Lscala/Function1;)Lscala/Function1;
   5:	areturn
  LineNumberTable: 
   line 140: 0

  LocalVariableTable: 
   Start  Length  Slot  Name   Signature
   0      6      0    this       Lscala/xml/parsing/FactoryAdapter$$anonfun$startElement$1;
   0      6      1    g       Lscala/Function1;


public java.lang.String toString();
  Code:
   Stack=1, Locals=1, Args_size=1
   0:	aload_0
   1:	invokestatic	#177; //Method scala/Function1$class.toString:(Lscala/Function1;)Ljava/lang/String;
   4:	areturn
  LineNumberTable: 
   line 140: 0


}

