Compiled from "FactoryAdapter.scala"
public final class scala.xml.parsing.FactoryAdapter$$anonfun$2 extends scala.runtime.AbstractFunction1 implements java.io.Serializable
  SourceFile: "FactoryAdapter.scala"
  Scala: length = 0x
   
  InnerClass: 
   public final $anonfun$2=class scala/xml/parsing/FactoryAdapter$$anonfun$2 of class scala/xml/parsing/FactoryAdapter
  minor version: 0
  major version: 49
  Constant pool:
Asciz	SourceFile;
Asciz	FactoryAdapter.scala;
Asciz	<clinit>;
Asciz	()V;
Asciz	Code;
Asciz	serialVersionUID;
Asciz	J;
Asciz	scala/xml/parsing/FactoryAdapter$$anonfun$2;
class	scala/xml/parsing/FactoryAdapter$$anonfun$2
NameAndType	serialVersionUID:J
Field	scala/xml/parsing/FactoryAdapter$$anonfun$2.serialVersionUID:J
Asciz	<init>;
Asciz	(Lscala/xml/parsing/FactoryAdapter;)V;
Asciz	LineNumberTable;
Asciz	scala/runtime/AbstractFunction1;
class	scala/runtime/AbstractFunction1
NameAndType	"<init>":()V
Method	scala/runtime/AbstractFunction1."<init>":()V
Asciz	this;
Asciz	Lscala/xml/parsing/FactoryAdapter$$anonfun$2;;
Asciz	$outer;
Asciz	Lscala/xml/parsing/FactoryAdapter;;
Asciz	LocalVariableTable;
Asciz	apply;
Asciz	(Ljava/lang/Object;)Ljava/lang/Object;;
Asciz	scala/xml/Node;
class	scala/xml/Node
Asciz	(Lscala/xml/Node;)Z;
NameAndType	apply:(Lscala/xml/Node;)Z
Method	scala/xml/parsing/FactoryAdapter$$anonfun$2.apply:(Lscala/xml/Node;)Z
Asciz	scala/runtime/BoxesRunTime;
class	scala/runtime/BoxesRunTime
Asciz	boxToBoolean;
Asciz	(Z)Ljava/lang/Boolean;;
NameAndType	boxToBoolean:(Z)Ljava/lang/Boolean;
Method	scala/runtime/BoxesRunTime.boxToBoolean:(Z)Ljava/lang/Boolean;
Asciz	v1;
Asciz	Ljava/lang/Object;;
Asciz	java/lang/Object;
class	java/lang/Object
Asciz	equals;
Asciz	(Ljava/lang/Object;)Z;
NameAndType	equals:(Ljava/lang/Object;)Z
Method	java/lang/Object.equals:(Ljava/lang/Object;)Z
Asciz	Scala;
Asciz	InnerClasses;
Asciz	scala/xml/parsing/FactoryAdapter;
class	scala/xml/parsing/FactoryAdapter
Asciz	$anonfun$2;
Asciz	java/io/Serializable;
class	java/io/Serializable

{
public static final long serialVersionUID;
  Signature: J

public static {};
  Signature: ()V
  Code:
   Stack=2, Locals=0, Args_size=0
	lconst_0
	putstatic	Field serialVersionUID:J
	return
  Labels:

public scala.xml.parsing.FactoryAdapter$$anonfun$2(scala.xml.parsing.FactoryAdapter);
  Signature: (Lscala/xml/parsing/FactoryAdapter;)V
  Code:
   Stack=1, Locals=2, Args_size=2
	aload_0
	invokespecial	Method scala/runtime/AbstractFunction1."<init>":()V
	return
  Labels:
  LocalVariableTable: 
   Start  Length  Slot  Name   Signature
   0      5      0    this       Lscala/xml/parsing/FactoryAdapter$$anonfun$2;
   0      5      1    $outer       Lscala/xml/parsing/FactoryAdapter;


public final java.lang.Object apply(java.lang.Object);
  Signature: (Ljava/lang/Object;)Ljava/lang/Object;
  Code:
   Stack=2, Locals=3, Args_size=2
	aload_0
	aload_1
	checkcast	class scala/xml/Node
	invokevirtual	Method apply:(Lscala/xml/Node;)Z
	istore_2
	iload_2
	invokestatic	Method scala/runtime/BoxesRunTime.boxToBoolean:(Z)Ljava/lang/Boolean;
	areturn
  Labels:
  LocalVariableTable: 
   Start  Length  Slot  Name   Signature
   0      14      0    this       Lscala/xml/parsing/FactoryAdapter$$anonfun$2;
   0      14      1    v1       Ljava/lang/Object;


public final boolean apply(scala.xml.Node);
  Signature: (Lscala/xml/Node;)Z
  Code:
   Stack=2, Locals=2, Args_size=2
	aload_1
	dup
	pop
	ifnull	l1 // iconst_0
	aload_1
	aconst_null
	invokevirtual	Method java/lang/Object.equals:(Ljava/lang/Object;)Z
	ifeq	l2 // iconst_1
l1	iconst_0
	goto	l3 // ireturn
l2	iconst_1
l3	ireturn
  Labels:
   	l1 = 14 // iconst_0
   	l2 = 18 // iconst_1
   	l3 = 19 // ireturn

}

