Compiled from "FatalError.scala"
public class scala.xml.parsing.FatalError extends java.lang.RuntimeException implements scala.ScalaObject,scala.Product,java.io.Serializable
  SourceFile: "FatalError.scala"
  ScalaSig: length = 0x3
   05 00 00 
  RuntimeVisibleAnnotations: length = 0xB
   00 01 00 6D 00 01 00 6E 73 00 6F 
  minor version: 0
  major version: 49
  Constant pool:
Asciz	SourceFile;
Asciz	FatalError.scala;
Asciz	andThen;
Asciz	(Lscala/Function1;)Lscala/Function1;;
Asciz	Code;
Asciz	scala/xml/parsing/FatalError$;
class	scala/xml/parsing/FatalError$
Asciz	MODULE$;
Asciz	Lscala/xml/parsing/FatalError$;;
NameAndType	MODULE$:Lscala/xml/parsing/FatalError$;
Field	scala/xml/parsing/FatalError$.MODULE$:Lscala/xml/parsing/FatalError$;
NameAndType	andThen:(Lscala/Function1;)Lscala/Function1;
Method	scala/xml/parsing/FatalError$.andThen:(Lscala/Function1;)Lscala/Function1;
Asciz	compose;
NameAndType	compose:(Lscala/Function1;)Lscala/Function1;
Method	scala/xml/parsing/FatalError$.compose:(Lscala/Function1;)Lscala/Function1;
Asciz	msg;
Asciz	Ljava/lang/String;;
Asciz	productElementName;
Asciz	(I)Ljava/lang/String;;
Asciz	LineNumberTable;
Asciz	scala/Product$class;
class	scala/Product$class
Asciz	(Lscala/Product;I)Ljava/lang/String;;
NameAndType	productElementName:(Lscala/Product;I)Ljava/lang/String;
Method	scala/Product$class.productElementName:(Lscala/Product;I)Ljava/lang/String;
Asciz	this;
Asciz	Lscala/xml/parsing/FatalError;;
Asciz	n;
Asciz	I;
Asciz	LocalVariableTable;
Asciz	productIterator;
Asciz	()Lscala/collection/Iterator;;
Asciz	(Lscala/Product;)Lscala/collection/Iterator;;
NameAndType	productIterator:(Lscala/Product;)Lscala/collection/Iterator;
Method	scala/Product$class.productIterator:(Lscala/Product;)Lscala/collection/Iterator;
Asciz	productElements;
NameAndType	productElements:(Lscala/Product;)Lscala/collection/Iterator;
Method	scala/Product$class.productElements:(Lscala/Product;)Lscala/collection/Iterator;
Asciz	Deprecated;
Asciz	copy$default$1;
Asciz	()Ljava/lang/String;;
Asciz	scala/xml/parsing/FatalError;
class	scala/xml/parsing/FatalError
NameAndType	msg:()Ljava/lang/String;
Method	scala/xml/parsing/FatalError.msg:()Ljava/lang/String;
NameAndType	msg:Ljava/lang/String;
Field	scala/xml/parsing/FatalError.msg:Ljava/lang/String;
Asciz	copy;
Asciz	(Ljava/lang/String;)Lscala/xml/parsing/FatalError;;
Asciz	<init>;
Asciz	(Ljava/lang/String;)V;
NameAndType	"<init>":(Ljava/lang/String;)V
Method	scala/xml/parsing/FatalError."<init>":(Ljava/lang/String;)V
Asciz	hashCode;
Asciz	()I;
Asciz	scala/runtime/ScalaRunTime$;
class	scala/runtime/ScalaRunTime$
Asciz	Lscala/runtime/ScalaRunTime$;;
NameAndType	MODULE$:Lscala/runtime/ScalaRunTime$;
Field	scala/runtime/ScalaRunTime$.MODULE$:Lscala/runtime/ScalaRunTime$;
Asciz	_hashCode;
Asciz	(Lscala/Product;)I;
NameAndType	_hashCode:(Lscala/Product;)I
Method	scala/runtime/ScalaRunTime$._hashCode:(Lscala/Product;)I
Asciz	equals;
Asciz	(Ljava/lang/Object;)Z;
Asciz	gd1$1;
Asciz	(Ljava/lang/String;)Z;
NameAndType	gd1$1:(Ljava/lang/String;)Z
Method	scala/xml/parsing/FatalError.gd1$1:(Ljava/lang/String;)Z
Asciz	scala/Equals;
class	scala/Equals
Asciz	canEqual;
NameAndType	canEqual:(Ljava/lang/Object;)Z
InterfaceMethod	scala/Equals.canEqual:(Ljava/lang/Object;)Z
Asciz	temp2;
Asciz	temp3;
Asciz	productPrefix;
Asciz	FatalError;
String	FatalError
Asciz	productArity;
Asciz	productElement;
Asciz	(I)Ljava/lang/Object;;
Asciz	java/lang/IndexOutOfBoundsException;
class	java/lang/IndexOutOfBoundsException
Asciz	scala/runtime/BoxesRunTime;
class	scala/runtime/BoxesRunTime
Asciz	boxToInteger;
Asciz	(I)Ljava/lang/Integer;;
NameAndType	boxToInteger:(I)Ljava/lang/Integer;
Method	scala/runtime/BoxesRunTime.boxToInteger:(I)Ljava/lang/Integer;
Asciz	java/lang/Object;
class	java/lang/Object
Asciz	toString;
NameAndType	toString:()Ljava/lang/String;
Method	java/lang/Object.toString:()Ljava/lang/String;
Method	java/lang/IndexOutOfBoundsException."<init>":(Ljava/lang/String;)V
NameAndType	equals:(Ljava/lang/Object;)Z
Method	java/lang/Object.equals:(Ljava/lang/Object;)Z
Asciz	java/lang/RuntimeException;
class	java/lang/RuntimeException
Method	java/lang/RuntimeException."<init>":(Ljava/lang/String;)V
Asciz	$init$;
Asciz	(Lscala/Product;)V;
NameAndType	$init$:(Lscala/Product;)V
Method	scala/Product$class.$init$:(Lscala/Product;)V
Asciz	ScalaSig;
Asciz	Lscala/reflect/ScalaSignature;;
Asciz	bytes;
Asciz	i4\"\t)\r$\r\#se>(BAM]:j]T!!alGNC8-7bB-A1E)QBDYtwMCQM^1\nEa!*v]RLW.Z#yGH/[8o!\tB#D\t)bAATGdm2kK$CA\n\tAbAAQe>$Wo;\ti!Q3Am\t1!\:h+aCA!\tb$ \r1K]3eKL!!\t\rM#(/8h\tyb%\tE\t!i7o\tAA\rqJg.;?)\tA#*5\t!CKAC-IA\t\r|/Q9BqAGAC1EIA\r|/eKW;%cU\t!Gg-\nA6u5\taG8qIQO\2iK\W\rs\t!\"8o_RG/[8o\tYdGA\tv]DWmY6fIZ'/[1oGD\"%\tEP\tQnQ8eKR\tq&I:$C\"\tI\t#\rX/7t)\t)\n\r&qI>|G.Z1oI%)!AA)12!\t2*M\r\tI\=\t9A!AB=Q:pIVG:fM&DX#)-\tBA\r!\"A\n\"9s_,8\r^!sSRLX#A \tYA!AB]a:pIVG/7f[tGK1\"9*VAy.\tII.\rg.R9vC2$\"!/\t%K!a\"A\t'}K!M,'/[1mSj'\r\3\t!EGQa);bY(o:%\"gC\t\tRA34'hUrAS\"5%4a:v]RLW.ZW\"#2tiJ7\r$v]$n821C\r\"n)bB8e%\t\t]CBH.QEDQA8AqAqa3E/Av]\=UDcA\nw9%qOB$n8\tea$;
Asciz	RuntimeVisibleAnnotations;
Asciz	scala/ScalaObject;
class	scala/ScalaObject
Asciz	scala/Product;
class	scala/Product
Asciz	java/io/Serializable;
class	java/io/Serializable

{
private final java.lang.String msg;
  Signature: Ljava/lang/String;

public static final scala.Function1 andThen(scala.Function1);
  Signature: (Lscala/Function1;)Lscala/Function1;
  Code:
   Stack=2, Locals=1, Args_size=1
	getstatic	Field scala/xml/parsing/FatalError$.MODULE$:Lscala/xml/parsing/FatalError$;
	aload_0
	invokevirtual	Method scala/xml/parsing/FatalError$.andThen:(Lscala/Function1;)Lscala/Function1;
	areturn
  Labels:

public static final scala.Function1 compose(scala.Function1);
  Signature: (Lscala/Function1;)Lscala/Function1;
  Code:
   Stack=2, Locals=1, Args_size=1
	getstatic	Field scala/xml/parsing/FatalError$.MODULE$:Lscala/xml/parsing/FatalError$;
	aload_0
	invokevirtual	Method scala/xml/parsing/FatalError$.compose:(Lscala/Function1;)Lscala/Function1;
	areturn
  Labels:

public java.lang.String productElementName(int);
  Signature: (I)Ljava/lang/String;
  Code:
   Stack=2, Locals=2, Args_size=2
	aload_0
	iload_1
	invokestatic	Method scala/Product$class.productElementName:(Lscala/Product;I)Ljava/lang/String;
	areturn
  Labels:
  LocalVariableTable: 
   Start  Length  Slot  Name   Signature
   0      6      0    this       Lscala/xml/parsing/FatalError;
   0      6      1    n       I


public scala.collection.Iterator productIterator();
  Signature: ()Lscala/collection/Iterator;
  Code:
   Stack=1, Locals=1, Args_size=1
	aload_0
	invokestatic	Method scala/Product$class.productIterator:(Lscala/Product;)Lscala/collection/Iterator;
	areturn
  Labels:

public scala.collection.Iterator productElements();
  Signature: ()Lscala/collection/Iterator;
  Code:
   Stack=1, Locals=1, Args_size=1
	aload_0
	invokestatic	Method scala/Product$class.productElements:(Lscala/Product;)Lscala/collection/Iterator;
	areturn
  Labels:
  Deprecated: true

public java.lang.String copy$default$1();
  Signature: ()Ljava/lang/String;
  Code:
   Stack=1, Locals=1, Args_size=1
	aload_0
	invokevirtual	Method msg:()Ljava/lang/String;
	areturn
  Labels:

public java.lang.String msg();
  Signature: ()Ljava/lang/String;
  Code:
   Stack=1, Locals=1, Args_size=1
	aload_0
	getfield	Field msg:Ljava/lang/String;
	areturn
  Labels:

public scala.xml.parsing.FatalError copy(java.lang.String);
  Signature: (Ljava/lang/String;)Lscala/xml/parsing/FatalError;
  Code:
   Stack=3, Locals=2, Args_size=2
	new	class scala/xml/parsing/FatalError
	dup
	aload_1
	invokespecial	Method "<init>":(Ljava/lang/String;)V
	areturn
  Labels:
  LocalVariableTable: 
   Start  Length  Slot  Name   Signature
   0      9      0    this       Lscala/xml/parsing/FatalError;
   0      9      1    msg       Ljava/lang/String;


public int hashCode();
  Signature: ()I
  Code:
   Stack=2, Locals=1, Args_size=1
	getstatic	Field scala/runtime/ScalaRunTime$.MODULE$:Lscala/runtime/ScalaRunTime$;
	aload_0
	invokevirtual	Method scala/runtime/ScalaRunTime$._hashCode:(Lscala/Product;)I
	ireturn
  Labels:

public boolean equals(java.lang.Object);
  Signature: (Ljava/lang/Object;)Z
  Code:
   Stack=2, Locals=4, Args_size=2
	aload_0
	aload_1
	if_acmpeq	l1 // iconst_1
	aload_1
	instanceof	class scala/xml/parsing/FatalError
	ifeq	l2 // iconst_0
	aload_1
	checkcast	class scala/xml/parsing/FatalError
	astore_2
	aload_2
	invokevirtual	Method msg:()Ljava/lang/String;
	astore_3
	aload_0
	aload_3
	invokespecial	Method gd1$1:(Ljava/lang/String;)Z
	ifeq	l3 // iconst_0
	aload_1
	checkcast	class scala/xml/parsing/FatalError
	aload_0
	invokeinterface	InterfaceMethod scala/Equals.canEqual:(Ljava/lang/Object;)Z
	goto	l4 // ifeq
l3	iconst_0
	goto	l4 // ifeq
l2	iconst_0
l4	ifeq	l5 // iconst_0
l1	iconst_1
	goto	l6 // ireturn
l5	iconst_0
l6	ireturn
  Labels:
   	l3 = 43 // iconst_0
   	l2 = 47 // iconst_0
   	l4 = 48 // ifeq
   	l1 = 51 // iconst_1
   	l5 = 55 // iconst_0
   	l6 = 56 // ireturn
  LocalVariableTable: 
   Start  Length  Slot  Name   Signature
   0      57      0    this       Lscala/xml/parsing/FatalError;
   17      30      2    temp2       Lscala/xml/parsing/FatalError;
   22      25      3    temp3       Ljava/lang/String;


public java.lang.String productPrefix();
  Signature: ()Ljava/lang/String;
  Code:
   Stack=1, Locals=1, Args_size=1
	ldc	String FatalError
	areturn
  Labels:

public int productArity();
  Signature: ()I
  Code:
   Stack=1, Locals=1, Args_size=1
	iconst_1
	ireturn
  Labels:

public java.lang.Object productElement(int);
  Signature: (I)Ljava/lang/Object;
  Code:
   Stack=3, Locals=2, Args_size=2
	iload_1
	iconst_0
	if_icmpne	l1 // new
	aload_0
	invokevirtual	Method msg:()Ljava/lang/String;
	areturn
l1	new	class java/lang/IndexOutOfBoundsException
	dup
	iload_1
	invokestatic	Method scala/runtime/BoxesRunTime.boxToInteger:(I)Ljava/lang/Integer;
	invokevirtual	Method java/lang/Object.toString:()Ljava/lang/String;
	invokespecial	Method java/lang/IndexOutOfBoundsException."<init>":(Ljava/lang/String;)V
	athrow
  Labels:
   	l1 = 10 // new

public boolean canEqual(java.lang.Object);
  Signature: (Ljava/lang/Object;)Z
  Code:
   Stack=1, Locals=2, Args_size=2
	aload_1
	instanceof	class scala/xml/parsing/FatalError
	ireturn
  Labels:

private final boolean gd1$1(java.lang.String);
  Signature: (Ljava/lang/String;)Z
  Code:
   Stack=2, Locals=3, Args_size=2
	aload_1
	aload_0
	invokevirtual	Method msg:()Ljava/lang/String;
	astore_2
	dup
	ifnonnull	l1 // aload_2
	pop
	aload_2
	ifnull	l2 // iconst_1
	goto	l3 // iconst_0
l1	aload_2
	invokevirtual	Method java/lang/Object.equals:(Ljava/lang/Object;)Z
	ifeq	l3 // iconst_0
l2	iconst_1
	goto	l4 // ireturn
l3	iconst_0
l4	ireturn
  Labels:
   	l1 = 18 // aload_2
   	l2 = 25 // iconst_1
   	l3 = 29 // iconst_0
   	l4 = 30 // ireturn

public scala.xml.parsing.FatalError(java.lang.String);
  Signature: (Ljava/lang/String;)V
  Code:
   Stack=2, Locals=2, Args_size=2
	aload_0
	aload_1
	putfield	Field msg:Ljava/lang/String;
	aload_0
	aload_1
	invokespecial	Method java/lang/RuntimeException."<init>":(Ljava/lang/String;)V
	aload_0
	invokestatic	Method scala/Product$class.$init$:(Lscala/Product;)V
	return
  Labels:
  LocalVariableTable: 
   Start  Length  Slot  Name   Signature
   0      15      0    this       Lscala/xml/parsing/FatalError;
   0      15      1    msg       Ljava/lang/String;


}

