Compiled from "MarkupParserCommon.scala"
public final class scala.xml.parsing.MarkupParserCommon$$anonfun$peek$1 extends scala.runtime.AbstractFunction1 implements java.io.Serializable
  SourceFile: "MarkupParserCommon.scala"
  Scala: length = 0x
   
  InnerClass: 
   public final $anonfun$peek$1=class scala/xml/parsing/MarkupParserCommon$$anonfun$peek$1 of class scala/xml/parsing/MarkupParserCommon
  minor version: 0
  major version: 49
  Constant pool:
Asciz	SourceFile;
Asciz	MarkupParserCommon.scala;
Asciz	<clinit>;
Asciz	()V;
Asciz	Code;
Asciz	serialVersionUID;
Asciz	J;
Asciz	scala/xml/parsing/MarkupParserCommon$$anonfun$peek$1;
class	scala/xml/parsing/MarkupParserCommon$$anonfun$peek$1
NameAndType	serialVersionUID:J
Field	scala/xml/parsing/MarkupParserCommon$$anonfun$peek$1.serialVersionUID:J
Asciz	$outer;
Asciz	Lscala/xml/parsing/MarkupParserCommon;;
Asciz	apply;
Asciz	(I)C;
Asciz	LineNumberTable;
NameAndType	$outer:Lscala/xml/parsing/MarkupParserCommon;
Field	scala/xml/parsing/MarkupParserCommon$$anonfun$peek$1.$outer:Lscala/xml/parsing/MarkupParserCommon;
Asciz	scala/xml/parsing/MarkupParserCommon;
class	scala/xml/parsing/MarkupParserCommon
Asciz	nextch;
Asciz	()C;
NameAndType	nextch:()C
InterfaceMethod	scala/xml/parsing/MarkupParserCommon.nextch:()C
Asciz	this;
Asciz	Lscala/xml/parsing/MarkupParserCommon$$anonfun$peek$1;;
Asciz	x$3;
Asciz	I;
Asciz	LocalVariableTable;
Asciz	(Ljava/lang/Object;)Ljava/lang/Object;;
Asciz	scala/runtime/BoxesRunTime;
class	scala/runtime/BoxesRunTime
Asciz	unboxToInt;
Asciz	(Ljava/lang/Object;)I;
NameAndType	unboxToInt:(Ljava/lang/Object;)I
Method	scala/runtime/BoxesRunTime.unboxToInt:(Ljava/lang/Object;)I
NameAndType	apply:(I)C
Method	scala/xml/parsing/MarkupParserCommon$$anonfun$peek$1.apply:(I)C
Asciz	boxToCharacter;
Asciz	(C)Ljava/lang/Character;;
NameAndType	boxToCharacter:(C)Ljava/lang/Character;
Method	scala/runtime/BoxesRunTime.boxToCharacter:(C)Ljava/lang/Character;
Asciz	v1;
Asciz	Ljava/lang/Object;;
Asciz	<init>;
Asciz	(Lscala/xml/parsing/MarkupParserCommon;)V;
Asciz	java/lang/NullPointerException;
class	java/lang/NullPointerException
NameAndType	"<init>":()V
Method	java/lang/NullPointerException."<init>":()V
Asciz	scala/runtime/AbstractFunction1;
class	scala/runtime/AbstractFunction1
Method	scala/runtime/AbstractFunction1."<init>":()V
Asciz	Scala;
Asciz	InnerClasses;
Asciz	$anonfun$peek$1;
Asciz	java/io/Serializable;
class	java/io/Serializable

{
public static final long serialVersionUID;
  Signature: J

private final scala.xml.parsing.MarkupParserCommon $outer;
  Signature: Lscala/xml/parsing/MarkupParserCommon;

public static {};
  Signature: ()V
  Code:
   Stack=2, Locals=0, Args_size=0
	lconst_0
	putstatic	Field serialVersionUID:J
	return
  Labels:

public final char apply(int);
  Signature: (I)C
  Code:
   Stack=1, Locals=2, Args_size=2
	aload_0
	getfield	Field $outer:Lscala/xml/parsing/MarkupParserCommon;
	invokeinterface	InterfaceMethod scala/xml/parsing/MarkupParserCommon.nextch:()C
	ireturn
  Labels:
  LocalVariableTable: 
   Start  Length  Slot  Name   Signature
   0      10      0    this       Lscala/xml/parsing/MarkupParserCommon$$anonfun$peek$1;
   0      10      1    x$3       I


public final java.lang.Object apply(java.lang.Object);
  Signature: (Ljava/lang/Object;)Ljava/lang/Object;
  Code:
   Stack=2, Locals=2, Args_size=2
	aload_0
	aload_1
	invokestatic	Method scala/runtime/BoxesRunTime.unboxToInt:(Ljava/lang/Object;)I
	invokevirtual	Method apply:(I)C
	invokestatic	Method scala/runtime/BoxesRunTime.boxToCharacter:(C)Ljava/lang/Character;
	areturn
  Labels:
  LocalVariableTable: 
   Start  Length  Slot  Name   Signature
   0      12      0    this       Lscala/xml/parsing/MarkupParserCommon$$anonfun$peek$1;
   0      12      1    v1       Ljava/lang/Object;


public scala.xml.parsing.MarkupParserCommon$$anonfun$peek$1(scala.xml.parsing.MarkupParserCommon);
  Signature: (Lscala/xml/parsing/MarkupParserCommon;)V
  Code:
   Stack=2, Locals=2, Args_size=2
	aload_1
	ifnonnull	l1 // aload_0
	new	class java/lang/NullPointerException
	dup
	invokespecial	Method java/lang/NullPointerException."<init>":()V
	athrow
l1	aload_0
	aload_1
	putfield	Field $outer:Lscala/xml/parsing/MarkupParserCommon;
	aload_0
	invokespecial	Method scala/runtime/AbstractFunction1."<init>":()V
	return
  Labels:
   	l1 = 12 // aload_0
  LocalVariableTable: 
   Start  Length  Slot  Name   Signature
   0      22      0    this       Lscala/xml/parsing/MarkupParserCommon$$anonfun$peek$1;
   0      22      1    $outer       Lscala/xml/parsing/MarkupParserCommon;


}

