Compiled from "MarkupParserCommon.scala"
public final class scala.xml.parsing.MarkupParserCommon$$anonfun$xProcInstr$1 extends scala.runtime.AbstractFunction2 implements java.io.Serializable
  SourceFile: "MarkupParserCommon.scala"
  Scala: length = 0x
   
  InnerClass: 
   public final $anonfun$xProcInstr$1=class scala/xml/parsing/MarkupParserCommon$$anonfun$xProcInstr$1 of class scala/xml/parsing/MarkupParserCommon
  minor version: 0
  major version: 49
  Constant pool:
Asciz	SourceFile;
Asciz	MarkupParserCommon.scala;
Asciz	<clinit>;
Asciz	()V;
Asciz	Code;
Asciz	serialVersionUID;
Asciz	J;
Asciz	scala/xml/parsing/MarkupParserCommon$$anonfun$xProcInstr$1;
class	scala/xml/parsing/MarkupParserCommon$$anonfun$xProcInstr$1
NameAndType	serialVersionUID:J
Field	scala/xml/parsing/MarkupParserCommon$$anonfun$xProcInstr$1.serialVersionUID:J
Asciz	n$1;
Asciz	Ljava/lang/String;;
Asciz	$outer;
Asciz	Lscala/xml/parsing/MarkupParserCommon;;
Asciz	<init>;
Asciz	(Lscala/xml/parsing/MarkupParserCommon;Ljava/lang/String;)V;
Asciz	LineNumberTable;
Asciz	java/lang/NullPointerException;
class	java/lang/NullPointerException
NameAndType	"<init>":()V
Method	java/lang/NullPointerException."<init>":()V
NameAndType	$outer:Lscala/xml/parsing/MarkupParserCommon;
Field	scala/xml/parsing/MarkupParserCommon$$anonfun$xProcInstr$1.$outer:Lscala/xml/parsing/MarkupParserCommon;
NameAndType	n$1:Ljava/lang/String;
Field	scala/xml/parsing/MarkupParserCommon$$anonfun$xProcInstr$1.n$1:Ljava/lang/String;
Asciz	scala/runtime/AbstractFunction2;
class	scala/runtime/AbstractFunction2
Method	scala/runtime/AbstractFunction2."<init>":()V
Asciz	this;
Asciz	Lscala/xml/parsing/MarkupParserCommon$$anonfun$xProcInstr$1;;
Asciz	LocalVariableTable;
Asciz	apply;
Asciz	(Ljava/lang/Object;Ljava/lang/Object;)Ljava/lang/Object;;
Asciz	java/lang/String;
class	java/lang/String
Asciz	(Ljava/lang/Object;Ljava/lang/String;)Ljava/lang/Object;;
NameAndType	apply:(Ljava/lang/Object;Ljava/lang/String;)Ljava/lang/Object;
Method	scala/xml/parsing/MarkupParserCommon$$anonfun$xProcInstr$1.apply:(Ljava/lang/Object;Ljava/lang/String;)Ljava/lang/Object;
Asciz	v1;
Asciz	Ljava/lang/Object;;
Asciz	v2;
Asciz	scala/xml/parsing/MarkupParserCommon;
class	scala/xml/parsing/MarkupParserCommon
Asciz	mkProcInstr;
Asciz	(Ljava/lang/Object;Ljava/lang/String;Ljava/lang/String;)Ljava/lang/Object;;
NameAndType	mkProcInstr:(Ljava/lang/Object;Ljava/lang/String;Ljava/lang/String;)Ljava/lang/Object;
InterfaceMethod	scala/xml/parsing/MarkupParserCommon.mkProcInstr:(Ljava/lang/Object;Ljava/lang/String;Ljava/lang/String;)Ljava/lang/Object;
Asciz	Scala;
Asciz	InnerClasses;
Asciz	$anonfun$xProcInstr$1;
Asciz	java/io/Serializable;
class	java/io/Serializable

{
public static final long serialVersionUID;
  Signature: J

public final java.lang.String n$1;
  Signature: Ljava/lang/String;

public final scala.xml.parsing.MarkupParserCommon $outer;
  Signature: Lscala/xml/parsing/MarkupParserCommon;

public static {};
  Signature: ()V
  Code:
   Stack=2, Locals=0, Args_size=0
	lconst_0
	putstatic	Field serialVersionUID:J
	return
  Labels:

public scala.xml.parsing.MarkupParserCommon$$anonfun$xProcInstr$1(scala.xml.parsing.MarkupParserCommon, java.lang.String);
  Signature: (Lscala/xml/parsing/MarkupParserCommon;Ljava/lang/String;)V
  Code:
   Stack=2, Locals=3, Args_size=3
	aload_1
	ifnonnull	l1 // aload_0
	new	class java/lang/NullPointerException
	dup
	invokespecial	Method java/lang/NullPointerException."<init>":()V
	athrow
l1	aload_0
	aload_1
	putfield	Field $outer:Lscala/xml/parsing/MarkupParserCommon;
	aload_0
	aload_2
	putfield	Field n$1:Ljava/lang/String;
	aload_0
	invokespecial	Method scala/runtime/AbstractFunction2."<init>":()V
	return
  Labels:
   	l1 = 12 // aload_0
  LocalVariableTable: 
   Start  Length  Slot  Name   Signature
   0      27      0    this       Lscala/xml/parsing/MarkupParserCommon$$anonfun$xProcInstr$1;
   0      27      1    $outer       Lscala/xml/parsing/MarkupParserCommon;


public final java.lang.Object apply(java.lang.Object, java.lang.Object);
  Signature: (Ljava/lang/Object;Ljava/lang/Object;)Ljava/lang/Object;
  Code:
   Stack=3, Locals=3, Args_size=3
	aload_0
	aload_1
	aload_2
	checkcast	class java/lang/String
	invokevirtual	Method apply:(Ljava/lang/Object;Ljava/lang/String;)Ljava/lang/Object;
	areturn
  Labels:
  LocalVariableTable: 
   Start  Length  Slot  Name   Signature
   0      10      0    this       Lscala/xml/parsing/MarkupParserCommon$$anonfun$xProcInstr$1;
   0      10      1    v1       Ljava/lang/Object;
   0      10      2    v2       Ljava/lang/Object;


public final java.lang.Object apply(java.lang.Object, java.lang.String);
  Signature: (Ljava/lang/Object;Ljava/lang/String;)Ljava/lang/Object;
  Code:
   Stack=4, Locals=3, Args_size=3
	aload_0
	getfield	Field $outer:Lscala/xml/parsing/MarkupParserCommon;
	aload_1
	aload_0
	getfield	Field n$1:Ljava/lang/String;
	aload_2
	invokeinterface	InterfaceMethod scala/xml/parsing/MarkupParserCommon.mkProcInstr:(Ljava/lang/Object;Ljava/lang/String;Ljava/lang/String;)Ljava/lang/Object;
	areturn
  Labels:

}

