Compiled from "MarkupParser.scala"
public final class scala.xml.parsing.MarkupParser$$anonfun$4 extends java.lang.Object implements scala.Function0,scala.ScalaObject,java.io.Serializable
  SourceFile: "MarkupParser.scala"
  Scala: length = 0x
   
  InnerClass: 
   public final $anonfun$4=class scala/xml/parsing/MarkupParser$$anonfun$4 of class scala/xml/parsing/MarkupParser
  minor version: 0
  major version: 49
  Constant pool:
Asciz	SourceFile;
Asciz	MarkupParser.scala;
Asciz	<clinit>;
Asciz	()V;
Asciz	Code;
Asciz	serialVersionUID;
Asciz	J;
Asciz	scala/xml/parsing/MarkupParser$$anonfun$4;
class	scala/xml/parsing/MarkupParser$$anonfun$4
NameAndType	serialVersionUID:J
Field	scala/xml/parsing/MarkupParser$$anonfun$4.serialVersionUID:J
Asciz	c$1;
Asciz	Lscala/runtime/CharRef;;
Asciz	it$1;
Asciz	Lscala/collection/Iterator;;
Asciz	<init>;
Asciz	(Lscala/xml/parsing/MarkupParser;Lscala/collection/Iterator;Lscala/runtime/CharRef;)V;
Asciz	LineNumberTable;
NameAndType	it$1:Lscala/collection/Iterator;
Field	scala/xml/parsing/MarkupParser$$anonfun$4.it$1:Lscala/collection/Iterator;
NameAndType	c$1:Lscala/runtime/CharRef;
Field	scala/xml/parsing/MarkupParser$$anonfun$4.c$1:Lscala/runtime/CharRef;
Asciz	java/lang/Object;
class	java/lang/Object
NameAndType	"<init>":()V
Method	java/lang/Object."<init>":()V
Asciz	scala/Function0$class;
class	scala/Function0$class
Asciz	$init$;
Asciz	(Lscala/Function0;)V;
NameAndType	$init$:(Lscala/Function0;)V
Method	scala/Function0$class.$init$:(Lscala/Function0;)V
Asciz	this;
Asciz	Lscala/xml/parsing/MarkupParser$$anonfun$4;;
Asciz	$outer;
Asciz	Lscala/xml/parsing/MarkupParser;;
Asciz	LocalVariableTable;
Asciz	apply;
Asciz	()Ljava/lang/Object;;
NameAndType	apply:()V
Method	scala/xml/parsing/MarkupParser$$anonfun$4.apply:()V
Asciz	scala/runtime/BoxedUnit;
class	scala/runtime/BoxedUnit
Asciz	UNIT;
Asciz	Lscala/runtime/BoxedUnit;;
NameAndType	UNIT:Lscala/runtime/BoxedUnit;
Field	scala/runtime/BoxedUnit.UNIT:Lscala/runtime/BoxedUnit;
Asciz	scala/collection/Iterator;
class	scala/collection/Iterator
Asciz	next;
NameAndType	next:()Ljava/lang/Object;
InterfaceMethod	scala/collection/Iterator.next:()Ljava/lang/Object;
Asciz	scala/runtime/BoxesRunTime;
class	scala/runtime/BoxesRunTime
Asciz	unboxToChar;
Asciz	(Ljava/lang/Object;)C;
NameAndType	unboxToChar:(Ljava/lang/Object;)C
Method	scala/runtime/BoxesRunTime.unboxToChar:(Ljava/lang/Object;)C
Asciz	scala/runtime/CharRef;
class	scala/runtime/CharRef
Asciz	elem;
Asciz	C;
NameAndType	elem:C
Field	scala/runtime/CharRef.elem:C
Asciz	toString;
Asciz	()Ljava/lang/String;;
Asciz	(Lscala/Function0;)Ljava/lang/String;;
NameAndType	toString:(Lscala/Function0;)Ljava/lang/String;
Method	scala/Function0$class.toString:(Lscala/Function0;)Ljava/lang/String;
Asciz	Scala;
Asciz	InnerClasses;
Asciz	scala/xml/parsing/MarkupParser;
class	scala/xml/parsing/MarkupParser
Asciz	$anonfun$4;
Asciz	scala/Function0;
class	scala/Function0
Asciz	scala/ScalaObject;
class	scala/ScalaObject
Asciz	java/io/Serializable;
class	java/io/Serializable

{
public static final long serialVersionUID;
  Signature: J

private final scala.runtime.CharRef c$1;
  Signature: Lscala/runtime/CharRef;

private final scala.collection.Iterator it$1;
  Signature: Lscala/collection/Iterator;

public static {};
  Signature: ()V
  Code:
   Stack=2, Locals=0, Args_size=0
	lconst_0
	putstatic	Field serialVersionUID:J
	return
  Labels:

public scala.xml.parsing.MarkupParser$$anonfun$4(scala.xml.parsing.MarkupParser, scala.collection.Iterator, scala.runtime.CharRef);
  Signature: (Lscala/xml/parsing/MarkupParser;Lscala/collection/Iterator;Lscala/runtime/CharRef;)V
  Code:
   Stack=2, Locals=4, Args_size=4
	aload_0
	aload_2
	putfield	Field it$1:Lscala/collection/Iterator;
	aload_0
	aload_3
	putfield	Field c$1:Lscala/runtime/CharRef;
	aload_0
	invokespecial	Method java/lang/Object."<init>":()V
	aload_0
	invokestatic	Method scala/Function0$class.$init$:(Lscala/Function0;)V
	return
  Labels:
  LocalVariableTable: 
   Start  Length  Slot  Name   Signature
   0      19      0    this       Lscala/xml/parsing/MarkupParser$$anonfun$4;
   0      19      1    $outer       Lscala/xml/parsing/MarkupParser;


public final java.lang.Object apply();
  Signature: ()Ljava/lang/Object;
  Code:
   Stack=1, Locals=1, Args_size=1
	aload_0
	invokevirtual	Method apply:()V
	getstatic	Field scala/runtime/BoxedUnit.UNIT:Lscala/runtime/BoxedUnit;
	areturn
  Labels:

public final void apply();
  Signature: ()V
  Code:
   Stack=2, Locals=1, Args_size=1
	aload_0
	getfield	Field c$1:Lscala/runtime/CharRef;
	aload_0
	getfield	Field it$1:Lscala/collection/Iterator;
	invokeinterface	InterfaceMethod scala/collection/Iterator.next:()Ljava/lang/Object;
	invokestatic	Method scala/runtime/BoxesRunTime.unboxToChar:(Ljava/lang/Object;)C
	putfield	Field scala/runtime/CharRef.elem:C
	return
  Labels:

public java.lang.String toString();
  Signature: ()Ljava/lang/String;
  Code:
   Stack=1, Locals=1, Args_size=1
	aload_0
	invokestatic	Method scala/Function0$class.toString:(Lscala/Function0;)Ljava/lang/String;
	areturn
  Labels:

}

