Compiled from "MarkupParser.scala"
public final class scala.xml.parsing.MarkupParser$$anonfun$xCharData$1 extends scala.runtime.AbstractFunction2 implements java.io.Serializable
  SourceFile: "MarkupParser.scala"
  Scala: length = 0x
   
  InnerClass: 
   public final $anonfun$xCharData$1=class scala/xml/parsing/MarkupParser$$anonfun$xCharData$1 of class scala/xml/parsing/MarkupParser
  minor version: 0
  major version: 49
  Constant pool:
Asciz	SourceFile;
Asciz	MarkupParser.scala;
Asciz	<clinit>;
Asciz	()V;
Asciz	Code;
Asciz	serialVersionUID;
Asciz	J;
Asciz	scala/xml/parsing/MarkupParser$$anonfun$xCharData$1;
class	scala/xml/parsing/MarkupParser$$anonfun$xCharData$1
NameAndType	serialVersionUID:J
Field	scala/xml/parsing/MarkupParser$$anonfun$xCharData$1.serialVersionUID:J
Asciz	$outer;
Asciz	Lscala/xml/parsing/MarkupHandler;;
Asciz	apply;
Asciz	(ILjava/lang/String;)Lscala/xml/NodeSeq;;
Asciz	LineNumberTable;
NameAndType	$outer:Lscala/xml/parsing/MarkupHandler;
Field	scala/xml/parsing/MarkupParser$$anonfun$xCharData$1.$outer:Lscala/xml/parsing/MarkupHandler;
Asciz	scala/xml/parsing/MarkupParser$class;
class	scala/xml/parsing/MarkupParser$class
Asciz	mkResult$1;
Asciz	(Lscala/xml/parsing/MarkupHandler;ILjava/lang/String;)Lscala/xml/NodeSeq;;
NameAndType	mkResult$1:(Lscala/xml/parsing/MarkupHandler;ILjava/lang/String;)Lscala/xml/NodeSeq;
Method	scala/xml/parsing/MarkupParser$class.mkResult$1:(Lscala/xml/parsing/MarkupHandler;ILjava/lang/String;)Lscala/xml/NodeSeq;
Asciz	(Ljava/lang/Object;Ljava/lang/Object;)Ljava/lang/Object;;
Asciz	scala/runtime/BoxesRunTime;
class	scala/runtime/BoxesRunTime
Asciz	unboxToInt;
Asciz	(Ljava/lang/Object;)I;
NameAndType	unboxToInt:(Ljava/lang/Object;)I
Method	scala/runtime/BoxesRunTime.unboxToInt:(Ljava/lang/Object;)I
Asciz	java/lang/String;
class	java/lang/String
NameAndType	apply:(ILjava/lang/String;)Lscala/xml/NodeSeq;
Method	scala/xml/parsing/MarkupParser$$anonfun$xCharData$1.apply:(ILjava/lang/String;)Lscala/xml/NodeSeq;
Asciz	this;
Asciz	Lscala/xml/parsing/MarkupParser$$anonfun$xCharData$1;;
Asciz	v1;
Asciz	Ljava/lang/Object;;
Asciz	v2;
Asciz	LocalVariableTable;
Asciz	<init>;
Asciz	(Lscala/xml/parsing/MarkupHandler;)V;
Asciz	java/lang/NullPointerException;
class	java/lang/NullPointerException
NameAndType	"<init>":()V
Method	java/lang/NullPointerException."<init>":()V
Asciz	scala/runtime/AbstractFunction2;
class	scala/runtime/AbstractFunction2
Method	scala/runtime/AbstractFunction2."<init>":()V
Asciz	Scala;
Asciz	InnerClasses;
Asciz	scala/xml/parsing/MarkupParser;
class	scala/xml/parsing/MarkupParser
Asciz	$anonfun$xCharData$1;
Asciz	java/io/Serializable;
class	java/io/Serializable

{
public static final long serialVersionUID;
  Signature: J

public final scala.xml.parsing.MarkupHandler $outer;
  Signature: Lscala/xml/parsing/MarkupHandler;

public static {};
  Signature: ()V
  Code:
   Stack=2, Locals=0, Args_size=0
	lconst_0
	putstatic	Field serialVersionUID:J
	return
  Labels:

public final scala.xml.NodeSeq apply(int, java.lang.String);
  Signature: (ILjava/lang/String;)Lscala/xml/NodeSeq;
  Code:
   Stack=3, Locals=3, Args_size=3
	aload_0
	getfield	Field $outer:Lscala/xml/parsing/MarkupHandler;
	iload_1
	aload_2
	invokestatic	Method scala/xml/parsing/MarkupParser$class.mkResult$1:(Lscala/xml/parsing/MarkupHandler;ILjava/lang/String;)Lscala/xml/NodeSeq;
	areturn
  Labels:

public final java.lang.Object apply(java.lang.Object, java.lang.Object);
  Signature: (Ljava/lang/Object;Ljava/lang/Object;)Ljava/lang/Object;
  Code:
   Stack=3, Locals=3, Args_size=3
	aload_0
	aload_1
	invokestatic	Method scala/runtime/BoxesRunTime.unboxToInt:(Ljava/lang/Object;)I
	aload_2
	checkcast	class java/lang/String
	invokevirtual	Method apply:(ILjava/lang/String;)Lscala/xml/NodeSeq;
	areturn
  Labels:
  LocalVariableTable: 
   Start  Length  Slot  Name   Signature
   0      13      0    this       Lscala/xml/parsing/MarkupParser$$anonfun$xCharData$1;
   0      13      1    v1       Ljava/lang/Object;
   0      13      2    v2       Ljava/lang/Object;


public scala.xml.parsing.MarkupParser$$anonfun$xCharData$1(scala.xml.parsing.MarkupHandler);
  Signature: (Lscala/xml/parsing/MarkupHandler;)V
  Code:
   Stack=2, Locals=2, Args_size=2
	aload_1
	ifnonnull	l1 // aload_0
	new	class java/lang/NullPointerException
	dup
	invokespecial	Method java/lang/NullPointerException."<init>":()V
	athrow
l1	aload_0
	aload_1
	putfield	Field $outer:Lscala/xml/parsing/MarkupHandler;
	aload_0
	invokespecial	Method scala/runtime/AbstractFunction2."<init>":()V
	return
  Labels:
   	l1 = 12 // aload_0
  LocalVariableTable: 
   Start  Length  Slot  Name   Signature
   0      22      0    this       Lscala/xml/parsing/MarkupParser$$anonfun$xCharData$1;
   0      22      1    $outer       Lscala/xml/parsing/MarkupHandler;


}

