Compiled from "MarkupParser.scala"
public final class scala.xml.parsing.MarkupParser$$anonfun$document$1 extends java.lang.Object implements scala.Function1,scala.ScalaObject,java.io.Serializable
  SourceFile: "MarkupParser.scala"
  Scala: length = 0x
   
  InnerClass: 
   public final $anonfun$document$1=class scala/xml/parsing/MarkupParser$$anonfun$document$1 of class scala/xml/parsing/MarkupParser
  minor version: 0
  major version: 49
  Constant pool:
Asciz	SourceFile;
Asciz	MarkupParser.scala;
Asciz	<clinit>;
Asciz	()V;
Asciz	Code;
Asciz	serialVersionUID;
Asciz	J;
Asciz	scala/xml/parsing/MarkupParser$$anonfun$document$1;
class	scala/xml/parsing/MarkupParser$$anonfun$document$1
NameAndType	serialVersionUID:J
Field	scala/xml/parsing/MarkupParser$$anonfun$document$1.serialVersionUID:J
Asciz	theNode$1;
Asciz	Lscala/runtime/ObjectRef;;
Asciz	elemCount$1;
Asciz	Lscala/runtime/IntRef;;
Asciz	$outer;
Asciz	Lscala/xml/parsing/MarkupParser;;
Asciz	<init>;
Asciz	(Lscala/xml/parsing/MarkupParser;Lscala/runtime/IntRef;Lscala/runtime/ObjectRef;)V;
Asciz	LineNumberTable;
Asciz	java/lang/NullPointerException;
class	java/lang/NullPointerException
NameAndType	"<init>":()V
Method	java/lang/NullPointerException."<init>":()V
NameAndType	$outer:Lscala/xml/parsing/MarkupParser;
Field	scala/xml/parsing/MarkupParser$$anonfun$document$1.$outer:Lscala/xml/parsing/MarkupParser;
NameAndType	elemCount$1:Lscala/runtime/IntRef;
Field	scala/xml/parsing/MarkupParser$$anonfun$document$1.elemCount$1:Lscala/runtime/IntRef;
NameAndType	theNode$1:Lscala/runtime/ObjectRef;
Field	scala/xml/parsing/MarkupParser$$anonfun$document$1.theNode$1:Lscala/runtime/ObjectRef;
Asciz	java/lang/Object;
class	java/lang/Object
Method	java/lang/Object."<init>":()V
Asciz	scala/Function1$class;
class	scala/Function1$class
Asciz	$init$;
Asciz	(Lscala/Function1;)V;
NameAndType	$init$:(Lscala/Function1;)V
Method	scala/Function1$class.$init$:(Lscala/Function1;)V
Asciz	this;
Asciz	Lscala/xml/parsing/MarkupParser$$anonfun$document$1;;
Asciz	LocalVariableTable;
Asciz	apply;
Asciz	(Ljava/lang/Object;)Ljava/lang/Object;;
Asciz	scala/xml/Node;
class	scala/xml/Node
Asciz	(Lscala/xml/Node;)V;
NameAndType	apply:(Lscala/xml/Node;)V
Method	scala/xml/parsing/MarkupParser$$anonfun$document$1.apply:(Lscala/xml/Node;)V
Asciz	scala/runtime/BoxedUnit;
class	scala/runtime/BoxedUnit
Asciz	UNIT;
Asciz	Lscala/runtime/BoxedUnit;;
NameAndType	UNIT:Lscala/runtime/BoxedUnit;
Field	scala/runtime/BoxedUnit.UNIT:Lscala/runtime/BoxedUnit;
Asciz	v1;
Asciz	Ljava/lang/Object;;
Asciz	scala/xml/ProcInstr;
class	scala/xml/ProcInstr
Asciz	scala/MatchError;
class	scala/MatchError
Asciz	toString;
Asciz	()Ljava/lang/String;;
NameAndType	toString:()Ljava/lang/String;
Method	scala/xml/Node.toString:()Ljava/lang/String;
Asciz	(Ljava/lang/String;)V;
NameAndType	"<init>":(Ljava/lang/String;)V
Method	scala/MatchError."<init>":(Ljava/lang/String;)V
Asciz	scala/xml/Comment;
class	scala/xml/Comment
Asciz	scala/xml/EntityRef;
class	scala/xml/EntityRef
Asciz	no entity references alllowed here;
String	no entity references alllowed here
Asciz	scala/xml/parsing/MarkupParser;
class	scala/xml/parsing/MarkupParser
Asciz	reportSyntaxError;
NameAndType	reportSyntaxError:(Ljava/lang/String;)V
InterfaceMethod	scala/xml/parsing/MarkupParser.reportSyntaxError:(Ljava/lang/String;)V
Asciz	scala/xml/SpecialNode;
class	scala/xml/SpecialNode
Method	scala/xml/SpecialNode.toString:()Ljava/lang/String;
Asciz	java/lang/String;
class	java/lang/String
Asciz	trim;
NameAndType	trim:()Ljava/lang/String;
Method	java/lang/String.trim:()Ljava/lang/String;
Asciz	length;
Asciz	()I;
NameAndType	length:()I
Method	java/lang/String.length:()I
Asciz	scala/runtime/IntRef;
class	scala/runtime/IntRef
Asciz	elem;
Asciz	I;
NameAndType	elem:I
Field	scala/runtime/IntRef.elem:I
Asciz	scala/runtime/ObjectRef;
class	scala/runtime/ObjectRef
NameAndType	elem:Ljava/lang/Object;
Field	scala/runtime/ObjectRef.elem:Ljava/lang/Object;
Asciz	c;
Asciz	Lscala/xml/Node;;
Asciz	temp36;
Asciz	Lscala/xml/SpecialNode;;
Asciz	andThen;
Asciz	(Lscala/Function1;)Lscala/Function1;;
Asciz	(Lscala/Function1;Lscala/Function1;)Lscala/Function1;;
NameAndType	andThen:(Lscala/Function1;Lscala/Function1;)Lscala/Function1;
Method	scala/Function1$class.andThen:(Lscala/Function1;Lscala/Function1;)Lscala/Function1;
Asciz	g;
Asciz	Lscala/Function1;;
Asciz	compose;
NameAndType	compose:(Lscala/Function1;Lscala/Function1;)Lscala/Function1;
Method	scala/Function1$class.compose:(Lscala/Function1;Lscala/Function1;)Lscala/Function1;
Asciz	(Lscala/Function1;)Ljava/lang/String;;
NameAndType	toString:(Lscala/Function1;)Ljava/lang/String;
Method	scala/Function1$class.toString:(Lscala/Function1;)Ljava/lang/String;
Asciz	Scala;
Asciz	InnerClasses;
Asciz	$anonfun$document$1;
Asciz	scala/Function1;
class	scala/Function1
Asciz	scala/ScalaObject;
class	scala/ScalaObject
Asciz	java/io/Serializable;
class	java/io/Serializable

{
public static final long serialVersionUID;
  Signature: J

private final scala.runtime.ObjectRef theNode$1;
  Signature: Lscala/runtime/ObjectRef;

private final scala.runtime.IntRef elemCount$1;
  Signature: Lscala/runtime/IntRef;

private final scala.xml.parsing.MarkupParser $outer;
  Signature: Lscala/xml/parsing/MarkupParser;

public static {};
  Signature: ()V
  Code:
   Stack=2, Locals=0, Args_size=0
	lconst_0
	putstatic	Field serialVersionUID:J
	return
  Labels:

public scala.xml.parsing.MarkupParser$$anonfun$document$1(scala.xml.parsing.MarkupParser, scala.runtime.IntRef, scala.runtime.ObjectRef);
  Signature: (Lscala/xml/parsing/MarkupParser;Lscala/runtime/IntRef;Lscala/runtime/ObjectRef;)V
  Code:
   Stack=2, Locals=4, Args_size=4
	aload_1
	ifnonnull	l1 // aload_0
	new	class java/lang/NullPointerException
	dup
	invokespecial	Method java/lang/NullPointerException."<init>":()V
	athrow
l1	aload_0
	aload_1
	putfield	Field $outer:Lscala/xml/parsing/MarkupParser;
	aload_0
	aload_2
	putfield	Field elemCount$1:Lscala/runtime/IntRef;
	aload_0
	aload_3
	putfield	Field theNode$1:Lscala/runtime/ObjectRef;
	aload_0
	invokespecial	Method java/lang/Object."<init>":()V
	aload_0
	invokestatic	Method scala/Function1$class.$init$:(Lscala/Function1;)V
	return
  Labels:
   	l1 = 12 // aload_0
  LocalVariableTable: 
   Start  Length  Slot  Name   Signature
   0      36      0    this       Lscala/xml/parsing/MarkupParser$$anonfun$document$1;
   0      36      1    $outer       Lscala/xml/parsing/MarkupParser;


public final java.lang.Object apply(java.lang.Object);
  Signature: (Ljava/lang/Object;)Ljava/lang/Object;
  Code:
   Stack=2, Locals=3, Args_size=2
	aload_0
	getfield	Field $outer:Lscala/xml/parsing/MarkupParser;
	astore_2
	aload_0
	aload_1
	checkcast	class scala/xml/Node
	invokevirtual	Method apply:(Lscala/xml/Node;)V
	getstatic	Field scala/runtime/BoxedUnit.UNIT:Lscala/runtime/BoxedUnit;
	areturn
  Labels:
  LocalVariableTable: 
   Start  Length  Slot  Name   Signature
   0      17      0    this       Lscala/xml/parsing/MarkupParser$$anonfun$document$1;
   5      12      1    v1       Ljava/lang/Object;


public final void apply(scala.xml.Node);
  Signature: (Lscala/xml/Node;)V
  Code:
   Stack=3, Locals=4, Args_size=2
	aload_0
	getfield	Field $outer:Lscala/xml/parsing/MarkupParser;
	astore_3
	aload_1
	instanceof	class scala/xml/ProcInstr
	ifeq	l1 // aload_1
	iconst_1
	ifne	l2 // return
	new	class scala/MatchError
	dup
	aload_1
	invokevirtual	Method scala/xml/Node.toString:()Ljava/lang/String;
	invokespecial	Method scala/MatchError."<init>":(Ljava/lang/String;)V
	athrow
l1	aload_1
	instanceof	class scala/xml/Comment
	ifeq	l3 // aload_1
	iconst_1
	ifne	l2 // return
	new	class scala/MatchError
	dup
	aload_1
	invokevirtual	Method scala/xml/Node.toString:()Ljava/lang/String;
	invokespecial	Method scala/MatchError."<init>":(Ljava/lang/String;)V
	athrow
l3	aload_1
	instanceof	class scala/xml/EntityRef
	ifeq	l4 // aload_1
	iconst_1
	ifeq	l5 // new
	aload_0
	getfield	Field $outer:Lscala/xml/parsing/MarkupParser;
	ldc	String no entity references alllowed here
	invokeinterface	InterfaceMethod scala/xml/parsing/MarkupParser.reportSyntaxError:(Ljava/lang/String;)V
	goto	l2 // return
l5	new	class scala/MatchError
	dup
	aload_1
	invokevirtual	Method scala/xml/Node.toString:()Ljava/lang/String;
	invokespecial	Method scala/MatchError."<init>":(Ljava/lang/String;)V
	athrow
l4	aload_1
	instanceof	class scala/xml/SpecialNode
	ifeq	l6 // aload_1
	aload_1
	checkcast	class scala/xml/SpecialNode
	astore_2
	iconst_1
	ifeq	l7 // new
	aload_2
	invokevirtual	Method scala/xml/SpecialNode.toString:()Ljava/lang/String;
	invokevirtual	Method java/lang/String.trim:()Ljava/lang/String;
	invokevirtual	Method java/lang/String.length:()I
	iconst_0
	if_icmple	l2 // return
	aload_0
	getfield	Field elemCount$1:Lscala/runtime/IntRef;
	aload_0
	getfield	Field elemCount$1:Lscala/runtime/IntRef;
	getfield	Field scala/runtime/IntRef.elem:I
	iconst_2
	iadd
	putfield	Field scala/runtime/IntRef.elem:I
	goto	l2 // return
l7	new	class scala/MatchError
	dup
	aload_1
	invokevirtual	Method scala/xml/Node.toString:()Ljava/lang/String;
	invokespecial	Method scala/MatchError."<init>":(Ljava/lang/String;)V
	athrow
l6	aload_1
	ifnull	l8 // new
	iconst_1
	ifeq	l9 // new
	aload_0
	getfield	Field elemCount$1:Lscala/runtime/IntRef;
	aload_0
	getfield	Field elemCount$1:Lscala/runtime/IntRef;
	getfield	Field scala/runtime/IntRef.elem:I
	iconst_1
	iadd
	putfield	Field scala/runtime/IntRef.elem:I
	aload_0
	getfield	Field theNode$1:Lscala/runtime/ObjectRef;
	aload_1
	putfield	Field scala/runtime/ObjectRef.elem:Ljava/lang/Object;
l2	return
l9	new	class scala/MatchError
	dup
	aload_1
	invokevirtual	Method scala/xml/Node.toString:()Ljava/lang/String;
	invokespecial	Method scala/MatchError."<init>":(Ljava/lang/String;)V
	athrow
l8	new	class scala/MatchError
	dup
	aload_1
	invokevirtual	Method scala/xml/Node.toString:()Ljava/lang/String;
	invokespecial	Method scala/MatchError."<init>":(Ljava/lang/String;)V
	athrow
  Labels:
   	l1 = 28 // aload_1
   	l3 = 51 // aload_1
   	l5 = 76 // new
   	l4 = 88 // aload_1
   	l7 = 137 // new
   	l6 = 149 // aload_1
   	l2 = 181 // return
   	l9 = 182 // new
   	l8 = 194 // new
  LocalVariableTable: 
   Start  Length  Slot  Name   Signature
   0      206      0    this       Lscala/xml/parsing/MarkupParser$$anonfun$document$1;
   5      201      1    c       Lscala/xml/Node;
   100      49      2    temp36       Lscala/xml/SpecialNode;


public scala.Function1 andThen(scala.Function1);
  Signature: (Lscala/Function1;)Lscala/Function1;
  Code:
   Stack=2, Locals=2, Args_size=2
	aload_0
	aload_1
	invokestatic	Method scala/Function1$class.andThen:(Lscala/Function1;Lscala/Function1;)Lscala/Function1;
	areturn
  Labels:
  LocalVariableTable: 
   Start  Length  Slot  Name   Signature
   0      6      0    this       Lscala/xml/parsing/MarkupParser$$anonfun$document$1;
   0      6      1    g       Lscala/Function1;


public scala.Function1 compose(scala.Function1);
  Signature: (Lscala/Function1;)Lscala/Function1;
  Code:
   Stack=2, Locals=2, Args_size=2
	aload_0
	aload_1
	invokestatic	Method scala/Function1$class.compose:(Lscala/Function1;Lscala/Function1;)Lscala/Function1;
	areturn
  Labels:
  LocalVariableTable: 
   Start  Length  Slot  Name   Signature
   0      6      0    this       Lscala/xml/parsing/MarkupParser$$anonfun$document$1;
   0      6      1    g       Lscala/Function1;


public java.lang.String toString();
  Signature: ()Ljava/lang/String;
  Code:
   Stack=1, Locals=1, Args_size=1
	aload_0
	invokestatic	Method scala/Function1$class.toString:(Lscala/Function1;)Ljava/lang/String;
	areturn
  Labels:

}

