Compiled from "MarkupParser.scala"
public final class scala.xml.parsing.MarkupParser$$anon$1 extends scala.xml.NodeSeq
  SourceFile: "MarkupParser.scala"
  Scala: length = 0x
   
  InnerClass: 
   public final #34= #17 of #33; //$anon$1=class scala/xml/parsing/MarkupParser$$anon$1 of class scala/xml/parsing/MarkupParser
  minor version: 0
  major version: 49
  Constant pool:
const #1 = Asciz	SourceFile;
const #2 = Asciz	MarkupParser.scala;
const #3 = Asciz	theSeq;
const #4 = Asciz	Lscala/collection/immutable/List;;
const #5 = Asciz	Lscala/collection/immutable/List<Lscala/xml/Node;>;;
const #6 = Asciz	Signature;
const #7 = Asciz	<init>;
const #8 = Asciz	(Lscala/xml/parsing/MarkupParser;Lscala/collection/immutable/List;)V;
const #9 = Asciz	Code;
const #10 = Asciz	LineNumberTable;
const #11 = Asciz	scala/xml/NodeSeq;
const #12 = class	#11;	//  scala/xml/NodeSeq
const #13 = Asciz	()V;
const #14 = NameAndType	#7:#13;//  "<init>":()V
const #15 = Method	#12.#14;	//  scala/xml/NodeSeq."<init>":()V
const #16 = Asciz	scala/xml/parsing/MarkupParser$$anon$1;
const #17 = class	#16;	//  scala/xml/parsing/MarkupParser$$anon$1
const #18 = NameAndType	#3:#4;//  theSeq:Lscala/collection/immutable/List;
const #19 = Field	#17.#18;	//  scala/xml/parsing/MarkupParser$$anon$1.theSeq:Lscala/collection/immutable/List;
const #20 = Asciz	this;
const #21 = Asciz	Lscala/xml/parsing/MarkupParser$$anon$1;;
const #22 = Asciz	$outer;
const #23 = Asciz	Lscala/xml/parsing/MarkupParser;;
const #24 = Asciz	LocalVariableTable;
const #25 = Asciz	()Lscala/collection/Seq;;
const #26 = Asciz	()Lscala/collection/immutable/List;;
const #27 = NameAndType	#3:#26;//  theSeq:()Lscala/collection/immutable/List;
const #28 = Method	#17.#27;	//  scala/xml/parsing/MarkupParser$$anon$1.theSeq:()Lscala/collection/immutable/List;
const #29 = Asciz	()Lscala/collection/immutable/List<Lscala/xml/Node;>;;
const #30 = Asciz	Scala;
const #31 = Asciz	InnerClasses;
const #32 = Asciz	scala/xml/parsing/MarkupParser;
const #33 = class	#32;	//  scala/xml/parsing/MarkupParser
const #34 = Asciz	$anon$1;

{
public scala.xml.parsing.MarkupParser$$anon$1(scala.xml.parsing.MarkupParser, scala.collection.immutable.List);
  Code:
   Stack=2, Locals=3, Args_size=3
   0:	aload_0
   1:	invokespecial	#15; //Method scala/xml/NodeSeq."<init>":()V
   4:	aload_0
   5:	aload_2
   6:	putfield	#19; //Field theSeq:Lscala/collection/immutable/List;
   9:	return
  LineNumberTable: 
   line 523: 0
   line 524: 4

  LocalVariableTable: 
   Start  Length  Slot  Name   Signature
   0      10      0    this       Lscala/xml/parsing/MarkupParser$$anon$1;
   0      10      1    $outer       Lscala/xml/parsing/MarkupParser;


public scala.collection.Seq theSeq();
  Code:
   Stack=1, Locals=1, Args_size=1
   0:	aload_0
   1:	invokevirtual	#28; //Method theSeq:()Lscala/collection/immutable/List;
   4:	areturn
  LineNumberTable: 
   line 523: 0


public scala.collection.immutable.List theSeq();
  Code:
   Stack=1, Locals=1, Args_size=1
   0:	aload_0
   1:	getfield	#19; //Field theSeq:Lscala/collection/immutable/List;
   4:	areturn
  LineNumberTable: 
   line 524: 0

  Signature: length = 0x2
   00 1D 

}

