Compiled from "MarkupParser.scala"
public abstract class scala.xml.parsing.MarkupParser$class extends java.lang.Object
  SourceFile: "MarkupParser.scala"
  Scala: length = 0x
   
  InnerClass: 
   public final $anon$1=class scala/xml/NodeSeq$$anon$1 of class scala/xml/NodeSeq
   public final $anon$2=class scala/xml/parsing/MarkupParser$$anon$2 of class scala/xml/parsing/MarkupParser
   public final $anon$1=class scala/xml/parsing/MarkupParser$$anon$1 of class scala/xml/parsing/MarkupParser
   public final $anonfun$2=class scala/xml/parsing/MarkupParser$$anonfun$2 of class scala/xml/parsing/MarkupParser
   public final $anonfun$1=class scala/xml/parsing/MarkupParser$$anonfun$1 of class scala/xml/parsing/MarkupParser
   public final $anonfun$4=class scala/xml/parsing/MarkupParser$$anonfun$4 of class scala/xml/parsing/MarkupParser
   public final $anonfun$3=class scala/xml/parsing/MarkupParser$$anonfun$3 of class scala/xml/parsing/MarkupParser
   public final $anonfun$document$1=class scala/xml/parsing/MarkupParser$$anonfun$document$1 of class scala/xml/parsing/MarkupParser
   public final $anonfun$xCharRef$1=class scala/xml/parsing/MarkupParser$$anonfun$xCharRef$1 of class scala/xml/parsing/MarkupParser
   public final $anonfun$appendText$1=class scala/xml/parsing/MarkupParser$$anonfun$appendText$1 of class scala/xml/parsing/MarkupParser
  minor version: 0
  major version: 49
  Constant pool:
Asciz	SourceFile;
Asciz	MarkupParser.scala;
Asciz	$init$;
Asciz	(Lscala/xml/parsing/MarkupHandler;)V;
Asciz	Code;
Asciz	LineNumberTable;
Asciz	scala/xml/parsing/MarkupParser;
class	scala/xml/parsing/MarkupParser
Asciz	input;
Asciz	()Lscala/io/Source;;
NameAndType	input:()Lscala/io/Source;
InterfaceMethod	scala/xml/parsing/MarkupParser.input:()Lscala/io/Source;
Asciz	curInput_$eq;
Asciz	(Lscala/io/Source;)V;
NameAndType	curInput_$eq:(Lscala/io/Source;)V
InterfaceMethod	scala/xml/parsing/MarkupParser.curInput_$eq:(Lscala/io/Source;)V
Asciz	scala$xml$parsing$MarkupParser$_setter_$scala$xml$parsing$MarkupParser$$handle_$eq;
NameAndType	scala$xml$parsing$MarkupParser$_setter_$scala$xml$parsing$MarkupParser$$handle_$eq:(Lscala/xml/parsing/MarkupHandler;)V
InterfaceMethod	scala/xml/parsing/MarkupParser.scala$xml$parsing$MarkupParser$_setter_$scala$xml$parsing$MarkupParser$$handle_$eq:(Lscala/xml/parsing/MarkupHandler;)V
Asciz	scala/collection/immutable/Nil$;
class	scala/collection/immutable/Nil$
Asciz	MODULE$;
Asciz	Lscala/collection/immutable/Nil$;;
NameAndType	MODULE$:Lscala/collection/immutable/Nil$;
Field	scala/collection/immutable/Nil$.MODULE$:Lscala/collection/immutable/Nil$;
Asciz	inpStack_$eq;
Asciz	(Lscala/collection/immutable/List;)V;
NameAndType	inpStack_$eq:(Lscala/collection/immutable/List;)V
InterfaceMethod	scala/xml/parsing/MarkupParser.inpStack_$eq:(Lscala/collection/immutable/List;)V
Asciz	extIndex_$eq;
Asciz	(I)V;
NameAndType	extIndex_$eq:(I)V
InterfaceMethod	scala/xml/parsing/MarkupParser.extIndex_$eq:(I)V
Asciz	scala/collection/mutable/StringBuilder;
class	scala/collection/mutable/StringBuilder
Asciz	<init>;
Asciz	()V;
NameAndType	"<init>":()V
Method	scala/collection/mutable/StringBuilder."<init>":()V
Asciz	scala$xml$parsing$MarkupParser$_setter_$cbuf_$eq;
Asciz	(Lscala/collection/mutable/StringBuilder;)V;
NameAndType	scala$xml$parsing$MarkupParser$_setter_$cbuf_$eq:(Lscala/collection/mutable/StringBuilder;)V
InterfaceMethod	scala/xml/parsing/MarkupParser.scala$xml$parsing$MarkupParser$_setter_$cbuf_$eq:(Lscala/collection/mutable/StringBuilder;)V
Asciz	dtd_$eq;
Asciz	(Lscala/xml/dtd/DTD;)V;
NameAndType	dtd_$eq:(Lscala/xml/dtd/DTD;)V
InterfaceMethod	scala/xml/parsing/MarkupParser.dtd_$eq:(Lscala/xml/dtd/DTD;)V
Asciz	doc_$eq;
Asciz	(Lscala/xml/Document;)V;
NameAndType	doc_$eq:(Lscala/xml/Document;)V
InterfaceMethod	scala/xml/parsing/MarkupParser.doc_$eq:(Lscala/xml/Document;)V
Asciz	eof_$eq;
Asciz	(Z)V;
NameAndType	eof_$eq:(Z)V
InterfaceMethod	scala/xml/parsing/MarkupParser.eof_$eq:(Z)V
Asciz	$this;
Asciz	Lscala/xml/parsing/MarkupHandler;;
Asciz	LocalVariableTable;
Asciz	gd2$1;
Asciz	(Lscala/xml/parsing/MarkupHandler;)Z;
Asciz	scala/xml/parsing/TokenTests;
class	scala/xml/parsing/TokenTests
Asciz	ch;
Asciz	()C;
NameAndType	ch:()C
InterfaceMethod	scala/xml/parsing/MarkupParser.ch:()C
Asciz	isSpace;
Asciz	(C)Z;
NameAndType	isSpace:(C)Z
InterfaceMethod	scala/xml/parsing/TokenTests.isSpace:(C)Z
Asciz	gd1$1;
Asciz	inpStack;
Asciz	()Lscala/collection/immutable/List;;
NameAndType	inpStack:()Lscala/collection/immutable/List;
InterfaceMethod	scala/xml/parsing/MarkupParser.inpStack:()Lscala/collection/immutable/List;
Asciz	scala/collection/LinearSeqLike;
class	scala/collection/LinearSeqLike
Asciz	length;
Asciz	()I;
NameAndType	length:()I
InterfaceMethod	scala/collection/LinearSeqLike.length:()I
Asciz	extIndex;
NameAndType	extIndex:()I
InterfaceMethod	scala/xml/parsing/MarkupParser.extIndex:()I
Asciz	doIgnore$1;
Asciz	(Lscala/xml/parsing/MarkupHandler;)C;
Asciz	scala/xml/parsing/MarkupParserCommon;
class	scala/xml/parsing/MarkupParserCommon
int	91;
Asciz	xToken;
Asciz	(C)V;
NameAndType	xToken:(C)V
InterfaceMethod	scala/xml/parsing/MarkupParserCommon.xToken:(C)V
int	93;
Asciz	nextch;
NameAndType	nextch:()C
InterfaceMethod	scala/xml/parsing/MarkupParser.nextch:()C
Asciz	doInclude$1;
Asciz	markupDecl;
NameAndType	markupDecl:()V
InterfaceMethod	scala/xml/parsing/MarkupParser.markupDecl:()V
Asciz	done$1;
Asciz	(Lscala/xml/parsing/MarkupHandler;Lscala/runtime/ObjectRef;)Lscala/xml/NodeSeq;;
Asciz	scala/xml/parsing/MarkupParser$$anon$1;
class	scala/xml/parsing/MarkupParser$$anon$1
Asciz	(Lscala/xml/parsing/MarkupHandler;Lscala/runtime/ObjectRef;)V;
NameAndType	"<init>":(Lscala/xml/parsing/MarkupHandler;Lscala/runtime/ObjectRef;)V
Method	scala/xml/parsing/MarkupParser$$anon$1."<init>":(Lscala/xml/parsing/MarkupHandler;Lscala/runtime/ObjectRef;)V
Asciz	normalizeAttributeValue;
Asciz	(Lscala/xml/parsing/MarkupHandler;Ljava/lang/String;)Ljava/lang/String;;
Asciz	scala/Predef$;
class	scala/Predef$
Asciz	Lscala/Predef$;;
NameAndType	MODULE$:Lscala/Predef$;
Field	scala/Predef$.MODULE$:Lscala/Predef$;
Asciz	wrapString;
Asciz	(Ljava/lang/String;)Lscala/collection/immutable/WrappedString;;
NameAndType	wrapString:(Ljava/lang/String;)Lscala/collection/immutable/WrappedString;
Method	scala/Predef$.wrapString:(Ljava/lang/String;)Lscala/collection/immutable/WrappedString;
Asciz	scala/collection/IterableLike;
class	scala/collection/IterableLike
Asciz	iterator;
Asciz	()Lscala/collection/Iterator;;
NameAndType	iterator:()Lscala/collection/Iterator;
InterfaceMethod	scala/collection/IterableLike.iterator:()Lscala/collection/Iterator;
Asciz	scala/collection/Iterator;
class	scala/collection/Iterator
Asciz	hasNext;
Asciz	()Z;
NameAndType	hasNext:()Z
InterfaceMethod	scala/collection/Iterator.hasNext:()Z
Asciz	next;
Asciz	()Ljava/lang/Object;;
NameAndType	next:()Ljava/lang/Object;
InterfaceMethod	scala/collection/Iterator.next:()Ljava/lang/Object;
Asciz	scala/runtime/BoxesRunTime;
class	scala/runtime/BoxesRunTime
Asciz	unboxToChar;
Asciz	(Ljava/lang/Object;)C;
NameAndType	unboxToChar:(Ljava/lang/Object;)C
Method	scala/runtime/BoxesRunTime.unboxToChar:(Ljava/lang/Object;)C
Asciz	cbuf;
Asciz	()Lscala/collection/mutable/StringBuilder;;
NameAndType	cbuf:()Lscala/collection/mutable/StringBuilder;
InterfaceMethod	scala/xml/parsing/MarkupParser.cbuf:()Lscala/collection/mutable/StringBuilder;
Asciz	append;
Asciz	(C)Lscala/collection/mutable/StringBuilder;;
NameAndType	append:(C)Lscala/collection/mutable/StringBuilder;
Method	scala/collection/mutable/StringBuilder.append:(C)Lscala/collection/mutable/StringBuilder;
Asciz	scala/MatchError;
class	scala/MatchError
Asciz	boxToCharacter;
Asciz	(C)Ljava/lang/Character;;
NameAndType	boxToCharacter:(C)Ljava/lang/Character;
Method	scala/runtime/BoxesRunTime.boxToCharacter:(C)Ljava/lang/Character;
Asciz	java/lang/Object;
class	java/lang/Object
Asciz	toString;
Asciz	()Ljava/lang/String;;
NameAndType	toString:()Ljava/lang/String;
Method	java/lang/Object.toString:()Ljava/lang/String;
Asciz	(Ljava/lang/String;)V;
NameAndType	"<init>":(Ljava/lang/String;)V
Method	scala/MatchError."<init>":(Ljava/lang/String;)V
int	35;
Asciz	scala/runtime/CharRef;
class	scala/runtime/CharRef
NameAndType	"<init>":(C)V
Method	scala/runtime/CharRef."<init>":(C)V
Asciz	scala/xml/parsing/MarkupParser$$anonfun$3;
class	scala/xml/parsing/MarkupParser$$anonfun$3
Asciz	(Lscala/xml/parsing/MarkupHandler;Lscala/runtime/CharRef;)V;
NameAndType	"<init>":(Lscala/xml/parsing/MarkupHandler;Lscala/runtime/CharRef;)V
Method	scala/xml/parsing/MarkupParser$$anonfun$3."<init>":(Lscala/xml/parsing/MarkupHandler;Lscala/runtime/CharRef;)V
Asciz	scala/xml/parsing/MarkupParser$$anonfun$4;
class	scala/xml/parsing/MarkupParser$$anonfun$4
Asciz	(Lscala/xml/parsing/MarkupHandler;Lscala/collection/Iterator;Lscala/runtime/CharRef;)V;
NameAndType	"<init>":(Lscala/xml/parsing/MarkupHandler;Lscala/collection/Iterator;Lscala/runtime/CharRef;)V
Method	scala/xml/parsing/MarkupParser$$anonfun$4."<init>":(Lscala/xml/parsing/MarkupHandler;Lscala/collection/Iterator;Lscala/runtime/CharRef;)V
Asciz	xCharRef;
Asciz	(Lscala/Function0;Lscala/Function0;)Ljava/lang/String;;
NameAndType	xCharRef:(Lscala/Function0;Lscala/Function0;)Ljava/lang/String;
InterfaceMethod	scala/xml/parsing/MarkupParser.xCharRef:(Lscala/Function0;Lscala/Function0;)Ljava/lang/String;
Asciz	(Ljava/lang/String;)Lscala/collection/mutable/StringBuilder;;
NameAndType	append:(Ljava/lang/String;)Lscala/collection/mutable/StringBuilder;
Method	scala/collection/mutable/StringBuilder.append:(Ljava/lang/String;)Lscala/collection/mutable/StringBuilder;
int	59;
Method	scala/collection/mutable/StringBuilder.toString:()Ljava/lang/String;
Asciz	lt;
String	lt
Asciz	equals;
Asciz	(Ljava/lang/Object;)Z;
NameAndType	equals:(Ljava/lang/Object;)Z
Method	java/lang/Object.equals:(Ljava/lang/Object;)Z
int	60;
Asciz	java/lang/String;
class	java/lang/String
Method	java/lang/String.toString:()Ljava/lang/String;
Asciz	gt;
String	gt
int	62;
Asciz	amp;
String	amp
int	38;
Asciz	apos;
String	apos
int	39;
Asciz	quot;
String	quot
int	34;
Asciz	quote;
String	quote
int	32;
Asciz	setLength;
NameAndType	setLength:(I)V
Method	scala/collection/mutable/StringBuilder.setLength:(I)V
Asciz	attval;
Asciz	Ljava/lang/String;;
Asciz	s;
Asciz	Lscala/collection/Seq;;
Asciz	c$1;
Asciz	Lscala/runtime/CharRef;;
Asciz	it$1;
Asciz	Lscala/collection/Iterator;;
Asciz	d;
Asciz	C;
Asciz	nbuf;
Asciz	Lscala/collection/mutable/StringBuilder;;
Asciz	temp77;
Asciz	temp84;
Asciz	temp85;
Asciz	name;
Asciz	pop;
Asciz	head;
NameAndType	head:()Ljava/lang/Object;
InterfaceMethod	scala/collection/IterableLike.head:()Ljava/lang/Object;
Asciz	scala/io/Source;
class	scala/io/Source
Asciz	scala/collection/TraversableLike;
class	scala/collection/TraversableLike
Asciz	tail;
NameAndType	tail:()Ljava/lang/Object;
InterfaceMethod	scala/collection/TraversableLike.tail:()Ljava/lang/Object;
Asciz	scala/collection/immutable/List;
class	scala/collection/immutable/List
Asciz	curInput;
NameAndType	curInput:()Lscala/io/Source;
InterfaceMethod	scala/xml/parsing/MarkupParser.curInput:()Lscala/io/Source;
Method	scala/io/Source.ch:()C
Asciz	ch_$eq;
NameAndType	ch_$eq:(C)V
InterfaceMethod	scala/xml/parsing/MarkupParser.ch_$eq:(C)V
Asciz	pos;
NameAndType	pos:()I
Method	scala/io/Source.pos:()I
Asciz	pos_$eq;
NameAndType	pos_$eq:(I)V
InterfaceMethod	scala/xml/parsing/MarkupParser.pos_$eq:(I)V
Asciz	pushExternal;
Asciz	(Lscala/xml/parsing/MarkupHandler;Ljava/lang/String;)V;
Asciz	eof;
NameAndType	eof:()Z
InterfaceMethod	scala/xml/parsing/MarkupParser.eof:()Z
Asciz	$colon$colon;
Asciz	(Ljava/lang/Object;)Lscala/collection/immutable/List;;
NameAndType	$colon$colon:(Ljava/lang/Object;)Lscala/collection/immutable/List;
Method	scala/collection/immutable/List.$colon$colon:(Ljava/lang/Object;)Lscala/collection/immutable/List;
Asciz	externalSource;
Asciz	(Ljava/lang/String;)Lscala/io/Source;;
NameAndType	externalSource:(Ljava/lang/String;)Lscala/io/Source;
InterfaceMethod	scala/xml/parsing/MarkupParser.externalSource:(Ljava/lang/String;)Lscala/io/Source;
Asciz	systemId;
Asciz	push;
Asciz	scala/xml/parsing/MarkupHandler;
class	scala/xml/parsing/MarkupHandler
Asciz	replacementText;
NameAndType	replacementText:(Ljava/lang/String;)Lscala/io/Source;
Method	scala/xml/parsing/MarkupHandler.replacementText:(Ljava/lang/String;)Lscala/io/Source;
Asciz	entityName;
Asciz	reportValidationError;
Asciz	(Lscala/xml/parsing/MarkupHandler;ILjava/lang/String;)V;
Asciz	reportSyntaxError;
Asciz	(ILjava/lang/String;)V;
NameAndType	reportSyntaxError:(ILjava/lang/String;)V
InterfaceMethod	scala/xml/parsing/MarkupParser.reportSyntaxError:(ILjava/lang/String;)V
Asciz	I;
Asciz	str;
InterfaceMethod	scala/xml/parsing/MarkupParser.pos:()I
Asciz	reportError$default$3;
Asciz	()Ljava/io/PrintStream;;
NameAndType	reportError$default$3:()Ljava/io/PrintStream;
Method	scala/io/Source.reportError$default$3:()Ljava/io/PrintStream;
Asciz	reportError;
Asciz	(ILjava/lang/String;Ljava/io/PrintStream;)V;
NameAndType	reportError:(ILjava/lang/String;Ljava/io/PrintStream;)V
Method	scala/io/Source.reportError:(ILjava/lang/String;Ljava/io/PrintStream;)V
Asciz	qual$2;
Asciz	Lscala/io/Source;;
Asciz	x$12;
Asciz	Ljava/io/PrintStream;;
Asciz	notationDecl;
Asciz	OTATION;
String	OTATION
Asciz	(Lscala/collection/Seq;)V;
NameAndType	xToken:(Lscala/collection/Seq;)V
InterfaceMethod	scala/xml/parsing/MarkupParserCommon.xToken:(Lscala/collection/Seq;)V
Asciz	xSpace;
NameAndType	xSpace:()V
InterfaceMethod	scala/xml/parsing/MarkupParserCommon.xSpace:()V
Asciz	xName;
NameAndType	xName:()Ljava/lang/String;
InterfaceMethod	scala/xml/parsing/MarkupParser.xName:()Ljava/lang/String;
int	83;
Asciz	externalID;
Asciz	()Lscala/xml/dtd/ExternalID;;
NameAndType	externalID:()Lscala/xml/dtd/ExternalID;
InterfaceMethod	scala/xml/parsing/MarkupParser.externalID:()Lscala/xml/dtd/ExternalID;
int	80;
Asciz	UBLIC;
String	UBLIC
Asciz	pubidLiteral;
NameAndType	pubidLiteral:()Ljava/lang/String;
InterfaceMethod	scala/xml/parsing/MarkupParser.pubidLiteral:()Ljava/lang/String;
Asciz	xSpaceOpt;
NameAndType	xSpaceOpt:()V
InterfaceMethod	scala/xml/parsing/MarkupParserCommon.xSpaceOpt:()V
Asciz	systemLiteral;
NameAndType	systemLiteral:()Ljava/lang/String;
InterfaceMethod	scala/xml/parsing/MarkupParser.systemLiteral:()Ljava/lang/String;
Asciz	scala/xml/dtd/PublicID;
class	scala/xml/dtd/PublicID
Asciz	(Ljava/lang/String;Ljava/lang/String;)V;
NameAndType	"<init>":(Ljava/lang/String;Ljava/lang/String;)V
Method	scala/xml/dtd/PublicID."<init>":(Ljava/lang/String;Ljava/lang/String;)V
Asciz	scala$xml$parsing$MarkupParser$$handle;
Asciz	()Lscala/xml/parsing/MarkupHandler;;
NameAndType	scala$xml$parsing$MarkupParser$$handle:()Lscala/xml/parsing/MarkupHandler;
InterfaceMethod	scala/xml/parsing/MarkupParser.scala$xml$parsing$MarkupParser$$handle:()Lscala/xml/parsing/MarkupHandler;
Asciz	(Ljava/lang/String;Lscala/xml/dtd/ExternalID;)V;
NameAndType	notationDecl:(Ljava/lang/String;Lscala/xml/dtd/ExternalID;)V
Method	scala/xml/parsing/MarkupHandler.notationDecl:(Ljava/lang/String;Lscala/xml/dtd/ExternalID;)V
Asciz	PUBLIC or SYSTEM expected;
String	PUBLIC or SYSTEM expected
NameAndType	reportSyntaxError:(Ljava/lang/String;)V
InterfaceMethod	scala/xml/parsing/MarkupParser.reportSyntaxError:(Ljava/lang/String;)V
Asciz	died parsing notationdecl;
String	died parsing notationdecl
Asciz	java/lang/RuntimeException;
class	java/lang/RuntimeException
Method	java/lang/RuntimeException."<init>":(Ljava/lang/String;)V
Asciz	pubID;
Asciz	sysID;
Asciz	notat;
Asciz	extID;
Asciz	Lscala/xml/dtd/ExternalID;;
Asciz	entityDecl;
Asciz	NTITY;
String	NTITY
int	37;
Asciz	scala/xml/dtd/ExtDef;
class	scala/xml/dtd/ExtDef
Asciz	(Lscala/xml/dtd/ExternalID;)V;
NameAndType	"<init>":(Lscala/xml/dtd/ExternalID;)V
Method	scala/xml/dtd/ExtDef."<init>":(Lscala/xml/dtd/ExternalID;)V
Asciz	parameterEntityDecl;
Asciz	(Ljava/lang/String;Lscala/xml/dtd/EntityDef;)V;
NameAndType	parameterEntityDecl:(Ljava/lang/String;Lscala/xml/dtd/EntityDef;)V
Method	scala/xml/parsing/MarkupHandler.parameterEntityDecl:(Ljava/lang/String;Lscala/xml/dtd/EntityDef;)V
Asciz	NDATA;
String	NDATA
Asciz	unparsedEntityDecl;
Asciz	(Ljava/lang/String;Lscala/xml/dtd/ExternalID;Ljava/lang/String;)V;
NameAndType	unparsedEntityDecl:(Ljava/lang/String;Lscala/xml/dtd/ExternalID;Ljava/lang/String;)V
Method	scala/xml/parsing/MarkupHandler.unparsedEntityDecl:(Ljava/lang/String;Lscala/xml/dtd/ExternalID;Ljava/lang/String;)V
Asciz	parsedEntityDecl;
NameAndType	parsedEntityDecl:(Ljava/lang/String;Lscala/xml/dtd/EntityDef;)V
Method	scala/xml/parsing/MarkupHandler.parsedEntityDecl:(Ljava/lang/String;Lscala/xml/dtd/EntityDef;)V
Asciz	xEntityValue;
NameAndType	xEntityValue:()Ljava/lang/String;
InterfaceMethod	scala/xml/parsing/MarkupParser.xEntityValue:()Ljava/lang/String;
Asciz	scala/xml/dtd/IntDef;
class	scala/xml/dtd/IntDef
Method	scala/xml/dtd/IntDef."<init>":(Ljava/lang/String;)V
Asciz	isParameterEntity;
Asciz	Z;
Asciz	n;
Asciz	av;
Asciz	temp76;
Asciz	attrDecl;
Asciz	TTLIST;
String	TTLIST
Asciz	scala/runtime/BoxedUnit;
class	scala/runtime/BoxedUnit
Asciz	UNIT;
Asciz	Lscala/runtime/BoxedUnit;;
NameAndType	UNIT:Lscala/runtime/BoxedUnit;
Field	scala/runtime/BoxedUnit.UNIT:Lscala/runtime/BoxedUnit;
Asciz	FIXED;
String	FIXED
Asciz	scala/xml/dtd/DEFAULT;
class	scala/xml/dtd/DEFAULT
Asciz	xAttributeValue;
NameAndType	xAttributeValue:()Ljava/lang/String;
InterfaceMethod	scala/xml/parsing/MarkupParser.xAttributeValue:()Ljava/lang/String;
Asciz	(ZLjava/lang/String;)V;
NameAndType	"<init>":(ZLjava/lang/String;)V
Method	scala/xml/dtd/DEFAULT."<init>":(ZLjava/lang/String;)V
Asciz	IMPLIED;
String	IMPLIED
Asciz	scala/xml/dtd/IMPLIED$;
class	scala/xml/dtd/IMPLIED$
Asciz	Lscala/xml/dtd/IMPLIED$;;
NameAndType	MODULE$:Lscala/xml/dtd/IMPLIED$;
Field	scala/xml/dtd/IMPLIED$.MODULE$:Lscala/xml/dtd/IMPLIED$;
Asciz	REQUIRED;
String	REQUIRED
Asciz	scala/xml/dtd/REQUIRED$;
class	scala/xml/dtd/REQUIRED$
Asciz	Lscala/xml/dtd/REQUIRED$;;
NameAndType	MODULE$:Lscala/xml/dtd/REQUIRED$;
Field	scala/xml/dtd/REQUIRED$.MODULE$:Lscala/xml/dtd/REQUIRED$;
Asciz	scala/xml/dtd/AttrDecl;
class	scala/xml/dtd/AttrDecl
Asciz	(Ljava/lang/String;Ljava/lang/String;Lscala/xml/dtd/DefaultDecl;)V;
NameAndType	"<init>":(Ljava/lang/String;Ljava/lang/String;Lscala/xml/dtd/DefaultDecl;)V
Method	scala/xml/dtd/AttrDecl."<init>":(Ljava/lang/String;Ljava/lang/String;Lscala/xml/dtd/DefaultDecl;)V
Asciz	reverse;
NameAndType	reverse:()Lscala/collection/immutable/List;
Method	scala/collection/immutable/List.reverse:()Lscala/collection/immutable/List;
Asciz	attListDecl;
Asciz	(Ljava/lang/String;Lscala/collection/immutable/List;)V;
NameAndType	attListDecl:(Ljava/lang/String;Lscala/collection/immutable/List;)V
Method	scala/xml/parsing/MarkupHandler.attListDecl:(Ljava/lang/String;Lscala/collection/immutable/List;)V
Asciz	temp71;
Asciz	aname;
Asciz	atpe;
Asciz	defdecl;
Asciz	Lscala/xml/dtd/DefaultDecl;;
Asciz	temp75;
Asciz	attList;
Asciz	Lscala/collection/immutable/List;;
Asciz	elementDecl;
Asciz	EMENT;
String	EMENT
Asciz	putChar;
NameAndType	putChar:(C)Lscala/collection/mutable/StringBuilder;
InterfaceMethod	scala/xml/parsing/MarkupParser.putChar:(C)Lscala/collection/mutable/StringBuilder;
Asciz	elemDecl;
NameAndType	elemDecl:(Ljava/lang/String;Ljava/lang/String;)V
Method	scala/xml/parsing/MarkupHandler.elemDecl:(Ljava/lang/String;Ljava/lang/String;)V
Asciz	cmstr;
Asciz	intSubset;
Asciz	isValidating;
NameAndType	isValidating:()Z
Method	scala/xml/parsing/MarkupHandler.isValidating:()Z
NameAndType	push:(Ljava/lang/String;)V
InterfaceMethod	scala/xml/parsing/MarkupParser.push:(Ljava/lang/String;)V
Asciz	peReference;
NameAndType	peReference:(Ljava/lang/String;)V
Method	scala/xml/parsing/MarkupHandler.peReference:(Ljava/lang/String;)V
Asciz	markupDecl1;
NameAndType	markupDecl1:()Ljava/lang/Object;
InterfaceMethod	scala/xml/parsing/MarkupParser.markupDecl1:()Ljava/lang/Object;
Asciz	scala/xml/parsing/MarkupParser$class;
class	scala/xml/parsing/MarkupParser$class
NameAndType	gd2$1:(Lscala/xml/parsing/MarkupHandler;)Z
Method	scala/xml/parsing/MarkupParser$class.gd2$1:(Lscala/xml/parsing/MarkupHandler;)Z
Method	scala/collection/mutable/StringBuilder."<init>":()V
Asciz	markupdecl: unexpected character ';
String	markupdecl: unexpected character '
Asciz	(Ljava/lang/Object;)Lscala/collection/mutable/StringBuilder;;
NameAndType	append:(Ljava/lang/Object;)Lscala/collection/mutable/StringBuilder;
Method	scala/collection/mutable/StringBuilder.append:(Ljava/lang/Object;)Lscala/collection/mutable/StringBuilder;
Asciz	' #;
String	' #
Asciz	boxToInteger;
Asciz	(I)Ljava/lang/Integer;;
NameAndType	boxToInteger:(I)Ljava/lang/Integer;
Method	scala/runtime/BoxesRunTime.boxToInteger:(I)Ljava/lang/Integer;
Method	scala/collection/mutable/StringBuilder.toString:()Ljava/lang/String;
Asciz	ent;
Asciz	temp68;
Asciz	(Lscala/xml/parsing/MarkupHandler;)Ljava/lang/Object;;
int	63;
Asciz	xProcInstr;
Asciz	()Lscala/xml/NodeSeq;;
NameAndType	xProcInstr:()Lscala/xml/NodeSeq;
InterfaceMethod	scala/xml/parsing/MarkupParser.xProcInstr:()Lscala/xml/NodeSeq;
int	33;
NameAndType	gd1$1:(Lscala/xml/parsing/MarkupHandler;)Z
Method	scala/xml/parsing/MarkupParser$class.gd1$1:(Lscala/xml/parsing/MarkupHandler;)Z
Asciz	NCLUDE;
String	NCLUDE
NameAndType	doInclude$1:(Lscala/xml/parsing/MarkupHandler;)C
Method	scala/xml/parsing/MarkupParser$class.doInclude$1:(Lscala/xml/parsing/MarkupHandler;)C
Asciz	NORE;
String	NORE
NameAndType	doIgnore$1:(Lscala/xml/parsing/MarkupHandler;)C
Method	scala/xml/parsing/MarkupParser$class.doIgnore$1:(Lscala/xml/parsing/MarkupHandler;)C
Asciz	INCLUDE;
String	INCLUDE
Asciz	IGNORE;
String	IGNORE
Asciz	unexpected character ';
String	unexpected character '
Asciz	', expected some markupdecl;
String	', expected some markupdecl
NameAndType	notationDecl:()V
InterfaceMethod	scala/xml/parsing/MarkupParser.notationDecl:()V
int	76;
NameAndType	elementDecl:()V
InterfaceMethod	scala/xml/parsing/MarkupParser.elementDecl:()V
NameAndType	entityDecl:()V
InterfaceMethod	scala/xml/parsing/MarkupParser.entityDecl:()V
NameAndType	attrDecl:()V
InterfaceMethod	scala/xml/parsing/MarkupParser.attrDecl:()V
Asciz	xComment;
NameAndType	xComment:()Lscala/xml/NodeSeq;
InterfaceMethod	scala/xml/parsing/MarkupParser.xComment:()Lscala/xml/NodeSeq;
Asciz	temp65;
Asciz	stmt;
Asciz	temp66;
Asciz	qual$1;
Asciz	x$7;
Asciz	x$8;
Asciz	x$9;
Asciz	temp67;
Asciz	extSubset;
Asciz	textDecl;
Asciz	()Lscala/Tuple2;;
NameAndType	textDecl:()Lscala/Tuple2;
InterfaceMethod	scala/xml/parsing/MarkupParser.textDecl:()Lscala/Tuple2;
Asciz	(Lscala/xml/parsing/MarkupHandler;)Ljava/lang/String;;
Asciz	quote ' or \" expected;
String	quote ' or \" expected
Asciz	isPubIDChar;
NameAndType	isPubIDChar:(C)Z
InterfaceMethod	scala/xml/parsing/TokenTests.isPubIDChar:(C)Z
Asciz	char ';
String	char '
Asciz	' is not allowed in public id;
String	' is not allowed in public id
Asciz	endch;
Asciz	xText;
Asciz	exit;
Asciz	(Lscala/xml/parsing/MarkupHandler;)Lscala/xml/NodeSeq;;
Method	scala/collection/mutable/StringBuilder.length:()I
Asciz	tmppos;
NameAndType	tmppos:()I
InterfaceMethod	scala/xml/parsing/MarkupParser.tmppos:()I
Asciz	procInstr;
Asciz	(ILjava/lang/String;Ljava/lang/String;)Lscala/xml/NodeSeq;;
NameAndType	procInstr:(ILjava/lang/String;Ljava/lang/String;)Lscala/xml/NodeSeq;
Method	scala/xml/parsing/MarkupHandler.procInstr:(ILjava/lang/String;Ljava/lang/String;)Lscala/xml/NodeSeq;
Asciz	?>;
String	?>
Asciz	sb;
Asciz	isNameStart;
NameAndType	isNameStart:(C)Z
InterfaceMethod	scala/xml/parsing/TokenTests.isNameStart:(C)Z
Asciz	isNameChar;
NameAndType	isNameChar:(C)Z
InterfaceMethod	scala/xml/parsing/TokenTests.isNameChar:(C)Z
Asciz	intern;
NameAndType	intern:()Ljava/lang/String;
Method	java/lang/String.intern:()Ljava/lang/String;
Asciz	name expected;
String	name expected
Asciz	;
String	
Asciz	element1;
Asciz	(Lscala/xml/parsing/MarkupHandler;Lscala/xml/NamespaceBinding;)Lscala/xml/NodeSeq;;
Asciz	xTag;
Asciz	(Lscala/xml/NamespaceBinding;)Lscala/Tuple3;;
NameAndType	xTag:(Lscala/xml/NamespaceBinding;)Lscala/Tuple3;
InterfaceMethod	scala/xml/parsing/MarkupParser.xTag:(Lscala/xml/NamespaceBinding;)Lscala/Tuple3;
Asciz	scala/Tuple3;
class	scala/Tuple3
Asciz	_1;
NameAndType	_1:()Ljava/lang/Object;
Method	scala/Tuple3._1:()Ljava/lang/Object;
Asciz	_2;
NameAndType	_2:()Ljava/lang/Object;
Method	scala/Tuple3._2:()Ljava/lang/Object;
Asciz	scala/xml/MetaData;
class	scala/xml/MetaData
Asciz	_3;
NameAndType	_3:()Ljava/lang/Object;
Method	scala/Tuple3._3:()Ljava/lang/Object;
Asciz	scala/xml/NamespaceBinding;
class	scala/xml/NamespaceBinding
Asciz	(Ljava/lang/Object;Ljava/lang/Object;Ljava/lang/Object;)V;
NameAndType	"<init>":(Ljava/lang/Object;Ljava/lang/Object;Ljava/lang/Object;)V
Method	scala/Tuple3."<init>":(Ljava/lang/Object;Ljava/lang/Object;Ljava/lang/Object;)V
Asciz	scala/xml/Utility$;
class	scala/xml/Utility$
Asciz	Lscala/xml/Utility$;;
NameAndType	MODULE$:Lscala/xml/Utility$;
Field	scala/xml/Utility$.MODULE$:Lscala/xml/Utility$;
Asciz	prefix;
Asciz	(Ljava/lang/String;)Lscala/Option;;
NameAndType	prefix:(Ljava/lang/String;)Lscala/Option;
Method	scala/xml/Utility$.prefix:(Ljava/lang/String;)Lscala/Option;
Asciz	scala/Some;
class	scala/Some
Asciz	x;
Asciz	Ljava/lang/Object;;
NameAndType	x:Ljava/lang/Object;
Field	scala/Some.x:Ljava/lang/Object;
Asciz	scala/Tuple2;
class	scala/Tuple2
Asciz	scala/collection/immutable/StringOps;
class	scala/collection/immutable/StringOps
Method	scala/collection/immutable/StringOps."<init>":(Ljava/lang/String;)V
Method	java/lang/String.length:()I
Asciz	scala/collection/IndexedSeqLike;
class	scala/collection/IndexedSeqLike
Asciz	drop;
Asciz	(I)Ljava/lang/Object;;
NameAndType	drop:(I)Ljava/lang/Object;
InterfaceMethod	scala/collection/IndexedSeqLike.drop:(I)Ljava/lang/Object;
Asciz	(Ljava/lang/Object;Ljava/lang/Object;)V;
NameAndType	"<init>":(Ljava/lang/Object;Ljava/lang/Object;)V
Method	scala/Tuple2."<init>":(Ljava/lang/Object;Ljava/lang/Object;)V
Asciz	scala/Option;
class	scala/Option
Method	scala/Option.toString:()Ljava/lang/String;
Method	scala/Tuple2._1:()Ljava/lang/Object;
Method	scala/Tuple2._2:()Ljava/lang/Object;
int	47;
Asciz	/>;
String	/>
Asciz	elemStart;
Asciz	(ILjava/lang/String;Ljava/lang/String;Lscala/xml/MetaData;Lscala/xml/NamespaceBinding;)V;
NameAndType	elemStart:(ILjava/lang/String;Ljava/lang/String;Lscala/xml/MetaData;Lscala/xml/NamespaceBinding;)V
Method	scala/xml/parsing/MarkupHandler.elemStart:(ILjava/lang/String;Ljava/lang/String;Lscala/xml/MetaData;Lscala/xml/NamespaceBinding;)V
Asciz	scala/xml/NodeSeq$;
class	scala/xml/NodeSeq$
Asciz	Lscala/xml/NodeSeq$;;
NameAndType	MODULE$:Lscala/xml/NodeSeq$;
Field	scala/xml/NodeSeq$.MODULE$:Lscala/xml/NodeSeq$;
Asciz	Empty;
NameAndType	Empty:()Lscala/xml/NodeSeq;
Method	scala/xml/NodeSeq$.Empty:()Lscala/xml/NodeSeq;
Asciz	content;
Asciz	(Lscala/xml/NamespaceBinding;)Lscala/xml/NodeSeq;;
NameAndType	content:(Lscala/xml/NamespaceBinding;)Lscala/xml/NodeSeq;
InterfaceMethod	scala/xml/parsing/MarkupParser.content:(Lscala/xml/NamespaceBinding;)Lscala/xml/NodeSeq;
Asciz	xEndTag;
NameAndType	xEndTag:(Ljava/lang/String;)V
InterfaceMethod	scala/xml/parsing/MarkupParser.xEndTag:(Ljava/lang/String;)V
Asciz	elem;
Asciz	(ILjava/lang/String;Ljava/lang/String;Lscala/xml/MetaData;Lscala/xml/NamespaceBinding;Lscala/xml/NodeSeq;)Lscala/xml/NodeSeq;;
NameAndType	elem:(ILjava/lang/String;Ljava/lang/String;Lscala/xml/MetaData;Lscala/xml/NamespaceBinding;Lscala/xml/NodeSeq;)Lscala/xml/NodeSeq;
Method	scala/xml/parsing/MarkupHandler.elem:(ILjava/lang/String;Ljava/lang/String;Lscala/xml/MetaData;Lscala/xml/NamespaceBinding;Lscala/xml/NodeSeq;)Lscala/xml/NodeSeq;
Asciz	elemEnd;
Asciz	(ILjava/lang/String;Ljava/lang/String;)V;
NameAndType	elemEnd:(ILjava/lang/String;Ljava/lang/String;)V
Method	scala/xml/parsing/MarkupHandler.elemEnd:(ILjava/lang/String;Ljava/lang/String;)V
Method	scala/Tuple2.toString:()Ljava/lang/String;
Method	scala/Tuple3.toString:()Ljava/lang/String;
Asciz	pscope;
Asciz	Lscala/xml/NamespaceBinding;;
Asciz	temp53;
Asciz	temp54;
Asciz	Lscala/xml/MetaData;;
Asciz	temp55;
Asciz	temp57;
Asciz	Lscala/Some;;
Asciz	temp58;
Asciz	temp60;
Asciz	temp61;
Asciz	qname;
Asciz	tmp;
Asciz	Lscala/xml/NodeSeq;;
Asciz	aMap;
Asciz	scope;
Asciz	ts;
Asciz	pre;
Asciz	local;
Asciz	res;
Asciz	temp59;
Asciz	Lscala/Tuple2;;
Asciz	temp56;
Asciz	Lscala/Option;;
Asciz	temp52;
Asciz	Lscala/Tuple3;;
Asciz	element;
NameAndType	element1:(Lscala/xml/NamespaceBinding;)Lscala/xml/NodeSeq;
InterfaceMethod	scala/xml/parsing/MarkupParser.element1:(Lscala/xml/NamespaceBinding;)Lscala/xml/NodeSeq;
Asciz	parseDTD;
Asciz	scala/runtime/ObjectRef;
class	scala/runtime/ObjectRef
Asciz	(Ljava/lang/Object;)V;
NameAndType	"<init>":(Ljava/lang/Object;)V
Method	scala/runtime/ObjectRef."<init>":(Ljava/lang/Object;)V
Asciz	dtd;
Asciz	()Lscala/xml/dtd/DTD;;
NameAndType	dtd:()Lscala/xml/dtd/DTD;
InterfaceMethod	scala/xml/parsing/MarkupParser.dtd:()Lscala/xml/dtd/DTD;
Asciz	unexpected character (DOCTYPE already defined;
String	unexpected character (DOCTYPE already defined
Asciz	DOCTYPE;
String	DOCTYPE
NameAndType	elem:Ljava/lang/Object;
Field	scala/runtime/ObjectRef.elem:Ljava/lang/Object;
Asciz	scala/xml/dtd/ExternalID;
class	scala/xml/dtd/ExternalID
NameAndType	systemId:()Ljava/lang/String;
Method	scala/xml/dtd/ExternalID.systemId:()Ljava/lang/String;
NameAndType	pushExternal:(Ljava/lang/String;)V
InterfaceMethod	scala/xml/parsing/MarkupParser.pushExternal:(Ljava/lang/String;)V
NameAndType	extSubset:()V
InterfaceMethod	scala/xml/parsing/MarkupParser.extSubset:()V
NameAndType	pop:()V
InterfaceMethod	scala/xml/parsing/MarkupParser.pop:()V
NameAndType	intSubset:()V
InterfaceMethod	scala/xml/parsing/MarkupParser.intSubset:()V
Asciz	scala/xml/parsing/MarkupParser$$anon$2;
class	scala/xml/parsing/MarkupParser$$anon$2
Method	scala/xml/parsing/MarkupParser$$anon$2."<init>":(Lscala/xml/parsing/MarkupHandler;Lscala/runtime/ObjectRef;)V
Asciz	doc;
Asciz	()Lscala/xml/Document;;
NameAndType	doc:()Lscala/xml/Document;
InterfaceMethod	scala/xml/parsing/MarkupParser.doc:()Lscala/xml/Document;
Asciz	scala/xml/Document;
class	scala/xml/Document
Method	scala/xml/Document.dtd_$eq:(Lscala/xml/dtd/DTD;)V
Asciz	endDTD;
NameAndType	endDTD:(Ljava/lang/String;)V
Method	scala/xml/parsing/MarkupHandler.endDTD:(Ljava/lang/String;)V
Asciz	extID$1;
Asciz	Lscala/runtime/ObjectRef;;
Asciz	(Lscala/xml/parsing/MarkupHandler;)Lscala/xml/dtd/ExternalID;;
Asciz	YSTEM;
String	YSTEM
Asciz	scala/xml/dtd/SystemID;
class	scala/xml/dtd/SystemID
Method	scala/xml/dtd/SystemID."<init>":(Ljava/lang/String;)V
Asciz	temp51;
Asciz	scala/xml/NodeBuffer;
class	scala/xml/NodeBuffer
Method	scala/xml/NodeBuffer."<init>":()V
NameAndType	done$1:(Lscala/xml/parsing/MarkupHandler;Lscala/runtime/ObjectRef;)Lscala/xml/NodeSeq;
Method	scala/xml/parsing/MarkupParser$class.done$1:(Lscala/xml/parsing/MarkupHandler;Lscala/runtime/ObjectRef;)Lscala/xml/NodeSeq;
Asciz	tmppos_$eq;
NameAndType	tmppos_$eq:(I)V
InterfaceMethod	scala/xml/parsing/MarkupParser.tmppos_$eq:(I)V
NameAndType	xText:()Ljava/lang/String;
InterfaceMethod	scala/xml/parsing/MarkupParser.xText:()Ljava/lang/String;
Asciz	appendText;
Asciz	(ILscala/xml/NodeBuffer;Ljava/lang/String;)V;
NameAndType	appendText:(ILscala/xml/NodeBuffer;Ljava/lang/String;)V
InterfaceMethod	scala/xml/parsing/MarkupParser.appendText:(ILscala/xml/NodeBuffer;Ljava/lang/String;)V
Asciz	content1;
Asciz	(Lscala/xml/NamespaceBinding;Lscala/xml/NodeBuffer;)V;
NameAndType	content1:(Lscala/xml/NamespaceBinding;Lscala/xml/NodeBuffer;)V
InterfaceMethod	scala/xml/parsing/MarkupParser.content1:(Lscala/xml/NamespaceBinding;Lscala/xml/NodeBuffer;)V
Asciz	scala/xml/parsing/MarkupParser$$anonfun$1;
class	scala/xml/parsing/MarkupParser$$anonfun$1
NameAndType	"<init>":(Lscala/xml/parsing/MarkupHandler;)V
Method	scala/xml/parsing/MarkupParser$$anonfun$1."<init>":(Lscala/xml/parsing/MarkupHandler;)V
Asciz	scala/xml/parsing/MarkupParser$$anonfun$2;
class	scala/xml/parsing/MarkupParser$$anonfun$2
Method	scala/xml/parsing/MarkupParser$$anonfun$2."<init>":(Lscala/xml/parsing/MarkupHandler;)V
Asciz	text;
Asciz	(ILjava/lang/String;)Lscala/xml/NodeSeq;;
NameAndType	text:(ILjava/lang/String;)Lscala/xml/NodeSeq;
Method	scala/xml/parsing/MarkupHandler.text:(ILjava/lang/String;)Lscala/xml/NodeSeq;
Asciz	$amp$plus;
Asciz	(Ljava/lang/Object;)Lscala/xml/NodeBuffer;;
NameAndType	$amp$plus:(Ljava/lang/Object;)Lscala/xml/NodeBuffer;
Method	scala/xml/NodeBuffer.$amp$plus:(Ljava/lang/Object;)Lscala/xml/NodeBuffer;
Asciz	scala/xml/Utility$Escapes$;
class	scala/xml/Utility$Escapes$
Asciz	Lscala/xml/Utility$Escapes$;;
NameAndType	MODULE$:Lscala/xml/Utility$Escapes$;
Field	scala/xml/Utility$Escapes$.MODULE$:Lscala/xml/Utility$Escapes$;
Asciz	pairs;
Asciz	()Lscala/collection/immutable/Map;;
NameAndType	pairs:()Lscala/collection/immutable/Map;
Method	scala/xml/Utility$Escapes$.pairs:()Lscala/collection/immutable/Map;
Asciz	scala/collection/MapLike;
class	scala/collection/MapLike
Asciz	contains;
NameAndType	contains:(Ljava/lang/Object;)Z
InterfaceMethod	scala/collection/MapLike.contains:(Ljava/lang/Object;)Z
Asciz	entityRef;
NameAndType	entityRef:(ILjava/lang/String;)Lscala/xml/NodeSeq;
Method	scala/xml/parsing/MarkupHandler.entityRef:(ILjava/lang/String;)Lscala/xml/NodeSeq;
Asciz	apply;
Asciz	(Ljava/lang/Object;)Ljava/lang/Object;;
NameAndType	apply:(Ljava/lang/Object;)Ljava/lang/Object;
InterfaceMethod	scala/collection/MapLike.apply:(Ljava/lang/Object;)Ljava/lang/Object;
Asciz	temp48;
Asciz	theChar;
Asciz	ts$2;
Asciz	temp49;
Asciz	temp50;
Asciz	(Lscala/xml/parsing/MarkupHandler;Lscala/xml/NamespaceBinding;Lscala/xml/NodeBuffer;)V;
Asciz	xCharData;
NameAndType	xCharData:()Lscala/xml/NodeSeq;
InterfaceMethod	scala/xml/parsing/MarkupParser.xCharData:()Lscala/xml/NodeSeq;
int	68;
NameAndType	parseDTD:()V
InterfaceMethod	scala/xml/parsing/MarkupParser.parseDTD:()V
Asciz	Lscala/xml/NodeBuffer;;
Asciz	temp47;
Asciz	(Lscala/xml/parsing/MarkupHandler;ILscala/xml/NodeBuffer;Ljava/lang/String;)V;
Asciz	preserveWS;
NameAndType	preserveWS:()Z
InterfaceMethod	scala/xml/parsing/MarkupParser.preserveWS:()Z
Asciz	scala/xml/TextBuffer;
class	scala/xml/TextBuffer
Method	scala/xml/TextBuffer."<init>":()V
Asciz	(Lscala/collection/Seq;)Lscala/xml/TextBuffer;;
NameAndType	append:(Lscala/collection/Seq;)Lscala/xml/TextBuffer;
Method	scala/xml/TextBuffer.append:(Lscala/collection/Seq;)Lscala/xml/TextBuffer;
Asciz	toText;
Asciz	()Lscala/collection/Seq;;
NameAndType	toText:()Lscala/collection/Seq;
Method	scala/xml/TextBuffer.toText:()Lscala/collection/Seq;
Asciz	scala/xml/parsing/MarkupParser$$anonfun$appendText$1;
class	scala/xml/parsing/MarkupParser$$anonfun$appendText$1
Asciz	(Lscala/xml/parsing/MarkupHandler;ILscala/xml/NodeBuffer;)V;
NameAndType	"<init>":(Lscala/xml/parsing/MarkupHandler;ILscala/xml/NodeBuffer;)V
Method	scala/xml/parsing/MarkupParser$$anonfun$appendText$1."<init>":(Lscala/xml/parsing/MarkupHandler;ILscala/xml/NodeBuffer;)V
Asciz	foreach;
Asciz	(Lscala/Function1;)V;
NameAndType	foreach:(Lscala/Function1;)V
InterfaceMethod	scala/collection/IterableLike.foreach:(Lscala/Function1;)V
Asciz	pos$1;
Asciz	ts$1;
Asciz	txt;
Asciz	--;
String	--
int	45;
Asciz	comment;
NameAndType	comment:(ILjava/lang/String;)Lscala/xml/NodeSeq;
Method	scala/xml/parsing/MarkupHandler.comment:(ILjava/lang/String;)Lscala/xml/NodeSeq;
Asciz	(Lscala/xml/parsing/MarkupHandler;Lscala/Function0;Lscala/Function0;)Ljava/lang/String;;
Asciz	scala/xml/parsing/MarkupParser$$anonfun$xCharRef$1;
class	scala/xml/parsing/MarkupParser$$anonfun$xCharRef$1
Method	scala/xml/parsing/MarkupParser$$anonfun$xCharRef$1."<init>":(Lscala/xml/parsing/MarkupHandler;)V
Asciz	parseCharRef;
Asciz	(Lscala/Function0;Lscala/Function0;Lscala/Function1;)Ljava/lang/String;;
NameAndType	parseCharRef:(Lscala/Function0;Lscala/Function0;Lscala/Function1;)Ljava/lang/String;
Method	scala/xml/Utility$.parseCharRef:(Lscala/Function0;Lscala/Function0;Lscala/Function1;)Ljava/lang/String;
Asciz	Lscala/Function0;;
Asciz	[CDATA[;
String	[CDATA[
Asciz	scala/xml/PCData;
class	scala/xml/PCData
Method	scala/xml/PCData."<init>":(Ljava/lang/String;)V
Asciz	expected closing tag of ;
String	expected closing tag of 
Asciz	m;
Asciz	(Lscala/xml/parsing/MarkupHandler;Lscala/xml/NamespaceBinding;)Lscala/Tuple3;;
Asciz	xAttributes;
Asciz	(Lscala/xml/NamespaceBinding;)Lscala/Tuple2;;
NameAndType	xAttributes:(Lscala/xml/NamespaceBinding;)Lscala/Tuple2;
InterfaceMethod	scala/xml/parsing/MarkupParser.xAttributes:(Lscala/xml/NamespaceBinding;)Lscala/Tuple2;
Asciz	scala/xml/Null$;
class	scala/xml/Null$
Asciz	Lscala/xml/Null$;;
NameAndType	MODULE$:Lscala/xml/Null$;
Field	scala/xml/Null$.MODULE$:Lscala/xml/Null$;
Asciz	temp42;
Asciz	temp43;
Asciz	temp41;
Asciz	'<' not allowed in attrib value;
String	'<' not allowed in attrib value
Asciz	(Ljava/lang/String;)Ljava/lang/String;;
NameAndType	normalizeAttributeValue:(Ljava/lang/String;)Ljava/lang/String;
InterfaceMethod	scala/xml/parsing/MarkupParser.normalizeAttributeValue:(Ljava/lang/String;)Ljava/lang/String;
Asciz	(Lscala/xml/parsing/MarkupHandler;Lscala/xml/NamespaceBinding;)Lscala/Tuple2;;
Asciz	xEQ;
NameAndType	xEQ:()V
InterfaceMethod	scala/xml/parsing/MarkupParserCommon.xEQ:()V
Asciz	xmlns;
String	xmlns
int	6;
Asciz	substring;
Asciz	(II)Ljava/lang/String;;
NameAndType	substring:(II)Ljava/lang/String;
Method	java/lang/String.substring:(II)Ljava/lang/String;
Asciz	(Ljava/lang/String;Ljava/lang/String;Lscala/xml/NamespaceBinding;)V;
NameAndType	"<init>":(Ljava/lang/String;Ljava/lang/String;Lscala/xml/NamespaceBinding;)V
Method	scala/xml/NamespaceBinding."<init>":(Ljava/lang/String;Ljava/lang/String;Lscala/xml/NamespaceBinding;)V
Asciz	scala/xml/PrefixedAttribute;
class	scala/xml/PrefixedAttribute
Asciz	scala/xml/Text$;
class	scala/xml/Text$
Asciz	Lscala/xml/Text$;;
NameAndType	MODULE$:Lscala/xml/Text$;
Field	scala/xml/Text$.MODULE$:Lscala/xml/Text$;
Asciz	(Ljava/lang/String;)Lscala/xml/Text;;
NameAndType	apply:(Ljava/lang/String;)Lscala/xml/Text;
Method	scala/xml/Text$.apply:(Ljava/lang/String;)Lscala/xml/Text;
Asciz	(Ljava/lang/String;Ljava/lang/String;Lscala/collection/Seq;Lscala/xml/MetaData;)V;
NameAndType	"<init>":(Ljava/lang/String;Ljava/lang/String;Lscala/collection/Seq;Lscala/xml/MetaData;)V
Method	scala/xml/PrefixedAttribute."<init>":(Ljava/lang/String;Ljava/lang/String;Lscala/collection/Seq;Lscala/xml/MetaData;)V
Asciz	scala/xml/UnprefixedAttribute;
class	scala/xml/UnprefixedAttribute
Asciz	(Ljava/lang/String;Lscala/collection/Seq;Lscala/xml/MetaData;)V;
NameAndType	"<init>":(Ljava/lang/String;Lscala/collection/Seq;Lscala/xml/MetaData;)V
Method	scala/xml/UnprefixedAttribute."<init>":(Ljava/lang/String;Lscala/collection/Seq;Lscala/xml/MetaData;)V
Asciz	wellformed;
Asciz	(Lscala/xml/NamespaceBinding;)Z;
NameAndType	wellformed:(Lscala/xml/NamespaceBinding;)Z
Method	scala/xml/MetaData.wellformed:(Lscala/xml/NamespaceBinding;)Z
Asciz	double attribute;
String	double attribute
Asciz	temp38;
Asciz	temp39;
Asciz	key;
Asciz	value;
Asciz	temp37;
Method	scala/io/Source.hasNext:()Z
NameAndType	next:()C
Method	scala/io/Source.next:()C
Asciz	ilen;
Asciz	initialize;
Asciz	(Lscala/xml/parsing/MarkupHandler;)Lscala/xml/parsing/MarkupHandler;;
Asciz	(Lscala/xml/parsing/MarkupHandler;C)Lscala/collection/mutable/StringBuilder;;
Asciz	c;
Asciz	document;
Asciz	(Lscala/xml/parsing/MarkupHandler;)Lscala/xml/Document;;
Method	scala/xml/Document."<init>":()V
Asciz	scala/None$;
class	scala/None$
Asciz	Lscala/None$;;
NameAndType	MODULE$:Lscala/None$;
Field	scala/None$.MODULE$:Lscala/None$;
Asciz	< expected;
String	< expected
Asciz	prolog;
Asciz	()Lscala/Tuple3;;
NameAndType	prolog:()Lscala/Tuple3;
InterfaceMethod	scala/xml/parsing/MarkupParser.prolog:()Lscala/Tuple3;
Asciz	version_$eq;
Asciz	(Lscala/Option;)V;
NameAndType	version_$eq:(Lscala/Option;)V
Method	scala/xml/Document.version_$eq:(Lscala/Option;)V
Asciz	encoding_$eq;
NameAndType	encoding_$eq:(Lscala/Option;)V
Method	scala/xml/Document.encoding_$eq:(Lscala/Option;)V
Asciz	standAlone_$eq;
NameAndType	standAlone_$eq:(Lscala/Option;)V
Method	scala/xml/Document.standAlone_$eq:(Lscala/Option;)V
Asciz	scala/xml/TopScope$;
class	scala/xml/TopScope$
Asciz	Lscala/xml/TopScope$;;
NameAndType	MODULE$:Lscala/xml/TopScope$;
Field	scala/xml/TopScope$.MODULE$:Lscala/xml/TopScope$;
Asciz	scala/xml/NodeSeq$$anon$1;
class	scala/xml/NodeSeq$$anon$1
NameAndType	"<init>":(Lscala/collection/Seq;)V
Method	scala/xml/NodeSeq$$anon$1."<init>":(Lscala/collection/Seq;)V
Asciz	scala/runtime/IntRef;
class	scala/runtime/IntRef
NameAndType	"<init>":(I)V
Method	scala/runtime/IntRef."<init>":(I)V
Asciz	scala/xml/parsing/MarkupParser$$anonfun$document$1;
class	scala/xml/parsing/MarkupParser$$anonfun$document$1
Asciz	(Lscala/xml/parsing/MarkupHandler;Lscala/runtime/IntRef;Lscala/runtime/ObjectRef;)V;
NameAndType	"<init>":(Lscala/xml/parsing/MarkupHandler;Lscala/runtime/IntRef;Lscala/runtime/ObjectRef;)V
Method	scala/xml/parsing/MarkupParser$$anonfun$document$1."<init>":(Lscala/xml/parsing/MarkupHandler;Lscala/runtime/IntRef;Lscala/runtime/ObjectRef;)V
NameAndType	elem:I
Field	scala/runtime/IntRef.elem:I
Asciz	document must contain exactly one element;
String	document must contain exactly one element
Asciz	scala/Console$;
class	scala/Console$
Asciz	Lscala/Console$;;
NameAndType	MODULE$:Lscala/Console$;
Field	scala/Console$.MODULE$:Lscala/Console$;
Asciz	toList;
NameAndType	toList:()Lscala/collection/immutable/List;
InterfaceMethod	scala/collection/TraversableLike.toList:()Lscala/collection/immutable/List;
Asciz	out;
NameAndType	out:()Ljava/io/PrintStream;
Method	scala/Console$.out:()Ljava/io/PrintStream;
Asciz	java/io/PrintStream;
class	java/io/PrintStream
Asciz	println;
NameAndType	println:(Ljava/lang/Object;)V
Method	java/io/PrintStream.println:(Ljava/lang/Object;)V
Asciz	children_$eq;
NameAndType	children_$eq:(Lscala/collection/Seq;)V
Method	scala/xml/Document.children_$eq:(Lscala/collection/Seq;)V
Asciz	scala/xml/Node;
class	scala/xml/Node
Asciz	docElem_$eq;
Asciz	(Lscala/xml/Node;)V;
NameAndType	docElem_$eq:(Lscala/xml/Node;)V
Method	scala/xml/Document.docElem_$eq:(Lscala/xml/Node;)V
Asciz	info_prolog;
Asciz	elemCount$1;
Asciz	Lscala/runtime/IntRef;;
Asciz	children;
Asciz	theNode$1;
Asciz	(Lscala/xml/parsing/MarkupHandler;)Lscala/Tuple2;;
Asciz	xmlProcInstr;
Asciz	()Lscala/xml/MetaData;;
NameAndType	xmlProcInstr:()Lscala/xml/MetaData;
InterfaceMethod	scala/xml/parsing/MarkupParser.xmlProcInstr:()Lscala/xml/MetaData;
Asciz	version;
String	version
Asciz	(Ljava/lang/String;)Lscala/collection/Seq;;
NameAndType	apply:(Ljava/lang/String;)Lscala/collection/Seq;
Method	scala/xml/MetaData.apply:(Ljava/lang/String;)Lscala/collection/Seq;
Asciz	scala/collection/SeqLike;
class	scala/collection/SeqLike
InterfaceMethod	scala/collection/SeqLike.toString:()Ljava/lang/String;
Asciz	unapply;
Asciz	(Ljava/lang/Object;)Lscala/Option;;
NameAndType	unapply:(Ljava/lang/Object;)Lscala/Option;
Method	scala/xml/Text$.unapply:(Ljava/lang/Object;)Lscala/Option;
Asciz	isEmpty;
NameAndType	isEmpty:()Z
Method	scala/Option.isEmpty:()Z
Asciz	get;
NameAndType	get:()Ljava/lang/Object;
Method	scala/Option.get:()Ljava/lang/Object;
Asciz	1.0;
String	1.0
Method	scala/Some."<init>":(Ljava/lang/Object;)V
Asciz	cannot deal with versions != 1.0;
String	cannot deal with versions != 1.0
Asciz	encoding;
String	encoding
Asciz	isValidIANAEncoding;
Asciz	(Lscala/collection/Seq;)Z;
NameAndType	isValidIANAEncoding:(Lscala/collection/Seq;)Z
InterfaceMethod	scala/xml/parsing/TokenTests.isValidIANAEncoding:(Lscala/collection/Seq;)Z
Asciz	\";
String	\"
Asciz	\" is not a valid encoding;
String	\" is not a valid encoding
Method	scala/xml/MetaData.length:()I
Asciz	VersionInfo EncodingDecl? or '?>' expected!;
String	VersionInfo EncodingDecl? or '?>' expected!
Asciz	temp21;
Asciz	temp26;
Asciz	temp27;
Asciz	info_ver;
Asciz	info_enc;
Asciz	temp24;
Asciz	temp19;
Asciz	(Lscala/xml/parsing/MarkupHandler;)Lscala/Tuple3;;
Asciz	standalone;
String	standalone
Asciz	yes;
String	yes
Asciz	boxToBoolean;
Asciz	(Z)Ljava/lang/Boolean;;
NameAndType	boxToBoolean:(Z)Ljava/lang/Boolean;
Method	scala/runtime/BoxesRunTime.boxToBoolean:(Z)Ljava/lang/Boolean;
Asciz	no;
String	no
Asciz	either 'yes' or 'no' expected;
String	either 'yes' or 'no' expected
Asciz	VersionInfo EncodingDecl? SDDecl? or '?>' expected!;
String	VersionInfo EncodingDecl? SDDecl? or '?>' expected!
Asciz	temp6;
Asciz	temp11;
Asciz	temp12;
Asciz	temp15;
Asciz	temp16;
Asciz	info_stdl;
Asciz	temp13;
Asciz	temp9;
Asciz	temp4;
Asciz	(Lscala/xml/parsing/MarkupHandler;)Lscala/xml/MetaData;;
Asciz	xml;
String	xml
Asciz	no xmlns definitions here, please.;
String	no xmlns definitions here, please.
Asciz	temp2;
Asciz	temp3;
Asciz	scp;
Asciz	md;
Asciz	temp1;
Asciz	xHandleError;
Asciz	(Lscala/xml/parsing/MarkupHandler;CLjava/lang/String;)V;
Asciz	that;
Asciz	msg;
Asciz	Scala;
Asciz	InnerClasses;
Asciz	scala/xml/NodeSeq;
class	scala/xml/NodeSeq
Asciz	$anon$1;
Asciz	$anon$2;
Asciz	$anonfun$2;
Asciz	$anonfun$1;
Asciz	$anonfun$4;
Asciz	$anonfun$3;
Asciz	$anonfun$document$1;
Asciz	$anonfun$xCharRef$1;
Asciz	$anonfun$appendText$1;

{
public static void $init$(scala.xml.parsing.MarkupHandler);
  Signature: (Lscala/xml/parsing/MarkupHandler;)V
  Code:
   Stack=3, Locals=1, Args_size=1
	aload_0
	checkcast	class scala/xml/parsing/MarkupParser
	aload_0
	checkcast	class scala/xml/parsing/MarkupParser
	invokeinterface	InterfaceMethod scala/xml/parsing/MarkupParser.input:()Lscala/io/Source;
	invokeinterface	InterfaceMethod scala/xml/parsing/MarkupParser.curInput_$eq:(Lscala/io/Source;)V
	aload_0
	checkcast	class scala/xml/parsing/MarkupParser
	aload_0
	invokeinterface	InterfaceMethod scala/xml/parsing/MarkupParser.scala$xml$parsing$MarkupParser$_setter_$scala$xml$parsing$MarkupParser$$handle_$eq:(Lscala/xml/parsing/MarkupHandler;)V
	aload_0
	checkcast	class scala/xml/parsing/MarkupParser
	getstatic	Field scala/collection/immutable/Nil$.MODULE$:Lscala/collection/immutable/Nil$;
	invokeinterface	InterfaceMethod scala/xml/parsing/MarkupParser.inpStack_$eq:(Lscala/collection/immutable/List;)V
	aload_0
	checkcast	class scala/xml/parsing/MarkupParser
	iconst_m1
	invokeinterface	InterfaceMethod scala/xml/parsing/MarkupParser.extIndex_$eq:(I)V
	aload_0
	checkcast	class scala/xml/parsing/MarkupParser
	new	class scala/collection/mutable/StringBuilder
	dup
	invokespecial	Method scala/collection/mutable/StringBuilder."<init>":()V
	invokeinterface	InterfaceMethod scala/xml/parsing/MarkupParser.scala$xml$parsing$MarkupParser$_setter_$cbuf_$eq:(Lscala/collection/mutable/StringBuilder;)V
	aload_0
	checkcast	class scala/xml/parsing/MarkupParser
	aconst_null
	invokeinterface	InterfaceMethod scala/xml/parsing/MarkupParser.dtd_$eq:(Lscala/xml/dtd/DTD;)V
	aload_0
	checkcast	class scala/xml/parsing/MarkupParser
	aconst_null
	invokeinterface	InterfaceMethod scala/xml/parsing/MarkupParser.doc_$eq:(Lscala/xml/Document;)V
	aload_0
	checkcast	class scala/xml/parsing/MarkupParser
	iconst_0
	invokeinterface	InterfaceMethod scala/xml/parsing/MarkupParser.eof_$eq:(Z)V
	return
  Labels:
  LocalVariableTable: 
   Start  Length  Slot  Name   Signature
   0      97      0    $this       Lscala/xml/parsing/MarkupHandler;


private static final boolean gd2$1(scala.xml.parsing.MarkupHandler);
  Signature: (Lscala/xml/parsing/MarkupHandler;)Z
  Code:
   Stack=2, Locals=1, Args_size=1
	aload_0
	checkcast	class scala/xml/parsing/TokenTests
	aload_0
	checkcast	class scala/xml/parsing/MarkupParser
	invokeinterface	InterfaceMethod scala/xml/parsing/MarkupParser.ch:()C
	invokeinterface	InterfaceMethod scala/xml/parsing/TokenTests.isSpace:(C)Z
	ireturn
  Labels:
  LocalVariableTable: 
   Start  Length  Slot  Name   Signature
   0      19      0    $this       Lscala/xml/parsing/MarkupHandler;


private static final boolean gd1$1(scala.xml.parsing.MarkupHandler);
  Signature: (Lscala/xml/parsing/MarkupHandler;)Z
  Code:
   Stack=2, Locals=1, Args_size=1
	aload_0
	checkcast	class scala/xml/parsing/MarkupParser
	invokeinterface	InterfaceMethod scala/xml/parsing/MarkupParser.inpStack:()Lscala/collection/immutable/List;
	invokeinterface	InterfaceMethod scala/collection/LinearSeqLike.length:()I
	aload_0
	checkcast	class scala/xml/parsing/MarkupParser
	invokeinterface	InterfaceMethod scala/xml/parsing/MarkupParser.extIndex:()I
	if_icmplt	l1 // iconst_0
	iconst_1
	goto	l2 // ireturn
l1	iconst_0
l2	ireturn
  Labels:
   	l1 = 30 // iconst_0
   	l2 = 31 // ireturn
  LocalVariableTable: 
   Start  Length  Slot  Name   Signature
   0      32      0    $this       Lscala/xml/parsing/MarkupHandler;


private static final char doIgnore$1(scala.xml.parsing.MarkupHandler);
  Signature: (Lscala/xml/parsing/MarkupHandler;)C
  Code:
   Stack=2, Locals=1, Args_size=1
	aload_0
	checkcast	class scala/xml/parsing/MarkupParserCommon
	ldc	int 91
	invokeinterface	InterfaceMethod scala/xml/parsing/MarkupParserCommon.xToken:(C)V
l2	ldc	int 93
	aload_0
	checkcast	class scala/xml/parsing/MarkupParser
	invokeinterface	InterfaceMethod scala/xml/parsing/MarkupParser.ch:()C
	if_icmpeq	l1 // aload_0
	aload_0
	checkcast	class scala/xml/parsing/MarkupParser
	invokeinterface	InterfaceMethod scala/xml/parsing/MarkupParser.nextch:()C
	pop
	goto	l2 // ldc
l1	aload_0
	checkcast	class scala/xml/parsing/MarkupParser
	invokeinterface	InterfaceMethod scala/xml/parsing/MarkupParser.nextch:()C
	ireturn
  Labels:
   	l2 = 11 // ldc
   	l1 = 38 // aload_0
  LocalVariableTable: 
   Start  Length  Slot  Name   Signature
   0      48      0    $this       Lscala/xml/parsing/MarkupHandler;


private static final char doInclude$1(scala.xml.parsing.MarkupHandler);
  Signature: (Lscala/xml/parsing/MarkupHandler;)C
  Code:
   Stack=2, Locals=1, Args_size=1
	aload_0
	checkcast	class scala/xml/parsing/MarkupParserCommon
	ldc	int 91
	invokeinterface	InterfaceMethod scala/xml/parsing/MarkupParserCommon.xToken:(C)V
l2	ldc	int 93
	aload_0
	checkcast	class scala/xml/parsing/MarkupParser
	invokeinterface	InterfaceMethod scala/xml/parsing/MarkupParser.ch:()C
	if_icmpeq	l1 // aload_0
	aload_0
	checkcast	class scala/xml/parsing/MarkupParser
	invokeinterface	InterfaceMethod scala/xml/parsing/MarkupParser.markupDecl:()V
	goto	l2 // ldc
l1	aload_0
	checkcast	class scala/xml/parsing/MarkupParser
	invokeinterface	InterfaceMethod scala/xml/parsing/MarkupParser.nextch:()C
	ireturn
  Labels:
   	l2 = 11 // ldc
   	l1 = 37 // aload_0
  LocalVariableTable: 
   Start  Length  Slot  Name   Signature
   0      47      0    $this       Lscala/xml/parsing/MarkupHandler;


private static final scala.xml.NodeSeq done$1(scala.xml.parsing.MarkupHandler, scala.runtime.ObjectRef);
  Signature: (Lscala/xml/parsing/MarkupHandler;Lscala/runtime/ObjectRef;)Lscala/xml/NodeSeq;
  Code:
   Stack=4, Locals=2, Args_size=2
	new	class scala/xml/parsing/MarkupParser$$anon$1
	dup
	aload_0
	aload_1
	invokespecial	Method scala/xml/parsing/MarkupParser$$anon$1."<init>":(Lscala/xml/parsing/MarkupHandler;Lscala/runtime/ObjectRef;)V
	areturn
  Labels:
  LocalVariableTable: 
   Start  Length  Slot  Name   Signature
   0      10      0    $this       Lscala/xml/parsing/MarkupHandler;


public static java.lang.String normalizeAttributeValue(scala.xml.parsing.MarkupHandler, java.lang.String);
  Signature: (Lscala/xml/parsing/MarkupHandler;Ljava/lang/String;)Ljava/lang/String;
  Code:
   Stack=7, Locals=20, Args_size=2
	getstatic	Field scala/Predef$.MODULE$:Lscala/Predef$;
	aload_1
	invokevirtual	Method scala/Predef$.wrapString:(Ljava/lang/String;)Lscala/collection/immutable/WrappedString;
	astore_2
	aload_2
	invokeinterface	InterfaceMethod scala/collection/IterableLike.iterator:()Lscala/collection/Iterator;
	astore	5
l36	aload	5
	invokeinterface	InterfaceMethod scala/collection/Iterator.hasNext:()Z
	ifeq	l1 // aload_0
	aload	5
	invokeinterface	InterfaceMethod scala/collection/Iterator.next:()Ljava/lang/Object;
	invokestatic	Method scala/runtime/BoxesRunTime.unboxToChar:(Ljava/lang/Object;)C
	istore	16
	iload	16
	lookupswitch{ //5
		9: 811;
		10: 791;
		13: 771;
		32: 751;
		38: 129;
		default: 92 }
	iconst_1
	ifeq	l2 // new
	aload_0
	checkcast	class scala/xml/parsing/MarkupParser
	invokeinterface	InterfaceMethod scala/xml/parsing/MarkupParser.cbuf:()Lscala/collection/mutable/StringBuilder;
	iload	16
	invokevirtual	Method scala/collection/mutable/StringBuilder.append:(C)Lscala/collection/mutable/StringBuilder;
	goto	l3 // pop
l2	new	class scala/MatchError
	dup
	iload	16
	invokestatic	Method scala/runtime/BoxesRunTime.boxToCharacter:(C)Ljava/lang/Character;
	invokevirtual	Method java/lang/Object.toString:()Ljava/lang/String;
	invokespecial	Method scala/MatchError."<init>":(Ljava/lang/String;)V
	athrow
	iconst_1
	ifeq	l4 // new
	aload	5
	invokeinterface	InterfaceMethod scala/collection/Iterator.next:()Ljava/lang/Object;
	invokestatic	Method scala/runtime/BoxesRunTime.unboxToChar:(Ljava/lang/Object;)C
	istore	15
	iload	15
	ldc	int 35
	if_icmpne	l5 // iconst_1
	iconst_1
	ifeq	l6 // new
	new	class scala/runtime/CharRef
	dup
	aload	5
	invokeinterface	InterfaceMethod scala/collection/Iterator.next:()Ljava/lang/Object;
	invokestatic	Method scala/runtime/BoxesRunTime.unboxToChar:(Ljava/lang/Object;)C
	invokespecial	Method scala/runtime/CharRef."<init>":(C)V
	astore_3
	aload_0
	checkcast	class scala/xml/parsing/MarkupParser
	new	class scala/xml/parsing/MarkupParser$$anonfun$3
	dup
	aload_0
	aload_3
	invokespecial	Method scala/xml/parsing/MarkupParser$$anonfun$3."<init>":(Lscala/xml/parsing/MarkupHandler;Lscala/runtime/CharRef;)V
	new	class scala/xml/parsing/MarkupParser$$anonfun$4
	dup
	aload_0
	aload	5
	aload_3
	invokespecial	Method scala/xml/parsing/MarkupParser$$anonfun$4."<init>":(Lscala/xml/parsing/MarkupHandler;Lscala/collection/Iterator;Lscala/runtime/CharRef;)V
	invokeinterface	InterfaceMethod scala/xml/parsing/MarkupParser.xCharRef:(Lscala/Function0;Lscala/Function0;)Ljava/lang/String;
	astore	4
	aload_0
	checkcast	class scala/xml/parsing/MarkupParser
	invokeinterface	InterfaceMethod scala/xml/parsing/MarkupParser.cbuf:()Lscala/collection/mutable/StringBuilder;
	aload	4
	invokevirtual	Method scala/collection/mutable/StringBuilder.append:(Ljava/lang/String;)Lscala/collection/mutable/StringBuilder;
	goto	l3 // pop
l6	new	class scala/MatchError
	dup
	iload	15
	invokestatic	Method scala/runtime/BoxesRunTime.boxToCharacter:(C)Ljava/lang/Character;
	invokevirtual	Method java/lang/Object.toString:()Ljava/lang/String;
	invokespecial	Method scala/MatchError."<init>":(Ljava/lang/String;)V
	athrow
l5	iconst_1
	ifeq	l7 // new
	new	class scala/collection/mutable/StringBuilder
	dup
	invokespecial	Method scala/collection/mutable/StringBuilder."<init>":()V
	astore	7
	iload	15
	istore	6
l8	aload	7
	iload	6
	invokevirtual	Method scala/collection/mutable/StringBuilder.append:(C)Lscala/collection/mutable/StringBuilder;
	pop
	aload	5
	invokeinterface	InterfaceMethod scala/collection/Iterator.next:()Ljava/lang/Object;
	invokestatic	Method scala/runtime/BoxesRunTime.unboxToChar:(Ljava/lang/Object;)C
	istore	6
	iload	6
	ldc	int 59
	if_icmpne	l8 // aload
	aload	7
	invokevirtual	Method scala/collection/mutable/StringBuilder.toString:()Ljava/lang/String;
	astore	14
	aload	14
	ldc	String lt
	astore	8
	dup
	ifnonnull	l9 // aload
	pop
	aload	8
	ifnull	l10 // iconst_1
	goto	l11 // aload
l9	aload	8
	invokevirtual	Method java/lang/Object.equals:(Ljava/lang/Object;)Z
	ifeq	l11 // aload
l10	iconst_1
	ifeq	l12 // new
	aload_0
	checkcast	class scala/xml/parsing/MarkupParser
	invokeinterface	InterfaceMethod scala/xml/parsing/MarkupParser.cbuf:()Lscala/collection/mutable/StringBuilder;
	ldc	int 60
	invokevirtual	Method scala/collection/mutable/StringBuilder.append:(C)Lscala/collection/mutable/StringBuilder;
	goto	l3 // pop
l12	new	class scala/MatchError
	dup
	aload	14
	invokevirtual	Method java/lang/String.toString:()Ljava/lang/String;
	invokespecial	Method scala/MatchError."<init>":(Ljava/lang/String;)V
	athrow
l11	aload	14
	ldc	String gt
	astore	9
	dup
	ifnonnull	l13 // aload
	pop
	aload	9
	ifnull	l14 // iconst_1
	goto	l15 // aload
l13	aload	9
	invokevirtual	Method java/lang/Object.equals:(Ljava/lang/Object;)Z
	ifeq	l15 // aload
l14	iconst_1
	ifeq	l16 // new
	aload_0
	checkcast	class scala/xml/parsing/MarkupParser
	invokeinterface	InterfaceMethod scala/xml/parsing/MarkupParser.cbuf:()Lscala/collection/mutable/StringBuilder;
	ldc	int 62
	invokevirtual	Method scala/collection/mutable/StringBuilder.append:(C)Lscala/collection/mutable/StringBuilder;
	goto	l3 // pop
l16	new	class scala/MatchError
	dup
	aload	14
	invokevirtual	Method java/lang/String.toString:()Ljava/lang/String;
	invokespecial	Method scala/MatchError."<init>":(Ljava/lang/String;)V
	athrow
l15	aload	14
	ldc	String amp
	astore	10
	dup
	ifnonnull	l17 // aload
	pop
	aload	10
	ifnull	l18 // iconst_1
	goto	l19 // aload
l17	aload	10
	invokevirtual	Method java/lang/Object.equals:(Ljava/lang/Object;)Z
	ifeq	l19 // aload
l18	iconst_1
	ifeq	l20 // new
	aload_0
	checkcast	class scala/xml/parsing/MarkupParser
	invokeinterface	InterfaceMethod scala/xml/parsing/MarkupParser.cbuf:()Lscala/collection/mutable/StringBuilder;
	ldc	int 38
	invokevirtual	Method scala/collection/mutable/StringBuilder.append:(C)Lscala/collection/mutable/StringBuilder;
	goto	l3 // pop
l20	new	class scala/MatchError
	dup
	aload	14
	invokevirtual	Method java/lang/String.toString:()Ljava/lang/String;
	invokespecial	Method scala/MatchError."<init>":(Ljava/lang/String;)V
	athrow
l19	aload	14
	ldc	String apos
	astore	11
	dup
	ifnonnull	l21 // aload
	pop
	aload	11
	ifnull	l22 // iconst_1
	goto	l23 // aload
l21	aload	11
	invokevirtual	Method java/lang/Object.equals:(Ljava/lang/Object;)Z
	ifeq	l23 // aload
l22	iconst_1
	ifeq	l24 // new
	aload_0
	checkcast	class scala/xml/parsing/MarkupParser
	invokeinterface	InterfaceMethod scala/xml/parsing/MarkupParser.cbuf:()Lscala/collection/mutable/StringBuilder;
	ldc	int 39
	invokevirtual	Method scala/collection/mutable/StringBuilder.append:(C)Lscala/collection/mutable/StringBuilder;
	goto	l3 // pop
l24	new	class scala/MatchError
	dup
	aload	14
	invokevirtual	Method java/lang/String.toString:()Ljava/lang/String;
	invokespecial	Method scala/MatchError."<init>":(Ljava/lang/String;)V
	athrow
l23	aload	14
	ldc	String quot
	astore	12
	dup
	ifnonnull	l25 // aload
	pop
	aload	12
	ifnull	l26 // iconst_1
	goto	l27 // aload
l25	aload	12
	invokevirtual	Method java/lang/Object.equals:(Ljava/lang/Object;)Z
	ifeq	l27 // aload
l26	iconst_1
	ifeq	l28 // new
	aload_0
	checkcast	class scala/xml/parsing/MarkupParser
	invokeinterface	InterfaceMethod scala/xml/parsing/MarkupParser.cbuf:()Lscala/collection/mutable/StringBuilder;
	ldc	int 34
	invokevirtual	Method scala/collection/mutable/StringBuilder.append:(C)Lscala/collection/mutable/StringBuilder;
	goto	l3 // pop
l28	new	class scala/MatchError
	dup
	aload	14
	invokevirtual	Method java/lang/String.toString:()Ljava/lang/String;
	invokespecial	Method scala/MatchError."<init>":(Ljava/lang/String;)V
	athrow
l27	aload	14
	ldc	String quote
	astore	13
	dup
	ifnonnull	l29 // aload
	pop
	aload	13
	ifnull	l30 // iconst_1
	goto	l31 // iconst_1
l29	aload	13
	invokevirtual	Method java/lang/Object.equals:(Ljava/lang/Object;)Z
	ifeq	l31 // iconst_1
l30	iconst_1
	ifeq	l32 // new
	aload_0
	checkcast	class scala/xml/parsing/MarkupParser
	invokeinterface	InterfaceMethod scala/xml/parsing/MarkupParser.cbuf:()Lscala/collection/mutable/StringBuilder;
	ldc	int 34
	invokevirtual	Method scala/collection/mutable/StringBuilder.append:(C)Lscala/collection/mutable/StringBuilder;
	goto	l3 // pop
l32	new	class scala/MatchError
	dup
	aload	14
	invokevirtual	Method java/lang/String.toString:()Ljava/lang/String;
	invokespecial	Method scala/MatchError."<init>":(Ljava/lang/String;)V
	athrow
l31	iconst_1
	ifeq	l33 // new
	aload_0
	checkcast	class scala/xml/parsing/MarkupParser
	invokeinterface	InterfaceMethod scala/xml/parsing/MarkupParser.cbuf:()Lscala/collection/mutable/StringBuilder;
	ldc	int 38
	invokevirtual	Method scala/collection/mutable/StringBuilder.append:(C)Lscala/collection/mutable/StringBuilder;
	pop
	aload_0
	checkcast	class scala/xml/parsing/MarkupParser
	invokeinterface	InterfaceMethod scala/xml/parsing/MarkupParser.cbuf:()Lscala/collection/mutable/StringBuilder;
	aload	14
	invokevirtual	Method scala/collection/mutable/StringBuilder.append:(Ljava/lang/String;)Lscala/collection/mutable/StringBuilder;
	pop
	aload_0
	checkcast	class scala/xml/parsing/MarkupParser
	invokeinterface	InterfaceMethod scala/xml/parsing/MarkupParser.cbuf:()Lscala/collection/mutable/StringBuilder;
	ldc	int 59
	invokevirtual	Method scala/collection/mutable/StringBuilder.append:(C)Lscala/collection/mutable/StringBuilder;
	goto	l3 // pop
l33	new	class scala/MatchError
	dup
	aload	14
	invokevirtual	Method java/lang/String.toString:()Ljava/lang/String;
	invokespecial	Method scala/MatchError."<init>":(Ljava/lang/String;)V
	athrow
l7	new	class scala/MatchError
	dup
	iload	15
	invokestatic	Method scala/runtime/BoxesRunTime.boxToCharacter:(C)Ljava/lang/Character;
	invokevirtual	Method java/lang/Object.toString:()Ljava/lang/String;
	invokespecial	Method scala/MatchError."<init>":(Ljava/lang/String;)V
	athrow
l4	new	class scala/MatchError
	dup
	iload	16
	invokestatic	Method scala/runtime/BoxesRunTime.boxToCharacter:(C)Ljava/lang/Character;
	invokevirtual	Method java/lang/Object.toString:()Ljava/lang/String;
	invokespecial	Method scala/MatchError."<init>":(Ljava/lang/String;)V
	athrow
	iconst_1
	ifne	l34 // aload_0
	new	class scala/MatchError
	dup
	iload	16
	invokestatic	Method scala/runtime/BoxesRunTime.boxToCharacter:(C)Ljava/lang/Character;
	invokevirtual	Method java/lang/Object.toString:()Ljava/lang/String;
	invokespecial	Method scala/MatchError."<init>":(Ljava/lang/String;)V
	athrow
	iconst_1
	ifne	l34 // aload_0
	new	class scala/MatchError
	dup
	iload	16
	invokestatic	Method scala/runtime/BoxesRunTime.boxToCharacter:(C)Ljava/lang/Character;
	invokevirtual	Method java/lang/Object.toString:()Ljava/lang/String;
	invokespecial	Method scala/MatchError."<init>":(Ljava/lang/String;)V
	athrow
	iconst_1
	ifne	l34 // aload_0
	new	class scala/MatchError
	dup
	iload	16
	invokestatic	Method scala/runtime/BoxesRunTime.boxToCharacter:(C)Ljava/lang/Character;
	invokevirtual	Method java/lang/Object.toString:()Ljava/lang/String;
	invokespecial	Method scala/MatchError."<init>":(Ljava/lang/String;)V
	athrow
	iconst_1
	ifeq	l35 // new
l34	aload_0
	checkcast	class scala/xml/parsing/MarkupParser
	invokeinterface	InterfaceMethod scala/xml/parsing/MarkupParser.cbuf:()Lscala/collection/mutable/StringBuilder;
	ldc	int 32
	invokevirtual	Method scala/collection/mutable/StringBuilder.append:(C)Lscala/collection/mutable/StringBuilder;
l3	pop
	goto	l36 // aload
l35	new	class scala/MatchError
	dup
	iload	16
	invokestatic	Method scala/runtime/BoxesRunTime.boxToCharacter:(C)Ljava/lang/Character;
	invokevirtual	Method java/lang/Object.toString:()Ljava/lang/String;
	invokespecial	Method scala/MatchError."<init>":(Ljava/lang/String;)V
	athrow
l1	aload_0
	checkcast	class scala/xml/parsing/MarkupParser
	invokeinterface	InterfaceMethod scala/xml/parsing/MarkupParser.cbuf:()Lscala/collection/mutable/StringBuilder;
	invokevirtual	Method scala/collection/mutable/StringBuilder.toString:()Ljava/lang/String;
	astore	19
	aload_0
	checkcast	class scala/xml/parsing/MarkupParser
	invokeinterface	InterfaceMethod scala/xml/parsing/MarkupParser.cbuf:()Lscala/collection/mutable/StringBuilder;
	iconst_0
	istore	18
	astore	17
	aload	17
	iload	18
	invokevirtual	Method scala/collection/mutable/StringBuilder.setLength:(I)V
	aload	19
	areturn
  Labels:
   	l36 = 16 // aload
   	l2 = 113 // new
   	l6 = 222 // new
   	l5 = 238 // iconst_1
   	l8 = 255 // aload
   	l9 = 308 // aload
   	l10 = 316 // iconst_1
   	l12 = 337 // new
   	l11 = 350 // aload
   	l13 = 369 // aload
   	l14 = 377 // iconst_1
   	l16 = 398 // new
   	l15 = 411 // aload
   	l17 = 430 // aload
   	l18 = 438 // iconst_1
   	l20 = 459 // new
   	l19 = 472 // aload
   	l21 = 491 // aload
   	l22 = 499 // iconst_1
   	l24 = 520 // new
   	l23 = 533 // aload
   	l25 = 552 // aload
   	l26 = 560 // iconst_1
   	l28 = 581 // new
   	l27 = 594 // aload
   	l29 = 613 // aload
   	l30 = 621 // iconst_1
   	l32 = 642 // new
   	l31 = 655 // iconst_1
   	l33 = 706 // new
   	l7 = 719 // new
   	l4 = 735 // new
   	l34 = 815 // aload_0
   	l3 = 829 // pop
   	l35 = 833 // new
   	l1 = 849 // aload_0
  LocalVariableTable: 
   Start  Length  Slot  Name   Signature
   0      887      0    $this       Lscala/xml/parsing/MarkupHandler;
   0      887      1    attval       Ljava/lang/String;
   8      878      2    s       Lscala/collection/Seq;
   174      45      3    c$1       Lscala/runtime/CharRef;
   205      14      4    s       Ljava/lang/String;
   16      870      5    it$1       Lscala/collection/Iterator;
   255      464      6    d       C
   251      468      7    nbuf       Lscala/collection/mutable/StringBuilder;
   289      430      14    temp77       Ljava/lang/String;
   145      590      15    temp84       C
   38      792      16    temp85       C
   833      16      16    temp85       C
   863      23      19    name       Ljava/lang/String;


public static void pop(scala.xml.parsing.MarkupHandler);
  Signature: (Lscala/xml/parsing/MarkupHandler;)V
  Code:
   Stack=2, Locals=1, Args_size=1
	aload_0
	checkcast	class scala/xml/parsing/MarkupParser
	aload_0
	checkcast	class scala/xml/parsing/MarkupParser
	invokeinterface	InterfaceMethod scala/xml/parsing/MarkupParser.inpStack:()Lscala/collection/immutable/List;
	invokeinterface	InterfaceMethod scala/collection/IterableLike.head:()Ljava/lang/Object;
	checkcast	class scala/io/Source
	invokeinterface	InterfaceMethod scala/xml/parsing/MarkupParser.curInput_$eq:(Lscala/io/Source;)V
	aload_0
	checkcast	class scala/xml/parsing/MarkupParser
	aload_0
	checkcast	class scala/xml/parsing/MarkupParser
	invokeinterface	InterfaceMethod scala/xml/parsing/MarkupParser.inpStack:()Lscala/collection/immutable/List;
	invokeinterface	InterfaceMethod scala/collection/TraversableLike.tail:()Ljava/lang/Object;
	checkcast	class scala/collection/immutable/List
	invokeinterface	InterfaceMethod scala/xml/parsing/MarkupParser.inpStack_$eq:(Lscala/collection/immutable/List;)V
	aload_0
	checkcast	class scala/xml/parsing/MarkupParser
	aload_0
	checkcast	class scala/xml/parsing/MarkupParser
	invokeinterface	InterfaceMethod scala/xml/parsing/MarkupParser.curInput:()Lscala/io/Source;
	invokevirtual	Method scala/io/Source.ch:()C
	invokeinterface	InterfaceMethod scala/xml/parsing/MarkupParser.ch_$eq:(C)V
	aload_0
	checkcast	class scala/xml/parsing/MarkupParser
	aload_0
	checkcast	class scala/xml/parsing/MarkupParser
	invokeinterface	InterfaceMethod scala/xml/parsing/MarkupParser.curInput:()Lscala/io/Source;
	invokevirtual	Method scala/io/Source.pos:()I
	invokeinterface	InterfaceMethod scala/xml/parsing/MarkupParser.pos_$eq:(I)V
	aload_0
	checkcast	class scala/xml/parsing/MarkupParser
	iconst_0
	invokeinterface	InterfaceMethod scala/xml/parsing/MarkupParser.eof_$eq:(Z)V
	return
  Labels:
  LocalVariableTable: 
   Start  Length  Slot  Name   Signature
   0      105      0    $this       Lscala/xml/parsing/MarkupHandler;


public static void pushExternal(scala.xml.parsing.MarkupHandler, java.lang.String);
  Signature: (Lscala/xml/parsing/MarkupHandler;Ljava/lang/String;)V
  Code:
   Stack=3, Locals=3, Args_size=2
	aload_0
	checkcast	class scala/xml/parsing/MarkupParser
	invokeinterface	InterfaceMethod scala/xml/parsing/MarkupParser.eof:()Z
	ifne	l1 // aload_0
	aload_0
	checkcast	class scala/xml/parsing/MarkupParser
	aload_0
	checkcast	class scala/xml/parsing/MarkupParser
	invokeinterface	InterfaceMethod scala/xml/parsing/MarkupParser.curInput:()Lscala/io/Source;
	astore_2
	aload_0
	checkcast	class scala/xml/parsing/MarkupParser
	invokeinterface	InterfaceMethod scala/xml/parsing/MarkupParser.inpStack:()Lscala/collection/immutable/List;
	aload_2
	invokevirtual	Method scala/collection/immutable/List.$colon$colon:(Ljava/lang/Object;)Lscala/collection/immutable/List;
	invokeinterface	InterfaceMethod scala/xml/parsing/MarkupParser.inpStack_$eq:(Lscala/collection/immutable/List;)V
l1	aload_0
	checkcast	class scala/xml/parsing/MarkupParser
	aload_0
	checkcast	class scala/xml/parsing/MarkupParser
	aload_1
	invokeinterface	InterfaceMethod scala/xml/parsing/MarkupParser.externalSource:(Ljava/lang/String;)Lscala/io/Source;
	invokeinterface	InterfaceMethod scala/xml/parsing/MarkupParser.curInput_$eq:(Lscala/io/Source;)V
	aload_0
	checkcast	class scala/xml/parsing/MarkupParser
	invokeinterface	InterfaceMethod scala/xml/parsing/MarkupParser.nextch:()C
	pop
	return
  Labels:
   	l1 = 44 // aload_0
  LocalVariableTable: 
   Start  Length  Slot  Name   Signature
   0      74      0    $this       Lscala/xml/parsing/MarkupHandler;
   0      74      1    systemId       Ljava/lang/String;


public static void push(scala.xml.parsing.MarkupHandler, java.lang.String);
  Signature: (Lscala/xml/parsing/MarkupHandler;Ljava/lang/String;)V
  Code:
   Stack=3, Locals=3, Args_size=2
	aload_0
	checkcast	class scala/xml/parsing/MarkupParser
	invokeinterface	InterfaceMethod scala/xml/parsing/MarkupParser.eof:()Z
	ifne	l1 // aload_0
	aload_0
	checkcast	class scala/xml/parsing/MarkupParser
	aload_0
	checkcast	class scala/xml/parsing/MarkupParser
	invokeinterface	InterfaceMethod scala/xml/parsing/MarkupParser.curInput:()Lscala/io/Source;
	astore_2
	aload_0
	checkcast	class scala/xml/parsing/MarkupParser
	invokeinterface	InterfaceMethod scala/xml/parsing/MarkupParser.inpStack:()Lscala/collection/immutable/List;
	aload_2
	invokevirtual	Method scala/collection/immutable/List.$colon$colon:(Ljava/lang/Object;)Lscala/collection/immutable/List;
	invokeinterface	InterfaceMethod scala/xml/parsing/MarkupParser.inpStack_$eq:(Lscala/collection/immutable/List;)V
l1	aload_0
	checkcast	class scala/xml/parsing/MarkupParser
	aload_0
	aload_1
	invokevirtual	Method scala/xml/parsing/MarkupHandler.replacementText:(Ljava/lang/String;)Lscala/io/Source;
	invokeinterface	InterfaceMethod scala/xml/parsing/MarkupParser.curInput_$eq:(Lscala/io/Source;)V
	aload_0
	checkcast	class scala/xml/parsing/MarkupParser
	invokeinterface	InterfaceMethod scala/xml/parsing/MarkupParser.nextch:()C
	pop
	return
  Labels:
   	l1 = 44 // aload_0
  LocalVariableTable: 
   Start  Length  Slot  Name   Signature
   0      69      0    $this       Lscala/xml/parsing/MarkupHandler;
   0      69      1    entityName       Ljava/lang/String;


public static void reportValidationError(scala.xml.parsing.MarkupHandler, int, java.lang.String);
  Signature: (Lscala/xml/parsing/MarkupHandler;ILjava/lang/String;)V
  Code:
   Stack=3, Locals=3, Args_size=3
	aload_0
	checkcast	class scala/xml/parsing/MarkupParser
	iload_1
	aload_2
	invokeinterface	InterfaceMethod scala/xml/parsing/MarkupParser.reportSyntaxError:(ILjava/lang/String;)V
	return
  Labels:
  LocalVariableTable: 
   Start  Length  Slot  Name   Signature
   0      12      0    $this       Lscala/xml/parsing/MarkupHandler;
   0      12      1    pos       I
   0      12      2    str       Ljava/lang/String;


public static void reportSyntaxError(scala.xml.parsing.MarkupHandler, java.lang.String);
  Signature: (Lscala/xml/parsing/MarkupHandler;Ljava/lang/String;)V
  Code:
   Stack=3, Locals=2, Args_size=2
	aload_0
	checkcast	class scala/xml/parsing/MarkupParser
	aload_0
	checkcast	class scala/xml/parsing/MarkupParser
	invokeinterface	InterfaceMethod scala/xml/parsing/MarkupParser.pos:()I
	aload_1
	invokeinterface	InterfaceMethod scala/xml/parsing/MarkupParser.reportSyntaxError:(ILjava/lang/String;)V
	return
  Labels:
  LocalVariableTable: 
   Start  Length  Slot  Name   Signature
   0      20      0    $this       Lscala/xml/parsing/MarkupHandler;
   0      20      1    str       Ljava/lang/String;


public static void reportSyntaxError(scala.xml.parsing.MarkupHandler, int, java.lang.String);
  Signature: (Lscala/xml/parsing/MarkupHandler;ILjava/lang/String;)V
  Code:
   Stack=4, Locals=5, Args_size=3
	aload_0
	checkcast	class scala/xml/parsing/MarkupParser
	invokeinterface	InterfaceMethod scala/xml/parsing/MarkupParser.curInput:()Lscala/io/Source;
	astore_3
	aload_3
	invokevirtual	Method scala/io/Source.reportError$default$3:()Ljava/io/PrintStream;
	astore	4
	aload_3
	iload_1
	aload_2
	aload	4
	invokevirtual	Method scala/io/Source.reportError:(ILjava/lang/String;Ljava/io/PrintStream;)V
	return
  Labels:
  LocalVariableTable: 
   Start  Length  Slot  Name   Signature
   0      25      0    $this       Lscala/xml/parsing/MarkupHandler;
   0      25      1    pos       I
   0      25      2    str       Ljava/lang/String;
   10      14      3    qual$2       Lscala/io/Source;
   16      8      4    x$12       Ljava/io/PrintStream;


public static void notationDecl(scala.xml.parsing.MarkupHandler);
  Signature: (Lscala/xml/parsing/MarkupHandler;)V
  Code:
   Stack=4, Locals=6, Args_size=1
	aload_0
	checkcast	class scala/xml/parsing/MarkupParserCommon
	getstatic	Field scala/Predef$.MODULE$:Lscala/Predef$;
	ldc_w	String OTATION
	invokevirtual	Method scala/Predef$.wrapString:(Ljava/lang/String;)Lscala/collection/immutable/WrappedString;
	invokeinterface	InterfaceMethod scala/xml/parsing/MarkupParserCommon.xToken:(Lscala/collection/Seq;)V
	aload_0
	checkcast	class scala/xml/parsing/MarkupParserCommon
	invokeinterface	InterfaceMethod scala/xml/parsing/MarkupParserCommon.xSpace:()V
	aload_0
	checkcast	class scala/xml/parsing/MarkupParser
	invokeinterface	InterfaceMethod scala/xml/parsing/MarkupParser.xName:()Ljava/lang/String;
	astore_3
	aload_0
	checkcast	class scala/xml/parsing/MarkupParserCommon
	invokeinterface	InterfaceMethod scala/xml/parsing/MarkupParserCommon.xSpace:()V
	aload_0
	checkcast	class scala/xml/parsing/MarkupParser
	invokeinterface	InterfaceMethod scala/xml/parsing/MarkupParser.ch:()C
	ldc_w	int 83
	if_icmpne	l1 // aload_0
	aload_0
	checkcast	class scala/xml/parsing/MarkupParser
	invokeinterface	InterfaceMethod scala/xml/parsing/MarkupParser.externalID:()Lscala/xml/dtd/ExternalID;
	goto	l2 // astore
l1	aload_0
	checkcast	class scala/xml/parsing/MarkupParser
	invokeinterface	InterfaceMethod scala/xml/parsing/MarkupParser.ch:()C
	ldc_w	int 80
	if_icmpne	l3 // aload_0
	aload_0
	checkcast	class scala/xml/parsing/MarkupParser
	invokeinterface	InterfaceMethod scala/xml/parsing/MarkupParser.nextch:()C
	pop
	aload_0
	checkcast	class scala/xml/parsing/MarkupParserCommon
	getstatic	Field scala/Predef$.MODULE$:Lscala/Predef$;
	ldc_w	String UBLIC
	invokevirtual	Method scala/Predef$.wrapString:(Ljava/lang/String;)Lscala/collection/immutable/WrappedString;
	invokeinterface	InterfaceMethod scala/xml/parsing/MarkupParserCommon.xToken:(Lscala/collection/Seq;)V
	aload_0
	checkcast	class scala/xml/parsing/MarkupParserCommon
	invokeinterface	InterfaceMethod scala/xml/parsing/MarkupParserCommon.xSpace:()V
	aload_0
	checkcast	class scala/xml/parsing/MarkupParser
	invokeinterface	InterfaceMethod scala/xml/parsing/MarkupParser.pubidLiteral:()Ljava/lang/String;
	astore_1
	aload_0
	checkcast	class scala/xml/parsing/MarkupParserCommon
	invokeinterface	InterfaceMethod scala/xml/parsing/MarkupParserCommon.xSpaceOpt:()V
	aload_0
	checkcast	class scala/xml/parsing/MarkupParser
	invokeinterface	InterfaceMethod scala/xml/parsing/MarkupParser.ch:()C
	ldc	int 62
	if_icmpeq	l4 // aconst_null
	aload_0
	checkcast	class scala/xml/parsing/MarkupParser
	invokeinterface	InterfaceMethod scala/xml/parsing/MarkupParser.systemLiteral:()Ljava/lang/String;
	goto	l5 // astore_2
l4	aconst_null
l5	astore_2
	new	class scala/xml/dtd/PublicID
	dup
	aload_1
	aload_2
	invokespecial	Method scala/xml/dtd/PublicID."<init>":(Ljava/lang/String;Ljava/lang/String;)V
l2	astore	4
	aload_0
	checkcast	class scala/xml/parsing/MarkupParserCommon
	invokeinterface	InterfaceMethod scala/xml/parsing/MarkupParserCommon.xSpaceOpt:()V
	aload_0
	checkcast	class scala/xml/parsing/MarkupParserCommon
	ldc	int 62
	invokeinterface	InterfaceMethod scala/xml/parsing/MarkupParserCommon.xToken:(C)V
	aload_0
	checkcast	class scala/xml/parsing/MarkupParser
	invokeinterface	InterfaceMethod scala/xml/parsing/MarkupParser.scala$xml$parsing$MarkupParser$$handle:()Lscala/xml/parsing/MarkupHandler;
	aload_3
	aload	4
	invokevirtual	Method scala/xml/parsing/MarkupHandler.notationDecl:(Ljava/lang/String;Lscala/xml/dtd/ExternalID;)V
	return
l3	aload_0
	checkcast	class scala/xml/parsing/MarkupParser
	ldc_w	String PUBLIC or SYSTEM expected
	invokeinterface	InterfaceMethod scala/xml/parsing/MarkupParser.reportSyntaxError:(Ljava/lang/String;)V
	ldc_w	String died parsing notationdecl
	astore	5
	new	class java/lang/RuntimeException
	dup
	aload	5
	invokespecial	Method java/lang/RuntimeException."<init>":(Ljava/lang/String;)V
	athrow
  Labels:
   	l1 = 73 // aload_0
   	l4 = 170 // aconst_null
   	l5 = 171 // astore_2
   	l2 = 181 // astore
   	l3 = 219 // aload_0
  LocalVariableTable: 
   Start  Length  Slot  Name   Signature
   0      246      0    $this       Lscala/xml/parsing/MarkupHandler;
   135      46      1    pubID       Ljava/lang/String;
   172      9      2    sysID       Ljava/lang/String;
   37      181      3    notat       Ljava/lang/String;
   219      27      3    notat       Ljava/lang/String;
   183      35      4    extID       Lscala/xml/dtd/ExternalID;


public static void entityDecl(scala.xml.parsing.MarkupHandler);
  Signature: (Lscala/xml/parsing/MarkupHandler;)V
  Code:
   Stack=5, Locals=7, Args_size=1
	iconst_0
	istore_3
	aload_0
	checkcast	class scala/xml/parsing/MarkupParserCommon
	getstatic	Field scala/Predef$.MODULE$:Lscala/Predef$;
	ldc_w	String NTITY
	invokevirtual	Method scala/Predef$.wrapString:(Ljava/lang/String;)Lscala/collection/immutable/WrappedString;
	invokeinterface	InterfaceMethod scala/xml/parsing/MarkupParserCommon.xToken:(Lscala/collection/Seq;)V
	aload_0
	checkcast	class scala/xml/parsing/MarkupParserCommon
	invokeinterface	InterfaceMethod scala/xml/parsing/MarkupParserCommon.xSpace:()V
	ldc_w	int 37
	aload_0
	checkcast	class scala/xml/parsing/MarkupParser
	invokeinterface	InterfaceMethod scala/xml/parsing/MarkupParser.ch:()C
	if_icmpne	l1 // aload_0
	aload_0
	checkcast	class scala/xml/parsing/MarkupParser
	invokeinterface	InterfaceMethod scala/xml/parsing/MarkupParser.nextch:()C
	pop
	iconst_1
	istore_3
	aload_0
	checkcast	class scala/xml/parsing/MarkupParserCommon
	invokeinterface	InterfaceMethod scala/xml/parsing/MarkupParserCommon.xSpace:()V
l1	aload_0
	checkcast	class scala/xml/parsing/MarkupParser
	invokeinterface	InterfaceMethod scala/xml/parsing/MarkupParser.xName:()Ljava/lang/String;
	astore	4
	aload_0
	checkcast	class scala/xml/parsing/MarkupParserCommon
	invokeinterface	InterfaceMethod scala/xml/parsing/MarkupParserCommon.xSpace:()V
	aload_0
	checkcast	class scala/xml/parsing/MarkupParser
	invokeinterface	InterfaceMethod scala/xml/parsing/MarkupParser.ch:()C
	istore	6
	iload	6
	lookupswitch{ //4
		34: 409;
		39: 389;
		80: 176;
		83: 156;
		default: 140 }
	new	class scala/MatchError
	dup
	iload	6
	invokestatic	Method scala/runtime/BoxesRunTime.boxToCharacter:(C)Ljava/lang/Character;
	invokevirtual	Method java/lang/Object.toString:()Ljava/lang/String;
	invokespecial	Method scala/MatchError."<init>":(Ljava/lang/String;)V
	athrow
	iconst_1
	ifne	l2 // aload_0
	new	class scala/MatchError
	dup
	iload	6
	invokestatic	Method scala/runtime/BoxesRunTime.boxToCharacter:(C)Ljava/lang/Character;
	invokevirtual	Method java/lang/Object.toString:()Ljava/lang/String;
	invokespecial	Method scala/MatchError."<init>":(Ljava/lang/String;)V
	athrow
	iconst_1
	ifeq	l3 // new
l2	aload_0
	checkcast	class scala/xml/parsing/MarkupParser
	invokeinterface	InterfaceMethod scala/xml/parsing/MarkupParser.externalID:()Lscala/xml/dtd/ExternalID;
	astore_2
	iload_3
	ifeq	l4 // aload_0
	aload_0
	checkcast	class scala/xml/parsing/MarkupParserCommon
	invokeinterface	InterfaceMethod scala/xml/parsing/MarkupParserCommon.xSpaceOpt:()V
	aload_0
	checkcast	class scala/xml/parsing/MarkupParserCommon
	ldc	int 62
	invokeinterface	InterfaceMethod scala/xml/parsing/MarkupParserCommon.xToken:(C)V
	aload_0
	checkcast	class scala/xml/parsing/MarkupParser
	invokeinterface	InterfaceMethod scala/xml/parsing/MarkupParser.scala$xml$parsing$MarkupParser$$handle:()Lscala/xml/parsing/MarkupHandler;
	aload	4
	new	class scala/xml/dtd/ExtDef
	dup
	aload_2
	invokespecial	Method scala/xml/dtd/ExtDef."<init>":(Lscala/xml/dtd/ExternalID;)V
	invokevirtual	Method scala/xml/parsing/MarkupHandler.parameterEntityDecl:(Ljava/lang/String;Lscala/xml/dtd/EntityDef;)V
	goto	l5 // return
l4	aload_0
	checkcast	class scala/xml/parsing/MarkupParserCommon
	invokeinterface	InterfaceMethod scala/xml/parsing/MarkupParserCommon.xSpace:()V
	ldc	int 62
	aload_0
	checkcast	class scala/xml/parsing/MarkupParser
	invokeinterface	InterfaceMethod scala/xml/parsing/MarkupParser.ch:()C
	if_icmpeq	l6 // aload_0
	aload_0
	checkcast	class scala/xml/parsing/MarkupParserCommon
	getstatic	Field scala/Predef$.MODULE$:Lscala/Predef$;
	ldc_w	String NDATA
	invokevirtual	Method scala/Predef$.wrapString:(Ljava/lang/String;)Lscala/collection/immutable/WrappedString;
	invokeinterface	InterfaceMethod scala/xml/parsing/MarkupParserCommon.xToken:(Lscala/collection/Seq;)V
	aload_0
	checkcast	class scala/xml/parsing/MarkupParserCommon
	invokeinterface	InterfaceMethod scala/xml/parsing/MarkupParserCommon.xSpace:()V
	aload_0
	checkcast	class scala/xml/parsing/MarkupParser
	invokeinterface	InterfaceMethod scala/xml/parsing/MarkupParser.xName:()Ljava/lang/String;
	astore_1
	aload_0
	checkcast	class scala/xml/parsing/MarkupParserCommon
	invokeinterface	InterfaceMethod scala/xml/parsing/MarkupParserCommon.xSpaceOpt:()V
	aload_0
	checkcast	class scala/xml/parsing/MarkupParserCommon
	ldc	int 62
	invokeinterface	InterfaceMethod scala/xml/parsing/MarkupParserCommon.xToken:(C)V
	aload_0
	checkcast	class scala/xml/parsing/MarkupParser
	invokeinterface	InterfaceMethod scala/xml/parsing/MarkupParser.scala$xml$parsing$MarkupParser$$handle:()Lscala/xml/parsing/MarkupHandler;
	aload	4
	aload_2
	aload_1
	invokevirtual	Method scala/xml/parsing/MarkupHandler.unparsedEntityDecl:(Ljava/lang/String;Lscala/xml/dtd/ExternalID;Ljava/lang/String;)V
	goto	l5 // return
l6	aload_0
	checkcast	class scala/xml/parsing/MarkupParser
	invokeinterface	InterfaceMethod scala/xml/parsing/MarkupParser.nextch:()C
	pop
	aload_0
	checkcast	class scala/xml/parsing/MarkupParser
	invokeinterface	InterfaceMethod scala/xml/parsing/MarkupParser.scala$xml$parsing$MarkupParser$$handle:()Lscala/xml/parsing/MarkupHandler;
	aload	4
	new	class scala/xml/dtd/ExtDef
	dup
	aload_2
	invokespecial	Method scala/xml/dtd/ExtDef."<init>":(Lscala/xml/dtd/ExternalID;)V
	invokevirtual	Method scala/xml/parsing/MarkupHandler.parsedEntityDecl:(Ljava/lang/String;Lscala/xml/dtd/EntityDef;)V
	goto	l5 // return
l3	new	class scala/MatchError
	dup
	iload	6
	invokestatic	Method scala/runtime/BoxesRunTime.boxToCharacter:(C)Ljava/lang/Character;
	invokevirtual	Method java/lang/Object.toString:()Ljava/lang/String;
	invokespecial	Method scala/MatchError."<init>":(Ljava/lang/String;)V
	athrow
	iconst_1
	ifne	l7 // aload_0
	new	class scala/MatchError
	dup
	iload	6
	invokestatic	Method scala/runtime/BoxesRunTime.boxToCharacter:(C)Ljava/lang/Character;
	invokevirtual	Method java/lang/Object.toString:()Ljava/lang/String;
	invokespecial	Method scala/MatchError."<init>":(Ljava/lang/String;)V
	athrow
	iconst_1
	ifeq	l8 // new
l7	aload_0
	checkcast	class scala/xml/parsing/MarkupParser
	invokeinterface	InterfaceMethod scala/xml/parsing/MarkupParser.xEntityValue:()Ljava/lang/String;
	astore	5
	aload_0
	checkcast	class scala/xml/parsing/MarkupParserCommon
	invokeinterface	InterfaceMethod scala/xml/parsing/MarkupParserCommon.xSpaceOpt:()V
	aload_0
	checkcast	class scala/xml/parsing/MarkupParserCommon
	ldc	int 62
	invokeinterface	InterfaceMethod scala/xml/parsing/MarkupParserCommon.xToken:(C)V
	iload_3
	ifeq	l9 // aload_0
	aload_0
	checkcast	class scala/xml/parsing/MarkupParser
	invokeinterface	InterfaceMethod scala/xml/parsing/MarkupParser.scala$xml$parsing$MarkupParser$$handle:()Lscala/xml/parsing/MarkupHandler;
	aload	4
	new	class scala/xml/dtd/IntDef
	dup
	aload	5
	invokespecial	Method scala/xml/dtd/IntDef."<init>":(Ljava/lang/String;)V
	invokevirtual	Method scala/xml/parsing/MarkupHandler.parameterEntityDecl:(Ljava/lang/String;Lscala/xml/dtd/EntityDef;)V
	goto	l5 // return
l9	aload_0
	checkcast	class scala/xml/parsing/MarkupParser
	invokeinterface	InterfaceMethod scala/xml/parsing/MarkupParser.scala$xml$parsing$MarkupParser$$handle:()Lscala/xml/parsing/MarkupHandler;
	aload	4
	new	class scala/xml/dtd/IntDef
	dup
	aload	5
	invokespecial	Method scala/xml/dtd/IntDef."<init>":(Ljava/lang/String;)V
	invokevirtual	Method scala/xml/parsing/MarkupHandler.parsedEntityDecl:(Ljava/lang/String;Lscala/xml/dtd/EntityDef;)V
l5	return
l8	new	class scala/MatchError
	dup
	iload	6
	invokestatic	Method scala/runtime/BoxesRunTime.boxToCharacter:(C)Ljava/lang/Character;
	invokevirtual	Method java/lang/Object.toString:()Ljava/lang/String;
	invokespecial	Method scala/MatchError."<init>":(Ljava/lang/String;)V
	athrow
  Labels:
   	l1 = 65 // aload_0
   	l2 = 180 // aload_0
   	l4 = 239 // aload_0
   	l6 = 338 // aload_0
   	l3 = 373 // new
   	l7 = 413 // aload_0
   	l9 = 474 // aload_0
   	l5 = 497 // return
   	l8 = 498 // new
  LocalVariableTable: 
   Start  Length  Slot  Name   Signature
   0      514      0    $this       Lscala/xml/parsing/MarkupHandler;
   299      36      1    notat       Ljava/lang/String;
   190      183      2    extID       Lscala/xml/dtd/ExternalID;
   2      512      3    isParameterEntity       Z
   76      438      4    n       Ljava/lang/String;
   424      73      5    av       Ljava/lang/String;
   96      418      6    temp76       C


public static void attrDecl(scala.xml.parsing.MarkupHandler);
  Signature: (Lscala/xml/parsing/MarkupHandler;)V
  Code:
   Stack=6, Locals=15, Args_size=1
	aload_0
	checkcast	class scala/xml/parsing/MarkupParserCommon
	getstatic	Field scala/Predef$.MODULE$:Lscala/Predef$;
	ldc_w	String TTLIST
	invokevirtual	Method scala/Predef$.wrapString:(Ljava/lang/String;)Lscala/collection/immutable/WrappedString;
	invokeinterface	InterfaceMethod scala/xml/parsing/MarkupParserCommon.xToken:(Lscala/collection/Seq;)V
	aload_0
	checkcast	class scala/xml/parsing/MarkupParserCommon
	invokeinterface	InterfaceMethod scala/xml/parsing/MarkupParserCommon.xSpace:()V
	aload_0
	checkcast	class scala/xml/parsing/MarkupParser
	invokeinterface	InterfaceMethod scala/xml/parsing/MarkupParser.xName:()Ljava/lang/String;
	astore	13
	aload_0
	checkcast	class scala/xml/parsing/MarkupParserCommon
	invokeinterface	InterfaceMethod scala/xml/parsing/MarkupParserCommon.xSpace:()V
	getstatic	Field scala/collection/immutable/Nil$.MODULE$:Lscala/collection/immutable/Nil$;
	astore	14
l23	ldc	int 62
	aload_0
	checkcast	class scala/xml/parsing/MarkupParser
	invokeinterface	InterfaceMethod scala/xml/parsing/MarkupParser.ch:()C
	if_icmpeq	l1 // aload_0
	aload_0
	checkcast	class scala/xml/parsing/MarkupParser
	invokeinterface	InterfaceMethod scala/xml/parsing/MarkupParser.xName:()Ljava/lang/String;
	astore	7
	aload_0
	checkcast	class scala/xml/parsing/MarkupParserCommon
	invokeinterface	InterfaceMethod scala/xml/parsing/MarkupParserCommon.xSpace:()V
l5	ldc	int 34
	aload_0
	checkcast	class scala/xml/parsing/MarkupParser
	invokeinterface	InterfaceMethod scala/xml/parsing/MarkupParser.ch:()C
	if_icmpeq	l2 // aload_0
	ldc	int 39
	aload_0
	checkcast	class scala/xml/parsing/MarkupParser
	invokeinterface	InterfaceMethod scala/xml/parsing/MarkupParser.ch:()C
	if_icmpeq	l2 // aload_0
	ldc	int 35
	aload_0
	checkcast	class scala/xml/parsing/MarkupParser
	invokeinterface	InterfaceMethod scala/xml/parsing/MarkupParser.ch:()C
	if_icmpeq	l2 // aload_0
	ldc	int 60
	aload_0
	checkcast	class scala/xml/parsing/MarkupParser
	invokeinterface	InterfaceMethod scala/xml/parsing/MarkupParser.ch:()C
	if_icmpeq	l2 // aload_0
	aload_0
	checkcast	class scala/xml/parsing/TokenTests
	aload_0
	checkcast	class scala/xml/parsing/MarkupParser
	invokeinterface	InterfaceMethod scala/xml/parsing/MarkupParser.ch:()C
	invokeinterface	InterfaceMethod scala/xml/parsing/TokenTests.isSpace:(C)Z
	ifeq	l3 // aload_0
	getstatic	Field scala/runtime/BoxedUnit.UNIT:Lscala/runtime/BoxedUnit;
	goto	l4 // pop
l3	aload_0
	checkcast	class scala/xml/parsing/MarkupParser
	invokeinterface	InterfaceMethod scala/xml/parsing/MarkupParser.cbuf:()Lscala/collection/mutable/StringBuilder;
	aload_0
	checkcast	class scala/xml/parsing/MarkupParser
	invokeinterface	InterfaceMethod scala/xml/parsing/MarkupParser.ch:()C
	invokevirtual	Method scala/collection/mutable/StringBuilder.append:(C)Lscala/collection/mutable/StringBuilder;
l4	pop
	aload_0
	checkcast	class scala/xml/parsing/MarkupParser
	invokeinterface	InterfaceMethod scala/xml/parsing/MarkupParser.nextch:()C
	pop
	goto	l5 // ldc
l2	aload_0
	checkcast	class scala/xml/parsing/MarkupParser
	invokeinterface	InterfaceMethod scala/xml/parsing/MarkupParser.cbuf:()Lscala/collection/mutable/StringBuilder;
	invokevirtual	Method scala/collection/mutable/StringBuilder.toString:()Ljava/lang/String;
	astore	8
	aload_0
	checkcast	class scala/xml/parsing/MarkupParser
	invokeinterface	InterfaceMethod scala/xml/parsing/MarkupParser.cbuf:()Lscala/collection/mutable/StringBuilder;
	iconst_0
	istore_2
	astore_1
	aload_1
	iload_2
	invokevirtual	Method scala/collection/mutable/StringBuilder.setLength:(I)V
	aload_0
	checkcast	class scala/xml/parsing/MarkupParser
	invokeinterface	InterfaceMethod scala/xml/parsing/MarkupParser.ch:()C
	istore	12
	iload	12
	lookupswitch{ //3
		34: 555;
		35: 328;
		39: 308;
		default: 284 }
	iconst_1
	ifeq	l6 // new
	aconst_null
	goto	l7 // astore
l6	new	class scala/MatchError
	dup
	iload	12
	invokestatic	Method scala/runtime/BoxesRunTime.boxToCharacter:(C)Ljava/lang/Character;
	invokevirtual	Method java/lang/Object.toString:()Ljava/lang/String;
	invokespecial	Method scala/MatchError."<init>":(Ljava/lang/String;)V
	athrow
	iconst_1
	ifne	l8 // new
	new	class scala/MatchError
	dup
	iload	12
	invokestatic	Method scala/runtime/BoxesRunTime.boxToCharacter:(C)Ljava/lang/Character;
	invokevirtual	Method java/lang/Object.toString:()Ljava/lang/String;
	invokespecial	Method scala/MatchError."<init>":(Ljava/lang/String;)V
	athrow
	iconst_1
	ifeq	l9 // new
	aload_0
	checkcast	class scala/xml/parsing/MarkupParser
	invokeinterface	InterfaceMethod scala/xml/parsing/MarkupParser.nextch:()C
	pop
	aload_0
	checkcast	class scala/xml/parsing/MarkupParser
	invokeinterface	InterfaceMethod scala/xml/parsing/MarkupParser.xName:()Ljava/lang/String;
	astore	6
	aload	6
	ldc_w	String FIXED
	astore_3
	dup
	ifnonnull	l10 // aload_3
	pop
	aload_3
	ifnull	l11 // iconst_1
	goto	l12 // aload
l10	aload_3
	invokevirtual	Method java/lang/Object.equals:(Ljava/lang/Object;)Z
	ifeq	l12 // aload
l11	iconst_1
	ifeq	l13 // new
	aload_0
	checkcast	class scala/xml/parsing/MarkupParserCommon
	invokeinterface	InterfaceMethod scala/xml/parsing/MarkupParserCommon.xSpace:()V
	new	class scala/xml/dtd/DEFAULT
	dup
	iconst_1
	aload_0
	checkcast	class scala/xml/parsing/MarkupParser
	invokeinterface	InterfaceMethod scala/xml/parsing/MarkupParser.xAttributeValue:()Ljava/lang/String;
	invokespecial	Method scala/xml/dtd/DEFAULT."<init>":(ZLjava/lang/String;)V
	goto	l7 // astore
l13	new	class scala/MatchError
	dup
	aload	6
	invokevirtual	Method java/lang/String.toString:()Ljava/lang/String;
	invokespecial	Method scala/MatchError."<init>":(Ljava/lang/String;)V
	athrow
l12	aload	6
	ldc_w	String IMPLIED
	astore	4
	dup
	ifnonnull	l14 // aload
	pop
	aload	4
	ifnull	l15 // iconst_1
	goto	l16 // aload
l14	aload	4
	invokevirtual	Method java/lang/Object.equals:(Ljava/lang/Object;)Z
	ifeq	l16 // aload
l15	iconst_1
	ifeq	l17 // new
	getstatic	Field scala/xml/dtd/IMPLIED$.MODULE$:Lscala/xml/dtd/IMPLIED$;
	goto	l7 // astore
l17	new	class scala/MatchError
	dup
	aload	6
	invokevirtual	Method java/lang/String.toString:()Ljava/lang/String;
	invokespecial	Method scala/MatchError."<init>":(Ljava/lang/String;)V
	athrow
l16	aload	6
	ldc_w	String REQUIRED
	astore	5
	dup
	ifnonnull	l18 // aload
	pop
	aload	5
	ifnull	l19 // iconst_1
	goto	l20 // new
l18	aload	5
	invokevirtual	Method java/lang/Object.equals:(Ljava/lang/Object;)Z
	ifeq	l20 // new
l19	iconst_1
	ifeq	l21 // new
	getstatic	Field scala/xml/dtd/REQUIRED$.MODULE$:Lscala/xml/dtd/REQUIRED$;
	goto	l7 // astore
l21	new	class scala/MatchError
	dup
	aload	6
	invokevirtual	Method java/lang/String.toString:()Ljava/lang/String;
	invokespecial	Method scala/MatchError."<init>":(Ljava/lang/String;)V
	athrow
l20	new	class scala/MatchError
	dup
	aload	6
	invokevirtual	Method java/lang/String.toString:()Ljava/lang/String;
	invokespecial	Method scala/MatchError."<init>":(Ljava/lang/String;)V
	athrow
l9	new	class scala/MatchError
	dup
	iload	12
	invokestatic	Method scala/runtime/BoxesRunTime.boxToCharacter:(C)Ljava/lang/Character;
	invokevirtual	Method java/lang/Object.toString:()Ljava/lang/String;
	invokespecial	Method scala/MatchError."<init>":(Ljava/lang/String;)V
	athrow
	iconst_1
	ifeq	l22 // new
l8	new	class scala/xml/dtd/DEFAULT
	dup
	iconst_0
	aload_0
	checkcast	class scala/xml/parsing/MarkupParser
	invokeinterface	InterfaceMethod scala/xml/parsing/MarkupParser.xAttributeValue:()Ljava/lang/String;
	invokespecial	Method scala/xml/dtd/DEFAULT."<init>":(ZLjava/lang/String;)V
l7	astore	9
	aload_0
	checkcast	class scala/xml/parsing/MarkupParserCommon
	invokeinterface	InterfaceMethod scala/xml/parsing/MarkupParserCommon.xSpaceOpt:()V
	aload	14
	new	class scala/xml/dtd/AttrDecl
	dup
	aload	7
	aload	8
	aload	9
	invokespecial	Method scala/xml/dtd/AttrDecl."<init>":(Ljava/lang/String;Ljava/lang/String;Lscala/xml/dtd/DefaultDecl;)V
	invokevirtual	Method scala/collection/immutable/List.$colon$colon:(Ljava/lang/Object;)Lscala/collection/immutable/List;
	astore	14
	aload_0
	checkcast	class scala/xml/parsing/MarkupParser
	invokeinterface	InterfaceMethod scala/xml/parsing/MarkupParser.cbuf:()Lscala/collection/mutable/StringBuilder;
	iconst_0
	istore	11
	astore	10
	aload	10
	iload	11
	invokevirtual	Method scala/collection/mutable/StringBuilder.setLength:(I)V
	goto	l23 // ldc
l22	new	class scala/MatchError
	dup
	iload	12
	invokestatic	Method scala/runtime/BoxesRunTime.boxToCharacter:(C)Ljava/lang/Character;
	invokevirtual	Method java/lang/Object.toString:()Ljava/lang/String;
	invokespecial	Method scala/MatchError."<init>":(Ljava/lang/String;)V
	athrow
l1	aload_0
	checkcast	class scala/xml/parsing/MarkupParser
	invokeinterface	InterfaceMethod scala/xml/parsing/MarkupParser.nextch:()C
	pop
	aload_0
	checkcast	class scala/xml/parsing/MarkupParser
	invokeinterface	InterfaceMethod scala/xml/parsing/MarkupParser.scala$xml$parsing$MarkupParser$$handle:()Lscala/xml/parsing/MarkupHandler;
	aload	13
	aload	14
	invokevirtual	Method scala/collection/immutable/List.reverse:()Lscala/collection/immutable/List;
	invokevirtual	Method scala/xml/parsing/MarkupHandler.attListDecl:(Ljava/lang/String;Lscala/collection/immutable/List;)V
	return
  Labels:
   	l23 = 52 // ldc
   	l5 = 86 // ldc
   	l3 = 169 // aload_0
   	l4 = 190 // pop
   	l2 = 204 // aload_0
   	l6 = 292 // new
   	l10 = 371 // aload_3
   	l11 = 378 // iconst_1
   	l13 = 411 // new
   	l12 = 424 // aload
   	l14 = 444 // aload
   	l15 = 452 // iconst_1
   	l17 = 462 // new
   	l16 = 475 // aload
   	l18 = 495 // aload
   	l19 = 503 // iconst_1
   	l21 = 513 // new
   	l20 = 526 // new
   	l9 = 539 // new
   	l8 = 559 // new
   	l7 = 576 // astore
   	l22 = 631 // new
   	l1 = 647 // aload_0
  LocalVariableTable: 
   Start  Length  Slot  Name   Signature
   0      677      0    $this       Lscala/xml/parsing/MarkupHandler;
   353      186      6    temp71       Ljava/lang/String;
   77      551      7    aname       Ljava/lang/String;
   631      16      7    aname       Ljava/lang/String;
   218      410      8    atpe       Ljava/lang/String;
   631      16      8    atpe       Ljava/lang/String;
   578      50      9    defdecl       Lscala/xml/dtd/DefaultDecl;
   246      401      12    temp75       C
   38      638      13    n       Ljava/lang/String;
   52      624      14    attList       Lscala/collection/immutable/List;


public static void elementDecl(scala.xml.parsing.MarkupHandler);
  Signature: (Lscala/xml/parsing/MarkupHandler;)V
  Code:
   Stack=3, Locals=5, Args_size=1
	aload_0
	checkcast	class scala/xml/parsing/MarkupParserCommon
	getstatic	Field scala/Predef$.MODULE$:Lscala/Predef$;
	ldc_w	String EMENT
	invokevirtual	Method scala/Predef$.wrapString:(Ljava/lang/String;)Lscala/collection/immutable/WrappedString;
	invokeinterface	InterfaceMethod scala/xml/parsing/MarkupParserCommon.xToken:(Lscala/collection/Seq;)V
	aload_0
	checkcast	class scala/xml/parsing/MarkupParserCommon
	invokeinterface	InterfaceMethod scala/xml/parsing/MarkupParserCommon.xSpace:()V
	aload_0
	checkcast	class scala/xml/parsing/MarkupParser
	invokeinterface	InterfaceMethod scala/xml/parsing/MarkupParser.xName:()Ljava/lang/String;
	astore_1
	aload_0
	checkcast	class scala/xml/parsing/MarkupParserCommon
	invokeinterface	InterfaceMethod scala/xml/parsing/MarkupParserCommon.xSpace:()V
l2	ldc	int 62
	aload_0
	checkcast	class scala/xml/parsing/MarkupParser
	invokeinterface	InterfaceMethod scala/xml/parsing/MarkupParser.ch:()C
	if_icmpeq	l1 // aload_0
	aload_0
	checkcast	class scala/xml/parsing/MarkupParser
	aload_0
	checkcast	class scala/xml/parsing/MarkupParser
	invokeinterface	InterfaceMethod scala/xml/parsing/MarkupParser.ch:()C
	invokeinterface	InterfaceMethod scala/xml/parsing/MarkupParser.putChar:(C)Lscala/collection/mutable/StringBuilder;
	pop
	aload_0
	checkcast	class scala/xml/parsing/MarkupParser
	invokeinterface	InterfaceMethod scala/xml/parsing/MarkupParser.nextch:()C
	pop
	goto	l2 // ldc
l1	aload_0
	checkcast	class scala/xml/parsing/MarkupParser
	invokeinterface	InterfaceMethod scala/xml/parsing/MarkupParser.nextch:()C
	pop
	aload_0
	checkcast	class scala/xml/parsing/MarkupParser
	invokeinterface	InterfaceMethod scala/xml/parsing/MarkupParser.cbuf:()Lscala/collection/mutable/StringBuilder;
	invokevirtual	Method scala/collection/mutable/StringBuilder.toString:()Ljava/lang/String;
	astore_2
	aload_0
	checkcast	class scala/xml/parsing/MarkupParser
	invokeinterface	InterfaceMethod scala/xml/parsing/MarkupParser.cbuf:()Lscala/collection/mutable/StringBuilder;
	iconst_0
	istore_3
	astore	4
	aload	4
	iload_3
	invokevirtual	Method scala/collection/mutable/StringBuilder.setLength:(I)V
	aload_0
	checkcast	class scala/xml/parsing/MarkupParser
	invokeinterface	InterfaceMethod scala/xml/parsing/MarkupParser.scala$xml$parsing$MarkupParser$$handle:()Lscala/xml/parsing/MarkupHandler;
	aload_1
	aload_2
	invokevirtual	Method scala/xml/parsing/MarkupHandler.elemDecl:(Ljava/lang/String;Ljava/lang/String;)V
	return
  Labels:
   	l2 = 46 // ldc
   	l1 = 92 // aload_0
  LocalVariableTable: 
   Start  Length  Slot  Name   Signature
   0      149      0    $this       Lscala/xml/parsing/MarkupHandler;
   37      111      1    n       Ljava/lang/String;
   115      33      2    cmstr       Ljava/lang/String;


public static void intSubset(scala.xml.parsing.MarkupHandler);
  Signature: (Lscala/xml/parsing/MarkupHandler;)V
  Code:
   Stack=2, Locals=1, Args_size=1
	aload_0
	checkcast	class scala/xml/parsing/MarkupParserCommon
	invokeinterface	InterfaceMethod scala/xml/parsing/MarkupParserCommon.xSpace:()V
l2	ldc	int 93
	aload_0
	checkcast	class scala/xml/parsing/MarkupParser
	invokeinterface	InterfaceMethod scala/xml/parsing/MarkupParser.ch:()C
	if_icmpeq	l1 // return
	aload_0
	checkcast	class scala/xml/parsing/MarkupParser
	invokeinterface	InterfaceMethod scala/xml/parsing/MarkupParser.markupDecl:()V
	goto	l2 // ldc
l1	return
  Labels:
   	l2 = 9 // ldc
   	l1 = 35 // return
  LocalVariableTable: 
   Start  Length  Slot  Name   Signature
   0      36      0    $this       Lscala/xml/parsing/MarkupHandler;


public static void markupDecl(scala.xml.parsing.MarkupHandler);
  Signature: (Lscala/xml/parsing/MarkupHandler;)V
  Code:
   Stack=3, Locals=5, Args_size=1
	aload_0
	checkcast	class scala/xml/parsing/MarkupParser
	invokeinterface	InterfaceMethod scala/xml/parsing/MarkupParser.ch:()C
	istore	4
	iload	4
	ldc_w	int 37
	if_icmpne	l1 // iload
	iconst_1
	ifeq	l2 // new
	aload_0
	checkcast	class scala/xml/parsing/MarkupParser
	invokeinterface	InterfaceMethod scala/xml/parsing/MarkupParser.nextch:()C
	pop
	aload_0
	checkcast	class scala/xml/parsing/MarkupParser
	invokeinterface	InterfaceMethod scala/xml/parsing/MarkupParser.xName:()Ljava/lang/String;
	astore_1
	aload_0
	checkcast	class scala/xml/parsing/MarkupParserCommon
	ldc	int 59
	invokeinterface	InterfaceMethod scala/xml/parsing/MarkupParserCommon.xToken:(C)V
	aload_0
	invokevirtual	Method scala/xml/parsing/MarkupHandler.isValidating:()Z
	ifeq	l3 // aload_0
	aload_0
	checkcast	class scala/xml/parsing/MarkupParser
	aload_1
	invokeinterface	InterfaceMethod scala/xml/parsing/MarkupParser.push:(Ljava/lang/String;)V
	goto	l4 // return
l3	aload_0
	checkcast	class scala/xml/parsing/MarkupParser
	invokeinterface	InterfaceMethod scala/xml/parsing/MarkupParser.scala$xml$parsing$MarkupParser$$handle:()Lscala/xml/parsing/MarkupHandler;
	aload_1
	invokevirtual	Method scala/xml/parsing/MarkupHandler.peReference:(Ljava/lang/String;)V
	goto	l4 // return
l2	new	class scala/MatchError
	dup
	iload	4
	invokestatic	Method scala/runtime/BoxesRunTime.boxToCharacter:(C)Ljava/lang/Character;
	invokevirtual	Method java/lang/Object.toString:()Ljava/lang/String;
	invokespecial	Method scala/MatchError."<init>":(Ljava/lang/String;)V
	athrow
l1	iload	4
	ldc	int 60
	if_icmpne	l5 // aload_0
	iconst_1
	ifeq	l6 // new
	aload_0
	checkcast	class scala/xml/parsing/MarkupParser
	invokeinterface	InterfaceMethod scala/xml/parsing/MarkupParser.nextch:()C
	pop
	aload_0
	checkcast	class scala/xml/parsing/MarkupParser
	invokeinterface	InterfaceMethod scala/xml/parsing/MarkupParser.markupDecl1:()Ljava/lang/Object;
	pop
	goto	l4 // return
l6	new	class scala/MatchError
	dup
	iload	4
	invokestatic	Method scala/runtime/BoxesRunTime.boxToCharacter:(C)Ljava/lang/Character;
	invokevirtual	Method java/lang/Object.toString:()Ljava/lang/String;
	invokespecial	Method scala/MatchError."<init>":(Ljava/lang/String;)V
	athrow
l5	aload_0
	invokestatic	Method gd2$1:(Lscala/xml/parsing/MarkupHandler;)Z
	ifeq	l7 // iconst_1
	aload_0
	checkcast	class scala/xml/parsing/MarkupParserCommon
	invokeinterface	InterfaceMethod scala/xml/parsing/MarkupParserCommon.xSpace:()V
	goto	l4 // return
l7	iconst_1
	ifeq	l8 // new
	aload_0
	checkcast	class scala/xml/parsing/MarkupParser
	new	class scala/collection/mutable/StringBuilder
	dup
	invokespecial	Method scala/collection/mutable/StringBuilder."<init>":()V
	ldc_w	String markupdecl: unexpected character '
	invokevirtual	Method scala/collection/mutable/StringBuilder.append:(Ljava/lang/Object;)Lscala/collection/mutable/StringBuilder;
	aload_0
	checkcast	class scala/xml/parsing/MarkupParser
	invokeinterface	InterfaceMethod scala/xml/parsing/MarkupParser.ch:()C
	istore_2
	iload_2
	invokestatic	Method scala/runtime/BoxesRunTime.boxToCharacter:(C)Ljava/lang/Character;
	invokevirtual	Method scala/collection/mutable/StringBuilder.append:(Ljava/lang/Object;)Lscala/collection/mutable/StringBuilder;
	ldc_w	String ' #
	invokevirtual	Method scala/collection/mutable/StringBuilder.append:(Ljava/lang/Object;)Lscala/collection/mutable/StringBuilder;
	aload_0
	checkcast	class scala/xml/parsing/MarkupParser
	invokeinterface	InterfaceMethod scala/xml/parsing/MarkupParser.ch:()C
	istore_3
	iload_3
	invokestatic	Method scala/runtime/BoxesRunTime.boxToInteger:(I)Ljava/lang/Integer;
	invokevirtual	Method scala/collection/mutable/StringBuilder.append:(Ljava/lang/Object;)Lscala/collection/mutable/StringBuilder;
	invokevirtual	Method scala/collection/mutable/StringBuilder.toString:()Ljava/lang/String;
	invokeinterface	InterfaceMethod scala/xml/parsing/MarkupParser.reportSyntaxError:(Ljava/lang/String;)V
	aload_0
	checkcast	class scala/xml/parsing/MarkupParser
	invokeinterface	InterfaceMethod scala/xml/parsing/MarkupParser.nextch:()C
	pop
l4	return
l8	new	class scala/MatchError
	dup
	iload	4
	invokestatic	Method scala/runtime/BoxesRunTime.boxToCharacter:(C)Ljava/lang/Character;
	invokevirtual	Method java/lang/Object.toString:()Ljava/lang/String;
	invokespecial	Method scala/MatchError."<init>":(Ljava/lang/String;)V
	athrow
  Labels:
   	l3 = 74 // aload_0
   	l2 = 90 // new
   	l1 = 106 // iload
   	l6 = 140 // new
   	l5 = 156 // aload_0
   	l7 = 175 // iconst_1
   	l4 = 254 // return
   	l8 = 255 // new
  LocalVariableTable: 
   Start  Length  Slot  Name   Signature
   0      271      0    $this       Lscala/xml/parsing/MarkupHandler;
   43      47      1    ent       Ljava/lang/String;
   11      260      4    temp68       C


public static java.lang.Object markupDecl1(scala.xml.parsing.MarkupHandler);
  Signature: (Lscala/xml/parsing/MarkupHandler;)Ljava/lang/Object;
  Code:
   Stack=4, Locals=13, Args_size=1
	ldc_w	int 63
	aload_0
	checkcast	class scala/xml/parsing/MarkupParser
	invokeinterface	InterfaceMethod scala/xml/parsing/MarkupParser.ch:()C
	if_icmpne	l1 // aload_0
	aload_0
	checkcast	class scala/xml/parsing/MarkupParser
	invokeinterface	InterfaceMethod scala/xml/parsing/MarkupParser.nextch:()C
	pop
	aload_0
	checkcast	class scala/xml/parsing/MarkupParser
	invokeinterface	InterfaceMethod scala/xml/parsing/MarkupParser.xProcInstr:()Lscala/xml/NodeSeq;
	goto	l2 // areturn
l1	aload_0
	checkcast	class scala/xml/parsing/MarkupParserCommon
	ldc_w	int 33
	invokeinterface	InterfaceMethod scala/xml/parsing/MarkupParserCommon.xToken:(C)V
	aload_0
	checkcast	class scala/xml/parsing/MarkupParser
	invokeinterface	InterfaceMethod scala/xml/parsing/MarkupParser.ch:()C
	istore	12
	iload	12
	lookupswitch{ //5
		45: 962;
		65: 917;
		69: 832;
		78: 787;
		91: 132;
		default: 112 }
	iconst_1
	ifne	l3 // aload_0
	new	class scala/MatchError
	dup
	iload	12
	invokestatic	Method scala/runtime/BoxesRunTime.boxToCharacter:(C)Ljava/lang/Character;
	invokevirtual	Method java/lang/Object.toString:()Ljava/lang/String;
	invokespecial	Method scala/MatchError."<init>":(Ljava/lang/String;)V
	athrow
	aload_0
	invokestatic	Method gd1$1:(Lscala/xml/parsing/MarkupHandler;)Z
	ifeq	l4 // iconst_1
	aload_0
	checkcast	class scala/xml/parsing/MarkupParser
	invokeinterface	InterfaceMethod scala/xml/parsing/MarkupParser.nextch:()C
	pop
	aload_0
	checkcast	class scala/xml/parsing/MarkupParserCommon
	invokeinterface	InterfaceMethod scala/xml/parsing/MarkupParserCommon.xSpaceOpt:()V
	aload_0
	checkcast	class scala/xml/parsing/MarkupParser
	invokeinterface	InterfaceMethod scala/xml/parsing/MarkupParser.ch:()C
	istore	6
	iload	6
	lookupswitch{ //2
		37: 412;
		73: 212;
		default: 196 }
	new	class scala/MatchError
	dup
	iload	6
	invokestatic	Method scala/runtime/BoxesRunTime.boxToCharacter:(C)Ljava/lang/Character;
	invokevirtual	Method java/lang/Object.toString:()Ljava/lang/String;
	invokespecial	Method scala/MatchError."<init>":(Ljava/lang/String;)V
	athrow
	iconst_1
	ifeq	l5 // new
	aload_0
	checkcast	class scala/xml/parsing/MarkupParser
	invokeinterface	InterfaceMethod scala/xml/parsing/MarkupParser.nextch:()C
	pop
	aload_0
	checkcast	class scala/xml/parsing/MarkupParser
	invokeinterface	InterfaceMethod scala/xml/parsing/MarkupParser.ch:()C
	istore_1
	iload_1
	lookupswitch{ //2
		71: 333;
		78: 279;
		default: 264 }
	new	class scala/MatchError
	dup
	iload_1
	invokestatic	Method scala/runtime/BoxesRunTime.boxToCharacter:(C)Ljava/lang/Character;
	invokevirtual	Method java/lang/Object.toString:()Ljava/lang/String;
	invokespecial	Method scala/MatchError."<init>":(Ljava/lang/String;)V
	athrow
	iconst_1
	ifeq	l6 // new
	aload_0
	checkcast	class scala/xml/parsing/MarkupParser
	invokeinterface	InterfaceMethod scala/xml/parsing/MarkupParser.nextch:()C
	pop
	aload_0
	checkcast	class scala/xml/parsing/MarkupParserCommon
	getstatic	Field scala/Predef$.MODULE$:Lscala/Predef$;
	ldc_w	String NCLUDE
	invokevirtual	Method scala/Predef$.wrapString:(Ljava/lang/String;)Lscala/collection/immutable/WrappedString;
	invokeinterface	InterfaceMethod scala/xml/parsing/MarkupParserCommon.xToken:(Lscala/collection/Seq;)V
	aload_0
	invokestatic	Method doInclude$1:(Lscala/xml/parsing/MarkupHandler;)C
	goto	l7 // pop
l6	new	class scala/MatchError
	dup
	iload_1
	invokestatic	Method scala/runtime/BoxesRunTime.boxToCharacter:(C)Ljava/lang/Character;
	invokevirtual	Method java/lang/Object.toString:()Ljava/lang/String;
	invokespecial	Method scala/MatchError."<init>":(Ljava/lang/String;)V
	athrow
	iconst_1
	ifeq	l8 // new
	aload_0
	checkcast	class scala/xml/parsing/MarkupParser
	invokeinterface	InterfaceMethod scala/xml/parsing/MarkupParser.nextch:()C
	pop
	aload_0
	checkcast	class scala/xml/parsing/MarkupParserCommon
	getstatic	Field scala/Predef$.MODULE$:Lscala/Predef$;
	ldc_w	String NORE
	invokevirtual	Method scala/Predef$.wrapString:(Ljava/lang/String;)Lscala/collection/immutable/WrappedString;
	invokeinterface	InterfaceMethod scala/xml/parsing/MarkupParserCommon.xToken:(Lscala/collection/Seq;)V
	aload_0
	checkcast	class scala/xml/parsing/MarkupParserCommon
	invokeinterface	InterfaceMethod scala/xml/parsing/MarkupParserCommon.xSpaceOpt:()V
	aload_0
	invokestatic	Method doIgnore$1:(Lscala/xml/parsing/MarkupHandler;)C
	goto	l7 // pop
l8	new	class scala/MatchError
	dup
	iload_1
	invokestatic	Method scala/runtime/BoxesRunTime.boxToCharacter:(C)Ljava/lang/Character;
	invokevirtual	Method java/lang/Object.toString:()Ljava/lang/String;
	invokespecial	Method scala/MatchError."<init>":(Ljava/lang/String;)V
	athrow
l5	new	class scala/MatchError
	dup
	iload	6
	invokestatic	Method scala/runtime/BoxesRunTime.boxToCharacter:(C)Ljava/lang/Character;
	invokevirtual	Method java/lang/Object.toString:()Ljava/lang/String;
	invokespecial	Method scala/MatchError."<init>":(Ljava/lang/String;)V
	athrow
	iconst_1
	ifeq	l9 // new
	aload_0
	checkcast	class scala/xml/parsing/MarkupParser
	invokeinterface	InterfaceMethod scala/xml/parsing/MarkupParser.nextch:()C
	pop
	aload_0
	checkcast	class scala/xml/parsing/MarkupParser
	invokeinterface	InterfaceMethod scala/xml/parsing/MarkupParser.xName:()Ljava/lang/String;
	astore_2
	aload_0
	checkcast	class scala/xml/parsing/MarkupParserCommon
	ldc	int 59
	invokeinterface	InterfaceMethod scala/xml/parsing/MarkupParserCommon.xToken:(C)V
	aload_0
	checkcast	class scala/xml/parsing/MarkupParserCommon
	invokeinterface	InterfaceMethod scala/xml/parsing/MarkupParserCommon.xSpaceOpt:()V
	aload_0
	checkcast	class scala/xml/parsing/MarkupParser
	aload_2
	invokeinterface	InterfaceMethod scala/xml/parsing/MarkupParser.push:(Ljava/lang/String;)V
	aload_0
	checkcast	class scala/xml/parsing/MarkupParserCommon
	invokeinterface	InterfaceMethod scala/xml/parsing/MarkupParserCommon.xSpaceOpt:()V
	aload_0
	checkcast	class scala/xml/parsing/MarkupParser
	invokeinterface	InterfaceMethod scala/xml/parsing/MarkupParser.xName:()Ljava/lang/String;
	astore	5
	aload_0
	checkcast	class scala/xml/parsing/MarkupParserCommon
	invokeinterface	InterfaceMethod scala/xml/parsing/MarkupParserCommon.xSpaceOpt:()V
	aload	5
	ldc_w	String INCLUDE
	astore_3
	dup
	ifnonnull	l10 // aload_3
	pop
	aload_3
	ifnull	l11 // iconst_1
	goto	l12 // aload
l10	aload_3
	invokevirtual	Method java/lang/Object.equals:(Ljava/lang/Object;)Z
	ifeq	l12 // aload
l11	iconst_1
	ifeq	l13 // new
	aload_0
	invokestatic	Method doInclude$1:(Lscala/xml/parsing/MarkupHandler;)C
	goto	l7 // pop
l13	new	class scala/MatchError
	dup
	aload	5
	invokevirtual	Method java/lang/String.toString:()Ljava/lang/String;
	invokespecial	Method scala/MatchError."<init>":(Ljava/lang/String;)V
	athrow
l12	aload	5
	ldc_w	String IGNORE
	astore	4
	dup
	ifnonnull	l14 // aload
	pop
	aload	4
	ifnull	l15 // iconst_1
	goto	l16 // new
l14	aload	4
	invokevirtual	Method java/lang/Object.equals:(Ljava/lang/Object;)Z
	ifeq	l16 // new
l15	iconst_1
	ifeq	l17 // new
	aload_0
	invokestatic	Method doIgnore$1:(Lscala/xml/parsing/MarkupHandler;)C
l7	pop
	aload_0
	checkcast	class scala/xml/parsing/MarkupParserCommon
	ldc	int 93
	invokeinterface	InterfaceMethod scala/xml/parsing/MarkupParserCommon.xToken:(C)V
	aload_0
	checkcast	class scala/xml/parsing/MarkupParserCommon
	ldc	int 62
	invokeinterface	InterfaceMethod scala/xml/parsing/MarkupParserCommon.xToken:(C)V
	getstatic	Field scala/runtime/BoxedUnit.UNIT:Lscala/runtime/BoxedUnit;
	goto	l2 // areturn
l17	new	class scala/MatchError
	dup
	aload	5
	invokevirtual	Method java/lang/String.toString:()Ljava/lang/String;
	invokespecial	Method scala/MatchError."<init>":(Ljava/lang/String;)V
	athrow
l16	new	class scala/MatchError
	dup
	aload	5
	invokevirtual	Method java/lang/String.toString:()Ljava/lang/String;
	invokespecial	Method scala/MatchError."<init>":(Ljava/lang/String;)V
	athrow
l9	new	class scala/MatchError
	dup
	iload	6
	invokestatic	Method scala/runtime/BoxesRunTime.boxToCharacter:(C)Ljava/lang/Character;
	invokevirtual	Method java/lang/Object.toString:()Ljava/lang/String;
	invokespecial	Method scala/MatchError."<init>":(Ljava/lang/String;)V
	athrow
l4	iconst_1
	ifeq	l18 // new
l3	aload_0
	checkcast	class scala/xml/parsing/MarkupParser
	invokeinterface	InterfaceMethod scala/xml/parsing/MarkupParser.curInput:()Lscala/io/Source;
	astore	8
	aload_0
	checkcast	class scala/xml/parsing/MarkupParser
	invokeinterface	InterfaceMethod scala/xml/parsing/MarkupParser.pos:()I
	istore	9
	new	class scala/collection/mutable/StringBuilder
	dup
	invokespecial	Method scala/collection/mutable/StringBuilder."<init>":()V
	ldc_w	String unexpected character '
	invokevirtual	Method scala/collection/mutable/StringBuilder.append:(Ljava/lang/Object;)Lscala/collection/mutable/StringBuilder;
	aload_0
	checkcast	class scala/xml/parsing/MarkupParser
	invokeinterface	InterfaceMethod scala/xml/parsing/MarkupParser.ch:()C
	istore	7
	iload	7
	invokestatic	Method scala/runtime/BoxesRunTime.boxToCharacter:(C)Ljava/lang/Character;
	invokevirtual	Method scala/collection/mutable/StringBuilder.append:(Ljava/lang/Object;)Lscala/collection/mutable/StringBuilder;
	ldc_w	String ', expected some markupdecl
	invokevirtual	Method scala/collection/mutable/StringBuilder.append:(Ljava/lang/Object;)Lscala/collection/mutable/StringBuilder;
	invokevirtual	Method scala/collection/mutable/StringBuilder.toString:()Ljava/lang/String;
	astore	10
	aload	8
	invokevirtual	Method scala/io/Source.reportError$default$3:()Ljava/io/PrintStream;
	astore	11
	aload	8
	iload	9
	aload	10
	aload	11
	invokevirtual	Method scala/io/Source.reportError:(ILjava/lang/String;Ljava/io/PrintStream;)V
l20	aload_0
	checkcast	class scala/xml/parsing/MarkupParser
	invokeinterface	InterfaceMethod scala/xml/parsing/MarkupParser.ch:()C
	ldc	int 62
	if_icmpeq	l19 // getstatic
	aload_0
	checkcast	class scala/xml/parsing/MarkupParser
	invokeinterface	InterfaceMethod scala/xml/parsing/MarkupParser.nextch:()C
	pop
	goto	l20 // aload_0
l19	getstatic	Field scala/runtime/BoxedUnit.UNIT:Lscala/runtime/BoxedUnit;
	goto	l2 // areturn
l18	new	class scala/MatchError
	dup
	iload	12
	invokestatic	Method scala/runtime/BoxesRunTime.boxToCharacter:(C)Ljava/lang/Character;
	invokevirtual	Method java/lang/Object.toString:()Ljava/lang/String;
	invokespecial	Method scala/MatchError."<init>":(Ljava/lang/String;)V
	athrow
	iconst_1
	ifeq	l21 // new
	aload_0
	checkcast	class scala/xml/parsing/MarkupParser
	invokeinterface	InterfaceMethod scala/xml/parsing/MarkupParser.nextch:()C
	pop
	aload_0
	checkcast	class scala/xml/parsing/MarkupParser
	invokeinterface	InterfaceMethod scala/xml/parsing/MarkupParser.notationDecl:()V
	getstatic	Field scala/runtime/BoxedUnit.UNIT:Lscala/runtime/BoxedUnit;
	goto	l2 // areturn
l21	new	class scala/MatchError
	dup
	iload	12
	invokestatic	Method scala/runtime/BoxesRunTime.boxToCharacter:(C)Ljava/lang/Character;
	invokevirtual	Method java/lang/Object.toString:()Ljava/lang/String;
	invokespecial	Method scala/MatchError."<init>":(Ljava/lang/String;)V
	athrow
	iconst_1
	ifeq	l22 // new
	aload_0
	checkcast	class scala/xml/parsing/MarkupParser
	invokeinterface	InterfaceMethod scala/xml/parsing/MarkupParser.nextch:()C
	pop
	ldc_w	int 76
	aload_0
	checkcast	class scala/xml/parsing/MarkupParser
	invokeinterface	InterfaceMethod scala/xml/parsing/MarkupParser.ch:()C
	if_icmpne	l23 // aload_0
	aload_0
	checkcast	class scala/xml/parsing/MarkupParser
	invokeinterface	InterfaceMethod scala/xml/parsing/MarkupParser.nextch:()C
	pop
	aload_0
	checkcast	class scala/xml/parsing/MarkupParser
	invokeinterface	InterfaceMethod scala/xml/parsing/MarkupParser.elementDecl:()V
	getstatic	Field scala/runtime/BoxedUnit.UNIT:Lscala/runtime/BoxedUnit;
	goto	l2 // areturn
l23	aload_0
	checkcast	class scala/xml/parsing/MarkupParser
	invokeinterface	InterfaceMethod scala/xml/parsing/MarkupParser.entityDecl:()V
	getstatic	Field scala/runtime/BoxedUnit.UNIT:Lscala/runtime/BoxedUnit;
	goto	l2 // areturn
l22	new	class scala/MatchError
	dup
	iload	12
	invokestatic	Method scala/runtime/BoxesRunTime.boxToCharacter:(C)Ljava/lang/Character;
	invokevirtual	Method java/lang/Object.toString:()Ljava/lang/String;
	invokespecial	Method scala/MatchError."<init>":(Ljava/lang/String;)V
	athrow
	iconst_1
	ifeq	l24 // new
	aload_0
	checkcast	class scala/xml/parsing/MarkupParser
	invokeinterface	InterfaceMethod scala/xml/parsing/MarkupParser.nextch:()C
	pop
	aload_0
	checkcast	class scala/xml/parsing/MarkupParser
	invokeinterface	InterfaceMethod scala/xml/parsing/MarkupParser.attrDecl:()V
	getstatic	Field scala/runtime/BoxedUnit.UNIT:Lscala/runtime/BoxedUnit;
	goto	l2 // areturn
l24	new	class scala/MatchError
	dup
	iload	12
	invokestatic	Method scala/runtime/BoxesRunTime.boxToCharacter:(C)Ljava/lang/Character;
	invokevirtual	Method java/lang/Object.toString:()Ljava/lang/String;
	invokespecial	Method scala/MatchError."<init>":(Ljava/lang/String;)V
	athrow
	iconst_1
	ifeq	l25 // new
	aload_0
	checkcast	class scala/xml/parsing/MarkupParser
	invokeinterface	InterfaceMethod scala/xml/parsing/MarkupParser.xComment:()Lscala/xml/NodeSeq;
l2	areturn
l25	new	class scala/MatchError
	dup
	iload	12
	invokestatic	Method scala/runtime/BoxesRunTime.boxToCharacter:(C)Ljava/lang/Character;
	invokevirtual	Method java/lang/Object.toString:()Ljava/lang/String;
	invokespecial	Method scala/MatchError."<init>":(Ljava/lang/String;)V
	athrow
  Labels:
   	l1 = 37 // aload_0
   	l6 = 318 // new
   	l8 = 381 // new
   	l5 = 396 // new
   	l10 = 513 // aload_3
   	l11 = 520 // iconst_1
   	l13 = 531 // new
   	l12 = 544 // aload
   	l14 = 564 // aload
   	l15 = 572 // iconst_1
   	l7 = 580 // pop
   	l17 = 609 // new
   	l16 = 622 // new
   	l9 = 635 // new
   	l4 = 651 // iconst_1
   	l3 = 655 // aload_0
   	l20 = 738 // aload_0
   	l19 = 765 // getstatic
   	l18 = 771 // new
   	l21 = 816 // new
   	l23 = 886 // aload_0
   	l22 = 901 // new
   	l24 = 946 // new
   	l2 = 975 // areturn
   	l25 = 976 // new
  LocalVariableTable: 
   Start  Length  Slot  Name   Signature
   0      992      0    $this       Lscala/xml/parsing/MarkupHandler;
   236      160      1    temp65       C
   436      144      2    ent       Ljava/lang/String;
   609      26      2    ent       Ljava/lang/String;
   486      94      5    stmt       Ljava/lang/String;
   609      26      5    stmt       Ljava/lang/String;
   169      412      6    temp66       C
   609      42      6    temp66       C
   666      72      8    qual$1       Lscala/io/Source;
   677      61      9    x$7       I
   720      18      10    x$8       Ljava/lang/String;
   727      11      11    x$9       Ljava/io/PrintStream;
   60      915      12    temp67       C
   976      16      12    temp67       C


public static void extSubset(scala.xml.parsing.MarkupHandler);
  Signature: (Lscala/xml/parsing/MarkupHandler;)V
  Code:
   Stack=2, Locals=1, Args_size=1
	aload_0
	checkcast	class scala/xml/parsing/MarkupParser
	invokeinterface	InterfaceMethod scala/xml/parsing/MarkupParser.ch:()C
	ldc	int 60
	if_icmpne	l1 // getstatic
	aload_0
	checkcast	class scala/xml/parsing/MarkupParser
	invokeinterface	InterfaceMethod scala/xml/parsing/MarkupParser.nextch:()C
	pop
	aload_0
	checkcast	class scala/xml/parsing/MarkupParser
	invokeinterface	InterfaceMethod scala/xml/parsing/MarkupParser.ch:()C
	ldc_w	int 63
	if_icmpne	l2 // aload_0
	aload_0
	checkcast	class scala/xml/parsing/MarkupParser
	invokeinterface	InterfaceMethod scala/xml/parsing/MarkupParser.nextch:()C
	pop
	aload_0
	checkcast	class scala/xml/parsing/MarkupParser
	invokeinterface	InterfaceMethod scala/xml/parsing/MarkupParser.textDecl:()Lscala/Tuple2;
	pop
	getstatic	Field scala/runtime/BoxedUnit.UNIT:Lscala/runtime/BoxedUnit;
	goto	l3 // pop
l2	aload_0
	checkcast	class scala/xml/parsing/MarkupParser
	invokeinterface	InterfaceMethod scala/xml/parsing/MarkupParser.markupDecl1:()Ljava/lang/Object;
	goto	l3 // pop
l1	getstatic	Field scala/runtime/BoxedUnit.UNIT:Lscala/runtime/BoxedUnit;
l3	pop
l5	aload_0
	checkcast	class scala/xml/parsing/MarkupParser
	invokeinterface	InterfaceMethod scala/xml/parsing/MarkupParser.eof:()Z
	ifeq	l4 // aload_0
	return
l4	aload_0
	checkcast	class scala/xml/parsing/MarkupParser
	invokeinterface	InterfaceMethod scala/xml/parsing/MarkupParser.markupDecl:()V
	goto	l5 // aload_0
  Labels:
   	l2 = 65 // aload_0
   	l1 = 77 // getstatic
   	l3 = 80 // pop
   	l5 = 81 // aload_0
   	l4 = 94 // aload_0
  LocalVariableTable: 
   Start  Length  Slot  Name   Signature
   0      106      0    $this       Lscala/xml/parsing/MarkupHandler;


public static java.lang.String pubidLiteral(scala.xml.parsing.MarkupHandler);
  Signature: (Lscala/xml/parsing/MarkupHandler;)Ljava/lang/String;
  Code:
   Stack=3, Locals=6, Args_size=1
	aload_0
	checkcast	class scala/xml/parsing/MarkupParser
	invokeinterface	InterfaceMethod scala/xml/parsing/MarkupParser.ch:()C
	istore_1
	aload_0
	checkcast	class scala/xml/parsing/MarkupParser
	invokeinterface	InterfaceMethod scala/xml/parsing/MarkupParser.ch:()C
	ldc	int 39
	if_icmpeq	l1 // aload_0
	aload_0
	checkcast	class scala/xml/parsing/MarkupParser
	invokeinterface	InterfaceMethod scala/xml/parsing/MarkupParser.ch:()C
	ldc	int 34
	if_icmpeq	l1 // aload_0
	aload_0
	checkcast	class scala/xml/parsing/MarkupParser
	ldc_w	String quote ' or \" expected
	invokeinterface	InterfaceMethod scala/xml/parsing/MarkupParser.reportSyntaxError:(Ljava/lang/String;)V
l1	aload_0
	checkcast	class scala/xml/parsing/MarkupParser
	invokeinterface	InterfaceMethod scala/xml/parsing/MarkupParser.nextch:()C
	pop
l4	aload_0
	checkcast	class scala/xml/parsing/MarkupParser
	invokeinterface	InterfaceMethod scala/xml/parsing/MarkupParser.ch:()C
	iload_1
	if_icmpeq	l2 // aload_0
	aload_0
	checkcast	class scala/xml/parsing/MarkupParser
	aload_0
	checkcast	class scala/xml/parsing/MarkupParser
	invokeinterface	InterfaceMethod scala/xml/parsing/MarkupParser.ch:()C
	invokeinterface	InterfaceMethod scala/xml/parsing/MarkupParser.putChar:(C)Lscala/collection/mutable/StringBuilder;
	pop
	aload_0
	checkcast	class scala/xml/parsing/TokenTests
	aload_0
	checkcast	class scala/xml/parsing/MarkupParser
	invokeinterface	InterfaceMethod scala/xml/parsing/MarkupParser.ch:()C
	invokeinterface	InterfaceMethod scala/xml/parsing/TokenTests.isPubIDChar:(C)Z
	ifne	l3 // aload_0
	aload_0
	checkcast	class scala/xml/parsing/MarkupParser
	new	class scala/collection/mutable/StringBuilder
	dup
	invokespecial	Method scala/collection/mutable/StringBuilder."<init>":()V
	ldc_w	String char '
	invokevirtual	Method scala/collection/mutable/StringBuilder.append:(Ljava/lang/Object;)Lscala/collection/mutable/StringBuilder;
	aload_0
	checkcast	class scala/xml/parsing/MarkupParser
	invokeinterface	InterfaceMethod scala/xml/parsing/MarkupParser.ch:()C
	istore_2
	iload_2
	invokestatic	Method scala/runtime/BoxesRunTime.boxToCharacter:(C)Ljava/lang/Character;
	invokevirtual	Method scala/collection/mutable/StringBuilder.append:(Ljava/lang/Object;)Lscala/collection/mutable/StringBuilder;
	ldc_w	String ' is not allowed in public id
	invokevirtual	Method scala/collection/mutable/StringBuilder.append:(Ljava/lang/Object;)Lscala/collection/mutable/StringBuilder;
	invokevirtual	Method scala/collection/mutable/StringBuilder.toString:()Ljava/lang/String;
	invokeinterface	InterfaceMethod scala/xml/parsing/MarkupParser.reportSyntaxError:(Ljava/lang/String;)V
l3	aload_0
	checkcast	class scala/xml/parsing/MarkupParser
	invokeinterface	InterfaceMethod scala/xml/parsing/MarkupParser.nextch:()C
	pop
	goto	l4 // aload_0
l2	aload_0
	checkcast	class scala/xml/parsing/MarkupParser
	invokeinterface	InterfaceMethod scala/xml/parsing/MarkupParser.nextch:()C
	pop
	aload_0
	checkcast	class scala/xml/parsing/MarkupParser
	invokeinterface	InterfaceMethod scala/xml/parsing/MarkupParser.cbuf:()Lscala/collection/mutable/StringBuilder;
	invokevirtual	Method scala/collection/mutable/StringBuilder.toString:()Ljava/lang/String;
	astore_3
	aload_0
	checkcast	class scala/xml/parsing/MarkupParser
	invokeinterface	InterfaceMethod scala/xml/parsing/MarkupParser.cbuf:()Lscala/collection/mutable/StringBuilder;
	iconst_0
	istore	4
	astore	5
	aload	5
	iload	4
	invokevirtual	Method scala/collection/mutable/StringBuilder.setLength:(I)V
	aload_3
	areturn
  Labels:
   	l1 = 50 // aload_0
   	l4 = 60 // aload_0
   	l3 = 161 // aload_0
   	l2 = 174 // aload_0
  LocalVariableTable: 
   Start  Length  Slot  Name   Signature
   0      220      0    $this       Lscala/xml/parsing/MarkupHandler;
   10      209      1    endch       C
   197      22      3    str       Ljava/lang/String;


public static java.lang.String systemLiteral(scala.xml.parsing.MarkupHandler);
  Signature: (Lscala/xml/parsing/MarkupHandler;)Ljava/lang/String;
  Code:
   Stack=2, Locals=5, Args_size=1
	aload_0
	checkcast	class scala/xml/parsing/MarkupParser
	invokeinterface	InterfaceMethod scala/xml/parsing/MarkupParser.ch:()C
	istore_1
	aload_0
	checkcast	class scala/xml/parsing/MarkupParser
	invokeinterface	InterfaceMethod scala/xml/parsing/MarkupParser.ch:()C
	ldc	int 39
	if_icmpeq	l1 // aload_0
	aload_0
	checkcast	class scala/xml/parsing/MarkupParser
	invokeinterface	InterfaceMethod scala/xml/parsing/MarkupParser.ch:()C
	ldc	int 34
	if_icmpeq	l1 // aload_0
	aload_0
	checkcast	class scala/xml/parsing/MarkupParser
	ldc_w	String quote ' or \" expected
	invokeinterface	InterfaceMethod scala/xml/parsing/MarkupParser.reportSyntaxError:(Ljava/lang/String;)V
l1	aload_0
	checkcast	class scala/xml/parsing/MarkupParser
	invokeinterface	InterfaceMethod scala/xml/parsing/MarkupParser.nextch:()C
	pop
l3	aload_0
	checkcast	class scala/xml/parsing/MarkupParser
	invokeinterface	InterfaceMethod scala/xml/parsing/MarkupParser.ch:()C
	iload_1
	if_icmpeq	l2 // aload_0
	aload_0
	checkcast	class scala/xml/parsing/MarkupParser
	aload_0
	checkcast	class scala/xml/parsing/MarkupParser
	invokeinterface	InterfaceMethod scala/xml/parsing/MarkupParser.ch:()C
	invokeinterface	InterfaceMethod scala/xml/parsing/MarkupParser.putChar:(C)Lscala/collection/mutable/StringBuilder;
	pop
	aload_0
	checkcast	class scala/xml/parsing/MarkupParser
	invokeinterface	InterfaceMethod scala/xml/parsing/MarkupParser.nextch:()C
	pop
	goto	l3 // aload_0
l2	aload_0
	checkcast	class scala/xml/parsing/MarkupParser
	invokeinterface	InterfaceMethod scala/xml/parsing/MarkupParser.nextch:()C
	pop
	aload_0
	checkcast	class scala/xml/parsing/MarkupParser
	invokeinterface	InterfaceMethod scala/xml/parsing/MarkupParser.cbuf:()Lscala/collection/mutable/StringBuilder;
	invokevirtual	Method scala/collection/mutable/StringBuilder.toString:()Ljava/lang/String;
	astore_2
	aload_0
	checkcast	class scala/xml/parsing/MarkupParser
	invokeinterface	InterfaceMethod scala/xml/parsing/MarkupParser.cbuf:()Lscala/collection/mutable/StringBuilder;
	iconst_0
	istore_3
	astore	4
	aload	4
	iload_3
	invokevirtual	Method scala/collection/mutable/StringBuilder.setLength:(I)V
	aload_2
	areturn
  Labels:
   	l1 = 50 // aload_0
   	l3 = 60 // aload_0
   	l2 = 105 // aload_0
  LocalVariableTable: 
   Start  Length  Slot  Name   Signature
   0      149      0    $this       Lscala/xml/parsing/MarkupHandler;
   10      138      1    endch       C
   128      20      2    str       Ljava/lang/String;


public static java.lang.String xText(scala.xml.parsing.MarkupHandler);
  Signature: (Lscala/xml/parsing/MarkupHandler;)Ljava/lang/String;
  Code:
   Stack=2, Locals=5, Args_size=1
	iconst_0
	istore	4
l5	iload	4
	ifeq	l1 // aload_0
	aload_0
	checkcast	class scala/xml/parsing/MarkupParser
	invokeinterface	InterfaceMethod scala/xml/parsing/MarkupParser.cbuf:()Lscala/collection/mutable/StringBuilder;
	invokevirtual	Method scala/collection/mutable/StringBuilder.toString:()Ljava/lang/String;
	astore_3
	aload_0
	checkcast	class scala/xml/parsing/MarkupParser
	invokeinterface	InterfaceMethod scala/xml/parsing/MarkupParser.cbuf:()Lscala/collection/mutable/StringBuilder;
	iconst_0
	istore_2
	astore_1
	aload_1
	iload_2
	invokevirtual	Method scala/collection/mutable/StringBuilder.setLength:(I)V
	aload_3
	areturn
l1	aload_0
	checkcast	class scala/xml/parsing/MarkupParser
	aload_0
	checkcast	class scala/xml/parsing/MarkupParser
	invokeinterface	InterfaceMethod scala/xml/parsing/MarkupParser.ch:()C
	invokeinterface	InterfaceMethod scala/xml/parsing/MarkupParser.putChar:(C)Lscala/collection/mutable/StringBuilder;
	pop
	aload_0
	checkcast	class scala/xml/parsing/MarkupParser
	invokeinterface	InterfaceMethod scala/xml/parsing/MarkupParser.nextch:()C
	pop
	aload_0
	checkcast	class scala/xml/parsing/MarkupParser
	invokeinterface	InterfaceMethod scala/xml/parsing/MarkupParser.eof:()Z
	ifne	l2 // iconst_1
	aload_0
	checkcast	class scala/xml/parsing/MarkupParser
	invokeinterface	InterfaceMethod scala/xml/parsing/MarkupParser.ch:()C
	ldc	int 60
	if_icmpeq	l2 // iconst_1
	aload_0
	checkcast	class scala/xml/parsing/MarkupParser
	invokeinterface	InterfaceMethod scala/xml/parsing/MarkupParser.ch:()C
	ldc	int 38
	if_icmpne	l3 // iconst_0
l2	iconst_1
	goto	l4 // istore
l3	iconst_0
l4	istore	4
	goto	l5 // iload
  Labels:
   	l5 = 3 // iload
   	l1 = 40 // aload_0
   	l2 = 109 // iconst_1
   	l3 = 113 // iconst_0
   	l4 = 114 // istore
  LocalVariableTable: 
   Start  Length  Slot  Name   Signature
   0      119      0    $this       Lscala/xml/parsing/MarkupHandler;
   21      18      3    str       Ljava/lang/String;
   3      36      4    exit       Z
   40      79      4    exit       Z


public static scala.xml.NodeSeq xProcInstr(scala.xml.parsing.MarkupHandler);
  Signature: (Lscala/xml/parsing/MarkupHandler;)Lscala/xml/NodeSeq;
  Code:
   Stack=4, Locals=4, Args_size=1
	new	class scala/collection/mutable/StringBuilder
	dup
	invokespecial	Method scala/collection/mutable/StringBuilder."<init>":()V
	astore_3
	aload_0
	checkcast	class scala/xml/parsing/MarkupParser
	invokeinterface	InterfaceMethod scala/xml/parsing/MarkupParser.xName:()Ljava/lang/String;
	astore_2
	aload_0
	checkcast	class scala/xml/parsing/TokenTests
	aload_0
	checkcast	class scala/xml/parsing/MarkupParser
	invokeinterface	InterfaceMethod scala/xml/parsing/MarkupParser.ch:()C
	invokeinterface	InterfaceMethod scala/xml/parsing/TokenTests.isSpace:(C)Z
	ifeq	l1 // aload_0
	aload_0
	checkcast	class scala/xml/parsing/MarkupParserCommon
	invokeinterface	InterfaceMethod scala/xml/parsing/MarkupParserCommon.xSpace:()V
l5	aload_0
	checkcast	class scala/xml/parsing/MarkupParser
	invokeinterface	InterfaceMethod scala/xml/parsing/MarkupParser.ch:()C
	ldc_w	int 63
	if_icmpne	l2 // aload_3
	aload_3
	aload_0
	checkcast	class scala/xml/parsing/MarkupParser
	invokeinterface	InterfaceMethod scala/xml/parsing/MarkupParser.ch:()C
	invokevirtual	Method scala/collection/mutable/StringBuilder.append:(C)Lscala/collection/mutable/StringBuilder;
	pop
	aload_0
	checkcast	class scala/xml/parsing/MarkupParser
	invokeinterface	InterfaceMethod scala/xml/parsing/MarkupParser.nextch:()C
	pop
	aload_0
	checkcast	class scala/xml/parsing/MarkupParser
	invokeinterface	InterfaceMethod scala/xml/parsing/MarkupParser.ch:()C
	ldc	int 62
	if_icmpne	l3 // iconst_0
	iconst_1
	goto	l4 // ifeq
l3	iconst_0
l4	ifeq	l2 // aload_3
	aload_3
	invokevirtual	Method scala/collection/mutable/StringBuilder.length:()I
	iconst_1
	isub
	istore_1
	aload_3
	iload_1
	invokevirtual	Method scala/collection/mutable/StringBuilder.setLength:(I)V
	aload_0
	checkcast	class scala/xml/parsing/MarkupParser
	invokeinterface	InterfaceMethod scala/xml/parsing/MarkupParser.nextch:()C
	pop
	aload_0
	checkcast	class scala/xml/parsing/MarkupParser
	invokeinterface	InterfaceMethod scala/xml/parsing/MarkupParser.scala$xml$parsing$MarkupParser$$handle:()Lscala/xml/parsing/MarkupHandler;
	aload_0
	checkcast	class scala/xml/parsing/MarkupParser
	invokeinterface	InterfaceMethod scala/xml/parsing/MarkupParser.tmppos:()I
	aload_2
	aload_3
	invokevirtual	Method scala/collection/mutable/StringBuilder.toString:()Ljava/lang/String;
	invokevirtual	Method scala/xml/parsing/MarkupHandler.procInstr:(ILjava/lang/String;Ljava/lang/String;)Lscala/xml/NodeSeq;
	areturn
l2	aload_3
	aload_0
	checkcast	class scala/xml/parsing/MarkupParser
	invokeinterface	InterfaceMethod scala/xml/parsing/MarkupParser.ch:()C
	invokevirtual	Method scala/collection/mutable/StringBuilder.append:(C)Lscala/collection/mutable/StringBuilder;
	pop
	aload_0
	checkcast	class scala/xml/parsing/MarkupParser
	invokeinterface	InterfaceMethod scala/xml/parsing/MarkupParser.nextch:()C
	pop
	goto	l5 // aload_0
l1	aload_0
	checkcast	class scala/xml/parsing/MarkupParserCommon
	getstatic	Field scala/Predef$.MODULE$:Lscala/Predef$;
	ldc_w	String ?>
	invokevirtual	Method scala/Predef$.wrapString:(Ljava/lang/String;)Lscala/collection/immutable/WrappedString;
	invokeinterface	InterfaceMethod scala/xml/parsing/MarkupParserCommon.xToken:(Lscala/collection/Seq;)V
	aload_0
	checkcast	class scala/xml/parsing/MarkupParser
	invokeinterface	InterfaceMethod scala/xml/parsing/MarkupParser.scala$xml$parsing$MarkupParser$$handle:()Lscala/xml/parsing/MarkupHandler;
	aload_0
	checkcast	class scala/xml/parsing/MarkupParser
	invokeinterface	InterfaceMethod scala/xml/parsing/MarkupParser.tmppos:()I
	aload_2
	aload_3
	invokevirtual	Method scala/collection/mutable/StringBuilder.toString:()Ljava/lang/String;
	invokevirtual	Method scala/xml/parsing/MarkupHandler.procInstr:(ILjava/lang/String;Ljava/lang/String;)Lscala/xml/NodeSeq;
	areturn
  Labels:
   	l5 = 48 // aload_0
   	l3 = 105 // iconst_0
   	l4 = 106 // ifeq
   	l2 = 158 // aload_3
   	l1 = 185 // aload_0
  LocalVariableTable: 
   Start  Length  Slot  Name   Signature
   0      230      0    $this       Lscala/xml/parsing/MarkupHandler;
   18      211      2    n       Ljava/lang/String;
   8      221      3    sb       Lscala/collection/mutable/StringBuilder;


public static java.lang.String xName(scala.xml.parsing.MarkupHandler);
  Signature: (Lscala/xml/parsing/MarkupHandler;)Ljava/lang/String;
  Code:
   Stack=2, Locals=4, Args_size=1
	aload_0
	checkcast	class scala/xml/parsing/TokenTests
	aload_0
	checkcast	class scala/xml/parsing/MarkupParser
	invokeinterface	InterfaceMethod scala/xml/parsing/MarkupParser.ch:()C
	invokeinterface	InterfaceMethod scala/xml/parsing/TokenTests.isNameStart:(C)Z
	ifeq	l1 // aload_0
l3	aload_0
	checkcast	class scala/xml/parsing/TokenTests
	aload_0
	checkcast	class scala/xml/parsing/MarkupParser
	invokeinterface	InterfaceMethod scala/xml/parsing/MarkupParser.ch:()C
	invokeinterface	InterfaceMethod scala/xml/parsing/TokenTests.isNameChar:(C)Z
	ifeq	l2 // aload_0
	aload_0
	checkcast	class scala/xml/parsing/MarkupParser
	aload_0
	checkcast	class scala/xml/parsing/MarkupParser
	invokeinterface	InterfaceMethod scala/xml/parsing/MarkupParser.ch:()C
	invokeinterface	InterfaceMethod scala/xml/parsing/MarkupParser.putChar:(C)Lscala/collection/mutable/StringBuilder;
	pop
	aload_0
	checkcast	class scala/xml/parsing/MarkupParser
	invokeinterface	InterfaceMethod scala/xml/parsing/MarkupParser.nextch:()C
	pop
	goto	l3 // aload_0
l2	aload_0
	checkcast	class scala/xml/parsing/MarkupParser
	invokeinterface	InterfaceMethod scala/xml/parsing/MarkupParser.cbuf:()Lscala/collection/mutable/StringBuilder;
	invokevirtual	Method scala/collection/mutable/StringBuilder.toString:()Ljava/lang/String;
	invokevirtual	Method java/lang/String.intern:()Ljava/lang/String;
	astore_1
	aload_0
	checkcast	class scala/xml/parsing/MarkupParser
	invokeinterface	InterfaceMethod scala/xml/parsing/MarkupParser.cbuf:()Lscala/collection/mutable/StringBuilder;
	iconst_0
	istore_2
	astore_3
	aload_3
	iload_2
	invokevirtual	Method scala/collection/mutable/StringBuilder.setLength:(I)V
	aload_1
	goto	l4 // areturn
l1	aload_0
	checkcast	class scala/xml/parsing/MarkupParser
	ldc_w	String name expected
	invokeinterface	InterfaceMethod scala/xml/parsing/MarkupParser.reportSyntaxError:(Ljava/lang/String;)V
	ldc_w	String 
l4	areturn
  Labels:
   	l3 = 21 // aload_0
   	l2 = 74 // aload_0
   	l1 = 111 // aload_0
   	l4 = 126 // areturn
  LocalVariableTable: 
   Start  Length  Slot  Name   Signature
   0      127      0    $this       Lscala/xml/parsing/MarkupHandler;
   90      18      1    n       Ljava/lang/String;


public static scala.xml.NodeSeq element1(scala.xml.parsing.MarkupHandler, scala.xml.NamespaceBinding);
  Signature: (Lscala/xml/parsing/MarkupHandler;Lscala/xml/NamespaceBinding;)Lscala/xml/NodeSeq;
  Code:
   Stack=7, Locals=23, Args_size=2
	aload_0
	checkcast	class scala/xml/parsing/MarkupParser
	invokeinterface	InterfaceMethod scala/xml/parsing/MarkupParser.pos:()I
	istore	16
	aload_0
	checkcast	class scala/xml/parsing/MarkupParser
	aload_1
	invokeinterface	InterfaceMethod scala/xml/parsing/MarkupParser.xTag:(Lscala/xml/NamespaceBinding;)Lscala/Tuple3;
	astore	22
	aload	22
	ifnull	l1 // new
	aload	22
	invokevirtual	Method scala/Tuple3._1:()Ljava/lang/Object;
	checkcast	class java/lang/String
	astore_2
	aload	22
	invokevirtual	Method scala/Tuple3._2:()Ljava/lang/Object;
	checkcast	class scala/xml/MetaData
	astore_3
	aload	22
	invokevirtual	Method scala/Tuple3._3:()Ljava/lang/Object;
	checkcast	class scala/xml/NamespaceBinding
	astore	4
	iconst_1
	ifeq	l2 // new
	new	class scala/Tuple3
	dup
	aload_2
	aload_3
	aload	4
	invokespecial	Method scala/Tuple3."<init>":(Ljava/lang/Object;Ljava/lang/Object;Ljava/lang/Object;)V
	astore	5
	aload	5
	invokevirtual	Method scala/Tuple3._1:()Ljava/lang/Object;
	checkcast	class java/lang/String
	astore	11
	aload	5
	invokevirtual	Method scala/Tuple3._2:()Ljava/lang/Object;
	checkcast	class scala/xml/MetaData
	astore	13
	aload	5
	invokevirtual	Method scala/Tuple3._3:()Ljava/lang/Object;
	checkcast	class scala/xml/NamespaceBinding
	astore	14
	getstatic	Field scala/xml/Utility$.MODULE$:Lscala/xml/Utility$;
	aload	11
	invokevirtual	Method scala/xml/Utility$.prefix:(Ljava/lang/String;)Lscala/Option;
	astore	21
	aload	21
	instanceof	class scala/Some
	ifeq	l3 // iconst_1
	aload	21
	checkcast	class scala/Some
	astore	6
	aload	6
	getfield	Field scala/Some.x:Ljava/lang/Object;
	checkcast	class java/lang/String
	astore	7
	iconst_1
	ifeq	l4 // new
	new	class scala/Tuple2
	dup
	aload	7
	new	class scala/collection/immutable/StringOps
	dup
	aload	11
	invokespecial	Method scala/collection/immutable/StringOps."<init>":(Ljava/lang/String;)V
	aload	7
	invokevirtual	Method java/lang/String.length:()I
	iconst_1
	iadd
	invokeinterface	InterfaceMethod scala/collection/IndexedSeqLike.drop:(I)Ljava/lang/Object;
	invokespecial	Method scala/Tuple2."<init>":(Ljava/lang/Object;Ljava/lang/Object;)V
	goto	l5 // astore
l4	new	class scala/MatchError
	dup
	aload	21
	invokevirtual	Method scala/Option.toString:()Ljava/lang/String;
	invokespecial	Method scala/MatchError."<init>":(Ljava/lang/String;)V
	athrow
l3	iconst_1
	ifeq	l6 // new
	new	class scala/Tuple2
	dup
	aconst_null
	aload	11
	invokespecial	Method scala/Tuple2."<init>":(Ljava/lang/Object;Ljava/lang/Object;)V
l5	astore	20
	aload	20
	ifnull	l7 // new
	aload	20
	invokevirtual	Method scala/Tuple2._1:()Ljava/lang/Object;
	checkcast	class java/lang/String
	astore	8
	aload	20
	invokevirtual	Method scala/Tuple2._2:()Ljava/lang/Object;
	checkcast	class java/lang/String
	astore	9
	iconst_1
	ifeq	l8 // new
	new	class scala/Tuple2
	dup
	aload	8
	aload	9
	invokespecial	Method scala/Tuple2."<init>":(Ljava/lang/Object;Ljava/lang/Object;)V
	astore	10
	aload	10
	invokevirtual	Method scala/Tuple2._1:()Ljava/lang/Object;
	checkcast	class java/lang/String
	astore	17
	aload	10
	invokevirtual	Method scala/Tuple2._2:()Ljava/lang/Object;
	checkcast	class java/lang/String
	astore	18
	aload_0
	checkcast	class scala/xml/parsing/MarkupParser
	invokeinterface	InterfaceMethod scala/xml/parsing/MarkupParser.ch:()C
	ldc_w	int 47
	if_icmpne	l9 // aload_0
	aload_0
	checkcast	class scala/xml/parsing/MarkupParserCommon
	getstatic	Field scala/Predef$.MODULE$:Lscala/Predef$;
	ldc_w	String />
	invokevirtual	Method scala/Predef$.wrapString:(Ljava/lang/String;)Lscala/collection/immutable/WrappedString;
	invokeinterface	InterfaceMethod scala/xml/parsing/MarkupParserCommon.xToken:(Lscala/collection/Seq;)V
	aload_0
	checkcast	class scala/xml/parsing/MarkupParser
	invokeinterface	InterfaceMethod scala/xml/parsing/MarkupParser.scala$xml$parsing$MarkupParser$$handle:()Lscala/xml/parsing/MarkupHandler;
	iload	16
	aload	17
	aload	18
	aload	13
	aload	14
	invokevirtual	Method scala/xml/parsing/MarkupHandler.elemStart:(ILjava/lang/String;Ljava/lang/String;Lscala/xml/MetaData;Lscala/xml/NamespaceBinding;)V
	getstatic	Field scala/xml/NodeSeq$.MODULE$:Lscala/xml/NodeSeq$;
	invokevirtual	Method scala/xml/NodeSeq$.Empty:()Lscala/xml/NodeSeq;
	goto	l10 // astore
l9	aload_0
	checkcast	class scala/xml/parsing/MarkupParserCommon
	ldc	int 62
	invokeinterface	InterfaceMethod scala/xml/parsing/MarkupParserCommon.xToken:(C)V
	aload_0
	checkcast	class scala/xml/parsing/MarkupParser
	invokeinterface	InterfaceMethod scala/xml/parsing/MarkupParser.scala$xml$parsing$MarkupParser$$handle:()Lscala/xml/parsing/MarkupHandler;
	iload	16
	aload	17
	aload	18
	aload	13
	aload	14
	invokevirtual	Method scala/xml/parsing/MarkupHandler.elemStart:(ILjava/lang/String;Ljava/lang/String;Lscala/xml/MetaData;Lscala/xml/NamespaceBinding;)V
	aload_0
	checkcast	class scala/xml/parsing/MarkupParser
	aload	14
	invokeinterface	InterfaceMethod scala/xml/parsing/MarkupParser.content:(Lscala/xml/NamespaceBinding;)Lscala/xml/NodeSeq;
	astore	12
	aload_0
	checkcast	class scala/xml/parsing/MarkupParser
	aload	11
	invokeinterface	InterfaceMethod scala/xml/parsing/MarkupParser.xEndTag:(Ljava/lang/String;)V
	aload	12
l10	astore	15
	aload_0
	checkcast	class scala/xml/parsing/MarkupParser
	invokeinterface	InterfaceMethod scala/xml/parsing/MarkupParser.scala$xml$parsing$MarkupParser$$handle:()Lscala/xml/parsing/MarkupHandler;
	iload	16
	aload	17
	aload	18
	aload	13
	aload	14
	aload	15
	invokevirtual	Method scala/xml/parsing/MarkupHandler.elem:(ILjava/lang/String;Ljava/lang/String;Lscala/xml/MetaData;Lscala/xml/NamespaceBinding;Lscala/xml/NodeSeq;)Lscala/xml/NodeSeq;
	astore	19
	aload_0
	checkcast	class scala/xml/parsing/MarkupParser
	invokeinterface	InterfaceMethod scala/xml/parsing/MarkupParser.scala$xml$parsing$MarkupParser$$handle:()Lscala/xml/parsing/MarkupHandler;
	iload	16
	aload	17
	aload	18
	invokevirtual	Method scala/xml/parsing/MarkupHandler.elemEnd:(ILjava/lang/String;Ljava/lang/String;)V
	aload	19
	areturn
l8	new	class scala/MatchError
	dup
	aload	20
	invokevirtual	Method scala/Tuple2.toString:()Ljava/lang/String;
	invokespecial	Method scala/MatchError."<init>":(Ljava/lang/String;)V
	athrow
l7	new	class scala/MatchError
	dup
	aload	20
	invokevirtual	Method scala/Tuple2.toString:()Ljava/lang/String;
	invokespecial	Method scala/MatchError."<init>":(Ljava/lang/String;)V
	athrow
l6	new	class scala/MatchError
	dup
	aload	21
	invokevirtual	Method scala/Option.toString:()Ljava/lang/String;
	invokespecial	Method scala/MatchError."<init>":(Ljava/lang/String;)V
	athrow
l2	new	class scala/MatchError
	dup
	aload	22
	invokevirtual	Method scala/Tuple3.toString:()Ljava/lang/String;
	invokespecial	Method scala/MatchError."<init>":(Ljava/lang/String;)V
	athrow
l1	new	class scala/MatchError
	dup
	aload	22
	invokevirtual	Method scala/Tuple3.toString:()Ljava/lang/String;
	invokespecial	Method scala/MatchError."<init>":(Ljava/lang/String;)V
	athrow
  Labels:
   	l4 = 175 // new
   	l3 = 188 // iconst_1
   	l5 = 202 // astore
   	l9 = 330 // aload_0
   	l10 = 389 // astore
   	l8 = 438 // new
   	l7 = 451 // new
   	l6 = 464 // new
   	l2 = 477 // new
   	l1 = 490 // new
  LocalVariableTable: 
   Start  Length  Slot  Name   Signature
   0      503      0    $this       Lscala/xml/parsing/MarkupHandler;
   0      503      1    pscope       Lscala/xml/NamespaceBinding;
   37      84      2    temp53       Ljava/lang/String;
   477      13      2    temp53       Ljava/lang/String;
   46      75      3    temp54       Lscala/xml/MetaData;
   477      13      3    temp54       Lscala/xml/MetaData;
   56      65      4    temp55       Lscala/xml/NamespaceBinding;
   477      13      4    temp55       Lscala/xml/NamespaceBinding;
   128      60      6    temp57       Lscala/Some;
   138      50      7    temp58       Ljava/lang/String;
   219      62      8    temp60       Ljava/lang/String;
   438      13      8    temp60       Ljava/lang/String;
   229      52      9    temp61       Ljava/lang/String;
   438      13      9    temp61       Ljava/lang/String;
   83      354      11    qname       Ljava/lang/String;
   438      39      11    qname       Ljava/lang/String;
   376      13      12    tmp       Lscala/xml/NodeSeq;
   93      344      13    aMap       Lscala/xml/MetaData;
   438      39      13    aMap       Lscala/xml/MetaData;
   103      334      14    scope       Lscala/xml/NamespaceBinding;
   438      39      14    scope       Lscala/xml/NamespaceBinding;
   391      46      15    ts       Lscala/xml/NodeSeq;
   11      426      16    pos       I
   438      65      16    pos       I
   256      181      17    pre       Ljava/lang/String;
   266      171      18    local       Ljava/lang/String;
   417      20      19    res       Lscala/xml/NodeSeq;
   204      77      20    temp59       Lscala/Tuple2;
   438      26      20    temp59       Lscala/Tuple2;
   113      96      21    temp56       Lscala/Option;
   464      13      21    temp56       Lscala/Option;
   23      98      22    temp52       Lscala/Tuple3;
   477      26      22    temp52       Lscala/Tuple3;


public static scala.xml.NodeSeq element(scala.xml.parsing.MarkupHandler, scala.xml.NamespaceBinding);
  Signature: (Lscala/xml/parsing/MarkupHandler;Lscala/xml/NamespaceBinding;)Lscala/xml/NodeSeq;
  Code:
   Stack=2, Locals=2, Args_size=2
	aload_0
	checkcast	class scala/xml/parsing/MarkupParserCommon
	ldc	int 60
	invokeinterface	InterfaceMethod scala/xml/parsing/MarkupParserCommon.xToken:(C)V
	aload_0
	checkcast	class scala/xml/parsing/MarkupParser
	aload_1
	invokeinterface	InterfaceMethod scala/xml/parsing/MarkupParser.element1:(Lscala/xml/NamespaceBinding;)Lscala/xml/NodeSeq;
	areturn
  Labels:
  LocalVariableTable: 
   Start  Length  Slot  Name   Signature
   0      22      0    $this       Lscala/xml/parsing/MarkupHandler;
   0      22      1    pscope       Lscala/xml/NamespaceBinding;


public static void parseDTD(scala.xml.parsing.MarkupHandler);
  Signature: (Lscala/xml/parsing/MarkupHandler;)V
  Code:
   Stack=5, Locals=3, Args_size=1
	new	class scala/runtime/ObjectRef
	dup
	aconst_null
	invokespecial	Method scala/runtime/ObjectRef."<init>":(Ljava/lang/Object;)V
	astore_1
	aload_0
	checkcast	class scala/xml/parsing/MarkupParser
	invokeinterface	InterfaceMethod scala/xml/parsing/MarkupParser.dtd:()Lscala/xml/dtd/DTD;
	ifnull	l1 // aload_0
	aload_0
	checkcast	class scala/xml/parsing/MarkupParser
	ldc_w	String unexpected character (DOCTYPE already defined
	invokeinterface	InterfaceMethod scala/xml/parsing/MarkupParser.reportSyntaxError:(Ljava/lang/String;)V
l1	aload_0
	checkcast	class scala/xml/parsing/MarkupParserCommon
	getstatic	Field scala/Predef$.MODULE$:Lscala/Predef$;
	ldc_w	String DOCTYPE
	invokevirtual	Method scala/Predef$.wrapString:(Ljava/lang/String;)Lscala/collection/immutable/WrappedString;
	invokeinterface	InterfaceMethod scala/xml/parsing/MarkupParserCommon.xToken:(Lscala/collection/Seq;)V
	aload_0
	checkcast	class scala/xml/parsing/MarkupParserCommon
	invokeinterface	InterfaceMethod scala/xml/parsing/MarkupParserCommon.xSpace:()V
	aload_0
	checkcast	class scala/xml/parsing/MarkupParser
	invokeinterface	InterfaceMethod scala/xml/parsing/MarkupParser.xName:()Ljava/lang/String;
	astore_2
	aload_0
	checkcast	class scala/xml/parsing/MarkupParserCommon
	invokeinterface	InterfaceMethod scala/xml/parsing/MarkupParserCommon.xSpace:()V
	ldc_w	int 83
	aload_0
	checkcast	class scala/xml/parsing/MarkupParser
	invokeinterface	InterfaceMethod scala/xml/parsing/MarkupParser.ch:()C
	if_icmpeq	l2 // aload_1
	ldc_w	int 80
	aload_0
	checkcast	class scala/xml/parsing/MarkupParser
	invokeinterface	InterfaceMethod scala/xml/parsing/MarkupParser.ch:()C
	if_icmpne	l3 // aload_1
l2	aload_1
	aload_0
	checkcast	class scala/xml/parsing/MarkupParser
	invokeinterface	InterfaceMethod scala/xml/parsing/MarkupParser.externalID:()Lscala/xml/dtd/ExternalID;
	putfield	Field scala/runtime/ObjectRef.elem:Ljava/lang/Object;
	aload_0
	checkcast	class scala/xml/parsing/MarkupParserCommon
	invokeinterface	InterfaceMethod scala/xml/parsing/MarkupParserCommon.xSpaceOpt:()V
l3	aload_1
	getfield	Field scala/runtime/ObjectRef.elem:Ljava/lang/Object;
	checkcast	class scala/xml/dtd/ExternalID
	ifnull	l4 // ldc
	aload_0
	invokevirtual	Method scala/xml/parsing/MarkupHandler.isValidating:()Z
	ifeq	l4 // ldc
	aload_0
	checkcast	class scala/xml/parsing/MarkupParser
	aload_1
	getfield	Field scala/runtime/ObjectRef.elem:Ljava/lang/Object;
	checkcast	class scala/xml/dtd/ExternalID
	invokevirtual	Method scala/xml/dtd/ExternalID.systemId:()Ljava/lang/String;
	invokeinterface	InterfaceMethod scala/xml/parsing/MarkupParser.pushExternal:(Ljava/lang/String;)V
	aload_0
	checkcast	class scala/xml/parsing/MarkupParser
	aload_0
	checkcast	class scala/xml/parsing/MarkupParser
	invokeinterface	InterfaceMethod scala/xml/parsing/MarkupParser.inpStack:()Lscala/collection/immutable/List;
	invokeinterface	InterfaceMethod scala/collection/LinearSeqLike.length:()I
	invokeinterface	InterfaceMethod scala/xml/parsing/MarkupParser.extIndex_$eq:(I)V
	aload_0
	checkcast	class scala/xml/parsing/MarkupParser
	invokeinterface	InterfaceMethod scala/xml/parsing/MarkupParser.extSubset:()V
	aload_0
	checkcast	class scala/xml/parsing/MarkupParser
	invokeinterface	InterfaceMethod scala/xml/parsing/MarkupParser.pop:()V
	aload_0
	checkcast	class scala/xml/parsing/MarkupParser
	iconst_m1
	invokeinterface	InterfaceMethod scala/xml/parsing/MarkupParser.extIndex_$eq:(I)V
l4	ldc	int 91
	aload_0
	checkcast	class scala/xml/parsing/MarkupParser
	invokeinterface	InterfaceMethod scala/xml/parsing/MarkupParser.ch:()C
	if_icmpne	l5 // aload_0
	aload_0
	checkcast	class scala/xml/parsing/MarkupParser
	invokeinterface	InterfaceMethod scala/xml/parsing/MarkupParser.nextch:()C
	pop
	aload_0
	checkcast	class scala/xml/parsing/MarkupParser
	invokeinterface	InterfaceMethod scala/xml/parsing/MarkupParser.intSubset:()V
	aload_0
	checkcast	class scala/xml/parsing/MarkupParserCommon
	ldc	int 93
	invokeinterface	InterfaceMethod scala/xml/parsing/MarkupParserCommon.xToken:(C)V
	aload_0
	checkcast	class scala/xml/parsing/MarkupParserCommon
	invokeinterface	InterfaceMethod scala/xml/parsing/MarkupParserCommon.xSpaceOpt:()V
l5	aload_0
	checkcast	class scala/xml/parsing/MarkupParserCommon
	ldc	int 62
	invokeinterface	InterfaceMethod scala/xml/parsing/MarkupParserCommon.xToken:(C)V
	aload_0
	checkcast	class scala/xml/parsing/MarkupParser
	new	class scala/xml/parsing/MarkupParser$$anon$2
	dup
	aload_0
	aload_1
	invokespecial	Method scala/xml/parsing/MarkupParser$$anon$2."<init>":(Lscala/xml/parsing/MarkupHandler;Lscala/runtime/ObjectRef;)V
	invokeinterface	InterfaceMethod scala/xml/parsing/MarkupParser.dtd_$eq:(Lscala/xml/dtd/DTD;)V
	aload_0
	checkcast	class scala/xml/parsing/MarkupParser
	invokeinterface	InterfaceMethod scala/xml/parsing/MarkupParser.doc:()Lscala/xml/Document;
	ifnull	l6 // aload_0
	aload_0
	checkcast	class scala/xml/parsing/MarkupParser
	invokeinterface	InterfaceMethod scala/xml/parsing/MarkupParser.doc:()Lscala/xml/Document;
	aload_0
	checkcast	class scala/xml/parsing/MarkupParser
	invokeinterface	InterfaceMethod scala/xml/parsing/MarkupParser.dtd:()Lscala/xml/dtd/DTD;
	invokevirtual	Method scala/xml/Document.dtd_$eq:(Lscala/xml/dtd/DTD;)V
l6	aload_0
	checkcast	class scala/xml/parsing/MarkupParser
	invokeinterface	InterfaceMethod scala/xml/parsing/MarkupParser.scala$xml$parsing$MarkupParser$$handle:()Lscala/xml/parsing/MarkupHandler;
	aload_2
	invokevirtual	Method scala/xml/parsing/MarkupHandler.endDTD:(Ljava/lang/String;)V
	return
  Labels:
   	l1 = 33 // aload_0
   	l2 = 109 // aload_1
   	l3 = 131 // aload_1
   	l4 = 218 // ldc
   	l5 = 271 // aload_0
   	l6 = 333 // aload_0
  LocalVariableTable: 
   Start  Length  Slot  Name   Signature
   0      347      0    $this       Lscala/xml/parsing/MarkupHandler;
   9      337      1    extID$1       Lscala/runtime/ObjectRef;
   70      276      2    n       Ljava/lang/String;


public static scala.xml.dtd.ExternalID externalID(scala.xml.parsing.MarkupHandler);
  Signature: (Lscala/xml/parsing/MarkupHandler;)Lscala/xml/dtd/ExternalID;
  Code:
   Stack=4, Locals=5, Args_size=1
	aload_0
	checkcast	class scala/xml/parsing/MarkupParser
	invokeinterface	InterfaceMethod scala/xml/parsing/MarkupParser.ch:()C
	istore	4
	iload	4
	lookupswitch{ //2
		80: 134;
		83: 56;
		default: 40 }
	new	class scala/MatchError
	dup
	iload	4
	invokestatic	Method scala/runtime/BoxesRunTime.boxToCharacter:(C)Ljava/lang/Character;
	invokevirtual	Method java/lang/Object.toString:()Ljava/lang/String;
	invokespecial	Method scala/MatchError."<init>":(Ljava/lang/String;)V
	athrow
	iconst_1
	ifeq	l1 // new
	aload_0
	checkcast	class scala/xml/parsing/MarkupParser
	invokeinterface	InterfaceMethod scala/xml/parsing/MarkupParser.nextch:()C
	pop
	aload_0
	checkcast	class scala/xml/parsing/MarkupParserCommon
	getstatic	Field scala/Predef$.MODULE$:Lscala/Predef$;
	ldc_w	String YSTEM
	invokevirtual	Method scala/Predef$.wrapString:(Ljava/lang/String;)Lscala/collection/immutable/WrappedString;
	invokeinterface	InterfaceMethod scala/xml/parsing/MarkupParserCommon.xToken:(Lscala/collection/Seq;)V
	aload_0
	checkcast	class scala/xml/parsing/MarkupParserCommon
	invokeinterface	InterfaceMethod scala/xml/parsing/MarkupParserCommon.xSpace:()V
	aload_0
	checkcast	class scala/xml/parsing/MarkupParser
	invokeinterface	InterfaceMethod scala/xml/parsing/MarkupParser.systemLiteral:()Ljava/lang/String;
	astore_1
	new	class scala/xml/dtd/SystemID
	dup
	aload_1
	invokespecial	Method scala/xml/dtd/SystemID."<init>":(Ljava/lang/String;)V
	goto	l2 // areturn
l1	new	class scala/MatchError
	dup
	iload	4
	invokestatic	Method scala/runtime/BoxesRunTime.boxToCharacter:(C)Ljava/lang/Character;
	invokevirtual	Method java/lang/Object.toString:()Ljava/lang/String;
	invokespecial	Method scala/MatchError."<init>":(Ljava/lang/String;)V
	athrow
	iconst_1
	ifeq	l3 // new
	aload_0
	checkcast	class scala/xml/parsing/MarkupParser
	invokeinterface	InterfaceMethod scala/xml/parsing/MarkupParser.nextch:()C
	pop
	aload_0
	checkcast	class scala/xml/parsing/MarkupParserCommon
	getstatic	Field scala/Predef$.MODULE$:Lscala/Predef$;
	ldc_w	String UBLIC
	invokevirtual	Method scala/Predef$.wrapString:(Ljava/lang/String;)Lscala/collection/immutable/WrappedString;
	invokeinterface	InterfaceMethod scala/xml/parsing/MarkupParserCommon.xToken:(Lscala/collection/Seq;)V
	aload_0
	checkcast	class scala/xml/parsing/MarkupParserCommon
	invokeinterface	InterfaceMethod scala/xml/parsing/MarkupParserCommon.xSpace:()V
	aload_0
	checkcast	class scala/xml/parsing/MarkupParser
	invokeinterface	InterfaceMethod scala/xml/parsing/MarkupParser.pubidLiteral:()Ljava/lang/String;
	astore_2
	aload_0
	checkcast	class scala/xml/parsing/MarkupParserCommon
	invokeinterface	InterfaceMethod scala/xml/parsing/MarkupParserCommon.xSpace:()V
	aload_0
	checkcast	class scala/xml/parsing/MarkupParser
	invokeinterface	InterfaceMethod scala/xml/parsing/MarkupParser.systemLiteral:()Ljava/lang/String;
	astore_3
	new	class scala/xml/dtd/PublicID
	dup
	aload_2
	aload_3
	invokespecial	Method scala/xml/dtd/PublicID."<init>":(Ljava/lang/String;Ljava/lang/String;)V
l2	areturn
l3	new	class scala/MatchError
	dup
	iload	4
	invokestatic	Method scala/runtime/BoxesRunTime.boxToCharacter:(C)Ljava/lang/Character;
	invokevirtual	Method java/lang/Object.toString:()Ljava/lang/String;
	invokespecial	Method scala/MatchError."<init>":(Ljava/lang/String;)V
	athrow
  Labels:
   	l1 = 118 // new
   	l2 = 213 // areturn
   	l3 = 214 // new
  LocalVariableTable: 
   Start  Length  Slot  Name   Signature
   0      230      0    $this       Lscala/xml/parsing/MarkupHandler;
   107      8      1    sysID       Ljava/lang/String;
   185      28      2    pubID       Ljava/lang/String;
   204      9      3    sysID       Ljava/lang/String;
   11      219      4    temp51       C


public static scala.xml.NodeSeq content(scala.xml.parsing.MarkupHandler, scala.xml.NamespaceBinding);
  Signature: (Lscala/xml/parsing/MarkupHandler;Lscala/xml/NamespaceBinding;)Lscala/xml/NodeSeq;
  Code:
   Stack=7, Locals=9, Args_size=2
	new	class scala/runtime/ObjectRef
	dup
	new	class scala/xml/NodeBuffer
	dup
	invokespecial	Method scala/xml/NodeBuffer."<init>":()V
	invokespecial	Method scala/runtime/ObjectRef."<init>":(Ljava/lang/Object;)V
	astore	5
	aload_0
	checkcast	class scala/xml/parsing/MarkupParser
	invokeinterface	InterfaceMethod scala/xml/parsing/MarkupParser.eof:()Z
	istore_2
l14	iload_2
	ifeq	l1 // aload_0
	aload_0
	aload	5
	invokestatic	Method done$1:(Lscala/xml/parsing/MarkupHandler;Lscala/runtime/ObjectRef;)Lscala/xml/NodeSeq;
	areturn
l1	aload_0
	checkcast	class scala/xml/parsing/MarkupParser
	aload_0
	checkcast	class scala/xml/parsing/MarkupParser
	invokeinterface	InterfaceMethod scala/xml/parsing/MarkupParser.pos:()I
	invokeinterface	InterfaceMethod scala/xml/parsing/MarkupParser.tmppos_$eq:(I)V
	aload_0
	checkcast	class scala/xml/parsing/MarkupParser
	invokeinterface	InterfaceMethod scala/xml/parsing/MarkupParser.eof:()Z
	istore_2
	aload_0
	checkcast	class scala/xml/parsing/MarkupParser
	invokeinterface	InterfaceMethod scala/xml/parsing/MarkupParser.eof:()Z
	ifeq	l2 // aload_0
	aload_0
	aload	5
	invokestatic	Method done$1:(Lscala/xml/parsing/MarkupHandler;Lscala/runtime/ObjectRef;)Lscala/xml/NodeSeq;
	areturn
l2	aload_0
	checkcast	class scala/xml/parsing/MarkupParser
	invokeinterface	InterfaceMethod scala/xml/parsing/MarkupParser.ch:()C
	istore	8
	iload	8
	lookupswitch{ //2
		38: 292;
		60: 185;
		default: 124 }
	iconst_1
	ifeq	l3 // new
	aload_0
	checkcast	class scala/xml/parsing/MarkupParser
	aload_0
	checkcast	class scala/xml/parsing/MarkupParser
	invokeinterface	InterfaceMethod scala/xml/parsing/MarkupParser.tmppos:()I
	aload	5
	getfield	Field scala/runtime/ObjectRef.elem:Ljava/lang/Object;
	checkcast	class scala/xml/NodeBuffer
	aload_0
	checkcast	class scala/xml/parsing/MarkupParser
	invokeinterface	InterfaceMethod scala/xml/parsing/MarkupParser.xText:()Ljava/lang/String;
	invokeinterface	InterfaceMethod scala/xml/parsing/MarkupParser.appendText:(ILscala/xml/NodeBuffer;Ljava/lang/String;)V
	getstatic	Field scala/runtime/BoxedUnit.UNIT:Lscala/runtime/BoxedUnit;
	goto	l4 // pop
l3	new	class scala/MatchError
	dup
	iload	8
	invokestatic	Method scala/runtime/BoxesRunTime.boxToCharacter:(C)Ljava/lang/Character;
	invokevirtual	Method java/lang/Object.toString:()Ljava/lang/String;
	invokespecial	Method scala/MatchError."<init>":(Ljava/lang/String;)V
	athrow
	iconst_1
	ifeq	l5 // new
	aload_0
	checkcast	class scala/xml/parsing/MarkupParser
	invokeinterface	InterfaceMethod scala/xml/parsing/MarkupParser.nextch:()C
	istore_3
	iload_3
	ldc_w	int 47
	if_icmpne	l6 // iconst_1
	iconst_1
	ifeq	l7 // new
	iconst_1
	istore_2
	getstatic	Field scala/runtime/BoxedUnit.UNIT:Lscala/runtime/BoxedUnit;
	goto	l4 // pop
l7	new	class scala/MatchError
	dup
	iload_3
	invokestatic	Method scala/runtime/BoxesRunTime.boxToCharacter:(C)Ljava/lang/Character;
	invokevirtual	Method java/lang/Object.toString:()Ljava/lang/String;
	invokespecial	Method scala/MatchError."<init>":(Ljava/lang/String;)V
	athrow
l6	iconst_1
	ifeq	l8 // new
	aload_0
	checkcast	class scala/xml/parsing/MarkupParser
	aload_1
	aload	5
	getfield	Field scala/runtime/ObjectRef.elem:Ljava/lang/Object;
	checkcast	class scala/xml/NodeBuffer
	invokeinterface	InterfaceMethod scala/xml/parsing/MarkupParser.content1:(Lscala/xml/NamespaceBinding;Lscala/xml/NodeBuffer;)V
	getstatic	Field scala/runtime/BoxedUnit.UNIT:Lscala/runtime/BoxedUnit;
	goto	l4 // pop
l8	new	class scala/MatchError
	dup
	iload_3
	invokestatic	Method scala/runtime/BoxesRunTime.boxToCharacter:(C)Ljava/lang/Character;
	invokevirtual	Method java/lang/Object.toString:()Ljava/lang/String;
	invokespecial	Method scala/MatchError."<init>":(Ljava/lang/String;)V
	athrow
l5	new	class scala/MatchError
	dup
	iload	8
	invokestatic	Method scala/runtime/BoxesRunTime.boxToCharacter:(C)Ljava/lang/Character;
	invokevirtual	Method java/lang/Object.toString:()Ljava/lang/String;
	invokespecial	Method scala/MatchError."<init>":(Ljava/lang/String;)V
	athrow
	iconst_1
	ifeq	l9 // new
	aload_0
	checkcast	class scala/xml/parsing/MarkupParser
	invokeinterface	InterfaceMethod scala/xml/parsing/MarkupParser.nextch:()C
	istore	7
	iload	7
	ldc	int 35
	if_icmpne	l10 // iconst_1
	iconst_1
	ifeq	l11 // new
	aload_0
	checkcast	class scala/xml/parsing/MarkupParser
	invokeinterface	InterfaceMethod scala/xml/parsing/MarkupParser.nextch:()C
	pop
	aload_0
	checkcast	class scala/xml/parsing/MarkupParser
	invokeinterface	InterfaceMethod scala/xml/parsing/MarkupParser.scala$xml$parsing$MarkupParser$$handle:()Lscala/xml/parsing/MarkupHandler;
	aload_0
	checkcast	class scala/xml/parsing/MarkupParser
	invokeinterface	InterfaceMethod scala/xml/parsing/MarkupParser.tmppos:()I
	aload_0
	checkcast	class scala/xml/parsing/MarkupParser
	new	class scala/xml/parsing/MarkupParser$$anonfun$1
	dup
	aload_0
	invokespecial	Method scala/xml/parsing/MarkupParser$$anonfun$1."<init>":(Lscala/xml/parsing/MarkupHandler;)V
	new	class scala/xml/parsing/MarkupParser$$anonfun$2
	dup
	aload_0
	invokespecial	Method scala/xml/parsing/MarkupParser$$anonfun$2."<init>":(Lscala/xml/parsing/MarkupHandler;)V
	invokeinterface	InterfaceMethod scala/xml/parsing/MarkupParser.xCharRef:(Lscala/Function0;Lscala/Function0;)Ljava/lang/String;
	invokevirtual	Method scala/xml/parsing/MarkupHandler.text:(ILjava/lang/String;)Lscala/xml/NodeSeq;
	astore	4
	aload_0
	checkcast	class scala/xml/parsing/MarkupParserCommon
	ldc	int 59
	invokeinterface	InterfaceMethod scala/xml/parsing/MarkupParserCommon.xToken:(C)V
	aload	5
	getfield	Field scala/runtime/ObjectRef.elem:Ljava/lang/Object;
	checkcast	class scala/xml/NodeBuffer
	aload	4
	invokevirtual	Method scala/xml/NodeBuffer.$amp$plus:(Ljava/lang/Object;)Lscala/xml/NodeBuffer;
	goto	l4 // pop
l11	new	class scala/MatchError
	dup
	iload	7
	invokestatic	Method scala/runtime/BoxesRunTime.boxToCharacter:(C)Ljava/lang/Character;
	invokevirtual	Method java/lang/Object.toString:()Ljava/lang/String;
	invokespecial	Method scala/MatchError."<init>":(Ljava/lang/String;)V
	athrow
l10	iconst_1
	ifeq	l12 // new
	aload_0
	checkcast	class scala/xml/parsing/MarkupParser
	invokeinterface	InterfaceMethod scala/xml/parsing/MarkupParser.xName:()Ljava/lang/String;
	astore	6
	aload_0
	checkcast	class scala/xml/parsing/MarkupParserCommon
	ldc	int 59
	invokeinterface	InterfaceMethod scala/xml/parsing/MarkupParserCommon.xToken:(C)V
	getstatic	Field scala/xml/Utility$Escapes$.MODULE$:Lscala/xml/Utility$Escapes$;
	invokevirtual	Method scala/xml/Utility$Escapes$.pairs:()Lscala/collection/immutable/Map;
	aload	6
	invokeinterface	InterfaceMethod scala/collection/MapLike.contains:(Ljava/lang/Object;)Z
	ifeq	l13 // aload_0
	aload_0
	checkcast	class scala/xml/parsing/MarkupParser
	invokeinterface	InterfaceMethod scala/xml/parsing/MarkupParser.scala$xml$parsing$MarkupParser$$handle:()Lscala/xml/parsing/MarkupHandler;
	aload_0
	checkcast	class scala/xml/parsing/MarkupParser
	invokeinterface	InterfaceMethod scala/xml/parsing/MarkupParser.tmppos:()I
	aload	6
	invokevirtual	Method scala/xml/parsing/MarkupHandler.entityRef:(ILjava/lang/String;)Lscala/xml/NodeSeq;
	pop
	aload	5
	getfield	Field scala/runtime/ObjectRef.elem:Ljava/lang/Object;
	checkcast	class scala/xml/NodeBuffer
	getstatic	Field scala/xml/Utility$Escapes$.MODULE$:Lscala/xml/Utility$Escapes$;
	invokevirtual	Method scala/xml/Utility$Escapes$.pairs:()Lscala/collection/immutable/Map;
	aload	6
	invokeinterface	InterfaceMethod scala/collection/MapLike.apply:(Ljava/lang/Object;)Ljava/lang/Object;
	invokevirtual	Method scala/xml/NodeBuffer.$amp$plus:(Ljava/lang/Object;)Lscala/xml/NodeBuffer;
	goto	l4 // pop
l13	aload_0
	checkcast	class scala/xml/parsing/MarkupParser
	aload	6
	invokeinterface	InterfaceMethod scala/xml/parsing/MarkupParser.push:(Ljava/lang/String;)V
	getstatic	Field scala/runtime/BoxedUnit.UNIT:Lscala/runtime/BoxedUnit;
l4	pop
	goto	l14 // iload_2
l12	new	class scala/MatchError
	dup
	iload	7
	invokestatic	Method scala/runtime/BoxesRunTime.boxToCharacter:(C)Ljava/lang/Character;
	invokevirtual	Method java/lang/Object.toString:()Ljava/lang/String;
	invokespecial	Method scala/MatchError."<init>":(Ljava/lang/String;)V
	athrow
l9	new	class scala/MatchError
	dup
	iload	8
	invokestatic	Method scala/runtime/BoxesRunTime.boxToCharacter:(C)Ljava/lang/Character;
	invokevirtual	Method java/lang/Object.toString:()Ljava/lang/String;
	invokespecial	Method scala/MatchError."<init>":(Ljava/lang/String;)V
	athrow
  Labels:
   	l14 = 26 // iload_2
   	l1 = 37 // aload_0
   	l2 = 84 // aload_0
   	l3 = 169 // new
   	l7 = 218 // new
   	l6 = 233 // iconst_1
   	l8 = 261 // new
   	l5 = 276 // new
   	l11 = 403 // new
   	l10 = 419 // iconst_1
   	l13 = 512 // aload_0
   	l4 = 526 // pop
   	l12 = 530 // new
   	l9 = 546 // new
  LocalVariableTable: 
   Start  Length  Slot  Name   Signature
   0      562      0    $this       Lscala/xml/parsing/MarkupHandler;
   0      562      1    pscope       Lscala/xml/NamespaceBinding;
   26      10      2    exit       Z
   37      525      2    exit       Z
   199      77      3    temp48       C
   376      24      4    theChar       Lscala/xml/NodeSeq;
   16      20      5    ts$2       Lscala/runtime/ObjectRef;
   37      525      5    ts$2       Lscala/runtime/ObjectRef;
   434      92      6    n       Ljava/lang/String;
   307      219      7    temp49       C
   530      16      7    temp49       C
   95      432      8    temp50       C
   530      32      8    temp50       C


public static void content1(scala.xml.parsing.MarkupHandler, scala.xml.NamespaceBinding, scala.xml.NodeBuffer);
  Signature: (Lscala/xml/parsing/MarkupHandler;Lscala/xml/NamespaceBinding;Lscala/xml/NodeBuffer;)V
  Code:
   Stack=3, Locals=4, Args_size=3
	aload_0
	checkcast	class scala/xml/parsing/MarkupParser
	invokeinterface	InterfaceMethod scala/xml/parsing/MarkupParser.ch:()C
	istore_3
	iload_3
	lookupswitch{ //2
		33: 119;
		63: 73;
		default: 36 }
	iconst_1
	ifeq	l1 // new
	aload_2
	aload_0
	checkcast	class scala/xml/parsing/MarkupParser
	aload_1
	invokeinterface	InterfaceMethod scala/xml/parsing/MarkupParser.element1:(Lscala/xml/NamespaceBinding;)Lscala/xml/NodeSeq;
	invokevirtual	Method scala/xml/NodeBuffer.$amp$plus:(Ljava/lang/Object;)Lscala/xml/NodeBuffer;
	pop
	goto	l2 // return
l1	new	class scala/MatchError
	dup
	iload_3
	invokestatic	Method scala/runtime/BoxesRunTime.boxToCharacter:(C)Ljava/lang/Character;
	invokevirtual	Method java/lang/Object.toString:()Ljava/lang/String;
	invokespecial	Method scala/MatchError."<init>":(Ljava/lang/String;)V
	athrow
	iconst_1
	ifeq	l3 // new
	aload_0
	checkcast	class scala/xml/parsing/MarkupParser
	invokeinterface	InterfaceMethod scala/xml/parsing/MarkupParser.nextch:()C
	pop
	aload_2
	aload_0
	checkcast	class scala/xml/parsing/MarkupParser
	invokeinterface	InterfaceMethod scala/xml/parsing/MarkupParser.xProcInstr:()Lscala/xml/NodeSeq;
	invokevirtual	Method scala/xml/NodeBuffer.$amp$plus:(Ljava/lang/Object;)Lscala/xml/NodeBuffer;
	pop
	goto	l2 // return
l3	new	class scala/MatchError
	dup
	iload_3
	invokestatic	Method scala/runtime/BoxesRunTime.boxToCharacter:(C)Ljava/lang/Character;
	invokevirtual	Method java/lang/Object.toString:()Ljava/lang/String;
	invokespecial	Method scala/MatchError."<init>":(Ljava/lang/String;)V
	athrow
	iconst_1
	ifeq	l4 // new
	aload_0
	checkcast	class scala/xml/parsing/MarkupParser
	invokeinterface	InterfaceMethod scala/xml/parsing/MarkupParser.nextch:()C
	pop
	ldc	int 91
	aload_0
	checkcast	class scala/xml/parsing/MarkupParser
	invokeinterface	InterfaceMethod scala/xml/parsing/MarkupParser.ch:()C
	if_icmpne	l5 // ldc_w
	aload_2
	aload_0
	checkcast	class scala/xml/parsing/MarkupParser
	invokeinterface	InterfaceMethod scala/xml/parsing/MarkupParser.xCharData:()Lscala/xml/NodeSeq;
	invokevirtual	Method scala/xml/NodeBuffer.$amp$plus:(Ljava/lang/Object;)Lscala/xml/NodeBuffer;
	pop
	goto	l2 // return
l5	ldc_w	int 68
	aload_0
	checkcast	class scala/xml/parsing/MarkupParser
	invokeinterface	InterfaceMethod scala/xml/parsing/MarkupParser.ch:()C
	if_icmpne	l6 // aload_2
	aload_0
	checkcast	class scala/xml/parsing/MarkupParser
	invokeinterface	InterfaceMethod scala/xml/parsing/MarkupParser.parseDTD:()V
	goto	l2 // return
l6	aload_2
	aload_0
	checkcast	class scala/xml/parsing/MarkupParser
	invokeinterface	InterfaceMethod scala/xml/parsing/MarkupParser.xComment:()Lscala/xml/NodeSeq;
	invokevirtual	Method scala/xml/NodeBuffer.$amp$plus:(Ljava/lang/Object;)Lscala/xml/NodeBuffer;
	pop
l2	return
l4	new	class scala/MatchError
	dup
	iload_3
	invokestatic	Method scala/runtime/BoxesRunTime.boxToCharacter:(C)Ljava/lang/Character;
	invokevirtual	Method java/lang/Object.toString:()Ljava/lang/String;
	invokespecial	Method scala/MatchError."<init>":(Ljava/lang/String;)V
	athrow
  Labels:
   	l1 = 58 // new
   	l3 = 104 // new
   	l5 = 164 // ldc_w
   	l6 = 191 // aload_2
   	l2 = 205 // return
   	l4 = 206 // new
  LocalVariableTable: 
   Start  Length  Slot  Name   Signature
   0      221      0    $this       Lscala/xml/parsing/MarkupHandler;
   0      221      1    pscope       Lscala/xml/NamespaceBinding;
   0      221      2    ts       Lscala/xml/NodeBuffer;
   10      211      3    temp47       C


public static void appendText(scala.xml.parsing.MarkupHandler, int, scala.xml.NodeBuffer, java.lang.String);
  Signature: (Lscala/xml/parsing/MarkupHandler;ILscala/xml/NodeBuffer;Ljava/lang/String;)V
  Code:
   Stack=6, Locals=4, Args_size=4
	aload_0
	checkcast	class scala/xml/parsing/MarkupParser
	invokeinterface	InterfaceMethod scala/xml/parsing/MarkupParser.preserveWS:()Z
	ifeq	l1 // new
	aload_2
	aload_0
	checkcast	class scala/xml/parsing/MarkupParser
	invokeinterface	InterfaceMethod scala/xml/parsing/MarkupParser.scala$xml$parsing$MarkupParser$$handle:()Lscala/xml/parsing/MarkupHandler;
	iload_1
	aload_3
	invokevirtual	Method scala/xml/parsing/MarkupHandler.text:(ILjava/lang/String;)Lscala/xml/NodeSeq;
	invokevirtual	Method scala/xml/NodeBuffer.$amp$plus:(Ljava/lang/Object;)Lscala/xml/NodeBuffer;
	pop
	goto	l2 // return
l1	new	class scala/xml/TextBuffer
	dup
	invokespecial	Method scala/xml/TextBuffer."<init>":()V
	getstatic	Field scala/Predef$.MODULE$:Lscala/Predef$;
	aload_3
	invokevirtual	Method scala/Predef$.wrapString:(Ljava/lang/String;)Lscala/collection/immutable/WrappedString;
	invokevirtual	Method scala/xml/TextBuffer.append:(Lscala/collection/Seq;)Lscala/xml/TextBuffer;
	invokevirtual	Method scala/xml/TextBuffer.toText:()Lscala/collection/Seq;
	new	class scala/xml/parsing/MarkupParser$$anonfun$appendText$1
	dup
	aload_0
	iload_1
	aload_2
	invokespecial	Method scala/xml/parsing/MarkupParser$$anonfun$appendText$1."<init>":(Lscala/xml/parsing/MarkupHandler;ILscala/xml/NodeBuffer;)V
	invokeinterface	InterfaceMethod scala/collection/IterableLike.foreach:(Lscala/Function1;)V
l2	return
  Labels:
   	l1 = 34 // new
   	l2 = 69 // return
  LocalVariableTable: 
   Start  Length  Slot  Name   Signature
   0      70      0    $this       Lscala/xml/parsing/MarkupHandler;
   0      70      1    pos$1       I
   0      70      2    ts$1       Lscala/xml/NodeBuffer;
   0      70      3    txt       Ljava/lang/String;


public static scala.xml.NodeSeq xComment(scala.xml.parsing.MarkupHandler);
  Signature: (Lscala/xml/parsing/MarkupHandler;)Lscala/xml/NodeSeq;
  Code:
   Stack=3, Locals=3, Args_size=1
	new	class scala/collection/mutable/StringBuilder
	dup
	invokespecial	Method scala/collection/mutable/StringBuilder."<init>":()V
	astore_2
	aload_0
	checkcast	class scala/xml/parsing/MarkupParserCommon
	getstatic	Field scala/Predef$.MODULE$:Lscala/Predef$;
	ldc_w	String --
	invokevirtual	Method scala/Predef$.wrapString:(Ljava/lang/String;)Lscala/collection/immutable/WrappedString;
	invokeinterface	InterfaceMethod scala/xml/parsing/MarkupParserCommon.xToken:(Lscala/collection/Seq;)V
l4	aload_0
	checkcast	class scala/xml/parsing/MarkupParser
	invokeinterface	InterfaceMethod scala/xml/parsing/MarkupParser.ch:()C
	ldc_w	int 45
	if_icmpne	l1 // aload_2
	aload_2
	aload_0
	checkcast	class scala/xml/parsing/MarkupParser
	invokeinterface	InterfaceMethod scala/xml/parsing/MarkupParser.ch:()C
	invokevirtual	Method scala/collection/mutable/StringBuilder.append:(C)Lscala/collection/mutable/StringBuilder;
	pop
	aload_0
	checkcast	class scala/xml/parsing/MarkupParser
	invokeinterface	InterfaceMethod scala/xml/parsing/MarkupParser.nextch:()C
	pop
	aload_0
	checkcast	class scala/xml/parsing/MarkupParser
	invokeinterface	InterfaceMethod scala/xml/parsing/MarkupParser.ch:()C
	ldc_w	int 45
	if_icmpne	l2 // iconst_0
	iconst_1
	goto	l3 // ifeq
l2	iconst_0
l3	ifeq	l1 // aload_2
	aload_2
	invokevirtual	Method scala/collection/mutable/StringBuilder.length:()I
	iconst_1
	isub
	istore_1
	aload_2
	iload_1
	invokevirtual	Method scala/collection/mutable/StringBuilder.setLength:(I)V
	aload_0
	checkcast	class scala/xml/parsing/MarkupParser
	invokeinterface	InterfaceMethod scala/xml/parsing/MarkupParser.nextch:()C
	pop
	aload_0
	checkcast	class scala/xml/parsing/MarkupParserCommon
	ldc	int 62
	invokeinterface	InterfaceMethod scala/xml/parsing/MarkupParserCommon.xToken:(C)V
	aload_0
	checkcast	class scala/xml/parsing/MarkupParser
	invokeinterface	InterfaceMethod scala/xml/parsing/MarkupParser.scala$xml$parsing$MarkupParser$$handle:()Lscala/xml/parsing/MarkupHandler;
	aload_0
	checkcast	class scala/xml/parsing/MarkupParser
	invokeinterface	InterfaceMethod scala/xml/parsing/MarkupParser.pos:()I
	aload_2
	invokevirtual	Method scala/collection/mutable/StringBuilder.toString:()Ljava/lang/String;
	invokevirtual	Method scala/xml/parsing/MarkupHandler.comment:(ILjava/lang/String;)Lscala/xml/NodeSeq;
	areturn
l1	aload_2
	aload_0
	checkcast	class scala/xml/parsing/MarkupParser
	invokeinterface	InterfaceMethod scala/xml/parsing/MarkupParser.ch:()C
	invokevirtual	Method scala/collection/mutable/StringBuilder.append:(C)Lscala/collection/mutable/StringBuilder;
	pop
	aload_0
	checkcast	class scala/xml/parsing/MarkupParser
	invokeinterface	InterfaceMethod scala/xml/parsing/MarkupParser.nextch:()C
	pop
	goto	l4 // aload_0
  Labels:
   	l4 = 26 // aload_0
   	l2 = 84 // iconst_0
   	l3 = 85 // ifeq
   	l1 = 147 // aload_2
  LocalVariableTable: 
   Start  Length  Slot  Name   Signature
   0      174      0    $this       Lscala/xml/parsing/MarkupHandler;
   8      166      2    sb       Lscala/collection/mutable/StringBuilder;


public static java.lang.String xCharRef(scala.xml.parsing.MarkupHandler, scala.Function0, scala.Function0);
  Signature: (Lscala/xml/parsing/MarkupHandler;Lscala/Function0;Lscala/Function0;)Ljava/lang/String;
  Code:
   Stack=6, Locals=3, Args_size=3
	getstatic	Field scala/xml/Utility$.MODULE$:Lscala/xml/Utility$;
	aload_1
	aload_2
	new	class scala/xml/parsing/MarkupParser$$anonfun$xCharRef$1
	dup
	aload_0
	invokespecial	Method scala/xml/parsing/MarkupParser$$anonfun$xCharRef$1."<init>":(Lscala/xml/parsing/MarkupHandler;)V
	invokevirtual	Method scala/xml/Utility$.parseCharRef:(Lscala/Function0;Lscala/Function0;Lscala/Function1;)Ljava/lang/String;
	areturn
  Labels:
  LocalVariableTable: 
   Start  Length  Slot  Name   Signature
   0      17      0    $this       Lscala/xml/parsing/MarkupHandler;
   0      17      1    ch       Lscala/Function0;
   0      17      2    nextch       Lscala/Function0;


public static scala.xml.NodeSeq xCharData(scala.xml.parsing.MarkupHandler);
  Signature: (Lscala/xml/parsing/MarkupHandler;)Lscala/xml/NodeSeq;
  Code:
   Stack=3, Locals=2, Args_size=1
	aload_0
	checkcast	class scala/xml/parsing/MarkupParserCommon
	getstatic	Field scala/Predef$.MODULE$:Lscala/Predef$;
	ldc_w	String [CDATA[
	invokevirtual	Method scala/Predef$.wrapString:(Ljava/lang/String;)Lscala/collection/immutable/WrappedString;
	invokeinterface	InterfaceMethod scala/xml/parsing/MarkupParserCommon.xToken:(Lscala/collection/Seq;)V
	new	class scala/collection/mutable/StringBuilder
	dup
	invokespecial	Method scala/collection/mutable/StringBuilder."<init>":()V
	astore_1
l6	aload_0
	checkcast	class scala/xml/parsing/MarkupParser
	invokeinterface	InterfaceMethod scala/xml/parsing/MarkupParser.ch:()C
	ldc	int 93
	if_icmpne	l1 // aload_1
	aload_1
	aload_0
	checkcast	class scala/xml/parsing/MarkupParser
	invokeinterface	InterfaceMethod scala/xml/parsing/MarkupParser.ch:()C
	invokevirtual	Method scala/collection/mutable/StringBuilder.append:(C)Lscala/collection/mutable/StringBuilder;
	pop
	aload_0
	checkcast	class scala/xml/parsing/MarkupParser
	invokeinterface	InterfaceMethod scala/xml/parsing/MarkupParser.nextch:()C
	pop
	aload_0
	checkcast	class scala/xml/parsing/MarkupParser
	invokeinterface	InterfaceMethod scala/xml/parsing/MarkupParser.ch:()C
	ldc	int 93
	if_icmpne	l2 // iconst_0
	iconst_1
	goto	l3 // ifeq
l2	iconst_0
l3	ifeq	l1 // aload_1
	aload_1
	aload_0
	checkcast	class scala/xml/parsing/MarkupParser
	invokeinterface	InterfaceMethod scala/xml/parsing/MarkupParser.ch:()C
	invokevirtual	Method scala/collection/mutable/StringBuilder.append:(C)Lscala/collection/mutable/StringBuilder;
	pop
	aload_0
	checkcast	class scala/xml/parsing/MarkupParser
	invokeinterface	InterfaceMethod scala/xml/parsing/MarkupParser.nextch:()C
	pop
	aload_0
	checkcast	class scala/xml/parsing/MarkupParser
	invokeinterface	InterfaceMethod scala/xml/parsing/MarkupParser.ch:()C
	ldc	int 62
	if_icmpne	l4 // iconst_0
	iconst_1
	goto	l5 // ifeq
l4	iconst_0
l5	ifeq	l1 // aload_1
	aload_1
	aload_1
	invokevirtual	Method scala/collection/mutable/StringBuilder.length:()I
	iconst_2
	isub
	invokevirtual	Method scala/collection/mutable/StringBuilder.setLength:(I)V
	aload_0
	checkcast	class scala/xml/parsing/MarkupParser
	invokeinterface	InterfaceMethod scala/xml/parsing/MarkupParser.nextch:()C
	pop
	new	class scala/xml/PCData
	dup
	aload_1
	invokevirtual	Method scala/collection/mutable/StringBuilder.toString:()Ljava/lang/String;
	invokespecial	Method scala/xml/PCData."<init>":(Ljava/lang/String;)V
	areturn
l1	aload_1
	aload_0
	checkcast	class scala/xml/parsing/MarkupParser
	invokeinterface	InterfaceMethod scala/xml/parsing/MarkupParser.ch:()C
	invokevirtual	Method scala/collection/mutable/StringBuilder.append:(C)Lscala/collection/mutable/StringBuilder;
	pop
	aload_0
	checkcast	class scala/xml/parsing/MarkupParser
	invokeinterface	InterfaceMethod scala/xml/parsing/MarkupParser.nextch:()C
	pop
	goto	l6 // aload_0
  Labels:
   	l6 = 26 // aload_0
   	l2 = 82 // iconst_0
   	l3 = 83 // ifeq
   	l4 = 128 // iconst_0
   	l5 = 129 // ifeq
   	l1 = 164 // aload_1
  LocalVariableTable: 
   Start  Length  Slot  Name   Signature
   0      191      0    $this       Lscala/xml/parsing/MarkupHandler;
   26      165      1    sb       Lscala/collection/mutable/StringBuilder;


public static void xEndTag(scala.xml.parsing.MarkupHandler, java.lang.String);
  Signature: (Lscala/xml/parsing/MarkupHandler;Ljava/lang/String;)V
  Code:
   Stack=3, Locals=3, Args_size=2
	aload_0
	checkcast	class scala/xml/parsing/MarkupParserCommon
	ldc_w	int 47
	invokeinterface	InterfaceMethod scala/xml/parsing/MarkupParserCommon.xToken:(C)V
	aload_0
	checkcast	class scala/xml/parsing/MarkupParser
	invokeinterface	InterfaceMethod scala/xml/parsing/MarkupParser.xName:()Ljava/lang/String;
	astore_2
	aload_1
	dup
	ifnonnull	l1 // aload_2
	pop
	aload_2
	ifnull	l2 // aload_0
	goto	l3 // aload_0
l1	aload_2
	invokevirtual	Method java/lang/Object.equals:(Ljava/lang/Object;)Z
	ifne	l2 // aload_0
l3	aload_0
	checkcast	class scala/xml/parsing/MarkupParser
	new	class scala/collection/mutable/StringBuilder
	dup
	invokespecial	Method scala/collection/mutable/StringBuilder."<init>":()V
	ldc_w	String expected closing tag of 
	invokevirtual	Method scala/collection/mutable/StringBuilder.append:(Ljava/lang/Object;)Lscala/collection/mutable/StringBuilder;
	aload_1
	invokevirtual	Method scala/collection/mutable/StringBuilder.append:(Ljava/lang/Object;)Lscala/collection/mutable/StringBuilder;
	invokevirtual	Method scala/collection/mutable/StringBuilder.toString:()Ljava/lang/String;
	invokeinterface	InterfaceMethod scala/xml/parsing/MarkupParser.reportSyntaxError:(Ljava/lang/String;)V
l2	aload_0
	checkcast	class scala/xml/parsing/MarkupParserCommon
	invokeinterface	InterfaceMethod scala/xml/parsing/MarkupParserCommon.xSpaceOpt:()V
	aload_0
	checkcast	class scala/xml/parsing/MarkupParserCommon
	ldc	int 62
	invokeinterface	InterfaceMethod scala/xml/parsing/MarkupParserCommon.xToken:(C)V
	return
  Labels:
   	l1 = 35 // aload_2
   	l3 = 42 // aload_0
   	l2 = 71 // aload_0
  LocalVariableTable: 
   Start  Length  Slot  Name   Signature
   0      92      0    $this       Lscala/xml/parsing/MarkupHandler;
   0      92      1    n       Ljava/lang/String;
   22      69      2    m       Ljava/lang/String;


public static scala.Tuple3 xTag(scala.xml.parsing.MarkupHandler, scala.xml.NamespaceBinding);
  Signature: (Lscala/xml/parsing/MarkupHandler;Lscala/xml/NamespaceBinding;)Lscala/Tuple3;
  Code:
   Stack=5, Locals=9, Args_size=2
	aload_0
	checkcast	class scala/xml/parsing/MarkupParser
	invokeinterface	InterfaceMethod scala/xml/parsing/MarkupParser.xName:()Ljava/lang/String;
	astore	5
	aload_0
	checkcast	class scala/xml/parsing/MarkupParserCommon
	invokeinterface	InterfaceMethod scala/xml/parsing/MarkupParserCommon.xSpaceOpt:()V
	aload_0
	checkcast	class scala/xml/parsing/TokenTests
	aload_0
	checkcast	class scala/xml/parsing/MarkupParser
	invokeinterface	InterfaceMethod scala/xml/parsing/MarkupParser.ch:()C
	invokeinterface	InterfaceMethod scala/xml/parsing/TokenTests.isNameStart:(C)Z
	ifeq	l1 // new
	aload_0
	checkcast	class scala/xml/parsing/MarkupParser
	aload_1
	invokeinterface	InterfaceMethod scala/xml/parsing/MarkupParser.xAttributes:(Lscala/xml/NamespaceBinding;)Lscala/Tuple2;
	goto	l2 // astore
l1	new	class scala/Tuple2
	dup
	getstatic	Field scala/xml/Null$.MODULE$:Lscala/xml/Null$;
	aload_1
	invokespecial	Method scala/Tuple2."<init>":(Ljava/lang/Object;Ljava/lang/Object;)V
l2	astore	8
	aload	8
	ifnull	l3 // new
	aload	8
	invokevirtual	Method scala/Tuple2._1:()Ljava/lang/Object;
	checkcast	class scala/xml/MetaData
	astore_2
	aload	8
	invokevirtual	Method scala/Tuple2._2:()Ljava/lang/Object;
	checkcast	class scala/xml/NamespaceBinding
	astore_3
	aload_2
	ifnull	l4 // new
	aload_3
	ifnull	l5 // new
	iconst_1
	ifeq	l6 // new
	new	class scala/Tuple2
	dup
	aload_2
	aload_3
	invokespecial	Method scala/Tuple2."<init>":(Ljava/lang/Object;Ljava/lang/Object;)V
	astore	4
	aload	4
	invokevirtual	Method scala/Tuple2._1:()Ljava/lang/Object;
	checkcast	class scala/xml/MetaData
	astore	6
	aload	4
	invokevirtual	Method scala/Tuple2._2:()Ljava/lang/Object;
	checkcast	class scala/xml/NamespaceBinding
	astore	7
	new	class scala/Tuple3
	dup
	aload	5
	aload	6
	aload	7
	invokespecial	Method scala/Tuple3."<init>":(Ljava/lang/Object;Ljava/lang/Object;Ljava/lang/Object;)V
	areturn
l6	new	class scala/MatchError
	dup
	aload	8
	invokevirtual	Method scala/Tuple2.toString:()Ljava/lang/String;
	invokespecial	Method scala/MatchError."<init>":(Ljava/lang/String;)V
	athrow
l5	new	class scala/MatchError
	dup
	aload	8
	invokevirtual	Method scala/Tuple2.toString:()Ljava/lang/String;
	invokespecial	Method scala/MatchError."<init>":(Ljava/lang/String;)V
	athrow
l4	new	class scala/MatchError
	dup
	aload	8
	invokevirtual	Method scala/Tuple2.toString:()Ljava/lang/String;
	invokespecial	Method scala/MatchError."<init>":(Ljava/lang/String;)V
	athrow
l3	new	class scala/MatchError
	dup
	aload	8
	invokevirtual	Method scala/Tuple2.toString:()Ljava/lang/String;
	invokespecial	Method scala/MatchError."<init>":(Ljava/lang/String;)V
	athrow
  Labels:
   	l1 = 54 // new
   	l2 = 65 // astore
   	l6 = 147 // new
   	l5 = 160 // new
   	l4 = 173 // new
   	l3 = 186 // new
  LocalVariableTable: 
   Start  Length  Slot  Name   Signature
   0      199      0    $this       Lscala/xml/parsing/MarkupHandler;
   0      199      1    pscope       Lscala/xml/NamespaceBinding;
   81      105      2    temp42       Lscala/xml/MetaData;
   90      96      3    temp43       Lscala/xml/NamespaceBinding;
   11      135      5    qname       Ljava/lang/String;
   147      52      5    qname       Ljava/lang/String;
   123      23      6    aMap       Lscala/xml/MetaData;
   133      13      7    scope       Lscala/xml/NamespaceBinding;
   67      132      8    temp41       Lscala/Tuple2;


public static java.lang.String xEntityValue(scala.xml.parsing.MarkupHandler);
  Signature: (Lscala/xml/parsing/MarkupHandler;)Ljava/lang/String;
  Code:
   Stack=2, Locals=5, Args_size=1
	aload_0
	checkcast	class scala/xml/parsing/MarkupParser
	invokeinterface	InterfaceMethod scala/xml/parsing/MarkupParser.ch:()C
	istore_1
	aload_0
	checkcast	class scala/xml/parsing/MarkupParser
	invokeinterface	InterfaceMethod scala/xml/parsing/MarkupParser.nextch:()C
	pop
l2	aload_0
	checkcast	class scala/xml/parsing/MarkupParser
	invokeinterface	InterfaceMethod scala/xml/parsing/MarkupParser.ch:()C
	iload_1
	if_icmpeq	l1 // aload_0
	aload_0
	checkcast	class scala/xml/parsing/MarkupParser
	aload_0
	checkcast	class scala/xml/parsing/MarkupParser
	invokeinterface	InterfaceMethod scala/xml/parsing/MarkupParser.ch:()C
	invokeinterface	InterfaceMethod scala/xml/parsing/MarkupParser.putChar:(C)Lscala/collection/mutable/StringBuilder;
	pop
	aload_0
	checkcast	class scala/xml/parsing/MarkupParser
	invokeinterface	InterfaceMethod scala/xml/parsing/MarkupParser.nextch:()C
	pop
	goto	l2 // aload_0
l1	aload_0
	checkcast	class scala/xml/parsing/MarkupParser
	invokeinterface	InterfaceMethod scala/xml/parsing/MarkupParser.nextch:()C
	pop
	aload_0
	checkcast	class scala/xml/parsing/MarkupParser
	invokeinterface	InterfaceMethod scala/xml/parsing/MarkupParser.cbuf:()Lscala/collection/mutable/StringBuilder;
	invokevirtual	Method scala/collection/mutable/StringBuilder.toString:()Ljava/lang/String;
	astore_2
	aload_0
	checkcast	class scala/xml/parsing/MarkupParser
	invokeinterface	InterfaceMethod scala/xml/parsing/MarkupParser.cbuf:()Lscala/collection/mutable/StringBuilder;
	iconst_0
	istore_3
	astore	4
	aload	4
	iload_3
	invokevirtual	Method scala/collection/mutable/StringBuilder.setLength:(I)V
	aload_2
	areturn
  Labels:
   	l2 = 20 // aload_0
   	l1 = 65 // aload_0
  LocalVariableTable: 
   Start  Length  Slot  Name   Signature
   0      109      0    $this       Lscala/xml/parsing/MarkupHandler;
   10      98      1    endch       C
   88      20      2    str       Ljava/lang/String;


public static java.lang.String xAttributeValue(scala.xml.parsing.MarkupHandler);
  Signature: (Lscala/xml/parsing/MarkupHandler;)Ljava/lang/String;
  Code:
   Stack=2, Locals=5, Args_size=1
	aload_0
	checkcast	class scala/xml/parsing/MarkupParser
	invokeinterface	InterfaceMethod scala/xml/parsing/MarkupParser.ch:()C
	istore_1
	aload_0
	checkcast	class scala/xml/parsing/MarkupParser
	invokeinterface	InterfaceMethod scala/xml/parsing/MarkupParser.nextch:()C
	pop
l3	aload_0
	checkcast	class scala/xml/parsing/MarkupParser
	invokeinterface	InterfaceMethod scala/xml/parsing/MarkupParser.ch:()C
	iload_1
	if_icmpeq	l1 // aload_0
	ldc	int 60
	aload_0
	checkcast	class scala/xml/parsing/MarkupParser
	invokeinterface	InterfaceMethod scala/xml/parsing/MarkupParser.ch:()C
	if_icmpne	l2 // aload_0
	aload_0
	checkcast	class scala/xml/parsing/MarkupParser
	ldc_w	String '<' not allowed in attrib value
	invokeinterface	InterfaceMethod scala/xml/parsing/MarkupParser.reportSyntaxError:(Ljava/lang/String;)V
l2	aload_0
	checkcast	class scala/xml/parsing/MarkupParser
	aload_0
	checkcast	class scala/xml/parsing/MarkupParser
	invokeinterface	InterfaceMethod scala/xml/parsing/MarkupParser.ch:()C
	invokeinterface	InterfaceMethod scala/xml/parsing/MarkupParser.putChar:(C)Lscala/collection/mutable/StringBuilder;
	pop
	aload_0
	checkcast	class scala/xml/parsing/MarkupParser
	invokeinterface	InterfaceMethod scala/xml/parsing/MarkupParser.nextch:()C
	pop
	goto	l3 // aload_0
l1	aload_0
	checkcast	class scala/xml/parsing/MarkupParser
	invokeinterface	InterfaceMethod scala/xml/parsing/MarkupParser.nextch:()C
	pop
	aload_0
	checkcast	class scala/xml/parsing/MarkupParser
	invokeinterface	InterfaceMethod scala/xml/parsing/MarkupParser.cbuf:()Lscala/collection/mutable/StringBuilder;
	invokevirtual	Method scala/collection/mutable/StringBuilder.toString:()Ljava/lang/String;
	astore_2
	aload_0
	checkcast	class scala/xml/parsing/MarkupParser
	invokeinterface	InterfaceMethod scala/xml/parsing/MarkupParser.cbuf:()Lscala/collection/mutable/StringBuilder;
	iconst_0
	istore_3
	astore	4
	aload	4
	iload_3
	invokevirtual	Method scala/collection/mutable/StringBuilder.setLength:(I)V
	aload_0
	checkcast	class scala/xml/parsing/MarkupParser
	aload_2
	invokeinterface	InterfaceMethod scala/xml/parsing/MarkupParser.normalizeAttributeValue:(Ljava/lang/String;)Ljava/lang/String;
	areturn
  Labels:
   	l3 = 20 // aload_0
   	l2 = 59 // aload_0
   	l1 = 91 // aload_0
  LocalVariableTable: 
   Start  Length  Slot  Name   Signature
   0      144      0    $this       Lscala/xml/parsing/MarkupHandler;
   10      133      1    endch       C
   114      29      2    str       Ljava/lang/String;


public static scala.Tuple2 xAttributes(scala.xml.parsing.MarkupHandler, scala.xml.NamespaceBinding);
  Signature: (Lscala/xml/parsing/MarkupHandler;Lscala/xml/NamespaceBinding;)Lscala/Tuple2;
  Code:
   Stack=6, Locals=13, Args_size=2
	aload_1
	astore	12
	getstatic	Field scala/xml/Null$.MODULE$:Lscala/xml/Null$;
	astore	11
l13	aload_0
	checkcast	class scala/xml/parsing/TokenTests
	aload_0
	checkcast	class scala/xml/parsing/MarkupParser
	invokeinterface	InterfaceMethod scala/xml/parsing/MarkupParser.ch:()C
	invokeinterface	InterfaceMethod scala/xml/parsing/TokenTests.isNameStart:(C)Z
	ifeq	l1 // aload
	aload_0
	checkcast	class scala/xml/parsing/MarkupParser
	invokeinterface	InterfaceMethod scala/xml/parsing/MarkupParser.xName:()Ljava/lang/String;
	astore	8
	aload_0
	checkcast	class scala/xml/parsing/MarkupParserCommon
	invokeinterface	InterfaceMethod scala/xml/parsing/MarkupParserCommon.xEQ:()V
	aload_0
	checkcast	class scala/xml/parsing/MarkupParser
	invokeinterface	InterfaceMethod scala/xml/parsing/MarkupParser.xAttributeValue:()Ljava/lang/String;
	astore	9
	getstatic	Field scala/xml/Utility$.MODULE$:Lscala/xml/Utility$;
	aload	8
	invokevirtual	Method scala/xml/Utility$.prefix:(Ljava/lang/String;)Lscala/Option;
	astore	10
	aload	10
	instanceof	class scala/Some
	ifeq	l2 // iconst_1
	aload	10
	checkcast	class scala/Some
	astore_2
	aload_2
	getfield	Field scala/Some.x:Ljava/lang/Object;
	checkcast	class java/lang/String
	astore	5
	aload	5
	ldc_w	String xmlns
	astore_3
	dup
	ifnonnull	l3 // aload_3
	pop
	aload_3
	ifnull	l4 // iconst_1
	goto	l5 // iconst_1
l3	aload_3
	invokevirtual	Method java/lang/Object.equals:(Ljava/lang/Object;)Z
	ifeq	l5 // iconst_1
l4	iconst_1
	ifeq	l6 // new
	aload	8
	ldc_w	int 6
	aload	8
	invokevirtual	Method java/lang/String.length:()I
	invokevirtual	Method java/lang/String.substring:(II)Ljava/lang/String;
	astore	4
	new	class scala/xml/NamespaceBinding
	dup
	aload	4
	aload	9
	aload	12
	invokespecial	Method scala/xml/NamespaceBinding."<init>":(Ljava/lang/String;Ljava/lang/String;Lscala/xml/NamespaceBinding;)V
	astore	12
	goto	l7 // aload_0
l6	new	class scala/MatchError
	dup
	aload	10
	invokevirtual	Method scala/Option.toString:()Ljava/lang/String;
	invokespecial	Method scala/MatchError."<init>":(Ljava/lang/String;)V
	athrow
l5	iconst_1
	ifeq	l8 // new
	aload	8
	aload	5
	invokevirtual	Method java/lang/String.length:()I
	iconst_1
	iadd
	aload	8
	invokevirtual	Method java/lang/String.length:()I
	invokevirtual	Method java/lang/String.substring:(II)Ljava/lang/String;
	astore	6
	new	class scala/xml/PrefixedAttribute
	dup
	aload	5
	aload	6
	getstatic	Field scala/xml/Text$.MODULE$:Lscala/xml/Text$;
	aload	9
	invokevirtual	Method scala/xml/Text$.apply:(Ljava/lang/String;)Lscala/xml/Text;
	aload	11
	invokespecial	Method scala/xml/PrefixedAttribute."<init>":(Ljava/lang/String;Ljava/lang/String;Lscala/collection/Seq;Lscala/xml/MetaData;)V
	astore	11
	goto	l7 // aload_0
l8	new	class scala/MatchError
	dup
	aload	10
	invokevirtual	Method scala/Option.toString:()Ljava/lang/String;
	invokespecial	Method scala/MatchError."<init>":(Ljava/lang/String;)V
	athrow
l2	iconst_1
	ifeq	l9 // new
	aload	8
	ldc_w	String xmlns
	astore	7
	dup
	ifnonnull	l10 // aload
	pop
	aload	7
	ifnull	l11 // new
	goto	l12 // new
l10	aload	7
	invokevirtual	Method java/lang/Object.equals:(Ljava/lang/Object;)Z
	ifeq	l12 // new
l11	new	class scala/xml/NamespaceBinding
	dup
	aconst_null
	aload	9
	aload	12
	invokespecial	Method scala/xml/NamespaceBinding."<init>":(Ljava/lang/String;Ljava/lang/String;Lscala/xml/NamespaceBinding;)V
	astore	12
	goto	l7 // aload_0
l12	new	class scala/xml/UnprefixedAttribute
	dup
	aload	8
	getstatic	Field scala/xml/Text$.MODULE$:Lscala/xml/Text$;
	aload	9
	invokevirtual	Method scala/xml/Text$.apply:(Ljava/lang/String;)Lscala/xml/Text;
	aload	11
	invokespecial	Method scala/xml/UnprefixedAttribute."<init>":(Ljava/lang/String;Lscala/collection/Seq;Lscala/xml/MetaData;)V
	astore	11
l7	aload_0
	checkcast	class scala/xml/parsing/MarkupParser
	invokeinterface	InterfaceMethod scala/xml/parsing/MarkupParser.ch:()C
	ldc_w	int 47
	if_icmpeq	l13 // aload_0
	aload_0
	checkcast	class scala/xml/parsing/MarkupParser
	invokeinterface	InterfaceMethod scala/xml/parsing/MarkupParser.ch:()C
	ldc	int 62
	if_icmpeq	l13 // aload_0
	ldc_w	int 63
	aload_0
	checkcast	class scala/xml/parsing/MarkupParser
	invokeinterface	InterfaceMethod scala/xml/parsing/MarkupParser.ch:()C
	if_icmpeq	l13 // aload_0
	aload_0
	checkcast	class scala/xml/parsing/MarkupParserCommon
	invokeinterface	InterfaceMethod scala/xml/parsing/MarkupParserCommon.xSpace:()V
	goto	l13 // aload_0
l9	new	class scala/MatchError
	dup
	aload	10
	invokevirtual	Method scala/Option.toString:()Ljava/lang/String;
	invokespecial	Method scala/MatchError."<init>":(Ljava/lang/String;)V
	athrow
l1	aload	11
	aload	12
	invokevirtual	Method scala/xml/MetaData.wellformed:(Lscala/xml/NamespaceBinding;)Z
	ifne	l14 // new
	aload_0
	checkcast	class scala/xml/parsing/MarkupParser
	ldc_w	String double attribute
	invokeinterface	InterfaceMethod scala/xml/parsing/MarkupParser.reportSyntaxError:(Ljava/lang/String;)V
l14	new	class scala/Tuple2
	dup
	aload	11
	aload	12
	invokespecial	Method scala/Tuple2."<init>":(Ljava/lang/Object;Ljava/lang/Object;)V
	areturn
  Labels:
   	l13 = 8 // aload_0
   	l3 = 111 // aload_3
   	l4 = 118 // iconst_1
   	l6 = 155 // new
   	l5 = 168 // iconst_1
   	l8 = 217 // new
   	l2 = 230 // iconst_1
   	l10 = 254 // aload
   	l11 = 262 // new
   	l12 = 279 // new
   	l7 = 300 // aload_0
   	l9 = 356 // new
   	l1 = 369 // aload
   	l14 = 391 // new
  LocalVariableTable: 
   Start  Length  Slot  Name   Signature
   0      403      0    $this       Lscala/xml/parsing/MarkupHandler;
   0      403      1    pscope       Lscala/xml/NamespaceBinding;
   84      146      2    temp38       Lscala/Some;
   137      15      4    prefix       Ljava/lang/String;
   93      137      5    temp39       Ljava/lang/String;
   191      23      6    key       Ljava/lang/String;
   40      329      8    qname       Ljava/lang/String;
   60      309      9    value       Ljava/lang/String;
   70      245      10    temp37       Lscala/Option;
   356      13      10    temp37       Lscala/Option;
   8      394      11    aMap       Lscala/xml/MetaData;
   3      399      12    scope       Lscala/xml/NamespaceBinding;


public static char nextch(scala.xml.parsing.MarkupHandler);
  Signature: (Lscala/xml/parsing/MarkupHandler;)C
  Code:
   Stack=2, Locals=2, Args_size=1
	aload_0
	checkcast	class scala/xml/parsing/MarkupParser
	invokeinterface	InterfaceMethod scala/xml/parsing/MarkupParser.curInput:()Lscala/io/Source;
	invokevirtual	Method scala/io/Source.hasNext:()Z
	ifeq	l1 // aload_0
	aload_0
	checkcast	class scala/xml/parsing/MarkupParser
	aload_0
	checkcast	class scala/xml/parsing/MarkupParser
	invokeinterface	InterfaceMethod scala/xml/parsing/MarkupParser.curInput:()Lscala/io/Source;
	invokevirtual	Method scala/io/Source.next:()C
	invokeinterface	InterfaceMethod scala/xml/parsing/MarkupParser.ch_$eq:(C)V
	aload_0
	checkcast	class scala/xml/parsing/MarkupParser
	aload_0
	checkcast	class scala/xml/parsing/MarkupParser
	invokeinterface	InterfaceMethod scala/xml/parsing/MarkupParser.curInput:()Lscala/io/Source;
	invokevirtual	Method scala/io/Source.pos:()I
	invokeinterface	InterfaceMethod scala/xml/parsing/MarkupParser.pos_$eq:(I)V
	goto	l2 // aload_0
l1	aload_0
	checkcast	class scala/xml/parsing/MarkupParser
	invokeinterface	InterfaceMethod scala/xml/parsing/MarkupParser.inpStack:()Lscala/collection/immutable/List;
	invokeinterface	InterfaceMethod scala/collection/LinearSeqLike.length:()I
	istore_1
	iload_1
	aload_0
	checkcast	class scala/xml/parsing/MarkupParser
	invokeinterface	InterfaceMethod scala/xml/parsing/MarkupParser.extIndex:()I
	if_icmpeq	l3 // aload_0
	iload_1
	iconst_0
	if_icmple	l3 // aload_0
	aload_0
	checkcast	class scala/xml/parsing/MarkupParser
	invokeinterface	InterfaceMethod scala/xml/parsing/MarkupParser.pop:()V
	goto	l2 // aload_0
l3	aload_0
	checkcast	class scala/xml/parsing/MarkupParser
	iconst_1
	invokeinterface	InterfaceMethod scala/xml/parsing/MarkupParser.eof_$eq:(Z)V
	aload_0
	checkcast	class scala/xml/parsing/MarkupParser
	iconst_0
	i2c
	invokeinterface	InterfaceMethod scala/xml/parsing/MarkupParser.ch_$eq:(C)V
l2	aload_0
	checkcast	class scala/xml/parsing/MarkupParser
	invokeinterface	InterfaceMethod scala/xml/parsing/MarkupParser.ch:()C
	ireturn
  Labels:
   	l1 = 60 // aload_0
   	l3 = 105 // aload_0
   	l2 = 126 // aload_0
  LocalVariableTable: 
   Start  Length  Slot  Name   Signature
   0      136      0    $this       Lscala/xml/parsing/MarkupHandler;
   75      51      1    ilen       I


public static scala.xml.parsing.MarkupHandler initialize(scala.xml.parsing.MarkupHandler);
  Signature: (Lscala/xml/parsing/MarkupHandler;)Lscala/xml/parsing/MarkupHandler;
  Code:
   Stack=1, Locals=1, Args_size=1
	aload_0
	checkcast	class scala/xml/parsing/MarkupParser
	invokeinterface	InterfaceMethod scala/xml/parsing/MarkupParser.nextch:()C
	pop
	aload_0
	areturn
  Labels:
  LocalVariableTable: 
   Start  Length  Slot  Name   Signature
   0      12      0    $this       Lscala/xml/parsing/MarkupHandler;


public static scala.collection.mutable.StringBuilder putChar(scala.xml.parsing.MarkupHandler, char);
  Signature: (Lscala/xml/parsing/MarkupHandler;C)Lscala/collection/mutable/StringBuilder;
  Code:
   Stack=2, Locals=2, Args_size=2
	aload_0
	checkcast	class scala/xml/parsing/MarkupParser
	invokeinterface	InterfaceMethod scala/xml/parsing/MarkupParser.cbuf:()Lscala/collection/mutable/StringBuilder;
	iload_1
	invokevirtual	Method scala/collection/mutable/StringBuilder.append:(C)Lscala/collection/mutable/StringBuilder;
	areturn
  Labels:
  LocalVariableTable: 
   Start  Length  Slot  Name   Signature
   0      14      0    $this       Lscala/xml/parsing/MarkupHandler;
   0      14      1    c       C


public static scala.xml.Document document(scala.xml.parsing.MarkupHandler);
  Signature: (Lscala/xml/parsing/MarkupHandler;)Lscala/xml/Document;
  Code:
   Stack=6, Locals=8, Args_size=1
	aload_0
	checkcast	class scala/xml/parsing/MarkupParser
	new	class scala/xml/Document
	dup
	invokespecial	Method scala/xml/Document."<init>":()V
	invokeinterface	InterfaceMethod scala/xml/parsing/MarkupParser.doc_$eq:(Lscala/xml/Document;)V
	aload_0
	checkcast	class scala/xml/parsing/MarkupParser
	aconst_null
	invokeinterface	InterfaceMethod scala/xml/parsing/MarkupParser.dtd_$eq:(Lscala/xml/dtd/DTD;)V
	new	class scala/Tuple3
	dup
	pop
	getstatic	Field scala/None$.MODULE$:Lscala/None$;
	getstatic	Field scala/None$.MODULE$:Lscala/None$;
	getstatic	Field scala/None$.MODULE$:Lscala/None$;
	invokespecial	Method scala/Tuple3."<init>":(Ljava/lang/Object;Ljava/lang/Object;Ljava/lang/Object;)V
	ldc	int 60
	aload_0
	checkcast	class scala/xml/parsing/MarkupParser
	invokeinterface	InterfaceMethod scala/xml/parsing/MarkupParser.ch:()C
	if_icmpeq	l1 // aload_0
	aload_0
	checkcast	class scala/xml/parsing/MarkupParser
	ldc_w	String < expected
	invokeinterface	InterfaceMethod scala/xml/parsing/MarkupParser.reportSyntaxError:(Ljava/lang/String;)V
	aconst_null
	areturn
l1	aload_0
	checkcast	class scala/xml/parsing/MarkupParser
	invokeinterface	InterfaceMethod scala/xml/parsing/MarkupParser.nextch:()C
	pop
	ldc_w	int 63
	aload_0
	checkcast	class scala/xml/parsing/MarkupParser
	invokeinterface	InterfaceMethod scala/xml/parsing/MarkupParser.ch:()C
	if_icmpne	l2 // new
	aload_0
	checkcast	class scala/xml/parsing/MarkupParser
	invokeinterface	InterfaceMethod scala/xml/parsing/MarkupParser.nextch:()C
	pop
	aload_0
	checkcast	class scala/xml/parsing/MarkupParser
	invokeinterface	InterfaceMethod scala/xml/parsing/MarkupParser.prolog:()Lscala/Tuple3;
	astore_1
	aload_0
	checkcast	class scala/xml/parsing/MarkupParser
	invokeinterface	InterfaceMethod scala/xml/parsing/MarkupParser.doc:()Lscala/xml/Document;
	aload_1
	invokevirtual	Method scala/Tuple3._1:()Ljava/lang/Object;
	checkcast	class scala/Option
	invokevirtual	Method scala/xml/Document.version_$eq:(Lscala/Option;)V
	aload_0
	checkcast	class scala/xml/parsing/MarkupParser
	invokeinterface	InterfaceMethod scala/xml/parsing/MarkupParser.doc:()Lscala/xml/Document;
	aload_1
	invokevirtual	Method scala/Tuple3._2:()Ljava/lang/Object;
	checkcast	class scala/Option
	invokevirtual	Method scala/xml/Document.encoding_$eq:(Lscala/Option;)V
	aload_0
	checkcast	class scala/xml/parsing/MarkupParser
	invokeinterface	InterfaceMethod scala/xml/parsing/MarkupParser.doc:()Lscala/xml/Document;
	aload_1
	invokevirtual	Method scala/Tuple3._3:()Ljava/lang/Object;
	checkcast	class scala/Option
	invokevirtual	Method scala/xml/Document.standAlone_$eq:(Lscala/Option;)V
	aload_0
	checkcast	class scala/xml/parsing/MarkupParser
	getstatic	Field scala/xml/TopScope$.MODULE$:Lscala/xml/TopScope$;
	invokeinterface	InterfaceMethod scala/xml/parsing/MarkupParser.content:(Lscala/xml/NamespaceBinding;)Lscala/xml/NodeSeq;
	astore	6
	goto	l3 // new
l2	new	class scala/xml/NodeBuffer
	dup
	invokespecial	Method scala/xml/NodeBuffer."<init>":()V
	astore_2
	aload_0
	checkcast	class scala/xml/parsing/MarkupParser
	getstatic	Field scala/xml/TopScope$.MODULE$:Lscala/xml/TopScope$;
	aload_2
	invokeinterface	InterfaceMethod scala/xml/parsing/MarkupParser.content1:(Lscala/xml/NamespaceBinding;Lscala/xml/NodeBuffer;)V
	aload_2
	aload_0
	checkcast	class scala/xml/parsing/MarkupParser
	getstatic	Field scala/xml/TopScope$.MODULE$:Lscala/xml/TopScope$;
	invokeinterface	InterfaceMethod scala/xml/parsing/MarkupParser.content:(Lscala/xml/NamespaceBinding;)Lscala/xml/NodeSeq;
	invokevirtual	Method scala/xml/NodeBuffer.$amp$plus:(Ljava/lang/Object;)Lscala/xml/NodeBuffer;
	pop
	new	class scala/xml/NodeSeq$$anon$1
	dup
	aload_2
	invokespecial	Method scala/xml/NodeSeq$$anon$1."<init>":(Lscala/collection/Seq;)V
	astore	6
l3	new	class scala/runtime/IntRef
	dup
	iconst_0
	invokespecial	Method scala/runtime/IntRef."<init>":(I)V
	astore_3
	new	class scala/runtime/ObjectRef
	dup
	aconst_null
	invokespecial	Method scala/runtime/ObjectRef."<init>":(Ljava/lang/Object;)V
	astore	7
	aload	6
	new	class scala/xml/parsing/MarkupParser$$anonfun$document$1
	dup
	aload_0
	aload_3
	aload	7
	invokespecial	Method scala/xml/parsing/MarkupParser$$anonfun$document$1."<init>":(Lscala/xml/parsing/MarkupHandler;Lscala/runtime/IntRef;Lscala/runtime/ObjectRef;)V
	invokeinterface	InterfaceMethod scala/collection/IterableLike.foreach:(Lscala/Function1;)V
	iconst_1
	aload_3
	getfield	Field scala/runtime/IntRef.elem:I
	if_icmpeq	l4 // aload_0
	aload_0
	checkcast	class scala/xml/parsing/MarkupParser
	ldc_w	String document must contain exactly one element
	invokeinterface	InterfaceMethod scala/xml/parsing/MarkupParser.reportSyntaxError:(Ljava/lang/String;)V
	getstatic	Field scala/Console$.MODULE$:Lscala/Console$;
	aload	6
	invokeinterface	InterfaceMethod scala/collection/TraversableLike.toList:()Lscala/collection/immutable/List;
	astore	5
	astore	4
	aload	4
	invokevirtual	Method scala/Console$.out:()Ljava/io/PrintStream;
	aload	5
	invokevirtual	Method java/io/PrintStream.println:(Ljava/lang/Object;)V
l4	aload_0
	checkcast	class scala/xml/parsing/MarkupParser
	invokeinterface	InterfaceMethod scala/xml/parsing/MarkupParser.doc:()Lscala/xml/Document;
	aload	6
	invokevirtual	Method scala/xml/Document.children_$eq:(Lscala/collection/Seq;)V
	aload_0
	checkcast	class scala/xml/parsing/MarkupParser
	invokeinterface	InterfaceMethod scala/xml/parsing/MarkupParser.doc:()Lscala/xml/Document;
	aload	7
	getfield	Field scala/runtime/ObjectRef.elem:Ljava/lang/Object;
	checkcast	class scala/xml/Node
	invokevirtual	Method scala/xml/Document.docElem_$eq:(Lscala/xml/Node;)V
	aload_0
	checkcast	class scala/xml/parsing/MarkupParser
	invokeinterface	InterfaceMethod scala/xml/parsing/MarkupParser.doc:()Lscala/xml/Document;
	areturn
  Labels:
   	l1 = 71 // aload_0
   	l2 = 190 // new
   	l3 = 238 // new
   	l4 = 319 // aload_0
  LocalVariableTable: 
   Start  Length  Slot  Name   Signature
   0      363      0    $this       Lscala/xml/parsing/MarkupHandler;
   43      319      1    info_prolog       Lscala/Tuple3;
   198      40      2    ts       Lscala/xml/NodeBuffer;
   247      115      3    elemCount$1       Lscala/runtime/IntRef;
   81      281      6    children       Lscala/xml/NodeSeq;
   257      105      7    theNode$1       Lscala/runtime/ObjectRef;


public static scala.Tuple2 textDecl(scala.xml.parsing.MarkupHandler);
  Signature: (Lscala/xml/parsing/MarkupHandler;)Lscala/Tuple2;
  Code:
   Stack=4, Locals=11, Args_size=1
	getstatic	Field scala/None$.MODULE$:Lscala/None$;
	astore	7
	getstatic	Field scala/None$.MODULE$:Lscala/None$;
	astore	8
	aload_0
	checkcast	class scala/xml/parsing/MarkupParser
	invokeinterface	InterfaceMethod scala/xml/parsing/MarkupParser.xmlProcInstr:()Lscala/xml/MetaData;
	astore	5
	iconst_0
	istore	6
	aload	5
	ldc_w	String version
	invokevirtual	Method scala/xml/MetaData.apply:(Ljava/lang/String;)Lscala/collection/Seq;
	astore	10
	aload	10
	ifnonnull	l1 // getstatic
	iconst_1
	ifne	l2 // aload
	new	class scala/MatchError
	dup
	aload	10
	invokeinterface	InterfaceMethod scala/collection/SeqLike.toString:()Ljava/lang/String;
	invokespecial	Method scala/MatchError."<init>":(Ljava/lang/String;)V
	athrow
l1	getstatic	Field scala/xml/Text$.MODULE$:Lscala/xml/Text$;
	aload	10
	invokevirtual	Method scala/xml/Text$.unapply:(Ljava/lang/Object;)Lscala/Option;
	astore_1
	aload_1
	invokevirtual	Method scala/Option.isEmpty:()Z
	ifeq	l3 // aload_1
	iconst_1
	ifne	l4 // aload_0
	new	class scala/MatchError
	dup
	aload	10
	invokeinterface	InterfaceMethod scala/collection/SeqLike.toString:()Ljava/lang/String;
	invokespecial	Method scala/MatchError."<init>":(Ljava/lang/String;)V
	athrow
l3	aload_1
	invokevirtual	Method scala/Option.get:()Ljava/lang/Object;
	ldc_w	String 1.0
	astore_2
	dup
	ifnonnull	l5 // aload_2
	pop
	aload_2
	ifnull	l6 // iconst_1
	goto	l7 // iconst_1
l5	aload_2
	invokevirtual	Method java/lang/Object.equals:(Ljava/lang/Object;)Z
	ifeq	l7 // iconst_1
l6	iconst_1
	ifeq	l8 // new
	new	class scala/Some
	dup
	ldc_w	String 1.0
	invokespecial	Method scala/Some."<init>":(Ljava/lang/Object;)V
	astore	7
	iload	6
	iconst_1
	iadd
	istore	6
	goto	l2 // aload
l8	new	class scala/MatchError
	dup
	aload	10
	invokeinterface	InterfaceMethod scala/collection/SeqLike.toString:()Ljava/lang/String;
	invokespecial	Method scala/MatchError."<init>":(Ljava/lang/String;)V
	athrow
l7	iconst_1
	ifeq	l9 // new
l4	aload_0
	checkcast	class scala/xml/parsing/MarkupParser
	ldc_w	String cannot deal with versions != 1.0
	invokeinterface	InterfaceMethod scala/xml/parsing/MarkupParser.reportSyntaxError:(Ljava/lang/String;)V
l2	aload	5
	ldc_w	String encoding
	invokevirtual	Method scala/xml/MetaData.apply:(Ljava/lang/String;)Lscala/collection/Seq;
	astore	9
	aload	9
	ifnonnull	l10 // getstatic
	iconst_1
	ifne	l11 // aload
	new	class scala/MatchError
	dup
	aload	9
	invokeinterface	InterfaceMethod scala/collection/SeqLike.toString:()Ljava/lang/String;
	invokespecial	Method scala/MatchError."<init>":(Ljava/lang/String;)V
	athrow
l10	getstatic	Field scala/xml/Text$.MODULE$:Lscala/xml/Text$;
	aload	9
	invokevirtual	Method scala/xml/Text$.unapply:(Ljava/lang/Object;)Lscala/Option;
	astore_3
	aload_3
	invokevirtual	Method scala/Option.isEmpty:()Z
	ifeq	l12 // aload_3
	new	class scala/MatchError
	dup
	aload	9
	invokeinterface	InterfaceMethod scala/collection/SeqLike.toString:()Ljava/lang/String;
	invokespecial	Method scala/MatchError."<init>":(Ljava/lang/String;)V
	athrow
l12	aload_3
	invokevirtual	Method scala/Option.get:()Ljava/lang/Object;
	checkcast	class java/lang/String
	astore	4
	iconst_1
	ifeq	l13 // new
	aload_0
	checkcast	class scala/xml/parsing/TokenTests
	getstatic	Field scala/Predef$.MODULE$:Lscala/Predef$;
	aload	4
	invokevirtual	Method scala/Predef$.wrapString:(Ljava/lang/String;)Lscala/collection/immutable/WrappedString;
	invokeinterface	InterfaceMethod scala/xml/parsing/TokenTests.isValidIANAEncoding:(Lscala/collection/Seq;)Z
	ifeq	l14 // aload_0
	new	class scala/Some
	dup
	aload	4
	invokespecial	Method scala/Some."<init>":(Ljava/lang/Object;)V
	astore	8
	iload	6
	iconst_1
	iadd
	istore	6
	goto	l11 // aload
l14	aload_0
	checkcast	class scala/xml/parsing/MarkupParser
	new	class scala/collection/mutable/StringBuilder
	dup
	invokespecial	Method scala/collection/mutable/StringBuilder."<init>":()V
	ldc_w	String \"
	invokevirtual	Method scala/collection/mutable/StringBuilder.append:(Ljava/lang/Object;)Lscala/collection/mutable/StringBuilder;
	aload	4
	invokevirtual	Method scala/collection/mutable/StringBuilder.append:(Ljava/lang/Object;)Lscala/collection/mutable/StringBuilder;
	ldc_w	String \" is not a valid encoding
	invokevirtual	Method scala/collection/mutable/StringBuilder.append:(Ljava/lang/Object;)Lscala/collection/mutable/StringBuilder;
	invokevirtual	Method scala/collection/mutable/StringBuilder.toString:()Ljava/lang/String;
	invokeinterface	InterfaceMethod scala/xml/parsing/MarkupParser.reportSyntaxError:(Ljava/lang/String;)V
l11	aload	5
	invokevirtual	Method scala/xml/MetaData.length:()I
	iload	6
	isub
	iconst_0
	if_icmpeq	l15 // new
	aload_0
	checkcast	class scala/xml/parsing/MarkupParser
	ldc_w	String VersionInfo EncodingDecl? or '?>' expected!
	invokeinterface	InterfaceMethod scala/xml/parsing/MarkupParser.reportSyntaxError:(Ljava/lang/String;)V
l15	new	class scala/Tuple2
	dup
	aload	7
	aload	8
	invokespecial	Method scala/Tuple2."<init>":(Ljava/lang/Object;Ljava/lang/Object;)V
	areturn
l13	new	class scala/MatchError
	dup
	aload	9
	invokeinterface	InterfaceMethod scala/collection/SeqLike.toString:()Ljava/lang/String;
	invokespecial	Method scala/MatchError."<init>":(Ljava/lang/String;)V
	athrow
l9	new	class scala/MatchError
	dup
	aload	10
	invokeinterface	InterfaceMethod scala/collection/SeqLike.toString:()Ljava/lang/String;
	invokespecial	Method scala/MatchError."<init>":(Ljava/lang/String;)V
	athrow
  Labels:
   	l1 = 58 // getstatic
   	l3 = 93 // aload_1
   	l5 = 113 // aload_2
   	l6 = 120 // iconst_1
   	l8 = 145 // new
   	l7 = 160 // iconst_1
   	l4 = 164 // aload_0
   	l2 = 176 // aload
   	l10 = 210 // getstatic
   	l12 = 241 // aload_3
   	l14 = 294 // aload_0
   	l11 = 330 // aload
   	l15 = 354 // new
   	l13 = 366 // new
   	l9 = 381 // new
  LocalVariableTable: 
   Start  Length  Slot  Name   Signature
   0      396      0    $this       Lscala/xml/parsing/MarkupHandler;
   67      109      1    temp21       Lscala/Option;
   381      15      1    temp21       Lscala/Option;
   219      111      3    temp26       Lscala/Option;
   366      15      3    temp26       Lscala/Option;
   250      80      4    temp27       Ljava/lang/String;
   366      15      4    temp27       Ljava/lang/String;
   21      344      5    m       Lscala/xml/MetaData;
   366      30      5    m       Lscala/xml/MetaData;
   24      341      6    n       I
   366      30      6    n       I
   5      360      7    info_ver       Lscala/Option;
   366      30      7    info_ver       Lscala/Option;
   10      355      8    info_enc       Lscala/Option;
   366      30      8    info_enc       Lscala/Option;
   186      156      9    temp24       Lscala/collection/Seq;
   366      15      9    temp24       Lscala/collection/Seq;
   34      157      10    temp19       Lscala/collection/Seq;
   381      15      10    temp19       Lscala/collection/Seq;


public static scala.Tuple3 prolog(scala.xml.parsing.MarkupHandler);
  Signature: (Lscala/xml/parsing/MarkupHandler;)Lscala/Tuple3;
  Code:
   Stack=5, Locals=19, Args_size=1
	iconst_0
	istore	12
	getstatic	Field scala/None$.MODULE$:Lscala/None$;
	astore	13
	getstatic	Field scala/None$.MODULE$:Lscala/None$;
	astore	14
	getstatic	Field scala/None$.MODULE$:Lscala/None$;
	astore	15
	aload_0
	checkcast	class scala/xml/parsing/MarkupParser
	invokeinterface	InterfaceMethod scala/xml/parsing/MarkupParser.xmlProcInstr:()Lscala/xml/MetaData;
	astore	11
	aload_0
	checkcast	class scala/xml/parsing/MarkupParserCommon
	invokeinterface	InterfaceMethod scala/xml/parsing/MarkupParserCommon.xSpaceOpt:()V
	aload	11
	ldc_w	String version
	invokevirtual	Method scala/xml/MetaData.apply:(Ljava/lang/String;)Lscala/collection/Seq;
	astore	18
	aload	18
	ifnonnull	l1 // getstatic
	iconst_1
	ifne	l2 // aload
	new	class scala/MatchError
	dup
	aload	18
	invokeinterface	InterfaceMethod scala/collection/SeqLike.toString:()Ljava/lang/String;
	invokespecial	Method scala/MatchError."<init>":(Ljava/lang/String;)V
	athrow
l1	getstatic	Field scala/xml/Text$.MODULE$:Lscala/xml/Text$;
	aload	18
	invokevirtual	Method scala/xml/Text$.unapply:(Ljava/lang/Object;)Lscala/Option;
	astore_1
	aload_1
	invokevirtual	Method scala/Option.isEmpty:()Z
	ifeq	l3 // aload_1
	iconst_1
	ifne	l4 // aload_0
	new	class scala/MatchError
	dup
	aload	18
	invokeinterface	InterfaceMethod scala/collection/SeqLike.toString:()Ljava/lang/String;
	invokespecial	Method scala/MatchError."<init>":(Ljava/lang/String;)V
	athrow
l3	aload_1
	invokevirtual	Method scala/Option.get:()Ljava/lang/Object;
	ldc_w	String 1.0
	astore_2
	dup
	ifnonnull	l5 // aload_2
	pop
	aload_2
	ifnull	l6 // iconst_1
	goto	l7 // iconst_1
l5	aload_2
	invokevirtual	Method java/lang/Object.equals:(Ljava/lang/Object;)Z
	ifeq	l7 // iconst_1
l6	iconst_1
	ifeq	l8 // new
	new	class scala/Some
	dup
	ldc_w	String 1.0
	invokespecial	Method scala/Some."<init>":(Ljava/lang/Object;)V
	astore	13
	iload	12
	iconst_1
	iadd
	istore	12
	goto	l2 // aload
l8	new	class scala/MatchError
	dup
	aload	18
	invokeinterface	InterfaceMethod scala/collection/SeqLike.toString:()Ljava/lang/String;
	invokespecial	Method scala/MatchError."<init>":(Ljava/lang/String;)V
	athrow
l7	iconst_1
	ifeq	l9 // new
l4	aload_0
	checkcast	class scala/xml/parsing/MarkupParser
	ldc_w	String cannot deal with versions != 1.0
	invokeinterface	InterfaceMethod scala/xml/parsing/MarkupParser.reportSyntaxError:(Ljava/lang/String;)V
l2	aload	11
	ldc_w	String encoding
	invokevirtual	Method scala/xml/MetaData.apply:(Ljava/lang/String;)Lscala/collection/Seq;
	astore	17
	aload	17
	ifnonnull	l10 // getstatic
	iconst_1
	ifne	l11 // aload
	new	class scala/MatchError
	dup
	aload	17
	invokeinterface	InterfaceMethod scala/collection/SeqLike.toString:()Ljava/lang/String;
	invokespecial	Method scala/MatchError."<init>":(Ljava/lang/String;)V
	athrow
l10	getstatic	Field scala/xml/Text$.MODULE$:Lscala/xml/Text$;
	aload	17
	invokevirtual	Method scala/xml/Text$.unapply:(Ljava/lang/Object;)Lscala/Option;
	astore_3
	aload_3
	invokevirtual	Method scala/Option.isEmpty:()Z
	ifeq	l12 // aload_3
	new	class scala/MatchError
	dup
	aload	17
	invokeinterface	InterfaceMethod scala/collection/SeqLike.toString:()Ljava/lang/String;
	invokespecial	Method scala/MatchError."<init>":(Ljava/lang/String;)V
	athrow
l12	aload_3
	invokevirtual	Method scala/Option.get:()Ljava/lang/Object;
	checkcast	class java/lang/String
	astore	4
	iconst_1
	ifeq	l13 // new
	aload_0
	checkcast	class scala/xml/parsing/TokenTests
	getstatic	Field scala/Predef$.MODULE$:Lscala/Predef$;
	aload	4
	invokevirtual	Method scala/Predef$.wrapString:(Ljava/lang/String;)Lscala/collection/immutable/WrappedString;
	invokeinterface	InterfaceMethod scala/xml/parsing/TokenTests.isValidIANAEncoding:(Lscala/collection/Seq;)Z
	ifeq	l14 // aload_0
	new	class scala/Some
	dup
	aload	4
	invokespecial	Method scala/Some."<init>":(Ljava/lang/Object;)V
	astore	14
	iload	12
	iconst_1
	iadd
	istore	12
	goto	l11 // aload
l14	aload_0
	checkcast	class scala/xml/parsing/MarkupParser
	new	class scala/collection/mutable/StringBuilder
	dup
	invokespecial	Method scala/collection/mutable/StringBuilder."<init>":()V
	ldc_w	String \"
	invokevirtual	Method scala/collection/mutable/StringBuilder.append:(Ljava/lang/Object;)Lscala/collection/mutable/StringBuilder;
	aload	4
	invokevirtual	Method scala/collection/mutable/StringBuilder.append:(Ljava/lang/Object;)Lscala/collection/mutable/StringBuilder;
	ldc_w	String \" is not a valid encoding
	invokevirtual	Method scala/collection/mutable/StringBuilder.append:(Ljava/lang/Object;)Lscala/collection/mutable/StringBuilder;
	invokevirtual	Method scala/collection/mutable/StringBuilder.toString:()Ljava/lang/String;
	invokeinterface	InterfaceMethod scala/xml/parsing/MarkupParser.reportSyntaxError:(Ljava/lang/String;)V
l11	aload	11
	ldc_w	String standalone
	invokevirtual	Method scala/xml/MetaData.apply:(Ljava/lang/String;)Lscala/collection/Seq;
	astore	16
	aload	16
	ifnonnull	l15 // getstatic
	iconst_1
	ifne	l16 // aload
	new	class scala/MatchError
	dup
	aload	16
	invokeinterface	InterfaceMethod scala/collection/SeqLike.toString:()Ljava/lang/String;
	invokespecial	Method scala/MatchError."<init>":(Ljava/lang/String;)V
	athrow
l15	getstatic	Field scala/xml/Text$.MODULE$:Lscala/xml/Text$;
	aload	16
	invokevirtual	Method scala/xml/Text$.unapply:(Ljava/lang/Object;)Lscala/Option;
	astore	5
	aload	5
	invokevirtual	Method scala/Option.isEmpty:()Z
	ifeq	l17 // aload
	iconst_1
	ifne	l18 // aload_0
	new	class scala/MatchError
	dup
	aload	16
	invokeinterface	InterfaceMethod scala/collection/SeqLike.toString:()Ljava/lang/String;
	invokespecial	Method scala/MatchError."<init>":(Ljava/lang/String;)V
	athrow
l17	aload	5
	invokevirtual	Method scala/Option.get:()Ljava/lang/Object;
	checkcast	class java/lang/String
	astore	8
	aload	8
	ldc_w	String yes
	astore	6
	dup
	ifnonnull	l19 // aload
	pop
	aload	6
	ifnull	l20 // iconst_1
	goto	l21 // aload
l19	aload	6
	invokevirtual	Method java/lang/Object.equals:(Ljava/lang/Object;)Z
	ifeq	l21 // aload
l20	iconst_1
	ifeq	l22 // new
	new	class scala/Some
	dup
	iconst_1
	istore	7
	iload	7
	invokestatic	Method scala/runtime/BoxesRunTime.boxToBoolean:(Z)Ljava/lang/Boolean;
	invokespecial	Method scala/Some."<init>":(Ljava/lang/Object;)V
	astore	15
	iload	12
	iconst_1
	iadd
	istore	12
	goto	l16 // aload
l22	new	class scala/MatchError
	dup
	aload	16
	invokeinterface	InterfaceMethod scala/collection/SeqLike.toString:()Ljava/lang/String;
	invokespecial	Method scala/MatchError."<init>":(Ljava/lang/String;)V
	athrow
l21	aload	8
	ldc_w	String no
	astore	9
	dup
	ifnonnull	l23 // aload
	pop
	aload	9
	ifnull	l24 // iconst_1
	goto	l25 // iconst_1
l23	aload	9
	invokevirtual	Method java/lang/Object.equals:(Ljava/lang/Object;)Z
	ifeq	l25 // iconst_1
l24	iconst_1
	ifeq	l26 // new
	new	class scala/Some
	dup
	iconst_0
	istore	10
	iload	10
	invokestatic	Method scala/runtime/BoxesRunTime.boxToBoolean:(Z)Ljava/lang/Boolean;
	invokespecial	Method scala/Some."<init>":(Ljava/lang/Object;)V
	astore	15
	iload	12
	iconst_1
	iadd
	istore	12
	goto	l16 // aload
l26	new	class scala/MatchError
	dup
	aload	16
	invokeinterface	InterfaceMethod scala/collection/SeqLike.toString:()Ljava/lang/String;
	invokespecial	Method scala/MatchError."<init>":(Ljava/lang/String;)V
	athrow
l25	iconst_1
	ifeq	l27 // new
l18	aload_0
	checkcast	class scala/xml/parsing/MarkupParser
	ldc_w	String either 'yes' or 'no' expected
	invokeinterface	InterfaceMethod scala/xml/parsing/MarkupParser.reportSyntaxError:(Ljava/lang/String;)V
l16	aload	11
	invokevirtual	Method scala/xml/MetaData.length:()I
	iload	12
	isub
	iconst_0
	if_icmpeq	l28 // new
	aload_0
	checkcast	class scala/xml/parsing/MarkupParser
	ldc_w	String VersionInfo EncodingDecl? SDDecl? or '?>' expected!
	invokeinterface	InterfaceMethod scala/xml/parsing/MarkupParser.reportSyntaxError:(Ljava/lang/String;)V
l28	new	class scala/Tuple3
	dup
	aload	13
	aload	14
	aload	15
	invokespecial	Method scala/Tuple3."<init>":(Ljava/lang/Object;Ljava/lang/Object;Ljava/lang/Object;)V
	areturn
l27	new	class scala/MatchError
	dup
	aload	16
	invokeinterface	InterfaceMethod scala/collection/SeqLike.toString:()Ljava/lang/String;
	invokespecial	Method scala/MatchError."<init>":(Ljava/lang/String;)V
	athrow
l13	new	class scala/MatchError
	dup
	aload	17
	invokeinterface	InterfaceMethod scala/collection/SeqLike.toString:()Ljava/lang/String;
	invokespecial	Method scala/MatchError."<init>":(Ljava/lang/String;)V
	athrow
l9	new	class scala/MatchError
	dup
	aload	18
	invokeinterface	InterfaceMethod scala/collection/SeqLike.toString:()Ljava/lang/String;
	invokespecial	Method scala/MatchError."<init>":(Ljava/lang/String;)V
	athrow
  Labels:
   	l1 = 72 // getstatic
   	l3 = 107 // aload_1
   	l5 = 127 // aload_2
   	l6 = 134 // iconst_1
   	l8 = 159 // new
   	l7 = 174 // iconst_1
   	l4 = 178 // aload_0
   	l2 = 190 // aload
   	l10 = 224 // getstatic
   	l12 = 255 // aload_3
   	l14 = 308 // aload_0
   	l11 = 344 // aload
   	l15 = 378 // getstatic
   	l17 = 415 // aload
   	l19 = 445 // aload
   	l20 = 453 // iconst_1
   	l22 = 483 // new
   	l21 = 498 // aload
   	l23 = 518 // aload
   	l24 = 526 // iconst_1
   	l26 = 556 // new
   	l25 = 571 // iconst_1
   	l18 = 575 // aload_0
   	l16 = 587 // aload
   	l28 = 611 // new
   	l27 = 625 // new
   	l13 = 640 // new
   	l9 = 655 // new
  LocalVariableTable: 
   Start  Length  Slot  Name   Signature
   0      670      0    $this       Lscala/xml/parsing/MarkupHandler;
   81      109      1    temp6       Lscala/Option;
   655      15      1    temp6       Lscala/Option;
   233      111      3    temp11       Lscala/Option;
   640      15      3    temp11       Lscala/Option;
   264      80      4    temp12       Ljava/lang/String;
   640      15      4    temp12       Ljava/lang/String;
   388      199      5    temp15       Lscala/Option;
   625      15      5    temp15       Lscala/Option;
   425      162      8    temp16       Ljava/lang/String;
   625      15      8    temp16       Ljava/lang/String;
   29      595      11    m       Lscala/xml/MetaData;
   625      45      11    m       Lscala/xml/MetaData;
   3      621      12    n       I
   625      45      12    n       I
   8      616      13    info_ver       Lscala/Option;
   625      45      13    info_ver       Lscala/Option;
   13      611      14    info_enc       Lscala/Option;
   625      45      14    info_enc       Lscala/Option;
   18      606      15    info_stdl       Lscala/Option;
   625      45      15    info_stdl       Lscala/Option;
   354      245      16    temp13       Lscala/collection/Seq;
   625      15      16    temp13       Lscala/collection/Seq;
   200      159      17    temp9       Lscala/collection/Seq;
   640      15      17    temp9       Lscala/collection/Seq;
   48      157      18    temp4       Lscala/collection/Seq;
   655      15      18    temp4       Lscala/collection/Seq;


public static scala.xml.MetaData xmlProcInstr(scala.xml.parsing.MarkupHandler);
  Signature: (Lscala/xml/parsing/MarkupHandler;)Lscala/xml/MetaData;
  Code:
   Stack=4, Locals=8, Args_size=1
	aload_0
	checkcast	class scala/xml/parsing/MarkupParserCommon
	getstatic	Field scala/Predef$.MODULE$:Lscala/Predef$;
	ldc_w	String xml
	invokevirtual	Method scala/Predef$.wrapString:(Ljava/lang/String;)Lscala/collection/immutable/WrappedString;
	invokeinterface	InterfaceMethod scala/xml/parsing/MarkupParserCommon.xToken:(Lscala/collection/Seq;)V
	aload_0
	checkcast	class scala/xml/parsing/MarkupParserCommon
	invokeinterface	InterfaceMethod scala/xml/parsing/MarkupParserCommon.xSpace:()V
	aload_0
	checkcast	class scala/xml/parsing/MarkupParser
	getstatic	Field scala/xml/TopScope$.MODULE$:Lscala/xml/TopScope$;
	invokeinterface	InterfaceMethod scala/xml/parsing/MarkupParser.xAttributes:(Lscala/xml/NamespaceBinding;)Lscala/Tuple2;
	astore	7
	aload	7
	ifnull	l1 // new
	aload	7
	invokevirtual	Method scala/Tuple2._1:()Ljava/lang/Object;
	checkcast	class scala/xml/MetaData
	astore_1
	aload	7
	invokevirtual	Method scala/Tuple2._2:()Ljava/lang/Object;
	checkcast	class scala/xml/NamespaceBinding
	astore_2
	iconst_1
	ifeq	l2 // new
	new	class scala/Tuple2
	dup
	aload_1
	aload_2
	invokespecial	Method scala/Tuple2."<init>":(Ljava/lang/Object;Ljava/lang/Object;)V
	astore_3
	aload_3
	invokevirtual	Method scala/Tuple2._1:()Ljava/lang/Object;
	checkcast	class scala/xml/MetaData
	astore	6
	aload_3
	invokevirtual	Method scala/Tuple2._2:()Ljava/lang/Object;
	checkcast	class scala/xml/NamespaceBinding
	astore	4
	aload	4
	getstatic	Field scala/xml/TopScope$.MODULE$:Lscala/xml/TopScope$;
	astore	5
	dup
	ifnonnull	l3 // aload
	pop
	aload	5
	ifnull	l4 // aload_0
	goto	l5 // aload_0
l3	aload	5
	invokevirtual	Method java/lang/Object.equals:(Ljava/lang/Object;)Z
	ifne	l4 // aload_0
l5	aload_0
	checkcast	class scala/xml/parsing/MarkupParser
	ldc_w	String no xmlns definitions here, please.
	invokeinterface	InterfaceMethod scala/xml/parsing/MarkupParser.reportSyntaxError:(Ljava/lang/String;)V
l4	aload_0
	checkcast	class scala/xml/parsing/MarkupParserCommon
	ldc_w	int 63
	invokeinterface	InterfaceMethod scala/xml/parsing/MarkupParserCommon.xToken:(C)V
	aload_0
	checkcast	class scala/xml/parsing/MarkupParserCommon
	ldc	int 62
	invokeinterface	InterfaceMethod scala/xml/parsing/MarkupParserCommon.xToken:(C)V
	aload	6
	areturn
l2	new	class scala/MatchError
	dup
	aload	7
	invokevirtual	Method scala/Tuple2.toString:()Ljava/lang/String;
	invokespecial	Method scala/MatchError."<init>":(Ljava/lang/String;)V
	athrow
l1	new	class scala/MatchError
	dup
	aload	7
	invokevirtual	Method scala/Tuple2.toString:()Ljava/lang/String;
	invokespecial	Method scala/MatchError."<init>":(Ljava/lang/String;)V
	athrow
  Labels:
   	l3 = 116 // aload
   	l5 = 124 // aload_0
   	l4 = 136 // aload_0
   	l2 = 162 // new
   	l1 = 175 // new
  LocalVariableTable: 
   Start  Length  Slot  Name   Signature
   0      188      0    $this       Lscala/xml/parsing/MarkupHandler;
   55      52      1    temp2       Lscala/xml/MetaData;
   162      13      1    temp2       Lscala/xml/MetaData;
   64      43      2    temp3       Lscala/xml/NamespaceBinding;
   162      13      2    temp3       Lscala/xml/NamespaceBinding;
   96      65      4    scp       Lscala/xml/NamespaceBinding;
   87      74      6    md       Lscala/xml/MetaData;
   41      66      7    temp1       Lscala/Tuple2;
   162      26      7    temp1       Lscala/Tuple2;


public static void xHandleError(scala.xml.parsing.MarkupHandler, char, java.lang.String);
  Signature: (Lscala/xml/parsing/MarkupHandler;CLjava/lang/String;)V
  Code:
   Stack=2, Locals=3, Args_size=3
	aload_0
	checkcast	class scala/xml/parsing/MarkupParser
	aload_2
	invokeinterface	InterfaceMethod scala/xml/parsing/MarkupParser.reportSyntaxError:(Ljava/lang/String;)V
	return
  Labels:
  LocalVariableTable: 
   Start  Length  Slot  Name   Signature
   0      11      0    $this       Lscala/xml/parsing/MarkupHandler;
   0      11      1    that       C
   0      11      2    msg       Ljava/lang/String;


}

