Compiled from "MarkupHandler.scala"
public abstract class scala.xml.parsing.MarkupHandler extends java.lang.Object implements scala.util.logging.Logged,scala.ScalaObject
  SourceFile: "MarkupHandler.scala"
  ScalaSig: length = 0x781
   05 00 FFFFFF82 01 06 08 01 02 FFFFFF84 FFFFFF80 FFFFFF80 FFFFFF81 00 09 02 0D
   4D 61 72 6B 75 70 48 61 6E 64 6C 65 72 0A 02 03
   04 01 07 70 61 72 73 69 6E 67 0A 02 05 06 01 03
   78 6D 6C 0A 01 07 01 05 73 63 61 6C 61 03 00 13
   04 00 0A 12 1A 10 02 0B 10 0D 01 0C 0A 02 0D 0E
   01 04 6C 61 6E 67 0A 01 0F 01 04 6A 61 76 61 09
   02 11 0C 02 06 4F 62 6A 65 63 74 10 02 13 18 0D
   01 14 0A 02 15 16 01 07 6C 6F 67 67 69 6E 67 0A
   02 17 06 01 04 75 74 69 6C 09 02 19 14 02 06 4C
   6F 67 67 65 64 10 02 1B 1C 0D 01 06 09 02 1D 06
   02 0B 53 63 61 6C 61 4F 62 6A 65 63 74 08 05 1F
   00 FFFFFF84 00 20 01 06 3C 69 6E 69 74 3E 14 01 21 10
   02 22 00 0D 01 02 08 07 24 00 FFFFFFC2 FFFFFF80 FFFFFF84 00 25 01
   0C 69 73 56 61 6C 69 64 61 74 69 6E 67 15 01 26
   10 02 1B 27 09 02 28 06 02 07 42 6F 6F 6C 65 61
   6E 08 06 2A 00 FFFFFFA0 FFFFFF80 04 26 01 0D 69 73 56 61 6C
   69 64 61 74 69 6E 67 20 08 07 2C 00 FFFFFFC0 FFFFFF80 FFFFFF84 00
   2D 01 05 64 65 63 6C 73 15 01 2E 10 03 2F 37 3A
   0E 02 30 35 0E 02 31 34 0D 01 32 0A 02 33 08 01
   06 3C 72 6F 6F 74 3E 09 01 07 09 02 36 06 01 07
   70 61 63 6B 61 67 65 09 02 38 39 02 04 4C 69 73
   74 0A 02 36 06 10 02 3B 3E 0D 01 3C 0A 02 3D 04
   01 03 64 74 64 09 02 3F 3C 02 04 44 65 63 6C 08
   07 41 00 FFFFFFC0 FFFFFF80 FFFFFF84 00 42 01 09 64 65 63 6C 73 5F
   24 65 71 14 02 43 46 10 02 1B 44 09 02 45 06 02
   04 55 6E 69 74 08 07 47 40 FFFFFF81 FFFFFF80 FFFFFFC0 00 2E 01 03
   78 24 31 08 06 49 00 FFFFFFA0 FFFFFFA0 04 2E 01 06 64 65 63
   6C 73 20 08 07 4B 00 FFFFFFC0 FFFFFF80 FFFFFF84 00 4C 01 03 65 6E
   74 15 01 4D 10 04 4E 53 55 5C 0D 01 4F 0A 02 50
   51 01 07 6D 75 74 61 62 6C 65 0A 02 52 06 01 0A
   63 6F 6C 6C 65 63 74 69 6F 6E 09 02 54 4F 02 03
   4D 61 70 10 02 56 59 0E 02 1B 57 09 02 58 06 01
   06 50 72 65 64 65 66 09 02 5A 5B 02 06 53 74 72
   69 6E 67 0A 02 58 06 10 02 3B 5D 09 02 5E 3C 02
   0A 45 6E 74 69 74 79 44 65 63 6C 08 07 60 00 FFFFFFC0
   FFFFFF80 FFFFFF84 00 61 01 07 65 6E 74 5F 24 65 71 14 02 43
   62 08 07 47 5F FFFFFF81 FFFFFF80 FFFFFFC0 00 4D 08 06 64 00 FFFFFFA0 FFFFFFA0
   04 4D 01 04 65 6E 74 20 08 05 66 00 FFFFFF84 00 67 01
   0E 6C 6F 6F 6B 75 70 45 6C 65 6D 44 65 63 6C 14
   02 68 6B 10 02 3B 69 09 02 6A 3C 02 08 45 6C 65
   6D 44 65 63 6C 08 05 6C 65 FFFFFFC0 00 55 01 05 4C 61
   62 65 6C 08 05 6E 00 FFFFFF84 00 6F 01 0F 72 65 70 6C
   61 63 65 6D 65 6E 74 54 65 78 74 14 02 70 76 10
   02 71 74 0D 01 72 0A 02 73 06 01 02 69 6F 09 02
   75 72 02 06 53 6F 75 72 63 65 08 05 77 6D FFFFFFC0 00
   55 01 0A 65 6E 74 69 74 79 4E 61 6D 65 08 05 79
   00 FFFFFF84 00 7A 01 06 65 6E 64 44 54 44 14 02 43 7B
   08 05 7C 78 FFFFFFC0 00 55 01 01 6E 08 05 7E 00 FFFFFF84 00
   7F 01 09 65 6C 65 6D 53 74 61 72 74 14 0B 43 FFFFFF81
   00 FFFFFF81 05 FFFFFF81 07 FFFFFF81 09 FFFFFF81 0F 08 07 FFFFFF81 01 7D FFFFFFC0 00
   FFFFFF81 02 01 03 70 6F 73 10 03 1B FFFFFF81 03 09 03 FFFFFF81 04
   06 02 03 49 6E 74 08 06 FFFFFF81 06 7D FFFFFFC0 00 55 01 03
   70 72 65 08 06 FFFFFF81 08 7D FFFFFFC0 00 55 01 05 6C 61 62
   65 6C 08 07 FFFFFF81 0A 7D FFFFFFC0 00 FFFFFF81 0B 01 05 61 74 74
   72 73 10 04 FFFFFF81 0C FFFFFF81 0D 0D 01 04 09 03 FFFFFF81 0E 04
   02 08 4D 65 74 61 44 61 74 61 08 07 FFFFFF81 10 7D FFFFFFC0
   00 FFFFFF81 11 01 05 73 63 6F 70 65 10 04 FFFFFF81 0C FFFFFF81 12
   09 03 FFFFFF81 13 04 02 10 4E 61 6D 65 73 70 61 63 65
   42 69 6E 64 69 6E 67 08 07 FFFFFF81 15 00 FFFFFF84 00 FFFFFF81 16
   01 07 65 6C 65 6D 45 6E 64 14 07 43 FFFFFF81 17 FFFFFF81 18
   FFFFFF81 19 08 08 FFFFFF81 01 FFFFFF81 14 FFFFFFC0 00 FFFFFF81 02 08 07 FFFFFF81 06
   FFFFFF81 14 FFFFFFC0 00 55 08 07 FFFFFF81 08 FFFFFF81 14 FFFFFFC0 00 55 08 07
   FFFFFF81 1B 00 FFFFFF86 00 FFFFFF81 1C 01 04 65 6C 65 6D 14 0E FFFFFF81
   1D FFFFFF81 20 FFFFFF81 21 FFFFFF81 22 FFFFFF81 23 FFFFFF81 24 FFFFFF81 25 10 04 FFFFFF81
   0C FFFFFF81 1E 09 03 FFFFFF81 1F 04 02 07 4E 6F 64 65 53 65
   71 08 08 FFFFFF81 01 FFFFFF81 1A FFFFFFC0 00 FFFFFF81 02 08 07 FFFFFF81 06 FFFFFF81
   1A FFFFFFC0 00 55 08 07 FFFFFF81 08 FFFFFF81 1A FFFFFFC0 00 55 08 08 FFFFFF81
   0A FFFFFF81 1A FFFFFFC0 00 FFFFFF81 0B 08 08 FFFFFF81 10 FFFFFF81 1A FFFFFFC0 00 FFFFFF81
   11 08 08 FFFFFF81 26 FFFFFF81 1A FFFFFFC0 00 FFFFFF81 1D 01 04 61 72 67
   73 08 07 FFFFFF81 28 00 FFFFFF86 00 FFFFFF81 29 01 09 70 72 6F 63
   49 6E 73 74 72 14 08 FFFFFF81 1D FFFFFF81 2A FFFFFF81 2B FFFFFF81 2D 08
   08 FFFFFF81 01 FFFFFF81 27 FFFFFFC0 00 FFFFFF81 02 08 07 FFFFFF81 2C FFFFFF81 27 FFFFFFC0
   00 55 01 06 74 61 72 67 65 74 08 07 FFFFFF81 2E FFFFFF81 27
   FFFFFFC0 00 55 01 03 74 78 74 08 07 FFFFFF81 30 00 FFFFFF86 00 FFFFFF81
   31 01 07 63 6F 6D 6D 65 6E 74 14 06 FFFFFF81 1D FFFFFF81 32
   FFFFFF81 33 08 08 FFFFFF81 01 FFFFFF81 2F FFFFFFC0 00 FFFFFF81 02 08 07 FFFFFF81 30
   FFFFFF81 2F FFFFFFC0 00 55 08 07 FFFFFF81 35 00 FFFFFF86 00 FFFFFF81 36 01 09
   65 6E 74 69 74 79 52 65 66 14 06 FFFFFF81 1D FFFFFF81 37 FFFFFF81
   38 08 08 FFFFFF81 01 FFFFFF81 34 FFFFFFC0 00 FFFFFF81 02 08 06 7C FFFFFF81 34
   FFFFFFC0 00 55 08 07 FFFFFF81 3A 00 FFFFFF86 00 FFFFFF81 3B 01 04 74 65
   78 74 14 06 FFFFFF81 1D FFFFFF81 3C FFFFFF81 3D 08 08 FFFFFF81 01 FFFFFF81 39
   FFFFFFC0 00 FFFFFF81 02 08 07 FFFFFF81 2E FFFFFF81 39 FFFFFFC0 00 55 08 07 FFFFFF81
   3F 00 FFFFFF84 00 FFFFFF81 40 01 08 65 6C 65 6D 44 65 63 6C
   14 05 43 FFFFFF81 41 FFFFFF81 42 08 06 7C FFFFFF81 3E FFFFFFC0 00 55 08
   07 FFFFFF81 43 FFFFFF81 3E FFFFFFC0 00 55 01 05 63 6D 73 74 72 08
   07 FFFFFF81 45 00 FFFFFF84 00 FFFFFF81 46 01 0B 61 74 74 4C 69 73
   74 44 65 63 6C 14 05 43 FFFFFF81 47 FFFFFF81 49 08 07 FFFFFF81 48
   FFFFFF81 44 FFFFFFC0 00 55 01 04 6E 61 6D 65 08 08 FFFFFF81 4A FFFFFF81
   44 FFFFFFC0 00 FFFFFF81 4B 01 07 61 74 74 4C 69 73 74 10 04
   2F 37 FFFFFF81 4C 10 03 3B FFFFFF81 4D 09 03 FFFFFF81 4E 3C 02 08
   41 74 74 72 44 65 63 6C 08 07 FFFFFF81 50 00 FFFFFF84 04 FFFFFF81
   51 01 0E 73 6F 6D 65 45 6E 74 69 74 79 44 65 63
   6C 14 07 43 FFFFFF81 52 FFFFFF81 53 FFFFFF81 58 08 07 FFFFFF81 48 FFFFFF81 4F
   FFFFFFC0 00 55 08 08 FFFFFF81 54 FFFFFF81 4F FFFFFFC0 00 FFFFFF81 55 01 04 65
   64 65 66 10 03 3B FFFFFF81 56 09 03 FFFFFF81 57 3C 02 09 45
   6E 74 69 74 79 44 65 66 08 08 FFFFFF81 59 FFFFFF81 4F FFFFFFC0 00
   FFFFFF81 5A 01 01 66 10 07 1B FFFFFF81 5B 55 FFFFFF81 55 5C 09 03
   FFFFFF81 5C 06 02 09 46 75 6E 63 74 69 6F 6E 32 08 07
   FFFFFF81 5E 00 FFFFFF84 00 FFFFFF81 5F 01 13 70 61 72 61 6D 65 74
   65 72 45 6E 74 69 74 79 44 65 63 6C 14 05 43 FFFFFF81
   60 FFFFFF81 61 08 07 FFFFFF81 48 FFFFFF81 5D FFFFFFC0 00 55 08 08 FFFFFF81 54
   FFFFFF81 5D FFFFFFC0 00 FFFFFF81 55 08 07 FFFFFF81 63 00 FFFFFF84 00 FFFFFF81 64 01
   10 70 61 72 73 65 64 45 6E 74 69 74 79 44 65 63
   6C 14 05 43 FFFFFF81 65 FFFFFF81 66 08 07 FFFFFF81 48 FFFFFF81 62 FFFFFFC0 00
   55 08 08 FFFFFF81 54 FFFFFF81 62 FFFFFFC0 00 FFFFFF81 55 08 07 FFFFFF81 68 00
   FFFFFF84 00 FFFFFF81 69 01 0B 70 65 52 65 66 65 72 65 6E 63
   65 14 03 43 FFFFFF81 6A 08 07 FFFFFF81 48 FFFFFF81 67 FFFFFFC0 00 55 08
   07 FFFFFF81 6C 00 FFFFFF84 00 FFFFFF81 6D 01 12 75 6E 70 61 72 73
   65 64 45 6E 74 69 74 79 44 65 63 6C 14 07 43 FFFFFF81
   6E FFFFFF81 6F FFFFFF81 74 08 07 FFFFFF81 48 FFFFFF81 6B FFFFFFC0 00 55 08 08
   FFFFFF81 70 FFFFFF81 6B FFFFFFC0 00 FFFFFF81 71 01 05 65 78 74 49 44 10
   03 3B FFFFFF81 72 09 03 FFFFFF81 73 3C 02 0A 45 78 74 65 72
   6E 61 6C 49 44 08 07 FFFFFF81 75 FFFFFF81 6B FFFFFFC0 00 55 01 05
   6E 6F 74 61 74 08 07 FFFFFF81 77 00 FFFFFF84 00 FFFFFF81 78 01 0C
   6E 6F 74 61 74 69 6F 6E 44 65 63 6C 14 05 43 FFFFFF81
   79 FFFFFF81 7A 08 07 FFFFFF81 75 FFFFFF81 76 FFFFFFC0 00 55 08 08 FFFFFF81 70
   FFFFFF81 76 FFFFFFC0 00 FFFFFF81 71 08 07 FFFFFF81 7C 00 FFFFFF86 00 FFFFFF81 7D 01
   11 72 65 70 6F 72 74 53 79 6E 74 61 78 45 72 72
   6F 72 14 05 43 FFFFFF81 7E FFFFFF81 7F 08 08 FFFFFF81 01 FFFFFF81 7B FFFFFFC0
   00 FFFFFF81 02 08 07 FFFFFF82 00 FFFFFF81 7B FFFFFFC0 00 55 01 03 73 74
   72 
  InnerClass: 
   public final $anon$1=class scala/io/Source$$anon$1 of class scala/io/Source
   public final $anonfun$fromIterable$1=class scala/io/Source$$anonfun$fromIterable$1 of class scala/io/Source
   public final $anonfun$lookupElemDecl$2=class scala/xml/parsing/MarkupHandler$$anonfun$lookupElemDecl$2 of class scala/xml/parsing/MarkupHandler
   public final $anonfun$lookupElemDecl$1=class scala/xml/parsing/MarkupHandler$$anonfun$lookupElemDecl$1 of class scala/xml/parsing/MarkupHandler
   public final $anonfun$parsedEntityDecl$1=class scala/xml/parsing/MarkupHandler$$anonfun$parsedEntityDecl$1 of class scala/xml/parsing/MarkupHandler
   public final $anonfun$parameterEntityDecl$1=class scala/xml/parsing/MarkupHandler$$anonfun$parameterEntityDecl$1 of class scala/xml/parsing/MarkupHandler
  minor version: 0
  major version: 49
  Constant pool:
Asciz	SourceFile;
Asciz	MarkupHandler.scala;
Asciz	ent;
Asciz	Lscala/collection/mutable/Map;;
Asciz	Lscala/collection/mutable/Map<Ljava/lang/String;Lscala/xml/dtd/EntityDecl;>;;
Asciz	Signature;
Asciz	decls;
Asciz	Lscala/collection/immutable/List;;
Asciz	Lscala/collection/immutable/List<Lscala/xml/dtd/Decl;>;;
Asciz	isValidating;
Asciz	Z;
Asciz	<init>;
Asciz	()V;
Asciz	Code;
Asciz	LineNumberTable;
Asciz	java/lang/Object;
class	java/lang/Object
NameAndType	"<init>":()V
Method	java/lang/Object."<init>":()V
Asciz	scala/util/logging/Logged$class;
class	scala/util/logging/Logged$class
Asciz	$init$;
Asciz	(Lscala/util/logging/Logged;)V;
NameAndType	$init$:(Lscala/util/logging/Logged;)V
Method	scala/util/logging/Logged$class.$init$:(Lscala/util/logging/Logged;)V
Asciz	scala/xml/parsing/MarkupHandler;
class	scala/xml/parsing/MarkupHandler
NameAndType	isValidating:Z
Field	scala/xml/parsing/MarkupHandler.isValidating:Z
Asciz	scala/collection/immutable/Nil$;
class	scala/collection/immutable/Nil$
Asciz	MODULE$;
Asciz	Lscala/collection/immutable/Nil$;;
NameAndType	MODULE$:Lscala/collection/immutable/Nil$;
Field	scala/collection/immutable/Nil$.MODULE$:Lscala/collection/immutable/Nil$;
NameAndType	decls:Lscala/collection/immutable/List;
Field	scala/xml/parsing/MarkupHandler.decls:Lscala/collection/immutable/List;
Asciz	scala/collection/mutable/HashMap;
class	scala/collection/mutable/HashMap
Method	scala/collection/mutable/HashMap."<init>":()V
NameAndType	ent:Lscala/collection/mutable/Map;
Field	scala/xml/parsing/MarkupHandler.ent:Lscala/collection/mutable/Map;
Asciz	gd1$1;
Asciz	()Z;
NameAndType	isValidating:()Z
Method	scala/xml/parsing/MarkupHandler.isValidating:()Z
Asciz	reportSyntaxError;
Asciz	(ILjava/lang/String;)V;
Asciz	notationDecl;
Asciz	(Ljava/lang/String;Lscala/xml/dtd/ExternalID;)V;
Asciz	this;
Asciz	Lscala/xml/parsing/MarkupHandler;;
Asciz	notat;
Asciz	Ljava/lang/String;;
Asciz	extID;
Asciz	Lscala/xml/dtd/ExternalID;;
Asciz	LocalVariableTable;
Asciz	unparsedEntityDecl;
Asciz	(Ljava/lang/String;Lscala/xml/dtd/ExternalID;Ljava/lang/String;)V;
Asciz	name;
Asciz	peReference;
Asciz	(Ljava/lang/String;)V;
Asciz	()Lscala/collection/immutable/List;;
NameAndType	decls:()Lscala/collection/immutable/List;
Method	scala/xml/parsing/MarkupHandler.decls:()Lscala/collection/immutable/List;
Asciz	scala/xml/dtd/PEReference;
class	scala/xml/dtd/PEReference
NameAndType	"<init>":(Ljava/lang/String;)V
Method	scala/xml/dtd/PEReference."<init>":(Ljava/lang/String;)V
Asciz	scala/collection/immutable/List;
class	scala/collection/immutable/List
Asciz	$colon$colon;
Asciz	(Ljava/lang/Object;)Lscala/collection/immutable/List;;
NameAndType	$colon$colon:(Ljava/lang/Object;)Lscala/collection/immutable/List;
Method	scala/collection/immutable/List.$colon$colon:(Ljava/lang/Object;)Lscala/collection/immutable/List;
Asciz	decls_$eq;
Asciz	(Lscala/collection/immutable/List;)V;
NameAndType	decls_$eq:(Lscala/collection/immutable/List;)V
Method	scala/xml/parsing/MarkupHandler.decls_$eq:(Lscala/collection/immutable/List;)V
Asciz	parsedEntityDecl;
Asciz	(Ljava/lang/String;Lscala/xml/dtd/EntityDef;)V;
Asciz	scala/xml/parsing/MarkupHandler$$anonfun$parsedEntityDecl$1;
class	scala/xml/parsing/MarkupHandler$$anonfun$parsedEntityDecl$1
Asciz	(Lscala/xml/parsing/MarkupHandler;)V;
NameAndType	"<init>":(Lscala/xml/parsing/MarkupHandler;)V
Method	scala/xml/parsing/MarkupHandler$$anonfun$parsedEntityDecl$1."<init>":(Lscala/xml/parsing/MarkupHandler;)V
Asciz	someEntityDecl;
Asciz	(Ljava/lang/String;Lscala/xml/dtd/EntityDef;Lscala/Function2;)V;
NameAndType	someEntityDecl:(Ljava/lang/String;Lscala/xml/dtd/EntityDef;Lscala/Function2;)V
Method	scala/xml/parsing/MarkupHandler.someEntityDecl:(Ljava/lang/String;Lscala/xml/dtd/EntityDef;Lscala/Function2;)V
Asciz	edef;
Asciz	Lscala/xml/dtd/EntityDef;;
Asciz	parameterEntityDecl;
Asciz	scala/xml/parsing/MarkupHandler$$anonfun$parameterEntityDecl$1;
class	scala/xml/parsing/MarkupHandler$$anonfun$parameterEntityDecl$1
Method	scala/xml/parsing/MarkupHandler$$anonfun$parameterEntityDecl$1."<init>":(Lscala/xml/parsing/MarkupHandler;)V
Asciz	scala/xml/dtd/ExtDef;
class	scala/xml/dtd/ExtDef
NameAndType	gd1$1:()Z
Method	scala/xml/parsing/MarkupHandler.gd1$1:()Z
Asciz	scala/Function2;
class	scala/Function2
Asciz	apply;
Asciz	(Ljava/lang/Object;Ljava/lang/Object;)Ljava/lang/Object;;
NameAndType	apply:(Ljava/lang/Object;Ljava/lang/Object;)Ljava/lang/Object;
InterfaceMethod	scala/Function2.apply:(Ljava/lang/Object;Ljava/lang/Object;)Ljava/lang/Object;
Asciz	scala/xml/dtd/EntityDecl;
class	scala/xml/dtd/EntityDecl
Asciz	()Lscala/collection/mutable/Map;;
NameAndType	ent:()Lscala/collection/mutable/Map;
Method	scala/xml/parsing/MarkupHandler.ent:()Lscala/collection/mutable/Map;
Asciz	scala/collection/mutable/MapLike;
class	scala/collection/mutable/MapLike
Asciz	update;
Asciz	(Ljava/lang/Object;Ljava/lang/Object;)V;
NameAndType	update:(Ljava/lang/Object;Ljava/lang/Object;)V
InterfaceMethod	scala/collection/mutable/MapLike.update:(Ljava/lang/Object;Ljava/lang/Object;)V
Asciz	f;
Asciz	Lscala/Function2;;
Asciz	y;
Asciz	Lscala/xml/dtd/EntityDecl;;
Asciz	(Ljava/lang/String;Lscala/xml/dtd/EntityDef;Lscala/Function2<Ljava/lang/String;Lscala/xml/dtd/EntityDef;Lscala/xml/dtd/EntityDecl;>;)V;
Asciz	attListDecl;
Asciz	(Ljava/lang/String;Lscala/collection/immutable/List;)V;
Asciz	attList;
Asciz	(Ljava/lang/String;Lscala/collection/immutable/List<Lscala/xml/dtd/AttrDecl;>;)V;
Asciz	elemDecl;
Asciz	(Ljava/lang/String;Ljava/lang/String;)V;
Asciz	n;
Asciz	cmstr;
Asciz	text;
Asciz	(ILjava/lang/String;)Lscala/xml/NodeSeq;;
Asciz	entityRef;
Asciz	comment;
Asciz	procInstr;
Asciz	(ILjava/lang/String;Ljava/lang/String;)Lscala/xml/NodeSeq;;
Asciz	elem;
Asciz	(ILjava/lang/String;Ljava/lang/String;Lscala/xml/MetaData;Lscala/xml/NamespaceBinding;Lscala/xml/NodeSeq;)Lscala/xml/NodeSeq;;
Asciz	elemEnd;
Asciz	(ILjava/lang/String;Ljava/lang/String;)V;
Asciz	pos;
Asciz	I;
Asciz	pre;
Asciz	label;
Asciz	elemStart;
Asciz	(ILjava/lang/String;Ljava/lang/String;Lscala/xml/MetaData;Lscala/xml/NamespaceBinding;)V;
Asciz	attrs;
Asciz	Lscala/xml/MetaData;;
Asciz	scope;
Asciz	Lscala/xml/NamespaceBinding;;
Asciz	endDTD;
Asciz	replacementText;
Asciz	(Ljava/lang/String;)Lscala/io/Source;;
Asciz	scala/collection/MapLike;
class	scala/collection/MapLike
Asciz	get;
Asciz	(Ljava/lang/Object;)Lscala/Option;;
NameAndType	get:(Ljava/lang/Object;)Lscala/Option;
InterfaceMethod	scala/collection/MapLike.get:(Ljava/lang/Object;)Lscala/Option;
Asciz	scala/Some;
class	scala/Some
Asciz	x;
Asciz	Ljava/lang/Object;;
NameAndType	x:Ljava/lang/Object;
Field	scala/Some.x:Ljava/lang/Object;
Asciz	scala/xml/dtd/ParsedEntityDecl;
class	scala/xml/dtd/ParsedEntityDecl
Asciz	entdef;
Asciz	()Lscala/xml/dtd/EntityDef;;
NameAndType	entdef:()Lscala/xml/dtd/EntityDef;
Method	scala/xml/dtd/ParsedEntityDecl.entdef:()Lscala/xml/dtd/EntityDef;
Asciz	scala/xml/dtd/IntDef;
class	scala/xml/dtd/IntDef
Asciz	value;
Asciz	()Ljava/lang/String;;
NameAndType	value:()Ljava/lang/String;
Method	scala/xml/dtd/IntDef.value:()Ljava/lang/String;
Asciz	scala/xml/dtd/ParameterEntityDecl;
class	scala/xml/dtd/ParameterEntityDecl
Method	scala/xml/dtd/ParameterEntityDecl.entdef:()Lscala/xml/dtd/EntityDef;
Asciz	 %s ;
String	 %s 
Asciz	scala/collection/immutable/StringOps;
class	scala/collection/immutable/StringOps
Method	scala/collection/immutable/StringOps."<init>":(Ljava/lang/String;)V
Asciz	scala/Predef$;
class	scala/Predef$
Asciz	Lscala/Predef$;;
NameAndType	MODULE$:Lscala/Predef$;
Field	scala/Predef$.MODULE$:Lscala/Predef$;
Asciz	genericWrapArray;
Asciz	(Ljava/lang/Object;)Lscala/collection/mutable/WrappedArray;;
NameAndType	genericWrapArray:(Ljava/lang/Object;)Lscala/collection/mutable/WrappedArray;
Method	scala/Predef$.genericWrapArray:(Ljava/lang/Object;)Lscala/collection/mutable/WrappedArray;
Asciz	scala/collection/immutable/StringLike;
class	scala/collection/immutable/StringLike
Asciz	format;
Asciz	(Lscala/collection/Seq;)Ljava/lang/String;;
NameAndType	format:(Lscala/collection/Seq;)Ljava/lang/String;
InterfaceMethod	scala/collection/immutable/StringLike.format:(Lscala/collection/Seq;)Ljava/lang/String;
Asciz	<!-- %s; -->;
String	<!-- %s; -->
Asciz	scala/None$;
class	scala/None$
Asciz	Lscala/None$;;
NameAndType	MODULE$:Lscala/None$;
Field	scala/None$.MODULE$:Lscala/None$;
Asciz	equals;
Asciz	(Ljava/lang/Object;)Z;
NameAndType	equals:(Ljava/lang/Object;)Z
Method	java/lang/Object.equals:(Ljava/lang/Object;)Z
Asciz	<!-- unknown entity %s; -->;
String	<!-- unknown entity %s; -->
Asciz	wrapString;
Asciz	(Ljava/lang/String;)Lscala/collection/immutable/WrappedString;;
NameAndType	wrapString:(Ljava/lang/String;)Lscala/collection/immutable/WrappedString;
Method	scala/Predef$.wrapString:(Ljava/lang/String;)Lscala/collection/immutable/WrappedString;
Asciz	scala/io/Source$$anon$1;
class	scala/io/Source$$anon$1
Asciz	(Lscala/collection/Iterable;)V;
NameAndType	"<init>":(Lscala/collection/Iterable;)V
Method	scala/io/Source$$anon$1."<init>":(Lscala/collection/Iterable;)V
Asciz	scala/io/Source$$anonfun$fromIterable$1;
class	scala/io/Source$$anonfun$fromIterable$1
Method	scala/io/Source$$anonfun$fromIterable$1."<init>":(Lscala/collection/Iterable;)V
Asciz	withReset;
Asciz	(Lscala/Function0;)Lscala/io/Source;;
NameAndType	withReset:(Lscala/Function0;)Lscala/io/Source;
Method	scala/io/Source$$anon$1.withReset:(Lscala/Function0;)Lscala/io/Source;
Asciz	scala/MatchError;
class	scala/MatchError
Asciz	scala/Option;
class	scala/Option
Asciz	toString;
NameAndType	toString:()Ljava/lang/String;
Method	scala/Option.toString:()Ljava/lang/String;
Method	scala/MatchError."<init>":(Ljava/lang/String;)V
Asciz	entityName;
Asciz	temp12;
Asciz	Lscala/Some;;
Asciz	temp14;
Asciz	Lscala/xml/dtd/ParsedEntityDecl;;
Asciz	temp16;
Asciz	temp17;
Asciz	Lscala/xml/dtd/IntDef;;
Asciz	temp18;
Asciz	temp13;
Asciz	temp19;
Asciz	Lscala/xml/dtd/ParameterEntityDecl;;
Asciz	temp21;
Asciz	temp22;
Asciz	temp23;
Asciz	temp11;
Asciz	Lscala/Option;;
Asciz	lookupElemDecl;
Asciz	(Ljava/lang/String;)Lscala/xml/dtd/ElemDecl;;
Asciz	scala/xml/parsing/MarkupHandler$$anonfun$lookupElemDecl$1;
class	scala/xml/parsing/MarkupHandler$$anonfun$lookupElemDecl$1
Asciz	(Lscala/xml/parsing/MarkupHandler;Ljava/lang/String;)V;
NameAndType	"<init>":(Lscala/xml/parsing/MarkupHandler;Ljava/lang/String;)V
Method	scala/xml/parsing/MarkupHandler$$anonfun$lookupElemDecl$1."<init>":(Lscala/xml/parsing/MarkupHandler;Ljava/lang/String;)V
Asciz	scala/collection/TraversableLike;
class	scala/collection/TraversableLike
Asciz	filter;
Asciz	(Lscala/Function1;)Ljava/lang/Object;;
NameAndType	filter:(Lscala/Function1;)Ljava/lang/Object;
InterfaceMethod	scala/collection/TraversableLike.filter:(Lscala/Function1;)Ljava/lang/Object;
Asciz	scala/collection/LinearSeqLike;
class	scala/collection/LinearSeqLike
Asciz	scala/xml/parsing/MarkupHandler$$anonfun$lookupElemDecl$2;
class	scala/xml/parsing/MarkupHandler$$anonfun$lookupElemDecl$2
Asciz	(Lscala/xml/parsing/MarkupHandler;Ljava/lang/String;Ljava/lang/Object;)V;
NameAndType	"<init>":(Lscala/xml/parsing/MarkupHandler;Ljava/lang/String;Ljava/lang/Object;)V
Method	scala/xml/parsing/MarkupHandler$$anonfun$lookupElemDecl$2."<init>":(Lscala/xml/parsing/MarkupHandler;Ljava/lang/String;Ljava/lang/Object;)V
Asciz	foreach;
Asciz	(Lscala/Function1;)V;
NameAndType	foreach:(Lscala/Function1;)V
InterfaceMethod	scala/collection/LinearSeqLike.foreach:(Lscala/Function1;)V
Asciz	scala/runtime/NonLocalReturnException;
class	scala/runtime/NonLocalReturnException
Asciz	key;
Asciz	()Ljava/lang/Object;;
NameAndType	key:()Ljava/lang/Object;
Method	scala/runtime/NonLocalReturnException.key:()Ljava/lang/Object;
NameAndType	value:()Ljava/lang/Object;
Method	scala/runtime/NonLocalReturnException.value:()Ljava/lang/Object;
Asciz	scala/xml/dtd/ElemDecl;
class	scala/xml/dtd/ElemDecl
Asciz	Label$1;
Asciz	exceptionResult1;
Asciz	Lscala/xml/dtd/ElemDecl;;
Asciz	ent_$eq;
Asciz	(Lscala/collection/mutable/Map;)V;
Asciz	(Lscala/collection/mutable/Map<Ljava/lang/String;Lscala/xml/dtd/EntityDecl;>;)V;
Asciz	()Lscala/collection/mutable/Map<Ljava/lang/String;Lscala/xml/dtd/EntityDecl;>;;
Asciz	(Lscala/collection/immutable/List<Lscala/xml/dtd/Decl;>;)V;
Asciz	()Lscala/collection/immutable/List<Lscala/xml/dtd/Decl;>;;
Asciz	log;
Asciz	(Lscala/util/logging/Logged;Ljava/lang/String;)V;
NameAndType	log:(Lscala/util/logging/Logged;Ljava/lang/String;)V
Method	scala/util/logging/Logged$class.log:(Lscala/util/logging/Logged;Ljava/lang/String;)V
Asciz	msg;
Asciz	ScalaSig;
Asciz	InnerClasses;
Asciz	scala/io/Source;
class	scala/io/Source
Asciz	$anon$1;
Asciz	$anonfun$fromIterable$1;
Asciz	$anonfun$lookupElemDecl$2;
Asciz	$anonfun$lookupElemDecl$1;
Asciz	$anonfun$parsedEntityDecl$1;
Asciz	$anonfun$parameterEntityDecl$1;
Asciz	scala/util/logging/Logged;
class	scala/util/logging/Logged
Asciz	scala/ScalaObject;
class	scala/ScalaObject

{
private scala.collection.mutable.Map ent;
  Signature: Lscala/collection/mutable/Map;
  Signature: length = 0x2
   00 05 

private scala.collection.immutable.List decls;
  Signature: Lscala/collection/immutable/List;
  Signature: length = 0x2
   00 09 

private final boolean isValidating;
  Signature: Z

public scala.xml.parsing.MarkupHandler();
  Signature: ()V
  Code:
   Stack=3, Locals=1, Args_size=1
	aload_0
	invokespecial	Method java/lang/Object."<init>":()V
	aload_0
	invokestatic	Method scala/util/logging/Logged$class.$init$:(Lscala/util/logging/Logged;)V
	aload_0
	iconst_0
	putfield	Field isValidating:Z
	aload_0
	getstatic	Field scala/collection/immutable/Nil$.MODULE$:Lscala/collection/immutable/Nil$;
	putfield	Field decls:Lscala/collection/immutable/List;
	aload_0
	new	class scala/collection/mutable/HashMap
	dup
	invokespecial	Method scala/collection/mutable/HashMap."<init>":()V
	putfield	Field ent:Lscala/collection/mutable/Map;
	return
  Labels:

private final boolean gd1$1();
  Signature: ()Z
  Code:
   Stack=1, Locals=1, Args_size=1
	aload_0
	invokevirtual	Method isValidating:()Z
	ifeq	l1 // iconst_1
	iconst_0
	goto	l2 // ireturn
l1	iconst_1
l2	ireturn
  Labels:
   	l1 = 11 // iconst_1
   	l2 = 12 // ireturn

public abstract void reportSyntaxError(int, java.lang.String);
  Signature: (ILjava/lang/String;)V

public void notationDecl(java.lang.String, scala.xml.dtd.ExternalID);
  Signature: (Ljava/lang/String;Lscala/xml/dtd/ExternalID;)V
  Code:
   Stack=0, Locals=3, Args_size=3
	return
  Labels:
  LocalVariableTable: 
   Start  Length  Slot  Name   Signature
   0      1      0    this       Lscala/xml/parsing/MarkupHandler;
   0      1      1    notat       Ljava/lang/String;
   0      1      2    extID       Lscala/xml/dtd/ExternalID;


public void unparsedEntityDecl(java.lang.String, scala.xml.dtd.ExternalID, java.lang.String);
  Signature: (Ljava/lang/String;Lscala/xml/dtd/ExternalID;Ljava/lang/String;)V
  Code:
   Stack=0, Locals=4, Args_size=4
	return
  Labels:
  LocalVariableTable: 
   Start  Length  Slot  Name   Signature
   0      1      0    this       Lscala/xml/parsing/MarkupHandler;
   0      1      1    name       Ljava/lang/String;
   0      1      2    extID       Lscala/xml/dtd/ExternalID;
   0      1      3    notat       Ljava/lang/String;


public void peReference(java.lang.String);
  Signature: (Ljava/lang/String;)V
  Code:
   Stack=5, Locals=2, Args_size=2
	aload_0
	aload_0
	invokevirtual	Method decls:()Lscala/collection/immutable/List;
	new	class scala/xml/dtd/PEReference
	dup
	aload_1
	invokespecial	Method scala/xml/dtd/PEReference."<init>":(Ljava/lang/String;)V
	invokevirtual	Method scala/collection/immutable/List.$colon$colon:(Ljava/lang/Object;)Lscala/collection/immutable/List;
	invokevirtual	Method decls_$eq:(Lscala/collection/immutable/List;)V
	return
  Labels:
  LocalVariableTable: 
   Start  Length  Slot  Name   Signature
   0      20      0    this       Lscala/xml/parsing/MarkupHandler;
   0      20      1    name       Ljava/lang/String;


public void parsedEntityDecl(java.lang.String, scala.xml.dtd.EntityDef);
  Signature: (Ljava/lang/String;Lscala/xml/dtd/EntityDef;)V
  Code:
   Stack=6, Locals=3, Args_size=3
	aload_0
	aload_1
	aload_2
	new	class scala/xml/parsing/MarkupHandler$$anonfun$parsedEntityDecl$1
	dup
	aload_0
	invokespecial	Method scala/xml/parsing/MarkupHandler$$anonfun$parsedEntityDecl$1."<init>":(Lscala/xml/parsing/MarkupHandler;)V
	invokespecial	Method someEntityDecl:(Ljava/lang/String;Lscala/xml/dtd/EntityDef;Lscala/Function2;)V
	return
  Labels:
  LocalVariableTable: 
   Start  Length  Slot  Name   Signature
   0      15      0    this       Lscala/xml/parsing/MarkupHandler;
   0      15      1    name       Ljava/lang/String;
   0      15      2    edef       Lscala/xml/dtd/EntityDef;


public void parameterEntityDecl(java.lang.String, scala.xml.dtd.EntityDef);
  Signature: (Ljava/lang/String;Lscala/xml/dtd/EntityDef;)V
  Code:
   Stack=6, Locals=3, Args_size=3
	aload_0
	aload_1
	aload_2
	new	class scala/xml/parsing/MarkupHandler$$anonfun$parameterEntityDecl$1
	dup
	aload_0
	invokespecial	Method scala/xml/parsing/MarkupHandler$$anonfun$parameterEntityDecl$1."<init>":(Lscala/xml/parsing/MarkupHandler;)V
	invokespecial	Method someEntityDecl:(Ljava/lang/String;Lscala/xml/dtd/EntityDef;Lscala/Function2;)V
	return
  Labels:
  LocalVariableTable: 
   Start  Length  Slot  Name   Signature
   0      15      0    this       Lscala/xml/parsing/MarkupHandler;
   0      15      1    name       Ljava/lang/String;
   0      15      2    edef       Lscala/xml/dtd/EntityDef;


private void someEntityDecl(java.lang.String, scala.xml.dtd.EntityDef, scala.Function2);
  Signature: (Ljava/lang/String;Lscala/xml/dtd/EntityDef;Lscala/Function2;)V
  Code:
   Stack=3, Locals=5, Args_size=4
	aload_2
	instanceof	class scala/xml/dtd/ExtDef
	ifeq	l1 // aload_3
	aload_0
	invokespecial	Method gd1$1:()Z
	ifne	l2 // return
l1	aload_3
	aload_1
	aload_2
	invokeinterface	InterfaceMethod scala/Function2.apply:(Ljava/lang/Object;Ljava/lang/Object;)Ljava/lang/Object;
	checkcast	class scala/xml/dtd/EntityDecl
	astore	4
	aload_0
	aload_0
	invokevirtual	Method decls:()Lscala/collection/immutable/List;
	aload	4
	invokevirtual	Method scala/collection/immutable/List.$colon$colon:(Ljava/lang/Object;)Lscala/collection/immutable/List;
	invokevirtual	Method decls_$eq:(Lscala/collection/immutable/List;)V
	aload_0
	invokevirtual	Method ent:()Lscala/collection/mutable/Map;
	aload_1
	aload	4
	invokeinterface	InterfaceMethod scala/collection/mutable/MapLike.update:(Ljava/lang/Object;Ljava/lang/Object;)V
l2	return
  Labels:
   	l1 = 14 // aload_3
   	l2 = 52 // return
  LocalVariableTable: 
   Start  Length  Slot  Name   Signature
   0      53      0    this       Lscala/xml/parsing/MarkupHandler;
   0      53      1    name       Ljava/lang/String;
   0      53      2    edef       Lscala/xml/dtd/EntityDef;
   0      53      3    f       Lscala/Function2;
   27      25      4    y       Lscala/xml/dtd/EntityDecl;

  Signature: length = 0x2
   00 7A 

public void attListDecl(java.lang.String, scala.collection.immutable.List);
  Signature: (Ljava/lang/String;Lscala/collection/immutable/List;)V
  Code:
   Stack=0, Locals=3, Args_size=3
	return
  Labels:
  LocalVariableTable: 
   Start  Length  Slot  Name   Signature
   0      1      0    this       Lscala/xml/parsing/MarkupHandler;
   0      1      1    name       Ljava/lang/String;
   0      1      2    attList       Lscala/collection/immutable/List;

  Signature: length = 0x2
   00 7E 

public void elemDecl(java.lang.String, java.lang.String);
  Signature: (Ljava/lang/String;Ljava/lang/String;)V
  Code:
   Stack=0, Locals=3, Args_size=3
	return
  Labels:
  LocalVariableTable: 
   Start  Length  Slot  Name   Signature
   0      1      0    this       Lscala/xml/parsing/MarkupHandler;
   0      1      1    n       Ljava/lang/String;
   0      1      2    cmstr       Ljava/lang/String;


public abstract scala.xml.NodeSeq text(int, java.lang.String);
  Signature: (ILjava/lang/String;)Lscala/xml/NodeSeq;

public abstract scala.xml.NodeSeq entityRef(int, java.lang.String);
  Signature: (ILjava/lang/String;)Lscala/xml/NodeSeq;

public abstract scala.xml.NodeSeq comment(int, java.lang.String);
  Signature: (ILjava/lang/String;)Lscala/xml/NodeSeq;

public abstract scala.xml.NodeSeq procInstr(int, java.lang.String, java.lang.String);
  Signature: (ILjava/lang/String;Ljava/lang/String;)Lscala/xml/NodeSeq;

public abstract scala.xml.NodeSeq elem(int, java.lang.String, java.lang.String, scala.xml.MetaData, scala.xml.NamespaceBinding, scala.xml.NodeSeq);
  Signature: (ILjava/lang/String;Ljava/lang/String;Lscala/xml/MetaData;Lscala/xml/NamespaceBinding;Lscala/xml/NodeSeq;)Lscala/xml/NodeSeq;

public void elemEnd(int, java.lang.String, java.lang.String);
  Signature: (ILjava/lang/String;Ljava/lang/String;)V
  Code:
   Stack=0, Locals=4, Args_size=4
	return
  Labels:
  LocalVariableTable: 
   Start  Length  Slot  Name   Signature
   0      1      0    this       Lscala/xml/parsing/MarkupHandler;
   0      1      1    pos       I
   0      1      2    pre       Ljava/lang/String;
   0      1      3    label       Ljava/lang/String;


public void elemStart(int, java.lang.String, java.lang.String, scala.xml.MetaData, scala.xml.NamespaceBinding);
  Signature: (ILjava/lang/String;Ljava/lang/String;Lscala/xml/MetaData;Lscala/xml/NamespaceBinding;)V
  Code:
   Stack=0, Locals=6, Args_size=6
	return
  Labels:
  LocalVariableTable: 
   Start  Length  Slot  Name   Signature
   0      1      0    this       Lscala/xml/parsing/MarkupHandler;
   0      1      1    pos       I
   0      1      2    pre       Ljava/lang/String;
   0      1      3    label       Ljava/lang/String;
   0      1      4    attrs       Lscala/xml/MetaData;
   0      1      5    scope       Lscala/xml/NamespaceBinding;


public void endDTD(java.lang.String);
  Signature: (Ljava/lang/String;)V
  Code:
   Stack=0, Locals=2, Args_size=2
	return
  Labels:
  LocalVariableTable: 
   Start  Length  Slot  Name   Signature
   0      1      0    this       Lscala/xml/parsing/MarkupHandler;
   0      1      1    n       Ljava/lang/String;


public scala.io.Source replacementText(java.lang.String);
  Signature: (Ljava/lang/String;)Lscala/io/Source;
  Code:
   Stack=6, Locals=18, Args_size=2
	aload_0
	invokevirtual	Method ent:()Lscala/collection/mutable/Map;
	aload_1
	invokeinterface	InterfaceMethod scala/collection/MapLike.get:(Ljava/lang/Object;)Lscala/Option;
	astore	17
	aload	17
	instanceof	class scala/Some
	ifeq	l1 // getstatic
	aload	17
	checkcast	class scala/Some
	astore_2
	aload_2
	getfield	Field scala/Some.x:Ljava/lang/Object;
	checkcast	class scala/xml/dtd/EntityDecl
	astore	7
	aload	7
	instanceof	class scala/xml/dtd/ParsedEntityDecl
	ifeq	l2 // aload
	aload	7
	checkcast	class scala/xml/dtd/ParsedEntityDecl
	astore_3
	aload_3
	invokevirtual	Method scala/xml/dtd/ParsedEntityDecl.entdef:()Lscala/xml/dtd/EntityDef;
	astore	4
	aload	4
	instanceof	class scala/xml/dtd/IntDef
	ifeq	l3 // ldc
	aload	4
	checkcast	class scala/xml/dtd/IntDef
	astore	5
	aload	5
	invokevirtual	Method scala/xml/dtd/IntDef.value:()Ljava/lang/String;
	astore	6
	aload	6
	goto	l4 // astore
l2	aload	7
	instanceof	class scala/xml/dtd/ParameterEntityDecl
	ifeq	l3 // ldc
	aload	7
	checkcast	class scala/xml/dtd/ParameterEntityDecl
	astore	8
	aload	8
	invokevirtual	Method scala/xml/dtd/ParameterEntityDecl.entdef:()Lscala/xml/dtd/EntityDef;
	astore	9
	aload	9
	instanceof	class scala/xml/dtd/IntDef
	ifeq	l3 // ldc
	aload	9
	checkcast	class scala/xml/dtd/IntDef
	astore	10
	aload	10
	invokevirtual	Method scala/xml/dtd/IntDef.value:()Ljava/lang/String;
	astore	12
	ldc	String  %s 
	astore	11
	new	class scala/collection/immutable/StringOps
	dup
	aload	11
	invokespecial	Method scala/collection/immutable/StringOps."<init>":(Ljava/lang/String;)V
	getstatic	Field scala/Predef$.MODULE$:Lscala/Predef$;
	iconst_1
	anewarray	class java/lang/Object
	dup
	iconst_0
	aload	12
	aastore
	invokevirtual	Method scala/Predef$.genericWrapArray:(Ljava/lang/Object;)Lscala/collection/mutable/WrappedArray;
	invokeinterface	InterfaceMethod scala/collection/immutable/StringLike.format:(Lscala/collection/Seq;)Ljava/lang/String;
	goto	l4 // astore
l3	ldc	String <!-- %s; -->
	astore	13
	new	class scala/collection/immutable/StringOps
	dup
	aload	13
	invokespecial	Method scala/collection/immutable/StringOps."<init>":(Ljava/lang/String;)V
	getstatic	Field scala/Predef$.MODULE$:Lscala/Predef$;
	iconst_1
	anewarray	class java/lang/Object
	dup
	iconst_0
	aload_1
	aastore
	invokevirtual	Method scala/Predef$.genericWrapArray:(Ljava/lang/Object;)Lscala/collection/mutable/WrappedArray;
	invokeinterface	InterfaceMethod scala/collection/immutable/StringLike.format:(Lscala/collection/Seq;)Ljava/lang/String;
	goto	l4 // astore
l1	getstatic	Field scala/None$.MODULE$:Lscala/None$;
	dup
	ifnonnull	l5 // aload
	pop
	aload	17
	ifnull	l6 // ldc
	goto	l7 // new
l5	aload	17
	invokevirtual	Method java/lang/Object.equals:(Ljava/lang/Object;)Z
	ifeq	l7 // new
l6	ldc	String <!-- unknown entity %s; -->
	astore	14
	new	class scala/collection/immutable/StringOps
	dup
	aload	14
	invokespecial	Method scala/collection/immutable/StringOps."<init>":(Ljava/lang/String;)V
	getstatic	Field scala/Predef$.MODULE$:Lscala/Predef$;
	iconst_1
	anewarray	class java/lang/Object
	dup
	iconst_0
	aload_1
	aastore
	invokevirtual	Method scala/Predef$.genericWrapArray:(Ljava/lang/Object;)Lscala/collection/mutable/WrappedArray;
	invokeinterface	InterfaceMethod scala/collection/immutable/StringLike.format:(Lscala/collection/Seq;)Ljava/lang/String;
l4	astore	15
	getstatic	Field scala/Predef$.MODULE$:Lscala/Predef$;
	aload	15
	invokevirtual	Method scala/Predef$.wrapString:(Ljava/lang/String;)Lscala/collection/immutable/WrappedString;
	astore	16
	new	class scala/io/Source$$anon$1
	dup
	aload	16
	invokespecial	Method scala/io/Source$$anon$1."<init>":(Lscala/collection/Iterable;)V
	new	class scala/io/Source$$anonfun$fromIterable$1
	dup
	aload	16
	invokespecial	Method scala/io/Source$$anonfun$fromIterable$1."<init>":(Lscala/collection/Iterable;)V
	invokevirtual	Method scala/io/Source$$anon$1.withReset:(Lscala/Function0;)Lscala/io/Source;
	areturn
l7	new	class scala/MatchError
	dup
	aload	17
	invokevirtual	Method scala/Option.toString:()Ljava/lang/String;
	invokespecial	Method scala/MatchError."<init>":(Ljava/lang/String;)V
	athrow
  Labels:
   	l2 = 82 // aload
   	l3 = 162 // ldc
   	l1 = 197 // getstatic
   	l5 = 213 // aload
   	l6 = 221 // ldc
   	l4 = 253 // astore
   	l7 = 287 // new
  LocalVariableTable: 
   Start  Length  Slot  Name   Signature
   0      300      0    this       Lscala/xml/parsing/MarkupHandler;
   0      300      1    entityName       Ljava/lang/String;
   26      171      2    temp12       Lscala/Some;
   49      33      3    temp14       Lscala/xml/dtd/ParsedEntityDecl;
   162      35      3    temp14       Lscala/xml/dtd/ParsedEntityDecl;
   55      27      4    temp16       Lscala/xml/dtd/EntityDef;
   162      35      4    temp16       Lscala/xml/dtd/EntityDef;
   70      9      5    temp17       Lscala/xml/dtd/IntDef;
   77      2      6    temp18       Ljava/lang/String;
   35      162      7    temp13       Lscala/xml/dtd/EntityDecl;
   97      65      8    temp19       Lscala/xml/dtd/ParameterEntityDecl;
   104      58      9    temp21       Lscala/xml/dtd/EntityDef;
   119      40      10    temp22       Lscala/xml/dtd/IntDef;
   126      33      12    temp23       Ljava/lang/String;
   12      288      17    temp11       Lscala/Option;


public scala.xml.dtd.ElemDecl lookupElemDecl(java.lang.String);
  Signature: (Ljava/lang/String;)Lscala/xml/dtd/ElemDecl;
  Code:
   Stack=6, Locals=5, Args_size=2
	new	class java/lang/Object
	dup
	invokespecial	Method java/lang/Object."<init>":()V
	astore_2
	aload_0
	invokevirtual	Method decls:()Lscala/collection/immutable/List;
	new	class scala/xml/parsing/MarkupHandler$$anonfun$lookupElemDecl$1
	dup
	aload_0
	aload_1
	invokespecial	Method scala/xml/parsing/MarkupHandler$$anonfun$lookupElemDecl$1."<init>":(Lscala/xml/parsing/MarkupHandler;Ljava/lang/String;)V
	invokeinterface	InterfaceMethod scala/collection/TraversableLike.filter:(Lscala/Function1;)Ljava/lang/Object;
	checkcast	class scala/collection/LinearSeqLike
	new	class scala/xml/parsing/MarkupHandler$$anonfun$lookupElemDecl$2
	dup
	aload_0
	aload_1
	aload_2
	invokespecial	Method scala/xml/parsing/MarkupHandler$$anonfun$lookupElemDecl$2."<init>":(Lscala/xml/parsing/MarkupHandler;Ljava/lang/String;Ljava/lang/Object;)V
	invokeinterface	InterfaceMethod scala/collection/LinearSeqLike.foreach:(Lscala/Function1;)V
	aconst_null
	astore_3
	goto	l1 // aload_3
	astore	4
	aload	4
	invokevirtual	Method scala/runtime/NonLocalReturnException.key:()Ljava/lang/Object;
	aload_2
	if_acmpne	l2 // aload
	aload	4
	invokevirtual	Method scala/runtime/NonLocalReturnException.value:()Ljava/lang/Object;
	checkcast	class scala/xml/dtd/ElemDecl
	astore_3
l1	aload_3
	areturn
l2	aload	4
	athrow
  Labels:
   	l1 = 69 // aload_3
   	l2 = 71 // aload
  Exception table:
   from   to  target type
     8    49    49   Class scala/runtime/NonLocalReturnException

  LocalVariableTable: 
   Start  Length  Slot  Name   Signature
   0      74      0    this       Lscala/xml/parsing/MarkupHandler;
   0      74      1    Label$1       Ljava/lang/String;
   8      62      3    exceptionResult1       Lscala/xml/dtd/ElemDecl;
   71      3      3    exceptionResult1       Lscala/xml/dtd/ElemDecl;


public void ent_$eq(scala.collection.mutable.Map);
  Signature: (Lscala/collection/mutable/Map;)V
  Code:
   Stack=2, Locals=2, Args_size=2
	aload_0
	aload_1
	putfield	Field ent:Lscala/collection/mutable/Map;
	return
  Labels:
  Signature: length = 0x2
   01 26 

public scala.collection.mutable.Map ent();
  Signature: ()Lscala/collection/mutable/Map;
  Code:
   Stack=1, Locals=1, Args_size=1
	aload_0
	getfield	Field ent:Lscala/collection/mutable/Map;
	areturn
  Labels:
  Signature: length = 0x2
   01 27 

public void decls_$eq(scala.collection.immutable.List);
  Signature: (Lscala/collection/immutable/List;)V
  Code:
   Stack=2, Locals=2, Args_size=2
	aload_0
	aload_1
	putfield	Field decls:Lscala/collection/immutable/List;
	return
  Labels:
  Signature: length = 0x2
   01 28 

public scala.collection.immutable.List decls();
  Signature: ()Lscala/collection/immutable/List;
  Code:
   Stack=1, Locals=1, Args_size=1
	aload_0
	getfield	Field decls:Lscala/collection/immutable/List;
	areturn
  Labels:
  Signature: length = 0x2
   01 29 

public boolean isValidating();
  Signature: ()Z
  Code:
   Stack=1, Locals=1, Args_size=1
	aload_0
	getfield	Field isValidating:Z
	ireturn
  Labels:

public void log(java.lang.String);
  Signature: (Ljava/lang/String;)V
  Code:
   Stack=2, Locals=2, Args_size=2
	aload_0
	aload_1
	invokestatic	Method scala/util/logging/Logged$class.log:(Lscala/util/logging/Logged;Ljava/lang/String;)V
	return
  Labels:
  LocalVariableTable: 
   Start  Length  Slot  Name   Signature
   0      6      0    this       Lscala/xml/parsing/MarkupHandler;
   0      6      1    msg       Ljava/lang/String;


}

