Compiled from "MarkupParser.scala"
public final class scala.xml.parsing.MarkupParser$$anonfun$4 extends java.lang.Object implements scala.Function0,scala.ScalaObject,java.io.Serializable
  SourceFile: "MarkupParser.scala"
  Scala: length = 0x
   
  InnerClass: 
   public final #74= #9 of #73; //$anonfun$4=class scala/xml/parsing/MarkupParser$$anonfun$4 of class scala/xml/parsing/MarkupParser
  minor version: 0
  major version: 49
  Constant pool:
const #1 = Asciz	SourceFile;
const #2 = Asciz	MarkupParser.scala;
const #3 = Asciz	<clinit>;
const #4 = Asciz	()V;
const #5 = Asciz	Code;
const #6 = Asciz	serialVersionUID;
const #7 = Asciz	J;
const #8 = Asciz	scala/xml/parsing/MarkupParser$$anonfun$4;
const #9 = class	#8;	//  scala/xml/parsing/MarkupParser$$anonfun$4
const #10 = NameAndType	#6:#7;//  serialVersionUID:J
const #11 = Field	#9.#10;	//  scala/xml/parsing/MarkupParser$$anonfun$4.serialVersionUID:J
const #12 = Asciz	c$1;
const #13 = Asciz	Lscala/runtime/CharRef;;
const #14 = Asciz	it$1;
const #15 = Asciz	Lscala/collection/Iterator;;
const #16 = Asciz	<init>;
const #17 = Asciz	(Lscala/xml/parsing/MarkupParser;Lscala/collection/Iterator;Lscala/runtime/CharRef;)V;
const #18 = Asciz	LineNumberTable;
const #19 = NameAndType	#14:#15;//  it$1:Lscala/collection/Iterator;
const #20 = Field	#9.#19;	//  scala/xml/parsing/MarkupParser$$anonfun$4.it$1:Lscala/collection/Iterator;
const #21 = NameAndType	#12:#13;//  c$1:Lscala/runtime/CharRef;
const #22 = Field	#9.#21;	//  scala/xml/parsing/MarkupParser$$anonfun$4.c$1:Lscala/runtime/CharRef;
const #23 = Asciz	java/lang/Object;
const #24 = class	#23;	//  java/lang/Object
const #25 = NameAndType	#16:#4;//  "<init>":()V
const #26 = Method	#24.#25;	//  java/lang/Object."<init>":()V
const #27 = Asciz	scala/Function0$class;
const #28 = class	#27;	//  scala/Function0$class
const #29 = Asciz	$init$;
const #30 = Asciz	(Lscala/Function0;)V;
const #31 = NameAndType	#29:#30;//  $init$:(Lscala/Function0;)V
const #32 = Method	#28.#31;	//  scala/Function0$class.$init$:(Lscala/Function0;)V
const #33 = Asciz	this;
const #34 = Asciz	Lscala/xml/parsing/MarkupParser$$anonfun$4;;
const #35 = Asciz	$outer;
const #36 = Asciz	Lscala/xml/parsing/MarkupParser;;
const #37 = Asciz	LocalVariableTable;
const #38 = Asciz	apply;
const #39 = Asciz	()Ljava/lang/Object;;
const #40 = NameAndType	#38:#4;//  apply:()V
const #41 = Method	#9.#40;	//  scala/xml/parsing/MarkupParser$$anonfun$4.apply:()V
const #42 = Asciz	scala/runtime/BoxedUnit;
const #43 = class	#42;	//  scala/runtime/BoxedUnit
const #44 = Asciz	UNIT;
const #45 = Asciz	Lscala/runtime/BoxedUnit;;
const #46 = NameAndType	#44:#45;//  UNIT:Lscala/runtime/BoxedUnit;
const #47 = Field	#43.#46;	//  scala/runtime/BoxedUnit.UNIT:Lscala/runtime/BoxedUnit;
const #48 = Asciz	scala/collection/Iterator;
const #49 = class	#48;	//  scala/collection/Iterator
const #50 = Asciz	next;
const #51 = NameAndType	#50:#39;//  next:()Ljava/lang/Object;
const #52 = InterfaceMethod	#49.#51;	//  scala/collection/Iterator.next:()Ljava/lang/Object;
const #53 = Asciz	scala/runtime/BoxesRunTime;
const #54 = class	#53;	//  scala/runtime/BoxesRunTime
const #55 = Asciz	unboxToChar;
const #56 = Asciz	(Ljava/lang/Object;)C;
const #57 = NameAndType	#55:#56;//  unboxToChar:(Ljava/lang/Object;)C
const #58 = Method	#54.#57;	//  scala/runtime/BoxesRunTime.unboxToChar:(Ljava/lang/Object;)C
const #59 = Asciz	scala/runtime/CharRef;
const #60 = class	#59;	//  scala/runtime/CharRef
const #61 = Asciz	elem;
const #62 = Asciz	C;
const #63 = NameAndType	#61:#62;//  elem:C
const #64 = Field	#60.#63;	//  scala/runtime/CharRef.elem:C
const #65 = Asciz	toString;
const #66 = Asciz	()Ljava/lang/String;;
const #67 = Asciz	(Lscala/Function0;)Ljava/lang/String;;
const #68 = NameAndType	#65:#67;//  toString:(Lscala/Function0;)Ljava/lang/String;
const #69 = Method	#28.#68;	//  scala/Function0$class.toString:(Lscala/Function0;)Ljava/lang/String;
const #70 = Asciz	Scala;
const #71 = Asciz	InnerClasses;
const #72 = Asciz	scala/xml/parsing/MarkupParser;
const #73 = class	#72;	//  scala/xml/parsing/MarkupParser
const #74 = Asciz	$anonfun$4;
const #75 = Asciz	scala/Function0;
const #76 = class	#75;	//  scala/Function0
const #77 = Asciz	scala/ScalaObject;
const #78 = class	#77;	//  scala/ScalaObject
const #79 = Asciz	java/io/Serializable;
const #80 = class	#79;	//  java/io/Serializable

{
public static final long serialVersionUID;

public static {};
  Code:
   Stack=2, Locals=0, Args_size=0
   0:	lconst_0
   1:	putstatic	#11; //Field serialVersionUID:J
   4:	return

public scala.xml.parsing.MarkupParser$$anonfun$4(scala.xml.parsing.MarkupParser, scala.collection.Iterator, scala.runtime.CharRef);
  Code:
   Stack=2, Locals=4, Args_size=4
   0:	aload_0
   1:	aload_2
   2:	putfield	#20; //Field it$1:Lscala/collection/Iterator;
   5:	aload_0
   6:	aload_3
   7:	putfield	#22; //Field c$1:Lscala/runtime/CharRef;
   10:	aload_0
   11:	invokespecial	#26; //Method java/lang/Object."<init>":()V
   14:	aload_0
   15:	invokestatic	#32; //Method scala/Function0$class.$init$:(Lscala/Function0;)V
   18:	return
  LineNumberTable: 
   line 1129: 0

  LocalVariableTable: 
   Start  Length  Slot  Name   Signature
   0      19      0    this       Lscala/xml/parsing/MarkupParser$$anonfun$4;
   0      19      1    $outer       Lscala/xml/parsing/MarkupParser;


public final java.lang.Object apply();
  Code:
   Stack=1, Locals=1, Args_size=1
   0:	aload_0
   1:	invokevirtual	#41; //Method apply:()V
   4:	getstatic	#47; //Field scala/runtime/BoxedUnit.UNIT:Lscala/runtime/BoxedUnit;
   7:	areturn
  LineNumberTable: 
   line 1129: 0


public final void apply();
  Code:
   Stack=2, Locals=1, Args_size=1
   0:	aload_0
   1:	getfield	#22; //Field c$1:Lscala/runtime/CharRef;
   4:	aload_0
   5:	getfield	#20; //Field it$1:Lscala/collection/Iterator;
   8:	invokeinterface	#52,  1; //InterfaceMethod scala/collection/Iterator.next:()Ljava/lang/Object;
   13:	invokestatic	#58; //Method scala/runtime/BoxesRunTime.unboxToChar:(Ljava/lang/Object;)C
   16:	putfield	#64; //Field scala/runtime/CharRef.elem:C
   19:	return
  LineNumberTable: 
   line 1129: 0


public java.lang.String toString();
  Code:
   Stack=1, Locals=1, Args_size=1
   0:	aload_0
   1:	invokestatic	#69; //Method scala/Function0$class.toString:(Lscala/Function0;)Ljava/lang/String;
   4:	areturn
  LineNumberTable: 
   line 1129: 0


}

