Compiled from "MarkupParser.scala"
public final class scala.xml.parsing.MarkupParser$$anonfun$xCharData$2 extends scala.runtime.AbstractFunction0 implements java.io.Serializable
  SourceFile: "MarkupParser.scala"
  Scala: length = 0x
   
  InnerClass: 
   public final $anonfun$xCharData$2=class scala/xml/parsing/MarkupParser$$anonfun$xCharData$2 of class scala/xml/parsing/MarkupParser
  minor version: 0
  major version: 49
  Constant pool:
Asciz	SourceFile;
Asciz	MarkupParser.scala;
Asciz	<clinit>;
Asciz	()V;
Asciz	Code;
Asciz	serialVersionUID;
Asciz	J;
Asciz	scala/xml/parsing/MarkupParser$$anonfun$xCharData$2;
class	scala/xml/parsing/MarkupParser$$anonfun$xCharData$2
NameAndType	serialVersionUID:J
Field	scala/xml/parsing/MarkupParser$$anonfun$xCharData$2.serialVersionUID:J
Asciz	$outer;
Asciz	Lscala/xml/parsing/MarkupHandler;;
Asciz	<init>;
Asciz	(Lscala/xml/parsing/MarkupHandler;)V;
Asciz	LineNumberTable;
Asciz	java/lang/NullPointerException;
class	java/lang/NullPointerException
NameAndType	"<init>":()V
Method	java/lang/NullPointerException."<init>":()V
NameAndType	$outer:Lscala/xml/parsing/MarkupHandler;
Field	scala/xml/parsing/MarkupParser$$anonfun$xCharData$2.$outer:Lscala/xml/parsing/MarkupHandler;
Asciz	scala/runtime/AbstractFunction0;
class	scala/runtime/AbstractFunction0
Method	scala/runtime/AbstractFunction0."<init>":()V
Asciz	this;
Asciz	Lscala/xml/parsing/MarkupParser$$anonfun$xCharData$2;;
Asciz	LocalVariableTable;
Asciz	apply;
Asciz	()Ljava/lang/Object;;
Asciz	()I;
NameAndType	apply:()I
Method	scala/xml/parsing/MarkupParser$$anonfun$xCharData$2.apply:()I
Asciz	scala/runtime/BoxesRunTime;
class	scala/runtime/BoxesRunTime
Asciz	boxToInteger;
Asciz	(I)Ljava/lang/Integer;;
NameAndType	boxToInteger:(I)Ljava/lang/Integer;
Method	scala/runtime/BoxesRunTime.boxToInteger:(I)Ljava/lang/Integer;
Asciz	scala/xml/parsing/MarkupParser;
class	scala/xml/parsing/MarkupParser
Asciz	pos;
NameAndType	pos:()I
InterfaceMethod	scala/xml/parsing/MarkupParser.pos:()I
Asciz	Scala;
Asciz	InnerClasses;
Asciz	$anonfun$xCharData$2;
Asciz	java/io/Serializable;
class	java/io/Serializable

{
public static final long serialVersionUID;
  Signature: J

public final scala.xml.parsing.MarkupHandler $outer;
  Signature: Lscala/xml/parsing/MarkupHandler;

public static {};
  Signature: ()V
  Code:
   Stack=2, Locals=0, Args_size=0
	lconst_0
	putstatic	Field serialVersionUID:J
	return
  Labels:

public scala.xml.parsing.MarkupParser$$anonfun$xCharData$2(scala.xml.parsing.MarkupHandler);
  Signature: (Lscala/xml/parsing/MarkupHandler;)V
  Code:
   Stack=2, Locals=2, Args_size=2
	aload_1
	ifnonnull	l1 // aload_0
	new	class java/lang/NullPointerException
	dup
	invokespecial	Method java/lang/NullPointerException."<init>":()V
	athrow
l1	aload_0
	aload_1
	putfield	Field $outer:Lscala/xml/parsing/MarkupHandler;
	aload_0
	invokespecial	Method scala/runtime/AbstractFunction0."<init>":()V
	return
  Labels:
   	l1 = 12 // aload_0
  LocalVariableTable: 
   Start  Length  Slot  Name   Signature
   0      22      0    this       Lscala/xml/parsing/MarkupParser$$anonfun$xCharData$2;
   0      22      1    $outer       Lscala/xml/parsing/MarkupHandler;


public final java.lang.Object apply();
  Signature: ()Ljava/lang/Object;
  Code:
   Stack=1, Locals=2, Args_size=1
	aload_0
	invokevirtual	Method apply:()I
	istore_1
	iload_1
	invokestatic	Method scala/runtime/BoxesRunTime.boxToInteger:(I)Ljava/lang/Integer;
	areturn
  Labels:

public final int apply();
  Signature: ()I
  Code:
   Stack=1, Locals=1, Args_size=1
	aload_0
	getfield	Field $outer:Lscala/xml/parsing/MarkupHandler;
	checkcast	class scala/xml/parsing/MarkupParser
	invokeinterface	InterfaceMethod scala/xml/parsing/MarkupParser.pos:()I
	ireturn
  Labels:

}

