Compiled from "MarkupHandler.scala"
public final class scala.xml.parsing.MarkupHandler$$anonfun$lookupElemDecl$2 extends java.lang.Object implements scala.Function1,scala.ScalaObject,java.io.Serializable
  SourceFile: "MarkupHandler.scala"
  Scala: length = 0x
   
  InnerClass: 
   public final $anonfun$lookupElemDecl$2=class scala/xml/parsing/MarkupHandler$$anonfun$lookupElemDecl$2 of class scala/xml/parsing/MarkupHandler
  minor version: 0
  major version: 49
  Constant pool:
Asciz	SourceFile;
Asciz	MarkupHandler.scala;
Asciz	<clinit>;
Asciz	()V;
Asciz	Code;
Asciz	serialVersionUID;
Asciz	J;
Asciz	scala/xml/parsing/MarkupHandler$$anonfun$lookupElemDecl$2;
class	scala/xml/parsing/MarkupHandler$$anonfun$lookupElemDecl$2
NameAndType	serialVersionUID:J
Field	scala/xml/parsing/MarkupHandler$$anonfun$lookupElemDecl$2.serialVersionUID:J
Asciz	nonLocalReturnKey1$1;
Asciz	Ljava/lang/Object;;
Asciz	Label$1;
Asciz	Ljava/lang/String;;
Asciz	<init>;
Asciz	(Lscala/xml/parsing/MarkupHandler;Ljava/lang/String;Ljava/lang/Object;)V;
Asciz	LineNumberTable;
NameAndType	Label$1:Ljava/lang/String;
Field	scala/xml/parsing/MarkupHandler$$anonfun$lookupElemDecl$2.Label$1:Ljava/lang/String;
NameAndType	nonLocalReturnKey1$1:Ljava/lang/Object;
Field	scala/xml/parsing/MarkupHandler$$anonfun$lookupElemDecl$2.nonLocalReturnKey1$1:Ljava/lang/Object;
Asciz	java/lang/Object;
class	java/lang/Object
NameAndType	"<init>":()V
Method	java/lang/Object."<init>":()V
Asciz	scala/Function1$class;
class	scala/Function1$class
Asciz	$init$;
Asciz	(Lscala/Function1;)V;
NameAndType	$init$:(Lscala/Function1;)V
Method	scala/Function1$class.$init$:(Lscala/Function1;)V
Asciz	this;
Asciz	Lscala/xml/parsing/MarkupHandler$$anonfun$lookupElemDecl$2;;
Asciz	$outer;
Asciz	Lscala/xml/parsing/MarkupHandler;;
Asciz	LocalVariableTable;
Asciz	apply;
Asciz	(Ljava/lang/Object;)Ljava/lang/Object;;
Asciz	scala/xml/dtd/Decl;
class	scala/xml/dtd/Decl
Asciz	(Lscala/xml/dtd/Decl;)Lscala/runtime/Nothing$;;
NameAndType	apply:(Lscala/xml/dtd/Decl;)Lscala/runtime/Nothing$;
Method	scala/xml/parsing/MarkupHandler$$anonfun$lookupElemDecl$2.apply:(Lscala/xml/dtd/Decl;)Lscala/runtime/Nothing$;
Asciz	v1;
Asciz	scala/xml/dtd/ElemDecl;
class	scala/xml/dtd/ElemDecl
Asciz	name;
Asciz	()Ljava/lang/String;;
NameAndType	name:()Ljava/lang/String;
Method	scala/xml/dtd/ElemDecl.name:()Ljava/lang/String;
Asciz	equals;
Asciz	(Ljava/lang/Object;)Z;
NameAndType	equals:(Ljava/lang/Object;)Z
Method	java/lang/Object.equals:(Ljava/lang/Object;)Z
Asciz	scala/runtime/NonLocalReturnException;
class	scala/runtime/NonLocalReturnException
Asciz	(Ljava/lang/Object;Ljava/lang/Object;)V;
NameAndType	"<init>":(Ljava/lang/Object;Ljava/lang/Object;)V
Method	scala/runtime/NonLocalReturnException."<init>":(Ljava/lang/Object;Ljava/lang/Object;)V
Asciz	scala/MatchError;
class	scala/MatchError
Asciz	toString;
NameAndType	toString:()Ljava/lang/String;
Method	scala/xml/dtd/Decl.toString:()Ljava/lang/String;
Asciz	(Ljava/lang/String;)V;
NameAndType	"<init>":(Ljava/lang/String;)V
Method	scala/MatchError."<init>":(Ljava/lang/String;)V
Asciz	temp7;
Asciz	Lscala/xml/dtd/ElemDecl;;
Asciz	andThen;
Asciz	(Lscala/Function1;)Lscala/Function1;;
Asciz	(Lscala/Function1;Lscala/Function1;)Lscala/Function1;;
NameAndType	andThen:(Lscala/Function1;Lscala/Function1;)Lscala/Function1;
Method	scala/Function1$class.andThen:(Lscala/Function1;Lscala/Function1;)Lscala/Function1;
Asciz	g;
Asciz	Lscala/Function1;;
Asciz	compose;
NameAndType	compose:(Lscala/Function1;Lscala/Function1;)Lscala/Function1;
Method	scala/Function1$class.compose:(Lscala/Function1;Lscala/Function1;)Lscala/Function1;
Asciz	(Lscala/Function1;)Ljava/lang/String;;
NameAndType	toString:(Lscala/Function1;)Ljava/lang/String;
Method	scala/Function1$class.toString:(Lscala/Function1;)Ljava/lang/String;
Asciz	Scala;
Asciz	InnerClasses;
Asciz	scala/xml/parsing/MarkupHandler;
class	scala/xml/parsing/MarkupHandler
Asciz	$anonfun$lookupElemDecl$2;
Asciz	scala/Function1;
class	scala/Function1
Asciz	scala/ScalaObject;
class	scala/ScalaObject
Asciz	java/io/Serializable;
class	java/io/Serializable

{
public static final long serialVersionUID;
  Signature: J

private final java.lang.Object nonLocalReturnKey1$1;
  Signature: Ljava/lang/Object;

private final java.lang.String Label$1;
  Signature: Ljava/lang/String;

public static {};
  Signature: ()V
  Code:
   Stack=2, Locals=0, Args_size=0
	lconst_0
	putstatic	Field serialVersionUID:J
	return
  Labels:

public scala.xml.parsing.MarkupHandler$$anonfun$lookupElemDecl$2(scala.xml.parsing.MarkupHandler, java.lang.String, java.lang.Object);
  Signature: (Lscala/xml/parsing/MarkupHandler;Ljava/lang/String;Ljava/lang/Object;)V
  Code:
   Stack=2, Locals=4, Args_size=4
	aload_0
	aload_2
	putfield	Field Label$1:Ljava/lang/String;
	aload_0
	aload_3
	putfield	Field nonLocalReturnKey1$1:Ljava/lang/Object;
	aload_0
	invokespecial	Method java/lang/Object."<init>":()V
	aload_0
	invokestatic	Method scala/Function1$class.$init$:(Lscala/Function1;)V
	return
  Labels:
  LocalVariableTable: 
   Start  Length  Slot  Name   Signature
   0      19      0    this       Lscala/xml/parsing/MarkupHandler$$anonfun$lookupElemDecl$2;
   0      19      1    $outer       Lscala/xml/parsing/MarkupHandler;


public final java.lang.Object apply(java.lang.Object);
  Signature: (Ljava/lang/Object;)Ljava/lang/Object;
  Code:
   Stack=2, Locals=2, Args_size=2
	aload_0
	aload_1
	checkcast	class scala/xml/dtd/Decl
	invokevirtual	Method apply:(Lscala/xml/dtd/Decl;)Lscala/runtime/Nothing$;
	athrow
  Labels:
  LocalVariableTable: 
   Start  Length  Slot  Name   Signature
   0      9      0    this       Lscala/xml/parsing/MarkupHandler$$anonfun$lookupElemDecl$2;
   0      9      1    v1       Ljava/lang/Object;


public final scala.runtime.Nothing$ apply(scala.xml.dtd.Decl);
  Signature: (Lscala/xml/dtd/Decl;)Lscala/runtime/Nothing$;
  Code:
   Stack=4, Locals=4, Args_size=2
	aload_1
	instanceof	class scala/xml/dtd/ElemDecl
	ifeq	l1 // new
	aload_1
	checkcast	class scala/xml/dtd/ElemDecl
	astore_3
	aload_0
	getfield	Field Label$1:Ljava/lang/String;
	aload_3
	invokevirtual	Method scala/xml/dtd/ElemDecl.name:()Ljava/lang/String;
	astore_2
	dup
	ifnonnull	l2 // aload_2
	pop
	aload_2
	ifnull	l3 // iconst_1
	goto	l4 // new
l2	aload_2
	invokevirtual	Method java/lang/Object.equals:(Ljava/lang/Object;)Z
	ifeq	l4 // new
l3	iconst_1
	ifeq	l5 // new
	new	class scala/runtime/NonLocalReturnException
	dup
	aload_0
	getfield	Field nonLocalReturnKey1$1:Ljava/lang/Object;
	aload_3
	invokespecial	Method scala/runtime/NonLocalReturnException."<init>":(Ljava/lang/Object;Ljava/lang/Object;)V
	athrow
l5	new	class scala/MatchError
	dup
	aload_1
	invokevirtual	Method scala/xml/dtd/Decl.toString:()Ljava/lang/String;
	invokespecial	Method scala/MatchError."<init>":(Ljava/lang/String;)V
	athrow
l4	new	class scala/MatchError
	dup
	aload_1
	invokevirtual	Method scala/xml/dtd/Decl.toString:()Ljava/lang/String;
	invokespecial	Method scala/MatchError."<init>":(Ljava/lang/String;)V
	athrow
l1	new	class scala/MatchError
	dup
	aload_1
	invokevirtual	Method scala/xml/dtd/Decl.toString:()Ljava/lang/String;
	invokespecial	Method scala/MatchError."<init>":(Ljava/lang/String;)V
	athrow
  Labels:
   	l2 = 33 // aload_2
   	l3 = 40 // iconst_1
   	l5 = 57 // new
   	l4 = 69 // new
   	l1 = 81 // new
  LocalVariableTable: 
   Start  Length  Slot  Name   Signature
   0      93      0    this       Lscala/xml/parsing/MarkupHandler$$anonfun$lookupElemDecl$2;
   12      69      3    temp7       Lscala/xml/dtd/ElemDecl;


public scala.Function1 andThen(scala.Function1);
  Signature: (Lscala/Function1;)Lscala/Function1;
  Code:
   Stack=2, Locals=2, Args_size=2
	aload_0
	aload_1
	invokestatic	Method scala/Function1$class.andThen:(Lscala/Function1;Lscala/Function1;)Lscala/Function1;
	areturn
  Labels:
  LocalVariableTable: 
   Start  Length  Slot  Name   Signature
   0      6      0    this       Lscala/xml/parsing/MarkupHandler$$anonfun$lookupElemDecl$2;
   0      6      1    g       Lscala/Function1;


public scala.Function1 compose(scala.Function1);
  Signature: (Lscala/Function1;)Lscala/Function1;
  Code:
   Stack=2, Locals=2, Args_size=2
	aload_0
	aload_1
	invokestatic	Method scala/Function1$class.compose:(Lscala/Function1;Lscala/Function1;)Lscala/Function1;
	areturn
  Labels:
  LocalVariableTable: 
   Start  Length  Slot  Name   Signature
   0      6      0    this       Lscala/xml/parsing/MarkupHandler$$anonfun$lookupElemDecl$2;
   0      6      1    g       Lscala/Function1;


public java.lang.String toString();
  Signature: ()Ljava/lang/String;
  Code:
   Stack=1, Locals=1, Args_size=1
	aload_0
	invokestatic	Method scala/Function1$class.toString:(Lscala/Function1;)Ljava/lang/String;
	areturn
  Labels:

}

