Compiled from "MarkupParser.scala"
public abstract class scala.xml.parsing.MarkupParser$class extends java.lang.Object
  SourceFile: "MarkupParser.scala"
  Scala: length = 0x
   
  InnerClass: 
   public final #1064= #752 of #8; //$anon$1=class scala/xml/parsing/MarkupParser$$anon$1 of class scala/xml/parsing/MarkupParser
   public final #1065= #722 of #8; //$anon$2=class scala/xml/parsing/MarkupParser$$anon$2 of class scala/xml/parsing/MarkupParser
   public final #1066= #166 of #8; //$anonfun$4=class scala/xml/parsing/MarkupParser$$anonfun$4 of class scala/xml/parsing/MarkupParser
   public final #1067= #774 of #8; //$anonfun$2=class scala/xml/parsing/MarkupParser$$anonfun$2 of class scala/xml/parsing/MarkupParser
   public final #1068= #770 of #8; //$anonfun$1=class scala/xml/parsing/MarkupParser$$anonfun$1 of class scala/xml/parsing/MarkupParser
   public final #1069= #161 of #8; //$anonfun$3=class scala/xml/parsing/MarkupParser$$anonfun$3 of class scala/xml/parsing/MarkupParser
   public final #1070= #835 of #8; //$anonfun$xCharRef$1=class scala/xml/parsing/MarkupParser$$anonfun$xCharRef$1 of class scala/xml/parsing/MarkupParser
   public final #1071= #956 of #8; //$anonfun$document$1=class scala/xml/parsing/MarkupParser$$anonfun$document$1 of class scala/xml/parsing/MarkupParser
   public final #1072= #818 of #8; //$anonfun$appendText$1=class scala/xml/parsing/MarkupParser$$anonfun$appendText$1 of class scala/xml/parsing/MarkupParser
  minor version: 0
  major version: 49
  Constant pool:
const #1 = Asciz	SourceFile;
const #2 = Asciz	MarkupParser.scala;
const #3 = Asciz	$init$;
const #4 = Asciz	(Lscala/xml/parsing/MarkupParser;)V;
const #5 = Asciz	Code;
const #6 = Asciz	LineNumberTable;
const #7 = Asciz	scala/xml/parsing/MarkupParser;
const #8 = class	#7;	//  scala/xml/parsing/MarkupParser
const #9 = Asciz	input;
const #10 = Asciz	()Lscala/io/Source;;
const #11 = NameAndType	#9:#10;//  input:()Lscala/io/Source;
const #12 = InterfaceMethod	#8.#11;	//  scala/xml/parsing/MarkupParser.input:()Lscala/io/Source;
const #13 = Asciz	curInput_$eq;
const #14 = Asciz	(Lscala/io/Source;)V;
const #15 = NameAndType	#13:#14;//  curInput_$eq:(Lscala/io/Source;)V
const #16 = InterfaceMethod	#8.#15;	//  scala/xml/parsing/MarkupParser.curInput_$eq:(Lscala/io/Source;)V
const #17 = Asciz	scala/xml/parsing/MarkupHandler;
const #18 = class	#17;	//  scala/xml/parsing/MarkupHandler
const #19 = Asciz	scala$xml$parsing$MarkupParser$_setter_$scala$xml$parsing$MarkupParser$$handle_$eq;
const #20 = Asciz	(Lscala/xml/parsing/MarkupHandler;)V;
const #21 = NameAndType	#19:#20;//  scala$xml$parsing$MarkupParser$_setter_$scala$xml$parsing$MarkupParser$$handle_$eq:(Lscala/xml/parsing/MarkupHandler;)V
const #22 = InterfaceMethod	#8.#21;	//  scala/xml/parsing/MarkupParser.scala$xml$parsing$MarkupParser$_setter_$scala$xml$parsing$MarkupParser$$handle_$eq:(Lscala/xml/parsing/MarkupHandler;)V
const #23 = Asciz	scala/collection/immutable/Nil$;
const #24 = class	#23;	//  scala/collection/immutable/Nil$
const #25 = Asciz	MODULE$;
const #26 = Asciz	Lscala/collection/immutable/Nil$;;
const #27 = NameAndType	#25:#26;//  MODULE$:Lscala/collection/immutable/Nil$;
const #28 = Field	#24.#27;	//  scala/collection/immutable/Nil$.MODULE$:Lscala/collection/immutable/Nil$;
const #29 = Asciz	inpStack_$eq;
const #30 = Asciz	(Lscala/collection/immutable/List;)V;
const #31 = NameAndType	#29:#30;//  inpStack_$eq:(Lscala/collection/immutable/List;)V
const #32 = InterfaceMethod	#8.#31;	//  scala/xml/parsing/MarkupParser.inpStack_$eq:(Lscala/collection/immutable/List;)V
const #33 = Asciz	extIndex_$eq;
const #34 = Asciz	(I)V;
const #35 = NameAndType	#33:#34;//  extIndex_$eq:(I)V
const #36 = InterfaceMethod	#8.#35;	//  scala/xml/parsing/MarkupParser.extIndex_$eq:(I)V
const #37 = Asciz	scala/collection/mutable/StringBuilder;
const #38 = class	#37;	//  scala/collection/mutable/StringBuilder
const #39 = Asciz	<init>;
const #40 = Asciz	()V;
const #41 = NameAndType	#39:#40;//  "<init>":()V
const #42 = Method	#38.#41;	//  scala/collection/mutable/StringBuilder."<init>":()V
const #43 = Asciz	scala$xml$parsing$MarkupParser$_setter_$cbuf_$eq;
const #44 = Asciz	(Lscala/collection/mutable/StringBuilder;)V;
const #45 = NameAndType	#43:#44;//  scala$xml$parsing$MarkupParser$_setter_$cbuf_$eq:(Lscala/collection/mutable/StringBuilder;)V
const #46 = InterfaceMethod	#8.#45;	//  scala/xml/parsing/MarkupParser.scala$xml$parsing$MarkupParser$_setter_$cbuf_$eq:(Lscala/collection/mutable/StringBuilder;)V
const #47 = Asciz	dtd_$eq;
const #48 = Asciz	(Lscala/xml/dtd/DTD;)V;
const #49 = NameAndType	#47:#48;//  dtd_$eq:(Lscala/xml/dtd/DTD;)V
const #50 = InterfaceMethod	#8.#49;	//  scala/xml/parsing/MarkupParser.dtd_$eq:(Lscala/xml/dtd/DTD;)V
const #51 = Asciz	doc_$eq;
const #52 = Asciz	(Lscala/xml/Document;)V;
const #53 = NameAndType	#51:#52;//  doc_$eq:(Lscala/xml/Document;)V
const #54 = InterfaceMethod	#8.#53;	//  scala/xml/parsing/MarkupParser.doc_$eq:(Lscala/xml/Document;)V
const #55 = Asciz	eof_$eq;
const #56 = Asciz	(Z)V;
const #57 = NameAndType	#55:#56;//  eof_$eq:(Z)V
const #58 = InterfaceMethod	#8.#57;	//  scala/xml/parsing/MarkupParser.eof_$eq:(Z)V
const #59 = Asciz	$this;
const #60 = Asciz	Lscala/xml/parsing/MarkupParser;;
const #61 = Asciz	LocalVariableTable;
const #62 = Asciz	gd2$1;
const #63 = Asciz	(Lscala/xml/parsing/MarkupParser;)Z;
const #64 = Asciz	ch;
const #65 = Asciz	()C;
const #66 = NameAndType	#64:#65;//  ch:()C
const #67 = InterfaceMethod	#8.#66;	//  scala/xml/parsing/MarkupParser.ch:()C
const #68 = Asciz	scala/xml/parsing/TokenTests;
const #69 = class	#68;	//  scala/xml/parsing/TokenTests
const #70 = Asciz	isSpace;
const #71 = Asciz	(C)Z;
const #72 = NameAndType	#70:#71;//  isSpace:(C)Z
const #73 = InterfaceMethod	#69.#72;	//  scala/xml/parsing/TokenTests.isSpace:(C)Z
const #74 = Asciz	gd1$1;
const #75 = Asciz	inpStack;
const #76 = Asciz	()Lscala/collection/immutable/List;;
const #77 = NameAndType	#75:#76;//  inpStack:()Lscala/collection/immutable/List;
const #78 = InterfaceMethod	#8.#77;	//  scala/xml/parsing/MarkupParser.inpStack:()Lscala/collection/immutable/List;
const #79 = Asciz	scala/collection/generic/LinearSequenceTemplate;
const #80 = class	#79;	//  scala/collection/generic/LinearSequenceTemplate
const #81 = Asciz	length;
const #82 = Asciz	()I;
const #83 = NameAndType	#81:#82;//  length:()I
const #84 = InterfaceMethod	#80.#83;	//  scala/collection/generic/LinearSequenceTemplate.length:()I
const #85 = Asciz	extIndex;
const #86 = NameAndType	#85:#82;//  extIndex:()I
const #87 = InterfaceMethod	#8.#86;	//  scala/xml/parsing/MarkupParser.extIndex:()I
const #88 = Asciz	doIgnore$1;
const #89 = int	91;
const #90 = Asciz	xToken;
const #91 = Asciz	(C)V;
const #92 = NameAndType	#90:#91;//  xToken:(C)V
const #93 = InterfaceMethod	#8.#92;	//  scala/xml/parsing/MarkupParser.xToken:(C)V
const #94 = int	93;
const #95 = Asciz	nextch;
const #96 = NameAndType	#95:#40;//  nextch:()V
const #97 = InterfaceMethod	#8.#96;	//  scala/xml/parsing/MarkupParser.nextch:()V
const #98 = Asciz	doInclude$1;
const #99 = Asciz	markupDecl;
const #100 = NameAndType	#99:#40;//  markupDecl:()V
const #101 = InterfaceMethod	#8.#100;	//  scala/xml/parsing/MarkupParser.markupDecl:()V
const #102 = Asciz	normalizeAttributeValue;
const #103 = Asciz	(Lscala/xml/parsing/MarkupParser;Ljava/lang/String;)Ljava/lang/String;;
const #104 = Asciz	scala/Predef$;
const #105 = class	#104;	//  scala/Predef$
const #106 = Asciz	Lscala/Predef$;;
const #107 = NameAndType	#25:#106;//  MODULE$:Lscala/Predef$;
const #108 = Field	#105.#107;	//  scala/Predef$.MODULE$:Lscala/Predef$;
const #109 = Asciz	stringWrapper;
const #110 = Asciz	(Ljava/lang/String;)Lscala/runtime/RichString;;
const #111 = NameAndType	#109:#110;//  stringWrapper:(Ljava/lang/String;)Lscala/runtime/RichString;
const #112 = Method	#105.#111;	//  scala/Predef$.stringWrapper:(Ljava/lang/String;)Lscala/runtime/RichString;
const #113 = Asciz	scala/collection/generic/IterableTemplate;
const #114 = class	#113;	//  scala/collection/generic/IterableTemplate
const #115 = Asciz	iterator;
const #116 = Asciz	()Lscala/collection/Iterator;;
const #117 = NameAndType	#115:#116;//  iterator:()Lscala/collection/Iterator;
const #118 = InterfaceMethod	#114.#117;	//  scala/collection/generic/IterableTemplate.iterator:()Lscala/collection/Iterator;
const #119 = Asciz	scala/collection/Iterator;
const #120 = class	#119;	//  scala/collection/Iterator
const #121 = Asciz	hasNext;
const #122 = Asciz	()Z;
const #123 = NameAndType	#121:#122;//  hasNext:()Z
const #124 = InterfaceMethod	#120.#123;	//  scala/collection/Iterator.hasNext:()Z
const #125 = Asciz	next;
const #126 = Asciz	()Ljava/lang/Object;;
const #127 = NameAndType	#125:#126;//  next:()Ljava/lang/Object;
const #128 = InterfaceMethod	#120.#127;	//  scala/collection/Iterator.next:()Ljava/lang/Object;
const #129 = Asciz	scala/runtime/BoxesRunTime;
const #130 = class	#129;	//  scala/runtime/BoxesRunTime
const #131 = Asciz	unboxToChar;
const #132 = Asciz	(Ljava/lang/Object;)C;
const #133 = NameAndType	#131:#132;//  unboxToChar:(Ljava/lang/Object;)C
const #134 = Method	#130.#133;	//  scala/runtime/BoxesRunTime.unboxToChar:(Ljava/lang/Object;)C
const #135 = Asciz	cbuf;
const #136 = Asciz	()Lscala/collection/mutable/StringBuilder;;
const #137 = NameAndType	#135:#136;//  cbuf:()Lscala/collection/mutable/StringBuilder;
const #138 = InterfaceMethod	#8.#137;	//  scala/xml/parsing/MarkupParser.cbuf:()Lscala/collection/mutable/StringBuilder;
const #139 = Asciz	append;
const #140 = Asciz	(C)Lscala/collection/mutable/StringBuilder;;
const #141 = NameAndType	#139:#140;//  append:(C)Lscala/collection/mutable/StringBuilder;
const #142 = Method	#38.#141;	//  scala/collection/mutable/StringBuilder.append:(C)Lscala/collection/mutable/StringBuilder;
const #143 = Asciz	boxToCharacter;
const #144 = Asciz	(C)Ljava/lang/Character;;
const #145 = NameAndType	#143:#144;//  boxToCharacter:(C)Ljava/lang/Character;
const #146 = Method	#130.#145;	//  scala/runtime/BoxesRunTime.boxToCharacter:(C)Ljava/lang/Character;
const #147 = int	35;
const #148 = Asciz	boxToInteger;
const #149 = Asciz	(I)Ljava/lang/Integer;;
const #150 = NameAndType	#148:#149;//  boxToInteger:(I)Ljava/lang/Integer;
const #151 = Method	#130.#150;	//  scala/runtime/BoxesRunTime.boxToInteger:(I)Ljava/lang/Integer;
const #152 = Asciz	equals;
const #153 = Asciz	(Ljava/lang/Object;Ljava/lang/Object;)Z;
const #154 = NameAndType	#152:#153;//  equals:(Ljava/lang/Object;Ljava/lang/Object;)Z
const #155 = Method	#130.#154;	//  scala/runtime/BoxesRunTime.equals:(Ljava/lang/Object;Ljava/lang/Object;)Z
const #156 = Asciz	scala/runtime/CharRef;
const #157 = class	#156;	//  scala/runtime/CharRef
const #158 = NameAndType	#39:#91;//  "<init>":(C)V
const #159 = Method	#157.#158;	//  scala/runtime/CharRef."<init>":(C)V
const #160 = Asciz	scala/xml/parsing/MarkupParser$$anonfun$3;
const #161 = class	#160;	//  scala/xml/parsing/MarkupParser$$anonfun$3
const #162 = Asciz	(Lscala/xml/parsing/MarkupParser;Lscala/runtime/CharRef;)V;
const #163 = NameAndType	#39:#162;//  "<init>":(Lscala/xml/parsing/MarkupParser;Lscala/runtime/CharRef;)V
const #164 = Method	#161.#163;	//  scala/xml/parsing/MarkupParser$$anonfun$3."<init>":(Lscala/xml/parsing/MarkupParser;Lscala/runtime/CharRef;)V
const #165 = Asciz	scala/xml/parsing/MarkupParser$$anonfun$4;
const #166 = class	#165;	//  scala/xml/parsing/MarkupParser$$anonfun$4
const #167 = Asciz	(Lscala/xml/parsing/MarkupParser;Lscala/collection/Iterator;Lscala/runtime/CharRef;)V;
const #168 = NameAndType	#39:#167;//  "<init>":(Lscala/xml/parsing/MarkupParser;Lscala/collection/Iterator;Lscala/runtime/CharRef;)V
const #169 = Method	#166.#168;	//  scala/xml/parsing/MarkupParser$$anonfun$4."<init>":(Lscala/xml/parsing/MarkupParser;Lscala/collection/Iterator;Lscala/runtime/CharRef;)V
const #170 = Asciz	xCharRef;
const #171 = Asciz	(Lscala/Function0;Lscala/Function0;)Ljava/lang/String;;
const #172 = NameAndType	#170:#171;//  xCharRef:(Lscala/Function0;Lscala/Function0;)Ljava/lang/String;
const #173 = InterfaceMethod	#8.#172;	//  scala/xml/parsing/MarkupParser.xCharRef:(Lscala/Function0;Lscala/Function0;)Ljava/lang/String;
const #174 = Asciz	(Ljava/lang/String;)Lscala/collection/mutable/StringBuilder;;
const #175 = NameAndType	#139:#174;//  append:(Ljava/lang/String;)Lscala/collection/mutable/StringBuilder;
const #176 = Method	#38.#175;	//  scala/collection/mutable/StringBuilder.append:(Ljava/lang/String;)Lscala/collection/mutable/StringBuilder;
const #177 = int	59;
const #178 = Asciz	toString;
const #179 = Asciz	()Ljava/lang/String;;
const #180 = NameAndType	#178:#179;//  toString:()Ljava/lang/String;
const #181 = Method	#38.#180;	//  scala/collection/mutable/StringBuilder.toString:()Ljava/lang/String;
const #182 = Asciz	lt;
const #183 = String	#182;	//  lt
const #184 = Asciz	java/lang/Object;
const #185 = class	#184;	//  java/lang/Object
const #186 = Asciz	(Ljava/lang/Object;)Z;
const #187 = NameAndType	#152:#186;//  equals:(Ljava/lang/Object;)Z
const #188 = Method	#185.#187;	//  java/lang/Object.equals:(Ljava/lang/Object;)Z
const #189 = int	60;
const #190 = Asciz	gt;
const #191 = String	#190;	//  gt
const #192 = int	62;
const #193 = Asciz	amp;
const #194 = String	#193;	//  amp
const #195 = int	38;
const #196 = Asciz	apos;
const #197 = String	#196;	//  apos
const #198 = int	39;
const #199 = Asciz	quot;
const #200 = String	#199;	//  quot
const #201 = int	34;
const #202 = Asciz	quote;
const #203 = String	#202;	//  quote
const #204 = int	32;
const #205 = Asciz	length_$eq;
const #206 = NameAndType	#205:#34;//  length_$eq:(I)V
const #207 = Method	#38.#206;	//  scala/collection/mutable/StringBuilder.length_$eq:(I)V
const #208 = Asciz	attval;
const #209 = Asciz	Ljava/lang/String;;
const #210 = Asciz	s;
const #211 = Asciz	Lscala/collection/Sequence;;
const #212 = Asciz	it$1;
const #213 = Asciz	Lscala/collection/Iterator;;
const #214 = Asciz	temp89;
const #215 = Asciz	C;
const #216 = Asciz	temp88;
const #217 = Asciz	c$1;
const #218 = Asciz	Lscala/runtime/CharRef;;
const #219 = Asciz	nchar;
const #220 = Asciz	nbuf;
const #221 = Asciz	Lscala/collection/mutable/StringBuilder;;
const #222 = Asciz	d;
const #223 = Asciz	temp81;
const #224 = Asciz	name;
const #225 = Asciz	pop;
const #226 = Asciz	head;
const #227 = NameAndType	#226:#126;//  head:()Ljava/lang/Object;
const #228 = InterfaceMethod	#114.#227;	//  scala/collection/generic/IterableTemplate.head:()Ljava/lang/Object;
const #229 = Asciz	scala/io/Source;
const #230 = class	#229;	//  scala/io/Source
const #231 = Asciz	scala/collection/generic/TraversableTemplate;
const #232 = class	#231;	//  scala/collection/generic/TraversableTemplate
const #233 = Asciz	tail;
const #234 = Asciz	()Lscala/collection/generic/TraversableTemplate;;
const #235 = NameAndType	#233:#234;//  tail:()Lscala/collection/generic/TraversableTemplate;
const #236 = InterfaceMethod	#232.#235;	//  scala/collection/generic/TraversableTemplate.tail:()Lscala/collection/generic/TraversableTemplate;
const #237 = Asciz	scala/collection/immutable/List;
const #238 = class	#237;	//  scala/collection/immutable/List
const #239 = Asciz	curInput;
const #240 = NameAndType	#239:#10;//  curInput:()Lscala/io/Source;
const #241 = InterfaceMethod	#8.#240;	//  scala/xml/parsing/MarkupParser.curInput:()Lscala/io/Source;
const #242 = Method	#230.#66;	//  scala/io/Source.ch:()C
const #243 = Asciz	ch_$eq;
const #244 = NameAndType	#243:#91;//  ch_$eq:(C)V
const #245 = InterfaceMethod	#8.#244;	//  scala/xml/parsing/MarkupParser.ch_$eq:(C)V
const #246 = Asciz	pos;
const #247 = NameAndType	#246:#82;//  pos:()I
const #248 = Method	#230.#247;	//  scala/io/Source.pos:()I
const #249 = Asciz	pos_$eq;
const #250 = NameAndType	#249:#34;//  pos_$eq:(I)V
const #251 = InterfaceMethod	#8.#250;	//  scala/xml/parsing/MarkupParser.pos_$eq:(I)V
const #252 = Asciz	pushExternal;
const #253 = Asciz	(Lscala/xml/parsing/MarkupParser;Ljava/lang/String;)V;
const #254 = Asciz	eof;
const #255 = NameAndType	#254:#122;//  eof:()Z
const #256 = InterfaceMethod	#8.#255;	//  scala/xml/parsing/MarkupParser.eof:()Z
const #257 = Asciz	$colon$colon;
const #258 = Asciz	(Ljava/lang/Object;)Lscala/collection/immutable/List;;
const #259 = NameAndType	#257:#258;//  $colon$colon:(Ljava/lang/Object;)Lscala/collection/immutable/List;
const #260 = Method	#238.#259;	//  scala/collection/immutable/List.$colon$colon:(Ljava/lang/Object;)Lscala/collection/immutable/List;
const #261 = Asciz	externalSource;
const #262 = Asciz	(Ljava/lang/String;)Lscala/io/Source;;
const #263 = NameAndType	#261:#262;//  externalSource:(Ljava/lang/String;)Lscala/io/Source;
const #264 = InterfaceMethod	#8.#263;	//  scala/xml/parsing/MarkupParser.externalSource:(Ljava/lang/String;)Lscala/io/Source;
const #265 = Asciz	systemId;
const #266 = Asciz	push;
const #267 = Asciz	replacementText;
const #268 = NameAndType	#267:#262;//  replacementText:(Ljava/lang/String;)Lscala/io/Source;
const #269 = Method	#18.#268;	//  scala/xml/parsing/MarkupHandler.replacementText:(Ljava/lang/String;)Lscala/io/Source;
const #270 = Asciz	entityName;
const #271 = Asciz	reportValidationError;
const #272 = Asciz	(Lscala/xml/parsing/MarkupParser;ILjava/lang/String;)V;
const #273 = Asciz	reportError$default$3;
const #274 = Asciz	()Ljava/io/PrintStream;;
const #275 = NameAndType	#273:#274;//  reportError$default$3:()Ljava/io/PrintStream;
const #276 = Method	#230.#275;	//  scala/io/Source.reportError$default$3:()Ljava/io/PrintStream;
const #277 = Asciz	reportError;
const #278 = Asciz	(ILjava/lang/String;Ljava/io/PrintStream;)V;
const #279 = NameAndType	#277:#278;//  reportError:(ILjava/lang/String;Ljava/io/PrintStream;)V
const #280 = Method	#230.#279;	//  scala/io/Source.reportError:(ILjava/lang/String;Ljava/io/PrintStream;)V
const #281 = Asciz	I;
const #282 = Asciz	str;
const #283 = Asciz	qual$3;
const #284 = Asciz	Lscala/io/Source;;
const #285 = Asciz	x$14;
const #286 = Asciz	x$15;
const #287 = Asciz	x$16;
const #288 = Asciz	Ljava/io/PrintStream;;
const #289 = Asciz	reportSyntaxError;
const #290 = InterfaceMethod	#8.#247;	//  scala/xml/parsing/MarkupParser.pos:()I
const #291 = Asciz	(ILjava/lang/String;)V;
const #292 = NameAndType	#289:#291;//  reportSyntaxError:(ILjava/lang/String;)V
const #293 = InterfaceMethod	#8.#292;	//  scala/xml/parsing/MarkupParser.reportSyntaxError:(ILjava/lang/String;)V
const #294 = Asciz	qual$2;
const #295 = Asciz	x$11;
const #296 = Asciz	x$12;
const #297 = Asciz	x$13;
const #298 = Asciz	notationDecl;
const #299 = Asciz	OTATION;
const #300 = String	#299;	//  OTATION
const #301 = Asciz	(Lscala/collection/Sequence;)V;
const #302 = NameAndType	#90:#301;//  xToken:(Lscala/collection/Sequence;)V
const #303 = InterfaceMethod	#8.#302;	//  scala/xml/parsing/MarkupParser.xToken:(Lscala/collection/Sequence;)V
const #304 = Asciz	xSpace;
const #305 = NameAndType	#304:#40;//  xSpace:()V
const #306 = InterfaceMethod	#8.#305;	//  scala/xml/parsing/MarkupParser.xSpace:()V
const #307 = Asciz	xName;
const #308 = NameAndType	#307:#179;//  xName:()Ljava/lang/String;
const #309 = InterfaceMethod	#8.#308;	//  scala/xml/parsing/MarkupParser.xName:()Ljava/lang/String;
const #310 = int	83;
const #311 = Asciz	externalID;
const #312 = Asciz	()Lscala/xml/dtd/ExternalID;;
const #313 = NameAndType	#311:#312;//  externalID:()Lscala/xml/dtd/ExternalID;
const #314 = InterfaceMethod	#8.#313;	//  scala/xml/parsing/MarkupParser.externalID:()Lscala/xml/dtd/ExternalID;
const #315 = int	80;
const #316 = Asciz	UBLIC;
const #317 = String	#316;	//  UBLIC
const #318 = Asciz	pubidLiteral;
const #319 = NameAndType	#318:#179;//  pubidLiteral:()Ljava/lang/String;
const #320 = InterfaceMethod	#8.#319;	//  scala/xml/parsing/MarkupParser.pubidLiteral:()Ljava/lang/String;
const #321 = Asciz	xSpaceOpt;
const #322 = NameAndType	#321:#40;//  xSpaceOpt:()V
const #323 = InterfaceMethod	#8.#322;	//  scala/xml/parsing/MarkupParser.xSpaceOpt:()V
const #324 = Asciz	systemLiteral;
const #325 = NameAndType	#324:#179;//  systemLiteral:()Ljava/lang/String;
const #326 = InterfaceMethod	#8.#325;	//  scala/xml/parsing/MarkupParser.systemLiteral:()Ljava/lang/String;
const #327 = Asciz	scala/xml/dtd/PublicID;
const #328 = class	#327;	//  scala/xml/dtd/PublicID
const #329 = Asciz	(Ljava/lang/String;Ljava/lang/String;)V;
const #330 = NameAndType	#39:#329;//  "<init>":(Ljava/lang/String;Ljava/lang/String;)V
const #331 = Method	#328.#330;	//  scala/xml/dtd/PublicID."<init>":(Ljava/lang/String;Ljava/lang/String;)V
const #332 = Asciz	scala$xml$parsing$MarkupParser$$handle;
const #333 = Asciz	()Lscala/xml/parsing/MarkupHandler;;
const #334 = NameAndType	#332:#333;//  scala$xml$parsing$MarkupParser$$handle:()Lscala/xml/parsing/MarkupHandler;
const #335 = InterfaceMethod	#8.#334;	//  scala/xml/parsing/MarkupParser.scala$xml$parsing$MarkupParser$$handle:()Lscala/xml/parsing/MarkupHandler;
const #336 = Asciz	(Ljava/lang/String;Lscala/xml/dtd/ExternalID;)V;
const #337 = NameAndType	#298:#336;//  notationDecl:(Ljava/lang/String;Lscala/xml/dtd/ExternalID;)V
const #338 = Method	#18.#337;	//  scala/xml/parsing/MarkupHandler.notationDecl:(Ljava/lang/String;Lscala/xml/dtd/ExternalID;)V
const #339 = Asciz	PUBLIC or SYSTEM expected;
const #340 = String	#339;	//  PUBLIC or SYSTEM expected
const #341 = Asciz	(Ljava/lang/String;)V;
const #342 = NameAndType	#289:#341;//  reportSyntaxError:(Ljava/lang/String;)V
const #343 = InterfaceMethod	#8.#342;	//  scala/xml/parsing/MarkupParser.reportSyntaxError:(Ljava/lang/String;)V
const #344 = Asciz	died parsing notationdecl;
const #345 = String	#344;	//  died parsing notationdecl
const #346 = Asciz	error;
const #347 = Asciz	(Ljava/lang/String;)Lscala/runtime/Nothing$;;
const #348 = NameAndType	#346:#347;//  error:(Ljava/lang/String;)Lscala/runtime/Nothing$;
const #349 = Method	#105.#348;	//  scala/Predef$.error:(Ljava/lang/String;)Lscala/runtime/Nothing$;
const #350 = Asciz	notat;
const #351 = Asciz	extID;
const #352 = Asciz	Lscala/xml/dtd/ExternalID;;
const #353 = Asciz	pubID;
const #354 = Asciz	sysID;
const #355 = Asciz	entityDecl;
const #356 = Asciz	NTITY;
const #357 = String	#356;	//  NTITY
const #358 = int	37;
const #359 = Asciz	scala/MatchError;
const #360 = class	#359;	//  scala/MatchError
const #361 = Method	#185.#180;	//  java/lang/Object.toString:()Ljava/lang/String;
const #362 = NameAndType	#39:#341;//  "<init>":(Ljava/lang/String;)V
const #363 = Method	#360.#362;	//  scala/MatchError."<init>":(Ljava/lang/String;)V
const #364 = Asciz	scala/xml/dtd/ExtDef;
const #365 = class	#364;	//  scala/xml/dtd/ExtDef
const #366 = Asciz	(Lscala/xml/dtd/ExternalID;)V;
const #367 = NameAndType	#39:#366;//  "<init>":(Lscala/xml/dtd/ExternalID;)V
const #368 = Method	#365.#367;	//  scala/xml/dtd/ExtDef."<init>":(Lscala/xml/dtd/ExternalID;)V
const #369 = Asciz	parameterEntityDecl;
const #370 = Asciz	(Ljava/lang/String;Lscala/xml/dtd/EntityDef;)V;
const #371 = NameAndType	#369:#370;//  parameterEntityDecl:(Ljava/lang/String;Lscala/xml/dtd/EntityDef;)V
const #372 = Method	#18.#371;	//  scala/xml/parsing/MarkupHandler.parameterEntityDecl:(Ljava/lang/String;Lscala/xml/dtd/EntityDef;)V
const #373 = Asciz	NDATA;
const #374 = String	#373;	//  NDATA
const #375 = Asciz	unparsedEntityDecl;
const #376 = Asciz	(Ljava/lang/String;Lscala/xml/dtd/ExternalID;Ljava/lang/String;)V;
const #377 = NameAndType	#375:#376;//  unparsedEntityDecl:(Ljava/lang/String;Lscala/xml/dtd/ExternalID;Ljava/lang/String;)V
const #378 = Method	#18.#377;	//  scala/xml/parsing/MarkupHandler.unparsedEntityDecl:(Ljava/lang/String;Lscala/xml/dtd/ExternalID;Ljava/lang/String;)V
const #379 = Asciz	parsedEntityDecl;
const #380 = NameAndType	#379:#370;//  parsedEntityDecl:(Ljava/lang/String;Lscala/xml/dtd/EntityDef;)V
const #381 = Method	#18.#380;	//  scala/xml/parsing/MarkupHandler.parsedEntityDecl:(Ljava/lang/String;Lscala/xml/dtd/EntityDef;)V
const #382 = Asciz	xEntityValue;
const #383 = NameAndType	#382:#179;//  xEntityValue:()Ljava/lang/String;
const #384 = InterfaceMethod	#8.#383;	//  scala/xml/parsing/MarkupParser.xEntityValue:()Ljava/lang/String;
const #385 = Asciz	scala/xml/dtd/IntDef;
const #386 = class	#385;	//  scala/xml/dtd/IntDef
const #387 = Method	#386.#362;	//  scala/xml/dtd/IntDef."<init>":(Ljava/lang/String;)V
const #388 = Asciz	isParameterEntity;
const #389 = Asciz	Z;
const #390 = Asciz	entdef;
const #391 = Asciz	Lscala/xml/dtd/EntityDef;;
const #392 = Asciz	n;
const #393 = Asciz	temp80;
const #394 = Asciz	av;
const #395 = Asciz	attrDecl;
const #396 = Asciz	TTLIST;
const #397 = String	#396;	//  TTLIST
const #398 = Asciz	scala/runtime/BoxedUnit;
const #399 = class	#398;	//  scala/runtime/BoxedUnit
const #400 = Asciz	UNIT;
const #401 = Asciz	Lscala/runtime/BoxedUnit;;
const #402 = NameAndType	#400:#401;//  UNIT:Lscala/runtime/BoxedUnit;
const #403 = Field	#399.#402;	//  scala/runtime/BoxedUnit.UNIT:Lscala/runtime/BoxedUnit;
const #404 = Asciz	FIXED;
const #405 = String	#404;	//  FIXED
const #406 = Asciz	xAttributeValue;
const #407 = NameAndType	#406:#179;//  xAttributeValue:()Ljava/lang/String;
const #408 = InterfaceMethod	#8.#407;	//  scala/xml/parsing/MarkupParser.xAttributeValue:()Ljava/lang/String;
const #409 = Asciz	scala/xml/dtd/DEFAULT;
const #410 = class	#409;	//  scala/xml/dtd/DEFAULT
const #411 = Asciz	(ZLjava/lang/String;)V;
const #412 = NameAndType	#39:#411;//  "<init>":(ZLjava/lang/String;)V
const #413 = Method	#410.#412;	//  scala/xml/dtd/DEFAULT."<init>":(ZLjava/lang/String;)V
const #414 = Asciz	IMPLIED;
const #415 = String	#414;	//  IMPLIED
const #416 = Asciz	scala/xml/dtd/IMPLIED$;
const #417 = class	#416;	//  scala/xml/dtd/IMPLIED$
const #418 = Asciz	Lscala/xml/dtd/IMPLIED$;;
const #419 = NameAndType	#25:#418;//  MODULE$:Lscala/xml/dtd/IMPLIED$;
const #420 = Field	#417.#419;	//  scala/xml/dtd/IMPLIED$.MODULE$:Lscala/xml/dtd/IMPLIED$;
const #421 = Asciz	REQUIRED;
const #422 = String	#421;	//  REQUIRED
const #423 = Asciz	scala/xml/dtd/REQUIRED$;
const #424 = class	#423;	//  scala/xml/dtd/REQUIRED$
const #425 = Asciz	Lscala/xml/dtd/REQUIRED$;;
const #426 = NameAndType	#25:#425;//  MODULE$:Lscala/xml/dtd/REQUIRED$;
const #427 = Field	#424.#426;	//  scala/xml/dtd/REQUIRED$.MODULE$:Lscala/xml/dtd/REQUIRED$;
const #428 = Asciz	java/lang/String;
const #429 = class	#428;	//  java/lang/String
const #430 = Method	#429.#180;	//  java/lang/String.toString:()Ljava/lang/String;
const #431 = Asciz	scala/xml/dtd/AttrDecl;
const #432 = class	#431;	//  scala/xml/dtd/AttrDecl
const #433 = Asciz	(Ljava/lang/String;Ljava/lang/String;Lscala/xml/dtd/DefaultDecl;)V;
const #434 = NameAndType	#39:#433;//  "<init>":(Ljava/lang/String;Ljava/lang/String;Lscala/xml/dtd/DefaultDecl;)V
const #435 = Method	#432.#434;	//  scala/xml/dtd/AttrDecl."<init>":(Ljava/lang/String;Ljava/lang/String;Lscala/xml/dtd/DefaultDecl;)V
const #436 = Asciz	reverse;
const #437 = NameAndType	#436:#76;//  reverse:()Lscala/collection/immutable/List;
const #438 = Method	#238.#437;	//  scala/collection/immutable/List.reverse:()Lscala/collection/immutable/List;
const #439 = Asciz	attListDecl;
const #440 = Asciz	(Ljava/lang/String;Lscala/collection/immutable/List;)V;
const #441 = NameAndType	#439:#440;//  attListDecl:(Ljava/lang/String;Lscala/collection/immutable/List;)V
const #442 = Method	#18.#441;	//  scala/xml/parsing/MarkupHandler.attListDecl:(Ljava/lang/String;Lscala/collection/immutable/List;)V
const #443 = Asciz	attList;
const #444 = Asciz	Lscala/collection/immutable/List;;
const #445 = Asciz	aname;
const #446 = Asciz	defdecl;
const #447 = Asciz	Lscala/xml/dtd/DefaultDecl;;
const #448 = Asciz	atpe;
const #449 = Asciz	temp79;
const #450 = Asciz	defValue;
const #451 = Asciz	temp75;
const #452 = Asciz	elementDecl;
const #453 = Asciz	EMENT;
const #454 = String	#453;	//  EMENT
const #455 = Asciz	putChar;
const #456 = NameAndType	#455:#140;//  putChar:(C)Lscala/collection/mutable/StringBuilder;
const #457 = InterfaceMethod	#8.#456;	//  scala/xml/parsing/MarkupParser.putChar:(C)Lscala/collection/mutable/StringBuilder;
const #458 = Asciz	elemDecl;
const #459 = NameAndType	#458:#329;//  elemDecl:(Ljava/lang/String;Ljava/lang/String;)V
const #460 = Method	#18.#459;	//  scala/xml/parsing/MarkupHandler.elemDecl:(Ljava/lang/String;Ljava/lang/String;)V
const #461 = Asciz	cmstr;
const #462 = Asciz	intSubset;
const #463 = Asciz	isValidating;
const #464 = NameAndType	#463:#122;//  isValidating:()Z
const #465 = Method	#18.#464;	//  scala/xml/parsing/MarkupHandler.isValidating:()Z
const #466 = NameAndType	#266:#341;//  push:(Ljava/lang/String;)V
const #467 = InterfaceMethod	#8.#466;	//  scala/xml/parsing/MarkupParser.push:(Ljava/lang/String;)V
const #468 = Asciz	peReference;
const #469 = NameAndType	#468:#341;//  peReference:(Ljava/lang/String;)V
const #470 = Method	#18.#469;	//  scala/xml/parsing/MarkupHandler.peReference:(Ljava/lang/String;)V
const #471 = Asciz	markupDecl1;
const #472 = NameAndType	#471:#126;//  markupDecl1:()Ljava/lang/Object;
const #473 = InterfaceMethod	#8.#472;	//  scala/xml/parsing/MarkupParser.markupDecl1:()Ljava/lang/Object;
const #474 = Asciz	scala/xml/parsing/MarkupParser$class;
const #475 = class	#474;	//  scala/xml/parsing/MarkupParser$class
const #476 = NameAndType	#62:#63;//  gd2$1:(Lscala/xml/parsing/MarkupParser;)Z
const #477 = Method	#475.#476;	//  scala/xml/parsing/MarkupParser$class.gd2$1:(Lscala/xml/parsing/MarkupParser;)Z
const #478 = Method	#38.#41;	//  scala/collection/mutable/StringBuilder."<init>":()V
const #479 = Asciz	markupdecl: unexpected character ';
const #480 = String	#479;	//  markupdecl: unexpected character '
const #481 = Asciz	(Ljava/lang/Object;)Lscala/collection/mutable/StringBuilder;;
const #482 = NameAndType	#139:#481;//  append:(Ljava/lang/Object;)Lscala/collection/mutable/StringBuilder;
const #483 = Method	#38.#482;	//  scala/collection/mutable/StringBuilder.append:(Ljava/lang/Object;)Lscala/collection/mutable/StringBuilder;
const #484 = Asciz	' #;
const #485 = String	#484;	//  ' #
const #486 = Method	#38.#180;	//  scala/collection/mutable/StringBuilder.toString:()Ljava/lang/String;
const #487 = Asciz	temp72;
const #488 = Asciz	ent;
const #489 = Asciz	(Lscala/xml/parsing/MarkupParser;)Ljava/lang/Object;;
const #490 = int	63;
const #491 = Asciz	xProcInstr;
const #492 = Asciz	()Lscala/xml/NodeSeq;;
const #493 = NameAndType	#491:#492;//  xProcInstr:()Lscala/xml/NodeSeq;
const #494 = InterfaceMethod	#8.#493;	//  scala/xml/parsing/MarkupParser.xProcInstr:()Lscala/xml/NodeSeq;
const #495 = int	33;
const #496 = NameAndType	#74:#63;//  gd1$1:(Lscala/xml/parsing/MarkupParser;)Z
const #497 = Method	#475.#496;	//  scala/xml/parsing/MarkupParser$class.gd1$1:(Lscala/xml/parsing/MarkupParser;)Z
const #498 = Asciz	NCLUDE;
const #499 = String	#498;	//  NCLUDE
const #500 = NameAndType	#98:#4;//  doInclude$1:(Lscala/xml/parsing/MarkupParser;)V
const #501 = Method	#475.#500;	//  scala/xml/parsing/MarkupParser$class.doInclude$1:(Lscala/xml/parsing/MarkupParser;)V
const #502 = Asciz	NORE;
const #503 = String	#502;	//  NORE
const #504 = NameAndType	#88:#4;//  doIgnore$1:(Lscala/xml/parsing/MarkupParser;)V
const #505 = Method	#475.#504;	//  scala/xml/parsing/MarkupParser$class.doIgnore$1:(Lscala/xml/parsing/MarkupParser;)V
const #506 = Asciz	INCLUDE;
const #507 = String	#506;	//  INCLUDE
const #508 = Asciz	IGNORE;
const #509 = String	#508;	//  IGNORE
const #510 = Asciz	unexpected character ';
const #511 = String	#510;	//  unexpected character '
const #512 = Asciz	', expected some markupdecl;
const #513 = String	#512;	//  ', expected some markupdecl
const #514 = NameAndType	#298:#40;//  notationDecl:()V
const #515 = InterfaceMethod	#8.#514;	//  scala/xml/parsing/MarkupParser.notationDecl:()V
const #516 = int	76;
const #517 = NameAndType	#452:#40;//  elementDecl:()V
const #518 = InterfaceMethod	#8.#517;	//  scala/xml/parsing/MarkupParser.elementDecl:()V
const #519 = NameAndType	#355:#40;//  entityDecl:()V
const #520 = InterfaceMethod	#8.#519;	//  scala/xml/parsing/MarkupParser.entityDecl:()V
const #521 = NameAndType	#395:#40;//  attrDecl:()V
const #522 = InterfaceMethod	#8.#521;	//  scala/xml/parsing/MarkupParser.attrDecl:()V
const #523 = Asciz	xComment;
const #524 = NameAndType	#523:#492;//  xComment:()Lscala/xml/NodeSeq;
const #525 = InterfaceMethod	#8.#524;	//  scala/xml/parsing/MarkupParser.xComment:()Lscala/xml/NodeSeq;
const #526 = Asciz	temp71;
const #527 = Asciz	temp70;
const #528 = Asciz	stmt;
const #529 = Asciz	temp66;
const #530 = Asciz	temp69;
const #531 = Asciz	qual$1;
const #532 = Asciz	x$8;
const #533 = Asciz	x$9;
const #534 = Asciz	x$10;
const #535 = Asciz	extSubset;
const #536 = Asciz	textDecl;
const #537 = Asciz	()Lscala/Tuple2;;
const #538 = NameAndType	#536:#537;//  textDecl:()Lscala/Tuple2;
const #539 = InterfaceMethod	#8.#538;	//  scala/xml/parsing/MarkupParser.textDecl:()Lscala/Tuple2;
const #540 = Asciz	textdecl;
const #541 = Asciz	Lscala/Tuple2;;
const #542 = Asciz	(Lscala/xml/parsing/MarkupParser;)Ljava/lang/String;;
const #543 = Asciz	quote ' or \" expected;
const #544 = String	#543;	//  quote ' or \" expected
const #545 = Asciz	isPubIDChar;
const #546 = NameAndType	#545:#71;//  isPubIDChar:(C)Z
const #547 = InterfaceMethod	#69.#546;	//  scala/xml/parsing/TokenTests.isPubIDChar:(C)Z
const #548 = Asciz	char ';
const #549 = String	#548;	//  char '
const #550 = Asciz	' is not allowed in public id;
const #551 = String	#550;	//  ' is not allowed in public id
const #552 = Asciz	endch;
const #553 = Asciz	xText;
const #554 = Asciz	exit;
const #555 = Asciz	opos;
const #556 = Asciz	(Lscala/xml/parsing/MarkupParser;)Lscala/xml/NodeSeq;;
const #557 = Method	#38.#83;	//  scala/collection/mutable/StringBuilder.length:()I
const #558 = Asciz	tmppos;
const #559 = NameAndType	#558:#82;//  tmppos:()I
const #560 = InterfaceMethod	#8.#559;	//  scala/xml/parsing/MarkupParser.tmppos:()I
const #561 = Asciz	procInstr;
const #562 = Asciz	(ILjava/lang/String;Ljava/lang/String;)Lscala/xml/NodeSeq;;
const #563 = NameAndType	#561:#562;//  procInstr:(ILjava/lang/String;Ljava/lang/String;)Lscala/xml/NodeSeq;
const #564 = Method	#18.#563;	//  scala/xml/parsing/MarkupHandler.procInstr:(ILjava/lang/String;Ljava/lang/String;)Lscala/xml/NodeSeq;
const #565 = Asciz	sb;
const #566 = Asciz	whitespace expected;
const #567 = String	#566;	//  whitespace expected
const #568 = Asciz	xEQ;
const #569 = int	61;
const #570 = Asciz	isNameStart;
const #571 = NameAndType	#570:#71;//  isNameStart:(C)Z
const #572 = InterfaceMethod	#69.#571;	//  scala/xml/parsing/TokenTests.isNameStart:(C)Z
const #573 = Asciz	isNameChar;
const #574 = NameAndType	#573:#71;//  isNameChar:(C)Z
const #575 = InterfaceMethod	#69.#574;	//  scala/xml/parsing/TokenTests.isNameChar:(C)Z
const #576 = Asciz	intern;
const #577 = NameAndType	#576:#179;//  intern:()Ljava/lang/String;
const #578 = Method	#429.#577;	//  java/lang/String.intern:()Ljava/lang/String;
const #579 = Asciz	name expected;
const #580 = String	#579;	//  name expected
const #581 = Asciz	;
const #582 = String	#581;	//  
const #583 = Asciz	element1;
const #584 = Asciz	(Lscala/xml/parsing/MarkupParser;Lscala/xml/NamespaceBinding;)Lscala/xml/NodeSeq;;
const #585 = Asciz	xTag;
const #586 = Asciz	(Lscala/xml/NamespaceBinding;)Lscala/Tuple3;;
const #587 = NameAndType	#585:#586;//  xTag:(Lscala/xml/NamespaceBinding;)Lscala/Tuple3;
const #588 = InterfaceMethod	#8.#587;	//  scala/xml/parsing/MarkupParser.xTag:(Lscala/xml/NamespaceBinding;)Lscala/Tuple3;
const #589 = Asciz	scala/Tuple3;
const #590 = class	#589;	//  scala/Tuple3
const #591 = Asciz	_1;
const #592 = NameAndType	#591:#126;//  _1:()Ljava/lang/Object;
const #593 = Method	#590.#592;	//  scala/Tuple3._1:()Ljava/lang/Object;
const #594 = Asciz	_2;
const #595 = NameAndType	#594:#126;//  _2:()Ljava/lang/Object;
const #596 = Method	#590.#595;	//  scala/Tuple3._2:()Ljava/lang/Object;
const #597 = Asciz	scala/xml/MetaData;
const #598 = class	#597;	//  scala/xml/MetaData
const #599 = Asciz	_3;
const #600 = NameAndType	#599:#126;//  _3:()Ljava/lang/Object;
const #601 = Method	#590.#600;	//  scala/Tuple3._3:()Ljava/lang/Object;
const #602 = Asciz	scala/xml/NamespaceBinding;
const #603 = class	#602;	//  scala/xml/NamespaceBinding
const #604 = Asciz	(Ljava/lang/Object;Ljava/lang/Object;Ljava/lang/Object;)V;
const #605 = NameAndType	#39:#604;//  "<init>":(Ljava/lang/Object;Ljava/lang/Object;Ljava/lang/Object;)V
const #606 = Method	#590.#605;	//  scala/Tuple3."<init>":(Ljava/lang/Object;Ljava/lang/Object;Ljava/lang/Object;)V
const #607 = Asciz	scala/xml/Utility$;
const #608 = class	#607;	//  scala/xml/Utility$
const #609 = Asciz	Lscala/xml/Utility$;;
const #610 = NameAndType	#25:#609;//  MODULE$:Lscala/xml/Utility$;
const #611 = Field	#608.#610;	//  scala/xml/Utility$.MODULE$:Lscala/xml/Utility$;
const #612 = Asciz	prefix;
const #613 = Asciz	(Ljava/lang/String;)Lscala/Option;;
const #614 = NameAndType	#612:#613;//  prefix:(Ljava/lang/String;)Lscala/Option;
const #615 = Method	#608.#614;	//  scala/xml/Utility$.prefix:(Ljava/lang/String;)Lscala/Option;
const #616 = Asciz	scala/Some;
const #617 = class	#616;	//  scala/Some
const #618 = Asciz	x;
const #619 = NameAndType	#618:#126;//  x:()Ljava/lang/Object;
const #620 = Method	#617.#619;	//  scala/Some.x:()Ljava/lang/Object;
const #621 = Asciz	scala/Tuple2;
const #622 = class	#621;	//  scala/Tuple2
const #623 = Method	#429.#83;	//  java/lang/String.length:()I
const #624 = Asciz	substring;
const #625 = Asciz	(II)Ljava/lang/String;;
const #626 = NameAndType	#624:#625;//  substring:(II)Ljava/lang/String;
const #627 = Method	#429.#626;	//  java/lang/String.substring:(II)Ljava/lang/String;
const #628 = Asciz	(Ljava/lang/Object;Ljava/lang/Object;)V;
const #629 = NameAndType	#39:#628;//  "<init>":(Ljava/lang/Object;Ljava/lang/Object;)V
const #630 = Method	#622.#629;	//  scala/Tuple2."<init>":(Ljava/lang/Object;Ljava/lang/Object;)V
const #631 = Method	#622.#592;	//  scala/Tuple2._1:()Ljava/lang/Object;
const #632 = Method	#622.#595;	//  scala/Tuple2._2:()Ljava/lang/Object;
const #633 = int	47;
const #634 = Asciz	elemStart;
const #635 = Asciz	(ILjava/lang/String;Ljava/lang/String;Lscala/xml/MetaData;Lscala/xml/NamespaceBinding;)V;
const #636 = NameAndType	#634:#635;//  elemStart:(ILjava/lang/String;Ljava/lang/String;Lscala/xml/MetaData;Lscala/xml/NamespaceBinding;)V
const #637 = Method	#18.#636;	//  scala/xml/parsing/MarkupHandler.elemStart:(ILjava/lang/String;Ljava/lang/String;Lscala/xml/MetaData;Lscala/xml/NamespaceBinding;)V
const #638 = Asciz	scala/xml/NodeSeq$;
const #639 = class	#638;	//  scala/xml/NodeSeq$
const #640 = Asciz	Lscala/xml/NodeSeq$;;
const #641 = NameAndType	#25:#640;//  MODULE$:Lscala/xml/NodeSeq$;
const #642 = Field	#639.#641;	//  scala/xml/NodeSeq$.MODULE$:Lscala/xml/NodeSeq$;
const #643 = Asciz	Empty;
const #644 = NameAndType	#643:#492;//  Empty:()Lscala/xml/NodeSeq;
const #645 = Method	#639.#644;	//  scala/xml/NodeSeq$.Empty:()Lscala/xml/NodeSeq;
const #646 = Asciz	content;
const #647 = Asciz	(Lscala/xml/NamespaceBinding;)Lscala/xml/NodeSeq;;
const #648 = NameAndType	#646:#647;//  content:(Lscala/xml/NamespaceBinding;)Lscala/xml/NodeSeq;
const #649 = InterfaceMethod	#8.#648;	//  scala/xml/parsing/MarkupParser.content:(Lscala/xml/NamespaceBinding;)Lscala/xml/NodeSeq;
const #650 = Asciz	xEndTag;
const #651 = NameAndType	#650:#341;//  xEndTag:(Ljava/lang/String;)V
const #652 = InterfaceMethod	#8.#651;	//  scala/xml/parsing/MarkupParser.xEndTag:(Ljava/lang/String;)V
const #653 = Asciz	elem;
const #654 = Asciz	(ILjava/lang/String;Ljava/lang/String;Lscala/xml/MetaData;Lscala/xml/NamespaceBinding;Lscala/xml/NodeSeq;)Lscala/xml/NodeSeq;;
const #655 = NameAndType	#653:#654;//  elem:(ILjava/lang/String;Ljava/lang/String;Lscala/xml/MetaData;Lscala/xml/NamespaceBinding;Lscala/xml/NodeSeq;)Lscala/xml/NodeSeq;
const #656 = Method	#18.#655;	//  scala/xml/parsing/MarkupHandler.elem:(ILjava/lang/String;Ljava/lang/String;Lscala/xml/MetaData;Lscala/xml/NamespaceBinding;Lscala/xml/NodeSeq;)Lscala/xml/NodeSeq;
const #657 = Asciz	elemEnd;
const #658 = Asciz	(ILjava/lang/String;Ljava/lang/String;)V;
const #659 = NameAndType	#657:#658;//  elemEnd:(ILjava/lang/String;Ljava/lang/String;)V
const #660 = Method	#18.#659;	//  scala/xml/parsing/MarkupHandler.elemEnd:(ILjava/lang/String;Ljava/lang/String;)V
const #661 = Method	#622.#180;	//  scala/Tuple2.toString:()Ljava/lang/String;
const #662 = Method	#590.#180;	//  scala/Tuple3.toString:()Ljava/lang/String;
const #663 = Asciz	pscope;
const #664 = Asciz	Lscala/xml/NamespaceBinding;;
const #665 = Asciz	temp56;
const #666 = Asciz	Lscala/Tuple3;;
const #667 = Asciz	temp57;
const #668 = Asciz	temp58;
const #669 = Asciz	Lscala/xml/MetaData;;
const #670 = Asciz	temp59;
const #671 = Asciz	scope;
const #672 = Asciz	aMap;
const #673 = Asciz	qname;
const #674 = Asciz	temp63;
const #675 = Asciz	temp60;
const #676 = Asciz	Lscala/Option;;
const #677 = Asciz	temp61;
const #678 = Asciz	Lscala/Some;;
const #679 = Asciz	temp62;
const #680 = Asciz	p;
const #681 = Asciz	temp64;
const #682 = Asciz	temp65;
const #683 = Asciz	local;
const #684 = Asciz	pre;
const #685 = Asciz	ts;
const #686 = Asciz	Lscala/xml/NodeSeq;;
const #687 = Asciz	tmp;
const #688 = Asciz	res;
const #689 = Asciz	element;
const #690 = NameAndType	#583:#647;//  element1:(Lscala/xml/NamespaceBinding;)Lscala/xml/NodeSeq;
const #691 = InterfaceMethod	#8.#690;	//  scala/xml/parsing/MarkupParser.element1:(Lscala/xml/NamespaceBinding;)Lscala/xml/NodeSeq;
const #692 = Asciz	parseDTD;
const #693 = Asciz	scala/runtime/ObjectRef;
const #694 = class	#693;	//  scala/runtime/ObjectRef
const #695 = Asciz	(Ljava/lang/Object;)V;
const #696 = NameAndType	#39:#695;//  "<init>":(Ljava/lang/Object;)V
const #697 = Method	#694.#696;	//  scala/runtime/ObjectRef."<init>":(Ljava/lang/Object;)V
const #698 = Asciz	dtd;
const #699 = Asciz	()Lscala/xml/dtd/DTD;;
const #700 = NameAndType	#698:#699;//  dtd:()Lscala/xml/dtd/DTD;
const #701 = InterfaceMethod	#8.#700;	//  scala/xml/parsing/MarkupParser.dtd:()Lscala/xml/dtd/DTD;
const #702 = Asciz	unexpected character (DOCTYPE already defined;
const #703 = String	#702;	//  unexpected character (DOCTYPE already defined
const #704 = Asciz	DOCTYPE;
const #705 = String	#704;	//  DOCTYPE
const #706 = Asciz	Ljava/lang/Object;;
const #707 = NameAndType	#653:#706;//  elem:Ljava/lang/Object;
const #708 = Field	#694.#707;	//  scala/runtime/ObjectRef.elem:Ljava/lang/Object;
const #709 = Asciz	scala/xml/dtd/ExternalID;
const #710 = class	#709;	//  scala/xml/dtd/ExternalID
const #711 = NameAndType	#265:#179;//  systemId:()Ljava/lang/String;
const #712 = Method	#710.#711;	//  scala/xml/dtd/ExternalID.systemId:()Ljava/lang/String;
const #713 = NameAndType	#252:#341;//  pushExternal:(Ljava/lang/String;)V
const #714 = InterfaceMethod	#8.#713;	//  scala/xml/parsing/MarkupParser.pushExternal:(Ljava/lang/String;)V
const #715 = NameAndType	#535:#40;//  extSubset:()V
const #716 = InterfaceMethod	#8.#715;	//  scala/xml/parsing/MarkupParser.extSubset:()V
const #717 = NameAndType	#225:#40;//  pop:()V
const #718 = InterfaceMethod	#8.#717;	//  scala/xml/parsing/MarkupParser.pop:()V
const #719 = NameAndType	#462:#40;//  intSubset:()V
const #720 = InterfaceMethod	#8.#719;	//  scala/xml/parsing/MarkupParser.intSubset:()V
const #721 = Asciz	scala/xml/parsing/MarkupParser$$anon$2;
const #722 = class	#721;	//  scala/xml/parsing/MarkupParser$$anon$2
const #723 = Asciz	(Lscala/xml/parsing/MarkupParser;Lscala/runtime/ObjectRef;)V;
const #724 = NameAndType	#39:#723;//  "<init>":(Lscala/xml/parsing/MarkupParser;Lscala/runtime/ObjectRef;)V
const #725 = Method	#722.#724;	//  scala/xml/parsing/MarkupParser$$anon$2."<init>":(Lscala/xml/parsing/MarkupParser;Lscala/runtime/ObjectRef;)V
const #726 = Asciz	doc;
const #727 = Asciz	()Lscala/xml/Document;;
const #728 = NameAndType	#726:#727;//  doc:()Lscala/xml/Document;
const #729 = InterfaceMethod	#8.#728;	//  scala/xml/parsing/MarkupParser.doc:()Lscala/xml/Document;
const #730 = Asciz	scala/xml/Document;
const #731 = class	#730;	//  scala/xml/Document
const #732 = Method	#731.#49;	//  scala/xml/Document.dtd_$eq:(Lscala/xml/dtd/DTD;)V
const #733 = Asciz	endDTD;
const #734 = NameAndType	#733:#341;//  endDTD:(Ljava/lang/String;)V
const #735 = Method	#18.#734;	//  scala/xml/parsing/MarkupHandler.endDTD:(Ljava/lang/String;)V
const #736 = Asciz	extID$1;
const #737 = Asciz	Lscala/runtime/ObjectRef;;
const #738 = Asciz	(Lscala/xml/parsing/MarkupParser;)Lscala/xml/dtd/ExternalID;;
const #739 = Asciz	YSTEM;
const #740 = String	#739;	//  YSTEM
const #741 = Asciz	scala/xml/dtd/SystemID;
const #742 = class	#741;	//  scala/xml/dtd/SystemID
const #743 = Method	#742.#362;	//  scala/xml/dtd/SystemID."<init>":(Ljava/lang/String;)V
const #744 = Asciz	temp55;
const #745 = Asciz	scala/xml/NodeBuffer;
const #746 = class	#745;	//  scala/xml/NodeBuffer
const #747 = Method	#746.#41;	//  scala/xml/NodeBuffer."<init>":()V
const #748 = Asciz	toList;
const #749 = NameAndType	#748:#76;//  toList:()Lscala/collection/immutable/List;
const #750 = InterfaceMethod	#232.#749;	//  scala/collection/generic/TraversableTemplate.toList:()Lscala/collection/immutable/List;
const #751 = Asciz	scala/xml/parsing/MarkupParser$$anon$1;
const #752 = class	#751;	//  scala/xml/parsing/MarkupParser$$anon$1
const #753 = Asciz	(Lscala/xml/parsing/MarkupParser;Lscala/collection/immutable/List;)V;
const #754 = NameAndType	#39:#753;//  "<init>":(Lscala/xml/parsing/MarkupParser;Lscala/collection/immutable/List;)V
const #755 = Method	#752.#754;	//  scala/xml/parsing/MarkupParser$$anon$1."<init>":(Lscala/xml/parsing/MarkupParser;Lscala/collection/immutable/List;)V
const #756 = Asciz	tmppos_$eq;
const #757 = NameAndType	#756:#34;//  tmppos_$eq:(I)V
const #758 = InterfaceMethod	#8.#757;	//  scala/xml/parsing/MarkupParser.tmppos_$eq:(I)V
const #759 = NameAndType	#553:#179;//  xText:()Ljava/lang/String;
const #760 = InterfaceMethod	#8.#759;	//  scala/xml/parsing/MarkupParser.xText:()Ljava/lang/String;
const #761 = Asciz	appendText;
const #762 = Asciz	(ILscala/xml/NodeBuffer;Ljava/lang/String;)V;
const #763 = NameAndType	#761:#762;//  appendText:(ILscala/xml/NodeBuffer;Ljava/lang/String;)V
const #764 = InterfaceMethod	#8.#763;	//  scala/xml/parsing/MarkupParser.appendText:(ILscala/xml/NodeBuffer;Ljava/lang/String;)V
const #765 = Asciz	content1;
const #766 = Asciz	(Lscala/xml/NamespaceBinding;Lscala/xml/NodeBuffer;)V;
const #767 = NameAndType	#765:#766;//  content1:(Lscala/xml/NamespaceBinding;Lscala/xml/NodeBuffer;)V
const #768 = InterfaceMethod	#8.#767;	//  scala/xml/parsing/MarkupParser.content1:(Lscala/xml/NamespaceBinding;Lscala/xml/NodeBuffer;)V
const #769 = Asciz	scala/xml/parsing/MarkupParser$$anonfun$1;
const #770 = class	#769;	//  scala/xml/parsing/MarkupParser$$anonfun$1
const #771 = NameAndType	#39:#4;//  "<init>":(Lscala/xml/parsing/MarkupParser;)V
const #772 = Method	#770.#771;	//  scala/xml/parsing/MarkupParser$$anonfun$1."<init>":(Lscala/xml/parsing/MarkupParser;)V
const #773 = Asciz	scala/xml/parsing/MarkupParser$$anonfun$2;
const #774 = class	#773;	//  scala/xml/parsing/MarkupParser$$anonfun$2
const #775 = Method	#774.#771;	//  scala/xml/parsing/MarkupParser$$anonfun$2."<init>":(Lscala/xml/parsing/MarkupParser;)V
const #776 = Asciz	text;
const #777 = Asciz	(ILjava/lang/String;)Lscala/xml/NodeSeq;;
const #778 = NameAndType	#776:#777;//  text:(ILjava/lang/String;)Lscala/xml/NodeSeq;
const #779 = Method	#18.#778;	//  scala/xml/parsing/MarkupHandler.text:(ILjava/lang/String;)Lscala/xml/NodeSeq;
const #780 = Asciz	$amp$plus;
const #781 = Asciz	(Ljava/lang/Object;)Lscala/xml/NodeBuffer;;
const #782 = NameAndType	#780:#781;//  $amp$plus:(Ljava/lang/Object;)Lscala/xml/NodeBuffer;
const #783 = Method	#746.#782;	//  scala/xml/NodeBuffer.$amp$plus:(Ljava/lang/Object;)Lscala/xml/NodeBuffer;
const #784 = Asciz	Lscala/xml/NodeBuffer;;
const #785 = Asciz	temp54;
const #786 = Asciz	temp53;
const #787 = Asciz	theChar;
const #788 = Asciz	temp48;
const #789 = Asciz	list$1;
const #790 = Asciz	(Lscala/xml/parsing/MarkupParser;Lscala/xml/NamespaceBinding;Lscala/xml/NodeBuffer;)V;
const #791 = Asciz	xCharData;
const #792 = NameAndType	#791:#492;//  xCharData:()Lscala/xml/NodeSeq;
const #793 = InterfaceMethod	#8.#792;	//  scala/xml/parsing/MarkupParser.xCharData:()Lscala/xml/NodeSeq;
const #794 = int	68;
const #795 = NameAndType	#692:#40;//  parseDTD:()V
const #796 = InterfaceMethod	#8.#795;	//  scala/xml/parsing/MarkupParser.parseDTD:()V
const #797 = Asciz	temp47;
const #798 = Asciz	(Lscala/xml/parsing/MarkupParser;ILscala/xml/NodeBuffer;Ljava/lang/String;)V;
const #799 = Asciz	preserveWS;
const #800 = NameAndType	#799:#122;//  preserveWS:()Z
const #801 = InterfaceMethod	#8.#800;	//  scala/xml/parsing/MarkupParser.preserveWS:()Z
const #802 = Asciz	scala/xml/TextBuffer$;
const #803 = class	#802;	//  scala/xml/TextBuffer$
const #804 = Asciz	Lscala/xml/TextBuffer$;;
const #805 = NameAndType	#25:#804;//  MODULE$:Lscala/xml/TextBuffer$;
const #806 = Field	#803.#805;	//  scala/xml/TextBuffer$.MODULE$:Lscala/xml/TextBuffer$;
const #807 = Asciz	fromString;
const #808 = Asciz	(Ljava/lang/String;)Lscala/xml/TextBuffer;;
const #809 = NameAndType	#807:#808;//  fromString:(Ljava/lang/String;)Lscala/xml/TextBuffer;
const #810 = Method	#803.#809;	//  scala/xml/TextBuffer$.fromString:(Ljava/lang/String;)Lscala/xml/TextBuffer;
const #811 = Asciz	scala/xml/TextBuffer;
const #812 = class	#811;	//  scala/xml/TextBuffer
const #813 = Asciz	toText;
const #814 = Asciz	()Lscala/collection/Sequence;;
const #815 = NameAndType	#813:#814;//  toText:()Lscala/collection/Sequence;
const #816 = Method	#812.#815;	//  scala/xml/TextBuffer.toText:()Lscala/collection/Sequence;
const #817 = Asciz	scala/xml/parsing/MarkupParser$$anonfun$appendText$1;
const #818 = class	#817;	//  scala/xml/parsing/MarkupParser$$anonfun$appendText$1
const #819 = Asciz	(Lscala/xml/parsing/MarkupParser;ILscala/xml/NodeBuffer;)V;
const #820 = NameAndType	#39:#819;//  "<init>":(Lscala/xml/parsing/MarkupParser;ILscala/xml/NodeBuffer;)V
const #821 = Method	#818.#820;	//  scala/xml/parsing/MarkupParser$$anonfun$appendText$1."<init>":(Lscala/xml/parsing/MarkupParser;ILscala/xml/NodeBuffer;)V
const #822 = Asciz	foreach;
const #823 = Asciz	(Lscala/Function1;)V;
const #824 = NameAndType	#822:#823;//  foreach:(Lscala/Function1;)V
const #825 = InterfaceMethod	#114.#824;	//  scala/collection/generic/IterableTemplate.foreach:(Lscala/Function1;)V
const #826 = Asciz	pos$1;
const #827 = Asciz	ts$1;
const #828 = Asciz	txt;
const #829 = int	45;
const #830 = Asciz	comment;
const #831 = NameAndType	#830:#777;//  comment:(ILjava/lang/String;)Lscala/xml/NodeSeq;
const #832 = Method	#18.#831;	//  scala/xml/parsing/MarkupHandler.comment:(ILjava/lang/String;)Lscala/xml/NodeSeq;
const #833 = Asciz	(Lscala/xml/parsing/MarkupParser;Lscala/Function0;Lscala/Function0;)Ljava/lang/String;;
const #834 = Asciz	scala/xml/parsing/MarkupParser$$anonfun$xCharRef$1;
const #835 = class	#834;	//  scala/xml/parsing/MarkupParser$$anonfun$xCharRef$1
const #836 = Method	#835.#771;	//  scala/xml/parsing/MarkupParser$$anonfun$xCharRef$1."<init>":(Lscala/xml/parsing/MarkupParser;)V
const #837 = Asciz	parseCharRef;
const #838 = Asciz	(Lscala/Function0;Lscala/Function0;Lscala/Function1;)Ljava/lang/String;;
const #839 = NameAndType	#837:#838;//  parseCharRef:(Lscala/Function0;Lscala/Function0;Lscala/Function1;)Ljava/lang/String;
const #840 = Method	#608.#839;	//  scala/xml/Utility$.parseCharRef:(Lscala/Function0;Lscala/Function0;Lscala/Function1;)Ljava/lang/String;
const #841 = Asciz	Lscala/Function0;;
const #842 = Asciz	[CDATA[;
const #843 = String	#842;	//  [CDATA[
const #844 = Asciz	pos1;
const #845 = Asciz	expected closing tag of ;
const #846 = String	#845;	//  expected closing tag of 
const #847 = Asciz	m;
const #848 = Asciz	(Lscala/xml/parsing/MarkupParser;Lscala/xml/NamespaceBinding;)Lscala/Tuple3;;
const #849 = Asciz	xAttributes;
const #850 = Asciz	(Lscala/xml/NamespaceBinding;)Lscala/Tuple2;;
const #851 = NameAndType	#849:#850;//  xAttributes:(Lscala/xml/NamespaceBinding;)Lscala/Tuple2;
const #852 = InterfaceMethod	#8.#851;	//  scala/xml/parsing/MarkupParser.xAttributes:(Lscala/xml/NamespaceBinding;)Lscala/Tuple2;
const #853 = Asciz	scala/xml/Null$;
const #854 = class	#853;	//  scala/xml/Null$
const #855 = Asciz	Lscala/xml/Null$;;
const #856 = NameAndType	#25:#855;//  MODULE$:Lscala/xml/Null$;
const #857 = Field	#854.#856;	//  scala/xml/Null$.MODULE$:Lscala/xml/Null$;
const #858 = Asciz	temp41;
const #859 = Asciz	temp42;
const #860 = Asciz	temp43;
const #861 = Asciz	'<' not allowed in attrib value;
const #862 = String	#861;	//  '<' not allowed in attrib value
const #863 = Asciz	(Ljava/lang/String;)Ljava/lang/String;;
const #864 = NameAndType	#102:#863;//  normalizeAttributeValue:(Ljava/lang/String;)Ljava/lang/String;
const #865 = InterfaceMethod	#8.#864;	//  scala/xml/parsing/MarkupParser.normalizeAttributeValue:(Ljava/lang/String;)Ljava/lang/String;
const #866 = Asciz	(Lscala/xml/parsing/MarkupParser;Lscala/xml/NamespaceBinding;)Lscala/Tuple2;;
const #867 = NameAndType	#568:#40;//  xEQ:()V
const #868 = InterfaceMethod	#8.#867;	//  scala/xml/parsing/MarkupParser.xEQ:()V
const #869 = Asciz	xmlns;
const #870 = String	#869;	//  xmlns
const #871 = int	6;
const #872 = Asciz	(Ljava/lang/String;Ljava/lang/String;Lscala/xml/NamespaceBinding;)V;
const #873 = NameAndType	#39:#872;//  "<init>":(Ljava/lang/String;Ljava/lang/String;Lscala/xml/NamespaceBinding;)V
const #874 = Method	#603.#873;	//  scala/xml/NamespaceBinding."<init>":(Ljava/lang/String;Ljava/lang/String;Lscala/xml/NamespaceBinding;)V
const #875 = Asciz	scala/xml/PrefixedAttribute;
const #876 = class	#875;	//  scala/xml/PrefixedAttribute
const #877 = Asciz	scala/xml/Text;
const #878 = class	#877;	//  scala/xml/Text
const #879 = Method	#878.#362;	//  scala/xml/Text."<init>":(Ljava/lang/String;)V
const #880 = Asciz	(Ljava/lang/String;Ljava/lang/String;Lscala/collection/Sequence;Lscala/xml/MetaData;)V;
const #881 = NameAndType	#39:#880;//  "<init>":(Ljava/lang/String;Ljava/lang/String;Lscala/collection/Sequence;Lscala/xml/MetaData;)V
const #882 = Method	#876.#881;	//  scala/xml/PrefixedAttribute."<init>":(Ljava/lang/String;Ljava/lang/String;Lscala/collection/Sequence;Lscala/xml/MetaData;)V
const #883 = Asciz	scala/xml/UnprefixedAttribute;
const #884 = class	#883;	//  scala/xml/UnprefixedAttribute
const #885 = Asciz	(Ljava/lang/String;Lscala/collection/Sequence;Lscala/xml/MetaData;)V;
const #886 = NameAndType	#39:#885;//  "<init>":(Ljava/lang/String;Lscala/collection/Sequence;Lscala/xml/MetaData;)V
const #887 = Method	#884.#886;	//  scala/xml/UnprefixedAttribute."<init>":(Ljava/lang/String;Lscala/collection/Sequence;Lscala/xml/MetaData;)V
const #888 = Asciz	wellformed;
const #889 = Asciz	(Lscala/xml/NamespaceBinding;)Z;
const #890 = NameAndType	#888:#889;//  wellformed:(Lscala/xml/NamespaceBinding;)Z
const #891 = Method	#598.#890;	//  scala/xml/MetaData.wellformed:(Lscala/xml/NamespaceBinding;)Z
const #892 = Asciz	double attribute;
const #893 = String	#892;	//  double attribute
const #894 = Asciz	_;
const #895 = Asciz	value;
const #896 = Asciz	temp37;
const #897 = Asciz	temp38;
const #898 = Asciz	temp39;
const #899 = Asciz	key;
const #900 = Asciz	(Lscala/xml/parsing/MarkupParser;Lscala/collection/Sequence;)V;
const #901 = Asciz	that;
const #902 = Asciz	it;
const #903 = Asciz	(Lscala/xml/parsing/MarkupParser;C)V;
const #904 = Asciz	';
const #905 = String	#904;	//  '
const #906 = Asciz	' expected instead of ';
const #907 = String	#906;	//  ' expected instead of '
const #908 = Asciz	FATAL;
const #909 = String	#908;	//  FATAL
const #910 = Method	#230.#123;	//  scala/io/Source.hasNext:()Z
const #911 = NameAndType	#125:#65;//  next:()C
const #912 = Method	#230.#911;	//  scala/io/Source.next:()C
const #913 = Asciz	ilen;
const #914 = Asciz	(Lscala/xml/parsing/MarkupParser;C)Lscala/collection/mutable/StringBuilder;;
const #915 = Asciz	c;
const #916 = Asciz	document;
const #917 = Asciz	(Lscala/xml/parsing/MarkupParser;)Lscala/xml/Document;;
const #918 = Method	#731.#41;	//  scala/xml/Document."<init>":()V
const #919 = Asciz	scala/None$;
const #920 = class	#919;	//  scala/None$
const #921 = Asciz	Lscala/None$;;
const #922 = NameAndType	#25:#921;//  MODULE$:Lscala/None$;
const #923 = Field	#920.#922;	//  scala/None$.MODULE$:Lscala/None$;
const #924 = Asciz	< expected;
const #925 = String	#924;	//  < expected
const #926 = Asciz	prolog;
const #927 = Asciz	()Lscala/Tuple3;;
const #928 = NameAndType	#926:#927;//  prolog:()Lscala/Tuple3;
const #929 = InterfaceMethod	#8.#928;	//  scala/xml/parsing/MarkupParser.prolog:()Lscala/Tuple3;
const #930 = Asciz	scala/Option;
const #931 = class	#930;	//  scala/Option
const #932 = Asciz	version_$eq;
const #933 = Asciz	(Lscala/Option;)V;
const #934 = NameAndType	#932:#933;//  version_$eq:(Lscala/Option;)V
const #935 = Method	#731.#934;	//  scala/xml/Document.version_$eq:(Lscala/Option;)V
const #936 = Asciz	encoding_$eq;
const #937 = NameAndType	#936:#933;//  encoding_$eq:(Lscala/Option;)V
const #938 = Method	#731.#937;	//  scala/xml/Document.encoding_$eq:(Lscala/Option;)V
const #939 = Asciz	standAlone_$eq;
const #940 = NameAndType	#939:#933;//  standAlone_$eq:(Lscala/Option;)V
const #941 = Method	#731.#940;	//  scala/xml/Document.standAlone_$eq:(Lscala/Option;)V
const #942 = Asciz	scala/xml/TopScope$;
const #943 = class	#942;	//  scala/xml/TopScope$
const #944 = Asciz	Lscala/xml/TopScope$;;
const #945 = NameAndType	#25:#944;//  MODULE$:Lscala/xml/TopScope$;
const #946 = Field	#943.#945;	//  scala/xml/TopScope$.MODULE$:Lscala/xml/TopScope$;
const #947 = Asciz	fromSeq;
const #948 = Asciz	(Lscala/collection/Sequence;)Lscala/xml/NodeSeq;;
const #949 = NameAndType	#947:#948;//  fromSeq:(Lscala/collection/Sequence;)Lscala/xml/NodeSeq;
const #950 = Method	#639.#949;	//  scala/xml/NodeSeq$.fromSeq:(Lscala/collection/Sequence;)Lscala/xml/NodeSeq;
const #951 = Asciz	scala/runtime/IntRef;
const #952 = class	#951;	//  scala/runtime/IntRef
const #953 = NameAndType	#39:#34;//  "<init>":(I)V
const #954 = Method	#952.#953;	//  scala/runtime/IntRef."<init>":(I)V
const #955 = Asciz	scala/xml/parsing/MarkupParser$$anonfun$document$1;
const #956 = class	#955;	//  scala/xml/parsing/MarkupParser$$anonfun$document$1
const #957 = Asciz	(Lscala/xml/parsing/MarkupParser;Lscala/runtime/IntRef;Lscala/runtime/ObjectRef;)V;
const #958 = NameAndType	#39:#957;//  "<init>":(Lscala/xml/parsing/MarkupParser;Lscala/runtime/IntRef;Lscala/runtime/ObjectRef;)V
const #959 = Method	#956.#958;	//  scala/xml/parsing/MarkupParser$$anonfun$document$1."<init>":(Lscala/xml/parsing/MarkupParser;Lscala/runtime/IntRef;Lscala/runtime/ObjectRef;)V
const #960 = NameAndType	#653:#281;//  elem:I
const #961 = Field	#952.#960;	//  scala/runtime/IntRef.elem:I
const #962 = Asciz	document must contain exactly one element;
const #963 = String	#962;	//  document must contain exactly one element
const #964 = Asciz	scala/Console$;
const #965 = class	#964;	//  scala/Console$
const #966 = Asciz	Lscala/Console$;;
const #967 = NameAndType	#25:#966;//  MODULE$:Lscala/Console$;
const #968 = Field	#965.#967;	//  scala/Console$.MODULE$:Lscala/Console$;
const #969 = Asciz	println;
const #970 = NameAndType	#969:#695;//  println:(Ljava/lang/Object;)V
const #971 = Method	#965.#970;	//  scala/Console$.println:(Ljava/lang/Object;)V
const #972 = Asciz	children_$eq;
const #973 = NameAndType	#972:#301;//  children_$eq:(Lscala/collection/Sequence;)V
const #974 = Method	#731.#973;	//  scala/xml/Document.children_$eq:(Lscala/collection/Sequence;)V
const #975 = Asciz	scala/xml/Node;
const #976 = class	#975;	//  scala/xml/Node
const #977 = Asciz	docElem_$eq;
const #978 = Asciz	(Lscala/xml/Node;)V;
const #979 = NameAndType	#977:#978;//  docElem_$eq:(Lscala/xml/Node;)V
const #980 = Method	#731.#979;	//  scala/xml/Document.docElem_$eq:(Lscala/xml/Node;)V
const #981 = Asciz	info_prolog;
const #982 = Asciz	children;
const #983 = Asciz	elemCount$1;
const #984 = Asciz	Lscala/runtime/IntRef;;
const #985 = Asciz	theNode$1;
const #986 = Asciz	(Lscala/xml/parsing/MarkupParser;)Lscala/Tuple2;;
const #987 = Asciz	xmlProcInstr;
const #988 = Asciz	()Lscala/xml/MetaData;;
const #989 = NameAndType	#987:#988;//  xmlProcInstr:()Lscala/xml/MetaData;
const #990 = InterfaceMethod	#8.#989;	//  scala/xml/parsing/MarkupParser.xmlProcInstr:()Lscala/xml/MetaData;
const #991 = Asciz	version;
const #992 = String	#991;	//  version
const #993 = Asciz	apply;
const #994 = Asciz	(Ljava/lang/String;)Lscala/collection/Sequence;;
const #995 = NameAndType	#993:#994;//  apply:(Ljava/lang/String;)Lscala/collection/Sequence;
const #996 = Method	#598.#995;	//  scala/xml/MetaData.apply:(Ljava/lang/String;)Lscala/collection/Sequence;
const #997 = Asciz	_data;
const #998 = NameAndType	#997:#179;//  _data:()Ljava/lang/String;
const #999 = Method	#878.#998;	//  scala/xml/Text._data:()Ljava/lang/String;
const #1000 = Asciz	1.0;
const #1001 = String	#1000;	//  1.0
const #1002 = Method	#617.#696;	//  scala/Some."<init>":(Ljava/lang/Object;)V
const #1003 = Asciz	cannot deal with versions != 1.0;
const #1004 = String	#1003;	//  cannot deal with versions != 1.0
const #1005 = Asciz	encoding;
const #1006 = String	#1005;	//  encoding
const #1007 = Asciz	isValidIANAEncoding;
const #1008 = Asciz	(Lscala/collection/Sequence;)Z;
const #1009 = NameAndType	#1007:#1008;//  isValidIANAEncoding:(Lscala/collection/Sequence;)Z
const #1010 = InterfaceMethod	#69.#1009;	//  scala/xml/parsing/TokenTests.isValidIANAEncoding:(Lscala/collection/Sequence;)Z
const #1011 = Asciz	\";
const #1012 = String	#1011;	//  \"
const #1013 = Asciz	\" is not a valid encoding;
const #1014 = String	#1013;	//  \" is not a valid encoding
const #1015 = Method	#598.#83;	//  scala/xml/MetaData.length:()I
const #1016 = Asciz	VersionInfo EncodingDecl? or '?>' expected!;
const #1017 = String	#1016;	//  VersionInfo EncodingDecl? or '?>' expected!
const #1018 = Asciz	scala/collection/generic/SequenceTemplate;
const #1019 = class	#1018;	//  scala/collection/generic/SequenceTemplate
const #1020 = InterfaceMethod	#1019.#180;	//  scala/collection/generic/SequenceTemplate.toString:()Ljava/lang/String;
const #1021 = Asciz	info_ver;
const #1022 = Asciz	info_enc;
const #1023 = Asciz	temp19;
const #1024 = Asciz	temp24;
const #1025 = Asciz	temp26;
const #1026 = Asciz	Lscala/xml/Text;;
const #1027 = Asciz	temp27;
const #1028 = Asciz	enc;
const #1029 = Asciz	(Lscala/xml/parsing/MarkupParser;)Lscala/Tuple3;;
const #1030 = Asciz	standalone;
const #1031 = String	#1030;	//  standalone
const #1032 = Asciz	yes;
const #1033 = String	#1032;	//  yes
const #1034 = Asciz	boxToBoolean;
const #1035 = Asciz	(Z)Ljava/lang/Boolean;;
const #1036 = NameAndType	#1034:#1035;//  boxToBoolean:(Z)Ljava/lang/Boolean;
const #1037 = Method	#130.#1036;	//  scala/runtime/BoxesRunTime.boxToBoolean:(Z)Ljava/lang/Boolean;
const #1038 = Asciz	no;
const #1039 = String	#1038;	//  no
const #1040 = Asciz	either 'yes' or 'no' expected;
const #1041 = String	#1040;	//  either 'yes' or 'no' expected
const #1042 = Asciz	VersionInfo EncodingDecl? SDDecl? or '?>' expected!;
const #1043 = String	#1042;	//  VersionInfo EncodingDecl? SDDecl? or '?>' expected!
const #1044 = Asciz	info_stdl;
const #1045 = Asciz	temp4;
const #1046 = Asciz	temp9;
const #1047 = Asciz	temp11;
const #1048 = Asciz	temp12;
const #1049 = Asciz	temp13;
const #1050 = Asciz	temp15;
const #1051 = Asciz	temp16;
const #1052 = Asciz	(Lscala/xml/parsing/MarkupParser;)Lscala/xml/MetaData;;
const #1053 = Asciz	xml;
const #1054 = String	#1053;	//  xml
const #1055 = Asciz	no xmlns definitions here, please.;
const #1056 = String	#1055;	//  no xmlns definitions here, please.
const #1057 = Asciz	temp1;
const #1058 = Asciz	temp2;
const #1059 = Asciz	temp3;
const #1060 = Asciz	scp;
const #1061 = Asciz	md;
const #1062 = Asciz	Scala;
const #1063 = Asciz	InnerClasses;
const #1064 = Asciz	$anon$1;
const #1065 = Asciz	$anon$2;
const #1066 = Asciz	$anonfun$4;
const #1067 = Asciz	$anonfun$2;
const #1068 = Asciz	$anonfun$1;
const #1069 = Asciz	$anonfun$3;
const #1070 = Asciz	$anonfun$xCharRef$1;
const #1071 = Asciz	$anonfun$document$1;
const #1072 = Asciz	$anonfun$appendText$1;

{
public static void $init$(scala.xml.parsing.MarkupParser);
  Code:
   Stack=3, Locals=1, Args_size=1
   0:	aload_0
   1:	aload_0
   2:	invokeinterface	#12,  1; //InterfaceMethod scala/xml/parsing/MarkupParser.input:()Lscala/io/Source;
   7:	invokeinterface	#16,  2; //InterfaceMethod scala/xml/parsing/MarkupParser.curInput_$eq:(Lscala/io/Source;)V
   12:	aload_0
   13:	aload_0
   14:	checkcast	#18; //class scala/xml/parsing/MarkupHandler
   17:	invokeinterface	#22,  2; //InterfaceMethod scala/xml/parsing/MarkupParser.scala$xml$parsing$MarkupParser$_setter_$scala$xml$parsing$MarkupParser$$handle_$eq:(Lscala/xml/parsing/MarkupHandler;)V
   22:	aload_0
   23:	getstatic	#28; //Field scala/collection/immutable/Nil$.MODULE$:Lscala/collection/immutable/Nil$;
   26:	invokeinterface	#32,  2; //InterfaceMethod scala/xml/parsing/MarkupParser.inpStack_$eq:(Lscala/collection/immutable/List;)V
   31:	aload_0
   32:	iconst_m1
   33:	invokeinterface	#36,  2; //InterfaceMethod scala/xml/parsing/MarkupParser.extIndex_$eq:(I)V
   38:	aload_0
   39:	new	#38; //class scala/collection/mutable/StringBuilder
   42:	dup
   43:	invokespecial	#42; //Method scala/collection/mutable/StringBuilder."<init>":()V
   46:	invokeinterface	#46,  2; //InterfaceMethod scala/xml/parsing/MarkupParser.scala$xml$parsing$MarkupParser$_setter_$cbuf_$eq:(Lscala/collection/mutable/StringBuilder;)V
   51:	aload_0
   52:	aconst_null
   53:	pop
   54:	aconst_null
   55:	invokeinterface	#50,  2; //InterfaceMethod scala/xml/parsing/MarkupParser.dtd_$eq:(Lscala/xml/dtd/DTD;)V
   60:	aload_0
   61:	aconst_null
   62:	pop
   63:	aconst_null
   64:	invokeinterface	#54,  2; //InterfaceMethod scala/xml/parsing/MarkupParser.doc_$eq:(Lscala/xml/Document;)V
   69:	aload_0
   70:	iconst_0
   71:	invokeinterface	#58,  2; //InterfaceMethod scala/xml/parsing/MarkupParser.eof_$eq:(Z)V
   76:	return
  LineNumberTable: 
   line 45: 0
   line 48: 12
   line 51: 22
   line 58: 31
   line 67: 38
   line 69: 51
   line 71: 60
   line 73: 69

  LocalVariableTable: 
   Start  Length  Slot  Name   Signature
   0      77      0    $this       Lscala/xml/parsing/MarkupParser;


public static java.lang.String normalizeAttributeValue(scala.xml.parsing.MarkupParser, java.lang.String);
  Code:
   Stack=7, Locals=19, Args_size=2
   0:	getstatic	#108; //Field scala/Predef$.MODULE$:Lscala/Predef$;
   3:	aload_1
   4:	invokevirtual	#112; //Method scala/Predef$.stringWrapper:(Ljava/lang/String;)Lscala/runtime/RichString;
   7:	astore_2
   8:	aload_2
   9:	invokeinterface	#118,  1; //InterfaceMethod scala/collection/generic/IterableTemplate.iterator:()Lscala/collection/Iterator;
   14:	astore_3
   15:	aload_3
   16:	invokeinterface	#124,  1; //InterfaceMethod scala/collection/Iterator.hasNext:()Z
   21:	ifeq	539
   24:	aload_3
   25:	invokeinterface	#128,  1; //InterfaceMethod scala/collection/Iterator.next:()Ljava/lang/Object;
   30:	invokestatic	#134; //Method scala/runtime/BoxesRunTime.unboxToChar:(Ljava/lang/Object;)C
   33:	istore	4
   35:	iload	4
   37:	lookupswitch{ //5
		9: 524;
		10: 524;
		13: 524;
		32: 524;
		38: 102;
		default: 88 }
   88:	aload_0
   89:	invokeinterface	#138,  1; //InterfaceMethod scala/xml/parsing/MarkupParser.cbuf:()Lscala/collection/mutable/StringBuilder;
   94:	iload	4
   96:	invokevirtual	#142; //Method scala/collection/mutable/StringBuilder.append:(C)Lscala/collection/mutable/StringBuilder;
   99:	goto	535
   102:	aload_3
   103:	invokeinterface	#128,  1; //InterfaceMethod scala/collection/Iterator.next:()Ljava/lang/Object;
   108:	invokestatic	#134; //Method scala/runtime/BoxesRunTime.unboxToChar:(Ljava/lang/Object;)C
   111:	istore	5
   113:	iload	5
   115:	invokestatic	#146; //Method scala/runtime/BoxesRunTime.boxToCharacter:(C)Ljava/lang/Character;
   118:	ldc	#147; //int 35
   120:	invokestatic	#151; //Method scala/runtime/BoxesRunTime.boxToInteger:(I)Ljava/lang/Integer;
   123:	invokestatic	#155; //Method scala/runtime/BoxesRunTime.equals:(Ljava/lang/Object;Ljava/lang/Object;)Z
   126:	ifeq	190
   129:	new	#157; //class scala/runtime/CharRef
   132:	dup
   133:	aload_3
   134:	invokeinterface	#128,  1; //InterfaceMethod scala/collection/Iterator.next:()Ljava/lang/Object;
   139:	invokestatic	#134; //Method scala/runtime/BoxesRunTime.unboxToChar:(Ljava/lang/Object;)C
   142:	invokespecial	#159; //Method scala/runtime/CharRef."<init>":(C)V
   145:	astore	6
   147:	aload_0
   148:	new	#161; //class scala/xml/parsing/MarkupParser$$anonfun$3
   151:	dup
   152:	aload_0
   153:	aload	6
   155:	invokespecial	#164; //Method scala/xml/parsing/MarkupParser$$anonfun$3."<init>":(Lscala/xml/parsing/MarkupParser;Lscala/runtime/CharRef;)V
   158:	new	#166; //class scala/xml/parsing/MarkupParser$$anonfun$4
   161:	dup
   162:	aload_0
   163:	aload_3
   164:	aload	6
   166:	invokespecial	#169; //Method scala/xml/parsing/MarkupParser$$anonfun$4."<init>":(Lscala/xml/parsing/MarkupParser;Lscala/collection/Iterator;Lscala/runtime/CharRef;)V
   169:	invokeinterface	#173,  3; //InterfaceMethod scala/xml/parsing/MarkupParser.xCharRef:(Lscala/Function0;Lscala/Function0;)Ljava/lang/String;
   174:	astore	7
   176:	aload_0
   177:	invokeinterface	#138,  1; //InterfaceMethod scala/xml/parsing/MarkupParser.cbuf:()Lscala/collection/mutable/StringBuilder;
   182:	aload	7
   184:	invokevirtual	#176; //Method scala/collection/mutable/StringBuilder.append:(Ljava/lang/String;)Lscala/collection/mutable/StringBuilder;
   187:	goto	535
   190:	iload	5
   192:	istore	8
   194:	new	#38; //class scala/collection/mutable/StringBuilder
   197:	dup
   198:	invokespecial	#42; //Method scala/collection/mutable/StringBuilder."<init>":()V
   201:	astore	9
   203:	iload	8
   205:	istore	10
   207:	aload	9
   209:	iload	10
   211:	invokevirtual	#142; //Method scala/collection/mutable/StringBuilder.append:(C)Lscala/collection/mutable/StringBuilder;
   214:	pop
   215:	aload_3
   216:	invokeinterface	#128,  1; //InterfaceMethod scala/collection/Iterator.next:()Ljava/lang/Object;
   221:	invokestatic	#134; //Method scala/runtime/BoxesRunTime.unboxToChar:(Ljava/lang/Object;)C
   224:	istore	10
   226:	iload	10
   228:	ldc	#177; //int 59
   230:	if_icmpne	207
   233:	aload	9
   235:	invokevirtual	#181; //Method scala/collection/mutable/StringBuilder.toString:()Ljava/lang/String;
   238:	astore	11
   240:	aload	11
   242:	ldc	#183; //String lt
   244:	astore	12
   246:	dup
   247:	ifnonnull	259
   250:	pop
   251:	aload	12
   253:	ifnull	267
   256:	goto	281
   259:	aload	12
   261:	invokevirtual	#188; //Method java/lang/Object.equals:(Ljava/lang/Object;)Z
   264:	ifeq	281
   267:	aload_0
   268:	invokeinterface	#138,  1; //InterfaceMethod scala/xml/parsing/MarkupParser.cbuf:()Lscala/collection/mutable/StringBuilder;
   273:	ldc	#189; //int 60
   275:	invokevirtual	#142; //Method scala/collection/mutable/StringBuilder.append:(C)Lscala/collection/mutable/StringBuilder;
   278:	goto	535
   281:	aload	11
   283:	ldc	#191; //String gt
   285:	astore	13
   287:	dup
   288:	ifnonnull	300
   291:	pop
   292:	aload	13
   294:	ifnull	308
   297:	goto	322
   300:	aload	13
   302:	invokevirtual	#188; //Method java/lang/Object.equals:(Ljava/lang/Object;)Z
   305:	ifeq	322
   308:	aload_0
   309:	invokeinterface	#138,  1; //InterfaceMethod scala/xml/parsing/MarkupParser.cbuf:()Lscala/collection/mutable/StringBuilder;
   314:	ldc	#192; //int 62
   316:	invokevirtual	#142; //Method scala/collection/mutable/StringBuilder.append:(C)Lscala/collection/mutable/StringBuilder;
   319:	goto	535
   322:	aload	11
   324:	ldc	#194; //String amp
   326:	astore	14
   328:	dup
   329:	ifnonnull	341
   332:	pop
   333:	aload	14
   335:	ifnull	349
   338:	goto	363
   341:	aload	14
   343:	invokevirtual	#188; //Method java/lang/Object.equals:(Ljava/lang/Object;)Z
   346:	ifeq	363
   349:	aload_0
   350:	invokeinterface	#138,  1; //InterfaceMethod scala/xml/parsing/MarkupParser.cbuf:()Lscala/collection/mutable/StringBuilder;
   355:	ldc	#195; //int 38
   357:	invokevirtual	#142; //Method scala/collection/mutable/StringBuilder.append:(C)Lscala/collection/mutable/StringBuilder;
   360:	goto	535
   363:	aload	11
   365:	ldc	#197; //String apos
   367:	astore	15
   369:	dup
   370:	ifnonnull	382
   373:	pop
   374:	aload	15
   376:	ifnull	390
   379:	goto	404
   382:	aload	15
   384:	invokevirtual	#188; //Method java/lang/Object.equals:(Ljava/lang/Object;)Z
   387:	ifeq	404
   390:	aload_0
   391:	invokeinterface	#138,  1; //InterfaceMethod scala/xml/parsing/MarkupParser.cbuf:()Lscala/collection/mutable/StringBuilder;
   396:	ldc	#198; //int 39
   398:	invokevirtual	#142; //Method scala/collection/mutable/StringBuilder.append:(C)Lscala/collection/mutable/StringBuilder;
   401:	goto	535
   404:	aload	11
   406:	ldc	#200; //String quot
   408:	astore	16
   410:	dup
   411:	ifnonnull	423
   414:	pop
   415:	aload	16
   417:	ifnull	431
   420:	goto	445
   423:	aload	16
   425:	invokevirtual	#188; //Method java/lang/Object.equals:(Ljava/lang/Object;)Z
   428:	ifeq	445
   431:	aload_0
   432:	invokeinterface	#138,  1; //InterfaceMethod scala/xml/parsing/MarkupParser.cbuf:()Lscala/collection/mutable/StringBuilder;
   437:	ldc	#201; //int 34
   439:	invokevirtual	#142; //Method scala/collection/mutable/StringBuilder.append:(C)Lscala/collection/mutable/StringBuilder;
   442:	goto	535
   445:	aload	11
   447:	ldc	#203; //String quote
   449:	astore	17
   451:	dup
   452:	ifnonnull	464
   455:	pop
   456:	aload	17
   458:	ifnull	472
   461:	goto	486
   464:	aload	17
   466:	invokevirtual	#188; //Method java/lang/Object.equals:(Ljava/lang/Object;)Z
   469:	ifeq	486
   472:	aload_0
   473:	invokeinterface	#138,  1; //InterfaceMethod scala/xml/parsing/MarkupParser.cbuf:()Lscala/collection/mutable/StringBuilder;
   478:	ldc	#201; //int 34
   480:	invokevirtual	#142; //Method scala/collection/mutable/StringBuilder.append:(C)Lscala/collection/mutable/StringBuilder;
   483:	goto	535
   486:	aload_0
   487:	invokeinterface	#138,  1; //InterfaceMethod scala/xml/parsing/MarkupParser.cbuf:()Lscala/collection/mutable/StringBuilder;
   492:	ldc	#195; //int 38
   494:	invokevirtual	#142; //Method scala/collection/mutable/StringBuilder.append:(C)Lscala/collection/mutable/StringBuilder;
   497:	pop
   498:	aload_0
   499:	invokeinterface	#138,  1; //InterfaceMethod scala/xml/parsing/MarkupParser.cbuf:()Lscala/collection/mutable/StringBuilder;
   504:	aload	11
   506:	invokevirtual	#176; //Method scala/collection/mutable/StringBuilder.append:(Ljava/lang/String;)Lscala/collection/mutable/StringBuilder;
   509:	pop
   510:	aload_0
   511:	invokeinterface	#138,  1; //InterfaceMethod scala/xml/parsing/MarkupParser.cbuf:()Lscala/collection/mutable/StringBuilder;
   516:	ldc	#177; //int 59
   518:	invokevirtual	#142; //Method scala/collection/mutable/StringBuilder.append:(C)Lscala/collection/mutable/StringBuilder;
   521:	goto	535
   524:	aload_0
   525:	invokeinterface	#138,  1; //InterfaceMethod scala/xml/parsing/MarkupParser.cbuf:()Lscala/collection/mutable/StringBuilder;
   530:	ldc	#204; //int 32
   532:	invokevirtual	#142; //Method scala/collection/mutable/StringBuilder.append:(C)Lscala/collection/mutable/StringBuilder;
   535:	pop
   536:	goto	15
   539:	aload_0
   540:	invokeinterface	#138,  1; //InterfaceMethod scala/xml/parsing/MarkupParser.cbuf:()Lscala/collection/mutable/StringBuilder;
   545:	invokevirtual	#181; //Method scala/collection/mutable/StringBuilder.toString:()Ljava/lang/String;
   548:	astore	18
   550:	aload_0
   551:	invokeinterface	#138,  1; //InterfaceMethod scala/xml/parsing/MarkupParser.cbuf:()Lscala/collection/mutable/StringBuilder;
   556:	iconst_0
   557:	invokevirtual	#207; //Method scala/collection/mutable/StringBuilder.length_$eq:(I)V
   560:	aload	18
   562:	areturn
  LineNumberTable: 
   line 1176: 0
   line 1177: 8
   line 1178: 15
   line 1179: 24
   line 1208: 88
   line 1207: 94
   line 1208: 96
   line 1179: 99
   line 1182: 102
   line 1184: 129
   line 1185: 147
   line 1186: 176
   line 1187: 190
   line 1188: 194
   line 1189: 203
   line 1191: 207
   line 1192: 215
   line 1193: 226
   line 1194: 233
   line 1195: 267
   line 1194: 281
   line 1196: 308
   line 1194: 322
   line 1197: 349
   line 1194: 363
   line 1198: 390
   line 1194: 404
   line 1199: 431
   line 1194: 445
   line 1200: 472
   line 1202: 486
   line 1203: 498
   line 1201: 504
   line 1203: 506
   line 1204: 510
   line 1181: 524
   line 1211: 535
   line 1179: 536
   line 1211: 539
   line 1212: 550
   line 1213: 560

  LocalVariableTable: 
   Start  Length  Slot  Name   Signature
   0      563      0    $this       Lscala/xml/parsing/MarkupParser;
   0      563      1    attval       Ljava/lang/String;
   8      554      2    s       Lscala/collection/Sequence;
   15      547      3    it$1       Lscala/collection/Iterator;
   35      501      4    temp89       C
   113      411      5    temp88       C
   147      40      6    c$1       Lscala/runtime/CharRef;
   176      11      7    s       Ljava/lang/String;
   194      330      8    nchar       C
   203      321      9    nbuf       Lscala/collection/mutable/StringBuilder;
   207      317      10    d       C
   240      284      11    temp81       Ljava/lang/String;
   550      12      18    name       Ljava/lang/String;


public static void pop(scala.xml.parsing.MarkupParser);
  Code:
   Stack=2, Locals=1, Args_size=1
   0:	aload_0
   1:	aload_0
   2:	invokeinterface	#78,  1; //InterfaceMethod scala/xml/parsing/MarkupParser.inpStack:()Lscala/collection/immutable/List;
   7:	invokeinterface	#228,  1; //InterfaceMethod scala/collection/generic/IterableTemplate.head:()Ljava/lang/Object;
   12:	checkcast	#230; //class scala/io/Source
   15:	invokeinterface	#16,  2; //InterfaceMethod scala/xml/parsing/MarkupParser.curInput_$eq:(Lscala/io/Source;)V
   20:	aload_0
   21:	aload_0
   22:	invokeinterface	#78,  1; //InterfaceMethod scala/xml/parsing/MarkupParser.inpStack:()Lscala/collection/immutable/List;
   27:	invokeinterface	#236,  1; //InterfaceMethod scala/collection/generic/TraversableTemplate.tail:()Lscala/collection/generic/TraversableTemplate;
   32:	checkcast	#238; //class scala/collection/immutable/List
   35:	invokeinterface	#32,  2; //InterfaceMethod scala/xml/parsing/MarkupParser.inpStack_$eq:(Lscala/collection/immutable/List;)V
   40:	aload_0
   41:	aload_0
   42:	invokeinterface	#241,  1; //InterfaceMethod scala/xml/parsing/MarkupParser.curInput:()Lscala/io/Source;
   47:	invokevirtual	#242; //Method scala/io/Source.ch:()C
   50:	invokeinterface	#245,  2; //InterfaceMethod scala/xml/parsing/MarkupParser.ch_$eq:(C)V
   55:	aload_0
   56:	aload_0
   57:	invokeinterface	#241,  1; //InterfaceMethod scala/xml/parsing/MarkupParser.curInput:()Lscala/io/Source;
   62:	invokevirtual	#248; //Method scala/io/Source.pos:()I
   65:	invokeinterface	#251,  2; //InterfaceMethod scala/xml/parsing/MarkupParser.pos_$eq:(I)V
   70:	aload_0
   71:	iconst_0
   72:	invokeinterface	#58,  2; //InterfaceMethod scala/xml/parsing/MarkupParser.eof_$eq:(Z)V
   77:	return
  LineNumberTable: 
   line 1162: 0
   line 1163: 20
   line 1164: 40
   line 1165: 55
   line 1166: 70

  LocalVariableTable: 
   Start  Length  Slot  Name   Signature
   0      78      0    $this       Lscala/xml/parsing/MarkupParser;


public static void pushExternal(scala.xml.parsing.MarkupParser, java.lang.String);
  Code:
   Stack=3, Locals=3, Args_size=2
   0:	aload_0
   1:	invokeinterface	#256,  1; //InterfaceMethod scala/xml/parsing/MarkupParser.eof:()Z
   6:	ifne	32
   9:	aload_0
   10:	aload_0
   11:	invokeinterface	#241,  1; //InterfaceMethod scala/xml/parsing/MarkupParser.curInput:()Lscala/io/Source;
   16:	astore_2
   17:	aload_0
   18:	invokeinterface	#78,  1; //InterfaceMethod scala/xml/parsing/MarkupParser.inpStack:()Lscala/collection/immutable/List;
   23:	aload_2
   24:	invokevirtual	#260; //Method scala/collection/immutable/List.$colon$colon:(Ljava/lang/Object;)Lscala/collection/immutable/List;
   27:	invokeinterface	#32,  2; //InterfaceMethod scala/xml/parsing/MarkupParser.inpStack_$eq:(Lscala/collection/immutable/List;)V
   32:	aload_0
   33:	aload_0
   34:	aload_1
   35:	invokeinterface	#264,  2; //InterfaceMethod scala/xml/parsing/MarkupParser.externalSource:(Ljava/lang/String;)Lscala/io/Source;
   40:	invokeinterface	#16,  2; //InterfaceMethod scala/xml/parsing/MarkupParser.curInput_$eq:(Lscala/io/Source;)V
   45:	aload_0
   46:	invokeinterface	#97,  1; //InterfaceMethod scala/xml/parsing/MarkupParser.nextch:()V
   51:	return
  LineNumberTable: 
   line 1150: 0
   line 1151: 9
   line 1153: 32
   line 1158: 45

  LocalVariableTable: 
   Start  Length  Slot  Name   Signature
   0      52      0    $this       Lscala/xml/parsing/MarkupParser;
   0      52      1    systemId       Ljava/lang/String;


public static void push(scala.xml.parsing.MarkupParser, java.lang.String);
  Code:
   Stack=3, Locals=3, Args_size=2
   0:	aload_0
   1:	invokeinterface	#256,  1; //InterfaceMethod scala/xml/parsing/MarkupParser.eof:()Z
   6:	ifne	32
   9:	aload_0
   10:	aload_0
   11:	invokeinterface	#241,  1; //InterfaceMethod scala/xml/parsing/MarkupParser.curInput:()Lscala/io/Source;
   16:	astore_2
   17:	aload_0
   18:	invokeinterface	#78,  1; //InterfaceMethod scala/xml/parsing/MarkupParser.inpStack:()Lscala/collection/immutable/List;
   23:	aload_2
   24:	invokevirtual	#260; //Method scala/collection/immutable/List.$colon$colon:(Ljava/lang/Object;)Lscala/collection/immutable/List;
   27:	invokeinterface	#32,  2; //InterfaceMethod scala/xml/parsing/MarkupParser.inpStack_$eq:(Lscala/collection/immutable/List;)V
   32:	aload_0
   33:	aload_0
   34:	checkcast	#18; //class scala/xml/parsing/MarkupHandler
   37:	aload_1
   38:	invokevirtual	#269; //Method scala/xml/parsing/MarkupHandler.replacementText:(Ljava/lang/String;)Lscala/io/Source;
   41:	invokeinterface	#16,  2; //InterfaceMethod scala/xml/parsing/MarkupParser.curInput_$eq:(Lscala/io/Source;)V
   46:	aload_0
   47:	invokeinterface	#97,  1; //InterfaceMethod scala/xml/parsing/MarkupParser.nextch:()V
   52:	return
  LineNumberTable: 
   line 1131: 0
   line 1132: 9
   line 1134: 32
   line 1135: 46

  LocalVariableTable: 
   Start  Length  Slot  Name   Signature
   0      53      0    $this       Lscala/xml/parsing/MarkupParser;
   0      53      1    entityName       Ljava/lang/String;


public static void reportValidationError(scala.xml.parsing.MarkupParser, int, java.lang.String);
  Code:
   Stack=4, Locals=7, Args_size=3
   0:	aload_0
   1:	invokeinterface	#241,  1; //InterfaceMethod scala/xml/parsing/MarkupParser.curInput:()Lscala/io/Source;
   6:	astore_3
   7:	iload_1
   8:	istore	4
   10:	aload_2
   11:	astore	5
   13:	aload_3
   14:	invokevirtual	#276; //Method scala/io/Source.reportError$default$3:()Ljava/io/PrintStream;
   17:	astore	6
   19:	aload_3
   20:	iload	4
   22:	aload	5
   24:	aload	6
   26:	invokevirtual	#280; //Method scala/io/Source.reportError:(ILjava/lang/String;Ljava/io/PrintStream;)V
   29:	return
  LineNumberTable: 
   line 1124: 0

  LocalVariableTable: 
   Start  Length  Slot  Name   Signature
   0      30      0    $this       Lscala/xml/parsing/MarkupParser;
   0      30      1    pos       I
   0      30      2    str       Ljava/lang/String;
   7      22      3    qual$3       Lscala/io/Source;
   10      19      4    x$14       I
   13      16      5    x$15       Ljava/lang/String;
   19      10      6    x$16       Ljava/io/PrintStream;


public static void reportSyntaxError(scala.xml.parsing.MarkupParser, java.lang.String);
  Code:
   Stack=3, Locals=2, Args_size=2
   0:	aload_0
   1:	aload_0
   2:	invokeinterface	#290,  1; //InterfaceMethod scala/xml/parsing/MarkupParser.pos:()I
   7:	aload_1
   8:	invokeinterface	#293,  3; //InterfaceMethod scala/xml/parsing/MarkupParser.reportSyntaxError:(ILjava/lang/String;)V
   13:	return
  LineNumberTable: 
   line 1118: 0

  LocalVariableTable: 
   Start  Length  Slot  Name   Signature
   0      14      0    $this       Lscala/xml/parsing/MarkupParser;
   0      14      1    str       Ljava/lang/String;


public static void reportSyntaxError(scala.xml.parsing.MarkupParser, int, java.lang.String);
  Code:
   Stack=4, Locals=7, Args_size=3
   0:	aload_0
   1:	invokeinterface	#241,  1; //InterfaceMethod scala/xml/parsing/MarkupParser.curInput:()Lscala/io/Source;
   6:	astore_3
   7:	iload_1
   8:	istore	4
   10:	aload_2
   11:	astore	5
   13:	aload_3
   14:	invokevirtual	#276; //Method scala/io/Source.reportError$default$3:()Ljava/io/PrintStream;
   17:	astore	6
   19:	aload_3
   20:	iload	4
   22:	aload	5
   24:	aload	6
   26:	invokevirtual	#280; //Method scala/io/Source.reportError:(ILjava/lang/String;Ljava/io/PrintStream;)V
   29:	return
  LineNumberTable: 
   line 1114: 0

  LocalVariableTable: 
   Start  Length  Slot  Name   Signature
   0      30      0    $this       Lscala/xml/parsing/MarkupParser;
   0      30      1    pos       I
   0      30      2    str       Ljava/lang/String;
   7      22      3    qual$2       Lscala/io/Source;
   10      19      4    x$11       I
   13      16      5    x$12       Ljava/lang/String;
   19      10      6    x$13       Ljava/io/PrintStream;


public static void notationDecl(scala.xml.parsing.MarkupParser);
  Code:
   Stack=4, Locals=5, Args_size=1
   0:	aload_0
   1:	getstatic	#108; //Field scala/Predef$.MODULE$:Lscala/Predef$;
   4:	ldc_w	#300; //String OTATION
   7:	invokevirtual	#112; //Method scala/Predef$.stringWrapper:(Ljava/lang/String;)Lscala/runtime/RichString;
   10:	invokeinterface	#303,  2; //InterfaceMethod scala/xml/parsing/MarkupParser.xToken:(Lscala/collection/Sequence;)V
   15:	aload_0
   16:	invokeinterface	#306,  1; //InterfaceMethod scala/xml/parsing/MarkupParser.xSpace:()V
   21:	aload_0
   22:	invokeinterface	#309,  1; //InterfaceMethod scala/xml/parsing/MarkupParser.xName:()Ljava/lang/String;
   27:	astore_1
   28:	aload_0
   29:	invokeinterface	#306,  1; //InterfaceMethod scala/xml/parsing/MarkupParser.xSpace:()V
   34:	aload_0
   35:	invokeinterface	#67,  1; //InterfaceMethod scala/xml/parsing/MarkupParser.ch:()C
   40:	ldc_w	#310; //int 83
   43:	if_icmpne	55
   46:	aload_0
   47:	invokeinterface	#314,  1; //InterfaceMethod scala/xml/parsing/MarkupParser.externalID:()Lscala/xml/dtd/ExternalID;
   52:	goto	142
   55:	aload_0
   56:	invokeinterface	#67,  1; //InterfaceMethod scala/xml/parsing/MarkupParser.ch:()C
   61:	ldc_w	#315; //int 80
   64:	if_icmpne	169
   67:	aload_0
   68:	invokeinterface	#97,  1; //InterfaceMethod scala/xml/parsing/MarkupParser.nextch:()V
   73:	aload_0
   74:	getstatic	#108; //Field scala/Predef$.MODULE$:Lscala/Predef$;
   77:	ldc_w	#317; //String UBLIC
   80:	invokevirtual	#112; //Method scala/Predef$.stringWrapper:(Ljava/lang/String;)Lscala/runtime/RichString;
   83:	invokeinterface	#303,  2; //InterfaceMethod scala/xml/parsing/MarkupParser.xToken:(Lscala/collection/Sequence;)V
   88:	aload_0
   89:	invokeinterface	#306,  1; //InterfaceMethod scala/xml/parsing/MarkupParser.xSpace:()V
   94:	aload_0
   95:	invokeinterface	#320,  1; //InterfaceMethod scala/xml/parsing/MarkupParser.pubidLiteral:()Ljava/lang/String;
   100:	astore_3
   101:	aload_0
   102:	invokeinterface	#323,  1; //InterfaceMethod scala/xml/parsing/MarkupParser.xSpaceOpt:()V
   107:	aload_0
   108:	invokeinterface	#67,  1; //InterfaceMethod scala/xml/parsing/MarkupParser.ch:()C
   113:	ldc	#192; //int 62
   115:	if_icmpeq	127
   118:	aload_0
   119:	invokeinterface	#326,  1; //InterfaceMethod scala/xml/parsing/MarkupParser.systemLiteral:()Ljava/lang/String;
   124:	goto	130
   127:	aconst_null
   128:	pop
   129:	aconst_null
   130:	astore	4
   132:	new	#328; //class scala/xml/dtd/PublicID
   135:	dup
   136:	aload_3
   137:	aload	4
   139:	invokespecial	#331; //Method scala/xml/dtd/PublicID."<init>":(Ljava/lang/String;Ljava/lang/String;)V
   142:	astore_2
   143:	aload_0
   144:	invokeinterface	#323,  1; //InterfaceMethod scala/xml/parsing/MarkupParser.xSpaceOpt:()V
   149:	aload_0
   150:	ldc	#192; //int 62
   152:	invokeinterface	#93,  2; //InterfaceMethod scala/xml/parsing/MarkupParser.xToken:(C)V
   157:	aload_0
   158:	invokeinterface	#335,  1; //InterfaceMethod scala/xml/parsing/MarkupParser.scala$xml$parsing$MarkupParser$$handle:()Lscala/xml/parsing/MarkupHandler;
   163:	aload_1
   164:	aload_2
   165:	invokevirtual	#338; //Method scala/xml/parsing/MarkupHandler.notationDecl:(Ljava/lang/String;Lscala/xml/dtd/ExternalID;)V
   168:	return
   169:	aload_0
   170:	ldc_w	#340; //String PUBLIC or SYSTEM expected
   173:	invokeinterface	#343,  2; //InterfaceMethod scala/xml/parsing/MarkupParser.reportSyntaxError:(Ljava/lang/String;)V
   178:	getstatic	#108; //Field scala/Predef$.MODULE$:Lscala/Predef$;
   181:	ldc_w	#345; //String died parsing notationdecl
   184:	invokevirtual	#349; //Method scala/Predef$.error:(Ljava/lang/String;)Lscala/runtime/Nothing$;
   187:	athrow
  LineNumberTable: 
   line 1082: 0
   line 1083: 15
   line 1084: 21
   line 1085: 28
   line 1086: 34
   line 1087: 46
   line 1089: 55
   line 1091: 67
   line 1092: 73
   line 1093: 88
   line 1094: 94
   line 1095: 101
   line 1096: 107
   line 1097: 118
   line 1099: 127
   line 1096: 130
   line 1100: 132
   line 1086: 142
   line 1105: 143
   line 1106: 149
   line 1107: 157
   line 1102: 169
   line 1103: 178

  LocalVariableTable: 
   Start  Length  Slot  Name   Signature
   0      188      0    $this       Lscala/xml/parsing/MarkupParser;
   28      140      1    notat       Ljava/lang/String;
   169      19      1    notat       Ljava/lang/String;
   143      25      2    extID       Lscala/xml/dtd/ExternalID;
   101      41      3    pubID       Ljava/lang/String;
   132      10      4    sysID       Ljava/lang/String;


public static void entityDecl(scala.xml.parsing.MarkupParser);
  Code:
   Stack=5, Locals=8, Args_size=1
   0:	iconst_0
   1:	istore_1
   2:	aconst_null
   3:	pop
   4:	aconst_null
   5:	astore_2
   6:	aload_0
   7:	getstatic	#108; //Field scala/Predef$.MODULE$:Lscala/Predef$;
   10:	ldc_w	#357; //String NTITY
   13:	invokevirtual	#112; //Method scala/Predef$.stringWrapper:(Ljava/lang/String;)Lscala/runtime/RichString;
   16:	invokeinterface	#303,  2; //InterfaceMethod scala/xml/parsing/MarkupParser.xToken:(Lscala/collection/Sequence;)V
   21:	aload_0
   22:	invokeinterface	#306,  1; //InterfaceMethod scala/xml/parsing/MarkupParser.xSpace:()V
   27:	ldc_w	#358; //int 37
   30:	aload_0
   31:	invokeinterface	#67,  1; //InterfaceMethod scala/xml/parsing/MarkupParser.ch:()C
   36:	if_icmpne	53
   39:	aload_0
   40:	invokeinterface	#97,  1; //InterfaceMethod scala/xml/parsing/MarkupParser.nextch:()V
   45:	iconst_1
   46:	istore_1
   47:	aload_0
   48:	invokeinterface	#306,  1; //InterfaceMethod scala/xml/parsing/MarkupParser.xSpace:()V
   53:	aload_0
   54:	invokeinterface	#309,  1; //InterfaceMethod scala/xml/parsing/MarkupParser.xName:()Ljava/lang/String;
   59:	astore_3
   60:	aload_0
   61:	invokeinterface	#306,  1; //InterfaceMethod scala/xml/parsing/MarkupParser.xSpace:()V
   66:	aload_0
   67:	invokeinterface	#67,  1; //InterfaceMethod scala/xml/parsing/MarkupParser.ch:()C
   72:	istore	4
   74:	iload	4
   76:	lookupswitch{ //4
		34: 289;
		39: 289;
		80: 136;
		83: 136;
		default: 120 }
   120:	new	#360; //class scala/MatchError
   123:	dup
   124:	iload	4
   126:	invokestatic	#146; //Method scala/runtime/BoxesRunTime.boxToCharacter:(C)Ljava/lang/Character;
   129:	invokevirtual	#361; //Method java/lang/Object.toString:()Ljava/lang/String;
   132:	invokespecial	#363; //Method scala/MatchError."<init>":(Ljava/lang/String;)V
   135:	athrow
   136:	aload_0
   137:	invokeinterface	#314,  1; //InterfaceMethod scala/xml/parsing/MarkupParser.externalID:()Lscala/xml/dtd/ExternalID;
   142:	astore	6
   144:	iload_1
   145:	ifeq	184
   148:	aload_0
   149:	invokeinterface	#323,  1; //InterfaceMethod scala/xml/parsing/MarkupParser.xSpaceOpt:()V
   154:	aload_0
   155:	ldc	#192; //int 62
   157:	invokeinterface	#93,  2; //InterfaceMethod scala/xml/parsing/MarkupParser.xToken:(C)V
   162:	aload_0
   163:	invokeinterface	#335,  1; //InterfaceMethod scala/xml/parsing/MarkupParser.scala$xml$parsing$MarkupParser$$handle:()Lscala/xml/parsing/MarkupHandler;
   168:	aload_3
   169:	new	#365; //class scala/xml/dtd/ExtDef
   172:	dup
   173:	aload	6
   175:	invokespecial	#368; //Method scala/xml/dtd/ExtDef."<init>":(Lscala/xml/dtd/ExternalID;)V
   178:	invokevirtual	#372; //Method scala/xml/parsing/MarkupHandler.parameterEntityDecl:(Ljava/lang/String;Lscala/xml/dtd/EntityDef;)V
   181:	goto	356
   184:	aload_0
   185:	invokeinterface	#306,  1; //InterfaceMethod scala/xml/parsing/MarkupParser.xSpace:()V
   190:	ldc	#192; //int 62
   192:	aload_0
   193:	invokeinterface	#67,  1; //InterfaceMethod scala/xml/parsing/MarkupParser.ch:()C
   198:	if_icmpeq	261
   201:	aload_0
   202:	getstatic	#108; //Field scala/Predef$.MODULE$:Lscala/Predef$;
   205:	ldc_w	#374; //String NDATA
   208:	invokevirtual	#112; //Method scala/Predef$.stringWrapper:(Ljava/lang/String;)Lscala/runtime/RichString;
   211:	invokeinterface	#303,  2; //InterfaceMethod scala/xml/parsing/MarkupParser.xToken:(Lscala/collection/Sequence;)V
   216:	aload_0
   217:	invokeinterface	#306,  1; //InterfaceMethod scala/xml/parsing/MarkupParser.xSpace:()V
   222:	aload_0
   223:	invokeinterface	#309,  1; //InterfaceMethod scala/xml/parsing/MarkupParser.xName:()Ljava/lang/String;
   228:	astore	7
   230:	aload_0
   231:	invokeinterface	#323,  1; //InterfaceMethod scala/xml/parsing/MarkupParser.xSpaceOpt:()V
   236:	aload_0
   237:	ldc	#192; //int 62
   239:	invokeinterface	#93,  2; //InterfaceMethod scala/xml/parsing/MarkupParser.xToken:(C)V
   244:	aload_0
   245:	invokeinterface	#335,  1; //InterfaceMethod scala/xml/parsing/MarkupParser.scala$xml$parsing$MarkupParser$$handle:()Lscala/xml/parsing/MarkupHandler;
   250:	aload_3
   251:	aload	6
   253:	aload	7
   255:	invokevirtual	#378; //Method scala/xml/parsing/MarkupHandler.unparsedEntityDecl:(Ljava/lang/String;Lscala/xml/dtd/ExternalID;Ljava/lang/String;)V
   258:	goto	356
   261:	aload_0
   262:	invokeinterface	#97,  1; //InterfaceMethod scala/xml/parsing/MarkupParser.nextch:()V
   267:	aload_0
   268:	invokeinterface	#335,  1; //InterfaceMethod scala/xml/parsing/MarkupParser.scala$xml$parsing$MarkupParser$$handle:()Lscala/xml/parsing/MarkupHandler;
   273:	aload_3
   274:	new	#365; //class scala/xml/dtd/ExtDef
   277:	dup
   278:	aload	6
   280:	invokespecial	#368; //Method scala/xml/dtd/ExtDef."<init>":(Lscala/xml/dtd/ExternalID;)V
   283:	invokevirtual	#381; //Method scala/xml/parsing/MarkupHandler.parsedEntityDecl:(Ljava/lang/String;Lscala/xml/dtd/EntityDef;)V
   286:	goto	356
   289:	aload_0
   290:	invokeinterface	#384,  1; //InterfaceMethod scala/xml/parsing/MarkupParser.xEntityValue:()Ljava/lang/String;
   295:	astore	5
   297:	aload_0
   298:	invokeinterface	#323,  1; //InterfaceMethod scala/xml/parsing/MarkupParser.xSpaceOpt:()V
   303:	aload_0
   304:	ldc	#192; //int 62
   306:	invokeinterface	#93,  2; //InterfaceMethod scala/xml/parsing/MarkupParser.xToken:(C)V
   311:	iload_1
   312:	ifeq	337
   315:	aload_0
   316:	invokeinterface	#335,  1; //InterfaceMethod scala/xml/parsing/MarkupParser.scala$xml$parsing$MarkupParser$$handle:()Lscala/xml/parsing/MarkupHandler;
   321:	aload_3
   322:	new	#386; //class scala/xml/dtd/IntDef
   325:	dup
   326:	aload	5
   328:	invokespecial	#387; //Method scala/xml/dtd/IntDef."<init>":(Ljava/lang/String;)V
   331:	invokevirtual	#372; //Method scala/xml/parsing/MarkupHandler.parameterEntityDecl:(Ljava/lang/String;Lscala/xml/dtd/EntityDef;)V
   334:	goto	356
   337:	aload_0
   338:	invokeinterface	#335,  1; //InterfaceMethod scala/xml/parsing/MarkupParser.scala$xml$parsing$MarkupParser$$handle:()Lscala/xml/parsing/MarkupHandler;
   343:	aload_3
   344:	new	#386; //class scala/xml/dtd/IntDef
   347:	dup
   348:	aload	5
   350:	invokespecial	#387; //Method scala/xml/dtd/IntDef."<init>":(Ljava/lang/String;)V
   353:	invokevirtual	#381; //Method scala/xml/parsing/MarkupHandler.parsedEntityDecl:(Ljava/lang/String;Lscala/xml/dtd/EntityDef;)V
   356:	return
  LineNumberTable: 
   line 1034: 0
   line 1035: 2
   line 1036: 6
   line 1037: 21
   line 1038: 27
   line 1039: 39
   line 1040: 45
   line 1041: 47
   line 1043: 53
   line 1044: 60
   line 1045: 66
   line 1047: 136
   line 1048: 144
   line 1049: 148
   line 1050: 154
   line 1051: 162
   line 1053: 184
   line 1054: 190
   line 1055: 201
   line 1056: 216
   line 1057: 222
   line 1058: 230
   line 1059: 236
   line 1060: 244
   line 1062: 261
   line 1063: 267
   line 1068: 289
   line 1069: 297
   line 1070: 303
   line 1071: 311
   line 1072: 315
   line 1074: 337
   line 1032: 356

  LocalVariableTable: 
   Start  Length  Slot  Name   Signature
   0      357      0    $this       Lscala/xml/parsing/MarkupParser;
   2      355      1    isParameterEntity       Z
   6      351      2    entdef       Lscala/xml/dtd/EntityDef;
   60      297      3    n       Ljava/lang/String;
   74      283      4    temp80       C
   297      59      5    av       Ljava/lang/String;
   144      145      6    extID       Lscala/xml/dtd/ExternalID;
   230      28      7    notat       Ljava/lang/String;


public static void attrDecl(scala.xml.parsing.MarkupParser);
  Code:
   Stack=5, Locals=14, Args_size=1
   0:	aload_0
   1:	getstatic	#108; //Field scala/Predef$.MODULE$:Lscala/Predef$;
   4:	ldc_w	#397; //String TTLIST
   7:	invokevirtual	#112; //Method scala/Predef$.stringWrapper:(Ljava/lang/String;)Lscala/runtime/RichString;
   10:	invokeinterface	#303,  2; //InterfaceMethod scala/xml/parsing/MarkupParser.xToken:(Lscala/collection/Sequence;)V
   15:	aload_0
   16:	invokeinterface	#306,  1; //InterfaceMethod scala/xml/parsing/MarkupParser.xSpace:()V
   21:	aload_0
   22:	invokeinterface	#309,  1; //InterfaceMethod scala/xml/parsing/MarkupParser.xName:()Ljava/lang/String;
   27:	astore_1
   28:	aload_0
   29:	invokeinterface	#306,  1; //InterfaceMethod scala/xml/parsing/MarkupParser.xSpace:()V
   34:	getstatic	#28; //Field scala/collection/immutable/Nil$.MODULE$:Lscala/collection/immutable/Nil$;
   37:	astore_2
   38:	ldc	#192; //int 62
   40:	aload_0
   41:	invokeinterface	#67,  1; //InterfaceMethod scala/xml/parsing/MarkupParser.ch:()C
   46:	if_icmpeq	440
   49:	aload_0
   50:	invokeinterface	#309,  1; //InterfaceMethod scala/xml/parsing/MarkupParser.xName:()Ljava/lang/String;
   55:	astore_3
   56:	aconst_null
   57:	pop
   58:	aconst_null
   59:	astore	4
   61:	aload_0
   62:	invokeinterface	#306,  1; //InterfaceMethod scala/xml/parsing/MarkupParser.xSpace:()V
   67:	ldc	#201; //int 34
   69:	aload_0
   70:	invokeinterface	#67,  1; //InterfaceMethod scala/xml/parsing/MarkupParser.ch:()C
   75:	if_icmpeq	157
   78:	ldc	#198; //int 39
   80:	aload_0
   81:	invokeinterface	#67,  1; //InterfaceMethod scala/xml/parsing/MarkupParser.ch:()C
   86:	if_icmpeq	157
   89:	ldc	#147; //int 35
   91:	aload_0
   92:	invokeinterface	#67,  1; //InterfaceMethod scala/xml/parsing/MarkupParser.ch:()C
   97:	if_icmpeq	157
   100:	ldc	#189; //int 60
   102:	aload_0
   103:	invokeinterface	#67,  1; //InterfaceMethod scala/xml/parsing/MarkupParser.ch:()C
   108:	if_icmpeq	157
   111:	aload_0
   112:	aload_0
   113:	invokeinterface	#67,  1; //InterfaceMethod scala/xml/parsing/MarkupParser.ch:()C
   118:	invokeinterface	#73,  2; //InterfaceMethod scala/xml/parsing/TokenTests.isSpace:(C)Z
   123:	ifeq	132
   126:	getstatic	#403; //Field scala/runtime/BoxedUnit.UNIT:Lscala/runtime/BoxedUnit;
   129:	goto	147
   132:	aload_0
   133:	invokeinterface	#138,  1; //InterfaceMethod scala/xml/parsing/MarkupParser.cbuf:()Lscala/collection/mutable/StringBuilder;
   138:	aload_0
   139:	invokeinterface	#67,  1; //InterfaceMethod scala/xml/parsing/MarkupParser.ch:()C
   144:	invokevirtual	#142; //Method scala/collection/mutable/StringBuilder.append:(C)Lscala/collection/mutable/StringBuilder;
   147:	pop
   148:	aload_0
   149:	invokeinterface	#97,  1; //InterfaceMethod scala/xml/parsing/MarkupParser.nextch:()V
   154:	goto	67
   157:	aload_0
   158:	invokeinterface	#138,  1; //InterfaceMethod scala/xml/parsing/MarkupParser.cbuf:()Lscala/collection/mutable/StringBuilder;
   163:	invokevirtual	#181; //Method scala/collection/mutable/StringBuilder.toString:()Ljava/lang/String;
   166:	astore	5
   168:	aload_0
   169:	invokeinterface	#138,  1; //InterfaceMethod scala/xml/parsing/MarkupParser.cbuf:()Lscala/collection/mutable/StringBuilder;
   174:	iconst_0
   175:	invokevirtual	#207; //Method scala/collection/mutable/StringBuilder.length_$eq:(I)V
   178:	aload_0
   179:	invokeinterface	#67,  1; //InterfaceMethod scala/xml/parsing/MarkupParser.ch:()C
   184:	istore	6
   186:	iload	6
   188:	lookupswitch{ //3
		34: 380;
		35: 224;
		39: 380;
		default: 400 }
   224:	aload_0
   225:	invokeinterface	#97,  1; //InterfaceMethod scala/xml/parsing/MarkupParser.nextch:()V
   230:	aload_0
   231:	invokeinterface	#309,  1; //InterfaceMethod scala/xml/parsing/MarkupParser.xName:()Ljava/lang/String;
   236:	astore	8
   238:	aload	8
   240:	ldc_w	#405; //String FIXED
   243:	astore	9
   245:	dup
   246:	ifnonnull	258
   249:	pop
   250:	aload	9
   252:	ifnull	266
   255:	goto	295
   258:	aload	9
   260:	invokevirtual	#188; //Method java/lang/Object.equals:(Ljava/lang/Object;)Z
   263:	ifeq	295
   266:	aload_0
   267:	invokeinterface	#306,  1; //InterfaceMethod scala/xml/parsing/MarkupParser.xSpace:()V
   272:	aload_0
   273:	invokeinterface	#408,  1; //InterfaceMethod scala/xml/parsing/MarkupParser.xAttributeValue:()Ljava/lang/String;
   278:	astore	10
   280:	new	#410; //class scala/xml/dtd/DEFAULT
   283:	dup
   284:	iconst_1
   285:	aload	10
   287:	invokespecial	#413; //Method scala/xml/dtd/DEFAULT."<init>":(ZLjava/lang/String;)V
   290:	astore	4
   292:	goto	400
   295:	aload	8
   297:	ldc_w	#415; //String IMPLIED
   300:	astore	11
   302:	dup
   303:	ifnonnull	315
   306:	pop
   307:	aload	11
   309:	ifnull	323
   312:	goto	331
   315:	aload	11
   317:	invokevirtual	#188; //Method java/lang/Object.equals:(Ljava/lang/Object;)Z
   320:	ifeq	331
   323:	getstatic	#420; //Field scala/xml/dtd/IMPLIED$.MODULE$:Lscala/xml/dtd/IMPLIED$;
   326:	astore	4
   328:	goto	400
   331:	aload	8
   333:	ldc_w	#422; //String REQUIRED
   336:	astore	12
   338:	dup
   339:	ifnonnull	351
   342:	pop
   343:	aload	12
   345:	ifnull	359
   348:	goto	367
   351:	aload	12
   353:	invokevirtual	#188; //Method java/lang/Object.equals:(Ljava/lang/Object;)Z
   356:	ifeq	367
   359:	getstatic	#427; //Field scala/xml/dtd/REQUIRED$.MODULE$:Lscala/xml/dtd/REQUIRED$;
   362:	astore	4
   364:	goto	400
   367:	new	#360; //class scala/MatchError
   370:	dup
   371:	aload	8
   373:	invokevirtual	#430; //Method java/lang/String.toString:()Ljava/lang/String;
   376:	invokespecial	#363; //Method scala/MatchError."<init>":(Ljava/lang/String;)V
   379:	athrow
   380:	aload_0
   381:	invokeinterface	#408,  1; //InterfaceMethod scala/xml/parsing/MarkupParser.xAttributeValue:()Ljava/lang/String;
   386:	astore	7
   388:	new	#410; //class scala/xml/dtd/DEFAULT
   391:	dup
   392:	iconst_0
   393:	aload	7
   395:	invokespecial	#413; //Method scala/xml/dtd/DEFAULT."<init>":(ZLjava/lang/String;)V
   398:	astore	4
   400:	aload_0
   401:	invokeinterface	#323,  1; //InterfaceMethod scala/xml/parsing/MarkupParser.xSpaceOpt:()V
   406:	new	#432; //class scala/xml/dtd/AttrDecl
   409:	dup
   410:	aload_3
   411:	aload	5
   413:	aload	4
   415:	invokespecial	#435; //Method scala/xml/dtd/AttrDecl."<init>":(Ljava/lang/String;Ljava/lang/String;Lscala/xml/dtd/DefaultDecl;)V
   418:	astore	13
   420:	aload_2
   421:	aload	13
   423:	invokevirtual	#260; //Method scala/collection/immutable/List.$colon$colon:(Ljava/lang/Object;)Lscala/collection/immutable/List;
   426:	astore_2
   427:	aload_0
   428:	invokeinterface	#138,  1; //InterfaceMethod scala/xml/parsing/MarkupParser.cbuf:()Lscala/collection/mutable/StringBuilder;
   433:	iconst_0
   434:	invokevirtual	#207; //Method scala/collection/mutable/StringBuilder.length_$eq:(I)V
   437:	goto	38
   440:	aload_0
   441:	invokeinterface	#97,  1; //InterfaceMethod scala/xml/parsing/MarkupParser.nextch:()V
   446:	aload_0
   447:	invokeinterface	#335,  1; //InterfaceMethod scala/xml/parsing/MarkupParser.scala$xml$parsing$MarkupParser$$handle:()Lscala/xml/parsing/MarkupHandler;
   452:	aload_1
   453:	aload_2
   454:	invokevirtual	#438; //Method scala/collection/immutable/List.reverse:()Lscala/collection/immutable/List;
   457:	invokevirtual	#442; //Method scala/xml/parsing/MarkupHandler.attListDecl:(Ljava/lang/String;Lscala/collection/immutable/List;)V
   460:	return
  LineNumberTable: 
   line 982: 0
   line 983: 15
   line 984: 21
   line 985: 28
   line 986: 34
   line 988: 38
   line 989: 49
   line 991: 56
   line 992: 61
   line 994: 67
   line 995: 111
   line 996: 132
   line 995: 147
   line 997: 148
   line 994: 154
   line 999: 157
   line 1000: 168
   line 1002: 178
   line 1008: 224
   line 1009: 230
   line 1011: 266
   line 1012: 272
   line 1013: 280
   line 1009: 295
   line 1015: 323
   line 1009: 331
   line 1017: 359
   line 1009: 367
   line 1004: 380
   line 1005: 388
   line 1021: 400
   line 1023: 406
   line 1024: 427
   line 988: 437
   line 1026: 440
   line 1027: 446

  LocalVariableTable: 
   Start  Length  Slot  Name   Signature
   0      461      0    $this       Lscala/xml/parsing/MarkupParser;
   28      432      1    n       Ljava/lang/String;
   38      422      2    attList       Lscala/collection/immutable/List;
   56      381      3    aname       Ljava/lang/String;
   61      376      4    defdecl       Lscala/xml/dtd/DefaultDecl;
   168      269      5    atpe       Ljava/lang/String;
   186      254      6    temp79       C
   388      12      7    defValue       Ljava/lang/String;
   238      142      8    temp75       Ljava/lang/String;
   280      12      10    defValue       Ljava/lang/String;


public static void elementDecl(scala.xml.parsing.MarkupParser);
  Code:
   Stack=3, Locals=3, Args_size=1
   0:	aload_0
   1:	getstatic	#108; //Field scala/Predef$.MODULE$:Lscala/Predef$;
   4:	ldc_w	#454; //String EMENT
   7:	invokevirtual	#112; //Method scala/Predef$.stringWrapper:(Ljava/lang/String;)Lscala/runtime/RichString;
   10:	invokeinterface	#303,  2; //InterfaceMethod scala/xml/parsing/MarkupParser.xToken:(Lscala/collection/Sequence;)V
   15:	aload_0
   16:	invokeinterface	#306,  1; //InterfaceMethod scala/xml/parsing/MarkupParser.xSpace:()V
   21:	aload_0
   22:	invokeinterface	#309,  1; //InterfaceMethod scala/xml/parsing/MarkupParser.xName:()Ljava/lang/String;
   27:	astore_1
   28:	aload_0
   29:	invokeinterface	#306,  1; //InterfaceMethod scala/xml/parsing/MarkupParser.xSpace:()V
   34:	ldc	#192; //int 62
   36:	aload_0
   37:	invokeinterface	#67,  1; //InterfaceMethod scala/xml/parsing/MarkupParser.ch:()C
   42:	if_icmpeq	67
   45:	aload_0
   46:	aload_0
   47:	invokeinterface	#67,  1; //InterfaceMethod scala/xml/parsing/MarkupParser.ch:()C
   52:	invokeinterface	#457,  2; //InterfaceMethod scala/xml/parsing/MarkupParser.putChar:(C)Lscala/collection/mutable/StringBuilder;
   57:	pop
   58:	aload_0
   59:	invokeinterface	#97,  1; //InterfaceMethod scala/xml/parsing/MarkupParser.nextch:()V
   64:	goto	34
   67:	aload_0
   68:	invokeinterface	#97,  1; //InterfaceMethod scala/xml/parsing/MarkupParser.nextch:()V
   73:	aload_0
   74:	invokeinterface	#138,  1; //InterfaceMethod scala/xml/parsing/MarkupParser.cbuf:()Lscala/collection/mutable/StringBuilder;
   79:	invokevirtual	#181; //Method scala/collection/mutable/StringBuilder.toString:()Ljava/lang/String;
   82:	astore_2
   83:	aload_0
   84:	invokeinterface	#138,  1; //InterfaceMethod scala/xml/parsing/MarkupParser.cbuf:()Lscala/collection/mutable/StringBuilder;
   89:	iconst_0
   90:	invokevirtual	#207; //Method scala/collection/mutable/StringBuilder.length_$eq:(I)V
   93:	aload_0
   94:	invokeinterface	#335,  1; //InterfaceMethod scala/xml/parsing/MarkupParser.scala$xml$parsing$MarkupParser$$handle:()Lscala/xml/parsing/MarkupHandler;
   99:	aload_1
   100:	aload_2
   101:	invokevirtual	#460; //Method scala/xml/parsing/MarkupHandler.elemDecl:(Ljava/lang/String;Ljava/lang/String;)V
   104:	return
  LineNumberTable: 
   line 963: 0
   line 964: 15
   line 965: 21
   line 966: 28
   line 967: 34
   line 969: 45
   line 970: 58
   line 967: 64
   line 973: 67
   line 974: 73
   line 975: 83
   line 976: 93

  LocalVariableTable: 
   Start  Length  Slot  Name   Signature
   0      105      0    $this       Lscala/xml/parsing/MarkupParser;
   28      76      1    n       Ljava/lang/String;
   83      21      2    cmstr       Ljava/lang/String;


public static void intSubset(scala.xml.parsing.MarkupParser);
  Code:
   Stack=2, Locals=1, Args_size=1
   0:	aload_0
   1:	invokeinterface	#306,  1; //InterfaceMethod scala/xml/parsing/MarkupParser.xSpace:()V
   6:	ldc	#94; //int 93
   8:	aload_0
   9:	invokeinterface	#67,  1; //InterfaceMethod scala/xml/parsing/MarkupParser.ch:()C
   14:	if_icmpeq	26
   17:	aload_0
   18:	invokeinterface	#101,  1; //InterfaceMethod scala/xml/parsing/MarkupParser.markupDecl:()V
   23:	goto	6
   26:	return
  LineNumberTable: 
   line 955: 0
   line 956: 6
   line 957: 17
   line 953: 26

  LocalVariableTable: 
   Start  Length  Slot  Name   Signature
   0      27      0    $this       Lscala/xml/parsing/MarkupParser;


public static void markupDecl(scala.xml.parsing.MarkupParser);
  Code:
   Stack=3, Locals=3, Args_size=1
   0:	aload_0
   1:	invokeinterface	#67,  1; //InterfaceMethod scala/xml/parsing/MarkupParser.ch:()C
   6:	istore_1
   7:	iload_1
   8:	invokestatic	#146; //Method scala/runtime/BoxesRunTime.boxToCharacter:(C)Ljava/lang/Character;
   11:	ldc_w	#358; //int 37
   14:	invokestatic	#146; //Method scala/runtime/BoxesRunTime.boxToCharacter:(C)Ljava/lang/Character;
   17:	invokestatic	#155; //Method scala/runtime/BoxesRunTime.equals:(Ljava/lang/Object;Ljava/lang/Object;)Z
   20:	ifeq	77
   23:	aload_0
   24:	invokeinterface	#97,  1; //InterfaceMethod scala/xml/parsing/MarkupParser.nextch:()V
   29:	aload_0
   30:	invokeinterface	#309,  1; //InterfaceMethod scala/xml/parsing/MarkupParser.xName:()Ljava/lang/String;
   35:	astore_2
   36:	aload_0
   37:	ldc	#177; //int 59
   39:	invokeinterface	#93,  2; //InterfaceMethod scala/xml/parsing/MarkupParser.xToken:(C)V
   44:	aload_0
   45:	checkcast	#18; //class scala/xml/parsing/MarkupHandler
   48:	invokevirtual	#465; //Method scala/xml/parsing/MarkupHandler.isValidating:()Z
   51:	ifeq	64
   54:	aload_0
   55:	aload_2
   56:	invokeinterface	#467,  2; //InterfaceMethod scala/xml/parsing/MarkupParser.push:(Ljava/lang/String;)V
   61:	goto	182
   64:	aload_0
   65:	invokeinterface	#335,  1; //InterfaceMethod scala/xml/parsing/MarkupParser.scala$xml$parsing$MarkupParser$$handle:()Lscala/xml/parsing/MarkupHandler;
   70:	aload_2
   71:	invokevirtual	#470; //Method scala/xml/parsing/MarkupHandler.peReference:(Ljava/lang/String;)V
   74:	goto	182
   77:	iload_1
   78:	invokestatic	#146; //Method scala/runtime/BoxesRunTime.boxToCharacter:(C)Ljava/lang/Character;
   81:	ldc	#189; //int 60
   83:	invokestatic	#146; //Method scala/runtime/BoxesRunTime.boxToCharacter:(C)Ljava/lang/Character;
   86:	invokestatic	#155; //Method scala/runtime/BoxesRunTime.equals:(Ljava/lang/Object;Ljava/lang/Object;)Z
   89:	ifeq	108
   92:	aload_0
   93:	invokeinterface	#97,  1; //InterfaceMethod scala/xml/parsing/MarkupParser.nextch:()V
   98:	aload_0
   99:	invokeinterface	#473,  1; //InterfaceMethod scala/xml/parsing/MarkupParser.markupDecl1:()Ljava/lang/Object;
   104:	pop
   105:	goto	182
   108:	aload_0
   109:	invokestatic	#477; //Method gd2$1:(Lscala/xml/parsing/MarkupParser;)Z
   112:	ifeq	124
   115:	aload_0
   116:	invokeinterface	#306,  1; //InterfaceMethod scala/xml/parsing/MarkupParser.xSpace:()V
   121:	goto	182
   124:	aload_0
   125:	new	#38; //class scala/collection/mutable/StringBuilder
   128:	dup
   129:	invokespecial	#478; //Method scala/collection/mutable/StringBuilder."<init>":()V
   132:	ldc_w	#480; //String markupdecl: unexpected character '
   135:	invokevirtual	#483; //Method scala/collection/mutable/StringBuilder.append:(Ljava/lang/Object;)Lscala/collection/mutable/StringBuilder;
   138:	aload_0
   139:	invokeinterface	#67,  1; //InterfaceMethod scala/xml/parsing/MarkupParser.ch:()C
   144:	invokestatic	#146; //Method scala/runtime/BoxesRunTime.boxToCharacter:(C)Ljava/lang/Character;
   147:	invokevirtual	#483; //Method scala/collection/mutable/StringBuilder.append:(Ljava/lang/Object;)Lscala/collection/mutable/StringBuilder;
   150:	ldc_w	#485; //String ' #
   153:	invokevirtual	#483; //Method scala/collection/mutable/StringBuilder.append:(Ljava/lang/Object;)Lscala/collection/mutable/StringBuilder;
   156:	aload_0
   157:	invokeinterface	#67,  1; //InterfaceMethod scala/xml/parsing/MarkupParser.ch:()C
   162:	invokestatic	#151; //Method scala/runtime/BoxesRunTime.boxToInteger:(I)Ljava/lang/Integer;
   165:	invokevirtual	#483; //Method scala/collection/mutable/StringBuilder.append:(Ljava/lang/Object;)Lscala/collection/mutable/StringBuilder;
   168:	invokevirtual	#486; //Method scala/collection/mutable/StringBuilder.toString:()Ljava/lang/String;
   171:	invokeinterface	#343,  2; //InterfaceMethod scala/xml/parsing/MarkupParser.reportSyntaxError:(Ljava/lang/String;)V
   176:	aload_0
   177:	invokeinterface	#97,  1; //InterfaceMethod scala/xml/parsing/MarkupParser.nextch:()V
   182:	return
  LineNumberTable: 
   line 929: 0
   line 931: 23
   line 932: 29
   line 933: 36
   line 934: 44
   line 937: 54
   line 935: 64
   line 929: 77
   line 941: 92
   line 942: 98
   line 929: 108
   line 944: 115
   line 946: 124
   line 947: 176
   line 929: 182

  LocalVariableTable: 
   Start  Length  Slot  Name   Signature
   0      183      0    $this       Lscala/xml/parsing/MarkupParser;
   7      176      1    temp72       C
   36      41      2    ent       Ljava/lang/String;


public static java.lang.Object markupDecl1(scala.xml.parsing.MarkupParser);
  Code:
   Stack=4, Locals=13, Args_size=1
   0:	ldc_w	#490; //int 63
   3:	aload_0
   4:	invokeinterface	#67,  1; //InterfaceMethod scala/xml/parsing/MarkupParser.ch:()C
   9:	if_icmpne	27
   12:	aload_0
   13:	invokeinterface	#97,  1; //InterfaceMethod scala/xml/parsing/MarkupParser.nextch:()V
   18:	aload_0
   19:	invokeinterface	#494,  1; //InterfaceMethod scala/xml/parsing/MarkupParser.xProcInstr:()Lscala/xml/NodeSeq;
   24:	goto	628
   27:	aload_0
   28:	ldc_w	#495; //int 33
   31:	invokeinterface	#93,  2; //InterfaceMethod scala/xml/parsing/MarkupParser.xToken:(C)V
   36:	aload_0
   37:	invokeinterface	#67,  1; //InterfaceMethod scala/xml/parsing/MarkupParser.ch:()C
   42:	istore_1
   43:	iload_1
   44:	lookupswitch{ //5
		45: 622;
		65: 604;
		69: 556;
		78: 538;
		91: 96;
		default: 442 }
   96:	aload_0
   97:	invokestatic	#497; //Method gd1$1:(Lscala/xml/parsing/MarkupParser;)Z
   100:	ifeq	442
   103:	aload_0
   104:	invokeinterface	#97,  1; //InterfaceMethod scala/xml/parsing/MarkupParser.nextch:()V
   109:	aload_0
   110:	invokeinterface	#323,  1; //InterfaceMethod scala/xml/parsing/MarkupParser.xSpaceOpt:()V
   115:	aload_0
   116:	invokeinterface	#67,  1; //InterfaceMethod scala/xml/parsing/MarkupParser.ch:()C
   121:	istore_2
   122:	iload_2
   123:	lookupswitch{ //2
		37: 282;
		73: 163;
		default: 148 }
   148:	new	#360; //class scala/MatchError
   151:	dup
   152:	iload_2
   153:	invokestatic	#146; //Method scala/runtime/BoxesRunTime.boxToCharacter:(C)Ljava/lang/Character;
   156:	invokevirtual	#361; //Method java/lang/Object.toString:()Ljava/lang/String;
   159:	invokespecial	#363; //Method scala/MatchError."<init>":(Ljava/lang/String;)V
   162:	athrow
   163:	aload_0
   164:	invokeinterface	#97,  1; //InterfaceMethod scala/xml/parsing/MarkupParser.nextch:()V
   169:	aload_0
   170:	invokeinterface	#67,  1; //InterfaceMethod scala/xml/parsing/MarkupParser.ch:()C
   175:	istore	8
   177:	iload	8
   179:	lookupswitch{ //2
		71: 248;
		78: 220;
		default: 204 }
   204:	new	#360; //class scala/MatchError
   207:	dup
   208:	iload	8
   210:	invokestatic	#146; //Method scala/runtime/BoxesRunTime.boxToCharacter:(C)Ljava/lang/Character;
   213:	invokevirtual	#361; //Method java/lang/Object.toString:()Ljava/lang/String;
   216:	invokespecial	#363; //Method scala/MatchError."<init>":(Ljava/lang/String;)V
   219:	athrow
   220:	aload_0
   221:	invokeinterface	#97,  1; //InterfaceMethod scala/xml/parsing/MarkupParser.nextch:()V
   226:	aload_0
   227:	getstatic	#108; //Field scala/Predef$.MODULE$:Lscala/Predef$;
   230:	ldc_w	#499; //String NCLUDE
   233:	invokevirtual	#112; //Method scala/Predef$.stringWrapper:(Ljava/lang/String;)Lscala/runtime/RichString;
   236:	invokeinterface	#303,  2; //InterfaceMethod scala/xml/parsing/MarkupParser.xToken:(Lscala/collection/Sequence;)V
   241:	aload_0
   242:	invokestatic	#501; //Method doInclude$1:(Lscala/xml/parsing/MarkupParser;)V
   245:	goto	407
   248:	aload_0
   249:	invokeinterface	#97,  1; //InterfaceMethod scala/xml/parsing/MarkupParser.nextch:()V
   254:	aload_0
   255:	getstatic	#108; //Field scala/Predef$.MODULE$:Lscala/Predef$;
   258:	ldc_w	#503; //String NORE
   261:	invokevirtual	#112; //Method scala/Predef$.stringWrapper:(Ljava/lang/String;)Lscala/runtime/RichString;
   264:	invokeinterface	#303,  2; //InterfaceMethod scala/xml/parsing/MarkupParser.xToken:(Lscala/collection/Sequence;)V
   269:	aload_0
   270:	invokeinterface	#323,  1; //InterfaceMethod scala/xml/parsing/MarkupParser.xSpaceOpt:()V
   275:	aload_0
   276:	invokestatic	#505; //Method doIgnore$1:(Lscala/xml/parsing/MarkupParser;)V
   279:	goto	407
   282:	aload_0
   283:	invokeinterface	#97,  1; //InterfaceMethod scala/xml/parsing/MarkupParser.nextch:()V
   288:	aload_0
   289:	invokeinterface	#309,  1; //InterfaceMethod scala/xml/parsing/MarkupParser.xName:()Ljava/lang/String;
   294:	astore_3
   295:	aload_0
   296:	ldc	#177; //int 59
   298:	invokeinterface	#93,  2; //InterfaceMethod scala/xml/parsing/MarkupParser.xToken:(C)V
   303:	aload_0
   304:	invokeinterface	#323,  1; //InterfaceMethod scala/xml/parsing/MarkupParser.xSpaceOpt:()V
   309:	aload_0
   310:	aload_3
   311:	invokeinterface	#467,  2; //InterfaceMethod scala/xml/parsing/MarkupParser.push:(Ljava/lang/String;)V
   316:	aload_0
   317:	invokeinterface	#323,  1; //InterfaceMethod scala/xml/parsing/MarkupParser.xSpaceOpt:()V
   322:	aload_0
   323:	invokeinterface	#309,  1; //InterfaceMethod scala/xml/parsing/MarkupParser.xName:()Ljava/lang/String;
   328:	astore	4
   330:	aload_0
   331:	invokeinterface	#323,  1; //InterfaceMethod scala/xml/parsing/MarkupParser.xSpaceOpt:()V
   336:	aload	4
   338:	astore	5
   340:	aload	5
   342:	ldc_w	#507; //String INCLUDE
   345:	astore	6
   347:	dup
   348:	ifnonnull	360
   351:	pop
   352:	aload	6
   354:	ifnull	368
   357:	goto	375
   360:	aload	6
   362:	invokevirtual	#188; //Method java/lang/Object.equals:(Ljava/lang/Object;)Z
   365:	ifeq	375
   368:	aload_0
   369:	invokestatic	#501; //Method doInclude$1:(Lscala/xml/parsing/MarkupParser;)V
   372:	goto	407
   375:	aload	5
   377:	ldc_w	#509; //String IGNORE
   380:	astore	7
   382:	dup
   383:	ifnonnull	395
   386:	pop
   387:	aload	7
   389:	ifnull	403
   392:	goto	429
   395:	aload	7
   397:	invokevirtual	#188; //Method java/lang/Object.equals:(Ljava/lang/Object;)Z
   400:	ifeq	429
   403:	aload_0
   404:	invokestatic	#505; //Method doIgnore$1:(Lscala/xml/parsing/MarkupParser;)V
   407:	aload_0
   408:	ldc	#94; //int 93
   410:	invokeinterface	#93,  2; //InterfaceMethod scala/xml/parsing/MarkupParser.xToken:(C)V
   415:	aload_0
   416:	ldc	#192; //int 62
   418:	invokeinterface	#93,  2; //InterfaceMethod scala/xml/parsing/MarkupParser.xToken:(C)V
   423:	getstatic	#403; //Field scala/runtime/BoxedUnit.UNIT:Lscala/runtime/BoxedUnit;
   426:	goto	628
   429:	new	#360; //class scala/MatchError
   432:	dup
   433:	aload	5
   435:	invokevirtual	#430; //Method java/lang/String.toString:()Ljava/lang/String;
   438:	invokespecial	#363; //Method scala/MatchError."<init>":(Ljava/lang/String;)V
   441:	athrow
   442:	aload_0
   443:	invokeinterface	#241,  1; //InterfaceMethod scala/xml/parsing/MarkupParser.curInput:()Lscala/io/Source;
   448:	astore	9
   450:	aload_0
   451:	invokeinterface	#290,  1; //InterfaceMethod scala/xml/parsing/MarkupParser.pos:()I
   456:	istore	10
   458:	new	#38; //class scala/collection/mutable/StringBuilder
   461:	dup
   462:	invokespecial	#478; //Method scala/collection/mutable/StringBuilder."<init>":()V
   465:	ldc_w	#511; //String unexpected character '
   468:	invokevirtual	#483; //Method scala/collection/mutable/StringBuilder.append:(Ljava/lang/Object;)Lscala/collection/mutable/StringBuilder;
   471:	aload_0
   472:	invokeinterface	#67,  1; //InterfaceMethod scala/xml/parsing/MarkupParser.ch:()C
   477:	invokestatic	#146; //Method scala/runtime/BoxesRunTime.boxToCharacter:(C)Ljava/lang/Character;
   480:	invokevirtual	#483; //Method scala/collection/mutable/StringBuilder.append:(Ljava/lang/Object;)Lscala/collection/mutable/StringBuilder;
   483:	ldc_w	#513; //String ', expected some markupdecl
   486:	invokevirtual	#483; //Method scala/collection/mutable/StringBuilder.append:(Ljava/lang/Object;)Lscala/collection/mutable/StringBuilder;
   489:	invokevirtual	#486; //Method scala/collection/mutable/StringBuilder.toString:()Ljava/lang/String;
   492:	astore	11
   494:	aload	9
   496:	invokevirtual	#276; //Method scala/io/Source.reportError$default$3:()Ljava/io/PrintStream;
   499:	astore	12
   501:	aload	9
   503:	iload	10
   505:	aload	11
   507:	aload	12
   509:	invokevirtual	#280; //Method scala/io/Source.reportError:(ILjava/lang/String;Ljava/io/PrintStream;)V
   512:	aload_0
   513:	invokeinterface	#67,  1; //InterfaceMethod scala/xml/parsing/MarkupParser.ch:()C
   518:	ldc	#192; //int 62
   520:	if_icmpeq	532
   523:	aload_0
   524:	invokeinterface	#97,  1; //InterfaceMethod scala/xml/parsing/MarkupParser.nextch:()V
   529:	goto	512
   532:	getstatic	#403; //Field scala/runtime/BoxedUnit.UNIT:Lscala/runtime/BoxedUnit;
   535:	goto	628
   538:	aload_0
   539:	invokeinterface	#97,  1; //InterfaceMethod scala/xml/parsing/MarkupParser.nextch:()V
   544:	aload_0
   545:	invokeinterface	#515,  1; //InterfaceMethod scala/xml/parsing/MarkupParser.notationDecl:()V
   550:	getstatic	#403; //Field scala/runtime/BoxedUnit.UNIT:Lscala/runtime/BoxedUnit;
   553:	goto	628
   556:	aload_0
   557:	invokeinterface	#97,  1; //InterfaceMethod scala/xml/parsing/MarkupParser.nextch:()V
   562:	ldc_w	#516; //int 76
   565:	aload_0
   566:	invokeinterface	#67,  1; //InterfaceMethod scala/xml/parsing/MarkupParser.ch:()C
   571:	if_icmpne	592
   574:	aload_0
   575:	invokeinterface	#97,  1; //InterfaceMethod scala/xml/parsing/MarkupParser.nextch:()V
   580:	aload_0
   581:	invokeinterface	#518,  1; //InterfaceMethod scala/xml/parsing/MarkupParser.elementDecl:()V
   586:	getstatic	#403; //Field scala/runtime/BoxedUnit.UNIT:Lscala/runtime/BoxedUnit;
   589:	goto	628
   592:	aload_0
   593:	invokeinterface	#520,  1; //InterfaceMethod scala/xml/parsing/MarkupParser.entityDecl:()V
   598:	getstatic	#403; //Field scala/runtime/BoxedUnit.UNIT:Lscala/runtime/BoxedUnit;
   601:	goto	628
   604:	aload_0
   605:	invokeinterface	#97,  1; //InterfaceMethod scala/xml/parsing/MarkupParser.nextch:()V
   610:	aload_0
   611:	invokeinterface	#522,  1; //InterfaceMethod scala/xml/parsing/MarkupParser.attrDecl:()V
   616:	getstatic	#403; //Field scala/runtime/BoxedUnit.UNIT:Lscala/runtime/BoxedUnit;
   619:	goto	628
   622:	aload_0
   623:	invokeinterface	#525,  1; //InterfaceMethod scala/xml/parsing/MarkupParser.xComment:()Lscala/xml/NodeSeq;
   628:	areturn
  LineNumberTable: 
   line 841: 0
   line 842: 12
   line 843: 18
   line 845: 27
   line 846: 36
   line 867: 103
   line 868: 109
   line 869: 115
   line 905: 163
   line 906: 169
   line 913: 220
   line 914: 226
   line 915: 241
   line 906: 245
   line 908: 248
   line 909: 254
   line 910: 269
   line 911: 275
   line 906: 279
   line 871: 282
   line 872: 288
   line 873: 295
   line 874: 303
   line 882: 309
   line 883: 316
   line 885: 322
   line 887: 330
   line 897: 336
   line 900: 368
   line 897: 375
   line 902: 403
   line 918: 407
   line 919: 415
   line 897: 429
   line 922: 442
   line 923: 512
   line 924: 523
   line 923: 532
   line 863: 538
   line 864: 544
   line 846: 553
   line 851: 556
   line 852: 562
   line 853: 574
   line 854: 580
   line 856: 592
   line 859: 604
   line 860: 610
   line 846: 619
   line 848: 622
   line 841: 628

  LocalVariableTable: 
   Start  Length  Slot  Name   Signature
   0      629      0    $this       Lscala/xml/parsing/MarkupParser;
   43      585      1    temp71       C
   122      320      2    temp70       C
   295      112      3    ent       Ljava/lang/String;
   429      13      3    ent       Ljava/lang/String;
   330      77      4    stmt       Ljava/lang/String;
   429      13      4    stmt       Ljava/lang/String;
   340      67      5    temp66       Ljava/lang/String;
   429      13      5    temp66       Ljava/lang/String;
   177      105      8    temp69       C
   450      62      9    qual$1       Lscala/io/Source;
   458      54      10    x$8       I
   494      18      11    x$9       Ljava/lang/String;
   501      11      12    x$10       Ljava/io/PrintStream;


public static void extSubset(scala.xml.parsing.MarkupParser);
  Code:
   Stack=2, Locals=2, Args_size=1
   0:	aconst_null
   1:	pop
   2:	aconst_null
   3:	astore_1
   4:	aload_0
   5:	invokeinterface	#67,  1; //InterfaceMethod scala/xml/parsing/MarkupParser.ch:()C
   10:	ldc	#189; //int 60
   12:	if_icmpne	61
   15:	aload_0
   16:	invokeinterface	#97,  1; //InterfaceMethod scala/xml/parsing/MarkupParser.nextch:()V
   21:	aload_0
   22:	invokeinterface	#67,  1; //InterfaceMethod scala/xml/parsing/MarkupParser.ch:()C
   27:	ldc_w	#490; //int 63
   30:	if_icmpne	52
   33:	aload_0
   34:	invokeinterface	#97,  1; //InterfaceMethod scala/xml/parsing/MarkupParser.nextch:()V
   39:	aload_0
   40:	invokeinterface	#539,  1; //InterfaceMethod scala/xml/parsing/MarkupParser.textDecl:()Lscala/Tuple2;
   45:	astore_1
   46:	getstatic	#403; //Field scala/runtime/BoxedUnit.UNIT:Lscala/runtime/BoxedUnit;
   49:	goto	64
   52:	aload_0
   53:	invokeinterface	#473,  1; //InterfaceMethod scala/xml/parsing/MarkupParser.markupDecl1:()Ljava/lang/Object;
   58:	goto	64
   61:	getstatic	#403; //Field scala/runtime/BoxedUnit.UNIT:Lscala/runtime/BoxedUnit;
   64:	pop
   65:	aload_0
   66:	invokeinterface	#256,  1; //InterfaceMethod scala/xml/parsing/MarkupParser.eof:()Z
   71:	ifeq	75
   74:	return
   75:	aload_0
   76:	invokeinterface	#101,  1; //InterfaceMethod scala/xml/parsing/MarkupParser.markupDecl:()V
   81:	goto	65
  LineNumberTable: 
   line 821: 0
   line 822: 4
   line 823: 15
   line 824: 21
   line 825: 33
   line 826: 39
   line 824: 46
   line 828: 52
   line 822: 61
   line 830: 65
   line 820: 74
   line 831: 75

  LocalVariableTable: 
   Start  Length  Slot  Name   Signature
   0      84      0    $this       Lscala/xml/parsing/MarkupParser;
   4      80      1    textdecl       Lscala/Tuple2;


public static java.lang.String pubidLiteral(scala.xml.parsing.MarkupParser);
  Code:
   Stack=3, Locals=3, Args_size=1
   0:	aload_0
   1:	invokeinterface	#67,  1; //InterfaceMethod scala/xml/parsing/MarkupParser.ch:()C
   6:	istore_1
   7:	aload_0
   8:	invokeinterface	#67,  1; //InterfaceMethod scala/xml/parsing/MarkupParser.ch:()C
   13:	ldc	#198; //int 39
   15:	if_icmpeq	38
   18:	aload_0
   19:	invokeinterface	#67,  1; //InterfaceMethod scala/xml/parsing/MarkupParser.ch:()C
   24:	ldc	#201; //int 34
   26:	if_icmpeq	38
   29:	aload_0
   30:	ldc_w	#544; //String quote ' or \" expected
   33:	invokeinterface	#343,  2; //InterfaceMethod scala/xml/parsing/MarkupParser.reportSyntaxError:(Ljava/lang/String;)V
   38:	aload_0
   39:	invokeinterface	#97,  1; //InterfaceMethod scala/xml/parsing/MarkupParser.nextch:()V
   44:	aload_0
   45:	invokeinterface	#67,  1; //InterfaceMethod scala/xml/parsing/MarkupParser.ch:()C
   50:	iload_1
   51:	if_icmpeq	131
   54:	aload_0
   55:	aload_0
   56:	invokeinterface	#67,  1; //InterfaceMethod scala/xml/parsing/MarkupParser.ch:()C
   61:	invokeinterface	#457,  2; //InterfaceMethod scala/xml/parsing/MarkupParser.putChar:(C)Lscala/collection/mutable/StringBuilder;
   66:	pop
   67:	aload_0
   68:	aload_0
   69:	invokeinterface	#67,  1; //InterfaceMethod scala/xml/parsing/MarkupParser.ch:()C
   74:	invokeinterface	#547,  2; //InterfaceMethod scala/xml/parsing/TokenTests.isPubIDChar:(C)Z
   79:	ifne	122
   82:	aload_0
   83:	new	#38; //class scala/collection/mutable/StringBuilder
   86:	dup
   87:	invokespecial	#478; //Method scala/collection/mutable/StringBuilder."<init>":()V
   90:	ldc_w	#549; //String char '
   93:	invokevirtual	#483; //Method scala/collection/mutable/StringBuilder.append:(Ljava/lang/Object;)Lscala/collection/mutable/StringBuilder;
   96:	aload_0
   97:	invokeinterface	#67,  1; //InterfaceMethod scala/xml/parsing/MarkupParser.ch:()C
   102:	invokestatic	#146; //Method scala/runtime/BoxesRunTime.boxToCharacter:(C)Ljava/lang/Character;
   105:	invokevirtual	#483; //Method scala/collection/mutable/StringBuilder.append:(Ljava/lang/Object;)Lscala/collection/mutable/StringBuilder;
   108:	ldc_w	#551; //String ' is not allowed in public id
   111:	invokevirtual	#483; //Method scala/collection/mutable/StringBuilder.append:(Ljava/lang/Object;)Lscala/collection/mutable/StringBuilder;
   114:	invokevirtual	#486; //Method scala/collection/mutable/StringBuilder.toString:()Ljava/lang/String;
   117:	invokeinterface	#343,  2; //InterfaceMethod scala/xml/parsing/MarkupParser.reportSyntaxError:(Ljava/lang/String;)V
   122:	aload_0
   123:	invokeinterface	#97,  1; //InterfaceMethod scala/xml/parsing/MarkupParser.nextch:()V
   128:	goto	44
   131:	aload_0
   132:	invokeinterface	#97,  1; //InterfaceMethod scala/xml/parsing/MarkupParser.nextch:()V
   137:	aload_0
   138:	invokeinterface	#138,  1; //InterfaceMethod scala/xml/parsing/MarkupParser.cbuf:()Lscala/collection/mutable/StringBuilder;
   143:	invokevirtual	#181; //Method scala/collection/mutable/StringBuilder.toString:()Ljava/lang/String;
   146:	astore_2
   147:	aload_0
   148:	invokeinterface	#138,  1; //InterfaceMethod scala/xml/parsing/MarkupParser.cbuf:()Lscala/collection/mutable/StringBuilder;
   153:	iconst_0
   154:	invokevirtual	#207; //Method scala/collection/mutable/StringBuilder.length_$eq:(I)V
   157:	aload_2
   158:	areturn
  LineNumberTable: 
   line 799: 0
   line 800: 7
   line 801: 29
   line 802: 38
   line 803: 44
   line 804: 54
   line 806: 67
   line 807: 82
   line 808: 122
   line 803: 128
   line 810: 131
   line 811: 137
   line 812: 147
   line 813: 157

  LocalVariableTable: 
   Start  Length  Slot  Name   Signature
   0      159      0    $this       Lscala/xml/parsing/MarkupParser;
   7      151      1    endch       C
   147      11      2    str       Ljava/lang/String;


public static java.lang.String systemLiteral(scala.xml.parsing.MarkupParser);
  Code:
   Stack=2, Locals=3, Args_size=1
   0:	aload_0
   1:	invokeinterface	#67,  1; //InterfaceMethod scala/xml/parsing/MarkupParser.ch:()C
   6:	istore_1
   7:	aload_0
   8:	invokeinterface	#67,  1; //InterfaceMethod scala/xml/parsing/MarkupParser.ch:()C
   13:	ldc	#198; //int 39
   15:	if_icmpeq	38
   18:	aload_0
   19:	invokeinterface	#67,  1; //InterfaceMethod scala/xml/parsing/MarkupParser.ch:()C
   24:	ldc	#201; //int 34
   26:	if_icmpeq	38
   29:	aload_0
   30:	ldc_w	#544; //String quote ' or \" expected
   33:	invokeinterface	#343,  2; //InterfaceMethod scala/xml/parsing/MarkupParser.reportSyntaxError:(Ljava/lang/String;)V
   38:	aload_0
   39:	invokeinterface	#97,  1; //InterfaceMethod scala/xml/parsing/MarkupParser.nextch:()V
   44:	aload_0
   45:	invokeinterface	#67,  1; //InterfaceMethod scala/xml/parsing/MarkupParser.ch:()C
   50:	iload_1
   51:	if_icmpeq	76
   54:	aload_0
   55:	aload_0
   56:	invokeinterface	#67,  1; //InterfaceMethod scala/xml/parsing/MarkupParser.ch:()C
   61:	invokeinterface	#457,  2; //InterfaceMethod scala/xml/parsing/MarkupParser.putChar:(C)Lscala/collection/mutable/StringBuilder;
   66:	pop
   67:	aload_0
   68:	invokeinterface	#97,  1; //InterfaceMethod scala/xml/parsing/MarkupParser.nextch:()V
   73:	goto	44
   76:	aload_0
   77:	invokeinterface	#97,  1; //InterfaceMethod scala/xml/parsing/MarkupParser.nextch:()V
   82:	aload_0
   83:	invokeinterface	#138,  1; //InterfaceMethod scala/xml/parsing/MarkupParser.cbuf:()Lscala/collection/mutable/StringBuilder;
   88:	invokevirtual	#181; //Method scala/collection/mutable/StringBuilder.toString:()Ljava/lang/String;
   91:	astore_2
   92:	aload_0
   93:	invokeinterface	#138,  1; //InterfaceMethod scala/xml/parsing/MarkupParser.cbuf:()Lscala/collection/mutable/StringBuilder;
   98:	iconst_0
   99:	invokevirtual	#207; //Method scala/collection/mutable/StringBuilder.length_$eq:(I)V
   102:	aload_2
   103:	areturn
  LineNumberTable: 
   line 782: 0
   line 783: 7
   line 784: 29
   line 785: 38
   line 786: 44
   line 787: 54
   line 788: 67
   line 786: 73
   line 790: 76
   line 791: 82
   line 792: 92
   line 793: 102

  LocalVariableTable: 
   Start  Length  Slot  Name   Signature
   0      104      0    $this       Lscala/xml/parsing/MarkupParser;
   7      96      1    endch       C
   92      11      2    str       Ljava/lang/String;


public static java.lang.String xText(scala.xml.parsing.MarkupParser);
  Code:
   Stack=2, Locals=4, Args_size=1
   0:	iconst_0
   1:	istore_1
   2:	iload_1
   3:	ifeq	28
   6:	aload_0
   7:	invokeinterface	#138,  1; //InterfaceMethod scala/xml/parsing/MarkupParser.cbuf:()Lscala/collection/mutable/StringBuilder;
   12:	invokevirtual	#181; //Method scala/collection/mutable/StringBuilder.toString:()Ljava/lang/String;
   15:	astore_3
   16:	aload_0
   17:	invokeinterface	#138,  1; //InterfaceMethod scala/xml/parsing/MarkupParser.cbuf:()Lscala/collection/mutable/StringBuilder;
   22:	iconst_0
   23:	invokevirtual	#207; //Method scala/collection/mutable/StringBuilder.length_$eq:(I)V
   26:	aload_3
   27:	areturn
   28:	aload_0
   29:	aload_0
   30:	invokeinterface	#67,  1; //InterfaceMethod scala/xml/parsing/MarkupParser.ch:()C
   35:	invokeinterface	#457,  2; //InterfaceMethod scala/xml/parsing/MarkupParser.putChar:(C)Lscala/collection/mutable/StringBuilder;
   40:	pop
   41:	aload_0
   42:	invokeinterface	#290,  1; //InterfaceMethod scala/xml/parsing/MarkupParser.pos:()I
   47:	istore_2
   48:	aload_0
   49:	invokeinterface	#97,  1; //InterfaceMethod scala/xml/parsing/MarkupParser.nextch:()V
   54:	aload_0
   55:	invokeinterface	#256,  1; //InterfaceMethod scala/xml/parsing/MarkupParser.eof:()Z
   60:	ifne	85
   63:	aload_0
   64:	invokeinterface	#67,  1; //InterfaceMethod scala/xml/parsing/MarkupParser.ch:()C
   69:	ldc	#189; //int 60
   71:	if_icmpeq	85
   74:	aload_0
   75:	invokeinterface	#67,  1; //InterfaceMethod scala/xml/parsing/MarkupParser.ch:()C
   80:	ldc	#195; //int 38
   82:	if_icmpne	89
   85:	iconst_1
   86:	goto	90
   89:	iconst_0
   90:	istore_1
   91:	goto	2
  LineNumberTable: 
   line 759: 0
   line 760: 2
   line 771: 6
   line 772: 16
   line 773: 26
   line 762: 28
   line 763: 41
   line 764: 48
   line 769: 54
   line 760: 91

  LocalVariableTable: 
   Start  Length  Slot  Name   Signature
   0      94      0    $this       Lscala/xml/parsing/MarkupParser;
   2      25      1    exit       Z
   28      66      1    exit       Z
   48      43      2    opos       I
   16      11      3    str       Ljava/lang/String;


public static scala.xml.NodeSeq xProcInstr(scala.xml.parsing.MarkupParser);
  Code:
   Stack=4, Locals=3, Args_size=1
   0:	new	#38; //class scala/collection/mutable/StringBuilder
   3:	dup
   4:	invokespecial	#42; //Method scala/collection/mutable/StringBuilder."<init>":()V
   7:	astore_1
   8:	aload_0
   9:	invokeinterface	#309,  1; //InterfaceMethod scala/xml/parsing/MarkupParser.xName:()Ljava/lang/String;
   14:	astore_2
   15:	aload_0
   16:	aload_0
   17:	invokeinterface	#67,  1; //InterfaceMethod scala/xml/parsing/MarkupParser.ch:()C
   22:	invokeinterface	#73,  2; //InterfaceMethod scala/xml/parsing/TokenTests.isSpace:(C)Z
   27:	ifeq	141
   30:	aload_0
   31:	invokeinterface	#306,  1; //InterfaceMethod scala/xml/parsing/MarkupParser.xSpace:()V
   36:	aload_0
   37:	invokeinterface	#67,  1; //InterfaceMethod scala/xml/parsing/MarkupParser.ch:()C
   42:	ldc_w	#490; //int 63
   45:	if_icmpne	121
   48:	aload_1
   49:	aload_0
   50:	invokeinterface	#67,  1; //InterfaceMethod scala/xml/parsing/MarkupParser.ch:()C
   55:	invokevirtual	#142; //Method scala/collection/mutable/StringBuilder.append:(C)Lscala/collection/mutable/StringBuilder;
   58:	pop
   59:	aload_0
   60:	invokeinterface	#97,  1; //InterfaceMethod scala/xml/parsing/MarkupParser.nextch:()V
   65:	aload_0
   66:	invokeinterface	#67,  1; //InterfaceMethod scala/xml/parsing/MarkupParser.ch:()C
   71:	ldc	#192; //int 62
   73:	if_icmpne	80
   76:	iconst_1
   77:	goto	81
   80:	iconst_0
   81:	ifeq	121
   84:	aload_1
   85:	aload_1
   86:	invokevirtual	#557; //Method scala/collection/mutable/StringBuilder.length:()I
   89:	iconst_1
   90:	isub
   91:	invokevirtual	#207; //Method scala/collection/mutable/StringBuilder.length_$eq:(I)V
   94:	aload_0
   95:	invokeinterface	#97,  1; //InterfaceMethod scala/xml/parsing/MarkupParser.nextch:()V
   100:	aload_0
   101:	invokeinterface	#335,  1; //InterfaceMethod scala/xml/parsing/MarkupParser.scala$xml$parsing$MarkupParser$$handle:()Lscala/xml/parsing/MarkupHandler;
   106:	aload_0
   107:	invokeinterface	#560,  1; //InterfaceMethod scala/xml/parsing/MarkupParser.tmppos:()I
   112:	aload_2
   113:	aload_1
   114:	invokevirtual	#181; //Method scala/collection/mutable/StringBuilder.toString:()Ljava/lang/String;
   117:	invokevirtual	#564; //Method scala/xml/parsing/MarkupHandler.procInstr:(ILjava/lang/String;Ljava/lang/String;)Lscala/xml/NodeSeq;
   120:	areturn
   121:	aload_1
   122:	aload_0
   123:	invokeinterface	#67,  1; //InterfaceMethod scala/xml/parsing/MarkupParser.ch:()C
   128:	invokevirtual	#142; //Method scala/collection/mutable/StringBuilder.append:(C)Lscala/collection/mutable/StringBuilder;
   131:	pop
   132:	aload_0
   133:	invokeinterface	#97,  1; //InterfaceMethod scala/xml/parsing/MarkupParser.nextch:()V
   138:	goto	36
   141:	aload_0
   142:	ldc_w	#490; //int 63
   145:	invokeinterface	#93,  2; //InterfaceMethod scala/xml/parsing/MarkupParser.xToken:(C)V
   150:	aload_0
   151:	ldc	#192; //int 62
   153:	invokeinterface	#93,  2; //InterfaceMethod scala/xml/parsing/MarkupParser.xToken:(C)V
   158:	aload_0
   159:	invokeinterface	#335,  1; //InterfaceMethod scala/xml/parsing/MarkupParser.scala$xml$parsing$MarkupParser$$handle:()Lscala/xml/parsing/MarkupHandler;
   164:	aload_0
   165:	invokeinterface	#560,  1; //InterfaceMethod scala/xml/parsing/MarkupParser.tmppos:()I
   170:	aload_2
   171:	aload_1
   172:	invokevirtual	#181; //Method scala/collection/mutable/StringBuilder.toString:()Ljava/lang/String;
   175:	invokevirtual	#564; //Method scala/xml/parsing/MarkupHandler.procInstr:(ILjava/lang/String;Ljava/lang/String;)Lscala/xml/NodeSeq;
   178:	areturn
  LineNumberTable: 
   line 730: 0
   line 731: 8
   line 732: 15
   line 733: 30
   line 735: 36
   line 736: 84
   line 737: 94
   line 738: 100
   line 740: 121
   line 735: 131
   line 741: 132
   line 734: 138
   line 744: 141
   line 745: 150
   line 746: 158

  LocalVariableTable: 
   Start  Length  Slot  Name   Signature
   0      179      0    $this       Lscala/xml/parsing/MarkupParser;
   8      170      1    sb       Lscala/collection/mutable/StringBuilder;
   15      163      2    n       Ljava/lang/String;


public static void xSpace(scala.xml.parsing.MarkupParser);
  Code:
   Stack=2, Locals=1, Args_size=1
   0:	aload_0
   1:	aload_0
   2:	invokeinterface	#67,  1; //InterfaceMethod scala/xml/parsing/MarkupParser.ch:()C
   7:	invokeinterface	#73,  2; //InterfaceMethod scala/xml/parsing/TokenTests.isSpace:(C)Z
   12:	ifeq	30
   15:	aload_0
   16:	invokeinterface	#97,  1; //InterfaceMethod scala/xml/parsing/MarkupParser.nextch:()V
   21:	aload_0
   22:	invokeinterface	#323,  1; //InterfaceMethod scala/xml/parsing/MarkupParser.xSpaceOpt:()V
   27:	goto	39
   30:	aload_0
   31:	ldc_w	#567; //String whitespace expected
   34:	invokeinterface	#343,  2; //InterfaceMethod scala/xml/parsing/MarkupParser.reportSyntaxError:(Ljava/lang/String;)V
   39:	return
  LineNumberTable: 
   line 722: 0
   line 723: 30
   line 722: 39

  LocalVariableTable: 
   Start  Length  Slot  Name   Signature
   0      40      0    $this       Lscala/xml/parsing/MarkupParser;


public static void xSpaceOpt(scala.xml.parsing.MarkupParser);
  Code:
   Stack=2, Locals=1, Args_size=1
   0:	aload_0
   1:	aload_0
   2:	invokeinterface	#67,  1; //InterfaceMethod scala/xml/parsing/MarkupParser.ch:()C
   7:	invokeinterface	#73,  2; //InterfaceMethod scala/xml/parsing/TokenTests.isSpace:(C)Z
   12:	ifeq	33
   15:	aload_0
   16:	invokeinterface	#256,  1; //InterfaceMethod scala/xml/parsing/MarkupParser.eof:()Z
   21:	ifne	33
   24:	aload_0
   25:	invokeinterface	#97,  1; //InterfaceMethod scala/xml/parsing/MarkupParser.nextch:()V
   30:	goto	0
   33:	return
  LineNumberTable: 
   line 718: 0

  LocalVariableTable: 
   Start  Length  Slot  Name   Signature
   0      34      0    $this       Lscala/xml/parsing/MarkupParser;


public static void xEQ(scala.xml.parsing.MarkupParser);
  Code:
   Stack=2, Locals=1, Args_size=1
   0:	aload_0
   1:	invokeinterface	#323,  1; //InterfaceMethod scala/xml/parsing/MarkupParser.xSpaceOpt:()V
   6:	aload_0
   7:	ldc_w	#569; //int 61
   10:	invokeinterface	#93,  2; //InterfaceMethod scala/xml/parsing/MarkupParser.xToken:(C)V
   15:	aload_0
   16:	invokeinterface	#323,  1; //InterfaceMethod scala/xml/parsing/MarkupParser.xSpaceOpt:()V
   21:	return
  LineNumberTable: 
   line 715: 0

  LocalVariableTable: 
   Start  Length  Slot  Name   Signature
   0      22      0    $this       Lscala/xml/parsing/MarkupParser;


public static java.lang.String xName(scala.xml.parsing.MarkupParser);
  Code:
   Stack=2, Locals=2, Args_size=1
   0:	aload_0
   1:	aload_0
   2:	invokeinterface	#67,  1; //InterfaceMethod scala/xml/parsing/MarkupParser.ch:()C
   7:	invokeinterface	#572,  2; //InterfaceMethod scala/xml/parsing/TokenTests.isNameStart:(C)Z
   12:	ifeq	79
   15:	aload_0
   16:	aload_0
   17:	invokeinterface	#67,  1; //InterfaceMethod scala/xml/parsing/MarkupParser.ch:()C
   22:	invokeinterface	#575,  2; //InterfaceMethod scala/xml/parsing/TokenTests.isNameChar:(C)Z
   27:	ifeq	52
   30:	aload_0
   31:	aload_0
   32:	invokeinterface	#67,  1; //InterfaceMethod scala/xml/parsing/MarkupParser.ch:()C
   37:	invokeinterface	#457,  2; //InterfaceMethod scala/xml/parsing/MarkupParser.putChar:(C)Lscala/collection/mutable/StringBuilder;
   42:	pop
   43:	aload_0
   44:	invokeinterface	#97,  1; //InterfaceMethod scala/xml/parsing/MarkupParser.nextch:()V
   49:	goto	15
   52:	aload_0
   53:	invokeinterface	#138,  1; //InterfaceMethod scala/xml/parsing/MarkupParser.cbuf:()Lscala/collection/mutable/StringBuilder;
   58:	invokevirtual	#181; //Method scala/collection/mutable/StringBuilder.toString:()Ljava/lang/String;
   61:	invokevirtual	#578; //Method java/lang/String.intern:()Ljava/lang/String;
   64:	astore_1
   65:	aload_0
   66:	invokeinterface	#138,  1; //InterfaceMethod scala/xml/parsing/MarkupParser.cbuf:()Lscala/collection/mutable/StringBuilder;
   71:	iconst_0
   72:	invokevirtual	#207; //Method scala/collection/mutable/StringBuilder.length_$eq:(I)V
   75:	aload_1
   76:	goto	91
   79:	aload_0
   80:	ldc_w	#580; //String name expected
   83:	invokeinterface	#343,  2; //InterfaceMethod scala/xml/parsing/MarkupParser.reportSyntaxError:(Ljava/lang/String;)V
   88:	ldc_w	#582; //String 
   91:	areturn
  LineNumberTable: 
   line 700: 0
   line 701: 15
   line 702: 30
   line 703: 43
   line 701: 49
   line 705: 52
   line 706: 65
   line 707: 75
   line 709: 79
   line 710: 88
   line 700: 91

  LocalVariableTable: 
   Start  Length  Slot  Name   Signature
   0      92      0    $this       Lscala/xml/parsing/MarkupParser;
   65      11      1    n       Ljava/lang/String;


public static scala.xml.NodeSeq element1(scala.xml.parsing.MarkupParser, scala.xml.NamespaceBinding);
  Code:
   Stack=7, Locals=27, Args_size=2
   0:	aload_0
   1:	invokeinterface	#290,  1; //InterfaceMethod scala/xml/parsing/MarkupParser.pos:()I
   6:	istore_2
   7:	aload_0
   8:	aload_1
   9:	invokeinterface	#588,  2; //InterfaceMethod scala/xml/parsing/MarkupParser.xTag:(Lscala/xml/NamespaceBinding;)Lscala/Tuple3;
   14:	astore	4
   16:	aload	4
   18:	ifnull	400
   21:	aload	4
   23:	invokevirtual	#593; //Method scala/Tuple3._1:()Ljava/lang/Object;
   26:	checkcast	#429; //class java/lang/String
   29:	astore	5
   31:	aload	4
   33:	invokevirtual	#596; //Method scala/Tuple3._2:()Ljava/lang/Object;
   36:	checkcast	#598; //class scala/xml/MetaData
   39:	astore	6
   41:	aload	4
   43:	invokevirtual	#601; //Method scala/Tuple3._3:()Ljava/lang/Object;
   46:	checkcast	#603; //class scala/xml/NamespaceBinding
   49:	astore	7
   51:	aload	7
   53:	astore	8
   55:	aload	6
   57:	astore	9
   59:	new	#590; //class scala/Tuple3
   62:	dup
   63:	aload	5
   65:	aload	9
   67:	aload	8
   69:	invokespecial	#606; //Method scala/Tuple3."<init>":(Ljava/lang/Object;Ljava/lang/Object;Ljava/lang/Object;)V
   72:	astore_3
   73:	aload_3
   74:	invokevirtual	#593; //Method scala/Tuple3._1:()Ljava/lang/Object;
   77:	checkcast	#429; //class java/lang/String
   80:	astore	10
   82:	aload_3
   83:	invokevirtual	#596; //Method scala/Tuple3._2:()Ljava/lang/Object;
   86:	checkcast	#598; //class scala/xml/MetaData
   89:	astore	11
   91:	aload_3
   92:	invokevirtual	#601; //Method scala/Tuple3._3:()Ljava/lang/Object;
   95:	checkcast	#603; //class scala/xml/NamespaceBinding
   98:	astore	12
   100:	getstatic	#611; //Field scala/xml/Utility$.MODULE$:Lscala/xml/Utility$;
   103:	aload	10
   105:	invokevirtual	#615; //Method scala/xml/Utility$.prefix:(Ljava/lang/String;)Lscala/Option;
   108:	astore	15
   110:	aload	15
   112:	instanceof	#617; //class scala/Some
   115:	ifeq	168
   118:	aload	15
   120:	checkcast	#617; //class scala/Some
   123:	astore	16
   125:	aload	16
   127:	invokevirtual	#620; //Method scala/Some.x:()Ljava/lang/Object;
   130:	checkcast	#429; //class java/lang/String
   133:	astore	17
   135:	aload	17
   137:	astore	18
   139:	new	#622; //class scala/Tuple2
   142:	dup
   143:	aload	18
   145:	aload	10
   147:	aload	18
   149:	invokevirtual	#623; //Method java/lang/String.length:()I
   152:	iconst_1
   153:	iadd
   154:	aload	10
   156:	invokevirtual	#623; //Method java/lang/String.length:()I
   159:	invokevirtual	#627; //Method java/lang/String.substring:(II)Ljava/lang/String;
   162:	invokespecial	#630; //Method scala/Tuple2."<init>":(Ljava/lang/Object;Ljava/lang/Object;)V
   165:	goto	180
   168:	new	#622; //class scala/Tuple2
   171:	dup
   172:	aconst_null
   173:	pop
   174:	aconst_null
   175:	aload	10
   177:	invokespecial	#630; //Method scala/Tuple2."<init>":(Ljava/lang/Object;Ljava/lang/Object;)V
   180:	astore	14
   182:	aload	14
   184:	ifnull	387
   187:	aload	14
   189:	invokevirtual	#631; //Method scala/Tuple2._1:()Ljava/lang/Object;
   192:	checkcast	#429; //class java/lang/String
   195:	astore	19
   197:	aload	14
   199:	invokevirtual	#632; //Method scala/Tuple2._2:()Ljava/lang/Object;
   202:	checkcast	#429; //class java/lang/String
   205:	astore	20
   207:	aload	20
   209:	astore	21
   211:	new	#622; //class scala/Tuple2
   214:	dup
   215:	aload	19
   217:	aload	21
   219:	invokespecial	#630; //Method scala/Tuple2."<init>":(Ljava/lang/Object;Ljava/lang/Object;)V
   222:	astore	13
   224:	aload	13
   226:	invokevirtual	#631; //Method scala/Tuple2._1:()Ljava/lang/Object;
   229:	checkcast	#429; //class java/lang/String
   232:	astore	22
   234:	aload	13
   236:	invokevirtual	#632; //Method scala/Tuple2._2:()Ljava/lang/Object;
   239:	checkcast	#429; //class java/lang/String
   242:	astore	23
   244:	aload_0
   245:	invokeinterface	#67,  1; //InterfaceMethod scala/xml/parsing/MarkupParser.ch:()C
   250:	ldc_w	#633; //int 47
   253:	if_icmpne	300
   256:	aload_0
   257:	ldc_w	#633; //int 47
   260:	invokeinterface	#93,  2; //InterfaceMethod scala/xml/parsing/MarkupParser.xToken:(C)V
   265:	aload_0
   266:	ldc	#192; //int 62
   268:	invokeinterface	#93,  2; //InterfaceMethod scala/xml/parsing/MarkupParser.xToken:(C)V
   273:	aload_0
   274:	invokeinterface	#335,  1; //InterfaceMethod scala/xml/parsing/MarkupParser.scala$xml$parsing$MarkupParser$$handle:()Lscala/xml/parsing/MarkupHandler;
   279:	iload_2
   280:	aload	22
   282:	aload	23
   284:	aload	11
   286:	aload	12
   288:	invokevirtual	#637; //Method scala/xml/parsing/MarkupHandler.elemStart:(ILjava/lang/String;Ljava/lang/String;Lscala/xml/MetaData;Lscala/xml/NamespaceBinding;)V
   291:	getstatic	#642; //Field scala/xml/NodeSeq$.MODULE$:Lscala/xml/NodeSeq$;
   294:	invokevirtual	#645; //Method scala/xml/NodeSeq$.Empty:()Lscala/xml/NodeSeq;
   297:	goto	346
   300:	aload_0
   301:	ldc	#192; //int 62
   303:	invokeinterface	#93,  2; //InterfaceMethod scala/xml/parsing/MarkupParser.xToken:(C)V
   308:	aload_0
   309:	invokeinterface	#335,  1; //InterfaceMethod scala/xml/parsing/MarkupParser.scala$xml$parsing$MarkupParser$$handle:()Lscala/xml/parsing/MarkupHandler;
   314:	iload_2
   315:	aload	22
   317:	aload	23
   319:	aload	11
   321:	aload	12
   323:	invokevirtual	#637; //Method scala/xml/parsing/MarkupHandler.elemStart:(ILjava/lang/String;Ljava/lang/String;Lscala/xml/MetaData;Lscala/xml/NamespaceBinding;)V
   326:	aload_0
   327:	aload	12
   329:	invokeinterface	#649,  2; //InterfaceMethod scala/xml/parsing/MarkupParser.content:(Lscala/xml/NamespaceBinding;)Lscala/xml/NodeSeq;
   334:	astore	25
   336:	aload_0
   337:	aload	10
   339:	invokeinterface	#652,  2; //InterfaceMethod scala/xml/parsing/MarkupParser.xEndTag:(Ljava/lang/String;)V
   344:	aload	25
   346:	astore	24
   348:	aload_0
   349:	invokeinterface	#335,  1; //InterfaceMethod scala/xml/parsing/MarkupParser.scala$xml$parsing$MarkupParser$$handle:()Lscala/xml/parsing/MarkupHandler;
   354:	iload_2
   355:	aload	22
   357:	aload	23
   359:	aload	11
   361:	aload	12
   363:	aload	24
   365:	invokevirtual	#656; //Method scala/xml/parsing/MarkupHandler.elem:(ILjava/lang/String;Ljava/lang/String;Lscala/xml/MetaData;Lscala/xml/NamespaceBinding;Lscala/xml/NodeSeq;)Lscala/xml/NodeSeq;
   368:	astore	26
   370:	aload_0
   371:	invokeinterface	#335,  1; //InterfaceMethod scala/xml/parsing/MarkupParser.scala$xml$parsing$MarkupParser$$handle:()Lscala/xml/parsing/MarkupHandler;
   376:	iload_2
   377:	aload	22
   379:	aload	23
   381:	invokevirtual	#660; //Method scala/xml/parsing/MarkupHandler.elemEnd:(ILjava/lang/String;Ljava/lang/String;)V
   384:	aload	26
   386:	areturn
   387:	new	#360; //class scala/MatchError
   390:	dup
   391:	aload	14
   393:	invokevirtual	#661; //Method scala/Tuple2.toString:()Ljava/lang/String;
   396:	invokespecial	#363; //Method scala/MatchError."<init>":(Ljava/lang/String;)V
   399:	athrow
   400:	new	#360; //class scala/MatchError
   403:	dup
   404:	aload	4
   406:	invokevirtual	#662; //Method scala/Tuple3.toString:()Ljava/lang/String;
   409:	invokespecial	#363; //Method scala/MatchError."<init>":(Ljava/lang/String;)V
   412:	athrow
  LineNumberTable: 
   line 667: 0
   line 668: 7
   line 669: 100
   line 670: 135
   line 671: 168
   line 669: 180
   line 674: 244
   line 675: 256
   line 676: 265
   line 677: 273
   line 678: 291
   line 681: 300
   line 682: 308
   line 683: 326
   line 684: 336
   line 685: 344
   line 673: 346
   line 688: 348
   line 689: 370
   line 690: 384
   line 669: 387
   line 668: 400

  LocalVariableTable: 
   Start  Length  Slot  Name   Signature
   0      413      0    $this       Lscala/xml/parsing/MarkupParser;
   0      413      1    pscope       Lscala/xml/NamespaceBinding;
   7      379      2    pos       I
   387      26      2    pos       I
   16      102      4    temp56       Lscala/Tuple3;
   400      13      4    temp56       Lscala/Tuple3;
   31      41      5    temp57       Ljava/lang/String;
   41      31      6    temp58       Lscala/xml/MetaData;
   51      21      7    temp59       Lscala/xml/NamespaceBinding;
   55      17      8    scope       Lscala/xml/NamespaceBinding;
   59      13      9    aMap       Lscala/xml/MetaData;
   82      304      10    qname       Ljava/lang/String;
   387      13      10    qname       Ljava/lang/String;
   91      295      11    aMap       Lscala/xml/MetaData;
   387      13      11    aMap       Lscala/xml/MetaData;
   100      286      12    scope       Lscala/xml/NamespaceBinding;
   387      13      12    scope       Lscala/xml/NamespaceBinding;
   182      74      14    temp63       Lscala/Tuple2;
   387      13      14    temp63       Lscala/Tuple2;
   110      77      15    temp60       Lscala/Option;
   125      40      16    temp61       Lscala/Some;
   135      30      17    temp62       Ljava/lang/String;
   139      26      18    p       Ljava/lang/String;
   197      25      19    temp64       Ljava/lang/String;
   207      15      20    temp65       Ljava/lang/String;
   211      11      21    local       Ljava/lang/String;
   234      152      22    pre       Ljava/lang/String;
   244      142      23    local       Ljava/lang/String;
   348      38      24    ts       Lscala/xml/NodeSeq;
   336      10      25    tmp       Lscala/xml/NodeSeq;
   370      16      26    res       Lscala/xml/NodeSeq;


public static scala.xml.NodeSeq element(scala.xml.parsing.MarkupParser, scala.xml.NamespaceBinding);
  Code:
   Stack=2, Locals=2, Args_size=2
   0:	aload_0
   1:	ldc	#189; //int 60
   3:	invokeinterface	#93,  2; //InterfaceMethod scala/xml/parsing/MarkupParser.xToken:(C)V
   8:	aload_0
   9:	aload_1
   10:	invokeinterface	#691,  2; //InterfaceMethod scala/xml/parsing/MarkupParser.element1:(Lscala/xml/NamespaceBinding;)Lscala/xml/NodeSeq;
   15:	areturn
  LineNumberTable: 
   line 659: 0
   line 660: 8

  LocalVariableTable: 
   Start  Length  Slot  Name   Signature
   0      16      0    $this       Lscala/xml/parsing/MarkupParser;
   0      16      1    pscope       Lscala/xml/NamespaceBinding;


public static void parseDTD(scala.xml.parsing.MarkupParser);
  Code:
   Stack=5, Locals=3, Args_size=1
   0:	new	#694; //class scala/runtime/ObjectRef
   3:	dup
   4:	aconst_null
   5:	pop
   6:	aconst_null
   7:	invokespecial	#697; //Method scala/runtime/ObjectRef."<init>":(Ljava/lang/Object;)V
   10:	astore_1
   11:	aload_0
   12:	invokeinterface	#701,  1; //InterfaceMethod scala/xml/parsing/MarkupParser.dtd:()Lscala/xml/dtd/DTD;
   17:	ifnull	29
   20:	aload_0
   21:	ldc_w	#703; //String unexpected character (DOCTYPE already defined
   24:	invokeinterface	#343,  2; //InterfaceMethod scala/xml/parsing/MarkupParser.reportSyntaxError:(Ljava/lang/String;)V
   29:	aload_0
   30:	getstatic	#108; //Field scala/Predef$.MODULE$:Lscala/Predef$;
   33:	ldc_w	#705; //String DOCTYPE
   36:	invokevirtual	#112; //Method scala/Predef$.stringWrapper:(Ljava/lang/String;)Lscala/runtime/RichString;
   39:	invokeinterface	#303,  2; //InterfaceMethod scala/xml/parsing/MarkupParser.xToken:(Lscala/collection/Sequence;)V
   44:	aload_0
   45:	invokeinterface	#306,  1; //InterfaceMethod scala/xml/parsing/MarkupParser.xSpace:()V
   50:	aload_0
   51:	invokeinterface	#309,  1; //InterfaceMethod scala/xml/parsing/MarkupParser.xName:()Ljava/lang/String;
   56:	astore_2
   57:	aload_0
   58:	invokeinterface	#306,  1; //InterfaceMethod scala/xml/parsing/MarkupParser.xSpace:()V
   63:	ldc_w	#310; //int 83
   66:	aload_0
   67:	invokeinterface	#67,  1; //InterfaceMethod scala/xml/parsing/MarkupParser.ch:()C
   72:	if_icmpeq	87
   75:	ldc_w	#315; //int 80
   78:	aload_0
   79:	invokeinterface	#67,  1; //InterfaceMethod scala/xml/parsing/MarkupParser.ch:()C
   84:	if_icmpne	103
   87:	aload_1
   88:	aload_0
   89:	invokeinterface	#314,  1; //InterfaceMethod scala/xml/parsing/MarkupParser.externalID:()Lscala/xml/dtd/ExternalID;
   94:	putfield	#708; //Field scala/runtime/ObjectRef.elem:Ljava/lang/Object;
   97:	aload_0
   98:	invokeinterface	#323,  1; //InterfaceMethod scala/xml/parsing/MarkupParser.xSpaceOpt:()V
   103:	aload_1
   104:	getfield	#708; //Field scala/runtime/ObjectRef.elem:Ljava/lang/Object;
   107:	checkcast	#710; //class scala/xml/dtd/ExternalID
   110:	ifnull	175
   113:	aload_0
   114:	checkcast	#18; //class scala/xml/parsing/MarkupHandler
   117:	invokevirtual	#465; //Method scala/xml/parsing/MarkupHandler.isValidating:()Z
   120:	ifeq	175
   123:	aload_0
   124:	aload_1
   125:	getfield	#708; //Field scala/runtime/ObjectRef.elem:Ljava/lang/Object;
   128:	checkcast	#710; //class scala/xml/dtd/ExternalID
   131:	invokevirtual	#712; //Method scala/xml/dtd/ExternalID.systemId:()Ljava/lang/String;
   134:	invokeinterface	#714,  2; //InterfaceMethod scala/xml/parsing/MarkupParser.pushExternal:(Ljava/lang/String;)V
   139:	aload_0
   140:	aload_0
   141:	invokeinterface	#78,  1; //InterfaceMethod scala/xml/parsing/MarkupParser.inpStack:()Lscala/collection/immutable/List;
   146:	invokeinterface	#84,  1; //InterfaceMethod scala/collection/generic/LinearSequenceTemplate.length:()I
   151:	invokeinterface	#36,  2; //InterfaceMethod scala/xml/parsing/MarkupParser.extIndex_$eq:(I)V
   156:	aload_0
   157:	invokeinterface	#716,  1; //InterfaceMethod scala/xml/parsing/MarkupParser.extSubset:()V
   162:	aload_0
   163:	invokeinterface	#718,  1; //InterfaceMethod scala/xml/parsing/MarkupParser.pop:()V
   168:	aload_0
   169:	iconst_m1
   170:	invokeinterface	#36,  2; //InterfaceMethod scala/xml/parsing/MarkupParser.extIndex_$eq:(I)V
   175:	ldc	#89; //int 91
   177:	aload_0
   178:	invokeinterface	#67,  1; //InterfaceMethod scala/xml/parsing/MarkupParser.ch:()C
   183:	if_icmpne	212
   186:	aload_0
   187:	invokeinterface	#97,  1; //InterfaceMethod scala/xml/parsing/MarkupParser.nextch:()V
   192:	aload_0
   193:	invokeinterface	#720,  1; //InterfaceMethod scala/xml/parsing/MarkupParser.intSubset:()V
   198:	aload_0
   199:	ldc	#94; //int 93
   201:	invokeinterface	#93,  2; //InterfaceMethod scala/xml/parsing/MarkupParser.xToken:(C)V
   206:	aload_0
   207:	invokeinterface	#323,  1; //InterfaceMethod scala/xml/parsing/MarkupParser.xSpaceOpt:()V
   212:	aload_0
   213:	ldc	#192; //int 62
   215:	invokeinterface	#93,  2; //InterfaceMethod scala/xml/parsing/MarkupParser.xToken:(C)V
   220:	aload_0
   221:	new	#722; //class scala/xml/parsing/MarkupParser$$anon$2
   224:	dup
   225:	aload_0
   226:	aload_1
   227:	invokespecial	#725; //Method scala/xml/parsing/MarkupParser$$anon$2."<init>":(Lscala/xml/parsing/MarkupParser;Lscala/runtime/ObjectRef;)V
   230:	invokeinterface	#50,  2; //InterfaceMethod scala/xml/parsing/MarkupParser.dtd_$eq:(Lscala/xml/dtd/DTD;)V
   235:	aload_0
   236:	invokeinterface	#729,  1; //InterfaceMethod scala/xml/parsing/MarkupParser.doc:()Lscala/xml/Document;
   241:	ifnull	259
   244:	aload_0
   245:	invokeinterface	#729,  1; //InterfaceMethod scala/xml/parsing/MarkupParser.doc:()Lscala/xml/Document;
   250:	aload_0
   251:	invokeinterface	#701,  1; //InterfaceMethod scala/xml/parsing/MarkupParser.dtd:()Lscala/xml/dtd/DTD;
   256:	invokevirtual	#732; //Method scala/xml/Document.dtd_$eq:(Lscala/xml/dtd/DTD;)V
   259:	aload_0
   260:	invokeinterface	#335,  1; //InterfaceMethod scala/xml/parsing/MarkupParser.scala$xml$parsing$MarkupParser$$handle:()Lscala/xml/parsing/MarkupHandler;
   265:	aload_2
   266:	invokevirtual	#735; //Method scala/xml/parsing/MarkupHandler.endDTD:(Ljava/lang/String;)V
   269:	return
  LineNumberTable: 
   line 582: 0
   line 583: 11
   line 584: 20
   line 585: 29
   line 586: 44
   line 587: 50
   line 588: 57
   line 590: 63
   line 591: 87
   line 592: 97
   line 598: 103
   line 600: 123
   line 603: 139
   line 619: 156
   line 621: 162
   line 623: 168
   line 635: 175
   line 636: 186
   line 639: 192
   line 643: 198
   line 644: 206
   line 646: 212
   line 647: 220
   line 652: 235
   line 653: 244
   line 655: 259

  LocalVariableTable: 
   Start  Length  Slot  Name   Signature
   0      270      0    $this       Lscala/xml/parsing/MarkupParser;
   11      258      1    extID$1       Lscala/runtime/ObjectRef;
   57      212      2    n       Ljava/lang/String;


public static scala.xml.dtd.ExternalID externalID(scala.xml.parsing.MarkupParser);
  Code:
   Stack=4, Locals=5, Args_size=1
   0:	aload_0
   1:	invokeinterface	#67,  1; //InterfaceMethod scala/xml/parsing/MarkupParser.ch:()C
   6:	istore_1
   7:	iload_1
   8:	lookupswitch{ //2
		80: 98;
		83: 51;
		default: 36 }
   36:	new	#360; //class scala/MatchError
   39:	dup
   40:	iload_1
   41:	invokestatic	#146; //Method scala/runtime/BoxesRunTime.boxToCharacter:(C)Ljava/lang/Character;
   44:	invokevirtual	#361; //Method java/lang/Object.toString:()Ljava/lang/String;
   47:	invokespecial	#363; //Method scala/MatchError."<init>":(Ljava/lang/String;)V
   50:	athrow
   51:	aload_0
   52:	invokeinterface	#97,  1; //InterfaceMethod scala/xml/parsing/MarkupParser.nextch:()V
   57:	aload_0
   58:	getstatic	#108; //Field scala/Predef$.MODULE$:Lscala/Predef$;
   61:	ldc_w	#740; //String YSTEM
   64:	invokevirtual	#112; //Method scala/Predef$.stringWrapper:(Ljava/lang/String;)Lscala/runtime/RichString;
   67:	invokeinterface	#303,  2; //InterfaceMethod scala/xml/parsing/MarkupParser.xToken:(Lscala/collection/Sequence;)V
   72:	aload_0
   73:	invokeinterface	#306,  1; //InterfaceMethod scala/xml/parsing/MarkupParser.xSpace:()V
   78:	aload_0
   79:	invokeinterface	#326,  1; //InterfaceMethod scala/xml/parsing/MarkupParser.systemLiteral:()Ljava/lang/String;
   84:	astore	4
   86:	new	#742; //class scala/xml/dtd/SystemID
   89:	dup
   90:	aload	4
   92:	invokespecial	#743; //Method scala/xml/dtd/SystemID."<init>":(Ljava/lang/String;)V
   95:	goto	154
   98:	aload_0
   99:	invokeinterface	#97,  1; //InterfaceMethod scala/xml/parsing/MarkupParser.nextch:()V
   104:	aload_0
   105:	getstatic	#108; //Field scala/Predef$.MODULE$:Lscala/Predef$;
   108:	ldc_w	#317; //String UBLIC
   111:	invokevirtual	#112; //Method scala/Predef$.stringWrapper:(Ljava/lang/String;)Lscala/runtime/RichString;
   114:	invokeinterface	#303,  2; //InterfaceMethod scala/xml/parsing/MarkupParser.xToken:(Lscala/collection/Sequence;)V
   119:	aload_0
   120:	invokeinterface	#306,  1; //InterfaceMethod scala/xml/parsing/MarkupParser.xSpace:()V
   125:	aload_0
   126:	invokeinterface	#320,  1; //InterfaceMethod scala/xml/parsing/MarkupParser.pubidLiteral:()Ljava/lang/String;
   131:	astore_2
   132:	aload_0
   133:	invokeinterface	#306,  1; //InterfaceMethod scala/xml/parsing/MarkupParser.xSpace:()V
   138:	aload_0
   139:	invokeinterface	#326,  1; //InterfaceMethod scala/xml/parsing/MarkupParser.systemLiteral:()Ljava/lang/String;
   144:	astore_3
   145:	new	#328; //class scala/xml/dtd/PublicID
   148:	dup
   149:	aload_2
   150:	aload_3
   151:	invokespecial	#331; //Method scala/xml/dtd/PublicID."<init>":(Ljava/lang/String;Ljava/lang/String;)V
   154:	areturn
  LineNumberTable: 
   line 558: 0
   line 560: 51
   line 561: 57
   line 562: 72
   line 563: 78
   line 564: 86
   line 558: 95
   line 566: 98
   line 567: 119
   line 568: 125
   line 569: 132
   line 570: 138
   line 571: 145
   line 558: 154

  LocalVariableTable: 
   Start  Length  Slot  Name   Signature
   0      155      0    $this       Lscala/xml/parsing/MarkupParser;
   7      148      1    temp55       C
   132      22      2    pubID       Ljava/lang/String;
   145      9      3    sysID       Ljava/lang/String;
   86      9      4    sysID       Ljava/lang/String;


public static scala.xml.NodeSeq content(scala.xml.parsing.MarkupParser, scala.xml.NamespaceBinding);
  Code:
   Stack=7, Locals=14, Args_size=2
   0:	new	#746; //class scala/xml/NodeBuffer
   3:	dup
   4:	invokespecial	#747; //Method scala/xml/NodeBuffer."<init>":()V
   7:	astore_2
   8:	aload_0
   9:	invokeinterface	#256,  1; //InterfaceMethod scala/xml/parsing/MarkupParser.eof:()Z
   14:	istore_3
   15:	iload_3
   16:	ifeq	38
   19:	aload_2
   20:	invokeinterface	#750,  1; //InterfaceMethod scala/collection/generic/TraversableTemplate.toList:()Lscala/collection/immutable/List;
   25:	astore	13
   27:	new	#752; //class scala/xml/parsing/MarkupParser$$anon$1
   30:	dup
   31:	aload_0
   32:	aload	13
   34:	invokespecial	#755; //Method scala/xml/parsing/MarkupParser$$anon$1."<init>":(Lscala/xml/parsing/MarkupParser;Lscala/collection/immutable/List;)V
   37:	areturn
   38:	aload_0
   39:	aload_0
   40:	invokeinterface	#290,  1; //InterfaceMethod scala/xml/parsing/MarkupParser.pos:()I
   45:	invokeinterface	#758,  2; //InterfaceMethod scala/xml/parsing/MarkupParser.tmppos_$eq:(I)V
   50:	aload_0
   51:	invokeinterface	#256,  1; //InterfaceMethod scala/xml/parsing/MarkupParser.eof:()Z
   56:	istore_3
   57:	aload_0
   58:	invokeinterface	#256,  1; //InterfaceMethod scala/xml/parsing/MarkupParser.eof:()Z
   63:	ifeq	72
   66:	getstatic	#403; //Field scala/runtime/BoxedUnit.UNIT:Lscala/runtime/BoxedUnit;
   69:	goto	449
   72:	aload_0
   73:	invokeinterface	#67,  1; //InterfaceMethod scala/xml/parsing/MarkupParser.ch:()C
   78:	istore	4
   80:	iload	4
   82:	lookupswitch{ //2
		38: 170;
		60: 133;
		default: 108 }
   108:	aload_0
   109:	aload_0
   110:	invokeinterface	#560,  1; //InterfaceMethod scala/xml/parsing/MarkupParser.tmppos:()I
   115:	aload_2
   116:	aload_0
   117:	invokeinterface	#760,  1; //InterfaceMethod scala/xml/parsing/MarkupParser.xText:()Ljava/lang/String;
   122:	invokeinterface	#764,  4; //InterfaceMethod scala/xml/parsing/MarkupParser.appendText:(ILscala/xml/NodeBuffer;Ljava/lang/String;)V
   127:	getstatic	#403; //Field scala/runtime/BoxedUnit.UNIT:Lscala/runtime/BoxedUnit;
   130:	goto	449
   133:	aload_0
   134:	invokeinterface	#97,  1; //InterfaceMethod scala/xml/parsing/MarkupParser.nextch:()V
   139:	ldc_w	#633; //int 47
   142:	aload_0
   143:	invokeinterface	#67,  1; //InterfaceMethod scala/xml/parsing/MarkupParser.ch:()C
   148:	if_icmpne	156
   151:	iconst_1
   152:	istore_3
   153:	goto	164
   156:	aload_0
   157:	aload_1
   158:	aload_2
   159:	invokeinterface	#768,  3; //InterfaceMethod scala/xml/parsing/MarkupParser.content1:(Lscala/xml/NamespaceBinding;Lscala/xml/NodeBuffer;)V
   164:	getstatic	#403; //Field scala/runtime/BoxedUnit.UNIT:Lscala/runtime/BoxedUnit;
   167:	goto	449
   170:	aload_0
   171:	invokeinterface	#97,  1; //InterfaceMethod scala/xml/parsing/MarkupParser.nextch:()V
   176:	aload_0
   177:	invokeinterface	#67,  1; //InterfaceMethod scala/xml/parsing/MarkupParser.ch:()C
   182:	istore	5
   184:	iload	5
   186:	invokestatic	#146; //Method scala/runtime/BoxesRunTime.boxToCharacter:(C)Ljava/lang/Character;
   189:	ldc	#147; //int 35
   191:	invokestatic	#151; //Method scala/runtime/BoxesRunTime.boxToInteger:(I)Ljava/lang/Integer;
   194:	invokestatic	#155; //Method scala/runtime/BoxesRunTime.equals:(Ljava/lang/Object;Ljava/lang/Object;)Z
   197:	ifeq	262
   200:	aload_0
   201:	invokeinterface	#97,  1; //InterfaceMethod scala/xml/parsing/MarkupParser.nextch:()V
   206:	aload_0
   207:	invokeinterface	#335,  1; //InterfaceMethod scala/xml/parsing/MarkupParser.scala$xml$parsing$MarkupParser$$handle:()Lscala/xml/parsing/MarkupHandler;
   212:	aload_0
   213:	invokeinterface	#560,  1; //InterfaceMethod scala/xml/parsing/MarkupParser.tmppos:()I
   218:	aload_0
   219:	new	#770; //class scala/xml/parsing/MarkupParser$$anonfun$1
   222:	dup
   223:	aload_0
   224:	invokespecial	#772; //Method scala/xml/parsing/MarkupParser$$anonfun$1."<init>":(Lscala/xml/parsing/MarkupParser;)V
   227:	new	#774; //class scala/xml/parsing/MarkupParser$$anonfun$2
   230:	dup
   231:	aload_0
   232:	invokespecial	#775; //Method scala/xml/parsing/MarkupParser$$anonfun$2."<init>":(Lscala/xml/parsing/MarkupParser;)V
   235:	invokeinterface	#173,  3; //InterfaceMethod scala/xml/parsing/MarkupParser.xCharRef:(Lscala/Function0;Lscala/Function0;)Ljava/lang/String;
   240:	invokevirtual	#779; //Method scala/xml/parsing/MarkupHandler.text:(ILjava/lang/String;)Lscala/xml/NodeSeq;
   243:	astore	6
   245:	aload_0
   246:	ldc	#177; //int 59
   248:	invokeinterface	#93,  2; //InterfaceMethod scala/xml/parsing/MarkupParser.xToken:(C)V
   253:	aload_2
   254:	aload	6
   256:	invokevirtual	#783; //Method scala/xml/NodeBuffer.$amp$plus:(Ljava/lang/Object;)Lscala/xml/NodeBuffer;
   259:	goto	449
   262:	aload_0
   263:	invokeinterface	#309,  1; //InterfaceMethod scala/xml/parsing/MarkupParser.xName:()Ljava/lang/String;
   268:	astore	7
   270:	aload_0
   271:	ldc	#177; //int 59
   273:	invokeinterface	#93,  2; //InterfaceMethod scala/xml/parsing/MarkupParser.xToken:(C)V
   278:	aload	7
   280:	astore	8
   282:	aload	8
   284:	ldc	#183; //String lt
   286:	astore	9
   288:	dup
   289:	ifnonnull	301
   292:	pop
   293:	aload	9
   295:	ifnull	309
   298:	goto	321
   301:	aload	9
   303:	invokevirtual	#188; //Method java/lang/Object.equals:(Ljava/lang/Object;)Z
   306:	ifeq	321
   309:	aload_2
   310:	ldc	#189; //int 60
   312:	invokestatic	#146; //Method scala/runtime/BoxesRunTime.boxToCharacter:(C)Ljava/lang/Character;
   315:	invokevirtual	#783; //Method scala/xml/NodeBuffer.$amp$plus:(Ljava/lang/Object;)Lscala/xml/NodeBuffer;
   318:	goto	449
   321:	aload	8
   323:	ldc	#191; //String gt
   325:	astore	10
   327:	dup
   328:	ifnonnull	340
   331:	pop
   332:	aload	10
   334:	ifnull	348
   337:	goto	360
   340:	aload	10
   342:	invokevirtual	#188; //Method java/lang/Object.equals:(Ljava/lang/Object;)Z
   345:	ifeq	360
   348:	aload_2
   349:	ldc	#192; //int 62
   351:	invokestatic	#146; //Method scala/runtime/BoxesRunTime.boxToCharacter:(C)Ljava/lang/Character;
   354:	invokevirtual	#783; //Method scala/xml/NodeBuffer.$amp$plus:(Ljava/lang/Object;)Lscala/xml/NodeBuffer;
   357:	goto	449
   360:	aload	8
   362:	ldc	#194; //String amp
   364:	astore	11
   366:	dup
   367:	ifnonnull	379
   370:	pop
   371:	aload	11
   373:	ifnull	387
   376:	goto	399
   379:	aload	11
   381:	invokevirtual	#188; //Method java/lang/Object.equals:(Ljava/lang/Object;)Z
   384:	ifeq	399
   387:	aload_2
   388:	ldc	#195; //int 38
   390:	invokestatic	#146; //Method scala/runtime/BoxesRunTime.boxToCharacter:(C)Ljava/lang/Character;
   393:	invokevirtual	#783; //Method scala/xml/NodeBuffer.$amp$plus:(Ljava/lang/Object;)Lscala/xml/NodeBuffer;
   396:	goto	449
   399:	aload	8
   401:	ldc	#200; //String quot
   403:	astore	12
   405:	dup
   406:	ifnonnull	418
   409:	pop
   410:	aload	12
   412:	ifnull	426
   415:	goto	438
   418:	aload	12
   420:	invokevirtual	#188; //Method java/lang/Object.equals:(Ljava/lang/Object;)Z
   423:	ifeq	438
   426:	aload_2
   427:	ldc	#201; //int 34
   429:	invokestatic	#146; //Method scala/runtime/BoxesRunTime.boxToCharacter:(C)Ljava/lang/Character;
   432:	invokevirtual	#783; //Method scala/xml/NodeBuffer.$amp$plus:(Ljava/lang/Object;)Lscala/xml/NodeBuffer;
   435:	goto	449
   438:	aload_0
   439:	aload	7
   441:	invokeinterface	#467,  2; //InterfaceMethod scala/xml/parsing/MarkupParser.push:(Ljava/lang/String;)V
   446:	getstatic	#403; //Field scala/runtime/BoxedUnit.UNIT:Lscala/runtime/BoxedUnit;
   449:	pop
   450:	goto	15
  LineNumberTable: 
   line 487: 0
   line 488: 8
   line 489: 15
   line 547: 19
   line 549: 27
   line 494: 38
   line 495: 50
   line 496: 57
   line 497: 72
   line 542: 108
   line 497: 127
   line 500: 133
   line 503: 139
   line 504: 151
   line 506: 156
   line 497: 164
   line 517: 170
   line 518: 176
   line 520: 200
   line 521: 206
   line 522: 218
   line 521: 240
   line 523: 245
   line 524: 253
   line 526: 262
   line 527: 270
   line 528: 278
   line 529: 309
   line 528: 321
   line 530: 348
   line 528: 360
   line 531: 387
   line 528: 399
   line 532: 426
   line 537: 438
   line 528: 446
   line 496: 449
   line 489: 450

  LocalVariableTable: 
   Start  Length  Slot  Name   Signature
   0      453      0    $this       Lscala/xml/parsing/MarkupParser;
   0      453      1    pscope       Lscala/xml/NamespaceBinding;
   8      29      2    ts       Lscala/xml/NodeBuffer;
   38      415      2    ts       Lscala/xml/NodeBuffer;
   15      22      3    exit       Z
   38      415      3    exit       Z
   80      369      4    temp54       C
   184      265      5    temp53       C
   245      14      6    theChar       Lscala/xml/NodeSeq;
   270      179      7    n       Ljava/lang/String;
   282      167      8    temp48       Ljava/lang/String;
   27      10      13    list$1       Lscala/collection/immutable/List;


public static void content1(scala.xml.parsing.MarkupParser, scala.xml.NamespaceBinding, scala.xml.NodeBuffer);
  Code:
   Stack=3, Locals=4, Args_size=3
   0:	aload_0
   1:	invokeinterface	#67,  1; //InterfaceMethod scala/xml/parsing/MarkupParser.ch:()C
   6:	istore_3
   7:	iload_3
   8:	lookupswitch{ //2
		33: 71;
		63: 51;
		default: 36 }
   36:	aload_2
   37:	aload_0
   38:	aload_1
   39:	invokeinterface	#691,  2; //InterfaceMethod scala/xml/parsing/MarkupParser.element1:(Lscala/xml/NamespaceBinding;)Lscala/xml/NodeSeq;
   44:	invokevirtual	#783; //Method scala/xml/NodeBuffer.$amp$plus:(Ljava/lang/Object;)Lscala/xml/NodeBuffer;
   47:	pop
   48:	goto	134
   51:	aload_0
   52:	invokeinterface	#97,  1; //InterfaceMethod scala/xml/parsing/MarkupParser.nextch:()V
   57:	aload_2
   58:	aload_0
   59:	invokeinterface	#494,  1; //InterfaceMethod scala/xml/parsing/MarkupParser.xProcInstr:()Lscala/xml/NodeSeq;
   64:	invokevirtual	#783; //Method scala/xml/NodeBuffer.$amp$plus:(Ljava/lang/Object;)Lscala/xml/NodeBuffer;
   67:	pop
   68:	goto	134
   71:	aload_0
   72:	invokeinterface	#97,  1; //InterfaceMethod scala/xml/parsing/MarkupParser.nextch:()V
   77:	ldc	#89; //int 91
   79:	aload_0
   80:	invokeinterface	#67,  1; //InterfaceMethod scala/xml/parsing/MarkupParser.ch:()C
   85:	if_icmpne	102
   88:	aload_2
   89:	aload_0
   90:	invokeinterface	#793,  1; //InterfaceMethod scala/xml/parsing/MarkupParser.xCharData:()Lscala/xml/NodeSeq;
   95:	invokevirtual	#783; //Method scala/xml/NodeBuffer.$amp$plus:(Ljava/lang/Object;)Lscala/xml/NodeBuffer;
   98:	pop
   99:	goto	134
   102:	ldc_w	#794; //int 68
   105:	aload_0
   106:	invokeinterface	#67,  1; //InterfaceMethod scala/xml/parsing/MarkupParser.ch:()C
   111:	if_icmpne	123
   114:	aload_0
   115:	invokeinterface	#796,  1; //InterfaceMethod scala/xml/parsing/MarkupParser.parseDTD:()V
   120:	goto	134
   123:	aload_2
   124:	aload_0
   125:	invokeinterface	#525,  1; //InterfaceMethod scala/xml/parsing/MarkupParser.xComment:()Lscala/xml/NodeSeq;
   130:	invokevirtual	#783; //Method scala/xml/NodeBuffer.$amp$plus:(Ljava/lang/Object;)Lscala/xml/NodeBuffer;
   133:	pop
   134:	return
  LineNumberTable: 
   line 469: 0
   line 482: 36
   line 469: 48
   line 479: 51
   line 480: 57
   line 469: 68
   line 471: 71
   line 472: 77
   line 473: 88
   line 474: 102
   line 475: 114
   line 477: 123
   line 469: 134

  LocalVariableTable: 
   Start  Length  Slot  Name   Signature
   0      135      0    $this       Lscala/xml/parsing/MarkupParser;
   0      135      1    pscope       Lscala/xml/NamespaceBinding;
   0      135      2    ts       Lscala/xml/NodeBuffer;
   7      128      3    temp47       C


public static void appendText(scala.xml.parsing.MarkupParser, int, scala.xml.NodeBuffer, java.lang.String);
  Code:
   Stack=6, Locals=4, Args_size=4
   0:	aload_0
   1:	invokeinterface	#801,  1; //InterfaceMethod scala/xml/parsing/MarkupParser.preserveWS:()Z
   6:	ifeq	28
   9:	aload_2
   10:	aload_0
   11:	invokeinterface	#335,  1; //InterfaceMethod scala/xml/parsing/MarkupParser.scala$xml$parsing$MarkupParser$$handle:()Lscala/xml/parsing/MarkupHandler;
   16:	iload_1
   17:	aload_3
   18:	invokevirtual	#779; //Method scala/xml/parsing/MarkupHandler.text:(ILjava/lang/String;)Lscala/xml/NodeSeq;
   21:	invokevirtual	#783; //Method scala/xml/NodeBuffer.$amp$plus:(Ljava/lang/Object;)Lscala/xml/NodeBuffer;
   24:	pop
   25:	goto	53
   28:	getstatic	#806; //Field scala/xml/TextBuffer$.MODULE$:Lscala/xml/TextBuffer$;
   31:	aload_3
   32:	invokevirtual	#810; //Method scala/xml/TextBuffer$.fromString:(Ljava/lang/String;)Lscala/xml/TextBuffer;
   35:	invokevirtual	#816; //Method scala/xml/TextBuffer.toText:()Lscala/collection/Sequence;
   38:	new	#818; //class scala/xml/parsing/MarkupParser$$anonfun$appendText$1
   41:	dup
   42:	aload_0
   43:	iload_1
   44:	aload_2
   45:	invokespecial	#821; //Method scala/xml/parsing/MarkupParser$$anonfun$appendText$1."<init>":(Lscala/xml/parsing/MarkupParser;ILscala/xml/NodeBuffer;)V
   48:	invokeinterface	#825,  2; //InterfaceMethod scala/collection/generic/IterableTemplate.foreach:(Lscala/Function1;)V
   53:	return
  LineNumberTable: 
   line 459: 0
   line 460: 9
   line 462: 28
   line 459: 53

  LocalVariableTable: 
   Start  Length  Slot  Name   Signature
   0      54      0    $this       Lscala/xml/parsing/MarkupParser;
   0      54      1    pos$1       I
   0      54      2    ts$1       Lscala/xml/NodeBuffer;
   0      54      3    txt       Ljava/lang/String;


public static scala.xml.NodeSeq xComment(scala.xml.parsing.MarkupParser);
  Code:
   Stack=3, Locals=2, Args_size=1
   0:	new	#38; //class scala/collection/mutable/StringBuilder
   3:	dup
   4:	invokespecial	#42; //Method scala/collection/mutable/StringBuilder."<init>":()V
   7:	astore_1
   8:	aload_0
   9:	ldc_w	#829; //int 45
   12:	invokeinterface	#93,  2; //InterfaceMethod scala/xml/parsing/MarkupParser.xToken:(C)V
   17:	aload_0
   18:	ldc_w	#829; //int 45
   21:	invokeinterface	#93,  2; //InterfaceMethod scala/xml/parsing/MarkupParser.xToken:(C)V
   26:	aload_0
   27:	invokeinterface	#67,  1; //InterfaceMethod scala/xml/parsing/MarkupParser.ch:()C
   32:	ldc_w	#829; //int 45
   35:	if_icmpne	119
   38:	aload_1
   39:	aload_0
   40:	invokeinterface	#67,  1; //InterfaceMethod scala/xml/parsing/MarkupParser.ch:()C
   45:	invokevirtual	#142; //Method scala/collection/mutable/StringBuilder.append:(C)Lscala/collection/mutable/StringBuilder;
   48:	pop
   49:	aload_0
   50:	invokeinterface	#97,  1; //InterfaceMethod scala/xml/parsing/MarkupParser.nextch:()V
   55:	aload_0
   56:	invokeinterface	#67,  1; //InterfaceMethod scala/xml/parsing/MarkupParser.ch:()C
   61:	ldc_w	#829; //int 45
   64:	if_icmpne	71
   67:	iconst_1
   68:	goto	72
   71:	iconst_0
   72:	ifeq	119
   75:	aload_1
   76:	aload_1
   77:	invokevirtual	#557; //Method scala/collection/mutable/StringBuilder.length:()I
   80:	iconst_1
   81:	isub
   82:	invokevirtual	#207; //Method scala/collection/mutable/StringBuilder.length_$eq:(I)V
   85:	aload_0
   86:	invokeinterface	#97,  1; //InterfaceMethod scala/xml/parsing/MarkupParser.nextch:()V
   91:	aload_0
   92:	ldc	#192; //int 62
   94:	invokeinterface	#93,  2; //InterfaceMethod scala/xml/parsing/MarkupParser.xToken:(C)V
   99:	aload_0
   100:	invokeinterface	#335,  1; //InterfaceMethod scala/xml/parsing/MarkupParser.scala$xml$parsing$MarkupParser$$handle:()Lscala/xml/parsing/MarkupHandler;
   105:	aload_0
   106:	invokeinterface	#290,  1; //InterfaceMethod scala/xml/parsing/MarkupParser.pos:()I
   111:	aload_1
   112:	invokevirtual	#181; //Method scala/collection/mutable/StringBuilder.toString:()Ljava/lang/String;
   115:	invokevirtual	#832; //Method scala/xml/parsing/MarkupHandler.comment:(ILjava/lang/String;)Lscala/xml/NodeSeq;
   118:	areturn
   119:	aload_1
   120:	aload_0
   121:	invokeinterface	#67,  1; //InterfaceMethod scala/xml/parsing/MarkupParser.ch:()C
   126:	invokevirtual	#142; //Method scala/collection/mutable/StringBuilder.append:(C)Lscala/collection/mutable/StringBuilder;
   129:	pop
   130:	aload_0
   131:	invokeinterface	#97,  1; //InterfaceMethod scala/xml/parsing/MarkupParser.nextch:()V
   136:	goto	26
  LineNumberTable: 
   line 442: 0
   line 443: 8
   line 444: 17
   line 446: 26
   line 447: 75
   line 448: 85
   line 449: 91
   line 450: 99
   line 451: 119
   line 446: 129
   line 452: 130
   line 445: 136

  LocalVariableTable: 
   Start  Length  Slot  Name   Signature
   0      139      0    $this       Lscala/xml/parsing/MarkupParser;
   8      131      1    sb       Lscala/collection/mutable/StringBuilder;


public static java.lang.String xCharRef(scala.xml.parsing.MarkupParser, scala.Function0, scala.Function0);
  Code:
   Stack=6, Locals=3, Args_size=3
   0:	getstatic	#611; //Field scala/xml/Utility$.MODULE$:Lscala/xml/Utility$;
   3:	aload_1
   4:	aload_2
   5:	new	#835; //class scala/xml/parsing/MarkupParser$$anonfun$xCharRef$1
   8:	dup
   9:	aload_0
   10:	invokespecial	#836; //Method scala/xml/parsing/MarkupParser$$anonfun$xCharRef$1."<init>":(Lscala/xml/parsing/MarkupParser;)V
   13:	invokevirtual	#840; //Method scala/xml/Utility$.parseCharRef:(Lscala/Function0;Lscala/Function0;Lscala/Function1;)Ljava/lang/String;
   16:	areturn
  LineNumberTable: 
   line 411: 0

  LocalVariableTable: 
   Start  Length  Slot  Name   Signature
   0      17      0    $this       Lscala/xml/parsing/MarkupParser;
   0      17      1    ch       Lscala/Function0;
   0      17      2    nextch       Lscala/Function0;


public static scala.xml.NodeSeq xCharData(scala.xml.parsing.MarkupParser);
  Code:
   Stack=3, Locals=3, Args_size=1
   0:	aload_0
   1:	getstatic	#108; //Field scala/Predef$.MODULE$:Lscala/Predef$;
   4:	ldc_w	#843; //String [CDATA[
   7:	invokevirtual	#112; //Method scala/Predef$.stringWrapper:(Ljava/lang/String;)Lscala/runtime/RichString;
   10:	invokeinterface	#303,  2; //InterfaceMethod scala/xml/parsing/MarkupParser.xToken:(Lscala/collection/Sequence;)V
   15:	aload_0
   16:	invokeinterface	#290,  1; //InterfaceMethod scala/xml/parsing/MarkupParser.pos:()I
   21:	istore_1
   22:	new	#38; //class scala/collection/mutable/StringBuilder
   25:	dup
   26:	invokespecial	#42; //Method scala/collection/mutable/StringBuilder."<init>":()V
   29:	astore_2
   30:	aload_0
   31:	invokeinterface	#67,  1; //InterfaceMethod scala/xml/parsing/MarkupParser.ch:()C
   36:	ldc	#94; //int 93
   38:	if_icmpne	144
   41:	aload_2
   42:	aload_0
   43:	invokeinterface	#67,  1; //InterfaceMethod scala/xml/parsing/MarkupParser.ch:()C
   48:	invokevirtual	#142; //Method scala/collection/mutable/StringBuilder.append:(C)Lscala/collection/mutable/StringBuilder;
   51:	pop
   52:	aload_0
   53:	invokeinterface	#97,  1; //InterfaceMethod scala/xml/parsing/MarkupParser.nextch:()V
   58:	aload_0
   59:	invokeinterface	#67,  1; //InterfaceMethod scala/xml/parsing/MarkupParser.ch:()C
   64:	ldc	#94; //int 93
   66:	if_icmpne	73
   69:	iconst_1
   70:	goto	74
   73:	iconst_0
   74:	ifeq	144
   77:	aload_2
   78:	aload_0
   79:	invokeinterface	#67,  1; //InterfaceMethod scala/xml/parsing/MarkupParser.ch:()C
   84:	invokevirtual	#142; //Method scala/collection/mutable/StringBuilder.append:(C)Lscala/collection/mutable/StringBuilder;
   87:	pop
   88:	aload_0
   89:	invokeinterface	#97,  1; //InterfaceMethod scala/xml/parsing/MarkupParser.nextch:()V
   94:	aload_0
   95:	invokeinterface	#67,  1; //InterfaceMethod scala/xml/parsing/MarkupParser.ch:()C
   100:	ldc	#192; //int 62
   102:	if_icmpne	109
   105:	iconst_1
   106:	goto	110
   109:	iconst_0
   110:	ifeq	144
   113:	aload_2
   114:	aload_2
   115:	invokevirtual	#557; //Method scala/collection/mutable/StringBuilder.length:()I
   118:	iconst_2
   119:	isub
   120:	invokevirtual	#207; //Method scala/collection/mutable/StringBuilder.length_$eq:(I)V
   123:	aload_0
   124:	invokeinterface	#97,  1; //InterfaceMethod scala/xml/parsing/MarkupParser.nextch:()V
   129:	aload_0
   130:	invokeinterface	#335,  1; //InterfaceMethod scala/xml/parsing/MarkupParser.scala$xml$parsing$MarkupParser$$handle:()Lscala/xml/parsing/MarkupHandler;
   135:	iload_1
   136:	aload_2
   137:	invokevirtual	#181; //Method scala/collection/mutable/StringBuilder.toString:()Ljava/lang/String;
   140:	invokevirtual	#779; //Method scala/xml/parsing/MarkupHandler.text:(ILjava/lang/String;)Lscala/xml/NodeSeq;
   143:	areturn
   144:	aload_2
   145:	aload_0
   146:	invokeinterface	#67,  1; //InterfaceMethod scala/xml/parsing/MarkupParser.ch:()C
   151:	invokevirtual	#142; //Method scala/collection/mutable/StringBuilder.append:(C)Lscala/collection/mutable/StringBuilder;
   154:	pop
   155:	aload_0
   156:	invokeinterface	#97,  1; //InterfaceMethod scala/xml/parsing/MarkupParser.nextch:()V
   161:	goto	30
  LineNumberTable: 
   line 389: 0
   line 390: 15
   line 391: 22
   line 393: 30
   line 394: 41
   line 395: 77
   line 396: 113
   line 397: 123
   line 398: 129
   line 399: 144
   line 393: 154
   line 400: 155
   line 392: 161

  LocalVariableTable: 
   Start  Length  Slot  Name   Signature
   0      164      0    $this       Lscala/xml/parsing/MarkupParser;
   22      142      1    pos1       I
   30      134      2    sb       Lscala/collection/mutable/StringBuilder;


public static void xEndTag(scala.xml.parsing.MarkupParser, java.lang.String);
  Code:
   Stack=3, Locals=4, Args_size=2
   0:	aload_0
   1:	ldc_w	#633; //int 47
   4:	invokeinterface	#93,  2; //InterfaceMethod scala/xml/parsing/MarkupParser.xToken:(C)V
   9:	aload_0
   10:	invokeinterface	#309,  1; //InterfaceMethod scala/xml/parsing/MarkupParser.xName:()Ljava/lang/String;
   15:	astore_2
   16:	aload_1
   17:	aload_2
   18:	astore_3
   19:	dup
   20:	ifnonnull	31
   23:	pop
   24:	aload_3
   25:	ifnull	64
   28:	goto	38
   31:	aload_3
   32:	invokevirtual	#188; //Method java/lang/Object.equals:(Ljava/lang/Object;)Z
   35:	ifne	64
   38:	aload_0
   39:	new	#38; //class scala/collection/mutable/StringBuilder
   42:	dup
   43:	invokespecial	#478; //Method scala/collection/mutable/StringBuilder."<init>":()V
   46:	ldc_w	#846; //String expected closing tag of 
   49:	invokevirtual	#483; //Method scala/collection/mutable/StringBuilder.append:(Ljava/lang/Object;)Lscala/collection/mutable/StringBuilder;
   52:	aload_1
   53:	invokevirtual	#483; //Method scala/collection/mutable/StringBuilder.append:(Ljava/lang/Object;)Lscala/collection/mutable/StringBuilder;
   56:	invokevirtual	#486; //Method scala/collection/mutable/StringBuilder.toString:()Ljava/lang/String;
   59:	invokeinterface	#343,  2; //InterfaceMethod scala/xml/parsing/MarkupParser.reportSyntaxError:(Ljava/lang/String;)V
   64:	aload_0
   65:	invokeinterface	#323,  1; //InterfaceMethod scala/xml/parsing/MarkupParser.xSpaceOpt:()V
   70:	aload_0
   71:	ldc	#192; //int 62
   73:	invokeinterface	#93,  2; //InterfaceMethod scala/xml/parsing/MarkupParser.xToken:(C)V
   78:	return
  LineNumberTable: 
   line 376: 0
   line 377: 9
   line 378: 16
   line 379: 38
   line 380: 64
   line 381: 70

  LocalVariableTable: 
   Start  Length  Slot  Name   Signature
   0      79      0    $this       Lscala/xml/parsing/MarkupParser;
   0      79      1    n       Ljava/lang/String;
   16      62      2    m       Ljava/lang/String;


public static scala.Tuple3 xTag(scala.xml.parsing.MarkupParser, scala.xml.NamespaceBinding);
  Code:
   Stack=5, Locals=10, Args_size=2
   0:	aload_0
   1:	invokeinterface	#309,  1; //InterfaceMethod scala/xml/parsing/MarkupParser.xName:()Ljava/lang/String;
   6:	astore_2
   7:	aload_0
   8:	invokeinterface	#323,  1; //InterfaceMethod scala/xml/parsing/MarkupParser.xSpaceOpt:()V
   13:	aload_0
   14:	aload_0
   15:	invokeinterface	#67,  1; //InterfaceMethod scala/xml/parsing/MarkupParser.ch:()C
   20:	invokeinterface	#572,  2; //InterfaceMethod scala/xml/parsing/TokenTests.isNameStart:(C)Z
   25:	ifeq	38
   28:	aload_0
   29:	aload_1
   30:	invokeinterface	#852,  2; //InterfaceMethod scala/xml/parsing/MarkupParser.xAttributes:(Lscala/xml/NamespaceBinding;)Lscala/Tuple2;
   35:	goto	49
   38:	new	#622; //class scala/Tuple2
   41:	dup
   42:	getstatic	#857; //Field scala/xml/Null$.MODULE$:Lscala/xml/Null$;
   45:	aload_1
   46:	invokespecial	#630; //Method scala/Tuple2."<init>":(Ljava/lang/Object;Ljava/lang/Object;)V
   49:	astore	4
   51:	aload	4
   53:	ifnull	159
   56:	aload	4
   58:	invokevirtual	#631; //Method scala/Tuple2._1:()Ljava/lang/Object;
   61:	checkcast	#598; //class scala/xml/MetaData
   64:	astore	5
   66:	aload	4
   68:	invokevirtual	#632; //Method scala/Tuple2._2:()Ljava/lang/Object;
   71:	checkcast	#603; //class scala/xml/NamespaceBinding
   74:	astore	6
   76:	aload	5
   78:	ifnull	146
   81:	aload	6
   83:	ifnull	133
   86:	aload	6
   88:	astore	7
   90:	new	#622; //class scala/Tuple2
   93:	dup
   94:	aload	5
   96:	aload	7
   98:	invokespecial	#630; //Method scala/Tuple2."<init>":(Ljava/lang/Object;Ljava/lang/Object;)V
   101:	astore_3
   102:	aload_3
   103:	invokevirtual	#631; //Method scala/Tuple2._1:()Ljava/lang/Object;
   106:	checkcast	#598; //class scala/xml/MetaData
   109:	astore	8
   111:	aload_3
   112:	invokevirtual	#632; //Method scala/Tuple2._2:()Ljava/lang/Object;
   115:	checkcast	#603; //class scala/xml/NamespaceBinding
   118:	astore	9
   120:	new	#590; //class scala/Tuple3
   123:	dup
   124:	aload_2
   125:	aload	8
   127:	aload	9
   129:	invokespecial	#606; //Method scala/Tuple3."<init>":(Ljava/lang/Object;Ljava/lang/Object;Ljava/lang/Object;)V
   132:	areturn
   133:	new	#360; //class scala/MatchError
   136:	dup
   137:	aload	4
   139:	invokevirtual	#661; //Method scala/Tuple2.toString:()Ljava/lang/String;
   142:	invokespecial	#363; //Method scala/MatchError."<init>":(Ljava/lang/String;)V
   145:	athrow
   146:	new	#360; //class scala/MatchError
   149:	dup
   150:	aload	4
   152:	invokevirtual	#661; //Method scala/Tuple2.toString:()Ljava/lang/String;
   155:	invokespecial	#363; //Method scala/MatchError."<init>":(Ljava/lang/String;)V
   158:	athrow
   159:	new	#360; //class scala/MatchError
   162:	dup
   163:	aload	4
   165:	invokevirtual	#661; //Method scala/Tuple2.toString:()Ljava/lang/String;
   168:	invokespecial	#363; //Method scala/MatchError."<init>":(Ljava/lang/String;)V
   171:	athrow
  LineNumberTable: 
   line 361: 0
   line 363: 7
   line 365: 13
   line 366: 28
   line 368: 38
   line 365: 49
   line 364: 51
   line 365: 56
   line 364: 76
   line 370: 120
   line 365: 133

  LocalVariableTable: 
   Start  Length  Slot  Name   Signature
   0      172      0    $this       Lscala/xml/parsing/MarkupParser;
   0      172      1    pscope       Lscala/xml/NamespaceBinding;
   7      125      2    qname       Ljava/lang/String;
   133      39      2    qname       Ljava/lang/String;
   51      121      4    temp41       Lscala/Tuple2;
   66      35      5    temp42       Lscala/xml/MetaData;
   133      26      5    temp42       Lscala/xml/MetaData;
   76      25      6    temp43       Lscala/xml/NamespaceBinding;
   133      26      6    temp43       Lscala/xml/NamespaceBinding;
   90      11      7    scope       Lscala/xml/NamespaceBinding;
   111      21      8    aMap       Lscala/xml/MetaData;
   120      12      9    scope       Lscala/xml/NamespaceBinding;


public static java.lang.String xEntityValue(scala.xml.parsing.MarkupParser);
  Code:
   Stack=2, Locals=3, Args_size=1
   0:	aload_0
   1:	invokeinterface	#67,  1; //InterfaceMethod scala/xml/parsing/MarkupParser.ch:()C
   6:	istore_1
   7:	aload_0
   8:	invokeinterface	#97,  1; //InterfaceMethod scala/xml/parsing/MarkupParser.nextch:()V
   13:	aload_0
   14:	invokeinterface	#67,  1; //InterfaceMethod scala/xml/parsing/MarkupParser.ch:()C
   19:	iload_1
   20:	if_icmpeq	45
   23:	aload_0
   24:	aload_0
   25:	invokeinterface	#67,  1; //InterfaceMethod scala/xml/parsing/MarkupParser.ch:()C
   30:	invokeinterface	#457,  2; //InterfaceMethod scala/xml/parsing/MarkupParser.putChar:(C)Lscala/collection/mutable/StringBuilder;
   35:	pop
   36:	aload_0
   37:	invokeinterface	#97,  1; //InterfaceMethod scala/xml/parsing/MarkupParser.nextch:()V
   42:	goto	13
   45:	aload_0
   46:	invokeinterface	#97,  1; //InterfaceMethod scala/xml/parsing/MarkupParser.nextch:()V
   51:	aload_0
   52:	invokeinterface	#138,  1; //InterfaceMethod scala/xml/parsing/MarkupParser.cbuf:()Lscala/collection/mutable/StringBuilder;
   57:	invokevirtual	#181; //Method scala/collection/mutable/StringBuilder.toString:()Ljava/lang/String;
   60:	astore_2
   61:	aload_0
   62:	invokeinterface	#138,  1; //InterfaceMethod scala/xml/parsing/MarkupParser.cbuf:()Lscala/collection/mutable/StringBuilder;
   67:	iconst_0
   68:	invokevirtual	#207; //Method scala/collection/mutable/StringBuilder.length_$eq:(I)V
   71:	aload_2
   72:	areturn
  LineNumberTable: 
   line 343: 0
   line 344: 7
   line 345: 13
   line 346: 23
   line 347: 36
   line 345: 42
   line 349: 45
   line 350: 51
   line 351: 61
   line 352: 71

  LocalVariableTable: 
   Start  Length  Slot  Name   Signature
   0      73      0    $this       Lscala/xml/parsing/MarkupParser;
   7      65      1    endch       C
   61      11      2    str       Ljava/lang/String;


public static java.lang.String xAttributeValue(scala.xml.parsing.MarkupParser);
  Code:
   Stack=2, Locals=3, Args_size=1
   0:	aload_0
   1:	invokeinterface	#67,  1; //InterfaceMethod scala/xml/parsing/MarkupParser.ch:()C
   6:	istore_1
   7:	aload_0
   8:	invokeinterface	#97,  1; //InterfaceMethod scala/xml/parsing/MarkupParser.nextch:()V
   13:	aload_0
   14:	invokeinterface	#67,  1; //InterfaceMethod scala/xml/parsing/MarkupParser.ch:()C
   19:	iload_1
   20:	if_icmpeq	65
   23:	ldc	#189; //int 60
   25:	aload_0
   26:	invokeinterface	#67,  1; //InterfaceMethod scala/xml/parsing/MarkupParser.ch:()C
   31:	if_icmpne	43
   34:	aload_0
   35:	ldc_w	#862; //String '<' not allowed in attrib value
   38:	invokeinterface	#343,  2; //InterfaceMethod scala/xml/parsing/MarkupParser.reportSyntaxError:(Ljava/lang/String;)V
   43:	aload_0
   44:	aload_0
   45:	invokeinterface	#67,  1; //InterfaceMethod scala/xml/parsing/MarkupParser.ch:()C
   50:	invokeinterface	#457,  2; //InterfaceMethod scala/xml/parsing/MarkupParser.putChar:(C)Lscala/collection/mutable/StringBuilder;
   55:	pop
   56:	aload_0
   57:	invokeinterface	#97,  1; //InterfaceMethod scala/xml/parsing/MarkupParser.nextch:()V
   62:	goto	13
   65:	aload_0
   66:	invokeinterface	#97,  1; //InterfaceMethod scala/xml/parsing/MarkupParser.nextch:()V
   71:	aload_0
   72:	invokeinterface	#138,  1; //InterfaceMethod scala/xml/parsing/MarkupParser.cbuf:()Lscala/collection/mutable/StringBuilder;
   77:	invokevirtual	#181; //Method scala/collection/mutable/StringBuilder.toString:()Ljava/lang/String;
   80:	astore_2
   81:	aload_0
   82:	invokeinterface	#138,  1; //InterfaceMethod scala/xml/parsing/MarkupParser.cbuf:()Lscala/collection/mutable/StringBuilder;
   87:	iconst_0
   88:	invokevirtual	#207; //Method scala/collection/mutable/StringBuilder.length_$eq:(I)V
   91:	aload_0
   92:	aload_2
   93:	invokeinterface	#865,  2; //InterfaceMethod scala/xml/parsing/MarkupParser.normalizeAttributeValue:(Ljava/lang/String;)Ljava/lang/String;
   98:	areturn
  LineNumberTable: 
   line 322: 0
   line 323: 7
   line 324: 13
   line 325: 23
   line 326: 34
   line 327: 43
   line 328: 56
   line 324: 62
   line 330: 65
   line 331: 71
   line 332: 81
   line 335: 91

  LocalVariableTable: 
   Start  Length  Slot  Name   Signature
   0      99      0    $this       Lscala/xml/parsing/MarkupParser;
   7      91      1    endch       C
   81      17      2    str       Ljava/lang/String;


public static scala.Tuple2 xAttributes(scala.xml.parsing.MarkupParser, scala.xml.NamespaceBinding);
  Code:
   Stack=7, Locals=16, Args_size=2
   0:	aload_1
   1:	astore_2
   2:	getstatic	#857; //Field scala/xml/Null$.MODULE$:Lscala/xml/Null$;
   5:	astore_3
   6:	aload_0
   7:	aload_0
   8:	invokeinterface	#67,  1; //InterfaceMethod scala/xml/parsing/MarkupParser.ch:()C
   13:	invokeinterface	#572,  2; //InterfaceMethod scala/xml/parsing/TokenTests.isNameStart:(C)Z
   18:	ifeq	307
   21:	aload_0
   22:	invokeinterface	#290,  1; //InterfaceMethod scala/xml/parsing/MarkupParser.pos:()I
   27:	istore	4
   29:	aload_0
   30:	invokeinterface	#309,  1; //InterfaceMethod scala/xml/parsing/MarkupParser.xName:()Ljava/lang/String;
   35:	astore	5
   37:	aload_0
   38:	invokeinterface	#868,  1; //InterfaceMethod scala/xml/parsing/MarkupParser.xEQ:()V
   43:	getstatic	#403; //Field scala/runtime/BoxedUnit.UNIT:Lscala/runtime/BoxedUnit;
   46:	astore	6
   48:	aload_0
   49:	invokeinterface	#408,  1; //InterfaceMethod scala/xml/parsing/MarkupParser.xAttributeValue:()Ljava/lang/String;
   54:	astore	7
   56:	getstatic	#611; //Field scala/xml/Utility$.MODULE$:Lscala/xml/Utility$;
   59:	aload	5
   61:	invokevirtual	#615; //Method scala/xml/Utility$.prefix:(Ljava/lang/String;)Lscala/Option;
   64:	astore	8
   66:	aload	8
   68:	instanceof	#617; //class scala/Some
   71:	ifeq	198
   74:	aload	8
   76:	checkcast	#617; //class scala/Some
   79:	astore	9
   81:	aload	9
   83:	invokevirtual	#620; //Method scala/Some.x:()Ljava/lang/Object;
   86:	checkcast	#429; //class java/lang/String
   89:	astore	10
   91:	aload	10
   93:	ldc_w	#870; //String xmlns
   96:	astore	11
   98:	dup
   99:	ifnonnull	111
   102:	pop
   103:	aload	11
   105:	ifnull	119
   108:	goto	150
   111:	aload	11
   113:	invokevirtual	#188; //Method java/lang/Object.equals:(Ljava/lang/Object;)Z
   116:	ifeq	150
   119:	aload	5
   121:	ldc_w	#871; //int 6
   124:	aload	5
   126:	invokevirtual	#623; //Method java/lang/String.length:()I
   129:	invokevirtual	#627; //Method java/lang/String.substring:(II)Ljava/lang/String;
   132:	astore	12
   134:	new	#603; //class scala/xml/NamespaceBinding
   137:	dup
   138:	aload	12
   140:	aload	7
   142:	aload_2
   143:	invokespecial	#874; //Method scala/xml/NamespaceBinding."<init>":(Ljava/lang/String;Ljava/lang/String;Lscala/xml/NamespaceBinding;)V
   146:	astore_2
   147:	goto	263
   150:	aload	10
   152:	astore	13
   154:	aload	5
   156:	aload	13
   158:	invokevirtual	#623; //Method java/lang/String.length:()I
   161:	iconst_1
   162:	iadd
   163:	aload	5
   165:	invokevirtual	#623; //Method java/lang/String.length:()I
   168:	invokevirtual	#627; //Method java/lang/String.substring:(II)Ljava/lang/String;
   171:	astore	14
   173:	new	#876; //class scala/xml/PrefixedAttribute
   176:	dup
   177:	aload	13
   179:	aload	14
   181:	new	#878; //class scala/xml/Text
   184:	dup
   185:	aload	7
   187:	invokespecial	#879; //Method scala/xml/Text."<init>":(Ljava/lang/String;)V
   190:	aload_3
   191:	invokespecial	#882; //Method scala/xml/PrefixedAttribute."<init>":(Ljava/lang/String;Ljava/lang/String;Lscala/collection/Sequence;Lscala/xml/MetaData;)V
   194:	astore_3
   195:	goto	263
   198:	aload	5
   200:	ldc_w	#870; //String xmlns
   203:	astore	15
   205:	dup
   206:	ifnonnull	218
   209:	pop
   210:	aload	15
   212:	ifnull	226
   215:	goto	243
   218:	aload	15
   220:	invokevirtual	#188; //Method java/lang/Object.equals:(Ljava/lang/Object;)Z
   223:	ifeq	243
   226:	new	#603; //class scala/xml/NamespaceBinding
   229:	dup
   230:	aconst_null
   231:	pop
   232:	aconst_null
   233:	aload	7
   235:	aload_2
   236:	invokespecial	#874; //Method scala/xml/NamespaceBinding."<init>":(Ljava/lang/String;Ljava/lang/String;Lscala/xml/NamespaceBinding;)V
   239:	astore_2
   240:	goto	263
   243:	new	#884; //class scala/xml/UnprefixedAttribute
   246:	dup
   247:	aload	5
   249:	new	#878; //class scala/xml/Text
   252:	dup
   253:	aload	7
   255:	invokespecial	#879; //Method scala/xml/Text."<init>":(Ljava/lang/String;)V
   258:	aload_3
   259:	invokespecial	#887; //Method scala/xml/UnprefixedAttribute."<init>":(Ljava/lang/String;Lscala/collection/Sequence;Lscala/xml/MetaData;)V
   262:	astore_3
   263:	aload_0
   264:	invokeinterface	#67,  1; //InterfaceMethod scala/xml/parsing/MarkupParser.ch:()C
   269:	ldc_w	#633; //int 47
   272:	if_icmpeq	6
   275:	aload_0
   276:	invokeinterface	#67,  1; //InterfaceMethod scala/xml/parsing/MarkupParser.ch:()C
   281:	ldc	#192; //int 62
   283:	if_icmpeq	6
   286:	ldc_w	#490; //int 63
   289:	aload_0
   290:	invokeinterface	#67,  1; //InterfaceMethod scala/xml/parsing/MarkupParser.ch:()C
   295:	if_icmpeq	6
   298:	aload_0
   299:	invokeinterface	#306,  1; //InterfaceMethod scala/xml/parsing/MarkupParser.xSpace:()V
   304:	goto	6
   307:	aload_3
   308:	aload_2
   309:	invokevirtual	#891; //Method scala/xml/MetaData.wellformed:(Lscala/xml/NamespaceBinding;)Z
   312:	ifne	324
   315:	aload_0
   316:	ldc_w	#893; //String double attribute
   319:	invokeinterface	#343,  2; //InterfaceMethod scala/xml/parsing/MarkupParser.reportSyntaxError:(Ljava/lang/String;)V
   324:	new	#622; //class scala/Tuple2
   327:	dup
   328:	aload_3
   329:	aload_2
   330:	invokespecial	#630; //Method scala/Tuple2."<init>":(Ljava/lang/Object;Ljava/lang/Object;)V
   333:	areturn
  LineNumberTable: 
   line 282: 0
   line 283: 2
   line 284: 6
   line 285: 21
   line 287: 29
   line 288: 37
   line 289: 48
   line 291: 56
   line 293: 119
   line 294: 134
   line 296: 150
   line 297: 154
   line 298: 173
   line 301: 198
   line 302: 226
   line 304: 243
   line 307: 263
   line 308: 298
   line 311: 307
   line 312: 315
   line 314: 324

  LocalVariableTable: 
   Start  Length  Slot  Name   Signature
   0      334      0    $this       Lscala/xml/parsing/MarkupParser;
   0      334      1    pscope       Lscala/xml/NamespaceBinding;
   2      331      2    scope       Lscala/xml/NamespaceBinding;
   6      327      3    aMap       Lscala/xml/MetaData;
   29      278      4    pos       I
   37      270      5    qname       Ljava/lang/String;
   48      259      6    _       Lscala/runtime/BoxedUnit;
   56      251      7    value       Ljava/lang/String;
   66      209      8    temp37       Lscala/Option;
   81      117      9    temp38       Lscala/Some;
   91      107      10    temp39       Ljava/lang/String;
   134      13      12    prefix       Ljava/lang/String;
   154      41      13    prefix       Ljava/lang/String;
   173      22      14    key       Ljava/lang/String;


public static void xToken(scala.xml.parsing.MarkupParser, scala.collection.Sequence);
  Code:
   Stack=2, Locals=3, Args_size=2
   0:	aload_1
   1:	invokeinterface	#118,  1; //InterfaceMethod scala/collection/generic/IterableTemplate.iterator:()Lscala/collection/Iterator;
   6:	astore_2
   7:	aload_2
   8:	invokeinterface	#124,  1; //InterfaceMethod scala/collection/Iterator.hasNext:()Z
   13:	ifeq	34
   16:	aload_0
   17:	aload_2
   18:	invokeinterface	#128,  1; //InterfaceMethod scala/collection/Iterator.next:()Ljava/lang/Object;
   23:	invokestatic	#134; //Method scala/runtime/BoxesRunTime.unboxToChar:(Ljava/lang/Object;)C
   26:	invokeinterface	#93,  2; //InterfaceMethod scala/xml/parsing/MarkupParser.xToken:(C)V
   31:	goto	7
   34:	return
  LineNumberTable: 
   line 273: 0
   line 274: 7
   line 275: 16
   line 272: 34

  LocalVariableTable: 
   Start  Length  Slot  Name   Signature
   0      35      0    $this       Lscala/xml/parsing/MarkupParser;
   0      35      1    that       Lscala/collection/Sequence;
   7      28      2    it       Lscala/collection/Iterator;


public static void xToken(scala.xml.parsing.MarkupParser, char);
  Code:
   Stack=3, Locals=2, Args_size=2
   0:	aload_0
   1:	invokeinterface	#67,  1; //InterfaceMethod scala/xml/parsing/MarkupParser.ch:()C
   6:	iload_1
   7:	if_icmpne	17
   10:	aload_0
   11:	invokeinterface	#97,  1; //InterfaceMethod scala/xml/parsing/MarkupParser.nextch:()V
   16:	return
   17:	aload_0
   18:	new	#38; //class scala/collection/mutable/StringBuilder
   21:	dup
   22:	invokespecial	#478; //Method scala/collection/mutable/StringBuilder."<init>":()V
   25:	ldc_w	#905; //String '
   28:	invokevirtual	#483; //Method scala/collection/mutable/StringBuilder.append:(Ljava/lang/Object;)Lscala/collection/mutable/StringBuilder;
   31:	iload_1
   32:	invokestatic	#146; //Method scala/runtime/BoxesRunTime.boxToCharacter:(C)Ljava/lang/Character;
   35:	invokevirtual	#483; //Method scala/collection/mutable/StringBuilder.append:(Ljava/lang/Object;)Lscala/collection/mutable/StringBuilder;
   38:	ldc_w	#907; //String ' expected instead of '
   41:	invokevirtual	#483; //Method scala/collection/mutable/StringBuilder.append:(Ljava/lang/Object;)Lscala/collection/mutable/StringBuilder;
   44:	aload_0
   45:	invokeinterface	#67,  1; //InterfaceMethod scala/xml/parsing/MarkupParser.ch:()C
   50:	invokestatic	#146; //Method scala/runtime/BoxesRunTime.boxToCharacter:(C)Ljava/lang/Character;
   53:	invokevirtual	#483; //Method scala/collection/mutable/StringBuilder.append:(Ljava/lang/Object;)Lscala/collection/mutable/StringBuilder;
   56:	ldc_w	#905; //String '
   59:	invokevirtual	#483; //Method scala/collection/mutable/StringBuilder.append:(Ljava/lang/Object;)Lscala/collection/mutable/StringBuilder;
   62:	invokevirtual	#486; //Method scala/collection/mutable/StringBuilder.toString:()Ljava/lang/String;
   65:	invokeinterface	#343,  2; //InterfaceMethod scala/xml/parsing/MarkupParser.reportSyntaxError:(Ljava/lang/String;)V
   70:	getstatic	#108; //Field scala/Predef$.MODULE$:Lscala/Predef$;
   73:	ldc_w	#909; //String FATAL
   76:	invokevirtual	#349; //Method scala/Predef$.error:(Ljava/lang/String;)Lscala/runtime/Nothing$;
   79:	athrow
  LineNumberTable: 
   line 264: 0
   line 265: 10
   line 264: 16
   line 267: 17
   line 268: 70

  LocalVariableTable: 
   Start  Length  Slot  Name   Signature
   0      80      0    $this       Lscala/xml/parsing/MarkupParser;
   0      80      1    that       C


public static void nextch(scala.xml.parsing.MarkupParser);
  Code:
   Stack=2, Locals=2, Args_size=1
   0:	aload_0
   1:	invokeinterface	#241,  1; //InterfaceMethod scala/xml/parsing/MarkupParser.curInput:()Lscala/io/Source;
   6:	invokevirtual	#910; //Method scala/io/Source.hasNext:()Z
   9:	ifeq	45
   12:	aload_0
   13:	aload_0
   14:	invokeinterface	#241,  1; //InterfaceMethod scala/xml/parsing/MarkupParser.curInput:()Lscala/io/Source;
   19:	invokevirtual	#912; //Method scala/io/Source.next:()C
   22:	invokeinterface	#245,  2; //InterfaceMethod scala/xml/parsing/MarkupParser.ch_$eq:(C)V
   27:	aload_0
   28:	aload_0
   29:	invokeinterface	#241,  1; //InterfaceMethod scala/xml/parsing/MarkupParser.curInput:()Lscala/io/Source;
   34:	invokevirtual	#248; //Method scala/io/Source.pos:()I
   37:	invokeinterface	#251,  2; //InterfaceMethod scala/xml/parsing/MarkupParser.pos_$eq:(I)V
   42:	goto	96
   45:	aload_0
   46:	invokeinterface	#78,  1; //InterfaceMethod scala/xml/parsing/MarkupParser.inpStack:()Lscala/collection/immutable/List;
   51:	invokeinterface	#84,  1; //InterfaceMethod scala/collection/generic/LinearSequenceTemplate.length:()I
   56:	istore_1
   57:	iload_1
   58:	aload_0
   59:	invokeinterface	#87,  1; //InterfaceMethod scala/xml/parsing/MarkupParser.extIndex:()I
   64:	if_icmpeq	81
   67:	iload_1
   68:	iconst_0
   69:	if_icmple	81
   72:	aload_0
   73:	invokeinterface	#718,  1; //InterfaceMethod scala/xml/parsing/MarkupParser.pop:()V
   78:	goto	96
   81:	aload_0
   82:	iconst_1
   83:	invokeinterface	#58,  2; //InterfaceMethod scala/xml/parsing/MarkupParser.eof_$eq:(Z)V
   88:	aload_0
   89:	iconst_0
   90:	i2c
   91:	invokeinterface	#245,  2; //InterfaceMethod scala/xml/parsing/MarkupParser.ch_$eq:(C)V
   96:	return
  LineNumberTable: 
   line 243: 0
   line 244: 12
   line 245: 27
   line 247: 45
   line 249: 57
   line 251: 72
   line 253: 81
   line 254: 88
   line 243: 96

  LocalVariableTable: 
   Start  Length  Slot  Name   Signature
   0      97      0    $this       Lscala/xml/parsing/MarkupParser;
   57      39      1    ilen       I


public static scala.collection.mutable.StringBuilder putChar(scala.xml.parsing.MarkupParser, char);
  Code:
   Stack=2, Locals=2, Args_size=2
   0:	aload_0
   1:	invokeinterface	#138,  1; //InterfaceMethod scala/xml/parsing/MarkupParser.cbuf:()Lscala/collection/mutable/StringBuilder;
   6:	iload_1
   7:	invokevirtual	#142; //Method scala/collection/mutable/StringBuilder.append:(C)Lscala/collection/mutable/StringBuilder;
   10:	areturn
  LineNumberTable: 
   line 237: 0

  LocalVariableTable: 
   Start  Length  Slot  Name   Signature
   0      11      0    $this       Lscala/xml/parsing/MarkupParser;
   0      11      1    c       C


public static scala.xml.Document document(scala.xml.parsing.MarkupParser);
  Code:
   Stack=6, Locals=6, Args_size=1
   0:	aload_0
   1:	new	#731; //class scala/xml/Document
   4:	dup
   5:	invokespecial	#918; //Method scala/xml/Document."<init>":()V
   8:	invokeinterface	#54,  2; //InterfaceMethod scala/xml/parsing/MarkupParser.doc_$eq:(Lscala/xml/Document;)V
   13:	aload_0
   14:	aconst_null
   15:	pop
   16:	aconst_null
   17:	invokeinterface	#50,  2; //InterfaceMethod scala/xml/parsing/MarkupParser.dtd_$eq:(Lscala/xml/dtd/DTD;)V
   22:	new	#590; //class scala/Tuple3
   25:	dup
   26:	getstatic	#923; //Field scala/None$.MODULE$:Lscala/None$;
   29:	getstatic	#923; //Field scala/None$.MODULE$:Lscala/None$;
   32:	getstatic	#923; //Field scala/None$.MODULE$:Lscala/None$;
   35:	invokespecial	#606; //Method scala/Tuple3."<init>":(Ljava/lang/Object;Ljava/lang/Object;Ljava/lang/Object;)V
   38:	astore_1
   39:	ldc	#189; //int 60
   41:	aload_0
   42:	invokeinterface	#67,  1; //InterfaceMethod scala/xml/parsing/MarkupParser.ch:()C
   47:	if_icmpeq	63
   50:	aload_0
   51:	ldc_w	#925; //String < expected
   54:	invokeinterface	#343,  2; //InterfaceMethod scala/xml/parsing/MarkupParser.reportSyntaxError:(Ljava/lang/String;)V
   59:	aconst_null
   60:	pop
   61:	aconst_null
   62:	areturn
   63:	aload_0
   64:	invokeinterface	#97,  1; //InterfaceMethod scala/xml/parsing/MarkupParser.nextch:()V
   69:	aconst_null
   70:	pop
   71:	aconst_null
   72:	astore_2
   73:	ldc_w	#490; //int 63
   76:	aload_0
   77:	invokeinterface	#67,  1; //InterfaceMethod scala/xml/parsing/MarkupParser.ch:()C
   82:	if_icmpne	159
   85:	aload_0
   86:	invokeinterface	#97,  1; //InterfaceMethod scala/xml/parsing/MarkupParser.nextch:()V
   91:	aload_0
   92:	invokeinterface	#929,  1; //InterfaceMethod scala/xml/parsing/MarkupParser.prolog:()Lscala/Tuple3;
   97:	astore_1
   98:	aload_0
   99:	invokeinterface	#729,  1; //InterfaceMethod scala/xml/parsing/MarkupParser.doc:()Lscala/xml/Document;
   104:	aload_1
   105:	invokevirtual	#593; //Method scala/Tuple3._1:()Ljava/lang/Object;
   108:	checkcast	#931; //class scala/Option
   111:	invokevirtual	#935; //Method scala/xml/Document.version_$eq:(Lscala/Option;)V
   114:	aload_0
   115:	invokeinterface	#729,  1; //InterfaceMethod scala/xml/parsing/MarkupParser.doc:()Lscala/xml/Document;
   120:	aload_1
   121:	invokevirtual	#596; //Method scala/Tuple3._2:()Ljava/lang/Object;
   124:	checkcast	#931; //class scala/Option
   127:	invokevirtual	#938; //Method scala/xml/Document.encoding_$eq:(Lscala/Option;)V
   130:	aload_0
   131:	invokeinterface	#729,  1; //InterfaceMethod scala/xml/parsing/MarkupParser.doc:()Lscala/xml/Document;
   136:	aload_1
   137:	invokevirtual	#601; //Method scala/Tuple3._3:()Ljava/lang/Object;
   140:	checkcast	#931; //class scala/Option
   143:	invokevirtual	#941; //Method scala/xml/Document.standAlone_$eq:(Lscala/Option;)V
   146:	aload_0
   147:	getstatic	#946; //Field scala/xml/TopScope$.MODULE$:Lscala/xml/TopScope$;
   150:	invokeinterface	#649,  2; //InterfaceMethod scala/xml/parsing/MarkupParser.content:(Lscala/xml/NamespaceBinding;)Lscala/xml/NodeSeq;
   155:	astore_2
   156:	goto	199
   159:	new	#746; //class scala/xml/NodeBuffer
   162:	dup
   163:	invokespecial	#747; //Method scala/xml/NodeBuffer."<init>":()V
   166:	astore_3
   167:	aload_0
   168:	getstatic	#946; //Field scala/xml/TopScope$.MODULE$:Lscala/xml/TopScope$;
   171:	aload_3
   172:	invokeinterface	#768,  3; //InterfaceMethod scala/xml/parsing/MarkupParser.content1:(Lscala/xml/NamespaceBinding;Lscala/xml/NodeBuffer;)V
   177:	aload_3
   178:	aload_0
   179:	getstatic	#946; //Field scala/xml/TopScope$.MODULE$:Lscala/xml/TopScope$;
   182:	invokeinterface	#649,  2; //InterfaceMethod scala/xml/parsing/MarkupParser.content:(Lscala/xml/NamespaceBinding;)Lscala/xml/NodeSeq;
   187:	invokevirtual	#783; //Method scala/xml/NodeBuffer.$amp$plus:(Ljava/lang/Object;)Lscala/xml/NodeBuffer;
   190:	pop
   191:	getstatic	#642; //Field scala/xml/NodeSeq$.MODULE$:Lscala/xml/NodeSeq$;
   194:	aload_3
   195:	invokevirtual	#950; //Method scala/xml/NodeSeq$.fromSeq:(Lscala/collection/Sequence;)Lscala/xml/NodeSeq;
   198:	astore_2
   199:	new	#952; //class scala/runtime/IntRef
   202:	dup
   203:	iconst_0
   204:	invokespecial	#954; //Method scala/runtime/IntRef."<init>":(I)V
   207:	astore	4
   209:	new	#694; //class scala/runtime/ObjectRef
   212:	dup
   213:	aconst_null
   214:	pop
   215:	aconst_null
   216:	invokespecial	#697; //Method scala/runtime/ObjectRef."<init>":(Ljava/lang/Object;)V
   219:	astore	5
   221:	aload_2
   222:	new	#956; //class scala/xml/parsing/MarkupParser$$anonfun$document$1
   225:	dup
   226:	aload_0
   227:	aload	4
   229:	aload	5
   231:	invokespecial	#959; //Method scala/xml/parsing/MarkupParser$$anonfun$document$1."<init>":(Lscala/xml/parsing/MarkupParser;Lscala/runtime/IntRef;Lscala/runtime/ObjectRef;)V
   234:	invokeinterface	#825,  2; //InterfaceMethod scala/collection/generic/IterableTemplate.foreach:(Lscala/Function1;)V
   239:	iconst_1
   240:	aload	4
   242:	getfield	#961; //Field scala/runtime/IntRef.elem:I
   245:	if_icmpeq	269
   248:	aload_0
   249:	ldc_w	#963; //String document must contain exactly one element
   252:	invokeinterface	#343,  2; //InterfaceMethod scala/xml/parsing/MarkupParser.reportSyntaxError:(Ljava/lang/String;)V
   257:	getstatic	#968; //Field scala/Console$.MODULE$:Lscala/Console$;
   260:	aload_2
   261:	invokeinterface	#750,  1; //InterfaceMethod scala/collection/generic/TraversableTemplate.toList:()Lscala/collection/immutable/List;
   266:	invokevirtual	#971; //Method scala/Console$.println:(Ljava/lang/Object;)V
   269:	aload_0
   270:	invokeinterface	#729,  1; //InterfaceMethod scala/xml/parsing/MarkupParser.doc:()Lscala/xml/Document;
   275:	aload_2
   276:	invokevirtual	#974; //Method scala/xml/Document.children_$eq:(Lscala/collection/Sequence;)V
   279:	aload_0
   280:	invokeinterface	#729,  1; //InterfaceMethod scala/xml/parsing/MarkupParser.doc:()Lscala/xml/Document;
   285:	aload	5
   287:	getfield	#708; //Field scala/runtime/ObjectRef.elem:Ljava/lang/Object;
   290:	checkcast	#976; //class scala/xml/Node
   293:	invokevirtual	#980; //Method scala/xml/Document.docElem_$eq:(Lscala/xml/Node;)V
   296:	aload_0
   297:	invokeinterface	#729,  1; //InterfaceMethod scala/xml/parsing/MarkupParser.doc:()Lscala/xml/Document;
   302:	areturn
  LineNumberTable: 
   line 182: 0
   line 184: 13
   line 185: 22
   line 186: 39
   line 187: 50
   line 188: 59
   line 191: 63
   line 192: 69
   line 193: 73
   line 195: 85
   line 196: 91
   line 197: 98
   line 198: 114
   line 199: 130
   line 201: 146
   line 206: 159
   line 207: 167
   line 208: 177
   line 209: 191
   line 212: 199
   line 213: 209
   line 214: 221
   line 226: 239
   line 227: 248
   line 228: 257
   line 231: 269
   line 232: 279
   line 233: 296

  LocalVariableTable: 
   Start  Length  Slot  Name   Signature
   0      303      0    $this       Lscala/xml/parsing/MarkupParser;
   39      263      1    info_prolog       Lscala/Tuple3;
   73      229      2    children       Lscala/xml/NodeSeq;
   167      32      3    ts       Lscala/xml/NodeBuffer;
   209      93      4    elemCount$1       Lscala/runtime/IntRef;
   221      81      5    theNode$1       Lscala/runtime/ObjectRef;


public static scala.Tuple2 textDecl(scala.xml.parsing.MarkupParser);
  Code:
   Stack=4, Locals=11, Args_size=1
   0:	getstatic	#923; //Field scala/None$.MODULE$:Lscala/None$;
   3:	astore_1
   4:	getstatic	#923; //Field scala/None$.MODULE$:Lscala/None$;
   7:	astore_2
   8:	aload_0
   9:	invokeinterface	#990,  1; //InterfaceMethod scala/xml/parsing/MarkupParser.xmlProcInstr:()Lscala/xml/MetaData;
   14:	astore_3
   15:	iconst_0
   16:	istore	4
   18:	aload_3
   19:	ldc_w	#992; //String version
   22:	invokevirtual	#996; //Method scala/xml/MetaData.apply:(Ljava/lang/String;)Lscala/collection/Sequence;
   25:	astore	5
   27:	aload	5
   29:	ifnull	103
   32:	aload	5
   34:	instanceof	#878; //class scala/xml/Text
   37:	ifeq	94
   40:	aload	5
   42:	checkcast	#878; //class scala/xml/Text
   45:	invokevirtual	#999; //Method scala/xml/Text._data:()Ljava/lang/String;
   48:	ldc_w	#1001; //String 1.0
   51:	astore	6
   53:	dup
   54:	ifnonnull	66
   57:	pop
   58:	aload	6
   60:	ifnull	74
   63:	goto	94
   66:	aload	6
   68:	invokevirtual	#188; //Method java/lang/Object.equals:(Ljava/lang/Object;)Z
   71:	ifeq	94
   74:	new	#617; //class scala/Some
   77:	dup
   78:	ldc_w	#1001; //String 1.0
   81:	invokespecial	#1002; //Method scala/Some."<init>":(Ljava/lang/Object;)V
   84:	astore_1
   85:	iload	4
   87:	iconst_1
   88:	iadd
   89:	istore	4
   91:	goto	103
   94:	aload_0
   95:	ldc_w	#1004; //String cannot deal with versions != 1.0
   98:	invokeinterface	#343,  2; //InterfaceMethod scala/xml/parsing/MarkupParser.reportSyntaxError:(Ljava/lang/String;)V
   103:	aload_3
   104:	ldc_w	#1006; //String encoding
   107:	invokevirtual	#996; //Method scala/xml/MetaData.apply:(Ljava/lang/String;)Lscala/collection/Sequence;
   110:	astore	7
   112:	aload	7
   114:	ifnull	212
   117:	aload	7
   119:	instanceof	#878; //class scala/xml/Text
   122:	ifeq	242
   125:	aload	7
   127:	checkcast	#878; //class scala/xml/Text
   130:	astore	8
   132:	aload	8
   134:	invokevirtual	#999; //Method scala/xml/Text._data:()Ljava/lang/String;
   137:	astore	9
   139:	aload	9
   141:	astore	10
   143:	aload_0
   144:	getstatic	#108; //Field scala/Predef$.MODULE$:Lscala/Predef$;
   147:	aload	10
   149:	invokevirtual	#112; //Method scala/Predef$.stringWrapper:(Ljava/lang/String;)Lscala/runtime/RichString;
   152:	invokeinterface	#1010,  2; //InterfaceMethod scala/xml/parsing/TokenTests.isValidIANAEncoding:(Lscala/collection/Sequence;)Z
   157:	ifeq	179
   160:	new	#617; //class scala/Some
   163:	dup
   164:	aload	10
   166:	invokespecial	#1002; //Method scala/Some."<init>":(Ljava/lang/Object;)V
   169:	astore_2
   170:	iload	4
   172:	iconst_1
   173:	iadd
   174:	istore	4
   176:	goto	212
   179:	aload_0
   180:	new	#38; //class scala/collection/mutable/StringBuilder
   183:	dup
   184:	invokespecial	#478; //Method scala/collection/mutable/StringBuilder."<init>":()V
   187:	ldc_w	#1012; //String \"
   190:	invokevirtual	#483; //Method scala/collection/mutable/StringBuilder.append:(Ljava/lang/Object;)Lscala/collection/mutable/StringBuilder;
   193:	aload	10
   195:	invokevirtual	#483; //Method scala/collection/mutable/StringBuilder.append:(Ljava/lang/Object;)Lscala/collection/mutable/StringBuilder;
   198:	ldc_w	#1014; //String \" is not a valid encoding
   201:	invokevirtual	#483; //Method scala/collection/mutable/StringBuilder.append:(Ljava/lang/Object;)Lscala/collection/mutable/StringBuilder;
   204:	invokevirtual	#486; //Method scala/collection/mutable/StringBuilder.toString:()Ljava/lang/String;
   207:	invokeinterface	#343,  2; //InterfaceMethod scala/xml/parsing/MarkupParser.reportSyntaxError:(Ljava/lang/String;)V
   212:	aload_3
   213:	invokevirtual	#1015; //Method scala/xml/MetaData.length:()I
   216:	iload	4
   218:	isub
   219:	iconst_0
   220:	if_icmpeq	232
   223:	aload_0
   224:	ldc_w	#1017; //String VersionInfo EncodingDecl? or '?>' expected!
   227:	invokeinterface	#343,  2; //InterfaceMethod scala/xml/parsing/MarkupParser.reportSyntaxError:(Ljava/lang/String;)V
   232:	new	#622; //class scala/Tuple2
   235:	dup
   236:	aload_1
   237:	aload_2
   238:	invokespecial	#630; //Method scala/Tuple2."<init>":(Ljava/lang/Object;Ljava/lang/Object;)V
   241:	areturn
   242:	new	#360; //class scala/MatchError
   245:	dup
   246:	aload	7
   248:	invokeinterface	#1020,  1; //InterfaceMethod scala/collection/generic/SequenceTemplate.toString:()Ljava/lang/String;
   253:	invokespecial	#363; //Method scala/MatchError."<init>":(Ljava/lang/String;)V
   256:	athrow
  LineNumberTable: 
   line 140: 0
   line 141: 4
   line 143: 8
   line 144: 15
   line 146: 18
   line 148: 74
   line 149: 94
   line 152: 103
   line 154: 139
   line 155: 143
   line 158: 160
   line 159: 170
   line 156: 179
   line 163: 212
   line 164: 223
   line 167: 232
   line 152: 242

  LocalVariableTable: 
   Start  Length  Slot  Name   Signature
   0      257      0    $this       Lscala/xml/parsing/MarkupParser;
   4      237      1    info_ver       Lscala/Option;
   242      15      1    info_ver       Lscala/Option;
   8      233      2    info_enc       Lscala/Option;
   242      15      2    info_enc       Lscala/Option;
   15      226      3    m       Lscala/xml/MetaData;
   242      15      3    m       Lscala/xml/MetaData;
   18      223      4    n       I
   242      15      4    n       I
   27      90      5    temp19       Lscala/collection/Sequence;
   112      111      7    temp24       Lscala/collection/Sequence;
   242      15      7    temp24       Lscala/collection/Sequence;
   132      80      8    temp26       Lscala/xml/Text;
   139      73      9    temp27       Ljava/lang/String;
   143      69      10    enc       Ljava/lang/String;


public static scala.Tuple3 prolog(scala.xml.parsing.MarkupParser);
  Code:
   Stack=5, Locals=17, Args_size=1
   0:	iconst_0
   1:	istore_1
   2:	getstatic	#923; //Field scala/None$.MODULE$:Lscala/None$;
   5:	astore_2
   6:	getstatic	#923; //Field scala/None$.MODULE$:Lscala/None$;
   9:	astore_3
   10:	getstatic	#923; //Field scala/None$.MODULE$:Lscala/None$;
   13:	astore	4
   15:	aload_0
   16:	invokeinterface	#990,  1; //InterfaceMethod scala/xml/parsing/MarkupParser.xmlProcInstr:()Lscala/xml/MetaData;
   21:	astore	5
   23:	aload_0
   24:	invokeinterface	#323,  1; //InterfaceMethod scala/xml/parsing/MarkupParser.xSpaceOpt:()V
   29:	aload	5
   31:	ldc_w	#992; //String version
   34:	invokevirtual	#996; //Method scala/xml/MetaData.apply:(Ljava/lang/String;)Lscala/collection/Sequence;
   37:	astore	6
   39:	aload	6
   41:	ifnull	113
   44:	aload	6
   46:	instanceof	#878; //class scala/xml/Text
   49:	ifeq	104
   52:	aload	6
   54:	checkcast	#878; //class scala/xml/Text
   57:	invokevirtual	#999; //Method scala/xml/Text._data:()Ljava/lang/String;
   60:	ldc_w	#1001; //String 1.0
   63:	astore	7
   65:	dup
   66:	ifnonnull	78
   69:	pop
   70:	aload	7
   72:	ifnull	86
   75:	goto	104
   78:	aload	7
   80:	invokevirtual	#188; //Method java/lang/Object.equals:(Ljava/lang/Object;)Z
   83:	ifeq	104
   86:	new	#617; //class scala/Some
   89:	dup
   90:	ldc_w	#1001; //String 1.0
   93:	invokespecial	#1002; //Method scala/Some."<init>":(Ljava/lang/Object;)V
   96:	astore_2
   97:	iload_1
   98:	iconst_1
   99:	iadd
   100:	istore_1
   101:	goto	113
   104:	aload_0
   105:	ldc_w	#1004; //String cannot deal with versions != 1.0
   108:	invokeinterface	#343,  2; //InterfaceMethod scala/xml/parsing/MarkupParser.reportSyntaxError:(Ljava/lang/String;)V
   113:	aload	5
   115:	ldc_w	#1006; //String encoding
   118:	invokevirtual	#996; //Method scala/xml/MetaData.apply:(Ljava/lang/String;)Lscala/collection/Sequence;
   121:	astore	8
   123:	aload	8
   125:	ifnull	221
   128:	aload	8
   130:	instanceof	#878; //class scala/xml/Text
   133:	ifeq	395
   136:	aload	8
   138:	checkcast	#878; //class scala/xml/Text
   141:	astore	9
   143:	aload	9
   145:	invokevirtual	#999; //Method scala/xml/Text._data:()Ljava/lang/String;
   148:	astore	10
   150:	aload	10
   152:	astore	11
   154:	aload_0
   155:	getstatic	#108; //Field scala/Predef$.MODULE$:Lscala/Predef$;
   158:	aload	11
   160:	invokevirtual	#112; //Method scala/Predef$.stringWrapper:(Ljava/lang/String;)Lscala/runtime/RichString;
   163:	invokeinterface	#1010,  2; //InterfaceMethod scala/xml/parsing/TokenTests.isValidIANAEncoding:(Lscala/collection/Sequence;)Z
   168:	ifeq	188
   171:	new	#617; //class scala/Some
   174:	dup
   175:	aload	11
   177:	invokespecial	#1002; //Method scala/Some."<init>":(Ljava/lang/Object;)V
   180:	astore_3
   181:	iload_1
   182:	iconst_1
   183:	iadd
   184:	istore_1
   185:	goto	221
   188:	aload_0
   189:	new	#38; //class scala/collection/mutable/StringBuilder
   192:	dup
   193:	invokespecial	#478; //Method scala/collection/mutable/StringBuilder."<init>":()V
   196:	ldc_w	#1012; //String \"
   199:	invokevirtual	#483; //Method scala/collection/mutable/StringBuilder.append:(Ljava/lang/Object;)Lscala/collection/mutable/StringBuilder;
   202:	aload	11
   204:	invokevirtual	#483; //Method scala/collection/mutable/StringBuilder.append:(Ljava/lang/Object;)Lscala/collection/mutable/StringBuilder;
   207:	ldc_w	#1014; //String \" is not a valid encoding
   210:	invokevirtual	#483; //Method scala/collection/mutable/StringBuilder.append:(Ljava/lang/Object;)Lscala/collection/mutable/StringBuilder;
   213:	invokevirtual	#486; //Method scala/collection/mutable/StringBuilder.toString:()Ljava/lang/String;
   216:	invokeinterface	#343,  2; //InterfaceMethod scala/xml/parsing/MarkupParser.reportSyntaxError:(Ljava/lang/String;)V
   221:	aload	5
   223:	ldc_w	#1031; //String standalone
   226:	invokevirtual	#996; //Method scala/xml/MetaData.apply:(Ljava/lang/String;)Lscala/collection/Sequence;
   229:	astore	12
   231:	aload	12
   233:	ifnull	363
   236:	aload	12
   238:	instanceof	#878; //class scala/xml/Text
   241:	ifeq	354
   244:	aload	12
   246:	checkcast	#878; //class scala/xml/Text
   249:	astore	13
   251:	aload	13
   253:	invokevirtual	#999; //Method scala/xml/Text._data:()Ljava/lang/String;
   256:	astore	14
   258:	aload	14
   260:	ldc_w	#1033; //String yes
   263:	astore	15
   265:	dup
   266:	ifnonnull	278
   269:	pop
   270:	aload	15
   272:	ifnull	286
   275:	goto	306
   278:	aload	15
   280:	invokevirtual	#188; //Method java/lang/Object.equals:(Ljava/lang/Object;)Z
   283:	ifeq	306
   286:	new	#617; //class scala/Some
   289:	dup
   290:	iconst_1
   291:	invokestatic	#1037; //Method scala/runtime/BoxesRunTime.boxToBoolean:(Z)Ljava/lang/Boolean;
   294:	invokespecial	#1002; //Method scala/Some."<init>":(Ljava/lang/Object;)V
   297:	astore	4
   299:	iload_1
   300:	iconst_1
   301:	iadd
   302:	istore_1
   303:	goto	363
   306:	aload	14
   308:	ldc_w	#1039; //String no
   311:	astore	16
   313:	dup
   314:	ifnonnull	326
   317:	pop
   318:	aload	16
   320:	ifnull	334
   323:	goto	354
   326:	aload	16
   328:	invokevirtual	#188; //Method java/lang/Object.equals:(Ljava/lang/Object;)Z
   331:	ifeq	354
   334:	new	#617; //class scala/Some
   337:	dup
   338:	iconst_0
   339:	invokestatic	#1037; //Method scala/runtime/BoxesRunTime.boxToBoolean:(Z)Ljava/lang/Boolean;
   342:	invokespecial	#1002; //Method scala/Some."<init>":(Ljava/lang/Object;)V
   345:	astore	4
   347:	iload_1
   348:	iconst_1
   349:	iadd
   350:	istore_1
   351:	goto	363
   354:	aload_0
   355:	ldc_w	#1041; //String either 'yes' or 'no' expected
   358:	invokeinterface	#343,  2; //InterfaceMethod scala/xml/parsing/MarkupParser.reportSyntaxError:(Ljava/lang/String;)V
   363:	aload	5
   365:	invokevirtual	#1015; //Method scala/xml/MetaData.length:()I
   368:	iload_1
   369:	isub
   370:	iconst_0
   371:	if_icmpeq	383
   374:	aload_0
   375:	ldc_w	#1043; //String VersionInfo EncodingDecl? SDDecl? or '?>' expected!
   378:	invokeinterface	#343,  2; //InterfaceMethod scala/xml/parsing/MarkupParser.reportSyntaxError:(Ljava/lang/String;)V
   383:	new	#590; //class scala/Tuple3
   386:	dup
   387:	aload_2
   388:	aload_3
   389:	aload	4
   391:	invokespecial	#606; //Method scala/Tuple3."<init>":(Ljava/lang/Object;Ljava/lang/Object;Ljava/lang/Object;)V
   394:	areturn
   395:	new	#360; //class scala/MatchError
   398:	dup
   399:	aload	8
   401:	invokeinterface	#1020,  1; //InterfaceMethod scala/collection/generic/SequenceTemplate.toString:()Ljava/lang/String;
   406:	invokespecial	#363; //Method scala/MatchError."<init>":(Ljava/lang/String;)V
   409:	athrow
  LineNumberTable: 
   line 98: 0
   line 99: 2
   line 100: 6
   line 101: 10
   line 103: 15
   line 105: 23
   line 107: 29
   line 109: 86
   line 110: 104
   line 113: 113
   line 115: 150
   line 116: 154
   line 119: 171
   line 120: 181
   line 117: 188
   line 123: 221
   line 125: 286
   line 123: 306
   line 126: 334
   line 127: 354
   line 130: 363
   line 131: 374
   line 134: 383
   line 113: 395

  LocalVariableTable: 
   Start  Length  Slot  Name   Signature
   0      410      0    $this       Lscala/xml/parsing/MarkupParser;
   2      392      1    n       I
   395      15      1    n       I
   6      388      2    info_ver       Lscala/Option;
   395      15      2    info_ver       Lscala/Option;
   10      384      3    info_enc       Lscala/Option;
   395      15      3    info_enc       Lscala/Option;
   15      379      4    info_stdl       Lscala/Option;
   395      15      4    info_stdl       Lscala/Option;
   23      371      5    m       Lscala/xml/MetaData;
   395      15      5    m       Lscala/xml/MetaData;
   39      89      6    temp4       Lscala/collection/Sequence;
   123      113      8    temp9       Lscala/collection/Sequence;
   395      15      8    temp9       Lscala/collection/Sequence;
   143      78      9    temp11       Lscala/xml/Text;
   150      71      10    temp12       Ljava/lang/String;
   154      67      11    enc       Ljava/lang/String;
   231      143      12    temp13       Lscala/collection/Sequence;
   251      112      13    temp15       Lscala/xml/Text;
   258      105      14    temp16       Ljava/lang/String;


public static scala.xml.MetaData xmlProcInstr(scala.xml.parsing.MarkupParser);
  Code:
   Stack=4, Locals=9, Args_size=1
   0:	aload_0
   1:	getstatic	#108; //Field scala/Predef$.MODULE$:Lscala/Predef$;
   4:	ldc_w	#1054; //String xml
   7:	invokevirtual	#112; //Method scala/Predef$.stringWrapper:(Ljava/lang/String;)Lscala/runtime/RichString;
   10:	invokeinterface	#303,  2; //InterfaceMethod scala/xml/parsing/MarkupParser.xToken:(Lscala/collection/Sequence;)V
   15:	aload_0
   16:	invokeinterface	#306,  1; //InterfaceMethod scala/xml/parsing/MarkupParser.xSpace:()V
   21:	aload_0
   22:	getstatic	#946; //Field scala/xml/TopScope$.MODULE$:Lscala/xml/TopScope$;
   25:	invokeinterface	#852,  2; //InterfaceMethod scala/xml/parsing/MarkupParser.xAttributes:(Lscala/xml/NamespaceBinding;)Lscala/Tuple2;
   30:	astore_2
   31:	aload_2
   32:	ifnull	142
   35:	aload_2
   36:	invokevirtual	#631; //Method scala/Tuple2._1:()Ljava/lang/Object;
   39:	checkcast	#598; //class scala/xml/MetaData
   42:	astore_3
   43:	aload_2
   44:	invokevirtual	#632; //Method scala/Tuple2._2:()Ljava/lang/Object;
   47:	checkcast	#603; //class scala/xml/NamespaceBinding
   50:	astore	4
   52:	aload	4
   54:	astore	5
   56:	new	#622; //class scala/Tuple2
   59:	dup
   60:	aload_3
   61:	aload	5
   63:	invokespecial	#630; //Method scala/Tuple2."<init>":(Ljava/lang/Object;Ljava/lang/Object;)V
   66:	astore_1
   67:	aload_1
   68:	invokevirtual	#631; //Method scala/Tuple2._1:()Ljava/lang/Object;
   71:	checkcast	#598; //class scala/xml/MetaData
   74:	astore	6
   76:	aload_1
   77:	invokevirtual	#632; //Method scala/Tuple2._2:()Ljava/lang/Object;
   80:	checkcast	#603; //class scala/xml/NamespaceBinding
   83:	astore	7
   85:	aload	7
   87:	getstatic	#946; //Field scala/xml/TopScope$.MODULE$:Lscala/xml/TopScope$;
   90:	astore	8
   92:	dup
   93:	ifnonnull	105
   96:	pop
   97:	aload	8
   99:	ifnull	122
   102:	goto	113
   105:	aload	8
   107:	invokevirtual	#188; //Method java/lang/Object.equals:(Ljava/lang/Object;)Z
   110:	ifne	122
   113:	aload_0
   114:	ldc_w	#1056; //String no xmlns definitions here, please.
   117:	invokeinterface	#343,  2; //InterfaceMethod scala/xml/parsing/MarkupParser.reportSyntaxError:(Ljava/lang/String;)V
   122:	aload_0
   123:	ldc_w	#490; //int 63
   126:	invokeinterface	#93,  2; //InterfaceMethod scala/xml/parsing/MarkupParser.xToken:(C)V
   131:	aload_0
   132:	ldc	#192; //int 62
   134:	invokeinterface	#93,  2; //InterfaceMethod scala/xml/parsing/MarkupParser.xToken:(C)V
   139:	aload	6
   141:	areturn
   142:	new	#360; //class scala/MatchError
   145:	dup
   146:	aload_2
   147:	invokevirtual	#661; //Method scala/Tuple2.toString:()Ljava/lang/String;
   150:	invokespecial	#363; //Method scala/MatchError."<init>":(Ljava/lang/String;)V
   153:	athrow
  LineNumberTable: 
   line 82: 0
   line 83: 15
   line 84: 21
   line 85: 85
   line 86: 113
   line 87: 122
   line 88: 131
   line 89: 139
   line 84: 142

  LocalVariableTable: 
   Start  Length  Slot  Name   Signature
   0      154      0    $this       Lscala/xml/parsing/MarkupParser;
   31      65      2    temp1       Lscala/Tuple2;
   142      12      2    temp1       Lscala/Tuple2;
   43      23      3    temp2       Lscala/xml/MetaData;
   52      14      4    temp3       Lscala/xml/NamespaceBinding;
   56      10      5    scp       Lscala/xml/NamespaceBinding;
   76      65      6    md       Lscala/xml/MetaData;
   85      56      7    scp       Lscala/xml/NamespaceBinding;


}

