Compiled from "MarkupParserCommon.scala"
public final class scala.xml.parsing.MarkupParserCommon$$anonfun$xCharRef$3 extends scala.runtime.AbstractFunction0 implements java.io.Serializable
  SourceFile: "MarkupParserCommon.scala"
  Scala: length = 0x
   
  InnerClass: 
   public final $anonfun$xCharRef$3=class scala/xml/parsing/MarkupParserCommon$$anonfun$xCharRef$3 of class scala/xml/parsing/MarkupParserCommon
  minor version: 0
  major version: 49
  Constant pool:
Asciz	SourceFile;
Asciz	MarkupParserCommon.scala;
Asciz	<clinit>;
Asciz	()V;
Asciz	Code;
Asciz	serialVersionUID;
Asciz	J;
Asciz	scala/xml/parsing/MarkupParserCommon$$anonfun$xCharRef$3;
class	scala/xml/parsing/MarkupParserCommon$$anonfun$xCharRef$3
NameAndType	serialVersionUID:J
Field	scala/xml/parsing/MarkupParserCommon$$anonfun$xCharRef$3.serialVersionUID:J
Asciz	c$1;
Asciz	Lscala/runtime/CharRef;;
Asciz	it$1;
Asciz	Lscala/collection/Iterator;;
Asciz	apply;
Asciz	LineNumberTable;
NameAndType	c$1:Lscala/runtime/CharRef;
Field	scala/xml/parsing/MarkupParserCommon$$anonfun$xCharRef$3.c$1:Lscala/runtime/CharRef;
NameAndType	it$1:Lscala/collection/Iterator;
Field	scala/xml/parsing/MarkupParserCommon$$anonfun$xCharRef$3.it$1:Lscala/collection/Iterator;
Asciz	scala/collection/Iterator;
class	scala/collection/Iterator
Asciz	next;
Asciz	()Ljava/lang/Object;;
NameAndType	next:()Ljava/lang/Object;
InterfaceMethod	scala/collection/Iterator.next:()Ljava/lang/Object;
Asciz	scala/runtime/BoxesRunTime;
class	scala/runtime/BoxesRunTime
Asciz	unboxToChar;
Asciz	(Ljava/lang/Object;)C;
NameAndType	unboxToChar:(Ljava/lang/Object;)C
Method	scala/runtime/BoxesRunTime.unboxToChar:(Ljava/lang/Object;)C
Asciz	scala/runtime/CharRef;
class	scala/runtime/CharRef
Asciz	elem;
Asciz	C;
NameAndType	elem:C
Field	scala/runtime/CharRef.elem:C
NameAndType	apply:()V
Method	scala/xml/parsing/MarkupParserCommon$$anonfun$xCharRef$3.apply:()V
Asciz	scala/runtime/BoxedUnit;
class	scala/runtime/BoxedUnit
Asciz	UNIT;
Asciz	Lscala/runtime/BoxedUnit;;
NameAndType	UNIT:Lscala/runtime/BoxedUnit;
Field	scala/runtime/BoxedUnit.UNIT:Lscala/runtime/BoxedUnit;
Asciz	<init>;
Asciz	(Lscala/xml/parsing/MarkupParserCommon;Lscala/collection/Iterator;Lscala/runtime/CharRef;)V;
Asciz	scala/runtime/AbstractFunction0;
class	scala/runtime/AbstractFunction0
NameAndType	"<init>":()V
Method	scala/runtime/AbstractFunction0."<init>":()V
Asciz	this;
Asciz	Lscala/xml/parsing/MarkupParserCommon$$anonfun$xCharRef$3;;
Asciz	$outer;
Asciz	Lscala/xml/parsing/MarkupParserCommon;;
Asciz	LocalVariableTable;
Asciz	Scala;
Asciz	InnerClasses;
Asciz	scala/xml/parsing/MarkupParserCommon;
class	scala/xml/parsing/MarkupParserCommon
Asciz	$anonfun$xCharRef$3;
Asciz	java/io/Serializable;
class	java/io/Serializable

{
public static final long serialVersionUID;
  Signature: J

private final scala.runtime.CharRef c$1;
  Signature: Lscala/runtime/CharRef;

private final scala.collection.Iterator it$1;
  Signature: Lscala/collection/Iterator;

public static {};
  Signature: ()V
  Code:
   Stack=2, Locals=0, Args_size=0
	lconst_0
	putstatic	Field serialVersionUID:J
	return
  Labels:

public final void apply();
  Signature: ()V
  Code:
   Stack=2, Locals=1, Args_size=1
	aload_0
	getfield	Field c$1:Lscala/runtime/CharRef;
	aload_0
	getfield	Field it$1:Lscala/collection/Iterator;
	invokeinterface	InterfaceMethod scala/collection/Iterator.next:()Ljava/lang/Object;
	invokestatic	Method scala/runtime/BoxesRunTime.unboxToChar:(Ljava/lang/Object;)C
	putfield	Field scala/runtime/CharRef.elem:C
	return
  Labels:

public final java.lang.Object apply();
  Signature: ()Ljava/lang/Object;
  Code:
   Stack=1, Locals=1, Args_size=1
	aload_0
	invokevirtual	Method apply:()V
	getstatic	Field scala/runtime/BoxedUnit.UNIT:Lscala/runtime/BoxedUnit;
	areturn
  Labels:

public scala.xml.parsing.MarkupParserCommon$$anonfun$xCharRef$3(scala.xml.parsing.MarkupParserCommon, scala.collection.Iterator, scala.runtime.CharRef);
  Signature: (Lscala/xml/parsing/MarkupParserCommon;Lscala/collection/Iterator;Lscala/runtime/CharRef;)V
  Code:
   Stack=2, Locals=4, Args_size=4
	aload_0
	aload_2
	putfield	Field it$1:Lscala/collection/Iterator;
	aload_0
	aload_3
	putfield	Field c$1:Lscala/runtime/CharRef;
	aload_0
	invokespecial	Method scala/runtime/AbstractFunction0."<init>":()V
	return
  Labels:
  LocalVariableTable: 
   Start  Length  Slot  Name   Signature
   0      15      0    this       Lscala/xml/parsing/MarkupParserCommon$$anonfun$xCharRef$3;
   0      15      1    $outer       Lscala/xml/parsing/MarkupParserCommon;


}

