Compiled from "MarkupParser.scala"
public final class scala.xml.parsing.MarkupParser$$anon$2 extends scala.xml.dtd.DTD
  SourceFile: "MarkupParser.scala"
  Scala: length = 0x
   
  InnerClass: 
   public final #54= #21 of #27; //$anon$2=class scala/xml/parsing/MarkupParser$$anon$2 of class scala/xml/parsing/MarkupParser
  minor version: 0
  major version: 49
  Constant pool:
const #1 = Asciz	SourceFile;
const #2 = Asciz	MarkupParser.scala;
const #3 = Asciz	<init>;
const #4 = Asciz	(Lscala/xml/parsing/MarkupParser;Lscala/runtime/ObjectRef;)V;
const #5 = Asciz	Code;
const #6 = Asciz	LineNumberTable;
const #7 = Asciz	scala/xml/dtd/DTD;
const #8 = class	#7;	//  scala/xml/dtd/DTD
const #9 = Asciz	()V;
const #10 = NameAndType	#3:#9;//  "<init>":()V
const #11 = Method	#8.#10;	//  scala/xml/dtd/DTD."<init>":()V
const #12 = Asciz	scala/runtime/ObjectRef;
const #13 = class	#12;	//  scala/runtime/ObjectRef
const #14 = Asciz	elem;
const #15 = Asciz	Ljava/lang/Object;;
const #16 = NameAndType	#14:#15;//  elem:Ljava/lang/Object;
const #17 = Field	#13.#16;	//  scala/runtime/ObjectRef.elem:Ljava/lang/Object;
const #18 = Asciz	scala/xml/dtd/ExternalID;
const #19 = class	#18;	//  scala/xml/dtd/ExternalID
const #20 = Asciz	scala/xml/parsing/MarkupParser$$anon$2;
const #21 = class	#20;	//  scala/xml/parsing/MarkupParser$$anon$2
const #22 = Asciz	externalID_$eq;
const #23 = Asciz	(Lscala/xml/dtd/ExternalID;)V;
const #24 = NameAndType	#22:#23;//  externalID_$eq:(Lscala/xml/dtd/ExternalID;)V
const #25 = Method	#21.#24;	//  scala/xml/parsing/MarkupParser$$anon$2.externalID_$eq:(Lscala/xml/dtd/ExternalID;)V
const #26 = Asciz	scala/xml/parsing/MarkupParser;
const #27 = class	#26;	//  scala/xml/parsing/MarkupParser
const #28 = Asciz	scala$xml$parsing$MarkupParser$$handle;
const #29 = Asciz	()Lscala/xml/parsing/MarkupHandler;;
const #30 = NameAndType	#28:#29;//  scala$xml$parsing$MarkupParser$$handle:()Lscala/xml/parsing/MarkupHandler;
const #31 = InterfaceMethod	#27.#30;	//  scala/xml/parsing/MarkupParser.scala$xml$parsing$MarkupParser$$handle:()Lscala/xml/parsing/MarkupHandler;
const #32 = Asciz	scala/xml/parsing/MarkupHandler;
const #33 = class	#32;	//  scala/xml/parsing/MarkupHandler
const #34 = Asciz	decls;
const #35 = Asciz	()Lscala/collection/immutable/List;;
const #36 = NameAndType	#34:#35;//  decls:()Lscala/collection/immutable/List;
const #37 = Method	#33.#36;	//  scala/xml/parsing/MarkupHandler.decls:()Lscala/collection/immutable/List;
const #38 = Asciz	scala/collection/immutable/List;
const #39 = class	#38;	//  scala/collection/immutable/List
const #40 = Asciz	reverse;
const #41 = NameAndType	#40:#35;//  reverse:()Lscala/collection/immutable/List;
const #42 = Method	#39.#41;	//  scala/collection/immutable/List.reverse:()Lscala/collection/immutable/List;
const #43 = Asciz	decls_$eq;
const #44 = Asciz	(Lscala/collection/immutable/List;)V;
const #45 = NameAndType	#43:#44;//  decls_$eq:(Lscala/collection/immutable/List;)V
const #46 = Method	#21.#45;	//  scala/xml/parsing/MarkupParser$$anon$2.decls_$eq:(Lscala/collection/immutable/List;)V
const #47 = Asciz	this;
const #48 = Asciz	Lscala/xml/parsing/MarkupParser$$anon$2;;
const #49 = Asciz	$outer;
const #50 = Asciz	Lscala/xml/parsing/MarkupParser;;
const #51 = Asciz	LocalVariableTable;
const #52 = Asciz	Scala;
const #53 = Asciz	InnerClasses;
const #54 = Asciz	$anon$2;

{
public scala.xml.parsing.MarkupParser$$anon$2(scala.xml.parsing.MarkupParser, scala.runtime.ObjectRef);
  Code:
   Stack=2, Locals=3, Args_size=3
   0:	aload_0
   1:	invokespecial	#11; //Method scala/xml/dtd/DTD."<init>":()V
   4:	aload_0
   5:	aload_2
   6:	getfield	#17; //Field scala/runtime/ObjectRef.elem:Ljava/lang/Object;
   9:	checkcast	#19; //class scala/xml/dtd/ExternalID
   12:	invokevirtual	#25; //Method externalID_$eq:(Lscala/xml/dtd/ExternalID;)V
   15:	aload_0
   16:	aload_1
   17:	invokeinterface	#31,  1; //InterfaceMethod scala/xml/parsing/MarkupParser.scala$xml$parsing$MarkupParser$$handle:()Lscala/xml/parsing/MarkupHandler;
   22:	invokevirtual	#37; //Method scala/xml/parsing/MarkupHandler.decls:()Lscala/collection/immutable/List;
   25:	invokevirtual	#42; //Method scala/collection/immutable/List.reverse:()Lscala/collection/immutable/List;
   28:	invokevirtual	#46; //Method decls_$eq:(Lscala/collection/immutable/List;)V
   31:	return
  LineNumberTable: 
   line 647: 0
   line 648: 4
   line 649: 15

  LocalVariableTable: 
   Start  Length  Slot  Name   Signature
   0      32      0    this       Lscala/xml/parsing/MarkupParser$$anon$2;
   0      32      1    $outer       Lscala/xml/parsing/MarkupParser;


}

