Compiled from "MarkupParserCommon.scala"
public abstract class scala.xml.parsing.MarkupParserCommon$class extends java.lang.Object
  SourceFile: "MarkupParserCommon.scala"
  Scala: length = 0x
   
  InnerClass: 
   public abstract ByOne=class scala/collection/immutable/Range$ByOne of class scala/collection/immutable/Range
   public final $anon$1=class scala/collection/immutable/Range$$anon$1 of class scala/collection/immutable/Range
   public final $anonfun$peek$1=class scala/xml/parsing/MarkupParserCommon$$anonfun$peek$1 of class scala/xml/parsing/MarkupParserCommon
   public final $anonfun$xToken$1=class scala/xml/parsing/MarkupParserCommon$$anonfun$xToken$1 of class scala/xml/parsing/MarkupParserCommon
   public final $anonfun$xCharRef$4=class scala/xml/parsing/MarkupParserCommon$$anonfun$xCharRef$4 of class scala/xml/parsing/MarkupParserCommon
   public final $anonfun$xCharRef$3=class scala/xml/parsing/MarkupParserCommon$$anonfun$xCharRef$3 of class scala/xml/parsing/MarkupParserCommon
   public final $anonfun$xCharRef$6=class scala/xml/parsing/MarkupParserCommon$$anonfun$xCharRef$6 of class scala/xml/parsing/MarkupParserCommon
   public final $anonfun$xCharRef$2=class scala/xml/parsing/MarkupParserCommon$$anonfun$xCharRef$2 of class scala/xml/parsing/MarkupParserCommon
   public final $anonfun$xCharRef$1=class scala/xml/parsing/MarkupParserCommon$$anonfun$xCharRef$1 of class scala/xml/parsing/MarkupParserCommon
   public final $anonfun$xCharRef$5=class scala/xml/parsing/MarkupParserCommon$$anonfun$xCharRef$5 of class scala/xml/parsing/MarkupParserCommon
   public final $anonfun$xProcInstr$2=class scala/xml/parsing/MarkupParserCommon$$anonfun$xProcInstr$2 of class scala/xml/parsing/MarkupParserCommon
   public final $anonfun$xProcInstr$1=class scala/xml/parsing/MarkupParserCommon$$anonfun$xProcInstr$1 of class scala/xml/parsing/MarkupParserCommon
  minor version: 0
  major version: 49
  Constant pool:
Asciz	SourceFile;
Asciz	MarkupParserCommon.scala;
Asciz	unreachable;
Asciz	(Lscala/xml/parsing/MarkupParserCommon;)Lscala/runtime/Nothing$;;
Asciz	Code;
Asciz	scala/Predef$;
class	scala/Predef$
Asciz	MODULE$;
Asciz	Lscala/Predef$;;
NameAndType	MODULE$:Lscala/Predef$;
Field	scala/Predef$.MODULE$:Lscala/Predef$;
Asciz	LineNumberTable;
Asciz	Cannot be reached.;
String	Cannot be reached.
Asciz	error;
Asciz	(Ljava/lang/String;)Lscala/runtime/Nothing$;;
NameAndType	error:(Ljava/lang/String;)Lscala/runtime/Nothing$;
Method	scala/Predef$.error:(Ljava/lang/String;)Lscala/runtime/Nothing$;
Asciz	$this;
Asciz	Lscala/xml/parsing/MarkupParserCommon;;
Asciz	LocalVariableTable;
Asciz	xTag;
Asciz	(Lscala/xml/parsing/MarkupParserCommon;Ljava/lang/Object;)Lscala/Tuple2;;
Asciz	scala/xml/parsing/MarkupParserCommon;
class	scala/xml/parsing/MarkupParserCommon
Asciz	xName;
Asciz	()Ljava/lang/String;;
NameAndType	xName:()Ljava/lang/String;
InterfaceMethod	scala/xml/parsing/MarkupParserCommon.xName:()Ljava/lang/String;
Asciz	xSpaceOpt;
Asciz	()V;
NameAndType	xSpaceOpt:()V
InterfaceMethod	scala/xml/parsing/MarkupParserCommon.xSpaceOpt:()V
Asciz	scala/Tuple2;
class	scala/Tuple2
Asciz	mkAttributes;
Asciz	(Ljava/lang/String;Ljava/lang/Object;)Ljava/lang/Object;;
NameAndType	mkAttributes:(Ljava/lang/String;Ljava/lang/Object;)Ljava/lang/Object;
InterfaceMethod	scala/xml/parsing/MarkupParserCommon.mkAttributes:(Ljava/lang/String;Ljava/lang/Object;)Ljava/lang/Object;
Asciz	<init>;
Asciz	(Ljava/lang/Object;Ljava/lang/Object;)V;
NameAndType	"<init>":(Ljava/lang/Object;Ljava/lang/Object;)V
Method	scala/Tuple2."<init>":(Ljava/lang/Object;Ljava/lang/Object;)V
Asciz	pscope;
Asciz	Ljava/lang/Object;;
Asciz	name;
Asciz	Ljava/lang/String;;
Asciz	xProcInstr;
Asciz	(Lscala/xml/parsing/MarkupParserCommon;)Ljava/lang/Object;;
Asciz	scala/xml/parsing/MarkupParserCommon$$anonfun$xProcInstr$1;
class	scala/xml/parsing/MarkupParserCommon$$anonfun$xProcInstr$1
Asciz	(Lscala/xml/parsing/MarkupParserCommon;Ljava/lang/String;)V;
NameAndType	"<init>":(Lscala/xml/parsing/MarkupParserCommon;Ljava/lang/String;)V
Method	scala/xml/parsing/MarkupParserCommon$$anonfun$xProcInstr$1."<init>":(Lscala/xml/parsing/MarkupParserCommon;Ljava/lang/String;)V
Asciz	scala/xml/parsing/MarkupParserCommon$$anonfun$xProcInstr$2;
class	scala/xml/parsing/MarkupParserCommon$$anonfun$xProcInstr$2
Asciz	(Lscala/xml/parsing/MarkupParserCommon;)V;
NameAndType	"<init>":(Lscala/xml/parsing/MarkupParserCommon;)V
Method	scala/xml/parsing/MarkupParserCommon$$anonfun$xProcInstr$2."<init>":(Lscala/xml/parsing/MarkupParserCommon;)V
Asciz	?>;
String	?>
Asciz	xTakeUntil;
Asciz	(Lscala/Function2;Lscala/Function0;Ljava/lang/String;)Ljava/lang/Object;;
NameAndType	xTakeUntil:(Lscala/Function2;Lscala/Function0;Ljava/lang/String;)Ljava/lang/Object;
InterfaceMethod	scala/xml/parsing/MarkupParserCommon.xTakeUntil:(Lscala/Function2;Lscala/Function0;Ljava/lang/String;)Ljava/lang/Object;
Asciz	n$1;
Asciz	xAttributeValue;
Asciz	(Lscala/xml/parsing/MarkupParserCommon;C)Ljava/lang/String;;
Asciz	scala/collection/mutable/StringBuilder;
class	scala/collection/mutable/StringBuilder
NameAndType	"<init>":()V
Method	scala/collection/mutable/StringBuilder."<init>":()V
Asciz	ch;
Asciz	()C;
NameAndType	ch:()C
InterfaceMethod	scala/xml/parsing/MarkupParserCommon.ch:()C
int	60;
Asciz	'<' not allowed in attrib value;
String	'<' not allowed in attrib value
Asciz	;
String	
Asciz	errorAndResult;
NameAndType	errorAndResult:(Ljava/lang/String;Ljava/lang/Object;)Ljava/lang/Object;
InterfaceMethod	scala/xml/parsing/MarkupParserCommon.errorAndResult:(Ljava/lang/String;Ljava/lang/Object;)Ljava/lang/Object;
Asciz	java/lang/String;
class	java/lang/String
int	26;
Asciz	truncatedError;
NameAndType	truncatedError:(Ljava/lang/String;)Lscala/runtime/Nothing$;
InterfaceMethod	scala/xml/parsing/MarkupParserCommon.truncatedError:(Ljava/lang/String;)Lscala/runtime/Nothing$;
Asciz	ch_returning_nextch;
NameAndType	ch_returning_nextch:()C
InterfaceMethod	scala/xml/parsing/MarkupParserCommon.ch_returning_nextch:()C
Asciz	append;
Asciz	(C)Lscala/collection/mutable/StringBuilder;;
NameAndType	append:(C)Lscala/collection/mutable/StringBuilder;
Method	scala/collection/mutable/StringBuilder.append:(C)Lscala/collection/mutable/StringBuilder;
Asciz	toString;
NameAndType	toString:()Ljava/lang/String;
Method	scala/collection/mutable/StringBuilder.toString:()Ljava/lang/String;
Asciz	endCh;
Asciz	C;
Asciz	buf;
Asciz	Lscala/collection/mutable/StringBuilder;;
Asciz	(Lscala/xml/parsing/MarkupParserCommon;)Ljava/lang/String;;
Asciz	(C)Ljava/lang/String;;
NameAndType	xAttributeValue:(C)Ljava/lang/String;
InterfaceMethod	scala/xml/parsing/MarkupParserCommon.xAttributeValue:(C)Ljava/lang/String;
Asciz	scala/xml/parsing/MarkupParserCommon$class;
class	scala/xml/parsing/MarkupParserCommon$class
Asciz	normalizeAttributeValue;
Asciz	(Lscala/xml/parsing/MarkupParserCommon;Ljava/lang/String;)Ljava/lang/String;;
NameAndType	normalizeAttributeValue:(Lscala/xml/parsing/MarkupParserCommon;Ljava/lang/String;)Ljava/lang/String;
Method	scala/xml/parsing/MarkupParserCommon$class.normalizeAttributeValue:(Lscala/xml/parsing/MarkupParserCommon;Ljava/lang/String;)Ljava/lang/String;
Asciz	str;
Asciz	takeUntilChar;
Asciz	(Lscala/xml/parsing/MarkupParserCommon;Lscala/collection/Iterator;C)Ljava/lang/String;;
Asciz	scala/collection/Iterator;
class	scala/collection/Iterator
Asciz	hasNext;
Asciz	()Z;
NameAndType	hasNext:()Z
InterfaceMethod	scala/collection/Iterator.hasNext:()Z
Asciz	next;
Asciz	()Ljava/lang/Object;;
NameAndType	next:()Ljava/lang/Object;
InterfaceMethod	scala/collection/Iterator.next:()Ljava/lang/Object;
Asciz	scala/runtime/BoxesRunTime;
class	scala/runtime/BoxesRunTime
Asciz	unboxToChar;
Asciz	(Ljava/lang/Object;)C;
NameAndType	unboxToChar:(Ljava/lang/Object;)C
Method	scala/runtime/BoxesRunTime.unboxToChar:(Ljava/lang/Object;)C
Asciz	Expected '%s';
String	Expected '%s'
Asciz	scala/collection/immutable/StringOps;
class	scala/collection/immutable/StringOps
Asciz	(Ljava/lang/String;)V;
NameAndType	"<init>":(Ljava/lang/String;)V
Method	scala/collection/immutable/StringOps."<init>":(Ljava/lang/String;)V
Asciz	java/lang/Object;
class	java/lang/Object
Asciz	boxToCharacter;
Asciz	(C)Ljava/lang/Character;;
NameAndType	boxToCharacter:(C)Ljava/lang/Character;
Method	scala/runtime/BoxesRunTime.boxToCharacter:(C)Ljava/lang/Character;
Asciz	genericWrapArray;
Asciz	(Ljava/lang/Object;)Lscala/collection/mutable/WrappedArray;;
NameAndType	genericWrapArray:(Ljava/lang/Object;)Lscala/collection/mutable/WrappedArray;
Method	scala/Predef$.genericWrapArray:(Ljava/lang/Object;)Lscala/collection/mutable/WrappedArray;
Asciz	scala/collection/immutable/StringLike$class;
class	scala/collection/immutable/StringLike$class
Asciz	format;
Asciz	(Lscala/collection/immutable/StringLike;Lscala/collection/Seq;)Ljava/lang/String;;
NameAndType	format:(Lscala/collection/immutable/StringLike;Lscala/collection/Seq;)Ljava/lang/String;
Method	scala/collection/immutable/StringLike$class.format:(Lscala/collection/immutable/StringLike;Lscala/collection/Seq;)Ljava/lang/String;
Asciz	java/lang/RuntimeException;
class	java/lang/RuntimeException
Method	java/lang/RuntimeException."<init>":(Ljava/lang/String;)V
Asciz	it;
Asciz	Lscala/collection/Iterator;;
Asciz	end;
Asciz	temp1;
Asciz	xEndTag;
int	47;
Asciz	xToken;
Asciz	(C)V;
NameAndType	xToken:(C)V
InterfaceMethod	scala/xml/parsing/MarkupParserCommon.xToken:(C)V
Asciz	equals;
Asciz	(Ljava/lang/Object;)Z;
NameAndType	equals:(Ljava/lang/Object;)Z
Method	java/lang/Object.equals:(Ljava/lang/Object;)Z
int	62;
Asciz	errorNoEnd;
NameAndType	errorNoEnd:(Ljava/lang/String;)Lscala/runtime/Nothing$;
InterfaceMethod	scala/xml/parsing/MarkupParserCommon.errorNoEnd:(Ljava/lang/String;)Lscala/runtime/Nothing$;
Asciz	startName;
Asciz	scala/xml/parsing/TokenTests;
class	scala/xml/parsing/TokenTests
Asciz	isNameStart;
Asciz	(C)Z;
NameAndType	isNameStart:(C)Z
InterfaceMethod	scala/xml/parsing/TokenTests.isNameStart:(C)Z
Asciz	isNameChar;
NameAndType	isNameChar:(C)Z
InterfaceMethod	scala/xml/parsing/TokenTests.isNameChar:(C)Z
Asciz	scala/collection/TraversableLike$class;
class	scala/collection/TraversableLike$class
Asciz	last;
Asciz	(Lscala/collection/TraversableLike;)Ljava/lang/Object;;
NameAndType	last:(Lscala/collection/TraversableLike;)Ljava/lang/Object;
Method	scala/collection/TraversableLike$class.last:(Lscala/collection/TraversableLike;)Ljava/lang/Object;
int	58;
Asciz	name cannot end in ':';
String	name cannot end in ':'
Asciz	reportSyntaxError;
NameAndType	reportSyntaxError:(Ljava/lang/String;)V
InterfaceMethod	scala/xml/parsing/MarkupParserCommon.reportSyntaxError:(Ljava/lang/String;)V
Asciz	scala/collection/IndexedSeqOptimized$class;
class	scala/collection/IndexedSeqOptimized$class
Asciz	dropRight;
Asciz	(Lscala/collection/IndexedSeqOptimized;I)Ljava/lang/Object;;
NameAndType	dropRight:(Lscala/collection/IndexedSeqOptimized;I)Ljava/lang/Object;
Method	scala/collection/IndexedSeqOptimized$class.dropRight:(Lscala/collection/IndexedSeqOptimized;I)Ljava/lang/Object;
Asciz	name expected, but char '%s' cannot start a name;
String	name expected, but char '%s' cannot start a name
Asciz	attr_unescape;
Asciz	lt;
String	lt
Asciz	<;
String	<
Asciz	gt;
String	gt
Asciz	>;
String	>
Asciz	amp;
String	amp
Asciz	&;
String	&
Asciz	apos;
String	apos
Asciz	';
String	'
Asciz	quot;
String	quot
Asciz	\";
String	\"
Asciz	quote;
String	quote
Method	scala/collection/mutable/StringBuilder."<init>":()V
Asciz	(Ljava/lang/Object;)Lscala/collection/mutable/StringBuilder;;
NameAndType	append:(Ljava/lang/Object;)Lscala/collection/mutable/StringBuilder;
Method	scala/collection/mutable/StringBuilder.append:(Ljava/lang/Object;)Lscala/collection/mutable/StringBuilder;
Asciz	;;
String	;
Method	scala/collection/mutable/StringBuilder.toString:()Ljava/lang/String;
Asciz	s;
Asciz	scala/collection/IndexedSeqLike$class;
class	scala/collection/IndexedSeqLike$class
Asciz	iterator;
Asciz	(Lscala/collection/IndexedSeqLike;)Lscala/collection/Iterator;;
NameAndType	iterator:(Lscala/collection/IndexedSeqLike;)Lscala/collection/Iterator;
Method	scala/collection/IndexedSeqLike$class.iterator:(Lscala/collection/IndexedSeqLike;)Lscala/collection/Iterator;
Asciz	buffered;
Asciz	()Lscala/collection/BufferedIterator;;
NameAndType	buffered:()Lscala/collection/BufferedIterator;
InterfaceMethod	scala/collection/Iterator.buffered:()Lscala/collection/BufferedIterator;
Asciz	gd1$1;
Asciz	(Lscala/xml/parsing/MarkupParserCommon;Lscala/collection/BufferedIterator;)Z;
NameAndType	gd1$1:(Lscala/xml/parsing/MarkupParserCommon;Lscala/collection/BufferedIterator;)Z
Method	scala/xml/parsing/MarkupParserCommon$class.gd1$1:(Lscala/xml/parsing/MarkupParserCommon;Lscala/collection/BufferedIterator;)Z
Asciz	xCharRef;
Asciz	(Lscala/collection/Iterator;)Ljava/lang/String;;
NameAndType	xCharRef:(Lscala/collection/Iterator;)Ljava/lang/String;
InterfaceMethod	scala/xml/parsing/MarkupParserCommon.xCharRef:(Lscala/collection/Iterator;)Ljava/lang/String;
int	59;
NameAndType	takeUntilChar:(Lscala/xml/parsing/MarkupParserCommon;Lscala/collection/Iterator;C)Ljava/lang/String;
Method	scala/xml/parsing/MarkupParserCommon$class.takeUntilChar:(Lscala/xml/parsing/MarkupParserCommon;Lscala/collection/Iterator;C)Ljava/lang/String;
NameAndType	attr_unescape:(Lscala/xml/parsing/MarkupParserCommon;Ljava/lang/String;)Ljava/lang/String;
Method	scala/xml/parsing/MarkupParserCommon$class.attr_unescape:(Lscala/xml/parsing/MarkupParserCommon;Ljava/lang/String;)Ljava/lang/String;
Asciz	 ;
String	 
Asciz	valueOf;
Asciz	(Ljava/lang/Object;)Ljava/lang/String;;
NameAndType	valueOf:(Ljava/lang/Object;)Ljava/lang/String;
Method	java/lang/String.valueOf:(Ljava/lang/Object;)Ljava/lang/String;
Asciz	(Ljava/lang/String;)Lscala/collection/mutable/StringBuilder;;
NameAndType	append:(Ljava/lang/String;)Lscala/collection/mutable/StringBuilder;
Method	scala/collection/mutable/StringBuilder.append:(Ljava/lang/String;)Lscala/collection/mutable/StringBuilder;
Asciz	attval;
Asciz	temp10;
Asciz	it$2;
Asciz	Lscala/collection/BufferedIterator;;
Asciz	(Lscala/xml/parsing/MarkupParserCommon;Lscala/Function0;Lscala/Function0;)Ljava/lang/String;;
Asciz	scala/xml/Utility$;
class	scala/xml/Utility$
Asciz	Lscala/xml/Utility$;;
NameAndType	MODULE$:Lscala/xml/Utility$;
Field	scala/xml/Utility$.MODULE$:Lscala/xml/Utility$;
Asciz	scala/xml/parsing/MarkupParserCommon$$anonfun$xCharRef$5;
class	scala/xml/parsing/MarkupParserCommon$$anonfun$xCharRef$5
Method	scala/xml/parsing/MarkupParserCommon$$anonfun$xCharRef$5."<init>":(Lscala/xml/parsing/MarkupParserCommon;)V
Asciz	parseCharRef;
Asciz	(Lscala/Function0;Lscala/Function0;Lscala/Function1;)Ljava/lang/String;;
NameAndType	parseCharRef:(Lscala/Function0;Lscala/Function0;Lscala/Function1;)Ljava/lang/String;
Method	scala/xml/Utility$.parseCharRef:(Lscala/Function0;Lscala/Function0;Lscala/Function1;)Ljava/lang/String;
Asciz	Lscala/Function0;;
Asciz	nextch;
Asciz	(Lscala/xml/parsing/MarkupParserCommon;Lscala/collection/Iterator;)Ljava/lang/String;;
Asciz	scala/runtime/CharRef;
class	scala/runtime/CharRef
NameAndType	"<init>":(C)V
Method	scala/runtime/CharRef."<init>":(C)V
Asciz	scala/xml/parsing/MarkupParserCommon$$anonfun$xCharRef$1;
class	scala/xml/parsing/MarkupParserCommon$$anonfun$xCharRef$1
Asciz	(Lscala/xml/parsing/MarkupParserCommon;Lscala/runtime/CharRef;)V;
NameAndType	"<init>":(Lscala/xml/parsing/MarkupParserCommon;Lscala/runtime/CharRef;)V
Method	scala/xml/parsing/MarkupParserCommon$$anonfun$xCharRef$1."<init>":(Lscala/xml/parsing/MarkupParserCommon;Lscala/runtime/CharRef;)V
Asciz	scala/xml/parsing/MarkupParserCommon$$anonfun$xCharRef$2;
class	scala/xml/parsing/MarkupParserCommon$$anonfun$xCharRef$2
Asciz	(Lscala/xml/parsing/MarkupParserCommon;Lscala/collection/Iterator;Lscala/runtime/CharRef;)V;
NameAndType	"<init>":(Lscala/xml/parsing/MarkupParserCommon;Lscala/collection/Iterator;Lscala/runtime/CharRef;)V
Method	scala/xml/parsing/MarkupParserCommon$$anonfun$xCharRef$2."<init>":(Lscala/xml/parsing/MarkupParserCommon;Lscala/collection/Iterator;Lscala/runtime/CharRef;)V
Asciz	scala/xml/parsing/MarkupParserCommon$$anonfun$xCharRef$6;
class	scala/xml/parsing/MarkupParserCommon$$anonfun$xCharRef$6
Method	scala/xml/parsing/MarkupParserCommon$$anonfun$xCharRef$6."<init>":(Lscala/xml/parsing/MarkupParserCommon;)V
Asciz	it$1;
Asciz	c$1;
Asciz	Lscala/runtime/CharRef;;
Asciz	scala/xml/parsing/MarkupParserCommon$$anonfun$xCharRef$3;
class	scala/xml/parsing/MarkupParserCommon$$anonfun$xCharRef$3
Method	scala/xml/parsing/MarkupParserCommon$$anonfun$xCharRef$3."<init>":(Lscala/xml/parsing/MarkupParserCommon;)V
Asciz	scala/xml/parsing/MarkupParserCommon$$anonfun$xCharRef$4;
class	scala/xml/parsing/MarkupParserCommon$$anonfun$xCharRef$4
Method	scala/xml/parsing/MarkupParserCommon$$anonfun$xCharRef$4."<init>":(Lscala/xml/parsing/MarkupParserCommon;)V
Asciz	(Lscala/Function0;Lscala/Function0;)Ljava/lang/String;;
NameAndType	xCharRef:(Lscala/Function0;Lscala/Function0;)Ljava/lang/String;
InterfaceMethod	scala/xml/parsing/MarkupParserCommon.xCharRef:(Lscala/Function0;Lscala/Function0;)Ljava/lang/String;
Asciz	(Lscala/xml/parsing/MarkupParserCommon;Ljava/lang/String;Ljava/lang/Object;)Ljava/lang/Object;;
Asciz	msg;
Asciz	x;
Asciz	(Lscala/xml/parsing/MarkupParserCommon;C)V;
NameAndType	nextch:()C
InterfaceMethod	scala/xml/parsing/MarkupParserCommon.nextch:()C
Asciz	'%s' expected instead of '%s';
String	'%s' expected instead of '%s'
Asciz	xHandleError;
Asciz	(CLjava/lang/String;)V;
NameAndType	xHandleError:(CLjava/lang/String;)V
InterfaceMethod	scala/xml/parsing/MarkupParserCommon.xHandleError:(CLjava/lang/String;)V
Asciz	that;
Asciz	(Lscala/xml/parsing/MarkupParserCommon;Lscala/collection/Seq;)V;
Asciz	scala/xml/parsing/MarkupParserCommon$$anonfun$xToken$1;
class	scala/xml/parsing/MarkupParserCommon$$anonfun$xToken$1
Method	scala/xml/parsing/MarkupParserCommon$$anonfun$xToken$1."<init>":(Lscala/xml/parsing/MarkupParserCommon;)V
Asciz	scala/collection/IterableLike;
class	scala/collection/IterableLike
Asciz	foreach;
Asciz	(Lscala/Function1;)V;
NameAndType	foreach:(Lscala/Function1;)V
InterfaceMethod	scala/collection/IterableLike.foreach:(Lscala/Function1;)V
Asciz	Lscala/collection/Seq;;
Asciz	xEQ;
int	61;
Asciz	isSpace;
NameAndType	isSpace:(C)Z
InterfaceMethod	scala/xml/parsing/TokenTests.isSpace:(C)Z
Asciz	eof;
NameAndType	eof:()Z
InterfaceMethod	scala/xml/parsing/MarkupParserCommon.eof:()Z
Asciz	xSpace;
Asciz	whitespace expected;
String	whitespace expected
Asciz	returning;
Asciz	(Lscala/xml/parsing/MarkupParserCommon;Ljava/lang/Object;Lscala/Function1;)Ljava/lang/Object;;
Asciz	scala/Function1;
class	scala/Function1
Asciz	apply;
Asciz	(Ljava/lang/Object;)Ljava/lang/Object;;
NameAndType	apply:(Ljava/lang/Object;)Ljava/lang/Object;
InterfaceMethod	scala/Function1.apply:(Ljava/lang/Object;)Ljava/lang/Object;
Asciz	f;
Asciz	Lscala/Function1;;
Asciz	saving;
Asciz	(Lscala/xml/parsing/MarkupParserCommon;Ljava/lang/Object;Lscala/Function1;Lscala/Function0;)Ljava/lang/Object;;
Asciz	scala/Function0;
class	scala/Function0
NameAndType	apply:()Ljava/lang/Object;
InterfaceMethod	scala/Function0.apply:()Ljava/lang/Object;
Asciz	getter;
Asciz	setter;
Asciz	body;
Asciz	exceptionResult1;
Asciz	(Lscala/xml/parsing/MarkupParserCommon;Lscala/Function2;Lscala/Function0;Ljava/lang/String;)Ljava/lang/Object;;
Asciz	charAt;
Asciz	(I)C;
NameAndType	charAt:(I)C
Method	java/lang/String.charAt:(I)C
Asciz	drop;
NameAndType	drop:(Lscala/collection/IndexedSeqOptimized;I)Ljava/lang/Object;
Method	scala/collection/IndexedSeqOptimized$class.drop:(Lscala/collection/IndexedSeqOptimized;I)Ljava/lang/Object;
Asciz	peek;
Asciz	(Lscala/xml/parsing/MarkupParserCommon;Ljava/lang/String;)Z;
NameAndType	peek:(Lscala/xml/parsing/MarkupParserCommon;Ljava/lang/String;)Z
Method	scala/xml/parsing/MarkupParserCommon$class.peek:(Lscala/xml/parsing/MarkupParserCommon;Ljava/lang/String;)Z
Asciz	scala/Function2;
class	scala/Function2
Asciz	(Ljava/lang/Object;Ljava/lang/Object;)Ljava/lang/Object;;
NameAndType	apply:(Ljava/lang/Object;Ljava/lang/Object;)Ljava/lang/Object;
InterfaceMethod	scala/Function2.apply:(Ljava/lang/Object;Ljava/lang/Object;)Ljava/lang/Object;
Asciz	handler;
Asciz	Lscala/Function2;;
Asciz	positioner;
Asciz	until;
Asciz	head;
Asciz	rest;
Asciz	sb;
Asciz	lookahead;
NameAndType	lookahead:()Lscala/collection/BufferedIterator;
InterfaceMethod	scala/xml/parsing/MarkupParserCommon.lookahead:()Lscala/collection/BufferedIterator;
Asciz	length;
Asciz	()I;
NameAndType	length:()I
Method	java/lang/String.length:()I
Asciz	take;
Asciz	(I)Lscala/collection/Iterator;;
NameAndType	take:(I)Lscala/collection/Iterator;
InterfaceMethod	scala/collection/Iterator.take:(I)Lscala/collection/Iterator;
Asciz	sameElements;
Asciz	(Lscala/collection/Iterator;)Z;
NameAndType	sameElements:(Lscala/collection/Iterator;)Z
InterfaceMethod	scala/collection/Iterator.sameElements:(Lscala/collection/Iterator;)Z
Asciz	scala/collection/immutable/Range$$anon$1;
class	scala/collection/immutable/Range$$anon$1
Asciz	(II)V;
NameAndType	"<init>":(II)V
Method	scala/collection/immutable/Range$$anon$1."<init>":(II)V
Asciz	scala/collection/immutable/Range$ByOne;
class	scala/collection/immutable/Range$ByOne
Asciz	scala/xml/parsing/MarkupParserCommon$$anonfun$peek$1;
class	scala/xml/parsing/MarkupParserCommon$$anonfun$peek$1
Method	scala/xml/parsing/MarkupParserCommon$$anonfun$peek$1."<init>":(Lscala/xml/parsing/MarkupParserCommon;)V
InterfaceMethod	scala/collection/immutable/Range$ByOne.foreach:(Lscala/Function1;)V
Asciz	lookingFor;
Asciz	scala/collection/BufferedIterator;
class	scala/collection/BufferedIterator
NameAndType	head:()Ljava/lang/Object;
InterfaceMethod	scala/collection/BufferedIterator.head:()Ljava/lang/Object;
int	35;
Asciz	$init$;
Asciz	Scala;
Asciz	InnerClasses;
Asciz	scala/collection/immutable/Range;
class	scala/collection/immutable/Range
Asciz	ByOne;
Asciz	$anon$1;
Asciz	$anonfun$peek$1;
Asciz	$anonfun$xToken$1;
Asciz	$anonfun$xCharRef$4;
Asciz	$anonfun$xCharRef$3;
Asciz	$anonfun$xCharRef$6;
Asciz	$anonfun$xCharRef$2;
Asciz	$anonfun$xCharRef$1;
Asciz	$anonfun$xCharRef$5;
Asciz	$anonfun$xProcInstr$2;
Asciz	$anonfun$xProcInstr$1;

{
public static scala.runtime.Nothing$ unreachable(scala.xml.parsing.MarkupParserCommon);
  Signature: (Lscala/xml/parsing/MarkupParserCommon;)Lscala/runtime/Nothing$;
  Code:
   Stack=2, Locals=1, Args_size=1
	getstatic	Field scala/Predef$.MODULE$:Lscala/Predef$;
	ldc	String Cannot be reached.
	invokevirtual	Method scala/Predef$.error:(Ljava/lang/String;)Lscala/runtime/Nothing$;
	areturn
  Labels:
  LocalVariableTable: 
   Start  Length  Slot  Name   Signature
   0      9      0    $this       Lscala/xml/parsing/MarkupParserCommon;


public static scala.Tuple2 xTag(scala.xml.parsing.MarkupParserCommon, java.lang.Object);
  Signature: (Lscala/xml/parsing/MarkupParserCommon;Ljava/lang/Object;)Lscala/Tuple2;
  Code:
   Stack=6, Locals=3, Args_size=2
	aload_0
	invokeinterface	InterfaceMethod scala/xml/parsing/MarkupParserCommon.xName:()Ljava/lang/String;
	astore_2
	aload_0
	invokeinterface	InterfaceMethod scala/xml/parsing/MarkupParserCommon.xSpaceOpt:()V
	new	class scala/Tuple2
	dup
	aload_2
	aload_0
	aload_2
	aload_1
	invokeinterface	InterfaceMethod scala/xml/parsing/MarkupParserCommon.mkAttributes:(Ljava/lang/String;Ljava/lang/Object;)Ljava/lang/Object;
	invokespecial	Method scala/Tuple2."<init>":(Ljava/lang/Object;Ljava/lang/Object;)V
	areturn
  Labels:
  LocalVariableTable: 
   Start  Length  Slot  Name   Signature
   0      30      0    $this       Lscala/xml/parsing/MarkupParserCommon;
   0      30      1    pscope       Ljava/lang/Object;
   7      22      2    name       Ljava/lang/String;


public static java.lang.Object xProcInstr(scala.xml.parsing.MarkupParserCommon);
  Signature: (Lscala/xml/parsing/MarkupParserCommon;)Ljava/lang/Object;
  Code:
   Stack=5, Locals=2, Args_size=1
	aload_0
	invokeinterface	InterfaceMethod scala/xml/parsing/MarkupParserCommon.xName:()Ljava/lang/String;
	astore_1
	aload_0
	invokeinterface	InterfaceMethod scala/xml/parsing/MarkupParserCommon.xSpaceOpt:()V
	aload_0
	new	class scala/xml/parsing/MarkupParserCommon$$anonfun$xProcInstr$1
	dup
	aload_0
	aload_1
	invokespecial	Method scala/xml/parsing/MarkupParserCommon$$anonfun$xProcInstr$1."<init>":(Lscala/xml/parsing/MarkupParserCommon;Ljava/lang/String;)V
	new	class scala/xml/parsing/MarkupParserCommon$$anonfun$xProcInstr$2
	dup
	aload_0
	invokespecial	Method scala/xml/parsing/MarkupParserCommon$$anonfun$xProcInstr$2."<init>":(Lscala/xml/parsing/MarkupParserCommon;)V
	ldc	String ?>
	invokeinterface	InterfaceMethod scala/xml/parsing/MarkupParserCommon.xTakeUntil:(Lscala/Function2;Lscala/Function0;Ljava/lang/String;)Ljava/lang/Object;
	areturn
  Labels:
  LocalVariableTable: 
   Start  Length  Slot  Name   Signature
   0      39      0    $this       Lscala/xml/parsing/MarkupParserCommon;
   7      31      1    n$1       Ljava/lang/String;


public static java.lang.String xAttributeValue(scala.xml.parsing.MarkupParserCommon, char);
  Signature: (Lscala/xml/parsing/MarkupParserCommon;C)Ljava/lang/String;
  Code:
   Stack=3, Locals=3, Args_size=2
	new	class scala/collection/mutable/StringBuilder
	dup
	invokespecial	Method scala/collection/mutable/StringBuilder."<init>":()V
	astore_2
l4	aload_0
	invokeinterface	InterfaceMethod scala/xml/parsing/MarkupParserCommon.ch:()C
	iload_1
	if_icmpeq	l1 // aload_0
	aload_0
	invokeinterface	InterfaceMethod scala/xml/parsing/MarkupParserCommon.ch:()C
	ldc	int 60
	if_icmpne	l2 // aload_0
	aload_0
	ldc	String '<' not allowed in attrib value
	ldc	String 
	invokeinterface	InterfaceMethod scala/xml/parsing/MarkupParserCommon.errorAndResult:(Ljava/lang/String;Ljava/lang/Object;)Ljava/lang/Object;
	checkcast	class java/lang/String
	areturn
l2	aload_0
	invokeinterface	InterfaceMethod scala/xml/parsing/MarkupParserCommon.ch:()C
	ldc	int 26
	if_icmpne	l3 // aload_2
	aload_0
	ldc	String 
	invokeinterface	InterfaceMethod scala/xml/parsing/MarkupParserCommon.truncatedError:(Ljava/lang/String;)Lscala/runtime/Nothing$;
	athrow
l3	aload_2
	aload_0
	invokeinterface	InterfaceMethod scala/xml/parsing/MarkupParserCommon.ch_returning_nextch:()C
	invokevirtual	Method scala/collection/mutable/StringBuilder.append:(C)Lscala/collection/mutable/StringBuilder;
	pop
	goto	l4 // aload_0
l1	aload_0
	invokeinterface	InterfaceMethod scala/xml/parsing/MarkupParserCommon.ch_returning_nextch:()C
	pop
	aload_2
	invokevirtual	Method scala/collection/mutable/StringBuilder.toString:()Ljava/lang/String;
	areturn
  Labels:
   	l4 = 8 // aload_0
   	l2 = 43 // aload_0
   	l3 = 63 // aload_2
   	l1 = 77 // aload_0
  LocalVariableTable: 
   Start  Length  Slot  Name   Signature
   0      89      0    $this       Lscala/xml/parsing/MarkupParserCommon;
   0      89      1    endCh       C
   8      80      2    buf       Lscala/collection/mutable/StringBuilder;


public static java.lang.String xAttributeValue(scala.xml.parsing.MarkupParserCommon);
  Signature: (Lscala/xml/parsing/MarkupParserCommon;)Ljava/lang/String;
  Code:
   Stack=2, Locals=2, Args_size=1
	aload_0
	aload_0
	invokeinterface	InterfaceMethod scala/xml/parsing/MarkupParserCommon.ch_returning_nextch:()C
	invokeinterface	InterfaceMethod scala/xml/parsing/MarkupParserCommon.xAttributeValue:(C)Ljava/lang/String;
	astore_1
	aload_0
	aload_1
	invokestatic	Method normalizeAttributeValue:(Lscala/xml/parsing/MarkupParserCommon;Ljava/lang/String;)Ljava/lang/String;
	areturn
  Labels:
  LocalVariableTable: 
   Start  Length  Slot  Name   Signature
   0      19      0    $this       Lscala/xml/parsing/MarkupParserCommon;
   13      5      1    str       Ljava/lang/String;


private static java.lang.String takeUntilChar(scala.xml.parsing.MarkupParserCommon, scala.collection.Iterator, char);
  Signature: (Lscala/xml/parsing/MarkupParserCommon;Lscala/collection/Iterator;C)Ljava/lang/String;
  Code:
   Stack=6, Locals=9, Args_size=3
	new	class scala/collection/mutable/StringBuilder
	dup
	invokespecial	Method scala/collection/mutable/StringBuilder."<init>":()V
	astore_3
l3	aload_1
	invokeinterface	InterfaceMethod scala/collection/Iterator.hasNext:()Z
	ifeq	l1 // ldc
	aload_1
	invokeinterface	InterfaceMethod scala/collection/Iterator.next:()Ljava/lang/Object;
	invokestatic	Method scala/runtime/BoxesRunTime.unboxToChar:(Ljava/lang/Object;)C
	istore	4
	iload_2
	iload	4
	if_icmpne	l2 // aload_3
	aload_3
	invokevirtual	Method scala/collection/mutable/StringBuilder.toString:()Ljava/lang/String;
	areturn
l2	aload_3
	iload	4
	invokevirtual	Method scala/collection/mutable/StringBuilder.append:(C)Lscala/collection/mutable/StringBuilder;
	pop
	goto	l3 // aload_1
l1	ldc	String Expected '%s'
	astore	5
	new	class scala/collection/immutable/StringOps
	dup
	aload	5
	invokespecial	Method scala/collection/immutable/StringOps."<init>":(Ljava/lang/String;)V
	getstatic	Field scala/Predef$.MODULE$:Lscala/Predef$;
	iconst_1
	anewarray	class java/lang/Object
	dup
	iconst_0
	iload_2
	invokestatic	Method scala/runtime/BoxesRunTime.boxToCharacter:(C)Ljava/lang/Character;
	aastore
	invokevirtual	Method scala/Predef$.genericWrapArray:(Ljava/lang/Object;)Lscala/collection/mutable/WrappedArray;
	astore	7
	astore	6
	aload	6
	aload	7
	invokestatic	Method scala/collection/immutable/StringLike$class.format:(Lscala/collection/immutable/StringLike;Lscala/collection/Seq;)Ljava/lang/String;
	astore	8
	new	class java/lang/RuntimeException
	dup
	aload	8
	invokespecial	Method java/lang/RuntimeException."<init>":(Ljava/lang/String;)V
	athrow
  Labels:
   	l3 = 8 // aload_1
   	l2 = 39 // aload_3
   	l1 = 49 // ldc
  LocalVariableTable: 
   Start  Length  Slot  Name   Signature
   0      102      0    $this       Lscala/xml/parsing/MarkupParserCommon;
   0      102      1    it       Lscala/collection/Iterator;
   0      102      2    end       C
   8      94      3    buf       Lscala/collection/mutable/StringBuilder;
   28      18      4    temp1       C


public static void xEndTag(scala.xml.parsing.MarkupParserCommon, java.lang.String);
  Signature: (Lscala/xml/parsing/MarkupParserCommon;Ljava/lang/String;)V
  Code:
   Stack=2, Locals=2, Args_size=2
	aload_0
	ldc	int 47
	invokeinterface	InterfaceMethod scala/xml/parsing/MarkupParserCommon.xToken:(C)V
	aload_0
	invokeinterface	InterfaceMethod scala/xml/parsing/MarkupParserCommon.xName:()Ljava/lang/String;
	dup
	ifnonnull	l1 // aload_1
	pop
	aload_1
	ifnull	l2 // aload_0
	goto	l3 // aload_0
l1	aload_1
	invokevirtual	Method java/lang/Object.equals:(Ljava/lang/Object;)Z
	ifeq	l3 // aload_0
l2	aload_0
	invokeinterface	InterfaceMethod scala/xml/parsing/MarkupParserCommon.xSpaceOpt:()V
	aload_0
	ldc	int 62
	invokeinterface	InterfaceMethod scala/xml/parsing/MarkupParserCommon.xToken:(C)V
	return
l3	aload_0
	aload_1
	invokeinterface	InterfaceMethod scala/xml/parsing/MarkupParserCommon.errorNoEnd:(Ljava/lang/String;)Lscala/runtime/Nothing$;
	athrow
  Labels:
   	l1 = 26 // aload_1
   	l2 = 33 // aload_0
   	l3 = 48 // aload_0
  LocalVariableTable: 
   Start  Length  Slot  Name   Signature
   0      56      0    $this       Lscala/xml/parsing/MarkupParserCommon;
   0      56      1    startName       Ljava/lang/String;


public static java.lang.String xName(scala.xml.parsing.MarkupParserCommon);
  Signature: (Lscala/xml/parsing/MarkupParserCommon;)Ljava/lang/String;
  Code:
   Stack=7, Locals=9, Args_size=1
	aload_0
	invokeinterface	InterfaceMethod scala/xml/parsing/MarkupParserCommon.ch:()C
	ldc	int 26
	if_icmpne	l1 // aload_0
	aload_0
	ldc	String 
	invokeinterface	InterfaceMethod scala/xml/parsing/MarkupParserCommon.truncatedError:(Ljava/lang/String;)Lscala/runtime/Nothing$;
	athrow
l1	aload_0
	aload_0
	invokeinterface	InterfaceMethod scala/xml/parsing/MarkupParserCommon.ch:()C
	invokeinterface	InterfaceMethod scala/xml/parsing/TokenTests.isNameStart:(C)Z
	ifeq	l2 // aload_0
	new	class scala/collection/mutable/StringBuilder
	dup
	invokespecial	Method scala/collection/mutable/StringBuilder."<init>":()V
	astore	4
l3	aload	4
	aload_0
	invokeinterface	InterfaceMethod scala/xml/parsing/MarkupParserCommon.ch_returning_nextch:()C
	invokevirtual	Method scala/collection/mutable/StringBuilder.append:(C)Lscala/collection/mutable/StringBuilder;
	pop
	aload_0
	aload_0
	invokeinterface	InterfaceMethod scala/xml/parsing/MarkupParserCommon.ch:()C
	invokeinterface	InterfaceMethod scala/xml/parsing/TokenTests.isNameChar:(C)Z
	ifne	l3 // aload
	aload	4
	invokestatic	Method scala/collection/TraversableLike$class.last:(Lscala/collection/TraversableLike;)Ljava/lang/Object;
	invokestatic	Method scala/runtime/BoxesRunTime.unboxToChar:(Ljava/lang/Object;)C
	ldc	int 58
	if_icmpne	l4 // aload
	aload_0
	ldc	String name cannot end in ':'
	invokeinterface	InterfaceMethod scala/xml/parsing/MarkupParserCommon.reportSyntaxError:(Ljava/lang/String;)V
	aload	4
	invokevirtual	Method scala/collection/mutable/StringBuilder.toString:()Ljava/lang/String;
	astore_1
	new	class scala/collection/immutable/StringOps
	dup
	aload_1
	invokespecial	Method scala/collection/immutable/StringOps."<init>":(Ljava/lang/String;)V
	iconst_1
	istore_3
	astore_2
	aload_2
	iload_3
	invokestatic	Method scala/collection/IndexedSeqOptimized$class.dropRight:(Lscala/collection/IndexedSeqOptimized;I)Ljava/lang/Object;
	checkcast	class java/lang/String
	goto	l5 // areturn
l4	aload	4
	invokevirtual	Method scala/collection/mutable/StringBuilder.toString:()Ljava/lang/String;
l5	areturn
l2	aload_0
	ldc	String name expected, but char '%s' cannot start a name
	astore	5
	new	class scala/collection/immutable/StringOps
	dup
	aload	5
	invokespecial	Method scala/collection/immutable/StringOps."<init>":(Ljava/lang/String;)V
	getstatic	Field scala/Predef$.MODULE$:Lscala/Predef$;
	iconst_1
	anewarray	class java/lang/Object
	dup
	iconst_0
	aload_0
	invokeinterface	InterfaceMethod scala/xml/parsing/MarkupParserCommon.ch:()C
	istore	6
	iload	6
	invokestatic	Method scala/runtime/BoxesRunTime.boxToCharacter:(C)Ljava/lang/Character;
	aastore
	invokevirtual	Method scala/Predef$.genericWrapArray:(Ljava/lang/Object;)Lscala/collection/mutable/WrappedArray;
	astore	8
	astore	7
	aload	7
	aload	8
	invokestatic	Method scala/collection/immutable/StringLike$class.format:(Lscala/collection/immutable/StringLike;Lscala/collection/Seq;)Ljava/lang/String;
	ldc	String 
	invokeinterface	InterfaceMethod scala/xml/parsing/MarkupParserCommon.errorAndResult:(Ljava/lang/String;Ljava/lang/Object;)Ljava/lang/Object;
	checkcast	class java/lang/String
	areturn
  Labels:
   	l1 = 20 // aload_0
   	l3 = 44 // aload
   	l4 = 120 // aload
   	l5 = 125 // areturn
   	l2 = 126 // aload_0
  LocalVariableTable: 
   Start  Length  Slot  Name   Signature
   0      188      0    $this       Lscala/xml/parsing/MarkupParserCommon;
   44      82      4    buf       Lscala/collection/mutable/StringBuilder;


private static java.lang.String attr_unescape(scala.xml.parsing.MarkupParserCommon, java.lang.String);
  Signature: (Lscala/xml/parsing/MarkupParserCommon;Ljava/lang/String;)Ljava/lang/String;
  Code:
   Stack=2, Locals=8, Args_size=2
	aload_1
	ldc	String lt
	astore_2
	dup
	ifnonnull	l1 // aload_2
	pop
	aload_2
	ifnull	l2 // ldc
	goto	l3 // aload_1
l1	aload_2
	invokevirtual	Method java/lang/Object.equals:(Ljava/lang/Object;)Z
	ifeq	l3 // aload_1
l2	ldc	String <
	goto	l4 // areturn
l3	aload_1
	ldc	String gt
	astore_3
	dup
	ifnonnull	l5 // aload_3
	pop
	aload_3
	ifnull	l6 // ldc
	goto	l7 // aload_1
l5	aload_3
	invokevirtual	Method java/lang/Object.equals:(Ljava/lang/Object;)Z
	ifeq	l7 // aload_1
l6	ldc	String >
	goto	l4 // areturn
l7	aload_1
	ldc	String amp
	astore	4
	dup
	ifnonnull	l8 // aload
	pop
	aload	4
	ifnull	l9 // ldc
	goto	l10 // aload_1
l8	aload	4
	invokevirtual	Method java/lang/Object.equals:(Ljava/lang/Object;)Z
	ifeq	l10 // aload_1
l9	ldc	String &
	goto	l4 // areturn
l10	aload_1
	ldc	String apos
	astore	5
	dup
	ifnonnull	l11 // aload
	pop
	aload	5
	ifnull	l12 // ldc
	goto	l13 // aload_1
l11	aload	5
	invokevirtual	Method java/lang/Object.equals:(Ljava/lang/Object;)Z
	ifeq	l13 // aload_1
l12	ldc	String '
	goto	l4 // areturn
l13	aload_1
	ldc	String quot
	astore	6
	dup
	ifnonnull	l14 // aload
	pop
	aload	6
	ifnull	l15 // ldc
	goto	l16 // aload_1
l14	aload	6
	invokevirtual	Method java/lang/Object.equals:(Ljava/lang/Object;)Z
	ifeq	l16 // aload_1
l15	ldc	String \"
	goto	l4 // areturn
l16	aload_1
	ldc	String quote
	astore	7
	dup
	ifnonnull	l17 // aload
	pop
	aload	7
	ifnull	l18 // ldc
	goto	l19 // new
l17	aload	7
	invokevirtual	Method java/lang/Object.equals:(Ljava/lang/Object;)Z
	ifeq	l19 // new
l18	ldc	String \"
	goto	l4 // areturn
l19	new	class scala/collection/mutable/StringBuilder
	dup
	invokespecial	Method scala/collection/mutable/StringBuilder."<init>":()V
	ldc	String &
	invokevirtual	Method scala/collection/mutable/StringBuilder.append:(Ljava/lang/Object;)Lscala/collection/mutable/StringBuilder;
	aload_1
	invokevirtual	Method scala/collection/mutable/StringBuilder.append:(Ljava/lang/Object;)Lscala/collection/mutable/StringBuilder;
	ldc	String ;
	invokevirtual	Method scala/collection/mutable/StringBuilder.append:(Ljava/lang/Object;)Lscala/collection/mutable/StringBuilder;
	invokevirtual	Method scala/collection/mutable/StringBuilder.toString:()Ljava/lang/String;
l4	areturn
  Labels:
   	l1 = 16 // aload_2
   	l2 = 23 // ldc
   	l3 = 28 // aload_1
   	l5 = 44 // aload_3
   	l6 = 51 // ldc
   	l7 = 56 // aload_1
   	l8 = 74 // aload
   	l9 = 82 // ldc
   	l10 = 87 // aload_1
   	l11 = 105 // aload
   	l12 = 113 // ldc
   	l13 = 118 // aload_1
   	l14 = 136 // aload
   	l15 = 144 // ldc
   	l16 = 149 // aload_1
   	l17 = 167 // aload
   	l18 = 175 // ldc
   	l19 = 180 // new
   	l4 = 204 // areturn
  LocalVariableTable: 
   Start  Length  Slot  Name   Signature
   0      205      0    $this       Lscala/xml/parsing/MarkupParserCommon;
   0      205      1    s       Ljava/lang/String;


private static java.lang.String normalizeAttributeValue(scala.xml.parsing.MarkupParserCommon, java.lang.String);
  Signature: (Lscala/xml/parsing/MarkupParserCommon;Ljava/lang/String;)Ljava/lang/String;
  Code:
   Stack=4, Locals=7, Args_size=2
	new	class scala/collection/mutable/StringBuilder
	dup
	invokespecial	Method scala/collection/mutable/StringBuilder."<init>":()V
	astore	6
	new	class scala/collection/immutable/StringOps
	dup
	aload_1
	invokespecial	Method scala/collection/immutable/StringOps."<init>":(Ljava/lang/String;)V
	astore_2
	aload_2
	invokestatic	Method scala/collection/IndexedSeqLike$class.iterator:(Lscala/collection/IndexedSeqLike;)Lscala/collection/Iterator;
	invokeinterface	InterfaceMethod scala/collection/Iterator.buffered:()Lscala/collection/BufferedIterator;
	astore	4
l4	aload	4
	invokeinterface	InterfaceMethod scala/collection/Iterator.hasNext:()Z
	ifeq	l1 // aload
	aload	4
	invokeinterface	InterfaceMethod scala/collection/Iterator.next:()Ljava/lang/Object;
	invokestatic	Method scala/runtime/BoxesRunTime.unboxToChar:(Ljava/lang/Object;)C
	istore_3
	iload_3
	lookupswitch{ //5
		9: 169;
		10: 163;
		13: 157;
		32: 151;
		38: 107;
		default: 100 }
	iload_3
	invokestatic	Method scala/runtime/BoxesRunTime.boxToCharacter:(C)Ljava/lang/Character;
	goto	l2 // astore
	aload_0
	aload	4
	invokestatic	Method gd1$1:(Lscala/xml/parsing/MarkupParserCommon;Lscala/collection/BufferedIterator;)Z
	ifeq	l3 // aload_0
	aload	4
	invokeinterface	InterfaceMethod scala/collection/Iterator.next:()Ljava/lang/Object;
	pop
	aload_0
	aload	4
	invokeinterface	InterfaceMethod scala/xml/parsing/MarkupParserCommon.xCharRef:(Lscala/collection/Iterator;)Ljava/lang/String;
	goto	l2 // astore
l3	aload_0
	aload_0
	aload	4
	ldc_w	int 59
	invokestatic	Method takeUntilChar:(Lscala/xml/parsing/MarkupParserCommon;Lscala/collection/Iterator;C)Ljava/lang/String;
	invokestatic	Method attr_unescape:(Lscala/xml/parsing/MarkupParserCommon;Ljava/lang/String;)Ljava/lang/String;
	goto	l2 // astore
	ldc_w	String  
	goto	l2 // astore
	ldc_w	String  
	goto	l2 // astore
	ldc_w	String  
	goto	l2 // astore
	ldc_w	String  
l2	astore	5
	aload	6
	aload	5
	invokestatic	Method java/lang/String.valueOf:(Ljava/lang/Object;)Ljava/lang/String;
	invokevirtual	Method scala/collection/mutable/StringBuilder.append:(Ljava/lang/String;)Lscala/collection/mutable/StringBuilder;
	pop
	goto	l4 // aload
l1	aload	6
	invokevirtual	Method scala/collection/mutable/StringBuilder.toString:()Ljava/lang/String;
	areturn
  Labels:
   	l4 = 29 // aload
   	l3 = 135 // aload_0
   	l2 = 172 // astore
   	l1 = 188 // aload
  LocalVariableTable: 
   Start  Length  Slot  Name   Signature
   0      194      0    $this       Lscala/xml/parsing/MarkupParserCommon;
   0      194      1    attval       Ljava/lang/String;
   50      138      3    temp10       C
   29      164      4    it$2       Lscala/collection/BufferedIterator;
   9      184      6    buf       Lscala/collection/mutable/StringBuilder;


public static java.lang.String xCharRef(scala.xml.parsing.MarkupParserCommon, scala.Function0, scala.Function0);
  Signature: (Lscala/xml/parsing/MarkupParserCommon;Lscala/Function0;Lscala/Function0;)Ljava/lang/String;
  Code:
   Stack=6, Locals=3, Args_size=3
	getstatic	Field scala/xml/Utility$.MODULE$:Lscala/xml/Utility$;
	aload_1
	aload_2
	new	class scala/xml/parsing/MarkupParserCommon$$anonfun$xCharRef$5
	dup
	aload_0
	invokespecial	Method scala/xml/parsing/MarkupParserCommon$$anonfun$xCharRef$5."<init>":(Lscala/xml/parsing/MarkupParserCommon;)V
	invokevirtual	Method scala/xml/Utility$.parseCharRef:(Lscala/Function0;Lscala/Function0;Lscala/Function1;)Ljava/lang/String;
	areturn
  Labels:
  LocalVariableTable: 
   Start  Length  Slot  Name   Signature
   0      17      0    $this       Lscala/xml/parsing/MarkupParserCommon;
   0      17      1    ch       Lscala/Function0;
   0      17      2    nextch       Lscala/Function0;


public static java.lang.String xCharRef(scala.xml.parsing.MarkupParserCommon, scala.collection.Iterator);
  Signature: (Lscala/xml/parsing/MarkupParserCommon;Lscala/collection/Iterator;)Ljava/lang/String;
  Code:
   Stack=7, Locals=3, Args_size=2
	new	class scala/runtime/CharRef
	dup
	aload_1
	invokeinterface	InterfaceMethod scala/collection/Iterator.next:()Ljava/lang/Object;
	invokestatic	Method scala/runtime/BoxesRunTime.unboxToChar:(Ljava/lang/Object;)C
	invokespecial	Method scala/runtime/CharRef."<init>":(C)V
	astore_2
	getstatic	Field scala/xml/Utility$.MODULE$:Lscala/xml/Utility$;
	new	class scala/xml/parsing/MarkupParserCommon$$anonfun$xCharRef$1
	dup
	aload_0
	aload_2
	invokespecial	Method scala/xml/parsing/MarkupParserCommon$$anonfun$xCharRef$1."<init>":(Lscala/xml/parsing/MarkupParserCommon;Lscala/runtime/CharRef;)V
	new	class scala/xml/parsing/MarkupParserCommon$$anonfun$xCharRef$2
	dup
	aload_0
	aload_1
	aload_2
	invokespecial	Method scala/xml/parsing/MarkupParserCommon$$anonfun$xCharRef$2."<init>":(Lscala/xml/parsing/MarkupParserCommon;Lscala/collection/Iterator;Lscala/runtime/CharRef;)V
	new	class scala/xml/parsing/MarkupParserCommon$$anonfun$xCharRef$6
	dup
	aload_0
	invokespecial	Method scala/xml/parsing/MarkupParserCommon$$anonfun$xCharRef$6."<init>":(Lscala/xml/parsing/MarkupParserCommon;)V
	invokevirtual	Method scala/xml/Utility$.parseCharRef:(Lscala/Function0;Lscala/Function0;Lscala/Function1;)Ljava/lang/String;
	areturn
  Labels:
  LocalVariableTable: 
   Start  Length  Slot  Name   Signature
   0      51      0    $this       Lscala/xml/parsing/MarkupParserCommon;
   0      51      1    it$1       Lscala/collection/Iterator;
   17      33      2    c$1       Lscala/runtime/CharRef;


public static java.lang.String xCharRef(scala.xml.parsing.MarkupParserCommon);
  Signature: (Lscala/xml/parsing/MarkupParserCommon;)Ljava/lang/String;
  Code:
   Stack=5, Locals=1, Args_size=1
	aload_0
	new	class scala/xml/parsing/MarkupParserCommon$$anonfun$xCharRef$3
	dup
	aload_0
	invokespecial	Method scala/xml/parsing/MarkupParserCommon$$anonfun$xCharRef$3."<init>":(Lscala/xml/parsing/MarkupParserCommon;)V
	new	class scala/xml/parsing/MarkupParserCommon$$anonfun$xCharRef$4
	dup
	aload_0
	invokespecial	Method scala/xml/parsing/MarkupParserCommon$$anonfun$xCharRef$4."<init>":(Lscala/xml/parsing/MarkupParserCommon;)V
	invokeinterface	InterfaceMethod scala/xml/parsing/MarkupParserCommon.xCharRef:(Lscala/Function0;Lscala/Function0;)Ljava/lang/String;
	areturn
  Labels:
  LocalVariableTable: 
   Start  Length  Slot  Name   Signature
   0      23      0    $this       Lscala/xml/parsing/MarkupParserCommon;


public static java.lang.Object errorAndResult(scala.xml.parsing.MarkupParserCommon, java.lang.String, java.lang.Object);
  Signature: (Lscala/xml/parsing/MarkupParserCommon;Ljava/lang/String;Ljava/lang/Object;)Ljava/lang/Object;
  Code:
   Stack=2, Locals=3, Args_size=3
	aload_0
	aload_1
	invokeinterface	InterfaceMethod scala/xml/parsing/MarkupParserCommon.reportSyntaxError:(Ljava/lang/String;)V
	aload_2
	areturn
  Labels:
  LocalVariableTable: 
   Start  Length  Slot  Name   Signature
   0      9      0    $this       Lscala/xml/parsing/MarkupParserCommon;
   0      9      1    msg       Ljava/lang/String;
   0      9      2    x       Ljava/lang/Object;


public static void xToken(scala.xml.parsing.MarkupParserCommon, char);
  Signature: (Lscala/xml/parsing/MarkupParserCommon;C)V
  Code:
   Stack=8, Locals=6, Args_size=2
	aload_0
	invokeinterface	InterfaceMethod scala/xml/parsing/MarkupParserCommon.ch:()C
	iload_1
	if_icmpne	l1 // aload_0
	aload_0
	invokeinterface	InterfaceMethod scala/xml/parsing/MarkupParserCommon.nextch:()C
	pop
	goto	l2 // return
l1	aload_0
	iload_1
	ldc_w	String '%s' expected instead of '%s'
	astore_2
	new	class scala/collection/immutable/StringOps
	dup
	aload_2
	invokespecial	Method scala/collection/immutable/StringOps."<init>":(Ljava/lang/String;)V
	getstatic	Field scala/Predef$.MODULE$:Lscala/Predef$;
	iconst_2
	anewarray	class java/lang/Object
	dup
	iconst_0
	iload_1
	invokestatic	Method scala/runtime/BoxesRunTime.boxToCharacter:(C)Ljava/lang/Character;
	aastore
	dup
	iconst_1
	aload_0
	invokeinterface	InterfaceMethod scala/xml/parsing/MarkupParserCommon.ch:()C
	istore_3
	iload_3
	invokestatic	Method scala/runtime/BoxesRunTime.boxToCharacter:(C)Ljava/lang/Character;
	aastore
	invokevirtual	Method scala/Predef$.genericWrapArray:(Ljava/lang/Object;)Lscala/collection/mutable/WrappedArray;
	astore	5
	astore	4
	aload	4
	aload	5
	invokestatic	Method scala/collection/immutable/StringLike$class.format:(Lscala/collection/immutable/StringLike;Lscala/collection/Seq;)Ljava/lang/String;
	invokeinterface	InterfaceMethod scala/xml/parsing/MarkupParserCommon.xHandleError:(CLjava/lang/String;)V
l2	return
  Labels:
   	l1 = 20 // aload_0
   	l2 = 81 // return
  LocalVariableTable: 
   Start  Length  Slot  Name   Signature
   0      82      0    $this       Lscala/xml/parsing/MarkupParserCommon;
   0      82      1    that       C


public static void xToken(scala.xml.parsing.MarkupParserCommon, scala.collection.Seq);
  Signature: (Lscala/xml/parsing/MarkupParserCommon;Lscala/collection/Seq;)V
  Code:
   Stack=4, Locals=2, Args_size=2
	aload_1
	new	class scala/xml/parsing/MarkupParserCommon$$anonfun$xToken$1
	dup
	aload_0
	invokespecial	Method scala/xml/parsing/MarkupParserCommon$$anonfun$xToken$1."<init>":(Lscala/xml/parsing/MarkupParserCommon;)V
	invokeinterface	InterfaceMethod scala/collection/IterableLike.foreach:(Lscala/Function1;)V
	return
  Labels:
  LocalVariableTable: 
   Start  Length  Slot  Name   Signature
   0      15      0    $this       Lscala/xml/parsing/MarkupParserCommon;
   0      15      1    that       Lscala/collection/Seq;


public static void xEQ(scala.xml.parsing.MarkupParserCommon);
  Signature: (Lscala/xml/parsing/MarkupParserCommon;)V
  Code:
   Stack=2, Locals=1, Args_size=1
	aload_0
	invokeinterface	InterfaceMethod scala/xml/parsing/MarkupParserCommon.xSpaceOpt:()V
	aload_0
	ldc_w	int 61
	invokeinterface	InterfaceMethod scala/xml/parsing/MarkupParserCommon.xToken:(C)V
	aload_0
	invokeinterface	InterfaceMethod scala/xml/parsing/MarkupParserCommon.xSpaceOpt:()V
	return
  Labels:
  LocalVariableTable: 
   Start  Length  Slot  Name   Signature
   0      22      0    $this       Lscala/xml/parsing/MarkupParserCommon;


public static void xSpaceOpt(scala.xml.parsing.MarkupParserCommon);
  Signature: (Lscala/xml/parsing/MarkupParserCommon;)V
  Code:
   Stack=2, Locals=1, Args_size=1
l2	aload_0
	aload_0
	invokeinterface	InterfaceMethod scala/xml/parsing/MarkupParserCommon.ch:()C
	invokeinterface	InterfaceMethod scala/xml/parsing/TokenTests.isSpace:(C)Z
	ifeq	l1 // return
	aload_0
	invokeinterface	InterfaceMethod scala/xml/parsing/MarkupParserCommon.eof:()Z
	ifne	l1 // return
	aload_0
	invokeinterface	InterfaceMethod scala/xml/parsing/MarkupParserCommon.nextch:()C
	pop
	goto	l2 // aload_0
l1	return
  Labels:
   	l2 = 0 // aload_0
   	l1 = 34 // return
  LocalVariableTable: 
   Start  Length  Slot  Name   Signature
   0      35      0    $this       Lscala/xml/parsing/MarkupParserCommon;


public static void xSpace(scala.xml.parsing.MarkupParserCommon);
  Signature: (Lscala/xml/parsing/MarkupParserCommon;)V
  Code:
   Stack=3, Locals=1, Args_size=1
	aload_0
	aload_0
	invokeinterface	InterfaceMethod scala/xml/parsing/MarkupParserCommon.ch:()C
	invokeinterface	InterfaceMethod scala/xml/parsing/TokenTests.isSpace:(C)Z
	ifeq	l1 // aload_0
	aload_0
	invokeinterface	InterfaceMethod scala/xml/parsing/MarkupParserCommon.nextch:()C
	pop
	aload_0
	invokeinterface	InterfaceMethod scala/xml/parsing/MarkupParserCommon.xSpaceOpt:()V
	goto	l2 // return
l1	aload_0
	aload_0
	invokeinterface	InterfaceMethod scala/xml/parsing/MarkupParserCommon.ch:()C
	ldc_w	String whitespace expected
	invokeinterface	InterfaceMethod scala/xml/parsing/MarkupParserCommon.xHandleError:(CLjava/lang/String;)V
l2	return
  Labels:
   	l1 = 31 // aload_0
   	l2 = 46 // return
  LocalVariableTable: 
   Start  Length  Slot  Name   Signature
   0      47      0    $this       Lscala/xml/parsing/MarkupParserCommon;


public static java.lang.Object returning(scala.xml.parsing.MarkupParserCommon, java.lang.Object, scala.Function1);
  Signature: (Lscala/xml/parsing/MarkupParserCommon;Ljava/lang/Object;Lscala/Function1;)Ljava/lang/Object;
  Code:
   Stack=2, Locals=3, Args_size=3
	aload_2
	aload_1
	invokeinterface	InterfaceMethod scala/Function1.apply:(Ljava/lang/Object;)Ljava/lang/Object;
	pop
	aload_1
	areturn
  Labels:
  LocalVariableTable: 
   Start  Length  Slot  Name   Signature
   0      10      0    $this       Lscala/xml/parsing/MarkupParserCommon;
   0      10      1    x       Ljava/lang/Object;
   0      10      2    f       Lscala/Function1;


public static java.lang.Object saving(scala.xml.parsing.MarkupParserCommon, java.lang.Object, scala.Function1, scala.Function0);
  Signature: (Lscala/xml/parsing/MarkupParserCommon;Ljava/lang/Object;Lscala/Function1;Lscala/Function0;)Ljava/lang/Object;
  Code:
   Stack=2, Locals=6, Args_size=4
	aload_3
	invokeinterface	InterfaceMethod scala/Function0.apply:()Ljava/lang/Object;
	astore	4
	aload_2
	aload_1
	invokeinterface	InterfaceMethod scala/Function1.apply:(Ljava/lang/Object;)Ljava/lang/Object;
	pop
	aload	4
	areturn
	astore	5
	aload_2
	aload_1
	invokeinterface	InterfaceMethod scala/Function1.apply:(Ljava/lang/Object;)Ljava/lang/Object;
	pop
	aload	5
	athrow
  Labels:
  Exception table:
   from   to  target type
     0     8    19   any
  LocalVariableTable: 
   Start  Length  Slot  Name   Signature
   0      32      0    $this       Lscala/xml/parsing/MarkupParserCommon;
   0      32      1    getter       Ljava/lang/Object;
   0      32      2    setter       Lscala/Function1;
   0      32      3    body       Lscala/Function0;
   0      18      4    exceptionResult1       Ljava/lang/Object;
   19      13      4    exceptionResult1       Ljava/lang/Object;


public static java.lang.Object xTakeUntil(scala.xml.parsing.MarkupParserCommon, scala.Function2, scala.Function0, java.lang.String);
  Signature: (Lscala/xml/parsing/MarkupParserCommon;Lscala/Function2;Lscala/Function0;Ljava/lang/String;)Ljava/lang/Object;
  Code:
   Stack=3, Locals=9, Args_size=4
	new	class scala/collection/mutable/StringBuilder
	dup
	invokespecial	Method scala/collection/mutable/StringBuilder."<init>":()V
	astore	8
	aload_3
	iconst_0
	invokevirtual	Method java/lang/String.charAt:(I)C
	istore	6
	new	class scala/collection/immutable/StringOps
	dup
	aload_3
	invokespecial	Method scala/collection/immutable/StringOps."<init>":(Ljava/lang/String;)V
	iconst_1
	istore	5
	astore	4
	aload	4
	iload	5
	invokestatic	Method scala/collection/IndexedSeqOptimized$class.drop:(Lscala/collection/IndexedSeqOptimized;I)Ljava/lang/Object;
	checkcast	class java/lang/String
	astore	7
l3	aload_0
	invokeinterface	InterfaceMethod scala/xml/parsing/MarkupParserCommon.ch:()C
	iload	6
	if_icmpne	l1 // aload_0
	aload_0
	aload	7
	invokestatic	Method peek:(Lscala/xml/parsing/MarkupParserCommon;Ljava/lang/String;)Z
	ifeq	l1 // aload_0
	aload_1
	aload_2
	invokeinterface	InterfaceMethod scala/Function0.apply:()Ljava/lang/Object;
	aload	8
	invokevirtual	Method scala/collection/mutable/StringBuilder.toString:()Ljava/lang/String;
	invokeinterface	InterfaceMethod scala/Function2.apply:(Ljava/lang/Object;Ljava/lang/Object;)Ljava/lang/Object;
	areturn
l1	aload_0
	invokeinterface	InterfaceMethod scala/xml/parsing/MarkupParserCommon.ch:()C
	ldc	int 26
	if_icmpne	l2 // aload
	aload_0
	ldc	String 
	invokeinterface	InterfaceMethod scala/xml/parsing/MarkupParserCommon.truncatedError:(Ljava/lang/String;)Lscala/runtime/Nothing$;
	athrow
l2	aload	8
	aload_0
	invokeinterface	InterfaceMethod scala/xml/parsing/MarkupParserCommon.ch:()C
	invokevirtual	Method scala/collection/mutable/StringBuilder.append:(C)Lscala/collection/mutable/StringBuilder;
	pop
	aload_0
	invokeinterface	InterfaceMethod scala/xml/parsing/MarkupParserCommon.nextch:()C
	pop
	goto	l3 // aload_0
  Labels:
   	l3 = 41 // aload_0
   	l1 = 79 // aload_0
   	l2 = 99 // aload
  LocalVariableTable: 
   Start  Length  Slot  Name   Signature
   0      121      0    $this       Lscala/xml/parsing/MarkupParserCommon;
   0      121      1    handler       Lscala/Function2;
   0      121      2    positioner       Lscala/Function0;
   0      121      3    until       Ljava/lang/String;
   16      105      6    head       C
   41      80      7    rest       Ljava/lang/String;
   9      112      8    sb       Lscala/collection/mutable/StringBuilder;


private static boolean peek(scala.xml.parsing.MarkupParserCommon, java.lang.String);
  Signature: (Lscala/xml/parsing/MarkupParserCommon;Ljava/lang/String;)Z
  Code:
   Stack=4, Locals=5, Args_size=2
	aload_0
	invokeinterface	InterfaceMethod scala/xml/parsing/MarkupParserCommon.lookahead:()Lscala/collection/BufferedIterator;
	aload_1
	invokevirtual	Method java/lang/String.length:()I
	invokeinterface	InterfaceMethod scala/collection/Iterator.take:(I)Lscala/collection/Iterator;
	new	class scala/collection/immutable/StringOps
	dup
	aload_1
	invokespecial	Method scala/collection/immutable/StringOps."<init>":(Ljava/lang/String;)V
	astore_2
	aload_2
	invokestatic	Method scala/collection/IndexedSeqLike$class.iterator:(Lscala/collection/IndexedSeqLike;)Lscala/collection/Iterator;
	invokeinterface	InterfaceMethod scala/collection/Iterator.sameElements:(Lscala/collection/Iterator;)Z
	ifeq	l1 // iconst_0
	aload_1
	invokevirtual	Method java/lang/String.length:()I
	istore	4
	iconst_0
	istore_3
	new	class scala/collection/immutable/Range$$anon$1
	dup
	iload_3
	iload	4
	invokespecial	Method scala/collection/immutable/Range$$anon$1."<init>":(II)V
	checkcast	class scala/collection/immutable/Range$ByOne
	new	class scala/xml/parsing/MarkupParserCommon$$anonfun$peek$1
	dup
	aload_0
	invokespecial	Method scala/xml/parsing/MarkupParserCommon$$anonfun$peek$1."<init>":(Lscala/xml/parsing/MarkupParserCommon;)V
	invokeinterface	InterfaceMethod scala/collection/immutable/Range$ByOne.foreach:(Lscala/Function1;)V
	iconst_1
	ifeq	l1 // iconst_0
	iconst_1
	goto	l2 // ireturn
l1	iconst_0
l2	ireturn
  Labels:
   	l1 = 78 // iconst_0
   	l2 = 79 // ireturn
  LocalVariableTable: 
   Start  Length  Slot  Name   Signature
   0      80      0    $this       Lscala/xml/parsing/MarkupParserCommon;
   0      80      1    lookingFor       Ljava/lang/String;


private static final boolean gd1$1(scala.xml.parsing.MarkupParserCommon, scala.collection.BufferedIterator);
  Signature: (Lscala/xml/parsing/MarkupParserCommon;Lscala/collection/BufferedIterator;)Z
  Code:
   Stack=2, Locals=2, Args_size=2
	aload_1
	invokeinterface	InterfaceMethod scala/collection/BufferedIterator.head:()Ljava/lang/Object;
	invokestatic	Method scala/runtime/BoxesRunTime.unboxToChar:(Ljava/lang/Object;)C
	ldc_w	int 35
	if_icmpne	l1 // iconst_0
	iconst_1
	goto	l2 // ireturn
l1	iconst_0
l2	ireturn
  Labels:
   	l1 = 19 // iconst_0
   	l2 = 20 // ireturn
  LocalVariableTable: 
   Start  Length  Slot  Name   Signature
   0      21      0    $this       Lscala/xml/parsing/MarkupParserCommon;


public static void $init$(scala.xml.parsing.MarkupParserCommon);
  Signature: (Lscala/xml/parsing/MarkupParserCommon;)V
  Code:
   Stack=0, Locals=1, Args_size=1
	return
  Labels:
  LocalVariableTable: 
   Start  Length  Slot  Name   Signature
   0      1      0    $this       Lscala/xml/parsing/MarkupParserCommon;


}

