Compiled from "NoBindingFactoryAdapter.scala"
public class scala.xml.parsing.NoBindingFactoryAdapter extends scala.xml.parsing.FactoryAdapter implements scala.xml.factory.NodeFactory,scala.ScalaObject
  SourceFile: "NoBindingFactoryAdapter.scala"
  Signature: length = 0x2
   00 FFFFFF89 
  ScalaSig: length = 0x2C2
   05 00 6B 06 08 01 02 FFFFFF84 FFFFFF80 FFFFFF80 FFFFFF80 00 09 02 17 4E
   6F 42 69 6E 64 69 6E 67 46 61 63 74 6F 72 79 41
   64 61 70 74 65 72 0A 02 03 04 01 07 70 61 72 73
   69 6E 67 0A 02 05 06 01 03 78 6D 6C 0A 01 07 01
   05 73 63 61 6C 61 03 00 13 04 00 0A 0E 18 10 02
   0B 0C 0D 01 02 09 02 0D 02 02 0E 46 61 63 74 6F
   72 79 41 64 61 70 74 65 72 10 03 0F 12 14 0D 01
   10 0A 02 11 04 01 07 66 61 63 74 6F 72 79 09 02
   13 10 02 0B 4E 6F 64 65 46 61 63 74 6F 72 79 10
   02 15 16 0D 01 04 09 02 17 04 02 04 45 6C 65 6D
   10 02 19 1A 0D 01 06 09 02 1B 06 02 0B 53 63 61
   6C 61 4F 62 6A 65 63 74 08 05 1D 00 FFFFFF84 00 1E 01
   06 3C 69 6E 69 74 3E 14 01 1F 10 02 0B 00 08 05
   21 00 FFFFFF84 00 22 01 10 6E 6F 64 65 43 6F 6E 74 61
   69 6E 73 54 65 78 74 14 02 23 26 10 02 19 24 09
   02 25 06 02 07 42 6F 6F 6C 65 61 6E 08 05 27 20
   FFFFFFC0 00 28 01 05 6C 61 62 65 6C 10 02 29 2C 0E 02
   19 2A 09 02 2B 06 01 06 50 72 65 64 65 66 09 02
   2D 2E 02 06 53 74 72 69 6E 67 0A 02 2B 06 08 05
   30 00 FFFFFF84 08 31 01 06 63 72 65 61 74 65 14 06 14
   32 34 35 3A 3F 08 05 33 2F FFFFFFC0 00 28 01 03 70 72
   65 08 05 27 2F FFFFFFC0 00 28 08 05 36 2F FFFFFFC0 00 37 01
   05 61 74 74 72 73 10 02 15 38 09 02 39 04 02 08
   4D 65 74 61 44 61 74 61 08 05 3B 2F FFFFFFC0 00 3C 01
   05 73 63 6F 70 65 10 02 15 3D 09 02 3E 04 02 10
   4E 61 6D 65 73 70 61 63 65 42 69 6E 64 69 6E 67
   08 05 40 2F FFFFFFC0 00 41 01 08 63 68 69 6C 64 72 65
   6E 10 03 42 45 47 0D 01 43 0A 02 44 06 01 0A 63
   6F 6C 6C 65 63 74 69 6F 6E 09 02 46 43 02 03 53
   65 71 10 02 15 48 09 02 49 04 02 04 4E 6F 64 65
   08 05 4B 00 FFFFFF84 00 4C 01 0A 63 72 65 61 74 65 4E
   6F 64 65 14 06 14 4D 4E 4F 50 51 08 05 33 4A FFFFFFC0
   00 28 08 05 27 4A FFFFFFC0 00 28 08 05 36 4A FFFFFFC0 00 37
   08 05 3B 4A FFFFFFC0 00 3C 08 05 40 4A FFFFFFC0 00 52 10 03
   53 56 47 0D 01 54 0A 02 55 43 01 09 69 6D 6D 75
   74 61 62 6C 65 09 02 57 54 02 04 4C 69 73 74 08
   05 59 00 FFFFFF84 00 5A 01 0A 63 72 65 61 74 65 54 65
   78 74 14 02 5B 5E 10 02 15 5C 09 02 5D 04 02 04
   54 65 78 74 08 05 5F 58 FFFFFFC0 00 28 01 04 74 65 78
   74 08 05 61 00 FFFFFF84 00 62 01 0F 63 72 65 61 74 65
   50 72 6F 63 49 6E 73 74 72 14 03 63 67 69 10 03
   42 45 64 10 02 15 65 09 02 66 04 02 09 50 72 6F
   63 49 6E 73 74 72 08 05 68 60 FFFFFFC0 00 28 01 06 74
   61 72 67 65 74 08 05 6A 60 FFFFFFC0 00 28 01 04 64 61
   74 61 
  minor version: 0
  major version: 49
  Constant pool:
Asciz	SourceFile;
Asciz	NoBindingFactoryAdapter.scala;
Asciz	cache;
Asciz	Lscala/collection/mutable/HashMap;;
Asciz	ignoreProcInstr;
Asciz	Z;
Asciz	ignoreComments;
Asciz	()Z;
Asciz	Code;
Asciz	LineNumberTable;
Asciz	scala/xml/parsing/NoBindingFactoryAdapter;
class	scala/xml/parsing/NoBindingFactoryAdapter
NameAndType	ignoreComments:Z
Field	scala/xml/parsing/NoBindingFactoryAdapter.ignoreComments:Z
NameAndType	ignoreProcInstr:Z
Field	scala/xml/parsing/NoBindingFactoryAdapter.ignoreProcInstr:Z
Asciz	()Lscala/collection/mutable/HashMap;;
NameAndType	cache:Lscala/collection/mutable/HashMap;
Field	scala/xml/parsing/NoBindingFactoryAdapter.cache:Lscala/collection/mutable/HashMap;
Asciz	scala$xml$factory$NodeFactory$_setter_$ignoreComments_$eq;
Asciz	(Z)V;
Asciz	scala$xml$factory$NodeFactory$_setter_$ignoreProcInstr_$eq;
Asciz	scala$xml$factory$NodeFactory$_setter_$cache_$eq;
Asciz	(Lscala/collection/mutable/HashMap;)V;
Asciz	construct;
Asciz	(ILscala/collection/immutable/List;Ljava/lang/String;Ljava/lang/String;Lscala/xml/MetaData;Lscala/xml/NamespaceBinding;Lscala/collection/Seq;)Lscala/xml/Node;;
Asciz	scala/xml/factory/NodeFactory$class;
class	scala/xml/factory/NodeFactory$class
Asciz	(Lscala/xml/factory/NodeFactory;ILscala/collection/immutable/List;Ljava/lang/String;Ljava/lang/String;Lscala/xml/MetaData;Lscala/xml/NamespaceBinding;Lscala/collection/Seq;)Lscala/xml/Node;;
NameAndType	construct:(Lscala/xml/factory/NodeFactory;ILscala/collection/immutable/List;Ljava/lang/String;Ljava/lang/String;Lscala/xml/MetaData;Lscala/xml/NamespaceBinding;Lscala/collection/Seq;)Lscala/xml/Node;
Method	scala/xml/factory/NodeFactory$class.construct:(Lscala/xml/factory/NodeFactory;ILscala/collection/immutable/List;Ljava/lang/String;Ljava/lang/String;Lscala/xml/MetaData;Lscala/xml/NamespaceBinding;Lscala/collection/Seq;)Lscala/xml/Node;
Asciz	this;
Asciz	Lscala/xml/parsing/NoBindingFactoryAdapter;;
Asciz	hash;
Asciz	I;
Asciz	old;
Asciz	Lscala/collection/immutable/List;;
Asciz	pre;
Asciz	Ljava/lang/String;;
Asciz	name;
Asciz	attrSeq;
Asciz	Lscala/xml/MetaData;;
Asciz	scope;
Asciz	Lscala/xml/NamespaceBinding;;
Asciz	children;
Asciz	Lscala/collection/Seq;;
Asciz	LocalVariableTable;
Asciz	eqElements;
Asciz	(Lscala/collection/Seq;Lscala/collection/Seq;)Z;
Asciz	(Lscala/xml/factory/NodeFactory;Lscala/collection/Seq;Lscala/collection/Seq;)Z;
NameAndType	eqElements:(Lscala/xml/factory/NodeFactory;Lscala/collection/Seq;Lscala/collection/Seq;)Z
Method	scala/xml/factory/NodeFactory$class.eqElements:(Lscala/xml/factory/NodeFactory;Lscala/collection/Seq;Lscala/collection/Seq;)Z
Asciz	ch1;
Asciz	ch2;
Asciz	nodeEquals;
Asciz	(Lscala/xml/Node;Ljava/lang/String;Ljava/lang/String;Lscala/xml/MetaData;Lscala/xml/NamespaceBinding;Lscala/collection/Seq;)Z;
Asciz	(Lscala/xml/factory/NodeFactory;Lscala/xml/Node;Ljava/lang/String;Ljava/lang/String;Lscala/xml/MetaData;Lscala/xml/NamespaceBinding;Lscala/collection/Seq;)Z;
NameAndType	nodeEquals:(Lscala/xml/factory/NodeFactory;Lscala/xml/Node;Ljava/lang/String;Ljava/lang/String;Lscala/xml/MetaData;Lscala/xml/NamespaceBinding;Lscala/collection/Seq;)Z
Method	scala/xml/factory/NodeFactory$class.nodeEquals:(Lscala/xml/factory/NodeFactory;Lscala/xml/Node;Ljava/lang/String;Ljava/lang/String;Lscala/xml/MetaData;Lscala/xml/NamespaceBinding;Lscala/collection/Seq;)Z
Asciz	n;
Asciz	Lscala/xml/Node;;
Asciz	makeNode;
Asciz	(Ljava/lang/String;Ljava/lang/String;Lscala/xml/MetaData;Lscala/xml/NamespaceBinding;Lscala/collection/Seq;)Lscala/xml/Node;;
Asciz	(Lscala/xml/factory/NodeFactory;Ljava/lang/String;Ljava/lang/String;Lscala/xml/MetaData;Lscala/xml/NamespaceBinding;Lscala/collection/Seq;)Lscala/xml/Node;;
NameAndType	makeNode:(Lscala/xml/factory/NodeFactory;Ljava/lang/String;Ljava/lang/String;Lscala/xml/MetaData;Lscala/xml/NamespaceBinding;Lscala/collection/Seq;)Lscala/xml/Node;
Method	scala/xml/factory/NodeFactory$class.makeNode:(Lscala/xml/factory/NodeFactory;Ljava/lang/String;Ljava/lang/String;Lscala/xml/MetaData;Lscala/xml/NamespaceBinding;Lscala/collection/Seq;)Lscala/xml/Node;
Asciz	makeText;
Asciz	(Ljava/lang/String;)Lscala/xml/Text;;
Asciz	(Lscala/xml/factory/NodeFactory;Ljava/lang/String;)Lscala/xml/Text;;
NameAndType	makeText:(Lscala/xml/factory/NodeFactory;Ljava/lang/String;)Lscala/xml/Text;
Method	scala/xml/factory/NodeFactory$class.makeText:(Lscala/xml/factory/NodeFactory;Ljava/lang/String;)Lscala/xml/Text;
Asciz	s;
Asciz	makeComment;
Asciz	(Ljava/lang/String;)Lscala/collection/Seq;;
Asciz	(Lscala/xml/factory/NodeFactory;Ljava/lang/String;)Lscala/collection/Seq;;
NameAndType	makeComment:(Lscala/xml/factory/NodeFactory;Ljava/lang/String;)Lscala/collection/Seq;
Method	scala/xml/factory/NodeFactory$class.makeComment:(Lscala/xml/factory/NodeFactory;Ljava/lang/String;)Lscala/collection/Seq;
Asciz	makeProcInstr;
Asciz	(Ljava/lang/String;Ljava/lang/String;)Lscala/collection/Seq;;
Asciz	(Lscala/xml/factory/NodeFactory;Ljava/lang/String;Ljava/lang/String;)Lscala/collection/Seq;;
NameAndType	makeProcInstr:(Lscala/xml/factory/NodeFactory;Ljava/lang/String;Ljava/lang/String;)Lscala/collection/Seq;
Method	scala/xml/factory/NodeFactory$class.makeProcInstr:(Lscala/xml/factory/NodeFactory;Ljava/lang/String;Ljava/lang/String;)Lscala/collection/Seq;
Asciz	t;
Asciz	nodeContainsText;
Asciz	(Ljava/lang/String;)Z;
Asciz	label;
Asciz	create;
Asciz	(Ljava/lang/String;Ljava/lang/String;Lscala/xml/MetaData;Lscala/xml/NamespaceBinding;Lscala/collection/Seq;)Lscala/xml/Elem;;
Asciz	scala/xml/Elem$;
class	scala/xml/Elem$
Asciz	MODULE$;
Asciz	Lscala/xml/Elem$;;
NameAndType	MODULE$:Lscala/xml/Elem$;
Field	scala/xml/Elem$.MODULE$:Lscala/xml/Elem$;
Asciz	apply;
NameAndType	apply:(Ljava/lang/String;Ljava/lang/String;Lscala/xml/MetaData;Lscala/xml/NamespaceBinding;Lscala/collection/Seq;)Lscala/xml/Elem;
Method	scala/xml/Elem$.apply:(Ljava/lang/String;Ljava/lang/String;Lscala/xml/MetaData;Lscala/xml/NamespaceBinding;Lscala/collection/Seq;)Lscala/xml/Elem;
Asciz	attrs;
Asciz	(Ljava/lang/String;Ljava/lang/String;Lscala/xml/MetaData;Lscala/xml/NamespaceBinding;Lscala/collection/Seq<Lscala/xml/Node;>;)Lscala/xml/Elem;;
Asciz	Signature;
Asciz	createNode;
Asciz	(Ljava/lang/String;Ljava/lang/String;Lscala/xml/MetaData;Lscala/xml/NamespaceBinding;Lscala/collection/immutable/List;)Lscala/xml/Elem;;
Asciz	(Ljava/lang/String;Ljava/lang/String;Lscala/xml/MetaData;Lscala/xml/NamespaceBinding;Lscala/collection/immutable/List<Lscala/xml/Node;>;)Lscala/xml/Elem;;
Asciz	createText;
Asciz	scala/xml/Text;
class	scala/xml/Text
Asciz	<init>;
Asciz	(Ljava/lang/String;)V;
NameAndType	"<init>":(Ljava/lang/String;)V
Method	scala/xml/Text."<init>":(Ljava/lang/String;)V
Asciz	text;
Asciz	createProcInstr;
Asciz	scala/xml/factory/NodeFactory;
class	scala/xml/factory/NodeFactory
NameAndType	makeProcInstr:(Ljava/lang/String;Ljava/lang/String;)Lscala/collection/Seq;
InterfaceMethod	scala/xml/factory/NodeFactory.makeProcInstr:(Ljava/lang/String;Ljava/lang/String;)Lscala/collection/Seq;
Asciz	target;
Asciz	data;
Asciz	(Ljava/lang/String;Ljava/lang/String;)Lscala/collection/Seq<Lscala/xml/ProcInstr;>;;
Asciz	(Ljava/lang/String;Ljava/lang/String;Lscala/xml/MetaData;Lscala/xml/NamespaceBinding;Lscala/collection/immutable/List;)Lscala/xml/Node;;
NameAndType	createNode:(Ljava/lang/String;Ljava/lang/String;Lscala/xml/MetaData;Lscala/xml/NamespaceBinding;Lscala/collection/immutable/List;)Lscala/xml/Elem;
Method	scala/xml/parsing/NoBindingFactoryAdapter.createNode:(Ljava/lang/String;Ljava/lang/String;Lscala/xml/MetaData;Lscala/xml/NamespaceBinding;Lscala/collection/immutable/List;)Lscala/xml/Elem;
Asciz	elemName;
Asciz	attribs;
Asciz	chIter;
NameAndType	create:(Ljava/lang/String;Ljava/lang/String;Lscala/xml/MetaData;Lscala/xml/NamespaceBinding;Lscala/collection/Seq;)Lscala/xml/Elem;
Method	scala/xml/parsing/NoBindingFactoryAdapter.create:(Ljava/lang/String;Ljava/lang/String;Lscala/xml/MetaData;Lscala/xml/NamespaceBinding;Lscala/collection/Seq;)Lscala/xml/Elem;
Asciz	()V;
Asciz	scala/xml/parsing/FactoryAdapter;
class	scala/xml/parsing/FactoryAdapter
NameAndType	"<init>":()V
Method	scala/xml/parsing/FactoryAdapter."<init>":()V
Asciz	$init$;
Asciz	(Lscala/xml/factory/NodeFactory;)V;
NameAndType	$init$:(Lscala/xml/factory/NodeFactory;)V
Method	scala/xml/factory/NodeFactory$class.$init$:(Lscala/xml/factory/NodeFactory;)V
Asciz	Lscala/xml/parsing/FactoryAdapter;Lscala/xml/factory/NodeFactory<Lscala/xml/Elem;>;Lscala/ScalaObject;;
Asciz	ScalaSig;
Asciz	scala/ScalaObject;
class	scala/ScalaObject

{
private final scala.collection.mutable.HashMap cache;
  Signature: Lscala/collection/mutable/HashMap;

private final boolean ignoreProcInstr;
  Signature: Z

private final boolean ignoreComments;
  Signature: Z

public boolean ignoreComments();
  Signature: ()Z
  Code:
   Stack=1, Locals=1, Args_size=1
	aload_0
	getfield	Field ignoreComments:Z
	ireturn
  Labels:

public boolean ignoreProcInstr();
  Signature: ()Z
  Code:
   Stack=1, Locals=1, Args_size=1
	aload_0
	getfield	Field ignoreProcInstr:Z
	ireturn
  Labels:

public scala.collection.mutable.HashMap cache();
  Signature: ()Lscala/collection/mutable/HashMap;
  Code:
   Stack=1, Locals=1, Args_size=1
	aload_0
	getfield	Field cache:Lscala/collection/mutable/HashMap;
	areturn
  Labels:

public void scala$xml$factory$NodeFactory$_setter_$ignoreComments_$eq(boolean);
  Signature: (Z)V
  Code:
   Stack=2, Locals=2, Args_size=2
	aload_0
	iload_1
	putfield	Field ignoreComments:Z
	return
  Labels:

public void scala$xml$factory$NodeFactory$_setter_$ignoreProcInstr_$eq(boolean);
  Signature: (Z)V
  Code:
   Stack=2, Locals=2, Args_size=2
	aload_0
	iload_1
	putfield	Field ignoreProcInstr:Z
	return
  Labels:

public void scala$xml$factory$NodeFactory$_setter_$cache_$eq(scala.collection.mutable.HashMap);
  Signature: (Lscala/collection/mutable/HashMap;)V
  Code:
   Stack=2, Locals=2, Args_size=2
	aload_0
	aload_1
	putfield	Field cache:Lscala/collection/mutable/HashMap;
	return
  Labels:

public scala.xml.Node construct(int, scala.collection.immutable.List, java.lang.String, java.lang.String, scala.xml.MetaData, scala.xml.NamespaceBinding, scala.collection.Seq);
  Signature: (ILscala/collection/immutable/List;Ljava/lang/String;Ljava/lang/String;Lscala/xml/MetaData;Lscala/xml/NamespaceBinding;Lscala/collection/Seq;)Lscala/xml/Node;
  Code:
   Stack=8, Locals=8, Args_size=8
	aload_0
	iload_1
	aload_2
	aload_3
	aload	4
	aload	5
	aload	6
	aload	7
	invokestatic	Method scala/xml/factory/NodeFactory$class.construct:(Lscala/xml/factory/NodeFactory;ILscala/collection/immutable/List;Ljava/lang/String;Ljava/lang/String;Lscala/xml/MetaData;Lscala/xml/NamespaceBinding;Lscala/collection/Seq;)Lscala/xml/Node;
	areturn
  Labels:
  LocalVariableTable: 
   Start  Length  Slot  Name   Signature
   0      16      0    this       Lscala/xml/parsing/NoBindingFactoryAdapter;
   0      16      1    hash       I
   0      16      2    old       Lscala/collection/immutable/List;
   0      16      3    pre       Ljava/lang/String;
   0      16      4    name       Ljava/lang/String;
   0      16      5    attrSeq       Lscala/xml/MetaData;
   0      16      6    scope       Lscala/xml/NamespaceBinding;
   0      16      7    children       Lscala/collection/Seq;


public boolean eqElements(scala.collection.Seq, scala.collection.Seq);
  Signature: (Lscala/collection/Seq;Lscala/collection/Seq;)Z
  Code:
   Stack=3, Locals=3, Args_size=3
	aload_0
	aload_1
	aload_2
	invokestatic	Method scala/xml/factory/NodeFactory$class.eqElements:(Lscala/xml/factory/NodeFactory;Lscala/collection/Seq;Lscala/collection/Seq;)Z
	ireturn
  Labels:
  LocalVariableTable: 
   Start  Length  Slot  Name   Signature
   0      7      0    this       Lscala/xml/parsing/NoBindingFactoryAdapter;
   0      7      1    ch1       Lscala/collection/Seq;
   0      7      2    ch2       Lscala/collection/Seq;


public boolean nodeEquals(scala.xml.Node, java.lang.String, java.lang.String, scala.xml.MetaData, scala.xml.NamespaceBinding, scala.collection.Seq);
  Signature: (Lscala/xml/Node;Ljava/lang/String;Ljava/lang/String;Lscala/xml/MetaData;Lscala/xml/NamespaceBinding;Lscala/collection/Seq;)Z
  Code:
   Stack=7, Locals=7, Args_size=7
	aload_0
	aload_1
	aload_2
	aload_3
	aload	4
	aload	5
	aload	6
	invokestatic	Method scala/xml/factory/NodeFactory$class.nodeEquals:(Lscala/xml/factory/NodeFactory;Lscala/xml/Node;Ljava/lang/String;Ljava/lang/String;Lscala/xml/MetaData;Lscala/xml/NamespaceBinding;Lscala/collection/Seq;)Z
	ireturn
  Labels:
  LocalVariableTable: 
   Start  Length  Slot  Name   Signature
   0      14      0    this       Lscala/xml/parsing/NoBindingFactoryAdapter;
   0      14      1    n       Lscala/xml/Node;
   0      14      2    pre       Ljava/lang/String;
   0      14      3    name       Ljava/lang/String;
   0      14      4    attrSeq       Lscala/xml/MetaData;
   0      14      5    scope       Lscala/xml/NamespaceBinding;
   0      14      6    children       Lscala/collection/Seq;


public scala.xml.Node makeNode(java.lang.String, java.lang.String, scala.xml.MetaData, scala.xml.NamespaceBinding, scala.collection.Seq);
  Signature: (Ljava/lang/String;Ljava/lang/String;Lscala/xml/MetaData;Lscala/xml/NamespaceBinding;Lscala/collection/Seq;)Lscala/xml/Node;
  Code:
   Stack=6, Locals=6, Args_size=6
	aload_0
	aload_1
	aload_2
	aload_3
	aload	4
	aload	5
	invokestatic	Method scala/xml/factory/NodeFactory$class.makeNode:(Lscala/xml/factory/NodeFactory;Ljava/lang/String;Ljava/lang/String;Lscala/xml/MetaData;Lscala/xml/NamespaceBinding;Lscala/collection/Seq;)Lscala/xml/Node;
	areturn
  Labels:
  LocalVariableTable: 
   Start  Length  Slot  Name   Signature
   0      12      0    this       Lscala/xml/parsing/NoBindingFactoryAdapter;
   0      12      1    pre       Ljava/lang/String;
   0      12      2    name       Ljava/lang/String;
   0      12      3    attrSeq       Lscala/xml/MetaData;
   0      12      4    scope       Lscala/xml/NamespaceBinding;
   0      12      5    children       Lscala/collection/Seq;


public scala.xml.Text makeText(java.lang.String);
  Signature: (Ljava/lang/String;)Lscala/xml/Text;
  Code:
   Stack=2, Locals=2, Args_size=2
	aload_0
	aload_1
	invokestatic	Method scala/xml/factory/NodeFactory$class.makeText:(Lscala/xml/factory/NodeFactory;Ljava/lang/String;)Lscala/xml/Text;
	areturn
  Labels:
  LocalVariableTable: 
   Start  Length  Slot  Name   Signature
   0      6      0    this       Lscala/xml/parsing/NoBindingFactoryAdapter;
   0      6      1    s       Ljava/lang/String;


public scala.collection.Seq makeComment(java.lang.String);
  Signature: (Ljava/lang/String;)Lscala/collection/Seq;
  Code:
   Stack=2, Locals=2, Args_size=2
	aload_0
	aload_1
	invokestatic	Method scala/xml/factory/NodeFactory$class.makeComment:(Lscala/xml/factory/NodeFactory;Ljava/lang/String;)Lscala/collection/Seq;
	areturn
  Labels:
  LocalVariableTable: 
   Start  Length  Slot  Name   Signature
   0      6      0    this       Lscala/xml/parsing/NoBindingFactoryAdapter;
   0      6      1    s       Ljava/lang/String;


public scala.collection.Seq makeProcInstr(java.lang.String, java.lang.String);
  Signature: (Ljava/lang/String;Ljava/lang/String;)Lscala/collection/Seq;
  Code:
   Stack=3, Locals=3, Args_size=3
	aload_0
	aload_1
	aload_2
	invokestatic	Method scala/xml/factory/NodeFactory$class.makeProcInstr:(Lscala/xml/factory/NodeFactory;Ljava/lang/String;Ljava/lang/String;)Lscala/collection/Seq;
	areturn
  Labels:
  LocalVariableTable: 
   Start  Length  Slot  Name   Signature
   0      7      0    this       Lscala/xml/parsing/NoBindingFactoryAdapter;
   0      7      1    t       Ljava/lang/String;
   0      7      2    s       Ljava/lang/String;


public boolean nodeContainsText(java.lang.String);
  Signature: (Ljava/lang/String;)Z
  Code:
   Stack=1, Locals=2, Args_size=2
	iconst_1
	ireturn
  Labels:
  LocalVariableTable: 
   Start  Length  Slot  Name   Signature
   0      2      0    this       Lscala/xml/parsing/NoBindingFactoryAdapter;
   0      2      1    label       Ljava/lang/String;


public scala.xml.Elem create(java.lang.String, java.lang.String, scala.xml.MetaData, scala.xml.NamespaceBinding, scala.collection.Seq);
  Signature: (Ljava/lang/String;Ljava/lang/String;Lscala/xml/MetaData;Lscala/xml/NamespaceBinding;Lscala/collection/Seq;)Lscala/xml/Elem;
  Code:
   Stack=6, Locals=6, Args_size=6
	getstatic	Field scala/xml/Elem$.MODULE$:Lscala/xml/Elem$;
	aload_1
	aload_2
	aload_3
	aload	4
	aload	5
	invokevirtual	Method scala/xml/Elem$.apply:(Ljava/lang/String;Ljava/lang/String;Lscala/xml/MetaData;Lscala/xml/NamespaceBinding;Lscala/collection/Seq;)Lscala/xml/Elem;
	areturn
  Labels:
  LocalVariableTable: 
   Start  Length  Slot  Name   Signature
   0      14      0    this       Lscala/xml/parsing/NoBindingFactoryAdapter;
   0      14      1    pre       Ljava/lang/String;
   0      14      2    label       Ljava/lang/String;
   0      14      3    attrs       Lscala/xml/MetaData;
   0      14      4    scope       Lscala/xml/NamespaceBinding;
   0      14      5    children       Lscala/collection/Seq;

  Signature: length = 0x2
   00 63 

public scala.xml.Elem createNode(java.lang.String, java.lang.String, scala.xml.MetaData, scala.xml.NamespaceBinding, scala.collection.immutable.List);
  Signature: (Ljava/lang/String;Ljava/lang/String;Lscala/xml/MetaData;Lscala/xml/NamespaceBinding;Lscala/collection/immutable/List;)Lscala/xml/Elem;
  Code:
   Stack=6, Locals=6, Args_size=6
	getstatic	Field scala/xml/Elem$.MODULE$:Lscala/xml/Elem$;
	aload_1
	aload_2
	aload_3
	aload	4
	aload	5
	invokevirtual	Method scala/xml/Elem$.apply:(Ljava/lang/String;Ljava/lang/String;Lscala/xml/MetaData;Lscala/xml/NamespaceBinding;Lscala/collection/Seq;)Lscala/xml/Elem;
	areturn
  Labels:
  LocalVariableTable: 
   Start  Length  Slot  Name   Signature
   0      14      0    this       Lscala/xml/parsing/NoBindingFactoryAdapter;
   0      14      1    pre       Ljava/lang/String;
   0      14      2    label       Ljava/lang/String;
   0      14      3    attrs       Lscala/xml/MetaData;
   0      14      4    scope       Lscala/xml/NamespaceBinding;
   0      14      5    children       Lscala/collection/immutable/List;

  Signature: length = 0x2
   00 67 

public scala.xml.Text createText(java.lang.String);
  Signature: (Ljava/lang/String;)Lscala/xml/Text;
  Code:
   Stack=3, Locals=2, Args_size=2
	new	class scala/xml/Text
	dup
	aload_1
	invokespecial	Method scala/xml/Text."<init>":(Ljava/lang/String;)V
	areturn
  Labels:
  LocalVariableTable: 
   Start  Length  Slot  Name   Signature
   0      9      0    this       Lscala/xml/parsing/NoBindingFactoryAdapter;
   0      9      1    text       Ljava/lang/String;


public scala.collection.Seq createProcInstr(java.lang.String, java.lang.String);
  Signature: (Ljava/lang/String;Ljava/lang/String;)Lscala/collection/Seq;
  Code:
   Stack=3, Locals=3, Args_size=3
	aload_0
	aload_1
	aload_2
	invokeinterface	InterfaceMethod scala/xml/factory/NodeFactory.makeProcInstr:(Ljava/lang/String;Ljava/lang/String;)Lscala/collection/Seq;
	areturn
  Labels:
  LocalVariableTable: 
   Start  Length  Slot  Name   Signature
   0      9      0    this       Lscala/xml/parsing/NoBindingFactoryAdapter;
   0      9      1    target       Ljava/lang/String;
   0      9      2    data       Ljava/lang/String;

  Signature: length = 0x2
   00 77 

public scala.xml.Node createNode(java.lang.String, java.lang.String, scala.xml.MetaData, scala.xml.NamespaceBinding, scala.collection.immutable.List);
  Signature: (Ljava/lang/String;Ljava/lang/String;Lscala/xml/MetaData;Lscala/xml/NamespaceBinding;Lscala/collection/immutable/List;)Lscala/xml/Node;
  Code:
   Stack=6, Locals=6, Args_size=6
	aload_0
	aload_1
	aload_2
	aload_3
	aload	4
	aload	5
	invokevirtual	Method createNode:(Ljava/lang/String;Ljava/lang/String;Lscala/xml/MetaData;Lscala/xml/NamespaceBinding;Lscala/collection/immutable/List;)Lscala/xml/Elem;
	areturn
  Labels:
  LocalVariableTable: 
   Start  Length  Slot  Name   Signature
   0      12      0    this       Lscala/xml/parsing/NoBindingFactoryAdapter;
   0      12      1    pre       Ljava/lang/String;
   0      12      2    elemName       Ljava/lang/String;
   0      12      3    attribs       Lscala/xml/MetaData;
   0      12      4    scope       Lscala/xml/NamespaceBinding;
   0      12      5    chIter       Lscala/collection/immutable/List;


public scala.xml.Node create(java.lang.String, java.lang.String, scala.xml.MetaData, scala.xml.NamespaceBinding, scala.collection.Seq);
  Signature: (Ljava/lang/String;Ljava/lang/String;Lscala/xml/MetaData;Lscala/xml/NamespaceBinding;Lscala/collection/Seq;)Lscala/xml/Node;
  Code:
   Stack=6, Locals=6, Args_size=6
	aload_0
	aload_1
	aload_2
	aload_3
	aload	4
	aload	5
	invokevirtual	Method create:(Ljava/lang/String;Ljava/lang/String;Lscala/xml/MetaData;Lscala/xml/NamespaceBinding;Lscala/collection/Seq;)Lscala/xml/Elem;
	areturn
  Labels:
  LocalVariableTable: 
   Start  Length  Slot  Name   Signature
   0      12      0    this       Lscala/xml/parsing/NoBindingFactoryAdapter;
   0      12      1    pre       Ljava/lang/String;
   0      12      2    name       Ljava/lang/String;
   0      12      3    attrs       Lscala/xml/MetaData;
   0      12      4    scope       Lscala/xml/NamespaceBinding;
   0      12      5    children       Lscala/collection/Seq;


public scala.xml.parsing.NoBindingFactoryAdapter();
  Signature: ()V
  Code:
   Stack=1, Locals=1, Args_size=1
	aload_0
	invokespecial	Method scala/xml/parsing/FactoryAdapter."<init>":()V
	aload_0
	invokestatic	Method scala/xml/factory/NodeFactory$class.$init$:(Lscala/xml/factory/NodeFactory;)V
	return
  Labels:

}

