Compiled from "TokenTests.scala"
public abstract class scala.xml.parsing.TokenTests$class extends java.lang.Object
  SourceFile: "TokenTests.scala"
  Scala: length = 0x
   
  InnerClass: 
   public final $anonfun$isName$1=class scala/xml/parsing/TokenTests$$anonfun$isName$1 of class scala/xml/parsing/TokenTests
   public final $anonfun$isSpace$1=class scala/xml/parsing/TokenTests$$anonfun$isSpace$1 of class scala/xml/parsing/TokenTests
   public final $anonfun$checkSysID$1=class scala/xml/parsing/TokenTests$$anonfun$checkSysID$1 of class scala/xml/parsing/TokenTests
   public final $anonfun$checkPubID$1=class scala/xml/parsing/TokenTests$$anonfun$checkPubID$1 of class scala/xml/parsing/TokenTests
   public final $anonfun$isValidIANAEncoding$1=class scala/xml/parsing/TokenTests$$anonfun$isValidIANAEncoding$1 of class scala/xml/parsing/TokenTests
  minor version: 0
  major version: 49
  Constant pool:
Asciz	SourceFile;
Asciz	TokenTests.scala;
Asciz	$init$;
Asciz	(Lscala/xml/parsing/TokenTests;)V;
Asciz	Code;
Asciz	LineNumberTable;
Asciz	$this;
Asciz	Lscala/xml/parsing/TokenTests;;
Asciz	LocalVariableTable;
Asciz	charOK$1;
Asciz	(Lscala/xml/parsing/TokenTests;C)Z;
Asciz	scala/xml/parsing/TokenTests;
class	scala/xml/parsing/TokenTests
Asciz	isAlphaDigit;
Asciz	(C)Z;
NameAndType	isAlphaDigit:(C)Z
InterfaceMethod	scala/xml/parsing/TokenTests.isAlphaDigit:(C)Z
Asciz	._-;
String	._-
Asciz	scala/collection/immutable/StringOps;
class	scala/collection/immutable/StringOps
Asciz	<init>;
Asciz	(Ljava/lang/String;)V;
NameAndType	"<init>":(Ljava/lang/String;)V
Method	scala/collection/immutable/StringOps."<init>":(Ljava/lang/String;)V
Asciz	scala/runtime/BoxesRunTime;
class	scala/runtime/BoxesRunTime
Asciz	boxToCharacter;
Asciz	(C)Ljava/lang/Character;;
NameAndType	boxToCharacter:(C)Ljava/lang/Character;
Method	scala/runtime/BoxesRunTime.boxToCharacter:(C)Ljava/lang/Character;
Asciz	scala/collection/SeqLike;
class	scala/collection/SeqLike
Asciz	contains;
Asciz	(Ljava/lang/Object;)Z;
NameAndType	contains:(Ljava/lang/Object;)Z
InterfaceMethod	scala/collection/SeqLike.contains:(Ljava/lang/Object;)Z
Asciz	c;
Asciz	C;
Asciz	checkPubID;
Asciz	(Lscala/xml/parsing/TokenTests;Ljava/lang/String;)Z;
Asciz	scala/Predef$;
class	scala/Predef$
Asciz	MODULE$;
Asciz	Lscala/Predef$;;
NameAndType	MODULE$:Lscala/Predef$;
Field	scala/Predef$.MODULE$:Lscala/Predef$;
Asciz	augmentString;
Asciz	(Ljava/lang/String;)Lscala/collection/immutable/StringOps;;
NameAndType	augmentString:(Ljava/lang/String;)Lscala/collection/immutable/StringOps;
Method	scala/Predef$.augmentString:(Ljava/lang/String;)Lscala/collection/immutable/StringOps;
Asciz	scala/xml/parsing/TokenTests$$anonfun$checkPubID$1;
class	scala/xml/parsing/TokenTests$$anonfun$checkPubID$1
NameAndType	"<init>":(Lscala/xml/parsing/TokenTests;)V
Method	scala/xml/parsing/TokenTests$$anonfun$checkPubID$1."<init>":(Lscala/xml/parsing/TokenTests;)V
Asciz	scala/collection/IndexedSeqLike;
class	scala/collection/IndexedSeqLike
Asciz	forall;
Asciz	(Lscala/Function1;)Z;
NameAndType	forall:(Lscala/Function1;)Z
InterfaceMethod	scala/collection/IndexedSeqLike.forall:(Lscala/Function1;)Z
Asciz	s;
Asciz	Ljava/lang/String;;
Asciz	checkSysID;
Asciz	scala/collection/immutable/List$;
class	scala/collection/immutable/List$
Asciz	Lscala/collection/immutable/List$;;
NameAndType	MODULE$:Lscala/collection/immutable/List$;
Field	scala/collection/immutable/List$.MODULE$:Lscala/collection/immutable/List$;
int	34;
int	39;
Asciz	wrapCharArray;
Asciz	([C)Lscala/collection/mutable/WrappedArray;;
NameAndType	wrapCharArray:([C)Lscala/collection/mutable/WrappedArray;
Method	scala/Predef$.wrapCharArray:([C)Lscala/collection/mutable/WrappedArray;
Asciz	apply;
Asciz	(Lscala/collection/Seq;)Lscala/collection/immutable/List;;
NameAndType	apply:(Lscala/collection/Seq;)Lscala/collection/immutable/List;
Method	scala/collection/immutable/List$.apply:(Lscala/collection/Seq;)Lscala/collection/immutable/List;
Asciz	scala/xml/parsing/TokenTests$$anonfun$checkSysID$1;
class	scala/xml/parsing/TokenTests$$anonfun$checkSysID$1
Asciz	(Lscala/xml/parsing/TokenTests;Ljava/lang/String;)V;
NameAndType	"<init>":(Lscala/xml/parsing/TokenTests;Ljava/lang/String;)V
Method	scala/xml/parsing/TokenTests$$anonfun$checkSysID$1."<init>":(Lscala/xml/parsing/TokenTests;Ljava/lang/String;)V
Asciz	scala/collection/LinearSeqLike;
class	scala/collection/LinearSeqLike
Asciz	exists;
NameAndType	exists:(Lscala/Function1;)Z
InterfaceMethod	scala/collection/LinearSeqLike.exists:(Lscala/Function1;)Z
Asciz	s$1;
Asciz	isValidIANAEncoding;
Asciz	(Lscala/xml/parsing/TokenTests;Lscala/collection/Seq;)Z;
Asciz	scala/collection/TraversableLike;
class	scala/collection/TraversableLike
Asciz	nonEmpty;
Asciz	()Z;
NameAndType	nonEmpty:()Z
InterfaceMethod	scala/collection/TraversableLike.nonEmpty:()Z
Asciz	scala/collection/IterableLike;
class	scala/collection/IterableLike
Asciz	head;
Asciz	()Ljava/lang/Object;;
NameAndType	head:()Ljava/lang/Object;
InterfaceMethod	scala/collection/IterableLike.head:()Ljava/lang/Object;
Asciz	unboxToChar;
Asciz	(Ljava/lang/Object;)C;
NameAndType	unboxToChar:(Ljava/lang/Object;)C
Method	scala/runtime/BoxesRunTime.unboxToChar:(Ljava/lang/Object;)C
Asciz	isAlpha;
NameAndType	isAlpha:(C)Z
InterfaceMethod	scala/xml/parsing/TokenTests.isAlpha:(C)Z
Asciz	tail;
NameAndType	tail:()Ljava/lang/Object;
InterfaceMethod	scala/collection/TraversableLike.tail:()Ljava/lang/Object;
Asciz	scala/xml/parsing/TokenTests$$anonfun$isValidIANAEncoding$1;
class	scala/xml/parsing/TokenTests$$anonfun$isValidIANAEncoding$1
Method	scala/xml/parsing/TokenTests$$anonfun$isValidIANAEncoding$1."<init>":(Lscala/xml/parsing/TokenTests;)V
InterfaceMethod	scala/collection/IterableLike.forall:(Lscala/Function1;)Z
Asciz	ianaEncoding;
Asciz	Lscala/collection/Seq;;
Asciz	isPubIDChar;
Asciz	isSpace;
NameAndType	isSpace:(C)Z
InterfaceMethod	scala/xml/parsing/TokenTests.isSpace:(C)Z
int	9;
Asciz	-\()+,./:=?;!*#@$_%;
String	-\()+,./:=?;!*#@$_%
Asciz	ch;
Asciz	isName;
InterfaceMethod	scala/collection/IndexedSeqLike.head:()Ljava/lang/Object;
Asciz	isNameStart;
NameAndType	isNameStart:(C)Z
InterfaceMethod	scala/xml/parsing/TokenTests.isNameStart:(C)Z
InterfaceMethod	scala/collection/IndexedSeqLike.tail:()Ljava/lang/Object;
Asciz	java/lang/String;
class	java/lang/String
Asciz	scala/xml/parsing/TokenTests$$anonfun$isName$1;
class	scala/xml/parsing/TokenTests$$anonfun$isName$1
Method	scala/xml/parsing/TokenTests$$anonfun$isName$1."<init>":(Lscala/xml/parsing/TokenTests;)V
Asciz	java/lang/Character;
class	java/lang/Character
Asciz	getType;
Asciz	(C)I;
NameAndType	getType:(C)I
Method	java/lang/Character.getType:(C)I
int	95;
Asciz	scala/MatchError;
class	scala/MatchError
Asciz	boxToByte;
Asciz	(B)Ljava/lang/Byte;;
NameAndType	boxToByte:(B)Ljava/lang/Byte;
Method	scala/runtime/BoxesRunTime.boxToByte:(B)Ljava/lang/Byte;
Asciz	java/lang/Object;
class	java/lang/Object
Asciz	toString;
Asciz	()Ljava/lang/String;;
NameAndType	toString:()Ljava/lang/String;
Method	java/lang/Object.toString:()Ljava/lang/String;
Method	scala/MatchError."<init>":(Ljava/lang/String;)V
Asciz	temp3;
Asciz	B;
Asciz	isNameChar;
Asciz	.-:;
String	.-:
Asciz	temp2;
int	48;
int	57;
int	65;
int	90;
int	97;
int	122;
Asciz	scala/xml/parsing/TokenTests$$anonfun$isSpace$1;
class	scala/xml/parsing/TokenTests$$anonfun$isSpace$1
Method	scala/xml/parsing/TokenTests$$anonfun$isSpace$1."<init>":(Lscala/xml/parsing/TokenTests;)V
Asciz	cs;
Asciz	Scala;
Asciz	InnerClasses;
Asciz	$anonfun$isName$1;
Asciz	$anonfun$isSpace$1;
Asciz	$anonfun$checkSysID$1;
Asciz	$anonfun$checkPubID$1;
Asciz	$anonfun$isValidIANAEncoding$1;
Asciz	scala/xml/parsing/TokenTests$class;
class	scala/xml/parsing/TokenTests$class

{
public static void $init$(scala.xml.parsing.TokenTests);
  Signature: (Lscala/xml/parsing/TokenTests;)V
  Code:
   Stack=0, Locals=1, Args_size=1
	return
  Labels:
  LocalVariableTable: 
   Start  Length  Slot  Name   Signature
   0      1      0    $this       Lscala/xml/parsing/TokenTests;


public static final boolean charOK$1(scala.xml.parsing.TokenTests, char);
  Signature: (Lscala/xml/parsing/TokenTests;C)Z
  Code:
   Stack=3, Locals=3, Args_size=2
	aload_0
	iload_1
	invokeinterface	InterfaceMethod scala/xml/parsing/TokenTests.isAlphaDigit:(C)Z
	ifne	l1 // iconst_1
	ldc	String ._-
	astore_2
	new	class scala/collection/immutable/StringOps
	dup
	aload_2
	invokespecial	Method scala/collection/immutable/StringOps."<init>":(Ljava/lang/String;)V
	iload_1
	invokestatic	Method scala/runtime/BoxesRunTime.boxToCharacter:(C)Ljava/lang/Character;
	invokeinterface	InterfaceMethod scala/collection/SeqLike.contains:(Ljava/lang/Object;)Z
	ifeq	l2 // iconst_0
l1	iconst_1
	goto	l3 // ireturn
l2	iconst_0
l3	ireturn
  Labels:
   	l1 = 33 // iconst_1
   	l2 = 37 // iconst_0
   	l3 = 38 // ireturn
  LocalVariableTable: 
   Start  Length  Slot  Name   Signature
   0      39      0    $this       Lscala/xml/parsing/TokenTests;
   0      39      1    c       C


public static boolean checkPubID(scala.xml.parsing.TokenTests, java.lang.String);
  Signature: (Lscala/xml/parsing/TokenTests;Ljava/lang/String;)Z
  Code:
   Stack=4, Locals=2, Args_size=2
	getstatic	Field scala/Predef$.MODULE$:Lscala/Predef$;
	aload_1
	invokevirtual	Method scala/Predef$.augmentString:(Ljava/lang/String;)Lscala/collection/immutable/StringOps;
	new	class scala/xml/parsing/TokenTests$$anonfun$checkPubID$1
	dup
	aload_0
	invokespecial	Method scala/xml/parsing/TokenTests$$anonfun$checkPubID$1."<init>":(Lscala/xml/parsing/TokenTests;)V
	invokeinterface	InterfaceMethod scala/collection/IndexedSeqLike.forall:(Lscala/Function1;)Z
	ireturn
  Labels:
  LocalVariableTable: 
   Start  Length  Slot  Name   Signature
   0      21      0    $this       Lscala/xml/parsing/TokenTests;
   0      21      1    s       Ljava/lang/String;


public static boolean checkSysID(scala.xml.parsing.TokenTests, java.lang.String);
  Signature: (Lscala/xml/parsing/TokenTests;Ljava/lang/String;)Z
  Code:
   Stack=6, Locals=2, Args_size=2
	getstatic	Field scala/collection/immutable/List$.MODULE$:Lscala/collection/immutable/List$;
	getstatic	Field scala/Predef$.MODULE$:Lscala/Predef$;
	iconst_2
	newarray char
	dup
	iconst_0
	ldc	int 34
	castore
	dup
	iconst_1
	ldc	int 39
	castore
	invokevirtual	Method scala/Predef$.wrapCharArray:([C)Lscala/collection/mutable/WrappedArray;
	invokevirtual	Method scala/collection/immutable/List$.apply:(Lscala/collection/Seq;)Lscala/collection/immutable/List;
	new	class scala/xml/parsing/TokenTests$$anonfun$checkSysID$1
	dup
	aload_0
	aload_1
	invokespecial	Method scala/xml/parsing/TokenTests$$anonfun$checkSysID$1."<init>":(Lscala/xml/parsing/TokenTests;Ljava/lang/String;)V
	invokeinterface	InterfaceMethod scala/collection/LinearSeqLike.exists:(Lscala/Function1;)Z
	ireturn
  Labels:
  LocalVariableTable: 
   Start  Length  Slot  Name   Signature
   0      40      0    $this       Lscala/xml/parsing/TokenTests;
   0      40      1    s$1       Ljava/lang/String;


public static boolean isValidIANAEncoding(scala.xml.parsing.TokenTests, scala.collection.Seq);
  Signature: (Lscala/xml/parsing/TokenTests;Lscala/collection/Seq;)Z
  Code:
   Stack=4, Locals=2, Args_size=2
	aload_1
	invokeinterface	InterfaceMethod scala/collection/TraversableLike.nonEmpty:()Z
	ifeq	l1 // iconst_0
	aload_0
	aload_1
	invokeinterface	InterfaceMethod scala/collection/IterableLike.head:()Ljava/lang/Object;
	invokestatic	Method scala/runtime/BoxesRunTime.unboxToChar:(Ljava/lang/Object;)C
	invokeinterface	InterfaceMethod scala/xml/parsing/TokenTests.isAlpha:(C)Z
	ifeq	l1 // iconst_0
	aload_1
	invokeinterface	InterfaceMethod scala/collection/TraversableLike.tail:()Ljava/lang/Object;
	checkcast	class scala/collection/IterableLike
	new	class scala/xml/parsing/TokenTests$$anonfun$isValidIANAEncoding$1
	dup
	aload_0
	invokespecial	Method scala/xml/parsing/TokenTests$$anonfun$isValidIANAEncoding$1."<init>":(Lscala/xml/parsing/TokenTests;)V
	invokeinterface	InterfaceMethod scala/collection/IterableLike.forall:(Lscala/Function1;)Z
	ifeq	l1 // iconst_0
	iconst_1
	goto	l2 // ireturn
l1	iconst_0
l2	ireturn
  Labels:
   	l1 = 56 // iconst_0
   	l2 = 57 // ireturn
  LocalVariableTable: 
   Start  Length  Slot  Name   Signature
   0      58      0    $this       Lscala/xml/parsing/TokenTests;
   0      58      1    ianaEncoding       Lscala/collection/Seq;


public static boolean isPubIDChar(scala.xml.parsing.TokenTests, char);
  Signature: (Lscala/xml/parsing/TokenTests;C)Z
  Code:
   Stack=3, Locals=3, Args_size=2
	aload_0
	iload_1
	invokeinterface	InterfaceMethod scala/xml/parsing/TokenTests.isAlphaDigit:(C)Z
	ifne	l1 // iconst_1
	aload_0
	iload_1
	invokeinterface	InterfaceMethod scala/xml/parsing/TokenTests.isSpace:(C)Z
	ifeq	l2 // ldc
	iload_1
	ldc	int 9
	if_icmpne	l1 // iconst_1
l2	ldc	String -\()+,./:=?;!*#@$_%
	astore_2
	new	class scala/collection/immutable/StringOps
	dup
	aload_2
	invokespecial	Method scala/collection/immutable/StringOps."<init>":(Ljava/lang/String;)V
	iload_1
	invokestatic	Method scala/runtime/BoxesRunTime.boxToCharacter:(C)Ljava/lang/Character;
	invokeinterface	InterfaceMethod scala/collection/SeqLike.contains:(Ljava/lang/Object;)Z
	ifeq	l3 // iconst_0
l1	iconst_1
	goto	l4 // ireturn
l3	iconst_0
l4	ireturn
  Labels:
   	l2 = 26 // ldc
   	l1 = 49 // iconst_1
   	l3 = 53 // iconst_0
   	l4 = 54 // ireturn
  LocalVariableTable: 
   Start  Length  Slot  Name   Signature
   0      55      0    $this       Lscala/xml/parsing/TokenTests;
   0      55      1    ch       C


public static boolean isName(scala.xml.parsing.TokenTests, java.lang.String);
  Signature: (Lscala/xml/parsing/TokenTests;Ljava/lang/String;)Z
  Code:
   Stack=4, Locals=2, Args_size=2
	new	class scala/collection/immutable/StringOps
	dup
	aload_1
	invokespecial	Method scala/collection/immutable/StringOps."<init>":(Ljava/lang/String;)V
	invokeinterface	InterfaceMethod scala/collection/TraversableLike.nonEmpty:()Z
	ifeq	l1 // iconst_0
	aload_0
	new	class scala/collection/immutable/StringOps
	dup
	aload_1
	invokespecial	Method scala/collection/immutable/StringOps."<init>":(Ljava/lang/String;)V
	invokeinterface	InterfaceMethod scala/collection/IndexedSeqLike.head:()Ljava/lang/Object;
	invokestatic	Method scala/runtime/BoxesRunTime.unboxToChar:(Ljava/lang/Object;)C
	invokeinterface	InterfaceMethod scala/xml/parsing/TokenTests.isNameStart:(C)Z
	ifeq	l1 // iconst_0
	getstatic	Field scala/Predef$.MODULE$:Lscala/Predef$;
	new	class scala/collection/immutable/StringOps
	dup
	aload_1
	invokespecial	Method scala/collection/immutable/StringOps."<init>":(Ljava/lang/String;)V
	invokeinterface	InterfaceMethod scala/collection/IndexedSeqLike.tail:()Ljava/lang/Object;
	checkcast	class java/lang/String
	invokevirtual	Method scala/Predef$.augmentString:(Ljava/lang/String;)Lscala/collection/immutable/StringOps;
	new	class scala/xml/parsing/TokenTests$$anonfun$isName$1
	dup
	aload_0
	invokespecial	Method scala/xml/parsing/TokenTests$$anonfun$isName$1."<init>":(Lscala/xml/parsing/TokenTests;)V
	invokeinterface	InterfaceMethod scala/collection/IndexedSeqLike.forall:(Lscala/Function1;)Z
	ifeq	l1 // iconst_0
	iconst_1
	goto	l2 // ireturn
l1	iconst_0
l2	ireturn
  Labels:
   	l1 = 83 // iconst_0
   	l2 = 84 // ireturn
  LocalVariableTable: 
   Start  Length  Slot  Name   Signature
   0      85      0    $this       Lscala/xml/parsing/TokenTests;
   0      85      1    s       Ljava/lang/String;


public static boolean isNameStart(scala.xml.parsing.TokenTests, char);
  Signature: (Lscala/xml/parsing/TokenTests;C)Z
  Code:
   Stack=3, Locals=3, Args_size=2
	iload_1
	invokestatic	Method java/lang/Character.getType:(C)I
	i2b
	istore_2
	iload_2
	lookupswitch{ //5
		1: 181;
		2: 158;
		3: 135;
		5: 112;
		10: 89;
		default: 56 }
	iconst_1
	ifeq	l1 // new
	iload_1
	ldc	int 95
	if_icmpne	l2 // iconst_0
	iconst_1
	goto	l3 // ireturn
l2	iconst_0
	goto	l3 // ireturn
l1	new	class scala/MatchError
	dup
	iload_2
	invokestatic	Method scala/runtime/BoxesRunTime.boxToByte:(B)Ljava/lang/Byte;
	invokevirtual	Method java/lang/Object.toString:()Ljava/lang/String;
	invokespecial	Method scala/MatchError."<init>":(Ljava/lang/String;)V
	athrow
	iconst_1
	ifeq	l4 // new
	iconst_1
	goto	l3 // ireturn
l4	new	class scala/MatchError
	dup
	iload_2
	invokestatic	Method scala/runtime/BoxesRunTime.boxToByte:(B)Ljava/lang/Byte;
	invokevirtual	Method java/lang/Object.toString:()Ljava/lang/String;
	invokespecial	Method scala/MatchError."<init>":(Ljava/lang/String;)V
	athrow
	iconst_1
	ifeq	l5 // new
	iconst_1
	goto	l3 // ireturn
l5	new	class scala/MatchError
	dup
	iload_2
	invokestatic	Method scala/runtime/BoxesRunTime.boxToByte:(B)Ljava/lang/Byte;
	invokevirtual	Method java/lang/Object.toString:()Ljava/lang/String;
	invokespecial	Method scala/MatchError."<init>":(Ljava/lang/String;)V
	athrow
	iconst_1
	ifeq	l6 // new
	iconst_1
	goto	l3 // ireturn
l6	new	class scala/MatchError
	dup
	iload_2
	invokestatic	Method scala/runtime/BoxesRunTime.boxToByte:(B)Ljava/lang/Byte;
	invokevirtual	Method java/lang/Object.toString:()Ljava/lang/String;
	invokespecial	Method scala/MatchError."<init>":(Ljava/lang/String;)V
	athrow
	iconst_1
	ifeq	l7 // new
	iconst_1
	goto	l3 // ireturn
l7	new	class scala/MatchError
	dup
	iload_2
	invokestatic	Method scala/runtime/BoxesRunTime.boxToByte:(B)Ljava/lang/Byte;
	invokevirtual	Method java/lang/Object.toString:()Ljava/lang/String;
	invokespecial	Method scala/MatchError."<init>":(Ljava/lang/String;)V
	athrow
	iconst_1
	ifeq	l8 // new
	iconst_1
l3	ireturn
l8	new	class scala/MatchError
	dup
	iload_2
	invokestatic	Method scala/runtime/BoxesRunTime.boxToByte:(B)Ljava/lang/Byte;
	invokevirtual	Method java/lang/Object.toString:()Ljava/lang/String;
	invokespecial	Method scala/MatchError."<init>":(Ljava/lang/String;)V
	athrow
  Labels:
   	l2 = 70 // iconst_0
   	l1 = 74 // new
   	l4 = 97 // new
   	l5 = 120 // new
   	l6 = 143 // new
   	l7 = 166 // new
   	l3 = 186 // ireturn
   	l8 = 187 // new
  LocalVariableTable: 
   Start  Length  Slot  Name   Signature
   0      202      0    $this       Lscala/xml/parsing/TokenTests;
   0      202      1    ch       C
   6      196      2    temp3       B


public static boolean isNameChar(scala.xml.parsing.TokenTests, char);
  Signature: (Lscala/xml/parsing/TokenTests;C)Z
  Code:
   Stack=3, Locals=4, Args_size=2
	aload_0
	iload_1
	invokeinterface	InterfaceMethod scala/xml/parsing/TokenTests.isNameStart:(C)Z
	ifne	l1 // iconst_1
	iload_1
	invokestatic	Method java/lang/Character.getType:(C)I
	i2b
	istore_3
	iload_3
	tableswitch{ //4 to 9
		4: 190;
		5: 56;
		6: 167;
		7: 144;
		8: 121;
		9: 98;
		default: 56 }
	iconst_1
	ifeq	l2 // new
	ldc	String .-:
	astore_2
	new	class scala/collection/immutable/StringOps
	dup
	aload_2
	invokespecial	Method scala/collection/immutable/StringOps."<init>":(Ljava/lang/String;)V
	iload_1
	invokestatic	Method scala/runtime/BoxesRunTime.boxToCharacter:(C)Ljava/lang/Character;
	invokeinterface	InterfaceMethod scala/collection/SeqLike.contains:(Ljava/lang/Object;)Z
	goto	l3 // ifeq
l2	new	class scala/MatchError
	dup
	iload_3
	invokestatic	Method scala/runtime/BoxesRunTime.boxToByte:(B)Ljava/lang/Byte;
	invokevirtual	Method java/lang/Object.toString:()Ljava/lang/String;
	invokespecial	Method scala/MatchError."<init>":(Ljava/lang/String;)V
	athrow
	iconst_1
	ifeq	l4 // new
	iconst_1
	goto	l3 // ifeq
l4	new	class scala/MatchError
	dup
	iload_3
	invokestatic	Method scala/runtime/BoxesRunTime.boxToByte:(B)Ljava/lang/Byte;
	invokevirtual	Method java/lang/Object.toString:()Ljava/lang/String;
	invokespecial	Method scala/MatchError."<init>":(Ljava/lang/String;)V
	athrow
	iconst_1
	ifeq	l5 // new
	iconst_1
	goto	l3 // ifeq
l5	new	class scala/MatchError
	dup
	iload_3
	invokestatic	Method scala/runtime/BoxesRunTime.boxToByte:(B)Ljava/lang/Byte;
	invokevirtual	Method java/lang/Object.toString:()Ljava/lang/String;
	invokespecial	Method scala/MatchError."<init>":(Ljava/lang/String;)V
	athrow
	iconst_1
	ifeq	l6 // new
	iconst_1
	goto	l3 // ifeq
l6	new	class scala/MatchError
	dup
	iload_3
	invokestatic	Method scala/runtime/BoxesRunTime.boxToByte:(B)Ljava/lang/Byte;
	invokevirtual	Method java/lang/Object.toString:()Ljava/lang/String;
	invokespecial	Method scala/MatchError."<init>":(Ljava/lang/String;)V
	athrow
	iconst_1
	ifeq	l7 // new
	iconst_1
	goto	l3 // ifeq
l7	new	class scala/MatchError
	dup
	iload_3
	invokestatic	Method scala/runtime/BoxesRunTime.boxToByte:(B)Ljava/lang/Byte;
	invokevirtual	Method java/lang/Object.toString:()Ljava/lang/String;
	invokespecial	Method scala/MatchError."<init>":(Ljava/lang/String;)V
	athrow
	iconst_1
	ifeq	l8 // new
	iconst_1
l3	ifeq	l9 // iconst_0
l1	iconst_1
	goto	l10 // ireturn
l9	iconst_0
l10	ireturn
l8	new	class scala/MatchError
	dup
	iload_3
	invokestatic	Method scala/runtime/BoxesRunTime.boxToByte:(B)Ljava/lang/Byte;
	invokevirtual	Method java/lang/Object.toString:()Ljava/lang/String;
	invokespecial	Method scala/MatchError."<init>":(Ljava/lang/String;)V
	athrow
  Labels:
   	l2 = 83 // new
   	l4 = 106 // new
   	l5 = 129 // new
   	l6 = 152 // new
   	l7 = 175 // new
   	l3 = 195 // ifeq
   	l1 = 198 // iconst_1
   	l9 = 202 // iconst_0
   	l10 = 203 // ireturn
   	l8 = 204 // new
  LocalVariableTable: 
   Start  Length  Slot  Name   Signature
   0      219      0    $this       Lscala/xml/parsing/TokenTests;
   0      219      1    ch       C
   16      182      3    temp2       B
   204      15      3    temp2       B


public static boolean isAlphaDigit(scala.xml.parsing.TokenTests, char);
  Signature: (Lscala/xml/parsing/TokenTests;C)Z
  Code:
   Stack=2, Locals=2, Args_size=2
	aload_0
	iload_1
	invokeinterface	InterfaceMethod scala/xml/parsing/TokenTests.isAlpha:(C)Z
	ifne	l1 // iconst_1
	iload_1
	ldc	int 48
	if_icmplt	l2 // iconst_0
	iload_1
	ldc	int 57
	if_icmpgt	l2 // iconst_0
l1	iconst_1
	goto	l3 // ireturn
l2	iconst_0
l3	ireturn
  Labels:
   	l1 = 22 // iconst_1
   	l2 = 26 // iconst_0
   	l3 = 27 // ireturn
  LocalVariableTable: 
   Start  Length  Slot  Name   Signature
   0      28      0    $this       Lscala/xml/parsing/TokenTests;
   0      28      1    c       C


public static boolean isAlpha(scala.xml.parsing.TokenTests, char);
  Signature: (Lscala/xml/parsing/TokenTests;C)Z
  Code:
   Stack=2, Locals=2, Args_size=2
	iload_1
	ldc	int 65
	if_icmplt	l1 // iload_1
	iload_1
	ldc	int 90
	if_icmple	l2 // iconst_1
l1	iload_1
	ldc	int 97
	if_icmplt	l3 // iconst_0
	iload_1
	ldc	int 122
	if_icmpgt	l3 // iconst_0
l2	iconst_1
	goto	l4 // ireturn
l3	iconst_0
l4	ireturn
  Labels:
   	l1 = 12 // iload_1
   	l2 = 24 // iconst_1
   	l3 = 28 // iconst_0
   	l4 = 29 // ireturn
  LocalVariableTable: 
   Start  Length  Slot  Name   Signature
   0      30      0    $this       Lscala/xml/parsing/TokenTests;
   0      30      1    c       C


public static final boolean isSpace(scala.xml.parsing.TokenTests, scala.collection.Seq);
  Signature: (Lscala/xml/parsing/TokenTests;Lscala/collection/Seq;)Z
  Code:
   Stack=4, Locals=2, Args_size=2
	aload_1
	invokeinterface	InterfaceMethod scala/collection/TraversableLike.nonEmpty:()Z
	ifeq	l1 // iconst_0
	aload_1
	new	class scala/xml/parsing/TokenTests$$anonfun$isSpace$1
	dup
	aload_0
	invokespecial	Method scala/xml/parsing/TokenTests$$anonfun$isSpace$1."<init>":(Lscala/xml/parsing/TokenTests;)V
	invokeinterface	InterfaceMethod scala/collection/IterableLike.forall:(Lscala/Function1;)Z
	ifeq	l1 // iconst_0
	iconst_1
	goto	l2 // ireturn
l1	iconst_0
l2	ireturn
  Labels:
   	l1 = 30 // iconst_0
   	l2 = 31 // ireturn
  LocalVariableTable: 
   Start  Length  Slot  Name   Signature
   0      32      0    $this       Lscala/xml/parsing/TokenTests;
   0      32      1    cs       Lscala/collection/Seq;


public static final boolean isSpace(scala.xml.parsing.TokenTests, char);
  Signature: (Lscala/xml/parsing/TokenTests;C)Z
  Code:
   Stack=3, Locals=2, Args_size=2
	iload_1
	lookupswitch{ //4
		9: 136;
		10: 113;
		13: 90;
		32: 67;
		default: 44 }
	iconst_1
	ifeq	l1 // new
	iconst_0
	goto	l2 // ireturn
l1	new	class scala/MatchError
	dup
	iload_1
	invokestatic	Method scala/runtime/BoxesRunTime.boxToCharacter:(C)Ljava/lang/Character;
	invokevirtual	Method java/lang/Object.toString:()Ljava/lang/String;
	invokespecial	Method scala/MatchError."<init>":(Ljava/lang/String;)V
	athrow
	iconst_1
	ifeq	l3 // new
	iconst_1
	goto	l2 // ireturn
l3	new	class scala/MatchError
	dup
	iload_1
	invokestatic	Method scala/runtime/BoxesRunTime.boxToCharacter:(C)Ljava/lang/Character;
	invokevirtual	Method java/lang/Object.toString:()Ljava/lang/String;
	invokespecial	Method scala/MatchError."<init>":(Ljava/lang/String;)V
	athrow
	iconst_1
	ifeq	l4 // new
	iconst_1
	goto	l2 // ireturn
l4	new	class scala/MatchError
	dup
	iload_1
	invokestatic	Method scala/runtime/BoxesRunTime.boxToCharacter:(C)Ljava/lang/Character;
	invokevirtual	Method java/lang/Object.toString:()Ljava/lang/String;
	invokespecial	Method scala/MatchError."<init>":(Ljava/lang/String;)V
	athrow
	iconst_1
	ifeq	l5 // new
	iconst_1
	goto	l2 // ireturn
l5	new	class scala/MatchError
	dup
	iload_1
	invokestatic	Method scala/runtime/BoxesRunTime.boxToCharacter:(C)Ljava/lang/Character;
	invokevirtual	Method java/lang/Object.toString:()Ljava/lang/String;
	invokespecial	Method scala/MatchError."<init>":(Ljava/lang/String;)V
	athrow
	iconst_1
	ifeq	l6 // new
	iconst_1
l2	ireturn
l6	new	class scala/MatchError
	dup
	iload_1
	invokestatic	Method scala/runtime/BoxesRunTime.boxToCharacter:(C)Ljava/lang/Character;
	invokevirtual	Method java/lang/Object.toString:()Ljava/lang/String;
	invokespecial	Method scala/MatchError."<init>":(Ljava/lang/String;)V
	athrow
  Labels:
   	l1 = 52 // new
   	l3 = 75 // new
   	l4 = 98 // new
   	l5 = 121 // new
   	l2 = 141 // ireturn
   	l6 = 142 // new
  LocalVariableTable: 
   Start  Length  Slot  Name   Signature
   0      157      0    $this       Lscala/xml/parsing/TokenTests;
   0      157      1    ch       C


}

