Compiled from "TokenTests.scala"
public final class scala.xml.parsing.TokenTests$$anonfun$checkSysID$1 extends java.lang.Object implements scala.Function1,scala.ScalaObject,java.io.Serializable
  SourceFile: "TokenTests.scala"
  Scala: length = 0x
   
  InnerClass: 
   public final $anonfun$checkSysID$1=class scala/xml/parsing/TokenTests$$anonfun$checkSysID$1 of class scala/xml/parsing/TokenTests
  minor version: 0
  major version: 49
  Constant pool:
Asciz	SourceFile;
Asciz	TokenTests.scala;
Asciz	<clinit>;
Asciz	()V;
Asciz	Code;
Asciz	serialVersionUID;
Asciz	J;
Asciz	scala/xml/parsing/TokenTests$$anonfun$checkSysID$1;
class	scala/xml/parsing/TokenTests$$anonfun$checkSysID$1
NameAndType	serialVersionUID:J
Field	scala/xml/parsing/TokenTests$$anonfun$checkSysID$1.serialVersionUID:J
Asciz	s$1;
Asciz	Ljava/lang/String;;
Asciz	<init>;
Asciz	(Lscala/xml/parsing/TokenTests;Ljava/lang/String;)V;
Asciz	LineNumberTable;
NameAndType	s$1:Ljava/lang/String;
Field	scala/xml/parsing/TokenTests$$anonfun$checkSysID$1.s$1:Ljava/lang/String;
Asciz	java/lang/Object;
class	java/lang/Object
NameAndType	"<init>":()V
Method	java/lang/Object."<init>":()V
Asciz	scala/Function1$class;
class	scala/Function1$class
Asciz	$init$;
Asciz	(Lscala/Function1;)V;
NameAndType	$init$:(Lscala/Function1;)V
Method	scala/Function1$class.$init$:(Lscala/Function1;)V
Asciz	this;
Asciz	Lscala/xml/parsing/TokenTests$$anonfun$checkSysID$1;;
Asciz	$outer;
Asciz	Lscala/xml/parsing/TokenTests;;
Asciz	LocalVariableTable;
Asciz	apply;
Asciz	(Ljava/lang/Object;)Ljava/lang/Object;;
Asciz	scala/runtime/BoxesRunTime;
class	scala/runtime/BoxesRunTime
Asciz	unboxToChar;
Asciz	(Ljava/lang/Object;)C;
NameAndType	unboxToChar:(Ljava/lang/Object;)C
Method	scala/runtime/BoxesRunTime.unboxToChar:(Ljava/lang/Object;)C
Asciz	(C)Z;
NameAndType	apply:(C)Z
Method	scala/xml/parsing/TokenTests$$anonfun$checkSysID$1.apply:(C)Z
Asciz	boxToBoolean;
Asciz	(Z)Ljava/lang/Boolean;;
NameAndType	boxToBoolean:(Z)Ljava/lang/Boolean;
Method	scala/runtime/BoxesRunTime.boxToBoolean:(Z)Ljava/lang/Boolean;
Asciz	v1;
Asciz	Ljava/lang/Object;;
Asciz	scala/collection/immutable/StringOps;
class	scala/collection/immutable/StringOps
Asciz	(Ljava/lang/String;)V;
NameAndType	"<init>":(Ljava/lang/String;)V
Method	scala/collection/immutable/StringOps."<init>":(Ljava/lang/String;)V
Asciz	boxToCharacter;
Asciz	(C)Ljava/lang/Character;;
NameAndType	boxToCharacter:(C)Ljava/lang/Character;
Method	scala/runtime/BoxesRunTime.boxToCharacter:(C)Ljava/lang/Character;
Asciz	scala/collection/SeqLike;
class	scala/collection/SeqLike
Asciz	contains;
Asciz	(Ljava/lang/Object;)Z;
NameAndType	contains:(Ljava/lang/Object;)Z
InterfaceMethod	scala/collection/SeqLike.contains:(Ljava/lang/Object;)Z
Asciz	c;
Asciz	C;
Asciz	andThen;
Asciz	(Lscala/Function1;)Lscala/Function1;;
Asciz	(Lscala/Function1;Lscala/Function1;)Lscala/Function1;;
NameAndType	andThen:(Lscala/Function1;Lscala/Function1;)Lscala/Function1;
Method	scala/Function1$class.andThen:(Lscala/Function1;Lscala/Function1;)Lscala/Function1;
Asciz	g;
Asciz	Lscala/Function1;;
Asciz	compose;
NameAndType	compose:(Lscala/Function1;Lscala/Function1;)Lscala/Function1;
Method	scala/Function1$class.compose:(Lscala/Function1;Lscala/Function1;)Lscala/Function1;
Asciz	toString;
Asciz	()Ljava/lang/String;;
Asciz	(Lscala/Function1;)Ljava/lang/String;;
NameAndType	toString:(Lscala/Function1;)Ljava/lang/String;
Method	scala/Function1$class.toString:(Lscala/Function1;)Ljava/lang/String;
Asciz	Scala;
Asciz	InnerClasses;
Asciz	scala/xml/parsing/TokenTests;
class	scala/xml/parsing/TokenTests
Asciz	$anonfun$checkSysID$1;
Asciz	scala/Function1;
class	scala/Function1
Asciz	scala/ScalaObject;
class	scala/ScalaObject
Asciz	java/io/Serializable;
class	java/io/Serializable

{
public static final long serialVersionUID;
  Signature: J

private final java.lang.String s$1;
  Signature: Ljava/lang/String;

public static {};
  Signature: ()V
  Code:
   Stack=2, Locals=0, Args_size=0
	lconst_0
	putstatic	Field serialVersionUID:J
	return
  Labels:

public scala.xml.parsing.TokenTests$$anonfun$checkSysID$1(scala.xml.parsing.TokenTests, java.lang.String);
  Signature: (Lscala/xml/parsing/TokenTests;Ljava/lang/String;)V
  Code:
   Stack=2, Locals=3, Args_size=3
	aload_0
	aload_2
	putfield	Field s$1:Ljava/lang/String;
	aload_0
	invokespecial	Method java/lang/Object."<init>":()V
	aload_0
	invokestatic	Method scala/Function1$class.$init$:(Lscala/Function1;)V
	return
  Labels:
  LocalVariableTable: 
   Start  Length  Slot  Name   Signature
   0      14      0    this       Lscala/xml/parsing/TokenTests$$anonfun$checkSysID$1;
   0      14      1    $outer       Lscala/xml/parsing/TokenTests;


public final java.lang.Object apply(java.lang.Object);
  Signature: (Ljava/lang/Object;)Ljava/lang/Object;
  Code:
   Stack=2, Locals=3, Args_size=2
	aload_0
	aload_1
	invokestatic	Method scala/runtime/BoxesRunTime.unboxToChar:(Ljava/lang/Object;)C
	invokevirtual	Method apply:(C)Z
	istore_2
	iload_2
	invokestatic	Method scala/runtime/BoxesRunTime.boxToBoolean:(Z)Ljava/lang/Boolean;
	areturn
  Labels:
  LocalVariableTable: 
   Start  Length  Slot  Name   Signature
   0      14      0    this       Lscala/xml/parsing/TokenTests$$anonfun$checkSysID$1;
   0      14      1    v1       Ljava/lang/Object;


public final boolean apply(char);
  Signature: (C)Z
  Code:
   Stack=3, Locals=3, Args_size=2
	aload_0
	getfield	Field s$1:Ljava/lang/String;
	astore_2
	new	class scala/collection/immutable/StringOps
	dup
	aload_2
	invokespecial	Method scala/collection/immutable/StringOps."<init>":(Ljava/lang/String;)V
	iload_1
	invokestatic	Method scala/runtime/BoxesRunTime.boxToCharacter:(C)Ljava/lang/Character;
	invokeinterface	InterfaceMethod scala/collection/SeqLike.contains:(Ljava/lang/Object;)Z
	ifeq	l1 // iconst_1
	iconst_0
	goto	l2 // ireturn
l1	iconst_1
l2	ireturn
  Labels:
   	l1 = 29 // iconst_1
   	l2 = 30 // ireturn
  LocalVariableTable: 
   Start  Length  Slot  Name   Signature
   0      31      0    this       Lscala/xml/parsing/TokenTests$$anonfun$checkSysID$1;
   0      31      1    c       C


public scala.Function1 andThen(scala.Function1);
  Signature: (Lscala/Function1;)Lscala/Function1;
  Code:
   Stack=2, Locals=2, Args_size=2
	aload_0
	aload_1
	invokestatic	Method scala/Function1$class.andThen:(Lscala/Function1;Lscala/Function1;)Lscala/Function1;
	areturn
  Labels:
  LocalVariableTable: 
   Start  Length  Slot  Name   Signature
   0      6      0    this       Lscala/xml/parsing/TokenTests$$anonfun$checkSysID$1;
   0      6      1    g       Lscala/Function1;


public scala.Function1 compose(scala.Function1);
  Signature: (Lscala/Function1;)Lscala/Function1;
  Code:
   Stack=2, Locals=2, Args_size=2
	aload_0
	aload_1
	invokestatic	Method scala/Function1$class.compose:(Lscala/Function1;Lscala/Function1;)Lscala/Function1;
	areturn
  Labels:
  LocalVariableTable: 
   Start  Length  Slot  Name   Signature
   0      6      0    this       Lscala/xml/parsing/TokenTests$$anonfun$checkSysID$1;
   0      6      1    g       Lscala/Function1;


public java.lang.String toString();
  Signature: ()Ljava/lang/String;
  Code:
   Stack=1, Locals=1, Args_size=1
	aload_0
	invokestatic	Method scala/Function1$class.toString:(Lscala/Function1;)Ljava/lang/String;
	areturn
  Labels:

}

