Compiled from "ValidatingMarkupHandler.scala"
public abstract class scala.xml.parsing.ValidatingMarkupHandler extends scala.xml.parsing.MarkupHandler implements scala.util.logging.Logged,scala.ScalaObject
  SourceFile: "ValidatingMarkupHandler.scala"
  ScalaSig: length = 0x5B4
   05 00 FFFFFF81 42 06 08 01 02 FFFFFF84 FFFFFF80 FFFFFF80 FFFFFF81 00 09 02 17
   56 61 6C 69 64 61 74 69 6E 67 4D 61 72 6B 75 70
   48 61 6E 64 6C 65 72 0A 02 03 04 01 07 70 61 72
   73 69 6E 67 0A 02 05 06 01 03 78 6D 6C 0A 01 07
   01 05 73 63 61 6C 61 03 00 13 04 00 0A 0E 16 10
   02 0B 0C 0D 01 02 09 02 0D 02 02 0D 4D 61 72 6B
   75 70 48 61 6E 64 6C 65 72 10 02 0F 14 0D 01 10
   0A 02 11 12 01 07 6C 6F 67 67 69 6E 67 0A 02 13
   06 01 04 75 74 69 6C 09 02 15 10 02 06 4C 6F 67
   67 65 64 10 02 17 18 0D 01 06 09 02 19 06 02 0B
   53 63 61 6C 61 4F 62 6A 65 63 74 08 05 1B 00 FFFFFF84
   00 1C 01 06 3C 69 6E 69 74 3E 14 01 1D 10 02 0B
   00 08 07 1F 00 FFFFFFC0 FFFFFF80 FFFFFF84 00 20 01 09 72 6F 6F 74
   4C 61 62 65 6C 15 01 21 10 02 22 25 0E 02 17 23
   09 02 24 06 01 06 50 72 65 64 65 66 09 02 26 27
   02 06 53 74 72 69 6E 67 0A 02 24 06 08 07 29 00
   FFFFFFC0 FFFFFF80 FFFFFF84 00 2A 01 0D 72 6F 6F 74 4C 61 62 65 6C
   5F 24 65 71 14 02 2B 2E 10 02 17 2C 09 02 2D 06
   02 04 55 6E 69 74 08 07 2F 28 FFFFFF81 FFFFFF80 FFFFFFC0 00 21 01
   03 78 24 31 08 06 31 00 FFFFFFA0 FFFFFFA0 04 21 01 0A 72 6F
   6F 74 4C 61 62 65 6C 20 08 07 33 00 FFFFFFC0 FFFFFF80 FFFFFF84 00
   34 01 06 71 53 74 61 63 6B 15 01 35 10 03 36 3E
   41 0E 02 37 3C 0E 02 38 3B 0D 01 39 0A 02 3A 08
   01 06 3C 72 6F 6F 74 3E 09 01 07 09 02 3D 06 01
   07 70 61 63 6B 61 67 65 09 02 3F 40 02 04 4C 69
   73 74 0A 02 3D 06 10 02 17 42 09 02 43 06 02 03
   49 6E 74 08 07 45 00 FFFFFFC0 FFFFFF80 FFFFFF84 00 46 01 0A 71 53
   74 61 63 6B 5F 24 65 71 14 02 2B 47 08 07 2F 44
   FFFFFF81 FFFFFF80 FFFFFFC0 00 35 08 06 49 00 FFFFFFA0 FFFFFFA0 04 35 01 07 71
   53 74 61 63 6B 20 08 07 4B 00 FFFFFFC0 FFFFFF80 FFFFFF84 00 4C 01
   08 71 43 75 72 72 65 6E 74 15 01 41 08 07 4E 00
   FFFFFFC0 FFFFFF80 FFFFFF84 00 4F 01 0C 71 43 75 72 72 65 6E 74 5F
   24 65 71 14 02 2B 50 08 07 2F 4D FFFFFF81 FFFFFF80 FFFFFFC0 00 41
   08 06 52 00 FFFFFFA0 FFFFFFA0 04 41 01 09 71 43 75 72 72 65
   6E 74 20 08 07 54 00 FFFFFFC0 FFFFFF80 FFFFFF84 00 55 01 09 64 65
   63 6C 53 74 61 63 6B 15 01 56 10 03 36 3E 57 10
   02 58 5B 0D 01 59 0A 02 5A 04 01 03 64 74 64 09
   02 5C 59 02 08 45 6C 65 6D 44 65 63 6C 08 07 5E
   00 FFFFFFC0 FFFFFF80 FFFFFF84 00 5F 01 0D 64 65 63 6C 53 74 61 63
   6B 5F 24 65 71 14 02 2B 60 08 07 2F 5D FFFFFF81 FFFFFF80 FFFFFFC0
   00 56 08 06 62 00 FFFFFFA0 FFFFFFA0 04 56 01 0A 64 65 63 6C
   53 74 61 63 6B 20 08 07 64 00 FFFFFFC0 FFFFFF80 FFFFFF84 00 65 01
   0B 64 65 63 6C 43 75 72 72 65 6E 74 15 01 57 08
   07 67 00 FFFFFFC0 FFFFFF80 FFFFFF84 00 68 01 0F 64 65 63 6C 43 75
   72 72 65 6E 74 5F 24 65 71 14 02 2B 69 08 07 2F
   66 FFFFFF81 FFFFFF80 FFFFFFC0 00 57 08 06 6B 00 FFFFFFA0 FFFFFFA0 04 57 01 0C
   64 65 63 6C 43 75 72 72 65 6E 74 20 08 07 6D 00
   FFFFFFC2 FFFFFF80 FFFFFF84 22 6E 01 0C 69 73 56 61 6C 69 64 61 74
   69 6E 67 15 01 6F 0F 01 70 19 01 01 08 06 72 00
   FFFFFFA0 FFFFFF80 06 6F 01 0D 69 73 56 61 6C 69 64 61 74 69
   6E 67 20 08 05 74 00 FFFFFF84 20 75 01 03 6C 6F 67 14
   02 2B 76 08 05 77 73 FFFFFFC0 00 21 01 03 6D 73 67 08
   05 79 00 FFFFFF84 20 7A 01 06 65 6E 64 44 54 44 14 02
   2B 7B 08 05 7C 78 FFFFFFC0 00 21 01 01 6E 08 05 7E 00
   FFFFFF84 20 7F 01 09 65 6C 65 6D 53 74 61 72 74 14 0B
   2B FFFFFF81 00 FFFFFF81 02 FFFFFF81 04 FFFFFF81 06 FFFFFF81 0C 08 06 FFFFFF81 01 7D
   FFFFFFC0 00 41 01 03 70 6F 73 08 06 FFFFFF81 03 7D FFFFFFC0 00 21
   01 03 70 72 65 08 06 FFFFFF81 05 7D FFFFFFC0 00 21 01 05 6C
   61 62 65 6C 08 07 FFFFFF81 07 7D FFFFFFC0 00 FFFFFF81 08 01 05 61
   74 74 72 73 10 04 FFFFFF81 09 FFFFFF81 0A 0D 01 04 09 03 FFFFFF81
   0B 04 02 08 4D 65 74 61 44 61 74 61 08 07 FFFFFF81 0D
   7D FFFFFFC0 00 FFFFFF81 0E 01 05 73 63 6F 70 65 10 04 FFFFFF81 09
   FFFFFF81 0F 09 03 FFFFFF81 10 04 02 10 4E 61 6D 65 73 70 61
   63 65 42 69 6E 64 69 6E 67 08 07 FFFFFF81 12 00 FFFFFF84 20
   FFFFFF81 13 01 07 65 6C 65 6D 45 6E 64 14 07 2B FFFFFF81 14
   FFFFFF81 15 FFFFFF81 16 08 07 FFFFFF81 01 FFFFFF81 11 FFFFFFC0 00 41 08 07 FFFFFF81
   03 FFFFFF81 11 FFFFFFC0 00 21 08 07 FFFFFF81 05 FFFFFF81 11 FFFFFFC0 00 21 08
   07 FFFFFF81 18 00 FFFFFF84 22 FFFFFF81 19 01 08 65 6C 65 6D 44 65
   63 6C 14 05 2B FFFFFF81 1A FFFFFF81 1C 08 07 FFFFFF81 1B FFFFFF81 17 FFFFFFC0
   00 21 01 04 6E 61 6D 65 08 07 FFFFFF81 1D FFFFFF81 17 FFFFFFC0 00
   21 01 05 63 6D 73 74 72 08 07 FFFFFF81 1F 00 FFFFFF84 22 FFFFFF81
   20 01 0B 61 74 74 4C 69 73 74 44 65 63 6C 14 05
   2B FFFFFF81 21 FFFFFF81 22 08 07 FFFFFF81 1B FFFFFF81 1E FFFFFFC0 00 21 08 08
   FFFFFF81 23 FFFFFF81 1E FFFFFFC0 00 FFFFFF81 24 01 07 61 74 74 4C 69 73
   74 10 04 36 3E FFFFFF81 25 10 03 58 FFFFFF81 26 09 03 FFFFFF81 27
   59 02 08 41 74 74 72 44 65 63 6C 08 07 FFFFFF81 29 00
   FFFFFF84 22 FFFFFF81 2A 01 12 75 6E 70 61 72 73 65 64 45 6E
   74 69 74 79 44 65 63 6C 14 07 2B FFFFFF81 2B FFFFFF81 2C FFFFFF81
   31 08 07 FFFFFF81 1B FFFFFF81 28 FFFFFFC0 00 21 08 08 FFFFFF81 2D FFFFFF81 28
   FFFFFFC0 00 FFFFFF81 2E 01 05 65 78 74 49 44 10 03 58 FFFFFF81 2F
   09 03 FFFFFF81 30 59 02 0A 45 78 74 65 72 6E 61 6C 49
   44 08 07 FFFFFF81 32 FFFFFF81 28 FFFFFFC0 00 21 01 05 6E 6F 74 61
   74 08 07 FFFFFF81 34 00 FFFFFF84 22 FFFFFF81 35 01 0C 6E 6F 74 61
   74 69 6F 6E 44 65 63 6C 14 05 2B FFFFFF81 36 FFFFFF81 37 08
   07 FFFFFF81 32 FFFFFF81 33 FFFFFFC0 00 21 08 08 FFFFFF81 2D FFFFFF81 33 FFFFFFC0 00
   FFFFFF81 2E 08 07 FFFFFF81 39 00 FFFFFF84 22 FFFFFF81 3A 01 0B 70 65 52
   65 66 65 72 65 6E 63 65 14 03 2B FFFFFF81 3B 08 07 FFFFFF81
   1B FFFFFF81 38 FFFFFFC0 00 21 08 07 FFFFFF81 3D 00 FFFFFF86 00 FFFFFF81 3E 01
   15 72 65 70 6F 72 74 56 61 6C 69 64 61 74 69 6F
   6E 45 72 72 6F 72 14 05 2B FFFFFF81 3F FFFFFF81 40 08 07 FFFFFF81
   01 FFFFFF81 3C FFFFFFC0 00 41 08 07 FFFFFF81 41 FFFFFF81 3C FFFFFFC0 00 21 01
   03 73 74 72 
  InnerClass: 
   public ElemName=class scala/xml/dtd/ContentModel$ElemName of class scala/xml/dtd/ContentModel
  minor version: 0
  major version: 49
  Constant pool:
Asciz	SourceFile;
Asciz	ValidatingMarkupHandler.scala;
Asciz	isValidating;
Asciz	Z;
Asciz	declCurrent;
Asciz	Lscala/xml/dtd/ElemDecl;;
Asciz	declStack;
Asciz	Lscala/collection/immutable/List;;
Asciz	Lscala/collection/immutable/List<Lscala/xml/dtd/ElemDecl;>;;
Asciz	Signature;
Asciz	qCurrent;
Asciz	I;
Asciz	qStack;
Asciz	Lscala/collection/immutable/List<Ljava/lang/Integer;>;;
Asciz	rootLabel;
Asciz	Ljava/lang/String;;
Asciz	<init>;
Asciz	()V;
Asciz	Code;
Asciz	LineNumberTable;
Asciz	scala/xml/parsing/MarkupHandler;
class	scala/xml/parsing/MarkupHandler
NameAndType	"<init>":()V
Method	scala/xml/parsing/MarkupHandler."<init>":()V
Asciz	scala/collection/immutable/Nil$;
class	scala/collection/immutable/Nil$
Asciz	MODULE$;
Asciz	Lscala/collection/immutable/Nil$;;
NameAndType	MODULE$:Lscala/collection/immutable/Nil$;
Field	scala/collection/immutable/Nil$.MODULE$:Lscala/collection/immutable/Nil$;
Asciz	scala/xml/parsing/ValidatingMarkupHandler;
class	scala/xml/parsing/ValidatingMarkupHandler
NameAndType	qStack:Lscala/collection/immutable/List;
Field	scala/xml/parsing/ValidatingMarkupHandler.qStack:Lscala/collection/immutable/List;
NameAndType	qCurrent:I
Field	scala/xml/parsing/ValidatingMarkupHandler.qCurrent:I
NameAndType	declStack:Lscala/collection/immutable/List;
Field	scala/xml/parsing/ValidatingMarkupHandler.declStack:Lscala/collection/immutable/List;
NameAndType	declCurrent:Lscala/xml/dtd/ElemDecl;
Field	scala/xml/parsing/ValidatingMarkupHandler.declCurrent:Lscala/xml/dtd/ElemDecl;
Asciz	advanceDFA$1;
Asciz	(Lscala/xml/dtd/DFAContentModel;ILjava/lang/String;)V;
Asciz	scala/xml/dtd/DFAContentModel;
class	scala/xml/dtd/DFAContentModel
Asciz	dfa;
Asciz	()Lscala/util/automata/DetWordAutom;;
NameAndType	dfa:()Lscala/util/automata/DetWordAutom;
Method	scala/xml/dtd/DFAContentModel.dfa:()Lscala/util/automata/DetWordAutom;
Asciz	scala/util/automata/DetWordAutom;
class	scala/util/automata/DetWordAutom
Asciz	delta;
Asciz	()[Lscala/collection/Map;;
NameAndType	delta:()[Lscala/collection/Map;
Method	scala/util/automata/DetWordAutom.delta:()[Lscala/collection/Map;
Asciz	()I;
NameAndType	qCurrent:()I
Method	scala/xml/parsing/ValidatingMarkupHandler.qCurrent:()I
Asciz	scala/collection/mutable/StringBuilder;
class	scala/collection/mutable/StringBuilder
Method	scala/collection/mutable/StringBuilder."<init>":()V
Asciz	advanceDFA(dm): ;
String	advanceDFA(dm): 
Asciz	append;
Asciz	(Ljava/lang/Object;)Lscala/collection/mutable/StringBuilder;;
NameAndType	append:(Ljava/lang/Object;)Lscala/collection/mutable/StringBuilder;
Method	scala/collection/mutable/StringBuilder.append:(Ljava/lang/Object;)Lscala/collection/mutable/StringBuilder;
Asciz	toString;
Asciz	()Ljava/lang/String;;
NameAndType	toString:()Ljava/lang/String;
Method	scala/collection/mutable/StringBuilder.toString:()Ljava/lang/String;
Asciz	log;
Asciz	(Ljava/lang/String;)V;
NameAndType	log:(Ljava/lang/String;)V
Method	scala/xml/parsing/ValidatingMarkupHandler.log:(Ljava/lang/String;)V
Asciz	advanceDFA(trans): ;
String	advanceDFA(trans): 
Asciz	scala/xml/dtd/ContentModel$ElemName;
class	scala/xml/dtd/ContentModel$ElemName
NameAndType	"<init>":(Ljava/lang/String;)V
Method	scala/xml/dtd/ContentModel$ElemName."<init>":(Ljava/lang/String;)V
Asciz	scala/collection/MapLike;
class	scala/collection/MapLike
Asciz	get;
Asciz	(Ljava/lang/Object;)Lscala/Option;;
NameAndType	get:(Ljava/lang/Object;)Lscala/Option;
InterfaceMethod	scala/collection/MapLike.get:(Ljava/lang/Object;)Lscala/Option;
Asciz	scala/Some;
class	scala/Some
Asciz	x;
Asciz	Ljava/lang/Object;;
NameAndType	x:Ljava/lang/Object;
Field	scala/Some.x:Ljava/lang/Object;
Asciz	scala/runtime/BoxesRunTime;
class	scala/runtime/BoxesRunTime
Asciz	unboxToInt;
Asciz	(Ljava/lang/Object;)I;
NameAndType	unboxToInt:(Ljava/lang/Object;)I
Method	scala/runtime/BoxesRunTime.unboxToInt:(Ljava/lang/Object;)I
Asciz	qCurrent_$eq;
Asciz	(I)V;
NameAndType	qCurrent_$eq:(I)V
Method	scala/xml/parsing/ValidatingMarkupHandler.qCurrent_$eq:(I)V
Asciz	scala/MatchError;
class	scala/MatchError
Asciz	scala/Option;
class	scala/Option
Method	scala/Option.toString:()Ljava/lang/String;
Method	scala/MatchError."<init>":(Ljava/lang/String;)V
Asciz	DTD says, wrong element, expected one of ;
String	DTD says, wrong element, expected one of 
Asciz	keysIterator;
Asciz	()Lscala/collection/Iterator;;
NameAndType	keysIterator:()Lscala/collection/Iterator;
InterfaceMethod	scala/collection/MapLike.keysIterator:()Lscala/collection/Iterator;
Asciz	reportValidationError;
Asciz	(ILjava/lang/String;)V;
NameAndType	reportValidationError:(ILjava/lang/String;)V
Method	scala/xml/parsing/ValidatingMarkupHandler.reportValidationError:(ILjava/lang/String;)V
Asciz	this;
Asciz	Lscala/xml/parsing/ValidatingMarkupHandler;;
Asciz	dm;
Asciz	Lscala/xml/dtd/DFAContentModel;;
Asciz	temp2;
Asciz	Lscala/Some;;
Asciz	temp3;
Asciz	trans;
Asciz	Lscala/collection/Map;;
Asciz	temp1;
Asciz	Lscala/Option;;
Asciz	LocalVariableTable;
Asciz	peReference;
Asciz	scala/xml/dtd/PEReference;
class	scala/xml/dtd/PEReference
Method	scala/xml/dtd/PEReference."<init>":(Ljava/lang/String;)V
Asciz	decls;
Asciz	()Lscala/collection/immutable/List;;
NameAndType	decls:()Lscala/collection/immutable/List;
Method	scala/xml/parsing/ValidatingMarkupHandler.decls:()Lscala/collection/immutable/List;
Asciz	scala/collection/immutable/List;
class	scala/collection/immutable/List
Asciz	$colon$colon;
Asciz	(Ljava/lang/Object;)Lscala/collection/immutable/List;;
NameAndType	$colon$colon:(Ljava/lang/Object;)Lscala/collection/immutable/List;
Method	scala/collection/immutable/List.$colon$colon:(Ljava/lang/Object;)Lscala/collection/immutable/List;
Asciz	decls_$eq;
Asciz	(Lscala/collection/immutable/List;)V;
NameAndType	decls_$eq:(Lscala/collection/immutable/List;)V
Method	scala/xml/parsing/ValidatingMarkupHandler.decls_$eq:(Lscala/collection/immutable/List;)V
Asciz	name;
Asciz	notationDecl;
Asciz	(Ljava/lang/String;Lscala/xml/dtd/ExternalID;)V;
Asciz	scala/xml/dtd/NotationDecl;
class	scala/xml/dtd/NotationDecl
NameAndType	"<init>":(Ljava/lang/String;Lscala/xml/dtd/ExternalID;)V
Method	scala/xml/dtd/NotationDecl."<init>":(Ljava/lang/String;Lscala/xml/dtd/ExternalID;)V
Asciz	notat;
Asciz	extID;
Asciz	Lscala/xml/dtd/ExternalID;;
Asciz	unparsedEntityDecl;
Asciz	(Ljava/lang/String;Lscala/xml/dtd/ExternalID;Ljava/lang/String;)V;
Asciz	scala/xml/dtd/UnparsedEntityDecl;
class	scala/xml/dtd/UnparsedEntityDecl
NameAndType	"<init>":(Ljava/lang/String;Lscala/xml/dtd/ExternalID;Ljava/lang/String;)V
Method	scala/xml/dtd/UnparsedEntityDecl."<init>":(Ljava/lang/String;Lscala/xml/dtd/ExternalID;Ljava/lang/String;)V
Asciz	attListDecl;
Asciz	(Ljava/lang/String;Lscala/collection/immutable/List;)V;
Asciz	scala/xml/dtd/AttListDecl;
class	scala/xml/dtd/AttListDecl
NameAndType	"<init>":(Ljava/lang/String;Lscala/collection/immutable/List;)V
Method	scala/xml/dtd/AttListDecl."<init>":(Ljava/lang/String;Lscala/collection/immutable/List;)V
Asciz	attList;
Asciz	(Ljava/lang/String;Lscala/collection/immutable/List<Lscala/xml/dtd/AttrDecl;>;)V;
Asciz	elemDecl;
Asciz	(Ljava/lang/String;Ljava/lang/String;)V;
Asciz	scala/xml/dtd/ElemDecl;
class	scala/xml/dtd/ElemDecl
Asciz	scala/xml/dtd/ContentModel$;
class	scala/xml/dtd/ContentModel$
Asciz	Lscala/xml/dtd/ContentModel$;;
NameAndType	MODULE$:Lscala/xml/dtd/ContentModel$;
Field	scala/xml/dtd/ContentModel$.MODULE$:Lscala/xml/dtd/ContentModel$;
Asciz	parse;
Asciz	(Ljava/lang/String;)Lscala/xml/dtd/ContentModel;;
NameAndType	parse:(Ljava/lang/String;)Lscala/xml/dtd/ContentModel;
Method	scala/xml/dtd/ContentModel$.parse:(Ljava/lang/String;)Lscala/xml/dtd/ContentModel;
Asciz	(Ljava/lang/String;Lscala/xml/dtd/ContentModel;)V;
NameAndType	"<init>":(Ljava/lang/String;Lscala/xml/dtd/ContentModel;)V
Method	scala/xml/dtd/ElemDecl."<init>":(Ljava/lang/String;Lscala/xml/dtd/ContentModel;)V
Asciz	cmstr;
Asciz	elemEnd;
Asciz	(ILjava/lang/String;Ljava/lang/String;)V;
Asciz	  elemEnd;
String	  elemEnd
NameAndType	qStack:()Lscala/collection/immutable/List;
Method	scala/xml/parsing/ValidatingMarkupHandler.qStack:()Lscala/collection/immutable/List;
Asciz	scala/collection/IterableLike;
class	scala/collection/IterableLike
Asciz	head;
Asciz	()Ljava/lang/Object;;
NameAndType	head:()Ljava/lang/Object;
InterfaceMethod	scala/collection/IterableLike.head:()Ljava/lang/Object;
Asciz	scala/collection/TraversableLike;
class	scala/collection/TraversableLike
Asciz	tail;
NameAndType	tail:()Ljava/lang/Object;
InterfaceMethod	scala/collection/TraversableLike.tail:()Ljava/lang/Object;
Asciz	qStack_$eq;
NameAndType	qStack_$eq:(Lscala/collection/immutable/List;)V
Method	scala/xml/parsing/ValidatingMarkupHandler.qStack_$eq:(Lscala/collection/immutable/List;)V
NameAndType	declStack:()Lscala/collection/immutable/List;
Method	scala/xml/parsing/ValidatingMarkupHandler.declStack:()Lscala/collection/immutable/List;
Asciz	declCurrent_$eq;
Asciz	(Lscala/xml/dtd/ElemDecl;)V;
NameAndType	declCurrent_$eq:(Lscala/xml/dtd/ElemDecl;)V
Method	scala/xml/parsing/ValidatingMarkupHandler.declCurrent_$eq:(Lscala/xml/dtd/ElemDecl;)V
Asciz	declStack_$eq;
NameAndType	declStack_$eq:(Lscala/collection/immutable/List;)V
Method	scala/xml/parsing/ValidatingMarkupHandler.declStack_$eq:(Lscala/collection/immutable/List;)V
Asciz	    qCurrent now;
String	    qCurrent now
Asciz	boxToInteger;
Asciz	(I)Ljava/lang/Integer;;
NameAndType	boxToInteger:(I)Ljava/lang/Integer;
Method	scala/runtime/BoxesRunTime.boxToInteger:(I)Ljava/lang/Integer;
Asciz	    declCurrent now;
String	    declCurrent now
Asciz	()Lscala/xml/dtd/ElemDecl;;
NameAndType	declCurrent:()Lscala/xml/dtd/ElemDecl;
Method	scala/xml/parsing/ValidatingMarkupHandler.declCurrent:()Lscala/xml/dtd/ElemDecl;
Asciz	pos;
Asciz	pre;
Asciz	label;
Asciz	elemStart;
Asciz	(ILjava/lang/String;Ljava/lang/String;Lscala/xml/MetaData;Lscala/xml/NamespaceBinding;)V;
Asciz	[qCurrent = ;
String	[qCurrent = 
Asciz	 visiting ;
String	 visiting 
Asciz	];
String	]
Asciz	  checking root;
String	  checking root
NameAndType	rootLabel:()Ljava/lang/String;
Method	scala/xml/parsing/ValidatingMarkupHandler.rootLabel:()Ljava/lang/String;
Asciz	java/lang/Object;
class	java/lang/Object
Asciz	equals;
Asciz	(Ljava/lang/Object;)Z;
NameAndType	equals:(Ljava/lang/Object;)Z
Method	java/lang/Object.equals:(Ljava/lang/Object;)Z
Asciz	this element should be ;
String	this element should be 
Asciz	  checking node;
String	  checking node
Asciz	contentModel;
Asciz	()Lscala/xml/dtd/ContentModel;;
NameAndType	contentModel:()Lscala/xml/dtd/ContentModel;
Method	scala/xml/dtd/ElemDecl.contentModel:()Lscala/xml/dtd/ContentModel;
Asciz	scala/xml/dtd/ANY$;
class	scala/xml/dtd/ANY$
Asciz	Lscala/xml/dtd/ANY$;;
NameAndType	MODULE$:Lscala/xml/dtd/ANY$;
Field	scala/xml/dtd/ANY$.MODULE$:Lscala/xml/dtd/ANY$;
Asciz	scala/xml/dtd/ContentModel;
class	scala/xml/dtd/ContentModel
Method	scala/xml/dtd/ContentModel.toString:()Ljava/lang/String;
Asciz	scala/xml/dtd/EMPTY$;
class	scala/xml/dtd/EMPTY$
Asciz	Lscala/xml/dtd/EMPTY$;;
NameAndType	MODULE$:Lscala/xml/dtd/EMPTY$;
Field	scala/xml/dtd/EMPTY$.MODULE$:Lscala/xml/dtd/EMPTY$;
Asciz	DTD says, no elems, no text allowed here;
String	DTD says, no elems, no text allowed here
Asciz	scala/xml/dtd/PCDATA$;
class	scala/xml/dtd/PCDATA$
Asciz	Lscala/xml/dtd/PCDATA$;;
NameAndType	MODULE$:Lscala/xml/dtd/PCDATA$;
Field	scala/xml/dtd/PCDATA$.MODULE$:Lscala/xml/dtd/PCDATA$;
Asciz	DTD says, no elements allowed here;
String	DTD says, no elements allowed here
Asciz	scala/xml/dtd/MIXED;
class	scala/xml/dtd/MIXED
NameAndType	advanceDFA$1:(Lscala/xml/dtd/DFAContentModel;ILjava/lang/String;)V
Method	scala/xml/parsing/ValidatingMarkupHandler.advanceDFA$1:(Lscala/xml/dtd/DFAContentModel;ILjava/lang/String;)V
Asciz	scala/xml/dtd/ELEMENTS;
class	scala/xml/dtd/ELEMENTS
Asciz	lookupElemDecl;
Asciz	(Ljava/lang/String;)Lscala/xml/dtd/ElemDecl;;
NameAndType	lookupElemDecl:(Ljava/lang/String;)Lscala/xml/dtd/ElemDecl;
Method	scala/xml/parsing/ValidatingMarkupHandler.lookupElemDecl:(Ljava/lang/String;)Lscala/xml/dtd/ElemDecl;
Asciz	  done  now;
String	  done  now
Asciz	pos$1;
Asciz	label$1;
Asciz	attrs;
Asciz	Lscala/xml/MetaData;;
Asciz	scope;
Asciz	Lscala/xml/NamespaceBinding;;
Asciz	temp8;
Asciz	Lscala/xml/dtd/MIXED;;
Asciz	temp10;
Asciz	Lscala/xml/dtd/ELEMENTS;;
Asciz	temp4;
Asciz	Lscala/xml/dtd/ContentModel;;
Asciz	endDTD;
Asciz	rootLabel_$eq;
NameAndType	rootLabel_$eq:(Ljava/lang/String;)V
Method	scala/xml/parsing/ValidatingMarkupHandler.rootLabel_$eq:(Ljava/lang/String;)V
Asciz	n;
Asciz	msg;
Asciz	()Z;
Asciz	(Lscala/collection/immutable/List<Lscala/xml/dtd/ElemDecl;>;)V;
Asciz	()Lscala/collection/immutable/List<Lscala/xml/dtd/ElemDecl;>;;
Asciz	(Lscala/collection/immutable/List<Ljava/lang/Integer;>;)V;
Asciz	()Lscala/collection/immutable/List<Ljava/lang/Integer;>;;
NameAndType	rootLabel:Ljava/lang/String;
Field	scala/xml/parsing/ValidatingMarkupHandler.rootLabel:Ljava/lang/String;
Asciz	ScalaSig;
Asciz	InnerClasses;
Asciz	ElemName;
Asciz	scala/util/logging/Logged;
class	scala/util/logging/Logged
Asciz	scala/ScalaObject;
class	scala/ScalaObject

{
private final boolean isValidating;
  Signature: Z

private scala.xml.dtd.ElemDecl declCurrent;
  Signature: Lscala/xml/dtd/ElemDecl;

private scala.collection.immutable.List declStack;
  Signature: Lscala/collection/immutable/List;
  Signature: length = 0x2
   00 09 

private int qCurrent;
  Signature: I

private scala.collection.immutable.List qStack;
  Signature: Lscala/collection/immutable/List;
  Signature: length = 0x2
   00 0E 

private java.lang.String rootLabel;
  Signature: Ljava/lang/String;

public scala.xml.parsing.ValidatingMarkupHandler();
  Signature: ()V
  Code:
   Stack=2, Locals=1, Args_size=1
	aload_0
	invokespecial	Method scala/xml/parsing/MarkupHandler."<init>":()V
	aload_0
	getstatic	Field scala/collection/immutable/Nil$.MODULE$:Lscala/collection/immutable/Nil$;
	putfield	Field qStack:Lscala/collection/immutable/List;
	aload_0
	iconst_m1
	putfield	Field qCurrent:I
	aload_0
	getstatic	Field scala/collection/immutable/Nil$.MODULE$:Lscala/collection/immutable/Nil$;
	putfield	Field declStack:Lscala/collection/immutable/List;
	aload_0
	aconst_null
	putfield	Field declCurrent:Lscala/xml/dtd/ElemDecl;
	return
  Labels:

private final void advanceDFA$1(scala.xml.dtd.DFAContentModel, int, java.lang.String);
  Signature: (Lscala/xml/dtd/DFAContentModel;ILjava/lang/String;)V
  Code:
   Stack=4, Locals=8, Args_size=4
	aload_1
	invokevirtual	Method scala/xml/dtd/DFAContentModel.dfa:()Lscala/util/automata/DetWordAutom;
	invokevirtual	Method scala/util/automata/DetWordAutom.delta:()[Lscala/collection/Map;
	aload_0
	invokevirtual	Method qCurrent:()I
	aaload
	astore	6
	aload_0
	new	class scala/collection/mutable/StringBuilder
	dup
	invokespecial	Method scala/collection/mutable/StringBuilder."<init>":()V
	ldc	String advanceDFA(dm): 
	invokevirtual	Method scala/collection/mutable/StringBuilder.append:(Ljava/lang/Object;)Lscala/collection/mutable/StringBuilder;
	aload_1
	invokevirtual	Method scala/collection/mutable/StringBuilder.append:(Ljava/lang/Object;)Lscala/collection/mutable/StringBuilder;
	invokevirtual	Method scala/collection/mutable/StringBuilder.toString:()Ljava/lang/String;
	invokevirtual	Method log:(Ljava/lang/String;)V
	aload_0
	new	class scala/collection/mutable/StringBuilder
	dup
	invokespecial	Method scala/collection/mutable/StringBuilder."<init>":()V
	ldc	String advanceDFA(trans): 
	invokevirtual	Method scala/collection/mutable/StringBuilder.append:(Ljava/lang/Object;)Lscala/collection/mutable/StringBuilder;
	aload	6
	invokevirtual	Method scala/collection/mutable/StringBuilder.append:(Ljava/lang/Object;)Lscala/collection/mutable/StringBuilder;
	invokevirtual	Method scala/collection/mutable/StringBuilder.toString:()Ljava/lang/String;
	invokevirtual	Method log:(Ljava/lang/String;)V
	aload	6
	new	class scala/xml/dtd/ContentModel$ElemName
	dup
	aload_3
	invokespecial	Method scala/xml/dtd/ContentModel$ElemName."<init>":(Ljava/lang/String;)V
	invokeinterface	InterfaceMethod scala/collection/MapLike.get:(Ljava/lang/Object;)Lscala/Option;
	astore	7
	aload	7
	instanceof	class scala/Some
	ifeq	l1 // iconst_1
	aload	7
	checkcast	class scala/Some
	astore	4
	aload	4
	getfield	Field scala/Some.x:Ljava/lang/Object;
	invokestatic	Method scala/runtime/BoxesRunTime.unboxToInt:(Ljava/lang/Object;)I
	istore	5
	iconst_1
	ifeq	l2 // new
	aload_0
	iload	5
	invokevirtual	Method qCurrent_$eq:(I)V
	goto	l3 // return
l2	new	class scala/MatchError
	dup
	aload	7
	invokevirtual	Method scala/Option.toString:()Ljava/lang/String;
	invokespecial	Method scala/MatchError."<init>":(Ljava/lang/String;)V
	athrow
l1	iconst_1
	ifeq	l4 // new
	aload_0
	iload_2
	new	class scala/collection/mutable/StringBuilder
	dup
	invokespecial	Method scala/collection/mutable/StringBuilder."<init>":()V
	ldc	String DTD says, wrong element, expected one of 
	invokevirtual	Method scala/collection/mutable/StringBuilder.append:(Ljava/lang/Object;)Lscala/collection/mutable/StringBuilder;
	aload	6
	invokeinterface	InterfaceMethod scala/collection/MapLike.keysIterator:()Lscala/collection/Iterator;
	invokevirtual	Method scala/collection/mutable/StringBuilder.append:(Ljava/lang/Object;)Lscala/collection/mutable/StringBuilder;
	invokevirtual	Method scala/collection/mutable/StringBuilder.toString:()Ljava/lang/String;
	invokevirtual	Method reportValidationError:(ILjava/lang/String;)V
l3	return
l4	new	class scala/MatchError
	dup
	aload	7
	invokevirtual	Method scala/Option.toString:()Ljava/lang/String;
	invokespecial	Method scala/MatchError."<init>":(Ljava/lang/String;)V
	athrow
  Labels:
   	l2 = 116 // new
   	l1 = 129 // iconst_1
   	l3 = 163 // return
   	l4 = 164 // new
  LocalVariableTable: 
   Start  Length  Slot  Name   Signature
   0      177      0    this       Lscala/xml/parsing/ValidatingMarkupHandler;
   0      177      1    dm       Lscala/xml/dtd/DFAContentModel;
   93      36      4    temp2       Lscala/Some;
   103      26      5    temp3       I
   14      163      6    trans       Lscala/collection/Map;
   78      99      7    temp1       Lscala/Option;


public abstract void reportValidationError(int, java.lang.String);
  Signature: (ILjava/lang/String;)V

public final void peReference(java.lang.String);
  Signature: (Ljava/lang/String;)V
  Code:
   Stack=4, Locals=3, Args_size=2
	aload_0
	new	class scala/xml/dtd/PEReference
	dup
	aload_1
	invokespecial	Method scala/xml/dtd/PEReference."<init>":(Ljava/lang/String;)V
	astore_2
	aload_0
	invokevirtual	Method decls:()Lscala/collection/immutable/List;
	aload_2
	invokevirtual	Method scala/collection/immutable/List.$colon$colon:(Ljava/lang/Object;)Lscala/collection/immutable/List;
	invokevirtual	Method decls_$eq:(Lscala/collection/immutable/List;)V
	return
  Labels:
  LocalVariableTable: 
   Start  Length  Slot  Name   Signature
   0      22      0    this       Lscala/xml/parsing/ValidatingMarkupHandler;
   0      22      1    name       Ljava/lang/String;


public final void notationDecl(java.lang.String, scala.xml.dtd.ExternalID);
  Signature: (Ljava/lang/String;Lscala/xml/dtd/ExternalID;)V
  Code:
   Stack=5, Locals=4, Args_size=3
	aload_0
	new	class scala/xml/dtd/NotationDecl
	dup
	aload_1
	aload_2
	invokespecial	Method scala/xml/dtd/NotationDecl."<init>":(Ljava/lang/String;Lscala/xml/dtd/ExternalID;)V
	astore_3
	aload_0
	invokevirtual	Method decls:()Lscala/collection/immutable/List;
	aload_3
	invokevirtual	Method scala/collection/immutable/List.$colon$colon:(Ljava/lang/Object;)Lscala/collection/immutable/List;
	invokevirtual	Method decls_$eq:(Lscala/collection/immutable/List;)V
	return
  Labels:
  LocalVariableTable: 
   Start  Length  Slot  Name   Signature
   0      23      0    this       Lscala/xml/parsing/ValidatingMarkupHandler;
   0      23      1    notat       Ljava/lang/String;
   0      23      2    extID       Lscala/xml/dtd/ExternalID;


public final void unparsedEntityDecl(java.lang.String, scala.xml.dtd.ExternalID, java.lang.String);
  Signature: (Ljava/lang/String;Lscala/xml/dtd/ExternalID;Ljava/lang/String;)V
  Code:
   Stack=6, Locals=5, Args_size=4
	aload_0
	new	class scala/xml/dtd/UnparsedEntityDecl
	dup
	aload_1
	aload_2
	aload_3
	invokespecial	Method scala/xml/dtd/UnparsedEntityDecl."<init>":(Ljava/lang/String;Lscala/xml/dtd/ExternalID;Ljava/lang/String;)V
	astore	4
	aload_0
	invokevirtual	Method decls:()Lscala/collection/immutable/List;
	aload	4
	invokevirtual	Method scala/collection/immutable/List.$colon$colon:(Ljava/lang/Object;)Lscala/collection/immutable/List;
	invokevirtual	Method decls_$eq:(Lscala/collection/immutable/List;)V
	return
  Labels:
  LocalVariableTable: 
   Start  Length  Slot  Name   Signature
   0      26      0    this       Lscala/xml/parsing/ValidatingMarkupHandler;
   0      26      1    name       Ljava/lang/String;
   0      26      2    extID       Lscala/xml/dtd/ExternalID;
   0      26      3    notat       Ljava/lang/String;


public final void attListDecl(java.lang.String, scala.collection.immutable.List);
  Signature: (Ljava/lang/String;Lscala/collection/immutable/List;)V
  Code:
   Stack=5, Locals=4, Args_size=3
	aload_0
	new	class scala/xml/dtd/AttListDecl
	dup
	aload_1
	aload_2
	invokespecial	Method scala/xml/dtd/AttListDecl."<init>":(Ljava/lang/String;Lscala/collection/immutable/List;)V
	astore_3
	aload_0
	invokevirtual	Method decls:()Lscala/collection/immutable/List;
	aload_3
	invokevirtual	Method scala/collection/immutable/List.$colon$colon:(Ljava/lang/Object;)Lscala/collection/immutable/List;
	invokevirtual	Method decls_$eq:(Lscala/collection/immutable/List;)V
	return
  Labels:
  LocalVariableTable: 
   Start  Length  Slot  Name   Signature
   0      23      0    this       Lscala/xml/parsing/ValidatingMarkupHandler;
   0      23      1    name       Ljava/lang/String;
   0      23      2    attList       Lscala/collection/immutable/List;

  Signature: length = 0x2
   00 FFFFFFAC 

public final void elemDecl(java.lang.String, java.lang.String);
  Signature: (Ljava/lang/String;Ljava/lang/String;)V
  Code:
   Stack=6, Locals=4, Args_size=3
	aload_0
	new	class scala/xml/dtd/ElemDecl
	dup
	aload_1
	getstatic	Field scala/xml/dtd/ContentModel$.MODULE$:Lscala/xml/dtd/ContentModel$;
	aload_2
	invokevirtual	Method scala/xml/dtd/ContentModel$.parse:(Ljava/lang/String;)Lscala/xml/dtd/ContentModel;
	invokespecial	Method scala/xml/dtd/ElemDecl."<init>":(Ljava/lang/String;Lscala/xml/dtd/ContentModel;)V
	astore_3
	aload_0
	invokevirtual	Method decls:()Lscala/collection/immutable/List;
	aload_3
	invokevirtual	Method scala/collection/immutable/List.$colon$colon:(Ljava/lang/Object;)Lscala/collection/immutable/List;
	invokevirtual	Method decls_$eq:(Lscala/collection/immutable/List;)V
	return
  Labels:
  LocalVariableTable: 
   Start  Length  Slot  Name   Signature
   0      29      0    this       Lscala/xml/parsing/ValidatingMarkupHandler;
   0      29      1    name       Ljava/lang/String;
   0      29      2    cmstr       Ljava/lang/String;


public void elemEnd(int, java.lang.String, java.lang.String);
  Signature: (ILjava/lang/String;Ljava/lang/String;)V
  Code:
   Stack=3, Locals=5, Args_size=4
	aload_0
	ldc	String   elemEnd
	invokevirtual	Method log:(Ljava/lang/String;)V
	aload_0
	aload_0
	invokevirtual	Method qStack:()Lscala/collection/immutable/List;
	invokeinterface	InterfaceMethod scala/collection/IterableLike.head:()Ljava/lang/Object;
	invokestatic	Method scala/runtime/BoxesRunTime.unboxToInt:(Ljava/lang/Object;)I
	invokevirtual	Method qCurrent_$eq:(I)V
	aload_0
	aload_0
	invokevirtual	Method qStack:()Lscala/collection/immutable/List;
	invokeinterface	InterfaceMethod scala/collection/TraversableLike.tail:()Ljava/lang/Object;
	checkcast	class scala/collection/immutable/List
	invokevirtual	Method qStack_$eq:(Lscala/collection/immutable/List;)V
	aload_0
	aload_0
	invokevirtual	Method declStack:()Lscala/collection/immutable/List;
	invokeinterface	InterfaceMethod scala/collection/IterableLike.head:()Ljava/lang/Object;
	checkcast	class scala/xml/dtd/ElemDecl
	invokevirtual	Method declCurrent_$eq:(Lscala/xml/dtd/ElemDecl;)V
	aload_0
	aload_0
	invokevirtual	Method declStack:()Lscala/collection/immutable/List;
	invokeinterface	InterfaceMethod scala/collection/TraversableLike.tail:()Ljava/lang/Object;
	checkcast	class scala/collection/immutable/List
	invokevirtual	Method declStack_$eq:(Lscala/collection/immutable/List;)V
	aload_0
	new	class scala/collection/mutable/StringBuilder
	dup
	invokespecial	Method scala/collection/mutable/StringBuilder."<init>":()V
	ldc	String     qCurrent now
	invokevirtual	Method scala/collection/mutable/StringBuilder.append:(Ljava/lang/Object;)Lscala/collection/mutable/StringBuilder;
	aload_0
	invokevirtual	Method qCurrent:()I
	istore	4
	iload	4
	invokestatic	Method scala/runtime/BoxesRunTime.boxToInteger:(I)Ljava/lang/Integer;
	invokevirtual	Method scala/collection/mutable/StringBuilder.append:(Ljava/lang/Object;)Lscala/collection/mutable/StringBuilder;
	invokevirtual	Method scala/collection/mutable/StringBuilder.toString:()Ljava/lang/String;
	invokevirtual	Method log:(Ljava/lang/String;)V
	aload_0
	new	class scala/collection/mutable/StringBuilder
	dup
	invokespecial	Method scala/collection/mutable/StringBuilder."<init>":()V
	ldc	String     declCurrent now
	invokevirtual	Method scala/collection/mutable/StringBuilder.append:(Ljava/lang/Object;)Lscala/collection/mutable/StringBuilder;
	aload_0
	invokevirtual	Method declCurrent:()Lscala/xml/dtd/ElemDecl;
	invokevirtual	Method scala/collection/mutable/StringBuilder.append:(Ljava/lang/Object;)Lscala/collection/mutable/StringBuilder;
	invokevirtual	Method scala/collection/mutable/StringBuilder.toString:()Ljava/lang/String;
	invokevirtual	Method log:(Ljava/lang/String;)V
	return
  Labels:
  LocalVariableTable: 
   Start  Length  Slot  Name   Signature
   0      130      0    this       Lscala/xml/parsing/ValidatingMarkupHandler;
   0      130      1    pos       I
   0      130      2    pre       Ljava/lang/String;
   0      130      3    label       Ljava/lang/String;


public void elemStart(int, java.lang.String, java.lang.String, scala.xml.MetaData, scala.xml.NamespaceBinding);
  Signature: (ILjava/lang/String;Ljava/lang/String;Lscala/xml/MetaData;Lscala/xml/NamespaceBinding;)V
  Code:
   Stack=4, Locals=13, Args_size=6
	aload_0
	new	class scala/collection/mutable/StringBuilder
	dup
	invokespecial	Method scala/collection/mutable/StringBuilder."<init>":()V
	ldc	String [qCurrent = 
	invokevirtual	Method scala/collection/mutable/StringBuilder.append:(Ljava/lang/Object;)Lscala/collection/mutable/StringBuilder;
	aload_0
	invokevirtual	Method qCurrent:()I
	istore	6
	iload	6
	invokestatic	Method scala/runtime/BoxesRunTime.boxToInteger:(I)Ljava/lang/Integer;
	invokevirtual	Method scala/collection/mutable/StringBuilder.append:(Ljava/lang/Object;)Lscala/collection/mutable/StringBuilder;
	ldc	String  visiting 
	invokevirtual	Method scala/collection/mutable/StringBuilder.append:(Ljava/lang/Object;)Lscala/collection/mutable/StringBuilder;
	aload_3
	invokevirtual	Method scala/collection/mutable/StringBuilder.append:(Ljava/lang/Object;)Lscala/collection/mutable/StringBuilder;
	ldc	String ]
	invokevirtual	Method scala/collection/mutable/StringBuilder.append:(Ljava/lang/Object;)Lscala/collection/mutable/StringBuilder;
	invokevirtual	Method scala/collection/mutable/StringBuilder.toString:()Ljava/lang/String;
	invokevirtual	Method log:(Ljava/lang/String;)V
	aload_0
	invokevirtual	Method qCurrent:()I
	iconst_m1
	if_icmpne	l1 // aload_0
	aload_0
	ldc	String   checking root
	invokevirtual	Method log:(Ljava/lang/String;)V
	aload_3
	aload_0
	invokevirtual	Method rootLabel:()Ljava/lang/String;
	astore	7
	dup
	ifnonnull	l2 // aload
	pop
	aload	7
	ifnull	l3 // aload_0
	goto	l4 // aload_0
l2	aload	7
	invokevirtual	Method java/lang/Object.equals:(Ljava/lang/Object;)Z
	ifne	l3 // aload_0
l4	aload_0
	iload_1
	new	class scala/collection/mutable/StringBuilder
	dup
	invokespecial	Method scala/collection/mutable/StringBuilder."<init>":()V
	ldc	String this element should be 
	invokevirtual	Method scala/collection/mutable/StringBuilder.append:(Ljava/lang/Object;)Lscala/collection/mutable/StringBuilder;
	aload_0
	invokevirtual	Method rootLabel:()Ljava/lang/String;
	invokevirtual	Method scala/collection/mutable/StringBuilder.append:(Ljava/lang/Object;)Lscala/collection/mutable/StringBuilder;
	invokevirtual	Method scala/collection/mutable/StringBuilder.toString:()Ljava/lang/String;
	invokevirtual	Method reportValidationError:(ILjava/lang/String;)V
	goto	l3 // aload_0
l1	aload_0
	ldc	String   checking node
	invokevirtual	Method log:(Ljava/lang/String;)V
	aload_0
	invokevirtual	Method declCurrent:()Lscala/xml/dtd/ElemDecl;
	invokevirtual	Method scala/xml/dtd/ElemDecl.contentModel:()Lscala/xml/dtd/ContentModel;
	astore	12
	getstatic	Field scala/xml/dtd/ANY$.MODULE$:Lscala/xml/dtd/ANY$;
	dup
	ifnonnull	l5 // aload
	pop
	aload	12
	ifnull	l6 // iconst_1
	goto	l7 // getstatic
l5	aload	12
	invokevirtual	Method java/lang/Object.equals:(Ljava/lang/Object;)Z
	ifeq	l7 // getstatic
l6	iconst_1
	ifne	l3 // aload_0
	new	class scala/MatchError
	dup
	aload	12
	invokevirtual	Method scala/xml/dtd/ContentModel.toString:()Ljava/lang/String;
	invokespecial	Method scala/MatchError."<init>":(Ljava/lang/String;)V
	athrow
l7	getstatic	Field scala/xml/dtd/EMPTY$.MODULE$:Lscala/xml/dtd/EMPTY$;
	dup
	ifnonnull	l8 // aload
	pop
	aload	12
	ifnull	l9 // iconst_1
	goto	l10 // getstatic
l8	aload	12
	invokevirtual	Method java/lang/Object.equals:(Ljava/lang/Object;)Z
	ifeq	l10 // getstatic
l9	iconst_1
	ifeq	l11 // new
	aload_0
	iload_1
	ldc_w	String DTD says, no elems, no text allowed here
	invokevirtual	Method reportValidationError:(ILjava/lang/String;)V
	goto	l3 // aload_0
l11	new	class scala/MatchError
	dup
	aload	12
	invokevirtual	Method scala/xml/dtd/ContentModel.toString:()Ljava/lang/String;
	invokespecial	Method scala/MatchError."<init>":(Ljava/lang/String;)V
	athrow
l10	getstatic	Field scala/xml/dtd/PCDATA$.MODULE$:Lscala/xml/dtd/PCDATA$;
	dup
	ifnonnull	l12 // aload
	pop
	aload	12
	ifnull	l13 // iconst_1
	goto	l14 // aload
l12	aload	12
	invokevirtual	Method java/lang/Object.equals:(Ljava/lang/Object;)Z
	ifeq	l14 // aload
l13	iconst_1
	ifeq	l15 // new
	aload_0
	iload_1
	ldc_w	String DTD says, no elements allowed here
	invokevirtual	Method reportValidationError:(ILjava/lang/String;)V
	goto	l3 // aload_0
l15	new	class scala/MatchError
	dup
	aload	12
	invokevirtual	Method scala/xml/dtd/ContentModel.toString:()Ljava/lang/String;
	invokespecial	Method scala/MatchError."<init>":(Ljava/lang/String;)V
	athrow
l14	aload	12
	instanceof	class scala/xml/dtd/MIXED
	ifeq	l16 // aload
	aload	12
	checkcast	class scala/xml/dtd/MIXED
	astore	8
	iconst_1
	ifeq	l17 // new
	aload_0
	aload	8
	iload_1
	aload_3
	invokespecial	Method advanceDFA$1:(Lscala/xml/dtd/DFAContentModel;ILjava/lang/String;)V
	goto	l3 // aload_0
l17	new	class scala/MatchError
	dup
	aload	12
	invokevirtual	Method scala/xml/dtd/ContentModel.toString:()Ljava/lang/String;
	invokespecial	Method scala/MatchError."<init>":(Ljava/lang/String;)V
	athrow
l16	aload	12
	instanceof	class scala/xml/dtd/ELEMENTS
	ifeq	l18 // new
	aload	12
	checkcast	class scala/xml/dtd/ELEMENTS
	astore	9
	iconst_1
	ifeq	l19 // new
	aload_0
	aload	9
	iload_1
	aload_3
	invokespecial	Method advanceDFA$1:(Lscala/xml/dtd/DFAContentModel;ILjava/lang/String;)V
l3	aload_0
	aload_0
	invokevirtual	Method qCurrent:()I
	istore	10
	aload_0
	invokevirtual	Method qStack:()Lscala/collection/immutable/List;
	iload	10
	invokestatic	Method scala/runtime/BoxesRunTime.boxToInteger:(I)Ljava/lang/Integer;
	invokevirtual	Method scala/collection/immutable/List.$colon$colon:(Ljava/lang/Object;)Lscala/collection/immutable/List;
	invokevirtual	Method qStack_$eq:(Lscala/collection/immutable/List;)V
	aload_0
	aload_0
	invokevirtual	Method declCurrent:()Lscala/xml/dtd/ElemDecl;
	astore	11
	aload_0
	invokevirtual	Method declStack:()Lscala/collection/immutable/List;
	aload	11
	invokevirtual	Method scala/collection/immutable/List.$colon$colon:(Ljava/lang/Object;)Lscala/collection/immutable/List;
	invokevirtual	Method declStack_$eq:(Lscala/collection/immutable/List;)V
	aload_0
	aload_0
	aload_3
	invokevirtual	Method lookupElemDecl:(Ljava/lang/String;)Lscala/xml/dtd/ElemDecl;
	invokevirtual	Method declCurrent_$eq:(Lscala/xml/dtd/ElemDecl;)V
	aload_0
	iconst_0
	invokevirtual	Method qCurrent_$eq:(I)V
	aload_0
	ldc_w	String   done  now
	invokevirtual	Method log:(Ljava/lang/String;)V
	return
l19	new	class scala/MatchError
	dup
	aload	12
	invokevirtual	Method scala/xml/dtd/ContentModel.toString:()Ljava/lang/String;
	invokespecial	Method scala/MatchError."<init>":(Ljava/lang/String;)V
	athrow
l18	new	class scala/MatchError
	dup
	aload	12
	invokevirtual	Method scala/xml/dtd/ContentModel.toString:()Ljava/lang/String;
	invokespecial	Method scala/MatchError."<init>":(Ljava/lang/String;)V
	athrow
  Labels:
   	l2 = 81 // aload
   	l4 = 89 // aload_0
   	l1 = 119 // aload_0
   	l5 = 150 // aload
   	l6 = 158 // iconst_1
   	l7 = 175 // getstatic
   	l8 = 191 // aload
   	l9 = 199 // iconst_1
   	l11 = 214 // new
   	l10 = 227 // getstatic
   	l12 = 243 // aload
   	l13 = 251 // iconst_1
   	l15 = 266 // new
   	l14 = 279 // aload
   	l17 = 309 // new
   	l16 = 322 // aload
   	l3 = 349 // aload_0
   	l19 = 412 // new
   	l18 = 425 // new
  LocalVariableTable: 
   Start  Length  Slot  Name   Signature
   0      438      0    this       Lscala/xml/parsing/ValidatingMarkupHandler;
   0      438      1    pos$1       I
   0      438      2    pre       Ljava/lang/String;
   0      438      3    label$1       Ljava/lang/String;
   0      438      4    attrs       Lscala/xml/MetaData;
   0      438      5    scope       Lscala/xml/NamespaceBinding;
   294      28      8    temp8       Lscala/xml/dtd/MIXED;
   337      12      9    temp10       Lscala/xml/dtd/ELEMENTS;
   412      13      9    temp10       Lscala/xml/dtd/ELEMENTS;
   134      215      12    temp4       Lscala/xml/dtd/ContentModel;
   412      26      12    temp4       Lscala/xml/dtd/ContentModel;


public void endDTD(java.lang.String);
  Signature: (Ljava/lang/String;)V
  Code:
   Stack=2, Locals=2, Args_size=2
	aload_0
	aload_1
	invokevirtual	Method rootLabel_$eq:(Ljava/lang/String;)V
	return
  Labels:
  LocalVariableTable: 
   Start  Length  Slot  Name   Signature
   0      6      0    this       Lscala/xml/parsing/ValidatingMarkupHandler;
   0      6      1    n       Ljava/lang/String;


public void log(java.lang.String);
  Signature: (Ljava/lang/String;)V
  Code:
   Stack=0, Locals=2, Args_size=2
	return
  Labels:
  LocalVariableTable: 
   Start  Length  Slot  Name   Signature
   0      1      0    this       Lscala/xml/parsing/ValidatingMarkupHandler;
   0      1      1    msg       Ljava/lang/String;


public final boolean isValidating();
  Signature: ()Z
  Code:
   Stack=1, Locals=1, Args_size=1
	iconst_1
	ireturn
  Labels:

public void declCurrent_$eq(scala.xml.dtd.ElemDecl);
  Signature: (Lscala/xml/dtd/ElemDecl;)V
  Code:
   Stack=2, Locals=2, Args_size=2
	aload_0
	aload_1
	putfield	Field declCurrent:Lscala/xml/dtd/ElemDecl;
	return
  Labels:

public scala.xml.dtd.ElemDecl declCurrent();
  Signature: ()Lscala/xml/dtd/ElemDecl;
  Code:
   Stack=1, Locals=1, Args_size=1
	aload_0
	getfield	Field declCurrent:Lscala/xml/dtd/ElemDecl;
	areturn
  Labels:

public void declStack_$eq(scala.collection.immutable.List);
  Signature: (Lscala/collection/immutable/List;)V
  Code:
   Stack=2, Locals=2, Args_size=2
	aload_0
	aload_1
	putfield	Field declStack:Lscala/collection/immutable/List;
	return
  Labels:
  Signature: length = 0x2
   01 38 

public scala.collection.immutable.List declStack();
  Signature: ()Lscala/collection/immutable/List;
  Code:
   Stack=1, Locals=1, Args_size=1
	aload_0
	getfield	Field declStack:Lscala/collection/immutable/List;
	areturn
  Labels:
  Signature: length = 0x2
   01 39 

public void qCurrent_$eq(int);
  Signature: (I)V
  Code:
   Stack=2, Locals=2, Args_size=2
	aload_0
	iload_1
	putfield	Field qCurrent:I
	return
  Labels:

public int qCurrent();
  Signature: ()I
  Code:
   Stack=1, Locals=1, Args_size=1
	aload_0
	getfield	Field qCurrent:I
	ireturn
  Labels:

public void qStack_$eq(scala.collection.immutable.List);
  Signature: (Lscala/collection/immutable/List;)V
  Code:
   Stack=2, Locals=2, Args_size=2
	aload_0
	aload_1
	putfield	Field qStack:Lscala/collection/immutable/List;
	return
  Labels:
  Signature: length = 0x2
   01 3A 

public scala.collection.immutable.List qStack();
  Signature: ()Lscala/collection/immutable/List;
  Code:
   Stack=1, Locals=1, Args_size=1
	aload_0
	getfield	Field qStack:Lscala/collection/immutable/List;
	areturn
  Labels:
  Signature: length = 0x2
   01 3B 

public void rootLabel_$eq(java.lang.String);
  Signature: (Ljava/lang/String;)V
  Code:
   Stack=2, Locals=2, Args_size=2
	aload_0
	aload_1
	putfield	Field rootLabel:Ljava/lang/String;
	return
  Labels:

public java.lang.String rootLabel();
  Signature: ()Ljava/lang/String;
  Code:
   Stack=1, Locals=1, Args_size=1
	aload_0
	getfield	Field rootLabel:Ljava/lang/String;
	areturn
  Labels:

}

