Compiled from "ValidatingMarkupHandler.scala"
public abstract class scala.xml.parsing.ValidatingMarkupHandler extends scala.xml.parsing.MarkupHandler implements scala.util.logging.Logged,scala.ScalaObject
  SourceFile: "ValidatingMarkupHandler.scala"
  ScalaSig: length = 0x5B4
   05 00 FFFFFF81 42 06 08 01 02 FFFFFF84 FFFFFF80 FFFFFF80 FFFFFF81 00 09 02 17
   56 61 6C 69 64 61 74 69 6E 67 4D 61 72 6B 75 70
   48 61 6E 64 6C 65 72 0A 02 03 04 01 07 70 61 72
   73 69 6E 67 0A 02 05 06 01 03 78 6D 6C 0A 01 07
   01 05 73 63 61 6C 61 03 00 13 04 00 0A 0E 16 10
   02 0B 0C 0D 01 02 09 02 0D 02 02 0D 4D 61 72 6B
   75 70 48 61 6E 64 6C 65 72 10 02 0F 14 0D 01 10
   0A 02 11 12 01 07 6C 6F 67 67 69 6E 67 0A 02 13
   06 01 04 75 74 69 6C 09 02 15 10 02 06 4C 6F 67
   67 65 64 10 02 17 18 0D 01 06 09 02 19 06 02 0B
   53 63 61 6C 61 4F 62 6A 65 63 74 08 05 1B 00 FFFFFF84
   00 1C 01 06 3C 69 6E 69 74 3E 14 01 1D 10 02 0B
   00 08 07 1F 00 FFFFFFC0 FFFFFF80 FFFFFF84 00 20 01 09 72 6F 6F 74
   4C 61 62 65 6C 15 01 21 10 02 22 25 0E 02 17 23
   09 02 24 06 01 06 50 72 65 64 65 66 09 02 26 27
   02 06 53 74 72 69 6E 67 0A 02 24 06 08 07 29 00
   FFFFFFC0 FFFFFF80 FFFFFF84 00 2A 01 0D 72 6F 6F 74 4C 61 62 65 6C
   5F 24 65 71 14 02 2B 2E 10 02 17 2C 09 02 2D 06
   02 04 55 6E 69 74 08 07 2F 28 FFFFFF81 FFFFFF80 FFFFFFC0 00 21 01
   03 78 24 31 08 06 31 00 FFFFFFA0 FFFFFFA0 04 21 01 0A 72 6F
   6F 74 4C 61 62 65 6C 20 08 07 33 00 FFFFFFC0 FFFFFF80 FFFFFF84 00
   34 01 06 71 53 74 61 63 6B 15 01 35 10 03 36 3E
   41 0E 02 37 3C 0E 02 38 3B 0D 01 39 0A 02 3A 08
   01 06 3C 72 6F 6F 74 3E 09 01 07 09 02 3D 06 01
   07 70 61 63 6B 61 67 65 09 02 3F 40 02 04 4C 69
   73 74 0A 02 3D 06 10 02 17 42 09 02 43 06 02 03
   49 6E 74 08 07 45 00 FFFFFFC0 FFFFFF80 FFFFFF84 00 46 01 0A 71 53
   74 61 63 6B 5F 24 65 71 14 02 2B 47 08 07 2F 44
   FFFFFF81 FFFFFF80 FFFFFFC0 00 35 08 06 49 00 FFFFFFA0 FFFFFFA0 04 35 01 07 71
   53 74 61 63 6B 20 08 07 4B 00 FFFFFFC0 FFFFFF80 FFFFFF84 00 4C 01
   08 71 43 75 72 72 65 6E 74 15 01 41 08 07 4E 00
   FFFFFFC0 FFFFFF80 FFFFFF84 00 4F 01 0C 71 43 75 72 72 65 6E 74 5F
   24 65 71 14 02 2B 50 08 07 2F 4D FFFFFF81 FFFFFF80 FFFFFFC0 00 41
   08 06 52 00 FFFFFFA0 FFFFFFA0 04 41 01 09 71 43 75 72 72 65
   6E 74 20 08 07 54 00 FFFFFFC0 FFFFFF80 FFFFFF84 00 55 01 09 64 65
   63 6C 53 74 61 63 6B 15 01 56 10 03 36 3E 57 10
   02 58 5B 0D 01 59 0A 02 5A 04 01 03 64 74 64 09
   02 5C 59 02 08 45 6C 65 6D 44 65 63 6C 08 07 5E
   00 FFFFFFC0 FFFFFF80 FFFFFF84 00 5F 01 0D 64 65 63 6C 53 74 61 63
   6B 5F 24 65 71 14 02 2B 60 08 07 2F 5D FFFFFF81 FFFFFF80 FFFFFFC0
   00 56 08 06 62 00 FFFFFFA0 FFFFFFA0 04 56 01 0A 64 65 63 6C
   53 74 61 63 6B 20 08 07 64 00 FFFFFFC0 FFFFFF80 FFFFFF84 00 65 01
   0B 64 65 63 6C 43 75 72 72 65 6E 74 15 01 57 08
   07 67 00 FFFFFFC0 FFFFFF80 FFFFFF84 00 68 01 0F 64 65 63 6C 43 75
   72 72 65 6E 74 5F 24 65 71 14 02 2B 69 08 07 2F
   66 FFFFFF81 FFFFFF80 FFFFFFC0 00 57 08 06 6B 00 FFFFFFA0 FFFFFFA0 04 57 01 0C
   64 65 63 6C 43 75 72 72 65 6E 74 20 08 07 6D 00
   FFFFFFC2 FFFFFF80 FFFFFF84 22 6E 01 0C 69 73 56 61 6C 69 64 61 74
   69 6E 67 15 01 6F 0F 01 70 19 01 01 08 06 72 00
   FFFFFFA0 FFFFFF80 06 6F 01 0D 69 73 56 61 6C 69 64 61 74 69
   6E 67 20 08 05 74 00 FFFFFF84 20 75 01 03 6C 6F 67 14
   02 2B 76 08 05 77 73 FFFFFFC0 00 21 01 03 6D 73 67 08
   05 79 00 FFFFFF84 20 7A 01 06 65 6E 64 44 54 44 14 02
   2B 7B 08 05 7C 78 FFFFFFC0 00 21 01 01 6E 08 05 7E 00
   FFFFFF84 20 7F 01 09 65 6C 65 6D 53 74 61 72 74 14 0B
   2B FFFFFF81 00 FFFFFF81 02 FFFFFF81 04 FFFFFF81 06 FFFFFF81 0C 08 06 FFFFFF81 01 7D
   FFFFFFC0 00 41 01 03 70 6F 73 08 06 FFFFFF81 03 7D FFFFFFC0 00 21
   01 03 70 72 65 08 06 FFFFFF81 05 7D FFFFFFC0 00 21 01 05 6C
   61 62 65 6C 08 07 FFFFFF81 07 7D FFFFFFC0 00 FFFFFF81 08 01 05 61
   74 74 72 73 10 04 FFFFFF81 09 FFFFFF81 0A 0D 01 04 09 03 FFFFFF81
   0B 04 02 08 4D 65 74 61 44 61 74 61 08 07 FFFFFF81 0D
   7D FFFFFFC0 00 FFFFFF81 0E 01 05 73 63 6F 70 65 10 04 FFFFFF81 09
   FFFFFF81 0F 09 03 FFFFFF81 10 04 02 10 4E 61 6D 65 73 70 61
   63 65 42 69 6E 64 69 6E 67 08 07 FFFFFF81 12 00 FFFFFF84 20
   FFFFFF81 13 01 07 65 6C 65 6D 45 6E 64 14 07 2B FFFFFF81 14
   FFFFFF81 15 FFFFFF81 16 08 07 FFFFFF81 01 FFFFFF81 11 FFFFFFC0 00 41 08 07 FFFFFF81
   03 FFFFFF81 11 FFFFFFC0 00 21 08 07 FFFFFF81 05 FFFFFF81 11 FFFFFFC0 00 21 08
   07 FFFFFF81 18 00 FFFFFF84 22 FFFFFF81 19 01 08 65 6C 65 6D 44 65
   63 6C 14 05 2B FFFFFF81 1A FFFFFF81 1C 08 07 FFFFFF81 1B FFFFFF81 17 FFFFFFC0
   00 21 01 04 6E 61 6D 65 08 07 FFFFFF81 1D FFFFFF81 17 FFFFFFC0 00
   21 01 05 63 6D 73 74 72 08 07 FFFFFF81 1F 00 FFFFFF84 22 FFFFFF81
   20 01 0B 61 74 74 4C 69 73 74 44 65 63 6C 14 05
   2B FFFFFF81 21 FFFFFF81 22 08 07 FFFFFF81 1B FFFFFF81 1E FFFFFFC0 00 21 08 08
   FFFFFF81 23 FFFFFF81 1E FFFFFFC0 00 FFFFFF81 24 01 07 61 74 74 4C 69 73
   74 10 04 36 3E FFFFFF81 25 10 03 58 FFFFFF81 26 09 03 FFFFFF81 27
   59 02 08 41 74 74 72 44 65 63 6C 08 07 FFFFFF81 29 00
   FFFFFF84 22 FFFFFF81 2A 01 12 75 6E 70 61 72 73 65 64 45 6E
   74 69 74 79 44 65 63 6C 14 07 2B FFFFFF81 2B FFFFFF81 2C FFFFFF81
   31 08 07 FFFFFF81 1B FFFFFF81 28 FFFFFFC0 00 21 08 08 FFFFFF81 2D FFFFFF81 28
   FFFFFFC0 00 FFFFFF81 2E 01 05 65 78 74 49 44 10 03 58 FFFFFF81 2F
   09 03 FFFFFF81 30 59 02 0A 45 78 74 65 72 6E 61 6C 49
   44 08 07 FFFFFF81 32 FFFFFF81 28 FFFFFFC0 00 21 01 05 6E 6F 74 61
   74 08 07 FFFFFF81 34 00 FFFFFF84 22 FFFFFF81 35 01 0C 6E 6F 74 61
   74 69 6F 6E 44 65 63 6C 14 05 2B FFFFFF81 36 FFFFFF81 37 08
   07 FFFFFF81 32 FFFFFF81 33 FFFFFFC0 00 21 08 08 FFFFFF81 2D FFFFFF81 33 FFFFFFC0 00
   FFFFFF81 2E 08 07 FFFFFF81 39 00 FFFFFF84 22 FFFFFF81 3A 01 0B 70 65 52
   65 66 65 72 65 6E 63 65 14 03 2B FFFFFF81 3B 08 07 FFFFFF81
   1B FFFFFF81 38 FFFFFFC0 00 21 08 07 FFFFFF81 3D 00 FFFFFF86 00 FFFFFF81 3E 01
   15 72 65 70 6F 72 74 56 61 6C 69 64 61 74 69 6F
   6E 45 72 72 6F 72 14 05 2B FFFFFF81 3F FFFFFF81 40 08 07 FFFFFF81
   01 FFFFFF81 3C FFFFFFC0 00 41 08 07 FFFFFF81 41 FFFFFF81 3C FFFFFFC0 00 21 01
   03 73 74 72 
  InnerClass: 
   public abstract #332= #329 of #331; //RegExp=class scala/util/regexp/Base$RegExp of class scala/util/regexp/Base
   public #333= #78 of #295; //ElemName=class scala/xml/dtd/ContentModel$ElemName of class scala/xml/dtd/ContentModel
  minor version: 0
  major version: 49
  Constant pool:
const #1 = Asciz	SourceFile;
const #2 = Asciz	ValidatingMarkupHandler.scala;
const #3 = Asciz	isValidating;
const #4 = Asciz	Z;
const #5 = Asciz	declCurrent;
const #6 = Asciz	Lscala/xml/dtd/ElemDecl;;
const #7 = Asciz	declStack;
const #8 = Asciz	Lscala/collection/immutable/List;;
const #9 = Asciz	Lscala/collection/immutable/List<Lscala/xml/dtd/ElemDecl;>;;
const #10 = Asciz	Signature;
const #11 = Asciz	qCurrent;
const #12 = Asciz	I;
const #13 = Asciz	qStack;
const #14 = Asciz	Lscala/collection/immutable/List<Ljava/lang/Integer;>;;
const #15 = Asciz	rootLabel;
const #16 = Asciz	Ljava/lang/String;;
const #17 = Asciz	<init>;
const #18 = Asciz	()V;
const #19 = Asciz	Code;
const #20 = Asciz	LineNumberTable;
const #21 = Asciz	scala/xml/parsing/MarkupHandler;
const #22 = class	#21;	//  scala/xml/parsing/MarkupHandler
const #23 = NameAndType	#17:#18;//  "<init>":()V
const #24 = Method	#22.#23;	//  scala/xml/parsing/MarkupHandler."<init>":()V
const #25 = Asciz	scala/collection/immutable/Nil$;
const #26 = class	#25;	//  scala/collection/immutable/Nil$
const #27 = Asciz	MODULE$;
const #28 = Asciz	Lscala/collection/immutable/Nil$;;
const #29 = NameAndType	#27:#28;//  MODULE$:Lscala/collection/immutable/Nil$;
const #30 = Field	#26.#29;	//  scala/collection/immutable/Nil$.MODULE$:Lscala/collection/immutable/Nil$;
const #31 = Asciz	scala/xml/parsing/ValidatingMarkupHandler;
const #32 = class	#31;	//  scala/xml/parsing/ValidatingMarkupHandler
const #33 = NameAndType	#13:#8;//  qStack:Lscala/collection/immutable/List;
const #34 = Field	#32.#33;	//  scala/xml/parsing/ValidatingMarkupHandler.qStack:Lscala/collection/immutable/List;
const #35 = NameAndType	#11:#12;//  qCurrent:I
const #36 = Field	#32.#35;	//  scala/xml/parsing/ValidatingMarkupHandler.qCurrent:I
const #37 = NameAndType	#7:#8;//  declStack:Lscala/collection/immutable/List;
const #38 = Field	#32.#37;	//  scala/xml/parsing/ValidatingMarkupHandler.declStack:Lscala/collection/immutable/List;
const #39 = NameAndType	#5:#6;//  declCurrent:Lscala/xml/dtd/ElemDecl;
const #40 = Field	#32.#39;	//  scala/xml/parsing/ValidatingMarkupHandler.declCurrent:Lscala/xml/dtd/ElemDecl;
const #41 = Asciz	advanceDFA$1;
const #42 = Asciz	(Lscala/xml/dtd/DFAContentModel;ILjava/lang/String;)V;
const #43 = Asciz	scala/xml/dtd/DFAContentModel;
const #44 = class	#43;	//  scala/xml/dtd/DFAContentModel
const #45 = Asciz	dfa;
const #46 = Asciz	()Lscala/util/automata/DetWordAutom;;
const #47 = NameAndType	#45:#46;//  dfa:()Lscala/util/automata/DetWordAutom;
const #48 = Method	#44.#47;	//  scala/xml/dtd/DFAContentModel.dfa:()Lscala/util/automata/DetWordAutom;
const #49 = Asciz	scala/util/automata/DetWordAutom;
const #50 = class	#49;	//  scala/util/automata/DetWordAutom
const #51 = Asciz	delta;
const #52 = Asciz	()[Lscala/collection/Map;;
const #53 = NameAndType	#51:#52;//  delta:()[Lscala/collection/Map;
const #54 = Method	#50.#53;	//  scala/util/automata/DetWordAutom.delta:()[Lscala/collection/Map;
const #55 = Asciz	()I;
const #56 = NameAndType	#11:#55;//  qCurrent:()I
const #57 = Method	#32.#56;	//  scala/xml/parsing/ValidatingMarkupHandler.qCurrent:()I
const #58 = Asciz	scala/collection/mutable/StringBuilder;
const #59 = class	#58;	//  scala/collection/mutable/StringBuilder
const #60 = Method	#59.#23;	//  scala/collection/mutable/StringBuilder."<init>":()V
const #61 = Asciz	advanceDFA(dm): ;
const #62 = String	#61;	//  advanceDFA(dm): 
const #63 = Asciz	append;
const #64 = Asciz	(Ljava/lang/Object;)Lscala/collection/mutable/StringBuilder;;
const #65 = NameAndType	#63:#64;//  append:(Ljava/lang/Object;)Lscala/collection/mutable/StringBuilder;
const #66 = Method	#59.#65;	//  scala/collection/mutable/StringBuilder.append:(Ljava/lang/Object;)Lscala/collection/mutable/StringBuilder;
const #67 = Asciz	toString;
const #68 = Asciz	()Ljava/lang/String;;
const #69 = NameAndType	#67:#68;//  toString:()Ljava/lang/String;
const #70 = Method	#59.#69;	//  scala/collection/mutable/StringBuilder.toString:()Ljava/lang/String;
const #71 = Asciz	log;
const #72 = Asciz	(Ljava/lang/String;)V;
const #73 = NameAndType	#71:#72;//  log:(Ljava/lang/String;)V
const #74 = Method	#32.#73;	//  scala/xml/parsing/ValidatingMarkupHandler.log:(Ljava/lang/String;)V
const #75 = Asciz	advanceDFA(trans): ;
const #76 = String	#75;	//  advanceDFA(trans): 
const #77 = Asciz	scala/xml/dtd/ContentModel$ElemName;
const #78 = class	#77;	//  scala/xml/dtd/ContentModel$ElemName
const #79 = NameAndType	#17:#72;//  "<init>":(Ljava/lang/String;)V
const #80 = Method	#78.#79;	//  scala/xml/dtd/ContentModel$ElemName."<init>":(Ljava/lang/String;)V
const #81 = Asciz	scala/collection/generic/MapTemplate;
const #82 = class	#81;	//  scala/collection/generic/MapTemplate
const #83 = Asciz	get;
const #84 = Asciz	(Ljava/lang/Object;)Lscala/Option;;
const #85 = NameAndType	#83:#84;//  get:(Ljava/lang/Object;)Lscala/Option;
const #86 = InterfaceMethod	#82.#85;	//  scala/collection/generic/MapTemplate.get:(Ljava/lang/Object;)Lscala/Option;
const #87 = Asciz	scala/Some;
const #88 = class	#87;	//  scala/Some
const #89 = Asciz	x;
const #90 = Asciz	()Ljava/lang/Object;;
const #91 = NameAndType	#89:#90;//  x:()Ljava/lang/Object;
const #92 = Method	#88.#91;	//  scala/Some.x:()Ljava/lang/Object;
const #93 = Asciz	scala/runtime/BoxesRunTime;
const #94 = class	#93;	//  scala/runtime/BoxesRunTime
const #95 = Asciz	unboxToInt;
const #96 = Asciz	(Ljava/lang/Object;)I;
const #97 = NameAndType	#95:#96;//  unboxToInt:(Ljava/lang/Object;)I
const #98 = Method	#94.#97;	//  scala/runtime/BoxesRunTime.unboxToInt:(Ljava/lang/Object;)I
const #99 = Asciz	qCurrent_$eq;
const #100 = Asciz	(I)V;
const #101 = NameAndType	#99:#100;//  qCurrent_$eq:(I)V
const #102 = Method	#32.#101;	//  scala/xml/parsing/ValidatingMarkupHandler.qCurrent_$eq:(I)V
const #103 = Asciz	DTD says, wrong element, expected one of ;
const #104 = String	#103;	//  DTD says, wrong element, expected one of 
const #105 = Asciz	keys;
const #106 = Asciz	()Lscala/collection/Iterator;;
const #107 = NameAndType	#105:#106;//  keys:()Lscala/collection/Iterator;
const #108 = InterfaceMethod	#82.#107;	//  scala/collection/generic/MapTemplate.keys:()Lscala/collection/Iterator;
const #109 = Asciz	scala/collection/Iterator;
const #110 = class	#109;	//  scala/collection/Iterator
const #111 = InterfaceMethod	#110.#69;	//  scala/collection/Iterator.toString:()Ljava/lang/String;
const #112 = Asciz	reportValidationError;
const #113 = Asciz	(ILjava/lang/String;)V;
const #114 = NameAndType	#112:#113;//  reportValidationError:(ILjava/lang/String;)V
const #115 = Method	#32.#114;	//  scala/xml/parsing/ValidatingMarkupHandler.reportValidationError:(ILjava/lang/String;)V
const #116 = Asciz	this;
const #117 = Asciz	Lscala/xml/parsing/ValidatingMarkupHandler;;
const #118 = Asciz	dm;
const #119 = Asciz	Lscala/xml/dtd/DFAContentModel;;
const #120 = Asciz	trans;
const #121 = Asciz	Lscala/collection/Map;;
const #122 = Asciz	temp1;
const #123 = Asciz	Lscala/Option;;
const #124 = Asciz	temp2;
const #125 = Asciz	Lscala/Some;;
const #126 = Asciz	temp3;
const #127 = Asciz	LocalVariableTable;
const #128 = Asciz	peReference;
const #129 = Asciz	scala/xml/dtd/PEReference;
const #130 = class	#129;	//  scala/xml/dtd/PEReference
const #131 = Method	#130.#79;	//  scala/xml/dtd/PEReference."<init>":(Ljava/lang/String;)V
const #132 = Asciz	decls;
const #133 = Asciz	()Lscala/collection/immutable/List;;
const #134 = NameAndType	#132:#133;//  decls:()Lscala/collection/immutable/List;
const #135 = Method	#32.#134;	//  scala/xml/parsing/ValidatingMarkupHandler.decls:()Lscala/collection/immutable/List;
const #136 = Asciz	scala/collection/immutable/List;
const #137 = class	#136;	//  scala/collection/immutable/List
const #138 = Asciz	$colon$colon;
const #139 = Asciz	(Ljava/lang/Object;)Lscala/collection/immutable/List;;
const #140 = NameAndType	#138:#139;//  $colon$colon:(Ljava/lang/Object;)Lscala/collection/immutable/List;
const #141 = Method	#137.#140;	//  scala/collection/immutable/List.$colon$colon:(Ljava/lang/Object;)Lscala/collection/immutable/List;
const #142 = Asciz	decls_$eq;
const #143 = Asciz	(Lscala/collection/immutable/List;)V;
const #144 = NameAndType	#142:#143;//  decls_$eq:(Lscala/collection/immutable/List;)V
const #145 = Method	#32.#144;	//  scala/xml/parsing/ValidatingMarkupHandler.decls_$eq:(Lscala/collection/immutable/List;)V
const #146 = Asciz	name;
const #147 = Asciz	notationDecl;
const #148 = Asciz	(Ljava/lang/String;Lscala/xml/dtd/ExternalID;)V;
const #149 = Asciz	scala/xml/dtd/NotationDecl;
const #150 = class	#149;	//  scala/xml/dtd/NotationDecl
const #151 = NameAndType	#17:#148;//  "<init>":(Ljava/lang/String;Lscala/xml/dtd/ExternalID;)V
const #152 = Method	#150.#151;	//  scala/xml/dtd/NotationDecl."<init>":(Ljava/lang/String;Lscala/xml/dtd/ExternalID;)V
const #153 = Asciz	notat;
const #154 = Asciz	extID;
const #155 = Asciz	Lscala/xml/dtd/ExternalID;;
const #156 = Asciz	unparsedEntityDecl;
const #157 = Asciz	(Ljava/lang/String;Lscala/xml/dtd/ExternalID;Ljava/lang/String;)V;
const #158 = Asciz	scala/xml/dtd/UnparsedEntityDecl;
const #159 = class	#158;	//  scala/xml/dtd/UnparsedEntityDecl
const #160 = NameAndType	#17:#157;//  "<init>":(Ljava/lang/String;Lscala/xml/dtd/ExternalID;Ljava/lang/String;)V
const #161 = Method	#159.#160;	//  scala/xml/dtd/UnparsedEntityDecl."<init>":(Ljava/lang/String;Lscala/xml/dtd/ExternalID;Ljava/lang/String;)V
const #162 = Asciz	attListDecl;
const #163 = Asciz	(Ljava/lang/String;Lscala/collection/immutable/List;)V;
const #164 = Asciz	scala/xml/dtd/AttListDecl;
const #165 = class	#164;	//  scala/xml/dtd/AttListDecl
const #166 = NameAndType	#17:#163;//  "<init>":(Ljava/lang/String;Lscala/collection/immutable/List;)V
const #167 = Method	#165.#166;	//  scala/xml/dtd/AttListDecl."<init>":(Ljava/lang/String;Lscala/collection/immutable/List;)V
const #168 = Asciz	attList;
const #169 = Asciz	(Ljava/lang/String;Lscala/collection/immutable/List<Lscala/xml/dtd/AttrDecl;>;)V;
const #170 = Asciz	elemDecl;
const #171 = Asciz	(Ljava/lang/String;Ljava/lang/String;)V;
const #172 = Asciz	scala/xml/dtd/ElemDecl;
const #173 = class	#172;	//  scala/xml/dtd/ElemDecl
const #174 = Asciz	scala/xml/dtd/ContentModel$;
const #175 = class	#174;	//  scala/xml/dtd/ContentModel$
const #176 = Asciz	Lscala/xml/dtd/ContentModel$;;
const #177 = NameAndType	#27:#176;//  MODULE$:Lscala/xml/dtd/ContentModel$;
const #178 = Field	#175.#177;	//  scala/xml/dtd/ContentModel$.MODULE$:Lscala/xml/dtd/ContentModel$;
const #179 = Asciz	parse;
const #180 = Asciz	(Ljava/lang/String;)Lscala/xml/dtd/ContentModel;;
const #181 = NameAndType	#179:#180;//  parse:(Ljava/lang/String;)Lscala/xml/dtd/ContentModel;
const #182 = Method	#175.#181;	//  scala/xml/dtd/ContentModel$.parse:(Ljava/lang/String;)Lscala/xml/dtd/ContentModel;
const #183 = Asciz	(Ljava/lang/String;Lscala/xml/dtd/ContentModel;)V;
const #184 = NameAndType	#17:#183;//  "<init>":(Ljava/lang/String;Lscala/xml/dtd/ContentModel;)V
const #185 = Method	#173.#184;	//  scala/xml/dtd/ElemDecl."<init>":(Ljava/lang/String;Lscala/xml/dtd/ContentModel;)V
const #186 = Asciz	cmstr;
const #187 = Asciz	elemEnd;
const #188 = Asciz	(ILjava/lang/String;Ljava/lang/String;)V;
const #189 = Asciz	  elemEnd;
const #190 = String	#189;	//    elemEnd
const #191 = NameAndType	#13:#133;//  qStack:()Lscala/collection/immutable/List;
const #192 = Method	#32.#191;	//  scala/xml/parsing/ValidatingMarkupHandler.qStack:()Lscala/collection/immutable/List;
const #193 = Asciz	scala/collection/generic/IterableTemplate;
const #194 = class	#193;	//  scala/collection/generic/IterableTemplate
const #195 = Asciz	head;
const #196 = NameAndType	#195:#90;//  head:()Ljava/lang/Object;
const #197 = InterfaceMethod	#194.#196;	//  scala/collection/generic/IterableTemplate.head:()Ljava/lang/Object;
const #198 = Asciz	scala/collection/generic/TraversableTemplate;
const #199 = class	#198;	//  scala/collection/generic/TraversableTemplate
const #200 = Asciz	tail;
const #201 = Asciz	()Lscala/collection/generic/TraversableTemplate;;
const #202 = NameAndType	#200:#201;//  tail:()Lscala/collection/generic/TraversableTemplate;
const #203 = InterfaceMethod	#199.#202;	//  scala/collection/generic/TraversableTemplate.tail:()Lscala/collection/generic/TraversableTemplate;
const #204 = Asciz	qStack_$eq;
const #205 = NameAndType	#204:#143;//  qStack_$eq:(Lscala/collection/immutable/List;)V
const #206 = Method	#32.#205;	//  scala/xml/parsing/ValidatingMarkupHandler.qStack_$eq:(Lscala/collection/immutable/List;)V
const #207 = NameAndType	#7:#133;//  declStack:()Lscala/collection/immutable/List;
const #208 = Method	#32.#207;	//  scala/xml/parsing/ValidatingMarkupHandler.declStack:()Lscala/collection/immutable/List;
const #209 = Asciz	declCurrent_$eq;
const #210 = Asciz	(Lscala/xml/dtd/ElemDecl;)V;
const #211 = NameAndType	#209:#210;//  declCurrent_$eq:(Lscala/xml/dtd/ElemDecl;)V
const #212 = Method	#32.#211;	//  scala/xml/parsing/ValidatingMarkupHandler.declCurrent_$eq:(Lscala/xml/dtd/ElemDecl;)V
const #213 = Asciz	declStack_$eq;
const #214 = NameAndType	#213:#143;//  declStack_$eq:(Lscala/collection/immutable/List;)V
const #215 = Method	#32.#214;	//  scala/xml/parsing/ValidatingMarkupHandler.declStack_$eq:(Lscala/collection/immutable/List;)V
const #216 = Asciz	    qCurrent now;
const #217 = String	#216;	//      qCurrent now
const #218 = Asciz	boxToInteger;
const #219 = Asciz	(I)Ljava/lang/Integer;;
const #220 = NameAndType	#218:#219;//  boxToInteger:(I)Ljava/lang/Integer;
const #221 = Method	#94.#220;	//  scala/runtime/BoxesRunTime.boxToInteger:(I)Ljava/lang/Integer;
const #222 = Asciz	    declCurrent now;
const #223 = String	#222;	//      declCurrent now
const #224 = Asciz	()Lscala/xml/dtd/ElemDecl;;
const #225 = NameAndType	#5:#224;//  declCurrent:()Lscala/xml/dtd/ElemDecl;
const #226 = Method	#32.#225;	//  scala/xml/parsing/ValidatingMarkupHandler.declCurrent:()Lscala/xml/dtd/ElemDecl;
const #227 = Asciz	pos;
const #228 = Asciz	pre;
const #229 = Asciz	label;
const #230 = Asciz	elemStart;
const #231 = Asciz	(ILjava/lang/String;Ljava/lang/String;Lscala/xml/MetaData;Lscala/xml/NamespaceBinding;)V;
const #232 = Asciz	[qCurrent = ;
const #233 = String	#232;	//  [qCurrent = 
const #234 = Asciz	 visiting ;
const #235 = String	#234;	//   visiting 
const #236 = Asciz	];
const #237 = String	#236;	//  ]
const #238 = Asciz	  checking root;
const #239 = String	#238;	//    checking root
const #240 = NameAndType	#15:#68;//  rootLabel:()Ljava/lang/String;
const #241 = Method	#32.#240;	//  scala/xml/parsing/ValidatingMarkupHandler.rootLabel:()Ljava/lang/String;
const #242 = Asciz	java/lang/Object;
const #243 = class	#242;	//  java/lang/Object
const #244 = Asciz	equals;
const #245 = Asciz	(Ljava/lang/Object;)Z;
const #246 = NameAndType	#244:#245;//  equals:(Ljava/lang/Object;)Z
const #247 = Method	#243.#246;	//  java/lang/Object.equals:(Ljava/lang/Object;)Z
const #248 = Asciz	this element should be ;
const #249 = String	#248;	//  this element should be 
const #250 = Asciz	  checking node;
const #251 = String	#250;	//    checking node
const #252 = Asciz	contentModel;
const #253 = Asciz	()Lscala/xml/dtd/ContentModel;;
const #254 = NameAndType	#252:#253;//  contentModel:()Lscala/xml/dtd/ContentModel;
const #255 = Method	#173.#254;	//  scala/xml/dtd/ElemDecl.contentModel:()Lscala/xml/dtd/ContentModel;
const #256 = Asciz	scala/xml/dtd/ANY$;
const #257 = class	#256;	//  scala/xml/dtd/ANY$
const #258 = Asciz	Lscala/xml/dtd/ANY$;;
const #259 = NameAndType	#27:#258;//  MODULE$:Lscala/xml/dtd/ANY$;
const #260 = Field	#257.#259;	//  scala/xml/dtd/ANY$.MODULE$:Lscala/xml/dtd/ANY$;
const #261 = Asciz	scala/xml/dtd/EMPTY$;
const #262 = class	#261;	//  scala/xml/dtd/EMPTY$
const #263 = Asciz	Lscala/xml/dtd/EMPTY$;;
const #264 = NameAndType	#27:#263;//  MODULE$:Lscala/xml/dtd/EMPTY$;
const #265 = Field	#262.#264;	//  scala/xml/dtd/EMPTY$.MODULE$:Lscala/xml/dtd/EMPTY$;
const #266 = Asciz	DTD says, no elems, no text allowed here;
const #267 = String	#266;	//  DTD says, no elems, no text allowed here
const #268 = Asciz	scala/xml/dtd/PCDATA$;
const #269 = class	#268;	//  scala/xml/dtd/PCDATA$
const #270 = Asciz	Lscala/xml/dtd/PCDATA$;;
const #271 = NameAndType	#27:#270;//  MODULE$:Lscala/xml/dtd/PCDATA$;
const #272 = Field	#269.#271;	//  scala/xml/dtd/PCDATA$.MODULE$:Lscala/xml/dtd/PCDATA$;
const #273 = Asciz	DTD says, no elements allowed here;
const #274 = String	#273;	//  DTD says, no elements allowed here
const #275 = Asciz	scala/xml/dtd/MIXED;
const #276 = class	#275;	//  scala/xml/dtd/MIXED
const #277 = Asciz	r;
const #278 = Asciz	()Lscala/util/regexp/Base$RegExp;;
const #279 = NameAndType	#277:#278;//  r:()Lscala/util/regexp/Base$RegExp;
const #280 = Method	#276.#279;	//  scala/xml/dtd/MIXED.r:()Lscala/util/regexp/Base$RegExp;
const #281 = NameAndType	#41:#42;//  advanceDFA$1:(Lscala/xml/dtd/DFAContentModel;ILjava/lang/String;)V
const #282 = Method	#32.#281;	//  scala/xml/parsing/ValidatingMarkupHandler.advanceDFA$1:(Lscala/xml/dtd/DFAContentModel;ILjava/lang/String;)V
const #283 = Asciz	scala/xml/dtd/ELEMENTS;
const #284 = class	#283;	//  scala/xml/dtd/ELEMENTS
const #285 = Method	#284.#279;	//  scala/xml/dtd/ELEMENTS.r:()Lscala/util/regexp/Base$RegExp;
const #286 = Asciz	lookupElemDecl;
const #287 = Asciz	(Ljava/lang/String;)Lscala/xml/dtd/ElemDecl;;
const #288 = NameAndType	#286:#287;//  lookupElemDecl:(Ljava/lang/String;)Lscala/xml/dtd/ElemDecl;
const #289 = Method	#32.#288;	//  scala/xml/parsing/ValidatingMarkupHandler.lookupElemDecl:(Ljava/lang/String;)Lscala/xml/dtd/ElemDecl;
const #290 = Asciz	  done  now;
const #291 = String	#290;	//    done  now
const #292 = Asciz	scala/MatchError;
const #293 = class	#292;	//  scala/MatchError
const #294 = Asciz	scala/xml/dtd/ContentModel;
const #295 = class	#294;	//  scala/xml/dtd/ContentModel
const #296 = Method	#295.#69;	//  scala/xml/dtd/ContentModel.toString:()Ljava/lang/String;
const #297 = Method	#293.#79;	//  scala/MatchError."<init>":(Ljava/lang/String;)V
const #298 = Asciz	pos$1;
const #299 = Asciz	label$1;
const #300 = Asciz	attrs;
const #301 = Asciz	Lscala/xml/MetaData;;
const #302 = Asciz	scope;
const #303 = Asciz	Lscala/xml/NamespaceBinding;;
const #304 = Asciz	temp4;
const #305 = Asciz	Lscala/xml/dtd/ContentModel;;
const #306 = Asciz	temp8;
const #307 = Asciz	Lscala/xml/dtd/MIXED;;
const #308 = Asciz	temp9;
const #309 = Asciz	Lscala/util/regexp/Base$RegExp;;
const #310 = Asciz	temp10;
const #311 = Asciz	Lscala/xml/dtd/ELEMENTS;;
const #312 = Asciz	temp11;
const #313 = Asciz	endDTD;
const #314 = Asciz	rootLabel_$eq;
const #315 = NameAndType	#314:#72;//  rootLabel_$eq:(Ljava/lang/String;)V
const #316 = Method	#32.#315;	//  scala/xml/parsing/ValidatingMarkupHandler.rootLabel_$eq:(Ljava/lang/String;)V
const #317 = Asciz	n;
const #318 = Asciz	msg;
const #319 = Asciz	()Z;
const #320 = Asciz	(Lscala/collection/immutable/List<Lscala/xml/dtd/ElemDecl;>;)V;
const #321 = Asciz	()Lscala/collection/immutable/List<Lscala/xml/dtd/ElemDecl;>;;
const #322 = Asciz	(Lscala/collection/immutable/List<Ljava/lang/Integer;>;)V;
const #323 = Asciz	()Lscala/collection/immutable/List<Ljava/lang/Integer;>;;
const #324 = NameAndType	#15:#16;//  rootLabel:Ljava/lang/String;
const #325 = Field	#32.#324;	//  scala/xml/parsing/ValidatingMarkupHandler.rootLabel:Ljava/lang/String;
const #326 = Asciz	ScalaSig;
const #327 = Asciz	InnerClasses;
const #328 = Asciz	scala/util/regexp/Base$RegExp;
const #329 = class	#328;	//  scala/util/regexp/Base$RegExp
const #330 = Asciz	scala/util/regexp/Base;
const #331 = class	#330;	//  scala/util/regexp/Base
const #332 = Asciz	RegExp;
const #333 = Asciz	ElemName;
const #334 = Asciz	scala/util/logging/Logged;
const #335 = class	#334;	//  scala/util/logging/Logged
const #336 = Asciz	scala/ScalaObject;
const #337 = class	#336;	//  scala/ScalaObject

{
public scala.xml.parsing.ValidatingMarkupHandler();
  Code:
   Stack=2, Locals=1, Args_size=1
   0:	aload_0
   1:	invokespecial	#24; //Method scala/xml/parsing/MarkupHandler."<init>":()V
   4:	aload_0
   5:	getstatic	#30; //Field scala/collection/immutable/Nil$.MODULE$:Lscala/collection/immutable/Nil$;
   8:	putfield	#34; //Field qStack:Lscala/collection/immutable/List;
   11:	aload_0
   12:	iconst_m1
   13:	putfield	#36; //Field qCurrent:I
   16:	aload_0
   17:	getstatic	#30; //Field scala/collection/immutable/Nil$.MODULE$:Lscala/collection/immutable/Nil$;
   20:	putfield	#38; //Field declStack:Lscala/collection/immutable/List;
   23:	aload_0
   24:	aconst_null
   25:	pop
   26:	aconst_null
   27:	putfield	#40; //Field declCurrent:Lscala/xml/dtd/ElemDecl;
   30:	return
  LineNumberTable: 
   line 18: 0
   line 21: 4
   line 22: 11
   line 24: 16
   line 25: 23


public abstract void reportValidationError(int, java.lang.String);

public final void peReference(java.lang.String);
  Code:
   Stack=4, Locals=3, Args_size=2
   0:	aload_0
   1:	new	#130; //class scala/xml/dtd/PEReference
   4:	dup
   5:	aload_1
   6:	invokespecial	#131; //Method scala/xml/dtd/PEReference."<init>":(Ljava/lang/String;)V
   9:	astore_2
   10:	aload_0
   11:	invokevirtual	#135; //Method decls:()Lscala/collection/immutable/List;
   14:	aload_2
   15:	invokevirtual	#141; //Method scala/collection/immutable/List.$colon$colon:(Ljava/lang/Object;)Lscala/collection/immutable/List;
   18:	invokevirtual	#145; //Method decls_$eq:(Lscala/collection/immutable/List;)V
   21:	return
  LineNumberTable: 
   line 114: 0

  LocalVariableTable: 
   Start  Length  Slot  Name   Signature
   0      22      0    this       Lscala/xml/parsing/ValidatingMarkupHandler;
   0      22      1    name       Ljava/lang/String;


public final void notationDecl(java.lang.String, scala.xml.dtd.ExternalID);
  Code:
   Stack=5, Locals=4, Args_size=3
   0:	aload_0
   1:	new	#150; //class scala/xml/dtd/NotationDecl
   4:	dup
   5:	aload_1
   6:	aload_2
   7:	invokespecial	#152; //Method scala/xml/dtd/NotationDecl."<init>":(Ljava/lang/String;Lscala/xml/dtd/ExternalID;)V
   10:	astore_3
   11:	aload_0
   12:	invokevirtual	#135; //Method decls:()Lscala/collection/immutable/List;
   15:	aload_3
   16:	invokevirtual	#141; //Method scala/collection/immutable/List.$colon$colon:(Ljava/lang/Object;)Lscala/collection/immutable/List;
   19:	invokevirtual	#145; //Method decls_$eq:(Lscala/collection/immutable/List;)V
   22:	return
  LineNumberTable: 
   line 110: 0

  LocalVariableTable: 
   Start  Length  Slot  Name   Signature
   0      23      0    this       Lscala/xml/parsing/ValidatingMarkupHandler;
   0      23      1    notat       Ljava/lang/String;
   0      23      2    extID       Lscala/xml/dtd/ExternalID;


public final void unparsedEntityDecl(java.lang.String, scala.xml.dtd.ExternalID, java.lang.String);
  Code:
   Stack=6, Locals=5, Args_size=4
   0:	aload_0
   1:	new	#159; //class scala/xml/dtd/UnparsedEntityDecl
   4:	dup
   5:	aload_1
   6:	aload_2
   7:	aload_3
   8:	invokespecial	#161; //Method scala/xml/dtd/UnparsedEntityDecl."<init>":(Ljava/lang/String;Lscala/xml/dtd/ExternalID;Ljava/lang/String;)V
   11:	astore	4
   13:	aload_0
   14:	invokevirtual	#135; //Method decls:()Lscala/collection/immutable/List;
   17:	aload	4
   19:	invokevirtual	#141; //Method scala/collection/immutable/List.$colon$colon:(Ljava/lang/Object;)Lscala/collection/immutable/List;
   22:	invokevirtual	#145; //Method decls_$eq:(Lscala/collection/immutable/List;)V
   25:	return
  LineNumberTable: 
   line 106: 0

  LocalVariableTable: 
   Start  Length  Slot  Name   Signature
   0      26      0    this       Lscala/xml/parsing/ValidatingMarkupHandler;
   0      26      1    name       Ljava/lang/String;
   0      26      2    extID       Lscala/xml/dtd/ExternalID;
   0      26      3    notat       Ljava/lang/String;


public final void attListDecl(java.lang.String, scala.collection.immutable.List);
  Code:
   Stack=5, Locals=4, Args_size=3
   0:	aload_0
   1:	new	#165; //class scala/xml/dtd/AttListDecl
   4:	dup
   5:	aload_1
   6:	aload_2
   7:	invokespecial	#167; //Method scala/xml/dtd/AttListDecl."<init>":(Ljava/lang/String;Lscala/collection/immutable/List;)V
   10:	astore_3
   11:	aload_0
   12:	invokevirtual	#135; //Method decls:()Lscala/collection/immutable/List;
   15:	aload_3
   16:	invokevirtual	#141; //Method scala/collection/immutable/List.$colon$colon:(Ljava/lang/Object;)Lscala/collection/immutable/List;
   19:	invokevirtual	#145; //Method decls_$eq:(Lscala/collection/immutable/List;)V
   22:	return
  LineNumberTable: 
   line 102: 0

  LocalVariableTable: 
   Start  Length  Slot  Name   Signature
   0      23      0    this       Lscala/xml/parsing/ValidatingMarkupHandler;
   0      23      1    name       Ljava/lang/String;
   0      23      2    attList       Lscala/collection/immutable/List;

  Signature: length = 0x2
   00 FFFFFFA9 

public final void elemDecl(java.lang.String, java.lang.String);
  Code:
   Stack=6, Locals=4, Args_size=3
   0:	aload_0
   1:	new	#173; //class scala/xml/dtd/ElemDecl
   4:	dup
   5:	aload_1
   6:	getstatic	#178; //Field scala/xml/dtd/ContentModel$.MODULE$:Lscala/xml/dtd/ContentModel$;
   9:	aload_2
   10:	invokevirtual	#182; //Method scala/xml/dtd/ContentModel$.parse:(Ljava/lang/String;)Lscala/xml/dtd/ContentModel;
   13:	invokespecial	#185; //Method scala/xml/dtd/ElemDecl."<init>":(Ljava/lang/String;Lscala/xml/dtd/ContentModel;)V
   16:	astore_3
   17:	aload_0
   18:	invokevirtual	#135; //Method decls:()Lscala/collection/immutable/List;
   21:	aload_3
   22:	invokevirtual	#141; //Method scala/collection/immutable/List.$colon$colon:(Ljava/lang/Object;)Lscala/collection/immutable/List;
   25:	invokevirtual	#145; //Method decls_$eq:(Lscala/collection/immutable/List;)V
   28:	return
  LineNumberTable: 
   line 98: 0

  LocalVariableTable: 
   Start  Length  Slot  Name   Signature
   0      29      0    this       Lscala/xml/parsing/ValidatingMarkupHandler;
   0      29      1    name       Ljava/lang/String;
   0      29      2    cmstr       Ljava/lang/String;


public void elemEnd(int, java.lang.String, java.lang.String);
  Code:
   Stack=3, Locals=4, Args_size=4
   0:	aload_0
   1:	ldc	#190; //String   elemEnd
   3:	invokevirtual	#74; //Method log:(Ljava/lang/String;)V
   6:	aload_0
   7:	aload_0
   8:	invokevirtual	#192; //Method qStack:()Lscala/collection/immutable/List;
   11:	invokeinterface	#197,  1; //InterfaceMethod scala/collection/generic/IterableTemplate.head:()Ljava/lang/Object;
   16:	invokestatic	#98; //Method scala/runtime/BoxesRunTime.unboxToInt:(Ljava/lang/Object;)I
   19:	invokevirtual	#102; //Method qCurrent_$eq:(I)V
   22:	aload_0
   23:	aload_0
   24:	invokevirtual	#192; //Method qStack:()Lscala/collection/immutable/List;
   27:	invokeinterface	#203,  1; //InterfaceMethod scala/collection/generic/TraversableTemplate.tail:()Lscala/collection/generic/TraversableTemplate;
   32:	checkcast	#137; //class scala/collection/immutable/List
   35:	invokevirtual	#206; //Method qStack_$eq:(Lscala/collection/immutable/List;)V
   38:	aload_0
   39:	aload_0
   40:	invokevirtual	#208; //Method declStack:()Lscala/collection/immutable/List;
   43:	invokeinterface	#197,  1; //InterfaceMethod scala/collection/generic/IterableTemplate.head:()Ljava/lang/Object;
   48:	checkcast	#173; //class scala/xml/dtd/ElemDecl
   51:	invokevirtual	#212; //Method declCurrent_$eq:(Lscala/xml/dtd/ElemDecl;)V
   54:	aload_0
   55:	aload_0
   56:	invokevirtual	#208; //Method declStack:()Lscala/collection/immutable/List;
   59:	invokeinterface	#203,  1; //InterfaceMethod scala/collection/generic/TraversableTemplate.tail:()Lscala/collection/generic/TraversableTemplate;
   64:	checkcast	#137; //class scala/collection/immutable/List
   67:	invokevirtual	#215; //Method declStack_$eq:(Lscala/collection/immutable/List;)V
   70:	aload_0
   71:	new	#59; //class scala/collection/mutable/StringBuilder
   74:	dup
   75:	invokespecial	#60; //Method scala/collection/mutable/StringBuilder."<init>":()V
   78:	ldc	#217; //String     qCurrent now
   80:	invokevirtual	#66; //Method scala/collection/mutable/StringBuilder.append:(Ljava/lang/Object;)Lscala/collection/mutable/StringBuilder;
   83:	aload_0
   84:	invokevirtual	#57; //Method qCurrent:()I
   87:	invokestatic	#221; //Method scala/runtime/BoxesRunTime.boxToInteger:(I)Ljava/lang/Integer;
   90:	invokevirtual	#66; //Method scala/collection/mutable/StringBuilder.append:(Ljava/lang/Object;)Lscala/collection/mutable/StringBuilder;
   93:	invokevirtual	#70; //Method scala/collection/mutable/StringBuilder.toString:()Ljava/lang/String;
   96:	invokevirtual	#74; //Method log:(Ljava/lang/String;)V
   99:	aload_0
   100:	new	#59; //class scala/collection/mutable/StringBuilder
   103:	dup
   104:	invokespecial	#60; //Method scala/collection/mutable/StringBuilder."<init>":()V
   107:	ldc	#223; //String     declCurrent now
   109:	invokevirtual	#66; //Method scala/collection/mutable/StringBuilder.append:(Ljava/lang/Object;)Lscala/collection/mutable/StringBuilder;
   112:	aload_0
   113:	invokevirtual	#226; //Method declCurrent:()Lscala/xml/dtd/ElemDecl;
   116:	invokevirtual	#66; //Method scala/collection/mutable/StringBuilder.append:(Ljava/lang/Object;)Lscala/collection/mutable/StringBuilder;
   119:	invokevirtual	#70; //Method scala/collection/mutable/StringBuilder.toString:()Ljava/lang/String;
   122:	invokevirtual	#74; //Method log:(Ljava/lang/String;)V
   125:	return
  LineNumberTable: 
   line 88: 0
   line 89: 6
   line 90: 22
   line 91: 38
   line 92: 54
   line 93: 70
   line 94: 99

  LocalVariableTable: 
   Start  Length  Slot  Name   Signature
   0      126      0    this       Lscala/xml/parsing/ValidatingMarkupHandler;
   0      126      1    pos       I
   0      126      2    pre       Ljava/lang/String;
   0      126      3    label       Ljava/lang/String;


public void elemStart(int, java.lang.String, java.lang.String, scala.xml.MetaData, scala.xml.NamespaceBinding);
  Code:
   Stack=4, Locals=19, Args_size=6
   0:	aload_0
   1:	new	#59; //class scala/collection/mutable/StringBuilder
   4:	dup
   5:	invokespecial	#60; //Method scala/collection/mutable/StringBuilder."<init>":()V
   8:	ldc	#233; //String [qCurrent = 
   10:	invokevirtual	#66; //Method scala/collection/mutable/StringBuilder.append:(Ljava/lang/Object;)Lscala/collection/mutable/StringBuilder;
   13:	aload_0
   14:	invokevirtual	#57; //Method qCurrent:()I
   17:	invokestatic	#221; //Method scala/runtime/BoxesRunTime.boxToInteger:(I)Ljava/lang/Integer;
   20:	invokevirtual	#66; //Method scala/collection/mutable/StringBuilder.append:(Ljava/lang/Object;)Lscala/collection/mutable/StringBuilder;
   23:	ldc	#235; //String  visiting 
   25:	invokevirtual	#66; //Method scala/collection/mutable/StringBuilder.append:(Ljava/lang/Object;)Lscala/collection/mutable/StringBuilder;
   28:	aload_3
   29:	invokevirtual	#66; //Method scala/collection/mutable/StringBuilder.append:(Ljava/lang/Object;)Lscala/collection/mutable/StringBuilder;
   32:	ldc	#237; //String ]
   34:	invokevirtual	#66; //Method scala/collection/mutable/StringBuilder.append:(Ljava/lang/Object;)Lscala/collection/mutable/StringBuilder;
   37:	invokevirtual	#70; //Method scala/collection/mutable/StringBuilder.toString:()Ljava/lang/String;
   40:	invokevirtual	#74; //Method log:(Ljava/lang/String;)V
   43:	aload_0
   44:	invokevirtual	#57; //Method qCurrent:()I
   47:	iconst_m1
   48:	if_icmpne	115
   51:	aload_0
   52:	ldc	#239; //String   checking root
   54:	invokevirtual	#74; //Method log:(Ljava/lang/String;)V
   57:	aload_3
   58:	aload_0
   59:	invokevirtual	#241; //Method rootLabel:()Ljava/lang/String;
   62:	astore	6
   64:	dup
   65:	ifnonnull	77
   68:	pop
   69:	aload	6
   71:	ifnull	331
   74:	goto	85
   77:	aload	6
   79:	invokevirtual	#247; //Method java/lang/Object.equals:(Ljava/lang/Object;)Z
   82:	ifne	331
   85:	aload_0
   86:	iload_1
   87:	new	#59; //class scala/collection/mutable/StringBuilder
   90:	dup
   91:	invokespecial	#60; //Method scala/collection/mutable/StringBuilder."<init>":()V
   94:	ldc	#249; //String this element should be 
   96:	invokevirtual	#66; //Method scala/collection/mutable/StringBuilder.append:(Ljava/lang/Object;)Lscala/collection/mutable/StringBuilder;
   99:	aload_0
   100:	invokevirtual	#241; //Method rootLabel:()Ljava/lang/String;
   103:	invokevirtual	#66; //Method scala/collection/mutable/StringBuilder.append:(Ljava/lang/Object;)Lscala/collection/mutable/StringBuilder;
   106:	invokevirtual	#70; //Method scala/collection/mutable/StringBuilder.toString:()Ljava/lang/String;
   109:	invokevirtual	#115; //Method reportValidationError:(ILjava/lang/String;)V
   112:	goto	331
   115:	aload_0
   116:	ldc	#251; //String   checking node
   118:	invokevirtual	#74; //Method log:(Ljava/lang/String;)V
   121:	aload_0
   122:	invokevirtual	#226; //Method declCurrent:()Lscala/xml/dtd/ElemDecl;
   125:	invokevirtual	#255; //Method scala/xml/dtd/ElemDecl.contentModel:()Lscala/xml/dtd/ContentModel;
   128:	astore	7
   130:	getstatic	#260; //Field scala/xml/dtd/ANY$.MODULE$:Lscala/xml/dtd/ANY$;
   133:	aload	7
   135:	astore	8
   137:	dup
   138:	ifnonnull	150
   141:	pop
   142:	aload	8
   144:	ifnull	158
   147:	goto	166
   150:	aload	8
   152:	invokevirtual	#247; //Method java/lang/Object.equals:(Ljava/lang/Object;)Z
   155:	ifeq	166
   158:	aload	7
   160:	instanceof	#257; //class scala/xml/dtd/ANY$
   163:	ifne	331
   166:	getstatic	#265; //Field scala/xml/dtd/EMPTY$.MODULE$:Lscala/xml/dtd/EMPTY$;
   169:	aload	7
   171:	astore	9
   173:	dup
   174:	ifnonnull	186
   177:	pop
   178:	aload	9
   180:	ifnull	194
   183:	goto	213
   186:	aload	9
   188:	invokevirtual	#247; //Method java/lang/Object.equals:(Ljava/lang/Object;)Z
   191:	ifeq	213
   194:	aload	7
   196:	instanceof	#262; //class scala/xml/dtd/EMPTY$
   199:	ifeq	213
   202:	aload_0
   203:	iload_1
   204:	ldc_w	#267; //String DTD says, no elems, no text allowed here
   207:	invokevirtual	#115; //Method reportValidationError:(ILjava/lang/String;)V
   210:	goto	331
   213:	getstatic	#272; //Field scala/xml/dtd/PCDATA$.MODULE$:Lscala/xml/dtd/PCDATA$;
   216:	aload	7
   218:	astore	10
   220:	dup
   221:	ifnonnull	233
   224:	pop
   225:	aload	10
   227:	ifnull	241
   230:	goto	260
   233:	aload	10
   235:	invokevirtual	#247; //Method java/lang/Object.equals:(Ljava/lang/Object;)Z
   238:	ifeq	260
   241:	aload	7
   243:	instanceof	#269; //class scala/xml/dtd/PCDATA$
   246:	ifeq	260
   249:	aload_0
   250:	iload_1
   251:	ldc_w	#274; //String DTD says, no elements allowed here
   254:	invokevirtual	#115; //Method reportValidationError:(ILjava/lang/String;)V
   257:	goto	331
   260:	aload	7
   262:	instanceof	#276; //class scala/xml/dtd/MIXED
   265:	ifeq	297
   268:	aload	7
   270:	checkcast	#276; //class scala/xml/dtd/MIXED
   273:	astore	11
   275:	aload	11
   277:	invokevirtual	#280; //Method scala/xml/dtd/MIXED.r:()Lscala/util/regexp/Base$RegExp;
   280:	astore	12
   282:	aload	12
   284:	astore	13
   286:	aload_0
   287:	aload	11
   289:	iload_1
   290:	aload_3
   291:	invokespecial	#282; //Method advanceDFA$1:(Lscala/xml/dtd/DFAContentModel;ILjava/lang/String;)V
   294:	goto	331
   297:	aload	7
   299:	instanceof	#284; //class scala/xml/dtd/ELEMENTS
   302:	ifeq	394
   305:	aload	7
   307:	checkcast	#284; //class scala/xml/dtd/ELEMENTS
   310:	astore	14
   312:	aload	14
   314:	invokevirtual	#285; //Method scala/xml/dtd/ELEMENTS.r:()Lscala/util/regexp/Base$RegExp;
   317:	astore	15
   319:	aload	15
   321:	astore	16
   323:	aload_0
   324:	aload	14
   326:	iload_1
   327:	aload_3
   328:	invokespecial	#282; //Method advanceDFA$1:(Lscala/xml/dtd/DFAContentModel;ILjava/lang/String;)V
   331:	aload_0
   332:	aload_0
   333:	invokevirtual	#57; //Method qCurrent:()I
   336:	istore	17
   338:	aload_0
   339:	invokevirtual	#192; //Method qStack:()Lscala/collection/immutable/List;
   342:	iload	17
   344:	invokestatic	#221; //Method scala/runtime/BoxesRunTime.boxToInteger:(I)Ljava/lang/Integer;
   347:	invokevirtual	#141; //Method scala/collection/immutable/List.$colon$colon:(Ljava/lang/Object;)Lscala/collection/immutable/List;
   350:	invokevirtual	#206; //Method qStack_$eq:(Lscala/collection/immutable/List;)V
   353:	aload_0
   354:	aload_0
   355:	invokevirtual	#226; //Method declCurrent:()Lscala/xml/dtd/ElemDecl;
   358:	astore	18
   360:	aload_0
   361:	invokevirtual	#208; //Method declStack:()Lscala/collection/immutable/List;
   364:	aload	18
   366:	invokevirtual	#141; //Method scala/collection/immutable/List.$colon$colon:(Ljava/lang/Object;)Lscala/collection/immutable/List;
   369:	invokevirtual	#215; //Method declStack_$eq:(Lscala/collection/immutable/List;)V
   372:	aload_0
   373:	aload_0
   374:	aload_3
   375:	invokevirtual	#289; //Method lookupElemDecl:(Ljava/lang/String;)Lscala/xml/dtd/ElemDecl;
   378:	invokevirtual	#212; //Method declCurrent_$eq:(Lscala/xml/dtd/ElemDecl;)V
   381:	aload_0
   382:	iconst_0
   383:	invokevirtual	#102; //Method qCurrent_$eq:(I)V
   386:	aload_0
   387:	ldc_w	#291; //String   done  now
   390:	invokevirtual	#74; //Method log:(Ljava/lang/String;)V
   393:	return
   394:	new	#293; //class scala/MatchError
   397:	dup
   398:	aload	7
   400:	invokevirtual	#296; //Method scala/xml/dtd/ContentModel.toString:()Ljava/lang/String;
   403:	invokespecial	#297; //Method scala/MatchError."<init>":(Ljava/lang/String;)V
   406:	athrow
  LineNumberTable: 
   line 58: 0
   line 60: 43
   line 61: 51
   line 62: 57
   line 63: 85
   line 65: 115
   line 66: 121
   line 69: 202
   line 66: 213
   line 71: 249
   line 66: 260
   line 72: 282
   line 73: 286
   line 72: 287
   line 73: 289
   line 66: 297
   line 74: 319
   line 75: 323
   line 74: 324
   line 75: 326
   line 79: 331
   line 80: 353
   line 82: 372
   line 83: 381
   line 84: 386
   line 66: 394

  LocalVariableTable: 
   Start  Length  Slot  Name   Signature
   0      407      0    this       Lscala/xml/parsing/ValidatingMarkupHandler;
   0      407      1    pos$1       I
   0      407      2    pre       Ljava/lang/String;
   0      407      3    label$1       Ljava/lang/String;
   0      407      4    attrs       Lscala/xml/MetaData;
   0      407      5    scope       Lscala/xml/NamespaceBinding;
   130      201      7    temp4       Lscala/xml/dtd/ContentModel;
   394      13      7    temp4       Lscala/xml/dtd/ContentModel;
   275      19      11    temp8       Lscala/xml/dtd/MIXED;
   282      12      12    temp9       Lscala/util/regexp/Base$RegExp;
   286      8      13    r       Lscala/util/regexp/Base$RegExp;
   312      19      14    temp10       Lscala/xml/dtd/ELEMENTS;
   319      12      15    temp11       Lscala/util/regexp/Base$RegExp;
   323      8      16    r       Lscala/util/regexp/Base$RegExp;


public void endDTD(java.lang.String);
  Code:
   Stack=2, Locals=2, Args_size=2
   0:	aload_0
   1:	aload_1
   2:	invokevirtual	#316; //Method rootLabel_$eq:(Ljava/lang/String;)V
   5:	return
  LineNumberTable: 
   line 44: 0

  LocalVariableTable: 
   Start  Length  Slot  Name   Signature
   0      6      0    this       Lscala/xml/parsing/ValidatingMarkupHandler;
   0      6      1    n       Ljava/lang/String;


public void log(java.lang.String);
  Code:
   Stack=0, Locals=2, Args_size=2
   0:	return
  LineNumberTable: 
   line 29: 0

  LocalVariableTable: 
   Start  Length  Slot  Name   Signature
   0      1      0    this       Lscala/xml/parsing/ValidatingMarkupHandler;
   0      1      1    msg       Ljava/lang/String;


public final boolean isValidating();
  Code:
   Stack=1, Locals=1, Args_size=1
   0:	iconst_1
   1:	ireturn
  LineNumberTable: 
   line 27: 0


public void declCurrent_$eq(scala.xml.dtd.ElemDecl);
  Code:
   Stack=2, Locals=2, Args_size=2
   0:	aload_0
   1:	aload_1
   2:	putfield	#40; //Field declCurrent:Lscala/xml/dtd/ElemDecl;
   5:	return
  LineNumberTable: 
   line 25: 0


public scala.xml.dtd.ElemDecl declCurrent();
  Code:
   Stack=1, Locals=1, Args_size=1
   0:	aload_0
   1:	getfield	#40; //Field declCurrent:Lscala/xml/dtd/ElemDecl;
   4:	areturn
  LineNumberTable: 
   line 25: 0


public void declStack_$eq(scala.collection.immutable.List);
  Code:
   Stack=2, Locals=2, Args_size=2
   0:	aload_0
   1:	aload_1
   2:	putfield	#38; //Field declStack:Lscala/collection/immutable/List;
   5:	return
  LineNumberTable: 
   line 24: 0

  Signature: length = 0x2
   01 40 

public scala.collection.immutable.List declStack();
  Code:
   Stack=1, Locals=1, Args_size=1
   0:	aload_0
   1:	getfield	#38; //Field declStack:Lscala/collection/immutable/List;
   4:	areturn
  LineNumberTable: 
   line 24: 0

  Signature: length = 0x2
   01 41 

public void qCurrent_$eq(int);
  Code:
   Stack=2, Locals=2, Args_size=2
   0:	aload_0
   1:	iload_1
   2:	putfield	#36; //Field qCurrent:I
   5:	return
  LineNumberTable: 
   line 22: 0


public int qCurrent();
  Code:
   Stack=1, Locals=1, Args_size=1
   0:	aload_0
   1:	getfield	#36; //Field qCurrent:I
   4:	ireturn
  LineNumberTable: 
   line 22: 0


public void qStack_$eq(scala.collection.immutable.List);
  Code:
   Stack=2, Locals=2, Args_size=2
   0:	aload_0
   1:	aload_1
   2:	putfield	#34; //Field qStack:Lscala/collection/immutable/List;
   5:	return
  LineNumberTable: 
   line 21: 0

  Signature: length = 0x2
   01 42 

public scala.collection.immutable.List qStack();
  Code:
   Stack=1, Locals=1, Args_size=1
   0:	aload_0
   1:	getfield	#34; //Field qStack:Lscala/collection/immutable/List;
   4:	areturn
  LineNumberTable: 
   line 21: 0

  Signature: length = 0x2
   01 43 

public void rootLabel_$eq(java.lang.String);
  Code:
   Stack=2, Locals=2, Args_size=2
   0:	aload_0
   1:	aload_1
   2:	putfield	#325; //Field rootLabel:Ljava/lang/String;
   5:	return
  LineNumberTable: 
   line 20: 0


public java.lang.String rootLabel();
  Code:
   Stack=1, Locals=1, Args_size=1
   0:	aload_0
   1:	getfield	#325; //Field rootLabel:Ljava/lang/String;
   4:	areturn
  LineNumberTable: 
   line 20: 0


}

