Compiled from "XhtmlEntities.scala"
public final class scala.xml.parsing.XhtmlEntities$ extends java.lang.Object implements scala.ScalaObject
  SourceFile: "XhtmlEntities.scala"
  Scala: length = 0x
   
  InnerClass: 
   public final $anonfun$2=class scala/xml/parsing/XhtmlEntities$$anonfun$2 of class scala/xml/parsing/XhtmlEntities
   public final $anonfun$1=class scala/xml/parsing/XhtmlEntities$$anonfun$1 of class scala/xml/parsing/XhtmlEntities
  minor version: 0
  major version: 49
  Constant pool:
Asciz	SourceFile;
Asciz	XhtmlEntities.scala;
Asciz	Scala;
Asciz	MODULE$;
Asciz	Lscala/xml/parsing/XhtmlEntities$;;
Asciz	<clinit>;
Asciz	()V;
Asciz	Code;
Asciz	scala/xml/parsing/XhtmlEntities$;
class	scala/xml/parsing/XhtmlEntities$
Asciz	<init>;
NameAndType	"<init>":()V
Method	scala/xml/parsing/XhtmlEntities$."<init>":()V
Asciz	entities;
Asciz	Lscala/collection/immutable/List;;
Asciz	Lscala/collection/immutable/List<Lscala/Tuple2<Ljava/lang/String;Lscala/xml/dtd/ParsedEntityDecl;>;>;;
Asciz	Signature;
Asciz	entMap;
Asciz	Lscala/collection/immutable/Map;;
Asciz	Lscala/collection/immutable/Map<Ljava/lang/String;Ljava/lang/Character;>;;
Asciz	entList;
Asciz	Lscala/collection/immutable/List<Lscala/Tuple2<Ljava/lang/String;Ljava/lang/Integer;>;>;;
Asciz	()Lscala/collection/immutable/List;;
Asciz	LineNumberTable;
NameAndType	entList:Lscala/collection/immutable/List;
Field	scala/xml/parsing/XhtmlEntities$.entList:Lscala/collection/immutable/List;
Asciz	()Lscala/collection/immutable/List<Lscala/Tuple2<Ljava/lang/String;Ljava/lang/Integer;>;>;;
Asciz	()Lscala/collection/immutable/Map;;
NameAndType	entMap:Lscala/collection/immutable/Map;
Field	scala/xml/parsing/XhtmlEntities$.entMap:Lscala/collection/immutable/Map;
Asciz	()Lscala/collection/immutable/Map<Ljava/lang/String;Ljava/lang/Character;>;;
NameAndType	entities:Lscala/collection/immutable/List;
Field	scala/xml/parsing/XhtmlEntities$.entities:Lscala/collection/immutable/List;
Asciz	()Lscala/collection/immutable/List<Lscala/Tuple2<Ljava/lang/String;Lscala/xml/dtd/ParsedEntityDecl;>;>;;
Asciz	apply;
NameAndType	entities:()Lscala/collection/immutable/List;
Method	scala/xml/parsing/XhtmlEntities$.entities:()Lscala/collection/immutable/List;
Asciz	java/lang/Object;
class	java/lang/Object
Method	java/lang/Object."<init>":()V
NameAndType	MODULE$:Lscala/xml/parsing/XhtmlEntities$;
Field	scala/xml/parsing/XhtmlEntities$.MODULE$:Lscala/xml/parsing/XhtmlEntities$;
Asciz	scala/collection/immutable/List$;
class	scala/collection/immutable/List$
Asciz	Lscala/collection/immutable/List$;;
NameAndType	MODULE$:Lscala/collection/immutable/List$;
Field	scala/collection/immutable/List$.MODULE$:Lscala/collection/immutable/List$;
Asciz	scala/Predef$;
class	scala/Predef$
Asciz	Lscala/Predef$;;
NameAndType	MODULE$:Lscala/Predef$;
Field	scala/Predef$.MODULE$:Lscala/Predef$;
int	249;
Asciz	scala/Tuple2;
class	scala/Tuple2
Asciz	quot;
String	quot
int	34;
Asciz	scala/runtime/BoxesRunTime;
class	scala/runtime/BoxesRunTime
Asciz	boxToInteger;
Asciz	(I)Ljava/lang/Integer;;
NameAndType	boxToInteger:(I)Ljava/lang/Integer;
Method	scala/runtime/BoxesRunTime.boxToInteger:(I)Ljava/lang/Integer;
Asciz	(Ljava/lang/Object;Ljava/lang/Object;)V;
NameAndType	"<init>":(Ljava/lang/Object;Ljava/lang/Object;)V
Method	scala/Tuple2."<init>":(Ljava/lang/Object;Ljava/lang/Object;)V
Asciz	amp;
String	amp
int	38;
Asciz	lt;
String	lt
int	60;
Asciz	gt;
String	gt
int	62;
Asciz	nbsp;
String	nbsp
int	160;
Asciz	iexcl;
String	iexcl
int	161;
int	6;
Asciz	cent;
String	cent
int	162;
int	7;
Asciz	pound;
String	pound
int	163;
int	8;
Asciz	curren;
String	curren
int	164;
int	9;
Asciz	yen;
String	yen
int	165;
int	10;
Asciz	euro;
String	euro
int	8364;
int	11;
Asciz	brvbar;
String	brvbar
int	166;
int	12;
Asciz	sect;
String	sect
int	167;
int	13;
Asciz	uml;
String	uml
int	168;
int	14;
Asciz	copy;
String	copy
int	169;
int	15;
Asciz	ordf;
String	ordf
int	170;
int	16;
Asciz	laquo;
String	laquo
int	171;
int	17;
Asciz	shy;
String	shy
int	173;
int	18;
Asciz	reg;
String	reg
int	174;
int	19;
Asciz	trade;
String	trade
int	8482;
int	20;
Asciz	macr;
String	macr
int	175;
int	21;
Asciz	deg;
String	deg
int	176;
int	22;
Asciz	plusmn;
String	plusmn
int	177;
int	23;
Asciz	sup2;
String	sup2
int	178;
int	24;
Asciz	sup3;
String	sup3
int	179;
int	25;
Asciz	acute;
String	acute
int	180;
int	26;
Asciz	micro;
String	micro
int	181;
int	27;
Asciz	para;
String	para
int	182;
int	28;
Asciz	middot;
String	middot
int	183;
int	29;
Asciz	cedil;
String	cedil
int	184;
int	30;
Asciz	sup1;
String	sup1
int	185;
int	31;
Asciz	ordm;
String	ordm
int	186;
int	32;
Asciz	raquo;
String	raquo
int	187;
int	33;
Asciz	frac14;
String	frac14
int	188;
Asciz	frac12;
String	frac12
int	189;
int	35;
Asciz	frac34;
String	frac34
int	190;
int	36;
Asciz	iquest;
String	iquest
int	191;
int	37;
Asciz	times;
String	times
int	215;
Asciz	divide;
String	divide
int	247;
int	39;
Asciz	Agrave;
String	Agrave
int	192;
int	40;
Asciz	Aacute;
String	Aacute
int	193;
int	41;
Asciz	Acirc;
String	Acirc
int	194;
int	42;
Asciz	Atilde;
String	Atilde
int	195;
int	43;
Asciz	Auml;
String	Auml
int	196;
int	44;
Asciz	Aring;
String	Aring
int	197;
int	45;
Asciz	AElig;
String	AElig
int	198;
int	46;
Asciz	Ccedil;
String	Ccedil
int	199;
int	47;
Asciz	Egrave;
String	Egrave
int	200;
int	48;
Asciz	Eacute;
String	Eacute
int	201;
int	49;
Asciz	Ecirc;
String	Ecirc
int	202;
int	50;
Asciz	Euml;
String	Euml
int	203;
int	51;
Asciz	Igrave;
String	Igrave
int	204;
int	52;
Asciz	Iacute;
String	Iacute
int	205;
int	53;
Asciz	Icirc;
String	Icirc
int	206;
int	54;
Asciz	Iuml;
String	Iuml
int	207;
int	55;
Asciz	ETH;
String	ETH
int	208;
int	56;
Asciz	Ntilde;
String	Ntilde
int	209;
int	57;
Asciz	Ograve;
String	Ograve
int	210;
int	58;
Asciz	Oacute;
String	Oacute
int	211;
int	59;
Asciz	Ocirc;
String	Ocirc
int	212;
Asciz	Otilde;
String	Otilde
int	213;
int	61;
Asciz	Ouml;
String	Ouml
int	214;
Asciz	Oslash;
String	Oslash
int	216;
int	63;
Asciz	Ugrave;
String	Ugrave
int	217;
int	64;
Asciz	Uacute;
String	Uacute
int	218;
int	65;
Asciz	Ucirc;
String	Ucirc
int	219;
int	66;
Asciz	Uuml;
String	Uuml
int	220;
int	67;
Asciz	Yacute;
String	Yacute
int	221;
int	68;
Asciz	THORN;
String	THORN
int	222;
int	69;
Asciz	szlig;
String	szlig
int	223;
int	70;
Asciz	agrave;
String	agrave
int	224;
int	71;
Asciz	aacute;
String	aacute
int	225;
int	72;
Asciz	acirc;
String	acirc
int	226;
int	73;
Asciz	atilde;
String	atilde
int	227;
int	74;
Asciz	auml;
String	auml
int	228;
int	75;
Asciz	aring;
String	aring
int	229;
int	76;
Asciz	aelig;
String	aelig
int	230;
int	77;
Asciz	ccedil;
String	ccedil
int	231;
int	78;
Asciz	egrave;
String	egrave
int	232;
int	79;
Asciz	eacute;
String	eacute
int	233;
int	80;
Asciz	ecirc;
String	ecirc
int	234;
int	81;
Asciz	euml;
String	euml
int	235;
int	82;
Asciz	igrave;
String	igrave
int	236;
int	83;
Asciz	iacute;
String	iacute
int	237;
int	84;
Asciz	icirc;
String	icirc
int	238;
int	85;
Asciz	iuml;
String	iuml
int	239;
int	86;
Asciz	eth;
String	eth
int	240;
int	87;
Asciz	ntilde;
String	ntilde
int	241;
int	88;
Asciz	ograve;
String	ograve
int	242;
int	89;
Asciz	oacute;
String	oacute
int	243;
int	90;
Asciz	ocirc;
String	ocirc
int	244;
int	91;
Asciz	otilde;
String	otilde
int	245;
int	92;
Asciz	ouml;
String	ouml
int	246;
int	93;
Asciz	oslash;
String	oslash
int	248;
int	94;
Asciz	ugrave;
String	ugrave
int	95;
Asciz	uacute;
String	uacute
int	250;
int	96;
Asciz	ucirc;
String	ucirc
int	251;
int	97;
Asciz	uuml;
String	uuml
int	252;
int	98;
Asciz	yacute;
String	yacute
int	253;
int	99;
Asciz	thorn;
String	thorn
int	254;
int	100;
Asciz	yuml;
String	yuml
int	255;
int	101;
Asciz	OElig;
String	OElig
int	338;
int	102;
Asciz	oelig;
String	oelig
int	339;
int	103;
Asciz	Scaron;
String	Scaron
int	352;
int	104;
Asciz	scaron;
String	scaron
int	353;
int	105;
Asciz	Yuml;
String	Yuml
int	376;
int	106;
Asciz	circ;
String	circ
int	710;
int	107;
Asciz	ensp;
String	ensp
int	8194;
int	108;
Asciz	emsp;
String	emsp
int	8195;
int	109;
Asciz	zwnj;
String	zwnj
int	110;
Asciz	zwj;
String	zwj
int	8205;
int	111;
Asciz	lrm;
String	lrm
int	8206;
int	112;
Asciz	rlm;
String	rlm
int	8207;
int	113;
Asciz	ndash;
String	ndash
int	8211;
int	114;
Asciz	mdash;
String	mdash
int	8212;
int	115;
Asciz	lsquo;
String	lsquo
int	8216;
int	116;
Asciz	rsquo;
String	rsquo
int	8217;
int	117;
Asciz	sbquo;
String	sbquo
int	8218;
int	118;
Asciz	ldquo;
String	ldquo
int	8220;
int	119;
Asciz	rdquo;
String	rdquo
int	8221;
int	120;
Asciz	bdquo;
String	bdquo
int	8222;
int	121;
Asciz	dagger;
String	dagger
int	8224;
int	122;
Asciz	Dagger;
String	Dagger
int	8225;
int	123;
Asciz	permil;
String	permil
int	8240;
int	124;
Asciz	lsaquo;
String	lsaquo
int	8249;
int	125;
Asciz	rsaquo;
String	rsaquo
int	8250;
int	126;
Asciz	fnof;
String	fnof
int	402;
int	127;
Asciz	bull;
String	bull
int	8226;
int	128;
Asciz	hellip;
String	hellip
int	8230;
int	129;
Asciz	prime;
String	prime
int	8242;
int	130;
Asciz	Prime;
String	Prime
int	8243;
int	131;
Asciz	oline;
String	oline
int	8254;
int	132;
Asciz	frasl;
String	frasl
int	8260;
int	133;
Asciz	weierp;
String	weierp
int	8472;
int	134;
Asciz	image;
String	image
int	8465;
int	135;
Asciz	real;
String	real
int	8476;
int	136;
Asciz	alefsym;
String	alefsym
int	8501;
int	137;
Asciz	larr;
String	larr
int	8592;
int	138;
Asciz	uarr;
String	uarr
int	8593;
int	139;
Asciz	rarr;
String	rarr
int	8594;
int	140;
Asciz	darr;
String	darr
int	8495;
int	141;
Asciz	harr;
String	harr
int	8596;
int	142;
Asciz	crarr;
String	crarr
int	8629;
int	143;
Asciz	lArr;
String	lArr
int	8656;
int	144;
Asciz	uArr;
String	uArr
int	8657;
int	145;
Asciz	rArr;
String	rArr
int	8658;
int	146;
Asciz	dArr;
String	dArr
int	8659;
int	147;
Asciz	hArr;
String	hArr
int	8660;
int	148;
Asciz	forall;
String	forall
int	8704;
int	149;
Asciz	part;
String	part
int	8706;
int	150;
Asciz	exist;
String	exist
int	8707;
int	151;
Asciz	empty;
String	empty
int	8709;
int	152;
Asciz	nabla;
String	nabla
int	8711;
int	153;
Asciz	isin;
String	isin
int	8712;
int	154;
Asciz	notin;
String	notin
int	8713;
int	155;
Asciz	ni;
String	ni
int	8715;
int	156;
Asciz	prod;
String	prod
int	8719;
int	157;
Asciz	sum;
String	sum
int	8721;
int	158;
Asciz	minus;
String	minus
int	8722;
int	159;
Asciz	lowast;
String	lowast
int	8727;
Asciz	radic;
String	radic
int	8730;
Asciz	prop;
String	prop
int	8733;
Asciz	infin;
String	infin
int	8734;
Asciz	ang;
String	ang
int	8736;
Asciz	and;
String	and
int	8743;
Asciz	or;
String	or
int	8744;
Asciz	cap;
String	cap
int	8745;
Asciz	cup;
String	cup
int	8746;
Asciz	int;
String	int
int	8747;
Asciz	there4;
String	there4
int	8756;
Asciz	sim;
String	sim
int	8764;
Asciz	cong;
String	cong
int	8773;
int	172;
Asciz	asymp;
String	asymp
int	8776;
Asciz	ne;
String	ne
int	8800;
Asciz	equiv;
String	equiv
int	8801;
Asciz	le;
String	le
int	8804;
Asciz	ge;
String	ge
int	8805;
Asciz	sub;
String	sub
int	8834;
Asciz	sup;
String	sup
int	8835;
Asciz	nsub;
String	nsub
int	8836;
Asciz	sube;
String	sube
int	8838;
Asciz	supe;
String	supe
int	8839;
Asciz	oplus;
String	oplus
int	8853;
Asciz	otimes;
String	otimes
int	8855;
Asciz	perp;
String	perp
int	8869;
Asciz	sdot;
String	sdot
int	8901;
Asciz	lceil;
String	lceil
int	8968;
Asciz	rceil;
String	rceil
int	8969;
Asciz	lfloor;
String	lfloor
int	8970;
Asciz	rfloor;
String	rfloor
int	8971;
Asciz	lang;
String	lang
int	9001;
Asciz	rang;
String	rang
int	9002;
Asciz	loz;
String	loz
int	9674;
Asciz	spades;
String	spades
int	9824;
Asciz	clubs;
String	clubs
int	9827;
Asciz	hearts;
String	hearts
int	9829;
Asciz	diams;
String	diams
int	9830;
Asciz	Alpha;
String	Alpha
int	913;
Asciz	Beta;
String	Beta
int	914;
Asciz	Gamma;
String	Gamma
int	915;
Asciz	Delta;
String	Delta
int	916;
Asciz	Epsilon;
String	Epsilon
int	917;
Asciz	Zeta;
String	Zeta
int	918;
Asciz	Eta;
String	Eta
int	919;
Asciz	Theta;
String	Theta
int	920;
Asciz	Iota;
String	Iota
int	921;
Asciz	Kappa;
String	Kappa
int	922;
Asciz	Lambda;
String	Lambda
int	923;
Asciz	Mu;
String	Mu
int	924;
Asciz	Nu;
String	Nu
int	925;
Asciz	Xi;
String	Xi
int	926;
Asciz	Omicron;
String	Omicron
int	927;
Asciz	Pi;
String	Pi
int	928;
Asciz	Rho;
String	Rho
int	929;
Asciz	Sigma;
String	Sigma
int	931;
Asciz	Tau;
String	Tau
int	932;
Asciz	Upsilon;
String	Upsilon
int	933;
Asciz	Phi;
String	Phi
int	934;
Asciz	Chi;
String	Chi
int	935;
Asciz	Psi;
String	Psi
int	936;
Asciz	Omega;
String	Omega
int	937;
Asciz	alpha;
String	alpha
int	945;
Asciz	beta;
String	beta
int	946;
Asciz	gamma;
String	gamma
int	947;
Asciz	delta;
String	delta
int	948;
Asciz	epsilon;
String	epsilon
int	949;
Asciz	zeta;
String	zeta
int	950;
Asciz	eta;
String	eta
int	951;
Asciz	theta;
String	theta
int	952;
Asciz	iota;
String	iota
int	953;
Asciz	kappa;
String	kappa
int	954;
Asciz	lambda;
String	lambda
int	955;
Asciz	mu;
String	mu
int	956;
Asciz	nu;
String	nu
int	957;
Asciz	xi;
String	xi
int	958;
Asciz	omicron;
String	omicron
int	959;
Asciz	pi;
String	pi
int	960;
Asciz	rho;
String	rho
int	961;
Asciz	sigmaf;
String	sigmaf
int	962;
Asciz	sigma;
String	sigma
int	963;
Asciz	tau;
String	tau
int	964;
Asciz	upsilon;
String	upsilon
int	965;
Asciz	phi;
String	phi
int	966;
Asciz	chi;
String	chi
int	967;
Asciz	psi;
String	psi
int	968;
Asciz	omega;
String	omega
int	969;
Asciz	thetasym;
String	thetasym
int	977;
Asciz	upsih;
String	upsih
int	978;
Asciz	piv;
String	piv
int	982;
Asciz	[Ljava/lang/Object;;
class	"[Ljava/lang/Object;"
Asciz	wrapRefArray;
Asciz	([Ljava/lang/Object;)Lscala/collection/mutable/WrappedArray;;
NameAndType	wrapRefArray:([Ljava/lang/Object;)Lscala/collection/mutable/WrappedArray;
Method	scala/Predef$.wrapRefArray:([Ljava/lang/Object;)Lscala/collection/mutable/WrappedArray;
Asciz	(Lscala/collection/Seq;)Lscala/collection/immutable/List;;
NameAndType	apply:(Lscala/collection/Seq;)Lscala/collection/immutable/List;
Method	scala/collection/immutable/List$.apply:(Lscala/collection/Seq;)Lscala/collection/immutable/List;
Asciz	Map;
Asciz	()Lscala/collection/immutable/Map$;;
NameAndType	Map:()Lscala/collection/immutable/Map$;
Method	scala/Predef$.Map:()Lscala/collection/immutable/Map$;
Asciz	scala/collection/immutable/Map$;
class	scala/collection/immutable/Map$
NameAndType	empty:()Lscala/collection/immutable/Map;
Method	scala/collection/immutable/Map$.empty:()Lscala/collection/immutable/Map;
NameAndType	entList:()Lscala/collection/immutable/List;
Method	scala/xml/parsing/XhtmlEntities$.entList:()Lscala/collection/immutable/List;
Asciz	scala/xml/parsing/XhtmlEntities$$anonfun$1;
class	scala/xml/parsing/XhtmlEntities$$anonfun$1
Method	scala/xml/parsing/XhtmlEntities$$anonfun$1."<init>":()V
Asciz	canBuildFrom;
Asciz	()Lscala/collection/generic/CanBuildFrom;;
NameAndType	canBuildFrom:()Lscala/collection/generic/CanBuildFrom;
Method	scala/collection/immutable/List$.canBuildFrom:()Lscala/collection/generic/CanBuildFrom;
Asciz	scala/collection/TraversableLike;
class	scala/collection/TraversableLike
Asciz	map;
Asciz	(Lscala/Function1;Lscala/collection/generic/CanBuildFrom;)Ljava/lang/Object;;
NameAndType	map:(Lscala/Function1;Lscala/collection/generic/CanBuildFrom;)Ljava/lang/Object;
InterfaceMethod	scala/collection/TraversableLike.map:(Lscala/Function1;Lscala/collection/generic/CanBuildFrom;)Ljava/lang/Object;
Asciz	scala/collection/Traversable;
class	scala/collection/Traversable
Asciz	scala/collection/immutable/MapLike;
class	scala/collection/immutable/MapLike
Asciz	$plus$plus;
Asciz	(Lscala/collection/Traversable;)Lscala/collection/immutable/Map;;
NameAndType	$plus$plus:(Lscala/collection/Traversable;)Lscala/collection/immutable/Map;
InterfaceMethod	scala/collection/immutable/MapLike.$plus$plus:(Lscala/collection/Traversable;)Lscala/collection/immutable/Map;
Asciz	scala/xml/parsing/XhtmlEntities$$anonfun$2;
class	scala/xml/parsing/XhtmlEntities$$anonfun$2
Method	scala/xml/parsing/XhtmlEntities$$anonfun$2."<init>":()V
Asciz	scala/collection/immutable/List;
class	scala/collection/immutable/List
Asciz	InnerClasses;
Asciz	scala/xml/parsing/XhtmlEntities;
class	scala/xml/parsing/XhtmlEntities
Asciz	$anonfun$2;
Asciz	$anonfun$1;
Asciz	scala/ScalaObject;
class	scala/ScalaObject

{
public static final scala.xml.parsing.XhtmlEntities$ MODULE$;
  Signature: Lscala/xml/parsing/XhtmlEntities$;

private final scala.collection.immutable.List entities;
  Signature: Lscala/collection/immutable/List;
  Signature: length = 0x2
   00 10 

private final scala.collection.immutable.Map entMap;
  Signature: Lscala/collection/immutable/Map;
  Signature: length = 0x2
   00 14 

private final scala.collection.immutable.List entList;
  Signature: Lscala/collection/immutable/List;
  Signature: length = 0x2
   00 16 

public static {};
  Signature: ()V
  Code:
   Stack=1, Locals=0, Args_size=0
	new	class scala/xml/parsing/XhtmlEntities$
	invokespecial	Method "<init>":()V
	return
  Labels:

public scala.collection.immutable.List entList();
  Signature: ()Lscala/collection/immutable/List;
  Code:
   Stack=1, Locals=1, Args_size=1
	aload_0
	getfield	Field entList:Lscala/collection/immutable/List;
	areturn
  Labels:
  Signature: length = 0x2
   00 1B 

public scala.collection.immutable.Map entMap();
  Signature: ()Lscala/collection/immutable/Map;
  Code:
   Stack=1, Locals=1, Args_size=1
	aload_0
	getfield	Field entMap:Lscala/collection/immutable/Map;
	areturn
  Labels:
  Signature: length = 0x2
   00 1F 

public scala.collection.immutable.List entities();
  Signature: ()Lscala/collection/immutable/List;
  Code:
   Stack=1, Locals=1, Args_size=1
	aload_0
	getfield	Field entities:Lscala/collection/immutable/List;
	areturn
  Labels:
  Signature: length = 0x2
   00 22 

public scala.collection.immutable.List apply();
  Signature: ()Lscala/collection/immutable/List;
  Code:
   Stack=1, Locals=1, Args_size=1
	aload_0
	invokevirtual	Method entities:()Lscala/collection/immutable/List;
	areturn
  Labels:
  Signature: length = 0x2
   00 22 

private scala.xml.parsing.XhtmlEntities$();
  Signature: ()V
  Code:
   Stack=10, Locals=250, Args_size=1
	aload_0
	invokespecial	Method java/lang/Object."<init>":()V
	aload_0
	putstatic	Field MODULE$:Lscala/xml/parsing/XhtmlEntities$;
	aload_0
	getstatic	Field scala/collection/immutable/List$.MODULE$:Lscala/collection/immutable/List$;
	getstatic	Field scala/Predef$.MODULE$:Lscala/Predef$;
	ldc	int 249
	anewarray	class scala/Tuple2
	dup
	iconst_0
	new	class scala/Tuple2
	dup
	ldc	String quot
	ldc	int 34
	istore_1
	iload_1
	invokestatic	Method scala/runtime/BoxesRunTime.boxToInteger:(I)Ljava/lang/Integer;
	invokespecial	Method scala/Tuple2."<init>":(Ljava/lang/Object;Ljava/lang/Object;)V
	aastore
	dup
	iconst_1
	new	class scala/Tuple2
	dup
	ldc	String amp
	ldc	int 38
	istore_2
	iload_2
	invokestatic	Method scala/runtime/BoxesRunTime.boxToInteger:(I)Ljava/lang/Integer;
	invokespecial	Method scala/Tuple2."<init>":(Ljava/lang/Object;Ljava/lang/Object;)V
	aastore
	dup
	iconst_2
	new	class scala/Tuple2
	dup
	ldc	String lt
	ldc	int 60
	istore_3
	iload_3
	invokestatic	Method scala/runtime/BoxesRunTime.boxToInteger:(I)Ljava/lang/Integer;
	invokespecial	Method scala/Tuple2."<init>":(Ljava/lang/Object;Ljava/lang/Object;)V
	aastore
	dup
	iconst_3
	new	class scala/Tuple2
	dup
	ldc	String gt
	ldc	int 62
	istore	4
	iload	4
	invokestatic	Method scala/runtime/BoxesRunTime.boxToInteger:(I)Ljava/lang/Integer;
	invokespecial	Method scala/Tuple2."<init>":(Ljava/lang/Object;Ljava/lang/Object;)V
	aastore
	dup
	iconst_4
	new	class scala/Tuple2
	dup
	ldc	String nbsp
	ldc	int 160
	istore	5
	iload	5
	invokestatic	Method scala/runtime/BoxesRunTime.boxToInteger:(I)Ljava/lang/Integer;
	invokespecial	Method scala/Tuple2."<init>":(Ljava/lang/Object;Ljava/lang/Object;)V
	aastore
	dup
	iconst_5
	new	class scala/Tuple2
	dup
	ldc	String iexcl
	ldc	int 161
	istore	6
	iload	6
	invokestatic	Method scala/runtime/BoxesRunTime.boxToInteger:(I)Ljava/lang/Integer;
	invokespecial	Method scala/Tuple2."<init>":(Ljava/lang/Object;Ljava/lang/Object;)V
	aastore
	dup
	ldc	int 6
	new	class scala/Tuple2
	dup
	ldc	String cent
	ldc	int 162
	istore	7
	iload	7
	invokestatic	Method scala/runtime/BoxesRunTime.boxToInteger:(I)Ljava/lang/Integer;
	invokespecial	Method scala/Tuple2."<init>":(Ljava/lang/Object;Ljava/lang/Object;)V
	aastore
	dup
	ldc	int 7
	new	class scala/Tuple2
	dup
	ldc	String pound
	ldc	int 163
	istore	8
	iload	8
	invokestatic	Method scala/runtime/BoxesRunTime.boxToInteger:(I)Ljava/lang/Integer;
	invokespecial	Method scala/Tuple2."<init>":(Ljava/lang/Object;Ljava/lang/Object;)V
	aastore
	dup
	ldc	int 8
	new	class scala/Tuple2
	dup
	ldc	String curren
	ldc	int 164
	istore	9
	iload	9
	invokestatic	Method scala/runtime/BoxesRunTime.boxToInteger:(I)Ljava/lang/Integer;
	invokespecial	Method scala/Tuple2."<init>":(Ljava/lang/Object;Ljava/lang/Object;)V
	aastore
	dup
	ldc	int 9
	new	class scala/Tuple2
	dup
	ldc	String yen
	ldc	int 165
	istore	10
	iload	10
	invokestatic	Method scala/runtime/BoxesRunTime.boxToInteger:(I)Ljava/lang/Integer;
	invokespecial	Method scala/Tuple2."<init>":(Ljava/lang/Object;Ljava/lang/Object;)V
	aastore
	dup
	ldc	int 10
	new	class scala/Tuple2
	dup
	ldc	String euro
	ldc	int 8364
	istore	11
	iload	11
	invokestatic	Method scala/runtime/BoxesRunTime.boxToInteger:(I)Ljava/lang/Integer;
	invokespecial	Method scala/Tuple2."<init>":(Ljava/lang/Object;Ljava/lang/Object;)V
	aastore
	dup
	ldc	int 11
	new	class scala/Tuple2
	dup
	ldc	String brvbar
	ldc	int 166
	istore	12
	iload	12
	invokestatic	Method scala/runtime/BoxesRunTime.boxToInteger:(I)Ljava/lang/Integer;
	invokespecial	Method scala/Tuple2."<init>":(Ljava/lang/Object;Ljava/lang/Object;)V
	aastore
	dup
	ldc	int 12
	new	class scala/Tuple2
	dup
	ldc	String sect
	ldc	int 167
	istore	13
	iload	13
	invokestatic	Method scala/runtime/BoxesRunTime.boxToInteger:(I)Ljava/lang/Integer;
	invokespecial	Method scala/Tuple2."<init>":(Ljava/lang/Object;Ljava/lang/Object;)V
	aastore
	dup
	ldc	int 13
	new	class scala/Tuple2
	dup
	ldc	String uml
	ldc	int 168
	istore	14
	iload	14
	invokestatic	Method scala/runtime/BoxesRunTime.boxToInteger:(I)Ljava/lang/Integer;
	invokespecial	Method scala/Tuple2."<init>":(Ljava/lang/Object;Ljava/lang/Object;)V
	aastore
	dup
	ldc	int 14
	new	class scala/Tuple2
	dup
	ldc	String copy
	ldc	int 169
	istore	15
	iload	15
	invokestatic	Method scala/runtime/BoxesRunTime.boxToInteger:(I)Ljava/lang/Integer;
	invokespecial	Method scala/Tuple2."<init>":(Ljava/lang/Object;Ljava/lang/Object;)V
	aastore
	dup
	ldc	int 15
	new	class scala/Tuple2
	dup
	ldc	String ordf
	ldc	int 170
	istore	16
	iload	16
	invokestatic	Method scala/runtime/BoxesRunTime.boxToInteger:(I)Ljava/lang/Integer;
	invokespecial	Method scala/Tuple2."<init>":(Ljava/lang/Object;Ljava/lang/Object;)V
	aastore
	dup
	ldc	int 16
	new	class scala/Tuple2
	dup
	ldc	String laquo
	ldc	int 171
	istore	17
	iload	17
	invokestatic	Method scala/runtime/BoxesRunTime.boxToInteger:(I)Ljava/lang/Integer;
	invokespecial	Method scala/Tuple2."<init>":(Ljava/lang/Object;Ljava/lang/Object;)V
	aastore
	dup
	ldc	int 17
	new	class scala/Tuple2
	dup
	ldc	String shy
	ldc	int 173
	istore	18
	iload	18
	invokestatic	Method scala/runtime/BoxesRunTime.boxToInteger:(I)Ljava/lang/Integer;
	invokespecial	Method scala/Tuple2."<init>":(Ljava/lang/Object;Ljava/lang/Object;)V
	aastore
	dup
	ldc	int 18
	new	class scala/Tuple2
	dup
	ldc	String reg
	ldc	int 174
	istore	19
	iload	19
	invokestatic	Method scala/runtime/BoxesRunTime.boxToInteger:(I)Ljava/lang/Integer;
	invokespecial	Method scala/Tuple2."<init>":(Ljava/lang/Object;Ljava/lang/Object;)V
	aastore
	dup
	ldc	int 19
	new	class scala/Tuple2
	dup
	ldc	String trade
	ldc	int 8482
	istore	20
	iload	20
	invokestatic	Method scala/runtime/BoxesRunTime.boxToInteger:(I)Ljava/lang/Integer;
	invokespecial	Method scala/Tuple2."<init>":(Ljava/lang/Object;Ljava/lang/Object;)V
	aastore
	dup
	ldc	int 20
	new	class scala/Tuple2
	dup
	ldc	String macr
	ldc	int 175
	istore	21
	iload	21
	invokestatic	Method scala/runtime/BoxesRunTime.boxToInteger:(I)Ljava/lang/Integer;
	invokespecial	Method scala/Tuple2."<init>":(Ljava/lang/Object;Ljava/lang/Object;)V
	aastore
	dup
	ldc	int 21
	new	class scala/Tuple2
	dup
	ldc	String deg
	ldc	int 176
	istore	22
	iload	22
	invokestatic	Method scala/runtime/BoxesRunTime.boxToInteger:(I)Ljava/lang/Integer;
	invokespecial	Method scala/Tuple2."<init>":(Ljava/lang/Object;Ljava/lang/Object;)V
	aastore
	dup
	ldc	int 22
	new	class scala/Tuple2
	dup
	ldc	String plusmn
	ldc	int 177
	istore	23
	iload	23
	invokestatic	Method scala/runtime/BoxesRunTime.boxToInteger:(I)Ljava/lang/Integer;
	invokespecial	Method scala/Tuple2."<init>":(Ljava/lang/Object;Ljava/lang/Object;)V
	aastore
	dup
	ldc	int 23
	new	class scala/Tuple2
	dup
	ldc	String sup2
	ldc	int 178
	istore	24
	iload	24
	invokestatic	Method scala/runtime/BoxesRunTime.boxToInteger:(I)Ljava/lang/Integer;
	invokespecial	Method scala/Tuple2."<init>":(Ljava/lang/Object;Ljava/lang/Object;)V
	aastore
	dup
	ldc	int 24
	new	class scala/Tuple2
	dup
	ldc	String sup3
	ldc	int 179
	istore	25
	iload	25
	invokestatic	Method scala/runtime/BoxesRunTime.boxToInteger:(I)Ljava/lang/Integer;
	invokespecial	Method scala/Tuple2."<init>":(Ljava/lang/Object;Ljava/lang/Object;)V
	aastore
	dup
	ldc	int 25
	new	class scala/Tuple2
	dup
	ldc	String acute
	ldc	int 180
	istore	26
	iload	26
	invokestatic	Method scala/runtime/BoxesRunTime.boxToInteger:(I)Ljava/lang/Integer;
	invokespecial	Method scala/Tuple2."<init>":(Ljava/lang/Object;Ljava/lang/Object;)V
	aastore
	dup
	ldc	int 26
	new	class scala/Tuple2
	dup
	ldc	String micro
	ldc	int 181
	istore	27
	iload	27
	invokestatic	Method scala/runtime/BoxesRunTime.boxToInteger:(I)Ljava/lang/Integer;
	invokespecial	Method scala/Tuple2."<init>":(Ljava/lang/Object;Ljava/lang/Object;)V
	aastore
	dup
	ldc	int 27
	new	class scala/Tuple2
	dup
	ldc	String para
	ldc	int 182
	istore	28
	iload	28
	invokestatic	Method scala/runtime/BoxesRunTime.boxToInteger:(I)Ljava/lang/Integer;
	invokespecial	Method scala/Tuple2."<init>":(Ljava/lang/Object;Ljava/lang/Object;)V
	aastore
	dup
	ldc	int 28
	new	class scala/Tuple2
	dup
	ldc	String middot
	ldc	int 183
	istore	29
	iload	29
	invokestatic	Method scala/runtime/BoxesRunTime.boxToInteger:(I)Ljava/lang/Integer;
	invokespecial	Method scala/Tuple2."<init>":(Ljava/lang/Object;Ljava/lang/Object;)V
	aastore
	dup
	ldc	int 29
	new	class scala/Tuple2
	dup
	ldc	String cedil
	ldc	int 184
	istore	30
	iload	30
	invokestatic	Method scala/runtime/BoxesRunTime.boxToInteger:(I)Ljava/lang/Integer;
	invokespecial	Method scala/Tuple2."<init>":(Ljava/lang/Object;Ljava/lang/Object;)V
	aastore
	dup
	ldc	int 30
	new	class scala/Tuple2
	dup
	ldc	String sup1
	ldc	int 185
	istore	31
	iload	31
	invokestatic	Method scala/runtime/BoxesRunTime.boxToInteger:(I)Ljava/lang/Integer;
	invokespecial	Method scala/Tuple2."<init>":(Ljava/lang/Object;Ljava/lang/Object;)V
	aastore
	dup
	ldc	int 31
	new	class scala/Tuple2
	dup
	ldc	String ordm
	ldc	int 186
	istore	32
	iload	32
	invokestatic	Method scala/runtime/BoxesRunTime.boxToInteger:(I)Ljava/lang/Integer;
	invokespecial	Method scala/Tuple2."<init>":(Ljava/lang/Object;Ljava/lang/Object;)V
	aastore
	dup
	ldc	int 32
	new	class scala/Tuple2
	dup
	ldc	String raquo
	ldc	int 187
	istore	33
	iload	33
	invokestatic	Method scala/runtime/BoxesRunTime.boxToInteger:(I)Ljava/lang/Integer;
	invokespecial	Method scala/Tuple2."<init>":(Ljava/lang/Object;Ljava/lang/Object;)V
	aastore
	dup
	ldc	int 33
	new	class scala/Tuple2
	dup
	ldc	String frac14
	ldc	int 188
	istore	34
	iload	34
	invokestatic	Method scala/runtime/BoxesRunTime.boxToInteger:(I)Ljava/lang/Integer;
	invokespecial	Method scala/Tuple2."<init>":(Ljava/lang/Object;Ljava/lang/Object;)V
	aastore
	dup
	ldc	int 34
	new	class scala/Tuple2
	dup
	ldc	String frac12
	ldc	int 189
	istore	35
	iload	35
	invokestatic	Method scala/runtime/BoxesRunTime.boxToInteger:(I)Ljava/lang/Integer;
	invokespecial	Method scala/Tuple2."<init>":(Ljava/lang/Object;Ljava/lang/Object;)V
	aastore
	dup
	ldc	int 35
	new	class scala/Tuple2
	dup
	ldc	String frac34
	ldc	int 190
	istore	36
	iload	36
	invokestatic	Method scala/runtime/BoxesRunTime.boxToInteger:(I)Ljava/lang/Integer;
	invokespecial	Method scala/Tuple2."<init>":(Ljava/lang/Object;Ljava/lang/Object;)V
	aastore
	dup
	ldc	int 36
	new	class scala/Tuple2
	dup
	ldc	String iquest
	ldc	int 191
	istore	37
	iload	37
	invokestatic	Method scala/runtime/BoxesRunTime.boxToInteger:(I)Ljava/lang/Integer;
	invokespecial	Method scala/Tuple2."<init>":(Ljava/lang/Object;Ljava/lang/Object;)V
	aastore
	dup
	ldc	int 37
	new	class scala/Tuple2
	dup
	ldc	String times
	ldc	int 215
	istore	38
	iload	38
	invokestatic	Method scala/runtime/BoxesRunTime.boxToInteger:(I)Ljava/lang/Integer;
	invokespecial	Method scala/Tuple2."<init>":(Ljava/lang/Object;Ljava/lang/Object;)V
	aastore
	dup
	ldc	int 38
	new	class scala/Tuple2
	dup
	ldc	String divide
	ldc	int 247
	istore	39
	iload	39
	invokestatic	Method scala/runtime/BoxesRunTime.boxToInteger:(I)Ljava/lang/Integer;
	invokespecial	Method scala/Tuple2."<init>":(Ljava/lang/Object;Ljava/lang/Object;)V
	aastore
	dup
	ldc	int 39
	new	class scala/Tuple2
	dup
	ldc	String Agrave
	ldc	int 192
	istore	40
	iload	40
	invokestatic	Method scala/runtime/BoxesRunTime.boxToInteger:(I)Ljava/lang/Integer;
	invokespecial	Method scala/Tuple2."<init>":(Ljava/lang/Object;Ljava/lang/Object;)V
	aastore
	dup
	ldc	int 40
	new	class scala/Tuple2
	dup
	ldc	String Aacute
	ldc	int 193
	istore	41
	iload	41
	invokestatic	Method scala/runtime/BoxesRunTime.boxToInteger:(I)Ljava/lang/Integer;
	invokespecial	Method scala/Tuple2."<init>":(Ljava/lang/Object;Ljava/lang/Object;)V
	aastore
	dup
	ldc	int 41
	new	class scala/Tuple2
	dup
	ldc	String Acirc
	ldc	int 194
	istore	42
	iload	42
	invokestatic	Method scala/runtime/BoxesRunTime.boxToInteger:(I)Ljava/lang/Integer;
	invokespecial	Method scala/Tuple2."<init>":(Ljava/lang/Object;Ljava/lang/Object;)V
	aastore
	dup
	ldc	int 42
	new	class scala/Tuple2
	dup
	ldc	String Atilde
	ldc	int 195
	istore	43
	iload	43
	invokestatic	Method scala/runtime/BoxesRunTime.boxToInteger:(I)Ljava/lang/Integer;
	invokespecial	Method scala/Tuple2."<init>":(Ljava/lang/Object;Ljava/lang/Object;)V
	aastore
	dup
	ldc	int 43
	new	class scala/Tuple2
	dup
	ldc	String Auml
	ldc	int 196
	istore	44
	iload	44
	invokestatic	Method scala/runtime/BoxesRunTime.boxToInteger:(I)Ljava/lang/Integer;
	invokespecial	Method scala/Tuple2."<init>":(Ljava/lang/Object;Ljava/lang/Object;)V
	aastore
	dup
	ldc	int 44
	new	class scala/Tuple2
	dup
	ldc	String Aring
	ldc	int 197
	istore	45
	iload	45
	invokestatic	Method scala/runtime/BoxesRunTime.boxToInteger:(I)Ljava/lang/Integer;
	invokespecial	Method scala/Tuple2."<init>":(Ljava/lang/Object;Ljava/lang/Object;)V
	aastore
	dup
	ldc	int 45
	new	class scala/Tuple2
	dup
	ldc	String AElig
	ldc	int 198
	istore	46
	iload	46
	invokestatic	Method scala/runtime/BoxesRunTime.boxToInteger:(I)Ljava/lang/Integer;
	invokespecial	Method scala/Tuple2."<init>":(Ljava/lang/Object;Ljava/lang/Object;)V
	aastore
	dup
	ldc	int 46
	new	class scala/Tuple2
	dup
	ldc	String Ccedil
	ldc	int 199
	istore	47
	iload	47
	invokestatic	Method scala/runtime/BoxesRunTime.boxToInteger:(I)Ljava/lang/Integer;
	invokespecial	Method scala/Tuple2."<init>":(Ljava/lang/Object;Ljava/lang/Object;)V
	aastore
	dup
	ldc	int 47
	new	class scala/Tuple2
	dup
	ldc	String Egrave
	ldc	int 200
	istore	48
	iload	48
	invokestatic	Method scala/runtime/BoxesRunTime.boxToInteger:(I)Ljava/lang/Integer;
	invokespecial	Method scala/Tuple2."<init>":(Ljava/lang/Object;Ljava/lang/Object;)V
	aastore
	dup
	ldc	int 48
	new	class scala/Tuple2
	dup
	ldc	String Eacute
	ldc	int 201
	istore	49
	iload	49
	invokestatic	Method scala/runtime/BoxesRunTime.boxToInteger:(I)Ljava/lang/Integer;
	invokespecial	Method scala/Tuple2."<init>":(Ljava/lang/Object;Ljava/lang/Object;)V
	aastore
	dup
	ldc	int 49
	new	class scala/Tuple2
	dup
	ldc	String Ecirc
	ldc_w	int 202
	istore	50
	iload	50
	invokestatic	Method scala/runtime/BoxesRunTime.boxToInteger:(I)Ljava/lang/Integer;
	invokespecial	Method scala/Tuple2."<init>":(Ljava/lang/Object;Ljava/lang/Object;)V
	aastore
	dup
	ldc_w	int 50
	new	class scala/Tuple2
	dup
	ldc_w	String Euml
	ldc_w	int 203
	istore	51
	iload	51
	invokestatic	Method scala/runtime/BoxesRunTime.boxToInteger:(I)Ljava/lang/Integer;
	invokespecial	Method scala/Tuple2."<init>":(Ljava/lang/Object;Ljava/lang/Object;)V
	aastore
	dup
	ldc_w	int 51
	new	class scala/Tuple2
	dup
	ldc_w	String Igrave
	ldc_w	int 204
	istore	52
	iload	52
	invokestatic	Method scala/runtime/BoxesRunTime.boxToInteger:(I)Ljava/lang/Integer;
	invokespecial	Method scala/Tuple2."<init>":(Ljava/lang/Object;Ljava/lang/Object;)V
	aastore
	dup
	ldc_w	int 52
	new	class scala/Tuple2
	dup
	ldc_w	String Iacute
	ldc_w	int 205
	istore	53
	iload	53
	invokestatic	Method scala/runtime/BoxesRunTime.boxToInteger:(I)Ljava/lang/Integer;
	invokespecial	Method scala/Tuple2."<init>":(Ljava/lang/Object;Ljava/lang/Object;)V
	aastore
	dup
	ldc_w	int 53
	new	class scala/Tuple2
	dup
	ldc_w	String Icirc
	ldc_w	int 206
	istore	54
	iload	54
	invokestatic	Method scala/runtime/BoxesRunTime.boxToInteger:(I)Ljava/lang/Integer;
	invokespecial	Method scala/Tuple2."<init>":(Ljava/lang/Object;Ljava/lang/Object;)V
	aastore
	dup
	ldc_w	int 54
	new	class scala/Tuple2
	dup
	ldc_w	String Iuml
	ldc_w	int 207
	istore	55
	iload	55
	invokestatic	Method scala/runtime/BoxesRunTime.boxToInteger:(I)Ljava/lang/Integer;
	invokespecial	Method scala/Tuple2."<init>":(Ljava/lang/Object;Ljava/lang/Object;)V
	aastore
	dup
	ldc_w	int 55
	new	class scala/Tuple2
	dup
	ldc_w	String ETH
	ldc_w	int 208
	istore	56
	iload	56
	invokestatic	Method scala/runtime/BoxesRunTime.boxToInteger:(I)Ljava/lang/Integer;
	invokespecial	Method scala/Tuple2."<init>":(Ljava/lang/Object;Ljava/lang/Object;)V
	aastore
	dup
	ldc_w	int 56
	new	class scala/Tuple2
	dup
	ldc_w	String Ntilde
	ldc_w	int 209
	istore	57
	iload	57
	invokestatic	Method scala/runtime/BoxesRunTime.boxToInteger:(I)Ljava/lang/Integer;
	invokespecial	Method scala/Tuple2."<init>":(Ljava/lang/Object;Ljava/lang/Object;)V
	aastore
	dup
	ldc_w	int 57
	new	class scala/Tuple2
	dup
	ldc_w	String Ograve
	ldc_w	int 210
	istore	58
	iload	58
	invokestatic	Method scala/runtime/BoxesRunTime.boxToInteger:(I)Ljava/lang/Integer;
	invokespecial	Method scala/Tuple2."<init>":(Ljava/lang/Object;Ljava/lang/Object;)V
	aastore
	dup
	ldc_w	int 58
	new	class scala/Tuple2
	dup
	ldc_w	String Oacute
	ldc_w	int 211
	istore	59
	iload	59
	invokestatic	Method scala/runtime/BoxesRunTime.boxToInteger:(I)Ljava/lang/Integer;
	invokespecial	Method scala/Tuple2."<init>":(Ljava/lang/Object;Ljava/lang/Object;)V
	aastore
	dup
	ldc_w	int 59
	new	class scala/Tuple2
	dup
	ldc_w	String Ocirc
	ldc_w	int 212
	istore	60
	iload	60
	invokestatic	Method scala/runtime/BoxesRunTime.boxToInteger:(I)Ljava/lang/Integer;
	invokespecial	Method scala/Tuple2."<init>":(Ljava/lang/Object;Ljava/lang/Object;)V
	aastore
	dup
	ldc	int 60
	new	class scala/Tuple2
	dup
	ldc_w	String Otilde
	ldc_w	int 213
	istore	61
	iload	61
	invokestatic	Method scala/runtime/BoxesRunTime.boxToInteger:(I)Ljava/lang/Integer;
	invokespecial	Method scala/Tuple2."<init>":(Ljava/lang/Object;Ljava/lang/Object;)V
	aastore
	dup
	ldc_w	int 61
	new	class scala/Tuple2
	dup
	ldc_w	String Ouml
	ldc_w	int 214
	istore	62
	iload	62
	invokestatic	Method scala/runtime/BoxesRunTime.boxToInteger:(I)Ljava/lang/Integer;
	invokespecial	Method scala/Tuple2."<init>":(Ljava/lang/Object;Ljava/lang/Object;)V
	aastore
	dup
	ldc	int 62
	new	class scala/Tuple2
	dup
	ldc_w	String Oslash
	ldc_w	int 216
	istore	63
	iload	63
	invokestatic	Method scala/runtime/BoxesRunTime.boxToInteger:(I)Ljava/lang/Integer;
	invokespecial	Method scala/Tuple2."<init>":(Ljava/lang/Object;Ljava/lang/Object;)V
	aastore
	dup
	ldc_w	int 63
	new	class scala/Tuple2
	dup
	ldc_w	String Ugrave
	ldc_w	int 217
	istore	64
	iload	64
	invokestatic	Method scala/runtime/BoxesRunTime.boxToInteger:(I)Ljava/lang/Integer;
	invokespecial	Method scala/Tuple2."<init>":(Ljava/lang/Object;Ljava/lang/Object;)V
	aastore
	dup
	ldc_w	int 64
	new	class scala/Tuple2
	dup
	ldc_w	String Uacute
	ldc_w	int 218
	istore	65
	iload	65
	invokestatic	Method scala/runtime/BoxesRunTime.boxToInteger:(I)Ljava/lang/Integer;
	invokespecial	Method scala/Tuple2."<init>":(Ljava/lang/Object;Ljava/lang/Object;)V
	aastore
	dup
	ldc_w	int 65
	new	class scala/Tuple2
	dup
	ldc_w	String Ucirc
	ldc_w	int 219
	istore	66
	iload	66
	invokestatic	Method scala/runtime/BoxesRunTime.boxToInteger:(I)Ljava/lang/Integer;
	invokespecial	Method scala/Tuple2."<init>":(Ljava/lang/Object;Ljava/lang/Object;)V
	aastore
	dup
	ldc_w	int 66
	new	class scala/Tuple2
	dup
	ldc_w	String Uuml
	ldc_w	int 220
	istore	67
	iload	67
	invokestatic	Method scala/runtime/BoxesRunTime.boxToInteger:(I)Ljava/lang/Integer;
	invokespecial	Method scala/Tuple2."<init>":(Ljava/lang/Object;Ljava/lang/Object;)V
	aastore
	dup
	ldc_w	int 67
	new	class scala/Tuple2
	dup
	ldc_w	String Yacute
	ldc_w	int 221
	istore	68
	iload	68
	invokestatic	Method scala/runtime/BoxesRunTime.boxToInteger:(I)Ljava/lang/Integer;
	invokespecial	Method scala/Tuple2."<init>":(Ljava/lang/Object;Ljava/lang/Object;)V
	aastore
	dup
	ldc_w	int 68
	new	class scala/Tuple2
	dup
	ldc_w	String THORN
	ldc_w	int 222
	istore	69
	iload	69
	invokestatic	Method scala/runtime/BoxesRunTime.boxToInteger:(I)Ljava/lang/Integer;
	invokespecial	Method scala/Tuple2."<init>":(Ljava/lang/Object;Ljava/lang/Object;)V
	aastore
	dup
	ldc_w	int 69
	new	class scala/Tuple2
	dup
	ldc_w	String szlig
	ldc_w	int 223
	istore	70
	iload	70
	invokestatic	Method scala/runtime/BoxesRunTime.boxToInteger:(I)Ljava/lang/Integer;
	invokespecial	Method scala/Tuple2."<init>":(Ljava/lang/Object;Ljava/lang/Object;)V
	aastore
	dup
	ldc_w	int 70
	new	class scala/Tuple2
	dup
	ldc_w	String agrave
	ldc_w	int 224
	istore	71
	iload	71
	invokestatic	Method scala/runtime/BoxesRunTime.boxToInteger:(I)Ljava/lang/Integer;
	invokespecial	Method scala/Tuple2."<init>":(Ljava/lang/Object;Ljava/lang/Object;)V
	aastore
	dup
	ldc_w	int 71
	new	class scala/Tuple2
	dup
	ldc_w	String aacute
	ldc_w	int 225
	istore	72
	iload	72
	invokestatic	Method scala/runtime/BoxesRunTime.boxToInteger:(I)Ljava/lang/Integer;
	invokespecial	Method scala/Tuple2."<init>":(Ljava/lang/Object;Ljava/lang/Object;)V
	aastore
	dup
	ldc_w	int 72
	new	class scala/Tuple2
	dup
	ldc_w	String acirc
	ldc_w	int 226
	istore	73
	iload	73
	invokestatic	Method scala/runtime/BoxesRunTime.boxToInteger:(I)Ljava/lang/Integer;
	invokespecial	Method scala/Tuple2."<init>":(Ljava/lang/Object;Ljava/lang/Object;)V
	aastore
	dup
	ldc_w	int 73
	new	class scala/Tuple2
	dup
	ldc_w	String atilde
	ldc_w	int 227
	istore	74
	iload	74
	invokestatic	Method scala/runtime/BoxesRunTime.boxToInteger:(I)Ljava/lang/Integer;
	invokespecial	Method scala/Tuple2."<init>":(Ljava/lang/Object;Ljava/lang/Object;)V
	aastore
	dup
	ldc_w	int 74
	new	class scala/Tuple2
	dup
	ldc_w	String auml
	ldc_w	int 228
	istore	75
	iload	75
	invokestatic	Method scala/runtime/BoxesRunTime.boxToInteger:(I)Ljava/lang/Integer;
	invokespecial	Method scala/Tuple2."<init>":(Ljava/lang/Object;Ljava/lang/Object;)V
	aastore
	dup
	ldc_w	int 75
	new	class scala/Tuple2
	dup
	ldc_w	String aring
	ldc_w	int 229
	istore	76
	iload	76
	invokestatic	Method scala/runtime/BoxesRunTime.boxToInteger:(I)Ljava/lang/Integer;
	invokespecial	Method scala/Tuple2."<init>":(Ljava/lang/Object;Ljava/lang/Object;)V
	aastore
	dup
	ldc_w	int 76
	new	class scala/Tuple2
	dup
	ldc_w	String aelig
	ldc_w	int 230
	istore	77
	iload	77
	invokestatic	Method scala/runtime/BoxesRunTime.boxToInteger:(I)Ljava/lang/Integer;
	invokespecial	Method scala/Tuple2."<init>":(Ljava/lang/Object;Ljava/lang/Object;)V
	aastore
	dup
	ldc_w	int 77
	new	class scala/Tuple2
	dup
	ldc_w	String ccedil
	ldc_w	int 231
	istore	78
	iload	78
	invokestatic	Method scala/runtime/BoxesRunTime.boxToInteger:(I)Ljava/lang/Integer;
	invokespecial	Method scala/Tuple2."<init>":(Ljava/lang/Object;Ljava/lang/Object;)V
	aastore
	dup
	ldc_w	int 78
	new	class scala/Tuple2
	dup
	ldc_w	String egrave
	ldc_w	int 232
	istore	79
	iload	79
	invokestatic	Method scala/runtime/BoxesRunTime.boxToInteger:(I)Ljava/lang/Integer;
	invokespecial	Method scala/Tuple2."<init>":(Ljava/lang/Object;Ljava/lang/Object;)V
	aastore
	dup
	ldc_w	int 79
	new	class scala/Tuple2
	dup
	ldc_w	String eacute
	ldc_w	int 233
	istore	80
	iload	80
	invokestatic	Method scala/runtime/BoxesRunTime.boxToInteger:(I)Ljava/lang/Integer;
	invokespecial	Method scala/Tuple2."<init>":(Ljava/lang/Object;Ljava/lang/Object;)V
	aastore
	dup
	ldc_w	int 80
	new	class scala/Tuple2
	dup
	ldc_w	String ecirc
	ldc_w	int 234
	istore	81
	iload	81
	invokestatic	Method scala/runtime/BoxesRunTime.boxToInteger:(I)Ljava/lang/Integer;
	invokespecial	Method scala/Tuple2."<init>":(Ljava/lang/Object;Ljava/lang/Object;)V
	aastore
	dup
	ldc_w	int 81
	new	class scala/Tuple2
	dup
	ldc_w	String euml
	ldc_w	int 235
	istore	82
	iload	82
	invokestatic	Method scala/runtime/BoxesRunTime.boxToInteger:(I)Ljava/lang/Integer;
	invokespecial	Method scala/Tuple2."<init>":(Ljava/lang/Object;Ljava/lang/Object;)V
	aastore
	dup
	ldc_w	int 82
	new	class scala/Tuple2
	dup
	ldc_w	String igrave
	ldc_w	int 236
	istore	83
	iload	83
	invokestatic	Method scala/runtime/BoxesRunTime.boxToInteger:(I)Ljava/lang/Integer;
	invokespecial	Method scala/Tuple2."<init>":(Ljava/lang/Object;Ljava/lang/Object;)V
	aastore
	dup
	ldc_w	int 83
	new	class scala/Tuple2
	dup
	ldc_w	String iacute
	ldc_w	int 237
	istore	84
	iload	84
	invokestatic	Method scala/runtime/BoxesRunTime.boxToInteger:(I)Ljava/lang/Integer;
	invokespecial	Method scala/Tuple2."<init>":(Ljava/lang/Object;Ljava/lang/Object;)V
	aastore
	dup
	ldc_w	int 84
	new	class scala/Tuple2
	dup
	ldc_w	String icirc
	ldc_w	int 238
	istore	85
	iload	85
	invokestatic	Method scala/runtime/BoxesRunTime.boxToInteger:(I)Ljava/lang/Integer;
	invokespecial	Method scala/Tuple2."<init>":(Ljava/lang/Object;Ljava/lang/Object;)V
	aastore
	dup
	ldc_w	int 85
	new	class scala/Tuple2
	dup
	ldc_w	String iuml
	ldc_w	int 239
	istore	86
	iload	86
	invokestatic	Method scala/runtime/BoxesRunTime.boxToInteger:(I)Ljava/lang/Integer;
	invokespecial	Method scala/Tuple2."<init>":(Ljava/lang/Object;Ljava/lang/Object;)V
	aastore
	dup
	ldc_w	int 86
	new	class scala/Tuple2
	dup
	ldc_w	String eth
	ldc_w	int 240
	istore	87
	iload	87
	invokestatic	Method scala/runtime/BoxesRunTime.boxToInteger:(I)Ljava/lang/Integer;
	invokespecial	Method scala/Tuple2."<init>":(Ljava/lang/Object;Ljava/lang/Object;)V
	aastore
	dup
	ldc_w	int 87
	new	class scala/Tuple2
	dup
	ldc_w	String ntilde
	ldc_w	int 241
	istore	88
	iload	88
	invokestatic	Method scala/runtime/BoxesRunTime.boxToInteger:(I)Ljava/lang/Integer;
	invokespecial	Method scala/Tuple2."<init>":(Ljava/lang/Object;Ljava/lang/Object;)V
	aastore
	dup
	ldc_w	int 88
	new	class scala/Tuple2
	dup
	ldc_w	String ograve
	ldc_w	int 242
	istore	89
	iload	89
	invokestatic	Method scala/runtime/BoxesRunTime.boxToInteger:(I)Ljava/lang/Integer;
	invokespecial	Method scala/Tuple2."<init>":(Ljava/lang/Object;Ljava/lang/Object;)V
	aastore
	dup
	ldc_w	int 89
	new	class scala/Tuple2
	dup
	ldc_w	String oacute
	ldc_w	int 243
	istore	90
	iload	90
	invokestatic	Method scala/runtime/BoxesRunTime.boxToInteger:(I)Ljava/lang/Integer;
	invokespecial	Method scala/Tuple2."<init>":(Ljava/lang/Object;Ljava/lang/Object;)V
	aastore
	dup
	ldc_w	int 90
	new	class scala/Tuple2
	dup
	ldc_w	String ocirc
	ldc_w	int 244
	istore	91
	iload	91
	invokestatic	Method scala/runtime/BoxesRunTime.boxToInteger:(I)Ljava/lang/Integer;
	invokespecial	Method scala/Tuple2."<init>":(Ljava/lang/Object;Ljava/lang/Object;)V
	aastore
	dup
	ldc_w	int 91
	new	class scala/Tuple2
	dup
	ldc_w	String otilde
	ldc_w	int 245
	istore	92
	iload	92
	invokestatic	Method scala/runtime/BoxesRunTime.boxToInteger:(I)Ljava/lang/Integer;
	invokespecial	Method scala/Tuple2."<init>":(Ljava/lang/Object;Ljava/lang/Object;)V
	aastore
	dup
	ldc_w	int 92
	new	class scala/Tuple2
	dup
	ldc_w	String ouml
	ldc_w	int 246
	istore	93
	iload	93
	invokestatic	Method scala/runtime/BoxesRunTime.boxToInteger:(I)Ljava/lang/Integer;
	invokespecial	Method scala/Tuple2."<init>":(Ljava/lang/Object;Ljava/lang/Object;)V
	aastore
	dup
	ldc_w	int 93
	new	class scala/Tuple2
	dup
	ldc_w	String oslash
	ldc_w	int 248
	istore	94
	iload	94
	invokestatic	Method scala/runtime/BoxesRunTime.boxToInteger:(I)Ljava/lang/Integer;
	invokespecial	Method scala/Tuple2."<init>":(Ljava/lang/Object;Ljava/lang/Object;)V
	aastore
	dup
	ldc_w	int 94
	new	class scala/Tuple2
	dup
	ldc_w	String ugrave
	ldc	int 249
	istore	95
	iload	95
	invokestatic	Method scala/runtime/BoxesRunTime.boxToInteger:(I)Ljava/lang/Integer;
	invokespecial	Method scala/Tuple2."<init>":(Ljava/lang/Object;Ljava/lang/Object;)V
	aastore
	dup
	ldc_w	int 95
	new	class scala/Tuple2
	dup
	ldc_w	String uacute
	ldc_w	int 250
	istore	96
	iload	96
	invokestatic	Method scala/runtime/BoxesRunTime.boxToInteger:(I)Ljava/lang/Integer;
	invokespecial	Method scala/Tuple2."<init>":(Ljava/lang/Object;Ljava/lang/Object;)V
	aastore
	dup
	ldc_w	int 96
	new	class scala/Tuple2
	dup
	ldc_w	String ucirc
	ldc_w	int 251
	istore	97
	iload	97
	invokestatic	Method scala/runtime/BoxesRunTime.boxToInteger:(I)Ljava/lang/Integer;
	invokespecial	Method scala/Tuple2."<init>":(Ljava/lang/Object;Ljava/lang/Object;)V
	aastore
	dup
	ldc_w	int 97
	new	class scala/Tuple2
	dup
	ldc_w	String uuml
	ldc_w	int 252
	istore	98
	iload	98
	invokestatic	Method scala/runtime/BoxesRunTime.boxToInteger:(I)Ljava/lang/Integer;
	invokespecial	Method scala/Tuple2."<init>":(Ljava/lang/Object;Ljava/lang/Object;)V
	aastore
	dup
	ldc_w	int 98
	new	class scala/Tuple2
	dup
	ldc_w	String yacute
	ldc_w	int 253
	istore	99
	iload	99
	invokestatic	Method scala/runtime/BoxesRunTime.boxToInteger:(I)Ljava/lang/Integer;
	invokespecial	Method scala/Tuple2."<init>":(Ljava/lang/Object;Ljava/lang/Object;)V
	aastore
	dup
	ldc_w	int 99
	new	class scala/Tuple2
	dup
	ldc_w	String thorn
	ldc_w	int 254
	istore	100
	iload	100
	invokestatic	Method scala/runtime/BoxesRunTime.boxToInteger:(I)Ljava/lang/Integer;
	invokespecial	Method scala/Tuple2."<init>":(Ljava/lang/Object;Ljava/lang/Object;)V
	aastore
	dup
	ldc_w	int 100
	new	class scala/Tuple2
	dup
	ldc_w	String yuml
	ldc_w	int 255
	istore	101
	iload	101
	invokestatic	Method scala/runtime/BoxesRunTime.boxToInteger:(I)Ljava/lang/Integer;
	invokespecial	Method scala/Tuple2."<init>":(Ljava/lang/Object;Ljava/lang/Object;)V
	aastore
	dup
	ldc_w	int 101
	new	class scala/Tuple2
	dup
	ldc_w	String OElig
	ldc_w	int 338
	istore	102
	iload	102
	invokestatic	Method scala/runtime/BoxesRunTime.boxToInteger:(I)Ljava/lang/Integer;
	invokespecial	Method scala/Tuple2."<init>":(Ljava/lang/Object;Ljava/lang/Object;)V
	aastore
	dup
	ldc_w	int 102
	new	class scala/Tuple2
	dup
	ldc_w	String oelig
	ldc_w	int 339
	istore	103
	iload	103
	invokestatic	Method scala/runtime/BoxesRunTime.boxToInteger:(I)Ljava/lang/Integer;
	invokespecial	Method scala/Tuple2."<init>":(Ljava/lang/Object;Ljava/lang/Object;)V
	aastore
	dup
	ldc_w	int 103
	new	class scala/Tuple2
	dup
	ldc_w	String Scaron
	ldc_w	int 352
	istore	104
	iload	104
	invokestatic	Method scala/runtime/BoxesRunTime.boxToInteger:(I)Ljava/lang/Integer;
	invokespecial	Method scala/Tuple2."<init>":(Ljava/lang/Object;Ljava/lang/Object;)V
	aastore
	dup
	ldc_w	int 104
	new	class scala/Tuple2
	dup
	ldc_w	String scaron
	ldc_w	int 353
	istore	105
	iload	105
	invokestatic	Method scala/runtime/BoxesRunTime.boxToInteger:(I)Ljava/lang/Integer;
	invokespecial	Method scala/Tuple2."<init>":(Ljava/lang/Object;Ljava/lang/Object;)V
	aastore
	dup
	ldc_w	int 105
	new	class scala/Tuple2
	dup
	ldc_w	String Yuml
	ldc_w	int 376
	istore	106
	iload	106
	invokestatic	Method scala/runtime/BoxesRunTime.boxToInteger:(I)Ljava/lang/Integer;
	invokespecial	Method scala/Tuple2."<init>":(Ljava/lang/Object;Ljava/lang/Object;)V
	aastore
	dup
	ldc_w	int 106
	new	class scala/Tuple2
	dup
	ldc_w	String circ
	ldc_w	int 710
	istore	107
	iload	107
	invokestatic	Method scala/runtime/BoxesRunTime.boxToInteger:(I)Ljava/lang/Integer;
	invokespecial	Method scala/Tuple2."<init>":(Ljava/lang/Object;Ljava/lang/Object;)V
	aastore
	dup
	ldc_w	int 107
	new	class scala/Tuple2
	dup
	ldc_w	String ensp
	ldc_w	int 8194
	istore	108
	iload	108
	invokestatic	Method scala/runtime/BoxesRunTime.boxToInteger:(I)Ljava/lang/Integer;
	invokespecial	Method scala/Tuple2."<init>":(Ljava/lang/Object;Ljava/lang/Object;)V
	aastore
	dup
	ldc_w	int 108
	new	class scala/Tuple2
	dup
	ldc_w	String emsp
	ldc_w	int 8195
	istore	109
	iload	109
	invokestatic	Method scala/runtime/BoxesRunTime.boxToInteger:(I)Ljava/lang/Integer;
	invokespecial	Method scala/Tuple2."<init>":(Ljava/lang/Object;Ljava/lang/Object;)V
	aastore
	dup
	ldc_w	int 109
	new	class scala/Tuple2
	dup
	ldc_w	String zwnj
	ldc_w	int 204
	istore	110
	iload	110
	invokestatic	Method scala/runtime/BoxesRunTime.boxToInteger:(I)Ljava/lang/Integer;
	invokespecial	Method scala/Tuple2."<init>":(Ljava/lang/Object;Ljava/lang/Object;)V
	aastore
	dup
	ldc_w	int 110
	new	class scala/Tuple2
	dup
	ldc_w	String zwj
	ldc_w	int 8205
	istore	111
	iload	111
	invokestatic	Method scala/runtime/BoxesRunTime.boxToInteger:(I)Ljava/lang/Integer;
	invokespecial	Method scala/Tuple2."<init>":(Ljava/lang/Object;Ljava/lang/Object;)V
	aastore
	dup
	ldc_w	int 111
	new	class scala/Tuple2
	dup
	ldc_w	String lrm
	ldc_w	int 8206
	istore	112
	iload	112
	invokestatic	Method scala/runtime/BoxesRunTime.boxToInteger:(I)Ljava/lang/Integer;
	invokespecial	Method scala/Tuple2."<init>":(Ljava/lang/Object;Ljava/lang/Object;)V
	aastore
	dup
	ldc_w	int 112
	new	class scala/Tuple2
	dup
	ldc_w	String rlm
	ldc_w	int 8207
	istore	113
	iload	113
	invokestatic	Method scala/runtime/BoxesRunTime.boxToInteger:(I)Ljava/lang/Integer;
	invokespecial	Method scala/Tuple2."<init>":(Ljava/lang/Object;Ljava/lang/Object;)V
	aastore
	dup
	ldc_w	int 113
	new	class scala/Tuple2
	dup
	ldc_w	String ndash
	ldc_w	int 8211
	istore	114
	iload	114
	invokestatic	Method scala/runtime/BoxesRunTime.boxToInteger:(I)Ljava/lang/Integer;
	invokespecial	Method scala/Tuple2."<init>":(Ljava/lang/Object;Ljava/lang/Object;)V
	aastore
	dup
	ldc_w	int 114
	new	class scala/Tuple2
	dup
	ldc_w	String mdash
	ldc_w	int 8212
	istore	115
	iload	115
	invokestatic	Method scala/runtime/BoxesRunTime.boxToInteger:(I)Ljava/lang/Integer;
	invokespecial	Method scala/Tuple2."<init>":(Ljava/lang/Object;Ljava/lang/Object;)V
	aastore
	dup
	ldc_w	int 115
	new	class scala/Tuple2
	dup
	ldc_w	String lsquo
	ldc_w	int 8216
	istore	116
	iload	116
	invokestatic	Method scala/runtime/BoxesRunTime.boxToInteger:(I)Ljava/lang/Integer;
	invokespecial	Method scala/Tuple2."<init>":(Ljava/lang/Object;Ljava/lang/Object;)V
	aastore
	dup
	ldc_w	int 116
	new	class scala/Tuple2
	dup
	ldc_w	String rsquo
	ldc_w	int 8217
	istore	117
	iload	117
	invokestatic	Method scala/runtime/BoxesRunTime.boxToInteger:(I)Ljava/lang/Integer;
	invokespecial	Method scala/Tuple2."<init>":(Ljava/lang/Object;Ljava/lang/Object;)V
	aastore
	dup
	ldc_w	int 117
	new	class scala/Tuple2
	dup
	ldc_w	String sbquo
	ldc_w	int 8218
	istore	118
	iload	118
	invokestatic	Method scala/runtime/BoxesRunTime.boxToInteger:(I)Ljava/lang/Integer;
	invokespecial	Method scala/Tuple2."<init>":(Ljava/lang/Object;Ljava/lang/Object;)V
	aastore
	dup
	ldc_w	int 118
	new	class scala/Tuple2
	dup
	ldc_w	String ldquo
	ldc_w	int 8220
	istore	119
	iload	119
	invokestatic	Method scala/runtime/BoxesRunTime.boxToInteger:(I)Ljava/lang/Integer;
	invokespecial	Method scala/Tuple2."<init>":(Ljava/lang/Object;Ljava/lang/Object;)V
	aastore
	dup
	ldc_w	int 119
	new	class scala/Tuple2
	dup
	ldc_w	String rdquo
	ldc_w	int 8221
	istore	120
	iload	120
	invokestatic	Method scala/runtime/BoxesRunTime.boxToInteger:(I)Ljava/lang/Integer;
	invokespecial	Method scala/Tuple2."<init>":(Ljava/lang/Object;Ljava/lang/Object;)V
	aastore
	dup
	ldc_w	int 120
	new	class scala/Tuple2
	dup
	ldc_w	String bdquo
	ldc_w	int 8222
	istore	121
	iload	121
	invokestatic	Method scala/runtime/BoxesRunTime.boxToInteger:(I)Ljava/lang/Integer;
	invokespecial	Method scala/Tuple2."<init>":(Ljava/lang/Object;Ljava/lang/Object;)V
	aastore
	dup
	ldc_w	int 121
	new	class scala/Tuple2
	dup
	ldc_w	String dagger
	ldc_w	int 8224
	istore	122
	iload	122
	invokestatic	Method scala/runtime/BoxesRunTime.boxToInteger:(I)Ljava/lang/Integer;
	invokespecial	Method scala/Tuple2."<init>":(Ljava/lang/Object;Ljava/lang/Object;)V
	aastore
	dup
	ldc_w	int 122
	new	class scala/Tuple2
	dup
	ldc_w	String Dagger
	ldc_w	int 8225
	istore	123
	iload	123
	invokestatic	Method scala/runtime/BoxesRunTime.boxToInteger:(I)Ljava/lang/Integer;
	invokespecial	Method scala/Tuple2."<init>":(Ljava/lang/Object;Ljava/lang/Object;)V
	aastore
	dup
	ldc_w	int 123
	new	class scala/Tuple2
	dup
	ldc_w	String permil
	ldc_w	int 8240
	istore	124
	iload	124
	invokestatic	Method scala/runtime/BoxesRunTime.boxToInteger:(I)Ljava/lang/Integer;
	invokespecial	Method scala/Tuple2."<init>":(Ljava/lang/Object;Ljava/lang/Object;)V
	aastore
	dup
	ldc_w	int 124
	new	class scala/Tuple2
	dup
	ldc_w	String lsaquo
	ldc_w	int 8249
	istore	125
	iload	125
	invokestatic	Method scala/runtime/BoxesRunTime.boxToInteger:(I)Ljava/lang/Integer;
	invokespecial	Method scala/Tuple2."<init>":(Ljava/lang/Object;Ljava/lang/Object;)V
	aastore
	dup
	ldc_w	int 125
	new	class scala/Tuple2
	dup
	ldc_w	String rsaquo
	ldc_w	int 8250
	istore	126
	iload	126
	invokestatic	Method scala/runtime/BoxesRunTime.boxToInteger:(I)Ljava/lang/Integer;
	invokespecial	Method scala/Tuple2."<init>":(Ljava/lang/Object;Ljava/lang/Object;)V
	aastore
	dup
	ldc_w	int 126
	new	class scala/Tuple2
	dup
	ldc_w	String fnof
	ldc_w	int 402
	istore	127
	iload	127
	invokestatic	Method scala/runtime/BoxesRunTime.boxToInteger:(I)Ljava/lang/Integer;
	invokespecial	Method scala/Tuple2."<init>":(Ljava/lang/Object;Ljava/lang/Object;)V
	aastore
	dup
	ldc_w	int 127
	new	class scala/Tuple2
	dup
	ldc_w	String bull
	ldc_w	int 8226
	istore	128
	iload	128
	invokestatic	Method scala/runtime/BoxesRunTime.boxToInteger:(I)Ljava/lang/Integer;
	invokespecial	Method scala/Tuple2."<init>":(Ljava/lang/Object;Ljava/lang/Object;)V
	aastore
	dup
	ldc_w	int 128
	new	class scala/Tuple2
	dup
	ldc_w	String hellip
	ldc_w	int 8230
	istore	129
	iload	129
	invokestatic	Method scala/runtime/BoxesRunTime.boxToInteger:(I)Ljava/lang/Integer;
	invokespecial	Method scala/Tuple2."<init>":(Ljava/lang/Object;Ljava/lang/Object;)V
	aastore
	dup
	ldc_w	int 129
	new	class scala/Tuple2
	dup
	ldc_w	String prime
	ldc_w	int 8242
	istore	130
	iload	130
	invokestatic	Method scala/runtime/BoxesRunTime.boxToInteger:(I)Ljava/lang/Integer;
	invokespecial	Method scala/Tuple2."<init>":(Ljava/lang/Object;Ljava/lang/Object;)V
	aastore
	dup
	ldc_w	int 130
	new	class scala/Tuple2
	dup
	ldc_w	String Prime
	ldc_w	int 8243
	istore	131
	iload	131
	invokestatic	Method scala/runtime/BoxesRunTime.boxToInteger:(I)Ljava/lang/Integer;
	invokespecial	Method scala/Tuple2."<init>":(Ljava/lang/Object;Ljava/lang/Object;)V
	aastore
	dup
	ldc_w	int 131
	new	class scala/Tuple2
	dup
	ldc_w	String oline
	ldc_w	int 8254
	istore	132
	iload	132
	invokestatic	Method scala/runtime/BoxesRunTime.boxToInteger:(I)Ljava/lang/Integer;
	invokespecial	Method scala/Tuple2."<init>":(Ljava/lang/Object;Ljava/lang/Object;)V
	aastore
	dup
	ldc_w	int 132
	new	class scala/Tuple2
	dup
	ldc_w	String frasl
	ldc_w	int 8260
	istore	133
	iload	133
	invokestatic	Method scala/runtime/BoxesRunTime.boxToInteger:(I)Ljava/lang/Integer;
	invokespecial	Method scala/Tuple2."<init>":(Ljava/lang/Object;Ljava/lang/Object;)V
	aastore
	dup
	ldc_w	int 133
	new	class scala/Tuple2
	dup
	ldc_w	String weierp
	ldc_w	int 8472
	istore	134
	iload	134
	invokestatic	Method scala/runtime/BoxesRunTime.boxToInteger:(I)Ljava/lang/Integer;
	invokespecial	Method scala/Tuple2."<init>":(Ljava/lang/Object;Ljava/lang/Object;)V
	aastore
	dup
	ldc_w	int 134
	new	class scala/Tuple2
	dup
	ldc_w	String image
	ldc_w	int 8465
	istore	135
	iload	135
	invokestatic	Method scala/runtime/BoxesRunTime.boxToInteger:(I)Ljava/lang/Integer;
	invokespecial	Method scala/Tuple2."<init>":(Ljava/lang/Object;Ljava/lang/Object;)V
	aastore
	dup
	ldc_w	int 135
	new	class scala/Tuple2
	dup
	ldc_w	String real
	ldc_w	int 8476
	istore	136
	iload	136
	invokestatic	Method scala/runtime/BoxesRunTime.boxToInteger:(I)Ljava/lang/Integer;
	invokespecial	Method scala/Tuple2."<init>":(Ljava/lang/Object;Ljava/lang/Object;)V
	aastore
	dup
	ldc_w	int 136
	new	class scala/Tuple2
	dup
	ldc_w	String alefsym
	ldc_w	int 8501
	istore	137
	iload	137
	invokestatic	Method scala/runtime/BoxesRunTime.boxToInteger:(I)Ljava/lang/Integer;
	invokespecial	Method scala/Tuple2."<init>":(Ljava/lang/Object;Ljava/lang/Object;)V
	aastore
	dup
	ldc_w	int 137
	new	class scala/Tuple2
	dup
	ldc_w	String larr
	ldc_w	int 8592
	istore	138
	iload	138
	invokestatic	Method scala/runtime/BoxesRunTime.boxToInteger:(I)Ljava/lang/Integer;
	invokespecial	Method scala/Tuple2."<init>":(Ljava/lang/Object;Ljava/lang/Object;)V
	aastore
	dup
	ldc_w	int 138
	new	class scala/Tuple2
	dup
	ldc_w	String uarr
	ldc_w	int 8593
	istore	139
	iload	139
	invokestatic	Method scala/runtime/BoxesRunTime.boxToInteger:(I)Ljava/lang/Integer;
	invokespecial	Method scala/Tuple2."<init>":(Ljava/lang/Object;Ljava/lang/Object;)V
	aastore
	dup
	ldc_w	int 139
	new	class scala/Tuple2
	dup
	ldc_w	String rarr
	ldc_w	int 8594
	istore	140
	iload	140
	invokestatic	Method scala/runtime/BoxesRunTime.boxToInteger:(I)Ljava/lang/Integer;
	invokespecial	Method scala/Tuple2."<init>":(Ljava/lang/Object;Ljava/lang/Object;)V
	aastore
	dup
	ldc_w	int 140
	new	class scala/Tuple2
	dup
	ldc_w	String darr
	ldc_w	int 8495
	istore	141
	iload	141
	invokestatic	Method scala/runtime/BoxesRunTime.boxToInteger:(I)Ljava/lang/Integer;
	invokespecial	Method scala/Tuple2."<init>":(Ljava/lang/Object;Ljava/lang/Object;)V
	aastore
	dup
	ldc_w	int 141
	new	class scala/Tuple2
	dup
	ldc_w	String harr
	ldc_w	int 8596
	istore	142
	iload	142
	invokestatic	Method scala/runtime/BoxesRunTime.boxToInteger:(I)Ljava/lang/Integer;
	invokespecial	Method scala/Tuple2."<init>":(Ljava/lang/Object;Ljava/lang/Object;)V
	aastore
	dup
	ldc_w	int 142
	new	class scala/Tuple2
	dup
	ldc_w	String crarr
	ldc_w	int 8629
	istore	143
	iload	143
	invokestatic	Method scala/runtime/BoxesRunTime.boxToInteger:(I)Ljava/lang/Integer;
	invokespecial	Method scala/Tuple2."<init>":(Ljava/lang/Object;Ljava/lang/Object;)V
	aastore
	dup
	ldc_w	int 143
	new	class scala/Tuple2
	dup
	ldc_w	String lArr
	ldc_w	int 8656
	istore	144
	iload	144
	invokestatic	Method scala/runtime/BoxesRunTime.boxToInteger:(I)Ljava/lang/Integer;
	invokespecial	Method scala/Tuple2."<init>":(Ljava/lang/Object;Ljava/lang/Object;)V
	aastore
	dup
	ldc_w	int 144
	new	class scala/Tuple2
	dup
	ldc_w	String uArr
	ldc_w	int 8657
	istore	145
	iload	145
	invokestatic	Method scala/runtime/BoxesRunTime.boxToInteger:(I)Ljava/lang/Integer;
	invokespecial	Method scala/Tuple2."<init>":(Ljava/lang/Object;Ljava/lang/Object;)V
	aastore
	dup
	ldc_w	int 145
	new	class scala/Tuple2
	dup
	ldc_w	String rArr
	ldc_w	int 8658
	istore	146
	iload	146
	invokestatic	Method scala/runtime/BoxesRunTime.boxToInteger:(I)Ljava/lang/Integer;
	invokespecial	Method scala/Tuple2."<init>":(Ljava/lang/Object;Ljava/lang/Object;)V
	aastore
	dup
	ldc_w	int 146
	new	class scala/Tuple2
	dup
	ldc_w	String dArr
	ldc_w	int 8659
	istore	147
	iload	147
	invokestatic	Method scala/runtime/BoxesRunTime.boxToInteger:(I)Ljava/lang/Integer;
	invokespecial	Method scala/Tuple2."<init>":(Ljava/lang/Object;Ljava/lang/Object;)V
	aastore
	dup
	ldc_w	int 147
	new	class scala/Tuple2
	dup
	ldc_w	String hArr
	ldc_w	int 8660
	istore	148
	iload	148
	invokestatic	Method scala/runtime/BoxesRunTime.boxToInteger:(I)Ljava/lang/Integer;
	invokespecial	Method scala/Tuple2."<init>":(Ljava/lang/Object;Ljava/lang/Object;)V
	aastore
	dup
	ldc_w	int 148
	new	class scala/Tuple2
	dup
	ldc_w	String forall
	ldc_w	int 8704
	istore	149
	iload	149
	invokestatic	Method scala/runtime/BoxesRunTime.boxToInteger:(I)Ljava/lang/Integer;
	invokespecial	Method scala/Tuple2."<init>":(Ljava/lang/Object;Ljava/lang/Object;)V
	aastore
	dup
	ldc_w	int 149
	new	class scala/Tuple2
	dup
	ldc_w	String part
	ldc_w	int 8706
	istore	150
	iload	150
	invokestatic	Method scala/runtime/BoxesRunTime.boxToInteger:(I)Ljava/lang/Integer;
	invokespecial	Method scala/Tuple2."<init>":(Ljava/lang/Object;Ljava/lang/Object;)V
	aastore
	dup
	ldc_w	int 150
	new	class scala/Tuple2
	dup
	ldc_w	String exist
	ldc_w	int 8707
	istore	151
	iload	151
	invokestatic	Method scala/runtime/BoxesRunTime.boxToInteger:(I)Ljava/lang/Integer;
	invokespecial	Method scala/Tuple2."<init>":(Ljava/lang/Object;Ljava/lang/Object;)V
	aastore
	dup
	ldc_w	int 151
	new	class scala/Tuple2
	dup
	ldc_w	String empty
	ldc_w	int 8709
	istore	152
	iload	152
	invokestatic	Method scala/runtime/BoxesRunTime.boxToInteger:(I)Ljava/lang/Integer;
	invokespecial	Method scala/Tuple2."<init>":(Ljava/lang/Object;Ljava/lang/Object;)V
	aastore
	dup
	ldc_w	int 152
	new	class scala/Tuple2
	dup
	ldc_w	String nabla
	ldc_w	int 8711
	istore	153
	iload	153
	invokestatic	Method scala/runtime/BoxesRunTime.boxToInteger:(I)Ljava/lang/Integer;
	invokespecial	Method scala/Tuple2."<init>":(Ljava/lang/Object;Ljava/lang/Object;)V
	aastore
	dup
	ldc_w	int 153
	new	class scala/Tuple2
	dup
	ldc_w	String isin
	ldc_w	int 8712
	istore	154
	iload	154
	invokestatic	Method scala/runtime/BoxesRunTime.boxToInteger:(I)Ljava/lang/Integer;
	invokespecial	Method scala/Tuple2."<init>":(Ljava/lang/Object;Ljava/lang/Object;)V
	aastore
	dup
	ldc_w	int 154
	new	class scala/Tuple2
	dup
	ldc_w	String notin
	ldc_w	int 8713
	istore	155
	iload	155
	invokestatic	Method scala/runtime/BoxesRunTime.boxToInteger:(I)Ljava/lang/Integer;
	invokespecial	Method scala/Tuple2."<init>":(Ljava/lang/Object;Ljava/lang/Object;)V
	aastore
	dup
	ldc_w	int 155
	new	class scala/Tuple2
	dup
	ldc_w	String ni
	ldc_w	int 8715
	istore	156
	iload	156
	invokestatic	Method scala/runtime/BoxesRunTime.boxToInteger:(I)Ljava/lang/Integer;
	invokespecial	Method scala/Tuple2."<init>":(Ljava/lang/Object;Ljava/lang/Object;)V
	aastore
	dup
	ldc_w	int 156
	new	class scala/Tuple2
	dup
	ldc_w	String prod
	ldc_w	int 8719
	istore	157
	iload	157
	invokestatic	Method scala/runtime/BoxesRunTime.boxToInteger:(I)Ljava/lang/Integer;
	invokespecial	Method scala/Tuple2."<init>":(Ljava/lang/Object;Ljava/lang/Object;)V
	aastore
	dup
	ldc_w	int 157
	new	class scala/Tuple2
	dup
	ldc_w	String sum
	ldc_w	int 8721
	istore	158
	iload	158
	invokestatic	Method scala/runtime/BoxesRunTime.boxToInteger:(I)Ljava/lang/Integer;
	invokespecial	Method scala/Tuple2."<init>":(Ljava/lang/Object;Ljava/lang/Object;)V
	aastore
	dup
	ldc_w	int 158
	new	class scala/Tuple2
	dup
	ldc_w	String minus
	ldc_w	int 8722
	istore	159
	iload	159
	invokestatic	Method scala/runtime/BoxesRunTime.boxToInteger:(I)Ljava/lang/Integer;
	invokespecial	Method scala/Tuple2."<init>":(Ljava/lang/Object;Ljava/lang/Object;)V
	aastore
	dup
	ldc_w	int 159
	new	class scala/Tuple2
	dup
	ldc_w	String lowast
	ldc_w	int 8727
	istore	160
	iload	160
	invokestatic	Method scala/runtime/BoxesRunTime.boxToInteger:(I)Ljava/lang/Integer;
	invokespecial	Method scala/Tuple2."<init>":(Ljava/lang/Object;Ljava/lang/Object;)V
	aastore
	dup
	ldc	int 160
	new	class scala/Tuple2
	dup
	ldc_w	String radic
	ldc_w	int 8730
	istore	161
	iload	161
	invokestatic	Method scala/runtime/BoxesRunTime.boxToInteger:(I)Ljava/lang/Integer;
	invokespecial	Method scala/Tuple2."<init>":(Ljava/lang/Object;Ljava/lang/Object;)V
	aastore
	dup
	ldc	int 161
	new	class scala/Tuple2
	dup
	ldc_w	String prop
	ldc_w	int 8733
	istore	162
	iload	162
	invokestatic	Method scala/runtime/BoxesRunTime.boxToInteger:(I)Ljava/lang/Integer;
	invokespecial	Method scala/Tuple2."<init>":(Ljava/lang/Object;Ljava/lang/Object;)V
	aastore
	dup
	ldc	int 162
	new	class scala/Tuple2
	dup
	ldc_w	String infin
	ldc_w	int 8734
	istore	163
	iload	163
	invokestatic	Method scala/runtime/BoxesRunTime.boxToInteger:(I)Ljava/lang/Integer;
	invokespecial	Method scala/Tuple2."<init>":(Ljava/lang/Object;Ljava/lang/Object;)V
	aastore
	dup
	ldc	int 163
	new	class scala/Tuple2
	dup
	ldc_w	String ang
	ldc_w	int 8736
	istore	164
	iload	164
	invokestatic	Method scala/runtime/BoxesRunTime.boxToInteger:(I)Ljava/lang/Integer;
	invokespecial	Method scala/Tuple2."<init>":(Ljava/lang/Object;Ljava/lang/Object;)V
	aastore
	dup
	ldc	int 164
	new	class scala/Tuple2
	dup
	ldc_w	String and
	ldc_w	int 8743
	istore	165
	iload	165
	invokestatic	Method scala/runtime/BoxesRunTime.boxToInteger:(I)Ljava/lang/Integer;
	invokespecial	Method scala/Tuple2."<init>":(Ljava/lang/Object;Ljava/lang/Object;)V
	aastore
	dup
	ldc	int 165
	new	class scala/Tuple2
	dup
	ldc_w	String or
	ldc_w	int 8744
	istore	166
	iload	166
	invokestatic	Method scala/runtime/BoxesRunTime.boxToInteger:(I)Ljava/lang/Integer;
	invokespecial	Method scala/Tuple2."<init>":(Ljava/lang/Object;Ljava/lang/Object;)V
	aastore
	dup
	ldc	int 166
	new	class scala/Tuple2
	dup
	ldc_w	String cap
	ldc_w	int 8745
	istore	167
	iload	167
	invokestatic	Method scala/runtime/BoxesRunTime.boxToInteger:(I)Ljava/lang/Integer;
	invokespecial	Method scala/Tuple2."<init>":(Ljava/lang/Object;Ljava/lang/Object;)V
	aastore
	dup
	ldc	int 167
	new	class scala/Tuple2
	dup
	ldc_w	String cup
	ldc_w	int 8746
	istore	168
	iload	168
	invokestatic	Method scala/runtime/BoxesRunTime.boxToInteger:(I)Ljava/lang/Integer;
	invokespecial	Method scala/Tuple2."<init>":(Ljava/lang/Object;Ljava/lang/Object;)V
	aastore
	dup
	ldc	int 168
	new	class scala/Tuple2
	dup
	ldc_w	String int
	ldc_w	int 8747
	istore	169
	iload	169
	invokestatic	Method scala/runtime/BoxesRunTime.boxToInteger:(I)Ljava/lang/Integer;
	invokespecial	Method scala/Tuple2."<init>":(Ljava/lang/Object;Ljava/lang/Object;)V
	aastore
	dup
	ldc	int 169
	new	class scala/Tuple2
	dup
	ldc_w	String there4
	ldc_w	int 8756
	istore	170
	iload	170
	invokestatic	Method scala/runtime/BoxesRunTime.boxToInteger:(I)Ljava/lang/Integer;
	invokespecial	Method scala/Tuple2."<init>":(Ljava/lang/Object;Ljava/lang/Object;)V
	aastore
	dup
	ldc	int 170
	new	class scala/Tuple2
	dup
	ldc_w	String sim
	ldc_w	int 8764
	istore	171
	iload	171
	invokestatic	Method scala/runtime/BoxesRunTime.boxToInteger:(I)Ljava/lang/Integer;
	invokespecial	Method scala/Tuple2."<init>":(Ljava/lang/Object;Ljava/lang/Object;)V
	aastore
	dup
	ldc	int 171
	new	class scala/Tuple2
	dup
	ldc_w	String cong
	ldc_w	int 8773
	istore	172
	iload	172
	invokestatic	Method scala/runtime/BoxesRunTime.boxToInteger:(I)Ljava/lang/Integer;
	invokespecial	Method scala/Tuple2."<init>":(Ljava/lang/Object;Ljava/lang/Object;)V
	aastore
	dup
	ldc_w	int 172
	new	class scala/Tuple2
	dup
	ldc_w	String asymp
	ldc_w	int 8776
	istore	173
	iload	173
	invokestatic	Method scala/runtime/BoxesRunTime.boxToInteger:(I)Ljava/lang/Integer;
	invokespecial	Method scala/Tuple2."<init>":(Ljava/lang/Object;Ljava/lang/Object;)V
	aastore
	dup
	ldc	int 173
	new	class scala/Tuple2
	dup
	ldc_w	String ne
	ldc_w	int 8800
	istore	174
	iload	174
	invokestatic	Method scala/runtime/BoxesRunTime.boxToInteger:(I)Ljava/lang/Integer;
	invokespecial	Method scala/Tuple2."<init>":(Ljava/lang/Object;Ljava/lang/Object;)V
	aastore
	dup
	ldc	int 174
	new	class scala/Tuple2
	dup
	ldc_w	String equiv
	ldc_w	int 8801
	istore	175
	iload	175
	invokestatic	Method scala/runtime/BoxesRunTime.boxToInteger:(I)Ljava/lang/Integer;
	invokespecial	Method scala/Tuple2."<init>":(Ljava/lang/Object;Ljava/lang/Object;)V
	aastore
	dup
	ldc	int 175
	new	class scala/Tuple2
	dup
	ldc_w	String le
	ldc_w	int 8804
	istore	176
	iload	176
	invokestatic	Method scala/runtime/BoxesRunTime.boxToInteger:(I)Ljava/lang/Integer;
	invokespecial	Method scala/Tuple2."<init>":(Ljava/lang/Object;Ljava/lang/Object;)V
	aastore
	dup
	ldc	int 176
	new	class scala/Tuple2
	dup
	ldc_w	String ge
	ldc_w	int 8805
	istore	177
	iload	177
	invokestatic	Method scala/runtime/BoxesRunTime.boxToInteger:(I)Ljava/lang/Integer;
	invokespecial	Method scala/Tuple2."<init>":(Ljava/lang/Object;Ljava/lang/Object;)V
	aastore
	dup
	ldc	int 177
	new	class scala/Tuple2
	dup
	ldc_w	String sub
	ldc_w	int 8834
	istore	178
	iload	178
	invokestatic	Method scala/runtime/BoxesRunTime.boxToInteger:(I)Ljava/lang/Integer;
	invokespecial	Method scala/Tuple2."<init>":(Ljava/lang/Object;Ljava/lang/Object;)V
	aastore
	dup
	ldc	int 178
	new	class scala/Tuple2
	dup
	ldc_w	String sup
	ldc_w	int 8835
	istore	179
	iload	179
	invokestatic	Method scala/runtime/BoxesRunTime.boxToInteger:(I)Ljava/lang/Integer;
	invokespecial	Method scala/Tuple2."<init>":(Ljava/lang/Object;Ljava/lang/Object;)V
	aastore
	dup
	ldc	int 179
	new	class scala/Tuple2
	dup
	ldc_w	String nsub
	ldc_w	int 8836
	istore	180
	iload	180
	invokestatic	Method scala/runtime/BoxesRunTime.boxToInteger:(I)Ljava/lang/Integer;
	invokespecial	Method scala/Tuple2."<init>":(Ljava/lang/Object;Ljava/lang/Object;)V
	aastore
	dup
	ldc	int 180
	new	class scala/Tuple2
	dup
	ldc_w	String sube
	ldc_w	int 8838
	istore	181
	iload	181
	invokestatic	Method scala/runtime/BoxesRunTime.boxToInteger:(I)Ljava/lang/Integer;
	invokespecial	Method scala/Tuple2."<init>":(Ljava/lang/Object;Ljava/lang/Object;)V
	aastore
	dup
	ldc	int 181
	new	class scala/Tuple2
	dup
	ldc_w	String supe
	ldc_w	int 8839
	istore	182
	iload	182
	invokestatic	Method scala/runtime/BoxesRunTime.boxToInteger:(I)Ljava/lang/Integer;
	invokespecial	Method scala/Tuple2."<init>":(Ljava/lang/Object;Ljava/lang/Object;)V
	aastore
	dup
	ldc	int 182
	new	class scala/Tuple2
	dup
	ldc_w	String oplus
	ldc_w	int 8853
	istore	183
	iload	183
	invokestatic	Method scala/runtime/BoxesRunTime.boxToInteger:(I)Ljava/lang/Integer;
	invokespecial	Method scala/Tuple2."<init>":(Ljava/lang/Object;Ljava/lang/Object;)V
	aastore
	dup
	ldc	int 183
	new	class scala/Tuple2
	dup
	ldc_w	String otimes
	ldc_w	int 8855
	istore	184
	iload	184
	invokestatic	Method scala/runtime/BoxesRunTime.boxToInteger:(I)Ljava/lang/Integer;
	invokespecial	Method scala/Tuple2."<init>":(Ljava/lang/Object;Ljava/lang/Object;)V
	aastore
	dup
	ldc	int 184
	new	class scala/Tuple2
	dup
	ldc_w	String perp
	ldc_w	int 8869
	istore	185
	iload	185
	invokestatic	Method scala/runtime/BoxesRunTime.boxToInteger:(I)Ljava/lang/Integer;
	invokespecial	Method scala/Tuple2."<init>":(Ljava/lang/Object;Ljava/lang/Object;)V
	aastore
	dup
	ldc	int 185
	new	class scala/Tuple2
	dup
	ldc_w	String sdot
	ldc_w	int 8901
	istore	186
	iload	186
	invokestatic	Method scala/runtime/BoxesRunTime.boxToInteger:(I)Ljava/lang/Integer;
	invokespecial	Method scala/Tuple2."<init>":(Ljava/lang/Object;Ljava/lang/Object;)V
	aastore
	dup
	ldc	int 186
	new	class scala/Tuple2
	dup
	ldc_w	String lceil
	ldc_w	int 8968
	istore	187
	iload	187
	invokestatic	Method scala/runtime/BoxesRunTime.boxToInteger:(I)Ljava/lang/Integer;
	invokespecial	Method scala/Tuple2."<init>":(Ljava/lang/Object;Ljava/lang/Object;)V
	aastore
	dup
	ldc	int 187
	new	class scala/Tuple2
	dup
	ldc_w	String rceil
	ldc_w	int 8969
	istore	188
	iload	188
	invokestatic	Method scala/runtime/BoxesRunTime.boxToInteger:(I)Ljava/lang/Integer;
	invokespecial	Method scala/Tuple2."<init>":(Ljava/lang/Object;Ljava/lang/Object;)V
	aastore
	dup
	ldc	int 188
	new	class scala/Tuple2
	dup
	ldc_w	String lfloor
	ldc_w	int 8970
	istore	189
	iload	189
	invokestatic	Method scala/runtime/BoxesRunTime.boxToInteger:(I)Ljava/lang/Integer;
	invokespecial	Method scala/Tuple2."<init>":(Ljava/lang/Object;Ljava/lang/Object;)V
	aastore
	dup
	ldc	int 189
	new	class scala/Tuple2
	dup
	ldc_w	String rfloor
	ldc_w	int 8971
	istore	190
	iload	190
	invokestatic	Method scala/runtime/BoxesRunTime.boxToInteger:(I)Ljava/lang/Integer;
	invokespecial	Method scala/Tuple2."<init>":(Ljava/lang/Object;Ljava/lang/Object;)V
	aastore
	dup
	ldc	int 190
	new	class scala/Tuple2
	dup
	ldc_w	String lang
	ldc_w	int 9001
	istore	191
	iload	191
	invokestatic	Method scala/runtime/BoxesRunTime.boxToInteger:(I)Ljava/lang/Integer;
	invokespecial	Method scala/Tuple2."<init>":(Ljava/lang/Object;Ljava/lang/Object;)V
	aastore
	dup
	ldc	int 191
	new	class scala/Tuple2
	dup
	ldc_w	String rang
	ldc_w	int 9002
	istore	192
	iload	192
	invokestatic	Method scala/runtime/BoxesRunTime.boxToInteger:(I)Ljava/lang/Integer;
	invokespecial	Method scala/Tuple2."<init>":(Ljava/lang/Object;Ljava/lang/Object;)V
	aastore
	dup
	ldc	int 192
	new	class scala/Tuple2
	dup
	ldc_w	String loz
	ldc_w	int 9674
	istore	193
	iload	193
	invokestatic	Method scala/runtime/BoxesRunTime.boxToInteger:(I)Ljava/lang/Integer;
	invokespecial	Method scala/Tuple2."<init>":(Ljava/lang/Object;Ljava/lang/Object;)V
	aastore
	dup
	ldc	int 193
	new	class scala/Tuple2
	dup
	ldc_w	String spades
	ldc_w	int 9824
	istore	194
	iload	194
	invokestatic	Method scala/runtime/BoxesRunTime.boxToInteger:(I)Ljava/lang/Integer;
	invokespecial	Method scala/Tuple2."<init>":(Ljava/lang/Object;Ljava/lang/Object;)V
	aastore
	dup
	ldc	int 194
	new	class scala/Tuple2
	dup
	ldc_w	String clubs
	ldc_w	int 9827
	istore	195
	iload	195
	invokestatic	Method scala/runtime/BoxesRunTime.boxToInteger:(I)Ljava/lang/Integer;
	invokespecial	Method scala/Tuple2."<init>":(Ljava/lang/Object;Ljava/lang/Object;)V
	aastore
	dup
	ldc	int 195
	new	class scala/Tuple2
	dup
	ldc_w	String hearts
	ldc_w	int 9829
	istore	196
	iload	196
	invokestatic	Method scala/runtime/BoxesRunTime.boxToInteger:(I)Ljava/lang/Integer;
	invokespecial	Method scala/Tuple2."<init>":(Ljava/lang/Object;Ljava/lang/Object;)V
	aastore
	dup
	ldc	int 196
	new	class scala/Tuple2
	dup
	ldc_w	String diams
	ldc_w	int 9830
	istore	197
	iload	197
	invokestatic	Method scala/runtime/BoxesRunTime.boxToInteger:(I)Ljava/lang/Integer;
	invokespecial	Method scala/Tuple2."<init>":(Ljava/lang/Object;Ljava/lang/Object;)V
	aastore
	dup
	ldc	int 197
	new	class scala/Tuple2
	dup
	ldc_w	String Alpha
	ldc_w	int 913
	istore	198
	iload	198
	invokestatic	Method scala/runtime/BoxesRunTime.boxToInteger:(I)Ljava/lang/Integer;
	invokespecial	Method scala/Tuple2."<init>":(Ljava/lang/Object;Ljava/lang/Object;)V
	aastore
	dup
	ldc	int 198
	new	class scala/Tuple2
	dup
	ldc_w	String Beta
	ldc_w	int 914
	istore	199
	iload	199
	invokestatic	Method scala/runtime/BoxesRunTime.boxToInteger:(I)Ljava/lang/Integer;
	invokespecial	Method scala/Tuple2."<init>":(Ljava/lang/Object;Ljava/lang/Object;)V
	aastore
	dup
	ldc	int 199
	new	class scala/Tuple2
	dup
	ldc_w	String Gamma
	ldc_w	int 915
	istore	200
	iload	200
	invokestatic	Method scala/runtime/BoxesRunTime.boxToInteger:(I)Ljava/lang/Integer;
	invokespecial	Method scala/Tuple2."<init>":(Ljava/lang/Object;Ljava/lang/Object;)V
	aastore
	dup
	ldc	int 200
	new	class scala/Tuple2
	dup
	ldc_w	String Delta
	ldc_w	int 916
	istore	201
	iload	201
	invokestatic	Method scala/runtime/BoxesRunTime.boxToInteger:(I)Ljava/lang/Integer;
	invokespecial	Method scala/Tuple2."<init>":(Ljava/lang/Object;Ljava/lang/Object;)V
	aastore
	dup
	ldc	int 201
	new	class scala/Tuple2
	dup
	ldc_w	String Epsilon
	ldc_w	int 917
	istore	202
	iload	202
	invokestatic	Method scala/runtime/BoxesRunTime.boxToInteger:(I)Ljava/lang/Integer;
	invokespecial	Method scala/Tuple2."<init>":(Ljava/lang/Object;Ljava/lang/Object;)V
	aastore
	dup
	ldc_w	int 202
	new	class scala/Tuple2
	dup
	ldc_w	String Zeta
	ldc_w	int 918
	istore	203
	iload	203
	invokestatic	Method scala/runtime/BoxesRunTime.boxToInteger:(I)Ljava/lang/Integer;
	invokespecial	Method scala/Tuple2."<init>":(Ljava/lang/Object;Ljava/lang/Object;)V
	aastore
	dup
	ldc_w	int 203
	new	class scala/Tuple2
	dup
	ldc_w	String Eta
	ldc_w	int 919
	istore	204
	iload	204
	invokestatic	Method scala/runtime/BoxesRunTime.boxToInteger:(I)Ljava/lang/Integer;
	invokespecial	Method scala/Tuple2."<init>":(Ljava/lang/Object;Ljava/lang/Object;)V
	aastore
	dup
	ldc_w	int 204
	new	class scala/Tuple2
	dup
	ldc_w	String Theta
	ldc_w	int 920
	istore	205
	iload	205
	invokestatic	Method scala/runtime/BoxesRunTime.boxToInteger:(I)Ljava/lang/Integer;
	invokespecial	Method scala/Tuple2."<init>":(Ljava/lang/Object;Ljava/lang/Object;)V
	aastore
	dup
	ldc_w	int 205
	new	class scala/Tuple2
	dup
	ldc_w	String Iota
	ldc_w	int 921
	istore	206
	iload	206
	invokestatic	Method scala/runtime/BoxesRunTime.boxToInteger:(I)Ljava/lang/Integer;
	invokespecial	Method scala/Tuple2."<init>":(Ljava/lang/Object;Ljava/lang/Object;)V
	aastore
	dup
	ldc_w	int 206
	new	class scala/Tuple2
	dup
	ldc_w	String Kappa
	ldc_w	int 922
	istore	207
	iload	207
	invokestatic	Method scala/runtime/BoxesRunTime.boxToInteger:(I)Ljava/lang/Integer;
	invokespecial	Method scala/Tuple2."<init>":(Ljava/lang/Object;Ljava/lang/Object;)V
	aastore
	dup
	ldc_w	int 207
	new	class scala/Tuple2
	dup
	ldc_w	String Lambda
	ldc_w	int 923
	istore	208
	iload	208
	invokestatic	Method scala/runtime/BoxesRunTime.boxToInteger:(I)Ljava/lang/Integer;
	invokespecial	Method scala/Tuple2."<init>":(Ljava/lang/Object;Ljava/lang/Object;)V
	aastore
	dup
	ldc_w	int 208
	new	class scala/Tuple2
	dup
	ldc_w	String Mu
	ldc_w	int 924
	istore	209
	iload	209
	invokestatic	Method scala/runtime/BoxesRunTime.boxToInteger:(I)Ljava/lang/Integer;
	invokespecial	Method scala/Tuple2."<init>":(Ljava/lang/Object;Ljava/lang/Object;)V
	aastore
	dup
	ldc_w	int 209
	new	class scala/Tuple2
	dup
	ldc_w	String Nu
	ldc_w	int 925
	istore	210
	iload	210
	invokestatic	Method scala/runtime/BoxesRunTime.boxToInteger:(I)Ljava/lang/Integer;
	invokespecial	Method scala/Tuple2."<init>":(Ljava/lang/Object;Ljava/lang/Object;)V
	aastore
	dup
	ldc_w	int 210
	new	class scala/Tuple2
	dup
	ldc_w	String Xi
	ldc_w	int 926
	istore	211
	iload	211
	invokestatic	Method scala/runtime/BoxesRunTime.boxToInteger:(I)Ljava/lang/Integer;
	invokespecial	Method scala/Tuple2."<init>":(Ljava/lang/Object;Ljava/lang/Object;)V
	aastore
	dup
	ldc_w	int 211
	new	class scala/Tuple2
	dup
	ldc_w	String Omicron
	ldc_w	int 927
	istore	212
	iload	212
	invokestatic	Method scala/runtime/BoxesRunTime.boxToInteger:(I)Ljava/lang/Integer;
	invokespecial	Method scala/Tuple2."<init>":(Ljava/lang/Object;Ljava/lang/Object;)V
	aastore
	dup
	ldc_w	int 212
	new	class scala/Tuple2
	dup
	ldc_w	String Pi
	ldc_w	int 928
	istore	213
	iload	213
	invokestatic	Method scala/runtime/BoxesRunTime.boxToInteger:(I)Ljava/lang/Integer;
	invokespecial	Method scala/Tuple2."<init>":(Ljava/lang/Object;Ljava/lang/Object;)V
	aastore
	dup
	ldc_w	int 213
	new	class scala/Tuple2
	dup
	ldc_w	String Rho
	ldc_w	int 929
	istore	214
	iload	214
	invokestatic	Method scala/runtime/BoxesRunTime.boxToInteger:(I)Ljava/lang/Integer;
	invokespecial	Method scala/Tuple2."<init>":(Ljava/lang/Object;Ljava/lang/Object;)V
	aastore
	dup
	ldc_w	int 214
	new	class scala/Tuple2
	dup
	ldc_w	String Sigma
	ldc_w	int 931
	istore	215
	iload	215
	invokestatic	Method scala/runtime/BoxesRunTime.boxToInteger:(I)Ljava/lang/Integer;
	invokespecial	Method scala/Tuple2."<init>":(Ljava/lang/Object;Ljava/lang/Object;)V
	aastore
	dup
	ldc	int 215
	new	class scala/Tuple2
	dup
	ldc_w	String Tau
	ldc_w	int 932
	istore	216
	iload	216
	invokestatic	Method scala/runtime/BoxesRunTime.boxToInteger:(I)Ljava/lang/Integer;
	invokespecial	Method scala/Tuple2."<init>":(Ljava/lang/Object;Ljava/lang/Object;)V
	aastore
	dup
	ldc_w	int 216
	new	class scala/Tuple2
	dup
	ldc_w	String Upsilon
	ldc_w	int 933
	istore	217
	iload	217
	invokestatic	Method scala/runtime/BoxesRunTime.boxToInteger:(I)Ljava/lang/Integer;
	invokespecial	Method scala/Tuple2."<init>":(Ljava/lang/Object;Ljava/lang/Object;)V
	aastore
	dup
	ldc_w	int 217
	new	class scala/Tuple2
	dup
	ldc_w	String Phi
	ldc_w	int 934
	istore	218
	iload	218
	invokestatic	Method scala/runtime/BoxesRunTime.boxToInteger:(I)Ljava/lang/Integer;
	invokespecial	Method scala/Tuple2."<init>":(Ljava/lang/Object;Ljava/lang/Object;)V
	aastore
	dup
	ldc_w	int 218
	new	class scala/Tuple2
	dup
	ldc_w	String Chi
	ldc_w	int 935
	istore	219
	iload	219
	invokestatic	Method scala/runtime/BoxesRunTime.boxToInteger:(I)Ljava/lang/Integer;
	invokespecial	Method scala/Tuple2."<init>":(Ljava/lang/Object;Ljava/lang/Object;)V
	aastore
	dup
	ldc_w	int 219
	new	class scala/Tuple2
	dup
	ldc_w	String Psi
	ldc_w	int 936
	istore	220
	iload	220
	invokestatic	Method scala/runtime/BoxesRunTime.boxToInteger:(I)Ljava/lang/Integer;
	invokespecial	Method scala/Tuple2."<init>":(Ljava/lang/Object;Ljava/lang/Object;)V
	aastore
	dup
	ldc_w	int 220
	new	class scala/Tuple2
	dup
	ldc_w	String Omega
	ldc_w	int 937
	istore	221
	iload	221
	invokestatic	Method scala/runtime/BoxesRunTime.boxToInteger:(I)Ljava/lang/Integer;
	invokespecial	Method scala/Tuple2."<init>":(Ljava/lang/Object;Ljava/lang/Object;)V
	aastore
	dup
	ldc_w	int 221
	new	class scala/Tuple2
	dup
	ldc_w	String alpha
	ldc_w	int 945
	istore	222
	iload	222
	invokestatic	Method scala/runtime/BoxesRunTime.boxToInteger:(I)Ljava/lang/Integer;
	invokespecial	Method scala/Tuple2."<init>":(Ljava/lang/Object;Ljava/lang/Object;)V
	aastore
	dup
	ldc_w	int 222
	new	class scala/Tuple2
	dup
	ldc_w	String beta
	ldc_w	int 946
	istore	223
	iload	223
	invokestatic	Method scala/runtime/BoxesRunTime.boxToInteger:(I)Ljava/lang/Integer;
	invokespecial	Method scala/Tuple2."<init>":(Ljava/lang/Object;Ljava/lang/Object;)V
	aastore
	dup
	ldc_w	int 223
	new	class scala/Tuple2
	dup
	ldc_w	String gamma
	ldc_w	int 947
	istore	224
	iload	224
	invokestatic	Method scala/runtime/BoxesRunTime.boxToInteger:(I)Ljava/lang/Integer;
	invokespecial	Method scala/Tuple2."<init>":(Ljava/lang/Object;Ljava/lang/Object;)V
	aastore
	dup
	ldc_w	int 224
	new	class scala/Tuple2
	dup
	ldc_w	String delta
	ldc_w	int 948
	istore	225
	iload	225
	invokestatic	Method scala/runtime/BoxesRunTime.boxToInteger:(I)Ljava/lang/Integer;
	invokespecial	Method scala/Tuple2."<init>":(Ljava/lang/Object;Ljava/lang/Object;)V
	aastore
	dup
	ldc_w	int 225
	new	class scala/Tuple2
	dup
	ldc_w	String epsilon
	ldc_w	int 949
	istore	226
	iload	226
	invokestatic	Method scala/runtime/BoxesRunTime.boxToInteger:(I)Ljava/lang/Integer;
	invokespecial	Method scala/Tuple2."<init>":(Ljava/lang/Object;Ljava/lang/Object;)V
	aastore
	dup
	ldc_w	int 226
	new	class scala/Tuple2
	dup
	ldc_w	String zeta
	ldc_w	int 950
	istore	227
	iload	227
	invokestatic	Method scala/runtime/BoxesRunTime.boxToInteger:(I)Ljava/lang/Integer;
	invokespecial	Method scala/Tuple2."<init>":(Ljava/lang/Object;Ljava/lang/Object;)V
	aastore
	dup
	ldc_w	int 227
	new	class scala/Tuple2
	dup
	ldc_w	String eta
	ldc_w	int 951
	istore	228
	iload	228
	invokestatic	Method scala/runtime/BoxesRunTime.boxToInteger:(I)Ljava/lang/Integer;
	invokespecial	Method scala/Tuple2."<init>":(Ljava/lang/Object;Ljava/lang/Object;)V
	aastore
	dup
	ldc_w	int 228
	new	class scala/Tuple2
	dup
	ldc_w	String theta
	ldc_w	int 952
	istore	229
	iload	229
	invokestatic	Method scala/runtime/BoxesRunTime.boxToInteger:(I)Ljava/lang/Integer;
	invokespecial	Method scala/Tuple2."<init>":(Ljava/lang/Object;Ljava/lang/Object;)V
	aastore
	dup
	ldc_w	int 229
	new	class scala/Tuple2
	dup
	ldc_w	String iota
	ldc_w	int 953
	istore	230
	iload	230
	invokestatic	Method scala/runtime/BoxesRunTime.boxToInteger:(I)Ljava/lang/Integer;
	invokespecial	Method scala/Tuple2."<init>":(Ljava/lang/Object;Ljava/lang/Object;)V
	aastore
	dup
	ldc_w	int 230
	new	class scala/Tuple2
	dup
	ldc_w	String kappa
	ldc_w	int 954
	istore	231
	iload	231
	invokestatic	Method scala/runtime/BoxesRunTime.boxToInteger:(I)Ljava/lang/Integer;
	invokespecial	Method scala/Tuple2."<init>":(Ljava/lang/Object;Ljava/lang/Object;)V
	aastore
	dup
	ldc_w	int 231
	new	class scala/Tuple2
	dup
	ldc_w	String lambda
	ldc_w	int 955
	istore	232
	iload	232
	invokestatic	Method scala/runtime/BoxesRunTime.boxToInteger:(I)Ljava/lang/Integer;
	invokespecial	Method scala/Tuple2."<init>":(Ljava/lang/Object;Ljava/lang/Object;)V
	aastore
	dup
	ldc_w	int 232
	new	class scala/Tuple2
	dup
	ldc_w	String mu
	ldc_w	int 956
	istore	233
	iload	233
	invokestatic	Method scala/runtime/BoxesRunTime.boxToInteger:(I)Ljava/lang/Integer;
	invokespecial	Method scala/Tuple2."<init>":(Ljava/lang/Object;Ljava/lang/Object;)V
	aastore
	dup
	ldc_w	int 233
	new	class scala/Tuple2
	dup
	ldc_w	String nu
	ldc_w	int 957
	istore	234
	iload	234
	invokestatic	Method scala/runtime/BoxesRunTime.boxToInteger:(I)Ljava/lang/Integer;
	invokespecial	Method scala/Tuple2."<init>":(Ljava/lang/Object;Ljava/lang/Object;)V
	aastore
	dup
	ldc_w	int 234
	new	class scala/Tuple2
	dup
	ldc_w	String xi
	ldc_w	int 958
	istore	235
	iload	235
	invokestatic	Method scala/runtime/BoxesRunTime.boxToInteger:(I)Ljava/lang/Integer;
	invokespecial	Method scala/Tuple2."<init>":(Ljava/lang/Object;Ljava/lang/Object;)V
	aastore
	dup
	ldc_w	int 235
	new	class scala/Tuple2
	dup
	ldc_w	String omicron
	ldc_w	int 959
	istore	236
	iload	236
	invokestatic	Method scala/runtime/BoxesRunTime.boxToInteger:(I)Ljava/lang/Integer;
	invokespecial	Method scala/Tuple2."<init>":(Ljava/lang/Object;Ljava/lang/Object;)V
	aastore
	dup
	ldc_w	int 236
	new	class scala/Tuple2
	dup
	ldc_w	String pi
	ldc_w	int 960
	istore	237
	iload	237
	invokestatic	Method scala/runtime/BoxesRunTime.boxToInteger:(I)Ljava/lang/Integer;
	invokespecial	Method scala/Tuple2."<init>":(Ljava/lang/Object;Ljava/lang/Object;)V
	aastore
	dup
	ldc_w	int 237
	new	class scala/Tuple2
	dup
	ldc_w	String rho
	ldc_w	int 961
	istore	238
	iload	238
	invokestatic	Method scala/runtime/BoxesRunTime.boxToInteger:(I)Ljava/lang/Integer;
	invokespecial	Method scala/Tuple2."<init>":(Ljava/lang/Object;Ljava/lang/Object;)V
	aastore
	dup
	ldc_w	int 238
	new	class scala/Tuple2
	dup
	ldc_w	String sigmaf
	ldc_w	int 962
	istore	239
	iload	239
	invokestatic	Method scala/runtime/BoxesRunTime.boxToInteger:(I)Ljava/lang/Integer;
	invokespecial	Method scala/Tuple2."<init>":(Ljava/lang/Object;Ljava/lang/Object;)V
	aastore
	dup
	ldc_w	int 239
	new	class scala/Tuple2
	dup
	ldc_w	String sigma
	ldc_w	int 963
	istore	240
	iload	240
	invokestatic	Method scala/runtime/BoxesRunTime.boxToInteger:(I)Ljava/lang/Integer;
	invokespecial	Method scala/Tuple2."<init>":(Ljava/lang/Object;Ljava/lang/Object;)V
	aastore
	dup
	ldc_w	int 240
	new	class scala/Tuple2
	dup
	ldc_w	String tau
	ldc_w	int 964
	istore	241
	iload	241
	invokestatic	Method scala/runtime/BoxesRunTime.boxToInteger:(I)Ljava/lang/Integer;
	invokespecial	Method scala/Tuple2."<init>":(Ljava/lang/Object;Ljava/lang/Object;)V
	aastore
	dup
	ldc_w	int 241
	new	class scala/Tuple2
	dup
	ldc_w	String upsilon
	ldc_w	int 965
	istore	242
	iload	242
	invokestatic	Method scala/runtime/BoxesRunTime.boxToInteger:(I)Ljava/lang/Integer;
	invokespecial	Method scala/Tuple2."<init>":(Ljava/lang/Object;Ljava/lang/Object;)V
	aastore
	dup
	ldc_w	int 242
	new	class scala/Tuple2
	dup
	ldc_w	String phi
	ldc_w	int 966
	istore	243
	iload	243
	invokestatic	Method scala/runtime/BoxesRunTime.boxToInteger:(I)Ljava/lang/Integer;
	invokespecial	Method scala/Tuple2."<init>":(Ljava/lang/Object;Ljava/lang/Object;)V
	aastore
	dup
	ldc_w	int 243
	new	class scala/Tuple2
	dup
	ldc_w	String chi
	ldc_w	int 967
	istore	244
	iload	244
	invokestatic	Method scala/runtime/BoxesRunTime.boxToInteger:(I)Ljava/lang/Integer;
	invokespecial	Method scala/Tuple2."<init>":(Ljava/lang/Object;Ljava/lang/Object;)V
	aastore
	dup
	ldc_w	int 244
	new	class scala/Tuple2
	dup
	ldc_w	String psi
	ldc_w	int 968
	istore	245
	iload	245
	invokestatic	Method scala/runtime/BoxesRunTime.boxToInteger:(I)Ljava/lang/Integer;
	invokespecial	Method scala/Tuple2."<init>":(Ljava/lang/Object;Ljava/lang/Object;)V
	aastore
	dup
	ldc_w	int 245
	new	class scala/Tuple2
	dup
	ldc_w	String omega
	ldc_w	int 969
	istore	246
	iload	246
	invokestatic	Method scala/runtime/BoxesRunTime.boxToInteger:(I)Ljava/lang/Integer;
	invokespecial	Method scala/Tuple2."<init>":(Ljava/lang/Object;Ljava/lang/Object;)V
	aastore
	dup
	ldc_w	int 246
	new	class scala/Tuple2
	dup
	ldc_w	String thetasym
	ldc_w	int 977
	istore	247
	iload	247
	invokestatic	Method scala/runtime/BoxesRunTime.boxToInteger:(I)Ljava/lang/Integer;
	invokespecial	Method scala/Tuple2."<init>":(Ljava/lang/Object;Ljava/lang/Object;)V
	aastore
	dup
	ldc	int 247
	new	class scala/Tuple2
	dup
	ldc_w	String upsih
	ldc_w	int 978
	istore	248
	iload	248
	invokestatic	Method scala/runtime/BoxesRunTime.boxToInteger:(I)Ljava/lang/Integer;
	invokespecial	Method scala/Tuple2."<init>":(Ljava/lang/Object;Ljava/lang/Object;)V
	aastore
	dup
	ldc_w	int 248
	new	class scala/Tuple2
	dup
	ldc_w	String piv
	ldc_w	int 982
	istore	249
	iload	249
	invokestatic	Method scala/runtime/BoxesRunTime.boxToInteger:(I)Ljava/lang/Integer;
	invokespecial	Method scala/Tuple2."<init>":(Ljava/lang/Object;Ljava/lang/Object;)V
	aastore
	checkcast	class "[Ljava/lang/Object;"
	invokevirtual	Method scala/Predef$.wrapRefArray:([Ljava/lang/Object;)Lscala/collection/mutable/WrappedArray;
	invokevirtual	Method scala/collection/immutable/List$.apply:(Lscala/collection/Seq;)Lscala/collection/immutable/List;
	putfield	Field entList:Lscala/collection/immutable/List;
	aload_0
	getstatic	Field scala/Predef$.MODULE$:Lscala/Predef$;
	invokevirtual	Method scala/Predef$.Map:()Lscala/collection/immutable/Map$;
	invokevirtual	Method scala/collection/immutable/Map$.empty:()Lscala/collection/immutable/Map;
	aload_0
	invokevirtual	Method entList:()Lscala/collection/immutable/List;
	new	class scala/xml/parsing/XhtmlEntities$$anonfun$1
	dup
	invokespecial	Method scala/xml/parsing/XhtmlEntities$$anonfun$1."<init>":()V
	getstatic	Field scala/collection/immutable/List$.MODULE$:Lscala/collection/immutable/List$;
	invokevirtual	Method scala/collection/immutable/List$.canBuildFrom:()Lscala/collection/generic/CanBuildFrom;
	invokeinterface	InterfaceMethod scala/collection/TraversableLike.map:(Lscala/Function1;Lscala/collection/generic/CanBuildFrom;)Ljava/lang/Object;
	checkcast	class scala/collection/Traversable
	invokeinterface	InterfaceMethod scala/collection/immutable/MapLike.$plus$plus:(Lscala/collection/Traversable;)Lscala/collection/immutable/Map;
	putfield	Field entMap:Lscala/collection/immutable/Map;
	aload_0
	aload_0
	invokevirtual	Method entList:()Lscala/collection/immutable/List;
	new	class scala/xml/parsing/XhtmlEntities$$anonfun$2
	dup
	invokespecial	Method scala/xml/parsing/XhtmlEntities$$anonfun$2."<init>":()V
	getstatic	Field scala/collection/immutable/List$.MODULE$:Lscala/collection/immutable/List$;
	invokevirtual	Method scala/collection/immutable/List$.canBuildFrom:()Lscala/collection/generic/CanBuildFrom;
	invokeinterface	InterfaceMethod scala/collection/TraversableLike.map:(Lscala/Function1;Lscala/collection/generic/CanBuildFrom;)Ljava/lang/Object;
	checkcast	class scala/collection/immutable/List
	putfield	Field entities:Lscala/collection/immutable/List;
	return
  Labels:

}

