Compiled from "XhtmlEntities.scala"
public final class scala.xml.parsing.XhtmlEntities$$anonfun$1 extends scala.runtime.AbstractFunction1 implements java.io.Serializable
  SourceFile: "XhtmlEntities.scala"
  Scala: length = 0x
   
  InnerClass: 
   public final $anonfun$1=class scala/xml/parsing/XhtmlEntities$$anonfun$1 of class scala/xml/parsing/XhtmlEntities
  minor version: 0
  major version: 49
  Constant pool:
Asciz	SourceFile;
Asciz	XhtmlEntities.scala;
Asciz	<clinit>;
Asciz	()V;
Asciz	Code;
Asciz	serialVersionUID;
Asciz	J;
Asciz	scala/xml/parsing/XhtmlEntities$$anonfun$1;
class	scala/xml/parsing/XhtmlEntities$$anonfun$1
NameAndType	serialVersionUID:J
Field	scala/xml/parsing/XhtmlEntities$$anonfun$1.serialVersionUID:J
Asciz	<init>;
Asciz	LineNumberTable;
Asciz	scala/runtime/AbstractFunction1;
class	scala/runtime/AbstractFunction1
NameAndType	"<init>":()V
Method	scala/runtime/AbstractFunction1."<init>":()V
Asciz	apply;
Asciz	(Ljava/lang/Object;)Ljava/lang/Object;;
Asciz	scala/Tuple2;
class	scala/Tuple2
Asciz	(Lscala/Tuple2;)Lscala/Tuple2;;
NameAndType	apply:(Lscala/Tuple2;)Lscala/Tuple2;
Method	scala/xml/parsing/XhtmlEntities$$anonfun$1.apply:(Lscala/Tuple2;)Lscala/Tuple2;
Asciz	this;
Asciz	Lscala/xml/parsing/XhtmlEntities$$anonfun$1;;
Asciz	v1;
Asciz	Ljava/lang/Object;;
Asciz	LocalVariableTable;
Asciz	_1;
Asciz	()Ljava/lang/Object;;
NameAndType	_1:()Ljava/lang/Object;
Method	scala/Tuple2._1:()Ljava/lang/Object;
Asciz	java/lang/String;
class	java/lang/String
Asciz	_2;
NameAndType	_2:()Ljava/lang/Object;
Method	scala/Tuple2._2:()Ljava/lang/Object;
Asciz	scala/runtime/BoxesRunTime;
class	scala/runtime/BoxesRunTime
Asciz	unboxToInt;
Asciz	(Ljava/lang/Object;)I;
NameAndType	unboxToInt:(Ljava/lang/Object;)I
Method	scala/runtime/BoxesRunTime.unboxToInt:(Ljava/lang/Object;)I
Asciz	boxToCharacter;
Asciz	(C)Ljava/lang/Character;;
NameAndType	boxToCharacter:(C)Ljava/lang/Character;
Method	scala/runtime/BoxesRunTime.boxToCharacter:(C)Ljava/lang/Character;
Asciz	(Ljava/lang/Object;Ljava/lang/Object;)V;
NameAndType	"<init>":(Ljava/lang/Object;Ljava/lang/Object;)V
Method	scala/Tuple2."<init>":(Ljava/lang/Object;Ljava/lang/Object;)V
Asciz	scala/MatchError;
class	scala/MatchError
Asciz	toString;
Asciz	()Ljava/lang/String;;
NameAndType	toString:()Ljava/lang/String;
Method	scala/Tuple2.toString:()Ljava/lang/String;
Asciz	(Ljava/lang/String;)V;
NameAndType	"<init>":(Ljava/lang/String;)V
Method	scala/MatchError."<init>":(Ljava/lang/String;)V
Asciz	temp2;
Asciz	Ljava/lang/String;;
Asciz	temp3;
Asciz	I;
Asciz	(Lscala/Tuple2<Ljava/lang/String;Ljava/lang/Integer;>;)Lscala/Tuple2<Ljava/lang/String;Ljava/lang/Character;>;;
Asciz	Signature;
Asciz	Scala;
Asciz	InnerClasses;
Asciz	scala/xml/parsing/XhtmlEntities;
class	scala/xml/parsing/XhtmlEntities
Asciz	$anonfun$1;
Asciz	java/io/Serializable;
class	java/io/Serializable

{
public static final long serialVersionUID;
  Signature: J

public static {};
  Signature: ()V
  Code:
   Stack=2, Locals=0, Args_size=0
	lconst_0
	putstatic	Field serialVersionUID:J
	return
  Labels:

public scala.xml.parsing.XhtmlEntities$$anonfun$1();
  Signature: ()V
  Code:
   Stack=1, Locals=1, Args_size=1
	aload_0
	invokespecial	Method scala/runtime/AbstractFunction1."<init>":()V
	return
  Labels:

public final java.lang.Object apply(java.lang.Object);
  Signature: (Ljava/lang/Object;)Ljava/lang/Object;
  Code:
   Stack=2, Locals=2, Args_size=2
	aload_0
	aload_1
	checkcast	class scala/Tuple2
	invokevirtual	Method apply:(Lscala/Tuple2;)Lscala/Tuple2;
	areturn
  Labels:
  LocalVariableTable: 
   Start  Length  Slot  Name   Signature
   0      9      0    this       Lscala/xml/parsing/XhtmlEntities$$anonfun$1;
   0      9      1    v1       Ljava/lang/Object;


public final scala.Tuple2 apply(scala.Tuple2);
  Signature: (Lscala/Tuple2;)Lscala/Tuple2;
  Code:
   Stack=4, Locals=5, Args_size=2
	aload_1
	ifnull	l1 // new
	aload_1
	invokevirtual	Method scala/Tuple2._1:()Ljava/lang/Object;
	checkcast	class java/lang/String
	astore_2
	aload_1
	invokevirtual	Method scala/Tuple2._2:()Ljava/lang/Object;
	invokestatic	Method scala/runtime/BoxesRunTime.unboxToInt:(Ljava/lang/Object;)I
	istore_3
	new	class scala/Tuple2
	dup
	aload_2
	iload_3
	i2c
	istore	4
	iload	4
	invokestatic	Method scala/runtime/BoxesRunTime.boxToCharacter:(C)Ljava/lang/Character;
	invokespecial	Method scala/Tuple2."<init>":(Ljava/lang/Object;Ljava/lang/Object;)V
	areturn
l1	new	class scala/MatchError
	dup
	aload_1
	invokevirtual	Method scala/Tuple2.toString:()Ljava/lang/String;
	invokespecial	Method scala/MatchError."<init>":(Ljava/lang/String;)V
	athrow
  Labels:
   	l1 = 38 // new
  LocalVariableTable: 
   Start  Length  Slot  Name   Signature
   0      50      0    this       Lscala/xml/parsing/XhtmlEntities$$anonfun$1;
   12      25      2    temp2       Ljava/lang/String;
   20      17      3    temp3       I

  Signature: length = 0x2
   00 41 

}

