Compiled from "BitSet.scala"
public class scala.collection.immutable.BitSet$BitSetN extends scala.collection.immutable.BitSet implements scala.ScalaObject
  SourceFile: "BitSet.scala"
  Scala: length = 0x
   
  InnerClass: 
   public BitSetN=class scala/collection/immutable/BitSet$BitSetN of class scala/collection/immutable/BitSet
  minor version: 0
  major version: 49
  Constant pool:
Asciz	SourceFile;
Asciz	BitSet.scala;
Asciz	elems;
Asciz	[J;
Asciz	<init>;
Asciz	([J)V;
Asciz	Code;
Asciz	LineNumberTable;
Asciz	scala/collection/immutable/BitSet$BitSetN;
class	scala/collection/immutable/BitSet$BitSetN
NameAndType	elems:[J
Field	scala/collection/immutable/BitSet$BitSetN.elems:[J
Asciz	scala/collection/immutable/BitSet;
class	scala/collection/immutable/BitSet
Asciz	()V;
NameAndType	"<init>":()V
Method	scala/collection/immutable/BitSet."<init>":()V
Asciz	this;
Asciz	Lscala/collection/immutable/BitSet$BitSetN;;
Asciz	LocalVariableTable;
Asciz	updateWord;
Asciz	(IJ)Lscala/collection/immutable/BitSet;;
Asciz	scala/collection/BitSetLike$;
class	scala/collection/BitSetLike$
Asciz	MODULE$;
Asciz	Lscala/collection/BitSetLike$;;
NameAndType	MODULE$:Lscala/collection/BitSetLike$;
Field	scala/collection/BitSetLike$.MODULE$:Lscala/collection/BitSetLike$;
Asciz	()[J;
NameAndType	elems:()[J
Method	scala/collection/immutable/BitSet$BitSetN.elems:()[J
Asciz	updateArray;
Asciz	([JIJ)[J;
NameAndType	updateArray:([JIJ)[J
Method	scala/collection/BitSetLike$.updateArray:([JIJ)[J
Asciz	fromArray;
Asciz	([J)Lscala/collection/immutable/BitSet;;
NameAndType	fromArray:([J)Lscala/collection/immutable/BitSet;
Method	scala/collection/immutable/BitSet$BitSetN.fromArray:([J)Lscala/collection/immutable/BitSet;
Asciz	idx;
Asciz	I;
Asciz	w;
Asciz	J;
Asciz	word;
Asciz	(I)J;
Asciz	nwords;
Asciz	()I;
NameAndType	nwords:()I
Method	scala/collection/immutable/BitSet$BitSetN.nwords:()I
Asciz	Scala;
Asciz	InnerClasses;
Asciz	BitSetN;
Asciz	scala/ScalaObject;
class	scala/ScalaObject

{
private final long[] elems;
  Signature: [J

public scala.collection.immutable.BitSet$BitSetN(long[]);
  Signature: ([J)V
  Code:
   Stack=2, Locals=2, Args_size=2
	aload_0
	aload_1
	putfield	Field elems:[J
	aload_0
	invokespecial	Method scala/collection/immutable/BitSet."<init>":()V
	return
  Labels:
  LocalVariableTable: 
   Start  Length  Slot  Name   Signature
   0      10      0    this       Lscala/collection/immutable/BitSet$BitSetN;
   0      10      1    elems       [J


public scala.collection.immutable.BitSet updateWord(int, long);
  Signature: (IJ)Lscala/collection/immutable/BitSet;
  Code:
   Stack=6, Locals=4, Args_size=3
	aload_0
	getstatic	Field scala/collection/BitSetLike$.MODULE$:Lscala/collection/BitSetLike$;
	aload_0
	invokevirtual	Method elems:()[J
	iload_1
	lload_2
	invokevirtual	Method scala/collection/BitSetLike$.updateArray:([JIJ)[J
	invokevirtual	Method fromArray:([J)Lscala/collection/immutable/BitSet;
	areturn
  Labels:
  LocalVariableTable: 
   Start  Length  Slot  Name   Signature
   0      17      0    this       Lscala/collection/immutable/BitSet$BitSetN;
   0      17      1    idx       I
   0      17      2    w       J


public long word(int);
  Signature: (I)J
  Code:
   Stack=2, Locals=2, Args_size=2
	iload_1
	aload_0
	invokevirtual	Method nwords:()I
	if_icmpge	l1 // lconst_0
	aload_0
	invokevirtual	Method elems:()[J
	iload_1
	laload
	goto	l2 // lreturn
l1	lconst_0
l2	lreturn
  Labels:
   	l1 = 17 // lconst_0
   	l2 = 18 // lreturn
  LocalVariableTable: 
   Start  Length  Slot  Name   Signature
   0      19      0    this       Lscala/collection/immutable/BitSet$BitSetN;
   0      19      1    idx       I


public int nwords();
  Signature: ()I
  Code:
   Stack=1, Locals=1, Args_size=1
	aload_0
	invokevirtual	Method elems:()[J
	arraylength
	ireturn
  Labels:

public long[] elems();
  Signature: ()[J
  Code:
   Stack=1, Locals=1, Args_size=1
	aload_0
	getfield	Field elems:[J
	areturn
  Labels:

}

