Compiled from "BitSet.scala"
public class scala.collection.immutable.BitSet$BitSet1 extends scala.collection.immutable.BitSet implements scala.ScalaObject
  SourceFile: "BitSet.scala"
  Scala: length = 0x
   
  InnerClass: 
   public BitSet2=class scala/collection/immutable/BitSet$BitSet2 of class scala/collection/immutable/BitSet
   public BitSet1=class scala/collection/immutable/BitSet$BitSet1 of class scala/collection/immutable/BitSet
   public final $anonfun$apply$7=class scala/Array$$anonfun$apply$7 of class scala/Array
  minor version: 0
  major version: 49
  Constant pool:
Asciz	SourceFile;
Asciz	BitSet.scala;
Asciz	elems;
Asciz	J;
Asciz	<init>;
Asciz	(J)V;
Asciz	Code;
Asciz	LineNumberTable;
Asciz	scala/collection/immutable/BitSet$BitSet1;
class	scala/collection/immutable/BitSet$BitSet1
NameAndType	elems:J
Field	scala/collection/immutable/BitSet$BitSet1.elems:J
Asciz	scala/collection/immutable/BitSet;
class	scala/collection/immutable/BitSet
Asciz	()V;
NameAndType	"<init>":()V
Method	scala/collection/immutable/BitSet."<init>":()V
Asciz	this;
Asciz	Lscala/collection/immutable/BitSet$BitSet1;;
Asciz	LocalVariableTable;
Asciz	updateWord;
Asciz	(IJ)Lscala/collection/immutable/BitSet;;
NameAndType	"<init>":(J)V
Method	scala/collection/immutable/BitSet$BitSet1."<init>":(J)V
Asciz	scala/collection/immutable/BitSet$BitSet2;
class	scala/collection/immutable/BitSet$BitSet2
Asciz	()J;
NameAndType	elems:()J
Method	scala/collection/immutable/BitSet$BitSet1.elems:()J
Asciz	(JJ)V;
NameAndType	"<init>":(JJ)V
Method	scala/collection/immutable/BitSet$BitSet2."<init>":(JJ)V
Asciz	scala/collection/BitSetLike$;
class	scala/collection/BitSetLike$
Asciz	MODULE$;
Asciz	Lscala/collection/BitSetLike$;;
NameAndType	MODULE$:Lscala/collection/BitSetLike$;
Field	scala/collection/BitSetLike$.MODULE$:Lscala/collection/BitSetLike$;
Asciz	scala/Predef$;
class	scala/Predef$
Asciz	Lscala/Predef$;;
NameAndType	MODULE$:Lscala/Predef$;
Field	scala/Predef$.MODULE$:Lscala/Predef$;
Asciz	wrapLongArray;
Asciz	([J)Lscala/collection/mutable/WrappedArray;;
NameAndType	wrapLongArray:([J)Lscala/collection/mutable/WrappedArray;
Method	scala/Predef$.wrapLongArray:([J)Lscala/collection/mutable/WrappedArray;
Asciz	scala/collection/SeqLike;
class	scala/collection/SeqLike
Asciz	length;
Asciz	()I;
NameAndType	length:()I
InterfaceMethod	scala/collection/SeqLike.length:()I
Asciz	scala/runtime/IntRef;
class	scala/runtime/IntRef
Asciz	(I)V;
NameAndType	"<init>":(I)V
Method	scala/runtime/IntRef."<init>":(I)V
Asciz	scala/collection/IterableLike;
class	scala/collection/IterableLike
Asciz	iterator;
Asciz	()Lscala/collection/Iterator;;
NameAndType	iterator:()Lscala/collection/Iterator;
InterfaceMethod	scala/collection/IterableLike.iterator:()Lscala/collection/Iterator;
Asciz	scala/Array$$anonfun$apply$7;
class	scala/Array$$anonfun$apply$7
Asciz	([JLscala/runtime/IntRef;)V;
NameAndType	"<init>":([JLscala/runtime/IntRef;)V
Method	scala/Array$$anonfun$apply$7."<init>":([JLscala/runtime/IntRef;)V
Asciz	scala/collection/Iterator;
class	scala/collection/Iterator
Asciz	foreach;
Asciz	(Lscala/Function1;)V;
NameAndType	foreach:(Lscala/Function1;)V
InterfaceMethod	scala/collection/Iterator.foreach:(Lscala/Function1;)V
Asciz	updateArray;
Asciz	([JIJ)[J;
NameAndType	updateArray:([JIJ)[J
Method	scala/collection/BitSetLike$.updateArray:([JIJ)[J
Asciz	fromArray;
Asciz	([J)Lscala/collection/immutable/BitSet;;
NameAndType	fromArray:([J)Lscala/collection/immutable/BitSet;
Method	scala/collection/immutable/BitSet$BitSet1.fromArray:([J)Lscala/collection/immutable/BitSet;
Asciz	idx;
Asciz	I;
Asciz	w;
Asciz	i$70;
Asciz	Lscala/runtime/IntRef;;
Asciz	array$70;
Asciz	[J;
Asciz	word;
Asciz	(I)J;
Asciz	nwords;
Asciz	Scala;
Asciz	InnerClasses;
Asciz	BitSet2;
Asciz	BitSet1;
Asciz	scala/Array;
class	scala/Array
Asciz	$anonfun$apply$7;
Asciz	scala/ScalaObject;
class	scala/ScalaObject

{
private final long elems;
  Signature: J

public scala.collection.immutable.BitSet$BitSet1(long);
  Signature: (J)V
  Code:
   Stack=3, Locals=3, Args_size=2
	aload_0
	lload_1
	putfield	Field elems:J
	aload_0
	invokespecial	Method scala/collection/immutable/BitSet."<init>":()V
	return
  Labels:
  LocalVariableTable: 
   Start  Length  Slot  Name   Signature
   0      10      0    this       Lscala/collection/immutable/BitSet$BitSet1;
   0      10      1    elems       J


public scala.collection.immutable.BitSet updateWord(int, long);
  Signature: (IJ)Lscala/collection/immutable/BitSet;
  Code:
   Stack=7, Locals=9, Args_size=3
	iload_1
	iconst_0
	if_icmpne	l1 // iload_1
	new	class scala/collection/immutable/BitSet$BitSet1
	dup
	lload_2
	invokespecial	Method "<init>":(J)V
	goto	l2 // areturn
l1	iload_1
	iconst_1
	if_icmpne	l3 // aload_0
	new	class scala/collection/immutable/BitSet$BitSet2
	dup
	aload_0
	invokevirtual	Method elems:()J
	lload_2
	invokespecial	Method scala/collection/immutable/BitSet$BitSet2."<init>":(JJ)V
	goto	l2 // areturn
l3	aload_0
	getstatic	Field scala/collection/BitSetLike$.MODULE$:Lscala/collection/BitSetLike$;
	aload_0
	invokevirtual	Method elems:()J
	getstatic	Field scala/Predef$.MODULE$:Lscala/Predef$;
	iconst_0
	newarray long
	invokevirtual	Method scala/Predef$.wrapLongArray:([J)Lscala/collection/mutable/WrappedArray;
	astore	6
	lstore	4
	aload	6
	invokeinterface	InterfaceMethod scala/collection/SeqLike.length:()I
	iconst_1
	iadd
	newarray long
	astore	8
	aload	8
	iconst_0
	lload	4
	lastore
	new	class scala/runtime/IntRef
	dup
	iconst_1
	invokespecial	Method scala/runtime/IntRef."<init>":(I)V
	astore	7
	aload	6
	invokeinterface	InterfaceMethod scala/collection/IterableLike.iterator:()Lscala/collection/Iterator;
	new	class scala/Array$$anonfun$apply$7
	dup
	aload	8
	aload	7
	invokespecial	Method scala/Array$$anonfun$apply$7."<init>":([JLscala/runtime/IntRef;)V
	invokeinterface	InterfaceMethod scala/collection/Iterator.foreach:(Lscala/Function1;)V
	aload	8
	iload_1
	lload_2
	invokevirtual	Method scala/collection/BitSetLike$.updateArray:([JIJ)[J
	invokevirtual	Method fromArray:([J)Lscala/collection/immutable/BitSet;
l2	areturn
  Labels:
   	l1 = 16 // iload_1
   	l3 = 36 // aload_0
   	l2 = 119 // areturn
  LocalVariableTable: 
   Start  Length  Slot  Name   Signature
   0      120      0    this       Lscala/collection/immutable/BitSet$BitSet1;
   0      120      1    idx       I
   0      120      2    w       J
   86      25      7    i$70       Lscala/runtime/IntRef;
   70      41      8    array$70       [J


public long word(int);
  Signature: (I)J
  Code:
   Stack=2, Locals=2, Args_size=2
	iload_1
	iconst_0
	if_icmpne	l1 // lconst_0
	aload_0
	invokevirtual	Method elems:()J
	goto	l2 // lreturn
l1	lconst_0
l2	lreturn
  Labels:
   	l1 = 12 // lconst_0
   	l2 = 13 // lreturn
  LocalVariableTable: 
   Start  Length  Slot  Name   Signature
   0      14      0    this       Lscala/collection/immutable/BitSet$BitSet1;
   0      14      1    idx       I


public int nwords();
  Signature: ()I
  Code:
   Stack=1, Locals=1, Args_size=1
	iconst_1
	ireturn
  Labels:

public long elems();
  Signature: ()J
  Code:
   Stack=2, Locals=1, Args_size=1
	aload_0
	getfield	Field elems:J
	lreturn
  Labels:

}

