Compiled from "BitSet.scala"
public class scala.collection.immutable.BitSet$BitSetN extends scala.collection.immutable.BitSet implements scala.ScalaObject
  SourceFile: "BitSet.scala"
  Scala: length = 0x
   
  InnerClass: 
   public #52= #10 of #14; //BitSetN=class scala/collection/immutable/BitSet$BitSetN of class scala/collection/immutable/BitSet
  minor version: 0
  major version: 49
  Constant pool:
const #1 = Asciz	SourceFile;
const #2 = Asciz	BitSet.scala;
const #3 = Asciz	elems;
const #4 = Asciz	[J;
const #5 = Asciz	<init>;
const #6 = Asciz	([J)V;
const #7 = Asciz	Code;
const #8 = Asciz	LineNumberTable;
const #9 = Asciz	scala/collection/immutable/BitSet$BitSetN;
const #10 = class	#9;	//  scala/collection/immutable/BitSet$BitSetN
const #11 = NameAndType	#3:#4;//  elems:[J
const #12 = Field	#10.#11;	//  scala/collection/immutable/BitSet$BitSetN.elems:[J
const #13 = Asciz	scala/collection/immutable/BitSet;
const #14 = class	#13;	//  scala/collection/immutable/BitSet
const #15 = Asciz	()V;
const #16 = NameAndType	#5:#15;//  "<init>":()V
const #17 = Method	#14.#16;	//  scala/collection/immutable/BitSet."<init>":()V
const #18 = Asciz	this;
const #19 = Asciz	Lscala/collection/immutable/BitSet$BitSetN;;
const #20 = Asciz	LocalVariableTable;
const #21 = Asciz	updateWord;
const #22 = Asciz	(IJ)Lscala/collection/immutable/BitSet;;
const #23 = Asciz	scala/collection/BitSetLike$;
const #24 = class	#23;	//  scala/collection/BitSetLike$
const #25 = Asciz	MODULE$;
const #26 = Asciz	Lscala/collection/BitSetLike$;;
const #27 = NameAndType	#25:#26;//  MODULE$:Lscala/collection/BitSetLike$;
const #28 = Field	#24.#27;	//  scala/collection/BitSetLike$.MODULE$:Lscala/collection/BitSetLike$;
const #29 = Asciz	()[J;
const #30 = NameAndType	#3:#29;//  elems:()[J
const #31 = Method	#10.#30;	//  scala/collection/immutable/BitSet$BitSetN.elems:()[J
const #32 = Asciz	updateArray;
const #33 = Asciz	([JIJ)[J;
const #34 = NameAndType	#32:#33;//  updateArray:([JIJ)[J
const #35 = Method	#24.#34;	//  scala/collection/BitSetLike$.updateArray:([JIJ)[J
const #36 = Asciz	fromArray;
const #37 = Asciz	([J)Lscala/collection/immutable/BitSet;;
const #38 = NameAndType	#36:#37;//  fromArray:([J)Lscala/collection/immutable/BitSet;
const #39 = Method	#10.#38;	//  scala/collection/immutable/BitSet$BitSetN.fromArray:([J)Lscala/collection/immutable/BitSet;
const #40 = Asciz	idx;
const #41 = Asciz	I;
const #42 = Asciz	w;
const #43 = Asciz	J;
const #44 = Asciz	word;
const #45 = Asciz	(I)J;
const #46 = Asciz	nwords;
const #47 = Asciz	()I;
const #48 = NameAndType	#46:#47;//  nwords:()I
const #49 = Method	#10.#48;	//  scala/collection/immutable/BitSet$BitSetN.nwords:()I
const #50 = Asciz	Scala;
const #51 = Asciz	InnerClasses;
const #52 = Asciz	BitSetN;
const #53 = Asciz	scala/ScalaObject;
const #54 = class	#53;	//  scala/ScalaObject

{
public scala.collection.immutable.BitSet$BitSetN(long[]);
  Code:
   Stack=2, Locals=2, Args_size=2
   0:	aload_0
   1:	aload_1
   2:	putfield	#12; //Field elems:[J
   5:	aload_0
   6:	invokespecial	#17; //Method scala/collection/immutable/BitSet."<init>":()V
   9:	return
  LineNumberTable: 
   line 97: 0

  LocalVariableTable: 
   Start  Length  Slot  Name   Signature
   0      10      0    this       Lscala/collection/immutable/BitSet$BitSetN;
   0      10      1    elems       [J


public scala.collection.immutable.BitSet updateWord(int, long);
  Code:
   Stack=6, Locals=4, Args_size=3
   0:	aload_0
   1:	getstatic	#28; //Field scala/collection/BitSetLike$.MODULE$:Lscala/collection/BitSetLike$;
   4:	aload_0
   5:	invokevirtual	#31; //Method elems:()[J
   8:	iload_1
   9:	lload_2
   10:	invokevirtual	#35; //Method scala/collection/BitSetLike$.updateArray:([JIJ)[J
   13:	invokevirtual	#39; //Method fromArray:([J)Lscala/collection/immutable/BitSet;
   16:	areturn
  LineNumberTable: 
   line 100: 0

  LocalVariableTable: 
   Start  Length  Slot  Name   Signature
   0      17      0    this       Lscala/collection/immutable/BitSet$BitSetN;
   0      17      1    idx       I
   0      17      2    w       J


public long word(int);
  Code:
   Stack=2, Locals=2, Args_size=2
   0:	iload_1
   1:	aload_0
   2:	invokevirtual	#49; //Method nwords:()I
   5:	if_icmpge	17
   8:	aload_0
   9:	invokevirtual	#31; //Method elems:()[J
   12:	iload_1
   13:	laload
   14:	goto	18
   17:	lconst_0
   18:	lreturn
  LineNumberTable: 
   line 99: 0

  LocalVariableTable: 
   Start  Length  Slot  Name   Signature
   0      19      0    this       Lscala/collection/immutable/BitSet$BitSetN;
   0      19      1    idx       I


public int nwords();
  Code:
   Stack=1, Locals=1, Args_size=1
   0:	aload_0
   1:	invokevirtual	#31; //Method elems:()[J
   4:	arraylength
   5:	ireturn
  LineNumberTable: 
   line 98: 0


public long[] elems();
  Code:
   Stack=1, Locals=1, Args_size=1
   0:	aload_0
   1:	getfield	#12; //Field elems:[J
   4:	areturn
  LineNumberTable: 
   line 97: 0


}

