Compiled from "DefaultMap.scala"
public final class scala.collection.immutable.DefaultMap$$anonfun$$minus$1 extends scala.runtime.AbstractFunction1 implements java.io.Serializable
  SourceFile: "DefaultMap.scala"
  Scala: length = 0x
   
  InnerClass: 
   public final $anonfun$$minus$1=class scala/collection/immutable/DefaultMap$$anonfun$$minus$1 of class scala/collection/immutable/DefaultMap
  minor version: 0
  major version: 49
  Constant pool:
Asciz	SourceFile;
Asciz	DefaultMap.scala;
Asciz	<clinit>;
Asciz	()V;
Asciz	Code;
Asciz	serialVersionUID;
Asciz	J;
Asciz	scala/collection/immutable/DefaultMap$$anonfun$$minus$1;
class	scala/collection/immutable/DefaultMap$$anonfun$$minus$1
NameAndType	serialVersionUID:J
Field	scala/collection/immutable/DefaultMap$$anonfun$$minus$1.serialVersionUID:J
Asciz	key$1;
Asciz	Ljava/lang/Object;;
Asciz	apply;
Asciz	(Ljava/lang/Object;)Z;
Asciz	LineNumberTable;
NameAndType	key$1:Ljava/lang/Object;
Field	scala/collection/immutable/DefaultMap$$anonfun$$minus$1.key$1:Ljava/lang/Object;
Asciz	scala/runtime/BoxesRunTime;
class	scala/runtime/BoxesRunTime
Asciz	equals;
Asciz	(Ljava/lang/Object;Ljava/lang/Object;)Z;
NameAndType	equals:(Ljava/lang/Object;Ljava/lang/Object;)Z
Method	scala/runtime/BoxesRunTime.equals:(Ljava/lang/Object;Ljava/lang/Object;)Z
Asciz	(Ljava/lang/Object;)Ljava/lang/Object;;
NameAndType	apply:(Ljava/lang/Object;)Z
Method	scala/collection/immutable/DefaultMap$$anonfun$$minus$1.apply:(Ljava/lang/Object;)Z
Asciz	boxToBoolean;
Asciz	(Z)Ljava/lang/Boolean;;
NameAndType	boxToBoolean:(Z)Ljava/lang/Boolean;
Method	scala/runtime/BoxesRunTime.boxToBoolean:(Z)Ljava/lang/Boolean;
Asciz	this;
Asciz	Lscala/collection/immutable/DefaultMap$$anonfun$$minus$1;;
Asciz	v1;
Asciz	LocalVariableTable;
Asciz	<init>;
Asciz	(Lscala/collection/immutable/DefaultMap;Ljava/lang/Object;)V;
Asciz	scala/runtime/AbstractFunction1;
class	scala/runtime/AbstractFunction1
NameAndType	"<init>":()V
Method	scala/runtime/AbstractFunction1."<init>":()V
Asciz	$outer;
Asciz	Lscala/collection/immutable/DefaultMap;;
Asciz	(Lscala/collection/immutable/DefaultMap<TA;TB;>;)V;
Asciz	Signature;
Asciz	Scala;
Asciz	InnerClasses;
Asciz	scala/collection/immutable/DefaultMap;
class	scala/collection/immutable/DefaultMap
Asciz	$anonfun$$minus$1;
Asciz	java/io/Serializable;
class	java/io/Serializable

{
public static final long serialVersionUID;
  Signature: J

private final java.lang.Object key$1;
  Signature: Ljava/lang/Object;

public static {};
  Signature: ()V
  Code:
   Stack=2, Locals=0, Args_size=0
	lconst_0
	putstatic	Field serialVersionUID:J
	return
  Labels:

public final boolean apply(java.lang.Object);
  Signature: (Ljava/lang/Object;)Z
  Code:
   Stack=2, Locals=2, Args_size=2
	aload_0
	getfield	Field key$1:Ljava/lang/Object;
	aload_1
	invokestatic	Method scala/runtime/BoxesRunTime.equals:(Ljava/lang/Object;Ljava/lang/Object;)Z
	ifeq	l1 // iconst_1
	iconst_0
	goto	l2 // ireturn
l1	iconst_1
l2	ireturn
  Labels:
   	l1 = 15 // iconst_1
   	l2 = 16 // ireturn

public final java.lang.Object apply(java.lang.Object);
  Signature: (Ljava/lang/Object;)Ljava/lang/Object;
  Code:
   Stack=2, Locals=2, Args_size=2
	aload_0
	aload_1
	invokevirtual	Method apply:(Ljava/lang/Object;)Z
	invokestatic	Method scala/runtime/BoxesRunTime.boxToBoolean:(Z)Ljava/lang/Boolean;
	areturn
  Labels:
  LocalVariableTable: 
   Start  Length  Slot  Name   Signature
   0      9      0    this       Lscala/collection/immutable/DefaultMap$$anonfun$$minus$1;
   0      9      1    v1       Ljava/lang/Object;


public scala.collection.immutable.DefaultMap$$anonfun$$minus$1(scala.collection.immutable.DefaultMap, java.lang.Object);
  Signature: (Lscala/collection/immutable/DefaultMap;Ljava/lang/Object;)V
  Code:
   Stack=2, Locals=3, Args_size=3
	aload_0
	aload_2
	putfield	Field key$1:Ljava/lang/Object;
	aload_0
	invokespecial	Method scala/runtime/AbstractFunction1."<init>":()V
	return
  Labels:
  LocalVariableTable: 
   Start  Length  Slot  Name   Signature
   0      10      0    this       Lscala/collection/immutable/DefaultMap$$anonfun$$minus$1;
   0      10      1    $outer       Lscala/collection/immutable/DefaultMap;

  Signature: length = 0x2
   00 2C 

}

