Compiled from "DefaultMap.scala"
public abstract class scala.collection.immutable.DefaultMap$class extends java.lang.Object
  SourceFile: "DefaultMap.scala"
  Scala: length = 0x
   
  InnerClass: 
   public final $anonfun$$minus$1=class scala/collection/immutable/DefaultMap$$anonfun$$minus$1 of class scala/collection/immutable/DefaultMap
  minor version: 0
  major version: 49
  Constant pool:
Asciz	SourceFile;
Asciz	DefaultMap.scala;
Asciz	$plus;
Asciz	(Lscala/collection/immutable/DefaultMap;Lscala/Tuple2;)Lscala/collection/immutable/Map;;
Asciz	Code;
Asciz	scala/collection/immutable/Map$;
class	scala/collection/immutable/Map$
Asciz	MODULE$;
Asciz	Lscala/collection/immutable/Map$;;
NameAndType	MODULE$:Lscala/collection/immutable/Map$;
Field	scala/collection/immutable/Map$.MODULE$:Lscala/collection/immutable/Map$;
Asciz	LineNumberTable;
Asciz	newBuilder;
Asciz	()Lscala/collection/mutable/Builder;;
NameAndType	newBuilder:()Lscala/collection/mutable/Builder;
Method	scala/collection/immutable/Map$.newBuilder:()Lscala/collection/mutable/Builder;
Asciz	scala/collection/generic/Growable;
class	scala/collection/generic/Growable
Asciz	$plus$plus$eq;
Asciz	(Lscala/collection/Traversable;)Lscala/collection/generic/Growable;;
NameAndType	$plus$plus$eq:(Lscala/collection/Traversable;)Lscala/collection/generic/Growable;
InterfaceMethod	scala/collection/generic/Growable.$plus$plus$eq:(Lscala/collection/Traversable;)Lscala/collection/generic/Growable;
Asciz	scala/Tuple2;
class	scala/Tuple2
Asciz	_1;
Asciz	()Ljava/lang/Object;;
NameAndType	_1:()Ljava/lang/Object;
Method	scala/Tuple2._1:()Ljava/lang/Object;
Asciz	_2;
NameAndType	_2:()Ljava/lang/Object;
Method	scala/Tuple2._2:()Ljava/lang/Object;
Asciz	<init>;
Asciz	(Ljava/lang/Object;Ljava/lang/Object;)V;
NameAndType	"<init>":(Ljava/lang/Object;Ljava/lang/Object;)V
Method	scala/Tuple2."<init>":(Ljava/lang/Object;Ljava/lang/Object;)V
Asciz	scala/collection/mutable/Builder;
class	scala/collection/mutable/Builder
Asciz	$plus$eq;
Asciz	(Ljava/lang/Object;)Lscala/collection/mutable/Builder;;
NameAndType	$plus$eq:(Ljava/lang/Object;)Lscala/collection/mutable/Builder;
InterfaceMethod	scala/collection/mutable/Builder.$plus$eq:(Ljava/lang/Object;)Lscala/collection/mutable/Builder;
Asciz	result;
NameAndType	result:()Ljava/lang/Object;
InterfaceMethod	scala/collection/mutable/Builder.result:()Ljava/lang/Object;
Asciz	scala/collection/immutable/Map;
class	scala/collection/immutable/Map
Asciz	$this;
Asciz	Lscala/collection/immutable/DefaultMap;;
Asciz	kv;
Asciz	Lscala/Tuple2;;
Asciz	b;
Asciz	Lscala/collection/mutable/Builder;;
Asciz	LocalVariableTable;
Asciz	$minus;
Asciz	(Lscala/collection/immutable/DefaultMap;Ljava/lang/Object;)Lscala/collection/immutable/Map;;
Asciz	scala/collection/MapLike;
class	scala/collection/MapLike
InterfaceMethod	scala/collection/MapLike.newBuilder:()Lscala/collection/mutable/Builder;
Asciz	scala/collection/immutable/DefaultMap$$anonfun$$minus$1;
class	scala/collection/immutable/DefaultMap$$anonfun$$minus$1
Asciz	(Lscala/collection/immutable/DefaultMap;Ljava/lang/Object;)V;
NameAndType	"<init>":(Lscala/collection/immutable/DefaultMap;Ljava/lang/Object;)V
Method	scala/collection/immutable/DefaultMap$$anonfun$$minus$1."<init>":(Lscala/collection/immutable/DefaultMap;Ljava/lang/Object;)V
Asciz	scala/collection/TraversableLike;
class	scala/collection/TraversableLike
Asciz	filter;
Asciz	(Lscala/Function1;)Ljava/lang/Object;;
NameAndType	filter:(Lscala/Function1;)Ljava/lang/Object;
InterfaceMethod	scala/collection/TraversableLike.filter:(Lscala/Function1;)Ljava/lang/Object;
Asciz	scala/collection/Traversable;
class	scala/collection/Traversable
Asciz	key$1;
Asciz	Ljava/lang/Object;;
Asciz	$init$;
Asciz	(Lscala/collection/immutable/DefaultMap;)V;
Asciz	Scala;
Asciz	InnerClasses;
Asciz	scala/collection/immutable/DefaultMap;
class	scala/collection/immutable/DefaultMap
Asciz	$anonfun$$minus$1;
Asciz	scala/collection/immutable/DefaultMap$class;
class	scala/collection/immutable/DefaultMap$class
Asciz	java/lang/Object;
class	java/lang/Object

{
public static scala.collection.immutable.Map $plus(scala.collection.immutable.DefaultMap, scala.Tuple2);
  Signature: (Lscala/collection/immutable/DefaultMap;Lscala/Tuple2;)Lscala/collection/immutable/Map;
  Code:
   Stack=5, Locals=3, Args_size=2
	getstatic	Field scala/collection/immutable/Map$.MODULE$:Lscala/collection/immutable/Map$;
	invokevirtual	Method scala/collection/immutable/Map$.newBuilder:()Lscala/collection/mutable/Builder;
	astore_2
	aload_2
	aload_0
	invokeinterface	InterfaceMethod scala/collection/generic/Growable.$plus$plus$eq:(Lscala/collection/Traversable;)Lscala/collection/generic/Growable;
	pop
	aload_2
	new	class scala/Tuple2
	dup
	aload_1
	invokevirtual	Method scala/Tuple2._1:()Ljava/lang/Object;
	aload_1
	invokevirtual	Method scala/Tuple2._2:()Ljava/lang/Object;
	invokespecial	Method scala/Tuple2."<init>":(Ljava/lang/Object;Ljava/lang/Object;)V
	invokeinterface	InterfaceMethod scala/collection/mutable/Builder.$plus$eq:(Ljava/lang/Object;)Lscala/collection/mutable/Builder;
	pop
	aload_2
	invokeinterface	InterfaceMethod scala/collection/mutable/Builder.result:()Ljava/lang/Object;
	checkcast	class scala/collection/immutable/Map
	areturn
  Labels:
  LocalVariableTable: 
   Start  Length  Slot  Name   Signature
   0      47      0    $this       Lscala/collection/immutable/DefaultMap;
   0      47      1    kv       Lscala/Tuple2;
   7      39      2    b       Lscala/collection/mutable/Builder;


public static scala.collection.immutable.Map $minus(scala.collection.immutable.DefaultMap, java.lang.Object);
  Signature: (Lscala/collection/immutable/DefaultMap;Ljava/lang/Object;)Lscala/collection/immutable/Map;
  Code:
   Stack=6, Locals=3, Args_size=2
	aload_0
	invokeinterface	InterfaceMethod scala/collection/MapLike.newBuilder:()Lscala/collection/mutable/Builder;
	astore_2
	aload_2
	aload_0
	new	class scala/collection/immutable/DefaultMap$$anonfun$$minus$1
	dup
	aload_0
	aload_1
	invokespecial	Method scala/collection/immutable/DefaultMap$$anonfun$$minus$1."<init>":(Lscala/collection/immutable/DefaultMap;Ljava/lang/Object;)V
	invokeinterface	InterfaceMethod scala/collection/TraversableLike.filter:(Lscala/Function1;)Ljava/lang/Object;
	checkcast	class scala/collection/Traversable
	invokeinterface	InterfaceMethod scala/collection/generic/Growable.$plus$plus$eq:(Lscala/collection/Traversable;)Lscala/collection/generic/Growable;
	pop
	aload_2
	invokeinterface	InterfaceMethod scala/collection/mutable/Builder.result:()Ljava/lang/Object;
	checkcast	class scala/collection/immutable/Map
	areturn
  Labels:
  LocalVariableTable: 
   Start  Length  Slot  Name   Signature
   0      42      0    $this       Lscala/collection/immutable/DefaultMap;
   0      42      1    key$1       Ljava/lang/Object;
   7      34      2    b       Lscala/collection/mutable/Builder;


public static void $init$(scala.collection.immutable.DefaultMap);
  Signature: (Lscala/collection/immutable/DefaultMap;)V
  Code:
   Stack=0, Locals=1, Args_size=1
	return
  Labels:
  LocalVariableTable: 
   Start  Length  Slot  Name   Signature
   0      1      0    $this       Lscala/collection/immutable/DefaultMap;


}

