Compiled from "HashSet.scala"
public final class scala.collection.immutable.HashSet$HashSetCollision1$$anonfun$updated0$1 extends scala.runtime.AbstractFunction1 implements java.io.Serializable
  SourceFile: "HashSet.scala"
  Scala: length = 0x
   
  InnerClass: 
   public HashSetCollision1=class scala/collection/immutable/HashSet$HashSetCollision1 of class scala/collection/immutable/HashSet
   public final $anonfun$updated0$1=class scala/collection/immutable/HashSet$HashSetCollision1$$anonfun$updated0$1 of class scala/collection/immutable/HashSet$HashSetCollision1
  minor version: 0
  major version: 49
  Constant pool:
Asciz	SourceFile;
Asciz	HashSet.scala;
Asciz	<clinit>;
Asciz	()V;
Asciz	Code;
Asciz	serialVersionUID;
Asciz	J;
Asciz	scala/collection/immutable/HashSet$HashSetCollision1$$anonfun$updated0$1;
class	scala/collection/immutable/HashSet$HashSetCollision1$$anonfun$updated0$1
NameAndType	serialVersionUID:J
Field	scala/collection/immutable/HashSet$HashSetCollision1$$anonfun$updated0$1.serialVersionUID:J
Asciz	$outer;
Asciz	Lscala/collection/immutable/HashSet$HashSetCollision1;;
Asciz	level$1;
Asciz	I;
Asciz	m$1;
Asciz	Lscala/runtime/ObjectRef;;
Asciz	apply;
Asciz	(Ljava/lang/Object;)V;
Asciz	LineNumberTable;
NameAndType	m$1:Lscala/runtime/ObjectRef;
Field	scala/collection/immutable/HashSet$HashSetCollision1$$anonfun$updated0$1.m$1:Lscala/runtime/ObjectRef;
Asciz	scala/runtime/ObjectRef;
class	scala/runtime/ObjectRef
Asciz	elem;
Asciz	Ljava/lang/Object;;
NameAndType	elem:Ljava/lang/Object;
Field	scala/runtime/ObjectRef.elem:Ljava/lang/Object;
Asciz	scala/collection/immutable/HashSet;
class	scala/collection/immutable/HashSet
NameAndType	$outer:Lscala/collection/immutable/HashSet$HashSetCollision1;
Field	scala/collection/immutable/HashSet$HashSetCollision1$$anonfun$updated0$1.$outer:Lscala/collection/immutable/HashSet$HashSetCollision1;
Asciz	scala/collection/immutable/HashSet$HashSetCollision1;
class	scala/collection/immutable/HashSet$HashSetCollision1
Asciz	hash;
Asciz	()I;
NameAndType	hash:()I
Method	scala/collection/immutable/HashSet$HashSetCollision1.hash:()I
NameAndType	level$1:I
Field	scala/collection/immutable/HashSet$HashSetCollision1$$anonfun$updated0$1.level$1:I
Asciz	updated0;
Asciz	(Ljava/lang/Object;II)Lscala/collection/immutable/HashSet;;
NameAndType	updated0:(Ljava/lang/Object;II)Lscala/collection/immutable/HashSet;
Method	scala/collection/immutable/HashSet.updated0:(Ljava/lang/Object;II)Lscala/collection/immutable/HashSet;
Asciz	this;
Asciz	Lscala/collection/immutable/HashSet$HashSetCollision1$$anonfun$updated0$1;;
Asciz	k;
Asciz	LocalVariableTable;
Asciz	(TA;)V;
Asciz	Signature;
Asciz	(Ljava/lang/Object;)Ljava/lang/Object;;
NameAndType	apply:(Ljava/lang/Object;)V
Method	scala/collection/immutable/HashSet$HashSetCollision1$$anonfun$updated0$1.apply:(Ljava/lang/Object;)V
Asciz	scala/runtime/BoxedUnit;
class	scala/runtime/BoxedUnit
Asciz	UNIT;
Asciz	Lscala/runtime/BoxedUnit;;
NameAndType	UNIT:Lscala/runtime/BoxedUnit;
Field	scala/runtime/BoxedUnit.UNIT:Lscala/runtime/BoxedUnit;
Asciz	v1;
Asciz	<init>;
Asciz	(Lscala/collection/immutable/HashSet$HashSetCollision1;ILscala/runtime/ObjectRef;)V;
Asciz	java/lang/NullPointerException;
class	java/lang/NullPointerException
NameAndType	"<init>":()V
Method	java/lang/NullPointerException."<init>":()V
Asciz	scala/runtime/AbstractFunction1;
class	scala/runtime/AbstractFunction1
Method	scala/runtime/AbstractFunction1."<init>":()V
Asciz	(Lscala/collection/immutable/HashSet$HashSetCollision1<TA;>;)V;
Asciz	Scala;
Asciz	InnerClasses;
Asciz	HashSetCollision1;
Asciz	$anonfun$updated0$1;
Asciz	java/io/Serializable;
class	java/io/Serializable

{
public static final long serialVersionUID;
  Signature: J

public final scala.collection.immutable.HashSet$HashSetCollision1 $outer;
  Signature: Lscala/collection/immutable/HashSet$HashSetCollision1;

public final int level$1;
  Signature: I

public final scala.runtime.ObjectRef m$1;
  Signature: Lscala/runtime/ObjectRef;

public static {};
  Signature: ()V
  Code:
   Stack=2, Locals=0, Args_size=0
	lconst_0
	putstatic	Field serialVersionUID:J
	return
  Labels:

public final void apply(java.lang.Object);
  Signature: (Ljava/lang/Object;)V
  Code:
   Stack=5, Locals=2, Args_size=2
	aload_0
	getfield	Field m$1:Lscala/runtime/ObjectRef;
	aload_0
	getfield	Field m$1:Lscala/runtime/ObjectRef;
	getfield	Field scala/runtime/ObjectRef.elem:Ljava/lang/Object;
	checkcast	class scala/collection/immutable/HashSet
	aload_1
	aload_0
	getfield	Field $outer:Lscala/collection/immutable/HashSet$HashSetCollision1;
	invokevirtual	Method scala/collection/immutable/HashSet$HashSetCollision1.hash:()I
	aload_0
	getfield	Field level$1:I
	invokevirtual	Method scala/collection/immutable/HashSet.updated0:(Ljava/lang/Object;II)Lscala/collection/immutable/HashSet;
	putfield	Field scala/runtime/ObjectRef.elem:Ljava/lang/Object;
	return
  Labels:
  LocalVariableTable: 
   Start  Length  Slot  Name   Signature
   0      33      0    this       Lscala/collection/immutable/HashSet$HashSetCollision1$$anonfun$updated0$1;
   0      33      1    k       Ljava/lang/Object;

  Signature: length = 0x2
   00 31 

public final java.lang.Object apply(java.lang.Object);
  Signature: (Ljava/lang/Object;)Ljava/lang/Object;
  Code:
   Stack=2, Locals=2, Args_size=2
	aload_0
	aload_1
	invokevirtual	Method apply:(Ljava/lang/Object;)V
	getstatic	Field scala/runtime/BoxedUnit.UNIT:Lscala/runtime/BoxedUnit;
	areturn
  Labels:
  LocalVariableTable: 
   Start  Length  Slot  Name   Signature
   0      9      0    this       Lscala/collection/immutable/HashSet$HashSetCollision1$$anonfun$updated0$1;
   0      9      1    v1       Ljava/lang/Object;


public scala.collection.immutable.HashSet$HashSetCollision1$$anonfun$updated0$1(scala.collection.immutable.HashSet$HashSetCollision1, int, scala.runtime.ObjectRef);
  Signature: (Lscala/collection/immutable/HashSet$HashSetCollision1;ILscala/runtime/ObjectRef;)V
  Code:
   Stack=2, Locals=4, Args_size=4
	aload_1
	ifnonnull	l1 // aload_0
	new	class java/lang/NullPointerException
	dup
	invokespecial	Method java/lang/NullPointerException."<init>":()V
	athrow
l1	aload_0
	aload_1
	putfield	Field $outer:Lscala/collection/immutable/HashSet$HashSetCollision1;
	aload_0
	iload_2
	putfield	Field level$1:I
	aload_0
	aload_3
	putfield	Field m$1:Lscala/runtime/ObjectRef;
	aload_0
	invokespecial	Method scala/runtime/AbstractFunction1."<init>":()V
	return
  Labels:
   	l1 = 12 // aload_0
  LocalVariableTable: 
   Start  Length  Slot  Name   Signature
   0      32      0    this       Lscala/collection/immutable/HashSet$HashSetCollision1$$anonfun$updated0$1;
   0      32      1    $outer       Lscala/collection/immutable/HashSet$HashSetCollision1;

  Signature: length = 0x2
   00 46 

}

