Compiled from "HashMap.scala"
public final class scala.collection.immutable.HashMap$SerializationProxy$$anonfun$readObject$1 extends scala.runtime.AbstractFunction1 implements java.io.Serializable
  SourceFile: "HashMap.scala"
  Scala: length = 0x
   
  InnerClass: 
   public SerializationProxy=class scala/collection/immutable/HashMap$SerializationProxy of class scala/collection/immutable/HashMap
   public final $anonfun$readObject$1=class scala/collection/immutable/HashMap$SerializationProxy$$anonfun$readObject$1 of class scala/collection/immutable/HashMap$SerializationProxy
  minor version: 0
  major version: 49
  Constant pool:
Asciz	SourceFile;
Asciz	HashMap.scala;
Asciz	<clinit>;
Asciz	()V;
Asciz	Code;
Asciz	serialVersionUID;
Asciz	J;
Asciz	scala/collection/immutable/HashMap$SerializationProxy$$anonfun$readObject$1;
class	scala/collection/immutable/HashMap$SerializationProxy$$anonfun$readObject$1
NameAndType	serialVersionUID:J
Field	scala/collection/immutable/HashMap$SerializationProxy$$anonfun$readObject$1.serialVersionUID:J
Asciz	$outer;
Asciz	Lscala/collection/immutable/HashMap$SerializationProxy;;
Asciz	in$1;
Asciz	Ljava/io/ObjectInputStream;;
Asciz	apply;
Asciz	(I)V;
Asciz	LineNumberTable;
NameAndType	in$1:Ljava/io/ObjectInputStream;
Field	scala/collection/immutable/HashMap$SerializationProxy$$anonfun$readObject$1.in$1:Ljava/io/ObjectInputStream;
Asciz	java/io/ObjectInputStream;
class	java/io/ObjectInputStream
Asciz	readObject;
Asciz	()Ljava/lang/Object;;
NameAndType	readObject:()Ljava/lang/Object;
Method	java/io/ObjectInputStream.readObject:()Ljava/lang/Object;
NameAndType	$outer:Lscala/collection/immutable/HashMap$SerializationProxy;
Field	scala/collection/immutable/HashMap$SerializationProxy$$anonfun$readObject$1.$outer:Lscala/collection/immutable/HashMap$SerializationProxy;
Asciz	scala/collection/immutable/HashMap$SerializationProxy;
class	scala/collection/immutable/HashMap$SerializationProxy
Asciz	scala$collection$immutable$HashMap$SerializationProxy$$orig;
Asciz	Lscala/collection/immutable/HashMap;;
NameAndType	scala$collection$immutable$HashMap$SerializationProxy$$orig:Lscala/collection/immutable/HashMap;
Field	scala/collection/immutable/HashMap$SerializationProxy.scala$collection$immutable$HashMap$SerializationProxy$$orig:Lscala/collection/immutable/HashMap;
Asciz	scala/collection/immutable/HashMap;
class	scala/collection/immutable/HashMap
Asciz	updated;
Asciz	(Ljava/lang/Object;Ljava/lang/Object;)Lscala/collection/immutable/HashMap;;
NameAndType	updated:(Ljava/lang/Object;Ljava/lang/Object;)Lscala/collection/immutable/HashMap;
Method	scala/collection/immutable/HashMap.updated:(Ljava/lang/Object;Ljava/lang/Object;)Lscala/collection/immutable/HashMap;
Asciz	this;
Asciz	Lscala/collection/immutable/HashMap$SerializationProxy$$anonfun$readObject$1;;
Asciz	i;
Asciz	I;
Asciz	key0;
Asciz	Ljava/lang/Object;;
Asciz	value0;
Asciz	LocalVariableTable;
Asciz	apply$mcVI$sp;
Asciz	()Lscala/collection/immutable/HashMap;;
NameAndType	scala$collection$immutable$HashMap$SerializationProxy$$orig:()Lscala/collection/immutable/HashMap;
Method	scala/collection/immutable/HashMap$SerializationProxy.scala$collection$immutable$HashMap$SerializationProxy$$orig:()Lscala/collection/immutable/HashMap;
Asciz	scala$collection$immutable$HashMap$SerializationProxy$$orig_$eq;
Asciz	(Lscala/collection/immutable/HashMap;)V;
NameAndType	scala$collection$immutable$HashMap$SerializationProxy$$orig_$eq:(Lscala/collection/immutable/HashMap;)V
Method	scala/collection/immutable/HashMap$SerializationProxy.scala$collection$immutable$HashMap$SerializationProxy$$orig_$eq:(Lscala/collection/immutable/HashMap;)V
Asciz	v1;
Asciz	key;
Asciz	value;
Asciz	(Ljava/lang/Object;)Ljava/lang/Object;;
Asciz	scala/runtime/BoxesRunTime;
class	scala/runtime/BoxesRunTime
Asciz	unboxToInt;
Asciz	(Ljava/lang/Object;)I;
NameAndType	unboxToInt:(Ljava/lang/Object;)I
Method	scala/runtime/BoxesRunTime.unboxToInt:(Ljava/lang/Object;)I
NameAndType	apply:(I)V
Method	scala/collection/immutable/HashMap$SerializationProxy$$anonfun$readObject$1.apply:(I)V
Asciz	scala/runtime/BoxedUnit;
class	scala/runtime/BoxedUnit
Asciz	UNIT;
Asciz	Lscala/runtime/BoxedUnit;;
NameAndType	UNIT:Lscala/runtime/BoxedUnit;
Field	scala/runtime/BoxedUnit.UNIT:Lscala/runtime/BoxedUnit;
Asciz	<init>;
Asciz	(Lscala/collection/immutable/HashMap$SerializationProxy;Ljava/io/ObjectInputStream;)V;
Asciz	java/lang/NullPointerException;
class	java/lang/NullPointerException
NameAndType	"<init>":()V
Method	java/lang/NullPointerException."<init>":()V
Asciz	scala/runtime/AbstractFunction1;
class	scala/runtime/AbstractFunction1
Method	scala/runtime/AbstractFunction1."<init>":()V
Asciz	(Lscala/collection/immutable/HashMap$SerializationProxy<TA;TB;>;)V;
Asciz	Signature;
Asciz	Scala;
Asciz	InnerClasses;
Asciz	SerializationProxy;
Asciz	$anonfun$readObject$1;
Asciz	java/io/Serializable;
class	java/io/Serializable

{
public static final long serialVersionUID;
  Signature: J

public final scala.collection.immutable.HashMap$SerializationProxy $outer;
  Signature: Lscala/collection/immutable/HashMap$SerializationProxy;

public final java.io.ObjectInputStream in$1;
  Signature: Ljava/io/ObjectInputStream;

public static {};
  Signature: ()V
  Code:
   Stack=2, Locals=0, Args_size=0
	lconst_0
	putstatic	Field serialVersionUID:J
	return
  Labels:

public final void apply(int);
  Signature: (I)V
  Code:
   Stack=4, Locals=7, Args_size=2
	aload_0
	getfield	Field in$1:Ljava/io/ObjectInputStream;
	invokevirtual	Method java/io/ObjectInputStream.readObject:()Ljava/lang/Object;
	astore_3
	aload_0
	getfield	Field in$1:Ljava/io/ObjectInputStream;
	invokevirtual	Method java/io/ObjectInputStream.readObject:()Ljava/lang/Object;
	astore	4
	aload_0
	getfield	Field $outer:Lscala/collection/immutable/HashMap$SerializationProxy;
	aload_0
	getfield	Field $outer:Lscala/collection/immutable/HashMap$SerializationProxy;
	astore_2
	aload_2
	getfield	Field scala/collection/immutable/HashMap$SerializationProxy.scala$collection$immutable$HashMap$SerializationProxy$$orig:Lscala/collection/immutable/HashMap;
	aload_3
	aload	4
	invokevirtual	Method scala/collection/immutable/HashMap.updated:(Ljava/lang/Object;Ljava/lang/Object;)Lscala/collection/immutable/HashMap;
	astore	6
	astore	5
	aload	5
	aload	6
	putfield	Field scala/collection/immutable/HashMap$SerializationProxy.scala$collection$immutable$HashMap$SerializationProxy$$orig:Lscala/collection/immutable/HashMap;
	return
  Labels:
  LocalVariableTable: 
   Start  Length  Slot  Name   Signature
   0      48      0    this       Lscala/collection/immutable/HashMap$SerializationProxy$$anonfun$readObject$1;
   0      48      1    i       I
   8      39      3    key0       Ljava/lang/Object;
   17      30      4    value0       Ljava/lang/Object;


public void apply$mcVI$sp(int);
  Signature: (I)V
  Code:
   Stack=4, Locals=4, Args_size=2
	aload_0
	getfield	Field in$1:Ljava/io/ObjectInputStream;
	invokevirtual	Method java/io/ObjectInputStream.readObject:()Ljava/lang/Object;
	astore_2
	aload_0
	getfield	Field in$1:Ljava/io/ObjectInputStream;
	invokevirtual	Method java/io/ObjectInputStream.readObject:()Ljava/lang/Object;
	astore_3
	aload_0
	getfield	Field $outer:Lscala/collection/immutable/HashMap$SerializationProxy;
	aload_0
	getfield	Field $outer:Lscala/collection/immutable/HashMap$SerializationProxy;
	invokevirtual	Method scala/collection/immutable/HashMap$SerializationProxy.scala$collection$immutable$HashMap$SerializationProxy$$orig:()Lscala/collection/immutable/HashMap;
	aload_2
	aload_3
	invokevirtual	Method scala/collection/immutable/HashMap.updated:(Ljava/lang/Object;Ljava/lang/Object;)Lscala/collection/immutable/HashMap;
	invokevirtual	Method scala/collection/immutable/HashMap$SerializationProxy.scala$collection$immutable$HashMap$SerializationProxy$$orig_$eq:(Lscala/collection/immutable/HashMap;)V
	return
  Labels:
  LocalVariableTable: 
   Start  Length  Slot  Name   Signature
   0      36      0    this       Lscala/collection/immutable/HashMap$SerializationProxy$$anonfun$readObject$1;
   0      36      1    v1       I
   8      27      2    key       Ljava/lang/Object;
   16      19      3    value       Ljava/lang/Object;


public final java.lang.Object apply(java.lang.Object);
  Signature: (Ljava/lang/Object;)Ljava/lang/Object;
  Code:
   Stack=2, Locals=2, Args_size=2
	aload_0
	aload_1
	invokestatic	Method scala/runtime/BoxesRunTime.unboxToInt:(Ljava/lang/Object;)I
	invokevirtual	Method apply:(I)V
	getstatic	Field scala/runtime/BoxedUnit.UNIT:Lscala/runtime/BoxedUnit;
	areturn
  Labels:
  LocalVariableTable: 
   Start  Length  Slot  Name   Signature
   0      12      0    this       Lscala/collection/immutable/HashMap$SerializationProxy$$anonfun$readObject$1;
   0      12      1    v1       Ljava/lang/Object;


public scala.collection.immutable.HashMap$SerializationProxy$$anonfun$readObject$1(scala.collection.immutable.HashMap$SerializationProxy, java.io.ObjectInputStream);
  Signature: (Lscala/collection/immutable/HashMap$SerializationProxy;Ljava/io/ObjectInputStream;)V
  Code:
   Stack=2, Locals=3, Args_size=3
	aload_1
	ifnonnull	l1 // aload_0
	new	class java/lang/NullPointerException
	dup
	invokespecial	Method java/lang/NullPointerException."<init>":()V
	athrow
l1	aload_0
	aload_1
	putfield	Field $outer:Lscala/collection/immutable/HashMap$SerializationProxy;
	aload_0
	aload_2
	putfield	Field in$1:Ljava/io/ObjectInputStream;
	aload_0
	invokespecial	Method scala/runtime/AbstractFunction1."<init>":()V
	return
  Labels:
   	l1 = 12 // aload_0
  LocalVariableTable: 
   Start  Length  Slot  Name   Signature
   0      27      0    this       Lscala/collection/immutable/HashMap$SerializationProxy$$anonfun$readObject$1;
   0      27      1    $outer       Lscala/collection/immutable/HashMap$SerializationProxy;

  Signature: length = 0x2
   00 54 

}

