Compiled from "HashMap.scala"
public final class scala.collection.immutable.HashMap$HashTrieMap$$anonfun$iterator$1 extends scala.runtime.AbstractFunction1 implements java.io.Serializable
  SourceFile: "HashMap.scala"
  Scala: length = 0x
   
  InnerClass: 
   public HashTrieMap=class scala/collection/immutable/HashMap$HashTrieMap of class scala/collection/immutable/HashMap
   public final $anonfun$iterator$1=class scala/collection/immutable/HashMap$HashTrieMap$$anonfun$iterator$1 of class scala/collection/immutable/HashMap$HashTrieMap
   public final $anonfun$apply$1=class scala/collection/immutable/HashMap$HashTrieMap$$anonfun$iterator$1$$anonfun$apply$1 of class scala/collection/immutable/HashMap$HashTrieMap$$anonfun$iterator$1
  minor version: 0
  major version: 49
  Constant pool:
Asciz	SourceFile;
Asciz	HashMap.scala;
Asciz	<clinit>;
Asciz	()V;
Asciz	Code;
Asciz	serialVersionUID;
Asciz	J;
Asciz	scala/collection/immutable/HashMap$HashTrieMap$$anonfun$iterator$1;
class	scala/collection/immutable/HashMap$HashTrieMap$$anonfun$iterator$1
NameAndType	serialVersionUID:J
Field	scala/collection/immutable/HashMap$HashTrieMap$$anonfun$iterator$1.serialVersionUID:J
Asciz	it$1;
Asciz	Lscala/runtime/ObjectRef;;
Asciz	apply;
Asciz	(Lscala/collection/immutable/Map;)V;
Asciz	LineNumberTable;
NameAndType	it$1:Lscala/runtime/ObjectRef;
Field	scala/collection/immutable/HashMap$HashTrieMap$$anonfun$iterator$1.it$1:Lscala/runtime/ObjectRef;
Asciz	scala/runtime/ObjectRef;
class	scala/runtime/ObjectRef
Asciz	elem;
Asciz	Ljava/lang/Object;;
NameAndType	elem:Ljava/lang/Object;
Field	scala/runtime/ObjectRef.elem:Ljava/lang/Object;
Asciz	scala/collection/Iterator;
class	scala/collection/Iterator
Asciz	scala/collection/immutable/HashMap$HashTrieMap$$anonfun$iterator$1$$anonfun$apply$1;
class	scala/collection/immutable/HashMap$HashTrieMap$$anonfun$iterator$1$$anonfun$apply$1
Asciz	<init>;
Asciz	(Lscala/collection/immutable/HashMap$HashTrieMap$$anonfun$iterator$1;Lscala/collection/immutable/Map;)V;
NameAndType	"<init>":(Lscala/collection/immutable/HashMap$HashTrieMap$$anonfun$iterator$1;Lscala/collection/immutable/Map;)V
Method	scala/collection/immutable/HashMap$HashTrieMap$$anonfun$iterator$1$$anonfun$apply$1."<init>":(Lscala/collection/immutable/HashMap$HashTrieMap$$anonfun$iterator$1;Lscala/collection/immutable/Map;)V
Asciz	$plus$plus;
Asciz	(Lscala/Function0;)Lscala/collection/Iterator;;
NameAndType	$plus$plus:(Lscala/Function0;)Lscala/collection/Iterator;
InterfaceMethod	scala/collection/Iterator.$plus$plus:(Lscala/Function0;)Lscala/collection/Iterator;
Asciz	this;
Asciz	Lscala/collection/immutable/HashMap$HashTrieMap$$anonfun$iterator$1;;
Asciz	m$2;
Asciz	Lscala/collection/immutable/Map;;
Asciz	LocalVariableTable;
Asciz	(Lscala/collection/immutable/Map<**>;)V;
Asciz	Signature;
Asciz	(Ljava/lang/Object;)Ljava/lang/Object;;
Asciz	scala/collection/immutable/Map;
class	scala/collection/immutable/Map
NameAndType	apply:(Lscala/collection/immutable/Map;)V
Method	scala/collection/immutable/HashMap$HashTrieMap$$anonfun$iterator$1.apply:(Lscala/collection/immutable/Map;)V
Asciz	scala/runtime/BoxedUnit;
class	scala/runtime/BoxedUnit
Asciz	UNIT;
Asciz	Lscala/runtime/BoxedUnit;;
NameAndType	UNIT:Lscala/runtime/BoxedUnit;
Field	scala/runtime/BoxedUnit.UNIT:Lscala/runtime/BoxedUnit;
Asciz	v1;
Asciz	(Lscala/collection/immutable/HashMap$HashTrieMap;Lscala/runtime/ObjectRef;)V;
Asciz	scala/runtime/AbstractFunction1;
class	scala/runtime/AbstractFunction1
NameAndType	"<init>":()V
Method	scala/runtime/AbstractFunction1."<init>":()V
Asciz	$outer;
Asciz	Lscala/collection/immutable/HashMap$HashTrieMap;;
Asciz	(Lscala/collection/immutable/HashMap$HashTrieMap<TA;TB;>;)V;
Asciz	Scala;
Asciz	InnerClasses;
Asciz	scala/collection/immutable/HashMap$HashTrieMap;
class	scala/collection/immutable/HashMap$HashTrieMap
Asciz	scala/collection/immutable/HashMap;
class	scala/collection/immutable/HashMap
Asciz	HashTrieMap;
Asciz	$anonfun$iterator$1;
Asciz	$anonfun$apply$1;
Asciz	java/io/Serializable;
class	java/io/Serializable

{
public static final long serialVersionUID;
  Signature: J

private final scala.runtime.ObjectRef it$1;
  Signature: Lscala/runtime/ObjectRef;

public static {};
  Signature: ()V
  Code:
   Stack=2, Locals=0, Args_size=0
	lconst_0
	putstatic	Field serialVersionUID:J
	return
  Labels:

public final void apply(scala.collection.immutable.Map);
  Signature: (Lscala/collection/immutable/Map;)V
  Code:
   Stack=6, Locals=2, Args_size=2
	aload_0
	getfield	Field it$1:Lscala/runtime/ObjectRef;
	aload_0
	getfield	Field it$1:Lscala/runtime/ObjectRef;
	getfield	Field scala/runtime/ObjectRef.elem:Ljava/lang/Object;
	checkcast	class scala/collection/Iterator
	new	class scala/collection/immutable/HashMap$HashTrieMap$$anonfun$iterator$1$$anonfun$apply$1
	dup
	aload_0
	aload_1
	invokespecial	Method scala/collection/immutable/HashMap$HashTrieMap$$anonfun$iterator$1$$anonfun$apply$1."<init>":(Lscala/collection/immutable/HashMap$HashTrieMap$$anonfun$iterator$1;Lscala/collection/immutable/Map;)V
	invokeinterface	InterfaceMethod scala/collection/Iterator.$plus$plus:(Lscala/Function0;)Lscala/collection/Iterator;
	putfield	Field scala/runtime/ObjectRef.elem:Ljava/lang/Object;
	return
  Labels:
  LocalVariableTable: 
   Start  Length  Slot  Name   Signature
   0      32      0    this       Lscala/collection/immutable/HashMap$HashTrieMap$$anonfun$iterator$1;
   0      32      1    m$2       Lscala/collection/immutable/Map;

  Signature: length = 0x2
   00 2A 

public final java.lang.Object apply(java.lang.Object);
  Signature: (Ljava/lang/Object;)Ljava/lang/Object;
  Code:
   Stack=2, Locals=2, Args_size=2
	aload_0
	aload_1
	checkcast	class scala/collection/immutable/Map
	invokevirtual	Method apply:(Lscala/collection/immutable/Map;)V
	getstatic	Field scala/runtime/BoxedUnit.UNIT:Lscala/runtime/BoxedUnit;
	areturn
  Labels:
  LocalVariableTable: 
   Start  Length  Slot  Name   Signature
   0      12      0    this       Lscala/collection/immutable/HashMap$HashTrieMap$$anonfun$iterator$1;
   0      12      1    v1       Ljava/lang/Object;


public scala.collection.immutable.HashMap$HashTrieMap$$anonfun$iterator$1(scala.collection.immutable.HashMap$HashTrieMap, scala.runtime.ObjectRef);
  Signature: (Lscala/collection/immutable/HashMap$HashTrieMap;Lscala/runtime/ObjectRef;)V
  Code:
   Stack=2, Locals=3, Args_size=3
	aload_0
	aload_2
	putfield	Field it$1:Lscala/runtime/ObjectRef;
	aload_0
	invokespecial	Method scala/runtime/AbstractFunction1."<init>":()V
	return
  Labels:
  LocalVariableTable: 
   Start  Length  Slot  Name   Signature
   0      10      0    this       Lscala/collection/immutable/HashMap$HashTrieMap$$anonfun$iterator$1;
   0      10      1    $outer       Lscala/collection/immutable/HashMap$HashTrieMap;

  Signature: length = 0x2
   00 3F 

}

