Compiled from "HashSet.scala"
public final class scala.collection.immutable.HashSet$HashTrieSet$$anonfun$writeObject$1 extends scala.runtime.AbstractFunction1 implements java.io.Serializable
  SourceFile: "HashSet.scala"
  Scala: length = 0x
   
  InnerClass: 
   public HashTrieSet=class scala/collection/immutable/HashSet$HashTrieSet of class scala/collection/immutable/HashSet
   public final $anonfun$writeObject$1=class scala/collection/immutable/HashSet$HashTrieSet$$anonfun$writeObject$1 of class scala/collection/immutable/HashSet$HashTrieSet
  minor version: 0
  major version: 49
  Constant pool:
Asciz	SourceFile;
Asciz	HashSet.scala;
Asciz	<clinit>;
Asciz	()V;
Asciz	Code;
Asciz	serialVersionUID;
Asciz	J;
Asciz	scala/collection/immutable/HashSet$HashTrieSet$$anonfun$writeObject$1;
class	scala/collection/immutable/HashSet$HashTrieSet$$anonfun$writeObject$1
NameAndType	serialVersionUID:J
Field	scala/collection/immutable/HashSet$HashTrieSet$$anonfun$writeObject$1.serialVersionUID:J
Asciz	out$1;
Asciz	Ljava/io/ObjectOutputStream;;
Asciz	apply;
Asciz	(Ljava/lang/Object;)V;
Asciz	LineNumberTable;
NameAndType	out$1:Ljava/io/ObjectOutputStream;
Field	scala/collection/immutable/HashSet$HashTrieSet$$anonfun$writeObject$1.out$1:Ljava/io/ObjectOutputStream;
Asciz	java/io/ObjectOutputStream;
class	java/io/ObjectOutputStream
Asciz	writeObject;
NameAndType	writeObject:(Ljava/lang/Object;)V
Method	java/io/ObjectOutputStream.writeObject:(Ljava/lang/Object;)V
Asciz	this;
Asciz	Lscala/collection/immutable/HashSet$HashTrieSet$$anonfun$writeObject$1;;
Asciz	e;
Asciz	Ljava/lang/Object;;
Asciz	LocalVariableTable;
Asciz	(TA;)V;
Asciz	Signature;
Asciz	(Ljava/lang/Object;)Ljava/lang/Object;;
NameAndType	apply:(Ljava/lang/Object;)V
Method	scala/collection/immutable/HashSet$HashTrieSet$$anonfun$writeObject$1.apply:(Ljava/lang/Object;)V
Asciz	scala/runtime/BoxedUnit;
class	scala/runtime/BoxedUnit
Asciz	UNIT;
Asciz	Lscala/runtime/BoxedUnit;;
NameAndType	UNIT:Lscala/runtime/BoxedUnit;
Field	scala/runtime/BoxedUnit.UNIT:Lscala/runtime/BoxedUnit;
Asciz	v1;
Asciz	<init>;
Asciz	(Lscala/collection/immutable/HashSet$HashTrieSet;Ljava/io/ObjectOutputStream;)V;
Asciz	scala/runtime/AbstractFunction1;
class	scala/runtime/AbstractFunction1
NameAndType	"<init>":()V
Method	scala/runtime/AbstractFunction1."<init>":()V
Asciz	$outer;
Asciz	Lscala/collection/immutable/HashSet$HashTrieSet;;
Asciz	(Lscala/collection/immutable/HashSet$HashTrieSet<TA;>;)V;
Asciz	Scala;
Asciz	InnerClasses;
Asciz	scala/collection/immutable/HashSet$HashTrieSet;
class	scala/collection/immutable/HashSet$HashTrieSet
Asciz	scala/collection/immutable/HashSet;
class	scala/collection/immutable/HashSet
Asciz	HashTrieSet;
Asciz	$anonfun$writeObject$1;
Asciz	java/io/Serializable;
class	java/io/Serializable

{
public static final long serialVersionUID;
  Signature: J

public final java.io.ObjectOutputStream out$1;
  Signature: Ljava/io/ObjectOutputStream;

public static {};
  Signature: ()V
  Code:
   Stack=2, Locals=0, Args_size=0
	lconst_0
	putstatic	Field serialVersionUID:J
	return
  Labels:

public final void apply(java.lang.Object);
  Signature: (Ljava/lang/Object;)V
  Code:
   Stack=2, Locals=2, Args_size=2
	aload_0
	getfield	Field out$1:Ljava/io/ObjectOutputStream;
	aload_1
	invokevirtual	Method java/io/ObjectOutputStream.writeObject:(Ljava/lang/Object;)V
	return
  Labels:
  LocalVariableTable: 
   Start  Length  Slot  Name   Signature
   0      9      0    this       Lscala/collection/immutable/HashSet$HashTrieSet$$anonfun$writeObject$1;
   0      9      1    e       Ljava/lang/Object;

  Signature: length = 0x2
   00 1D 

public final java.lang.Object apply(java.lang.Object);
  Signature: (Ljava/lang/Object;)Ljava/lang/Object;
  Code:
   Stack=2, Locals=2, Args_size=2
	aload_0
	aload_1
	invokevirtual	Method apply:(Ljava/lang/Object;)V
	getstatic	Field scala/runtime/BoxedUnit.UNIT:Lscala/runtime/BoxedUnit;
	areturn
  Labels:
  LocalVariableTable: 
   Start  Length  Slot  Name   Signature
   0      9      0    this       Lscala/collection/immutable/HashSet$HashTrieSet$$anonfun$writeObject$1;
   0      9      1    v1       Ljava/lang/Object;


public scala.collection.immutable.HashSet$HashTrieSet$$anonfun$writeObject$1(scala.collection.immutable.HashSet$HashTrieSet, java.io.ObjectOutputStream);
  Signature: (Lscala/collection/immutable/HashSet$HashTrieSet;Ljava/io/ObjectOutputStream;)V
  Code:
   Stack=2, Locals=3, Args_size=3
	aload_0
	aload_2
	putfield	Field out$1:Ljava/io/ObjectOutputStream;
	aload_0
	invokespecial	Method scala/runtime/AbstractFunction1."<init>":()V
	return
  Labels:
  LocalVariableTable: 
   Start  Length  Slot  Name   Signature
   0      10      0    this       Lscala/collection/immutable/HashSet$HashTrieSet$$anonfun$writeObject$1;
   0      10      1    $outer       Lscala/collection/immutable/HashSet$HashTrieSet;

  Signature: length = 0x2
   00 31 

}

