Compiled from "HashSet.scala"
public final class scala.collection.immutable.HashSet$HashTrieSet$$anon$1 extends java.lang.Object implements scala.collection.Iterator
  InnerClass: 
   public HashSet1=class scala/collection/immutable/HashSet$HashSet1 of class scala/collection/immutable/HashSet
   public HashTrieSet=class scala/collection/immutable/HashSet$HashTrieSet of class scala/collection/immutable/HashSet
   public final $anon$1=class scala/collection/immutable/HashSet$HashTrieSet$$anon$1 of class scala/collection/immutable/HashSet$HashTrieSet
  Scala: length = 0x
   
  Signature: length = 0x2
   00 FFFFFF9B 
  SourceFile: "HashSet.scala"
  minor version: 0
  major version: 49
  Constant pool:
int	6;
class	"[Lscala/collection/immutable/HashSet;"
class	java/lang/Object
class	scala/collection/Iterator
class	scala/collection/Iterator$class
class	scala/collection/TraversableOnce$class
class	scala/collection/immutable/HashSet
class	scala/collection/immutable/HashSet$HashSet1
class	scala/collection/immutable/HashSet$HashTrieSet
class	scala/collection/immutable/HashSet$HashTrieSet$$anon$1
Field	scala/collection/immutable/HashSet$HashTrieSet.scala$collection$immutable$HashSet$HashTrieSet$$elems:[Lscala/collection/immutable/HashSet;
Field	scala/collection/immutable/HashSet$HashTrieSet$$anon$1.arrayD:[Lscala/collection/immutable/HashSet;
Field	scala/collection/immutable/HashSet$HashTrieSet$$anon$1.arrayStack:[[Lscala/collection/immutable/HashSet;
Field	scala/collection/immutable/HashSet$HashTrieSet$$anon$1.depth:I
Field	scala/collection/immutable/HashSet$HashTrieSet$$anon$1.posD:I
Field	scala/collection/immutable/HashSet$HashTrieSet$$anon$1.posStack:[I
Field	scala/collection/immutable/HashSet$HashTrieSet$$anon$1.subIter:Lscala/collection/Iterator;
Method	java/lang/Object."<init>":()V
Method	scala/collection/Iterator$class.$init$:(Lscala/collection/Iterator;)V
Method	scala/collection/Iterator$class.$plus$plus:(Lscala/collection/Iterator;Lscala/Function0;)Lscala/collection/Iterator;
Method	scala/collection/Iterator$class.copyToArray:(Lscala/collection/Iterator;Ljava/lang/Object;II)V
Method	scala/collection/Iterator$class.drop:(Lscala/collection/Iterator;I)Lscala/collection/Iterator;
Method	scala/collection/Iterator$class.exists:(Lscala/collection/Iterator;Lscala/Function1;)Z
Method	scala/collection/Iterator$class.forall:(Lscala/collection/Iterator;Lscala/Function1;)Z
Method	scala/collection/Iterator$class.foreach:(Lscala/collection/Iterator;Lscala/Function1;)V
Method	scala/collection/Iterator$class.isEmpty:(Lscala/collection/Iterator;)Z
Method	scala/collection/Iterator$class.isTraversableAgain:(Lscala/collection/Iterator;)Z
Method	scala/collection/Iterator$class.length:(Lscala/collection/Iterator;)I
Method	scala/collection/Iterator$class.toString:(Lscala/collection/Iterator;)Ljava/lang/String;
Method	scala/collection/TraversableOnce$class.$div$colon:(Lscala/collection/TraversableOnce;Ljava/lang/Object;Lscala/Function2;)Ljava/lang/Object;
Method	scala/collection/TraversableOnce$class.$init$:(Lscala/collection/TraversableOnce;)V
Method	scala/collection/TraversableOnce$class.addString:(Lscala/collection/TraversableOnce;Lscala/collection/mutable/StringBuilder;Ljava/lang/String;Ljava/lang/String;Ljava/lang/String;)Lscala/collection/mutable/StringBuilder;
Method	scala/collection/TraversableOnce$class.copyToArray:(Lscala/collection/TraversableOnce;Ljava/lang/Object;I)V
Method	scala/collection/TraversableOnce$class.foldLeft:(Lscala/collection/TraversableOnce;Ljava/lang/Object;Lscala/Function2;)Ljava/lang/Object;
Method	scala/collection/TraversableOnce$class.mkString:(Lscala/collection/TraversableOnce;)Ljava/lang/String;
Method	scala/collection/TraversableOnce$class.mkString:(Lscala/collection/TraversableOnce;Ljava/lang/String;)Ljava/lang/String;
Method	scala/collection/TraversableOnce$class.mkString:(Lscala/collection/TraversableOnce;Ljava/lang/String;Ljava/lang/String;Ljava/lang/String;)Ljava/lang/String;
Method	scala/collection/TraversableOnce$class.nonEmpty:(Lscala/collection/TraversableOnce;)Z
Method	scala/collection/TraversableOnce$class.size:(Lscala/collection/TraversableOnce;)I
Method	scala/collection/TraversableOnce$class.sum:(Lscala/collection/TraversableOnce;Lscala/math/Numeric;)Ljava/lang/Object;
Method	scala/collection/TraversableOnce$class.toArray:(Lscala/collection/TraversableOnce;Lscala/reflect/ClassManifest;)Ljava/lang/Object;
Method	scala/collection/TraversableOnce$class.toList:(Lscala/collection/TraversableOnce;)Lscala/collection/immutable/List;
Method	scala/collection/TraversableOnce$class.toSet:(Lscala/collection/TraversableOnce;)Lscala/collection/immutable/Set;
Method	scala/collection/TraversableOnce$class.toStream:(Lscala/collection/TraversableOnce;)Lscala/collection/immutable/Stream;
Method	scala/collection/immutable/HashSet.iterator:()Lscala/collection/Iterator;
Method	scala/collection/immutable/HashSet$HashSet1.key:()Ljava/lang/Object;
Method	scala/collection/immutable/HashSet$HashTrieSet.scala$collection$immutable$HashSet$HashTrieSet$$elems:()[Lscala/collection/immutable/HashSet;
Method	scala/collection/immutable/HashSet$HashTrieSet$$anon$1.next0:([Lscala/collection/immutable/HashSet;I)Ljava/lang/Object;
InterfaceMethod	scala/collection/Iterator.hasNext:()Z
InterfaceMethod	scala/collection/Iterator.next:()Ljava/lang/Object;
NameAndType	$div$colon:(Lscala/collection/TraversableOnce;Ljava/lang/Object;Lscala/Function2;)Ljava/lang/Object;
NameAndType	$init$:(Lscala/collection/Iterator;)V
NameAndType	$init$:(Lscala/collection/TraversableOnce;)V
NameAndType	$plus$plus:(Lscala/collection/Iterator;Lscala/Function0;)Lscala/collection/Iterator;
NameAndType	"<init>":()V
NameAndType	addString:(Lscala/collection/TraversableOnce;Lscala/collection/mutable/StringBuilder;Ljava/lang/String;Ljava/lang/String;Ljava/lang/String;)Lscala/collection/mutable/StringBuilder;
NameAndType	arrayD:[Lscala/collection/immutable/HashSet;
NameAndType	arrayStack:[[Lscala/collection/immutable/HashSet;
NameAndType	copyToArray:(Lscala/collection/Iterator;Ljava/lang/Object;II)V
NameAndType	copyToArray:(Lscala/collection/TraversableOnce;Ljava/lang/Object;I)V
NameAndType	depth:I
NameAndType	drop:(Lscala/collection/Iterator;I)Lscala/collection/Iterator;
NameAndType	exists:(Lscala/collection/Iterator;Lscala/Function1;)Z
NameAndType	foldLeft:(Lscala/collection/TraversableOnce;Ljava/lang/Object;Lscala/Function2;)Ljava/lang/Object;
NameAndType	forall:(Lscala/collection/Iterator;Lscala/Function1;)Z
NameAndType	foreach:(Lscala/collection/Iterator;Lscala/Function1;)V
NameAndType	hasNext:()Z
NameAndType	isEmpty:(Lscala/collection/Iterator;)Z
NameAndType	isTraversableAgain:(Lscala/collection/Iterator;)Z
NameAndType	iterator:()Lscala/collection/Iterator;
NameAndType	key:()Ljava/lang/Object;
NameAndType	length:(Lscala/collection/Iterator;)I
NameAndType	mkString:(Lscala/collection/TraversableOnce;)Ljava/lang/String;
NameAndType	mkString:(Lscala/collection/TraversableOnce;Ljava/lang/String;)Ljava/lang/String;
NameAndType	mkString:(Lscala/collection/TraversableOnce;Ljava/lang/String;Ljava/lang/String;Ljava/lang/String;)Ljava/lang/String;
NameAndType	next:()Ljava/lang/Object;
NameAndType	next0:([Lscala/collection/immutable/HashSet;I)Ljava/lang/Object;
NameAndType	nonEmpty:(Lscala/collection/TraversableOnce;)Z
NameAndType	posD:I
NameAndType	posStack:[I
NameAndType	scala$collection$immutable$HashSet$HashTrieSet$$elems:()[Lscala/collection/immutable/HashSet;
NameAndType	scala$collection$immutable$HashSet$HashTrieSet$$elems:[Lscala/collection/immutable/HashSet;
NameAndType	size:(Lscala/collection/TraversableOnce;)I
NameAndType	subIter:Lscala/collection/Iterator;
NameAndType	sum:(Lscala/collection/TraversableOnce;Lscala/math/Numeric;)Ljava/lang/Object;
NameAndType	toArray:(Lscala/collection/TraversableOnce;Lscala/reflect/ClassManifest;)Ljava/lang/Object;
NameAndType	toList:(Lscala/collection/TraversableOnce;)Lscala/collection/immutable/List;
NameAndType	toSet:(Lscala/collection/TraversableOnce;)Lscala/collection/immutable/Set;
NameAndType	toStream:(Lscala/collection/TraversableOnce;)Lscala/collection/immutable/Stream;
NameAndType	toString:(Lscala/collection/Iterator;)Ljava/lang/String;
Asciz	$anon$1;
Asciz	$div$colon;
Asciz	$init$;
Asciz	$outer;
Asciz	$plus$plus;
Asciz	()I;
Asciz	()Ljava/lang/Object;;
Asciz	()Ljava/lang/String;;
Asciz	()Lscala/collection/Iterator;;
Asciz	()Lscala/collection/immutable/List;;
Asciz	()Lscala/collection/immutable/Set;;
Asciz	()Lscala/collection/immutable/Stream;;
Asciz	()TA;;
Asciz	()V;
Asciz	()Z;
Asciz	()[Lscala/collection/immutable/HashSet;;
Asciz	(I)Lscala/collection/Iterator;;
Asciz	(Ljava/lang/Object;I)V;
Asciz	(Ljava/lang/Object;II)V;
Asciz	(Ljava/lang/Object;Lscala/Function2;)Ljava/lang/Object;;
Asciz	(Ljava/lang/String;)Ljava/lang/String;;
Asciz	(Ljava/lang/String;Ljava/lang/String;Ljava/lang/String;)Ljava/lang/String;;
Asciz	(Lscala/Function0;)Lscala/collection/Iterator;;
Asciz	(Lscala/Function1;)V;
Asciz	(Lscala/Function1;)Z;
Asciz	(Lscala/collection/Iterator;)I;
Asciz	(Lscala/collection/Iterator;)Ljava/lang/String;;
Asciz	(Lscala/collection/Iterator;)V;
Asciz	(Lscala/collection/Iterator;)Z;
Asciz	(Lscala/collection/Iterator;I)Lscala/collection/Iterator;;
Asciz	(Lscala/collection/Iterator;Ljava/lang/Object;II)V;
Asciz	(Lscala/collection/Iterator;Lscala/Function0;)Lscala/collection/Iterator;;
Asciz	(Lscala/collection/Iterator;Lscala/Function1;)V;
Asciz	(Lscala/collection/Iterator;Lscala/Function1;)Z;
Asciz	(Lscala/collection/TraversableOnce;)I;
Asciz	(Lscala/collection/TraversableOnce;)Ljava/lang/String;;
Asciz	(Lscala/collection/TraversableOnce;)Lscala/collection/immutable/List;;
Asciz	(Lscala/collection/TraversableOnce;)Lscala/collection/immutable/Set;;
Asciz	(Lscala/collection/TraversableOnce;)Lscala/collection/immutable/Stream;;
Asciz	(Lscala/collection/TraversableOnce;)V;
Asciz	(Lscala/collection/TraversableOnce;)Z;
Asciz	(Lscala/collection/TraversableOnce;Ljava/lang/Object;I)V;
Asciz	(Lscala/collection/TraversableOnce;Ljava/lang/Object;Lscala/Function2;)Ljava/lang/Object;;
Asciz	(Lscala/collection/TraversableOnce;Ljava/lang/String;)Ljava/lang/String;;
Asciz	(Lscala/collection/TraversableOnce;Ljava/lang/String;Ljava/lang/String;Ljava/lang/String;)Ljava/lang/String;;
Asciz	(Lscala/collection/TraversableOnce;Lscala/collection/mutable/StringBuilder;Ljava/lang/String;Ljava/lang/String;Ljava/lang/String;)Lscala/collection/mutable/StringBuilder;;
Asciz	(Lscala/collection/TraversableOnce;Lscala/math/Numeric;)Ljava/lang/Object;;
Asciz	(Lscala/collection/TraversableOnce;Lscala/reflect/ClassManifest;)Ljava/lang/Object;;
Asciz	(Lscala/collection/immutable/HashSet$HashTrieSet;)V;
Asciz	(Lscala/collection/immutable/HashSet$HashTrieSet<TA;>;)V;
Asciz	(Lscala/collection/mutable/StringBuilder;Ljava/lang/String;Ljava/lang/String;Ljava/lang/String;)Lscala/collection/mutable/StringBuilder;;
Asciz	(Lscala/math/Numeric;)Ljava/lang/Object;;
Asciz	(Lscala/reflect/ClassManifest;)Ljava/lang/Object;;
Asciz	([Lscala/collection/immutable/HashSet;I)Ljava/lang/Object;;
Asciz	([Lscala/collection/immutable/HashSet<TA;>;I)TA;;
Asciz	<init>;
Asciz	Code;
Asciz	HashSet.scala;
Asciz	HashSet1;
Asciz	HashTrieSet;
Asciz	I;
Asciz	InnerClasses;
Asciz	LineNumberTable;
Asciz	Ljava/lang/Object;;
Asciz	Ljava/lang/Object;Lscala/collection/Iterator<TA;>;;
Asciz	Ljava/lang/String;;
Asciz	LocalVariableTable;
Asciz	Lscala/Function0;;
Asciz	Lscala/Function1;;
Asciz	Lscala/Function2;;
Asciz	Lscala/collection/Iterator;;
Asciz	Lscala/collection/Iterator<TA;>;;
Asciz	Lscala/collection/immutable/HashSet$HashTrieSet$$anon$1;;
Asciz	Lscala/collection/immutable/HashSet$HashTrieSet;;
Asciz	Lscala/collection/immutable/HashSet;;
Asciz	Lscala/collection/mutable/StringBuilder;;
Asciz	Lscala/math/Numeric;;
Asciz	Lscala/reflect/ClassManifest;;
Asciz	Scala;
Asciz	Signature;
Asciz	SourceFile;
Asciz	[I;
Asciz	[Lscala/collection/immutable/HashSet;;
Asciz	[Lscala/collection/immutable/HashSet<TA;>;;
Asciz	[[Lscala/collection/immutable/HashSet;;
Asciz	[[Lscala/collection/immutable/HashSet<TA;>;;
Asciz	addString;
Asciz	arrayD;
Asciz	arrayStack;
Asciz	b;
Asciz	copyToArray;
Asciz	depth;
Asciz	drop;
Asciz	el;
Asciz	elems;
Asciz	end;
Asciz	evidence$1;
Asciz	exists;
Asciz	f;
Asciz	foldLeft;
Asciz	forall;
Asciz	foreach;
Asciz	hasNext;
Asciz	i;
Asciz	isEmpty;
Asciz	isTraversableAgain;
Asciz	iterator;
Asciz	java/lang/Object;
Asciz	key;
Asciz	len;
Asciz	length;
Asciz	mkString;
Asciz	n;
Asciz	next;
Asciz	next0;
Asciz	nonEmpty;
Asciz	num;
Asciz	op;
Asciz	p;
Asciz	posD;
Asciz	posStack;
Asciz	scala$collection$immutable$HashSet$HashTrieSet$$elems;
Asciz	scala/collection/Iterator;
Asciz	scala/collection/Iterator$class;
Asciz	scala/collection/TraversableOnce$class;
Asciz	scala/collection/immutable/HashSet;
Asciz	scala/collection/immutable/HashSet$HashSet1;
Asciz	scala/collection/immutable/HashSet$HashTrieSet;
Asciz	scala/collection/immutable/HashSet$HashTrieSet$$anon$1;
Asciz	sep;
Asciz	size;
Asciz	start;
Asciz	subIter;
Asciz	sum;
Asciz	temp1;
Asciz	temp2;
Asciz	that;
Asciz	this;
Asciz	toArray;
Asciz	toList;
Asciz	toSet;
Asciz	toStream;
Asciz	toString;
Asciz	xs;
Asciz	z;

{
private int depth;
  Signature: I

private scala.collection.immutable.HashSet[][] arrayStack;
  Signature: [[Lscala/collection/immutable/HashSet;
  Signature: length = 0x2
   00 FFFFFFB0 

private int[] posStack;
  Signature: [I

private scala.collection.immutable.HashSet[] arrayD;
  Signature: [Lscala/collection/immutable/HashSet;
  Signature: length = 0x2
   00 FFFFFFAE 

private int posD;
  Signature: I

private scala.collection.Iterator subIter;
  Signature: Lscala/collection/Iterator;
  Signature: length = 0x2
   00 FFFFFFA2 

public boolean isEmpty();
  Signature: ()Z
  Code:
   Stack=1, Locals=1, Args_size=1
	aload_0
	invokestatic	Method scala/collection/Iterator$class.isEmpty:(Lscala/collection/Iterator;)Z
	ireturn
  Labels:

public boolean isTraversableAgain();
  Signature: ()Z
  Code:
   Stack=1, Locals=1, Args_size=1
	aload_0
	invokestatic	Method scala/collection/Iterator$class.isTraversableAgain:(Lscala/collection/Iterator;)Z
	ireturn
  Labels:

public scala.collection.Iterator drop(int);
  Signature: (I)Lscala/collection/Iterator;
  Code:
   Stack=2, Locals=2, Args_size=2
	aload_0
	iload_1
	invokestatic	Method scala/collection/Iterator$class.drop:(Lscala/collection/Iterator;I)Lscala/collection/Iterator;
	areturn
  Labels:
  LocalVariableTable: 
   Start  Length  Slot  Name   Signature
   0      6      0    this       Lscala/collection/immutable/HashSet$HashTrieSet$$anon$1;
   0      6      1    n       I


public scala.collection.Iterator $plus$plus(scala.Function0);
  Signature: (Lscala/Function0;)Lscala/collection/Iterator;
  Code:
   Stack=2, Locals=2, Args_size=2
	aload_0
	aload_1
	invokestatic	Method scala/collection/Iterator$class.$plus$plus:(Lscala/collection/Iterator;Lscala/Function0;)Lscala/collection/Iterator;
	areturn
  Labels:
  LocalVariableTable: 
   Start  Length  Slot  Name   Signature
   0      6      0    this       Lscala/collection/immutable/HashSet$HashTrieSet$$anon$1;
   0      6      1    that       Lscala/Function0;


public void foreach(scala.Function1);
  Signature: (Lscala/Function1;)V
  Code:
   Stack=2, Locals=2, Args_size=2
	aload_0
	aload_1
	invokestatic	Method scala/collection/Iterator$class.foreach:(Lscala/collection/Iterator;Lscala/Function1;)V
	return
  Labels:
  LocalVariableTable: 
   Start  Length  Slot  Name   Signature
   0      6      0    this       Lscala/collection/immutable/HashSet$HashTrieSet$$anon$1;
   0      6      1    f       Lscala/Function1;


public boolean forall(scala.Function1);
  Signature: (Lscala/Function1;)Z
  Code:
   Stack=2, Locals=2, Args_size=2
	aload_0
	aload_1
	invokestatic	Method scala/collection/Iterator$class.forall:(Lscala/collection/Iterator;Lscala/Function1;)Z
	ireturn
  Labels:
  LocalVariableTable: 
   Start  Length  Slot  Name   Signature
   0      6      0    this       Lscala/collection/immutable/HashSet$HashTrieSet$$anon$1;
   0      6      1    p       Lscala/Function1;


public boolean exists(scala.Function1);
  Signature: (Lscala/Function1;)Z
  Code:
   Stack=2, Locals=2, Args_size=2
	aload_0
	aload_1
	invokestatic	Method scala/collection/Iterator$class.exists:(Lscala/collection/Iterator;Lscala/Function1;)Z
	ireturn
  Labels:
  LocalVariableTable: 
   Start  Length  Slot  Name   Signature
   0      6      0    this       Lscala/collection/immutable/HashSet$HashTrieSet$$anon$1;
   0      6      1    p       Lscala/Function1;


public int length();
  Signature: ()I
  Code:
   Stack=1, Locals=1, Args_size=1
	aload_0
	invokestatic	Method scala/collection/Iterator$class.length:(Lscala/collection/Iterator;)I
	ireturn
  Labels:

public void copyToArray(java.lang.Object, int, int);
  Signature: (Ljava/lang/Object;II)V
  Code:
   Stack=4, Locals=4, Args_size=4
	aload_0
	aload_1
	iload_2
	iload_3
	invokestatic	Method scala/collection/Iterator$class.copyToArray:(Lscala/collection/Iterator;Ljava/lang/Object;II)V
	return
  Labels:
  LocalVariableTable: 
   Start  Length  Slot  Name   Signature
   0      8      0    this       Lscala/collection/immutable/HashSet$HashTrieSet$$anon$1;
   0      8      1    xs       Ljava/lang/Object;
   0      8      2    start       I
   0      8      3    len       I


public java.lang.String toString();
  Signature: ()Ljava/lang/String;
  Code:
   Stack=1, Locals=1, Args_size=1
	aload_0
	invokestatic	Method scala/collection/Iterator$class.toString:(Lscala/collection/Iterator;)Ljava/lang/String;
	areturn
  Labels:

public int size();
  Signature: ()I
  Code:
   Stack=1, Locals=1, Args_size=1
	aload_0
	invokestatic	Method scala/collection/TraversableOnce$class.size:(Lscala/collection/TraversableOnce;)I
	ireturn
  Labels:

public boolean nonEmpty();
  Signature: ()Z
  Code:
   Stack=1, Locals=1, Args_size=1
	aload_0
	invokestatic	Method scala/collection/TraversableOnce$class.nonEmpty:(Lscala/collection/TraversableOnce;)Z
	ireturn
  Labels:

public java.lang.Object $div$colon(java.lang.Object, scala.Function2);
  Signature: (Ljava/lang/Object;Lscala/Function2;)Ljava/lang/Object;
  Code:
   Stack=3, Locals=3, Args_size=3
	aload_0
	aload_1
	aload_2
	invokestatic	Method scala/collection/TraversableOnce$class.$div$colon:(Lscala/collection/TraversableOnce;Ljava/lang/Object;Lscala/Function2;)Ljava/lang/Object;
	areturn
  Labels:
  LocalVariableTable: 
   Start  Length  Slot  Name   Signature
   0      7      0    this       Lscala/collection/immutable/HashSet$HashTrieSet$$anon$1;
   0      7      1    z       Ljava/lang/Object;
   0      7      2    op       Lscala/Function2;


public java.lang.Object foldLeft(java.lang.Object, scala.Function2);
  Signature: (Ljava/lang/Object;Lscala/Function2;)Ljava/lang/Object;
  Code:
   Stack=3, Locals=3, Args_size=3
	aload_0
	aload_1
	aload_2
	invokestatic	Method scala/collection/TraversableOnce$class.foldLeft:(Lscala/collection/TraversableOnce;Ljava/lang/Object;Lscala/Function2;)Ljava/lang/Object;
	areturn
  Labels:
  LocalVariableTable: 
   Start  Length  Slot  Name   Signature
   0      7      0    this       Lscala/collection/immutable/HashSet$HashTrieSet$$anon$1;
   0      7      1    z       Ljava/lang/Object;
   0      7      2    op       Lscala/Function2;


public java.lang.Object sum(scala.math.Numeric);
  Signature: (Lscala/math/Numeric;)Ljava/lang/Object;
  Code:
   Stack=2, Locals=2, Args_size=2
	aload_0
	aload_1
	invokestatic	Method scala/collection/TraversableOnce$class.sum:(Lscala/collection/TraversableOnce;Lscala/math/Numeric;)Ljava/lang/Object;
	areturn
  Labels:
  LocalVariableTable: 
   Start  Length  Slot  Name   Signature
   0      6      0    this       Lscala/collection/immutable/HashSet$HashTrieSet$$anon$1;
   0      6      1    num       Lscala/math/Numeric;


public void copyToArray(java.lang.Object, int);
  Signature: (Ljava/lang/Object;I)V
  Code:
   Stack=3, Locals=3, Args_size=3
	aload_0
	aload_1
	iload_2
	invokestatic	Method scala/collection/TraversableOnce$class.copyToArray:(Lscala/collection/TraversableOnce;Ljava/lang/Object;I)V
	return
  Labels:
  LocalVariableTable: 
   Start  Length  Slot  Name   Signature
   0      7      0    this       Lscala/collection/immutable/HashSet$HashTrieSet$$anon$1;
   0      7      1    xs       Ljava/lang/Object;
   0      7      2    start       I


public java.lang.Object toArray(scala.reflect.ClassManifest);
  Signature: (Lscala/reflect/ClassManifest;)Ljava/lang/Object;
  Code:
   Stack=2, Locals=2, Args_size=2
	aload_0
	aload_1
	invokestatic	Method scala/collection/TraversableOnce$class.toArray:(Lscala/collection/TraversableOnce;Lscala/reflect/ClassManifest;)Ljava/lang/Object;
	areturn
  Labels:
  LocalVariableTable: 
   Start  Length  Slot  Name   Signature
   0      6      0    this       Lscala/collection/immutable/HashSet$HashTrieSet$$anon$1;
   0      6      1    evidence$1       Lscala/reflect/ClassManifest;


public scala.collection.immutable.List toList();
  Signature: ()Lscala/collection/immutable/List;
  Code:
   Stack=1, Locals=1, Args_size=1
	aload_0
	invokestatic	Method scala/collection/TraversableOnce$class.toList:(Lscala/collection/TraversableOnce;)Lscala/collection/immutable/List;
	areturn
  Labels:

public scala.collection.immutable.Stream toStream();
  Signature: ()Lscala/collection/immutable/Stream;
  Code:
   Stack=1, Locals=1, Args_size=1
	aload_0
	invokestatic	Method scala/collection/TraversableOnce$class.toStream:(Lscala/collection/TraversableOnce;)Lscala/collection/immutable/Stream;
	areturn
  Labels:

public scala.collection.immutable.Set toSet();
  Signature: ()Lscala/collection/immutable/Set;
  Code:
   Stack=1, Locals=1, Args_size=1
	aload_0
	invokestatic	Method scala/collection/TraversableOnce$class.toSet:(Lscala/collection/TraversableOnce;)Lscala/collection/immutable/Set;
	areturn
  Labels:

public java.lang.String mkString(java.lang.String, java.lang.String, java.lang.String);
  Signature: (Ljava/lang/String;Ljava/lang/String;Ljava/lang/String;)Ljava/lang/String;
  Code:
   Stack=4, Locals=4, Args_size=4
	aload_0
	aload_1
	aload_2
	aload_3
	invokestatic	Method scala/collection/TraversableOnce$class.mkString:(Lscala/collection/TraversableOnce;Ljava/lang/String;Ljava/lang/String;Ljava/lang/String;)Ljava/lang/String;
	areturn
  Labels:
  LocalVariableTable: 
   Start  Length  Slot  Name   Signature
   0      8      0    this       Lscala/collection/immutable/HashSet$HashTrieSet$$anon$1;
   0      8      1    start       Ljava/lang/String;
   0      8      2    sep       Ljava/lang/String;
   0      8      3    end       Ljava/lang/String;


public java.lang.String mkString(java.lang.String);
  Signature: (Ljava/lang/String;)Ljava/lang/String;
  Code:
   Stack=2, Locals=2, Args_size=2
	aload_0
	aload_1
	invokestatic	Method scala/collection/TraversableOnce$class.mkString:(Lscala/collection/TraversableOnce;Ljava/lang/String;)Ljava/lang/String;
	areturn
  Labels:
  LocalVariableTable: 
   Start  Length  Slot  Name   Signature
   0      6      0    this       Lscala/collection/immutable/HashSet$HashTrieSet$$anon$1;
   0      6      1    sep       Ljava/lang/String;


public java.lang.String mkString();
  Signature: ()Ljava/lang/String;
  Code:
   Stack=1, Locals=1, Args_size=1
	aload_0
	invokestatic	Method scala/collection/TraversableOnce$class.mkString:(Lscala/collection/TraversableOnce;)Ljava/lang/String;
	areturn
  Labels:

public scala.collection.mutable.StringBuilder addString(scala.collection.mutable.StringBuilder, java.lang.String, java.lang.String, java.lang.String);
  Signature: (Lscala/collection/mutable/StringBuilder;Ljava/lang/String;Ljava/lang/String;Ljava/lang/String;)Lscala/collection/mutable/StringBuilder;
  Code:
   Stack=5, Locals=5, Args_size=5
	aload_0
	aload_1
	aload_2
	aload_3
	aload	4
	invokestatic	Method scala/collection/TraversableOnce$class.addString:(Lscala/collection/TraversableOnce;Lscala/collection/mutable/StringBuilder;Ljava/lang/String;Ljava/lang/String;Ljava/lang/String;)Lscala/collection/mutable/StringBuilder;
	areturn
  Labels:
  LocalVariableTable: 
   Start  Length  Slot  Name   Signature
   0      10      0    this       Lscala/collection/immutable/HashSet$HashTrieSet$$anon$1;
   0      10      1    b       Lscala/collection/mutable/StringBuilder;
   0      10      2    start       Ljava/lang/String;
   0      10      3    sep       Ljava/lang/String;
   0      10      4    end       Ljava/lang/String;


public boolean hasNext();
  Signature: ()Z
  Code:
   Stack=2, Locals=1, Args_size=1
	aload_0
	getfield	Field subIter:Lscala/collection/Iterator;
	ifnonnull	l1 // iconst_1
	aload_0
	getfield	Field depth:I
	iconst_0
	if_icmplt	l2 // iconst_0
l1	iconst_1
	goto	l3 // ireturn
l2	iconst_0
l3	ireturn
  Labels:
   	l1 = 15 // iconst_1
   	l2 = 19 // iconst_0
   	l3 = 20 // ireturn

public java.lang.Object next();
  Signature: ()Ljava/lang/Object;
  Code:
   Stack=3, Locals=2, Args_size=1
	aload_0
	getfield	Field subIter:Lscala/collection/Iterator;
	ifnull	l1 // aload_0
	aload_0
	getfield	Field subIter:Lscala/collection/Iterator;
	invokeinterface	InterfaceMethod scala/collection/Iterator.next:()Ljava/lang/Object;
	astore_1
	aload_0
	getfield	Field subIter:Lscala/collection/Iterator;
	invokeinterface	InterfaceMethod scala/collection/Iterator.hasNext:()Z
	ifne	l2 // aload_1
	aload_0
	aconst_null
	putfield	Field subIter:Lscala/collection/Iterator;
l2	aload_1
	goto	l3 // areturn
l1	aload_0
	aload_0
	getfield	Field arrayD:[Lscala/collection/immutable/HashSet;
	aload_0
	getfield	Field posD:I
	invokespecial	Method next0:([Lscala/collection/immutable/HashSet;I)Ljava/lang/Object;
l3	areturn
  Labels:
   	l2 = 34 // aload_1
   	l1 = 38 // aload_0
   	l3 = 50 // areturn
  LocalVariableTable: 
   Start  Length  Slot  Name   Signature
   0      51      0    this       Lscala/collection/immutable/HashSet$HashTrieSet$$anon$1;
   17      18      1    el       Ljava/lang/Object;

  Signature: length = 0x2
   00 67 

private java.lang.Object next0(scala.collection.immutable.HashSet[], int);
  Signature: ([Lscala/collection/immutable/HashSet;I)Ljava/lang/Object;
  Code:
   Stack=3, Locals=5, Args_size=3
l6	iload_2
	aload_1
	arraylength
	iconst_1
	isub
	if_icmpne	l1 // aload_0
	aload_0
	aload_0
	getfield	Field depth:I
	iconst_1
	isub
	putfield	Field depth:I
	aload_0
	getfield	Field depth:I
	iconst_0
	if_icmplt	l2 // aload_0
	aload_0
	aload_0
	getfield	Field arrayStack:[[Lscala/collection/immutable/HashSet;
	aload_0
	getfield	Field depth:I
	aaload
	putfield	Field arrayD:[Lscala/collection/immutable/HashSet;
	aload_0
	aload_0
	getfield	Field posStack:[I
	aload_0
	getfield	Field depth:I
	iaload
	putfield	Field posD:I
	aload_0
	getfield	Field arrayStack:[[Lscala/collection/immutable/HashSet;
	aload_0
	getfield	Field depth:I
	aconst_null
	aastore
	goto	l3 // aload_1
l2	aload_0
	aconst_null
	putfield	Field arrayD:[Lscala/collection/immutable/HashSet;
	aload_0
	iconst_0
	putfield	Field posD:I
	goto	l3 // aload_1
l1	aload_0
	aload_0
	getfield	Field posD:I
	iconst_1
	iadd
	putfield	Field posD:I
l3	aload_1
	iload_2
	aaload
	astore	4
	aload	4
	instanceof	class scala/collection/immutable/HashSet$HashTrieSet
	ifeq	l4 // aload
	aload	4
	checkcast	class scala/collection/immutable/HashSet$HashTrieSet
	astore_3
	aload_0
	getfield	Field depth:I
	iconst_0
	if_icmplt	l5 // aload_0
	aload_0
	getfield	Field arrayStack:[[Lscala/collection/immutable/HashSet;
	aload_0
	getfield	Field depth:I
	aload_0
	getfield	Field arrayD:[Lscala/collection/immutable/HashSet;
	aastore
	aload_0
	getfield	Field posStack:[I
	aload_0
	getfield	Field depth:I
	aload_0
	getfield	Field posD:I
	iastore
l5	aload_0
	aload_0
	getfield	Field depth:I
	iconst_1
	iadd
	putfield	Field depth:I
	aload_0
	aload_3
	getfield	Field scala/collection/immutable/HashSet$HashTrieSet.scala$collection$immutable$HashSet$HashTrieSet$$elems:[Lscala/collection/immutable/HashSet;
	putfield	Field arrayD:[Lscala/collection/immutable/HashSet;
	aload_0
	iconst_0
	putfield	Field posD:I
	aload_3
	getfield	Field scala/collection/immutable/HashSet$HashTrieSet.scala$collection$immutable$HashSet$HashTrieSet$$elems:[Lscala/collection/immutable/HashSet;
	iconst_0
	istore_2
	astore_1
	goto	l6 // iload_2
l4	aload	4
	instanceof	class scala/collection/immutable/HashSet$HashSet1
	ifeq	l7 // aload_0
	aload	4
	checkcast	class scala/collection/immutable/HashSet$HashSet1
	invokevirtual	Method scala/collection/immutable/HashSet$HashSet1.key:()Ljava/lang/Object;
	goto	l8 // areturn
l7	aload_0
	aload	4
	invokevirtual	Method scala/collection/immutable/HashSet.iterator:()Lscala/collection/Iterator;
	putfield	Field subIter:Lscala/collection/Iterator;
	aload_0
	getfield	Field subIter:Lscala/collection/Iterator;
	invokeinterface	InterfaceMethod scala/collection/Iterator.next:()Ljava/lang/Object;
l8	areturn
  Labels:
   	l6 = 0 // iload_2
   	l2 = 65 // aload_0
   	l1 = 78 // aload_0
   	l3 = 88 // aload_1
   	l5 = 141 // aload_0
   	l4 = 174 // aload
   	l7 = 193 // aload_0
   	l8 = 211 // areturn
  LocalVariableTable: 
   Start  Length  Slot  Name   Signature
   0      212      0    this       Lscala/collection/immutable/HashSet$HashTrieSet$$anon$1;
   0      212      1    elems       [Lscala/collection/immutable/HashSet;
   0      212      2    i       I
   107      67      3    temp2       Lscala/collection/immutable/HashSet$HashTrieSet;
   93      119      4    temp1       Lscala/collection/immutable/HashSet;

  Signature: length = 0x2
   00 FFFFFF91 

public scala.collection.immutable.HashSet$HashTrieSet$$anon$1(scala.collection.immutable.HashSet$HashTrieSet);
  Signature: (Lscala/collection/immutable/HashSet$HashTrieSet;)V
  Code:
   Stack=2, Locals=2, Args_size=2
	aload_0
	invokespecial	Method java/lang/Object."<init>":()V
	aload_0
	invokestatic	Method scala/collection/TraversableOnce$class.$init$:(Lscala/collection/TraversableOnce;)V
	aload_0
	invokestatic	Method scala/collection/Iterator$class.$init$:(Lscala/collection/Iterator;)V
	aload_0
	iconst_0
	putfield	Field depth:I
	aload_0
	ldc	int 6
	anewarray	class "[Lscala/collection/immutable/HashSet;"
	putfield	Field arrayStack:[[Lscala/collection/immutable/HashSet;
	aload_0
	ldc	int 6
	newarray int
	putfield	Field posStack:[I
	aload_0
	aload_1
	invokevirtual	Method scala/collection/immutable/HashSet$HashTrieSet.scala$collection$immutable$HashSet$HashTrieSet$$elems:()[Lscala/collection/immutable/HashSet;
	putfield	Field arrayD:[Lscala/collection/immutable/HashSet;
	aload_0
	iconst_0
	putfield	Field posD:I
	aload_0
	aconst_null
	putfield	Field subIter:Lscala/collection/Iterator;
	return
  Labels:

  Signature: length = 0x2
   00 FFFFFF8C 

}

