Compiled from "HashSet.scala"
public final class scala.collection.immutable.HashSet$SerializationProxy$$anonfun$readObject$1 extends scala.runtime.AbstractFunction1 implements java.io.Serializable
  SourceFile: "HashSet.scala"
  Scala: length = 0x
   
  InnerClass: 
   public SerializationProxy=class scala/collection/immutable/HashSet$SerializationProxy of class scala/collection/immutable/HashSet
   public final $anonfun$readObject$1=class scala/collection/immutable/HashSet$SerializationProxy$$anonfun$readObject$1 of class scala/collection/immutable/HashSet$SerializationProxy
  minor version: 0
  major version: 49
  Constant pool:
Asciz	SourceFile;
Asciz	HashSet.scala;
Asciz	<clinit>;
Asciz	()V;
Asciz	Code;
Asciz	serialVersionUID;
Asciz	J;
Asciz	scala/collection/immutable/HashSet$SerializationProxy$$anonfun$readObject$1;
class	scala/collection/immutable/HashSet$SerializationProxy$$anonfun$readObject$1
NameAndType	serialVersionUID:J
Field	scala/collection/immutable/HashSet$SerializationProxy$$anonfun$readObject$1.serialVersionUID:J
Asciz	$outer;
Asciz	Lscala/collection/immutable/HashSet$SerializationProxy;;
Asciz	in$1;
Asciz	Ljava/io/ObjectInputStream;;
Asciz	apply;
Asciz	(I)V;
Asciz	LineNumberTable;
NameAndType	in$1:Ljava/io/ObjectInputStream;
Field	scala/collection/immutable/HashSet$SerializationProxy$$anonfun$readObject$1.in$1:Ljava/io/ObjectInputStream;
Asciz	java/io/ObjectInputStream;
class	java/io/ObjectInputStream
Asciz	readObject;
Asciz	()Ljava/lang/Object;;
NameAndType	readObject:()Ljava/lang/Object;
Method	java/io/ObjectInputStream.readObject:()Ljava/lang/Object;
NameAndType	$outer:Lscala/collection/immutable/HashSet$SerializationProxy;
Field	scala/collection/immutable/HashSet$SerializationProxy$$anonfun$readObject$1.$outer:Lscala/collection/immutable/HashSet$SerializationProxy;
Asciz	scala/collection/immutable/HashSet$SerializationProxy;
class	scala/collection/immutable/HashSet$SerializationProxy
Asciz	scala$collection$immutable$HashSet$SerializationProxy$$orig;
Asciz	Lscala/collection/immutable/HashSet;;
NameAndType	scala$collection$immutable$HashSet$SerializationProxy$$orig:Lscala/collection/immutable/HashSet;
Field	scala/collection/immutable/HashSet$SerializationProxy.scala$collection$immutable$HashSet$SerializationProxy$$orig:Lscala/collection/immutable/HashSet;
Asciz	scala/collection/immutable/HashSet;
class	scala/collection/immutable/HashSet
Asciz	$plus;
Asciz	(Ljava/lang/Object;)Lscala/collection/immutable/HashSet;;
NameAndType	$plus:(Ljava/lang/Object;)Lscala/collection/immutable/HashSet;
Method	scala/collection/immutable/HashSet.$plus:(Ljava/lang/Object;)Lscala/collection/immutable/HashSet;
Asciz	this;
Asciz	Lscala/collection/immutable/HashSet$SerializationProxy$$anonfun$readObject$1;;
Asciz	i;
Asciz	I;
Asciz	e0;
Asciz	Ljava/lang/Object;;
Asciz	LocalVariableTable;
Asciz	apply$mcVI$sp;
Asciz	()Lscala/collection/immutable/HashSet;;
NameAndType	scala$collection$immutable$HashSet$SerializationProxy$$orig:()Lscala/collection/immutable/HashSet;
Method	scala/collection/immutable/HashSet$SerializationProxy.scala$collection$immutable$HashSet$SerializationProxy$$orig:()Lscala/collection/immutable/HashSet;
Asciz	scala$collection$immutable$HashSet$SerializationProxy$$orig_$eq;
Asciz	(Lscala/collection/immutable/HashSet;)V;
NameAndType	scala$collection$immutable$HashSet$SerializationProxy$$orig_$eq:(Lscala/collection/immutable/HashSet;)V
Method	scala/collection/immutable/HashSet$SerializationProxy.scala$collection$immutable$HashSet$SerializationProxy$$orig_$eq:(Lscala/collection/immutable/HashSet;)V
Asciz	v1;
Asciz	e;
Asciz	(Ljava/lang/Object;)Ljava/lang/Object;;
Asciz	scala/runtime/BoxesRunTime;
class	scala/runtime/BoxesRunTime
Asciz	unboxToInt;
Asciz	(Ljava/lang/Object;)I;
NameAndType	unboxToInt:(Ljava/lang/Object;)I
Method	scala/runtime/BoxesRunTime.unboxToInt:(Ljava/lang/Object;)I
NameAndType	apply:(I)V
Method	scala/collection/immutable/HashSet$SerializationProxy$$anonfun$readObject$1.apply:(I)V
Asciz	scala/runtime/BoxedUnit;
class	scala/runtime/BoxedUnit
Asciz	UNIT;
Asciz	Lscala/runtime/BoxedUnit;;
NameAndType	UNIT:Lscala/runtime/BoxedUnit;
Field	scala/runtime/BoxedUnit.UNIT:Lscala/runtime/BoxedUnit;
Asciz	<init>;
Asciz	(Lscala/collection/immutable/HashSet$SerializationProxy;Ljava/io/ObjectInputStream;)V;
Asciz	java/lang/NullPointerException;
class	java/lang/NullPointerException
NameAndType	"<init>":()V
Method	java/lang/NullPointerException."<init>":()V
Asciz	scala/runtime/AbstractFunction1;
class	scala/runtime/AbstractFunction1
Method	scala/runtime/AbstractFunction1."<init>":()V
Asciz	(Lscala/collection/immutable/HashSet$SerializationProxy<TA;TB;>;)V;
Asciz	Signature;
Asciz	Scala;
Asciz	InnerClasses;
Asciz	SerializationProxy;
Asciz	$anonfun$readObject$1;
Asciz	java/io/Serializable;
class	java/io/Serializable

{
public static final long serialVersionUID;
  Signature: J

public final scala.collection.immutable.HashSet$SerializationProxy $outer;
  Signature: Lscala/collection/immutable/HashSet$SerializationProxy;

public final java.io.ObjectInputStream in$1;
  Signature: Ljava/io/ObjectInputStream;

public static {};
  Signature: ()V
  Code:
   Stack=2, Locals=0, Args_size=0
	lconst_0
	putstatic	Field serialVersionUID:J
	return
  Labels:

public final void apply(int);
  Signature: (I)V
  Code:
   Stack=3, Locals=6, Args_size=2
	aload_0
	getfield	Field in$1:Ljava/io/ObjectInputStream;
	invokevirtual	Method java/io/ObjectInputStream.readObject:()Ljava/lang/Object;
	astore_3
	aload_0
	getfield	Field $outer:Lscala/collection/immutable/HashSet$SerializationProxy;
	aload_0
	getfield	Field $outer:Lscala/collection/immutable/HashSet$SerializationProxy;
	astore_2
	aload_2
	getfield	Field scala/collection/immutable/HashSet$SerializationProxy.scala$collection$immutable$HashSet$SerializationProxy$$orig:Lscala/collection/immutable/HashSet;
	aload_3
	invokevirtual	Method scala/collection/immutable/HashSet.$plus:(Ljava/lang/Object;)Lscala/collection/immutable/HashSet;
	astore	5
	astore	4
	aload	4
	aload	5
	putfield	Field scala/collection/immutable/HashSet$SerializationProxy.scala$collection$immutable$HashSet$SerializationProxy$$orig:Lscala/collection/immutable/HashSet;
	return
  Labels:
  LocalVariableTable: 
   Start  Length  Slot  Name   Signature
   0      37      0    this       Lscala/collection/immutable/HashSet$SerializationProxy$$anonfun$readObject$1;
   0      37      1    i       I
   8      28      3    e0       Ljava/lang/Object;


public void apply$mcVI$sp(int);
  Signature: (I)V
  Code:
   Stack=3, Locals=3, Args_size=2
	aload_0
	getfield	Field in$1:Ljava/io/ObjectInputStream;
	invokevirtual	Method java/io/ObjectInputStream.readObject:()Ljava/lang/Object;
	astore_2
	aload_0
	getfield	Field $outer:Lscala/collection/immutable/HashSet$SerializationProxy;
	aload_0
	getfield	Field $outer:Lscala/collection/immutable/HashSet$SerializationProxy;
	invokevirtual	Method scala/collection/immutable/HashSet$SerializationProxy.scala$collection$immutable$HashSet$SerializationProxy$$orig:()Lscala/collection/immutable/HashSet;
	aload_2
	invokevirtual	Method scala/collection/immutable/HashSet.$plus:(Ljava/lang/Object;)Lscala/collection/immutable/HashSet;
	invokevirtual	Method scala/collection/immutable/HashSet$SerializationProxy.scala$collection$immutable$HashSet$SerializationProxy$$orig_$eq:(Lscala/collection/immutable/HashSet;)V
	return
  Labels:
  LocalVariableTable: 
   Start  Length  Slot  Name   Signature
   0      27      0    this       Lscala/collection/immutable/HashSet$SerializationProxy$$anonfun$readObject$1;
   0      27      1    v1       I
   8      18      2    e       Ljava/lang/Object;


public final java.lang.Object apply(java.lang.Object);
  Signature: (Ljava/lang/Object;)Ljava/lang/Object;
  Code:
   Stack=2, Locals=2, Args_size=2
	aload_0
	aload_1
	invokestatic	Method scala/runtime/BoxesRunTime.unboxToInt:(Ljava/lang/Object;)I
	invokevirtual	Method apply:(I)V
	getstatic	Field scala/runtime/BoxedUnit.UNIT:Lscala/runtime/BoxedUnit;
	areturn
  Labels:
  LocalVariableTable: 
   Start  Length  Slot  Name   Signature
   0      12      0    this       Lscala/collection/immutable/HashSet$SerializationProxy$$anonfun$readObject$1;
   0      12      1    v1       Ljava/lang/Object;


public scala.collection.immutable.HashSet$SerializationProxy$$anonfun$readObject$1(scala.collection.immutable.HashSet$SerializationProxy, java.io.ObjectInputStream);
  Signature: (Lscala/collection/immutable/HashSet$SerializationProxy;Ljava/io/ObjectInputStream;)V
  Code:
   Stack=2, Locals=3, Args_size=3
	aload_1
	ifnonnull	l1 // aload_0
	new	class java/lang/NullPointerException
	dup
	invokespecial	Method java/lang/NullPointerException."<init>":()V
	athrow
l1	aload_0
	aload_1
	putfield	Field $outer:Lscala/collection/immutable/HashSet$SerializationProxy;
	aload_0
	aload_2
	putfield	Field in$1:Ljava/io/ObjectInputStream;
	aload_0
	invokespecial	Method scala/runtime/AbstractFunction1."<init>":()V
	return
  Labels:
   	l1 = 12 // aload_0
  LocalVariableTable: 
   Start  Length  Slot  Name   Signature
   0      27      0    this       Lscala/collection/immutable/HashSet$SerializationProxy$$anonfun$readObject$1;
   0      27      1    $outer       Lscala/collection/immutable/HashSet$SerializationProxy;

  Signature: length = 0x2
   00 52 

}

