Compiled from "HashSet.scala"
public final class scala.collection.immutable.HashSet$$anonfun$makeCopy$3 extends scala.runtime.AbstractFunction1 implements java.io.Serializable
  SourceFile: "HashSet.scala"
  Scala: length = 0x
   
  InnerClass: 
   public final $anonfun$makeCopy$3=class scala/collection/immutable/HashSet$$anonfun$makeCopy$3 of class scala/collection/immutable/HashSet
  minor version: 0
  major version: 49
  Constant pool:
Asciz	SourceFile;
Asciz	HashSet.scala;
Asciz	<clinit>;
Asciz	()V;
Asciz	Code;
Asciz	serialVersionUID;
Asciz	J;
Asciz	scala/collection/immutable/HashSet$$anonfun$makeCopy$3;
class	scala/collection/immutable/HashSet$$anonfun$makeCopy$3
NameAndType	serialVersionUID:J
Field	scala/collection/immutable/HashSet$$anonfun$makeCopy$3.serialVersionUID:J
Asciz	$outer;
Asciz	Lscala/collection/immutable/HashSet;;
Asciz	<init>;
Asciz	(Lscala/collection/immutable/HashSet;)V;
Asciz	LineNumberTable;
Asciz	java/lang/NullPointerException;
class	java/lang/NullPointerException
NameAndType	"<init>":()V
Method	java/lang/NullPointerException."<init>":()V
NameAndType	$outer:Lscala/collection/immutable/HashSet;
Field	scala/collection/immutable/HashSet$$anonfun$makeCopy$3.$outer:Lscala/collection/immutable/HashSet;
Asciz	scala/runtime/AbstractFunction1;
class	scala/runtime/AbstractFunction1
Method	scala/runtime/AbstractFunction1."<init>":()V
Asciz	this;
Asciz	Lscala/collection/immutable/HashSet$$anonfun$makeCopy$3;;
Asciz	LocalVariableTable;
Asciz	(Lscala/collection/immutable/HashSet<TA;>;)V;
Asciz	Signature;
Asciz	apply;
Asciz	(Ljava/lang/Object;)Ljava/lang/Object;;
Asciz	scala/collection/immutable/HashSet;
class	scala/collection/immutable/HashSet
NameAndType	apply:(Lscala/collection/immutable/HashSet;)V
Method	scala/collection/immutable/HashSet$$anonfun$makeCopy$3.apply:(Lscala/collection/immutable/HashSet;)V
Asciz	scala/runtime/BoxedUnit;
class	scala/runtime/BoxedUnit
Asciz	UNIT;
Asciz	Lscala/runtime/BoxedUnit;;
NameAndType	UNIT:Lscala/runtime/BoxedUnit;
Field	scala/runtime/BoxedUnit.UNIT:Lscala/runtime/BoxedUnit;
Asciz	v1;
Asciz	Ljava/lang/Object;;
Asciz	undo$1;
NameAndType	undo$1:(Lscala/collection/immutable/HashSet;)V
Method	scala/collection/immutable/HashSet.undo$1:(Lscala/collection/immutable/HashSet;)V
Asciz	Scala;
Asciz	InnerClasses;
Asciz	$anonfun$makeCopy$3;
Asciz	java/io/Serializable;
class	java/io/Serializable

{
public static final long serialVersionUID;
  Signature: J

public final scala.collection.immutable.HashSet $outer;
  Signature: Lscala/collection/immutable/HashSet;

public static {};
  Signature: ()V
  Code:
   Stack=2, Locals=0, Args_size=0
	lconst_0
	putstatic	Field serialVersionUID:J
	return
  Labels:

public scala.collection.immutable.HashSet$$anonfun$makeCopy$3(scala.collection.immutable.HashSet);
  Signature: (Lscala/collection/immutable/HashSet;)V
  Code:
   Stack=2, Locals=2, Args_size=2
	aload_1
	ifnonnull	l1 // aload_0
	new	class java/lang/NullPointerException
	dup
	invokespecial	Method java/lang/NullPointerException."<init>":()V
	athrow
l1	aload_0
	aload_1
	putfield	Field $outer:Lscala/collection/immutable/HashSet;
	aload_0
	invokespecial	Method scala/runtime/AbstractFunction1."<init>":()V
	return
  Labels:
   	l1 = 12 // aload_0
  LocalVariableTable: 
   Start  Length  Slot  Name   Signature
   0      22      0    this       Lscala/collection/immutable/HashSet$$anonfun$makeCopy$3;
   0      22      1    $outer       Lscala/collection/immutable/HashSet;

  Signature: length = 0x2
   00 1D 

public final java.lang.Object apply(java.lang.Object);
  Signature: (Ljava/lang/Object;)Ljava/lang/Object;
  Code:
   Stack=2, Locals=2, Args_size=2
	aload_0
	aload_1
	checkcast	class scala/collection/immutable/HashSet
	invokevirtual	Method apply:(Lscala/collection/immutable/HashSet;)V
	getstatic	Field scala/runtime/BoxedUnit.UNIT:Lscala/runtime/BoxedUnit;
	areturn
  Labels:
  LocalVariableTable: 
   Start  Length  Slot  Name   Signature
   0      12      0    this       Lscala/collection/immutable/HashSet$$anonfun$makeCopy$3;
   0      12      1    v1       Ljava/lang/Object;


public final void apply(scala.collection.immutable.HashSet);
  Signature: (Lscala/collection/immutable/HashSet;)V
  Code:
   Stack=2, Locals=2, Args_size=2
	aload_0
	getfield	Field $outer:Lscala/collection/immutable/HashSet;
	aload_1
	invokevirtual	Method scala/collection/immutable/HashSet.undo$1:(Lscala/collection/immutable/HashSet;)V
	return
  Labels:
  Signature: length = 0x2
   00 1D 

}

