Compiled from "HashSet.scala"
public final class scala.collection.immutable.HashSet$$anon$1 extends scala.collection.immutable.HashSet
  InnerClass: 
   public final $anon$1=class scala/collection/immutable/HashSet$$anon$1 of class scala/collection/immutable/HashSet
  Scala: length = 0x
   
  Signature: length = 0x2
   00 28 
  SourceFile: "HashSet.scala"
  minor version: 0
  major version: 49
  Constant pool:
class	scala/collection/immutable/HashSet
class	scala/collection/immutable/HashSet$$anon$1
class	scala/collection/mutable/FlatHashTable
Field	scala/collection/immutable/HashSet$$anon$1.lf$1:I
Method	scala/collection/immutable/HashSet."<init>":()V
Method	scala/collection/immutable/HashSet$$anon$1._newLoadFactor:()I
InterfaceMethod	scala/collection/mutable/FlatHashTable.table:()[Ljava/lang/Object;
InterfaceMethod	scala/collection/mutable/FlatHashTable.tableSize:()I
InterfaceMethod	scala/collection/mutable/FlatHashTable.tableSize_$eq:(I)V
InterfaceMethod	scala/collection/mutable/FlatHashTable.table_$eq:([Ljava/lang/Object;)V
InterfaceMethod	scala/collection/mutable/FlatHashTable.threshold:()I
InterfaceMethod	scala/collection/mutable/FlatHashTable.threshold_$eq:(I)V
NameAndType	"<init>":()V
NameAndType	_newLoadFactor:()I
NameAndType	lf$1:I
NameAndType	table:()[Ljava/lang/Object;
NameAndType	tableSize:()I
NameAndType	tableSize_$eq:(I)V
NameAndType	table_$eq:([Ljava/lang/Object;)V
NameAndType	threshold:()I
NameAndType	threshold_$eq:(I)V
Asciz	$anon$1;
Asciz	$outer;
Asciz	()I;
Asciz	()V;
Asciz	()[Ljava/lang/Object;;
Asciz	(I)V;
Asciz	(Lscala/collection/immutable/HashSet;I)V;
Asciz	(Lscala/collection/immutable/HashSet<TA;>;)V;
Asciz	([Ljava/lang/Object;)V;
Asciz	<init>;
Asciz	Code;
Asciz	HashSet.scala;
Asciz	I;
Asciz	InnerClasses;
Asciz	LineNumberTable;
Asciz	LocalVariableTable;
Asciz	Lscala/collection/immutable/HashSet$$anon$1;;
Asciz	Lscala/collection/immutable/HashSet;;
Asciz	Lscala/collection/immutable/HashSet<TA;>;;
Asciz	Scala;
Asciz	Signature;
Asciz	SourceFile;
Asciz	_newLoadFactor;
Asciz	initialSize;
Asciz	lf$1;
Asciz	loadFactor;
Asciz	scala/collection/immutable/HashSet;
Asciz	scala/collection/immutable/HashSet$$anon$1;
Asciz	scala/collection/mutable/FlatHashTable;
Asciz	table;
Asciz	tableSize;
Asciz	tableSize_$eq;
Asciz	table_$eq;
Asciz	this;
Asciz	threshold;
Asciz	threshold_$eq;

{
private final int lf$1;
  Signature: I

public scala.collection.immutable.HashSet$$anon$1(scala.collection.immutable.HashSet, int);
  Signature: (Lscala/collection/immutable/HashSet;I)V
  Code:
   Stack=2, Locals=3, Args_size=3
	aload_0
	iload_2
	putfield	Field lf$1:I
	aload_0
	invokespecial	Method scala/collection/immutable/HashSet."<init>":()V
	aload_0
	aload_1
	invokeinterface	InterfaceMethod scala/collection/mutable/FlatHashTable.table:()[Ljava/lang/Object;
	invokeinterface	InterfaceMethod scala/collection/mutable/FlatHashTable.table_$eq:([Ljava/lang/Object;)V
	aload_0
	aload_1
	invokeinterface	InterfaceMethod scala/collection/mutable/FlatHashTable.tableSize:()I
	invokeinterface	InterfaceMethod scala/collection/mutable/FlatHashTable.tableSize_$eq:(I)V
	aload_0
	aload_1
	invokeinterface	InterfaceMethod scala/collection/mutable/FlatHashTable.threshold:()I
	invokeinterface	InterfaceMethod scala/collection/mutable/FlatHashTable.threshold_$eq:(I)V
	return
  Labels:
  LocalVariableTable: 
   Start  Length  Slot  Name   Signature
   0      46      0    this       Lscala/collection/immutable/HashSet$$anon$1;
   0      46      1    $outer       Lscala/collection/immutable/HashSet;

  Signature: length = 0x2
   00 1D 

public int loadFactor();
  Signature: ()I
  Code:
   Stack=1, Locals=1, Args_size=1
	aload_0
	invokespecial	Method _newLoadFactor:()I
	ireturn
  Labels:

private int _newLoadFactor();
  Signature: ()I
  Code:
   Stack=1, Locals=1, Args_size=1
	aload_0
	getfield	Field lf$1:I
	ireturn
  Labels:

public int initialSize();
  Signature: ()I
  Code:
   Stack=1, Locals=1, Args_size=1
	iconst_0
	ireturn
  Labels:

}

