Compiled from "HashMap.scala"
public final class scala.collection.immutable.HashMap$HashTrieMap$$anonfun$writeObject$1 extends scala.runtime.AbstractFunction1 implements java.io.Serializable
  SourceFile: "HashMap.scala"
  Scala: length = 0x
   
  InnerClass: 
   public HashTrieMap=class scala/collection/immutable/HashMap$HashTrieMap of class scala/collection/immutable/HashMap
   public final $anonfun$writeObject$1=class scala/collection/immutable/HashMap$HashTrieMap$$anonfun$writeObject$1 of class scala/collection/immutable/HashMap$HashTrieMap
  minor version: 0
  major version: 49
  Constant pool:
Asciz	SourceFile;
Asciz	HashMap.scala;
Asciz	<clinit>;
Asciz	()V;
Asciz	Code;
Asciz	serialVersionUID;
Asciz	J;
Asciz	scala/collection/immutable/HashMap$HashTrieMap$$anonfun$writeObject$1;
class	scala/collection/immutable/HashMap$HashTrieMap$$anonfun$writeObject$1
NameAndType	serialVersionUID:J
Field	scala/collection/immutable/HashMap$HashTrieMap$$anonfun$writeObject$1.serialVersionUID:J
Asciz	out$1;
Asciz	Ljava/io/ObjectOutputStream;;
Asciz	apply;
Asciz	(Lscala/Tuple2;)V;
Asciz	LineNumberTable;
NameAndType	out$1:Ljava/io/ObjectOutputStream;
Field	scala/collection/immutable/HashMap$HashTrieMap$$anonfun$writeObject$1.out$1:Ljava/io/ObjectOutputStream;
Asciz	scala/Tuple2;
class	scala/Tuple2
Asciz	_1;
Asciz	()Ljava/lang/Object;;
NameAndType	_1:()Ljava/lang/Object;
Method	scala/Tuple2._1:()Ljava/lang/Object;
Asciz	java/io/ObjectOutputStream;
class	java/io/ObjectOutputStream
Asciz	writeObject;
Asciz	(Ljava/lang/Object;)V;
NameAndType	writeObject:(Ljava/lang/Object;)V
Method	java/io/ObjectOutputStream.writeObject:(Ljava/lang/Object;)V
Asciz	_2;
NameAndType	_2:()Ljava/lang/Object;
Method	scala/Tuple2._2:()Ljava/lang/Object;
Asciz	this;
Asciz	Lscala/collection/immutable/HashMap$HashTrieMap$$anonfun$writeObject$1;;
Asciz	p;
Asciz	Lscala/Tuple2;;
Asciz	LocalVariableTable;
Asciz	(Lscala/Tuple2<TA;TB;>;)V;
Asciz	Signature;
Asciz	(Ljava/lang/Object;)Ljava/lang/Object;;
NameAndType	apply:(Lscala/Tuple2;)V
Method	scala/collection/immutable/HashMap$HashTrieMap$$anonfun$writeObject$1.apply:(Lscala/Tuple2;)V
Asciz	scala/runtime/BoxedUnit;
class	scala/runtime/BoxedUnit
Asciz	UNIT;
Asciz	Lscala/runtime/BoxedUnit;;
NameAndType	UNIT:Lscala/runtime/BoxedUnit;
Field	scala/runtime/BoxedUnit.UNIT:Lscala/runtime/BoxedUnit;
Asciz	v1;
Asciz	Ljava/lang/Object;;
Asciz	<init>;
Asciz	(Lscala/collection/immutable/HashMap$HashTrieMap;Ljava/io/ObjectOutputStream;)V;
Asciz	scala/runtime/AbstractFunction1;
class	scala/runtime/AbstractFunction1
NameAndType	"<init>":()V
Method	scala/runtime/AbstractFunction1."<init>":()V
Asciz	$outer;
Asciz	Lscala/collection/immutable/HashMap$HashTrieMap;;
Asciz	(Lscala/collection/immutable/HashMap$HashTrieMap<TA;TB;>;)V;
Asciz	Scala;
Asciz	InnerClasses;
Asciz	scala/collection/immutable/HashMap$HashTrieMap;
class	scala/collection/immutable/HashMap$HashTrieMap
Asciz	scala/collection/immutable/HashMap;
class	scala/collection/immutable/HashMap
Asciz	HashTrieMap;
Asciz	$anonfun$writeObject$1;
Asciz	java/io/Serializable;
class	java/io/Serializable

{
public static final long serialVersionUID;
  Signature: J

public final java.io.ObjectOutputStream out$1;
  Signature: Ljava/io/ObjectOutputStream;

public static {};
  Signature: ()V
  Code:
   Stack=2, Locals=0, Args_size=0
	lconst_0
	putstatic	Field serialVersionUID:J
	return
  Labels:

public final void apply(scala.Tuple2);
  Signature: (Lscala/Tuple2;)V
  Code:
   Stack=2, Locals=2, Args_size=2
	aload_0
	getfield	Field out$1:Ljava/io/ObjectOutputStream;
	aload_1
	invokevirtual	Method scala/Tuple2._1:()Ljava/lang/Object;
	invokevirtual	Method java/io/ObjectOutputStream.writeObject:(Ljava/lang/Object;)V
	aload_0
	getfield	Field out$1:Ljava/io/ObjectOutputStream;
	aload_1
	invokevirtual	Method scala/Tuple2._2:()Ljava/lang/Object;
	invokevirtual	Method java/io/ObjectOutputStream.writeObject:(Ljava/lang/Object;)V
	return
  Labels:
  LocalVariableTable: 
   Start  Length  Slot  Name   Signature
   0      23      0    this       Lscala/collection/immutable/HashMap$HashTrieMap$$anonfun$writeObject$1;
   0      23      1    p       Lscala/Tuple2;

  Signature: length = 0x2
   00 27 

public final java.lang.Object apply(java.lang.Object);
  Signature: (Ljava/lang/Object;)Ljava/lang/Object;
  Code:
   Stack=2, Locals=2, Args_size=2
	aload_0
	aload_1
	checkcast	class scala/Tuple2
	invokevirtual	Method apply:(Lscala/Tuple2;)V
	getstatic	Field scala/runtime/BoxedUnit.UNIT:Lscala/runtime/BoxedUnit;
	areturn
  Labels:
  LocalVariableTable: 
   Start  Length  Slot  Name   Signature
   0      12      0    this       Lscala/collection/immutable/HashMap$HashTrieMap$$anonfun$writeObject$1;
   0      12      1    v1       Ljava/lang/Object;


public scala.collection.immutable.HashMap$HashTrieMap$$anonfun$writeObject$1(scala.collection.immutable.HashMap$HashTrieMap, java.io.ObjectOutputStream);
  Signature: (Lscala/collection/immutable/HashMap$HashTrieMap;Ljava/io/ObjectOutputStream;)V
  Code:
   Stack=2, Locals=3, Args_size=3
	aload_0
	aload_2
	putfield	Field out$1:Ljava/io/ObjectOutputStream;
	aload_0
	invokespecial	Method scala/runtime/AbstractFunction1."<init>":()V
	return
  Labels:
  LocalVariableTable: 
   Start  Length  Slot  Name   Signature
   0      10      0    this       Lscala/collection/immutable/HashMap$HashTrieMap$$anonfun$writeObject$1;
   0      10      1    $outer       Lscala/collection/immutable/HashMap$HashTrieMap;

  Signature: length = 0x2
   00 3C 

}

