Compiled from "HashSet.scala"
public final class scala.collection.immutable.HashSet$$anon$1 extends scala.collection.immutable.HashSet
  SourceFile: "HashSet.scala"
  Signature: length = 0x2
   00 33 
  Scala: length = 0x
   
  InnerClass: 
   public final #54= #10 of #14; //$anon$1=class scala/collection/immutable/HashSet$$anon$1 of class scala/collection/immutable/HashSet
  minor version: 0
  major version: 49
  Constant pool:
const #1 = Asciz	SourceFile;
const #2 = Asciz	HashSet.scala;
const #3 = Asciz	lv$1;
const #4 = Asciz	I;
const #5 = Asciz	<init>;
const #6 = Asciz	(Lscala/collection/immutable/HashSet;I)V;
const #7 = Asciz	Code;
const #8 = Asciz	LineNumberTable;
const #9 = Asciz	scala/collection/immutable/HashSet$$anon$1;
const #10 = class	#9;	//  scala/collection/immutable/HashSet$$anon$1
const #11 = NameAndType	#3:#4;//  lv$1:I
const #12 = Field	#10.#11;	//  scala/collection/immutable/HashSet$$anon$1.lv$1:I
const #13 = Asciz	scala/collection/immutable/HashSet;
const #14 = class	#13;	//  scala/collection/immutable/HashSet
const #15 = Asciz	()V;
const #16 = NameAndType	#5:#15;//  "<init>":()V
const #17 = Method	#14.#16;	//  scala/collection/immutable/HashSet."<init>":()V
const #18 = Asciz	scala/collection/mutable/FlatHashTable;
const #19 = class	#18;	//  scala/collection/mutable/FlatHashTable
const #20 = Asciz	table;
const #21 = Asciz	()[Ljava/lang/Object;;
const #22 = NameAndType	#20:#21;//  table:()[Ljava/lang/Object;
const #23 = InterfaceMethod	#19.#22;	//  scala/collection/mutable/FlatHashTable.table:()[Ljava/lang/Object;
const #24 = Asciz	table_$eq;
const #25 = Asciz	([Ljava/lang/Object;)V;
const #26 = NameAndType	#24:#25;//  table_$eq:([Ljava/lang/Object;)V
const #27 = InterfaceMethod	#19.#26;	//  scala/collection/mutable/FlatHashTable.table_$eq:([Ljava/lang/Object;)V
const #28 = Asciz	tableSize;
const #29 = Asciz	()I;
const #30 = NameAndType	#28:#29;//  tableSize:()I
const #31 = InterfaceMethod	#19.#30;	//  scala/collection/mutable/FlatHashTable.tableSize:()I
const #32 = Asciz	tableSize_$eq;
const #33 = Asciz	(I)V;
const #34 = NameAndType	#32:#33;//  tableSize_$eq:(I)V
const #35 = InterfaceMethod	#19.#34;	//  scala/collection/mutable/FlatHashTable.tableSize_$eq:(I)V
const #36 = Asciz	threshold;
const #37 = NameAndType	#36:#29;//  threshold:()I
const #38 = InterfaceMethod	#19.#37;	//  scala/collection/mutable/FlatHashTable.threshold:()I
const #39 = Asciz	threshold_$eq;
const #40 = NameAndType	#39:#33;//  threshold_$eq:(I)V
const #41 = InterfaceMethod	#19.#40;	//  scala/collection/mutable/FlatHashTable.threshold_$eq:(I)V
const #42 = Asciz	this;
const #43 = Asciz	Lscala/collection/immutable/HashSet$$anon$1;;
const #44 = Asciz	$outer;
const #45 = Asciz	Lscala/collection/immutable/HashSet;;
const #46 = Asciz	LocalVariableTable;
const #47 = Asciz	(Lscala/collection/immutable/HashSet<TA;>;)V;
const #48 = Asciz	Signature;
const #49 = Asciz	loadFactor;
const #50 = Asciz	initialSize;
const #51 = Asciz	Lscala/collection/immutable/HashSet<TA;>;;
const #52 = Asciz	Scala;
const #53 = Asciz	InnerClasses;
const #54 = Asciz	$anon$1;

{
public scala.collection.immutable.HashSet$$anon$1(scala.collection.immutable.HashSet, int);
  Code:
   Stack=2, Locals=3, Args_size=3
   0:	aload_0
   1:	iload_2
   2:	putfield	#12; //Field lv$1:I
   5:	aload_0
   6:	invokespecial	#17; //Method scala/collection/immutable/HashSet."<init>":()V
   9:	aload_0
   10:	aload_1
   11:	invokeinterface	#23,  1; //InterfaceMethod scala/collection/mutable/FlatHashTable.table:()[Ljava/lang/Object;
   16:	invokeinterface	#27,  2; //InterfaceMethod scala/collection/mutable/FlatHashTable.table_$eq:([Ljava/lang/Object;)V
   21:	aload_0
   22:	aload_1
   23:	invokeinterface	#31,  1; //InterfaceMethod scala/collection/mutable/FlatHashTable.tableSize:()I
   28:	invokeinterface	#35,  2; //InterfaceMethod scala/collection/mutable/FlatHashTable.tableSize_$eq:(I)V
   33:	aload_0
   34:	aload_1
   35:	invokeinterface	#38,  1; //InterfaceMethod scala/collection/mutable/FlatHashTable.threshold:()I
   40:	invokeinterface	#41,  2; //InterfaceMethod scala/collection/mutable/FlatHashTable.threshold_$eq:(I)V
   45:	return
  LineNumberTable: 
   line 103: 0
   line 106: 9
   line 107: 21
   line 108: 33

  LocalVariableTable: 
   Start  Length  Slot  Name   Signature
   0      46      0    this       Lscala/collection/immutable/HashSet$$anon$1;
   0      46      1    $outer       Lscala/collection/immutable/HashSet;

  Signature: length = 0x2
   00 2F 

public int loadFactor();
  Code:
   Stack=1, Locals=1, Args_size=1
   0:	aload_0
   1:	getfield	#12; //Field lv$1:I
   4:	ireturn
  LineNumberTable: 
   line 105: 0


public int initialSize();
  Code:
   Stack=1, Locals=1, Args_size=1
   0:	iconst_0
   1:	ireturn
  LineNumberTable: 
   line 104: 0


}

