Compiled from "HashMap.scala"
public final class scala.collection.immutable.HashMap$$anon$1 extends scala.collection.immutable.HashMap
  SourceFile: "HashMap.scala"
  Signature: length = 0x2
   00 33 
  Scala: length = 0x
   
  InnerClass: 
   public final $anon$1=class scala/collection/immutable/HashMap$$anon$1 of class scala/collection/immutable/HashMap
  minor version: 0
  major version: 49
  Constant pool:
Asciz	SourceFile;
Asciz	HashMap.scala;
Asciz	lv$1;
Asciz	I;
Asciz	<init>;
Asciz	(Lscala/collection/immutable/HashMap;I)V;
Asciz	Code;
Asciz	LineNumberTable;
Asciz	scala/collection/immutable/HashMap$$anon$1;
class	scala/collection/immutable/HashMap$$anon$1
NameAndType	lv$1:I
Field	scala/collection/immutable/HashMap$$anon$1.lv$1:I
Asciz	scala/collection/immutable/HashMap;
class	scala/collection/immutable/HashMap
Asciz	()V;
NameAndType	"<init>":()V
Method	scala/collection/immutable/HashMap."<init>":()V
Asciz	scala/collection/mutable/HashTable;
class	scala/collection/mutable/HashTable
Asciz	table;
Asciz	()[Lscala/collection/mutable/HashEntry;;
NameAndType	table:()[Lscala/collection/mutable/HashEntry;
InterfaceMethod	scala/collection/mutable/HashTable.table:()[Lscala/collection/mutable/HashEntry;
Asciz	table_$eq;
Asciz	([Lscala/collection/mutable/HashEntry;)V;
NameAndType	table_$eq:([Lscala/collection/mutable/HashEntry;)V
InterfaceMethod	scala/collection/mutable/HashTable.table_$eq:([Lscala/collection/mutable/HashEntry;)V
Asciz	tableSize;
Asciz	()I;
NameAndType	tableSize:()I
InterfaceMethod	scala/collection/mutable/HashTable.tableSize:()I
Asciz	tableSize_$eq;
Asciz	(I)V;
NameAndType	tableSize_$eq:(I)V
InterfaceMethod	scala/collection/mutable/HashTable.tableSize_$eq:(I)V
Asciz	threshold;
NameAndType	threshold:()I
InterfaceMethod	scala/collection/mutable/HashTable.threshold:()I
Asciz	threshold_$eq;
NameAndType	threshold_$eq:(I)V
InterfaceMethod	scala/collection/mutable/HashTable.threshold_$eq:(I)V
Asciz	this;
Asciz	Lscala/collection/immutable/HashMap$$anon$1;;
Asciz	$outer;
Asciz	Lscala/collection/immutable/HashMap;;
Asciz	LocalVariableTable;
Asciz	(Lscala/collection/immutable/HashMap<TA;TB;>;)V;
Asciz	Signature;
Asciz	loadFactor;
Asciz	initialSize;
Asciz	Lscala/collection/immutable/HashMap<TA;TB;>;;
Asciz	Scala;
Asciz	InnerClasses;
Asciz	$anon$1;

{
private final int lv$1;
  Signature: I

public scala.collection.immutable.HashMap$$anon$1(scala.collection.immutable.HashMap, int);
  Signature: (Lscala/collection/immutable/HashMap;I)V
  Code:
   Stack=2, Locals=3, Args_size=3
	aload_0
	iload_2
	putfield	Field lv$1:I
	aload_0
	invokespecial	Method scala/collection/immutable/HashMap."<init>":()V
	aload_0
	aload_1
	invokeinterface	InterfaceMethod scala/collection/mutable/HashTable.table:()[Lscala/collection/mutable/HashEntry;
	invokeinterface	InterfaceMethod scala/collection/mutable/HashTable.table_$eq:([Lscala/collection/mutable/HashEntry;)V
	aload_0
	aload_1
	invokeinterface	InterfaceMethod scala/collection/mutable/HashTable.tableSize:()I
	invokeinterface	InterfaceMethod scala/collection/mutable/HashTable.tableSize_$eq:(I)V
	aload_0
	aload_1
	invokeinterface	InterfaceMethod scala/collection/mutable/HashTable.threshold:()I
	invokeinterface	InterfaceMethod scala/collection/mutable/HashTable.threshold_$eq:(I)V
	return
  Labels:
  LocalVariableTable: 
   Start  Length  Slot  Name   Signature
   0      46      0    this       Lscala/collection/immutable/HashMap$$anon$1;
   0      46      1    $outer       Lscala/collection/immutable/HashMap;

  Signature: length = 0x2
   00 2F 

public int loadFactor();
  Signature: ()I
  Code:
   Stack=1, Locals=1, Args_size=1
	aload_0
	getfield	Field lv$1:I
	ireturn
  Labels:

public int initialSize();
  Signature: ()I
  Code:
   Stack=1, Locals=1, Args_size=1
	iconst_0
	ireturn
  Labels:

}

