Compiled from "HashMap.scala"
public final class scala.collection.immutable.HashMap$HashMapCollision1$$anonfun$updated0$1 extends scala.runtime.AbstractFunction1 implements java.io.Serializable
  SourceFile: "HashMap.scala"
  Scala: length = 0x
   
  InnerClass: 
   public HashMapCollision1=class scala/collection/immutable/HashMap$HashMapCollision1 of class scala/collection/immutable/HashMap
   public final $anonfun$updated0$1=class scala/collection/immutable/HashMap$HashMapCollision1$$anonfun$updated0$1 of class scala/collection/immutable/HashMap$HashMapCollision1
  minor version: 0
  major version: 49
  Constant pool:
Asciz	SourceFile;
Asciz	HashMap.scala;
Asciz	<clinit>;
Asciz	()V;
Asciz	Code;
Asciz	serialVersionUID;
Asciz	J;
Asciz	scala/collection/immutable/HashMap$HashMapCollision1$$anonfun$updated0$1;
class	scala/collection/immutable/HashMap$HashMapCollision1$$anonfun$updated0$1
NameAndType	serialVersionUID:J
Field	scala/collection/immutable/HashMap$HashMapCollision1$$anonfun$updated0$1.serialVersionUID:J
Asciz	m$1;
Asciz	Lscala/runtime/ObjectRef;;
Asciz	level$1;
Asciz	I;
Asciz	$outer;
Asciz	Lscala/collection/immutable/HashMap$HashMapCollision1;;
Asciz	apply;
Asciz	(Lscala/Tuple2;)V;
Asciz	LineNumberTable;
NameAndType	m$1:Lscala/runtime/ObjectRef;
Field	scala/collection/immutable/HashMap$HashMapCollision1$$anonfun$updated0$1.m$1:Lscala/runtime/ObjectRef;
Asciz	scala/runtime/ObjectRef;
class	scala/runtime/ObjectRef
Asciz	elem;
Asciz	Ljava/lang/Object;;
NameAndType	elem:Ljava/lang/Object;
Field	scala/runtime/ObjectRef.elem:Ljava/lang/Object;
Asciz	scala/collection/immutable/HashMap;
class	scala/collection/immutable/HashMap
Asciz	scala/Tuple2;
class	scala/Tuple2
Asciz	_1;
Asciz	()Ljava/lang/Object;;
NameAndType	_1:()Ljava/lang/Object;
Method	scala/Tuple2._1:()Ljava/lang/Object;
NameAndType	$outer:Lscala/collection/immutable/HashMap$HashMapCollision1;
Field	scala/collection/immutable/HashMap$HashMapCollision1$$anonfun$updated0$1.$outer:Lscala/collection/immutable/HashMap$HashMapCollision1;
Asciz	scala/collection/immutable/HashMap$HashMapCollision1;
class	scala/collection/immutable/HashMap$HashMapCollision1
Asciz	hash;
Asciz	()I;
NameAndType	hash:()I
Method	scala/collection/immutable/HashMap$HashMapCollision1.hash:()I
NameAndType	level$1:I
Field	scala/collection/immutable/HashMap$HashMapCollision1$$anonfun$updated0$1.level$1:I
Asciz	_2;
NameAndType	_2:()Ljava/lang/Object;
Method	scala/Tuple2._2:()Ljava/lang/Object;
Asciz	updated0;
Asciz	(Ljava/lang/Object;IILjava/lang/Object;Lscala/Tuple2;)Lscala/collection/immutable/HashMap;;
NameAndType	updated0:(Ljava/lang/Object;IILjava/lang/Object;Lscala/Tuple2;)Lscala/collection/immutable/HashMap;
Method	scala/collection/immutable/HashMap.updated0:(Ljava/lang/Object;IILjava/lang/Object;Lscala/Tuple2;)Lscala/collection/immutable/HashMap;
Asciz	scala/MatchError;
class	scala/MatchError
Asciz	<init>;
Asciz	(Ljava/lang/Object;)V;
NameAndType	"<init>":(Ljava/lang/Object;)V
Method	scala/MatchError."<init>":(Ljava/lang/Object;)V
Asciz	this;
Asciz	Lscala/collection/immutable/HashMap$HashMapCollision1$$anonfun$updated0$1;;
Asciz	temp1;
Asciz	Lscala/Tuple2;;
Asciz	LocalVariableTable;
Asciz	(Lscala/Tuple2<TA;TB;>;)V;
Asciz	Signature;
Asciz	(Ljava/lang/Object;)Ljava/lang/Object;;
NameAndType	apply:(Lscala/Tuple2;)V
Method	scala/collection/immutable/HashMap$HashMapCollision1$$anonfun$updated0$1.apply:(Lscala/Tuple2;)V
Asciz	scala/runtime/BoxedUnit;
class	scala/runtime/BoxedUnit
Asciz	UNIT;
Asciz	Lscala/runtime/BoxedUnit;;
NameAndType	UNIT:Lscala/runtime/BoxedUnit;
Field	scala/runtime/BoxedUnit.UNIT:Lscala/runtime/BoxedUnit;
Asciz	v1;
Asciz	(Lscala/collection/immutable/HashMap$HashMapCollision1;ILscala/runtime/ObjectRef;)V;
Asciz	java/lang/NullPointerException;
class	java/lang/NullPointerException
NameAndType	"<init>":()V
Method	java/lang/NullPointerException."<init>":()V
Asciz	scala/runtime/AbstractFunction1;
class	scala/runtime/AbstractFunction1
Method	scala/runtime/AbstractFunction1."<init>":()V
Asciz	(Lscala/collection/immutable/HashMap$HashMapCollision1<TA;TB;>;)V;
Asciz	Scala;
Asciz	InnerClasses;
Asciz	HashMapCollision1;
Asciz	$anonfun$updated0$1;
Asciz	java/io/Serializable;
class	java/io/Serializable

{
public static final long serialVersionUID;
  Signature: J

private final scala.runtime.ObjectRef m$1;
  Signature: Lscala/runtime/ObjectRef;

private final int level$1;
  Signature: I

private final scala.collection.immutable.HashMap$HashMapCollision1 $outer;
  Signature: Lscala/collection/immutable/HashMap$HashMapCollision1;

public static {};
  Signature: ()V
  Code:
   Stack=2, Locals=0, Args_size=0
	lconst_0
	putstatic	Field serialVersionUID:J
	return
  Labels:

public final void apply(scala.Tuple2);
  Signature: (Lscala/Tuple2;)V
  Code:
   Stack=7, Locals=3, Args_size=2
	aload_1
	astore_2
	aload_2
	ifnull	l1 // new
	aload_0
	getfield	Field m$1:Lscala/runtime/ObjectRef;
	aload_0
	getfield	Field m$1:Lscala/runtime/ObjectRef;
	getfield	Field scala/runtime/ObjectRef.elem:Ljava/lang/Object;
	checkcast	class scala/collection/immutable/HashMap
	aload_2
	invokevirtual	Method scala/Tuple2._1:()Ljava/lang/Object;
	aload_0
	getfield	Field $outer:Lscala/collection/immutable/HashMap$HashMapCollision1;
	invokevirtual	Method scala/collection/immutable/HashMap$HashMapCollision1.hash:()I
	aload_0
	getfield	Field level$1:I
	aload_2
	invokevirtual	Method scala/Tuple2._2:()Ljava/lang/Object;
	aconst_null
	pop
	aconst_null
	invokevirtual	Method scala/collection/immutable/HashMap.updated0:(Ljava/lang/Object;IILjava/lang/Object;Lscala/Tuple2;)Lscala/collection/immutable/HashMap;
	putfield	Field scala/runtime/ObjectRef.elem:Ljava/lang/Object;
	return
l1	new	class scala/MatchError
	dup
	aload_2
	invokespecial	Method scala/MatchError."<init>":(Ljava/lang/Object;)V
	athrow
  Labels:
   	l1 = 49 // new
  LocalVariableTable: 
   Start  Length  Slot  Name   Signature
   0      58      0    this       Lscala/collection/immutable/HashMap$HashMapCollision1$$anonfun$updated0$1;
   2      56      2    temp1       Lscala/Tuple2;

  Signature: length = 0x2
   00 41 

public final java.lang.Object apply(java.lang.Object);
  Signature: (Ljava/lang/Object;)Ljava/lang/Object;
  Code:
   Stack=2, Locals=2, Args_size=2
	aload_0
	aload_1
	checkcast	class scala/Tuple2
	invokevirtual	Method apply:(Lscala/Tuple2;)V
	getstatic	Field scala/runtime/BoxedUnit.UNIT:Lscala/runtime/BoxedUnit;
	areturn
  Labels:
  LocalVariableTable: 
   Start  Length  Slot  Name   Signature
   0      12      0    this       Lscala/collection/immutable/HashMap$HashMapCollision1$$anonfun$updated0$1;
   0      12      1    v1       Ljava/lang/Object;


public scala.collection.immutable.HashMap$HashMapCollision1$$anonfun$updated0$1(scala.collection.immutable.HashMap$HashMapCollision1, int, scala.runtime.ObjectRef);
  Signature: (Lscala/collection/immutable/HashMap$HashMapCollision1;ILscala/runtime/ObjectRef;)V
  Code:
   Stack=2, Locals=4, Args_size=4
	aload_1
	ifnonnull	l1 // aload_0
	new	class java/lang/NullPointerException
	dup
	invokespecial	Method java/lang/NullPointerException."<init>":()V
	athrow
l1	aload_0
	aload_1
	putfield	Field $outer:Lscala/collection/immutable/HashMap$HashMapCollision1;
	aload_0
	iload_2
	putfield	Field level$1:I
	aload_0
	aload_3
	putfield	Field m$1:Lscala/runtime/ObjectRef;
	aload_0
	invokespecial	Method scala/runtime/AbstractFunction1."<init>":()V
	return
  Labels:
   	l1 = 12 // aload_0
  LocalVariableTable: 
   Start  Length  Slot  Name   Signature
   0      32      0    this       Lscala/collection/immutable/HashMap$HashMapCollision1$$anonfun$updated0$1;
   0      32      1    $outer       Lscala/collection/immutable/HashMap$HashMapCollision1;

  Signature: length = 0x2
   00 55 

}

