Compiled from "HashSet.scala"
public final class scala.collection.immutable.HashSet$$anonfun$makeCopy$2 extends scala.runtime.AbstractFunction1 implements java.io.Serializable
  InnerClass: 
   public final $anonfun$makeCopy$2=class scala/collection/immutable/HashSet$$anonfun$makeCopy$2 of class scala/collection/immutable/HashSet
  Scala: length = 0x
   
  SourceFile: "HashSet.scala"
  minor version: 0
  major version: 49
  Constant pool:
class	java/io/Serializable
class	scala/collection/immutable/HashSet
class	scala/collection/immutable/HashSet$$anonfun$makeCopy$2
class	scala/runtime/AbstractFunction1
class	scala/runtime/BoxesRunTime
Field	scala/collection/immutable/HashSet$$anonfun$makeCopy$2.last$1:Lscala/collection/immutable/HashSet;
Field	scala/collection/immutable/HashSet$$anonfun$makeCopy$2.serialVersionUID:J
Method	scala/collection/immutable/HashSet$$anonfun$makeCopy$2.apply:(Lscala/collection/immutable/HashSet;)Z
Method	scala/runtime/AbstractFunction1."<init>":()V
Method	scala/runtime/BoxesRunTime.boxToBoolean:(Z)Ljava/lang/Boolean;
NameAndType	"<init>":()V
NameAndType	apply:(Lscala/collection/immutable/HashSet;)Z
NameAndType	boxToBoolean:(Z)Ljava/lang/Boolean;
NameAndType	last$1:Lscala/collection/immutable/HashSet;
NameAndType	serialVersionUID:J
Asciz	$anonfun$makeCopy$2;
Asciz	$outer;
Asciz	()V;
Asciz	(Ljava/lang/Object;)Ljava/lang/Object;;
Asciz	(Lscala/collection/immutable/HashSet;)Z;
Asciz	(Lscala/collection/immutable/HashSet;Lscala/collection/immutable/HashSet;)V;
Asciz	(Lscala/collection/immutable/HashSet<TA;>;)V;
Asciz	(Lscala/collection/immutable/HashSet<TA;>;)Z;
Asciz	(Z)Ljava/lang/Boolean;;
Asciz	<clinit>;
Asciz	<init>;
Asciz	Code;
Asciz	HashSet.scala;
Asciz	InnerClasses;
Asciz	J;
Asciz	LineNumberTable;
Asciz	Ljava/lang/Object;;
Asciz	LocalVariableTable;
Asciz	Lscala/collection/immutable/HashSet$$anonfun$makeCopy$2;;
Asciz	Lscala/collection/immutable/HashSet;;
Asciz	Scala;
Asciz	Signature;
Asciz	SourceFile;
Asciz	apply;
Asciz	boxToBoolean;
Asciz	java/io/Serializable;
Asciz	last$1;
Asciz	scala/collection/immutable/HashSet;
Asciz	scala/collection/immutable/HashSet$$anonfun$makeCopy$2;
Asciz	scala/runtime/AbstractFunction1;
Asciz	scala/runtime/BoxesRunTime;
Asciz	serialVersionUID;
Asciz	this;
Asciz	v1;

{
public static final long serialVersionUID;
  Signature: J

public final scala.collection.immutable.HashSet last$1;
  Signature: Lscala/collection/immutable/HashSet;

public static {};
  Signature: ()V
  Code:
   Stack=2, Locals=0, Args_size=0
	lconst_0
	putstatic	Field serialVersionUID:J
	return
  Labels:

public scala.collection.immutable.HashSet$$anonfun$makeCopy$2(scala.collection.immutable.HashSet, scala.collection.immutable.HashSet);
  Signature: (Lscala/collection/immutable/HashSet;Lscala/collection/immutable/HashSet;)V
  Code:
   Stack=2, Locals=3, Args_size=3
	aload_0
	aload_2
	putfield	Field last$1:Lscala/collection/immutable/HashSet;
	aload_0
	invokespecial	Method scala/runtime/AbstractFunction1."<init>":()V
	return
  Labels:
  LocalVariableTable: 
   Start  Length  Slot  Name   Signature
   0      10      0    this       Lscala/collection/immutable/HashSet$$anonfun$makeCopy$2;
   0      10      1    $outer       Lscala/collection/immutable/HashSet;

  Signature: length = 0x2
   00 16 

public final java.lang.Object apply(java.lang.Object);
  Signature: (Ljava/lang/Object;)Ljava/lang/Object;
  Code:
   Stack=2, Locals=3, Args_size=2
	aload_0
	aload_1
	checkcast	class scala/collection/immutable/HashSet
	invokevirtual	Method apply:(Lscala/collection/immutable/HashSet;)Z
	istore_2
	iload_2
	invokestatic	Method scala/runtime/BoxesRunTime.boxToBoolean:(Z)Ljava/lang/Boolean;
	areturn
  Labels:
  LocalVariableTable: 
   Start  Length  Slot  Name   Signature
   0      14      0    this       Lscala/collection/immutable/HashSet$$anonfun$makeCopy$2;
   0      14      1    v1       Ljava/lang/Object;


public final boolean apply(scala.collection.immutable.HashSet);
  Signature: (Lscala/collection/immutable/HashSet;)Z
  Code:
   Stack=2, Locals=2, Args_size=2
	aload_1
	aload_0
	getfield	Field last$1:Lscala/collection/immutable/HashSet;
	if_acmpeq	l1 // iconst_0
	iconst_1
	goto	l2 // ireturn
l1	iconst_0
l2	ireturn
  Labels:
   	l1 = 12 // iconst_0
   	l2 = 13 // ireturn
  Signature: length = 0x2
   00 17 

}

