Compiled from "IndexedSeq.scala"
public final class scala.collection.immutable.IndexedSeq$$anonfun$newBuilder$1 extends scala.runtime.AbstractFunction1 implements java.io.Serializable
  SourceFile: "IndexedSeq.scala"
  Scala: length = 0x
   
  InnerClass: 
   public #43= #31 of #42; //Impl=class scala/collection/immutable/IndexedSeq$Impl of class scala/collection/immutable/IndexedSeq
   public final #44= #9 of #42; //$anonfun$newBuilder$1=class scala/collection/immutable/IndexedSeq$$anonfun$newBuilder$1 of class scala/collection/immutable/IndexedSeq
  minor version: 0
  major version: 49
  Constant pool:
const #1 = Asciz	SourceFile;
const #2 = Asciz	IndexedSeq.scala;
const #3 = Asciz	<clinit>;
const #4 = Asciz	()V;
const #5 = Asciz	Code;
const #6 = Asciz	serialVersionUID;
const #7 = Asciz	J;
const #8 = Asciz	scala/collection/immutable/IndexedSeq$$anonfun$newBuilder$1;
const #9 = class	#8;	//  scala/collection/immutable/IndexedSeq$$anonfun$newBuilder$1
const #10 = NameAndType	#6:#7;//  serialVersionUID:J
const #11 = Field	#9.#10;	//  scala/collection/immutable/IndexedSeq$$anonfun$newBuilder$1.serialVersionUID:J
const #12 = Asciz	<init>;
const #13 = Asciz	LineNumberTable;
const #14 = Asciz	scala/runtime/AbstractFunction1;
const #15 = class	#14;	//  scala/runtime/AbstractFunction1
const #16 = NameAndType	#12:#4;//  "<init>":()V
const #17 = Method	#15.#16;	//  scala/runtime/AbstractFunction1."<init>":()V
const #18 = Asciz	apply;
const #19 = Asciz	(Ljava/lang/Object;)Ljava/lang/Object;;
const #20 = Asciz	scala/collection/mutable/ArrayBuffer;
const #21 = class	#20;	//  scala/collection/mutable/ArrayBuffer
const #22 = Asciz	(Lscala/collection/mutable/ArrayBuffer;)Lscala/collection/immutable/IndexedSeq$Impl;;
const #23 = NameAndType	#18:#22;//  apply:(Lscala/collection/mutable/ArrayBuffer;)Lscala/collection/immutable/IndexedSeq$Impl;
const #24 = Method	#9.#23;	//  scala/collection/immutable/IndexedSeq$$anonfun$newBuilder$1.apply:(Lscala/collection/mutable/ArrayBuffer;)Lscala/collection/immutable/IndexedSeq$Impl;
const #25 = Asciz	this;
const #26 = Asciz	Lscala/collection/immutable/IndexedSeq$$anonfun$newBuilder$1;;
const #27 = Asciz	v1;
const #28 = Asciz	Ljava/lang/Object;;
const #29 = Asciz	LocalVariableTable;
const #30 = Asciz	scala/collection/immutable/IndexedSeq$Impl;
const #31 = class	#30;	//  scala/collection/immutable/IndexedSeq$Impl
const #32 = Asciz	(Lscala/collection/mutable/ArrayBuffer;)V;
const #33 = NameAndType	#12:#32;//  "<init>":(Lscala/collection/mutable/ArrayBuffer;)V
const #34 = Method	#31.#33;	//  scala/collection/immutable/IndexedSeq$Impl."<init>":(Lscala/collection/mutable/ArrayBuffer;)V
const #35 = Asciz	buf;
const #36 = Asciz	Lscala/collection/mutable/ArrayBuffer;;
const #37 = Asciz	(Lscala/collection/mutable/ArrayBuffer<TA;>;)Lscala/collection/immutable/IndexedSeq$Impl<TA;>;;
const #38 = Asciz	Signature;
const #39 = Asciz	Scala;
const #40 = Asciz	InnerClasses;
const #41 = Asciz	scala/collection/immutable/IndexedSeq;
const #42 = class	#41;	//  scala/collection/immutable/IndexedSeq
const #43 = Asciz	Impl;
const #44 = Asciz	$anonfun$newBuilder$1;
const #45 = Asciz	java/io/Serializable;
const #46 = class	#45;	//  java/io/Serializable

{
public static final long serialVersionUID;

public static {};
  Code:
   Stack=2, Locals=0, Args_size=0
   0:	lconst_0
   1:	putstatic	#11; //Field serialVersionUID:J
   4:	return

public scala.collection.immutable.IndexedSeq$$anonfun$newBuilder$1();
  Code:
   Stack=1, Locals=1, Args_size=1
   0:	aload_0
   1:	invokespecial	#17; //Method scala/runtime/AbstractFunction1."<init>":()V
   4:	return
  LineNumberTable: 
   line 39: 0


public final java.lang.Object apply(java.lang.Object);
  Code:
   Stack=2, Locals=2, Args_size=2
   0:	aload_0
   1:	aload_1
   2:	checkcast	#21; //class scala/collection/mutable/ArrayBuffer
   5:	invokevirtual	#24; //Method apply:(Lscala/collection/mutable/ArrayBuffer;)Lscala/collection/immutable/IndexedSeq$Impl;
   8:	areturn
  LineNumberTable: 
   line 39: 0

  LocalVariableTable: 
   Start  Length  Slot  Name   Signature
   0      9      0    this       Lscala/collection/immutable/IndexedSeq$$anonfun$newBuilder$1;
   0      9      1    v1       Ljava/lang/Object;


public final scala.collection.immutable.IndexedSeq$Impl apply(scala.collection.mutable.ArrayBuffer);
  Code:
   Stack=3, Locals=2, Args_size=2
   0:	new	#31; //class scala/collection/immutable/IndexedSeq$Impl
   3:	dup
   4:	aload_1
   5:	invokespecial	#34; //Method scala/collection/immutable/IndexedSeq$Impl."<init>":(Lscala/collection/mutable/ArrayBuffer;)V
   8:	areturn
  LineNumberTable: 
   line 39: 0

  LocalVariableTable: 
   Start  Length  Slot  Name   Signature
   0      9      0    this       Lscala/collection/immutable/IndexedSeq$$anonfun$newBuilder$1;
   0      9      1    buf       Lscala/collection/mutable/ArrayBuffer;

  Signature: length = 0x2
   00 25 

}

