Compiled from "IntMap.scala"
public final class scala.collection.immutable.IntMap$$anonfun$unionWith$1 extends scala.runtime.AbstractFunction2 implements java.io.Serializable
  SourceFile: "IntMap.scala"
  Scala: length = 0x
   
  InnerClass: 
   public final $anonfun$unionWith$1=class scala/collection/immutable/IntMap$$anonfun$unionWith$1 of class scala/collection/immutable/IntMap
  minor version: 0
  major version: 49
  Constant pool:
Asciz	SourceFile;
Asciz	IntMap.scala;
Asciz	<clinit>;
Asciz	()V;
Asciz	Code;
Asciz	serialVersionUID;
Asciz	J;
Asciz	scala/collection/immutable/IntMap$$anonfun$unionWith$1;
class	scala/collection/immutable/IntMap$$anonfun$unionWith$1
NameAndType	serialVersionUID:J
Field	scala/collection/immutable/IntMap$$anonfun$unionWith$1.serialVersionUID:J
Asciz	key$1;
Asciz	I;
Asciz	f$1;
Asciz	Lscala/Function3;;
Asciz	apply;
Asciz	(Ljava/lang/Object;Ljava/lang/Object;)Ljava/lang/Object;;
Asciz	LineNumberTable;
NameAndType	f$1:Lscala/Function3;
Field	scala/collection/immutable/IntMap$$anonfun$unionWith$1.f$1:Lscala/Function3;
NameAndType	key$1:I
Field	scala/collection/immutable/IntMap$$anonfun$unionWith$1.key$1:I
Asciz	scala/runtime/BoxesRunTime;
class	scala/runtime/BoxesRunTime
Asciz	boxToInteger;
Asciz	(I)Ljava/lang/Integer;;
NameAndType	boxToInteger:(I)Ljava/lang/Integer;
Method	scala/runtime/BoxesRunTime.boxToInteger:(I)Ljava/lang/Integer;
Asciz	scala/Function3;
class	scala/Function3
Asciz	(Ljava/lang/Object;Ljava/lang/Object;Ljava/lang/Object;)Ljava/lang/Object;;
NameAndType	apply:(Ljava/lang/Object;Ljava/lang/Object;Ljava/lang/Object;)Ljava/lang/Object;
InterfaceMethod	scala/Function3.apply:(Ljava/lang/Object;Ljava/lang/Object;Ljava/lang/Object;)Ljava/lang/Object;
Asciz	this;
Asciz	Lscala/collection/immutable/IntMap$$anonfun$unionWith$1;;
Asciz	x;
Asciz	Ljava/lang/Object;;
Asciz	y;
Asciz	LocalVariableTable;
Asciz	(TS;TS;)TS;;
Asciz	Signature;
Asciz	<init>;
Asciz	(Lscala/collection/immutable/IntMap;Lscala/Function3;I)V;
Asciz	scala/runtime/AbstractFunction2;
class	scala/runtime/AbstractFunction2
NameAndType	"<init>":()V
Method	scala/runtime/AbstractFunction2."<init>":()V
Asciz	$outer;
Asciz	Lscala/collection/immutable/IntMap;;
Asciz	(Lscala/collection/immutable/IntMap<TT;>;)V;
Asciz	Scala;
Asciz	InnerClasses;
Asciz	scala/collection/immutable/IntMap;
class	scala/collection/immutable/IntMap
Asciz	$anonfun$unionWith$1;
Asciz	java/io/Serializable;
class	java/io/Serializable

{
public static final long serialVersionUID;
  Signature: J

private final int key$1;
  Signature: I

private final scala.Function3 f$1;
  Signature: Lscala/Function3;

public static {};
  Signature: ()V
  Code:
   Stack=2, Locals=0, Args_size=0
	lconst_0
	putstatic	Field serialVersionUID:J
	return
  Labels:

public final java.lang.Object apply(java.lang.Object, java.lang.Object);
  Signature: (Ljava/lang/Object;Ljava/lang/Object;)Ljava/lang/Object;
  Code:
   Stack=4, Locals=4, Args_size=3
	aload_0
	getfield	Field f$1:Lscala/Function3;
	aload_0
	getfield	Field key$1:I
	istore_3
	iload_3
	invokestatic	Method scala/runtime/BoxesRunTime.boxToInteger:(I)Ljava/lang/Integer;
	aload_2
	aload_1
	invokeinterface	InterfaceMethod scala/Function3.apply:(Ljava/lang/Object;Ljava/lang/Object;Ljava/lang/Object;)Ljava/lang/Object;
	areturn
  Labels:
  LocalVariableTable: 
   Start  Length  Slot  Name   Signature
   0      21      0    this       Lscala/collection/immutable/IntMap$$anonfun$unionWith$1;
   0      21      1    x       Ljava/lang/Object;
   0      21      2    y       Ljava/lang/Object;

  Signature: length = 0x2
   00 28 

public scala.collection.immutable.IntMap$$anonfun$unionWith$1(scala.collection.immutable.IntMap, scala.Function3, int);
  Signature: (Lscala/collection/immutable/IntMap;Lscala/Function3;I)V
  Code:
   Stack=2, Locals=4, Args_size=4
	aload_0
	aload_2
	putfield	Field f$1:Lscala/Function3;
	aload_0
	iload_3
	putfield	Field key$1:I
	aload_0
	invokespecial	Method scala/runtime/AbstractFunction2."<init>":()V
	return
  Labels:
  LocalVariableTable: 
   Start  Length  Slot  Name   Signature
   0      15      0    this       Lscala/collection/immutable/IntMap$$anonfun$unionWith$1;
   0      15      1    $outer       Lscala/collection/immutable/IntMap;

  Signature: length = 0x2
   00 32 

}

