Compiled from "IntMap.scala"
public final class scala.collection.immutable.IntMap$ extends java.lang.Object implements scala.ScalaObject
  SourceFile: "IntMap.scala"
  Scala: length = 0x
   
  InnerClass: 
   public #64= #63 of #36; //Bin=class scala/collection/immutable/IntMap$Bin of class scala/collection/immutable/IntMap
   public #65= #46 of #36; //Tip=class scala/collection/immutable/IntMap$Tip of class scala/collection/immutable/IntMap
   public final #66= #27 of #36; //$anonfun$apply$1=class scala/collection/immutable/IntMap$$anonfun$apply$1 of class scala/collection/immutable/IntMap
   public final #69= #68 of #36; //$anonfun$toList$1=class scala/collection/immutable/IntMap$$anonfun$toList$1 of class scala/collection/immutable/IntMap
   public final #72= #71 of #36; //$anonfun$unionWith$1=class scala/collection/immutable/IntMap$$anonfun$unionWith$1 of class scala/collection/immutable/IntMap
   public final #75= #74 of #36; //$anonfun$unionWith$2=class scala/collection/immutable/IntMap$$anonfun$unionWith$2 of class scala/collection/immutable/IntMap
   public final #78= #77 of #36; //$anonfun$$plus$plus$1=class scala/collection/immutable/IntMap$$anonfun$$plus$plus$1 of class scala/collection/immutable/IntMap
   public final #81= #80 of #36; //$anonfun$intersection$1=class scala/collection/immutable/IntMap$$anonfun$intersection$1 of class scala/collection/immutable/IntMap
  minor version: 0
  major version: 49
  Constant pool:
const #1 = Asciz	SourceFile;
const #2 = Asciz	IntMap.scala;
const #3 = Asciz	Scala;
const #4 = Asciz	MODULE$;
const #5 = Asciz	Lscala/collection/immutable/IntMap$;;
const #6 = Asciz	<clinit>;
const #7 = Asciz	()V;
const #8 = Asciz	Code;
const #9 = Asciz	scala/collection/immutable/IntMap$;
const #10 = class	#9;	//  scala/collection/immutable/IntMap$
const #11 = Asciz	<init>;
const #12 = NameAndType	#11:#7;//  "<init>":()V
const #13 = Method	#10.#12;	//  scala/collection/immutable/IntMap$."<init>":()V
const #14 = Asciz	LineNumberTable;
const #15 = Asciz	java/lang/Object;
const #16 = class	#15;	//  java/lang/Object
const #17 = Method	#16.#12;	//  java/lang/Object."<init>":()V
const #18 = NameAndType	#4:#5;//  MODULE$:Lscala/collection/immutable/IntMap$;
const #19 = Field	#10.#18;	//  scala/collection/immutable/IntMap$.MODULE$:Lscala/collection/immutable/IntMap$;
const #20 = Asciz	apply;
const #21 = Asciz	(Lscala/collection/Seq;)Lscala/collection/immutable/IntMap;;
const #22 = Asciz	empty;
const #23 = Asciz	()Lscala/collection/immutable/IntMap;;
const #24 = NameAndType	#22:#23;//  empty:()Lscala/collection/immutable/IntMap;
const #25 = Method	#10.#24;	//  scala/collection/immutable/IntMap$.empty:()Lscala/collection/immutable/IntMap;
const #26 = Asciz	scala/collection/immutable/IntMap$$anonfun$apply$1;
const #27 = class	#26;	//  scala/collection/immutable/IntMap$$anonfun$apply$1
const #28 = Method	#27.#12;	//  scala/collection/immutable/IntMap$$anonfun$apply$1."<init>":()V
const #29 = Asciz	scala/collection/TraversableLike;
const #30 = class	#29;	//  scala/collection/TraversableLike
const #31 = Asciz	foldLeft;
const #32 = Asciz	(Ljava/lang/Object;Lscala/Function2;)Ljava/lang/Object;;
const #33 = NameAndType	#31:#32;//  foldLeft:(Ljava/lang/Object;Lscala/Function2;)Ljava/lang/Object;
const #34 = InterfaceMethod	#30.#33;	//  scala/collection/TraversableLike.foldLeft:(Ljava/lang/Object;Lscala/Function2;)Ljava/lang/Object;
const #35 = Asciz	scala/collection/immutable/IntMap;
const #36 = class	#35;	//  scala/collection/immutable/IntMap
const #37 = Asciz	this;
const #38 = Asciz	elems;
const #39 = Asciz	Lscala/collection/Seq;;
const #40 = Asciz	LocalVariableTable;
const #41 = Asciz	<T:Ljava/lang/Object;>(Lscala/collection/Seq<Lscala/Tuple2<Ljava/lang/Integer;TT;>;>;)Lscala/collection/immutable/IntMap<TT;>;;
const #42 = Asciz	Signature;
const #43 = Asciz	singleton;
const #44 = Asciz	(ILjava/lang/Object;)Lscala/collection/immutable/IntMap;;
const #45 = Asciz	scala/collection/immutable/IntMap$Tip;
const #46 = class	#45;	//  scala/collection/immutable/IntMap$Tip
const #47 = Asciz	(ILjava/lang/Object;)V;
const #48 = NameAndType	#11:#47;//  "<init>":(ILjava/lang/Object;)V
const #49 = Method	#46.#48;	//  scala/collection/immutable/IntMap$Tip."<init>":(ILjava/lang/Object;)V
const #50 = Asciz	key;
const #51 = Asciz	I;
const #52 = Asciz	value;
const #53 = Asciz	Ljava/lang/Object;;
const #54 = Asciz	<T:Ljava/lang/Object;>(ITT;)Lscala/collection/immutable/IntMap<TT;>;;
const #55 = Asciz	scala/collection/immutable/IntMap$Nil$;
const #56 = class	#55;	//  scala/collection/immutable/IntMap$Nil$
const #57 = Asciz	Lscala/collection/immutable/IntMap$Nil$;;
const #58 = NameAndType	#4:#57;//  MODULE$:Lscala/collection/immutable/IntMap$Nil$;
const #59 = Field	#56.#58;	//  scala/collection/immutable/IntMap$Nil$.MODULE$:Lscala/collection/immutable/IntMap$Nil$;
const #60 = Asciz	<T:Ljava/lang/Object;>()Lscala/collection/immutable/IntMap<TT;>;;
const #61 = Asciz	InnerClasses;
const #62 = Asciz	scala/collection/immutable/IntMap$Bin;
const #63 = class	#62;	//  scala/collection/immutable/IntMap$Bin
const #64 = Asciz	Bin;
const #65 = Asciz	Tip;
const #66 = Asciz	$anonfun$apply$1;
const #67 = Asciz	scala/collection/immutable/IntMap$$anonfun$toList$1;
const #68 = class	#67;	//  scala/collection/immutable/IntMap$$anonfun$toList$1
const #69 = Asciz	$anonfun$toList$1;
const #70 = Asciz	scala/collection/immutable/IntMap$$anonfun$unionWith$1;
const #71 = class	#70;	//  scala/collection/immutable/IntMap$$anonfun$unionWith$1
const #72 = Asciz	$anonfun$unionWith$1;
const #73 = Asciz	scala/collection/immutable/IntMap$$anonfun$unionWith$2;
const #74 = class	#73;	//  scala/collection/immutable/IntMap$$anonfun$unionWith$2
const #75 = Asciz	$anonfun$unionWith$2;
const #76 = Asciz	scala/collection/immutable/IntMap$$anonfun$$plus$plus$1;
const #77 = class	#76;	//  scala/collection/immutable/IntMap$$anonfun$$plus$plus$1
const #78 = Asciz	$anonfun$$plus$plus$1;
const #79 = Asciz	scala/collection/immutable/IntMap$$anonfun$intersection$1;
const #80 = class	#79;	//  scala/collection/immutable/IntMap$$anonfun$intersection$1
const #81 = Asciz	$anonfun$intersection$1;
const #82 = Asciz	scala/ScalaObject;
const #83 = class	#82;	//  scala/ScalaObject

{
public static final scala.collection.immutable.IntMap$ MODULE$;

public static {};
  Code:
   Stack=1, Locals=0, Args_size=0
   0:	new	#10; //class scala/collection/immutable/IntMap$
   3:	invokespecial	#13; //Method "<init>":()V
   6:	return

public scala.collection.immutable.IntMap apply(scala.collection.Seq);
  Code:
   Stack=4, Locals=2, Args_size=2
   0:	aload_1
   1:	aload_0
   2:	invokevirtual	#25; //Method empty:()Lscala/collection/immutable/IntMap;
   5:	new	#27; //class scala/collection/immutable/IntMap$$anonfun$apply$1
   8:	dup
   9:	invokespecial	#28; //Method scala/collection/immutable/IntMap$$anonfun$apply$1."<init>":()V
   12:	invokeinterface	#34,  3; //InterfaceMethod scala/collection/TraversableLike.foldLeft:(Ljava/lang/Object;Lscala/Function2;)Ljava/lang/Object;
   17:	checkcast	#36; //class scala/collection/immutable/IntMap
   20:	areturn
  LineNumberTable: 
   line 60: 0

  LocalVariableTable: 
   Start  Length  Slot  Name   Signature
   0      21      0    this       Lscala/collection/immutable/IntMap$;
   0      21      1    elems       Lscala/collection/Seq;

  Signature: length = 0x2
   00 29 

public scala.collection.immutable.IntMap singleton(int, java.lang.Object);
  Code:
   Stack=4, Locals=3, Args_size=3
   0:	new	#46; //class scala/collection/immutable/IntMap$Tip
   3:	dup
   4:	iload_1
   5:	aload_2
   6:	invokespecial	#49; //Method scala/collection/immutable/IntMap$Tip."<init>":(ILjava/lang/Object;)V
   9:	areturn
  LineNumberTable: 
   line 58: 0

  LocalVariableTable: 
   Start  Length  Slot  Name   Signature
   0      10      0    this       Lscala/collection/immutable/IntMap$;
   0      10      1    key       I
   0      10      2    value       Ljava/lang/Object;

  Signature: length = 0x2
   00 36 

public scala.collection.immutable.IntMap empty();
  Code:
   Stack=1, Locals=1, Args_size=1
   0:	getstatic	#59; //Field scala/collection/immutable/IntMap$Nil$.MODULE$:Lscala/collection/immutable/IntMap$Nil$;
   3:	areturn
  LineNumberTable: 
   line 57: 0

  Signature: length = 0x2
   00 3C 

}

