Compiled from "IntMap.scala"
public final class scala.collection.immutable.IntMapUtils$ extends java.lang.Object implements scala.ScalaObject
  SourceFile: "IntMap.scala"
  Scala: length = 0x
   
  InnerClass: 
   public #99= #46 of #98; //Bin=class scala/collection/immutable/IntMap$Bin of class scala/collection/immutable/IntMap
  minor version: 0
  major version: 49
  Constant pool:
const #1 = Asciz	SourceFile;
const #2 = Asciz	IntMap.scala;
const #3 = Asciz	Scala;
const #4 = Asciz	MODULE$;
const #5 = Asciz	Lscala/collection/immutable/IntMapUtils$;;
const #6 = Asciz	<clinit>;
const #7 = Asciz	()V;
const #8 = Asciz	Code;
const #9 = Asciz	scala/collection/immutable/IntMapUtils$;
const #10 = class	#9;	//  scala/collection/immutable/IntMapUtils$
const #11 = Asciz	<init>;
const #12 = NameAndType	#11:#7;//  "<init>":()V
const #13 = Method	#10.#12;	//  scala/collection/immutable/IntMapUtils$."<init>":()V
const #14 = Asciz	LineNumberTable;
const #15 = Asciz	java/lang/Object;
const #16 = class	#15;	//  java/lang/Object
const #17 = Method	#16.#12;	//  java/lang/Object."<init>":()V
const #18 = NameAndType	#4:#5;//  MODULE$:Lscala/collection/immutable/IntMapUtils$;
const #19 = Field	#10.#18;	//  scala/collection/immutable/IntMapUtils$.MODULE$:Lscala/collection/immutable/IntMapUtils$;
const #20 = Asciz	bin;
const #21 = Asciz	(IILscala/collection/immutable/IntMap;Lscala/collection/immutable/IntMap;)Lscala/collection/immutable/IntMap;;
const #22 = Asciz	scala/collection/immutable/IntMap$Nil$;
const #23 = class	#22;	//  scala/collection/immutable/IntMap$Nil$
const #24 = Asciz	Lscala/collection/immutable/IntMap$Nil$;;
const #25 = NameAndType	#4:#24;//  MODULE$:Lscala/collection/immutable/IntMap$Nil$;
const #26 = Field	#23.#25;	//  scala/collection/immutable/IntMap$Nil$.MODULE$:Lscala/collection/immutable/IntMap$Nil$;
const #27 = Asciz	equals;
const #28 = Asciz	(Ljava/lang/Object;)Z;
const #29 = NameAndType	#27:#28;//  equals:(Ljava/lang/Object;)Z
const #30 = Method	#16.#29;	//  java/lang/Object.equals:(Ljava/lang/Object;)Z
const #31 = Asciz	scala/MatchError;
const #32 = class	#31;	//  scala/MatchError
const #33 = Asciz	scala/Tuple2;
const #34 = class	#33;	//  scala/Tuple2
const #35 = Asciz	(Ljava/lang/Object;Ljava/lang/Object;)V;
const #36 = NameAndType	#11:#35;//  "<init>":(Ljava/lang/Object;Ljava/lang/Object;)V
const #37 = Method	#34.#36;	//  scala/Tuple2."<init>":(Ljava/lang/Object;Ljava/lang/Object;)V
const #38 = Asciz	toString;
const #39 = Asciz	()Ljava/lang/String;;
const #40 = NameAndType	#38:#39;//  toString:()Ljava/lang/String;
const #41 = Method	#34.#40;	//  scala/Tuple2.toString:()Ljava/lang/String;
const #42 = Asciz	(Ljava/lang/String;)V;
const #43 = NameAndType	#11:#42;//  "<init>":(Ljava/lang/String;)V
const #44 = Method	#32.#43;	//  scala/MatchError."<init>":(Ljava/lang/String;)V
const #45 = Asciz	scala/collection/immutable/IntMap$Bin;
const #46 = class	#45;	//  scala/collection/immutable/IntMap$Bin
const #47 = Asciz	(IILscala/collection/immutable/IntMap;Lscala/collection/immutable/IntMap;)V;
const #48 = NameAndType	#11:#47;//  "<init>":(IILscala/collection/immutable/IntMap;Lscala/collection/immutable/IntMap;)V
const #49 = Method	#46.#48;	//  scala/collection/immutable/IntMap$Bin."<init>":(IILscala/collection/immutable/IntMap;Lscala/collection/immutable/IntMap;)V
const #50 = Asciz	this;
const #51 = Asciz	prefix;
const #52 = Asciz	I;
const #53 = Asciz	mask;
const #54 = Asciz	left;
const #55 = Asciz	Lscala/collection/immutable/IntMap;;
const #56 = Asciz	right;
const #57 = Asciz	LocalVariableTable;
const #58 = Asciz	<T:Ljava/lang/Object;>(IILscala/collection/immutable/IntMap<TT;>;Lscala/collection/immutable/IntMap<TT;>;)Lscala/collection/immutable/IntMap<TT;>;;
const #59 = Asciz	Signature;
const #60 = Asciz	join;
const #61 = Asciz	(ILscala/collection/immutable/IntMap;ILscala/collection/immutable/IntMap;)Lscala/collection/immutable/IntMap;;
const #62 = int	8;
const #63 = int	16;
const #64 = Asciz	zero;
const #65 = Asciz	(II)Z;
const #66 = NameAndType	#64:#65;//  zero:(II)Z
const #67 = Method	#10.#66;	//  scala/collection/immutable/IntMapUtils$.zero:(II)Z
const #68 = Asciz	p1;
const #69 = Asciz	t1;
const #70 = Asciz	p2;
const #71 = Asciz	t2;
const #72 = Asciz	i1;
const #73 = Asciz	p;
const #74 = Asciz	m;
const #75 = Asciz	<T:Ljava/lang/Object;>(ILscala/collection/immutable/IntMap<TT;>;ILscala/collection/immutable/IntMap<TT;>;)Lscala/collection/immutable/IntMap<TT;>;;
const #76 = Asciz	branchMask;
const #77 = Asciz	(II)I;
const #78 = Asciz	highestOneBit;
const #79 = Asciz	(I)I;
const #80 = NameAndType	#78:#79;//  highestOneBit:(I)I
const #81 = Method	#10.#80;	//  scala/collection/immutable/IntMapUtils$.highestOneBit:(I)I
const #82 = Asciz	i;
const #83 = Asciz	j;
const #84 = Asciz	complement;
const #85 = Asciz	shorter;
const #86 = Asciz	unsignedCompare;
const #87 = NameAndType	#86:#65;//  unsignedCompare:(II)Z
const #88 = Method	#10.#87;	//  scala/collection/immutable/IntMapUtils$.unsignedCompare:(II)Z
const #89 = Asciz	m1;
const #90 = Asciz	m2;
const #91 = Asciz	hasMatch;
const #92 = Asciz	(III)Z;
const #93 = Asciz	key;
const #94 = NameAndType	#84:#79;//  complement:(I)I
const #95 = Method	#10.#94;	//  scala/collection/immutable/IntMapUtils$.complement:(I)I
const #96 = Asciz	InnerClasses;
const #97 = Asciz	scala/collection/immutable/IntMap;
const #98 = class	#97;	//  scala/collection/immutable/IntMap
const #99 = Asciz	Bin;
const #100 = Asciz	scala/ScalaObject;
const #101 = class	#100;	//  scala/ScalaObject

{
public static final scala.collection.immutable.IntMapUtils$ MODULE$;

public static {};
  Code:
   Stack=1, Locals=0, Args_size=0
   0:	new	#10; //class scala/collection/immutable/IntMapUtils$
   3:	invokespecial	#13; //Method "<init>":()V
   6:	return

public scala.collection.immutable.IntMap bin(int, int, scala.collection.immutable.IntMap, scala.collection.immutable.IntMap);
  Code:
   Stack=6, Locals=5, Args_size=5
   0:	getstatic	#26; //Field scala/collection/immutable/IntMap$Nil$.MODULE$:Lscala/collection/immutable/IntMap$Nil$;
   3:	dup
   4:	ifnonnull	16
   7:	pop
   8:	aload	4
   10:	ifnull	24
   13:	goto	53
   16:	aload	4
   18:	invokevirtual	#30; //Method java/lang/Object.equals:(Ljava/lang/Object;)Z
   21:	ifeq	53
   24:	iconst_1
   25:	ifeq	32
   28:	aload_3
   29:	goto	121
   32:	new	#32; //class scala/MatchError
   35:	dup
   36:	new	#34; //class scala/Tuple2
   39:	dup
   40:	aload_3
   41:	aload	4
   43:	invokespecial	#37; //Method scala/Tuple2."<init>":(Ljava/lang/Object;Ljava/lang/Object;)V
   46:	invokevirtual	#41; //Method scala/Tuple2.toString:()Ljava/lang/String;
   49:	invokespecial	#44; //Method scala/MatchError."<init>":(Ljava/lang/String;)V
   52:	athrow
   53:	getstatic	#26; //Field scala/collection/immutable/IntMap$Nil$.MODULE$:Lscala/collection/immutable/IntMap$Nil$;
   56:	dup
   57:	ifnonnull	68
   60:	pop
   61:	aload_3
   62:	ifnull	75
   65:	goto	105
   68:	aload_3
   69:	invokevirtual	#30; //Method java/lang/Object.equals:(Ljava/lang/Object;)Z
   72:	ifeq	105
   75:	iconst_1
   76:	ifeq	84
   79:	aload	4
   81:	goto	121
   84:	new	#32; //class scala/MatchError
   87:	dup
   88:	new	#34; //class scala/Tuple2
   91:	dup
   92:	aload_3
   93:	aload	4
   95:	invokespecial	#37; //Method scala/Tuple2."<init>":(Ljava/lang/Object;Ljava/lang/Object;)V
   98:	invokevirtual	#41; //Method scala/Tuple2.toString:()Ljava/lang/String;
   101:	invokespecial	#44; //Method scala/MatchError."<init>":(Ljava/lang/String;)V
   104:	athrow
   105:	iconst_1
   106:	ifeq	122
   109:	new	#46; //class scala/collection/immutable/IntMap$Bin
   112:	dup
   113:	iload_1
   114:	iload_2
   115:	aload_3
   116:	aload	4
   118:	invokespecial	#49; //Method scala/collection/immutable/IntMap$Bin."<init>":(IILscala/collection/immutable/IntMap;Lscala/collection/immutable/IntMap;)V
   121:	areturn
   122:	new	#32; //class scala/MatchError
   125:	dup
   126:	new	#34; //class scala/Tuple2
   129:	dup
   130:	aload_3
   131:	aload	4
   133:	invokespecial	#37; //Method scala/Tuple2."<init>":(Ljava/lang/Object;Ljava/lang/Object;)V
   136:	invokevirtual	#41; //Method scala/Tuple2.toString:()Ljava/lang/String;
   139:	invokespecial	#44; //Method scala/MatchError."<init>":(Ljava/lang/String;)V
   142:	athrow
  LineNumberTable: 
   line 44: 0
   line 21: 24
   line 45: 28
   line 44: 32
   line 21: 75
   line 46: 79
   line 44: 84
   line 21: 105
   line 47: 109
   line 44: 121

  LocalVariableTable: 
   Start  Length  Slot  Name   Signature
   0      143      0    this       Lscala/collection/immutable/IntMapUtils$;
   0      143      1    prefix       I
   0      143      2    mask       I
   0      143      3    left       Lscala/collection/immutable/IntMap;
   0      143      4    right       Lscala/collection/immutable/IntMap;

  Signature: length = 0x2
   00 3A 

public scala.collection.immutable.IntMap join(int, scala.collection.immutable.IntMap, int, scala.collection.immutable.IntMap);
  Code:
   Stack=6, Locals=10, Args_size=5
   0:	iload_1
   1:	iload_3
   2:	ixor
   3:	istore	5
   5:	iload	5
   7:	iload	5
   9:	iconst_1
   10:	ishr
   11:	ior
   12:	istore	6
   14:	iload	6
   16:	iload	6
   18:	iconst_2
   19:	ishr
   20:	ior
   21:	istore	6
   23:	iload	6
   25:	iload	6
   27:	iconst_4
   28:	ishr
   29:	ior
   30:	istore	6
   32:	iload	6
   34:	iload	6
   36:	ldc	#62; //int 8
   38:	ishr
   39:	ior
   40:	istore	6
   42:	iload	6
   44:	iload	6
   46:	ldc	#63; //int 16
   48:	ishr
   49:	ior
   50:	istore	6
   52:	iload	6
   54:	iload	6
   56:	iconst_1
   57:	iushr
   58:	isub
   59:	istore	9
   61:	iload_1
   62:	iload	9
   64:	iconst_1
   65:	isub
   66:	istore	7
   68:	iconst_m1
   69:	iload	7
   71:	ixor
   72:	iload	9
   74:	ixor
   75:	iand
   76:	istore	8
   78:	aload_0
   79:	iload_1
   80:	iload	9
   82:	invokevirtual	#67; //Method zero:(II)Z
   85:	ifeq	105
   88:	new	#46; //class scala/collection/immutable/IntMap$Bin
   91:	dup
   92:	iload	8
   94:	iload	9
   96:	aload_2
   97:	aload	4
   99:	invokespecial	#49; //Method scala/collection/immutable/IntMap$Bin."<init>":(IILscala/collection/immutable/IntMap;Lscala/collection/immutable/IntMap;)V
   102:	goto	119
   105:	new	#46; //class scala/collection/immutable/IntMap$Bin
   108:	dup
   109:	iload	8
   111:	iload	9
   113:	aload	4
   115:	aload_2
   116:	invokespecial	#49; //Method scala/collection/immutable/IntMap$Bin."<init>":(IILscala/collection/immutable/IntMap;Lscala/collection/immutable/IntMap;)V
   119:	areturn
  LineNumberTable: 
   line 38: 0
   line 39: 61
   line 40: 78
   line 41: 105
   line 37: 119

  LocalVariableTable: 
   Start  Length  Slot  Name   Signature
   0      120      0    this       Lscala/collection/immutable/IntMapUtils$;
   0      120      1    p1       I
   0      120      2    t1       Lscala/collection/immutable/IntMap;
   0      120      3    p2       I
   0      120      4    t2       Lscala/collection/immutable/IntMap;
   5      54      6    i1       I
   78      42      8    p       I
   61      59      9    m       I

  Signature: length = 0x2
   00 4B 

public int branchMask(int, int);
  Code:
   Stack=3, Locals=3, Args_size=3
   0:	aload_0
   1:	iload_1
   2:	iload_2
   3:	ixor
   4:	invokevirtual	#81; //Method highestOneBit:(I)I
   7:	ireturn
  LineNumberTable: 
   line 35: 0

  LocalVariableTable: 
   Start  Length  Slot  Name   Signature
   0      8      0    this       Lscala/collection/immutable/IntMapUtils$;
   0      8      1    i       I
   0      8      2    j       I


public int highestOneBit(int);
  Code:
   Stack=3, Locals=3, Args_size=2
   0:	iload_1
   1:	iload_1
   2:	iconst_1
   3:	ishr
   4:	ior
   5:	istore_2
   6:	iload_2
   7:	iload_2
   8:	iconst_2
   9:	ishr
   10:	ior
   11:	istore_2
   12:	iload_2
   13:	iload_2
   14:	iconst_4
   15:	ishr
   16:	ior
   17:	istore_2
   18:	iload_2
   19:	iload_2
   20:	ldc	#62; //int 8
   22:	ishr
   23:	ior
   24:	istore_2
   25:	iload_2
   26:	iload_2
   27:	ldc	#63; //int 16
   29:	ishr
   30:	ior
   31:	istore_2
   32:	iload_2
   33:	iload_2
   34:	iconst_1
   35:	iushr
   36:	isub
   37:	ireturn
  LineNumberTable: 
   line 27: 0
   line 28: 6
   line 29: 12
   line 30: 18
   line 31: 25
   line 32: 32

  LocalVariableTable: 
   Start  Length  Slot  Name   Signature
   0      38      0    this       Lscala/collection/immutable/IntMapUtils$;
   0      38      1    j       I
   0      37      2    i       I


public int complement(int);
  Code:
   Stack=2, Locals=2, Args_size=2
   0:	iconst_m1
   1:	iload_1
   2:	ixor
   3:	ireturn
  LineNumberTable: 
   line 24: 0

  LocalVariableTable: 
   Start  Length  Slot  Name   Signature
   0      4      0    this       Lscala/collection/immutable/IntMapUtils$;
   0      4      1    i       I


public boolean shorter(int, int);
  Code:
   Stack=3, Locals=3, Args_size=3
   0:	aload_0
   1:	iload_2
   2:	iload_1
   3:	invokevirtual	#88; //Method unsignedCompare:(II)Z
   6:	ireturn
  LineNumberTable: 
   line 23: 0

  LocalVariableTable: 
   Start  Length  Slot  Name   Signature
   0      7      0    this       Lscala/collection/immutable/IntMapUtils$;
   0      7      1    m1       I
   0      7      2    m2       I


public boolean unsignedCompare(int, int);
  Code:
   Stack=3, Locals=3, Args_size=3
   0:	iload_1
   1:	iload_2
   2:	if_icmpge	9
   5:	iconst_1
   6:	goto	10
   9:	iconst_0
   10:	iload_1
   11:	iconst_0
   12:	if_icmpge	19
   15:	iconst_1
   16:	goto	20
   19:	iconst_0
   20:	ixor
   21:	iload_2
   22:	iconst_0
   23:	if_icmpge	30
   26:	iconst_1
   27:	goto	31
   30:	iconst_0
   31:	ixor
   32:	ireturn
  LineNumberTable: 
   line 22: 0

  LocalVariableTable: 
   Start  Length  Slot  Name   Signature
   0      33      0    this       Lscala/collection/immutable/IntMapUtils$;
   0      33      1    i       I
   0      33      2    j       I


public boolean hasMatch(int, int, int);
  Code:
   Stack=3, Locals=5, Args_size=4
   0:	iload_1
   1:	iload_3
   2:	iconst_1
   3:	isub
   4:	istore	4
   6:	iconst_m1
   7:	iload	4
   9:	ixor
   10:	iload_3
   11:	ixor
   12:	iand
   13:	iload_2
   14:	if_icmpne	21
   17:	iconst_1
   18:	goto	22
   21:	iconst_0
   22:	ireturn
  LineNumberTable: 
   line 21: 0

  LocalVariableTable: 
   Start  Length  Slot  Name   Signature
   0      23      0    this       Lscala/collection/immutable/IntMapUtils$;
   0      23      1    key       I
   0      23      2    prefix       I
   0      23      3    m       I


public int mask(int, int);
  Code:
   Stack=4, Locals=3, Args_size=3
   0:	iload_1
   1:	aload_0
   2:	iload_2
   3:	iconst_1
   4:	isub
   5:	invokevirtual	#95; //Method complement:(I)I
   8:	iload_2
   9:	ixor
   10:	iand
   11:	ireturn
  LineNumberTable: 
   line 20: 0

  LocalVariableTable: 
   Start  Length  Slot  Name   Signature
   0      12      0    this       Lscala/collection/immutable/IntMapUtils$;
   0      12      1    i       I
   0      12      2    mask       I


public boolean zero(int, int);
  Code:
   Stack=2, Locals=3, Args_size=3
   0:	iload_1
   1:	iload_2
   2:	iand
   3:	iconst_0
   4:	if_icmpne	11
   7:	iconst_1
   8:	goto	12
   11:	iconst_0
   12:	ireturn
  LineNumberTable: 
   line 19: 0

  LocalVariableTable: 
   Start  Length  Slot  Name   Signature
   0      13      0    this       Lscala/collection/immutable/IntMapUtils$;
   0      13      1    i       I
   0      13      2    mask       I


}

