Compiled from "IntMap.scala"
public final class scala.collection.immutable.IntMapUtils$ extends java.lang.Object implements scala.ScalaObject
  SourceFile: "IntMap.scala"
  Scala: length = 0x
   
  InnerClass: 
   public Bin=class scala/collection/immutable/IntMap$Bin of class scala/collection/immutable/IntMap
  minor version: 0
  major version: 49
  Constant pool:
Asciz	SourceFile;
Asciz	IntMap.scala;
Asciz	Scala;
Asciz	MODULE$;
Asciz	Lscala/collection/immutable/IntMapUtils$;;
Asciz	<clinit>;
Asciz	()V;
Asciz	Code;
Asciz	scala/collection/immutable/IntMapUtils$;
class	scala/collection/immutable/IntMapUtils$
Asciz	<init>;
NameAndType	"<init>":()V
Method	scala/collection/immutable/IntMapUtils$."<init>":()V
Asciz	LineNumberTable;
Asciz	java/lang/Object;
class	java/lang/Object
Method	java/lang/Object."<init>":()V
NameAndType	MODULE$:Lscala/collection/immutable/IntMapUtils$;
Field	scala/collection/immutable/IntMapUtils$.MODULE$:Lscala/collection/immutable/IntMapUtils$;
Asciz	bin;
Asciz	(IILscala/collection/immutable/IntMap;Lscala/collection/immutable/IntMap;)Lscala/collection/immutable/IntMap;;
Asciz	scala/collection/immutable/IntMap$Nil$;
class	scala/collection/immutable/IntMap$Nil$
Asciz	Lscala/collection/immutable/IntMap$Nil$;;
NameAndType	MODULE$:Lscala/collection/immutable/IntMap$Nil$;
Field	scala/collection/immutable/IntMap$Nil$.MODULE$:Lscala/collection/immutable/IntMap$Nil$;
Asciz	equals;
Asciz	(Ljava/lang/Object;)Z;
NameAndType	equals:(Ljava/lang/Object;)Z
Method	java/lang/Object.equals:(Ljava/lang/Object;)Z
Asciz	scala/MatchError;
class	scala/MatchError
Asciz	scala/Tuple2;
class	scala/Tuple2
Asciz	(Ljava/lang/Object;Ljava/lang/Object;)V;
NameAndType	"<init>":(Ljava/lang/Object;Ljava/lang/Object;)V
Method	scala/Tuple2."<init>":(Ljava/lang/Object;Ljava/lang/Object;)V
Asciz	toString;
Asciz	()Ljava/lang/String;;
NameAndType	toString:()Ljava/lang/String;
Method	scala/Tuple2.toString:()Ljava/lang/String;
Asciz	(Ljava/lang/String;)V;
NameAndType	"<init>":(Ljava/lang/String;)V
Method	scala/MatchError."<init>":(Ljava/lang/String;)V
Asciz	scala/collection/immutable/IntMap$Bin;
class	scala/collection/immutable/IntMap$Bin
Asciz	(IILscala/collection/immutable/IntMap;Lscala/collection/immutable/IntMap;)V;
NameAndType	"<init>":(IILscala/collection/immutable/IntMap;Lscala/collection/immutable/IntMap;)V
Method	scala/collection/immutable/IntMap$Bin."<init>":(IILscala/collection/immutable/IntMap;Lscala/collection/immutable/IntMap;)V
Asciz	this;
Asciz	prefix;
Asciz	I;
Asciz	mask;
Asciz	left;
Asciz	Lscala/collection/immutable/IntMap;;
Asciz	right;
Asciz	LocalVariableTable;
Asciz	<T:Ljava/lang/Object;>(IILscala/collection/immutable/IntMap<TT;>;Lscala/collection/immutable/IntMap<TT;>;)Lscala/collection/immutable/IntMap<TT;>;;
Asciz	Signature;
Asciz	join;
Asciz	(ILscala/collection/immutable/IntMap;ILscala/collection/immutable/IntMap;)Lscala/collection/immutable/IntMap;;
int	8;
int	16;
Asciz	zero;
Asciz	(II)Z;
NameAndType	zero:(II)Z
Method	scala/collection/immutable/IntMapUtils$.zero:(II)Z
Asciz	p1;
Asciz	t1;
Asciz	p2;
Asciz	t2;
Asciz	i1;
Asciz	p;
Asciz	m;
Asciz	<T:Ljava/lang/Object;>(ILscala/collection/immutable/IntMap<TT;>;ILscala/collection/immutable/IntMap<TT;>;)Lscala/collection/immutable/IntMap<TT;>;;
Asciz	branchMask;
Asciz	(II)I;
Asciz	highestOneBit;
Asciz	(I)I;
NameAndType	highestOneBit:(I)I
Method	scala/collection/immutable/IntMapUtils$.highestOneBit:(I)I
Asciz	i;
Asciz	j;
Asciz	complement;
Asciz	shorter;
Asciz	unsignedCompare;
NameAndType	unsignedCompare:(II)Z
Method	scala/collection/immutable/IntMapUtils$.unsignedCompare:(II)Z
Asciz	m1;
Asciz	m2;
Asciz	hasMatch;
Asciz	(III)Z;
Asciz	key;
NameAndType	complement:(I)I
Method	scala/collection/immutable/IntMapUtils$.complement:(I)I
Asciz	InnerClasses;
Asciz	scala/collection/immutable/IntMap;
class	scala/collection/immutable/IntMap
Asciz	Bin;
Asciz	scala/ScalaObject;
class	scala/ScalaObject

{
public static final scala.collection.immutable.IntMapUtils$ MODULE$;
  Signature: Lscala/collection/immutable/IntMapUtils$;

public static {};
  Signature: ()V
  Code:
   Stack=1, Locals=0, Args_size=0
	new	class scala/collection/immutable/IntMapUtils$
	invokespecial	Method "<init>":()V
	return
  Labels:

private scala.collection.immutable.IntMapUtils$();
  Signature: ()V
  Code:
   Stack=1, Locals=1, Args_size=1
	aload_0
	invokespecial	Method java/lang/Object."<init>":()V
	aload_0
	putstatic	Field MODULE$:Lscala/collection/immutable/IntMapUtils$;
	return
  Labels:

public scala.collection.immutable.IntMap bin(int, int, scala.collection.immutable.IntMap, scala.collection.immutable.IntMap);
  Signature: (IILscala/collection/immutable/IntMap;Lscala/collection/immutable/IntMap;)Lscala/collection/immutable/IntMap;
  Code:
   Stack=6, Locals=5, Args_size=5
	getstatic	Field scala/collection/immutable/IntMap$Nil$.MODULE$:Lscala/collection/immutable/IntMap$Nil$;
	dup
	ifnonnull	l1 // aload
	pop
	aload	4
	ifnull	l2 // iconst_1
	goto	l3 // getstatic
l1	aload	4
	invokevirtual	Method java/lang/Object.equals:(Ljava/lang/Object;)Z
	ifeq	l3 // getstatic
l2	iconst_1
	ifeq	l4 // new
	aload_3
	goto	l5 // areturn
l4	new	class scala/MatchError
	dup
	new	class scala/Tuple2
	dup
	aload_3
	aload	4
	invokespecial	Method scala/Tuple2."<init>":(Ljava/lang/Object;Ljava/lang/Object;)V
	invokevirtual	Method scala/Tuple2.toString:()Ljava/lang/String;
	invokespecial	Method scala/MatchError."<init>":(Ljava/lang/String;)V
	athrow
l3	getstatic	Field scala/collection/immutable/IntMap$Nil$.MODULE$:Lscala/collection/immutable/IntMap$Nil$;
	dup
	ifnonnull	l6 // aload_3
	pop
	aload_3
	ifnull	l7 // iconst_1
	goto	l8 // iconst_1
l6	aload_3
	invokevirtual	Method java/lang/Object.equals:(Ljava/lang/Object;)Z
	ifeq	l8 // iconst_1
l7	iconst_1
	ifeq	l9 // new
	aload	4
	goto	l5 // areturn
l9	new	class scala/MatchError
	dup
	new	class scala/Tuple2
	dup
	aload_3
	aload	4
	invokespecial	Method scala/Tuple2."<init>":(Ljava/lang/Object;Ljava/lang/Object;)V
	invokevirtual	Method scala/Tuple2.toString:()Ljava/lang/String;
	invokespecial	Method scala/MatchError."<init>":(Ljava/lang/String;)V
	athrow
l8	iconst_1
	ifeq	l10 // new
	new	class scala/collection/immutable/IntMap$Bin
	dup
	iload_1
	iload_2
	aload_3
	aload	4
	invokespecial	Method scala/collection/immutable/IntMap$Bin."<init>":(IILscala/collection/immutable/IntMap;Lscala/collection/immutable/IntMap;)V
l5	areturn
l10	new	class scala/MatchError
	dup
	new	class scala/Tuple2
	dup
	aload_3
	aload	4
	invokespecial	Method scala/Tuple2."<init>":(Ljava/lang/Object;Ljava/lang/Object;)V
	invokevirtual	Method scala/Tuple2.toString:()Ljava/lang/String;
	invokespecial	Method scala/MatchError."<init>":(Ljava/lang/String;)V
	athrow
  Labels:
   	l1 = 16 // aload
   	l2 = 24 // iconst_1
   	l4 = 32 // new
   	l3 = 53 // getstatic
   	l6 = 68 // aload_3
   	l7 = 75 // iconst_1
   	l9 = 84 // new
   	l8 = 105 // iconst_1
   	l5 = 121 // areturn
   	l10 = 122 // new
  LocalVariableTable: 
   Start  Length  Slot  Name   Signature
   0      143      0    this       Lscala/collection/immutable/IntMapUtils$;
   0      143      1    prefix       I
   0      143      2    mask       I
   0      143      3    left       Lscala/collection/immutable/IntMap;
   0      143      4    right       Lscala/collection/immutable/IntMap;

  Signature: length = 0x2
   00 3A 

public scala.collection.immutable.IntMap join(int, scala.collection.immutable.IntMap, int, scala.collection.immutable.IntMap);
  Signature: (ILscala/collection/immutable/IntMap;ILscala/collection/immutable/IntMap;)Lscala/collection/immutable/IntMap;
  Code:
   Stack=6, Locals=10, Args_size=5
	iload_1
	iload_3
	ixor
	istore	5
	iload	5
	iload	5
	iconst_1
	ishr
	ior
	istore	6
	iload	6
	iload	6
	iconst_2
	ishr
	ior
	istore	6
	iload	6
	iload	6
	iconst_4
	ishr
	ior
	istore	6
	iload	6
	iload	6
	ldc	int 8
	ishr
	ior
	istore	6
	iload	6
	iload	6
	ldc	int 16
	ishr
	ior
	istore	6
	iload	6
	iload	6
	iconst_1
	iushr
	isub
	istore	9
	iload_1
	iload	9
	iconst_1
	isub
	istore	7
	iconst_m1
	iload	7
	ixor
	iload	9
	ixor
	iand
	istore	8
	aload_0
	iload_1
	iload	9
	invokevirtual	Method zero:(II)Z
	ifeq	l1 // new
	new	class scala/collection/immutable/IntMap$Bin
	dup
	iload	8
	iload	9
	aload_2
	aload	4
	invokespecial	Method scala/collection/immutable/IntMap$Bin."<init>":(IILscala/collection/immutable/IntMap;Lscala/collection/immutable/IntMap;)V
	goto	l2 // areturn
l1	new	class scala/collection/immutable/IntMap$Bin
	dup
	iload	8
	iload	9
	aload	4
	aload_2
	invokespecial	Method scala/collection/immutable/IntMap$Bin."<init>":(IILscala/collection/immutable/IntMap;Lscala/collection/immutable/IntMap;)V
l2	areturn
  Labels:
   	l1 = 105 // new
   	l2 = 119 // areturn
  LocalVariableTable: 
   Start  Length  Slot  Name   Signature
   0      120      0    this       Lscala/collection/immutable/IntMapUtils$;
   0      120      1    p1       I
   0      120      2    t1       Lscala/collection/immutable/IntMap;
   0      120      3    p2       I
   0      120      4    t2       Lscala/collection/immutable/IntMap;
   5      54      6    i1       I
   78      42      8    p       I
   61      59      9    m       I

  Signature: length = 0x2
   00 4B 

public int branchMask(int, int);
  Signature: (II)I
  Code:
   Stack=3, Locals=3, Args_size=3
	aload_0
	iload_1
	iload_2
	ixor
	invokevirtual	Method highestOneBit:(I)I
	ireturn
  Labels:
  LocalVariableTable: 
   Start  Length  Slot  Name   Signature
   0      8      0    this       Lscala/collection/immutable/IntMapUtils$;
   0      8      1    i       I
   0      8      2    j       I


public int highestOneBit(int);
  Signature: (I)I
  Code:
   Stack=3, Locals=3, Args_size=2
	iload_1
	iload_1
	iconst_1
	ishr
	ior
	istore_2
	iload_2
	iload_2
	iconst_2
	ishr
	ior
	istore_2
	iload_2
	iload_2
	iconst_4
	ishr
	ior
	istore_2
	iload_2
	iload_2
	ldc	int 8
	ishr
	ior
	istore_2
	iload_2
	iload_2
	ldc	int 16
	ishr
	ior
	istore_2
	iload_2
	iload_2
	iconst_1
	iushr
	isub
	ireturn
  Labels:
  LocalVariableTable: 
   Start  Length  Slot  Name   Signature
   0      38      0    this       Lscala/collection/immutable/IntMapUtils$;
   0      38      1    j       I
   0      37      2    i       I


public int complement(int);
  Signature: (I)I
  Code:
   Stack=2, Locals=2, Args_size=2
	iconst_m1
	iload_1
	ixor
	ireturn
  Labels:
  LocalVariableTable: 
   Start  Length  Slot  Name   Signature
   0      4      0    this       Lscala/collection/immutable/IntMapUtils$;
   0      4      1    i       I


public boolean shorter(int, int);
  Signature: (II)Z
  Code:
   Stack=3, Locals=3, Args_size=3
	aload_0
	iload_2
	iload_1
	invokevirtual	Method unsignedCompare:(II)Z
	ireturn
  Labels:
  LocalVariableTable: 
   Start  Length  Slot  Name   Signature
   0      7      0    this       Lscala/collection/immutable/IntMapUtils$;
   0      7      1    m1       I
   0      7      2    m2       I


public boolean unsignedCompare(int, int);
  Signature: (II)Z
  Code:
   Stack=3, Locals=3, Args_size=3
	iload_1
	iload_2
	if_icmpge	l1 // iconst_0
	iconst_1
	goto	l2 // iload_1
l1	iconst_0
l2	iload_1
	iconst_0
	if_icmpge	l3 // iconst_0
	iconst_1
	goto	l4 // ixor
l3	iconst_0
l4	ixor
	iload_2
	iconst_0
	if_icmpge	l5 // iconst_0
	iconst_1
	goto	l6 // ixor
l5	iconst_0
l6	ixor
	ireturn
  Labels:
   	l1 = 9 // iconst_0
   	l2 = 10 // iload_1
   	l3 = 19 // iconst_0
   	l4 = 20 // ixor
   	l5 = 30 // iconst_0
   	l6 = 31 // ixor
  LocalVariableTable: 
   Start  Length  Slot  Name   Signature
   0      33      0    this       Lscala/collection/immutable/IntMapUtils$;
   0      33      1    i       I
   0      33      2    j       I


public boolean hasMatch(int, int, int);
  Signature: (III)Z
  Code:
   Stack=3, Locals=5, Args_size=4
	iload_1
	iload_3
	iconst_1
	isub
	istore	4
	iconst_m1
	iload	4
	ixor
	iload_3
	ixor
	iand
	iload_2
	if_icmpne	l1 // iconst_0
	iconst_1
	goto	l2 // ireturn
l1	iconst_0
l2	ireturn
  Labels:
   	l1 = 21 // iconst_0
   	l2 = 22 // ireturn
  LocalVariableTable: 
   Start  Length  Slot  Name   Signature
   0      23      0    this       Lscala/collection/immutable/IntMapUtils$;
   0      23      1    key       I
   0      23      2    prefix       I
   0      23      3    m       I


public int mask(int, int);
  Signature: (II)I
  Code:
   Stack=4, Locals=3, Args_size=3
	iload_1
	aload_0
	iload_2
	iconst_1
	isub
	invokevirtual	Method complement:(I)I
	iload_2
	ixor
	iand
	ireturn
  Labels:
  LocalVariableTable: 
   Start  Length  Slot  Name   Signature
   0      12      0    this       Lscala/collection/immutable/IntMapUtils$;
   0      12      1    i       I
   0      12      2    mask       I


public boolean zero(int, int);
  Signature: (II)Z
  Code:
   Stack=2, Locals=3, Args_size=3
	iload_1
	iload_2
	iand
	iconst_0
	if_icmpne	l1 // iconst_0
	iconst_1
	goto	l2 // ireturn
l1	iconst_0
l2	ireturn
  Labels:
   	l1 = 11 // iconst_0
   	l2 = 12 // ireturn
  LocalVariableTable: 
   Start  Length  Slot  Name   Signature
   0      13      0    this       Lscala/collection/immutable/IntMapUtils$;
   0      13      1    i       I
   0      13      2    mask       I


}

