Compiled from "List.scala"
public final class scala.collection.immutable.ListSerializeEnd extends java.lang.Object
  SourceFile: "List.scala"
  ScalaSig: length = 0x3
   05 00 00 
  RuntimeVisibleAnnotations: length = 0xB
   00 01 00 27 00 01 00 28 73 00 29 
  minor version: 0
  major version: 49
  Constant pool:
Asciz	SourceFile;
Asciz	List.scala;
Asciz	productElements;
Asciz	()Lscala/collection/Iterator;;
Asciz	Code;
Asciz	scala/collection/immutable/ListSerializeEnd$;
class	scala/collection/immutable/ListSerializeEnd$
Asciz	MODULE$;
Asciz	Lscala/collection/immutable/ListSerializeEnd$;;
NameAndType	MODULE$:Lscala/collection/immutable/ListSerializeEnd$;
Field	scala/collection/immutable/ListSerializeEnd$.MODULE$:Lscala/collection/immutable/ListSerializeEnd$;
NameAndType	productElements:()Lscala/collection/Iterator;
Method	scala/collection/immutable/ListSerializeEnd$.productElements:()Lscala/collection/Iterator;
Asciz	Deprecated;
Asciz	productIterator;
NameAndType	productIterator:()Lscala/collection/Iterator;
Method	scala/collection/immutable/ListSerializeEnd$.productIterator:()Lscala/collection/Iterator;
Asciz	productElementName;
Asciz	(I)Ljava/lang/String;;
NameAndType	productElementName:(I)Ljava/lang/String;
Method	scala/collection/immutable/ListSerializeEnd$.productElementName:(I)Ljava/lang/String;
Asciz	canEqual;
Asciz	(Ljava/lang/Object;)Z;
NameAndType	canEqual:(Ljava/lang/Object;)Z
Method	scala/collection/immutable/ListSerializeEnd$.canEqual:(Ljava/lang/Object;)Z
Asciz	productElement;
Asciz	(I)Ljava/lang/Object;;
NameAndType	productElement:(I)Ljava/lang/Object;
Method	scala/collection/immutable/ListSerializeEnd$.productElement:(I)Ljava/lang/Object;
Asciz	productArity;
Asciz	()I;
NameAndType	productArity:()I
Method	scala/collection/immutable/ListSerializeEnd$.productArity:()I
Asciz	productPrefix;
Asciz	()Ljava/lang/String;;
NameAndType	productPrefix:()Ljava/lang/String;
Method	scala/collection/immutable/ListSerializeEnd$.productPrefix:()Ljava/lang/String;
Asciz	ScalaSig;
Asciz	Lscala/reflect/ScalaSignature;;
Asciz	bytes;
Asciz	-;a!\tA'jgRVM]5bY&TX-8e\tA!Aj[6,H/2mK*QABG>dG.Z2uS>t'\"AM\r\1%QQ\"-A!A\ta!'jgRVM]5bY&TX-8e'QQ\"F\r9R\"AA\t7b]TAEU4-\t1qJ6fGR\"AFI!M\r\1PE*,7\r\t-iI!aAxZ;di\")QDC?1A(8jizF\t!\t#\"A\n;p'RN\4\r\"A\nz!AB*ue&tw\r(\t\")5(o3vGR&/4jqV\t1+\t\",1(o3vGR%/;z+aC.\tqcAAJ]RD\r%\t%MaJ|G-^2u2,W.8u)\tTg%AG:Lb0\rLq\n\tII\rg.R9vC2$\"AOYYBun7fC:DqAN!@\t\"A-X-3SKN|GN^35A3A\"F!\t12)E\r\t2+:jC24VM]:j_:,\n\ts7l~*[\"!b\t-!K!!M,'/[1mSj'\r\3)U\t;
Asciz	RuntimeVisibleAnnotations;
Asciz	scala/collection/immutable/ListSerializeEnd;
class	scala/collection/immutable/ListSerializeEnd
Asciz	java/lang/Object;
class	java/lang/Object

{
public static final scala.collection.Iterator productElements();
  Signature: ()Lscala/collection/Iterator;
  Code:
   Stack=1, Locals=0, Args_size=0
	getstatic	Field scala/collection/immutable/ListSerializeEnd$.MODULE$:Lscala/collection/immutable/ListSerializeEnd$;
	invokevirtual	Method scala/collection/immutable/ListSerializeEnd$.productElements:()Lscala/collection/Iterator;
	areturn
  Labels:
  Deprecated: true

public static final scala.collection.Iterator productIterator();
  Signature: ()Lscala/collection/Iterator;
  Code:
   Stack=1, Locals=0, Args_size=0
	getstatic	Field scala/collection/immutable/ListSerializeEnd$.MODULE$:Lscala/collection/immutable/ListSerializeEnd$;
	invokevirtual	Method scala/collection/immutable/ListSerializeEnd$.productIterator:()Lscala/collection/Iterator;
	areturn
  Labels:

public static final java.lang.String productElementName(int);
  Signature: (I)Ljava/lang/String;
  Code:
   Stack=2, Locals=1, Args_size=1
	getstatic	Field scala/collection/immutable/ListSerializeEnd$.MODULE$:Lscala/collection/immutable/ListSerializeEnd$;
	iload_0
	invokevirtual	Method scala/collection/immutable/ListSerializeEnd$.productElementName:(I)Ljava/lang/String;
	areturn
  Labels:

public static final boolean canEqual(java.lang.Object);
  Signature: (Ljava/lang/Object;)Z
  Code:
   Stack=2, Locals=1, Args_size=1
	getstatic	Field scala/collection/immutable/ListSerializeEnd$.MODULE$:Lscala/collection/immutable/ListSerializeEnd$;
	aload_0
	invokevirtual	Method scala/collection/immutable/ListSerializeEnd$.canEqual:(Ljava/lang/Object;)Z
	ireturn
  Labels:

public static final java.lang.Object productElement(int);
  Signature: (I)Ljava/lang/Object;
  Code:
   Stack=2, Locals=1, Args_size=1
	getstatic	Field scala/collection/immutable/ListSerializeEnd$.MODULE$:Lscala/collection/immutable/ListSerializeEnd$;
	iload_0
	invokevirtual	Method scala/collection/immutable/ListSerializeEnd$.productElement:(I)Ljava/lang/Object;
	areturn
  Labels:

public static final int productArity();
  Signature: ()I
  Code:
   Stack=1, Locals=0, Args_size=0
	getstatic	Field scala/collection/immutable/ListSerializeEnd$.MODULE$:Lscala/collection/immutable/ListSerializeEnd$;
	invokevirtual	Method scala/collection/immutable/ListSerializeEnd$.productArity:()I
	ireturn
  Labels:

public static final java.lang.String productPrefix();
  Signature: ()Ljava/lang/String;
  Code:
   Stack=1, Locals=0, Args_size=0
	getstatic	Field scala/collection/immutable/ListSerializeEnd$.MODULE$:Lscala/collection/immutable/ListSerializeEnd$;
	invokevirtual	Method scala/collection/immutable/ListSerializeEnd$.productPrefix:()Ljava/lang/String;
	areturn
  Labels:

}

