Compiled from "List.scala"
public final class scala.collection.immutable.ListSerializeEnd extends java.lang.Object
  SourceFile: "List.scala"
  ScalaSig: length = 0x206
   05 00 4A 07 06 01 02 FFFFFF88 42 06 08 01 10 4C 69 73
   74 53 65 72 69 61 6C 69 7A 65 45 6E 64 0A 02 03
   04 01 09 69 6D 6D 75 74 61 62 6C 65 0A 02 05 06
   01 0A 63 6F 6C 6C 65 63 74 69 6F 6E 0A 01 07 01
   05 73 63 61 6C 61 10 02 09 0A 0D 01 02 06 09 0B
   02 FFFFFF84 FFFFFF80 FFFFFF80 FFFFFF88 42 06 0C 02 10 4C 69 73 74 53 65
   72 69 61 6C 69 7A 65 45 6E 64 13 04 0A 0D 15 19
   10 02 0E 13 0D 01 0F 0A 02 10 11 01 04 6C 61 6E
   67 0A 01 12 01 04 6A 61 76 61 09 02 14 0F 02 06
   4F 62 6A 65 63 74 10 02 16 17 0D 01 06 09 02 18
   06 02 0B 53 63 61 6C 61 4F 62 6A 65 63 74 10 02
   16 1A 09 02 1B 06 02 07 50 72 6F 64 75 63 74 08
   05 1D 0A FFFFFF84 00 1F 01 06 3C 69 6E 69 74 3E 03 00
   14 01 08 08 08 21 0A FFFFFF84 FFFFFF80 FFFFFF80 FFFFFF84 22 22 01 08 74
   6F 53 74 72 69 6E 67 14 01 23 10 02 0E 24 09 02
   25 0F 02 06 53 74 72 69 6E 67 08 08 27 0A FFFFFF84 FFFFFF80
   FFFFFF80 FFFFFF84 20 28 01 0D 70 72 6F 64 75 63 74 50 72 65
   66 69 78 15 01 23 08 08 2A 0A FFFFFF84 FFFFFF80 FFFFFF80 FFFFFF84 20 2B
   01 0C 70 72 6F 64 75 63 74 41 72 69 74 79 15 01
   2C 10 02 16 2D 09 02 2E 06 02 03 49 6E 74 08 08
   30 0A FFFFFF84 FFFFFF80 FFFFFF80 FFFFFF84 20 31 01 0E 70 72 6F 64 75 63
   74 45 6C 65 6D 65 6E 74 14 02 32 35 10 02 16 33
   09 02 34 06 02 03 41 6E 79 08 07 36 2F FFFFFF81 FFFFFF80 FFFFFFC0
   00 2C 01 03 78 24 31 08 08 38 0A FFFFFF84 FFFFFF80 FFFFFF80 FFFFFF84 20
   39 01 08 63 61 6E 45 71 75 61 6C 14 02 3A 3D 10
   02 16 3B 09 02 3C 06 02 07 42 6F 6F 6C 65 61 6E
   08 07 36 37 FFFFFF81 FFFFFF80 FFFFFFC0 00 32 08 08 3F 0A FFFFFF84 FFFFFF80 FFFFFF80
   FFFFFF84 08 40 01 0B 72 65 61 64 52 65 73 6F 6C 76 65
   14 01 0D 28 03 0A 42 45 10 02 16 43 09 02 44 06
   02 10 53 65 72 69 61 6C 56 65 72 73 69 6F 6E 55
   49 44 1E 08 FFFFFF8A 5C 63 5B FFFFFFF7 53 0B 6D 28 02 0A 47
   10 02 16 48 09 02 49 06 02 0C 73 65 72 69 61 6C
   69 7A 61 62 6C 65 
  minor version: 0
  major version: 49
  Constant pool:
const #1 = Asciz	SourceFile;
const #2 = Asciz	List.scala;
const #3 = Asciz	productElements;
const #4 = Asciz	()Lscala/collection/Iterator;;
const #5 = Asciz	Code;
const #6 = Asciz	scala/collection/immutable/ListSerializeEnd$;
const #7 = class	#6;	//  scala/collection/immutable/ListSerializeEnd$
const #8 = Asciz	MODULE$;
const #9 = Asciz	Lscala/collection/immutable/ListSerializeEnd$;;
const #10 = NameAndType	#8:#9;//  MODULE$:Lscala/collection/immutable/ListSerializeEnd$;
const #11 = Field	#7.#10;	//  scala/collection/immutable/ListSerializeEnd$.MODULE$:Lscala/collection/immutable/ListSerializeEnd$;
const #12 = NameAndType	#3:#4;//  productElements:()Lscala/collection/Iterator;
const #13 = Method	#7.#12;	//  scala/collection/immutable/ListSerializeEnd$.productElements:()Lscala/collection/Iterator;
const #14 = Asciz	Deprecated;
const #15 = Asciz	productIterator;
const #16 = NameAndType	#15:#4;//  productIterator:()Lscala/collection/Iterator;
const #17 = Method	#7.#16;	//  scala/collection/immutable/ListSerializeEnd$.productIterator:()Lscala/collection/Iterator;
const #18 = Asciz	canEqual;
const #19 = Asciz	(Ljava/lang/Object;)Z;
const #20 = NameAndType	#18:#19;//  canEqual:(Ljava/lang/Object;)Z
const #21 = Method	#7.#20;	//  scala/collection/immutable/ListSerializeEnd$.canEqual:(Ljava/lang/Object;)Z
const #22 = Asciz	productElement;
const #23 = Asciz	(I)Ljava/lang/Object;;
const #24 = NameAndType	#22:#23;//  productElement:(I)Ljava/lang/Object;
const #25 = Method	#7.#24;	//  scala/collection/immutable/ListSerializeEnd$.productElement:(I)Ljava/lang/Object;
const #26 = Asciz	productArity;
const #27 = Asciz	()I;
const #28 = NameAndType	#26:#27;//  productArity:()I
const #29 = Method	#7.#28;	//  scala/collection/immutable/ListSerializeEnd$.productArity:()I
const #30 = Asciz	productPrefix;
const #31 = Asciz	()Ljava/lang/String;;
const #32 = NameAndType	#30:#31;//  productPrefix:()Ljava/lang/String;
const #33 = Method	#7.#32;	//  scala/collection/immutable/ListSerializeEnd$.productPrefix:()Ljava/lang/String;
const #34 = Asciz	ScalaSig;
const #35 = Asciz	scala/collection/immutable/ListSerializeEnd;
const #36 = class	#35;	//  scala/collection/immutable/ListSerializeEnd
const #37 = Asciz	java/lang/Object;
const #38 = class	#37;	//  java/lang/Object

{
public static final scala.collection.Iterator productElements();
  Code:
   Stack=1, Locals=0, Args_size=0
   0:	getstatic	#11; //Field scala/collection/immutable/ListSerializeEnd$.MODULE$:Lscala/collection/immutable/ListSerializeEnd$;
   3:	invokevirtual	#13; //Method scala/collection/immutable/ListSerializeEnd$.productElements:()Lscala/collection/Iterator;
   6:	areturn
  Deprecated: true

public static final scala.collection.Iterator productIterator();
  Code:
   Stack=1, Locals=0, Args_size=0
   0:	getstatic	#11; //Field scala/collection/immutable/ListSerializeEnd$.MODULE$:Lscala/collection/immutable/ListSerializeEnd$;
   3:	invokevirtual	#17; //Method scala/collection/immutable/ListSerializeEnd$.productIterator:()Lscala/collection/Iterator;
   6:	areturn

public static final boolean canEqual(java.lang.Object);
  Code:
   Stack=2, Locals=1, Args_size=1
   0:	getstatic	#11; //Field scala/collection/immutable/ListSerializeEnd$.MODULE$:Lscala/collection/immutable/ListSerializeEnd$;
   3:	aload_0
   4:	invokevirtual	#21; //Method scala/collection/immutable/ListSerializeEnd$.canEqual:(Ljava/lang/Object;)Z
   7:	ireturn

public static final java.lang.Object productElement(int);
  Code:
   Stack=2, Locals=1, Args_size=1
   0:	getstatic	#11; //Field scala/collection/immutable/ListSerializeEnd$.MODULE$:Lscala/collection/immutable/ListSerializeEnd$;
   3:	iload_0
   4:	invokevirtual	#25; //Method scala/collection/immutable/ListSerializeEnd$.productElement:(I)Ljava/lang/Object;
   7:	areturn

public static final int productArity();
  Code:
   Stack=1, Locals=0, Args_size=0
   0:	getstatic	#11; //Field scala/collection/immutable/ListSerializeEnd$.MODULE$:Lscala/collection/immutable/ListSerializeEnd$;
   3:	invokevirtual	#29; //Method scala/collection/immutable/ListSerializeEnd$.productArity:()I
   6:	ireturn

public static final java.lang.String productPrefix();
  Code:
   Stack=1, Locals=0, Args_size=0
   0:	getstatic	#11; //Field scala/collection/immutable/ListSerializeEnd$.MODULE$:Lscala/collection/immutable/ListSerializeEnd$;
   3:	invokevirtual	#33; //Method scala/collection/immutable/ListSerializeEnd$.productPrefix:()Ljava/lang/String;
   6:	areturn

}

