Compiled from "List.scala"
public final class scala.collection.immutable.List$$anonfun$separate$1 extends java.lang.Object implements scala.Function2,scala.ScalaObject,java.io.Serializable
  SourceFile: "List.scala"
  Scala: length = 0x
   
  InnerClass: 
   public final $anonfun$separate$1=class scala/collection/immutable/List$$anonfun$separate$1 of class scala/collection/immutable/List
  minor version: 0
  major version: 49
  Constant pool:
Asciz	SourceFile;
Asciz	List.scala;
Asciz	<clinit>;
Asciz	()V;
Asciz	Code;
Asciz	serialVersionUID;
Asciz	J;
Asciz	scala/collection/immutable/List$$anonfun$separate$1;
class	scala/collection/immutable/List$$anonfun$separate$1
NameAndType	serialVersionUID:J
Field	scala/collection/immutable/List$$anonfun$separate$1.serialVersionUID:J
Asciz	<init>;
Asciz	LineNumberTable;
Asciz	java/lang/Object;
class	java/lang/Object
NameAndType	"<init>":()V
Method	java/lang/Object."<init>":()V
Asciz	scala/Function2$class;
class	scala/Function2$class
Asciz	$init$;
Asciz	(Lscala/Function2;)V;
NameAndType	$init$:(Lscala/Function2;)V
Method	scala/Function2$class.$init$:(Lscala/Function2;)V
Asciz	apply;
Asciz	(Ljava/lang/Object;Ljava/lang/Object;)Ljava/lang/Object;;
Asciz	scala/Either;
class	scala/Either
Asciz	scala/Tuple2;
class	scala/Tuple2
Asciz	(Lscala/Either;Lscala/Tuple2;)Lscala/Tuple2;;
NameAndType	apply:(Lscala/Either;Lscala/Tuple2;)Lscala/Tuple2;
Method	scala/collection/immutable/List$$anonfun$separate$1.apply:(Lscala/Either;Lscala/Tuple2;)Lscala/Tuple2;
Asciz	this;
Asciz	Lscala/collection/immutable/List$$anonfun$separate$1;;
Asciz	v1;
Asciz	Ljava/lang/Object;;
Asciz	v2;
Asciz	LocalVariableTable;
Asciz	scala/Left;
class	scala/Left
Asciz	a;
NameAndType	a:Ljava/lang/Object;
Field	scala/Left.a:Ljava/lang/Object;
Asciz	_1;
Asciz	()Ljava/lang/Object;;
NameAndType	_1:()Ljava/lang/Object;
Method	scala/Tuple2._1:()Ljava/lang/Object;
Asciz	scala/collection/immutable/List;
class	scala/collection/immutable/List
Asciz	_2;
NameAndType	_2:()Ljava/lang/Object;
Method	scala/Tuple2._2:()Ljava/lang/Object;
Asciz	$colon$colon;
Asciz	(Ljava/lang/Object;)Lscala/collection/immutable/List;;
NameAndType	$colon$colon:(Ljava/lang/Object;)Lscala/collection/immutable/List;
Method	scala/collection/immutable/List.$colon$colon:(Ljava/lang/Object;)Lscala/collection/immutable/List;
Asciz	(Ljava/lang/Object;Ljava/lang/Object;)V;
NameAndType	"<init>":(Ljava/lang/Object;Ljava/lang/Object;)V
Method	scala/Tuple2."<init>":(Ljava/lang/Object;Ljava/lang/Object;)V
Asciz	scala/MatchError;
class	scala/MatchError
Asciz	toString;
Asciz	()Ljava/lang/String;;
NameAndType	toString:()Ljava/lang/String;
Method	scala/Tuple2.toString:()Ljava/lang/String;
Asciz	(Ljava/lang/String;)V;
NameAndType	"<init>":(Ljava/lang/String;)V
Method	scala/MatchError."<init>":(Ljava/lang/String;)V
Asciz	scala/Right;
class	scala/Right
Asciz	b;
NameAndType	b:Ljava/lang/Object;
Field	scala/Right.b:Ljava/lang/Object;
Asciz	temp39;
Asciz	Lscala/Left;;
Asciz	temp41;
Asciz	Lscala/collection/immutable/List;;
Asciz	temp40;
Asciz	temp42;
Asciz	temp43;
Asciz	Lscala/Right;;
Asciz	temp45;
Asciz	temp46;
Asciz	temp44;
Asciz	(Lscala/Either<TA;TB;>;Lscala/Tuple2<Lscala/collection/immutable/List<TA;>;Lscala/collection/immutable/List<TB;>;>;)Lscala/Tuple2<Lscala/collection/immutable/List<TA;>;Lscala/collection/immutable/List<TB;>;>;;
Asciz	Signature;
Asciz	curry;
Asciz	()Lscala/Function1;;
Asciz	(Lscala/Function2;)Lscala/Function1;;
NameAndType	curry:(Lscala/Function2;)Lscala/Function1;
Method	scala/Function2$class.curry:(Lscala/Function2;)Lscala/Function1;
Asciz	(Lscala/Function2;)Ljava/lang/String;;
NameAndType	toString:(Lscala/Function2;)Ljava/lang/String;
Method	scala/Function2$class.toString:(Lscala/Function2;)Ljava/lang/String;
Asciz	Scala;
Asciz	InnerClasses;
Asciz	$anonfun$separate$1;
Asciz	scala/Function2;
class	scala/Function2
Asciz	scala/ScalaObject;
class	scala/ScalaObject
Asciz	java/io/Serializable;
class	java/io/Serializable

{
public static final long serialVersionUID;
  Signature: J

public static {};
  Signature: ()V
  Code:
   Stack=2, Locals=0, Args_size=0
	lconst_0
	putstatic	Field serialVersionUID:J
	return
  Labels:

public scala.collection.immutable.List$$anonfun$separate$1();
  Signature: ()V
  Code:
   Stack=1, Locals=1, Args_size=1
	aload_0
	invokespecial	Method java/lang/Object."<init>":()V
	aload_0
	invokestatic	Method scala/Function2$class.$init$:(Lscala/Function2;)V
	return
  Labels:

public final java.lang.Object apply(java.lang.Object, java.lang.Object);
  Signature: (Ljava/lang/Object;Ljava/lang/Object;)Ljava/lang/Object;
  Code:
   Stack=3, Locals=3, Args_size=3
	aload_0
	aload_1
	checkcast	class scala/Either
	aload_2
	checkcast	class scala/Tuple2
	invokevirtual	Method apply:(Lscala/Either;Lscala/Tuple2;)Lscala/Tuple2;
	areturn
  Labels:
  LocalVariableTable: 
   Start  Length  Slot  Name   Signature
   0      13      0    this       Lscala/collection/immutable/List$$anonfun$separate$1;
   0      13      1    v1       Ljava/lang/Object;
   0      13      2    v2       Ljava/lang/Object;


public final scala.Tuple2 apply(scala.Either, scala.Tuple2);
  Signature: (Lscala/Either;Lscala/Tuple2;)Lscala/Tuple2;
  Code:
   Stack=6, Locals=11, Args_size=3
	aload_1
	instanceof	class scala/Left
	ifeq	l1 // aload_1
	aload_1
	checkcast	class scala/Left
	astore_3
	aload_3
	getfield	Field scala/Left.a:Ljava/lang/Object;
	astore	5
	aload_2
	ifnull	l2 // new
	aload_2
	invokevirtual	Method scala/Tuple2._1:()Ljava/lang/Object;
	checkcast	class scala/collection/immutable/List
	astore	4
	aload_2
	invokevirtual	Method scala/Tuple2._2:()Ljava/lang/Object;
	checkcast	class scala/collection/immutable/List
	astore	6
	iconst_1
	ifeq	l3 // new
	new	class scala/Tuple2
	dup
	aload	4
	aload	5
	invokevirtual	Method scala/collection/immutable/List.$colon$colon:(Ljava/lang/Object;)Lscala/collection/immutable/List;
	aload	6
	invokespecial	Method scala/Tuple2."<init>":(Ljava/lang/Object;Ljava/lang/Object;)V
	goto	l4 // areturn
l3	new	class scala/MatchError
	dup
	new	class scala/Tuple2
	dup
	aload_1
	aload_2
	invokespecial	Method scala/Tuple2."<init>":(Ljava/lang/Object;Ljava/lang/Object;)V
	invokevirtual	Method scala/Tuple2.toString:()Ljava/lang/String;
	invokespecial	Method scala/MatchError."<init>":(Ljava/lang/String;)V
	athrow
l2	new	class scala/MatchError
	dup
	new	class scala/Tuple2
	dup
	aload_1
	aload_2
	invokespecial	Method scala/Tuple2."<init>":(Ljava/lang/Object;Ljava/lang/Object;)V
	invokevirtual	Method scala/Tuple2.toString:()Ljava/lang/String;
	invokespecial	Method scala/MatchError."<init>":(Ljava/lang/String;)V
	athrow
l1	aload_1
	instanceof	class scala/Right
	ifeq	l5 // new
	aload_1
	checkcast	class scala/Right
	astore	7
	aload	7
	getfield	Field scala/Right.b:Ljava/lang/Object;
	astore	10
	aload_2
	ifnull	l6 // new
	aload_2
	invokevirtual	Method scala/Tuple2._1:()Ljava/lang/Object;
	checkcast	class scala/collection/immutable/List
	astore	8
	aload_2
	invokevirtual	Method scala/Tuple2._2:()Ljava/lang/Object;
	checkcast	class scala/collection/immutable/List
	astore	9
	iconst_1
	ifeq	l7 // new
	new	class scala/Tuple2
	dup
	aload	8
	aload	9
	aload	10
	invokevirtual	Method scala/collection/immutable/List.$colon$colon:(Ljava/lang/Object;)Lscala/collection/immutable/List;
	invokespecial	Method scala/Tuple2."<init>":(Ljava/lang/Object;Ljava/lang/Object;)V
l4	areturn
l7	new	class scala/MatchError
	dup
	new	class scala/Tuple2
	dup
	aload_1
	aload_2
	invokespecial	Method scala/Tuple2."<init>":(Ljava/lang/Object;Ljava/lang/Object;)V
	invokevirtual	Method scala/Tuple2.toString:()Ljava/lang/String;
	invokespecial	Method scala/MatchError."<init>":(Ljava/lang/String;)V
	athrow
l6	new	class scala/MatchError
	dup
	new	class scala/Tuple2
	dup
	aload_1
	aload_2
	invokespecial	Method scala/Tuple2."<init>":(Ljava/lang/Object;Ljava/lang/Object;)V
	invokevirtual	Method scala/Tuple2.toString:()Ljava/lang/String;
	invokespecial	Method scala/MatchError."<init>":(Ljava/lang/String;)V
	athrow
l5	new	class scala/MatchError
	dup
	new	class scala/Tuple2
	dup
	aload_1
	aload_2
	invokespecial	Method scala/Tuple2."<init>":(Ljava/lang/Object;Ljava/lang/Object;)V
	invokevirtual	Method scala/Tuple2.toString:()Ljava/lang/String;
	invokespecial	Method scala/MatchError."<init>":(Ljava/lang/String;)V
	athrow
  Labels:
   	l3 = 63 // new
   	l2 = 83 // new
   	l1 = 103 // aload_1
   	l4 = 165 // areturn
   	l7 = 166 // new
   	l6 = 186 // new
   	l5 = 206 // new
  LocalVariableTable: 
   Start  Length  Slot  Name   Signature
   0      226      0    this       Lscala/collection/immutable/List$$anonfun$separate$1;
   12      91      3    temp39       Lscala/Left;
   31      52      4    temp41       Lscala/collection/immutable/List;
   18      85      5    temp40       Ljava/lang/Object;
   40      43      6    temp42       Lscala/collection/immutable/List;
   116      49      7    temp43       Lscala/Right;
   166      40      7    temp43       Lscala/Right;
   136      29      8    temp45       Lscala/collection/immutable/List;
   166      20      8    temp45       Lscala/collection/immutable/List;
   145      20      9    temp46       Lscala/collection/immutable/List;
   166      20      9    temp46       Lscala/collection/immutable/List;
   123      42      10    temp44       Ljava/lang/Object;
   166      40      10    temp44       Ljava/lang/Object;

  Signature: length = 0x2
   00 55 

public scala.Function1 curry();
  Signature: ()Lscala/Function1;
  Code:
   Stack=1, Locals=1, Args_size=1
	aload_0
	invokestatic	Method scala/Function2$class.curry:(Lscala/Function2;)Lscala/Function1;
	areturn
  Labels:

public java.lang.String toString();
  Signature: ()Ljava/lang/String;
  Code:
   Stack=1, Locals=1, Args_size=1
	aload_0
	invokestatic	Method scala/Function2$class.toString:(Lscala/Function2;)Ljava/lang/String;
	areturn
  Labels:

}

