Compiled from "List.scala"
public final class scala.collection.immutable.List$$anonfun$separate$1 extends java.lang.Object implements scala.Function2,scala.ScalaObject,java.io.Serializable
  SourceFile: "List.scala"
  Scala: length = 0x
   
  InnerClass: 
   public final #97= #9 of #49; //$anonfun$separate$1=class scala/collection/immutable/List$$anonfun$separate$1 of class scala/collection/immutable/List
  minor version: 0
  major version: 49
  Constant pool:
const #1 = Asciz	SourceFile;
const #2 = Asciz	List.scala;
const #3 = Asciz	<clinit>;
const #4 = Asciz	()V;
const #5 = Asciz	Code;
const #6 = Asciz	serialVersionUID;
const #7 = Asciz	J;
const #8 = Asciz	scala/collection/immutable/List$$anonfun$separate$1;
const #9 = class	#8;	//  scala/collection/immutable/List$$anonfun$separate$1
const #10 = NameAndType	#6:#7;//  serialVersionUID:J
const #11 = Field	#9.#10;	//  scala/collection/immutable/List$$anonfun$separate$1.serialVersionUID:J
const #12 = Asciz	<init>;
const #13 = Asciz	LineNumberTable;
const #14 = Asciz	java/lang/Object;
const #15 = class	#14;	//  java/lang/Object
const #16 = NameAndType	#12:#4;//  "<init>":()V
const #17 = Method	#15.#16;	//  java/lang/Object."<init>":()V
const #18 = Asciz	scala/Function2$class;
const #19 = class	#18;	//  scala/Function2$class
const #20 = Asciz	$init$;
const #21 = Asciz	(Lscala/Function2;)V;
const #22 = NameAndType	#20:#21;//  $init$:(Lscala/Function2;)V
const #23 = Method	#19.#22;	//  scala/Function2$class.$init$:(Lscala/Function2;)V
const #24 = Asciz	apply;
const #25 = Asciz	(Ljava/lang/Object;Ljava/lang/Object;)Ljava/lang/Object;;
const #26 = Asciz	scala/Either;
const #27 = class	#26;	//  scala/Either
const #28 = Asciz	scala/Tuple2;
const #29 = class	#28;	//  scala/Tuple2
const #30 = Asciz	(Lscala/Either;Lscala/Tuple2;)Lscala/Tuple2;;
const #31 = NameAndType	#24:#30;//  apply:(Lscala/Either;Lscala/Tuple2;)Lscala/Tuple2;
const #32 = Method	#9.#31;	//  scala/collection/immutable/List$$anonfun$separate$1.apply:(Lscala/Either;Lscala/Tuple2;)Lscala/Tuple2;
const #33 = Asciz	this;
const #34 = Asciz	Lscala/collection/immutable/List$$anonfun$separate$1;;
const #35 = Asciz	v1;
const #36 = Asciz	Ljava/lang/Object;;
const #37 = Asciz	v2;
const #38 = Asciz	LocalVariableTable;
const #39 = Asciz	scala/Left;
const #40 = class	#39;	//  scala/Left
const #41 = Asciz	a;
const #42 = NameAndType	#41:#36;//  a:Ljava/lang/Object;
const #43 = Field	#40.#42;	//  scala/Left.a:Ljava/lang/Object;
const #44 = Asciz	_1;
const #45 = Asciz	()Ljava/lang/Object;;
const #46 = NameAndType	#44:#45;//  _1:()Ljava/lang/Object;
const #47 = Method	#29.#46;	//  scala/Tuple2._1:()Ljava/lang/Object;
const #48 = Asciz	scala/collection/immutable/List;
const #49 = class	#48;	//  scala/collection/immutable/List
const #50 = Asciz	_2;
const #51 = NameAndType	#50:#45;//  _2:()Ljava/lang/Object;
const #52 = Method	#29.#51;	//  scala/Tuple2._2:()Ljava/lang/Object;
const #53 = Asciz	$colon$colon;
const #54 = Asciz	(Ljava/lang/Object;)Lscala/collection/immutable/List;;
const #55 = NameAndType	#53:#54;//  $colon$colon:(Ljava/lang/Object;)Lscala/collection/immutable/List;
const #56 = Method	#49.#55;	//  scala/collection/immutable/List.$colon$colon:(Ljava/lang/Object;)Lscala/collection/immutable/List;
const #57 = Asciz	(Ljava/lang/Object;Ljava/lang/Object;)V;
const #58 = NameAndType	#12:#57;//  "<init>":(Ljava/lang/Object;Ljava/lang/Object;)V
const #59 = Method	#29.#58;	//  scala/Tuple2."<init>":(Ljava/lang/Object;Ljava/lang/Object;)V
const #60 = Asciz	scala/MatchError;
const #61 = class	#60;	//  scala/MatchError
const #62 = Asciz	toString;
const #63 = Asciz	()Ljava/lang/String;;
const #64 = NameAndType	#62:#63;//  toString:()Ljava/lang/String;
const #65 = Method	#29.#64;	//  scala/Tuple2.toString:()Ljava/lang/String;
const #66 = Asciz	(Ljava/lang/String;)V;
const #67 = NameAndType	#12:#66;//  "<init>":(Ljava/lang/String;)V
const #68 = Method	#61.#67;	//  scala/MatchError."<init>":(Ljava/lang/String;)V
const #69 = Asciz	scala/Right;
const #70 = class	#69;	//  scala/Right
const #71 = Asciz	b;
const #72 = NameAndType	#71:#36;//  b:Ljava/lang/Object;
const #73 = Field	#70.#72;	//  scala/Right.b:Ljava/lang/Object;
const #74 = Asciz	temp39;
const #75 = Asciz	Lscala/Left;;
const #76 = Asciz	temp41;
const #77 = Asciz	Lscala/collection/immutable/List;;
const #78 = Asciz	temp40;
const #79 = Asciz	temp42;
const #80 = Asciz	temp43;
const #81 = Asciz	Lscala/Right;;
const #82 = Asciz	temp45;
const #83 = Asciz	temp46;
const #84 = Asciz	temp44;
const #85 = Asciz	(Lscala/Either<TA;TB;>;Lscala/Tuple2<Lscala/collection/immutable/List<TA;>;Lscala/collection/immutable/List<TB;>;>;)Lscala/Tuple2<Lscala/collection/immutable/List<TA;>;Lscala/collection/immutable/List<TB;>;>;;
const #86 = Asciz	Signature;
const #87 = Asciz	curry;
const #88 = Asciz	()Lscala/Function1;;
const #89 = Asciz	(Lscala/Function2;)Lscala/Function1;;
const #90 = NameAndType	#87:#89;//  curry:(Lscala/Function2;)Lscala/Function1;
const #91 = Method	#19.#90;	//  scala/Function2$class.curry:(Lscala/Function2;)Lscala/Function1;
const #92 = Asciz	(Lscala/Function2;)Ljava/lang/String;;
const #93 = NameAndType	#62:#92;//  toString:(Lscala/Function2;)Ljava/lang/String;
const #94 = Method	#19.#93;	//  scala/Function2$class.toString:(Lscala/Function2;)Ljava/lang/String;
const #95 = Asciz	Scala;
const #96 = Asciz	InnerClasses;
const #97 = Asciz	$anonfun$separate$1;
const #98 = Asciz	scala/Function2;
const #99 = class	#98;	//  scala/Function2
const #100 = Asciz	scala/ScalaObject;
const #101 = class	#100;	//  scala/ScalaObject
const #102 = Asciz	java/io/Serializable;
const #103 = class	#102;	//  java/io/Serializable

{
public static final long serialVersionUID;

public static {};
  Code:
   Stack=2, Locals=0, Args_size=0
   0:	lconst_0
   1:	putstatic	#11; //Field serialVersionUID:J
   4:	return

public scala.collection.immutable.List$$anonfun$separate$1();
  Code:
   Stack=1, Locals=1, Args_size=1
   0:	aload_0
   1:	invokespecial	#17; //Method java/lang/Object."<init>":()V
   4:	aload_0
   5:	invokestatic	#23; //Method scala/Function2$class.$init$:(Lscala/Function2;)V
   8:	return
  LineNumberTable: 
   line 624: 0


public final java.lang.Object apply(java.lang.Object, java.lang.Object);
  Code:
   Stack=3, Locals=3, Args_size=3
   0:	aload_0
   1:	aload_1
   2:	checkcast	#27; //class scala/Either
   5:	aload_2
   6:	checkcast	#29; //class scala/Tuple2
   9:	invokevirtual	#32; //Method apply:(Lscala/Either;Lscala/Tuple2;)Lscala/Tuple2;
   12:	areturn
  LineNumberTable: 
   line 624: 0

  LocalVariableTable: 
   Start  Length  Slot  Name   Signature
   0      13      0    this       Lscala/collection/immutable/List$$anonfun$separate$1;
   0      13      1    v1       Ljava/lang/Object;
   0      13      2    v2       Ljava/lang/Object;


public final scala.Tuple2 apply(scala.Either, scala.Tuple2);
  Code:
   Stack=6, Locals=11, Args_size=3
   0:	aload_1
   1:	instanceof	#40; //class scala/Left
   4:	ifeq	103
   7:	aload_1
   8:	checkcast	#40; //class scala/Left
   11:	astore_3
   12:	aload_3
   13:	getfield	#43; //Field scala/Left.a:Ljava/lang/Object;
   16:	astore	5
   18:	aload_2
   19:	ifnull	83
   22:	aload_2
   23:	invokevirtual	#47; //Method scala/Tuple2._1:()Ljava/lang/Object;
   26:	checkcast	#49; //class scala/collection/immutable/List
   29:	astore	4
   31:	aload_2
   32:	invokevirtual	#52; //Method scala/Tuple2._2:()Ljava/lang/Object;
   35:	checkcast	#49; //class scala/collection/immutable/List
   38:	astore	6
   40:	iconst_1
   41:	ifeq	63
   44:	new	#29; //class scala/Tuple2
   47:	dup
   48:	aload	4
   50:	aload	5
   52:	invokevirtual	#56; //Method scala/collection/immutable/List.$colon$colon:(Ljava/lang/Object;)Lscala/collection/immutable/List;
   55:	aload	6
   57:	invokespecial	#59; //Method scala/Tuple2."<init>":(Ljava/lang/Object;Ljava/lang/Object;)V
   60:	goto	165
   63:	new	#61; //class scala/MatchError
   66:	dup
   67:	new	#29; //class scala/Tuple2
   70:	dup
   71:	aload_1
   72:	aload_2
   73:	invokespecial	#59; //Method scala/Tuple2."<init>":(Ljava/lang/Object;Ljava/lang/Object;)V
   76:	invokevirtual	#65; //Method scala/Tuple2.toString:()Ljava/lang/String;
   79:	invokespecial	#68; //Method scala/MatchError."<init>":(Ljava/lang/String;)V
   82:	athrow
   83:	new	#61; //class scala/MatchError
   86:	dup
   87:	new	#29; //class scala/Tuple2
   90:	dup
   91:	aload_1
   92:	aload_2
   93:	invokespecial	#59; //Method scala/Tuple2."<init>":(Ljava/lang/Object;Ljava/lang/Object;)V
   96:	invokevirtual	#65; //Method scala/Tuple2.toString:()Ljava/lang/String;
   99:	invokespecial	#68; //Method scala/MatchError."<init>":(Ljava/lang/String;)V
   102:	athrow
   103:	aload_1
   104:	instanceof	#70; //class scala/Right
   107:	ifeq	206
   110:	aload_1
   111:	checkcast	#70; //class scala/Right
   114:	astore	7
   116:	aload	7
   118:	getfield	#73; //Field scala/Right.b:Ljava/lang/Object;
   121:	astore	10
   123:	aload_2
   124:	ifnull	186
   127:	aload_2
   128:	invokevirtual	#47; //Method scala/Tuple2._1:()Ljava/lang/Object;
   131:	checkcast	#49; //class scala/collection/immutable/List
   134:	astore	8
   136:	aload_2
   137:	invokevirtual	#52; //Method scala/Tuple2._2:()Ljava/lang/Object;
   140:	checkcast	#49; //class scala/collection/immutable/List
   143:	astore	9
   145:	iconst_1
   146:	ifeq	166
   149:	new	#29; //class scala/Tuple2
   152:	dup
   153:	aload	8
   155:	aload	9
   157:	aload	10
   159:	invokevirtual	#56; //Method scala/collection/immutable/List.$colon$colon:(Ljava/lang/Object;)Lscala/collection/immutable/List;
   162:	invokespecial	#59; //Method scala/Tuple2."<init>":(Ljava/lang/Object;Ljava/lang/Object;)V
   165:	areturn
   166:	new	#61; //class scala/MatchError
   169:	dup
   170:	new	#29; //class scala/Tuple2
   173:	dup
   174:	aload_1
   175:	aload_2
   176:	invokespecial	#59; //Method scala/Tuple2."<init>":(Ljava/lang/Object;Ljava/lang/Object;)V
   179:	invokevirtual	#65; //Method scala/Tuple2.toString:()Ljava/lang/String;
   182:	invokespecial	#68; //Method scala/MatchError."<init>":(Ljava/lang/String;)V
   185:	athrow
   186:	new	#61; //class scala/MatchError
   189:	dup
   190:	new	#29; //class scala/Tuple2
   193:	dup
   194:	aload_1
   195:	aload_2
   196:	invokespecial	#59; //Method scala/Tuple2."<init>":(Ljava/lang/Object;Ljava/lang/Object;)V
   199:	invokevirtual	#65; //Method scala/Tuple2.toString:()Ljava/lang/String;
   202:	invokespecial	#68; //Method scala/MatchError."<init>":(Ljava/lang/String;)V
   205:	athrow
   206:	new	#61; //class scala/MatchError
   209:	dup
   210:	new	#29; //class scala/Tuple2
   213:	dup
   214:	aload_1
   215:	aload_2
   216:	invokespecial	#59; //Method scala/Tuple2."<init>":(Ljava/lang/Object;Ljava/lang/Object;)V
   219:	invokevirtual	#65; //Method scala/Tuple2.toString:()Ljava/lang/String;
   222:	invokespecial	#68; //Method scala/MatchError."<init>":(Ljava/lang/String;)V
   225:	athrow
  LineNumberTable: 
   line 624: 0
   line 21: 40
   line 625: 44
   line 624: 63
   line 21: 145
   line 626: 149
   line 624: 165

  LocalVariableTable: 
   Start  Length  Slot  Name   Signature
   0      226      0    this       Lscala/collection/immutable/List$$anonfun$separate$1;
   12      91      3    temp39       Lscala/Left;
   31      52      4    temp41       Lscala/collection/immutable/List;
   18      85      5    temp40       Ljava/lang/Object;
   40      43      6    temp42       Lscala/collection/immutable/List;
   116      49      7    temp43       Lscala/Right;
   166      40      7    temp43       Lscala/Right;
   136      29      8    temp45       Lscala/collection/immutable/List;
   166      20      8    temp45       Lscala/collection/immutable/List;
   145      20      9    temp46       Lscala/collection/immutable/List;
   166      20      9    temp46       Lscala/collection/immutable/List;
   123      42      10    temp44       Ljava/lang/Object;
   166      40      10    temp44       Ljava/lang/Object;

  Signature: length = 0x2
   00 55 

public scala.Function1 curry();
  Code:
   Stack=1, Locals=1, Args_size=1
   0:	aload_0
   1:	invokestatic	#91; //Method scala/Function2$class.curry:(Lscala/Function2;)Lscala/Function1;
   4:	areturn
  LineNumberTable: 
   line 624: 0


public java.lang.String toString();
  Code:
   Stack=1, Locals=1, Args_size=1
   0:	aload_0
   1:	invokestatic	#94; //Method scala/Function2$class.toString:(Lscala/Function2;)Ljava/lang/String;
   4:	areturn
  LineNumberTable: 
   line 624: 0


}

