Compiled from "List.scala"
public final class scala.collection.immutable.List$$anonfun$flatten$1 extends java.lang.Object implements scala.Function1,scala.ScalaObject,java.io.Serializable
  SourceFile: "List.scala"
  Scala: length = 0x
   
  InnerClass: 
   public final $anonfun$flatten$1=class scala/collection/immutable/List$$anonfun$flatten$1 of class scala/collection/immutable/List
  minor version: 0
  major version: 49
  Constant pool:
Asciz	SourceFile;
Asciz	List.scala;
Asciz	<clinit>;
Asciz	()V;
Asciz	Code;
Asciz	serialVersionUID;
Asciz	J;
Asciz	scala/collection/immutable/List$$anonfun$flatten$1;
class	scala/collection/immutable/List$$anonfun$flatten$1
NameAndType	serialVersionUID:J
Field	scala/collection/immutable/List$$anonfun$flatten$1.serialVersionUID:J
Asciz	b$1;
Asciz	Lscala/collection/mutable/ListBuffer;;
Asciz	<init>;
Asciz	(Lscala/collection/mutable/ListBuffer;)V;
Asciz	LineNumberTable;
NameAndType	b$1:Lscala/collection/mutable/ListBuffer;
Field	scala/collection/immutable/List$$anonfun$flatten$1.b$1:Lscala/collection/mutable/ListBuffer;
Asciz	java/lang/Object;
class	java/lang/Object
NameAndType	"<init>":()V
Method	java/lang/Object."<init>":()V
Asciz	scala/Function1$class;
class	scala/Function1$class
Asciz	$init$;
Asciz	(Lscala/Function1;)V;
NameAndType	$init$:(Lscala/Function1;)V
Method	scala/Function1$class.$init$:(Lscala/Function1;)V
Asciz	apply;
Asciz	(Ljava/lang/Object;)Ljava/lang/Object;;
Asciz	scala/collection/immutable/List;
class	scala/collection/immutable/List
Asciz	(Lscala/collection/immutable/List;)V;
NameAndType	apply:(Lscala/collection/immutable/List;)V
Method	scala/collection/immutable/List$$anonfun$flatten$1.apply:(Lscala/collection/immutable/List;)V
Asciz	scala/runtime/BoxedUnit;
class	scala/runtime/BoxedUnit
Asciz	UNIT;
Asciz	Lscala/runtime/BoxedUnit;;
NameAndType	UNIT:Lscala/runtime/BoxedUnit;
Field	scala/runtime/BoxedUnit.UNIT:Lscala/runtime/BoxedUnit;
Asciz	this;
Asciz	Lscala/collection/immutable/List$$anonfun$flatten$1;;
Asciz	v1;
Asciz	Ljava/lang/Object;;
Asciz	LocalVariableTable;
Asciz	scala/collection/IterableLike;
class	scala/collection/IterableLike
Asciz	isEmpty;
Asciz	()Z;
NameAndType	isEmpty:()Z
InterfaceMethod	scala/collection/IterableLike.isEmpty:()Z
Asciz	head;
Asciz	()Ljava/lang/Object;;
NameAndType	head:()Ljava/lang/Object;
InterfaceMethod	scala/collection/IterableLike.head:()Ljava/lang/Object;
Asciz	scala/collection/mutable/ListBuffer;
class	scala/collection/mutable/ListBuffer
Asciz	$plus$eq;
Asciz	(Ljava/lang/Object;)Lscala/collection/mutable/ListBuffer;;
NameAndType	$plus$eq:(Ljava/lang/Object;)Lscala/collection/mutable/ListBuffer;
Method	scala/collection/mutable/ListBuffer.$plus$eq:(Ljava/lang/Object;)Lscala/collection/mutable/ListBuffer;
Asciz	scala/collection/TraversableLike;
class	scala/collection/TraversableLike
Asciz	tail;
NameAndType	tail:()Ljava/lang/Object;
InterfaceMethod	scala/collection/TraversableLike.tail:()Ljava/lang/Object;
Asciz	xs;
Asciz	Lscala/collection/immutable/List;;
Asciz	xc;
Asciz	(Lscala/collection/immutable/List<TA;>;)V;
Asciz	Signature;
Asciz	andThen;
Asciz	(Lscala/Function1;)Lscala/Function1;;
Asciz	(Lscala/Function1;Lscala/Function1;)Lscala/Function1;;
NameAndType	andThen:(Lscala/Function1;Lscala/Function1;)Lscala/Function1;
Method	scala/Function1$class.andThen:(Lscala/Function1;Lscala/Function1;)Lscala/Function1;
Asciz	g;
Asciz	Lscala/Function1;;
Asciz	compose;
NameAndType	compose:(Lscala/Function1;Lscala/Function1;)Lscala/Function1;
Method	scala/Function1$class.compose:(Lscala/Function1;Lscala/Function1;)Lscala/Function1;
Asciz	toString;
Asciz	()Ljava/lang/String;;
Asciz	(Lscala/Function1;)Ljava/lang/String;;
NameAndType	toString:(Lscala/Function1;)Ljava/lang/String;
Method	scala/Function1$class.toString:(Lscala/Function1;)Ljava/lang/String;
Asciz	Scala;
Asciz	InnerClasses;
Asciz	$anonfun$flatten$1;
Asciz	scala/Function1;
class	scala/Function1
Asciz	scala/ScalaObject;
class	scala/ScalaObject
Asciz	java/io/Serializable;
class	java/io/Serializable

{
public static final long serialVersionUID;
  Signature: J

private final scala.collection.mutable.ListBuffer b$1;
  Signature: Lscala/collection/mutable/ListBuffer;

public static {};
  Signature: ()V
  Code:
   Stack=2, Locals=0, Args_size=0
	lconst_0
	putstatic	Field serialVersionUID:J
	return
  Labels:

public scala.collection.immutable.List$$anonfun$flatten$1(scala.collection.mutable.ListBuffer);
  Signature: (Lscala/collection/mutable/ListBuffer;)V
  Code:
   Stack=2, Locals=2, Args_size=2
	aload_0
	aload_1
	putfield	Field b$1:Lscala/collection/mutable/ListBuffer;
	aload_0
	invokespecial	Method java/lang/Object."<init>":()V
	aload_0
	invokestatic	Method scala/Function1$class.$init$:(Lscala/Function1;)V
	return
  Labels:

public final java.lang.Object apply(java.lang.Object);
  Signature: (Ljava/lang/Object;)Ljava/lang/Object;
  Code:
   Stack=2, Locals=2, Args_size=2
	aload_0
	aload_1
	checkcast	class scala/collection/immutable/List
	invokevirtual	Method apply:(Lscala/collection/immutable/List;)V
	getstatic	Field scala/runtime/BoxedUnit.UNIT:Lscala/runtime/BoxedUnit;
	areturn
  Labels:
  LocalVariableTable: 
   Start  Length  Slot  Name   Signature
   0      12      0    this       Lscala/collection/immutable/List$$anonfun$flatten$1;
   0      12      1    v1       Ljava/lang/Object;


public final void apply(scala.collection.immutable.List);
  Signature: (Lscala/collection/immutable/List;)V
  Code:
   Stack=2, Locals=3, Args_size=2
	aload_1
	astore_2
l2	aload_2
	invokeinterface	InterfaceMethod scala/collection/IterableLike.isEmpty:()Z
	ifeq	l1 // aload_0
	return
l1	aload_0
	getfield	Field b$1:Lscala/collection/mutable/ListBuffer;
	aload_2
	invokeinterface	InterfaceMethod scala/collection/IterableLike.head:()Ljava/lang/Object;
	invokevirtual	Method scala/collection/mutable/ListBuffer.$plus$eq:(Ljava/lang/Object;)Lscala/collection/mutable/ListBuffer;
	pop
	aload_2
	invokeinterface	InterfaceMethod scala/collection/TraversableLike.tail:()Ljava/lang/Object;
	checkcast	class scala/collection/immutable/List
	astore_2
	goto	l2 // aload_2
  Labels:
   	l2 = 2 // aload_2
   	l1 = 12 // aload_0
  LocalVariableTable: 
   Start  Length  Slot  Name   Signature
   0      39      0    this       Lscala/collection/immutable/List$$anonfun$flatten$1;
   0      39      1    xs       Lscala/collection/immutable/List;
   2      37      2    xc       Lscala/collection/immutable/List;

  Signature: length = 0x2
   00 47 

public scala.Function1 andThen(scala.Function1);
  Signature: (Lscala/Function1;)Lscala/Function1;
  Code:
   Stack=2, Locals=2, Args_size=2
	aload_0
	aload_1
	invokestatic	Method scala/Function1$class.andThen:(Lscala/Function1;Lscala/Function1;)Lscala/Function1;
	areturn
  Labels:
  LocalVariableTable: 
   Start  Length  Slot  Name   Signature
   0      6      0    this       Lscala/collection/immutable/List$$anonfun$flatten$1;
   0      6      1    g       Lscala/Function1;


public scala.Function1 compose(scala.Function1);
  Signature: (Lscala/Function1;)Lscala/Function1;
  Code:
   Stack=2, Locals=2, Args_size=2
	aload_0
	aload_1
	invokestatic	Method scala/Function1$class.compose:(Lscala/Function1;Lscala/Function1;)Lscala/Function1;
	areturn
  Labels:
  LocalVariableTable: 
   Start  Length  Slot  Name   Signature
   0      6      0    this       Lscala/collection/immutable/List$$anonfun$flatten$1;
   0      6      1    g       Lscala/Function1;


public java.lang.String toString();
  Signature: ()Ljava/lang/String;
  Code:
   Stack=1, Locals=1, Args_size=1
	aload_0
	invokestatic	Method scala/Function1$class.toString:(Lscala/Function1;)Ljava/lang/String;
	areturn
  Labels:

}

