Compiled from "List.scala"
public final class scala.collection.immutable.List$$anonfun$break$1 extends scala.runtime.AbstractFunction1 implements java.io.Serializable
  SourceFile: "List.scala"
  Scala: length = 0x
   
  InnerClass: 
   public final $anonfun$break$1=class scala/collection/immutable/List$$anonfun$break$1 of class scala/collection/immutable/List
  minor version: 0
  major version: 49
  Constant pool:
Asciz	SourceFile;
Asciz	List.scala;
Asciz	<clinit>;
Asciz	()V;
Asciz	Code;
Asciz	serialVersionUID;
Asciz	J;
Asciz	scala/collection/immutable/List$$anonfun$break$1;
class	scala/collection/immutable/List$$anonfun$break$1
NameAndType	serialVersionUID:J
Field	scala/collection/immutable/List$$anonfun$break$1.serialVersionUID:J
Asciz	p$2;
Asciz	Lscala/Function1;;
Asciz	<init>;
Asciz	(Lscala/collection/immutable/List;Lscala/Function1;)V;
Asciz	LineNumberTable;
NameAndType	p$2:Lscala/Function1;
Field	scala/collection/immutable/List$$anonfun$break$1.p$2:Lscala/Function1;
Asciz	scala/runtime/AbstractFunction1;
class	scala/runtime/AbstractFunction1
NameAndType	"<init>":()V
Method	scala/runtime/AbstractFunction1."<init>":()V
Asciz	this;
Asciz	Lscala/collection/immutable/List$$anonfun$break$1;;
Asciz	$outer;
Asciz	Lscala/collection/immutable/List;;
Asciz	LocalVariableTable;
Asciz	(Lscala/collection/immutable/List<TA;>;)V;
Asciz	Signature;
Asciz	apply;
Asciz	(Ljava/lang/Object;)Ljava/lang/Object;;
Asciz	(Ljava/lang/Object;)Z;
NameAndType	apply:(Ljava/lang/Object;)Z
Method	scala/collection/immutable/List$$anonfun$break$1.apply:(Ljava/lang/Object;)Z
Asciz	scala/runtime/BoxesRunTime;
class	scala/runtime/BoxesRunTime
Asciz	boxToBoolean;
Asciz	(Z)Ljava/lang/Boolean;;
NameAndType	boxToBoolean:(Z)Ljava/lang/Boolean;
Method	scala/runtime/BoxesRunTime.boxToBoolean:(Z)Ljava/lang/Boolean;
Asciz	v1;
Asciz	Ljava/lang/Object;;
Asciz	scala/Function1;
class	scala/Function1
NameAndType	apply:(Ljava/lang/Object;)Ljava/lang/Object;
InterfaceMethod	scala/Function1.apply:(Ljava/lang/Object;)Ljava/lang/Object;
Asciz	unboxToBoolean;
NameAndType	unboxToBoolean:(Ljava/lang/Object;)Z
Method	scala/runtime/BoxesRunTime.unboxToBoolean:(Ljava/lang/Object;)Z
Asciz	x;
Asciz	(TA;)Z;
Asciz	Scala;
Asciz	InnerClasses;
Asciz	scala/collection/immutable/List;
class	scala/collection/immutable/List
Asciz	$anonfun$break$1;
Asciz	java/io/Serializable;
class	java/io/Serializable

{
public static final long serialVersionUID;
  Signature: J

private final scala.Function1 p$2;
  Signature: Lscala/Function1;

public static {};
  Signature: ()V
  Code:
   Stack=2, Locals=0, Args_size=0
	lconst_0
	putstatic	Field serialVersionUID:J
	return
  Labels:

public scala.collection.immutable.List$$anonfun$break$1(scala.collection.immutable.List, scala.Function1);
  Signature: (Lscala/collection/immutable/List;Lscala/Function1;)V
  Code:
   Stack=2, Locals=3, Args_size=3
	aload_0
	aload_2
	putfield	Field p$2:Lscala/Function1;
	aload_0
	invokespecial	Method scala/runtime/AbstractFunction1."<init>":()V
	return
  Labels:
  LocalVariableTable: 
   Start  Length  Slot  Name   Signature
   0      10      0    this       Lscala/collection/immutable/List$$anonfun$break$1;
   0      10      1    $outer       Lscala/collection/immutable/List;

  Signature: length = 0x2
   00 1C 

public final java.lang.Object apply(java.lang.Object);
  Signature: (Ljava/lang/Object;)Ljava/lang/Object;
  Code:
   Stack=2, Locals=3, Args_size=2
	aload_0
	aload_1
	invokevirtual	Method apply:(Ljava/lang/Object;)Z
	istore_2
	iload_2
	invokestatic	Method scala/runtime/BoxesRunTime.boxToBoolean:(Z)Ljava/lang/Boolean;
	areturn
  Labels:
  LocalVariableTable: 
   Start  Length  Slot  Name   Signature
   0      11      0    this       Lscala/collection/immutable/List$$anonfun$break$1;
   0      11      1    v1       Ljava/lang/Object;


public final boolean apply(java.lang.Object);
  Signature: (Ljava/lang/Object;)Z
  Code:
   Stack=2, Locals=2, Args_size=2
	aload_0
	getfield	Field p$2:Lscala/Function1;
	aload_1
	invokeinterface	InterfaceMethod scala/Function1.apply:(Ljava/lang/Object;)Ljava/lang/Object;
	invokestatic	Method scala/runtime/BoxesRunTime.unboxToBoolean:(Ljava/lang/Object;)Z
	ifeq	l1 // iconst_1
	iconst_0
	goto	l2 // ireturn
l1	iconst_1
l2	ireturn
  Labels:
   	l1 = 20 // iconst_1
   	l2 = 21 // ireturn
  LocalVariableTable: 
   Start  Length  Slot  Name   Signature
   0      22      0    this       Lscala/collection/immutable/List$$anonfun$break$1;
   0      22      1    x       Ljava/lang/Object;

  Signature: length = 0x2
   00 33 

}

