Compiled from "List.scala"
public final class scala.collection.immutable.List$$anonfun$unzip$1 extends scala.runtime.AbstractFunction2 implements java.io.Serializable
  SourceFile: "List.scala"
  Scala: length = 0x
   
  InnerClass: 
   public final $anonfun$unzip$1=class scala/collection/immutable/List$$anonfun$unzip$1 of class scala/collection/immutable/List
  minor version: 0
  major version: 49
  Constant pool:
Asciz	SourceFile;
Asciz	List.scala;
Asciz	<clinit>;
Asciz	()V;
Asciz	Code;
Asciz	serialVersionUID;
Asciz	J;
Asciz	scala/collection/immutable/List$$anonfun$unzip$1;
class	scala/collection/immutable/List$$anonfun$unzip$1
NameAndType	serialVersionUID:J
Field	scala/collection/immutable/List$$anonfun$unzip$1.serialVersionUID:J
Asciz	<init>;
Asciz	LineNumberTable;
Asciz	scala/runtime/AbstractFunction2;
class	scala/runtime/AbstractFunction2
NameAndType	"<init>":()V
Method	scala/runtime/AbstractFunction2."<init>":()V
Asciz	apply;
Asciz	(Ljava/lang/Object;Ljava/lang/Object;)Ljava/lang/Object;;
Asciz	scala/Tuple2;
class	scala/Tuple2
Asciz	(Lscala/Tuple2;Lscala/Tuple2;)Lscala/Tuple2;;
NameAndType	apply:(Lscala/Tuple2;Lscala/Tuple2;)Lscala/Tuple2;
Method	scala/collection/immutable/List$$anonfun$unzip$1.apply:(Lscala/Tuple2;Lscala/Tuple2;)Lscala/Tuple2;
Asciz	this;
Asciz	Lscala/collection/immutable/List$$anonfun$unzip$1;;
Asciz	v1;
Asciz	Ljava/lang/Object;;
Asciz	v2;
Asciz	LocalVariableTable;
Asciz	_1;
Asciz	()Ljava/lang/Object;;
NameAndType	_1:()Ljava/lang/Object;
Method	scala/Tuple2._1:()Ljava/lang/Object;
Asciz	_2;
NameAndType	_2:()Ljava/lang/Object;
Method	scala/Tuple2._2:()Ljava/lang/Object;
Asciz	scala/collection/immutable/List;
class	scala/collection/immutable/List
Asciz	$colon$colon;
Asciz	(Ljava/lang/Object;)Lscala/collection/immutable/List;;
NameAndType	$colon$colon:(Ljava/lang/Object;)Lscala/collection/immutable/List;
Method	scala/collection/immutable/List.$colon$colon:(Ljava/lang/Object;)Lscala/collection/immutable/List;
Asciz	(Ljava/lang/Object;Ljava/lang/Object;)V;
NameAndType	"<init>":(Ljava/lang/Object;Ljava/lang/Object;)V
Method	scala/Tuple2."<init>":(Ljava/lang/Object;Ljava/lang/Object;)V
Asciz	scala/MatchError;
class	scala/MatchError
Asciz	toString;
Asciz	()Ljava/lang/String;;
NameAndType	toString:()Ljava/lang/String;
Method	scala/Tuple2.toString:()Ljava/lang/String;
Asciz	(Ljava/lang/String;)V;
NameAndType	"<init>":(Ljava/lang/String;)V
Method	scala/MatchError."<init>":(Ljava/lang/String;)V
Asciz	temp27;
Asciz	Lscala/collection/immutable/List;;
Asciz	temp25;
Asciz	temp28;
Asciz	temp26;
Asciz	(Lscala/Tuple2<TA;TB;>;Lscala/Tuple2<Lscala/collection/immutable/List<TA;>;Lscala/collection/immutable/List<TB;>;>;)Lscala/Tuple2<Lscala/collection/immutable/List<TA;>;Lscala/collection/immutable/List<TB;>;>;;
Asciz	Signature;
Asciz	Scala;
Asciz	InnerClasses;
Asciz	$anonfun$unzip$1;
Asciz	java/io/Serializable;
class	java/io/Serializable

{
public static final long serialVersionUID;
  Signature: J

public static {};
  Signature: ()V
  Code:
   Stack=2, Locals=0, Args_size=0
	lconst_0
	putstatic	Field serialVersionUID:J
	return
  Labels:

public scala.collection.immutable.List$$anonfun$unzip$1();
  Signature: ()V
  Code:
   Stack=1, Locals=1, Args_size=1
	aload_0
	invokespecial	Method scala/runtime/AbstractFunction2."<init>":()V
	return
  Labels:

public final java.lang.Object apply(java.lang.Object, java.lang.Object);
  Signature: (Ljava/lang/Object;Ljava/lang/Object;)Ljava/lang/Object;
  Code:
   Stack=3, Locals=3, Args_size=3
	aload_0
	aload_1
	checkcast	class scala/Tuple2
	aload_2
	checkcast	class scala/Tuple2
	invokevirtual	Method apply:(Lscala/Tuple2;Lscala/Tuple2;)Lscala/Tuple2;
	areturn
  Labels:
  LocalVariableTable: 
   Start  Length  Slot  Name   Signature
   0      13      0    this       Lscala/collection/immutable/List$$anonfun$unzip$1;
   0      13      1    v1       Ljava/lang/Object;
   0      13      2    v2       Ljava/lang/Object;


public final scala.Tuple2 apply(scala.Tuple2, scala.Tuple2);
  Signature: (Lscala/Tuple2;Lscala/Tuple2;)Lscala/Tuple2;
  Code:
   Stack=6, Locals=7, Args_size=3
	aload_1
	ifnull	l1 // new
	aload_1
	invokevirtual	Method scala/Tuple2._1:()Ljava/lang/Object;
	astore	4
	aload_1
	invokevirtual	Method scala/Tuple2._2:()Ljava/lang/Object;
	astore	6
	aload_2
	ifnull	l2 // new
	aload_2
	invokevirtual	Method scala/Tuple2._1:()Ljava/lang/Object;
	checkcast	class scala/collection/immutable/List
	astore_3
	aload_2
	invokevirtual	Method scala/Tuple2._2:()Ljava/lang/Object;
	checkcast	class scala/collection/immutable/List
	astore	5
	iconst_1
	ifeq	l3 // new
	new	class scala/Tuple2
	dup
	aload_3
	aload	4
	invokevirtual	Method scala/collection/immutable/List.$colon$colon:(Ljava/lang/Object;)Lscala/collection/immutable/List;
	aload	5
	aload	6
	invokevirtual	Method scala/collection/immutable/List.$colon$colon:(Ljava/lang/Object;)Lscala/collection/immutable/List;
	invokespecial	Method scala/Tuple2."<init>":(Ljava/lang/Object;Ljava/lang/Object;)V
	areturn
l3	new	class scala/MatchError
	dup
	new	class scala/Tuple2
	dup
	aload_1
	aload_2
	invokespecial	Method scala/Tuple2."<init>":(Ljava/lang/Object;Ljava/lang/Object;)V
	invokevirtual	Method scala/Tuple2.toString:()Ljava/lang/String;
	invokespecial	Method scala/MatchError."<init>":(Ljava/lang/String;)V
	athrow
l2	new	class scala/MatchError
	dup
	new	class scala/Tuple2
	dup
	aload_1
	aload_2
	invokespecial	Method scala/Tuple2."<init>":(Ljava/lang/Object;Ljava/lang/Object;)V
	invokevirtual	Method scala/Tuple2.toString:()Ljava/lang/String;
	invokespecial	Method scala/MatchError."<init>":(Ljava/lang/String;)V
	athrow
l1	new	class scala/MatchError
	dup
	new	class scala/Tuple2
	dup
	aload_1
	aload_2
	invokespecial	Method scala/Tuple2."<init>":(Ljava/lang/Object;Ljava/lang/Object;)V
	invokevirtual	Method scala/Tuple2.toString:()Ljava/lang/String;
	invokespecial	Method scala/MatchError."<init>":(Ljava/lang/String;)V
	athrow
  Labels:
   	l3 = 62 // new
   	l2 = 82 // new
   	l1 = 102 // new
  LocalVariableTable: 
   Start  Length  Slot  Name   Signature
   0      122      0    this       Lscala/collection/immutable/List$$anonfun$unzip$1;
   28      54      3    temp27       Lscala/collection/immutable/List;
   10      92      4    temp25       Ljava/lang/Object;
   37      45      5    temp28       Lscala/collection/immutable/List;
   16      86      6    temp26       Ljava/lang/Object;

  Signature: length = 0x2
   00 3D 

}

