Compiled from "LongMap.scala"
public final class scala.collection.immutable.LongMapUtils$ extends java.lang.Object implements scala.ScalaObject
  SourceFile: "LongMap.scala"
  Scala: length = 0x
   
  InnerClass: 
   public #102= #46 of #101; //Bin=class scala/collection/immutable/LongMap$Bin of class scala/collection/immutable/LongMap
  minor version: 0
  major version: 49
  Constant pool:
const #1 = Asciz	SourceFile;
const #2 = Asciz	LongMap.scala;
const #3 = Asciz	Scala;
const #4 = Asciz	MODULE$;
const #5 = Asciz	Lscala/collection/immutable/LongMapUtils$;;
const #6 = Asciz	<clinit>;
const #7 = Asciz	()V;
const #8 = Asciz	Code;
const #9 = Asciz	scala/collection/immutable/LongMapUtils$;
const #10 = class	#9;	//  scala/collection/immutable/LongMapUtils$
const #11 = Asciz	<init>;
const #12 = NameAndType	#11:#7;//  "<init>":()V
const #13 = Method	#10.#12;	//  scala/collection/immutable/LongMapUtils$."<init>":()V
const #14 = Asciz	LineNumberTable;
const #15 = Asciz	java/lang/Object;
const #16 = class	#15;	//  java/lang/Object
const #17 = Method	#16.#12;	//  java/lang/Object."<init>":()V
const #18 = NameAndType	#4:#5;//  MODULE$:Lscala/collection/immutable/LongMapUtils$;
const #19 = Field	#10.#18;	//  scala/collection/immutable/LongMapUtils$.MODULE$:Lscala/collection/immutable/LongMapUtils$;
const #20 = Asciz	bin;
const #21 = Asciz	(JJLscala/collection/immutable/LongMap;Lscala/collection/immutable/LongMap;)Lscala/collection/immutable/LongMap;;
const #22 = Asciz	scala/collection/immutable/LongMap$Nil$;
const #23 = class	#22;	//  scala/collection/immutable/LongMap$Nil$
const #24 = Asciz	Lscala/collection/immutable/LongMap$Nil$;;
const #25 = NameAndType	#4:#24;//  MODULE$:Lscala/collection/immutable/LongMap$Nil$;
const #26 = Field	#23.#25;	//  scala/collection/immutable/LongMap$Nil$.MODULE$:Lscala/collection/immutable/LongMap$Nil$;
const #27 = Asciz	equals;
const #28 = Asciz	(Ljava/lang/Object;)Z;
const #29 = NameAndType	#27:#28;//  equals:(Ljava/lang/Object;)Z
const #30 = Method	#16.#29;	//  java/lang/Object.equals:(Ljava/lang/Object;)Z
const #31 = Asciz	scala/MatchError;
const #32 = class	#31;	//  scala/MatchError
const #33 = Asciz	scala/Tuple2;
const #34 = class	#33;	//  scala/Tuple2
const #35 = Asciz	(Ljava/lang/Object;Ljava/lang/Object;)V;
const #36 = NameAndType	#11:#35;//  "<init>":(Ljava/lang/Object;Ljava/lang/Object;)V
const #37 = Method	#34.#36;	//  scala/Tuple2."<init>":(Ljava/lang/Object;Ljava/lang/Object;)V
const #38 = Asciz	toString;
const #39 = Asciz	()Ljava/lang/String;;
const #40 = NameAndType	#38:#39;//  toString:()Ljava/lang/String;
const #41 = Method	#34.#40;	//  scala/Tuple2.toString:()Ljava/lang/String;
const #42 = Asciz	(Ljava/lang/String;)V;
const #43 = NameAndType	#11:#42;//  "<init>":(Ljava/lang/String;)V
const #44 = Method	#32.#43;	//  scala/MatchError."<init>":(Ljava/lang/String;)V
const #45 = Asciz	scala/collection/immutable/LongMap$Bin;
const #46 = class	#45;	//  scala/collection/immutable/LongMap$Bin
const #47 = Asciz	(JJLscala/collection/immutable/LongMap;Lscala/collection/immutable/LongMap;)V;
const #48 = NameAndType	#11:#47;//  "<init>":(JJLscala/collection/immutable/LongMap;Lscala/collection/immutable/LongMap;)V
const #49 = Method	#46.#48;	//  scala/collection/immutable/LongMap$Bin."<init>":(JJLscala/collection/immutable/LongMap;Lscala/collection/immutable/LongMap;)V
const #50 = Asciz	this;
const #51 = Asciz	prefix;
const #52 = Asciz	J;
const #53 = Asciz	mask;
const #54 = Asciz	left;
const #55 = Asciz	Lscala/collection/immutable/LongMap;;
const #56 = Asciz	right;
const #57 = Asciz	LocalVariableTable;
const #58 = Asciz	<T:Ljava/lang/Object;>(JJLscala/collection/immutable/LongMap<TT;>;Lscala/collection/immutable/LongMap<TT;>;)Lscala/collection/immutable/LongMap<TT;>;;
const #59 = Asciz	Signature;
const #60 = Asciz	join;
const #61 = Asciz	(JLscala/collection/immutable/LongMap;JLscala/collection/immutable/LongMap;)Lscala/collection/immutable/LongMap;;
const #62 = int	8;
const #63 = int	16;
const #64 = int	32;
const #65 = long	-1l;
const #67 = Asciz	zero;
const #68 = Asciz	(JJ)Z;
const #69 = NameAndType	#67:#68;//  zero:(JJ)Z
const #70 = Method	#10.#69;	//  scala/collection/immutable/LongMapUtils$.zero:(JJ)Z
const #71 = Asciz	p1;
const #72 = Asciz	t1;
const #73 = Asciz	p2;
const #74 = Asciz	t2;
const #75 = Asciz	i1;
const #76 = Asciz	p;
const #77 = Asciz	m;
const #78 = Asciz	<T:Ljava/lang/Object;>(JLscala/collection/immutable/LongMap<TT;>;JLscala/collection/immutable/LongMap<TT;>;)Lscala/collection/immutable/LongMap<TT;>;;
const #79 = Asciz	highestOneBit;
const #80 = Asciz	(J)J;
const #81 = Asciz	j;
const #82 = Asciz	i;
const #83 = Asciz	branchMask;
const #84 = Asciz	(JJ)J;
const #85 = NameAndType	#79:#80;//  highestOneBit:(J)J
const #86 = Method	#10.#85;	//  scala/collection/immutable/LongMapUtils$.highestOneBit:(J)J
const #87 = Asciz	complement;
const #88 = Asciz	shorter;
const #89 = Asciz	unsignedCompare;
const #90 = NameAndType	#89:#68;//  unsignedCompare:(JJ)Z
const #91 = Method	#10.#90;	//  scala/collection/immutable/LongMapUtils$.unsignedCompare:(JJ)Z
const #92 = Asciz	m1;
const #93 = Asciz	m2;
const #94 = Asciz	hasMatch;
const #95 = Asciz	(JJJ)Z;
const #96 = Asciz	key;
const #97 = NameAndType	#87:#80;//  complement:(J)J
const #98 = Method	#10.#97;	//  scala/collection/immutable/LongMapUtils$.complement:(J)J
const #99 = Asciz	InnerClasses;
const #100 = Asciz	scala/collection/immutable/LongMap;
const #101 = class	#100;	//  scala/collection/immutable/LongMap
const #102 = Asciz	Bin;
const #103 = Asciz	scala/ScalaObject;
const #104 = class	#103;	//  scala/ScalaObject

{
public static final scala.collection.immutable.LongMapUtils$ MODULE$;

public static {};
  Code:
   Stack=1, Locals=0, Args_size=0
   0:	new	#10; //class scala/collection/immutable/LongMapUtils$
   3:	invokespecial	#13; //Method "<init>":()V
   6:	return

public scala.collection.immutable.LongMap bin(long, long, scala.collection.immutable.LongMap, scala.collection.immutable.LongMap);
  Code:
   Stack=8, Locals=7, Args_size=5
   0:	getstatic	#26; //Field scala/collection/immutable/LongMap$Nil$.MODULE$:Lscala/collection/immutable/LongMap$Nil$;
   3:	dup
   4:	ifnonnull	16
   7:	pop
   8:	aload	6
   10:	ifnull	24
   13:	goto	55
   16:	aload	6
   18:	invokevirtual	#30; //Method java/lang/Object.equals:(Ljava/lang/Object;)Z
   21:	ifeq	55
   24:	iconst_1
   25:	ifeq	33
   28:	aload	5
   30:	goto	127
   33:	new	#32; //class scala/MatchError
   36:	dup
   37:	new	#34; //class scala/Tuple2
   40:	dup
   41:	aload	5
   43:	aload	6
   45:	invokespecial	#37; //Method scala/Tuple2."<init>":(Ljava/lang/Object;Ljava/lang/Object;)V
   48:	invokevirtual	#41; //Method scala/Tuple2.toString:()Ljava/lang/String;
   51:	invokespecial	#44; //Method scala/MatchError."<init>":(Ljava/lang/String;)V
   54:	athrow
   55:	getstatic	#26; //Field scala/collection/immutable/LongMap$Nil$.MODULE$:Lscala/collection/immutable/LongMap$Nil$;
   58:	dup
   59:	ifnonnull	71
   62:	pop
   63:	aload	5
   65:	ifnull	79
   68:	goto	110
   71:	aload	5
   73:	invokevirtual	#30; //Method java/lang/Object.equals:(Ljava/lang/Object;)Z
   76:	ifeq	110
   79:	iconst_1
   80:	ifeq	88
   83:	aload	6
   85:	goto	127
   88:	new	#32; //class scala/MatchError
   91:	dup
   92:	new	#34; //class scala/Tuple2
   95:	dup
   96:	aload	5
   98:	aload	6
   100:	invokespecial	#37; //Method scala/Tuple2."<init>":(Ljava/lang/Object;Ljava/lang/Object;)V
   103:	invokevirtual	#41; //Method scala/Tuple2.toString:()Ljava/lang/String;
   106:	invokespecial	#44; //Method scala/MatchError."<init>":(Ljava/lang/String;)V
   109:	athrow
   110:	iconst_1
   111:	ifeq	128
   114:	new	#46; //class scala/collection/immutable/LongMap$Bin
   117:	dup
   118:	lload_1
   119:	lload_3
   120:	aload	5
   122:	aload	6
   124:	invokespecial	#49; //Method scala/collection/immutable/LongMap$Bin."<init>":(JJLscala/collection/immutable/LongMap;Lscala/collection/immutable/LongMap;)V
   127:	areturn
   128:	new	#32; //class scala/MatchError
   131:	dup
   132:	new	#34; //class scala/Tuple2
   135:	dup
   136:	aload	5
   138:	aload	6
   140:	invokespecial	#37; //Method scala/Tuple2."<init>":(Ljava/lang/Object;Ljava/lang/Object;)V
   143:	invokevirtual	#41; //Method scala/Tuple2.toString:()Ljava/lang/String;
   146:	invokespecial	#44; //Method scala/MatchError."<init>":(Ljava/lang/String;)V
   149:	athrow
  LineNumberTable: 
   line 34: 0
   line 21: 24
   line 35: 28
   line 34: 33
   line 21: 79
   line 36: 83
   line 34: 88
   line 21: 110
   line 37: 114
   line 34: 127

  LocalVariableTable: 
   Start  Length  Slot  Name   Signature
   0      150      0    this       Lscala/collection/immutable/LongMapUtils$;
   0      150      1    prefix       J
   0      150      3    mask       J
   0      150      5    left       Lscala/collection/immutable/LongMap;
   0      150      6    right       Lscala/collection/immutable/LongMap;

  Signature: length = 0x2
   00 3A 

public scala.collection.immutable.LongMap join(long, scala.collection.immutable.LongMap, long, scala.collection.immutable.LongMap);
  Code:
   Stack=8, Locals=17, Args_size=5
   0:	lload_1
   1:	lload	4
   3:	lxor
   4:	lstore	7
   6:	lload	7
   8:	lload	7
   10:	iconst_1
   11:	lshr
   12:	lor
   13:	lstore	9
   15:	lload	9
   17:	lload	9
   19:	iconst_2
   20:	lshr
   21:	lor
   22:	lstore	9
   24:	lload	9
   26:	lload	9
   28:	iconst_4
   29:	lshr
   30:	lor
   31:	lstore	9
   33:	lload	9
   35:	lload	9
   37:	ldc	#62; //int 8
   39:	lshr
   40:	lor
   41:	lstore	9
   43:	lload	9
   45:	lload	9
   47:	ldc	#63; //int 16
   49:	lshr
   50:	lor
   51:	lstore	9
   53:	lload	9
   55:	lload	9
   57:	ldc	#64; //int 32
   59:	lshr
   60:	lor
   61:	lstore	9
   63:	lload	9
   65:	lload	9
   67:	iconst_1
   68:	lushr
   69:	lsub
   70:	lstore	15
   72:	lload_1
   73:	lload	15
   75:	lconst_1
   76:	lsub
   77:	lstore	11
   79:	ldc2_w	#65; //long -1l
   82:	lload	11
   84:	lxor
   85:	lload	15
   87:	lxor
   88:	land
   89:	lstore	13
   91:	aload_0
   92:	lload_1
   93:	lload	15
   95:	invokevirtual	#70; //Method zero:(JJ)Z
   98:	ifeq	118
   101:	new	#46; //class scala/collection/immutable/LongMap$Bin
   104:	dup
   105:	lload	13
   107:	lload	15
   109:	aload_3
   110:	aload	6
   112:	invokespecial	#49; //Method scala/collection/immutable/LongMap$Bin."<init>":(JJLscala/collection/immutable/LongMap;Lscala/collection/immutable/LongMap;)V
   115:	goto	132
   118:	new	#46; //class scala/collection/immutable/LongMap$Bin
   121:	dup
   122:	lload	13
   124:	lload	15
   126:	aload	6
   128:	aload_3
   129:	invokespecial	#49; //Method scala/collection/immutable/LongMap$Bin."<init>":(JJLscala/collection/immutable/LongMap;Lscala/collection/immutable/LongMap;)V
   132:	areturn
  LineNumberTable: 
   line 28: 0
   line 29: 72
   line 30: 91
   line 31: 118
   line 27: 132

  LocalVariableTable: 
   Start  Length  Slot  Name   Signature
   0      133      0    this       Lscala/collection/immutable/LongMapUtils$;
   0      133      1    p1       J
   0      133      3    t1       Lscala/collection/immutable/LongMap;
   0      133      4    p2       J
   0      133      6    t2       Lscala/collection/immutable/LongMap;
   6      64      9    i1       J
   91      42      13    p       J
   72      61      15    m       J

  Signature: length = 0x2
   00 4E 

public long highestOneBit(long);
  Code:
   Stack=5, Locals=5, Args_size=2
   0:	lload_1
   1:	lload_1
   2:	iconst_1
   3:	lshr
   4:	lor
   5:	lstore_3
   6:	lload_3
   7:	lload_3
   8:	iconst_2
   9:	lshr
   10:	lor
   11:	lstore_3
   12:	lload_3
   13:	lload_3
   14:	iconst_4
   15:	lshr
   16:	lor
   17:	lstore_3
   18:	lload_3
   19:	lload_3
   20:	ldc	#62; //int 8
   22:	lshr
   23:	lor
   24:	lstore_3
   25:	lload_3
   26:	lload_3
   27:	ldc	#63; //int 16
   29:	lshr
   30:	lor
   31:	lstore_3
   32:	lload_3
   33:	lload_3
   34:	ldc	#64; //int 32
   36:	lshr
   37:	lor
   38:	lstore_3
   39:	lload_3
   40:	lload_3
   41:	iconst_1
   42:	lushr
   43:	lsub
   44:	lreturn
  LineNumberTable: 
   line 18: 0
   line 19: 6
   line 20: 12
   line 21: 18
   line 22: 25
   line 23: 32
   line 24: 39

  LocalVariableTable: 
   Start  Length  Slot  Name   Signature
   0      45      0    this       Lscala/collection/immutable/LongMapUtils$;
   0      45      1    j       J
   0      44      3    i       J


public long branchMask(long, long);
  Code:
   Stack=5, Locals=5, Args_size=3
   0:	aload_0
   1:	lload_1
   2:	lload_3
   3:	lxor
   4:	invokevirtual	#86; //Method highestOneBit:(J)J
   7:	lreturn
  LineNumberTable: 
   line 14: 0

  LocalVariableTable: 
   Start  Length  Slot  Name   Signature
   0      8      0    this       Lscala/collection/immutable/LongMapUtils$;
   0      8      1    i       J
   0      8      3    j       J


public long complement(long);
  Code:
   Stack=4, Locals=3, Args_size=2
   0:	ldc2_w	#65; //long -1l
   3:	lload_1
   4:	lxor
   5:	lreturn
  LineNumberTable: 
   line 13: 0

  LocalVariableTable: 
   Start  Length  Slot  Name   Signature
   0      6      0    this       Lscala/collection/immutable/LongMapUtils$;
   0      6      1    i       J


public boolean shorter(long, long);
  Code:
   Stack=5, Locals=5, Args_size=3
   0:	aload_0
   1:	lload_3
   2:	lload_1
   3:	invokevirtual	#91; //Method unsignedCompare:(JJ)Z
   6:	ireturn
  LineNumberTable: 
   line 12: 0

  LocalVariableTable: 
   Start  Length  Slot  Name   Signature
   0      7      0    this       Lscala/collection/immutable/LongMapUtils$;
   0      7      1    m1       J
   0      7      3    m2       J


public boolean unsignedCompare(long, long);
  Code:
   Stack=5, Locals=5, Args_size=3
   0:	lload_1
   1:	lload_3
   2:	lcmp
   3:	ifge	10
   6:	iconst_1
   7:	goto	11
   10:	iconst_0
   11:	lload_1
   12:	lconst_0
   13:	lcmp
   14:	ifge	21
   17:	iconst_1
   18:	goto	22
   21:	iconst_0
   22:	ixor
   23:	lload_3
   24:	lconst_0
   25:	lcmp
   26:	ifge	33
   29:	iconst_1
   30:	goto	34
   33:	iconst_0
   34:	ixor
   35:	ireturn
  LineNumberTable: 
   line 11: 0

  LocalVariableTable: 
   Start  Length  Slot  Name   Signature
   0      36      0    this       Lscala/collection/immutable/LongMapUtils$;
   0      36      1    i       J
   0      36      3    j       J


public boolean hasMatch(long, long, long);
  Code:
   Stack=6, Locals=9, Args_size=4
   0:	lload_1
   1:	lload	5
   3:	lconst_1
   4:	lsub
   5:	lstore	7
   7:	ldc2_w	#65; //long -1l
   10:	lload	7
   12:	lxor
   13:	lload	5
   15:	lxor
   16:	land
   17:	lload_3
   18:	lcmp
   19:	ifne	26
   22:	iconst_1
   23:	goto	27
   26:	iconst_0
   27:	ireturn
  LineNumberTable: 
   line 10: 0

  LocalVariableTable: 
   Start  Length  Slot  Name   Signature
   0      28      0    this       Lscala/collection/immutable/LongMapUtils$;
   0      28      1    key       J
   0      28      3    prefix       J
   0      28      5    m       J


public long mask(long, long);
  Code:
   Stack=7, Locals=5, Args_size=3
   0:	lload_1
   1:	aload_0
   2:	lload_3
   3:	lconst_1
   4:	lsub
   5:	invokevirtual	#98; //Method complement:(J)J
   8:	lload_3
   9:	lxor
   10:	land
   11:	lreturn
  LineNumberTable: 
   line 9: 0

  LocalVariableTable: 
   Start  Length  Slot  Name   Signature
   0      12      0    this       Lscala/collection/immutable/LongMapUtils$;
   0      12      1    i       J
   0      12      3    mask       J


public boolean zero(long, long);
  Code:
   Stack=4, Locals=5, Args_size=3
   0:	lload_1
   1:	lload_3
   2:	land
   3:	lconst_0
   4:	lcmp
   5:	ifne	12
   8:	iconst_1
   9:	goto	13
   12:	iconst_0
   13:	ireturn
  LineNumberTable: 
   line 8: 0

  LocalVariableTable: 
   Start  Length  Slot  Name   Signature
   0      14      0    this       Lscala/collection/immutable/LongMapUtils$;
   0      14      1    i       J
   0      14      3    mask       J


}

