Compiled from "LongMap.scala"
public final class scala.collection.immutable.LongMapUtils$ extends java.lang.Object implements scala.ScalaObject
  SourceFile: "LongMap.scala"
  Scala: length = 0x
   
  InnerClass: 
   public Bin=class scala/collection/immutable/LongMap$Bin of class scala/collection/immutable/LongMap
  minor version: 0
  major version: 49
  Constant pool:
Asciz	SourceFile;
Asciz	LongMap.scala;
Asciz	Scala;
Asciz	MODULE$;
Asciz	Lscala/collection/immutable/LongMapUtils$;;
Asciz	<clinit>;
Asciz	()V;
Asciz	Code;
Asciz	scala/collection/immutable/LongMapUtils$;
class	scala/collection/immutable/LongMapUtils$
Asciz	<init>;
NameAndType	"<init>":()V
Method	scala/collection/immutable/LongMapUtils$."<init>":()V
Asciz	LineNumberTable;
Asciz	java/lang/Object;
class	java/lang/Object
Method	java/lang/Object."<init>":()V
NameAndType	MODULE$:Lscala/collection/immutable/LongMapUtils$;
Field	scala/collection/immutable/LongMapUtils$.MODULE$:Lscala/collection/immutable/LongMapUtils$;
Asciz	bin;
Asciz	(JJLscala/collection/immutable/LongMap;Lscala/collection/immutable/LongMap;)Lscala/collection/immutable/LongMap;;
Asciz	scala/collection/immutable/LongMap$Nil$;
class	scala/collection/immutable/LongMap$Nil$
Asciz	Lscala/collection/immutable/LongMap$Nil$;;
NameAndType	MODULE$:Lscala/collection/immutable/LongMap$Nil$;
Field	scala/collection/immutable/LongMap$Nil$.MODULE$:Lscala/collection/immutable/LongMap$Nil$;
Asciz	equals;
Asciz	(Ljava/lang/Object;)Z;
NameAndType	equals:(Ljava/lang/Object;)Z
Method	java/lang/Object.equals:(Ljava/lang/Object;)Z
Asciz	scala/collection/immutable/LongMap$Bin;
class	scala/collection/immutable/LongMap$Bin
Asciz	(JJLscala/collection/immutable/LongMap;Lscala/collection/immutable/LongMap;)V;
NameAndType	"<init>":(JJLscala/collection/immutable/LongMap;Lscala/collection/immutable/LongMap;)V
Method	scala/collection/immutable/LongMap$Bin."<init>":(JJLscala/collection/immutable/LongMap;Lscala/collection/immutable/LongMap;)V
Asciz	this;
Asciz	prefix;
Asciz	J;
Asciz	mask;
Asciz	left;
Asciz	Lscala/collection/immutable/LongMap;;
Asciz	right;
Asciz	LocalVariableTable;
Asciz	<T:Ljava/lang/Object;>(JJLscala/collection/immutable/LongMap<TT;>;Lscala/collection/immutable/LongMap<TT;>;)Lscala/collection/immutable/LongMap<TT;>;;
Asciz	Signature;
Asciz	join;
Asciz	(JLscala/collection/immutable/LongMap;JLscala/collection/immutable/LongMap;)Lscala/collection/immutable/LongMap;;
int	8;
int	16;
int	32;
long	-1l;
Asciz	zero;
Asciz	(JJ)Z;
NameAndType	zero:(JJ)Z
Method	scala/collection/immutable/LongMapUtils$.zero:(JJ)Z
Asciz	p1;
Asciz	t1;
Asciz	p2;
Asciz	t2;
Asciz	i1;
Asciz	p;
Asciz	m;
Asciz	<T:Ljava/lang/Object;>(JLscala/collection/immutable/LongMap<TT;>;JLscala/collection/immutable/LongMap<TT;>;)Lscala/collection/immutable/LongMap<TT;>;;
Asciz	highestOneBit;
Asciz	(J)J;
Asciz	j;
Asciz	i;
Asciz	branchMask;
Asciz	(JJ)J;
NameAndType	highestOneBit:(J)J
Method	scala/collection/immutable/LongMapUtils$.highestOneBit:(J)J
Asciz	complement;
Asciz	shorter;
Asciz	unsignedCompare;
NameAndType	unsignedCompare:(JJ)Z
Method	scala/collection/immutable/LongMapUtils$.unsignedCompare:(JJ)Z
Asciz	m1;
Asciz	m2;
Asciz	hasMatch;
Asciz	(JJJ)Z;
Asciz	key;
NameAndType	complement:(J)J
Method	scala/collection/immutable/LongMapUtils$.complement:(J)J
Asciz	InnerClasses;
Asciz	scala/collection/immutable/LongMap;
class	scala/collection/immutable/LongMap
Asciz	Bin;
Asciz	scala/ScalaObject;
class	scala/ScalaObject

{
public static final scala.collection.immutable.LongMapUtils$ MODULE$;
  Signature: Lscala/collection/immutable/LongMapUtils$;

public static {};
  Signature: ()V
  Code:
   Stack=1, Locals=0, Args_size=0
	new	class scala/collection/immutable/LongMapUtils$
	invokespecial	Method "<init>":()V
	return
  Labels:

private scala.collection.immutable.LongMapUtils$();
  Signature: ()V
  Code:
   Stack=1, Locals=1, Args_size=1
	aload_0
	invokespecial	Method java/lang/Object."<init>":()V
	aload_0
	putstatic	Field MODULE$:Lscala/collection/immutable/LongMapUtils$;
	return
  Labels:

public scala.collection.immutable.LongMap bin(long, long, scala.collection.immutable.LongMap, scala.collection.immutable.LongMap);
  Signature: (JJLscala/collection/immutable/LongMap;Lscala/collection/immutable/LongMap;)Lscala/collection/immutable/LongMap;
  Code:
   Stack=8, Locals=7, Args_size=5
	getstatic	Field scala/collection/immutable/LongMap$Nil$.MODULE$:Lscala/collection/immutable/LongMap$Nil$;
	dup
	ifnonnull	l1 // aload
	pop
	aload	6
	ifnull	l2 // aload
	goto	l3 // getstatic
l1	aload	6
	invokevirtual	Method java/lang/Object.equals:(Ljava/lang/Object;)Z
	ifeq	l3 // getstatic
l2	aload	5
	goto	l4 // areturn
l3	getstatic	Field scala/collection/immutable/LongMap$Nil$.MODULE$:Lscala/collection/immutable/LongMap$Nil$;
	dup
	ifnonnull	l5 // aload
	pop
	aload	5
	ifnull	l6 // aload
	goto	l7 // new
l5	aload	5
	invokevirtual	Method java/lang/Object.equals:(Ljava/lang/Object;)Z
	ifeq	l7 // new
l6	aload	6
	goto	l4 // areturn
l7	new	class scala/collection/immutable/LongMap$Bin
	dup
	lload_1
	lload_3
	aload	5
	aload	6
	invokespecial	Method scala/collection/immutable/LongMap$Bin."<init>":(JJLscala/collection/immutable/LongMap;Lscala/collection/immutable/LongMap;)V
l4	areturn
  Labels:
   	l1 = 16 // aload
   	l2 = 24 // aload
   	l3 = 29 // getstatic
   	l5 = 45 // aload
   	l6 = 53 // aload
   	l7 = 58 // new
   	l4 = 71 // areturn
  LocalVariableTable: 
   Start  Length  Slot  Name   Signature
   0      72      0    this       Lscala/collection/immutable/LongMapUtils$;
   0      72      1    prefix       J
   0      72      3    mask       J
   0      72      5    left       Lscala/collection/immutable/LongMap;
   0      72      6    right       Lscala/collection/immutable/LongMap;

  Signature: length = 0x2
   00 2C 

public scala.collection.immutable.LongMap join(long, scala.collection.immutable.LongMap, long, scala.collection.immutable.LongMap);
  Signature: (JLscala/collection/immutable/LongMap;JLscala/collection/immutable/LongMap;)Lscala/collection/immutable/LongMap;
  Code:
   Stack=8, Locals=17, Args_size=5
	lload_1
	lload	4
	lxor
	lstore	7
	lload	7
	lload	7
	iconst_1
	lshr
	lor
	lstore	9
	lload	9
	lload	9
	iconst_2
	lshr
	lor
	lstore	9
	lload	9
	lload	9
	iconst_4
	lshr
	lor
	lstore	9
	lload	9
	lload	9
	ldc	int 8
	lshr
	lor
	lstore	9
	lload	9
	lload	9
	ldc	int 16
	lshr
	lor
	lstore	9
	lload	9
	lload	9
	ldc	int 32
	lshr
	lor
	lstore	9
	lload	9
	lload	9
	iconst_1
	lushr
	lsub
	lstore	15
	lload_1
	lload	15
	lconst_1
	lsub
	lstore	11
	ldc2_w	long -1l
	lload	11
	lxor
	lload	15
	lxor
	land
	lstore	13
	aload_0
	lload_1
	lload	15
	invokevirtual	Method zero:(JJ)Z
	ifeq	l1 // new
	new	class scala/collection/immutable/LongMap$Bin
	dup
	lload	13
	lload	15
	aload_3
	aload	6
	invokespecial	Method scala/collection/immutable/LongMap$Bin."<init>":(JJLscala/collection/immutable/LongMap;Lscala/collection/immutable/LongMap;)V
	goto	l2 // areturn
l1	new	class scala/collection/immutable/LongMap$Bin
	dup
	lload	13
	lload	15
	aload	6
	aload_3
	invokespecial	Method scala/collection/immutable/LongMap$Bin."<init>":(JJLscala/collection/immutable/LongMap;Lscala/collection/immutable/LongMap;)V
l2	areturn
  Labels:
   	l1 = 118 // new
   	l2 = 132 // areturn
  LocalVariableTable: 
   Start  Length  Slot  Name   Signature
   0      133      0    this       Lscala/collection/immutable/LongMapUtils$;
   0      133      1    p1       J
   0      133      3    t1       Lscala/collection/immutable/LongMap;
   0      133      4    p2       J
   0      133      6    t2       Lscala/collection/immutable/LongMap;
   6      64      9    i1       J
   91      42      13    p       J
   72      61      15    m       J

  Signature: length = 0x2
   00 40 

public long highestOneBit(long);
  Signature: (J)J
  Code:
   Stack=5, Locals=5, Args_size=2
	lload_1
	lload_1
	iconst_1
	lshr
	lor
	lstore_3
	lload_3
	lload_3
	iconst_2
	lshr
	lor
	lstore_3
	lload_3
	lload_3
	iconst_4
	lshr
	lor
	lstore_3
	lload_3
	lload_3
	ldc	int 8
	lshr
	lor
	lstore_3
	lload_3
	lload_3
	ldc	int 16
	lshr
	lor
	lstore_3
	lload_3
	lload_3
	ldc	int 32
	lshr
	lor
	lstore_3
	lload_3
	lload_3
	iconst_1
	lushr
	lsub
	lreturn
  Labels:
  LocalVariableTable: 
   Start  Length  Slot  Name   Signature
   0      45      0    this       Lscala/collection/immutable/LongMapUtils$;
   0      45      1    j       J
   0      44      3    i       J


public long branchMask(long, long);
  Signature: (JJ)J
  Code:
   Stack=5, Locals=5, Args_size=3
	aload_0
	lload_1
	lload_3
	lxor
	invokevirtual	Method highestOneBit:(J)J
	lreturn
  Labels:
  LocalVariableTable: 
   Start  Length  Slot  Name   Signature
   0      8      0    this       Lscala/collection/immutable/LongMapUtils$;
   0      8      1    i       J
   0      8      3    j       J


public long complement(long);
  Signature: (J)J
  Code:
   Stack=4, Locals=3, Args_size=2
	ldc2_w	long -1l
	lload_1
	lxor
	lreturn
  Labels:
  LocalVariableTable: 
   Start  Length  Slot  Name   Signature
   0      6      0    this       Lscala/collection/immutable/LongMapUtils$;
   0      6      1    i       J


public boolean shorter(long, long);
  Signature: (JJ)Z
  Code:
   Stack=5, Locals=5, Args_size=3
	aload_0
	lload_3
	lload_1
	invokevirtual	Method unsignedCompare:(JJ)Z
	ireturn
  Labels:
  LocalVariableTable: 
   Start  Length  Slot  Name   Signature
   0      7      0    this       Lscala/collection/immutable/LongMapUtils$;
   0      7      1    m1       J
   0      7      3    m2       J


public boolean unsignedCompare(long, long);
  Signature: (JJ)Z
  Code:
   Stack=5, Locals=5, Args_size=3
	lload_1
	lload_3
	lcmp
	ifge	l1 // iconst_0
	iconst_1
	goto	l2 // lload_1
l1	iconst_0
l2	lload_1
	lconst_0
	lcmp
	ifge	l3 // iconst_0
	iconst_1
	goto	l4 // ixor
l3	iconst_0
l4	ixor
	lload_3
	lconst_0
	lcmp
	ifge	l5 // iconst_0
	iconst_1
	goto	l6 // ixor
l5	iconst_0
l6	ixor
	ireturn
  Labels:
   	l1 = 10 // iconst_0
   	l2 = 11 // lload_1
   	l3 = 21 // iconst_0
   	l4 = 22 // ixor
   	l5 = 33 // iconst_0
   	l6 = 34 // ixor
  LocalVariableTable: 
   Start  Length  Slot  Name   Signature
   0      36      0    this       Lscala/collection/immutable/LongMapUtils$;
   0      36      1    i       J
   0      36      3    j       J


public boolean hasMatch(long, long, long);
  Signature: (JJJ)Z
  Code:
   Stack=6, Locals=9, Args_size=4
	lload_1
	lload	5
	lconst_1
	lsub
	lstore	7
	ldc2_w	long -1l
	lload	7
	lxor
	lload	5
	lxor
	land
	lload_3
	lcmp
	ifne	l1 // iconst_0
	iconst_1
	goto	l2 // ireturn
l1	iconst_0
l2	ireturn
  Labels:
   	l1 = 26 // iconst_0
   	l2 = 27 // ireturn
  LocalVariableTable: 
   Start  Length  Slot  Name   Signature
   0      28      0    this       Lscala/collection/immutable/LongMapUtils$;
   0      28      1    key       J
   0      28      3    prefix       J
   0      28      5    m       J


public long mask(long, long);
  Signature: (JJ)J
  Code:
   Stack=7, Locals=5, Args_size=3
	lload_1
	aload_0
	lload_3
	lconst_1
	lsub
	invokevirtual	Method complement:(J)J
	lload_3
	lxor
	land
	lreturn
  Labels:
  LocalVariableTable: 
   Start  Length  Slot  Name   Signature
   0      12      0    this       Lscala/collection/immutable/LongMapUtils$;
   0      12      1    i       J
   0      12      3    mask       J


public boolean zero(long, long);
  Signature: (JJ)Z
  Code:
   Stack=4, Locals=5, Args_size=3
	lload_1
	lload_3
	land
	lconst_0
	lcmp
	ifne	l1 // iconst_0
	iconst_1
	goto	l2 // ireturn
l1	iconst_0
l2	ireturn
  Labels:
   	l1 = 12 // iconst_0
   	l2 = 13 // ireturn
  LocalVariableTable: 
   Start  Length  Slot  Name   Signature
   0      14      0    this       Lscala/collection/immutable/LongMapUtils$;
   0      14      1    i       J
   0      14      3    mask       J


}

