Compiled from "LongMap.scala"
public final class scala.collection.immutable.LongMap$$anonfun$toList$1 extends java.lang.Object implements scala.Function1,scala.ScalaObject,java.io.Serializable
  SourceFile: "LongMap.scala"
  Scala: length = 0x
   
  InnerClass: 
   public final $anonfun$toList$1=class scala/collection/immutable/LongMap$$anonfun$toList$1 of class scala/collection/immutable/LongMap
  minor version: 0
  major version: 49
  Constant pool:
Asciz	SourceFile;
Asciz	LongMap.scala;
Asciz	<clinit>;
Asciz	()V;
Asciz	Code;
Asciz	serialVersionUID;
Asciz	J;
Asciz	scala/collection/immutable/LongMap$$anonfun$toList$1;
class	scala/collection/immutable/LongMap$$anonfun$toList$1
NameAndType	serialVersionUID:J
Field	scala/collection/immutable/LongMap$$anonfun$toList$1.serialVersionUID:J
Asciz	buffer$1;
Asciz	Lscala/collection/mutable/ListBuffer;;
Asciz	<init>;
Asciz	(Lscala/collection/immutable/LongMap;Lscala/collection/mutable/ListBuffer;)V;
Asciz	LineNumberTable;
NameAndType	buffer$1:Lscala/collection/mutable/ListBuffer;
Field	scala/collection/immutable/LongMap$$anonfun$toList$1.buffer$1:Lscala/collection/mutable/ListBuffer;
Asciz	java/lang/Object;
class	java/lang/Object
NameAndType	"<init>":()V
Method	java/lang/Object."<init>":()V
Asciz	scala/Function1$class;
class	scala/Function1$class
Asciz	$init$;
Asciz	(Lscala/Function1;)V;
NameAndType	$init$:(Lscala/Function1;)V
Method	scala/Function1$class.$init$:(Lscala/Function1;)V
Asciz	this;
Asciz	Lscala/collection/immutable/LongMap$$anonfun$toList$1;;
Asciz	$outer;
Asciz	Lscala/collection/immutable/LongMap;;
Asciz	LocalVariableTable;
Asciz	(Lscala/collection/immutable/LongMap<TT;>;)V;
Asciz	Signature;
Asciz	apply;
Asciz	(Ljava/lang/Object;)Ljava/lang/Object;;
Asciz	scala/Tuple2;
class	scala/Tuple2
Asciz	(Lscala/Tuple2;)Lscala/collection/mutable/ListBuffer;;
NameAndType	apply:(Lscala/Tuple2;)Lscala/collection/mutable/ListBuffer;
Method	scala/collection/immutable/LongMap$$anonfun$toList$1.apply:(Lscala/Tuple2;)Lscala/collection/mutable/ListBuffer;
Asciz	v1;
Asciz	Ljava/lang/Object;;
Asciz	scala/collection/mutable/ListBuffer;
class	scala/collection/mutable/ListBuffer
Asciz	$plus$eq;
Asciz	(Ljava/lang/Object;)Lscala/collection/mutable/ListBuffer;;
NameAndType	$plus$eq:(Ljava/lang/Object;)Lscala/collection/mutable/ListBuffer;
Method	scala/collection/mutable/ListBuffer.$plus$eq:(Ljava/lang/Object;)Lscala/collection/mutable/ListBuffer;
Asciz	(Lscala/Tuple2<Ljava/lang/Long;TT;>;)Lscala/collection/mutable/ListBuffer<Lscala/Tuple2<Ljava/lang/Long;TT;>;>;;
Asciz	andThen;
Asciz	(Lscala/Function1;)Lscala/Function1;;
Asciz	(Lscala/Function1;Lscala/Function1;)Lscala/Function1;;
NameAndType	andThen:(Lscala/Function1;Lscala/Function1;)Lscala/Function1;
Method	scala/Function1$class.andThen:(Lscala/Function1;Lscala/Function1;)Lscala/Function1;
Asciz	g;
Asciz	Lscala/Function1;;
Asciz	compose;
NameAndType	compose:(Lscala/Function1;Lscala/Function1;)Lscala/Function1;
Method	scala/Function1$class.compose:(Lscala/Function1;Lscala/Function1;)Lscala/Function1;
Asciz	toString;
Asciz	()Ljava/lang/String;;
Asciz	(Lscala/Function1;)Ljava/lang/String;;
NameAndType	toString:(Lscala/Function1;)Ljava/lang/String;
Method	scala/Function1$class.toString:(Lscala/Function1;)Ljava/lang/String;
Asciz	Scala;
Asciz	InnerClasses;
Asciz	scala/collection/immutable/LongMap;
class	scala/collection/immutable/LongMap
Asciz	$anonfun$toList$1;
Asciz	scala/Function1;
class	scala/Function1
Asciz	scala/ScalaObject;
class	scala/ScalaObject
Asciz	java/io/Serializable;
class	java/io/Serializable

{
public static final long serialVersionUID;
  Signature: J

private final scala.collection.mutable.ListBuffer buffer$1;
  Signature: Lscala/collection/mutable/ListBuffer;

public static {};
  Signature: ()V
  Code:
   Stack=2, Locals=0, Args_size=0
	lconst_0
	putstatic	Field serialVersionUID:J
	return
  Labels:

public scala.collection.immutable.LongMap$$anonfun$toList$1(scala.collection.immutable.LongMap, scala.collection.mutable.ListBuffer);
  Signature: (Lscala/collection/immutable/LongMap;Lscala/collection/mutable/ListBuffer;)V
  Code:
   Stack=2, Locals=3, Args_size=3
	aload_0
	aload_2
	putfield	Field buffer$1:Lscala/collection/mutable/ListBuffer;
	aload_0
	invokespecial	Method java/lang/Object."<init>":()V
	aload_0
	invokestatic	Method scala/Function1$class.$init$:(Lscala/Function1;)V
	return
  Labels:
  LocalVariableTable: 
   Start  Length  Slot  Name   Signature
   0      14      0    this       Lscala/collection/immutable/LongMap$$anonfun$toList$1;
   0      14      1    $outer       Lscala/collection/immutable/LongMap;

  Signature: length = 0x2
   00 22 

public final java.lang.Object apply(java.lang.Object);
  Signature: (Ljava/lang/Object;)Ljava/lang/Object;
  Code:
   Stack=2, Locals=2, Args_size=2
	aload_0
	aload_1
	checkcast	class scala/Tuple2
	invokevirtual	Method apply:(Lscala/Tuple2;)Lscala/collection/mutable/ListBuffer;
	areturn
  Labels:
  LocalVariableTable: 
   Start  Length  Slot  Name   Signature
   0      9      0    this       Lscala/collection/immutable/LongMap$$anonfun$toList$1;
   0      9      1    v1       Ljava/lang/Object;


public final scala.collection.mutable.ListBuffer apply(scala.Tuple2);
  Signature: (Lscala/Tuple2;)Lscala/collection/mutable/ListBuffer;
  Code:
   Stack=2, Locals=2, Args_size=2
	aload_0
	getfield	Field buffer$1:Lscala/collection/mutable/ListBuffer;
	aload_1
	invokevirtual	Method scala/collection/mutable/ListBuffer.$plus$eq:(Ljava/lang/Object;)Lscala/collection/mutable/ListBuffer;
	areturn
  Labels:
  Signature: length = 0x2
   00 33 

public scala.Function1 andThen(scala.Function1);
  Signature: (Lscala/Function1;)Lscala/Function1;
  Code:
   Stack=2, Locals=2, Args_size=2
	aload_0
	aload_1
	invokestatic	Method scala/Function1$class.andThen:(Lscala/Function1;Lscala/Function1;)Lscala/Function1;
	areturn
  Labels:
  LocalVariableTable: 
   Start  Length  Slot  Name   Signature
   0      6      0    this       Lscala/collection/immutable/LongMap$$anonfun$toList$1;
   0      6      1    g       Lscala/Function1;


public scala.Function1 compose(scala.Function1);
  Signature: (Lscala/Function1;)Lscala/Function1;
  Code:
   Stack=2, Locals=2, Args_size=2
	aload_0
	aload_1
	invokestatic	Method scala/Function1$class.compose:(Lscala/Function1;Lscala/Function1;)Lscala/Function1;
	areturn
  Labels:
  LocalVariableTable: 
   Start  Length  Slot  Name   Signature
   0      6      0    this       Lscala/collection/immutable/LongMap$$anonfun$toList$1;
   0      6      1    g       Lscala/Function1;


public java.lang.String toString();
  Signature: ()Ljava/lang/String;
  Code:
   Stack=1, Locals=1, Args_size=1
	aload_0
	invokestatic	Method scala/Function1$class.toString:(Lscala/Function1;)Ljava/lang/String;
	areturn
  Labels:

}

