Compiled from "LongMap.scala"
public class scala.collection.immutable.LongMapKeyIterator extends scala.collection.immutable.LongMapIterator implements scala.ScalaObject
  SourceFile: "LongMap.scala"
  Signature: length = 0x2
   00 28 
  ScalaSig: length = 0x14D
   05 00 37 06 05 01 02 00 02 08 02 12 4C 6F 6E 67
   4D 61 70 4B 65 79 49 74 65 72 61 74 6F 72 0A 02
   03 04 01 09 69 6D 6D 75 74 61 62 6C 65 0A 02 05
   06 01 0A 63 6F 6C 6C 65 63 74 69 6F 6E 0A 01 07
   01 05 73 63 61 6C 61 15 02 09 10 13 03 00 0A 1E
   10 04 0B 0C 0E 1B 0D 01 02 09 02 0D 02 02 0F 4C
   6F 6E 67 4D 61 70 49 74 65 72 61 74 6F 72 10 02
   0F 10 0C 00 04 08 11 00 FFFFFF84 FFFFFF80 FFFFFF80 FFFFFFC2 00 13 02 01
   56 03 00 11 02 14 18 10 02 15 16 0D 01 06 09 02
   17 06 02 07 4E 6F 74 68 69 6E 67 10 02 15 19 09
   02 1A 06 02 03 41 6E 79 10 02 15 1C 09 02 1D 06
   02 04 4C 6F 6E 67 10 02 15 1F 09 02 20 06 02 0B
   53 63 61 6C 61 4F 62 6A 65 63 74 08 08 22 00 FFFFFF82
   FFFFFF80 FFFFFFA0 FFFFFF80 04 23 01 02 69 74 10 03 0B 24 0E 09 02
   25 02 02 07 4C 6F 6E 67 4D 61 70 08 05 27 00 FFFFFF84
   00 28 01 06 3C 69 6E 69 74 3E 14 02 29 2A 10 03
   0B 00 0E 08 05 22 26 FFFFFFC0 00 23 08 05 2C 00 FFFFFF84 00
   2D 01 07 76 61 6C 75 65 4F 66 14 02 1B 2E 08 05
   2F 2B FFFFFFC0 00 30 01 03 74 69 70 10 03 31 34 0E 0E
   02 0B 32 09 02 33 02 01 07 4C 6F 6E 67 4D 61 70
   09 02 35 36 02 03 54 69 70 0A 02 33 02 
  InnerClass: 
   public Tip=class scala/collection/immutable/LongMap$Tip of class scala/collection/immutable/LongMap
  minor version: 0
  major version: 49
  Constant pool:
Asciz	SourceFile;
Asciz	LongMap.scala;
Asciz	valueOf;
Asciz	(Lscala/collection/immutable/LongMap$Tip;)J;
Asciz	Code;
Asciz	LineNumberTable;
Asciz	scala/collection/immutable/LongMap$Tip;
class	scala/collection/immutable/LongMap$Tip
Asciz	key;
Asciz	()J;
NameAndType	key:()J
Method	scala/collection/immutable/LongMap$Tip.key:()J
Asciz	this;
Asciz	Lscala/collection/immutable/LongMapKeyIterator;;
Asciz	tip;
Asciz	Lscala/collection/immutable/LongMap$Tip;;
Asciz	LocalVariableTable;
Asciz	(Lscala/collection/immutable/LongMap$Tip<TV;>;)J;
Asciz	Signature;
Asciz	(Lscala/collection/immutable/LongMap$Tip;)Ljava/lang/Object;;
Asciz	scala/collection/immutable/LongMapKeyIterator;
class	scala/collection/immutable/LongMapKeyIterator
NameAndType	valueOf:(Lscala/collection/immutable/LongMap$Tip;)J
Method	scala/collection/immutable/LongMapKeyIterator.valueOf:(Lscala/collection/immutable/LongMap$Tip;)J
Asciz	scala/runtime/BoxesRunTime;
class	scala/runtime/BoxesRunTime
Asciz	boxToLong;
Asciz	(J)Ljava/lang/Long;;
NameAndType	boxToLong:(J)Ljava/lang/Long;
Method	scala/runtime/BoxesRunTime.boxToLong:(J)Ljava/lang/Long;
Asciz	<init>;
Asciz	(Lscala/collection/immutable/LongMap;)V;
Asciz	scala/collection/immutable/LongMapIterator;
class	scala/collection/immutable/LongMapIterator
NameAndType	"<init>":(Lscala/collection/immutable/LongMap;)V
Method	scala/collection/immutable/LongMapIterator."<init>":(Lscala/collection/immutable/LongMap;)V
Asciz	it;
Asciz	Lscala/collection/immutable/LongMap;;
Asciz	(Lscala/collection/immutable/LongMap<TV;>;)V;
Asciz	<V:Ljava/lang/Object;>Lscala/collection/immutable/LongMapIterator<TV;Ljava/lang/Long;>;Lscala/ScalaObject;;
Asciz	ScalaSig;
Asciz	InnerClasses;
Asciz	scala/collection/immutable/LongMap;
class	scala/collection/immutable/LongMap
Asciz	Tip;
Asciz	scala/ScalaObject;
class	scala/ScalaObject

{
public long valueOf(scala.collection.immutable.LongMap$Tip);
  Signature: (Lscala/collection/immutable/LongMap$Tip;)J
  Code:
   Stack=2, Locals=2, Args_size=2
	aload_1
	invokevirtual	Method scala/collection/immutable/LongMap$Tip.key:()J
	lreturn
  Labels:
  LocalVariableTable: 
   Start  Length  Slot  Name   Signature
   0      5      0    this       Lscala/collection/immutable/LongMapKeyIterator;
   0      5      1    tip       Lscala/collection/immutable/LongMap$Tip;

  Signature: length = 0x2
   00 12 

public java.lang.Object valueOf(scala.collection.immutable.LongMap$Tip);
  Signature: (Lscala/collection/immutable/LongMap$Tip;)Ljava/lang/Object;
  Code:
   Stack=2, Locals=4, Args_size=2
	aload_0
	aload_1
	invokevirtual	Method valueOf:(Lscala/collection/immutable/LongMap$Tip;)J
	lstore_2
	lload_2
	invokestatic	Method scala/runtime/BoxesRunTime.boxToLong:(J)Ljava/lang/Long;
	areturn
  Labels:
  LocalVariableTable: 
   Start  Length  Slot  Name   Signature
   0      11      0    this       Lscala/collection/immutable/LongMapKeyIterator;
   0      11      1    tip       Lscala/collection/immutable/LongMap$Tip;


public scala.collection.immutable.LongMapKeyIterator(scala.collection.immutable.LongMap);
  Signature: (Lscala/collection/immutable/LongMap;)V
  Code:
   Stack=2, Locals=2, Args_size=2
	aload_0
	aload_1
	invokespecial	Method scala/collection/immutable/LongMapIterator."<init>":(Lscala/collection/immutable/LongMap;)V
	return
  Labels:
  LocalVariableTable: 
   Start  Length  Slot  Name   Signature
   0      6      0    this       Lscala/collection/immutable/LongMapKeyIterator;
   0      6      1    it       Lscala/collection/immutable/LongMap;

  Signature: length = 0x2
   00 27 

}

