Compiled from "LongMap.scala"
public final class scala.collection.immutable.LongMap$$anonfun$intersection$1 extends java.lang.Object implements scala.Function3,scala.ScalaObject,java.io.Serializable
  SourceFile: "LongMap.scala"
  Scala: length = 0x
   
  InnerClass: 
   public final $anonfun$intersection$1=class scala/collection/immutable/LongMap$$anonfun$intersection$1 of class scala/collection/immutable/LongMap
  minor version: 0
  major version: 49
  Constant pool:
Asciz	SourceFile;
Asciz	LongMap.scala;
Asciz	<clinit>;
Asciz	()V;
Asciz	Code;
Asciz	serialVersionUID;
Asciz	J;
Asciz	scala/collection/immutable/LongMap$$anonfun$intersection$1;
class	scala/collection/immutable/LongMap$$anonfun$intersection$1
NameAndType	serialVersionUID:J
Field	scala/collection/immutable/LongMap$$anonfun$intersection$1.serialVersionUID:J
Asciz	<init>;
Asciz	(Lscala/collection/immutable/LongMap;)V;
Asciz	LineNumberTable;
Asciz	java/lang/Object;
class	java/lang/Object
NameAndType	"<init>":()V
Method	java/lang/Object."<init>":()V
Asciz	scala/Function3$class;
class	scala/Function3$class
Asciz	$init$;
Asciz	(Lscala/Function3;)V;
NameAndType	$init$:(Lscala/Function3;)V
Method	scala/Function3$class.$init$:(Lscala/Function3;)V
Asciz	this;
Asciz	Lscala/collection/immutable/LongMap$$anonfun$intersection$1;;
Asciz	$outer;
Asciz	Lscala/collection/immutable/LongMap;;
Asciz	LocalVariableTable;
Asciz	(Lscala/collection/immutable/LongMap<TT;>;)V;
Asciz	Signature;
Asciz	apply;
Asciz	(Ljava/lang/Object;Ljava/lang/Object;Ljava/lang/Object;)Ljava/lang/Object;;
Asciz	scala/runtime/BoxesRunTime;
class	scala/runtime/BoxesRunTime
Asciz	unboxToLong;
Asciz	(Ljava/lang/Object;)J;
NameAndType	unboxToLong:(Ljava/lang/Object;)J
Method	scala/runtime/BoxesRunTime.unboxToLong:(Ljava/lang/Object;)J
Asciz	(JLjava/lang/Object;Ljava/lang/Object;)Ljava/lang/Object;;
NameAndType	apply:(JLjava/lang/Object;Ljava/lang/Object;)Ljava/lang/Object;
Method	scala/collection/immutable/LongMap$$anonfun$intersection$1.apply:(JLjava/lang/Object;Ljava/lang/Object;)Ljava/lang/Object;
Asciz	v1;
Asciz	Ljava/lang/Object;;
Asciz	v2;
Asciz	v3;
Asciz	key;
Asciz	value;
Asciz	value2;
Asciz	(JTT;TR;)TT;;
Asciz	curry;
Asciz	()Lscala/Function1;;
Asciz	(Lscala/Function3;)Lscala/Function1;;
NameAndType	curry:(Lscala/Function3;)Lscala/Function1;
Method	scala/Function3$class.curry:(Lscala/Function3;)Lscala/Function1;
Asciz	toString;
Asciz	()Ljava/lang/String;;
Asciz	(Lscala/Function3;)Ljava/lang/String;;
NameAndType	toString:(Lscala/Function3;)Ljava/lang/String;
Method	scala/Function3$class.toString:(Lscala/Function3;)Ljava/lang/String;
Asciz	Scala;
Asciz	InnerClasses;
Asciz	scala/collection/immutable/LongMap;
class	scala/collection/immutable/LongMap
Asciz	$anonfun$intersection$1;
Asciz	scala/Function3;
class	scala/Function3
Asciz	scala/ScalaObject;
class	scala/ScalaObject
Asciz	java/io/Serializable;
class	java/io/Serializable

{
public static final long serialVersionUID;
  Signature: J

public static {};
  Signature: ()V
  Code:
   Stack=2, Locals=0, Args_size=0
	lconst_0
	putstatic	Field serialVersionUID:J
	return
  Labels:

public scala.collection.immutable.LongMap$$anonfun$intersection$1(scala.collection.immutable.LongMap);
  Signature: (Lscala/collection/immutable/LongMap;)V
  Code:
   Stack=1, Locals=2, Args_size=2
	aload_0
	invokespecial	Method java/lang/Object."<init>":()V
	aload_0
	invokestatic	Method scala/Function3$class.$init$:(Lscala/Function3;)V
	return
  Labels:
  LocalVariableTable: 
   Start  Length  Slot  Name   Signature
   0      9      0    this       Lscala/collection/immutable/LongMap$$anonfun$intersection$1;
   0      9      1    $outer       Lscala/collection/immutable/LongMap;

  Signature: length = 0x2
   00 1E 

public final java.lang.Object apply(java.lang.Object, java.lang.Object, java.lang.Object);
  Signature: (Ljava/lang/Object;Ljava/lang/Object;Ljava/lang/Object;)Ljava/lang/Object;
  Code:
   Stack=5, Locals=4, Args_size=4
	aload_0
	aload_1
	invokestatic	Method scala/runtime/BoxesRunTime.unboxToLong:(Ljava/lang/Object;)J
	aload_2
	aload_3
	invokevirtual	Method apply:(JLjava/lang/Object;Ljava/lang/Object;)Ljava/lang/Object;
	areturn
  Labels:
  LocalVariableTable: 
   Start  Length  Slot  Name   Signature
   0      11      0    this       Lscala/collection/immutable/LongMap$$anonfun$intersection$1;
   0      11      1    v1       Ljava/lang/Object;
   0      11      2    v2       Ljava/lang/Object;
   0      11      3    v3       Ljava/lang/Object;


public final java.lang.Object apply(long, java.lang.Object, java.lang.Object);
  Signature: (JLjava/lang/Object;Ljava/lang/Object;)Ljava/lang/Object;
  Code:
   Stack=1, Locals=5, Args_size=4
	aload_3
	areturn
  Labels:
  LocalVariableTable: 
   Start  Length  Slot  Name   Signature
   0      2      0    this       Lscala/collection/immutable/LongMap$$anonfun$intersection$1;
   0      2      1    key       J
   0      2      3    value       Ljava/lang/Object;
   0      2      4    value2       Ljava/lang/Object;

  Signature: length = 0x2
   00 32 

public scala.Function1 curry();
  Signature: ()Lscala/Function1;
  Code:
   Stack=1, Locals=1, Args_size=1
	aload_0
	invokestatic	Method scala/Function3$class.curry:(Lscala/Function3;)Lscala/Function1;
	areturn
  Labels:

public java.lang.String toString();
  Signature: ()Ljava/lang/String;
  Code:
   Stack=1, Locals=1, Args_size=1
	aload_0
	invokestatic	Method scala/Function3$class.toString:(Lscala/Function3;)Ljava/lang/String;
	areturn
  Labels:

}

