Compiled from "Map.scala"
public final class scala.collection.immutable.Map$WithDefault$$anonfun$get$1 extends java.lang.Object implements scala.Function0,scala.ScalaObject,java.io.Serializable
  SourceFile: "Map.scala"
  Scala: length = 0x
   
  InnerClass: 
   public WithDefault=class scala/collection/immutable/Map$WithDefault of class scala/collection/immutable/Map
   public final $anonfun$get$1=class scala/collection/immutable/Map$WithDefault$$anonfun$get$1 of class scala/collection/immutable/Map$WithDefault
  minor version: 0
  major version: 49
  Constant pool:
Asciz	SourceFile;
Asciz	Map.scala;
Asciz	<clinit>;
Asciz	()V;
Asciz	Code;
Asciz	serialVersionUID;
Asciz	J;
Asciz	scala/collection/immutable/Map$WithDefault$$anonfun$get$1;
class	scala/collection/immutable/Map$WithDefault$$anonfun$get$1
NameAndType	serialVersionUID:J
Field	scala/collection/immutable/Map$WithDefault$$anonfun$get$1.serialVersionUID:J
Asciz	key$1;
Asciz	Ljava/lang/Object;;
Asciz	$outer;
Asciz	Lscala/collection/immutable/Map$WithDefault;;
Asciz	<init>;
Asciz	(Lscala/collection/immutable/Map$WithDefault;Ljava/lang/Object;)V;
Asciz	LineNumberTable;
Asciz	java/lang/NullPointerException;
class	java/lang/NullPointerException
NameAndType	"<init>":()V
Method	java/lang/NullPointerException."<init>":()V
NameAndType	$outer:Lscala/collection/immutable/Map$WithDefault;
Field	scala/collection/immutable/Map$WithDefault$$anonfun$get$1.$outer:Lscala/collection/immutable/Map$WithDefault;
NameAndType	key$1:Ljava/lang/Object;
Field	scala/collection/immutable/Map$WithDefault$$anonfun$get$1.key$1:Ljava/lang/Object;
Asciz	java/lang/Object;
class	java/lang/Object
Method	java/lang/Object."<init>":()V
Asciz	scala/Function0$class;
class	scala/Function0$class
Asciz	$init$;
Asciz	(Lscala/Function0;)V;
NameAndType	$init$:(Lscala/Function0;)V
Method	scala/Function0$class.$init$:(Lscala/Function0;)V
Asciz	this;
Asciz	Lscala/collection/immutable/Map$WithDefault$$anonfun$get$1;;
Asciz	LocalVariableTable;
Asciz	(Lscala/collection/immutable/Map$WithDefault<TA;TB;>;)V;
Asciz	Signature;
Asciz	apply;
Asciz	()Ljava/lang/Object;;
Asciz	()Lscala/Some;;
NameAndType	apply:()Lscala/Some;
Method	scala/collection/immutable/Map$WithDefault$$anonfun$get$1.apply:()Lscala/Some;
Asciz	scala/Some;
class	scala/Some
Asciz	scala/collection/immutable/Map$WithDefault;
class	scala/collection/immutable/Map$WithDefault
Asciz	default;
Asciz	(Ljava/lang/Object;)Ljava/lang/Object;;
NameAndType	default:(Ljava/lang/Object;)Ljava/lang/Object;
Method	scala/collection/immutable/Map$WithDefault.default:(Ljava/lang/Object;)Ljava/lang/Object;
Asciz	(Ljava/lang/Object;)V;
NameAndType	"<init>":(Ljava/lang/Object;)V
Method	scala/Some."<init>":(Ljava/lang/Object;)V
Asciz	()Lscala/Some<TB;>;;
Asciz	toString;
Asciz	()Ljava/lang/String;;
Asciz	(Lscala/Function0;)Ljava/lang/String;;
NameAndType	toString:(Lscala/Function0;)Ljava/lang/String;
Method	scala/Function0$class.toString:(Lscala/Function0;)Ljava/lang/String;
Asciz	Scala;
Asciz	InnerClasses;
Asciz	scala/collection/immutable/Map;
class	scala/collection/immutable/Map
Asciz	WithDefault;
Asciz	$anonfun$get$1;
Asciz	scala/Function0;
class	scala/Function0
Asciz	scala/ScalaObject;
class	scala/ScalaObject
Asciz	java/io/Serializable;
class	java/io/Serializable

{
public static final long serialVersionUID;
  Signature: J

private final java.lang.Object key$1;
  Signature: Ljava/lang/Object;

private final scala.collection.immutable.Map$WithDefault $outer;
  Signature: Lscala/collection/immutable/Map$WithDefault;

public static {};
  Signature: ()V
  Code:
   Stack=2, Locals=0, Args_size=0
	lconst_0
	putstatic	Field serialVersionUID:J
	return
  Labels:

public scala.collection.immutable.Map$WithDefault$$anonfun$get$1(scala.collection.immutable.Map$WithDefault, java.lang.Object);
  Signature: (Lscala/collection/immutable/Map$WithDefault;Ljava/lang/Object;)V
  Code:
   Stack=2, Locals=3, Args_size=3
	aload_1
	ifnonnull	l1 // aload_0
	new	class java/lang/NullPointerException
	dup
	invokespecial	Method java/lang/NullPointerException."<init>":()V
	athrow
l1	aload_0
	aload_1
	putfield	Field $outer:Lscala/collection/immutable/Map$WithDefault;
	aload_0
	aload_2
	putfield	Field key$1:Ljava/lang/Object;
	aload_0
	invokespecial	Method java/lang/Object."<init>":()V
	aload_0
	invokestatic	Method scala/Function0$class.$init$:(Lscala/Function0;)V
	return
  Labels:
   	l1 = 12 // aload_0
  LocalVariableTable: 
   Start  Length  Slot  Name   Signature
   0      31      0    this       Lscala/collection/immutable/Map$WithDefault$$anonfun$get$1;
   0      31      1    $outer       Lscala/collection/immutable/Map$WithDefault;

  Signature: length = 0x2
   00 27 

public final java.lang.Object apply();
  Signature: ()Ljava/lang/Object;
  Code:
   Stack=1, Locals=2, Args_size=1
	aload_0
	getfield	Field $outer:Lscala/collection/immutable/Map$WithDefault;
	astore_1
	aload_0
	invokevirtual	Method apply:()Lscala/Some;
	areturn
  Labels:
  LocalVariableTable: 
   Start  Length  Slot  Name   Signature
   0      10      0    this       Lscala/collection/immutable/Map$WithDefault$$anonfun$get$1;


public final scala.Some apply();
  Signature: ()Lscala/Some;
  Code:
   Stack=4, Locals=2, Args_size=1
	aload_0
	getfield	Field $outer:Lscala/collection/immutable/Map$WithDefault;
	astore_1
	new	class scala/Some
	dup
	aload_0
	getfield	Field $outer:Lscala/collection/immutable/Map$WithDefault;
	aload_0
	getfield	Field key$1:Ljava/lang/Object;
	invokevirtual	Method scala/collection/immutable/Map$WithDefault.default:(Ljava/lang/Object;)Ljava/lang/Object;
	invokespecial	Method scala/Some."<init>":(Ljava/lang/Object;)V
	areturn
  Labels:
  LocalVariableTable: 
   Start  Length  Slot  Name   Signature
   0      24      0    this       Lscala/collection/immutable/Map$WithDefault$$anonfun$get$1;

  Signature: length = 0x2
   00 39 

public java.lang.String toString();
  Signature: ()Ljava/lang/String;
  Code:
   Stack=1, Locals=1, Args_size=1
	aload_0
	invokestatic	Method scala/Function0$class.toString:(Lscala/Function0;)Ljava/lang/String;
	areturn
  Labels:

}

