Compiled from "Map.scala"
public class scala.collection.immutable.Map$Map4 extends java.lang.Object implements scala.collection.immutable.Map,scala.ScalaObject,java.io.Serializable
  SourceFile: "Map.scala"
  Signature: length = 0x2
   03 26 
  Scala: length = 0x
   
  InnerClass: 
   public Map3=class scala/collection/immutable/Map$Map3 of class scala/collection/immutable/Map
   public Map4=class scala/collection/immutable/Map$Map4 of class scala/collection/immutable/Map
   public abstract $less$colon$less=class scala/Predef$$less$colon$less of class scala/Predef
   public WithFilter=class scala/collection/TraversableLike$WithFilter of class scala/collection/TraversableLike
  minor version: 0
  major version: 49
  Constant pool:
Asciz	SourceFile;
Asciz	Map.scala;
Asciz	value4;
Asciz	Ljava/lang/Object;;
Asciz	TB;;
Asciz	Signature;
Asciz	key4;
Asciz	TA;;
Asciz	value3;
Asciz	key3;
Asciz	value2;
Asciz	key2;
Asciz	value1;
Asciz	key1;
Asciz	<init>;
Asciz	(Ljava/lang/Object;Ljava/lang/Object;Ljava/lang/Object;Ljava/lang/Object;Ljava/lang/Object;Ljava/lang/Object;Ljava/lang/Object;Ljava/lang/Object;)V;
Asciz	Code;
Asciz	LineNumberTable;
Asciz	scala/collection/immutable/Map$Map4;
class	scala/collection/immutable/Map$Map4
NameAndType	key1:Ljava/lang/Object;
Field	scala/collection/immutable/Map$Map4.key1:Ljava/lang/Object;
NameAndType	value1:Ljava/lang/Object;
Field	scala/collection/immutable/Map$Map4.value1:Ljava/lang/Object;
NameAndType	key2:Ljava/lang/Object;
Field	scala/collection/immutable/Map$Map4.key2:Ljava/lang/Object;
NameAndType	value2:Ljava/lang/Object;
Field	scala/collection/immutable/Map$Map4.value2:Ljava/lang/Object;
NameAndType	key3:Ljava/lang/Object;
Field	scala/collection/immutable/Map$Map4.key3:Ljava/lang/Object;
NameAndType	value3:Ljava/lang/Object;
Field	scala/collection/immutable/Map$Map4.value3:Ljava/lang/Object;
NameAndType	key4:Ljava/lang/Object;
Field	scala/collection/immutable/Map$Map4.key4:Ljava/lang/Object;
NameAndType	value4:Ljava/lang/Object;
Field	scala/collection/immutable/Map$Map4.value4:Ljava/lang/Object;
Asciz	java/lang/Object;
class	java/lang/Object
Asciz	()V;
NameAndType	"<init>":()V
Method	java/lang/Object."<init>":()V
Asciz	scala/collection/TraversableLike$class;
class	scala/collection/TraversableLike$class
Asciz	$init$;
Asciz	(Lscala/collection/TraversableLike;)V;
NameAndType	$init$:(Lscala/collection/TraversableLike;)V
Method	scala/collection/TraversableLike$class.$init$:(Lscala/collection/TraversableLike;)V
Asciz	scala/collection/generic/GenericTraversableTemplate$class;
class	scala/collection/generic/GenericTraversableTemplate$class
Asciz	(Lscala/collection/generic/GenericTraversableTemplate;)V;
NameAndType	$init$:(Lscala/collection/generic/GenericTraversableTemplate;)V
Method	scala/collection/generic/GenericTraversableTemplate$class.$init$:(Lscala/collection/generic/GenericTraversableTemplate;)V
Asciz	scala/collection/Traversable$class;
class	scala/collection/Traversable$class
Asciz	(Lscala/collection/Traversable;)V;
NameAndType	$init$:(Lscala/collection/Traversable;)V
Method	scala/collection/Traversable$class.$init$:(Lscala/collection/Traversable;)V
Asciz	scala/collection/immutable/Traversable$class;
class	scala/collection/immutable/Traversable$class
Asciz	(Lscala/collection/immutable/Traversable;)V;
NameAndType	$init$:(Lscala/collection/immutable/Traversable;)V
Method	scala/collection/immutable/Traversable$class.$init$:(Lscala/collection/immutable/Traversable;)V
Asciz	scala/collection/IterableLike$class;
class	scala/collection/IterableLike$class
Asciz	(Lscala/collection/IterableLike;)V;
NameAndType	$init$:(Lscala/collection/IterableLike;)V
Method	scala/collection/IterableLike$class.$init$:(Lscala/collection/IterableLike;)V
Asciz	scala/collection/Iterable$class;
class	scala/collection/Iterable$class
Asciz	(Lscala/collection/Iterable;)V;
NameAndType	$init$:(Lscala/collection/Iterable;)V
Method	scala/collection/Iterable$class.$init$:(Lscala/collection/Iterable;)V
Asciz	scala/collection/immutable/Iterable$class;
class	scala/collection/immutable/Iterable$class
Asciz	(Lscala/collection/immutable/Iterable;)V;
NameAndType	$init$:(Lscala/collection/immutable/Iterable;)V
Method	scala/collection/immutable/Iterable$class.$init$:(Lscala/collection/immutable/Iterable;)V
Asciz	scala/Function1$class;
class	scala/Function1$class
Asciz	(Lscala/Function1;)V;
NameAndType	$init$:(Lscala/Function1;)V
Method	scala/Function1$class.$init$:(Lscala/Function1;)V
Asciz	scala/PartialFunction$class;
class	scala/PartialFunction$class
Asciz	(Lscala/PartialFunction;)V;
NameAndType	$init$:(Lscala/PartialFunction;)V
Method	scala/PartialFunction$class.$init$:(Lscala/PartialFunction;)V
Asciz	scala/collection/generic/Subtractable$class;
class	scala/collection/generic/Subtractable$class
Asciz	(Lscala/collection/generic/Subtractable;)V;
NameAndType	$init$:(Lscala/collection/generic/Subtractable;)V
Method	scala/collection/generic/Subtractable$class.$init$:(Lscala/collection/generic/Subtractable;)V
Asciz	scala/collection/MapLike$class;
class	scala/collection/MapLike$class
Asciz	(Lscala/collection/MapLike;)V;
NameAndType	$init$:(Lscala/collection/MapLike;)V
Method	scala/collection/MapLike$class.$init$:(Lscala/collection/MapLike;)V
Asciz	scala/collection/Map$class;
class	scala/collection/Map$class
Asciz	(Lscala/collection/Map;)V;
NameAndType	$init$:(Lscala/collection/Map;)V
Method	scala/collection/Map$class.$init$:(Lscala/collection/Map;)V
Asciz	scala/collection/immutable/MapLike$class;
class	scala/collection/immutable/MapLike$class
Asciz	(Lscala/collection/immutable/MapLike;)V;
NameAndType	$init$:(Lscala/collection/immutable/MapLike;)V
Method	scala/collection/immutable/MapLike$class.$init$:(Lscala/collection/immutable/MapLike;)V
Asciz	scala/collection/immutable/Map$class;
class	scala/collection/immutable/Map$class
Asciz	(Lscala/collection/immutable/Map;)V;
NameAndType	$init$:(Lscala/collection/immutable/Map;)V
Method	scala/collection/immutable/Map$class.$init$:(Lscala/collection/immutable/Map;)V
Asciz	this;
Asciz	Lscala/collection/immutable/Map$Map4;;
Asciz	LocalVariableTable;
Asciz	(TA;TB;TA;TB;TA;TB;TA;TB;)V;
Asciz	updated;
Asciz	(Ljava/lang/Object;Ljava/lang/Object;)Lscala/collection/Map;;
Asciz	(Ljava/lang/Object;Ljava/lang/Object;)Lscala/collection/immutable/Map;;
NameAndType	updated:(Ljava/lang/Object;Ljava/lang/Object;)Lscala/collection/immutable/Map;
Method	scala/collection/immutable/Map$Map4.updated:(Ljava/lang/Object;Ljava/lang/Object;)Lscala/collection/immutable/Map;
Asciz	key;
Asciz	value;
Asciz	$plus;
Asciz	(Lscala/Tuple2;)Lscala/collection/Map;;
Asciz	(Lscala/Tuple2;)Lscala/collection/immutable/Map;;
NameAndType	$plus:(Lscala/Tuple2;)Lscala/collection/immutable/Map;
Method	scala/collection/immutable/Map$Map4.$plus:(Lscala/Tuple2;)Lscala/collection/immutable/Map;
Asciz	kv;
Asciz	Lscala/Tuple2;;
Asciz	$minus;
Asciz	(Ljava/lang/Object;)Lscala/collection/Map;;
Asciz	(Ljava/lang/Object;)Lscala/collection/immutable/Map;;
NameAndType	$minus:(Ljava/lang/Object;)Lscala/collection/immutable/Map;
Method	scala/collection/immutable/Map$Map4.$minus:(Ljava/lang/Object;)Lscala/collection/immutable/Map;
Asciz	(Ljava/lang/Object;)Lscala/collection/generic/Subtractable;;
Asciz	elem;
Asciz	empty;
Asciz	()Lscala/collection/Map;;
Asciz	scala/collection/immutable/Map;
class	scala/collection/immutable/Map
Asciz	()Lscala/collection/immutable/Map;;
NameAndType	empty:()Lscala/collection/immutable/Map;
InterfaceMethod	scala/collection/immutable/Map.empty:()Lscala/collection/immutable/Map;
Asciz	(Lscala/Tuple2;Lscala/Tuple2;Lscala/collection/Seq;)Lscala/collection/Map;;
Asciz	scala/collection/immutable/MapLike;
class	scala/collection/immutable/MapLike
Asciz	(Lscala/Tuple2;Lscala/Tuple2;Lscala/collection/Seq;)Lscala/collection/immutable/Map;;
NameAndType	$plus:(Lscala/Tuple2;Lscala/Tuple2;Lscala/collection/Seq;)Lscala/collection/immutable/Map;
InterfaceMethod	scala/collection/immutable/MapLike.$plus:(Lscala/Tuple2;Lscala/Tuple2;Lscala/collection/Seq;)Lscala/collection/immutable/Map;
Asciz	kv1;
Asciz	kv2;
Asciz	kvs;
Asciz	Lscala/collection/Seq;;
Asciz	$plus$plus;
Asciz	(Lscala/collection/Traversable;)Lscala/collection/Map;;
Asciz	(Lscala/collection/Traversable;)Lscala/collection/immutable/Map;;
NameAndType	$plus$plus:(Lscala/collection/Traversable;)Lscala/collection/immutable/Map;
InterfaceMethod	scala/collection/immutable/MapLike.$plus$plus:(Lscala/collection/Traversable;)Lscala/collection/immutable/Map;
Asciz	Lscala/collection/Traversable;;
Asciz	(Lscala/collection/Iterator;)Lscala/collection/Map;;
Asciz	(Lscala/collection/Iterator;)Lscala/collection/immutable/Map;;
NameAndType	$plus$plus:(Lscala/collection/Iterator;)Lscala/collection/immutable/Map;
InterfaceMethod	scala/collection/immutable/MapLike.$plus$plus:(Lscala/collection/Iterator;)Lscala/collection/immutable/Map;
Asciz	iter;
Asciz	Lscala/collection/Iterator;;
Asciz	filterNot;
Asciz	(Lscala/Function1;)Ljava/lang/Object;;
Asciz	(Lscala/Function1;)Lscala/collection/immutable/Map;;
NameAndType	filterNot:(Lscala/Function1;)Lscala/collection/immutable/Map;
InterfaceMethod	scala/collection/immutable/MapLike.filterNot:(Lscala/Function1;)Lscala/collection/immutable/Map;
Asciz	p;
Asciz	Lscala/Function1;;
Asciz	andThen;
Asciz	(Lscala/Function1;)Lscala/Function1;;
Asciz	scala/PartialFunction;
class	scala/PartialFunction
Asciz	(Lscala/Function1;)Lscala/PartialFunction;;
NameAndType	andThen:(Lscala/Function1;)Lscala/PartialFunction;
InterfaceMethod	scala/PartialFunction.andThen:(Lscala/Function1;)Lscala/PartialFunction;
Asciz	g;
Asciz	thisCollection;
Asciz	()Lscala/collection/Traversable;;
Asciz	scala/collection/IterableLike;
class	scala/collection/IterableLike
Asciz	()Lscala/collection/Iterable;;
NameAndType	thisCollection:()Lscala/collection/Iterable;
InterfaceMethod	scala/collection/IterableLike.thisCollection:()Lscala/collection/Iterable;
Asciz	toCollection;
Asciz	(Ljava/lang/Object;)Lscala/collection/Traversable;;
Asciz	(Ljava/lang/Object;)Lscala/collection/Iterable;;
NameAndType	toCollection:(Ljava/lang/Object;)Lscala/collection/Iterable;
InterfaceMethod	scala/collection/IterableLike.toCollection:(Ljava/lang/Object;)Lscala/collection/Iterable;
Asciz	repr;
Asciz	view;
Asciz	()Lscala/collection/TraversableView;;
Asciz	()Lscala/collection/IterableView;;
NameAndType	view:()Lscala/collection/IterableView;
InterfaceMethod	scala/collection/IterableLike.view:()Lscala/collection/IterableView;
Asciz	(II)Lscala/collection/TraversableView;;
Asciz	(II)Lscala/collection/IterableView;;
NameAndType	view:(II)Lscala/collection/IterableView;
InterfaceMethod	scala/collection/IterableLike.view:(II)Lscala/collection/IterableView;
Asciz	from;
Asciz	I;
Asciz	until;
Asciz	()Lscala/collection/generic/Subtractable;;
Asciz	scala/collection/TraversableLike;
class	scala/collection/TraversableLike
Asciz	()Ljava/lang/Object;;
NameAndType	repr:()Ljava/lang/Object;
InterfaceMethod	scala/collection/TraversableLike.repr:()Ljava/lang/Object;
Asciz	scala/collection/generic/Subtractable;
class	scala/collection/generic/Subtractable
Asciz	foreach;
Asciz	scala/Tuple2;
class	scala/Tuple2
Asciz	(Ljava/lang/Object;Ljava/lang/Object;)V;
NameAndType	"<init>":(Ljava/lang/Object;Ljava/lang/Object;)V
Method	scala/Tuple2."<init>":(Ljava/lang/Object;Ljava/lang/Object;)V
Asciz	scala/Function1;
class	scala/Function1
Asciz	apply;
Asciz	(Ljava/lang/Object;)Ljava/lang/Object;;
NameAndType	apply:(Ljava/lang/Object;)Ljava/lang/Object;
InterfaceMethod	scala/Function1.apply:(Ljava/lang/Object;)Ljava/lang/Object;
Asciz	f;
Asciz	<U:Ljava/lang/Object;>(Lscala/Function1<Lscala/Tuple2<TA;TB;>;TU;>;)V;
Asciz	java/lang/Number;
class	java/lang/Number
Asciz	java/lang/Character;
class	java/lang/Character
Asciz	scala/runtime/BoxesRunTime;
class	scala/runtime/BoxesRunTime
Asciz	equals2;
Asciz	(Ljava/lang/Object;Ljava/lang/Object;)Z;
NameAndType	equals2:(Ljava/lang/Object;Ljava/lang/Object;)Z
Method	scala/runtime/BoxesRunTime.equals2:(Ljava/lang/Object;Ljava/lang/Object;)Z
Asciz	equals;
Asciz	(Ljava/lang/Object;)Z;
NameAndType	equals:(Ljava/lang/Object;)Z
Method	java/lang/Object.equals:(Ljava/lang/Object;)Z
Asciz	scala/collection/immutable/Map$Map3;
class	scala/collection/immutable/Map$Map3
Asciz	(Ljava/lang/Object;Ljava/lang/Object;Ljava/lang/Object;Ljava/lang/Object;Ljava/lang/Object;Ljava/lang/Object;)V;
NameAndType	"<init>":(Ljava/lang/Object;Ljava/lang/Object;Ljava/lang/Object;Ljava/lang/Object;Ljava/lang/Object;Ljava/lang/Object;)V
Method	scala/collection/immutable/Map$Map3."<init>":(Ljava/lang/Object;Ljava/lang/Object;Ljava/lang/Object;Ljava/lang/Object;Ljava/lang/Object;Ljava/lang/Object;)V
Asciz	y0;
Asciz	y1;
Asciz	y2;
Asciz	y3;
Asciz	(TA;)Lscala/collection/immutable/Map<TA;TB;>;;
Asciz	_1;
NameAndType	_1:()Ljava/lang/Object;
Method	scala/Tuple2._1:()Ljava/lang/Object;
Asciz	_2;
NameAndType	_2:()Ljava/lang/Object;
Method	scala/Tuple2._2:()Ljava/lang/Object;
Asciz	<B1:Ljava/lang/Object;>(Lscala/Tuple2<TA;TB1;>;)Lscala/collection/immutable/Map<TA;TB1;>;;
NameAndType	"<init>":(Ljava/lang/Object;Ljava/lang/Object;Ljava/lang/Object;Ljava/lang/Object;Ljava/lang/Object;Ljava/lang/Object;Ljava/lang/Object;Ljava/lang/Object;)V
Method	scala/collection/immutable/Map$Map4."<init>":(Ljava/lang/Object;Ljava/lang/Object;Ljava/lang/Object;Ljava/lang/Object;Ljava/lang/Object;Ljava/lang/Object;Ljava/lang/Object;Ljava/lang/Object;)V
Asciz	scala/collection/immutable/HashMap;
class	scala/collection/immutable/HashMap
Method	scala/collection/immutable/HashMap."<init>":()V
Asciz	scala/Predef$;
class	scala/Predef$
Asciz	MODULE$;
Asciz	Lscala/Predef$;;
NameAndType	MODULE$:Lscala/Predef$;
Field	scala/Predef$.MODULE$:Lscala/Predef$;
Asciz	[Ljava/lang/Object;;
class	"[Ljava/lang/Object;"
Asciz	wrapRefArray;
Asciz	([Ljava/lang/Object;)Lscala/collection/mutable/WrappedArray;;
NameAndType	wrapRefArray:([Ljava/lang/Object;)Lscala/collection/mutable/WrappedArray;
Method	scala/Predef$.wrapRefArray:([Ljava/lang/Object;)Lscala/collection/mutable/WrappedArray;
Asciz	(Lscala/Tuple2;Lscala/Tuple2;Lscala/collection/Seq;)Lscala/collection/immutable/HashMap;;
NameAndType	$plus:(Lscala/Tuple2;Lscala/Tuple2;Lscala/collection/Seq;)Lscala/collection/immutable/HashMap;
Method	scala/collection/immutable/HashMap.$plus:(Lscala/Tuple2;Lscala/Tuple2;Lscala/collection/Seq;)Lscala/collection/immutable/HashMap;
Asciz	<B1:Ljava/lang/Object;>(TA;TB1;)Lscala/collection/immutable/Map<TA;TB1;>;;
Asciz	iterator;
Asciz	()Lscala/collection/Iterator;;
Asciz	scala/collection/Iterator$;
class	scala/collection/Iterator$
Asciz	Lscala/collection/Iterator$;;
NameAndType	MODULE$:Lscala/collection/Iterator$;
Field	scala/collection/Iterator$.MODULE$:Lscala/collection/Iterator$;
Asciz	(Lscala/collection/Seq;)Lscala/collection/Iterator;;
NameAndType	apply:(Lscala/collection/Seq;)Lscala/collection/Iterator;
Method	scala/collection/Iterator$.apply:(Lscala/collection/Seq;)Lscala/collection/Iterator;
Asciz	()Lscala/collection/Iterator<Lscala/Tuple2<TA;TB;>;>;;
Asciz	get;
Asciz	(Ljava/lang/Object;)Lscala/Option;;
Asciz	scala/Some;
class	scala/Some
Asciz	(Ljava/lang/Object;)V;
NameAndType	"<init>":(Ljava/lang/Object;)V
Method	scala/Some."<init>":(Ljava/lang/Object;)V
Asciz	scala/None$;
class	scala/None$
Asciz	Lscala/None$;;
NameAndType	MODULE$:Lscala/None$;
Field	scala/None$.MODULE$:Lscala/None$;
Asciz	(TA;)Lscala/Option<TB;>;;
Asciz	size;
Asciz	()I;
Asciz	withFilter;
Asciz	(Lscala/Function1;)Lscala/collection/TraversableLike$WithFilter;;
Asciz	(Lscala/collection/TraversableLike;Lscala/Function1;)Lscala/collection/TraversableLike$WithFilter;;
NameAndType	withFilter:(Lscala/collection/TraversableLike;Lscala/Function1;)Lscala/collection/TraversableLike$WithFilter;
Method	scala/collection/TraversableLike$class.withFilter:(Lscala/collection/TraversableLike;Lscala/Function1;)Lscala/collection/TraversableLike$WithFilter;
Asciz	addString;
Asciz	(Lscala/collection/mutable/StringBuilder;)Lscala/collection/mutable/StringBuilder;;
Asciz	(Lscala/collection/TraversableLike;Lscala/collection/mutable/StringBuilder;)Lscala/collection/mutable/StringBuilder;;
NameAndType	addString:(Lscala/collection/TraversableLike;Lscala/collection/mutable/StringBuilder;)Lscala/collection/mutable/StringBuilder;
Method	scala/collection/TraversableLike$class.addString:(Lscala/collection/TraversableLike;Lscala/collection/mutable/StringBuilder;)Lscala/collection/mutable/StringBuilder;
Asciz	b;
Asciz	Lscala/collection/mutable/StringBuilder;;
Asciz	(Lscala/collection/mutable/StringBuilder;Ljava/lang/String;)Lscala/collection/mutable/StringBuilder;;
Asciz	(Lscala/collection/TraversableLike;Lscala/collection/mutable/StringBuilder;Ljava/lang/String;)Lscala/collection/mutable/StringBuilder;;
NameAndType	addString:(Lscala/collection/TraversableLike;Lscala/collection/mutable/StringBuilder;Ljava/lang/String;)Lscala/collection/mutable/StringBuilder;
Method	scala/collection/TraversableLike$class.addString:(Lscala/collection/TraversableLike;Lscala/collection/mutable/StringBuilder;Ljava/lang/String;)Lscala/collection/mutable/StringBuilder;
Asciz	sep;
Asciz	Ljava/lang/String;;
Asciz	mkString;
Asciz	()Ljava/lang/String;;
Asciz	(Lscala/collection/TraversableLike;)Ljava/lang/String;;
NameAndType	mkString:(Lscala/collection/TraversableLike;)Ljava/lang/String;
Method	scala/collection/TraversableLike$class.mkString:(Lscala/collection/TraversableLike;)Ljava/lang/String;
Asciz	(Ljava/lang/String;)Ljava/lang/String;;
Asciz	(Lscala/collection/TraversableLike;Ljava/lang/String;)Ljava/lang/String;;
NameAndType	mkString:(Lscala/collection/TraversableLike;Ljava/lang/String;)Ljava/lang/String;
Method	scala/collection/TraversableLike$class.mkString:(Lscala/collection/TraversableLike;Ljava/lang/String;)Ljava/lang/String;
Asciz	(Ljava/lang/String;Ljava/lang/String;Ljava/lang/String;)Ljava/lang/String;;
Asciz	(Lscala/collection/TraversableLike;Ljava/lang/String;Ljava/lang/String;Ljava/lang/String;)Ljava/lang/String;;
NameAndType	mkString:(Lscala/collection/TraversableLike;Ljava/lang/String;Ljava/lang/String;Ljava/lang/String;)Ljava/lang/String;
Method	scala/collection/TraversableLike$class.mkString:(Lscala/collection/TraversableLike;Ljava/lang/String;Ljava/lang/String;Ljava/lang/String;)Ljava/lang/String;
Asciz	start;
Asciz	end;
Asciz	toMap;
Asciz	(Lscala/Predef$$less$colon$less;)Lscala/collection/immutable/Map;;
Asciz	(Lscala/collection/TraversableLike;Lscala/Predef$$less$colon$less;)Lscala/collection/immutable/Map;;
NameAndType	toMap:(Lscala/collection/TraversableLike;Lscala/Predef$$less$colon$less;)Lscala/collection/immutable/Map;
Method	scala/collection/TraversableLike$class.toMap:(Lscala/collection/TraversableLike;Lscala/Predef$$less$colon$less;)Lscala/collection/immutable/Map;
Asciz	ev;
Asciz	Lscala/Predef$$less$colon$less;;
Asciz	toSet;
Asciz	()Lscala/collection/immutable/Set;;
Asciz	(Lscala/collection/TraversableLike;)Lscala/collection/immutable/Set;;
NameAndType	toSet:(Lscala/collection/TraversableLike;)Lscala/collection/immutable/Set;
Method	scala/collection/TraversableLike$class.toSet:(Lscala/collection/TraversableLike;)Lscala/collection/immutable/Set;
Asciz	toIndexedSeq;
Asciz	()Lscala/collection/mutable/IndexedSeq;;
Asciz	(Lscala/collection/TraversableLike;)Lscala/collection/mutable/IndexedSeq;;
NameAndType	toIndexedSeq:(Lscala/collection/TraversableLike;)Lscala/collection/mutable/IndexedSeq;
Method	scala/collection/TraversableLike$class.toIndexedSeq:(Lscala/collection/TraversableLike;)Lscala/collection/mutable/IndexedSeq;
Asciz	toSeq;
Asciz	()Lscala/collection/Seq;;
Asciz	(Lscala/collection/TraversableLike;)Lscala/collection/Seq;;
NameAndType	toSeq:(Lscala/collection/TraversableLike;)Lscala/collection/Seq;
Method	scala/collection/TraversableLike$class.toSeq:(Lscala/collection/TraversableLike;)Lscala/collection/Seq;
Asciz	toList;
Asciz	()Lscala/collection/immutable/List;;
Asciz	(Lscala/collection/TraversableLike;)Lscala/collection/immutable/List;;
NameAndType	toList:(Lscala/collection/TraversableLike;)Lscala/collection/immutable/List;
Method	scala/collection/TraversableLike$class.toList:(Lscala/collection/TraversableLike;)Lscala/collection/immutable/List;
Asciz	toArray;
Asciz	(Lscala/reflect/ClassManifest;)Ljava/lang/Object;;
Asciz	(Lscala/collection/TraversableLike;Lscala/reflect/ClassManifest;)Ljava/lang/Object;;
NameAndType	toArray:(Lscala/collection/TraversableLike;Lscala/reflect/ClassManifest;)Ljava/lang/Object;
Method	scala/collection/TraversableLike$class.toArray:(Lscala/collection/TraversableLike;Lscala/reflect/ClassManifest;)Ljava/lang/Object;
Asciz	evidence$1;
Asciz	Lscala/reflect/ClassManifest;;
Asciz	copyToArray;
Asciz	(Lscala/collection/TraversableLike;Ljava/lang/Object;)V;
NameAndType	copyToArray:(Lscala/collection/TraversableLike;Ljava/lang/Object;)V
Method	scala/collection/TraversableLike$class.copyToArray:(Lscala/collection/TraversableLike;Ljava/lang/Object;)V
Asciz	xs;
Asciz	(Ljava/lang/Object;I)V;
Asciz	(Lscala/collection/TraversableLike;Ljava/lang/Object;I)V;
NameAndType	copyToArray:(Lscala/collection/TraversableLike;Ljava/lang/Object;I)V
Method	scala/collection/TraversableLike$class.copyToArray:(Lscala/collection/TraversableLike;Ljava/lang/Object;I)V
Asciz	copyToBuffer;
Asciz	(Lscala/collection/mutable/Buffer;)V;
Asciz	(Lscala/collection/TraversableLike;Lscala/collection/mutable/Buffer;)V;
NameAndType	copyToBuffer:(Lscala/collection/TraversableLike;Lscala/collection/mutable/Buffer;)V
Method	scala/collection/TraversableLike$class.copyToBuffer:(Lscala/collection/TraversableLike;Lscala/collection/mutable/Buffer;)V
Asciz	dest;
Asciz	Lscala/collection/mutable/Buffer;;
Asciz	splitAt;
Asciz	(I)Lscala/Tuple2;;
Asciz	(Lscala/collection/TraversableLike;I)Lscala/Tuple2;;
NameAndType	splitAt:(Lscala/collection/TraversableLike;I)Lscala/Tuple2;
Method	scala/collection/TraversableLike$class.splitAt:(Lscala/collection/TraversableLike;I)Lscala/Tuple2;
Asciz	n;
Asciz	span;
Asciz	(Lscala/Function1;)Lscala/Tuple2;;
Asciz	(Lscala/collection/TraversableLike;Lscala/Function1;)Lscala/Tuple2;;
NameAndType	span:(Lscala/collection/TraversableLike;Lscala/Function1;)Lscala/Tuple2;
Method	scala/collection/TraversableLike$class.span:(Lscala/collection/TraversableLike;Lscala/Function1;)Lscala/Tuple2;
Asciz	dropWhile;
Asciz	(Lscala/collection/TraversableLike;Lscala/Function1;)Ljava/lang/Object;;
NameAndType	dropWhile:(Lscala/collection/TraversableLike;Lscala/Function1;)Ljava/lang/Object;
Method	scala/collection/TraversableLike$class.dropWhile:(Lscala/collection/TraversableLike;Lscala/Function1;)Ljava/lang/Object;
Asciz	drop;
Asciz	(I)Ljava/lang/Object;;
Asciz	(Lscala/collection/TraversableLike;I)Ljava/lang/Object;;
NameAndType	drop:(Lscala/collection/TraversableLike;I)Ljava/lang/Object;
Method	scala/collection/TraversableLike$class.drop:(Lscala/collection/TraversableLike;I)Ljava/lang/Object;
Asciz	init;
Asciz	(Lscala/collection/TraversableLike;)Ljava/lang/Object;;
NameAndType	init:(Lscala/collection/TraversableLike;)Ljava/lang/Object;
Method	scala/collection/TraversableLike$class.init:(Lscala/collection/TraversableLike;)Ljava/lang/Object;
Asciz	lastOption;
Asciz	()Lscala/Option;;
Asciz	(Lscala/collection/TraversableLike;)Lscala/Option;;
NameAndType	lastOption:(Lscala/collection/TraversableLike;)Lscala/Option;
Method	scala/collection/TraversableLike$class.lastOption:(Lscala/collection/TraversableLike;)Lscala/Option;
Asciz	last;
NameAndType	last:(Lscala/collection/TraversableLike;)Ljava/lang/Object;
Method	scala/collection/TraversableLike$class.last:(Lscala/collection/TraversableLike;)Ljava/lang/Object;
Asciz	tail;
NameAndType	tail:(Lscala/collection/TraversableLike;)Ljava/lang/Object;
Method	scala/collection/TraversableLike$class.tail:(Lscala/collection/TraversableLike;)Ljava/lang/Object;
Asciz	headOption;
NameAndType	headOption:(Lscala/collection/TraversableLike;)Lscala/Option;
Method	scala/collection/TraversableLike$class.headOption:(Lscala/collection/TraversableLike;)Lscala/Option;
Asciz	max;
Asciz	(Lscala/math/Ordering;)Ljava/lang/Object;;
Asciz	(Lscala/collection/TraversableLike;Lscala/math/Ordering;)Ljava/lang/Object;;
NameAndType	max:(Lscala/collection/TraversableLike;Lscala/math/Ordering;)Ljava/lang/Object;
Method	scala/collection/TraversableLike$class.max:(Lscala/collection/TraversableLike;Lscala/math/Ordering;)Ljava/lang/Object;
Asciz	cmp;
Asciz	Lscala/math/Ordering;;
Asciz	min;
NameAndType	min:(Lscala/collection/TraversableLike;Lscala/math/Ordering;)Ljava/lang/Object;
Method	scala/collection/TraversableLike$class.min:(Lscala/collection/TraversableLike;Lscala/math/Ordering;)Ljava/lang/Object;
Asciz	product;
Asciz	(Lscala/math/Numeric;)Ljava/lang/Object;;
Asciz	(Lscala/collection/TraversableLike;Lscala/math/Numeric;)Ljava/lang/Object;;
NameAndType	product:(Lscala/collection/TraversableLike;Lscala/math/Numeric;)Ljava/lang/Object;
Method	scala/collection/TraversableLike$class.product:(Lscala/collection/TraversableLike;Lscala/math/Numeric;)Ljava/lang/Object;
Asciz	num;
Asciz	Lscala/math/Numeric;;
Asciz	sum;
NameAndType	sum:(Lscala/collection/TraversableLike;Lscala/math/Numeric;)Ljava/lang/Object;
Method	scala/collection/TraversableLike$class.sum:(Lscala/collection/TraversableLike;Lscala/math/Numeric;)Ljava/lang/Object;
Asciz	reduceRightOption;
Asciz	(Lscala/Function2;)Lscala/Option;;
Asciz	(Lscala/collection/TraversableLike;Lscala/Function2;)Lscala/Option;;
NameAndType	reduceRightOption:(Lscala/collection/TraversableLike;Lscala/Function2;)Lscala/Option;
Method	scala/collection/TraversableLike$class.reduceRightOption:(Lscala/collection/TraversableLike;Lscala/Function2;)Lscala/Option;
Asciz	op;
Asciz	Lscala/Function2;;
Asciz	reduceLeftOption;
NameAndType	reduceLeftOption:(Lscala/collection/TraversableLike;Lscala/Function2;)Lscala/Option;
Method	scala/collection/TraversableLike$class.reduceLeftOption:(Lscala/collection/TraversableLike;Lscala/Function2;)Lscala/Option;
Asciz	reduceLeft;
Asciz	(Lscala/Function2;)Ljava/lang/Object;;
Asciz	(Lscala/collection/TraversableLike;Lscala/Function2;)Ljava/lang/Object;;
NameAndType	reduceLeft:(Lscala/collection/TraversableLike;Lscala/Function2;)Ljava/lang/Object;
Method	scala/collection/TraversableLike$class.reduceLeft:(Lscala/collection/TraversableLike;Lscala/Function2;)Ljava/lang/Object;
Asciz	$colon$bslash;
Asciz	(Ljava/lang/Object;Lscala/Function2;)Ljava/lang/Object;;
Asciz	(Lscala/collection/TraversableLike;Ljava/lang/Object;Lscala/Function2;)Ljava/lang/Object;;
NameAndType	$colon$bslash:(Lscala/collection/TraversableLike;Ljava/lang/Object;Lscala/Function2;)Ljava/lang/Object;
Method	scala/collection/TraversableLike$class.$colon$bslash:(Lscala/collection/TraversableLike;Ljava/lang/Object;Lscala/Function2;)Ljava/lang/Object;
Asciz	z;
Asciz	$div$colon;
NameAndType	$div$colon:(Lscala/collection/TraversableLike;Ljava/lang/Object;Lscala/Function2;)Ljava/lang/Object;
Method	scala/collection/TraversableLike$class.$div$colon:(Lscala/collection/TraversableLike;Ljava/lang/Object;Lscala/Function2;)Ljava/lang/Object;
Asciz	foldLeft;
NameAndType	foldLeft:(Lscala/collection/TraversableLike;Ljava/lang/Object;Lscala/Function2;)Ljava/lang/Object;
Method	scala/collection/TraversableLike$class.foldLeft:(Lscala/collection/TraversableLike;Ljava/lang/Object;Lscala/Function2;)Ljava/lang/Object;
Asciz	count;
Asciz	(Lscala/Function1;)I;
Asciz	(Lscala/collection/TraversableLike;Lscala/Function1;)I;
NameAndType	count:(Lscala/collection/TraversableLike;Lscala/Function1;)I
Method	scala/collection/TraversableLike$class.count:(Lscala/collection/TraversableLike;Lscala/Function1;)I
Asciz	groupBy;
Asciz	(Lscala/Function1;)Lscala/collection/Map;;
Asciz	(Lscala/collection/TraversableLike;Lscala/Function1;)Lscala/collection/Map;;
NameAndType	groupBy:(Lscala/collection/TraversableLike;Lscala/Function1;)Lscala/collection/Map;
Method	scala/collection/TraversableLike$class.groupBy:(Lscala/collection/TraversableLike;Lscala/Function1;)Lscala/collection/Map;
Asciz	partition;
NameAndType	partition:(Lscala/collection/TraversableLike;Lscala/Function1;)Lscala/Tuple2;
Method	scala/collection/TraversableLike$class.partition:(Lscala/collection/TraversableLike;Lscala/Function1;)Lscala/Tuple2;
Asciz	partialMap;
Asciz	(Lscala/PartialFunction;Lscala/collection/generic/CanBuildFrom;)Ljava/lang/Object;;
Asciz	(Lscala/collection/TraversableLike;Lscala/PartialFunction;Lscala/collection/generic/CanBuildFrom;)Ljava/lang/Object;;
NameAndType	partialMap:(Lscala/collection/TraversableLike;Lscala/PartialFunction;Lscala/collection/generic/CanBuildFrom;)Ljava/lang/Object;
Method	scala/collection/TraversableLike$class.partialMap:(Lscala/collection/TraversableLike;Lscala/PartialFunction;Lscala/collection/generic/CanBuildFrom;)Ljava/lang/Object;
Asciz	pf;
Asciz	Lscala/PartialFunction;;
Asciz	bf;
Asciz	Lscala/collection/generic/CanBuildFrom;;
Asciz	filter;
NameAndType	filter:(Lscala/collection/TraversableLike;Lscala/Function1;)Ljava/lang/Object;
Method	scala/collection/TraversableLike$class.filter:(Lscala/collection/TraversableLike;Lscala/Function1;)Ljava/lang/Object;
Asciz	flatMap;
Asciz	(Lscala/Function1;Lscala/collection/generic/CanBuildFrom;)Ljava/lang/Object;;
Asciz	(Lscala/collection/TraversableLike;Lscala/Function1;Lscala/collection/generic/CanBuildFrom;)Ljava/lang/Object;;
NameAndType	flatMap:(Lscala/collection/TraversableLike;Lscala/Function1;Lscala/collection/generic/CanBuildFrom;)Ljava/lang/Object;
Method	scala/collection/TraversableLike$class.flatMap:(Lscala/collection/TraversableLike;Lscala/Function1;Lscala/collection/generic/CanBuildFrom;)Ljava/lang/Object;
Asciz	map;
NameAndType	map:(Lscala/collection/TraversableLike;Lscala/Function1;Lscala/collection/generic/CanBuildFrom;)Ljava/lang/Object;
Method	scala/collection/TraversableLike$class.map:(Lscala/collection/TraversableLike;Lscala/Function1;Lscala/collection/generic/CanBuildFrom;)Ljava/lang/Object;
Asciz	(Lscala/collection/Iterator;Lscala/collection/generic/CanBuildFrom;)Ljava/lang/Object;;
Asciz	(Lscala/collection/TraversableLike;Lscala/collection/Iterator;Lscala/collection/generic/CanBuildFrom;)Ljava/lang/Object;;
NameAndType	$plus$plus:(Lscala/collection/TraversableLike;Lscala/collection/Iterator;Lscala/collection/generic/CanBuildFrom;)Ljava/lang/Object;
Method	scala/collection/TraversableLike$class.$plus$plus:(Lscala/collection/TraversableLike;Lscala/collection/Iterator;Lscala/collection/generic/CanBuildFrom;)Ljava/lang/Object;
Asciz	that;
Asciz	(Lscala/collection/Traversable;Lscala/collection/generic/CanBuildFrom;)Ljava/lang/Object;;
Asciz	(Lscala/collection/TraversableLike;Lscala/collection/Traversable;Lscala/collection/generic/CanBuildFrom;)Ljava/lang/Object;;
NameAndType	$plus$plus:(Lscala/collection/TraversableLike;Lscala/collection/Traversable;Lscala/collection/generic/CanBuildFrom;)Ljava/lang/Object;
Method	scala/collection/TraversableLike$class.$plus$plus:(Lscala/collection/TraversableLike;Lscala/collection/Traversable;Lscala/collection/generic/CanBuildFrom;)Ljava/lang/Object;
Asciz	hasDefiniteSize;
Asciz	()Z;
Asciz	(Lscala/collection/TraversableLike;)Z;
NameAndType	hasDefiniteSize:(Lscala/collection/TraversableLike;)Z
Method	scala/collection/TraversableLike$class.hasDefiniteSize:(Lscala/collection/TraversableLike;)Z
Asciz	nonEmpty;
NameAndType	nonEmpty:(Lscala/collection/TraversableLike;)Z
Method	scala/collection/TraversableLike$class.nonEmpty:(Lscala/collection/TraversableLike;)Z
NameAndType	repr:(Lscala/collection/TraversableLike;)Ljava/lang/Object;
Method	scala/collection/TraversableLike$class.repr:(Lscala/collection/TraversableLike;)Ljava/lang/Object;
Asciz	transpose;
Asciz	(Lscala/Function1;)Lscala/collection/Traversable;;
Asciz	(Lscala/collection/generic/GenericTraversableTemplate;Lscala/Function1;)Lscala/collection/Traversable;;
NameAndType	transpose:(Lscala/collection/generic/GenericTraversableTemplate;Lscala/Function1;)Lscala/collection/Traversable;
Method	scala/collection/generic/GenericTraversableTemplate$class.transpose:(Lscala/collection/generic/GenericTraversableTemplate;Lscala/Function1;)Lscala/collection/Traversable;
Asciz	asTraversable;
Asciz	flatten;
NameAndType	flatten:(Lscala/collection/generic/GenericTraversableTemplate;Lscala/Function1;)Lscala/collection/Traversable;
Method	scala/collection/generic/GenericTraversableTemplate$class.flatten:(Lscala/collection/generic/GenericTraversableTemplate;Lscala/Function1;)Lscala/collection/Traversable;
Asciz	unzip;
Asciz	(Lscala/collection/generic/GenericTraversableTemplate;Lscala/Function1;)Lscala/Tuple2;;
NameAndType	unzip:(Lscala/collection/generic/GenericTraversableTemplate;Lscala/Function1;)Lscala/Tuple2;
Method	scala/collection/generic/GenericTraversableTemplate$class.unzip:(Lscala/collection/generic/GenericTraversableTemplate;Lscala/Function1;)Lscala/Tuple2;
Asciz	asPair;
Asciz	genericBuilder;
Asciz	()Lscala/collection/mutable/Builder;;
Asciz	(Lscala/collection/generic/GenericTraversableTemplate;)Lscala/collection/mutable/Builder;;
NameAndType	genericBuilder:(Lscala/collection/generic/GenericTraversableTemplate;)Lscala/collection/mutable/Builder;
Method	scala/collection/generic/GenericTraversableTemplate$class.genericBuilder:(Lscala/collection/generic/GenericTraversableTemplate;)Lscala/collection/mutable/Builder;
Asciz	projection;
Asciz	(Lscala/collection/IterableLike;)Lscala/collection/IterableView;;
NameAndType	projection:(Lscala/collection/IterableLike;)Lscala/collection/IterableView;
Method	scala/collection/IterableLike$class.projection:(Lscala/collection/IterableLike;)Lscala/collection/IterableView;
Asciz	Deprecated;
Asciz	firstOption;
Asciz	(Lscala/collection/IterableLike;)Lscala/Option;;
NameAndType	firstOption:(Lscala/collection/IterableLike;)Lscala/Option;
Method	scala/collection/IterableLike$class.firstOption:(Lscala/collection/IterableLike;)Lscala/Option;
Asciz	first;
Asciz	(Lscala/collection/IterableLike;)Ljava/lang/Object;;
NameAndType	first:(Lscala/collection/IterableLike;)Ljava/lang/Object;
Method	scala/collection/IterableLike$class.first:(Lscala/collection/IterableLike;)Ljava/lang/Object;
Asciz	(Lscala/collection/IterableLike;II)Lscala/collection/IterableView;;
NameAndType	view:(Lscala/collection/IterableLike;II)Lscala/collection/IterableView;
Method	scala/collection/IterableLike$class.view:(Lscala/collection/IterableLike;II)Lscala/collection/IterableView;
NameAndType	view:(Lscala/collection/IterableLike;)Lscala/collection/IterableView;
Method	scala/collection/IterableLike$class.view:(Lscala/collection/IterableLike;)Lscala/collection/IterableView;
Asciz	canEqual;
Asciz	(Lscala/collection/IterableLike;Ljava/lang/Object;)Z;
NameAndType	canEqual:(Lscala/collection/IterableLike;Ljava/lang/Object;)Z
Method	scala/collection/IterableLike$class.canEqual:(Lscala/collection/IterableLike;Ljava/lang/Object;)Z
Asciz	toStream;
Asciz	()Lscala/collection/immutable/Stream;;
Asciz	(Lscala/collection/IterableLike;)Lscala/collection/immutable/Stream;;
NameAndType	toStream:(Lscala/collection/IterableLike;)Lscala/collection/immutable/Stream;
Method	scala/collection/IterableLike$class.toStream:(Lscala/collection/IterableLike;)Lscala/collection/immutable/Stream;
Asciz	sameElements;
Asciz	(Lscala/collection/Iterable;)Z;
Asciz	(Lscala/collection/IterableLike;Lscala/collection/Iterable;)Z;
NameAndType	sameElements:(Lscala/collection/IterableLike;Lscala/collection/Iterable;)Z
Method	scala/collection/IterableLike$class.sameElements:(Lscala/collection/IterableLike;Lscala/collection/Iterable;)Z
Asciz	Lscala/collection/Iterable;;
Asciz	zipWithIndex;
Asciz	(Lscala/collection/generic/CanBuildFrom;)Ljava/lang/Object;;
Asciz	(Lscala/collection/IterableLike;Lscala/collection/generic/CanBuildFrom;)Ljava/lang/Object;;
NameAndType	zipWithIndex:(Lscala/collection/IterableLike;Lscala/collection/generic/CanBuildFrom;)Ljava/lang/Object;
Method	scala/collection/IterableLike$class.zipWithIndex:(Lscala/collection/IterableLike;Lscala/collection/generic/CanBuildFrom;)Ljava/lang/Object;
Asciz	zipAll;
Asciz	(Lscala/collection/Iterable;Ljava/lang/Object;Ljava/lang/Object;Lscala/collection/generic/CanBuildFrom;)Ljava/lang/Object;;
Asciz	(Lscala/collection/IterableLike;Lscala/collection/Iterable;Ljava/lang/Object;Ljava/lang/Object;Lscala/collection/generic/CanBuildFrom;)Ljava/lang/Object;;
NameAndType	zipAll:(Lscala/collection/IterableLike;Lscala/collection/Iterable;Ljava/lang/Object;Ljava/lang/Object;Lscala/collection/generic/CanBuildFrom;)Ljava/lang/Object;
Method	scala/collection/IterableLike$class.zipAll:(Lscala/collection/IterableLike;Lscala/collection/Iterable;Ljava/lang/Object;Ljava/lang/Object;Lscala/collection/generic/CanBuildFrom;)Ljava/lang/Object;
Asciz	thisElem;
Asciz	thatElem;
Asciz	zip;
Asciz	(Lscala/collection/Iterable;Lscala/collection/generic/CanBuildFrom;)Ljava/lang/Object;;
Asciz	(Lscala/collection/IterableLike;Lscala/collection/Iterable;Lscala/collection/generic/CanBuildFrom;)Ljava/lang/Object;;
NameAndType	zip:(Lscala/collection/IterableLike;Lscala/collection/Iterable;Lscala/collection/generic/CanBuildFrom;)Ljava/lang/Object;
Method	scala/collection/IterableLike$class.zip:(Lscala/collection/IterableLike;Lscala/collection/Iterable;Lscala/collection/generic/CanBuildFrom;)Ljava/lang/Object;
Asciz	(Ljava/lang/Object;II)V;
Asciz	(Lscala/collection/IterableLike;Ljava/lang/Object;II)V;
NameAndType	copyToArray:(Lscala/collection/IterableLike;Ljava/lang/Object;II)V
Method	scala/collection/IterableLike$class.copyToArray:(Lscala/collection/IterableLike;Ljava/lang/Object;II)V
Asciz	len;
Asciz	dropRight;
Asciz	(Lscala/collection/IterableLike;I)Ljava/lang/Object;;
NameAndType	dropRight:(Lscala/collection/IterableLike;I)Ljava/lang/Object;
Method	scala/collection/IterableLike$class.dropRight:(Lscala/collection/IterableLike;I)Ljava/lang/Object;
Asciz	takeRight;
NameAndType	takeRight:(Lscala/collection/IterableLike;I)Ljava/lang/Object;
Method	scala/collection/IterableLike$class.takeRight:(Lscala/collection/IterableLike;I)Ljava/lang/Object;
Asciz	takeWhile;
Asciz	(Lscala/collection/IterableLike;Lscala/Function1;)Ljava/lang/Object;;
NameAndType	takeWhile:(Lscala/collection/IterableLike;Lscala/Function1;)Ljava/lang/Object;
Method	scala/collection/IterableLike$class.takeWhile:(Lscala/collection/IterableLike;Lscala/Function1;)Ljava/lang/Object;
Asciz	slice;
Asciz	(II)Ljava/lang/Object;;
Asciz	(Lscala/collection/IterableLike;II)Ljava/lang/Object;;
NameAndType	slice:(Lscala/collection/IterableLike;II)Ljava/lang/Object;
Method	scala/collection/IterableLike$class.slice:(Lscala/collection/IterableLike;II)Ljava/lang/Object;
Asciz	take;
NameAndType	take:(Lscala/collection/IterableLike;I)Ljava/lang/Object;
Method	scala/collection/IterableLike$class.take:(Lscala/collection/IterableLike;I)Ljava/lang/Object;
Asciz	head;
NameAndType	head:(Lscala/collection/IterableLike;)Ljava/lang/Object;
Method	scala/collection/IterableLike$class.head:(Lscala/collection/IterableLike;)Ljava/lang/Object;
Asciz	toIterable;
Asciz	(Lscala/collection/IterableLike;)Lscala/collection/Iterable;;
NameAndType	toIterable:(Lscala/collection/IterableLike;)Lscala/collection/Iterable;
Method	scala/collection/IterableLike$class.toIterable:(Lscala/collection/IterableLike;)Lscala/collection/Iterable;
Asciz	reduceRight;
Asciz	(Lscala/collection/IterableLike;Lscala/Function2;)Ljava/lang/Object;;
NameAndType	reduceRight:(Lscala/collection/IterableLike;Lscala/Function2;)Ljava/lang/Object;
Method	scala/collection/IterableLike$class.reduceRight:(Lscala/collection/IterableLike;Lscala/Function2;)Ljava/lang/Object;
Asciz	foldRight;
Asciz	(Lscala/collection/IterableLike;Ljava/lang/Object;Lscala/Function2;)Ljava/lang/Object;;
NameAndType	foldRight:(Lscala/collection/IterableLike;Ljava/lang/Object;Lscala/Function2;)Ljava/lang/Object;
Method	scala/collection/IterableLike$class.foldRight:(Lscala/collection/IterableLike;Ljava/lang/Object;Lscala/Function2;)Ljava/lang/Object;
Asciz	find;
Asciz	(Lscala/Function1;)Lscala/Option;;
Asciz	(Lscala/collection/IterableLike;Lscala/Function1;)Lscala/Option;;
NameAndType	find:(Lscala/collection/IterableLike;Lscala/Function1;)Lscala/Option;
Method	scala/collection/IterableLike$class.find:(Lscala/collection/IterableLike;Lscala/Function1;)Lscala/Option;
Asciz	exists;
Asciz	(Lscala/Function1;)Z;
Asciz	(Lscala/collection/IterableLike;Lscala/Function1;)Z;
NameAndType	exists:(Lscala/collection/IterableLike;Lscala/Function1;)Z
Method	scala/collection/IterableLike$class.exists:(Lscala/collection/IterableLike;Lscala/Function1;)Z
Asciz	forall;
NameAndType	forall:(Lscala/collection/IterableLike;Lscala/Function1;)Z
Method	scala/collection/IterableLike$class.forall:(Lscala/collection/IterableLike;Lscala/Function1;)Z
Asciz	elements;
Asciz	(Lscala/collection/IterableLike;)Lscala/collection/Iterator;;
NameAndType	elements:(Lscala/collection/IterableLike;)Lscala/collection/Iterator;
Method	scala/collection/IterableLike$class.elements:(Lscala/collection/IterableLike;)Lscala/collection/Iterator;
Asciz	(Lscala/collection/IterableLike;Ljava/lang/Object;)Lscala/collection/Iterable;;
NameAndType	toCollection:(Lscala/collection/IterableLike;Ljava/lang/Object;)Lscala/collection/Iterable;
Method	scala/collection/IterableLike$class.toCollection:(Lscala/collection/IterableLike;Ljava/lang/Object;)Lscala/collection/Iterable;
NameAndType	thisCollection:(Lscala/collection/IterableLike;)Lscala/collection/Iterable;
Method	scala/collection/IterableLike$class.thisCollection:(Lscala/collection/IterableLike;)Lscala/collection/Iterable;
Asciz	companion;
Asciz	()Lscala/collection/generic/GenericCompanion;;
Asciz	(Lscala/collection/immutable/Iterable;)Lscala/collection/generic/GenericCompanion;;
NameAndType	companion:(Lscala/collection/immutable/Iterable;)Lscala/collection/generic/GenericCompanion;
Method	scala/collection/immutable/Iterable$class.companion:(Lscala/collection/immutable/Iterable;)Lscala/collection/generic/GenericCompanion;
Asciz	compose;
Asciz	(Lscala/Function1;Lscala/Function1;)Lscala/Function1;;
NameAndType	compose:(Lscala/Function1;Lscala/Function1;)Lscala/Function1;
Method	scala/Function1$class.compose:(Lscala/Function1;Lscala/Function1;)Lscala/Function1;
Asciz	lift;
Asciz	()Lscala/Function1;;
Asciz	(Lscala/PartialFunction;)Lscala/Function1;;
NameAndType	lift:(Lscala/PartialFunction;)Lscala/Function1;
Method	scala/PartialFunction$class.lift:(Lscala/PartialFunction;)Lscala/Function1;
Asciz	(Lscala/PartialFunction;Lscala/Function1;)Lscala/PartialFunction;;
NameAndType	andThen:(Lscala/PartialFunction;Lscala/Function1;)Lscala/PartialFunction;
Method	scala/PartialFunction$class.andThen:(Lscala/PartialFunction;Lscala/Function1;)Lscala/PartialFunction;
Asciz	k;
Asciz	orElse;
Asciz	(Lscala/PartialFunction;)Lscala/PartialFunction;;
Asciz	(Lscala/PartialFunction;Lscala/PartialFunction;)Lscala/PartialFunction;;
NameAndType	orElse:(Lscala/PartialFunction;Lscala/PartialFunction;)Lscala/PartialFunction;
Method	scala/PartialFunction$class.orElse:(Lscala/PartialFunction;Lscala/PartialFunction;)Lscala/PartialFunction;
Asciz	$minus$minus;
Asciz	(Lscala/collection/Iterator;)Lscala/collection/generic/Subtractable;;
Asciz	(Lscala/collection/generic/Subtractable;Lscala/collection/Iterator;)Lscala/collection/generic/Subtractable;;
NameAndType	$minus$minus:(Lscala/collection/generic/Subtractable;Lscala/collection/Iterator;)Lscala/collection/generic/Subtractable;
Method	scala/collection/generic/Subtractable$class.$minus$minus:(Lscala/collection/generic/Subtractable;Lscala/collection/Iterator;)Lscala/collection/generic/Subtractable;
Asciz	(Lscala/collection/Traversable;)Lscala/collection/generic/Subtractable;;
Asciz	(Lscala/collection/generic/Subtractable;Lscala/collection/Traversable;)Lscala/collection/generic/Subtractable;;
NameAndType	$minus$minus:(Lscala/collection/generic/Subtractable;Lscala/collection/Traversable;)Lscala/collection/generic/Subtractable;
Method	scala/collection/generic/Subtractable$class.$minus$minus:(Lscala/collection/generic/Subtractable;Lscala/collection/Traversable;)Lscala/collection/generic/Subtractable;
Asciz	elems;
Asciz	(Ljava/lang/Object;Ljava/lang/Object;Lscala/collection/Seq;)Lscala/collection/generic/Subtractable;;
Asciz	(Lscala/collection/generic/Subtractable;Ljava/lang/Object;Ljava/lang/Object;Lscala/collection/Seq;)Lscala/collection/generic/Subtractable;;
NameAndType	$minus:(Lscala/collection/generic/Subtractable;Ljava/lang/Object;Ljava/lang/Object;Lscala/collection/Seq;)Lscala/collection/generic/Subtractable;
Method	scala/collection/generic/Subtractable$class.$minus:(Lscala/collection/generic/Subtractable;Ljava/lang/Object;Ljava/lang/Object;Lscala/collection/Seq;)Lscala/collection/generic/Subtractable;
Asciz	elem1;
Asciz	elem2;
Asciz	(Lscala/collection/MapLike;Ljava/lang/Object;)Z;
NameAndType	equals:(Lscala/collection/MapLike;Ljava/lang/Object;)Z
Method	scala/collection/MapLike$class.equals:(Lscala/collection/MapLike;Ljava/lang/Object;)Z
Asciz	hashCode;
Asciz	(Lscala/collection/MapLike;)I;
NameAndType	hashCode:(Lscala/collection/MapLike;)I
Method	scala/collection/MapLike$class.hashCode:(Lscala/collection/MapLike;)I
Asciz	toString;
Asciz	(Lscala/collection/MapLike;)Ljava/lang/String;;
NameAndType	toString:(Lscala/collection/MapLike;)Ljava/lang/String;
Method	scala/collection/MapLike$class.toString:(Lscala/collection/MapLike;)Ljava/lang/String;
Asciz	stringPrefix;
NameAndType	stringPrefix:(Lscala/collection/MapLike;)Ljava/lang/String;
Method	scala/collection/MapLike$class.stringPrefix:(Lscala/collection/MapLike;)Ljava/lang/String;
Asciz	(Lscala/collection/mutable/StringBuilder;Ljava/lang/String;Ljava/lang/String;Ljava/lang/String;)Lscala/collection/mutable/StringBuilder;;
Asciz	(Lscala/collection/MapLike;Lscala/collection/mutable/StringBuilder;Ljava/lang/String;Ljava/lang/String;Ljava/lang/String;)Lscala/collection/mutable/StringBuilder;;
NameAndType	addString:(Lscala/collection/MapLike;Lscala/collection/mutable/StringBuilder;Ljava/lang/String;Ljava/lang/String;Ljava/lang/String;)Lscala/collection/mutable/StringBuilder;
Method	scala/collection/MapLike$class.addString:(Lscala/collection/MapLike;Lscala/collection/mutable/StringBuilder;Ljava/lang/String;Ljava/lang/String;Ljava/lang/String;)Lscala/collection/mutable/StringBuilder;
Asciz	mapElements;
Asciz	(Lscala/Function1;)Lscala/collection/DefaultMap;;
Asciz	(Lscala/collection/MapLike;Lscala/Function1;)Lscala/collection/DefaultMap;;
NameAndType	mapElements:(Lscala/collection/MapLike;Lscala/Function1;)Lscala/collection/DefaultMap;
Method	scala/collection/MapLike$class.mapElements:(Lscala/collection/MapLike;Lscala/Function1;)Lscala/collection/DefaultMap;
Asciz	mapValues;
NameAndType	mapValues:(Lscala/collection/MapLike;Lscala/Function1;)Lscala/collection/DefaultMap;
Method	scala/collection/MapLike$class.mapValues:(Lscala/collection/MapLike;Lscala/Function1;)Lscala/collection/DefaultMap;
Asciz	filterKeys;
NameAndType	filterKeys:(Lscala/collection/MapLike;Lscala/Function1;)Lscala/collection/DefaultMap;
Method	scala/collection/MapLike$class.filterKeys:(Lscala/collection/MapLike;Lscala/Function1;)Lscala/collection/DefaultMap;
Asciz	default;
Asciz	(Lscala/collection/MapLike;Ljava/lang/Object;)Ljava/lang/Object;;
NameAndType	default:(Lscala/collection/MapLike;Ljava/lang/Object;)Ljava/lang/Object;
Method	scala/collection/MapLike$class.default:(Lscala/collection/MapLike;Ljava/lang/Object;)Ljava/lang/Object;
Asciz	values;
Asciz	(Lscala/collection/MapLike;)Lscala/collection/Iterator;;
NameAndType	values:(Lscala/collection/MapLike;)Lscala/collection/Iterator;
Method	scala/collection/MapLike$class.values:(Lscala/collection/MapLike;)Lscala/collection/Iterator;
Asciz	valuesIterator;
NameAndType	valuesIterator:(Lscala/collection/MapLike;)Lscala/collection/Iterator;
Method	scala/collection/MapLike$class.valuesIterator:(Lscala/collection/MapLike;)Lscala/collection/Iterator;
Asciz	valuesIterable;
Asciz	(Lscala/collection/MapLike;)Lscala/collection/Iterable;;
NameAndType	valuesIterable:(Lscala/collection/MapLike;)Lscala/collection/Iterable;
Method	scala/collection/MapLike$class.valuesIterable:(Lscala/collection/MapLike;)Lscala/collection/Iterable;
Asciz	keys;
NameAndType	keys:(Lscala/collection/MapLike;)Lscala/collection/Iterator;
Method	scala/collection/MapLike$class.keys:(Lscala/collection/MapLike;)Lscala/collection/Iterator;
Asciz	keysIterator;
NameAndType	keysIterator:(Lscala/collection/MapLike;)Lscala/collection/Iterator;
Method	scala/collection/MapLike$class.keysIterator:(Lscala/collection/MapLike;)Lscala/collection/Iterator;
Asciz	keySet;
Asciz	()Lscala/collection/Set;;
Asciz	(Lscala/collection/MapLike;)Lscala/collection/Set;;
NameAndType	keySet:(Lscala/collection/MapLike;)Lscala/collection/Set;
Method	scala/collection/MapLike$class.keySet:(Lscala/collection/MapLike;)Lscala/collection/Set;
Asciz	isDefinedAt;
NameAndType	isDefinedAt:(Lscala/collection/MapLike;Ljava/lang/Object;)Z
Method	scala/collection/MapLike$class.isDefinedAt:(Lscala/collection/MapLike;Ljava/lang/Object;)Z
Asciz	contains;
NameAndType	contains:(Lscala/collection/MapLike;Ljava/lang/Object;)Z
Method	scala/collection/MapLike$class.contains:(Lscala/collection/MapLike;Ljava/lang/Object;)Z
NameAndType	apply:(Lscala/collection/MapLike;Ljava/lang/Object;)Ljava/lang/Object;
Method	scala/collection/MapLike$class.apply:(Lscala/collection/MapLike;Ljava/lang/Object;)Ljava/lang/Object;
Asciz	getOrElse;
Asciz	(Ljava/lang/Object;Lscala/Function0;)Ljava/lang/Object;;
Asciz	(Lscala/collection/MapLike;Ljava/lang/Object;Lscala/Function0;)Ljava/lang/Object;;
NameAndType	getOrElse:(Lscala/collection/MapLike;Ljava/lang/Object;Lscala/Function0;)Ljava/lang/Object;
Method	scala/collection/MapLike$class.getOrElse:(Lscala/collection/MapLike;Ljava/lang/Object;Lscala/Function0;)Ljava/lang/Object;
Asciz	Lscala/Function0;;
Asciz	isEmpty;
Asciz	(Lscala/collection/MapLike;)Z;
NameAndType	isEmpty:(Lscala/collection/MapLike;)Z
Method	scala/collection/MapLike$class.isEmpty:(Lscala/collection/MapLike;)Z
Asciz	newBuilder;
Asciz	(Lscala/collection/MapLike;)Lscala/collection/mutable/Builder;;
NameAndType	newBuilder:(Lscala/collection/MapLike;)Lscala/collection/mutable/Builder;
Method	scala/collection/MapLike$class.newBuilder:(Lscala/collection/MapLike;)Lscala/collection/mutable/Builder;
Asciz	update;
Asciz	(Lscala/collection/immutable/MapLike;Ljava/lang/Object;Ljava/lang/Object;)Lscala/collection/immutable/Map;;
NameAndType	update:(Lscala/collection/immutable/MapLike;Ljava/lang/Object;Ljava/lang/Object;)Lscala/collection/immutable/Map;
Method	scala/collection/immutable/MapLike$class.update:(Lscala/collection/immutable/MapLike;Ljava/lang/Object;Ljava/lang/Object;)Lscala/collection/immutable/Map;
Asciz	(Lscala/collection/immutable/MapLike;Lscala/Function1;)Lscala/collection/immutable/Map;;
NameAndType	filterNot:(Lscala/collection/immutable/MapLike;Lscala/Function1;)Lscala/collection/immutable/Map;
Method	scala/collection/immutable/MapLike$class.filterNot:(Lscala/collection/immutable/MapLike;Lscala/Function1;)Lscala/collection/immutable/Map;
Asciz	transform;
Asciz	(Lscala/Function2;Lscala/collection/generic/CanBuildFrom;)Ljava/lang/Object;;
Asciz	(Lscala/collection/immutable/MapLike;Lscala/Function2;Lscala/collection/generic/CanBuildFrom;)Ljava/lang/Object;;
NameAndType	transform:(Lscala/collection/immutable/MapLike;Lscala/Function2;Lscala/collection/generic/CanBuildFrom;)Ljava/lang/Object;
Method	scala/collection/immutable/MapLike$class.transform:(Lscala/collection/immutable/MapLike;Lscala/Function2;Lscala/collection/generic/CanBuildFrom;)Ljava/lang/Object;
Asciz	(Lscala/collection/immutable/MapLike;Lscala/collection/Iterator;)Lscala/collection/immutable/Map;;
NameAndType	$plus$plus:(Lscala/collection/immutable/MapLike;Lscala/collection/Iterator;)Lscala/collection/immutable/Map;
Method	scala/collection/immutable/MapLike$class.$plus$plus:(Lscala/collection/immutable/MapLike;Lscala/collection/Iterator;)Lscala/collection/immutable/Map;
Asciz	(Lscala/collection/immutable/MapLike;Lscala/collection/Traversable;)Lscala/collection/immutable/Map;;
NameAndType	$plus$plus:(Lscala/collection/immutable/MapLike;Lscala/collection/Traversable;)Lscala/collection/immutable/Map;
Method	scala/collection/immutable/MapLike$class.$plus$plus:(Lscala/collection/immutable/MapLike;Lscala/collection/Traversable;)Lscala/collection/immutable/Map;
Asciz	(Lscala/collection/immutable/MapLike;Lscala/Tuple2;Lscala/Tuple2;Lscala/collection/Seq;)Lscala/collection/immutable/Map;;
NameAndType	$plus:(Lscala/collection/immutable/MapLike;Lscala/Tuple2;Lscala/Tuple2;Lscala/collection/Seq;)Lscala/collection/immutable/Map;
Method	scala/collection/immutable/MapLike$class.$plus:(Lscala/collection/immutable/MapLike;Lscala/Tuple2;Lscala/Tuple2;Lscala/collection/Seq;)Lscala/collection/immutable/Map;
Asciz	withDefaultValue;
Asciz	(Lscala/collection/immutable/Map;Ljava/lang/Object;)Lscala/collection/immutable/Map;;
NameAndType	withDefaultValue:(Lscala/collection/immutable/Map;Ljava/lang/Object;)Lscala/collection/immutable/Map;
Method	scala/collection/immutable/Map$class.withDefaultValue:(Lscala/collection/immutable/Map;Ljava/lang/Object;)Lscala/collection/immutable/Map;
Asciz	d;
Asciz	withDefault;
Asciz	(Lscala/collection/immutable/Map;Lscala/Function1;)Lscala/collection/immutable/Map;;
NameAndType	withDefault:(Lscala/collection/immutable/Map;Lscala/Function1;)Lscala/collection/immutable/Map;
Method	scala/collection/immutable/Map$class.withDefault:(Lscala/collection/immutable/Map;Lscala/Function1;)Lscala/collection/immutable/Map;
Asciz	(Lscala/collection/immutable/Map;)Lscala/collection/immutable/Map;;
NameAndType	empty:(Lscala/collection/immutable/Map;)Lscala/collection/immutable/Map;
Method	scala/collection/immutable/Map$class.empty:(Lscala/collection/immutable/Map;)Lscala/collection/immutable/Map;
Asciz	<A:Ljava/lang/Object;B:Ljava/lang/Object;>Ljava/lang/Object;Lscala/collection/immutable/Map<TA;TB;>;Lscala/ScalaObject;;
Asciz	Scala;
Asciz	InnerClasses;
Asciz	Map3;
Asciz	Map4;
Asciz	scala/Predef$$less$colon$less;
class	scala/Predef$$less$colon$less
Asciz	scala/Predef;
class	scala/Predef
Asciz	$less$colon$less;
Asciz	scala/collection/TraversableLike$WithFilter;
class	scala/collection/TraversableLike$WithFilter
Asciz	WithFilter;
Asciz	scala/ScalaObject;
class	scala/ScalaObject
Asciz	java/io/Serializable;
class	java/io/Serializable

{
private final java.lang.Object value4;
  Signature: Ljava/lang/Object;
  Signature: length = 0x2
   00 05 

private final java.lang.Object key4;
  Signature: Ljava/lang/Object;
  Signature: length = 0x2
   00 08 

private final java.lang.Object value3;
  Signature: Ljava/lang/Object;
  Signature: length = 0x2
   00 05 

private final java.lang.Object key3;
  Signature: Ljava/lang/Object;
  Signature: length = 0x2
   00 08 

private final java.lang.Object value2;
  Signature: Ljava/lang/Object;
  Signature: length = 0x2
   00 05 

private final java.lang.Object key2;
  Signature: Ljava/lang/Object;
  Signature: length = 0x2
   00 08 

private final java.lang.Object value1;
  Signature: Ljava/lang/Object;
  Signature: length = 0x2
   00 05 

private final java.lang.Object key1;
  Signature: Ljava/lang/Object;
  Signature: length = 0x2
   00 08 

public scala.collection.immutable.Map$Map4(java.lang.Object, java.lang.Object, java.lang.Object, java.lang.Object, java.lang.Object, java.lang.Object, java.lang.Object, java.lang.Object);
  Signature: (Ljava/lang/Object;Ljava/lang/Object;Ljava/lang/Object;Ljava/lang/Object;Ljava/lang/Object;Ljava/lang/Object;Ljava/lang/Object;Ljava/lang/Object;)V
  Code:
   Stack=2, Locals=9, Args_size=9
	aload_0
	aload_1
	putfield	Field key1:Ljava/lang/Object;
	aload_0
	aload_2
	putfield	Field value1:Ljava/lang/Object;
	aload_0
	aload_3
	putfield	Field key2:Ljava/lang/Object;
	aload_0
	aload	4
	putfield	Field value2:Ljava/lang/Object;
	aload_0
	aload	5
	putfield	Field key3:Ljava/lang/Object;
	aload_0
	aload	6
	putfield	Field value3:Ljava/lang/Object;
	aload_0
	aload	7
	putfield	Field key4:Ljava/lang/Object;
	aload_0
	aload	8
	putfield	Field value4:Ljava/lang/Object;
	aload_0
	invokespecial	Method java/lang/Object."<init>":()V
	aload_0
	invokestatic	Method scala/collection/TraversableLike$class.$init$:(Lscala/collection/TraversableLike;)V
	aload_0
	invokestatic	Method scala/collection/generic/GenericTraversableTemplate$class.$init$:(Lscala/collection/generic/GenericTraversableTemplate;)V
	aload_0
	invokestatic	Method scala/collection/Traversable$class.$init$:(Lscala/collection/Traversable;)V
	aload_0
	invokestatic	Method scala/collection/immutable/Traversable$class.$init$:(Lscala/collection/immutable/Traversable;)V
	aload_0
	invokestatic	Method scala/collection/IterableLike$class.$init$:(Lscala/collection/IterableLike;)V
	aload_0
	invokestatic	Method scala/collection/Iterable$class.$init$:(Lscala/collection/Iterable;)V
	aload_0
	invokestatic	Method scala/collection/immutable/Iterable$class.$init$:(Lscala/collection/immutable/Iterable;)V
	aload_0
	invokestatic	Method scala/Function1$class.$init$:(Lscala/Function1;)V
	aload_0
	invokestatic	Method scala/PartialFunction$class.$init$:(Lscala/PartialFunction;)V
	aload_0
	invokestatic	Method scala/collection/generic/Subtractable$class.$init$:(Lscala/collection/generic/Subtractable;)V
	aload_0
	invokestatic	Method scala/collection/MapLike$class.$init$:(Lscala/collection/MapLike;)V
	aload_0
	invokestatic	Method scala/collection/Map$class.$init$:(Lscala/collection/Map;)V
	aload_0
	invokestatic	Method scala/collection/immutable/MapLike$class.$init$:(Lscala/collection/immutable/MapLike;)V
	aload_0
	invokestatic	Method scala/collection/immutable/Map$class.$init$:(Lscala/collection/immutable/Map;)V
	return
  Labels:
  LocalVariableTable: 
   Start  Length  Slot  Name   Signature
   0      106      0    this       Lscala/collection/immutable/Map$Map4;
   0      106      1    key1       Ljava/lang/Object;
   0      106      2    value1       Ljava/lang/Object;
   0      106      3    key2       Ljava/lang/Object;
   0      106      4    value2       Ljava/lang/Object;
   0      106      5    key3       Ljava/lang/Object;
   0      106      6    value3       Ljava/lang/Object;
   0      106      7    key4       Ljava/lang/Object;
   0      106      8    value4       Ljava/lang/Object;

  Signature: length = 0x2
   00 74 

public scala.collection.Map updated(java.lang.Object, java.lang.Object);
  Signature: (Ljava/lang/Object;Ljava/lang/Object;)Lscala/collection/Map;
  Code:
   Stack=3, Locals=3, Args_size=3
	aload_0
	aload_1
	aload_2
	invokevirtual	Method updated:(Ljava/lang/Object;Ljava/lang/Object;)Lscala/collection/immutable/Map;
	areturn
  Labels:
  LocalVariableTable: 
   Start  Length  Slot  Name   Signature
   0      7      0    this       Lscala/collection/immutable/Map$Map4;
   0      7      1    key       Ljava/lang/Object;
   0      7      2    value       Ljava/lang/Object;


public scala.collection.Map $plus(scala.Tuple2);
  Signature: (Lscala/Tuple2;)Lscala/collection/Map;
  Code:
   Stack=2, Locals=2, Args_size=2
	aload_0
	aload_1
	invokevirtual	Method $plus:(Lscala/Tuple2;)Lscala/collection/immutable/Map;
	areturn
  Labels:
  LocalVariableTable: 
   Start  Length  Slot  Name   Signature
   0      6      0    this       Lscala/collection/immutable/Map$Map4;
   0      6      1    kv       Lscala/Tuple2;


public scala.collection.Map $minus(java.lang.Object);
  Signature: (Ljava/lang/Object;)Lscala/collection/Map;
  Code:
   Stack=2, Locals=2, Args_size=2
	aload_0
	aload_1
	invokevirtual	Method $minus:(Ljava/lang/Object;)Lscala/collection/immutable/Map;
	areturn
  Labels:
  LocalVariableTable: 
   Start  Length  Slot  Name   Signature
   0      6      0    this       Lscala/collection/immutable/Map$Map4;
   0      6      1    key       Ljava/lang/Object;


public scala.collection.generic.Subtractable $minus(java.lang.Object);
  Signature: (Ljava/lang/Object;)Lscala/collection/generic/Subtractable;
  Code:
   Stack=2, Locals=2, Args_size=2
	aload_0
	aload_1
	invokevirtual	Method $minus:(Ljava/lang/Object;)Lscala/collection/immutable/Map;
	areturn
  Labels:
  LocalVariableTable: 
   Start  Length  Slot  Name   Signature
   0      6      0    this       Lscala/collection/immutable/Map$Map4;
   0      6      1    elem       Ljava/lang/Object;


public scala.collection.Map empty();
  Signature: ()Lscala/collection/Map;
  Code:
   Stack=1, Locals=1, Args_size=1
	aload_0
	invokeinterface	InterfaceMethod scala/collection/immutable/Map.empty:()Lscala/collection/immutable/Map;
	areturn
  Labels:

public scala.collection.Map $plus(scala.Tuple2, scala.Tuple2, scala.collection.Seq);
  Signature: (Lscala/Tuple2;Lscala/Tuple2;Lscala/collection/Seq;)Lscala/collection/Map;
  Code:
   Stack=4, Locals=4, Args_size=4
	aload_0
	aload_1
	aload_2
	aload_3
	invokeinterface	InterfaceMethod scala/collection/immutable/MapLike.$plus:(Lscala/Tuple2;Lscala/Tuple2;Lscala/collection/Seq;)Lscala/collection/immutable/Map;
	areturn
  Labels:
  LocalVariableTable: 
   Start  Length  Slot  Name   Signature
   0      10      0    this       Lscala/collection/immutable/Map$Map4;
   0      10      1    kv1       Lscala/Tuple2;
   0      10      2    kv2       Lscala/Tuple2;
   0      10      3    kvs       Lscala/collection/Seq;


public scala.collection.Map $plus$plus(scala.collection.Traversable);
  Signature: (Lscala/collection/Traversable;)Lscala/collection/Map;
  Code:
   Stack=2, Locals=2, Args_size=2
	aload_0
	aload_1
	invokeinterface	InterfaceMethod scala/collection/immutable/MapLike.$plus$plus:(Lscala/collection/Traversable;)Lscala/collection/immutable/Map;
	areturn
  Labels:
  LocalVariableTable: 
   Start  Length  Slot  Name   Signature
   0      8      0    this       Lscala/collection/immutable/Map$Map4;
   0      8      1    kvs       Lscala/collection/Traversable;


public scala.collection.Map $plus$plus(scala.collection.Iterator);
  Signature: (Lscala/collection/Iterator;)Lscala/collection/Map;
  Code:
   Stack=2, Locals=2, Args_size=2
	aload_0
	aload_1
	invokeinterface	InterfaceMethod scala/collection/immutable/MapLike.$plus$plus:(Lscala/collection/Iterator;)Lscala/collection/immutable/Map;
	areturn
  Labels:
  LocalVariableTable: 
   Start  Length  Slot  Name   Signature
   0      8      0    this       Lscala/collection/immutable/Map$Map4;
   0      8      1    iter       Lscala/collection/Iterator;


public java.lang.Object filterNot(scala.Function1);
  Signature: (Lscala/Function1;)Ljava/lang/Object;
  Code:
   Stack=2, Locals=2, Args_size=2
	aload_0
	aload_1
	invokeinterface	InterfaceMethod scala/collection/immutable/MapLike.filterNot:(Lscala/Function1;)Lscala/collection/immutable/Map;
	areturn
  Labels:
  LocalVariableTable: 
   Start  Length  Slot  Name   Signature
   0      8      0    this       Lscala/collection/immutable/Map$Map4;
   0      8      1    p       Lscala/Function1;


public scala.Function1 andThen(scala.Function1);
  Signature: (Lscala/Function1;)Lscala/Function1;
  Code:
   Stack=2, Locals=2, Args_size=2
	aload_0
	aload_1
	invokeinterface	InterfaceMethod scala/PartialFunction.andThen:(Lscala/Function1;)Lscala/PartialFunction;
	areturn
  Labels:
  LocalVariableTable: 
   Start  Length  Slot  Name   Signature
   0      8      0    this       Lscala/collection/immutable/Map$Map4;
   0      8      1    g       Lscala/Function1;


public scala.collection.Traversable thisCollection();
  Signature: ()Lscala/collection/Traversable;
  Code:
   Stack=1, Locals=1, Args_size=1
	aload_0
	invokeinterface	InterfaceMethod scala/collection/IterableLike.thisCollection:()Lscala/collection/Iterable;
	areturn
  Labels:

public scala.collection.Traversable toCollection(java.lang.Object);
  Signature: (Ljava/lang/Object;)Lscala/collection/Traversable;
  Code:
   Stack=2, Locals=2, Args_size=2
	aload_0
	aload_1
	invokeinterface	InterfaceMethod scala/collection/IterableLike.toCollection:(Ljava/lang/Object;)Lscala/collection/Iterable;
	areturn
  Labels:
  LocalVariableTable: 
   Start  Length  Slot  Name   Signature
   0      8      0    this       Lscala/collection/immutable/Map$Map4;
   0      8      1    repr       Ljava/lang/Object;


public scala.collection.TraversableView view();
  Signature: ()Lscala/collection/TraversableView;
  Code:
   Stack=1, Locals=1, Args_size=1
	aload_0
	invokeinterface	InterfaceMethod scala/collection/IterableLike.view:()Lscala/collection/IterableView;
	areturn
  Labels:

public scala.collection.TraversableView view(int, int);
  Signature: (II)Lscala/collection/TraversableView;
  Code:
   Stack=3, Locals=3, Args_size=3
	aload_0
	iload_1
	iload_2
	invokeinterface	InterfaceMethod scala/collection/IterableLike.view:(II)Lscala/collection/IterableView;
	areturn
  Labels:
  LocalVariableTable: 
   Start  Length  Slot  Name   Signature
   0      9      0    this       Lscala/collection/immutable/Map$Map4;
   0      9      1    from       I
   0      9      2    until       I


public scala.collection.generic.Subtractable repr();
  Signature: ()Lscala/collection/generic/Subtractable;
  Code:
   Stack=1, Locals=1, Args_size=1
	aload_0
	invokeinterface	InterfaceMethod scala/collection/TraversableLike.repr:()Ljava/lang/Object;
	checkcast	class scala/collection/generic/Subtractable
	areturn
  Labels:

public void foreach(scala.Function1);
  Signature: (Lscala/Function1;)V
  Code:
   Stack=5, Locals=2, Args_size=2
	aload_1
	new	class scala/Tuple2
	dup
	aload_0
	getfield	Field key1:Ljava/lang/Object;
	aload_0
	getfield	Field value1:Ljava/lang/Object;
	invokespecial	Method scala/Tuple2."<init>":(Ljava/lang/Object;Ljava/lang/Object;)V
	invokeinterface	InterfaceMethod scala/Function1.apply:(Ljava/lang/Object;)Ljava/lang/Object;
	pop
	aload_1
	new	class scala/Tuple2
	dup
	aload_0
	getfield	Field key2:Ljava/lang/Object;
	aload_0
	getfield	Field value2:Ljava/lang/Object;
	invokespecial	Method scala/Tuple2."<init>":(Ljava/lang/Object;Ljava/lang/Object;)V
	invokeinterface	InterfaceMethod scala/Function1.apply:(Ljava/lang/Object;)Ljava/lang/Object;
	pop
	aload_1
	new	class scala/Tuple2
	dup
	aload_0
	getfield	Field key3:Ljava/lang/Object;
	aload_0
	getfield	Field value3:Ljava/lang/Object;
	invokespecial	Method scala/Tuple2."<init>":(Ljava/lang/Object;Ljava/lang/Object;)V
	invokeinterface	InterfaceMethod scala/Function1.apply:(Ljava/lang/Object;)Ljava/lang/Object;
	pop
	aload_1
	new	class scala/Tuple2
	dup
	aload_0
	getfield	Field key4:Ljava/lang/Object;
	aload_0
	getfield	Field value4:Ljava/lang/Object;
	invokespecial	Method scala/Tuple2."<init>":(Ljava/lang/Object;Ljava/lang/Object;)V
	invokeinterface	InterfaceMethod scala/Function1.apply:(Ljava/lang/Object;)Ljava/lang/Object;
	pop
	return
  Labels:
  LocalVariableTable: 
   Start  Length  Slot  Name   Signature
   0      89      0    this       Lscala/collection/immutable/Map$Map4;
   0      89      1    f       Lscala/Function1;

  Signature: length = 0x2
   00 FFFFFFE4 

public scala.collection.immutable.Map $minus(java.lang.Object);
  Signature: (Ljava/lang/Object;)Lscala/collection/immutable/Map;
  Code:
   Stack=8, Locals=6, Args_size=2
	aload_0
	getfield	Field key1:Ljava/lang/Object;
	astore_2
	aload_1
	aload_2
	if_acmpne	l1 // aload_1
	iconst_1
	goto	l2 // ifeq
l1	aload_1
	ifnonnull	l3 // aload_1
	iconst_0
	goto	l2 // ifeq
l3	aload_1
	instanceof	class java/lang/Number
	ifne	l4 // aload_1
	aload_1
	instanceof	class java/lang/Character
	ifeq	l5 // aload_1
l4	aload_1
	aload_2
	invokestatic	Method scala/runtime/BoxesRunTime.equals2:(Ljava/lang/Object;Ljava/lang/Object;)Z
	goto	l2 // ifeq
l5	aload_1
	aload_2
	invokevirtual	Method java/lang/Object.equals:(Ljava/lang/Object;)Z
l2	ifeq	l6 // aload_0
	new	class scala/collection/immutable/Map$Map3
	dup
	aload_0
	getfield	Field key2:Ljava/lang/Object;
	aload_0
	getfield	Field value2:Ljava/lang/Object;
	aload_0
	getfield	Field key3:Ljava/lang/Object;
	aload_0
	getfield	Field value3:Ljava/lang/Object;
	aload_0
	getfield	Field key4:Ljava/lang/Object;
	aload_0
	getfield	Field value4:Ljava/lang/Object;
	invokespecial	Method scala/collection/immutable/Map$Map3."<init>":(Ljava/lang/Object;Ljava/lang/Object;Ljava/lang/Object;Ljava/lang/Object;Ljava/lang/Object;Ljava/lang/Object;)V
	goto	l7 // areturn
l6	aload_0
	getfield	Field key2:Ljava/lang/Object;
	astore_3
	aload_1
	aload_3
	if_acmpne	l8 // aload_1
	iconst_1
	goto	l9 // ifeq
l8	aload_1
	ifnonnull	l10 // aload_1
	iconst_0
	goto	l9 // ifeq
l10	aload_1
	instanceof	class java/lang/Number
	ifne	l11 // aload_1
	aload_1
	instanceof	class java/lang/Character
	ifeq	l12 // aload_1
l11	aload_1
	aload_3
	invokestatic	Method scala/runtime/BoxesRunTime.equals2:(Ljava/lang/Object;Ljava/lang/Object;)Z
	goto	l9 // ifeq
l12	aload_1
	aload_3
	invokevirtual	Method java/lang/Object.equals:(Ljava/lang/Object;)Z
l9	ifeq	l13 // aload_0
	new	class scala/collection/immutable/Map$Map3
	dup
	aload_0
	getfield	Field key1:Ljava/lang/Object;
	aload_0
	getfield	Field value1:Ljava/lang/Object;
	aload_0
	getfield	Field key3:Ljava/lang/Object;
	aload_0
	getfield	Field value3:Ljava/lang/Object;
	aload_0
	getfield	Field key4:Ljava/lang/Object;
	aload_0
	getfield	Field value4:Ljava/lang/Object;
	invokespecial	Method scala/collection/immutable/Map$Map3."<init>":(Ljava/lang/Object;Ljava/lang/Object;Ljava/lang/Object;Ljava/lang/Object;Ljava/lang/Object;Ljava/lang/Object;)V
	goto	l7 // areturn
l13	aload_0
	getfield	Field key3:Ljava/lang/Object;
	astore	4
	aload_1
	aload	4
	if_acmpne	l14 // aload_1
	iconst_1
	goto	l15 // ifeq
l14	aload_1
	ifnonnull	l16 // aload_1
	iconst_0
	goto	l15 // ifeq
l16	aload_1
	instanceof	class java/lang/Number
	ifne	l17 // aload_1
	aload_1
	instanceof	class java/lang/Character
	ifeq	l18 // aload_1
l17	aload_1
	aload	4
	invokestatic	Method scala/runtime/BoxesRunTime.equals2:(Ljava/lang/Object;Ljava/lang/Object;)Z
	goto	l15 // ifeq
l18	aload_1
	aload	4
	invokevirtual	Method java/lang/Object.equals:(Ljava/lang/Object;)Z
l15	ifeq	l19 // aload_0
	new	class scala/collection/immutable/Map$Map3
	dup
	aload_0
	getfield	Field key1:Ljava/lang/Object;
	aload_0
	getfield	Field value1:Ljava/lang/Object;
	aload_0
	getfield	Field key2:Ljava/lang/Object;
	aload_0
	getfield	Field value2:Ljava/lang/Object;
	aload_0
	getfield	Field key4:Ljava/lang/Object;
	aload_0
	getfield	Field value4:Ljava/lang/Object;
	invokespecial	Method scala/collection/immutable/Map$Map3."<init>":(Ljava/lang/Object;Ljava/lang/Object;Ljava/lang/Object;Ljava/lang/Object;Ljava/lang/Object;Ljava/lang/Object;)V
	goto	l7 // areturn
l19	aload_0
	getfield	Field key4:Ljava/lang/Object;
	astore	5
	aload_1
	aload	5
	if_acmpne	l20 // aload_1
	iconst_1
	goto	l21 // ifeq
l20	aload_1
	ifnonnull	l22 // aload_1
	iconst_0
	goto	l21 // ifeq
l22	aload_1
	instanceof	class java/lang/Number
	ifne	l23 // aload_1
	aload_1
	instanceof	class java/lang/Character
	ifeq	l24 // aload_1
l23	aload_1
	aload	5
	invokestatic	Method scala/runtime/BoxesRunTime.equals2:(Ljava/lang/Object;Ljava/lang/Object;)Z
	goto	l21 // ifeq
l24	aload_1
	aload	5
	invokevirtual	Method java/lang/Object.equals:(Ljava/lang/Object;)Z
l21	ifeq	l25 // aload_0
	new	class scala/collection/immutable/Map$Map3
	dup
	aload_0
	getfield	Field key1:Ljava/lang/Object;
	aload_0
	getfield	Field value1:Ljava/lang/Object;
	aload_0
	getfield	Field key2:Ljava/lang/Object;
	aload_0
	getfield	Field value2:Ljava/lang/Object;
	aload_0
	getfield	Field key3:Ljava/lang/Object;
	aload_0
	getfield	Field value3:Ljava/lang/Object;
	invokespecial	Method scala/collection/immutable/Map$Map3."<init>":(Ljava/lang/Object;Ljava/lang/Object;Ljava/lang/Object;Ljava/lang/Object;Ljava/lang/Object;Ljava/lang/Object;)V
	goto	l7 // areturn
l25	aload_0
l7	areturn
  Labels:
   	l1 = 14 // aload_1
   	l3 = 22 // aload_1
   	l4 = 36 // aload_1
   	l5 = 44 // aload_1
   	l2 = 49 // ifeq
   	l6 = 86 // aload_0
   	l8 = 100 // aload_1
   	l10 = 108 // aload_1
   	l11 = 122 // aload_1
   	l12 = 130 // aload_1
   	l9 = 135 // ifeq
   	l13 = 172 // aload_0
   	l14 = 188 // aload_1
   	l16 = 196 // aload_1
   	l17 = 210 // aload_1
   	l18 = 219 // aload_1
   	l15 = 225 // ifeq
   	l19 = 262 // aload_0
   	l20 = 278 // aload_1
   	l22 = 286 // aload_1
   	l23 = 300 // aload_1
   	l24 = 309 // aload_1
   	l21 = 315 // ifeq
   	l25 = 352 // aload_0
   	l7 = 353 // areturn
  LocalVariableTable: 
   Start  Length  Slot  Name   Signature
   0      354      0    this       Lscala/collection/immutable/Map$Map4;
   0      354      1    key       Ljava/lang/Object;
   10      42      2    y0       Ljava/lang/Object;
   96      42      3    y1       Ljava/lang/Object;
   184      44      4    y2       Ljava/lang/Object;
   274      44      5    y3       Ljava/lang/Object;

  Signature: length = 0x2
   00 FFFFFFFC 

public scala.collection.immutable.Map $plus(scala.Tuple2);
  Signature: (Lscala/Tuple2;)Lscala/collection/immutable/Map;
  Code:
   Stack=3, Locals=2, Args_size=2
	aload_0
	aload_1
	invokevirtual	Method scala/Tuple2._1:()Ljava/lang/Object;
	aload_1
	invokevirtual	Method scala/Tuple2._2:()Ljava/lang/Object;
	invokevirtual	Method updated:(Ljava/lang/Object;Ljava/lang/Object;)Lscala/collection/immutable/Map;
	areturn
  Labels:
  LocalVariableTable: 
   Start  Length  Slot  Name   Signature
   0      13      0    this       Lscala/collection/immutable/Map$Map4;
   0      13      1    kv       Lscala/Tuple2;

  Signature: length = 0x2
   01 03 

public scala.collection.immutable.Map updated(java.lang.Object, java.lang.Object);
  Signature: (Ljava/lang/Object;Ljava/lang/Object;)Lscala/collection/immutable/Map;
  Code:
   Stack=11, Locals=7, Args_size=3
	aload_0
	getfield	Field key1:Ljava/lang/Object;
	astore_3
	aload_1
	aload_3
	if_acmpne	l1 // aload_1
	iconst_1
	goto	l2 // ifeq
l1	aload_1
	ifnonnull	l3 // aload_1
	iconst_0
	goto	l2 // ifeq
l3	aload_1
	instanceof	class java/lang/Number
	ifne	l4 // aload_1
	aload_1
	instanceof	class java/lang/Character
	ifeq	l5 // aload_1
l4	aload_1
	aload_3
	invokestatic	Method scala/runtime/BoxesRunTime.equals2:(Ljava/lang/Object;Ljava/lang/Object;)Z
	goto	l2 // ifeq
l5	aload_1
	aload_3
	invokevirtual	Method java/lang/Object.equals:(Ljava/lang/Object;)Z
l2	ifeq	l6 // aload_0
	new	class scala/collection/immutable/Map$Map4
	dup
	aload_0
	getfield	Field key1:Ljava/lang/Object;
	aload_2
	aload_0
	getfield	Field key2:Ljava/lang/Object;
	aload_0
	getfield	Field value2:Ljava/lang/Object;
	aload_0
	getfield	Field key3:Ljava/lang/Object;
	aload_0
	getfield	Field value3:Ljava/lang/Object;
	aload_0
	getfield	Field key4:Ljava/lang/Object;
	aload_0
	getfield	Field value4:Ljava/lang/Object;
	invokespecial	Method "<init>":(Ljava/lang/Object;Ljava/lang/Object;Ljava/lang/Object;Ljava/lang/Object;Ljava/lang/Object;Ljava/lang/Object;Ljava/lang/Object;Ljava/lang/Object;)V
	goto	l7 // areturn
l6	aload_0
	getfield	Field key2:Ljava/lang/Object;
	astore	4
	aload_1
	aload	4
	if_acmpne	l8 // aload_1
	iconst_1
	goto	l9 // ifeq
l8	aload_1
	ifnonnull	l10 // aload_1
	iconst_0
	goto	l9 // ifeq
l10	aload_1
	instanceof	class java/lang/Number
	ifne	l11 // aload_1
	aload_1
	instanceof	class java/lang/Character
	ifeq	l12 // aload_1
l11	aload_1
	aload	4
	invokestatic	Method scala/runtime/BoxesRunTime.equals2:(Ljava/lang/Object;Ljava/lang/Object;)Z
	goto	l9 // ifeq
l12	aload_1
	aload	4
	invokevirtual	Method java/lang/Object.equals:(Ljava/lang/Object;)Z
l9	ifeq	l13 // aload_0
	new	class scala/collection/immutable/Map$Map4
	dup
	aload_0
	getfield	Field key1:Ljava/lang/Object;
	aload_0
	getfield	Field value1:Ljava/lang/Object;
	aload_0
	getfield	Field key2:Ljava/lang/Object;
	aload_2
	aload_0
	getfield	Field key3:Ljava/lang/Object;
	aload_0
	getfield	Field value3:Ljava/lang/Object;
	aload_0
	getfield	Field key4:Ljava/lang/Object;
	aload_0
	getfield	Field value4:Ljava/lang/Object;
	invokespecial	Method "<init>":(Ljava/lang/Object;Ljava/lang/Object;Ljava/lang/Object;Ljava/lang/Object;Ljava/lang/Object;Ljava/lang/Object;Ljava/lang/Object;Ljava/lang/Object;)V
	goto	l7 // areturn
l13	aload_0
	getfield	Field key3:Ljava/lang/Object;
	astore	5
	aload_1
	aload	5
	if_acmpne	l14 // aload_1
	iconst_1
	goto	l15 // ifeq
l14	aload_1
	ifnonnull	l16 // aload_1
	iconst_0
	goto	l15 // ifeq
l16	aload_1
	instanceof	class java/lang/Number
	ifne	l17 // aload_1
	aload_1
	instanceof	class java/lang/Character
	ifeq	l18 // aload_1
l17	aload_1
	aload	5
	invokestatic	Method scala/runtime/BoxesRunTime.equals2:(Ljava/lang/Object;Ljava/lang/Object;)Z
	goto	l15 // ifeq
l18	aload_1
	aload	5
	invokevirtual	Method java/lang/Object.equals:(Ljava/lang/Object;)Z
l15	ifeq	l19 // aload_0
	new	class scala/collection/immutable/Map$Map4
	dup
	aload_0
	getfield	Field key1:Ljava/lang/Object;
	aload_0
	getfield	Field value1:Ljava/lang/Object;
	aload_0
	getfield	Field key2:Ljava/lang/Object;
	aload_0
	getfield	Field value2:Ljava/lang/Object;
	aload_0
	getfield	Field key3:Ljava/lang/Object;
	aload_2
	aload_0
	getfield	Field key4:Ljava/lang/Object;
	aload_0
	getfield	Field value4:Ljava/lang/Object;
	invokespecial	Method "<init>":(Ljava/lang/Object;Ljava/lang/Object;Ljava/lang/Object;Ljava/lang/Object;Ljava/lang/Object;Ljava/lang/Object;Ljava/lang/Object;Ljava/lang/Object;)V
	goto	l7 // areturn
l19	aload_0
	getfield	Field key4:Ljava/lang/Object;
	astore	6
	aload_1
	aload	6
	if_acmpne	l20 // aload_1
	iconst_1
	goto	l21 // ifeq
l20	aload_1
	ifnonnull	l22 // aload_1
	iconst_0
	goto	l21 // ifeq
l22	aload_1
	instanceof	class java/lang/Number
	ifne	l23 // aload_1
	aload_1
	instanceof	class java/lang/Character
	ifeq	l24 // aload_1
l23	aload_1
	aload	6
	invokestatic	Method scala/runtime/BoxesRunTime.equals2:(Ljava/lang/Object;Ljava/lang/Object;)Z
	goto	l21 // ifeq
l24	aload_1
	aload	6
	invokevirtual	Method java/lang/Object.equals:(Ljava/lang/Object;)Z
l21	ifeq	l25 // new
	new	class scala/collection/immutable/Map$Map4
	dup
	aload_0
	getfield	Field key1:Ljava/lang/Object;
	aload_0
	getfield	Field value1:Ljava/lang/Object;
	aload_0
	getfield	Field key2:Ljava/lang/Object;
	aload_0
	getfield	Field value2:Ljava/lang/Object;
	aload_0
	getfield	Field key3:Ljava/lang/Object;
	aload_0
	getfield	Field value3:Ljava/lang/Object;
	aload_0
	getfield	Field key4:Ljava/lang/Object;
	aload_2
	invokespecial	Method "<init>":(Ljava/lang/Object;Ljava/lang/Object;Ljava/lang/Object;Ljava/lang/Object;Ljava/lang/Object;Ljava/lang/Object;Ljava/lang/Object;Ljava/lang/Object;)V
	goto	l7 // areturn
l25	new	class scala/collection/immutable/HashMap
	dup
	invokespecial	Method scala/collection/immutable/HashMap."<init>":()V
	new	class scala/Tuple2
	dup
	aload_0
	getfield	Field key1:Ljava/lang/Object;
	aload_0
	getfield	Field value1:Ljava/lang/Object;
	invokespecial	Method scala/Tuple2."<init>":(Ljava/lang/Object;Ljava/lang/Object;)V
	new	class scala/Tuple2
	dup
	aload_0
	getfield	Field key2:Ljava/lang/Object;
	aload_0
	getfield	Field value2:Ljava/lang/Object;
	invokespecial	Method scala/Tuple2."<init>":(Ljava/lang/Object;Ljava/lang/Object;)V
	getstatic	Field scala/Predef$.MODULE$:Lscala/Predef$;
	iconst_3
	anewarray	class scala/Tuple2
	dup
	iconst_0
	new	class scala/Tuple2
	dup
	aload_0
	getfield	Field key3:Ljava/lang/Object;
	aload_0
	getfield	Field value3:Ljava/lang/Object;
	invokespecial	Method scala/Tuple2."<init>":(Ljava/lang/Object;Ljava/lang/Object;)V
	aastore
	dup
	iconst_1
	new	class scala/Tuple2
	dup
	aload_0
	getfield	Field key4:Ljava/lang/Object;
	aload_0
	getfield	Field value4:Ljava/lang/Object;
	invokespecial	Method scala/Tuple2."<init>":(Ljava/lang/Object;Ljava/lang/Object;)V
	aastore
	dup
	iconst_2
	new	class scala/Tuple2
	dup
	aload_1
	aload_2
	invokespecial	Method scala/Tuple2."<init>":(Ljava/lang/Object;Ljava/lang/Object;)V
	aastore
	checkcast	class "[Ljava/lang/Object;"
	invokevirtual	Method scala/Predef$.wrapRefArray:([Ljava/lang/Object;)Lscala/collection/mutable/WrappedArray;
	invokevirtual	Method scala/collection/immutable/HashMap.$plus:(Lscala/Tuple2;Lscala/Tuple2;Lscala/collection/Seq;)Lscala/collection/immutable/HashMap;
l7	areturn
  Labels:
   	l1 = 14 // aload_1
   	l3 = 22 // aload_1
   	l4 = 36 // aload_1
   	l5 = 44 // aload_1
   	l2 = 49 // ifeq
   	l6 = 91 // aload_0
   	l8 = 107 // aload_1
   	l10 = 115 // aload_1
   	l11 = 129 // aload_1
   	l12 = 138 // aload_1
   	l9 = 144 // ifeq
   	l13 = 186 // aload_0
   	l14 = 202 // aload_1
   	l16 = 210 // aload_1
   	l17 = 224 // aload_1
   	l18 = 233 // aload_1
   	l15 = 239 // ifeq
   	l19 = 281 // aload_0
   	l20 = 297 // aload_1
   	l22 = 305 // aload_1
   	l23 = 319 // aload_1
   	l24 = 328 // aload_1
   	l21 = 334 // ifeq
   	l25 = 376 // new
   	l7 = 477 // areturn
  LocalVariableTable: 
   Start  Length  Slot  Name   Signature
   0      478      0    this       Lscala/collection/immutable/Map$Map4;
   0      478      1    key       Ljava/lang/Object;
   0      478      2    value       Ljava/lang/Object;
   10      42      3    y0       Ljava/lang/Object;
   103      44      4    y1       Ljava/lang/Object;
   198      44      5    y2       Ljava/lang/Object;
   293      44      6    y3       Ljava/lang/Object;

  Signature: length = 0x2
   01 18 

public scala.collection.Iterator iterator();
  Signature: ()Lscala/collection/Iterator;
  Code:
   Stack=9, Locals=1, Args_size=1
	getstatic	Field scala/collection/Iterator$.MODULE$:Lscala/collection/Iterator$;
	getstatic	Field scala/Predef$.MODULE$:Lscala/Predef$;
	iconst_4
	anewarray	class scala/Tuple2
	dup
	iconst_0
	new	class scala/Tuple2
	dup
	aload_0
	getfield	Field key1:Ljava/lang/Object;
	aload_0
	getfield	Field value1:Ljava/lang/Object;
	invokespecial	Method scala/Tuple2."<init>":(Ljava/lang/Object;Ljava/lang/Object;)V
	aastore
	dup
	iconst_1
	new	class scala/Tuple2
	dup
	aload_0
	getfield	Field key2:Ljava/lang/Object;
	aload_0
	getfield	Field value2:Ljava/lang/Object;
	invokespecial	Method scala/Tuple2."<init>":(Ljava/lang/Object;Ljava/lang/Object;)V
	aastore
	dup
	iconst_2
	new	class scala/Tuple2
	dup
	aload_0
	getfield	Field key3:Ljava/lang/Object;
	aload_0
	getfield	Field value3:Ljava/lang/Object;
	invokespecial	Method scala/Tuple2."<init>":(Ljava/lang/Object;Ljava/lang/Object;)V
	aastore
	dup
	iconst_3
	new	class scala/Tuple2
	dup
	aload_0
	getfield	Field key4:Ljava/lang/Object;
	aload_0
	getfield	Field value4:Ljava/lang/Object;
	invokespecial	Method scala/Tuple2."<init>":(Ljava/lang/Object;Ljava/lang/Object;)V
	aastore
	checkcast	class "[Ljava/lang/Object;"
	invokevirtual	Method scala/Predef$.wrapRefArray:([Ljava/lang/Object;)Lscala/collection/mutable/WrappedArray;
	invokevirtual	Method scala/collection/Iterator$.apply:(Lscala/collection/Seq;)Lscala/collection/Iterator;
	areturn
  Labels:
  Signature: length = 0x2
   01 23 

public scala.Option get(java.lang.Object);
  Signature: (Ljava/lang/Object;)Lscala/Option;
  Code:
   Stack=3, Locals=6, Args_size=2
	aload_0
	getfield	Field key1:Ljava/lang/Object;
	astore_2
	aload_1
	aload_2
	if_acmpne	l1 // aload_1
	iconst_1
	goto	l2 // ifeq
l1	aload_1
	ifnonnull	l3 // aload_1
	iconst_0
	goto	l2 // ifeq
l3	aload_1
	instanceof	class java/lang/Number
	ifne	l4 // aload_1
	aload_1
	instanceof	class java/lang/Character
	ifeq	l5 // aload_1
l4	aload_1
	aload_2
	invokestatic	Method scala/runtime/BoxesRunTime.equals2:(Ljava/lang/Object;Ljava/lang/Object;)Z
	goto	l2 // ifeq
l5	aload_1
	aload_2
	invokevirtual	Method java/lang/Object.equals:(Ljava/lang/Object;)Z
l2	ifeq	l6 // aload_0
	new	class scala/Some
	dup
	aload_0
	getfield	Field value1:Ljava/lang/Object;
	invokespecial	Method scala/Some."<init>":(Ljava/lang/Object;)V
	goto	l7 // areturn
l6	aload_0
	getfield	Field key2:Ljava/lang/Object;
	astore_3
	aload_1
	aload_3
	if_acmpne	l8 // aload_1
	iconst_1
	goto	l9 // ifeq
l8	aload_1
	ifnonnull	l10 // aload_1
	iconst_0
	goto	l9 // ifeq
l10	aload_1
	instanceof	class java/lang/Number
	ifne	l11 // aload_1
	aload_1
	instanceof	class java/lang/Character
	ifeq	l12 // aload_1
l11	aload_1
	aload_3
	invokestatic	Method scala/runtime/BoxesRunTime.equals2:(Ljava/lang/Object;Ljava/lang/Object;)Z
	goto	l9 // ifeq
l12	aload_1
	aload_3
	invokevirtual	Method java/lang/Object.equals:(Ljava/lang/Object;)Z
l9	ifeq	l13 // aload_0
	new	class scala/Some
	dup
	aload_0
	getfield	Field value2:Ljava/lang/Object;
	invokespecial	Method scala/Some."<init>":(Ljava/lang/Object;)V
	goto	l7 // areturn
l13	aload_0
	getfield	Field key3:Ljava/lang/Object;
	astore	4
	aload_1
	aload	4
	if_acmpne	l14 // aload_1
	iconst_1
	goto	l15 // ifeq
l14	aload_1
	ifnonnull	l16 // aload_1
	iconst_0
	goto	l15 // ifeq
l16	aload_1
	instanceof	class java/lang/Number
	ifne	l17 // aload_1
	aload_1
	instanceof	class java/lang/Character
	ifeq	l18 // aload_1
l17	aload_1
	aload	4
	invokestatic	Method scala/runtime/BoxesRunTime.equals2:(Ljava/lang/Object;Ljava/lang/Object;)Z
	goto	l15 // ifeq
l18	aload_1
	aload	4
	invokevirtual	Method java/lang/Object.equals:(Ljava/lang/Object;)Z
l15	ifeq	l19 // aload_0
	new	class scala/Some
	dup
	aload_0
	getfield	Field value3:Ljava/lang/Object;
	invokespecial	Method scala/Some."<init>":(Ljava/lang/Object;)V
	goto	l7 // areturn
l19	aload_0
	getfield	Field key4:Ljava/lang/Object;
	astore	5
	aload_1
	aload	5
	if_acmpne	l20 // aload_1
	iconst_1
	goto	l21 // ifeq
l20	aload_1
	ifnonnull	l22 // aload_1
	iconst_0
	goto	l21 // ifeq
l22	aload_1
	instanceof	class java/lang/Number
	ifne	l23 // aload_1
	aload_1
	instanceof	class java/lang/Character
	ifeq	l24 // aload_1
l23	aload_1
	aload	5
	invokestatic	Method scala/runtime/BoxesRunTime.equals2:(Ljava/lang/Object;Ljava/lang/Object;)Z
	goto	l21 // ifeq
l24	aload_1
	aload	5
	invokevirtual	Method java/lang/Object.equals:(Ljava/lang/Object;)Z
l21	ifeq	l25 // getstatic
	new	class scala/Some
	dup
	aload_0
	getfield	Field value4:Ljava/lang/Object;
	invokespecial	Method scala/Some."<init>":(Ljava/lang/Object;)V
	goto	l7 // areturn
l25	getstatic	Field scala/None$.MODULE$:Lscala/None$;
l7	areturn
  Labels:
   	l1 = 14 // aload_1
   	l3 = 22 // aload_1
   	l4 = 36 // aload_1
   	l5 = 44 // aload_1
   	l2 = 49 // ifeq
   	l6 = 66 // aload_0
   	l8 = 80 // aload_1
   	l10 = 88 // aload_1
   	l11 = 102 // aload_1
   	l12 = 110 // aload_1
   	l9 = 115 // ifeq
   	l13 = 132 // aload_0
   	l14 = 148 // aload_1
   	l16 = 156 // aload_1
   	l17 = 170 // aload_1
   	l18 = 179 // aload_1
   	l15 = 185 // ifeq
   	l19 = 202 // aload_0
   	l20 = 218 // aload_1
   	l22 = 226 // aload_1
   	l23 = 240 // aload_1
   	l24 = 249 // aload_1
   	l21 = 255 // ifeq
   	l25 = 272 // getstatic
   	l7 = 275 // areturn
  LocalVariableTable: 
   Start  Length  Slot  Name   Signature
   0      276      0    this       Lscala/collection/immutable/Map$Map4;
   0      276      1    key       Ljava/lang/Object;
   10      42      2    y0       Ljava/lang/Object;
   76      42      3    y1       Ljava/lang/Object;
   144      44      4    y2       Ljava/lang/Object;
   214      44      5    y3       Ljava/lang/Object;

  Signature: length = 0x2
   01 30 

public int size();
  Signature: ()I
  Code:
   Stack=1, Locals=1, Args_size=1
	iconst_4
	ireturn
  Labels:

public scala.collection.TraversableLike$WithFilter withFilter(scala.Function1);
  Signature: (Lscala/Function1;)Lscala/collection/TraversableLike$WithFilter;
  Code:
   Stack=2, Locals=2, Args_size=2
	aload_0
	aload_1
	invokestatic	Method scala/collection/TraversableLike$class.withFilter:(Lscala/collection/TraversableLike;Lscala/Function1;)Lscala/collection/TraversableLike$WithFilter;
	areturn
  Labels:
  LocalVariableTable: 
   Start  Length  Slot  Name   Signature
   0      6      0    this       Lscala/collection/immutable/Map$Map4;
   0      6      1    p       Lscala/Function1;

  Signature: length = 0x2
   01 34 

public scala.collection.mutable.StringBuilder addString(scala.collection.mutable.StringBuilder);
  Signature: (Lscala/collection/mutable/StringBuilder;)Lscala/collection/mutable/StringBuilder;
  Code:
   Stack=2, Locals=2, Args_size=2
	aload_0
	aload_1
	invokestatic	Method scala/collection/TraversableLike$class.addString:(Lscala/collection/TraversableLike;Lscala/collection/mutable/StringBuilder;)Lscala/collection/mutable/StringBuilder;
	areturn
  Labels:
  LocalVariableTable: 
   Start  Length  Slot  Name   Signature
   0      6      0    this       Lscala/collection/immutable/Map$Map4;
   0      6      1    b       Lscala/collection/mutable/StringBuilder;


public scala.collection.mutable.StringBuilder addString(scala.collection.mutable.StringBuilder, java.lang.String);
  Signature: (Lscala/collection/mutable/StringBuilder;Ljava/lang/String;)Lscala/collection/mutable/StringBuilder;
  Code:
   Stack=3, Locals=3, Args_size=3
	aload_0
	aload_1
	aload_2
	invokestatic	Method scala/collection/TraversableLike$class.addString:(Lscala/collection/TraversableLike;Lscala/collection/mutable/StringBuilder;Ljava/lang/String;)Lscala/collection/mutable/StringBuilder;
	areturn
  Labels:
  LocalVariableTable: 
   Start  Length  Slot  Name   Signature
   0      7      0    this       Lscala/collection/immutable/Map$Map4;
   0      7      1    b       Lscala/collection/mutable/StringBuilder;
   0      7      2    sep       Ljava/lang/String;


public java.lang.String mkString();
  Signature: ()Ljava/lang/String;
  Code:
   Stack=1, Locals=1, Args_size=1
	aload_0
	invokestatic	Method scala/collection/TraversableLike$class.mkString:(Lscala/collection/TraversableLike;)Ljava/lang/String;
	areturn
  Labels:

public java.lang.String mkString(java.lang.String);
  Signature: (Ljava/lang/String;)Ljava/lang/String;
  Code:
   Stack=2, Locals=2, Args_size=2
	aload_0
	aload_1
	invokestatic	Method scala/collection/TraversableLike$class.mkString:(Lscala/collection/TraversableLike;Ljava/lang/String;)Ljava/lang/String;
	areturn
  Labels:
  LocalVariableTable: 
   Start  Length  Slot  Name   Signature
   0      6      0    this       Lscala/collection/immutable/Map$Map4;
   0      6      1    sep       Ljava/lang/String;


public java.lang.String mkString(java.lang.String, java.lang.String, java.lang.String);
  Signature: (Ljava/lang/String;Ljava/lang/String;Ljava/lang/String;)Ljava/lang/String;
  Code:
   Stack=4, Locals=4, Args_size=4
	aload_0
	aload_1
	aload_2
	aload_3
	invokestatic	Method scala/collection/TraversableLike$class.mkString:(Lscala/collection/TraversableLike;Ljava/lang/String;Ljava/lang/String;Ljava/lang/String;)Ljava/lang/String;
	areturn
  Labels:
  LocalVariableTable: 
   Start  Length  Slot  Name   Signature
   0      8      0    this       Lscala/collection/immutable/Map$Map4;
   0      8      1    start       Ljava/lang/String;
   0      8      2    sep       Ljava/lang/String;
   0      8      3    end       Ljava/lang/String;


public scala.collection.immutable.Map toMap(scala.Predef$$less$colon$less);
  Signature: (Lscala/Predef$$less$colon$less;)Lscala/collection/immutable/Map;
  Code:
   Stack=2, Locals=2, Args_size=2
	aload_0
	aload_1
	invokestatic	Method scala/collection/TraversableLike$class.toMap:(Lscala/collection/TraversableLike;Lscala/Predef$$less$colon$less;)Lscala/collection/immutable/Map;
	areturn
  Labels:
  LocalVariableTable: 
   Start  Length  Slot  Name   Signature
   0      6      0    this       Lscala/collection/immutable/Map$Map4;
   0      6      1    ev       Lscala/Predef$$less$colon$less;


public scala.collection.immutable.Set toSet();
  Signature: ()Lscala/collection/immutable/Set;
  Code:
   Stack=1, Locals=1, Args_size=1
	aload_0
	invokestatic	Method scala/collection/TraversableLike$class.toSet:(Lscala/collection/TraversableLike;)Lscala/collection/immutable/Set;
	areturn
  Labels:

public scala.collection.mutable.IndexedSeq toIndexedSeq();
  Signature: ()Lscala/collection/mutable/IndexedSeq;
  Code:
   Stack=1, Locals=1, Args_size=1
	aload_0
	invokestatic	Method scala/collection/TraversableLike$class.toIndexedSeq:(Lscala/collection/TraversableLike;)Lscala/collection/mutable/IndexedSeq;
	areturn
  Labels:

public scala.collection.Seq toSeq();
  Signature: ()Lscala/collection/Seq;
  Code:
   Stack=1, Locals=1, Args_size=1
	aload_0
	invokestatic	Method scala/collection/TraversableLike$class.toSeq:(Lscala/collection/TraversableLike;)Lscala/collection/Seq;
	areturn
  Labels:

public scala.collection.immutable.List toList();
  Signature: ()Lscala/collection/immutable/List;
  Code:
   Stack=1, Locals=1, Args_size=1
	aload_0
	invokestatic	Method scala/collection/TraversableLike$class.toList:(Lscala/collection/TraversableLike;)Lscala/collection/immutable/List;
	areturn
  Labels:

public java.lang.Object toArray(scala.reflect.ClassManifest);
  Signature: (Lscala/reflect/ClassManifest;)Ljava/lang/Object;
  Code:
   Stack=2, Locals=2, Args_size=2
	aload_0
	aload_1
	invokestatic	Method scala/collection/TraversableLike$class.toArray:(Lscala/collection/TraversableLike;Lscala/reflect/ClassManifest;)Ljava/lang/Object;
	areturn
  Labels:
  LocalVariableTable: 
   Start  Length  Slot  Name   Signature
   0      6      0    this       Lscala/collection/immutable/Map$Map4;
   0      6      1    evidence$1       Lscala/reflect/ClassManifest;


public void copyToArray(java.lang.Object);
  Signature: (Ljava/lang/Object;)V
  Code:
   Stack=2, Locals=2, Args_size=2
	aload_0
	aload_1
	invokestatic	Method scala/collection/TraversableLike$class.copyToArray:(Lscala/collection/TraversableLike;Ljava/lang/Object;)V
	return
  Labels:
  LocalVariableTable: 
   Start  Length  Slot  Name   Signature
   0      6      0    this       Lscala/collection/immutable/Map$Map4;
   0      6      1    xs       Ljava/lang/Object;


public void copyToArray(java.lang.Object, int);
  Signature: (Ljava/lang/Object;I)V
  Code:
   Stack=3, Locals=3, Args_size=3
	aload_0
	aload_1
	iload_2
	invokestatic	Method scala/collection/TraversableLike$class.copyToArray:(Lscala/collection/TraversableLike;Ljava/lang/Object;I)V
	return
  Labels:
  LocalVariableTable: 
   Start  Length  Slot  Name   Signature
   0      7      0    this       Lscala/collection/immutable/Map$Map4;
   0      7      1    xs       Ljava/lang/Object;
   0      7      2    start       I


public void copyToBuffer(scala.collection.mutable.Buffer);
  Signature: (Lscala/collection/mutable/Buffer;)V
  Code:
   Stack=2, Locals=2, Args_size=2
	aload_0
	aload_1
	invokestatic	Method scala/collection/TraversableLike$class.copyToBuffer:(Lscala/collection/TraversableLike;Lscala/collection/mutable/Buffer;)V
	return
  Labels:
  LocalVariableTable: 
   Start  Length  Slot  Name   Signature
   0      6      0    this       Lscala/collection/immutable/Map$Map4;
   0      6      1    dest       Lscala/collection/mutable/Buffer;


public scala.Tuple2 splitAt(int);
  Signature: (I)Lscala/Tuple2;
  Code:
   Stack=2, Locals=2, Args_size=2
	aload_0
	iload_1
	invokestatic	Method scala/collection/TraversableLike$class.splitAt:(Lscala/collection/TraversableLike;I)Lscala/Tuple2;
	areturn
  Labels:
  LocalVariableTable: 
   Start  Length  Slot  Name   Signature
   0      6      0    this       Lscala/collection/immutable/Map$Map4;
   0      6      1    n       I


public scala.Tuple2 span(scala.Function1);
  Signature: (Lscala/Function1;)Lscala/Tuple2;
  Code:
   Stack=2, Locals=2, Args_size=2
	aload_0
	aload_1
	invokestatic	Method scala/collection/TraversableLike$class.span:(Lscala/collection/TraversableLike;Lscala/Function1;)Lscala/Tuple2;
	areturn
  Labels:
  LocalVariableTable: 
   Start  Length  Slot  Name   Signature
   0      6      0    this       Lscala/collection/immutable/Map$Map4;
   0      6      1    p       Lscala/Function1;


public java.lang.Object dropWhile(scala.Function1);
  Signature: (Lscala/Function1;)Ljava/lang/Object;
  Code:
   Stack=2, Locals=2, Args_size=2
	aload_0
	aload_1
	invokestatic	Method scala/collection/TraversableLike$class.dropWhile:(Lscala/collection/TraversableLike;Lscala/Function1;)Ljava/lang/Object;
	areturn
  Labels:
  LocalVariableTable: 
   Start  Length  Slot  Name   Signature
   0      6      0    this       Lscala/collection/immutable/Map$Map4;
   0      6      1    p       Lscala/Function1;


public java.lang.Object drop(int);
  Signature: (I)Ljava/lang/Object;
  Code:
   Stack=2, Locals=2, Args_size=2
	aload_0
	iload_1
	invokestatic	Method scala/collection/TraversableLike$class.drop:(Lscala/collection/TraversableLike;I)Ljava/lang/Object;
	areturn
  Labels:
  LocalVariableTable: 
   Start  Length  Slot  Name   Signature
   0      6      0    this       Lscala/collection/immutable/Map$Map4;
   0      6      1    n       I


public java.lang.Object init();
  Signature: ()Ljava/lang/Object;
  Code:
   Stack=1, Locals=1, Args_size=1
	aload_0
	invokestatic	Method scala/collection/TraversableLike$class.init:(Lscala/collection/TraversableLike;)Ljava/lang/Object;
	areturn
  Labels:

public scala.Option lastOption();
  Signature: ()Lscala/Option;
  Code:
   Stack=1, Locals=1, Args_size=1
	aload_0
	invokestatic	Method scala/collection/TraversableLike$class.lastOption:(Lscala/collection/TraversableLike;)Lscala/Option;
	areturn
  Labels:

public java.lang.Object last();
  Signature: ()Ljava/lang/Object;
  Code:
   Stack=1, Locals=1, Args_size=1
	aload_0
	invokestatic	Method scala/collection/TraversableLike$class.last:(Lscala/collection/TraversableLike;)Ljava/lang/Object;
	areturn
  Labels:

public java.lang.Object tail();
  Signature: ()Ljava/lang/Object;
  Code:
   Stack=1, Locals=1, Args_size=1
	aload_0
	invokestatic	Method scala/collection/TraversableLike$class.tail:(Lscala/collection/TraversableLike;)Ljava/lang/Object;
	areturn
  Labels:

public scala.Option headOption();
  Signature: ()Lscala/Option;
  Code:
   Stack=1, Locals=1, Args_size=1
	aload_0
	invokestatic	Method scala/collection/TraversableLike$class.headOption:(Lscala/collection/TraversableLike;)Lscala/Option;
	areturn
  Labels:

public java.lang.Object max(scala.math.Ordering);
  Signature: (Lscala/math/Ordering;)Ljava/lang/Object;
  Code:
   Stack=2, Locals=2, Args_size=2
	aload_0
	aload_1
	invokestatic	Method scala/collection/TraversableLike$class.max:(Lscala/collection/TraversableLike;Lscala/math/Ordering;)Ljava/lang/Object;
	areturn
  Labels:
  LocalVariableTable: 
   Start  Length  Slot  Name   Signature
   0      6      0    this       Lscala/collection/immutable/Map$Map4;
   0      6      1    cmp       Lscala/math/Ordering;


public java.lang.Object min(scala.math.Ordering);
  Signature: (Lscala/math/Ordering;)Ljava/lang/Object;
  Code:
   Stack=2, Locals=2, Args_size=2
	aload_0
	aload_1
	invokestatic	Method scala/collection/TraversableLike$class.min:(Lscala/collection/TraversableLike;Lscala/math/Ordering;)Ljava/lang/Object;
	areturn
  Labels:
  LocalVariableTable: 
   Start  Length  Slot  Name   Signature
   0      6      0    this       Lscala/collection/immutable/Map$Map4;
   0      6      1    cmp       Lscala/math/Ordering;


public java.lang.Object product(scala.math.Numeric);
  Signature: (Lscala/math/Numeric;)Ljava/lang/Object;
  Code:
   Stack=2, Locals=2, Args_size=2
	aload_0
	aload_1
	invokestatic	Method scala/collection/TraversableLike$class.product:(Lscala/collection/TraversableLike;Lscala/math/Numeric;)Ljava/lang/Object;
	areturn
  Labels:
  LocalVariableTable: 
   Start  Length  Slot  Name   Signature
   0      6      0    this       Lscala/collection/immutable/Map$Map4;
   0      6      1    num       Lscala/math/Numeric;


public java.lang.Object sum(scala.math.Numeric);
  Signature: (Lscala/math/Numeric;)Ljava/lang/Object;
  Code:
   Stack=2, Locals=2, Args_size=2
	aload_0
	aload_1
	invokestatic	Method scala/collection/TraversableLike$class.sum:(Lscala/collection/TraversableLike;Lscala/math/Numeric;)Ljava/lang/Object;
	areturn
  Labels:
  LocalVariableTable: 
   Start  Length  Slot  Name   Signature
   0      6      0    this       Lscala/collection/immutable/Map$Map4;
   0      6      1    num       Lscala/math/Numeric;


public scala.Option reduceRightOption(scala.Function2);
  Signature: (Lscala/Function2;)Lscala/Option;
  Code:
   Stack=2, Locals=2, Args_size=2
	aload_0
	aload_1
	invokestatic	Method scala/collection/TraversableLike$class.reduceRightOption:(Lscala/collection/TraversableLike;Lscala/Function2;)Lscala/Option;
	areturn
  Labels:
  LocalVariableTable: 
   Start  Length  Slot  Name   Signature
   0      6      0    this       Lscala/collection/immutable/Map$Map4;
   0      6      1    op       Lscala/Function2;


public scala.Option reduceLeftOption(scala.Function2);
  Signature: (Lscala/Function2;)Lscala/Option;
  Code:
   Stack=2, Locals=2, Args_size=2
	aload_0
	aload_1
	invokestatic	Method scala/collection/TraversableLike$class.reduceLeftOption:(Lscala/collection/TraversableLike;Lscala/Function2;)Lscala/Option;
	areturn
  Labels:
  LocalVariableTable: 
   Start  Length  Slot  Name   Signature
   0      6      0    this       Lscala/collection/immutable/Map$Map4;
   0      6      1    op       Lscala/Function2;


public java.lang.Object reduceLeft(scala.Function2);
  Signature: (Lscala/Function2;)Ljava/lang/Object;
  Code:
   Stack=2, Locals=2, Args_size=2
	aload_0
	aload_1
	invokestatic	Method scala/collection/TraversableLike$class.reduceLeft:(Lscala/collection/TraversableLike;Lscala/Function2;)Ljava/lang/Object;
	areturn
  Labels:
  LocalVariableTable: 
   Start  Length  Slot  Name   Signature
   0      6      0    this       Lscala/collection/immutable/Map$Map4;
   0      6      1    op       Lscala/Function2;


public java.lang.Object $colon$bslash(java.lang.Object, scala.Function2);
  Signature: (Ljava/lang/Object;Lscala/Function2;)Ljava/lang/Object;
  Code:
   Stack=3, Locals=3, Args_size=3
	aload_0
	aload_1
	aload_2
	invokestatic	Method scala/collection/TraversableLike$class.$colon$bslash:(Lscala/collection/TraversableLike;Ljava/lang/Object;Lscala/Function2;)Ljava/lang/Object;
	areturn
  Labels:
  LocalVariableTable: 
   Start  Length  Slot  Name   Signature
   0      7      0    this       Lscala/collection/immutable/Map$Map4;
   0      7      1    z       Ljava/lang/Object;
   0      7      2    op       Lscala/Function2;


public java.lang.Object $div$colon(java.lang.Object, scala.Function2);
  Signature: (Ljava/lang/Object;Lscala/Function2;)Ljava/lang/Object;
  Code:
   Stack=3, Locals=3, Args_size=3
	aload_0
	aload_1
	aload_2
	invokestatic	Method scala/collection/TraversableLike$class.$div$colon:(Lscala/collection/TraversableLike;Ljava/lang/Object;Lscala/Function2;)Ljava/lang/Object;
	areturn
  Labels:
  LocalVariableTable: 
   Start  Length  Slot  Name   Signature
   0      7      0    this       Lscala/collection/immutable/Map$Map4;
   0      7      1    z       Ljava/lang/Object;
   0      7      2    op       Lscala/Function2;


public java.lang.Object foldLeft(java.lang.Object, scala.Function2);
  Signature: (Ljava/lang/Object;Lscala/Function2;)Ljava/lang/Object;
  Code:
   Stack=3, Locals=3, Args_size=3
	aload_0
	aload_1
	aload_2
	invokestatic	Method scala/collection/TraversableLike$class.foldLeft:(Lscala/collection/TraversableLike;Ljava/lang/Object;Lscala/Function2;)Ljava/lang/Object;
	areturn
  Labels:
  LocalVariableTable: 
   Start  Length  Slot  Name   Signature
   0      7      0    this       Lscala/collection/immutable/Map$Map4;
   0      7      1    z       Ljava/lang/Object;
   0      7      2    op       Lscala/Function2;


public int count(scala.Function1);
  Signature: (Lscala/Function1;)I
  Code:
   Stack=2, Locals=2, Args_size=2
	aload_0
	aload_1
	invokestatic	Method scala/collection/TraversableLike$class.count:(Lscala/collection/TraversableLike;Lscala/Function1;)I
	ireturn
  Labels:
  LocalVariableTable: 
   Start  Length  Slot  Name   Signature
   0      6      0    this       Lscala/collection/immutable/Map$Map4;
   0      6      1    p       Lscala/Function1;


public scala.collection.Map groupBy(scala.Function1);
  Signature: (Lscala/Function1;)Lscala/collection/Map;
  Code:
   Stack=2, Locals=2, Args_size=2
	aload_0
	aload_1
	invokestatic	Method scala/collection/TraversableLike$class.groupBy:(Lscala/collection/TraversableLike;Lscala/Function1;)Lscala/collection/Map;
	areturn
  Labels:
  LocalVariableTable: 
   Start  Length  Slot  Name   Signature
   0      6      0    this       Lscala/collection/immutable/Map$Map4;
   0      6      1    f       Lscala/Function1;


public scala.Tuple2 partition(scala.Function1);
  Signature: (Lscala/Function1;)Lscala/Tuple2;
  Code:
   Stack=2, Locals=2, Args_size=2
	aload_0
	aload_1
	invokestatic	Method scala/collection/TraversableLike$class.partition:(Lscala/collection/TraversableLike;Lscala/Function1;)Lscala/Tuple2;
	areturn
  Labels:
  LocalVariableTable: 
   Start  Length  Slot  Name   Signature
   0      6      0    this       Lscala/collection/immutable/Map$Map4;
   0      6      1    p       Lscala/Function1;


public java.lang.Object partialMap(scala.PartialFunction, scala.collection.generic.CanBuildFrom);
  Signature: (Lscala/PartialFunction;Lscala/collection/generic/CanBuildFrom;)Ljava/lang/Object;
  Code:
   Stack=3, Locals=3, Args_size=3
	aload_0
	aload_1
	aload_2
	invokestatic	Method scala/collection/TraversableLike$class.partialMap:(Lscala/collection/TraversableLike;Lscala/PartialFunction;Lscala/collection/generic/CanBuildFrom;)Ljava/lang/Object;
	areturn
  Labels:
  LocalVariableTable: 
   Start  Length  Slot  Name   Signature
   0      7      0    this       Lscala/collection/immutable/Map$Map4;
   0      7      1    pf       Lscala/PartialFunction;
   0      7      2    bf       Lscala/collection/generic/CanBuildFrom;


public java.lang.Object filter(scala.Function1);
  Signature: (Lscala/Function1;)Ljava/lang/Object;
  Code:
   Stack=2, Locals=2, Args_size=2
	aload_0
	aload_1
	invokestatic	Method scala/collection/TraversableLike$class.filter:(Lscala/collection/TraversableLike;Lscala/Function1;)Ljava/lang/Object;
	areturn
  Labels:
  LocalVariableTable: 
   Start  Length  Slot  Name   Signature
   0      6      0    this       Lscala/collection/immutable/Map$Map4;
   0      6      1    p       Lscala/Function1;


public java.lang.Object flatMap(scala.Function1, scala.collection.generic.CanBuildFrom);
  Signature: (Lscala/Function1;Lscala/collection/generic/CanBuildFrom;)Ljava/lang/Object;
  Code:
   Stack=3, Locals=3, Args_size=3
	aload_0
	aload_1
	aload_2
	invokestatic	Method scala/collection/TraversableLike$class.flatMap:(Lscala/collection/TraversableLike;Lscala/Function1;Lscala/collection/generic/CanBuildFrom;)Ljava/lang/Object;
	areturn
  Labels:
  LocalVariableTable: 
   Start  Length  Slot  Name   Signature
   0      7      0    this       Lscala/collection/immutable/Map$Map4;
   0      7      1    f       Lscala/Function1;
   0      7      2    bf       Lscala/collection/generic/CanBuildFrom;


public java.lang.Object map(scala.Function1, scala.collection.generic.CanBuildFrom);
  Signature: (Lscala/Function1;Lscala/collection/generic/CanBuildFrom;)Ljava/lang/Object;
  Code:
   Stack=3, Locals=3, Args_size=3
	aload_0
	aload_1
	aload_2
	invokestatic	Method scala/collection/TraversableLike$class.map:(Lscala/collection/TraversableLike;Lscala/Function1;Lscala/collection/generic/CanBuildFrom;)Ljava/lang/Object;
	areturn
  Labels:
  LocalVariableTable: 
   Start  Length  Slot  Name   Signature
   0      7      0    this       Lscala/collection/immutable/Map$Map4;
   0      7      1    f       Lscala/Function1;
   0      7      2    bf       Lscala/collection/generic/CanBuildFrom;


public java.lang.Object $plus$plus(scala.collection.Iterator, scala.collection.generic.CanBuildFrom);
  Signature: (Lscala/collection/Iterator;Lscala/collection/generic/CanBuildFrom;)Ljava/lang/Object;
  Code:
   Stack=3, Locals=3, Args_size=3
	aload_0
	aload_1
	aload_2
	invokestatic	Method scala/collection/TraversableLike$class.$plus$plus:(Lscala/collection/TraversableLike;Lscala/collection/Iterator;Lscala/collection/generic/CanBuildFrom;)Ljava/lang/Object;
	areturn
  Labels:
  LocalVariableTable: 
   Start  Length  Slot  Name   Signature
   0      7      0    this       Lscala/collection/immutable/Map$Map4;
   0      7      1    that       Lscala/collection/Iterator;
   0      7      2    bf       Lscala/collection/generic/CanBuildFrom;


public java.lang.Object $plus$plus(scala.collection.Traversable, scala.collection.generic.CanBuildFrom);
  Signature: (Lscala/collection/Traversable;Lscala/collection/generic/CanBuildFrom;)Ljava/lang/Object;
  Code:
   Stack=3, Locals=3, Args_size=3
	aload_0
	aload_1
	aload_2
	invokestatic	Method scala/collection/TraversableLike$class.$plus$plus:(Lscala/collection/TraversableLike;Lscala/collection/Traversable;Lscala/collection/generic/CanBuildFrom;)Ljava/lang/Object;
	areturn
  Labels:
  LocalVariableTable: 
   Start  Length  Slot  Name   Signature
   0      7      0    this       Lscala/collection/immutable/Map$Map4;
   0      7      1    that       Lscala/collection/Traversable;
   0      7      2    bf       Lscala/collection/generic/CanBuildFrom;


public boolean hasDefiniteSize();
  Signature: ()Z
  Code:
   Stack=1, Locals=1, Args_size=1
	aload_0
	invokestatic	Method scala/collection/TraversableLike$class.hasDefiniteSize:(Lscala/collection/TraversableLike;)Z
	ireturn
  Labels:

public boolean nonEmpty();
  Signature: ()Z
  Code:
   Stack=1, Locals=1, Args_size=1
	aload_0
	invokestatic	Method scala/collection/TraversableLike$class.nonEmpty:(Lscala/collection/TraversableLike;)Z
	ireturn
  Labels:

public java.lang.Object repr();
  Signature: ()Ljava/lang/Object;
  Code:
   Stack=1, Locals=1, Args_size=1
	aload_0
	invokestatic	Method scala/collection/TraversableLike$class.repr:(Lscala/collection/TraversableLike;)Ljava/lang/Object;
	areturn
  Labels:

public scala.collection.Traversable transpose(scala.Function1);
  Signature: (Lscala/Function1;)Lscala/collection/Traversable;
  Code:
   Stack=2, Locals=2, Args_size=2
	aload_0
	aload_1
	invokestatic	Method scala/collection/generic/GenericTraversableTemplate$class.transpose:(Lscala/collection/generic/GenericTraversableTemplate;Lscala/Function1;)Lscala/collection/Traversable;
	areturn
  Labels:
  LocalVariableTable: 
   Start  Length  Slot  Name   Signature
   0      6      0    this       Lscala/collection/immutable/Map$Map4;
   0      6      1    asTraversable       Lscala/Function1;


public scala.collection.Traversable flatten(scala.Function1);
  Signature: (Lscala/Function1;)Lscala/collection/Traversable;
  Code:
   Stack=2, Locals=2, Args_size=2
	aload_0
	aload_1
	invokestatic	Method scala/collection/generic/GenericTraversableTemplate$class.flatten:(Lscala/collection/generic/GenericTraversableTemplate;Lscala/Function1;)Lscala/collection/Traversable;
	areturn
  Labels:
  LocalVariableTable: 
   Start  Length  Slot  Name   Signature
   0      6      0    this       Lscala/collection/immutable/Map$Map4;
   0      6      1    asTraversable       Lscala/Function1;


public scala.Tuple2 unzip(scala.Function1);
  Signature: (Lscala/Function1;)Lscala/Tuple2;
  Code:
   Stack=2, Locals=2, Args_size=2
	aload_0
	aload_1
	invokestatic	Method scala/collection/generic/GenericTraversableTemplate$class.unzip:(Lscala/collection/generic/GenericTraversableTemplate;Lscala/Function1;)Lscala/Tuple2;
	areturn
  Labels:
  LocalVariableTable: 
   Start  Length  Slot  Name   Signature
   0      6      0    this       Lscala/collection/immutable/Map$Map4;
   0      6      1    asPair       Lscala/Function1;


public scala.collection.mutable.Builder genericBuilder();
  Signature: ()Lscala/collection/mutable/Builder;
  Code:
   Stack=1, Locals=1, Args_size=1
	aload_0
	invokestatic	Method scala/collection/generic/GenericTraversableTemplate$class.genericBuilder:(Lscala/collection/generic/GenericTraversableTemplate;)Lscala/collection/mutable/Builder;
	areturn
  Labels:

public scala.collection.IterableView projection();
  Signature: ()Lscala/collection/IterableView;
  Code:
   Stack=1, Locals=1, Args_size=1
	aload_0
	invokestatic	Method scala/collection/IterableLike$class.projection:(Lscala/collection/IterableLike;)Lscala/collection/IterableView;
	areturn
  Labels:
  Deprecated: true

public scala.Option firstOption();
  Signature: ()Lscala/Option;
  Code:
   Stack=1, Locals=1, Args_size=1
	aload_0
	invokestatic	Method scala/collection/IterableLike$class.firstOption:(Lscala/collection/IterableLike;)Lscala/Option;
	areturn
  Labels:
  Deprecated: true

public java.lang.Object first();
  Signature: ()Ljava/lang/Object;
  Code:
   Stack=1, Locals=1, Args_size=1
	aload_0
	invokestatic	Method scala/collection/IterableLike$class.first:(Lscala/collection/IterableLike;)Ljava/lang/Object;
	areturn
  Labels:
  Deprecated: true

public scala.collection.IterableView view(int, int);
  Signature: (II)Lscala/collection/IterableView;
  Code:
   Stack=3, Locals=3, Args_size=3
	aload_0
	iload_1
	iload_2
	invokestatic	Method scala/collection/IterableLike$class.view:(Lscala/collection/IterableLike;II)Lscala/collection/IterableView;
	areturn
  Labels:
  LocalVariableTable: 
   Start  Length  Slot  Name   Signature
   0      7      0    this       Lscala/collection/immutable/Map$Map4;
   0      7      1    from       I
   0      7      2    until       I


public scala.collection.IterableView view();
  Signature: ()Lscala/collection/IterableView;
  Code:
   Stack=1, Locals=1, Args_size=1
	aload_0
	invokestatic	Method scala/collection/IterableLike$class.view:(Lscala/collection/IterableLike;)Lscala/collection/IterableView;
	areturn
  Labels:

public boolean canEqual(java.lang.Object);
  Signature: (Ljava/lang/Object;)Z
  Code:
   Stack=2, Locals=2, Args_size=2
	aload_0
	aload_1
	invokestatic	Method scala/collection/IterableLike$class.canEqual:(Lscala/collection/IterableLike;Ljava/lang/Object;)Z
	ireturn
  Labels:
  LocalVariableTable: 
   Start  Length  Slot  Name   Signature
   0      6      0    this       Lscala/collection/immutable/Map$Map4;
   0      6      1    that       Ljava/lang/Object;


public scala.collection.immutable.Stream toStream();
  Signature: ()Lscala/collection/immutable/Stream;
  Code:
   Stack=1, Locals=1, Args_size=1
	aload_0
	invokestatic	Method scala/collection/IterableLike$class.toStream:(Lscala/collection/IterableLike;)Lscala/collection/immutable/Stream;
	areturn
  Labels:

public boolean sameElements(scala.collection.Iterable);
  Signature: (Lscala/collection/Iterable;)Z
  Code:
   Stack=2, Locals=2, Args_size=2
	aload_0
	aload_1
	invokestatic	Method scala/collection/IterableLike$class.sameElements:(Lscala/collection/IterableLike;Lscala/collection/Iterable;)Z
	ireturn
  Labels:
  LocalVariableTable: 
   Start  Length  Slot  Name   Signature
   0      6      0    this       Lscala/collection/immutable/Map$Map4;
   0      6      1    that       Lscala/collection/Iterable;


public java.lang.Object zipWithIndex(scala.collection.generic.CanBuildFrom);
  Signature: (Lscala/collection/generic/CanBuildFrom;)Ljava/lang/Object;
  Code:
   Stack=2, Locals=2, Args_size=2
	aload_0
	aload_1
	invokestatic	Method scala/collection/IterableLike$class.zipWithIndex:(Lscala/collection/IterableLike;Lscala/collection/generic/CanBuildFrom;)Ljava/lang/Object;
	areturn
  Labels:
  LocalVariableTable: 
   Start  Length  Slot  Name   Signature
   0      6      0    this       Lscala/collection/immutable/Map$Map4;
   0      6      1    bf       Lscala/collection/generic/CanBuildFrom;


public java.lang.Object zipAll(scala.collection.Iterable, java.lang.Object, java.lang.Object, scala.collection.generic.CanBuildFrom);
  Signature: (Lscala/collection/Iterable;Ljava/lang/Object;Ljava/lang/Object;Lscala/collection/generic/CanBuildFrom;)Ljava/lang/Object;
  Code:
   Stack=5, Locals=5, Args_size=5
	aload_0
	aload_1
	aload_2
	aload_3
	aload	4
	invokestatic	Method scala/collection/IterableLike$class.zipAll:(Lscala/collection/IterableLike;Lscala/collection/Iterable;Ljava/lang/Object;Ljava/lang/Object;Lscala/collection/generic/CanBuildFrom;)Ljava/lang/Object;
	areturn
  Labels:
  LocalVariableTable: 
   Start  Length  Slot  Name   Signature
   0      10      0    this       Lscala/collection/immutable/Map$Map4;
   0      10      1    that       Lscala/collection/Iterable;
   0      10      2    thisElem       Ljava/lang/Object;
   0      10      3    thatElem       Ljava/lang/Object;
   0      10      4    bf       Lscala/collection/generic/CanBuildFrom;


public java.lang.Object zip(scala.collection.Iterable, scala.collection.generic.CanBuildFrom);
  Signature: (Lscala/collection/Iterable;Lscala/collection/generic/CanBuildFrom;)Ljava/lang/Object;
  Code:
   Stack=3, Locals=3, Args_size=3
	aload_0
	aload_1
	aload_2
	invokestatic	Method scala/collection/IterableLike$class.zip:(Lscala/collection/IterableLike;Lscala/collection/Iterable;Lscala/collection/generic/CanBuildFrom;)Ljava/lang/Object;
	areturn
  Labels:
  LocalVariableTable: 
   Start  Length  Slot  Name   Signature
   0      7      0    this       Lscala/collection/immutable/Map$Map4;
   0      7      1    that       Lscala/collection/Iterable;
   0      7      2    bf       Lscala/collection/generic/CanBuildFrom;


public void copyToArray(java.lang.Object, int, int);
  Signature: (Ljava/lang/Object;II)V
  Code:
   Stack=4, Locals=4, Args_size=4
	aload_0
	aload_1
	iload_2
	iload_3
	invokestatic	Method scala/collection/IterableLike$class.copyToArray:(Lscala/collection/IterableLike;Ljava/lang/Object;II)V
	return
  Labels:
  LocalVariableTable: 
   Start  Length  Slot  Name   Signature
   0      8      0    this       Lscala/collection/immutable/Map$Map4;
   0      8      1    xs       Ljava/lang/Object;
   0      8      2    start       I
   0      8      3    len       I


public java.lang.Object dropRight(int);
  Signature: (I)Ljava/lang/Object;
  Code:
   Stack=2, Locals=2, Args_size=2
	aload_0
	iload_1
	invokestatic	Method scala/collection/IterableLike$class.dropRight:(Lscala/collection/IterableLike;I)Ljava/lang/Object;
	areturn
  Labels:
  LocalVariableTable: 
   Start  Length  Slot  Name   Signature
   0      6      0    this       Lscala/collection/immutable/Map$Map4;
   0      6      1    n       I


public java.lang.Object takeRight(int);
  Signature: (I)Ljava/lang/Object;
  Code:
   Stack=2, Locals=2, Args_size=2
	aload_0
	iload_1
	invokestatic	Method scala/collection/IterableLike$class.takeRight:(Lscala/collection/IterableLike;I)Ljava/lang/Object;
	areturn
  Labels:
  LocalVariableTable: 
   Start  Length  Slot  Name   Signature
   0      6      0    this       Lscala/collection/immutable/Map$Map4;
   0      6      1    n       I


public java.lang.Object takeWhile(scala.Function1);
  Signature: (Lscala/Function1;)Ljava/lang/Object;
  Code:
   Stack=2, Locals=2, Args_size=2
	aload_0
	aload_1
	invokestatic	Method scala/collection/IterableLike$class.takeWhile:(Lscala/collection/IterableLike;Lscala/Function1;)Ljava/lang/Object;
	areturn
  Labels:
  LocalVariableTable: 
   Start  Length  Slot  Name   Signature
   0      6      0    this       Lscala/collection/immutable/Map$Map4;
   0      6      1    p       Lscala/Function1;


public java.lang.Object slice(int, int);
  Signature: (II)Ljava/lang/Object;
  Code:
   Stack=3, Locals=3, Args_size=3
	aload_0
	iload_1
	iload_2
	invokestatic	Method scala/collection/IterableLike$class.slice:(Lscala/collection/IterableLike;II)Ljava/lang/Object;
	areturn
  Labels:
  LocalVariableTable: 
   Start  Length  Slot  Name   Signature
   0      7      0    this       Lscala/collection/immutable/Map$Map4;
   0      7      1    from       I
   0      7      2    until       I


public java.lang.Object take(int);
  Signature: (I)Ljava/lang/Object;
  Code:
   Stack=2, Locals=2, Args_size=2
	aload_0
	iload_1
	invokestatic	Method scala/collection/IterableLike$class.take:(Lscala/collection/IterableLike;I)Ljava/lang/Object;
	areturn
  Labels:
  LocalVariableTable: 
   Start  Length  Slot  Name   Signature
   0      6      0    this       Lscala/collection/immutable/Map$Map4;
   0      6      1    n       I


public java.lang.Object head();
  Signature: ()Ljava/lang/Object;
  Code:
   Stack=1, Locals=1, Args_size=1
	aload_0
	invokestatic	Method scala/collection/IterableLike$class.head:(Lscala/collection/IterableLike;)Ljava/lang/Object;
	areturn
  Labels:

public scala.collection.Iterable toIterable();
  Signature: ()Lscala/collection/Iterable;
  Code:
   Stack=1, Locals=1, Args_size=1
	aload_0
	invokestatic	Method scala/collection/IterableLike$class.toIterable:(Lscala/collection/IterableLike;)Lscala/collection/Iterable;
	areturn
  Labels:

public java.lang.Object reduceRight(scala.Function2);
  Signature: (Lscala/Function2;)Ljava/lang/Object;
  Code:
   Stack=2, Locals=2, Args_size=2
	aload_0
	aload_1
	invokestatic	Method scala/collection/IterableLike$class.reduceRight:(Lscala/collection/IterableLike;Lscala/Function2;)Ljava/lang/Object;
	areturn
  Labels:
  LocalVariableTable: 
   Start  Length  Slot  Name   Signature
   0      6      0    this       Lscala/collection/immutable/Map$Map4;
   0      6      1    op       Lscala/Function2;


public java.lang.Object foldRight(java.lang.Object, scala.Function2);
  Signature: (Ljava/lang/Object;Lscala/Function2;)Ljava/lang/Object;
  Code:
   Stack=3, Locals=3, Args_size=3
	aload_0
	aload_1
	aload_2
	invokestatic	Method scala/collection/IterableLike$class.foldRight:(Lscala/collection/IterableLike;Ljava/lang/Object;Lscala/Function2;)Ljava/lang/Object;
	areturn
  Labels:
  LocalVariableTable: 
   Start  Length  Slot  Name   Signature
   0      7      0    this       Lscala/collection/immutable/Map$Map4;
   0      7      1    z       Ljava/lang/Object;
   0      7      2    op       Lscala/Function2;


public scala.Option find(scala.Function1);
  Signature: (Lscala/Function1;)Lscala/Option;
  Code:
   Stack=2, Locals=2, Args_size=2
	aload_0
	aload_1
	invokestatic	Method scala/collection/IterableLike$class.find:(Lscala/collection/IterableLike;Lscala/Function1;)Lscala/Option;
	areturn
  Labels:
  LocalVariableTable: 
   Start  Length  Slot  Name   Signature
   0      6      0    this       Lscala/collection/immutable/Map$Map4;
   0      6      1    p       Lscala/Function1;


public boolean exists(scala.Function1);
  Signature: (Lscala/Function1;)Z
  Code:
   Stack=2, Locals=2, Args_size=2
	aload_0
	aload_1
	invokestatic	Method scala/collection/IterableLike$class.exists:(Lscala/collection/IterableLike;Lscala/Function1;)Z
	ireturn
  Labels:
  LocalVariableTable: 
   Start  Length  Slot  Name   Signature
   0      6      0    this       Lscala/collection/immutable/Map$Map4;
   0      6      1    p       Lscala/Function1;


public boolean forall(scala.Function1);
  Signature: (Lscala/Function1;)Z
  Code:
   Stack=2, Locals=2, Args_size=2
	aload_0
	aload_1
	invokestatic	Method scala/collection/IterableLike$class.forall:(Lscala/collection/IterableLike;Lscala/Function1;)Z
	ireturn
  Labels:
  LocalVariableTable: 
   Start  Length  Slot  Name   Signature
   0      6      0    this       Lscala/collection/immutable/Map$Map4;
   0      6      1    p       Lscala/Function1;


public scala.collection.Iterator elements();
  Signature: ()Lscala/collection/Iterator;
  Code:
   Stack=1, Locals=1, Args_size=1
	aload_0
	invokestatic	Method scala/collection/IterableLike$class.elements:(Lscala/collection/IterableLike;)Lscala/collection/Iterator;
	areturn
  Labels:
  Deprecated: true

public scala.collection.Iterable toCollection(java.lang.Object);
  Signature: (Ljava/lang/Object;)Lscala/collection/Iterable;
  Code:
   Stack=2, Locals=2, Args_size=2
	aload_0
	aload_1
	invokestatic	Method scala/collection/IterableLike$class.toCollection:(Lscala/collection/IterableLike;Ljava/lang/Object;)Lscala/collection/Iterable;
	areturn
  Labels:
  LocalVariableTable: 
   Start  Length  Slot  Name   Signature
   0      6      0    this       Lscala/collection/immutable/Map$Map4;
   0      6      1    repr       Ljava/lang/Object;


public scala.collection.Iterable thisCollection();
  Signature: ()Lscala/collection/Iterable;
  Code:
   Stack=1, Locals=1, Args_size=1
	aload_0
	invokestatic	Method scala/collection/IterableLike$class.thisCollection:(Lscala/collection/IterableLike;)Lscala/collection/Iterable;
	areturn
  Labels:

public scala.collection.generic.GenericCompanion companion();
  Signature: ()Lscala/collection/generic/GenericCompanion;
  Code:
   Stack=1, Locals=1, Args_size=1
	aload_0
	invokestatic	Method scala/collection/immutable/Iterable$class.companion:(Lscala/collection/immutable/Iterable;)Lscala/collection/generic/GenericCompanion;
	areturn
  Labels:

public scala.Function1 compose(scala.Function1);
  Signature: (Lscala/Function1;)Lscala/Function1;
  Code:
   Stack=2, Locals=2, Args_size=2
	aload_0
	aload_1
	invokestatic	Method scala/Function1$class.compose:(Lscala/Function1;Lscala/Function1;)Lscala/Function1;
	areturn
  Labels:
  LocalVariableTable: 
   Start  Length  Slot  Name   Signature
   0      6      0    this       Lscala/collection/immutable/Map$Map4;
   0      6      1    g       Lscala/Function1;


public scala.Function1 lift();
  Signature: ()Lscala/Function1;
  Code:
   Stack=1, Locals=1, Args_size=1
	aload_0
	invokestatic	Method scala/PartialFunction$class.lift:(Lscala/PartialFunction;)Lscala/Function1;
	areturn
  Labels:

public scala.PartialFunction andThen(scala.Function1);
  Signature: (Lscala/Function1;)Lscala/PartialFunction;
  Code:
   Stack=2, Locals=2, Args_size=2
	aload_0
	aload_1
	invokestatic	Method scala/PartialFunction$class.andThen:(Lscala/PartialFunction;Lscala/Function1;)Lscala/PartialFunction;
	areturn
  Labels:
  LocalVariableTable: 
   Start  Length  Slot  Name   Signature
   0      6      0    this       Lscala/collection/immutable/Map$Map4;
   0      6      1    k       Lscala/Function1;


public scala.PartialFunction orElse(scala.PartialFunction);
  Signature: (Lscala/PartialFunction;)Lscala/PartialFunction;
  Code:
   Stack=2, Locals=2, Args_size=2
	aload_0
	aload_1
	invokestatic	Method scala/PartialFunction$class.orElse:(Lscala/PartialFunction;Lscala/PartialFunction;)Lscala/PartialFunction;
	areturn
  Labels:
  LocalVariableTable: 
   Start  Length  Slot  Name   Signature
   0      6      0    this       Lscala/collection/immutable/Map$Map4;
   0      6      1    that       Lscala/PartialFunction;


public scala.collection.generic.Subtractable $minus$minus(scala.collection.Iterator);
  Signature: (Lscala/collection/Iterator;)Lscala/collection/generic/Subtractable;
  Code:
   Stack=2, Locals=2, Args_size=2
	aload_0
	aload_1
	invokestatic	Method scala/collection/generic/Subtractable$class.$minus$minus:(Lscala/collection/generic/Subtractable;Lscala/collection/Iterator;)Lscala/collection/generic/Subtractable;
	areturn
  Labels:
  LocalVariableTable: 
   Start  Length  Slot  Name   Signature
   0      6      0    this       Lscala/collection/immutable/Map$Map4;
   0      6      1    iter       Lscala/collection/Iterator;


public scala.collection.generic.Subtractable $minus$minus(scala.collection.Traversable);
  Signature: (Lscala/collection/Traversable;)Lscala/collection/generic/Subtractable;
  Code:
   Stack=2, Locals=2, Args_size=2
	aload_0
	aload_1
	invokestatic	Method scala/collection/generic/Subtractable$class.$minus$minus:(Lscala/collection/generic/Subtractable;Lscala/collection/Traversable;)Lscala/collection/generic/Subtractable;
	areturn
  Labels:
  LocalVariableTable: 
   Start  Length  Slot  Name   Signature
   0      6      0    this       Lscala/collection/immutable/Map$Map4;
   0      6      1    elems       Lscala/collection/Traversable;


public scala.collection.generic.Subtractable $minus(java.lang.Object, java.lang.Object, scala.collection.Seq);
  Signature: (Ljava/lang/Object;Ljava/lang/Object;Lscala/collection/Seq;)Lscala/collection/generic/Subtractable;
  Code:
   Stack=4, Locals=4, Args_size=4
	aload_0
	aload_1
	aload_2
	aload_3
	invokestatic	Method scala/collection/generic/Subtractable$class.$minus:(Lscala/collection/generic/Subtractable;Ljava/lang/Object;Ljava/lang/Object;Lscala/collection/Seq;)Lscala/collection/generic/Subtractable;
	areturn
  Labels:
  LocalVariableTable: 
   Start  Length  Slot  Name   Signature
   0      8      0    this       Lscala/collection/immutable/Map$Map4;
   0      8      1    elem1       Ljava/lang/Object;
   0      8      2    elem2       Ljava/lang/Object;
   0      8      3    elems       Lscala/collection/Seq;


public boolean equals(java.lang.Object);
  Signature: (Ljava/lang/Object;)Z
  Code:
   Stack=2, Locals=2, Args_size=2
	aload_0
	aload_1
	invokestatic	Method scala/collection/MapLike$class.equals:(Lscala/collection/MapLike;Ljava/lang/Object;)Z
	ireturn
  Labels:
  LocalVariableTable: 
   Start  Length  Slot  Name   Signature
   0      6      0    this       Lscala/collection/immutable/Map$Map4;
   0      6      1    that       Ljava/lang/Object;


public int hashCode();
  Signature: ()I
  Code:
   Stack=1, Locals=1, Args_size=1
	aload_0
	invokestatic	Method scala/collection/MapLike$class.hashCode:(Lscala/collection/MapLike;)I
	ireturn
  Labels:

public java.lang.String toString();
  Signature: ()Ljava/lang/String;
  Code:
   Stack=1, Locals=1, Args_size=1
	aload_0
	invokestatic	Method scala/collection/MapLike$class.toString:(Lscala/collection/MapLike;)Ljava/lang/String;
	areturn
  Labels:

public java.lang.String stringPrefix();
  Signature: ()Ljava/lang/String;
  Code:
   Stack=1, Locals=1, Args_size=1
	aload_0
	invokestatic	Method scala/collection/MapLike$class.stringPrefix:(Lscala/collection/MapLike;)Ljava/lang/String;
	areturn
  Labels:

public scala.collection.mutable.StringBuilder addString(scala.collection.mutable.StringBuilder, java.lang.String, java.lang.String, java.lang.String);
  Signature: (Lscala/collection/mutable/StringBuilder;Ljava/lang/String;Ljava/lang/String;Ljava/lang/String;)Lscala/collection/mutable/StringBuilder;
  Code:
   Stack=5, Locals=5, Args_size=5
	aload_0
	aload_1
	aload_2
	aload_3
	aload	4
	invokestatic	Method scala/collection/MapLike$class.addString:(Lscala/collection/MapLike;Lscala/collection/mutable/StringBuilder;Ljava/lang/String;Ljava/lang/String;Ljava/lang/String;)Lscala/collection/mutable/StringBuilder;
	areturn
  Labels:
  LocalVariableTable: 
   Start  Length  Slot  Name   Signature
   0      10      0    this       Lscala/collection/immutable/Map$Map4;
   0      10      1    b       Lscala/collection/mutable/StringBuilder;
   0      10      2    start       Ljava/lang/String;
   0      10      3    sep       Ljava/lang/String;
   0      10      4    end       Ljava/lang/String;


public scala.collection.DefaultMap mapElements(scala.Function1);
  Signature: (Lscala/Function1;)Lscala/collection/DefaultMap;
  Code:
   Stack=2, Locals=2, Args_size=2
	aload_0
	aload_1
	invokestatic	Method scala/collection/MapLike$class.mapElements:(Lscala/collection/MapLike;Lscala/Function1;)Lscala/collection/DefaultMap;
	areturn
  Labels:
  LocalVariableTable: 
   Start  Length  Slot  Name   Signature
   0      6      0    this       Lscala/collection/immutable/Map$Map4;
   0      6      1    f       Lscala/Function1;

  Deprecated: true

public scala.collection.DefaultMap mapValues(scala.Function1);
  Signature: (Lscala/Function1;)Lscala/collection/DefaultMap;
  Code:
   Stack=2, Locals=2, Args_size=2
	aload_0
	aload_1
	invokestatic	Method scala/collection/MapLike$class.mapValues:(Lscala/collection/MapLike;Lscala/Function1;)Lscala/collection/DefaultMap;
	areturn
  Labels:
  LocalVariableTable: 
   Start  Length  Slot  Name   Signature
   0      6      0    this       Lscala/collection/immutable/Map$Map4;
   0      6      1    f       Lscala/Function1;


public scala.collection.DefaultMap filterKeys(scala.Function1);
  Signature: (Lscala/Function1;)Lscala/collection/DefaultMap;
  Code:
   Stack=2, Locals=2, Args_size=2
	aload_0
	aload_1
	invokestatic	Method scala/collection/MapLike$class.filterKeys:(Lscala/collection/MapLike;Lscala/Function1;)Lscala/collection/DefaultMap;
	areturn
  Labels:
  LocalVariableTable: 
   Start  Length  Slot  Name   Signature
   0      6      0    this       Lscala/collection/immutable/Map$Map4;
   0      6      1    p       Lscala/Function1;


public java.lang.Object default(java.lang.Object);
  Signature: (Ljava/lang/Object;)Ljava/lang/Object;
  Code:
   Stack=2, Locals=2, Args_size=2
	aload_0
	aload_1
	invokestatic	Method scala/collection/MapLike$class.default:(Lscala/collection/MapLike;Ljava/lang/Object;)Ljava/lang/Object;
	areturn
  Labels:
  LocalVariableTable: 
   Start  Length  Slot  Name   Signature
   0      6      0    this       Lscala/collection/immutable/Map$Map4;
   0      6      1    key       Ljava/lang/Object;


public scala.collection.Iterator values();
  Signature: ()Lscala/collection/Iterator;
  Code:
   Stack=1, Locals=1, Args_size=1
	aload_0
	invokestatic	Method scala/collection/MapLike$class.values:(Lscala/collection/MapLike;)Lscala/collection/Iterator;
	areturn
  Labels:
  Deprecated: true

public scala.collection.Iterator valuesIterator();
  Signature: ()Lscala/collection/Iterator;
  Code:
   Stack=1, Locals=1, Args_size=1
	aload_0
	invokestatic	Method scala/collection/MapLike$class.valuesIterator:(Lscala/collection/MapLike;)Lscala/collection/Iterator;
	areturn
  Labels:

public scala.collection.Iterable valuesIterable();
  Signature: ()Lscala/collection/Iterable;
  Code:
   Stack=1, Locals=1, Args_size=1
	aload_0
	invokestatic	Method scala/collection/MapLike$class.valuesIterable:(Lscala/collection/MapLike;)Lscala/collection/Iterable;
	areturn
  Labels:

public scala.collection.Iterator keys();
  Signature: ()Lscala/collection/Iterator;
  Code:
   Stack=1, Locals=1, Args_size=1
	aload_0
	invokestatic	Method scala/collection/MapLike$class.keys:(Lscala/collection/MapLike;)Lscala/collection/Iterator;
	areturn
  Labels:
  Deprecated: true

public scala.collection.Iterator keysIterator();
  Signature: ()Lscala/collection/Iterator;
  Code:
   Stack=1, Locals=1, Args_size=1
	aload_0
	invokestatic	Method scala/collection/MapLike$class.keysIterator:(Lscala/collection/MapLike;)Lscala/collection/Iterator;
	areturn
  Labels:

public scala.collection.Set keySet();
  Signature: ()Lscala/collection/Set;
  Code:
   Stack=1, Locals=1, Args_size=1
	aload_0
	invokestatic	Method scala/collection/MapLike$class.keySet:(Lscala/collection/MapLike;)Lscala/collection/Set;
	areturn
  Labels:

public boolean isDefinedAt(java.lang.Object);
  Signature: (Ljava/lang/Object;)Z
  Code:
   Stack=2, Locals=2, Args_size=2
	aload_0
	aload_1
	invokestatic	Method scala/collection/MapLike$class.isDefinedAt:(Lscala/collection/MapLike;Ljava/lang/Object;)Z
	ireturn
  Labels:
  LocalVariableTable: 
   Start  Length  Slot  Name   Signature
   0      6      0    this       Lscala/collection/immutable/Map$Map4;
   0      6      1    key       Ljava/lang/Object;


public boolean contains(java.lang.Object);
  Signature: (Ljava/lang/Object;)Z
  Code:
   Stack=2, Locals=2, Args_size=2
	aload_0
	aload_1
	invokestatic	Method scala/collection/MapLike$class.contains:(Lscala/collection/MapLike;Ljava/lang/Object;)Z
	ireturn
  Labels:
  LocalVariableTable: 
   Start  Length  Slot  Name   Signature
   0      6      0    this       Lscala/collection/immutable/Map$Map4;
   0      6      1    key       Ljava/lang/Object;


public java.lang.Object apply(java.lang.Object);
  Signature: (Ljava/lang/Object;)Ljava/lang/Object;
  Code:
   Stack=2, Locals=2, Args_size=2
	aload_0
	aload_1
	invokestatic	Method scala/collection/MapLike$class.apply:(Lscala/collection/MapLike;Ljava/lang/Object;)Ljava/lang/Object;
	areturn
  Labels:
  LocalVariableTable: 
   Start  Length  Slot  Name   Signature
   0      6      0    this       Lscala/collection/immutable/Map$Map4;
   0      6      1    key       Ljava/lang/Object;


public java.lang.Object getOrElse(java.lang.Object, scala.Function0);
  Signature: (Ljava/lang/Object;Lscala/Function0;)Ljava/lang/Object;
  Code:
   Stack=3, Locals=3, Args_size=3
	aload_0
	aload_1
	aload_2
	invokestatic	Method scala/collection/MapLike$class.getOrElse:(Lscala/collection/MapLike;Ljava/lang/Object;Lscala/Function0;)Ljava/lang/Object;
	areturn
  Labels:
  LocalVariableTable: 
   Start  Length  Slot  Name   Signature
   0      7      0    this       Lscala/collection/immutable/Map$Map4;
   0      7      1    key       Ljava/lang/Object;
   0      7      2    default       Lscala/Function0;


public boolean isEmpty();
  Signature: ()Z
  Code:
   Stack=1, Locals=1, Args_size=1
	aload_0
	invokestatic	Method scala/collection/MapLike$class.isEmpty:(Lscala/collection/MapLike;)Z
	ireturn
  Labels:

public scala.collection.mutable.Builder newBuilder();
  Signature: ()Lscala/collection/mutable/Builder;
  Code:
   Stack=1, Locals=1, Args_size=1
	aload_0
	invokestatic	Method scala/collection/MapLike$class.newBuilder:(Lscala/collection/MapLike;)Lscala/collection/mutable/Builder;
	areturn
  Labels:

public scala.collection.immutable.Map update(java.lang.Object, java.lang.Object);
  Signature: (Ljava/lang/Object;Ljava/lang/Object;)Lscala/collection/immutable/Map;
  Code:
   Stack=3, Locals=3, Args_size=3
	aload_0
	aload_1
	aload_2
	invokestatic	Method scala/collection/immutable/MapLike$class.update:(Lscala/collection/immutable/MapLike;Ljava/lang/Object;Ljava/lang/Object;)Lscala/collection/immutable/Map;
	areturn
  Labels:
  LocalVariableTable: 
   Start  Length  Slot  Name   Signature
   0      7      0    this       Lscala/collection/immutable/Map$Map4;
   0      7      1    key       Ljava/lang/Object;
   0      7      2    value       Ljava/lang/Object;

  Deprecated: true

public scala.collection.immutable.Map filterNot(scala.Function1);
  Signature: (Lscala/Function1;)Lscala/collection/immutable/Map;
  Code:
   Stack=2, Locals=2, Args_size=2
	aload_0
	aload_1
	invokestatic	Method scala/collection/immutable/MapLike$class.filterNot:(Lscala/collection/immutable/MapLike;Lscala/Function1;)Lscala/collection/immutable/Map;
	areturn
  Labels:
  LocalVariableTable: 
   Start  Length  Slot  Name   Signature
   0      6      0    this       Lscala/collection/immutable/Map$Map4;
   0      6      1    p       Lscala/Function1;


public java.lang.Object transform(scala.Function2, scala.collection.generic.CanBuildFrom);
  Signature: (Lscala/Function2;Lscala/collection/generic/CanBuildFrom;)Ljava/lang/Object;
  Code:
   Stack=3, Locals=3, Args_size=3
	aload_0
	aload_1
	aload_2
	invokestatic	Method scala/collection/immutable/MapLike$class.transform:(Lscala/collection/immutable/MapLike;Lscala/Function2;Lscala/collection/generic/CanBuildFrom;)Ljava/lang/Object;
	areturn
  Labels:
  LocalVariableTable: 
   Start  Length  Slot  Name   Signature
   0      7      0    this       Lscala/collection/immutable/Map$Map4;
   0      7      1    f       Lscala/Function2;
   0      7      2    bf       Lscala/collection/generic/CanBuildFrom;


public scala.collection.immutable.Map $plus$plus(scala.collection.Iterator);
  Signature: (Lscala/collection/Iterator;)Lscala/collection/immutable/Map;
  Code:
   Stack=2, Locals=2, Args_size=2
	aload_0
	aload_1
	invokestatic	Method scala/collection/immutable/MapLike$class.$plus$plus:(Lscala/collection/immutable/MapLike;Lscala/collection/Iterator;)Lscala/collection/immutable/Map;
	areturn
  Labels:
  LocalVariableTable: 
   Start  Length  Slot  Name   Signature
   0      6      0    this       Lscala/collection/immutable/Map$Map4;
   0      6      1    iter       Lscala/collection/Iterator;


public scala.collection.immutable.Map $plus$plus(scala.collection.Traversable);
  Signature: (Lscala/collection/Traversable;)Lscala/collection/immutable/Map;
  Code:
   Stack=2, Locals=2, Args_size=2
	aload_0
	aload_1
	invokestatic	Method scala/collection/immutable/MapLike$class.$plus$plus:(Lscala/collection/immutable/MapLike;Lscala/collection/Traversable;)Lscala/collection/immutable/Map;
	areturn
  Labels:
  LocalVariableTable: 
   Start  Length  Slot  Name   Signature
   0      6      0    this       Lscala/collection/immutable/Map$Map4;
   0      6      1    elems       Lscala/collection/Traversable;


public scala.collection.immutable.Map $plus(scala.Tuple2, scala.Tuple2, scala.collection.Seq);
  Signature: (Lscala/Tuple2;Lscala/Tuple2;Lscala/collection/Seq;)Lscala/collection/immutable/Map;
  Code:
   Stack=4, Locals=4, Args_size=4
	aload_0
	aload_1
	aload_2
	aload_3
	invokestatic	Method scala/collection/immutable/MapLike$class.$plus:(Lscala/collection/immutable/MapLike;Lscala/Tuple2;Lscala/Tuple2;Lscala/collection/Seq;)Lscala/collection/immutable/Map;
	areturn
  Labels:
  LocalVariableTable: 
   Start  Length  Slot  Name   Signature
   0      8      0    this       Lscala/collection/immutable/Map$Map4;
   0      8      1    elem1       Lscala/Tuple2;
   0      8      2    elem2       Lscala/Tuple2;
   0      8      3    elems       Lscala/collection/Seq;


public scala.collection.immutable.Map withDefaultValue(java.lang.Object);
  Signature: (Ljava/lang/Object;)Lscala/collection/immutable/Map;
  Code:
   Stack=2, Locals=2, Args_size=2
	aload_0
	aload_1
	invokestatic	Method scala/collection/immutable/Map$class.withDefaultValue:(Lscala/collection/immutable/Map;Ljava/lang/Object;)Lscala/collection/immutable/Map;
	areturn
  Labels:
  LocalVariableTable: 
   Start  Length  Slot  Name   Signature
   0      6      0    this       Lscala/collection/immutable/Map$Map4;
   0      6      1    d       Ljava/lang/Object;


public scala.collection.immutable.Map withDefault(scala.Function1);
  Signature: (Lscala/Function1;)Lscala/collection/immutable/Map;
  Code:
   Stack=2, Locals=2, Args_size=2
	aload_0
	aload_1
	invokestatic	Method scala/collection/immutable/Map$class.withDefault:(Lscala/collection/immutable/Map;Lscala/Function1;)Lscala/collection/immutable/Map;
	areturn
  Labels:
  LocalVariableTable: 
   Start  Length  Slot  Name   Signature
   0      6      0    this       Lscala/collection/immutable/Map$Map4;
   0      6      1    d       Lscala/Function1;


public scala.collection.immutable.Map empty();
  Signature: ()Lscala/collection/immutable/Map;
  Code:
   Stack=1, Locals=1, Args_size=1
	aload_0
	invokestatic	Method scala/collection/immutable/Map$class.empty:(Lscala/collection/immutable/Map;)Lscala/collection/immutable/Map;
	areturn
  Labels:

}

