Compiled from "Map.scala"
public abstract class scala.collection.immutable.Map$class extends java.lang.Object
  SourceFile: "Map.scala"
  Scala: length = 0x
   
  InnerClass: 
   public #70= #13 of #69; //WithDefault=class scala/collection/immutable/Map$WithDefault of class scala/collection/immutable/Map
   public final #71= #48 of #69; //$anonfun$hashCode$1=class scala/collection/immutable/Map$$anonfun$hashCode$1 of class scala/collection/immutable/Map
   public final #72= #15 of #69; //$anonfun$withDefaultValue$1=class scala/collection/immutable/Map$$anonfun$withDefaultValue$1 of class scala/collection/immutable/Map
  minor version: 0
  major version: 49
  Constant pool:
const #1 = Asciz	SourceFile;
const #2 = Asciz	Map.scala;
const #3 = Asciz	$init$;
const #4 = Asciz	(Lscala/collection/immutable/Map;)V;
const #5 = Asciz	Code;
const #6 = Asciz	LineNumberTable;
const #7 = Asciz	$this;
const #8 = Asciz	Lscala/collection/immutable/Map;;
const #9 = Asciz	LocalVariableTable;
const #10 = Asciz	withDefaultValue;
const #11 = Asciz	(Lscala/collection/immutable/Map;Ljava/lang/Object;)Lscala/collection/immutable/Map;;
const #12 = Asciz	scala/collection/immutable/Map$WithDefault;
const #13 = class	#12;	//  scala/collection/immutable/Map$WithDefault
const #14 = Asciz	scala/collection/immutable/Map$$anonfun$withDefaultValue$1;
const #15 = class	#14;	//  scala/collection/immutable/Map$$anonfun$withDefaultValue$1
const #16 = Asciz	<init>;
const #17 = Asciz	(Lscala/collection/immutable/Map;Ljava/lang/Object;)V;
const #18 = NameAndType	#16:#17;//  "<init>":(Lscala/collection/immutable/Map;Ljava/lang/Object;)V
const #19 = Method	#15.#18;	//  scala/collection/immutable/Map$$anonfun$withDefaultValue$1."<init>":(Lscala/collection/immutable/Map;Ljava/lang/Object;)V
const #20 = Asciz	(Lscala/collection/immutable/Map;Lscala/Function1;)V;
const #21 = NameAndType	#16:#20;//  "<init>":(Lscala/collection/immutable/Map;Lscala/Function1;)V
const #22 = Method	#13.#21;	//  scala/collection/immutable/Map$WithDefault."<init>":(Lscala/collection/immutable/Map;Lscala/Function1;)V
const #23 = Asciz	d$1;
const #24 = Asciz	Ljava/lang/Object;;
const #25 = Asciz	withDefault;
const #26 = Asciz	(Lscala/collection/immutable/Map;Lscala/Function1;)Lscala/collection/immutable/Map;;
const #27 = Asciz	d;
const #28 = Asciz	Lscala/Function1;;
const #29 = Asciz	hashCode;
const #30 = Asciz	(Lscala/collection/immutable/Map;)I;
const #31 = Asciz	scala/collection/immutable/Map$;
const #32 = class	#31;	//  scala/collection/immutable/Map$
const #33 = Asciz	MODULE$;
const #34 = Asciz	Lscala/collection/immutable/Map$;;
const #35 = NameAndType	#33:#34;//  MODULE$:Lscala/collection/immutable/Map$;
const #36 = Field	#32.#35;	//  scala/collection/immutable/Map$.MODULE$:Lscala/collection/immutable/Map$;
const #37 = Asciz	scala$collection$immutable$Map$$hashSeed;
const #38 = Asciz	()I;
const #39 = NameAndType	#37:#38;//  scala$collection$immutable$Map$$hashSeed:()I
const #40 = Method	#32.#39;	//  scala/collection/immutable/Map$.scala$collection$immutable$Map$$hashSeed:()I
const #41 = Asciz	scala/runtime/BoxesRunTime;
const #42 = class	#41;	//  scala/runtime/BoxesRunTime
const #43 = Asciz	boxToInteger;
const #44 = Asciz	(I)Ljava/lang/Integer;;
const #45 = NameAndType	#43:#44;//  boxToInteger:(I)Ljava/lang/Integer;
const #46 = Method	#42.#45;	//  scala/runtime/BoxesRunTime.boxToInteger:(I)Ljava/lang/Integer;
const #47 = Asciz	scala/collection/immutable/Map$$anonfun$hashCode$1;
const #48 = class	#47;	//  scala/collection/immutable/Map$$anonfun$hashCode$1
const #49 = NameAndType	#16:#4;//  "<init>":(Lscala/collection/immutable/Map;)V
const #50 = Method	#48.#49;	//  scala/collection/immutable/Map$$anonfun$hashCode$1."<init>":(Lscala/collection/immutable/Map;)V
const #51 = Asciz	scala/collection/generic/TraversableTemplate;
const #52 = class	#51;	//  scala/collection/generic/TraversableTemplate
const #53 = Asciz	$div$colon;
const #54 = Asciz	(Ljava/lang/Object;Lscala/Function2;)Ljava/lang/Object;;
const #55 = NameAndType	#53:#54;//  $div$colon:(Ljava/lang/Object;Lscala/Function2;)Ljava/lang/Object;
const #56 = InterfaceMethod	#52.#55;	//  scala/collection/generic/TraversableTemplate.$div$colon:(Ljava/lang/Object;Lscala/Function2;)Ljava/lang/Object;
const #57 = Asciz	unboxToInt;
const #58 = Asciz	(Ljava/lang/Object;)I;
const #59 = NameAndType	#57:#58;//  unboxToInt:(Ljava/lang/Object;)I
const #60 = Method	#42.#59;	//  scala/runtime/BoxesRunTime.unboxToInt:(Ljava/lang/Object;)I
const #61 = Asciz	empty;
const #62 = Asciz	(Lscala/collection/immutable/Map;)Lscala/collection/immutable/Map;;
const #63 = Asciz	()Lscala/collection/immutable/Map;;
const #64 = NameAndType	#61:#63;//  empty:()Lscala/collection/immutable/Map;
const #65 = Method	#32.#64;	//  scala/collection/immutable/Map$.empty:()Lscala/collection/immutable/Map;
const #66 = Asciz	Scala;
const #67 = Asciz	InnerClasses;
const #68 = Asciz	scala/collection/immutable/Map;
const #69 = class	#68;	//  scala/collection/immutable/Map
const #70 = Asciz	WithDefault;
const #71 = Asciz	$anonfun$hashCode$1;
const #72 = Asciz	$anonfun$withDefaultValue$1;
const #73 = Asciz	scala/collection/immutable/Map$class;
const #74 = class	#73;	//  scala/collection/immutable/Map$class
const #75 = Asciz	java/lang/Object;
const #76 = class	#75;	//  java/lang/Object

{
public static void $init$(scala.collection.immutable.Map);
  Code:
   Stack=0, Locals=1, Args_size=1
   0:	return
  LineNumberTable: 
   line 16: 0

  LocalVariableTable: 
   Start  Length  Slot  Name   Signature
   0      1      0    $this       Lscala/collection/immutable/Map;


public static scala.collection.immutable.Map withDefaultValue(scala.collection.immutable.Map, java.lang.Object);
  Code:
   Stack=7, Locals=2, Args_size=2
   0:	new	#13; //class scala/collection/immutable/Map$WithDefault
   3:	dup
   4:	aload_0
   5:	new	#15; //class scala/collection/immutable/Map$$anonfun$withDefaultValue$1
   8:	dup
   9:	aload_0
   10:	aload_1
   11:	invokespecial	#19; //Method scala/collection/immutable/Map$$anonfun$withDefaultValue$1."<init>":(Lscala/collection/immutable/Map;Ljava/lang/Object;)V
   14:	invokespecial	#22; //Method scala/collection/immutable/Map$WithDefault."<init>":(Lscala/collection/immutable/Map;Lscala/Function1;)V
   17:	areturn
  LineNumberTable: 
   line 39: 0

  LocalVariableTable: 
   Start  Length  Slot  Name   Signature
   0      18      0    $this       Lscala/collection/immutable/Map;
   0      18      1    d$1       Ljava/lang/Object;


public static scala.collection.immutable.Map withDefault(scala.collection.immutable.Map, scala.Function1);
  Code:
   Stack=4, Locals=2, Args_size=2
   0:	new	#13; //class scala/collection/immutable/Map$WithDefault
   3:	dup
   4:	aload_0
   5:	aload_1
   6:	invokespecial	#22; //Method scala/collection/immutable/Map$WithDefault."<init>":(Lscala/collection/immutable/Map;Lscala/Function1;)V
   9:	areturn
  LineNumberTable: 
   line 36: 0

  LocalVariableTable: 
   Start  Length  Slot  Name   Signature
   0      10      0    $this       Lscala/collection/immutable/Map;
   0      10      1    d       Lscala/Function1;


public static int hashCode(scala.collection.immutable.Map);
  Code:
   Stack=5, Locals=2, Args_size=1
   0:	getstatic	#36; //Field scala/collection/immutable/Map$.MODULE$:Lscala/collection/immutable/Map$;
   3:	invokevirtual	#40; //Method scala/collection/immutable/Map$.scala$collection$immutable$Map$$hashSeed:()I
   6:	istore_1
   7:	aload_0
   8:	iload_1
   9:	invokestatic	#46; //Method scala/runtime/BoxesRunTime.boxToInteger:(I)Ljava/lang/Integer;
   12:	new	#48; //class scala/collection/immutable/Map$$anonfun$hashCode$1
   15:	dup
   16:	aload_0
   17:	invokespecial	#50; //Method scala/collection/immutable/Map$$anonfun$hashCode$1."<init>":(Lscala/collection/immutable/Map;)V
   20:	invokeinterface	#56,  3; //InterfaceMethod scala/collection/generic/TraversableTemplate.$div$colon:(Ljava/lang/Object;Lscala/Function2;)Ljava/lang/Object;
   25:	invokestatic	#60; //Method scala/runtime/BoxesRunTime.unboxToInt:(Ljava/lang/Object;)I
   28:	ireturn
  LineNumberTable: 
   line 33: 0

  LocalVariableTable: 
   Start  Length  Slot  Name   Signature
   0      29      0    $this       Lscala/collection/immutable/Map;


public static scala.collection.immutable.Map empty(scala.collection.immutable.Map);
  Code:
   Stack=1, Locals=1, Args_size=1
   0:	getstatic	#36; //Field scala/collection/immutable/Map$.MODULE$:Lscala/collection/immutable/Map$;
   3:	invokevirtual	#65; //Method scala/collection/immutable/Map$.empty:()Lscala/collection/immutable/Map;
   6:	areturn
  LineNumberTable: 
   line 20: 0

  LocalVariableTable: 
   Start  Length  Slot  Name   Signature
   0      7      0    $this       Lscala/collection/immutable/Map;


}

