Compiled from "MapLike.scala"
public abstract class scala.collection.immutable.MapLike$class extends java.lang.Object
  SourceFile: "MapLike.scala"
  Scala: length = 0x
   
  InnerClass: 
   public final #128= #71 of #13; //$anonfun$transform$2=class scala/collection/immutable/MapLike$$anonfun$transform$2 of class scala/collection/immutable/MapLike
   public final #129= #63 of #13; //$anonfun$transform$1=class scala/collection/immutable/MapLike$$anonfun$transform$1 of class scala/collection/immutable/MapLike
   public final #130= #37 of #13; //$anonfun$filterNot$1=class scala/collection/immutable/MapLike$$anonfun$filterNot$1 of class scala/collection/immutable/MapLike
   public final #131= #103 of #13; //$anonfun$$plus$plus$1=class scala/collection/immutable/MapLike$$anonfun$$plus$plus$1 of class scala/collection/immutable/MapLike
   public final #132= #91 of #13; //$anonfun$$plus$plus$2=class scala/collection/immutable/MapLike$$anonfun$$plus$plus$2 of class scala/collection/immutable/MapLike
  minor version: 0
  major version: 49
  Constant pool:
const #1 = Asciz	SourceFile;
const #2 = Asciz	MapLike.scala;
const #3 = Asciz	$init$;
const #4 = Asciz	(Lscala/collection/immutable/MapLike;)V;
const #5 = Asciz	Code;
const #6 = Asciz	LineNumberTable;
const #7 = Asciz	$this;
const #8 = Asciz	Lscala/collection/immutable/MapLike;;
const #9 = Asciz	LocalVariableTable;
const #10 = Asciz	update;
const #11 = Asciz	(Lscala/collection/immutable/MapLike;Ljava/lang/Object;Ljava/lang/Object;)Lscala/collection/immutable/Map;;
const #12 = Asciz	scala/collection/immutable/MapLike;
const #13 = class	#12;	//  scala/collection/immutable/MapLike
const #14 = Asciz	updated;
const #15 = Asciz	(Ljava/lang/Object;Ljava/lang/Object;)Lscala/collection/immutable/Map;;
const #16 = NameAndType	#14:#15;//  updated:(Ljava/lang/Object;Ljava/lang/Object;)Lscala/collection/immutable/Map;
const #17 = InterfaceMethod	#13.#16;	//  scala/collection/immutable/MapLike.updated:(Ljava/lang/Object;Ljava/lang/Object;)Lscala/collection/immutable/Map;
const #18 = Asciz	key;
const #19 = Asciz	Ljava/lang/Object;;
const #20 = Asciz	value;
const #21 = Asciz	Deprecated;
const #22 = Asciz	filterNot;
const #23 = Asciz	(Lscala/collection/immutable/MapLike;Lscala/Function1;)Lscala/collection/immutable/MapLike;;
const #24 = Asciz	scala/runtime/ObjectRef;
const #25 = class	#24;	//  scala/runtime/ObjectRef
const #26 = Asciz	scala/collection/TraversableLike;
const #27 = class	#26;	//  scala/collection/TraversableLike
const #28 = Asciz	repr;
const #29 = Asciz	()Ljava/lang/Object;;
const #30 = NameAndType	#28:#29;//  repr:()Ljava/lang/Object;
const #31 = InterfaceMethod	#27.#30;	//  scala/collection/TraversableLike.repr:()Ljava/lang/Object;
const #32 = Asciz	<init>;
const #33 = Asciz	(Ljava/lang/Object;)V;
const #34 = NameAndType	#32:#33;//  "<init>":(Ljava/lang/Object;)V
const #35 = Method	#25.#34;	//  scala/runtime/ObjectRef."<init>":(Ljava/lang/Object;)V
const #36 = Asciz	scala/collection/immutable/MapLike$$anonfun$filterNot$1;
const #37 = class	#36;	//  scala/collection/immutable/MapLike$$anonfun$filterNot$1
const #38 = Asciz	(Lscala/collection/immutable/MapLike;Lscala/Function1;Lscala/runtime/ObjectRef;)V;
const #39 = NameAndType	#32:#38;//  "<init>":(Lscala/collection/immutable/MapLike;Lscala/Function1;Lscala/runtime/ObjectRef;)V
const #40 = Method	#37.#39;	//  scala/collection/immutable/MapLike$$anonfun$filterNot$1."<init>":(Lscala/collection/immutable/MapLike;Lscala/Function1;Lscala/runtime/ObjectRef;)V
const #41 = Asciz	scala/collection/IterableLike;
const #42 = class	#41;	//  scala/collection/IterableLike
const #43 = Asciz	foreach;
const #44 = Asciz	(Lscala/Function1;)V;
const #45 = NameAndType	#43:#44;//  foreach:(Lscala/Function1;)V
const #46 = InterfaceMethod	#42.#45;	//  scala/collection/IterableLike.foreach:(Lscala/Function1;)V
const #47 = Asciz	elem;
const #48 = NameAndType	#47:#19;//  elem:Ljava/lang/Object;
const #49 = Field	#25.#48;	//  scala/runtime/ObjectRef.elem:Ljava/lang/Object;
const #50 = Asciz	p$1;
const #51 = Asciz	Lscala/Function1;;
const #52 = Asciz	res$1;
const #53 = Asciz	Lscala/runtime/ObjectRef;;
const #54 = Asciz	transform;
const #55 = Asciz	(Lscala/collection/immutable/MapLike;Lscala/Function2;Lscala/collection/generic/CanBuildFrom;)Ljava/lang/Object;;
const #56 = Asciz	scala/collection/generic/CanBuildFrom;
const #57 = class	#56;	//  scala/collection/generic/CanBuildFrom
const #58 = Asciz	apply;
const #59 = Asciz	(Ljava/lang/Object;)Lscala/collection/mutable/Builder;;
const #60 = NameAndType	#58:#59;//  apply:(Ljava/lang/Object;)Lscala/collection/mutable/Builder;
const #61 = InterfaceMethod	#57.#60;	//  scala/collection/generic/CanBuildFrom.apply:(Ljava/lang/Object;)Lscala/collection/mutable/Builder;
const #62 = Asciz	scala/collection/immutable/MapLike$$anonfun$transform$1;
const #63 = class	#62;	//  scala/collection/immutable/MapLike$$anonfun$transform$1
const #64 = NameAndType	#32:#4;//  "<init>":(Lscala/collection/immutable/MapLike;)V
const #65 = Method	#63.#64;	//  scala/collection/immutable/MapLike$$anonfun$transform$1."<init>":(Lscala/collection/immutable/MapLike;)V
const #66 = Asciz	filter;
const #67 = Asciz	(Lscala/Function1;)Ljava/lang/Object;;
const #68 = NameAndType	#66:#67;//  filter:(Lscala/Function1;)Ljava/lang/Object;
const #69 = InterfaceMethod	#27.#68;	//  scala/collection/TraversableLike.filter:(Lscala/Function1;)Ljava/lang/Object;
const #70 = Asciz	scala/collection/immutable/MapLike$$anonfun$transform$2;
const #71 = class	#70;	//  scala/collection/immutable/MapLike$$anonfun$transform$2
const #72 = Asciz	(Lscala/collection/immutable/MapLike;Lscala/Function2;Lscala/collection/mutable/Builder;)V;
const #73 = NameAndType	#32:#72;//  "<init>":(Lscala/collection/immutable/MapLike;Lscala/Function2;Lscala/collection/mutable/Builder;)V
const #74 = Method	#71.#73;	//  scala/collection/immutable/MapLike$$anonfun$transform$2."<init>":(Lscala/collection/immutable/MapLike;Lscala/Function2;Lscala/collection/mutable/Builder;)V
const #75 = Asciz	scala/collection/mutable/Builder;
const #76 = class	#75;	//  scala/collection/mutable/Builder
const #77 = Asciz	result;
const #78 = NameAndType	#77:#29;//  result:()Ljava/lang/Object;
const #79 = InterfaceMethod	#76.#78;	//  scala/collection/mutable/Builder.result:()Ljava/lang/Object;
const #80 = Asciz	f$1;
const #81 = Asciz	Lscala/Function2;;
const #82 = Asciz	bf;
const #83 = Asciz	Lscala/collection/generic/CanBuildFrom;;
const #84 = Asciz	b$1;
const #85 = Asciz	Lscala/collection/mutable/Builder;;
const #86 = Asciz	$plus$plus;
const #87 = Asciz	(Lscala/collection/immutable/MapLike;Lscala/collection/Iterator;)Lscala/collection/immutable/Map;;
const #88 = Asciz	scala/collection/immutable/Map;
const #89 = class	#88;	//  scala/collection/immutable/Map
const #90 = Asciz	scala/collection/immutable/MapLike$$anonfun$$plus$plus$2;
const #91 = class	#90;	//  scala/collection/immutable/MapLike$$anonfun$$plus$plus$2
const #92 = Method	#91.#64;	//  scala/collection/immutable/MapLike$$anonfun$$plus$plus$2."<init>":(Lscala/collection/immutable/MapLike;)V
const #93 = Asciz	scala/collection/Iterator;
const #94 = class	#93;	//  scala/collection/Iterator
const #95 = Asciz	$div$colon;
const #96 = Asciz	(Ljava/lang/Object;Lscala/Function2;)Ljava/lang/Object;;
const #97 = NameAndType	#95:#96;//  $div$colon:(Ljava/lang/Object;Lscala/Function2;)Ljava/lang/Object;
const #98 = InterfaceMethod	#94.#97;	//  scala/collection/Iterator.$div$colon:(Ljava/lang/Object;Lscala/Function2;)Ljava/lang/Object;
const #99 = Asciz	iter;
const #100 = Asciz	Lscala/collection/Iterator;;
const #101 = Asciz	(Lscala/collection/immutable/MapLike;Lscala/collection/Traversable;)Lscala/collection/immutable/Map;;
const #102 = Asciz	scala/collection/immutable/MapLike$$anonfun$$plus$plus$1;
const #103 = class	#102;	//  scala/collection/immutable/MapLike$$anonfun$$plus$plus$1
const #104 = Method	#103.#64;	//  scala/collection/immutable/MapLike$$anonfun$$plus$plus$1."<init>":(Lscala/collection/immutable/MapLike;)V
const #105 = InterfaceMethod	#27.#97;	//  scala/collection/TraversableLike.$div$colon:(Ljava/lang/Object;Lscala/Function2;)Ljava/lang/Object;
const #106 = Asciz	elems;
const #107 = Asciz	Lscala/collection/Traversable;;
const #108 = Asciz	$plus;
const #109 = Asciz	(Lscala/collection/immutable/MapLike;Lscala/Tuple2;Lscala/Tuple2;Lscala/collection/Seq;)Lscala/collection/immutable/Map;;
const #110 = Asciz	(Lscala/Tuple2;)Lscala/collection/immutable/Map;;
const #111 = NameAndType	#108:#110;//  $plus:(Lscala/Tuple2;)Lscala/collection/immutable/Map;
const #112 = InterfaceMethod	#13.#111;	//  scala/collection/immutable/MapLike.$plus:(Lscala/Tuple2;)Lscala/collection/immutable/Map;
const #113 = InterfaceMethod	#89.#111;	//  scala/collection/immutable/Map.$plus:(Lscala/Tuple2;)Lscala/collection/immutable/Map;
const #114 = Asciz	(Lscala/collection/Traversable;)Lscala/collection/immutable/Map;;
const #115 = NameAndType	#86:#114;//  $plus$plus:(Lscala/collection/Traversable;)Lscala/collection/immutable/Map;
const #116 = InterfaceMethod	#13.#115;	//  scala/collection/immutable/MapLike.$plus$plus:(Lscala/collection/Traversable;)Lscala/collection/immutable/Map;
const #117 = Asciz	elem1;
const #118 = Asciz	Lscala/Tuple2;;
const #119 = Asciz	elem2;
const #120 = Asciz	Lscala/collection/Seq;;
const #121 = Asciz	scala/Tuple2;
const #122 = class	#121;	//  scala/Tuple2
const #123 = Asciz	(Ljava/lang/Object;Ljava/lang/Object;)V;
const #124 = NameAndType	#32:#123;//  "<init>":(Ljava/lang/Object;Ljava/lang/Object;)V
const #125 = Method	#122.#124;	//  scala/Tuple2."<init>":(Ljava/lang/Object;Ljava/lang/Object;)V
const #126 = Asciz	Scala;
const #127 = Asciz	InnerClasses;
const #128 = Asciz	$anonfun$transform$2;
const #129 = Asciz	$anonfun$transform$1;
const #130 = Asciz	$anonfun$filterNot$1;
const #131 = Asciz	$anonfun$$plus$plus$1;
const #132 = Asciz	$anonfun$$plus$plus$2;
const #133 = Asciz	scala/collection/immutable/MapLike$class;
const #134 = class	#133;	//  scala/collection/immutable/MapLike$class
const #135 = Asciz	java/lang/Object;
const #136 = class	#135;	//  java/lang/Object

{
public static void $init$(scala.collection.immutable.MapLike);
  Code:
   Stack=0, Locals=1, Args_size=1
   0:	return
  LineNumberTable: 
   line 44: 0

  LocalVariableTable: 
   Start  Length  Slot  Name   Signature
   0      1      0    $this       Lscala/collection/immutable/MapLike;


public static scala.collection.immutable.Map update(scala.collection.immutable.MapLike, java.lang.Object, java.lang.Object);
  Code:
   Stack=3, Locals=3, Args_size=3
   0:	aload_0
   1:	aload_1
   2:	aload_2
   3:	invokeinterface	#17,  3; //InterfaceMethod scala/collection/immutable/MapLike.updated:(Ljava/lang/Object;Ljava/lang/Object;)Lscala/collection/immutable/Map;
   8:	areturn
  LineNumberTable: 
   line 118: 0

  LocalVariableTable: 
   Start  Length  Slot  Name   Signature
   0      9      0    $this       Lscala/collection/immutable/MapLike;
   0      9      1    key       Ljava/lang/Object;
   0      9      2    value       Ljava/lang/Object;

  Deprecated: true

public static scala.collection.immutable.MapLike filterNot(scala.collection.immutable.MapLike, scala.Function1);
  Code:
   Stack=6, Locals=3, Args_size=2
   0:	new	#25; //class scala/runtime/ObjectRef
   3:	dup
   4:	aload_0
   5:	invokeinterface	#31,  1; //InterfaceMethod scala/collection/TraversableLike.repr:()Ljava/lang/Object;
   10:	checkcast	#13; //class scala/collection/immutable/MapLike
   13:	invokespecial	#35; //Method scala/runtime/ObjectRef."<init>":(Ljava/lang/Object;)V
   16:	astore_2
   17:	aload_0
   18:	new	#37; //class scala/collection/immutable/MapLike$$anonfun$filterNot$1
   21:	dup
   22:	aload_0
   23:	aload_1
   24:	aload_2
   25:	invokespecial	#40; //Method scala/collection/immutable/MapLike$$anonfun$filterNot$1."<init>":(Lscala/collection/immutable/MapLike;Lscala/Function1;Lscala/runtime/ObjectRef;)V
   28:	invokeinterface	#46,  2; //InterfaceMethod scala/collection/IterableLike.foreach:(Lscala/Function1;)V
   33:	aload_2
   34:	getfield	#49; //Field scala/runtime/ObjectRef.elem:Ljava/lang/Object;
   37:	checkcast	#13; //class scala/collection/immutable/MapLike
   40:	areturn
  LineNumberTable: 
   line 111: 0
   line 112: 17
   line 114: 24
   line 112: 25
   line 114: 33

  LocalVariableTable: 
   Start  Length  Slot  Name   Signature
   0      41      0    $this       Lscala/collection/immutable/MapLike;
   0      41      1    p$1       Lscala/Function1;
   17      23      2    res$1       Lscala/runtime/ObjectRef;


public static java.lang.Object transform(scala.collection.immutable.MapLike, scala.Function2, scala.collection.generic.CanBuildFrom);
  Code:
   Stack=6, Locals=4, Args_size=3
   0:	aload_2
   1:	aload_0
   2:	invokeinterface	#31,  1; //InterfaceMethod scala/collection/TraversableLike.repr:()Ljava/lang/Object;
   7:	invokeinterface	#61,  2; //InterfaceMethod scala/collection/generic/CanBuildFrom.apply:(Ljava/lang/Object;)Lscala/collection/mutable/Builder;
   12:	astore_3
   13:	aload_0
   14:	new	#63; //class scala/collection/immutable/MapLike$$anonfun$transform$1
   17:	dup
   18:	aload_0
   19:	invokespecial	#65; //Method scala/collection/immutable/MapLike$$anonfun$transform$1."<init>":(Lscala/collection/immutable/MapLike;)V
   22:	invokeinterface	#69,  2; //InterfaceMethod scala/collection/TraversableLike.filter:(Lscala/Function1;)Ljava/lang/Object;
   27:	checkcast	#42; //class scala/collection/IterableLike
   30:	new	#71; //class scala/collection/immutable/MapLike$$anonfun$transform$2
   33:	dup
   34:	aload_0
   35:	aload_1
   36:	aload_3
   37:	invokespecial	#74; //Method scala/collection/immutable/MapLike$$anonfun$transform$2."<init>":(Lscala/collection/immutable/MapLike;Lscala/Function2;Lscala/collection/mutable/Builder;)V
   40:	invokeinterface	#46,  2; //InterfaceMethod scala/collection/IterableLike.foreach:(Lscala/Function1;)V
   45:	aload_3
   46:	invokeinterface	#79,  1; //InterfaceMethod scala/collection/mutable/Builder.result:()Ljava/lang/Object;
   51:	areturn
  LineNumberTable: 
   line 95: 0
   line 96: 13
   line 97: 45

  LocalVariableTable: 
   Start  Length  Slot  Name   Signature
   0      52      0    $this       Lscala/collection/immutable/MapLike;
   0      52      1    f$1       Lscala/Function2;
   0      52      2    bf       Lscala/collection/generic/CanBuildFrom;
   13      38      3    b$1       Lscala/collection/mutable/Builder;


public static scala.collection.immutable.Map $plus$plus(scala.collection.immutable.MapLike, scala.collection.Iterator);
  Code:
   Stack=5, Locals=3, Args_size=2
   0:	aload_0
   1:	invokeinterface	#31,  1; //InterfaceMethod scala/collection/TraversableLike.repr:()Ljava/lang/Object;
   6:	checkcast	#89; //class scala/collection/immutable/Map
   9:	astore_2
   10:	aload_1
   11:	aload_2
   12:	new	#91; //class scala/collection/immutable/MapLike$$anonfun$$plus$plus$2
   15:	dup
   16:	aload_0
   17:	invokespecial	#92; //Method scala/collection/immutable/MapLike$$anonfun$$plus$plus$2."<init>":(Lscala/collection/immutable/MapLike;)V
   20:	invokeinterface	#98,  3; //InterfaceMethod scala/collection/Iterator.$div$colon:(Ljava/lang/Object;Lscala/Function2;)Ljava/lang/Object;
   25:	checkcast	#89; //class scala/collection/immutable/Map
   28:	areturn
  LineNumberTable: 
   line 86: 0

  LocalVariableTable: 
   Start  Length  Slot  Name   Signature
   0      29      0    $this       Lscala/collection/immutable/MapLike;
   0      29      1    iter       Lscala/collection/Iterator;


public static scala.collection.immutable.Map $plus$plus(scala.collection.immutable.MapLike, scala.collection.Traversable);
  Code:
   Stack=5, Locals=3, Args_size=2
   0:	aload_0
   1:	invokeinterface	#31,  1; //InterfaceMethod scala/collection/TraversableLike.repr:()Ljava/lang/Object;
   6:	checkcast	#89; //class scala/collection/immutable/Map
   9:	astore_2
   10:	aload_1
   11:	aload_2
   12:	new	#103; //class scala/collection/immutable/MapLike$$anonfun$$plus$plus$1
   15:	dup
   16:	aload_0
   17:	invokespecial	#104; //Method scala/collection/immutable/MapLike$$anonfun$$plus$plus$1."<init>":(Lscala/collection/immutable/MapLike;)V
   20:	invokeinterface	#105,  3; //InterfaceMethod scala/collection/TraversableLike.$div$colon:(Ljava/lang/Object;Lscala/Function2;)Ljava/lang/Object;
   25:	checkcast	#89; //class scala/collection/immutable/Map
   28:	areturn
  LineNumberTable: 
   line 78: 0

  LocalVariableTable: 
   Start  Length  Slot  Name   Signature
   0      29      0    $this       Lscala/collection/immutable/MapLike;
   0      29      1    elems       Lscala/collection/Traversable;


public static scala.collection.immutable.Map $plus(scala.collection.immutable.MapLike, scala.Tuple2, scala.Tuple2, scala.collection.Seq);
  Code:
   Stack=2, Locals=4, Args_size=4
   0:	aload_0
   1:	aload_1
   2:	invokeinterface	#112,  2; //InterfaceMethod scala/collection/immutable/MapLike.$plus:(Lscala/Tuple2;)Lscala/collection/immutable/Map;
   7:	aload_2
   8:	invokeinterface	#113,  2; //InterfaceMethod scala/collection/immutable/Map.$plus:(Lscala/Tuple2;)Lscala/collection/immutable/Map;
   13:	aload_3
   14:	invokeinterface	#116,  2; //InterfaceMethod scala/collection/immutable/MapLike.$plus$plus:(Lscala/collection/Traversable;)Lscala/collection/immutable/Map;
   19:	areturn
  LineNumberTable: 
   line 70: 0

  LocalVariableTable: 
   Start  Length  Slot  Name   Signature
   0      20      0    $this       Lscala/collection/immutable/MapLike;
   0      20      1    elem1       Lscala/Tuple2;
   0      20      2    elem2       Lscala/Tuple2;
   0      20      3    elems       Lscala/collection/Seq;


public static scala.collection.immutable.Map updated(scala.collection.immutable.MapLike, java.lang.Object, java.lang.Object);
  Code:
   Stack=5, Locals=3, Args_size=3
   0:	aload_0
   1:	new	#122; //class scala/Tuple2
   4:	dup
   5:	aload_1
   6:	aload_2
   7:	invokespecial	#125; //Method scala/Tuple2."<init>":(Ljava/lang/Object;Ljava/lang/Object;)V
   10:	invokeinterface	#112,  2; //InterfaceMethod scala/collection/immutable/MapLike.$plus:(Lscala/Tuple2;)Lscala/collection/immutable/Map;
   15:	areturn
  LineNumberTable: 
   line 54: 0

  LocalVariableTable: 
   Start  Length  Slot  Name   Signature
   0      16      0    $this       Lscala/collection/immutable/MapLike;
   0      16      1    key       Ljava/lang/Object;
   0      16      2    value       Ljava/lang/Object;


}

