Compiled from "MapLike.scala"
public final class scala.collection.immutable.MapLike$$anonfun$transform$2 extends java.lang.Object implements scala.Function1,scala.ScalaObject,java.io.Serializable
  SourceFile: "MapLike.scala"
  Scala: length = 0x
   
  InnerClass: 
   public final $anonfun$transform$2=class scala/collection/immutable/MapLike$$anonfun$transform$2 of class scala/collection/immutable/MapLike
  minor version: 0
  major version: 49
  Constant pool:
Asciz	SourceFile;
Asciz	MapLike.scala;
Asciz	<clinit>;
Asciz	()V;
Asciz	Code;
Asciz	serialVersionUID;
Asciz	J;
Asciz	scala/collection/immutable/MapLike$$anonfun$transform$2;
class	scala/collection/immutable/MapLike$$anonfun$transform$2
NameAndType	serialVersionUID:J
Field	scala/collection/immutable/MapLike$$anonfun$transform$2.serialVersionUID:J
Asciz	b$1;
Asciz	Lscala/collection/mutable/Builder;;
Asciz	f$1;
Asciz	Lscala/Function2;;
Asciz	<init>;
Asciz	(Lscala/collection/immutable/MapLike;Lscala/Function2;Lscala/collection/mutable/Builder;)V;
Asciz	LineNumberTable;
NameAndType	f$1:Lscala/Function2;
Field	scala/collection/immutable/MapLike$$anonfun$transform$2.f$1:Lscala/Function2;
NameAndType	b$1:Lscala/collection/mutable/Builder;
Field	scala/collection/immutable/MapLike$$anonfun$transform$2.b$1:Lscala/collection/mutable/Builder;
Asciz	java/lang/Object;
class	java/lang/Object
NameAndType	"<init>":()V
Method	java/lang/Object."<init>":()V
Asciz	scala/Function1$class;
class	scala/Function1$class
Asciz	$init$;
Asciz	(Lscala/Function1;)V;
NameAndType	$init$:(Lscala/Function1;)V
Method	scala/Function1$class.$init$:(Lscala/Function1;)V
Asciz	this;
Asciz	Lscala/collection/immutable/MapLike$$anonfun$transform$2;;
Asciz	$outer;
Asciz	Lscala/collection/immutable/MapLike;;
Asciz	LocalVariableTable;
Asciz	(Lscala/collection/immutable/MapLike<TA;TB;TThis;>;)V;
Asciz	Signature;
Asciz	apply;
Asciz	(Ljava/lang/Object;)Ljava/lang/Object;;
Asciz	scala/Tuple2;
class	scala/Tuple2
Asciz	(Lscala/Tuple2;)Lscala/collection/mutable/Builder;;
NameAndType	apply:(Lscala/Tuple2;)Lscala/collection/mutable/Builder;
Method	scala/collection/immutable/MapLike$$anonfun$transform$2.apply:(Lscala/Tuple2;)Lscala/collection/mutable/Builder;
Asciz	v1;
Asciz	Ljava/lang/Object;;
Asciz	_1;
Asciz	()Ljava/lang/Object;;
NameAndType	_1:()Ljava/lang/Object;
Method	scala/Tuple2._1:()Ljava/lang/Object;
Asciz	_2;
NameAndType	_2:()Ljava/lang/Object;
Method	scala/Tuple2._2:()Ljava/lang/Object;
Asciz	scala/Function2;
class	scala/Function2
Asciz	(Ljava/lang/Object;Ljava/lang/Object;)Ljava/lang/Object;;
NameAndType	apply:(Ljava/lang/Object;Ljava/lang/Object;)Ljava/lang/Object;
InterfaceMethod	scala/Function2.apply:(Ljava/lang/Object;Ljava/lang/Object;)Ljava/lang/Object;
Asciz	(Ljava/lang/Object;Ljava/lang/Object;)V;
NameAndType	"<init>":(Ljava/lang/Object;Ljava/lang/Object;)V
Method	scala/Tuple2."<init>":(Ljava/lang/Object;Ljava/lang/Object;)V
Asciz	scala/collection/mutable/Builder;
class	scala/collection/mutable/Builder
Asciz	$plus$eq;
Asciz	(Ljava/lang/Object;)Lscala/collection/mutable/Builder;;
NameAndType	$plus$eq:(Ljava/lang/Object;)Lscala/collection/mutable/Builder;
InterfaceMethod	scala/collection/mutable/Builder.$plus$eq:(Ljava/lang/Object;)Lscala/collection/mutable/Builder;
Asciz	scala/MatchError;
class	scala/MatchError
Asciz	toString;
Asciz	()Ljava/lang/String;;
NameAndType	toString:()Ljava/lang/String;
Method	scala/Tuple2.toString:()Ljava/lang/String;
Asciz	(Ljava/lang/String;)V;
NameAndType	"<init>":(Ljava/lang/String;)V
Method	scala/MatchError."<init>":(Ljava/lang/String;)V
Asciz	temp5;
Asciz	temp6;
Asciz	(Lscala/Tuple2<TA;TB;>;)Lscala/collection/mutable/Builder<Lscala/Tuple2<TA;TC;>;TThat;>;;
Asciz	andThen;
Asciz	(Lscala/Function1;)Lscala/Function1;;
Asciz	(Lscala/Function1;Lscala/Function1;)Lscala/Function1;;
NameAndType	andThen:(Lscala/Function1;Lscala/Function1;)Lscala/Function1;
Method	scala/Function1$class.andThen:(Lscala/Function1;Lscala/Function1;)Lscala/Function1;
Asciz	g;
Asciz	Lscala/Function1;;
Asciz	compose;
NameAndType	compose:(Lscala/Function1;Lscala/Function1;)Lscala/Function1;
Method	scala/Function1$class.compose:(Lscala/Function1;Lscala/Function1;)Lscala/Function1;
Asciz	(Lscala/Function1;)Ljava/lang/String;;
NameAndType	toString:(Lscala/Function1;)Ljava/lang/String;
Method	scala/Function1$class.toString:(Lscala/Function1;)Ljava/lang/String;
Asciz	Scala;
Asciz	InnerClasses;
Asciz	scala/collection/immutable/MapLike;
class	scala/collection/immutable/MapLike
Asciz	$anonfun$transform$2;
Asciz	scala/Function1;
class	scala/Function1
Asciz	scala/ScalaObject;
class	scala/ScalaObject
Asciz	java/io/Serializable;
class	java/io/Serializable

{
public static final long serialVersionUID;
  Signature: J

private final scala.collection.mutable.Builder b$1;
  Signature: Lscala/collection/mutable/Builder;

private final scala.Function2 f$1;
  Signature: Lscala/Function2;

public static {};
  Signature: ()V
  Code:
   Stack=2, Locals=0, Args_size=0
	lconst_0
	putstatic	Field serialVersionUID:J
	return
  Labels:

public scala.collection.immutable.MapLike$$anonfun$transform$2(scala.collection.immutable.MapLike, scala.Function2, scala.collection.mutable.Builder);
  Signature: (Lscala/collection/immutable/MapLike;Lscala/Function2;Lscala/collection/mutable/Builder;)V
  Code:
   Stack=2, Locals=4, Args_size=4
	aload_0
	aload_2
	putfield	Field f$1:Lscala/Function2;
	aload_0
	aload_3
	putfield	Field b$1:Lscala/collection/mutable/Builder;
	aload_0
	invokespecial	Method java/lang/Object."<init>":()V
	aload_0
	invokestatic	Method scala/Function1$class.$init$:(Lscala/Function1;)V
	return
  Labels:
  LocalVariableTable: 
   Start  Length  Slot  Name   Signature
   0      19      0    this       Lscala/collection/immutable/MapLike$$anonfun$transform$2;
   0      19      1    $outer       Lscala/collection/immutable/MapLike;

  Signature: length = 0x2
   00 26 

public final java.lang.Object apply(java.lang.Object);
  Signature: (Ljava/lang/Object;)Ljava/lang/Object;
  Code:
   Stack=2, Locals=2, Args_size=2
	aload_0
	aload_1
	checkcast	class scala/Tuple2
	invokevirtual	Method apply:(Lscala/Tuple2;)Lscala/collection/mutable/Builder;
	areturn
  Labels:
  LocalVariableTable: 
   Start  Length  Slot  Name   Signature
   0      9      0    this       Lscala/collection/immutable/MapLike$$anonfun$transform$2;
   0      9      1    v1       Ljava/lang/Object;


public final scala.collection.mutable.Builder apply(scala.Tuple2);
  Signature: (Lscala/Tuple2;)Lscala/collection/mutable/Builder;
  Code:
   Stack=7, Locals=4, Args_size=2
	aload_1
	ifnull	l1 // new
	aload_1
	invokevirtual	Method scala/Tuple2._1:()Ljava/lang/Object;
	astore_2
	aload_1
	invokevirtual	Method scala/Tuple2._2:()Ljava/lang/Object;
	astore_3
	iconst_1
	ifeq	l2 // new
	aload_0
	getfield	Field b$1:Lscala/collection/mutable/Builder;
	new	class scala/Tuple2
	dup
	aload_2
	aload_0
	getfield	Field f$1:Lscala/Function2;
	aload_2
	aload_3
	invokeinterface	InterfaceMethod scala/Function2.apply:(Ljava/lang/Object;Ljava/lang/Object;)Ljava/lang/Object;
	invokespecial	Method scala/Tuple2."<init>":(Ljava/lang/Object;Ljava/lang/Object;)V
	invokeinterface	InterfaceMethod scala/collection/mutable/Builder.$plus$eq:(Ljava/lang/Object;)Lscala/collection/mutable/Builder;
	areturn
l2	new	class scala/MatchError
	dup
	aload_1
	invokevirtual	Method scala/Tuple2.toString:()Ljava/lang/String;
	invokespecial	Method scala/MatchError."<init>":(Ljava/lang/String;)V
	athrow
l1	new	class scala/MatchError
	dup
	aload_1
	invokevirtual	Method scala/Tuple2.toString:()Ljava/lang/String;
	invokespecial	Method scala/MatchError."<init>":(Ljava/lang/String;)V
	athrow
  Labels:
   	l2 = 47 // new
   	l1 = 59 // new
  LocalVariableTable: 
   Start  Length  Slot  Name   Signature
   0      71      0    this       Lscala/collection/immutable/MapLike$$anonfun$transform$2;
   9      50      2    temp5       Ljava/lang/Object;
   14      45      3    temp6       Ljava/lang/Object;

  Signature: length = 0x2
   00 51 

public scala.Function1 andThen(scala.Function1);
  Signature: (Lscala/Function1;)Lscala/Function1;
  Code:
   Stack=2, Locals=2, Args_size=2
	aload_0
	aload_1
	invokestatic	Method scala/Function1$class.andThen:(Lscala/Function1;Lscala/Function1;)Lscala/Function1;
	areturn
  Labels:
  LocalVariableTable: 
   Start  Length  Slot  Name   Signature
   0      6      0    this       Lscala/collection/immutable/MapLike$$anonfun$transform$2;
   0      6      1    g       Lscala/Function1;


public scala.Function1 compose(scala.Function1);
  Signature: (Lscala/Function1;)Lscala/Function1;
  Code:
   Stack=2, Locals=2, Args_size=2
	aload_0
	aload_1
	invokestatic	Method scala/Function1$class.compose:(Lscala/Function1;Lscala/Function1;)Lscala/Function1;
	areturn
  Labels:
  LocalVariableTable: 
   Start  Length  Slot  Name   Signature
   0      6      0    this       Lscala/collection/immutable/MapLike$$anonfun$transform$2;
   0      6      1    g       Lscala/Function1;


public java.lang.String toString();
  Signature: ()Ljava/lang/String;
  Code:
   Stack=1, Locals=1, Args_size=1
	aload_0
	invokestatic	Method scala/Function1$class.toString:(Lscala/Function1;)Ljava/lang/String;
	areturn
  Labels:

}

