Compiled from "MapLike.scala"
public final class scala.collection.immutable.MapLike$$anon$2$$anonfun$foreach$3 extends scala.runtime.AbstractFunction1 implements java.io.Serializable
  SourceFile: "MapLike.scala"
  Scala: length = 0x
   
  InnerClass: 
   public final $anon$2=class scala/collection/immutable/MapLike$$anon$2 of class scala/collection/immutable/MapLike
   public final $anonfun$foreach$3=class scala/collection/immutable/MapLike$$anon$2$$anonfun$foreach$3 of class scala/collection/immutable/MapLike$$anon$2
  minor version: 0
  major version: 49
  Constant pool:
Asciz	SourceFile;
Asciz	MapLike.scala;
Asciz	<clinit>;
Asciz	()V;
Asciz	Code;
Asciz	serialVersionUID;
Asciz	J;
Asciz	scala/collection/immutable/MapLike$$anon$2$$anonfun$foreach$3;
class	scala/collection/immutable/MapLike$$anon$2$$anonfun$foreach$3
NameAndType	serialVersionUID:J
Field	scala/collection/immutable/MapLike$$anon$2$$anonfun$foreach$3.serialVersionUID:J
Asciz	g$1;
Asciz	Lscala/Function1;;
Asciz	$outer;
Asciz	Lscala/collection/immutable/MapLike$$anon$2;;
Asciz	apply;
Asciz	(Lscala/Tuple2;)Ljava/lang/Object;;
Asciz	LineNumberTable;
NameAndType	g$1:Lscala/Function1;
Field	scala/collection/immutable/MapLike$$anon$2$$anonfun$foreach$3.g$1:Lscala/Function1;
Asciz	scala/Tuple2;
class	scala/Tuple2
Asciz	_1;
Asciz	()Ljava/lang/Object;;
NameAndType	_1:()Ljava/lang/Object;
Method	scala/Tuple2._1:()Ljava/lang/Object;
NameAndType	$outer:Lscala/collection/immutable/MapLike$$anon$2;
Field	scala/collection/immutable/MapLike$$anon$2$$anonfun$foreach$3.$outer:Lscala/collection/immutable/MapLike$$anon$2;
Asciz	scala/collection/immutable/MapLike$$anon$2;
class	scala/collection/immutable/MapLike$$anon$2
Asciz	f$1;
NameAndType	f$1:Lscala/Function1;
Field	scala/collection/immutable/MapLike$$anon$2.f$1:Lscala/Function1;
Asciz	_2;
NameAndType	_2:()Ljava/lang/Object;
Method	scala/Tuple2._2:()Ljava/lang/Object;
Asciz	scala/Function1;
class	scala/Function1
Asciz	(Ljava/lang/Object;)Ljava/lang/Object;;
NameAndType	apply:(Ljava/lang/Object;)Ljava/lang/Object;
InterfaceMethod	scala/Function1.apply:(Ljava/lang/Object;)Ljava/lang/Object;
Asciz	<init>;
Asciz	(Ljava/lang/Object;Ljava/lang/Object;)V;
NameAndType	"<init>":(Ljava/lang/Object;Ljava/lang/Object;)V
Method	scala/Tuple2."<init>":(Ljava/lang/Object;Ljava/lang/Object;)V
Asciz	scala/MatchError;
class	scala/MatchError
Asciz	toString;
Asciz	()Ljava/lang/String;;
NameAndType	toString:()Ljava/lang/String;
Method	scala/Tuple2.toString:()Ljava/lang/String;
Asciz	(Ljava/lang/String;)V;
NameAndType	"<init>":(Ljava/lang/String;)V
Method	scala/MatchError."<init>":(Ljava/lang/String;)V
Asciz	(Lscala/Tuple2<TA;TB;>;)TD;;
Asciz	Signature;
NameAndType	apply:(Lscala/Tuple2;)Ljava/lang/Object;
Method	scala/collection/immutable/MapLike$$anon$2$$anonfun$foreach$3.apply:(Lscala/Tuple2;)Ljava/lang/Object;
Asciz	this;
Asciz	Lscala/collection/immutable/MapLike$$anon$2$$anonfun$foreach$3;;
Asciz	v1;
Asciz	Ljava/lang/Object;;
Asciz	LocalVariableTable;
Asciz	(Lscala/collection/immutable/MapLike$$anon$2;Lscala/Function1;)V;
Asciz	java/lang/NullPointerException;
class	java/lang/NullPointerException
NameAndType	"<init>":()V
Method	java/lang/NullPointerException."<init>":()V
Asciz	scala/runtime/AbstractFunction1;
class	scala/runtime/AbstractFunction1
Method	scala/runtime/AbstractFunction1."<init>":()V
Asciz	(Lscala/collection/immutable/MapLike<TA;TB;TThis;>.$anon$2;)V;
Asciz	Scala;
Asciz	InnerClasses;
Asciz	scala/collection/immutable/MapLike;
class	scala/collection/immutable/MapLike
Asciz	$anon$2;
Asciz	$anonfun$foreach$3;
Asciz	java/io/Serializable;
class	java/io/Serializable

{
public static final long serialVersionUID;
  Signature: J

public final scala.Function1 g$1;
  Signature: Lscala/Function1;

public final scala.collection.immutable.MapLike$$anon$2 $outer;
  Signature: Lscala/collection/immutable/MapLike$$anon$2;

public static {};
  Signature: ()V
  Code:
   Stack=2, Locals=0, Args_size=0
	lconst_0
	putstatic	Field serialVersionUID:J
	return
  Labels:

public final java.lang.Object apply(scala.Tuple2);
  Signature: (Lscala/Tuple2;)Ljava/lang/Object;
  Code:
   Stack=6, Locals=2, Args_size=2
	aload_1
	ifnull	l1 // new
	aload_0
	getfield	Field g$1:Lscala/Function1;
	new	class scala/Tuple2
	dup
	aload_1
	invokevirtual	Method scala/Tuple2._1:()Ljava/lang/Object;
	aload_0
	getfield	Field $outer:Lscala/collection/immutable/MapLike$$anon$2;
	getfield	Field scala/collection/immutable/MapLike$$anon$2.f$1:Lscala/Function1;
	aload_1
	invokevirtual	Method scala/Tuple2._2:()Ljava/lang/Object;
	invokeinterface	InterfaceMethod scala/Function1.apply:(Ljava/lang/Object;)Ljava/lang/Object;
	invokespecial	Method scala/Tuple2."<init>":(Ljava/lang/Object;Ljava/lang/Object;)V
	invokeinterface	InterfaceMethod scala/Function1.apply:(Ljava/lang/Object;)Ljava/lang/Object;
	areturn
l1	new	class scala/MatchError
	dup
	aload_1
	invokevirtual	Method scala/Tuple2.toString:()Ljava/lang/String;
	invokespecial	Method scala/MatchError."<init>":(Ljava/lang/String;)V
	athrow
  Labels:
   	l1 = 41 // new
  Signature: length = 0x2
   00 37 

public final java.lang.Object apply(java.lang.Object);
  Signature: (Ljava/lang/Object;)Ljava/lang/Object;
  Code:
   Stack=2, Locals=2, Args_size=2
	aload_0
	aload_1
	checkcast	class scala/Tuple2
	invokevirtual	Method apply:(Lscala/Tuple2;)Ljava/lang/Object;
	areturn
  Labels:
  LocalVariableTable: 
   Start  Length  Slot  Name   Signature
   0      9      0    this       Lscala/collection/immutable/MapLike$$anon$2$$anonfun$foreach$3;
   0      9      1    v1       Ljava/lang/Object;


public scala.collection.immutable.MapLike$$anon$2$$anonfun$foreach$3(scala.collection.immutable.MapLike$$anon$2, scala.Function1);
  Signature: (Lscala/collection/immutable/MapLike$$anon$2;Lscala/Function1;)V
  Code:
   Stack=2, Locals=3, Args_size=3
	aload_1
	ifnonnull	l1 // aload_0
	new	class java/lang/NullPointerException
	dup
	invokespecial	Method java/lang/NullPointerException."<init>":()V
	athrow
l1	aload_0
	aload_1
	putfield	Field $outer:Lscala/collection/immutable/MapLike$$anon$2;
	aload_0
	aload_2
	putfield	Field g$1:Lscala/Function1;
	aload_0
	invokespecial	Method scala/runtime/AbstractFunction1."<init>":()V
	return
  Labels:
   	l1 = 12 // aload_0
  LocalVariableTable: 
   Start  Length  Slot  Name   Signature
   0      27      0    this       Lscala/collection/immutable/MapLike$$anon$2$$anonfun$foreach$3;
   0      27      1    $outer       Lscala/collection/immutable/MapLike$$anon$2;

  Signature: length = 0x2
   00 48 

}

