Compiled from "MapLike.scala"
public final class scala.collection.immutable.MapLike$$anonfun$filterNot$1 extends scala.runtime.AbstractFunction1 implements java.io.Serializable
  SourceFile: "MapLike.scala"
  Scala: length = 0x
   
  InnerClass: 
   public final $anonfun$filterNot$1=class scala/collection/immutable/MapLike$$anonfun$filterNot$1 of class scala/collection/immutable/MapLike
  minor version: 0
  major version: 49
  Constant pool:
Asciz	SourceFile;
Asciz	MapLike.scala;
Asciz	<clinit>;
Asciz	()V;
Asciz	Code;
Asciz	serialVersionUID;
Asciz	J;
Asciz	scala/collection/immutable/MapLike$$anonfun$filterNot$1;
class	scala/collection/immutable/MapLike$$anonfun$filterNot$1
NameAndType	serialVersionUID:J
Field	scala/collection/immutable/MapLike$$anonfun$filterNot$1.serialVersionUID:J
Asciz	res$1;
Asciz	Lscala/runtime/ObjectRef;;
Asciz	p$1;
Asciz	Lscala/Function1;;
Asciz	<init>;
Asciz	(Lscala/collection/immutable/MapLike;Lscala/Function1;Lscala/runtime/ObjectRef;)V;
Asciz	LineNumberTable;
NameAndType	p$1:Lscala/Function1;
Field	scala/collection/immutable/MapLike$$anonfun$filterNot$1.p$1:Lscala/Function1;
NameAndType	res$1:Lscala/runtime/ObjectRef;
Field	scala/collection/immutable/MapLike$$anonfun$filterNot$1.res$1:Lscala/runtime/ObjectRef;
Asciz	scala/runtime/AbstractFunction1;
class	scala/runtime/AbstractFunction1
NameAndType	"<init>":()V
Method	scala/runtime/AbstractFunction1."<init>":()V
Asciz	this;
Asciz	Lscala/collection/immutable/MapLike$$anonfun$filterNot$1;;
Asciz	$outer;
Asciz	Lscala/collection/immutable/MapLike;;
Asciz	LocalVariableTable;
Asciz	(Lscala/collection/immutable/MapLike<TA;TB;TThis;>;)V;
Asciz	Signature;
Asciz	apply;
Asciz	(Ljava/lang/Object;)Ljava/lang/Object;;
Asciz	scala/Tuple2;
class	scala/Tuple2
Asciz	(Lscala/Tuple2;)V;
NameAndType	apply:(Lscala/Tuple2;)V
Method	scala/collection/immutable/MapLike$$anonfun$filterNot$1.apply:(Lscala/Tuple2;)V
Asciz	scala/runtime/BoxedUnit;
class	scala/runtime/BoxedUnit
Asciz	UNIT;
Asciz	Lscala/runtime/BoxedUnit;;
NameAndType	UNIT:Lscala/runtime/BoxedUnit;
Field	scala/runtime/BoxedUnit.UNIT:Lscala/runtime/BoxedUnit;
Asciz	v1;
Asciz	Ljava/lang/Object;;
Asciz	scala/Function1;
class	scala/Function1
NameAndType	apply:(Ljava/lang/Object;)Ljava/lang/Object;
InterfaceMethod	scala/Function1.apply:(Ljava/lang/Object;)Ljava/lang/Object;
Asciz	scala/runtime/BoxesRunTime;
class	scala/runtime/BoxesRunTime
Asciz	unboxToBoolean;
Asciz	(Ljava/lang/Object;)Z;
NameAndType	unboxToBoolean:(Ljava/lang/Object;)Z
Method	scala/runtime/BoxesRunTime.unboxToBoolean:(Ljava/lang/Object;)Z
Asciz	scala/runtime/ObjectRef;
class	scala/runtime/ObjectRef
Asciz	elem;
NameAndType	elem:Ljava/lang/Object;
Field	scala/runtime/ObjectRef.elem:Ljava/lang/Object;
Asciz	scala/collection/immutable/Map;
class	scala/collection/immutable/Map
Asciz	_1;
Asciz	()Ljava/lang/Object;;
NameAndType	_1:()Ljava/lang/Object;
Method	scala/Tuple2._1:()Ljava/lang/Object;
Asciz	scala/collection/MapLike;
class	scala/collection/MapLike
Asciz	$minus;
Asciz	(Ljava/lang/Object;)Lscala/collection/Map;;
NameAndType	$minus:(Ljava/lang/Object;)Lscala/collection/Map;
InterfaceMethod	scala/collection/MapLike.$minus:(Ljava/lang/Object;)Lscala/collection/Map;
Asciz	kv;
Asciz	Lscala/Tuple2;;
Asciz	(Lscala/Tuple2<TA;TB;>;)V;
Asciz	Scala;
Asciz	InnerClasses;
Asciz	scala/collection/immutable/MapLike;
class	scala/collection/immutable/MapLike
Asciz	$anonfun$filterNot$1;
Asciz	java/io/Serializable;
class	java/io/Serializable

{
public static final long serialVersionUID;
  Signature: J

private final scala.runtime.ObjectRef res$1;
  Signature: Lscala/runtime/ObjectRef;

private final scala.Function1 p$1;
  Signature: Lscala/Function1;

public static {};
  Signature: ()V
  Code:
   Stack=2, Locals=0, Args_size=0
	lconst_0
	putstatic	Field serialVersionUID:J
	return
  Labels:

public scala.collection.immutable.MapLike$$anonfun$filterNot$1(scala.collection.immutable.MapLike, scala.Function1, scala.runtime.ObjectRef);
  Signature: (Lscala/collection/immutable/MapLike;Lscala/Function1;Lscala/runtime/ObjectRef;)V
  Code:
   Stack=2, Locals=4, Args_size=4
	aload_0
	aload_2
	putfield	Field p$1:Lscala/Function1;
	aload_0
	aload_3
	putfield	Field res$1:Lscala/runtime/ObjectRef;
	aload_0
	invokespecial	Method scala/runtime/AbstractFunction1."<init>":()V
	return
  Labels:
  LocalVariableTable: 
   Start  Length  Slot  Name   Signature
   0      15      0    this       Lscala/collection/immutable/MapLike$$anonfun$filterNot$1;
   0      15      1    $outer       Lscala/collection/immutable/MapLike;

  Signature: length = 0x2
   00 20 

public final java.lang.Object apply(java.lang.Object);
  Signature: (Ljava/lang/Object;)Ljava/lang/Object;
  Code:
   Stack=2, Locals=2, Args_size=2
	aload_0
	aload_1
	checkcast	class scala/Tuple2
	invokevirtual	Method apply:(Lscala/Tuple2;)V
	getstatic	Field scala/runtime/BoxedUnit.UNIT:Lscala/runtime/BoxedUnit;
	areturn
  Labels:
  LocalVariableTable: 
   Start  Length  Slot  Name   Signature
   0      12      0    this       Lscala/collection/immutable/MapLike$$anonfun$filterNot$1;
   0      12      1    v1       Ljava/lang/Object;


public final void apply(scala.Tuple2);
  Signature: (Lscala/Tuple2;)V
  Code:
   Stack=3, Locals=2, Args_size=2
	aload_0
	getfield	Field p$1:Lscala/Function1;
	aload_1
	invokeinterface	InterfaceMethod scala/Function1.apply:(Ljava/lang/Object;)Ljava/lang/Object;
	invokestatic	Method scala/runtime/BoxesRunTime.unboxToBoolean:(Ljava/lang/Object;)Z
	ifeq	l1 // return
	aload_0
	getfield	Field res$1:Lscala/runtime/ObjectRef;
	aload_0
	getfield	Field res$1:Lscala/runtime/ObjectRef;
	getfield	Field scala/runtime/ObjectRef.elem:Ljava/lang/Object;
	checkcast	class scala/collection/immutable/Map
	aload_1
	invokevirtual	Method scala/Tuple2._1:()Ljava/lang/Object;
	invokeinterface	InterfaceMethod scala/collection/MapLike.$minus:(Ljava/lang/Object;)Lscala/collection/Map;
	checkcast	class scala/collection/immutable/Map
	putfield	Field scala/runtime/ObjectRef.elem:Ljava/lang/Object;
l1	return
  Labels:
   	l1 = 45 // return
  LocalVariableTable: 
   Start  Length  Slot  Name   Signature
   0      46      0    this       Lscala/collection/immutable/MapLike$$anonfun$filterNot$1;
   0      46      1    kv       Lscala/Tuple2;

  Signature: length = 0x2
   00 4E 

}

