Compiled from "MapProxy.scala"
public abstract class scala.collection.immutable.MapProxy$class extends java.lang.Object
  SourceFile: "MapProxy.scala"
  Scala: length = 0x
   
  InnerClass: 
   public final #74= #62 of #73; //$anon$1=class scala/collection/immutable/MapProxy$$anon$1 of class scala/collection/immutable/MapProxy
  minor version: 0
  major version: 49
  Constant pool:
const #1 = Asciz	SourceFile;
const #2 = Asciz	MapProxy.scala;
const #3 = Asciz	$init$;
const #4 = Asciz	(Lscala/collection/immutable/MapProxy;)V;
const #5 = Asciz	Code;
const #6 = Asciz	LineNumberTable;
const #7 = Asciz	$this;
const #8 = Asciz	Lscala/collection/immutable/MapProxy;;
const #9 = Asciz	LocalVariableTable;
const #10 = Asciz	$minus;
const #11 = Asciz	(Lscala/collection/immutable/MapProxy;Ljava/lang/Object;)Lscala/collection/immutable/MapProxy;;
const #12 = Asciz	scala/collection/TraversableProxyLike;
const #13 = class	#12;	//  scala/collection/TraversableProxyLike
const #14 = Asciz	self;
const #15 = Asciz	()Lscala/collection/TraversableLike;;
const #16 = NameAndType	#14:#15;//  self:()Lscala/collection/TraversableLike;
const #17 = InterfaceMethod	#13.#16;	//  scala/collection/TraversableProxyLike.self:()Lscala/collection/TraversableLike;
const #18 = Asciz	scala/collection/MapLike;
const #19 = class	#18;	//  scala/collection/MapLike
const #20 = Asciz	(Ljava/lang/Object;)Lscala/collection/MapLike;;
const #21 = NameAndType	#10:#20;//  $minus:(Ljava/lang/Object;)Lscala/collection/MapLike;
const #22 = InterfaceMethod	#19.#21;	//  scala/collection/MapLike.$minus:(Ljava/lang/Object;)Lscala/collection/MapLike;
const #23 = Asciz	scala/collection/immutable/Map;
const #24 = class	#23;	//  scala/collection/immutable/Map
const #25 = Asciz	scala/collection/immutable/MapProxy$class;
const #26 = class	#25;	//  scala/collection/immutable/MapProxy$class
const #27 = Asciz	newProxy;
const #28 = Asciz	(Lscala/collection/immutable/MapProxy;Lscala/collection/immutable/Map;)Lscala/collection/immutable/MapProxy;;
const #29 = NameAndType	#27:#28;//  newProxy:(Lscala/collection/immutable/MapProxy;Lscala/collection/immutable/Map;)Lscala/collection/immutable/MapProxy;
const #30 = Method	#26.#29;	//  scala/collection/immutable/MapProxy$class.newProxy:(Lscala/collection/immutable/MapProxy;Lscala/collection/immutable/Map;)Lscala/collection/immutable/MapProxy;
const #31 = Asciz	key;
const #32 = Asciz	Ljava/lang/Object;;
const #33 = Asciz	$plus;
const #34 = Asciz	(Lscala/collection/immutable/MapProxy;Lscala/Tuple2;Lscala/Tuple2;Lscala/collection/Seq;)Lscala/collection/immutable/MapProxy;;
const #35 = Asciz	scala/collection/immutable/MapLike;
const #36 = class	#35;	//  scala/collection/immutable/MapLike
const #37 = Asciz	(Lscala/Tuple2;Lscala/Tuple2;Lscala/collection/Seq;)Lscala/collection/immutable/Map;;
const #38 = NameAndType	#33:#37;//  $plus:(Lscala/Tuple2;Lscala/Tuple2;Lscala/collection/Seq;)Lscala/collection/immutable/Map;
const #39 = InterfaceMethod	#36.#38;	//  scala/collection/immutable/MapLike.$plus:(Lscala/Tuple2;Lscala/Tuple2;Lscala/collection/Seq;)Lscala/collection/immutable/Map;
const #40 = Asciz	elem1;
const #41 = Asciz	Lscala/Tuple2;;
const #42 = Asciz	elem2;
const #43 = Asciz	elems;
const #44 = Asciz	Lscala/collection/Seq;;
const #45 = Asciz	(Lscala/collection/immutable/MapProxy;Lscala/Tuple2;)Lscala/collection/immutable/Map;;
const #46 = Asciz	(Lscala/Tuple2;)Lscala/collection/immutable/Map;;
const #47 = NameAndType	#33:#46;//  $plus:(Lscala/Tuple2;)Lscala/collection/immutable/Map;
const #48 = InterfaceMethod	#24.#47;	//  scala/collection/immutable/Map.$plus:(Lscala/Tuple2;)Lscala/collection/immutable/Map;
const #49 = Asciz	kv;
const #50 = Asciz	updated;
const #51 = Asciz	(Lscala/collection/immutable/MapProxy;Ljava/lang/Object;Ljava/lang/Object;)Lscala/collection/immutable/MapProxy;;
const #52 = Asciz	(Ljava/lang/Object;Ljava/lang/Object;)Lscala/collection/immutable/Map;;
const #53 = NameAndType	#50:#52;//  updated:(Ljava/lang/Object;Ljava/lang/Object;)Lscala/collection/immutable/Map;
const #54 = InterfaceMethod	#36.#53;	//  scala/collection/immutable/MapLike.updated:(Ljava/lang/Object;Ljava/lang/Object;)Lscala/collection/immutable/Map;
const #55 = Asciz	value;
const #56 = Asciz	empty;
const #57 = Asciz	(Lscala/collection/immutable/MapProxy;)Lscala/collection/immutable/MapProxy;;
const #58 = Asciz	()Lscala/collection/immutable/Map;;
const #59 = NameAndType	#56:#58;//  empty:()Lscala/collection/immutable/Map;
const #60 = InterfaceMethod	#24.#59;	//  scala/collection/immutable/Map.empty:()Lscala/collection/immutable/Map;
const #61 = Asciz	scala/collection/immutable/MapProxy$$anon$1;
const #62 = class	#61;	//  scala/collection/immutable/MapProxy$$anon$1
const #63 = Asciz	<init>;
const #64 = Asciz	(Lscala/collection/immutable/MapProxy;Lscala/collection/immutable/Map;)V;
const #65 = NameAndType	#63:#64;//  "<init>":(Lscala/collection/immutable/MapProxy;Lscala/collection/immutable/Map;)V
const #66 = Method	#62.#65;	//  scala/collection/immutable/MapProxy$$anon$1."<init>":(Lscala/collection/immutable/MapProxy;Lscala/collection/immutable/Map;)V
const #67 = Asciz	newSelf$1;
const #68 = Asciz	Lscala/collection/immutable/Map;;
const #69 = Asciz	repr;
const #70 = Asciz	Scala;
const #71 = Asciz	InnerClasses;
const #72 = Asciz	scala/collection/immutable/MapProxy;
const #73 = class	#72;	//  scala/collection/immutable/MapProxy
const #74 = Asciz	$anon$1;
const #75 = Asciz	java/lang/Object;
const #76 = class	#75;	//  java/lang/Object

{
public static void $init$(scala.collection.immutable.MapProxy);
  Code:
   Stack=0, Locals=1, Args_size=1
   0:	return
  LineNumberTable: 
   line 28: 0

  LocalVariableTable: 
   Start  Length  Slot  Name   Signature
   0      1      0    $this       Lscala/collection/immutable/MapProxy;


public static scala.collection.immutable.MapProxy $minus(scala.collection.immutable.MapProxy, java.lang.Object);
  Code:
   Stack=3, Locals=2, Args_size=2
   0:	aload_0
   1:	aload_0
   2:	invokeinterface	#17,  1; //InterfaceMethod scala/collection/TraversableProxyLike.self:()Lscala/collection/TraversableLike;
   7:	checkcast	#19; //class scala/collection/MapLike
   10:	aload_1
   11:	invokeinterface	#22,  2; //InterfaceMethod scala/collection/MapLike.$minus:(Ljava/lang/Object;)Lscala/collection/MapLike;
   16:	checkcast	#24; //class scala/collection/immutable/Map
   19:	invokestatic	#30; //Method newProxy:(Lscala/collection/immutable/MapProxy;Lscala/collection/immutable/Map;)Lscala/collection/immutable/MapProxy;
   22:	areturn
  LineNumberTable: 
   line 40: 0

  LocalVariableTable: 
   Start  Length  Slot  Name   Signature
   0      23      0    $this       Lscala/collection/immutable/MapProxy;
   0      23      1    key       Ljava/lang/Object;


public static scala.collection.immutable.MapProxy $plus(scala.collection.immutable.MapProxy, scala.Tuple2, scala.Tuple2, scala.collection.Seq);
  Code:
   Stack=5, Locals=4, Args_size=4
   0:	aload_0
   1:	aload_0
   2:	invokeinterface	#17,  1; //InterfaceMethod scala/collection/TraversableProxyLike.self:()Lscala/collection/TraversableLike;
   7:	checkcast	#36; //class scala/collection/immutable/MapLike
   10:	aload_1
   11:	aload_2
   12:	aload_3
   13:	invokeinterface	#39,  4; //InterfaceMethod scala/collection/immutable/MapLike.$plus:(Lscala/Tuple2;Lscala/Tuple2;Lscala/collection/Seq;)Lscala/collection/immutable/Map;
   18:	invokestatic	#30; //Method newProxy:(Lscala/collection/immutable/MapProxy;Lscala/collection/immutable/Map;)Lscala/collection/immutable/MapProxy;
   21:	areturn
  LineNumberTable: 
   line 39: 0

  LocalVariableTable: 
   Start  Length  Slot  Name   Signature
   0      22      0    $this       Lscala/collection/immutable/MapProxy;
   0      22      1    elem1       Lscala/Tuple2;
   0      22      2    elem2       Lscala/Tuple2;
   0      22      3    elems       Lscala/collection/Seq;


public static scala.collection.immutable.Map $plus(scala.collection.immutable.MapProxy, scala.Tuple2);
  Code:
   Stack=3, Locals=2, Args_size=2
   0:	aload_0
   1:	aload_0
   2:	invokeinterface	#17,  1; //InterfaceMethod scala/collection/TraversableProxyLike.self:()Lscala/collection/TraversableLike;
   7:	checkcast	#24; //class scala/collection/immutable/Map
   10:	aload_1
   11:	invokeinterface	#48,  2; //InterfaceMethod scala/collection/immutable/Map.$plus:(Lscala/Tuple2;)Lscala/collection/immutable/Map;
   16:	invokestatic	#30; //Method newProxy:(Lscala/collection/immutable/MapProxy;Lscala/collection/immutable/Map;)Lscala/collection/immutable/MapProxy;
   19:	areturn
  LineNumberTable: 
   line 37: 0

  LocalVariableTable: 
   Start  Length  Slot  Name   Signature
   0      20      0    $this       Lscala/collection/immutable/MapProxy;
   0      20      1    kv       Lscala/Tuple2;


public static scala.collection.immutable.MapProxy updated(scala.collection.immutable.MapProxy, java.lang.Object, java.lang.Object);
  Code:
   Stack=4, Locals=3, Args_size=3
   0:	aload_0
   1:	aload_0
   2:	invokeinterface	#17,  1; //InterfaceMethod scala/collection/TraversableProxyLike.self:()Lscala/collection/TraversableLike;
   7:	checkcast	#36; //class scala/collection/immutable/MapLike
   10:	aload_1
   11:	aload_2
   12:	invokeinterface	#54,  3; //InterfaceMethod scala/collection/immutable/MapLike.updated:(Ljava/lang/Object;Ljava/lang/Object;)Lscala/collection/immutable/Map;
   17:	invokestatic	#30; //Method newProxy:(Lscala/collection/immutable/MapProxy;Lscala/collection/immutable/Map;)Lscala/collection/immutable/MapProxy;
   20:	areturn
  LineNumberTable: 
   line 35: 0

  LocalVariableTable: 
   Start  Length  Slot  Name   Signature
   0      21      0    $this       Lscala/collection/immutable/MapProxy;
   0      21      1    key       Ljava/lang/Object;
   0      21      2    value       Ljava/lang/Object;


public static scala.collection.immutable.MapProxy empty(scala.collection.immutable.MapProxy);
  Code:
   Stack=2, Locals=1, Args_size=1
   0:	aload_0
   1:	aload_0
   2:	invokeinterface	#17,  1; //InterfaceMethod scala/collection/TraversableProxyLike.self:()Lscala/collection/TraversableLike;
   7:	checkcast	#24; //class scala/collection/immutable/Map
   10:	invokeinterface	#60,  1; //InterfaceMethod scala/collection/immutable/Map.empty:()Lscala/collection/immutable/Map;
   15:	invokestatic	#30; //Method newProxy:(Lscala/collection/immutable/MapProxy;Lscala/collection/immutable/Map;)Lscala/collection/immutable/MapProxy;
   18:	areturn
  LineNumberTable: 
   line 34: 0

  LocalVariableTable: 
   Start  Length  Slot  Name   Signature
   0      19      0    $this       Lscala/collection/immutable/MapProxy;


public static scala.collection.immutable.MapProxy repr(scala.collection.immutable.MapProxy);
  Code:
   Stack=1, Locals=1, Args_size=1
   0:	aload_0
   1:	areturn
  LineNumberTable: 
   line 30: 0

  LocalVariableTable: 
   Start  Length  Slot  Name   Signature
   0      2      0    $this       Lscala/collection/immutable/MapProxy;


}

