Compiled from "List.scala"
public final class scala.collection.immutable.Nil extends java.lang.Object
  SourceFile: "List.scala"
  ScalaSig: length = 0x3
   05 00 00 
  RuntimeVisibleAnnotations: length = 0xB
   00 01 02 5F 00 01 02 60 73 02 61 
  InnerClass: 
   public abstract $less$colon$less=class scala/Predef$$less$colon$less of class scala/Predef
   public WithFilter=class scala/collection/TraversableLike$WithFilter of class scala/collection/TraversableLike
  minor version: 0
  major version: 49
  Constant pool:
Asciz	SourceFile;
Asciz	List.scala;
Asciz	productElement;
Asciz	(I)Ljava/lang/Object;;
Asciz	Code;
Asciz	scala/collection/immutable/Nil$;
class	scala/collection/immutable/Nil$
Asciz	MODULE$;
Asciz	Lscala/collection/immutable/Nil$;;
NameAndType	MODULE$:Lscala/collection/immutable/Nil$;
Field	scala/collection/immutable/Nil$.MODULE$:Lscala/collection/immutable/Nil$;
NameAndType	productElement:(I)Ljava/lang/Object;
Method	scala/collection/immutable/Nil$.productElement:(I)Ljava/lang/Object;
Asciz	productArity;
Asciz	()I;
NameAndType	productArity:()I
Method	scala/collection/immutable/Nil$.productArity:()I
Asciz	productPrefix;
Asciz	()Ljava/lang/String;;
NameAndType	productPrefix:()Ljava/lang/String;
Method	scala/collection/immutable/Nil$.productPrefix:()Ljava/lang/String;
Asciz	tail;
Asciz	()Lscala/collection/immutable/List;;
NameAndType	tail:()Lscala/collection/immutable/List;
Method	scala/collection/immutable/Nil$.tail:()Lscala/collection/immutable/List;
Asciz	()Lscala/collection/immutable/List<Lscala/runtime/Nothing$;>;;
Asciz	Signature;
Asciz	head;
Asciz	()Lscala/runtime/Nothing$;;
NameAndType	head:()Lscala/runtime/Nothing$;
Method	scala/collection/immutable/Nil$.head:()Lscala/runtime/Nothing$;
Asciz	isEmpty;
Asciz	()Z;
NameAndType	isEmpty:()Z
Method	scala/collection/immutable/Nil$.isEmpty:()Z
Asciz	addString;
Asciz	(Lscala/collection/mutable/StringBuilder;)Lscala/collection/mutable/StringBuilder;;
NameAndType	addString:(Lscala/collection/mutable/StringBuilder;)Lscala/collection/mutable/StringBuilder;
Method	scala/collection/immutable/Nil$.addString:(Lscala/collection/mutable/StringBuilder;)Lscala/collection/mutable/StringBuilder;
Asciz	(Lscala/collection/mutable/StringBuilder;Ljava/lang/String;)Lscala/collection/mutable/StringBuilder;;
NameAndType	addString:(Lscala/collection/mutable/StringBuilder;Ljava/lang/String;)Lscala/collection/mutable/StringBuilder;
Method	scala/collection/immutable/Nil$.addString:(Lscala/collection/mutable/StringBuilder;Ljava/lang/String;)Lscala/collection/mutable/StringBuilder;
Asciz	(Lscala/collection/mutable/StringBuilder;Ljava/lang/String;Ljava/lang/String;Ljava/lang/String;)Lscala/collection/mutable/StringBuilder;;
NameAndType	addString:(Lscala/collection/mutable/StringBuilder;Ljava/lang/String;Ljava/lang/String;Ljava/lang/String;)Lscala/collection/mutable/StringBuilder;
Method	scala/collection/immutable/Nil$.addString:(Lscala/collection/mutable/StringBuilder;Ljava/lang/String;Ljava/lang/String;Ljava/lang/String;)Lscala/collection/mutable/StringBuilder;
Asciz	mkString;
NameAndType	mkString:()Ljava/lang/String;
Method	scala/collection/immutable/Nil$.mkString:()Ljava/lang/String;
Asciz	(Ljava/lang/String;)Ljava/lang/String;;
NameAndType	mkString:(Ljava/lang/String;)Ljava/lang/String;
Method	scala/collection/immutable/Nil$.mkString:(Ljava/lang/String;)Ljava/lang/String;
Asciz	(Ljava/lang/String;Ljava/lang/String;Ljava/lang/String;)Ljava/lang/String;;
NameAndType	mkString:(Ljava/lang/String;Ljava/lang/String;Ljava/lang/String;)Ljava/lang/String;
Method	scala/collection/immutable/Nil$.mkString:(Ljava/lang/String;Ljava/lang/String;Ljava/lang/String;)Ljava/lang/String;
Asciz	toMap;
Asciz	(Lscala/Predef$$less$colon$less;)Lscala/collection/immutable/Map;;
NameAndType	toMap:(Lscala/Predef$$less$colon$less;)Lscala/collection/immutable/Map;
Method	scala/collection/immutable/Nil$.toMap:(Lscala/Predef$$less$colon$less;)Lscala/collection/immutable/Map;
Asciz	toSet;
Asciz	()Lscala/collection/immutable/Set;;
NameAndType	toSet:()Lscala/collection/immutable/Set;
Method	scala/collection/immutable/Nil$.toSet:()Lscala/collection/immutable/Set;
Asciz	toIndexedSeq;
Asciz	()Lscala/collection/mutable/IndexedSeq;;
NameAndType	toIndexedSeq:()Lscala/collection/mutable/IndexedSeq;
Method	scala/collection/immutable/Nil$.toIndexedSeq:()Lscala/collection/mutable/IndexedSeq;
Asciz	toArray;
Asciz	(Lscala/reflect/ClassManifest;)Ljava/lang/Object;;
NameAndType	toArray:(Lscala/reflect/ClassManifest;)Ljava/lang/Object;
Method	scala/collection/immutable/Nil$.toArray:(Lscala/reflect/ClassManifest;)Ljava/lang/Object;
Asciz	copyToArray;
Asciz	(Ljava/lang/Object;)V;
NameAndType	copyToArray:(Ljava/lang/Object;)V
Method	scala/collection/immutable/Nil$.copyToArray:(Ljava/lang/Object;)V
Asciz	(Ljava/lang/Object;I)V;
NameAndType	copyToArray:(Ljava/lang/Object;I)V
Method	scala/collection/immutable/Nil$.copyToArray:(Ljava/lang/Object;I)V
Asciz	copyToBuffer;
Asciz	(Lscala/collection/mutable/Buffer;)V;
NameAndType	copyToBuffer:(Lscala/collection/mutable/Buffer;)V
Method	scala/collection/immutable/Nil$.copyToBuffer:(Lscala/collection/mutable/Buffer;)V
Asciz	max;
Asciz	(Lscala/math/Ordering;)Ljava/lang/Object;;
NameAndType	max:(Lscala/math/Ordering;)Ljava/lang/Object;
Method	scala/collection/immutable/Nil$.max:(Lscala/math/Ordering;)Ljava/lang/Object;
Asciz	min;
NameAndType	min:(Lscala/math/Ordering;)Ljava/lang/Object;
Method	scala/collection/immutable/Nil$.min:(Lscala/math/Ordering;)Ljava/lang/Object;
Asciz	product;
Asciz	(Lscala/math/Numeric;)Ljava/lang/Object;;
NameAndType	product:(Lscala/math/Numeric;)Ljava/lang/Object;
Method	scala/collection/immutable/Nil$.product:(Lscala/math/Numeric;)Ljava/lang/Object;
Asciz	sum;
NameAndType	sum:(Lscala/math/Numeric;)Ljava/lang/Object;
Method	scala/collection/immutable/Nil$.sum:(Lscala/math/Numeric;)Ljava/lang/Object;
Asciz	reduceRightOption;
Asciz	(Lscala/Function2;)Lscala/Option;;
NameAndType	reduceRightOption:(Lscala/Function2;)Lscala/Option;
Method	scala/collection/immutable/Nil$.reduceRightOption:(Lscala/Function2;)Lscala/Option;
Asciz	reduceLeftOption;
NameAndType	reduceLeftOption:(Lscala/Function2;)Lscala/Option;
Method	scala/collection/immutable/Nil$.reduceLeftOption:(Lscala/Function2;)Lscala/Option;
Asciz	$colon$bslash;
Asciz	(Ljava/lang/Object;Lscala/Function2;)Ljava/lang/Object;;
NameAndType	$colon$bslash:(Ljava/lang/Object;Lscala/Function2;)Ljava/lang/Object;
Method	scala/collection/immutable/Nil$.$colon$bslash:(Ljava/lang/Object;Lscala/Function2;)Ljava/lang/Object;
Asciz	$div$colon;
NameAndType	$div$colon:(Ljava/lang/Object;Lscala/Function2;)Ljava/lang/Object;
Method	scala/collection/immutable/Nil$.$div$colon:(Ljava/lang/Object;Lscala/Function2;)Ljava/lang/Object;
Asciz	nonEmpty;
NameAndType	nonEmpty:()Z
Method	scala/collection/immutable/Nil$.nonEmpty:()Z
Asciz	withFilter;
Asciz	(Lscala/Function1;)Lscala/collection/TraversableLike$WithFilter;;
NameAndType	withFilter:(Lscala/Function1;)Lscala/collection/TraversableLike$WithFilter;
Method	scala/collection/immutable/Nil$.withFilter:(Lscala/Function1;)Lscala/collection/TraversableLike$WithFilter;
Asciz	toIterator;
Asciz	()Lscala/collection/Iterator;;
NameAndType	toIterator:()Lscala/collection/Iterator;
Method	scala/collection/immutable/Nil$.toIterator:()Lscala/collection/Iterator;
Asciz	toTraversable;
Asciz	()Lscala/collection/Traversable;;
NameAndType	toTraversable:()Lscala/collection/Traversable;
Method	scala/collection/immutable/Nil$.toTraversable:()Lscala/collection/Traversable;
Asciz	init;
Asciz	()Ljava/lang/Object;;
NameAndType	init:()Ljava/lang/Object;
Method	scala/collection/immutable/Nil$.init:()Ljava/lang/Object;
Asciz	lastOption;
Asciz	()Lscala/Option;;
NameAndType	lastOption:()Lscala/Option;
Method	scala/collection/immutable/Nil$.lastOption:()Lscala/Option;
NameAndType	tail:()Ljava/lang/Object;
Method	scala/collection/immutable/Nil$.tail:()Ljava/lang/Object;
Asciz	headOption;
NameAndType	headOption:()Lscala/Option;
Method	scala/collection/immutable/Nil$.headOption:()Lscala/Option;
Asciz	scanRight;
Asciz	(Ljava/lang/Object;Lscala/Function2;Lscala/collection/generic/CanBuildFrom;)Ljava/lang/Object;;
NameAndType	scanRight:(Ljava/lang/Object;Lscala/Function2;Lscala/collection/generic/CanBuildFrom;)Ljava/lang/Object;
Method	scala/collection/immutable/Nil$.scanRight:(Ljava/lang/Object;Lscala/Function2;Lscala/collection/generic/CanBuildFrom;)Ljava/lang/Object;
Asciz	scanLeft;
NameAndType	scanLeft:(Ljava/lang/Object;Lscala/Function2;Lscala/collection/generic/CanBuildFrom;)Ljava/lang/Object;
Method	scala/collection/immutable/Nil$.scanLeft:(Ljava/lang/Object;Lscala/Function2;Lscala/collection/generic/CanBuildFrom;)Ljava/lang/Object;
Asciz	groupBy;
Asciz	(Lscala/Function1;)Lscala/collection/Map;;
NameAndType	groupBy:(Lscala/Function1;)Lscala/collection/Map;
Method	scala/collection/immutable/Nil$.groupBy:(Lscala/Function1;)Lscala/collection/Map;
Asciz	partition;
Asciz	(Lscala/Function1;)Lscala/Tuple2;;
NameAndType	partition:(Lscala/Function1;)Lscala/Tuple2;
Method	scala/collection/immutable/Nil$.partition:(Lscala/Function1;)Lscala/Tuple2;
Asciz	collect;
Asciz	(Lscala/PartialFunction;Lscala/collection/generic/CanBuildFrom;)Ljava/lang/Object;;
NameAndType	collect:(Lscala/PartialFunction;Lscala/collection/generic/CanBuildFrom;)Ljava/lang/Object;
Method	scala/collection/immutable/Nil$.collect:(Lscala/PartialFunction;Lscala/collection/generic/CanBuildFrom;)Ljava/lang/Object;
Asciz	filterNot;
Asciz	(Lscala/Function1;)Ljava/lang/Object;;
NameAndType	filterNot:(Lscala/Function1;)Ljava/lang/Object;
Method	scala/collection/immutable/Nil$.filterNot:(Lscala/Function1;)Ljava/lang/Object;
Asciz	filter;
NameAndType	filter:(Lscala/Function1;)Ljava/lang/Object;
Method	scala/collection/immutable/Nil$.filter:(Lscala/Function1;)Ljava/lang/Object;
Asciz	flatMap;
Asciz	(Lscala/Function1;Lscala/collection/generic/CanBuildFrom;)Ljava/lang/Object;;
NameAndType	flatMap:(Lscala/Function1;Lscala/collection/generic/CanBuildFrom;)Ljava/lang/Object;
Method	scala/collection/immutable/Nil$.flatMap:(Lscala/Function1;Lscala/collection/generic/CanBuildFrom;)Ljava/lang/Object;
Asciz	map;
NameAndType	map:(Lscala/Function1;Lscala/collection/generic/CanBuildFrom;)Ljava/lang/Object;
Method	scala/collection/immutable/Nil$.map:(Lscala/Function1;Lscala/collection/generic/CanBuildFrom;)Ljava/lang/Object;
Asciz	hasDefiniteSize;
NameAndType	hasDefiniteSize:()Z
Method	scala/collection/immutable/Nil$.hasDefiniteSize:()Z
Asciz	isTraversableAgain;
NameAndType	isTraversableAgain:()Z
Method	scala/collection/immutable/Nil$.isTraversableAgain:()Z
Asciz	repr;
NameAndType	repr:()Ljava/lang/Object;
Method	scala/collection/immutable/Nil$.repr:()Ljava/lang/Object;
Asciz	transpose;
Asciz	(Lscala/Function1;)Lscala/collection/Traversable;;
NameAndType	transpose:(Lscala/Function1;)Lscala/collection/Traversable;
Method	scala/collection/immutable/Nil$.transpose:(Lscala/Function1;)Lscala/collection/Traversable;
Asciz	flatten;
NameAndType	flatten:(Lscala/Function1;)Lscala/collection/Traversable;
Method	scala/collection/immutable/Nil$.flatten:(Lscala/Function1;)Lscala/collection/Traversable;
Asciz	unzip;
NameAndType	unzip:(Lscala/Function1;)Lscala/Tuple2;
Method	scala/collection/immutable/Nil$.unzip:(Lscala/Function1;)Lscala/Tuple2;
Asciz	genericBuilder;
Asciz	()Lscala/collection/mutable/Builder;;
NameAndType	genericBuilder:()Lscala/collection/mutable/Builder;
Method	scala/collection/immutable/Nil$.genericBuilder:()Lscala/collection/mutable/Builder;
Asciz	firstOption;
NameAndType	firstOption:()Lscala/Option;
Method	scala/collection/immutable/Nil$.firstOption:()Lscala/Option;
Asciz	Deprecated;
Asciz	first;
NameAndType	first:()Ljava/lang/Object;
Method	scala/collection/immutable/Nil$.first:()Ljava/lang/Object;
Asciz	elements;
NameAndType	elements:()Lscala/collection/Iterator;
Method	scala/collection/immutable/Nil$.elements:()Lscala/collection/Iterator;
Asciz	canEqual;
Asciz	(Ljava/lang/Object;)Z;
NameAndType	canEqual:(Ljava/lang/Object;)Z
Method	scala/collection/immutable/Nil$.canEqual:(Ljava/lang/Object;)Z
Asciz	zipWithIndex;
Asciz	(Lscala/collection/generic/CanBuildFrom;)Ljava/lang/Object;;
NameAndType	zipWithIndex:(Lscala/collection/generic/CanBuildFrom;)Ljava/lang/Object;
Method	scala/collection/immutable/Nil$.zipWithIndex:(Lscala/collection/generic/CanBuildFrom;)Ljava/lang/Object;
Asciz	zipAll;
Asciz	(Lscala/collection/Iterable;Ljava/lang/Object;Ljava/lang/Object;Lscala/collection/generic/CanBuildFrom;)Ljava/lang/Object;;
NameAndType	zipAll:(Lscala/collection/Iterable;Ljava/lang/Object;Ljava/lang/Object;Lscala/collection/generic/CanBuildFrom;)Ljava/lang/Object;
Method	scala/collection/immutable/Nil$.zipAll:(Lscala/collection/Iterable;Ljava/lang/Object;Ljava/lang/Object;Lscala/collection/generic/CanBuildFrom;)Ljava/lang/Object;
Asciz	zip;
Asciz	(Lscala/collection/Iterable;Lscala/collection/generic/CanBuildFrom;)Ljava/lang/Object;;
NameAndType	zip:(Lscala/collection/Iterable;Lscala/collection/generic/CanBuildFrom;)Ljava/lang/Object;
Method	scala/collection/immutable/Nil$.zip:(Lscala/collection/Iterable;Lscala/collection/generic/CanBuildFrom;)Ljava/lang/Object;
Asciz	(Ljava/lang/Object;II)V;
NameAndType	copyToArray:(Ljava/lang/Object;II)V
Method	scala/collection/immutable/Nil$.copyToArray:(Ljava/lang/Object;II)V
Asciz	sliding;
Asciz	(II)Lscala/collection/Iterator;;
NameAndType	sliding:(II)Lscala/collection/Iterator;
Method	scala/collection/immutable/Nil$.sliding:(II)Lscala/collection/Iterator;
Asciz	(I)Lscala/collection/Iterator;;
NameAndType	sliding:(I)Lscala/collection/Iterator;
Method	scala/collection/immutable/Nil$.sliding:(I)Lscala/collection/Iterator;
Asciz	grouped;
NameAndType	grouped:(I)Lscala/collection/Iterator;
Method	scala/collection/immutable/Nil$.grouped:(I)Lscala/collection/Iterator;
Asciz	toIterable;
Asciz	()Lscala/collection/Iterable;;
NameAndType	toIterable:()Lscala/collection/Iterable;
Method	scala/collection/immutable/Nil$.toIterable:()Lscala/collection/Iterable;
Asciz	compose;
Asciz	(Lscala/Function1;)Lscala/Function1;;
NameAndType	compose:(Lscala/Function1;)Lscala/Function1;
Method	scala/collection/immutable/Nil$.compose:(Lscala/Function1;)Lscala/Function1;
Asciz	lift;
Asciz	()Lscala/Function1;;
NameAndType	lift:()Lscala/Function1;
Method	scala/collection/immutable/Nil$.lift:()Lscala/Function1;
Asciz	andThen;
Asciz	(Lscala/Function1;)Lscala/PartialFunction;;
NameAndType	andThen:(Lscala/Function1;)Lscala/PartialFunction;
Method	scala/collection/immutable/Nil$.andThen:(Lscala/Function1;)Lscala/PartialFunction;
Asciz	orElse;
Asciz	(Lscala/PartialFunction;)Lscala/PartialFunction;;
NameAndType	orElse:(Lscala/PartialFunction;)Lscala/PartialFunction;
Method	scala/collection/immutable/Nil$.orElse:(Lscala/PartialFunction;)Lscala/PartialFunction;
Asciz	projection;
Asciz	()Lscala/collection/SeqView;;
NameAndType	projection:()Lscala/collection/SeqView;
Method	scala/collection/immutable/Nil$.projection:()Lscala/collection/SeqView;
Asciz	equalsWith;
Asciz	(Lscala/collection/Seq;Lscala/Function2;)Z;
NameAndType	equalsWith:(Lscala/collection/Seq;Lscala/Function2;)Z
Method	scala/collection/immutable/Nil$.equalsWith:(Lscala/collection/Seq;Lscala/Function2;)Z
Asciz	findLastIndexOf;
Asciz	(Lscala/Function1;)I;
NameAndType	findLastIndexOf:(Lscala/Function1;)I
Method	scala/collection/immutable/Nil$.findLastIndexOf:(Lscala/Function1;)I
Asciz	view;
Asciz	(II)Lscala/collection/SeqView;;
NameAndType	view:(II)Lscala/collection/SeqView;
Method	scala/collection/immutable/Nil$.view:(II)Lscala/collection/SeqView;
NameAndType	view:()Lscala/collection/SeqView;
Method	scala/collection/immutable/Nil$.view:()Lscala/collection/SeqView;
Asciz	indices;
Asciz	()Lscala/collection/immutable/Range;;
NameAndType	indices:()Lscala/collection/immutable/Range;
Method	scala/collection/immutable/Nil$.indices:()Lscala/collection/immutable/Range;
Asciz	toSeq;
Asciz	()Lscala/collection/Seq;;
NameAndType	toSeq:()Lscala/collection/Seq;
Method	scala/collection/immutable/Nil$.toSeq:()Lscala/collection/Seq;
Asciz	sorted;
NameAndType	sorted:(Lscala/math/Ordering;)Ljava/lang/Object;
Method	scala/collection/immutable/Nil$.sorted:(Lscala/math/Ordering;)Ljava/lang/Object;
Asciz	sortBy;
Asciz	(Lscala/Function1;Lscala/math/Ordering;)Ljava/lang/Object;;
NameAndType	sortBy:(Lscala/Function1;Lscala/math/Ordering;)Ljava/lang/Object;
Method	scala/collection/immutable/Nil$.sortBy:(Lscala/Function1;Lscala/math/Ordering;)Ljava/lang/Object;
Asciz	sortWith;
Asciz	(Lscala/Function2;)Ljava/lang/Object;;
NameAndType	sortWith:(Lscala/Function2;)Ljava/lang/Object;
Method	scala/collection/immutable/Nil$.sortWith:(Lscala/Function2;)Ljava/lang/Object;
Asciz	corresponds;
NameAndType	corresponds:(Lscala/collection/Seq;Lscala/Function2;)Z
Method	scala/collection/immutable/Nil$.corresponds:(Lscala/collection/Seq;Lscala/Function2;)Z
Asciz	padTo;
Asciz	(ILjava/lang/Object;Lscala/collection/generic/CanBuildFrom;)Ljava/lang/Object;;
NameAndType	padTo:(ILjava/lang/Object;Lscala/collection/generic/CanBuildFrom;)Ljava/lang/Object;
Method	scala/collection/immutable/Nil$.padTo:(ILjava/lang/Object;Lscala/collection/generic/CanBuildFrom;)Ljava/lang/Object;
Asciz	$colon$plus;
Asciz	(Ljava/lang/Object;Lscala/collection/generic/CanBuildFrom;)Ljava/lang/Object;;
NameAndType	$colon$plus:(Ljava/lang/Object;Lscala/collection/generic/CanBuildFrom;)Ljava/lang/Object;
Method	scala/collection/immutable/Nil$.$colon$plus:(Ljava/lang/Object;Lscala/collection/generic/CanBuildFrom;)Ljava/lang/Object;
Asciz	updated;
NameAndType	updated:(ILjava/lang/Object;Lscala/collection/generic/CanBuildFrom;)Ljava/lang/Object;
Method	scala/collection/immutable/Nil$.updated:(ILjava/lang/Object;Lscala/collection/generic/CanBuildFrom;)Ljava/lang/Object;
Asciz	patch;
Asciz	(ILscala/collection/Seq;ILscala/collection/generic/CanBuildFrom;)Ljava/lang/Object;;
NameAndType	patch:(ILscala/collection/Seq;ILscala/collection/generic/CanBuildFrom;)Ljava/lang/Object;
Method	scala/collection/immutable/Nil$.patch:(ILscala/collection/Seq;ILscala/collection/generic/CanBuildFrom;)Ljava/lang/Object;
Asciz	distinct;
NameAndType	distinct:()Ljava/lang/Object;
Method	scala/collection/immutable/Nil$.distinct:()Ljava/lang/Object;
Asciz	intersect;
Asciz	(Lscala/collection/Seq;)Ljava/lang/Object;;
NameAndType	intersect:(Lscala/collection/Seq;)Ljava/lang/Object;
Method	scala/collection/immutable/Nil$.intersect:(Lscala/collection/Seq;)Ljava/lang/Object;
Asciz	diff;
NameAndType	diff:(Lscala/collection/Seq;)Ljava/lang/Object;
Method	scala/collection/immutable/Nil$.diff:(Lscala/collection/Seq;)Ljava/lang/Object;
Asciz	union;
Asciz	(Lscala/collection/Seq;Lscala/collection/generic/CanBuildFrom;)Ljava/lang/Object;;
NameAndType	union:(Lscala/collection/Seq;Lscala/collection/generic/CanBuildFrom;)Ljava/lang/Object;
Method	scala/collection/immutable/Nil$.union:(Lscala/collection/Seq;Lscala/collection/generic/CanBuildFrom;)Ljava/lang/Object;
Asciz	contains;
NameAndType	contains:(Ljava/lang/Object;)Z
Method	scala/collection/immutable/Nil$.contains:(Ljava/lang/Object;)Z
Asciz	containsSlice;
Asciz	(Lscala/collection/Seq;)Z;
NameAndType	containsSlice:(Lscala/collection/Seq;)Z
Method	scala/collection/immutable/Nil$.containsSlice:(Lscala/collection/Seq;)Z
Asciz	lastIndexOfSlice;
Asciz	(Lscala/collection/Seq;I)I;
NameAndType	lastIndexOfSlice:(Lscala/collection/Seq;I)I
Method	scala/collection/immutable/Nil$.lastIndexOfSlice:(Lscala/collection/Seq;I)I
Asciz	(Lscala/collection/Seq;)I;
NameAndType	lastIndexOfSlice:(Lscala/collection/Seq;)I
Method	scala/collection/immutable/Nil$.lastIndexOfSlice:(Lscala/collection/Seq;)I
Asciz	indexOfSlice;
NameAndType	indexOfSlice:(Lscala/collection/Seq;I)I
Method	scala/collection/immutable/Nil$.indexOfSlice:(Lscala/collection/Seq;I)I
NameAndType	indexOfSlice:(Lscala/collection/Seq;)I
Method	scala/collection/immutable/Nil$.indexOfSlice:(Lscala/collection/Seq;)I
Asciz	endsWith;
NameAndType	endsWith:(Lscala/collection/Seq;)Z
Method	scala/collection/immutable/Nil$.endsWith:(Lscala/collection/Seq;)Z
Asciz	startsWith;
NameAndType	startsWith:(Lscala/collection/Seq;)Z
Method	scala/collection/immutable/Nil$.startsWith:(Lscala/collection/Seq;)Z
Asciz	(Lscala/collection/Seq;I)Z;
NameAndType	startsWith:(Lscala/collection/Seq;I)Z
Method	scala/collection/immutable/Nil$.startsWith:(Lscala/collection/Seq;I)Z
Asciz	reversedElements;
NameAndType	reversedElements:()Lscala/collection/Iterator;
Method	scala/collection/immutable/Nil$.reversedElements:()Lscala/collection/Iterator;
Asciz	reverseIterator;
NameAndType	reverseIterator:()Lscala/collection/Iterator;
Method	scala/collection/immutable/Nil$.reverseIterator:()Lscala/collection/Iterator;
Asciz	reverseMap;
NameAndType	reverseMap:(Lscala/Function1;Lscala/collection/generic/CanBuildFrom;)Ljava/lang/Object;
Method	scala/collection/immutable/Nil$.reverseMap:(Lscala/Function1;Lscala/collection/generic/CanBuildFrom;)Ljava/lang/Object;
Asciz	lastIndexWhere;
NameAndType	lastIndexWhere:(Lscala/Function1;)I
Method	scala/collection/immutable/Nil$.lastIndexWhere:(Lscala/Function1;)I
Asciz	lastIndexOf;
Asciz	(Ljava/lang/Object;I)I;
NameAndType	lastIndexOf:(Ljava/lang/Object;I)I
Method	scala/collection/immutable/Nil$.lastIndexOf:(Ljava/lang/Object;I)I
Asciz	(Ljava/lang/Object;)I;
NameAndType	lastIndexOf:(Ljava/lang/Object;)I
Method	scala/collection/immutable/Nil$.lastIndexOf:(Ljava/lang/Object;)I
Asciz	indexOf;
NameAndType	indexOf:(Ljava/lang/Object;I)I
Method	scala/collection/immutable/Nil$.indexOf:(Ljava/lang/Object;I)I
NameAndType	indexOf:(Ljava/lang/Object;)I
Method	scala/collection/immutable/Nil$.indexOf:(Ljava/lang/Object;)I
Asciz	findIndexOf;
NameAndType	findIndexOf:(Lscala/Function1;)I
Method	scala/collection/immutable/Nil$.findIndexOf:(Lscala/Function1;)I
Asciz	indexWhere;
NameAndType	indexWhere:(Lscala/Function1;)I
Method	scala/collection/immutable/Nil$.indexWhere:(Lscala/Function1;)I
Asciz	prefixLength;
NameAndType	prefixLength:(Lscala/Function1;)I
Method	scala/collection/immutable/Nil$.prefixLength:(Lscala/Function1;)I
Asciz	size;
NameAndType	size:()I
Method	scala/collection/immutable/Nil$.size:()I
Asciz	iterator;
NameAndType	iterator:()Lscala/collection/Iterator;
Method	scala/collection/immutable/Nil$.iterator:()Lscala/collection/Iterator;
Asciz	productElements;
NameAndType	productElements:()Lscala/collection/Iterator;
Method	scala/collection/immutable/Nil$.productElements:()Lscala/collection/Iterator;
Asciz	productIterator;
NameAndType	productIterator:()Lscala/collection/Iterator;
Method	scala/collection/immutable/Nil$.productIterator:()Lscala/collection/Iterator;
Asciz	productElementName;
Asciz	(I)Ljava/lang/String;;
NameAndType	productElementName:(I)Ljava/lang/String;
Method	scala/collection/immutable/Nil$.productElementName:(I)Ljava/lang/String;
Asciz	(Lscala/Function1;I)I;
NameAndType	lastIndexWhere:(Lscala/Function1;I)I
Method	scala/collection/immutable/Nil$.lastIndexWhere:(Lscala/Function1;I)I
NameAndType	indexWhere:(Lscala/Function1;I)I
Method	scala/collection/immutable/Nil$.indexWhere:(Lscala/Function1;I)I
Asciz	segmentLength;
NameAndType	segmentLength:(Lscala/Function1;I)I
Method	scala/collection/immutable/Nil$.segmentLength:(Lscala/Function1;I)I
Asciz	isDefinedAt;
Asciz	(I)Z;
NameAndType	isDefinedAt:(I)Z
Method	scala/collection/immutable/Nil$.isDefinedAt:(I)Z
Asciz	lengthCompare;
Asciz	(I)I;
NameAndType	lengthCompare:(I)I
Method	scala/collection/immutable/Nil$.lengthCompare:(I)I
Asciz	sameElements;
Asciz	(Lscala/collection/Iterable;)Z;
NameAndType	sameElements:(Lscala/collection/Iterable;)Z
Method	scala/collection/immutable/Nil$.sameElements:(Lscala/collection/Iterable;)Z
Asciz	dropRight;
Asciz	(I)Lscala/collection/LinearSeqOptimized;;
NameAndType	dropRight:(I)Lscala/collection/LinearSeqOptimized;
Method	scala/collection/immutable/Nil$.dropRight:(I)Lscala/collection/LinearSeqOptimized;
Asciz	last;
NameAndType	last:()Ljava/lang/Object;
Method	scala/collection/immutable/Nil$.last:()Ljava/lang/Object;
Asciz	reduceRight;
NameAndType	reduceRight:(Lscala/Function2;)Ljava/lang/Object;
Method	scala/collection/immutable/Nil$.reduceRight:(Lscala/Function2;)Ljava/lang/Object;
Asciz	reduceLeft;
NameAndType	reduceLeft:(Lscala/Function2;)Ljava/lang/Object;
Method	scala/collection/immutable/Nil$.reduceLeft:(Lscala/Function2;)Ljava/lang/Object;
Asciz	foldRight;
NameAndType	foldRight:(Ljava/lang/Object;Lscala/Function2;)Ljava/lang/Object;
Method	scala/collection/immutable/Nil$.foldRight:(Ljava/lang/Object;Lscala/Function2;)Ljava/lang/Object;
Asciz	foldLeft;
NameAndType	foldLeft:(Ljava/lang/Object;Lscala/Function2;)Ljava/lang/Object;
Method	scala/collection/immutable/Nil$.foldLeft:(Ljava/lang/Object;Lscala/Function2;)Ljava/lang/Object;
Asciz	find;
Asciz	(Lscala/Function1;)Lscala/Option;;
NameAndType	find:(Lscala/Function1;)Lscala/Option;
Method	scala/collection/immutable/Nil$.find:(Lscala/Function1;)Lscala/Option;
Asciz	count;
NameAndType	count:(Lscala/Function1;)I
Method	scala/collection/immutable/Nil$.count:(Lscala/Function1;)I
Asciz	exists;
Asciz	(Lscala/Function1;)Z;
NameAndType	exists:(Lscala/Function1;)Z
Method	scala/collection/immutable/Nil$.exists:(Lscala/Function1;)Z
Asciz	forall;
NameAndType	forall:(Lscala/Function1;)Z
Method	scala/collection/immutable/Nil$.forall:(Lscala/Function1;)Z
Asciz	foreach;
Asciz	(Lscala/Function1;)V;
NameAndType	foreach:(Lscala/Function1;)V
Method	scala/collection/immutable/Nil$.foreach:(Lscala/Function1;)V
Asciz	apply;
NameAndType	apply:(I)Ljava/lang/Object;
Method	scala/collection/immutable/Nil$.apply:(I)Ljava/lang/Object;
Asciz	length;
NameAndType	length:()I
Method	scala/collection/immutable/Nil$.length:()I
Asciz	scala$collection$LinearSeqOptimized$$super$sameElements;
NameAndType	scala$collection$LinearSeqOptimized$$super$sameElements:(Lscala/collection/Iterable;)Z
Method	scala/collection/immutable/Nil$.scala$collection$LinearSeqOptimized$$super$sameElements:(Lscala/collection/Iterable;)Z
Asciz	sort;
Asciz	(Lscala/Function2;)Lscala/collection/immutable/List;;
NameAndType	sort:(Lscala/Function2;)Lscala/collection/immutable/List;
Method	scala/collection/immutable/Nil$.sort:(Lscala/Function2;)Lscala/collection/immutable/List;
Asciz	(Lscala/Function2<Lscala/runtime/Nothing$;Lscala/runtime/Nothing$;Ljava/lang/Boolean;>;)Lscala/collection/immutable/List<Lscala/runtime/Nothing$;>;;
Asciz	removeDuplicates;
NameAndType	removeDuplicates:()Lscala/collection/immutable/List;
Method	scala/collection/immutable/Nil$.removeDuplicates:()Lscala/collection/immutable/List;
Asciz	$minus;
Asciz	(Ljava/lang/Object;)Lscala/collection/immutable/List;;
NameAndType	$minus:(Ljava/lang/Object;)Lscala/collection/immutable/List;
Method	scala/collection/immutable/Nil$.$minus:(Ljava/lang/Object;)Lscala/collection/immutable/List;
Asciz	<B:Ljava/lang/Object;>(TB;)Lscala/collection/immutable/List<TB;>;;
Asciz	$minus$minus;
Asciz	(Lscala/collection/immutable/List;)Lscala/collection/immutable/List;;
NameAndType	$minus$minus:(Lscala/collection/immutable/List;)Lscala/collection/immutable/List;
Method	scala/collection/immutable/Nil$.$minus$minus:(Lscala/collection/immutable/List;)Lscala/collection/immutable/List;
Asciz	<B:Ljava/lang/Object;>(Lscala/collection/immutable/List<TB;>;)Lscala/collection/immutable/List<TB;>;;
Asciz	remove;
Asciz	(Lscala/Function1;)Lscala/collection/immutable/List;;
NameAndType	remove:(Lscala/Function1;)Lscala/collection/immutable/List;
Method	scala/collection/immutable/Nil$.remove:(Lscala/Function1;)Lscala/collection/immutable/List;
Asciz	(Lscala/Function1<Lscala/runtime/Nothing$;Ljava/lang/Boolean;>;)Lscala/collection/immutable/List<Lscala/runtime/Nothing$;>;;
Asciz	break;
NameAndType	break:(Lscala/Function1;)Lscala/Tuple2;
Method	scala/collection/immutable/Nil$.break:(Lscala/Function1;)Lscala/Tuple2;
Asciz	(Lscala/Function1<Lscala/runtime/Nothing$;Ljava/lang/Boolean;>;)Lscala/Tuple2<Lscala/collection/immutable/List<Lscala/runtime/Nothing$;>;Lscala/collection/immutable/List<Lscala/runtime/Nothing$;>;>;;
Asciz	toStream;
Asciz	()Lscala/collection/immutable/Stream;;
NameAndType	toStream:()Lscala/collection/immutable/Stream;
Method	scala/collection/immutable/Nil$.toStream:()Lscala/collection/immutable/Stream;
Asciz	()Lscala/collection/immutable/Stream<Lscala/runtime/Nothing$;>;;
Asciz	stringPrefix;
NameAndType	stringPrefix:()Ljava/lang/String;
Method	scala/collection/immutable/Nil$.stringPrefix:()Ljava/lang/String;
Asciz	reverse;
NameAndType	reverse:()Lscala/collection/immutable/List;
Method	scala/collection/immutable/Nil$.reverse:()Lscala/collection/immutable/List;
Asciz	span;
NameAndType	span:(Lscala/Function1;)Lscala/Tuple2;
Method	scala/collection/immutable/Nil$.span:(Lscala/Function1;)Lscala/Tuple2;
Asciz	dropWhile;
NameAndType	dropWhile:(Lscala/Function1;)Lscala/collection/immutable/List;
Method	scala/collection/immutable/Nil$.dropWhile:(Lscala/Function1;)Lscala/collection/immutable/List;
Asciz	takeWhile;
NameAndType	takeWhile:(Lscala/Function1;)Lscala/collection/immutable/List;
Method	scala/collection/immutable/Nil$.takeWhile:(Lscala/Function1;)Lscala/collection/immutable/List;
Asciz	splitAt;
Asciz	(I)Lscala/Tuple2;;
NameAndType	splitAt:(I)Lscala/Tuple2;
Method	scala/collection/immutable/Nil$.splitAt:(I)Lscala/Tuple2;
Asciz	(I)Lscala/Tuple2<Lscala/collection/immutable/List<Lscala/runtime/Nothing$;>;Lscala/collection/immutable/List<Lscala/runtime/Nothing$;>;>;;
Asciz	takeRight;
Asciz	(I)Lscala/collection/immutable/List;;
NameAndType	takeRight:(I)Lscala/collection/immutable/List;
Method	scala/collection/immutable/Nil$.takeRight:(I)Lscala/collection/immutable/List;
Asciz	(I)Lscala/collection/immutable/List<Lscala/runtime/Nothing$;>;;
Asciz	slice;
Asciz	(II)Lscala/collection/immutable/List;;
NameAndType	slice:(II)Lscala/collection/immutable/List;
Method	scala/collection/immutable/Nil$.slice:(II)Lscala/collection/immutable/List;
Asciz	(II)Lscala/collection/immutable/List<Lscala/runtime/Nothing$;>;;
Asciz	drop;
NameAndType	drop:(I)Lscala/collection/immutable/List;
Method	scala/collection/immutable/Nil$.drop:(I)Lscala/collection/immutable/List;
Asciz	take;
NameAndType	take:(I)Lscala/collection/immutable/List;
Method	scala/collection/immutable/Nil$.take:(I)Lscala/collection/immutable/List;
Asciz	toList;
NameAndType	toList:()Lscala/collection/immutable/List;
Method	scala/collection/immutable/Nil$.toList:()Lscala/collection/immutable/List;
Asciz	$plus$colon;
NameAndType	$plus$colon:(Ljava/lang/Object;Lscala/collection/generic/CanBuildFrom;)Ljava/lang/Object;
Method	scala/collection/immutable/Nil$.$plus$colon:(Ljava/lang/Object;Lscala/collection/generic/CanBuildFrom;)Ljava/lang/Object;
Asciz	<B:Ljava/lang/Object;That:Ljava/lang/Object;>(TB;Lscala/collection/generic/CanBuildFrom<Lscala/collection/immutable/List<Lscala/runtime/Nothing$;>;TB;TThat;>;)TThat;;
Asciz	$plus$plus;
Asciz	(Lscala/collection/TraversableOnce;Lscala/collection/generic/CanBuildFrom;)Ljava/lang/Object;;
NameAndType	$plus$plus:(Lscala/collection/TraversableOnce;Lscala/collection/generic/CanBuildFrom;)Ljava/lang/Object;
Method	scala/collection/immutable/Nil$.$plus$plus:(Lscala/collection/TraversableOnce;Lscala/collection/generic/CanBuildFrom;)Ljava/lang/Object;
Asciz	<B:Ljava/lang/Object;That:Ljava/lang/Object;>(Lscala/collection/TraversableOnce<TB;>;Lscala/collection/generic/CanBuildFrom<Lscala/collection/immutable/List<Lscala/runtime/Nothing$;>;TB;TThat;>;)TThat;;
Asciz	mapConserve;
NameAndType	mapConserve:(Lscala/Function1;)Lscala/collection/immutable/List;
Method	scala/collection/immutable/Nil$.mapConserve:(Lscala/Function1;)Lscala/collection/immutable/List;
Asciz	<B:Ljava/lang/Object;>(Lscala/Function1<Lscala/runtime/Nothing$;TB;>;)Lscala/collection/immutable/List<TB;>;;
Asciz	reverse_$colon$colon$colon;
NameAndType	reverse_$colon$colon$colon:(Lscala/collection/immutable/List;)Lscala/collection/immutable/List;
Method	scala/collection/immutable/Nil$.reverse_$colon$colon$colon:(Lscala/collection/immutable/List;)Lscala/collection/immutable/List;
Asciz	$colon$colon$colon;
NameAndType	$colon$colon$colon:(Lscala/collection/immutable/List;)Lscala/collection/immutable/List;
Method	scala/collection/immutable/Nil$.$colon$colon$colon:(Lscala/collection/immutable/List;)Lscala/collection/immutable/List;
Asciz	$colon$colon;
NameAndType	$colon$colon:(Ljava/lang/Object;)Lscala/collection/immutable/List;
Method	scala/collection/immutable/Nil$.$colon$colon:(Ljava/lang/Object;)Lscala/collection/immutable/List;
Asciz	companion;
Asciz	()Lscala/collection/generic/GenericCompanion;;
NameAndType	companion:()Lscala/collection/generic/GenericCompanion;
Method	scala/collection/immutable/Nil$.companion:()Lscala/collection/generic/GenericCompanion;
Asciz	()Lscala/collection/generic/GenericCompanion<Lscala/collection/immutable/List;>;;
Asciz	(Lscala/Function1;)Lscala/collection/LinearSeqOptimized;;
NameAndType	takeWhile:(Lscala/Function1;)Lscala/collection/LinearSeqOptimized;
Method	scala/collection/immutable/Nil$.takeWhile:(Lscala/Function1;)Lscala/collection/LinearSeqOptimized;
Asciz	(II)Lscala/collection/LinearSeqOptimized;;
NameAndType	slice:(II)Lscala/collection/LinearSeqOptimized;
Method	scala/collection/immutable/Nil$.slice:(II)Lscala/collection/LinearSeqOptimized;
NameAndType	drop:(I)Lscala/collection/LinearSeqOptimized;
Method	scala/collection/immutable/Nil$.drop:(I)Lscala/collection/LinearSeqOptimized;
NameAndType	take:(I)Lscala/collection/LinearSeqOptimized;
Method	scala/collection/immutable/Nil$.take:(I)Lscala/collection/LinearSeqOptimized;
NameAndType	reverse:()Ljava/lang/Object;
Method	scala/collection/immutable/Nil$.reverse:()Ljava/lang/Object;
NameAndType	andThen:(Lscala/Function1;)Lscala/Function1;
Method	scala/collection/immutable/Nil$.andThen:(Lscala/Function1;)Lscala/Function1;
Asciz	()Lscala/collection/IterableView;;
NameAndType	projection:()Lscala/collection/IterableView;
Method	scala/collection/immutable/Nil$.projection:()Lscala/collection/IterableView;
Asciz	(II)Lscala/collection/IterableView;;
NameAndType	view:(II)Lscala/collection/IterableView;
Method	scala/collection/immutable/Nil$.view:(II)Lscala/collection/IterableView;
NameAndType	view:()Lscala/collection/IterableView;
Method	scala/collection/immutable/Nil$.view:()Lscala/collection/IterableView;
NameAndType	dropRight:(I)Ljava/lang/Object;
Method	scala/collection/immutable/Nil$.dropRight:(I)Ljava/lang/Object;
NameAndType	takeRight:(I)Ljava/lang/Object;
Method	scala/collection/immutable/Nil$.takeRight:(I)Ljava/lang/Object;
NameAndType	takeWhile:(Lscala/Function1;)Ljava/lang/Object;
Method	scala/collection/immutable/Nil$.takeWhile:(Lscala/Function1;)Ljava/lang/Object;
Asciz	(II)Ljava/lang/Object;;
NameAndType	slice:(II)Ljava/lang/Object;
Method	scala/collection/immutable/Nil$.slice:(II)Ljava/lang/Object;
NameAndType	take:(I)Ljava/lang/Object;
Method	scala/collection/immutable/Nil$.take:(I)Ljava/lang/Object;
Asciz	(II)Lscala/collection/TraversableView;;
NameAndType	view:(II)Lscala/collection/TraversableView;
Method	scala/collection/immutable/Nil$.view:(II)Lscala/collection/TraversableView;
Asciz	()Lscala/collection/TraversableView;;
NameAndType	view:()Lscala/collection/TraversableView;
Method	scala/collection/immutable/Nil$.view:()Lscala/collection/TraversableView;
NameAndType	dropWhile:(Lscala/Function1;)Ljava/lang/Object;
Method	scala/collection/immutable/Nil$.dropWhile:(Lscala/Function1;)Ljava/lang/Object;
NameAndType	drop:(I)Ljava/lang/Object;
Method	scala/collection/immutable/Nil$.drop:(I)Ljava/lang/Object;
Asciz	ScalaSig;
Asciz	Lscala/reflect/ScalaSignature;;
Asciz	bytes;
Asciz	a;Q!\t&\t1AT5m\tA!Aj[6,H/2mK*QABG>dG.Z2uS>t'\"AM\r\1A!bCAABC#UBAOS2Ba1A!bD\t\nA!'jgR\"AE\nI!9{G[5oOB!CF/1bU2bY|%M[3diB!#G5q:pIVGCQ$=S:LGO!)qdC!A9n]#naRLX#AIBAun7fC:DQ!JB\nA[3bIV\tC)&uC&dW#\t-ZA\t\rX/7t)\t\tSC/Uq&uQ$C\n1\t\tdAAB]fDbM%\tNaJ|G-^2u!J,g-=U\"AN]R!O\t1gnu!!.<b\tatGTiJLgn\t}-!\t!C!aO]8ek$I]5usV\t\t&!I:$#\tII#AxZ;dicW-\3oiRqF\t1A\rAH%\r\t.!\t!C\tY!/Z1e%x<f)YCM\tiuGPE*,7\r=C\nQ\t\tfA\tTKJL\r,feNLwN\+J\tzAQ2qvt-=U)B!#V-Ab]3sSdN_1cYD3A(S;
Asciz	RuntimeVisibleAnnotations;
Asciz	InnerClasses;
Asciz	scala/Predef$$less$colon$less;
class	scala/Predef$$less$colon$less
Asciz	scala/Predef;
class	scala/Predef
Asciz	$less$colon$less;
Asciz	scala/collection/TraversableLike$WithFilter;
class	scala/collection/TraversableLike$WithFilter
Asciz	scala/collection/TraversableLike;
class	scala/collection/TraversableLike
Asciz	WithFilter;
Asciz	scala/collection/immutable/Nil;
class	scala/collection/immutable/Nil
Asciz	java/lang/Object;
class	java/lang/Object

{
public static final java.lang.Object productElement(int);
  Signature: (I)Ljava/lang/Object;
  Code:
   Stack=2, Locals=1, Args_size=1
	getstatic	Field scala/collection/immutable/Nil$.MODULE$:Lscala/collection/immutable/Nil$;
	iload_0
	invokevirtual	Method scala/collection/immutable/Nil$.productElement:(I)Ljava/lang/Object;
	areturn
  Labels:

public static final int productArity();
  Signature: ()I
  Code:
   Stack=1, Locals=0, Args_size=0
	getstatic	Field scala/collection/immutable/Nil$.MODULE$:Lscala/collection/immutable/Nil$;
	invokevirtual	Method scala/collection/immutable/Nil$.productArity:()I
	ireturn
  Labels:

public static final java.lang.String productPrefix();
  Signature: ()Ljava/lang/String;
  Code:
   Stack=1, Locals=0, Args_size=0
	getstatic	Field scala/collection/immutable/Nil$.MODULE$:Lscala/collection/immutable/Nil$;
	invokevirtual	Method scala/collection/immutable/Nil$.productPrefix:()Ljava/lang/String;
	areturn
  Labels:

public static final scala.collection.immutable.List tail();
  Signature: ()Lscala/collection/immutable/List;
  Code:
   Stack=1, Locals=0, Args_size=0
	getstatic	Field scala/collection/immutable/Nil$.MODULE$:Lscala/collection/immutable/Nil$;
	invokevirtual	Method scala/collection/immutable/Nil$.tail:()Lscala/collection/immutable/List;
	areturn
  Labels:
  Signature: length = 0x2
   00 1A 

public static final scala.runtime.Nothing$ head();
  Signature: ()Lscala/runtime/Nothing$;
  Code:
   Stack=1, Locals=0, Args_size=0
	getstatic	Field scala/collection/immutable/Nil$.MODULE$:Lscala/collection/immutable/Nil$;
	invokevirtual	Method scala/collection/immutable/Nil$.head:()Lscala/runtime/Nothing$;
	areturn
  Labels:

public static final boolean isEmpty();
  Signature: ()Z
  Code:
   Stack=1, Locals=0, Args_size=0
	getstatic	Field scala/collection/immutable/Nil$.MODULE$:Lscala/collection/immutable/Nil$;
	invokevirtual	Method scala/collection/immutable/Nil$.isEmpty:()Z
	ireturn
  Labels:

public static final scala.collection.mutable.StringBuilder addString(scala.collection.mutable.StringBuilder);
  Signature: (Lscala/collection/mutable/StringBuilder;)Lscala/collection/mutable/StringBuilder;
  Code:
   Stack=2, Locals=1, Args_size=1
	getstatic	Field scala/collection/immutable/Nil$.MODULE$:Lscala/collection/immutable/Nil$;
	aload_0
	invokevirtual	Method scala/collection/immutable/Nil$.addString:(Lscala/collection/mutable/StringBuilder;)Lscala/collection/mutable/StringBuilder;
	areturn
  Labels:

public static final scala.collection.mutable.StringBuilder addString(scala.collection.mutable.StringBuilder, java.lang.String);
  Signature: (Lscala/collection/mutable/StringBuilder;Ljava/lang/String;)Lscala/collection/mutable/StringBuilder;
  Code:
   Stack=3, Locals=2, Args_size=2
	getstatic	Field scala/collection/immutable/Nil$.MODULE$:Lscala/collection/immutable/Nil$;
	aload_0
	aload_1
	invokevirtual	Method scala/collection/immutable/Nil$.addString:(Lscala/collection/mutable/StringBuilder;Ljava/lang/String;)Lscala/collection/mutable/StringBuilder;
	areturn
  Labels:

public static final scala.collection.mutable.StringBuilder addString(scala.collection.mutable.StringBuilder, java.lang.String, java.lang.String, java.lang.String);
  Signature: (Lscala/collection/mutable/StringBuilder;Ljava/lang/String;Ljava/lang/String;Ljava/lang/String;)Lscala/collection/mutable/StringBuilder;
  Code:
   Stack=5, Locals=4, Args_size=4
	getstatic	Field scala/collection/immutable/Nil$.MODULE$:Lscala/collection/immutable/Nil$;
	aload_0
	aload_1
	aload_2
	aload_3
	invokevirtual	Method scala/collection/immutable/Nil$.addString:(Lscala/collection/mutable/StringBuilder;Ljava/lang/String;Ljava/lang/String;Ljava/lang/String;)Lscala/collection/mutable/StringBuilder;
	areturn
  Labels:

public static final java.lang.String mkString();
  Signature: ()Ljava/lang/String;
  Code:
   Stack=1, Locals=0, Args_size=0
	getstatic	Field scala/collection/immutable/Nil$.MODULE$:Lscala/collection/immutable/Nil$;
	invokevirtual	Method scala/collection/immutable/Nil$.mkString:()Ljava/lang/String;
	areturn
  Labels:

public static final java.lang.String mkString(java.lang.String);
  Signature: (Ljava/lang/String;)Ljava/lang/String;
  Code:
   Stack=2, Locals=1, Args_size=1
	getstatic	Field scala/collection/immutable/Nil$.MODULE$:Lscala/collection/immutable/Nil$;
	aload_0
	invokevirtual	Method scala/collection/immutable/Nil$.mkString:(Ljava/lang/String;)Ljava/lang/String;
	areturn
  Labels:

public static final java.lang.String mkString(java.lang.String, java.lang.String, java.lang.String);
  Signature: (Ljava/lang/String;Ljava/lang/String;Ljava/lang/String;)Ljava/lang/String;
  Code:
   Stack=4, Locals=3, Args_size=3
	getstatic	Field scala/collection/immutable/Nil$.MODULE$:Lscala/collection/immutable/Nil$;
	aload_0
	aload_1
	aload_2
	invokevirtual	Method scala/collection/immutable/Nil$.mkString:(Ljava/lang/String;Ljava/lang/String;Ljava/lang/String;)Ljava/lang/String;
	areturn
  Labels:

public static final scala.collection.immutable.Map toMap(scala.Predef$$less$colon$less);
  Signature: (Lscala/Predef$$less$colon$less;)Lscala/collection/immutable/Map;
  Code:
   Stack=2, Locals=1, Args_size=1
	getstatic	Field scala/collection/immutable/Nil$.MODULE$:Lscala/collection/immutable/Nil$;
	aload_0
	invokevirtual	Method scala/collection/immutable/Nil$.toMap:(Lscala/Predef$$less$colon$less;)Lscala/collection/immutable/Map;
	areturn
  Labels:

public static final scala.collection.immutable.Set toSet();
  Signature: ()Lscala/collection/immutable/Set;
  Code:
   Stack=1, Locals=0, Args_size=0
	getstatic	Field scala/collection/immutable/Nil$.MODULE$:Lscala/collection/immutable/Nil$;
	invokevirtual	Method scala/collection/immutable/Nil$.toSet:()Lscala/collection/immutable/Set;
	areturn
  Labels:

public static final scala.collection.mutable.IndexedSeq toIndexedSeq();
  Signature: ()Lscala/collection/mutable/IndexedSeq;
  Code:
   Stack=1, Locals=0, Args_size=0
	getstatic	Field scala/collection/immutable/Nil$.MODULE$:Lscala/collection/immutable/Nil$;
	invokevirtual	Method scala/collection/immutable/Nil$.toIndexedSeq:()Lscala/collection/mutable/IndexedSeq;
	areturn
  Labels:

public static final java.lang.Object toArray(scala.reflect.ClassManifest);
  Signature: (Lscala/reflect/ClassManifest;)Ljava/lang/Object;
  Code:
   Stack=2, Locals=1, Args_size=1
	getstatic	Field scala/collection/immutable/Nil$.MODULE$:Lscala/collection/immutable/Nil$;
	aload_0
	invokevirtual	Method scala/collection/immutable/Nil$.toArray:(Lscala/reflect/ClassManifest;)Ljava/lang/Object;
	areturn
  Labels:

public static final void copyToArray(java.lang.Object);
  Signature: (Ljava/lang/Object;)V
  Code:
   Stack=2, Locals=1, Args_size=1
	getstatic	Field scala/collection/immutable/Nil$.MODULE$:Lscala/collection/immutable/Nil$;
	aload_0
	invokevirtual	Method scala/collection/immutable/Nil$.copyToArray:(Ljava/lang/Object;)V
	return
  Labels:

public static final void copyToArray(java.lang.Object, int);
  Signature: (Ljava/lang/Object;I)V
  Code:
   Stack=3, Locals=2, Args_size=2
	getstatic	Field scala/collection/immutable/Nil$.MODULE$:Lscala/collection/immutable/Nil$;
	aload_0
	iload_1
	invokevirtual	Method scala/collection/immutable/Nil$.copyToArray:(Ljava/lang/Object;I)V
	return
  Labels:

public static final void copyToBuffer(scala.collection.mutable.Buffer);
  Signature: (Lscala/collection/mutable/Buffer;)V
  Code:
   Stack=2, Locals=1, Args_size=1
	getstatic	Field scala/collection/immutable/Nil$.MODULE$:Lscala/collection/immutable/Nil$;
	aload_0
	invokevirtual	Method scala/collection/immutable/Nil$.copyToBuffer:(Lscala/collection/mutable/Buffer;)V
	return
  Labels:

public static final java.lang.Object max(scala.math.Ordering);
  Signature: (Lscala/math/Ordering;)Ljava/lang/Object;
  Code:
   Stack=2, Locals=1, Args_size=1
	getstatic	Field scala/collection/immutable/Nil$.MODULE$:Lscala/collection/immutable/Nil$;
	aload_0
	invokevirtual	Method scala/collection/immutable/Nil$.max:(Lscala/math/Ordering;)Ljava/lang/Object;
	areturn
  Labels:

public static final java.lang.Object min(scala.math.Ordering);
  Signature: (Lscala/math/Ordering;)Ljava/lang/Object;
  Code:
   Stack=2, Locals=1, Args_size=1
	getstatic	Field scala/collection/immutable/Nil$.MODULE$:Lscala/collection/immutable/Nil$;
	aload_0
	invokevirtual	Method scala/collection/immutable/Nil$.min:(Lscala/math/Ordering;)Ljava/lang/Object;
	areturn
  Labels:

public static final java.lang.Object product(scala.math.Numeric);
  Signature: (Lscala/math/Numeric;)Ljava/lang/Object;
  Code:
   Stack=2, Locals=1, Args_size=1
	getstatic	Field scala/collection/immutable/Nil$.MODULE$:Lscala/collection/immutable/Nil$;
	aload_0
	invokevirtual	Method scala/collection/immutable/Nil$.product:(Lscala/math/Numeric;)Ljava/lang/Object;
	areturn
  Labels:

public static final java.lang.Object sum(scala.math.Numeric);
  Signature: (Lscala/math/Numeric;)Ljava/lang/Object;
  Code:
   Stack=2, Locals=1, Args_size=1
	getstatic	Field scala/collection/immutable/Nil$.MODULE$:Lscala/collection/immutable/Nil$;
	aload_0
	invokevirtual	Method scala/collection/immutable/Nil$.sum:(Lscala/math/Numeric;)Ljava/lang/Object;
	areturn
  Labels:

public static final scala.Option reduceRightOption(scala.Function2);
  Signature: (Lscala/Function2;)Lscala/Option;
  Code:
   Stack=2, Locals=1, Args_size=1
	getstatic	Field scala/collection/immutable/Nil$.MODULE$:Lscala/collection/immutable/Nil$;
	aload_0
	invokevirtual	Method scala/collection/immutable/Nil$.reduceRightOption:(Lscala/Function2;)Lscala/Option;
	areturn
  Labels:

public static final scala.Option reduceLeftOption(scala.Function2);
  Signature: (Lscala/Function2;)Lscala/Option;
  Code:
   Stack=2, Locals=1, Args_size=1
	getstatic	Field scala/collection/immutable/Nil$.MODULE$:Lscala/collection/immutable/Nil$;
	aload_0
	invokevirtual	Method scala/collection/immutable/Nil$.reduceLeftOption:(Lscala/Function2;)Lscala/Option;
	areturn
  Labels:

public static final java.lang.Object $colon$bslash(java.lang.Object, scala.Function2);
  Signature: (Ljava/lang/Object;Lscala/Function2;)Ljava/lang/Object;
  Code:
   Stack=3, Locals=2, Args_size=2
	getstatic	Field scala/collection/immutable/Nil$.MODULE$:Lscala/collection/immutable/Nil$;
	aload_0
	aload_1
	invokevirtual	Method scala/collection/immutable/Nil$.$colon$bslash:(Ljava/lang/Object;Lscala/Function2;)Ljava/lang/Object;
	areturn
  Labels:

public static final java.lang.Object $div$colon(java.lang.Object, scala.Function2);
  Signature: (Ljava/lang/Object;Lscala/Function2;)Ljava/lang/Object;
  Code:
   Stack=3, Locals=2, Args_size=2
	getstatic	Field scala/collection/immutable/Nil$.MODULE$:Lscala/collection/immutable/Nil$;
	aload_0
	aload_1
	invokevirtual	Method scala/collection/immutable/Nil$.$div$colon:(Ljava/lang/Object;Lscala/Function2;)Ljava/lang/Object;
	areturn
  Labels:

public static final boolean nonEmpty();
  Signature: ()Z
  Code:
   Stack=1, Locals=0, Args_size=0
	getstatic	Field scala/collection/immutable/Nil$.MODULE$:Lscala/collection/immutable/Nil$;
	invokevirtual	Method scala/collection/immutable/Nil$.nonEmpty:()Z
	ireturn
  Labels:

public static final scala.collection.TraversableLike$WithFilter withFilter(scala.Function1);
  Signature: (Lscala/Function1;)Lscala/collection/TraversableLike$WithFilter;
  Code:
   Stack=2, Locals=1, Args_size=1
	getstatic	Field scala/collection/immutable/Nil$.MODULE$:Lscala/collection/immutable/Nil$;
	aload_0
	invokevirtual	Method scala/collection/immutable/Nil$.withFilter:(Lscala/Function1;)Lscala/collection/TraversableLike$WithFilter;
	areturn
  Labels:
  Signature: length = 0x2
   00 72 

public static final scala.collection.Iterator toIterator();
  Signature: ()Lscala/collection/Iterator;
  Code:
   Stack=1, Locals=0, Args_size=0
	getstatic	Field scala/collection/immutable/Nil$.MODULE$:Lscala/collection/immutable/Nil$;
	invokevirtual	Method scala/collection/immutable/Nil$.toIterator:()Lscala/collection/Iterator;
	areturn
  Labels:

public static final scala.collection.Traversable toTraversable();
  Signature: ()Lscala/collection/Traversable;
  Code:
   Stack=1, Locals=0, Args_size=0
	getstatic	Field scala/collection/immutable/Nil$.MODULE$:Lscala/collection/immutable/Nil$;
	invokevirtual	Method scala/collection/immutable/Nil$.toTraversable:()Lscala/collection/Traversable;
	areturn
  Labels:

public static final java.lang.Object init();
  Signature: ()Ljava/lang/Object;
  Code:
   Stack=1, Locals=0, Args_size=0
	getstatic	Field scala/collection/immutable/Nil$.MODULE$:Lscala/collection/immutable/Nil$;
	invokevirtual	Method scala/collection/immutable/Nil$.init:()Ljava/lang/Object;
	areturn
  Labels:

public static final scala.Option lastOption();
  Signature: ()Lscala/Option;
  Code:
   Stack=1, Locals=0, Args_size=0
	getstatic	Field scala/collection/immutable/Nil$.MODULE$:Lscala/collection/immutable/Nil$;
	invokevirtual	Method scala/collection/immutable/Nil$.lastOption:()Lscala/Option;
	areturn
  Labels:

public static final java.lang.Object tail();
  Signature: ()Ljava/lang/Object;
  Code:
   Stack=1, Locals=0, Args_size=0
	getstatic	Field scala/collection/immutable/Nil$.MODULE$:Lscala/collection/immutable/Nil$;
	invokevirtual	Method scala/collection/immutable/Nil$.tail:()Ljava/lang/Object;
	areturn
  Labels:

public static final scala.Option headOption();
  Signature: ()Lscala/Option;
  Code:
   Stack=1, Locals=0, Args_size=0
	getstatic	Field scala/collection/immutable/Nil$.MODULE$:Lscala/collection/immutable/Nil$;
	invokevirtual	Method scala/collection/immutable/Nil$.headOption:()Lscala/Option;
	areturn
  Labels:

public static final java.lang.Object scanRight(java.lang.Object, scala.Function2, scala.collection.generic.CanBuildFrom);
  Signature: (Ljava/lang/Object;Lscala/Function2;Lscala/collection/generic/CanBuildFrom;)Ljava/lang/Object;
  Code:
   Stack=4, Locals=3, Args_size=3
	getstatic	Field scala/collection/immutable/Nil$.MODULE$:Lscala/collection/immutable/Nil$;
	aload_0
	aload_1
	aload_2
	invokevirtual	Method scala/collection/immutable/Nil$.scanRight:(Ljava/lang/Object;Lscala/Function2;Lscala/collection/generic/CanBuildFrom;)Ljava/lang/Object;
	areturn
  Labels:

public static final java.lang.Object scanLeft(java.lang.Object, scala.Function2, scala.collection.generic.CanBuildFrom);
  Signature: (Ljava/lang/Object;Lscala/Function2;Lscala/collection/generic/CanBuildFrom;)Ljava/lang/Object;
  Code:
   Stack=4, Locals=3, Args_size=3
	getstatic	Field scala/collection/immutable/Nil$.MODULE$:Lscala/collection/immutable/Nil$;
	aload_0
	aload_1
	aload_2
	invokevirtual	Method scala/collection/immutable/Nil$.scanLeft:(Ljava/lang/Object;Lscala/Function2;Lscala/collection/generic/CanBuildFrom;)Ljava/lang/Object;
	areturn
  Labels:

public static final scala.collection.Map groupBy(scala.Function1);
  Signature: (Lscala/Function1;)Lscala/collection/Map;
  Code:
   Stack=2, Locals=1, Args_size=1
	getstatic	Field scala/collection/immutable/Nil$.MODULE$:Lscala/collection/immutable/Nil$;
	aload_0
	invokevirtual	Method scala/collection/immutable/Nil$.groupBy:(Lscala/Function1;)Lscala/collection/Map;
	areturn
  Labels:

public static final scala.Tuple2 partition(scala.Function1);
  Signature: (Lscala/Function1;)Lscala/Tuple2;
  Code:
   Stack=2, Locals=1, Args_size=1
	getstatic	Field scala/collection/immutable/Nil$.MODULE$:Lscala/collection/immutable/Nil$;
	aload_0
	invokevirtual	Method scala/collection/immutable/Nil$.partition:(Lscala/Function1;)Lscala/Tuple2;
	areturn
  Labels:

public static final java.lang.Object collect(scala.PartialFunction, scala.collection.generic.CanBuildFrom);
  Signature: (Lscala/PartialFunction;Lscala/collection/generic/CanBuildFrom;)Ljava/lang/Object;
  Code:
   Stack=3, Locals=2, Args_size=2
	getstatic	Field scala/collection/immutable/Nil$.MODULE$:Lscala/collection/immutable/Nil$;
	aload_0
	aload_1
	invokevirtual	Method scala/collection/immutable/Nil$.collect:(Lscala/PartialFunction;Lscala/collection/generic/CanBuildFrom;)Ljava/lang/Object;
	areturn
  Labels:

public static final java.lang.Object filterNot(scala.Function1);
  Signature: (Lscala/Function1;)Ljava/lang/Object;
  Code:
   Stack=2, Locals=1, Args_size=1
	getstatic	Field scala/collection/immutable/Nil$.MODULE$:Lscala/collection/immutable/Nil$;
	aload_0
	invokevirtual	Method scala/collection/immutable/Nil$.filterNot:(Lscala/Function1;)Ljava/lang/Object;
	areturn
  Labels:

public static final java.lang.Object filter(scala.Function1);
  Signature: (Lscala/Function1;)Ljava/lang/Object;
  Code:
   Stack=2, Locals=1, Args_size=1
	getstatic	Field scala/collection/immutable/Nil$.MODULE$:Lscala/collection/immutable/Nil$;
	aload_0
	invokevirtual	Method scala/collection/immutable/Nil$.filter:(Lscala/Function1;)Ljava/lang/Object;
	areturn
  Labels:

public static final java.lang.Object flatMap(scala.Function1, scala.collection.generic.CanBuildFrom);
  Signature: (Lscala/Function1;Lscala/collection/generic/CanBuildFrom;)Ljava/lang/Object;
  Code:
   Stack=3, Locals=2, Args_size=2
	getstatic	Field scala/collection/immutable/Nil$.MODULE$:Lscala/collection/immutable/Nil$;
	aload_0
	aload_1
	invokevirtual	Method scala/collection/immutable/Nil$.flatMap:(Lscala/Function1;Lscala/collection/generic/CanBuildFrom;)Ljava/lang/Object;
	areturn
  Labels:

public static final java.lang.Object map(scala.Function1, scala.collection.generic.CanBuildFrom);
  Signature: (Lscala/Function1;Lscala/collection/generic/CanBuildFrom;)Ljava/lang/Object;
  Code:
   Stack=3, Locals=2, Args_size=2
	getstatic	Field scala/collection/immutable/Nil$.MODULE$:Lscala/collection/immutable/Nil$;
	aload_0
	aload_1
	invokevirtual	Method scala/collection/immutable/Nil$.map:(Lscala/Function1;Lscala/collection/generic/CanBuildFrom;)Ljava/lang/Object;
	areturn
  Labels:

public static final boolean hasDefiniteSize();
  Signature: ()Z
  Code:
   Stack=1, Locals=0, Args_size=0
	getstatic	Field scala/collection/immutable/Nil$.MODULE$:Lscala/collection/immutable/Nil$;
	invokevirtual	Method scala/collection/immutable/Nil$.hasDefiniteSize:()Z
	ireturn
  Labels:

public static final boolean isTraversableAgain();
  Signature: ()Z
  Code:
   Stack=1, Locals=0, Args_size=0
	getstatic	Field scala/collection/immutable/Nil$.MODULE$:Lscala/collection/immutable/Nil$;
	invokevirtual	Method scala/collection/immutable/Nil$.isTraversableAgain:()Z
	ireturn
  Labels:

public static final java.lang.Object repr();
  Signature: ()Ljava/lang/Object;
  Code:
   Stack=1, Locals=0, Args_size=0
	getstatic	Field scala/collection/immutable/Nil$.MODULE$:Lscala/collection/immutable/Nil$;
	invokevirtual	Method scala/collection/immutable/Nil$.repr:()Ljava/lang/Object;
	areturn
  Labels:

public static final scala.collection.Traversable transpose(scala.Function1);
  Signature: (Lscala/Function1;)Lscala/collection/Traversable;
  Code:
   Stack=2, Locals=1, Args_size=1
	getstatic	Field scala/collection/immutable/Nil$.MODULE$:Lscala/collection/immutable/Nil$;
	aload_0
	invokevirtual	Method scala/collection/immutable/Nil$.transpose:(Lscala/Function1;)Lscala/collection/Traversable;
	areturn
  Labels:

public static final scala.collection.Traversable flatten(scala.Function1);
  Signature: (Lscala/Function1;)Lscala/collection/Traversable;
  Code:
   Stack=2, Locals=1, Args_size=1
	getstatic	Field scala/collection/immutable/Nil$.MODULE$:Lscala/collection/immutable/Nil$;
	aload_0
	invokevirtual	Method scala/collection/immutable/Nil$.flatten:(Lscala/Function1;)Lscala/collection/Traversable;
	areturn
  Labels:

public static final scala.Tuple2 unzip(scala.Function1);
  Signature: (Lscala/Function1;)Lscala/Tuple2;
  Code:
   Stack=2, Locals=1, Args_size=1
	getstatic	Field scala/collection/immutable/Nil$.MODULE$:Lscala/collection/immutable/Nil$;
	aload_0
	invokevirtual	Method scala/collection/immutable/Nil$.unzip:(Lscala/Function1;)Lscala/Tuple2;
	areturn
  Labels:

public static final scala.collection.mutable.Builder genericBuilder();
  Signature: ()Lscala/collection/mutable/Builder;
  Code:
   Stack=1, Locals=0, Args_size=0
	getstatic	Field scala/collection/immutable/Nil$.MODULE$:Lscala/collection/immutable/Nil$;
	invokevirtual	Method scala/collection/immutable/Nil$.genericBuilder:()Lscala/collection/mutable/Builder;
	areturn
  Labels:

public static final scala.Option firstOption();
  Signature: ()Lscala/Option;
  Code:
   Stack=1, Locals=0, Args_size=0
	getstatic	Field scala/collection/immutable/Nil$.MODULE$:Lscala/collection/immutable/Nil$;
	invokevirtual	Method scala/collection/immutable/Nil$.firstOption:()Lscala/Option;
	areturn
  Labels:
  Deprecated: true

public static final java.lang.Object first();
  Signature: ()Ljava/lang/Object;
  Code:
   Stack=1, Locals=0, Args_size=0
	getstatic	Field scala/collection/immutable/Nil$.MODULE$:Lscala/collection/immutable/Nil$;
	invokevirtual	Method scala/collection/immutable/Nil$.first:()Ljava/lang/Object;
	areturn
  Labels:
  Deprecated: true

public static final scala.collection.Iterator elements();
  Signature: ()Lscala/collection/Iterator;
  Code:
   Stack=1, Locals=0, Args_size=0
	getstatic	Field scala/collection/immutable/Nil$.MODULE$:Lscala/collection/immutable/Nil$;
	invokevirtual	Method scala/collection/immutable/Nil$.elements:()Lscala/collection/Iterator;
	areturn
  Labels:
  Deprecated: true

public static final boolean canEqual(java.lang.Object);
  Signature: (Ljava/lang/Object;)Z
  Code:
   Stack=2, Locals=1, Args_size=1
	getstatic	Field scala/collection/immutable/Nil$.MODULE$:Lscala/collection/immutable/Nil$;
	aload_0
	invokevirtual	Method scala/collection/immutable/Nil$.canEqual:(Ljava/lang/Object;)Z
	ireturn
  Labels:

public static final java.lang.Object zipWithIndex(scala.collection.generic.CanBuildFrom);
  Signature: (Lscala/collection/generic/CanBuildFrom;)Ljava/lang/Object;
  Code:
   Stack=2, Locals=1, Args_size=1
	getstatic	Field scala/collection/immutable/Nil$.MODULE$:Lscala/collection/immutable/Nil$;
	aload_0
	invokevirtual	Method scala/collection/immutable/Nil$.zipWithIndex:(Lscala/collection/generic/CanBuildFrom;)Ljava/lang/Object;
	areturn
  Labels:

public static final java.lang.Object zipAll(scala.collection.Iterable, java.lang.Object, java.lang.Object, scala.collection.generic.CanBuildFrom);
  Signature: (Lscala/collection/Iterable;Ljava/lang/Object;Ljava/lang/Object;Lscala/collection/generic/CanBuildFrom;)Ljava/lang/Object;
  Code:
   Stack=5, Locals=4, Args_size=4
	getstatic	Field scala/collection/immutable/Nil$.MODULE$:Lscala/collection/immutable/Nil$;
	aload_0
	aload_1
	aload_2
	aload_3
	invokevirtual	Method scala/collection/immutable/Nil$.zipAll:(Lscala/collection/Iterable;Ljava/lang/Object;Ljava/lang/Object;Lscala/collection/generic/CanBuildFrom;)Ljava/lang/Object;
	areturn
  Labels:

public static final java.lang.Object zip(scala.collection.Iterable, scala.collection.generic.CanBuildFrom);
  Signature: (Lscala/collection/Iterable;Lscala/collection/generic/CanBuildFrom;)Ljava/lang/Object;
  Code:
   Stack=3, Locals=2, Args_size=2
	getstatic	Field scala/collection/immutable/Nil$.MODULE$:Lscala/collection/immutable/Nil$;
	aload_0
	aload_1
	invokevirtual	Method scala/collection/immutable/Nil$.zip:(Lscala/collection/Iterable;Lscala/collection/generic/CanBuildFrom;)Ljava/lang/Object;
	areturn
  Labels:

public static final void copyToArray(java.lang.Object, int, int);
  Signature: (Ljava/lang/Object;II)V
  Code:
   Stack=4, Locals=3, Args_size=3
	getstatic	Field scala/collection/immutable/Nil$.MODULE$:Lscala/collection/immutable/Nil$;
	aload_0
	iload_1
	iload_2
	invokevirtual	Method scala/collection/immutable/Nil$.copyToArray:(Ljava/lang/Object;II)V
	return
  Labels:

public static final scala.collection.Iterator sliding(int, int);
  Signature: (II)Lscala/collection/Iterator;
  Code:
   Stack=3, Locals=2, Args_size=2
	getstatic	Field scala/collection/immutable/Nil$.MODULE$:Lscala/collection/immutable/Nil$;
	iload_0
	iload_1
	invokevirtual	Method scala/collection/immutable/Nil$.sliding:(II)Lscala/collection/Iterator;
	areturn
  Labels:

public static final scala.collection.Iterator sliding(int);
  Signature: (I)Lscala/collection/Iterator;
  Code:
   Stack=2, Locals=1, Args_size=1
	getstatic	Field scala/collection/immutable/Nil$.MODULE$:Lscala/collection/immutable/Nil$;
	iload_0
	invokevirtual	Method scala/collection/immutable/Nil$.sliding:(I)Lscala/collection/Iterator;
	areturn
  Labels:

public static final scala.collection.Iterator grouped(int);
  Signature: (I)Lscala/collection/Iterator;
  Code:
   Stack=2, Locals=1, Args_size=1
	getstatic	Field scala/collection/immutable/Nil$.MODULE$:Lscala/collection/immutable/Nil$;
	iload_0
	invokevirtual	Method scala/collection/immutable/Nil$.grouped:(I)Lscala/collection/Iterator;
	areturn
  Labels:

public static final scala.collection.Iterable toIterable();
  Signature: ()Lscala/collection/Iterable;
  Code:
   Stack=1, Locals=0, Args_size=0
	getstatic	Field scala/collection/immutable/Nil$.MODULE$:Lscala/collection/immutable/Nil$;
	invokevirtual	Method scala/collection/immutable/Nil$.toIterable:()Lscala/collection/Iterable;
	areturn
  Labels:

public static final scala.Function1 compose(scala.Function1);
  Signature: (Lscala/Function1;)Lscala/Function1;
  Code:
   Stack=2, Locals=1, Args_size=1
	getstatic	Field scala/collection/immutable/Nil$.MODULE$:Lscala/collection/immutable/Nil$;
	aload_0
	invokevirtual	Method scala/collection/immutable/Nil$.compose:(Lscala/Function1;)Lscala/Function1;
	areturn
  Labels:

public static final scala.Function1 lift();
  Signature: ()Lscala/Function1;
  Code:
   Stack=1, Locals=0, Args_size=0
	getstatic	Field scala/collection/immutable/Nil$.MODULE$:Lscala/collection/immutable/Nil$;
	invokevirtual	Method scala/collection/immutable/Nil$.lift:()Lscala/Function1;
	areturn
  Labels:

public static final scala.PartialFunction andThen(scala.Function1);
  Signature: (Lscala/Function1;)Lscala/PartialFunction;
  Code:
   Stack=2, Locals=1, Args_size=1
	getstatic	Field scala/collection/immutable/Nil$.MODULE$:Lscala/collection/immutable/Nil$;
	aload_0
	invokevirtual	Method scala/collection/immutable/Nil$.andThen:(Lscala/Function1;)Lscala/PartialFunction;
	areturn
  Labels:

public static final scala.PartialFunction orElse(scala.PartialFunction);
  Signature: (Lscala/PartialFunction;)Lscala/PartialFunction;
  Code:
   Stack=2, Locals=1, Args_size=1
	getstatic	Field scala/collection/immutable/Nil$.MODULE$:Lscala/collection/immutable/Nil$;
	aload_0
	invokevirtual	Method scala/collection/immutable/Nil$.orElse:(Lscala/PartialFunction;)Lscala/PartialFunction;
	areturn
  Labels:

public static final scala.collection.SeqView projection();
  Signature: ()Lscala/collection/SeqView;
  Code:
   Stack=1, Locals=0, Args_size=0
	getstatic	Field scala/collection/immutable/Nil$.MODULE$:Lscala/collection/immutable/Nil$;
	invokevirtual	Method scala/collection/immutable/Nil$.projection:()Lscala/collection/SeqView;
	areturn
  Labels:
  Deprecated: true

public static final boolean equalsWith(scala.collection.Seq, scala.Function2);
  Signature: (Lscala/collection/Seq;Lscala/Function2;)Z
  Code:
   Stack=3, Locals=2, Args_size=2
	getstatic	Field scala/collection/immutable/Nil$.MODULE$:Lscala/collection/immutable/Nil$;
	aload_0
	aload_1
	invokevirtual	Method scala/collection/immutable/Nil$.equalsWith:(Lscala/collection/Seq;Lscala/Function2;)Z
	ireturn
  Labels:
  Deprecated: true

public static final int findLastIndexOf(scala.Function1);
  Signature: (Lscala/Function1;)I
  Code:
   Stack=2, Locals=1, Args_size=1
	getstatic	Field scala/collection/immutable/Nil$.MODULE$:Lscala/collection/immutable/Nil$;
	aload_0
	invokevirtual	Method scala/collection/immutable/Nil$.findLastIndexOf:(Lscala/Function1;)I
	ireturn
  Labels:
  Deprecated: true

public static final scala.collection.SeqView view(int, int);
  Signature: (II)Lscala/collection/SeqView;
  Code:
   Stack=3, Locals=2, Args_size=2
	getstatic	Field scala/collection/immutable/Nil$.MODULE$:Lscala/collection/immutable/Nil$;
	iload_0
	iload_1
	invokevirtual	Method scala/collection/immutable/Nil$.view:(II)Lscala/collection/SeqView;
	areturn
  Labels:

public static final scala.collection.SeqView view();
  Signature: ()Lscala/collection/SeqView;
  Code:
   Stack=1, Locals=0, Args_size=0
	getstatic	Field scala/collection/immutable/Nil$.MODULE$:Lscala/collection/immutable/Nil$;
	invokevirtual	Method scala/collection/immutable/Nil$.view:()Lscala/collection/SeqView;
	areturn
  Labels:

public static final scala.collection.immutable.Range indices();
  Signature: ()Lscala/collection/immutable/Range;
  Code:
   Stack=1, Locals=0, Args_size=0
	getstatic	Field scala/collection/immutable/Nil$.MODULE$:Lscala/collection/immutable/Nil$;
	invokevirtual	Method scala/collection/immutable/Nil$.indices:()Lscala/collection/immutable/Range;
	areturn
  Labels:

public static final scala.collection.Seq toSeq();
  Signature: ()Lscala/collection/Seq;
  Code:
   Stack=1, Locals=0, Args_size=0
	getstatic	Field scala/collection/immutable/Nil$.MODULE$:Lscala/collection/immutable/Nil$;
	invokevirtual	Method scala/collection/immutable/Nil$.toSeq:()Lscala/collection/Seq;
	areturn
  Labels:

public static final java.lang.Object sorted(scala.math.Ordering);
  Signature: (Lscala/math/Ordering;)Ljava/lang/Object;
  Code:
   Stack=2, Locals=1, Args_size=1
	getstatic	Field scala/collection/immutable/Nil$.MODULE$:Lscala/collection/immutable/Nil$;
	aload_0
	invokevirtual	Method scala/collection/immutable/Nil$.sorted:(Lscala/math/Ordering;)Ljava/lang/Object;
	areturn
  Labels:

public static final java.lang.Object sortBy(scala.Function1, scala.math.Ordering);
  Signature: (Lscala/Function1;Lscala/math/Ordering;)Ljava/lang/Object;
  Code:
   Stack=3, Locals=2, Args_size=2
	getstatic	Field scala/collection/immutable/Nil$.MODULE$:Lscala/collection/immutable/Nil$;
	aload_0
	aload_1
	invokevirtual	Method scala/collection/immutable/Nil$.sortBy:(Lscala/Function1;Lscala/math/Ordering;)Ljava/lang/Object;
	areturn
  Labels:

public static final java.lang.Object sortWith(scala.Function2);
  Signature: (Lscala/Function2;)Ljava/lang/Object;
  Code:
   Stack=2, Locals=1, Args_size=1
	getstatic	Field scala/collection/immutable/Nil$.MODULE$:Lscala/collection/immutable/Nil$;
	aload_0
	invokevirtual	Method scala/collection/immutable/Nil$.sortWith:(Lscala/Function2;)Ljava/lang/Object;
	areturn
  Labels:

public static final boolean corresponds(scala.collection.Seq, scala.Function2);
  Signature: (Lscala/collection/Seq;Lscala/Function2;)Z
  Code:
   Stack=3, Locals=2, Args_size=2
	getstatic	Field scala/collection/immutable/Nil$.MODULE$:Lscala/collection/immutable/Nil$;
	aload_0
	aload_1
	invokevirtual	Method scala/collection/immutable/Nil$.corresponds:(Lscala/collection/Seq;Lscala/Function2;)Z
	ireturn
  Labels:

public static final java.lang.Object padTo(int, java.lang.Object, scala.collection.generic.CanBuildFrom);
  Signature: (ILjava/lang/Object;Lscala/collection/generic/CanBuildFrom;)Ljava/lang/Object;
  Code:
   Stack=4, Locals=3, Args_size=3
	getstatic	Field scala/collection/immutable/Nil$.MODULE$:Lscala/collection/immutable/Nil$;
	iload_0
	aload_1
	aload_2
	invokevirtual	Method scala/collection/immutable/Nil$.padTo:(ILjava/lang/Object;Lscala/collection/generic/CanBuildFrom;)Ljava/lang/Object;
	areturn
  Labels:

public static final java.lang.Object $colon$plus(java.lang.Object, scala.collection.generic.CanBuildFrom);
  Signature: (Ljava/lang/Object;Lscala/collection/generic/CanBuildFrom;)Ljava/lang/Object;
  Code:
   Stack=3, Locals=2, Args_size=2
	getstatic	Field scala/collection/immutable/Nil$.MODULE$:Lscala/collection/immutable/Nil$;
	aload_0
	aload_1
	invokevirtual	Method scala/collection/immutable/Nil$.$colon$plus:(Ljava/lang/Object;Lscala/collection/generic/CanBuildFrom;)Ljava/lang/Object;
	areturn
  Labels:

public static final java.lang.Object updated(int, java.lang.Object, scala.collection.generic.CanBuildFrom);
  Signature: (ILjava/lang/Object;Lscala/collection/generic/CanBuildFrom;)Ljava/lang/Object;
  Code:
   Stack=4, Locals=3, Args_size=3
	getstatic	Field scala/collection/immutable/Nil$.MODULE$:Lscala/collection/immutable/Nil$;
	iload_0
	aload_1
	aload_2
	invokevirtual	Method scala/collection/immutable/Nil$.updated:(ILjava/lang/Object;Lscala/collection/generic/CanBuildFrom;)Ljava/lang/Object;
	areturn
  Labels:

public static final java.lang.Object patch(int, scala.collection.Seq, int, scala.collection.generic.CanBuildFrom);
  Signature: (ILscala/collection/Seq;ILscala/collection/generic/CanBuildFrom;)Ljava/lang/Object;
  Code:
   Stack=5, Locals=4, Args_size=4
	getstatic	Field scala/collection/immutable/Nil$.MODULE$:Lscala/collection/immutable/Nil$;
	iload_0
	aload_1
	iload_2
	aload_3
	invokevirtual	Method scala/collection/immutable/Nil$.patch:(ILscala/collection/Seq;ILscala/collection/generic/CanBuildFrom;)Ljava/lang/Object;
	areturn
  Labels:

public static final java.lang.Object distinct();
  Signature: ()Ljava/lang/Object;
  Code:
   Stack=1, Locals=0, Args_size=0
	getstatic	Field scala/collection/immutable/Nil$.MODULE$:Lscala/collection/immutable/Nil$;
	invokevirtual	Method scala/collection/immutable/Nil$.distinct:()Ljava/lang/Object;
	areturn
  Labels:

public static final java.lang.Object intersect(scala.collection.Seq);
  Signature: (Lscala/collection/Seq;)Ljava/lang/Object;
  Code:
   Stack=2, Locals=1, Args_size=1
	getstatic	Field scala/collection/immutable/Nil$.MODULE$:Lscala/collection/immutable/Nil$;
	aload_0
	invokevirtual	Method scala/collection/immutable/Nil$.intersect:(Lscala/collection/Seq;)Ljava/lang/Object;
	areturn
  Labels:

public static final java.lang.Object diff(scala.collection.Seq);
  Signature: (Lscala/collection/Seq;)Ljava/lang/Object;
  Code:
   Stack=2, Locals=1, Args_size=1
	getstatic	Field scala/collection/immutable/Nil$.MODULE$:Lscala/collection/immutable/Nil$;
	aload_0
	invokevirtual	Method scala/collection/immutable/Nil$.diff:(Lscala/collection/Seq;)Ljava/lang/Object;
	areturn
  Labels:

public static final java.lang.Object union(scala.collection.Seq, scala.collection.generic.CanBuildFrom);
  Signature: (Lscala/collection/Seq;Lscala/collection/generic/CanBuildFrom;)Ljava/lang/Object;
  Code:
   Stack=3, Locals=2, Args_size=2
	getstatic	Field scala/collection/immutable/Nil$.MODULE$:Lscala/collection/immutable/Nil$;
	aload_0
	aload_1
	invokevirtual	Method scala/collection/immutable/Nil$.union:(Lscala/collection/Seq;Lscala/collection/generic/CanBuildFrom;)Ljava/lang/Object;
	areturn
  Labels:

public static final boolean contains(java.lang.Object);
  Signature: (Ljava/lang/Object;)Z
  Code:
   Stack=2, Locals=1, Args_size=1
	getstatic	Field scala/collection/immutable/Nil$.MODULE$:Lscala/collection/immutable/Nil$;
	aload_0
	invokevirtual	Method scala/collection/immutable/Nil$.contains:(Ljava/lang/Object;)Z
	ireturn
  Labels:

public static final boolean containsSlice(scala.collection.Seq);
  Signature: (Lscala/collection/Seq;)Z
  Code:
   Stack=2, Locals=1, Args_size=1
	getstatic	Field scala/collection/immutable/Nil$.MODULE$:Lscala/collection/immutable/Nil$;
	aload_0
	invokevirtual	Method scala/collection/immutable/Nil$.containsSlice:(Lscala/collection/Seq;)Z
	ireturn
  Labels:

public static final int lastIndexOfSlice(scala.collection.Seq, int);
  Signature: (Lscala/collection/Seq;I)I
  Code:
   Stack=3, Locals=2, Args_size=2
	getstatic	Field scala/collection/immutable/Nil$.MODULE$:Lscala/collection/immutable/Nil$;
	aload_0
	iload_1
	invokevirtual	Method scala/collection/immutable/Nil$.lastIndexOfSlice:(Lscala/collection/Seq;I)I
	ireturn
  Labels:

public static final int lastIndexOfSlice(scala.collection.Seq);
  Signature: (Lscala/collection/Seq;)I
  Code:
   Stack=2, Locals=1, Args_size=1
	getstatic	Field scala/collection/immutable/Nil$.MODULE$:Lscala/collection/immutable/Nil$;
	aload_0
	invokevirtual	Method scala/collection/immutable/Nil$.lastIndexOfSlice:(Lscala/collection/Seq;)I
	ireturn
  Labels:

public static final int indexOfSlice(scala.collection.Seq, int);
  Signature: (Lscala/collection/Seq;I)I
  Code:
   Stack=3, Locals=2, Args_size=2
	getstatic	Field scala/collection/immutable/Nil$.MODULE$:Lscala/collection/immutable/Nil$;
	aload_0
	iload_1
	invokevirtual	Method scala/collection/immutable/Nil$.indexOfSlice:(Lscala/collection/Seq;I)I
	ireturn
  Labels:

public static final int indexOfSlice(scala.collection.Seq);
  Signature: (Lscala/collection/Seq;)I
  Code:
   Stack=2, Locals=1, Args_size=1
	getstatic	Field scala/collection/immutable/Nil$.MODULE$:Lscala/collection/immutable/Nil$;
	aload_0
	invokevirtual	Method scala/collection/immutable/Nil$.indexOfSlice:(Lscala/collection/Seq;)I
	ireturn
  Labels:

public static final boolean endsWith(scala.collection.Seq);
  Signature: (Lscala/collection/Seq;)Z
  Code:
   Stack=2, Locals=1, Args_size=1
	getstatic	Field scala/collection/immutable/Nil$.MODULE$:Lscala/collection/immutable/Nil$;
	aload_0
	invokevirtual	Method scala/collection/immutable/Nil$.endsWith:(Lscala/collection/Seq;)Z
	ireturn
  Labels:

public static final boolean startsWith(scala.collection.Seq);
  Signature: (Lscala/collection/Seq;)Z
  Code:
   Stack=2, Locals=1, Args_size=1
	getstatic	Field scala/collection/immutable/Nil$.MODULE$:Lscala/collection/immutable/Nil$;
	aload_0
	invokevirtual	Method scala/collection/immutable/Nil$.startsWith:(Lscala/collection/Seq;)Z
	ireturn
  Labels:

public static final boolean startsWith(scala.collection.Seq, int);
  Signature: (Lscala/collection/Seq;I)Z
  Code:
   Stack=3, Locals=2, Args_size=2
	getstatic	Field scala/collection/immutable/Nil$.MODULE$:Lscala/collection/immutable/Nil$;
	aload_0
	iload_1
	invokevirtual	Method scala/collection/immutable/Nil$.startsWith:(Lscala/collection/Seq;I)Z
	ireturn
  Labels:

public static final scala.collection.Iterator reversedElements();
  Signature: ()Lscala/collection/Iterator;
  Code:
   Stack=1, Locals=0, Args_size=0
	getstatic	Field scala/collection/immutable/Nil$.MODULE$:Lscala/collection/immutable/Nil$;
	invokevirtual	Method scala/collection/immutable/Nil$.reversedElements:()Lscala/collection/Iterator;
	areturn
  Labels:
  Deprecated: true

public static final scala.collection.Iterator reverseIterator();
  Signature: ()Lscala/collection/Iterator;
  Code:
   Stack=1, Locals=0, Args_size=0
	getstatic	Field scala/collection/immutable/Nil$.MODULE$:Lscala/collection/immutable/Nil$;
	invokevirtual	Method scala/collection/immutable/Nil$.reverseIterator:()Lscala/collection/Iterator;
	areturn
  Labels:

public static final java.lang.Object reverseMap(scala.Function1, scala.collection.generic.CanBuildFrom);
  Signature: (Lscala/Function1;Lscala/collection/generic/CanBuildFrom;)Ljava/lang/Object;
  Code:
   Stack=3, Locals=2, Args_size=2
	getstatic	Field scala/collection/immutable/Nil$.MODULE$:Lscala/collection/immutable/Nil$;
	aload_0
	aload_1
	invokevirtual	Method scala/collection/immutable/Nil$.reverseMap:(Lscala/Function1;Lscala/collection/generic/CanBuildFrom;)Ljava/lang/Object;
	areturn
  Labels:

public static final int lastIndexWhere(scala.Function1);
  Signature: (Lscala/Function1;)I
  Code:
   Stack=2, Locals=1, Args_size=1
	getstatic	Field scala/collection/immutable/Nil$.MODULE$:Lscala/collection/immutable/Nil$;
	aload_0
	invokevirtual	Method scala/collection/immutable/Nil$.lastIndexWhere:(Lscala/Function1;)I
	ireturn
  Labels:

public static final int lastIndexOf(java.lang.Object, int);
  Signature: (Ljava/lang/Object;I)I
  Code:
   Stack=3, Locals=2, Args_size=2
	getstatic	Field scala/collection/immutable/Nil$.MODULE$:Lscala/collection/immutable/Nil$;
	aload_0
	iload_1
	invokevirtual	Method scala/collection/immutable/Nil$.lastIndexOf:(Ljava/lang/Object;I)I
	ireturn
  Labels:

public static final int lastIndexOf(java.lang.Object);
  Signature: (Ljava/lang/Object;)I
  Code:
   Stack=2, Locals=1, Args_size=1
	getstatic	Field scala/collection/immutable/Nil$.MODULE$:Lscala/collection/immutable/Nil$;
	aload_0
	invokevirtual	Method scala/collection/immutable/Nil$.lastIndexOf:(Ljava/lang/Object;)I
	ireturn
  Labels:

public static final int indexOf(java.lang.Object, int);
  Signature: (Ljava/lang/Object;I)I
  Code:
   Stack=3, Locals=2, Args_size=2
	getstatic	Field scala/collection/immutable/Nil$.MODULE$:Lscala/collection/immutable/Nil$;
	aload_0
	iload_1
	invokevirtual	Method scala/collection/immutable/Nil$.indexOf:(Ljava/lang/Object;I)I
	ireturn
  Labels:

public static final int indexOf(java.lang.Object);
  Signature: (Ljava/lang/Object;)I
  Code:
   Stack=2, Locals=1, Args_size=1
	getstatic	Field scala/collection/immutable/Nil$.MODULE$:Lscala/collection/immutable/Nil$;
	aload_0
	invokevirtual	Method scala/collection/immutable/Nil$.indexOf:(Ljava/lang/Object;)I
	ireturn
  Labels:

public static final int findIndexOf(scala.Function1);
  Signature: (Lscala/Function1;)I
  Code:
   Stack=2, Locals=1, Args_size=1
	getstatic	Field scala/collection/immutable/Nil$.MODULE$:Lscala/collection/immutable/Nil$;
	aload_0
	invokevirtual	Method scala/collection/immutable/Nil$.findIndexOf:(Lscala/Function1;)I
	ireturn
  Labels:

public static final int indexWhere(scala.Function1);
  Signature: (Lscala/Function1;)I
  Code:
   Stack=2, Locals=1, Args_size=1
	getstatic	Field scala/collection/immutable/Nil$.MODULE$:Lscala/collection/immutable/Nil$;
	aload_0
	invokevirtual	Method scala/collection/immutable/Nil$.indexWhere:(Lscala/Function1;)I
	ireturn
  Labels:

public static final int prefixLength(scala.Function1);
  Signature: (Lscala/Function1;)I
  Code:
   Stack=2, Locals=1, Args_size=1
	getstatic	Field scala/collection/immutable/Nil$.MODULE$:Lscala/collection/immutable/Nil$;
	aload_0
	invokevirtual	Method scala/collection/immutable/Nil$.prefixLength:(Lscala/Function1;)I
	ireturn
  Labels:

public static final int size();
  Signature: ()I
  Code:
   Stack=1, Locals=0, Args_size=0
	getstatic	Field scala/collection/immutable/Nil$.MODULE$:Lscala/collection/immutable/Nil$;
	invokevirtual	Method scala/collection/immutable/Nil$.size:()I
	ireturn
  Labels:

public static final scala.collection.Iterator iterator();
  Signature: ()Lscala/collection/Iterator;
  Code:
   Stack=1, Locals=0, Args_size=0
	getstatic	Field scala/collection/immutable/Nil$.MODULE$:Lscala/collection/immutable/Nil$;
	invokevirtual	Method scala/collection/immutable/Nil$.iterator:()Lscala/collection/Iterator;
	areturn
  Labels:

public static final scala.collection.Iterator productElements();
  Signature: ()Lscala/collection/Iterator;
  Code:
   Stack=1, Locals=0, Args_size=0
	getstatic	Field scala/collection/immutable/Nil$.MODULE$:Lscala/collection/immutable/Nil$;
	invokevirtual	Method scala/collection/immutable/Nil$.productElements:()Lscala/collection/Iterator;
	areturn
  Labels:
  Deprecated: true

public static final scala.collection.Iterator productIterator();
  Signature: ()Lscala/collection/Iterator;
  Code:
   Stack=1, Locals=0, Args_size=0
	getstatic	Field scala/collection/immutable/Nil$.MODULE$:Lscala/collection/immutable/Nil$;
	invokevirtual	Method scala/collection/immutable/Nil$.productIterator:()Lscala/collection/Iterator;
	areturn
  Labels:

public static final java.lang.String productElementName(int);
  Signature: (I)Ljava/lang/String;
  Code:
   Stack=2, Locals=1, Args_size=1
	getstatic	Field scala/collection/immutable/Nil$.MODULE$:Lscala/collection/immutable/Nil$;
	iload_0
	invokevirtual	Method scala/collection/immutable/Nil$.productElementName:(I)Ljava/lang/String;
	areturn
  Labels:

public static final int lastIndexWhere(scala.Function1, int);
  Signature: (Lscala/Function1;I)I
  Code:
   Stack=3, Locals=2, Args_size=2
	getstatic	Field scala/collection/immutable/Nil$.MODULE$:Lscala/collection/immutable/Nil$;
	aload_0
	iload_1
	invokevirtual	Method scala/collection/immutable/Nil$.lastIndexWhere:(Lscala/Function1;I)I
	ireturn
  Labels:

public static final int indexWhere(scala.Function1, int);
  Signature: (Lscala/Function1;I)I
  Code:
   Stack=3, Locals=2, Args_size=2
	getstatic	Field scala/collection/immutable/Nil$.MODULE$:Lscala/collection/immutable/Nil$;
	aload_0
	iload_1
	invokevirtual	Method scala/collection/immutable/Nil$.indexWhere:(Lscala/Function1;I)I
	ireturn
  Labels:

public static final int segmentLength(scala.Function1, int);
  Signature: (Lscala/Function1;I)I
  Code:
   Stack=3, Locals=2, Args_size=2
	getstatic	Field scala/collection/immutable/Nil$.MODULE$:Lscala/collection/immutable/Nil$;
	aload_0
	iload_1
	invokevirtual	Method scala/collection/immutable/Nil$.segmentLength:(Lscala/Function1;I)I
	ireturn
  Labels:

public static final boolean isDefinedAt(int);
  Signature: (I)Z
  Code:
   Stack=2, Locals=1, Args_size=1
	getstatic	Field scala/collection/immutable/Nil$.MODULE$:Lscala/collection/immutable/Nil$;
	iload_0
	invokevirtual	Method scala/collection/immutable/Nil$.isDefinedAt:(I)Z
	ireturn
  Labels:

public static final int lengthCompare(int);
  Signature: (I)I
  Code:
   Stack=2, Locals=1, Args_size=1
	getstatic	Field scala/collection/immutable/Nil$.MODULE$:Lscala/collection/immutable/Nil$;
	iload_0
	invokevirtual	Method scala/collection/immutable/Nil$.lengthCompare:(I)I
	ireturn
  Labels:

public static final boolean sameElements(scala.collection.Iterable);
  Signature: (Lscala/collection/Iterable;)Z
  Code:
   Stack=2, Locals=1, Args_size=1
	getstatic	Field scala/collection/immutable/Nil$.MODULE$:Lscala/collection/immutable/Nil$;
	aload_0
	invokevirtual	Method scala/collection/immutable/Nil$.sameElements:(Lscala/collection/Iterable;)Z
	ireturn
  Labels:

public static final scala.collection.LinearSeqOptimized dropRight(int);
  Signature: (I)Lscala/collection/LinearSeqOptimized;
  Code:
   Stack=2, Locals=1, Args_size=1
	getstatic	Field scala/collection/immutable/Nil$.MODULE$:Lscala/collection/immutable/Nil$;
	iload_0
	invokevirtual	Method scala/collection/immutable/Nil$.dropRight:(I)Lscala/collection/LinearSeqOptimized;
	areturn
  Labels:

public static final java.lang.Object last();
  Signature: ()Ljava/lang/Object;
  Code:
   Stack=1, Locals=0, Args_size=0
	getstatic	Field scala/collection/immutable/Nil$.MODULE$:Lscala/collection/immutable/Nil$;
	invokevirtual	Method scala/collection/immutable/Nil$.last:()Ljava/lang/Object;
	areturn
  Labels:

public static final java.lang.Object reduceRight(scala.Function2);
  Signature: (Lscala/Function2;)Ljava/lang/Object;
  Code:
   Stack=2, Locals=1, Args_size=1
	getstatic	Field scala/collection/immutable/Nil$.MODULE$:Lscala/collection/immutable/Nil$;
	aload_0
	invokevirtual	Method scala/collection/immutable/Nil$.reduceRight:(Lscala/Function2;)Ljava/lang/Object;
	areturn
  Labels:

public static final java.lang.Object reduceLeft(scala.Function2);
  Signature: (Lscala/Function2;)Ljava/lang/Object;
  Code:
   Stack=2, Locals=1, Args_size=1
	getstatic	Field scala/collection/immutable/Nil$.MODULE$:Lscala/collection/immutable/Nil$;
	aload_0
	invokevirtual	Method scala/collection/immutable/Nil$.reduceLeft:(Lscala/Function2;)Ljava/lang/Object;
	areturn
  Labels:

public static final java.lang.Object foldRight(java.lang.Object, scala.Function2);
  Signature: (Ljava/lang/Object;Lscala/Function2;)Ljava/lang/Object;
  Code:
   Stack=3, Locals=2, Args_size=2
	getstatic	Field scala/collection/immutable/Nil$.MODULE$:Lscala/collection/immutable/Nil$;
	aload_0
	aload_1
	invokevirtual	Method scala/collection/immutable/Nil$.foldRight:(Ljava/lang/Object;Lscala/Function2;)Ljava/lang/Object;
	areturn
  Labels:

public static final java.lang.Object foldLeft(java.lang.Object, scala.Function2);
  Signature: (Ljava/lang/Object;Lscala/Function2;)Ljava/lang/Object;
  Code:
   Stack=3, Locals=2, Args_size=2
	getstatic	Field scala/collection/immutable/Nil$.MODULE$:Lscala/collection/immutable/Nil$;
	aload_0
	aload_1
	invokevirtual	Method scala/collection/immutable/Nil$.foldLeft:(Ljava/lang/Object;Lscala/Function2;)Ljava/lang/Object;
	areturn
  Labels:

public static final scala.Option find(scala.Function1);
  Signature: (Lscala/Function1;)Lscala/Option;
  Code:
   Stack=2, Locals=1, Args_size=1
	getstatic	Field scala/collection/immutable/Nil$.MODULE$:Lscala/collection/immutable/Nil$;
	aload_0
	invokevirtual	Method scala/collection/immutable/Nil$.find:(Lscala/Function1;)Lscala/Option;
	areturn
  Labels:

public static final int count(scala.Function1);
  Signature: (Lscala/Function1;)I
  Code:
   Stack=2, Locals=1, Args_size=1
	getstatic	Field scala/collection/immutable/Nil$.MODULE$:Lscala/collection/immutable/Nil$;
	aload_0
	invokevirtual	Method scala/collection/immutable/Nil$.count:(Lscala/Function1;)I
	ireturn
  Labels:

public static final boolean exists(scala.Function1);
  Signature: (Lscala/Function1;)Z
  Code:
   Stack=2, Locals=1, Args_size=1
	getstatic	Field scala/collection/immutable/Nil$.MODULE$:Lscala/collection/immutable/Nil$;
	aload_0
	invokevirtual	Method scala/collection/immutable/Nil$.exists:(Lscala/Function1;)Z
	ireturn
  Labels:

public static final boolean forall(scala.Function1);
  Signature: (Lscala/Function1;)Z
  Code:
   Stack=2, Locals=1, Args_size=1
	getstatic	Field scala/collection/immutable/Nil$.MODULE$:Lscala/collection/immutable/Nil$;
	aload_0
	invokevirtual	Method scala/collection/immutable/Nil$.forall:(Lscala/Function1;)Z
	ireturn
  Labels:

public static final void foreach(scala.Function1);
  Signature: (Lscala/Function1;)V
  Code:
   Stack=2, Locals=1, Args_size=1
	getstatic	Field scala/collection/immutable/Nil$.MODULE$:Lscala/collection/immutable/Nil$;
	aload_0
	invokevirtual	Method scala/collection/immutable/Nil$.foreach:(Lscala/Function1;)V
	return
  Labels:

public static final java.lang.Object apply(int);
  Signature: (I)Ljava/lang/Object;
  Code:
   Stack=2, Locals=1, Args_size=1
	getstatic	Field scala/collection/immutable/Nil$.MODULE$:Lscala/collection/immutable/Nil$;
	iload_0
	invokevirtual	Method scala/collection/immutable/Nil$.apply:(I)Ljava/lang/Object;
	areturn
  Labels:

public static final int length();
  Signature: ()I
  Code:
   Stack=1, Locals=0, Args_size=0
	getstatic	Field scala/collection/immutable/Nil$.MODULE$:Lscala/collection/immutable/Nil$;
	invokevirtual	Method scala/collection/immutable/Nil$.length:()I
	ireturn
  Labels:

public static final boolean scala$collection$LinearSeqOptimized$$super$sameElements(scala.collection.Iterable);
  Signature: (Lscala/collection/Iterable;)Z
  Code:
   Stack=2, Locals=1, Args_size=1
	getstatic	Field scala/collection/immutable/Nil$.MODULE$:Lscala/collection/immutable/Nil$;
	aload_0
	invokevirtual	Method scala/collection/immutable/Nil$.scala$collection$LinearSeqOptimized$$super$sameElements:(Lscala/collection/Iterable;)Z
	ireturn
  Labels:

public static final scala.collection.immutable.List sort(scala.Function2);
  Signature: (Lscala/Function2;)Lscala/collection/immutable/List;
  Code:
   Stack=2, Locals=1, Args_size=1
	getstatic	Field scala/collection/immutable/Nil$.MODULE$:Lscala/collection/immutable/Nil$;
	aload_0
	invokevirtual	Method scala/collection/immutable/Nil$.sort:(Lscala/Function2;)Lscala/collection/immutable/List;
	areturn
  Labels:
  Signature: length = 0x2
   01 FFFFFFD5 
  Deprecated: true

public static final scala.collection.immutable.List removeDuplicates();
  Signature: ()Lscala/collection/immutable/List;
  Code:
   Stack=1, Locals=0, Args_size=0
	getstatic	Field scala/collection/immutable/Nil$.MODULE$:Lscala/collection/immutable/Nil$;
	invokevirtual	Method scala/collection/immutable/Nil$.removeDuplicates:()Lscala/collection/immutable/List;
	areturn
  Labels:
  Signature: length = 0x2
   00 1A 
  Deprecated: true

public static final scala.collection.immutable.List $minus(java.lang.Object);
  Signature: (Ljava/lang/Object;)Lscala/collection/immutable/List;
  Code:
   Stack=2, Locals=1, Args_size=1
	getstatic	Field scala/collection/immutable/Nil$.MODULE$:Lscala/collection/immutable/Nil$;
	aload_0
	invokevirtual	Method scala/collection/immutable/Nil$.$minus:(Ljava/lang/Object;)Lscala/collection/immutable/List;
	areturn
  Labels:
  Signature: length = 0x2
   01 FFFFFFDD 
  Deprecated: true

public static final scala.collection.immutable.List $minus$minus(scala.collection.immutable.List);
  Signature: (Lscala/collection/immutable/List;)Lscala/collection/immutable/List;
  Code:
   Stack=2, Locals=1, Args_size=1
	getstatic	Field scala/collection/immutable/Nil$.MODULE$:Lscala/collection/immutable/Nil$;
	aload_0
	invokevirtual	Method scala/collection/immutable/Nil$.$minus$minus:(Lscala/collection/immutable/List;)Lscala/collection/immutable/List;
	areturn
  Labels:
  Signature: length = 0x2
   01 FFFFFFE2 
  Deprecated: true

public static final scala.collection.immutable.List remove(scala.Function1);
  Signature: (Lscala/Function1;)Lscala/collection/immutable/List;
  Code:
   Stack=2, Locals=1, Args_size=1
	getstatic	Field scala/collection/immutable/Nil$.MODULE$:Lscala/collection/immutable/Nil$;
	aload_0
	invokevirtual	Method scala/collection/immutable/Nil$.remove:(Lscala/Function1;)Lscala/collection/immutable/List;
	areturn
  Labels:
  Signature: length = 0x2
   01 FFFFFFE7 
  Deprecated: true

public static final scala.Tuple2 break(scala.Function1);
  Signature: (Lscala/Function1;)Lscala/Tuple2;
  Code:
   Stack=2, Locals=1, Args_size=1
	getstatic	Field scala/collection/immutable/Nil$.MODULE$:Lscala/collection/immutable/Nil$;
	aload_0
	invokevirtual	Method scala/collection/immutable/Nil$.break:(Lscala/Function1;)Lscala/Tuple2;
	areturn
  Labels:
  Signature: length = 0x2
   01 FFFFFFEB 
  Deprecated: true

public static final scala.collection.immutable.Stream toStream();
  Signature: ()Lscala/collection/immutable/Stream;
  Code:
   Stack=1, Locals=0, Args_size=0
	getstatic	Field scala/collection/immutable/Nil$.MODULE$:Lscala/collection/immutable/Nil$;
	invokevirtual	Method scala/collection/immutable/Nil$.toStream:()Lscala/collection/immutable/Stream;
	areturn
  Labels:
  Signature: length = 0x2
   01 FFFFFFF0 

public static final java.lang.String stringPrefix();
  Signature: ()Ljava/lang/String;
  Code:
   Stack=1, Locals=0, Args_size=0
	getstatic	Field scala/collection/immutable/Nil$.MODULE$:Lscala/collection/immutable/Nil$;
	invokevirtual	Method scala/collection/immutable/Nil$.stringPrefix:()Ljava/lang/String;
	areturn
  Labels:

public static final scala.collection.immutable.List reverse();
  Signature: ()Lscala/collection/immutable/List;
  Code:
   Stack=1, Locals=0, Args_size=0
	getstatic	Field scala/collection/immutable/Nil$.MODULE$:Lscala/collection/immutable/Nil$;
	invokevirtual	Method scala/collection/immutable/Nil$.reverse:()Lscala/collection/immutable/List;
	areturn
  Labels:
  Signature: length = 0x2
   00 1A 

public static final scala.Tuple2 span(scala.Function1);
  Signature: (Lscala/Function1;)Lscala/Tuple2;
  Code:
   Stack=2, Locals=1, Args_size=1
	getstatic	Field scala/collection/immutable/Nil$.MODULE$:Lscala/collection/immutable/Nil$;
	aload_0
	invokevirtual	Method scala/collection/immutable/Nil$.span:(Lscala/Function1;)Lscala/Tuple2;
	areturn
  Labels:
  Signature: length = 0x2
   01 FFFFFFEB 

public static final scala.collection.immutable.List dropWhile(scala.Function1);
  Signature: (Lscala/Function1;)Lscala/collection/immutable/List;
  Code:
   Stack=2, Locals=1, Args_size=1
	getstatic	Field scala/collection/immutable/Nil$.MODULE$:Lscala/collection/immutable/Nil$;
	aload_0
	invokevirtual	Method scala/collection/immutable/Nil$.dropWhile:(Lscala/Function1;)Lscala/collection/immutable/List;
	areturn
  Labels:
  Signature: length = 0x2
   01 FFFFFFE7 

public static final scala.collection.immutable.List takeWhile(scala.Function1);
  Signature: (Lscala/Function1;)Lscala/collection/immutable/List;
  Code:
   Stack=2, Locals=1, Args_size=1
	getstatic	Field scala/collection/immutable/Nil$.MODULE$:Lscala/collection/immutable/Nil$;
	aload_0
	invokevirtual	Method scala/collection/immutable/Nil$.takeWhile:(Lscala/Function1;)Lscala/collection/immutable/List;
	areturn
  Labels:
  Signature: length = 0x2
   01 FFFFFFE7 

public static final scala.Tuple2 splitAt(int);
  Signature: (I)Lscala/Tuple2;
  Code:
   Stack=2, Locals=1, Args_size=1
	getstatic	Field scala/collection/immutable/Nil$.MODULE$:Lscala/collection/immutable/Nil$;
	iload_0
	invokevirtual	Method scala/collection/immutable/Nil$.splitAt:(I)Lscala/Tuple2;
	areturn
  Labels:
  Signature: length = 0x2
   02 04 

public static final scala.collection.immutable.List takeRight(int);
  Signature: (I)Lscala/collection/immutable/List;
  Code:
   Stack=2, Locals=1, Args_size=1
	getstatic	Field scala/collection/immutable/Nil$.MODULE$:Lscala/collection/immutable/Nil$;
	iload_0
	invokevirtual	Method scala/collection/immutable/Nil$.takeRight:(I)Lscala/collection/immutable/List;
	areturn
  Labels:
  Signature: length = 0x2
   02 09 

public static final scala.collection.immutable.List slice(int, int);
  Signature: (II)Lscala/collection/immutable/List;
  Code:
   Stack=3, Locals=2, Args_size=2
	getstatic	Field scala/collection/immutable/Nil$.MODULE$:Lscala/collection/immutable/Nil$;
	iload_0
	iload_1
	invokevirtual	Method scala/collection/immutable/Nil$.slice:(II)Lscala/collection/immutable/List;
	areturn
  Labels:
  Signature: length = 0x2
   02 0E 

public static final scala.collection.immutable.List drop(int);
  Signature: (I)Lscala/collection/immutable/List;
  Code:
   Stack=2, Locals=1, Args_size=1
	getstatic	Field scala/collection/immutable/Nil$.MODULE$:Lscala/collection/immutable/Nil$;
	iload_0
	invokevirtual	Method scala/collection/immutable/Nil$.drop:(I)Lscala/collection/immutable/List;
	areturn
  Labels:
  Signature: length = 0x2
   02 09 

public static final scala.collection.immutable.List take(int);
  Signature: (I)Lscala/collection/immutable/List;
  Code:
   Stack=2, Locals=1, Args_size=1
	getstatic	Field scala/collection/immutable/Nil$.MODULE$:Lscala/collection/immutable/Nil$;
	iload_0
	invokevirtual	Method scala/collection/immutable/Nil$.take:(I)Lscala/collection/immutable/List;
	areturn
  Labels:
  Signature: length = 0x2
   02 09 

public static final scala.collection.immutable.List toList();
  Signature: ()Lscala/collection/immutable/List;
  Code:
   Stack=1, Locals=0, Args_size=0
	getstatic	Field scala/collection/immutable/Nil$.MODULE$:Lscala/collection/immutable/Nil$;
	invokevirtual	Method scala/collection/immutable/Nil$.toList:()Lscala/collection/immutable/List;
	areturn
  Labels:
  Signature: length = 0x2
   00 1A 

public static final java.lang.Object $plus$colon(java.lang.Object, scala.collection.generic.CanBuildFrom);
  Signature: (Ljava/lang/Object;Lscala/collection/generic/CanBuildFrom;)Ljava/lang/Object;
  Code:
   Stack=3, Locals=2, Args_size=2
	getstatic	Field scala/collection/immutable/Nil$.MODULE$:Lscala/collection/immutable/Nil$;
	aload_0
	aload_1
	invokevirtual	Method scala/collection/immutable/Nil$.$plus$colon:(Ljava/lang/Object;Lscala/collection/generic/CanBuildFrom;)Ljava/lang/Object;
	areturn
  Labels:
  Signature: length = 0x2
   02 1B 

public static final java.lang.Object $plus$plus(scala.collection.TraversableOnce, scala.collection.generic.CanBuildFrom);
  Signature: (Lscala/collection/TraversableOnce;Lscala/collection/generic/CanBuildFrom;)Ljava/lang/Object;
  Code:
   Stack=3, Locals=2, Args_size=2
	getstatic	Field scala/collection/immutable/Nil$.MODULE$:Lscala/collection/immutable/Nil$;
	aload_0
	aload_1
	invokevirtual	Method scala/collection/immutable/Nil$.$plus$plus:(Lscala/collection/TraversableOnce;Lscala/collection/generic/CanBuildFrom;)Ljava/lang/Object;
	areturn
  Labels:
  Signature: length = 0x2
   02 20 

public static final scala.collection.immutable.List mapConserve(scala.Function1);
  Signature: (Lscala/Function1;)Lscala/collection/immutable/List;
  Code:
   Stack=2, Locals=1, Args_size=1
	getstatic	Field scala/collection/immutable/Nil$.MODULE$:Lscala/collection/immutable/Nil$;
	aload_0
	invokevirtual	Method scala/collection/immutable/Nil$.mapConserve:(Lscala/Function1;)Lscala/collection/immutable/List;
	areturn
  Labels:
  Signature: length = 0x2
   02 24 

public static final scala.collection.immutable.List reverse_$colon$colon$colon(scala.collection.immutable.List);
  Signature: (Lscala/collection/immutable/List;)Lscala/collection/immutable/List;
  Code:
   Stack=2, Locals=1, Args_size=1
	getstatic	Field scala/collection/immutable/Nil$.MODULE$:Lscala/collection/immutable/Nil$;
	aload_0
	invokevirtual	Method scala/collection/immutable/Nil$.reverse_$colon$colon$colon:(Lscala/collection/immutable/List;)Lscala/collection/immutable/List;
	areturn
  Labels:
  Signature: length = 0x2
   01 FFFFFFE2 

public static final scala.collection.immutable.List $colon$colon$colon(scala.collection.immutable.List);
  Signature: (Lscala/collection/immutable/List;)Lscala/collection/immutable/List;
  Code:
   Stack=2, Locals=1, Args_size=1
	getstatic	Field scala/collection/immutable/Nil$.MODULE$:Lscala/collection/immutable/Nil$;
	aload_0
	invokevirtual	Method scala/collection/immutable/Nil$.$colon$colon$colon:(Lscala/collection/immutable/List;)Lscala/collection/immutable/List;
	areturn
  Labels:
  Signature: length = 0x2
   01 FFFFFFE2 

public static final scala.collection.immutable.List $colon$colon(java.lang.Object);
  Signature: (Ljava/lang/Object;)Lscala/collection/immutable/List;
  Code:
   Stack=2, Locals=1, Args_size=1
	getstatic	Field scala/collection/immutable/Nil$.MODULE$:Lscala/collection/immutable/Nil$;
	aload_0
	invokevirtual	Method scala/collection/immutable/Nil$.$colon$colon:(Ljava/lang/Object;)Lscala/collection/immutable/List;
	areturn
  Labels:
  Signature: length = 0x2
   01 FFFFFFDD 

public static final scala.collection.generic.GenericCompanion companion();
  Signature: ()Lscala/collection/generic/GenericCompanion;
  Code:
   Stack=1, Locals=0, Args_size=0
	getstatic	Field scala/collection/immutable/Nil$.MODULE$:Lscala/collection/immutable/Nil$;
	invokevirtual	Method scala/collection/immutable/Nil$.companion:()Lscala/collection/generic/GenericCompanion;
	areturn
  Labels:
  Signature: length = 0x2
   02 32 

public static final scala.collection.LinearSeqOptimized takeWhile(scala.Function1);
  Signature: (Lscala/Function1;)Lscala/collection/LinearSeqOptimized;
  Code:
   Stack=2, Locals=1, Args_size=1
	getstatic	Field scala/collection/immutable/Nil$.MODULE$:Lscala/collection/immutable/Nil$;
	aload_0
	invokevirtual	Method scala/collection/immutable/Nil$.takeWhile:(Lscala/Function1;)Lscala/collection/LinearSeqOptimized;
	areturn
  Labels:

public static final scala.collection.LinearSeqOptimized slice(int, int);
  Signature: (II)Lscala/collection/LinearSeqOptimized;
  Code:
   Stack=3, Locals=2, Args_size=2
	getstatic	Field scala/collection/immutable/Nil$.MODULE$:Lscala/collection/immutable/Nil$;
	iload_0
	iload_1
	invokevirtual	Method scala/collection/immutable/Nil$.slice:(II)Lscala/collection/LinearSeqOptimized;
	areturn
  Labels:

public static final scala.collection.LinearSeqOptimized drop(int);
  Signature: (I)Lscala/collection/LinearSeqOptimized;
  Code:
   Stack=2, Locals=1, Args_size=1
	getstatic	Field scala/collection/immutable/Nil$.MODULE$:Lscala/collection/immutable/Nil$;
	iload_0
	invokevirtual	Method scala/collection/immutable/Nil$.drop:(I)Lscala/collection/LinearSeqOptimized;
	areturn
  Labels:

public static final scala.collection.LinearSeqOptimized take(int);
  Signature: (I)Lscala/collection/LinearSeqOptimized;
  Code:
   Stack=2, Locals=1, Args_size=1
	getstatic	Field scala/collection/immutable/Nil$.MODULE$:Lscala/collection/immutable/Nil$;
	iload_0
	invokevirtual	Method scala/collection/immutable/Nil$.take:(I)Lscala/collection/LinearSeqOptimized;
	areturn
  Labels:

public static final java.lang.Object reverse();
  Signature: ()Ljava/lang/Object;
  Code:
   Stack=1, Locals=0, Args_size=0
	getstatic	Field scala/collection/immutable/Nil$.MODULE$:Lscala/collection/immutable/Nil$;
	invokevirtual	Method scala/collection/immutable/Nil$.reverse:()Ljava/lang/Object;
	areturn
  Labels:

public static final scala.Function1 andThen(scala.Function1);
  Signature: (Lscala/Function1;)Lscala/Function1;
  Code:
   Stack=2, Locals=1, Args_size=1
	getstatic	Field scala/collection/immutable/Nil$.MODULE$:Lscala/collection/immutable/Nil$;
	aload_0
	invokevirtual	Method scala/collection/immutable/Nil$.andThen:(Lscala/Function1;)Lscala/Function1;
	areturn
  Labels:

public static final scala.collection.IterableView projection();
  Signature: ()Lscala/collection/IterableView;
  Code:
   Stack=1, Locals=0, Args_size=0
	getstatic	Field scala/collection/immutable/Nil$.MODULE$:Lscala/collection/immutable/Nil$;
	invokevirtual	Method scala/collection/immutable/Nil$.projection:()Lscala/collection/IterableView;
	areturn
  Labels:
  Deprecated: true

public static final scala.collection.IterableView view(int, int);
  Signature: (II)Lscala/collection/IterableView;
  Code:
   Stack=3, Locals=2, Args_size=2
	getstatic	Field scala/collection/immutable/Nil$.MODULE$:Lscala/collection/immutable/Nil$;
	iload_0
	iload_1
	invokevirtual	Method scala/collection/immutable/Nil$.view:(II)Lscala/collection/IterableView;
	areturn
  Labels:

public static final scala.collection.IterableView view();
  Signature: ()Lscala/collection/IterableView;
  Code:
   Stack=1, Locals=0, Args_size=0
	getstatic	Field scala/collection/immutable/Nil$.MODULE$:Lscala/collection/immutable/Nil$;
	invokevirtual	Method scala/collection/immutable/Nil$.view:()Lscala/collection/IterableView;
	areturn
  Labels:

public static final java.lang.Object dropRight(int);
  Signature: (I)Ljava/lang/Object;
  Code:
   Stack=2, Locals=1, Args_size=1
	getstatic	Field scala/collection/immutable/Nil$.MODULE$:Lscala/collection/immutable/Nil$;
	iload_0
	invokevirtual	Method scala/collection/immutable/Nil$.dropRight:(I)Ljava/lang/Object;
	areturn
  Labels:

public static final java.lang.Object takeRight(int);
  Signature: (I)Ljava/lang/Object;
  Code:
   Stack=2, Locals=1, Args_size=1
	getstatic	Field scala/collection/immutable/Nil$.MODULE$:Lscala/collection/immutable/Nil$;
	iload_0
	invokevirtual	Method scala/collection/immutable/Nil$.takeRight:(I)Ljava/lang/Object;
	areturn
  Labels:

public static final java.lang.Object takeWhile(scala.Function1);
  Signature: (Lscala/Function1;)Ljava/lang/Object;
  Code:
   Stack=2, Locals=1, Args_size=1
	getstatic	Field scala/collection/immutable/Nil$.MODULE$:Lscala/collection/immutable/Nil$;
	aload_0
	invokevirtual	Method scala/collection/immutable/Nil$.takeWhile:(Lscala/Function1;)Ljava/lang/Object;
	areturn
  Labels:

public static final java.lang.Object slice(int, int);
  Signature: (II)Ljava/lang/Object;
  Code:
   Stack=3, Locals=2, Args_size=2
	getstatic	Field scala/collection/immutable/Nil$.MODULE$:Lscala/collection/immutable/Nil$;
	iload_0
	iload_1
	invokevirtual	Method scala/collection/immutable/Nil$.slice:(II)Ljava/lang/Object;
	areturn
  Labels:

public static final java.lang.Object take(int);
  Signature: (I)Ljava/lang/Object;
  Code:
   Stack=2, Locals=1, Args_size=1
	getstatic	Field scala/collection/immutable/Nil$.MODULE$:Lscala/collection/immutable/Nil$;
	iload_0
	invokevirtual	Method scala/collection/immutable/Nil$.take:(I)Ljava/lang/Object;
	areturn
  Labels:

public static final scala.collection.TraversableView view(int, int);
  Signature: (II)Lscala/collection/TraversableView;
  Code:
   Stack=3, Locals=2, Args_size=2
	getstatic	Field scala/collection/immutable/Nil$.MODULE$:Lscala/collection/immutable/Nil$;
	iload_0
	iload_1
	invokevirtual	Method scala/collection/immutable/Nil$.view:(II)Lscala/collection/TraversableView;
	areturn
  Labels:

public static final scala.collection.TraversableView view();
  Signature: ()Lscala/collection/TraversableView;
  Code:
   Stack=1, Locals=0, Args_size=0
	getstatic	Field scala/collection/immutable/Nil$.MODULE$:Lscala/collection/immutable/Nil$;
	invokevirtual	Method scala/collection/immutable/Nil$.view:()Lscala/collection/TraversableView;
	areturn
  Labels:

public static final java.lang.Object dropWhile(scala.Function1);
  Signature: (Lscala/Function1;)Ljava/lang/Object;
  Code:
   Stack=2, Locals=1, Args_size=1
	getstatic	Field scala/collection/immutable/Nil$.MODULE$:Lscala/collection/immutable/Nil$;
	aload_0
	invokevirtual	Method scala/collection/immutable/Nil$.dropWhile:(Lscala/Function1;)Ljava/lang/Object;
	areturn
  Labels:

public static final java.lang.Object drop(int);
  Signature: (I)Ljava/lang/Object;
  Code:
   Stack=2, Locals=1, Args_size=1
	getstatic	Field scala/collection/immutable/Nil$.MODULE$:Lscala/collection/immutable/Nil$;
	iload_0
	invokevirtual	Method scala/collection/immutable/Nil$.drop:(I)Ljava/lang/Object;
	areturn
  Labels:

}

