Compiled from "NumericRange.scala"
public class scala.collection.immutable.NumericRange$Inclusive extends scala.collection.immutable.NumericRange implements scala.ScalaObject
  SourceFile: "NumericRange.scala"
  Signature: length = 0x2
   00 3A 
  Scala: length = 0x
   
  InnerClass: 
   public Exclusive=class scala/collection/immutable/NumericRange$Exclusive of class scala/collection/immutable/NumericRange
   public Inclusive=class scala/collection/immutable/NumericRange$Inclusive of class scala/collection/immutable/NumericRange
  minor version: 0
  major version: 49
  Constant pool:
Asciz	SourceFile;
Asciz	NumericRange.scala;
Asciz	num;
Asciz	Lscala/math/Integral;;
Asciz	Lscala/math/Integral<TT;>;;
Asciz	Signature;
Asciz	copy;
Asciz	(Ljava/lang/Object;Ljava/lang/Object;Ljava/lang/Object;)Lscala/collection/immutable/NumericRange$Inclusive;;
Asciz	Code;
Asciz	scala/collection/immutable/NumericRange$;
class	scala/collection/immutable/NumericRange$
Asciz	MODULE$;
Asciz	Lscala/collection/immutable/NumericRange$;;
NameAndType	MODULE$:Lscala/collection/immutable/NumericRange$;
Field	scala/collection/immutable/NumericRange$.MODULE$:Lscala/collection/immutable/NumericRange$;
Asciz	LineNumberTable;
Asciz	scala/collection/immutable/NumericRange$Inclusive;
class	scala/collection/immutable/NumericRange$Inclusive
NameAndType	num:Lscala/math/Integral;
Field	scala/collection/immutable/NumericRange$Inclusive.num:Lscala/math/Integral;
Asciz	inclusive;
Asciz	(Ljava/lang/Object;Ljava/lang/Object;Ljava/lang/Object;Lscala/math/Integral;)Lscala/collection/immutable/NumericRange$Inclusive;;
NameAndType	inclusive:(Ljava/lang/Object;Ljava/lang/Object;Ljava/lang/Object;Lscala/math/Integral;)Lscala/collection/immutable/NumericRange$Inclusive;
Method	scala/collection/immutable/NumericRange$.inclusive:(Ljava/lang/Object;Ljava/lang/Object;Ljava/lang/Object;Lscala/math/Integral;)Lscala/collection/immutable/NumericRange$Inclusive;
Asciz	this;
Asciz	Lscala/collection/immutable/NumericRange$Inclusive;;
Asciz	start;
Asciz	Ljava/lang/Object;;
Asciz	end;
Asciz	step;
Asciz	LocalVariableTable;
Asciz	(TT;TT;TT;)Lscala/collection/immutable/NumericRange$Inclusive<TT;>;;
Asciz	exclusive;
Asciz	()Lscala/collection/immutable/NumericRange$Exclusive;;
Asciz	scala/collection/immutable/NumericRange;
class	scala/collection/immutable/NumericRange
Asciz	()Ljava/lang/Object;;
NameAndType	start:()Ljava/lang/Object;
Method	scala/collection/immutable/NumericRange.start:()Ljava/lang/Object;
NameAndType	end:()Ljava/lang/Object;
Method	scala/collection/immutable/NumericRange.end:()Ljava/lang/Object;
NameAndType	step:()Ljava/lang/Object;
Method	scala/collection/immutable/NumericRange.step:()Ljava/lang/Object;
Asciz	apply;
Asciz	(Ljava/lang/Object;Ljava/lang/Object;Ljava/lang/Object;Lscala/math/Integral;)Lscala/collection/immutable/NumericRange$Exclusive;;
NameAndType	apply:(Ljava/lang/Object;Ljava/lang/Object;Ljava/lang/Object;Lscala/math/Integral;)Lscala/collection/immutable/NumericRange$Exclusive;
Method	scala/collection/immutable/NumericRange$.apply:(Ljava/lang/Object;Ljava/lang/Object;Ljava/lang/Object;Lscala/math/Integral;)Lscala/collection/immutable/NumericRange$Exclusive;
Asciz	()Lscala/collection/immutable/NumericRange$Exclusive<TT;>;;
Asciz	(Ljava/lang/Object;Ljava/lang/Object;Ljava/lang/Object;)Lscala/collection/immutable/NumericRange;;
NameAndType	copy:(Ljava/lang/Object;Ljava/lang/Object;Ljava/lang/Object;)Lscala/collection/immutable/NumericRange$Inclusive;
Method	scala/collection/immutable/NumericRange$Inclusive.copy:(Ljava/lang/Object;Ljava/lang/Object;Ljava/lang/Object;)Lscala/collection/immutable/NumericRange$Inclusive;
Asciz	<init>;
Asciz	(Ljava/lang/Object;Ljava/lang/Object;Ljava/lang/Object;Lscala/math/Integral;)V;
Asciz	(Ljava/lang/Object;Ljava/lang/Object;Ljava/lang/Object;ZLscala/math/Integral;)V;
NameAndType	"<init>":(Ljava/lang/Object;Ljava/lang/Object;Ljava/lang/Object;ZLscala/math/Integral;)V
Method	scala/collection/immutable/NumericRange."<init>":(Ljava/lang/Object;Ljava/lang/Object;Ljava/lang/Object;ZLscala/math/Integral;)V
Asciz	(TT;TT;TT;Lscala/math/Integral<TT;>;)V;
Asciz	<T:Ljava/lang/Object;>Lscala/collection/immutable/NumericRange<TT;>;Lscala/ScalaObject;;
Asciz	Scala;
Asciz	InnerClasses;
Asciz	scala/collection/immutable/NumericRange$Exclusive;
class	scala/collection/immutable/NumericRange$Exclusive
Asciz	Exclusive;
Asciz	Inclusive;
Asciz	scala/ScalaObject;
class	scala/ScalaObject

{
private final scala.math.Integral num;
  Signature: Lscala/math/Integral;
  Signature: length = 0x2
   00 05 

public scala.collection.immutable.NumericRange$Inclusive copy(java.lang.Object, java.lang.Object, java.lang.Object);
  Signature: (Ljava/lang/Object;Ljava/lang/Object;Ljava/lang/Object;)Lscala/collection/immutable/NumericRange$Inclusive;
  Code:
   Stack=5, Locals=4, Args_size=4
	getstatic	Field scala/collection/immutable/NumericRange$.MODULE$:Lscala/collection/immutable/NumericRange$;
	aload_1
	aload_2
	aload_3
	aload_0
	getfield	Field num:Lscala/math/Integral;
	invokevirtual	Method scala/collection/immutable/NumericRange$.inclusive:(Ljava/lang/Object;Ljava/lang/Object;Ljava/lang/Object;Lscala/math/Integral;)Lscala/collection/immutable/NumericRange$Inclusive;
	areturn
  Labels:
  LocalVariableTable: 
   Start  Length  Slot  Name   Signature
   0      14      0    this       Lscala/collection/immutable/NumericRange$Inclusive;
   0      14      1    start       Ljava/lang/Object;
   0      14      2    end       Ljava/lang/Object;
   0      14      3    step       Ljava/lang/Object;

  Signature: length = 0x2
   00 20 

public scala.collection.immutable.NumericRange$Exclusive exclusive();
  Signature: ()Lscala/collection/immutable/NumericRange$Exclusive;
  Code:
   Stack=5, Locals=1, Args_size=1
	getstatic	Field scala/collection/immutable/NumericRange$.MODULE$:Lscala/collection/immutable/NumericRange$;
	aload_0
	invokespecial	Method scala/collection/immutable/NumericRange.start:()Ljava/lang/Object;
	aload_0
	invokespecial	Method scala/collection/immutable/NumericRange.end:()Ljava/lang/Object;
	aload_0
	invokespecial	Method scala/collection/immutable/NumericRange.step:()Ljava/lang/Object;
	aload_0
	getfield	Field num:Lscala/math/Integral;
	invokevirtual	Method scala/collection/immutable/NumericRange$.apply:(Ljava/lang/Object;Ljava/lang/Object;Ljava/lang/Object;Lscala/math/Integral;)Lscala/collection/immutable/NumericRange$Exclusive;
	areturn
  Labels:
  Signature: length = 0x2
   00 30 

public scala.collection.immutable.NumericRange copy(java.lang.Object, java.lang.Object, java.lang.Object);
  Signature: (Ljava/lang/Object;Ljava/lang/Object;Ljava/lang/Object;)Lscala/collection/immutable/NumericRange;
  Code:
   Stack=4, Locals=4, Args_size=4
	aload_0
	aload_1
	aload_2
	aload_3
	invokevirtual	Method copy:(Ljava/lang/Object;Ljava/lang/Object;Ljava/lang/Object;)Lscala/collection/immutable/NumericRange$Inclusive;
	areturn
  Labels:
  LocalVariableTable: 
   Start  Length  Slot  Name   Signature
   0      8      0    this       Lscala/collection/immutable/NumericRange$Inclusive;
   0      8      1    start       Ljava/lang/Object;
   0      8      2    end       Ljava/lang/Object;
   0      8      3    step       Ljava/lang/Object;


public scala.collection.immutable.NumericRange$Inclusive(java.lang.Object, java.lang.Object, java.lang.Object, scala.math.Integral);
  Signature: (Ljava/lang/Object;Ljava/lang/Object;Ljava/lang/Object;Lscala/math/Integral;)V
  Code:
   Stack=6, Locals=5, Args_size=5
	aload_0
	aload	4
	putfield	Field num:Lscala/math/Integral;
	aload_0
	aload_1
	aload_2
	aload_3
	iconst_1
	aload	4
	invokespecial	Method scala/collection/immutable/NumericRange."<init>":(Ljava/lang/Object;Ljava/lang/Object;Ljava/lang/Object;ZLscala/math/Integral;)V
	return
  Labels:
  LocalVariableTable: 
   Start  Length  Slot  Name   Signature
   0      17      0    this       Lscala/collection/immutable/NumericRange$Inclusive;
   0      17      1    start       Ljava/lang/Object;
   0      17      2    end       Ljava/lang/Object;
   0      17      3    step       Ljava/lang/Object;
   0      17      4    num       Lscala/math/Integral;

  Signature: length = 0x2
   00 39 

}

