Compiled from "NumericRange.scala"
public class scala.collection.immutable.NumericRange$Exclusive extends scala.collection.immutable.NumericRange implements scala.ScalaObject
  SourceFile: "NumericRange.scala"
  Signature: length = 0x2
   00 39 
  Scala: length = 0x
   
  InnerClass: 
   public #62= #61 of #16; //Inclusive=class scala/collection/immutable/NumericRange$Inclusive of class scala/collection/immutable/NumericRange
   public #63= #12 of #16; //Exclusive=class scala/collection/immutable/NumericRange$Exclusive of class scala/collection/immutable/NumericRange
  minor version: 0
  major version: 49
  Constant pool:
const #1 = Asciz	SourceFile;
const #2 = Asciz	NumericRange.scala;
const #3 = Asciz	num;
const #4 = Asciz	Lscala/math/Integral;;
const #5 = Asciz	Lscala/math/Integral<TT;>;;
const #6 = Asciz	Signature;
const #7 = Asciz	<init>;
const #8 = Asciz	(Ljava/lang/Object;Ljava/lang/Object;Ljava/lang/Object;Lscala/math/Integral;)V;
const #9 = Asciz	Code;
const #10 = Asciz	LineNumberTable;
const #11 = Asciz	scala/collection/immutable/NumericRange$Exclusive;
const #12 = class	#11;	//  scala/collection/immutable/NumericRange$Exclusive
const #13 = NameAndType	#3:#4;//  num:Lscala/math/Integral;
const #14 = Field	#12.#13;	//  scala/collection/immutable/NumericRange$Exclusive.num:Lscala/math/Integral;
const #15 = Asciz	scala/collection/immutable/NumericRange;
const #16 = class	#15;	//  scala/collection/immutable/NumericRange
const #17 = Asciz	(Ljava/lang/Object;Ljava/lang/Object;Ljava/lang/Object;ZLscala/math/Integral;)V;
const #18 = NameAndType	#7:#17;//  "<init>":(Ljava/lang/Object;Ljava/lang/Object;Ljava/lang/Object;ZLscala/math/Integral;)V
const #19 = Method	#16.#18;	//  scala/collection/immutable/NumericRange."<init>":(Ljava/lang/Object;Ljava/lang/Object;Ljava/lang/Object;ZLscala/math/Integral;)V
const #20 = Asciz	this;
const #21 = Asciz	Lscala/collection/immutable/NumericRange$Exclusive;;
const #22 = Asciz	start;
const #23 = Asciz	Ljava/lang/Object;;
const #24 = Asciz	end;
const #25 = Asciz	step;
const #26 = Asciz	LocalVariableTable;
const #27 = Asciz	(TT;TT;TT;Lscala/math/Integral<TT;>;)V;
const #28 = Asciz	copy;
const #29 = Asciz	(Ljava/lang/Object;Ljava/lang/Object;Ljava/lang/Object;Lscala/math/Integral;)Lscala/collection/immutable/NumericRange;;
const #30 = Asciz	(Ljava/lang/Object;Ljava/lang/Object;Ljava/lang/Object;Lscala/math/Integral;)Lscala/collection/immutable/NumericRange$Exclusive;;
const #31 = NameAndType	#28:#30;//  copy:(Ljava/lang/Object;Ljava/lang/Object;Ljava/lang/Object;Lscala/math/Integral;)Lscala/collection/immutable/NumericRange$Exclusive;
const #32 = Method	#12.#31;	//  scala/collection/immutable/NumericRange$Exclusive.copy:(Ljava/lang/Object;Ljava/lang/Object;Ljava/lang/Object;Lscala/math/Integral;)Lscala/collection/immutable/NumericRange$Exclusive;
const #33 = Asciz	unum;
const #34 = Asciz	inclusive;
const #35 = Asciz	()Lscala/collection/immutable/NumericRange$Inclusive;;
const #36 = Asciz	scala/collection/immutable/NumericRange$;
const #37 = class	#36;	//  scala/collection/immutable/NumericRange$
const #38 = Asciz	MODULE$;
const #39 = Asciz	Lscala/collection/immutable/NumericRange$;;
const #40 = NameAndType	#38:#39;//  MODULE$:Lscala/collection/immutable/NumericRange$;
const #41 = Field	#37.#40;	//  scala/collection/immutable/NumericRange$.MODULE$:Lscala/collection/immutable/NumericRange$;
const #42 = Asciz	()Ljava/lang/Object;;
const #43 = NameAndType	#22:#42;//  start:()Ljava/lang/Object;
const #44 = Method	#16.#43;	//  scala/collection/immutable/NumericRange.start:()Ljava/lang/Object;
const #45 = NameAndType	#24:#42;//  end:()Ljava/lang/Object;
const #46 = Method	#16.#45;	//  scala/collection/immutable/NumericRange.end:()Ljava/lang/Object;
const #47 = NameAndType	#25:#42;//  step:()Ljava/lang/Object;
const #48 = Method	#16.#47;	//  scala/collection/immutable/NumericRange.step:()Ljava/lang/Object;
const #49 = Asciz	(Ljava/lang/Object;Ljava/lang/Object;Ljava/lang/Object;Lscala/math/Integral;)Lscala/collection/immutable/NumericRange$Inclusive;;
const #50 = NameAndType	#34:#49;//  inclusive:(Ljava/lang/Object;Ljava/lang/Object;Ljava/lang/Object;Lscala/math/Integral;)Lscala/collection/immutable/NumericRange$Inclusive;
const #51 = Method	#37.#50;	//  scala/collection/immutable/NumericRange$.inclusive:(Ljava/lang/Object;Ljava/lang/Object;Ljava/lang/Object;Lscala/math/Integral;)Lscala/collection/immutable/NumericRange$Inclusive;
const #52 = Asciz	()Lscala/collection/immutable/NumericRange$Inclusive<TT;>;;
const #53 = Asciz	apply;
const #54 = NameAndType	#53:#30;//  apply:(Ljava/lang/Object;Ljava/lang/Object;Ljava/lang/Object;Lscala/math/Integral;)Lscala/collection/immutable/NumericRange$Exclusive;
const #55 = Method	#37.#54;	//  scala/collection/immutable/NumericRange$.apply:(Ljava/lang/Object;Ljava/lang/Object;Ljava/lang/Object;Lscala/math/Integral;)Lscala/collection/immutable/NumericRange$Exclusive;
const #56 = Asciz	<U:Ljava/lang/Object;>(TU;TU;TU;Lscala/math/Integral<TU;>;)Lscala/collection/immutable/NumericRange$Exclusive<TU;>;;
const #57 = Asciz	<T:Ljava/lang/Object;>Lscala/collection/immutable/NumericRange<TT;>;Lscala/ScalaObject;;
const #58 = Asciz	Scala;
const #59 = Asciz	InnerClasses;
const #60 = Asciz	scala/collection/immutable/NumericRange$Inclusive;
const #61 = class	#60;	//  scala/collection/immutable/NumericRange$Inclusive
const #62 = Asciz	Inclusive;
const #63 = Asciz	Exclusive;
const #64 = Asciz	scala/ScalaObject;
const #65 = class	#64;	//  scala/ScalaObject

{
public scala.collection.immutable.NumericRange$Exclusive(java.lang.Object, java.lang.Object, java.lang.Object, scala.math.Integral);
  Code:
   Stack=6, Locals=5, Args_size=5
   0:	aload_0
   1:	aload	4
   3:	putfield	#14; //Field num:Lscala/math/Integral;
   6:	aload_0
   7:	aload_1
   8:	aload_2
   9:	aload_3
   10:	iconst_0
   11:	aload	4
   13:	invokespecial	#19; //Method scala/collection/immutable/NumericRange."<init>":(Ljava/lang/Object;Ljava/lang/Object;Ljava/lang/Object;ZLscala/math/Integral;)V
   16:	return
  LineNumberTable: 
   line 209: 0
   line 210: 7
   line 209: 11

  LocalVariableTable: 
   Start  Length  Slot  Name   Signature
   0      17      0    this       Lscala/collection/immutable/NumericRange$Exclusive;
   0      17      1    start       Ljava/lang/Object;
   0      17      2    end       Ljava/lang/Object;
   0      17      3    step       Ljava/lang/Object;
   0      17      4    num       Lscala/math/Integral;

  Signature: length = 0x2
   00 1B 

public scala.collection.immutable.NumericRange copy(java.lang.Object, java.lang.Object, java.lang.Object, scala.math.Integral);
  Code:
   Stack=5, Locals=5, Args_size=5
   0:	aload_0
   1:	aload_1
   2:	aload_2
   3:	aload_3
   4:	aload	4
   6:	invokevirtual	#32; //Method copy:(Ljava/lang/Object;Ljava/lang/Object;Ljava/lang/Object;Lscala/math/Integral;)Lscala/collection/immutable/NumericRange$Exclusive;
   9:	areturn
  LineNumberTable: 
   line 209: 0

  LocalVariableTable: 
   Start  Length  Slot  Name   Signature
   0      10      0    this       Lscala/collection/immutable/NumericRange$Exclusive;
   0      10      1    start       Ljava/lang/Object;
   0      10      2    end       Ljava/lang/Object;
   0      10      3    step       Ljava/lang/Object;
   0      10      4    unum       Lscala/math/Integral;


public scala.collection.immutable.NumericRange$Inclusive inclusive();
  Code:
   Stack=5, Locals=1, Args_size=1
   0:	getstatic	#41; //Field scala/collection/immutable/NumericRange$.MODULE$:Lscala/collection/immutable/NumericRange$;
   3:	aload_0
   4:	invokespecial	#44; //Method scala/collection/immutable/NumericRange.start:()Ljava/lang/Object;
   7:	aload_0
   8:	invokespecial	#46; //Method scala/collection/immutable/NumericRange.end:()Ljava/lang/Object;
   11:	aload_0
   12:	invokespecial	#48; //Method scala/collection/immutable/NumericRange.step:()Ljava/lang/Object;
   15:	aload_0
   16:	getfield	#14; //Field num:Lscala/math/Integral;
   19:	invokevirtual	#51; //Method scala/collection/immutable/NumericRange$.inclusive:(Ljava/lang/Object;Ljava/lang/Object;Ljava/lang/Object;Lscala/math/Integral;)Lscala/collection/immutable/NumericRange$Inclusive;
   22:	areturn
  LineNumberTable: 
   line 214: 0

  Signature: length = 0x2
   00 34 

public scala.collection.immutable.NumericRange$Exclusive copy(java.lang.Object, java.lang.Object, java.lang.Object, scala.math.Integral);
  Code:
   Stack=5, Locals=5, Args_size=5
   0:	getstatic	#41; //Field scala/collection/immutable/NumericRange$.MODULE$:Lscala/collection/immutable/NumericRange$;
   3:	aload_1
   4:	aload_2
   5:	aload_3
   6:	aload	4
   8:	invokevirtual	#55; //Method scala/collection/immutable/NumericRange$.apply:(Ljava/lang/Object;Ljava/lang/Object;Ljava/lang/Object;Lscala/math/Integral;)Lscala/collection/immutable/NumericRange$Exclusive;
   11:	areturn
  LineNumberTable: 
   line 212: 0

  LocalVariableTable: 
   Start  Length  Slot  Name   Signature
   0      12      0    this       Lscala/collection/immutable/NumericRange$Exclusive;
   0      12      1    start       Ljava/lang/Object;
   0      12      2    end       Ljava/lang/Object;
   0      12      3    step       Ljava/lang/Object;
   0      12      4    unum       Lscala/math/Integral;

  Signature: length = 0x2
   00 38 

}

