Compiled from "PagedSeq.scala"
public class scala.collection.immutable.Page extends java.lang.Object implements scala.ScalaObject
  SourceFile: "PagedSeq.scala"
  Signature: length = 0x2
   00 FFFFFF89 
  ScalaSig: length = 0x36E
   05 00 FFFFFF81 06 06 04 01 02 04 09 02 04 50 61 67 65
   0A 02 03 04 01 09 69 6D 6D 75 74 61 62 6C 65 0A
   02 05 06 01 0A 63 6F 6C 6C 65 63 74 69 6F 6E 0A
   01 07 01 05 73 63 61 6C 61 03 00 15 02 0A 2A 13
   03 00 0B 13 10 02 0C 11 0D 01 0D 0A 02 0E 0F 01
   04 6C 61 6E 67 0A 01 10 01 04 6A 61 76 61 09 02
   12 0D 02 06 4F 62 6A 65 63 74 10 02 14 15 0D 01
   06 09 02 16 06 02 0B 53 63 61 6C 61 4F 62 6A 65
   63 74 08 08 18 00 FFFFFF82 FFFFFFC2 FFFFFF80 FFFFFF84 00 19 01 03 6E 75
   6D 15 01 1A 10 02 14 1B 09 02 1C 06 02 03 49 6E
   74 08 08 1E 00 FFFFFF82 FFFFFF80 FFFFFFA0 FFFFFF80 04 1A 01 04 6E 75 6D
   20 08 08 20 00 FFFFFF82 FFFFFF80 FFFFFFA0 FFFFFF80 05 21 01 0A 65 76 69
   64 65 6E 63 65 24 35 10 03 22 25 28 0E 02 14 23
   09 02 24 06 01 06 50 72 65 64 65 66 09 02 26 27
   02 0D 43 6C 61 73 73 4D 61 6E 69 66 65 73 74 0A
   02 24 06 10 02 29 2A 0C 00 04 08 2B 00 FFFFFF84 FFFFFF80 FFFFFF80
   FFFFFFC2 00 2C 02 01 54 11 02 2D 30 10 02 14 2E 09 02
   2F 06 02 07 4E 6F 74 68 69 6E 67 10 02 14 31 09
   02 32 06 02 03 41 6E 79 08 05 34 00 FFFFFF84 00 35 01
   06 3C 69 6E 69 74 3E 14 02 36 3A 16 02 37 39 10
   03 38 00 28 0D 01 02 08 05 20 33 FFFFFFC0 01 21 08 05
   18 33 FFFFFFC0 00 1A 08 07 3C 00 FFFFFFC2 FFFFFF80 FFFFFF84 06 3D 01 08
   50 61 67 65 53 69 7A 65 15 01 3E 0F 01 3F 1D 02
   10 00 08 06 41 00 FFFFFFA0 FFFFFF80 06 3E 01 09 50 61 67 65
   53 69 7A 65 20 08 07 43 00 FFFFFFC0 FFFFFF80 FFFFFF84 00 44 01 04
   6E 65 78 74 15 01 37 08 07 46 00 FFFFFFC0 FFFFFF80 FFFFFF84 00 47
   01 08 6E 65 78 74 5F 24 65 71 14 02 48 4B 10 02
   14 49 09 02 4A 06 02 04 55 6E 69 74 08 07 4C 45
   FFFFFF81 FFFFFF80 FFFFFFC0 00 37 01 03 78 24 31 08 06 4E 00 FFFFFFA0 FFFFFFA0
   04 37 01 05 6E 65 78 74 20 08 07 50 00 FFFFFFC0 FFFFFF80 FFFFFF84
   00 44 01 05 6C 61 74 65 72 08 07 52 00 FFFFFFC0 FFFFFF80 FFFFFF84
   00 53 01 09 6C 61 74 65 72 5F 24 65 71 14 02 48
   54 08 07 4C 51 FFFFFF81 FFFFFF80 FFFFFFC0 00 37 08 06 56 00 FFFFFFA0 FFFFFFA0
   04 37 01 06 6C 61 74 65 72 20 08 07 58 00 FFFFFFC0 FFFFFF80
   FFFFFF84 00 19 01 06 66 69 6C 6C 65 64 08 07 5A 00 FFFFFFC0
   FFFFFF80 FFFFFF84 00 5B 01 0A 66 69 6C 6C 65 64 5F 24 65 71
   14 02 48 5C 08 07 4C 59 FFFFFF81 FFFFFF80 FFFFFFC0 00 1A 08 06 5E
   00 FFFFFFA0 FFFFFFA0 04 1A 01 07 66 69 6C 6C 65 64 20 08 07
   60 00 FFFFFFC0 FFFFFF80 FFFFFF84 00 61 01 06 69 73 4C 61 73 74 15
   01 62 10 02 14 63 09 02 64 06 02 07 42 6F 6F 6C
   65 61 6E 08 07 66 00 FFFFFFC0 FFFFFF80 FFFFFF84 00 67 01 0A 69 73
   4C 61 73 74 5F 24 65 71 14 02 48 68 08 07 4C 65
   FFFFFF81 FFFFFF80 FFFFFFC0 00 62 08 06 6A 00 FFFFFFA0 FFFFFFA0 04 62 01 07 69
   73 4C 61 73 74 20 08 07 6C 00 FFFFFFC2 FFFFFF80 FFFFFF84 02 6D 01
   04 64 61 74 61 15 01 6E 10 03 14 6F 28 09 02 70
   06 02 05 41 72 72 61 79 08 06 72 00 FFFFFFA0 FFFFFF80 06 6E
   01 05 64 61 74 61 20 08 05 74 00 FFFFFF84 02 19 01 05
   73 74 61 72 74 08 05 76 00 FFFFFF84 02 19 01 03 65 6E
   64 08 05 78 00 FFFFFF84 02 44 01 06 6C 61 74 65 73 74
   08 05 7A 00 FFFFFF84 00 7B 01 05 61 70 70 6C 79 14 02
   28 7C 08 05 7D 79 FFFFFFC0 00 1A 01 05 69 6E 64 65 78
   08 06 7F 00 FFFFFF84 02 FFFFFF81 00 01 07 61 64 64 4D 6F 72
   65 14 03 37 FFFFFF81 01 08 07 FFFFFF81 02 7E FFFFFFC0 00 FFFFFF81 03 01
   04 6D 6F 72 65 10 07 14 FFFFFF81 04 6E 1A 1A 1A 09 03
   FFFFFF81 05 06 02 09 46 75 6E 63 74 69 6F 6E 33 
  minor version: 0
  major version: 49
  Constant pool:
const #1 = Asciz	SourceFile;
const #2 = Asciz	PagedSeq.scala;
const #3 = Asciz	data;
const #4 = Asciz	Ljava/lang/Object;;
const #5 = Asciz	[TT;;
const #6 = Asciz	Signature;
const #7 = Asciz	isLast;
const #8 = Asciz	Z;
const #9 = Asciz	filled;
const #10 = Asciz	I;
const #11 = Asciz	later;
const #12 = Asciz	Lscala/collection/immutable/Page;;
const #13 = Asciz	Lscala/collection/immutable/Page<TT;>;;
const #14 = Asciz	next;
const #15 = Asciz	PageSize;
const #16 = Asciz	evidence$5;
const #17 = Asciz	Lscala/reflect/ClassManifest;;
const #18 = Asciz	Lscala/reflect/ClassManifest<TT;>;;
const #19 = Asciz	num;
const #20 = Asciz	<init>;
const #21 = Asciz	(ILscala/reflect/ClassManifest;)V;
const #22 = Asciz	Code;
const #23 = Asciz	LineNumberTable;
const #24 = Asciz	scala/collection/immutable/Page;
const #25 = class	#24;	//  scala/collection/immutable/Page
const #26 = NameAndType	#19:#10;//  num:I
const #27 = Field	#25.#26;	//  scala/collection/immutable/Page.num:I
const #28 = NameAndType	#16:#17;//  evidence$5:Lscala/reflect/ClassManifest;
const #29 = Field	#25.#28;	//  scala/collection/immutable/Page.evidence$5:Lscala/reflect/ClassManifest;
const #30 = Asciz	java/lang/Object;
const #31 = class	#30;	//  java/lang/Object
const #32 = Asciz	()V;
const #33 = NameAndType	#20:#32;//  "<init>":()V
const #34 = Method	#31.#33;	//  java/lang/Object."<init>":()V
const #35 = NameAndType	#14:#12;//  next:Lscala/collection/immutable/Page;
const #36 = Field	#25.#35;	//  scala/collection/immutable/Page.next:Lscala/collection/immutable/Page;
const #37 = NameAndType	#11:#12;//  later:Lscala/collection/immutable/Page;
const #38 = Field	#25.#37;	//  scala/collection/immutable/Page.later:Lscala/collection/immutable/Page;
const #39 = NameAndType	#9:#10;//  filled:I
const #40 = Field	#25.#39;	//  scala/collection/immutable/Page.filled:I
const #41 = NameAndType	#7:#8;//  isLast:Z
const #42 = Field	#25.#41;	//  scala/collection/immutable/Page.isLast:Z
const #43 = int	4096;
const #44 = Asciz	scala/reflect/ClassManifest;
const #45 = class	#44;	//  scala/reflect/ClassManifest
const #46 = Asciz	newArray;
const #47 = Asciz	(I)Ljava/lang/Object;;
const #48 = NameAndType	#46:#47;//  newArray:(I)Ljava/lang/Object;
const #49 = InterfaceMethod	#45.#48;	//  scala/reflect/ClassManifest.newArray:(I)Ljava/lang/Object;
const #50 = NameAndType	#3:#4;//  data:Ljava/lang/Object;
const #51 = Field	#25.#50;	//  scala/collection/immutable/Page.data:Ljava/lang/Object;
const #52 = Asciz	this;
const #53 = Asciz	LocalVariableTable;
const #54 = Asciz	(ILscala/reflect/ClassManifest<TT;>;)V;
const #55 = Asciz	addMore;
const #56 = Asciz	(Lscala/Function3;)Lscala/collection/immutable/Page;;
const #57 = Asciz	()I;
const #58 = NameAndType	#9:#57;//  filled:()I
const #59 = Method	#25.#58;	//  scala/collection/immutable/Page.filled:()I
const #60 = NameAndType	#19:#57;//  num:()I
const #61 = Method	#25.#60;	//  scala/collection/immutable/Page.num:()I
const #62 = NameAndType	#20:#21;//  "<init>":(ILscala/reflect/ClassManifest;)V
const #63 = Method	#25.#62;	//  scala/collection/immutable/Page."<init>":(ILscala/reflect/ClassManifest;)V
const #64 = Asciz	next_$eq;
const #65 = Asciz	(Lscala/collection/immutable/Page;)V;
const #66 = NameAndType	#64:#65;//  next_$eq:(Lscala/collection/immutable/Page;)V
const #67 = Method	#25.#66;	//  scala/collection/immutable/Page.next_$eq:(Lscala/collection/immutable/Page;)V
const #68 = Asciz	()Lscala/collection/immutable/Page;;
const #69 = NameAndType	#14:#68;//  next:()Lscala/collection/immutable/Page;
const #70 = Method	#25.#69;	//  scala/collection/immutable/Page.next:()Lscala/collection/immutable/Page;
const #71 = Asciz	scala/runtime/BoxesRunTime;
const #72 = class	#71;	//  scala/runtime/BoxesRunTime
const #73 = Asciz	boxToInteger;
const #74 = Asciz	(I)Ljava/lang/Integer;;
const #75 = NameAndType	#73:#74;//  boxToInteger:(I)Ljava/lang/Integer;
const #76 = Method	#72.#75;	//  scala/runtime/BoxesRunTime.boxToInteger:(I)Ljava/lang/Integer;
const #77 = Asciz	scala/Function3;
const #78 = class	#77;	//  scala/Function3
const #79 = Asciz	apply;
const #80 = Asciz	(Ljava/lang/Object;Ljava/lang/Object;Ljava/lang/Object;)Ljava/lang/Object;;
const #81 = NameAndType	#79:#80;//  apply:(Ljava/lang/Object;Ljava/lang/Object;Ljava/lang/Object;)Ljava/lang/Object;
const #82 = InterfaceMethod	#78.#81;	//  scala/Function3.apply:(Ljava/lang/Object;Ljava/lang/Object;Ljava/lang/Object;)Ljava/lang/Object;
const #83 = Asciz	unboxToInt;
const #84 = Asciz	(Ljava/lang/Object;)I;
const #85 = NameAndType	#83:#84;//  unboxToInt:(Ljava/lang/Object;)I
const #86 = Method	#72.#85;	//  scala/runtime/BoxesRunTime.unboxToInt:(Ljava/lang/Object;)I
const #87 = Asciz	isLast_$eq;
const #88 = Asciz	(Z)V;
const #89 = NameAndType	#87:#88;//  isLast_$eq:(Z)V
const #90 = Method	#25.#89;	//  scala/collection/immutable/Page.isLast_$eq:(Z)V
const #91 = Asciz	filled_$eq;
const #92 = Asciz	(I)V;
const #93 = NameAndType	#91:#92;//  filled_$eq:(I)V
const #94 = Method	#25.#93;	//  scala/collection/immutable/Page.filled_$eq:(I)V
const #95 = Asciz	more;
const #96 = Asciz	Lscala/Function3;;
const #97 = Asciz	count;
const #98 = Asciz	(Lscala/Function3<[TT;Ljava/lang/Integer;Ljava/lang/Integer;Ljava/lang/Integer;>;)Lscala/collection/immutable/Page<TT;>;;
const #99 = Asciz	java/lang/IndexOutOfBoundsException;
const #100 = class	#99;	//  java/lang/IndexOutOfBoundsException
const #101 = Asciz	toString;
const #102 = Asciz	()Ljava/lang/String;;
const #103 = NameAndType	#101:#102;//  toString:()Ljava/lang/String;
const #104 = Method	#31.#103;	//  java/lang/Object.toString:()Ljava/lang/String;
const #105 = Asciz	(Ljava/lang/String;)V;
const #106 = NameAndType	#20:#105;//  "<init>":(Ljava/lang/String;)V
const #107 = Method	#100.#106;	//  java/lang/IndexOutOfBoundsException."<init>":(Ljava/lang/String;)V
const #108 = Asciz	java/lang/reflect/Array;
const #109 = class	#108;	//  java/lang/reflect/Array
const #110 = Asciz	get;
const #111 = Asciz	(Ljava/lang/Object;I)Ljava/lang/Object;;
const #112 = NameAndType	#110:#111;//  get:(Ljava/lang/Object;I)Ljava/lang/Object;
const #113 = Method	#109.#112;	//  java/lang/reflect/Array.get:(Ljava/lang/Object;I)Ljava/lang/Object;
const #114 = Asciz	index;
const #115 = Asciz	(I)TT;;
const #116 = Asciz	latest;
const #117 = NameAndType	#11:#68;//  later:()Lscala/collection/immutable/Page;
const #118 = Method	#25.#117;	//  scala/collection/immutable/Page.later:()Lscala/collection/immutable/Page;
const #119 = Asciz	equals;
const #120 = Asciz	(Ljava/lang/Object;)Z;
const #121 = NameAndType	#119:#120;//  equals:(Ljava/lang/Object;)Z
const #122 = Method	#31.#121;	//  java/lang/Object.equals:(Ljava/lang/Object;)Z
const #123 = NameAndType	#116:#68;//  latest:()Lscala/collection/immutable/Page;
const #124 = Method	#25.#123;	//  scala/collection/immutable/Page.latest:()Lscala/collection/immutable/Page;
const #125 = Asciz	later_$eq;
const #126 = NameAndType	#125:#65;//  later_$eq:(Lscala/collection/immutable/Page;)V
const #127 = Method	#25.#126;	//  scala/collection/immutable/Page.later_$eq:(Lscala/collection/immutable/Page;)V
const #128 = Asciz	()Lscala/collection/immutable/Page<TT;>;;
const #129 = Asciz	end;
const #130 = Asciz	start;
const #131 = NameAndType	#130:#57;//  start:()I
const #132 = Method	#25.#131;	//  scala/collection/immutable/Page.start:()I
const #133 = Asciz	()Ljava/lang/Object;;
const #134 = Asciz	()[TT;;
const #135 = Asciz	()Z;
const #136 = Asciz	(Lscala/collection/immutable/Page<TT;>;)V;
const #137 = Asciz	<T:Ljava/lang/Object;>Ljava/lang/Object;Lscala/ScalaObject;;
const #138 = Asciz	ScalaSig;
const #139 = Asciz	scala/ScalaObject;
const #140 = class	#139;	//  scala/ScalaObject

{
public scala.collection.immutable.Page(int, scala.reflect.ClassManifest);
  Code:
   Stack=3, Locals=3, Args_size=3
   0:	aload_0
   1:	iload_1
   2:	putfield	#27; //Field num:I
   5:	aload_0
   6:	aload_2
   7:	putfield	#29; //Field evidence$5:Lscala/reflect/ClassManifest;
   10:	aload_0
   11:	invokespecial	#34; //Method java/lang/Object."<init>":()V
   14:	aload_0
   15:	aconst_null
   16:	putfield	#36; //Field next:Lscala/collection/immutable/Page;
   19:	aload_0
   20:	aload_0
   21:	putfield	#38; //Field later:Lscala/collection/immutable/Page;
   24:	aload_0
   25:	iconst_0
   26:	putfield	#40; //Field filled:I
   29:	aload_0
   30:	iconst_0
   31:	putfield	#42; //Field isLast:Z
   34:	aload_0
   35:	aload_2
   36:	ldc	#43; //int 4096
   38:	invokeinterface	#49,  2; //InterfaceMethod scala/reflect/ClassManifest.newArray:(I)Ljava/lang/Object;
   43:	putfield	#51; //Field data:Ljava/lang/Object;
   46:	return
  LineNumberTable: 
   line 198: 0
   line 203: 14
   line 206: 19
   line 209: 24
   line 213: 29
   line 216: 34

  LocalVariableTable: 
   Start  Length  Slot  Name   Signature
   0      47      0    this       Lscala/collection/immutable/Page;
   0      47      1    num       I
   0      47      2    evidence$5       Lscala/reflect/ClassManifest;

  Signature: length = 0x2
   00 36 

public final scala.collection.immutable.Page addMore(scala.Function3);
  Code:
   Stack=5, Locals=5, Args_size=2
   0:	aload_0
   1:	invokevirtual	#59; //Method filled:()I
   4:	ldc	#43; //int 4096
   6:	if_icmpne	38
   9:	aload_0
   10:	new	#25; //class scala/collection/immutable/Page
   13:	dup
   14:	aload_0
   15:	invokevirtual	#61; //Method num:()I
   18:	iconst_1
   19:	iadd
   20:	aload_0
   21:	getfield	#29; //Field evidence$5:Lscala/reflect/ClassManifest;
   24:	invokespecial	#63; //Method "<init>":(ILscala/reflect/ClassManifest;)V
   27:	invokevirtual	#67; //Method next_$eq:(Lscala/collection/immutable/Page;)V
   30:	aload_0
   31:	invokevirtual	#70; //Method next:()Lscala/collection/immutable/Page;
   34:	astore_0
   35:	goto	0
   38:	aload_1
   39:	aload_0
   40:	getfield	#51; //Field data:Ljava/lang/Object;
   43:	aload_0
   44:	invokevirtual	#59; //Method filled:()I
   47:	istore_2
   48:	iload_2
   49:	invokestatic	#76; //Method scala/runtime/BoxesRunTime.boxToInteger:(I)Ljava/lang/Integer;
   52:	ldc	#43; //int 4096
   54:	aload_0
   55:	invokevirtual	#59; //Method filled:()I
   58:	isub
   59:	istore_3
   60:	iload_3
   61:	invokestatic	#76; //Method scala/runtime/BoxesRunTime.boxToInteger:(I)Ljava/lang/Integer;
   64:	invokeinterface	#82,  4; //InterfaceMethod scala/Function3.apply:(Ljava/lang/Object;Ljava/lang/Object;Ljava/lang/Object;)Ljava/lang/Object;
   69:	invokestatic	#86; //Method scala/runtime/BoxesRunTime.unboxToInt:(Ljava/lang/Object;)I
   72:	istore	4
   74:	iload	4
   76:	iconst_0
   77:	if_icmpge	88
   80:	aload_0
   81:	iconst_1
   82:	invokevirtual	#90; //Method isLast_$eq:(Z)V
   85:	goto	99
   88:	aload_0
   89:	aload_0
   90:	invokevirtual	#59; //Method filled:()I
   93:	iload	4
   95:	iadd
   96:	invokevirtual	#94; //Method filled_$eq:(I)V
   99:	aload_0
   100:	areturn
  LineNumberTable: 
   line 243: 0
   line 244: 9
   line 245: 30
   line 247: 38
   line 248: 74
   line 249: 88
   line 250: 99
   line 242: 100

  LocalVariableTable: 
   Start  Length  Slot  Name   Signature
   0      101      0    this       Lscala/collection/immutable/Page;
   0      101      1    more       Lscala/Function3;
   74      26      4    count       I

  Signature: length = 0x2
   00 62 

public java.lang.Object apply(int);
  Code:
   Stack=4, Locals=4, Args_size=2
   0:	iload_1
   1:	aload_0
   2:	invokevirtual	#61; //Method num:()I
   5:	ldc	#43; //int 4096
   7:	imul
   8:	if_icmplt	27
   11:	iload_1
   12:	aload_0
   13:	invokevirtual	#61; //Method num:()I
   16:	ldc	#43; //int 4096
   18:	imul
   19:	isub
   20:	aload_0
   21:	invokevirtual	#59; //Method filled:()I
   24:	if_icmplt	42
   27:	new	#100; //class java/lang/IndexOutOfBoundsException
   30:	dup
   31:	iload_1
   32:	invokestatic	#76; //Method scala/runtime/BoxesRunTime.boxToInteger:(I)Ljava/lang/Integer;
   35:	invokevirtual	#104; //Method java/lang/Object.toString:()Ljava/lang/String;
   38:	invokespecial	#107; //Method java/lang/IndexOutOfBoundsException."<init>":(Ljava/lang/String;)V
   41:	athrow
   42:	aload_0
   43:	getfield	#51; //Field data:Ljava/lang/Object;
   46:	iload_1
   47:	aload_0
   48:	invokevirtual	#61; //Method num:()I
   51:	ldc	#43; //int 4096
   53:	imul
   54:	isub
   55:	istore_3
   56:	astore_2
   57:	aload_2
   58:	iload_3
   59:	invokestatic	#113; //Method java/lang/reflect/Array.get:(Ljava/lang/Object;I)Ljava/lang/Object;
   62:	areturn
  LineNumberTable: 
   line 234: 0
   line 235: 42

  LocalVariableTable: 
   Start  Length  Slot  Name   Signature
   0      63      0    this       Lscala/collection/immutable/Page;
   0      63      1    index       I

  Signature: length = 0x2
   00 73 

public final scala.collection.immutable.Page latest();
  Code:
   Stack=2, Locals=2, Args_size=1
   0:	aload_0
   1:	invokevirtual	#118; //Method later:()Lscala/collection/immutable/Page;
   4:	invokevirtual	#70; //Method next:()Lscala/collection/immutable/Page;
   7:	dup
   8:	astore_1
   9:	ifnull	34
   12:	aload_1
   13:	aconst_null
   14:	invokevirtual	#122; //Method java/lang/Object.equals:(Ljava/lang/Object;)Z
   17:	ifne	34
   20:	aload_0
   21:	aload_0
   22:	invokevirtual	#118; //Method later:()Lscala/collection/immutable/Page;
   25:	invokevirtual	#70; //Method next:()Lscala/collection/immutable/Page;
   28:	invokevirtual	#124; //Method latest:()Lscala/collection/immutable/Page;
   31:	invokevirtual	#127; //Method later_$eq:(Lscala/collection/immutable/Page;)V
   34:	aload_0
   35:	invokevirtual	#118; //Method later:()Lscala/collection/immutable/Page;
   38:	areturn
  LineNumberTable: 
   line 227: 0
   line 228: 34

  Signature: length = 0x2
   00 FFFFFF80 

public final int end();
  Code:
   Stack=2, Locals=1, Args_size=1
   0:	aload_0
   1:	invokevirtual	#132; //Method start:()I
   4:	aload_0
   5:	invokevirtual	#59; //Method filled:()I
   8:	iadd
   9:	ireturn
  LineNumberTable: 
   line 223: 0


public final int start();
  Code:
   Stack=2, Locals=1, Args_size=1
   0:	aload_0
   1:	invokevirtual	#61; //Method num:()I
   4:	ldc	#43; //int 4096
   6:	imul
   7:	ireturn
  LineNumberTable: 
   line 219: 0


public final java.lang.Object data();
  Code:
   Stack=1, Locals=1, Args_size=1
   0:	aload_0
   1:	getfield	#51; //Field data:Ljava/lang/Object;
   4:	areturn
  LineNumberTable: 
   line 216: 0

  Signature: length = 0x2
   00 FFFFFF86 

public void isLast_$eq(boolean);
  Code:
   Stack=2, Locals=2, Args_size=2
   0:	aload_0
   1:	iload_1
   2:	putfield	#42; //Field isLast:Z
   5:	return
  LineNumberTable: 
   line 213: 0


public boolean isLast();
  Code:
   Stack=1, Locals=1, Args_size=1
   0:	aload_0
   1:	getfield	#42; //Field isLast:Z
   4:	ireturn
  LineNumberTable: 
   line 213: 0


public void filled_$eq(int);
  Code:
   Stack=2, Locals=2, Args_size=2
   0:	aload_0
   1:	iload_1
   2:	putfield	#40; //Field filled:I
   5:	return
  LineNumberTable: 
   line 209: 0


public int filled();
  Code:
   Stack=1, Locals=1, Args_size=1
   0:	aload_0
   1:	getfield	#40; //Field filled:I
   4:	ireturn
  LineNumberTable: 
   line 209: 0


public void later_$eq(scala.collection.immutable.Page);
  Code:
   Stack=2, Locals=2, Args_size=2
   0:	aload_0
   1:	aload_1
   2:	putfield	#38; //Field later:Lscala/collection/immutable/Page;
   5:	return
  LineNumberTable: 
   line 206: 0

  Signature: length = 0x2
   00 FFFFFF88 

public scala.collection.immutable.Page later();
  Code:
   Stack=1, Locals=1, Args_size=1
   0:	aload_0
   1:	getfield	#38; //Field later:Lscala/collection/immutable/Page;
   4:	areturn
  LineNumberTable: 
   line 206: 0

  Signature: length = 0x2
   00 FFFFFF80 

public void next_$eq(scala.collection.immutable.Page);
  Code:
   Stack=2, Locals=2, Args_size=2
   0:	aload_0
   1:	aload_1
   2:	putfield	#36; //Field next:Lscala/collection/immutable/Page;
   5:	return
  LineNumberTable: 
   line 203: 0

  Signature: length = 0x2
   00 FFFFFF88 

public scala.collection.immutable.Page next();
  Code:
   Stack=1, Locals=1, Args_size=1
   0:	aload_0
   1:	getfield	#36; //Field next:Lscala/collection/immutable/Page;
   4:	areturn
  LineNumberTable: 
   line 203: 0

  Signature: length = 0x2
   00 FFFFFF80 

public int num();
  Code:
   Stack=1, Locals=1, Args_size=1
   0:	aload_0
   1:	getfield	#27; //Field num:I
   4:	ireturn
  LineNumberTable: 
   line 198: 0


}

