Compiled from "PagedSeq.scala"
public final class scala.collection.immutable.PagedSeq$$anonfun$fromReader$1 extends java.lang.Object implements scala.Function3,scala.ScalaObject,java.io.Serializable
  SourceFile: "PagedSeq.scala"
  Scala: length = 0x
   
  InnerClass: 
   public final #85= #10 of #84; //$anonfun$fromReader$1=class scala/collection/immutable/PagedSeq$$anonfun$fromReader$1 of class scala/collection/immutable/PagedSeq
  minor version: 0
  major version: 49
  Constant pool:
const #1 = Asciz	SourceFile;
const #2 = Asciz	PagedSeq.scala;
const #3 = Asciz	source$3;
const #4 = Asciz	Ljava/io/Reader;;
const #5 = Asciz	<init>;
const #6 = Asciz	(Ljava/io/Reader;)V;
const #7 = Asciz	Code;
const #8 = Asciz	LineNumberTable;
const #9 = Asciz	scala/collection/immutable/PagedSeq$$anonfun$fromReader$1;
const #10 = class	#9;	//  scala/collection/immutable/PagedSeq$$anonfun$fromReader$1
const #11 = NameAndType	#3:#4;//  source$3:Ljava/io/Reader;
const #12 = Field	#10.#11;	//  scala/collection/immutable/PagedSeq$$anonfun$fromReader$1.source$3:Ljava/io/Reader;
const #13 = Asciz	java/lang/Object;
const #14 = class	#13;	//  java/lang/Object
const #15 = Asciz	()V;
const #16 = NameAndType	#5:#15;//  "<init>":()V
const #17 = Method	#14.#16;	//  java/lang/Object."<init>":()V
const #18 = Asciz	scala/Function3$class;
const #19 = class	#18;	//  scala/Function3$class
const #20 = Asciz	$init$;
const #21 = Asciz	(Lscala/Function3;)V;
const #22 = NameAndType	#20:#21;//  $init$:(Lscala/Function3;)V
const #23 = Method	#19.#22;	//  scala/Function3$class.$init$:(Lscala/Function3;)V
const #24 = Asciz	apply;
const #25 = Asciz	(Ljava/lang/Object;Ljava/lang/Object;Ljava/lang/Object;)Ljava/lang/Object;;
const #26 = Asciz	scala/runtime/BoxedArray;
const #27 = class	#26;	//  scala/runtime/BoxedArray
const #28 = Asciz	scala/runtime/ScalaRunTime$;
const #29 = class	#28;	//  scala/runtime/ScalaRunTime$
const #30 = Asciz	MODULE$;
const #31 = Asciz	Lscala/runtime/ScalaRunTime$;;
const #32 = NameAndType	#30:#31;//  MODULE$:Lscala/runtime/ScalaRunTime$;
const #33 = Field	#29.#32;	//  scala/runtime/ScalaRunTime$.MODULE$:Lscala/runtime/ScalaRunTime$;
const #34 = Asciz	java/lang/Character;
const #35 = class	#34;	//  java/lang/Character
const #36 = Asciz	TYPE;
const #37 = Asciz	Ljava/lang/Class;;
const #38 = NameAndType	#36:#37;//  TYPE:Ljava/lang/Class;
const #39 = Field	#35.#38;	//  java/lang/Character.TYPE:Ljava/lang/Class;
const #40 = Asciz	arrayValue;
const #41 = Asciz	(Lscala/runtime/BoxedArray;Ljava/lang/Class;)Ljava/lang/Object;;
const #42 = NameAndType	#40:#41;//  arrayValue:(Lscala/runtime/BoxedArray;Ljava/lang/Class;)Ljava/lang/Object;
const #43 = Method	#29.#42;	//  scala/runtime/ScalaRunTime$.arrayValue:(Lscala/runtime/BoxedArray;Ljava/lang/Class;)Ljava/lang/Object;
const #44 = Asciz	[C;
const #45 = class	#44;	//  "[C"
const #46 = Asciz	scala/runtime/BoxesRunTime;
const #47 = class	#46;	//  scala/runtime/BoxesRunTime
const #48 = Asciz	unboxToInt;
const #49 = Asciz	(Ljava/lang/Object;)I;
const #50 = NameAndType	#48:#49;//  unboxToInt:(Ljava/lang/Object;)I
const #51 = Method	#47.#50;	//  scala/runtime/BoxesRunTime.unboxToInt:(Ljava/lang/Object;)I
const #52 = Asciz	([CII)I;
const #53 = NameAndType	#24:#52;//  apply:([CII)I
const #54 = Method	#10.#53;	//  scala/collection/immutable/PagedSeq$$anonfun$fromReader$1.apply:([CII)I
const #55 = Asciz	boxToInteger;
const #56 = Asciz	(I)Ljava/lang/Integer;;
const #57 = NameAndType	#55:#56;//  boxToInteger:(I)Ljava/lang/Integer;
const #58 = Method	#47.#57;	//  scala/runtime/BoxesRunTime.boxToInteger:(I)Ljava/lang/Integer;
const #59 = Asciz	this;
const #60 = Asciz	Lscala/collection/immutable/PagedSeq$$anonfun$fromReader$1;;
const #61 = Asciz	v1;
const #62 = Asciz	Ljava/lang/Object;;
const #63 = Asciz	v2;
const #64 = Asciz	v3;
const #65 = Asciz	LocalVariableTable;
const #66 = Asciz	java/io/Reader;
const #67 = class	#66;	//  java/io/Reader
const #68 = Asciz	read;
const #69 = NameAndType	#68:#52;//  read:([CII)I
const #70 = Method	#67.#69;	//  java/io/Reader.read:([CII)I
const #71 = Asciz	curry;
const #72 = Asciz	()Lscala/Function1;;
const #73 = Asciz	(Lscala/Function3;)Lscala/Function1;;
const #74 = NameAndType	#71:#73;//  curry:(Lscala/Function3;)Lscala/Function1;
const #75 = Method	#19.#74;	//  scala/Function3$class.curry:(Lscala/Function3;)Lscala/Function1;
const #76 = Asciz	toString;
const #77 = Asciz	()Ljava/lang/String;;
const #78 = Asciz	(Lscala/Function3;)Ljava/lang/String;;
const #79 = NameAndType	#76:#78;//  toString:(Lscala/Function3;)Ljava/lang/String;
const #80 = Method	#19.#79;	//  scala/Function3$class.toString:(Lscala/Function3;)Ljava/lang/String;
const #81 = Asciz	Scala;
const #82 = Asciz	InnerClasses;
const #83 = Asciz	scala/collection/immutable/PagedSeq;
const #84 = class	#83;	//  scala/collection/immutable/PagedSeq
const #85 = Asciz	$anonfun$fromReader$1;
const #86 = Asciz	scala/Function3;
const #87 = class	#86;	//  scala/Function3
const #88 = Asciz	scala/ScalaObject;
const #89 = class	#88;	//  scala/ScalaObject
const #90 = Asciz	java/io/Serializable;
const #91 = class	#90;	//  java/io/Serializable

{
public scala.collection.immutable.PagedSeq$$anonfun$fromReader$1(java.io.Reader);
  Code:
   Stack=2, Locals=2, Args_size=2
   0:	aload_0
   1:	aload_1
   2:	putfield	#12; //Field source$3:Ljava/io/Reader;
   5:	aload_0
   6:	invokespecial	#17; //Method java/lang/Object."<init>":()V
   9:	aload_0
   10:	invokestatic	#23; //Method scala/Function3$class.$init$:(Lscala/Function3;)V
   13:	return
  LineNumberTable: 
   line 84: 0


public final java.lang.Object apply(java.lang.Object, java.lang.Object, java.lang.Object);
  Code:
   Stack=4, Locals=4, Args_size=4
   0:	aload_0
   1:	aload_1
   2:	instanceof	#27; //class scala/runtime/BoxedArray
   5:	ifeq	24
   8:	getstatic	#33; //Field scala/runtime/ScalaRunTime$.MODULE$:Lscala/runtime/ScalaRunTime$;
   11:	aload_1
   12:	checkcast	#27; //class scala/runtime/BoxedArray
   15:	getstatic	#39; //Field java/lang/Character.TYPE:Ljava/lang/Class;
   18:	invokevirtual	#43; //Method scala/runtime/ScalaRunTime$.arrayValue:(Lscala/runtime/BoxedArray;Ljava/lang/Class;)Ljava/lang/Object;
   21:	goto	25
   24:	aload_1
   25:	checkcast	#45; //class "[C"
   28:	aload_2
   29:	invokestatic	#51; //Method scala/runtime/BoxesRunTime.unboxToInt:(Ljava/lang/Object;)I
   32:	aload_3
   33:	invokestatic	#51; //Method scala/runtime/BoxesRunTime.unboxToInt:(Ljava/lang/Object;)I
   36:	invokevirtual	#54; //Method apply:([CII)I
   39:	invokestatic	#58; //Method scala/runtime/BoxesRunTime.boxToInteger:(I)Ljava/lang/Integer;
   42:	areturn
  LineNumberTable: 
   line 84: 0

  LocalVariableTable: 
   Start  Length  Slot  Name   Signature
   0      43      0    this       Lscala/collection/immutable/PagedSeq$$anonfun$fromReader$1;
   0      43      1    v1       Ljava/lang/Object;
   0      43      2    v2       Ljava/lang/Object;
   0      43      3    v3       Ljava/lang/Object;


public final int apply(char[], int, int);
  Code:
   Stack=4, Locals=4, Args_size=4
   0:	aload_0
   1:	getfield	#12; //Field source$3:Ljava/io/Reader;
   4:	aload_1
   5:	iload_2
   6:	iload_3
   7:	invokevirtual	#70; //Method java/io/Reader.read:([CII)I
   10:	ireturn
  LineNumberTable: 
   line 84: 0


public scala.Function1 curry();
  Code:
   Stack=1, Locals=1, Args_size=1
   0:	aload_0
   1:	invokestatic	#75; //Method scala/Function3$class.curry:(Lscala/Function3;)Lscala/Function1;
   4:	areturn
  LineNumberTable: 
   line 84: 0


public java.lang.String toString();
  Code:
   Stack=1, Locals=1, Args_size=1
   0:	aload_0
   1:	invokestatic	#80; //Method scala/Function3$class.toString:(Lscala/Function3;)Ljava/lang/String;
   4:	areturn
  LineNumberTable: 
   line 84: 0


}

