Compiled from "Range.scala"
public final class scala.collection.immutable.Range$Double$$anonfun$inclusive$1 extends scala.runtime.AbstractFunction1 implements java.io.Serializable
  SourceFile: "Range.scala"
  Scala: length = 0x
   
  InnerClass: 
   public final #44= #9 of #43; //$anonfun$inclusive$1=class scala/collection/immutable/Range$Double$$anonfun$inclusive$1 of class scala/collection/immutable/Range$Double$
  minor version: 0
  major version: 49
  Constant pool:
const #1 = Asciz	SourceFile;
const #2 = Asciz	Range.scala;
const #3 = Asciz	<clinit>;
const #4 = Asciz	()V;
const #5 = Asciz	Code;
const #6 = Asciz	serialVersionUID;
const #7 = Asciz	J;
const #8 = Asciz	scala/collection/immutable/Range$Double$$anonfun$inclusive$1;
const #9 = class	#8;	//  scala/collection/immutable/Range$Double$$anonfun$inclusive$1
const #10 = NameAndType	#6:#7;//  serialVersionUID:J
const #11 = Field	#9.#10;	//  scala/collection/immutable/Range$Double$$anonfun$inclusive$1.serialVersionUID:J
const #12 = Asciz	<init>;
const #13 = Asciz	LineNumberTable;
const #14 = Asciz	scala/runtime/AbstractFunction1;
const #15 = class	#14;	//  scala/runtime/AbstractFunction1
const #16 = NameAndType	#12:#4;//  "<init>":()V
const #17 = Method	#15.#16;	//  scala/runtime/AbstractFunction1."<init>":()V
const #18 = Asciz	apply;
const #19 = Asciz	(Ljava/lang/Object;)Ljava/lang/Object;;
const #20 = Asciz	scala/math/BigDecimal;
const #21 = class	#20;	//  scala/math/BigDecimal
const #22 = Asciz	(Lscala/math/BigDecimal;)D;
const #23 = NameAndType	#18:#22;//  apply:(Lscala/math/BigDecimal;)D
const #24 = Method	#9.#23;	//  scala/collection/immutable/Range$Double$$anonfun$inclusive$1.apply:(Lscala/math/BigDecimal;)D
const #25 = Asciz	scala/runtime/BoxesRunTime;
const #26 = class	#25;	//  scala/runtime/BoxesRunTime
const #27 = Asciz	boxToDouble;
const #28 = Asciz	(D)Ljava/lang/Double;;
const #29 = NameAndType	#27:#28;//  boxToDouble:(D)Ljava/lang/Double;
const #30 = Method	#26.#29;	//  scala/runtime/BoxesRunTime.boxToDouble:(D)Ljava/lang/Double;
const #31 = Asciz	this;
const #32 = Asciz	Lscala/collection/immutable/Range$Double$$anonfun$inclusive$1;;
const #33 = Asciz	v1;
const #34 = Asciz	Ljava/lang/Object;;
const #35 = Asciz	LocalVariableTable;
const #36 = Asciz	doubleValue;
const #37 = Asciz	()D;
const #38 = NameAndType	#36:#37;//  doubleValue:()D
const #39 = Method	#21.#38;	//  scala/math/BigDecimal.doubleValue:()D
const #40 = Asciz	Scala;
const #41 = Asciz	InnerClasses;
const #42 = Asciz	scala/collection/immutable/Range$Double$;
const #43 = class	#42;	//  scala/collection/immutable/Range$Double$
const #44 = Asciz	$anonfun$inclusive$1;
const #45 = Asciz	java/io/Serializable;
const #46 = class	#45;	//  java/io/Serializable

{
public static final long serialVersionUID;

public static {};
  Code:
   Stack=2, Locals=0, Args_size=0
   0:	lconst_0
   1:	putstatic	#11; //Field serialVersionUID:J
   4:	return

public scala.collection.immutable.Range$Double$$anonfun$inclusive$1();
  Code:
   Stack=1, Locals=1, Args_size=1
   0:	aload_0
   1:	invokespecial	#17; //Method scala/runtime/AbstractFunction1."<init>":()V
   4:	return
  LineNumberTable: 
   line 217: 0


public final java.lang.Object apply(java.lang.Object);
  Code:
   Stack=2, Locals=4, Args_size=2
   0:	aload_0
   1:	aload_1
   2:	checkcast	#21; //class scala/math/BigDecimal
   5:	invokevirtual	#24; //Method apply:(Lscala/math/BigDecimal;)D
   8:	dstore_2
   9:	dload_2
   10:	invokestatic	#30; //Method scala/runtime/BoxesRunTime.boxToDouble:(D)Ljava/lang/Double;
   13:	areturn
  LineNumberTable: 
   line 217: 0

  LocalVariableTable: 
   Start  Length  Slot  Name   Signature
   0      14      0    this       Lscala/collection/immutable/Range$Double$$anonfun$inclusive$1;
   0      14      1    v1       Ljava/lang/Object;


public final double apply(scala.math.BigDecimal);
  Code:
   Stack=2, Locals=2, Args_size=2
   0:	aload_1
   1:	invokevirtual	#39; //Method scala/math/BigDecimal.doubleValue:()D
   4:	dreturn
  LineNumberTable: 
   line 217: 0


}

