Compiled from "Range.scala"
public class scala.collection.immutable.Range$Inclusive extends scala.collection.immutable.Range implements scala.ScalaObject
  SourceFile: "Range.scala"
  Scala: length = 0x
   
  InnerClass: 
   public Inclusive=class scala/collection/immutable/Range$Inclusive of class scala/collection/immutable/Range
  minor version: 0
  major version: 49
  Constant pool:
Asciz	SourceFile;
Asciz	Range.scala;
Asciz	isInclusive;
Asciz	()Z;
Asciz	Code;
Asciz	LineNumberTable;
Asciz	copy;
Asciz	(III)Lscala/collection/immutable/Range;;
Asciz	scala/collection/immutable/Range$Inclusive;
class	scala/collection/immutable/Range$Inclusive
Asciz	<init>;
Asciz	(III)V;
NameAndType	"<init>":(III)V
Method	scala/collection/immutable/Range$Inclusive."<init>":(III)V
Asciz	this;
Asciz	Lscala/collection/immutable/Range$Inclusive;;
Asciz	start;
Asciz	I;
Asciz	end;
Asciz	step;
Asciz	LocalVariableTable;
Asciz	last;
Asciz	()I;
Asciz	scala/collection/immutable/Range;
class	scala/collection/immutable/Range
NameAndType	step:()I
Method	scala/collection/immutable/Range.step:()I
NameAndType	end:()I
Method	scala/collection/immutable/Range.end:()I
NameAndType	start:()I
Method	scala/collection/immutable/Range.start:()I
Asciz	fullLength;
Asciz	()J;
NameAndType	last:()I
Method	scala/collection/immutable/Range$Inclusive.last:()I
Asciz	()Ljava/lang/Object;;
Asciz	scala/runtime/BoxesRunTime;
class	scala/runtime/BoxesRunTime
Asciz	boxToInteger;
Asciz	(I)Ljava/lang/Integer;;
NameAndType	boxToInteger:(I)Ljava/lang/Integer;
Method	scala/runtime/BoxesRunTime.boxToInteger:(I)Ljava/lang/Integer;
Method	scala/collection/immutable/Range."<init>":(III)V
Asciz	Scala;
Asciz	InnerClasses;
Asciz	Inclusive;
Asciz	scala/ScalaObject;
class	scala/ScalaObject

{
public boolean isInclusive();
  Signature: ()Z
  Code:
   Stack=1, Locals=1, Args_size=1
	iconst_1
	ireturn
  Labels:

public scala.collection.immutable.Range copy(int, int, int);
  Signature: (III)Lscala/collection/immutable/Range;
  Code:
   Stack=5, Locals=4, Args_size=4
	new	class scala/collection/immutable/Range$Inclusive
	dup
	iload_1
	iload_2
	iload_3
	invokespecial	Method "<init>":(III)V
	areturn
  Labels:
  LocalVariableTable: 
   Start  Length  Slot  Name   Signature
   0      11      0    this       Lscala/collection/immutable/Range$Inclusive;
   0      11      1    start       I
   0      11      2    end       I
   0      11      3    step       I


public int last();
  Signature: ()I
  Code:
   Stack=4, Locals=1, Args_size=1
	aload_0
	invokespecial	Method scala/collection/immutable/Range.step:()I
	iconst_1
	if_icmpeq	l1 // aload_0
	aload_0
	invokespecial	Method scala/collection/immutable/Range.step:()I
	iconst_m1
	if_icmpne	l2 // aload_0
l1	aload_0
	invokespecial	Method scala/collection/immutable/Range.end:()I
	goto	l3 // ireturn
l2	aload_0
	invokespecial	Method scala/collection/immutable/Range.end:()I
	i2l
	aload_0
	invokespecial	Method scala/collection/immutable/Range.start:()I
	i2l
	lsub
	aload_0
	invokespecial	Method scala/collection/immutable/Range.step:()I
	i2l
	ldiv
	aload_0
	invokespecial	Method scala/collection/immutable/Range.step:()I
	i2l
	lmul
	aload_0
	invokespecial	Method scala/collection/immutable/Range.start:()I
	i2l
	ladd
	l2i
l3	ireturn
  Labels:
   	l1 = 16 // aload_0
   	l2 = 23 // aload_0
   	l3 = 53 // ireturn

public long fullLength();
  Signature: ()J
  Code:
   Stack=4, Locals=1, Args_size=1
	aload_0
	invokespecial	Method scala/collection/immutable/Range.end:()I
	aload_0
	invokespecial	Method scala/collection/immutable/Range.start:()I
	if_icmple	l1 // iconst_0
	iconst_1
	goto	l2 // aload_0
l1	iconst_0
l2	aload_0
	invokespecial	Method scala/collection/immutable/Range.step:()I
	iconst_0
	if_icmple	l3 // iconst_0
	iconst_1
	goto	l4 // if_icmpeq
l3	iconst_0
l4	if_icmpeq	l5 // aload_0
	aload_0
	invokespecial	Method scala/collection/immutable/Range.start:()I
	aload_0
	invokespecial	Method scala/collection/immutable/Range.end:()I
	if_icmpne	l6 // lconst_0
l5	aload_0
	invokevirtual	Method last:()I
	i2l
	aload_0
	invokespecial	Method scala/collection/immutable/Range.start:()I
	i2l
	lsub
	aload_0
	invokespecial	Method scala/collection/immutable/Range.step:()I
	i2l
	ldiv
	lconst_1
	ladd
	goto	l7 // lreturn
l6	lconst_0
l7	lreturn
  Labels:
   	l1 = 15 // iconst_0
   	l2 = 16 // aload_0
   	l3 = 28 // iconst_0
   	l4 = 29 // if_icmpeq
   	l5 = 43 // aload_0
   	l6 = 65 // lconst_0
   	l7 = 66 // lreturn

public java.lang.Object last();
  Signature: ()Ljava/lang/Object;
  Code:
   Stack=1, Locals=2, Args_size=1
	aload_0
	invokevirtual	Method last:()I
	istore_1
	iload_1
	invokestatic	Method scala/runtime/BoxesRunTime.boxToInteger:(I)Ljava/lang/Integer;
	areturn
  Labels:

public scala.collection.immutable.Range$Inclusive(int, int, int);
  Signature: (III)V
  Code:
   Stack=4, Locals=4, Args_size=4
	aload_0
	iload_1
	iload_2
	iload_3
	invokespecial	Method scala/collection/immutable/Range."<init>":(III)V
	return
  Labels:
  LocalVariableTable: 
   Start  Length  Slot  Name   Signature
   0      8      0    this       Lscala/collection/immutable/Range$Inclusive;
   0      8      1    start       I
   0      8      2    end       I
   0      8      3    step       I


}

