Compiled from "Range.scala"
public final class scala.collection.immutable.Range$$anon$2 extends scala.collection.immutable.Range implements scala.collection.immutable.Range$ByOne
  SourceFile: "Range.scala"
  Scala: length = 0x
   
  InnerClass: 
   public abstract ByOne=class scala/collection/immutable/Range$ByOne of class scala/collection/immutable/Range
   public final $anon$2=class scala/collection/immutable/Range$$anon$2 of class scala/collection/immutable/Range
  minor version: 0
  major version: 49
  Constant pool:
Asciz	SourceFile;
Asciz	Range.scala;
Asciz	foreach;
Asciz	(Lscala/Function1;)V;
Asciz	Code;
Asciz	LineNumberTable;
Asciz	scala/collection/immutable/Range$ByOne$class;
class	scala/collection/immutable/Range$ByOne$class
Asciz	(Lscala/collection/immutable/Range$ByOne;Lscala/Function1;)V;
NameAndType	foreach:(Lscala/collection/immutable/Range$ByOne;Lscala/Function1;)V
Method	scala/collection/immutable/Range$ByOne$class.foreach:(Lscala/collection/immutable/Range$ByOne;Lscala/Function1;)V
Asciz	this;
Asciz	Lscala/collection/immutable/Range$$anon$2;;
Asciz	f;
Asciz	Lscala/Function1;;
Asciz	LocalVariableTable;
Asciz	foreach$mVc$sp;
NameAndType	foreach$mVc$sp:(Lscala/collection/immutable/Range$ByOne;Lscala/Function1;)V
Method	scala/collection/immutable/Range$ByOne$class.foreach$mVc$sp:(Lscala/collection/immutable/Range$ByOne;Lscala/Function1;)V
Asciz	<init>;
Asciz	(II)V;
Asciz	scala/collection/immutable/Range;
class	scala/collection/immutable/Range
Asciz	(III)V;
NameAndType	"<init>":(III)V
Method	scala/collection/immutable/Range."<init>":(III)V
Asciz	$init$;
Asciz	(Lscala/collection/immutable/Range$ByOne;)V;
NameAndType	$init$:(Lscala/collection/immutable/Range$ByOne;)V
Method	scala/collection/immutable/Range$ByOne$class.$init$:(Lscala/collection/immutable/Range$ByOne;)V
Asciz	Scala;
Asciz	InnerClasses;
Asciz	scala/collection/immutable/Range$ByOne;
class	scala/collection/immutable/Range$ByOne
Asciz	ByOne;
Asciz	scala/collection/immutable/Range$$anon$2;
class	scala/collection/immutable/Range$$anon$2
Asciz	$anon$2;

{
public final void foreach(scala.Function1);
  Signature: (Lscala/Function1;)V
  Code:
   Stack=2, Locals=2, Args_size=2
	aload_0
	aload_1
	invokestatic	Method scala/collection/immutable/Range$ByOne$class.foreach:(Lscala/collection/immutable/Range$ByOne;Lscala/Function1;)V
	return
  Labels:
  LocalVariableTable: 
   Start  Length  Slot  Name   Signature
   0      6      0    this       Lscala/collection/immutable/Range$$anon$2;
   0      6      1    f       Lscala/Function1;


public final void foreach$mVc$sp(scala.Function1);
  Signature: (Lscala/Function1;)V
  Code:
   Stack=2, Locals=2, Args_size=2
	aload_0
	aload_1
	invokestatic	Method scala/collection/immutable/Range$ByOne$class.foreach$mVc$sp:(Lscala/collection/immutable/Range$ByOne;Lscala/Function1;)V
	return
  Labels:
  LocalVariableTable: 
   Start  Length  Slot  Name   Signature
   0      6      0    this       Lscala/collection/immutable/Range$$anon$2;
   0      6      1    f       Lscala/Function1;


public scala.collection.immutable.Range$$anon$2(int, int);
  Signature: (II)V
  Code:
   Stack=4, Locals=3, Args_size=3
	aload_0
	iload_1
	iload_2
	iconst_1
	invokespecial	Method scala/collection/immutable/Range."<init>":(III)V
	aload_0
	invokestatic	Method scala/collection/immutable/Range$ByOne$class.$init$:(Lscala/collection/immutable/Range$ByOne;)V
	return
  Labels:

}

