Compiled from "Range.scala"
public final class scala.collection.immutable.Range$BigDecimal$ extends java.lang.Object implements scala.ScalaObject
  SourceFile: "Range.scala"
  Scala: length = 0x
   
  InnerClass: 
   public #60= #57 of #59; //Exclusive=class scala/collection/immutable/NumericRange$Exclusive of class scala/collection/immutable/NumericRange
   public #63= #62 of #59; //Inclusive=class scala/collection/immutable/NumericRange$Inclusive of class scala/collection/immutable/NumericRange
  minor version: 0
  major version: 49
  Constant pool:
const #1 = Asciz	SourceFile;
const #2 = Asciz	Range.scala;
const #3 = Asciz	Scala;
const #4 = Asciz	MODULE$;
const #5 = Asciz	Lscala/collection/immutable/Range$BigDecimal$;;
const #6 = Asciz	<clinit>;
const #7 = Asciz	()V;
const #8 = Asciz	Code;
const #9 = Asciz	scala/collection/immutable/Range$BigDecimal$;
const #10 = class	#9;	//  scala/collection/immutable/Range$BigDecimal$
const #11 = Asciz	<init>;
const #12 = NameAndType	#11:#7;//  "<init>":()V
const #13 = Method	#10.#12;	//  scala/collection/immutable/Range$BigDecimal$."<init>":()V
const #14 = Asciz	bigDecAsIntegral;
const #15 = Asciz	Lscala/math/Numeric$BigDecimalAsIfIntegral$;;
const #16 = Asciz	LineNumberTable;
const #17 = Asciz	java/lang/Object;
const #18 = class	#17;	//  java/lang/Object
const #19 = Method	#18.#12;	//  java/lang/Object."<init>":()V
const #20 = NameAndType	#4:#5;//  MODULE$:Lscala/collection/immutable/Range$BigDecimal$;
const #21 = Field	#10.#20;	//  scala/collection/immutable/Range$BigDecimal$.MODULE$:Lscala/collection/immutable/Range$BigDecimal$;
const #22 = Asciz	scala/math/Numeric$BigDecimalAsIfIntegral$;
const #23 = class	#22;	//  scala/math/Numeric$BigDecimalAsIfIntegral$
const #24 = NameAndType	#4:#15;//  MODULE$:Lscala/math/Numeric$BigDecimalAsIfIntegral$;
const #25 = Field	#23.#24;	//  scala/math/Numeric$BigDecimalAsIfIntegral$.MODULE$:Lscala/math/Numeric$BigDecimalAsIfIntegral$;
const #26 = NameAndType	#14:#15;//  bigDecAsIntegral:Lscala/math/Numeric$BigDecimalAsIfIntegral$;
const #27 = Field	#10.#26;	//  scala/collection/immutable/Range$BigDecimal$.bigDecAsIntegral:Lscala/math/Numeric$BigDecimalAsIfIntegral$;
const #28 = Asciz	inclusive;
const #29 = Asciz	(Lscala/math/BigDecimal;Lscala/math/BigDecimal;Lscala/math/BigDecimal;)Lscala/collection/immutable/NumericRange$Inclusive;;
const #30 = Asciz	scala/collection/immutable/NumericRange$;
const #31 = class	#30;	//  scala/collection/immutable/NumericRange$
const #32 = Asciz	Lscala/collection/immutable/NumericRange$;;
const #33 = NameAndType	#4:#32;//  MODULE$:Lscala/collection/immutable/NumericRange$;
const #34 = Field	#31.#33;	//  scala/collection/immutable/NumericRange$.MODULE$:Lscala/collection/immutable/NumericRange$;
const #35 = Asciz	()Lscala/math/Numeric$BigDecimalAsIfIntegral$;;
const #36 = NameAndType	#14:#35;//  bigDecAsIntegral:()Lscala/math/Numeric$BigDecimalAsIfIntegral$;
const #37 = Method	#10.#36;	//  scala/collection/immutable/Range$BigDecimal$.bigDecAsIntegral:()Lscala/math/Numeric$BigDecimalAsIfIntegral$;
const #38 = Asciz	(Ljava/lang/Object;Ljava/lang/Object;Ljava/lang/Object;Lscala/math/Integral;)Lscala/collection/immutable/NumericRange$Inclusive;;
const #39 = NameAndType	#28:#38;//  inclusive:(Ljava/lang/Object;Ljava/lang/Object;Ljava/lang/Object;Lscala/math/Integral;)Lscala/collection/immutable/NumericRange$Inclusive;
const #40 = Method	#31.#39;	//  scala/collection/immutable/NumericRange$.inclusive:(Ljava/lang/Object;Ljava/lang/Object;Ljava/lang/Object;Lscala/math/Integral;)Lscala/collection/immutable/NumericRange$Inclusive;
const #41 = Asciz	this;
const #42 = Asciz	start;
const #43 = Asciz	Lscala/math/BigDecimal;;
const #44 = Asciz	end;
const #45 = Asciz	step;
const #46 = Asciz	LocalVariableTable;
const #47 = Asciz	(Lscala/math/BigDecimal;Lscala/math/BigDecimal;Lscala/math/BigDecimal;)Lscala/collection/immutable/NumericRange$Inclusive<Lscala/math/BigDecimal;>;;
const #48 = Asciz	Signature;
const #49 = Asciz	apply;
const #50 = Asciz	(Lscala/math/BigDecimal;Lscala/math/BigDecimal;Lscala/math/BigDecimal;)Lscala/collection/immutable/NumericRange$Exclusive;;
const #51 = Asciz	(Ljava/lang/Object;Ljava/lang/Object;Ljava/lang/Object;Lscala/math/Integral;)Lscala/collection/immutable/NumericRange$Exclusive;;
const #52 = NameAndType	#49:#51;//  apply:(Ljava/lang/Object;Ljava/lang/Object;Ljava/lang/Object;Lscala/math/Integral;)Lscala/collection/immutable/NumericRange$Exclusive;
const #53 = Method	#31.#52;	//  scala/collection/immutable/NumericRange$.apply:(Ljava/lang/Object;Ljava/lang/Object;Ljava/lang/Object;Lscala/math/Integral;)Lscala/collection/immutable/NumericRange$Exclusive;
const #54 = Asciz	(Lscala/math/BigDecimal;Lscala/math/BigDecimal;Lscala/math/BigDecimal;)Lscala/collection/immutable/NumericRange$Exclusive<Lscala/math/BigDecimal;>;;
const #55 = Asciz	InnerClasses;
const #56 = Asciz	scala/collection/immutable/NumericRange$Exclusive;
const #57 = class	#56;	//  scala/collection/immutable/NumericRange$Exclusive
const #58 = Asciz	scala/collection/immutable/NumericRange;
const #59 = class	#58;	//  scala/collection/immutable/NumericRange
const #60 = Asciz	Exclusive;
const #61 = Asciz	scala/collection/immutable/NumericRange$Inclusive;
const #62 = class	#61;	//  scala/collection/immutable/NumericRange$Inclusive
const #63 = Asciz	Inclusive;
const #64 = Asciz	scala/ScalaObject;
const #65 = class	#64;	//  scala/ScalaObject

{
public static final scala.collection.immutable.Range$BigDecimal$ MODULE$;

public static {};
  Code:
   Stack=1, Locals=0, Args_size=0
   0:	new	#10; //class scala/collection/immutable/Range$BigDecimal$
   3:	invokespecial	#13; //Method "<init>":()V
   6:	return

public scala.collection.immutable.Range$BigDecimal$();
  Code:
   Stack=2, Locals=1, Args_size=1
   0:	aload_0
   1:	invokespecial	#19; //Method java/lang/Object."<init>":()V
   4:	aload_0
   5:	putstatic	#21; //Field MODULE$:Lscala/collection/immutable/Range$BigDecimal$;
   8:	aload_0
   9:	getstatic	#25; //Field scala/math/Numeric$BigDecimalAsIfIntegral$.MODULE$:Lscala/math/Numeric$BigDecimalAsIfIntegral$;
   12:	putfield	#27; //Field bigDecAsIntegral:Lscala/math/Numeric$BigDecimalAsIfIntegral$;
   15:	return
  LineNumberTable: 
   line 193: 0
   line 194: 8


public scala.collection.immutable.NumericRange$Inclusive inclusive(scala.math.BigDecimal, scala.math.BigDecimal, scala.math.BigDecimal);
  Code:
   Stack=5, Locals=4, Args_size=4
   0:	getstatic	#34; //Field scala/collection/immutable/NumericRange$.MODULE$:Lscala/collection/immutable/NumericRange$;
   3:	aload_1
   4:	aload_2
   5:	aload_3
   6:	aload_0
   7:	invokevirtual	#37; //Method bigDecAsIntegral:()Lscala/math/Numeric$BigDecimalAsIfIntegral$;
   10:	invokevirtual	#40; //Method scala/collection/immutable/NumericRange$.inclusive:(Ljava/lang/Object;Ljava/lang/Object;Ljava/lang/Object;Lscala/math/Integral;)Lscala/collection/immutable/NumericRange$Inclusive;
   13:	areturn
  LineNumberTable: 
   line 199: 0

  LocalVariableTable: 
   Start  Length  Slot  Name   Signature
   0      14      0    this       Lscala/collection/immutable/Range$BigDecimal$;
   0      14      1    start       Lscala/math/BigDecimal;
   0      14      2    end       Lscala/math/BigDecimal;
   0      14      3    step       Lscala/math/BigDecimal;

  Signature: length = 0x2
   00 2F 

public scala.collection.immutable.NumericRange$Exclusive apply(scala.math.BigDecimal, scala.math.BigDecimal, scala.math.BigDecimal);
  Code:
   Stack=5, Locals=4, Args_size=4
   0:	getstatic	#34; //Field scala/collection/immutable/NumericRange$.MODULE$:Lscala/collection/immutable/NumericRange$;
   3:	aload_1
   4:	aload_2
   5:	aload_3
   6:	aload_0
   7:	invokevirtual	#37; //Method bigDecAsIntegral:()Lscala/math/Numeric$BigDecimalAsIfIntegral$;
   10:	invokevirtual	#53; //Method scala/collection/immutable/NumericRange$.apply:(Ljava/lang/Object;Ljava/lang/Object;Ljava/lang/Object;Lscala/math/Integral;)Lscala/collection/immutable/NumericRange$Exclusive;
   13:	areturn
  LineNumberTable: 
   line 197: 0

  LocalVariableTable: 
   Start  Length  Slot  Name   Signature
   0      14      0    this       Lscala/collection/immutable/Range$BigDecimal$;
   0      14      1    start       Lscala/math/BigDecimal;
   0      14      2    end       Lscala/math/BigDecimal;
   0      14      3    step       Lscala/math/BigDecimal;

  Signature: length = 0x2
   00 36 

public scala.math.Numeric$BigDecimalAsIfIntegral$ bigDecAsIntegral();
  Code:
   Stack=1, Locals=1, Args_size=1
   0:	aload_0
   1:	getfield	#27; //Field bigDecAsIntegral:Lscala/math/Numeric$BigDecimalAsIfIntegral$;
   4:	areturn
  LineNumberTable: 
   line 194: 0


}

