Compiled from "Range.scala"
public abstract class scala.collection.immutable.Range$ByOne$class extends java.lang.Object
  SourceFile: "Range.scala"
  Scala: length = 0x
   
  InnerClass: 
   public abstract #42= #41 of #13; //ByOne=class scala/collection/immutable/Range$ByOne of class scala/collection/immutable/Range
  minor version: 0
  major version: 49
  Constant pool:
const #1 = Asciz	SourceFile;
const #2 = Asciz	Range.scala;
const #3 = Asciz	$init$;
const #4 = Asciz	(Lscala/collection/immutable/Range$ByOne;)V;
const #5 = Asciz	Code;
const #6 = Asciz	LineNumberTable;
const #7 = Asciz	$this;
const #8 = Asciz	Lscala/collection/immutable/Range$ByOne;;
const #9 = Asciz	LocalVariableTable;
const #10 = Asciz	foreach;
const #11 = Asciz	(Lscala/collection/immutable/Range$ByOne;Lscala/Function1;)V;
const #12 = Asciz	scala/collection/immutable/Range;
const #13 = class	#12;	//  scala/collection/immutable/Range
const #14 = Asciz	start;
const #15 = Asciz	()I;
const #16 = NameAndType	#14:#15;//  start:()I
const #17 = Method	#13.#16;	//  scala/collection/immutable/Range.start:()I
const #18 = Asciz	limit;
const #19 = NameAndType	#18:#15;//  limit:()I
const #20 = Method	#13.#19;	//  scala/collection/immutable/Range.limit:()I
const #21 = Asciz	scala/runtime/BoxesRunTime;
const #22 = class	#21;	//  scala/runtime/BoxesRunTime
const #23 = Asciz	boxToInteger;
const #24 = Asciz	(I)Ljava/lang/Integer;;
const #25 = NameAndType	#23:#24;//  boxToInteger:(I)Ljava/lang/Integer;
const #26 = Method	#22.#25;	//  scala/runtime/BoxesRunTime.boxToInteger:(I)Ljava/lang/Integer;
const #27 = Asciz	scala/Function1;
const #28 = class	#27;	//  scala/Function1
const #29 = Asciz	apply;
const #30 = Asciz	(Ljava/lang/Object;)Ljava/lang/Object;;
const #31 = NameAndType	#29:#30;//  apply:(Ljava/lang/Object;)Ljava/lang/Object;
const #32 = InterfaceMethod	#28.#31;	//  scala/Function1.apply:(Ljava/lang/Object;)Ljava/lang/Object;
const #33 = Asciz	f;
const #34 = Asciz	Lscala/Function1;;
const #35 = Asciz	l;
const #36 = Asciz	I;
const #37 = Asciz	i;
const #38 = Asciz	Scala;
const #39 = Asciz	InnerClasses;
const #40 = Asciz	scala/collection/immutable/Range$ByOne;
const #41 = class	#40;	//  scala/collection/immutable/Range$ByOne
const #42 = Asciz	ByOne;
const #43 = Asciz	scala/collection/immutable/Range$ByOne$class;
const #44 = class	#43;	//  scala/collection/immutable/Range$ByOne$class
const #45 = Asciz	java/lang/Object;
const #46 = class	#45;	//  java/lang/Object

{
public static void $init$(scala.collection.immutable.Range$ByOne);
  Code:
   Stack=0, Locals=1, Args_size=1
   0:	return
  LineNumberTable: 
   line 166: 0

  LocalVariableTable: 
   Start  Length  Slot  Name   Signature
   0      1      0    $this       Lscala/collection/immutable/Range$ByOne;


public static final void foreach(scala.collection.immutable.Range$ByOne, scala.Function1);
  Code:
   Stack=2, Locals=4, Args_size=2
   0:	aload_0
   1:	checkcast	#13; //class scala/collection/immutable/Range
   4:	invokevirtual	#17; //Method scala/collection/immutable/Range.start:()I
   7:	istore_3
   8:	aload_0
   9:	checkcast	#13; //class scala/collection/immutable/Range
   12:	invokevirtual	#20; //Method scala/collection/immutable/Range.limit:()I
   15:	istore_2
   16:	iload_3
   17:	iload_2
   18:	if_icmpge	39
   21:	aload_1
   22:	iload_3
   23:	invokestatic	#26; //Method scala/runtime/BoxesRunTime.boxToInteger:(I)Ljava/lang/Integer;
   26:	invokeinterface	#32,  2; //InterfaceMethod scala/Function1.apply:(Ljava/lang/Object;)Ljava/lang/Object;
   31:	pop
   32:	iload_3
   33:	iconst_1
   34:	iadd
   35:	istore_3
   36:	goto	16
   39:	return
  LineNumberTable: 
   line 168: 0
   line 169: 8
   line 170: 16
   line 171: 21
   line 172: 32
   line 167: 39

  LocalVariableTable: 
   Start  Length  Slot  Name   Signature
   0      40      0    $this       Lscala/collection/immutable/Range$ByOne;
   0      40      1    f       Lscala/Function1;
   16      24      2    l       I
   8      32      3    i       I


}

