Compiled from "Range.scala"
public abstract class scala.collection.immutable.Range$ByOne$class extends java.lang.Object
  SourceFile: "Range.scala"
  Scala: length = 0x
   
  InnerClass: 
   public abstract ByOne=class scala/collection/immutable/Range$ByOne of class scala/collection/immutable/Range
  minor version: 0
  major version: 49
  Constant pool:
Asciz	SourceFile;
Asciz	Range.scala;
Asciz	foreach;
Asciz	(Lscala/collection/immutable/Range$ByOne;Lscala/Function1;)V;
Asciz	Code;
Asciz	LineNumberTable;
Asciz	scala/collection/immutable/Range;
class	scala/collection/immutable/Range
Asciz	length;
Asciz	()I;
NameAndType	length:()I
Method	scala/collection/immutable/Range.length:()I
Asciz	last;
NameAndType	last:()I
Method	scala/collection/immutable/Range.last:()I
Asciz	start;
NameAndType	start:()I
Method	scala/collection/immutable/Range.start:()I
Asciz	scala/runtime/BoxesRunTime;
class	scala/runtime/BoxesRunTime
Asciz	boxToInteger;
Asciz	(I)Ljava/lang/Integer;;
NameAndType	boxToInteger:(I)Ljava/lang/Integer;
Method	scala/runtime/BoxesRunTime.boxToInteger:(I)Ljava/lang/Integer;
Asciz	scala/Function1;
class	scala/Function1
Asciz	apply;
Asciz	(Ljava/lang/Object;)Ljava/lang/Object;;
NameAndType	apply:(Ljava/lang/Object;)Ljava/lang/Object;
InterfaceMethod	scala/Function1.apply:(Ljava/lang/Object;)Ljava/lang/Object;
Asciz	$this;
Asciz	Lscala/collection/immutable/Range$ByOne;;
Asciz	f;
Asciz	Lscala/Function1;;
Asciz	I;
Asciz	i;
Asciz	LocalVariableTable;
Asciz	foreach$mVc$sp;
Asciz	apply$mcVI$sp;
Asciz	(I)V;
NameAndType	apply$mcVI$sp:(I)V
InterfaceMethod	scala/Function1.apply$mcVI$sp:(I)V
Asciz	$init$;
Asciz	(Lscala/collection/immutable/Range$ByOne;)V;
Asciz	Scala;
Asciz	InnerClasses;
Asciz	scala/collection/immutable/Range$ByOne;
class	scala/collection/immutable/Range$ByOne
Asciz	ByOne;
Asciz	scala/collection/immutable/Range$ByOne$class;
class	scala/collection/immutable/Range$ByOne$class
Asciz	java/lang/Object;
class	java/lang/Object

{
public static final void foreach(scala.collection.immutable.Range$ByOne, scala.Function1);
  Signature: (Lscala/collection/immutable/Range$ByOne;Lscala/Function1;)V
  Code:
   Stack=2, Locals=4, Args_size=2
	aload_0
	checkcast	class scala/collection/immutable/Range
	invokevirtual	Method scala/collection/immutable/Range.length:()I
	iconst_0
	if_icmple	l1 // return
	aload_0
	checkcast	class scala/collection/immutable/Range
	invokevirtual	Method scala/collection/immutable/Range.last:()I
	istore_2
	aload_0
	checkcast	class scala/collection/immutable/Range
	invokevirtual	Method scala/collection/immutable/Range.start:()I
	istore_3
l3	iload_3
	iload_2
	if_icmpeq	l2 // aload_1
	aload_1
	iload_3
	invokestatic	Method scala/runtime/BoxesRunTime.boxToInteger:(I)Ljava/lang/Integer;
	invokeinterface	InterfaceMethod scala/Function1.apply:(Ljava/lang/Object;)Ljava/lang/Object;
	pop
	iload_3
	iconst_1
	iadd
	istore_3
	goto	l3 // iload_3
l2	aload_1
	iload_3
	invokestatic	Method scala/runtime/BoxesRunTime.boxToInteger:(I)Ljava/lang/Integer;
	invokeinterface	InterfaceMethod scala/Function1.apply:(Ljava/lang/Object;)Ljava/lang/Object;
	pop
l1	return
  Labels:
   	l3 = 27 // iload_3
   	l2 = 50 // aload_1
   	l1 = 61 // return
  LocalVariableTable: 
   Start  Length  Slot  Name   Signature
   0      62      0    $this       Lscala/collection/immutable/Range$ByOne;
   0      62      1    f       Lscala/Function1;
   19      42      2    last       I
   27      34      3    i       I


public static final void foreach$mVc$sp(scala.collection.immutable.Range$ByOne, scala.Function1);
  Signature: (Lscala/collection/immutable/Range$ByOne;Lscala/Function1;)V
  Code:
   Stack=2, Locals=4, Args_size=2
	aload_0
	checkcast	class scala/collection/immutable/Range
	invokevirtual	Method scala/collection/immutable/Range.length:()I
	iconst_0
	if_icmple	l1 // return
	aload_0
	checkcast	class scala/collection/immutable/Range
	invokevirtual	Method scala/collection/immutable/Range.last:()I
	istore_2
	aload_0
	checkcast	class scala/collection/immutable/Range
	invokevirtual	Method scala/collection/immutable/Range.start:()I
	istore_3
l3	iload_3
	iload_2
	if_icmpeq	l2 // aload_1
	aload_1
	iload_3
	invokeinterface	InterfaceMethod scala/Function1.apply$mcVI$sp:(I)V
	iload_3
	iconst_1
	iadd
	istore_3
	goto	l3 // iload_3
l2	aload_1
	iload_3
	invokeinterface	InterfaceMethod scala/Function1.apply$mcVI$sp:(I)V
l1	return
  Labels:
   	l3 = 27 // iload_3
   	l2 = 46 // aload_1
   	l1 = 53 // return
  LocalVariableTable: 
   Start  Length  Slot  Name   Signature
   0      54      0    $this       Lscala/collection/immutable/Range$ByOne;
   0      54      1    f       Lscala/Function1;
   19      34      2    last       I
   27      26      3    i       I


public static void $init$(scala.collection.immutable.Range$ByOne);
  Signature: (Lscala/collection/immutable/Range$ByOne;)V
  Code:
   Stack=0, Locals=1, Args_size=1
	return
  Labels:
  LocalVariableTable: 
   Start  Length  Slot  Name   Signature
   0      1      0    $this       Lscala/collection/immutable/Range$ByOne;


}

