Compiled from "RedBlack.scala"
public final class scala.collection.immutable.RedBlack$BlackTree$ extends java.lang.Object implements scala.ScalaObject
  SourceFile: "RedBlack.scala"
  Scala: length = 0x
   
  InnerClass: 
   public abstract #69= #66 of #68; //Tree=class scala/collection/immutable/RedBlack$Tree of class scala/collection/immutable/RedBlack
   public #70= #30 of #68; //BlackTree=class scala/collection/immutable/RedBlack$BlackTree of class scala/collection/immutable/RedBlack
  minor version: 0
  major version: 49
  Constant pool:
const #1 = Asciz	SourceFile;
const #2 = Asciz	RedBlack.scala;
const #3 = Asciz	Scala;
const #4 = Asciz	$outer;
const #5 = Asciz	Lscala/collection/immutable/RedBlack;;
const #6 = Asciz	<init>;
const #7 = Asciz	(Lscala/collection/immutable/RedBlack;)V;
const #8 = Asciz	Code;
const #9 = Asciz	LineNumberTable;
const #10 = Asciz	java/lang/NullPointerException;
const #11 = class	#10;	//  java/lang/NullPointerException
const #12 = Asciz	()V;
const #13 = NameAndType	#6:#12;//  "<init>":()V
const #14 = Method	#11.#13;	//  java/lang/NullPointerException."<init>":()V
const #15 = Asciz	scala/collection/immutable/RedBlack$BlackTree$;
const #16 = class	#15;	//  scala/collection/immutable/RedBlack$BlackTree$
const #17 = NameAndType	#4:#5;//  $outer:Lscala/collection/immutable/RedBlack;
const #18 = Field	#16.#17;	//  scala/collection/immutable/RedBlack$BlackTree$.$outer:Lscala/collection/immutable/RedBlack;
const #19 = Asciz	java/lang/Object;
const #20 = class	#19;	//  java/lang/Object
const #21 = Method	#20.#13;	//  java/lang/Object."<init>":()V
const #22 = Asciz	this;
const #23 = Asciz	Lscala/collection/immutable/RedBlack$BlackTree$;;
const #24 = Asciz	LocalVariableTable;
const #25 = Asciz	(Lscala/collection/immutable/RedBlack<TA;>;)V;
const #26 = Asciz	Signature;
const #27 = Asciz	apply;
const #28 = Asciz	(Ljava/lang/Object;Ljava/lang/Object;Lscala/collection/immutable/RedBlack$Tree;Lscala/collection/immutable/RedBlack$Tree;)Lscala/collection/immutable/RedBlack$BlackTree;;
const #29 = Asciz	scala/collection/immutable/RedBlack$BlackTree;
const #30 = class	#29;	//  scala/collection/immutable/RedBlack$BlackTree
const #31 = Asciz	(Lscala/collection/immutable/RedBlack;Ljava/lang/Object;Ljava/lang/Object;Lscala/collection/immutable/RedBlack$Tree;Lscala/collection/immutable/RedBlack$Tree;)V;
const #32 = NameAndType	#6:#31;//  "<init>":(Lscala/collection/immutable/RedBlack;Ljava/lang/Object;Ljava/lang/Object;Lscala/collection/immutable/RedBlack$Tree;Lscala/collection/immutable/RedBlack$Tree;)V
const #33 = Method	#30.#32;	//  scala/collection/immutable/RedBlack$BlackTree."<init>":(Lscala/collection/immutable/RedBlack;Ljava/lang/Object;Ljava/lang/Object;Lscala/collection/immutable/RedBlack$Tree;Lscala/collection/immutable/RedBlack$Tree;)V
const #34 = Asciz	key;
const #35 = Asciz	Ljava/lang/Object;;
const #36 = Asciz	value;
const #37 = Asciz	left;
const #38 = Asciz	Lscala/collection/immutable/RedBlack$Tree;;
const #39 = Asciz	right;
const #40 = Asciz	unapply;
const #41 = Asciz	(Lscala/collection/immutable/RedBlack$BlackTree;)Lscala/Some;;
const #42 = Asciz	scala/Some;
const #43 = class	#42;	//  scala/Some
const #44 = Asciz	scala/Tuple4;
const #45 = class	#44;	//  scala/Tuple4
const #46 = Asciz	()Ljava/lang/Object;;
const #47 = NameAndType	#34:#46;//  key:()Ljava/lang/Object;
const #48 = Method	#30.#47;	//  scala/collection/immutable/RedBlack$BlackTree.key:()Ljava/lang/Object;
const #49 = NameAndType	#36:#46;//  value:()Ljava/lang/Object;
const #50 = Method	#30.#49;	//  scala/collection/immutable/RedBlack$BlackTree.value:()Ljava/lang/Object;
const #51 = Asciz	()Lscala/collection/immutable/RedBlack$Tree;;
const #52 = NameAndType	#37:#51;//  left:()Lscala/collection/immutable/RedBlack$Tree;
const #53 = Method	#30.#52;	//  scala/collection/immutable/RedBlack$BlackTree.left:()Lscala/collection/immutable/RedBlack$Tree;
const #54 = NameAndType	#39:#51;//  right:()Lscala/collection/immutable/RedBlack$Tree;
const #55 = Method	#30.#54;	//  scala/collection/immutable/RedBlack$BlackTree.right:()Lscala/collection/immutable/RedBlack$Tree;
const #56 = Asciz	(Ljava/lang/Object;Ljava/lang/Object;Ljava/lang/Object;Ljava/lang/Object;)V;
const #57 = NameAndType	#6:#56;//  "<init>":(Ljava/lang/Object;Ljava/lang/Object;Ljava/lang/Object;Ljava/lang/Object;)V
const #58 = Method	#45.#57;	//  scala/Tuple4."<init>":(Ljava/lang/Object;Ljava/lang/Object;Ljava/lang/Object;Ljava/lang/Object;)V
const #59 = Asciz	(Ljava/lang/Object;)V;
const #60 = NameAndType	#6:#59;//  "<init>":(Ljava/lang/Object;)V
const #61 = Method	#43.#60;	//  scala/Some."<init>":(Ljava/lang/Object;)V
const #62 = Asciz	x$0;
const #63 = Asciz	Lscala/collection/immutable/RedBlack$BlackTree;;
const #64 = Asciz	InnerClasses;
const #65 = Asciz	scala/collection/immutable/RedBlack$Tree;
const #66 = class	#65;	//  scala/collection/immutable/RedBlack$Tree
const #67 = Asciz	scala/collection/immutable/RedBlack;
const #68 = class	#67;	//  scala/collection/immutable/RedBlack
const #69 = Asciz	Tree;
const #70 = Asciz	BlackTree;
const #71 = Asciz	scala/ScalaObject;
const #72 = class	#71;	//  scala/ScalaObject

{
public scala.collection.immutable.RedBlack$BlackTree$(scala.collection.immutable.RedBlack);
  Code:
   Stack=2, Locals=2, Args_size=2
   0:	aload_1
   1:	ifnonnull	12
   4:	new	#11; //class java/lang/NullPointerException
   7:	dup
   8:	invokespecial	#14; //Method java/lang/NullPointerException."<init>":()V
   11:	athrow
   12:	aload_0
   13:	aload_1
   14:	putfield	#18; //Field $outer:Lscala/collection/immutable/RedBlack;
   17:	aload_0
   18:	invokespecial	#21; //Method java/lang/Object."<init>":()V
   21:	return
  LineNumberTable: 
   line 153: 0

  LocalVariableTable: 
   Start  Length  Slot  Name   Signature
   0      22      0    this       Lscala/collection/immutable/RedBlack$BlackTree$;
   0      22      1    $outer       Lscala/collection/immutable/RedBlack;

  Signature: length = 0x2
   00 19 

public scala.collection.immutable.RedBlack$BlackTree apply(java.lang.Object, java.lang.Object, scala.collection.immutable.RedBlack$Tree, scala.collection.immutable.RedBlack$Tree);
  Code:
   Stack=7, Locals=5, Args_size=5
   0:	new	#30; //class scala/collection/immutable/RedBlack$BlackTree
   3:	dup
   4:	aload_0
   5:	getfield	#18; //Field $outer:Lscala/collection/immutable/RedBlack;
   8:	aload_1
   9:	aload_2
   10:	aload_3
   11:	aload	4
   13:	invokespecial	#33; //Method scala/collection/immutable/RedBlack$BlackTree."<init>":(Lscala/collection/immutable/RedBlack;Ljava/lang/Object;Ljava/lang/Object;Lscala/collection/immutable/RedBlack$Tree;Lscala/collection/immutable/RedBlack$Tree;)V
   16:	areturn
  LineNumberTable: 
   line 153: 0

  LocalVariableTable: 
   Start  Length  Slot  Name   Signature
   0      17      0    this       Lscala/collection/immutable/RedBlack$BlackTree$;
   0      17      1    key       Ljava/lang/Object;
   0      17      2    value       Ljava/lang/Object;
   0      17      3    left       Lscala/collection/immutable/RedBlack$Tree;
   0      17      4    right       Lscala/collection/immutable/RedBlack$Tree;


public scala.Some unapply(scala.collection.immutable.RedBlack$BlackTree);
  Code:
   Stack=8, Locals=2, Args_size=2
   0:	new	#43; //class scala/Some
   3:	dup
   4:	new	#45; //class scala/Tuple4
   7:	dup
   8:	aload_1
   9:	invokevirtual	#48; //Method scala/collection/immutable/RedBlack$BlackTree.key:()Ljava/lang/Object;
   12:	aload_1
   13:	invokevirtual	#50; //Method scala/collection/immutable/RedBlack$BlackTree.value:()Ljava/lang/Object;
   16:	aload_1
   17:	invokevirtual	#53; //Method scala/collection/immutable/RedBlack$BlackTree.left:()Lscala/collection/immutable/RedBlack$Tree;
   20:	aload_1
   21:	invokevirtual	#55; //Method scala/collection/immutable/RedBlack$BlackTree.right:()Lscala/collection/immutable/RedBlack$Tree;
   24:	invokespecial	#58; //Method scala/Tuple4."<init>":(Ljava/lang/Object;Ljava/lang/Object;Ljava/lang/Object;Ljava/lang/Object;)V
   27:	invokespecial	#61; //Method scala/Some."<init>":(Ljava/lang/Object;)V
   30:	areturn
  LineNumberTable: 
   line 153: 0

  LocalVariableTable: 
   Start  Length  Slot  Name   Signature
   0      31      0    this       Lscala/collection/immutable/RedBlack$BlackTree$;
   0      31      1    x$0       Lscala/collection/immutable/RedBlack$BlackTree;


}

