Compiled from "RedBlack.scala"
public final class scala.collection.immutable.RedBlack$RedTree$ extends java.lang.Object implements scala.ScalaObject
  SourceFile: "RedBlack.scala"
  Scala: length = 0x
   
  InnerClass: 
   public abstract Tree=class scala/collection/immutable/RedBlack$Tree of class scala/collection/immutable/RedBlack
   public RedTree=class scala/collection/immutable/RedBlack$RedTree of class scala/collection/immutable/RedBlack
  minor version: 0
  major version: 49
  Constant pool:
Asciz	SourceFile;
Asciz	RedBlack.scala;
Asciz	Scala;
Asciz	$outer;
Asciz	Lscala/collection/immutable/RedBlack;;
Asciz	unapply;
Asciz	(Lscala/collection/immutable/RedBlack$RedTree;)Lscala/Some;;
Asciz	Code;
Asciz	scala/Some;
class	scala/Some
Asciz	LineNumberTable;
Asciz	scala/Tuple4;
class	scala/Tuple4
Asciz	scala/collection/immutable/RedBlack$RedTree;
class	scala/collection/immutable/RedBlack$RedTree
Asciz	key;
Asciz	()Ljava/lang/Object;;
NameAndType	key:()Ljava/lang/Object;
Method	scala/collection/immutable/RedBlack$RedTree.key:()Ljava/lang/Object;
Asciz	value;
NameAndType	value:()Ljava/lang/Object;
Method	scala/collection/immutable/RedBlack$RedTree.value:()Ljava/lang/Object;
Asciz	left;
Asciz	()Lscala/collection/immutable/RedBlack$Tree;;
NameAndType	left:()Lscala/collection/immutable/RedBlack$Tree;
Method	scala/collection/immutable/RedBlack$RedTree.left:()Lscala/collection/immutable/RedBlack$Tree;
Asciz	right;
NameAndType	right:()Lscala/collection/immutable/RedBlack$Tree;
Method	scala/collection/immutable/RedBlack$RedTree.right:()Lscala/collection/immutable/RedBlack$Tree;
Asciz	<init>;
Asciz	(Ljava/lang/Object;Ljava/lang/Object;Ljava/lang/Object;Ljava/lang/Object;)V;
NameAndType	"<init>":(Ljava/lang/Object;Ljava/lang/Object;Ljava/lang/Object;Ljava/lang/Object;)V
Method	scala/Tuple4."<init>":(Ljava/lang/Object;Ljava/lang/Object;Ljava/lang/Object;Ljava/lang/Object;)V
Asciz	(Ljava/lang/Object;)V;
NameAndType	"<init>":(Ljava/lang/Object;)V
Method	scala/Some."<init>":(Ljava/lang/Object;)V
Asciz	this;
Asciz	Lscala/collection/immutable/RedBlack$RedTree$;;
Asciz	x$0;
Asciz	Lscala/collection/immutable/RedBlack$RedTree;;
Asciz	LocalVariableTable;
Asciz	apply;
Asciz	(Ljava/lang/Object;Ljava/lang/Object;Lscala/collection/immutable/RedBlack$Tree;Lscala/collection/immutable/RedBlack$Tree;)Lscala/collection/immutable/RedBlack$RedTree;;
Asciz	scala/collection/immutable/RedBlack$RedTree$;
class	scala/collection/immutable/RedBlack$RedTree$
NameAndType	$outer:Lscala/collection/immutable/RedBlack;
Field	scala/collection/immutable/RedBlack$RedTree$.$outer:Lscala/collection/immutable/RedBlack;
Asciz	(Lscala/collection/immutable/RedBlack;Ljava/lang/Object;Ljava/lang/Object;Lscala/collection/immutable/RedBlack$Tree;Lscala/collection/immutable/RedBlack$Tree;)V;
NameAndType	"<init>":(Lscala/collection/immutable/RedBlack;Ljava/lang/Object;Ljava/lang/Object;Lscala/collection/immutable/RedBlack$Tree;Lscala/collection/immutable/RedBlack$Tree;)V
Method	scala/collection/immutable/RedBlack$RedTree."<init>":(Lscala/collection/immutable/RedBlack;Ljava/lang/Object;Ljava/lang/Object;Lscala/collection/immutable/RedBlack$Tree;Lscala/collection/immutable/RedBlack$Tree;)V
Asciz	Ljava/lang/Object;;
Asciz	Lscala/collection/immutable/RedBlack$Tree;;
Asciz	(Lscala/collection/immutable/RedBlack;)V;
Asciz	java/lang/NullPointerException;
class	java/lang/NullPointerException
Asciz	()V;
NameAndType	"<init>":()V
Method	java/lang/NullPointerException."<init>":()V
Asciz	java/lang/Object;
class	java/lang/Object
Method	java/lang/Object."<init>":()V
Asciz	(Lscala/collection/immutable/RedBlack<TA;>;)V;
Asciz	Signature;
Asciz	InnerClasses;
Asciz	scala/collection/immutable/RedBlack$Tree;
class	scala/collection/immutable/RedBlack$Tree
Asciz	scala/collection/immutable/RedBlack;
class	scala/collection/immutable/RedBlack
Asciz	Tree;
Asciz	RedTree;
Asciz	scala/ScalaObject;
class	scala/ScalaObject

{
private final scala.collection.immutable.RedBlack $outer;
  Signature: Lscala/collection/immutable/RedBlack;

public scala.Some unapply(scala.collection.immutable.RedBlack$RedTree);
  Signature: (Lscala/collection/immutable/RedBlack$RedTree;)Lscala/Some;
  Code:
   Stack=8, Locals=2, Args_size=2
	new	class scala/Some
	dup
	new	class scala/Tuple4
	dup
	aload_1
	invokevirtual	Method scala/collection/immutable/RedBlack$RedTree.key:()Ljava/lang/Object;
	aload_1
	invokevirtual	Method scala/collection/immutable/RedBlack$RedTree.value:()Ljava/lang/Object;
	aload_1
	invokevirtual	Method scala/collection/immutable/RedBlack$RedTree.left:()Lscala/collection/immutable/RedBlack$Tree;
	aload_1
	invokevirtual	Method scala/collection/immutable/RedBlack$RedTree.right:()Lscala/collection/immutable/RedBlack$Tree;
	invokespecial	Method scala/Tuple4."<init>":(Ljava/lang/Object;Ljava/lang/Object;Ljava/lang/Object;Ljava/lang/Object;)V
	invokespecial	Method scala/Some."<init>":(Ljava/lang/Object;)V
	areturn
  Labels:
  LocalVariableTable: 
   Start  Length  Slot  Name   Signature
   0      31      0    this       Lscala/collection/immutable/RedBlack$RedTree$;
   0      31      1    x$0       Lscala/collection/immutable/RedBlack$RedTree;


public scala.collection.immutable.RedBlack$RedTree apply(java.lang.Object, java.lang.Object, scala.collection.immutable.RedBlack$Tree, scala.collection.immutable.RedBlack$Tree);
  Signature: (Ljava/lang/Object;Ljava/lang/Object;Lscala/collection/immutable/RedBlack$Tree;Lscala/collection/immutable/RedBlack$Tree;)Lscala/collection/immutable/RedBlack$RedTree;
  Code:
   Stack=7, Locals=5, Args_size=5
	new	class scala/collection/immutable/RedBlack$RedTree
	dup
	aload_0
	getfield	Field $outer:Lscala/collection/immutable/RedBlack;
	aload_1
	aload_2
	aload_3
	aload	4
	invokespecial	Method scala/collection/immutable/RedBlack$RedTree."<init>":(Lscala/collection/immutable/RedBlack;Ljava/lang/Object;Ljava/lang/Object;Lscala/collection/immutable/RedBlack$Tree;Lscala/collection/immutable/RedBlack$Tree;)V
	areturn
  Labels:
  LocalVariableTable: 
   Start  Length  Slot  Name   Signature
   0      17      0    this       Lscala/collection/immutable/RedBlack$RedTree$;
   0      17      1    key       Ljava/lang/Object;
   0      17      2    value       Ljava/lang/Object;
   0      17      3    left       Lscala/collection/immutable/RedBlack$Tree;
   0      17      4    right       Lscala/collection/immutable/RedBlack$Tree;


public scala.collection.immutable.RedBlack$RedTree$(scala.collection.immutable.RedBlack);
  Signature: (Lscala/collection/immutable/RedBlack;)V
  Code:
   Stack=2, Locals=2, Args_size=2
	aload_1
	ifnonnull	l1 // aload_0
	new	class java/lang/NullPointerException
	dup
	invokespecial	Method java/lang/NullPointerException."<init>":()V
	athrow
l1	aload_0
	aload_1
	putfield	Field $outer:Lscala/collection/immutable/RedBlack;
	aload_0
	invokespecial	Method java/lang/Object."<init>":()V
	return
  Labels:
   	l1 = 12 // aload_0
  LocalVariableTable: 
   Start  Length  Slot  Name   Signature
   0      22      0    this       Lscala/collection/immutable/RedBlack$RedTree$;
   0      22      1    $outer       Lscala/collection/immutable/RedBlack;

  Signature: length = 0x2
   00 3E 

}

