Compiled from "RedBlack.scala"
public class scala.collection.immutable.RedBlack$BlackTree extends scala.collection.immutable.RedBlack$NonEmpty implements scala.ScalaObject,scala.Product,java.io.Serializable
  SourceFile: "RedBlack.scala"
  Signature: length = 0x2
   00 FFFFFF9E 
  Scala: length = 0x
   
  InnerClass: 
   public abstract Tree=class scala/collection/immutable/RedBlack$Tree of class scala/collection/immutable/RedBlack
   public abstract NonEmpty=class scala/collection/immutable/RedBlack$NonEmpty of class scala/collection/immutable/RedBlack
   public BlackTree=class scala/collection/immutable/RedBlack$BlackTree of class scala/collection/immutable/RedBlack
  minor version: 0
  major version: 49
  Constant pool:
Asciz	SourceFile;
Asciz	RedBlack.scala;
Asciz	right;
Asciz	Lscala/collection/immutable/RedBlack$Tree;;
Asciz	Lscala/collection/immutable/RedBlack<TA;>.Tree<TB;>;;
Asciz	Signature;
Asciz	left;
Asciz	value;
Asciz	Ljava/lang/Object;;
Asciz	TB;;
Asciz	key;
Asciz	TA;;
Asciz	productIterator;
Asciz	()Lscala/collection/Iterator;;
Asciz	Code;
Asciz	LineNumberTable;
Asciz	scala/Product$class;
class	scala/Product$class
Asciz	(Lscala/Product;)Lscala/collection/Iterator;;
NameAndType	productIterator:(Lscala/Product;)Lscala/collection/Iterator;
Method	scala/Product$class.productIterator:(Lscala/Product;)Lscala/collection/Iterator;
Asciz	productElements;
NameAndType	productElements:(Lscala/Product;)Lscala/collection/Iterator;
Method	scala/Product$class.productElements:(Lscala/Product;)Lscala/collection/Iterator;
Asciz	Deprecated;
Asciz	copy$default$4;
Asciz	()Lscala/collection/immutable/RedBlack$Tree;;
Asciz	scala/collection/immutable/RedBlack$BlackTree;
class	scala/collection/immutable/RedBlack$BlackTree
NameAndType	right:()Lscala/collection/immutable/RedBlack$Tree;
Method	scala/collection/immutable/RedBlack$BlackTree.right:()Lscala/collection/immutable/RedBlack$Tree;
Asciz	copy$default$3;
NameAndType	left:()Lscala/collection/immutable/RedBlack$Tree;
Method	scala/collection/immutable/RedBlack$BlackTree.left:()Lscala/collection/immutable/RedBlack$Tree;
Asciz	copy$default$2;
Asciz	()Ljava/lang/Object;;
NameAndType	value:()Ljava/lang/Object;
Method	scala/collection/immutable/RedBlack$BlackTree.value:()Ljava/lang/Object;
Asciz	copy$default$1;
NameAndType	key:()Ljava/lang/Object;
Method	scala/collection/immutable/RedBlack$BlackTree.key:()Ljava/lang/Object;
NameAndType	key:Ljava/lang/Object;
Field	scala/collection/immutable/RedBlack$BlackTree.key:Ljava/lang/Object;
Asciz	()TA;;
NameAndType	value:Ljava/lang/Object;
Field	scala/collection/immutable/RedBlack$BlackTree.value:Ljava/lang/Object;
Asciz	()TB;;
NameAndType	left:Lscala/collection/immutable/RedBlack$Tree;
Field	scala/collection/immutable/RedBlack$BlackTree.left:Lscala/collection/immutable/RedBlack$Tree;
Asciz	()Lscala/collection/immutable/RedBlack<TA;>.Tree<TB;>;;
NameAndType	right:Lscala/collection/immutable/RedBlack$Tree;
Field	scala/collection/immutable/RedBlack$BlackTree.right:Lscala/collection/immutable/RedBlack$Tree;
Asciz	isBlack;
Asciz	()Z;
Asciz	copy;
Asciz	(Ljava/lang/Object;Ljava/lang/Object;Lscala/collection/immutable/RedBlack$Tree;Lscala/collection/immutable/RedBlack$Tree;)Lscala/collection/immutable/RedBlack$BlackTree;;
Asciz	scala$collection$immutable$RedBlack$BlackTree$$$outer;
Asciz	()Lscala/collection/immutable/RedBlack;;
NameAndType	scala$collection$immutable$RedBlack$BlackTree$$$outer:()Lscala/collection/immutable/RedBlack;
Method	scala/collection/immutable/RedBlack$BlackTree.scala$collection$immutable$RedBlack$BlackTree$$$outer:()Lscala/collection/immutable/RedBlack;
Asciz	<init>;
Asciz	(Lscala/collection/immutable/RedBlack;Ljava/lang/Object;Ljava/lang/Object;Lscala/collection/immutable/RedBlack$Tree;Lscala/collection/immutable/RedBlack$Tree;)V;
NameAndType	"<init>":(Lscala/collection/immutable/RedBlack;Ljava/lang/Object;Ljava/lang/Object;Lscala/collection/immutable/RedBlack$Tree;Lscala/collection/immutable/RedBlack$Tree;)V
Method	scala/collection/immutable/RedBlack$BlackTree."<init>":(Lscala/collection/immutable/RedBlack;Ljava/lang/Object;Ljava/lang/Object;Lscala/collection/immutable/RedBlack$Tree;Lscala/collection/immutable/RedBlack$Tree;)V
Asciz	this;
Asciz	Lscala/collection/immutable/RedBlack$BlackTree;;
Asciz	LocalVariableTable;
Asciz	hashCode;
Asciz	()I;
Asciz	scala/runtime/ScalaRunTime$;
class	scala/runtime/ScalaRunTime$
Asciz	MODULE$;
Asciz	Lscala/runtime/ScalaRunTime$;;
NameAndType	MODULE$:Lscala/runtime/ScalaRunTime$;
Field	scala/runtime/ScalaRunTime$.MODULE$:Lscala/runtime/ScalaRunTime$;
Asciz	_hashCode;
Asciz	(Lscala/Product;)I;
NameAndType	_hashCode:(Lscala/Product;)I
Method	scala/runtime/ScalaRunTime$._hashCode:(Lscala/Product;)I
Asciz	toString;
Asciz	()Ljava/lang/String;;
Asciz	_toString;
Asciz	(Lscala/Product;)Ljava/lang/String;;
NameAndType	_toString:(Lscala/Product;)Ljava/lang/String;
Method	scala/runtime/ScalaRunTime$._toString:(Lscala/Product;)Ljava/lang/String;
Asciz	equals;
Asciz	(Ljava/lang/Object;)Z;
Asciz	gd4$1;
Asciz	(Ljava/lang/Object;Ljava/lang/Object;Lscala/collection/immutable/RedBlack$Tree;Lscala/collection/immutable/RedBlack$Tree;)Z;
NameAndType	gd4$1:(Ljava/lang/Object;Ljava/lang/Object;Lscala/collection/immutable/RedBlack$Tree;Lscala/collection/immutable/RedBlack$Tree;)Z
Method	scala/collection/immutable/RedBlack$BlackTree.gd4$1:(Ljava/lang/Object;Ljava/lang/Object;Lscala/collection/immutable/RedBlack$Tree;Lscala/collection/immutable/RedBlack$Tree;)Z
Asciz	scala/Equals;
class	scala/Equals
Asciz	canEqual;
NameAndType	canEqual:(Ljava/lang/Object;)Z
InterfaceMethod	scala/Equals.canEqual:(Ljava/lang/Object;)Z
Asciz	temp185;
Asciz	temp186;
Asciz	temp187;
Asciz	temp188;
Asciz	temp189;
Asciz	temp190;
Asciz	right$2;
Asciz	left$2;
Asciz	value$2;
Asciz	key$2;
Asciz	productPrefix;
Asciz	BlackTree;
String	BlackTree
Asciz	productArity;
Asciz	productElement;
Asciz	(I)Ljava/lang/Object;;
Asciz	java/lang/IndexOutOfBoundsException;
class	java/lang/IndexOutOfBoundsException
Asciz	scala/runtime/BoxesRunTime;
class	scala/runtime/BoxesRunTime
Asciz	boxToInteger;
Asciz	(I)Ljava/lang/Integer;;
NameAndType	boxToInteger:(I)Ljava/lang/Integer;
Method	scala/runtime/BoxesRunTime.boxToInteger:(I)Ljava/lang/Integer;
Asciz	java/lang/Object;
class	java/lang/Object
NameAndType	toString:()Ljava/lang/String;
Method	java/lang/Object.toString:()Ljava/lang/String;
Asciz	(Ljava/lang/String;)V;
NameAndType	"<init>":(Ljava/lang/String;)V
Method	java/lang/IndexOutOfBoundsException."<init>":(Ljava/lang/String;)V
Asciz	temp191;
Asciz	I;
Asciz	productElementName;
Asciz	(I)Ljava/lang/String;;
String	right
String	left
String	value
String	key
Asciz	temp192;
Asciz	scala/collection/immutable/RedBlack$Tree;
class	scala/collection/immutable/RedBlack$Tree
Asciz	$outer;
Asciz	Lscala/collection/immutable/RedBlack;;
NameAndType	$outer:Lscala/collection/immutable/RedBlack;
Field	scala/collection/immutable/RedBlack$Tree.$outer:Lscala/collection/immutable/RedBlack;
Asciz	(Ljava/lang/Object;Ljava/lang/Object;)Z;
NameAndType	equals:(Ljava/lang/Object;Ljava/lang/Object;)Z
Method	scala/runtime/BoxesRunTime.equals:(Ljava/lang/Object;Ljava/lang/Object;)Z
NameAndType	equals:(Ljava/lang/Object;)Z
Method	java/lang/Object.equals:(Ljava/lang/Object;)Z
Asciz	scala/collection/immutable/RedBlack$NonEmpty;
class	scala/collection/immutable/RedBlack$NonEmpty
Asciz	(Lscala/collection/immutable/RedBlack;)V;
NameAndType	"<init>":(Lscala/collection/immutable/RedBlack;)V
Method	scala/collection/immutable/RedBlack$NonEmpty."<init>":(Lscala/collection/immutable/RedBlack;)V
Asciz	$init$;
Asciz	(Lscala/Product;)V;
NameAndType	$init$:(Lscala/Product;)V
Method	scala/Product$class.$init$:(Lscala/Product;)V
Asciz	(Lscala/collection/immutable/RedBlack<TA;>;TA;TB;Lscala/collection/immutable/RedBlack<TA;>.Tree<TB;>;Lscala/collection/immutable/RedBlack<TA;>.Tree<TB;>;)V;
Asciz	<B:Ljava/lang/Object;>Lscala/collection/immutable/RedBlack<TA;>.NonEmpty<TB;>;Lscala/ScalaObject;Lscala/Product;;
Asciz	Scala;
Asciz	InnerClasses;
Asciz	scala/collection/immutable/RedBlack;
class	scala/collection/immutable/RedBlack
Asciz	Tree;
Asciz	NonEmpty;
Asciz	scala/ScalaObject;
class	scala/ScalaObject
Asciz	scala/Product;
class	scala/Product
Asciz	java/io/Serializable;
class	java/io/Serializable

{
private final scala.collection.immutable.RedBlack$Tree right;
  Signature: Lscala/collection/immutable/RedBlack$Tree;
  Signature: length = 0x2
   00 05 

private final scala.collection.immutable.RedBlack$Tree left;
  Signature: Lscala/collection/immutable/RedBlack$Tree;
  Signature: length = 0x2
   00 05 

private final java.lang.Object value;
  Signature: Ljava/lang/Object;
  Signature: length = 0x2
   00 0A 

private final java.lang.Object key;
  Signature: Ljava/lang/Object;
  Signature: length = 0x2
   00 0C 

public scala.collection.Iterator productIterator();
  Signature: ()Lscala/collection/Iterator;
  Code:
   Stack=1, Locals=1, Args_size=1
	aload_0
	invokestatic	Method scala/Product$class.productIterator:(Lscala/Product;)Lscala/collection/Iterator;
	areturn
  Labels:

public scala.collection.Iterator productElements();
  Signature: ()Lscala/collection/Iterator;
  Code:
   Stack=1, Locals=1, Args_size=1
	aload_0
	invokestatic	Method scala/Product$class.productElements:(Lscala/Product;)Lscala/collection/Iterator;
	areturn
  Labels:
  Deprecated: true

public scala.collection.immutable.RedBlack$Tree copy$default$4();
  Signature: ()Lscala/collection/immutable/RedBlack$Tree;
  Code:
   Stack=1, Locals=1, Args_size=1
	aload_0
	invokevirtual	Method right:()Lscala/collection/immutable/RedBlack$Tree;
	areturn
  Labels:

public scala.collection.immutable.RedBlack$Tree copy$default$3();
  Signature: ()Lscala/collection/immutable/RedBlack$Tree;
  Code:
   Stack=1, Locals=1, Args_size=1
	aload_0
	invokevirtual	Method left:()Lscala/collection/immutable/RedBlack$Tree;
	areturn
  Labels:

public java.lang.Object copy$default$2();
  Signature: ()Ljava/lang/Object;
  Code:
   Stack=1, Locals=1, Args_size=1
	aload_0
	invokevirtual	Method value:()Ljava/lang/Object;
	areturn
  Labels:

public java.lang.Object copy$default$1();
  Signature: ()Ljava/lang/Object;
  Code:
   Stack=1, Locals=1, Args_size=1
	aload_0
	invokevirtual	Method key:()Ljava/lang/Object;
	areturn
  Labels:

public java.lang.Object key();
  Signature: ()Ljava/lang/Object;
  Code:
   Stack=1, Locals=1, Args_size=1
	aload_0
	getfield	Field key:Ljava/lang/Object;
	areturn
  Labels:
  Signature: length = 0x2
   00 2C 

public java.lang.Object value();
  Signature: ()Ljava/lang/Object;
  Code:
   Stack=1, Locals=1, Args_size=1
	aload_0
	getfield	Field value:Ljava/lang/Object;
	areturn
  Labels:
  Signature: length = 0x2
   00 2F 

public scala.collection.immutable.RedBlack$Tree left();
  Signature: ()Lscala/collection/immutable/RedBlack$Tree;
  Code:
   Stack=1, Locals=1, Args_size=1
	aload_0
	getfield	Field left:Lscala/collection/immutable/RedBlack$Tree;
	areturn
  Labels:
  Signature: length = 0x2
   00 32 

public scala.collection.immutable.RedBlack$Tree right();
  Signature: ()Lscala/collection/immutable/RedBlack$Tree;
  Code:
   Stack=1, Locals=1, Args_size=1
	aload_0
	getfield	Field right:Lscala/collection/immutable/RedBlack$Tree;
	areturn
  Labels:
  Signature: length = 0x2
   00 32 

public boolean isBlack();
  Signature: ()Z
  Code:
   Stack=1, Locals=1, Args_size=1
	iconst_1
	ireturn
  Labels:

public scala.collection.immutable.RedBlack$BlackTree copy(java.lang.Object, java.lang.Object, scala.collection.immutable.RedBlack$Tree, scala.collection.immutable.RedBlack$Tree);
  Signature: (Ljava/lang/Object;Ljava/lang/Object;Lscala/collection/immutable/RedBlack$Tree;Lscala/collection/immutable/RedBlack$Tree;)Lscala/collection/immutable/RedBlack$BlackTree;
  Code:
   Stack=7, Locals=5, Args_size=5
	new	class scala/collection/immutable/RedBlack$BlackTree
	dup
	aload_0
	invokevirtual	Method scala$collection$immutable$RedBlack$BlackTree$$$outer:()Lscala/collection/immutable/RedBlack;
	aload_1
	aload_2
	aload_3
	aload	4
	invokespecial	Method "<init>":(Lscala/collection/immutable/RedBlack;Ljava/lang/Object;Ljava/lang/Object;Lscala/collection/immutable/RedBlack$Tree;Lscala/collection/immutable/RedBlack$Tree;)V
	areturn
  Labels:
  LocalVariableTable: 
   Start  Length  Slot  Name   Signature
   0      17      0    this       Lscala/collection/immutable/RedBlack$BlackTree;
   0      17      1    key       Ljava/lang/Object;
   0      17      2    value       Ljava/lang/Object;
   0      17      3    left       Lscala/collection/immutable/RedBlack$Tree;
   0      17      4    right       Lscala/collection/immutable/RedBlack$Tree;


public int hashCode();
  Signature: ()I
  Code:
   Stack=2, Locals=1, Args_size=1
	getstatic	Field scala/runtime/ScalaRunTime$.MODULE$:Lscala/runtime/ScalaRunTime$;
	aload_0
	invokevirtual	Method scala/runtime/ScalaRunTime$._hashCode:(Lscala/Product;)I
	ireturn
  Labels:

public java.lang.String toString();
  Signature: ()Ljava/lang/String;
  Code:
   Stack=2, Locals=1, Args_size=1
	getstatic	Field scala/runtime/ScalaRunTime$.MODULE$:Lscala/runtime/ScalaRunTime$;
	aload_0
	invokevirtual	Method scala/runtime/ScalaRunTime$._toString:(Lscala/Product;)Ljava/lang/String;
	areturn
  Labels:

public boolean equals(java.lang.Object);
  Signature: (Ljava/lang/Object;)Z
  Code:
   Stack=5, Locals=12, Args_size=2
	aload_0
	aload_1
	if_acmpeq	l1 // iconst_1
	aload_1
	astore_2
	aload_2
	instanceof	class scala/collection/immutable/RedBlack$BlackTree
	ifeq	l2 // iconst_0
	aload_2
	checkcast	class scala/collection/immutable/RedBlack$BlackTree
	invokevirtual	Method scala$collection$immutable$RedBlack$BlackTree$$$outer:()Lscala/collection/immutable/RedBlack;
	aload_0
	invokevirtual	Method scala$collection$immutable$RedBlack$BlackTree$$$outer:()Lscala/collection/immutable/RedBlack;
	if_acmpne	l2 // iconst_0
	aload_2
	checkcast	class scala/collection/immutable/RedBlack$BlackTree
	astore_3
	aload_3
	invokevirtual	Method key:()Ljava/lang/Object;
	astore	4
	aload_3
	invokevirtual	Method value:()Ljava/lang/Object;
	astore	5
	aload_3
	invokevirtual	Method left:()Lscala/collection/immutable/RedBlack$Tree;
	astore	6
	aload_3
	invokevirtual	Method right:()Lscala/collection/immutable/RedBlack$Tree;
	astore	7
	aload	7
	astore	8
	aload	6
	astore	9
	aload	5
	astore	10
	aload	4
	astore	11
	aload_0
	aload	11
	aload	10
	aload	9
	aload	8
	invokespecial	Method gd4$1:(Ljava/lang/Object;Ljava/lang/Object;Lscala/collection/immutable/RedBlack$Tree;Lscala/collection/immutable/RedBlack$Tree;)Z
	ifeq	l3 // iconst_0
	aload_1
	checkcast	class scala/collection/immutable/RedBlack$BlackTree
	aload_0
	invokeinterface	InterfaceMethod scala/Equals.canEqual:(Ljava/lang/Object;)Z
	goto	l4 // ifeq
l3	iconst_0
	goto	l4 // ifeq
l2	iconst_0
l4	ifeq	l5 // iconst_0
l1	iconst_1
	goto	l6 // ireturn
l5	iconst_0
l6	ireturn
  Labels:
   	l3 = 101 // iconst_0
   	l2 = 105 // iconst_0
   	l4 = 106 // ifeq
   	l1 = 109 // iconst_1
   	l5 = 113 // iconst_0
   	l6 = 114 // ireturn
  LocalVariableTable: 
   Start  Length  Slot  Name   Signature
   0      115      0    this       Lscala/collection/immutable/RedBlack$BlackTree;
   7      102      2    temp185       Ljava/lang/Object;
   33      72      3    temp186       Lscala/collection/immutable/RedBlack$BlackTree;
   39      66      4    temp187       Ljava/lang/Object;
   45      60      5    temp188       Ljava/lang/Object;
   51      54      6    temp189       Lscala/collection/immutable/RedBlack$Tree;
   57      48      7    temp190       Lscala/collection/immutable/RedBlack$Tree;
   61      44      8    right$2       Lscala/collection/immutable/RedBlack$Tree;
   65      40      9    left$2       Lscala/collection/immutable/RedBlack$Tree;
   69      36      10    value$2       Ljava/lang/Object;
   73      32      11    key$2       Ljava/lang/Object;


public java.lang.String productPrefix();
  Signature: ()Ljava/lang/String;
  Code:
   Stack=1, Locals=1, Args_size=1
	ldc	String BlackTree
	areturn
  Labels:

public int productArity();
  Signature: ()I
  Code:
   Stack=1, Locals=1, Args_size=1
	iconst_4
	ireturn
  Labels:

public java.lang.Object productElement(int);
  Signature: (I)Ljava/lang/Object;
  Code:
   Stack=3, Locals=3, Args_size=2
	iload_1
	istore_2
	iload_2
	tableswitch{ //0 to 3
		0: 68;
		1: 61;
		2: 54;
		3: 47;
		default: 32 }
	new	class java/lang/IndexOutOfBoundsException
	dup
	iload_1
	invokestatic	Method scala/runtime/BoxesRunTime.boxToInteger:(I)Ljava/lang/Integer;
	invokevirtual	Method java/lang/Object.toString:()Ljava/lang/String;
	invokespecial	Method java/lang/IndexOutOfBoundsException."<init>":(Ljava/lang/String;)V
	athrow
	aload_0
	invokevirtual	Method right:()Lscala/collection/immutable/RedBlack$Tree;
	goto	l1 // areturn
	aload_0
	invokevirtual	Method left:()Lscala/collection/immutable/RedBlack$Tree;
	goto	l1 // areturn
	aload_0
	invokevirtual	Method value:()Ljava/lang/Object;
	goto	l1 // areturn
	aload_0
	invokevirtual	Method key:()Ljava/lang/Object;
l1	areturn
  Labels:
   	l1 = 72 // areturn
  LocalVariableTable: 
   Start  Length  Slot  Name   Signature
   0      73      0    this       Lscala/collection/immutable/RedBlack$BlackTree;
   2      71      2    temp191       I


public java.lang.String productElementName(int);
  Signature: (I)Ljava/lang/String;
  Code:
   Stack=3, Locals=3, Args_size=2
	iload_1
	istore_2
	iload_2
	tableswitch{ //0 to 3
		0: 62;
		1: 57;
		2: 52;
		3: 47;
		default: 32 }
	new	class java/lang/IndexOutOfBoundsException
	dup
	iload_1
	invokestatic	Method scala/runtime/BoxesRunTime.boxToInteger:(I)Ljava/lang/Integer;
	invokevirtual	Method java/lang/Object.toString:()Ljava/lang/String;
	invokespecial	Method java/lang/IndexOutOfBoundsException."<init>":(Ljava/lang/String;)V
	athrow
	ldc	String right
	goto	l1 // areturn
	ldc	String left
	goto	l1 // areturn
	ldc	String value
	goto	l1 // areturn
	ldc	String key
l1	areturn
  Labels:
   	l1 = 64 // areturn
  LocalVariableTable: 
   Start  Length  Slot  Name   Signature
   0      65      0    this       Lscala/collection/immutable/RedBlack$BlackTree;
   2      63      2    temp192       I


public boolean canEqual(java.lang.Object);
  Signature: (Ljava/lang/Object;)Z
  Code:
   Stack=1, Locals=2, Args_size=2
	aload_1
	instanceof	class scala/collection/immutable/RedBlack$BlackTree
	ireturn
  Labels:

public scala.collection.immutable.RedBlack scala$collection$immutable$RedBlack$BlackTree$$$outer();
  Signature: ()Lscala/collection/immutable/RedBlack;
  Code:
   Stack=1, Locals=1, Args_size=1
	aload_0
	getfield	Field scala/collection/immutable/RedBlack$Tree.$outer:Lscala/collection/immutable/RedBlack;
	areturn
  Labels:

private final boolean gd4$1(java.lang.Object, java.lang.Object, scala.collection.immutable.RedBlack$Tree, scala.collection.immutable.RedBlack$Tree);
  Signature: (Ljava/lang/Object;Ljava/lang/Object;Lscala/collection/immutable/RedBlack$Tree;Lscala/collection/immutable/RedBlack$Tree;)Z
  Code:
   Stack=2, Locals=7, Args_size=5
	aload_1
	aload_0
	invokevirtual	Method key:()Ljava/lang/Object;
	invokestatic	Method scala/runtime/BoxesRunTime.equals:(Ljava/lang/Object;Ljava/lang/Object;)Z
	ifeq	l1 // iconst_0
	aload_2
	aload_0
	invokevirtual	Method value:()Ljava/lang/Object;
	invokestatic	Method scala/runtime/BoxesRunTime.equals:(Ljava/lang/Object;Ljava/lang/Object;)Z
	ifeq	l1 // iconst_0
	aload_3
	aload_0
	invokevirtual	Method left:()Lscala/collection/immutable/RedBlack$Tree;
	astore	5
	dup
	ifnonnull	l2 // aload
	pop
	aload	5
	ifnull	l3 // aload
	goto	l1 // iconst_0
l2	aload	5
	invokevirtual	Method java/lang/Object.equals:(Ljava/lang/Object;)Z
	ifeq	l1 // iconst_0
l3	aload	4
	aload_0
	invokevirtual	Method right:()Lscala/collection/immutable/RedBlack$Tree;
	astore	6
	dup
	ifnonnull	l4 // aload
	pop
	aload	6
	ifnull	l5 // iconst_1
	goto	l1 // iconst_0
l4	aload	6
	invokevirtual	Method java/lang/Object.equals:(Ljava/lang/Object;)Z
	ifeq	l1 // iconst_0
l5	iconst_1
	goto	l6 // ireturn
l1	iconst_0
l6	ireturn
  Labels:
   	l2 = 42 // aload
   	l3 = 50 // aload
   	l4 = 71 // aload
   	l5 = 79 // iconst_1
   	l1 = 83 // iconst_0
   	l6 = 84 // ireturn

public scala.collection.immutable.RedBlack$BlackTree(scala.collection.immutable.RedBlack, java.lang.Object, java.lang.Object, scala.collection.immutable.RedBlack$Tree, scala.collection.immutable.RedBlack$Tree);
  Signature: (Lscala/collection/immutable/RedBlack;Ljava/lang/Object;Ljava/lang/Object;Lscala/collection/immutable/RedBlack$Tree;Lscala/collection/immutable/RedBlack$Tree;)V
  Code:
   Stack=2, Locals=6, Args_size=6
	aload_0
	aload_2
	putfield	Field key:Ljava/lang/Object;
	aload_0
	aload_3
	putfield	Field value:Ljava/lang/Object;
	aload_0
	aload	4
	putfield	Field left:Lscala/collection/immutable/RedBlack$Tree;
	aload_0
	aload	5
	putfield	Field right:Lscala/collection/immutable/RedBlack$Tree;
	aload_0
	aload_1
	invokespecial	Method scala/collection/immutable/RedBlack$NonEmpty."<init>":(Lscala/collection/immutable/RedBlack;)V
	aload_0
	invokestatic	Method scala/Product$class.$init$:(Lscala/Product;)V
	return
  Labels:
  LocalVariableTable: 
   Start  Length  Slot  Name   Signature
   0      32      0    this       Lscala/collection/immutable/RedBlack$BlackTree;
   0      32      1    $outer       Lscala/collection/immutable/RedBlack;
   0      32      2    key       Ljava/lang/Object;
   0      32      3    value       Ljava/lang/Object;
   0      32      4    left       Lscala/collection/immutable/RedBlack$Tree;
   0      32      5    right       Lscala/collection/immutable/RedBlack$Tree;

  Signature: length = 0x2
   00 FFFFFF9D 

}

