Compiled from "RedBlack.scala"
public class scala.collection.immutable.RedBlack$RedTree extends scala.collection.immutable.RedBlack$NonEmpty implements scala.ScalaObject,scala.Product,java.io.Serializable
  SourceFile: "RedBlack.scala"
  Signature: length = 0x2
   00 FFFFFF99 
  Scala: length = 0x
   
  InnerClass: 
   public abstract #158= #77 of #157; //Tree=class scala/collection/immutable/RedBlack$Tree of class scala/collection/immutable/RedBlack
   public #102= #18 of #157; //RedTree=class scala/collection/immutable/RedBlack$RedTree of class scala/collection/immutable/RedBlack
   public abstract #159= #28 of #157; //NonEmpty=class scala/collection/immutable/RedBlack$NonEmpty of class scala/collection/immutable/RedBlack
  minor version: 0
  major version: 49
  Constant pool:
const #1 = Asciz	SourceFile;
const #2 = Asciz	RedBlack.scala;
const #3 = Asciz	right;
const #4 = Asciz	Lscala/collection/immutable/RedBlack$Tree;;
const #5 = Asciz	Lscala/collection/immutable/RedBlack<TA;>.Tree<TB;>;;
const #6 = Asciz	Signature;
const #7 = Asciz	left;
const #8 = Asciz	value;
const #9 = Asciz	Ljava/lang/Object;;
const #10 = Asciz	TB;;
const #11 = Asciz	key;
const #12 = Asciz	TA;;
const #13 = Asciz	<init>;
const #14 = Asciz	(Lscala/collection/immutable/RedBlack;Ljava/lang/Object;Ljava/lang/Object;Lscala/collection/immutable/RedBlack$Tree;Lscala/collection/immutable/RedBlack$Tree;)V;
const #15 = Asciz	Code;
const #16 = Asciz	LineNumberTable;
const #17 = Asciz	scala/collection/immutable/RedBlack$RedTree;
const #18 = class	#17;	//  scala/collection/immutable/RedBlack$RedTree
const #19 = NameAndType	#11:#9;//  key:Ljava/lang/Object;
const #20 = Field	#18.#19;	//  scala/collection/immutable/RedBlack$RedTree.key:Ljava/lang/Object;
const #21 = NameAndType	#8:#9;//  value:Ljava/lang/Object;
const #22 = Field	#18.#21;	//  scala/collection/immutable/RedBlack$RedTree.value:Ljava/lang/Object;
const #23 = NameAndType	#7:#4;//  left:Lscala/collection/immutable/RedBlack$Tree;
const #24 = Field	#18.#23;	//  scala/collection/immutable/RedBlack$RedTree.left:Lscala/collection/immutable/RedBlack$Tree;
const #25 = NameAndType	#3:#4;//  right:Lscala/collection/immutable/RedBlack$Tree;
const #26 = Field	#18.#25;	//  scala/collection/immutable/RedBlack$RedTree.right:Lscala/collection/immutable/RedBlack$Tree;
const #27 = Asciz	scala/collection/immutable/RedBlack$NonEmpty;
const #28 = class	#27;	//  scala/collection/immutable/RedBlack$NonEmpty
const #29 = Asciz	(Lscala/collection/immutable/RedBlack;)V;
const #30 = NameAndType	#13:#29;//  "<init>":(Lscala/collection/immutable/RedBlack;)V
const #31 = Method	#28.#30;	//  scala/collection/immutable/RedBlack$NonEmpty."<init>":(Lscala/collection/immutable/RedBlack;)V
const #32 = Asciz	scala/Product$class;
const #33 = class	#32;	//  scala/Product$class
const #34 = Asciz	$init$;
const #35 = Asciz	(Lscala/Product;)V;
const #36 = NameAndType	#34:#35;//  $init$:(Lscala/Product;)V
const #37 = Method	#33.#36;	//  scala/Product$class.$init$:(Lscala/Product;)V
const #38 = Asciz	this;
const #39 = Asciz	Lscala/collection/immutable/RedBlack$RedTree;;
const #40 = Asciz	$outer;
const #41 = Asciz	Lscala/collection/immutable/RedBlack;;
const #42 = Asciz	LocalVariableTable;
const #43 = Asciz	(Lscala/collection/immutable/RedBlack<TA;>;TA;TB;Lscala/collection/immutable/RedBlack<TA;>.Tree<TB;>;Lscala/collection/immutable/RedBlack<TA;>.Tree<TB;>;)V;
const #44 = Asciz	gd1$1;
const #45 = Asciz	(Ljava/lang/Object;Ljava/lang/Object;Lscala/collection/immutable/RedBlack$Tree;Lscala/collection/immutable/RedBlack$Tree;)Z;
const #46 = Asciz	()Ljava/lang/Object;;
const #47 = NameAndType	#11:#46;//  key:()Ljava/lang/Object;
const #48 = Method	#18.#47;	//  scala/collection/immutable/RedBlack$RedTree.key:()Ljava/lang/Object;
const #49 = Asciz	java/lang/Number;
const #50 = class	#49;	//  java/lang/Number
const #51 = Asciz	java/lang/Character;
const #52 = class	#51;	//  java/lang/Character
const #53 = Asciz	scala/runtime/BoxesRunTime;
const #54 = class	#53;	//  scala/runtime/BoxesRunTime
const #55 = Asciz	equals2;
const #56 = Asciz	(Ljava/lang/Object;Ljava/lang/Object;)Z;
const #57 = NameAndType	#55:#56;//  equals2:(Ljava/lang/Object;Ljava/lang/Object;)Z
const #58 = Method	#54.#57;	//  scala/runtime/BoxesRunTime.equals2:(Ljava/lang/Object;Ljava/lang/Object;)Z
const #59 = Asciz	java/lang/Object;
const #60 = class	#59;	//  java/lang/Object
const #61 = Asciz	equals;
const #62 = Asciz	(Ljava/lang/Object;)Z;
const #63 = NameAndType	#61:#62;//  equals:(Ljava/lang/Object;)Z
const #64 = Method	#60.#63;	//  java/lang/Object.equals:(Ljava/lang/Object;)Z
const #65 = NameAndType	#8:#46;//  value:()Ljava/lang/Object;
const #66 = Method	#18.#65;	//  scala/collection/immutable/RedBlack$RedTree.value:()Ljava/lang/Object;
const #67 = Asciz	()Lscala/collection/immutable/RedBlack$Tree;;
const #68 = NameAndType	#7:#67;//  left:()Lscala/collection/immutable/RedBlack$Tree;
const #69 = Method	#18.#68;	//  scala/collection/immutable/RedBlack$RedTree.left:()Lscala/collection/immutable/RedBlack$Tree;
const #70 = NameAndType	#3:#67;//  right:()Lscala/collection/immutable/RedBlack$Tree;
const #71 = Method	#18.#70;	//  scala/collection/immutable/RedBlack$RedTree.right:()Lscala/collection/immutable/RedBlack$Tree;
const #72 = Asciz	y0;
const #73 = Asciz	y1;
const #74 = Asciz	scala$collection$immutable$RedBlack$RedTree$$$outer;
const #75 = Asciz	()Lscala/collection/immutable/RedBlack;;
const #76 = Asciz	scala/collection/immutable/RedBlack$Tree;
const #77 = class	#76;	//  scala/collection/immutable/RedBlack$Tree
const #78 = NameAndType	#40:#41;//  $outer:Lscala/collection/immutable/RedBlack;
const #79 = Field	#77.#78;	//  scala/collection/immutable/RedBlack$Tree.$outer:Lscala/collection/immutable/RedBlack;
const #80 = Asciz	canEqual;
const #81 = Asciz	productElement;
const #82 = Asciz	(I)Ljava/lang/Object;;
const #83 = Asciz	java/lang/IndexOutOfBoundsException;
const #84 = class	#83;	//  java/lang/IndexOutOfBoundsException
const #85 = Asciz	boxToInteger;
const #86 = Asciz	(I)Ljava/lang/Integer;;
const #87 = NameAndType	#85:#86;//  boxToInteger:(I)Ljava/lang/Integer;
const #88 = Method	#54.#87;	//  scala/runtime/BoxesRunTime.boxToInteger:(I)Ljava/lang/Integer;
const #89 = Asciz	toString;
const #90 = Asciz	()Ljava/lang/String;;
const #91 = NameAndType	#89:#90;//  toString:()Ljava/lang/String;
const #92 = Method	#60.#91;	//  java/lang/Object.toString:()Ljava/lang/String;
const #93 = Asciz	(Ljava/lang/String;)V;
const #94 = NameAndType	#13:#93;//  "<init>":(Ljava/lang/String;)V
const #95 = Method	#84.#94;	//  java/lang/IndexOutOfBoundsException."<init>":(Ljava/lang/String;)V
const #96 = Asciz	scala/MatchError;
const #97 = class	#96;	//  scala/MatchError
const #98 = Method	#97.#94;	//  scala/MatchError."<init>":(Ljava/lang/String;)V
const #99 = Asciz	productArity;
const #100 = Asciz	()I;
const #101 = Asciz	productPrefix;
const #102 = Asciz	RedTree;
const #103 = String	#102;	//  RedTree
const #104 = NameAndType	#74:#75;//  scala$collection$immutable$RedBlack$RedTree$$$outer:()Lscala/collection/immutable/RedBlack;
const #105 = Method	#18.#104;	//  scala/collection/immutable/RedBlack$RedTree.scala$collection$immutable$RedBlack$RedTree$$$outer:()Lscala/collection/immutable/RedBlack;
const #106 = NameAndType	#44:#45;//  gd1$1:(Ljava/lang/Object;Ljava/lang/Object;Lscala/collection/immutable/RedBlack$Tree;Lscala/collection/immutable/RedBlack$Tree;)Z
const #107 = Method	#18.#106;	//  scala/collection/immutable/RedBlack$RedTree.gd1$1:(Ljava/lang/Object;Ljava/lang/Object;Lscala/collection/immutable/RedBlack$Tree;Lscala/collection/immutable/RedBlack$Tree;)Z
const #108 = Asciz	scala/Equals;
const #109 = class	#108;	//  scala/Equals
const #110 = NameAndType	#80:#62;//  canEqual:(Ljava/lang/Object;)Z
const #111 = InterfaceMethod	#109.#110;	//  scala/Equals.canEqual:(Ljava/lang/Object;)Z
const #112 = Asciz	temp41;
const #113 = Asciz	temp42;
const #114 = Asciz	temp43;
const #115 = Asciz	temp44;
const #116 = Asciz	temp45;
const #117 = Asciz	scala/runtime/ScalaRunTime$;
const #118 = class	#117;	//  scala/runtime/ScalaRunTime$
const #119 = Asciz	MODULE$;
const #120 = Asciz	Lscala/runtime/ScalaRunTime$;;
const #121 = NameAndType	#119:#120;//  MODULE$:Lscala/runtime/ScalaRunTime$;
const #122 = Field	#118.#121;	//  scala/runtime/ScalaRunTime$.MODULE$:Lscala/runtime/ScalaRunTime$;
const #123 = Asciz	_toString;
const #124 = Asciz	(Lscala/Product;)Ljava/lang/String;;
const #125 = NameAndType	#123:#124;//  _toString:(Lscala/Product;)Ljava/lang/String;
const #126 = Method	#118.#125;	//  scala/runtime/ScalaRunTime$._toString:(Lscala/Product;)Ljava/lang/String;
const #127 = Asciz	hashCode;
const #128 = Asciz	_hashCode;
const #129 = Asciz	(Lscala/Product;)I;
const #130 = NameAndType	#128:#129;//  _hashCode:(Lscala/Product;)I
const #131 = Method	#118.#130;	//  scala/runtime/ScalaRunTime$._hashCode:(Lscala/Product;)I
const #132 = Asciz	copy;
const #133 = Asciz	(Ljava/lang/Object;Ljava/lang/Object;Lscala/collection/immutable/RedBlack$Tree;Lscala/collection/immutable/RedBlack$Tree;)Lscala/collection/immutable/RedBlack$RedTree;;
const #134 = NameAndType	#13:#14;//  "<init>":(Lscala/collection/immutable/RedBlack;Ljava/lang/Object;Ljava/lang/Object;Lscala/collection/immutable/RedBlack$Tree;Lscala/collection/immutable/RedBlack$Tree;)V
const #135 = Method	#18.#134;	//  scala/collection/immutable/RedBlack$RedTree."<init>":(Lscala/collection/immutable/RedBlack;Ljava/lang/Object;Ljava/lang/Object;Lscala/collection/immutable/RedBlack$Tree;Lscala/collection/immutable/RedBlack$Tree;)V
const #136 = Asciz	isBlack;
const #137 = Asciz	()Z;
const #138 = Asciz	()Lscala/collection/immutable/RedBlack<TA;>.Tree<TB;>;;
const #139 = Asciz	()TB;;
const #140 = Asciz	()TA;;
const #141 = Asciz	copy$default$1;
const #142 = Asciz	copy$default$2;
const #143 = Asciz	copy$default$3;
const #144 = Asciz	copy$default$4;
const #145 = Asciz	productElements;
const #146 = Asciz	()Lscala/collection/Iterator;;
const #147 = Asciz	(Lscala/Product;)Lscala/collection/Iterator;;
const #148 = NameAndType	#145:#147;//  productElements:(Lscala/Product;)Lscala/collection/Iterator;
const #149 = Method	#33.#148;	//  scala/Product$class.productElements:(Lscala/Product;)Lscala/collection/Iterator;
const #150 = Asciz	productIterator;
const #151 = NameAndType	#150:#147;//  productIterator:(Lscala/Product;)Lscala/collection/Iterator;
const #152 = Method	#33.#151;	//  scala/Product$class.productIterator:(Lscala/Product;)Lscala/collection/Iterator;
const #153 = Asciz	<B:Ljava/lang/Object;>Lscala/collection/immutable/RedBlack<TA;>.NonEmpty<TB;>;Lscala/ScalaObject;Lscala/Product;;
const #154 = Asciz	Scala;
const #155 = Asciz	InnerClasses;
const #156 = Asciz	scala/collection/immutable/RedBlack;
const #157 = class	#156;	//  scala/collection/immutable/RedBlack
const #158 = Asciz	Tree;
const #159 = Asciz	NonEmpty;
const #160 = Asciz	scala/ScalaObject;
const #161 = class	#160;	//  scala/ScalaObject
const #162 = Asciz	scala/Product;
const #163 = class	#162;	//  scala/Product
const #164 = Asciz	java/io/Serializable;
const #165 = class	#164;	//  java/io/Serializable

{
public scala.collection.immutable.RedBlack$RedTree(scala.collection.immutable.RedBlack, java.lang.Object, java.lang.Object, scala.collection.immutable.RedBlack$Tree, scala.collection.immutable.RedBlack$Tree);
  Code:
   Stack=2, Locals=6, Args_size=6
   0:	aload_0
   1:	aload_2
   2:	putfield	#20; //Field key:Ljava/lang/Object;
   5:	aload_0
   6:	aload_3
   7:	putfield	#22; //Field value:Ljava/lang/Object;
   10:	aload_0
   11:	aload	4
   13:	putfield	#24; //Field left:Lscala/collection/immutable/RedBlack$Tree;
   16:	aload_0
   17:	aload	5
   19:	putfield	#26; //Field right:Lscala/collection/immutable/RedBlack$Tree;
   22:	aload_0
   23:	aload_1
   24:	invokespecial	#31; //Method scala/collection/immutable/RedBlack$NonEmpty."<init>":(Lscala/collection/immutable/RedBlack;)V
   27:	aload_0
   28:	invokestatic	#37; //Method scala/Product$class.$init$:(Lscala/Product;)V
   31:	return
  LineNumberTable: 
   line 153: 0
   line 154: 5
   line 155: 10
   line 156: 16
   line 153: 22

  LocalVariableTable: 
   Start  Length  Slot  Name   Signature
   0      32      0    this       Lscala/collection/immutable/RedBlack$RedTree;
   0      32      1    $outer       Lscala/collection/immutable/RedBlack;
   0      32      2    key       Ljava/lang/Object;
   0      32      3    value       Ljava/lang/Object;
   0      32      4    left       Lscala/collection/immutable/RedBlack$Tree;
   0      32      5    right       Lscala/collection/immutable/RedBlack$Tree;

  Signature: length = 0x2
   00 2B 

public scala.collection.immutable.RedBlack scala$collection$immutable$RedBlack$RedTree$$$outer();
  Code:
   Stack=1, Locals=1, Args_size=1
   0:	aload_0
   1:	getfield	#79; //Field scala/collection/immutable/RedBlack$Tree.$outer:Lscala/collection/immutable/RedBlack;
   4:	areturn
  LineNumberTable: 
   line 153: 0


public boolean canEqual(java.lang.Object);
  Code:
   Stack=1, Locals=2, Args_size=2
   0:	aload_1
   1:	instanceof	#18; //class scala/collection/immutable/RedBlack$RedTree
   4:	ireturn
  LineNumberTable: 
   line 153: 0


public java.lang.Object productElement(int);
  Code:
   Stack=3, Locals=2, Args_size=2
   0:	iload_1
   1:	tableswitch{ //0 to 3
		0: 144;
		1: 118;
		2: 92;
		3: 66;
		default: 32 }
   32:	iconst_1
   33:	ifeq	51
   36:	new	#84; //class java/lang/IndexOutOfBoundsException
   39:	dup
   40:	iload_1
   41:	invokestatic	#88; //Method scala/runtime/BoxesRunTime.boxToInteger:(I)Ljava/lang/Integer;
   44:	invokevirtual	#92; //Method java/lang/Object.toString:()Ljava/lang/String;
   47:	invokespecial	#95; //Method java/lang/IndexOutOfBoundsException."<init>":(Ljava/lang/String;)V
   50:	athrow
   51:	new	#97; //class scala/MatchError
   54:	dup
   55:	iload_1
   56:	invokestatic	#88; //Method scala/runtime/BoxesRunTime.boxToInteger:(I)Ljava/lang/Integer;
   59:	invokevirtual	#92; //Method java/lang/Object.toString:()Ljava/lang/String;
   62:	invokespecial	#98; //Method scala/MatchError."<init>":(Ljava/lang/String;)V
   65:	athrow
   66:	iconst_1
   67:	ifeq	77
   70:	aload_0
   71:	invokevirtual	#71; //Method right:()Lscala/collection/immutable/RedBlack$Tree;
   74:	goto	152
   77:	new	#97; //class scala/MatchError
   80:	dup
   81:	iload_1
   82:	invokestatic	#88; //Method scala/runtime/BoxesRunTime.boxToInteger:(I)Ljava/lang/Integer;
   85:	invokevirtual	#92; //Method java/lang/Object.toString:()Ljava/lang/String;
   88:	invokespecial	#98; //Method scala/MatchError."<init>":(Ljava/lang/String;)V
   91:	athrow
   92:	iconst_1
   93:	ifeq	103
   96:	aload_0
   97:	invokevirtual	#69; //Method left:()Lscala/collection/immutable/RedBlack$Tree;
   100:	goto	152
   103:	new	#97; //class scala/MatchError
   106:	dup
   107:	iload_1
   108:	invokestatic	#88; //Method scala/runtime/BoxesRunTime.boxToInteger:(I)Ljava/lang/Integer;
   111:	invokevirtual	#92; //Method java/lang/Object.toString:()Ljava/lang/String;
   114:	invokespecial	#98; //Method scala/MatchError."<init>":(Ljava/lang/String;)V
   117:	athrow
   118:	iconst_1
   119:	ifeq	129
   122:	aload_0
   123:	invokevirtual	#66; //Method value:()Ljava/lang/Object;
   126:	goto	152
   129:	new	#97; //class scala/MatchError
   132:	dup
   133:	iload_1
   134:	invokestatic	#88; //Method scala/runtime/BoxesRunTime.boxToInteger:(I)Ljava/lang/Integer;
   137:	invokevirtual	#92; //Method java/lang/Object.toString:()Ljava/lang/String;
   140:	invokespecial	#98; //Method scala/MatchError."<init>":(Ljava/lang/String;)V
   143:	athrow
   144:	iconst_1
   145:	ifeq	153
   148:	aload_0
   149:	invokevirtual	#48; //Method key:()Ljava/lang/Object;
   152:	areturn
   153:	new	#97; //class scala/MatchError
   156:	dup
   157:	iload_1
   158:	invokestatic	#88; //Method scala/runtime/BoxesRunTime.boxToInteger:(I)Ljava/lang/Integer;
   161:	invokevirtual	#92; //Method java/lang/Object.toString:()Ljava/lang/String;
   164:	invokespecial	#98; //Method scala/MatchError."<init>":(Ljava/lang/String;)V
   167:	athrow
  LineNumberTable: 
   line 153: 0
   line 21: 32
   line 153: 36
   line 21: 66
   line 153: 70
   line 21: 92
   line 153: 96
   line 21: 118
   line 153: 122
   line 21: 144
   line 153: 148


public int productArity();
  Code:
   Stack=1, Locals=1, Args_size=1
   0:	iconst_4
   1:	ireturn
  LineNumberTable: 
   line 153: 0


public java.lang.String productPrefix();
  Code:
   Stack=1, Locals=1, Args_size=1
   0:	ldc	#103; //String RedTree
   2:	areturn
  LineNumberTable: 
   line 153: 0


public boolean equals(java.lang.Object);
  Code:
   Stack=5, Locals=7, Args_size=2
   0:	aload_0
   1:	aload_1
   2:	if_acmpeq	109
   5:	aload_1
   6:	instanceof	#18; //class scala/collection/immutable/RedBlack$RedTree
   9:	ifeq	101
   12:	aload_1
   13:	checkcast	#18; //class scala/collection/immutable/RedBlack$RedTree
   16:	invokevirtual	#105; //Method scala$collection$immutable$RedBlack$RedTree$$$outer:()Lscala/collection/immutable/RedBlack;
   19:	aload_0
   20:	invokevirtual	#105; //Method scala$collection$immutable$RedBlack$RedTree$$$outer:()Lscala/collection/immutable/RedBlack;
   23:	if_acmpne	101
   26:	aload_1
   27:	checkcast	#18; //class scala/collection/immutable/RedBlack$RedTree
   30:	astore_2
   31:	aload_2
   32:	invokevirtual	#48; //Method key:()Ljava/lang/Object;
   35:	astore_3
   36:	aload_2
   37:	invokevirtual	#66; //Method value:()Ljava/lang/Object;
   40:	astore	4
   42:	aload_2
   43:	invokevirtual	#69; //Method left:()Lscala/collection/immutable/RedBlack$Tree;
   46:	astore	5
   48:	aload_2
   49:	invokevirtual	#71; //Method right:()Lscala/collection/immutable/RedBlack$Tree;
   52:	astore	6
   54:	aload_0
   55:	aload_3
   56:	aload	4
   58:	aload	5
   60:	aload	6
   62:	invokespecial	#107; //Method gd1$1:(Ljava/lang/Object;Ljava/lang/Object;Lscala/collection/immutable/RedBlack$Tree;Lscala/collection/immutable/RedBlack$Tree;)Z
   65:	ifeq	81
   68:	aload_1
   69:	checkcast	#18; //class scala/collection/immutable/RedBlack$RedTree
   72:	aload_0
   73:	invokeinterface	#111,  2; //InterfaceMethod scala/Equals.canEqual:(Ljava/lang/Object;)Z
   78:	goto	106
   81:	iconst_1
   82:	ifeq	89
   85:	iconst_0
   86:	goto	106
   89:	new	#97; //class scala/MatchError
   92:	dup
   93:	aload_1
   94:	invokevirtual	#92; //Method java/lang/Object.toString:()Ljava/lang/String;
   97:	invokespecial	#98; //Method scala/MatchError."<init>":(Ljava/lang/String;)V
   100:	athrow
   101:	iconst_1
   102:	ifeq	115
   105:	iconst_0
   106:	ifeq	113
   109:	iconst_1
   110:	goto	114
   113:	iconst_0
   114:	ireturn
   115:	new	#97; //class scala/MatchError
   118:	dup
   119:	aload_1
   120:	invokevirtual	#92; //Method java/lang/Object.toString:()Ljava/lang/String;
   123:	invokespecial	#98; //Method scala/MatchError."<init>":(Ljava/lang/String;)V
   126:	athrow
  LineNumberTable: 
   line 153: 0
   line 21: 81
   line 153: 89
   line 21: 101
   line 153: 106

  LocalVariableTable: 
   Start  Length  Slot  Name   Signature
   0      127      0    this       Lscala/collection/immutable/RedBlack$RedTree;
   31      70      2    temp41       Lscala/collection/immutable/RedBlack$RedTree;
   36      65      3    temp42       Ljava/lang/Object;
   42      59      4    temp43       Ljava/lang/Object;
   48      53      5    temp44       Lscala/collection/immutable/RedBlack$Tree;
   54      47      6    temp45       Lscala/collection/immutable/RedBlack$Tree;


public java.lang.String toString();
  Code:
   Stack=2, Locals=1, Args_size=1
   0:	getstatic	#122; //Field scala/runtime/ScalaRunTime$.MODULE$:Lscala/runtime/ScalaRunTime$;
   3:	aload_0
   4:	invokevirtual	#126; //Method scala/runtime/ScalaRunTime$._toString:(Lscala/Product;)Ljava/lang/String;
   7:	areturn
  LineNumberTable: 
   line 153: 0


public int hashCode();
  Code:
   Stack=2, Locals=1, Args_size=1
   0:	getstatic	#122; //Field scala/runtime/ScalaRunTime$.MODULE$:Lscala/runtime/ScalaRunTime$;
   3:	aload_0
   4:	invokevirtual	#131; //Method scala/runtime/ScalaRunTime$._hashCode:(Lscala/Product;)I
   7:	ireturn
  LineNumberTable: 
   line 153: 0


public scala.collection.immutable.RedBlack$RedTree copy(java.lang.Object, java.lang.Object, scala.collection.immutable.RedBlack$Tree, scala.collection.immutable.RedBlack$Tree);
  Code:
   Stack=7, Locals=5, Args_size=5
   0:	new	#18; //class scala/collection/immutable/RedBlack$RedTree
   3:	dup
   4:	aload_0
   5:	invokevirtual	#105; //Method scala$collection$immutable$RedBlack$RedTree$$$outer:()Lscala/collection/immutable/RedBlack;
   8:	aload_1
   9:	aload_2
   10:	aload_3
   11:	aload	4
   13:	invokespecial	#135; //Method "<init>":(Lscala/collection/immutable/RedBlack;Ljava/lang/Object;Ljava/lang/Object;Lscala/collection/immutable/RedBlack$Tree;Lscala/collection/immutable/RedBlack$Tree;)V
   16:	areturn
  LineNumberTable: 
   line 153: 0
   line 154: 9
   line 155: 10
   line 156: 11
   line 153: 13

  LocalVariableTable: 
   Start  Length  Slot  Name   Signature
   0      17      0    this       Lscala/collection/immutable/RedBlack$RedTree;
   0      17      1    key       Ljava/lang/Object;
   0      17      2    value       Ljava/lang/Object;
   0      17      3    left       Lscala/collection/immutable/RedBlack$Tree;
   0      17      4    right       Lscala/collection/immutable/RedBlack$Tree;


public boolean isBlack();
  Code:
   Stack=1, Locals=1, Args_size=1
   0:	iconst_0
   1:	ireturn
  LineNumberTable: 
   line 157: 0


public scala.collection.immutable.RedBlack$Tree right();
  Code:
   Stack=1, Locals=1, Args_size=1
   0:	aload_0
   1:	getfield	#26; //Field right:Lscala/collection/immutable/RedBlack$Tree;
   4:	areturn
  LineNumberTable: 
   line 156: 0

  Signature: length = 0x2
   00 FFFFFF8A 

public scala.collection.immutable.RedBlack$Tree left();
  Code:
   Stack=1, Locals=1, Args_size=1
   0:	aload_0
   1:	getfield	#24; //Field left:Lscala/collection/immutable/RedBlack$Tree;
   4:	areturn
  LineNumberTable: 
   line 155: 0

  Signature: length = 0x2
   00 FFFFFF8A 

public java.lang.Object value();
  Code:
   Stack=1, Locals=1, Args_size=1
   0:	aload_0
   1:	getfield	#22; //Field value:Ljava/lang/Object;
   4:	areturn
  LineNumberTable: 
   line 154: 0

  Signature: length = 0x2
   00 FFFFFF8B 

public java.lang.Object key();
  Code:
   Stack=1, Locals=1, Args_size=1
   0:	aload_0
   1:	getfield	#20; //Field key:Ljava/lang/Object;
   4:	areturn
  LineNumberTable: 
   line 153: 0

  Signature: length = 0x2
   00 FFFFFF8C 

public java.lang.Object copy$default$1();
  Code:
   Stack=1, Locals=1, Args_size=1
   0:	aload_0
   1:	invokevirtual	#48; //Method key:()Ljava/lang/Object;
   4:	areturn
  LineNumberTable: 
   line 153: 0


public java.lang.Object copy$default$2();
  Code:
   Stack=1, Locals=1, Args_size=1
   0:	aload_0
   1:	invokevirtual	#66; //Method value:()Ljava/lang/Object;
   4:	areturn
  LineNumberTable: 
   line 154: 0


public scala.collection.immutable.RedBlack$Tree copy$default$3();
  Code:
   Stack=1, Locals=1, Args_size=1
   0:	aload_0
   1:	invokevirtual	#69; //Method left:()Lscala/collection/immutable/RedBlack$Tree;
   4:	areturn
  LineNumberTable: 
   line 155: 0


public scala.collection.immutable.RedBlack$Tree copy$default$4();
  Code:
   Stack=1, Locals=1, Args_size=1
   0:	aload_0
   1:	invokevirtual	#71; //Method right:()Lscala/collection/immutable/RedBlack$Tree;
   4:	areturn
  LineNumberTable: 
   line 156: 0


public scala.collection.Iterator productElements();
  Code:
   Stack=1, Locals=1, Args_size=1
   0:	aload_0
   1:	invokestatic	#149; //Method scala/Product$class.productElements:(Lscala/Product;)Lscala/collection/Iterator;
   4:	areturn
  LineNumberTable: 
   line 153: 0


public scala.collection.Iterator productIterator();
  Code:
   Stack=1, Locals=1, Args_size=1
   0:	aload_0
   1:	invokestatic	#152; //Method scala/Product$class.productIterator:(Lscala/Product;)Lscala/collection/Iterator;
   4:	areturn
  LineNumberTable: 
   line 153: 0


}

