Compiled from "RedBlack.scala"
public abstract class scala.collection.immutable.RedBlack extends java.lang.Object implements scala.ScalaObject,java.io.Serializable
  SourceFile: "RedBlack.scala"
  Signature: length = 0x2
   00 6D 
  ScalaSig: length = 0x127F
   05 00 FFFFFF84 57 06 05 01 02 FFFFFF81 00 09 02 08 52 65 64
   42 6C 61 63 6B 0A 02 03 04 01 09 69 6D 6D 75 74
   61 62 6C 65 0A 02 05 06 01 0A 63 6F 6C 6C 65 63
   74 69 6F 6E 0A 01 07 01 05 73 63 61 6C 61 03 00
   15 02 0A 1E 13 03 00 0B 13 10 02 0C 11 0D 01 0D
   0A 02 0E 0F 01 04 6C 61 6E 67 0A 01 10 01 04 6A
   61 76 61 09 02 12 0D 02 06 4F 62 6A 65 63 74 10
   02 14 15 0D 01 06 09 02 16 06 02 0B 53 63 61 6C
   61 4F 62 6A 65 63 74 08 05 18 00 FFFFFF84 00 19 01 06
   3C 69 6E 69 74 3E 14 01 1A 10 03 1B 00 1C 0D 01
   02 10 02 1D 1E 0C 00 04 08 1F 00 FFFFFF84 FFFFFF80 FFFFFF80 FFFFFFC2 00
   20 02 01 41 11 02 21 24 10 02 14 22 09 02 23 06
   02 07 4E 6F 74 68 69 6E 67 10 02 14 25 09 02 26
   06 02 03 41 6E 79 08 05 28 00 FFFFFF86 00 29 01 09 69
   73 53 6D 61 6C 6C 65 72 14 03 2A 2D 2F 10 02 14
   2B 09 02 2C 06 02 07 42 6F 6F 6C 65 61 6E 08 05
   2E 27 FFFFFFC0 00 1C 01 01 78 08 05 30 27 FFFFFFC0 00 1C 01
   01 79 08 05 32 00 FFFFFF84 04 33 01 07 62 6C 61 63 6B
   65 6E 15 03 34 FFFFFF82 06 14 03 35 FFFFFF82 07 10 04 36 37
   FFFFFF82 05 0D 01 00 06 05 38 00 FFFFFF81 00 39 02 04 54 72
   65 65 15 02 3A 3F 13 03 37 0B 13 08 05 18 37 FFFFFF84
   00 3C 14 01 3D 10 03 36 37 3E 10 02 1D 3F 04 08
   40 37 FFFFFF84 FFFFFF80 FFFFFF84 FFFFFFC2 00 20 02 01 42 08 05 42 37 FFFFFF86
   00 43 01 07 69 73 45 6D 70 74 79 15 01 2A 08 05
   45 37 FFFFFF86 00 43 01 07 69 73 42 6C 61 63 6B 08 05
   47 37 FFFFFF86 00 48 01 06 6C 6F 6F 6B 75 70 14 02 3D
   49 08 05 2E 46 FFFFFFC0 00 1C 08 05 4B 37 FFFFFF84 00 4C 01
   06 75 70 64 61 74 65 15 02 4D 50 14 03 4E 53 55
   10 03 36 37 4F 10 02 1D 50 04 08 51 4A FFFFFF84 FFFFFF80 FFFFFF80
   FFFFFFC2 00 52 02 02 42 31 11 02 3E 24 08 05 54 4A FFFFFFC0
   00 1C 01 01 6B 08 05 56 4A FFFFFFC0 00 4F 01 01 76 08
   05 58 37 FFFFFF84 00 59 01 06 64 65 6C 65 74 65 14 02
   3D 5A 08 05 54 57 FFFFFFC0 00 1C 08 05 5C 37 FFFFFF86 00 5D
   01 07 66 6F 72 65 61 63 68 15 02 5E 68 14 02 5F
   62 10 02 14 60 09 02 61 06 02 04 55 6E 69 74 08
   05 63 5B FFFFFFC0 00 64 01 01 66 10 05 14 65 1C 3E 67
   09 02 66 06 02 09 46 75 6E 63 74 69 6F 6E 32 10
   02 1D 68 04 08 69 5B FFFFFF84 FFFFFF80 FFFFFF80 FFFFFFC2 00 20 02 01 55
   08 05 6B 37 FFFFFF86 00 6C 01 05 76 69 73 69 74 15 02
   6D 73 14 02 6E 79 14 02 6F 75 10 04 14 70 2A 72
   09 02 71 06 02 06 54 75 70 6C 65 32 10 02 1D 73
   04 08 74 6A FFFFFF84 FFFFFF80 FFFFFF80 FFFFFFC2 00 20 02 01 54 08 05 63
   6A FFFFFFC0 00 76 10 06 14 77 72 1C 3E 6F 09 02 78 06
   02 09 46 75 6E 63 74 69 6F 6E 33 08 05 7A 6A FFFFFFC0
   00 72 01 05 69 6E 70 75 74 28 03 6A 7C 7F 10 02
   14 7D 09 02 7E 06 02 0A 64 65 70 72 65 63 61 74
   65 64 21 02 FFFFFF81 00 01 15 75 73 65 20 60 66 6F 72
   65 61 63 68 27 20 69 6E 73 74 65 61 64 08 07 FFFFFF81
   02 37 FFFFFF86 00 FFFFFF81 03 01 08 74 6F 53 74 72 65 61 6D
   15 02 FFFFFF81 04 10 05 1B FFFFFF81 05 FFFFFF81 07 09 03 FFFFFF81 06 02
   02 06 53 74 72 65 61 6D 10 04 14 70 1C 3E 08 07
   FFFFFF81 09 37 FFFFFF86 00 FFFFFF81 0A 01 08 69 74 65 72 61 74 6F
   72 15 02 FFFFFF81 0B 10 06 FFFFFF81 0C FFFFFF81 0D FFFFFF81 07 0D 01 04
   09 03 FFFFFF81 0E 04 02 08 49 74 65 72 61 74 6F 72 08
   07 FFFFFF81 10 37 FFFFFF84 00 FFFFFF81 0A 01 08 65 6C 65 6D 65 6E
   74 73 28 05 FFFFFF81 0F 7C FFFFFF81 12 21 02 FFFFFF81 13 01 16 75
   73 65 20 60 69 74 65 72 61 74 6F 72 27 20 69 6E
   73 74 65 61 64 08 07 FFFFFF81 15 37 FFFFFF86 00 FFFFFF81 16 01 03
   75 70 64 15 04 FFFFFF81 17 FFFFFF81 1A 14 06 FFFFFF81 18 FFFFFF81 1B FFFFFF81
   1C 10 04 36 37 FFFFFF81 19 10 03 1D FFFFFF81 1A 04 09 51 FFFFFF81
   14 FFFFFF84 FFFFFF80 FFFFFF80 FFFFFFC2 00 52 08 06 54 FFFFFF81 14 FFFFFFC0 00 1C 08
   07 56 FFFFFF81 14 FFFFFFC0 00 FFFFFF81 19 08 07 FFFFFF81 1E 37 FFFFFF86 00 FFFFFF81
   1F 01 03 64 65 6C 14 03 3D FFFFFF81 20 08 06 54 FFFFFF81 1D
   FFFFFFC0 00 1C 08 07 FFFFFF81 22 37 FFFFFF86 00 FFFFFF81 23 01 08 73 6D
   61 6C 6C 65 73 74 15 02 FFFFFF81 24 10 04 36 FFFFFF81 25 3E
   06 07 FFFFFF81 26 00 FFFFFF81 00 FFFFFF81 27 02 08 4E 6F 6E 45 6D
   70 74 79 15 04 FFFFFF81 28 FFFFFF81 2B 13 05 FFFFFF81 25 FFFFFF81 29 13
   10 04 36 37 FFFFFF81 2A 10 03 1D FFFFFF81 2B 04 09 40 FFFFFF81 25
   FFFFFF84 FFFFFF80 FFFFFF84 FFFFFFC2 00 20 08 07 18 FFFFFF81 25 FFFFFF84 00 FFFFFF81 2D 14
   02 FFFFFF81 2E 10 05 36 FFFFFF81 25 FFFFFF81 2A 08 06 42 FFFFFF81 25 FFFFFF84
   00 43 08 08 FFFFFF81 31 FFFFFF81 25 FFFFFF86 00 FFFFFF81 32 01 03 6B 65
   79 15 01 1C 08 08 FFFFFF81 34 FFFFFF81 25 FFFFFF86 00 FFFFFF81 35 01 05
   76 61 6C 75 65 15 02 FFFFFF81 2A 08 08 FFFFFF81 37 FFFFFF81 25 FFFFFF86
   00 FFFFFF81 38 01 04 6C 65 66 74 15 02 FFFFFF81 29 08 08 FFFFFF81
   3A FFFFFF81 25 FFFFFF86 00 FFFFFF81 38 01 05 72 69 67 68 74 08 07
   47 FFFFFF81 25 FFFFFF84 00 FFFFFF81 3C 14 04 FFFFFF81 29 FFFFFF81 3D 08 06 54
   FFFFFF81 3B FFFFFFC0 00 1C 08 08 FFFFFF81 15 FFFFFF81 25 FFFFFF84 00 FFFFFF81 3F 15
   04 FFFFFF81 40 FFFFFF81 43 14 06 FFFFFF81 41 FFFFFF81 45 FFFFFF81 46 10 04 36
   37 FFFFFF81 42 10 03 1D FFFFFF81 43 04 0A 51 FFFFFF81 3E FFFFFF84 FFFFFF80 FFFFFF80
   FFFFFFC2 00 FFFFFF81 44 11 03 FFFFFF81 2A 24 08 06 54 FFFFFF81 3E FFFFFFC0 00
   1C 08 07 56 FFFFFF81 3E FFFFFFC0 00 FFFFFF81 42 08 08 FFFFFF81 1E FFFFFF81 25
   FFFFFF84 00 FFFFFF81 48 14 04 FFFFFF81 29 FFFFFF81 49 08 06 54 FFFFFF81 47 FFFFFFC0
   00 1C 08 08 FFFFFF81 22 FFFFFF81 25 FFFFFF84 00 FFFFFF81 4B 15 02 FFFFFF81 2E
   08 08 FFFFFF81 02 FFFFFF81 25 FFFFFF84 00 FFFFFF81 4D 15 02 FFFFFF81 4E 10 05
   1B FFFFFF81 05 FFFFFF81 4F 10 05 14 70 1C FFFFFF81 2A 08 08 FFFFFF81 09
   FFFFFF81 25 FFFFFF84 00 FFFFFF81 51 15 02 FFFFFF81 52 10 06 FFFFFF81 0C FFFFFF81 0D
   FFFFFF81 4F 08 07 5C FFFFFF81 25 FFFFFF84 00 FFFFFF81 54 15 04 FFFFFF81 55 FFFFFF81
   59 14 03 5F FFFFFF81 56 08 07 63 FFFFFF81 53 FFFFFFC0 00 FFFFFF81 57 10
   07 14 65 1C FFFFFF81 2A FFFFFF81 58 10 03 1D FFFFFF81 59 04 09 69
   FFFFFF81 53 FFFFFF84 FFFFFF80 FFFFFF80 FFFFFFC2 00 20 08 07 6B FFFFFF81 25 FFFFFF84 00 FFFFFF81
   5B 15 04 FFFFFF81 5C FFFFFF81 60 14 04 FFFFFF81 5D FFFFFF81 63 14 04 FFFFFF81
   5E FFFFFF81 61 10 05 14 70 2A FFFFFF81 5F 10 03 1D FFFFFF81 60 04
   09 74 FFFFFF81 5A FFFFFF84 FFFFFF80 FFFFFF80 FFFFFFC2 00 20 08 07 63 FFFFFF81 5A FFFFFFC0
   00 FFFFFF81 62 10 09 14 77 FFFFFF81 5F 1C FFFFFF81 2A FFFFFF81 5E 08 07
   7A FFFFFF81 5A FFFFFFC0 00 FFFFFF81 5F 28 04 FFFFFF81 5A 7C 7F 08 08 FFFFFF81
   66 FFFFFF81 25 FFFFFF84 20 FFFFFF81 67 01 05 72 61 6E 67 65 14 06
   FFFFFF81 29 FFFFFF81 68 FFFFFF81 6D 08 08 FFFFFF81 69 FFFFFF81 65 FFFFFFC0 00 FFFFFF81 6A
   01 04 66 72 6F 6D 10 04 14 FFFFFF81 6B 1C 09 03 FFFFFF81 6C
   06 02 06 4F 70 74 69 6F 6E 08 08 FFFFFF81 6E FFFFFF81 65 FFFFFFC0
   00 FFFFFF81 6A 01 05 75 6E 74 69 6C 08 08 FFFFFF81 70 FFFFFF81 25
   FFFFFF84 00 FFFFFF81 32 01 05 66 69 72 73 74 08 08 FFFFFF81 72 FFFFFF81
   25 FFFFFF84 00 FFFFFF81 32 01 04 6C 61 73 74 08 08 FFFFFF81 74 FFFFFF81
   25 FFFFFF84 00 FFFFFF81 75 01 05 63 6F 75 6E 74 15 02 FFFFFF81 76
   10 03 14 FFFFFF81 77 09 03 FFFFFF81 78 06 02 03 49 6E 74 28
   04 FFFFFF81 25 FFFFFF81 7A 10 03 14 FFFFFF81 7B 09 03 FFFFFF81 7C 06 02
   0C 73 65 72 69 61 6C 69 7A 61 62 6C 65 08 07 FFFFFF81
   66 37 FFFFFF86 00 FFFFFF81 7E 14 05 3D FFFFFF81 7F FFFFFF82 00 08 08 FFFFFF81
   69 FFFFFF81 7D FFFFFFC0 00 FFFFFF81 6A 08 08 FFFFFF81 6E FFFFFF81 7D FFFFFFC0 00 FFFFFF81
   6A 08 07 FFFFFF81 70 37 FFFFFF86 00 FFFFFF81 32 08 07 FFFFFF81 72 37 FFFFFF86
   00 FFFFFF81 32 08 07 FFFFFF81 74 37 FFFFFF86 00 FFFFFF81 75 28 03 37 FFFFFF81
   7A 10 03 1D FFFFFF82 06 04 08 40 31 FFFFFF84 FFFFFF80 FFFFFF80 FFFFFFC2 00 20
   08 06 FFFFFF82 08 31 FFFFFFC0 00 35 01 01 74 08 07 FFFFFF82 0A 00
   FFFFFF84 04 FFFFFF82 0B 01 06 6D 6B 54 72 65 65 15 04 FFFFFF82 0C
   FFFFFF82 15 14 0C FFFFFF82 0D FFFFFF82 16 FFFFFF82 17 FFFFFF82 18 FFFFFF82 19 FFFFFF82 1C
   12 06 FFFFFF82 0E FFFFFF82 10 FFFFFF82 13 06 0A FFFFFF82 0F 00 FFFFFF84 FFFFFF80 FFFFFF80
   FFFFFF80 00 FFFFFF82 0D 02 0C 3C 72 65 66 69 6E 65 6D 65 6E
   74 3E 10 03 14 FFFFFF82 11 09 03 FFFFFF82 12 06 02 07 50 72
   6F 64 75 63 74 10 05 36 FFFFFF81 25 FFFFFF82 14 10 03 1D FFFFFF82
   15 04 09 40 FFFFFF82 09 FFFFFF84 FFFFFF80 FFFFFF80 FFFFFFC2 00 20 08 06 45 FFFFFF82
   09 FFFFFFC0 00 2A 08 06 54 FFFFFF82 09 FFFFFFC0 00 1C 08 07 56 FFFFFF82
   09 FFFFFFC0 00 FFFFFF82 14 08 08 FFFFFF82 1A FFFFFF82 09 FFFFFFC0 00 FFFFFF82 1B 01
   01 6C 10 04 36 37 FFFFFF82 14 08 08 FFFFFF82 1D FFFFFF82 09 FFFFFFC0 00
   FFFFFF82 1B 01 01 72 07 07 FFFFFF82 1F 00 FFFFFF88 42 FFFFFF82 20 01 05
   45 6D 70 74 79 10 03 36 FFFFFF82 21 06 0A FFFFFF82 22 00 FFFFFF84
   FFFFFF80 FFFFFF80 FFFFFF88 42 FFFFFF82 23 02 05 45 6D 70 74 79 13 07 FFFFFF82
   21 FFFFFF82 24 13 FFFFFF82 10 10 03 36 37 21 08 07 18 FFFFFF82 21
   FFFFFF84 00 FFFFFF82 26 14 02 FFFFFF82 20 08 06 42 FFFFFF82 21 FFFFFF84 00 43
   08 06 45 FFFFFF82 21 FFFFFF84 00 43 08 07 47 FFFFFF82 21 FFFFFF84 00 FFFFFF82
   2A 14 04 FFFFFF82 24 FFFFFF82 2B 08 06 54 FFFFFF82 29 FFFFFFC0 00 1C 08
   08 FFFFFF81 15 FFFFFF82 21 FFFFFF84 00 FFFFFF82 2D 15 04 FFFFFF82 2E FFFFFF82 31 14
   06 FFFFFF82 2F FFFFFF82 32 FFFFFF82 33 10 04 36 37 FFFFFF82 30 10 03 1D
   FFFFFF82 31 04 09 40 FFFFFF82 2C FFFFFF84 FFFFFF80 FFFFFF80 FFFFFFC2 00 20 08 06 54
   FFFFFF82 2C FFFFFFC0 00 1C 08 07 56 FFFFFF82 2C FFFFFFC0 00 FFFFFF82 30 08 08
   FFFFFF81 1E FFFFFF82 21 FFFFFF84 00 FFFFFF82 35 14 04 FFFFFF82 24 FFFFFF82 36 08 06
   54 FFFFFF82 34 FFFFFFC0 00 1C 08 08 FFFFFF81 22 FFFFFF82 21 FFFFFF84 00 FFFFFF82 38
   15 02 FFFFFF82 39 10 04 36 FFFFFF81 25 21 08 08 FFFFFF81 09 FFFFFF82 21
   FFFFFF84 00 FFFFFF82 3B 15 02 FFFFFF82 3C 10 06 FFFFFF81 0C FFFFFF81 0D FFFFFF82 3D
   10 04 14 70 1C 21 08 08 FFFFFF81 02 FFFFFF82 21 FFFFFF84 00 FFFFFF82 3F
   15 02 FFFFFF82 40 10 05 1B FFFFFF81 05 FFFFFF82 3D 08 07 5C FFFFFF82 21
   FFFFFF84 00 FFFFFF82 42 15 04 FFFFFF82 43 FFFFFF82 47 14 03 5F FFFFFF82 44 08
   07 63 FFFFFF82 41 FFFFFFC0 00 FFFFFF82 45 10 06 14 65 1C 21 FFFFFF82 46
   10 03 1D FFFFFF82 47 04 09 69 FFFFFF82 41 FFFFFF84 FFFFFF80 FFFFFF80 FFFFFFC2 00 20
   08 07 6B FFFFFF82 21 FFFFFF84 00 FFFFFF82 49 15 04 FFFFFF82 4A FFFFFF82 4E 14
   04 FFFFFF82 4B FFFFFF82 51 14 04 FFFFFF82 4C FFFFFF82 4F 10 05 14 70 2A
   FFFFFF82 4D 10 03 1D FFFFFF82 4E 04 09 74 FFFFFF82 48 FFFFFF84 FFFFFF80 FFFFFF80 FFFFFFC2
   00 20 08 07 63 FFFFFF82 48 FFFFFFC0 00 FFFFFF82 50 10 08 14 77 FFFFFF82
   4D 1C 21 FFFFFF82 4C 08 07 7A FFFFFF82 48 FFFFFFC0 00 FFFFFF82 4D 28 04
   FFFFFF82 48 7C 7F 08 08 FFFFFF81 66 FFFFFF82 21 FFFFFF84 00 FFFFFF82 54 14 06
   FFFFFF82 20 FFFFFF82 55 FFFFFF82 56 08 08 FFFFFF81 69 FFFFFF82 53 FFFFFFC0 00 FFFFFF81 6A
   08 08 FFFFFF81 6E FFFFFF82 53 FFFFFFC0 00 FFFFFF81 6A 08 08 FFFFFF81 70 FFFFFF82 21
   FFFFFF84 00 FFFFFF82 58 15 01 21 08 08 FFFFFF81 72 FFFFFF82 21 FFFFFF84 00 FFFFFF82
   58 08 08 FFFFFF81 74 FFFFFF82 21 FFFFFF84 00 FFFFFF81 75 08 0B FFFFFF82 5C FFFFFF82
   21 FFFFFF84 FFFFFF80 FFFFFF80 FFFFFF84 22 FFFFFF82 5D 01 08 74 6F 53 74 72 69
   6E 67 14 02 FFFFFF82 5E 10 03 0C FFFFFF82 5F 09 03 FFFFFF82 60 0D
   02 06 53 74 72 69 6E 67 08 0B FFFFFF82 62 FFFFFF82 21 FFFFFF84 FFFFFF80
   FFFFFF80 FFFFFF84 20 FFFFFF82 63 01 0D 70 72 6F 64 75 63 74 50 72
   65 66 69 78 15 02 FFFFFF82 5E 08 0B FFFFFF82 65 FFFFFF82 21 FFFFFF84 FFFFFF80
   FFFFFF80 FFFFFF84 20 FFFFFF81 75 01 0C 70 72 6F 64 75 63 74 41 72
   69 74 79 08 0B FFFFFF82 67 FFFFFF82 21 FFFFFF84 FFFFFF80 FFFFFF80 FFFFFF84 20 FFFFFF82 68
   01 0E 70 72 6F 64 75 63 74 45 6C 65 6D 65 6E 74
   14 03 24 FFFFFF82 69 08 0A FFFFFF82 6A FFFFFF82 66 FFFFFF81 FFFFFF80 FFFFFFC0 00 FFFFFF81
   76 01 03 78 24 31 08 0B FFFFFF82 6C FFFFFF82 21 FFFFFF84 FFFFFF80 FFFFFF80 FFFFFF84
   20 FFFFFF82 6D 01 08 63 61 6E 45 71 75 61 6C 14 03 2A
   FFFFFF82 6E 08 09 FFFFFF82 6A FFFFFF82 6B FFFFFF81 FFFFFF80 FFFFFFC0 00 24 08 0B FFFFFF82
   70 FFFFFF82 21 FFFFFF84 FFFFFF80 FFFFFF80 FFFFFF84 08 FFFFFF82 71 01 0B 72 65 61 64
   52 65 73 6F 6C 76 65 14 01 0B 28 04 FFFFFF82 21 FFFFFF81 7A
   06 06 FFFFFF82 74 00 40 FFFFFF82 75 02 07 52 65 64 54 72 65
   65 15 04 FFFFFF82 76 FFFFFF82 79 13 07 FFFFFF82 73 FFFFFF82 77 13 FFFFFF82 10
   10 05 36 FFFFFF81 25 FFFFFF82 78 10 03 1D FFFFFF82 79 04 09 40 FFFFFF82
   73 FFFFFF84 FFFFFF80 FFFFFF84 FFFFFFC2 00 20 08 0B FFFFFF81 31 FFFFFF82 73 FFFFFF82 FFFFFFCA FFFFFF80
   FFFFFF84 20 FFFFFF81 32 08 0A FFFFFF82 7C FFFFFF82 73 FFFFFF82 FFFFFF88 FFFFFFA0 FFFFFF80 04 1C
   01 04 6B 65 79 20 08 0B FFFFFF81 34 FFFFFF82 73 FFFFFF82 FFFFFFCA FFFFFF80 FFFFFF84
   20 FFFFFF82 7E 15 02 FFFFFF82 78 08 0B FFFFFF83 00 FFFFFF82 73 FFFFFF82 FFFFFF88 FFFFFFA0
   FFFFFF80 04 FFFFFF82 78 01 06 76 61 6C 75 65 20 08 0B FFFFFF81 37
   FFFFFF82 73 FFFFFF82 FFFFFFCA FFFFFF80 FFFFFF84 20 FFFFFF83 02 15 02 FFFFFF83 03 10 04 36
   37 FFFFFF82 78 08 0B FFFFFF83 05 FFFFFF82 73 FFFFFF82 FFFFFF88 FFFFFFA0 FFFFFF80 04 FFFFFF83 03
   01 05 6C 65 66 74 20 08 0B FFFFFF81 3A FFFFFF82 73 FFFFFF82 FFFFFFCA FFFFFF80
   FFFFFF84 20 FFFFFF83 02 08 0B FFFFFF83 08 FFFFFF82 73 FFFFFF82 FFFFFF88 FFFFFFA0 FFFFFF80 04 FFFFFF83
   03 01 06 72 69 67 68 74 20 08 07 18 FFFFFF82 73 FFFFFF84 00
   FFFFFF83 0A 14 0A FFFFFF83 0B FFFFFF83 0C FFFFFF83 0D FFFFFF83 0E FFFFFF83 0F 10 05
   36 FFFFFF82 73 FFFFFF82 78 08 07 FFFFFF81 31 FFFFFF83 09 FFFFFFC0 00 1C 08 08
   FFFFFF81 34 FFFFFF83 09 FFFFFFC0 00 FFFFFF82 78 08 08 FFFFFF81 37 FFFFFF83 09 FFFFFFC0 00
   FFFFFF83 03 08 08 FFFFFF81 3A FFFFFF83 09 FFFFFFC0 00 FFFFFF83 03 08 06 45 FFFFFF82
   73 FFFFFF84 00 43 08 0A FFFFFF83 12 FFFFFF82 73 FFFFFF81 FFFFFF80 FFFFFF84 00 FFFFFF83 13
   01 04 63 6F 70 79 15 04 FFFFFF83 14 FFFFFF83 17 14 0A FFFFFF83 15
   FFFFFF83 18 FFFFFF83 27 FFFFFF83 2D FFFFFF83 34 10 05 36 FFFFFF82 73 FFFFFF83 16 10
   03 1D FFFFFF83 17 04 09 40 FFFFFF83 11 FFFFFF84 FFFFFF80 FFFFFF80 FFFFFFC2 00 20 08
   0B FFFFFF83 19 FFFFFF81 31 FFFFFF83 11 FFFFFF90 FFFFFF80 FFFFFFC0 00 1C 08 0A FFFFFF83 1A
   FFFFFF82 73 FFFFFF91 FFFFFF80 FFFFFF84 00 FFFFFF83 1B 01 0E 63 6F 70 79 24 64
   65 66 61 75 6C 74 24 31 15 04 FFFFFF83 1C FFFFFF83 26 2A 03
   1C FFFFFF83 1D 2B 02 FFFFFF83 1E 10 04 FFFFFF83 1F FFFFFF83 24 0D 02 FFFFFF83
   20 0A 04 FFFFFF83 21 FFFFFF83 22 01 09 75 6E 63 68 65 63 6B
   65 64 0A 03 FFFFFF83 23 06 01 0A 61 6E 6E 6F 74 61 74
   69 6F 6E 09 04 FFFFFF83 25 FFFFFF83 20 02 11 75 6E 63 68 65
   63 6B 65 64 56 61 72 69 61 6E 63 65 04 09 40 FFFFFF83
   19 FFFFFF84 FFFFFF80 FFFFFF80 FFFFFFC2 00 20 08 0C FFFFFF83 28 FFFFFF81 34 FFFFFF83 11 FFFFFF90
   FFFFFF80 FFFFFFC0 00 FFFFFF83 16 08 0A FFFFFF83 29 FFFFFF82 73 FFFFFF91 FFFFFF80 FFFFFF84 00 FFFFFF83
   2A 01 0E 63 6F 70 79 24 64 65 66 61 75 6C 74 24
   32 15 04 FFFFFF83 2B FFFFFF83 2C 2A 04 FFFFFF82 78 FFFFFF83 1D 04 09 40
   FFFFFF83 28 FFFFFF84 FFFFFF80 FFFFFF80 FFFFFFC2 00 20 08 0C FFFFFF83 2F FFFFFF81 37 FFFFFF83 11
   FFFFFF90 FFFFFF80 FFFFFFC0 00 FFFFFF83 2E 10 04 36 37 FFFFFF83 16 08 0A FFFFFF83 30
   FFFFFF82 73 FFFFFF91 FFFFFF80 FFFFFF84 00 FFFFFF83 31 01 0E 63 6F 70 79 24 64
   65 66 61 75 6C 74 24 33 15 04 FFFFFF83 32 FFFFFF83 33 2A 04
   FFFFFF83 03 FFFFFF83 1D 04 09 40 FFFFFF83 2F FFFFFF84 FFFFFF80 FFFFFF80 FFFFFFC2 00 20 08
   0C FFFFFF83 35 FFFFFF81 3A FFFFFF83 11 FFFFFF90 FFFFFF80 FFFFFFC0 00 FFFFFF83 2E 08 0A FFFFFF83
   36 FFFFFF82 73 FFFFFF91 FFFFFF80 FFFFFF84 00 FFFFFF83 37 01 0E 63 6F 70 79 24
   64 65 66 61 75 6C 74 24 34 15 04 FFFFFF83 32 FFFFFF83 38 04
   09 40 FFFFFF83 35 FFFFFF84 FFFFFF80 FFFFFF80 FFFFFFC2 00 20 08 0B FFFFFF83 3A FFFFFF82 73
   FFFFFF84 FFFFFF80 FFFFFF80 FFFFFF84 20 FFFFFF83 3B 01 08 68 61 73 68 43 6F 64
   65 14 02 FFFFFF81 76 08 0B FFFFFF82 5C FFFFFF82 73 FFFFFF84 FFFFFF80 FFFFFF80 FFFFFF84 20
   FFFFFF83 3D 14 02 FFFFFF83 3E 10 04 FFFFFF83 3F FFFFFF83 42 0E 03 14 FFFFFF83
   40 09 03 FFFFFF83 41 06 01 06 50 72 65 64 65 66 09 04
   FFFFFF82 60 FFFFFF83 43 0A 03 FFFFFF83 41 06 08 0B FFFFFF83 45 FFFFFF82 73 FFFFFF84
   FFFFFF80 FFFFFF80 FFFFFF84 20 FFFFFF83 46 01 06 65 71 75 61 6C 73 14 03
   2A FFFFFF83 47 08 09 FFFFFF82 6A FFFFFF83 44 FFFFFF81 FFFFFF80 FFFFFFC0 00 24 08 0B
   FFFFFF82 62 FFFFFF82 73 FFFFFF84 FFFFFF80 FFFFFF80 FFFFFF84 20 FFFFFF82 63 08 0B FFFFFF82 65 FFFFFF82
   73 FFFFFF84 FFFFFF80 FFFFFF80 FFFFFF84 20 FFFFFF81 75 08 0B FFFFFF82 67 FFFFFF82 73 FFFFFF84 FFFFFF80
   FFFFFF80 FFFFFF84 20 FFFFFF83 4B 14 03 24 FFFFFF83 4C 08 0A FFFFFF82 6A FFFFFF83 4A
   FFFFFF81 FFFFFF80 FFFFFFC0 00 FFFFFF81 76 08 0B FFFFFF82 6C FFFFFF82 73 FFFFFF84 FFFFFF80 FFFFFF80 FFFFFF84
   20 FFFFFF83 4E 14 03 2A FFFFFF83 4F 08 09 FFFFFF82 6A FFFFFF83 4D FFFFFF81 FFFFFF80
   FFFFFFC0 00 24 28 04 FFFFFF82 73 FFFFFF81 7A 07 09 FFFFFF83 52 00 FFFFFF81 FFFFFF80
   FFFFFF88 02 FFFFFF83 53 01 07 52 65 64 54 72 65 65 10 03 36
   FFFFFF83 54 06 0A FFFFFF82 74 00 FFFFFF84 FFFFFF81 FFFFFF80 FFFFFF88 02 FFFFFF83 55 13 04
   FFFFFF83 54 0B 13 08 07 18 FFFFFF83 54 FFFFFF84 00 FFFFFF83 57 14 02 FFFFFF83
   53 08 0A FFFFFF83 59 FFFFFF83 54 FFFFFF81 FFFFFF80 FFFFFF84 40 FFFFFF83 5A 01 05 61
   70 70 6C 79 15 04 FFFFFF83 5B FFFFFF83 5E 14 0A FFFFFF83 5C FFFFFF83 5F
   FFFFFF83 60 FFFFFF83 61 FFFFFF83 63 10 05 36 FFFFFF82 73 FFFFFF83 5D 10 03 1D
   FFFFFF83 5E 04 09 40 FFFFFF83 58 FFFFFF84 FFFFFF80 FFFFFF80 FFFFFFC2 00 20 08 07 FFFFFF81
   31 FFFFFF83 58 FFFFFFC0 00 1C 08 08 FFFFFF81 34 FFFFFF83 58 FFFFFFC0 00 FFFFFF83 5D
   08 08 FFFFFF81 37 FFFFFF83 58 FFFFFFC0 00 FFFFFF83 62 10 04 36 37 FFFFFF83 5D
   08 08 FFFFFF81 3A FFFFFF83 58 FFFFFFC0 00 FFFFFF83 62 08 0A FFFFFF83 65 FFFFFF83 54
   FFFFFF81 FFFFFF80 FFFFFF84 40 FFFFFF83 66 01 07 75 6E 61 70 70 6C 79 15
   04 FFFFFF83 67 FFFFFF83 6F 14 04 FFFFFF83 68 FFFFFF83 71 10 05 14 FFFFFF83 69
   FFFFFF83 6B 09 03 FFFFFF83 6A 06 02 04 53 6F 6D 65 10 0A 14
   FFFFFF83 6C 1C FFFFFF83 6E FFFFFF83 70 FFFFFF83 70 09 03 FFFFFF83 6D 06 02 06
   54 75 70 6C 65 34 10 03 1D FFFFFF83 6F 04 09 40 FFFFFF83 64
   FFFFFF84 FFFFFF80 FFFFFF80 FFFFFFC2 00 20 10 04 36 37 FFFFFF83 6E 08 08 FFFFFF83 72
   FFFFFF83 64 FFFFFFC0 00 FFFFFF83 73 01 03 78 24 30 10 05 36 FFFFFF82 73
   FFFFFF83 6E 06 06 FFFFFF83 75 00 40 FFFFFF83 76 02 09 42 6C 61 63
   6B 54 72 65 65 15 04 FFFFFF83 77 FFFFFF83 7A 13 07 FFFFFF83 74 FFFFFF83
   78 13 FFFFFF82 10 10 05 36 FFFFFF81 25 FFFFFF83 79 10 03 1D FFFFFF83 7A
   04 09 40 FFFFFF83 74 FFFFFF84 FFFFFF80 FFFFFF84 FFFFFFC2 00 20 08 0B FFFFFF81 31 FFFFFF83
   74 FFFFFF82 FFFFFFCA FFFFFF80 FFFFFF84 20 FFFFFF81 32 08 0A FFFFFF82 7C FFFFFF83 74 FFFFFF82 FFFFFF88
   FFFFFFA0 FFFFFF80 04 1C 08 0B FFFFFF81 34 FFFFFF83 74 FFFFFF82 FFFFFFCA FFFFFF80 FFFFFF84 20 FFFFFF83
   7E 15 02 FFFFFF83 79 08 0B FFFFFF83 00 FFFFFF83 74 FFFFFF82 FFFFFF88 FFFFFFA0 FFFFFF80 04
   FFFFFF83 79 08 0B FFFFFF81 37 FFFFFF83 74 FFFFFF82 FFFFFFCA FFFFFF80 FFFFFF84 20 FFFFFF84 01 15
   02 FFFFFF84 02 10 04 36 37 FFFFFF83 79 08 0B FFFFFF83 05 FFFFFF83 74 FFFFFF82
   FFFFFF88 FFFFFFA0 FFFFFF80 04 FFFFFF84 02 08 0B FFFFFF81 3A FFFFFF83 74 FFFFFF82 FFFFFFCA FFFFFF80 FFFFFF84
   20 FFFFFF84 01 08 0B FFFFFF83 08 FFFFFF83 74 FFFFFF82 FFFFFF88 FFFFFFA0 FFFFFF80 04 FFFFFF84 02
   08 07 18 FFFFFF83 74 FFFFFF84 00 FFFFFF84 07 14 0A FFFFFF84 08 FFFFFF84 09 FFFFFF84
   0A FFFFFF84 0B FFFFFF84 0C 10 05 36 FFFFFF83 74 FFFFFF83 79 08 07 FFFFFF81 31
   FFFFFF84 06 FFFFFFC0 00 1C 08 08 FFFFFF81 34 FFFFFF84 06 FFFFFFC0 00 FFFFFF83 79 08
   08 FFFFFF81 37 FFFFFF84 06 FFFFFFC0 00 FFFFFF84 02 08 08 FFFFFF81 3A FFFFFF84 06 FFFFFFC0
   00 FFFFFF84 02 08 06 45 FFFFFF83 74 FFFFFF84 00 43 08 0A FFFFFF83 12 FFFFFF83
   74 FFFFFF81 FFFFFF80 FFFFFF84 00 FFFFFF84 0F 15 04 FFFFFF84 10 FFFFFF84 13 14 0A FFFFFF84
   11 FFFFFF84 14 FFFFFF84 18 FFFFFF84 1D FFFFFF84 23 10 05 36 FFFFFF83 74 FFFFFF84 12
   10 03 1D FFFFFF84 13 04 09 40 FFFFFF84 0E FFFFFF84 FFFFFF80 FFFFFF80 FFFFFFC2 00 20
   08 0B FFFFFF84 15 FFFFFF81 31 FFFFFF84 0E FFFFFF90 FFFFFF80 FFFFFFC0 00 1C 08 0A FFFFFF83
   1A FFFFFF83 74 FFFFFF91 FFFFFF80 FFFFFF84 00 FFFFFF84 16 15 04 FFFFFF83 1C FFFFFF84 17 04
   09 40 FFFFFF84 15 FFFFFF84 FFFFFF80 FFFFFF80 FFFFFFC2 00 20 08 0C FFFFFF84 19 FFFFFF81 34
   FFFFFF84 0E FFFFFF90 FFFFFF80 FFFFFFC0 00 FFFFFF84 12 08 0A FFFFFF83 29 FFFFFF83 74 FFFFFF91 FFFFFF80
   FFFFFF84 00 FFFFFF84 1A 15 04 FFFFFF84 1B FFFFFF84 1C 2A 04 FFFFFF83 79 FFFFFF83 1D
   04 09 40 FFFFFF84 19 FFFFFF84 FFFFFF80 FFFFFF80 FFFFFFC2 00 20 08 0C FFFFFF84 1F FFFFFF81
   37 FFFFFF84 0E FFFFFF90 FFFFFF80 FFFFFFC0 00 FFFFFF84 1E 10 04 36 37 FFFFFF84 12 08
   0A FFFFFF83 30 FFFFFF83 74 FFFFFF91 FFFFFF80 FFFFFF84 00 FFFFFF84 20 15 04 FFFFFF84 21 FFFFFF84
   22 2A 04 FFFFFF84 02 FFFFFF83 1D 04 09 40 FFFFFF84 1F FFFFFF84 FFFFFF80 FFFFFF80 FFFFFFC2
   00 20 08 0C FFFFFF84 24 FFFFFF81 3A FFFFFF84 0E FFFFFF90 FFFFFF80 FFFFFFC0 00 FFFFFF84 1E
   08 0A FFFFFF83 36 FFFFFF83 74 FFFFFF91 FFFFFF80 FFFFFF84 00 FFFFFF84 25 15 04 FFFFFF84 21
   FFFFFF84 26 04 09 40 FFFFFF84 24 FFFFFF84 FFFFFF80 FFFFFF80 FFFFFFC2 00 20 08 0B FFFFFF83
   3A FFFFFF83 74 FFFFFF84 FFFFFF80 FFFFFF80 FFFFFF84 20 FFFFFF83 3B 08 0B FFFFFF82 5C FFFFFF83 74
   FFFFFF84 FFFFFF80 FFFFFF80 FFFFFF84 20 FFFFFF83 3D 08 0B FFFFFF83 45 FFFFFF83 74 FFFFFF84 FFFFFF80 FFFFFF80
   FFFFFF84 20 FFFFFF84 2A 14 03 2A FFFFFF84 2B 08 09 FFFFFF82 6A FFFFFF84 29 FFFFFF81
   FFFFFF80 FFFFFFC0 00 24 08 0B FFFFFF82 62 FFFFFF83 74 FFFFFF84 FFFFFF80 FFFFFF80 FFFFFF84 20 FFFFFF82
   63 08 0B FFFFFF82 65 FFFFFF83 74 FFFFFF84 FFFFFF80 FFFFFF80 FFFFFF84 20 FFFFFF81 75 08 0B
   FFFFFF82 67 FFFFFF83 74 FFFFFF84 FFFFFF80 FFFFFF80 FFFFFF84 20 FFFFFF84 2F 14 03 24 FFFFFF84 30
   08 0A FFFFFF82 6A FFFFFF84 2E FFFFFF81 FFFFFF80 FFFFFFC0 00 FFFFFF81 76 08 0B FFFFFF82 6C
   FFFFFF83 74 FFFFFF84 FFFFFF80 FFFFFF80 FFFFFF84 20 FFFFFF84 32 14 03 2A FFFFFF84 33 08 09
   FFFFFF82 6A FFFFFF84 31 FFFFFF81 FFFFFF80 FFFFFFC0 00 24 28 04 FFFFFF83 74 FFFFFF81 7A 07
   09 FFFFFF84 36 00 FFFFFF81 FFFFFF80 FFFFFF88 02 FFFFFF84 37 01 09 42 6C 61 63
   6B 54 72 65 65 10 03 36 FFFFFF84 38 06 0A FFFFFF83 75 00 FFFFFF84
   FFFFFF81 FFFFFF80 FFFFFF88 02 FFFFFF84 39 13 04 FFFFFF84 38 0B 13 08 07 18 FFFFFF84
   38 FFFFFF84 00 FFFFFF84 3B 14 02 FFFFFF84 37 08 0A FFFFFF83 59 FFFFFF84 38 FFFFFF81
   FFFFFF80 FFFFFF84 40 FFFFFF84 3D 15 04 FFFFFF84 3E FFFFFF84 41 14 0A FFFFFF84 3F FFFFFF84
   42 FFFFFF84 43 FFFFFF84 44 FFFFFF84 46 10 05 36 FFFFFF83 74 FFFFFF84 40 10 03
   1D FFFFFF84 41 04 09 40 FFFFFF84 3C FFFFFF84 FFFFFF80 FFFFFF80 FFFFFFC2 00 20 08 07
   FFFFFF81 31 FFFFFF84 3C FFFFFFC0 00 1C 08 08 FFFFFF81 34 FFFFFF84 3C FFFFFFC0 00 FFFFFF84
   40 08 08 FFFFFF81 37 FFFFFF84 3C FFFFFFC0 00 FFFFFF84 45 10 04 36 37 FFFFFF84
   40 08 08 FFFFFF81 3A FFFFFF84 3C FFFFFFC0 00 FFFFFF84 45 08 0A FFFFFF83 65 FFFFFF84
   38 FFFFFF81 FFFFFF80 FFFFFF84 40 FFFFFF84 48 15 04 FFFFFF84 49 FFFFFF84 4D 14 04 FFFFFF84
   4A FFFFFF84 4F 10 05 14 FFFFFF83 69 FFFFFF84 4B 10 0A 14 FFFFFF83 6C 1C
   FFFFFF84 4C FFFFFF84 4E FFFFFF84 4E 10 03 1D FFFFFF84 4D 04 09 40 FFFFFF84 47
   FFFFFF84 FFFFFF80 FFFFFF80 FFFFFFC2 00 20 10 04 36 37 FFFFFF84 4C 08 08 FFFFFF83 72
   FFFFFF84 47 FFFFFFC0 00 FFFFFF84 50 10 05 36 FFFFFF83 74 FFFFFF84 4C 28 05 00
   FFFFFF84 52 FFFFFF84 55 10 03 14 FFFFFF84 53 09 03 FFFFFF84 54 06 02 10
   53 65 72 69 61 6C 56 65 72 73 69 6F 6E 55 49 44
   1E 08 78 FFFFFF9F FFFFFFC8 34 FFFFFFEA 73 19 79 28 03 00 FFFFFF81 7A 
  InnerClass: 
   public abstract #112= #91 of #11; //Tree=class scala/collection/immutable/RedBlack$Tree of class scala/collection/immutable/RedBlack
   public #27= #59 of #11; //RedTree=class scala/collection/immutable/RedBlack$RedTree of class scala/collection/immutable/RedBlack
   public abstract #115= #114 of #11; //NonEmpty=class scala/collection/immutable/RedBlack$NonEmpty of class scala/collection/immutable/RedBlack
   public #36= #54 of #11; //BlackTree=class scala/collection/immutable/RedBlack$BlackTree of class scala/collection/immutable/RedBlack
  minor version: 0
  major version: 49
  Constant pool:
const #1 = Asciz	SourceFile;
const #2 = Asciz	RedBlack.scala;
const #3 = Asciz	<clinit>;
const #4 = Asciz	()V;
const #5 = Asciz	Code;
const #6 = Asciz	serialVersionUID;
const #7 = Asciz	J;
const #8 = long	8691885935445612921l;
const #10 = Asciz	scala/collection/immutable/RedBlack;
const #11 = class	#10;	//  scala/collection/immutable/RedBlack
const #12 = NameAndType	#6:#7;//  serialVersionUID:J
const #13 = Field	#11.#12;	//  scala/collection/immutable/RedBlack.serialVersionUID:J
const #14 = Asciz	RedTree$module;
const #15 = Asciz	Lscala/collection/immutable/RedBlack$RedTree$;;
const #16 = Asciz	BlackTree$module;
const #17 = Asciz	Lscala/collection/immutable/RedBlack$BlackTree$;;
const #18 = Asciz	Empty$module;
const #19 = Asciz	Lscala/collection/immutable/RedBlack$Empty$;;
const #20 = Asciz	<init>;
const #21 = Asciz	LineNumberTable;
const #22 = Asciz	java/lang/Object;
const #23 = class	#22;	//  java/lang/Object
const #24 = NameAndType	#20:#4;//  "<init>":()V
const #25 = Method	#23.#24;	//  java/lang/Object."<init>":()V
const #26 = Asciz	Signature;
const #27 = Asciz	RedTree;
const #28 = Asciz	()Lscala/collection/immutable/RedBlack$RedTree$;;
const #29 = NameAndType	#14:#15;//  RedTree$module:Lscala/collection/immutable/RedBlack$RedTree$;
const #30 = Field	#11.#29;	//  scala/collection/immutable/RedBlack.RedTree$module:Lscala/collection/immutable/RedBlack$RedTree$;
const #31 = Asciz	scala/collection/immutable/RedBlack$RedTree$;
const #32 = class	#31;	//  scala/collection/immutable/RedBlack$RedTree$
const #33 = Asciz	(Lscala/collection/immutable/RedBlack;)V;
const #34 = NameAndType	#20:#33;//  "<init>":(Lscala/collection/immutable/RedBlack;)V
const #35 = Method	#32.#34;	//  scala/collection/immutable/RedBlack$RedTree$."<init>":(Lscala/collection/immutable/RedBlack;)V
const #36 = Asciz	BlackTree;
const #37 = Asciz	()Lscala/collection/immutable/RedBlack$BlackTree$;;
const #38 = NameAndType	#16:#17;//  BlackTree$module:Lscala/collection/immutable/RedBlack$BlackTree$;
const #39 = Field	#11.#38;	//  scala/collection/immutable/RedBlack.BlackTree$module:Lscala/collection/immutable/RedBlack$BlackTree$;
const #40 = Asciz	scala/collection/immutable/RedBlack$BlackTree$;
const #41 = class	#40;	//  scala/collection/immutable/RedBlack$BlackTree$
const #42 = Method	#41.#34;	//  scala/collection/immutable/RedBlack$BlackTree$."<init>":(Lscala/collection/immutable/RedBlack;)V
const #43 = Asciz	Empty;
const #44 = Asciz	()Lscala/collection/immutable/RedBlack$Empty$;;
const #45 = NameAndType	#18:#19;//  Empty$module:Lscala/collection/immutable/RedBlack$Empty$;
const #46 = Field	#11.#45;	//  scala/collection/immutable/RedBlack.Empty$module:Lscala/collection/immutable/RedBlack$Empty$;
const #47 = Asciz	scala/collection/immutable/RedBlack$Empty$;
const #48 = class	#47;	//  scala/collection/immutable/RedBlack$Empty$
const #49 = Method	#48.#34;	//  scala/collection/immutable/RedBlack$Empty$."<init>":(Lscala/collection/immutable/RedBlack;)V
const #50 = Asciz	()Lscala/collection/immutable/RedBlack<TA;>.Empty;;
const #51 = Asciz	scala$collection$immutable$RedBlack$$mkTree;
const #52 = Asciz	(ZLjava/lang/Object;Ljava/lang/Object;Lscala/collection/immutable/RedBlack$Tree;Lscala/collection/immutable/RedBlack$Tree;)Lscala/Product;;
const #53 = Asciz	scala/collection/immutable/RedBlack$BlackTree;
const #54 = class	#53;	//  scala/collection/immutable/RedBlack$BlackTree
const #55 = Asciz	(Lscala/collection/immutable/RedBlack;Ljava/lang/Object;Ljava/lang/Object;Lscala/collection/immutable/RedBlack$Tree;Lscala/collection/immutable/RedBlack$Tree;)V;
const #56 = NameAndType	#20:#55;//  "<init>":(Lscala/collection/immutable/RedBlack;Ljava/lang/Object;Ljava/lang/Object;Lscala/collection/immutable/RedBlack$Tree;Lscala/collection/immutable/RedBlack$Tree;)V
const #57 = Method	#54.#56;	//  scala/collection/immutable/RedBlack$BlackTree."<init>":(Lscala/collection/immutable/RedBlack;Ljava/lang/Object;Ljava/lang/Object;Lscala/collection/immutable/RedBlack$Tree;Lscala/collection/immutable/RedBlack$Tree;)V
const #58 = Asciz	scala/collection/immutable/RedBlack$RedTree;
const #59 = class	#58;	//  scala/collection/immutable/RedBlack$RedTree
const #60 = Method	#59.#56;	//  scala/collection/immutable/RedBlack$RedTree."<init>":(Lscala/collection/immutable/RedBlack;Ljava/lang/Object;Ljava/lang/Object;Lscala/collection/immutable/RedBlack$Tree;Lscala/collection/immutable/RedBlack$Tree;)V
const #61 = Asciz	this;
const #62 = Asciz	Lscala/collection/immutable/RedBlack;;
const #63 = Asciz	isBlack;
const #64 = Asciz	Z;
const #65 = Asciz	k;
const #66 = Asciz	Ljava/lang/Object;;
const #67 = Asciz	v;
const #68 = Asciz	l;
const #69 = Asciz	Lscala/collection/immutable/RedBlack$Tree;;
const #70 = Asciz	r;
const #71 = Asciz	LocalVariableTable;
const #72 = Asciz	scala$collection$immutable$RedBlack$$blacken;
const #73 = Asciz	(Lscala/collection/immutable/RedBlack$Tree;)Lscala/collection/immutable/RedBlack$Tree;;
const #74 = Asciz	key;
const #75 = Asciz	()Ljava/lang/Object;;
const #76 = NameAndType	#74:#75;//  key:()Ljava/lang/Object;
const #77 = Method	#59.#76;	//  scala/collection/immutable/RedBlack$RedTree.key:()Ljava/lang/Object;
const #78 = Asciz	value;
const #79 = NameAndType	#78:#75;//  value:()Ljava/lang/Object;
const #80 = Method	#59.#79;	//  scala/collection/immutable/RedBlack$RedTree.value:()Ljava/lang/Object;
const #81 = Asciz	left;
const #82 = Asciz	()Lscala/collection/immutable/RedBlack$Tree;;
const #83 = NameAndType	#81:#82;//  left:()Lscala/collection/immutable/RedBlack$Tree;
const #84 = Method	#59.#83;	//  scala/collection/immutable/RedBlack$RedTree.left:()Lscala/collection/immutable/RedBlack$Tree;
const #85 = Asciz	right;
const #86 = NameAndType	#85:#82;//  right:()Lscala/collection/immutable/RedBlack$Tree;
const #87 = Method	#59.#86;	//  scala/collection/immutable/RedBlack$RedTree.right:()Lscala/collection/immutable/RedBlack$Tree;
const #88 = Asciz	scala/MatchError;
const #89 = class	#88;	//  scala/MatchError
const #90 = Asciz	scala/collection/immutable/RedBlack$Tree;
const #91 = class	#90;	//  scala/collection/immutable/RedBlack$Tree
const #92 = Asciz	toString;
const #93 = Asciz	()Ljava/lang/String;;
const #94 = NameAndType	#92:#93;//  toString:()Ljava/lang/String;
const #95 = Method	#91.#94;	//  scala/collection/immutable/RedBlack$Tree.toString:()Ljava/lang/String;
const #96 = Asciz	(Ljava/lang/String;)V;
const #97 = NameAndType	#20:#96;//  "<init>":(Ljava/lang/String;)V
const #98 = Method	#89.#97;	//  scala/MatchError."<init>":(Ljava/lang/String;)V
const #99 = Asciz	t;
const #100 = Asciz	temp2;
const #101 = Asciz	Lscala/collection/immutable/RedBlack$RedTree;;
const #102 = Asciz	temp3;
const #103 = Asciz	temp4;
const #104 = Asciz	temp5;
const #105 = Asciz	temp6;
const #106 = Asciz	isSmaller;
const #107 = Asciz	(Ljava/lang/Object;Ljava/lang/Object;)Z;
const #108 = Asciz	(TA;TA;)Z;
const #109 = Asciz	<A:Ljava/lang/Object;>Ljava/lang/Object;Lscala/ScalaObject;;
const #110 = Asciz	ScalaSig;
const #111 = Asciz	InnerClasses;
const #112 = Asciz	Tree;
const #113 = Asciz	scala/collection/immutable/RedBlack$NonEmpty;
const #114 = class	#113;	//  scala/collection/immutable/RedBlack$NonEmpty
const #115 = Asciz	NonEmpty;
const #116 = Asciz	scala/ScalaObject;
const #117 = class	#116;	//  scala/ScalaObject
const #118 = Asciz	java/io/Serializable;
const #119 = class	#118;	//  java/io/Serializable

{
public static final long serialVersionUID;

public static {};
  Code:
   Stack=2, Locals=0, Args_size=0
   0:	ldc2_w	#8; //long 8691885935445612921l
   3:	putstatic	#13; //Field serialVersionUID:J
   6:	return

public scala.collection.immutable.RedBlack();
  Code:
   Stack=1, Locals=1, Args_size=1
   0:	aload_0
   1:	invokespecial	#25; //Method java/lang/Object."<init>":()V
   4:	return
  LineNumberTable: 
   line 19: 0

  Signature: length = 0x2
   00 04 

public final scala.collection.immutable.RedBlack$RedTree$ RedTree();
  Code:
   Stack=4, Locals=1, Args_size=1
   0:	aload_0
   1:	getfield	#30; //Field RedTree$module:Lscala/collection/immutable/RedBlack$RedTree$;
   4:	ifnonnull	19
   7:	aload_0
   8:	new	#32; //class scala/collection/immutable/RedBlack$RedTree$
   11:	dup
   12:	aload_0
   13:	invokespecial	#35; //Method scala/collection/immutable/RedBlack$RedTree$."<init>":(Lscala/collection/immutable/RedBlack;)V
   16:	putfield	#30; //Field RedTree$module:Lscala/collection/immutable/RedBlack$RedTree$;
   19:	aload_0
   20:	getfield	#30; //Field RedTree$module:Lscala/collection/immutable/RedBlack$RedTree$;
   23:	areturn
  LineNumberTable: 
   line 153: 0


public final scala.collection.immutable.RedBlack$BlackTree$ BlackTree();
  Code:
   Stack=4, Locals=1, Args_size=1
   0:	aload_0
   1:	getfield	#39; //Field BlackTree$module:Lscala/collection/immutable/RedBlack$BlackTree$;
   4:	ifnonnull	19
   7:	aload_0
   8:	new	#41; //class scala/collection/immutable/RedBlack$BlackTree$
   11:	dup
   12:	aload_0
   13:	invokespecial	#42; //Method scala/collection/immutable/RedBlack$BlackTree$."<init>":(Lscala/collection/immutable/RedBlack;)V
   16:	putfield	#39; //Field BlackTree$module:Lscala/collection/immutable/RedBlack$BlackTree$;
   19:	aload_0
   20:	getfield	#39; //Field BlackTree$module:Lscala/collection/immutable/RedBlack$BlackTree$;
   23:	areturn
  LineNumberTable: 
   line 160: 0


public final scala.collection.immutable.RedBlack$Empty$ Empty();
  Code:
   Stack=4, Locals=1, Args_size=1
   0:	aload_0
   1:	getfield	#46; //Field Empty$module:Lscala/collection/immutable/RedBlack$Empty$;
   4:	ifnonnull	19
   7:	aload_0
   8:	new	#48; //class scala/collection/immutable/RedBlack$Empty$
   11:	dup
   12:	aload_0
   13:	invokespecial	#49; //Method scala/collection/immutable/RedBlack$Empty$."<init>":(Lscala/collection/immutable/RedBlack;)V
   16:	putfield	#46; //Field Empty$module:Lscala/collection/immutable/RedBlack$Empty$;
   19:	aload_0
   20:	getfield	#46; //Field Empty$module:Lscala/collection/immutable/RedBlack$Empty$;
   23:	areturn
  LineNumberTable: 
   line 132: 0

  Signature: length = 0x2
   00 32 

public final scala.Product scala$collection$immutable$RedBlack$$mkTree(boolean, java.lang.Object, java.lang.Object, scala.collection.immutable.RedBlack$Tree, scala.collection.immutable.RedBlack$Tree);
  Code:
   Stack=7, Locals=6, Args_size=6
   0:	iload_1
   1:	ifeq	21
   4:	new	#54; //class scala/collection/immutable/RedBlack$BlackTree
   7:	dup
   8:	aload_0
   9:	aload_2
   10:	aload_3
   11:	aload	4
   13:	aload	5
   15:	invokespecial	#57; //Method scala/collection/immutable/RedBlack$BlackTree."<init>":(Lscala/collection/immutable/RedBlack;Ljava/lang/Object;Ljava/lang/Object;Lscala/collection/immutable/RedBlack$Tree;Lscala/collection/immutable/RedBlack$Tree;)V
   18:	goto	35
   21:	new	#59; //class scala/collection/immutable/RedBlack$RedTree
   24:	dup
   25:	aload_0
   26:	aload_2
   27:	aload_3
   28:	aload	4
   30:	aload	5
   32:	invokespecial	#60; //Method scala/collection/immutable/RedBlack$RedTree."<init>":(Lscala/collection/immutable/RedBlack;Ljava/lang/Object;Ljava/lang/Object;Lscala/collection/immutable/RedBlack$Tree;Lscala/collection/immutable/RedBlack$Tree;)V
   35:	areturn
  LineNumberTable: 
   line 28: 0

  LocalVariableTable: 
   Start  Length  Slot  Name   Signature
   0      36      0    this       Lscala/collection/immutable/RedBlack;
   0      36      1    isBlack       Z
   0      36      2    k       Ljava/lang/Object;
   0      36      3    v       Ljava/lang/Object;
   0      36      4    l       Lscala/collection/immutable/RedBlack$Tree;
   0      36      5    r       Lscala/collection/immutable/RedBlack$Tree;


public final scala.collection.immutable.RedBlack$Tree scala$collection$immutable$RedBlack$$blacken(scala.collection.immutable.RedBlack$Tree);
  Code:
   Stack=7, Locals=7, Args_size=2
   0:	aload_1
   1:	instanceof	#59; //class scala/collection/immutable/RedBlack$RedTree
   4:	ifeq	69
   7:	aload_1
   8:	checkcast	#59; //class scala/collection/immutable/RedBlack$RedTree
   11:	astore_2
   12:	aload_2
   13:	invokevirtual	#77; //Method scala/collection/immutable/RedBlack$RedTree.key:()Ljava/lang/Object;
   16:	astore_3
   17:	aload_2
   18:	invokevirtual	#80; //Method scala/collection/immutable/RedBlack$RedTree.value:()Ljava/lang/Object;
   21:	astore	4
   23:	aload_2
   24:	invokevirtual	#84; //Method scala/collection/immutable/RedBlack$RedTree.left:()Lscala/collection/immutable/RedBlack$Tree;
   27:	astore	5
   29:	aload_2
   30:	invokevirtual	#87; //Method scala/collection/immutable/RedBlack$RedTree.right:()Lscala/collection/immutable/RedBlack$Tree;
   33:	astore	6
   35:	iconst_1
   36:	ifeq	57
   39:	new	#54; //class scala/collection/immutable/RedBlack$BlackTree
   42:	dup
   43:	aload_0
   44:	aload_3
   45:	aload	4
   47:	aload	5
   49:	aload	6
   51:	invokespecial	#57; //Method scala/collection/immutable/RedBlack$BlackTree."<init>":(Lscala/collection/immutable/RedBlack;Ljava/lang/Object;Ljava/lang/Object;Lscala/collection/immutable/RedBlack$Tree;Lscala/collection/immutable/RedBlack$Tree;)V
   54:	goto	74
   57:	new	#89; //class scala/MatchError
   60:	dup
   61:	aload_1
   62:	invokevirtual	#95; //Method scala/collection/immutable/RedBlack$Tree.toString:()Ljava/lang/String;
   65:	invokespecial	#98; //Method scala/MatchError."<init>":(Ljava/lang/String;)V
   68:	athrow
   69:	iconst_1
   70:	ifeq	75
   73:	aload_1
   74:	areturn
   75:	new	#89; //class scala/MatchError
   78:	dup
   79:	aload_1
   80:	invokevirtual	#95; //Method scala/collection/immutable/RedBlack$Tree.toString:()Ljava/lang/String;
   83:	invokespecial	#98; //Method scala/MatchError."<init>":(Ljava/lang/String;)V
   86:	athrow
  LineNumberTable: 
   line 23: 0
   line 21: 35
   line 24: 39
   line 23: 57
   line 21: 69
   line 25: 73
   line 23: 74

  LocalVariableTable: 
   Start  Length  Slot  Name   Signature
   0      87      0    this       Lscala/collection/immutable/RedBlack;
   0      87      1    t       Lscala/collection/immutable/RedBlack$Tree;
   12      57      2    temp2       Lscala/collection/immutable/RedBlack$RedTree;
   17      52      3    temp3       Ljava/lang/Object;
   23      46      4    temp4       Ljava/lang/Object;
   29      40      5    temp5       Lscala/collection/immutable/RedBlack$Tree;
   35      34      6    temp6       Lscala/collection/immutable/RedBlack$Tree;


public abstract boolean isSmaller(java.lang.Object, java.lang.Object);
  Signature: length = 0x2
   00 6C 

}

