Compiled from "RedBlack.scala"
public final class scala.collection.immutable.RedBlack$Empty$ extends scala.collection.immutable.RedBlack$Tree implements scala.ScalaObject,scala.Product,java.io.Serializable
  SourceFile: "RedBlack.scala"
  Scala: length = 0x
   
  Signature: length = 0x2
   00 FFFFFFA3 
  InnerClass: 
   public abstract #165= #9 of #51; //Tree=class scala/collection/immutable/RedBlack$Tree of class scala/collection/immutable/RedBlack
   public #166= #146 of #51; //RedTree=class scala/collection/immutable/RedBlack$RedTree of class scala/collection/immutable/RedBlack
   public abstract #169= #168 of #51; //NonEmpty=class scala/collection/immutable/RedBlack$NonEmpty of class scala/collection/immutable/RedBlack
  minor version: 0
  major version: 49
  Constant pool:
const #1 = Asciz	SourceFile;
const #2 = Asciz	RedBlack.scala;
const #3 = Asciz	Scala;
const #4 = Asciz	<init>;
const #5 = Asciz	(Lscala/collection/immutable/RedBlack;)V;
const #6 = Asciz	Code;
const #7 = Asciz	LineNumberTable;
const #8 = Asciz	scala/collection/immutable/RedBlack$Tree;
const #9 = class	#8;	//  scala/collection/immutable/RedBlack$Tree
const #10 = NameAndType	#4:#5;//  "<init>":(Lscala/collection/immutable/RedBlack;)V
const #11 = Method	#9.#10;	//  scala/collection/immutable/RedBlack$Tree."<init>":(Lscala/collection/immutable/RedBlack;)V
const #12 = Asciz	scala/Product$class;
const #13 = class	#12;	//  scala/Product$class
const #14 = Asciz	$init$;
const #15 = Asciz	(Lscala/Product;)V;
const #16 = NameAndType	#14:#15;//  $init$:(Lscala/Product;)V
const #17 = Method	#13.#16;	//  scala/Product$class.$init$:(Lscala/Product;)V
const #18 = Asciz	this;
const #19 = Asciz	Lscala/collection/immutable/RedBlack$Empty$;;
const #20 = Asciz	$outer;
const #21 = Asciz	Lscala/collection/immutable/RedBlack;;
const #22 = Asciz	LocalVariableTable;
const #23 = Asciz	(Lscala/collection/immutable/RedBlack<TA;>;)V;
const #24 = Asciz	Signature;
const #25 = Asciz	range;
const #26 = Asciz	(Lscala/Option;Lscala/Option;)Lscala/collection/immutable/RedBlack$Tree;;
const #27 = Asciz	scala/collection/immutable/RedBlack$Empty$;
const #28 = class	#27;	//  scala/collection/immutable/RedBlack$Empty$
const #29 = Asciz	(Lscala/Option;Lscala/Option;)Lscala/collection/immutable/RedBlack$Empty$;;
const #30 = NameAndType	#25:#29;//  range:(Lscala/Option;Lscala/Option;)Lscala/collection/immutable/RedBlack$Empty$;
const #31 = Method	#28.#30;	//  scala/collection/immutable/RedBlack$Empty$.range:(Lscala/Option;Lscala/Option;)Lscala/collection/immutable/RedBlack$Empty$;
const #32 = Asciz	from;
const #33 = Asciz	Lscala/Option;;
const #34 = Asciz	until;
const #35 = Asciz	first;
const #36 = Asciz	()Ljava/lang/Object;;
const #37 = Asciz	()Lscala/runtime/Nothing$;;
const #38 = NameAndType	#35:#37;//  first:()Lscala/runtime/Nothing$;
const #39 = Method	#28.#38;	//  scala/collection/immutable/RedBlack$Empty$.first:()Lscala/runtime/Nothing$;
const #40 = Asciz	last;
const #41 = NameAndType	#40:#37;//  last:()Lscala/runtime/Nothing$;
const #42 = Method	#28.#41;	//  scala/collection/immutable/RedBlack$Empty$.last:()Lscala/runtime/Nothing$;
const #43 = Asciz	scala$collection$immutable$RedBlack$Empty$$$outer;
const #44 = Asciz	()Lscala/collection/immutable/RedBlack;;
const #45 = NameAndType	#20:#21;//  $outer:Lscala/collection/immutable/RedBlack;
const #46 = Field	#9.#45;	//  scala/collection/immutable/RedBlack$Tree.$outer:Lscala/collection/immutable/RedBlack;
const #47 = Asciz	readResolve;
const #48 = NameAndType	#43:#44;//  scala$collection$immutable$RedBlack$Empty$$$outer:()Lscala/collection/immutable/RedBlack;
const #49 = Method	#28.#48;	//  scala/collection/immutable/RedBlack$Empty$.scala$collection$immutable$RedBlack$Empty$$$outer:()Lscala/collection/immutable/RedBlack;
const #50 = Asciz	scala/collection/immutable/RedBlack;
const #51 = class	#50;	//  scala/collection/immutable/RedBlack
const #52 = Asciz	Empty;
const #53 = Asciz	()Lscala/collection/immutable/RedBlack$Empty$;;
const #54 = NameAndType	#52:#53;//  Empty:()Lscala/collection/immutable/RedBlack$Empty$;
const #55 = Method	#51.#54;	//  scala/collection/immutable/RedBlack.Empty:()Lscala/collection/immutable/RedBlack$Empty$;
const #56 = Asciz	canEqual;
const #57 = Asciz	(Ljava/lang/Object;)Z;
const #58 = Asciz	productElement;
const #59 = Asciz	(I)Ljava/lang/Object;;
const #60 = Asciz	java/lang/IndexOutOfBoundsException;
const #61 = class	#60;	//  java/lang/IndexOutOfBoundsException
const #62 = Asciz	scala/runtime/BoxesRunTime;
const #63 = class	#62;	//  scala/runtime/BoxesRunTime
const #64 = Asciz	boxToInteger;
const #65 = Asciz	(I)Ljava/lang/Integer;;
const #66 = NameAndType	#64:#65;//  boxToInteger:(I)Ljava/lang/Integer;
const #67 = Method	#63.#66;	//  scala/runtime/BoxesRunTime.boxToInteger:(I)Ljava/lang/Integer;
const #68 = Asciz	java/lang/Object;
const #69 = class	#68;	//  java/lang/Object
const #70 = Asciz	toString;
const #71 = Asciz	()Ljava/lang/String;;
const #72 = NameAndType	#70:#71;//  toString:()Ljava/lang/String;
const #73 = Method	#69.#72;	//  java/lang/Object.toString:()Ljava/lang/String;
const #74 = Asciz	(Ljava/lang/String;)V;
const #75 = NameAndType	#4:#74;//  "<init>":(Ljava/lang/String;)V
const #76 = Method	#61.#75;	//  java/lang/IndexOutOfBoundsException."<init>":(Ljava/lang/String;)V
const #77 = Asciz	scala/MatchError;
const #78 = class	#77;	//  scala/MatchError
const #79 = Method	#78.#75;	//  scala/MatchError."<init>":(Ljava/lang/String;)V
const #80 = Asciz	productArity;
const #81 = Asciz	()I;
const #82 = Asciz	productPrefix;
const #83 = String	#52;	//  Empty
const #84 = Asciz	count;
const #85 = Asciz	java/util/NoSuchElementException;
const #86 = class	#85;	//  java/util/NoSuchElementException
const #87 = Asciz	empty map;
const #88 = String	#87;	//  empty map
const #89 = Method	#86.#75;	//  java/util/NoSuchElementException."<init>":(Ljava/lang/String;)V
const #90 = Asciz	(Lscala/Option<TA;>;Lscala/Option<TA;>;)Lscala/collection/immutable/RedBlack<TA;>.Empty;;
const #91 = Asciz	visit;
const #92 = Asciz	(Ljava/lang/Object;Lscala/Function3;)Lscala/Tuple2;;
const #93 = Asciz	scala/Tuple2;
const #94 = class	#93;	//  scala/Tuple2
const #95 = Asciz	boxToBoolean;
const #96 = Asciz	(Z)Ljava/lang/Boolean;;
const #97 = NameAndType	#95:#96;//  boxToBoolean:(Z)Ljava/lang/Boolean;
const #98 = Method	#63.#97;	//  scala/runtime/BoxesRunTime.boxToBoolean:(Z)Ljava/lang/Boolean;
const #99 = Asciz	(Ljava/lang/Object;Ljava/lang/Object;)V;
const #100 = NameAndType	#4:#99;//  "<init>":(Ljava/lang/Object;Ljava/lang/Object;)V
const #101 = Method	#94.#100;	//  scala/Tuple2."<init>":(Ljava/lang/Object;Ljava/lang/Object;)V
const #102 = Asciz	input;
const #103 = Asciz	Ljava/lang/Object;;
const #104 = Asciz	f;
const #105 = Asciz	Lscala/Function3;;
const #106 = Asciz	<T:Ljava/lang/Object;>(TT;Lscala/Function3<TT;TA;Lscala/runtime/Nothing$;Lscala/Tuple2<Ljava/lang/Boolean;TT;>;>;)Lscala/Tuple2<Ljava/lang/Boolean;TT;>;;
const #107 = Asciz	Deprecated;
const #108 = Asciz	foreach;
const #109 = Asciz	(Lscala/Function2;)V;
const #110 = Asciz	Lscala/Function2;;
const #111 = Asciz	<U:Ljava/lang/Object;>(Lscala/Function2<TA;Lscala/runtime/Nothing$;TU;>;)V;
const #112 = Asciz	toStream;
const #113 = Asciz	()Lscala/collection/immutable/Stream;;
const #114 = Asciz	scala/collection/immutable/Stream$;
const #115 = class	#114;	//  scala/collection/immutable/Stream$
const #116 = Asciz	MODULE$;
const #117 = Asciz	Lscala/collection/immutable/Stream$;;
const #118 = NameAndType	#116:#117;//  MODULE$:Lscala/collection/immutable/Stream$;
const #119 = Field	#115.#118;	//  scala/collection/immutable/Stream$.MODULE$:Lscala/collection/immutable/Stream$;
const #120 = Asciz	empty;
const #121 = NameAndType	#120:#113;//  empty:()Lscala/collection/immutable/Stream;
const #122 = Method	#115.#121;	//  scala/collection/immutable/Stream$.empty:()Lscala/collection/immutable/Stream;
const #123 = Asciz	()Lscala/collection/immutable/Stream<Lscala/Tuple2<TA;Lscala/runtime/Nothing$;>;>;;
const #124 = Asciz	iterator;
const #125 = Asciz	()Lscala/collection/Iterator;;
const #126 = Asciz	scala/collection/Iterator$;
const #127 = class	#126;	//  scala/collection/Iterator$
const #128 = Asciz	Lscala/collection/Iterator$;;
const #129 = NameAndType	#116:#128;//  MODULE$:Lscala/collection/Iterator$;
const #130 = Field	#127.#129;	//  scala/collection/Iterator$.MODULE$:Lscala/collection/Iterator$;
const #131 = NameAndType	#120:#36;//  empty:()Ljava/lang/Object;
const #132 = Method	#127.#131;	//  scala/collection/Iterator$.empty:()Ljava/lang/Object;
const #133 = Asciz	scala/collection/Iterator;
const #134 = class	#133;	//  scala/collection/Iterator
const #135 = Asciz	()Lscala/collection/Iterator<Lscala/Tuple2<TA;Lscala/runtime/Nothing$;>;>;;
const #136 = Asciz	smallest;
const #137 = Asciz	()Lscala/collection/immutable/RedBlack$NonEmpty;;
const #138 = Asciz	()Lscala/collection/immutable/RedBlack<TA;>.NonEmpty<Lscala/runtime/Nothing$;>;;
const #139 = Asciz	del;
const #140 = Asciz	(Ljava/lang/Object;)Lscala/collection/immutable/RedBlack$Tree;;
const #141 = Asciz	k;
const #142 = Asciz	(TA;)Lscala/collection/immutable/RedBlack<TA;>.Tree<Lscala/runtime/Nothing$;>;;
const #143 = Asciz	upd;
const #144 = Asciz	(Ljava/lang/Object;Ljava/lang/Object;)Lscala/collection/immutable/RedBlack$Tree;;
const #145 = Asciz	scala/collection/immutable/RedBlack$RedTree;
const #146 = class	#145;	//  scala/collection/immutable/RedBlack$RedTree
const #147 = Asciz	(Lscala/collection/immutable/RedBlack;Ljava/lang/Object;Ljava/lang/Object;Lscala/collection/immutable/RedBlack$Tree;Lscala/collection/immutable/RedBlack$Tree;)V;
const #148 = NameAndType	#4:#147;//  "<init>":(Lscala/collection/immutable/RedBlack;Ljava/lang/Object;Ljava/lang/Object;Lscala/collection/immutable/RedBlack$Tree;Lscala/collection/immutable/RedBlack$Tree;)V
const #149 = Method	#146.#148;	//  scala/collection/immutable/RedBlack$RedTree."<init>":(Lscala/collection/immutable/RedBlack;Ljava/lang/Object;Ljava/lang/Object;Lscala/collection/immutable/RedBlack$Tree;Lscala/collection/immutable/RedBlack$Tree;)V
const #150 = Asciz	v;
const #151 = Asciz	<B:Ljava/lang/Object;>(TA;TB;)Lscala/collection/immutable/RedBlack<TA;>.Tree<TB;>;;
const #152 = Asciz	lookup;
const #153 = Asciz	isBlack;
const #154 = Asciz	()Z;
const #155 = Asciz	isEmpty;
const #156 = Asciz	productElements;
const #157 = Asciz	(Lscala/Product;)Lscala/collection/Iterator;;
const #158 = NameAndType	#156:#157;//  productElements:(Lscala/Product;)Lscala/collection/Iterator;
const #159 = Method	#13.#158;	//  scala/Product$class.productElements:(Lscala/Product;)Lscala/collection/Iterator;
const #160 = Asciz	productIterator;
const #161 = NameAndType	#160:#157;//  productIterator:(Lscala/Product;)Lscala/collection/Iterator;
const #162 = Method	#13.#161;	//  scala/Product$class.productIterator:(Lscala/Product;)Lscala/collection/Iterator;
const #163 = Asciz	Lscala/collection/immutable/RedBlack<TA;>.Tree<Lscala/runtime/Nothing$;>;Lscala/ScalaObject;Lscala/Product;;
const #164 = Asciz	InnerClasses;
const #165 = Asciz	Tree;
const #166 = Asciz	RedTree;
const #167 = Asciz	scala/collection/immutable/RedBlack$NonEmpty;
const #168 = class	#167;	//  scala/collection/immutable/RedBlack$NonEmpty
const #169 = Asciz	NonEmpty;
const #170 = Asciz	scala/ScalaObject;
const #171 = class	#170;	//  scala/ScalaObject
const #172 = Asciz	scala/Product;
const #173 = class	#172;	//  scala/Product
const #174 = Asciz	java/io/Serializable;
const #175 = class	#174;	//  java/io/Serializable

{
public scala.collection.immutable.RedBlack$Empty$(scala.collection.immutable.RedBlack);
  Code:
   Stack=2, Locals=2, Args_size=2
   0:	aload_0
   1:	aload_1
   2:	invokespecial	#11; //Method scala/collection/immutable/RedBlack$Tree."<init>":(Lscala/collection/immutable/RedBlack;)V
   5:	aload_0
   6:	invokestatic	#17; //Method scala/Product$class.$init$:(Lscala/Product;)V
   9:	return
  LineNumberTable: 
   line 132: 0

  LocalVariableTable: 
   Start  Length  Slot  Name   Signature
   0      10      0    this       Lscala/collection/immutable/RedBlack$Empty$;
   0      10      1    $outer       Lscala/collection/immutable/RedBlack;

  Signature: length = 0x2
   00 17 

public scala.collection.immutable.RedBlack$Tree range(scala.Option, scala.Option);
  Code:
   Stack=3, Locals=3, Args_size=3
   0:	aload_0
   1:	aload_1
   2:	aload_2
   3:	invokevirtual	#31; //Method range:(Lscala/Option;Lscala/Option;)Lscala/collection/immutable/RedBlack$Empty$;
   6:	areturn
  LineNumberTable: 
   line 132: 0

  LocalVariableTable: 
   Start  Length  Slot  Name   Signature
   0      7      0    this       Lscala/collection/immutable/RedBlack$Empty$;
   0      7      1    from       Lscala/Option;
   0      7      2    until       Lscala/Option;

  Signature: length = 0x2
   00 1A 

public java.lang.Object first();
  Code:
   Stack=1, Locals=1, Args_size=1
   0:	aload_0
   1:	invokevirtual	#39; //Method first:()Lscala/runtime/Nothing$;
   4:	athrow
  LineNumberTable: 
   line 132: 0


public java.lang.Object last();
  Code:
   Stack=1, Locals=1, Args_size=1
   0:	aload_0
   1:	invokevirtual	#42; //Method last:()Lscala/runtime/Nothing$;
   4:	athrow
  LineNumberTable: 
   line 132: 0


public scala.collection.immutable.RedBlack scala$collection$immutable$RedBlack$Empty$$$outer();
  Code:
   Stack=1, Locals=1, Args_size=1
   0:	aload_0
   1:	getfield	#46; //Field scala/collection/immutable/RedBlack$Tree.$outer:Lscala/collection/immutable/RedBlack;
   4:	areturn
  LineNumberTable: 
   line 132: 0


public java.lang.Object readResolve();
  Code:
   Stack=1, Locals=1, Args_size=1
   0:	aload_0
   1:	invokevirtual	#49; //Method scala$collection$immutable$RedBlack$Empty$$$outer:()Lscala/collection/immutable/RedBlack;
   4:	invokevirtual	#55; //Method scala/collection/immutable/RedBlack.Empty:()Lscala/collection/immutable/RedBlack$Empty$;
   7:	areturn
  LineNumberTable: 
   line 132: 0


public boolean canEqual(java.lang.Object);
  Code:
   Stack=1, Locals=2, Args_size=2
   0:	aload_1
   1:	instanceof	#28; //class scala/collection/immutable/RedBlack$Empty$
   4:	ireturn
  LineNumberTable: 
   line 132: 0


public java.lang.Object productElement(int);
  Code:
   Stack=3, Locals=2, Args_size=2
   0:	iconst_1
   1:	ifeq	19
   4:	new	#61; //class java/lang/IndexOutOfBoundsException
   7:	dup
   8:	iload_1
   9:	invokestatic	#67; //Method scala/runtime/BoxesRunTime.boxToInteger:(I)Ljava/lang/Integer;
   12:	invokevirtual	#73; //Method java/lang/Object.toString:()Ljava/lang/String;
   15:	invokespecial	#76; //Method java/lang/IndexOutOfBoundsException."<init>":(Ljava/lang/String;)V
   18:	athrow
   19:	new	#78; //class scala/MatchError
   22:	dup
   23:	iload_1
   24:	invokestatic	#67; //Method scala/runtime/BoxesRunTime.boxToInteger:(I)Ljava/lang/Integer;
   27:	invokevirtual	#73; //Method java/lang/Object.toString:()Ljava/lang/String;
   30:	invokespecial	#79; //Method scala/MatchError."<init>":(Ljava/lang/String;)V
   33:	athrow
  LineNumberTable: 
   line 21: 0
   line 132: 4


public int productArity();
  Code:
   Stack=1, Locals=1, Args_size=1
   0:	iconst_0
   1:	ireturn
  LineNumberTable: 
   line 132: 0


public java.lang.String productPrefix();
  Code:
   Stack=1, Locals=1, Args_size=1
   0:	ldc	#83; //String Empty
   2:	areturn
  LineNumberTable: 
   line 132: 0


public final java.lang.String toString();
  Code:
   Stack=1, Locals=1, Args_size=1
   0:	ldc	#83; //String Empty
   2:	areturn
  LineNumberTable: 
   line 132: 0


public int count();
  Code:
   Stack=1, Locals=1, Args_size=1
   0:	iconst_0
   1:	ireturn
  LineNumberTable: 
   line 150: 0


public scala.runtime.Nothing$ last();
  Code:
   Stack=3, Locals=1, Args_size=1
   0:	new	#86; //class java/util/NoSuchElementException
   3:	dup
   4:	ldc	#88; //String empty map
   6:	invokespecial	#89; //Method java/util/NoSuchElementException."<init>":(Ljava/lang/String;)V
   9:	athrow
  LineNumberTable: 
   line 149: 0


public scala.runtime.Nothing$ first();
  Code:
   Stack=3, Locals=1, Args_size=1
   0:	new	#86; //class java/util/NoSuchElementException
   3:	dup
   4:	ldc	#88; //String empty map
   6:	invokespecial	#89; //Method java/util/NoSuchElementException."<init>":(Ljava/lang/String;)V
   9:	athrow
  LineNumberTable: 
   line 148: 0


public scala.collection.immutable.RedBlack$Empty$ range(scala.Option, scala.Option);
  Code:
   Stack=1, Locals=3, Args_size=3
   0:	aload_0
   1:	areturn
  LineNumberTable: 
   line 147: 0

  LocalVariableTable: 
   Start  Length  Slot  Name   Signature
   0      2      0    this       Lscala/collection/immutable/RedBlack$Empty$;
   0      2      1    from       Lscala/Option;
   0      2      2    until       Lscala/Option;

  Signature: length = 0x2
   00 5A 

public scala.Tuple2 visit(java.lang.Object, scala.Function3);
  Code:
   Stack=4, Locals=4, Args_size=3
   0:	new	#94; //class scala/Tuple2
   3:	dup
   4:	iconst_1
   5:	istore_3
   6:	iload_3
   7:	invokestatic	#98; //Method scala/runtime/BoxesRunTime.boxToBoolean:(Z)Ljava/lang/Boolean;
   10:	aload_1
   11:	invokespecial	#101; //Method scala/Tuple2."<init>":(Ljava/lang/Object;Ljava/lang/Object;)V
   14:	areturn
  LineNumberTable: 
   line 145: 0

  LocalVariableTable: 
   Start  Length  Slot  Name   Signature
   0      15      0    this       Lscala/collection/immutable/RedBlack$Empty$;
   0      15      1    input       Ljava/lang/Object;
   0      15      2    f       Lscala/Function3;

  Signature: length = 0x2
   00 6A 
  Deprecated: true

public void foreach(scala.Function2);
  Code:
   Stack=0, Locals=2, Args_size=2
   0:	return
  LineNumberTable: 
   line 142: 0

  LocalVariableTable: 
   Start  Length  Slot  Name   Signature
   0      1      0    this       Lscala/collection/immutable/RedBlack$Empty$;
   0      1      1    f       Lscala/Function2;

  Signature: length = 0x2
   00 6F 

public scala.collection.immutable.Stream toStream();
  Code:
   Stack=1, Locals=1, Args_size=1
   0:	getstatic	#119; //Field scala/collection/immutable/Stream$.MODULE$:Lscala/collection/immutable/Stream$;
   3:	invokevirtual	#122; //Method scala/collection/immutable/Stream$.empty:()Lscala/collection/immutable/Stream;
   6:	areturn
  LineNumberTable: 
   line 140: 0

  Signature: length = 0x2
   00 7B 

public scala.collection.Iterator iterator();
  Code:
   Stack=1, Locals=1, Args_size=1
   0:	getstatic	#130; //Field scala/collection/Iterator$.MODULE$:Lscala/collection/Iterator$;
   3:	invokevirtual	#132; //Method scala/collection/Iterator$.empty:()Ljava/lang/Object;
   6:	checkcast	#134; //class scala/collection/Iterator
   9:	areturn
  LineNumberTable: 
   line 139: 0

  Signature: length = 0x2
   00 FFFFFF87 

public scala.collection.immutable.RedBlack$NonEmpty smallest();
  Code:
   Stack=3, Locals=1, Args_size=1
   0:	new	#86; //class java/util/NoSuchElementException
   3:	dup
   4:	ldc	#88; //String empty map
   6:	invokespecial	#89; //Method java/util/NoSuchElementException."<init>":(Ljava/lang/String;)V
   9:	athrow
  LineNumberTable: 
   line 138: 0

  Signature: length = 0x2
   00 FFFFFF8A 

public scala.collection.immutable.RedBlack$Tree del(java.lang.Object);
  Code:
   Stack=1, Locals=2, Args_size=2
   0:	aload_0
   1:	areturn
  LineNumberTable: 
   line 137: 0

  LocalVariableTable: 
   Start  Length  Slot  Name   Signature
   0      2      0    this       Lscala/collection/immutable/RedBlack$Empty$;
   0      2      1    k       Ljava/lang/Object;

  Signature: length = 0x2
   00 FFFFFF8E 

public scala.collection.immutable.RedBlack$Tree upd(java.lang.Object, java.lang.Object);
  Code:
   Stack=7, Locals=3, Args_size=3
   0:	new	#146; //class scala/collection/immutable/RedBlack$RedTree
   3:	dup
   4:	aload_0
   5:	invokevirtual	#49; //Method scala$collection$immutable$RedBlack$Empty$$$outer:()Lscala/collection/immutable/RedBlack;
   8:	aload_1
   9:	aload_2
   10:	aload_0
   11:	invokevirtual	#49; //Method scala$collection$immutable$RedBlack$Empty$$$outer:()Lscala/collection/immutable/RedBlack;
   14:	invokevirtual	#55; //Method scala/collection/immutable/RedBlack.Empty:()Lscala/collection/immutable/RedBlack$Empty$;
   17:	aload_0
   18:	invokevirtual	#49; //Method scala$collection$immutable$RedBlack$Empty$$$outer:()Lscala/collection/immutable/RedBlack;
   21:	invokevirtual	#55; //Method scala/collection/immutable/RedBlack.Empty:()Lscala/collection/immutable/RedBlack$Empty$;
   24:	invokespecial	#149; //Method scala/collection/immutable/RedBlack$RedTree."<init>":(Lscala/collection/immutable/RedBlack;Ljava/lang/Object;Ljava/lang/Object;Lscala/collection/immutable/RedBlack$Tree;Lscala/collection/immutable/RedBlack$Tree;)V
   27:	areturn
  LineNumberTable: 
   line 136: 0

  LocalVariableTable: 
   Start  Length  Slot  Name   Signature
   0      28      0    this       Lscala/collection/immutable/RedBlack$Empty$;
   0      28      1    k       Ljava/lang/Object;
   0      28      2    v       Ljava/lang/Object;

  Signature: length = 0x2
   00 FFFFFF97 

public scala.collection.immutable.RedBlack$Tree lookup(java.lang.Object);
  Code:
   Stack=1, Locals=2, Args_size=2
   0:	aload_0
   1:	areturn
  LineNumberTable: 
   line 135: 0

  LocalVariableTable: 
   Start  Length  Slot  Name   Signature
   0      2      0    this       Lscala/collection/immutable/RedBlack$Empty$;
   0      2      1    k       Ljava/lang/Object;

  Signature: length = 0x2
   00 FFFFFF8E 

public boolean isBlack();
  Code:
   Stack=1, Locals=1, Args_size=1
   0:	iconst_1
   1:	ireturn
  LineNumberTable: 
   line 134: 0


public boolean isEmpty();
  Code:
   Stack=1, Locals=1, Args_size=1
   0:	iconst_1
   1:	ireturn
  LineNumberTable: 
   line 133: 0


public scala.collection.Iterator productElements();
  Code:
   Stack=1, Locals=1, Args_size=1
   0:	aload_0
   1:	invokestatic	#159; //Method scala/Product$class.productElements:(Lscala/Product;)Lscala/collection/Iterator;
   4:	areturn
  LineNumberTable: 
   line 132: 0

  Deprecated: true

public scala.collection.Iterator productIterator();
  Code:
   Stack=1, Locals=1, Args_size=1
   0:	aload_0
   1:	invokestatic	#162; //Method scala/Product$class.productIterator:(Lscala/Product;)Lscala/collection/Iterator;
   4:	areturn
  LineNumberTable: 
   line 132: 0


}

