Compiled from "RedBlack.scala"
public abstract class scala.collection.immutable.RedBlack$Tree extends java.lang.Object implements scala.ScalaObject,java.io.Serializable
  SourceFile: "RedBlack.scala"
  Scala: length = 0x
   
  Signature: length = 0x2
   00 54 
  InnerClass: 
   public abstract Tree=class scala/collection/immutable/RedBlack$Tree of class scala/collection/immutable/RedBlack
   public abstract NonEmpty=class scala/collection/immutable/RedBlack$NonEmpty of class scala/collection/immutable/RedBlack
  minor version: 0
  major version: 49
  Constant pool:
Asciz	SourceFile;
Asciz	RedBlack.scala;
Asciz	$outer;
Asciz	Lscala/collection/immutable/RedBlack;;
Asciz	isEmpty;
Asciz	()Z;
Asciz	isBlack;
Asciz	lookup;
Asciz	(Ljava/lang/Object;)Lscala/collection/immutable/RedBlack$Tree;;
Asciz	(TA;)Lscala/collection/immutable/RedBlack<TA;>.Tree<TB;>;;
Asciz	Signature;
Asciz	update;
Asciz	(Ljava/lang/Object;Ljava/lang/Object;)Lscala/collection/immutable/RedBlack$Tree;;
Asciz	Code;
Asciz	LineNumberTable;
Asciz	scala/collection/immutable/RedBlack$Tree;
class	scala/collection/immutable/RedBlack$Tree
Asciz	scala$collection$immutable$RedBlack$Tree$$$outer;
Asciz	()Lscala/collection/immutable/RedBlack;;
NameAndType	scala$collection$immutable$RedBlack$Tree$$$outer:()Lscala/collection/immutable/RedBlack;
Method	scala/collection/immutable/RedBlack$Tree.scala$collection$immutable$RedBlack$Tree$$$outer:()Lscala/collection/immutable/RedBlack;
Asciz	upd;
NameAndType	upd:(Ljava/lang/Object;Ljava/lang/Object;)Lscala/collection/immutable/RedBlack$Tree;
Method	scala/collection/immutable/RedBlack$Tree.upd:(Ljava/lang/Object;Ljava/lang/Object;)Lscala/collection/immutable/RedBlack$Tree;
Asciz	scala/collection/immutable/RedBlack;
class	scala/collection/immutable/RedBlack
Asciz	scala$collection$immutable$RedBlack$$blacken;
Asciz	(Lscala/collection/immutable/RedBlack$Tree;)Lscala/collection/immutable/RedBlack$Tree;;
NameAndType	scala$collection$immutable$RedBlack$$blacken:(Lscala/collection/immutable/RedBlack$Tree;)Lscala/collection/immutable/RedBlack$Tree;
Method	scala/collection/immutable/RedBlack.scala$collection$immutable$RedBlack$$blacken:(Lscala/collection/immutable/RedBlack$Tree;)Lscala/collection/immutable/RedBlack$Tree;
Asciz	this;
Asciz	Lscala/collection/immutable/RedBlack$Tree;;
Asciz	k;
Asciz	Ljava/lang/Object;;
Asciz	v;
Asciz	LocalVariableTable;
Asciz	<B1:Ljava/lang/Object;>(TA;TB1;)Lscala/collection/immutable/RedBlack<TA;>.Tree<TB1;>;;
Asciz	delete;
Asciz	del;
NameAndType	del:(Ljava/lang/Object;)Lscala/collection/immutable/RedBlack$Tree;
Method	scala/collection/immutable/RedBlack$Tree.del:(Ljava/lang/Object;)Lscala/collection/immutable/RedBlack$Tree;
Asciz	foreach;
Asciz	(Lscala/Function2;)V;
Asciz	<U:Ljava/lang/Object;>(Lscala/Function2<TA;TB;TU;>;)V;
Asciz	visit;
Asciz	(Ljava/lang/Object;Lscala/Function3;)Lscala/Tuple2;;
Asciz	<T:Ljava/lang/Object;>(TT;Lscala/Function3<TT;TA;TB;Lscala/Tuple2<Ljava/lang/Boolean;TT;>;>;)Lscala/Tuple2<Ljava/lang/Boolean;TT;>;;
Asciz	Deprecated;
Asciz	toStream;
Asciz	()Lscala/collection/immutable/Stream;;
Asciz	()Lscala/collection/immutable/Stream<Lscala/Tuple2<TA;TB;>;>;;
Asciz	iterator;
Asciz	()Lscala/collection/Iterator;;
Asciz	()Lscala/collection/Iterator<Lscala/Tuple2<TA;TB;>;>;;
Asciz	elements;
NameAndType	iterator:()Lscala/collection/Iterator;
Method	scala/collection/immutable/RedBlack$Tree.iterator:()Lscala/collection/Iterator;
Asciz	smallest;
Asciz	()Lscala/collection/immutable/RedBlack$NonEmpty;;
Asciz	()Lscala/collection/immutable/RedBlack<TA;>.NonEmpty<TB;>;;
Asciz	range;
Asciz	(Lscala/Option;Lscala/Option;)Lscala/collection/immutable/RedBlack$Tree;;
Asciz	(Lscala/Option<TA;>;Lscala/Option<TA;>;)Lscala/collection/immutable/RedBlack<TA;>.Tree<TB;>;;
Asciz	first;
Asciz	()Ljava/lang/Object;;
Asciz	()TA;;
Asciz	last;
Asciz	count;
Asciz	()I;
NameAndType	$outer:Lscala/collection/immutable/RedBlack;
Field	scala/collection/immutable/RedBlack$Tree.$outer:Lscala/collection/immutable/RedBlack;
Asciz	<init>;
Asciz	(Lscala/collection/immutable/RedBlack;)V;
Asciz	java/lang/NullPointerException;
class	java/lang/NullPointerException
Asciz	()V;
NameAndType	"<init>":()V
Method	java/lang/NullPointerException."<init>":()V
Asciz	java/lang/Object;
class	java/lang/Object
Method	java/lang/Object."<init>":()V
Asciz	(Lscala/collection/immutable/RedBlack<TA;>;)V;
Asciz	Scala;
Asciz	<B:Ljava/lang/Object;>Ljava/lang/Object;Lscala/ScalaObject;;
Asciz	InnerClasses;
Asciz	Tree;
Asciz	scala/collection/immutable/RedBlack$NonEmpty;
class	scala/collection/immutable/RedBlack$NonEmpty
Asciz	NonEmpty;
Asciz	scala/ScalaObject;
class	scala/ScalaObject
Asciz	java/io/Serializable;
class	java/io/Serializable

{
public final scala.collection.immutable.RedBlack $outer;
  Signature: Lscala/collection/immutable/RedBlack;

public abstract boolean isEmpty();
  Signature: ()Z

public abstract boolean isBlack();
  Signature: ()Z

public abstract scala.collection.immutable.RedBlack$Tree lookup(java.lang.Object);
  Signature: (Ljava/lang/Object;)Lscala/collection/immutable/RedBlack$Tree;
  Signature: length = 0x2
   00 0A 

public scala.collection.immutable.RedBlack$Tree update(java.lang.Object, java.lang.Object);
  Signature: (Ljava/lang/Object;Ljava/lang/Object;)Lscala/collection/immutable/RedBlack$Tree;
  Code:
   Stack=4, Locals=3, Args_size=3
	aload_0
	invokevirtual	Method scala$collection$immutable$RedBlack$Tree$$$outer:()Lscala/collection/immutable/RedBlack;
	aload_0
	aload_1
	aload_2
	invokevirtual	Method upd:(Ljava/lang/Object;Ljava/lang/Object;)Lscala/collection/immutable/RedBlack$Tree;
	invokevirtual	Method scala/collection/immutable/RedBlack.scala$collection$immutable$RedBlack$$blacken:(Lscala/collection/immutable/RedBlack$Tree;)Lscala/collection/immutable/RedBlack$Tree;
	areturn
  Labels:
  LocalVariableTable: 
   Start  Length  Slot  Name   Signature
   0      14      0    this       Lscala/collection/immutable/RedBlack$Tree;
   0      14      1    k       Ljava/lang/Object;
   0      14      2    v       Ljava/lang/Object;

  Signature: length = 0x2
   00 25 

public scala.collection.immutable.RedBlack$Tree delete(java.lang.Object);
  Signature: (Ljava/lang/Object;)Lscala/collection/immutable/RedBlack$Tree;
  Code:
   Stack=3, Locals=2, Args_size=2
	aload_0
	invokevirtual	Method scala$collection$immutable$RedBlack$Tree$$$outer:()Lscala/collection/immutable/RedBlack;
	aload_0
	aload_1
	invokevirtual	Method del:(Ljava/lang/Object;)Lscala/collection/immutable/RedBlack$Tree;
	invokevirtual	Method scala/collection/immutable/RedBlack.scala$collection$immutable$RedBlack$$blacken:(Lscala/collection/immutable/RedBlack$Tree;)Lscala/collection/immutable/RedBlack$Tree;
	areturn
  Labels:
  LocalVariableTable: 
   Start  Length  Slot  Name   Signature
   0      13      0    this       Lscala/collection/immutable/RedBlack$Tree;
   0      13      1    k       Ljava/lang/Object;

  Signature: length = 0x2
   00 0A 

public abstract void foreach(scala.Function2);
  Signature: (Lscala/Function2;)V
  Signature: length = 0x2
   00 2C 

public abstract scala.Tuple2 visit(java.lang.Object, scala.Function3);
  Signature: (Ljava/lang/Object;Lscala/Function3;)Lscala/Tuple2;
  Signature: length = 0x2
   00 2F 
  Deprecated: true

public abstract scala.collection.immutable.Stream toStream();
  Signature: ()Lscala/collection/immutable/Stream;
  Signature: length = 0x2
   00 33 

public abstract scala.collection.Iterator iterator();
  Signature: ()Lscala/collection/Iterator;
  Signature: length = 0x2
   00 36 

public scala.collection.Iterator elements();
  Signature: ()Lscala/collection/Iterator;
  Code:
   Stack=1, Locals=1, Args_size=1
	aload_0
	invokevirtual	Method iterator:()Lscala/collection/Iterator;
	areturn
  Labels:
  Signature: length = 0x2
   00 36 
  Deprecated: true

public abstract scala.collection.immutable.RedBlack$Tree upd(java.lang.Object, java.lang.Object);
  Signature: (Ljava/lang/Object;Ljava/lang/Object;)Lscala/collection/immutable/RedBlack$Tree;
  Signature: length = 0x2
   00 25 

public abstract scala.collection.immutable.RedBlack$Tree del(java.lang.Object);
  Signature: (Ljava/lang/Object;)Lscala/collection/immutable/RedBlack$Tree;
  Signature: length = 0x2
   00 0A 

public abstract scala.collection.immutable.RedBlack$NonEmpty smallest();
  Signature: ()Lscala/collection/immutable/RedBlack$NonEmpty;
  Signature: length = 0x2
   00 3C 

public abstract scala.collection.immutable.RedBlack$Tree range(scala.Option, scala.Option);
  Signature: (Lscala/Option;Lscala/Option;)Lscala/collection/immutable/RedBlack$Tree;
  Signature: length = 0x2
   00 3F 

public abstract java.lang.Object first();
  Signature: ()Ljava/lang/Object;
  Signature: length = 0x2
   00 42 

public abstract java.lang.Object last();
  Signature: ()Ljava/lang/Object;
  Signature: length = 0x2
   00 42 

public abstract int count();
  Signature: ()I

public scala.collection.immutable.RedBlack scala$collection$immutable$RedBlack$Tree$$$outer();
  Signature: ()Lscala/collection/immutable/RedBlack;
  Code:
   Stack=1, Locals=1, Args_size=1
	aload_0
	getfield	Field $outer:Lscala/collection/immutable/RedBlack;
	areturn
  Labels:

public scala.collection.immutable.RedBlack$Tree(scala.collection.immutable.RedBlack);
  Signature: (Lscala/collection/immutable/RedBlack;)V
  Code:
   Stack=2, Locals=2, Args_size=2
	aload_1
	ifnonnull	l1 // aload_0
	new	class java/lang/NullPointerException
	dup
	invokespecial	Method java/lang/NullPointerException."<init>":()V
	athrow
l1	aload_0
	aload_1
	putfield	Field $outer:Lscala/collection/immutable/RedBlack;
	aload_0
	invokespecial	Method java/lang/Object."<init>":()V
	return
  Labels:
   	l1 = 12 // aload_0
  LocalVariableTable: 
   Start  Length  Slot  Name   Signature
   0      22      0    this       Lscala/collection/immutable/RedBlack$Tree;
   0      22      1    $outer       Lscala/collection/immutable/RedBlack;

  Signature: length = 0x2
   00 52 

}

