Compiled from "RedBlack.scala"
public final class scala.collection.immutable.RedBlack$NonEmpty$$anonfun$iterator$1 extends java.lang.Object implements scala.Function0,scala.ScalaObject,java.io.Serializable
  SourceFile: "RedBlack.scala"
  Scala: length = 0x
   
  InnerClass: 
   public abstract NonEmpty=class scala/collection/immutable/RedBlack$NonEmpty of class scala/collection/immutable/RedBlack
   public final $anonfun$iterator$1=class scala/collection/immutable/RedBlack$NonEmpty$$anonfun$iterator$1 of class scala/collection/immutable/RedBlack$NonEmpty
  minor version: 0
  major version: 49
  Constant pool:
Asciz	SourceFile;
Asciz	RedBlack.scala;
Asciz	<clinit>;
Asciz	()V;
Asciz	Code;
Asciz	serialVersionUID;
Asciz	J;
Asciz	scala/collection/immutable/RedBlack$NonEmpty$$anonfun$iterator$1;
class	scala/collection/immutable/RedBlack$NonEmpty$$anonfun$iterator$1
NameAndType	serialVersionUID:J
Field	scala/collection/immutable/RedBlack$NonEmpty$$anonfun$iterator$1.serialVersionUID:J
Asciz	$outer;
Asciz	Lscala/collection/immutable/RedBlack$NonEmpty;;
Asciz	<init>;
Asciz	(Lscala/collection/immutable/RedBlack$NonEmpty;)V;
Asciz	LineNumberTable;
Asciz	java/lang/NullPointerException;
class	java/lang/NullPointerException
NameAndType	"<init>":()V
Method	java/lang/NullPointerException."<init>":()V
NameAndType	$outer:Lscala/collection/immutable/RedBlack$NonEmpty;
Field	scala/collection/immutable/RedBlack$NonEmpty$$anonfun$iterator$1.$outer:Lscala/collection/immutable/RedBlack$NonEmpty;
Asciz	java/lang/Object;
class	java/lang/Object
Method	java/lang/Object."<init>":()V
Asciz	scala/Function0$class;
class	scala/Function0$class
Asciz	$init$;
Asciz	(Lscala/Function0;)V;
NameAndType	$init$:(Lscala/Function0;)V
Method	scala/Function0$class.$init$:(Lscala/Function0;)V
Asciz	this;
Asciz	Lscala/collection/immutable/RedBlack$NonEmpty$$anonfun$iterator$1;;
Asciz	LocalVariableTable;
Asciz	(Lscala/collection/immutable/RedBlack<TA;>.NonEmpty<TB;>;)V;
Asciz	Signature;
Asciz	apply;
Asciz	()Ljava/lang/Object;;
Asciz	scala/collection/Iterator$;
class	scala/collection/Iterator$
Asciz	MODULE$;
Asciz	Lscala/collection/Iterator$;;
NameAndType	MODULE$:Lscala/collection/Iterator$;
Field	scala/collection/Iterator$.MODULE$:Lscala/collection/Iterator$;
Asciz	scala/Predef$Pair$;
class	scala/Predef$Pair$
Asciz	Lscala/Predef$Pair$;;
NameAndType	MODULE$:Lscala/Predef$Pair$;
Field	scala/Predef$Pair$.MODULE$:Lscala/Predef$Pair$;
Asciz	scala/collection/immutable/RedBlack$NonEmpty;
class	scala/collection/immutable/RedBlack$NonEmpty
Asciz	key;
NameAndType	key:()Ljava/lang/Object;
Method	scala/collection/immutable/RedBlack$NonEmpty.key:()Ljava/lang/Object;
Asciz	value;
NameAndType	value:()Ljava/lang/Object;
Method	scala/collection/immutable/RedBlack$NonEmpty.value:()Ljava/lang/Object;
Asciz	(Ljava/lang/Object;Ljava/lang/Object;)Lscala/Tuple2;;
NameAndType	apply:(Ljava/lang/Object;Ljava/lang/Object;)Lscala/Tuple2;
Method	scala/Predef$Pair$.apply:(Ljava/lang/Object;Ljava/lang/Object;)Lscala/Tuple2;
Asciz	single;
Asciz	(Ljava/lang/Object;)Ljava/lang/Object;;
NameAndType	single:(Ljava/lang/Object;)Ljava/lang/Object;
Method	scala/collection/Iterator$.single:(Ljava/lang/Object;)Ljava/lang/Object;
Asciz	toString;
Asciz	()Ljava/lang/String;;
Asciz	(Lscala/Function0;)Ljava/lang/String;;
NameAndType	toString:(Lscala/Function0;)Ljava/lang/String;
Method	scala/Function0$class.toString:(Lscala/Function0;)Ljava/lang/String;
Asciz	Scala;
Asciz	InnerClasses;
Asciz	scala/collection/immutable/RedBlack;
class	scala/collection/immutable/RedBlack
Asciz	NonEmpty;
Asciz	$anonfun$iterator$1;
Asciz	scala/Function0;
class	scala/Function0
Asciz	scala/ScalaObject;
class	scala/ScalaObject
Asciz	java/io/Serializable;
class	java/io/Serializable

{
public static final long serialVersionUID;
  Signature: J

private final scala.collection.immutable.RedBlack$NonEmpty $outer;
  Signature: Lscala/collection/immutable/RedBlack$NonEmpty;

public static {};
  Signature: ()V
  Code:
   Stack=2, Locals=0, Args_size=0
	lconst_0
	putstatic	Field serialVersionUID:J
	return
  Labels:

public scala.collection.immutable.RedBlack$NonEmpty$$anonfun$iterator$1(scala.collection.immutable.RedBlack$NonEmpty);
  Signature: (Lscala/collection/immutable/RedBlack$NonEmpty;)V
  Code:
   Stack=2, Locals=2, Args_size=2
	aload_1
	ifnonnull	l1 // aload_0
	new	class java/lang/NullPointerException
	dup
	invokespecial	Method java/lang/NullPointerException."<init>":()V
	athrow
l1	aload_0
	aload_1
	putfield	Field $outer:Lscala/collection/immutable/RedBlack$NonEmpty;
	aload_0
	invokespecial	Method java/lang/Object."<init>":()V
	aload_0
	invokestatic	Method scala/Function0$class.$init$:(Lscala/Function0;)V
	return
  Labels:
   	l1 = 12 // aload_0
  LocalVariableTable: 
   Start  Length  Slot  Name   Signature
   0      26      0    this       Lscala/collection/immutable/RedBlack$NonEmpty$$anonfun$iterator$1;
   0      26      1    $outer       Lscala/collection/immutable/RedBlack$NonEmpty;

  Signature: length = 0x2
   00 23 

public final java.lang.Object apply();
  Signature: ()Ljava/lang/Object;
  Code:
   Stack=4, Locals=2, Args_size=1
	aload_0
	getfield	Field $outer:Lscala/collection/immutable/RedBlack$NonEmpty;
	astore_1
	getstatic	Field scala/collection/Iterator$.MODULE$:Lscala/collection/Iterator$;
	getstatic	Field scala/Predef$Pair$.MODULE$:Lscala/Predef$Pair$;
	aload_0
	getfield	Field $outer:Lscala/collection/immutable/RedBlack$NonEmpty;
	invokevirtual	Method scala/collection/immutable/RedBlack$NonEmpty.key:()Ljava/lang/Object;
	aload_0
	getfield	Field $outer:Lscala/collection/immutable/RedBlack$NonEmpty;
	invokevirtual	Method scala/collection/immutable/RedBlack$NonEmpty.value:()Ljava/lang/Object;
	invokevirtual	Method scala/Predef$Pair$.apply:(Ljava/lang/Object;Ljava/lang/Object;)Lscala/Tuple2;
	invokevirtual	Method scala/collection/Iterator$.single:(Ljava/lang/Object;)Ljava/lang/Object;
	areturn
  Labels:
  LocalVariableTable: 
   Start  Length  Slot  Name   Signature
   0      32      0    this       Lscala/collection/immutable/RedBlack$NonEmpty$$anonfun$iterator$1;


public java.lang.String toString();
  Signature: ()Ljava/lang/String;
  Code:
   Stack=1, Locals=1, Args_size=1
	aload_0
	invokestatic	Method scala/Function0$class.toString:(Lscala/Function0;)Ljava/lang/String;
	areturn
  Labels:

}

