Compiled from "RedBlack.scala"
public abstract class scala.collection.immutable.RedBlack$NonEmpty extends scala.collection.immutable.RedBlack$Tree implements scala.ScalaObject,java.io.Serializable
  SourceFile: "RedBlack.scala"
  Signature: length = 0x2
   01 1F 
  Scala: length = 0x
   
  InnerClass: 
   public abstract #290= #8 of #58; //Tree=class scala/collection/immutable/RedBlack$Tree of class scala/collection/immutable/RedBlack
   public #291= #21 of #58; //RedTree=class scala/collection/immutable/RedBlack$RedTree of class scala/collection/immutable/RedBlack
   public abstract #292= #37 of #58; //NonEmpty=class scala/collection/immutable/RedBlack$NonEmpty of class scala/collection/immutable/RedBlack
   public #293= #43 of #58; //BlackTree=class scala/collection/immutable/RedBlack$BlackTree of class scala/collection/immutable/RedBlack
   public final #294= #225 of #37; //$anonfun$iterator$2=class scala/collection/immutable/RedBlack$NonEmpty$$anonfun$iterator$2 of class scala/collection/immutable/RedBlack$NonEmpty
   public final #295= #214 of #37; //$anonfun$iterator$1=class scala/collection/immutable/RedBlack$NonEmpty$$anonfun$iterator$1 of class scala/collection/immutable/RedBlack$NonEmpty
  minor version: 0
  major version: 49
  Constant pool:
const #1 = Asciz	SourceFile;
const #2 = Asciz	RedBlack.scala;
const #3 = Asciz	<init>;
const #4 = Asciz	(Lscala/collection/immutable/RedBlack;)V;
const #5 = Asciz	Code;
const #6 = Asciz	LineNumberTable;
const #7 = Asciz	scala/collection/immutable/RedBlack$Tree;
const #8 = class	#7;	//  scala/collection/immutable/RedBlack$Tree
const #9 = NameAndType	#3:#4;//  "<init>":(Lscala/collection/immutable/RedBlack;)V
const #10 = Method	#8.#9;	//  scala/collection/immutable/RedBlack$Tree."<init>":(Lscala/collection/immutable/RedBlack;)V
const #11 = Asciz	this;
const #12 = Asciz	Lscala/collection/immutable/RedBlack$NonEmpty;;
const #13 = Asciz	$outer;
const #14 = Asciz	Lscala/collection/immutable/RedBlack;;
const #15 = Asciz	LocalVariableTable;
const #16 = Asciz	(Lscala/collection/immutable/RedBlack<TA;>;)V;
const #17 = Asciz	Signature;
const #18 = Asciz	balanceRight$1;
const #19 = Asciz	(ZLjava/lang/Object;Ljava/lang/Object;Lscala/collection/immutable/RedBlack$Tree;Lscala/collection/immutable/RedBlack$Tree;)Lscala/Product;;
const #20 = Asciz	scala/collection/immutable/RedBlack$RedTree;
const #21 = class	#20;	//  scala/collection/immutable/RedBlack$RedTree
const #22 = Asciz	key;
const #23 = Asciz	()Ljava/lang/Object;;
const #24 = NameAndType	#22:#23;//  key:()Ljava/lang/Object;
const #25 = Method	#21.#24;	//  scala/collection/immutable/RedBlack$RedTree.key:()Ljava/lang/Object;
const #26 = Asciz	value;
const #27 = NameAndType	#26:#23;//  value:()Ljava/lang/Object;
const #28 = Method	#21.#27;	//  scala/collection/immutable/RedBlack$RedTree.value:()Ljava/lang/Object;
const #29 = Asciz	left;
const #30 = Asciz	()Lscala/collection/immutable/RedBlack$Tree;;
const #31 = NameAndType	#29:#30;//  left:()Lscala/collection/immutable/RedBlack$Tree;
const #32 = Method	#21.#31;	//  scala/collection/immutable/RedBlack$RedTree.left:()Lscala/collection/immutable/RedBlack$Tree;
const #33 = Asciz	right;
const #34 = NameAndType	#33:#30;//  right:()Lscala/collection/immutable/RedBlack$Tree;
const #35 = Method	#21.#34;	//  scala/collection/immutable/RedBlack$RedTree.right:()Lscala/collection/immutable/RedBlack$Tree;
const #36 = Asciz	scala/collection/immutable/RedBlack$NonEmpty;
const #37 = class	#36;	//  scala/collection/immutable/RedBlack$NonEmpty
const #38 = Asciz	scala$collection$immutable$RedBlack$NonEmpty$$$outer;
const #39 = Asciz	()Lscala/collection/immutable/RedBlack;;
const #40 = NameAndType	#38:#39;//  scala$collection$immutable$RedBlack$NonEmpty$$$outer:()Lscala/collection/immutable/RedBlack;
const #41 = Method	#37.#40;	//  scala/collection/immutable/RedBlack$NonEmpty.scala$collection$immutable$RedBlack$NonEmpty$$$outer:()Lscala/collection/immutable/RedBlack;
const #42 = Asciz	scala/collection/immutable/RedBlack$BlackTree;
const #43 = class	#42;	//  scala/collection/immutable/RedBlack$BlackTree
const #44 = Asciz	(Lscala/collection/immutable/RedBlack;Ljava/lang/Object;Ljava/lang/Object;Lscala/collection/immutable/RedBlack$Tree;Lscala/collection/immutable/RedBlack$Tree;)V;
const #45 = NameAndType	#3:#44;//  "<init>":(Lscala/collection/immutable/RedBlack;Ljava/lang/Object;Ljava/lang/Object;Lscala/collection/immutable/RedBlack$Tree;Lscala/collection/immutable/RedBlack$Tree;)V
const #46 = Method	#43.#45;	//  scala/collection/immutable/RedBlack$BlackTree."<init>":(Lscala/collection/immutable/RedBlack;Ljava/lang/Object;Ljava/lang/Object;Lscala/collection/immutable/RedBlack$Tree;Lscala/collection/immutable/RedBlack$Tree;)V
const #47 = Method	#21.#45;	//  scala/collection/immutable/RedBlack$RedTree."<init>":(Lscala/collection/immutable/RedBlack;Ljava/lang/Object;Ljava/lang/Object;Lscala/collection/immutable/RedBlack$Tree;Lscala/collection/immutable/RedBlack$Tree;)V
const #48 = Asciz	scala/MatchError;
const #49 = class	#48;	//  scala/MatchError
const #50 = Asciz	toString;
const #51 = Asciz	()Ljava/lang/String;;
const #52 = NameAndType	#50:#51;//  toString:()Ljava/lang/String;
const #53 = Method	#8.#52;	//  scala/collection/immutable/RedBlack$Tree.toString:()Ljava/lang/String;
const #54 = Asciz	(Ljava/lang/String;)V;
const #55 = NameAndType	#3:#54;//  "<init>":(Ljava/lang/String;)V
const #56 = Method	#49.#55;	//  scala/MatchError."<init>":(Ljava/lang/String;)V
const #57 = Asciz	scala/collection/immutable/RedBlack;
const #58 = class	#57;	//  scala/collection/immutable/RedBlack
const #59 = Asciz	scala$collection$immutable$RedBlack$$mkTree;
const #60 = NameAndType	#59:#19;//  scala$collection$immutable$RedBlack$$mkTree:(ZLjava/lang/Object;Ljava/lang/Object;Lscala/collection/immutable/RedBlack$Tree;Lscala/collection/immutable/RedBlack$Tree;)Lscala/Product;
const #61 = Method	#58.#60;	//  scala/collection/immutable/RedBlack.scala$collection$immutable$RedBlack$$mkTree:(ZLjava/lang/Object;Ljava/lang/Object;Lscala/collection/immutable/RedBlack$Tree;Lscala/collection/immutable/RedBlack$Tree;)Lscala/Product;
const #62 = Asciz	isBlack;
const #63 = Asciz	Z;
const #64 = Asciz	x;
const #65 = Asciz	Ljava/lang/Object;;
const #66 = Asciz	xv;
const #67 = Asciz	a;
const #68 = Asciz	Lscala/collection/immutable/RedBlack$Tree;;
const #69 = Asciz	r;
const #70 = Asciz	temp24;
const #71 = Asciz	Lscala/collection/immutable/RedBlack$RedTree;;
const #72 = Asciz	temp29;
const #73 = Asciz	temp30;
const #74 = Asciz	temp31;
const #75 = Asciz	temp32;
const #76 = Asciz	temp33;
const #77 = Asciz	temp28;
const #78 = Asciz	temp34;
const #79 = Asciz	temp25;
const #80 = Asciz	temp26;
const #81 = Asciz	temp27;
const #82 = Asciz	temp35;
const #83 = Asciz	temp36;
const #84 = Asciz	temp37;
const #85 = Asciz	temp38;
const #86 = Asciz	balanceLeft$1;
const #87 = Asciz	z;
const #88 = Asciz	zv;
const #89 = Asciz	l;
const #90 = Asciz	d;
const #91 = Asciz	temp8;
const #92 = Asciz	temp13;
const #93 = Asciz	temp14;
const #94 = Asciz	temp15;
const #95 = Asciz	temp16;
const #96 = Asciz	temp17;
const #97 = Asciz	temp12;
const #98 = Asciz	temp18;
const #99 = Asciz	temp19;
const #100 = Asciz	temp20;
const #101 = Asciz	temp9;
const #102 = Asciz	temp10;
const #103 = Asciz	temp11;
const #104 = Asciz	temp21;
const #105 = Asciz	temp22;
const #106 = NameAndType	#13:#14;//  $outer:Lscala/collection/immutable/RedBlack;
const #107 = Field	#8.#106;	//  scala/collection/immutable/RedBlack$Tree.$outer:Lscala/collection/immutable/RedBlack;
const #108 = Asciz	count;
const #109 = Asciz	()I;
const #110 = Method	#37.#31;	//  scala/collection/immutable/RedBlack$NonEmpty.left:()Lscala/collection/immutable/RedBlack$Tree;
const #111 = NameAndType	#108:#109;//  count:()I
const #112 = Method	#8.#111;	//  scala/collection/immutable/RedBlack$Tree.count:()I
const #113 = Method	#37.#34;	//  scala/collection/immutable/RedBlack$NonEmpty.right:()Lscala/collection/immutable/RedBlack$Tree;
const #114 = Asciz	last;
const #115 = Asciz	isEmpty;
const #116 = Asciz	()Z;
const #117 = NameAndType	#115:#116;//  isEmpty:()Z
const #118 = Method	#8.#117;	//  scala/collection/immutable/RedBlack$Tree.isEmpty:()Z
const #119 = Method	#37.#24;	//  scala/collection/immutable/RedBlack$NonEmpty.key:()Ljava/lang/Object;
const #120 = NameAndType	#114:#23;//  last:()Ljava/lang/Object;
const #121 = Method	#8.#120;	//  scala/collection/immutable/RedBlack$Tree.last:()Ljava/lang/Object;
const #122 = Asciz	()TA;;
const #123 = Asciz	first;
const #124 = NameAndType	#123:#23;//  first:()Ljava/lang/Object;
const #125 = Method	#8.#124;	//  scala/collection/immutable/RedBlack$Tree.first:()Ljava/lang/Object;
const #126 = Asciz	range;
const #127 = Asciz	(Lscala/Option;Lscala/Option;)Lscala/collection/immutable/RedBlack$Tree;;
const #128 = Asciz	scala/None$;
const #129 = class	#128;	//  scala/None$
const #130 = Asciz	MODULE$;
const #131 = Asciz	Lscala/None$;;
const #132 = NameAndType	#130:#131;//  MODULE$:Lscala/None$;
const #133 = Field	#129.#132;	//  scala/None$.MODULE$:Lscala/None$;
const #134 = Asciz	java/lang/Object;
const #135 = class	#134;	//  java/lang/Object
const #136 = Asciz	equals;
const #137 = Asciz	(Ljava/lang/Object;)Z;
const #138 = NameAndType	#136:#137;//  equals:(Ljava/lang/Object;)Z
const #139 = Method	#135.#138;	//  java/lang/Object.equals:(Ljava/lang/Object;)Z
const #140 = Asciz	scala/Option;
const #141 = class	#140;	//  scala/Option
const #142 = Asciz	get;
const #143 = NameAndType	#142:#23;//  get:()Ljava/lang/Object;
const #144 = Method	#141.#143;	//  scala/Option.get:()Ljava/lang/Object;
const #145 = Asciz	isSmaller;
const #146 = Asciz	(Ljava/lang/Object;Ljava/lang/Object;)Z;
const #147 = NameAndType	#145:#146;//  isSmaller:(Ljava/lang/Object;Ljava/lang/Object;)Z
const #148 = Method	#58.#147;	//  scala/collection/immutable/RedBlack.isSmaller:(Ljava/lang/Object;Ljava/lang/Object;)Z
const #149 = NameAndType	#126:#127;//  range:(Lscala/Option;Lscala/Option;)Lscala/collection/immutable/RedBlack$Tree;
const #150 = Method	#8.#149;	//  scala/collection/immutable/RedBlack$Tree.range:(Lscala/Option;Lscala/Option;)Lscala/collection/immutable/RedBlack$Tree;
const #151 = Asciz	Empty;
const #152 = Asciz	()Lscala/collection/immutable/RedBlack$Empty$;;
const #153 = NameAndType	#151:#152;//  Empty:()Lscala/collection/immutable/RedBlack$Empty$;
const #154 = Method	#58.#153;	//  scala/collection/immutable/RedBlack.Empty:()Lscala/collection/immutable/RedBlack$Empty$;
const #155 = Method	#37.#27;	//  scala/collection/immutable/RedBlack$NonEmpty.value:()Ljava/lang/Object;
const #156 = Asciz	upd;
const #157 = Asciz	(Ljava/lang/Object;Ljava/lang/Object;)Lscala/collection/immutable/RedBlack$Tree;;
const #158 = NameAndType	#156:#157;//  upd:(Ljava/lang/Object;Ljava/lang/Object;)Lscala/collection/immutable/RedBlack$Tree;
const #159 = Method	#8.#158;	//  scala/collection/immutable/RedBlack$Tree.upd:(Ljava/lang/Object;Ljava/lang/Object;)Lscala/collection/immutable/RedBlack$Tree;
const #160 = NameAndType	#62:#116;//  isBlack:()Z
const #161 = Method	#37.#160;	//  scala/collection/immutable/RedBlack$NonEmpty.isBlack:()Z
const #162 = Asciz	from;
const #163 = Asciz	Lscala/Option;;
const #164 = Asciz	until;
const #165 = Asciz	newLeft;
const #166 = Asciz	newRight;
const #167 = Asciz	(Lscala/Option<TA;>;Lscala/Option<TA;>;)Lscala/collection/immutable/RedBlack<TA;>.Tree<TB;>;;
const #168 = Asciz	visit;
const #169 = Asciz	(Ljava/lang/Object;Lscala/Function3;)Lscala/Tuple2;;
const #170 = NameAndType	#168:#169;//  visit:(Ljava/lang/Object;Lscala/Function3;)Lscala/Tuple2;
const #171 = Method	#8.#170;	//  scala/collection/immutable/RedBlack$Tree.visit:(Ljava/lang/Object;Lscala/Function3;)Lscala/Tuple2;
const #172 = Asciz	scala/Tuple2;
const #173 = class	#172;	//  scala/Tuple2
const #174 = Asciz	_1;
const #175 = NameAndType	#174:#23;//  _1:()Ljava/lang/Object;
const #176 = Method	#173.#175;	//  scala/Tuple2._1:()Ljava/lang/Object;
const #177 = Asciz	scala/runtime/BoxesRunTime;
const #178 = class	#177;	//  scala/runtime/BoxesRunTime
const #179 = Asciz	unboxToBoolean;
const #180 = NameAndType	#179:#137;//  unboxToBoolean:(Ljava/lang/Object;)Z
const #181 = Method	#178.#180;	//  scala/runtime/BoxesRunTime.unboxToBoolean:(Ljava/lang/Object;)Z
const #182 = Asciz	_2;
const #183 = NameAndType	#182:#23;//  _2:()Ljava/lang/Object;
const #184 = Method	#173.#183;	//  scala/Tuple2._2:()Ljava/lang/Object;
const #185 = Asciz	scala/Function3;
const #186 = class	#185;	//  scala/Function3
const #187 = Asciz	apply;
const #188 = Asciz	(Ljava/lang/Object;Ljava/lang/Object;Ljava/lang/Object;)Ljava/lang/Object;;
const #189 = NameAndType	#187:#188;//  apply:(Ljava/lang/Object;Ljava/lang/Object;Ljava/lang/Object;)Ljava/lang/Object;
const #190 = InterfaceMethod	#186.#189;	//  scala/Function3.apply:(Ljava/lang/Object;Ljava/lang/Object;Ljava/lang/Object;)Ljava/lang/Object;
const #191 = Asciz	input;
const #192 = Asciz	f;
const #193 = Asciz	Lscala/Function3;;
const #194 = Asciz	Lscala/Tuple2;;
const #195 = Asciz	middle;
const #196 = Asciz	<T:Ljava/lang/Object;>(TT;Lscala/Function3<TT;TA;TB;Lscala/Tuple2<Ljava/lang/Boolean;TT;>;>;)Lscala/Tuple2<Ljava/lang/Boolean;TT;>;;
const #197 = Asciz	Deprecated;
const #198 = Asciz	foreach;
const #199 = Asciz	(Lscala/Function2;)V;
const #200 = NameAndType	#198:#199;//  foreach:(Lscala/Function2;)V
const #201 = Method	#8.#200;	//  scala/collection/immutable/RedBlack$Tree.foreach:(Lscala/Function2;)V
const #202 = Asciz	scala/Function2;
const #203 = class	#202;	//  scala/Function2
const #204 = Asciz	(Ljava/lang/Object;Ljava/lang/Object;)Ljava/lang/Object;;
const #205 = NameAndType	#187:#204;//  apply:(Ljava/lang/Object;Ljava/lang/Object;)Ljava/lang/Object;
const #206 = InterfaceMethod	#203.#205;	//  scala/Function2.apply:(Ljava/lang/Object;Ljava/lang/Object;)Ljava/lang/Object;
const #207 = Asciz	Lscala/Function2;;
const #208 = Asciz	<U:Ljava/lang/Object;>(Lscala/Function2<TA;TB;TU;>;)V;
const #209 = Asciz	iterator;
const #210 = Asciz	()Lscala/collection/Iterator;;
const #211 = NameAndType	#209:#210;//  iterator:()Lscala/collection/Iterator;
const #212 = Method	#8.#211;	//  scala/collection/immutable/RedBlack$Tree.iterator:()Lscala/collection/Iterator;
const #213 = Asciz	scala/collection/immutable/RedBlack$NonEmpty$$anonfun$iterator$1;
const #214 = class	#213;	//  scala/collection/immutable/RedBlack$NonEmpty$$anonfun$iterator$1
const #215 = Asciz	(Lscala/collection/immutable/RedBlack$NonEmpty;)V;
const #216 = NameAndType	#3:#215;//  "<init>":(Lscala/collection/immutable/RedBlack$NonEmpty;)V
const #217 = Method	#214.#216;	//  scala/collection/immutable/RedBlack$NonEmpty$$anonfun$iterator$1."<init>":(Lscala/collection/immutable/RedBlack$NonEmpty;)V
const #218 = Asciz	scala/collection/Iterator;
const #219 = class	#218;	//  scala/collection/Iterator
const #220 = Asciz	$plus$plus;
const #221 = Asciz	(Lscala/Function0;)Lscala/collection/Iterator;;
const #222 = NameAndType	#220:#221;//  $plus$plus:(Lscala/Function0;)Lscala/collection/Iterator;
const #223 = InterfaceMethod	#219.#222;	//  scala/collection/Iterator.$plus$plus:(Lscala/Function0;)Lscala/collection/Iterator;
const #224 = Asciz	scala/collection/immutable/RedBlack$NonEmpty$$anonfun$iterator$2;
const #225 = class	#224;	//  scala/collection/immutable/RedBlack$NonEmpty$$anonfun$iterator$2
const #226 = Method	#225.#216;	//  scala/collection/immutable/RedBlack$NonEmpty$$anonfun$iterator$2."<init>":(Lscala/collection/immutable/RedBlack$NonEmpty;)V
const #227 = Asciz	()Lscala/collection/Iterator<Lscala/Tuple2<TA;TB;>;>;;
const #228 = Asciz	toStream;
const #229 = Asciz	()Lscala/collection/immutable/Stream;;
const #230 = NameAndType	#228:#229;//  toStream:()Lscala/collection/immutable/Stream;
const #231 = Method	#8.#230;	//  scala/collection/immutable/RedBlack$Tree.toStream:()Lscala/collection/immutable/Stream;
const #232 = Asciz	scala/collection/immutable/Stream$;
const #233 = class	#232;	//  scala/collection/immutable/Stream$
const #234 = Asciz	Lscala/collection/immutable/Stream$;;
const #235 = NameAndType	#130:#234;//  MODULE$:Lscala/collection/immutable/Stream$;
const #236 = Field	#233.#235;	//  scala/collection/immutable/Stream$.MODULE$:Lscala/collection/immutable/Stream$;
const #237 = Asciz	scala/Predef$;
const #238 = class	#237;	//  scala/Predef$
const #239 = Asciz	Lscala/Predef$;;
const #240 = NameAndType	#130:#239;//  MODULE$:Lscala/Predef$;
const #241 = Field	#238.#240;	//  scala/Predef$.MODULE$:Lscala/Predef$;
const #242 = Asciz	(Ljava/lang/Object;Ljava/lang/Object;)V;
const #243 = NameAndType	#3:#242;//  "<init>":(Ljava/lang/Object;Ljava/lang/Object;)V
const #244 = Method	#173.#243;	//  scala/Tuple2."<init>":(Ljava/lang/Object;Ljava/lang/Object;)V
const #245 = Asciz	[Ljava/lang/Object;;
const #246 = class	#245;	//  "[Ljava/lang/Object;"
const #247 = Asciz	wrapRefArray;
const #248 = Asciz	([Ljava/lang/Object;)Lscala/collection/mutable/WrappedArray;;
const #249 = NameAndType	#247:#248;//  wrapRefArray:([Ljava/lang/Object;)Lscala/collection/mutable/WrappedArray;
const #250 = Method	#238.#249;	//  scala/Predef$.wrapRefArray:([Ljava/lang/Object;)Lscala/collection/mutable/WrappedArray;
const #251 = Asciz	(Lscala/collection/Seq;)Lscala/collection/immutable/Stream;;
const #252 = NameAndType	#187:#251;//  apply:(Lscala/collection/Seq;)Lscala/collection/immutable/Stream;
const #253 = Method	#233.#252;	//  scala/collection/immutable/Stream$.apply:(Lscala/collection/Seq;)Lscala/collection/immutable/Stream;
const #254 = Asciz	canBuildFrom;
const #255 = Asciz	()Lscala/collection/generic/CanBuildFrom;;
const #256 = NameAndType	#254:#255;//  canBuildFrom:()Lscala/collection/generic/CanBuildFrom;
const #257 = Method	#233.#256;	//  scala/collection/immutable/Stream$.canBuildFrom:()Lscala/collection/generic/CanBuildFrom;
const #258 = Asciz	scala/collection/immutable/Stream;
const #259 = class	#258;	//  scala/collection/immutable/Stream
const #260 = Asciz	(Lscala/collection/Traversable;Lscala/collection/generic/CanBuildFrom;)Ljava/lang/Object;;
const #261 = NameAndType	#220:#260;//  $plus$plus:(Lscala/collection/Traversable;Lscala/collection/generic/CanBuildFrom;)Ljava/lang/Object;
const #262 = Method	#259.#261;	//  scala/collection/immutable/Stream.$plus$plus:(Lscala/collection/Traversable;Lscala/collection/generic/CanBuildFrom;)Ljava/lang/Object;
const #263 = Asciz	()Lscala/collection/immutable/Stream<Lscala/Tuple2<TA;TB;>;>;;
const #264 = Asciz	smallest;
const #265 = Asciz	()Lscala/collection/immutable/RedBlack$NonEmpty;;
const #266 = NameAndType	#264:#265;//  smallest:()Lscala/collection/immutable/RedBlack$NonEmpty;
const #267 = Method	#8.#266;	//  scala/collection/immutable/RedBlack$Tree.smallest:()Lscala/collection/immutable/RedBlack$NonEmpty;
const #268 = Asciz	()Lscala/collection/immutable/RedBlack<TA;>.NonEmpty<TB;>;;
const #269 = Asciz	del;
const #270 = Asciz	(Ljava/lang/Object;)Lscala/collection/immutable/RedBlack$Tree;;
const #271 = NameAndType	#269:#270;//  del:(Ljava/lang/Object;)Lscala/collection/immutable/RedBlack$Tree;
const #272 = Method	#8.#271;	//  scala/collection/immutable/RedBlack$Tree.del:(Ljava/lang/Object;)Lscala/collection/immutable/RedBlack$Tree;
const #273 = Asciz	k;
const #274 = Asciz	s;
const #275 = Asciz	(TA;)Lscala/collection/immutable/RedBlack<TA;>.Tree<TB;>;;
const #276 = NameAndType	#86:#19;//  balanceLeft$1:(ZLjava/lang/Object;Ljava/lang/Object;Lscala/collection/immutable/RedBlack$Tree;Lscala/collection/immutable/RedBlack$Tree;)Lscala/Product;
const #277 = Method	#37.#276;	//  scala/collection/immutable/RedBlack$NonEmpty.balanceLeft$1:(ZLjava/lang/Object;Ljava/lang/Object;Lscala/collection/immutable/RedBlack$Tree;Lscala/collection/immutable/RedBlack$Tree;)Lscala/Product;
const #278 = NameAndType	#18:#19;//  balanceRight$1:(ZLjava/lang/Object;Ljava/lang/Object;Lscala/collection/immutable/RedBlack$Tree;Lscala/collection/immutable/RedBlack$Tree;)Lscala/Product;
const #279 = Method	#37.#278;	//  scala/collection/immutable/RedBlack$NonEmpty.balanceRight$1:(ZLjava/lang/Object;Ljava/lang/Object;Lscala/collection/immutable/RedBlack$Tree;Lscala/collection/immutable/RedBlack$Tree;)Lscala/Product;
const #280 = Asciz	v;
const #281 = Asciz	<B1:Ljava/lang/Object;>(TA;TB1;)Lscala/collection/immutable/RedBlack<TA;>.Tree<TB1;>;;
const #282 = Asciz	lookup;
const #283 = NameAndType	#282:#270;//  lookup:(Ljava/lang/Object;)Lscala/collection/immutable/RedBlack$Tree;
const #284 = Method	#8.#283;	//  scala/collection/immutable/RedBlack$Tree.lookup:(Ljava/lang/Object;)Lscala/collection/immutable/RedBlack$Tree;
const #285 = Asciz	()Lscala/collection/immutable/RedBlack<TA;>.Tree<TB;>;;
const #286 = Asciz	()TB;;
const #287 = Asciz	<B:Ljava/lang/Object;>Lscala/collection/immutable/RedBlack<TA;>.Tree<TB;>;Lscala/ScalaObject;;
const #288 = Asciz	Scala;
const #289 = Asciz	InnerClasses;
const #290 = Asciz	Tree;
const #291 = Asciz	RedTree;
const #292 = Asciz	NonEmpty;
const #293 = Asciz	BlackTree;
const #294 = Asciz	$anonfun$iterator$2;
const #295 = Asciz	$anonfun$iterator$1;
const #296 = Asciz	scala/ScalaObject;
const #297 = class	#296;	//  scala/ScalaObject
const #298 = Asciz	java/io/Serializable;
const #299 = class	#298;	//  java/io/Serializable

{
public scala.collection.immutable.RedBlack$NonEmpty(scala.collection.immutable.RedBlack);
  Code:
   Stack=2, Locals=2, Args_size=2
   0:	aload_0
   1:	aload_1
   2:	invokespecial	#10; //Method scala/collection/immutable/RedBlack$Tree."<init>":(Lscala/collection/immutable/RedBlack;)V
   5:	return
  LineNumberTable: 
   line 52: 0

  LocalVariableTable: 
   Start  Length  Slot  Name   Signature
   0      6      0    this       Lscala/collection/immutable/RedBlack$NonEmpty;
   0      6      1    $outer       Lscala/collection/immutable/RedBlack;

  Signature: length = 0x2
   00 10 

public scala.collection.immutable.RedBlack scala$collection$immutable$RedBlack$NonEmpty$$$outer();
  Code:
   Stack=1, Locals=1, Args_size=1
   0:	aload_0
   1:	getfield	#107; //Field scala/collection/immutable/RedBlack$Tree.$outer:Lscala/collection/immutable/RedBlack;
   4:	areturn
  LineNumberTable: 
   line 52: 0


public int count();
  Code:
   Stack=2, Locals=1, Args_size=1
   0:	iconst_1
   1:	aload_0
   2:	invokevirtual	#110; //Method left:()Lscala/collection/immutable/RedBlack$Tree;
   5:	invokevirtual	#112; //Method scala/collection/immutable/RedBlack$Tree.count:()I
   8:	iadd
   9:	aload_0
   10:	invokevirtual	#113; //Method right:()Lscala/collection/immutable/RedBlack$Tree;
   13:	invokevirtual	#112; //Method scala/collection/immutable/RedBlack$Tree.count:()I
   16:	iadd
   17:	ireturn
  LineNumberTable: 
   line 129: 0


public java.lang.Object last();
  Code:
   Stack=1, Locals=1, Args_size=1
   0:	aload_0
   1:	invokevirtual	#113; //Method right:()Lscala/collection/immutable/RedBlack$Tree;
   4:	invokevirtual	#118; //Method scala/collection/immutable/RedBlack$Tree.isEmpty:()Z
   7:	ifeq	17
   10:	aload_0
   11:	invokevirtual	#119; //Method key:()Ljava/lang/Object;
   14:	goto	24
   17:	aload_0
   18:	invokevirtual	#113; //Method right:()Lscala/collection/immutable/RedBlack$Tree;
   21:	invokevirtual	#121; //Method scala/collection/immutable/RedBlack$Tree.last:()Ljava/lang/Object;
   24:	areturn
  LineNumberTable: 
   line 128: 0

  Signature: length = 0x2
   00 7A 

public java.lang.Object first();
  Code:
   Stack=1, Locals=1, Args_size=1
   0:	aload_0
   1:	invokevirtual	#110; //Method left:()Lscala/collection/immutable/RedBlack$Tree;
   4:	invokevirtual	#118; //Method scala/collection/immutable/RedBlack$Tree.isEmpty:()Z
   7:	ifeq	17
   10:	aload_0
   11:	invokevirtual	#119; //Method key:()Ljava/lang/Object;
   14:	goto	24
   17:	aload_0
   18:	invokevirtual	#110; //Method left:()Lscala/collection/immutable/RedBlack$Tree;
   21:	invokevirtual	#125; //Method scala/collection/immutable/RedBlack$Tree.first:()Ljava/lang/Object;
   24:	areturn
  LineNumberTable: 
   line 127: 0

  Signature: length = 0x2
   00 7A 

public scala.collection.immutable.RedBlack$Tree range(scala.Option, scala.Option);
  Code:
   Stack=6, Locals=9, Args_size=3
   0:	aload_1
   1:	getstatic	#133; //Field scala/None$.MODULE$:Lscala/None$;
   4:	astore_3
   5:	dup
   6:	ifnonnull	17
   9:	pop
   10:	aload_3
   11:	ifnull	24
   14:	goto	53
   17:	aload_3
   18:	invokevirtual	#139; //Method java/lang/Object.equals:(Ljava/lang/Object;)Z
   21:	ifeq	53
   24:	aload_2
   25:	getstatic	#133; //Field scala/None$.MODULE$:Lscala/None$;
   28:	astore	4
   30:	dup
   31:	ifnonnull	43
   34:	pop
   35:	aload	4
   37:	ifnull	51
   40:	goto	53
   43:	aload	4
   45:	invokevirtual	#139; //Method java/lang/Object.equals:(Ljava/lang/Object;)Z
   48:	ifeq	53
   51:	aload_0
   52:	areturn
   53:	aload_1
   54:	getstatic	#133; //Field scala/None$.MODULE$:Lscala/None$;
   57:	astore	5
   59:	dup
   60:	ifnonnull	72
   63:	pop
   64:	aload	5
   66:	ifnull	108
   69:	goto	80
   72:	aload	5
   74:	invokevirtual	#139; //Method java/lang/Object.equals:(Ljava/lang/Object;)Z
   77:	ifne	108
   80:	aload_0
   81:	invokevirtual	#41; //Method scala$collection$immutable$RedBlack$NonEmpty$$$outer:()Lscala/collection/immutable/RedBlack;
   84:	aload_0
   85:	invokevirtual	#119; //Method key:()Ljava/lang/Object;
   88:	aload_1
   89:	invokevirtual	#144; //Method scala/Option.get:()Ljava/lang/Object;
   92:	invokevirtual	#148; //Method scala/collection/immutable/RedBlack.isSmaller:(Ljava/lang/Object;Ljava/lang/Object;)Z
   95:	ifeq	108
   98:	aload_0
   99:	invokevirtual	#113; //Method right:()Lscala/collection/immutable/RedBlack$Tree;
   102:	aload_1
   103:	aload_2
   104:	invokevirtual	#150; //Method scala/collection/immutable/RedBlack$Tree.range:(Lscala/Option;Lscala/Option;)Lscala/collection/immutable/RedBlack$Tree;
   107:	areturn
   108:	aload_2
   109:	getstatic	#133; //Field scala/None$.MODULE$:Lscala/None$;
   112:	astore	6
   114:	dup
   115:	ifnonnull	127
   118:	pop
   119:	aload	6
   121:	ifnull	171
   124:	goto	135
   127:	aload	6
   129:	invokevirtual	#139; //Method java/lang/Object.equals:(Ljava/lang/Object;)Z
   132:	ifne	171
   135:	aload_0
   136:	invokevirtual	#41; //Method scala$collection$immutable$RedBlack$NonEmpty$$$outer:()Lscala/collection/immutable/RedBlack;
   139:	aload_2
   140:	invokevirtual	#144; //Method scala/Option.get:()Ljava/lang/Object;
   143:	aload_0
   144:	invokevirtual	#119; //Method key:()Ljava/lang/Object;
   147:	invokevirtual	#148; //Method scala/collection/immutable/RedBlack.isSmaller:(Ljava/lang/Object;Ljava/lang/Object;)Z
   150:	ifne	302
   153:	aload_0
   154:	invokevirtual	#41; //Method scala$collection$immutable$RedBlack$NonEmpty$$$outer:()Lscala/collection/immutable/RedBlack;
   157:	aload_0
   158:	invokevirtual	#119; //Method key:()Ljava/lang/Object;
   161:	aload_2
   162:	invokevirtual	#144; //Method scala/Option.get:()Ljava/lang/Object;
   165:	invokevirtual	#148; //Method scala/collection/immutable/RedBlack.isSmaller:(Ljava/lang/Object;Ljava/lang/Object;)Z
   168:	ifeq	302
   171:	aload_0
   172:	invokevirtual	#110; //Method left:()Lscala/collection/immutable/RedBlack$Tree;
   175:	aload_1
   176:	getstatic	#133; //Field scala/None$.MODULE$:Lscala/None$;
   179:	invokevirtual	#150; //Method scala/collection/immutable/RedBlack$Tree.range:(Lscala/Option;Lscala/Option;)Lscala/collection/immutable/RedBlack$Tree;
   182:	astore	7
   184:	aload_0
   185:	invokevirtual	#113; //Method right:()Lscala/collection/immutable/RedBlack$Tree;
   188:	getstatic	#133; //Field scala/None$.MODULE$:Lscala/None$;
   191:	aload_2
   192:	invokevirtual	#150; //Method scala/collection/immutable/RedBlack$Tree.range:(Lscala/Option;Lscala/Option;)Lscala/collection/immutable/RedBlack$Tree;
   195:	astore	8
   197:	aload	7
   199:	aload_0
   200:	invokevirtual	#110; //Method left:()Lscala/collection/immutable/RedBlack$Tree;
   203:	if_acmpne	219
   206:	aload	8
   208:	aload_0
   209:	invokevirtual	#113; //Method right:()Lscala/collection/immutable/RedBlack$Tree;
   212:	if_acmpne	219
   215:	aload_0
   216:	goto	301
   219:	aload	7
   221:	aload_0
   222:	invokevirtual	#41; //Method scala$collection$immutable$RedBlack$NonEmpty$$$outer:()Lscala/collection/immutable/RedBlack;
   225:	invokevirtual	#154; //Method scala/collection/immutable/RedBlack.Empty:()Lscala/collection/immutable/RedBlack$Empty$;
   228:	if_acmpne	247
   231:	aload	8
   233:	aload_0
   234:	invokevirtual	#119; //Method key:()Ljava/lang/Object;
   237:	aload_0
   238:	invokevirtual	#155; //Method value:()Ljava/lang/Object;
   241:	invokevirtual	#159; //Method scala/collection/immutable/RedBlack$Tree.upd:(Ljava/lang/Object;Ljava/lang/Object;)Lscala/collection/immutable/RedBlack$Tree;
   244:	goto	301
   247:	aload	8
   249:	aload_0
   250:	invokevirtual	#41; //Method scala$collection$immutable$RedBlack$NonEmpty$$$outer:()Lscala/collection/immutable/RedBlack;
   253:	invokevirtual	#154; //Method scala/collection/immutable/RedBlack.Empty:()Lscala/collection/immutable/RedBlack$Empty$;
   256:	if_acmpne	275
   259:	aload	7
   261:	aload_0
   262:	invokevirtual	#119; //Method key:()Ljava/lang/Object;
   265:	aload_0
   266:	invokevirtual	#155; //Method value:()Ljava/lang/Object;
   269:	invokevirtual	#159; //Method scala/collection/immutable/RedBlack$Tree.upd:(Ljava/lang/Object;Ljava/lang/Object;)Lscala/collection/immutable/RedBlack$Tree;
   272:	goto	301
   275:	aload_0
   276:	invokevirtual	#41; //Method scala$collection$immutable$RedBlack$NonEmpty$$$outer:()Lscala/collection/immutable/RedBlack;
   279:	aload_0
   280:	invokevirtual	#161; //Method isBlack:()Z
   283:	aload_0
   284:	invokevirtual	#119; //Method key:()Ljava/lang/Object;
   287:	aload_0
   288:	invokevirtual	#155; //Method value:()Ljava/lang/Object;
   291:	aload	7
   293:	aload	8
   295:	invokevirtual	#61; //Method scala/collection/immutable/RedBlack.scala$collection$immutable$RedBlack$$mkTree:(ZLjava/lang/Object;Ljava/lang/Object;Lscala/collection/immutable/RedBlack$Tree;Lscala/collection/immutable/RedBlack$Tree;)Lscala/Product;
   298:	checkcast	#8; //class scala/collection/immutable/RedBlack$Tree
   301:	areturn
   302:	aload_0
   303:	invokevirtual	#110; //Method left:()Lscala/collection/immutable/RedBlack$Tree;
   306:	aload_1
   307:	aload_2
   308:	invokevirtual	#150; //Method scala/collection/immutable/RedBlack$Tree.range:(Lscala/Option;Lscala/Option;)Lscala/collection/immutable/RedBlack$Tree;
   311:	areturn
  LineNumberTable: 
   line 116: 0
   line 117: 53
   line 118: 108
   line 120: 171
   line 121: 184
   line 122: 197
   line 123: 219
   line 124: 247
   line 125: 275
   line 115: 301
   line 119: 302

  LocalVariableTable: 
   Start  Length  Slot  Name   Signature
   0      312      0    this       Lscala/collection/immutable/RedBlack$NonEmpty;
   0      312      1    from       Lscala/Option;
   0      312      2    until       Lscala/Option;
   184      118      7    newLeft       Lscala/collection/immutable/RedBlack$Tree;
   197      105      8    newRight       Lscala/collection/immutable/RedBlack$Tree;

  Signature: length = 0x2
   00 FFFFFFA7 

public scala.Tuple2 visit(java.lang.Object, scala.Function3);
  Code:
   Stack=4, Locals=5, Args_size=3
   0:	aload_0
   1:	invokevirtual	#110; //Method left:()Lscala/collection/immutable/RedBlack$Tree;
   4:	aload_1
   5:	aload_2
   6:	invokevirtual	#171; //Method scala/collection/immutable/RedBlack$Tree.visit:(Ljava/lang/Object;Lscala/Function3;)Lscala/Tuple2;
   9:	astore_3
   10:	aload_3
   11:	invokevirtual	#176; //Method scala/Tuple2._1:()Ljava/lang/Object;
   14:	invokestatic	#181; //Method scala/runtime/BoxesRunTime.unboxToBoolean:(Ljava/lang/Object;)Z
   17:	ifeq	71
   20:	aload_2
   21:	aload_3
   22:	invokevirtual	#184; //Method scala/Tuple2._2:()Ljava/lang/Object;
   25:	aload_0
   26:	invokevirtual	#119; //Method key:()Ljava/lang/Object;
   29:	aload_0
   30:	invokevirtual	#155; //Method value:()Ljava/lang/Object;
   33:	invokeinterface	#190,  4; //InterfaceMethod scala/Function3.apply:(Ljava/lang/Object;Ljava/lang/Object;Ljava/lang/Object;)Ljava/lang/Object;
   38:	checkcast	#173; //class scala/Tuple2
   41:	astore	4
   43:	aload	4
   45:	invokevirtual	#176; //Method scala/Tuple2._1:()Ljava/lang/Object;
   48:	invokestatic	#181; //Method scala/runtime/BoxesRunTime.unboxToBoolean:(Ljava/lang/Object;)Z
   51:	ifeq	68
   54:	aload_0
   55:	invokevirtual	#113; //Method right:()Lscala/collection/immutable/RedBlack$Tree;
   58:	aload	4
   60:	invokevirtual	#184; //Method scala/Tuple2._2:()Ljava/lang/Object;
   63:	aload_2
   64:	invokevirtual	#171; //Method scala/collection/immutable/RedBlack$Tree.visit:(Ljava/lang/Object;Lscala/Function3;)Lscala/Tuple2;
   67:	areturn
   68:	aload	4
   70:	areturn
   71:	aload_3
   72:	areturn
  LineNumberTable: 
   line 109: 0
   line 110: 10
   line 111: 20
   line 112: 43
   line 113: 54
   line 112: 68
   line 110: 71

  LocalVariableTable: 
   Start  Length  Slot  Name   Signature
   0      73      0    this       Lscala/collection/immutable/RedBlack$NonEmpty;
   0      73      1    input       Ljava/lang/Object;
   0      73      2    f       Lscala/Function3;
   10      63      3    left       Lscala/Tuple2;
   43      28      4    middle       Lscala/Tuple2;

  Signature: length = 0x2
   00 FFFFFFC4 
  Deprecated: true

public void foreach(scala.Function2);
  Code:
   Stack=3, Locals=2, Args_size=2
   0:	aload_0
   1:	invokevirtual	#110; //Method left:()Lscala/collection/immutable/RedBlack$Tree;
   4:	aload_1
   5:	invokevirtual	#201; //Method scala/collection/immutable/RedBlack$Tree.foreach:(Lscala/Function2;)V
   8:	aload_1
   9:	aload_0
   10:	invokevirtual	#119; //Method key:()Ljava/lang/Object;
   13:	aload_0
   14:	invokevirtual	#155; //Method value:()Ljava/lang/Object;
   17:	invokeinterface	#206,  3; //InterfaceMethod scala/Function2.apply:(Ljava/lang/Object;Ljava/lang/Object;)Ljava/lang/Object;
   22:	pop
   23:	aload_0
   24:	invokevirtual	#113; //Method right:()Lscala/collection/immutable/RedBlack$Tree;
   27:	aload_1
   28:	invokevirtual	#201; //Method scala/collection/immutable/RedBlack$Tree.foreach:(Lscala/Function2;)V
   31:	return
  LineNumberTable: 
   line 102: 0
   line 103: 8
   line 104: 23

  LocalVariableTable: 
   Start  Length  Slot  Name   Signature
   0      32      0    this       Lscala/collection/immutable/RedBlack$NonEmpty;
   0      32      1    f       Lscala/Function2;

  Signature: length = 0x2
   00 FFFFFFD0 

public scala.collection.Iterator iterator();
  Code:
   Stack=4, Locals=1, Args_size=1
   0:	aload_0
   1:	invokevirtual	#110; //Method left:()Lscala/collection/immutable/RedBlack$Tree;
   4:	invokevirtual	#212; //Method scala/collection/immutable/RedBlack$Tree.iterator:()Lscala/collection/Iterator;
   7:	new	#214; //class scala/collection/immutable/RedBlack$NonEmpty$$anonfun$iterator$1
   10:	dup
   11:	aload_0
   12:	invokespecial	#217; //Method scala/collection/immutable/RedBlack$NonEmpty$$anonfun$iterator$1."<init>":(Lscala/collection/immutable/RedBlack$NonEmpty;)V
   15:	invokeinterface	#223,  2; //InterfaceMethod scala/collection/Iterator.$plus$plus:(Lscala/Function0;)Lscala/collection/Iterator;
   20:	new	#225; //class scala/collection/immutable/RedBlack$NonEmpty$$anonfun$iterator$2
   23:	dup
   24:	aload_0
   25:	invokespecial	#226; //Method scala/collection/immutable/RedBlack$NonEmpty$$anonfun$iterator$2."<init>":(Lscala/collection/immutable/RedBlack$NonEmpty;)V
   28:	invokeinterface	#223,  2; //InterfaceMethod scala/collection/Iterator.$plus$plus:(Lscala/Function0;)Lscala/collection/Iterator;
   33:	areturn
  LineNumberTable: 
   line 99: 0

  Signature: length = 0x2
   00 FFFFFFE3 

public scala.collection.immutable.Stream toStream();
  Code:
   Stack=10, Locals=1, Args_size=1
   0:	aload_0
   1:	invokevirtual	#110; //Method left:()Lscala/collection/immutable/RedBlack$Tree;
   4:	invokevirtual	#231; //Method scala/collection/immutable/RedBlack$Tree.toStream:()Lscala/collection/immutable/Stream;
   7:	getstatic	#236; //Field scala/collection/immutable/Stream$.MODULE$:Lscala/collection/immutable/Stream$;
   10:	getstatic	#241; //Field scala/Predef$.MODULE$:Lscala/Predef$;
   13:	iconst_1
   14:	anewarray	#173; //class scala/Tuple2
   17:	dup
   18:	iconst_0
   19:	new	#173; //class scala/Tuple2
   22:	dup
   23:	aload_0
   24:	invokevirtual	#119; //Method key:()Ljava/lang/Object;
   27:	aload_0
   28:	invokevirtual	#155; //Method value:()Ljava/lang/Object;
   31:	invokespecial	#244; //Method scala/Tuple2."<init>":(Ljava/lang/Object;Ljava/lang/Object;)V
   34:	aastore
   35:	checkcast	#246; //class "[Ljava/lang/Object;"
   38:	invokevirtual	#250; //Method scala/Predef$.wrapRefArray:([Ljava/lang/Object;)Lscala/collection/mutable/WrappedArray;
   41:	invokevirtual	#253; //Method scala/collection/immutable/Stream$.apply:(Lscala/collection/Seq;)Lscala/collection/immutable/Stream;
   44:	getstatic	#236; //Field scala/collection/immutable/Stream$.MODULE$:Lscala/collection/immutable/Stream$;
   47:	invokevirtual	#257; //Method scala/collection/immutable/Stream$.canBuildFrom:()Lscala/collection/generic/CanBuildFrom;
   50:	invokevirtual	#262; //Method scala/collection/immutable/Stream.$plus$plus:(Lscala/collection/Traversable;Lscala/collection/generic/CanBuildFrom;)Ljava/lang/Object;
   53:	checkcast	#259; //class scala/collection/immutable/Stream
   56:	aload_0
   57:	invokevirtual	#113; //Method right:()Lscala/collection/immutable/RedBlack$Tree;
   60:	invokevirtual	#231; //Method scala/collection/immutable/RedBlack$Tree.toStream:()Lscala/collection/immutable/Stream;
   63:	getstatic	#236; //Field scala/collection/immutable/Stream$.MODULE$:Lscala/collection/immutable/Stream$;
   66:	invokevirtual	#257; //Method scala/collection/immutable/Stream$.canBuildFrom:()Lscala/collection/generic/CanBuildFrom;
   69:	invokevirtual	#262; //Method scala/collection/immutable/Stream.$plus$plus:(Lscala/collection/Traversable;Lscala/collection/generic/CanBuildFrom;)Ljava/lang/Object;
   72:	checkcast	#259; //class scala/collection/immutable/Stream
   75:	areturn
  LineNumberTable: 
   line 96: 0

  Signature: length = 0x2
   01 07 

public scala.collection.immutable.RedBlack$NonEmpty smallest();
  Code:
   Stack=1, Locals=1, Args_size=1
   0:	aload_0
   1:	invokevirtual	#110; //Method left:()Lscala/collection/immutable/RedBlack$Tree;
   4:	invokevirtual	#118; //Method scala/collection/immutable/RedBlack$Tree.isEmpty:()Z
   7:	ifeq	14
   10:	aload_0
   11:	goto	21
   14:	aload_0
   15:	invokevirtual	#110; //Method left:()Lscala/collection/immutable/RedBlack$Tree;
   18:	invokevirtual	#267; //Method scala/collection/immutable/RedBlack$Tree.smallest:()Lscala/collection/immutable/RedBlack$NonEmpty;
   21:	areturn
  LineNumberTable: 
   line 93: 0

  Signature: length = 0x2
   01 0C 

public scala.collection.immutable.RedBlack$Tree del(java.lang.Object);
  Code:
   Stack=7, Locals=3, Args_size=2
   0:	aload_0
   1:	invokevirtual	#41; //Method scala$collection$immutable$RedBlack$NonEmpty$$$outer:()Lscala/collection/immutable/RedBlack;
   4:	aload_1
   5:	aload_0
   6:	invokevirtual	#119; //Method key:()Ljava/lang/Object;
   9:	invokevirtual	#148; //Method scala/collection/immutable/RedBlack.isSmaller:(Ljava/lang/Object;Ljava/lang/Object;)Z
   12:	ifeq	52
   15:	aload_0
   16:	invokevirtual	#41; //Method scala$collection$immutable$RedBlack$NonEmpty$$$outer:()Lscala/collection/immutable/RedBlack;
   19:	aload_0
   20:	invokevirtual	#161; //Method isBlack:()Z
   23:	aload_0
   24:	invokevirtual	#119; //Method key:()Ljava/lang/Object;
   27:	aload_0
   28:	invokevirtual	#155; //Method value:()Ljava/lang/Object;
   31:	aload_0
   32:	invokevirtual	#110; //Method left:()Lscala/collection/immutable/RedBlack$Tree;
   35:	aload_1
   36:	invokevirtual	#272; //Method scala/collection/immutable/RedBlack$Tree.del:(Ljava/lang/Object;)Lscala/collection/immutable/RedBlack$Tree;
   39:	aload_0
   40:	invokevirtual	#113; //Method right:()Lscala/collection/immutable/RedBlack$Tree;
   43:	invokevirtual	#61; //Method scala/collection/immutable/RedBlack.scala$collection$immutable$RedBlack$$mkTree:(ZLjava/lang/Object;Ljava/lang/Object;Lscala/collection/immutable/RedBlack$Tree;Lscala/collection/immutable/RedBlack$Tree;)Lscala/Product;
   46:	checkcast	#8; //class scala/collection/immutable/RedBlack$Tree
   49:	goto	183
   52:	aload_0
   53:	invokevirtual	#41; //Method scala$collection$immutable$RedBlack$NonEmpty$$$outer:()Lscala/collection/immutable/RedBlack;
   56:	aload_0
   57:	invokevirtual	#119; //Method key:()Ljava/lang/Object;
   60:	aload_1
   61:	invokevirtual	#148; //Method scala/collection/immutable/RedBlack.isSmaller:(Ljava/lang/Object;Ljava/lang/Object;)Z
   64:	ifeq	104
   67:	aload_0
   68:	invokevirtual	#41; //Method scala$collection$immutable$RedBlack$NonEmpty$$$outer:()Lscala/collection/immutable/RedBlack;
   71:	aload_0
   72:	invokevirtual	#161; //Method isBlack:()Z
   75:	aload_0
   76:	invokevirtual	#119; //Method key:()Ljava/lang/Object;
   79:	aload_0
   80:	invokevirtual	#155; //Method value:()Ljava/lang/Object;
   83:	aload_0
   84:	invokevirtual	#110; //Method left:()Lscala/collection/immutable/RedBlack$Tree;
   87:	aload_0
   88:	invokevirtual	#113; //Method right:()Lscala/collection/immutable/RedBlack$Tree;
   91:	aload_1
   92:	invokevirtual	#272; //Method scala/collection/immutable/RedBlack$Tree.del:(Ljava/lang/Object;)Lscala/collection/immutable/RedBlack$Tree;
   95:	invokevirtual	#61; //Method scala/collection/immutable/RedBlack.scala$collection$immutable$RedBlack$$mkTree:(ZLjava/lang/Object;Ljava/lang/Object;Lscala/collection/immutable/RedBlack$Tree;Lscala/collection/immutable/RedBlack$Tree;)Lscala/Product;
   98:	checkcast	#8; //class scala/collection/immutable/RedBlack$Tree
   101:	goto	183
   104:	aload_0
   105:	invokevirtual	#110; //Method left:()Lscala/collection/immutable/RedBlack$Tree;
   108:	invokevirtual	#118; //Method scala/collection/immutable/RedBlack$Tree.isEmpty:()Z
   111:	ifeq	121
   114:	aload_0
   115:	invokevirtual	#113; //Method right:()Lscala/collection/immutable/RedBlack$Tree;
   118:	goto	183
   121:	aload_0
   122:	invokevirtual	#113; //Method right:()Lscala/collection/immutable/RedBlack$Tree;
   125:	invokevirtual	#118; //Method scala/collection/immutable/RedBlack$Tree.isEmpty:()Z
   128:	ifeq	138
   131:	aload_0
   132:	invokevirtual	#110; //Method left:()Lscala/collection/immutable/RedBlack$Tree;
   135:	goto	183
   138:	aload_0
   139:	invokevirtual	#113; //Method right:()Lscala/collection/immutable/RedBlack$Tree;
   142:	invokevirtual	#267; //Method scala/collection/immutable/RedBlack$Tree.smallest:()Lscala/collection/immutable/RedBlack$NonEmpty;
   145:	astore_2
   146:	aload_0
   147:	invokevirtual	#41; //Method scala$collection$immutable$RedBlack$NonEmpty$$$outer:()Lscala/collection/immutable/RedBlack;
   150:	aload_0
   151:	invokevirtual	#161; //Method isBlack:()Z
   154:	aload_2
   155:	invokevirtual	#119; //Method key:()Ljava/lang/Object;
   158:	aload_2
   159:	invokevirtual	#155; //Method value:()Ljava/lang/Object;
   162:	aload_0
   163:	invokevirtual	#110; //Method left:()Lscala/collection/immutable/RedBlack$Tree;
   166:	aload_0
   167:	invokevirtual	#113; //Method right:()Lscala/collection/immutable/RedBlack$Tree;
   170:	aload_2
   171:	invokevirtual	#119; //Method key:()Ljava/lang/Object;
   174:	invokevirtual	#272; //Method scala/collection/immutable/RedBlack$Tree.del:(Ljava/lang/Object;)Lscala/collection/immutable/RedBlack$Tree;
   177:	invokevirtual	#61; //Method scala/collection/immutable/RedBlack.scala$collection$immutable$RedBlack$$mkTree:(ZLjava/lang/Object;Ljava/lang/Object;Lscala/collection/immutable/RedBlack$Tree;Lscala/collection/immutable/RedBlack$Tree;)Lscala/Product;
   180:	checkcast	#8; //class scala/collection/immutable/RedBlack$Tree
   183:	areturn
  LineNumberTable: 
   line 84: 0
   line 85: 52
   line 86: 104
   line 87: 121
   line 89: 138
   line 90: 146
   line 84: 183

  LocalVariableTable: 
   Start  Length  Slot  Name   Signature
   0      184      0    this       Lscala/collection/immutable/RedBlack$NonEmpty;
   0      184      1    k       Ljava/lang/Object;
   146      37      2    s       Lscala/collection/immutable/RedBlack$NonEmpty;

  Signature: length = 0x2
   01 13 

public scala.collection.immutable.RedBlack$Tree upd(java.lang.Object, java.lang.Object);
  Code:
   Stack=8, Locals=3, Args_size=3
   0:	aload_0
   1:	invokevirtual	#41; //Method scala$collection$immutable$RedBlack$NonEmpty$$$outer:()Lscala/collection/immutable/RedBlack;
   4:	aload_1
   5:	aload_0
   6:	invokevirtual	#119; //Method key:()Ljava/lang/Object;
   9:	invokevirtual	#148; //Method scala/collection/immutable/RedBlack.isSmaller:(Ljava/lang/Object;Ljava/lang/Object;)Z
   12:	ifeq	50
   15:	aload_0
   16:	aload_0
   17:	invokevirtual	#161; //Method isBlack:()Z
   20:	aload_0
   21:	invokevirtual	#119; //Method key:()Ljava/lang/Object;
   24:	aload_0
   25:	invokevirtual	#155; //Method value:()Ljava/lang/Object;
   28:	aload_0
   29:	invokevirtual	#110; //Method left:()Lscala/collection/immutable/RedBlack$Tree;
   32:	aload_1
   33:	aload_2
   34:	invokevirtual	#159; //Method scala/collection/immutable/RedBlack$Tree.upd:(Ljava/lang/Object;Ljava/lang/Object;)Lscala/collection/immutable/RedBlack$Tree;
   37:	aload_0
   38:	invokevirtual	#113; //Method right:()Lscala/collection/immutable/RedBlack$Tree;
   41:	invokespecial	#277; //Method balanceLeft$1:(ZLjava/lang/Object;Ljava/lang/Object;Lscala/collection/immutable/RedBlack$Tree;Lscala/collection/immutable/RedBlack$Tree;)Lscala/Product;
   44:	checkcast	#8; //class scala/collection/immutable/RedBlack$Tree
   47:	goto	124
   50:	aload_0
   51:	invokevirtual	#41; //Method scala$collection$immutable$RedBlack$NonEmpty$$$outer:()Lscala/collection/immutable/RedBlack;
   54:	aload_0
   55:	invokevirtual	#119; //Method key:()Ljava/lang/Object;
   58:	aload_1
   59:	invokevirtual	#148; //Method scala/collection/immutable/RedBlack.isSmaller:(Ljava/lang/Object;Ljava/lang/Object;)Z
   62:	ifeq	100
   65:	aload_0
   66:	aload_0
   67:	invokevirtual	#161; //Method isBlack:()Z
   70:	aload_0
   71:	invokevirtual	#119; //Method key:()Ljava/lang/Object;
   74:	aload_0
   75:	invokevirtual	#155; //Method value:()Ljava/lang/Object;
   78:	aload_0
   79:	invokevirtual	#110; //Method left:()Lscala/collection/immutable/RedBlack$Tree;
   82:	aload_0
   83:	invokevirtual	#113; //Method right:()Lscala/collection/immutable/RedBlack$Tree;
   86:	aload_1
   87:	aload_2
   88:	invokevirtual	#159; //Method scala/collection/immutable/RedBlack$Tree.upd:(Ljava/lang/Object;Ljava/lang/Object;)Lscala/collection/immutable/RedBlack$Tree;
   91:	invokespecial	#279; //Method balanceRight$1:(ZLjava/lang/Object;Ljava/lang/Object;Lscala/collection/immutable/RedBlack$Tree;Lscala/collection/immutable/RedBlack$Tree;)Lscala/Product;
   94:	checkcast	#8; //class scala/collection/immutable/RedBlack$Tree
   97:	goto	124
   100:	aload_0
   101:	invokevirtual	#41; //Method scala$collection$immutable$RedBlack$NonEmpty$$$outer:()Lscala/collection/immutable/RedBlack;
   104:	aload_0
   105:	invokevirtual	#161; //Method isBlack:()Z
   108:	aload_1
   109:	aload_2
   110:	aload_0
   111:	invokevirtual	#110; //Method left:()Lscala/collection/immutable/RedBlack$Tree;
   114:	aload_0
   115:	invokevirtual	#113; //Method right:()Lscala/collection/immutable/RedBlack$Tree;
   118:	invokevirtual	#61; //Method scala/collection/immutable/RedBlack.scala$collection$immutable$RedBlack$$mkTree:(ZLjava/lang/Object;Ljava/lang/Object;Lscala/collection/immutable/RedBlack$Tree;Lscala/collection/immutable/RedBlack$Tree;)Lscala/Product;
   121:	checkcast	#8; //class scala/collection/immutable/RedBlack$Tree
   124:	areturn
  LineNumberTable: 
   line 79: 0
   line 80: 50
   line 81: 100
   line 79: 124

  LocalVariableTable: 
   Start  Length  Slot  Name   Signature
   0      125      0    this       Lscala/collection/immutable/RedBlack$NonEmpty;
   0      125      1    k       Ljava/lang/Object;
   0      125      2    v       Ljava/lang/Object;

  Signature: length = 0x2
   01 19 

public scala.collection.immutable.RedBlack$Tree lookup(java.lang.Object);
  Code:
   Stack=3, Locals=2, Args_size=2
   0:	aload_0
   1:	invokevirtual	#41; //Method scala$collection$immutable$RedBlack$NonEmpty$$$outer:()Lscala/collection/immutable/RedBlack;
   4:	aload_1
   5:	aload_0
   6:	invokevirtual	#119; //Method key:()Ljava/lang/Object;
   9:	invokevirtual	#148; //Method scala/collection/immutable/RedBlack.isSmaller:(Ljava/lang/Object;Ljava/lang/Object;)Z
   12:	ifeq	26
   15:	aload_0
   16:	invokevirtual	#110; //Method left:()Lscala/collection/immutable/RedBlack$Tree;
   19:	aload_1
   20:	invokevirtual	#284; //Method scala/collection/immutable/RedBlack$Tree.lookup:(Ljava/lang/Object;)Lscala/collection/immutable/RedBlack$Tree;
   23:	goto	53
   26:	aload_0
   27:	invokevirtual	#41; //Method scala$collection$immutable$RedBlack$NonEmpty$$$outer:()Lscala/collection/immutable/RedBlack;
   30:	aload_0
   31:	invokevirtual	#119; //Method key:()Ljava/lang/Object;
   34:	aload_1
   35:	invokevirtual	#148; //Method scala/collection/immutable/RedBlack.isSmaller:(Ljava/lang/Object;Ljava/lang/Object;)Z
   38:	ifeq	52
   41:	aload_0
   42:	invokevirtual	#113; //Method right:()Lscala/collection/immutable/RedBlack$Tree;
   45:	aload_1
   46:	invokevirtual	#284; //Method scala/collection/immutable/RedBlack$Tree.lookup:(Ljava/lang/Object;)Lscala/collection/immutable/RedBlack$Tree;
   49:	goto	53
   52:	aload_0
   53:	areturn
  LineNumberTable: 
   line 59: 0
   line 60: 26
   line 61: 52
   line 59: 53

  LocalVariableTable: 
   Start  Length  Slot  Name   Signature
   0      54      0    this       Lscala/collection/immutable/RedBlack$NonEmpty;
   0      54      1    k       Ljava/lang/Object;

  Signature: length = 0x2
   01 13 

public abstract scala.collection.immutable.RedBlack$Tree right();
  Signature: length = 0x2
   01 1D 

public abstract scala.collection.immutable.RedBlack$Tree left();
  Signature: length = 0x2
   01 1D 

public abstract java.lang.Object value();
  Signature: length = 0x2
   01 1E 

public abstract java.lang.Object key();
  Signature: length = 0x2
   00 7A 

public boolean isEmpty();
  Code:
   Stack=1, Locals=1, Args_size=1
   0:	iconst_0
   1:	ireturn
  LineNumberTable: 
   line 53: 0


}

