Compiled from "RedBlack.scala"
public class scala.collection.immutable.RedBlack$RedTree extends scala.collection.immutable.RedBlack$NonEmpty implements scala.ScalaObject,scala.Product,java.io.Serializable
  SourceFile: "RedBlack.scala"
  Signature: length = 0x2
   00 FFFFFF9A 
  Scala: length = 0x
   
  InnerClass: 
   public abstract Tree=class scala/collection/immutable/RedBlack$Tree of class scala/collection/immutable/RedBlack
   public RedTree=class scala/collection/immutable/RedBlack$RedTree of class scala/collection/immutable/RedBlack
   public abstract NonEmpty=class scala/collection/immutable/RedBlack$NonEmpty of class scala/collection/immutable/RedBlack
  minor version: 0
  major version: 49
  Constant pool:
Asciz	SourceFile;
Asciz	RedBlack.scala;
Asciz	right;
Asciz	Lscala/collection/immutable/RedBlack$Tree;;
Asciz	Lscala/collection/immutable/RedBlack<TA;>.Tree<TB;>;;
Asciz	Signature;
Asciz	left;
Asciz	value;
Asciz	Ljava/lang/Object;;
Asciz	TB;;
Asciz	key;
Asciz	TA;;
Asciz	<init>;
Asciz	(Lscala/collection/immutable/RedBlack;Ljava/lang/Object;Ljava/lang/Object;Lscala/collection/immutable/RedBlack$Tree;Lscala/collection/immutable/RedBlack$Tree;)V;
Asciz	Code;
Asciz	LineNumberTable;
Asciz	scala/collection/immutable/RedBlack$RedTree;
class	scala/collection/immutable/RedBlack$RedTree
NameAndType	key:Ljava/lang/Object;
Field	scala/collection/immutable/RedBlack$RedTree.key:Ljava/lang/Object;
NameAndType	value:Ljava/lang/Object;
Field	scala/collection/immutable/RedBlack$RedTree.value:Ljava/lang/Object;
NameAndType	left:Lscala/collection/immutable/RedBlack$Tree;
Field	scala/collection/immutable/RedBlack$RedTree.left:Lscala/collection/immutable/RedBlack$Tree;
NameAndType	right:Lscala/collection/immutable/RedBlack$Tree;
Field	scala/collection/immutable/RedBlack$RedTree.right:Lscala/collection/immutable/RedBlack$Tree;
Asciz	scala/collection/immutable/RedBlack$NonEmpty;
class	scala/collection/immutable/RedBlack$NonEmpty
Asciz	(Lscala/collection/immutable/RedBlack;)V;
NameAndType	"<init>":(Lscala/collection/immutable/RedBlack;)V
Method	scala/collection/immutable/RedBlack$NonEmpty."<init>":(Lscala/collection/immutable/RedBlack;)V
Asciz	scala/Product$class;
class	scala/Product$class
Asciz	$init$;
Asciz	(Lscala/Product;)V;
NameAndType	$init$:(Lscala/Product;)V
Method	scala/Product$class.$init$:(Lscala/Product;)V
Asciz	this;
Asciz	Lscala/collection/immutable/RedBlack$RedTree;;
Asciz	$outer;
Asciz	Lscala/collection/immutable/RedBlack;;
Asciz	LocalVariableTable;
Asciz	(Lscala/collection/immutable/RedBlack<TA;>;TA;TB;Lscala/collection/immutable/RedBlack<TA;>.Tree<TB;>;Lscala/collection/immutable/RedBlack<TA;>.Tree<TB;>;)V;
Asciz	gd1$1;
Asciz	(Ljava/lang/Object;Ljava/lang/Object;Lscala/collection/immutable/RedBlack$Tree;Lscala/collection/immutable/RedBlack$Tree;)Z;
Asciz	()Ljava/lang/Object;;
NameAndType	key:()Ljava/lang/Object;
Method	scala/collection/immutable/RedBlack$RedTree.key:()Ljava/lang/Object;
Asciz	java/lang/Number;
class	java/lang/Number
Asciz	java/lang/Character;
class	java/lang/Character
Asciz	scala/runtime/BoxesRunTime;
class	scala/runtime/BoxesRunTime
Asciz	equals2;
Asciz	(Ljava/lang/Object;Ljava/lang/Object;)Z;
NameAndType	equals2:(Ljava/lang/Object;Ljava/lang/Object;)Z
Method	scala/runtime/BoxesRunTime.equals2:(Ljava/lang/Object;Ljava/lang/Object;)Z
Asciz	java/lang/Object;
class	java/lang/Object
Asciz	equals;
Asciz	(Ljava/lang/Object;)Z;
NameAndType	equals:(Ljava/lang/Object;)Z
Method	java/lang/Object.equals:(Ljava/lang/Object;)Z
NameAndType	value:()Ljava/lang/Object;
Method	scala/collection/immutable/RedBlack$RedTree.value:()Ljava/lang/Object;
Asciz	()Lscala/collection/immutable/RedBlack$Tree;;
NameAndType	left:()Lscala/collection/immutable/RedBlack$Tree;
Method	scala/collection/immutable/RedBlack$RedTree.left:()Lscala/collection/immutable/RedBlack$Tree;
NameAndType	right:()Lscala/collection/immutable/RedBlack$Tree;
Method	scala/collection/immutable/RedBlack$RedTree.right:()Lscala/collection/immutable/RedBlack$Tree;
Asciz	y0;
Asciz	y1;
Asciz	scala$collection$immutable$RedBlack$RedTree$$$outer;
Asciz	()Lscala/collection/immutable/RedBlack;;
Asciz	scala/collection/immutable/RedBlack$Tree;
class	scala/collection/immutable/RedBlack$Tree
NameAndType	$outer:Lscala/collection/immutable/RedBlack;
Field	scala/collection/immutable/RedBlack$Tree.$outer:Lscala/collection/immutable/RedBlack;
Asciz	canEqual;
Asciz	productElement;
Asciz	(I)Ljava/lang/Object;;
Asciz	java/lang/IndexOutOfBoundsException;
class	java/lang/IndexOutOfBoundsException
Asciz	boxToInteger;
Asciz	(I)Ljava/lang/Integer;;
NameAndType	boxToInteger:(I)Ljava/lang/Integer;
Method	scala/runtime/BoxesRunTime.boxToInteger:(I)Ljava/lang/Integer;
Asciz	toString;
Asciz	()Ljava/lang/String;;
NameAndType	toString:()Ljava/lang/String;
Method	java/lang/Object.toString:()Ljava/lang/String;
Asciz	(Ljava/lang/String;)V;
NameAndType	"<init>":(Ljava/lang/String;)V
Method	java/lang/IndexOutOfBoundsException."<init>":(Ljava/lang/String;)V
Asciz	scala/MatchError;
class	scala/MatchError
Method	scala/MatchError."<init>":(Ljava/lang/String;)V
Asciz	productArity;
Asciz	()I;
Asciz	productPrefix;
Asciz	RedTree;
String	RedTree
NameAndType	scala$collection$immutable$RedBlack$RedTree$$$outer:()Lscala/collection/immutable/RedBlack;
Method	scala/collection/immutable/RedBlack$RedTree.scala$collection$immutable$RedBlack$RedTree$$$outer:()Lscala/collection/immutable/RedBlack;
NameAndType	gd1$1:(Ljava/lang/Object;Ljava/lang/Object;Lscala/collection/immutable/RedBlack$Tree;Lscala/collection/immutable/RedBlack$Tree;)Z
Method	scala/collection/immutable/RedBlack$RedTree.gd1$1:(Ljava/lang/Object;Ljava/lang/Object;Lscala/collection/immutable/RedBlack$Tree;Lscala/collection/immutable/RedBlack$Tree;)Z
Asciz	scala/Equals;
class	scala/Equals
NameAndType	canEqual:(Ljava/lang/Object;)Z
InterfaceMethod	scala/Equals.canEqual:(Ljava/lang/Object;)Z
Asciz	temp41;
Asciz	temp42;
Asciz	temp43;
Asciz	temp44;
Asciz	temp45;
Asciz	scala/runtime/ScalaRunTime$;
class	scala/runtime/ScalaRunTime$
Asciz	MODULE$;
Asciz	Lscala/runtime/ScalaRunTime$;;
NameAndType	MODULE$:Lscala/runtime/ScalaRunTime$;
Field	scala/runtime/ScalaRunTime$.MODULE$:Lscala/runtime/ScalaRunTime$;
Asciz	_toString;
Asciz	(Lscala/Product;)Ljava/lang/String;;
NameAndType	_toString:(Lscala/Product;)Ljava/lang/String;
Method	scala/runtime/ScalaRunTime$._toString:(Lscala/Product;)Ljava/lang/String;
Asciz	hashCode;
Asciz	_hashCode;
Asciz	(Lscala/Product;)I;
NameAndType	_hashCode:(Lscala/Product;)I
Method	scala/runtime/ScalaRunTime$._hashCode:(Lscala/Product;)I
Asciz	copy;
Asciz	(Ljava/lang/Object;Ljava/lang/Object;Lscala/collection/immutable/RedBlack$Tree;Lscala/collection/immutable/RedBlack$Tree;)Lscala/collection/immutable/RedBlack$RedTree;;
NameAndType	"<init>":(Lscala/collection/immutable/RedBlack;Ljava/lang/Object;Ljava/lang/Object;Lscala/collection/immutable/RedBlack$Tree;Lscala/collection/immutable/RedBlack$Tree;)V
Method	scala/collection/immutable/RedBlack$RedTree."<init>":(Lscala/collection/immutable/RedBlack;Ljava/lang/Object;Ljava/lang/Object;Lscala/collection/immutable/RedBlack$Tree;Lscala/collection/immutable/RedBlack$Tree;)V
Asciz	isBlack;
Asciz	()Z;
Asciz	()Lscala/collection/immutable/RedBlack<TA;>.Tree<TB;>;;
Asciz	()TB;;
Asciz	()TA;;
Asciz	copy$default$1;
Asciz	copy$default$2;
Asciz	copy$default$3;
Asciz	copy$default$4;
Asciz	productElements;
Asciz	()Lscala/collection/Iterator;;
Asciz	(Lscala/Product;)Lscala/collection/Iterator;;
NameAndType	productElements:(Lscala/Product;)Lscala/collection/Iterator;
Method	scala/Product$class.productElements:(Lscala/Product;)Lscala/collection/Iterator;
Asciz	Deprecated;
Asciz	productIterator;
NameAndType	productIterator:(Lscala/Product;)Lscala/collection/Iterator;
Method	scala/Product$class.productIterator:(Lscala/Product;)Lscala/collection/Iterator;
Asciz	<B:Ljava/lang/Object;>Lscala/collection/immutable/RedBlack<TA;>.NonEmpty<TB;>;Lscala/ScalaObject;Lscala/Product;;
Asciz	Scala;
Asciz	InnerClasses;
Asciz	scala/collection/immutable/RedBlack;
class	scala/collection/immutable/RedBlack
Asciz	Tree;
Asciz	NonEmpty;
Asciz	scala/ScalaObject;
class	scala/ScalaObject
Asciz	scala/Product;
class	scala/Product
Asciz	java/io/Serializable;
class	java/io/Serializable

{
private final scala.collection.immutable.RedBlack$Tree right;
  Signature: Lscala/collection/immutable/RedBlack$Tree;
  Signature: length = 0x2
   00 05 

private final scala.collection.immutable.RedBlack$Tree left;
  Signature: Lscala/collection/immutable/RedBlack$Tree;
  Signature: length = 0x2
   00 05 

private final java.lang.Object value;
  Signature: Ljava/lang/Object;
  Signature: length = 0x2
   00 0A 

private final java.lang.Object key;
  Signature: Ljava/lang/Object;
  Signature: length = 0x2
   00 0C 

public scala.collection.immutable.RedBlack$RedTree(scala.collection.immutable.RedBlack, java.lang.Object, java.lang.Object, scala.collection.immutable.RedBlack$Tree, scala.collection.immutable.RedBlack$Tree);
  Signature: (Lscala/collection/immutable/RedBlack;Ljava/lang/Object;Ljava/lang/Object;Lscala/collection/immutable/RedBlack$Tree;Lscala/collection/immutable/RedBlack$Tree;)V
  Code:
   Stack=2, Locals=6, Args_size=6
	aload_0
	aload_2
	putfield	Field key:Ljava/lang/Object;
	aload_0
	aload_3
	putfield	Field value:Ljava/lang/Object;
	aload_0
	aload	4
	putfield	Field left:Lscala/collection/immutable/RedBlack$Tree;
	aload_0
	aload	5
	putfield	Field right:Lscala/collection/immutable/RedBlack$Tree;
	aload_0
	aload_1
	invokespecial	Method scala/collection/immutable/RedBlack$NonEmpty."<init>":(Lscala/collection/immutable/RedBlack;)V
	aload_0
	invokestatic	Method scala/Product$class.$init$:(Lscala/Product;)V
	return
  Labels:
  LocalVariableTable: 
   Start  Length  Slot  Name   Signature
   0      32      0    this       Lscala/collection/immutable/RedBlack$RedTree;
   0      32      1    $outer       Lscala/collection/immutable/RedBlack;
   0      32      2    key       Ljava/lang/Object;
   0      32      3    value       Ljava/lang/Object;
   0      32      4    left       Lscala/collection/immutable/RedBlack$Tree;
   0      32      5    right       Lscala/collection/immutable/RedBlack$Tree;

  Signature: length = 0x2
   00 2B 

private final boolean gd1$1(java.lang.Object, java.lang.Object, scala.collection.immutable.RedBlack$Tree, scala.collection.immutable.RedBlack$Tree);
  Signature: (Ljava/lang/Object;Ljava/lang/Object;Lscala/collection/immutable/RedBlack$Tree;Lscala/collection/immutable/RedBlack$Tree;)Z
  Code:
   Stack=2, Locals=9, Args_size=5
	aload_0
	invokevirtual	Method key:()Ljava/lang/Object;
	astore	5
	aload_1
	aload	5
	if_acmpne	l1 // aload_1
	iconst_1
	goto	l2 // ifeq
l1	aload_1
	ifnonnull	l3 // aload_1
	iconst_0
	goto	l2 // ifeq
l3	aload_1
	instanceof	class java/lang/Number
	ifne	l4 // aload_1
	aload_1
	instanceof	class java/lang/Character
	ifeq	l5 // aload_1
l4	aload_1
	aload	5
	invokestatic	Method scala/runtime/BoxesRunTime.equals2:(Ljava/lang/Object;Ljava/lang/Object;)Z
	goto	l2 // ifeq
l5	aload_1
	aload	5
	invokevirtual	Method java/lang/Object.equals:(Ljava/lang/Object;)Z
l2	ifeq	l6 // iconst_0
	aload_0
	invokevirtual	Method value:()Ljava/lang/Object;
	astore	6
	aload_2
	aload	6
	if_acmpne	l7 // aload_2
	iconst_1
	goto	l8 // ifeq
l7	aload_2
	ifnonnull	l9 // aload_2
	iconst_0
	goto	l8 // ifeq
l9	aload_2
	instanceof	class java/lang/Number
	ifne	l10 // aload_2
	aload_2
	instanceof	class java/lang/Character
	ifeq	l11 // aload_2
l10	aload_2
	aload	6
	invokestatic	Method scala/runtime/BoxesRunTime.equals2:(Ljava/lang/Object;Ljava/lang/Object;)Z
	goto	l8 // ifeq
l11	aload_2
	aload	6
	invokevirtual	Method java/lang/Object.equals:(Ljava/lang/Object;)Z
l8	ifeq	l6 // iconst_0
	aload_3
	aload_0
	invokevirtual	Method left:()Lscala/collection/immutable/RedBlack$Tree;
	astore	7
	dup
	ifnonnull	l12 // aload
	pop
	aload	7
	ifnull	l13 // aload
	goto	l6 // iconst_0
l12	aload	7
	invokevirtual	Method java/lang/Object.equals:(Ljava/lang/Object;)Z
	ifeq	l6 // iconst_0
l13	aload	4
	aload_0
	invokevirtual	Method right:()Lscala/collection/immutable/RedBlack$Tree;
	astore	8
	dup
	ifnonnull	l14 // aload
	pop
	aload	8
	ifnull	l15 // iconst_1
	goto	l6 // iconst_0
l14	aload	8
	invokevirtual	Method java/lang/Object.equals:(Ljava/lang/Object;)Z
	ifeq	l6 // iconst_0
l15	iconst_1
	goto	l16 // ireturn
l6	iconst_0
l16	ireturn
  Labels:
   	l1 = 16 // aload_1
   	l3 = 24 // aload_1
   	l4 = 38 // aload_1
   	l5 = 47 // aload_1
   	l2 = 53 // ifeq
   	l7 = 72 // aload_2
   	l9 = 80 // aload_2
   	l10 = 94 // aload_2
   	l11 = 103 // aload_2
   	l8 = 109 // ifeq
   	l12 = 132 // aload
   	l13 = 140 // aload
   	l14 = 161 // aload
   	l15 = 169 // iconst_1
   	l6 = 173 // iconst_0
   	l16 = 174 // ireturn
  LocalVariableTable: 
   Start  Length  Slot  Name   Signature
   0      175      0    this       Lscala/collection/immutable/RedBlack$RedTree;
   12      44      5    y0       Ljava/lang/Object;
   68      44      6    y1       Ljava/lang/Object;


public scala.collection.immutable.RedBlack scala$collection$immutable$RedBlack$RedTree$$$outer();
  Signature: ()Lscala/collection/immutable/RedBlack;
  Code:
   Stack=1, Locals=1, Args_size=1
	aload_0
	getfield	Field scala/collection/immutable/RedBlack$Tree.$outer:Lscala/collection/immutable/RedBlack;
	areturn
  Labels:

public boolean canEqual(java.lang.Object);
  Signature: (Ljava/lang/Object;)Z
  Code:
   Stack=1, Locals=2, Args_size=2
	aload_1
	instanceof	class scala/collection/immutable/RedBlack$RedTree
	ireturn
  Labels:

public java.lang.Object productElement(int);
  Signature: (I)Ljava/lang/Object;
  Code:
   Stack=3, Locals=2, Args_size=2
	iload_1
	tableswitch{ //0 to 3
		0: 144;
		1: 118;
		2: 92;
		3: 66;
		default: 32 }
	iconst_1
	ifeq	l1 // new
	new	class java/lang/IndexOutOfBoundsException
	dup
	iload_1
	invokestatic	Method scala/runtime/BoxesRunTime.boxToInteger:(I)Ljava/lang/Integer;
	invokevirtual	Method java/lang/Object.toString:()Ljava/lang/String;
	invokespecial	Method java/lang/IndexOutOfBoundsException."<init>":(Ljava/lang/String;)V
	athrow
l1	new	class scala/MatchError
	dup
	iload_1
	invokestatic	Method scala/runtime/BoxesRunTime.boxToInteger:(I)Ljava/lang/Integer;
	invokevirtual	Method java/lang/Object.toString:()Ljava/lang/String;
	invokespecial	Method scala/MatchError."<init>":(Ljava/lang/String;)V
	athrow
	iconst_1
	ifeq	l2 // new
	aload_0
	invokevirtual	Method right:()Lscala/collection/immutable/RedBlack$Tree;
	goto	l3 // areturn
l2	new	class scala/MatchError
	dup
	iload_1
	invokestatic	Method scala/runtime/BoxesRunTime.boxToInteger:(I)Ljava/lang/Integer;
	invokevirtual	Method java/lang/Object.toString:()Ljava/lang/String;
	invokespecial	Method scala/MatchError."<init>":(Ljava/lang/String;)V
	athrow
	iconst_1
	ifeq	l4 // new
	aload_0
	invokevirtual	Method left:()Lscala/collection/immutable/RedBlack$Tree;
	goto	l3 // areturn
l4	new	class scala/MatchError
	dup
	iload_1
	invokestatic	Method scala/runtime/BoxesRunTime.boxToInteger:(I)Ljava/lang/Integer;
	invokevirtual	Method java/lang/Object.toString:()Ljava/lang/String;
	invokespecial	Method scala/MatchError."<init>":(Ljava/lang/String;)V
	athrow
	iconst_1
	ifeq	l5 // new
	aload_0
	invokevirtual	Method value:()Ljava/lang/Object;
	goto	l3 // areturn
l5	new	class scala/MatchError
	dup
	iload_1
	invokestatic	Method scala/runtime/BoxesRunTime.boxToInteger:(I)Ljava/lang/Integer;
	invokevirtual	Method java/lang/Object.toString:()Ljava/lang/String;
	invokespecial	Method scala/MatchError."<init>":(Ljava/lang/String;)V
	athrow
	iconst_1
	ifeq	l6 // new
	aload_0
	invokevirtual	Method key:()Ljava/lang/Object;
l3	areturn
l6	new	class scala/MatchError
	dup
	iload_1
	invokestatic	Method scala/runtime/BoxesRunTime.boxToInteger:(I)Ljava/lang/Integer;
	invokevirtual	Method java/lang/Object.toString:()Ljava/lang/String;
	invokespecial	Method scala/MatchError."<init>":(Ljava/lang/String;)V
	athrow
  Labels:
   	l1 = 51 // new
   	l2 = 77 // new
   	l4 = 103 // new
   	l5 = 129 // new
   	l3 = 152 // areturn
   	l6 = 153 // new

public int productArity();
  Signature: ()I
  Code:
   Stack=1, Locals=1, Args_size=1
	iconst_4
	ireturn
  Labels:

public java.lang.String productPrefix();
  Signature: ()Ljava/lang/String;
  Code:
   Stack=1, Locals=1, Args_size=1
	ldc	String RedTree
	areturn
  Labels:

public boolean equals(java.lang.Object);
  Signature: (Ljava/lang/Object;)Z
  Code:
   Stack=5, Locals=7, Args_size=2
	aload_0
	aload_1
	if_acmpeq	l1 // iconst_1
	aload_1
	instanceof	class scala/collection/immutable/RedBlack$RedTree
	ifeq	l2 // iconst_1
	aload_1
	checkcast	class scala/collection/immutable/RedBlack$RedTree
	invokevirtual	Method scala$collection$immutable$RedBlack$RedTree$$$outer:()Lscala/collection/immutable/RedBlack;
	aload_0
	invokevirtual	Method scala$collection$immutable$RedBlack$RedTree$$$outer:()Lscala/collection/immutable/RedBlack;
	if_acmpne	l2 // iconst_1
	aload_1
	checkcast	class scala/collection/immutable/RedBlack$RedTree
	astore_2
	aload_2
	invokevirtual	Method key:()Ljava/lang/Object;
	astore_3
	aload_2
	invokevirtual	Method value:()Ljava/lang/Object;
	astore	4
	aload_2
	invokevirtual	Method left:()Lscala/collection/immutable/RedBlack$Tree;
	astore	5
	aload_2
	invokevirtual	Method right:()Lscala/collection/immutable/RedBlack$Tree;
	astore	6
	aload_0
	aload_3
	aload	4
	aload	5
	aload	6
	invokespecial	Method gd1$1:(Ljava/lang/Object;Ljava/lang/Object;Lscala/collection/immutable/RedBlack$Tree;Lscala/collection/immutable/RedBlack$Tree;)Z
	ifeq	l3 // iconst_1
	aload_1
	checkcast	class scala/collection/immutable/RedBlack$RedTree
	aload_0
	invokeinterface	InterfaceMethod scala/Equals.canEqual:(Ljava/lang/Object;)Z
	goto	l4 // ifeq
l3	iconst_1
	ifeq	l5 // new
	iconst_0
	goto	l4 // ifeq
l5	new	class scala/MatchError
	dup
	aload_1
	invokevirtual	Method java/lang/Object.toString:()Ljava/lang/String;
	invokespecial	Method scala/MatchError."<init>":(Ljava/lang/String;)V
	athrow
l2	iconst_1
	ifeq	l6 // new
	iconst_0
l4	ifeq	l7 // iconst_0
l1	iconst_1
	goto	l8 // ireturn
l7	iconst_0
l8	ireturn
l6	new	class scala/MatchError
	dup
	aload_1
	invokevirtual	Method java/lang/Object.toString:()Ljava/lang/String;
	invokespecial	Method scala/MatchError."<init>":(Ljava/lang/String;)V
	athrow
  Labels:
   	l3 = 81 // iconst_1
   	l5 = 89 // new
   	l2 = 101 // iconst_1
   	l4 = 106 // ifeq
   	l1 = 109 // iconst_1
   	l7 = 113 // iconst_0
   	l8 = 114 // ireturn
   	l6 = 115 // new
  LocalVariableTable: 
   Start  Length  Slot  Name   Signature
   0      127      0    this       Lscala/collection/immutable/RedBlack$RedTree;
   31      70      2    temp41       Lscala/collection/immutable/RedBlack$RedTree;
   36      65      3    temp42       Ljava/lang/Object;
   42      59      4    temp43       Ljava/lang/Object;
   48      53      5    temp44       Lscala/collection/immutable/RedBlack$Tree;
   54      47      6    temp45       Lscala/collection/immutable/RedBlack$Tree;


public java.lang.String toString();
  Signature: ()Ljava/lang/String;
  Code:
   Stack=2, Locals=1, Args_size=1
	getstatic	Field scala/runtime/ScalaRunTime$.MODULE$:Lscala/runtime/ScalaRunTime$;
	aload_0
	invokevirtual	Method scala/runtime/ScalaRunTime$._toString:(Lscala/Product;)Ljava/lang/String;
	areturn
  Labels:

public int hashCode();
  Signature: ()I
  Code:
   Stack=2, Locals=1, Args_size=1
	getstatic	Field scala/runtime/ScalaRunTime$.MODULE$:Lscala/runtime/ScalaRunTime$;
	aload_0
	invokevirtual	Method scala/runtime/ScalaRunTime$._hashCode:(Lscala/Product;)I
	ireturn
  Labels:

public scala.collection.immutable.RedBlack$RedTree copy(java.lang.Object, java.lang.Object, scala.collection.immutable.RedBlack$Tree, scala.collection.immutable.RedBlack$Tree);
  Signature: (Ljava/lang/Object;Ljava/lang/Object;Lscala/collection/immutable/RedBlack$Tree;Lscala/collection/immutable/RedBlack$Tree;)Lscala/collection/immutable/RedBlack$RedTree;
  Code:
   Stack=7, Locals=5, Args_size=5
	new	class scala/collection/immutable/RedBlack$RedTree
	dup
	aload_0
	invokevirtual	Method scala$collection$immutable$RedBlack$RedTree$$$outer:()Lscala/collection/immutable/RedBlack;
	aload_1
	aload_2
	aload_3
	aload	4
	invokespecial	Method "<init>":(Lscala/collection/immutable/RedBlack;Ljava/lang/Object;Ljava/lang/Object;Lscala/collection/immutable/RedBlack$Tree;Lscala/collection/immutable/RedBlack$Tree;)V
	areturn
  Labels:
  LocalVariableTable: 
   Start  Length  Slot  Name   Signature
   0      17      0    this       Lscala/collection/immutable/RedBlack$RedTree;
   0      17      1    key       Ljava/lang/Object;
   0      17      2    value       Ljava/lang/Object;
   0      17      3    left       Lscala/collection/immutable/RedBlack$Tree;
   0      17      4    right       Lscala/collection/immutable/RedBlack$Tree;


public boolean isBlack();
  Signature: ()Z
  Code:
   Stack=1, Locals=1, Args_size=1
	iconst_0
	ireturn
  Labels:

public scala.collection.immutable.RedBlack$Tree right();
  Signature: ()Lscala/collection/immutable/RedBlack$Tree;
  Code:
   Stack=1, Locals=1, Args_size=1
	aload_0
	getfield	Field right:Lscala/collection/immutable/RedBlack$Tree;
	areturn
  Labels:
  Signature: length = 0x2
   00 FFFFFF8A 

public scala.collection.immutable.RedBlack$Tree left();
  Signature: ()Lscala/collection/immutable/RedBlack$Tree;
  Code:
   Stack=1, Locals=1, Args_size=1
	aload_0
	getfield	Field left:Lscala/collection/immutable/RedBlack$Tree;
	areturn
  Labels:
  Signature: length = 0x2
   00 FFFFFF8A 

public java.lang.Object value();
  Signature: ()Ljava/lang/Object;
  Code:
   Stack=1, Locals=1, Args_size=1
	aload_0
	getfield	Field value:Ljava/lang/Object;
	areturn
  Labels:
  Signature: length = 0x2
   00 FFFFFF8B 

public java.lang.Object key();
  Signature: ()Ljava/lang/Object;
  Code:
   Stack=1, Locals=1, Args_size=1
	aload_0
	getfield	Field key:Ljava/lang/Object;
	areturn
  Labels:
  Signature: length = 0x2
   00 FFFFFF8C 

public java.lang.Object copy$default$1();
  Signature: ()Ljava/lang/Object;
  Code:
   Stack=1, Locals=1, Args_size=1
	aload_0
	invokevirtual	Method key:()Ljava/lang/Object;
	areturn
  Labels:

public java.lang.Object copy$default$2();
  Signature: ()Ljava/lang/Object;
  Code:
   Stack=1, Locals=1, Args_size=1
	aload_0
	invokevirtual	Method value:()Ljava/lang/Object;
	areturn
  Labels:

public scala.collection.immutable.RedBlack$Tree copy$default$3();
  Signature: ()Lscala/collection/immutable/RedBlack$Tree;
  Code:
   Stack=1, Locals=1, Args_size=1
	aload_0
	invokevirtual	Method left:()Lscala/collection/immutable/RedBlack$Tree;
	areturn
  Labels:

public scala.collection.immutable.RedBlack$Tree copy$default$4();
  Signature: ()Lscala/collection/immutable/RedBlack$Tree;
  Code:
   Stack=1, Locals=1, Args_size=1
	aload_0
	invokevirtual	Method right:()Lscala/collection/immutable/RedBlack$Tree;
	areturn
  Labels:

public scala.collection.Iterator productElements();
  Signature: ()Lscala/collection/Iterator;
  Code:
   Stack=1, Locals=1, Args_size=1
	aload_0
	invokestatic	Method scala/Product$class.productElements:(Lscala/Product;)Lscala/collection/Iterator;
	areturn
  Labels:
  Deprecated: true

public scala.collection.Iterator productIterator();
  Signature: ()Lscala/collection/Iterator;
  Code:
   Stack=1, Locals=1, Args_size=1
	aload_0
	invokestatic	Method scala/Product$class.productIterator:(Lscala/Product;)Lscala/collection/Iterator;
	areturn
  Labels:

}

