Compiled from "RedBlack.scala"
public final class scala.collection.immutable.RedBlack$Empty$ extends scala.collection.immutable.RedBlack$Tree implements scala.ScalaObject,scala.Product,java.io.Serializable
  SourceFile: "RedBlack.scala"
  Scala: length = 0x
   
  Signature: length = 0x2
   00 FFFFFF9E 
  InnerClass: 
   public abstract Tree=class scala/collection/immutable/RedBlack$Tree of class scala/collection/immutable/RedBlack
   public RedTree=class scala/collection/immutable/RedBlack$RedTree of class scala/collection/immutable/RedBlack
   public abstract NonEmpty=class scala/collection/immutable/RedBlack$NonEmpty of class scala/collection/immutable/RedBlack
  minor version: 0
  major version: 49
  Constant pool:
Asciz	SourceFile;
Asciz	RedBlack.scala;
Asciz	Scala;
Asciz	productIterator;
Asciz	()Lscala/collection/Iterator;;
Asciz	Code;
Asciz	LineNumberTable;
Asciz	scala/Product$class;
class	scala/Product$class
Asciz	(Lscala/Product;)Lscala/collection/Iterator;;
NameAndType	productIterator:(Lscala/Product;)Lscala/collection/Iterator;
Method	scala/Product$class.productIterator:(Lscala/Product;)Lscala/collection/Iterator;
Asciz	productElements;
NameAndType	productElements:(Lscala/Product;)Lscala/collection/Iterator;
Method	scala/Product$class.productElements:(Lscala/Product;)Lscala/collection/Iterator;
Asciz	Deprecated;
Asciz	isEmpty;
Asciz	()Z;
Asciz	isBlack;
Asciz	lookup;
Asciz	(Ljava/lang/Object;)Lscala/collection/immutable/RedBlack$Tree;;
Asciz	this;
Asciz	Lscala/collection/immutable/RedBlack$Empty$;;
Asciz	k;
Asciz	Ljava/lang/Object;;
Asciz	LocalVariableTable;
Asciz	(TA;)Lscala/collection/immutable/RedBlack<TA;>.Tree<Lscala/runtime/Nothing$;>;;
Asciz	Signature;
Asciz	upd;
Asciz	(Ljava/lang/Object;Ljava/lang/Object;)Lscala/collection/immutable/RedBlack$Tree;;
Asciz	scala/collection/immutable/RedBlack$RedTree;
class	scala/collection/immutable/RedBlack$RedTree
Asciz	scala/collection/immutable/RedBlack$Empty$;
class	scala/collection/immutable/RedBlack$Empty$
Asciz	scala$collection$immutable$RedBlack$Empty$$$outer;
Asciz	()Lscala/collection/immutable/RedBlack;;
NameAndType	scala$collection$immutable$RedBlack$Empty$$$outer:()Lscala/collection/immutable/RedBlack;
Method	scala/collection/immutable/RedBlack$Empty$.scala$collection$immutable$RedBlack$Empty$$$outer:()Lscala/collection/immutable/RedBlack;
Asciz	scala/collection/immutable/RedBlack;
class	scala/collection/immutable/RedBlack
Asciz	Empty;
Asciz	()Lscala/collection/immutable/RedBlack$Empty$;;
NameAndType	Empty:()Lscala/collection/immutable/RedBlack$Empty$;
Method	scala/collection/immutable/RedBlack.Empty:()Lscala/collection/immutable/RedBlack$Empty$;
Asciz	<init>;
Asciz	(Lscala/collection/immutable/RedBlack;Ljava/lang/Object;Ljava/lang/Object;Lscala/collection/immutable/RedBlack$Tree;Lscala/collection/immutable/RedBlack$Tree;)V;
NameAndType	"<init>":(Lscala/collection/immutable/RedBlack;Ljava/lang/Object;Ljava/lang/Object;Lscala/collection/immutable/RedBlack$Tree;Lscala/collection/immutable/RedBlack$Tree;)V
Method	scala/collection/immutable/RedBlack$RedTree."<init>":(Lscala/collection/immutable/RedBlack;Ljava/lang/Object;Ljava/lang/Object;Lscala/collection/immutable/RedBlack$Tree;Lscala/collection/immutable/RedBlack$Tree;)V
Asciz	v;
Asciz	<B:Ljava/lang/Object;>(TA;TB;)Lscala/collection/immutable/RedBlack<TA;>.Tree<TB;>;;
Asciz	del;
Asciz	smallest;
Asciz	()Lscala/collection/immutable/RedBlack$NonEmpty;;
Asciz	java/util/NoSuchElementException;
class	java/util/NoSuchElementException
Asciz	empty map;
String	empty map
Asciz	(Ljava/lang/String;)V;
NameAndType	"<init>":(Ljava/lang/String;)V
Method	java/util/NoSuchElementException."<init>":(Ljava/lang/String;)V
Asciz	()Lscala/collection/immutable/RedBlack<TA;>.NonEmpty<Lscala/runtime/Nothing$;>;;
Asciz	iterator;
Asciz	scala/collection/Iterator$;
class	scala/collection/Iterator$
Asciz	MODULE$;
Asciz	Lscala/collection/Iterator$;;
NameAndType	MODULE$:Lscala/collection/Iterator$;
Field	scala/collection/Iterator$.MODULE$:Lscala/collection/Iterator$;
Asciz	empty;
NameAndType	empty:()Lscala/collection/Iterator;
Method	scala/collection/Iterator$.empty:()Lscala/collection/Iterator;
Asciz	()Lscala/collection/Iterator<Lscala/Tuple2<TA;Lscala/runtime/Nothing$;>;>;;
Asciz	toStream;
Asciz	()Lscala/collection/immutable/Stream;;
Asciz	scala/collection/immutable/Stream$;
class	scala/collection/immutable/Stream$
Asciz	Lscala/collection/immutable/Stream$;;
NameAndType	MODULE$:Lscala/collection/immutable/Stream$;
Field	scala/collection/immutable/Stream$.MODULE$:Lscala/collection/immutable/Stream$;
NameAndType	empty:()Lscala/collection/immutable/Stream;
Method	scala/collection/immutable/Stream$.empty:()Lscala/collection/immutable/Stream;
Asciz	()Lscala/collection/immutable/Stream<Lscala/Tuple2<TA;Lscala/runtime/Nothing$;>;>;;
Asciz	foreach;
Asciz	(Lscala/Function2;)V;
Asciz	f;
Asciz	Lscala/Function2;;
Asciz	<U:Ljava/lang/Object;>(Lscala/Function2<TA;Lscala/runtime/Nothing$;TU;>;)V;
Asciz	visit;
Asciz	(Ljava/lang/Object;Lscala/Function3;)Lscala/Tuple2;;
Asciz	scala/Tuple2;
class	scala/Tuple2
Asciz	scala/runtime/BoxesRunTime;
class	scala/runtime/BoxesRunTime
Asciz	boxToBoolean;
Asciz	(Z)Ljava/lang/Boolean;;
NameAndType	boxToBoolean:(Z)Ljava/lang/Boolean;
Method	scala/runtime/BoxesRunTime.boxToBoolean:(Z)Ljava/lang/Boolean;
Asciz	(Ljava/lang/Object;Ljava/lang/Object;)V;
NameAndType	"<init>":(Ljava/lang/Object;Ljava/lang/Object;)V
Method	scala/Tuple2."<init>":(Ljava/lang/Object;Ljava/lang/Object;)V
Asciz	input;
Asciz	Lscala/Function3;;
Asciz	<T:Ljava/lang/Object;>(TT;Lscala/Function3<TT;TA;Lscala/runtime/Nothing$;Lscala/Tuple2<Ljava/lang/Boolean;TT;>;>;)Lscala/Tuple2<Ljava/lang/Boolean;TT;>;;
Asciz	range;
Asciz	(Lscala/Option;Lscala/Option;)Lscala/collection/immutable/RedBlack$Empty$;;
Asciz	from;
Asciz	Lscala/Option;;
Asciz	until;
Asciz	(Lscala/Option<TA;>;Lscala/Option<TA;>;)Lscala/collection/immutable/RedBlack<TA;>.Empty;;
Asciz	first;
Asciz	()Lscala/runtime/Nothing$;;
Asciz	last;
Asciz	count;
Asciz	()I;
Asciz	toString;
Asciz	()Ljava/lang/String;;
String	Empty
Asciz	productPrefix;
Asciz	productArity;
Asciz	productElement;
Asciz	(I)Ljava/lang/Object;;
Asciz	java/lang/IndexOutOfBoundsException;
class	java/lang/IndexOutOfBoundsException
Asciz	boxToInteger;
Asciz	(I)Ljava/lang/Integer;;
NameAndType	boxToInteger:(I)Ljava/lang/Integer;
Method	scala/runtime/BoxesRunTime.boxToInteger:(I)Ljava/lang/Integer;
Asciz	java/lang/Object;
class	java/lang/Object
NameAndType	toString:()Ljava/lang/String;
Method	java/lang/Object.toString:()Ljava/lang/String;
Method	java/lang/IndexOutOfBoundsException."<init>":(Ljava/lang/String;)V
Asciz	canEqual;
Asciz	(Ljava/lang/Object;)Z;
Asciz	readResolve;
Asciz	()Ljava/lang/Object;;
Asciz	scala/collection/immutable/RedBlack$Tree;
class	scala/collection/immutable/RedBlack$Tree
Asciz	$outer;
Asciz	Lscala/collection/immutable/RedBlack;;
NameAndType	$outer:Lscala/collection/immutable/RedBlack;
Field	scala/collection/immutable/RedBlack$Tree.$outer:Lscala/collection/immutable/RedBlack;
NameAndType	last:()Lscala/runtime/Nothing$;
Method	scala/collection/immutable/RedBlack$Empty$.last:()Lscala/runtime/Nothing$;
NameAndType	first:()Lscala/runtime/Nothing$;
Method	scala/collection/immutable/RedBlack$Empty$.first:()Lscala/runtime/Nothing$;
Asciz	(Lscala/Option;Lscala/Option;)Lscala/collection/immutable/RedBlack$Tree;;
NameAndType	range:(Lscala/Option;Lscala/Option;)Lscala/collection/immutable/RedBlack$Empty$;
Method	scala/collection/immutable/RedBlack$Empty$.range:(Lscala/Option;Lscala/Option;)Lscala/collection/immutable/RedBlack$Empty$;
Asciz	(Lscala/collection/immutable/RedBlack;)V;
NameAndType	"<init>":(Lscala/collection/immutable/RedBlack;)V
Method	scala/collection/immutable/RedBlack$Tree."<init>":(Lscala/collection/immutable/RedBlack;)V
Asciz	$init$;
Asciz	(Lscala/Product;)V;
NameAndType	$init$:(Lscala/Product;)V
Method	scala/Product$class.$init$:(Lscala/Product;)V
Asciz	(Lscala/collection/immutable/RedBlack<TA;>;)V;
Asciz	Lscala/collection/immutable/RedBlack<TA;>.Tree<Lscala/runtime/Nothing$;>;Lscala/ScalaObject;Lscala/Product;;
Asciz	InnerClasses;
Asciz	Tree;
Asciz	RedTree;
Asciz	scala/collection/immutable/RedBlack$NonEmpty;
class	scala/collection/immutable/RedBlack$NonEmpty
Asciz	NonEmpty;
Asciz	scala/ScalaObject;
class	scala/ScalaObject
Asciz	scala/Product;
class	scala/Product
Asciz	java/io/Serializable;
class	java/io/Serializable

{
public scala.collection.Iterator productIterator();
  Signature: ()Lscala/collection/Iterator;
  Code:
   Stack=1, Locals=1, Args_size=1
	aload_0
	invokestatic	Method scala/Product$class.productIterator:(Lscala/Product;)Lscala/collection/Iterator;
	areturn
  Labels:

public scala.collection.Iterator productElements();
  Signature: ()Lscala/collection/Iterator;
  Code:
   Stack=1, Locals=1, Args_size=1
	aload_0
	invokestatic	Method scala/Product$class.productElements:(Lscala/Product;)Lscala/collection/Iterator;
	areturn
  Labels:
  Deprecated: true

public boolean isEmpty();
  Signature: ()Z
  Code:
   Stack=1, Locals=1, Args_size=1
	iconst_1
	ireturn
  Labels:

public boolean isBlack();
  Signature: ()Z
  Code:
   Stack=1, Locals=1, Args_size=1
	iconst_1
	ireturn
  Labels:

public scala.collection.immutable.RedBlack$Tree lookup(java.lang.Object);
  Signature: (Ljava/lang/Object;)Lscala/collection/immutable/RedBlack$Tree;
  Code:
   Stack=1, Locals=2, Args_size=2
	aload_0
	areturn
  Labels:
  LocalVariableTable: 
   Start  Length  Slot  Name   Signature
   0      2      0    this       Lscala/collection/immutable/RedBlack$Empty$;
   0      2      1    k       Ljava/lang/Object;

  Signature: length = 0x2
   00 1B 

public scala.collection.immutable.RedBlack$Tree upd(java.lang.Object, java.lang.Object);
  Signature: (Ljava/lang/Object;Ljava/lang/Object;)Lscala/collection/immutable/RedBlack$Tree;
  Code:
   Stack=7, Locals=3, Args_size=3
	new	class scala/collection/immutable/RedBlack$RedTree
	dup
	aload_0
	invokevirtual	Method scala$collection$immutable$RedBlack$Empty$$$outer:()Lscala/collection/immutable/RedBlack;
	aload_1
	aload_2
	aload_0
	invokevirtual	Method scala$collection$immutable$RedBlack$Empty$$$outer:()Lscala/collection/immutable/RedBlack;
	invokevirtual	Method scala/collection/immutable/RedBlack.Empty:()Lscala/collection/immutable/RedBlack$Empty$;
	aload_0
	invokevirtual	Method scala$collection$immutable$RedBlack$Empty$$$outer:()Lscala/collection/immutable/RedBlack;
	invokevirtual	Method scala/collection/immutable/RedBlack.Empty:()Lscala/collection/immutable/RedBlack$Empty$;
	invokespecial	Method scala/collection/immutable/RedBlack$RedTree."<init>":(Lscala/collection/immutable/RedBlack;Ljava/lang/Object;Ljava/lang/Object;Lscala/collection/immutable/RedBlack$Tree;Lscala/collection/immutable/RedBlack$Tree;)V
	areturn
  Labels:
  LocalVariableTable: 
   Start  Length  Slot  Name   Signature
   0      28      0    this       Lscala/collection/immutable/RedBlack$Empty$;
   0      28      1    k       Ljava/lang/Object;
   0      28      2    v       Ljava/lang/Object;

  Signature: length = 0x2
   00 32 

public scala.collection.immutable.RedBlack$Tree del(java.lang.Object);
  Signature: (Ljava/lang/Object;)Lscala/collection/immutable/RedBlack$Tree;
  Code:
   Stack=1, Locals=2, Args_size=2
	aload_0
	areturn
  Labels:
  LocalVariableTable: 
   Start  Length  Slot  Name   Signature
   0      2      0    this       Lscala/collection/immutable/RedBlack$Empty$;
   0      2      1    k       Ljava/lang/Object;

  Signature: length = 0x2
   00 1B 

public scala.collection.immutable.RedBlack$NonEmpty smallest();
  Signature: ()Lscala/collection/immutable/RedBlack$NonEmpty;
  Code:
   Stack=3, Locals=1, Args_size=1
	new	class java/util/NoSuchElementException
	dup
	ldc	String empty map
	invokespecial	Method java/util/NoSuchElementException."<init>":(Ljava/lang/String;)V
	athrow
  Labels:
  Signature: length = 0x2
   00 3D 

public scala.collection.Iterator iterator();
  Signature: ()Lscala/collection/Iterator;
  Code:
   Stack=1, Locals=1, Args_size=1
	getstatic	Field scala/collection/Iterator$.MODULE$:Lscala/collection/Iterator$;
	invokevirtual	Method scala/collection/Iterator$.empty:()Lscala/collection/Iterator;
	areturn
  Labels:
  Signature: length = 0x2
   00 48 

public scala.collection.immutable.Stream toStream();
  Signature: ()Lscala/collection/immutable/Stream;
  Code:
   Stack=1, Locals=1, Args_size=1
	getstatic	Field scala/collection/immutable/Stream$.MODULE$:Lscala/collection/immutable/Stream$;
	invokevirtual	Method scala/collection/immutable/Stream$.empty:()Lscala/collection/immutable/Stream;
	areturn
  Labels:
  Signature: length = 0x2
   00 52 

public void foreach(scala.Function2);
  Signature: (Lscala/Function2;)V
  Code:
   Stack=0, Locals=2, Args_size=2
	return
  Labels:
  LocalVariableTable: 
   Start  Length  Slot  Name   Signature
   0      1      0    this       Lscala/collection/immutable/RedBlack$Empty$;
   0      1      1    f       Lscala/Function2;

  Signature: length = 0x2
   00 57 

public scala.Tuple2 visit(java.lang.Object, scala.Function3);
  Signature: (Ljava/lang/Object;Lscala/Function3;)Lscala/Tuple2;
  Code:
   Stack=4, Locals=4, Args_size=3
	new	class scala/Tuple2
	dup
	iconst_1
	istore_3
	iload_3
	invokestatic	Method scala/runtime/BoxesRunTime.boxToBoolean:(Z)Ljava/lang/Boolean;
	aload_1
	invokespecial	Method scala/Tuple2."<init>":(Ljava/lang/Object;Ljava/lang/Object;)V
	areturn
  Labels:
  LocalVariableTable: 
   Start  Length  Slot  Name   Signature
   0      15      0    this       Lscala/collection/immutable/RedBlack$Empty$;
   0      15      1    input       Ljava/lang/Object;
   0      15      2    f       Lscala/Function3;

  Signature: length = 0x2
   00 67 
  Deprecated: true

public scala.collection.immutable.RedBlack$Empty$ range(scala.Option, scala.Option);
  Signature: (Lscala/Option;Lscala/Option;)Lscala/collection/immutable/RedBlack$Empty$;
  Code:
   Stack=1, Locals=3, Args_size=3
	aload_0
	areturn
  Labels:
  LocalVariableTable: 
   Start  Length  Slot  Name   Signature
   0      2      0    this       Lscala/collection/immutable/RedBlack$Empty$;
   0      2      1    from       Lscala/Option;
   0      2      2    until       Lscala/Option;

  Signature: length = 0x2
   00 6D 

public scala.runtime.Nothing$ first();
  Signature: ()Lscala/runtime/Nothing$;
  Code:
   Stack=3, Locals=1, Args_size=1
	new	class java/util/NoSuchElementException
	dup
	ldc	String empty map
	invokespecial	Method java/util/NoSuchElementException."<init>":(Ljava/lang/String;)V
	athrow
  Labels:

public scala.runtime.Nothing$ last();
  Signature: ()Lscala/runtime/Nothing$;
  Code:
   Stack=3, Locals=1, Args_size=1
	new	class java/util/NoSuchElementException
	dup
	ldc	String empty map
	invokespecial	Method java/util/NoSuchElementException."<init>":(Ljava/lang/String;)V
	athrow
  Labels:

public int count();
  Signature: ()I
  Code:
   Stack=1, Locals=1, Args_size=1
	iconst_0
	ireturn
  Labels:

public final java.lang.String toString();
  Signature: ()Ljava/lang/String;
  Code:
   Stack=1, Locals=1, Args_size=1
	ldc	String Empty
	areturn
  Labels:

public java.lang.String productPrefix();
  Signature: ()Ljava/lang/String;
  Code:
   Stack=1, Locals=1, Args_size=1
	ldc	String Empty
	areturn
  Labels:

public int productArity();
  Signature: ()I
  Code:
   Stack=1, Locals=1, Args_size=1
	iconst_0
	ireturn
  Labels:

public java.lang.Object productElement(int);
  Signature: (I)Ljava/lang/Object;
  Code:
   Stack=3, Locals=2, Args_size=2
	new	class java/lang/IndexOutOfBoundsException
	dup
	iload_1
	invokestatic	Method scala/runtime/BoxesRunTime.boxToInteger:(I)Ljava/lang/Integer;
	invokevirtual	Method java/lang/Object.toString:()Ljava/lang/String;
	invokespecial	Method java/lang/IndexOutOfBoundsException."<init>":(Ljava/lang/String;)V
	athrow
  Labels:

public boolean canEqual(java.lang.Object);
  Signature: (Ljava/lang/Object;)Z
  Code:
   Stack=1, Locals=2, Args_size=2
	aload_1
	instanceof	class scala/collection/immutable/RedBlack$Empty$
	ireturn
  Labels:

public java.lang.Object readResolve();
  Signature: ()Ljava/lang/Object;
  Code:
   Stack=1, Locals=1, Args_size=1
	aload_0
	invokevirtual	Method scala$collection$immutable$RedBlack$Empty$$$outer:()Lscala/collection/immutable/RedBlack;
	invokevirtual	Method scala/collection/immutable/RedBlack.Empty:()Lscala/collection/immutable/RedBlack$Empty$;
	areturn
  Labels:

public scala.collection.immutable.RedBlack scala$collection$immutable$RedBlack$Empty$$$outer();
  Signature: ()Lscala/collection/immutable/RedBlack;
  Code:
   Stack=1, Locals=1, Args_size=1
	aload_0
	getfield	Field scala/collection/immutable/RedBlack$Tree.$outer:Lscala/collection/immutable/RedBlack;
	areturn
  Labels:

public java.lang.Object last();
  Signature: ()Ljava/lang/Object;
  Code:
   Stack=1, Locals=1, Args_size=1
	aload_0
	invokevirtual	Method last:()Lscala/runtime/Nothing$;
	athrow
  Labels:

public java.lang.Object first();
  Signature: ()Ljava/lang/Object;
  Code:
   Stack=1, Locals=1, Args_size=1
	aload_0
	invokevirtual	Method first:()Lscala/runtime/Nothing$;
	athrow
  Labels:

public scala.collection.immutable.RedBlack$Tree range(scala.Option, scala.Option);
  Signature: (Lscala/Option;Lscala/Option;)Lscala/collection/immutable/RedBlack$Tree;
  Code:
   Stack=3, Locals=3, Args_size=3
	aload_0
	aload_1
	aload_2
	invokevirtual	Method range:(Lscala/Option;Lscala/Option;)Lscala/collection/immutable/RedBlack$Empty$;
	areturn
  Labels:
  LocalVariableTable: 
   Start  Length  Slot  Name   Signature
   0      7      0    this       Lscala/collection/immutable/RedBlack$Empty$;
   0      7      1    from       Lscala/Option;
   0      7      2    until       Lscala/Option;

  Signature: length = 0x2
   00 FFFFFF93 

public scala.collection.immutable.RedBlack$Empty$(scala.collection.immutable.RedBlack);
  Signature: (Lscala/collection/immutable/RedBlack;)V
  Code:
   Stack=2, Locals=2, Args_size=2
	aload_0
	aload_1
	invokespecial	Method scala/collection/immutable/RedBlack$Tree."<init>":(Lscala/collection/immutable/RedBlack;)V
	aload_0
	invokestatic	Method scala/Product$class.$init$:(Lscala/Product;)V
	return
  Labels:
  LocalVariableTable: 
   Start  Length  Slot  Name   Signature
   0      10      0    this       Lscala/collection/immutable/RedBlack$Empty$;
   0      10      1    $outer       Lscala/collection/immutable/RedBlack;

  Signature: length = 0x2
   00 FFFFFF9D 

}

