Compiled from "RedBlack.scala"
public abstract class scala.collection.immutable.RedBlack extends java.lang.Object implements scala.ScalaObject,java.io.Serializable
  SourceFile: "RedBlack.scala"
  Signature: length = 0x2
   00 5F 
  ScalaSig: length = 0x12DB
   05 00 FFFFFF84 60 06 05 01 02 FFFFFF81 00 09 02 08 52 65 64
   42 6C 61 63 6B 0A 02 03 04 01 09 69 6D 6D 75 74
   61 62 6C 65 0A 02 05 06 01 0A 63 6F 6C 6C 65 63
   74 69 6F 6E 0A 01 07 01 05 73 63 61 6C 61 03 00
   15 02 0A 1E 13 03 00 0B 13 10 02 0C 11 0D 01 0D
   0A 02 0E 0F 01 04 6C 61 6E 67 0A 01 10 01 04 6A
   61 76 61 09 02 12 0D 02 06 4F 62 6A 65 63 74 10
   02 14 15 0D 01 06 09 02 16 06 02 0B 53 63 61 6C
   61 4F 62 6A 65 63 74 08 05 18 00 FFFFFF84 00 19 01 06
   3C 69 6E 69 74 3E 14 01 1A 10 03 1B 00 1C 0D 01
   02 10 02 1D 1E 0C 00 04 08 1F 00 FFFFFF84 FFFFFF80 FFFFFF80 FFFFFFC2 00
   20 02 01 41 11 02 21 24 10 02 14 22 09 02 23 06
   02 07 4E 6F 74 68 69 6E 67 10 02 14 25 09 02 26
   06 02 03 41 6E 79 08 05 28 00 FFFFFF86 00 29 01 09 69
   73 53 6D 61 6C 6C 65 72 14 03 2A 2D 2F 10 02 14
   2B 09 02 2C 06 02 07 42 6F 6F 6C 65 61 6E 08 05
   2E 27 FFFFFFC0 00 1C 01 01 78 08 05 30 27 FFFFFFC0 00 1C 01
   01 79 08 05 32 00 FFFFFF84 04 33 01 07 62 6C 61 63 6B
   65 6E 15 03 34 FFFFFF82 06 14 03 35 FFFFFF82 07 10 04 36 37
   FFFFFF82 05 0D 01 00 06 05 38 00 FFFFFF81 00 39 02 04 54 72
   65 65 15 02 3A 3F 13 03 37 0B 13 08 05 18 37 FFFFFF84
   00 3C 14 01 3D 10 03 36 37 3E 10 02 1D 3F 04 08
   40 37 FFFFFF84 FFFFFF80 FFFFFF84 FFFFFFC2 00 20 02 01 42 08 05 42 37 FFFFFF86
   00 43 01 07 69 73 45 6D 70 74 79 15 01 2A 08 05
   45 37 FFFFFF86 00 43 01 07 69 73 42 6C 61 63 6B 08 05
   47 37 FFFFFF86 00 48 01 06 6C 6F 6F 6B 75 70 14 02 3D
   49 08 05 2E 46 FFFFFFC0 00 1C 08 05 4B 37 FFFFFF84 00 4C 01
   06 75 70 64 61 74 65 15 02 4D 50 14 03 4E 53 55
   10 03 36 37 4F 10 02 1D 50 04 08 51 4A FFFFFF84 FFFFFF80 FFFFFF80
   FFFFFFC2 00 52 02 02 42 31 11 02 3E 24 08 05 54 4A FFFFFFC0
   00 1C 01 01 6B 08 05 56 4A FFFFFFC0 00 4F 01 01 76 08
   05 58 37 FFFFFF84 00 59 01 06 64 65 6C 65 74 65 14 02
   3D 5A 08 05 54 57 FFFFFFC0 00 1C 08 05 5C 37 FFFFFF86 00 5D
   01 07 66 6F 72 65 61 63 68 15 02 5E 68 14 02 5F
   62 10 02 14 60 09 02 61 06 02 04 55 6E 69 74 08
   05 63 5B FFFFFFC0 00 64 01 01 66 10 05 14 65 1C 3E 67
   09 02 66 06 02 09 46 75 6E 63 74 69 6F 6E 32 10
   02 1D 68 04 08 69 5B FFFFFF84 FFFFFF80 FFFFFF80 FFFFFFC2 00 20 02 01 55
   08 05 6B 37 FFFFFF86 00 6C 01 05 76 69 73 69 74 15 02
   6D 73 14 02 6E 79 14 02 6F 75 10 04 14 70 2A 72
   09 02 71 06 02 06 54 75 70 6C 65 32 10 02 1D 73
   04 08 74 6A FFFFFF84 FFFFFF80 FFFFFF80 FFFFFFC2 00 20 02 01 54 08 05 63
   6A FFFFFFC0 00 76 10 06 14 77 72 1C 3E 6F 09 02 78 06
   02 09 46 75 6E 63 74 69 6F 6E 33 08 05 7A 6A FFFFFFC0
   00 72 01 05 69 6E 70 75 74 28 03 6A 7C 7F 10 02
   14 7D 09 02 7E 06 02 0A 64 65 70 72 65 63 61 74
   65 64 21 02 FFFFFF81 00 01 15 75 73 65 20 60 66 6F 72
   65 61 63 68 27 20 69 6E 73 74 65 61 64 08 07 FFFFFF81
   02 37 FFFFFF86 00 FFFFFF81 03 01 08 74 6F 53 74 72 65 61 6D
   15 02 FFFFFF81 04 10 05 1B FFFFFF81 05 FFFFFF81 07 09 03 FFFFFF81 06 02
   02 06 53 74 72 65 61 6D 10 04 14 70 1C 3E 08 07
   FFFFFF81 09 37 FFFFFF86 00 FFFFFF81 0A 01 08 69 74 65 72 61 74 6F
   72 15 02 FFFFFF81 0B 10 06 FFFFFF81 0C FFFFFF81 0D FFFFFF81 07 0D 01 04
   09 03 FFFFFF81 0E 04 02 08 49 74 65 72 61 74 6F 72 08
   07 FFFFFF81 10 37 FFFFFF84 00 FFFFFF81 0A 01 08 65 6C 65 6D 65 6E
   74 73 28 05 FFFFFF81 0F 7C FFFFFF81 12 21 02 FFFFFF81 13 01 16 75
   73 65 20 60 69 74 65 72 61 74 6F 72 27 20 69 6E
   73 74 65 61 64 08 07 FFFFFF81 15 37 FFFFFF86 00 FFFFFF81 16 01 03
   75 70 64 15 04 FFFFFF81 17 FFFFFF81 1A 14 06 FFFFFF81 18 FFFFFF81 1B FFFFFF81
   1C 10 04 36 37 FFFFFF81 19 10 03 1D FFFFFF81 1A 04 09 51 FFFFFF81
   14 FFFFFF84 FFFFFF80 FFFFFF80 FFFFFFC2 00 52 08 06 54 FFFFFF81 14 FFFFFFC0 00 1C 08
   07 56 FFFFFF81 14 FFFFFFC0 00 FFFFFF81 19 08 07 FFFFFF81 1E 37 FFFFFF86 00 FFFFFF81
   1F 01 03 64 65 6C 14 03 3D FFFFFF81 20 08 06 54 FFFFFF81 1D
   FFFFFFC0 00 1C 08 07 FFFFFF81 22 37 FFFFFF86 00 FFFFFF81 23 01 08 73 6D
   61 6C 6C 65 73 74 15 02 FFFFFF81 24 10 04 36 FFFFFF81 25 3E
   06 07 FFFFFF81 26 00 FFFFFF81 00 FFFFFF81 27 02 08 4E 6F 6E 45 6D
   70 74 79 15 04 FFFFFF81 28 FFFFFF81 2B 13 05 FFFFFF81 25 FFFFFF81 29 13
   10 04 36 37 FFFFFF81 2A 10 03 1D FFFFFF81 2B 04 09 40 FFFFFF81 25
   FFFFFF84 FFFFFF80 FFFFFF84 FFFFFFC2 00 20 08 07 18 FFFFFF81 25 FFFFFF84 00 FFFFFF81 2D 14
   02 FFFFFF81 2E 10 05 36 FFFFFF81 25 FFFFFF81 2A 08 06 42 FFFFFF81 25 FFFFFF84
   00 43 08 08 FFFFFF81 31 FFFFFF81 25 FFFFFF86 00 FFFFFF81 32 01 03 6B 65
   79 15 01 1C 08 08 FFFFFF81 34 FFFFFF81 25 FFFFFF86 00 FFFFFF81 35 01 05
   76 61 6C 75 65 15 02 FFFFFF81 2A 08 08 FFFFFF81 37 FFFFFF81 25 FFFFFF86
   00 FFFFFF81 38 01 04 6C 65 66 74 15 02 FFFFFF81 29 08 08 FFFFFF81
   3A FFFFFF81 25 FFFFFF86 00 FFFFFF81 38 01 05 72 69 67 68 74 08 07
   47 FFFFFF81 25 FFFFFF84 00 FFFFFF81 3C 14 04 FFFFFF81 29 FFFFFF81 3D 08 06 54
   FFFFFF81 3B FFFFFFC0 00 1C 08 08 FFFFFF81 15 FFFFFF81 25 FFFFFF84 00 FFFFFF81 3F 15
   04 FFFFFF81 40 FFFFFF81 43 14 06 FFFFFF81 41 FFFFFF81 45 FFFFFF81 46 10 04 36
   37 FFFFFF81 42 10 03 1D FFFFFF81 43 04 0A 51 FFFFFF81 3E FFFFFF84 FFFFFF80 FFFFFF80
   FFFFFFC2 00 FFFFFF81 44 11 03 FFFFFF81 2A 24 08 06 54 FFFFFF81 3E FFFFFFC0 00
   1C 08 07 56 FFFFFF81 3E FFFFFFC0 00 FFFFFF81 42 08 08 FFFFFF81 1E FFFFFF81 25
   FFFFFF84 00 FFFFFF81 48 14 04 FFFFFF81 29 FFFFFF81 49 08 06 54 FFFFFF81 47 FFFFFFC0
   00 1C 08 08 FFFFFF81 22 FFFFFF81 25 FFFFFF84 00 FFFFFF81 4B 15 02 FFFFFF81 2E
   08 08 FFFFFF81 02 FFFFFF81 25 FFFFFF84 00 FFFFFF81 4D 15 02 FFFFFF81 4E 10 05
   1B FFFFFF81 05 FFFFFF81 4F 10 05 14 70 1C FFFFFF81 2A 08 08 FFFFFF81 09
   FFFFFF81 25 FFFFFF84 00 FFFFFF81 51 15 02 FFFFFF81 52 10 06 FFFFFF81 0C FFFFFF81 0D
   FFFFFF81 4F 08 07 5C FFFFFF81 25 FFFFFF84 00 FFFFFF81 54 15 04 FFFFFF81 55 FFFFFF81
   59 14 03 5F FFFFFF81 56 08 07 63 FFFFFF81 53 FFFFFFC0 00 FFFFFF81 57 10
   07 14 65 1C FFFFFF81 2A FFFFFF81 58 10 03 1D FFFFFF81 59 04 09 69
   FFFFFF81 53 FFFFFF84 FFFFFF80 FFFFFF80 FFFFFFC2 00 20 08 07 6B FFFFFF81 25 FFFFFF84 00 FFFFFF81
   5B 15 04 FFFFFF81 5C FFFFFF81 60 14 04 FFFFFF81 5D FFFFFF81 63 14 04 FFFFFF81
   5E FFFFFF81 61 10 05 14 70 2A FFFFFF81 5F 10 03 1D FFFFFF81 60 04
   09 74 FFFFFF81 5A FFFFFF84 FFFFFF80 FFFFFF80 FFFFFFC2 00 20 08 07 63 FFFFFF81 5A FFFFFFC0
   00 FFFFFF81 62 10 09 14 77 FFFFFF81 5F 1C FFFFFF81 2A FFFFFF81 5E 08 07
   7A FFFFFF81 5A FFFFFFC0 00 FFFFFF81 5F 28 04 FFFFFF81 5A 7C 7F 08 08 FFFFFF81
   66 FFFFFF81 25 FFFFFF84 20 FFFFFF81 67 01 05 72 61 6E 67 65 14 06
   FFFFFF81 29 FFFFFF81 68 FFFFFF81 6D 08 08 FFFFFF81 69 FFFFFF81 65 FFFFFFC0 00 FFFFFF81 6A
   01 04 66 72 6F 6D 10 04 14 FFFFFF81 6B 1C 09 03 FFFFFF81 6C
   06 02 06 4F 70 74 69 6F 6E 08 08 FFFFFF81 6E FFFFFF81 65 FFFFFFC0
   00 FFFFFF81 6A 01 05 75 6E 74 69 6C 08 08 FFFFFF81 70 FFFFFF81 25
   FFFFFF84 00 FFFFFF81 32 01 05 66 69 72 73 74 08 08 FFFFFF81 72 FFFFFF81
   25 FFFFFF84 00 FFFFFF81 32 01 04 6C 61 73 74 08 08 FFFFFF81 74 FFFFFF81
   25 FFFFFF84 00 FFFFFF81 75 01 05 63 6F 75 6E 74 15 02 FFFFFF81 76
   10 03 14 FFFFFF81 77 09 03 FFFFFF81 78 06 02 03 49 6E 74 28
   04 FFFFFF81 25 FFFFFF81 7A 10 03 14 FFFFFF81 7B 09 03 FFFFFF81 7C 06 02
   0C 73 65 72 69 61 6C 69 7A 61 62 6C 65 08 07 FFFFFF81
   66 37 FFFFFF86 00 FFFFFF81 7E 14 05 3D FFFFFF81 7F FFFFFF82 00 08 08 FFFFFF81
   69 FFFFFF81 7D FFFFFFC0 00 FFFFFF81 6A 08 08 FFFFFF81 6E FFFFFF81 7D FFFFFFC0 00 FFFFFF81
   6A 08 07 FFFFFF81 70 37 FFFFFF86 00 FFFFFF81 32 08 07 FFFFFF81 72 37 FFFFFF86
   00 FFFFFF81 32 08 07 FFFFFF81 74 37 FFFFFF86 00 FFFFFF81 75 28 03 37 FFFFFF81
   7A 10 03 1D FFFFFF82 06 04 08 40 31 FFFFFF84 FFFFFF80 FFFFFF80 FFFFFFC2 00 20
   08 06 FFFFFF82 08 31 FFFFFFC0 00 35 01 01 74 08 07 FFFFFF82 0A 00
   FFFFFF84 04 FFFFFF82 0B 01 06 6D 6B 54 72 65 65 15 04 FFFFFF82 0C
   FFFFFF82 15 14 0C FFFFFF82 0D FFFFFF82 16 FFFFFF82 17 FFFFFF82 18 FFFFFF82 19 FFFFFF82 1C
   12 06 FFFFFF82 0E FFFFFF82 10 FFFFFF82 13 06 0A FFFFFF82 0F 00 FFFFFF84 FFFFFF80 FFFFFF80
   FFFFFF80 00 FFFFFF82 0D 02 0C 3C 72 65 66 69 6E 65 6D 65 6E
   74 3E 10 03 14 FFFFFF82 11 09 03 FFFFFF82 12 06 02 07 50 72
   6F 64 75 63 74 10 05 36 FFFFFF81 25 FFFFFF82 14 10 03 1D FFFFFF82
   15 04 09 40 FFFFFF82 09 FFFFFF84 FFFFFF80 FFFFFF80 FFFFFFC2 00 20 08 06 45 FFFFFF82
   09 FFFFFFC0 00 2A 08 06 54 FFFFFF82 09 FFFFFFC0 00 1C 08 07 56 FFFFFF82
   09 FFFFFFC0 00 FFFFFF82 14 08 08 FFFFFF82 1A FFFFFF82 09 FFFFFFC0 00 FFFFFF82 1B 01
   01 6C 10 04 36 37 FFFFFF82 14 08 08 FFFFFF82 1D FFFFFF82 09 FFFFFFC0 00
   FFFFFF82 1B 01 01 72 07 07 FFFFFF82 1F 00 FFFFFF88 42 FFFFFF82 20 01 05
   45 6D 70 74 79 10 03 36 FFFFFF82 21 06 0A FFFFFF82 22 00 FFFFFF84
   FFFFFF80 FFFFFF80 FFFFFF88 42 FFFFFF82 23 02 05 45 6D 70 74 79 13 07 FFFFFF82
   21 FFFFFF82 24 13 FFFFFF82 10 10 03 36 37 21 08 07 18 FFFFFF82 21
   FFFFFF84 00 FFFFFF82 26 14 02 FFFFFF82 20 08 06 42 FFFFFF82 21 FFFFFF84 00 43
   08 06 45 FFFFFF82 21 FFFFFF84 00 43 08 07 47 FFFFFF82 21 FFFFFF84 00 FFFFFF82
   2A 14 04 FFFFFF82 24 FFFFFF82 2B 08 06 54 FFFFFF82 29 FFFFFFC0 00 1C 08
   08 FFFFFF81 15 FFFFFF82 21 FFFFFF84 00 FFFFFF82 2D 15 04 FFFFFF82 2E FFFFFF82 31 14
   06 FFFFFF82 2F FFFFFF82 32 FFFFFF82 33 10 04 36 37 FFFFFF82 30 10 03 1D
   FFFFFF82 31 04 09 40 FFFFFF82 2C FFFFFF84 FFFFFF80 FFFFFF80 FFFFFFC2 00 20 08 06 54
   FFFFFF82 2C FFFFFFC0 00 1C 08 07 56 FFFFFF82 2C FFFFFFC0 00 FFFFFF82 30 08 08
   FFFFFF81 1E FFFFFF82 21 FFFFFF84 00 FFFFFF82 35 14 04 FFFFFF82 24 FFFFFF82 36 08 06
   54 FFFFFF82 34 FFFFFFC0 00 1C 08 08 FFFFFF81 22 FFFFFF82 21 FFFFFF84 00 FFFFFF82 38
   15 02 FFFFFF82 39 10 04 36 FFFFFF81 25 21 08 08 FFFFFF81 09 FFFFFF82 21
   FFFFFF84 00 FFFFFF82 3B 15 02 FFFFFF82 3C 10 06 FFFFFF81 0C FFFFFF81 0D FFFFFF82 3D
   10 04 14 70 1C 21 08 08 FFFFFF81 02 FFFFFF82 21 FFFFFF84 00 FFFFFF82 3F
   15 02 FFFFFF82 40 10 05 1B FFFFFF81 05 FFFFFF82 3D 08 07 5C FFFFFF82 21
   FFFFFF84 00 FFFFFF82 42 15 04 FFFFFF82 43 FFFFFF82 47 14 03 5F FFFFFF82 44 08
   07 63 FFFFFF82 41 FFFFFFC0 00 FFFFFF82 45 10 06 14 65 1C 21 FFFFFF82 46
   10 03 1D FFFFFF82 47 04 09 69 FFFFFF82 41 FFFFFF84 FFFFFF80 FFFFFF80 FFFFFFC2 00 20
   08 07 6B FFFFFF82 21 FFFFFF84 00 FFFFFF82 49 15 04 FFFFFF82 4A FFFFFF82 4E 14
   04 FFFFFF82 4B FFFFFF82 51 14 04 FFFFFF82 4C FFFFFF82 4F 10 05 14 70 2A
   FFFFFF82 4D 10 03 1D FFFFFF82 4E 04 09 74 FFFFFF82 48 FFFFFF84 FFFFFF80 FFFFFF80 FFFFFFC2
   00 20 08 07 63 FFFFFF82 48 FFFFFFC0 00 FFFFFF82 50 10 08 14 77 FFFFFF82
   4D 1C 21 FFFFFF82 4C 08 07 7A FFFFFF82 48 FFFFFFC0 00 FFFFFF82 4D 28 04
   FFFFFF82 48 7C 7F 08 08 FFFFFF81 66 FFFFFF82 21 FFFFFF84 00 FFFFFF82 54 14 06
   FFFFFF82 20 FFFFFF82 55 FFFFFF82 56 08 08 FFFFFF81 69 FFFFFF82 53 FFFFFFC0 00 FFFFFF81 6A
   08 08 FFFFFF81 6E FFFFFF82 53 FFFFFFC0 00 FFFFFF81 6A 08 08 FFFFFF81 70 FFFFFF82 21
   FFFFFF84 00 FFFFFF82 58 15 01 21 08 08 FFFFFF81 72 FFFFFF82 21 FFFFFF84 00 FFFFFF82
   58 08 08 FFFFFF81 74 FFFFFF82 21 FFFFFF84 00 FFFFFF81 75 08 0B FFFFFF82 5C FFFFFF82
   21 FFFFFF84 FFFFFF80 FFFFFF80 FFFFFF84 22 FFFFFF82 5D 01 08 74 6F 53 74 72 69
   6E 67 14 02 FFFFFF82 5E 10 03 0C FFFFFF82 5F 09 03 FFFFFF82 60 0D
   02 06 53 74 72 69 6E 67 08 0B FFFFFF82 62 FFFFFF82 21 FFFFFF84 FFFFFF80
   FFFFFF80 FFFFFF84 20 FFFFFF82 63 01 0D 70 72 6F 64 75 63 74 50 72
   65 66 69 78 15 02 FFFFFF82 5E 08 0B FFFFFF82 65 FFFFFF82 21 FFFFFF84 FFFFFF80
   FFFFFF80 FFFFFF84 20 FFFFFF81 75 01 0C 70 72 6F 64 75 63 74 41 72
   69 74 79 08 0B FFFFFF82 67 FFFFFF82 21 FFFFFF84 FFFFFF80 FFFFFF80 FFFFFF84 20 FFFFFF82 68
   01 0E 70 72 6F 64 75 63 74 45 6C 65 6D 65 6E 74
   14 03 24 FFFFFF82 69 08 0A FFFFFF82 6A FFFFFF82 66 FFFFFF81 FFFFFF80 FFFFFFC0 00 FFFFFF81
   76 01 03 78 24 31 08 0B FFFFFF82 6C FFFFFF82 21 FFFFFF84 FFFFFF80 FFFFFF80 FFFFFF84
   20 FFFFFF82 6D 01 12 70 72 6F 64 75 63 74 45 6C 65 6D
   65 6E 74 4E 61 6D 65 14 04 FFFFFF82 5E FFFFFF82 6E 08 0A FFFFFF82
   6A FFFFFF82 6B FFFFFF81 FFFFFF80 FFFFFFC0 00 FFFFFF81 76 08 0B FFFFFF82 70 FFFFFF82 21 FFFFFF84
   FFFFFF80 FFFFFF80 FFFFFF84 20 FFFFFF82 71 01 08 63 61 6E 45 71 75 61 6C
   14 03 2A FFFFFF82 72 08 09 FFFFFF82 6A FFFFFF82 6F FFFFFF81 FFFFFF80 FFFFFFC0 00 24
   08 0B FFFFFF82 74 FFFFFF82 21 FFFFFF84 FFFFFF80 FFFFFF80 FFFFFF84 08 FFFFFF82 75 01 0B 72
   65 61 64 52 65 73 6F 6C 76 65 14 01 0B 28 04 FFFFFF82
   21 FFFFFF81 7A 28 04 FFFFFF82 1E FFFFFF81 7A 06 06 FFFFFF82 79 00 40 FFFFFF82
   7A 02 07 52 65 64 54 72 65 65 15 04 FFFFFF82 7B FFFFFF82 7E
   13 07 FFFFFF82 78 FFFFFF82 7C 13 FFFFFF82 10 10 05 36 FFFFFF81 25 FFFFFF82 7D
   10 03 1D FFFFFF82 7E 04 09 40 FFFFFF82 78 FFFFFF84 FFFFFF80 FFFFFF84 FFFFFFC2 00 20
   08 0B FFFFFF81 31 FFFFFF82 78 FFFFFF82 FFFFFFCA FFFFFF80 FFFFFF84 20 FFFFFF81 32 08 0A FFFFFF83
   01 FFFFFF82 78 FFFFFF82 FFFFFF88 FFFFFFA0 FFFFFF80 04 1C 01 04 6B 65 79 20 08
   0B FFFFFF81 34 FFFFFF82 78 FFFFFF82 FFFFFFCA FFFFFF80 FFFFFF84 20 FFFFFF83 03 15 02 FFFFFF82 7D
   08 0B FFFFFF83 05 FFFFFF82 78 FFFFFF82 FFFFFF88 FFFFFFA0 FFFFFF80 04 FFFFFF82 7D 01 06 76
   61 6C 75 65 20 08 0B FFFFFF81 37 FFFFFF82 78 FFFFFF82 FFFFFFCA FFFFFF80 FFFFFF84 20
   FFFFFF83 07 15 02 FFFFFF83 08 10 04 36 37 FFFFFF82 7D 08 0B FFFFFF83 0A
   FFFFFF82 78 FFFFFF82 FFFFFF88 FFFFFFA0 FFFFFF80 04 FFFFFF83 08 01 05 6C 65 66 74 20
   08 0B FFFFFF81 3A FFFFFF82 78 FFFFFF82 FFFFFFCA FFFFFF80 FFFFFF84 20 FFFFFF83 07 08 0B FFFFFF83
   0D FFFFFF82 78 FFFFFF82 FFFFFF88 FFFFFFA0 FFFFFF80 04 FFFFFF83 08 01 06 72 69 67 68
   74 20 08 07 18 FFFFFF82 78 FFFFFF84 00 FFFFFF83 0F 14 0A FFFFFF83 10 FFFFFF83
   11 FFFFFF83 12 FFFFFF83 13 FFFFFF83 14 10 05 36 FFFFFF82 78 FFFFFF82 7D 08 07
   FFFFFF81 31 FFFFFF83 0E FFFFFFC0 00 1C 08 08 FFFFFF81 34 FFFFFF83 0E FFFFFFC0 00 FFFFFF82
   7D 08 08 FFFFFF81 37 FFFFFF83 0E FFFFFFC0 00 FFFFFF83 08 08 08 FFFFFF81 3A FFFFFF83
   0E FFFFFFC0 00 FFFFFF83 08 08 06 45 FFFFFF82 78 FFFFFF84 00 43 08 0A FFFFFF83
   17 FFFFFF82 78 FFFFFF81 FFFFFF80 FFFFFF84 00 FFFFFF83 18 01 04 63 6F 70 79 15
   04 FFFFFF83 19 FFFFFF83 1C 14 0A FFFFFF83 1A FFFFFF83 1D FFFFFF83 1E FFFFFF83 1F FFFFFF83
   21 10 05 36 FFFFFF82 78 FFFFFF83 1B 10 03 1D FFFFFF83 1C 04 09 40
   FFFFFF83 16 FFFFFF84 FFFFFF80 FFFFFF80 FFFFFFC2 00 20 08 09 FFFFFF81 31 FFFFFF83 16 FFFFFF90 FFFFFF80
   FFFFFFC0 00 1C 08 0A FFFFFF81 34 FFFFFF83 16 FFFFFF90 FFFFFF80 FFFFFFC0 00 FFFFFF83 1B 08
   0A FFFFFF81 37 FFFFFF83 16 FFFFFF90 FFFFFF80 FFFFFFC0 00 FFFFFF83 20 10 04 36 37 FFFFFF83
   1B 08 0A FFFFFF81 3A FFFFFF83 16 FFFFFF90 FFFFFF80 FFFFFFC0 00 FFFFFF83 20 08 0A FFFFFF83
   23 FFFFFF82 78 FFFFFF91 FFFFFF80 FFFFFF84 00 FFFFFF83 24 01 0E 63 6F 70 79 24
   64 65 66 61 75 6C 74 24 31 15 04 FFFFFF83 25 FFFFFF83 2F 2A
   03 1C FFFFFF83 26 2B 02 FFFFFF83 27 10 04 FFFFFF83 28 FFFFFF83 2D 0D 02
   FFFFFF83 29 0A 04 FFFFFF83 2A FFFFFF83 2B 01 09 75 6E 63 68 65 63
   6B 65 64 0A 03 FFFFFF83 2C 06 01 0A 61 6E 6E 6F 74 61
   74 69 6F 6E 09 04 FFFFFF83 2E FFFFFF83 29 02 11 75 6E 63 68
   65 63 6B 65 64 56 61 72 69 61 6E 63 65 04 09 40
   FFFFFF83 22 FFFFFF84 FFFFFF80 FFFFFF80 FFFFFFC2 00 20 08 0A FFFFFF83 31 FFFFFF82 78 FFFFFF91 FFFFFF80
   FFFFFF84 00 FFFFFF83 32 01 0E 63 6F 70 79 24 64 65 66 61 75
   6C 74 24 32 15 04 FFFFFF83 33 FFFFFF83 34 2A 04 FFFFFF82 7D FFFFFF83 26
   04 09 40 FFFFFF83 30 FFFFFF84 FFFFFF80 FFFFFF80 FFFFFFC2 00 20 08 0A FFFFFF83 36 FFFFFF82
   78 FFFFFF91 FFFFFF80 FFFFFF84 00 FFFFFF83 37 01 0E 63 6F 70 79 24 64 65
   66 61 75 6C 74 24 33 15 04 FFFFFF83 38 FFFFFF83 39 2A 04 FFFFFF83
   08 FFFFFF83 26 04 09 40 FFFFFF83 35 FFFFFF84 FFFFFF80 FFFFFF80 FFFFFFC2 00 20 08 0A
   FFFFFF83 3B FFFFFF82 78 FFFFFF91 FFFFFF80 FFFFFF84 00 FFFFFF83 3C 01 0E 63 6F 70 79
   24 64 65 66 61 75 6C 74 24 34 15 04 FFFFFF83 38 FFFFFF83 3D
   04 09 40 FFFFFF83 3A FFFFFF84 FFFFFF80 FFFFFF80 FFFFFFC2 00 20 08 0B FFFFFF83 3F FFFFFF82
   78 FFFFFF84 FFFFFF80 FFFFFF80 FFFFFF84 20 FFFFFF83 40 01 08 68 61 73 68 43 6F
   64 65 14 02 FFFFFF81 76 08 0B FFFFFF82 5C FFFFFF82 78 FFFFFF84 FFFFFF80 FFFFFF80 FFFFFF84
   20 FFFFFF83 42 14 02 FFFFFF83 43 10 04 FFFFFF83 44 FFFFFF83 47 0E 03 14
   FFFFFF83 45 09 03 FFFFFF83 46 06 01 06 50 72 65 64 65 66 09
   04 FFFFFF82 60 FFFFFF83 48 0A 03 FFFFFF83 46 06 08 0B FFFFFF83 4A FFFFFF82 78
   FFFFFF84 FFFFFF80 FFFFFF80 FFFFFF84 20 FFFFFF83 4B 01 06 65 71 75 61 6C 73 14
   03 2A FFFFFF83 4C 08 09 FFFFFF82 6A FFFFFF83 49 FFFFFF81 FFFFFF80 FFFFFFC0 00 24 08
   0B FFFFFF82 62 FFFFFF82 78 FFFFFF84 FFFFFF80 FFFFFF80 FFFFFF84 20 FFFFFF82 63 08 0B FFFFFF82 65
   FFFFFF82 78 FFFFFF84 FFFFFF80 FFFFFF80 FFFFFF84 20 FFFFFF81 75 08 0B FFFFFF82 67 FFFFFF82 78 FFFFFF84
   FFFFFF80 FFFFFF80 FFFFFF84 20 FFFFFF83 50 14 03 24 FFFFFF83 51 08 0A FFFFFF82 6A FFFFFF83
   4F FFFFFF81 FFFFFF80 FFFFFFC0 00 FFFFFF81 76 08 0B FFFFFF82 6C FFFFFF82 78 FFFFFF84 FFFFFF80 FFFFFF80
   FFFFFF84 20 FFFFFF83 53 14 04 FFFFFF82 5E FFFFFF83 54 08 0A FFFFFF82 6A FFFFFF83 52
   FFFFFF81 FFFFFF80 FFFFFFC0 00 FFFFFF81 76 08 0B FFFFFF82 70 FFFFFF82 78 FFFFFF84 FFFFFF80 FFFFFF80 FFFFFF84
   20 FFFFFF83 56 14 03 2A FFFFFF83 57 08 09 FFFFFF82 6A FFFFFF83 55 FFFFFF81 FFFFFF80
   FFFFFFC0 00 24 28 04 FFFFFF82 78 FFFFFF81 7A 07 09 FFFFFF83 5A 00 FFFFFF81 FFFFFF80
   FFFFFF88 02 FFFFFF83 5B 01 07 52 65 64 54 72 65 65 10 03 36
   FFFFFF83 5C 06 0A FFFFFF82 79 00 FFFFFF84 FFFFFF81 FFFFFF80 FFFFFF88 02 FFFFFF83 5D 13 04
   FFFFFF83 5C 0B 13 08 07 18 FFFFFF83 5C FFFFFF84 00 FFFFFF83 5F 14 02 FFFFFF83
   5B 08 0A FFFFFF83 61 FFFFFF83 5C FFFFFF81 FFFFFF80 FFFFFF84 40 FFFFFF83 62 01 05 61
   70 70 6C 79 15 04 FFFFFF83 63 FFFFFF83 66 14 0A FFFFFF83 64 FFFFFF83 67
   FFFFFF83 68 FFFFFF83 69 FFFFFF83 6B 10 05 36 FFFFFF82 78 FFFFFF83 65 10 03 1D
   FFFFFF83 66 04 09 40 FFFFFF83 60 FFFFFF84 FFFFFF80 FFFFFF80 FFFFFFC2 00 20 08 07 FFFFFF81
   31 FFFFFF83 60 FFFFFFC0 00 1C 08 08 FFFFFF81 34 FFFFFF83 60 FFFFFFC0 00 FFFFFF83 65
   08 08 FFFFFF81 37 FFFFFF83 60 FFFFFFC0 00 FFFFFF83 6A 10 04 36 37 FFFFFF83 65
   08 08 FFFFFF81 3A FFFFFF83 60 FFFFFFC0 00 FFFFFF83 6A 08 0A FFFFFF83 6D FFFFFF83 5C
   FFFFFF81 FFFFFF80 FFFFFF84 40 FFFFFF83 6E 01 07 75 6E 61 70 70 6C 79 15
   04 FFFFFF83 6F FFFFFF83 75 14 04 FFFFFF83 70 FFFFFF83 77 10 05 14 FFFFFF81 6B
   FFFFFF83 71 10 0A 14 FFFFFF83 72 1C FFFFFF83 74 FFFFFF83 76 FFFFFF83 76 09 03
   FFFFFF83 73 06 02 06 54 75 70 6C 65 34 10 03 1D FFFFFF83 75
   04 09 40 FFFFFF83 6C FFFFFF84 FFFFFF80 FFFFFF80 FFFFFFC2 00 20 10 04 36 37 FFFFFF83
   74 08 08 FFFFFF83 78 FFFFFF83 6C FFFFFFC0 00 FFFFFF83 79 01 03 78 24 30
   10 05 36 FFFFFF82 78 FFFFFF83 74 06 06 FFFFFF83 7B 00 40 FFFFFF83 7C 02
   09 42 6C 61 63 6B 54 72 65 65 15 04 FFFFFF83 7D FFFFFF84 00
   13 07 FFFFFF83 7A FFFFFF83 7E 13 FFFFFF82 10 10 05 36 FFFFFF81 25 FFFFFF83 7F
   10 03 1D FFFFFF84 00 04 09 40 FFFFFF83 7A FFFFFF84 FFFFFF80 FFFFFF84 FFFFFFC2 00 20
   08 0B FFFFFF81 31 FFFFFF83 7A FFFFFF82 FFFFFFCA FFFFFF80 FFFFFF84 20 FFFFFF81 32 08 0A FFFFFF83
   01 FFFFFF83 7A FFFFFF82 FFFFFF88 FFFFFFA0 FFFFFF80 04 1C 08 0B FFFFFF81 34 FFFFFF83 7A FFFFFF82
   FFFFFFCA FFFFFF80 FFFFFF84 20 FFFFFF84 04 15 02 FFFFFF83 7F 08 0B FFFFFF83 05 FFFFFF83 7A
   FFFFFF82 FFFFFF88 FFFFFFA0 FFFFFF80 04 FFFFFF83 7F 08 0B FFFFFF81 37 FFFFFF83 7A FFFFFF82 FFFFFFCA FFFFFF80
   FFFFFF84 20 FFFFFF84 07 15 02 FFFFFF84 08 10 04 36 37 FFFFFF83 7F 08 0B
   FFFFFF83 0A FFFFFF83 7A FFFFFF82 FFFFFF88 FFFFFFA0 FFFFFF80 04 FFFFFF84 08 08 0B FFFFFF81 3A FFFFFF83
   7A FFFFFF82 FFFFFFCA FFFFFF80 FFFFFF84 20 FFFFFF84 07 08 0B FFFFFF83 0D FFFFFF83 7A FFFFFF82 FFFFFF88
   FFFFFFA0 FFFFFF80 04 FFFFFF84 08 08 07 18 FFFFFF83 7A FFFFFF84 00 FFFFFF84 0D 14 0A
   FFFFFF84 0E FFFFFF84 0F FFFFFF84 10 FFFFFF84 11 FFFFFF84 12 10 05 36 FFFFFF83 7A FFFFFF83
   7F 08 07 FFFFFF81 31 FFFFFF84 0C FFFFFFC0 00 1C 08 08 FFFFFF81 34 FFFFFF84 0C
   FFFFFFC0 00 FFFFFF83 7F 08 08 FFFFFF81 37 FFFFFF84 0C FFFFFFC0 00 FFFFFF84 08 08 08
   FFFFFF81 3A FFFFFF84 0C FFFFFFC0 00 FFFFFF84 08 08 06 45 FFFFFF83 7A FFFFFF84 00 43
   08 0A FFFFFF83 17 FFFFFF83 7A FFFFFF81 FFFFFF80 FFFFFF84 00 FFFFFF84 15 15 04 FFFFFF84 16
   FFFFFF84 19 14 0A FFFFFF84 17 FFFFFF84 1A FFFFFF84 1B FFFFFF84 1C FFFFFF84 1E 10 05
   36 FFFFFF83 7A FFFFFF84 18 10 03 1D FFFFFF84 19 04 09 40 FFFFFF84 14 FFFFFF84
   FFFFFF80 FFFFFF80 FFFFFFC2 00 20 08 09 FFFFFF81 31 FFFFFF84 14 FFFFFF90 FFFFFF80 FFFFFFC0 00 1C
   08 0A FFFFFF81 34 FFFFFF84 14 FFFFFF90 FFFFFF80 FFFFFFC0 00 FFFFFF84 18 08 0A FFFFFF81 37
   FFFFFF84 14 FFFFFF90 FFFFFF80 FFFFFFC0 00 FFFFFF84 1D 10 04 36 37 FFFFFF84 18 08 0A
   FFFFFF81 3A FFFFFF84 14 FFFFFF90 FFFFFF80 FFFFFFC0 00 FFFFFF84 1D 08 0A FFFFFF83 23 FFFFFF83 7A
   FFFFFF91 FFFFFF80 FFFFFF84 00 FFFFFF84 20 15 04 FFFFFF83 25 FFFFFF84 21 04 09 40 FFFFFF84
   1F FFFFFF84 FFFFFF80 FFFFFF80 FFFFFFC2 00 20 08 0A FFFFFF83 31 FFFFFF83 7A FFFFFF91 FFFFFF80 FFFFFF84
   00 FFFFFF84 23 15 04 FFFFFF84 24 FFFFFF84 25 2A 04 FFFFFF83 7F FFFFFF83 26 04
   09 40 FFFFFF84 22 FFFFFF84 FFFFFF80 FFFFFF80 FFFFFFC2 00 20 08 0A FFFFFF83 36 FFFFFF83 7A
   FFFFFF91 FFFFFF80 FFFFFF84 00 FFFFFF84 27 15 04 FFFFFF84 28 FFFFFF84 29 2A 04 FFFFFF84 08
   FFFFFF83 26 04 09 40 FFFFFF84 26 FFFFFF84 FFFFFF80 FFFFFF80 FFFFFFC2 00 20 08 0A FFFFFF83
   3B FFFFFF83 7A FFFFFF91 FFFFFF80 FFFFFF84 00 FFFFFF84 2B 15 04 FFFFFF84 28 FFFFFF84 2C 04
   09 40 FFFFFF84 2A FFFFFF84 FFFFFF80 FFFFFF80 FFFFFFC2 00 20 08 0B FFFFFF83 3F FFFFFF83 7A
   FFFFFF84 FFFFFF80 FFFFFF80 FFFFFF84 20 FFFFFF83 40 08 0B FFFFFF82 5C FFFFFF83 7A FFFFFF84 FFFFFF80 FFFFFF80
   FFFFFF84 20 FFFFFF83 42 08 0B FFFFFF83 4A FFFFFF83 7A FFFFFF84 FFFFFF80 FFFFFF80 FFFFFF84 20 FFFFFF84
   30 14 03 2A FFFFFF84 31 08 09 FFFFFF82 6A FFFFFF84 2F FFFFFF81 FFFFFF80 FFFFFFC0 00
   24 08 0B FFFFFF82 62 FFFFFF83 7A FFFFFF84 FFFFFF80 FFFFFF80 FFFFFF84 20 FFFFFF82 63 08 0B
   FFFFFF82 65 FFFFFF83 7A FFFFFF84 FFFFFF80 FFFFFF80 FFFFFF84 20 FFFFFF81 75 08 0B FFFFFF82 67 FFFFFF83
   7A FFFFFF84 FFFFFF80 FFFFFF80 FFFFFF84 20 FFFFFF84 35 14 03 24 FFFFFF84 36 08 0A FFFFFF82
   6A FFFFFF84 34 FFFFFF81 FFFFFF80 FFFFFFC0 00 FFFFFF81 76 08 0B FFFFFF82 6C FFFFFF83 7A FFFFFF84
   FFFFFF80 FFFFFF80 FFFFFF84 20 FFFFFF84 38 14 04 FFFFFF82 5E FFFFFF84 39 08 0A FFFFFF82 6A
   FFFFFF84 37 FFFFFF81 FFFFFF80 FFFFFFC0 00 FFFFFF81 76 08 0B FFFFFF82 70 FFFFFF83 7A FFFFFF84 FFFFFF80
   FFFFFF80 FFFFFF84 20 FFFFFF84 3B 14 03 2A FFFFFF84 3C 08 09 FFFFFF82 6A FFFFFF84 3A
   FFFFFF81 FFFFFF80 FFFFFFC0 00 24 28 04 FFFFFF83 7A FFFFFF81 7A 07 09 FFFFFF84 3F 00
   FFFFFF81 FFFFFF80 FFFFFF88 02 FFFFFF84 40 01 09 42 6C 61 63 6B 54 72 65
   65 10 03 36 FFFFFF84 41 06 0A FFFFFF83 7B 00 FFFFFF84 FFFFFF81 FFFFFF80 FFFFFF88 02
   FFFFFF84 42 13 04 FFFFFF84 41 0B 13 08 07 18 FFFFFF84 41 FFFFFF84 00 FFFFFF84
   44 14 02 FFFFFF84 40 08 0A FFFFFF83 61 FFFFFF84 41 FFFFFF81 FFFFFF80 FFFFFF84 40 FFFFFF84
   46 15 04 FFFFFF84 47 FFFFFF84 4A 14 0A FFFFFF84 48 FFFFFF84 4B FFFFFF84 4C FFFFFF84
   4D FFFFFF84 4F 10 05 36 FFFFFF83 7A FFFFFF84 49 10 03 1D FFFFFF84 4A 04
   09 40 FFFFFF84 45 FFFFFF84 FFFFFF80 FFFFFF80 FFFFFFC2 00 20 08 07 FFFFFF81 31 FFFFFF84 45
   FFFFFFC0 00 1C 08 08 FFFFFF81 34 FFFFFF84 45 FFFFFFC0 00 FFFFFF84 49 08 08 FFFFFF81
   37 FFFFFF84 45 FFFFFFC0 00 FFFFFF84 4E 10 04 36 37 FFFFFF84 49 08 08 FFFFFF81
   3A FFFFFF84 45 FFFFFFC0 00 FFFFFF84 4E 08 0A FFFFFF83 6D FFFFFF84 41 FFFFFF81 FFFFFF80 FFFFFF84
   40 FFFFFF84 51 15 04 FFFFFF84 52 FFFFFF84 56 14 04 FFFFFF84 53 FFFFFF84 58 10
   05 14 FFFFFF81 6B FFFFFF84 54 10 0A 14 FFFFFF83 72 1C FFFFFF84 55 FFFFFF84 57
   FFFFFF84 57 10 03 1D FFFFFF84 56 04 09 40 FFFFFF84 50 FFFFFF84 FFFFFF80 FFFFFF80 FFFFFFC2
   00 20 10 04 36 37 FFFFFF84 55 08 08 FFFFFF83 78 FFFFFF84 50 FFFFFFC0 00
   FFFFFF84 59 10 05 36 FFFFFF83 7A FFFFFF84 55 28 05 00 FFFFFF84 5B FFFFFF84 5E
   10 03 14 FFFFFF84 5C 09 03 FFFFFF84 5D 06 02 10 53 65 72 69
   61 6C 56 65 72 73 69 6F 6E 55 49 44 1E 08 78 FFFFFF9F
   FFFFFFC8 34 FFFFFFEA 73 19 79 28 03 00 FFFFFF81 7A 
  InnerClass: 
   public abstract Tree=class scala/collection/immutable/RedBlack$Tree of class scala/collection/immutable/RedBlack
   public RedTree=class scala/collection/immutable/RedBlack$RedTree of class scala/collection/immutable/RedBlack
   public abstract NonEmpty=class scala/collection/immutable/RedBlack$NonEmpty of class scala/collection/immutable/RedBlack
   public BlackTree=class scala/collection/immutable/RedBlack$BlackTree of class scala/collection/immutable/RedBlack
  minor version: 0
  major version: 49
  Constant pool:
Asciz	SourceFile;
Asciz	RedBlack.scala;
Asciz	<clinit>;
Asciz	()V;
Asciz	Code;
Asciz	serialVersionUID;
Asciz	J;
long	8691885935445612921l;
Asciz	scala/collection/immutable/RedBlack;
class	scala/collection/immutable/RedBlack
NameAndType	serialVersionUID:J
Field	scala/collection/immutable/RedBlack.serialVersionUID:J
Asciz	RedTree$module;
Asciz	Lscala/collection/immutable/RedBlack$RedTree$;;
Asciz	BlackTree$module;
Asciz	Lscala/collection/immutable/RedBlack$BlackTree$;;
Asciz	Empty$module;
Asciz	Lscala/collection/immutable/RedBlack$Empty$;;
Asciz	isSmaller;
Asciz	(Ljava/lang/Object;Ljava/lang/Object;)Z;
Asciz	(TA;TA;)Z;
Asciz	Signature;
Asciz	scala$collection$immutable$RedBlack$$blacken;
Asciz	(Lscala/collection/immutable/RedBlack$Tree;)Lscala/collection/immutable/RedBlack$Tree;;
Asciz	LineNumberTable;
Asciz	scala/collection/immutable/RedBlack$RedTree;
class	scala/collection/immutable/RedBlack$RedTree
Asciz	scala/collection/immutable/RedBlack$BlackTree;
class	scala/collection/immutable/RedBlack$BlackTree
Asciz	key;
Asciz	()Ljava/lang/Object;;
NameAndType	key:()Ljava/lang/Object;
Method	scala/collection/immutable/RedBlack$RedTree.key:()Ljava/lang/Object;
Asciz	value;
NameAndType	value:()Ljava/lang/Object;
Method	scala/collection/immutable/RedBlack$RedTree.value:()Ljava/lang/Object;
Asciz	left;
Asciz	()Lscala/collection/immutable/RedBlack$Tree;;
NameAndType	left:()Lscala/collection/immutable/RedBlack$Tree;
Method	scala/collection/immutable/RedBlack$RedTree.left:()Lscala/collection/immutable/RedBlack$Tree;
Asciz	right;
NameAndType	right:()Lscala/collection/immutable/RedBlack$Tree;
Method	scala/collection/immutable/RedBlack$RedTree.right:()Lscala/collection/immutable/RedBlack$Tree;
Asciz	<init>;
Asciz	(Lscala/collection/immutable/RedBlack;Ljava/lang/Object;Ljava/lang/Object;Lscala/collection/immutable/RedBlack$Tree;Lscala/collection/immutable/RedBlack$Tree;)V;
NameAndType	"<init>":(Lscala/collection/immutable/RedBlack;Ljava/lang/Object;Ljava/lang/Object;Lscala/collection/immutable/RedBlack$Tree;Lscala/collection/immutable/RedBlack$Tree;)V
Method	scala/collection/immutable/RedBlack$BlackTree."<init>":(Lscala/collection/immutable/RedBlack;Ljava/lang/Object;Ljava/lang/Object;Lscala/collection/immutable/RedBlack$Tree;Lscala/collection/immutable/RedBlack$Tree;)V
Asciz	this;
Asciz	Lscala/collection/immutable/RedBlack;;
Asciz	t;
Asciz	Lscala/collection/immutable/RedBlack$Tree;;
Asciz	temp1;
Asciz	temp2;
Asciz	Lscala/collection/immutable/RedBlack$RedTree;;
Asciz	LocalVariableTable;
Asciz	scala$collection$immutable$RedBlack$$mkTree;
Asciz	(ZLjava/lang/Object;Ljava/lang/Object;Lscala/collection/immutable/RedBlack$Tree;Lscala/collection/immutable/RedBlack$Tree;)Lscala/collection/immutable/RedBlack$NonEmpty;;
Method	scala/collection/immutable/RedBlack$RedTree."<init>":(Lscala/collection/immutable/RedBlack;Ljava/lang/Object;Ljava/lang/Object;Lscala/collection/immutable/RedBlack$Tree;Lscala/collection/immutable/RedBlack$Tree;)V
Asciz	isBlack;
Asciz	Z;
Asciz	k;
Asciz	Ljava/lang/Object;;
Asciz	v;
Asciz	l;
Asciz	r;
Asciz	Empty;
Asciz	()Lscala/collection/immutable/RedBlack$Empty$;;
NameAndType	Empty$module:Lscala/collection/immutable/RedBlack$Empty$;
Field	scala/collection/immutable/RedBlack.Empty$module:Lscala/collection/immutable/RedBlack$Empty$;
Asciz	scala/collection/immutable/RedBlack$Empty$;
class	scala/collection/immutable/RedBlack$Empty$
Asciz	(Lscala/collection/immutable/RedBlack;)V;
NameAndType	"<init>":(Lscala/collection/immutable/RedBlack;)V
Method	scala/collection/immutable/RedBlack$Empty$."<init>":(Lscala/collection/immutable/RedBlack;)V
Asciz	()Lscala/collection/immutable/RedBlack<TA;>.Empty;;
Asciz	BlackTree;
Asciz	()Lscala/collection/immutable/RedBlack$BlackTree$;;
NameAndType	BlackTree$module:Lscala/collection/immutable/RedBlack$BlackTree$;
Field	scala/collection/immutable/RedBlack.BlackTree$module:Lscala/collection/immutable/RedBlack$BlackTree$;
Asciz	scala/collection/immutable/RedBlack$BlackTree$;
class	scala/collection/immutable/RedBlack$BlackTree$
Method	scala/collection/immutable/RedBlack$BlackTree$."<init>":(Lscala/collection/immutable/RedBlack;)V
Asciz	RedTree;
Asciz	()Lscala/collection/immutable/RedBlack$RedTree$;;
NameAndType	RedTree$module:Lscala/collection/immutable/RedBlack$RedTree$;
Field	scala/collection/immutable/RedBlack.RedTree$module:Lscala/collection/immutable/RedBlack$RedTree$;
Asciz	scala/collection/immutable/RedBlack$RedTree$;
class	scala/collection/immutable/RedBlack$RedTree$
Method	scala/collection/immutable/RedBlack$RedTree$."<init>":(Lscala/collection/immutable/RedBlack;)V
Asciz	java/lang/Object;
class	java/lang/Object
NameAndType	"<init>":()V
Method	java/lang/Object."<init>":()V
Asciz	<A:Ljava/lang/Object;>Ljava/lang/Object;Lscala/ScalaObject;;
Asciz	ScalaSig;
Asciz	InnerClasses;
Asciz	scala/collection/immutable/RedBlack$Tree;
class	scala/collection/immutable/RedBlack$Tree
Asciz	Tree;
Asciz	scala/collection/immutable/RedBlack$NonEmpty;
class	scala/collection/immutable/RedBlack$NonEmpty
Asciz	NonEmpty;
Asciz	scala/ScalaObject;
class	scala/ScalaObject
Asciz	java/io/Serializable;
class	java/io/Serializable

{
public static final long serialVersionUID;
  Signature: J

private scala.collection.immutable.RedBlack$RedTree$ RedTree$module;
  Signature: Lscala/collection/immutable/RedBlack$RedTree$;

private scala.collection.immutable.RedBlack$BlackTree$ BlackTree$module;
  Signature: Lscala/collection/immutable/RedBlack$BlackTree$;

private scala.collection.immutable.RedBlack$Empty$ Empty$module;
  Signature: Lscala/collection/immutable/RedBlack$Empty$;

public static {};
  Signature: ()V
  Code:
   Stack=2, Locals=0, Args_size=0
	ldc2_w	long 8691885935445612921l
	putstatic	Field serialVersionUID:J
	return
  Labels:

public abstract boolean isSmaller(java.lang.Object, java.lang.Object);
  Signature: (Ljava/lang/Object;Ljava/lang/Object;)Z
  Signature: length = 0x2
   00 16 

public final scala.collection.immutable.RedBlack$Tree scala$collection$immutable$RedBlack$$blacken(scala.collection.immutable.RedBlack$Tree);
  Signature: (Lscala/collection/immutable/RedBlack$Tree;)Lscala/collection/immutable/RedBlack$Tree;
  Code:
   Stack=7, Locals=4, Args_size=2
	aload_1
	astore_2
	aload_2
	instanceof	class scala/collection/immutable/RedBlack$RedTree
	ifeq	l1 // aload_2
	aload_2
	checkcast	class scala/collection/immutable/RedBlack$RedTree
	astore_3
	new	class scala/collection/immutable/RedBlack$BlackTree
	dup
	aload_0
	aload_3
	invokevirtual	Method scala/collection/immutable/RedBlack$RedTree.key:()Ljava/lang/Object;
	aload_3
	invokevirtual	Method scala/collection/immutable/RedBlack$RedTree.value:()Ljava/lang/Object;
	aload_3
	invokevirtual	Method scala/collection/immutable/RedBlack$RedTree.left:()Lscala/collection/immutable/RedBlack$Tree;
	aload_3
	invokevirtual	Method scala/collection/immutable/RedBlack$RedTree.right:()Lscala/collection/immutable/RedBlack$Tree;
	invokespecial	Method scala/collection/immutable/RedBlack$BlackTree."<init>":(Lscala/collection/immutable/RedBlack;Ljava/lang/Object;Ljava/lang/Object;Lscala/collection/immutable/RedBlack$Tree;Lscala/collection/immutable/RedBlack$Tree;)V
	goto	l2 // areturn
l1	aload_2
l2	areturn
  Labels:
   	l1 = 41 // aload_2
   	l2 = 42 // areturn
  LocalVariableTable: 
   Start  Length  Slot  Name   Signature
   0      43      0    this       Lscala/collection/immutable/RedBlack;
   0      43      1    t       Lscala/collection/immutable/RedBlack$Tree;
   2      41      2    temp1       Lscala/collection/immutable/RedBlack$Tree;
   14      24      3    temp2       Lscala/collection/immutable/RedBlack$RedTree;


public final scala.collection.immutable.RedBlack$NonEmpty scala$collection$immutable$RedBlack$$mkTree(boolean, java.lang.Object, java.lang.Object, scala.collection.immutable.RedBlack$Tree, scala.collection.immutable.RedBlack$Tree);
  Signature: (ZLjava/lang/Object;Ljava/lang/Object;Lscala/collection/immutable/RedBlack$Tree;Lscala/collection/immutable/RedBlack$Tree;)Lscala/collection/immutable/RedBlack$NonEmpty;
  Code:
   Stack=7, Locals=6, Args_size=6
	iload_1
	ifeq	l1 // new
	new	class scala/collection/immutable/RedBlack$BlackTree
	dup
	aload_0
	aload_2
	aload_3
	aload	4
	aload	5
	invokespecial	Method scala/collection/immutable/RedBlack$BlackTree."<init>":(Lscala/collection/immutable/RedBlack;Ljava/lang/Object;Ljava/lang/Object;Lscala/collection/immutable/RedBlack$Tree;Lscala/collection/immutable/RedBlack$Tree;)V
	goto	l2 // areturn
l1	new	class scala/collection/immutable/RedBlack$RedTree
	dup
	aload_0
	aload_2
	aload_3
	aload	4
	aload	5
	invokespecial	Method scala/collection/immutable/RedBlack$RedTree."<init>":(Lscala/collection/immutable/RedBlack;Ljava/lang/Object;Ljava/lang/Object;Lscala/collection/immutable/RedBlack$Tree;Lscala/collection/immutable/RedBlack$Tree;)V
l2	areturn
  Labels:
   	l1 = 21 // new
   	l2 = 35 // areturn
  LocalVariableTable: 
   Start  Length  Slot  Name   Signature
   0      36      0    this       Lscala/collection/immutable/RedBlack;
   0      36      1    isBlack       Z
   0      36      2    k       Ljava/lang/Object;
   0      36      3    v       Ljava/lang/Object;
   0      36      4    l       Lscala/collection/immutable/RedBlack$Tree;
   0      36      5    r       Lscala/collection/immutable/RedBlack$Tree;


public final scala.collection.immutable.RedBlack$Empty$ Empty();
  Signature: ()Lscala/collection/immutable/RedBlack$Empty$;
  Code:
   Stack=4, Locals=1, Args_size=1
	aload_0
	getfield	Field Empty$module:Lscala/collection/immutable/RedBlack$Empty$;
	ifnonnull	l1 // aload_0
	aload_0
	new	class scala/collection/immutable/RedBlack$Empty$
	dup
	aload_0
	invokespecial	Method scala/collection/immutable/RedBlack$Empty$."<init>":(Lscala/collection/immutable/RedBlack;)V
	putfield	Field Empty$module:Lscala/collection/immutable/RedBlack$Empty$;
l1	aload_0
	getfield	Field Empty$module:Lscala/collection/immutable/RedBlack$Empty$;
	areturn
  Labels:
   	l1 = 19 // aload_0
  Signature: length = 0x2
   00 4C 

public final scala.collection.immutable.RedBlack$BlackTree$ BlackTree();
  Signature: ()Lscala/collection/immutable/RedBlack$BlackTree$;
  Code:
   Stack=4, Locals=1, Args_size=1
	aload_0
	getfield	Field BlackTree$module:Lscala/collection/immutable/RedBlack$BlackTree$;
	ifnonnull	l1 // aload_0
	aload_0
	new	class scala/collection/immutable/RedBlack$BlackTree$
	dup
	aload_0
	invokespecial	Method scala/collection/immutable/RedBlack$BlackTree$."<init>":(Lscala/collection/immutable/RedBlack;)V
	putfield	Field BlackTree$module:Lscala/collection/immutable/RedBlack$BlackTree$;
l1	aload_0
	getfield	Field BlackTree$module:Lscala/collection/immutable/RedBlack$BlackTree$;
	areturn
  Labels:
   	l1 = 19 // aload_0

public final scala.collection.immutable.RedBlack$RedTree$ RedTree();
  Signature: ()Lscala/collection/immutable/RedBlack$RedTree$;
  Code:
   Stack=4, Locals=1, Args_size=1
	aload_0
	getfield	Field RedTree$module:Lscala/collection/immutable/RedBlack$RedTree$;
	ifnonnull	l1 // aload_0
	aload_0
	new	class scala/collection/immutable/RedBlack$RedTree$
	dup
	aload_0
	invokespecial	Method scala/collection/immutable/RedBlack$RedTree$."<init>":(Lscala/collection/immutable/RedBlack;)V
	putfield	Field RedTree$module:Lscala/collection/immutable/RedBlack$RedTree$;
l1	aload_0
	getfield	Field RedTree$module:Lscala/collection/immutable/RedBlack$RedTree$;
	areturn
  Labels:
   	l1 = 19 // aload_0

public scala.collection.immutable.RedBlack();
  Signature: ()V
  Code:
   Stack=1, Locals=1, Args_size=1
	aload_0
	invokespecial	Method java/lang/Object."<init>":()V
	return
  Labels:
  Signature: length = 0x2
   00 04 

}

