Compiled from "RedBlack.scala"
public abstract class scala.collection.immutable.RedBlack$NonEmpty extends scala.collection.immutable.RedBlack$Tree implements scala.ScalaObject,java.io.Serializable
  SourceFile: "RedBlack.scala"
  Signature: length = 0x2
   01 FFFFFFD1 
  Scala: length = 0x
   
  InnerClass: 
   public abstract Tree=class scala/collection/immutable/RedBlack$Tree of class scala/collection/immutable/RedBlack
   public RedTree=class scala/collection/immutable/RedBlack$RedTree of class scala/collection/immutable/RedBlack
   public abstract NonEmpty=class scala/collection/immutable/RedBlack$NonEmpty of class scala/collection/immutable/RedBlack
   public BlackTree=class scala/collection/immutable/RedBlack$BlackTree of class scala/collection/immutable/RedBlack
   public final $anonfun$iterator$2=class scala/collection/immutable/RedBlack$NonEmpty$$anonfun$iterator$2 of class scala/collection/immutable/RedBlack$NonEmpty
   public final $anonfun$iterator$1=class scala/collection/immutable/RedBlack$NonEmpty$$anonfun$iterator$1 of class scala/collection/immutable/RedBlack$NonEmpty
  minor version: 0
  major version: 49
  Constant pool:
Asciz	SourceFile;
Asciz	RedBlack.scala;
Asciz	isEmpty;
Asciz	()Z;
Asciz	Code;
Asciz	LineNumberTable;
Asciz	key;
Asciz	()Ljava/lang/Object;;
Asciz	()TA;;
Asciz	Signature;
Asciz	value;
Asciz	()TB;;
Asciz	left;
Asciz	()Lscala/collection/immutable/RedBlack$Tree;;
Asciz	()Lscala/collection/immutable/RedBlack<TA;>.Tree<TB;>;;
Asciz	right;
Asciz	lookup;
Asciz	(Ljava/lang/Object;)Lscala/collection/immutable/RedBlack$Tree;;
Asciz	scala/collection/immutable/RedBlack$NonEmpty;
class	scala/collection/immutable/RedBlack$NonEmpty
Asciz	scala$collection$immutable$RedBlack$NonEmpty$$$outer;
Asciz	()Lscala/collection/immutable/RedBlack;;
NameAndType	scala$collection$immutable$RedBlack$NonEmpty$$$outer:()Lscala/collection/immutable/RedBlack;
Method	scala/collection/immutable/RedBlack$NonEmpty.scala$collection$immutable$RedBlack$NonEmpty$$$outer:()Lscala/collection/immutable/RedBlack;
NameAndType	key:()Ljava/lang/Object;
Method	scala/collection/immutable/RedBlack$NonEmpty.key:()Ljava/lang/Object;
Asciz	scala/collection/immutable/RedBlack;
class	scala/collection/immutable/RedBlack
Asciz	isSmaller;
Asciz	(Ljava/lang/Object;Ljava/lang/Object;)Z;
NameAndType	isSmaller:(Ljava/lang/Object;Ljava/lang/Object;)Z
Method	scala/collection/immutable/RedBlack.isSmaller:(Ljava/lang/Object;Ljava/lang/Object;)Z
NameAndType	left:()Lscala/collection/immutable/RedBlack$Tree;
Method	scala/collection/immutable/RedBlack$NonEmpty.left:()Lscala/collection/immutable/RedBlack$Tree;
Asciz	scala/collection/immutable/RedBlack$Tree;
class	scala/collection/immutable/RedBlack$Tree
NameAndType	lookup:(Ljava/lang/Object;)Lscala/collection/immutable/RedBlack$Tree;
Method	scala/collection/immutable/RedBlack$Tree.lookup:(Ljava/lang/Object;)Lscala/collection/immutable/RedBlack$Tree;
NameAndType	right:()Lscala/collection/immutable/RedBlack$Tree;
Method	scala/collection/immutable/RedBlack$NonEmpty.right:()Lscala/collection/immutable/RedBlack$Tree;
Asciz	this;
Asciz	Lscala/collection/immutable/RedBlack$NonEmpty;;
Asciz	k;
Asciz	Ljava/lang/Object;;
Asciz	LocalVariableTable;
Asciz	(TA;)Lscala/collection/immutable/RedBlack<TA;>.Tree<TB;>;;
Asciz	upd;
Asciz	(Ljava/lang/Object;Ljava/lang/Object;)Lscala/collection/immutable/RedBlack$Tree;;
Asciz	isBlack;
NameAndType	isBlack:()Z
Method	scala/collection/immutable/RedBlack$NonEmpty.isBlack:()Z
NameAndType	value:()Ljava/lang/Object;
Method	scala/collection/immutable/RedBlack$NonEmpty.value:()Ljava/lang/Object;
NameAndType	upd:(Ljava/lang/Object;Ljava/lang/Object;)Lscala/collection/immutable/RedBlack$Tree;
Method	scala/collection/immutable/RedBlack$Tree.upd:(Ljava/lang/Object;Ljava/lang/Object;)Lscala/collection/immutable/RedBlack$Tree;
Asciz	balanceLeft$1;
Asciz	(ZLjava/lang/Object;Ljava/lang/Object;Lscala/collection/immutable/RedBlack$Tree;Lscala/collection/immutable/RedBlack$Tree;)Lscala/collection/immutable/RedBlack$NonEmpty;;
NameAndType	balanceLeft$1:(ZLjava/lang/Object;Ljava/lang/Object;Lscala/collection/immutable/RedBlack$Tree;Lscala/collection/immutable/RedBlack$Tree;)Lscala/collection/immutable/RedBlack$NonEmpty;
Method	scala/collection/immutable/RedBlack$NonEmpty.balanceLeft$1:(ZLjava/lang/Object;Ljava/lang/Object;Lscala/collection/immutable/RedBlack$Tree;Lscala/collection/immutable/RedBlack$Tree;)Lscala/collection/immutable/RedBlack$NonEmpty;
Asciz	balanceRight$1;
NameAndType	balanceRight$1:(ZLjava/lang/Object;Ljava/lang/Object;Lscala/collection/immutable/RedBlack$Tree;Lscala/collection/immutable/RedBlack$Tree;)Lscala/collection/immutable/RedBlack$NonEmpty;
Method	scala/collection/immutable/RedBlack$NonEmpty.balanceRight$1:(ZLjava/lang/Object;Ljava/lang/Object;Lscala/collection/immutable/RedBlack$Tree;Lscala/collection/immutable/RedBlack$Tree;)Lscala/collection/immutable/RedBlack$NonEmpty;
Asciz	scala$collection$immutable$RedBlack$$mkTree;
NameAndType	scala$collection$immutable$RedBlack$$mkTree:(ZLjava/lang/Object;Ljava/lang/Object;Lscala/collection/immutable/RedBlack$Tree;Lscala/collection/immutable/RedBlack$Tree;)Lscala/collection/immutable/RedBlack$NonEmpty;
Method	scala/collection/immutable/RedBlack.scala$collection$immutable$RedBlack$$mkTree:(ZLjava/lang/Object;Ljava/lang/Object;Lscala/collection/immutable/RedBlack$Tree;Lscala/collection/immutable/RedBlack$Tree;)Lscala/collection/immutable/RedBlack$NonEmpty;
Asciz	v;
Asciz	<B1:Ljava/lang/Object;>(TA;TB1;)Lscala/collection/immutable/RedBlack<TA;>.Tree<TB1;>;;
Asciz	del;
Asciz	gd1$1;
Asciz	(Ljava/lang/Object;)Z;
NameAndType	gd1$1:(Ljava/lang/Object;)Z
Method	scala/collection/immutable/RedBlack$NonEmpty.gd1$1:(Ljava/lang/Object;)Z
Asciz	delLeft$1;
Asciz	(Ljava/lang/Object;)Lscala/collection/immutable/RedBlack$NonEmpty;;
NameAndType	delLeft$1:(Ljava/lang/Object;)Lscala/collection/immutable/RedBlack$NonEmpty;
Method	scala/collection/immutable/RedBlack$NonEmpty.delLeft$1:(Ljava/lang/Object;)Lscala/collection/immutable/RedBlack$NonEmpty;
Asciz	gd2$1;
NameAndType	gd2$1:(Ljava/lang/Object;)Z
Method	scala/collection/immutable/RedBlack$NonEmpty.gd2$1:(Ljava/lang/Object;)Z
Asciz	delRight$1;
NameAndType	delRight$1:(Ljava/lang/Object;)Lscala/collection/immutable/RedBlack$NonEmpty;
Method	scala/collection/immutable/RedBlack$NonEmpty.delRight$1:(Ljava/lang/Object;)Lscala/collection/immutable/RedBlack$NonEmpty;
Asciz	append$1;
Asciz	(Lscala/collection/immutable/RedBlack$Tree;Lscala/collection/immutable/RedBlack$Tree;)Lscala/collection/immutable/RedBlack$Tree;;
NameAndType	append$1:(Lscala/collection/immutable/RedBlack$Tree;Lscala/collection/immutable/RedBlack$Tree;)Lscala/collection/immutable/RedBlack$Tree;
Method	scala/collection/immutable/RedBlack$NonEmpty.append$1:(Lscala/collection/immutable/RedBlack$Tree;Lscala/collection/immutable/RedBlack$Tree;)Lscala/collection/immutable/RedBlack$Tree;
Asciz	k$1;
Asciz	smallest;
Asciz	()Lscala/collection/immutable/RedBlack$NonEmpty;;
NameAndType	isEmpty:()Z
Method	scala/collection/immutable/RedBlack$Tree.isEmpty:()Z
NameAndType	smallest:()Lscala/collection/immutable/RedBlack$NonEmpty;
Method	scala/collection/immutable/RedBlack$Tree.smallest:()Lscala/collection/immutable/RedBlack$NonEmpty;
Asciz	()Lscala/collection/immutable/RedBlack<TA;>.NonEmpty<TB;>;;
Asciz	toStream;
Asciz	()Lscala/collection/immutable/Stream;;
NameAndType	toStream:()Lscala/collection/immutable/Stream;
Method	scala/collection/immutable/RedBlack$Tree.toStream:()Lscala/collection/immutable/Stream;
Asciz	scala/collection/immutable/Stream$;
class	scala/collection/immutable/Stream$
Asciz	MODULE$;
Asciz	Lscala/collection/immutable/Stream$;;
NameAndType	MODULE$:Lscala/collection/immutable/Stream$;
Field	scala/collection/immutable/Stream$.MODULE$:Lscala/collection/immutable/Stream$;
Asciz	scala/Predef$;
class	scala/Predef$
Asciz	Lscala/Predef$;;
NameAndType	MODULE$:Lscala/Predef$;
Field	scala/Predef$.MODULE$:Lscala/Predef$;
Asciz	scala/Tuple2;
class	scala/Tuple2
Asciz	<init>;
Asciz	(Ljava/lang/Object;Ljava/lang/Object;)V;
NameAndType	"<init>":(Ljava/lang/Object;Ljava/lang/Object;)V
Method	scala/Tuple2."<init>":(Ljava/lang/Object;Ljava/lang/Object;)V
Asciz	[Ljava/lang/Object;;
class	"[Ljava/lang/Object;"
Asciz	wrapRefArray;
Asciz	([Ljava/lang/Object;)Lscala/collection/mutable/WrappedArray;;
NameAndType	wrapRefArray:([Ljava/lang/Object;)Lscala/collection/mutable/WrappedArray;
Method	scala/Predef$.wrapRefArray:([Ljava/lang/Object;)Lscala/collection/mutable/WrappedArray;
Asciz	apply;
Asciz	(Lscala/collection/Seq;)Lscala/collection/immutable/Stream;;
NameAndType	apply:(Lscala/collection/Seq;)Lscala/collection/immutable/Stream;
Method	scala/collection/immutable/Stream$.apply:(Lscala/collection/Seq;)Lscala/collection/immutable/Stream;
Asciz	canBuildFrom;
Asciz	()Lscala/collection/generic/CanBuildFrom;;
NameAndType	canBuildFrom:()Lscala/collection/generic/CanBuildFrom;
Method	scala/collection/immutable/Stream$.canBuildFrom:()Lscala/collection/generic/CanBuildFrom;
Asciz	scala/collection/immutable/Stream;
class	scala/collection/immutable/Stream
Asciz	$plus$plus;
Asciz	(Lscala/collection/Traversable;Lscala/collection/generic/CanBuildFrom;)Ljava/lang/Object;;
NameAndType	$plus$plus:(Lscala/collection/Traversable;Lscala/collection/generic/CanBuildFrom;)Ljava/lang/Object;
Method	scala/collection/immutable/Stream.$plus$plus:(Lscala/collection/Traversable;Lscala/collection/generic/CanBuildFrom;)Ljava/lang/Object;
Asciz	()Lscala/collection/immutable/Stream<Lscala/Tuple2<TA;TB;>;>;;
Asciz	iterator;
Asciz	()Lscala/collection/Iterator;;
NameAndType	iterator:()Lscala/collection/Iterator;
Method	scala/collection/immutable/RedBlack$Tree.iterator:()Lscala/collection/Iterator;
Asciz	scala/collection/immutable/RedBlack$NonEmpty$$anonfun$iterator$1;
class	scala/collection/immutable/RedBlack$NonEmpty$$anonfun$iterator$1
Asciz	(Lscala/collection/immutable/RedBlack$NonEmpty;)V;
NameAndType	"<init>":(Lscala/collection/immutable/RedBlack$NonEmpty;)V
Method	scala/collection/immutable/RedBlack$NonEmpty$$anonfun$iterator$1."<init>":(Lscala/collection/immutable/RedBlack$NonEmpty;)V
Asciz	scala/collection/Iterator;
class	scala/collection/Iterator
Asciz	(Lscala/Function0;)Lscala/collection/Iterator;;
NameAndType	$plus$plus:(Lscala/Function0;)Lscala/collection/Iterator;
InterfaceMethod	scala/collection/Iterator.$plus$plus:(Lscala/Function0;)Lscala/collection/Iterator;
Asciz	scala/collection/immutable/RedBlack$NonEmpty$$anonfun$iterator$2;
class	scala/collection/immutable/RedBlack$NonEmpty$$anonfun$iterator$2
Method	scala/collection/immutable/RedBlack$NonEmpty$$anonfun$iterator$2."<init>":(Lscala/collection/immutable/RedBlack$NonEmpty;)V
Asciz	()Lscala/collection/Iterator<Lscala/Tuple2<TA;TB;>;>;;
Asciz	foreach;
Asciz	(Lscala/Function2;)V;
NameAndType	foreach:(Lscala/Function2;)V
Method	scala/collection/immutable/RedBlack$Tree.foreach:(Lscala/Function2;)V
Asciz	scala/Function2;
class	scala/Function2
Asciz	(Ljava/lang/Object;Ljava/lang/Object;)Ljava/lang/Object;;
NameAndType	apply:(Ljava/lang/Object;Ljava/lang/Object;)Ljava/lang/Object;
InterfaceMethod	scala/Function2.apply:(Ljava/lang/Object;Ljava/lang/Object;)Ljava/lang/Object;
Asciz	f;
Asciz	Lscala/Function2;;
Asciz	<U:Ljava/lang/Object;>(Lscala/Function2<TA;TB;TU;>;)V;
Asciz	visit;
Asciz	(Ljava/lang/Object;Lscala/Function3;)Lscala/Tuple2;;
NameAndType	visit:(Ljava/lang/Object;Lscala/Function3;)Lscala/Tuple2;
Method	scala/collection/immutable/RedBlack$Tree.visit:(Ljava/lang/Object;Lscala/Function3;)Lscala/Tuple2;
Asciz	_1;
NameAndType	_1:()Ljava/lang/Object;
Method	scala/Tuple2._1:()Ljava/lang/Object;
Asciz	scala/runtime/BoxesRunTime;
class	scala/runtime/BoxesRunTime
Asciz	unboxToBoolean;
NameAndType	unboxToBoolean:(Ljava/lang/Object;)Z
Method	scala/runtime/BoxesRunTime.unboxToBoolean:(Ljava/lang/Object;)Z
Asciz	_2;
NameAndType	_2:()Ljava/lang/Object;
Method	scala/Tuple2._2:()Ljava/lang/Object;
Asciz	scala/Function3;
class	scala/Function3
Asciz	(Ljava/lang/Object;Ljava/lang/Object;Ljava/lang/Object;)Ljava/lang/Object;;
NameAndType	apply:(Ljava/lang/Object;Ljava/lang/Object;Ljava/lang/Object;)Ljava/lang/Object;
InterfaceMethod	scala/Function3.apply:(Ljava/lang/Object;Ljava/lang/Object;Ljava/lang/Object;)Ljava/lang/Object;
Asciz	input;
Asciz	Lscala/Function3;;
Asciz	Lscala/Tuple2;;
Asciz	middle;
Asciz	<T:Ljava/lang/Object;>(TT;Lscala/Function3<TT;TA;TB;Lscala/Tuple2<Ljava/lang/Boolean;TT;>;>;)Lscala/Tuple2<Ljava/lang/Boolean;TT;>;;
Asciz	Deprecated;
Asciz	range;
Asciz	(Lscala/Option;Lscala/Option;)Lscala/collection/immutable/RedBlack$Tree;;
Asciz	scala/None$;
class	scala/None$
Asciz	Lscala/None$;;
NameAndType	MODULE$:Lscala/None$;
Field	scala/None$.MODULE$:Lscala/None$;
Asciz	java/lang/Object;
class	java/lang/Object
Asciz	equals;
NameAndType	equals:(Ljava/lang/Object;)Z
Method	java/lang/Object.equals:(Ljava/lang/Object;)Z
Asciz	scala/Option;
class	scala/Option
Asciz	get;
NameAndType	get:()Ljava/lang/Object;
Method	scala/Option.get:()Ljava/lang/Object;
NameAndType	range:(Lscala/Option;Lscala/Option;)Lscala/collection/immutable/RedBlack$Tree;
Method	scala/collection/immutable/RedBlack$Tree.range:(Lscala/Option;Lscala/Option;)Lscala/collection/immutable/RedBlack$Tree;
Asciz	Empty;
Asciz	()Lscala/collection/immutable/RedBlack$Empty$;;
NameAndType	Empty:()Lscala/collection/immutable/RedBlack$Empty$;
Method	scala/collection/immutable/RedBlack.Empty:()Lscala/collection/immutable/RedBlack$Empty$;
Asciz	from;
Asciz	Lscala/Option;;
Asciz	until;
Asciz	newLeft;
Asciz	Lscala/collection/immutable/RedBlack$Tree;;
Asciz	newRight;
Asciz	(Lscala/Option<TA;>;Lscala/Option<TA;>;)Lscala/collection/immutable/RedBlack<TA;>.Tree<TB;>;;
Asciz	first;
NameAndType	first:()Ljava/lang/Object;
Method	scala/collection/immutable/RedBlack$Tree.first:()Ljava/lang/Object;
Asciz	last;
NameAndType	last:()Ljava/lang/Object;
Method	scala/collection/immutable/RedBlack$Tree.last:()Ljava/lang/Object;
Asciz	count;
Asciz	()I;
NameAndType	count:()I
Method	scala/collection/immutable/RedBlack$Tree.count:()I
Asciz	$outer;
Asciz	Lscala/collection/immutable/RedBlack;;
NameAndType	$outer:Lscala/collection/immutable/RedBlack;
Field	scala/collection/immutable/RedBlack$Tree.$outer:Lscala/collection/immutable/RedBlack;
Asciz	scala/collection/immutable/RedBlack$RedTree;
class	scala/collection/immutable/RedBlack$RedTree
Method	scala/collection/immutable/RedBlack$RedTree.key:()Ljava/lang/Object;
Method	scala/collection/immutable/RedBlack$RedTree.value:()Ljava/lang/Object;
Method	scala/collection/immutable/RedBlack$RedTree.left:()Lscala/collection/immutable/RedBlack$Tree;
Method	scala/collection/immutable/RedBlack$RedTree.right:()Lscala/collection/immutable/RedBlack$Tree;
Asciz	scala/collection/immutable/RedBlack$BlackTree;
class	scala/collection/immutable/RedBlack$BlackTree
Asciz	(Lscala/collection/immutable/RedBlack;Ljava/lang/Object;Ljava/lang/Object;Lscala/collection/immutable/RedBlack$Tree;Lscala/collection/immutable/RedBlack$Tree;)V;
NameAndType	"<init>":(Lscala/collection/immutable/RedBlack;Ljava/lang/Object;Ljava/lang/Object;Lscala/collection/immutable/RedBlack$Tree;Lscala/collection/immutable/RedBlack$Tree;)V
Method	scala/collection/immutable/RedBlack$BlackTree."<init>":(Lscala/collection/immutable/RedBlack;Ljava/lang/Object;Ljava/lang/Object;Lscala/collection/immutable/RedBlack$Tree;Lscala/collection/immutable/RedBlack$Tree;)V
Method	scala/collection/immutable/RedBlack$RedTree."<init>":(Lscala/collection/immutable/RedBlack;Ljava/lang/Object;Ljava/lang/Object;Lscala/collection/immutable/RedBlack$Tree;Lscala/collection/immutable/RedBlack$Tree;)V
Asciz	Z;
Asciz	z;
Asciz	zv;
Asciz	l;
Asciz	d;
Asciz	temp8;
Asciz	Lscala/collection/immutable/RedBlack$RedTree;;
Asciz	temp13;
Asciz	temp14;
Asciz	temp15;
Asciz	temp16;
Asciz	temp17;
Asciz	temp12;
Asciz	temp18;
Asciz	temp19;
Asciz	temp20;
Asciz	temp9;
Asciz	temp10;
Asciz	temp11;
Asciz	temp21;
Asciz	temp22;
Asciz	x;
Asciz	xv;
Asciz	a;
Asciz	r;
Asciz	temp24;
Asciz	temp29;
Asciz	temp30;
Asciz	temp31;
Asciz	temp32;
Asciz	temp33;
Asciz	temp28;
Asciz	temp34;
Asciz	temp25;
Asciz	temp26;
Asciz	temp27;
Asciz	temp35;
Asciz	temp36;
Asciz	temp37;
Asciz	temp38;
Asciz	balance$1;
Asciz	(Ljava/lang/Object;Ljava/lang/Object;Lscala/collection/immutable/RedBlack$Tree;Lscala/collection/immutable/RedBlack$Tree;)Lscala/collection/immutable/RedBlack$NonEmpty;;
Asciz	tl;
Asciz	tr;
Asciz	temp44;
Asciz	temp45;
Asciz	temp46;
Asciz	temp47;
Asciz	temp48;
Asciz	temp49;
Asciz	temp50;
Asciz	temp51;
Asciz	temp52;
Asciz	temp53;
Asciz	temp43;
Asciz	temp54;
Asciz	temp55;
Asciz	temp56;
Asciz	temp40;
Asciz	temp41;
Asciz	temp42;
Asciz	temp57;
Asciz	temp58;
Asciz	temp39;
Asciz	temp64;
Asciz	temp65;
Asciz	temp66;
Asciz	temp67;
Asciz	temp68;
Asciz	temp62;
Asciz	temp69;
Asciz	temp70;
Asciz	temp71;
Asciz	temp72;
Asciz	temp60;
Asciz	temp61;
Asciz	temp73;
Asciz	temp63;
Asciz	temp59;
Asciz	b;
Asciz	subl$1;
Asciz	(Lscala/collection/immutable/RedBlack$Tree;)Lscala/collection/immutable/RedBlack$RedTree;;
Method	scala/collection/immutable/RedBlack$BlackTree.key:()Ljava/lang/Object;
Method	scala/collection/immutable/RedBlack$BlackTree.value:()Ljava/lang/Object;
Method	scala/collection/immutable/RedBlack$BlackTree.left:()Lscala/collection/immutable/RedBlack$Tree;
Method	scala/collection/immutable/RedBlack$BlackTree.right:()Lscala/collection/immutable/RedBlack$Tree;
Asciz	scala/collection/mutable/StringBuilder;
class	scala/collection/mutable/StringBuilder
Asciz	()V;
NameAndType	"<init>":()V
Method	scala/collection/mutable/StringBuilder."<init>":()V
Asciz	Defect: invariance violation; expected black, got ;
String	Defect: invariance violation; expected black, got 
Asciz	append;
Asciz	(Ljava/lang/Object;)Lscala/collection/mutable/StringBuilder;;
NameAndType	append:(Ljava/lang/Object;)Lscala/collection/mutable/StringBuilder;
Method	scala/collection/mutable/StringBuilder.append:(Ljava/lang/Object;)Lscala/collection/mutable/StringBuilder;
Asciz	toString;
Asciz	()Ljava/lang/String;;
NameAndType	toString:()Ljava/lang/String;
Method	scala/collection/mutable/StringBuilder.toString:()Ljava/lang/String;
Asciz	java/lang/RuntimeException;
class	java/lang/RuntimeException
Asciz	(Ljava/lang/String;)V;
NameAndType	"<init>":(Ljava/lang/String;)V
Method	java/lang/RuntimeException."<init>":(Ljava/lang/String;)V
Asciz	t;
Asciz	temp75;
Asciz	Lscala/collection/immutable/RedBlack$BlackTree;;
Asciz	temp76;
Asciz	temp77;
Asciz	temp78;
Asciz	temp79;
Asciz	balLeft$1;
NameAndType	balance$1:(Ljava/lang/Object;Ljava/lang/Object;Lscala/collection/immutable/RedBlack$Tree;Lscala/collection/immutable/RedBlack$Tree;)Lscala/collection/immutable/RedBlack$NonEmpty;
Method	scala/collection/immutable/RedBlack$NonEmpty.balance$1:(Ljava/lang/Object;Ljava/lang/Object;Lscala/collection/immutable/RedBlack$Tree;Lscala/collection/immutable/RedBlack$Tree;)Lscala/collection/immutable/RedBlack$NonEmpty;
NameAndType	subl$1:(Lscala/collection/immutable/RedBlack$Tree;)Lscala/collection/immutable/RedBlack$RedTree;
Method	scala/collection/immutable/RedBlack$NonEmpty.subl$1:(Lscala/collection/immutable/RedBlack$Tree;)Lscala/collection/immutable/RedBlack$RedTree;
Asciz	Defect: invariance violation at ;
String	Defect: invariance violation at 
Asciz	temp80;
Asciz	temp81;
Asciz	temp82;
Asciz	temp83;
Asciz	temp84;
Asciz	temp85;
Asciz	temp86;
Asciz	temp87;
Asciz	temp88;
Asciz	temp89;
Asciz	temp90;
Asciz	temp93;
Asciz	temp95;
Asciz	temp96;
Asciz	temp97;
Asciz	temp98;
Asciz	temp91;
Asciz	temp92;
Asciz	temp99;
Asciz	temp94;
Asciz	balRight$1;
Asciz	temp100;
Asciz	temp101;
Asciz	temp102;
Asciz	temp103;
Asciz	temp104;
Asciz	temp105;
Asciz	temp106;
Asciz	temp107;
Asciz	temp108;
Asciz	temp109;
Asciz	temp110;
Asciz	temp114;
Asciz	temp115;
Asciz	temp116;
Asciz	temp117;
Asciz	temp111;
Asciz	temp112;
Asciz	temp113;
Asciz	temp118;
Asciz	temp119;
NameAndType	del:(Ljava/lang/Object;)Lscala/collection/immutable/RedBlack$Tree;
Method	scala/collection/immutable/RedBlack$Tree.del:(Ljava/lang/Object;)Lscala/collection/immutable/RedBlack$Tree;
NameAndType	balLeft$1:(Ljava/lang/Object;Ljava/lang/Object;Lscala/collection/immutable/RedBlack$Tree;Lscala/collection/immutable/RedBlack$Tree;)Lscala/collection/immutable/RedBlack$NonEmpty;
Method	scala/collection/immutable/RedBlack$NonEmpty.balLeft$1:(Ljava/lang/Object;Ljava/lang/Object;Lscala/collection/immutable/RedBlack$Tree;Lscala/collection/immutable/RedBlack$Tree;)Lscala/collection/immutable/RedBlack$NonEmpty;
Asciz	temp120;
NameAndType	balRight$1:(Ljava/lang/Object;Ljava/lang/Object;Lscala/collection/immutable/RedBlack$Tree;Lscala/collection/immutable/RedBlack$Tree;)Lscala/collection/immutable/RedBlack$NonEmpty;
Method	scala/collection/immutable/RedBlack$NonEmpty.balRight$1:(Ljava/lang/Object;Ljava/lang/Object;Lscala/collection/immutable/RedBlack$Tree;Lscala/collection/immutable/RedBlack$Tree;)Lscala/collection/immutable/RedBlack$NonEmpty;
Asciz	temp126;
Asciz	scala/MatchError;
class	scala/MatchError
Method	scala/Tuple2.toString:()Ljava/lang/String;
Method	scala/MatchError."<init>":(Ljava/lang/String;)V
Asciz	temp144;
Asciz	temp149;
Asciz	temp153;
Asciz	temp133;
Asciz	temp134;
Asciz	temp135;
Asciz	temp136;
Asciz	temp137;
Asciz	temp150;
Asciz	temp151;
Asciz	temp152;
Asciz	temp132;
Asciz	temp145;
Asciz	temp146;
Asciz	temp147;
Asciz	temp148;
Asciz	temp159;
Asciz	temp163;
Asciz	temp157;
Asciz	temp139;
Asciz	temp140;
Asciz	temp141;
Asciz	temp142;
Asciz	temp143;
Asciz	temp160;
Asciz	temp161;
Asciz	temp162;
Asciz	temp155;
Asciz	temp156;
Asciz	temp138;
Asciz	temp158;
Asciz	temp164;
Asciz	temp165;
Asciz	temp166;
Asciz	temp167;
Asciz	temp168;
Asciz	temp154;
Asciz	temp169;
Asciz	c;
Asciz	(Lscala/collection/immutable/RedBlack;)V;
NameAndType	"<init>":(Lscala/collection/immutable/RedBlack;)V
Method	scala/collection/immutable/RedBlack$Tree."<init>":(Lscala/collection/immutable/RedBlack;)V
Asciz	(Lscala/collection/immutable/RedBlack<TA;>;)V;
Asciz	<B:Ljava/lang/Object;>Lscala/collection/immutable/RedBlack<TA;>.Tree<TB;>;Lscala/ScalaObject;;
Asciz	Scala;
Asciz	InnerClasses;
Asciz	Tree;
Asciz	RedTree;
Asciz	NonEmpty;
Asciz	BlackTree;
Asciz	$anonfun$iterator$2;
Asciz	$anonfun$iterator$1;
Asciz	scala/ScalaObject;
class	scala/ScalaObject
Asciz	java/io/Serializable;
class	java/io/Serializable

{
public boolean isEmpty();
  Signature: ()Z
  Code:
   Stack=1, Locals=1, Args_size=1
	iconst_0
	ireturn
  Labels:

public abstract java.lang.Object key();
  Signature: ()Ljava/lang/Object;
  Signature: length = 0x2
   00 09 

public abstract java.lang.Object value();
  Signature: ()Ljava/lang/Object;
  Signature: length = 0x2
   00 0C 

public abstract scala.collection.immutable.RedBlack$Tree left();
  Signature: ()Lscala/collection/immutable/RedBlack$Tree;
  Signature: length = 0x2
   00 0F 

public abstract scala.collection.immutable.RedBlack$Tree right();
  Signature: ()Lscala/collection/immutable/RedBlack$Tree;
  Signature: length = 0x2
   00 0F 

public scala.collection.immutable.RedBlack$Tree lookup(java.lang.Object);
  Signature: (Ljava/lang/Object;)Lscala/collection/immutable/RedBlack$Tree;
  Code:
   Stack=3, Locals=2, Args_size=2
	aload_0
	invokevirtual	Method scala$collection$immutable$RedBlack$NonEmpty$$$outer:()Lscala/collection/immutable/RedBlack;
	aload_1
	aload_0
	invokevirtual	Method key:()Ljava/lang/Object;
	invokevirtual	Method scala/collection/immutable/RedBlack.isSmaller:(Ljava/lang/Object;Ljava/lang/Object;)Z
	ifeq	l1 // aload_0
	aload_0
	invokevirtual	Method left:()Lscala/collection/immutable/RedBlack$Tree;
	aload_1
	invokevirtual	Method scala/collection/immutable/RedBlack$Tree.lookup:(Ljava/lang/Object;)Lscala/collection/immutable/RedBlack$Tree;
	goto	l2 // areturn
l1	aload_0
	invokevirtual	Method scala$collection$immutable$RedBlack$NonEmpty$$$outer:()Lscala/collection/immutable/RedBlack;
	aload_0
	invokevirtual	Method key:()Ljava/lang/Object;
	aload_1
	invokevirtual	Method scala/collection/immutable/RedBlack.isSmaller:(Ljava/lang/Object;Ljava/lang/Object;)Z
	ifeq	l3 // aload_0
	aload_0
	invokevirtual	Method right:()Lscala/collection/immutable/RedBlack$Tree;
	aload_1
	invokevirtual	Method scala/collection/immutable/RedBlack$Tree.lookup:(Ljava/lang/Object;)Lscala/collection/immutable/RedBlack$Tree;
	goto	l2 // areturn
l3	aload_0
l2	areturn
  Labels:
   	l1 = 26 // aload_0
   	l3 = 52 // aload_0
   	l2 = 53 // areturn
  LocalVariableTable: 
   Start  Length  Slot  Name   Signature
   0      54      0    this       Lscala/collection/immutable/RedBlack$NonEmpty;
   0      54      1    k       Ljava/lang/Object;

  Signature: length = 0x2
   00 2E 

public scala.collection.immutable.RedBlack$Tree upd(java.lang.Object, java.lang.Object);
  Signature: (Ljava/lang/Object;Ljava/lang/Object;)Lscala/collection/immutable/RedBlack$Tree;
  Code:
   Stack=8, Locals=3, Args_size=3
	aload_0
	invokevirtual	Method scala$collection$immutable$RedBlack$NonEmpty$$$outer:()Lscala/collection/immutable/RedBlack;
	aload_1
	aload_0
	invokevirtual	Method key:()Ljava/lang/Object;
	invokevirtual	Method scala/collection/immutable/RedBlack.isSmaller:(Ljava/lang/Object;Ljava/lang/Object;)Z
	ifeq	l1 // aload_0
	aload_0
	aload_0
	invokevirtual	Method isBlack:()Z
	aload_0
	invokevirtual	Method key:()Ljava/lang/Object;
	aload_0
	invokevirtual	Method value:()Ljava/lang/Object;
	aload_0
	invokevirtual	Method left:()Lscala/collection/immutable/RedBlack$Tree;
	aload_1
	aload_2
	invokevirtual	Method scala/collection/immutable/RedBlack$Tree.upd:(Ljava/lang/Object;Ljava/lang/Object;)Lscala/collection/immutable/RedBlack$Tree;
	aload_0
	invokevirtual	Method right:()Lscala/collection/immutable/RedBlack$Tree;
	invokespecial	Method balanceLeft$1:(ZLjava/lang/Object;Ljava/lang/Object;Lscala/collection/immutable/RedBlack$Tree;Lscala/collection/immutable/RedBlack$Tree;)Lscala/collection/immutable/RedBlack$NonEmpty;
	goto	l2 // areturn
l1	aload_0
	invokevirtual	Method scala$collection$immutable$RedBlack$NonEmpty$$$outer:()Lscala/collection/immutable/RedBlack;
	aload_0
	invokevirtual	Method key:()Ljava/lang/Object;
	aload_1
	invokevirtual	Method scala/collection/immutable/RedBlack.isSmaller:(Ljava/lang/Object;Ljava/lang/Object;)Z
	ifeq	l3 // aload_0
	aload_0
	aload_0
	invokevirtual	Method isBlack:()Z
	aload_0
	invokevirtual	Method key:()Ljava/lang/Object;
	aload_0
	invokevirtual	Method value:()Ljava/lang/Object;
	aload_0
	invokevirtual	Method left:()Lscala/collection/immutable/RedBlack$Tree;
	aload_0
	invokevirtual	Method right:()Lscala/collection/immutable/RedBlack$Tree;
	aload_1
	aload_2
	invokevirtual	Method scala/collection/immutable/RedBlack$Tree.upd:(Ljava/lang/Object;Ljava/lang/Object;)Lscala/collection/immutable/RedBlack$Tree;
	invokespecial	Method balanceRight$1:(ZLjava/lang/Object;Ljava/lang/Object;Lscala/collection/immutable/RedBlack$Tree;Lscala/collection/immutable/RedBlack$Tree;)Lscala/collection/immutable/RedBlack$NonEmpty;
	goto	l2 // areturn
l3	aload_0
	invokevirtual	Method scala$collection$immutable$RedBlack$NonEmpty$$$outer:()Lscala/collection/immutable/RedBlack;
	aload_0
	invokevirtual	Method isBlack:()Z
	aload_1
	aload_2
	aload_0
	invokevirtual	Method left:()Lscala/collection/immutable/RedBlack$Tree;
	aload_0
	invokevirtual	Method right:()Lscala/collection/immutable/RedBlack$Tree;
	invokevirtual	Method scala/collection/immutable/RedBlack.scala$collection$immutable$RedBlack$$mkTree:(ZLjava/lang/Object;Ljava/lang/Object;Lscala/collection/immutable/RedBlack$Tree;Lscala/collection/immutable/RedBlack$Tree;)Lscala/collection/immutable/RedBlack$NonEmpty;
l2	areturn
  Labels:
   	l1 = 47 // aload_0
   	l3 = 94 // aload_0
   	l2 = 115 // areturn
  LocalVariableTable: 
   Start  Length  Slot  Name   Signature
   0      116      0    this       Lscala/collection/immutable/RedBlack$NonEmpty;
   0      116      1    k       Ljava/lang/Object;
   0      116      2    v       Ljava/lang/Object;

  Signature: length = 0x2
   00 43 

public scala.collection.immutable.RedBlack$Tree del(java.lang.Object);
  Signature: (Ljava/lang/Object;)Lscala/collection/immutable/RedBlack$Tree;
  Code:
   Stack=3, Locals=2, Args_size=2
	aload_0
	aload_1
	invokespecial	Method gd1$1:(Ljava/lang/Object;)Z
	ifeq	l1 // aload_0
	aload_0
	aload_1
	invokespecial	Method delLeft$1:(Ljava/lang/Object;)Lscala/collection/immutable/RedBlack$NonEmpty;
	goto	l2 // areturn
l1	aload_0
	aload_1
	invokespecial	Method gd2$1:(Ljava/lang/Object;)Z
	ifeq	l3 // aload_0
	aload_0
	aload_1
	invokespecial	Method delRight$1:(Ljava/lang/Object;)Lscala/collection/immutable/RedBlack$NonEmpty;
	goto	l2 // areturn
l3	aload_0
	aload_0
	invokevirtual	Method left:()Lscala/collection/immutable/RedBlack$Tree;
	aload_0
	invokevirtual	Method right:()Lscala/collection/immutable/RedBlack$Tree;
	invokespecial	Method append$1:(Lscala/collection/immutable/RedBlack$Tree;Lscala/collection/immutable/RedBlack$Tree;)Lscala/collection/immutable/RedBlack$Tree;
l2	areturn
  Labels:
   	l1 = 16 // aload_0
   	l3 = 32 // aload_0
   	l2 = 44 // areturn
  LocalVariableTable: 
   Start  Length  Slot  Name   Signature
   0      45      0    this       Lscala/collection/immutable/RedBlack$NonEmpty;
   0      45      1    k$1       Ljava/lang/Object;

  Signature: length = 0x2
   00 2E 

public scala.collection.immutable.RedBlack$NonEmpty smallest();
  Signature: ()Lscala/collection/immutable/RedBlack$NonEmpty;
  Code:
   Stack=1, Locals=1, Args_size=1
	aload_0
	invokevirtual	Method left:()Lscala/collection/immutable/RedBlack$Tree;
	invokevirtual	Method scala/collection/immutable/RedBlack$Tree.isEmpty:()Z
	ifeq	l1 // aload_0
	aload_0
	goto	l2 // areturn
l1	aload_0
	invokevirtual	Method left:()Lscala/collection/immutable/RedBlack$Tree;
	invokevirtual	Method scala/collection/immutable/RedBlack$Tree.smallest:()Lscala/collection/immutable/RedBlack$NonEmpty;
l2	areturn
  Labels:
   	l1 = 14 // aload_0
   	l2 = 21 // areturn
  Signature: length = 0x2
   00 5E 

public scala.collection.immutable.Stream toStream();
  Signature: ()Lscala/collection/immutable/Stream;
  Code:
   Stack=10, Locals=1, Args_size=1
	aload_0
	invokevirtual	Method left:()Lscala/collection/immutable/RedBlack$Tree;
	invokevirtual	Method scala/collection/immutable/RedBlack$Tree.toStream:()Lscala/collection/immutable/Stream;
	getstatic	Field scala/collection/immutable/Stream$.MODULE$:Lscala/collection/immutable/Stream$;
	getstatic	Field scala/Predef$.MODULE$:Lscala/Predef$;
	iconst_1
	anewarray	class scala/Tuple2
	dup
	iconst_0
	new	class scala/Tuple2
	dup
	aload_0
	invokevirtual	Method key:()Ljava/lang/Object;
	aload_0
	invokevirtual	Method value:()Ljava/lang/Object;
	invokespecial	Method scala/Tuple2."<init>":(Ljava/lang/Object;Ljava/lang/Object;)V
	aastore
	checkcast	class "[Ljava/lang/Object;"
	invokevirtual	Method scala/Predef$.wrapRefArray:([Ljava/lang/Object;)Lscala/collection/mutable/WrappedArray;
	invokevirtual	Method scala/collection/immutable/Stream$.apply:(Lscala/collection/Seq;)Lscala/collection/immutable/Stream;
	getstatic	Field scala/collection/immutable/Stream$.MODULE$:Lscala/collection/immutable/Stream$;
	invokevirtual	Method scala/collection/immutable/Stream$.canBuildFrom:()Lscala/collection/generic/CanBuildFrom;
	invokevirtual	Method scala/collection/immutable/Stream.$plus$plus:(Lscala/collection/Traversable;Lscala/collection/generic/CanBuildFrom;)Ljava/lang/Object;
	checkcast	class scala/collection/immutable/Stream
	aload_0
	invokevirtual	Method right:()Lscala/collection/immutable/RedBlack$Tree;
	invokevirtual	Method scala/collection/immutable/RedBlack$Tree.toStream:()Lscala/collection/immutable/Stream;
	getstatic	Field scala/collection/immutable/Stream$.MODULE$:Lscala/collection/immutable/Stream$;
	invokevirtual	Method scala/collection/immutable/Stream$.canBuildFrom:()Lscala/collection/generic/CanBuildFrom;
	invokevirtual	Method scala/collection/immutable/Stream.$plus$plus:(Lscala/collection/Traversable;Lscala/collection/generic/CanBuildFrom;)Ljava/lang/Object;
	checkcast	class scala/collection/immutable/Stream
	areturn
  Labels:
  Signature: length = 0x2
   00 FFFFFF88 

public scala.collection.Iterator iterator();
  Signature: ()Lscala/collection/Iterator;
  Code:
   Stack=4, Locals=1, Args_size=1
	aload_0
	invokevirtual	Method left:()Lscala/collection/immutable/RedBlack$Tree;
	invokevirtual	Method scala/collection/immutable/RedBlack$Tree.iterator:()Lscala/collection/Iterator;
	new	class scala/collection/immutable/RedBlack$NonEmpty$$anonfun$iterator$1
	dup
	aload_0
	invokespecial	Method scala/collection/immutable/RedBlack$NonEmpty$$anonfun$iterator$1."<init>":(Lscala/collection/immutable/RedBlack$NonEmpty;)V
	invokeinterface	InterfaceMethod scala/collection/Iterator.$plus$plus:(Lscala/Function0;)Lscala/collection/Iterator;
	new	class scala/collection/immutable/RedBlack$NonEmpty$$anonfun$iterator$2
	dup
	aload_0
	invokespecial	Method scala/collection/immutable/RedBlack$NonEmpty$$anonfun$iterator$2."<init>":(Lscala/collection/immutable/RedBlack$NonEmpty;)V
	invokeinterface	InterfaceMethod scala/collection/Iterator.$plus$plus:(Lscala/Function0;)Lscala/collection/Iterator;
	areturn
  Labels:
  Signature: length = 0x2
   00 FFFFFF9A 

public void foreach(scala.Function2);
  Signature: (Lscala/Function2;)V
  Code:
   Stack=3, Locals=2, Args_size=2
	aload_0
	invokevirtual	Method left:()Lscala/collection/immutable/RedBlack$Tree;
	aload_1
	invokevirtual	Method scala/collection/immutable/RedBlack$Tree.foreach:(Lscala/Function2;)V
	aload_1
	aload_0
	invokevirtual	Method key:()Ljava/lang/Object;
	aload_0
	invokevirtual	Method value:()Ljava/lang/Object;
	invokeinterface	InterfaceMethod scala/Function2.apply:(Ljava/lang/Object;Ljava/lang/Object;)Ljava/lang/Object;
	pop
	aload_0
	invokevirtual	Method right:()Lscala/collection/immutable/RedBlack$Tree;
	aload_1
	invokevirtual	Method scala/collection/immutable/RedBlack$Tree.foreach:(Lscala/Function2;)V
	return
  Labels:
  LocalVariableTable: 
   Start  Length  Slot  Name   Signature
   0      32      0    this       Lscala/collection/immutable/RedBlack$NonEmpty;
   0      32      1    f       Lscala/Function2;

  Signature: length = 0x2
   00 FFFFFFA6 

public scala.Tuple2 visit(java.lang.Object, scala.Function3);
  Signature: (Ljava/lang/Object;Lscala/Function3;)Lscala/Tuple2;
  Code:
   Stack=4, Locals=5, Args_size=3
	aload_0
	invokevirtual	Method left:()Lscala/collection/immutable/RedBlack$Tree;
	aload_1
	aload_2
	invokevirtual	Method scala/collection/immutable/RedBlack$Tree.visit:(Ljava/lang/Object;Lscala/Function3;)Lscala/Tuple2;
	astore_3
	aload_3
	invokevirtual	Method scala/Tuple2._1:()Ljava/lang/Object;
	invokestatic	Method scala/runtime/BoxesRunTime.unboxToBoolean:(Ljava/lang/Object;)Z
	ifeq	l1 // aload_3
	aload_2
	aload_3
	invokevirtual	Method scala/Tuple2._2:()Ljava/lang/Object;
	aload_0
	invokevirtual	Method key:()Ljava/lang/Object;
	aload_0
	invokevirtual	Method value:()Ljava/lang/Object;
	invokeinterface	InterfaceMethod scala/Function3.apply:(Ljava/lang/Object;Ljava/lang/Object;Ljava/lang/Object;)Ljava/lang/Object;
	checkcast	class scala/Tuple2
	astore	4
	aload	4
	invokevirtual	Method scala/Tuple2._1:()Ljava/lang/Object;
	invokestatic	Method scala/runtime/BoxesRunTime.unboxToBoolean:(Ljava/lang/Object;)Z
	ifeq	l2 // aload
	aload_0
	invokevirtual	Method right:()Lscala/collection/immutable/RedBlack$Tree;
	aload	4
	invokevirtual	Method scala/Tuple2._2:()Ljava/lang/Object;
	aload_2
	invokevirtual	Method scala/collection/immutable/RedBlack$Tree.visit:(Ljava/lang/Object;Lscala/Function3;)Lscala/Tuple2;
	areturn
l2	aload	4
	areturn
l1	aload_3
	areturn
  Labels:
   	l2 = 68 // aload
   	l1 = 71 // aload_3
  LocalVariableTable: 
   Start  Length  Slot  Name   Signature
   0      73      0    this       Lscala/collection/immutable/RedBlack$NonEmpty;
   0      73      1    input       Ljava/lang/Object;
   0      73      2    f       Lscala/Function3;
   10      63      3    left       Lscala/Tuple2;
   43      28      4    middle       Lscala/Tuple2;

  Signature: length = 0x2
   00 FFFFFFBF 
  Deprecated: true

public scala.collection.immutable.RedBlack$Tree range(scala.Option, scala.Option);
  Signature: (Lscala/Option;Lscala/Option;)Lscala/collection/immutable/RedBlack$Tree;
  Code:
   Stack=6, Locals=9, Args_size=3
	aload_1
	getstatic	Field scala/None$.MODULE$:Lscala/None$;
	astore_3
	dup
	ifnonnull	l1 // aload_3
	pop
	aload_3
	ifnull	l2 // aload_2
	goto	l3 // aload_1
l1	aload_3
	invokevirtual	Method java/lang/Object.equals:(Ljava/lang/Object;)Z
	ifeq	l3 // aload_1
l2	aload_2
	getstatic	Field scala/None$.MODULE$:Lscala/None$;
	astore	4
	dup
	ifnonnull	l4 // aload
	pop
	aload	4
	ifnull	l5 // aload_0
	goto	l3 // aload_1
l4	aload	4
	invokevirtual	Method java/lang/Object.equals:(Ljava/lang/Object;)Z
	ifeq	l3 // aload_1
l5	aload_0
	areturn
l3	aload_1
	getstatic	Field scala/None$.MODULE$:Lscala/None$;
	astore	5
	dup
	ifnonnull	l6 // aload
	pop
	aload	5
	ifnull	l7 // aload_2
	goto	l8 // aload_0
l6	aload	5
	invokevirtual	Method java/lang/Object.equals:(Ljava/lang/Object;)Z
	ifne	l7 // aload_2
l8	aload_0
	invokevirtual	Method scala$collection$immutable$RedBlack$NonEmpty$$$outer:()Lscala/collection/immutable/RedBlack;
	aload_0
	invokevirtual	Method key:()Ljava/lang/Object;
	aload_1
	invokevirtual	Method scala/Option.get:()Ljava/lang/Object;
	invokevirtual	Method scala/collection/immutable/RedBlack.isSmaller:(Ljava/lang/Object;Ljava/lang/Object;)Z
	ifeq	l7 // aload_2
	aload_0
	invokevirtual	Method right:()Lscala/collection/immutable/RedBlack$Tree;
	aload_1
	aload_2
	invokevirtual	Method scala/collection/immutable/RedBlack$Tree.range:(Lscala/Option;Lscala/Option;)Lscala/collection/immutable/RedBlack$Tree;
	areturn
l7	aload_2
	getstatic	Field scala/None$.MODULE$:Lscala/None$;
	astore	6
	dup
	ifnonnull	l9 // aload
	pop
	aload	6
	ifnull	l10 // aload_0
	goto	l11 // aload_0
l9	aload	6
	invokevirtual	Method java/lang/Object.equals:(Ljava/lang/Object;)Z
	ifne	l10 // aload_0
l11	aload_0
	invokevirtual	Method scala$collection$immutable$RedBlack$NonEmpty$$$outer:()Lscala/collection/immutable/RedBlack;
	aload_2
	invokevirtual	Method scala/Option.get:()Ljava/lang/Object;
	aload_0
	invokevirtual	Method key:()Ljava/lang/Object;
	invokevirtual	Method scala/collection/immutable/RedBlack.isSmaller:(Ljava/lang/Object;Ljava/lang/Object;)Z
	ifne	l12 // aload_0
	aload_0
	invokevirtual	Method scala$collection$immutable$RedBlack$NonEmpty$$$outer:()Lscala/collection/immutable/RedBlack;
	aload_0
	invokevirtual	Method key:()Ljava/lang/Object;
	aload_2
	invokevirtual	Method scala/Option.get:()Ljava/lang/Object;
	invokevirtual	Method scala/collection/immutable/RedBlack.isSmaller:(Ljava/lang/Object;Ljava/lang/Object;)Z
	ifeq	l12 // aload_0
l10	aload_0
	invokevirtual	Method left:()Lscala/collection/immutable/RedBlack$Tree;
	aload_1
	getstatic	Field scala/None$.MODULE$:Lscala/None$;
	invokevirtual	Method scala/collection/immutable/RedBlack$Tree.range:(Lscala/Option;Lscala/Option;)Lscala/collection/immutable/RedBlack$Tree;
	astore	7
	aload_0
	invokevirtual	Method right:()Lscala/collection/immutable/RedBlack$Tree;
	getstatic	Field scala/None$.MODULE$:Lscala/None$;
	aload_2
	invokevirtual	Method scala/collection/immutable/RedBlack$Tree.range:(Lscala/Option;Lscala/Option;)Lscala/collection/immutable/RedBlack$Tree;
	astore	8
	aload	7
	aload_0
	invokevirtual	Method left:()Lscala/collection/immutable/RedBlack$Tree;
	if_acmpne	l13 // aload
	aload	8
	aload_0
	invokevirtual	Method right:()Lscala/collection/immutable/RedBlack$Tree;
	if_acmpne	l13 // aload
	aload_0
	goto	l14 // areturn
l13	aload	7
	aload_0
	invokevirtual	Method scala$collection$immutable$RedBlack$NonEmpty$$$outer:()Lscala/collection/immutable/RedBlack;
	invokevirtual	Method scala/collection/immutable/RedBlack.Empty:()Lscala/collection/immutable/RedBlack$Empty$;
	if_acmpne	l15 // aload
	aload	8
	aload_0
	invokevirtual	Method key:()Ljava/lang/Object;
	aload_0
	invokevirtual	Method value:()Ljava/lang/Object;
	invokevirtual	Method scala/collection/immutable/RedBlack$Tree.upd:(Ljava/lang/Object;Ljava/lang/Object;)Lscala/collection/immutable/RedBlack$Tree;
	goto	l14 // areturn
l15	aload	8
	aload_0
	invokevirtual	Method scala$collection$immutable$RedBlack$NonEmpty$$$outer:()Lscala/collection/immutable/RedBlack;
	invokevirtual	Method scala/collection/immutable/RedBlack.Empty:()Lscala/collection/immutable/RedBlack$Empty$;
	if_acmpne	l16 // aload_0
	aload	7
	aload_0
	invokevirtual	Method key:()Ljava/lang/Object;
	aload_0
	invokevirtual	Method value:()Ljava/lang/Object;
	invokevirtual	Method scala/collection/immutable/RedBlack$Tree.upd:(Ljava/lang/Object;Ljava/lang/Object;)Lscala/collection/immutable/RedBlack$Tree;
	goto	l14 // areturn
l16	aload_0
	invokevirtual	Method scala$collection$immutable$RedBlack$NonEmpty$$$outer:()Lscala/collection/immutable/RedBlack;
	aload_0
	invokevirtual	Method isBlack:()Z
	aload_0
	invokevirtual	Method key:()Ljava/lang/Object;
	aload_0
	invokevirtual	Method value:()Ljava/lang/Object;
	aload	7
	aload	8
	invokevirtual	Method scala/collection/immutable/RedBlack.scala$collection$immutable$RedBlack$$mkTree:(ZLjava/lang/Object;Ljava/lang/Object;Lscala/collection/immutable/RedBlack$Tree;Lscala/collection/immutable/RedBlack$Tree;)Lscala/collection/immutable/RedBlack$NonEmpty;
l14	areturn
l12	aload_0
	invokevirtual	Method left:()Lscala/collection/immutable/RedBlack$Tree;
	aload_1
	aload_2
	invokevirtual	Method scala/collection/immutable/RedBlack$Tree.range:(Lscala/Option;Lscala/Option;)Lscala/collection/immutable/RedBlack$Tree;
	areturn
  Labels:
   	l1 = 17 // aload_3
   	l2 = 24 // aload_2
   	l4 = 43 // aload
   	l5 = 51 // aload_0
   	l3 = 53 // aload_1
   	l6 = 72 // aload
   	l8 = 80 // aload_0
   	l7 = 108 // aload_2
   	l9 = 127 // aload
   	l11 = 135 // aload_0
   	l10 = 171 // aload_0
   	l13 = 219 // aload
   	l15 = 247 // aload
   	l16 = 275 // aload_0
   	l14 = 298 // areturn
   	l12 = 299 // aload_0
  LocalVariableTable: 
   Start  Length  Slot  Name   Signature
   0      309      0    this       Lscala/collection/immutable/RedBlack$NonEmpty;
   0      309      1    from       Lscala/Option;
   0      309      2    until       Lscala/Option;
   184      115      7    newLeft       Lscala/collection/immutable/RedBlack$Tree;
   197      102      8    newRight       Lscala/collection/immutable/RedBlack$Tree;

  Signature: length = 0x2
   00 FFFFFFDE 

public java.lang.Object first();
  Signature: ()Ljava/lang/Object;
  Code:
   Stack=1, Locals=1, Args_size=1
	aload_0
	invokevirtual	Method left:()Lscala/collection/immutable/RedBlack$Tree;
	invokevirtual	Method scala/collection/immutable/RedBlack$Tree.isEmpty:()Z
	ifeq	l1 // aload_0
	aload_0
	invokevirtual	Method key:()Ljava/lang/Object;
	goto	l2 // areturn
l1	aload_0
	invokevirtual	Method left:()Lscala/collection/immutable/RedBlack$Tree;
	invokevirtual	Method scala/collection/immutable/RedBlack$Tree.first:()Ljava/lang/Object;
l2	areturn
  Labels:
   	l1 = 17 // aload_0
   	l2 = 24 // areturn
  Signature: length = 0x2
   00 09 

public java.lang.Object last();
  Signature: ()Ljava/lang/Object;
  Code:
   Stack=1, Locals=1, Args_size=1
	aload_0
	invokevirtual	Method right:()Lscala/collection/immutable/RedBlack$Tree;
	invokevirtual	Method scala/collection/immutable/RedBlack$Tree.isEmpty:()Z
	ifeq	l1 // aload_0
	aload_0
	invokevirtual	Method key:()Ljava/lang/Object;
	goto	l2 // areturn
l1	aload_0
	invokevirtual	Method right:()Lscala/collection/immutable/RedBlack$Tree;
	invokevirtual	Method scala/collection/immutable/RedBlack$Tree.last:()Ljava/lang/Object;
l2	areturn
  Labels:
   	l1 = 17 // aload_0
   	l2 = 24 // areturn
  Signature: length = 0x2
   00 09 

public int count();
  Signature: ()I
  Code:
   Stack=2, Locals=1, Args_size=1
	iconst_1
	aload_0
	invokevirtual	Method left:()Lscala/collection/immutable/RedBlack$Tree;
	invokevirtual	Method scala/collection/immutable/RedBlack$Tree.count:()I
	iadd
	aload_0
	invokevirtual	Method right:()Lscala/collection/immutable/RedBlack$Tree;
	invokevirtual	Method scala/collection/immutable/RedBlack$Tree.count:()I
	iadd
	ireturn
  Labels:

public scala.collection.immutable.RedBlack scala$collection$immutable$RedBlack$NonEmpty$$$outer();
  Signature: ()Lscala/collection/immutable/RedBlack;
  Code:
   Stack=1, Locals=1, Args_size=1
	aload_0
	getfield	Field scala/collection/immutable/RedBlack$Tree.$outer:Lscala/collection/immutable/RedBlack;
	areturn
  Labels:

private final scala.collection.immutable.RedBlack$NonEmpty balanceLeft$1(boolean, java.lang.Object, java.lang.Object, scala.collection.immutable.RedBlack$Tree, scala.collection.immutable.RedBlack$Tree);
  Signature: (ZLjava/lang/Object;Ljava/lang/Object;Lscala/collection/immutable/RedBlack$Tree;Lscala/collection/immutable/RedBlack$Tree;)Lscala/collection/immutable/RedBlack$NonEmpty;
  Code:
   Stack=13, Locals=21, Args_size=6
	aload	4
	instanceof	class scala/collection/immutable/RedBlack$RedTree
	ifeq	l1 // aload_0
	aload	4
	checkcast	class scala/collection/immutable/RedBlack$RedTree
	astore	6
	aload	6
	invokevirtual	Method scala/collection/immutable/RedBlack$RedTree.key:()Ljava/lang/Object;
	astore	16
	aload	6
	invokevirtual	Method scala/collection/immutable/RedBlack$RedTree.value:()Ljava/lang/Object;
	astore	17
	aload	6
	invokevirtual	Method scala/collection/immutable/RedBlack$RedTree.left:()Lscala/collection/immutable/RedBlack$Tree;
	astore	18
	aload	6
	invokevirtual	Method scala/collection/immutable/RedBlack$RedTree.right:()Lscala/collection/immutable/RedBlack$Tree;
	astore	12
	aload	18
	instanceof	class scala/collection/immutable/RedBlack$RedTree
	ifeq	l2 // aload
	aload	18
	checkcast	class scala/collection/immutable/RedBlack$RedTree
	astore	7
	aload	7
	invokevirtual	Method scala/collection/immutable/RedBlack$RedTree.key:()Ljava/lang/Object;
	astore	8
	aload	7
	invokevirtual	Method scala/collection/immutable/RedBlack$RedTree.value:()Ljava/lang/Object;
	astore	9
	aload	7
	invokevirtual	Method scala/collection/immutable/RedBlack$RedTree.left:()Lscala/collection/immutable/RedBlack$Tree;
	astore	10
	aload	7
	invokevirtual	Method scala/collection/immutable/RedBlack$RedTree.right:()Lscala/collection/immutable/RedBlack$Tree;
	astore	11
	new	class scala/collection/immutable/RedBlack$RedTree
	dup
	aload_0
	invokevirtual	Method scala$collection$immutable$RedBlack$NonEmpty$$$outer:()Lscala/collection/immutable/RedBlack;
	aload	16
	aload	17
	new	class scala/collection/immutable/RedBlack$BlackTree
	dup
	aload_0
	invokevirtual	Method scala$collection$immutable$RedBlack$NonEmpty$$$outer:()Lscala/collection/immutable/RedBlack;
	aload	8
	aload	9
	aload	10
	aload	11
	invokespecial	Method scala/collection/immutable/RedBlack$BlackTree."<init>":(Lscala/collection/immutable/RedBlack;Ljava/lang/Object;Ljava/lang/Object;Lscala/collection/immutable/RedBlack$Tree;Lscala/collection/immutable/RedBlack$Tree;)V
	new	class scala/collection/immutable/RedBlack$BlackTree
	dup
	aload_0
	invokevirtual	Method scala$collection$immutable$RedBlack$NonEmpty$$$outer:()Lscala/collection/immutable/RedBlack;
	aload_2
	aload_3
	aload	12
	aload	5
	invokespecial	Method scala/collection/immutable/RedBlack$BlackTree."<init>":(Lscala/collection/immutable/RedBlack;Ljava/lang/Object;Ljava/lang/Object;Lscala/collection/immutable/RedBlack$Tree;Lscala/collection/immutable/RedBlack$Tree;)V
	invokespecial	Method scala/collection/immutable/RedBlack$RedTree."<init>":(Lscala/collection/immutable/RedBlack;Ljava/lang/Object;Ljava/lang/Object;Lscala/collection/immutable/RedBlack$Tree;Lscala/collection/immutable/RedBlack$Tree;)V
	goto	l3 // areturn
l2	aload	12
	instanceof	class scala/collection/immutable/RedBlack$RedTree
	ifeq	l1 // aload_0
	aload	12
	checkcast	class scala/collection/immutable/RedBlack$RedTree
	astore	13
	aload	13
	invokevirtual	Method scala/collection/immutable/RedBlack$RedTree.key:()Ljava/lang/Object;
	astore	14
	aload	13
	invokevirtual	Method scala/collection/immutable/RedBlack$RedTree.value:()Ljava/lang/Object;
	astore	15
	aload	13
	invokevirtual	Method scala/collection/immutable/RedBlack$RedTree.left:()Lscala/collection/immutable/RedBlack$Tree;
	astore	19
	aload	13
	invokevirtual	Method scala/collection/immutable/RedBlack$RedTree.right:()Lscala/collection/immutable/RedBlack$Tree;
	astore	20
	new	class scala/collection/immutable/RedBlack$RedTree
	dup
	aload_0
	invokevirtual	Method scala$collection$immutable$RedBlack$NonEmpty$$$outer:()Lscala/collection/immutable/RedBlack;
	aload	14
	aload	15
	new	class scala/collection/immutable/RedBlack$BlackTree
	dup
	aload_0
	invokevirtual	Method scala$collection$immutable$RedBlack$NonEmpty$$$outer:()Lscala/collection/immutable/RedBlack;
	aload	16
	aload	17
	aload	18
	aload	19
	invokespecial	Method scala/collection/immutable/RedBlack$BlackTree."<init>":(Lscala/collection/immutable/RedBlack;Ljava/lang/Object;Ljava/lang/Object;Lscala/collection/immutable/RedBlack$Tree;Lscala/collection/immutable/RedBlack$Tree;)V
	new	class scala/collection/immutable/RedBlack$BlackTree
	dup
	aload_0
	invokevirtual	Method scala$collection$immutable$RedBlack$NonEmpty$$$outer:()Lscala/collection/immutable/RedBlack;
	aload_2
	aload_3
	aload	20
	aload	5
	invokespecial	Method scala/collection/immutable/RedBlack$BlackTree."<init>":(Lscala/collection/immutable/RedBlack;Ljava/lang/Object;Ljava/lang/Object;Lscala/collection/immutable/RedBlack$Tree;Lscala/collection/immutable/RedBlack$Tree;)V
	invokespecial	Method scala/collection/immutable/RedBlack$RedTree."<init>":(Lscala/collection/immutable/RedBlack;Ljava/lang/Object;Ljava/lang/Object;Lscala/collection/immutable/RedBlack$Tree;Lscala/collection/immutable/RedBlack$Tree;)V
	goto	l3 // areturn
l1	aload_0
	invokevirtual	Method scala$collection$immutable$RedBlack$NonEmpty$$$outer:()Lscala/collection/immutable/RedBlack;
	iload_1
	aload_2
	aload_3
	aload	4
	aload	5
	invokevirtual	Method scala/collection/immutable/RedBlack.scala$collection$immutable$RedBlack$$mkTree:(ZLjava/lang/Object;Ljava/lang/Object;Lscala/collection/immutable/RedBlack$Tree;Lscala/collection/immutable/RedBlack$Tree;)Lscala/collection/immutable/RedBlack$NonEmpty;
l3	areturn
  Labels:
   	l2 = 140 // aload
   	l1 = 237 // aload_0
   	l3 = 251 // areturn
  LocalVariableTable: 
   Start  Length  Slot  Name   Signature
   0      252      0    this       Lscala/collection/immutable/RedBlack$NonEmpty;
   0      252      1    isBlack       Z
   0      252      2    z       Ljava/lang/Object;
   0      252      3    zv       Ljava/lang/Object;
   0      252      4    l       Lscala/collection/immutable/RedBlack$Tree;
   0      252      5    d       Lscala/collection/immutable/RedBlack$Tree;
   15      236      6    temp8       Lscala/collection/immutable/RedBlack$RedTree;
   58      79      7    temp13       Lscala/collection/immutable/RedBlack$RedTree;
   65      72      8    temp14       Ljava/lang/Object;
   72      65      9    temp15       Ljava/lang/Object;
   79      58      10    temp16       Lscala/collection/immutable/RedBlack$Tree;
   86      51      11    temp17       Lscala/collection/immutable/RedBlack$Tree;
   43      208      12    temp12       Lscala/collection/immutable/RedBlack$Tree;
   155      79      13    temp18       Lscala/collection/immutable/RedBlack$RedTree;
   162      72      14    temp19       Ljava/lang/Object;
   169      65      15    temp20       Ljava/lang/Object;
   22      229      16    temp9       Ljava/lang/Object;
   29      222      17    temp10       Ljava/lang/Object;
   36      215      18    temp11       Lscala/collection/immutable/RedBlack$Tree;
   176      58      19    temp21       Lscala/collection/immutable/RedBlack$Tree;
   183      51      20    temp22       Lscala/collection/immutable/RedBlack$Tree;


private final scala.collection.immutable.RedBlack$NonEmpty balanceRight$1(boolean, java.lang.Object, java.lang.Object, scala.collection.immutable.RedBlack$Tree, scala.collection.immutable.RedBlack$Tree);
  Signature: (ZLjava/lang/Object;Ljava/lang/Object;Lscala/collection/immutable/RedBlack$Tree;Lscala/collection/immutable/RedBlack$Tree;)Lscala/collection/immutable/RedBlack$NonEmpty;
  Code:
   Stack=13, Locals=21, Args_size=6
	aload	5
	instanceof	class scala/collection/immutable/RedBlack$RedTree
	ifeq	l1 // aload_0
	aload	5
	checkcast	class scala/collection/immutable/RedBlack$RedTree
	astore	6
	aload	6
	invokevirtual	Method scala/collection/immutable/RedBlack$RedTree.key:()Ljava/lang/Object;
	astore	14
	aload	6
	invokevirtual	Method scala/collection/immutable/RedBlack$RedTree.value:()Ljava/lang/Object;
	astore	15
	aload	6
	invokevirtual	Method scala/collection/immutable/RedBlack$RedTree.left:()Lscala/collection/immutable/RedBlack$Tree;
	astore	16
	aload	6
	invokevirtual	Method scala/collection/immutable/RedBlack$RedTree.right:()Lscala/collection/immutable/RedBlack$Tree;
	astore	12
	aload	16
	instanceof	class scala/collection/immutable/RedBlack$RedTree
	ifeq	l2 // aload
	aload	16
	checkcast	class scala/collection/immutable/RedBlack$RedTree
	astore	7
	aload	7
	invokevirtual	Method scala/collection/immutable/RedBlack$RedTree.key:()Ljava/lang/Object;
	astore	8
	aload	7
	invokevirtual	Method scala/collection/immutable/RedBlack$RedTree.value:()Ljava/lang/Object;
	astore	9
	aload	7
	invokevirtual	Method scala/collection/immutable/RedBlack$RedTree.left:()Lscala/collection/immutable/RedBlack$Tree;
	astore	10
	aload	7
	invokevirtual	Method scala/collection/immutable/RedBlack$RedTree.right:()Lscala/collection/immutable/RedBlack$Tree;
	astore	11
	new	class scala/collection/immutable/RedBlack$RedTree
	dup
	aload_0
	invokevirtual	Method scala$collection$immutable$RedBlack$NonEmpty$$$outer:()Lscala/collection/immutable/RedBlack;
	aload	8
	aload	9
	new	class scala/collection/immutable/RedBlack$BlackTree
	dup
	aload_0
	invokevirtual	Method scala$collection$immutable$RedBlack$NonEmpty$$$outer:()Lscala/collection/immutable/RedBlack;
	aload_2
	aload_3
	aload	4
	aload	10
	invokespecial	Method scala/collection/immutable/RedBlack$BlackTree."<init>":(Lscala/collection/immutable/RedBlack;Ljava/lang/Object;Ljava/lang/Object;Lscala/collection/immutable/RedBlack$Tree;Lscala/collection/immutable/RedBlack$Tree;)V
	new	class scala/collection/immutable/RedBlack$BlackTree
	dup
	aload_0
	invokevirtual	Method scala$collection$immutable$RedBlack$NonEmpty$$$outer:()Lscala/collection/immutable/RedBlack;
	aload	14
	aload	15
	aload	11
	aload	12
	invokespecial	Method scala/collection/immutable/RedBlack$BlackTree."<init>":(Lscala/collection/immutable/RedBlack;Ljava/lang/Object;Ljava/lang/Object;Lscala/collection/immutable/RedBlack$Tree;Lscala/collection/immutable/RedBlack$Tree;)V
	invokespecial	Method scala/collection/immutable/RedBlack$RedTree."<init>":(Lscala/collection/immutable/RedBlack;Ljava/lang/Object;Ljava/lang/Object;Lscala/collection/immutable/RedBlack$Tree;Lscala/collection/immutable/RedBlack$Tree;)V
	goto	l3 // areturn
l2	aload	12
	instanceof	class scala/collection/immutable/RedBlack$RedTree
	ifeq	l1 // aload_0
	aload	12
	checkcast	class scala/collection/immutable/RedBlack$RedTree
	astore	13
	aload	13
	invokevirtual	Method scala/collection/immutable/RedBlack$RedTree.key:()Ljava/lang/Object;
	astore	17
	aload	13
	invokevirtual	Method scala/collection/immutable/RedBlack$RedTree.value:()Ljava/lang/Object;
	astore	18
	aload	13
	invokevirtual	Method scala/collection/immutable/RedBlack$RedTree.left:()Lscala/collection/immutable/RedBlack$Tree;
	astore	19
	aload	13
	invokevirtual	Method scala/collection/immutable/RedBlack$RedTree.right:()Lscala/collection/immutable/RedBlack$Tree;
	astore	20
	new	class scala/collection/immutable/RedBlack$RedTree
	dup
	aload_0
	invokevirtual	Method scala$collection$immutable$RedBlack$NonEmpty$$$outer:()Lscala/collection/immutable/RedBlack;
	aload	14
	aload	15
	new	class scala/collection/immutable/RedBlack$BlackTree
	dup
	aload_0
	invokevirtual	Method scala$collection$immutable$RedBlack$NonEmpty$$$outer:()Lscala/collection/immutable/RedBlack;
	aload_2
	aload_3
	aload	4
	aload	16
	invokespecial	Method scala/collection/immutable/RedBlack$BlackTree."<init>":(Lscala/collection/immutable/RedBlack;Ljava/lang/Object;Ljava/lang/Object;Lscala/collection/immutable/RedBlack$Tree;Lscala/collection/immutable/RedBlack$Tree;)V
	new	class scala/collection/immutable/RedBlack$BlackTree
	dup
	aload_0
	invokevirtual	Method scala$collection$immutable$RedBlack$NonEmpty$$$outer:()Lscala/collection/immutable/RedBlack;
	aload	17
	aload	18
	aload	19
	aload	20
	invokespecial	Method scala/collection/immutable/RedBlack$BlackTree."<init>":(Lscala/collection/immutable/RedBlack;Ljava/lang/Object;Ljava/lang/Object;Lscala/collection/immutable/RedBlack$Tree;Lscala/collection/immutable/RedBlack$Tree;)V
	invokespecial	Method scala/collection/immutable/RedBlack$RedTree."<init>":(Lscala/collection/immutable/RedBlack;Ljava/lang/Object;Ljava/lang/Object;Lscala/collection/immutable/RedBlack$Tree;Lscala/collection/immutable/RedBlack$Tree;)V
	goto	l3 // areturn
l1	aload_0
	invokevirtual	Method scala$collection$immutable$RedBlack$NonEmpty$$$outer:()Lscala/collection/immutable/RedBlack;
	iload_1
	aload_2
	aload_3
	aload	4
	aload	5
	invokevirtual	Method scala/collection/immutable/RedBlack.scala$collection$immutable$RedBlack$$mkTree:(ZLjava/lang/Object;Ljava/lang/Object;Lscala/collection/immutable/RedBlack$Tree;Lscala/collection/immutable/RedBlack$Tree;)Lscala/collection/immutable/RedBlack$NonEmpty;
l3	areturn
  Labels:
   	l2 = 140 // aload
   	l1 = 237 // aload_0
   	l3 = 251 // areturn
  LocalVariableTable: 
   Start  Length  Slot  Name   Signature
   0      252      0    this       Lscala/collection/immutable/RedBlack$NonEmpty;
   0      252      1    isBlack       Z
   0      252      2    x       Ljava/lang/Object;
   0      252      3    xv       Ljava/lang/Object;
   0      252      4    a       Lscala/collection/immutable/RedBlack$Tree;
   0      252      5    r       Lscala/collection/immutable/RedBlack$Tree;
   15      236      6    temp24       Lscala/collection/immutable/RedBlack$RedTree;
   58      79      7    temp29       Lscala/collection/immutable/RedBlack$RedTree;
   65      72      8    temp30       Ljava/lang/Object;
   72      65      9    temp31       Ljava/lang/Object;
   79      58      10    temp32       Lscala/collection/immutable/RedBlack$Tree;
   86      51      11    temp33       Lscala/collection/immutable/RedBlack$Tree;
   43      208      12    temp28       Lscala/collection/immutable/RedBlack$Tree;
   155      79      13    temp34       Lscala/collection/immutable/RedBlack$RedTree;
   22      229      14    temp25       Ljava/lang/Object;
   29      222      15    temp26       Ljava/lang/Object;
   36      215      16    temp27       Lscala/collection/immutable/RedBlack$Tree;
   162      72      17    temp35       Ljava/lang/Object;
   169      65      18    temp36       Ljava/lang/Object;
   176      58      19    temp37       Lscala/collection/immutable/RedBlack$Tree;
   183      51      20    temp38       Lscala/collection/immutable/RedBlack$Tree;


private final scala.collection.immutable.RedBlack$NonEmpty balance$1(java.lang.Object, java.lang.Object, scala.collection.immutable.RedBlack$Tree, scala.collection.immutable.RedBlack$Tree);
  Signature: (Ljava/lang/Object;Ljava/lang/Object;Lscala/collection/immutable/RedBlack$Tree;Lscala/collection/immutable/RedBlack$Tree;)Lscala/collection/immutable/RedBlack$NonEmpty;
  Code:
   Stack=13, Locals=42, Args_size=5
	aload_3
	instanceof	class scala/collection/immutable/RedBlack$RedTree
	ifeq	l1 // aload
	aload_3
	checkcast	class scala/collection/immutable/RedBlack$RedTree
	astore	24
	aload	24
	invokevirtual	Method scala/collection/immutable/RedBlack$RedTree.key:()Ljava/lang/Object;
	astore	19
	aload	24
	invokevirtual	Method scala/collection/immutable/RedBlack$RedTree.value:()Ljava/lang/Object;
	astore	20
	aload	24
	invokevirtual	Method scala/collection/immutable/RedBlack$RedTree.left:()Lscala/collection/immutable/RedBlack$Tree;
	astore	21
	aload	24
	invokevirtual	Method scala/collection/immutable/RedBlack$RedTree.right:()Lscala/collection/immutable/RedBlack$Tree;
	astore	15
	aload	4
	instanceof	class scala/collection/immutable/RedBlack$RedTree
	ifeq	l2 // aload
	aload	4
	checkcast	class scala/collection/immutable/RedBlack$RedTree
	astore	5
	aload	5
	invokevirtual	Method scala/collection/immutable/RedBlack$RedTree.key:()Ljava/lang/Object;
	astore	6
	aload	5
	invokevirtual	Method scala/collection/immutable/RedBlack$RedTree.value:()Ljava/lang/Object;
	astore	7
	aload	5
	invokevirtual	Method scala/collection/immutable/RedBlack$RedTree.left:()Lscala/collection/immutable/RedBlack$Tree;
	astore	8
	aload	5
	invokevirtual	Method scala/collection/immutable/RedBlack$RedTree.right:()Lscala/collection/immutable/RedBlack$Tree;
	astore	9
	new	class scala/collection/immutable/RedBlack$RedTree
	dup
	aload_0
	invokevirtual	Method scala$collection$immutable$RedBlack$NonEmpty$$$outer:()Lscala/collection/immutable/RedBlack;
	aload_1
	aload_2
	new	class scala/collection/immutable/RedBlack$BlackTree
	dup
	aload_0
	invokevirtual	Method scala$collection$immutable$RedBlack$NonEmpty$$$outer:()Lscala/collection/immutable/RedBlack;
	aload	19
	aload	20
	aload	21
	aload	15
	invokespecial	Method scala/collection/immutable/RedBlack$BlackTree."<init>":(Lscala/collection/immutable/RedBlack;Ljava/lang/Object;Ljava/lang/Object;Lscala/collection/immutable/RedBlack$Tree;Lscala/collection/immutable/RedBlack$Tree;)V
	new	class scala/collection/immutable/RedBlack$BlackTree
	dup
	aload_0
	invokevirtual	Method scala$collection$immutable$RedBlack$NonEmpty$$$outer:()Lscala/collection/immutable/RedBlack;
	aload	6
	aload	7
	aload	8
	aload	9
	invokespecial	Method scala/collection/immutable/RedBlack$BlackTree."<init>":(Lscala/collection/immutable/RedBlack;Ljava/lang/Object;Ljava/lang/Object;Lscala/collection/immutable/RedBlack$Tree;Lscala/collection/immutable/RedBlack$Tree;)V
	invokespecial	Method scala/collection/immutable/RedBlack$RedTree."<init>":(Lscala/collection/immutable/RedBlack;Ljava/lang/Object;Ljava/lang/Object;Lscala/collection/immutable/RedBlack$Tree;Lscala/collection/immutable/RedBlack$Tree;)V
	goto	l3 // areturn
l2	aload	21
	instanceof	class scala/collection/immutable/RedBlack$RedTree
	ifeq	l4 // aload
	aload	21
	checkcast	class scala/collection/immutable/RedBlack$RedTree
	astore	10
	aload	10
	invokevirtual	Method scala/collection/immutable/RedBlack$RedTree.key:()Ljava/lang/Object;
	astore	11
	aload	10
	invokevirtual	Method scala/collection/immutable/RedBlack$RedTree.value:()Ljava/lang/Object;
	astore	12
	aload	10
	invokevirtual	Method scala/collection/immutable/RedBlack$RedTree.left:()Lscala/collection/immutable/RedBlack$Tree;
	astore	13
	aload	10
	invokevirtual	Method scala/collection/immutable/RedBlack$RedTree.right:()Lscala/collection/immutable/RedBlack$Tree;
	astore	14
	new	class scala/collection/immutable/RedBlack$RedTree
	dup
	aload_0
	invokevirtual	Method scala$collection$immutable$RedBlack$NonEmpty$$$outer:()Lscala/collection/immutable/RedBlack;
	aload	19
	aload	20
	new	class scala/collection/immutable/RedBlack$BlackTree
	dup
	aload_0
	invokevirtual	Method scala$collection$immutable$RedBlack$NonEmpty$$$outer:()Lscala/collection/immutable/RedBlack;
	aload	11
	aload	12
	aload	13
	aload	14
	invokespecial	Method scala/collection/immutable/RedBlack$BlackTree."<init>":(Lscala/collection/immutable/RedBlack;Ljava/lang/Object;Ljava/lang/Object;Lscala/collection/immutable/RedBlack$Tree;Lscala/collection/immutable/RedBlack$Tree;)V
	new	class scala/collection/immutable/RedBlack$BlackTree
	dup
	aload_0
	invokevirtual	Method scala$collection$immutable$RedBlack$NonEmpty$$$outer:()Lscala/collection/immutable/RedBlack;
	aload_1
	aload_2
	aload	15
	aload	4
	invokespecial	Method scala/collection/immutable/RedBlack$BlackTree."<init>":(Lscala/collection/immutable/RedBlack;Ljava/lang/Object;Ljava/lang/Object;Lscala/collection/immutable/RedBlack$Tree;Lscala/collection/immutable/RedBlack$Tree;)V
	invokespecial	Method scala/collection/immutable/RedBlack$RedTree."<init>":(Lscala/collection/immutable/RedBlack;Ljava/lang/Object;Ljava/lang/Object;Lscala/collection/immutable/RedBlack$Tree;Lscala/collection/immutable/RedBlack$Tree;)V
	goto	l3 // areturn
l4	aload	15
	instanceof	class scala/collection/immutable/RedBlack$RedTree
	ifeq	l5 // aload
	aload	15
	checkcast	class scala/collection/immutable/RedBlack$RedTree
	astore	16
	aload	16
	invokevirtual	Method scala/collection/immutable/RedBlack$RedTree.key:()Ljava/lang/Object;
	astore	17
	aload	16
	invokevirtual	Method scala/collection/immutable/RedBlack$RedTree.value:()Ljava/lang/Object;
	astore	18
	aload	16
	invokevirtual	Method scala/collection/immutable/RedBlack$RedTree.left:()Lscala/collection/immutable/RedBlack$Tree;
	astore	22
	aload	16
	invokevirtual	Method scala/collection/immutable/RedBlack$RedTree.right:()Lscala/collection/immutable/RedBlack$Tree;
	astore	23
	new	class scala/collection/immutable/RedBlack$RedTree
	dup
	aload_0
	invokevirtual	Method scala$collection$immutable$RedBlack$NonEmpty$$$outer:()Lscala/collection/immutable/RedBlack;
	aload	17
	aload	18
	new	class scala/collection/immutable/RedBlack$BlackTree
	dup
	aload_0
	invokevirtual	Method scala$collection$immutable$RedBlack$NonEmpty$$$outer:()Lscala/collection/immutable/RedBlack;
	aload	19
	aload	20
	aload	21
	aload	22
	invokespecial	Method scala/collection/immutable/RedBlack$BlackTree."<init>":(Lscala/collection/immutable/RedBlack;Ljava/lang/Object;Ljava/lang/Object;Lscala/collection/immutable/RedBlack$Tree;Lscala/collection/immutable/RedBlack$Tree;)V
	new	class scala/collection/immutable/RedBlack$BlackTree
	dup
	aload_0
	invokevirtual	Method scala$collection$immutable$RedBlack$NonEmpty$$$outer:()Lscala/collection/immutable/RedBlack;
	aload_1
	aload_2
	aload	23
	aload	4
	invokespecial	Method scala/collection/immutable/RedBlack$BlackTree."<init>":(Lscala/collection/immutable/RedBlack;Ljava/lang/Object;Ljava/lang/Object;Lscala/collection/immutable/RedBlack$Tree;Lscala/collection/immutable/RedBlack$Tree;)V
	invokespecial	Method scala/collection/immutable/RedBlack$RedTree."<init>":(Lscala/collection/immutable/RedBlack;Ljava/lang/Object;Ljava/lang/Object;Lscala/collection/immutable/RedBlack$Tree;Lscala/collection/immutable/RedBlack$Tree;)V
	goto	l3 // areturn
l5	aload	24
	astore	40
	aload	4
	astore	41
	goto	l6 // new
l1	aload	4
	instanceof	class scala/collection/immutable/RedBlack$RedTree
	ifeq	l7 // aload_3
	aload	4
	checkcast	class scala/collection/immutable/RedBlack$RedTree
	astore	39
	aload	39
	invokevirtual	Method scala/collection/immutable/RedBlack$RedTree.key:()Ljava/lang/Object;
	astore	35
	aload	39
	invokevirtual	Method scala/collection/immutable/RedBlack$RedTree.value:()Ljava/lang/Object;
	astore	36
	aload	39
	invokevirtual	Method scala/collection/immutable/RedBlack$RedTree.left:()Lscala/collection/immutable/RedBlack$Tree;
	astore	30
	aload	39
	invokevirtual	Method scala/collection/immutable/RedBlack$RedTree.right:()Lscala/collection/immutable/RedBlack$Tree;
	astore	38
	aload	38
	instanceof	class scala/collection/immutable/RedBlack$RedTree
	ifeq	l8 // aload
	aload	38
	checkcast	class scala/collection/immutable/RedBlack$RedTree
	astore	25
	aload	25
	invokevirtual	Method scala/collection/immutable/RedBlack$RedTree.key:()Ljava/lang/Object;
	astore	26
	aload	25
	invokevirtual	Method scala/collection/immutable/RedBlack$RedTree.value:()Ljava/lang/Object;
	astore	27
	aload	25
	invokevirtual	Method scala/collection/immutable/RedBlack$RedTree.left:()Lscala/collection/immutable/RedBlack$Tree;
	astore	28
	aload	25
	invokevirtual	Method scala/collection/immutable/RedBlack$RedTree.right:()Lscala/collection/immutable/RedBlack$Tree;
	astore	29
	new	class scala/collection/immutable/RedBlack$RedTree
	dup
	aload_0
	invokevirtual	Method scala$collection$immutable$RedBlack$NonEmpty$$$outer:()Lscala/collection/immutable/RedBlack;
	aload	35
	aload	36
	new	class scala/collection/immutable/RedBlack$BlackTree
	dup
	aload_0
	invokevirtual	Method scala$collection$immutable$RedBlack$NonEmpty$$$outer:()Lscala/collection/immutable/RedBlack;
	aload_1
	aload_2
	aload_3
	aload	30
	invokespecial	Method scala/collection/immutable/RedBlack$BlackTree."<init>":(Lscala/collection/immutable/RedBlack;Ljava/lang/Object;Ljava/lang/Object;Lscala/collection/immutable/RedBlack$Tree;Lscala/collection/immutable/RedBlack$Tree;)V
	new	class scala/collection/immutable/RedBlack$BlackTree
	dup
	aload_0
	invokevirtual	Method scala$collection$immutable$RedBlack$NonEmpty$$$outer:()Lscala/collection/immutable/RedBlack;
	aload	26
	aload	27
	aload	28
	aload	29
	invokespecial	Method scala/collection/immutable/RedBlack$BlackTree."<init>":(Lscala/collection/immutable/RedBlack;Ljava/lang/Object;Ljava/lang/Object;Lscala/collection/immutable/RedBlack$Tree;Lscala/collection/immutable/RedBlack$Tree;)V
	invokespecial	Method scala/collection/immutable/RedBlack$RedTree."<init>":(Lscala/collection/immutable/RedBlack;Ljava/lang/Object;Ljava/lang/Object;Lscala/collection/immutable/RedBlack$Tree;Lscala/collection/immutable/RedBlack$Tree;)V
	goto	l3 // areturn
l8	aload	30
	instanceof	class scala/collection/immutable/RedBlack$RedTree
	ifeq	l9 // aload_3
	aload	30
	checkcast	class scala/collection/immutable/RedBlack$RedTree
	astore	31
	aload	31
	invokevirtual	Method scala/collection/immutable/RedBlack$RedTree.key:()Ljava/lang/Object;
	astore	32
	aload	31
	invokevirtual	Method scala/collection/immutable/RedBlack$RedTree.value:()Ljava/lang/Object;
	astore	33
	aload	31
	invokevirtual	Method scala/collection/immutable/RedBlack$RedTree.left:()Lscala/collection/immutable/RedBlack$Tree;
	astore	34
	aload	31
	invokevirtual	Method scala/collection/immutable/RedBlack$RedTree.right:()Lscala/collection/immutable/RedBlack$Tree;
	astore	37
	new	class scala/collection/immutable/RedBlack$RedTree
	dup
	aload_0
	invokevirtual	Method scala$collection$immutable$RedBlack$NonEmpty$$$outer:()Lscala/collection/immutable/RedBlack;
	aload	32
	aload	33
	new	class scala/collection/immutable/RedBlack$BlackTree
	dup
	aload_0
	invokevirtual	Method scala$collection$immutable$RedBlack$NonEmpty$$$outer:()Lscala/collection/immutable/RedBlack;
	aload_1
	aload_2
	aload_3
	aload	34
	invokespecial	Method scala/collection/immutable/RedBlack$BlackTree."<init>":(Lscala/collection/immutable/RedBlack;Ljava/lang/Object;Ljava/lang/Object;Lscala/collection/immutable/RedBlack$Tree;Lscala/collection/immutable/RedBlack$Tree;)V
	new	class scala/collection/immutable/RedBlack$BlackTree
	dup
	aload_0
	invokevirtual	Method scala$collection$immutable$RedBlack$NonEmpty$$$outer:()Lscala/collection/immutable/RedBlack;
	aload	35
	aload	36
	aload	37
	aload	38
	invokespecial	Method scala/collection/immutable/RedBlack$BlackTree."<init>":(Lscala/collection/immutable/RedBlack;Ljava/lang/Object;Ljava/lang/Object;Lscala/collection/immutable/RedBlack$Tree;Lscala/collection/immutable/RedBlack$Tree;)V
	invokespecial	Method scala/collection/immutable/RedBlack$RedTree."<init>":(Lscala/collection/immutable/RedBlack;Ljava/lang/Object;Ljava/lang/Object;Lscala/collection/immutable/RedBlack$Tree;Lscala/collection/immutable/RedBlack$Tree;)V
	goto	l3 // areturn
l9	aload_3
	aload	39
	astore	41
	astore	40
	goto	l6 // new
l7	aload_3
	aload	4
	astore	41
	astore	40
l6	new	class scala/collection/immutable/RedBlack$BlackTree
	dup
	aload_0
	invokevirtual	Method scala$collection$immutable$RedBlack$NonEmpty$$$outer:()Lscala/collection/immutable/RedBlack;
	aload_1
	aload_2
	aload	40
	aload	41
	invokespecial	Method scala/collection/immutable/RedBlack$BlackTree."<init>":(Lscala/collection/immutable/RedBlack;Ljava/lang/Object;Ljava/lang/Object;Lscala/collection/immutable/RedBlack$Tree;Lscala/collection/immutable/RedBlack$Tree;)V
l3	areturn
  Labels:
   	l2 = 138 // aload
   	l4 = 235 // aload
   	l5 = 332 // aload
   	l1 = 343 // aload
   	l8 = 482 // aload
   	l9 = 578 // aload_3
   	l7 = 588 // aload_3
   	l6 = 595 // new
   	l3 = 612 // areturn
  LocalVariableTable: 
   Start  Length  Slot  Name   Signature
   0      613      0    this       Lscala/collection/immutable/RedBlack$NonEmpty;
   0      613      1    x       Ljava/lang/Object;
   0      613      2    xv       Ljava/lang/Object;
   0      613      3    tl       Lscala/collection/immutable/RedBlack$Tree;
   0      613      4    tr       Lscala/collection/immutable/RedBlack$Tree;
   56      79      5    temp44       Lscala/collection/immutable/RedBlack$RedTree;
   63      72      6    temp45       Ljava/lang/Object;
   70      65      7    temp46       Ljava/lang/Object;
   77      58      8    temp47       Lscala/collection/immutable/RedBlack$Tree;
   84      51      9    temp48       Lscala/collection/immutable/RedBlack$Tree;
   153      79      10    temp49       Lscala/collection/immutable/RedBlack$RedTree;
   160      72      11    temp50       Ljava/lang/Object;
   167      65      12    temp51       Ljava/lang/Object;
   174      58      13    temp52       Lscala/collection/immutable/RedBlack$Tree;
   181      51      14    temp53       Lscala/collection/immutable/RedBlack$Tree;
   41      302      15    temp43       Lscala/collection/immutable/RedBlack$Tree;
   595      17      15    temp43       Lscala/collection/immutable/RedBlack$Tree;
   250      79      16    temp54       Lscala/collection/immutable/RedBlack$RedTree;
   257      72      17    temp55       Ljava/lang/Object;
   264      65      18    temp56       Ljava/lang/Object;
   20      323      19    temp40       Ljava/lang/Object;
   595      17      19    temp40       Ljava/lang/Object;
   27      316      20    temp41       Ljava/lang/Object;
   595      17      20    temp41       Ljava/lang/Object;
   34      309      21    temp42       Lscala/collection/immutable/RedBlack$Tree;
   595      17      21    temp42       Lscala/collection/immutable/RedBlack$Tree;
   271      58      22    temp57       Lscala/collection/immutable/RedBlack$Tree;
   278      51      23    temp58       Lscala/collection/immutable/RedBlack$Tree;
   13      330      24    temp39       Lscala/collection/immutable/RedBlack$RedTree;
   595      17      24    temp39       Lscala/collection/immutable/RedBlack$RedTree;
   401      78      25    temp64       Lscala/collection/immutable/RedBlack$RedTree;
   408      71      26    temp65       Ljava/lang/Object;
   415      64      27    temp66       Ljava/lang/Object;
   422      57      28    temp67       Lscala/collection/immutable/RedBlack$Tree;
   429      50      29    temp68       Lscala/collection/immutable/RedBlack$Tree;
   379      209      30    temp62       Lscala/collection/immutable/RedBlack$Tree;
   497      78      31    temp69       Lscala/collection/immutable/RedBlack$RedTree;
   504      71      32    temp70       Ljava/lang/Object;
   511      64      33    temp71       Ljava/lang/Object;
   518      57      34    temp72       Lscala/collection/immutable/RedBlack$Tree;
   365      223      35    temp60       Ljava/lang/Object;
   372      216      36    temp61       Ljava/lang/Object;
   525      50      37    temp73       Lscala/collection/immutable/RedBlack$Tree;
   386      202      38    temp63       Lscala/collection/immutable/RedBlack$Tree;
   358      230      39    temp59       Lscala/collection/immutable/RedBlack$RedTree;
   336      7      40    a       Lscala/collection/immutable/RedBlack$Tree;
   595      17      40    a       Lscala/collection/immutable/RedBlack$Tree;
   340      3      41    b       Lscala/collection/immutable/RedBlack$Tree;
   595      17      41    b       Lscala/collection/immutable/RedBlack$Tree;


private final scala.collection.immutable.RedBlack$RedTree subl$1(scala.collection.immutable.RedBlack$Tree);
  Signature: (Lscala/collection/immutable/RedBlack$Tree;)Lscala/collection/immutable/RedBlack$RedTree;
  Code:
   Stack=7, Locals=8, Args_size=2
	aload_1
	instanceof	class scala/collection/immutable/RedBlack$BlackTree
	ifeq	l1 // new
	aload_1
	checkcast	class scala/collection/immutable/RedBlack$BlackTree
	astore_2
	aload_2
	invokevirtual	Method scala/collection/immutable/RedBlack$BlackTree.key:()Ljava/lang/Object;
	astore_3
	aload_2
	invokevirtual	Method scala/collection/immutable/RedBlack$BlackTree.value:()Ljava/lang/Object;
	astore	4
	aload_2
	invokevirtual	Method scala/collection/immutable/RedBlack$BlackTree.left:()Lscala/collection/immutable/RedBlack$Tree;
	astore	5
	aload_2
	invokevirtual	Method scala/collection/immutable/RedBlack$BlackTree.right:()Lscala/collection/immutable/RedBlack$Tree;
	astore	6
	new	class scala/collection/immutable/RedBlack$RedTree
	dup
	aload_0
	invokevirtual	Method scala$collection$immutable$RedBlack$NonEmpty$$$outer:()Lscala/collection/immutable/RedBlack;
	aload_3
	aload	4
	aload	5
	aload	6
	invokespecial	Method scala/collection/immutable/RedBlack$RedTree."<init>":(Lscala/collection/immutable/RedBlack;Ljava/lang/Object;Ljava/lang/Object;Lscala/collection/immutable/RedBlack$Tree;Lscala/collection/immutable/RedBlack$Tree;)V
	areturn
l1	new	class scala/collection/mutable/StringBuilder
	dup
	invokespecial	Method scala/collection/mutable/StringBuilder."<init>":()V
	ldc_w	String Defect: invariance violation; expected black, got 
	invokevirtual	Method scala/collection/mutable/StringBuilder.append:(Ljava/lang/Object;)Lscala/collection/mutable/StringBuilder;
	aload_1
	invokevirtual	Method scala/collection/mutable/StringBuilder.append:(Ljava/lang/Object;)Lscala/collection/mutable/StringBuilder;
	invokevirtual	Method scala/collection/mutable/StringBuilder.toString:()Ljava/lang/String;
	astore	7
	new	class java/lang/RuntimeException
	dup
	aload	7
	invokespecial	Method java/lang/RuntimeException."<init>":(Ljava/lang/String;)V
	athrow
  Labels:
   	l1 = 54 // new
  LocalVariableTable: 
   Start  Length  Slot  Name   Signature
   0      86      0    this       Lscala/collection/immutable/RedBlack$NonEmpty;
   0      86      1    t       Lscala/collection/immutable/RedBlack$Tree;
   12      41      2    temp75       Lscala/collection/immutable/RedBlack$BlackTree;
   17      36      3    temp76       Ljava/lang/Object;
   23      30      4    temp77       Ljava/lang/Object;
   29      24      5    temp78       Lscala/collection/immutable/RedBlack$Tree;
   35      18      6    temp79       Lscala/collection/immutable/RedBlack$Tree;


private final scala.collection.immutable.RedBlack$NonEmpty balLeft$1(java.lang.Object, java.lang.Object, scala.collection.immutable.RedBlack$Tree, scala.collection.immutable.RedBlack$Tree);
  Signature: (Ljava/lang/Object;Ljava/lang/Object;Lscala/collection/immutable/RedBlack$Tree;Lscala/collection/immutable/RedBlack$Tree;)Lscala/collection/immutable/RedBlack$NonEmpty;
  Code:
   Stack=12, Locals=26, Args_size=5
	aload_3
	instanceof	class scala/collection/immutable/RedBlack$RedTree
	ifeq	l1 // aload
	aload_3
	checkcast	class scala/collection/immutable/RedBlack$RedTree
	astore	5
	aload	5
	invokevirtual	Method scala/collection/immutable/RedBlack$RedTree.key:()Ljava/lang/Object;
	astore	6
	aload	5
	invokevirtual	Method scala/collection/immutable/RedBlack$RedTree.value:()Ljava/lang/Object;
	astore	7
	aload	5
	invokevirtual	Method scala/collection/immutable/RedBlack$RedTree.left:()Lscala/collection/immutable/RedBlack$Tree;
	astore	8
	aload	5
	invokevirtual	Method scala/collection/immutable/RedBlack$RedTree.right:()Lscala/collection/immutable/RedBlack$Tree;
	astore	9
	new	class scala/collection/immutable/RedBlack$RedTree
	dup
	aload_0
	invokevirtual	Method scala$collection$immutable$RedBlack$NonEmpty$$$outer:()Lscala/collection/immutable/RedBlack;
	aload_1
	aload_2
	new	class scala/collection/immutable/RedBlack$BlackTree
	dup
	aload_0
	invokevirtual	Method scala$collection$immutable$RedBlack$NonEmpty$$$outer:()Lscala/collection/immutable/RedBlack;
	aload	6
	aload	7
	aload	8
	aload	9
	invokespecial	Method scala/collection/immutable/RedBlack$BlackTree."<init>":(Lscala/collection/immutable/RedBlack;Ljava/lang/Object;Ljava/lang/Object;Lscala/collection/immutable/RedBlack$Tree;Lscala/collection/immutable/RedBlack$Tree;)V
	aload	4
	invokespecial	Method scala/collection/immutable/RedBlack$RedTree."<init>":(Lscala/collection/immutable/RedBlack;Ljava/lang/Object;Ljava/lang/Object;Lscala/collection/immutable/RedBlack$Tree;Lscala/collection/immutable/RedBlack$Tree;)V
	goto	l2 // areturn
l1	aload	4
	instanceof	class scala/collection/immutable/RedBlack$BlackTree
	ifeq	l3 // aload
	aload	4
	checkcast	class scala/collection/immutable/RedBlack$BlackTree
	astore	10
	aload	10
	invokevirtual	Method scala/collection/immutable/RedBlack$BlackTree.key:()Ljava/lang/Object;
	astore	11
	aload	10
	invokevirtual	Method scala/collection/immutable/RedBlack$BlackTree.value:()Ljava/lang/Object;
	astore	12
	aload	10
	invokevirtual	Method scala/collection/immutable/RedBlack$BlackTree.left:()Lscala/collection/immutable/RedBlack$Tree;
	astore	13
	aload	10
	invokevirtual	Method scala/collection/immutable/RedBlack$BlackTree.right:()Lscala/collection/immutable/RedBlack$Tree;
	astore	14
	aload_0
	aload_1
	aload_2
	aload_3
	new	class scala/collection/immutable/RedBlack$RedTree
	dup
	aload_0
	invokevirtual	Method scala$collection$immutable$RedBlack$NonEmpty$$$outer:()Lscala/collection/immutable/RedBlack;
	aload	11
	aload	12
	aload	13
	aload	14
	invokespecial	Method scala/collection/immutable/RedBlack$RedTree."<init>":(Lscala/collection/immutable/RedBlack;Ljava/lang/Object;Ljava/lang/Object;Lscala/collection/immutable/RedBlack$Tree;Lscala/collection/immutable/RedBlack$Tree;)V
	invokespecial	Method balance$1:(Ljava/lang/Object;Ljava/lang/Object;Lscala/collection/immutable/RedBlack$Tree;Lscala/collection/immutable/RedBlack$Tree;)Lscala/collection/immutable/RedBlack$NonEmpty;
	goto	l2 // areturn
l3	aload	4
	instanceof	class scala/collection/immutable/RedBlack$RedTree
	ifeq	l4 // new
	aload	4
	checkcast	class scala/collection/immutable/RedBlack$RedTree
	astore	15
	aload	15
	invokevirtual	Method scala/collection/immutable/RedBlack$RedTree.key:()Ljava/lang/Object;
	astore	21
	aload	15
	invokevirtual	Method scala/collection/immutable/RedBlack$RedTree.value:()Ljava/lang/Object;
	astore	22
	aload	15
	invokevirtual	Method scala/collection/immutable/RedBlack$RedTree.left:()Lscala/collection/immutable/RedBlack$Tree;
	astore	16
	aload	15
	invokevirtual	Method scala/collection/immutable/RedBlack$RedTree.right:()Lscala/collection/immutable/RedBlack$Tree;
	astore	24
	aload	16
	instanceof	class scala/collection/immutable/RedBlack$BlackTree
	ifeq	l4 // new
	aload	16
	checkcast	class scala/collection/immutable/RedBlack$BlackTree
	astore	17
	aload	17
	invokevirtual	Method scala/collection/immutable/RedBlack$BlackTree.key:()Ljava/lang/Object;
	astore	18
	aload	17
	invokevirtual	Method scala/collection/immutable/RedBlack$BlackTree.value:()Ljava/lang/Object;
	astore	19
	aload	17
	invokevirtual	Method scala/collection/immutable/RedBlack$BlackTree.left:()Lscala/collection/immutable/RedBlack$Tree;
	astore	20
	aload	17
	invokevirtual	Method scala/collection/immutable/RedBlack$BlackTree.right:()Lscala/collection/immutable/RedBlack$Tree;
	astore	23
	new	class scala/collection/immutable/RedBlack$RedTree
	dup
	aload_0
	invokevirtual	Method scala$collection$immutable$RedBlack$NonEmpty$$$outer:()Lscala/collection/immutable/RedBlack;
	aload	18
	aload	19
	new	class scala/collection/immutable/RedBlack$BlackTree
	dup
	aload_0
	invokevirtual	Method scala$collection$immutable$RedBlack$NonEmpty$$$outer:()Lscala/collection/immutable/RedBlack;
	aload_1
	aload_2
	aload_3
	aload	20
	invokespecial	Method scala/collection/immutable/RedBlack$BlackTree."<init>":(Lscala/collection/immutable/RedBlack;Ljava/lang/Object;Ljava/lang/Object;Lscala/collection/immutable/RedBlack$Tree;Lscala/collection/immutable/RedBlack$Tree;)V
	aload_0
	aload	21
	aload	22
	aload	23
	aload_0
	aload	24
	invokespecial	Method subl$1:(Lscala/collection/immutable/RedBlack$Tree;)Lscala/collection/immutable/RedBlack$RedTree;
	invokespecial	Method balance$1:(Ljava/lang/Object;Ljava/lang/Object;Lscala/collection/immutable/RedBlack$Tree;Lscala/collection/immutable/RedBlack$Tree;)Lscala/collection/immutable/RedBlack$NonEmpty;
	invokespecial	Method scala/collection/immutable/RedBlack$RedTree."<init>":(Lscala/collection/immutable/RedBlack;Ljava/lang/Object;Ljava/lang/Object;Lscala/collection/immutable/RedBlack$Tree;Lscala/collection/immutable/RedBlack$Tree;)V
l2	areturn
l4	new	class scala/collection/mutable/StringBuilder
	dup
	invokespecial	Method scala/collection/mutable/StringBuilder."<init>":()V
	ldc_w	String Defect: invariance violation at 
	invokevirtual	Method scala/collection/mutable/StringBuilder.append:(Ljava/lang/Object;)Lscala/collection/mutable/StringBuilder;
	aload_0
	invokevirtual	Method right:()Lscala/collection/immutable/RedBlack$Tree;
	invokevirtual	Method scala/collection/mutable/StringBuilder.append:(Ljava/lang/Object;)Lscala/collection/mutable/StringBuilder;
	invokevirtual	Method scala/collection/mutable/StringBuilder.toString:()Ljava/lang/String;
	astore	25
	new	class java/lang/RuntimeException
	dup
	aload	25
	invokespecial	Method java/lang/RuntimeException."<init>":(Ljava/lang/String;)V
	athrow
  Labels:
   	l1 = 78 // aload
   	l3 = 150 // aload
   	l2 = 283 // areturn
   	l4 = 284 // new
  LocalVariableTable: 
   Start  Length  Slot  Name   Signature
   0      319      0    this       Lscala/collection/immutable/RedBlack$NonEmpty;
   0      319      1    x       Ljava/lang/Object;
   0      319      2    xv       Ljava/lang/Object;
   0      319      3    tl       Lscala/collection/immutable/RedBlack$Tree;
   0      319      4    tr       Lscala/collection/immutable/RedBlack$Tree;
   13      62      5    temp80       Lscala/collection/immutable/RedBlack$RedTree;
   20      55      6    temp81       Ljava/lang/Object;
   27      48      7    temp82       Ljava/lang/Object;
   34      41      8    temp83       Lscala/collection/immutable/RedBlack$Tree;
   41      34      9    temp84       Lscala/collection/immutable/RedBlack$Tree;
   93      54      10    temp85       Lscala/collection/immutable/RedBlack$BlackTree;
   100      47      11    temp86       Ljava/lang/Object;
   107      40      12    temp87       Ljava/lang/Object;
   114      33      13    temp88       Lscala/collection/immutable/RedBlack$Tree;
   121      26      14    temp89       Lscala/collection/immutable/RedBlack$Tree;
   165      118      15    temp90       Lscala/collection/immutable/RedBlack$RedTree;
   284      35      15    temp90       Lscala/collection/immutable/RedBlack$RedTree;
   186      97      16    temp93       Lscala/collection/immutable/RedBlack$Tree;
   284      35      16    temp93       Lscala/collection/immutable/RedBlack$Tree;
   208      75      17    temp95       Lscala/collection/immutable/RedBlack$BlackTree;
   215      68      18    temp96       Ljava/lang/Object;
   222      61      19    temp97       Ljava/lang/Object;
   229      54      20    temp98       Lscala/collection/immutable/RedBlack$Tree;
   172      111      21    temp91       Ljava/lang/Object;
   284      35      21    temp91       Ljava/lang/Object;
   179      104      22    temp92       Ljava/lang/Object;
   284      35      22    temp92       Ljava/lang/Object;
   236      47      23    temp99       Lscala/collection/immutable/RedBlack$Tree;
   193      90      24    temp94       Lscala/collection/immutable/RedBlack$Tree;
   284      35      24    temp94       Lscala/collection/immutable/RedBlack$Tree;


private final scala.collection.immutable.RedBlack$NonEmpty balRight$1(java.lang.Object, java.lang.Object, scala.collection.immutable.RedBlack$Tree, scala.collection.immutable.RedBlack$Tree);
  Signature: (Ljava/lang/Object;Ljava/lang/Object;Lscala/collection/immutable/RedBlack$Tree;Lscala/collection/immutable/RedBlack$Tree;)Lscala/collection/immutable/RedBlack$NonEmpty;
  Code:
   Stack=13, Locals=26, Args_size=5
	aload	4
	instanceof	class scala/collection/immutable/RedBlack$RedTree
	ifeq	l1 // aload_3
	aload	4
	checkcast	class scala/collection/immutable/RedBlack$RedTree
	astore	5
	aload	5
	invokevirtual	Method scala/collection/immutable/RedBlack$RedTree.key:()Ljava/lang/Object;
	astore	6
	aload	5
	invokevirtual	Method scala/collection/immutable/RedBlack$RedTree.value:()Ljava/lang/Object;
	astore	7
	aload	5
	invokevirtual	Method scala/collection/immutable/RedBlack$RedTree.left:()Lscala/collection/immutable/RedBlack$Tree;
	astore	8
	aload	5
	invokevirtual	Method scala/collection/immutable/RedBlack$RedTree.right:()Lscala/collection/immutable/RedBlack$Tree;
	astore	9
	new	class scala/collection/immutable/RedBlack$RedTree
	dup
	aload_0
	invokevirtual	Method scala$collection$immutable$RedBlack$NonEmpty$$$outer:()Lscala/collection/immutable/RedBlack;
	aload_1
	aload_2
	aload_3
	new	class scala/collection/immutable/RedBlack$BlackTree
	dup
	aload_0
	invokevirtual	Method scala$collection$immutable$RedBlack$NonEmpty$$$outer:()Lscala/collection/immutable/RedBlack;
	aload	6
	aload	7
	aload	8
	aload	9
	invokespecial	Method scala/collection/immutable/RedBlack$BlackTree."<init>":(Lscala/collection/immutable/RedBlack;Ljava/lang/Object;Ljava/lang/Object;Lscala/collection/immutable/RedBlack$Tree;Lscala/collection/immutable/RedBlack$Tree;)V
	invokespecial	Method scala/collection/immutable/RedBlack$RedTree."<init>":(Lscala/collection/immutable/RedBlack;Ljava/lang/Object;Ljava/lang/Object;Lscala/collection/immutable/RedBlack$Tree;Lscala/collection/immutable/RedBlack$Tree;)V
	goto	l2 // areturn
l1	aload_3
	instanceof	class scala/collection/immutable/RedBlack$BlackTree
	ifeq	l3 // aload_3
	aload_3
	checkcast	class scala/collection/immutable/RedBlack$BlackTree
	astore	10
	aload	10
	invokevirtual	Method scala/collection/immutable/RedBlack$BlackTree.key:()Ljava/lang/Object;
	astore	11
	aload	10
	invokevirtual	Method scala/collection/immutable/RedBlack$BlackTree.value:()Ljava/lang/Object;
	astore	12
	aload	10
	invokevirtual	Method scala/collection/immutable/RedBlack$BlackTree.left:()Lscala/collection/immutable/RedBlack$Tree;
	astore	13
	aload	10
	invokevirtual	Method scala/collection/immutable/RedBlack$BlackTree.right:()Lscala/collection/immutable/RedBlack$Tree;
	astore	14
	aload_0
	aload_1
	aload_2
	new	class scala/collection/immutable/RedBlack$RedTree
	dup
	aload_0
	invokevirtual	Method scala$collection$immutable$RedBlack$NonEmpty$$$outer:()Lscala/collection/immutable/RedBlack;
	aload	11
	aload	12
	aload	13
	aload	14
	invokespecial	Method scala/collection/immutable/RedBlack$RedTree."<init>":(Lscala/collection/immutable/RedBlack;Ljava/lang/Object;Ljava/lang/Object;Lscala/collection/immutable/RedBlack$Tree;Lscala/collection/immutable/RedBlack$Tree;)V
	aload	4
	invokespecial	Method balance$1:(Ljava/lang/Object;Ljava/lang/Object;Lscala/collection/immutable/RedBlack$Tree;Lscala/collection/immutable/RedBlack$Tree;)Lscala/collection/immutable/RedBlack$NonEmpty;
	goto	l2 // areturn
l3	aload_3
	instanceof	class scala/collection/immutable/RedBlack$RedTree
	ifeq	l4 // new
	aload_3
	checkcast	class scala/collection/immutable/RedBlack$RedTree
	astore	15
	aload	15
	invokevirtual	Method scala/collection/immutable/RedBlack$RedTree.key:()Ljava/lang/Object;
	astore	20
	aload	15
	invokevirtual	Method scala/collection/immutable/RedBlack$RedTree.value:()Ljava/lang/Object;
	astore	21
	aload	15
	invokevirtual	Method scala/collection/immutable/RedBlack$RedTree.left:()Lscala/collection/immutable/RedBlack$Tree;
	astore	22
	aload	15
	invokevirtual	Method scala/collection/immutable/RedBlack$RedTree.right:()Lscala/collection/immutable/RedBlack$Tree;
	astore	16
	aload	16
	instanceof	class scala/collection/immutable/RedBlack$BlackTree
	ifeq	l4 // new
	aload	16
	checkcast	class scala/collection/immutable/RedBlack$BlackTree
	astore	17
	aload	17
	invokevirtual	Method scala/collection/immutable/RedBlack$BlackTree.key:()Ljava/lang/Object;
	astore	18
	aload	17
	invokevirtual	Method scala/collection/immutable/RedBlack$BlackTree.value:()Ljava/lang/Object;
	astore	19
	aload	17
	invokevirtual	Method scala/collection/immutable/RedBlack$BlackTree.left:()Lscala/collection/immutable/RedBlack$Tree;
	astore	23
	aload	17
	invokevirtual	Method scala/collection/immutable/RedBlack$BlackTree.right:()Lscala/collection/immutable/RedBlack$Tree;
	astore	24
	new	class scala/collection/immutable/RedBlack$RedTree
	dup
	aload_0
	invokevirtual	Method scala$collection$immutable$RedBlack$NonEmpty$$$outer:()Lscala/collection/immutable/RedBlack;
	aload	18
	aload	19
	aload_0
	aload	20
	aload	21
	aload_0
	aload	22
	invokespecial	Method subl$1:(Lscala/collection/immutable/RedBlack$Tree;)Lscala/collection/immutable/RedBlack$RedTree;
	aload	23
	invokespecial	Method balance$1:(Ljava/lang/Object;Ljava/lang/Object;Lscala/collection/immutable/RedBlack$Tree;Lscala/collection/immutable/RedBlack$Tree;)Lscala/collection/immutable/RedBlack$NonEmpty;
	new	class scala/collection/immutable/RedBlack$BlackTree
	dup
	aload_0
	invokevirtual	Method scala$collection$immutable$RedBlack$NonEmpty$$$outer:()Lscala/collection/immutable/RedBlack;
	aload_1
	aload_2
	aload	24
	aload	4
	invokespecial	Method scala/collection/immutable/RedBlack$BlackTree."<init>":(Lscala/collection/immutable/RedBlack;Ljava/lang/Object;Ljava/lang/Object;Lscala/collection/immutable/RedBlack$Tree;Lscala/collection/immutable/RedBlack$Tree;)V
	invokespecial	Method scala/collection/immutable/RedBlack$RedTree."<init>":(Lscala/collection/immutable/RedBlack;Ljava/lang/Object;Ljava/lang/Object;Lscala/collection/immutable/RedBlack$Tree;Lscala/collection/immutable/RedBlack$Tree;)V
l2	areturn
l4	new	class scala/collection/mutable/StringBuilder
	dup
	invokespecial	Method scala/collection/mutable/StringBuilder."<init>":()V
	ldc_w	String Defect: invariance violation at 
	invokevirtual	Method scala/collection/mutable/StringBuilder.append:(Ljava/lang/Object;)Lscala/collection/mutable/StringBuilder;
	aload_0
	invokevirtual	Method left:()Lscala/collection/immutable/RedBlack$Tree;
	invokevirtual	Method scala/collection/mutable/StringBuilder.append:(Ljava/lang/Object;)Lscala/collection/mutable/StringBuilder;
	invokevirtual	Method scala/collection/mutable/StringBuilder.toString:()Ljava/lang/String;
	astore	25
	new	class java/lang/RuntimeException
	dup
	aload	25
	invokespecial	Method java/lang/RuntimeException."<init>":(Ljava/lang/String;)V
	athrow
  Labels:
   	l1 = 79 // aload_3
   	l3 = 150 // aload_3
   	l2 = 282 // areturn
   	l4 = 283 // new
  LocalVariableTable: 
   Start  Length  Slot  Name   Signature
   0      318      0    this       Lscala/collection/immutable/RedBlack$NonEmpty;
   0      318      1    x       Ljava/lang/Object;
   0      318      2    xv       Ljava/lang/Object;
   0      318      3    tl       Lscala/collection/immutable/RedBlack$Tree;
   0      318      4    tr       Lscala/collection/immutable/RedBlack$Tree;
   15      61      5    temp100       Lscala/collection/immutable/RedBlack$RedTree;
   22      54      6    temp101       Ljava/lang/Object;
   29      47      7    temp102       Ljava/lang/Object;
   36      40      8    temp103       Lscala/collection/immutable/RedBlack$Tree;
   43      33      9    temp104       Lscala/collection/immutable/RedBlack$Tree;
   92      55      10    temp105       Lscala/collection/immutable/RedBlack$BlackTree;
   99      48      11    temp106       Ljava/lang/Object;
   106      41      12    temp107       Ljava/lang/Object;
   113      34      13    temp108       Lscala/collection/immutable/RedBlack$Tree;
   120      27      14    temp109       Lscala/collection/immutable/RedBlack$Tree;
   163      119      15    temp110       Lscala/collection/immutable/RedBlack$RedTree;
   283      35      15    temp110       Lscala/collection/immutable/RedBlack$RedTree;
   191      91      16    temp114       Lscala/collection/immutable/RedBlack$Tree;
   283      35      16    temp114       Lscala/collection/immutable/RedBlack$Tree;
   206      76      17    temp115       Lscala/collection/immutable/RedBlack$BlackTree;
   213      69      18    temp116       Ljava/lang/Object;
   220      62      19    temp117       Ljava/lang/Object;
   170      112      20    temp111       Ljava/lang/Object;
   283      35      20    temp111       Ljava/lang/Object;
   177      105      21    temp112       Ljava/lang/Object;
   283      35      21    temp112       Ljava/lang/Object;
   184      98      22    temp113       Lscala/collection/immutable/RedBlack$Tree;
   283      35      22    temp113       Lscala/collection/immutable/RedBlack$Tree;
   227      55      23    temp118       Lscala/collection/immutable/RedBlack$Tree;
   234      48      24    temp119       Lscala/collection/immutable/RedBlack$Tree;


private final scala.collection.immutable.RedBlack$NonEmpty delLeft$1(java.lang.Object);
  Signature: (Ljava/lang/Object;)Lscala/collection/immutable/RedBlack$NonEmpty;
  Code:
   Stack=7, Locals=3, Args_size=2
	aload_0
	invokevirtual	Method left:()Lscala/collection/immutable/RedBlack$Tree;
	astore_2
	aload_2
	instanceof	class scala/collection/immutable/RedBlack$BlackTree
	ifeq	l1 // new
	aload_0
	aload_0
	invokevirtual	Method key:()Ljava/lang/Object;
	aload_0
	invokevirtual	Method value:()Ljava/lang/Object;
	aload_0
	invokevirtual	Method left:()Lscala/collection/immutable/RedBlack$Tree;
	aload_1
	invokevirtual	Method scala/collection/immutable/RedBlack$Tree.del:(Ljava/lang/Object;)Lscala/collection/immutable/RedBlack$Tree;
	aload_0
	invokevirtual	Method right:()Lscala/collection/immutable/RedBlack$Tree;
	invokespecial	Method balLeft$1:(Ljava/lang/Object;Ljava/lang/Object;Lscala/collection/immutable/RedBlack$Tree;Lscala/collection/immutable/RedBlack$Tree;)Lscala/collection/immutable/RedBlack$NonEmpty;
	goto	l2 // areturn
l1	new	class scala/collection/immutable/RedBlack$RedTree
	dup
	aload_0
	invokevirtual	Method scala$collection$immutable$RedBlack$NonEmpty$$$outer:()Lscala/collection/immutable/RedBlack;
	aload_0
	invokevirtual	Method key:()Ljava/lang/Object;
	aload_0
	invokevirtual	Method value:()Ljava/lang/Object;
	aload_0
	invokevirtual	Method left:()Lscala/collection/immutable/RedBlack$Tree;
	aload_1
	invokevirtual	Method scala/collection/immutable/RedBlack$Tree.del:(Ljava/lang/Object;)Lscala/collection/immutable/RedBlack$Tree;
	aload_0
	invokevirtual	Method right:()Lscala/collection/immutable/RedBlack$Tree;
	invokespecial	Method scala/collection/immutable/RedBlack$RedTree."<init>":(Lscala/collection/immutable/RedBlack;Ljava/lang/Object;Ljava/lang/Object;Lscala/collection/immutable/RedBlack$Tree;Lscala/collection/immutable/RedBlack$Tree;)V
l2	areturn
  Labels:
   	l1 = 39 // new
   	l2 = 70 // areturn
  LocalVariableTable: 
   Start  Length  Slot  Name   Signature
   0      71      0    this       Lscala/collection/immutable/RedBlack$NonEmpty;
   5      66      2    temp120       Lscala/collection/immutable/RedBlack$Tree;


private final scala.collection.immutable.RedBlack$NonEmpty delRight$1(java.lang.Object);
  Signature: (Ljava/lang/Object;)Lscala/collection/immutable/RedBlack$NonEmpty;
  Code:
   Stack=8, Locals=3, Args_size=2
	aload_0
	invokevirtual	Method right:()Lscala/collection/immutable/RedBlack$Tree;
	astore_2
	aload_2
	instanceof	class scala/collection/immutable/RedBlack$BlackTree
	ifeq	l1 // new
	aload_0
	aload_0
	invokevirtual	Method key:()Ljava/lang/Object;
	aload_0
	invokevirtual	Method value:()Ljava/lang/Object;
	aload_0
	invokevirtual	Method left:()Lscala/collection/immutable/RedBlack$Tree;
	aload_0
	invokevirtual	Method right:()Lscala/collection/immutable/RedBlack$Tree;
	aload_1
	invokevirtual	Method scala/collection/immutable/RedBlack$Tree.del:(Ljava/lang/Object;)Lscala/collection/immutable/RedBlack$Tree;
	invokespecial	Method balRight$1:(Ljava/lang/Object;Ljava/lang/Object;Lscala/collection/immutable/RedBlack$Tree;Lscala/collection/immutable/RedBlack$Tree;)Lscala/collection/immutable/RedBlack$NonEmpty;
	goto	l2 // areturn
l1	new	class scala/collection/immutable/RedBlack$RedTree
	dup
	aload_0
	invokevirtual	Method scala$collection$immutable$RedBlack$NonEmpty$$$outer:()Lscala/collection/immutable/RedBlack;
	aload_0
	invokevirtual	Method key:()Ljava/lang/Object;
	aload_0
	invokevirtual	Method value:()Ljava/lang/Object;
	aload_0
	invokevirtual	Method left:()Lscala/collection/immutable/RedBlack$Tree;
	aload_0
	invokevirtual	Method right:()Lscala/collection/immutable/RedBlack$Tree;
	aload_1
	invokevirtual	Method scala/collection/immutable/RedBlack$Tree.del:(Ljava/lang/Object;)Lscala/collection/immutable/RedBlack$Tree;
	invokespecial	Method scala/collection/immutable/RedBlack$RedTree."<init>":(Lscala/collection/immutable/RedBlack;Ljava/lang/Object;Ljava/lang/Object;Lscala/collection/immutable/RedBlack$Tree;Lscala/collection/immutable/RedBlack$Tree;)V
l2	areturn
  Labels:
   	l1 = 39 // new
   	l2 = 70 // areturn
  LocalVariableTable: 
   Start  Length  Slot  Name   Signature
   0      71      0    this       Lscala/collection/immutable/RedBlack$NonEmpty;
   5      66      2    temp126       Lscala/collection/immutable/RedBlack$Tree;


private final scala.collection.immutable.RedBlack$Tree append$1(scala.collection.immutable.RedBlack$Tree, scala.collection.immutable.RedBlack$Tree);
  Signature: (Lscala/collection/immutable/RedBlack$Tree;Lscala/collection/immutable/RedBlack$Tree;)Lscala/collection/immutable/RedBlack$Tree;
  Code:
   Stack=13, Locals=48, Args_size=3
	aload_1
	aload_0
	invokevirtual	Method scala$collection$immutable$RedBlack$NonEmpty$$$outer:()Lscala/collection/immutable/RedBlack;
	invokevirtual	Method scala/collection/immutable/RedBlack.Empty:()Lscala/collection/immutable/RedBlack$Empty$;
	astore_3
	dup
	ifnonnull	l1 // aload_3
	pop
	aload_3
	ifnull	l2 // aload_2
	goto	l3 // aload_2
l1	aload_3
	invokevirtual	Method java/lang/Object.equals:(Ljava/lang/Object;)Z
	ifeq	l3 // aload_2
l2	aload_2
	goto	l4 // areturn
l3	aload_2
	aload_0
	invokevirtual	Method scala$collection$immutable$RedBlack$NonEmpty$$$outer:()Lscala/collection/immutable/RedBlack;
	invokevirtual	Method scala/collection/immutable/RedBlack.Empty:()Lscala/collection/immutable/RedBlack$Empty$;
	astore	4
	dup
	ifnonnull	l5 // aload
	pop
	aload	4
	ifnull	l6 // aload_1
	goto	l7 // aload_2
l5	aload	4
	invokevirtual	Method java/lang/Object.equals:(Ljava/lang/Object;)Z
	ifeq	l7 // aload_2
l6	aload_1
	goto	l4 // areturn
l7	aload_2
	instanceof	class scala/collection/immutable/RedBlack$RedTree
	ifeq	l8 // aload_2
	aload_2
	checkcast	class scala/collection/immutable/RedBlack$RedTree
	astore	5
	aload	5
	invokevirtual	Method scala/collection/immutable/RedBlack$RedTree.key:()Ljava/lang/Object;
	astore	17
	aload	5
	invokevirtual	Method scala/collection/immutable/RedBlack$RedTree.value:()Ljava/lang/Object;
	astore	18
	aload	5
	invokevirtual	Method scala/collection/immutable/RedBlack$RedTree.left:()Lscala/collection/immutable/RedBlack$Tree;
	astore	19
	aload	5
	invokevirtual	Method scala/collection/immutable/RedBlack$RedTree.right:()Lscala/collection/immutable/RedBlack$Tree;
	astore	20
	aload_1
	instanceof	class scala/collection/immutable/RedBlack$RedTree
	ifeq	l9 // new
	aload_1
	checkcast	class scala/collection/immutable/RedBlack$RedTree
	astore	6
	aload	6
	invokevirtual	Method scala/collection/immutable/RedBlack$RedTree.key:()Ljava/lang/Object;
	astore	13
	aload	6
	invokevirtual	Method scala/collection/immutable/RedBlack$RedTree.value:()Ljava/lang/Object;
	astore	14
	aload	6
	invokevirtual	Method scala/collection/immutable/RedBlack$RedTree.left:()Lscala/collection/immutable/RedBlack$Tree;
	astore	15
	aload	6
	invokevirtual	Method scala/collection/immutable/RedBlack$RedTree.right:()Lscala/collection/immutable/RedBlack$Tree;
	astore	7
	aload_0
	aload	7
	aload	19
	invokespecial	Method append$1:(Lscala/collection/immutable/RedBlack$Tree;Lscala/collection/immutable/RedBlack$Tree;)Lscala/collection/immutable/RedBlack$Tree;
	astore	16
	aload	16
	instanceof	class scala/collection/immutable/RedBlack$RedTree
	ifeq	l10 // new
	aload	16
	checkcast	class scala/collection/immutable/RedBlack$RedTree
	astore	8
	aload	8
	invokevirtual	Method scala/collection/immutable/RedBlack$RedTree.key:()Ljava/lang/Object;
	astore	9
	aload	8
	invokevirtual	Method scala/collection/immutable/RedBlack$RedTree.value:()Ljava/lang/Object;
	astore	10
	aload	8
	invokevirtual	Method scala/collection/immutable/RedBlack$RedTree.left:()Lscala/collection/immutable/RedBlack$Tree;
	astore	11
	aload	8
	invokevirtual	Method scala/collection/immutable/RedBlack$RedTree.right:()Lscala/collection/immutable/RedBlack$Tree;
	astore	12
	new	class scala/collection/immutable/RedBlack$RedTree
	dup
	aload_0
	invokevirtual	Method scala$collection$immutable$RedBlack$NonEmpty$$$outer:()Lscala/collection/immutable/RedBlack;
	aload	9
	aload	10
	new	class scala/collection/immutable/RedBlack$RedTree
	dup
	aload_0
	invokevirtual	Method scala$collection$immutable$RedBlack$NonEmpty$$$outer:()Lscala/collection/immutable/RedBlack;
	aload	13
	aload	14
	aload	15
	aload	11
	invokespecial	Method scala/collection/immutable/RedBlack$RedTree."<init>":(Lscala/collection/immutable/RedBlack;Ljava/lang/Object;Ljava/lang/Object;Lscala/collection/immutable/RedBlack$Tree;Lscala/collection/immutable/RedBlack$Tree;)V
	new	class scala/collection/immutable/RedBlack$RedTree
	dup
	aload_0
	invokevirtual	Method scala$collection$immutable$RedBlack$NonEmpty$$$outer:()Lscala/collection/immutable/RedBlack;
	aload	17
	aload	18
	aload	12
	aload	20
	invokespecial	Method scala/collection/immutable/RedBlack$RedTree."<init>":(Lscala/collection/immutable/RedBlack;Ljava/lang/Object;Ljava/lang/Object;Lscala/collection/immutable/RedBlack$Tree;Lscala/collection/immutable/RedBlack$Tree;)V
	invokespecial	Method scala/collection/immutable/RedBlack$RedTree."<init>":(Lscala/collection/immutable/RedBlack;Ljava/lang/Object;Ljava/lang/Object;Lscala/collection/immutable/RedBlack$Tree;Lscala/collection/immutable/RedBlack$Tree;)V
	goto	l4 // areturn
l10	new	class scala/collection/immutable/RedBlack$RedTree
	dup
	aload_0
	invokevirtual	Method scala$collection$immutable$RedBlack$NonEmpty$$$outer:()Lscala/collection/immutable/RedBlack;
	aload	13
	aload	14
	aload	15
	new	class scala/collection/immutable/RedBlack$RedTree
	dup
	aload_0
	invokevirtual	Method scala$collection$immutable$RedBlack$NonEmpty$$$outer:()Lscala/collection/immutable/RedBlack;
	aload	17
	aload	18
	aload	16
	aload	20
	invokespecial	Method scala/collection/immutable/RedBlack$RedTree."<init>":(Lscala/collection/immutable/RedBlack;Ljava/lang/Object;Ljava/lang/Object;Lscala/collection/immutable/RedBlack$Tree;Lscala/collection/immutable/RedBlack$Tree;)V
	invokespecial	Method scala/collection/immutable/RedBlack$RedTree."<init>":(Lscala/collection/immutable/RedBlack;Ljava/lang/Object;Ljava/lang/Object;Lscala/collection/immutable/RedBlack$Tree;Lscala/collection/immutable/RedBlack$Tree;)V
	goto	l4 // areturn
l9	new	class scala/collection/immutable/RedBlack$RedTree
	dup
	aload_0
	invokevirtual	Method scala$collection$immutable$RedBlack$NonEmpty$$$outer:()Lscala/collection/immutable/RedBlack;
	aload	17
	aload	18
	aload_0
	aload_1
	aload	19
	invokespecial	Method append$1:(Lscala/collection/immutable/RedBlack$Tree;Lscala/collection/immutable/RedBlack$Tree;)Lscala/collection/immutable/RedBlack$Tree;
	aload	20
	invokespecial	Method scala/collection/immutable/RedBlack$RedTree."<init>":(Lscala/collection/immutable/RedBlack;Ljava/lang/Object;Ljava/lang/Object;Lscala/collection/immutable/RedBlack$Tree;Lscala/collection/immutable/RedBlack$Tree;)V
	goto	l4 // areturn
l8	aload_2
	instanceof	class scala/collection/immutable/RedBlack$BlackTree
	ifeq	l11 // aload_1
	aload_2
	checkcast	class scala/collection/immutable/RedBlack$BlackTree
	astore	41
	aload	41
	invokevirtual	Method scala/collection/immutable/RedBlack$BlackTree.key:()Ljava/lang/Object;
	astore	32
	aload	41
	invokevirtual	Method scala/collection/immutable/RedBlack$BlackTree.value:()Ljava/lang/Object;
	astore	33
	aload	41
	invokevirtual	Method scala/collection/immutable/RedBlack$BlackTree.left:()Lscala/collection/immutable/RedBlack$Tree;
	astore	23
	aload	41
	invokevirtual	Method scala/collection/immutable/RedBlack$BlackTree.right:()Lscala/collection/immutable/RedBlack$Tree;
	astore	35
	aload_1
	instanceof	class scala/collection/immutable/RedBlack$BlackTree
	ifeq	l12 // aload_1
	aload_1
	checkcast	class scala/collection/immutable/RedBlack$BlackTree
	astore	21
	aload	21
	invokevirtual	Method scala/collection/immutable/RedBlack$BlackTree.key:()Ljava/lang/Object;
	astore	29
	aload	21
	invokevirtual	Method scala/collection/immutable/RedBlack$BlackTree.value:()Ljava/lang/Object;
	astore	30
	aload	21
	invokevirtual	Method scala/collection/immutable/RedBlack$BlackTree.left:()Lscala/collection/immutable/RedBlack$Tree;
	astore	31
	aload	21
	invokevirtual	Method scala/collection/immutable/RedBlack$BlackTree.right:()Lscala/collection/immutable/RedBlack$Tree;
	astore	22
	aload_0
	aload	22
	aload	23
	invokespecial	Method append$1:(Lscala/collection/immutable/RedBlack$Tree;Lscala/collection/immutable/RedBlack$Tree;)Lscala/collection/immutable/RedBlack$Tree;
	astore	34
	aload	34
	instanceof	class scala/collection/immutable/RedBlack$RedTree
	ifeq	l13 // aload_0
	aload	34
	checkcast	class scala/collection/immutable/RedBlack$RedTree
	astore	24
	aload	24
	invokevirtual	Method scala/collection/immutable/RedBlack$RedTree.key:()Ljava/lang/Object;
	astore	25
	aload	24
	invokevirtual	Method scala/collection/immutable/RedBlack$RedTree.value:()Ljava/lang/Object;
	astore	26
	aload	24
	invokevirtual	Method scala/collection/immutable/RedBlack$RedTree.left:()Lscala/collection/immutable/RedBlack$Tree;
	astore	27
	aload	24
	invokevirtual	Method scala/collection/immutable/RedBlack$RedTree.right:()Lscala/collection/immutable/RedBlack$Tree;
	astore	28
	new	class scala/collection/immutable/RedBlack$RedTree
	dup
	aload_0
	invokevirtual	Method scala$collection$immutable$RedBlack$NonEmpty$$$outer:()Lscala/collection/immutable/RedBlack;
	aload	25
	aload	26
	new	class scala/collection/immutable/RedBlack$BlackTree
	dup
	aload_0
	invokevirtual	Method scala$collection$immutable$RedBlack$NonEmpty$$$outer:()Lscala/collection/immutable/RedBlack;
	aload	29
	aload	30
	aload	31
	aload	27
	invokespecial	Method scala/collection/immutable/RedBlack$BlackTree."<init>":(Lscala/collection/immutable/RedBlack;Ljava/lang/Object;Ljava/lang/Object;Lscala/collection/immutable/RedBlack$Tree;Lscala/collection/immutable/RedBlack$Tree;)V
	new	class scala/collection/immutable/RedBlack$BlackTree
	dup
	aload_0
	invokevirtual	Method scala$collection$immutable$RedBlack$NonEmpty$$$outer:()Lscala/collection/immutable/RedBlack;
	aload	32
	aload	33
	aload	28
	aload	35
	invokespecial	Method scala/collection/immutable/RedBlack$BlackTree."<init>":(Lscala/collection/immutable/RedBlack;Ljava/lang/Object;Ljava/lang/Object;Lscala/collection/immutable/RedBlack$Tree;Lscala/collection/immutable/RedBlack$Tree;)V
	invokespecial	Method scala/collection/immutable/RedBlack$RedTree."<init>":(Lscala/collection/immutable/RedBlack;Ljava/lang/Object;Ljava/lang/Object;Lscala/collection/immutable/RedBlack$Tree;Lscala/collection/immutable/RedBlack$Tree;)V
	goto	l4 // areturn
l13	aload_0
	aload	29
	aload	30
	aload	31
	new	class scala/collection/immutable/RedBlack$BlackTree
	dup
	aload_0
	invokevirtual	Method scala$collection$immutable$RedBlack$NonEmpty$$$outer:()Lscala/collection/immutable/RedBlack;
	aload	32
	aload	33
	aload	34
	aload	35
	invokespecial	Method scala/collection/immutable/RedBlack$BlackTree."<init>":(Lscala/collection/immutable/RedBlack;Ljava/lang/Object;Ljava/lang/Object;Lscala/collection/immutable/RedBlack$Tree;Lscala/collection/immutable/RedBlack$Tree;)V
	invokespecial	Method balLeft$1:(Ljava/lang/Object;Ljava/lang/Object;Lscala/collection/immutable/RedBlack$Tree;Lscala/collection/immutable/RedBlack$Tree;)Lscala/collection/immutable/RedBlack$NonEmpty;
	goto	l4 // areturn
l12	aload_1
	instanceof	class scala/collection/immutable/RedBlack$RedTree
	ifeq	l14 // new
	aload_1
	checkcast	class scala/collection/immutable/RedBlack$RedTree
	astore	36
	aload	36
	invokevirtual	Method scala/collection/immutable/RedBlack$RedTree.key:()Ljava/lang/Object;
	astore	37
	aload	36
	invokevirtual	Method scala/collection/immutable/RedBlack$RedTree.value:()Ljava/lang/Object;
	astore	38
	aload	36
	invokevirtual	Method scala/collection/immutable/RedBlack$RedTree.left:()Lscala/collection/immutable/RedBlack$Tree;
	astore	39
	aload	36
	invokevirtual	Method scala/collection/immutable/RedBlack$RedTree.right:()Lscala/collection/immutable/RedBlack$Tree;
	astore	40
	aload	37
	astore	43
	aload	38
	astore	44
	aload	39
	astore	45
	aload	40
	astore	46
	aload	41
	astore	47
	goto	l15 // new
l14	new	class scala/MatchError
	dup
	new	class scala/Tuple2
	dup
	aload_1
	aload_2
	invokespecial	Method scala/Tuple2."<init>":(Ljava/lang/Object;Ljava/lang/Object;)V
	invokevirtual	Method scala/Tuple2.toString:()Ljava/lang/String;
	invokespecial	Method scala/MatchError."<init>":(Ljava/lang/String;)V
	athrow
l11	aload_1
	instanceof	class scala/collection/immutable/RedBlack$RedTree
	ifeq	l16 // new
	aload_1
	checkcast	class scala/collection/immutable/RedBlack$RedTree
	astore	42
	aload	42
	invokevirtual	Method scala/collection/immutable/RedBlack$RedTree.key:()Ljava/lang/Object;
	aload	42
	invokevirtual	Method scala/collection/immutable/RedBlack$RedTree.value:()Ljava/lang/Object;
	aload	42
	invokevirtual	Method scala/collection/immutable/RedBlack$RedTree.left:()Lscala/collection/immutable/RedBlack$Tree;
	aload	42
	invokevirtual	Method scala/collection/immutable/RedBlack$RedTree.right:()Lscala/collection/immutable/RedBlack$Tree;
	aload_2
	astore	47
	astore	46
	astore	45
	astore	44
	astore	43
l15	new	class scala/collection/immutable/RedBlack$RedTree
	dup
	aload_0
	invokevirtual	Method scala$collection$immutable$RedBlack$NonEmpty$$$outer:()Lscala/collection/immutable/RedBlack;
	aload	43
	aload	44
	aload	45
	aload_0
	aload	46
	aload	47
	invokespecial	Method append$1:(Lscala/collection/immutable/RedBlack$Tree;Lscala/collection/immutable/RedBlack$Tree;)Lscala/collection/immutable/RedBlack$Tree;
	invokespecial	Method scala/collection/immutable/RedBlack$RedTree."<init>":(Lscala/collection/immutable/RedBlack;Ljava/lang/Object;Ljava/lang/Object;Lscala/collection/immutable/RedBlack$Tree;Lscala/collection/immutable/RedBlack$Tree;)V
l4	areturn
l16	new	class scala/MatchError
	dup
	new	class scala/Tuple2
	dup
	aload_1
	aload_2
	invokespecial	Method scala/Tuple2."<init>":(Ljava/lang/Object;Ljava/lang/Object;)V
	invokevirtual	Method scala/Tuple2.toString:()Ljava/lang/String;
	invokespecial	Method scala/MatchError."<init>":(Ljava/lang/String;)V
	athrow
  Labels:
   	l1 = 21 // aload_3
   	l2 = 28 // aload_2
   	l3 = 32 // aload_2
   	l5 = 55 // aload
   	l6 = 63 // aload_1
   	l7 = 67 // aload_2
   	l10 = 258 // new
   	l9 = 297 // new
   	l8 = 324 // aload_2
   	l13 = 515 // aload_0
   	l12 = 547 // aload_1
   	l14 = 611 // new
   	l11 = 631 // aload_1
   	l15 = 675 // new
   	l4 = 700 // areturn
   	l16 = 701 // new
  LocalVariableTable: 
   Start  Length  Slot  Name   Signature
   0      721      0    this       Lscala/collection/immutable/RedBlack$NonEmpty;
   0      721      1    tl       Lscala/collection/immutable/RedBlack$Tree;
   0      721      2    tr       Lscala/collection/immutable/RedBlack$Tree;
   80      244      5    temp144       Lscala/collection/immutable/RedBlack$RedTree;
   121      176      6    temp149       Lscala/collection/immutable/RedBlack$RedTree;
   149      148      7    temp153       Lscala/collection/immutable/RedBlack$Tree;
   174      81      8    temp133       Lscala/collection/immutable/RedBlack$RedTree;
   181      74      9    temp134       Ljava/lang/Object;
   188      67      10    temp135       Ljava/lang/Object;
   195      60      11    temp136       Lscala/collection/immutable/RedBlack$Tree;
   202      53      12    temp137       Lscala/collection/immutable/RedBlack$Tree;
   128      169      13    temp150       Ljava/lang/Object;
   135      162      14    temp151       Ljava/lang/Object;
   142      155      15    temp152       Lscala/collection/immutable/RedBlack$Tree;
   159      138      16    temp132       Lscala/collection/immutable/RedBlack$Tree;
   87      237      17    temp145       Ljava/lang/Object;
   94      230      18    temp146       Ljava/lang/Object;
   101      223      19    temp147       Lscala/collection/immutable/RedBlack$Tree;
   108      216      20    temp148       Lscala/collection/immutable/RedBlack$Tree;
   378      169      21    temp159       Lscala/collection/immutable/RedBlack$BlackTree;
   406      141      22    temp163       Lscala/collection/immutable/RedBlack$Tree;
   358      273      23    temp157       Lscala/collection/immutable/RedBlack$Tree;
   675      25      23    temp157       Lscala/collection/immutable/RedBlack$Tree;
   431      81      24    temp139       Lscala/collection/immutable/RedBlack$RedTree;
   438      74      25    temp140       Ljava/lang/Object;
   445      67      26    temp141       Ljava/lang/Object;
   452      60      27    temp142       Lscala/collection/immutable/RedBlack$Tree;
   459      53      28    temp143       Lscala/collection/immutable/RedBlack$Tree;
   385      162      29    temp160       Ljava/lang/Object;
   392      155      30    temp161       Ljava/lang/Object;
   399      148      31    temp162       Lscala/collection/immutable/RedBlack$Tree;
   344      287      32    temp155       Ljava/lang/Object;
   675      25      32    temp155       Ljava/lang/Object;
   351      280      33    temp156       Ljava/lang/Object;
   675      25      33    temp156       Ljava/lang/Object;
   416      131      34    temp138       Lscala/collection/immutable/RedBlack$Tree;
   365      266      35    temp158       Lscala/collection/immutable/RedBlack$Tree;
   675      25      35    temp158       Lscala/collection/immutable/RedBlack$Tree;
   560      51      36    temp164       Lscala/collection/immutable/RedBlack$RedTree;
   675      25      36    temp164       Lscala/collection/immutable/RedBlack$RedTree;
   567      44      37    temp165       Ljava/lang/Object;
   675      25      37    temp165       Ljava/lang/Object;
   574      37      38    temp166       Ljava/lang/Object;
   675      25      38    temp166       Ljava/lang/Object;
   581      30      39    temp167       Lscala/collection/immutable/RedBlack$Tree;
   675      25      39    temp167       Lscala/collection/immutable/RedBlack$Tree;
   588      23      40    temp168       Lscala/collection/immutable/RedBlack$Tree;
   675      25      40    temp168       Lscala/collection/immutable/RedBlack$Tree;
   337      294      41    temp154       Lscala/collection/immutable/RedBlack$BlackTree;
   675      25      41    temp154       Lscala/collection/immutable/RedBlack$BlackTree;
   644      31      42    temp169       Lscala/collection/immutable/RedBlack$RedTree;
   592      19      43    x       Ljava/lang/Object;
   675      25      43    x       Ljava/lang/Object;
   596      15      44    xv       Ljava/lang/Object;
   675      25      44    xv       Ljava/lang/Object;
   600      11      45    a       Lscala/collection/immutable/RedBlack$Tree;
   675      25      45    a       Lscala/collection/immutable/RedBlack$Tree;
   604      7      46    b       Lscala/collection/immutable/RedBlack$Tree;
   675      25      46    b       Lscala/collection/immutable/RedBlack$Tree;
   608      3      47    c       Lscala/collection/immutable/RedBlack$Tree;
   675      25      47    c       Lscala/collection/immutable/RedBlack$Tree;


private final boolean gd1$1(java.lang.Object);
  Signature: (Ljava/lang/Object;)Z
  Code:
   Stack=3, Locals=2, Args_size=2
	aload_0
	invokevirtual	Method scala$collection$immutable$RedBlack$NonEmpty$$$outer:()Lscala/collection/immutable/RedBlack;
	aload_1
	aload_0
	invokevirtual	Method key:()Ljava/lang/Object;
	invokevirtual	Method scala/collection/immutable/RedBlack.isSmaller:(Ljava/lang/Object;Ljava/lang/Object;)Z
	ireturn
  Labels:

private final boolean gd2$1(java.lang.Object);
  Signature: (Ljava/lang/Object;)Z
  Code:
   Stack=3, Locals=2, Args_size=2
	aload_0
	invokevirtual	Method scala$collection$immutable$RedBlack$NonEmpty$$$outer:()Lscala/collection/immutable/RedBlack;
	aload_0
	invokevirtual	Method key:()Ljava/lang/Object;
	aload_1
	invokevirtual	Method scala/collection/immutable/RedBlack.isSmaller:(Ljava/lang/Object;Ljava/lang/Object;)Z
	ireturn
  Labels:

public scala.collection.immutable.RedBlack$NonEmpty(scala.collection.immutable.RedBlack);
  Signature: (Lscala/collection/immutable/RedBlack;)V
  Code:
   Stack=2, Locals=2, Args_size=2
	aload_0
	aload_1
	invokespecial	Method scala/collection/immutable/RedBlack$Tree."<init>":(Lscala/collection/immutable/RedBlack;)V
	return
  Labels:
  LocalVariableTable: 
   Start  Length  Slot  Name   Signature
   0      6      0    this       Lscala/collection/immutable/RedBlack$NonEmpty;
   0      6      1    $outer       Lscala/collection/immutable/RedBlack;

  Signature: length = 0x2
   01 FFFFFFD0 

}

