Compiled from "RedBlack.scala"
public final class scala.collection.immutable.RedBlack$NonEmpty$$anonfun$iterator$1 extends java.lang.Object implements scala.Function0,scala.ScalaObject,java.io.Serializable
  SourceFile: "RedBlack.scala"
  Scala: length = 0x
   
  InnerClass: 
   public abstract #74= #51 of #73; //NonEmpty=class scala/collection/immutable/RedBlack$NonEmpty of class scala/collection/immutable/RedBlack
   public final #75= #9 of #51; //$anonfun$iterator$1=class scala/collection/immutable/RedBlack$NonEmpty$$anonfun$iterator$1 of class scala/collection/immutable/RedBlack$NonEmpty
  minor version: 0
  major version: 49
  Constant pool:
const #1 = Asciz	SourceFile;
const #2 = Asciz	RedBlack.scala;
const #3 = Asciz	<clinit>;
const #4 = Asciz	()V;
const #5 = Asciz	Code;
const #6 = Asciz	serialVersionUID;
const #7 = Asciz	J;
const #8 = Asciz	scala/collection/immutable/RedBlack$NonEmpty$$anonfun$iterator$1;
const #9 = class	#8;	//  scala/collection/immutable/RedBlack$NonEmpty$$anonfun$iterator$1
const #10 = NameAndType	#6:#7;//  serialVersionUID:J
const #11 = Field	#9.#10;	//  scala/collection/immutable/RedBlack$NonEmpty$$anonfun$iterator$1.serialVersionUID:J
const #12 = Asciz	$outer;
const #13 = Asciz	Lscala/collection/immutable/RedBlack$NonEmpty;;
const #14 = Asciz	<init>;
const #15 = Asciz	(Lscala/collection/immutable/RedBlack$NonEmpty;)V;
const #16 = Asciz	LineNumberTable;
const #17 = Asciz	java/lang/NullPointerException;
const #18 = class	#17;	//  java/lang/NullPointerException
const #19 = NameAndType	#14:#4;//  "<init>":()V
const #20 = Method	#18.#19;	//  java/lang/NullPointerException."<init>":()V
const #21 = NameAndType	#12:#13;//  $outer:Lscala/collection/immutable/RedBlack$NonEmpty;
const #22 = Field	#9.#21;	//  scala/collection/immutable/RedBlack$NonEmpty$$anonfun$iterator$1.$outer:Lscala/collection/immutable/RedBlack$NonEmpty;
const #23 = Asciz	java/lang/Object;
const #24 = class	#23;	//  java/lang/Object
const #25 = Method	#24.#19;	//  java/lang/Object."<init>":()V
const #26 = Asciz	scala/Function0$class;
const #27 = class	#26;	//  scala/Function0$class
const #28 = Asciz	$init$;
const #29 = Asciz	(Lscala/Function0;)V;
const #30 = NameAndType	#28:#29;//  $init$:(Lscala/Function0;)V
const #31 = Method	#27.#30;	//  scala/Function0$class.$init$:(Lscala/Function0;)V
const #32 = Asciz	this;
const #33 = Asciz	Lscala/collection/immutable/RedBlack$NonEmpty$$anonfun$iterator$1;;
const #34 = Asciz	LocalVariableTable;
const #35 = Asciz	(Lscala/collection/immutable/RedBlack<TA;>.NonEmpty<TB;>;)V;
const #36 = Asciz	Signature;
const #37 = Asciz	apply;
const #38 = Asciz	()Ljava/lang/Object;;
const #39 = Asciz	scala/collection/Iterator$;
const #40 = class	#39;	//  scala/collection/Iterator$
const #41 = Asciz	MODULE$;
const #42 = Asciz	Lscala/collection/Iterator$;;
const #43 = NameAndType	#41:#42;//  MODULE$:Lscala/collection/Iterator$;
const #44 = Field	#40.#43;	//  scala/collection/Iterator$.MODULE$:Lscala/collection/Iterator$;
const #45 = Asciz	scala/Predef$Pair$;
const #46 = class	#45;	//  scala/Predef$Pair$
const #47 = Asciz	Lscala/Predef$Pair$;;
const #48 = NameAndType	#41:#47;//  MODULE$:Lscala/Predef$Pair$;
const #49 = Field	#46.#48;	//  scala/Predef$Pair$.MODULE$:Lscala/Predef$Pair$;
const #50 = Asciz	scala/collection/immutable/RedBlack$NonEmpty;
const #51 = class	#50;	//  scala/collection/immutable/RedBlack$NonEmpty
const #52 = Asciz	key;
const #53 = NameAndType	#52:#38;//  key:()Ljava/lang/Object;
const #54 = Method	#51.#53;	//  scala/collection/immutable/RedBlack$NonEmpty.key:()Ljava/lang/Object;
const #55 = Asciz	value;
const #56 = NameAndType	#55:#38;//  value:()Ljava/lang/Object;
const #57 = Method	#51.#56;	//  scala/collection/immutable/RedBlack$NonEmpty.value:()Ljava/lang/Object;
const #58 = Asciz	(Ljava/lang/Object;Ljava/lang/Object;)Lscala/Tuple2;;
const #59 = NameAndType	#37:#58;//  apply:(Ljava/lang/Object;Ljava/lang/Object;)Lscala/Tuple2;
const #60 = Method	#46.#59;	//  scala/Predef$Pair$.apply:(Ljava/lang/Object;Ljava/lang/Object;)Lscala/Tuple2;
const #61 = Asciz	single;
const #62 = Asciz	(Ljava/lang/Object;)Ljava/lang/Object;;
const #63 = NameAndType	#61:#62;//  single:(Ljava/lang/Object;)Ljava/lang/Object;
const #64 = Method	#40.#63;	//  scala/collection/Iterator$.single:(Ljava/lang/Object;)Ljava/lang/Object;
const #65 = Asciz	toString;
const #66 = Asciz	()Ljava/lang/String;;
const #67 = Asciz	(Lscala/Function0;)Ljava/lang/String;;
const #68 = NameAndType	#65:#67;//  toString:(Lscala/Function0;)Ljava/lang/String;
const #69 = Method	#27.#68;	//  scala/Function0$class.toString:(Lscala/Function0;)Ljava/lang/String;
const #70 = Asciz	Scala;
const #71 = Asciz	InnerClasses;
const #72 = Asciz	scala/collection/immutable/RedBlack;
const #73 = class	#72;	//  scala/collection/immutable/RedBlack
const #74 = Asciz	NonEmpty;
const #75 = Asciz	$anonfun$iterator$1;
const #76 = Asciz	scala/Function0;
const #77 = class	#76;	//  scala/Function0
const #78 = Asciz	scala/ScalaObject;
const #79 = class	#78;	//  scala/ScalaObject
const #80 = Asciz	java/io/Serializable;
const #81 = class	#80;	//  java/io/Serializable

{
public static final long serialVersionUID;

public static {};
  Code:
   Stack=2, Locals=0, Args_size=0
   0:	lconst_0
   1:	putstatic	#11; //Field serialVersionUID:J
   4:	return

public scala.collection.immutable.RedBlack$NonEmpty$$anonfun$iterator$1(scala.collection.immutable.RedBlack$NonEmpty);
  Code:
   Stack=2, Locals=2, Args_size=2
   0:	aload_1
   1:	ifnonnull	12
   4:	new	#18; //class java/lang/NullPointerException
   7:	dup
   8:	invokespecial	#20; //Method java/lang/NullPointerException."<init>":()V
   11:	athrow
   12:	aload_0
   13:	aload_1
   14:	putfield	#22; //Field $outer:Lscala/collection/immutable/RedBlack$NonEmpty;
   17:	aload_0
   18:	invokespecial	#25; //Method java/lang/Object."<init>":()V
   21:	aload_0
   22:	invokestatic	#31; //Method scala/Function0$class.$init$:(Lscala/Function0;)V
   25:	return
  LineNumberTable: 
   line 99: 0

  LocalVariableTable: 
   Start  Length  Slot  Name   Signature
   0      26      0    this       Lscala/collection/immutable/RedBlack$NonEmpty$$anonfun$iterator$1;
   0      26      1    $outer       Lscala/collection/immutable/RedBlack$NonEmpty;

  Signature: length = 0x2
   00 23 

public final java.lang.Object apply();
  Code:
   Stack=4, Locals=2, Args_size=1
   0:	aload_0
   1:	getfield	#22; //Field $outer:Lscala/collection/immutable/RedBlack$NonEmpty;
   4:	astore_1
   5:	getstatic	#44; //Field scala/collection/Iterator$.MODULE$:Lscala/collection/Iterator$;
   8:	getstatic	#49; //Field scala/Predef$Pair$.MODULE$:Lscala/Predef$Pair$;
   11:	aload_0
   12:	getfield	#22; //Field $outer:Lscala/collection/immutable/RedBlack$NonEmpty;
   15:	invokevirtual	#54; //Method scala/collection/immutable/RedBlack$NonEmpty.key:()Ljava/lang/Object;
   18:	aload_0
   19:	getfield	#22; //Field $outer:Lscala/collection/immutable/RedBlack$NonEmpty;
   22:	invokevirtual	#57; //Method scala/collection/immutable/RedBlack$NonEmpty.value:()Ljava/lang/Object;
   25:	invokevirtual	#60; //Method scala/Predef$Pair$.apply:(Ljava/lang/Object;Ljava/lang/Object;)Lscala/Tuple2;
   28:	invokevirtual	#64; //Method scala/collection/Iterator$.single:(Ljava/lang/Object;)Ljava/lang/Object;
   31:	areturn
  LineNumberTable: 
   line 99: 0

  LocalVariableTable: 
   Start  Length  Slot  Name   Signature
   0      32      0    this       Lscala/collection/immutable/RedBlack$NonEmpty$$anonfun$iterator$1;


public java.lang.String toString();
  Code:
   Stack=1, Locals=1, Args_size=1
   0:	aload_0
   1:	invokestatic	#69; //Method scala/Function0$class.toString:(Lscala/Function0;)Ljava/lang/String;
   4:	areturn
  LineNumberTable: 
   line 99: 0


}

