Compiled from "Sequence.scala"
public final class scala.collection.immutable.Sequence$ extends scala.collection.generic.SequenceFactory implements scala.ScalaObject
  SourceFile: "Sequence.scala"
  Scala: length = 0x
   
  Signature: length = 0x2
   00 2F 
  InnerClass: 
   public #51= #42 of #50; //VirtualBuilderFactory=class scala/collection/generic/TraversableFactory$VirtualBuilderFactory of class scala/collection/generic/TraversableFactory
  minor version: 0
  major version: 49
  Constant pool:
const #1 = Asciz	SourceFile;
const #2 = Asciz	Sequence.scala;
const #3 = Asciz	Scala;
const #4 = Asciz	MODULE$;
const #5 = Asciz	Lscala/collection/immutable/Sequence$;;
const #6 = Asciz	<clinit>;
const #7 = Asciz	()V;
const #8 = Asciz	Code;
const #9 = Asciz	scala/collection/immutable/Sequence$;
const #10 = class	#9;	//  scala/collection/immutable/Sequence$
const #11 = Asciz	<init>;
const #12 = NameAndType	#11:#7;//  "<init>":()V
const #13 = Method	#10.#12;	//  scala/collection/immutable/Sequence$."<init>":()V
const #14 = Asciz	scala$collection$immutable$Sequence$$hashSeed;
const #15 = Asciz	I;
const #16 = Asciz	LineNumberTable;
const #17 = Asciz	scala/collection/generic/SequenceFactory;
const #18 = class	#17;	//  scala/collection/generic/SequenceFactory
const #19 = Method	#18.#12;	//  scala/collection/generic/SequenceFactory."<init>":()V
const #20 = NameAndType	#4:#5;//  MODULE$:Lscala/collection/immutable/Sequence$;
const #21 = Field	#10.#20;	//  scala/collection/immutable/Sequence$.MODULE$:Lscala/collection/immutable/Sequence$;
const #22 = Asciz	Sequence;
const #23 = String	#22;	//  Sequence
const #24 = Asciz	java/lang/String;
const #25 = class	#24;	//  java/lang/String
const #26 = Asciz	hashCode;
const #27 = Asciz	()I;
const #28 = NameAndType	#26:#27;//  hashCode:()I
const #29 = Method	#25.#28;	//  java/lang/String.hashCode:()I
const #30 = NameAndType	#14:#15;//  scala$collection$immutable$Sequence$$hashSeed:I
const #31 = Field	#10.#30;	//  scala/collection/immutable/Sequence$.scala$collection$immutable$Sequence$$hashSeed:I
const #32 = Asciz	newBuilder;
const #33 = Asciz	()Lscala/collection/generic/Builder;;
const #34 = Asciz	scala/collection/mutable/ListBuffer;
const #35 = class	#34;	//  scala/collection/mutable/ListBuffer
const #36 = Method	#35.#12;	//  scala/collection/mutable/ListBuffer."<init>":()V
const #37 = Asciz	<A:Ljava/lang/Object;>()Lscala/collection/generic/Builder<TA;Lscala/collection/immutable/Sequence<TA;>;>;;
const #38 = Asciz	Signature;
const #39 = Asciz	builderFactory;
const #40 = Asciz	()Lscala/collection/generic/BuilderFactory;;
const #41 = Asciz	scala/collection/generic/TraversableFactory$VirtualBuilderFactory;
const #42 = class	#41;	//  scala/collection/generic/TraversableFactory$VirtualBuilderFactory
const #43 = Asciz	(Lscala/collection/generic/TraversableFactory;)V;
const #44 = NameAndType	#11:#43;//  "<init>":(Lscala/collection/generic/TraversableFactory;)V
const #45 = Method	#42.#44;	//  scala/collection/generic/TraversableFactory$VirtualBuilderFactory."<init>":(Lscala/collection/generic/TraversableFactory;)V
const #46 = Asciz	<A:Ljava/lang/Object;>()Lscala/collection/generic/BuilderFactory<TA;Lscala/collection/immutable/Sequence<TA;>;Lscala/collection/immutable/Sequence<*>;>;;
const #47 = Asciz	Lscala/collection/generic/SequenceFactory<Lscala/collection/immutable/Sequence<TA;>;>;Lscala/ScalaObject;;
const #48 = Asciz	InnerClasses;
const #49 = Asciz	scala/collection/generic/TraversableFactory;
const #50 = class	#49;	//  scala/collection/generic/TraversableFactory
const #51 = Asciz	VirtualBuilderFactory;
const #52 = Asciz	scala/ScalaObject;
const #53 = class	#52;	//  scala/ScalaObject

{
public static final scala.collection.immutable.Sequence$ MODULE$;

public static {};
  Code:
   Stack=1, Locals=0, Args_size=0
   0:	new	#10; //class scala/collection/immutable/Sequence$
   3:	invokespecial	#13; //Method "<init>":()V
   6:	return

public scala.collection.generic.Builder newBuilder();
  Code:
   Stack=2, Locals=1, Args_size=1
   0:	new	#35; //class scala/collection/mutable/ListBuffer
   3:	dup
   4:	invokespecial	#36; //Method scala/collection/mutable/ListBuffer."<init>":()V
   7:	areturn
  LineNumberTable: 
   line 28: 0

  Signature: length = 0x2
   00 25 

public scala.collection.generic.BuilderFactory builderFactory();
  Code:
   Stack=3, Locals=1, Args_size=1
   0:	new	#42; //class scala/collection/generic/TraversableFactory$VirtualBuilderFactory
   3:	dup
   4:	aload_0
   5:	invokespecial	#45; //Method scala/collection/generic/TraversableFactory$VirtualBuilderFactory."<init>":(Lscala/collection/generic/TraversableFactory;)V
   8:	areturn
  LineNumberTable: 
   line 27: 0

  Signature: length = 0x2
   00 2E 

public final int scala$collection$immutable$Sequence$$hashSeed();
  Code:
   Stack=1, Locals=1, Args_size=1
   0:	aload_0
   1:	getfield	#31; //Field scala$collection$immutable$Sequence$$hashSeed:I
   4:	ireturn
  LineNumberTable: 
   line 26: 0


}

