Compiled from "Set.scala"
public final class scala.collection.immutable.Set$ extends scala.collection.generic.SetFactory implements scala.ScalaObject
  SourceFile: "Set.scala"
  Scala: length = 0x
   
  Signature: length = 0x2
   00 30 
  InnerClass: 
   public Set4=class scala/collection/immutable/Set$Set4 of class scala/collection/immutable/Set
   public Set3=class scala/collection/immutable/Set$Set3 of class scala/collection/immutable/Set
   public Set2=class scala/collection/immutable/Set$Set2 of class scala/collection/immutable/Set
   public Set1=class scala/collection/immutable/Set$Set1 of class scala/collection/immutable/Set
   public EmptySet=class scala/collection/immutable/Set$EmptySet of class scala/collection/immutable/Set
  minor version: 0
  major version: 49
  Constant pool:
Asciz	SourceFile;
Asciz	Set.scala;
Asciz	Scala;
Asciz	MODULE$;
Asciz	Lscala/collection/immutable/Set$;;
Asciz	<clinit>;
Asciz	()V;
Asciz	Code;
Asciz	scala/collection/immutable/Set$;
class	scala/collection/immutable/Set$
Asciz	<init>;
NameAndType	"<init>":()V
Method	scala/collection/immutable/Set$."<init>":()V
Asciz	hashSeed;
Asciz	I;
Asciz	canBuildFrom;
Asciz	()Lscala/collection/generic/CanBuildFrom;;
Asciz	LineNumberTable;
Asciz	setCanBuildFrom;
NameAndType	setCanBuildFrom:()Lscala/collection/generic/CanBuildFrom;
Method	scala/collection/immutable/Set$.setCanBuildFrom:()Lscala/collection/generic/CanBuildFrom;
Asciz	<A:Ljava/lang/Object;>()Lscala/collection/generic/CanBuildFrom<Lscala/collection/immutable/Set<*>;TA;Lscala/collection/immutable/Set<TA;>;>;;
Asciz	Signature;
Asciz	empty;
Asciz	()Lscala/collection/immutable/Set;;
Asciz	scala/collection/immutable/Set$EmptySet;
class	scala/collection/immutable/Set$EmptySet
Method	scala/collection/immutable/Set$EmptySet."<init>":()V
Asciz	<A:Ljava/lang/Object;>()Lscala/collection/immutable/Set<TA;>;;
Asciz	()I;
NameAndType	hashSeed:I
Field	scala/collection/immutable/Set$.hashSeed:I
Asciz	()Lscala/collection/Traversable;;
NameAndType	empty:()Lscala/collection/immutable/Set;
Method	scala/collection/immutable/Set$.empty:()Lscala/collection/immutable/Set;
Asciz	scala/collection/generic/SetFactory;
class	scala/collection/generic/SetFactory
Method	scala/collection/generic/SetFactory."<init>":()V
NameAndType	MODULE$:Lscala/collection/immutable/Set$;
Field	scala/collection/immutable/Set$.MODULE$:Lscala/collection/immutable/Set$;
Asciz	Set;
String	Set
Asciz	java/lang/String;
class	java/lang/String
Asciz	hashCode;
NameAndType	hashCode:()I
Method	java/lang/String.hashCode:()I
Asciz	Lscala/collection/generic/SetFactory<Lscala/collection/immutable/Set;>;Lscala/ScalaObject;;
Asciz	InnerClasses;
Asciz	scala/collection/immutable/Set$Set4;
class	scala/collection/immutable/Set$Set4
Asciz	scala/collection/immutable/Set;
class	scala/collection/immutable/Set
Asciz	Set4;
Asciz	scala/collection/immutable/Set$Set3;
class	scala/collection/immutable/Set$Set3
Asciz	Set3;
Asciz	scala/collection/immutable/Set$Set2;
class	scala/collection/immutable/Set$Set2
Asciz	Set2;
Asciz	scala/collection/immutable/Set$Set1;
class	scala/collection/immutable/Set$Set1
Asciz	Set1;
Asciz	EmptySet;
Asciz	scala/ScalaObject;
class	scala/ScalaObject

{
public static final scala.collection.immutable.Set$ MODULE$;
  Signature: Lscala/collection/immutable/Set$;

private final int hashSeed;
  Signature: I

public static {};
  Signature: ()V
  Code:
   Stack=1, Locals=0, Args_size=0
	new	class scala/collection/immutable/Set$
	invokespecial	Method "<init>":()V
	return
  Labels:

public scala.collection.generic.CanBuildFrom canBuildFrom();
  Signature: ()Lscala/collection/generic/CanBuildFrom;
  Code:
   Stack=1, Locals=1, Args_size=1
	aload_0
	invokevirtual	Method setCanBuildFrom:()Lscala/collection/generic/CanBuildFrom;
	areturn
  Labels:
  Signature: length = 0x2
   00 16 

public scala.collection.immutable.Set empty();
  Signature: ()Lscala/collection/immutable/Set;
  Code:
   Stack=2, Locals=1, Args_size=1
	new	class scala/collection/immutable/Set$EmptySet
	dup
	invokespecial	Method scala/collection/immutable/Set$EmptySet."<init>":()V
	areturn
  Labels:
  Signature: length = 0x2
   00 1D 

private int hashSeed();
  Signature: ()I
  Code:
   Stack=1, Locals=1, Args_size=1
	aload_0
	getfield	Field hashSeed:I
	ireturn
  Labels:

public scala.collection.Traversable empty();
  Signature: ()Lscala/collection/Traversable;
  Code:
   Stack=1, Locals=1, Args_size=1
	aload_0
	invokevirtual	Method empty:()Lscala/collection/immutable/Set;
	areturn
  Labels:

private scala.collection.immutable.Set$();
  Signature: ()V
  Code:
   Stack=2, Locals=1, Args_size=1
	aload_0
	invokespecial	Method scala/collection/generic/SetFactory."<init>":()V
	aload_0
	putstatic	Field MODULE$:Lscala/collection/immutable/Set$;
	aload_0
	ldc	String Set
	invokevirtual	Method java/lang/String.hashCode:()I
	putfield	Field hashSeed:I
	return
  Labels:

}

