Compiled from "Set.scala"
public class scala.collection.immutable.Set$Set3 extends java.lang.Object implements java.io.Serializable,scala.collection.immutable.Set
  InnerClass: 
   public Set2=class scala/collection/immutable/Set$Set2 of class scala/collection/immutable/Set
   public Set4=class scala/collection/immutable/Set$Set4 of class scala/collection/immutable/Set
   public Set3=class scala/collection/immutable/Set$Set3 of class scala/collection/immutable/Set
  Scala: length = 0x
   
  Signature: length = 0x2
   01 13 
  SourceFile: "Set.scala"
  minor version: 0
  major version: 49
  Constant pool:
class	java/io/Serializable
class	java/lang/Character
class	java/lang/Number
class	java/lang/Object
class	scala/Function1
class	scala/Function1$class
class	scala/Predef$
class	scala/collection/Iterable$class
class	scala/collection/IterableLike$class
class	scala/collection/Iterator$
class	scala/collection/Set$class
class	scala/collection/SetLike
class	scala/collection/SetLike$class
class	scala/collection/Traversable$class
class	scala/collection/TraversableLike
class	scala/collection/TraversableLike$class
class	scala/collection/TraversableOnce$class
class	scala/collection/generic/Addable
class	scala/collection/generic/Addable$class
class	scala/collection/generic/GenericSetTemplate$class
class	scala/collection/generic/GenericTraversableTemplate$class
class	scala/collection/generic/Subtractable$class
class	scala/collection/immutable/Iterable$class
class	scala/collection/immutable/Set
class	scala/collection/immutable/Set$Set2
class	scala/collection/immutable/Set$Set3
class	scala/collection/immutable/Set$Set4
class	scala/collection/immutable/Set$class
class	scala/collection/immutable/Traversable$class
class	scala/runtime/BoxesRunTime
long	-3590273538119220064l;
Field	scala/Predef$.MODULE$:Lscala/Predef$;
Field	scala/collection/Iterator$.MODULE$:Lscala/collection/Iterator$;
Field	scala/collection/immutable/Set$Set3.elem1:Ljava/lang/Object;
Field	scala/collection/immutable/Set$Set3.elem2:Ljava/lang/Object;
Field	scala/collection/immutable/Set$Set3.elem3:Ljava/lang/Object;
Field	scala/collection/immutable/Set$Set3.serialVersionUID:J
Method	java/lang/Object."<init>":()V
Method	java/lang/Object.equals:(Ljava/lang/Object;)Z
Method	scala/Function1$class.$init$:(Lscala/Function1;)V
Method	scala/Predef$.genericWrapArray:(Ljava/lang/Object;)Lscala/collection/mutable/WrappedArray;
Method	scala/collection/Iterable$class.$init$:(Lscala/collection/Iterable;)V
Method	scala/collection/IterableLike$class.$init$:(Lscala/collection/IterableLike;)V
Method	scala/collection/IterableLike$class.canEqual:(Lscala/collection/IterableLike;Ljava/lang/Object;)Z
Method	scala/collection/IterableLike$class.copyToArray:(Lscala/collection/IterableLike;Ljava/lang/Object;II)V
Method	scala/collection/IterableLike$class.exists:(Lscala/collection/IterableLike;Lscala/Function1;)Z
Method	scala/collection/IterableLike$class.forall:(Lscala/collection/IterableLike;Lscala/Function1;)Z
Method	scala/collection/IterableLike$class.head:(Lscala/collection/IterableLike;)Ljava/lang/Object;
Method	scala/collection/IterableLike$class.sameElements:(Lscala/collection/IterableLike;Lscala/collection/Iterable;)Z
Method	scala/collection/IterableLike$class.toStream:(Lscala/collection/IterableLike;)Lscala/collection/immutable/Stream;
Method	scala/collection/IterableLike$class.zip:(Lscala/collection/IterableLike;Lscala/collection/Iterable;Lscala/collection/generic/CanBuildFrom;)Ljava/lang/Object;
Method	scala/collection/Iterator$.apply:(Lscala/collection/Seq;)Lscala/collection/Iterator;
Method	scala/collection/Set$class.$init$:(Lscala/collection/Set;)V
Method	scala/collection/SetLike$class.$init$:(Lscala/collection/SetLike;)V
Method	scala/collection/SetLike$class.apply:(Lscala/collection/SetLike;Ljava/lang/Object;)Z
Method	scala/collection/SetLike$class.equals:(Lscala/collection/SetLike;Ljava/lang/Object;)Z
Method	scala/collection/SetLike$class.hashCode:(Lscala/collection/SetLike;)I
Method	scala/collection/SetLike$class.isEmpty:(Lscala/collection/SetLike;)Z
Method	scala/collection/SetLike$class.newBuilder:(Lscala/collection/SetLike;)Lscala/collection/mutable/Builder;
Method	scala/collection/SetLike$class.stringPrefix:(Lscala/collection/SetLike;)Ljava/lang/String;
Method	scala/collection/SetLike$class.subsetOf:(Lscala/collection/SetLike;Lscala/collection/Set;)Z
Method	scala/collection/SetLike$class.toString:(Lscala/collection/SetLike;)Ljava/lang/String;
Method	scala/collection/Traversable$class.$init$:(Lscala/collection/Traversable;)V
Method	scala/collection/TraversableLike$class.$init$:(Lscala/collection/TraversableLike;)V
Method	scala/collection/TraversableLike$class.drop:(Lscala/collection/TraversableLike;I)Ljava/lang/Object;
Method	scala/collection/TraversableLike$class.filter:(Lscala/collection/TraversableLike;Lscala/Function1;)Ljava/lang/Object;
Method	scala/collection/TraversableLike$class.filterNot:(Lscala/collection/TraversableLike;Lscala/Function1;)Ljava/lang/Object;
Method	scala/collection/TraversableLike$class.isTraversableAgain:(Lscala/collection/TraversableLike;)Z
Method	scala/collection/TraversableLike$class.map:(Lscala/collection/TraversableLike;Lscala/Function1;Lscala/collection/generic/CanBuildFrom;)Ljava/lang/Object;
Method	scala/collection/TraversableLike$class.repr:(Lscala/collection/TraversableLike;)Ljava/lang/Object;
Method	scala/collection/TraversableLike$class.tail:(Lscala/collection/TraversableLike;)Ljava/lang/Object;
Method	scala/collection/TraversableOnce$class.$div$colon:(Lscala/collection/TraversableOnce;Ljava/lang/Object;Lscala/Function2;)Ljava/lang/Object;
Method	scala/collection/TraversableOnce$class.$init$:(Lscala/collection/TraversableOnce;)V
Method	scala/collection/TraversableOnce$class.addString:(Lscala/collection/TraversableOnce;Lscala/collection/mutable/StringBuilder;Ljava/lang/String;Ljava/lang/String;Ljava/lang/String;)Lscala/collection/mutable/StringBuilder;
Method	scala/collection/TraversableOnce$class.copyToArray:(Lscala/collection/TraversableOnce;Ljava/lang/Object;I)V
Method	scala/collection/TraversableOnce$class.foldLeft:(Lscala/collection/TraversableOnce;Ljava/lang/Object;Lscala/Function2;)Ljava/lang/Object;
Method	scala/collection/TraversableOnce$class.mkString:(Lscala/collection/TraversableOnce;)Ljava/lang/String;
Method	scala/collection/TraversableOnce$class.mkString:(Lscala/collection/TraversableOnce;Ljava/lang/String;)Ljava/lang/String;
Method	scala/collection/TraversableOnce$class.mkString:(Lscala/collection/TraversableOnce;Ljava/lang/String;Ljava/lang/String;Ljava/lang/String;)Ljava/lang/String;
Method	scala/collection/TraversableOnce$class.nonEmpty:(Lscala/collection/TraversableOnce;)Z
Method	scala/collection/TraversableOnce$class.sum:(Lscala/collection/TraversableOnce;Lscala/math/Numeric;)Ljava/lang/Object;
Method	scala/collection/TraversableOnce$class.toArray:(Lscala/collection/TraversableOnce;Lscala/reflect/ClassManifest;)Ljava/lang/Object;
Method	scala/collection/TraversableOnce$class.toList:(Lscala/collection/TraversableOnce;)Lscala/collection/immutable/List;
Method	scala/collection/TraversableOnce$class.toSet:(Lscala/collection/TraversableOnce;)Lscala/collection/immutable/Set;
Method	scala/collection/generic/Addable$class.$init$:(Lscala/collection/generic/Addable;)V
Method	scala/collection/generic/Addable$class.$plus$plus:(Lscala/collection/generic/Addable;Lscala/collection/TraversableOnce;)Lscala/collection/generic/Addable;
Method	scala/collection/generic/GenericSetTemplate$class.$init$:(Lscala/collection/generic/GenericSetTemplate;)V
Method	scala/collection/generic/GenericSetTemplate$class.empty:(Lscala/collection/generic/GenericSetTemplate;)Lscala/collection/Set;
Method	scala/collection/generic/GenericTraversableTemplate$class.$init$:(Lscala/collection/generic/GenericTraversableTemplate;)V
Method	scala/collection/generic/GenericTraversableTemplate$class.genericBuilder:(Lscala/collection/generic/GenericTraversableTemplate;)Lscala/collection/mutable/Builder;
Method	scala/collection/generic/Subtractable$class.$init$:(Lscala/collection/generic/Subtractable;)V
Method	scala/collection/immutable/Iterable$class.$init$:(Lscala/collection/immutable/Iterable;)V
Method	scala/collection/immutable/Set$Set3.$plus:(Ljava/lang/Object;)Lscala/collection/immutable/Set;
Method	scala/collection/immutable/Set$Set3.contains:(Ljava/lang/Object;)Z
Method	scala/collection/immutable/Set$Set4."<init>":(Ljava/lang/Object;Ljava/lang/Object;Ljava/lang/Object;Ljava/lang/Object;)V
Method	scala/collection/immutable/Set$class.$init$:(Lscala/collection/immutable/Set;)V
Method	scala/collection/immutable/Set$class.companion:(Lscala/collection/immutable/Set;)Lscala/collection/generic/GenericCompanion;
Method	scala/collection/immutable/Traversable$class.$init$:(Lscala/collection/immutable/Traversable;)V
Method	scala/runtime/BoxesRunTime.boxToBoolean:(Z)Ljava/lang/Boolean;
Method	scala/runtime/BoxesRunTime.equalsCharObject:(Ljava/lang/Character;Ljava/lang/Object;)Z
Method	scala/runtime/BoxesRunTime.equalsNumObject:(Ljava/lang/Number;Ljava/lang/Object;)Z
InterfaceMethod	scala/Function1.apply:(Ljava/lang/Object;)Ljava/lang/Object;
InterfaceMethod	scala/collection/SetLike.apply:(Ljava/lang/Object;)Z
InterfaceMethod	scala/collection/TraversableLike.repr:()Ljava/lang/Object;
NameAndType	$div$colon:(Lscala/collection/TraversableOnce;Ljava/lang/Object;Lscala/Function2;)Ljava/lang/Object;
NameAndType	$init$:(Lscala/Function1;)V
NameAndType	$init$:(Lscala/collection/Iterable;)V
NameAndType	$init$:(Lscala/collection/IterableLike;)V
NameAndType	$init$:(Lscala/collection/Set;)V
NameAndType	$init$:(Lscala/collection/SetLike;)V
NameAndType	$init$:(Lscala/collection/Traversable;)V
NameAndType	$init$:(Lscala/collection/TraversableLike;)V
NameAndType	$init$:(Lscala/collection/TraversableOnce;)V
NameAndType	$init$:(Lscala/collection/generic/Addable;)V
NameAndType	$init$:(Lscala/collection/generic/GenericSetTemplate;)V
NameAndType	$init$:(Lscala/collection/generic/GenericTraversableTemplate;)V
NameAndType	$init$:(Lscala/collection/generic/Subtractable;)V
NameAndType	$init$:(Lscala/collection/immutable/Iterable;)V
NameAndType	$init$:(Lscala/collection/immutable/Set;)V
NameAndType	$init$:(Lscala/collection/immutable/Traversable;)V
NameAndType	$plus:(Ljava/lang/Object;)Lscala/collection/immutable/Set;
NameAndType	$plus$plus:(Lscala/collection/generic/Addable;Lscala/collection/TraversableOnce;)Lscala/collection/generic/Addable;
NameAndType	"<init>":()V
NameAndType	"<init>":(Ljava/lang/Object;Ljava/lang/Object;Ljava/lang/Object;Ljava/lang/Object;)V
NameAndType	MODULE$:Lscala/Predef$;
NameAndType	MODULE$:Lscala/collection/Iterator$;
NameAndType	addString:(Lscala/collection/TraversableOnce;Lscala/collection/mutable/StringBuilder;Ljava/lang/String;Ljava/lang/String;Ljava/lang/String;)Lscala/collection/mutable/StringBuilder;
NameAndType	apply:(Ljava/lang/Object;)Ljava/lang/Object;
NameAndType	apply:(Ljava/lang/Object;)Z
NameAndType	apply:(Lscala/collection/Seq;)Lscala/collection/Iterator;
NameAndType	apply:(Lscala/collection/SetLike;Ljava/lang/Object;)Z
NameAndType	boxToBoolean:(Z)Ljava/lang/Boolean;
NameAndType	canEqual:(Lscala/collection/IterableLike;Ljava/lang/Object;)Z
NameAndType	companion:(Lscala/collection/immutable/Set;)Lscala/collection/generic/GenericCompanion;
NameAndType	contains:(Ljava/lang/Object;)Z
NameAndType	copyToArray:(Lscala/collection/IterableLike;Ljava/lang/Object;II)V
NameAndType	copyToArray:(Lscala/collection/TraversableOnce;Ljava/lang/Object;I)V
NameAndType	drop:(Lscala/collection/TraversableLike;I)Ljava/lang/Object;
NameAndType	elem1:Ljava/lang/Object;
NameAndType	elem2:Ljava/lang/Object;
NameAndType	elem3:Ljava/lang/Object;
NameAndType	empty:(Lscala/collection/generic/GenericSetTemplate;)Lscala/collection/Set;
NameAndType	equals:(Ljava/lang/Object;)Z
NameAndType	equals:(Lscala/collection/SetLike;Ljava/lang/Object;)Z
NameAndType	equalsCharObject:(Ljava/lang/Character;Ljava/lang/Object;)Z
NameAndType	equalsNumObject:(Ljava/lang/Number;Ljava/lang/Object;)Z
NameAndType	exists:(Lscala/collection/IterableLike;Lscala/Function1;)Z
NameAndType	filter:(Lscala/collection/TraversableLike;Lscala/Function1;)Ljava/lang/Object;
NameAndType	filterNot:(Lscala/collection/TraversableLike;Lscala/Function1;)Ljava/lang/Object;
NameAndType	foldLeft:(Lscala/collection/TraversableOnce;Ljava/lang/Object;Lscala/Function2;)Ljava/lang/Object;
NameAndType	forall:(Lscala/collection/IterableLike;Lscala/Function1;)Z
NameAndType	genericBuilder:(Lscala/collection/generic/GenericTraversableTemplate;)Lscala/collection/mutable/Builder;
NameAndType	genericWrapArray:(Ljava/lang/Object;)Lscala/collection/mutable/WrappedArray;
NameAndType	hashCode:(Lscala/collection/SetLike;)I
NameAndType	head:(Lscala/collection/IterableLike;)Ljava/lang/Object;
NameAndType	isEmpty:(Lscala/collection/SetLike;)Z
NameAndType	isTraversableAgain:(Lscala/collection/TraversableLike;)Z
NameAndType	map:(Lscala/collection/TraversableLike;Lscala/Function1;Lscala/collection/generic/CanBuildFrom;)Ljava/lang/Object;
NameAndType	mkString:(Lscala/collection/TraversableOnce;)Ljava/lang/String;
NameAndType	mkString:(Lscala/collection/TraversableOnce;Ljava/lang/String;)Ljava/lang/String;
NameAndType	mkString:(Lscala/collection/TraversableOnce;Ljava/lang/String;Ljava/lang/String;Ljava/lang/String;)Ljava/lang/String;
NameAndType	newBuilder:(Lscala/collection/SetLike;)Lscala/collection/mutable/Builder;
NameAndType	nonEmpty:(Lscala/collection/TraversableOnce;)Z
NameAndType	repr:()Ljava/lang/Object;
NameAndType	repr:(Lscala/collection/TraversableLike;)Ljava/lang/Object;
NameAndType	sameElements:(Lscala/collection/IterableLike;Lscala/collection/Iterable;)Z
NameAndType	serialVersionUID:J
NameAndType	stringPrefix:(Lscala/collection/SetLike;)Ljava/lang/String;
NameAndType	subsetOf:(Lscala/collection/SetLike;Lscala/collection/Set;)Z
NameAndType	sum:(Lscala/collection/TraversableOnce;Lscala/math/Numeric;)Ljava/lang/Object;
NameAndType	tail:(Lscala/collection/TraversableLike;)Ljava/lang/Object;
NameAndType	toArray:(Lscala/collection/TraversableOnce;Lscala/reflect/ClassManifest;)Ljava/lang/Object;
NameAndType	toList:(Lscala/collection/TraversableOnce;)Lscala/collection/immutable/List;
NameAndType	toSet:(Lscala/collection/TraversableOnce;)Lscala/collection/immutable/Set;
NameAndType	toStream:(Lscala/collection/IterableLike;)Lscala/collection/immutable/Stream;
NameAndType	toString:(Lscala/collection/SetLike;)Ljava/lang/String;
NameAndType	zip:(Lscala/collection/IterableLike;Lscala/collection/Iterable;Lscala/collection/generic/CanBuildFrom;)Ljava/lang/Object;
Asciz	$div$colon;
Asciz	$init$;
Asciz	$plus;
Asciz	$plus$plus;
Asciz	()I;
Asciz	()Ljava/lang/Object;;
Asciz	()Ljava/lang/String;;
Asciz	()Lscala/collection/Iterator;;
Asciz	()Lscala/collection/Iterator<TA;>;;
Asciz	()Lscala/collection/Set;;
Asciz	()Lscala/collection/generic/Addable;;
Asciz	()Lscala/collection/generic/GenericCompanion;;
Asciz	()Lscala/collection/immutable/List;;
Asciz	()Lscala/collection/immutable/Set;;
Asciz	()Lscala/collection/immutable/Stream;;
Asciz	()Lscala/collection/mutable/Builder;;
Asciz	()V;
Asciz	()Z;
Asciz	(I)Ljava/lang/Object;;
Asciz	(Ljava/lang/Character;Ljava/lang/Object;)Z;
Asciz	(Ljava/lang/Number;Ljava/lang/Object;)Z;
Asciz	(Ljava/lang/Object;)Ljava/lang/Object;;
Asciz	(Ljava/lang/Object;)Lscala/collection/generic/Addable;;
Asciz	(Ljava/lang/Object;)Lscala/collection/immutable/Set;;
Asciz	(Ljava/lang/Object;)Lscala/collection/mutable/WrappedArray;;
Asciz	(Ljava/lang/Object;)Z;
Asciz	(Ljava/lang/Object;I)V;
Asciz	(Ljava/lang/Object;II)V;
Asciz	(Ljava/lang/Object;Ljava/lang/Object;Ljava/lang/Object;)V;
Asciz	(Ljava/lang/Object;Ljava/lang/Object;Ljava/lang/Object;Ljava/lang/Object;)V;
Asciz	(Ljava/lang/Object;Lscala/Function2;)Ljava/lang/Object;;
Asciz	(Ljava/lang/String;)Ljava/lang/String;;
Asciz	(Ljava/lang/String;Ljava/lang/String;Ljava/lang/String;)Ljava/lang/String;;
Asciz	(Lscala/Function1;)Ljava/lang/Object;;
Asciz	(Lscala/Function1;)V;
Asciz	(Lscala/Function1;)Z;
Asciz	(Lscala/Function1;Lscala/collection/generic/CanBuildFrom;)Ljava/lang/Object;;
Asciz	(Lscala/collection/Iterable;)V;
Asciz	(Lscala/collection/Iterable;)Z;
Asciz	(Lscala/collection/Iterable;Lscala/collection/generic/CanBuildFrom;)Ljava/lang/Object;;
Asciz	(Lscala/collection/IterableLike;)Ljava/lang/Object;;
Asciz	(Lscala/collection/IterableLike;)Lscala/collection/immutable/Stream;;
Asciz	(Lscala/collection/IterableLike;)V;
Asciz	(Lscala/collection/IterableLike;Ljava/lang/Object;)Z;
Asciz	(Lscala/collection/IterableLike;Ljava/lang/Object;II)V;
Asciz	(Lscala/collection/IterableLike;Lscala/Function1;)Z;
Asciz	(Lscala/collection/IterableLike;Lscala/collection/Iterable;)Z;
Asciz	(Lscala/collection/IterableLike;Lscala/collection/Iterable;Lscala/collection/generic/CanBuildFrom;)Ljava/lang/Object;;
Asciz	(Lscala/collection/Seq;)Lscala/collection/Iterator;;
Asciz	(Lscala/collection/Set;)V;
Asciz	(Lscala/collection/Set;)Z;
Asciz	(Lscala/collection/SetLike;)I;
Asciz	(Lscala/collection/SetLike;)Ljava/lang/String;;
Asciz	(Lscala/collection/SetLike;)Lscala/collection/mutable/Builder;;
Asciz	(Lscala/collection/SetLike;)V;
Asciz	(Lscala/collection/SetLike;)Z;
Asciz	(Lscala/collection/SetLike;Ljava/lang/Object;)Z;
Asciz	(Lscala/collection/SetLike;Lscala/collection/Set;)Z;
Asciz	(Lscala/collection/Traversable;)V;
Asciz	(Lscala/collection/TraversableLike;)Ljava/lang/Object;;
Asciz	(Lscala/collection/TraversableLike;)V;
Asciz	(Lscala/collection/TraversableLike;)Z;
Asciz	(Lscala/collection/TraversableLike;I)Ljava/lang/Object;;
Asciz	(Lscala/collection/TraversableLike;Lscala/Function1;)Ljava/lang/Object;;
Asciz	(Lscala/collection/TraversableLike;Lscala/Function1;Lscala/collection/generic/CanBuildFrom;)Ljava/lang/Object;;
Asciz	(Lscala/collection/TraversableOnce;)Ljava/lang/String;;
Asciz	(Lscala/collection/TraversableOnce;)Lscala/collection/generic/Addable;;
Asciz	(Lscala/collection/TraversableOnce;)Lscala/collection/immutable/List;;
Asciz	(Lscala/collection/TraversableOnce;)Lscala/collection/immutable/Set;;
Asciz	(Lscala/collection/TraversableOnce;)V;
Asciz	(Lscala/collection/TraversableOnce;)Z;
Asciz	(Lscala/collection/TraversableOnce;Ljava/lang/Object;I)V;
Asciz	(Lscala/collection/TraversableOnce;Ljava/lang/Object;Lscala/Function2;)Ljava/lang/Object;;
Asciz	(Lscala/collection/TraversableOnce;Ljava/lang/String;)Ljava/lang/String;;
Asciz	(Lscala/collection/TraversableOnce;Ljava/lang/String;Ljava/lang/String;Ljava/lang/String;)Ljava/lang/String;;
Asciz	(Lscala/collection/TraversableOnce;Lscala/collection/mutable/StringBuilder;Ljava/lang/String;Ljava/lang/String;Ljava/lang/String;)Lscala/collection/mutable/StringBuilder;;
Asciz	(Lscala/collection/TraversableOnce;Lscala/math/Numeric;)Ljava/lang/Object;;
Asciz	(Lscala/collection/TraversableOnce;Lscala/reflect/ClassManifest;)Ljava/lang/Object;;
Asciz	(Lscala/collection/generic/Addable;)V;
Asciz	(Lscala/collection/generic/Addable;Lscala/collection/TraversableOnce;)Lscala/collection/generic/Addable;;
Asciz	(Lscala/collection/generic/GenericSetTemplate;)Lscala/collection/Set;;
Asciz	(Lscala/collection/generic/GenericSetTemplate;)V;
Asciz	(Lscala/collection/generic/GenericTraversableTemplate;)Lscala/collection/mutable/Builder;;
Asciz	(Lscala/collection/generic/GenericTraversableTemplate;)V;
Asciz	(Lscala/collection/generic/Subtractable;)V;
Asciz	(Lscala/collection/immutable/Iterable;)V;
Asciz	(Lscala/collection/immutable/Set;)Lscala/collection/generic/GenericCompanion;;
Asciz	(Lscala/collection/immutable/Set;)V;
Asciz	(Lscala/collection/immutable/Traversable;)V;
Asciz	(Lscala/collection/mutable/StringBuilder;Ljava/lang/String;Ljava/lang/String;Ljava/lang/String;)Lscala/collection/mutable/StringBuilder;;
Asciz	(Lscala/math/Numeric;)Ljava/lang/Object;;
Asciz	(Lscala/reflect/ClassManifest;)Ljava/lang/Object;;
Asciz	(TA;)Lscala/collection/immutable/Set<TA;>;;
Asciz	(TA;)Z;
Asciz	(TA;TA;TA;)V;
Asciz	(Z)Ljava/lang/Boolean;;
Asciz	<A:Ljava/lang/Object;>Ljava/lang/Object;Lscala/collection/immutable/Set<TA;>;;
Asciz	<U:Ljava/lang/Object;>(Lscala/Function1<TA;TU;>;)V;
Asciz	<clinit>;
Asciz	<init>;
Asciz	Code;
Asciz	I;
Asciz	InnerClasses;
Asciz	J;
Asciz	LineNumberTable;
Asciz	Ljava/lang/Object;;
Asciz	Ljava/lang/String;;
Asciz	LocalVariableTable;
Asciz	Lscala/Function1;;
Asciz	Lscala/Function2;;
Asciz	Lscala/Predef$;;
Asciz	Lscala/collection/Iterable;;
Asciz	Lscala/collection/Iterator$;;
Asciz	Lscala/collection/Set;;
Asciz	Lscala/collection/TraversableOnce;;
Asciz	Lscala/collection/generic/CanBuildFrom;;
Asciz	Lscala/collection/immutable/Set$Set3;;
Asciz	Lscala/collection/mutable/StringBuilder;;
Asciz	Lscala/math/Numeric;;
Asciz	Lscala/reflect/ClassManifest;;
Asciz	MODULE$;
Asciz	Scala;
Asciz	Set.scala;
Asciz	Set2;
Asciz	Set3;
Asciz	Set4;
Asciz	Signature;
Asciz	SourceFile;
Asciz	TA;;
Asciz	addString;
Asciz	apply;
Asciz	b;
Asciz	bf;
Asciz	boxToBoolean;
Asciz	canEqual;
Asciz	companion;
Asciz	contains;
Asciz	copyToArray;
Asciz	drop;
Asciz	elem;
Asciz	elem1;
Asciz	elem2;
Asciz	elem3;
Asciz	empty;
Asciz	end;
Asciz	equals;
Asciz	equalsCharObject;
Asciz	equalsNumObject;
Asciz	evidence$1;
Asciz	exists;
Asciz	f;
Asciz	filter;
Asciz	filterNot;
Asciz	foldLeft;
Asciz	forall;
Asciz	foreach;
Asciz	genericBuilder;
Asciz	genericWrapArray;
Asciz	hashCode;
Asciz	head;
Asciz	isEmpty;
Asciz	isTraversableAgain;
Asciz	iterator;
Asciz	java/io/Serializable;
Asciz	java/lang/Character;
Asciz	java/lang/Number;
Asciz	java/lang/Object;
Asciz	len;
Asciz	map;
Asciz	mkString;
Asciz	n;
Asciz	newBuilder;
Asciz	nonEmpty;
Asciz	num;
Asciz	op;
Asciz	p;
Asciz	repr;
Asciz	sameElements;
Asciz	scala/Function1;
Asciz	scala/Function1$class;
Asciz	scala/Predef$;
Asciz	scala/collection/Iterable$class;
Asciz	scala/collection/IterableLike$class;
Asciz	scala/collection/Iterator$;
Asciz	scala/collection/Set$class;
Asciz	scala/collection/SetLike;
Asciz	scala/collection/SetLike$class;
Asciz	scala/collection/Traversable$class;
Asciz	scala/collection/TraversableLike;
Asciz	scala/collection/TraversableLike$class;
Asciz	scala/collection/TraversableOnce$class;
Asciz	scala/collection/generic/Addable;
Asciz	scala/collection/generic/Addable$class;
Asciz	scala/collection/generic/GenericSetTemplate$class;
Asciz	scala/collection/generic/GenericTraversableTemplate$class;
Asciz	scala/collection/generic/Subtractable$class;
Asciz	scala/collection/immutable/Iterable$class;
Asciz	scala/collection/immutable/Set;
Asciz	scala/collection/immutable/Set$Set2;
Asciz	scala/collection/immutable/Set$Set3;
Asciz	scala/collection/immutable/Set$Set4;
Asciz	scala/collection/immutable/Set$class;
Asciz	scala/collection/immutable/Traversable$class;
Asciz	scala/runtime/BoxesRunTime;
Asciz	sep;
Asciz	serialVersionUID;
Asciz	size;
Asciz	start;
Asciz	stringPrefix;
Asciz	subsetOf;
Asciz	sum;
Asciz	tail;
Asciz	that;
Asciz	this;
Asciz	toArray;
Asciz	toList;
Asciz	toSet;
Asciz	toStream;
Asciz	toString;
Asciz	v1;
Asciz	xs;
Asciz	y0;
Asciz	y1;
Asciz	y2;
Asciz	z;
Asciz	zip;

{
public static final long serialVersionUID;
  Signature: J

private final java.lang.Object elem1;
  Signature: Ljava/lang/Object;
  Signature: length = 0x2
   01 33 

private final java.lang.Object elem2;
  Signature: Ljava/lang/Object;
  Signature: length = 0x2
   01 33 

private final java.lang.Object elem3;
  Signature: Ljava/lang/Object;
  Signature: length = 0x2
   01 33 

public static {};
  Signature: ()V
  Code:
   Stack=2, Locals=0, Args_size=0
	ldc2_w	long -3590273538119220064l
	putstatic	Field serialVersionUID:J
	return
  Labels:

public scala.collection.generic.GenericCompanion companion();
  Signature: ()Lscala/collection/generic/GenericCompanion;
  Code:
   Stack=1, Locals=1, Args_size=1
	aload_0
	invokestatic	Method scala/collection/immutable/Set$class.companion:(Lscala/collection/immutable/Set;)Lscala/collection/generic/GenericCompanion;
	areturn
  Labels:

public scala.collection.mutable.Builder newBuilder();
  Signature: ()Lscala/collection/mutable/Builder;
  Code:
   Stack=1, Locals=1, Args_size=1
	aload_0
	invokestatic	Method scala/collection/SetLike$class.newBuilder:(Lscala/collection/SetLike;)Lscala/collection/mutable/Builder;
	areturn
  Labels:

public boolean isEmpty();
  Signature: ()Z
  Code:
   Stack=1, Locals=1, Args_size=1
	aload_0
	invokestatic	Method scala/collection/SetLike$class.isEmpty:(Lscala/collection/SetLike;)Z
	ireturn
  Labels:

public boolean apply(java.lang.Object);
  Signature: (Ljava/lang/Object;)Z
  Code:
   Stack=2, Locals=2, Args_size=2
	aload_0
	aload_1
	invokestatic	Method scala/collection/SetLike$class.apply:(Lscala/collection/SetLike;Ljava/lang/Object;)Z
	ireturn
  Labels:
  LocalVariableTable: 
   Start  Length  Slot  Name   Signature
   0      6      0    this       Lscala/collection/immutable/Set$Set3;
   0      6      1    elem       Ljava/lang/Object;


public boolean subsetOf(scala.collection.Set);
  Signature: (Lscala/collection/Set;)Z
  Code:
   Stack=2, Locals=2, Args_size=2
	aload_0
	aload_1
	invokestatic	Method scala/collection/SetLike$class.subsetOf:(Lscala/collection/SetLike;Lscala/collection/Set;)Z
	ireturn
  Labels:
  LocalVariableTable: 
   Start  Length  Slot  Name   Signature
   0      6      0    this       Lscala/collection/immutable/Set$Set3;
   0      6      1    that       Lscala/collection/Set;


public java.lang.String stringPrefix();
  Signature: ()Ljava/lang/String;
  Code:
   Stack=1, Locals=1, Args_size=1
	aload_0
	invokestatic	Method scala/collection/SetLike$class.stringPrefix:(Lscala/collection/SetLike;)Ljava/lang/String;
	areturn
  Labels:

public java.lang.String toString();
  Signature: ()Ljava/lang/String;
  Code:
   Stack=1, Locals=1, Args_size=1
	aload_0
	invokestatic	Method scala/collection/SetLike$class.toString:(Lscala/collection/SetLike;)Ljava/lang/String;
	areturn
  Labels:

public int hashCode();
  Signature: ()I
  Code:
   Stack=1, Locals=1, Args_size=1
	aload_0
	invokestatic	Method scala/collection/SetLike$class.hashCode:(Lscala/collection/SetLike;)I
	ireturn
  Labels:

public boolean equals(java.lang.Object);
  Signature: (Ljava/lang/Object;)Z
  Code:
   Stack=2, Locals=2, Args_size=2
	aload_0
	aload_1
	invokestatic	Method scala/collection/SetLike$class.equals:(Lscala/collection/SetLike;Ljava/lang/Object;)Z
	ireturn
  Labels:
  LocalVariableTable: 
   Start  Length  Slot  Name   Signature
   0      6      0    this       Lscala/collection/immutable/Set$Set3;
   0      6      1    that       Ljava/lang/Object;


public scala.collection.generic.Addable $plus$plus(scala.collection.TraversableOnce);
  Signature: (Lscala/collection/TraversableOnce;)Lscala/collection/generic/Addable;
  Code:
   Stack=2, Locals=2, Args_size=2
	aload_0
	aload_1
	invokestatic	Method scala/collection/generic/Addable$class.$plus$plus:(Lscala/collection/generic/Addable;Lscala/collection/TraversableOnce;)Lscala/collection/generic/Addable;
	areturn
  Labels:
  LocalVariableTable: 
   Start  Length  Slot  Name   Signature
   0      6      0    this       Lscala/collection/immutable/Set$Set3;
   0      6      1    xs       Lscala/collection/TraversableOnce;


public scala.collection.Set empty();
  Signature: ()Lscala/collection/Set;
  Code:
   Stack=1, Locals=1, Args_size=1
	aload_0
	invokestatic	Method scala/collection/generic/GenericSetTemplate$class.empty:(Lscala/collection/generic/GenericSetTemplate;)Lscala/collection/Set;
	areturn
  Labels:

public boolean forall(scala.Function1);
  Signature: (Lscala/Function1;)Z
  Code:
   Stack=2, Locals=2, Args_size=2
	aload_0
	aload_1
	invokestatic	Method scala/collection/IterableLike$class.forall:(Lscala/collection/IterableLike;Lscala/Function1;)Z
	ireturn
  Labels:
  LocalVariableTable: 
   Start  Length  Slot  Name   Signature
   0      6      0    this       Lscala/collection/immutable/Set$Set3;
   0      6      1    p       Lscala/Function1;


public boolean exists(scala.Function1);
  Signature: (Lscala/Function1;)Z
  Code:
   Stack=2, Locals=2, Args_size=2
	aload_0
	aload_1
	invokestatic	Method scala/collection/IterableLike$class.exists:(Lscala/collection/IterableLike;Lscala/Function1;)Z
	ireturn
  Labels:
  LocalVariableTable: 
   Start  Length  Slot  Name   Signature
   0      6      0    this       Lscala/collection/immutable/Set$Set3;
   0      6      1    p       Lscala/Function1;


public java.lang.Object head();
  Signature: ()Ljava/lang/Object;
  Code:
   Stack=1, Locals=1, Args_size=1
	aload_0
	invokestatic	Method scala/collection/IterableLike$class.head:(Lscala/collection/IterableLike;)Ljava/lang/Object;
	areturn
  Labels:

public void copyToArray(java.lang.Object, int, int);
  Signature: (Ljava/lang/Object;II)V
  Code:
   Stack=4, Locals=4, Args_size=4
	aload_0
	aload_1
	iload_2
	iload_3
	invokestatic	Method scala/collection/IterableLike$class.copyToArray:(Lscala/collection/IterableLike;Ljava/lang/Object;II)V
	return
  Labels:
  LocalVariableTable: 
   Start  Length  Slot  Name   Signature
   0      8      0    this       Lscala/collection/immutable/Set$Set3;
   0      8      1    xs       Ljava/lang/Object;
   0      8      2    start       I
   0      8      3    len       I


public java.lang.Object zip(scala.collection.Iterable, scala.collection.generic.CanBuildFrom);
  Signature: (Lscala/collection/Iterable;Lscala/collection/generic/CanBuildFrom;)Ljava/lang/Object;
  Code:
   Stack=3, Locals=3, Args_size=3
	aload_0
	aload_1
	aload_2
	invokestatic	Method scala/collection/IterableLike$class.zip:(Lscala/collection/IterableLike;Lscala/collection/Iterable;Lscala/collection/generic/CanBuildFrom;)Ljava/lang/Object;
	areturn
  Labels:
  LocalVariableTable: 
   Start  Length  Slot  Name   Signature
   0      7      0    this       Lscala/collection/immutable/Set$Set3;
   0      7      1    that       Lscala/collection/Iterable;
   0      7      2    bf       Lscala/collection/generic/CanBuildFrom;


public boolean sameElements(scala.collection.Iterable);
  Signature: (Lscala/collection/Iterable;)Z
  Code:
   Stack=2, Locals=2, Args_size=2
	aload_0
	aload_1
	invokestatic	Method scala/collection/IterableLike$class.sameElements:(Lscala/collection/IterableLike;Lscala/collection/Iterable;)Z
	ireturn
  Labels:
  LocalVariableTable: 
   Start  Length  Slot  Name   Signature
   0      6      0    this       Lscala/collection/immutable/Set$Set3;
   0      6      1    that       Lscala/collection/Iterable;


public scala.collection.immutable.Stream toStream();
  Signature: ()Lscala/collection/immutable/Stream;
  Code:
   Stack=1, Locals=1, Args_size=1
	aload_0
	invokestatic	Method scala/collection/IterableLike$class.toStream:(Lscala/collection/IterableLike;)Lscala/collection/immutable/Stream;
	areturn
  Labels:

public boolean canEqual(java.lang.Object);
  Signature: (Ljava/lang/Object;)Z
  Code:
   Stack=2, Locals=2, Args_size=2
	aload_0
	aload_1
	invokestatic	Method scala/collection/IterableLike$class.canEqual:(Lscala/collection/IterableLike;Ljava/lang/Object;)Z
	ireturn
  Labels:
  LocalVariableTable: 
   Start  Length  Slot  Name   Signature
   0      6      0    this       Lscala/collection/immutable/Set$Set3;
   0      6      1    that       Ljava/lang/Object;


public scala.collection.mutable.Builder genericBuilder();
  Signature: ()Lscala/collection/mutable/Builder;
  Code:
   Stack=1, Locals=1, Args_size=1
	aload_0
	invokestatic	Method scala/collection/generic/GenericTraversableTemplate$class.genericBuilder:(Lscala/collection/generic/GenericTraversableTemplate;)Lscala/collection/mutable/Builder;
	areturn
  Labels:

public java.lang.Object repr();
  Signature: ()Ljava/lang/Object;
  Code:
   Stack=1, Locals=1, Args_size=1
	aload_0
	invokestatic	Method scala/collection/TraversableLike$class.repr:(Lscala/collection/TraversableLike;)Ljava/lang/Object;
	areturn
  Labels:

public final boolean isTraversableAgain();
  Signature: ()Z
  Code:
   Stack=1, Locals=1, Args_size=1
	aload_0
	invokestatic	Method scala/collection/TraversableLike$class.isTraversableAgain:(Lscala/collection/TraversableLike;)Z
	ireturn
  Labels:

public java.lang.Object map(scala.Function1, scala.collection.generic.CanBuildFrom);
  Signature: (Lscala/Function1;Lscala/collection/generic/CanBuildFrom;)Ljava/lang/Object;
  Code:
   Stack=3, Locals=3, Args_size=3
	aload_0
	aload_1
	aload_2
	invokestatic	Method scala/collection/TraversableLike$class.map:(Lscala/collection/TraversableLike;Lscala/Function1;Lscala/collection/generic/CanBuildFrom;)Ljava/lang/Object;
	areturn
  Labels:
  LocalVariableTable: 
   Start  Length  Slot  Name   Signature
   0      7      0    this       Lscala/collection/immutable/Set$Set3;
   0      7      1    f       Lscala/Function1;
   0      7      2    bf       Lscala/collection/generic/CanBuildFrom;


public java.lang.Object filter(scala.Function1);
  Signature: (Lscala/Function1;)Ljava/lang/Object;
  Code:
   Stack=2, Locals=2, Args_size=2
	aload_0
	aload_1
	invokestatic	Method scala/collection/TraversableLike$class.filter:(Lscala/collection/TraversableLike;Lscala/Function1;)Ljava/lang/Object;
	areturn
  Labels:
  LocalVariableTable: 
   Start  Length  Slot  Name   Signature
   0      6      0    this       Lscala/collection/immutable/Set$Set3;
   0      6      1    p       Lscala/Function1;


public java.lang.Object filterNot(scala.Function1);
  Signature: (Lscala/Function1;)Ljava/lang/Object;
  Code:
   Stack=2, Locals=2, Args_size=2
	aload_0
	aload_1
	invokestatic	Method scala/collection/TraversableLike$class.filterNot:(Lscala/collection/TraversableLike;Lscala/Function1;)Ljava/lang/Object;
	areturn
  Labels:
  LocalVariableTable: 
   Start  Length  Slot  Name   Signature
   0      6      0    this       Lscala/collection/immutable/Set$Set3;
   0      6      1    p       Lscala/Function1;


public java.lang.Object tail();
  Signature: ()Ljava/lang/Object;
  Code:
   Stack=1, Locals=1, Args_size=1
	aload_0
	invokestatic	Method scala/collection/TraversableLike$class.tail:(Lscala/collection/TraversableLike;)Ljava/lang/Object;
	areturn
  Labels:

public java.lang.Object drop(int);
  Signature: (I)Ljava/lang/Object;
  Code:
   Stack=2, Locals=2, Args_size=2
	aload_0
	iload_1
	invokestatic	Method scala/collection/TraversableLike$class.drop:(Lscala/collection/TraversableLike;I)Ljava/lang/Object;
	areturn
  Labels:
  LocalVariableTable: 
   Start  Length  Slot  Name   Signature
   0      6      0    this       Lscala/collection/immutable/Set$Set3;
   0      6      1    n       I


public boolean nonEmpty();
  Signature: ()Z
  Code:
   Stack=1, Locals=1, Args_size=1
	aload_0
	invokestatic	Method scala/collection/TraversableOnce$class.nonEmpty:(Lscala/collection/TraversableOnce;)Z
	ireturn
  Labels:

public java.lang.Object $div$colon(java.lang.Object, scala.Function2);
  Signature: (Ljava/lang/Object;Lscala/Function2;)Ljava/lang/Object;
  Code:
   Stack=3, Locals=3, Args_size=3
	aload_0
	aload_1
	aload_2
	invokestatic	Method scala/collection/TraversableOnce$class.$div$colon:(Lscala/collection/TraversableOnce;Ljava/lang/Object;Lscala/Function2;)Ljava/lang/Object;
	areturn
  Labels:
  LocalVariableTable: 
   Start  Length  Slot  Name   Signature
   0      7      0    this       Lscala/collection/immutable/Set$Set3;
   0      7      1    z       Ljava/lang/Object;
   0      7      2    op       Lscala/Function2;


public java.lang.Object foldLeft(java.lang.Object, scala.Function2);
  Signature: (Ljava/lang/Object;Lscala/Function2;)Ljava/lang/Object;
  Code:
   Stack=3, Locals=3, Args_size=3
	aload_0
	aload_1
	aload_2
	invokestatic	Method scala/collection/TraversableOnce$class.foldLeft:(Lscala/collection/TraversableOnce;Ljava/lang/Object;Lscala/Function2;)Ljava/lang/Object;
	areturn
  Labels:
  LocalVariableTable: 
   Start  Length  Slot  Name   Signature
   0      7      0    this       Lscala/collection/immutable/Set$Set3;
   0      7      1    z       Ljava/lang/Object;
   0      7      2    op       Lscala/Function2;


public java.lang.Object sum(scala.math.Numeric);
  Signature: (Lscala/math/Numeric;)Ljava/lang/Object;
  Code:
   Stack=2, Locals=2, Args_size=2
	aload_0
	aload_1
	invokestatic	Method scala/collection/TraversableOnce$class.sum:(Lscala/collection/TraversableOnce;Lscala/math/Numeric;)Ljava/lang/Object;
	areturn
  Labels:
  LocalVariableTable: 
   Start  Length  Slot  Name   Signature
   0      6      0    this       Lscala/collection/immutable/Set$Set3;
   0      6      1    num       Lscala/math/Numeric;


public void copyToArray(java.lang.Object, int);
  Signature: (Ljava/lang/Object;I)V
  Code:
   Stack=3, Locals=3, Args_size=3
	aload_0
	aload_1
	iload_2
	invokestatic	Method scala/collection/TraversableOnce$class.copyToArray:(Lscala/collection/TraversableOnce;Ljava/lang/Object;I)V
	return
  Labels:
  LocalVariableTable: 
   Start  Length  Slot  Name   Signature
   0      7      0    this       Lscala/collection/immutable/Set$Set3;
   0      7      1    xs       Ljava/lang/Object;
   0      7      2    start       I


public java.lang.Object toArray(scala.reflect.ClassManifest);
  Signature: (Lscala/reflect/ClassManifest;)Ljava/lang/Object;
  Code:
   Stack=2, Locals=2, Args_size=2
	aload_0
	aload_1
	invokestatic	Method scala/collection/TraversableOnce$class.toArray:(Lscala/collection/TraversableOnce;Lscala/reflect/ClassManifest;)Ljava/lang/Object;
	areturn
  Labels:
  LocalVariableTable: 
   Start  Length  Slot  Name   Signature
   0      6      0    this       Lscala/collection/immutable/Set$Set3;
   0      6      1    evidence$1       Lscala/reflect/ClassManifest;


public scala.collection.immutable.List toList();
  Signature: ()Lscala/collection/immutable/List;
  Code:
   Stack=1, Locals=1, Args_size=1
	aload_0
	invokestatic	Method scala/collection/TraversableOnce$class.toList:(Lscala/collection/TraversableOnce;)Lscala/collection/immutable/List;
	areturn
  Labels:

public scala.collection.immutable.Set toSet();
  Signature: ()Lscala/collection/immutable/Set;
  Code:
   Stack=1, Locals=1, Args_size=1
	aload_0
	invokestatic	Method scala/collection/TraversableOnce$class.toSet:(Lscala/collection/TraversableOnce;)Lscala/collection/immutable/Set;
	areturn
  Labels:

public java.lang.String mkString(java.lang.String, java.lang.String, java.lang.String);
  Signature: (Ljava/lang/String;Ljava/lang/String;Ljava/lang/String;)Ljava/lang/String;
  Code:
   Stack=4, Locals=4, Args_size=4
	aload_0
	aload_1
	aload_2
	aload_3
	invokestatic	Method scala/collection/TraversableOnce$class.mkString:(Lscala/collection/TraversableOnce;Ljava/lang/String;Ljava/lang/String;Ljava/lang/String;)Ljava/lang/String;
	areturn
  Labels:
  LocalVariableTable: 
   Start  Length  Slot  Name   Signature
   0      8      0    this       Lscala/collection/immutable/Set$Set3;
   0      8      1    start       Ljava/lang/String;
   0      8      2    sep       Ljava/lang/String;
   0      8      3    end       Ljava/lang/String;


public java.lang.String mkString(java.lang.String);
  Signature: (Ljava/lang/String;)Ljava/lang/String;
  Code:
   Stack=2, Locals=2, Args_size=2
	aload_0
	aload_1
	invokestatic	Method scala/collection/TraversableOnce$class.mkString:(Lscala/collection/TraversableOnce;Ljava/lang/String;)Ljava/lang/String;
	areturn
  Labels:
  LocalVariableTable: 
   Start  Length  Slot  Name   Signature
   0      6      0    this       Lscala/collection/immutable/Set$Set3;
   0      6      1    sep       Ljava/lang/String;


public java.lang.String mkString();
  Signature: ()Ljava/lang/String;
  Code:
   Stack=1, Locals=1, Args_size=1
	aload_0
	invokestatic	Method scala/collection/TraversableOnce$class.mkString:(Lscala/collection/TraversableOnce;)Ljava/lang/String;
	areturn
  Labels:

public scala.collection.mutable.StringBuilder addString(scala.collection.mutable.StringBuilder, java.lang.String, java.lang.String, java.lang.String);
  Signature: (Lscala/collection/mutable/StringBuilder;Ljava/lang/String;Ljava/lang/String;Ljava/lang/String;)Lscala/collection/mutable/StringBuilder;
  Code:
   Stack=5, Locals=5, Args_size=5
	aload_0
	aload_1
	aload_2
	aload_3
	aload	4
	invokestatic	Method scala/collection/TraversableOnce$class.addString:(Lscala/collection/TraversableOnce;Lscala/collection/mutable/StringBuilder;Ljava/lang/String;Ljava/lang/String;Ljava/lang/String;)Lscala/collection/mutable/StringBuilder;
	areturn
  Labels:
  LocalVariableTable: 
   Start  Length  Slot  Name   Signature
   0      10      0    this       Lscala/collection/immutable/Set$Set3;
   0      10      1    b       Lscala/collection/mutable/StringBuilder;
   0      10      2    start       Ljava/lang/String;
   0      10      3    sep       Ljava/lang/String;
   0      10      4    end       Ljava/lang/String;


public int size();
  Signature: ()I
  Code:
   Stack=1, Locals=1, Args_size=1
	iconst_3
	ireturn
  Labels:

public boolean contains(java.lang.Object);
  Signature: (Ljava/lang/Object;)Z
  Code:
   Stack=2, Locals=5, Args_size=2
	aload_0
	getfield	Field elem1:Ljava/lang/Object;
	astore_2
	aload_1
	aload_2
	if_acmpne	l1 // aload_1
	iconst_1
	goto	l2 // ifne
l1	aload_1
	ifnonnull	l3 // aload_1
	iconst_0
	goto	l2 // ifne
l3	aload_1
	instanceof	class java/lang/Number
	ifeq	l4 // aload_1
	aload_1
	checkcast	class java/lang/Number
	aload_2
	invokestatic	Method scala/runtime/BoxesRunTime.equalsNumObject:(Ljava/lang/Number;Ljava/lang/Object;)Z
	goto	l2 // ifne
l4	aload_1
	instanceof	class java/lang/Character
	ifeq	l5 // aload_1
	aload_1
	checkcast	class java/lang/Character
	aload_2
	invokestatic	Method scala/runtime/BoxesRunTime.equalsCharObject:(Ljava/lang/Character;Ljava/lang/Object;)Z
	goto	l2 // ifne
l5	aload_1
	aload_2
	invokevirtual	Method java/lang/Object.equals:(Ljava/lang/Object;)Z
l2	ifne	l6 // iconst_1
	aload_0
	getfield	Field elem2:Ljava/lang/Object;
	astore_3
	aload_1
	aload_3
	if_acmpne	l7 // aload_1
	iconst_1
	goto	l8 // ifne
l7	aload_1
	ifnonnull	l9 // aload_1
	iconst_0
	goto	l8 // ifne
l9	aload_1
	instanceof	class java/lang/Number
	ifeq	l10 // aload_1
	aload_1
	checkcast	class java/lang/Number
	aload_3
	invokestatic	Method scala/runtime/BoxesRunTime.equalsNumObject:(Ljava/lang/Number;Ljava/lang/Object;)Z
	goto	l8 // ifne
l10	aload_1
	instanceof	class java/lang/Character
	ifeq	l11 // aload_1
	aload_1
	checkcast	class java/lang/Character
	aload_3
	invokestatic	Method scala/runtime/BoxesRunTime.equalsCharObject:(Ljava/lang/Character;Ljava/lang/Object;)Z
	goto	l8 // ifne
l11	aload_1
	aload_3
	invokevirtual	Method java/lang/Object.equals:(Ljava/lang/Object;)Z
l8	ifne	l6 // iconst_1
	aload_0
	getfield	Field elem3:Ljava/lang/Object;
	astore	4
	aload_1
	aload	4
	if_acmpne	l12 // aload_1
	iconst_1
	goto	l13 // ifeq
l12	aload_1
	ifnonnull	l14 // aload_1
	iconst_0
	goto	l13 // ifeq
l14	aload_1
	instanceof	class java/lang/Number
	ifeq	l15 // aload_1
	aload_1
	checkcast	class java/lang/Number
	aload	4
	invokestatic	Method scala/runtime/BoxesRunTime.equalsNumObject:(Ljava/lang/Number;Ljava/lang/Object;)Z
	goto	l13 // ifeq
l15	aload_1
	instanceof	class java/lang/Character
	ifeq	l16 // aload_1
	aload_1
	checkcast	class java/lang/Character
	aload	4
	invokestatic	Method scala/runtime/BoxesRunTime.equalsCharObject:(Ljava/lang/Character;Ljava/lang/Object;)Z
	goto	l13 // ifeq
l16	aload_1
	aload	4
	invokevirtual	Method java/lang/Object.equals:(Ljava/lang/Object;)Z
l13	ifeq	l17 // iconst_0
l6	iconst_1
	goto	l18 // ireturn
l17	iconst_0
l18	ireturn
  Labels:
   	l1 = 14 // aload_1
   	l3 = 22 // aload_1
   	l4 = 40 // aload_1
   	l5 = 58 // aload_1
   	l2 = 63 // ifne
   	l7 = 80 // aload_1
   	l9 = 88 // aload_1
   	l10 = 106 // aload_1
   	l11 = 124 // aload_1
   	l8 = 129 // ifne
   	l12 = 148 // aload_1
   	l14 = 156 // aload_1
   	l15 = 175 // aload_1
   	l16 = 194 // aload_1
   	l13 = 200 // ifeq
   	l6 = 203 // iconst_1
   	l17 = 207 // iconst_0
   	l18 = 208 // ireturn
  LocalVariableTable: 
   Start  Length  Slot  Name   Signature
   0      209      0    this       Lscala/collection/immutable/Set$Set3;
   0      209      1    elem       Ljava/lang/Object;
   10      56      2    y0       Ljava/lang/Object;
   76      56      3    y1       Ljava/lang/Object;
   144      59      4    y2       Ljava/lang/Object;

  Signature: length = 0x2
   01 10 

public scala.collection.immutable.Set $plus(java.lang.Object);
  Signature: (Ljava/lang/Object;)Lscala/collection/immutable/Set;
  Code:
   Stack=6, Locals=2, Args_size=2
	aload_0
	aload_1
	invokevirtual	Method contains:(Ljava/lang/Object;)Z
	ifeq	l1 // new
	aload_0
	goto	l2 // areturn
l1	new	class scala/collection/immutable/Set$Set4
	dup
	aload_0
	getfield	Field elem1:Ljava/lang/Object;
	aload_0
	getfield	Field elem2:Ljava/lang/Object;
	aload_0
	getfield	Field elem3:Ljava/lang/Object;
	aload_1
	invokespecial	Method scala/collection/immutable/Set$Set4."<init>":(Ljava/lang/Object;Ljava/lang/Object;Ljava/lang/Object;Ljava/lang/Object;)V
l2	areturn
  Labels:
   	l1 = 12 // new
   	l2 = 32 // areturn
  LocalVariableTable: 
   Start  Length  Slot  Name   Signature
   0      33      0    this       Lscala/collection/immutable/Set$Set3;
   0      33      1    elem       Ljava/lang/Object;

  Signature: length = 0x2
   01 0F 

public scala.collection.Iterator iterator();
  Signature: ()Lscala/collection/Iterator;
  Code:
   Stack=6, Locals=1, Args_size=1
	getstatic	Field scala/collection/Iterator$.MODULE$:Lscala/collection/Iterator$;
	getstatic	Field scala/Predef$.MODULE$:Lscala/Predef$;
	iconst_3
	anewarray	class java/lang/Object
	dup
	iconst_0
	aload_0
	getfield	Field elem1:Ljava/lang/Object;
	aastore
	dup
	iconst_1
	aload_0
	getfield	Field elem2:Ljava/lang/Object;
	aastore
	dup
	iconst_2
	aload_0
	getfield	Field elem3:Ljava/lang/Object;
	aastore
	invokevirtual	Method scala/Predef$.genericWrapArray:(Ljava/lang/Object;)Lscala/collection/mutable/WrappedArray;
	invokevirtual	Method scala/collection/Iterator$.apply:(Lscala/collection/Seq;)Lscala/collection/Iterator;
	areturn
  Labels:
  Signature: length = 0x2
   00 FFFFFFBB 

public void foreach(scala.Function1);
  Signature: (Lscala/Function1;)V
  Code:
   Stack=2, Locals=2, Args_size=2
	aload_1
	aload_0
	getfield	Field elem1:Ljava/lang/Object;
	invokeinterface	InterfaceMethod scala/Function1.apply:(Ljava/lang/Object;)Ljava/lang/Object;
	pop
	aload_1
	aload_0
	getfield	Field elem2:Ljava/lang/Object;
	invokeinterface	InterfaceMethod scala/Function1.apply:(Ljava/lang/Object;)Ljava/lang/Object;
	pop
	aload_1
	aload_0
	getfield	Field elem3:Ljava/lang/Object;
	invokeinterface	InterfaceMethod scala/Function1.apply:(Ljava/lang/Object;)Ljava/lang/Object;
	pop
	return
  Labels:
  LocalVariableTable: 
   Start  Length  Slot  Name   Signature
   0      34      0    this       Lscala/collection/immutable/Set$Set3;
   0      34      1    f       Lscala/Function1;

  Signature: length = 0x2
   01 14 

public scala.collection.generic.Addable repr();
  Signature: ()Lscala/collection/generic/Addable;
  Code:
   Stack=1, Locals=1, Args_size=1
	aload_0
	invokeinterface	InterfaceMethod scala/collection/TraversableLike.repr:()Ljava/lang/Object;
	checkcast	class scala/collection/generic/Addable
	areturn
  Labels:

public java.lang.Object apply(java.lang.Object);
  Signature: (Ljava/lang/Object;)Ljava/lang/Object;
  Code:
   Stack=2, Locals=3, Args_size=2
	aload_0
	aload_1
	invokeinterface	InterfaceMethod scala/collection/SetLike.apply:(Ljava/lang/Object;)Z
	istore_2
	iload_2
	invokestatic	Method scala/runtime/BoxesRunTime.boxToBoolean:(Z)Ljava/lang/Boolean;
	areturn
  Labels:
  LocalVariableTable: 
   Start  Length  Slot  Name   Signature
   0      13      0    this       Lscala/collection/immutable/Set$Set3;
   0      13      1    v1       Ljava/lang/Object;


public scala.collection.generic.Addable $plus(java.lang.Object);
  Signature: (Ljava/lang/Object;)Lscala/collection/generic/Addable;
  Code:
   Stack=2, Locals=2, Args_size=2
	aload_0
	aload_1
	invokevirtual	Method $plus:(Ljava/lang/Object;)Lscala/collection/immutable/Set;
	areturn
  Labels:
  LocalVariableTable: 
   Start  Length  Slot  Name   Signature
   0      6      0    this       Lscala/collection/immutable/Set$Set3;
   0      6      1    elem       Ljava/lang/Object;


public scala.collection.immutable.Set$Set3(java.lang.Object, java.lang.Object, java.lang.Object);
  Signature: (Ljava/lang/Object;Ljava/lang/Object;Ljava/lang/Object;)V
  Code:
   Stack=2, Locals=4, Args_size=4
	aload_0
	aload_1
	putfield	Field elem1:Ljava/lang/Object;
	aload_0
	aload_2
	putfield	Field elem2:Ljava/lang/Object;
	aload_0
	aload_3
	putfield	Field elem3:Ljava/lang/Object;
	aload_0
	invokespecial	Method java/lang/Object."<init>":()V
	aload_0
	invokestatic	Method scala/collection/TraversableOnce$class.$init$:(Lscala/collection/TraversableOnce;)V
	aload_0
	invokestatic	Method scala/collection/TraversableLike$class.$init$:(Lscala/collection/TraversableLike;)V
	aload_0
	invokestatic	Method scala/collection/generic/GenericTraversableTemplate$class.$init$:(Lscala/collection/generic/GenericTraversableTemplate;)V
	aload_0
	invokestatic	Method scala/collection/Traversable$class.$init$:(Lscala/collection/Traversable;)V
	aload_0
	invokestatic	Method scala/collection/immutable/Traversable$class.$init$:(Lscala/collection/immutable/Traversable;)V
	aload_0
	invokestatic	Method scala/collection/IterableLike$class.$init$:(Lscala/collection/IterableLike;)V
	aload_0
	invokestatic	Method scala/collection/Iterable$class.$init$:(Lscala/collection/Iterable;)V
	aload_0
	invokestatic	Method scala/collection/immutable/Iterable$class.$init$:(Lscala/collection/immutable/Iterable;)V
	aload_0
	invokestatic	Method scala/Function1$class.$init$:(Lscala/Function1;)V
	aload_0
	invokestatic	Method scala/collection/generic/GenericSetTemplate$class.$init$:(Lscala/collection/generic/GenericSetTemplate;)V
	aload_0
	invokestatic	Method scala/collection/generic/Addable$class.$init$:(Lscala/collection/generic/Addable;)V
	aload_0
	invokestatic	Method scala/collection/generic/Subtractable$class.$init$:(Lscala/collection/generic/Subtractable;)V
	aload_0
	invokestatic	Method scala/collection/SetLike$class.$init$:(Lscala/collection/SetLike;)V
	aload_0
	invokestatic	Method scala/collection/Set$class.$init$:(Lscala/collection/Set;)V
	aload_0
	invokestatic	Method scala/collection/immutable/Set$class.$init$:(Lscala/collection/immutable/Set;)V
	return
  Labels:
  LocalVariableTable: 
   Start  Length  Slot  Name   Signature
   0      80      0    this       Lscala/collection/immutable/Set$Set3;
   0      80      1    elem1       Ljava/lang/Object;
   0      80      2    elem2       Ljava/lang/Object;
   0      80      3    elem3       Ljava/lang/Object;

  Signature: length = 0x2
   01 11 

}

