Compiled from "SortedSet.scala"
public abstract class scala.collection.immutable.SortedSet$class extends java.lang.Object
  SourceFile: "SortedSet.scala"
  Scala: length = 0x
   
  minor version: 0
  major version: 49
  Constant pool:
const #1 = Asciz	SourceFile;
const #2 = Asciz	SortedSet.scala;
const #3 = Asciz	$init$;
const #4 = Asciz	(Lscala/collection/immutable/SortedSet;)V;
const #5 = Asciz	Code;
const #6 = Asciz	LineNumberTable;
const #7 = Asciz	$this;
const #8 = Asciz	Lscala/collection/immutable/SortedSet;;
const #9 = Asciz	LocalVariableTable;
const #10 = Asciz	empty;
const #11 = Asciz	(Lscala/collection/immutable/SortedSet;)Lscala/collection/immutable/SortedSet;;
const #12 = Asciz	scala/collection/immutable/SortedSet$;
const #13 = class	#12;	//  scala/collection/immutable/SortedSet$
const #14 = Asciz	MODULE$;
const #15 = Asciz	Lscala/collection/immutable/SortedSet$;;
const #16 = NameAndType	#14:#15;//  MODULE$:Lscala/collection/immutable/SortedSet$;
const #17 = Field	#13.#16;	//  scala/collection/immutable/SortedSet$.MODULE$:Lscala/collection/immutable/SortedSet$;
const #18 = Asciz	scala/collection/SortedSetLike;
const #19 = class	#18;	//  scala/collection/SortedSetLike
const #20 = Asciz	ordering;
const #21 = Asciz	()Lscala/math/Ordering;;
const #22 = NameAndType	#20:#21;//  ordering:()Lscala/math/Ordering;
const #23 = InterfaceMethod	#19.#22;	//  scala/collection/SortedSetLike.ordering:()Lscala/math/Ordering;
const #24 = Asciz	(Lscala/math/Ordering;)Lscala/collection/immutable/SortedSet;;
const #25 = NameAndType	#10:#24;//  empty:(Lscala/math/Ordering;)Lscala/collection/immutable/SortedSet;
const #26 = Method	#13.#25;	//  scala/collection/immutable/SortedSet$.empty:(Lscala/math/Ordering;)Lscala/collection/immutable/SortedSet;
const #27 = Asciz	Scala;
const #28 = Asciz	scala/collection/immutable/SortedSet$class;
const #29 = class	#28;	//  scala/collection/immutable/SortedSet$class
const #30 = Asciz	java/lang/Object;
const #31 = class	#30;	//  java/lang/Object

{
public static void $init$(scala.collection.immutable.SortedSet);
  Code:
   Stack=0, Locals=1, Args_size=1
   0:	return
  LineNumberTable: 
   line 25: 0

  LocalVariableTable: 
   Start  Length  Slot  Name   Signature
   0      1      0    $this       Lscala/collection/immutable/SortedSet;


public static scala.collection.immutable.SortedSet empty(scala.collection.immutable.SortedSet);
  Code:
   Stack=2, Locals=1, Args_size=1
   0:	getstatic	#17; //Field scala/collection/immutable/SortedSet$.MODULE$:Lscala/collection/immutable/SortedSet$;
   3:	aload_0
   4:	invokeinterface	#23,  1; //InterfaceMethod scala/collection/SortedSetLike.ordering:()Lscala/math/Ordering;
   9:	invokevirtual	#26; //Method scala/collection/immutable/SortedSet$.empty:(Lscala/math/Ordering;)Lscala/collection/immutable/SortedSet;
   12:	areturn
  LineNumberTable: 
   line 27: 0

  LocalVariableTable: 
   Start  Length  Slot  Name   Signature
   0      13      0    $this       Lscala/collection/immutable/SortedSet;


}

