Compiled from "SortedMap.scala"
public final class scala.collection.immutable.SortedMap$$anonfun$$plus$plus$1 extends java.lang.Object implements scala.Function2,scala.ScalaObject,java.io.Serializable
  SourceFile: "SortedMap.scala"
  Scala: length = 0x
   
  InnerClass: 
   public final $anonfun$$plus$plus$1=class scala/collection/immutable/SortedMap$$anonfun$$plus$plus$1 of class scala/collection/immutable/SortedMap
  minor version: 0
  major version: 49
  Constant pool:
Asciz	SourceFile;
Asciz	SortedMap.scala;
Asciz	<clinit>;
Asciz	()V;
Asciz	Code;
Asciz	serialVersionUID;
Asciz	J;
Asciz	scala/collection/immutable/SortedMap$$anonfun$$plus$plus$1;
class	scala/collection/immutable/SortedMap$$anonfun$$plus$plus$1
NameAndType	serialVersionUID:J
Field	scala/collection/immutable/SortedMap$$anonfun$$plus$plus$1.serialVersionUID:J
Asciz	<init>;
Asciz	(Lscala/collection/immutable/SortedMap;)V;
Asciz	LineNumberTable;
Asciz	java/lang/Object;
class	java/lang/Object
NameAndType	"<init>":()V
Method	java/lang/Object."<init>":()V
Asciz	scala/Function2$class;
class	scala/Function2$class
Asciz	$init$;
Asciz	(Lscala/Function2;)V;
NameAndType	$init$:(Lscala/Function2;)V
Method	scala/Function2$class.$init$:(Lscala/Function2;)V
Asciz	this;
Asciz	Lscala/collection/immutable/SortedMap$$anonfun$$plus$plus$1;;
Asciz	$outer;
Asciz	Lscala/collection/immutable/SortedMap;;
Asciz	LocalVariableTable;
Asciz	(Lscala/collection/immutable/SortedMap<TA;TB;>;)V;
Asciz	Signature;
Asciz	apply;
Asciz	(Ljava/lang/Object;Ljava/lang/Object;)Ljava/lang/Object;;
Asciz	scala/collection/immutable/SortedMap;
class	scala/collection/immutable/SortedMap
Asciz	scala/Tuple2;
class	scala/Tuple2
Asciz	(Lscala/collection/immutable/SortedMap;Lscala/Tuple2;)Lscala/collection/immutable/SortedMap;;
NameAndType	apply:(Lscala/collection/immutable/SortedMap;Lscala/Tuple2;)Lscala/collection/immutable/SortedMap;
Method	scala/collection/immutable/SortedMap$$anonfun$$plus$plus$1.apply:(Lscala/collection/immutable/SortedMap;Lscala/Tuple2;)Lscala/collection/immutable/SortedMap;
Asciz	v1;
Asciz	Ljava/lang/Object;;
Asciz	v2;
Asciz	$plus;
Asciz	(Lscala/Tuple2;)Lscala/collection/immutable/SortedMap;;
NameAndType	$plus:(Lscala/Tuple2;)Lscala/collection/immutable/SortedMap;
InterfaceMethod	scala/collection/immutable/SortedMap.$plus:(Lscala/Tuple2;)Lscala/collection/immutable/SortedMap;
Asciz	(Lscala/collection/immutable/SortedMap<TA;TB1;>;Lscala/Tuple2<TA;TB1;>;)Lscala/collection/immutable/SortedMap<TA;TB1;>;;
Asciz	curry;
Asciz	()Lscala/Function1;;
Asciz	(Lscala/Function2;)Lscala/Function1;;
NameAndType	curry:(Lscala/Function2;)Lscala/Function1;
Method	scala/Function2$class.curry:(Lscala/Function2;)Lscala/Function1;
Asciz	toString;
Asciz	()Ljava/lang/String;;
Asciz	(Lscala/Function2;)Ljava/lang/String;;
NameAndType	toString:(Lscala/Function2;)Ljava/lang/String;
Method	scala/Function2$class.toString:(Lscala/Function2;)Ljava/lang/String;
Asciz	Scala;
Asciz	InnerClasses;
Asciz	$anonfun$$plus$plus$1;
Asciz	scala/Function2;
class	scala/Function2
Asciz	scala/ScalaObject;
class	scala/ScalaObject
Asciz	java/io/Serializable;
class	java/io/Serializable

{
public static final long serialVersionUID;
  Signature: J

public static {};
  Signature: ()V
  Code:
   Stack=2, Locals=0, Args_size=0
	lconst_0
	putstatic	Field serialVersionUID:J
	return
  Labels:

public scala.collection.immutable.SortedMap$$anonfun$$plus$plus$1(scala.collection.immutable.SortedMap);
  Signature: (Lscala/collection/immutable/SortedMap;)V
  Code:
   Stack=1, Locals=2, Args_size=2
	aload_0
	invokespecial	Method java/lang/Object."<init>":()V
	aload_0
	invokestatic	Method scala/Function2$class.$init$:(Lscala/Function2;)V
	return
  Labels:
  LocalVariableTable: 
   Start  Length  Slot  Name   Signature
   0      9      0    this       Lscala/collection/immutable/SortedMap$$anonfun$$plus$plus$1;
   0      9      1    $outer       Lscala/collection/immutable/SortedMap;

  Signature: length = 0x2
   00 1E 

public final java.lang.Object apply(java.lang.Object, java.lang.Object);
  Signature: (Ljava/lang/Object;Ljava/lang/Object;)Ljava/lang/Object;
  Code:
   Stack=3, Locals=3, Args_size=3
	aload_0
	aload_1
	checkcast	class scala/collection/immutable/SortedMap
	aload_2
	checkcast	class scala/Tuple2
	invokevirtual	Method apply:(Lscala/collection/immutable/SortedMap;Lscala/Tuple2;)Lscala/collection/immutable/SortedMap;
	areturn
  Labels:
  LocalVariableTable: 
   Start  Length  Slot  Name   Signature
   0      13      0    this       Lscala/collection/immutable/SortedMap$$anonfun$$plus$plus$1;
   0      13      1    v1       Ljava/lang/Object;
   0      13      2    v2       Ljava/lang/Object;


public final scala.collection.immutable.SortedMap apply(scala.collection.immutable.SortedMap, scala.Tuple2);
  Signature: (Lscala/collection/immutable/SortedMap;Lscala/Tuple2;)Lscala/collection/immutable/SortedMap;
  Code:
   Stack=2, Locals=3, Args_size=3
	aload_1
	aload_2
	invokeinterface	InterfaceMethod scala/collection/immutable/SortedMap.$plus:(Lscala/Tuple2;)Lscala/collection/immutable/SortedMap;
	areturn
  Labels:
  Signature: length = 0x2
   00 30 

public scala.Function1 curry();
  Signature: ()Lscala/Function1;
  Code:
   Stack=1, Locals=1, Args_size=1
	aload_0
	invokestatic	Method scala/Function2$class.curry:(Lscala/Function2;)Lscala/Function1;
	areturn
  Labels:

public java.lang.String toString();
  Signature: ()Ljava/lang/String;
  Code:
   Stack=1, Locals=1, Args_size=1
	aload_0
	invokestatic	Method scala/Function2$class.toString:(Lscala/Function2;)Ljava/lang/String;
	areturn
  Labels:

}

