Compiled from "SortedMap.scala"
public abstract class scala.collection.immutable.SortedMap$class extends java.lang.Object
  SourceFile: "SortedMap.scala"
  Scala: length = 0x
   
  InnerClass: 
   public final #90= #35 of #19; //$anonfun$$plus$plus$1=class scala/collection/immutable/SortedMap$$anonfun$$plus$plus$1 of class scala/collection/immutable/SortedMap
   public final #91= #21 of #19; //$anonfun$$plus$plus$2=class scala/collection/immutable/SortedMap$$anonfun$$plus$plus$2 of class scala/collection/immutable/SortedMap
  minor version: 0
  major version: 49
  Constant pool:
const #1 = Asciz	SourceFile;
const #2 = Asciz	SortedMap.scala;
const #3 = Asciz	$init$;
const #4 = Asciz	(Lscala/collection/immutable/SortedMap;)V;
const #5 = Asciz	Code;
const #6 = Asciz	LineNumberTable;
const #7 = Asciz	$this;
const #8 = Asciz	Lscala/collection/immutable/SortedMap;;
const #9 = Asciz	LocalVariableTable;
const #10 = Asciz	$plus$plus;
const #11 = Asciz	(Lscala/collection/immutable/SortedMap;Lscala/collection/Iterator;)Lscala/collection/immutable/SortedMap;;
const #12 = Asciz	scala/collection/TraversableLike;
const #13 = class	#12;	//  scala/collection/TraversableLike
const #14 = Asciz	repr;
const #15 = Asciz	()Ljava/lang/Object;;
const #16 = NameAndType	#14:#15;//  repr:()Ljava/lang/Object;
const #17 = InterfaceMethod	#13.#16;	//  scala/collection/TraversableLike.repr:()Ljava/lang/Object;
const #18 = Asciz	scala/collection/immutable/SortedMap;
const #19 = class	#18;	//  scala/collection/immutable/SortedMap
const #20 = Asciz	scala/collection/immutable/SortedMap$$anonfun$$plus$plus$2;
const #21 = class	#20;	//  scala/collection/immutable/SortedMap$$anonfun$$plus$plus$2
const #22 = Asciz	<init>;
const #23 = NameAndType	#22:#4;//  "<init>":(Lscala/collection/immutable/SortedMap;)V
const #24 = Method	#21.#23;	//  scala/collection/immutable/SortedMap$$anonfun$$plus$plus$2."<init>":(Lscala/collection/immutable/SortedMap;)V
const #25 = Asciz	scala/collection/Iterator;
const #26 = class	#25;	//  scala/collection/Iterator
const #27 = Asciz	$div$colon;
const #28 = Asciz	(Ljava/lang/Object;Lscala/Function2;)Ljava/lang/Object;;
const #29 = NameAndType	#27:#28;//  $div$colon:(Ljava/lang/Object;Lscala/Function2;)Ljava/lang/Object;
const #30 = InterfaceMethod	#26.#29;	//  scala/collection/Iterator.$div$colon:(Ljava/lang/Object;Lscala/Function2;)Ljava/lang/Object;
const #31 = Asciz	iter;
const #32 = Asciz	Lscala/collection/Iterator;;
const #33 = Asciz	(Lscala/collection/immutable/SortedMap;Lscala/collection/Traversable;)Lscala/collection/immutable/SortedMap;;
const #34 = Asciz	scala/collection/immutable/SortedMap$$anonfun$$plus$plus$1;
const #35 = class	#34;	//  scala/collection/immutable/SortedMap$$anonfun$$plus$plus$1
const #36 = Method	#35.#23;	//  scala/collection/immutable/SortedMap$$anonfun$$plus$plus$1."<init>":(Lscala/collection/immutable/SortedMap;)V
const #37 = InterfaceMethod	#13.#29;	//  scala/collection/TraversableLike.$div$colon:(Ljava/lang/Object;Lscala/Function2;)Ljava/lang/Object;
const #38 = Asciz	elems;
const #39 = Asciz	Lscala/collection/Traversable;;
const #40 = Asciz	$plus;
const #41 = Asciz	(Lscala/collection/immutable/SortedMap;Lscala/Tuple2;Lscala/Tuple2;Lscala/collection/Seq;)Lscala/collection/immutable/SortedMap;;
const #42 = Asciz	(Lscala/Tuple2;)Lscala/collection/immutable/SortedMap;;
const #43 = NameAndType	#40:#42;//  $plus:(Lscala/Tuple2;)Lscala/collection/immutable/SortedMap;
const #44 = InterfaceMethod	#19.#43;	//  scala/collection/immutable/SortedMap.$plus:(Lscala/Tuple2;)Lscala/collection/immutable/SortedMap;
const #45 = Asciz	(Lscala/collection/Traversable;)Lscala/collection/immutable/SortedMap;;
const #46 = NameAndType	#10:#45;//  $plus$plus:(Lscala/collection/Traversable;)Lscala/collection/immutable/SortedMap;
const #47 = InterfaceMethod	#19.#46;	//  scala/collection/immutable/SortedMap.$plus$plus:(Lscala/collection/Traversable;)Lscala/collection/immutable/SortedMap;
const #48 = Asciz	elem1;
const #49 = Asciz	Lscala/Tuple2;;
const #50 = Asciz	elem2;
const #51 = Asciz	Lscala/collection/Seq;;
const #52 = Asciz	(Lscala/collection/immutable/SortedMap;Lscala/Tuple2;)Lscala/collection/immutable/SortedMap;;
const #53 = Asciz	java/lang/AbstractMethodError;
const #54 = class	#53;	//  java/lang/AbstractMethodError
const #55 = Asciz	SortedMap.+;
const #56 = String	#55;	//  SortedMap.+
const #57 = Asciz	(Ljava/lang/String;)V;
const #58 = NameAndType	#22:#57;//  "<init>":(Ljava/lang/String;)V
const #59 = Method	#54.#58;	//  java/lang/AbstractMethodError."<init>":(Ljava/lang/String;)V
const #60 = Asciz	kv;
const #61 = Asciz	updated;
const #62 = Asciz	(Lscala/collection/immutable/SortedMap;Ljava/lang/Object;Ljava/lang/Object;)Lscala/collection/immutable/SortedMap;;
const #63 = Asciz	scala/Tuple2;
const #64 = class	#63;	//  scala/Tuple2
const #65 = Asciz	(Ljava/lang/Object;Ljava/lang/Object;)V;
const #66 = NameAndType	#22:#65;//  "<init>":(Ljava/lang/Object;Ljava/lang/Object;)V
const #67 = Method	#64.#66;	//  scala/Tuple2."<init>":(Ljava/lang/Object;Ljava/lang/Object;)V
const #68 = Asciz	key;
const #69 = Asciz	Ljava/lang/Object;;
const #70 = Asciz	value;
const #71 = Asciz	newBuilder;
const #72 = Asciz	(Lscala/collection/immutable/SortedMap;)Lscala/collection/mutable/Builder;;
const #73 = Asciz	scala/collection/immutable/SortedMap$;
const #74 = class	#73;	//  scala/collection/immutable/SortedMap$
const #75 = Asciz	MODULE$;
const #76 = Asciz	Lscala/collection/immutable/SortedMap$;;
const #77 = NameAndType	#75:#76;//  MODULE$:Lscala/collection/immutable/SortedMap$;
const #78 = Field	#74.#77;	//  scala/collection/immutable/SortedMap$.MODULE$:Lscala/collection/immutable/SortedMap$;
const #79 = Asciz	scala/collection/SortedMapLike;
const #80 = class	#79;	//  scala/collection/SortedMapLike
const #81 = Asciz	ordering;
const #82 = Asciz	()Lscala/math/Ordering;;
const #83 = NameAndType	#81:#82;//  ordering:()Lscala/math/Ordering;
const #84 = InterfaceMethod	#80.#83;	//  scala/collection/SortedMapLike.ordering:()Lscala/math/Ordering;
const #85 = Asciz	(Lscala/math/Ordering;)Lscala/collection/mutable/Builder;;
const #86 = NameAndType	#71:#85;//  newBuilder:(Lscala/math/Ordering;)Lscala/collection/mutable/Builder;
const #87 = Method	#74.#86;	//  scala/collection/immutable/SortedMap$.newBuilder:(Lscala/math/Ordering;)Lscala/collection/mutable/Builder;
const #88 = Asciz	Scala;
const #89 = Asciz	InnerClasses;
const #90 = Asciz	$anonfun$$plus$plus$1;
const #91 = Asciz	$anonfun$$plus$plus$2;
const #92 = Asciz	scala/collection/immutable/SortedMap$class;
const #93 = class	#92;	//  scala/collection/immutable/SortedMap$class
const #94 = Asciz	java/lang/Object;
const #95 = class	#94;	//  java/lang/Object

{
public static void $init$(scala.collection.immutable.SortedMap);
  Code:
   Stack=0, Locals=1, Args_size=1
   0:	return
  LineNumberTable: 
   line 26: 0

  LocalVariableTable: 
   Start  Length  Slot  Name   Signature
   0      1      0    $this       Lscala/collection/immutable/SortedMap;


public static scala.collection.immutable.SortedMap $plus$plus(scala.collection.immutable.SortedMap, scala.collection.Iterator);
  Code:
   Stack=5, Locals=3, Args_size=2
   0:	aload_0
   1:	invokeinterface	#17,  1; //InterfaceMethod scala/collection/TraversableLike.repr:()Ljava/lang/Object;
   6:	checkcast	#19; //class scala/collection/immutable/SortedMap
   9:	astore_2
   10:	aload_1
   11:	aload_2
   12:	new	#21; //class scala/collection/immutable/SortedMap$$anonfun$$plus$plus$2
   15:	dup
   16:	aload_0
   17:	invokespecial	#24; //Method scala/collection/immutable/SortedMap$$anonfun$$plus$plus$2."<init>":(Lscala/collection/immutable/SortedMap;)V
   20:	invokeinterface	#30,  3; //InterfaceMethod scala/collection/Iterator.$div$colon:(Ljava/lang/Object;Lscala/Function2;)Ljava/lang/Object;
   25:	checkcast	#19; //class scala/collection/immutable/SortedMap
   28:	areturn
  LineNumberTable: 
   line 68: 0

  LocalVariableTable: 
   Start  Length  Slot  Name   Signature
   0      29      0    $this       Lscala/collection/immutable/SortedMap;
   0      29      1    iter       Lscala/collection/Iterator;


public static scala.collection.immutable.SortedMap $plus$plus(scala.collection.immutable.SortedMap, scala.collection.Traversable);
  Code:
   Stack=5, Locals=3, Args_size=2
   0:	aload_0
   1:	invokeinterface	#17,  1; //InterfaceMethod scala/collection/TraversableLike.repr:()Ljava/lang/Object;
   6:	checkcast	#19; //class scala/collection/immutable/SortedMap
   9:	astore_2
   10:	aload_1
   11:	aload_2
   12:	new	#35; //class scala/collection/immutable/SortedMap$$anonfun$$plus$plus$1
   15:	dup
   16:	aload_0
   17:	invokespecial	#36; //Method scala/collection/immutable/SortedMap$$anonfun$$plus$plus$1."<init>":(Lscala/collection/immutable/SortedMap;)V
   20:	invokeinterface	#37,  3; //InterfaceMethod scala/collection/TraversableLike.$div$colon:(Ljava/lang/Object;Lscala/Function2;)Ljava/lang/Object;
   25:	checkcast	#19; //class scala/collection/immutable/SortedMap
   28:	areturn
  LineNumberTable: 
   line 60: 0

  LocalVariableTable: 
   Start  Length  Slot  Name   Signature
   0      29      0    $this       Lscala/collection/immutable/SortedMap;
   0      29      1    elems       Lscala/collection/Traversable;


public static scala.collection.immutable.SortedMap $plus(scala.collection.immutable.SortedMap, scala.Tuple2, scala.Tuple2, scala.collection.Seq);
  Code:
   Stack=2, Locals=4, Args_size=4
   0:	aload_0
   1:	aload_1
   2:	invokeinterface	#44,  2; //InterfaceMethod scala/collection/immutable/SortedMap.$plus:(Lscala/Tuple2;)Lscala/collection/immutable/SortedMap;
   7:	aload_2
   8:	invokeinterface	#44,  2; //InterfaceMethod scala/collection/immutable/SortedMap.$plus:(Lscala/Tuple2;)Lscala/collection/immutable/SortedMap;
   13:	aload_3
   14:	invokeinterface	#47,  2; //InterfaceMethod scala/collection/immutable/SortedMap.$plus$plus:(Lscala/collection/Traversable;)Lscala/collection/immutable/SortedMap;
   19:	areturn
  LineNumberTable: 
   line 52: 0

  LocalVariableTable: 
   Start  Length  Slot  Name   Signature
   0      20      0    $this       Lscala/collection/immutable/SortedMap;
   0      20      1    elem1       Lscala/Tuple2;
   0      20      2    elem2       Lscala/Tuple2;
   0      20      3    elems       Lscala/collection/Seq;


public static scala.collection.immutable.SortedMap $plus(scala.collection.immutable.SortedMap, scala.Tuple2);
  Code:
   Stack=3, Locals=2, Args_size=2
   0:	new	#54; //class java/lang/AbstractMethodError
   3:	dup
   4:	ldc	#56; //String SortedMap.+
   6:	invokespecial	#59; //Method java/lang/AbstractMethodError."<init>":(Ljava/lang/String;)V
   9:	athrow
  LineNumberTable: 
   line 42: 0

  LocalVariableTable: 
   Start  Length  Slot  Name   Signature
   0      10      0    $this       Lscala/collection/immutable/SortedMap;
   0      10      1    kv       Lscala/Tuple2;


public static scala.collection.immutable.SortedMap updated(scala.collection.immutable.SortedMap, java.lang.Object, java.lang.Object);
  Code:
   Stack=5, Locals=3, Args_size=3
   0:	aload_0
   1:	new	#64; //class scala/Tuple2
   4:	dup
   5:	aload_1
   6:	aload_2
   7:	invokespecial	#67; //Method scala/Tuple2."<init>":(Ljava/lang/Object;Ljava/lang/Object;)V
   10:	invokeinterface	#44,  2; //InterfaceMethod scala/collection/immutable/SortedMap.$plus:(Lscala/Tuple2;)Lscala/collection/immutable/SortedMap;
   15:	areturn
  LineNumberTable: 
   line 34: 0

  LocalVariableTable: 
   Start  Length  Slot  Name   Signature
   0      16      0    $this       Lscala/collection/immutable/SortedMap;
   0      16      1    key       Ljava/lang/Object;
   0      16      2    value       Ljava/lang/Object;


public static scala.collection.mutable.Builder newBuilder(scala.collection.immutable.SortedMap);
  Code:
   Stack=2, Locals=1, Args_size=1
   0:	getstatic	#78; //Field scala/collection/immutable/SortedMap$.MODULE$:Lscala/collection/immutable/SortedMap$;
   3:	aload_0
   4:	invokeinterface	#84,  1; //InterfaceMethod scala/collection/SortedMapLike.ordering:()Lscala/math/Ordering;
   9:	invokevirtual	#87; //Method scala/collection/immutable/SortedMap$.newBuilder:(Lscala/math/Ordering;)Lscala/collection/mutable/Builder;
   12:	areturn
  LineNumberTable: 
   line 32: 0

  LocalVariableTable: 
   Start  Length  Slot  Name   Signature
   0      13      0    $this       Lscala/collection/immutable/SortedMap;


}

