Compiled from "Stack.scala"
public class scala.collection.immutable.Stack$Node extends scala.collection.immutable.Stack implements scala.ScalaObject,java.io.Serializable
  SourceFile: "Stack.scala"
  Signature: length = 0x2
   00 35 
  Scala: length = 0x
   
  InnerClass: 
   public #56= #14 of #25; //Node=class scala/collection/immutable/Stack$Node of class scala/collection/immutable/Stack
  minor version: 0
  major version: 49
  Constant pool:
const #1 = Asciz	SourceFile;
const #2 = Asciz	Stack.scala;
const #3 = Asciz	$outer;
const #4 = Asciz	Lscala/collection/immutable/Stack;;
const #5 = Asciz	elem;
const #6 = Asciz	Ljava/lang/Object;;
const #7 = Asciz	TB;;
const #8 = Asciz	Signature;
const #9 = Asciz	<init>;
const #10 = Asciz	(Lscala/collection/immutable/Stack;Ljava/lang/Object;)V;
const #11 = Asciz	Code;
const #12 = Asciz	LineNumberTable;
const #13 = Asciz	scala/collection/immutable/Stack$Node;
const #14 = class	#13;	//  scala/collection/immutable/Stack$Node
const #15 = NameAndType	#5:#6;//  elem:Ljava/lang/Object;
const #16 = Field	#14.#15;	//  scala/collection/immutable/Stack$Node.elem:Ljava/lang/Object;
const #17 = Asciz	java/lang/NullPointerException;
const #18 = class	#17;	//  java/lang/NullPointerException
const #19 = Asciz	()V;
const #20 = NameAndType	#9:#19;//  "<init>":()V
const #21 = Method	#18.#20;	//  java/lang/NullPointerException."<init>":()V
const #22 = NameAndType	#3:#4;//  $outer:Lscala/collection/immutable/Stack;
const #23 = Field	#14.#22;	//  scala/collection/immutable/Stack$Node.$outer:Lscala/collection/immutable/Stack;
const #24 = Asciz	scala/collection/immutable/Stack;
const #25 = class	#24;	//  scala/collection/immutable/Stack
const #26 = Method	#25.#20;	//  scala/collection/immutable/Stack."<init>":()V
const #27 = Asciz	this;
const #28 = Asciz	Lscala/collection/immutable/Stack$Node;;
const #29 = Asciz	LocalVariableTable;
const #30 = Asciz	(Lscala/collection/immutable/Stack<TA;>;TB;)V;
const #31 = Asciz	scala$collection$immutable$Stack$Node$$$outer;
const #32 = Asciz	()Lscala/collection/immutable/Stack;;
const #33 = Asciz	hashCode;
const #34 = Asciz	()I;
const #35 = Asciz	java/lang/Object;
const #36 = class	#35;	//  java/lang/Object
const #37 = NameAndType	#33:#34;//  hashCode:()I
const #38 = Method	#36.#37;	//  java/lang/Object.hashCode:()I
const #39 = int	37;
const #40 = NameAndType	#31:#32;//  scala$collection$immutable$Stack$Node$$$outer:()Lscala/collection/immutable/Stack;
const #41 = Method	#14.#40;	//  scala/collection/immutable/Stack$Node.scala$collection$immutable$Stack$Node$$$outer:()Lscala/collection/immutable/Stack;
const #42 = Method	#25.#37;	//  scala/collection/immutable/Stack.hashCode:()I
const #43 = Asciz	pop;
const #44 = Asciz	()Lscala/collection/immutable/Stack<TB;>;;
const #45 = Asciz	top;
const #46 = Asciz	()Ljava/lang/Object;;
const #47 = Asciz	()TB;;
const #48 = Asciz	length;
const #49 = NameAndType	#48:#34;//  length:()I
const #50 = Method	#25.#49;	//  scala/collection/immutable/Stack.length:()I
const #51 = Asciz	isEmpty;
const #52 = Asciz	()Z;
const #53 = Asciz	<B:Ljava/lang/Object;>Lscala/collection/immutable/Stack<TB;>;Lscala/ScalaObject;;
const #54 = Asciz	Scala;
const #55 = Asciz	InnerClasses;
const #56 = Asciz	Node;
const #57 = Asciz	scala/ScalaObject;
const #58 = class	#57;	//  scala/ScalaObject
const #59 = Asciz	java/io/Serializable;
const #60 = class	#59;	//  java/io/Serializable

{
public final scala.collection.immutable.Stack $outer;

public scala.collection.immutable.Stack$Node(scala.collection.immutable.Stack, java.lang.Object);
  Code:
   Stack=2, Locals=3, Args_size=3
   0:	aload_0
   1:	aload_2
   2:	putfield	#16; //Field elem:Ljava/lang/Object;
   5:	aload_1
   6:	ifnonnull	17
   9:	new	#18; //class java/lang/NullPointerException
   12:	dup
   13:	invokespecial	#21; //Method java/lang/NullPointerException."<init>":()V
   16:	athrow
   17:	aload_0
   18:	aload_1
   19:	putfield	#23; //Field $outer:Lscala/collection/immutable/Stack;
   22:	aload_0
   23:	invokespecial	#26; //Method scala/collection/immutable/Stack."<init>":()V
   26:	return
  LineNumberTable: 
   line 126: 0

  LocalVariableTable: 
   Start  Length  Slot  Name   Signature
   0      27      0    this       Lscala/collection/immutable/Stack$Node;
   0      27      1    $outer       Lscala/collection/immutable/Stack;
   0      27      2    elem       Ljava/lang/Object;

  Signature: length = 0x2
   00 1E 

public scala.collection.immutable.Stack scala$collection$immutable$Stack$Node$$$outer();
  Code:
   Stack=1, Locals=1, Args_size=1
   0:	aload_0
   1:	getfield	#23; //Field $outer:Lscala/collection/immutable/Stack;
   4:	areturn
  LineNumberTable: 
   line 126: 0


public int hashCode();
  Code:
   Stack=2, Locals=1, Args_size=1
   0:	aload_0
   1:	getfield	#16; //Field elem:Ljava/lang/Object;
   4:	invokevirtual	#38; //Method java/lang/Object.hashCode:()I
   7:	ldc	#39; //int 37
   9:	imul
   10:	aload_0
   11:	invokevirtual	#41; //Method scala$collection$immutable$Stack$Node$$$outer:()Lscala/collection/immutable/Stack;
   14:	invokevirtual	#42; //Method scala/collection/immutable/Stack.hashCode:()I
   17:	iadd
   18:	ireturn
  LineNumberTable: 
   line 131: 0


public scala.collection.immutable.Stack pop();
  Code:
   Stack=1, Locals=1, Args_size=1
   0:	aload_0
   1:	invokevirtual	#41; //Method scala$collection$immutable$Stack$Node$$$outer:()Lscala/collection/immutable/Stack;
   4:	areturn
  LineNumberTable: 
   line 130: 0

  Signature: length = 0x2
   00 2C 

public java.lang.Object top();
  Code:
   Stack=1, Locals=1, Args_size=1
   0:	aload_0
   1:	getfield	#16; //Field elem:Ljava/lang/Object;
   4:	areturn
  LineNumberTable: 
   line 129: 0

  Signature: length = 0x2
   00 2F 

public int length();
  Code:
   Stack=2, Locals=1, Args_size=1
   0:	aload_0
   1:	invokevirtual	#41; //Method scala$collection$immutable$Stack$Node$$$outer:()Lscala/collection/immutable/Stack;
   4:	invokevirtual	#50; //Method scala/collection/immutable/Stack.length:()I
   7:	iconst_1
   8:	iadd
   9:	ireturn
  LineNumberTable: 
   line 128: 0


public boolean isEmpty();
  Code:
   Stack=1, Locals=1, Args_size=1
   0:	iconst_0
   1:	ireturn
  LineNumberTable: 
   line 127: 0


}

