Compiled from "Stack.scala"
public final class scala.collection.immutable.Stack$ extends scala.collection.generic.SeqFactory implements scala.ScalaObject
  SourceFile: "Stack.scala"
  Scala: length = 0x
   
  Signature: length = 0x2
   00 47 
  InnerClass: 
   public final $anonfun$pushAll$2=class scala/collection/immutable/Stack$$anonfun$pushAll$2 of class scala/collection/immutable/Stack
   public final $anonfun$pushAll$1=class scala/collection/immutable/Stack$$anonfun$pushAll$1 of class scala/collection/immutable/Stack
   public final $anonfun$newBuilder$1=class scala/collection/immutable/Stack$$anonfun$newBuilder$1 of class scala/collection/immutable/Stack
   public GenericCanBuildFrom=class scala/collection/generic/TraversableFactory$GenericCanBuildFrom of class scala/collection/generic/TraversableFactory
  minor version: 0
  major version: 49
  Constant pool:
Asciz	SourceFile;
Asciz	Stack.scala;
Asciz	Scala;
Asciz	MODULE$;
Asciz	Lscala/collection/immutable/Stack$;;
Asciz	<clinit>;
Asciz	()V;
Asciz	Code;
Asciz	scala/collection/immutable/Stack$;
class	scala/collection/immutable/Stack$
Asciz	<init>;
NameAndType	"<init>":()V
Method	scala/collection/immutable/Stack$."<init>":()V
Asciz	Empty;
Asciz	Lscala/collection/immutable/Stack;;
Asciz	Lscala/collection/immutable/Stack<Lscala/runtime/Nothing$;>;;
Asciz	Signature;
Asciz	LineNumberTable;
Asciz	scala/collection/generic/SeqFactory;
class	scala/collection/generic/SeqFactory
Method	scala/collection/generic/SeqFactory."<init>":()V
NameAndType	MODULE$:Lscala/collection/immutable/Stack$;
Field	scala/collection/immutable/Stack$.MODULE$:Lscala/collection/immutable/Stack$;
Asciz	scala/Predef$;
class	scala/Predef$
Asciz	Lscala/Predef$;;
NameAndType	MODULE$:Lscala/Predef$;
Field	scala/Predef$.MODULE$:Lscala/Predef$;
Asciz	scala/runtime/Nothing$;
class	scala/runtime/Nothing$
Asciz	[Ljava/lang/Object;;
class	"[Ljava/lang/Object;"
Asciz	genericWrapArray;
Asciz	(Ljava/lang/Object;)Lscala/collection/mutable/WrappedArray;;
NameAndType	genericWrapArray:(Ljava/lang/Object;)Lscala/collection/mutable/WrappedArray;
Method	scala/Predef$.genericWrapArray:(Ljava/lang/Object;)Lscala/collection/mutable/WrappedArray;
Asciz	apply;
Asciz	(Lscala/collection/Seq;)Lscala/collection/Traversable;;
NameAndType	apply:(Lscala/collection/Seq;)Lscala/collection/Traversable;
Method	scala/collection/immutable/Stack$.apply:(Lscala/collection/Seq;)Lscala/collection/Traversable;
Asciz	scala/collection/immutable/Stack;
class	scala/collection/immutable/Stack
NameAndType	Empty:Lscala/collection/immutable/Stack;
Field	scala/collection/immutable/Stack$.Empty:Lscala/collection/immutable/Stack;
Asciz	()Lscala/collection/immutable/Stack;;
Asciz	()Lscala/collection/immutable/Stack<Lscala/runtime/Nothing$;>;;
Asciz	Deprecated;
Asciz	newBuilder;
Asciz	()Lscala/collection/mutable/Builder;;
Asciz	scala/collection/mutable/ArrayBuffer;
class	scala/collection/mutable/ArrayBuffer
Method	scala/collection/mutable/ArrayBuffer."<init>":()V
Asciz	scala/collection/immutable/Stack$$anonfun$newBuilder$1;
class	scala/collection/immutable/Stack$$anonfun$newBuilder$1
Method	scala/collection/immutable/Stack$$anonfun$newBuilder$1."<init>":()V
Asciz	scala/collection/mutable/Builder;
class	scala/collection/mutable/Builder
Asciz	mapResult;
Asciz	(Lscala/Function1;)Lscala/collection/mutable/Builder;;
NameAndType	mapResult:(Lscala/Function1;)Lscala/collection/mutable/Builder;
InterfaceMethod	scala/collection/mutable/Builder.mapResult:(Lscala/Function1;)Lscala/collection/mutable/Builder;
Asciz	<A:Ljava/lang/Object;>()Lscala/collection/mutable/Builder<TA;Lscala/collection/immutable/Stack<TA;>;>;;
Asciz	canBuildFrom;
Asciz	()Lscala/collection/generic/CanBuildFrom;;
Asciz	scala/collection/generic/TraversableFactory$GenericCanBuildFrom;
class	scala/collection/generic/TraversableFactory$GenericCanBuildFrom
Asciz	(Lscala/collection/generic/TraversableFactory;)V;
NameAndType	"<init>":(Lscala/collection/generic/TraversableFactory;)V
Method	scala/collection/generic/TraversableFactory$GenericCanBuildFrom."<init>":(Lscala/collection/generic/TraversableFactory;)V
Asciz	<A:Ljava/lang/Object;>()Lscala/collection/generic/CanBuildFrom<Lscala/collection/immutable/Stack<*>;TA;Lscala/collection/immutable/Stack<TA;>;>;;
Asciz	Lscala/collection/generic/SeqFactory<Lscala/collection/immutable/Stack;>;Lscala/ScalaObject;;
Asciz	InnerClasses;
Asciz	scala/collection/immutable/Stack$$anonfun$pushAll$2;
class	scala/collection/immutable/Stack$$anonfun$pushAll$2
Asciz	$anonfun$pushAll$2;
Asciz	scala/collection/immutable/Stack$$anonfun$pushAll$1;
class	scala/collection/immutable/Stack$$anonfun$pushAll$1
Asciz	$anonfun$pushAll$1;
Asciz	$anonfun$newBuilder$1;
Asciz	scala/collection/generic/TraversableFactory;
class	scala/collection/generic/TraversableFactory
Asciz	GenericCanBuildFrom;
Asciz	scala/ScalaObject;
class	scala/ScalaObject

{
public static final scala.collection.immutable.Stack$ MODULE$;
  Signature: Lscala/collection/immutable/Stack$;

private final scala.collection.immutable.Stack Empty;
  Signature: Lscala/collection/immutable/Stack;
  Signature: length = 0x2
   00 10 

public static {};
  Signature: ()V
  Code:
   Stack=1, Locals=0, Args_size=0
	new	class scala/collection/immutable/Stack$
	invokespecial	Method "<init>":()V
	return
  Labels:

private scala.collection.immutable.Stack$();
  Signature: ()V
  Code:
   Stack=4, Locals=1, Args_size=1
	aload_0
	invokespecial	Method scala/collection/generic/SeqFactory."<init>":()V
	aload_0
	putstatic	Field MODULE$:Lscala/collection/immutable/Stack$;
	aload_0
	aload_0
	getstatic	Field scala/Predef$.MODULE$:Lscala/Predef$;
	iconst_0
	anewarray	class scala/runtime/Nothing$
	checkcast	class "[Ljava/lang/Object;"
	invokevirtual	Method scala/Predef$.genericWrapArray:(Ljava/lang/Object;)Lscala/collection/mutable/WrappedArray;
	invokevirtual	Method apply:(Lscala/collection/Seq;)Lscala/collection/Traversable;
	checkcast	class scala/collection/immutable/Stack
	putfield	Field Empty:Lscala/collection/immutable/Stack;
	return
  Labels:

public scala.collection.immutable.Stack Empty();
  Signature: ()Lscala/collection/immutable/Stack;
  Code:
   Stack=1, Locals=1, Args_size=1
	aload_0
	getfield	Field Empty:Lscala/collection/immutable/Stack;
	areturn
  Labels:
  Signature: length = 0x2
   00 2E 
  Deprecated: true

public scala.collection.mutable.Builder newBuilder();
  Signature: ()Lscala/collection/mutable/Builder;
  Code:
   Stack=3, Locals=1, Args_size=1
	new	class scala/collection/mutable/ArrayBuffer
	dup
	invokespecial	Method scala/collection/mutable/ArrayBuffer."<init>":()V
	new	class scala/collection/immutable/Stack$$anonfun$newBuilder$1
	dup
	invokespecial	Method scala/collection/immutable/Stack$$anonfun$newBuilder$1."<init>":()V
	invokeinterface	InterfaceMethod scala/collection/mutable/Builder.mapResult:(Lscala/Function1;)Lscala/collection/mutable/Builder;
	areturn
  Labels:
  Signature: length = 0x2
   00 3E 

public scala.collection.generic.CanBuildFrom canBuildFrom();
  Signature: ()Lscala/collection/generic/CanBuildFrom;
  Code:
   Stack=3, Locals=1, Args_size=1
	new	class scala/collection/generic/TraversableFactory$GenericCanBuildFrom
	dup
	aload_0
	invokespecial	Method scala/collection/generic/TraversableFactory$GenericCanBuildFrom."<init>":(Lscala/collection/generic/TraversableFactory;)V
	areturn
  Labels:
  Signature: length = 0x2
   00 46 

}

