Compiled from "Stack.scala"
public final class scala.collection.immutable.Stack$$anonfun$pushAll$2 extends java.lang.Object implements scala.Function2,scala.ScalaObject,java.io.Serializable
  SourceFile: "Stack.scala"
  Scala: length = 0x
   
  InnerClass: 
   public final $anonfun$pushAll$2=class scala/collection/immutable/Stack$$anonfun$pushAll$2 of class scala/collection/immutable/Stack
  minor version: 0
  major version: 49
  Constant pool:
Asciz	SourceFile;
Asciz	Stack.scala;
Asciz	<clinit>;
Asciz	()V;
Asciz	Code;
Asciz	serialVersionUID;
Asciz	J;
Asciz	scala/collection/immutable/Stack$$anonfun$pushAll$2;
class	scala/collection/immutable/Stack$$anonfun$pushAll$2
NameAndType	serialVersionUID:J
Field	scala/collection/immutable/Stack$$anonfun$pushAll$2.serialVersionUID:J
Asciz	<init>;
Asciz	(Lscala/collection/immutable/Stack;)V;
Asciz	LineNumberTable;
Asciz	java/lang/Object;
class	java/lang/Object
NameAndType	"<init>":()V
Method	java/lang/Object."<init>":()V
Asciz	scala/Function2$class;
class	scala/Function2$class
Asciz	$init$;
Asciz	(Lscala/Function2;)V;
NameAndType	$init$:(Lscala/Function2;)V
Method	scala/Function2$class.$init$:(Lscala/Function2;)V
Asciz	this;
Asciz	Lscala/collection/immutable/Stack$$anonfun$pushAll$2;;
Asciz	$outer;
Asciz	Lscala/collection/immutable/Stack;;
Asciz	LocalVariableTable;
Asciz	(Lscala/collection/immutable/Stack<TA;>;)V;
Asciz	Signature;
Asciz	apply;
Asciz	(Ljava/lang/Object;Ljava/lang/Object;)Ljava/lang/Object;;
Asciz	scala/collection/immutable/Stack;
class	scala/collection/immutable/Stack
Asciz	(Lscala/collection/immutable/Stack;Ljava/lang/Object;)Lscala/collection/immutable/Stack;;
NameAndType	apply:(Lscala/collection/immutable/Stack;Ljava/lang/Object;)Lscala/collection/immutable/Stack;
Method	scala/collection/immutable/Stack$$anonfun$pushAll$2.apply:(Lscala/collection/immutable/Stack;Ljava/lang/Object;)Lscala/collection/immutable/Stack;
Asciz	v1;
Asciz	Ljava/lang/Object;;
Asciz	v2;
Asciz	push;
Asciz	(Ljava/lang/Object;)Lscala/collection/immutable/Stack;;
NameAndType	push:(Ljava/lang/Object;)Lscala/collection/immutable/Stack;
Method	scala/collection/immutable/Stack.push:(Ljava/lang/Object;)Lscala/collection/immutable/Stack;
Asciz	(Lscala/collection/immutable/Stack<TB;>;TB;)Lscala/collection/immutable/Stack<TB;>;;
Asciz	curry;
Asciz	()Lscala/Function1;;
Asciz	(Lscala/Function2;)Lscala/Function1;;
NameAndType	curry:(Lscala/Function2;)Lscala/Function1;
Method	scala/Function2$class.curry:(Lscala/Function2;)Lscala/Function1;
Asciz	toString;
Asciz	()Ljava/lang/String;;
Asciz	(Lscala/Function2;)Ljava/lang/String;;
NameAndType	toString:(Lscala/Function2;)Ljava/lang/String;
Method	scala/Function2$class.toString:(Lscala/Function2;)Ljava/lang/String;
Asciz	Scala;
Asciz	InnerClasses;
Asciz	$anonfun$pushAll$2;
Asciz	scala/Function2;
class	scala/Function2
Asciz	scala/ScalaObject;
class	scala/ScalaObject
Asciz	java/io/Serializable;
class	java/io/Serializable

{
public static final long serialVersionUID;
  Signature: J

public static {};
  Signature: ()V
  Code:
   Stack=2, Locals=0, Args_size=0
	lconst_0
	putstatic	Field serialVersionUID:J
	return
  Labels:

public scala.collection.immutable.Stack$$anonfun$pushAll$2(scala.collection.immutable.Stack);
  Signature: (Lscala/collection/immutable/Stack;)V
  Code:
   Stack=1, Locals=2, Args_size=2
	aload_0
	invokespecial	Method java/lang/Object."<init>":()V
	aload_0
	invokestatic	Method scala/Function2$class.$init$:(Lscala/Function2;)V
	return
  Labels:
  LocalVariableTable: 
   Start  Length  Slot  Name   Signature
   0      9      0    this       Lscala/collection/immutable/Stack$$anonfun$pushAll$2;
   0      9      1    $outer       Lscala/collection/immutable/Stack;

  Signature: length = 0x2
   00 1E 

public final java.lang.Object apply(java.lang.Object, java.lang.Object);
  Signature: (Ljava/lang/Object;Ljava/lang/Object;)Ljava/lang/Object;
  Code:
   Stack=3, Locals=3, Args_size=3
	aload_0
	aload_1
	checkcast	class scala/collection/immutable/Stack
	aload_2
	invokevirtual	Method apply:(Lscala/collection/immutable/Stack;Ljava/lang/Object;)Lscala/collection/immutable/Stack;
	areturn
  Labels:
  LocalVariableTable: 
   Start  Length  Slot  Name   Signature
   0      10      0    this       Lscala/collection/immutable/Stack$$anonfun$pushAll$2;
   0      10      1    v1       Ljava/lang/Object;
   0      10      2    v2       Ljava/lang/Object;


public final scala.collection.immutable.Stack apply(scala.collection.immutable.Stack, java.lang.Object);
  Signature: (Lscala/collection/immutable/Stack;Ljava/lang/Object;)Lscala/collection/immutable/Stack;
  Code:
   Stack=2, Locals=3, Args_size=3
	aload_1
	aload_2
	invokevirtual	Method scala/collection/immutable/Stack.push:(Ljava/lang/Object;)Lscala/collection/immutable/Stack;
	areturn
  Labels:
  Signature: length = 0x2
   00 2E 

public scala.Function1 curry();
  Signature: ()Lscala/Function1;
  Code:
   Stack=1, Locals=1, Args_size=1
	aload_0
	invokestatic	Method scala/Function2$class.curry:(Lscala/Function2;)Lscala/Function1;
	areturn
  Labels:

public java.lang.String toString();
  Signature: ()Ljava/lang/String;
  Code:
   Stack=1, Locals=1, Args_size=1
	aload_0
	invokestatic	Method scala/Function2$class.toString:(Lscala/Function2;)Ljava/lang/String;
	areturn
  Labels:

}

