Compiled from "Stream.scala"
public final class scala.collection.immutable.Stream$StreamWithFilter$$anonfun$flatMap$2 extends scala.runtime.AbstractFunction0 implements java.io.Serializable
  SourceFile: "Stream.scala"
  Scala: length = 0x
   
  InnerClass: 
   public final StreamWithFilter=class scala/collection/immutable/Stream$StreamWithFilter of class scala/collection/immutable/Stream
   public final $anonfun$flatMap$2=class scala/collection/immutable/Stream$StreamWithFilter$$anonfun$flatMap$2 of class scala/collection/immutable/Stream$StreamWithFilter
  minor version: 0
  major version: 49
  Constant pool:
Asciz	SourceFile;
Asciz	Stream.scala;
Asciz	<clinit>;
Asciz	()V;
Asciz	Code;
Asciz	serialVersionUID;
Asciz	J;
Asciz	scala/collection/immutable/Stream$StreamWithFilter$$anonfun$flatMap$2;
class	scala/collection/immutable/Stream$StreamWithFilter$$anonfun$flatMap$2
NameAndType	serialVersionUID:J
Field	scala/collection/immutable/Stream$StreamWithFilter$$anonfun$flatMap$2.serialVersionUID:J
Asciz	$outer;
Asciz	Lscala/collection/immutable/Stream$StreamWithFilter;;
Asciz	f$4;
Asciz	Lscala/Function1;;
Asciz	apply;
Asciz	()Lscala/collection/immutable/Stream;;
Asciz	LineNumberTable;
NameAndType	$outer:Lscala/collection/immutable/Stream$StreamWithFilter;
Field	scala/collection/immutable/Stream$StreamWithFilter$$anonfun$flatMap$2.$outer:Lscala/collection/immutable/Stream$StreamWithFilter;
NameAndType	f$4:Lscala/Function1;
Field	scala/collection/immutable/Stream$StreamWithFilter$$anonfun$flatMap$2.f$4:Lscala/Function1;
Asciz	scala/collection/immutable/Stream$StreamWithFilter;
class	scala/collection/immutable/Stream$StreamWithFilter
Asciz	tailFlatMap$1;
Asciz	(Lscala/Function1;)Lscala/collection/immutable/Stream;;
NameAndType	tailFlatMap$1:(Lscala/Function1;)Lscala/collection/immutable/Stream;
Method	scala/collection/immutable/Stream$StreamWithFilter.tailFlatMap$1:(Lscala/Function1;)Lscala/collection/immutable/Stream;
Asciz	()Lscala/collection/immutable/Stream<TB;>;;
Asciz	Signature;
Asciz	()Ljava/lang/Object;;
NameAndType	apply:()Lscala/collection/immutable/Stream;
Method	scala/collection/immutable/Stream$StreamWithFilter$$anonfun$flatMap$2.apply:()Lscala/collection/immutable/Stream;
Asciz	<init>;
Asciz	(Lscala/collection/immutable/Stream$StreamWithFilter;Lscala/Function1;)V;
Asciz	java/lang/NullPointerException;
class	java/lang/NullPointerException
NameAndType	"<init>":()V
Method	java/lang/NullPointerException."<init>":()V
Asciz	scala/runtime/AbstractFunction0;
class	scala/runtime/AbstractFunction0
Method	scala/runtime/AbstractFunction0."<init>":()V
Asciz	this;
Asciz	Lscala/collection/immutable/Stream$StreamWithFilter$$anonfun$flatMap$2;;
Asciz	LocalVariableTable;
Asciz	(Lscala/collection/immutable/Stream<TA;>.StreamWithFilter;)V;
Asciz	Scala;
Asciz	InnerClasses;
Asciz	scala/collection/immutable/Stream;
class	scala/collection/immutable/Stream
Asciz	StreamWithFilter;
Asciz	$anonfun$flatMap$2;
Asciz	java/io/Serializable;
class	java/io/Serializable

{
public static final long serialVersionUID;
  Signature: J

public final scala.collection.immutable.Stream$StreamWithFilter $outer;
  Signature: Lscala/collection/immutable/Stream$StreamWithFilter;

public final scala.Function1 f$4;
  Signature: Lscala/Function1;

public static {};
  Signature: ()V
  Code:
   Stack=2, Locals=0, Args_size=0
	lconst_0
	putstatic	Field serialVersionUID:J
	return
  Labels:

public final scala.collection.immutable.Stream apply();
  Signature: ()Lscala/collection/immutable/Stream;
  Code:
   Stack=2, Locals=1, Args_size=1
	aload_0
	getfield	Field $outer:Lscala/collection/immutable/Stream$StreamWithFilter;
	aload_0
	getfield	Field f$4:Lscala/Function1;
	invokevirtual	Method scala/collection/immutable/Stream$StreamWithFilter.tailFlatMap$1:(Lscala/Function1;)Lscala/collection/immutable/Stream;
	areturn
  Labels:
  Signature: length = 0x2
   00 1D 

public final java.lang.Object apply();
  Signature: ()Ljava/lang/Object;
  Code:
   Stack=1, Locals=1, Args_size=1
	aload_0
	invokevirtual	Method apply:()Lscala/collection/immutable/Stream;
	areturn
  Labels:

public scala.collection.immutable.Stream$StreamWithFilter$$anonfun$flatMap$2(scala.collection.immutable.Stream$StreamWithFilter, scala.Function1);
  Signature: (Lscala/collection/immutable/Stream$StreamWithFilter;Lscala/Function1;)V
  Code:
   Stack=2, Locals=3, Args_size=3
	aload_1
	ifnonnull	l1 // aload_0
	new	class java/lang/NullPointerException
	dup
	invokespecial	Method java/lang/NullPointerException."<init>":()V
	athrow
l1	aload_0
	aload_1
	putfield	Field $outer:Lscala/collection/immutable/Stream$StreamWithFilter;
	aload_0
	aload_2
	putfield	Field f$4:Lscala/Function1;
	aload_0
	invokespecial	Method scala/runtime/AbstractFunction0."<init>":()V
	return
  Labels:
   	l1 = 12 // aload_0
  LocalVariableTable: 
   Start  Length  Slot  Name   Signature
   0      27      0    this       Lscala/collection/immutable/Stream$StreamWithFilter$$anonfun$flatMap$2;
   0      27      1    $outer       Lscala/collection/immutable/Stream$StreamWithFilter;

  Signature: length = 0x2
   00 2E 

}

