Compiled from "Stream.scala"
public final class scala.collection.immutable.Stream$$anonfun$zip$1 extends java.lang.Object implements scala.Function0,scala.ScalaObject,java.io.Serializable
  SourceFile: "Stream.scala"
  Scala: length = 0x
   
  InnerClass: 
   public final $anonfun$zip$1=class scala/collection/immutable/Stream$$anonfun$zip$1 of class scala/collection/immutable/Stream
  minor version: 0
  major version: 49
  Constant pool:
Asciz	SourceFile;
Asciz	Stream.scala;
Asciz	<clinit>;
Asciz	()V;
Asciz	Code;
Asciz	serialVersionUID;
Asciz	J;
Asciz	scala/collection/immutable/Stream$$anonfun$zip$1;
class	scala/collection/immutable/Stream$$anonfun$zip$1
NameAndType	serialVersionUID:J
Field	scala/collection/immutable/Stream$$anonfun$zip$1.serialVersionUID:J
Asciz	bf$3;
Asciz	Lscala/collection/generic/CanBuildFrom;;
Asciz	that$2;
Asciz	Lscala/collection/Iterable;;
Asciz	$outer;
Asciz	Lscala/collection/immutable/Stream;;
Asciz	<init>;
Asciz	(Lscala/collection/immutable/Stream;Lscala/collection/Iterable;Lscala/collection/generic/CanBuildFrom;)V;
Asciz	LineNumberTable;
Asciz	java/lang/NullPointerException;
class	java/lang/NullPointerException
NameAndType	"<init>":()V
Method	java/lang/NullPointerException."<init>":()V
NameAndType	$outer:Lscala/collection/immutable/Stream;
Field	scala/collection/immutable/Stream$$anonfun$zip$1.$outer:Lscala/collection/immutable/Stream;
NameAndType	that$2:Lscala/collection/Iterable;
Field	scala/collection/immutable/Stream$$anonfun$zip$1.that$2:Lscala/collection/Iterable;
NameAndType	bf$3:Lscala/collection/generic/CanBuildFrom;
Field	scala/collection/immutable/Stream$$anonfun$zip$1.bf$3:Lscala/collection/generic/CanBuildFrom;
Asciz	java/lang/Object;
class	java/lang/Object
Method	java/lang/Object."<init>":()V
Asciz	scala/Function0$class;
class	scala/Function0$class
Asciz	$init$;
Asciz	(Lscala/Function0;)V;
NameAndType	$init$:(Lscala/Function0;)V
Method	scala/Function0$class.$init$:(Lscala/Function0;)V
Asciz	this;
Asciz	Lscala/collection/immutable/Stream$$anonfun$zip$1;;
Asciz	LocalVariableTable;
Asciz	(Lscala/collection/immutable/Stream<TA;>;)V;
Asciz	Signature;
Asciz	apply;
Asciz	()Ljava/lang/Object;;
Asciz	()Lscala/collection/immutable/Stream;;
NameAndType	apply:()Lscala/collection/immutable/Stream;
Method	scala/collection/immutable/Stream$$anonfun$zip$1.apply:()Lscala/collection/immutable/Stream;
Asciz	scala/collection/TraversableLike;
class	scala/collection/TraversableLike
Asciz	tail;
NameAndType	tail:()Ljava/lang/Object;
InterfaceMethod	scala/collection/TraversableLike.tail:()Ljava/lang/Object;
Asciz	scala/collection/immutable/Stream;
class	scala/collection/immutable/Stream
Asciz	scala/collection/Iterable;
class	scala/collection/Iterable
Asciz	zip;
Asciz	(Lscala/collection/Iterable;Lscala/collection/generic/CanBuildFrom;)Ljava/lang/Object;;
NameAndType	zip:(Lscala/collection/Iterable;Lscala/collection/generic/CanBuildFrom;)Ljava/lang/Object;
Method	scala/collection/immutable/Stream.zip:(Lscala/collection/Iterable;Lscala/collection/generic/CanBuildFrom;)Ljava/lang/Object;
Asciz	()Lscala/collection/immutable/Stream<Lscala/Tuple2<TA1;TB;>;>;;
Asciz	toString;
Asciz	()Ljava/lang/String;;
Asciz	(Lscala/Function0;)Ljava/lang/String;;
NameAndType	toString:(Lscala/Function0;)Ljava/lang/String;
Method	scala/Function0$class.toString:(Lscala/Function0;)Ljava/lang/String;
Asciz	Scala;
Asciz	InnerClasses;
Asciz	$anonfun$zip$1;
Asciz	scala/Function0;
class	scala/Function0
Asciz	scala/ScalaObject;
class	scala/ScalaObject
Asciz	java/io/Serializable;
class	java/io/Serializable

{
public static final long serialVersionUID;
  Signature: J

private final scala.collection.generic.CanBuildFrom bf$3;
  Signature: Lscala/collection/generic/CanBuildFrom;

private final scala.collection.Iterable that$2;
  Signature: Lscala/collection/Iterable;

private final scala.collection.immutable.Stream $outer;
  Signature: Lscala/collection/immutable/Stream;

public static {};
  Signature: ()V
  Code:
   Stack=2, Locals=0, Args_size=0
	lconst_0
	putstatic	Field serialVersionUID:J
	return
  Labels:

public scala.collection.immutable.Stream$$anonfun$zip$1(scala.collection.immutable.Stream, scala.collection.Iterable, scala.collection.generic.CanBuildFrom);
  Signature: (Lscala/collection/immutable/Stream;Lscala/collection/Iterable;Lscala/collection/generic/CanBuildFrom;)V
  Code:
   Stack=2, Locals=4, Args_size=4
	aload_1
	ifnonnull	l1 // aload_0
	new	class java/lang/NullPointerException
	dup
	invokespecial	Method java/lang/NullPointerException."<init>":()V
	athrow
l1	aload_0
	aload_1
	putfield	Field $outer:Lscala/collection/immutable/Stream;
	aload_0
	aload_2
	putfield	Field that$2:Lscala/collection/Iterable;
	aload_0
	aload_3
	putfield	Field bf$3:Lscala/collection/generic/CanBuildFrom;
	aload_0
	invokespecial	Method java/lang/Object."<init>":()V
	aload_0
	invokestatic	Method scala/Function0$class.$init$:(Lscala/Function0;)V
	return
  Labels:
   	l1 = 12 // aload_0
  LocalVariableTable: 
   Start  Length  Slot  Name   Signature
   0      36      0    this       Lscala/collection/immutable/Stream$$anonfun$zip$1;
   0      36      1    $outer       Lscala/collection/immutable/Stream;

  Signature: length = 0x2
   00 2B 

public final java.lang.Object apply();
  Signature: ()Ljava/lang/Object;
  Code:
   Stack=1, Locals=2, Args_size=1
	aload_0
	getfield	Field $outer:Lscala/collection/immutable/Stream;
	astore_1
	aload_0
	invokevirtual	Method apply:()Lscala/collection/immutable/Stream;
	areturn
  Labels:
  LocalVariableTable: 
   Start  Length  Slot  Name   Signature
   0      10      0    this       Lscala/collection/immutable/Stream$$anonfun$zip$1;


public final scala.collection.immutable.Stream apply();
  Signature: ()Lscala/collection/immutable/Stream;
  Code:
   Stack=3, Locals=2, Args_size=1
	aload_0
	getfield	Field $outer:Lscala/collection/immutable/Stream;
	astore_1
	aload_0
	getfield	Field $outer:Lscala/collection/immutable/Stream;
	invokeinterface	InterfaceMethod scala/collection/TraversableLike.tail:()Ljava/lang/Object;
	checkcast	class scala/collection/immutable/Stream
	aload_0
	getfield	Field that$2:Lscala/collection/Iterable;
	invokeinterface	InterfaceMethod scala/collection/TraversableLike.tail:()Ljava/lang/Object;
	checkcast	class scala/collection/Iterable
	aload_0
	getfield	Field bf$3:Lscala/collection/generic/CanBuildFrom;
	invokevirtual	Method scala/collection/immutable/Stream.zip:(Lscala/collection/Iterable;Lscala/collection/generic/CanBuildFrom;)Ljava/lang/Object;
	checkcast	class scala/collection/immutable/Stream
	areturn
  Labels:
  LocalVariableTable: 
   Start  Length  Slot  Name   Signature
   0      40      0    this       Lscala/collection/immutable/Stream$$anonfun$zip$1;

  Signature: length = 0x2
   00 3F 

public java.lang.String toString();
  Signature: ()Ljava/lang/String;
  Code:
   Stack=1, Locals=1, Args_size=1
	aload_0
	invokestatic	Method scala/Function0$class.toString:(Lscala/Function0;)Ljava/lang/String;
	areturn
  Labels:

}

