Compiled from "Stream.scala"
public final class scala.collection.immutable.Stream$$anonfun$removeDuplicates$1 extends java.lang.Object implements scala.Function0,scala.ScalaObject,java.io.Serializable
  SourceFile: "Stream.scala"
  Scala: length = 0x
   
  InnerClass: 
   public final #113= #88 of #48; //Cons=class scala/collection/immutable/Stream$Cons of class scala/collection/immutable/Stream
   public final #114= #62 of #48; //$anonfun$1=class scala/collection/immutable/Stream$$anonfun$1 of class scala/collection/immutable/Stream
   public final #115= #90 of #48; //$anonfun$filter$1=class scala/collection/immutable/Stream$$anonfun$filter$1 of class scala/collection/immutable/Stream
   public final #116= #9 of #48; //$anonfun$removeDuplicates$1=class scala/collection/immutable/Stream$$anonfun$removeDuplicates$1 of class scala/collection/immutable/Stream
   public final #117= #55 of #9; //$anonfun$apply$1=class scala/collection/immutable/Stream$$anonfun$removeDuplicates$1$$anonfun$apply$1 of class scala/collection/immutable/Stream$$anonfun$removeDuplicates$1
  minor version: 0
  major version: 49
  Constant pool:
const #1 = Asciz	SourceFile;
const #2 = Asciz	Stream.scala;
const #3 = Asciz	<clinit>;
const #4 = Asciz	()V;
const #5 = Asciz	Code;
const #6 = Asciz	serialVersionUID;
const #7 = Asciz	J;
const #8 = Asciz	scala/collection/immutable/Stream$$anonfun$removeDuplicates$1;
const #9 = class	#8;	//  scala/collection/immutable/Stream$$anonfun$removeDuplicates$1
const #10 = NameAndType	#6:#7;//  serialVersionUID:J
const #11 = Field	#9.#10;	//  scala/collection/immutable/Stream$$anonfun$removeDuplicates$1.serialVersionUID:J
const #12 = Asciz	$outer;
const #13 = Asciz	Lscala/collection/immutable/Stream;;
const #14 = Asciz	<init>;
const #15 = Asciz	(Lscala/collection/immutable/Stream;)V;
const #16 = Asciz	LineNumberTable;
const #17 = Asciz	java/lang/NullPointerException;
const #18 = class	#17;	//  java/lang/NullPointerException
const #19 = NameAndType	#14:#4;//  "<init>":()V
const #20 = Method	#18.#19;	//  java/lang/NullPointerException."<init>":()V
const #21 = NameAndType	#12:#13;//  $outer:Lscala/collection/immutable/Stream;
const #22 = Field	#9.#21;	//  scala/collection/immutable/Stream$$anonfun$removeDuplicates$1.$outer:Lscala/collection/immutable/Stream;
const #23 = Asciz	java/lang/Object;
const #24 = class	#23;	//  java/lang/Object
const #25 = Method	#24.#19;	//  java/lang/Object."<init>":()V
const #26 = Asciz	scala/Function0$class;
const #27 = class	#26;	//  scala/Function0$class
const #28 = Asciz	$init$;
const #29 = Asciz	(Lscala/Function0;)V;
const #30 = NameAndType	#28:#29;//  $init$:(Lscala/Function0;)V
const #31 = Method	#27.#30;	//  scala/Function0$class.$init$:(Lscala/Function0;)V
const #32 = Asciz	this;
const #33 = Asciz	Lscala/collection/immutable/Stream$$anonfun$removeDuplicates$1;;
const #34 = Asciz	LocalVariableTable;
const #35 = Asciz	(Lscala/collection/immutable/Stream<TA;>;)V;
const #36 = Asciz	Signature;
const #37 = Asciz	apply;
const #38 = Asciz	()Ljava/lang/Object;;
const #39 = Asciz	()Lscala/collection/immutable/Stream;;
const #40 = NameAndType	#37:#39;//  apply:()Lscala/collection/immutable/Stream;
const #41 = Method	#9.#40;	//  scala/collection/immutable/Stream$$anonfun$removeDuplicates$1.apply:()Lscala/collection/immutable/Stream;
const #42 = Asciz	scala/collection/TraversableLike;
const #43 = class	#42;	//  scala/collection/TraversableLike
const #44 = Asciz	tail;
const #45 = NameAndType	#44:#38;//  tail:()Ljava/lang/Object;
const #46 = InterfaceMethod	#43.#45;	//  scala/collection/TraversableLike.tail:()Ljava/lang/Object;
const #47 = Asciz	scala/collection/immutable/Stream;
const #48 = class	#47;	//  scala/collection/immutable/Stream
const #49 = Asciz	scala/collection/IterableLike;
const #50 = class	#49;	//  scala/collection/IterableLike
const #51 = Asciz	head;
const #52 = NameAndType	#51:#38;//  head:()Ljava/lang/Object;
const #53 = InterfaceMethod	#50.#52;	//  scala/collection/IterableLike.head:()Ljava/lang/Object;
const #54 = Asciz	scala/collection/immutable/Stream$$anonfun$removeDuplicates$1$$anonfun$apply$1;
const #55 = class	#54;	//  scala/collection/immutable/Stream$$anonfun$removeDuplicates$1$$anonfun$apply$1
const #56 = Asciz	(Lscala/collection/immutable/Stream$$anonfun$removeDuplicates$1;Ljava/lang/Object;)V;
const #57 = NameAndType	#14:#56;//  "<init>":(Lscala/collection/immutable/Stream$$anonfun$removeDuplicates$1;Ljava/lang/Object;)V
const #58 = Method	#55.#57;	//  scala/collection/immutable/Stream$$anonfun$removeDuplicates$1$$anonfun$apply$1."<init>":(Lscala/collection/immutable/Stream$$anonfun$removeDuplicates$1;Ljava/lang/Object;)V
const #59 = Asciz	scala/runtime/ObjectRef;
const #60 = class	#59;	//  scala/runtime/ObjectRef
const #61 = Asciz	scala/collection/immutable/Stream$$anonfun$1;
const #62 = class	#61;	//  scala/collection/immutable/Stream$$anonfun$1
const #63 = Asciz	(Lscala/collection/immutable/Stream;Lscala/Function1;)V;
const #64 = NameAndType	#14:#63;//  "<init>":(Lscala/collection/immutable/Stream;Lscala/Function1;)V
const #65 = Method	#62.#64;	//  scala/collection/immutable/Stream$$anonfun$1."<init>":(Lscala/collection/immutable/Stream;Lscala/Function1;)V
const #66 = Asciz	dropWhile;
const #67 = Asciz	(Lscala/Function1;)Lscala/collection/immutable/Stream;;
const #68 = NameAndType	#66:#67;//  dropWhile:(Lscala/Function1;)Lscala/collection/immutable/Stream;
const #69 = Method	#48.#68;	//  scala/collection/immutable/Stream.dropWhile:(Lscala/Function1;)Lscala/collection/immutable/Stream;
const #70 = Asciz	(Ljava/lang/Object;)V;
const #71 = NameAndType	#14:#70;//  "<init>":(Ljava/lang/Object;)V
const #72 = Method	#60.#71;	//  scala/runtime/ObjectRef."<init>":(Ljava/lang/Object;)V
const #73 = Asciz	elem;
const #74 = Asciz	Ljava/lang/Object;;
const #75 = NameAndType	#73:#74;//  elem:Ljava/lang/Object;
const #76 = Field	#60.#75;	//  scala/runtime/ObjectRef.elem:Ljava/lang/Object;
const #77 = Asciz	isEmpty;
const #78 = Asciz	()Z;
const #79 = NameAndType	#77:#78;//  isEmpty:()Z
const #80 = InterfaceMethod	#50.#79;	//  scala/collection/IterableLike.isEmpty:()Z
const #81 = Asciz	scala/collection/immutable/Stream$Empty$;
const #82 = class	#81;	//  scala/collection/immutable/Stream$Empty$
const #83 = Asciz	MODULE$;
const #84 = Asciz	Lscala/collection/immutable/Stream$Empty$;;
const #85 = NameAndType	#83:#84;//  MODULE$:Lscala/collection/immutable/Stream$Empty$;
const #86 = Field	#82.#85;	//  scala/collection/immutable/Stream$Empty$.MODULE$:Lscala/collection/immutable/Stream$Empty$;
const #87 = Asciz	scala/collection/immutable/Stream$Cons;
const #88 = class	#87;	//  scala/collection/immutable/Stream$Cons
const #89 = Asciz	scala/collection/immutable/Stream$$anonfun$filter$1;
const #90 = class	#89;	//  scala/collection/immutable/Stream$$anonfun$filter$1
const #91 = Asciz	(Lscala/collection/immutable/Stream;Lscala/Function1;Lscala/runtime/ObjectRef;)V;
const #92 = NameAndType	#14:#91;//  "<init>":(Lscala/collection/immutable/Stream;Lscala/Function1;Lscala/runtime/ObjectRef;)V
const #93 = Method	#90.#92;	//  scala/collection/immutable/Stream$$anonfun$filter$1."<init>":(Lscala/collection/immutable/Stream;Lscala/Function1;Lscala/runtime/ObjectRef;)V
const #94 = Asciz	(Ljava/lang/Object;Lscala/Function0;)V;
const #95 = NameAndType	#14:#94;//  "<init>":(Ljava/lang/Object;Lscala/Function0;)V
const #96 = Method	#88.#95;	//  scala/collection/immutable/Stream$Cons."<init>":(Ljava/lang/Object;Lscala/Function0;)V
const #97 = Asciz	removeDuplicates;
const #98 = NameAndType	#97:#39;//  removeDuplicates:()Lscala/collection/immutable/Stream;
const #99 = Method	#48.#98;	//  scala/collection/immutable/Stream.removeDuplicates:()Lscala/collection/immutable/Stream;
const #100 = Asciz	$inlThis0;
const #101 = Asciz	p$30;
const #102 = Asciz	Lscala/Function1;;
const #103 = Asciz	rest$20;
const #104 = Asciz	Lscala/runtime/ObjectRef;;
const #105 = Asciz	()Lscala/collection/immutable/Stream<TA;>;;
const #106 = Asciz	toString;
const #107 = Asciz	()Ljava/lang/String;;
const #108 = Asciz	(Lscala/Function0;)Ljava/lang/String;;
const #109 = NameAndType	#106:#108;//  toString:(Lscala/Function0;)Ljava/lang/String;
const #110 = Method	#27.#109;	//  scala/Function0$class.toString:(Lscala/Function0;)Ljava/lang/String;
const #111 = Asciz	Scala;
const #112 = Asciz	InnerClasses;
const #113 = Asciz	Cons;
const #114 = Asciz	$anonfun$1;
const #115 = Asciz	$anonfun$filter$1;
const #116 = Asciz	$anonfun$removeDuplicates$1;
const #117 = Asciz	$anonfun$apply$1;
const #118 = Asciz	scala/Function0;
const #119 = class	#118;	//  scala/Function0
const #120 = Asciz	scala/ScalaObject;
const #121 = class	#120;	//  scala/ScalaObject
const #122 = Asciz	java/io/Serializable;
const #123 = class	#122;	//  java/io/Serializable

{
public static final long serialVersionUID;

public static {};
  Code:
   Stack=2, Locals=0, Args_size=0
   0:	lconst_0
   1:	putstatic	#11; //Field serialVersionUID:J
   4:	return

public scala.collection.immutable.Stream$$anonfun$removeDuplicates$1(scala.collection.immutable.Stream);
  Code:
   Stack=2, Locals=2, Args_size=2
   0:	aload_1
   1:	ifnonnull	12
   4:	new	#18; //class java/lang/NullPointerException
   7:	dup
   8:	invokespecial	#20; //Method java/lang/NullPointerException."<init>":()V
   11:	athrow
   12:	aload_0
   13:	aload_1
   14:	putfield	#22; //Field $outer:Lscala/collection/immutable/Stream;
   17:	aload_0
   18:	invokespecial	#25; //Method java/lang/Object."<init>":()V
   21:	aload_0
   22:	invokestatic	#31; //Method scala/Function0$class.$init$:(Lscala/Function0;)V
   25:	return
  LineNumberTable: 
   line 349: 0

  LocalVariableTable: 
   Start  Length  Slot  Name   Signature
   0      26      0    this       Lscala/collection/immutable/Stream$$anonfun$removeDuplicates$1;
   0      26      1    $outer       Lscala/collection/immutable/Stream;

  Signature: length = 0x2
   00 23 

public final java.lang.Object apply();
  Code:
   Stack=1, Locals=2, Args_size=1
   0:	aload_0
   1:	getfield	#22; //Field $outer:Lscala/collection/immutable/Stream;
   4:	astore_1
   5:	aload_0
   6:	invokevirtual	#41; //Method apply:()Lscala/collection/immutable/Stream;
   9:	areturn
  LineNumberTable: 
   line 349: 0

  LocalVariableTable: 
   Start  Length  Slot  Name   Signature
   0      10      0    this       Lscala/collection/immutable/Stream$$anonfun$removeDuplicates$1;


public final scala.collection.immutable.Stream apply();
  Code:
   Stack=8, Locals=6, Args_size=1
   0:	aload_0
   1:	getfield	#22; //Field $outer:Lscala/collection/immutable/Stream;
   4:	astore	5
   6:	aload_0
   7:	getfield	#22; //Field $outer:Lscala/collection/immutable/Stream;
   10:	invokeinterface	#46,  1; //InterfaceMethod scala/collection/TraversableLike.tail:()Ljava/lang/Object;
   15:	checkcast	#48; //class scala/collection/immutable/Stream
   18:	aload_0
   19:	getfield	#22; //Field $outer:Lscala/collection/immutable/Stream;
   22:	invokeinterface	#53,  1; //InterfaceMethod scala/collection/IterableLike.head:()Ljava/lang/Object;
   27:	astore_1
   28:	new	#55; //class scala/collection/immutable/Stream$$anonfun$removeDuplicates$1$$anonfun$apply$1
   31:	dup
   32:	aload_0
   33:	aload_1
   34:	invokespecial	#58; //Method scala/collection/immutable/Stream$$anonfun$removeDuplicates$1$$anonfun$apply$1."<init>":(Lscala/collection/immutable/Stream$$anonfun$removeDuplicates$1;Ljava/lang/Object;)V
   37:	astore_3
   38:	astore_2
   39:	new	#60; //class scala/runtime/ObjectRef
   42:	dup
   43:	aload_2
   44:	new	#62; //class scala/collection/immutable/Stream$$anonfun$1
   47:	dup
   48:	aload_2
   49:	aload_3
   50:	invokespecial	#65; //Method scala/collection/immutable/Stream$$anonfun$1."<init>":(Lscala/collection/immutable/Stream;Lscala/Function1;)V
   53:	invokevirtual	#69; //Method scala/collection/immutable/Stream.dropWhile:(Lscala/Function1;)Lscala/collection/immutable/Stream;
   56:	invokespecial	#72; //Method scala/runtime/ObjectRef."<init>":(Ljava/lang/Object;)V
   59:	astore	4
   61:	aload	4
   63:	getfield	#76; //Field scala/runtime/ObjectRef.elem:Ljava/lang/Object;
   66:	checkcast	#48; //class scala/collection/immutable/Stream
   69:	invokeinterface	#80,  1; //InterfaceMethod scala/collection/IterableLike.isEmpty:()Z
   74:	ifeq	83
   77:	getstatic	#86; //Field scala/collection/immutable/Stream$Empty$.MODULE$:Lscala/collection/immutable/Stream$Empty$;
   80:	goto	114
   83:	new	#88; //class scala/collection/immutable/Stream$Cons
   86:	dup
   87:	aload	4
   89:	getfield	#76; //Field scala/runtime/ObjectRef.elem:Ljava/lang/Object;
   92:	checkcast	#48; //class scala/collection/immutable/Stream
   95:	invokeinterface	#53,  1; //InterfaceMethod scala/collection/IterableLike.head:()Ljava/lang/Object;
   100:	new	#90; //class scala/collection/immutable/Stream$$anonfun$filter$1
   103:	dup
   104:	aload_2
   105:	aload_3
   106:	aload	4
   108:	invokespecial	#93; //Method scala/collection/immutable/Stream$$anonfun$filter$1."<init>":(Lscala/collection/immutable/Stream;Lscala/Function1;Lscala/runtime/ObjectRef;)V
   111:	invokespecial	#96; //Method scala/collection/immutable/Stream$Cons."<init>":(Ljava/lang/Object;Lscala/Function0;)V
   114:	invokevirtual	#99; //Method scala/collection/immutable/Stream.removeDuplicates:()Lscala/collection/immutable/Stream;
   117:	areturn
  LineNumberTable: 
   line 349: 0

  LocalVariableTable: 
   Start  Length  Slot  Name   Signature
   0      118      0    this       Lscala/collection/immutable/Stream$$anonfun$removeDuplicates$1;
   77      41      2    $inlThis0       Ljava/lang/Object;
   77      41      3    p$30       Lscala/Function1;
   61      57      4    rest$20       Lscala/runtime/ObjectRef;

  Signature: length = 0x2
   00 69 

public java.lang.String toString();
  Code:
   Stack=1, Locals=1, Args_size=1
   0:	aload_0
   1:	invokestatic	#110; //Method scala/Function0$class.toString:(Lscala/Function0;)Ljava/lang/String;
   4:	areturn
  LineNumberTable: 
   line 349: 0


}

