Compiled from "Stream.scala"
public final class scala.collection.immutable.Stream$$anonfun$loop$4$2 extends java.lang.Object implements scala.Function0,scala.ScalaObject,java.io.Serializable
  SourceFile: "Stream.scala"
  Scala: length = 0x
   
  InnerClass: 
   public final #72= #9 of #59; //$anonfun$loop$4$2=class scala/collection/immutable/Stream$$anonfun$loop$4$2 of class scala/collection/immutable/Stream
  minor version: 0
  major version: 49
  Constant pool:
const #1 = Asciz	SourceFile;
const #2 = Asciz	Stream.scala;
const #3 = Asciz	<clinit>;
const #4 = Asciz	()V;
const #5 = Asciz	Code;
const #6 = Asciz	serialVersionUID;
const #7 = Asciz	J;
const #8 = Asciz	scala/collection/immutable/Stream$$anonfun$loop$4$2;
const #9 = class	#8;	//  scala/collection/immutable/Stream$$anonfun$loop$4$2
const #10 = NameAndType	#6:#7;//  serialVersionUID:J
const #11 = Field	#9.#10;	//  scala/collection/immutable/Stream$$anonfun$loop$4$2.serialVersionUID:J
const #12 = Asciz	these$1;
const #13 = Asciz	Lscala/collection/immutable/Stream;;
const #14 = Asciz	len$1;
const #15 = Asciz	I;
const #16 = Asciz	elem$2;
const #17 = Asciz	Ljava/lang/Object;;
const #18 = Asciz	$outer;
const #19 = Asciz	<init>;
const #20 = Asciz	(Lscala/collection/immutable/Stream;Ljava/lang/Object;ILscala/collection/immutable/Stream;)V;
const #21 = Asciz	LineNumberTable;
const #22 = Asciz	java/lang/NullPointerException;
const #23 = class	#22;	//  java/lang/NullPointerException
const #24 = NameAndType	#19:#4;//  "<init>":()V
const #25 = Method	#23.#24;	//  java/lang/NullPointerException."<init>":()V
const #26 = NameAndType	#18:#13;//  $outer:Lscala/collection/immutable/Stream;
const #27 = Field	#9.#26;	//  scala/collection/immutable/Stream$$anonfun$loop$4$2.$outer:Lscala/collection/immutable/Stream;
const #28 = NameAndType	#16:#17;//  elem$2:Ljava/lang/Object;
const #29 = Field	#9.#28;	//  scala/collection/immutable/Stream$$anonfun$loop$4$2.elem$2:Ljava/lang/Object;
const #30 = NameAndType	#14:#15;//  len$1:I
const #31 = Field	#9.#30;	//  scala/collection/immutable/Stream$$anonfun$loop$4$2.len$1:I
const #32 = NameAndType	#12:#13;//  these$1:Lscala/collection/immutable/Stream;
const #33 = Field	#9.#32;	//  scala/collection/immutable/Stream$$anonfun$loop$4$2.these$1:Lscala/collection/immutable/Stream;
const #34 = Asciz	java/lang/Object;
const #35 = class	#34;	//  java/lang/Object
const #36 = Method	#35.#24;	//  java/lang/Object."<init>":()V
const #37 = Asciz	scala/Function0$class;
const #38 = class	#37;	//  scala/Function0$class
const #39 = Asciz	$init$;
const #40 = Asciz	(Lscala/Function0;)V;
const #41 = NameAndType	#39:#40;//  $init$:(Lscala/Function0;)V
const #42 = Method	#38.#41;	//  scala/Function0$class.$init$:(Lscala/Function0;)V
const #43 = Asciz	this;
const #44 = Asciz	Lscala/collection/immutable/Stream$$anonfun$loop$4$2;;
const #45 = Asciz	LocalVariableTable;
const #46 = Asciz	(Lscala/collection/immutable/Stream<TA;>;)V;
const #47 = Asciz	Signature;
const #48 = Asciz	apply;
const #49 = Asciz	()Ljava/lang/Object;;
const #50 = Asciz	()Lscala/collection/immutable/Stream;;
const #51 = NameAndType	#48:#50;//  apply:()Lscala/collection/immutable/Stream;
const #52 = Method	#9.#51;	//  scala/collection/immutable/Stream$$anonfun$loop$4$2.apply:()Lscala/collection/immutable/Stream;
const #53 = Asciz	scala/collection/TraversableLike;
const #54 = class	#53;	//  scala/collection/TraversableLike
const #55 = Asciz	tail;
const #56 = NameAndType	#55:#49;//  tail:()Ljava/lang/Object;
const #57 = InterfaceMethod	#54.#56;	//  scala/collection/TraversableLike.tail:()Ljava/lang/Object;
const #58 = Asciz	scala/collection/immutable/Stream;
const #59 = class	#58;	//  scala/collection/immutable/Stream
const #60 = Asciz	loop$4;
const #61 = Asciz	(ILscala/collection/immutable/Stream;Ljava/lang/Object;)Lscala/collection/immutable/Stream;;
const #62 = NameAndType	#60:#61;//  loop$4:(ILscala/collection/immutable/Stream;Ljava/lang/Object;)Lscala/collection/immutable/Stream;
const #63 = Method	#59.#62;	//  scala/collection/immutable/Stream.loop$4:(ILscala/collection/immutable/Stream;Ljava/lang/Object;)Lscala/collection/immutable/Stream;
const #64 = Asciz	()Lscala/collection/immutable/Stream<TB;>;;
const #65 = Asciz	toString;
const #66 = Asciz	()Ljava/lang/String;;
const #67 = Asciz	(Lscala/Function0;)Ljava/lang/String;;
const #68 = NameAndType	#65:#67;//  toString:(Lscala/Function0;)Ljava/lang/String;
const #69 = Method	#38.#68;	//  scala/Function0$class.toString:(Lscala/Function0;)Ljava/lang/String;
const #70 = Asciz	Scala;
const #71 = Asciz	InnerClasses;
const #72 = Asciz	$anonfun$loop$4$2;
const #73 = Asciz	scala/Function0;
const #74 = class	#73;	//  scala/Function0
const #75 = Asciz	scala/ScalaObject;
const #76 = class	#75;	//  scala/ScalaObject
const #77 = Asciz	java/io/Serializable;
const #78 = class	#77;	//  java/io/Serializable

{
public static final long serialVersionUID;

public static {};
  Code:
   Stack=2, Locals=0, Args_size=0
   0:	lconst_0
   1:	putstatic	#11; //Field serialVersionUID:J
   4:	return

public scala.collection.immutable.Stream$$anonfun$loop$4$2(scala.collection.immutable.Stream, java.lang.Object, int, scala.collection.immutable.Stream);
  Code:
   Stack=2, Locals=5, Args_size=5
   0:	aload_1
   1:	ifnonnull	12
   4:	new	#23; //class java/lang/NullPointerException
   7:	dup
   8:	invokespecial	#25; //Method java/lang/NullPointerException."<init>":()V
   11:	athrow
   12:	aload_0
   13:	aload_1
   14:	putfield	#27; //Field $outer:Lscala/collection/immutable/Stream;
   17:	aload_0
   18:	aload_2
   19:	putfield	#29; //Field elem$2:Ljava/lang/Object;
   22:	aload_0
   23:	iload_3
   24:	putfield	#31; //Field len$1:I
   27:	aload_0
   28:	aload	4
   30:	putfield	#33; //Field these$1:Lscala/collection/immutable/Stream;
   33:	aload_0
   34:	invokespecial	#36; //Method java/lang/Object."<init>":()V
   37:	aload_0
   38:	invokestatic	#42; //Method scala/Function0$class.$init$:(Lscala/Function0;)V
   41:	return
  LineNumberTable: 
   line 357: 0

  LocalVariableTable: 
   Start  Length  Slot  Name   Signature
   0      42      0    this       Lscala/collection/immutable/Stream$$anonfun$loop$4$2;
   0      42      1    $outer       Lscala/collection/immutable/Stream;

  Signature: length = 0x2
   00 2E 

public final java.lang.Object apply();
  Code:
   Stack=1, Locals=2, Args_size=1
   0:	aload_0
   1:	getfield	#27; //Field $outer:Lscala/collection/immutable/Stream;
   4:	astore_1
   5:	aload_0
   6:	invokevirtual	#52; //Method apply:()Lscala/collection/immutable/Stream;
   9:	areturn
  LineNumberTable: 
   line 357: 0

  LocalVariableTable: 
   Start  Length  Slot  Name   Signature
   0      10      0    this       Lscala/collection/immutable/Stream$$anonfun$loop$4$2;


public final scala.collection.immutable.Stream apply();
  Code:
   Stack=4, Locals=2, Args_size=1
   0:	aload_0
   1:	getfield	#27; //Field $outer:Lscala/collection/immutable/Stream;
   4:	astore_1
   5:	aload_0
   6:	getfield	#27; //Field $outer:Lscala/collection/immutable/Stream;
   9:	aload_0
   10:	getfield	#31; //Field len$1:I
   13:	iconst_1
   14:	isub
   15:	aload_0
   16:	getfield	#33; //Field these$1:Lscala/collection/immutable/Stream;
   19:	invokeinterface	#57,  1; //InterfaceMethod scala/collection/TraversableLike.tail:()Ljava/lang/Object;
   24:	checkcast	#59; //class scala/collection/immutable/Stream
   27:	aload_0
   28:	getfield	#29; //Field elem$2:Ljava/lang/Object;
   31:	invokevirtual	#63; //Method scala/collection/immutable/Stream.loop$4:(ILscala/collection/immutable/Stream;Ljava/lang/Object;)Lscala/collection/immutable/Stream;
   34:	areturn
  LineNumberTable: 
   line 357: 0

  LocalVariableTable: 
   Start  Length  Slot  Name   Signature
   0      35      0    this       Lscala/collection/immutable/Stream$$anonfun$loop$4$2;

  Signature: length = 0x2
   00 40 

public java.lang.String toString();
  Code:
   Stack=1, Locals=1, Args_size=1
   0:	aload_0
   1:	invokestatic	#69; //Method scala/Function0$class.toString:(Lscala/Function0;)Ljava/lang/String;
   4:	areturn
  LineNumberTable: 
   line 357: 0


}

