Compiled from "Stream.scala"
public final class scala.collection.immutable.Stream$$anonfun$removeDuplicates$1$$anonfun$apply$1 extends scala.runtime.AbstractFunction1 implements java.io.Serializable
  SourceFile: "Stream.scala"
  Scala: length = 0x
   
  InnerClass: 
   public final #62= #59 of #61; //$anonfun$removeDuplicates$1=class scala/collection/immutable/Stream$$anonfun$removeDuplicates$1 of class scala/collection/immutable/Stream
   public final #63= #9 of #59; //$anonfun$apply$1=class scala/collection/immutable/Stream$$anonfun$removeDuplicates$1$$anonfun$apply$1 of class scala/collection/immutable/Stream$$anonfun$removeDuplicates$1
  minor version: 0
  major version: 49
  Constant pool:
const #1 = Asciz	SourceFile;
const #2 = Asciz	Stream.scala;
const #3 = Asciz	<clinit>;
const #4 = Asciz	()V;
const #5 = Asciz	Code;
const #6 = Asciz	serialVersionUID;
const #7 = Asciz	J;
const #8 = Asciz	scala/collection/immutable/Stream$$anonfun$removeDuplicates$1$$anonfun$apply$1;
const #9 = class	#8;	//  scala/collection/immutable/Stream$$anonfun$removeDuplicates$1$$anonfun$apply$1
const #10 = NameAndType	#6:#7;//  serialVersionUID:J
const #11 = Field	#9.#10;	//  scala/collection/immutable/Stream$$anonfun$removeDuplicates$1$$anonfun$apply$1.serialVersionUID:J
const #12 = Asciz	eta$0$1$1;
const #13 = Asciz	Ljava/lang/Object;;
const #14 = Asciz	<init>;
const #15 = Asciz	(Lscala/collection/immutable/Stream$$anonfun$removeDuplicates$1;Ljava/lang/Object;)V;
const #16 = Asciz	LineNumberTable;
const #17 = NameAndType	#12:#13;//  eta$0$1$1:Ljava/lang/Object;
const #18 = Field	#9.#17;	//  scala/collection/immutable/Stream$$anonfun$removeDuplicates$1$$anonfun$apply$1.eta$0$1$1:Ljava/lang/Object;
const #19 = Asciz	scala/runtime/AbstractFunction1;
const #20 = class	#19;	//  scala/runtime/AbstractFunction1
const #21 = NameAndType	#14:#4;//  "<init>":()V
const #22 = Method	#20.#21;	//  scala/runtime/AbstractFunction1."<init>":()V
const #23 = Asciz	this;
const #24 = Asciz	Lscala/collection/immutable/Stream$$anonfun$removeDuplicates$1$$anonfun$apply$1;;
const #25 = Asciz	$outer;
const #26 = Asciz	Lscala/collection/immutable/Stream$$anonfun$removeDuplicates$1;;
const #27 = Asciz	LocalVariableTable;
const #28 = Asciz	(Lscala/collection/immutable/Stream<TA;>.$anonfun$removeDuplicates$1;)V;
const #29 = Asciz	Signature;
const #30 = Asciz	apply;
const #31 = Asciz	(Ljava/lang/Object;)Ljava/lang/Object;;
const #32 = Asciz	(Ljava/lang/Object;)Z;
const #33 = NameAndType	#30:#32;//  apply:(Ljava/lang/Object;)Z
const #34 = Method	#9.#33;	//  scala/collection/immutable/Stream$$anonfun$removeDuplicates$1$$anonfun$apply$1.apply:(Ljava/lang/Object;)Z
const #35 = Asciz	scala/runtime/BoxesRunTime;
const #36 = class	#35;	//  scala/runtime/BoxesRunTime
const #37 = Asciz	boxToBoolean;
const #38 = Asciz	(Z)Ljava/lang/Boolean;;
const #39 = NameAndType	#37:#38;//  boxToBoolean:(Z)Ljava/lang/Boolean;
const #40 = Method	#36.#39;	//  scala/runtime/BoxesRunTime.boxToBoolean:(Z)Ljava/lang/Boolean;
const #41 = Asciz	v1;
const #42 = Asciz	java/lang/Number;
const #43 = class	#42;	//  java/lang/Number
const #44 = Asciz	java/lang/Character;
const #45 = class	#44;	//  java/lang/Character
const #46 = Asciz	equals2;
const #47 = Asciz	(Ljava/lang/Object;Ljava/lang/Object;)Z;
const #48 = NameAndType	#46:#47;//  equals2:(Ljava/lang/Object;Ljava/lang/Object;)Z
const #49 = Method	#36.#48;	//  scala/runtime/BoxesRunTime.equals2:(Ljava/lang/Object;Ljava/lang/Object;)Z
const #50 = Asciz	java/lang/Object;
const #51 = class	#50;	//  java/lang/Object
const #52 = Asciz	equals;
const #53 = NameAndType	#52:#32;//  equals:(Ljava/lang/Object;)Z
const #54 = Method	#51.#53;	//  java/lang/Object.equals:(Ljava/lang/Object;)Z
const #55 = Asciz	x0;
const #56 = Asciz	Scala;
const #57 = Asciz	InnerClasses;
const #58 = Asciz	scala/collection/immutable/Stream$$anonfun$removeDuplicates$1;
const #59 = class	#58;	//  scala/collection/immutable/Stream$$anonfun$removeDuplicates$1
const #60 = Asciz	scala/collection/immutable/Stream;
const #61 = class	#60;	//  scala/collection/immutable/Stream
const #62 = Asciz	$anonfun$removeDuplicates$1;
const #63 = Asciz	$anonfun$apply$1;
const #64 = Asciz	java/io/Serializable;
const #65 = class	#64;	//  java/io/Serializable

{
public static final long serialVersionUID;

public static {};
  Code:
   Stack=2, Locals=0, Args_size=0
   0:	lconst_0
   1:	putstatic	#11; //Field serialVersionUID:J
   4:	return

public scala.collection.immutable.Stream$$anonfun$removeDuplicates$1$$anonfun$apply$1(scala.collection.immutable.Stream$$anonfun$removeDuplicates$1, java.lang.Object);
  Code:
   Stack=2, Locals=3, Args_size=3
   0:	aload_0
   1:	aload_2
   2:	putfield	#18; //Field eta$0$1$1:Ljava/lang/Object;
   5:	aload_0
   6:	invokespecial	#22; //Method scala/runtime/AbstractFunction1."<init>":()V
   9:	return
  LineNumberTable: 
   line 349: 0

  LocalVariableTable: 
   Start  Length  Slot  Name   Signature
   0      10      0    this       Lscala/collection/immutable/Stream$$anonfun$removeDuplicates$1$$anonfun$apply$1;
   0      10      1    $outer       Lscala/collection/immutable/Stream$$anonfun$removeDuplicates$1;

  Signature: length = 0x2
   00 1C 

public final java.lang.Object apply(java.lang.Object);
  Code:
   Stack=2, Locals=3, Args_size=2
   0:	aload_0
   1:	aload_1
   2:	invokevirtual	#34; //Method apply:(Ljava/lang/Object;)Z
   5:	istore_2
   6:	iload_2
   7:	invokestatic	#40; //Method scala/runtime/BoxesRunTime.boxToBoolean:(Z)Ljava/lang/Boolean;
   10:	areturn
  LineNumberTable: 
   line 349: 0

  LocalVariableTable: 
   Start  Length  Slot  Name   Signature
   0      11      0    this       Lscala/collection/immutable/Stream$$anonfun$removeDuplicates$1$$anonfun$apply$1;
   0      11      1    v1       Ljava/lang/Object;


public final boolean apply(java.lang.Object);
  Code:
   Stack=2, Locals=3, Args_size=2
   0:	aload_0
   1:	getfield	#18; //Field eta$0$1$1:Ljava/lang/Object;
   4:	astore_2
   5:	aload_2
   6:	aload_1
   7:	if_acmpne	14
   10:	iconst_1
   11:	goto	49
   14:	aload_2
   15:	ifnonnull	22
   18:	iconst_0
   19:	goto	49
   22:	aload_2
   23:	instanceof	#43; //class java/lang/Number
   26:	ifne	36
   29:	aload_2
   30:	instanceof	#45; //class java/lang/Character
   33:	ifeq	44
   36:	aload_2
   37:	aload_1
   38:	invokestatic	#49; //Method scala/runtime/BoxesRunTime.equals2:(Ljava/lang/Object;Ljava/lang/Object;)Z
   41:	goto	49
   44:	aload_2
   45:	aload_1
   46:	invokevirtual	#54; //Method java/lang/Object.equals:(Ljava/lang/Object;)Z
   49:	ifeq	56
   52:	iconst_0
   53:	goto	57
   56:	iconst_1
   57:	ireturn
  LineNumberTable: 
   line 349: 0

  LocalVariableTable: 
   Start  Length  Slot  Name   Signature
   0      58      0    this       Lscala/collection/immutable/Stream$$anonfun$removeDuplicates$1$$anonfun$apply$1;
   10      42      2    x0       Ljava/lang/Object;


}

