Compiled from "Stream.scala"
public final class scala.collection.immutable.Stream$$anonfun$removeDuplicates$1 extends java.lang.Object implements scala.Function0,scala.ScalaObject,java.io.Serializable
  SourceFile: "Stream.scala"
  Scala: length = 0x
   
  InnerClass: 
   public final Cons=class scala/collection/immutable/Stream$Cons of class scala/collection/immutable/Stream
   public final $anonfun$1=class scala/collection/immutable/Stream$$anonfun$1 of class scala/collection/immutable/Stream
   public final $anonfun$filter$1=class scala/collection/immutable/Stream$$anonfun$filter$1 of class scala/collection/immutable/Stream
   public final $anonfun$removeDuplicates$1=class scala/collection/immutable/Stream$$anonfun$removeDuplicates$1 of class scala/collection/immutable/Stream
   public final $anonfun$apply$1=class scala/collection/immutable/Stream$$anonfun$removeDuplicates$1$$anonfun$apply$1 of class scala/collection/immutable/Stream$$anonfun$removeDuplicates$1
  minor version: 0
  major version: 49
  Constant pool:
Asciz	SourceFile;
Asciz	Stream.scala;
Asciz	<clinit>;
Asciz	()V;
Asciz	Code;
Asciz	serialVersionUID;
Asciz	J;
Asciz	scala/collection/immutable/Stream$$anonfun$removeDuplicates$1;
class	scala/collection/immutable/Stream$$anonfun$removeDuplicates$1
NameAndType	serialVersionUID:J
Field	scala/collection/immutable/Stream$$anonfun$removeDuplicates$1.serialVersionUID:J
Asciz	$outer;
Asciz	Lscala/collection/immutable/Stream;;
Asciz	<init>;
Asciz	(Lscala/collection/immutable/Stream;)V;
Asciz	LineNumberTable;
Asciz	java/lang/NullPointerException;
class	java/lang/NullPointerException
NameAndType	"<init>":()V
Method	java/lang/NullPointerException."<init>":()V
NameAndType	$outer:Lscala/collection/immutable/Stream;
Field	scala/collection/immutable/Stream$$anonfun$removeDuplicates$1.$outer:Lscala/collection/immutable/Stream;
Asciz	java/lang/Object;
class	java/lang/Object
Method	java/lang/Object."<init>":()V
Asciz	scala/Function0$class;
class	scala/Function0$class
Asciz	$init$;
Asciz	(Lscala/Function0;)V;
NameAndType	$init$:(Lscala/Function0;)V
Method	scala/Function0$class.$init$:(Lscala/Function0;)V
Asciz	this;
Asciz	Lscala/collection/immutable/Stream$$anonfun$removeDuplicates$1;;
Asciz	LocalVariableTable;
Asciz	(Lscala/collection/immutable/Stream<TA;>;)V;
Asciz	Signature;
Asciz	apply;
Asciz	()Ljava/lang/Object;;
Asciz	()Lscala/collection/immutable/Stream;;
NameAndType	apply:()Lscala/collection/immutable/Stream;
Method	scala/collection/immutable/Stream$$anonfun$removeDuplicates$1.apply:()Lscala/collection/immutable/Stream;
Asciz	scala/collection/TraversableLike;
class	scala/collection/TraversableLike
Asciz	tail;
NameAndType	tail:()Ljava/lang/Object;
InterfaceMethod	scala/collection/TraversableLike.tail:()Ljava/lang/Object;
Asciz	scala/collection/immutable/Stream;
class	scala/collection/immutable/Stream
Asciz	scala/collection/IterableLike;
class	scala/collection/IterableLike
Asciz	head;
NameAndType	head:()Ljava/lang/Object;
InterfaceMethod	scala/collection/IterableLike.head:()Ljava/lang/Object;
Asciz	scala/collection/immutable/Stream$$anonfun$removeDuplicates$1$$anonfun$apply$1;
class	scala/collection/immutable/Stream$$anonfun$removeDuplicates$1$$anonfun$apply$1
Asciz	(Lscala/collection/immutable/Stream$$anonfun$removeDuplicates$1;Ljava/lang/Object;)V;
NameAndType	"<init>":(Lscala/collection/immutable/Stream$$anonfun$removeDuplicates$1;Ljava/lang/Object;)V
Method	scala/collection/immutable/Stream$$anonfun$removeDuplicates$1$$anonfun$apply$1."<init>":(Lscala/collection/immutable/Stream$$anonfun$removeDuplicates$1;Ljava/lang/Object;)V
Asciz	scala/runtime/ObjectRef;
class	scala/runtime/ObjectRef
Asciz	scala/collection/immutable/Stream$$anonfun$1;
class	scala/collection/immutable/Stream$$anonfun$1
Asciz	(Lscala/collection/immutable/Stream;Lscala/Function1;)V;
NameAndType	"<init>":(Lscala/collection/immutable/Stream;Lscala/Function1;)V
Method	scala/collection/immutable/Stream$$anonfun$1."<init>":(Lscala/collection/immutable/Stream;Lscala/Function1;)V
Asciz	dropWhile;
Asciz	(Lscala/Function1;)Lscala/collection/immutable/Stream;;
NameAndType	dropWhile:(Lscala/Function1;)Lscala/collection/immutable/Stream;
Method	scala/collection/immutable/Stream.dropWhile:(Lscala/Function1;)Lscala/collection/immutable/Stream;
Asciz	(Ljava/lang/Object;)V;
NameAndType	"<init>":(Ljava/lang/Object;)V
Method	scala/runtime/ObjectRef."<init>":(Ljava/lang/Object;)V
Asciz	elem;
Asciz	Ljava/lang/Object;;
NameAndType	elem:Ljava/lang/Object;
Field	scala/runtime/ObjectRef.elem:Ljava/lang/Object;
Asciz	isEmpty;
Asciz	()Z;
NameAndType	isEmpty:()Z
InterfaceMethod	scala/collection/IterableLike.isEmpty:()Z
Asciz	scala/collection/immutable/Stream$Empty$;
class	scala/collection/immutable/Stream$Empty$
Asciz	MODULE$;
Asciz	Lscala/collection/immutable/Stream$Empty$;;
NameAndType	MODULE$:Lscala/collection/immutable/Stream$Empty$;
Field	scala/collection/immutable/Stream$Empty$.MODULE$:Lscala/collection/immutable/Stream$Empty$;
Asciz	scala/collection/immutable/Stream$Cons;
class	scala/collection/immutable/Stream$Cons
Asciz	scala/collection/immutable/Stream$$anonfun$filter$1;
class	scala/collection/immutable/Stream$$anonfun$filter$1
Asciz	(Lscala/collection/immutable/Stream;Lscala/Function1;Lscala/runtime/ObjectRef;)V;
NameAndType	"<init>":(Lscala/collection/immutable/Stream;Lscala/Function1;Lscala/runtime/ObjectRef;)V
Method	scala/collection/immutable/Stream$$anonfun$filter$1."<init>":(Lscala/collection/immutable/Stream;Lscala/Function1;Lscala/runtime/ObjectRef;)V
Asciz	(Ljava/lang/Object;Lscala/Function0;)V;
NameAndType	"<init>":(Ljava/lang/Object;Lscala/Function0;)V
Method	scala/collection/immutable/Stream$Cons."<init>":(Ljava/lang/Object;Lscala/Function0;)V
Asciz	removeDuplicates;
NameAndType	removeDuplicates:()Lscala/collection/immutable/Stream;
Method	scala/collection/immutable/Stream.removeDuplicates:()Lscala/collection/immutable/Stream;
Asciz	$inlThis0;
Asciz	p$30;
Asciz	Lscala/Function1;;
Asciz	rest$20;
Asciz	Lscala/runtime/ObjectRef;;
Asciz	()Lscala/collection/immutable/Stream<TA;>;;
Asciz	toString;
Asciz	()Ljava/lang/String;;
Asciz	(Lscala/Function0;)Ljava/lang/String;;
NameAndType	toString:(Lscala/Function0;)Ljava/lang/String;
Method	scala/Function0$class.toString:(Lscala/Function0;)Ljava/lang/String;
Asciz	Scala;
Asciz	InnerClasses;
Asciz	Cons;
Asciz	$anonfun$1;
Asciz	$anonfun$filter$1;
Asciz	$anonfun$removeDuplicates$1;
Asciz	$anonfun$apply$1;
Asciz	scala/Function0;
class	scala/Function0
Asciz	scala/ScalaObject;
class	scala/ScalaObject
Asciz	java/io/Serializable;
class	java/io/Serializable

{
public static final long serialVersionUID;
  Signature: J

private final scala.collection.immutable.Stream $outer;
  Signature: Lscala/collection/immutable/Stream;

public static {};
  Signature: ()V
  Code:
   Stack=2, Locals=0, Args_size=0
	lconst_0
	putstatic	Field serialVersionUID:J
	return
  Labels:

public scala.collection.immutable.Stream$$anonfun$removeDuplicates$1(scala.collection.immutable.Stream);
  Signature: (Lscala/collection/immutable/Stream;)V
  Code:
   Stack=2, Locals=2, Args_size=2
	aload_1
	ifnonnull	l1 // aload_0
	new	class java/lang/NullPointerException
	dup
	invokespecial	Method java/lang/NullPointerException."<init>":()V
	athrow
l1	aload_0
	aload_1
	putfield	Field $outer:Lscala/collection/immutable/Stream;
	aload_0
	invokespecial	Method java/lang/Object."<init>":()V
	aload_0
	invokestatic	Method scala/Function0$class.$init$:(Lscala/Function0;)V
	return
  Labels:
   	l1 = 12 // aload_0
  LocalVariableTable: 
   Start  Length  Slot  Name   Signature
   0      26      0    this       Lscala/collection/immutable/Stream$$anonfun$removeDuplicates$1;
   0      26      1    $outer       Lscala/collection/immutable/Stream;

  Signature: length = 0x2
   00 23 

public final java.lang.Object apply();
  Signature: ()Ljava/lang/Object;
  Code:
   Stack=1, Locals=2, Args_size=1
	aload_0
	getfield	Field $outer:Lscala/collection/immutable/Stream;
	astore_1
	aload_0
	invokevirtual	Method apply:()Lscala/collection/immutable/Stream;
	areturn
  Labels:
  LocalVariableTable: 
   Start  Length  Slot  Name   Signature
   0      10      0    this       Lscala/collection/immutable/Stream$$anonfun$removeDuplicates$1;


public final scala.collection.immutable.Stream apply();
  Signature: ()Lscala/collection/immutable/Stream;
  Code:
   Stack=8, Locals=6, Args_size=1
	aload_0
	getfield	Field $outer:Lscala/collection/immutable/Stream;
	astore	5
	aload_0
	getfield	Field $outer:Lscala/collection/immutable/Stream;
	invokeinterface	InterfaceMethod scala/collection/TraversableLike.tail:()Ljava/lang/Object;
	checkcast	class scala/collection/immutable/Stream
	aload_0
	getfield	Field $outer:Lscala/collection/immutable/Stream;
	invokeinterface	InterfaceMethod scala/collection/IterableLike.head:()Ljava/lang/Object;
	astore_1
	new	class scala/collection/immutable/Stream$$anonfun$removeDuplicates$1$$anonfun$apply$1
	dup
	aload_0
	aload_1
	invokespecial	Method scala/collection/immutable/Stream$$anonfun$removeDuplicates$1$$anonfun$apply$1."<init>":(Lscala/collection/immutable/Stream$$anonfun$removeDuplicates$1;Ljava/lang/Object;)V
	astore_3
	astore_2
	new	class scala/runtime/ObjectRef
	dup
	aload_2
	new	class scala/collection/immutable/Stream$$anonfun$1
	dup
	aload_2
	aload_3
	invokespecial	Method scala/collection/immutable/Stream$$anonfun$1."<init>":(Lscala/collection/immutable/Stream;Lscala/Function1;)V
	invokevirtual	Method scala/collection/immutable/Stream.dropWhile:(Lscala/Function1;)Lscala/collection/immutable/Stream;
	invokespecial	Method scala/runtime/ObjectRef."<init>":(Ljava/lang/Object;)V
	astore	4
	aload	4
	getfield	Field scala/runtime/ObjectRef.elem:Ljava/lang/Object;
	checkcast	class scala/collection/immutable/Stream
	invokeinterface	InterfaceMethod scala/collection/IterableLike.isEmpty:()Z
	ifeq	l1 // new
	getstatic	Field scala/collection/immutable/Stream$Empty$.MODULE$:Lscala/collection/immutable/Stream$Empty$;
	goto	l2 // invokevirtual
l1	new	class scala/collection/immutable/Stream$Cons
	dup
	aload	4
	getfield	Field scala/runtime/ObjectRef.elem:Ljava/lang/Object;
	checkcast	class scala/collection/immutable/Stream
	invokeinterface	InterfaceMethod scala/collection/IterableLike.head:()Ljava/lang/Object;
	new	class scala/collection/immutable/Stream$$anonfun$filter$1
	dup
	aload_2
	aload_3
	aload	4
	invokespecial	Method scala/collection/immutable/Stream$$anonfun$filter$1."<init>":(Lscala/collection/immutable/Stream;Lscala/Function1;Lscala/runtime/ObjectRef;)V
	invokespecial	Method scala/collection/immutable/Stream$Cons."<init>":(Ljava/lang/Object;Lscala/Function0;)V
l2	invokevirtual	Method scala/collection/immutable/Stream.removeDuplicates:()Lscala/collection/immutable/Stream;
	areturn
  Labels:
   	l1 = 83 // new
   	l2 = 114 // invokevirtual
  LocalVariableTable: 
   Start  Length  Slot  Name   Signature
   0      118      0    this       Lscala/collection/immutable/Stream$$anonfun$removeDuplicates$1;
   77      41      2    $inlThis0       Ljava/lang/Object;
   77      41      3    p$30       Lscala/Function1;
   61      57      4    rest$20       Lscala/runtime/ObjectRef;

  Signature: length = 0x2
   00 69 

public java.lang.String toString();
  Signature: ()Ljava/lang/String;
  Code:
   Stack=1, Locals=1, Args_size=1
	aload_0
	invokestatic	Method scala/Function0$class.toString:(Lscala/Function0;)Ljava/lang/String;
	areturn
  Labels:

}

