Compiled from "Stream.scala"
public final class scala.collection.immutable.Stream$$anonfun$distinct$1$$anonfun$apply$1 extends scala.runtime.AbstractFunction1 implements java.io.Serializable
  SourceFile: "Stream.scala"
  Scala: length = 0x
   
  InnerClass: 
   public final $anonfun$distinct$1=class scala/collection/immutable/Stream$$anonfun$distinct$1 of class scala/collection/immutable/Stream
   public final $anonfun$apply$1=class scala/collection/immutable/Stream$$anonfun$distinct$1$$anonfun$apply$1 of class scala/collection/immutable/Stream$$anonfun$distinct$1
  minor version: 0
  major version: 49
  Constant pool:
Asciz	SourceFile;
Asciz	Stream.scala;
Asciz	<clinit>;
Asciz	()V;
Asciz	Code;
Asciz	serialVersionUID;
Asciz	J;
Asciz	scala/collection/immutable/Stream$$anonfun$distinct$1$$anonfun$apply$1;
class	scala/collection/immutable/Stream$$anonfun$distinct$1$$anonfun$apply$1
NameAndType	serialVersionUID:J
Field	scala/collection/immutable/Stream$$anonfun$distinct$1$$anonfun$apply$1.serialVersionUID:J
Asciz	eta$0$1$1;
Asciz	Ljava/lang/Object;;
Asciz	apply;
Asciz	(Ljava/lang/Object;)Z;
Asciz	LineNumberTable;
NameAndType	eta$0$1$1:Ljava/lang/Object;
Field	scala/collection/immutable/Stream$$anonfun$distinct$1$$anonfun$apply$1.eta$0$1$1:Ljava/lang/Object;
Asciz	java/lang/Number;
class	java/lang/Number
Asciz	scala/runtime/BoxesRunTime;
class	scala/runtime/BoxesRunTime
Asciz	equalsNumObject;
Asciz	(Ljava/lang/Number;Ljava/lang/Object;)Z;
NameAndType	equalsNumObject:(Ljava/lang/Number;Ljava/lang/Object;)Z
Method	scala/runtime/BoxesRunTime.equalsNumObject:(Ljava/lang/Number;Ljava/lang/Object;)Z
Asciz	java/lang/Character;
class	java/lang/Character
Asciz	equalsCharObject;
Asciz	(Ljava/lang/Character;Ljava/lang/Object;)Z;
NameAndType	equalsCharObject:(Ljava/lang/Character;Ljava/lang/Object;)Z
Method	scala/runtime/BoxesRunTime.equalsCharObject:(Ljava/lang/Character;Ljava/lang/Object;)Z
Asciz	java/lang/Object;
class	java/lang/Object
Asciz	equals;
NameAndType	equals:(Ljava/lang/Object;)Z
Method	java/lang/Object.equals:(Ljava/lang/Object;)Z
Asciz	this;
Asciz	Lscala/collection/immutable/Stream$$anonfun$distinct$1$$anonfun$apply$1;;
Asciz	x0;
Asciz	LocalVariableTable;
Asciz	(Ljava/lang/Object;)Ljava/lang/Object;;
NameAndType	apply:(Ljava/lang/Object;)Z
Method	scala/collection/immutable/Stream$$anonfun$distinct$1$$anonfun$apply$1.apply:(Ljava/lang/Object;)Z
Asciz	boxToBoolean;
Asciz	(Z)Ljava/lang/Boolean;;
NameAndType	boxToBoolean:(Z)Ljava/lang/Boolean;
Method	scala/runtime/BoxesRunTime.boxToBoolean:(Z)Ljava/lang/Boolean;
Asciz	v1;
Asciz	<init>;
Asciz	(Lscala/collection/immutable/Stream$$anonfun$distinct$1;Ljava/lang/Object;)V;
Asciz	scala/runtime/AbstractFunction1;
class	scala/runtime/AbstractFunction1
NameAndType	"<init>":()V
Method	scala/runtime/AbstractFunction1."<init>":()V
Asciz	$outer;
Asciz	Lscala/collection/immutable/Stream$$anonfun$distinct$1;;
Asciz	(Lscala/collection/immutable/Stream<TA;>.$anonfun$distinct$1;)V;
Asciz	Signature;
Asciz	Scala;
Asciz	InnerClasses;
Asciz	scala/collection/immutable/Stream$$anonfun$distinct$1;
class	scala/collection/immutable/Stream$$anonfun$distinct$1
Asciz	scala/collection/immutable/Stream;
class	scala/collection/immutable/Stream
Asciz	$anonfun$distinct$1;
Asciz	$anonfun$apply$1;
Asciz	java/io/Serializable;
class	java/io/Serializable

{
public static final long serialVersionUID;
  Signature: J

public final java.lang.Object eta$0$1$1;
  Signature: Ljava/lang/Object;

public static {};
  Signature: ()V
  Code:
   Stack=2, Locals=0, Args_size=0
	lconst_0
	putstatic	Field serialVersionUID:J
	return
  Labels:

public final boolean apply(java.lang.Object);
  Signature: (Ljava/lang/Object;)Z
  Code:
   Stack=2, Locals=3, Args_size=2
	aload_0
	getfield	Field eta$0$1$1:Ljava/lang/Object;
	astore_2
	aload_2
	aload_1
	if_acmpne	l1 // aload_2
	iconst_1
	goto	l2 // ifeq
l1	aload_2
	ifnonnull	l3 // aload_2
	iconst_0
	goto	l2 // ifeq
l3	aload_2
	instanceof	class java/lang/Number
	ifeq	l4 // aload_2
	aload_2
	checkcast	class java/lang/Number
	aload_1
	invokestatic	Method scala/runtime/BoxesRunTime.equalsNumObject:(Ljava/lang/Number;Ljava/lang/Object;)Z
	goto	l2 // ifeq
l4	aload_2
	instanceof	class java/lang/Character
	ifeq	l5 // aload_2
	aload_2
	checkcast	class java/lang/Character
	aload_1
	invokestatic	Method scala/runtime/BoxesRunTime.equalsCharObject:(Ljava/lang/Character;Ljava/lang/Object;)Z
	goto	l2 // ifeq
l5	aload_2
	aload_1
	invokevirtual	Method java/lang/Object.equals:(Ljava/lang/Object;)Z
l2	ifeq	l6 // iconst_1
	iconst_0
	goto	l7 // ireturn
l6	iconst_1
l7	ireturn
  Labels:
   	l1 = 14 // aload_2
   	l3 = 22 // aload_2
   	l4 = 40 // aload_2
   	l5 = 58 // aload_2
   	l2 = 63 // ifeq
   	l6 = 70 // iconst_1
   	l7 = 71 // ireturn
  LocalVariableTable: 
   Start  Length  Slot  Name   Signature
   0      72      0    this       Lscala/collection/immutable/Stream$$anonfun$distinct$1$$anonfun$apply$1;
   10      56      2    x0       Ljava/lang/Object;


public final java.lang.Object apply(java.lang.Object);
  Signature: (Ljava/lang/Object;)Ljava/lang/Object;
  Code:
   Stack=2, Locals=3, Args_size=2
	aload_0
	aload_1
	invokevirtual	Method apply:(Ljava/lang/Object;)Z
	istore_2
	iload_2
	invokestatic	Method scala/runtime/BoxesRunTime.boxToBoolean:(Z)Ljava/lang/Boolean;
	areturn
  Labels:
  LocalVariableTable: 
   Start  Length  Slot  Name   Signature
   0      11      0    this       Lscala/collection/immutable/Stream$$anonfun$distinct$1$$anonfun$apply$1;
   0      11      1    v1       Ljava/lang/Object;


public scala.collection.immutable.Stream$$anonfun$distinct$1$$anonfun$apply$1(scala.collection.immutable.Stream$$anonfun$distinct$1, java.lang.Object);
  Signature: (Lscala/collection/immutable/Stream$$anonfun$distinct$1;Ljava/lang/Object;)V
  Code:
   Stack=2, Locals=3, Args_size=3
	aload_0
	aload_2
	putfield	Field eta$0$1$1:Ljava/lang/Object;
	aload_0
	invokespecial	Method scala/runtime/AbstractFunction1."<init>":()V
	return
  Labels:
  LocalVariableTable: 
   Start  Length  Slot  Name   Signature
   0      10      0    this       Lscala/collection/immutable/Stream$$anonfun$distinct$1$$anonfun$apply$1;
   0      10      1    $outer       Lscala/collection/immutable/Stream$$anonfun$distinct$1;

  Signature: length = 0x2
   00 3A 

}

