Compiled from "Stream.scala"
public final class scala.collection.immutable.Stream$$anonfun$range$1 extends java.lang.Object implements scala.Function0,scala.ScalaObject,java.io.Serializable
  SourceFile: "Stream.scala"
  Scala: length = 0x
   
  InnerClass: 
   public final #61= #9 of #60; //$anonfun$range$1=class scala/collection/immutable/Stream$$anonfun$range$1 of class scala/collection/immutable/Stream
  minor version: 0
  major version: 49
  Constant pool:
const #1 = Asciz	SourceFile;
const #2 = Asciz	Stream.scala;
const #3 = Asciz	<clinit>;
const #4 = Asciz	()V;
const #5 = Asciz	Code;
const #6 = Asciz	serialVersionUID;
const #7 = Asciz	J;
const #8 = Asciz	scala/collection/immutable/Stream$$anonfun$range$1;
const #9 = class	#8;	//  scala/collection/immutable/Stream$$anonfun$range$1
const #10 = NameAndType	#6:#7;//  serialVersionUID:J
const #11 = Field	#9.#10;	//  scala/collection/immutable/Stream$$anonfun$range$1.serialVersionUID:J
const #12 = Asciz	step$2;
const #13 = Asciz	I;
const #14 = Asciz	end$1;
const #15 = Asciz	start$3;
const #16 = Asciz	<init>;
const #17 = Asciz	(III)V;
const #18 = Asciz	LineNumberTable;
const #19 = NameAndType	#15:#13;//  start$3:I
const #20 = Field	#9.#19;	//  scala/collection/immutable/Stream$$anonfun$range$1.start$3:I
const #21 = NameAndType	#14:#13;//  end$1:I
const #22 = Field	#9.#21;	//  scala/collection/immutable/Stream$$anonfun$range$1.end$1:I
const #23 = NameAndType	#12:#13;//  step$2:I
const #24 = Field	#9.#23;	//  scala/collection/immutable/Stream$$anonfun$range$1.step$2:I
const #25 = Asciz	java/lang/Object;
const #26 = class	#25;	//  java/lang/Object
const #27 = NameAndType	#16:#4;//  "<init>":()V
const #28 = Method	#26.#27;	//  java/lang/Object."<init>":()V
const #29 = Asciz	scala/Function0$class;
const #30 = class	#29;	//  scala/Function0$class
const #31 = Asciz	$init$;
const #32 = Asciz	(Lscala/Function0;)V;
const #33 = NameAndType	#31:#32;//  $init$:(Lscala/Function0;)V
const #34 = Method	#30.#33;	//  scala/Function0$class.$init$:(Lscala/Function0;)V
const #35 = Asciz	apply;
const #36 = Asciz	()Ljava/lang/Object;;
const #37 = Asciz	()Lscala/collection/immutable/Stream;;
const #38 = NameAndType	#35:#37;//  apply:()Lscala/collection/immutable/Stream;
const #39 = Method	#9.#38;	//  scala/collection/immutable/Stream$$anonfun$range$1.apply:()Lscala/collection/immutable/Stream;
const #40 = Asciz	scala/collection/immutable/Stream$;
const #41 = class	#40;	//  scala/collection/immutable/Stream$
const #42 = Asciz	MODULE$;
const #43 = Asciz	Lscala/collection/immutable/Stream$;;
const #44 = NameAndType	#42:#43;//  MODULE$:Lscala/collection/immutable/Stream$;
const #45 = Field	#41.#44;	//  scala/collection/immutable/Stream$.MODULE$:Lscala/collection/immutable/Stream$;
const #46 = Asciz	range;
const #47 = Asciz	(III)Lscala/collection/immutable/Stream;;
const #48 = NameAndType	#46:#47;//  range:(III)Lscala/collection/immutable/Stream;
const #49 = Method	#41.#48;	//  scala/collection/immutable/Stream$.range:(III)Lscala/collection/immutable/Stream;
const #50 = Asciz	()Lscala/collection/immutable/Stream<Ljava/lang/Integer;>;;
const #51 = Asciz	Signature;
const #52 = Asciz	toString;
const #53 = Asciz	()Ljava/lang/String;;
const #54 = Asciz	(Lscala/Function0;)Ljava/lang/String;;
const #55 = NameAndType	#52:#54;//  toString:(Lscala/Function0;)Ljava/lang/String;
const #56 = Method	#30.#55;	//  scala/Function0$class.toString:(Lscala/Function0;)Ljava/lang/String;
const #57 = Asciz	Scala;
const #58 = Asciz	InnerClasses;
const #59 = Asciz	scala/collection/immutable/Stream;
const #60 = class	#59;	//  scala/collection/immutable/Stream
const #61 = Asciz	$anonfun$range$1;
const #62 = Asciz	scala/Function0;
const #63 = class	#62;	//  scala/Function0
const #64 = Asciz	scala/ScalaObject;
const #65 = class	#64;	//  scala/ScalaObject
const #66 = Asciz	java/io/Serializable;
const #67 = class	#66;	//  java/io/Serializable

{
public static final long serialVersionUID;

public static {};
  Code:
   Stack=2, Locals=0, Args_size=0
   0:	lconst_0
   1:	putstatic	#11; //Field serialVersionUID:J
   4:	return

public scala.collection.immutable.Stream$$anonfun$range$1(int, int, int);
  Code:
   Stack=2, Locals=4, Args_size=4
   0:	aload_0
   1:	iload_1
   2:	putfield	#20; //Field start$3:I
   5:	aload_0
   6:	iload_2
   7:	putfield	#22; //Field end$1:I
   10:	aload_0
   11:	iload_3
   12:	putfield	#24; //Field step$2:I
   15:	aload_0
   16:	invokespecial	#28; //Method java/lang/Object."<init>":()V
   19:	aload_0
   20:	invokestatic	#34; //Method scala/Function0$class.$init$:(Lscala/Function0;)V
   23:	return
  LineNumberTable: 
   line 546: 0


public final java.lang.Object apply();
  Code:
   Stack=1, Locals=1, Args_size=1
   0:	aload_0
   1:	invokevirtual	#39; //Method apply:()Lscala/collection/immutable/Stream;
   4:	areturn
  LineNumberTable: 
   line 546: 0


public final scala.collection.immutable.Stream apply();
  Code:
   Stack=4, Locals=1, Args_size=1
   0:	getstatic	#45; //Field scala/collection/immutable/Stream$.MODULE$:Lscala/collection/immutable/Stream$;
   3:	aload_0
   4:	getfield	#20; //Field start$3:I
   7:	aload_0
   8:	getfield	#24; //Field step$2:I
   11:	iadd
   12:	aload_0
   13:	getfield	#22; //Field end$1:I
   16:	aload_0
   17:	getfield	#24; //Field step$2:I
   20:	invokevirtual	#49; //Method scala/collection/immutable/Stream$.range:(III)Lscala/collection/immutable/Stream;
   23:	areturn
  LineNumberTable: 
   line 546: 0

  Signature: length = 0x2
   00 32 

public java.lang.String toString();
  Code:
   Stack=1, Locals=1, Args_size=1
   0:	aload_0
   1:	invokestatic	#56; //Method scala/Function0$class.toString:(Lscala/Function0;)Ljava/lang/String;
   4:	areturn
  LineNumberTable: 
   line 546: 0


}

