Compiled from "Stream.scala"
public class scala.collection.immutable.Stream$StreamCanBuildFrom extends scala.collection.generic.TraversableFactory$GenericCanBuildFrom implements scala.ScalaObject
  SourceFile: "Stream.scala"
  Signature: length = 0x2
   00 13 
  Scala: length = 0x
   
  InnerClass: 
   public #26= #23 of #25; //StreamCanBuildFrom=class scala/collection/immutable/Stream$StreamCanBuildFrom of class scala/collection/immutable/Stream
   public #29= #14 of #28; //GenericCanBuildFrom=class scala/collection/generic/TraversableFactory$GenericCanBuildFrom of class scala/collection/generic/TraversableFactory
  minor version: 0
  major version: 49
  Constant pool:
const #1 = Asciz	SourceFile;
const #2 = Asciz	Stream.scala;
const #3 = Asciz	<init>;
const #4 = Asciz	()V;
const #5 = Asciz	Code;
const #6 = Asciz	LineNumberTable;
const #7 = Asciz	scala/collection/immutable/Stream$;
const #8 = class	#7;	//  scala/collection/immutable/Stream$
const #9 = Asciz	MODULE$;
const #10 = Asciz	Lscala/collection/immutable/Stream$;;
const #11 = NameAndType	#9:#10;//  MODULE$:Lscala/collection/immutable/Stream$;
const #12 = Field	#8.#11;	//  scala/collection/immutable/Stream$.MODULE$:Lscala/collection/immutable/Stream$;
const #13 = Asciz	scala/collection/generic/TraversableFactory$GenericCanBuildFrom;
const #14 = class	#13;	//  scala/collection/generic/TraversableFactory$GenericCanBuildFrom
const #15 = Asciz	(Lscala/collection/generic/TraversableFactory;)V;
const #16 = NameAndType	#3:#15;//  "<init>":(Lscala/collection/generic/TraversableFactory;)V
const #17 = Method	#14.#16;	//  scala/collection/generic/TraversableFactory$GenericCanBuildFrom."<init>":(Lscala/collection/generic/TraversableFactory;)V
const #18 = Asciz	Signature;
const #19 = Asciz	<A:Ljava/lang/Object;>Lscala/collection/generic/TraversableFactory<Lscala/collection/immutable/Stream;>.GenericCanBuildFrom<TA;>;Lscala/ScalaObject;;
const #20 = Asciz	Scala;
const #21 = Asciz	InnerClasses;
const #22 = Asciz	scala/collection/immutable/Stream$StreamCanBuildFrom;
const #23 = class	#22;	//  scala/collection/immutable/Stream$StreamCanBuildFrom
const #24 = Asciz	scala/collection/immutable/Stream;
const #25 = class	#24;	//  scala/collection/immutable/Stream
const #26 = Asciz	StreamCanBuildFrom;
const #27 = Asciz	scala/collection/generic/TraversableFactory;
const #28 = class	#27;	//  scala/collection/generic/TraversableFactory
const #29 = Asciz	GenericCanBuildFrom;
const #30 = Asciz	scala/ScalaObject;
const #31 = class	#30;	//  scala/ScalaObject

{
public scala.collection.immutable.Stream$StreamCanBuildFrom();
  Code:
   Stack=2, Locals=1, Args_size=1
   0:	aload_0
   1:	getstatic	#12; //Field scala/collection/immutable/Stream$.MODULE$:Lscala/collection/immutable/Stream$;
   4:	invokespecial	#17; //Method scala/collection/generic/TraversableFactory$GenericCanBuildFrom."<init>":(Lscala/collection/generic/TraversableFactory;)V
   7:	return
  LineNumberTable: 
   line 413: 0

  Signature: length = 0x2
   00 04 

}

