Compiled from "Stream.scala"
public final class scala.collection.immutable.Stream$$anonfun$filter$1 extends scala.runtime.AbstractFunction0 implements java.io.Serializable
  SourceFile: "Stream.scala"
  Scala: length = 0x
   
  InnerClass: 
   public final Cons=class scala/collection/immutable/Stream$Cons of class scala/collection/immutable/Stream
   public final $anonfun$1=class scala/collection/immutable/Stream$$anonfun$1 of class scala/collection/immutable/Stream
   public final $anonfun$filter$1=class scala/collection/immutable/Stream$$anonfun$filter$1 of class scala/collection/immutable/Stream
  minor version: 0
  major version: 49
  Constant pool:
Asciz	SourceFile;
Asciz	Stream.scala;
Asciz	<clinit>;
Asciz	()V;
Asciz	Code;
Asciz	serialVersionUID;
Asciz	J;
Asciz	scala/collection/immutable/Stream$$anonfun$filter$1;
class	scala/collection/immutable/Stream$$anonfun$filter$1
NameAndType	serialVersionUID:J
Field	scala/collection/immutable/Stream$$anonfun$filter$1.serialVersionUID:J
Asciz	rest$2;
Asciz	Lscala/runtime/ObjectRef;;
Asciz	p$3;
Asciz	Lscala/Function1;;
Asciz	<init>;
Asciz	(Lscala/collection/immutable/Stream;Lscala/Function1;Lscala/runtime/ObjectRef;)V;
Asciz	LineNumberTable;
NameAndType	p$3:Lscala/Function1;
Field	scala/collection/immutable/Stream$$anonfun$filter$1.p$3:Lscala/Function1;
NameAndType	rest$2:Lscala/runtime/ObjectRef;
Field	scala/collection/immutable/Stream$$anonfun$filter$1.rest$2:Lscala/runtime/ObjectRef;
Asciz	scala/runtime/AbstractFunction0;
class	scala/runtime/AbstractFunction0
NameAndType	"<init>":()V
Method	scala/runtime/AbstractFunction0."<init>":()V
Asciz	this;
Asciz	Lscala/collection/immutable/Stream$$anonfun$filter$1;;
Asciz	$outer;
Asciz	Lscala/collection/immutable/Stream;;
Asciz	LocalVariableTable;
Asciz	(Lscala/collection/immutable/Stream<TA;>;)V;
Asciz	Signature;
Asciz	apply;
Asciz	()Ljava/lang/Object;;
Asciz	()Lscala/collection/immutable/Stream;;
NameAndType	apply:()Lscala/collection/immutable/Stream;
Method	scala/collection/immutable/Stream$$anonfun$filter$1.apply:()Lscala/collection/immutable/Stream;
Asciz	scala/runtime/ObjectRef;
class	scala/runtime/ObjectRef
Asciz	elem;
Asciz	Ljava/lang/Object;;
NameAndType	elem:Ljava/lang/Object;
Field	scala/runtime/ObjectRef.elem:Ljava/lang/Object;
Asciz	scala/collection/immutable/Stream;
class	scala/collection/immutable/Stream
Asciz	scala/collection/TraversableLike;
class	scala/collection/TraversableLike
Asciz	tail;
NameAndType	tail:()Ljava/lang/Object;
InterfaceMethod	scala/collection/TraversableLike.tail:()Ljava/lang/Object;
Asciz	scala/collection/immutable/Stream$$anonfun$1;
class	scala/collection/immutable/Stream$$anonfun$1
Asciz	(Lscala/collection/immutable/Stream;Lscala/Function1;)V;
NameAndType	"<init>":(Lscala/collection/immutable/Stream;Lscala/Function1;)V
Method	scala/collection/immutable/Stream$$anonfun$1."<init>":(Lscala/collection/immutable/Stream;Lscala/Function1;)V
Asciz	dropWhile;
Asciz	(Lscala/Function1;)Lscala/collection/immutable/Stream;;
NameAndType	dropWhile:(Lscala/Function1;)Lscala/collection/immutable/Stream;
Method	scala/collection/immutable/Stream.dropWhile:(Lscala/Function1;)Lscala/collection/immutable/Stream;
Asciz	(Ljava/lang/Object;)V;
NameAndType	"<init>":(Ljava/lang/Object;)V
Method	scala/runtime/ObjectRef."<init>":(Ljava/lang/Object;)V
Asciz	scala/collection/IterableLike;
class	scala/collection/IterableLike
Asciz	isEmpty;
Asciz	()Z;
NameAndType	isEmpty:()Z
InterfaceMethod	scala/collection/IterableLike.isEmpty:()Z
Asciz	scala/collection/immutable/Stream$Empty$;
class	scala/collection/immutable/Stream$Empty$
Asciz	MODULE$;
Asciz	Lscala/collection/immutable/Stream$Empty$;;
NameAndType	MODULE$:Lscala/collection/immutable/Stream$Empty$;
Field	scala/collection/immutable/Stream$Empty$.MODULE$:Lscala/collection/immutable/Stream$Empty$;
Asciz	scala/collection/immutable/Stream$Cons;
class	scala/collection/immutable/Stream$Cons
Asciz	head;
NameAndType	head:()Ljava/lang/Object;
InterfaceMethod	scala/collection/IterableLike.head:()Ljava/lang/Object;
NameAndType	"<init>":(Lscala/collection/immutable/Stream;Lscala/Function1;Lscala/runtime/ObjectRef;)V
Method	scala/collection/immutable/Stream$$anonfun$filter$1."<init>":(Lscala/collection/immutable/Stream;Lscala/Function1;Lscala/runtime/ObjectRef;)V
Asciz	(Ljava/lang/Object;Lscala/Function0;)V;
NameAndType	"<init>":(Ljava/lang/Object;Lscala/Function0;)V
Method	scala/collection/immutable/Stream$Cons."<init>":(Ljava/lang/Object;Lscala/Function0;)V
Asciz	$inlThis0;
Asciz	p$30;
Asciz	rest$20;
Asciz	()Lscala/collection/immutable/Stream<TA;>;;
Asciz	Scala;
Asciz	InnerClasses;
Asciz	Cons;
Asciz	$anonfun$1;
Asciz	$anonfun$filter$1;
Asciz	java/io/Serializable;
class	java/io/Serializable

{
public static final long serialVersionUID;
  Signature: J

public final scala.runtime.ObjectRef rest$2;
  Signature: Lscala/runtime/ObjectRef;

public final scala.Function1 p$3;
  Signature: Lscala/Function1;

public static {};
  Signature: ()V
  Code:
   Stack=2, Locals=0, Args_size=0
	lconst_0
	putstatic	Field serialVersionUID:J
	return
  Labels:

public scala.collection.immutable.Stream$$anonfun$filter$1(scala.collection.immutable.Stream, scala.Function1, scala.runtime.ObjectRef);
  Signature: (Lscala/collection/immutable/Stream;Lscala/Function1;Lscala/runtime/ObjectRef;)V
  Code:
   Stack=2, Locals=4, Args_size=4
	aload_0
	aload_2
	putfield	Field p$3:Lscala/Function1;
	aload_0
	aload_3
	putfield	Field rest$2:Lscala/runtime/ObjectRef;
	aload_0
	invokespecial	Method scala/runtime/AbstractFunction0."<init>":()V
	return
  Labels:
  LocalVariableTable: 
   Start  Length  Slot  Name   Signature
   0      15      0    this       Lscala/collection/immutable/Stream$$anonfun$filter$1;
   0      15      1    $outer       Lscala/collection/immutable/Stream;

  Signature: length = 0x2
   00 20 

public final java.lang.Object apply();
  Signature: ()Ljava/lang/Object;
  Code:
   Stack=1, Locals=1, Args_size=1
	aload_0
	invokevirtual	Method apply:()Lscala/collection/immutable/Stream;
	areturn
  Labels:

public final scala.collection.immutable.Stream apply();
  Signature: ()Lscala/collection/immutable/Stream;
  Code:
   Stack=8, Locals=4, Args_size=1
	aload_0
	getfield	Field rest$2:Lscala/runtime/ObjectRef;
	getfield	Field scala/runtime/ObjectRef.elem:Ljava/lang/Object;
	checkcast	class scala/collection/immutable/Stream
	invokeinterface	InterfaceMethod scala/collection/TraversableLike.tail:()Ljava/lang/Object;
	checkcast	class scala/collection/immutable/Stream
	aload_0
	getfield	Field p$3:Lscala/Function1;
	astore_2
	astore_1
	new	class scala/runtime/ObjectRef
	dup
	aload_1
	new	class scala/collection/immutable/Stream$$anonfun$1
	dup
	aload_1
	aload_2
	invokespecial	Method scala/collection/immutable/Stream$$anonfun$1."<init>":(Lscala/collection/immutable/Stream;Lscala/Function1;)V
	invokevirtual	Method scala/collection/immutable/Stream.dropWhile:(Lscala/Function1;)Lscala/collection/immutable/Stream;
	invokespecial	Method scala/runtime/ObjectRef."<init>":(Ljava/lang/Object;)V
	astore_3
	aload_3
	getfield	Field scala/runtime/ObjectRef.elem:Ljava/lang/Object;
	checkcast	class scala/collection/immutable/Stream
	invokeinterface	InterfaceMethod scala/collection/IterableLike.isEmpty:()Z
	ifeq	l1 // new
	getstatic	Field scala/collection/immutable/Stream$Empty$.MODULE$:Lscala/collection/immutable/Stream$Empty$;
	goto	l2 // areturn
l1	new	class scala/collection/immutable/Stream$Cons
	dup
	aload_3
	getfield	Field scala/runtime/ObjectRef.elem:Ljava/lang/Object;
	checkcast	class scala/collection/immutable/Stream
	invokeinterface	InterfaceMethod scala/collection/IterableLike.head:()Ljava/lang/Object;
	new	class scala/collection/immutable/Stream$$anonfun$filter$1
	dup
	aload_1
	aload_2
	aload_3
	invokespecial	Method "<init>":(Lscala/collection/immutable/Stream;Lscala/Function1;Lscala/runtime/ObjectRef;)V
	invokespecial	Method scala/collection/immutable/Stream$Cons."<init>":(Ljava/lang/Object;Lscala/Function0;)V
l2	areturn
  Labels:
   	l1 = 66 // new
   	l2 = 95 // areturn
  LocalVariableTable: 
   Start  Length  Slot  Name   Signature
   0      96      0    this       Lscala/collection/immutable/Stream$$anonfun$filter$1;
   60      36      1    $inlThis0       Ljava/lang/Object;
   60      36      2    p$30       Lscala/Function1;
   45      51      3    rest$20       Lscala/runtime/ObjectRef;

  Signature: length = 0x2
   00 59 

}

