Compiled from "Stream.scala"
public final class scala.collection.immutable.Stream$$anonfun$2 extends java.lang.Object implements scala.Function0,scala.ScalaObject,java.io.Serializable
  SourceFile: "Stream.scala"
  Scala: length = 0x
   
  InnerClass: 
   public final $anonfun$2=class scala/collection/immutable/Stream$$anonfun$2 of class scala/collection/immutable/Stream
  minor version: 0
  major version: 49
  Constant pool:
Asciz	SourceFile;
Asciz	Stream.scala;
Asciz	<clinit>;
Asciz	()V;
Asciz	Code;
Asciz	serialVersionUID;
Asciz	J;
Asciz	scala/collection/immutable/Stream$$anonfun$2;
class	scala/collection/immutable/Stream$$anonfun$2
NameAndType	serialVersionUID:J
Field	scala/collection/immutable/Stream$$anonfun$2.serialVersionUID:J
Asciz	result$1;
Asciz	Lscala/runtime/ObjectRef;;
Asciz	<init>;
Asciz	(Lscala/collection/immutable/Stream;Lscala/runtime/ObjectRef;)V;
Asciz	LineNumberTable;
NameAndType	result$1:Lscala/runtime/ObjectRef;
Field	scala/collection/immutable/Stream$$anonfun$2.result$1:Lscala/runtime/ObjectRef;
Asciz	java/lang/Object;
class	java/lang/Object
NameAndType	"<init>":()V
Method	java/lang/Object."<init>":()V
Asciz	scala/Function0$class;
class	scala/Function0$class
Asciz	$init$;
Asciz	(Lscala/Function0;)V;
NameAndType	$init$:(Lscala/Function0;)V
Method	scala/Function0$class.$init$:(Lscala/Function0;)V
Asciz	this;
Asciz	Lscala/collection/immutable/Stream$$anonfun$2;;
Asciz	$outer;
Asciz	Lscala/collection/immutable/Stream;;
Asciz	LocalVariableTable;
Asciz	(Lscala/collection/immutable/Stream<TA;>;)V;
Asciz	Signature;
Asciz	apply;
Asciz	()Ljava/lang/Object;;
Asciz	()Lscala/collection/immutable/Stream;;
NameAndType	apply:()Lscala/collection/immutable/Stream;
Method	scala/collection/immutable/Stream$$anonfun$2.apply:()Lscala/collection/immutable/Stream;
Asciz	scala/runtime/ObjectRef;
class	scala/runtime/ObjectRef
Asciz	elem;
Asciz	Ljava/lang/Object;;
NameAndType	elem:Ljava/lang/Object;
Field	scala/runtime/ObjectRef.elem:Ljava/lang/Object;
Asciz	scala/collection/immutable/Stream;
class	scala/collection/immutable/Stream
Asciz	()Lscala/collection/immutable/Stream<TA;>;;
Asciz	toString;
Asciz	()Ljava/lang/String;;
Asciz	(Lscala/Function0;)Ljava/lang/String;;
NameAndType	toString:(Lscala/Function0;)Ljava/lang/String;
Method	scala/Function0$class.toString:(Lscala/Function0;)Ljava/lang/String;
Asciz	Scala;
Asciz	InnerClasses;
Asciz	$anonfun$2;
Asciz	scala/Function0;
class	scala/Function0
Asciz	scala/ScalaObject;
class	scala/ScalaObject
Asciz	java/io/Serializable;
class	java/io/Serializable

{
public static final long serialVersionUID;
  Signature: J

private final scala.runtime.ObjectRef result$1;
  Signature: Lscala/runtime/ObjectRef;

public static {};
  Signature: ()V
  Code:
   Stack=2, Locals=0, Args_size=0
	lconst_0
	putstatic	Field serialVersionUID:J
	return
  Labels:

public scala.collection.immutable.Stream$$anonfun$2(scala.collection.immutable.Stream, scala.runtime.ObjectRef);
  Signature: (Lscala/collection/immutable/Stream;Lscala/runtime/ObjectRef;)V
  Code:
   Stack=2, Locals=3, Args_size=3
	aload_0
	aload_2
	putfield	Field result$1:Lscala/runtime/ObjectRef;
	aload_0
	invokespecial	Method java/lang/Object."<init>":()V
	aload_0
	invokestatic	Method scala/Function0$class.$init$:(Lscala/Function0;)V
	return
  Labels:
  LocalVariableTable: 
   Start  Length  Slot  Name   Signature
   0      14      0    this       Lscala/collection/immutable/Stream$$anonfun$2;
   0      14      1    $outer       Lscala/collection/immutable/Stream;

  Signature: length = 0x2
   00 22 

public final java.lang.Object apply();
  Signature: ()Ljava/lang/Object;
  Code:
   Stack=1, Locals=1, Args_size=1
	aload_0
	invokevirtual	Method apply:()Lscala/collection/immutable/Stream;
	areturn
  Labels:

public final scala.collection.immutable.Stream apply();
  Signature: ()Lscala/collection/immutable/Stream;
  Code:
   Stack=1, Locals=1, Args_size=1
	aload_0
	getfield	Field result$1:Lscala/runtime/ObjectRef;
	getfield	Field scala/runtime/ObjectRef.elem:Ljava/lang/Object;
	checkcast	class scala/collection/immutable/Stream
	areturn
  Labels:
  Signature: length = 0x2
   00 31 

public java.lang.String toString();
  Signature: ()Ljava/lang/String;
  Code:
   Stack=1, Locals=1, Args_size=1
	aload_0
	invokestatic	Method scala/Function0$class.toString:(Lscala/Function0;)Ljava/lang/String;
	areturn
  Labels:

}

