Compiled from "Stream.scala"
public final class scala.collection.immutable.Stream$$anonfun$loop$4$2 extends java.lang.Object implements scala.Function0,scala.ScalaObject,java.io.Serializable
  SourceFile: "Stream.scala"
  Scala: length = 0x
   
  InnerClass: 
   public final $anonfun$loop$4$2=class scala/collection/immutable/Stream$$anonfun$loop$4$2 of class scala/collection/immutable/Stream
  minor version: 0
  major version: 49
  Constant pool:
Asciz	SourceFile;
Asciz	Stream.scala;
Asciz	<clinit>;
Asciz	()V;
Asciz	Code;
Asciz	serialVersionUID;
Asciz	J;
Asciz	scala/collection/immutable/Stream$$anonfun$loop$4$2;
class	scala/collection/immutable/Stream$$anonfun$loop$4$2
NameAndType	serialVersionUID:J
Field	scala/collection/immutable/Stream$$anonfun$loop$4$2.serialVersionUID:J
Asciz	these$1;
Asciz	Lscala/collection/immutable/Stream;;
Asciz	len$1;
Asciz	I;
Asciz	elem$2;
Asciz	Ljava/lang/Object;;
Asciz	$outer;
Asciz	<init>;
Asciz	(Lscala/collection/immutable/Stream;Ljava/lang/Object;ILscala/collection/immutable/Stream;)V;
Asciz	LineNumberTable;
Asciz	java/lang/NullPointerException;
class	java/lang/NullPointerException
NameAndType	"<init>":()V
Method	java/lang/NullPointerException."<init>":()V
NameAndType	$outer:Lscala/collection/immutable/Stream;
Field	scala/collection/immutable/Stream$$anonfun$loop$4$2.$outer:Lscala/collection/immutable/Stream;
NameAndType	elem$2:Ljava/lang/Object;
Field	scala/collection/immutable/Stream$$anonfun$loop$4$2.elem$2:Ljava/lang/Object;
NameAndType	len$1:I
Field	scala/collection/immutable/Stream$$anonfun$loop$4$2.len$1:I
NameAndType	these$1:Lscala/collection/immutable/Stream;
Field	scala/collection/immutable/Stream$$anonfun$loop$4$2.these$1:Lscala/collection/immutable/Stream;
Asciz	java/lang/Object;
class	java/lang/Object
Method	java/lang/Object."<init>":()V
Asciz	scala/Function0$class;
class	scala/Function0$class
Asciz	$init$;
Asciz	(Lscala/Function0;)V;
NameAndType	$init$:(Lscala/Function0;)V
Method	scala/Function0$class.$init$:(Lscala/Function0;)V
Asciz	this;
Asciz	Lscala/collection/immutable/Stream$$anonfun$loop$4$2;;
Asciz	LocalVariableTable;
Asciz	(Lscala/collection/immutable/Stream<TA;>;)V;
Asciz	Signature;
Asciz	apply;
Asciz	()Ljava/lang/Object;;
Asciz	()Lscala/collection/immutable/Stream;;
NameAndType	apply:()Lscala/collection/immutable/Stream;
Method	scala/collection/immutable/Stream$$anonfun$loop$4$2.apply:()Lscala/collection/immutable/Stream;
Asciz	scala/collection/TraversableLike;
class	scala/collection/TraversableLike
Asciz	tail;
NameAndType	tail:()Ljava/lang/Object;
InterfaceMethod	scala/collection/TraversableLike.tail:()Ljava/lang/Object;
Asciz	scala/collection/immutable/Stream;
class	scala/collection/immutable/Stream
Asciz	loop$4;
Asciz	(ILscala/collection/immutable/Stream;Ljava/lang/Object;)Lscala/collection/immutable/Stream;;
NameAndType	loop$4:(ILscala/collection/immutable/Stream;Ljava/lang/Object;)Lscala/collection/immutable/Stream;
Method	scala/collection/immutable/Stream.loop$4:(ILscala/collection/immutable/Stream;Ljava/lang/Object;)Lscala/collection/immutable/Stream;
Asciz	()Lscala/collection/immutable/Stream<TB;>;;
Asciz	toString;
Asciz	()Ljava/lang/String;;
Asciz	(Lscala/Function0;)Ljava/lang/String;;
NameAndType	toString:(Lscala/Function0;)Ljava/lang/String;
Method	scala/Function0$class.toString:(Lscala/Function0;)Ljava/lang/String;
Asciz	Scala;
Asciz	InnerClasses;
Asciz	$anonfun$loop$4$2;
Asciz	scala/Function0;
class	scala/Function0
Asciz	scala/ScalaObject;
class	scala/ScalaObject
Asciz	java/io/Serializable;
class	java/io/Serializable

{
public static final long serialVersionUID;
  Signature: J

private final scala.collection.immutable.Stream these$1;
  Signature: Lscala/collection/immutable/Stream;

private final int len$1;
  Signature: I

private final java.lang.Object elem$2;
  Signature: Ljava/lang/Object;

private final scala.collection.immutable.Stream $outer;
  Signature: Lscala/collection/immutable/Stream;

public static {};
  Signature: ()V
  Code:
   Stack=2, Locals=0, Args_size=0
	lconst_0
	putstatic	Field serialVersionUID:J
	return
  Labels:

public scala.collection.immutable.Stream$$anonfun$loop$4$2(scala.collection.immutable.Stream, java.lang.Object, int, scala.collection.immutable.Stream);
  Signature: (Lscala/collection/immutable/Stream;Ljava/lang/Object;ILscala/collection/immutable/Stream;)V
  Code:
   Stack=2, Locals=5, Args_size=5
	aload_1
	ifnonnull	l1 // aload_0
	new	class java/lang/NullPointerException
	dup
	invokespecial	Method java/lang/NullPointerException."<init>":()V
	athrow
l1	aload_0
	aload_1
	putfield	Field $outer:Lscala/collection/immutable/Stream;
	aload_0
	aload_2
	putfield	Field elem$2:Ljava/lang/Object;
	aload_0
	iload_3
	putfield	Field len$1:I
	aload_0
	aload	4
	putfield	Field these$1:Lscala/collection/immutable/Stream;
	aload_0
	invokespecial	Method java/lang/Object."<init>":()V
	aload_0
	invokestatic	Method scala/Function0$class.$init$:(Lscala/Function0;)V
	return
  Labels:
   	l1 = 12 // aload_0
  LocalVariableTable: 
   Start  Length  Slot  Name   Signature
   0      42      0    this       Lscala/collection/immutable/Stream$$anonfun$loop$4$2;
   0      42      1    $outer       Lscala/collection/immutable/Stream;

  Signature: length = 0x2
   00 2E 

public final java.lang.Object apply();
  Signature: ()Ljava/lang/Object;
  Code:
   Stack=1, Locals=2, Args_size=1
	aload_0
	getfield	Field $outer:Lscala/collection/immutable/Stream;
	astore_1
	aload_0
	invokevirtual	Method apply:()Lscala/collection/immutable/Stream;
	areturn
  Labels:
  LocalVariableTable: 
   Start  Length  Slot  Name   Signature
   0      10      0    this       Lscala/collection/immutable/Stream$$anonfun$loop$4$2;


public final scala.collection.immutable.Stream apply();
  Signature: ()Lscala/collection/immutable/Stream;
  Code:
   Stack=4, Locals=2, Args_size=1
	aload_0
	getfield	Field $outer:Lscala/collection/immutable/Stream;
	astore_1
	aload_0
	getfield	Field $outer:Lscala/collection/immutable/Stream;
	aload_0
	getfield	Field len$1:I
	iconst_1
	isub
	aload_0
	getfield	Field these$1:Lscala/collection/immutable/Stream;
	invokeinterface	InterfaceMethod scala/collection/TraversableLike.tail:()Ljava/lang/Object;
	checkcast	class scala/collection/immutable/Stream
	aload_0
	getfield	Field elem$2:Ljava/lang/Object;
	invokevirtual	Method scala/collection/immutable/Stream.loop$4:(ILscala/collection/immutable/Stream;Ljava/lang/Object;)Lscala/collection/immutable/Stream;
	areturn
  Labels:
  LocalVariableTable: 
   Start  Length  Slot  Name   Signature
   0      35      0    this       Lscala/collection/immutable/Stream$$anonfun$loop$4$2;

  Signature: length = 0x2
   00 40 

public java.lang.String toString();
  Signature: ()Ljava/lang/String;
  Code:
   Stack=1, Locals=1, Args_size=1
	aload_0
	invokestatic	Method scala/Function0$class.toString:(Lscala/Function0;)Ljava/lang/String;
	areturn
  Labels:

}

