Compiled from "Stream.scala"
public final class scala.collection.immutable.Stream$StreamBuilder$$anonfun$result$1 extends java.lang.Object implements scala.Function1,scala.ScalaObject,java.io.Serializable
  SourceFile: "Stream.scala"
  Scala: length = 0x
   
  InnerClass: 
   public StreamBuilder=class scala/collection/immutable/Stream$StreamBuilder of class scala/collection/immutable/Stream
   public final $anonfun$result$1=class scala/collection/immutable/Stream$StreamBuilder$$anonfun$result$1 of class scala/collection/immutable/Stream$StreamBuilder
   public final $anonfun$apply$2=class scala/collection/immutable/Stream$StreamBuilder$$anonfun$result$1$$anonfun$apply$2 of class scala/collection/immutable/Stream$StreamBuilder$$anonfun$result$1
  minor version: 0
  major version: 49
  Constant pool:
Asciz	SourceFile;
Asciz	Stream.scala;
Asciz	<clinit>;
Asciz	()V;
Asciz	Code;
Asciz	serialVersionUID;
Asciz	J;
Asciz	scala/collection/immutable/Stream$StreamBuilder$$anonfun$result$1;
class	scala/collection/immutable/Stream$StreamBuilder$$anonfun$result$1
NameAndType	serialVersionUID:J
Field	scala/collection/immutable/Stream$StreamBuilder$$anonfun$result$1.serialVersionUID:J
Asciz	<init>;
Asciz	(Lscala/collection/immutable/Stream$StreamBuilder;)V;
Asciz	LineNumberTable;
Asciz	java/lang/Object;
class	java/lang/Object
NameAndType	"<init>":()V
Method	java/lang/Object."<init>":()V
Asciz	scala/Function1$class;
class	scala/Function1$class
Asciz	$init$;
Asciz	(Lscala/Function1;)V;
NameAndType	$init$:(Lscala/Function1;)V
Method	scala/Function1$class.$init$:(Lscala/Function1;)V
Asciz	this;
Asciz	Lscala/collection/immutable/Stream$StreamBuilder$$anonfun$result$1;;
Asciz	$outer;
Asciz	Lscala/collection/immutable/Stream$StreamBuilder;;
Asciz	LocalVariableTable;
Asciz	(Lscala/collection/immutable/Stream$StreamBuilder<TA;>;)V;
Asciz	Signature;
Asciz	apply;
Asciz	(Ljava/lang/Object;)Ljava/lang/Object;;
Asciz	scala/collection/Traversable;
class	scala/collection/Traversable
Asciz	(Lscala/collection/Traversable;)Lscala/collection/Iterator;;
NameAndType	apply:(Lscala/collection/Traversable;)Lscala/collection/Iterator;
Method	scala/collection/immutable/Stream$StreamBuilder$$anonfun$result$1.apply:(Lscala/collection/Traversable;)Lscala/collection/Iterator;
Asciz	v1;
Asciz	Ljava/lang/Object;;
Asciz	scala/collection/TraversableLike;
class	scala/collection/TraversableLike
Asciz	toIterable;
Asciz	()Lscala/collection/Iterable;;
NameAndType	toIterable:()Lscala/collection/Iterable;
InterfaceMethod	scala/collection/TraversableLike.toIterable:()Lscala/collection/Iterable;
Asciz	scala/collection/IterableLike;
class	scala/collection/IterableLike
Asciz	iterator;
Asciz	()Lscala/collection/Iterator;;
NameAndType	iterator:()Lscala/collection/Iterator;
InterfaceMethod	scala/collection/IterableLike.iterator:()Lscala/collection/Iterator;
Asciz	scala/collection/immutable/Stream$StreamBuilder$$anonfun$result$1$$anonfun$apply$2;
class	scala/collection/immutable/Stream$StreamBuilder$$anonfun$result$1$$anonfun$apply$2
Asciz	(Lscala/collection/immutable/Stream$StreamBuilder$$anonfun$result$1;)V;
NameAndType	"<init>":(Lscala/collection/immutable/Stream$StreamBuilder$$anonfun$result$1;)V
Method	scala/collection/immutable/Stream$StreamBuilder$$anonfun$result$1$$anonfun$apply$2."<init>":(Lscala/collection/immutable/Stream$StreamBuilder$$anonfun$result$1;)V
Asciz	scala/collection/Iterator;
class	scala/collection/Iterator
Asciz	map;
Asciz	(Lscala/Function1;)Lscala/collection/Iterator;;
NameAndType	map:(Lscala/Function1;)Lscala/collection/Iterator;
InterfaceMethod	scala/collection/Iterator.map:(Lscala/Function1;)Lscala/collection/Iterator;
Asciz	xs;
Asciz	Lscala/collection/Traversable;;
Asciz	(Lscala/collection/Traversable<TA;>;)Lscala/collection/Iterator<TA;>;;
Asciz	andThen;
Asciz	(Lscala/Function1;)Lscala/Function1;;
Asciz	(Lscala/Function1;Lscala/Function1;)Lscala/Function1;;
NameAndType	andThen:(Lscala/Function1;Lscala/Function1;)Lscala/Function1;
Method	scala/Function1$class.andThen:(Lscala/Function1;Lscala/Function1;)Lscala/Function1;
Asciz	g;
Asciz	Lscala/Function1;;
Asciz	compose;
NameAndType	compose:(Lscala/Function1;Lscala/Function1;)Lscala/Function1;
Method	scala/Function1$class.compose:(Lscala/Function1;Lscala/Function1;)Lscala/Function1;
Asciz	toString;
Asciz	()Ljava/lang/String;;
Asciz	(Lscala/Function1;)Ljava/lang/String;;
NameAndType	toString:(Lscala/Function1;)Ljava/lang/String;
Method	scala/Function1$class.toString:(Lscala/Function1;)Ljava/lang/String;
Asciz	Scala;
Asciz	InnerClasses;
Asciz	scala/collection/immutable/Stream$StreamBuilder;
class	scala/collection/immutable/Stream$StreamBuilder
Asciz	scala/collection/immutable/Stream;
class	scala/collection/immutable/Stream
Asciz	StreamBuilder;
Asciz	$anonfun$result$1;
Asciz	$anonfun$apply$2;
Asciz	scala/Function1;
class	scala/Function1
Asciz	scala/ScalaObject;
class	scala/ScalaObject
Asciz	java/io/Serializable;
class	java/io/Serializable

{
public static final long serialVersionUID;
  Signature: J

public static {};
  Signature: ()V
  Code:
   Stack=2, Locals=0, Args_size=0
	lconst_0
	putstatic	Field serialVersionUID:J
	return
  Labels:

public scala.collection.immutable.Stream$StreamBuilder$$anonfun$result$1(scala.collection.immutable.Stream$StreamBuilder);
  Signature: (Lscala/collection/immutable/Stream$StreamBuilder;)V
  Code:
   Stack=1, Locals=2, Args_size=2
	aload_0
	invokespecial	Method java/lang/Object."<init>":()V
	aload_0
	invokestatic	Method scala/Function1$class.$init$:(Lscala/Function1;)V
	return
  Labels:
  LocalVariableTable: 
   Start  Length  Slot  Name   Signature
   0      9      0    this       Lscala/collection/immutable/Stream$StreamBuilder$$anonfun$result$1;
   0      9      1    $outer       Lscala/collection/immutable/Stream$StreamBuilder;

  Signature: length = 0x2
   00 1E 

public final java.lang.Object apply(java.lang.Object);
  Signature: (Ljava/lang/Object;)Ljava/lang/Object;
  Code:
   Stack=2, Locals=2, Args_size=2
	aload_0
	aload_1
	checkcast	class scala/collection/Traversable
	invokevirtual	Method apply:(Lscala/collection/Traversable;)Lscala/collection/Iterator;
	areturn
  Labels:
  LocalVariableTable: 
   Start  Length  Slot  Name   Signature
   0      9      0    this       Lscala/collection/immutable/Stream$StreamBuilder$$anonfun$result$1;
   0      9      1    v1       Ljava/lang/Object;


public final scala.collection.Iterator apply(scala.collection.Traversable);
  Signature: (Lscala/collection/Traversable;)Lscala/collection/Iterator;
  Code:
   Stack=4, Locals=2, Args_size=2
	aload_1
	invokeinterface	InterfaceMethod scala/collection/TraversableLike.toIterable:()Lscala/collection/Iterable;
	invokeinterface	InterfaceMethod scala/collection/IterableLike.iterator:()Lscala/collection/Iterator;
	new	class scala/collection/immutable/Stream$StreamBuilder$$anonfun$result$1$$anonfun$apply$2
	dup
	aload_0
	invokespecial	Method scala/collection/immutable/Stream$StreamBuilder$$anonfun$result$1$$anonfun$apply$2."<init>":(Lscala/collection/immutable/Stream$StreamBuilder$$anonfun$result$1;)V
	invokeinterface	InterfaceMethod scala/collection/Iterator.map:(Lscala/Function1;)Lscala/collection/Iterator;
	areturn
  Labels:
  LocalVariableTable: 
   Start  Length  Slot  Name   Signature
   0      25      0    this       Lscala/collection/immutable/Stream$StreamBuilder$$anonfun$result$1;
   0      25      1    xs       Lscala/collection/Traversable;

  Signature: length = 0x2
   00 42 

public scala.Function1 andThen(scala.Function1);
  Signature: (Lscala/Function1;)Lscala/Function1;
  Code:
   Stack=2, Locals=2, Args_size=2
	aload_0
	aload_1
	invokestatic	Method scala/Function1$class.andThen:(Lscala/Function1;Lscala/Function1;)Lscala/Function1;
	areturn
  Labels:
  LocalVariableTable: 
   Start  Length  Slot  Name   Signature
   0      6      0    this       Lscala/collection/immutable/Stream$StreamBuilder$$anonfun$result$1;
   0      6      1    g       Lscala/Function1;


public scala.Function1 compose(scala.Function1);
  Signature: (Lscala/Function1;)Lscala/Function1;
  Code:
   Stack=2, Locals=2, Args_size=2
	aload_0
	aload_1
	invokestatic	Method scala/Function1$class.compose:(Lscala/Function1;Lscala/Function1;)Lscala/Function1;
	areturn
  Labels:
  LocalVariableTable: 
   Start  Length  Slot  Name   Signature
   0      6      0    this       Lscala/collection/immutable/Stream$StreamBuilder$$anonfun$result$1;
   0      6      1    g       Lscala/Function1;


public java.lang.String toString();
  Signature: ()Ljava/lang/String;
  Code:
   Stack=1, Locals=1, Args_size=1
	aload_0
	invokestatic	Method scala/Function1$class.toString:(Lscala/Function1;)Ljava/lang/String;
	areturn
  Labels:

}

