Compiled from "Stream.scala"
public final class scala.collection.immutable.Stream$$anonfun$$plus$plus$1 extends scala.runtime.AbstractFunction0 implements java.io.Serializable
  SourceFile: "Stream.scala"
  Scala: length = 0x
   
  InnerClass: 
   public StreamCanBuildFrom=class scala/collection/immutable/Stream$StreamCanBuildFrom of class scala/collection/immutable/Stream
   public final $anonfun$$plus$plus$1=class scala/collection/immutable/Stream$$anonfun$$plus$plus$1 of class scala/collection/immutable/Stream
  minor version: 0
  major version: 49
  Constant pool:
Asciz	SourceFile;
Asciz	Stream.scala;
Asciz	<clinit>;
Asciz	()V;
Asciz	Code;
Asciz	serialVersionUID;
Asciz	J;
Asciz	scala/collection/immutable/Stream$$anonfun$$plus$plus$1;
class	scala/collection/immutable/Stream$$anonfun$$plus$plus$1
NameAndType	serialVersionUID:J
Field	scala/collection/immutable/Stream$$anonfun$$plus$plus$1.serialVersionUID:J
Asciz	$outer;
Asciz	Lscala/collection/immutable/Stream;;
Asciz	that$1;
Asciz	Lscala/collection/TraversableOnce;;
Asciz	apply;
Asciz	()Lscala/collection/immutable/Stream;;
Asciz	LineNumberTable;
NameAndType	$outer:Lscala/collection/immutable/Stream;
Field	scala/collection/immutable/Stream$$anonfun$$plus$plus$1.$outer:Lscala/collection/immutable/Stream;
Asciz	scala/collection/TraversableLike;
class	scala/collection/TraversableLike
Asciz	tail;
Asciz	()Ljava/lang/Object;;
NameAndType	tail:()Ljava/lang/Object;
InterfaceMethod	scala/collection/TraversableLike.tail:()Ljava/lang/Object;
Asciz	scala/collection/immutable/Stream;
class	scala/collection/immutable/Stream
NameAndType	that$1:Lscala/collection/TraversableOnce;
Field	scala/collection/immutable/Stream$$anonfun$$plus$plus$1.that$1:Lscala/collection/TraversableOnce;
Asciz	scala/collection/immutable/Stream$StreamCanBuildFrom;
class	scala/collection/immutable/Stream$StreamCanBuildFrom
Asciz	<init>;
NameAndType	"<init>":()V
Method	scala/collection/immutable/Stream$StreamCanBuildFrom."<init>":()V
Asciz	$plus$plus;
Asciz	(Lscala/collection/TraversableOnce;Lscala/collection/generic/CanBuildFrom;)Ljava/lang/Object;;
NameAndType	$plus$plus:(Lscala/collection/TraversableOnce;Lscala/collection/generic/CanBuildFrom;)Ljava/lang/Object;
Method	scala/collection/immutable/Stream.$plus$plus:(Lscala/collection/TraversableOnce;Lscala/collection/generic/CanBuildFrom;)Ljava/lang/Object;
Asciz	this;
Asciz	Lscala/collection/immutable/Stream$$anonfun$$plus$plus$1;;
Asciz	LocalVariableTable;
Asciz	()Lscala/collection/immutable/Stream<TA;>;;
Asciz	Signature;
NameAndType	apply:()Lscala/collection/immutable/Stream;
Method	scala/collection/immutable/Stream$$anonfun$$plus$plus$1.apply:()Lscala/collection/immutable/Stream;
Asciz	(Lscala/collection/immutable/Stream;Lscala/collection/TraversableOnce;)V;
Asciz	java/lang/NullPointerException;
class	java/lang/NullPointerException
Method	java/lang/NullPointerException."<init>":()V
Asciz	scala/runtime/AbstractFunction0;
class	scala/runtime/AbstractFunction0
Method	scala/runtime/AbstractFunction0."<init>":()V
Asciz	(Lscala/collection/immutable/Stream<TA;>;)V;
Asciz	Scala;
Asciz	InnerClasses;
Asciz	StreamCanBuildFrom;
Asciz	$anonfun$$plus$plus$1;
Asciz	java/io/Serializable;
class	java/io/Serializable

{
public static final long serialVersionUID;
  Signature: J

public final scala.collection.immutable.Stream $outer;
  Signature: Lscala/collection/immutable/Stream;

public final scala.collection.TraversableOnce that$1;
  Signature: Lscala/collection/TraversableOnce;

public static {};
  Signature: ()V
  Code:
   Stack=2, Locals=0, Args_size=0
	lconst_0
	putstatic	Field serialVersionUID:J
	return
  Labels:

public final scala.collection.immutable.Stream apply();
  Signature: ()Lscala/collection/immutable/Stream;
  Code:
   Stack=4, Locals=2, Args_size=1
	aload_0
	getfield	Field $outer:Lscala/collection/immutable/Stream;
	invokeinterface	InterfaceMethod scala/collection/TraversableLike.tail:()Ljava/lang/Object;
	checkcast	class scala/collection/immutable/Stream
	aload_0
	getfield	Field that$1:Lscala/collection/TraversableOnce;
	new	class scala/collection/immutable/Stream$StreamCanBuildFrom
	dup
	invokespecial	Method scala/collection/immutable/Stream$StreamCanBuildFrom."<init>":()V
	invokevirtual	Method scala/collection/immutable/Stream.$plus$plus:(Lscala/collection/TraversableOnce;Lscala/collection/generic/CanBuildFrom;)Ljava/lang/Object;
	astore_1
	aload_1
	checkcast	class scala/collection/immutable/Stream
	areturn
  Labels:
  LocalVariableTable: 
   Start  Length  Slot  Name   Signature
   0      32      0    this       Lscala/collection/immutable/Stream$$anonfun$$plus$plus$1;

  Signature: length = 0x2
   00 2B 

public final java.lang.Object apply();
  Signature: ()Ljava/lang/Object;
  Code:
   Stack=1, Locals=1, Args_size=1
	aload_0
	invokevirtual	Method apply:()Lscala/collection/immutable/Stream;
	areturn
  Labels:

public scala.collection.immutable.Stream$$anonfun$$plus$plus$1(scala.collection.immutable.Stream, scala.collection.TraversableOnce);
  Signature: (Lscala/collection/immutable/Stream;Lscala/collection/TraversableOnce;)V
  Code:
   Stack=2, Locals=3, Args_size=3
	aload_1
	ifnonnull	l1 // aload_0
	new	class java/lang/NullPointerException
	dup
	invokespecial	Method java/lang/NullPointerException."<init>":()V
	athrow
l1	aload_0
	aload_1
	putfield	Field $outer:Lscala/collection/immutable/Stream;
	aload_0
	aload_2
	putfield	Field that$1:Lscala/collection/TraversableOnce;
	aload_0
	invokespecial	Method scala/runtime/AbstractFunction0."<init>":()V
	return
  Labels:
   	l1 = 12 // aload_0
  LocalVariableTable: 
   Start  Length  Slot  Name   Signature
   0      27      0    this       Lscala/collection/immutable/Stream$$anonfun$$plus$plus$1;
   0      27      1    $outer       Lscala/collection/immutable/Stream;

  Signature: length = 0x2
   00 36 

}

