Compiled from "Stream.scala"
public final class scala.collection.immutable.Stream$$anonfun$const$1 extends java.lang.Object implements scala.Function0,scala.ScalaObject,java.io.Serializable
  SourceFile: "Stream.scala"
  Scala: length = 0x
   
  InnerClass: 
   public final $anonfun$const$1=class scala/collection/immutable/Stream$$anonfun$const$1 of class scala/collection/immutable/Stream
  minor version: 0
  major version: 49
  Constant pool:
Asciz	SourceFile;
Asciz	Stream.scala;
Asciz	<clinit>;
Asciz	()V;
Asciz	Code;
Asciz	serialVersionUID;
Asciz	J;
Asciz	scala/collection/immutable/Stream$$anonfun$const$1;
class	scala/collection/immutable/Stream$$anonfun$const$1
NameAndType	serialVersionUID:J
Field	scala/collection/immutable/Stream$$anonfun$const$1.serialVersionUID:J
Asciz	elem$4;
Asciz	Ljava/lang/Object;;
Asciz	<init>;
Asciz	(Ljava/lang/Object;)V;
Asciz	LineNumberTable;
NameAndType	elem$4:Ljava/lang/Object;
Field	scala/collection/immutable/Stream$$anonfun$const$1.elem$4:Ljava/lang/Object;
Asciz	java/lang/Object;
class	java/lang/Object
NameAndType	"<init>":()V
Method	java/lang/Object."<init>":()V
Asciz	scala/Function0$class;
class	scala/Function0$class
Asciz	$init$;
Asciz	(Lscala/Function0;)V;
NameAndType	$init$:(Lscala/Function0;)V
Method	scala/Function0$class.$init$:(Lscala/Function0;)V
Asciz	apply;
Asciz	()Ljava/lang/Object;;
Asciz	()Lscala/collection/immutable/Stream;;
NameAndType	apply:()Lscala/collection/immutable/Stream;
Method	scala/collection/immutable/Stream$$anonfun$const$1.apply:()Lscala/collection/immutable/Stream;
Asciz	scala/collection/immutable/Stream$;
class	scala/collection/immutable/Stream$
Asciz	MODULE$;
Asciz	Lscala/collection/immutable/Stream$;;
NameAndType	MODULE$:Lscala/collection/immutable/Stream$;
Field	scala/collection/immutable/Stream$.MODULE$:Lscala/collection/immutable/Stream$;
Asciz	const;
Asciz	(Ljava/lang/Object;)Lscala/collection/immutable/Stream;;
NameAndType	const:(Ljava/lang/Object;)Lscala/collection/immutable/Stream;
Method	scala/collection/immutable/Stream$.const:(Ljava/lang/Object;)Lscala/collection/immutable/Stream;
Asciz	()Lscala/collection/immutable/Stream<TA;>;;
Asciz	Signature;
Asciz	toString;
Asciz	()Ljava/lang/String;;
Asciz	(Lscala/Function0;)Ljava/lang/String;;
NameAndType	toString:(Lscala/Function0;)Ljava/lang/String;
Method	scala/Function0$class.toString:(Lscala/Function0;)Ljava/lang/String;
Asciz	Scala;
Asciz	InnerClasses;
Asciz	scala/collection/immutable/Stream;
class	scala/collection/immutable/Stream
Asciz	$anonfun$const$1;
Asciz	scala/Function0;
class	scala/Function0
Asciz	scala/ScalaObject;
class	scala/ScalaObject
Asciz	java/io/Serializable;
class	java/io/Serializable

{
public static final long serialVersionUID;
  Signature: J

private final java.lang.Object elem$4;
  Signature: Ljava/lang/Object;

public static {};
  Signature: ()V
  Code:
   Stack=2, Locals=0, Args_size=0
	lconst_0
	putstatic	Field serialVersionUID:J
	return
  Labels:

public scala.collection.immutable.Stream$$anonfun$const$1(java.lang.Object);
  Signature: (Ljava/lang/Object;)V
  Code:
   Stack=2, Locals=2, Args_size=2
	aload_0
	aload_1
	putfield	Field elem$4:Ljava/lang/Object;
	aload_0
	invokespecial	Method java/lang/Object."<init>":()V
	aload_0
	invokestatic	Method scala/Function0$class.$init$:(Lscala/Function0;)V
	return
  Labels:

public final java.lang.Object apply();
  Signature: ()Ljava/lang/Object;
  Code:
   Stack=1, Locals=1, Args_size=1
	aload_0
	invokevirtual	Method apply:()Lscala/collection/immutable/Stream;
	areturn
  Labels:

public final scala.collection.immutable.Stream apply();
  Signature: ()Lscala/collection/immutable/Stream;
  Code:
   Stack=2, Locals=1, Args_size=1
	getstatic	Field scala/collection/immutable/Stream$.MODULE$:Lscala/collection/immutable/Stream$;
	aload_0
	getfield	Field elem$4:Ljava/lang/Object;
	invokevirtual	Method scala/collection/immutable/Stream$.const:(Ljava/lang/Object;)Lscala/collection/immutable/Stream;
	areturn
  Labels:
  Signature: length = 0x2
   00 2C 

public java.lang.String toString();
  Signature: ()Ljava/lang/String;
  Code:
   Stack=1, Locals=1, Args_size=1
	aload_0
	invokestatic	Method scala/Function0$class.toString:(Lscala/Function0;)Ljava/lang/String;
	areturn
  Labels:

}

