Compiled from "Stream.scala"
public final class scala.collection.immutable.Stream$Cons extends scala.collection.immutable.Stream implements scala.ScalaObject,java.io.Serializable
  SourceFile: "Stream.scala"
  Signature: length = 0x2
   00 3C 
  Scala: length = 0x
   
  InnerClass: 
   public final #63= #11 of #32; //Cons=class scala/collection/immutable/Stream$Cons of class scala/collection/immutable/Stream
  minor version: 0
  major version: 49
  Constant pool:
const #1 = Asciz	SourceFile;
const #2 = Asciz	Stream.scala;
const #3 = Asciz	<clinit>;
const #4 = Asciz	()V;
const #5 = Asciz	Code;
const #6 = Asciz	serialVersionUID;
const #7 = Asciz	J;
const #8 = long	-602202424901551803l;
const #10 = Asciz	scala/collection/immutable/Stream$Cons;
const #11 = class	#10;	//  scala/collection/immutable/Stream$Cons
const #12 = NameAndType	#6:#7;//  serialVersionUID:J
const #13 = Field	#11.#12;	//  scala/collection/immutable/Stream$Cons.serialVersionUID:J
const #14 = Asciz	tlVal;
const #15 = Asciz	Lscala/collection/immutable/Stream;;
const #16 = Asciz	Lscala/collection/immutable/Stream<TA;>;;
const #17 = Asciz	Signature;
const #18 = Asciz	tl;
const #19 = Asciz	Lscala/Function0;;
const #20 = Asciz	Lscala/Function0<Lscala/collection/immutable/Stream<TA;>;>;;
const #21 = Asciz	hd;
const #22 = Asciz	Ljava/lang/Object;;
const #23 = Asciz	TA;;
const #24 = Asciz	<init>;
const #25 = Asciz	(Ljava/lang/Object;Lscala/Function0;)V;
const #26 = Asciz	LineNumberTable;
const #27 = NameAndType	#21:#22;//  hd:Ljava/lang/Object;
const #28 = Field	#11.#27;	//  scala/collection/immutable/Stream$Cons.hd:Ljava/lang/Object;
const #29 = NameAndType	#18:#19;//  tl:Lscala/Function0;
const #30 = Field	#11.#29;	//  scala/collection/immutable/Stream$Cons.tl:Lscala/Function0;
const #31 = Asciz	scala/collection/immutable/Stream;
const #32 = class	#31;	//  scala/collection/immutable/Stream
const #33 = NameAndType	#24:#4;//  "<init>":()V
const #34 = Method	#32.#33;	//  scala/collection/immutable/Stream."<init>":()V
const #35 = Asciz	this;
const #36 = Asciz	Lscala/collection/immutable/Stream$Cons;;
const #37 = Asciz	LocalVariableTable;
const #38 = Asciz	(TA;Lscala/Function0<Lscala/collection/immutable/Stream<TA;>;>;)V;
const #39 = Asciz	tail;
const #40 = Asciz	()Ljava/lang/Object;;
const #41 = Asciz	()Lscala/collection/immutable/Stream;;
const #42 = NameAndType	#39:#41;//  tail:()Lscala/collection/immutable/Stream;
const #43 = Method	#11.#42;	//  scala/collection/immutable/Stream$Cons.tail:()Lscala/collection/immutable/Stream;
const #44 = Asciz	()Lscala/collection/LinearSeqLike;;
const #45 = Asciz	tailDefined;
const #46 = Asciz	()Z;
const #47 = NameAndType	#45:#46;//  tailDefined:()Z
const #48 = Method	#11.#47;	//  scala/collection/immutable/Stream$Cons.tailDefined:()Z
const #49 = Asciz	scala/Function0;
const #50 = class	#49;	//  scala/Function0
const #51 = Asciz	apply;
const #52 = NameAndType	#51:#40;//  apply:()Ljava/lang/Object;
const #53 = InterfaceMethod	#50.#52;	//  scala/Function0.apply:()Ljava/lang/Object;
const #54 = NameAndType	#14:#15;//  tlVal:Lscala/collection/immutable/Stream;
const #55 = Field	#11.#54;	//  scala/collection/immutable/Stream$Cons.tlVal:Lscala/collection/immutable/Stream;
const #56 = Asciz	()Lscala/collection/immutable/Stream<TA;>;;
const #57 = Asciz	head;
const #58 = Asciz	()TA;;
const #59 = Asciz	isEmpty;
const #60 = Asciz	<A:Ljava/lang/Object;>Lscala/collection/immutable/Stream<TA;>;Lscala/ScalaObject;;
const #61 = Asciz	Scala;
const #62 = Asciz	InnerClasses;
const #63 = Asciz	Cons;
const #64 = Asciz	scala/ScalaObject;
const #65 = class	#64;	//  scala/ScalaObject
const #66 = Asciz	java/io/Serializable;
const #67 = class	#66;	//  java/io/Serializable

{
public static final long serialVersionUID;

public static {};
  Code:
   Stack=2, Locals=0, Args_size=0
   0:	ldc2_w	#8; //long -602202424901551803l
   3:	putstatic	#13; //Field serialVersionUID:J
   6:	return

public scala.collection.immutable.Stream$Cons(java.lang.Object, scala.Function0);
  Code:
   Stack=2, Locals=3, Args_size=3
   0:	aload_0
   1:	aload_1
   2:	putfield	#28; //Field hd:Ljava/lang/Object;
   5:	aload_0
   6:	aload_2
   7:	putfield	#30; //Field tl:Lscala/Function0;
   10:	aload_0
   11:	invokespecial	#34; //Method scala/collection/immutable/Stream."<init>":()V
   14:	return
  LineNumberTable: 
   line 484: 0

  LocalVariableTable: 
   Start  Length  Slot  Name   Signature
   0      15      0    this       Lscala/collection/immutable/Stream$Cons;
   0      15      1    hd       Ljava/lang/Object;
   0      15      2    tl       Lscala/Function0;

  Signature: length = 0x2
   00 26 

public java.lang.Object tail();
  Code:
   Stack=1, Locals=1, Args_size=1
   0:	aload_0
   1:	invokevirtual	#43; //Method tail:()Lscala/collection/immutable/Stream;
   4:	areturn
  LineNumberTable: 
   line 484: 0


public scala.collection.LinearSeqLike tail();
  Code:
   Stack=1, Locals=1, Args_size=1
   0:	aload_0
   1:	invokevirtual	#43; //Method tail:()Lscala/collection/immutable/Stream;
   4:	areturn
  LineNumberTable: 
   line 484: 0


public scala.collection.immutable.Stream tail();
  Code:
   Stack=2, Locals=1, Args_size=1
   0:	aload_0
   1:	invokevirtual	#48; //Method tailDefined:()Z
   4:	ifne	23
   7:	aload_0
   8:	aload_0
   9:	getfield	#30; //Field tl:Lscala/Function0;
   12:	invokeinterface	#53,  1; //InterfaceMethod scala/Function0.apply:()Ljava/lang/Object;
   17:	checkcast	#32; //class scala/collection/immutable/Stream
   20:	putfield	#55; //Field tlVal:Lscala/collection/immutable/Stream;
   23:	aload_0
   24:	getfield	#55; //Field tlVal:Lscala/collection/immutable/Stream;
   27:	areturn
  LineNumberTable: 
   line 490: 0
   line 491: 23

  Signature: length = 0x2
   00 38 

public boolean tailDefined();
  Code:
   Stack=1, Locals=1, Args_size=1
   0:	aload_0
   1:	getfield	#55; //Field tlVal:Lscala/collection/immutable/Stream;
   4:	ifnull	11
   7:	iconst_1
   8:	goto	12
   11:	iconst_0
   12:	ireturn
  LineNumberTable: 
   line 488: 0


public java.lang.Object head();
  Code:
   Stack=1, Locals=1, Args_size=1
   0:	aload_0
   1:	getfield	#28; //Field hd:Ljava/lang/Object;
   4:	areturn
  LineNumberTable: 
   line 486: 0

  Signature: length = 0x2
   00 3A 

public boolean isEmpty();
  Code:
   Stack=1, Locals=1, Args_size=1
   0:	iconst_0
   1:	ireturn
  LineNumberTable: 
   line 485: 0


}

