Compiled from "Stream.scala"
public final class scala.collection.immutable.Stream$ extends scala.collection.generic.SeqFactory implements scala.ScalaObject
  SourceFile: "Stream.scala"
  Scala: length = 0x
   
  Signature: length = 0x2
   00 FFFFFFF9 
  InnerClass: 
   public final #251= #32 of #121; //Cons=class scala/collection/immutable/Stream$Cons of class scala/collection/immutable/Stream
   public final #254= #253 of #121; //$anonfun$2=class scala/collection/immutable/Stream$$anonfun$2 of class scala/collection/immutable/Stream
   public final #257= #256 of #121; //$anonfun$1=class scala/collection/immutable/Stream$$anonfun$1 of class scala/collection/immutable/Stream
   public #258= #230 of #121; //ConsWrapper=class scala/collection/immutable/Stream$ConsWrapper of class scala/collection/immutable/Stream
   public #259= #240 of #121; //StreamBuilder=class scala/collection/immutable/Stream$StreamBuilder of class scala/collection/immutable/Stream
   public final #262= #261 of #121; //$anonfun$zip$1=class scala/collection/immutable/Stream$$anonfun$zip$1 of class scala/collection/immutable/Stream
   public final #265= #264 of #121; //$anonfun$map$1=class scala/collection/immutable/Stream$$anonfun$map$1 of class scala/collection/immutable/Stream
   public final #268= #267 of #121; //$anonfun$init$1=class scala/collection/immutable/Stream$$anonfun$init$1 of class scala/collection/immutable/Stream
   public final #271= #270 of #121; //$anonfun$take$1=class scala/collection/immutable/Stream$$anonfun$take$1 of class scala/collection/immutable/Stream
   public final #272= #206 of #121; //$anonfun$from$1=class scala/collection/immutable/Stream$$anonfun$from$1 of class scala/collection/immutable/Stream
   public final #273= #184 of #121; //$anonfun$fill$1=class scala/collection/immutable/Stream$$anonfun$fill$1 of class scala/collection/immutable/Stream
   public final #274= #100 of #121; //$anonfun$make$1=class scala/collection/immutable/Stream$$anonfun$make$1 of class scala/collection/immutable/Stream
   public final #275= #165 of #121; //$anonfun$range$1=class scala/collection/immutable/Stream$$anonfun$range$1 of class scala/collection/immutable/Stream
   public abstract #280= #277 of #279; //$less$colon$less=class scala/Predef$$less$colon$less of class scala/Predef
   public final #281= #111 of #121; //$anonfun$const$1=class scala/collection/immutable/Stream$$anonfun$const$1 of class scala/collection/immutable/Stream
   public final #284= #283 of #121; //$anonfun$loop$4$2=class scala/collection/immutable/Stream$$anonfun$loop$4$2 of class scala/collection/immutable/Stream
   public final #287= #286 of #121; //$anonfun$loop$4$1=class scala/collection/immutable/Stream$$anonfun$loop$4$1 of class scala/collection/immutable/Stream
   public final #290= #289 of #121; //$anonfun$filter$1=class scala/collection/immutable/Stream$$anonfun$filter$1 of class scala/collection/immutable/Stream
   public final #293= #292 of #121; //$anonfun$append$1=class scala/collection/immutable/Stream$$anonfun$append$1 of class scala/collection/immutable/Stream
   public final #294= #46 of #121; //$anonfun$loop$5$1=class scala/collection/immutable/Stream$$anonfun$loop$5$1 of class scala/collection/immutable/Stream
   public final #297= #296 of #121; //$anonfun$flatMap$1=class scala/collection/immutable/Stream$$anonfun$flatMap$1 of class scala/collection/immutable/Stream
   public #298= #246 of #121; //StreamCanBuildFrom=class scala/collection/immutable/Stream$StreamCanBuildFrom of class scala/collection/immutable/Stream
   public final #299= #116 of #121; //$anonfun$iterate$1=class scala/collection/immutable/Stream$$anonfun$iterate$1 of class scala/collection/immutable/Stream
   public final #302= #301 of #121; //$anonfun$takeWhile$1=class scala/collection/immutable/Stream$$anonfun$takeWhile$1 of class scala/collection/immutable/Stream
   public final #305= #304 of #121; //$anonfun$partition$2=class scala/collection/immutable/Stream$$anonfun$partition$2 of class scala/collection/immutable/Stream
   public final #308= #307 of #121; //$anonfun$partition$1=class scala/collection/immutable/Stream$$anonfun$partition$1 of class scala/collection/immutable/Stream
   public final #311= #310 of #121; //$anonfun$flatten1$1$1=class scala/collection/immutable/Stream$$anonfun$flatten1$1$1 of class scala/collection/immutable/Stream
   public final #314= #313 of #121; //$anonfun$$plus$plus$1=class scala/collection/immutable/Stream$$anonfun$$plus$plus$1 of class scala/collection/immutable/Stream
   public final #315= #194 of #121; //$anonfun$continually$1=class scala/collection/immutable/Stream$$anonfun$continually$1 of class scala/collection/immutable/Stream
   public final #318= #317 of #121; //$anonfun$removeDuplicates$1=class scala/collection/immutable/Stream$$anonfun$removeDuplicates$1 of class scala/collection/immutable/Stream
  minor version: 0
  major version: 49
  Constant pool:
const #1 = Asciz	SourceFile;
const #2 = Asciz	Stream.scala;
const #3 = Asciz	Scala;
const #4 = Asciz	MODULE$;
const #5 = Asciz	Lscala/collection/immutable/Stream$;;
const #6 = Asciz	<clinit>;
const #7 = Asciz	()V;
const #8 = Asciz	Code;
const #9 = Asciz	scala/collection/immutable/Stream$;
const #10 = class	#9;	//  scala/collection/immutable/Stream$
const #11 = Asciz	<init>;
const #12 = NameAndType	#11:#7;//  "<init>":()V
const #13 = Method	#10.#12;	//  scala/collection/immutable/Stream$."<init>":()V
const #14 = Asciz	bitmap$0;
const #15 = Asciz	I;
const #16 = Asciz	lazy_$colon$colon;
const #17 = Asciz	Lscala/collection/immutable/Stream$$hash$colon$colon$;;
const #18 = Asciz	LineNumberTable;
const #19 = Asciz	scala/collection/generic/SeqFactory;
const #20 = class	#19;	//  scala/collection/generic/SeqFactory
const #21 = Method	#20.#12;	//  scala/collection/generic/SeqFactory."<init>":()V
const #22 = NameAndType	#4:#5;//  MODULE$:Lscala/collection/immutable/Stream$;
const #23 = Field	#10.#22;	//  scala/collection/immutable/Stream$.MODULE$:Lscala/collection/immutable/Stream$;
const #24 = Asciz	loop$5;
const #25 = Asciz	(IILscala/Function1;)Lscala/collection/immutable/Stream;;
const #26 = Asciz	scala/collection/immutable/Stream$Empty$;
const #27 = class	#26;	//  scala/collection/immutable/Stream$Empty$
const #28 = Asciz	Lscala/collection/immutable/Stream$Empty$;;
const #29 = NameAndType	#4:#28;//  MODULE$:Lscala/collection/immutable/Stream$Empty$;
const #30 = Field	#27.#29;	//  scala/collection/immutable/Stream$Empty$.MODULE$:Lscala/collection/immutable/Stream$Empty$;
const #31 = Asciz	scala/collection/immutable/Stream$Cons;
const #32 = class	#31;	//  scala/collection/immutable/Stream$Cons
const #33 = Asciz	scala/runtime/BoxesRunTime;
const #34 = class	#33;	//  scala/runtime/BoxesRunTime
const #35 = Asciz	boxToInteger;
const #36 = Asciz	(I)Ljava/lang/Integer;;
const #37 = NameAndType	#35:#36;//  boxToInteger:(I)Ljava/lang/Integer;
const #38 = Method	#34.#37;	//  scala/runtime/BoxesRunTime.boxToInteger:(I)Ljava/lang/Integer;
const #39 = Asciz	scala/Function1;
const #40 = class	#39;	//  scala/Function1
const #41 = Asciz	apply;
const #42 = Asciz	(Ljava/lang/Object;)Ljava/lang/Object;;
const #43 = NameAndType	#41:#42;//  apply:(Ljava/lang/Object;)Ljava/lang/Object;
const #44 = InterfaceMethod	#40.#43;	//  scala/Function1.apply:(Ljava/lang/Object;)Ljava/lang/Object;
const #45 = Asciz	scala/collection/immutable/Stream$$anonfun$loop$5$1;
const #46 = class	#45;	//  scala/collection/immutable/Stream$$anonfun$loop$5$1
const #47 = Asciz	(Lscala/Function1;I)V;
const #48 = NameAndType	#11:#47;//  "<init>":(Lscala/Function1;I)V
const #49 = Method	#46.#48;	//  scala/collection/immutable/Stream$$anonfun$loop$5$1."<init>":(Lscala/Function1;I)V
const #50 = Asciz	(Ljava/lang/Object;Lscala/Function0;)V;
const #51 = NameAndType	#11:#50;//  "<init>":(Ljava/lang/Object;Lscala/Function0;)V
const #52 = Method	#32.#51;	//  scala/collection/immutable/Stream$Cons."<init>":(Ljava/lang/Object;Lscala/Function0;)V
const #53 = Asciz	this;
const #54 = Asciz	i$1;
const #55 = Asciz	LocalVariableTable;
const #56 = Asciz	empty;
const #57 = Asciz	()Lscala/collection/Traversable;;
const #58 = Asciz	()Lscala/collection/immutable/Stream;;
const #59 = NameAndType	#56:#58;//  empty:()Lscala/collection/immutable/Stream;
const #60 = Method	#10.#59;	//  scala/collection/immutable/Stream$.empty:()Lscala/collection/immutable/Stream;
const #61 = Asciz	(Lscala/collection/Seq;)Lscala/collection/Traversable;;
const #62 = Asciz	(Lscala/collection/Seq;)Lscala/collection/immutable/Stream;;
const #63 = NameAndType	#41:#62;//  apply:(Lscala/collection/Seq;)Lscala/collection/immutable/Stream;
const #64 = Method	#10.#63;	//  scala/collection/immutable/Stream$.apply:(Lscala/collection/Seq;)Lscala/collection/immutable/Stream;
const #65 = Asciz	elems;
const #66 = Asciz	Lscala/collection/Seq;;
const #67 = Asciz	iterate;
const #68 = Asciz	(Ljava/lang/Object;ILscala/Function1;)Lscala/collection/Traversable;;
const #69 = Asciz	(Ljava/lang/Object;ILscala/Function1;)Lscala/collection/immutable/Stream;;
const #70 = NameAndType	#67:#69;//  iterate:(Ljava/lang/Object;ILscala/Function1;)Lscala/collection/immutable/Stream;
const #71 = Method	#10.#70;	//  scala/collection/immutable/Stream$.iterate:(Ljava/lang/Object;ILscala/Function1;)Lscala/collection/immutable/Stream;
const #72 = Asciz	start;
const #73 = Asciz	Ljava/lang/Object;;
const #74 = Asciz	len;
const #75 = Asciz	f;
const #76 = Asciz	Lscala/Function1;;
const #77 = Asciz	fill;
const #78 = Asciz	(ILscala/Function0;)Lscala/collection/Traversable;;
const #79 = Asciz	(ILscala/Function0;)Lscala/collection/immutable/Stream;;
const #80 = NameAndType	#77:#79;//  fill:(ILscala/Function0;)Lscala/collection/immutable/Stream;
const #81 = Method	#10.#80;	//  scala/collection/immutable/Stream$.fill:(ILscala/Function0;)Lscala/collection/immutable/Stream;
const #82 = Asciz	n;
const #83 = Asciz	elem;
const #84 = Asciz	Lscala/Function0;;
const #85 = Asciz	tabulate;
const #86 = Asciz	(ILscala/Function1;)Lscala/collection/Traversable;;
const #87 = Asciz	(ILscala/Function1;)Lscala/collection/immutable/Stream;;
const #88 = NameAndType	#85:#87;//  tabulate:(ILscala/Function1;)Lscala/collection/immutable/Stream;
const #89 = Method	#10.#88;	//  scala/collection/immutable/Stream$.tabulate:(ILscala/Function1;)Lscala/collection/immutable/Stream;
const #90 = Asciz	range;
const #91 = Asciz	(III)Lscala/collection/Traversable;;
const #92 = Asciz	(III)Lscala/collection/immutable/Stream;;
const #93 = NameAndType	#90:#92;//  range:(III)Lscala/collection/immutable/Stream;
const #94 = Method	#10.#93;	//  scala/collection/immutable/Stream$.range:(III)Lscala/collection/immutable/Stream;
const #95 = Asciz	end;
const #96 = Asciz	step;
const #97 = Asciz	make;
const #98 = Asciz	(ILjava/lang/Object;)Lscala/collection/immutable/Stream;;
const #99 = Asciz	scala/collection/immutable/Stream$$anonfun$make$1;
const #100 = class	#99;	//  scala/collection/immutable/Stream$$anonfun$make$1
const #101 = Asciz	(Ljava/lang/Object;)V;
const #102 = NameAndType	#11:#101;//  "<init>":(Ljava/lang/Object;)V
const #103 = Method	#100.#102;	//  scala/collection/immutable/Stream$$anonfun$make$1."<init>":(Ljava/lang/Object;)V
const #104 = Asciz	elem$5;
const #105 = Asciz	<A:Ljava/lang/Object;>(ITA;)Lscala/collection/immutable/Stream<TA;>;;
const #106 = Asciz	Signature;
const #107 = Asciz	Deprecated;
const #108 = Asciz	const;
const #109 = Asciz	(Ljava/lang/Object;)Lscala/collection/immutable/Stream;;
const #110 = Asciz	scala/collection/immutable/Stream$$anonfun$const$1;
const #111 = class	#110;	//  scala/collection/immutable/Stream$$anonfun$const$1
const #112 = Method	#111.#102;	//  scala/collection/immutable/Stream$$anonfun$const$1."<init>":(Ljava/lang/Object;)V
const #113 = Asciz	elem$4;
const #114 = Asciz	<A:Ljava/lang/Object;>(TA;)Lscala/collection/immutable/Stream<TA;>;;
const #115 = Asciz	scala/collection/immutable/Stream$$anonfun$iterate$1;
const #116 = class	#115;	//  scala/collection/immutable/Stream$$anonfun$iterate$1
const #117 = Asciz	(Ljava/lang/Object;Lscala/Function1;)V;
const #118 = NameAndType	#11:#117;//  "<init>":(Ljava/lang/Object;Lscala/Function1;)V
const #119 = Method	#116.#118;	//  scala/collection/immutable/Stream$$anonfun$iterate$1."<init>":(Ljava/lang/Object;Lscala/Function1;)V
const #120 = Asciz	scala/collection/immutable/Stream;
const #121 = class	#120;	//  scala/collection/immutable/Stream
const #122 = Asciz	take;
const #123 = Asciz	(I)Lscala/collection/immutable/Stream;;
const #124 = NameAndType	#122:#123;//  take:(I)Lscala/collection/immutable/Stream;
const #125 = Method	#121.#124;	//  scala/collection/immutable/Stream.take:(I)Lscala/collection/immutable/Stream;
const #126 = Asciz	(IILscala/Function1<Ljava/lang/Integer;Ljava/lang/Integer;>;)Lscala/collection/immutable/Stream<Ljava/lang/Integer;>;;
const #127 = Asciz	concat;
const #128 = Asciz	(Lscala/collection/Iterator;)Lscala/collection/immutable/Stream;;
const #129 = Asciz	scala/collection/Iterator;
const #130 = class	#129;	//  scala/collection/Iterator
const #131 = Asciz	toStream;
const #132 = NameAndType	#131:#58;//  toStream:()Lscala/collection/immutable/Stream;
const #133 = InterfaceMethod	#130.#132;	//  scala/collection/Iterator.toStream:()Lscala/collection/immutable/Stream;
const #134 = Asciz	scala/Predef$;
const #135 = class	#134;	//  scala/Predef$
const #136 = Asciz	Lscala/Predef$;;
const #137 = NameAndType	#4:#136;//  MODULE$:Lscala/Predef$;
const #138 = Field	#135.#137;	//  scala/Predef$.MODULE$:Lscala/Predef$;
const #139 = Asciz	conforms;
const #140 = Asciz	()Lscala/Predef$$less$colon$less;;
const #141 = NameAndType	#139:#140;//  conforms:()Lscala/Predef$$less$colon$less;
const #142 = Method	#135.#141;	//  scala/Predef$.conforms:()Lscala/Predef$$less$colon$less;
const #143 = Asciz	flatten;
const #144 = Asciz	(Lscala/Function1;)Lscala/collection/immutable/Stream;;
const #145 = NameAndType	#143:#144;//  flatten:(Lscala/Function1;)Lscala/collection/immutable/Stream;
const #146 = Method	#121.#145;	//  scala/collection/immutable/Stream.flatten:(Lscala/Function1;)Lscala/collection/immutable/Stream;
const #147 = Asciz	xs;
const #148 = Asciz	Lscala/collection/Iterator;;
const #149 = Asciz	<A:Ljava/lang/Object;>(Lscala/collection/Iterator<Lscala/collection/immutable/Stream<TA;>;>;)Lscala/collection/immutable/Stream<TA;>;;
const #150 = Asciz	(Lscala/collection/Iterable;)Lscala/collection/immutable/Stream;;
const #151 = Asciz	scala/collection/IterableLike;
const #152 = class	#151;	//  scala/collection/IterableLike
const #153 = Asciz	iterator;
const #154 = Asciz	()Lscala/collection/Iterator;;
const #155 = NameAndType	#153:#154;//  iterator:()Lscala/collection/Iterator;
const #156 = InterfaceMethod	#152.#155;	//  scala/collection/IterableLike.iterator:()Lscala/collection/Iterator;
const #157 = NameAndType	#127:#128;//  concat:(Lscala/collection/Iterator;)Lscala/collection/immutable/Stream;
const #158 = Method	#10.#157;	//  scala/collection/immutable/Stream$.concat:(Lscala/collection/Iterator;)Lscala/collection/immutable/Stream;
const #159 = Asciz	Lscala/collection/Iterable;;
const #160 = Asciz	<A:Ljava/lang/Object;>(Lscala/collection/Iterable<Lscala/collection/immutable/Stream<TA;>;>;)Lscala/collection/immutable/Stream<TA;>;;
const #161 = Asciz	fromIterator;
const #162 = Asciz	it;
const #163 = Asciz	<A:Ljava/lang/Object;>(Lscala/collection/Iterator<TA;>;)Lscala/collection/immutable/Stream<TA;>;;
const #164 = Asciz	scala/collection/immutable/Stream$$anonfun$range$1;
const #165 = class	#164;	//  scala/collection/immutable/Stream$$anonfun$range$1
const #166 = Asciz	(III)V;
const #167 = NameAndType	#11:#166;//  "<init>":(III)V
const #168 = Method	#165.#167;	//  scala/collection/immutable/Stream$$anonfun$range$1."<init>":(III)V
const #169 = Asciz	start$3;
const #170 = Asciz	end$1;
const #171 = Asciz	step$2;
const #172 = Asciz	(III)Lscala/collection/immutable/Stream<Ljava/lang/Integer;>;;
const #173 = NameAndType	#24:#25;//  loop$5:(IILscala/Function1;)Lscala/collection/immutable/Stream;
const #174 = Method	#10.#173;	//  scala/collection/immutable/Stream$.loop$5:(IILscala/Function1;)Lscala/collection/immutable/Stream;
const #175 = Asciz	n$1;
const #176 = Asciz	f$2;
const #177 = Asciz	<A:Ljava/lang/Object;>(ILscala/Function1<Ljava/lang/Integer;TA;>;)Lscala/collection/immutable/Stream<TA;>;;
const #178 = Asciz	scala/Function0;
const #179 = class	#178;	//  scala/Function0
const #180 = Asciz	()Ljava/lang/Object;;
const #181 = NameAndType	#41:#180;//  apply:()Ljava/lang/Object;
const #182 = InterfaceMethod	#179.#181;	//  scala/Function0.apply:()Ljava/lang/Object;
const #183 = Asciz	scala/collection/immutable/Stream$$anonfun$fill$1;
const #184 = class	#183;	//  scala/collection/immutable/Stream$$anonfun$fill$1
const #185 = Asciz	(ILscala/Function0;)V;
const #186 = NameAndType	#11:#185;//  "<init>":(ILscala/Function0;)V
const #187 = Method	#184.#186;	//  scala/collection/immutable/Stream$$anonfun$fill$1."<init>":(ILscala/Function0;)V
const #188 = Asciz	n$2;
const #189 = Asciz	elem$1;
const #190 = Asciz	<A:Ljava/lang/Object;>(ILscala/Function0<TA;>;)Lscala/collection/immutable/Stream<TA;>;;
const #191 = Asciz	continually;
const #192 = Asciz	(Lscala/Function0;)Lscala/collection/immutable/Stream;;
const #193 = Asciz	scala/collection/immutable/Stream$$anonfun$continually$1;
const #194 = class	#193;	//  scala/collection/immutable/Stream$$anonfun$continually$1
const #195 = Asciz	(Lscala/Function0;)V;
const #196 = NameAndType	#11:#195;//  "<init>":(Lscala/Function0;)V
const #197 = Method	#194.#196;	//  scala/collection/immutable/Stream$$anonfun$continually$1."<init>":(Lscala/Function0;)V
const #198 = Asciz	elem$3;
const #199 = Asciz	<A:Ljava/lang/Object;>(Lscala/Function0<TA;>;)Lscala/collection/immutable/Stream<TA;>;;
const #200 = Asciz	from;
const #201 = Asciz	(II)Lscala/collection/immutable/Stream;;
const #202 = NameAndType	#200:#201;//  from:(II)Lscala/collection/immutable/Stream;
const #203 = Method	#10.#202;	//  scala/collection/immutable/Stream$.from:(II)Lscala/collection/immutable/Stream;
const #204 = Asciz	(I)Lscala/collection/immutable/Stream<Ljava/lang/Integer;>;;
const #205 = Asciz	scala/collection/immutable/Stream$$anonfun$from$1;
const #206 = class	#205;	//  scala/collection/immutable/Stream$$anonfun$from$1
const #207 = Asciz	(II)V;
const #208 = NameAndType	#11:#207;//  "<init>":(II)V
const #209 = Method	#206.#208;	//  scala/collection/immutable/Stream$$anonfun$from$1."<init>":(II)V
const #210 = Asciz	start$1;
const #211 = Asciz	step$1;
const #212 = Asciz	(II)Lscala/collection/immutable/Stream<Ljava/lang/Integer;>;;
const #213 = Asciz	<A:Ljava/lang/Object;>(TA;ILscala/Function1<TA;TA;>;)Lscala/collection/immutable/Stream<TA;>;;
const #214 = Asciz	(Ljava/lang/Object;Lscala/Function1;)Lscala/collection/immutable/Stream;;
const #215 = Asciz	start$2;
const #216 = Asciz	f$1;
const #217 = Asciz	<A:Ljava/lang/Object;>(TA;Lscala/Function1<TA;TA;>;)Lscala/collection/immutable/Stream<TA;>;;
const #218 = Asciz	()Lscala/collection/immutable/Stream$$hash$colon$colon$;;
const #219 = NameAndType	#14:#15;//  bitmap$0:I
const #220 = Field	#10.#219;	//  scala/collection/immutable/Stream$.bitmap$0:I
const #221 = Asciz	scala/collection/immutable/Stream$$hash$colon$colon$;
const #222 = class	#221;	//  scala/collection/immutable/Stream$$hash$colon$colon$
const #223 = NameAndType	#4:#17;//  MODULE$:Lscala/collection/immutable/Stream$$hash$colon$colon$;
const #224 = Field	#222.#223;	//  scala/collection/immutable/Stream$$hash$colon$colon$.MODULE$:Lscala/collection/immutable/Stream$$hash$colon$colon$;
const #225 = NameAndType	#16:#17;//  lazy_$colon$colon:Lscala/collection/immutable/Stream$$hash$colon$colon$;
const #226 = Field	#10.#225;	//  scala/collection/immutable/Stream$.lazy_$colon$colon:Lscala/collection/immutable/Stream$$hash$colon$colon$;
const #227 = Asciz	consWrapper;
const #228 = Asciz	(Lscala/Function0;)Lscala/collection/immutable/Stream$ConsWrapper;;
const #229 = Asciz	scala/collection/immutable/Stream$ConsWrapper;
const #230 = class	#229;	//  scala/collection/immutable/Stream$ConsWrapper
const #231 = Method	#230.#196;	//  scala/collection/immutable/Stream$ConsWrapper."<init>":(Lscala/Function0;)V
const #232 = Asciz	stream;
const #233 = Asciz	<A:Ljava/lang/Object;>(Lscala/Function0<Lscala/collection/immutable/Stream<TA;>;>;)Lscala/collection/immutable/Stream$ConsWrapper<TA;>;;
const #234 = InterfaceMethod	#152.#132;	//  scala/collection/IterableLike.toStream:()Lscala/collection/immutable/Stream;
const #235 = Asciz	<A:Ljava/lang/Object;>(Lscala/collection/Seq<TA;>;)Lscala/collection/immutable/Stream<TA;>;;
const #236 = Asciz	<A:Ljava/lang/Object;>()Lscala/collection/immutable/Stream<TA;>;;
const #237 = Asciz	newBuilder;
const #238 = Asciz	()Lscala/collection/mutable/Builder;;
const #239 = Asciz	scala/collection/immutable/Stream$StreamBuilder;
const #240 = class	#239;	//  scala/collection/immutable/Stream$StreamBuilder
const #241 = Method	#240.#12;	//  scala/collection/immutable/Stream$StreamBuilder."<init>":()V
const #242 = Asciz	<A:Ljava/lang/Object;>()Lscala/collection/mutable/Builder<TA;Lscala/collection/immutable/Stream<TA;>;>;;
const #243 = Asciz	canBuildFrom;
const #244 = Asciz	()Lscala/collection/generic/CanBuildFrom;;
const #245 = Asciz	scala/collection/immutable/Stream$StreamCanBuildFrom;
const #246 = class	#245;	//  scala/collection/immutable/Stream$StreamCanBuildFrom
const #247 = Method	#246.#12;	//  scala/collection/immutable/Stream$StreamCanBuildFrom."<init>":()V
const #248 = Asciz	<A:Ljava/lang/Object;>()Lscala/collection/generic/CanBuildFrom<Lscala/collection/immutable/Stream<*>;TA;Lscala/collection/immutable/Stream<TA;>;>;;
const #249 = Asciz	Lscala/collection/generic/SeqFactory<Lscala/collection/immutable/Stream;>;Lscala/ScalaObject;;
const #250 = Asciz	InnerClasses;
const #251 = Asciz	Cons;
const #252 = Asciz	scala/collection/immutable/Stream$$anonfun$2;
const #253 = class	#252;	//  scala/collection/immutable/Stream$$anonfun$2
const #254 = Asciz	$anonfun$2;
const #255 = Asciz	scala/collection/immutable/Stream$$anonfun$1;
const #256 = class	#255;	//  scala/collection/immutable/Stream$$anonfun$1
const #257 = Asciz	$anonfun$1;
const #258 = Asciz	ConsWrapper;
const #259 = Asciz	StreamBuilder;
const #260 = Asciz	scala/collection/immutable/Stream$$anonfun$zip$1;
const #261 = class	#260;	//  scala/collection/immutable/Stream$$anonfun$zip$1
const #262 = Asciz	$anonfun$zip$1;
const #263 = Asciz	scala/collection/immutable/Stream$$anonfun$map$1;
const #264 = class	#263;	//  scala/collection/immutable/Stream$$anonfun$map$1
const #265 = Asciz	$anonfun$map$1;
const #266 = Asciz	scala/collection/immutable/Stream$$anonfun$init$1;
const #267 = class	#266;	//  scala/collection/immutable/Stream$$anonfun$init$1
const #268 = Asciz	$anonfun$init$1;
const #269 = Asciz	scala/collection/immutable/Stream$$anonfun$take$1;
const #270 = class	#269;	//  scala/collection/immutable/Stream$$anonfun$take$1
const #271 = Asciz	$anonfun$take$1;
const #272 = Asciz	$anonfun$from$1;
const #273 = Asciz	$anonfun$fill$1;
const #274 = Asciz	$anonfun$make$1;
const #275 = Asciz	$anonfun$range$1;
const #276 = Asciz	scala/Predef$$less$colon$less;
const #277 = class	#276;	//  scala/Predef$$less$colon$less
const #278 = Asciz	scala/Predef;
const #279 = class	#278;	//  scala/Predef
const #280 = Asciz	$less$colon$less;
const #281 = Asciz	$anonfun$const$1;
const #282 = Asciz	scala/collection/immutable/Stream$$anonfun$loop$4$2;
const #283 = class	#282;	//  scala/collection/immutable/Stream$$anonfun$loop$4$2
const #284 = Asciz	$anonfun$loop$4$2;
const #285 = Asciz	scala/collection/immutable/Stream$$anonfun$loop$4$1;
const #286 = class	#285;	//  scala/collection/immutable/Stream$$anonfun$loop$4$1
const #287 = Asciz	$anonfun$loop$4$1;
const #288 = Asciz	scala/collection/immutable/Stream$$anonfun$filter$1;
const #289 = class	#288;	//  scala/collection/immutable/Stream$$anonfun$filter$1
const #290 = Asciz	$anonfun$filter$1;
const #291 = Asciz	scala/collection/immutable/Stream$$anonfun$append$1;
const #292 = class	#291;	//  scala/collection/immutable/Stream$$anonfun$append$1
const #293 = Asciz	$anonfun$append$1;
const #294 = Asciz	$anonfun$loop$5$1;
const #295 = Asciz	scala/collection/immutable/Stream$$anonfun$flatMap$1;
const #296 = class	#295;	//  scala/collection/immutable/Stream$$anonfun$flatMap$1
const #297 = Asciz	$anonfun$flatMap$1;
const #298 = Asciz	StreamCanBuildFrom;
const #299 = Asciz	$anonfun$iterate$1;
const #300 = Asciz	scala/collection/immutable/Stream$$anonfun$takeWhile$1;
const #301 = class	#300;	//  scala/collection/immutable/Stream$$anonfun$takeWhile$1
const #302 = Asciz	$anonfun$takeWhile$1;
const #303 = Asciz	scala/collection/immutable/Stream$$anonfun$partition$2;
const #304 = class	#303;	//  scala/collection/immutable/Stream$$anonfun$partition$2
const #305 = Asciz	$anonfun$partition$2;
const #306 = Asciz	scala/collection/immutable/Stream$$anonfun$partition$1;
const #307 = class	#306;	//  scala/collection/immutable/Stream$$anonfun$partition$1
const #308 = Asciz	$anonfun$partition$1;
const #309 = Asciz	scala/collection/immutable/Stream$$anonfun$flatten1$1$1;
const #310 = class	#309;	//  scala/collection/immutable/Stream$$anonfun$flatten1$1$1
const #311 = Asciz	$anonfun$flatten1$1$1;
const #312 = Asciz	scala/collection/immutable/Stream$$anonfun$$plus$plus$1;
const #313 = class	#312;	//  scala/collection/immutable/Stream$$anonfun$$plus$plus$1
const #314 = Asciz	$anonfun$$plus$plus$1;
const #315 = Asciz	$anonfun$continually$1;
const #316 = Asciz	scala/collection/immutable/Stream$$anonfun$removeDuplicates$1;
const #317 = class	#316;	//  scala/collection/immutable/Stream$$anonfun$removeDuplicates$1
const #318 = Asciz	$anonfun$removeDuplicates$1;
const #319 = Asciz	scala/ScalaObject;
const #320 = class	#319;	//  scala/ScalaObject

{
public static final scala.collection.immutable.Stream$ MODULE$;

public volatile int bitmap$0;

public static {};
  Code:
   Stack=1, Locals=0, Args_size=0
   0:	new	#10; //class scala/collection/immutable/Stream$
   3:	invokespecial	#13; //Method "<init>":()V
   6:	return

public scala.collection.Traversable empty();
  Code:
   Stack=1, Locals=1, Args_size=1
   0:	aload_0
   1:	invokevirtual	#60; //Method empty:()Lscala/collection/immutable/Stream;
   4:	areturn
  LineNumberTable: 
   line 403: 0


public scala.collection.Traversable apply(scala.collection.Seq);
  Code:
   Stack=2, Locals=2, Args_size=2
   0:	aload_0
   1:	aload_1
   2:	invokevirtual	#64; //Method apply:(Lscala/collection/Seq;)Lscala/collection/immutable/Stream;
   5:	areturn
  LineNumberTable: 
   line 403: 0

  LocalVariableTable: 
   Start  Length  Slot  Name   Signature
   0      6      0    this       Lscala/collection/immutable/Stream$;
   0      6      1    elems       Lscala/collection/Seq;


public scala.collection.Traversable iterate(java.lang.Object, int, scala.Function1);
  Code:
   Stack=4, Locals=4, Args_size=4
   0:	aload_0
   1:	aload_1
   2:	iload_2
   3:	aload_3
   4:	invokevirtual	#71; //Method iterate:(Ljava/lang/Object;ILscala/Function1;)Lscala/collection/immutable/Stream;
   7:	areturn
  LineNumberTable: 
   line 403: 0

  LocalVariableTable: 
   Start  Length  Slot  Name   Signature
   0      8      0    this       Lscala/collection/immutable/Stream$;
   0      8      1    start       Ljava/lang/Object;
   0      8      2    len       I
   0      8      3    f       Lscala/Function1;


public scala.collection.Traversable fill(int, scala.Function0);
  Code:
   Stack=3, Locals=3, Args_size=3
   0:	aload_0
   1:	iload_1
   2:	aload_2
   3:	invokevirtual	#81; //Method fill:(ILscala/Function0;)Lscala/collection/immutable/Stream;
   6:	areturn
  LineNumberTable: 
   line 403: 0

  LocalVariableTable: 
   Start  Length  Slot  Name   Signature
   0      7      0    this       Lscala/collection/immutable/Stream$;
   0      7      1    n       I
   0      7      2    elem       Lscala/Function0;


public scala.collection.Traversable tabulate(int, scala.Function1);
  Code:
   Stack=3, Locals=3, Args_size=3
   0:	aload_0
   1:	iload_1
   2:	aload_2
   3:	invokevirtual	#89; //Method tabulate:(ILscala/Function1;)Lscala/collection/immutable/Stream;
   6:	areturn
  LineNumberTable: 
   line 403: 0

  LocalVariableTable: 
   Start  Length  Slot  Name   Signature
   0      7      0    this       Lscala/collection/immutable/Stream$;
   0      7      1    n       I
   0      7      2    f       Lscala/Function1;


public scala.collection.Traversable range(int, int, int);
  Code:
   Stack=4, Locals=4, Args_size=4
   0:	aload_0
   1:	iload_1
   2:	iload_2
   3:	iload_3
   4:	invokevirtual	#94; //Method range:(III)Lscala/collection/immutable/Stream;
   7:	areturn
  LineNumberTable: 
   line 403: 0

  LocalVariableTable: 
   Start  Length  Slot  Name   Signature
   0      8      0    this       Lscala/collection/immutable/Stream$;
   0      8      1    start       I
   0      8      2    end       I
   0      8      3    step       I


public scala.collection.immutable.Stream make(int, java.lang.Object);
  Code:
   Stack=5, Locals=3, Args_size=3
   0:	aload_0
   1:	iload_1
   2:	new	#100; //class scala/collection/immutable/Stream$$anonfun$make$1
   5:	dup
   6:	aload_2
   7:	invokespecial	#103; //Method scala/collection/immutable/Stream$$anonfun$make$1."<init>":(Ljava/lang/Object;)V
   10:	invokevirtual	#81; //Method fill:(ILscala/Function0;)Lscala/collection/immutable/Stream;
   13:	areturn
  LineNumberTable: 
   line 595: 0

  LocalVariableTable: 
   Start  Length  Slot  Name   Signature
   0      14      0    this       Lscala/collection/immutable/Stream$;
   0      14      1    n       I
   0      14      2    elem$5       Ljava/lang/Object;

  Signature: length = 0x2
   00 69 
  Deprecated: true

public scala.collection.immutable.Stream const(java.lang.Object);
  Code:
   Stack=4, Locals=3, Args_size=2
   0:	new	#111; //class scala/collection/immutable/Stream$$anonfun$const$1
   3:	dup
   4:	aload_1
   5:	invokespecial	#112; //Method scala/collection/immutable/Stream$$anonfun$const$1."<init>":(Ljava/lang/Object;)V
   8:	astore_2
   9:	new	#32; //class scala/collection/immutable/Stream$Cons
   12:	dup
   13:	aload_1
   14:	aload_2
   15:	invokespecial	#52; //Method scala/collection/immutable/Stream$Cons."<init>":(Ljava/lang/Object;Lscala/Function0;)V
   18:	areturn
  LineNumberTable: 
   line 586: 0

  LocalVariableTable: 
   Start  Length  Slot  Name   Signature
   0      19      0    this       Lscala/collection/immutable/Stream$;
   0      19      1    elem$4       Ljava/lang/Object;

  Signature: length = 0x2
   00 72 
  Deprecated: true

public scala.collection.immutable.Stream range(int, int, scala.Function1);
  Code:
   Stack=7, Locals=6, Args_size=4
   0:	iload_1
   1:	invokestatic	#38; //Method scala/runtime/BoxesRunTime.boxToInteger:(I)Ljava/lang/Integer;
   4:	iload_2
   5:	iload_1
   6:	isub
   7:	istore	5
   9:	astore	4
   11:	new	#32; //class scala/collection/immutable/Stream$Cons
   14:	dup
   15:	aload	4
   17:	new	#116; //class scala/collection/immutable/Stream$$anonfun$iterate$1
   20:	dup
   21:	aload	4
   23:	aload_3
   24:	invokespecial	#119; //Method scala/collection/immutable/Stream$$anonfun$iterate$1."<init>":(Ljava/lang/Object;Lscala/Function1;)V
   27:	invokespecial	#52; //Method scala/collection/immutable/Stream$Cons."<init>":(Ljava/lang/Object;Lscala/Function0;)V
   30:	iload	5
   32:	invokevirtual	#125; //Method scala/collection/immutable/Stream.take:(I)Lscala/collection/immutable/Stream;
   35:	areturn
  LineNumberTable: 
   line 577: 0

  LocalVariableTable: 
   Start  Length  Slot  Name   Signature
   0      36      0    this       Lscala/collection/immutable/Stream$;
   0      36      1    start       I
   0      36      2    end       I
   0      36      3    step       Lscala/Function1;

  Signature: length = 0x2
   00 7E 
  Deprecated: true

public scala.collection.immutable.Stream concat(scala.collection.Iterator);
  Code:
   Stack=2, Locals=2, Args_size=2
   0:	aload_1
   1:	invokeinterface	#133,  1; //InterfaceMethod scala/collection/Iterator.toStream:()Lscala/collection/immutable/Stream;
   6:	getstatic	#138; //Field scala/Predef$.MODULE$:Lscala/Predef$;
   9:	invokevirtual	#142; //Method scala/Predef$.conforms:()Lscala/Predef$$less$colon$less;
   12:	invokevirtual	#146; //Method scala/collection/immutable/Stream.flatten:(Lscala/Function1;)Lscala/collection/immutable/Stream;
   15:	areturn
  LineNumberTable: 
   line 562: 0

  LocalVariableTable: 
   Start  Length  Slot  Name   Signature
   0      16      0    this       Lscala/collection/immutable/Stream$;
   0      16      1    xs       Lscala/collection/Iterator;

  Signature: length = 0x2
   00 FFFFFF95 
  Deprecated: true

public scala.collection.immutable.Stream concat(scala.collection.Iterable);
  Code:
   Stack=2, Locals=2, Args_size=2
   0:	aload_0
   1:	aload_1
   2:	invokeinterface	#156,  1; //InterfaceMethod scala/collection/IterableLike.iterator:()Lscala/collection/Iterator;
   7:	invokevirtual	#158; //Method concat:(Lscala/collection/Iterator;)Lscala/collection/immutable/Stream;
   10:	areturn
  LineNumberTable: 
   line 557: 0

  LocalVariableTable: 
   Start  Length  Slot  Name   Signature
   0      11      0    this       Lscala/collection/immutable/Stream$;
   0      11      1    xs       Lscala/collection/Iterable;

  Signature: length = 0x2
   00 FFFFFFA0 
  Deprecated: true

public scala.collection.immutable.Stream fromIterator(scala.collection.Iterator);
  Code:
   Stack=1, Locals=2, Args_size=2
   0:	aload_1
   1:	invokeinterface	#133,  1; //InterfaceMethod scala/collection/Iterator.toStream:()Lscala/collection/immutable/Stream;
   6:	areturn
  LineNumberTable: 
   line 552: 0

  LocalVariableTable: 
   Start  Length  Slot  Name   Signature
   0      7      0    this       Lscala/collection/immutable/Stream$;
   0      7      1    it       Lscala/collection/Iterator;

  Signature: length = 0x2
   00 FFFFFFA3 
  Deprecated: true

public scala.collection.immutable.Stream range(int, int, int);
  Code:
   Stack=8, Locals=4, Args_size=4
   0:	iload_3
   1:	iconst_0
   2:	if_icmpge	18
   5:	iload_1
   6:	iload_2
   7:	if_icmpgt	14
   10:	iconst_1
   11:	goto	28
   14:	iconst_0
   15:	goto	28
   18:	iload_2
   19:	iload_1
   20:	if_icmpgt	27
   23:	iconst_1
   24:	goto	28
   27:	iconst_0
   28:	ifeq	37
   31:	getstatic	#30; //Field scala/collection/immutable/Stream$Empty$.MODULE$:Lscala/collection/immutable/Stream$Empty$;
   34:	goto	58
   37:	new	#32; //class scala/collection/immutable/Stream$Cons
   40:	dup
   41:	iload_1
   42:	invokestatic	#38; //Method scala/runtime/BoxesRunTime.boxToInteger:(I)Ljava/lang/Integer;
   45:	new	#165; //class scala/collection/immutable/Stream$$anonfun$range$1
   48:	dup
   49:	iload_1
   50:	iload_2
   51:	iload_3
   52:	invokespecial	#168; //Method scala/collection/immutable/Stream$$anonfun$range$1."<init>":(III)V
   55:	invokespecial	#52; //Method scala/collection/immutable/Stream$Cons."<init>":(Ljava/lang/Object;Lscala/Function0;)V
   58:	areturn
  LineNumberTable: 
   line 545: 0
   line 546: 37
   line 545: 58

  LocalVariableTable: 
   Start  Length  Slot  Name   Signature
   0      59      0    this       Lscala/collection/immutable/Stream$;
   0      59      1    start$3       I
   0      59      2    end$1       I
   0      59      3    step$2       I

  Signature: length = 0x2
   00 FFFFFFAC 

public scala.collection.immutable.Stream tabulate(int, scala.Function1);
  Code:
   Stack=4, Locals=3, Args_size=3
   0:	aload_0
   1:	iconst_0
   2:	iload_1
   3:	aload_2
   4:	invokespecial	#174; //Method loop$5:(IILscala/Function1;)Lscala/collection/immutable/Stream;
   7:	areturn
  LineNumberTable: 
   line 541: 0

  LocalVariableTable: 
   Start  Length  Slot  Name   Signature
   0      8      0    this       Lscala/collection/immutable/Stream$;
   0      8      1    n$1       I
   0      8      2    f$2       Lscala/Function1;

  Signature: length = 0x2
   00 FFFFFFB1 

public scala.collection.immutable.Stream fill(int, scala.Function0);
  Code:
   Stack=7, Locals=3, Args_size=3
   0:	iload_1
   1:	iconst_0
   2:	if_icmpgt	11
   5:	getstatic	#30; //Field scala/collection/immutable/Stream$Empty$.MODULE$:Lscala/collection/immutable/Stream$Empty$;
   8:	goto	33
   11:	new	#32; //class scala/collection/immutable/Stream$Cons
   14:	dup
   15:	aload_2
   16:	invokeinterface	#182,  1; //InterfaceMethod scala/Function0.apply:()Ljava/lang/Object;
   21:	new	#184; //class scala/collection/immutable/Stream$$anonfun$fill$1
   24:	dup
   25:	iload_1
   26:	aload_2
   27:	invokespecial	#187; //Method scala/collection/immutable/Stream$$anonfun$fill$1."<init>":(ILscala/Function0;)V
   30:	invokespecial	#52; //Method scala/collection/immutable/Stream$Cons."<init>":(Ljava/lang/Object;Lscala/Function0;)V
   33:	areturn
  LineNumberTable: 
   line 536: 0

  LocalVariableTable: 
   Start  Length  Slot  Name   Signature
   0      34      0    this       Lscala/collection/immutable/Stream$;
   0      34      1    n$2       I
   0      34      2    elem$1       Lscala/Function0;

  Signature: length = 0x2
   00 FFFFFFBE 

public scala.collection.immutable.Stream continually(scala.Function0);
  Code:
   Stack=6, Locals=2, Args_size=2
   0:	new	#32; //class scala/collection/immutable/Stream$Cons
   3:	dup
   4:	aload_1
   5:	invokeinterface	#182,  1; //InterfaceMethod scala/Function0.apply:()Ljava/lang/Object;
   10:	new	#194; //class scala/collection/immutable/Stream$$anonfun$continually$1
   13:	dup
   14:	aload_1
   15:	invokespecial	#197; //Method scala/collection/immutable/Stream$$anonfun$continually$1."<init>":(Lscala/Function0;)V
   18:	invokespecial	#52; //Method scala/collection/immutable/Stream$Cons."<init>":(Ljava/lang/Object;Lscala/Function0;)V
   21:	areturn
  LineNumberTable: 
   line 533: 0

  LocalVariableTable: 
   Start  Length  Slot  Name   Signature
   0      22      0    this       Lscala/collection/immutable/Stream$;
   0      22      1    elem$3       Lscala/Function0;

  Signature: length = 0x2
   00 FFFFFFC7 

public scala.collection.immutable.Stream from(int);
  Code:
   Stack=3, Locals=2, Args_size=2
   0:	aload_0
   1:	iload_1
   2:	iconst_1
   3:	invokevirtual	#203; //Method from:(II)Lscala/collection/immutable/Stream;
   6:	areturn
  LineNumberTable: 
   line 524: 0

  LocalVariableTable: 
   Start  Length  Slot  Name   Signature
   0      7      0    this       Lscala/collection/immutable/Stream$;
   0      7      1    start       I

  Signature: length = 0x2
   00 FFFFFFCC 

public scala.collection.immutable.Stream from(int, int);
  Code:
   Stack=7, Locals=3, Args_size=3
   0:	new	#32; //class scala/collection/immutable/Stream$Cons
   3:	dup
   4:	iload_1
   5:	invokestatic	#38; //Method scala/runtime/BoxesRunTime.boxToInteger:(I)Ljava/lang/Integer;
   8:	new	#206; //class scala/collection/immutable/Stream$$anonfun$from$1
   11:	dup
   12:	iload_1
   13:	iload_2
   14:	invokespecial	#209; //Method scala/collection/immutable/Stream$$anonfun$from$1."<init>":(II)V
   17:	invokespecial	#52; //Method scala/collection/immutable/Stream$Cons."<init>":(Ljava/lang/Object;Lscala/Function0;)V
   20:	areturn
  LineNumberTable: 
   line 515: 0

  LocalVariableTable: 
   Start  Length  Slot  Name   Signature
   0      21      0    this       Lscala/collection/immutable/Stream$;
   0      21      1    start$1       I
   0      21      2    step$1       I

  Signature: length = 0x2
   00 FFFFFFD4 

public scala.collection.immutable.Stream iterate(java.lang.Object, int, scala.Function1);
  Code:
   Stack=7, Locals=4, Args_size=4
   0:	new	#32; //class scala/collection/immutable/Stream$Cons
   3:	dup
   4:	aload_1
   5:	new	#116; //class scala/collection/immutable/Stream$$anonfun$iterate$1
   8:	dup
   9:	aload_1
   10:	aload_3
   11:	invokespecial	#119; //Method scala/collection/immutable/Stream$$anonfun$iterate$1."<init>":(Ljava/lang/Object;Lscala/Function1;)V
   14:	invokespecial	#52; //Method scala/collection/immutable/Stream$Cons."<init>":(Ljava/lang/Object;Lscala/Function0;)V
   17:	iload_2
   18:	invokevirtual	#125; //Method scala/collection/immutable/Stream.take:(I)Lscala/collection/immutable/Stream;
   21:	areturn
  LineNumberTable: 
   line 504: 0

  LocalVariableTable: 
   Start  Length  Slot  Name   Signature
   0      22      0    this       Lscala/collection/immutable/Stream$;
   0      22      1    start       Ljava/lang/Object;
   0      22      2    len       I
   0      22      3    f       Lscala/Function1;

  Signature: length = 0x2
   00 FFFFFFD5 

public scala.collection.immutable.Stream iterate(java.lang.Object, scala.Function1);
  Code:
   Stack=7, Locals=3, Args_size=3
   0:	new	#32; //class scala/collection/immutable/Stream$Cons
   3:	dup
   4:	aload_1
   5:	new	#116; //class scala/collection/immutable/Stream$$anonfun$iterate$1
   8:	dup
   9:	aload_1
   10:	aload_2
   11:	invokespecial	#119; //Method scala/collection/immutable/Stream$$anonfun$iterate$1."<init>":(Ljava/lang/Object;Lscala/Function1;)V
   14:	invokespecial	#52; //Method scala/collection/immutable/Stream$Cons."<init>":(Ljava/lang/Object;Lscala/Function0;)V
   17:	areturn
  LineNumberTable: 
   line 501: 0

  LocalVariableTable: 
   Start  Length  Slot  Name   Signature
   0      18      0    this       Lscala/collection/immutable/Stream$;
   0      18      1    start$2       Ljava/lang/Object;
   0      18      2    f$1       Lscala/Function1;

  Signature: length = 0x2
   00 FFFFFFD9 

public scala.collection.immutable.Stream$$hash$colon$colon$ lazy_$colon$colon();
  Code:
   Stack=3, Locals=1, Args_size=1
   0:	aload_0
   1:	getfield	#220; //Field bitmap$0:I
   4:	iconst_1
   5:	iand
   6:	iconst_0
   7:	if_icmpne	43
   10:	aload_0
   11:	dup
   12:	pop
   13:	monitorenter
   14:	aload_0
   15:	getfield	#220; //Field bitmap$0:I
   18:	iconst_1
   19:	iand
   20:	iconst_0
   21:	if_icmpne	41
   24:	aload_0
   25:	getstatic	#224; //Field scala/collection/immutable/Stream$$hash$colon$colon$.MODULE$:Lscala/collection/immutable/Stream$$hash$colon$colon$;
   28:	putfield	#226; //Field lazy_$colon$colon:Lscala/collection/immutable/Stream$$hash$colon$colon$;
   31:	aload_0
   32:	aload_0
   33:	getfield	#220; //Field bitmap$0:I
   36:	iconst_1
   37:	ior
   38:	putfield	#220; //Field bitmap$0:I
   41:	aload_0
   42:	monitorexit
   43:	aload_0
   44:	getfield	#226; //Field lazy_$colon$colon:Lscala/collection/immutable/Stream$$hash$colon$colon$;
   47:	areturn
   48:	aload_0
   49:	monitorexit
   50:	athrow
  Exception table:
   from   to  target type
    14    43    48   any
  LineNumberTable: 
   line 466: 0
   line 341: 6
   line 466: 10
   line 341: 20
   line 466: 24

  Deprecated: true

public scala.collection.immutable.Stream$ConsWrapper consWrapper(scala.Function0);
  Code:
   Stack=3, Locals=2, Args_size=2
   0:	new	#230; //class scala/collection/immutable/Stream$ConsWrapper
   3:	dup
   4:	aload_1
   5:	invokespecial	#231; //Method scala/collection/immutable/Stream$ConsWrapper."<init>":(Lscala/Function0;)V
   8:	areturn
  LineNumberTable: 
   line 456: 0

  LocalVariableTable: 
   Start  Length  Slot  Name   Signature
   0      9      0    this       Lscala/collection/immutable/Stream$;
   0      9      1    stream       Lscala/Function0;

  Signature: length = 0x2
   00 FFFFFFE9 

public scala.collection.immutable.Stream apply(scala.collection.Seq);
  Code:
   Stack=1, Locals=2, Args_size=2
   0:	aload_1
   1:	invokeinterface	#234,  1; //InterfaceMethod scala/collection/IterableLike.toStream:()Lscala/collection/immutable/Stream;
   6:	areturn
  LineNumberTable: 
   line 442: 0

  LocalVariableTable: 
   Start  Length  Slot  Name   Signature
   0      7      0    this       Lscala/collection/immutable/Stream$;
   0      7      1    xs       Lscala/collection/Seq;

  Signature: length = 0x2
   00 FFFFFFEB 

public scala.collection.immutable.Stream empty();
  Code:
   Stack=1, Locals=1, Args_size=1
   0:	getstatic	#30; //Field scala/collection/immutable/Stream$Empty$.MODULE$:Lscala/collection/immutable/Stream$Empty$;
   3:	areturn
  LineNumberTable: 
   line 439: 0

  Signature: length = 0x2
   00 FFFFFFEC 

public scala.collection.mutable.Builder newBuilder();
  Code:
   Stack=2, Locals=1, Args_size=1
   0:	new	#240; //class scala/collection/immutable/Stream$StreamBuilder
   3:	dup
   4:	invokespecial	#241; //Method scala/collection/immutable/Stream$StreamBuilder."<init>":()V
   7:	areturn
  LineNumberTable: 
   line 418: 0

  Signature: length = 0x2
   00 FFFFFFF2 

public scala.collection.generic.CanBuildFrom canBuildFrom();
  Code:
   Stack=2, Locals=1, Args_size=1
   0:	new	#246; //class scala/collection/immutable/Stream$StreamCanBuildFrom
   3:	dup
   4:	invokespecial	#247; //Method scala/collection/immutable/Stream$StreamCanBuildFrom."<init>":()V
   7:	areturn
  LineNumberTable: 
   line 415: 0

  Signature: length = 0x2
   00 FFFFFFF8 

}

