Compiled from "Stream.scala"
public final class scala.collection.immutable.Stream$Cons extends scala.collection.immutable.Stream implements java.io.Serializable
  InnerClass: 
   public final Cons=class scala/collection/immutable/Stream$Cons of class scala/collection/immutable/Stream
  Scala: length = 0x
   
  Signature: length = 0x2
   00 1F 
  SourceFile: "Stream.scala"
  minor version: 0
  major version: 49
  Constant pool:
class	java/io/Serializable
class	scala/Function0
class	scala/collection/immutable/Stream
class	scala/collection/immutable/Stream$Cons
long	-602202424901551803l;
Field	scala/collection/immutable/Stream$Cons.hd:Ljava/lang/Object;
Field	scala/collection/immutable/Stream$Cons.serialVersionUID:J
Field	scala/collection/immutable/Stream$Cons.tl:Lscala/Function0;
Field	scala/collection/immutable/Stream$Cons.tlVal:Lscala/collection/immutable/Stream;
Method	scala/collection/immutable/Stream."<init>":()V
Method	scala/collection/immutable/Stream$Cons.tail:()Lscala/collection/immutable/Stream;
Method	scala/collection/immutable/Stream$Cons.tailDefined:()Z
InterfaceMethod	scala/Function0.apply:()Ljava/lang/Object;
NameAndType	"<init>":()V
NameAndType	apply:()Ljava/lang/Object;
NameAndType	hd:Ljava/lang/Object;
NameAndType	serialVersionUID:J
NameAndType	tail:()Lscala/collection/immutable/Stream;
NameAndType	tailDefined:()Z
NameAndType	tl:Lscala/Function0;
NameAndType	tlVal:Lscala/collection/immutable/Stream;
Asciz	()Ljava/lang/Object;;
Asciz	()Lscala/collection/immutable/Stream;;
Asciz	()Lscala/collection/immutable/Stream<TA;>;;
Asciz	()TA;;
Asciz	()V;
Asciz	()Z;
Asciz	(Ljava/lang/Object;Lscala/Function0;)V;
Asciz	(TA;Lscala/Function0<Lscala/collection/immutable/Stream<TA;>;>;)V;
Asciz	<A:Ljava/lang/Object;>Lscala/collection/immutable/Stream<TA;>;;
Asciz	<clinit>;
Asciz	<init>;
Asciz	Code;
Asciz	Cons;
Asciz	InnerClasses;
Asciz	J;
Asciz	LineNumberTable;
Asciz	Ljava/lang/Object;;
Asciz	LocalVariableTable;
Asciz	Lscala/Function0;;
Asciz	Lscala/Function0<Lscala/collection/immutable/Stream<TA;>;>;;
Asciz	Lscala/collection/immutable/Stream$Cons;;
Asciz	Lscala/collection/immutable/Stream;;
Asciz	Lscala/collection/immutable/Stream<TA;>;;
Asciz	Scala;
Asciz	Signature;
Asciz	SourceFile;
Asciz	Stream.scala;
Asciz	TA;;
Asciz	apply;
Asciz	hd;
Asciz	head;
Asciz	isEmpty;
Asciz	java/io/Serializable;
Asciz	scala/Function0;
Asciz	scala/collection/immutable/Stream;
Asciz	scala/collection/immutable/Stream$Cons;
Asciz	serialVersionUID;
Asciz	tail;
Asciz	tailDefined;
Asciz	this;
Asciz	tl;
Asciz	tlVal;

{
public static final long serialVersionUID;
  Signature: J

private scala.collection.immutable.Stream tlVal;
  Signature: Lscala/collection/immutable/Stream;
  Signature: length = 0x2
   00 2D 

public final scala.Function0 tl;
  Signature: Lscala/Function0;
  Signature: length = 0x2
   00 2A 

private final java.lang.Object hd;
  Signature: Ljava/lang/Object;
  Signature: length = 0x2
   00 32 

public static {};
  Signature: ()V
  Code:
   Stack=2, Locals=0, Args_size=0
	ldc2_w	long -602202424901551803l
	putstatic	Field serialVersionUID:J
	return
  Labels:

public scala.collection.immutable.Stream$Cons(java.lang.Object, scala.Function0);
  Signature: (Ljava/lang/Object;Lscala/Function0;)V
  Code:
   Stack=2, Locals=3, Args_size=3
	aload_0
	aload_1
	putfield	Field hd:Ljava/lang/Object;
	aload_0
	aload_2
	putfield	Field tl:Lscala/Function0;
	aload_0
	invokespecial	Method scala/collection/immutable/Stream."<init>":()V
	return
  Labels:
  LocalVariableTable: 
   Start  Length  Slot  Name   Signature
   0      15      0    this       Lscala/collection/immutable/Stream$Cons;
   0      15      1    hd       Ljava/lang/Object;
   0      15      2    tl       Lscala/Function0;

  Signature: length = 0x2
   00 1E 

public java.lang.Object tail();
  Signature: ()Ljava/lang/Object;
  Code:
   Stack=1, Locals=1, Args_size=1
	aload_0
	invokevirtual	Method tail:()Lscala/collection/immutable/Stream;
	areturn
  Labels:

public scala.collection.immutable.Stream tail();
  Signature: ()Lscala/collection/immutable/Stream;
  Code:
   Stack=2, Locals=1, Args_size=1
	aload_0
	invokevirtual	Method tailDefined:()Z
	ifne	l1 // aload_0
	aload_0
	aload_0
	getfield	Field tl:Lscala/Function0;
	invokeinterface	InterfaceMethod scala/Function0.apply:()Ljava/lang/Object;
	checkcast	class scala/collection/immutable/Stream
	putfield	Field tlVal:Lscala/collection/immutable/Stream;
l1	aload_0
	getfield	Field tlVal:Lscala/collection/immutable/Stream;
	areturn
  Labels:
   	l1 = 23 // aload_0
  Signature: length = 0x2
   00 19 

public boolean tailDefined();
  Signature: ()Z
  Code:
   Stack=1, Locals=1, Args_size=1
	aload_0
	getfield	Field tlVal:Lscala/collection/immutable/Stream;
	ifnull	l1 // iconst_0
	iconst_1
	goto	l2 // ireturn
l1	iconst_0
l2	ireturn
  Labels:
   	l1 = 11 // iconst_0
   	l2 = 12 // ireturn

public java.lang.Object head();
  Signature: ()Ljava/lang/Object;
  Code:
   Stack=1, Locals=1, Args_size=1
	aload_0
	getfield	Field hd:Ljava/lang/Object;
	areturn
  Labels:
  Signature: length = 0x2
   00 1A 

public boolean isEmpty();
  Signature: ()Z
  Code:
   Stack=1, Locals=1, Args_size=1
	iconst_0
	ireturn
  Labels:

}

