Compiled from "Stream.scala"
public abstract class scala.collection.immutable.Stream extends java.lang.Object implements scala.collection.immutable.LinearSeq,scala.collection.generic.GenericTraversableTemplate,scala.collection.LinearSeqLike,scala.ScalaObject
  SourceFile: "Stream.scala"
  Signature: length = 0x2
   04 56 
  ScalaSig: length = 0x1566
   05 00 FFFFFF85 35 06 05 01 02 FFFFFF81 00 09 02 06 53 74 72
   65 61 6D 0A 02 03 04 01 09 69 6D 6D 75 74 61 62
   6C 65 0A 02 05 06 01 0A 63 6F 6C 6C 65 63 74 69
   6F 6E 0A 01 07 01 05 73 63 61 6C 61 03 00 15 02
   0A 19 13 06 00 0B 13 23 2A 2F 10 02 0C 11 0D 01
   0D 0A 02 0E 0F 01 04 6C 61 6E 67 0A 01 10 01 04
   6A 61 76 61 09 02 12 0D 02 06 4F 62 6A 65 63 74
   10 03 14 15 17 0D 01 02 09 02 16 02 02 09 4C 69
   6E 65 61 72 53 65 71 10 02 18 19 0C 00 04 08 1A
   00 FFFFFF84 FFFFFF80 FFFFFF84 FFFFFFC2 00 1B 02 01 41 11 02 1C 20 10 02
   1D 1E 0D 01 06 09 02 1F 06 02 07 4E 6F 74 68 69
   6E 67 10 02 1D 21 09 02 22 06 02 03 41 6E 79 10
   04 24 27 17 29 0D 01 25 0A 02 26 04 01 07 67 65
   6E 65 72 69 63 09 02 28 25 02 1A 47 65 6E 65 72
   69 63 54 72 61 76 65 72 73 61 62 6C 65 54 65 6D
   70 6C 61 74 65 10 02 14 00 10 04 2B 2C 17 2E 0D
   01 04 09 02 2D 04 02 0D 4C 69 6E 65 61 72 53 65
   71 4C 69 6B 65 10 03 14 00 17 10 02 1D 30 09 02
   31 06 02 0B 53 63 61 6C 61 4F 62 6A 65 63 74 08
   05 33 00 FFFFFF84 00 34 01 06 3C 69 6E 69 74 3E 14 01
   2E 08 05 36 00 FFFFFF84 20 37 01 09 63 6F 6D 70 61 6E
   69 6F 6E 15 01 38 10 03 24 39 29 09 02 3A 25 02
   10 47 65 6E 65 72 69 63 43 6F 6D 70 61 6E 69 6F
   6E 08 05 3C 00 FFFFFF86 00 3D 01 07 69 73 45 6D 70 74
   79 15 01 3E 10 02 1D 3F 09 02 40 06 02 07 42 6F
   6F 6C 65 61 6E 08 05 42 00 FFFFFF86 00 43 01 04 68 65
   61 64 15 01 17 08 05 45 00 FFFFFF86 00 46 01 04 74 61
   69 6C 15 01 2E 08 05 48 00 FFFFFF86 08 3D 01 0B 74 61
   69 6C 44 65 66 69 6E 65 64 08 05 4A 00 FFFFFF84 00 4B
   01 06 61 70 70 65 6E 64 15 02 4C 4F 14 02 4D 52
   10 03 14 00 4E 10 02 18 4F 04 08 50 49 FFFFFF84 FFFFFF80 FFFFFF80
   FFFFFFC2 00 51 02 01 42 11 02 17 20 08 06 53 49 FFFFFF84 FFFFFFC0
   00 54 01 04 72 65 73 74 10 03 1D 55 57 09 02 56
   06 02 08 3C 62 79 6E 61 6D 65 3E 10 03 2B 58 4E
   09 02 59 04 02 0B 54 72 61 76 65 72 73 61 62 6C
   65 08 05 5B 00 FFFFFF84 00 46 01 05 66 6F 72 63 65 08
   05 5D 00 FFFFFF84 00 5E 01 05 70 72 69 6E 74 14 01 5F
   10 02 1D 60 09 02 61 06 02 04 55 6E 69 74 08 05
   5D 00 FFFFFF84 00 63 14 02 5F 64 08 05 65 62 FFFFFFC0 00 66
   01 03 73 65 70 10 02 67 6A 0E 02 1D 68 09 02 69
   06 01 06 50 72 65 64 65 66 09 02 6B 6C 02 06 53
   74 72 69 6E 67 0A 02 69 06 08 05 6E 00 FFFFFF84 20 46
   01 08 74 6F 53 74 72 65 61 6D 08 05 70 00 FFFFFF84 20
   3D 01 0F 68 61 73 44 65 66 69 6E 69 74 65 53 69
   7A 65 08 05 72 00 FFFFFF84 20 73 01 0A 24 70 6C 75 73
   24 70 6C 75 73 15 03 74 7F 77 14 03 75 FFFFFF81 00 16
   02 76 79 10 02 18 77 04 08 78 71 FFFFFF84 FFFFFF80 FFFFFF80 FFFFFFC2 00
   1B 02 04 54 68 61 74 08 05 7A 71 FFFFFFC0 01 7B 01 02
   62 66 10 05 24 7C 2E 7E 76 09 02 7D 25 02 0C 43
   61 6E 42 75 69 6C 64 46 72 6F 6D 10 02 18 7F 04
   08 50 71 FFFFFF84 FFFFFF80 FFFFFF80 FFFFFFC2 00 51 08 07 FFFFFF81 01 71 FFFFFFC0 00
   FFFFFF81 02 01 04 74 68 61 74 10 03 2B 58 7E 08 06 72
   00 FFFFFF84 20 FFFFFF81 04 15 06 FFFFFF81 05 FFFFFF81 0C FFFFFF81 08 14 04 FFFFFF81
   06 FFFFFF81 0D 16 04 FFFFFF81 07 FFFFFF81 09 10 03 18 FFFFFF81 08 04 09
   78 FFFFFF81 03 FFFFFF84 FFFFFF80 FFFFFF80 FFFFFFC2 00 1B 08 07 7A FFFFFF81 03 FFFFFFC0 01
   FFFFFF81 0A 10 07 24 7C 2E FFFFFF81 0B FFFFFF81 07 10 03 18 FFFFFF81 0C
   04 09 50 FFFFFF81 03 FFFFFF84 FFFFFF80 FFFFFF80 FFFFFFC2 00 51 08 08 FFFFFF81 01 FFFFFF81
   03 FFFFFFC0 00 FFFFFF81 0E 10 05 2B FFFFFF81 0F FFFFFF81 0B 09 03 FFFFFF81 10
   04 02 08 49 74 65 72 61 74 6F 72 08 07 FFFFFF81 12 00
   FFFFFF84 22 FFFFFF81 13 01 03 6D 61 70 15 06 FFFFFF81 14 FFFFFF81 1B FFFFFF81
   17 14 04 FFFFFF81 15 FFFFFF81 1C 16 04 FFFFFF81 16 FFFFFF81 18 10 03 18
   FFFFFF81 17 04 09 78 FFFFFF81 11 FFFFFF84 FFFFFF80 FFFFFF80 FFFFFFC2 00 1B 08 07 7A
   FFFFFF81 11 FFFFFFC0 01 FFFFFF81 19 10 07 24 7C 2E FFFFFF81 1A FFFFFF81 16 10
   03 18 FFFFFF81 1B 04 09 50 FFFFFF81 11 FFFFFF84 FFFFFF80 FFFFFF80 FFFFFFC2 00 1B 08
   08 FFFFFF81 1D FFFFFF81 11 FFFFFFC0 00 FFFFFF81 1E 01 01 66 10 06 1D FFFFFF81
   1F 17 FFFFFF81 1A 09 03 FFFFFF81 20 06 02 09 46 75 6E 63 74
   69 6F 6E 31 08 07 FFFFFF81 22 00 FFFFFF84 22 FFFFFF81 23 01 07 66
   6C 61 74 4D 61 70 15 06 FFFFFF81 24 FFFFFF81 2B FFFFFF81 27 14 04
   FFFFFF81 25 FFFFFF81 2C 16 04 FFFFFF81 26 FFFFFF81 28 10 03 18 FFFFFF81 27 04
   09 78 FFFFFF81 21 FFFFFF84 FFFFFF80 FFFFFF80 FFFFFFC2 00 1B 08 07 7A FFFFFF81 21 FFFFFFC0
   01 FFFFFF81 29 10 07 24 7C 2E FFFFFF81 2A FFFFFF81 26 10 03 18 FFFFFF81
   2B 04 09 50 FFFFFF81 21 FFFFFF84 FFFFFF80 FFFFFF80 FFFFFFC2 00 1B 08 08 FFFFFF81 1D
   FFFFFF81 21 FFFFFFC0 00 FFFFFF81 2D 10 06 1D FFFFFF81 1F 17 FFFFFF81 2E 10 04
   2B 58 FFFFFF81 2A 08 07 FFFFFF81 30 00 FFFFFF84 22 FFFFFF81 31 01 06 66
   69 6C 74 65 72 14 03 2E FFFFFF81 32 08 08 FFFFFF81 33 FFFFFF81 2F
   FFFFFFC0 00 FFFFFF81 34 01 01 70 10 05 1D FFFFFF81 1F 17 3E 08 07
   FFFFFF81 36 00 FFFFFF84 22 FFFFFF81 37 01 07 66 6F 72 65 61 63 68
   15 04 FFFFFF81 38 FFFFFF81 3C 14 03 5F FFFFFF81 39 08 08 FFFFFF81 1D FFFFFF81
   35 FFFFFFC0 00 FFFFFF81 3A 10 06 1D FFFFFF81 1F 17 FFFFFF81 3B 10 03 18
   FFFFFF81 3C 04 09 50 FFFFFF81 35 FFFFFF84 FFFFFF80 FFFFFF80 FFFFFFC2 00 1B 28 04 FFFFFF81
   35 FFFFFF81 3E 10 04 FFFFFF81 3F FFFFFF81 42 0D 02 FFFFFF81 40 0A 03 FFFFFF81
   41 06 01 0A 61 6E 6E 6F 74 61 74 69 6F 6E 09 04
   FFFFFF81 43 FFFFFF81 40 02 07 74 61 69 6C 72 65 63 08 07 FFFFFF81
   45 00 FFFFFF84 22 FFFFFF81 46 01 08 66 6F 6C 64 4C 65 66 74
   15 04 FFFFFF81 47 FFFFFF81 4A 14 04 FFFFFF81 48 FFFFFF81 50 14 04 FFFFFF81 49
   FFFFFF81 4B 10 03 18 FFFFFF81 4A 04 09 50 FFFFFF81 44 FFFFFF84 FFFFFF80 FFFFFF80 FFFFFFC2
   00 1B 08 08 FFFFFF81 4C FFFFFF81 44 FFFFFFC0 00 FFFFFF81 4D 01 02 6F 70
   10 08 1D FFFFFF81 4E FFFFFF81 49 17 FFFFFF81 49 09 03 FFFFFF81 4F 06 02
   09 46 75 6E 63 74 69 6F 6E 32 08 08 FFFFFF81 51 FFFFFF81 44
   FFFFFFC0 00 FFFFFF81 49 01 01 7A 28 04 FFFFFF81 44 FFFFFF81 3E 08 07 FFFFFF81
   54 00 FFFFFF84 20 FFFFFF81 55 01 09 70 61 72 74 69 74 69 6F
   6E 14 04 FFFFFF81 56 FFFFFF81 59 10 05 1D FFFFFF81 57 2E 2E 09 03
   FFFFFF81 58 06 02 06 54 75 70 6C 65 32 08 08 FFFFFF81 33 FFFFFF81
   53 FFFFFFC0 00 FFFFFF81 34 08 07 FFFFFF81 5B 00 FFFFFF84 22 FFFFFF81 5C 01 03
   7A 69 70 15 08 FFFFFF81 5D FFFFFF81 65 FFFFFF81 68 FFFFFF81 60 14 04 FFFFFF81
   5E FFFFFF81 69 16 04 FFFFFF81 5F FFFFFF81 61 10 03 18 FFFFFF81 60 04 09
   78 FFFFFF81 5A FFFFFF84 FFFFFF80 FFFFFF80 FFFFFFC2 00 1B 08 07 7A FFFFFF81 5A FFFFFFC0 01
   FFFFFF81 62 10 07 24 7C 2E FFFFFF81 63 FFFFFF81 5F 10 07 1D FFFFFF81 57
   FFFFFF81 64 FFFFFF81 67 10 03 18 FFFFFF81 65 04 0A FFFFFF81 66 FFFFFF81 5A FFFFFF84
   FFFFFF80 FFFFFF80 FFFFFFC2 00 51 02 02 41 31 10 03 18 FFFFFF81 68 04 09
   50 FFFFFF81 5A FFFFFF84 FFFFFF80 FFFFFF80 FFFFFFC2 00 1B 08 08 FFFFFF81 01 FFFFFF81 5A FFFFFFC0
   00 FFFFFF81 6A 10 05 2B FFFFFF81 6B FFFFFF81 67 09 03 FFFFFF81 6C 04 02
   08 49 74 65 72 61 62 6C 65 08 07 FFFFFF81 6E 00 FFFFFF84 20
   FFFFFF81 6F 01 0C 7A 69 70 57 69 74 68 49 6E 64 65 78
   15 06 FFFFFF81 70 FFFFFF81 77 FFFFFF81 72 16 04 FFFFFF81 71 FFFFFF81 73 10 03
   18 FFFFFF81 72 04 09 78 FFFFFF81 6D FFFFFF84 FFFFFF80 FFFFFF80 FFFFFFC2 00 1B 08 07
   7A FFFFFF81 6D FFFFFFC0 01 FFFFFF81 74 10 07 24 7C 2E FFFFFF81 75 FFFFFF81 71
   10 07 1D FFFFFF81 57 FFFFFF81 76 FFFFFF81 78 10 03 18 FFFFFF81 77 04 0A
   FFFFFF81 66 FFFFFF81 6D FFFFFF84 FFFFFF80 FFFFFF80 FFFFFFC2 00 51 10 03 1D FFFFFF81 79 09
   03 FFFFFF81 7A 06 02 03 49 6E 74 08 07 FFFFFF81 7C 00 FFFFFF84 20
   FFFFFF81 7D 01 09 61 64 64 53 74 72 69 6E 67 14 0A FFFFFF81
   7E FFFFFF82 04 FFFFFF82 06 FFFFFF82 08 FFFFFF82 09 10 04 FFFFFF81 7F FFFFFF82 02 0D
   02 FFFFFF82 00 0A 03 FFFFFF82 01 04 01 07 6D 75 74 61 62 6C
   65 09 04 FFFFFF82 03 FFFFFF82 00 02 0D 53 74 72 69 6E 67 42
   75 69 6C 64 65 72 08 08 FFFFFF82 05 FFFFFF81 7B FFFFFFC0 00 FFFFFF81 7E
   01 01 62 08 07 FFFFFF82 07 FFFFFF81 7B FFFFFFC0 00 66 01 05 73 74
   61 72 74 08 06 65 FFFFFF81 7B FFFFFFC0 00 66 08 07 FFFFFF82 0A FFFFFF81
   7B FFFFFFC0 00 66 01 03 65 6E 64 08 07 FFFFFF82 0C 00 FFFFFF84 20
   FFFFFF82 0D 01 08 6D 6B 53 74 72 69 6E 67 14 07 66 FFFFFF82
   0E FFFFFF82 0F FFFFFF82 10 08 07 FFFFFF82 07 FFFFFF82 0B FFFFFFC0 00 66 08 06
   65 FFFFFF82 0B FFFFFFC0 00 66 08 07 FFFFFF82 0A FFFFFF82 0B FFFFFFC0 00 66 08
   07 FFFFFF82 0C 00 FFFFFF84 20 FFFFFF82 12 14 03 66 FFFFFF82 13 08 06 65
   FFFFFF82 11 FFFFFFC0 00 66 08 07 FFFFFF82 0C 00 FFFFFF84 20 FFFFFF82 15 15 01
   66 08 07 FFFFFF82 17 00 FFFFFF84 20 FFFFFF82 18 01 08 74 6F 53 74
   72 69 6E 67 14 01 66 08 07 FFFFFF82 1A 00 FFFFFF84 20 FFFFFF82 1B
   01 04 74 61 6B 65 14 03 2E FFFFFF82 1C 08 08 FFFFFF82 1D FFFFFF82
   19 FFFFFFC0 00 FFFFFF81 78 01 01 6E 08 07 FFFFFF82 1F 00 FFFFFF84 20 FFFFFF82
   20 01 05 73 6C 69 63 65 14 05 2E FFFFFF82 21 FFFFFF82 22 08
   08 FFFFFF82 07 FFFFFF82 1E FFFFFFC0 00 FFFFFF81 78 08 08 FFFFFF82 0A FFFFFF82 1E FFFFFFC0
   00 FFFFFF81 78 08 06 FFFFFF82 24 00 FFFFFF84 20 46 01 04 69 6E 69
   74 08 07 FFFFFF82 26 00 FFFFFF84 20 FFFFFF82 27 01 09 74 61 6B 65
   52 69 67 68 74 14 03 2E FFFFFF82 28 08 08 FFFFFF82 1D FFFFFF82 25
   FFFFFFC0 00 FFFFFF81 78 08 07 FFFFFF82 2A 00 FFFFFF84 20 FFFFFF82 2B 01 09 74
   61 6B 65 57 68 69 6C 65 14 03 2E FFFFFF82 2C 08 08 FFFFFF81
   33 FFFFFF82 29 FFFFFFC0 00 FFFFFF81 34 08 07 FFFFFF82 2E 00 FFFFFF84 20 FFFFFF82 2F
   01 09 64 72 6F 70 57 68 69 6C 65 14 03 2E FFFFFF82 30
   08 08 FFFFFF81 33 FFFFFF82 2D FFFFFFC0 00 FFFFFF81 34 08 06 FFFFFF82 32 00 FFFFFF84
   20 46 01 10 72 65 6D 6F 76 65 44 75 70 6C 69 63
   61 74 65 73 08 07 FFFFFF82 34 00 FFFFFF84 20 FFFFFF82 35 01 05 70
   61 64 54 6F 15 06 FFFFFF82 36 FFFFFF82 3D FFFFFF82 39 14 06 FFFFFF82 37
   FFFFFF82 3E FFFFFF82 40 16 04 FFFFFF82 38 FFFFFF82 3A 10 03 18 FFFFFF82 39 04
   09 78 FFFFFF82 33 FFFFFF84 FFFFFF80 FFFFFF80 FFFFFFC2 00 1B 08 07 7A FFFFFF82 33 FFFFFFC0
   01 FFFFFF82 3B 10 07 24 7C 2E FFFFFF82 3C FFFFFF82 38 10 03 18 FFFFFF82
   3D 04 09 50 FFFFFF82 33 FFFFFF84 FFFFFF80 FFFFFF80 FFFFFFC2 00 51 08 08 FFFFFF82 3F
   FFFFFF82 33 FFFFFFC0 00 FFFFFF81 78 01 03 6C 65 6E 08 08 FFFFFF82 41 FFFFFF82
   33 FFFFFFC0 00 FFFFFF82 3C 01 04 65 6C 65 6D 08 06 FFFFFF82 43 00
   FFFFFF84 20 46 01 07 72 65 76 65 72 73 65 08 07 FFFFFF82 45
   00 FFFFFF84 20 FFFFFF82 46 01 07 66 6C 61 74 74 65 6E 15 04
   FFFFFF82 47 FFFFFF82 4A 16 04 FFFFFF82 48 FFFFFF82 4B 10 04 14 00 FFFFFF82 49
   10 03 18 FFFFFF82 4A 04 09 50 FFFFFF82 44 FFFFFF84 FFFFFF80 FFFFFF80 FFFFFFC2 00 1B
   08 08 FFFFFF82 4C FFFFFF82 44 FFFFFFC0 01 FFFFFF82 4D 01 0D 61 73 54 72
   61 76 65 72 73 61 62 6C 65 10 06 1D FFFFFF81 1F 17 FFFFFF82
   4E 10 04 2B 58 FFFFFF82 49 08 07 FFFFFF82 50 00 FFFFFF84 20 FFFFFF82 51
   01 0C 73 74 72 69 6E 67 50 72 65 66 69 78 15 02
   FFFFFF82 52 10 03 0C FFFFFF82 53 09 02 6B 0D 07 07 FFFFFF82 55 02
   FFFFFF88 02 FFFFFF82 56 01 06 53 74 72 65 61 6D 10 03 14 FFFFFF82
   57 06 09 01 02 FFFFFF84 FFFFFF80 FFFFFF80 FFFFFF88 02 FFFFFF82 58 13 05 FFFFFF82 57
   FFFFFF82 59 2F 10 04 24 FFFFFF82 5A 29 09 03 FFFFFF82 5B 25 02 0A
   53 65 71 46 61 63 74 6F 72 79 08 07 33 FFFFFF82 57 FFFFFF84
   00 FFFFFF82 5D 14 02 FFFFFF82 56 06 07 FFFFFF82 5F FFFFFF82 57 00 FFFFFF82 60
   02 12 53 74 72 65 61 6D 43 61 6E 42 75 69 6C 64
   46 72 6F 6D 15 04 FFFFFF82 61 FFFFFF82 69 13 05 FFFFFF82 5E FFFFFF82 62
   2F 10 06 FFFFFF82 63 FFFFFF82 64 FFFFFF82 68 0D 02 FFFFFF82 57 09 04 FFFFFF82
   65 FFFFFF82 66 02 13 47 65 6E 65 72 69 63 43 61 6E 42
   75 69 6C 64 46 72 6F 6D 09 03 FFFFFF82 67 25 02 12 54
   72 61 76 65 72 73 61 62 6C 65 46 61 63 74 6F 72
   79 10 03 18 FFFFFF82 69 04 09 1A FFFFFF82 5E FFFFFF84 FFFFFF80 FFFFFF80 FFFFFFC2 00
   1B 08 07 33 FFFFFF82 5E FFFFFF84 00 FFFFFF82 6B 14 02 FFFFFF82 6C 10 06
   FFFFFF82 63 FFFFFF82 5E FFFFFF82 68 08 08 FFFFFF82 6E FFFFFF82 57 FFFFFF84 01 FFFFFF82 6F
   01 0C 63 61 6E 42 75 69 6C 64 46 72 6F 6D 15 04
   FFFFFF82 70 FFFFFF82 75 10 08 24 7C FFFFFF82 71 FFFFFF82 74 FFFFFF82 76 10 04
   FFFFFF82 63 FFFFFF82 72 09 03 FFFFFF82 73 39 02 04 43 6F 6C 6C 10
   03 18 FFFFFF82 75 04 09 1A FFFFFF82 6D FFFFFF84 FFFFFF80 FFFFFF80 FFFFFFC2 00 1B 10
   04 14 00 FFFFFF82 74 08 08 FFFFFF82 78 FFFFFF82 57 FFFFFF84 00 FFFFFF82 79 01
   0A 6E 65 77 42 75 69 6C 64 65 72 15 04 FFFFFF82 7A FFFFFF82
   7E 10 08 FFFFFF81 7F FFFFFF82 7B FFFFFF82 7D FFFFFF82 7F 09 04 FFFFFF82 7C FFFFFF82
   00 02 07 42 75 69 6C 64 65 72 10 03 18 FFFFFF82 7E 04
   09 1A FFFFFF82 77 FFFFFF84 FFFFFF80 FFFFFF80 FFFFFFC2 00 1B 10 04 14 00 FFFFFF82 7D
   06 07 FFFFFF83 01 FFFFFF82 57 00 FFFFFF83 02 02 0D 53 74 72 65 61
   6D 42 75 69 6C 64 65 72 15 04 FFFFFF83 03 FFFFFF83 08 13 05
   FFFFFF83 00 FFFFFF83 04 2F 10 08 FFFFFF81 7F FFFFFF83 05 FFFFFF83 07 FFFFFF83 09 09
   04 FFFFFF83 06 FFFFFF82 00 02 0B 4C 61 7A 79 42 75 69 6C 64
   65 72 10 03 18 FFFFFF83 08 04 09 1A FFFFFF83 00 FFFFFF84 FFFFFF80 FFFFFF80 FFFFFFC2
   00 1B 10 04 14 00 FFFFFF83 07 08 07 33 FFFFFF83 00 FFFFFF84 00 FFFFFF83
   0B 14 02 FFFFFF83 0C 10 06 FFFFFF82 63 FFFFFF83 00 FFFFFF83 07 08 08 FFFFFF83
   0E FFFFFF83 00 FFFFFF84 00 FFFFFF83 0F 01 06 72 65 73 75 6C 74 14
   02 FFFFFF83 09 07 08 FFFFFF83 11 FFFFFF82 57 FFFFFF88 02 FFFFFF83 12 01 05 45
   6D 70 74 79 10 04 FFFFFF82 63 FFFFFF83 13 06 0B FFFFFF83 14 FFFFFF82 57
   FFFFFF84 FFFFFF80 FFFFFF80 FFFFFF88 02 FFFFFF83 15 02 05 45 6D 70 74 79 13 05
   FFFFFF83 13 FFFFFF83 16 2F 10 03 14 00 1C 08 07 33 FFFFFF83 13 FFFFFF84
   00 FFFFFF83 18 14 02 FFFFFF83 12 08 06 3C FFFFFF83 13 FFFFFF84 20 3D 08
   07 42 FFFFFF83 13 FFFFFF84 20 FFFFFF83 1B 15 01 1C 08 07 45 FFFFFF83 13
   FFFFFF84 20 FFFFFF83 1B 08 06 48 FFFFFF83 13 FFFFFF84 00 3D 08 08 FFFFFF83 1F
   FFFFFF82 57 FFFFFF84 20 FFFFFF83 20 01 05 65 6D 70 74 79 15 04 FFFFFF83
   21 FFFFFF83 23 10 04 14 00 FFFFFF83 22 10 03 18 FFFFFF83 23 04 09
   1A FFFFFF83 1E FFFFFF84 FFFFFF80 FFFFFF80 FFFFFFC2 00 1B 08 08 FFFFFF83 25 FFFFFF82 57 FFFFFF84
   20 FFFFFF83 26 01 05 61 70 70 6C 79 15 04 FFFFFF83 27 FFFFFF83 2A
   14 04 FFFFFF83 28 FFFFFF83 2B 10 04 14 00 FFFFFF83 29 10 03 18 FFFFFF83
   2A 04 09 1A FFFFFF83 24 FFFFFF84 FFFFFF80 FFFFFF80 FFFFFFC2 00 1B 08 08 FFFFFF83 2C
   FFFFFF83 24 FFFFFFC0 00 FFFFFF83 2D 01 02 78 73 10 05 1D FFFFFF83 2E FFFFFF83
   29 09 03 FFFFFF83 2F 06 02 0A 3C 72 65 70 65 61 74 65
   64 3E 06 07 FFFFFF83 31 FFFFFF82 57 00 FFFFFF83 32 02 0B 43 6F 6E
   73 57 72 61 70 70 65 72 15 04 FFFFFF83 33 FFFFFF83 39 13 04
   FFFFFF83 30 0B 2F 08 0B FFFFFF83 35 FFFFFF83 30 FFFFFF82 FFFFFF80 FFFFFFA4 FFFFFF80 04 FFFFFF83
   36 01 02 74 6C 10 04 1D 55 FFFFFF83 37 10 04 14 00 FFFFFF83
   38 10 03 18 FFFFFF83 39 04 09 1A FFFFFF83 30 FFFFFF84 FFFFFF80 FFFFFF80 FFFFFFC2 00
   1B 08 07 33 FFFFFF83 30 FFFFFF84 00 FFFFFF83 3B 14 04 FFFFFF83 3C FFFFFF83 3D
   10 06 FFFFFF82 63 FFFFFF83 30 FFFFFF83 38 08 08 FFFFFF83 35 FFFFFF83 3A FFFFFFC0 00
   FFFFFF83 36 08 08 FFFFFF83 3F FFFFFF83 30 FFFFFF84 00 FFFFFF83 40 01 11 24 68
   61 73 68 24 63 6F 6C 6F 6E 24 63 6F 6C 6F 6E 14
   04 FFFFFF83 37 FFFFFF83 41 08 08 FFFFFF83 42 FFFFFF83 3E FFFFFFC0 00 FFFFFF83 38 01
   02 68 64 08 08 FFFFFF83 44 FFFFFF83 30 FFFFFF84 00 FFFFFF83 45 01 17 24
   68 61 73 68 24 63 6F 6C 6F 6E 24 63 6F 6C 6F 6E
   24 63 6F 6C 6F 6E 14 04 FFFFFF83 37 FFFFFF83 46 08 08 FFFFFF83 47
   FFFFFF83 43 FFFFFFC0 00 FFFFFF83 37 01 06 70 72 65 66 69 78 08 08
   FFFFFF83 49 FFFFFF82 57 FFFFFF84 01 FFFFFF83 4A 01 0B 63 6F 6E 73 57 72
   61 70 70 65 72 15 04 FFFFFF83 4B FFFFFF83 4E 14 04 FFFFFF83 4C FFFFFF83
   4F 10 06 FFFFFF82 63 FFFFFF83 30 FFFFFF83 4D 10 03 18 FFFFFF83 4E 04 09
   1A FFFFFF83 48 FFFFFF84 FFFFFF80 FFFFFF80 FFFFFFC2 00 1B 08 09 FFFFFF83 50 FFFFFF83 48 FFFFFF84
   FFFFFFC0 00 FFFFFF83 51 01 06 73 74 72 65 61 6D 10 04 1D 55
   FFFFFF83 52 10 04 14 00 FFFFFF83 4D 07 08 FFFFFF83 3F FFFFFF82 57 FFFFFF88 02
   FFFFFF83 54 10 04 FFFFFF82 63 FFFFFF83 55 06 0B FFFFFF83 56 FFFFFF82 57 FFFFFF84 FFFFFF80
   FFFFFF80 FFFFFF88 02 FFFFFF83 57 02 11 24 68 61 73 68 24 63 6F 6C
   6F 6E 24 63 6F 6C 6F 6E 13 04 FFFFFF83 55 0B 2F 08 07
   33 FFFFFF83 55 FFFFFF84 00 FFFFFF83 59 14 02 FFFFFF83 54 08 08 FFFFFF83 5B FFFFFF83
   55 FFFFFF84 00 FFFFFF83 5C 01 07 75 6E 61 70 70 6C 79 15 04
   FFFFFF83 5D FFFFFF83 63 14 04 FFFFFF83 5E FFFFFF83 65 10 05 1D FFFFFF83 5F FFFFFF83
   61 09 03 FFFFFF83 60 06 02 06 4F 70 74 69 6F 6E 10 07
   1D FFFFFF81 57 FFFFFF83 62 FFFFFF83 64 10 03 18 FFFFFF83 63 04 09 1A FFFFFF83
   5A FFFFFF84 FFFFFF80 FFFFFF80 FFFFFFC2 00 1B 10 04 14 00 FFFFFF83 62 08 08 FFFFFF83
   2C FFFFFF83 5A FFFFFFC0 00 FFFFFF83 64 08 0B FFFFFF83 67 FFFFFF82 57 FFFFFF88 FFFFFFC2 FFFFFF80
   FFFFFF84 00 FFFFFF83 68 01 11 6C 61 7A 79 5F 24 63 6F 6C 6F
   6E 24 63 6F 6C 6F 6E 15 02 FFFFFF83 54 28 06 FFFFFF83 66 FFFFFF83
   6A FFFFFF83 6D 10 03 1D FFFFFF83 6B 09 03 FFFFFF83 6C 06 02 0A 64
   65 70 72 65 63 61 74 65 64 21 02 FFFFFF83 6E 01 0F 75
   73 65 20 23 3A 3A 20 69 6E 73 74 65 61 64 08 0B
   FFFFFF83 70 FFFFFF82 57 FFFFFF88 FFFFFF80 FFFFFFA0 FFFFFFA0 04 FFFFFF83 54 01 12 6C 61 7A
   79 5F 24 63 6F 6C 6F 6E 24 63 6F 6C 6F 6E 20 07
   08 FFFFFF83 72 FFFFFF82 57 FFFFFF88 02 FFFFFF83 73 01 04 63 6F 6E 73 10
   04 FFFFFF82 63 FFFFFF83 74 06 0B FFFFFF83 75 FFFFFF82 57 FFFFFF84 FFFFFF80 FFFFFF80 FFFFFF88 02
   FFFFFF83 76 02 04 63 6F 6E 73 13 04 FFFFFF83 74 0B 2F 08 07
   33 FFFFFF83 74 FFFFFF84 00 FFFFFF83 78 14 02 FFFFFF83 73 08 08 FFFFFF83 25 FFFFFF83
   74 FFFFFF84 00 FFFFFF83 7A 15 04 FFFFFF83 7B FFFFFF84 1E 14 06 FFFFFF83 7C FFFFFF84
   1F FFFFFF84 20 10 06 FFFFFF82 63 FFFFFF83 7D FFFFFF84 1D 06 07 FFFFFF83 7E FFFFFF82
   57 02 FFFFFF83 7F 02 04 43 6F 6E 73 15 04 FFFFFF84 00 FFFFFF84 03
   13 05 FFFFFF83 7D FFFFFF84 01 2F 10 04 14 00 FFFFFF84 02 10 03 18
   FFFFFF84 03 04 09 1A FFFFFF83 7D FFFFFF84 FFFFFF80 FFFFFF84 FFFFFFC2 00 1B 08 0B FFFFFF83
   42 FFFFFF83 7D FFFFFF82 FFFFFF80 FFFFFFA0 FFFFFF80 04 FFFFFF84 02 08 0B FFFFFF83 35 FFFFFF83 7D
   FFFFFF82 FFFFFF80 FFFFFFA4 FFFFFF80 04 FFFFFF84 06 10 04 1D 55 FFFFFF84 01 08 07 33
   FFFFFF83 7D FFFFFF84 00 FFFFFF84 08 14 06 FFFFFF84 09 FFFFFF84 0A FFFFFF84 0B 10 06
   FFFFFF82 63 FFFFFF83 7D FFFFFF84 02 08 08 FFFFFF83 42 FFFFFF84 07 FFFFFFC0 00 FFFFFF84 02
   08 08 FFFFFF83 35 FFFFFF84 07 FFFFFFC0 00 FFFFFF84 06 08 06 3C FFFFFF83 7D FFFFFF84
   20 3D 08 07 42 FFFFFF83 7D FFFFFF84 20 FFFFFF84 0E 15 02 FFFFFF84 02 08
   09 FFFFFF84 10 FFFFFF83 7D FFFFFFA0 FFFFFFA0 04 FFFFFF84 01 01 05 74 6C 56 61
   6C 08 06 48 FFFFFF83 7D FFFFFF84 00 3D 08 07 45 FFFFFF83 7D FFFFFF84 20
   FFFFFF84 13 15 02 FFFFFF84 01 28 06 FFFFFF83 7D FFFFFF84 15 FFFFFF84 18 10 03
   1D FFFFFF84 16 09 03 FFFFFF84 17 06 02 10 53 65 72 69 61 6C
   56 65 72 73 69 6F 6E 55 49 44 1E 08 FFFFFFF7 FFFFFFA4 FFFFFF8C 15
   FFFFFFCC FFFFFFDD 39 45 28 04 FFFFFF83 7D FFFFFF84 1A 10 03 1D FFFFFF84 1B 09
   03 FFFFFF84 1C 06 02 0C 73 65 72 69 61 6C 69 7A 61 62
   6C 65 10 03 18 FFFFFF84 1E 04 09 1A FFFFFF83 79 FFFFFF84 FFFFFF80 FFFFFF80 FFFFFFC2
   00 1B 08 08 FFFFFF83 42 FFFFFF83 79 FFFFFFC0 00 FFFFFF84 1D 08 09 FFFFFF83 35
   FFFFFF83 79 FFFFFF84 FFFFFFC0 00 FFFFFF84 21 10 04 1D 55 FFFFFF84 22 10 04 14
   00 FFFFFF84 1D 08 08 FFFFFF83 5B FFFFFF83 74 FFFFFF84 00 FFFFFF84 24 15 04 FFFFFF84
   25 FFFFFF84 29 14 04 FFFFFF84 26 FFFFFF84 2B 10 05 1D FFFFFF83 5F FFFFFF84 27
   10 07 1D FFFFFF81 57 FFFFFF84 28 FFFFFF84 2A 10 03 18 FFFFFF84 29 04 09
   1A FFFFFF84 23 FFFFFF84 FFFFFF80 FFFFFF80 FFFFFFC2 00 1B 10 04 14 00 FFFFFF84 28 08
   08 FFFFFF83 2C FFFFFF84 23 FFFFFFC0 00 FFFFFF84 2A 08 08 FFFFFF84 2D FFFFFF82 57 FFFFFF84
   00 FFFFFF84 2E 01 07 69 74 65 72 61 74 65 15 04 FFFFFF84 2F
   FFFFFF84 33 14 04 FFFFFF84 30 FFFFFF84 36 14 04 FFFFFF84 31 FFFFFF84 34 10 04
   14 00 FFFFFF84 32 10 03 18 FFFFFF84 33 04 09 1A FFFFFF84 2C FFFFFF84 FFFFFF80
   FFFFFF80 FFFFFFC2 00 1B 08 08 FFFFFF81 1D FFFFFF84 2C FFFFFFC0 00 FFFFFF84 35 10 07
   1D FFFFFF81 1F FFFFFF84 32 FFFFFF84 32 08 08 FFFFFF82 07 FFFFFF84 2C FFFFFFC0 00 FFFFFF84
   32 08 08 FFFFFF84 2D FFFFFF82 57 FFFFFF84 20 FFFFFF84 38 15 04 FFFFFF84 39 FFFFFF84
   3D 14 06 FFFFFF84 3A FFFFFF84 40 FFFFFF84 41 14 04 FFFFFF84 3B FFFFFF84 3E 10
   04 14 00 FFFFFF84 3C 10 03 18 FFFFFF84 3D 04 09 1A FFFFFF84 37 FFFFFF84
   FFFFFF80 FFFFFF80 FFFFFFC2 00 1B 08 08 FFFFFF81 1D FFFFFF84 37 FFFFFFC0 00 FFFFFF84 3F 10
   07 1D FFFFFF81 1F FFFFFF84 3C FFFFFF84 3C 08 08 FFFFFF82 07 FFFFFF84 37 FFFFFFC0 00
   FFFFFF84 3C 08 08 FFFFFF82 3F FFFFFF84 37 FFFFFFC0 00 FFFFFF81 78 08 08 FFFFFF84 43
   FFFFFF82 57 FFFFFF84 00 FFFFFF84 44 01 04 66 72 6F 6D 14 06 FFFFFF84 45
   FFFFFF84 46 FFFFFF84 47 10 04 14 00 FFFFFF81 78 08 08 FFFFFF82 07 FFFFFF84 42
   FFFFFFC0 00 FFFFFF81 78 08 08 FFFFFF84 48 FFFFFF84 42 FFFFFFC0 00 FFFFFF81 78 01 04
   73 74 65 70 08 08 FFFFFF84 43 FFFFFF82 57 FFFFFF84 00 FFFFFF84 4A 14 04
   FFFFFF84 45 FFFFFF84 4B 08 08 FFFFFF82 07 FFFFFF84 49 FFFFFFC0 00 FFFFFF81 78 08 08
   FFFFFF84 4D FFFFFF82 57 FFFFFF84 00 FFFFFF84 4E 01 0B 63 6F 6E 74 69 6E
   75 61 6C 6C 79 15 04 FFFFFF84 4F FFFFFF84 52 14 04 FFFFFF84 50 FFFFFF84
   53 10 04 14 00 FFFFFF84 51 10 03 18 FFFFFF84 52 04 09 1A FFFFFF84
   4C FFFFFF84 FFFFFF80 FFFFFF80 FFFFFFC2 00 1B 08 09 FFFFFF82 41 FFFFFF84 4C FFFFFF84 FFFFFFC0 00
   FFFFFF84 54 10 04 1D 55 FFFFFF84 51 08 08 FFFFFF84 56 FFFFFF82 57 FFFFFF84 20
   FFFFFF84 57 01 04 66 69 6C 6C 15 04 FFFFFF84 58 FFFFFF84 5C 14 04
   FFFFFF84 59 FFFFFF84 5F 14 04 FFFFFF84 5A FFFFFF84 5D 10 04 14 00 FFFFFF84 5B
   10 03 18 FFFFFF84 5C 04 09 1A FFFFFF84 55 FFFFFF84 FFFFFF80 FFFFFF80 FFFFFFC2 00 1B
   08 09 FFFFFF82 41 FFFFFF84 55 FFFFFF84 FFFFFFC0 00 FFFFFF84 5E 10 04 1D 55 FFFFFF84
   5B 08 08 FFFFFF82 1D FFFFFF84 55 FFFFFFC0 00 FFFFFF81 78 08 08 FFFFFF84 61 FFFFFF82
   57 FFFFFF84 20 FFFFFF84 62 01 08 74 61 62 75 6C 61 74 65 15
   04 FFFFFF84 63 FFFFFF84 67 14 04 FFFFFF84 64 FFFFFF84 6A 14 04 FFFFFF84 65 FFFFFF84
   68 10 04 14 00 FFFFFF84 66 10 03 18 FFFFFF84 67 04 09 1A FFFFFF84
   60 FFFFFF84 FFFFFF80 FFFFFF80 FFFFFFC2 00 1B 08 08 FFFFFF81 1D FFFFFF84 60 FFFFFFC0 00 FFFFFF84
   69 10 07 1D FFFFFF81 1F FFFFFF81 78 FFFFFF84 66 08 08 FFFFFF82 1D FFFFFF84 60
   FFFFFFC0 00 FFFFFF81 78 08 08 FFFFFF84 6C FFFFFF82 57 FFFFFF84 20 FFFFFF84 6D 01 05
   72 61 6E 67 65 14 08 FFFFFF84 45 FFFFFF84 6E FFFFFF84 6F FFFFFF84 70 08
   08 FFFFFF82 07 FFFFFF84 6B FFFFFFC0 00 FFFFFF81 78 08 08 FFFFFF82 0A FFFFFF84 6B FFFFFFC0
   00 FFFFFF81 78 08 08 FFFFFF84 48 FFFFFF84 6B FFFFFFC0 00 FFFFFF81 78 08 08 FFFFFF84
   72 FFFFFF82 57 FFFFFF84 00 FFFFFF84 73 01 0C 66 72 6F 6D 49 74 65
   72 61 74 6F 72 15 04 FFFFFF84 74 FFFFFF84 77 14 04 FFFFFF84 75 FFFFFF84
   78 10 04 14 00 FFFFFF84 76 10 03 18 FFFFFF84 77 04 09 1A FFFFFF84
   71 FFFFFF84 FFFFFF80 FFFFFF80 FFFFFFC2 00 1B 08 08 FFFFFF84 79 FFFFFF84 71 FFFFFFC0 00 FFFFFF84
   7A 01 02 69 74 10 05 2B FFFFFF81 0F FFFFFF84 76 28 06 FFFFFF84 71
   FFFFFF83 6A FFFFFF84 7C 21 02 FFFFFF84 7D 01 17 75 73 65 20 69 74
   2E 74 6F 53 74 72 65 61 6D 20 69 6E 73 74 65 61
   64 08 08 FFFFFF84 7F FFFFFF82 57 FFFFFF84 00 FFFFFF85 00 01 06 63 6F 6E
   63 61 74 15 04 FFFFFF85 01 FFFFFF85 04 14 04 FFFFFF85 02 FFFFFF85 05 10
   04 14 00 FFFFFF85 03 10 03 18 FFFFFF85 04 04 09 1A FFFFFF84 7E FFFFFF84
   FFFFFF80 FFFFFF80 FFFFFFC2 00 1B 08 08 FFFFFF83 2C FFFFFF84 7E FFFFFFC0 00 FFFFFF85 06 10
   05 2B FFFFFF81 6B FFFFFF85 02 28 06 FFFFFF84 7E FFFFFF83 6A FFFFFF85 08 21 02
   FFFFFF85 09 01 16 75 73 65 20 78 73 2E 66 6C 61 74 74
   65 6E 20 69 6E 73 74 65 61 64 08 08 FFFFFF84 7F FFFFFF82 57
   FFFFFF84 00 FFFFFF85 0B 15 04 FFFFFF85 0C FFFFFF85 0F 14 04 FFFFFF85 0D FFFFFF85 10
   10 04 14 00 FFFFFF85 0E 10 03 18 FFFFFF85 0F 04 09 1A FFFFFF85 0A
   FFFFFF84 FFFFFF80 FFFFFF80 FFFFFFC2 00 1B 08 08 FFFFFF83 2C FFFFFF85 0A FFFFFFC0 00 FFFFFF85 11
   10 05 2B FFFFFF81 0F FFFFFF85 0D 28 06 FFFFFF85 0A FFFFFF83 6A FFFFFF85 13 21
   02 FFFFFF85 14 01 1F 75 73 65 20 78 73 2E 74 6F 53 74
   72 65 61 6D 2E 66 6C 61 74 74 65 6E 20 69 6E 73
   74 65 61 64 08 08 FFFFFF84 6C FFFFFF82 57 FFFFFF84 00 FFFFFF85 16 14 08
   FFFFFF84 45 FFFFFF85 17 FFFFFF85 18 FFFFFF85 19 08 08 FFFFFF82 07 FFFFFF85 15 FFFFFFC0 00
   FFFFFF81 78 08 08 FFFFFF82 0A FFFFFF85 15 FFFFFFC0 00 FFFFFF81 78 08 08 FFFFFF84 48
   FFFFFF85 15 FFFFFFC0 00 FFFFFF85 1A 10 07 1D FFFFFF81 1F FFFFFF81 78 FFFFFF81 78 28
   06 FFFFFF85 15 FFFFFF83 6A FFFFFF85 1C 21 02 FFFFFF85 1D 01 16 75 73 65
   20 60 69 74 65 72 61 74 65 27 20 69 6E 73 74 65
   61 64 2E 08 08 FFFFFF85 1F FFFFFF82 57 FFFFFF84 00 FFFFFF85 20 01 05 63
   6F 6E 73 74 15 04 FFFFFF85 21 FFFFFF85 24 14 04 FFFFFF85 22 FFFFFF85 25
   10 04 14 00 FFFFFF85 23 10 03 18 FFFFFF85 24 04 09 1A FFFFFF85 1E
   FFFFFF84 FFFFFF80 FFFFFF80 FFFFFFC2 00 1B 08 08 FFFFFF82 41 FFFFFF85 1E FFFFFFC0 00 FFFFFF85 23
   28 06 FFFFFF85 1E FFFFFF83 6A FFFFFF85 27 21 02 FFFFFF85 28 01 19 75 73
   65 20 60 63 6F 6E 74 69 6E 75 61 6C 6C 79 27 20
   69 6E 73 74 65 61 64 08 08 FFFFFF85 2A FFFFFF82 57 FFFFFF84 00 FFFFFF85
   2B 01 04 6D 61 6B 65 15 04 FFFFFF85 2C FFFFFF85 2F 14 06 FFFFFF85
   2D FFFFFF85 30 FFFFFF85 31 10 04 14 00 FFFFFF85 2E 10 03 18 FFFFFF85 2F
   04 09 1A FFFFFF85 29 FFFFFF84 FFFFFF80 FFFFFF80 FFFFFFC2 00 1B 08 08 FFFFFF82 1D FFFFFF85
   29 FFFFFFC0 00 FFFFFF81 78 08 08 FFFFFF82 41 FFFFFF85 29 FFFFFFC0 00 FFFFFF85 2E 28
   06 FFFFFF85 29 FFFFFF83 6A FFFFFF85 33 21 02 FFFFFF85 34 01 19 75 73 65
   20 66 69 6C 6C 28 6E 2C 20 65 6C 65 6D 29 20 69
   6E 73 74 65 61 64 
  InnerClass: 
   public final #1113= #256 of #250; //Cons=class scala/collection/immutable/Stream$Cons of class scala/collection/immutable/Stream
   public final #1114= #584 of #250; //$anonfun$1=class scala/collection/immutable/Stream$$anonfun$1 of class scala/collection/immutable/Stream
   public final #1115= #460 of #250; //$anonfun$2=class scala/collection/immutable/Stream$$anonfun$2 of class scala/collection/immutable/Stream
   public #1116= #465 of #250; //ConsWrapper=class scala/collection/immutable/Stream$ConsWrapper of class scala/collection/immutable/Stream
   public #1119= #1118 of #250; //StreamBuilder=class scala/collection/immutable/Stream$StreamBuilder of class scala/collection/immutable/Stream
   public final #1120= #636 of #250; //$anonfun$map$1=class scala/collection/immutable/Stream$$anonfun$map$1 of class scala/collection/immutable/Stream
   public final #1121= #570 of #250; //$anonfun$zip$1=class scala/collection/immutable/Stream$$anonfun$zip$1 of class scala/collection/immutable/Stream
   public final #1124= #1123 of #250; //$anonfun$make$1=class scala/collection/immutable/Stream$$anonfun$make$1 of class scala/collection/immutable/Stream
   public final #1127= #1126 of #250; //$anonfun$from$1=class scala/collection/immutable/Stream$$anonfun$from$1 of class scala/collection/immutable/Stream
   public final #1128= #511 of #250; //$anonfun$take$1=class scala/collection/immutable/Stream$$anonfun$take$1 of class scala/collection/immutable/Stream
   public final #1129= #506 of #250; //$anonfun$init$1=class scala/collection/immutable/Stream$$anonfun$init$1 of class scala/collection/immutable/Stream
   public final #1130= #289 of #250; //$anonfun$fill$1=class scala/collection/immutable/Stream$$anonfun$fill$1 of class scala/collection/immutable/Stream
   public final #1133= #1132 of #250; //$anonfun$const$1=class scala/collection/immutable/Stream$$anonfun$const$1 of class scala/collection/immutable/Stream
   public final #1136= #1135 of #250; //$anonfun$range$1=class scala/collection/immutable/Stream$$anonfun$range$1 of class scala/collection/immutable/Stream
   public final #1139= #1138 of #250; //$anonfun$loop$5$1=class scala/collection/immutable/Stream$$anonfun$loop$5$1 of class scala/collection/immutable/Stream
   public final #1140= #676 of #250; //$anonfun$append$1=class scala/collection/immutable/Stream$$anonfun$append$1 of class scala/collection/immutable/Stream
   public final #1141= #587 of #250; //$anonfun$filter$1=class scala/collection/immutable/Stream$$anonfun$filter$1 of class scala/collection/immutable/Stream
   public final #1142= #295 of #250; //$anonfun$loop$4$2=class scala/collection/immutable/Stream$$anonfun$loop$4$2 of class scala/collection/immutable/Stream
   public final #1143= #279 of #250; //$anonfun$loop$4$1=class scala/collection/immutable/Stream$$anonfun$loop$4$1 of class scala/collection/immutable/Stream
   public final #1146= #1145 of #250; //$anonfun$iterate$1=class scala/collection/immutable/Stream$$anonfun$iterate$1 of class scala/collection/immutable/Stream
   public #1149= #1148 of #250; //StreamCanBuildFrom=class scala/collection/immutable/Stream$StreamCanBuildFrom of class scala/collection/immutable/Stream
   public final #1150= #623 of #250; //$anonfun$flatMap$1=class scala/collection/immutable/Stream$$anonfun$flatMap$1 of class scala/collection/immutable/Stream
   public #1153= #1152 of #240; //WithFilter=class scala/collection/TraversableLike$WithFilter of class scala/collection/TraversableLike
   public final #1154= #592 of #250; //$anonfun$partition$2=class scala/collection/immutable/Stream$$anonfun$partition$2 of class scala/collection/immutable/Stream
   public final #1155= #581 of #250; //$anonfun$partition$1=class scala/collection/immutable/Stream$$anonfun$partition$1 of class scala/collection/immutable/Stream
   public final #1156= #495 of #250; //$anonfun$takeWhile$1=class scala/collection/immutable/Stream$$anonfun$takeWhile$1 of class scala/collection/immutable/Stream
   public final #1157= #655 of #250; //$anonfun$$plus$plus$1=class scala/collection/immutable/Stream$$anonfun$$plus$plus$1 of class scala/collection/immutable/Stream
   public final #1158= #261 of #250; //$anonfun$flatten1$1$1=class scala/collection/immutable/Stream$$anonfun$flatten1$1$1 of class scala/collection/immutable/Stream
   public final #1161= #1160 of #250; //$anonfun$continually$1=class scala/collection/immutable/Stream$$anonfun$continually$1 of class scala/collection/immutable/Stream
   public final #1162= #486 of #250; //$anonfun$removeDuplicates$1=class scala/collection/immutable/Stream$$anonfun$removeDuplicates$1 of class scala/collection/immutable/Stream
  minor version: 0
  major version: 49
  Constant pool:
const #1 = Asciz	SourceFile;
const #2 = Asciz	Stream.scala;
const #3 = Asciz	make;
const #4 = Asciz	(ILjava/lang/Object;)Lscala/collection/immutable/Stream;;
const #5 = Asciz	Code;
const #6 = Asciz	scala/collection/immutable/Stream$;
const #7 = class	#6;	//  scala/collection/immutable/Stream$
const #8 = Asciz	MODULE$;
const #9 = Asciz	Lscala/collection/immutable/Stream$;;
const #10 = NameAndType	#8:#9;//  MODULE$:Lscala/collection/immutable/Stream$;
const #11 = Field	#7.#10;	//  scala/collection/immutable/Stream$.MODULE$:Lscala/collection/immutable/Stream$;
const #12 = NameAndType	#3:#4;//  make:(ILjava/lang/Object;)Lscala/collection/immutable/Stream;
const #13 = Method	#7.#12;	//  scala/collection/immutable/Stream$.make:(ILjava/lang/Object;)Lscala/collection/immutable/Stream;
const #14 = Asciz	<A:Ljava/lang/Object;>(ITA;)Lscala/collection/immutable/Stream<TA;>;;
const #15 = Asciz	Signature;
const #16 = Asciz	const;
const #17 = Asciz	(Ljava/lang/Object;)Lscala/collection/immutable/Stream;;
const #18 = NameAndType	#16:#17;//  const:(Ljava/lang/Object;)Lscala/collection/immutable/Stream;
const #19 = Method	#7.#18;	//  scala/collection/immutable/Stream$.const:(Ljava/lang/Object;)Lscala/collection/immutable/Stream;
const #20 = Asciz	<A:Ljava/lang/Object;>(TA;)Lscala/collection/immutable/Stream<TA;>;;
const #21 = Asciz	range;
const #22 = Asciz	(IILscala/Function1;)Lscala/collection/immutable/Stream;;
const #23 = NameAndType	#21:#22;//  range:(IILscala/Function1;)Lscala/collection/immutable/Stream;
const #24 = Method	#7.#23;	//  scala/collection/immutable/Stream$.range:(IILscala/Function1;)Lscala/collection/immutable/Stream;
const #25 = Asciz	(IILscala/Function1<Ljava/lang/Integer;Ljava/lang/Integer;>;)Lscala/collection/immutable/Stream<Ljava/lang/Integer;>;;
const #26 = Asciz	concat;
const #27 = Asciz	(Lscala/collection/Iterator;)Lscala/collection/immutable/Stream;;
const #28 = NameAndType	#26:#27;//  concat:(Lscala/collection/Iterator;)Lscala/collection/immutable/Stream;
const #29 = Method	#7.#28;	//  scala/collection/immutable/Stream$.concat:(Lscala/collection/Iterator;)Lscala/collection/immutable/Stream;
const #30 = Asciz	<A:Ljava/lang/Object;>(Lscala/collection/Iterator<Lscala/collection/immutable/Stream<TA;>;>;)Lscala/collection/immutable/Stream<TA;>;;
const #31 = Asciz	(Lscala/collection/Iterable;)Lscala/collection/immutable/Stream;;
const #32 = NameAndType	#26:#31;//  concat:(Lscala/collection/Iterable;)Lscala/collection/immutable/Stream;
const #33 = Method	#7.#32;	//  scala/collection/immutable/Stream$.concat:(Lscala/collection/Iterable;)Lscala/collection/immutable/Stream;
const #34 = Asciz	<A:Ljava/lang/Object;>(Lscala/collection/Iterable<Lscala/collection/immutable/Stream<TA;>;>;)Lscala/collection/immutable/Stream<TA;>;;
const #35 = Asciz	fromIterator;
const #36 = NameAndType	#35:#27;//  fromIterator:(Lscala/collection/Iterator;)Lscala/collection/immutable/Stream;
const #37 = Method	#7.#36;	//  scala/collection/immutable/Stream$.fromIterator:(Lscala/collection/Iterator;)Lscala/collection/immutable/Stream;
const #38 = Asciz	<A:Ljava/lang/Object;>(Lscala/collection/Iterator<TA;>;)Lscala/collection/immutable/Stream<TA;>;;
const #39 = Asciz	(III)Lscala/collection/immutable/Stream;;
const #40 = NameAndType	#21:#39;//  range:(III)Lscala/collection/immutable/Stream;
const #41 = Method	#7.#40;	//  scala/collection/immutable/Stream$.range:(III)Lscala/collection/immutable/Stream;
const #42 = Asciz	(III)Lscala/collection/immutable/Stream<Ljava/lang/Integer;>;;
const #43 = Asciz	tabulate;
const #44 = Asciz	(ILscala/Function1;)Lscala/collection/immutable/Stream;;
const #45 = NameAndType	#43:#44;//  tabulate:(ILscala/Function1;)Lscala/collection/immutable/Stream;
const #46 = Method	#7.#45;	//  scala/collection/immutable/Stream$.tabulate:(ILscala/Function1;)Lscala/collection/immutable/Stream;
const #47 = Asciz	<A:Ljava/lang/Object;>(ILscala/Function1<Ljava/lang/Integer;TA;>;)Lscala/collection/immutable/Stream<TA;>;;
const #48 = Asciz	fill;
const #49 = Asciz	(ILscala/Function0;)Lscala/collection/immutable/Stream;;
const #50 = NameAndType	#48:#49;//  fill:(ILscala/Function0;)Lscala/collection/immutable/Stream;
const #51 = Method	#7.#50;	//  scala/collection/immutable/Stream$.fill:(ILscala/Function0;)Lscala/collection/immutable/Stream;
const #52 = Asciz	<A:Ljava/lang/Object;>(ILscala/Function0<TA;>;)Lscala/collection/immutable/Stream<TA;>;;
const #53 = Asciz	continually;
const #54 = Asciz	(Lscala/Function0;)Lscala/collection/immutable/Stream;;
const #55 = NameAndType	#53:#54;//  continually:(Lscala/Function0;)Lscala/collection/immutable/Stream;
const #56 = Method	#7.#55;	//  scala/collection/immutable/Stream$.continually:(Lscala/Function0;)Lscala/collection/immutable/Stream;
const #57 = Asciz	<A:Ljava/lang/Object;>(Lscala/Function0<TA;>;)Lscala/collection/immutable/Stream<TA;>;;
const #58 = Asciz	from;
const #59 = Asciz	(I)Lscala/collection/immutable/Stream;;
const #60 = NameAndType	#58:#59;//  from:(I)Lscala/collection/immutable/Stream;
const #61 = Method	#7.#60;	//  scala/collection/immutable/Stream$.from:(I)Lscala/collection/immutable/Stream;
const #62 = Asciz	(I)Lscala/collection/immutable/Stream<Ljava/lang/Integer;>;;
const #63 = Asciz	(II)Lscala/collection/immutable/Stream;;
const #64 = NameAndType	#58:#63;//  from:(II)Lscala/collection/immutable/Stream;
const #65 = Method	#7.#64;	//  scala/collection/immutable/Stream$.from:(II)Lscala/collection/immutable/Stream;
const #66 = Asciz	(II)Lscala/collection/immutable/Stream<Ljava/lang/Integer;>;;
const #67 = Asciz	iterate;
const #68 = Asciz	(Ljava/lang/Object;ILscala/Function1;)Lscala/collection/immutable/Stream;;
const #69 = NameAndType	#67:#68;//  iterate:(Ljava/lang/Object;ILscala/Function1;)Lscala/collection/immutable/Stream;
const #70 = Method	#7.#69;	//  scala/collection/immutable/Stream$.iterate:(Ljava/lang/Object;ILscala/Function1;)Lscala/collection/immutable/Stream;
const #71 = Asciz	<A:Ljava/lang/Object;>(TA;ILscala/Function1<TA;TA;>;)Lscala/collection/immutable/Stream<TA;>;;
const #72 = Asciz	(Ljava/lang/Object;Lscala/Function1;)Lscala/collection/immutable/Stream;;
const #73 = NameAndType	#67:#72;//  iterate:(Ljava/lang/Object;Lscala/Function1;)Lscala/collection/immutable/Stream;
const #74 = Method	#7.#73;	//  scala/collection/immutable/Stream$.iterate:(Ljava/lang/Object;Lscala/Function1;)Lscala/collection/immutable/Stream;
const #75 = Asciz	<A:Ljava/lang/Object;>(TA;Lscala/Function1<TA;TA;>;)Lscala/collection/immutable/Stream<TA;>;;
const #76 = Asciz	lazy_$colon$colon;
const #77 = Asciz	()Lscala/collection/immutable/Stream$$hash$colon$colon$;;
const #78 = NameAndType	#76:#77;//  lazy_$colon$colon:()Lscala/collection/immutable/Stream$$hash$colon$colon$;
const #79 = Method	#7.#78;	//  scala/collection/immutable/Stream$.lazy_$colon$colon:()Lscala/collection/immutable/Stream$$hash$colon$colon$;
const #80 = Asciz	consWrapper;
const #81 = Asciz	(Lscala/Function0;)Lscala/collection/immutable/Stream$ConsWrapper;;
const #82 = NameAndType	#80:#81;//  consWrapper:(Lscala/Function0;)Lscala/collection/immutable/Stream$ConsWrapper;
const #83 = Method	#7.#82;	//  scala/collection/immutable/Stream$.consWrapper:(Lscala/Function0;)Lscala/collection/immutable/Stream$ConsWrapper;
const #84 = Asciz	<A:Ljava/lang/Object;>(Lscala/Function0<Lscala/collection/immutable/Stream<TA;>;>;)Lscala/collection/immutable/Stream$ConsWrapper<TA;>;;
const #85 = Asciz	empty;
const #86 = Asciz	()Lscala/collection/immutable/Stream;;
const #87 = NameAndType	#85:#86;//  empty:()Lscala/collection/immutable/Stream;
const #88 = Method	#7.#87;	//  scala/collection/immutable/Stream$.empty:()Lscala/collection/immutable/Stream;
const #89 = Asciz	<A:Ljava/lang/Object;>()Lscala/collection/immutable/Stream<TA;>;;
const #90 = Asciz	canBuildFrom;
const #91 = Asciz	()Lscala/collection/generic/CanBuildFrom;;
const #92 = NameAndType	#90:#91;//  canBuildFrom:()Lscala/collection/generic/CanBuildFrom;
const #93 = Method	#7.#92;	//  scala/collection/immutable/Stream$.canBuildFrom:()Lscala/collection/generic/CanBuildFrom;
const #94 = Asciz	<A:Ljava/lang/Object;>()Lscala/collection/generic/CanBuildFrom<Lscala/collection/immutable/Stream<*>;TA;Lscala/collection/immutable/Stream<TA;>;>;;
const #95 = Asciz	unapplySeq;
const #96 = Asciz	(Lscala/collection/Seq;)Lscala/Some;;
const #97 = NameAndType	#95:#96;//  unapplySeq:(Lscala/collection/Seq;)Lscala/Some;
const #98 = Method	#7.#97;	//  scala/collection/immutable/Stream$.unapplySeq:(Lscala/collection/Seq;)Lscala/Some;
const #99 = Asciz	<A:Ljava/lang/Object;>(Lscala/collection/immutable/Stream<TA;>;)Lscala/Some<Lscala/collection/immutable/Stream<TA;>;>;;
const #100 = Asciz	(Ljava/lang/Object;ILscala/Function1;)Lscala/collection/Traversable;;
const #101 = NameAndType	#67:#100;//  iterate:(Ljava/lang/Object;ILscala/Function1;)Lscala/collection/Traversable;
const #102 = Method	#7.#101;	//  scala/collection/immutable/Stream$.iterate:(Ljava/lang/Object;ILscala/Function1;)Lscala/collection/Traversable;
const #103 = Asciz	(III)Lscala/collection/Traversable;;
const #104 = NameAndType	#21:#103;//  range:(III)Lscala/collection/Traversable;
const #105 = Method	#7.#104;	//  scala/collection/immutable/Stream$.range:(III)Lscala/collection/Traversable;
const #106 = Asciz	(II)Lscala/collection/Traversable;;
const #107 = NameAndType	#21:#106;//  range:(II)Lscala/collection/Traversable;
const #108 = Method	#7.#107;	//  scala/collection/immutable/Stream$.range:(II)Lscala/collection/Traversable;
const #109 = Asciz	(IIIIILscala/Function5;)Lscala/collection/Traversable;;
const #110 = NameAndType	#43:#109;//  tabulate:(IIIIILscala/Function5;)Lscala/collection/Traversable;
const #111 = Method	#7.#110;	//  scala/collection/immutable/Stream$.tabulate:(IIIIILscala/Function5;)Lscala/collection/Traversable;
const #112 = Asciz	<A:Ljava/lang/Object;>(IIIIILscala/Function5<Ljava/lang/Integer;Ljava/lang/Integer;Ljava/lang/Integer;Ljava/lang/Integer;Ljava/lang/Integer;TA;>;)Lscala/collection/immutable/Stream<Lscala/collection/immutable/Stream<Lscala/collection/immutable/Stream<Lscala/collection/immutable/Stream<Lscala/collection/immutable/Stream<TA;>;>;>;>;>;;
const #113 = Asciz	(IIIILscala/Function4;)Lscala/collection/Traversable;;
const #114 = NameAndType	#43:#113;//  tabulate:(IIIILscala/Function4;)Lscala/collection/Traversable;
const #115 = Method	#7.#114;	//  scala/collection/immutable/Stream$.tabulate:(IIIILscala/Function4;)Lscala/collection/Traversable;
const #116 = Asciz	<A:Ljava/lang/Object;>(IIIILscala/Function4<Ljava/lang/Integer;Ljava/lang/Integer;Ljava/lang/Integer;Ljava/lang/Integer;TA;>;)Lscala/collection/immutable/Stream<Lscala/collection/immutable/Stream<Lscala/collection/immutable/Stream<Lscala/collection/immutable/Stream<TA;>;>;>;>;;
const #117 = Asciz	(IIILscala/Function3;)Lscala/collection/Traversable;;
const #118 = NameAndType	#43:#117;//  tabulate:(IIILscala/Function3;)Lscala/collection/Traversable;
const #119 = Method	#7.#118;	//  scala/collection/immutable/Stream$.tabulate:(IIILscala/Function3;)Lscala/collection/Traversable;
const #120 = Asciz	<A:Ljava/lang/Object;>(IIILscala/Function3<Ljava/lang/Integer;Ljava/lang/Integer;Ljava/lang/Integer;TA;>;)Lscala/collection/immutable/Stream<Lscala/collection/immutable/Stream<Lscala/collection/immutable/Stream<TA;>;>;>;;
const #121 = Asciz	(IILscala/Function2;)Lscala/collection/Traversable;;
const #122 = NameAndType	#43:#121;//  tabulate:(IILscala/Function2;)Lscala/collection/Traversable;
const #123 = Method	#7.#122;	//  scala/collection/immutable/Stream$.tabulate:(IILscala/Function2;)Lscala/collection/Traversable;
const #124 = Asciz	<A:Ljava/lang/Object;>(IILscala/Function2<Ljava/lang/Integer;Ljava/lang/Integer;TA;>;)Lscala/collection/immutable/Stream<Lscala/collection/immutable/Stream<TA;>;>;;
const #125 = Asciz	(ILscala/Function1;)Lscala/collection/Traversable;;
const #126 = NameAndType	#43:#125;//  tabulate:(ILscala/Function1;)Lscala/collection/Traversable;
const #127 = Method	#7.#126;	//  scala/collection/immutable/Stream$.tabulate:(ILscala/Function1;)Lscala/collection/Traversable;
const #128 = Asciz	(IIIIILscala/Function0;)Lscala/collection/Traversable;;
const #129 = NameAndType	#48:#128;//  fill:(IIIIILscala/Function0;)Lscala/collection/Traversable;
const #130 = Method	#7.#129;	//  scala/collection/immutable/Stream$.fill:(IIIIILscala/Function0;)Lscala/collection/Traversable;
const #131 = Asciz	<A:Ljava/lang/Object;>(IIIIILscala/Function0<TA;>;)Lscala/collection/immutable/Stream<Lscala/collection/immutable/Stream<Lscala/collection/immutable/Stream<Lscala/collection/immutable/Stream<Lscala/collection/immutable/Stream<TA;>;>;>;>;>;;
const #132 = Asciz	(IIIILscala/Function0;)Lscala/collection/Traversable;;
const #133 = NameAndType	#48:#132;//  fill:(IIIILscala/Function0;)Lscala/collection/Traversable;
const #134 = Method	#7.#133;	//  scala/collection/immutable/Stream$.fill:(IIIILscala/Function0;)Lscala/collection/Traversable;
const #135 = Asciz	<A:Ljava/lang/Object;>(IIIILscala/Function0<TA;>;)Lscala/collection/immutable/Stream<Lscala/collection/immutable/Stream<Lscala/collection/immutable/Stream<Lscala/collection/immutable/Stream<TA;>;>;>;>;;
const #136 = Asciz	(IIILscala/Function0;)Lscala/collection/Traversable;;
const #137 = NameAndType	#48:#136;//  fill:(IIILscala/Function0;)Lscala/collection/Traversable;
const #138 = Method	#7.#137;	//  scala/collection/immutable/Stream$.fill:(IIILscala/Function0;)Lscala/collection/Traversable;
const #139 = Asciz	<A:Ljava/lang/Object;>(IIILscala/Function0<TA;>;)Lscala/collection/immutable/Stream<Lscala/collection/immutable/Stream<Lscala/collection/immutable/Stream<TA;>;>;>;;
const #140 = Asciz	(IILscala/Function0;)Lscala/collection/Traversable;;
const #141 = NameAndType	#48:#140;//  fill:(IILscala/Function0;)Lscala/collection/Traversable;
const #142 = Method	#7.#141;	//  scala/collection/immutable/Stream$.fill:(IILscala/Function0;)Lscala/collection/Traversable;
const #143 = Asciz	<A:Ljava/lang/Object;>(IILscala/Function0<TA;>;)Lscala/collection/immutable/Stream<Lscala/collection/immutable/Stream<TA;>;>;;
const #144 = Asciz	(ILscala/Function0;)Lscala/collection/Traversable;;
const #145 = NameAndType	#48:#144;//  fill:(ILscala/Function0;)Lscala/collection/Traversable;
const #146 = Method	#7.#145;	//  scala/collection/immutable/Stream$.fill:(ILscala/Function0;)Lscala/collection/Traversable;
const #147 = Asciz	(Lscala/collection/Seq;)Lscala/collection/Traversable;;
const #148 = NameAndType	#26:#147;//  concat:(Lscala/collection/Seq;)Lscala/collection/Traversable;
const #149 = Method	#7.#148;	//  scala/collection/immutable/Stream$.concat:(Lscala/collection/Seq;)Lscala/collection/Traversable;
const #150 = Asciz	<A:Ljava/lang/Object;>(Lscala/collection/Seq<Lscala/collection/Traversable<TA;>;>;)Lscala/collection/immutable/Stream<TA;>;;
const #151 = Asciz	()Lscala/collection/Traversable;;
const #152 = NameAndType	#85:#151;//  empty:()Lscala/collection/Traversable;
const #153 = Method	#7.#152;	//  scala/collection/immutable/Stream$.empty:()Lscala/collection/Traversable;
const #154 = Asciz	<init>;
const #155 = Asciz	()V;
const #156 = Asciz	LineNumberTable;
const #157 = Asciz	java/lang/Object;
const #158 = class	#157;	//  java/lang/Object
const #159 = NameAndType	#154:#155;//  "<init>":()V
const #160 = Method	#158.#159;	//  java/lang/Object."<init>":()V
const #161 = Asciz	scala/collection/TraversableLike$class;
const #162 = class	#161;	//  scala/collection/TraversableLike$class
const #163 = Asciz	$init$;
const #164 = Asciz	(Lscala/collection/TraversableLike;)V;
const #165 = NameAndType	#163:#164;//  $init$:(Lscala/collection/TraversableLike;)V
const #166 = Method	#162.#165;	//  scala/collection/TraversableLike$class.$init$:(Lscala/collection/TraversableLike;)V
const #167 = Asciz	scala/collection/generic/GenericTraversableTemplate$class;
const #168 = class	#167;	//  scala/collection/generic/GenericTraversableTemplate$class
const #169 = Asciz	(Lscala/collection/generic/GenericTraversableTemplate;)V;
const #170 = NameAndType	#163:#169;//  $init$:(Lscala/collection/generic/GenericTraversableTemplate;)V
const #171 = Method	#168.#170;	//  scala/collection/generic/GenericTraversableTemplate$class.$init$:(Lscala/collection/generic/GenericTraversableTemplate;)V
const #172 = Asciz	scala/collection/Traversable$class;
const #173 = class	#172;	//  scala/collection/Traversable$class
const #174 = Asciz	(Lscala/collection/Traversable;)V;
const #175 = NameAndType	#163:#174;//  $init$:(Lscala/collection/Traversable;)V
const #176 = Method	#173.#175;	//  scala/collection/Traversable$class.$init$:(Lscala/collection/Traversable;)V
const #177 = Asciz	scala/collection/immutable/Traversable$class;
const #178 = class	#177;	//  scala/collection/immutable/Traversable$class
const #179 = Asciz	(Lscala/collection/immutable/Traversable;)V;
const #180 = NameAndType	#163:#179;//  $init$:(Lscala/collection/immutable/Traversable;)V
const #181 = Method	#178.#180;	//  scala/collection/immutable/Traversable$class.$init$:(Lscala/collection/immutable/Traversable;)V
const #182 = Asciz	scala/collection/IterableLike$class;
const #183 = class	#182;	//  scala/collection/IterableLike$class
const #184 = Asciz	(Lscala/collection/IterableLike;)V;
const #185 = NameAndType	#163:#184;//  $init$:(Lscala/collection/IterableLike;)V
const #186 = Method	#183.#185;	//  scala/collection/IterableLike$class.$init$:(Lscala/collection/IterableLike;)V
const #187 = Asciz	scala/collection/Iterable$class;
const #188 = class	#187;	//  scala/collection/Iterable$class
const #189 = Asciz	(Lscala/collection/Iterable;)V;
const #190 = NameAndType	#163:#189;//  $init$:(Lscala/collection/Iterable;)V
const #191 = Method	#188.#190;	//  scala/collection/Iterable$class.$init$:(Lscala/collection/Iterable;)V
const #192 = Asciz	scala/collection/immutable/Iterable$class;
const #193 = class	#192;	//  scala/collection/immutable/Iterable$class
const #194 = Asciz	(Lscala/collection/immutable/Iterable;)V;
const #195 = NameAndType	#163:#194;//  $init$:(Lscala/collection/immutable/Iterable;)V
const #196 = Method	#193.#195;	//  scala/collection/immutable/Iterable$class.$init$:(Lscala/collection/immutable/Iterable;)V
const #197 = Asciz	scala/Function1$class;
const #198 = class	#197;	//  scala/Function1$class
const #199 = Asciz	(Lscala/Function1;)V;
const #200 = NameAndType	#163:#199;//  $init$:(Lscala/Function1;)V
const #201 = Method	#198.#200;	//  scala/Function1$class.$init$:(Lscala/Function1;)V
const #202 = Asciz	scala/PartialFunction$class;
const #203 = class	#202;	//  scala/PartialFunction$class
const #204 = Asciz	(Lscala/PartialFunction;)V;
const #205 = NameAndType	#163:#204;//  $init$:(Lscala/PartialFunction;)V
const #206 = Method	#203.#205;	//  scala/PartialFunction$class.$init$:(Lscala/PartialFunction;)V
const #207 = Asciz	scala/collection/SeqLike$class;
const #208 = class	#207;	//  scala/collection/SeqLike$class
const #209 = Asciz	(Lscala/collection/SeqLike;)V;
const #210 = NameAndType	#163:#209;//  $init$:(Lscala/collection/SeqLike;)V
const #211 = Method	#208.#210;	//  scala/collection/SeqLike$class.$init$:(Lscala/collection/SeqLike;)V
const #212 = Asciz	scala/collection/Seq$class;
const #213 = class	#212;	//  scala/collection/Seq$class
const #214 = Asciz	(Lscala/collection/Seq;)V;
const #215 = NameAndType	#163:#214;//  $init$:(Lscala/collection/Seq;)V
const #216 = Method	#213.#215;	//  scala/collection/Seq$class.$init$:(Lscala/collection/Seq;)V
const #217 = Asciz	scala/collection/immutable/Seq$class;
const #218 = class	#217;	//  scala/collection/immutable/Seq$class
const #219 = Asciz	(Lscala/collection/immutable/Seq;)V;
const #220 = NameAndType	#163:#219;//  $init$:(Lscala/collection/immutable/Seq;)V
const #221 = Method	#218.#220;	//  scala/collection/immutable/Seq$class.$init$:(Lscala/collection/immutable/Seq;)V
const #222 = Asciz	scala/collection/LinearSeqLike$class;
const #223 = class	#222;	//  scala/collection/LinearSeqLike$class
const #224 = Asciz	(Lscala/collection/LinearSeqLike;)V;
const #225 = NameAndType	#163:#224;//  $init$:(Lscala/collection/LinearSeqLike;)V
const #226 = Method	#223.#225;	//  scala/collection/LinearSeqLike$class.$init$:(Lscala/collection/LinearSeqLike;)V
const #227 = Asciz	scala/collection/LinearSeq$class;
const #228 = class	#227;	//  scala/collection/LinearSeq$class
const #229 = Asciz	(Lscala/collection/LinearSeq;)V;
const #230 = NameAndType	#163:#229;//  $init$:(Lscala/collection/LinearSeq;)V
const #231 = Method	#228.#230;	//  scala/collection/LinearSeq$class.$init$:(Lscala/collection/LinearSeq;)V
const #232 = Asciz	scala/collection/immutable/LinearSeq$class;
const #233 = class	#232;	//  scala/collection/immutable/LinearSeq$class
const #234 = Asciz	(Lscala/collection/immutable/LinearSeq;)V;
const #235 = NameAndType	#163:#234;//  $init$:(Lscala/collection/immutable/LinearSeq;)V
const #236 = Method	#233.#235;	//  scala/collection/immutable/LinearSeq$class.$init$:(Lscala/collection/immutable/LinearSeq;)V
const #237 = Asciz	flatten1$1;
const #238 = Asciz	(Lscala/collection/Traversable;Lscala/Function1;)Lscala/collection/immutable/Stream;;
const #239 = Asciz	scala/collection/TraversableLike;
const #240 = class	#239;	//  scala/collection/TraversableLike
const #241 = Asciz	isEmpty;
const #242 = Asciz	()Z;
const #243 = NameAndType	#241:#242;//  isEmpty:()Z
const #244 = InterfaceMethod	#240.#243;	//  scala/collection/TraversableLike.isEmpty:()Z
const #245 = Asciz	tail;
const #246 = Asciz	()Ljava/lang/Object;;
const #247 = NameAndType	#245:#246;//  tail:()Ljava/lang/Object;
const #248 = InterfaceMethod	#240.#247;	//  scala/collection/TraversableLike.tail:()Ljava/lang/Object;
const #249 = Asciz	scala/collection/immutable/Stream;
const #250 = class	#249;	//  scala/collection/immutable/Stream
const #251 = Asciz	flatten;
const #252 = Asciz	(Lscala/Function1;)Lscala/collection/immutable/Stream;;
const #253 = NameAndType	#251:#252;//  flatten:(Lscala/Function1;)Lscala/collection/immutable/Stream;
const #254 = Method	#250.#253;	//  scala/collection/immutable/Stream.flatten:(Lscala/Function1;)Lscala/collection/immutable/Stream;
const #255 = Asciz	scala/collection/immutable/Stream$Cons;
const #256 = class	#255;	//  scala/collection/immutable/Stream$Cons
const #257 = Asciz	head;
const #258 = NameAndType	#257:#246;//  head:()Ljava/lang/Object;
const #259 = InterfaceMethod	#240.#258;	//  scala/collection/TraversableLike.head:()Ljava/lang/Object;
const #260 = Asciz	scala/collection/immutable/Stream$$anonfun$flatten1$1$1;
const #261 = class	#260;	//  scala/collection/immutable/Stream$$anonfun$flatten1$1$1
const #262 = Asciz	(Lscala/collection/immutable/Stream;Lscala/Function1;Lscala/collection/Traversable;)V;
const #263 = NameAndType	#154:#262;//  "<init>":(Lscala/collection/immutable/Stream;Lscala/Function1;Lscala/collection/Traversable;)V
const #264 = Method	#261.#263;	//  scala/collection/immutable/Stream$$anonfun$flatten1$1$1."<init>":(Lscala/collection/immutable/Stream;Lscala/Function1;Lscala/collection/Traversable;)V
const #265 = Asciz	(Ljava/lang/Object;Lscala/Function0;)V;
const #266 = NameAndType	#154:#265;//  "<init>":(Ljava/lang/Object;Lscala/Function0;)V
const #267 = Method	#256.#266;	//  scala/collection/immutable/Stream$Cons."<init>":(Ljava/lang/Object;Lscala/Function0;)V
const #268 = Asciz	this;
const #269 = Asciz	Lscala/collection/immutable/Stream;;
const #270 = Asciz	t$1;
const #271 = Asciz	Lscala/collection/Traversable;;
const #272 = Asciz	LocalVariableTable;
const #273 = Asciz	loop$4;
const #274 = Asciz	(ILscala/collection/immutable/Stream;Ljava/lang/Object;)Lscala/collection/immutable/Stream;;
const #275 = Asciz	scala/collection/IterableLike;
const #276 = class	#275;	//  scala/collection/IterableLike
const #277 = InterfaceMethod	#276.#243;	//  scala/collection/IterableLike.isEmpty:()Z
const #278 = Asciz	scala/collection/immutable/Stream$$anonfun$loop$4$1;
const #279 = class	#278;	//  scala/collection/immutable/Stream$$anonfun$loop$4$1
const #280 = Asciz	(Lscala/collection/immutable/Stream;Ljava/lang/Object;)V;
const #281 = NameAndType	#154:#280;//  "<init>":(Lscala/collection/immutable/Stream;Ljava/lang/Object;)V
const #282 = Method	#279.#281;	//  scala/collection/immutable/Stream$$anonfun$loop$4$1."<init>":(Lscala/collection/immutable/Stream;Ljava/lang/Object;)V
const #283 = Asciz	scala/collection/immutable/Stream$Empty$;
const #284 = class	#283;	//  scala/collection/immutable/Stream$Empty$
const #285 = Asciz	Lscala/collection/immutable/Stream$Empty$;;
const #286 = NameAndType	#8:#285;//  MODULE$:Lscala/collection/immutable/Stream$Empty$;
const #287 = Field	#284.#286;	//  scala/collection/immutable/Stream$Empty$.MODULE$:Lscala/collection/immutable/Stream$Empty$;
const #288 = Asciz	scala/collection/immutable/Stream$$anonfun$fill$1;
const #289 = class	#288;	//  scala/collection/immutable/Stream$$anonfun$fill$1
const #290 = Asciz	(ILscala/Function0;)V;
const #291 = NameAndType	#154:#290;//  "<init>":(ILscala/Function0;)V
const #292 = Method	#289.#291;	//  scala/collection/immutable/Stream$$anonfun$fill$1."<init>":(ILscala/Function0;)V
const #293 = InterfaceMethod	#276.#258;	//  scala/collection/IterableLike.head:()Ljava/lang/Object;
const #294 = Asciz	scala/collection/immutable/Stream$$anonfun$loop$4$2;
const #295 = class	#294;	//  scala/collection/immutable/Stream$$anonfun$loop$4$2
const #296 = Asciz	(Lscala/collection/immutable/Stream;Ljava/lang/Object;ILscala/collection/immutable/Stream;)V;
const #297 = NameAndType	#154:#296;//  "<init>":(Lscala/collection/immutable/Stream;Ljava/lang/Object;ILscala/collection/immutable/Stream;)V
const #298 = Method	#295.#297;	//  scala/collection/immutable/Stream$$anonfun$loop$4$2."<init>":(Lscala/collection/immutable/Stream;Ljava/lang/Object;ILscala/collection/immutable/Stream;)V
const #299 = Asciz	len$1;
const #300 = Asciz	I;
const #301 = Asciz	these$1;
const #302 = Asciz	elem$10;
const #303 = Asciz	Lscala/Function0;;
const #304 = Asciz	loop$3;
const #305 = Asciz	(Ljava/lang/String;Lscala/collection/immutable/Stream;Lscala/collection/mutable/StringBuilder;Ljava/lang/String;Ljava/lang/String;)V;
const #306 = Asciz	scala/collection/mutable/StringBuilder;
const #307 = class	#306;	//  scala/collection/mutable/StringBuilder
const #308 = Asciz	append;
const #309 = Asciz	(Ljava/lang/String;)Lscala/collection/mutable/StringBuilder;;
const #310 = NameAndType	#308:#309;//  append:(Ljava/lang/String;)Lscala/collection/mutable/StringBuilder;
const #311 = Method	#307.#310;	//  scala/collection/mutable/StringBuilder.append:(Ljava/lang/String;)Lscala/collection/mutable/StringBuilder;
const #312 = Asciz	java/lang/String;
const #313 = class	#312;	//  java/lang/String
const #314 = Asciz	valueOf;
const #315 = Asciz	(Ljava/lang/Object;)Ljava/lang/String;;
const #316 = NameAndType	#314:#315;//  valueOf:(Ljava/lang/Object;)Ljava/lang/String;
const #317 = Method	#313.#316;	//  java/lang/String.valueOf:(Ljava/lang/Object;)Ljava/lang/String;
const #318 = Asciz	tailDefined;
const #319 = NameAndType	#318:#242;//  tailDefined:()Z
const #320 = Method	#250.#319;	//  scala/collection/immutable/Stream.tailDefined:()Z
const #321 = Asciz	?;
const #322 = String	#321;	//  ?
const #323 = Asciz	pre;
const #324 = Asciz	Ljava/lang/String;;
const #325 = Asciz	these;
const #326 = Asciz	loop$2;
const #327 = Asciz	(Lscala/collection/immutable/Stream;)Z;
const #328 = Asciz	s;
const #329 = Asciz	loop$1;
const #330 = Asciz	(Lscala/collection/immutable/Stream;Ljava/lang/String;Ljava/lang/String;)V;
const #331 = Asciz	scala/Console$;
const #332 = class	#331;	//  scala/Console$
const #333 = Asciz	Lscala/Console$;;
const #334 = NameAndType	#8:#333;//  MODULE$:Lscala/Console$;
const #335 = Field	#332.#334;	//  scala/Console$.MODULE$:Lscala/Console$;
const #336 = Asciz	print;
const #337 = Asciz	(Ljava/lang/Object;)V;
const #338 = NameAndType	#336:#337;//  print:(Ljava/lang/Object;)V
const #339 = Method	#332.#338;	//  scala/Console$.print:(Ljava/lang/Object;)V
const #340 = String	#85;	//  empty
const #341 = Asciz	start;
const #342 = Asciz	filter;
const #343 = Asciz	(Lscala/Function1;)Ljava/lang/Object;;
const #344 = NameAndType	#342:#252;//  filter:(Lscala/Function1;)Lscala/collection/immutable/Stream;
const #345 = Method	#250.#344;	//  scala/collection/immutable/Stream.filter:(Lscala/Function1;)Lscala/collection/immutable/Stream;
const #346 = Asciz	p;
const #347 = Asciz	Lscala/Function1;;
const #348 = Asciz	take;
const #349 = Asciz	(I)Lscala/collection/LinearSeqLike;;
const #350 = NameAndType	#348:#59;//  take:(I)Lscala/collection/immutable/Stream;
const #351 = Method	#250.#350;	//  scala/collection/immutable/Stream.take:(I)Lscala/collection/immutable/Stream;
const #352 = Asciz	n;
const #353 = Asciz	(I)Ljava/lang/Object;;
const #354 = Asciz	slice;
const #355 = Asciz	(II)Lscala/collection/LinearSeqLike;;
const #356 = NameAndType	#354:#63;//  slice:(II)Lscala/collection/immutable/Stream;
const #357 = Method	#250.#356;	//  scala/collection/immutable/Stream.slice:(II)Lscala/collection/immutable/Stream;
const #358 = Asciz	until;
const #359 = Asciz	(II)Ljava/lang/Object;;
const #360 = Asciz	init;
const #361 = NameAndType	#360:#86;//  init:()Lscala/collection/immutable/Stream;
const #362 = Method	#250.#361;	//  scala/collection/immutable/Stream.init:()Lscala/collection/immutable/Stream;
const #363 = Asciz	takeRight;
const #364 = NameAndType	#363:#59;//  takeRight:(I)Lscala/collection/immutable/Stream;
const #365 = Method	#250.#364;	//  scala/collection/immutable/Stream.takeRight:(I)Lscala/collection/immutable/Stream;
const #366 = Asciz	takeWhile;
const #367 = Asciz	(Lscala/Function1;)Lscala/collection/LinearSeqLike;;
const #368 = NameAndType	#366:#252;//  takeWhile:(Lscala/Function1;)Lscala/collection/immutable/Stream;
const #369 = Method	#250.#368;	//  scala/collection/immutable/Stream.takeWhile:(Lscala/Function1;)Lscala/collection/immutable/Stream;
const #370 = Asciz	dropWhile;
const #371 = NameAndType	#370:#252;//  dropWhile:(Lscala/Function1;)Lscala/collection/immutable/Stream;
const #372 = Method	#250.#371;	//  scala/collection/immutable/Stream.dropWhile:(Lscala/Function1;)Lscala/collection/immutable/Stream;
const #373 = Asciz	removeDuplicates;
const #374 = NameAndType	#373:#86;//  removeDuplicates:()Lscala/collection/immutable/Stream;
const #375 = Method	#250.#374;	//  scala/collection/immutable/Stream.removeDuplicates:()Lscala/collection/immutable/Stream;
const #376 = Asciz	reverse;
const #377 = NameAndType	#376:#86;//  reverse:()Lscala/collection/immutable/Stream;
const #378 = Method	#250.#377;	//  scala/collection/immutable/Stream.reverse:()Lscala/collection/immutable/Stream;
const #379 = Asciz	(Lscala/Function1;)Lscala/collection/Traversable;;
const #380 = Asciz	asTraversable;
const #381 = Asciz	thisCollection;
const #382 = Asciz	()Lscala/collection/Seq;;
const #383 = Asciz	scala/collection/LinearSeqLike;
const #384 = class	#383;	//  scala/collection/LinearSeqLike
const #385 = Asciz	()Lscala/collection/LinearSeq;;
const #386 = NameAndType	#381:#385;//  thisCollection:()Lscala/collection/LinearSeq;
const #387 = InterfaceMethod	#384.#386;	//  scala/collection/LinearSeqLike.thisCollection:()Lscala/collection/LinearSeq;
const #388 = Asciz	()Lscala/collection/Iterable;;
const #389 = Asciz	toCollection;
const #390 = Asciz	(Ljava/lang/Object;)Lscala/collection/Seq;;
const #391 = Asciz	(Lscala/collection/LinearSeqLike;)Lscala/collection/LinearSeq;;
const #392 = NameAndType	#389:#391;//  toCollection:(Lscala/collection/LinearSeqLike;)Lscala/collection/LinearSeq;
const #393 = InterfaceMethod	#384.#392;	//  scala/collection/LinearSeqLike.toCollection:(Lscala/collection/LinearSeqLike;)Lscala/collection/LinearSeq;
const #394 = Asciz	repr;
const #395 = Asciz	Ljava/lang/Object;;
const #396 = Asciz	(Ljava/lang/Object;)Lscala/collection/Iterable;;
const #397 = Asciz	(Ljava/lang/Object;)Lscala/collection/Traversable;;
const #398 = Asciz	apply;
const #399 = Asciz	(Ljava/lang/Object;)Ljava/lang/Object;;
const #400 = Asciz	scala/runtime/BoxesRunTime;
const #401 = class	#400;	//  scala/runtime/BoxesRunTime
const #402 = Asciz	unboxToInt;
const #403 = Asciz	(Ljava/lang/Object;)I;
const #404 = NameAndType	#402:#403;//  unboxToInt:(Ljava/lang/Object;)I
const #405 = Method	#401.#404;	//  scala/runtime/BoxesRunTime.unboxToInt:(Ljava/lang/Object;)I
const #406 = NameAndType	#398:#353;//  apply:(I)Ljava/lang/Object;
const #407 = InterfaceMethod	#384.#406;	//  scala/collection/LinearSeqLike.apply:(I)Ljava/lang/Object;
const #408 = Asciz	v1;
const #409 = Asciz	drop;
const #410 = NameAndType	#409:#349;//  drop:(I)Lscala/collection/LinearSeqLike;
const #411 = InterfaceMethod	#384.#410;	//  scala/collection/LinearSeqLike.drop:(I)Lscala/collection/LinearSeqLike;
const #412 = Asciz	dropRight;
const #413 = NameAndType	#412:#349;//  dropRight:(I)Lscala/collection/LinearSeqLike;
const #414 = InterfaceMethod	#384.#413;	//  scala/collection/LinearSeqLike.dropRight:(I)Lscala/collection/LinearSeqLike;
const #415 = Asciz	isDefinedAt;
const #416 = Asciz	(Ljava/lang/Object;)Z;
const #417 = Asciz	(I)Z;
const #418 = NameAndType	#415:#417;//  isDefinedAt:(I)Z
const #419 = InterfaceMethod	#384.#418;	//  scala/collection/LinearSeqLike.isDefinedAt:(I)Z
const #420 = Asciz	x;
const #421 = Asciz	view;
const #422 = Asciz	(II)Lscala/collection/IterableView;;
const #423 = Asciz	scala/collection/SeqLike;
const #424 = class	#423;	//  scala/collection/SeqLike
const #425 = Asciz	(II)Lscala/collection/SeqView;;
const #426 = NameAndType	#421:#425;//  view:(II)Lscala/collection/SeqView;
const #427 = InterfaceMethod	#424.#426;	//  scala/collection/SeqLike.view:(II)Lscala/collection/SeqView;
const #428 = Asciz	(II)Lscala/collection/TraversableView;;
const #429 = Asciz	andThen;
const #430 = Asciz	(Lscala/Function1;)Lscala/Function1;;
const #431 = Asciz	scala/PartialFunction;
const #432 = class	#431;	//  scala/PartialFunction
const #433 = Asciz	(Lscala/Function1;)Lscala/PartialFunction;;
const #434 = NameAndType	#429:#433;//  andThen:(Lscala/Function1;)Lscala/PartialFunction;
const #435 = InterfaceMethod	#432.#434;	//  scala/PartialFunction.andThen:(Lscala/Function1;)Lscala/PartialFunction;
const #436 = Asciz	g;
const #437 = Asciz	()Lscala/collection/LinearSeqLike;;
const #438 = Asciz	stringPrefix;
const #439 = Asciz	()Ljava/lang/String;;
const #440 = Asciz	Stream;
const #441 = String	#440;	//  Stream
const #442 = Asciz	scala/Function1;
const #443 = class	#442;	//  scala/Function1
const #444 = NameAndType	#398:#399;//  apply:(Ljava/lang/Object;)Ljava/lang/Object;
const #445 = InterfaceMethod	#443.#444;	//  scala/Function1.apply:(Ljava/lang/Object;)Ljava/lang/Object;
const #446 = Asciz	scala/collection/Traversable;
const #447 = class	#446;	//  scala/collection/Traversable
const #448 = NameAndType	#237:#238;//  flatten1$1:(Lscala/collection/Traversable;Lscala/Function1;)Lscala/collection/immutable/Stream;
const #449 = Method	#250.#448;	//  scala/collection/immutable/Stream.flatten1$1:(Lscala/collection/Traversable;Lscala/Function1;)Lscala/collection/immutable/Stream;
const #450 = Asciz	asTraversable$1;
const #451 = Asciz	<B:Ljava/lang/Object;>(Lscala/Function1<TA;Lscala/collection/Traversable<TB;>;>;)Lscala/collection/immutable/Stream<TB;>;;
const #452 = Asciz	scala/runtime/ObjectRef;
const #453 = class	#452;	//  scala/runtime/ObjectRef
const #454 = NameAndType	#154:#337;//  "<init>":(Ljava/lang/Object;)V
const #455 = Method	#453.#454;	//  scala/runtime/ObjectRef."<init>":(Ljava/lang/Object;)V
const #456 = Asciz	elem;
const #457 = NameAndType	#456:#395;//  elem:Ljava/lang/Object;
const #458 = Field	#453.#457;	//  scala/runtime/ObjectRef.elem:Ljava/lang/Object;
const #459 = Asciz	scala/collection/immutable/Stream$$anonfun$2;
const #460 = class	#459;	//  scala/collection/immutable/Stream$$anonfun$2
const #461 = Asciz	(Lscala/collection/immutable/Stream;Lscala/runtime/ObjectRef;)V;
const #462 = NameAndType	#154:#461;//  "<init>":(Lscala/collection/immutable/Stream;Lscala/runtime/ObjectRef;)V
const #463 = Method	#460.#462;	//  scala/collection/immutable/Stream$$anonfun$2."<init>":(Lscala/collection/immutable/Stream;Lscala/runtime/ObjectRef;)V
const #464 = Asciz	scala/collection/immutable/Stream$ConsWrapper;
const #465 = class	#464;	//  scala/collection/immutable/Stream$ConsWrapper
const #466 = Asciz	(Lscala/Function0;)V;
const #467 = NameAndType	#154:#466;//  "<init>":(Lscala/Function0;)V
const #468 = Method	#465.#467;	//  scala/collection/immutable/Stream$ConsWrapper."<init>":(Lscala/Function0;)V
const #469 = Asciz	$hash$colon$colon;
const #470 = NameAndType	#469:#17;//  $hash$colon$colon:(Ljava/lang/Object;)Lscala/collection/immutable/Stream;
const #471 = Method	#465.#470;	//  scala/collection/immutable/Stream$ConsWrapper.$hash$colon$colon:(Ljava/lang/Object;)Lscala/collection/immutable/Stream;
const #472 = Asciz	result$1;
const #473 = Asciz	Lscala/runtime/ObjectRef;;
const #474 = Asciz	r;
const #475 = Asciz	()Lscala/collection/immutable/Stream<TA;>;;
const #476 = Asciz	padTo;
const #477 = Asciz	(ILjava/lang/Object;Lscala/collection/generic/CanBuildFrom;)Ljava/lang/Object;;
const #478 = NameAndType	#273:#274;//  loop$4:(ILscala/collection/immutable/Stream;Ljava/lang/Object;)Lscala/collection/immutable/Stream;
const #479 = Method	#250.#478;	//  scala/collection/immutable/Stream.loop$4:(ILscala/collection/immutable/Stream;Ljava/lang/Object;)Lscala/collection/immutable/Stream;
const #480 = Asciz	len;
const #481 = Asciz	elem$2;
const #482 = Asciz	bf;
const #483 = Asciz	Lscala/collection/generic/CanBuildFrom;;
const #484 = Asciz	<B:Ljava/lang/Object;That:Ljava/lang/Object;>(ITB;Lscala/collection/generic/CanBuildFrom<Lscala/collection/immutable/Stream<TA;>;TB;TThat;>;)TThat;;
const #485 = Asciz	scala/collection/immutable/Stream$$anonfun$removeDuplicates$1;
const #486 = class	#485;	//  scala/collection/immutable/Stream$$anonfun$removeDuplicates$1
const #487 = Asciz	(Lscala/collection/immutable/Stream;)V;
const #488 = NameAndType	#154:#487;//  "<init>":(Lscala/collection/immutable/Stream;)V
const #489 = Method	#486.#488;	//  scala/collection/immutable/Stream$$anonfun$removeDuplicates$1."<init>":(Lscala/collection/immutable/Stream;)V
const #490 = Asciz	unboxToBoolean;
const #491 = NameAndType	#490:#416;//  unboxToBoolean:(Ljava/lang/Object;)Z
const #492 = Method	#401.#491;	//  scala/runtime/BoxesRunTime.unboxToBoolean:(Ljava/lang/Object;)Z
const #493 = Asciz	(Lscala/Function1<TA;Ljava/lang/Boolean;>;)Lscala/collection/immutable/Stream<TA;>;;
const #494 = Asciz	scala/collection/immutable/Stream$$anonfun$takeWhile$1;
const #495 = class	#494;	//  scala/collection/immutable/Stream$$anonfun$takeWhile$1
const #496 = Asciz	(Lscala/collection/immutable/Stream;Lscala/Function1;)V;
const #497 = NameAndType	#154:#496;//  "<init>":(Lscala/collection/immutable/Stream;Lscala/Function1;)V
const #498 = Method	#495.#497;	//  scala/collection/immutable/Stream$$anonfun$takeWhile$1."<init>":(Lscala/collection/immutable/Stream;Lscala/Function1;)V
const #499 = Asciz	p$1;
const #500 = Asciz	lead;
const #501 = Asciz	(I)Lscala/collection/immutable/Stream<TA;>;;
const #502 = Asciz	(Lscala/collection/TraversableLike;)Ljava/lang/Object;;
const #503 = NameAndType	#360:#502;//  init:(Lscala/collection/TraversableLike;)Ljava/lang/Object;
const #504 = Method	#162.#503;	//  scala/collection/TraversableLike$class.init:(Lscala/collection/TraversableLike;)Ljava/lang/Object;
const #505 = Asciz	scala/collection/immutable/Stream$$anonfun$init$1;
const #506 = class	#505;	//  scala/collection/immutable/Stream$$anonfun$init$1
const #507 = Method	#506.#488;	//  scala/collection/immutable/Stream$$anonfun$init$1."<init>":(Lscala/collection/immutable/Stream;)V
const #508 = Asciz	end;
const #509 = Asciz	(II)Lscala/collection/immutable/Stream<TA;>;;
const #510 = Asciz	scala/collection/immutable/Stream$$anonfun$take$1;
const #511 = class	#510;	//  scala/collection/immutable/Stream$$anonfun$take$1
const #512 = Asciz	(Lscala/collection/immutable/Stream;I)V;
const #513 = NameAndType	#154:#512;//  "<init>":(Lscala/collection/immutable/Stream;I)V
const #514 = Method	#511.#513;	//  scala/collection/immutable/Stream$$anonfun$take$1."<init>":(Lscala/collection/immutable/Stream;I)V
const #515 = Asciz	n$3;
const #516 = Asciz	toString;
const #517 = Method	#307.#159;	//  scala/collection/mutable/StringBuilder."<init>":()V
const #518 = NameAndType	#438:#439;//  stringPrefix:()Ljava/lang/String;
const #519 = Method	#250.#518;	//  scala/collection/immutable/Stream.stringPrefix:()Ljava/lang/String;
const #520 = Asciz	(Ljava/lang/Object;)Lscala/collection/mutable/StringBuilder;;
const #521 = NameAndType	#308:#520;//  append:(Ljava/lang/Object;)Lscala/collection/mutable/StringBuilder;
const #522 = Method	#307.#521;	//  scala/collection/mutable/StringBuilder.append:(Ljava/lang/Object;)Lscala/collection/mutable/StringBuilder;
const #523 = Asciz	(;
const #524 = String	#523;	//  (
const #525 = NameAndType	#516:#439;//  toString:()Ljava/lang/String;
const #526 = Method	#307.#525;	//  scala/collection/mutable/StringBuilder.toString:()Ljava/lang/String;
const #527 = Asciz	, ;
const #528 = String	#527;	//  , 
const #529 = Asciz	);
const #530 = String	#529;	//  )
const #531 = Asciz	mkString;
const #532 = Asciz	(Lscala/collection/TraversableLike;Ljava/lang/String;Ljava/lang/String;Ljava/lang/String;)Ljava/lang/String;;
const #533 = NameAndType	#531:#532;//  mkString:(Lscala/collection/TraversableLike;Ljava/lang/String;Ljava/lang/String;Ljava/lang/String;)Ljava/lang/String;
const #534 = Method	#162.#533;	//  scala/collection/TraversableLike$class.mkString:(Lscala/collection/TraversableLike;Ljava/lang/String;Ljava/lang/String;Ljava/lang/String;)Ljava/lang/String;
const #535 = Asciz	force;
const #536 = NameAndType	#535:#86;//  force:()Lscala/collection/immutable/Stream;
const #537 = Method	#250.#536;	//  scala/collection/immutable/Stream.force:()Lscala/collection/immutable/Stream;
const #538 = Asciz	(Lscala/collection/TraversableLike;)Ljava/lang/String;;
const #539 = NameAndType	#531:#538;//  mkString:(Lscala/collection/TraversableLike;)Ljava/lang/String;
const #540 = Method	#162.#539;	//  scala/collection/TraversableLike$class.mkString:(Lscala/collection/TraversableLike;)Ljava/lang/String;
const #541 = Asciz	(Ljava/lang/String;)Ljava/lang/String;;
const #542 = Asciz	(Lscala/collection/TraversableLike;Ljava/lang/String;)Ljava/lang/String;;
const #543 = NameAndType	#531:#542;//  mkString:(Lscala/collection/TraversableLike;Ljava/lang/String;)Ljava/lang/String;
const #544 = Method	#162.#543;	//  scala/collection/TraversableLike$class.mkString:(Lscala/collection/TraversableLike;Ljava/lang/String;)Ljava/lang/String;
const #545 = Asciz	sep;
const #546 = Asciz	(Ljava/lang/String;Ljava/lang/String;Ljava/lang/String;)Ljava/lang/String;;
const #547 = Asciz	addString;
const #548 = Asciz	(Lscala/collection/mutable/StringBuilder;Ljava/lang/String;Ljava/lang/String;Ljava/lang/String;)Lscala/collection/mutable/StringBuilder;;
const #549 = Asciz	;
const #550 = String	#549;	//  
const #551 = NameAndType	#304:#305;//  loop$3:(Ljava/lang/String;Lscala/collection/immutable/Stream;Lscala/collection/mutable/StringBuilder;Ljava/lang/String;Ljava/lang/String;)V
const #552 = Method	#250.#551;	//  scala/collection/immutable/Stream.loop$3:(Ljava/lang/String;Lscala/collection/immutable/Stream;Lscala/collection/mutable/StringBuilder;Ljava/lang/String;Ljava/lang/String;)V
const #553 = Asciz	b$1;
const #554 = Asciz	Lscala/collection/mutable/StringBuilder;;
const #555 = Asciz	sep$2;
const #556 = Asciz	end$2;
const #557 = Asciz	zipWithIndex;
const #558 = Asciz	(Lscala/collection/generic/CanBuildFrom;)Ljava/lang/Object;;
const #559 = Asciz	zip;
const #560 = Asciz	(Lscala/collection/Iterable;Lscala/collection/generic/CanBuildFrom;)Ljava/lang/Object;;
const #561 = NameAndType	#559:#560;//  zip:(Lscala/collection/Iterable;Lscala/collection/generic/CanBuildFrom;)Ljava/lang/Object;
const #562 = Method	#250.#561;	//  scala/collection/immutable/Stream.zip:(Lscala/collection/Iterable;Lscala/collection/generic/CanBuildFrom;)Ljava/lang/Object;
const #563 = Asciz	<A1:Ljava/lang/Object;That:Ljava/lang/Object;>(Lscala/collection/generic/CanBuildFrom<Lscala/collection/immutable/Stream<TA;>;Lscala/Tuple2<TA1;Ljava/lang/Integer;>;TThat;>;)TThat;;
const #564 = Asciz	scala/Tuple2;
const #565 = class	#564;	//  scala/Tuple2
const #566 = Asciz	(Ljava/lang/Object;Ljava/lang/Object;)V;
const #567 = NameAndType	#154:#566;//  "<init>":(Ljava/lang/Object;Ljava/lang/Object;)V
const #568 = Method	#565.#567;	//  scala/Tuple2."<init>":(Ljava/lang/Object;Ljava/lang/Object;)V
const #569 = Asciz	scala/collection/immutable/Stream$$anonfun$zip$1;
const #570 = class	#569;	//  scala/collection/immutable/Stream$$anonfun$zip$1
const #571 = Asciz	(Lscala/collection/immutable/Stream;Lscala/collection/Iterable;Lscala/collection/generic/CanBuildFrom;)V;
const #572 = NameAndType	#154:#571;//  "<init>":(Lscala/collection/immutable/Stream;Lscala/collection/Iterable;Lscala/collection/generic/CanBuildFrom;)V
const #573 = Method	#570.#572;	//  scala/collection/immutable/Stream$$anonfun$zip$1."<init>":(Lscala/collection/immutable/Stream;Lscala/collection/Iterable;Lscala/collection/generic/CanBuildFrom;)V
const #574 = Asciz	that$2;
const #575 = Asciz	Lscala/collection/Iterable;;
const #576 = Asciz	bf$3;
const #577 = Asciz	<A1:Ljava/lang/Object;B:Ljava/lang/Object;That:Ljava/lang/Object;>(Lscala/collection/Iterable<TB;>;Lscala/collection/generic/CanBuildFrom<Lscala/collection/immutable/Stream<TA;>;Lscala/Tuple2<TA1;TB;>;TThat;>;)TThat;;
const #578 = Asciz	partition;
const #579 = Asciz	(Lscala/Function1;)Lscala/Tuple2;;
const #580 = Asciz	scala/collection/immutable/Stream$$anonfun$partition$1;
const #581 = class	#580;	//  scala/collection/immutable/Stream$$anonfun$partition$1
const #582 = Method	#581.#497;	//  scala/collection/immutable/Stream$$anonfun$partition$1."<init>":(Lscala/collection/immutable/Stream;Lscala/Function1;)V
const #583 = Asciz	scala/collection/immutable/Stream$$anonfun$1;
const #584 = class	#583;	//  scala/collection/immutable/Stream$$anonfun$1
const #585 = Method	#584.#497;	//  scala/collection/immutable/Stream$$anonfun$1."<init>":(Lscala/collection/immutable/Stream;Lscala/Function1;)V
const #586 = Asciz	scala/collection/immutable/Stream$$anonfun$filter$1;
const #587 = class	#586;	//  scala/collection/immutable/Stream$$anonfun$filter$1
const #588 = Asciz	(Lscala/collection/immutable/Stream;Lscala/Function1;Lscala/runtime/ObjectRef;)V;
const #589 = NameAndType	#154:#588;//  "<init>":(Lscala/collection/immutable/Stream;Lscala/Function1;Lscala/runtime/ObjectRef;)V
const #590 = Method	#587.#589;	//  scala/collection/immutable/Stream$$anonfun$filter$1."<init>":(Lscala/collection/immutable/Stream;Lscala/Function1;Lscala/runtime/ObjectRef;)V
const #591 = Asciz	scala/collection/immutable/Stream$$anonfun$partition$2;
const #592 = class	#591;	//  scala/collection/immutable/Stream$$anonfun$partition$2
const #593 = Method	#592.#497;	//  scala/collection/immutable/Stream$$anonfun$partition$2."<init>":(Lscala/collection/immutable/Stream;Lscala/Function1;)V
const #594 = Asciz	filterNot;
const #595 = NameAndType	#594:#343;//  filterNot:(Lscala/Function1;)Ljava/lang/Object;
const #596 = InterfaceMethod	#240.#595;	//  scala/collection/TraversableLike.filterNot:(Lscala/Function1;)Ljava/lang/Object;
const #597 = Asciz	p$2;
const #598 = Asciz	p$30;
const #599 = Asciz	rest$20;
const #600 = Asciz	(Lscala/Function1<TA;Ljava/lang/Boolean;>;)Lscala/Tuple2<Lscala/collection/immutable/Stream<TA;>;Lscala/collection/immutable/Stream<TA;>;>;;
const #601 = Asciz	foldLeft;
const #602 = Asciz	(Ljava/lang/Object;Lscala/Function2;)Ljava/lang/Object;;
const #603 = Asciz	scala/Function2;
const #604 = class	#603;	//  scala/Function2
const #605 = Asciz	(Ljava/lang/Object;Ljava/lang/Object;)Ljava/lang/Object;;
const #606 = NameAndType	#398:#605;//  apply:(Ljava/lang/Object;Ljava/lang/Object;)Ljava/lang/Object;
const #607 = InterfaceMethod	#604.#606;	//  scala/Function2.apply:(Ljava/lang/Object;Ljava/lang/Object;)Ljava/lang/Object;
const #608 = Asciz	z;
const #609 = Asciz	op;
const #610 = Asciz	Lscala/Function2;;
const #611 = Asciz	<B:Ljava/lang/Object;>(TB;Lscala/Function2<TB;TA;TB;>;)TB;;
const #612 = Asciz	foreach;
const #613 = Asciz	f;
const #614 = Asciz	<B:Ljava/lang/Object;>(Lscala/Function1<TA;TB;>;)V;
const #615 = Asciz	p$3;
const #616 = Asciz	rest$2;
const #617 = Asciz	flatMap;
const #618 = Asciz	(Lscala/Function1;Lscala/collection/generic/CanBuildFrom;)Ljava/lang/Object;;
const #619 = Asciz	toStream;
const #620 = NameAndType	#619:#86;//  toStream:()Lscala/collection/immutable/Stream;
const #621 = InterfaceMethod	#240.#620;	//  scala/collection/TraversableLike.toStream:()Lscala/collection/immutable/Stream;
const #622 = Asciz	scala/collection/immutable/Stream$$anonfun$flatMap$1;
const #623 = class	#622;	//  scala/collection/immutable/Stream$$anonfun$flatMap$1
const #624 = Asciz	(Lscala/collection/immutable/Stream;Lscala/Function1;Lscala/collection/generic/CanBuildFrom;Lscala/runtime/ObjectRef;)V;
const #625 = NameAndType	#154:#624;//  "<init>":(Lscala/collection/immutable/Stream;Lscala/Function1;Lscala/collection/generic/CanBuildFrom;Lscala/runtime/ObjectRef;)V
const #626 = Method	#623.#625;	//  scala/collection/immutable/Stream$$anonfun$flatMap$1."<init>":(Lscala/collection/immutable/Stream;Lscala/Function1;Lscala/collection/generic/CanBuildFrom;Lscala/runtime/ObjectRef;)V
const #627 = NameAndType	#308:#54;//  append:(Lscala/Function0;)Lscala/collection/immutable/Stream;
const #628 = Method	#250.#627;	//  scala/collection/immutable/Stream.append:(Lscala/Function0;)Lscala/collection/immutable/Stream;
const #629 = Asciz	f$4;
const #630 = Asciz	bf$4;
const #631 = Asciz	prefix;
const #632 = Asciz	nonEmptyPrefix$1;
const #633 = Asciz	<B:Ljava/lang/Object;That:Ljava/lang/Object;>(Lscala/Function1<TA;Lscala/collection/Traversable<TB;>;>;Lscala/collection/generic/CanBuildFrom<Lscala/collection/immutable/Stream<TA;>;TB;TThat;>;)TThat;;
const #634 = Asciz	map;
const #635 = Asciz	scala/collection/immutable/Stream$$anonfun$map$1;
const #636 = class	#635;	//  scala/collection/immutable/Stream$$anonfun$map$1
const #637 = Asciz	(Lscala/collection/immutable/Stream;Lscala/Function1;Lscala/collection/generic/CanBuildFrom;)V;
const #638 = NameAndType	#154:#637;//  "<init>":(Lscala/collection/immutable/Stream;Lscala/Function1;Lscala/collection/generic/CanBuildFrom;)V
const #639 = Method	#636.#638;	//  scala/collection/immutable/Stream$$anonfun$map$1."<init>":(Lscala/collection/immutable/Stream;Lscala/Function1;Lscala/collection/generic/CanBuildFrom;)V
const #640 = Asciz	f$3;
const #641 = Asciz	bf$2;
const #642 = Asciz	<B:Ljava/lang/Object;That:Ljava/lang/Object;>(Lscala/Function1<TA;TB;>;Lscala/collection/generic/CanBuildFrom<Lscala/collection/immutable/Stream<TA;>;TB;TThat;>;)TThat;;
const #643 = Asciz	$plus$plus;
const #644 = Asciz	(Lscala/collection/Iterator;Lscala/collection/generic/CanBuildFrom;)Ljava/lang/Object;;
const #645 = Asciz	scala/collection/Iterator;
const #646 = class	#645;	//  scala/collection/Iterator
const #647 = InterfaceMethod	#646.#620;	//  scala/collection/Iterator.toStream:()Lscala/collection/immutable/Stream;
const #648 = Asciz	(Lscala/collection/Traversable;Lscala/collection/generic/CanBuildFrom;)Ljava/lang/Object;;
const #649 = NameAndType	#643:#648;//  $plus$plus:(Lscala/collection/Traversable;Lscala/collection/generic/CanBuildFrom;)Ljava/lang/Object;
const #650 = Method	#250.#649;	//  scala/collection/immutable/Stream.$plus$plus:(Lscala/collection/Traversable;Lscala/collection/generic/CanBuildFrom;)Ljava/lang/Object;
const #651 = Asciz	that;
const #652 = Asciz	Lscala/collection/Iterator;;
const #653 = Asciz	<B:Ljava/lang/Object;That:Ljava/lang/Object;>(Lscala/collection/Iterator<TB;>;Lscala/collection/generic/CanBuildFrom<Lscala/collection/immutable/Stream<TA;>;TB;TThat;>;)TThat;;
const #654 = Asciz	scala/collection/immutable/Stream$$anonfun$$plus$plus$1;
const #655 = class	#654;	//  scala/collection/immutable/Stream$$anonfun$$plus$plus$1
const #656 = Asciz	(Lscala/collection/immutable/Stream;Lscala/collection/Traversable;Lscala/collection/generic/CanBuildFrom;)V;
const #657 = NameAndType	#154:#656;//  "<init>":(Lscala/collection/immutable/Stream;Lscala/collection/Traversable;Lscala/collection/generic/CanBuildFrom;)V
const #658 = Method	#655.#657;	//  scala/collection/immutable/Stream$$anonfun$$plus$plus$1."<init>":(Lscala/collection/immutable/Stream;Lscala/collection/Traversable;Lscala/collection/generic/CanBuildFrom;)V
const #659 = Asciz	that$1;
const #660 = Asciz	bf$1;
const #661 = Asciz	<B:Ljava/lang/Object;That:Ljava/lang/Object;>(Lscala/collection/Traversable<TB;>;Lscala/collection/generic/CanBuildFrom<Lscala/collection/immutable/Stream<TA;>;TB;TThat;>;)TThat;;
const #662 = Asciz	hasDefiniteSize;
const #663 = NameAndType	#326:#327;//  loop$2:(Lscala/collection/immutable/Stream;)Z
const #664 = Method	#250.#663;	//  scala/collection/immutable/Stream.loop$2:(Lscala/collection/immutable/Stream;)Z
const #665 = Asciz	(Ljava/lang/String;)V;
const #666 = NameAndType	#329:#330;//  loop$1:(Lscala/collection/immutable/Stream;Ljava/lang/String;Ljava/lang/String;)V
const #667 = Method	#250.#666;	//  scala/collection/immutable/Stream.loop$1:(Lscala/collection/immutable/Stream;Ljava/lang/String;Ljava/lang/String;)V
const #668 = Asciz	sep$1;
const #669 = NameAndType	#336:#665;//  print:(Ljava/lang/String;)V
const #670 = Method	#250.#669;	//  scala/collection/immutable/Stream.print:(Ljava/lang/String;)V
const #671 = Asciz	scala/Function0;
const #672 = class	#671;	//  scala/Function0
const #673 = NameAndType	#398:#246;//  apply:()Ljava/lang/Object;
const #674 = InterfaceMethod	#672.#673;	//  scala/Function0.apply:()Ljava/lang/Object;
const #675 = Asciz	scala/collection/immutable/Stream$$anonfun$append$1;
const #676 = class	#675;	//  scala/collection/immutable/Stream$$anonfun$append$1
const #677 = Asciz	(Lscala/collection/immutable/Stream;Lscala/Function0;)V;
const #678 = NameAndType	#154:#677;//  "<init>":(Lscala/collection/immutable/Stream;Lscala/Function0;)V
const #679 = Method	#676.#678;	//  scala/collection/immutable/Stream$$anonfun$append$1."<init>":(Lscala/collection/immutable/Stream;Lscala/Function0;)V
const #680 = Asciz	rest$1;
const #681 = Asciz	<B:Ljava/lang/Object;>(Lscala/Function0<Lscala/collection/Traversable<TB;>;>;)Lscala/collection/immutable/Stream<TB;>;;
const #682 = Asciz	()TA;;
const #683 = Asciz	companion;
const #684 = Asciz	()Lscala/collection/generic/GenericCompanion;;
const #685 = Asciz	()Lscala/collection/generic/GenericCompanion<Lscala/collection/immutable/Stream;>;;
const #686 = Asciz	withFilter;
const #687 = Asciz	(Lscala/Function1;)Lscala/collection/TraversableLike$WithFilter;;
const #688 = Asciz	(Lscala/collection/TraversableLike;Lscala/Function1;)Lscala/collection/TraversableLike$WithFilter;;
const #689 = NameAndType	#686:#688;//  withFilter:(Lscala/collection/TraversableLike;Lscala/Function1;)Lscala/collection/TraversableLike$WithFilter;
const #690 = Method	#162.#689;	//  scala/collection/TraversableLike$class.withFilter:(Lscala/collection/TraversableLike;Lscala/Function1;)Lscala/collection/TraversableLike$WithFilter;
const #691 = Asciz	(Lscala/collection/mutable/StringBuilder;)Lscala/collection/mutable/StringBuilder;;
const #692 = Asciz	(Lscala/collection/TraversableLike;Lscala/collection/mutable/StringBuilder;)Lscala/collection/mutable/StringBuilder;;
const #693 = NameAndType	#547:#692;//  addString:(Lscala/collection/TraversableLike;Lscala/collection/mutable/StringBuilder;)Lscala/collection/mutable/StringBuilder;
const #694 = Method	#162.#693;	//  scala/collection/TraversableLike$class.addString:(Lscala/collection/TraversableLike;Lscala/collection/mutable/StringBuilder;)Lscala/collection/mutable/StringBuilder;
const #695 = Asciz	b;
const #696 = Asciz	(Lscala/collection/mutable/StringBuilder;Ljava/lang/String;)Lscala/collection/mutable/StringBuilder;;
const #697 = Asciz	(Lscala/collection/TraversableLike;Lscala/collection/mutable/StringBuilder;Ljava/lang/String;)Lscala/collection/mutable/StringBuilder;;
const #698 = NameAndType	#547:#697;//  addString:(Lscala/collection/TraversableLike;Lscala/collection/mutable/StringBuilder;Ljava/lang/String;)Lscala/collection/mutable/StringBuilder;
const #699 = Method	#162.#698;	//  scala/collection/TraversableLike$class.addString:(Lscala/collection/TraversableLike;Lscala/collection/mutable/StringBuilder;Ljava/lang/String;)Lscala/collection/mutable/StringBuilder;
const #700 = Asciz	toSet;
const #701 = Asciz	()Lscala/collection/immutable/Set;;
const #702 = Asciz	(Lscala/collection/TraversableLike;)Lscala/collection/immutable/Set;;
const #703 = NameAndType	#700:#702;//  toSet:(Lscala/collection/TraversableLike;)Lscala/collection/immutable/Set;
const #704 = Method	#162.#703;	//  scala/collection/TraversableLike$class.toSet:(Lscala/collection/TraversableLike;)Lscala/collection/immutable/Set;
const #705 = Asciz	toIndexedSeq;
const #706 = Asciz	()Lscala/collection/mutable/IndexedSeq;;
const #707 = Asciz	(Lscala/collection/TraversableLike;)Lscala/collection/mutable/IndexedSeq;;
const #708 = NameAndType	#705:#707;//  toIndexedSeq:(Lscala/collection/TraversableLike;)Lscala/collection/mutable/IndexedSeq;
const #709 = Method	#162.#708;	//  scala/collection/TraversableLike$class.toIndexedSeq:(Lscala/collection/TraversableLike;)Lscala/collection/mutable/IndexedSeq;
const #710 = Asciz	toList;
const #711 = Asciz	()Lscala/collection/immutable/List;;
const #712 = Asciz	(Lscala/collection/TraversableLike;)Lscala/collection/immutable/List;;
const #713 = NameAndType	#710:#712;//  toList:(Lscala/collection/TraversableLike;)Lscala/collection/immutable/List;
const #714 = Method	#162.#713;	//  scala/collection/TraversableLike$class.toList:(Lscala/collection/TraversableLike;)Lscala/collection/immutable/List;
const #715 = Asciz	toArray;
const #716 = Asciz	(Lscala/reflect/ClassManifest;)Ljava/lang/Object;;
const #717 = Asciz	(Lscala/collection/TraversableLike;Lscala/reflect/ClassManifest;)Ljava/lang/Object;;
const #718 = NameAndType	#715:#717;//  toArray:(Lscala/collection/TraversableLike;Lscala/reflect/ClassManifest;)Ljava/lang/Object;
const #719 = Method	#162.#718;	//  scala/collection/TraversableLike$class.toArray:(Lscala/collection/TraversableLike;Lscala/reflect/ClassManifest;)Ljava/lang/Object;
const #720 = Asciz	evidence$1;
const #721 = Asciz	Lscala/reflect/ClassManifest;;
const #722 = Asciz	copyToArray;
const #723 = Asciz	(Ljava/lang/Object;I)V;
const #724 = Asciz	(Lscala/collection/TraversableLike;Ljava/lang/Object;I)V;
const #725 = NameAndType	#722:#724;//  copyToArray:(Lscala/collection/TraversableLike;Ljava/lang/Object;I)V
const #726 = Method	#162.#725;	//  scala/collection/TraversableLike$class.copyToArray:(Lscala/collection/TraversableLike;Ljava/lang/Object;I)V
const #727 = Asciz	xs;
const #728 = Asciz	copyToBuffer;
const #729 = Asciz	(Lscala/collection/mutable/Buffer;)V;
const #730 = Asciz	(Lscala/collection/TraversableLike;Lscala/collection/mutable/Buffer;)V;
const #731 = NameAndType	#728:#730;//  copyToBuffer:(Lscala/collection/TraversableLike;Lscala/collection/mutable/Buffer;)V
const #732 = Method	#162.#731;	//  scala/collection/TraversableLike$class.copyToBuffer:(Lscala/collection/TraversableLike;Lscala/collection/mutable/Buffer;)V
const #733 = Asciz	dest;
const #734 = Asciz	Lscala/collection/mutable/Buffer;;
const #735 = Asciz	splitAt;
const #736 = Asciz	(I)Lscala/Tuple2;;
const #737 = Asciz	(Lscala/collection/TraversableLike;I)Lscala/Tuple2;;
const #738 = NameAndType	#735:#737;//  splitAt:(Lscala/collection/TraversableLike;I)Lscala/Tuple2;
const #739 = Method	#162.#738;	//  scala/collection/TraversableLike$class.splitAt:(Lscala/collection/TraversableLike;I)Lscala/Tuple2;
const #740 = Asciz	lastOption;
const #741 = Asciz	()Lscala/Option;;
const #742 = Asciz	(Lscala/collection/TraversableLike;)Lscala/Option;;
const #743 = NameAndType	#740:#742;//  lastOption:(Lscala/collection/TraversableLike;)Lscala/Option;
const #744 = Method	#162.#743;	//  scala/collection/TraversableLike$class.lastOption:(Lscala/collection/TraversableLike;)Lscala/Option;
const #745 = NameAndType	#245:#502;//  tail:(Lscala/collection/TraversableLike;)Ljava/lang/Object;
const #746 = Method	#162.#745;	//  scala/collection/TraversableLike$class.tail:(Lscala/collection/TraversableLike;)Ljava/lang/Object;
const #747 = Asciz	headOption;
const #748 = NameAndType	#747:#742;//  headOption:(Lscala/collection/TraversableLike;)Lscala/Option;
const #749 = Method	#162.#748;	//  scala/collection/TraversableLike$class.headOption:(Lscala/collection/TraversableLike;)Lscala/Option;
const #750 = Asciz	max;
const #751 = Asciz	(Lscala/math/Ordering;)Ljava/lang/Object;;
const #752 = Asciz	(Lscala/collection/TraversableLike;Lscala/math/Ordering;)Ljava/lang/Object;;
const #753 = NameAndType	#750:#752;//  max:(Lscala/collection/TraversableLike;Lscala/math/Ordering;)Ljava/lang/Object;
const #754 = Method	#162.#753;	//  scala/collection/TraversableLike$class.max:(Lscala/collection/TraversableLike;Lscala/math/Ordering;)Ljava/lang/Object;
const #755 = Asciz	cmp;
const #756 = Asciz	Lscala/math/Ordering;;
const #757 = Asciz	min;
const #758 = NameAndType	#757:#752;//  min:(Lscala/collection/TraversableLike;Lscala/math/Ordering;)Ljava/lang/Object;
const #759 = Method	#162.#758;	//  scala/collection/TraversableLike$class.min:(Lscala/collection/TraversableLike;Lscala/math/Ordering;)Ljava/lang/Object;
const #760 = Asciz	product;
const #761 = Asciz	(Lscala/math/Numeric;)Ljava/lang/Object;;
const #762 = Asciz	(Lscala/collection/TraversableLike;Lscala/math/Numeric;)Ljava/lang/Object;;
const #763 = NameAndType	#760:#762;//  product:(Lscala/collection/TraversableLike;Lscala/math/Numeric;)Ljava/lang/Object;
const #764 = Method	#162.#763;	//  scala/collection/TraversableLike$class.product:(Lscala/collection/TraversableLike;Lscala/math/Numeric;)Ljava/lang/Object;
const #765 = Asciz	num;
const #766 = Asciz	Lscala/math/Numeric;;
const #767 = Asciz	sum;
const #768 = NameAndType	#767:#762;//  sum:(Lscala/collection/TraversableLike;Lscala/math/Numeric;)Ljava/lang/Object;
const #769 = Method	#162.#768;	//  scala/collection/TraversableLike$class.sum:(Lscala/collection/TraversableLike;Lscala/math/Numeric;)Ljava/lang/Object;
const #770 = Asciz	reduceRightOption;
const #771 = Asciz	(Lscala/Function2;)Lscala/Option;;
const #772 = Asciz	(Lscala/collection/TraversableLike;Lscala/Function2;)Lscala/Option;;
const #773 = NameAndType	#770:#772;//  reduceRightOption:(Lscala/collection/TraversableLike;Lscala/Function2;)Lscala/Option;
const #774 = Method	#162.#773;	//  scala/collection/TraversableLike$class.reduceRightOption:(Lscala/collection/TraversableLike;Lscala/Function2;)Lscala/Option;
const #775 = Asciz	reduceLeftOption;
const #776 = NameAndType	#775:#772;//  reduceLeftOption:(Lscala/collection/TraversableLike;Lscala/Function2;)Lscala/Option;
const #777 = Method	#162.#776;	//  scala/collection/TraversableLike$class.reduceLeftOption:(Lscala/collection/TraversableLike;Lscala/Function2;)Lscala/Option;
const #778 = Asciz	$colon$bslash;
const #779 = Asciz	(Lscala/collection/TraversableLike;Ljava/lang/Object;Lscala/Function2;)Ljava/lang/Object;;
const #780 = NameAndType	#778:#779;//  $colon$bslash:(Lscala/collection/TraversableLike;Ljava/lang/Object;Lscala/Function2;)Ljava/lang/Object;
const #781 = Method	#162.#780;	//  scala/collection/TraversableLike$class.$colon$bslash:(Lscala/collection/TraversableLike;Ljava/lang/Object;Lscala/Function2;)Ljava/lang/Object;
const #782 = Asciz	$div$colon;
const #783 = NameAndType	#782:#779;//  $div$colon:(Lscala/collection/TraversableLike;Ljava/lang/Object;Lscala/Function2;)Ljava/lang/Object;
const #784 = Method	#162.#783;	//  scala/collection/TraversableLike$class.$div$colon:(Lscala/collection/TraversableLike;Ljava/lang/Object;Lscala/Function2;)Ljava/lang/Object;
const #785 = Asciz	groupBy;
const #786 = Asciz	(Lscala/Function1;)Lscala/collection/Map;;
const #787 = Asciz	(Lscala/collection/TraversableLike;Lscala/Function1;)Lscala/collection/Map;;
const #788 = NameAndType	#785:#787;//  groupBy:(Lscala/collection/TraversableLike;Lscala/Function1;)Lscala/collection/Map;
const #789 = Method	#162.#788;	//  scala/collection/TraversableLike$class.groupBy:(Lscala/collection/TraversableLike;Lscala/Function1;)Lscala/collection/Map;
const #790 = Asciz	partialMap;
const #791 = Asciz	(Lscala/PartialFunction;Lscala/collection/generic/CanBuildFrom;)Ljava/lang/Object;;
const #792 = Asciz	(Lscala/collection/TraversableLike;Lscala/PartialFunction;Lscala/collection/generic/CanBuildFrom;)Ljava/lang/Object;;
const #793 = NameAndType	#790:#792;//  partialMap:(Lscala/collection/TraversableLike;Lscala/PartialFunction;Lscala/collection/generic/CanBuildFrom;)Ljava/lang/Object;
const #794 = Method	#162.#793;	//  scala/collection/TraversableLike$class.partialMap:(Lscala/collection/TraversableLike;Lscala/PartialFunction;Lscala/collection/generic/CanBuildFrom;)Ljava/lang/Object;
const #795 = Asciz	pf;
const #796 = Asciz	Lscala/PartialFunction;;
const #797 = Asciz	(Lscala/collection/TraversableLike;Lscala/Function1;)Ljava/lang/Object;;
const #798 = NameAndType	#594:#797;//  filterNot:(Lscala/collection/TraversableLike;Lscala/Function1;)Ljava/lang/Object;
const #799 = Method	#162.#798;	//  scala/collection/TraversableLike$class.filterNot:(Lscala/collection/TraversableLike;Lscala/Function1;)Ljava/lang/Object;
const #800 = Asciz	nonEmpty;
const #801 = Asciz	(Lscala/collection/TraversableLike;)Z;
const #802 = NameAndType	#800:#801;//  nonEmpty:(Lscala/collection/TraversableLike;)Z
const #803 = Method	#162.#802;	//  scala/collection/TraversableLike$class.nonEmpty:(Lscala/collection/TraversableLike;)Z
const #804 = NameAndType	#394:#502;//  repr:(Lscala/collection/TraversableLike;)Ljava/lang/Object;
const #805 = Method	#162.#804;	//  scala/collection/TraversableLike$class.repr:(Lscala/collection/TraversableLike;)Ljava/lang/Object;
const #806 = Asciz	transpose;
const #807 = Asciz	(Lscala/collection/generic/GenericTraversableTemplate;Lscala/Function1;)Lscala/collection/Traversable;;
const #808 = NameAndType	#806:#807;//  transpose:(Lscala/collection/generic/GenericTraversableTemplate;Lscala/Function1;)Lscala/collection/Traversable;
const #809 = Method	#168.#808;	//  scala/collection/generic/GenericTraversableTemplate$class.transpose:(Lscala/collection/generic/GenericTraversableTemplate;Lscala/Function1;)Lscala/collection/Traversable;
const #810 = Asciz	unzip;
const #811 = Asciz	(Lscala/collection/generic/GenericTraversableTemplate;Lscala/Function1;)Lscala/Tuple2;;
const #812 = NameAndType	#810:#811;//  unzip:(Lscala/collection/generic/GenericTraversableTemplate;Lscala/Function1;)Lscala/Tuple2;
const #813 = Method	#168.#812;	//  scala/collection/generic/GenericTraversableTemplate$class.unzip:(Lscala/collection/generic/GenericTraversableTemplate;Lscala/Function1;)Lscala/Tuple2;
const #814 = Asciz	asPair;
const #815 = Asciz	genericBuilder;
const #816 = Asciz	()Lscala/collection/mutable/Builder;;
const #817 = Asciz	(Lscala/collection/generic/GenericTraversableTemplate;)Lscala/collection/mutable/Builder;;
const #818 = NameAndType	#815:#817;//  genericBuilder:(Lscala/collection/generic/GenericTraversableTemplate;)Lscala/collection/mutable/Builder;
const #819 = Method	#168.#818;	//  scala/collection/generic/GenericTraversableTemplate$class.genericBuilder:(Lscala/collection/generic/GenericTraversableTemplate;)Lscala/collection/mutable/Builder;
const #820 = Asciz	newBuilder;
const #821 = NameAndType	#820:#817;//  newBuilder:(Lscala/collection/generic/GenericTraversableTemplate;)Lscala/collection/mutable/Builder;
const #822 = Method	#168.#821;	//  scala/collection/generic/GenericTraversableTemplate$class.newBuilder:(Lscala/collection/generic/GenericTraversableTemplate;)Lscala/collection/mutable/Builder;
const #823 = Asciz	firstOption;
const #824 = Asciz	(Lscala/collection/IterableLike;)Lscala/Option;;
const #825 = NameAndType	#823:#824;//  firstOption:(Lscala/collection/IterableLike;)Lscala/Option;
const #826 = Method	#183.#825;	//  scala/collection/IterableLike$class.firstOption:(Lscala/collection/IterableLike;)Lscala/Option;
const #827 = Asciz	first;
const #828 = Asciz	(Lscala/collection/IterableLike;)Ljava/lang/Object;;
const #829 = NameAndType	#827:#828;//  first:(Lscala/collection/IterableLike;)Ljava/lang/Object;
const #830 = Method	#183.#829;	//  scala/collection/IterableLike$class.first:(Lscala/collection/IterableLike;)Ljava/lang/Object;
const #831 = Asciz	canEqual;
const #832 = Asciz	(Lscala/collection/IterableLike;Ljava/lang/Object;)Z;
const #833 = NameAndType	#831:#832;//  canEqual:(Lscala/collection/IterableLike;Ljava/lang/Object;)Z
const #834 = Method	#183.#833;	//  scala/collection/IterableLike$class.canEqual:(Lscala/collection/IterableLike;Ljava/lang/Object;)Z
const #835 = Asciz	zipAll;
const #836 = Asciz	(Lscala/collection/Iterable;Ljava/lang/Object;Ljava/lang/Object;Lscala/collection/generic/CanBuildFrom;)Ljava/lang/Object;;
const #837 = Asciz	(Lscala/collection/IterableLike;Lscala/collection/Iterable;Ljava/lang/Object;Ljava/lang/Object;Lscala/collection/generic/CanBuildFrom;)Ljava/lang/Object;;
const #838 = NameAndType	#835:#837;//  zipAll:(Lscala/collection/IterableLike;Lscala/collection/Iterable;Ljava/lang/Object;Ljava/lang/Object;Lscala/collection/generic/CanBuildFrom;)Ljava/lang/Object;
const #839 = Method	#183.#838;	//  scala/collection/IterableLike$class.zipAll:(Lscala/collection/IterableLike;Lscala/collection/Iterable;Ljava/lang/Object;Ljava/lang/Object;Lscala/collection/generic/CanBuildFrom;)Ljava/lang/Object;
const #840 = Asciz	thisElem;
const #841 = Asciz	thatElem;
const #842 = Asciz	(Ljava/lang/Object;II)V;
const #843 = Asciz	(Lscala/collection/IterableLike;Ljava/lang/Object;II)V;
const #844 = NameAndType	#722:#843;//  copyToArray:(Lscala/collection/IterableLike;Ljava/lang/Object;II)V
const #845 = Method	#183.#844;	//  scala/collection/IterableLike$class.copyToArray:(Lscala/collection/IterableLike;Ljava/lang/Object;II)V
const #846 = Asciz	toIterable;
const #847 = Asciz	(Lscala/collection/IterableLike;)Lscala/collection/Iterable;;
const #848 = NameAndType	#846:#847;//  toIterable:(Lscala/collection/IterableLike;)Lscala/collection/Iterable;
const #849 = Method	#183.#848;	//  scala/collection/IterableLike$class.toIterable:(Lscala/collection/IterableLike;)Lscala/collection/Iterable;
const #850 = Asciz	elements;
const #851 = Asciz	()Lscala/collection/Iterator;;
const #852 = Asciz	(Lscala/collection/IterableLike;)Lscala/collection/Iterator;;
const #853 = NameAndType	#850:#852;//  elements:(Lscala/collection/IterableLike;)Lscala/collection/Iterator;
const #854 = Method	#183.#853;	//  scala/collection/IterableLike$class.elements:(Lscala/collection/IterableLike;)Lscala/collection/Iterator;
const #855 = Asciz	compose;
const #856 = Asciz	(Lscala/Function1;Lscala/Function1;)Lscala/Function1;;
const #857 = NameAndType	#855:#856;//  compose:(Lscala/Function1;Lscala/Function1;)Lscala/Function1;
const #858 = Method	#198.#857;	//  scala/Function1$class.compose:(Lscala/Function1;Lscala/Function1;)Lscala/Function1;
const #859 = Asciz	(Lscala/PartialFunction;Lscala/Function1;)Lscala/PartialFunction;;
const #860 = NameAndType	#429:#859;//  andThen:(Lscala/PartialFunction;Lscala/Function1;)Lscala/PartialFunction;
const #861 = Method	#203.#860;	//  scala/PartialFunction$class.andThen:(Lscala/PartialFunction;Lscala/Function1;)Lscala/PartialFunction;
const #862 = Asciz	k;
const #863 = Asciz	orElse;
const #864 = Asciz	(Lscala/PartialFunction;)Lscala/PartialFunction;;
const #865 = Asciz	(Lscala/PartialFunction;Lscala/PartialFunction;)Lscala/PartialFunction;;
const #866 = NameAndType	#863:#865;//  orElse:(Lscala/PartialFunction;Lscala/PartialFunction;)Lscala/PartialFunction;
const #867 = Method	#203.#866;	//  scala/PartialFunction$class.orElse:(Lscala/PartialFunction;Lscala/PartialFunction;)Lscala/PartialFunction;
const #868 = Asciz	projection;
const #869 = Asciz	(Lscala/collection/SeqLike;)Ljava/lang/Object;;
const #870 = NameAndType	#868:#869;//  projection:(Lscala/collection/SeqLike;)Ljava/lang/Object;
const #871 = Method	#208.#870;	//  scala/collection/SeqLike$class.projection:(Lscala/collection/SeqLike;)Ljava/lang/Object;
const #872 = Asciz	containsSlice;
const #873 = Asciz	(Lscala/collection/Seq;)Z;
const #874 = Asciz	(Lscala/collection/SeqLike;Lscala/collection/Seq;)Z;
const #875 = NameAndType	#872:#874;//  containsSlice:(Lscala/collection/SeqLike;Lscala/collection/Seq;)Z
const #876 = Method	#208.#875;	//  scala/collection/SeqLike$class.containsSlice:(Lscala/collection/SeqLike;Lscala/collection/Seq;)Z
const #877 = Asciz	Lscala/collection/Seq;;
const #878 = Asciz	equalsWith;
const #879 = Asciz	(Lscala/collection/Seq;Lscala/Function2;)Z;
const #880 = Asciz	(Lscala/collection/SeqLike;Lscala/collection/Seq;Lscala/Function2;)Z;
const #881 = NameAndType	#878:#880;//  equalsWith:(Lscala/collection/SeqLike;Lscala/collection/Seq;Lscala/Function2;)Z
const #882 = Method	#208.#881;	//  scala/collection/SeqLike$class.equalsWith:(Lscala/collection/SeqLike;Lscala/collection/Seq;Lscala/Function2;)Z
const #883 = Asciz	findLastIndexOf;
const #884 = Asciz	(Lscala/Function1;)I;
const #885 = Asciz	(Lscala/collection/SeqLike;Lscala/Function1;)I;
const #886 = NameAndType	#883:#885;//  findLastIndexOf:(Lscala/collection/SeqLike;Lscala/Function1;)I
const #887 = Method	#208.#886;	//  scala/collection/SeqLike$class.findLastIndexOf:(Lscala/collection/SeqLike;Lscala/Function1;)I
const #888 = Asciz	equals;
const #889 = Asciz	(Lscala/collection/SeqLike;Ljava/lang/Object;)Z;
const #890 = NameAndType	#888:#889;//  equals:(Lscala/collection/SeqLike;Ljava/lang/Object;)Z
const #891 = Method	#208.#890;	//  scala/collection/SeqLike$class.equals:(Lscala/collection/SeqLike;Ljava/lang/Object;)Z
const #892 = Asciz	hashCode;
const #893 = Asciz	()I;
const #894 = Asciz	(Lscala/collection/SeqLike;)I;
const #895 = NameAndType	#892:#894;//  hashCode:(Lscala/collection/SeqLike;)I
const #896 = Method	#208.#895;	//  scala/collection/SeqLike$class.hashCode:(Lscala/collection/SeqLike;)I
const #897 = Asciz	(Lscala/collection/SeqLike;II)Lscala/collection/SeqView;;
const #898 = NameAndType	#421:#897;//  view:(Lscala/collection/SeqLike;II)Lscala/collection/SeqView;
const #899 = Method	#208.#898;	//  scala/collection/SeqLike$class.view:(Lscala/collection/SeqLike;II)Lscala/collection/SeqView;
const #900 = NameAndType	#421:#869;//  view:(Lscala/collection/SeqLike;)Ljava/lang/Object;
const #901 = Method	#208.#900;	//  scala/collection/SeqLike$class.view:(Lscala/collection/SeqLike;)Ljava/lang/Object;
const #902 = Asciz	indices;
const #903 = Asciz	()Lscala/collection/immutable/Range;;
const #904 = Asciz	(Lscala/collection/SeqLike;)Lscala/collection/immutable/Range;;
const #905 = NameAndType	#902:#904;//  indices:(Lscala/collection/SeqLike;)Lscala/collection/immutable/Range;
const #906 = Method	#208.#905;	//  scala/collection/SeqLike$class.indices:(Lscala/collection/SeqLike;)Lscala/collection/immutable/Range;
const #907 = Asciz	toSeq;
const #908 = Asciz	(Lscala/collection/SeqLike;)Lscala/collection/Seq;;
const #909 = NameAndType	#907:#908;//  toSeq:(Lscala/collection/SeqLike;)Lscala/collection/Seq;
const #910 = Method	#208.#909;	//  scala/collection/SeqLike$class.toSeq:(Lscala/collection/SeqLike;)Lscala/collection/Seq;
const #911 = Asciz	sortBy;
const #912 = Asciz	(Lscala/Function1;Lscala/math/Ordering;)Ljava/lang/Object;;
const #913 = Asciz	(Lscala/collection/SeqLike;Lscala/Function1;Lscala/math/Ordering;)Ljava/lang/Object;;
const #914 = NameAndType	#911:#913;//  sortBy:(Lscala/collection/SeqLike;Lscala/Function1;Lscala/math/Ordering;)Ljava/lang/Object;
const #915 = Method	#208.#914;	//  scala/collection/SeqLike$class.sortBy:(Lscala/collection/SeqLike;Lscala/Function1;Lscala/math/Ordering;)Ljava/lang/Object;
const #916 = Asciz	ord;
const #917 = Asciz	sortWith;
const #918 = Asciz	(Lscala/collection/SeqLike;Lscala/math/Ordering;)Ljava/lang/Object;;
const #919 = NameAndType	#917:#918;//  sortWith:(Lscala/collection/SeqLike;Lscala/math/Ordering;)Ljava/lang/Object;
const #920 = Method	#208.#919;	//  scala/collection/SeqLike$class.sortWith:(Lscala/collection/SeqLike;Lscala/math/Ordering;)Ljava/lang/Object;
const #921 = Asciz	(Lscala/Function2;)Ljava/lang/Object;;
const #922 = Asciz	(Lscala/collection/SeqLike;Lscala/Function2;)Ljava/lang/Object;;
const #923 = NameAndType	#917:#922;//  sortWith:(Lscala/collection/SeqLike;Lscala/Function2;)Ljava/lang/Object;
const #924 = Method	#208.#923;	//  scala/collection/SeqLike$class.sortWith:(Lscala/collection/SeqLike;Lscala/Function2;)Ljava/lang/Object;
const #925 = Asciz	lt;
const #926 = Asciz	$colon$plus;
const #927 = Asciz	(Ljava/lang/Object;Lscala/collection/generic/CanBuildFrom;)Ljava/lang/Object;;
const #928 = Asciz	(Lscala/collection/SeqLike;Ljava/lang/Object;Lscala/collection/generic/CanBuildFrom;)Ljava/lang/Object;;
const #929 = NameAndType	#926:#928;//  $colon$plus:(Lscala/collection/SeqLike;Ljava/lang/Object;Lscala/collection/generic/CanBuildFrom;)Ljava/lang/Object;
const #930 = Method	#208.#929;	//  scala/collection/SeqLike$class.$colon$plus:(Lscala/collection/SeqLike;Ljava/lang/Object;Lscala/collection/generic/CanBuildFrom;)Ljava/lang/Object;
const #931 = Asciz	$plus$colon;
const #932 = NameAndType	#931:#928;//  $plus$colon:(Lscala/collection/SeqLike;Ljava/lang/Object;Lscala/collection/generic/CanBuildFrom;)Ljava/lang/Object;
const #933 = Method	#208.#932;	//  scala/collection/SeqLike$class.$plus$colon:(Lscala/collection/SeqLike;Ljava/lang/Object;Lscala/collection/generic/CanBuildFrom;)Ljava/lang/Object;
const #934 = Asciz	updated;
const #935 = Asciz	(Lscala/collection/SeqLike;ILjava/lang/Object;Lscala/collection/generic/CanBuildFrom;)Ljava/lang/Object;;
const #936 = NameAndType	#934:#935;//  updated:(Lscala/collection/SeqLike;ILjava/lang/Object;Lscala/collection/generic/CanBuildFrom;)Ljava/lang/Object;
const #937 = Method	#208.#936;	//  scala/collection/SeqLike$class.updated:(Lscala/collection/SeqLike;ILjava/lang/Object;Lscala/collection/generic/CanBuildFrom;)Ljava/lang/Object;
const #938 = Asciz	index;
const #939 = Asciz	patch;
const #940 = Asciz	(ILscala/collection/Seq;ILscala/collection/generic/CanBuildFrom;)Ljava/lang/Object;;
const #941 = Asciz	(Lscala/collection/SeqLike;ILscala/collection/Seq;ILscala/collection/generic/CanBuildFrom;)Ljava/lang/Object;;
const #942 = NameAndType	#939:#941;//  patch:(Lscala/collection/SeqLike;ILscala/collection/Seq;ILscala/collection/generic/CanBuildFrom;)Ljava/lang/Object;
const #943 = Method	#208.#942;	//  scala/collection/SeqLike$class.patch:(Lscala/collection/SeqLike;ILscala/collection/Seq;ILscala/collection/generic/CanBuildFrom;)Ljava/lang/Object;
const #944 = Asciz	replaced;
const #945 = Asciz	intersect;
const #946 = Asciz	(Lscala/collection/Seq;)Ljava/lang/Object;;
const #947 = Asciz	(Lscala/collection/SeqLike;Lscala/collection/Seq;)Ljava/lang/Object;;
const #948 = NameAndType	#945:#947;//  intersect:(Lscala/collection/SeqLike;Lscala/collection/Seq;)Ljava/lang/Object;
const #949 = Method	#208.#948;	//  scala/collection/SeqLike$class.intersect:(Lscala/collection/SeqLike;Lscala/collection/Seq;)Ljava/lang/Object;
const #950 = Asciz	diff;
const #951 = NameAndType	#950:#947;//  diff:(Lscala/collection/SeqLike;Lscala/collection/Seq;)Ljava/lang/Object;
const #952 = Method	#208.#951;	//  scala/collection/SeqLike$class.diff:(Lscala/collection/SeqLike;Lscala/collection/Seq;)Ljava/lang/Object;
const #953 = Asciz	union;
const #954 = Asciz	(Lscala/collection/Seq;Lscala/collection/generic/CanBuildFrom;)Ljava/lang/Object;;
const #955 = Asciz	(Lscala/collection/SeqLike;Lscala/collection/Seq;Lscala/collection/generic/CanBuildFrom;)Ljava/lang/Object;;
const #956 = NameAndType	#953:#955;//  union:(Lscala/collection/SeqLike;Lscala/collection/Seq;Lscala/collection/generic/CanBuildFrom;)Ljava/lang/Object;
const #957 = Method	#208.#956;	//  scala/collection/SeqLike$class.union:(Lscala/collection/SeqLike;Lscala/collection/Seq;Lscala/collection/generic/CanBuildFrom;)Ljava/lang/Object;
const #958 = Asciz	contains;
const #959 = NameAndType	#958:#889;//  contains:(Lscala/collection/SeqLike;Ljava/lang/Object;)Z
const #960 = Method	#208.#959;	//  scala/collection/SeqLike$class.contains:(Lscala/collection/SeqLike;Ljava/lang/Object;)Z
const #961 = Asciz	lastIndexOfSlice;
const #962 = Asciz	(Lscala/collection/Seq;I)I;
const #963 = Asciz	(Lscala/collection/SeqLike;Lscala/collection/Seq;I)I;
const #964 = NameAndType	#961:#963;//  lastIndexOfSlice:(Lscala/collection/SeqLike;Lscala/collection/Seq;I)I
const #965 = Method	#208.#964;	//  scala/collection/SeqLike$class.lastIndexOfSlice:(Lscala/collection/SeqLike;Lscala/collection/Seq;I)I
const #966 = Asciz	fromIndex;
const #967 = Asciz	(Lscala/collection/Seq;)I;
const #968 = Asciz	(Lscala/collection/SeqLike;Lscala/collection/Seq;)I;
const #969 = NameAndType	#961:#968;//  lastIndexOfSlice:(Lscala/collection/SeqLike;Lscala/collection/Seq;)I
const #970 = Method	#208.#969;	//  scala/collection/SeqLike$class.lastIndexOfSlice:(Lscala/collection/SeqLike;Lscala/collection/Seq;)I
const #971 = Asciz	indexOfSlice;
const #972 = NameAndType	#971:#963;//  indexOfSlice:(Lscala/collection/SeqLike;Lscala/collection/Seq;I)I
const #973 = Method	#208.#972;	//  scala/collection/SeqLike$class.indexOfSlice:(Lscala/collection/SeqLike;Lscala/collection/Seq;I)I
const #974 = NameAndType	#971:#968;//  indexOfSlice:(Lscala/collection/SeqLike;Lscala/collection/Seq;)I
const #975 = Method	#208.#974;	//  scala/collection/SeqLike$class.indexOfSlice:(Lscala/collection/SeqLike;Lscala/collection/Seq;)I
const #976 = Asciz	endsWith;
const #977 = NameAndType	#976:#874;//  endsWith:(Lscala/collection/SeqLike;Lscala/collection/Seq;)Z
const #978 = Method	#208.#977;	//  scala/collection/SeqLike$class.endsWith:(Lscala/collection/SeqLike;Lscala/collection/Seq;)Z
const #979 = Asciz	startsWith;
const #980 = NameAndType	#979:#874;//  startsWith:(Lscala/collection/SeqLike;Lscala/collection/Seq;)Z
const #981 = Method	#208.#980;	//  scala/collection/SeqLike$class.startsWith:(Lscala/collection/SeqLike;Lscala/collection/Seq;)Z
const #982 = Asciz	(Lscala/collection/Seq;I)Z;
const #983 = Asciz	(Lscala/collection/SeqLike;Lscala/collection/Seq;I)Z;
const #984 = NameAndType	#979:#983;//  startsWith:(Lscala/collection/SeqLike;Lscala/collection/Seq;I)Z
const #985 = Method	#208.#984;	//  scala/collection/SeqLike$class.startsWith:(Lscala/collection/SeqLike;Lscala/collection/Seq;I)Z
const #986 = Asciz	offset;
const #987 = Asciz	reversedElements;
const #988 = Asciz	(Lscala/collection/SeqLike;)Lscala/collection/Iterator;;
const #989 = NameAndType	#987:#988;//  reversedElements:(Lscala/collection/SeqLike;)Lscala/collection/Iterator;
const #990 = Method	#208.#989;	//  scala/collection/SeqLike$class.reversedElements:(Lscala/collection/SeqLike;)Lscala/collection/Iterator;
const #991 = Asciz	reverseIterator;
const #992 = NameAndType	#991:#988;//  reverseIterator:(Lscala/collection/SeqLike;)Lscala/collection/Iterator;
const #993 = Method	#208.#992;	//  scala/collection/SeqLike$class.reverseIterator:(Lscala/collection/SeqLike;)Lscala/collection/Iterator;
const #994 = Asciz	reverseMap;
const #995 = Asciz	(Lscala/collection/SeqLike;Lscala/Function1;Lscala/collection/generic/CanBuildFrom;)Ljava/lang/Object;;
const #996 = NameAndType	#994:#995;//  reverseMap:(Lscala/collection/SeqLike;Lscala/Function1;Lscala/collection/generic/CanBuildFrom;)Ljava/lang/Object;
const #997 = Method	#208.#996;	//  scala/collection/SeqLike$class.reverseMap:(Lscala/collection/SeqLike;Lscala/Function1;Lscala/collection/generic/CanBuildFrom;)Ljava/lang/Object;
const #998 = Asciz	lastIndexWhere;
const #999 = NameAndType	#998:#885;//  lastIndexWhere:(Lscala/collection/SeqLike;Lscala/Function1;)I
const #1000 = Method	#208.#999;	//  scala/collection/SeqLike$class.lastIndexWhere:(Lscala/collection/SeqLike;Lscala/Function1;)I
const #1001 = Asciz	lastIndexOf;
const #1002 = Asciz	(Ljava/lang/Object;I)I;
const #1003 = Asciz	(Lscala/collection/SeqLike;Ljava/lang/Object;I)I;
const #1004 = NameAndType	#1001:#1003;//  lastIndexOf:(Lscala/collection/SeqLike;Ljava/lang/Object;I)I
const #1005 = Method	#208.#1004;	//  scala/collection/SeqLike$class.lastIndexOf:(Lscala/collection/SeqLike;Ljava/lang/Object;I)I
const #1006 = Asciz	(Lscala/collection/SeqLike;Ljava/lang/Object;)I;
const #1007 = NameAndType	#1001:#1006;//  lastIndexOf:(Lscala/collection/SeqLike;Ljava/lang/Object;)I
const #1008 = Method	#208.#1007;	//  scala/collection/SeqLike$class.lastIndexOf:(Lscala/collection/SeqLike;Ljava/lang/Object;)I
const #1009 = Asciz	indexOf;
const #1010 = NameAndType	#1009:#1003;//  indexOf:(Lscala/collection/SeqLike;Ljava/lang/Object;I)I
const #1011 = Method	#208.#1010;	//  scala/collection/SeqLike$class.indexOf:(Lscala/collection/SeqLike;Ljava/lang/Object;I)I
const #1012 = NameAndType	#1009:#1006;//  indexOf:(Lscala/collection/SeqLike;Ljava/lang/Object;)I
const #1013 = Method	#208.#1012;	//  scala/collection/SeqLike$class.indexOf:(Lscala/collection/SeqLike;Ljava/lang/Object;)I
const #1014 = Asciz	findIndexOf;
const #1015 = NameAndType	#1014:#885;//  findIndexOf:(Lscala/collection/SeqLike;Lscala/Function1;)I
const #1016 = Method	#208.#1015;	//  scala/collection/SeqLike$class.findIndexOf:(Lscala/collection/SeqLike;Lscala/Function1;)I
const #1017 = Asciz	indexWhere;
const #1018 = NameAndType	#1017:#885;//  indexWhere:(Lscala/collection/SeqLike;Lscala/Function1;)I
const #1019 = Method	#208.#1018;	//  scala/collection/SeqLike$class.indexWhere:(Lscala/collection/SeqLike;Lscala/Function1;)I
const #1020 = Asciz	prefixLength;
const #1021 = NameAndType	#1020:#885;//  prefixLength:(Lscala/collection/SeqLike;Lscala/Function1;)I
const #1022 = Method	#208.#1021;	//  scala/collection/SeqLike$class.prefixLength:(Lscala/collection/SeqLike;Lscala/Function1;)I
const #1023 = Asciz	size;
const #1024 = NameAndType	#1023:#894;//  size:(Lscala/collection/SeqLike;)I
const #1025 = Method	#208.#1024;	//  scala/collection/SeqLike$class.size:(Lscala/collection/SeqLike;)I
const #1026 = Asciz	(Lscala/Function1;I)I;
const #1027 = Asciz	(Lscala/collection/LinearSeqLike;Lscala/Function1;I)I;
const #1028 = NameAndType	#998:#1027;//  lastIndexWhere:(Lscala/collection/LinearSeqLike;Lscala/Function1;I)I
const #1029 = Method	#223.#1028;	//  scala/collection/LinearSeqLike$class.lastIndexWhere:(Lscala/collection/LinearSeqLike;Lscala/Function1;I)I
const #1030 = NameAndType	#1017:#1027;//  indexWhere:(Lscala/collection/LinearSeqLike;Lscala/Function1;I)I
const #1031 = Method	#223.#1030;	//  scala/collection/LinearSeqLike$class.indexWhere:(Lscala/collection/LinearSeqLike;Lscala/Function1;I)I
const #1032 = Asciz	segmentLength;
const #1033 = NameAndType	#1032:#1027;//  segmentLength:(Lscala/collection/LinearSeqLike;Lscala/Function1;I)I
const #1034 = Method	#223.#1033;	//  scala/collection/LinearSeqLike$class.segmentLength:(Lscala/collection/LinearSeqLike;Lscala/Function1;I)I
const #1035 = Asciz	(Lscala/collection/LinearSeqLike;I)Z;
const #1036 = NameAndType	#415:#1035;//  isDefinedAt:(Lscala/collection/LinearSeqLike;I)Z
const #1037 = Method	#223.#1036;	//  scala/collection/LinearSeqLike$class.isDefinedAt:(Lscala/collection/LinearSeqLike;I)Z
const #1038 = Asciz	lengthCompare;
const #1039 = Asciz	(I)I;
const #1040 = Asciz	(Lscala/collection/LinearSeqLike;I)I;
const #1041 = NameAndType	#1038:#1040;//  lengthCompare:(Lscala/collection/LinearSeqLike;I)I
const #1042 = Method	#223.#1041;	//  scala/collection/LinearSeqLike$class.lengthCompare:(Lscala/collection/LinearSeqLike;I)I
const #1043 = Asciz	sameElements;
const #1044 = Asciz	(Lscala/collection/Iterable;)Z;
const #1045 = Asciz	(Lscala/collection/LinearSeqLike;Lscala/collection/Iterable;)Z;
const #1046 = NameAndType	#1043:#1045;//  sameElements:(Lscala/collection/LinearSeqLike;Lscala/collection/Iterable;)Z
const #1047 = Method	#223.#1046;	//  scala/collection/LinearSeqLike$class.sameElements:(Lscala/collection/LinearSeqLike;Lscala/collection/Iterable;)Z
const #1048 = Asciz	span;
const #1049 = Asciz	(Lscala/collection/LinearSeqLike;Lscala/Function1;)Lscala/Tuple2;;
const #1050 = NameAndType	#1048:#1049;//  span:(Lscala/collection/LinearSeqLike;Lscala/Function1;)Lscala/Tuple2;
const #1051 = Method	#223.#1050;	//  scala/collection/LinearSeqLike$class.span:(Lscala/collection/LinearSeqLike;Lscala/Function1;)Lscala/Tuple2;
const #1052 = Asciz	(Lscala/collection/LinearSeqLike;I)Lscala/collection/LinearSeqLike;;
const #1053 = NameAndType	#412:#1052;//  dropRight:(Lscala/collection/LinearSeqLike;I)Lscala/collection/LinearSeqLike;
const #1054 = Method	#223.#1053;	//  scala/collection/LinearSeqLike$class.dropRight:(Lscala/collection/LinearSeqLike;I)Lscala/collection/LinearSeqLike;
const #1055 = NameAndType	#409:#1052;//  drop:(Lscala/collection/LinearSeqLike;I)Lscala/collection/LinearSeqLike;
const #1056 = Method	#223.#1055;	//  scala/collection/LinearSeqLike$class.drop:(Lscala/collection/LinearSeqLike;I)Lscala/collection/LinearSeqLike;
const #1057 = Asciz	last;
const #1058 = Asciz	(Lscala/collection/LinearSeqLike;)Ljava/lang/Object;;
const #1059 = NameAndType	#1057:#1058;//  last:(Lscala/collection/LinearSeqLike;)Ljava/lang/Object;
const #1060 = Method	#223.#1059;	//  scala/collection/LinearSeqLike$class.last:(Lscala/collection/LinearSeqLike;)Ljava/lang/Object;
const #1061 = Asciz	reduceRight;
const #1062 = Asciz	(Lscala/collection/LinearSeqLike;Lscala/Function2;)Ljava/lang/Object;;
const #1063 = NameAndType	#1061:#1062;//  reduceRight:(Lscala/collection/LinearSeqLike;Lscala/Function2;)Ljava/lang/Object;
const #1064 = Method	#223.#1063;	//  scala/collection/LinearSeqLike$class.reduceRight:(Lscala/collection/LinearSeqLike;Lscala/Function2;)Ljava/lang/Object;
const #1065 = Asciz	reduceLeft;
const #1066 = NameAndType	#1065:#1062;//  reduceLeft:(Lscala/collection/LinearSeqLike;Lscala/Function2;)Ljava/lang/Object;
const #1067 = Method	#223.#1066;	//  scala/collection/LinearSeqLike$class.reduceLeft:(Lscala/collection/LinearSeqLike;Lscala/Function2;)Ljava/lang/Object;
const #1068 = Asciz	foldRight;
const #1069 = Asciz	(Lscala/collection/LinearSeqLike;Ljava/lang/Object;Lscala/Function2;)Ljava/lang/Object;;
const #1070 = NameAndType	#1068:#1069;//  foldRight:(Lscala/collection/LinearSeqLike;Ljava/lang/Object;Lscala/Function2;)Ljava/lang/Object;
const #1071 = Method	#223.#1070;	//  scala/collection/LinearSeqLike$class.foldRight:(Lscala/collection/LinearSeqLike;Ljava/lang/Object;Lscala/Function2;)Ljava/lang/Object;
const #1072 = Asciz	find;
const #1073 = Asciz	(Lscala/Function1;)Lscala/Option;;
const #1074 = Asciz	(Lscala/collection/LinearSeqLike;Lscala/Function1;)Lscala/Option;;
const #1075 = NameAndType	#1072:#1074;//  find:(Lscala/collection/LinearSeqLike;Lscala/Function1;)Lscala/Option;
const #1076 = Method	#223.#1075;	//  scala/collection/LinearSeqLike$class.find:(Lscala/collection/LinearSeqLike;Lscala/Function1;)Lscala/Option;
const #1077 = Asciz	count;
const #1078 = Asciz	(Lscala/collection/LinearSeqLike;Lscala/Function1;)I;
const #1079 = NameAndType	#1077:#1078;//  count:(Lscala/collection/LinearSeqLike;Lscala/Function1;)I
const #1080 = Method	#223.#1079;	//  scala/collection/LinearSeqLike$class.count:(Lscala/collection/LinearSeqLike;Lscala/Function1;)I
const #1081 = Asciz	exists;
const #1082 = Asciz	(Lscala/Function1;)Z;
const #1083 = Asciz	(Lscala/collection/LinearSeqLike;Lscala/Function1;)Z;
const #1084 = NameAndType	#1081:#1083;//  exists:(Lscala/collection/LinearSeqLike;Lscala/Function1;)Z
const #1085 = Method	#223.#1084;	//  scala/collection/LinearSeqLike$class.exists:(Lscala/collection/LinearSeqLike;Lscala/Function1;)Z
const #1086 = Asciz	forall;
const #1087 = NameAndType	#1086:#1083;//  forall:(Lscala/collection/LinearSeqLike;Lscala/Function1;)Z
const #1088 = Method	#223.#1087;	//  scala/collection/LinearSeqLike$class.forall:(Lscala/collection/LinearSeqLike;Lscala/Function1;)Z
const #1089 = Asciz	iterator;
const #1090 = Asciz	(Lscala/collection/LinearSeqLike;)Lscala/collection/Iterator;;
const #1091 = NameAndType	#1089:#1090;//  iterator:(Lscala/collection/LinearSeqLike;)Lscala/collection/Iterator;
const #1092 = Method	#223.#1091;	//  scala/collection/LinearSeqLike$class.iterator:(Lscala/collection/LinearSeqLike;)Lscala/collection/Iterator;
const #1093 = Asciz	(Lscala/collection/LinearSeqLike;I)Ljava/lang/Object;;
const #1094 = NameAndType	#398:#1093;//  apply:(Lscala/collection/LinearSeqLike;I)Ljava/lang/Object;
const #1095 = Method	#223.#1094;	//  scala/collection/LinearSeqLike$class.apply:(Lscala/collection/LinearSeqLike;I)Ljava/lang/Object;
const #1096 = Asciz	length;
const #1097 = Asciz	(Lscala/collection/LinearSeqLike;)I;
const #1098 = NameAndType	#1096:#1097;//  length:(Lscala/collection/LinearSeqLike;)I
const #1099 = Method	#223.#1098;	//  scala/collection/LinearSeqLike$class.length:(Lscala/collection/LinearSeqLike;)I
const #1100 = Asciz	(Lscala/collection/LinearSeqLike;Lscala/collection/LinearSeqLike;)Lscala/collection/LinearSeq;;
const #1101 = NameAndType	#389:#1100;//  toCollection:(Lscala/collection/LinearSeqLike;Lscala/collection/LinearSeqLike;)Lscala/collection/LinearSeq;
const #1102 = Method	#223.#1101;	//  scala/collection/LinearSeqLike$class.toCollection:(Lscala/collection/LinearSeqLike;Lscala/collection/LinearSeqLike;)Lscala/collection/LinearSeq;
const #1103 = Asciz	Lscala/collection/LinearSeqLike;;
const #1104 = NameAndType	#381:#391;//  thisCollection:(Lscala/collection/LinearSeqLike;)Lscala/collection/LinearSeq;
const #1105 = Method	#223.#1104;	//  scala/collection/LinearSeqLike$class.thisCollection:(Lscala/collection/LinearSeqLike;)Lscala/collection/LinearSeq;
const #1106 = Asciz	scala$collection$LinearSeqLike$$super$sameElements;
const #1107 = Asciz	(Lscala/collection/IterableLike;Lscala/collection/Iterable;)Z;
const #1108 = NameAndType	#1043:#1107;//  sameElements:(Lscala/collection/IterableLike;Lscala/collection/Iterable;)Z
const #1109 = Method	#183.#1108;	//  scala/collection/IterableLike$class.sameElements:(Lscala/collection/IterableLike;Lscala/collection/Iterable;)Z
const #1110 = Asciz	<A:Ljava/lang/Object;>Ljava/lang/Object;Lscala/collection/immutable/LinearSeq<TA;>;Lscala/collection/generic/GenericTraversableTemplate<TA;Lscala/collection/immutable/Stream;>;Lscala/collection/LinearSeqLike<TA;Lscala/collection/immutable/Stream<TA;>;>;Lscala/ScalaObject;;
const #1111 = Asciz	ScalaSig;
const #1112 = Asciz	InnerClasses;
const #1113 = Asciz	Cons;
const #1114 = Asciz	$anonfun$1;
const #1115 = Asciz	$anonfun$2;
const #1116 = Asciz	ConsWrapper;
const #1117 = Asciz	scala/collection/immutable/Stream$StreamBuilder;
const #1118 = class	#1117;	//  scala/collection/immutable/Stream$StreamBuilder
const #1119 = Asciz	StreamBuilder;
const #1120 = Asciz	$anonfun$map$1;
const #1121 = Asciz	$anonfun$zip$1;
const #1122 = Asciz	scala/collection/immutable/Stream$$anonfun$make$1;
const #1123 = class	#1122;	//  scala/collection/immutable/Stream$$anonfun$make$1
const #1124 = Asciz	$anonfun$make$1;
const #1125 = Asciz	scala/collection/immutable/Stream$$anonfun$from$1;
const #1126 = class	#1125;	//  scala/collection/immutable/Stream$$anonfun$from$1
const #1127 = Asciz	$anonfun$from$1;
const #1128 = Asciz	$anonfun$take$1;
const #1129 = Asciz	$anonfun$init$1;
const #1130 = Asciz	$anonfun$fill$1;
const #1131 = Asciz	scala/collection/immutable/Stream$$anonfun$const$1;
const #1132 = class	#1131;	//  scala/collection/immutable/Stream$$anonfun$const$1
const #1133 = Asciz	$anonfun$const$1;
const #1134 = Asciz	scala/collection/immutable/Stream$$anonfun$range$1;
const #1135 = class	#1134;	//  scala/collection/immutable/Stream$$anonfun$range$1
const #1136 = Asciz	$anonfun$range$1;
const #1137 = Asciz	scala/collection/immutable/Stream$$anonfun$loop$5$1;
const #1138 = class	#1137;	//  scala/collection/immutable/Stream$$anonfun$loop$5$1
const #1139 = Asciz	$anonfun$loop$5$1;
const #1140 = Asciz	$anonfun$append$1;
const #1141 = Asciz	$anonfun$filter$1;
const #1142 = Asciz	$anonfun$loop$4$2;
const #1143 = Asciz	$anonfun$loop$4$1;
const #1144 = Asciz	scala/collection/immutable/Stream$$anonfun$iterate$1;
const #1145 = class	#1144;	//  scala/collection/immutable/Stream$$anonfun$iterate$1
const #1146 = Asciz	$anonfun$iterate$1;
const #1147 = Asciz	scala/collection/immutable/Stream$StreamCanBuildFrom;
const #1148 = class	#1147;	//  scala/collection/immutable/Stream$StreamCanBuildFrom
const #1149 = Asciz	StreamCanBuildFrom;
const #1150 = Asciz	$anonfun$flatMap$1;
const #1151 = Asciz	scala/collection/TraversableLike$WithFilter;
const #1152 = class	#1151;	//  scala/collection/TraversableLike$WithFilter
const #1153 = Asciz	WithFilter;
const #1154 = Asciz	$anonfun$partition$2;
const #1155 = Asciz	$anonfun$partition$1;
const #1156 = Asciz	$anonfun$takeWhile$1;
const #1157 = Asciz	$anonfun$$plus$plus$1;
const #1158 = Asciz	$anonfun$flatten1$1$1;
const #1159 = Asciz	scala/collection/immutable/Stream$$anonfun$continually$1;
const #1160 = class	#1159;	//  scala/collection/immutable/Stream$$anonfun$continually$1
const #1161 = Asciz	$anonfun$continually$1;
const #1162 = Asciz	$anonfun$removeDuplicates$1;
const #1163 = Asciz	scala/collection/immutable/LinearSeq;
const #1164 = class	#1163;	//  scala/collection/immutable/LinearSeq
const #1165 = Asciz	scala/collection/generic/GenericTraversableTemplate;
const #1166 = class	#1165;	//  scala/collection/generic/GenericTraversableTemplate
const #1167 = Asciz	scala/ScalaObject;
const #1168 = class	#1167;	//  scala/ScalaObject

{
public static final scala.collection.immutable.Stream make(int, java.lang.Object);
  Code:
   Stack=3, Locals=2, Args_size=2
   0:	getstatic	#11; //Field scala/collection/immutable/Stream$.MODULE$:Lscala/collection/immutable/Stream$;
   3:	iload_0
   4:	aload_1
   5:	invokevirtual	#13; //Method scala/collection/immutable/Stream$.make:(ILjava/lang/Object;)Lscala/collection/immutable/Stream;
   8:	areturn
  Signature: length = 0x2
   00 0E 

public static final scala.collection.immutable.Stream const(java.lang.Object);
  Code:
   Stack=2, Locals=1, Args_size=1
   0:	getstatic	#11; //Field scala/collection/immutable/Stream$.MODULE$:Lscala/collection/immutable/Stream$;
   3:	aload_0
   4:	invokevirtual	#19; //Method scala/collection/immutable/Stream$.const:(Ljava/lang/Object;)Lscala/collection/immutable/Stream;
   7:	areturn
  Signature: length = 0x2
   00 14 

public static final scala.collection.immutable.Stream range(int, int, scala.Function1);
  Code:
   Stack=4, Locals=3, Args_size=3
   0:	getstatic	#11; //Field scala/collection/immutable/Stream$.MODULE$:Lscala/collection/immutable/Stream$;
   3:	iload_0
   4:	iload_1
   5:	aload_2
   6:	invokevirtual	#24; //Method scala/collection/immutable/Stream$.range:(IILscala/Function1;)Lscala/collection/immutable/Stream;
   9:	areturn
  Signature: length = 0x2
   00 19 

public static final scala.collection.immutable.Stream concat(scala.collection.Iterator);
  Code:
   Stack=2, Locals=1, Args_size=1
   0:	getstatic	#11; //Field scala/collection/immutable/Stream$.MODULE$:Lscala/collection/immutable/Stream$;
   3:	aload_0
   4:	invokevirtual	#29; //Method scala/collection/immutable/Stream$.concat:(Lscala/collection/Iterator;)Lscala/collection/immutable/Stream;
   7:	areturn
  Signature: length = 0x2
   00 1E 

public static final scala.collection.immutable.Stream concat(scala.collection.Iterable);
  Code:
   Stack=2, Locals=1, Args_size=1
   0:	getstatic	#11; //Field scala/collection/immutable/Stream$.MODULE$:Lscala/collection/immutable/Stream$;
   3:	aload_0
   4:	invokevirtual	#33; //Method scala/collection/immutable/Stream$.concat:(Lscala/collection/Iterable;)Lscala/collection/immutable/Stream;
   7:	areturn
  Signature: length = 0x2
   00 22 

public static final scala.collection.immutable.Stream fromIterator(scala.collection.Iterator);
  Code:
   Stack=2, Locals=1, Args_size=1
   0:	getstatic	#11; //Field scala/collection/immutable/Stream$.MODULE$:Lscala/collection/immutable/Stream$;
   3:	aload_0
   4:	invokevirtual	#37; //Method scala/collection/immutable/Stream$.fromIterator:(Lscala/collection/Iterator;)Lscala/collection/immutable/Stream;
   7:	areturn
  Signature: length = 0x2
   00 26 

public static final scala.collection.immutable.Stream range(int, int, int);
  Code:
   Stack=4, Locals=3, Args_size=3
   0:	getstatic	#11; //Field scala/collection/immutable/Stream$.MODULE$:Lscala/collection/immutable/Stream$;
   3:	iload_0
   4:	iload_1
   5:	iload_2
   6:	invokevirtual	#41; //Method scala/collection/immutable/Stream$.range:(III)Lscala/collection/immutable/Stream;
   9:	areturn
  Signature: length = 0x2
   00 2A 

public static final scala.collection.immutable.Stream tabulate(int, scala.Function1);
  Code:
   Stack=3, Locals=2, Args_size=2
   0:	getstatic	#11; //Field scala/collection/immutable/Stream$.MODULE$:Lscala/collection/immutable/Stream$;
   3:	iload_0
   4:	aload_1
   5:	invokevirtual	#46; //Method scala/collection/immutable/Stream$.tabulate:(ILscala/Function1;)Lscala/collection/immutable/Stream;
   8:	areturn
  Signature: length = 0x2
   00 2F 

public static final scala.collection.immutable.Stream fill(int, scala.Function0);
  Code:
   Stack=3, Locals=2, Args_size=2
   0:	getstatic	#11; //Field scala/collection/immutable/Stream$.MODULE$:Lscala/collection/immutable/Stream$;
   3:	iload_0
   4:	aload_1
   5:	invokevirtual	#51; //Method scala/collection/immutable/Stream$.fill:(ILscala/Function0;)Lscala/collection/immutable/Stream;
   8:	areturn
  Signature: length = 0x2
   00 34 

public static final scala.collection.immutable.Stream continually(scala.Function0);
  Code:
   Stack=2, Locals=1, Args_size=1
   0:	getstatic	#11; //Field scala/collection/immutable/Stream$.MODULE$:Lscala/collection/immutable/Stream$;
   3:	aload_0
   4:	invokevirtual	#56; //Method scala/collection/immutable/Stream$.continually:(Lscala/Function0;)Lscala/collection/immutable/Stream;
   7:	areturn
  Signature: length = 0x2
   00 39 

public static final scala.collection.immutable.Stream from(int);
  Code:
   Stack=2, Locals=1, Args_size=1
   0:	getstatic	#11; //Field scala/collection/immutable/Stream$.MODULE$:Lscala/collection/immutable/Stream$;
   3:	iload_0
   4:	invokevirtual	#61; //Method scala/collection/immutable/Stream$.from:(I)Lscala/collection/immutable/Stream;
   7:	areturn
  Signature: length = 0x2
   00 3E 

public static final scala.collection.immutable.Stream from(int, int);
  Code:
   Stack=3, Locals=2, Args_size=2
   0:	getstatic	#11; //Field scala/collection/immutable/Stream$.MODULE$:Lscala/collection/immutable/Stream$;
   3:	iload_0
   4:	iload_1
   5:	invokevirtual	#65; //Method scala/collection/immutable/Stream$.from:(II)Lscala/collection/immutable/Stream;
   8:	areturn
  Signature: length = 0x2
   00 42 

public static final scala.collection.immutable.Stream iterate(java.lang.Object, int, scala.Function1);
  Code:
   Stack=4, Locals=3, Args_size=3
   0:	getstatic	#11; //Field scala/collection/immutable/Stream$.MODULE$:Lscala/collection/immutable/Stream$;
   3:	aload_0
   4:	iload_1
   5:	aload_2
   6:	invokevirtual	#70; //Method scala/collection/immutable/Stream$.iterate:(Ljava/lang/Object;ILscala/Function1;)Lscala/collection/immutable/Stream;
   9:	areturn
  Signature: length = 0x2
   00 47 

public static final scala.collection.immutable.Stream iterate(java.lang.Object, scala.Function1);
  Code:
   Stack=3, Locals=2, Args_size=2
   0:	getstatic	#11; //Field scala/collection/immutable/Stream$.MODULE$:Lscala/collection/immutable/Stream$;
   3:	aload_0
   4:	aload_1
   5:	invokevirtual	#74; //Method scala/collection/immutable/Stream$.iterate:(Ljava/lang/Object;Lscala/Function1;)Lscala/collection/immutable/Stream;
   8:	areturn
  Signature: length = 0x2
   00 4B 

public static final scala.collection.immutable.Stream$$hash$colon$colon$ lazy_$colon$colon();
  Code:
   Stack=1, Locals=0, Args_size=0
   0:	getstatic	#11; //Field scala/collection/immutable/Stream$.MODULE$:Lscala/collection/immutable/Stream$;
   3:	invokevirtual	#79; //Method scala/collection/immutable/Stream$.lazy_$colon$colon:()Lscala/collection/immutable/Stream$$hash$colon$colon$;
   6:	areturn

public static final scala.collection.immutable.Stream$ConsWrapper consWrapper(scala.Function0);
  Code:
   Stack=2, Locals=1, Args_size=1
   0:	getstatic	#11; //Field scala/collection/immutable/Stream$.MODULE$:Lscala/collection/immutable/Stream$;
   3:	aload_0
   4:	invokevirtual	#83; //Method scala/collection/immutable/Stream$.consWrapper:(Lscala/Function0;)Lscala/collection/immutable/Stream$ConsWrapper;
   7:	areturn
  Signature: length = 0x2
   00 54 

public static final scala.collection.immutable.Stream empty();
  Code:
   Stack=1, Locals=0, Args_size=0
   0:	getstatic	#11; //Field scala/collection/immutable/Stream$.MODULE$:Lscala/collection/immutable/Stream$;
   3:	invokevirtual	#88; //Method scala/collection/immutable/Stream$.empty:()Lscala/collection/immutable/Stream;
   6:	areturn
  Signature: length = 0x2
   00 59 

public static final scala.collection.generic.CanBuildFrom canBuildFrom();
  Code:
   Stack=1, Locals=0, Args_size=0
   0:	getstatic	#11; //Field scala/collection/immutable/Stream$.MODULE$:Lscala/collection/immutable/Stream$;
   3:	invokevirtual	#93; //Method scala/collection/immutable/Stream$.canBuildFrom:()Lscala/collection/generic/CanBuildFrom;
   6:	areturn
  Signature: length = 0x2
   00 5E 

public static final scala.Some unapplySeq(scala.collection.Seq);
  Code:
   Stack=2, Locals=1, Args_size=1
   0:	getstatic	#11; //Field scala/collection/immutable/Stream$.MODULE$:Lscala/collection/immutable/Stream$;
   3:	aload_0
   4:	invokevirtual	#98; //Method scala/collection/immutable/Stream$.unapplySeq:(Lscala/collection/Seq;)Lscala/Some;
   7:	areturn
  Signature: length = 0x2
   00 63 

public static final scala.collection.Traversable iterate(java.lang.Object, int, scala.Function1);
  Code:
   Stack=4, Locals=3, Args_size=3
   0:	getstatic	#11; //Field scala/collection/immutable/Stream$.MODULE$:Lscala/collection/immutable/Stream$;
   3:	aload_0
   4:	iload_1
   5:	aload_2
   6:	invokevirtual	#102; //Method scala/collection/immutable/Stream$.iterate:(Ljava/lang/Object;ILscala/Function1;)Lscala/collection/Traversable;
   9:	areturn
  Signature: length = 0x2
   00 47 

public static final scala.collection.Traversable range(int, int, int);
  Code:
   Stack=4, Locals=3, Args_size=3
   0:	getstatic	#11; //Field scala/collection/immutable/Stream$.MODULE$:Lscala/collection/immutable/Stream$;
   3:	iload_0
   4:	iload_1
   5:	iload_2
   6:	invokevirtual	#105; //Method scala/collection/immutable/Stream$.range:(III)Lscala/collection/Traversable;
   9:	areturn
  Signature: length = 0x2
   00 2A 

public static final scala.collection.Traversable range(int, int);
  Code:
   Stack=3, Locals=2, Args_size=2
   0:	getstatic	#11; //Field scala/collection/immutable/Stream$.MODULE$:Lscala/collection/immutable/Stream$;
   3:	iload_0
   4:	iload_1
   5:	invokevirtual	#108; //Method scala/collection/immutable/Stream$.range:(II)Lscala/collection/Traversable;
   8:	areturn
  Signature: length = 0x2
   00 42 

public static final scala.collection.Traversable tabulate(int, int, int, int, int, scala.Function5);
  Code:
   Stack=7, Locals=6, Args_size=6
   0:	getstatic	#11; //Field scala/collection/immutable/Stream$.MODULE$:Lscala/collection/immutable/Stream$;
   3:	iload_0
   4:	iload_1
   5:	iload_2
   6:	iload_3
   7:	iload	4
   9:	aload	5
   11:	invokevirtual	#111; //Method scala/collection/immutable/Stream$.tabulate:(IIIIILscala/Function5;)Lscala/collection/Traversable;
   14:	areturn
  Signature: length = 0x2
   00 70 

public static final scala.collection.Traversable tabulate(int, int, int, int, scala.Function4);
  Code:
   Stack=6, Locals=5, Args_size=5
   0:	getstatic	#11; //Field scala/collection/immutable/Stream$.MODULE$:Lscala/collection/immutable/Stream$;
   3:	iload_0
   4:	iload_1
   5:	iload_2
   6:	iload_3
   7:	aload	4
   9:	invokevirtual	#115; //Method scala/collection/immutable/Stream$.tabulate:(IIIILscala/Function4;)Lscala/collection/Traversable;
   12:	areturn
  Signature: length = 0x2
   00 74 

public static final scala.collection.Traversable tabulate(int, int, int, scala.Function3);
  Code:
   Stack=5, Locals=4, Args_size=4
   0:	getstatic	#11; //Field scala/collection/immutable/Stream$.MODULE$:Lscala/collection/immutable/Stream$;
   3:	iload_0
   4:	iload_1
   5:	iload_2
   6:	aload_3
   7:	invokevirtual	#119; //Method scala/collection/immutable/Stream$.tabulate:(IIILscala/Function3;)Lscala/collection/Traversable;
   10:	areturn
  Signature: length = 0x2
   00 78 

public static final scala.collection.Traversable tabulate(int, int, scala.Function2);
  Code:
   Stack=4, Locals=3, Args_size=3
   0:	getstatic	#11; //Field scala/collection/immutable/Stream$.MODULE$:Lscala/collection/immutable/Stream$;
   3:	iload_0
   4:	iload_1
   5:	aload_2
   6:	invokevirtual	#123; //Method scala/collection/immutable/Stream$.tabulate:(IILscala/Function2;)Lscala/collection/Traversable;
   9:	areturn
  Signature: length = 0x2
   00 7C 

public static final scala.collection.Traversable tabulate(int, scala.Function1);
  Code:
   Stack=3, Locals=2, Args_size=2
   0:	getstatic	#11; //Field scala/collection/immutable/Stream$.MODULE$:Lscala/collection/immutable/Stream$;
   3:	iload_0
   4:	aload_1
   5:	invokevirtual	#127; //Method scala/collection/immutable/Stream$.tabulate:(ILscala/Function1;)Lscala/collection/Traversable;
   8:	areturn
  Signature: length = 0x2
   00 2F 

public static final scala.collection.Traversable fill(int, int, int, int, int, scala.Function0);
  Code:
   Stack=7, Locals=6, Args_size=6
   0:	getstatic	#11; //Field scala/collection/immutable/Stream$.MODULE$:Lscala/collection/immutable/Stream$;
   3:	iload_0
   4:	iload_1
   5:	iload_2
   6:	iload_3
   7:	iload	4
   9:	aload	5
   11:	invokevirtual	#130; //Method scala/collection/immutable/Stream$.fill:(IIIIILscala/Function0;)Lscala/collection/Traversable;
   14:	areturn
  Signature: length = 0x2
   00 FFFFFF83 

public static final scala.collection.Traversable fill(int, int, int, int, scala.Function0);
  Code:
   Stack=6, Locals=5, Args_size=5
   0:	getstatic	#11; //Field scala/collection/immutable/Stream$.MODULE$:Lscala/collection/immutable/Stream$;
   3:	iload_0
   4:	iload_1
   5:	iload_2
   6:	iload_3
   7:	aload	4
   9:	invokevirtual	#134; //Method scala/collection/immutable/Stream$.fill:(IIIILscala/Function0;)Lscala/collection/Traversable;
   12:	areturn
  Signature: length = 0x2
   00 FFFFFF87 

public static final scala.collection.Traversable fill(int, int, int, scala.Function0);
  Code:
   Stack=5, Locals=4, Args_size=4
   0:	getstatic	#11; //Field scala/collection/immutable/Stream$.MODULE$:Lscala/collection/immutable/Stream$;
   3:	iload_0
   4:	iload_1
   5:	iload_2
   6:	aload_3
   7:	invokevirtual	#138; //Method scala/collection/immutable/Stream$.fill:(IIILscala/Function0;)Lscala/collection/Traversable;
   10:	areturn
  Signature: length = 0x2
   00 FFFFFF8B 

public static final scala.collection.Traversable fill(int, int, scala.Function0);
  Code:
   Stack=4, Locals=3, Args_size=3
   0:	getstatic	#11; //Field scala/collection/immutable/Stream$.MODULE$:Lscala/collection/immutable/Stream$;
   3:	iload_0
   4:	iload_1
   5:	aload_2
   6:	invokevirtual	#142; //Method scala/collection/immutable/Stream$.fill:(IILscala/Function0;)Lscala/collection/Traversable;
   9:	areturn
  Signature: length = 0x2
   00 FFFFFF8F 

public static final scala.collection.Traversable fill(int, scala.Function0);
  Code:
   Stack=3, Locals=2, Args_size=2
   0:	getstatic	#11; //Field scala/collection/immutable/Stream$.MODULE$:Lscala/collection/immutable/Stream$;
   3:	iload_0
   4:	aload_1
   5:	invokevirtual	#146; //Method scala/collection/immutable/Stream$.fill:(ILscala/Function0;)Lscala/collection/Traversable;
   8:	areturn
  Signature: length = 0x2
   00 34 

public static final scala.collection.Traversable concat(scala.collection.Seq);
  Code:
   Stack=2, Locals=1, Args_size=1
   0:	getstatic	#11; //Field scala/collection/immutable/Stream$.MODULE$:Lscala/collection/immutable/Stream$;
   3:	aload_0
   4:	invokevirtual	#149; //Method scala/collection/immutable/Stream$.concat:(Lscala/collection/Seq;)Lscala/collection/Traversable;
   7:	areturn
  Signature: length = 0x2
   00 FFFFFF96 

public static final scala.collection.Traversable empty();
  Code:
   Stack=1, Locals=0, Args_size=0
   0:	getstatic	#11; //Field scala/collection/immutable/Stream$.MODULE$:Lscala/collection/immutable/Stream$;
   3:	invokevirtual	#153; //Method scala/collection/immutable/Stream$.empty:()Lscala/collection/Traversable;
   6:	areturn
  Signature: length = 0x2
   00 59 

public scala.collection.immutable.Stream();
  Code:
   Stack=1, Locals=1, Args_size=1
   0:	aload_0
   1:	invokespecial	#160; //Method java/lang/Object."<init>":()V
   4:	aload_0
   5:	invokestatic	#166; //Method scala/collection/TraversableLike$class.$init$:(Lscala/collection/TraversableLike;)V
   8:	aload_0
   9:	invokestatic	#171; //Method scala/collection/generic/GenericTraversableTemplate$class.$init$:(Lscala/collection/generic/GenericTraversableTemplate;)V
   12:	aload_0
   13:	invokestatic	#176; //Method scala/collection/Traversable$class.$init$:(Lscala/collection/Traversable;)V
   16:	aload_0
   17:	invokestatic	#181; //Method scala/collection/immutable/Traversable$class.$init$:(Lscala/collection/immutable/Traversable;)V
   20:	aload_0
   21:	invokestatic	#186; //Method scala/collection/IterableLike$class.$init$:(Lscala/collection/IterableLike;)V
   24:	aload_0
   25:	invokestatic	#191; //Method scala/collection/Iterable$class.$init$:(Lscala/collection/Iterable;)V
   28:	aload_0
   29:	invokestatic	#196; //Method scala/collection/immutable/Iterable$class.$init$:(Lscala/collection/immutable/Iterable;)V
   32:	aload_0
   33:	invokestatic	#201; //Method scala/Function1$class.$init$:(Lscala/Function1;)V
   36:	aload_0
   37:	invokestatic	#206; //Method scala/PartialFunction$class.$init$:(Lscala/PartialFunction;)V
   40:	aload_0
   41:	invokestatic	#211; //Method scala/collection/SeqLike$class.$init$:(Lscala/collection/SeqLike;)V
   44:	aload_0
   45:	invokestatic	#216; //Method scala/collection/Seq$class.$init$:(Lscala/collection/Seq;)V
   48:	aload_0
   49:	invokestatic	#221; //Method scala/collection/immutable/Seq$class.$init$:(Lscala/collection/immutable/Seq;)V
   52:	aload_0
   53:	invokestatic	#226; //Method scala/collection/LinearSeqLike$class.$init$:(Lscala/collection/LinearSeqLike;)V
   56:	aload_0
   57:	invokestatic	#231; //Method scala/collection/LinearSeq$class.$init$:(Lscala/collection/LinearSeq;)V
   60:	aload_0
   61:	invokestatic	#236; //Method scala/collection/immutable/LinearSeq$class.$init$:(Lscala/collection/immutable/LinearSeq;)V
   64:	return
  LineNumberTable: 
   line 41: 0

  Signature: length = 0x2
   00 FFFFFF9B 

public final scala.collection.immutable.Stream flatten1$1(scala.collection.Traversable, scala.Function1);
  Code:
   Stack=8, Locals=3, Args_size=3
   0:	aload_1
   1:	invokeinterface	#244,  1; //InterfaceMethod scala/collection/TraversableLike.isEmpty:()Z
   6:	ifeq	25
   9:	aload_0
   10:	invokeinterface	#248,  1; //InterfaceMethod scala/collection/TraversableLike.tail:()Ljava/lang/Object;
   15:	checkcast	#250; //class scala/collection/immutable/Stream
   18:	aload_2
   19:	invokevirtual	#254; //Method flatten:(Lscala/Function1;)Lscala/collection/immutable/Stream;
   22:	goto	48
   25:	new	#256; //class scala/collection/immutable/Stream$Cons
   28:	dup
   29:	aload_1
   30:	invokeinterface	#259,  1; //InterfaceMethod scala/collection/TraversableLike.head:()Ljava/lang/Object;
   35:	new	#261; //class scala/collection/immutable/Stream$$anonfun$flatten1$1$1
   38:	dup
   39:	aload_0
   40:	aload_2
   41:	aload_1
   42:	invokespecial	#264; //Method scala/collection/immutable/Stream$$anonfun$flatten1$1$1."<init>":(Lscala/collection/immutable/Stream;Lscala/Function1;Lscala/collection/Traversable;)V
   45:	invokespecial	#267; //Method scala/collection/immutable/Stream$Cons."<init>":(Ljava/lang/Object;Lscala/Function0;)V
   48:	areturn
  LineNumberTable: 
   line 379: 0
   line 382: 9
   line 379: 22
   line 380: 25
   line 379: 48

  LocalVariableTable: 
   Start  Length  Slot  Name   Signature
   0      49      0    this       Lscala/collection/immutable/Stream;
   0      49      1    t$1       Lscala/collection/Traversable;


public final scala.collection.immutable.Stream loop$4(int, scala.collection.immutable.Stream, java.lang.Object);
  Code:
   Stack=9, Locals=5, Args_size=4
   0:	aload_2
   1:	invokeinterface	#277,  1; //InterfaceMethod scala/collection/IterableLike.isEmpty:()Z
   6:	ifeq	52
   9:	new	#279; //class scala/collection/immutable/Stream$$anonfun$loop$4$1
   12:	dup
   13:	aload_0
   14:	aload_3
   15:	invokespecial	#282; //Method scala/collection/immutable/Stream$$anonfun$loop$4$1."<init>":(Lscala/collection/immutable/Stream;Ljava/lang/Object;)V
   18:	astore	4
   20:	iload_1
   21:	iconst_0
   22:	if_icmpgt	31
   25:	getstatic	#287; //Field scala/collection/immutable/Stream$Empty$.MODULE$:Lscala/collection/immutable/Stream$Empty$;
   28:	goto	49
   31:	new	#256; //class scala/collection/immutable/Stream$Cons
   34:	dup
   35:	aload_3
   36:	new	#289; //class scala/collection/immutable/Stream$$anonfun$fill$1
   39:	dup
   40:	iload_1
   41:	aload	4
   43:	invokespecial	#292; //Method scala/collection/immutable/Stream$$anonfun$fill$1."<init>":(ILscala/Function0;)V
   46:	invokespecial	#267; //Method scala/collection/immutable/Stream$Cons."<init>":(Ljava/lang/Object;Lscala/Function0;)V
   49:	goto	76
   52:	new	#256; //class scala/collection/immutable/Stream$Cons
   55:	dup
   56:	aload_2
   57:	invokeinterface	#293,  1; //InterfaceMethod scala/collection/IterableLike.head:()Ljava/lang/Object;
   62:	new	#295; //class scala/collection/immutable/Stream$$anonfun$loop$4$2
   65:	dup
   66:	aload_0
   67:	aload_3
   68:	iload_1
   69:	aload_2
   70:	invokespecial	#298; //Method scala/collection/immutable/Stream$$anonfun$loop$4$2."<init>":(Lscala/collection/immutable/Stream;Ljava/lang/Object;ILscala/collection/immutable/Stream;)V
   73:	invokespecial	#267; //Method scala/collection/immutable/Stream$Cons."<init>":(Ljava/lang/Object;Lscala/Function0;)V
   76:	areturn
  LineNumberTable: 
   line 356: 0
   line 357: 52
   line 356: 76

  LocalVariableTable: 
   Start  Length  Slot  Name   Signature
   0      77      0    this       Lscala/collection/immutable/Stream;
   0      77      1    len$1       I
   0      77      2    these$1       Lscala/collection/immutable/Stream;
   25      27      4    elem$10       Lscala/Function0;


public final java.lang.Object filter(scala.Function1);
  Code:
   Stack=2, Locals=2, Args_size=2
   0:	aload_0
   1:	aload_1
   2:	invokevirtual	#345; //Method filter:(Lscala/Function1;)Lscala/collection/immutable/Stream;
   5:	areturn
  LineNumberTable: 
   line 41: 0

  LocalVariableTable: 
   Start  Length  Slot  Name   Signature
   0      6      0    this       Lscala/collection/immutable/Stream;
   0      6      1    p       Lscala/Function1;


public scala.collection.LinearSeqLike take(int);
  Code:
   Stack=2, Locals=2, Args_size=2
   0:	aload_0
   1:	iload_1
   2:	invokevirtual	#351; //Method take:(I)Lscala/collection/immutable/Stream;
   5:	areturn
  LineNumberTable: 
   line 41: 0

  LocalVariableTable: 
   Start  Length  Slot  Name   Signature
   0      6      0    this       Lscala/collection/immutable/Stream;
   0      6      1    n       I


public java.lang.Object take(int);
  Code:
   Stack=2, Locals=2, Args_size=2
   0:	aload_0
   1:	iload_1
   2:	invokevirtual	#351; //Method take:(I)Lscala/collection/immutable/Stream;
   5:	areturn
  LineNumberTable: 
   line 41: 0

  LocalVariableTable: 
   Start  Length  Slot  Name   Signature
   0      6      0    this       Lscala/collection/immutable/Stream;
   0      6      1    n       I


public scala.collection.LinearSeqLike slice(int, int);
  Code:
   Stack=3, Locals=3, Args_size=3
   0:	aload_0
   1:	iload_1
   2:	iload_2
   3:	invokevirtual	#357; //Method slice:(II)Lscala/collection/immutable/Stream;
   6:	areturn
  LineNumberTable: 
   line 41: 0

  LocalVariableTable: 
   Start  Length  Slot  Name   Signature
   0      7      0    this       Lscala/collection/immutable/Stream;
   0      7      1    from       I
   0      7      2    until       I


public java.lang.Object slice(int, int);
  Code:
   Stack=3, Locals=3, Args_size=3
   0:	aload_0
   1:	iload_1
   2:	iload_2
   3:	invokevirtual	#357; //Method slice:(II)Lscala/collection/immutable/Stream;
   6:	areturn
  LineNumberTable: 
   line 41: 0

  LocalVariableTable: 
   Start  Length  Slot  Name   Signature
   0      7      0    this       Lscala/collection/immutable/Stream;
   0      7      1    from       I
   0      7      2    until       I


public java.lang.Object init();
  Code:
   Stack=1, Locals=1, Args_size=1
   0:	aload_0
   1:	invokevirtual	#362; //Method init:()Lscala/collection/immutable/Stream;
   4:	areturn
  LineNumberTable: 
   line 41: 0


public java.lang.Object takeRight(int);
  Code:
   Stack=2, Locals=2, Args_size=2
   0:	aload_0
   1:	iload_1
   2:	invokevirtual	#365; //Method takeRight:(I)Lscala/collection/immutable/Stream;
   5:	areturn
  LineNumberTable: 
   line 41: 0

  LocalVariableTable: 
   Start  Length  Slot  Name   Signature
   0      6      0    this       Lscala/collection/immutable/Stream;
   0      6      1    n       I


public scala.collection.LinearSeqLike takeWhile(scala.Function1);
  Code:
   Stack=2, Locals=2, Args_size=2
   0:	aload_0
   1:	aload_1
   2:	invokevirtual	#369; //Method takeWhile:(Lscala/Function1;)Lscala/collection/immutable/Stream;
   5:	areturn
  LineNumberTable: 
   line 41: 0

  LocalVariableTable: 
   Start  Length  Slot  Name   Signature
   0      6      0    this       Lscala/collection/immutable/Stream;
   0      6      1    p       Lscala/Function1;


public java.lang.Object takeWhile(scala.Function1);
  Code:
   Stack=2, Locals=2, Args_size=2
   0:	aload_0
   1:	aload_1
   2:	invokevirtual	#369; //Method takeWhile:(Lscala/Function1;)Lscala/collection/immutable/Stream;
   5:	areturn
  LineNumberTable: 
   line 41: 0

  LocalVariableTable: 
   Start  Length  Slot  Name   Signature
   0      6      0    this       Lscala/collection/immutable/Stream;
   0      6      1    p       Lscala/Function1;


public java.lang.Object dropWhile(scala.Function1);
  Code:
   Stack=2, Locals=2, Args_size=2
   0:	aload_0
   1:	aload_1
   2:	invokevirtual	#372; //Method dropWhile:(Lscala/Function1;)Lscala/collection/immutable/Stream;
   5:	areturn
  LineNumberTable: 
   line 41: 0

  LocalVariableTable: 
   Start  Length  Slot  Name   Signature
   0      6      0    this       Lscala/collection/immutable/Stream;
   0      6      1    p       Lscala/Function1;


public java.lang.Object removeDuplicates();
  Code:
   Stack=1, Locals=1, Args_size=1
   0:	aload_0
   1:	invokevirtual	#375; //Method removeDuplicates:()Lscala/collection/immutable/Stream;
   4:	areturn
  LineNumberTable: 
   line 41: 0


public java.lang.Object reverse();
  Code:
   Stack=1, Locals=1, Args_size=1
   0:	aload_0
   1:	invokevirtual	#378; //Method reverse:()Lscala/collection/immutable/Stream;
   4:	areturn
  LineNumberTable: 
   line 41: 0


public scala.collection.Traversable flatten(scala.Function1);
  Code:
   Stack=2, Locals=2, Args_size=2
   0:	aload_0
   1:	aload_1
   2:	invokevirtual	#254; //Method flatten:(Lscala/Function1;)Lscala/collection/immutable/Stream;
   5:	areturn
  LineNumberTable: 
   line 41: 0

  LocalVariableTable: 
   Start  Length  Slot  Name   Signature
   0      6      0    this       Lscala/collection/immutable/Stream;
   0      6      1    asTraversable       Lscala/Function1;


public scala.collection.Seq thisCollection();
  Code:
   Stack=1, Locals=1, Args_size=1
   0:	aload_0
   1:	invokeinterface	#387,  1; //InterfaceMethod scala/collection/LinearSeqLike.thisCollection:()Lscala/collection/LinearSeq;
   6:	areturn
  LineNumberTable: 
   line 41: 0


public scala.collection.Iterable thisCollection();
  Code:
   Stack=1, Locals=1, Args_size=1
   0:	aload_0
   1:	invokeinterface	#387,  1; //InterfaceMethod scala/collection/LinearSeqLike.thisCollection:()Lscala/collection/LinearSeq;
   6:	areturn
  LineNumberTable: 
   line 41: 0


public scala.collection.Traversable thisCollection();
  Code:
   Stack=1, Locals=1, Args_size=1
   0:	aload_0
   1:	invokeinterface	#387,  1; //InterfaceMethod scala/collection/LinearSeqLike.thisCollection:()Lscala/collection/LinearSeq;
   6:	areturn
  LineNumberTable: 
   line 41: 0


public scala.collection.Seq toCollection(java.lang.Object);
  Code:
   Stack=2, Locals=2, Args_size=2
   0:	aload_0
   1:	aload_1
   2:	checkcast	#384; //class scala/collection/LinearSeqLike
   5:	invokeinterface	#393,  2; //InterfaceMethod scala/collection/LinearSeqLike.toCollection:(Lscala/collection/LinearSeqLike;)Lscala/collection/LinearSeq;
   10:	areturn
  LineNumberTable: 
   line 41: 0

  LocalVariableTable: 
   Start  Length  Slot  Name   Signature
   0      11      0    this       Lscala/collection/immutable/Stream;
   0      11      1    repr       Ljava/lang/Object;


public scala.collection.Iterable toCollection(java.lang.Object);
  Code:
   Stack=2, Locals=2, Args_size=2
   0:	aload_0
   1:	aload_1
   2:	checkcast	#384; //class scala/collection/LinearSeqLike
   5:	invokeinterface	#393,  2; //InterfaceMethod scala/collection/LinearSeqLike.toCollection:(Lscala/collection/LinearSeqLike;)Lscala/collection/LinearSeq;
   10:	areturn
  LineNumberTable: 
   line 41: 0

  LocalVariableTable: 
   Start  Length  Slot  Name   Signature
   0      11      0    this       Lscala/collection/immutable/Stream;
   0      11      1    repr       Ljava/lang/Object;


public scala.collection.Traversable toCollection(java.lang.Object);
  Code:
   Stack=2, Locals=2, Args_size=2
   0:	aload_0
   1:	aload_1
   2:	checkcast	#384; //class scala/collection/LinearSeqLike
   5:	invokeinterface	#393,  2; //InterfaceMethod scala/collection/LinearSeqLike.toCollection:(Lscala/collection/LinearSeqLike;)Lscala/collection/LinearSeq;
   10:	areturn
  LineNumberTable: 
   line 41: 0

  LocalVariableTable: 
   Start  Length  Slot  Name   Signature
   0      11      0    this       Lscala/collection/immutable/Stream;
   0      11      1    repr       Ljava/lang/Object;


public java.lang.Object apply(java.lang.Object);
  Code:
   Stack=2, Locals=2, Args_size=2
   0:	aload_0
   1:	aload_1
   2:	invokestatic	#405; //Method scala/runtime/BoxesRunTime.unboxToInt:(Ljava/lang/Object;)I
   5:	invokeinterface	#407,  2; //InterfaceMethod scala/collection/LinearSeqLike.apply:(I)Ljava/lang/Object;
   10:	areturn
  LineNumberTable: 
   line 41: 0

  LocalVariableTable: 
   Start  Length  Slot  Name   Signature
   0      11      0    this       Lscala/collection/immutable/Stream;
   0      11      1    v1       Ljava/lang/Object;


public java.lang.Object drop(int);
  Code:
   Stack=2, Locals=2, Args_size=2
   0:	aload_0
   1:	iload_1
   2:	invokeinterface	#411,  2; //InterfaceMethod scala/collection/LinearSeqLike.drop:(I)Lscala/collection/LinearSeqLike;
   7:	areturn
  LineNumberTable: 
   line 41: 0

  LocalVariableTable: 
   Start  Length  Slot  Name   Signature
   0      8      0    this       Lscala/collection/immutable/Stream;
   0      8      1    n       I


public java.lang.Object dropRight(int);
  Code:
   Stack=2, Locals=2, Args_size=2
   0:	aload_0
   1:	iload_1
   2:	invokeinterface	#414,  2; //InterfaceMethod scala/collection/LinearSeqLike.dropRight:(I)Lscala/collection/LinearSeqLike;
   7:	areturn
  LineNumberTable: 
   line 41: 0

  LocalVariableTable: 
   Start  Length  Slot  Name   Signature
   0      8      0    this       Lscala/collection/immutable/Stream;
   0      8      1    n       I


public boolean isDefinedAt(java.lang.Object);
  Code:
   Stack=2, Locals=2, Args_size=2
   0:	aload_0
   1:	aload_1
   2:	invokestatic	#405; //Method scala/runtime/BoxesRunTime.unboxToInt:(Ljava/lang/Object;)I
   5:	invokeinterface	#419,  2; //InterfaceMethod scala/collection/LinearSeqLike.isDefinedAt:(I)Z
   10:	ireturn
  LineNumberTable: 
   line 41: 0

  LocalVariableTable: 
   Start  Length  Slot  Name   Signature
   0      11      0    this       Lscala/collection/immutable/Stream;
   0      11      1    x       Ljava/lang/Object;


public scala.collection.IterableView view(int, int);
  Code:
   Stack=3, Locals=3, Args_size=3
   0:	aload_0
   1:	iload_1
   2:	iload_2
   3:	invokeinterface	#427,  3; //InterfaceMethod scala/collection/SeqLike.view:(II)Lscala/collection/SeqView;
   8:	areturn
  LineNumberTable: 
   line 41: 0

  LocalVariableTable: 
   Start  Length  Slot  Name   Signature
   0      9      0    this       Lscala/collection/immutable/Stream;
   0      9      1    from       I
   0      9      2    until       I


public scala.collection.TraversableView view(int, int);
  Code:
   Stack=3, Locals=3, Args_size=3
   0:	aload_0
   1:	iload_1
   2:	iload_2
   3:	invokeinterface	#427,  3; //InterfaceMethod scala/collection/SeqLike.view:(II)Lscala/collection/SeqView;
   8:	areturn
  LineNumberTable: 
   line 41: 0

  LocalVariableTable: 
   Start  Length  Slot  Name   Signature
   0      9      0    this       Lscala/collection/immutable/Stream;
   0      9      1    from       I
   0      9      2    until       I


public scala.Function1 andThen(scala.Function1);
  Code:
   Stack=2, Locals=2, Args_size=2
   0:	aload_0
   1:	aload_1
   2:	invokeinterface	#435,  2; //InterfaceMethod scala/PartialFunction.andThen:(Lscala/Function1;)Lscala/PartialFunction;
   7:	areturn
  LineNumberTable: 
   line 41: 0

  LocalVariableTable: 
   Start  Length  Slot  Name   Signature
   0      8      0    this       Lscala/collection/immutable/Stream;
   0      8      1    g       Lscala/Function1;


public scala.collection.immutable.Stream tail();
  Code:
   Stack=1, Locals=1, Args_size=1
   0:	aload_0
   1:	invokeinterface	#248,  1; //InterfaceMethod scala/collection/TraversableLike.tail:()Ljava/lang/Object;
   6:	checkcast	#250; //class scala/collection/immutable/Stream
   9:	areturn
  LineNumberTable: 
   line 41: 0


public scala.collection.LinearSeqLike tail();
  Code:
   Stack=1, Locals=1, Args_size=1
   0:	aload_0
   1:	invokeinterface	#248,  1; //InterfaceMethod scala/collection/TraversableLike.tail:()Ljava/lang/Object;
   6:	checkcast	#384; //class scala/collection/LinearSeqLike
   9:	areturn
  LineNumberTable: 
   line 41: 0


public java.lang.String stringPrefix();
  Code:
   Stack=1, Locals=1, Args_size=1
   0:	ldc_w	#441; //String Stream
   3:	areturn
  LineNumberTable: 
   line 392: 0


public scala.collection.immutable.Stream flatten(scala.Function1);
  Code:
   Stack=3, Locals=2, Args_size=2
   0:	aload_0
   1:	invokeinterface	#277,  1; //InterfaceMethod scala/collection/IterableLike.isEmpty:()Z
   6:	ifeq	15
   9:	getstatic	#287; //Field scala/collection/immutable/Stream$Empty$.MODULE$:Lscala/collection/immutable/Stream$Empty$;
   12:	goto	35
   15:	aload_0
   16:	aload_1
   17:	aload_0
   18:	invokeinterface	#293,  1; //InterfaceMethod scala/collection/IterableLike.head:()Ljava/lang/Object;
   23:	invokeinterface	#445,  2; //InterfaceMethod scala/Function1.apply:(Ljava/lang/Object;)Ljava/lang/Object;
   28:	checkcast	#447; //class scala/collection/Traversable
   31:	aload_1
   32:	invokevirtual	#449; //Method flatten1$1:(Lscala/collection/Traversable;Lscala/Function1;)Lscala/collection/immutable/Stream;
   35:	areturn
  LineNumberTable: 
   line 384: 0
   line 385: 9
   line 387: 15
   line 384: 35

  LocalVariableTable: 
   Start  Length  Slot  Name   Signature
   0      36      0    this       Lscala/collection/immutable/Stream;
   0      36      1    asTraversable$1       Lscala/Function1;

  Signature: length = 0x2
   01 FFFFFFC3 

public scala.collection.immutable.Stream reverse();
  Code:
   Stack=4, Locals=5, Args_size=1
   0:	new	#453; //class scala/runtime/ObjectRef
   3:	dup
   4:	getstatic	#287; //Field scala/collection/immutable/Stream$Empty$.MODULE$:Lscala/collection/immutable/Stream$Empty$;
   7:	invokespecial	#455; //Method scala/runtime/ObjectRef."<init>":(Ljava/lang/Object;)V
   10:	astore_2
   11:	aload_0
   12:	astore	4
   14:	aload	4
   16:	invokeinterface	#277,  1; //InterfaceMethod scala/collection/IterableLike.isEmpty:()Z
   21:	ifeq	32
   24:	aload_2
   25:	getfield	#458; //Field scala/runtime/ObjectRef.elem:Ljava/lang/Object;
   28:	checkcast	#250; //class scala/collection/immutable/Stream
   31:	areturn
   32:	new	#460; //class scala/collection/immutable/Stream$$anonfun$2
   35:	dup
   36:	aload_0
   37:	aload_2
   38:	invokespecial	#463; //Method scala/collection/immutable/Stream$$anonfun$2."<init>":(Lscala/collection/immutable/Stream;Lscala/runtime/ObjectRef;)V
   41:	astore_1
   42:	new	#465; //class scala/collection/immutable/Stream$ConsWrapper
   45:	dup
   46:	aload_1
   47:	invokespecial	#468; //Method scala/collection/immutable/Stream$ConsWrapper."<init>":(Lscala/Function0;)V
   50:	aload	4
   52:	invokeinterface	#293,  1; //InterfaceMethod scala/collection/IterableLike.head:()Ljava/lang/Object;
   57:	invokevirtual	#471; //Method scala/collection/immutable/Stream$ConsWrapper.$hash$colon$colon:(Ljava/lang/Object;)Lscala/collection/immutable/Stream;
   60:	astore_3
   61:	aload_3
   62:	invokeinterface	#248,  1; //InterfaceMethod scala/collection/TraversableLike.tail:()Ljava/lang/Object;
   67:	pop
   68:	aload_2
   69:	aload_3
   70:	putfield	#458; //Field scala/runtime/ObjectRef.elem:Ljava/lang/Object;
   73:	aload	4
   75:	invokeinterface	#248,  1; //InterfaceMethod scala/collection/TraversableLike.tail:()Ljava/lang/Object;
   80:	checkcast	#250; //class scala/collection/immutable/Stream
   83:	astore	4
   85:	goto	14
  LineNumberTable: 
   line 366: 0
   line 367: 11
   line 368: 14
   line 374: 24
   line 369: 32
   line 371: 37
   line 369: 38
   line 370: 61
   line 371: 68
   line 372: 73

  LocalVariableTable: 
   Start  Length  Slot  Name   Signature
   0      88      0    this       Lscala/collection/immutable/Stream;
   11      20      2    result$1       Lscala/runtime/ObjectRef;
   32      56      2    result$1       Lscala/runtime/ObjectRef;
   61      24      3    r       Lscala/collection/immutable/Stream;
   14      17      4    these       Lscala/collection/immutable/Stream;
   32      56      4    these       Lscala/collection/immutable/Stream;

  Signature: length = 0x2
   01 FFFFFFDB 

public java.lang.Object padTo(int, java.lang.Object, scala.collection.generic.CanBuildFrom);
  Code:
   Stack=4, Locals=4, Args_size=4
   0:	aload_0
   1:	iload_1
   2:	aload_0
   3:	aload_2
   4:	invokevirtual	#479; //Method loop$4:(ILscala/collection/immutable/Stream;Ljava/lang/Object;)Lscala/collection/immutable/Stream;
   7:	areturn
  LineNumberTable: 
   line 358: 0

  LocalVariableTable: 
   Start  Length  Slot  Name   Signature
   0      8      0    this       Lscala/collection/immutable/Stream;
   0      8      1    len       I
   0      8      2    elem$2       Ljava/lang/Object;
   0      8      3    bf       Lscala/collection/generic/CanBuildFrom;

  Signature: length = 0x2
   01 FFFFFFE4 

public scala.collection.immutable.Stream removeDuplicates();
  Code:
   Stack=6, Locals=1, Args_size=1
   0:	aload_0
   1:	invokeinterface	#277,  1; //InterfaceMethod scala/collection/IterableLike.isEmpty:()Z
   6:	ifeq	13
   9:	aload_0
   10:	goto	34
   13:	new	#256; //class scala/collection/immutable/Stream$Cons
   16:	dup
   17:	aload_0
   18:	invokeinterface	#293,  1; //InterfaceMethod scala/collection/IterableLike.head:()Ljava/lang/Object;
   23:	new	#486; //class scala/collection/immutable/Stream$$anonfun$removeDuplicates$1
   26:	dup
   27:	aload_0
   28:	invokespecial	#489; //Method scala/collection/immutable/Stream$$anonfun$removeDuplicates$1."<init>":(Lscala/collection/immutable/Stream;)V
   31:	invokespecial	#267; //Method scala/collection/immutable/Stream$Cons."<init>":(Ljava/lang/Object;Lscala/Function0;)V
   34:	areturn
  LineNumberTable: 
   line 348: 0
   line 349: 13
   line 348: 34

  Signature: length = 0x2
   01 FFFFFFDB 

public scala.collection.immutable.Stream dropWhile(scala.Function1);
  Code:
   Stack=2, Locals=3, Args_size=2
   0:	aload_0
   1:	astore_2
   2:	aload_2
   3:	invokeinterface	#277,  1; //InterfaceMethod scala/collection/IterableLike.isEmpty:()Z
   8:	ifne	42
   11:	aload_1
   12:	aload_2
   13:	invokeinterface	#293,  1; //InterfaceMethod scala/collection/IterableLike.head:()Ljava/lang/Object;
   18:	invokeinterface	#445,  2; //InterfaceMethod scala/Function1.apply:(Ljava/lang/Object;)Ljava/lang/Object;
   23:	invokestatic	#492; //Method scala/runtime/BoxesRunTime.unboxToBoolean:(Ljava/lang/Object;)Z
   26:	ifeq	42
   29:	aload_2
   30:	invokeinterface	#248,  1; //InterfaceMethod scala/collection/TraversableLike.tail:()Ljava/lang/Object;
   35:	checkcast	#250; //class scala/collection/immutable/Stream
   38:	astore_2
   39:	goto	2
   42:	aload_2
   43:	areturn
  LineNumberTable: 
   line 339: 0
   line 340: 2
   line 341: 42

  LocalVariableTable: 
   Start  Length  Slot  Name   Signature
   0      44      0    this       Lscala/collection/immutable/Stream;
   0      44      1    p       Lscala/Function1;
   2      41      2    these       Lscala/collection/immutable/Stream;

  Signature: length = 0x2
   01 FFFFFFED 

public scala.collection.immutable.Stream takeWhile(scala.Function1);
  Code:
   Stack=7, Locals=2, Args_size=2
   0:	aload_0
   1:	invokeinterface	#277,  1; //InterfaceMethod scala/collection/IterableLike.isEmpty:()Z
   6:	ifne	52
   9:	aload_1
   10:	aload_0
   11:	invokeinterface	#293,  1; //InterfaceMethod scala/collection/IterableLike.head:()Ljava/lang/Object;
   16:	invokeinterface	#445,  2; //InterfaceMethod scala/Function1.apply:(Ljava/lang/Object;)Ljava/lang/Object;
   21:	invokestatic	#492; //Method scala/runtime/BoxesRunTime.unboxToBoolean:(Ljava/lang/Object;)Z
   24:	ifeq	52
   27:	new	#256; //class scala/collection/immutable/Stream$Cons
   30:	dup
   31:	aload_0
   32:	invokeinterface	#293,  1; //InterfaceMethod scala/collection/IterableLike.head:()Ljava/lang/Object;
   37:	new	#495; //class scala/collection/immutable/Stream$$anonfun$takeWhile$1
   40:	dup
   41:	aload_0
   42:	aload_1
   43:	invokespecial	#498; //Method scala/collection/immutable/Stream$$anonfun$takeWhile$1."<init>":(Lscala/collection/immutable/Stream;Lscala/Function1;)V
   46:	invokespecial	#267; //Method scala/collection/immutable/Stream$Cons."<init>":(Ljava/lang/Object;Lscala/Function0;)V
   49:	goto	55
   52:	getstatic	#287; //Field scala/collection/immutable/Stream$Empty$.MODULE$:Lscala/collection/immutable/Stream$Empty$;
   55:	areturn
  LineNumberTable: 
   line 330: 0
   line 331: 52
   line 330: 55

  LocalVariableTable: 
   Start  Length  Slot  Name   Signature
   0      56      0    this       Lscala/collection/immutable/Stream;
   0      56      1    p$1       Lscala/Function1;

  Signature: length = 0x2
   01 FFFFFFED 

public scala.collection.immutable.Stream takeRight(int);
  Code:
   Stack=2, Locals=4, Args_size=2
   0:	aload_0
   1:	astore_2
   2:	aload_0
   3:	iload_1
   4:	invokeinterface	#411,  2; //InterfaceMethod scala/collection/LinearSeqLike.drop:(I)Lscala/collection/LinearSeqLike;
   9:	checkcast	#250; //class scala/collection/immutable/Stream
   12:	astore_3
   13:	aload_3
   14:	invokeinterface	#277,  1; //InterfaceMethod scala/collection/IterableLike.isEmpty:()Z
   19:	ifeq	24
   22:	aload_2
   23:	areturn
   24:	aload_2
   25:	invokeinterface	#248,  1; //InterfaceMethod scala/collection/TraversableLike.tail:()Ljava/lang/Object;
   30:	checkcast	#250; //class scala/collection/immutable/Stream
   33:	astore_2
   34:	aload_3
   35:	invokeinterface	#248,  1; //InterfaceMethod scala/collection/TraversableLike.tail:()Ljava/lang/Object;
   40:	checkcast	#250; //class scala/collection/immutable/Stream
   43:	astore_3
   44:	goto	13
  LineNumberTable: 
   line 313: 0
   line 314: 2
   line 315: 13
   line 319: 22
   line 316: 24
   line 317: 34

  LocalVariableTable: 
   Start  Length  Slot  Name   Signature
   0      47      0    this       Lscala/collection/immutable/Stream;
   0      47      1    n       I
   2      21      2    these       Lscala/collection/immutable/Stream;
   24      23      2    these       Lscala/collection/immutable/Stream;
   13      10      3    lead       Lscala/collection/immutable/Stream;
   24      23      3    lead       Lscala/collection/immutable/Stream;

  Signature: length = 0x2
   01 FFFFFFF5 

public scala.collection.immutable.Stream init();
  Code:
   Stack=6, Locals=1, Args_size=1
   0:	aload_0
   1:	invokeinterface	#277,  1; //InterfaceMethod scala/collection/IterableLike.isEmpty:()Z
   6:	ifeq	19
   9:	aload_0
   10:	invokestatic	#504; //Method scala/collection/TraversableLike$class.init:(Lscala/collection/TraversableLike;)Ljava/lang/Object;
   13:	checkcast	#250; //class scala/collection/immutable/Stream
   16:	goto	63
   19:	aload_0
   20:	invokeinterface	#248,  1; //InterfaceMethod scala/collection/TraversableLike.tail:()Ljava/lang/Object;
   25:	checkcast	#276; //class scala/collection/IterableLike
   28:	invokeinterface	#277,  1; //InterfaceMethod scala/collection/IterableLike.isEmpty:()Z
   33:	ifeq	42
   36:	getstatic	#287; //Field scala/collection/immutable/Stream$Empty$.MODULE$:Lscala/collection/immutable/Stream$Empty$;
   39:	goto	63
   42:	new	#256; //class scala/collection/immutable/Stream$Cons
   45:	dup
   46:	aload_0
   47:	invokeinterface	#293,  1; //InterfaceMethod scala/collection/IterableLike.head:()Ljava/lang/Object;
   52:	new	#506; //class scala/collection/immutable/Stream$$anonfun$init$1
   55:	dup
   56:	aload_0
   57:	invokespecial	#507; //Method scala/collection/immutable/Stream$$anonfun$init$1."<init>":(Lscala/collection/immutable/Stream;)V
   60:	invokespecial	#267; //Method scala/collection/immutable/Stream$Cons."<init>":(Ljava/lang/Object;Lscala/Function0;)V
   63:	areturn
  LineNumberTable: 
   line 305: 0
   line 306: 19
   line 307: 42
   line 305: 63

  Signature: length = 0x2
   01 FFFFFFDB 

public scala.collection.immutable.Stream slice(int, int);
  Code:
   Stack=2, Locals=4, Args_size=3
   0:	iload_2
   1:	istore_3
   2:	iload_1
   3:	iconst_0
   4:	if_icmple	11
   7:	iload_2
   8:	iload_1
   9:	isub
   10:	istore_3
   11:	aload_0
   12:	iload_1
   13:	invokeinterface	#411,  2; //InterfaceMethod scala/collection/LinearSeqLike.drop:(I)Lscala/collection/LinearSeqLike;
   18:	checkcast	#250; //class scala/collection/immutable/Stream
   21:	iload_3
   22:	invokevirtual	#351; //Method take:(I)Lscala/collection/immutable/Stream;
   25:	areturn
  LineNumberTable: 
   line 296: 0
   line 297: 2
   line 298: 11

  LocalVariableTable: 
   Start  Length  Slot  Name   Signature
   0      26      0    this       Lscala/collection/immutable/Stream;
   0      26      1    start       I
   0      26      2    end       I
   2      23      3    len       I

  Signature: length = 0x2
   01 FFFFFFFD 

public scala.collection.immutable.Stream take(int);
  Code:
   Stack=7, Locals=2, Args_size=2
   0:	iload_1
   1:	iconst_0
   2:	if_icmple	14
   5:	aload_0
   6:	invokeinterface	#277,  1; //InterfaceMethod scala/collection/IterableLike.isEmpty:()Z
   11:	ifeq	20
   14:	getstatic	#287; //Field scala/collection/immutable/Stream$Empty$.MODULE$:Lscala/collection/immutable/Stream$Empty$;
   17:	goto	42
   20:	new	#256; //class scala/collection/immutable/Stream$Cons
   23:	dup
   24:	aload_0
   25:	invokeinterface	#293,  1; //InterfaceMethod scala/collection/IterableLike.head:()Ljava/lang/Object;
   30:	new	#511; //class scala/collection/immutable/Stream$$anonfun$take$1
   33:	dup
   34:	aload_0
   35:	iload_1
   36:	invokespecial	#514; //Method scala/collection/immutable/Stream$$anonfun$take$1."<init>":(Lscala/collection/immutable/Stream;I)V
   39:	invokespecial	#267; //Method scala/collection/immutable/Stream$Cons."<init>":(Ljava/lang/Object;Lscala/Function0;)V
   42:	areturn
  LineNumberTable: 
   line 280: 0
   line 281: 20
   line 280: 42

  LocalVariableTable: 
   Start  Length  Slot  Name   Signature
   0      43      0    this       Lscala/collection/immutable/Stream;
   0      43      1    n$3       I

  Signature: length = 0x2
   01 FFFFFFF5 

public java.lang.String toString();
  Code:
   Stack=4, Locals=1, Args_size=1
   0:	aload_0
   1:	new	#307; //class scala/collection/mutable/StringBuilder
   4:	dup
   5:	invokespecial	#517; //Method scala/collection/mutable/StringBuilder."<init>":()V
   8:	aload_0
   9:	invokevirtual	#519; //Method stringPrefix:()Ljava/lang/String;
   12:	invokevirtual	#522; //Method scala/collection/mutable/StringBuilder.append:(Ljava/lang/Object;)Lscala/collection/mutable/StringBuilder;
   15:	ldc_w	#524; //String (
   18:	invokevirtual	#522; //Method scala/collection/mutable/StringBuilder.append:(Ljava/lang/Object;)Lscala/collection/mutable/StringBuilder;
   21:	invokevirtual	#526; //Method scala/collection/mutable/StringBuilder.toString:()Ljava/lang/String;
   24:	ldc_w	#528; //String , 
   27:	ldc_w	#530; //String )
   30:	invokestatic	#534; //Method scala/collection/TraversableLike$class.mkString:(Lscala/collection/TraversableLike;Ljava/lang/String;Ljava/lang/String;Ljava/lang/String;)Ljava/lang/String;
   33:	areturn
  LineNumberTable: 
   line 271: 0


public java.lang.String mkString();
  Code:
   Stack=1, Locals=1, Args_size=1
   0:	aload_0
   1:	invokevirtual	#537; //Method force:()Lscala/collection/immutable/Stream;
   4:	pop
   5:	aload_0
   6:	invokestatic	#540; //Method scala/collection/TraversableLike$class.mkString:(Lscala/collection/TraversableLike;)Ljava/lang/String;
   9:	areturn
  LineNumberTable: 
   line 267: 0
   line 268: 5


public java.lang.String mkString(java.lang.String);
  Code:
   Stack=2, Locals=2, Args_size=2
   0:	aload_0
   1:	invokevirtual	#537; //Method force:()Lscala/collection/immutable/Stream;
   4:	pop
   5:	aload_0
   6:	aload_1
   7:	invokestatic	#544; //Method scala/collection/TraversableLike$class.mkString:(Lscala/collection/TraversableLike;Ljava/lang/String;)Ljava/lang/String;
   10:	areturn
  LineNumberTable: 
   line 262: 0
   line 263: 5

  LocalVariableTable: 
   Start  Length  Slot  Name   Signature
   0      11      0    this       Lscala/collection/immutable/Stream;
   0      11      1    sep       Ljava/lang/String;


public java.lang.String mkString(java.lang.String, java.lang.String, java.lang.String);
  Code:
   Stack=4, Locals=4, Args_size=4
   0:	aload_0
   1:	invokevirtual	#537; //Method force:()Lscala/collection/immutable/Stream;
   4:	pop
   5:	aload_0
   6:	aload_1
   7:	aload_2
   8:	aload_3
   9:	invokestatic	#534; //Method scala/collection/TraversableLike$class.mkString:(Lscala/collection/TraversableLike;Ljava/lang/String;Ljava/lang/String;Ljava/lang/String;)Ljava/lang/String;
   12:	areturn
  LineNumberTable: 
   line 257: 0
   line 258: 5

  LocalVariableTable: 
   Start  Length  Slot  Name   Signature
   0      13      0    this       Lscala/collection/immutable/Stream;
   0      13      1    start       Ljava/lang/String;
   0      13      2    sep       Ljava/lang/String;
   0      13      3    end       Ljava/lang/String;


public scala.collection.mutable.StringBuilder addString(scala.collection.mutable.StringBuilder, java.lang.String, java.lang.String, java.lang.String);
  Code:
   Stack=6, Locals=5, Args_size=5
   0:	aload_1
   1:	aload_2
   2:	invokevirtual	#311; //Method scala/collection/mutable/StringBuilder.append:(Ljava/lang/String;)Lscala/collection/mutable/StringBuilder;
   5:	pop
   6:	aload_0
   7:	ldc_w	#550; //String 
   10:	aload_0
   11:	aload_1
   12:	aload_3
   13:	aload	4
   15:	invokespecial	#552; //Method loop$3:(Ljava/lang/String;Lscala/collection/immutable/Stream;Lscala/collection/mutable/StringBuilder;Ljava/lang/String;Ljava/lang/String;)V
   18:	aload_1
   19:	areturn
  LineNumberTable: 
   line 251: 0
   line 252: 6
   line 253: 18

  LocalVariableTable: 
   Start  Length  Slot  Name   Signature
   0      20      0    this       Lscala/collection/immutable/Stream;
   0      20      1    b$1       Lscala/collection/mutable/StringBuilder;
   0      20      2    start       Ljava/lang/String;
   0      20      3    sep$2       Ljava/lang/String;
   0      20      4    end$2       Ljava/lang/String;


public java.lang.Object zipWithIndex(scala.collection.generic.CanBuildFrom);
  Code:
   Stack=3, Locals=2, Args_size=2
   0:	aload_0
   1:	getstatic	#11; //Field scala/collection/immutable/Stream$.MODULE$:Lscala/collection/immutable/Stream$;
   4:	iconst_0
   5:	invokevirtual	#61; //Method scala/collection/immutable/Stream$.from:(I)Lscala/collection/immutable/Stream;
   8:	aload_1
   9:	invokevirtual	#562; //Method zip:(Lscala/collection/Iterable;Lscala/collection/generic/CanBuildFrom;)Ljava/lang/Object;
   12:	areturn
  LineNumberTable: 
   line 233: 0

  LocalVariableTable: 
   Start  Length  Slot  Name   Signature
   0      13      0    this       Lscala/collection/immutable/Stream;
   0      13      1    bf       Lscala/collection/generic/CanBuildFrom;

  Signature: length = 0x2
   02 33 

public final java.lang.Object zip(scala.collection.Iterable, scala.collection.generic.CanBuildFrom);
  Code:
   Stack=8, Locals=3, Args_size=3
   0:	aload_0
   1:	invokeinterface	#277,  1; //InterfaceMethod scala/collection/IterableLike.isEmpty:()Z
   6:	ifne	18
   9:	aload_1
   10:	invokeinterface	#277,  1; //InterfaceMethod scala/collection/IterableLike.isEmpty:()Z
   15:	ifeq	24
   18:	getstatic	#287; //Field scala/collection/immutable/Stream$Empty$.MODULE$:Lscala/collection/immutable/Stream$Empty$;
   21:	goto	60
   24:	new	#256; //class scala/collection/immutable/Stream$Cons
   27:	dup
   28:	new	#565; //class scala/Tuple2
   31:	dup
   32:	aload_0
   33:	invokeinterface	#293,  1; //InterfaceMethod scala/collection/IterableLike.head:()Ljava/lang/Object;
   38:	aload_1
   39:	invokeinterface	#293,  1; //InterfaceMethod scala/collection/IterableLike.head:()Ljava/lang/Object;
   44:	invokespecial	#568; //Method scala/Tuple2."<init>":(Ljava/lang/Object;Ljava/lang/Object;)V
   47:	new	#570; //class scala/collection/immutable/Stream$$anonfun$zip$1
   50:	dup
   51:	aload_0
   52:	aload_1
   53:	aload_2
   54:	invokespecial	#573; //Method scala/collection/immutable/Stream$$anonfun$zip$1."<init>":(Lscala/collection/immutable/Stream;Lscala/collection/Iterable;Lscala/collection/generic/CanBuildFrom;)V
   57:	invokespecial	#267; //Method scala/collection/immutable/Stream$Cons."<init>":(Ljava/lang/Object;Lscala/Function0;)V
   60:	areturn
  LineNumberTable: 
   line 225: 0
   line 226: 24
   line 225: 60

  LocalVariableTable: 
   Start  Length  Slot  Name   Signature
   0      61      0    this       Lscala/collection/immutable/Stream;
   0      61      1    that$2       Lscala/collection/Iterable;
   0      61      2    bf$3       Lscala/collection/generic/CanBuildFrom;

  Signature: length = 0x2
   02 41 

public scala.Tuple2 partition(scala.Function1);
  Code:
   Stack=10, Locals=4, Args_size=2
   0:	new	#565; //class scala/Tuple2
   3:	dup
   4:	new	#581; //class scala/collection/immutable/Stream$$anonfun$partition$1
   7:	dup
   8:	aload_0
   9:	aload_1
   10:	invokespecial	#582; //Method scala/collection/immutable/Stream$$anonfun$partition$1."<init>":(Lscala/collection/immutable/Stream;Lscala/Function1;)V
   13:	astore_2
   14:	new	#453; //class scala/runtime/ObjectRef
   17:	dup
   18:	aload_0
   19:	new	#584; //class scala/collection/immutable/Stream$$anonfun$1
   22:	dup
   23:	aload_0
   24:	aload_2
   25:	invokespecial	#585; //Method scala/collection/immutable/Stream$$anonfun$1."<init>":(Lscala/collection/immutable/Stream;Lscala/Function1;)V
   28:	invokevirtual	#372; //Method dropWhile:(Lscala/Function1;)Lscala/collection/immutable/Stream;
   31:	invokespecial	#455; //Method scala/runtime/ObjectRef."<init>":(Ljava/lang/Object;)V
   34:	astore_3
   35:	aload_3
   36:	getfield	#458; //Field scala/runtime/ObjectRef.elem:Ljava/lang/Object;
   39:	checkcast	#250; //class scala/collection/immutable/Stream
   42:	invokeinterface	#277,  1; //InterfaceMethod scala/collection/IterableLike.isEmpty:()Z
   47:	ifeq	56
   50:	getstatic	#287; //Field scala/collection/immutable/Stream$Empty$.MODULE$:Lscala/collection/immutable/Stream$Empty$;
   53:	goto	85
   56:	new	#256; //class scala/collection/immutable/Stream$Cons
   59:	dup
   60:	aload_3
   61:	getfield	#458; //Field scala/runtime/ObjectRef.elem:Ljava/lang/Object;
   64:	checkcast	#250; //class scala/collection/immutable/Stream
   67:	invokeinterface	#293,  1; //InterfaceMethod scala/collection/IterableLike.head:()Ljava/lang/Object;
   72:	new	#587; //class scala/collection/immutable/Stream$$anonfun$filter$1
   75:	dup
   76:	aload_0
   77:	aload_2
   78:	aload_3
   79:	invokespecial	#590; //Method scala/collection/immutable/Stream$$anonfun$filter$1."<init>":(Lscala/collection/immutable/Stream;Lscala/Function1;Lscala/runtime/ObjectRef;)V
   82:	invokespecial	#267; //Method scala/collection/immutable/Stream$Cons."<init>":(Ljava/lang/Object;Lscala/Function0;)V
   85:	aload_0
   86:	new	#592; //class scala/collection/immutable/Stream$$anonfun$partition$2
   89:	dup
   90:	aload_0
   91:	aload_1
   92:	invokespecial	#593; //Method scala/collection/immutable/Stream$$anonfun$partition$2."<init>":(Lscala/collection/immutable/Stream;Lscala/Function1;)V
   95:	invokeinterface	#596,  2; //InterfaceMethod scala/collection/TraversableLike.filterNot:(Lscala/Function1;)Ljava/lang/Object;
   100:	invokespecial	#568; //Method scala/Tuple2."<init>":(Ljava/lang/Object;Ljava/lang/Object;)V
   103:	areturn
  LineNumberTable: 
   line 211: 0

  LocalVariableTable: 
   Start  Length  Slot  Name   Signature
   0      104      0    this       Lscala/collection/immutable/Stream;
   0      104      1    p$2       Lscala/Function1;
   50      54      2    p$30       Lscala/Function1;
   35      69      3    rest$20       Lscala/runtime/ObjectRef;

  Signature: length = 0x2
   02 58 

public final java.lang.Object foldLeft(java.lang.Object, scala.Function2);
  Code:
   Stack=4, Locals=3, Args_size=3
   0:	aload_0
   1:	invokeinterface	#277,  1; //InterfaceMethod scala/collection/IterableLike.isEmpty:()Z
   6:	ifeq	11
   9:	aload_1
   10:	areturn
   11:	aload_0
   12:	invokeinterface	#248,  1; //InterfaceMethod scala/collection/TraversableLike.tail:()Ljava/lang/Object;
   17:	checkcast	#250; //class scala/collection/immutable/Stream
   20:	aload_2
   21:	aload_1
   22:	aload_0
   23:	invokeinterface	#293,  1; //InterfaceMethod scala/collection/IterableLike.head:()Ljava/lang/Object;
   28:	invokeinterface	#607,  3; //InterfaceMethod scala/Function2.apply:(Ljava/lang/Object;Ljava/lang/Object;)Ljava/lang/Object;
   33:	astore_1
   34:	astore_0
   35:	goto	0
  LineNumberTable: 
   line 201: 0
   line 200: 10
   line 202: 11

  LocalVariableTable: 
   Start  Length  Slot  Name   Signature
   0      38      0    this       Lscala/collection/immutable/Stream;
   0      38      1    z       Ljava/lang/Object;
   0      38      2    op       Lscala/Function2;

  Signature: length = 0x2
   02 63 

public final void foreach(scala.Function1);
  Code:
   Stack=2, Locals=2, Args_size=2
   0:	aload_0
   1:	invokeinterface	#277,  1; //InterfaceMethod scala/collection/IterableLike.isEmpty:()Z
   6:	ifeq	10
   9:	return
   10:	aload_1
   11:	aload_0
   12:	invokeinterface	#293,  1; //InterfaceMethod scala/collection/IterableLike.head:()Ljava/lang/Object;
   17:	invokeinterface	#445,  2; //InterfaceMethod scala/Function1.apply:(Ljava/lang/Object;)Ljava/lang/Object;
   22:	pop
   23:	aload_0
   24:	invokeinterface	#248,  1; //InterfaceMethod scala/collection/TraversableLike.tail:()Ljava/lang/Object;
   29:	checkcast	#250; //class scala/collection/immutable/Stream
   32:	astore_0
   33:	goto	0
  LineNumberTable: 
   line 190: 0
   line 189: 9
   line 191: 10
   line 192: 23

  LocalVariableTable: 
   Start  Length  Slot  Name   Signature
   0      36      0    this       Lscala/collection/immutable/Stream;
   0      36      1    f       Lscala/Function1;

  Signature: length = 0x2
   02 66 

public final scala.collection.immutable.Stream filter(scala.Function1);
  Code:
   Stack=8, Locals=3, Args_size=2
   0:	new	#453; //class scala/runtime/ObjectRef
   3:	dup
   4:	aload_0
   5:	new	#584; //class scala/collection/immutable/Stream$$anonfun$1
   8:	dup
   9:	aload_0
   10:	aload_1
   11:	invokespecial	#585; //Method scala/collection/immutable/Stream$$anonfun$1."<init>":(Lscala/collection/immutable/Stream;Lscala/Function1;)V
   14:	invokevirtual	#372; //Method dropWhile:(Lscala/Function1;)Lscala/collection/immutable/Stream;
   17:	invokespecial	#455; //Method scala/runtime/ObjectRef."<init>":(Ljava/lang/Object;)V
   20:	astore_2
   21:	aload_2
   22:	getfield	#458; //Field scala/runtime/ObjectRef.elem:Ljava/lang/Object;
   25:	checkcast	#250; //class scala/collection/immutable/Stream
   28:	invokeinterface	#277,  1; //InterfaceMethod scala/collection/IterableLike.isEmpty:()Z
   33:	ifeq	42
   36:	getstatic	#287; //Field scala/collection/immutable/Stream$Empty$.MODULE$:Lscala/collection/immutable/Stream$Empty$;
   39:	goto	71
   42:	new	#256; //class scala/collection/immutable/Stream$Cons
   45:	dup
   46:	aload_2
   47:	getfield	#458; //Field scala/runtime/ObjectRef.elem:Ljava/lang/Object;
   50:	checkcast	#250; //class scala/collection/immutable/Stream
   53:	invokeinterface	#293,  1; //InterfaceMethod scala/collection/IterableLike.head:()Ljava/lang/Object;
   58:	new	#587; //class scala/collection/immutable/Stream$$anonfun$filter$1
   61:	dup
   62:	aload_0
   63:	aload_1
   64:	aload_2
   65:	invokespecial	#590; //Method scala/collection/immutable/Stream$$anonfun$filter$1."<init>":(Lscala/collection/immutable/Stream;Lscala/Function1;Lscala/runtime/ObjectRef;)V
   68:	invokespecial	#267; //Method scala/collection/immutable/Stream$Cons."<init>":(Ljava/lang/Object;Lscala/Function0;)V
   71:	areturn
  LineNumberTable: 
   line 174: 0
   line 175: 21
   line 176: 42
   line 172: 71

  LocalVariableTable: 
   Start  Length  Slot  Name   Signature
   0      72      0    this       Lscala/collection/immutable/Stream;
   0      72      1    p$3       Lscala/Function1;
   21      51      2    rest$2       Lscala/runtime/ObjectRef;

  Signature: length = 0x2
   01 FFFFFFED 

public final java.lang.Object flatMap(scala.Function1, scala.collection.generic.CanBuildFrom);
  Code:
   Stack=7, Locals=5, Args_size=3
   0:	aload_0
   1:	invokeinterface	#277,  1; //InterfaceMethod scala/collection/IterableLike.isEmpty:()Z
   6:	ifeq	15
   9:	getstatic	#287; //Field scala/collection/immutable/Stream$Empty$.MODULE$:Lscala/collection/immutable/Stream$Empty$;
   12:	goto	184
   15:	new	#453; //class scala/runtime/ObjectRef
   18:	dup
   19:	aload_0
   20:	invokespecial	#455; //Method scala/runtime/ObjectRef."<init>":(Ljava/lang/Object;)V
   23:	astore	4
   25:	aload_1
   26:	aload	4
   28:	getfield	#458; //Field scala/runtime/ObjectRef.elem:Ljava/lang/Object;
   31:	checkcast	#250; //class scala/collection/immutable/Stream
   34:	invokeinterface	#293,  1; //InterfaceMethod scala/collection/IterableLike.head:()Ljava/lang/Object;
   39:	invokeinterface	#445,  2; //InterfaceMethod scala/Function1.apply:(Ljava/lang/Object;)Ljava/lang/Object;
   44:	checkcast	#240; //class scala/collection/TraversableLike
   47:	invokeinterface	#621,  1; //InterfaceMethod scala/collection/TraversableLike.toStream:()Lscala/collection/immutable/Stream;
   52:	astore_3
   53:	aload	4
   55:	getfield	#458; //Field scala/runtime/ObjectRef.elem:Ljava/lang/Object;
   58:	checkcast	#250; //class scala/collection/immutable/Stream
   61:	invokeinterface	#277,  1; //InterfaceMethod scala/collection/IterableLike.isEmpty:()Z
   66:	ifne	146
   69:	aload_3
   70:	invokeinterface	#277,  1; //InterfaceMethod scala/collection/IterableLike.isEmpty:()Z
   75:	ifeq	146
   78:	aload	4
   80:	aload	4
   82:	getfield	#458; //Field scala/runtime/ObjectRef.elem:Ljava/lang/Object;
   85:	checkcast	#250; //class scala/collection/immutable/Stream
   88:	invokeinterface	#248,  1; //InterfaceMethod scala/collection/TraversableLike.tail:()Ljava/lang/Object;
   93:	checkcast	#250; //class scala/collection/immutable/Stream
   96:	putfield	#458; //Field scala/runtime/ObjectRef.elem:Ljava/lang/Object;
   99:	aload	4
   101:	getfield	#458; //Field scala/runtime/ObjectRef.elem:Ljava/lang/Object;
   104:	checkcast	#250; //class scala/collection/immutable/Stream
   107:	invokeinterface	#277,  1; //InterfaceMethod scala/collection/IterableLike.isEmpty:()Z
   112:	ifne	53
   115:	aload_1
   116:	aload	4
   118:	getfield	#458; //Field scala/runtime/ObjectRef.elem:Ljava/lang/Object;
   121:	checkcast	#250; //class scala/collection/immutable/Stream
   124:	invokeinterface	#293,  1; //InterfaceMethod scala/collection/IterableLike.head:()Ljava/lang/Object;
   129:	invokeinterface	#445,  2; //InterfaceMethod scala/Function1.apply:(Ljava/lang/Object;)Ljava/lang/Object;
   134:	checkcast	#240; //class scala/collection/TraversableLike
   137:	invokeinterface	#621,  1; //InterfaceMethod scala/collection/TraversableLike.toStream:()Lscala/collection/immutable/Stream;
   142:	astore_3
   143:	goto	53
   146:	aload	4
   148:	getfield	#458; //Field scala/runtime/ObjectRef.elem:Ljava/lang/Object;
   151:	checkcast	#250; //class scala/collection/immutable/Stream
   154:	invokeinterface	#277,  1; //InterfaceMethod scala/collection/IterableLike.isEmpty:()Z
   159:	ifeq	168
   162:	getstatic	#287; //Field scala/collection/immutable/Stream$Empty$.MODULE$:Lscala/collection/immutable/Stream$Empty$;
   165:	goto	184
   168:	aload_3
   169:	new	#623; //class scala/collection/immutable/Stream$$anonfun$flatMap$1
   172:	dup
   173:	aload_0
   174:	aload_1
   175:	aload_2
   176:	aload	4
   178:	invokespecial	#626; //Method scala/collection/immutable/Stream$$anonfun$flatMap$1."<init>":(Lscala/collection/immutable/Stream;Lscala/Function1;Lscala/collection/generic/CanBuildFrom;Lscala/runtime/ObjectRef;)V
   181:	invokevirtual	#628; //Method append:(Lscala/Function0;)Lscala/collection/immutable/Stream;
   184:	areturn
  LineNumberTable: 
   line 151: 0
   line 154: 15
   line 155: 25
   line 156: 53
   line 158: 78
   line 157: 80
   line 158: 99
   line 159: 115
   line 162: 146
   line 163: 168
   line 151: 184

  LocalVariableTable: 
   Start  Length  Slot  Name   Signature
   0      185      0    this       Lscala/collection/immutable/Stream;
   0      185      1    f$4       Lscala/Function1;
   0      185      2    bf$4       Lscala/collection/generic/CanBuildFrom;
   53      131      3    prefix       Lscala/collection/immutable/Stream;
   25      159      4    nonEmptyPrefix$1       Lscala/runtime/ObjectRef;

  Signature: length = 0x2
   02 79 

public final java.lang.Object map(scala.Function1, scala.collection.generic.CanBuildFrom);
  Code:
   Stack=8, Locals=3, Args_size=3
   0:	aload_0
   1:	invokeinterface	#277,  1; //InterfaceMethod scala/collection/IterableLike.isEmpty:()Z
   6:	ifeq	15
   9:	getstatic	#287; //Field scala/collection/immutable/Stream$Empty$.MODULE$:Lscala/collection/immutable/Stream$Empty$;
   12:	goto	44
   15:	new	#256; //class scala/collection/immutable/Stream$Cons
   18:	dup
   19:	aload_1
   20:	aload_0
   21:	invokeinterface	#293,  1; //InterfaceMethod scala/collection/IterableLike.head:()Ljava/lang/Object;
   26:	invokeinterface	#445,  2; //InterfaceMethod scala/Function1.apply:(Ljava/lang/Object;)Ljava/lang/Object;
   31:	new	#636; //class scala/collection/immutable/Stream$$anonfun$map$1
   34:	dup
   35:	aload_0
   36:	aload_1
   37:	aload_2
   38:	invokespecial	#639; //Method scala/collection/immutable/Stream$$anonfun$map$1."<init>":(Lscala/collection/immutable/Stream;Lscala/Function1;Lscala/collection/generic/CanBuildFrom;)V
   41:	invokespecial	#267; //Method scala/collection/immutable/Stream$Cons."<init>":(Ljava/lang/Object;Lscala/Function0;)V
   44:	areturn
  LineNumberTable: 
   line 136: 0
   line 137: 15
   line 136: 44

  LocalVariableTable: 
   Start  Length  Slot  Name   Signature
   0      45      0    this       Lscala/collection/immutable/Stream;
   0      45      1    f$3       Lscala/Function1;
   0      45      2    bf$2       Lscala/collection/generic/CanBuildFrom;

  Signature: length = 0x2
   02 FFFFFF82 

public java.lang.Object $plus$plus(scala.collection.Iterator, scala.collection.generic.CanBuildFrom);
  Code:
   Stack=3, Locals=3, Args_size=3
   0:	aload_0
   1:	aload_1
   2:	invokeinterface	#647,  1; //InterfaceMethod scala/collection/Iterator.toStream:()Lscala/collection/immutable/Stream;
   7:	aload_2
   8:	invokevirtual	#650; //Method $plus$plus:(Lscala/collection/Traversable;Lscala/collection/generic/CanBuildFrom;)Ljava/lang/Object;
   11:	areturn
  LineNumberTable: 
   line 126: 0

  LocalVariableTable: 
   Start  Length  Slot  Name   Signature
   0      12      0    this       Lscala/collection/immutable/Stream;
   0      12      1    that       Lscala/collection/Iterator;
   0      12      2    bf       Lscala/collection/generic/CanBuildFrom;

  Signature: length = 0x2
   02 FFFFFF8D 

public java.lang.Object $plus$plus(scala.collection.Traversable, scala.collection.generic.CanBuildFrom);
  Code:
   Stack=8, Locals=3, Args_size=3
   0:	aload_0
   1:	invokeinterface	#277,  1; //InterfaceMethod scala/collection/IterableLike.isEmpty:()Z
   6:	ifeq	18
   9:	aload_1
   10:	invokeinterface	#621,  1; //InterfaceMethod scala/collection/TraversableLike.toStream:()Lscala/collection/immutable/Stream;
   15:	goto	41
   18:	new	#256; //class scala/collection/immutable/Stream$Cons
   21:	dup
   22:	aload_0
   23:	invokeinterface	#293,  1; //InterfaceMethod scala/collection/IterableLike.head:()Ljava/lang/Object;
   28:	new	#655; //class scala/collection/immutable/Stream$$anonfun$$plus$plus$1
   31:	dup
   32:	aload_0
   33:	aload_1
   34:	aload_2
   35:	invokespecial	#658; //Method scala/collection/immutable/Stream$$anonfun$$plus$plus$1."<init>":(Lscala/collection/immutable/Stream;Lscala/collection/Traversable;Lscala/collection/generic/CanBuildFrom;)V
   38:	invokespecial	#267; //Method scala/collection/immutable/Stream$Cons."<init>":(Ljava/lang/Object;Lscala/Function0;)V
   41:	areturn
  LineNumberTable: 
   line 118: 0
   line 119: 18
   line 118: 41

  LocalVariableTable: 
   Start  Length  Slot  Name   Signature
   0      42      0    this       Lscala/collection/immutable/Stream;
   0      42      1    that$1       Lscala/collection/Traversable;
   0      42      2    bf$1       Lscala/collection/generic/CanBuildFrom;

  Signature: length = 0x2
   02 FFFFFF95 

public boolean hasDefiniteSize();
  Code:
   Stack=2, Locals=1, Args_size=1
   0:	aload_0
   1:	aload_0
   2:	invokespecial	#664; //Method loop$2:(Lscala/collection/immutable/Stream;)Z
   5:	ireturn
  LineNumberTable: 
   line 106: 0


public scala.collection.immutable.Stream toStream();
  Code:
   Stack=1, Locals=1, Args_size=1
   0:	aload_0
   1:	areturn
  LineNumberTable: 
   line 102: 0

  Signature: length = 0x2
   01 FFFFFFDB 

public void print(java.lang.String);
  Code:
   Stack=4, Locals=2, Args_size=2
   0:	aload_0
   1:	aload_0
   2:	ldc_w	#550; //String 
   5:	aload_1
   6:	invokespecial	#667; //Method loop$1:(Lscala/collection/immutable/Stream;Ljava/lang/String;Ljava/lang/String;)V
   9:	return
  LineNumberTable: 
   line 97: 0

  LocalVariableTable: 
   Start  Length  Slot  Name   Signature
   0      10      0    this       Lscala/collection/immutable/Stream;
   0      10      1    sep$1       Ljava/lang/String;


public void print();
  Code:
   Stack=2, Locals=1, Args_size=1
   0:	aload_0
   1:	ldc_w	#528; //String , 
   4:	invokevirtual	#670; //Method print:(Ljava/lang/String;)V
   7:	return
  LineNumberTable: 
   line 83: 0


public scala.collection.immutable.Stream force();
  Code:
   Stack=1, Locals=2, Args_size=1
   0:	aload_0
   1:	astore_1
   2:	aload_1
   3:	invokeinterface	#277,  1; //InterfaceMethod scala/collection/IterableLike.isEmpty:()Z
   8:	ifeq	13
   11:	aload_0
   12:	areturn
   13:	aload_1
   14:	invokeinterface	#248,  1; //InterfaceMethod scala/collection/TraversableLike.tail:()Ljava/lang/Object;
   19:	checkcast	#250; //class scala/collection/immutable/Stream
   22:	astore_1
   23:	goto	2
  LineNumberTable: 
   line 77: 0
   line 78: 2
   line 79: 11
   line 78: 13

  LocalVariableTable: 
   Start  Length  Slot  Name   Signature
   0      26      0    this       Lscala/collection/immutable/Stream;
   2      10      1    these       Lscala/collection/immutable/Stream;
   13      13      1    these       Lscala/collection/immutable/Stream;

  Signature: length = 0x2
   01 FFFFFFDB 

public scala.collection.immutable.Stream append(scala.Function0);
  Code:
   Stack=7, Locals=2, Args_size=2
   0:	aload_0
   1:	invokeinterface	#277,  1; //InterfaceMethod scala/collection/IterableLike.isEmpty:()Z
   6:	ifeq	26
   9:	aload_1
   10:	invokeinterface	#674,  1; //InterfaceMethod scala/Function0.apply:()Ljava/lang/Object;
   15:	checkcast	#240; //class scala/collection/TraversableLike
   18:	invokeinterface	#621,  1; //InterfaceMethod scala/collection/TraversableLike.toStream:()Lscala/collection/immutable/Stream;
   23:	goto	48
   26:	new	#256; //class scala/collection/immutable/Stream$Cons
   29:	dup
   30:	aload_0
   31:	invokeinterface	#293,  1; //InterfaceMethod scala/collection/IterableLike.head:()Ljava/lang/Object;
   36:	new	#676; //class scala/collection/immutable/Stream$$anonfun$append$1
   39:	dup
   40:	aload_0
   41:	aload_1
   42:	invokespecial	#679; //Method scala/collection/immutable/Stream$$anonfun$append$1."<init>":(Lscala/collection/immutable/Stream;Lscala/Function0;)V
   45:	invokespecial	#267; //Method scala/collection/immutable/Stream$Cons."<init>":(Ljava/lang/Object;Lscala/Function0;)V
   48:	areturn
  LineNumberTable: 
   line 73: 0

  LocalVariableTable: 
   Start  Length  Slot  Name   Signature
   0      49      0    this       Lscala/collection/immutable/Stream;
   0      49      1    rest$1       Lscala/Function0;

  Signature: length = 0x2
   02 FFFFFFA9 

public abstract boolean tailDefined();

public abstract java.lang.Object head();
  Signature: length = 0x2
   02 FFFFFFAA 

public abstract boolean isEmpty();

public scala.collection.generic.GenericCompanion companion();
  Code:
   Stack=1, Locals=1, Args_size=1
   0:	getstatic	#11; //Field scala/collection/immutable/Stream$.MODULE$:Lscala/collection/immutable/Stream$;
   3:	areturn
  LineNumberTable: 
   line 45: 0

  Signature: length = 0x2
   02 FFFFFFAD 

public scala.collection.TraversableLike$WithFilter withFilter(scala.Function1);
  Code:
   Stack=2, Locals=2, Args_size=2
   0:	aload_0
   1:	aload_1
   2:	invokestatic	#690; //Method scala/collection/TraversableLike$class.withFilter:(Lscala/collection/TraversableLike;Lscala/Function1;)Lscala/collection/TraversableLike$WithFilter;
   5:	areturn
  LineNumberTable: 
   line 41: 0

  LocalVariableTable: 
   Start  Length  Slot  Name   Signature
   0      6      0    this       Lscala/collection/immutable/Stream;
   0      6      1    p       Lscala/Function1;

  Signature: length = 0x2
   02 FFFFFFAF 

public scala.collection.mutable.StringBuilder addString(scala.collection.mutable.StringBuilder);
  Code:
   Stack=2, Locals=2, Args_size=2
   0:	aload_0
   1:	aload_1
   2:	invokestatic	#694; //Method scala/collection/TraversableLike$class.addString:(Lscala/collection/TraversableLike;Lscala/collection/mutable/StringBuilder;)Lscala/collection/mutable/StringBuilder;
   5:	areturn
  LineNumberTable: 
   line 41: 0

  LocalVariableTable: 
   Start  Length  Slot  Name   Signature
   0      6      0    this       Lscala/collection/immutable/Stream;
   0      6      1    b       Lscala/collection/mutable/StringBuilder;


public scala.collection.mutable.StringBuilder addString(scala.collection.mutable.StringBuilder, java.lang.String);
  Code:
   Stack=3, Locals=3, Args_size=3
   0:	aload_0
   1:	aload_1
   2:	aload_2
   3:	invokestatic	#699; //Method scala/collection/TraversableLike$class.addString:(Lscala/collection/TraversableLike;Lscala/collection/mutable/StringBuilder;Ljava/lang/String;)Lscala/collection/mutable/StringBuilder;
   6:	areturn
  LineNumberTable: 
   line 41: 0

  LocalVariableTable: 
   Start  Length  Slot  Name   Signature
   0      7      0    this       Lscala/collection/immutable/Stream;
   0      7      1    b       Lscala/collection/mutable/StringBuilder;
   0      7      2    sep       Ljava/lang/String;


public scala.collection.immutable.Set toSet();
  Code:
   Stack=1, Locals=1, Args_size=1
   0:	aload_0
   1:	invokestatic	#704; //Method scala/collection/TraversableLike$class.toSet:(Lscala/collection/TraversableLike;)Lscala/collection/immutable/Set;
   4:	areturn
  LineNumberTable: 
   line 41: 0


public scala.collection.mutable.IndexedSeq toIndexedSeq();
  Code:
   Stack=1, Locals=1, Args_size=1
   0:	aload_0
   1:	invokestatic	#709; //Method scala/collection/TraversableLike$class.toIndexedSeq:(Lscala/collection/TraversableLike;)Lscala/collection/mutable/IndexedSeq;
   4:	areturn
  LineNumberTable: 
   line 41: 0


public scala.collection.immutable.List toList();
  Code:
   Stack=1, Locals=1, Args_size=1
   0:	aload_0
   1:	invokestatic	#714; //Method scala/collection/TraversableLike$class.toList:(Lscala/collection/TraversableLike;)Lscala/collection/immutable/List;
   4:	areturn
  LineNumberTable: 
   line 41: 0


public java.lang.Object toArray(scala.reflect.ClassManifest);
  Code:
   Stack=2, Locals=2, Args_size=2
   0:	aload_0
   1:	aload_1
   2:	invokestatic	#719; //Method scala/collection/TraversableLike$class.toArray:(Lscala/collection/TraversableLike;Lscala/reflect/ClassManifest;)Ljava/lang/Object;
   5:	areturn
  LineNumberTable: 
   line 41: 0

  LocalVariableTable: 
   Start  Length  Slot  Name   Signature
   0      6      0    this       Lscala/collection/immutable/Stream;
   0      6      1    evidence$1       Lscala/reflect/ClassManifest;


public void copyToArray(java.lang.Object, int);
  Code:
   Stack=3, Locals=3, Args_size=3
   0:	aload_0
   1:	aload_1
   2:	iload_2
   3:	invokestatic	#726; //Method scala/collection/TraversableLike$class.copyToArray:(Lscala/collection/TraversableLike;Ljava/lang/Object;I)V
   6:	return
  LineNumberTable: 
   line 41: 0

  LocalVariableTable: 
   Start  Length  Slot  Name   Signature
   0      7      0    this       Lscala/collection/immutable/Stream;
   0      7      1    xs       Ljava/lang/Object;
   0      7      2    start       I


public void copyToBuffer(scala.collection.mutable.Buffer);
  Code:
   Stack=2, Locals=2, Args_size=2
   0:	aload_0
   1:	aload_1
   2:	invokestatic	#732; //Method scala/collection/TraversableLike$class.copyToBuffer:(Lscala/collection/TraversableLike;Lscala/collection/mutable/Buffer;)V
   5:	return
  LineNumberTable: 
   line 41: 0

  LocalVariableTable: 
   Start  Length  Slot  Name   Signature
   0      6      0    this       Lscala/collection/immutable/Stream;
   0      6      1    dest       Lscala/collection/mutable/Buffer;


public scala.Tuple2 splitAt(int);
  Code:
   Stack=2, Locals=2, Args_size=2
   0:	aload_0
   1:	iload_1
   2:	invokestatic	#739; //Method scala/collection/TraversableLike$class.splitAt:(Lscala/collection/TraversableLike;I)Lscala/Tuple2;
   5:	areturn
  LineNumberTable: 
   line 41: 0

  LocalVariableTable: 
   Start  Length  Slot  Name   Signature
   0      6      0    this       Lscala/collection/immutable/Stream;
   0      6      1    n       I


public scala.Option lastOption();
  Code:
   Stack=1, Locals=1, Args_size=1
   0:	aload_0
   1:	invokestatic	#744; //Method scala/collection/TraversableLike$class.lastOption:(Lscala/collection/TraversableLike;)Lscala/Option;
   4:	areturn
  LineNumberTable: 
   line 41: 0


public java.lang.Object tail();
  Code:
   Stack=1, Locals=1, Args_size=1
   0:	aload_0
   1:	invokestatic	#746; //Method scala/collection/TraversableLike$class.tail:(Lscala/collection/TraversableLike;)Ljava/lang/Object;
   4:	areturn
  LineNumberTable: 
   line 41: 0


public scala.Option headOption();
  Code:
   Stack=1, Locals=1, Args_size=1
   0:	aload_0
   1:	invokestatic	#749; //Method scala/collection/TraversableLike$class.headOption:(Lscala/collection/TraversableLike;)Lscala/Option;
   4:	areturn
  LineNumberTable: 
   line 41: 0


public java.lang.Object max(scala.math.Ordering);
  Code:
   Stack=2, Locals=2, Args_size=2
   0:	aload_0
   1:	aload_1
   2:	invokestatic	#754; //Method scala/collection/TraversableLike$class.max:(Lscala/collection/TraversableLike;Lscala/math/Ordering;)Ljava/lang/Object;
   5:	areturn
  LineNumberTable: 
   line 41: 0

  LocalVariableTable: 
   Start  Length  Slot  Name   Signature
   0      6      0    this       Lscala/collection/immutable/Stream;
   0      6      1    cmp       Lscala/math/Ordering;


public java.lang.Object min(scala.math.Ordering);
  Code:
   Stack=2, Locals=2, Args_size=2
   0:	aload_0
   1:	aload_1
   2:	invokestatic	#759; //Method scala/collection/TraversableLike$class.min:(Lscala/collection/TraversableLike;Lscala/math/Ordering;)Ljava/lang/Object;
   5:	areturn
  LineNumberTable: 
   line 41: 0

  LocalVariableTable: 
   Start  Length  Slot  Name   Signature
   0      6      0    this       Lscala/collection/immutable/Stream;
   0      6      1    cmp       Lscala/math/Ordering;


public java.lang.Object product(scala.math.Numeric);
  Code:
   Stack=2, Locals=2, Args_size=2
   0:	aload_0
   1:	aload_1
   2:	invokestatic	#764; //Method scala/collection/TraversableLike$class.product:(Lscala/collection/TraversableLike;Lscala/math/Numeric;)Ljava/lang/Object;
   5:	areturn
  LineNumberTable: 
   line 41: 0

  LocalVariableTable: 
   Start  Length  Slot  Name   Signature
   0      6      0    this       Lscala/collection/immutable/Stream;
   0      6      1    num       Lscala/math/Numeric;


public java.lang.Object sum(scala.math.Numeric);
  Code:
   Stack=2, Locals=2, Args_size=2
   0:	aload_0
   1:	aload_1
   2:	invokestatic	#769; //Method scala/collection/TraversableLike$class.sum:(Lscala/collection/TraversableLike;Lscala/math/Numeric;)Ljava/lang/Object;
   5:	areturn
  LineNumberTable: 
   line 41: 0

  LocalVariableTable: 
   Start  Length  Slot  Name   Signature
   0      6      0    this       Lscala/collection/immutable/Stream;
   0      6      1    num       Lscala/math/Numeric;


public scala.Option reduceRightOption(scala.Function2);
  Code:
   Stack=2, Locals=2, Args_size=2
   0:	aload_0
   1:	aload_1
   2:	invokestatic	#774; //Method scala/collection/TraversableLike$class.reduceRightOption:(Lscala/collection/TraversableLike;Lscala/Function2;)Lscala/Option;
   5:	areturn
  LineNumberTable: 
   line 41: 0

  LocalVariableTable: 
   Start  Length  Slot  Name   Signature
   0      6      0    this       Lscala/collection/immutable/Stream;
   0      6      1    op       Lscala/Function2;


public scala.Option reduceLeftOption(scala.Function2);
  Code:
   Stack=2, Locals=2, Args_size=2
   0:	aload_0
   1:	aload_1
   2:	invokestatic	#777; //Method scala/collection/TraversableLike$class.reduceLeftOption:(Lscala/collection/TraversableLike;Lscala/Function2;)Lscala/Option;
   5:	areturn
  LineNumberTable: 
   line 41: 0

  LocalVariableTable: 
   Start  Length  Slot  Name   Signature
   0      6      0    this       Lscala/collection/immutable/Stream;
   0      6      1    op       Lscala/Function2;


public java.lang.Object $colon$bslash(java.lang.Object, scala.Function2);
  Code:
   Stack=3, Locals=3, Args_size=3
   0:	aload_0
   1:	aload_1
   2:	aload_2
   3:	invokestatic	#781; //Method scala/collection/TraversableLike$class.$colon$bslash:(Lscala/collection/TraversableLike;Ljava/lang/Object;Lscala/Function2;)Ljava/lang/Object;
   6:	areturn
  LineNumberTable: 
   line 41: 0

  LocalVariableTable: 
   Start  Length  Slot  Name   Signature
   0      7      0    this       Lscala/collection/immutable/Stream;
   0      7      1    z       Ljava/lang/Object;
   0      7      2    op       Lscala/Function2;


public java.lang.Object $div$colon(java.lang.Object, scala.Function2);
  Code:
   Stack=3, Locals=3, Args_size=3
   0:	aload_0
   1:	aload_1
   2:	aload_2
   3:	invokestatic	#784; //Method scala/collection/TraversableLike$class.$div$colon:(Lscala/collection/TraversableLike;Ljava/lang/Object;Lscala/Function2;)Ljava/lang/Object;
   6:	areturn
  LineNumberTable: 
   line 41: 0

  LocalVariableTable: 
   Start  Length  Slot  Name   Signature
   0      7      0    this       Lscala/collection/immutable/Stream;
   0      7      1    z       Ljava/lang/Object;
   0      7      2    op       Lscala/Function2;


public scala.collection.Map groupBy(scala.Function1);
  Code:
   Stack=2, Locals=2, Args_size=2
   0:	aload_0
   1:	aload_1
   2:	invokestatic	#789; //Method scala/collection/TraversableLike$class.groupBy:(Lscala/collection/TraversableLike;Lscala/Function1;)Lscala/collection/Map;
   5:	areturn
  LineNumberTable: 
   line 41: 0

  LocalVariableTable: 
   Start  Length  Slot  Name   Signature
   0      6      0    this       Lscala/collection/immutable/Stream;
   0      6      1    f       Lscala/Function1;


public java.lang.Object partialMap(scala.PartialFunction, scala.collection.generic.CanBuildFrom);
  Code:
   Stack=3, Locals=3, Args_size=3
   0:	aload_0
   1:	aload_1
   2:	aload_2
   3:	invokestatic	#794; //Method scala/collection/TraversableLike$class.partialMap:(Lscala/collection/TraversableLike;Lscala/PartialFunction;Lscala/collection/generic/CanBuildFrom;)Ljava/lang/Object;
   6:	areturn
  LineNumberTable: 
   line 41: 0

  LocalVariableTable: 
   Start  Length  Slot  Name   Signature
   0      7      0    this       Lscala/collection/immutable/Stream;
   0      7      1    pf       Lscala/PartialFunction;
   0      7      2    bf       Lscala/collection/generic/CanBuildFrom;


public java.lang.Object filterNot(scala.Function1);
  Code:
   Stack=2, Locals=2, Args_size=2
   0:	aload_0
   1:	aload_1
   2:	invokestatic	#799; //Method scala/collection/TraversableLike$class.filterNot:(Lscala/collection/TraversableLike;Lscala/Function1;)Ljava/lang/Object;
   5:	areturn
  LineNumberTable: 
   line 41: 0

  LocalVariableTable: 
   Start  Length  Slot  Name   Signature
   0      6      0    this       Lscala/collection/immutable/Stream;
   0      6      1    p       Lscala/Function1;


public boolean nonEmpty();
  Code:
   Stack=1, Locals=1, Args_size=1
   0:	aload_0
   1:	invokestatic	#803; //Method scala/collection/TraversableLike$class.nonEmpty:(Lscala/collection/TraversableLike;)Z
   4:	ireturn
  LineNumberTable: 
   line 41: 0


public java.lang.Object repr();
  Code:
   Stack=1, Locals=1, Args_size=1
   0:	aload_0
   1:	invokestatic	#805; //Method scala/collection/TraversableLike$class.repr:(Lscala/collection/TraversableLike;)Ljava/lang/Object;
   4:	areturn
  LineNumberTable: 
   line 41: 0


public scala.collection.Traversable transpose(scala.Function1);
  Code:
   Stack=2, Locals=2, Args_size=2
   0:	aload_0
   1:	aload_1
   2:	invokestatic	#809; //Method scala/collection/generic/GenericTraversableTemplate$class.transpose:(Lscala/collection/generic/GenericTraversableTemplate;Lscala/Function1;)Lscala/collection/Traversable;
   5:	areturn
  LineNumberTable: 
   line 41: 0

  LocalVariableTable: 
   Start  Length  Slot  Name   Signature
   0      6      0    this       Lscala/collection/immutable/Stream;
   0      6      1    asTraversable       Lscala/Function1;


public scala.Tuple2 unzip(scala.Function1);
  Code:
   Stack=2, Locals=2, Args_size=2
   0:	aload_0
   1:	aload_1
   2:	invokestatic	#813; //Method scala/collection/generic/GenericTraversableTemplate$class.unzip:(Lscala/collection/generic/GenericTraversableTemplate;Lscala/Function1;)Lscala/Tuple2;
   5:	areturn
  LineNumberTable: 
   line 41: 0

  LocalVariableTable: 
   Start  Length  Slot  Name   Signature
   0      6      0    this       Lscala/collection/immutable/Stream;
   0      6      1    asPair       Lscala/Function1;


public scala.collection.mutable.Builder genericBuilder();
  Code:
   Stack=1, Locals=1, Args_size=1
   0:	aload_0
   1:	invokestatic	#819; //Method scala/collection/generic/GenericTraversableTemplate$class.genericBuilder:(Lscala/collection/generic/GenericTraversableTemplate;)Lscala/collection/mutable/Builder;
   4:	areturn
  LineNumberTable: 
   line 41: 0


public scala.collection.mutable.Builder newBuilder();
  Code:
   Stack=1, Locals=1, Args_size=1
   0:	aload_0
   1:	invokestatic	#822; //Method scala/collection/generic/GenericTraversableTemplate$class.newBuilder:(Lscala/collection/generic/GenericTraversableTemplate;)Lscala/collection/mutable/Builder;
   4:	areturn
  LineNumberTable: 
   line 41: 0


public scala.Option firstOption();
  Code:
   Stack=1, Locals=1, Args_size=1
   0:	aload_0
   1:	invokestatic	#826; //Method scala/collection/IterableLike$class.firstOption:(Lscala/collection/IterableLike;)Lscala/Option;
   4:	areturn
  LineNumberTable: 
   line 41: 0


public java.lang.Object first();
  Code:
   Stack=1, Locals=1, Args_size=1
   0:	aload_0
   1:	invokestatic	#830; //Method scala/collection/IterableLike$class.first:(Lscala/collection/IterableLike;)Ljava/lang/Object;
   4:	areturn
  LineNumberTable: 
   line 41: 0


public boolean canEqual(java.lang.Object);
  Code:
   Stack=2, Locals=2, Args_size=2
   0:	aload_0
   1:	aload_1
   2:	invokestatic	#834; //Method scala/collection/IterableLike$class.canEqual:(Lscala/collection/IterableLike;Ljava/lang/Object;)Z
   5:	ireturn
  LineNumberTable: 
   line 41: 0

  LocalVariableTable: 
   Start  Length  Slot  Name   Signature
   0      6      0    this       Lscala/collection/immutable/Stream;
   0      6      1    that       Ljava/lang/Object;


public java.lang.Object zipAll(scala.collection.Iterable, java.lang.Object, java.lang.Object, scala.collection.generic.CanBuildFrom);
  Code:
   Stack=5, Locals=5, Args_size=5
   0:	aload_0
   1:	aload_1
   2:	aload_2
   3:	aload_3
   4:	aload	4
   6:	invokestatic	#839; //Method scala/collection/IterableLike$class.zipAll:(Lscala/collection/IterableLike;Lscala/collection/Iterable;Ljava/lang/Object;Ljava/lang/Object;Lscala/collection/generic/CanBuildFrom;)Ljava/lang/Object;
   9:	areturn
  LineNumberTable: 
   line 41: 0

  LocalVariableTable: 
   Start  Length  Slot  Name   Signature
   0      10      0    this       Lscala/collection/immutable/Stream;
   0      10      1    that       Lscala/collection/Iterable;
   0      10      2    thisElem       Ljava/lang/Object;
   0      10      3    thatElem       Ljava/lang/Object;
   0      10      4    bf       Lscala/collection/generic/CanBuildFrom;


public void copyToArray(java.lang.Object, int, int);
  Code:
   Stack=4, Locals=4, Args_size=4
   0:	aload_0
   1:	aload_1
   2:	iload_2
   3:	iload_3
   4:	invokestatic	#845; //Method scala/collection/IterableLike$class.copyToArray:(Lscala/collection/IterableLike;Ljava/lang/Object;II)V
   7:	return
  LineNumberTable: 
   line 41: 0

  LocalVariableTable: 
   Start  Length  Slot  Name   Signature
   0      8      0    this       Lscala/collection/immutable/Stream;
   0      8      1    xs       Ljava/lang/Object;
   0      8      2    start       I
   0      8      3    len       I


public scala.collection.Iterable toIterable();
  Code:
   Stack=1, Locals=1, Args_size=1
   0:	aload_0
   1:	invokestatic	#849; //Method scala/collection/IterableLike$class.toIterable:(Lscala/collection/IterableLike;)Lscala/collection/Iterable;
   4:	areturn
  LineNumberTable: 
   line 41: 0


public scala.collection.Iterator elements();
  Code:
   Stack=1, Locals=1, Args_size=1
   0:	aload_0
   1:	invokestatic	#854; //Method scala/collection/IterableLike$class.elements:(Lscala/collection/IterableLike;)Lscala/collection/Iterator;
   4:	areturn
  LineNumberTable: 
   line 41: 0


public scala.Function1 compose(scala.Function1);
  Code:
   Stack=2, Locals=2, Args_size=2
   0:	aload_0
   1:	aload_1
   2:	invokestatic	#858; //Method scala/Function1$class.compose:(Lscala/Function1;Lscala/Function1;)Lscala/Function1;
   5:	areturn
  LineNumberTable: 
   line 41: 0

  LocalVariableTable: 
   Start  Length  Slot  Name   Signature
   0      6      0    this       Lscala/collection/immutable/Stream;
   0      6      1    g       Lscala/Function1;


public scala.PartialFunction andThen(scala.Function1);
  Code:
   Stack=2, Locals=2, Args_size=2
   0:	aload_0
   1:	aload_1
   2:	invokestatic	#861; //Method scala/PartialFunction$class.andThen:(Lscala/PartialFunction;Lscala/Function1;)Lscala/PartialFunction;
   5:	areturn
  LineNumberTable: 
   line 41: 0

  LocalVariableTable: 
   Start  Length  Slot  Name   Signature
   0      6      0    this       Lscala/collection/immutable/Stream;
   0      6      1    k       Lscala/Function1;


public scala.PartialFunction orElse(scala.PartialFunction);
  Code:
   Stack=2, Locals=2, Args_size=2
   0:	aload_0
   1:	aload_1
   2:	invokestatic	#867; //Method scala/PartialFunction$class.orElse:(Lscala/PartialFunction;Lscala/PartialFunction;)Lscala/PartialFunction;
   5:	areturn
  LineNumberTable: 
   line 41: 0

  LocalVariableTable: 
   Start  Length  Slot  Name   Signature
   0      6      0    this       Lscala/collection/immutable/Stream;
   0      6      1    that       Lscala/PartialFunction;


public java.lang.Object projection();
  Code:
   Stack=1, Locals=1, Args_size=1
   0:	aload_0
   1:	invokestatic	#871; //Method scala/collection/SeqLike$class.projection:(Lscala/collection/SeqLike;)Ljava/lang/Object;
   4:	areturn
  LineNumberTable: 
   line 41: 0


public boolean containsSlice(scala.collection.Seq);
  Code:
   Stack=2, Locals=2, Args_size=2
   0:	aload_0
   1:	aload_1
   2:	invokestatic	#876; //Method scala/collection/SeqLike$class.containsSlice:(Lscala/collection/SeqLike;Lscala/collection/Seq;)Z
   5:	ireturn
  LineNumberTable: 
   line 41: 0

  LocalVariableTable: 
   Start  Length  Slot  Name   Signature
   0      6      0    this       Lscala/collection/immutable/Stream;
   0      6      1    that       Lscala/collection/Seq;


public boolean equalsWith(scala.collection.Seq, scala.Function2);
  Code:
   Stack=3, Locals=3, Args_size=3
   0:	aload_0
   1:	aload_1
   2:	aload_2
   3:	invokestatic	#882; //Method scala/collection/SeqLike$class.equalsWith:(Lscala/collection/SeqLike;Lscala/collection/Seq;Lscala/Function2;)Z
   6:	ireturn
  LineNumberTable: 
   line 41: 0

  LocalVariableTable: 
   Start  Length  Slot  Name   Signature
   0      7      0    this       Lscala/collection/immutable/Stream;
   0      7      1    that       Lscala/collection/Seq;
   0      7      2    f       Lscala/Function2;


public int findLastIndexOf(scala.Function1);
  Code:
   Stack=2, Locals=2, Args_size=2
   0:	aload_0
   1:	aload_1
   2:	invokestatic	#887; //Method scala/collection/SeqLike$class.findLastIndexOf:(Lscala/collection/SeqLike;Lscala/Function1;)I
   5:	ireturn
  LineNumberTable: 
   line 41: 0

  LocalVariableTable: 
   Start  Length  Slot  Name   Signature
   0      6      0    this       Lscala/collection/immutable/Stream;
   0      6      1    p       Lscala/Function1;


public boolean equals(java.lang.Object);
  Code:
   Stack=2, Locals=2, Args_size=2
   0:	aload_0
   1:	aload_1
   2:	invokestatic	#891; //Method scala/collection/SeqLike$class.equals:(Lscala/collection/SeqLike;Ljava/lang/Object;)Z
   5:	ireturn
  LineNumberTable: 
   line 41: 0

  LocalVariableTable: 
   Start  Length  Slot  Name   Signature
   0      6      0    this       Lscala/collection/immutable/Stream;
   0      6      1    that       Ljava/lang/Object;


public int hashCode();
  Code:
   Stack=1, Locals=1, Args_size=1
   0:	aload_0
   1:	invokestatic	#896; //Method scala/collection/SeqLike$class.hashCode:(Lscala/collection/SeqLike;)I
   4:	ireturn
  LineNumberTable: 
   line 41: 0


public scala.collection.SeqView view(int, int);
  Code:
   Stack=3, Locals=3, Args_size=3
   0:	aload_0
   1:	iload_1
   2:	iload_2
   3:	invokestatic	#899; //Method scala/collection/SeqLike$class.view:(Lscala/collection/SeqLike;II)Lscala/collection/SeqView;
   6:	areturn
  LineNumberTable: 
   line 41: 0

  LocalVariableTable: 
   Start  Length  Slot  Name   Signature
   0      7      0    this       Lscala/collection/immutable/Stream;
   0      7      1    from       I
   0      7      2    until       I


public java.lang.Object view();
  Code:
   Stack=1, Locals=1, Args_size=1
   0:	aload_0
   1:	invokestatic	#901; //Method scala/collection/SeqLike$class.view:(Lscala/collection/SeqLike;)Ljava/lang/Object;
   4:	areturn
  LineNumberTable: 
   line 41: 0


public scala.collection.immutable.Range indices();
  Code:
   Stack=1, Locals=1, Args_size=1
   0:	aload_0
   1:	invokestatic	#906; //Method scala/collection/SeqLike$class.indices:(Lscala/collection/SeqLike;)Lscala/collection/immutable/Range;
   4:	areturn
  LineNumberTable: 
   line 41: 0


public scala.collection.Seq toSeq();
  Code:
   Stack=1, Locals=1, Args_size=1
   0:	aload_0
   1:	invokestatic	#910; //Method scala/collection/SeqLike$class.toSeq:(Lscala/collection/SeqLike;)Lscala/collection/Seq;
   4:	areturn
  LineNumberTable: 
   line 41: 0


public java.lang.Object sortBy(scala.Function1, scala.math.Ordering);
  Code:
   Stack=3, Locals=3, Args_size=3
   0:	aload_0
   1:	aload_1
   2:	aload_2
   3:	invokestatic	#915; //Method scala/collection/SeqLike$class.sortBy:(Lscala/collection/SeqLike;Lscala/Function1;Lscala/math/Ordering;)Ljava/lang/Object;
   6:	areturn
  LineNumberTable: 
   line 41: 0

  LocalVariableTable: 
   Start  Length  Slot  Name   Signature
   0      7      0    this       Lscala/collection/immutable/Stream;
   0      7      1    f       Lscala/Function1;
   0      7      2    ord       Lscala/math/Ordering;


public java.lang.Object sortWith(scala.math.Ordering);
  Code:
   Stack=2, Locals=2, Args_size=2
   0:	aload_0
   1:	aload_1
   2:	invokestatic	#920; //Method scala/collection/SeqLike$class.sortWith:(Lscala/collection/SeqLike;Lscala/math/Ordering;)Ljava/lang/Object;
   5:	areturn
  LineNumberTable: 
   line 41: 0

  LocalVariableTable: 
   Start  Length  Slot  Name   Signature
   0      6      0    this       Lscala/collection/immutable/Stream;
   0      6      1    ord       Lscala/math/Ordering;


public java.lang.Object sortWith(scala.Function2);
  Code:
   Stack=2, Locals=2, Args_size=2
   0:	aload_0
   1:	aload_1
   2:	invokestatic	#924; //Method scala/collection/SeqLike$class.sortWith:(Lscala/collection/SeqLike;Lscala/Function2;)Ljava/lang/Object;
   5:	areturn
  LineNumberTable: 
   line 41: 0

  LocalVariableTable: 
   Start  Length  Slot  Name   Signature
   0      6      0    this       Lscala/collection/immutable/Stream;
   0      6      1    lt       Lscala/Function2;


public java.lang.Object $colon$plus(java.lang.Object, scala.collection.generic.CanBuildFrom);
  Code:
   Stack=3, Locals=3, Args_size=3
   0:	aload_0
   1:	aload_1
   2:	aload_2
   3:	invokestatic	#930; //Method scala/collection/SeqLike$class.$colon$plus:(Lscala/collection/SeqLike;Ljava/lang/Object;Lscala/collection/generic/CanBuildFrom;)Ljava/lang/Object;
   6:	areturn
  LineNumberTable: 
   line 41: 0

  LocalVariableTable: 
   Start  Length  Slot  Name   Signature
   0      7      0    this       Lscala/collection/immutable/Stream;
   0      7      1    elem       Ljava/lang/Object;
   0      7      2    bf       Lscala/collection/generic/CanBuildFrom;


public java.lang.Object $plus$colon(java.lang.Object, scala.collection.generic.CanBuildFrom);
  Code:
   Stack=3, Locals=3, Args_size=3
   0:	aload_0
   1:	aload_1
   2:	aload_2
   3:	invokestatic	#933; //Method scala/collection/SeqLike$class.$plus$colon:(Lscala/collection/SeqLike;Ljava/lang/Object;Lscala/collection/generic/CanBuildFrom;)Ljava/lang/Object;
   6:	areturn
  LineNumberTable: 
   line 41: 0

  LocalVariableTable: 
   Start  Length  Slot  Name   Signature
   0      7      0    this       Lscala/collection/immutable/Stream;
   0      7      1    elem       Ljava/lang/Object;
   0      7      2    bf       Lscala/collection/generic/CanBuildFrom;


public java.lang.Object updated(int, java.lang.Object, scala.collection.generic.CanBuildFrom);
  Code:
   Stack=4, Locals=4, Args_size=4
   0:	aload_0
   1:	iload_1
   2:	aload_2
   3:	aload_3
   4:	invokestatic	#937; //Method scala/collection/SeqLike$class.updated:(Lscala/collection/SeqLike;ILjava/lang/Object;Lscala/collection/generic/CanBuildFrom;)Ljava/lang/Object;
   7:	areturn
  LineNumberTable: 
   line 41: 0

  LocalVariableTable: 
   Start  Length  Slot  Name   Signature
   0      8      0    this       Lscala/collection/immutable/Stream;
   0      8      1    index       I
   0      8      2    elem       Ljava/lang/Object;
   0      8      3    bf       Lscala/collection/generic/CanBuildFrom;


public java.lang.Object patch(int, scala.collection.Seq, int, scala.collection.generic.CanBuildFrom);
  Code:
   Stack=5, Locals=5, Args_size=5
   0:	aload_0
   1:	iload_1
   2:	aload_2
   3:	iload_3
   4:	aload	4
   6:	invokestatic	#943; //Method scala/collection/SeqLike$class.patch:(Lscala/collection/SeqLike;ILscala/collection/Seq;ILscala/collection/generic/CanBuildFrom;)Ljava/lang/Object;
   9:	areturn
  LineNumberTable: 
   line 41: 0

  LocalVariableTable: 
   Start  Length  Slot  Name   Signature
   0      10      0    this       Lscala/collection/immutable/Stream;
   0      10      1    from       I
   0      10      2    patch       Lscala/collection/Seq;
   0      10      3    replaced       I
   0      10      4    bf       Lscala/collection/generic/CanBuildFrom;


public java.lang.Object intersect(scala.collection.Seq);
  Code:
   Stack=2, Locals=2, Args_size=2
   0:	aload_0
   1:	aload_1
   2:	invokestatic	#949; //Method scala/collection/SeqLike$class.intersect:(Lscala/collection/SeqLike;Lscala/collection/Seq;)Ljava/lang/Object;
   5:	areturn
  LineNumberTable: 
   line 41: 0

  LocalVariableTable: 
   Start  Length  Slot  Name   Signature
   0      6      0    this       Lscala/collection/immutable/Stream;
   0      6      1    that       Lscala/collection/Seq;


public java.lang.Object diff(scala.collection.Seq);
  Code:
   Stack=2, Locals=2, Args_size=2
   0:	aload_0
   1:	aload_1
   2:	invokestatic	#952; //Method scala/collection/SeqLike$class.diff:(Lscala/collection/SeqLike;Lscala/collection/Seq;)Ljava/lang/Object;
   5:	areturn
  LineNumberTable: 
   line 41: 0

  LocalVariableTable: 
   Start  Length  Slot  Name   Signature
   0      6      0    this       Lscala/collection/immutable/Stream;
   0      6      1    that       Lscala/collection/Seq;


public java.lang.Object union(scala.collection.Seq, scala.collection.generic.CanBuildFrom);
  Code:
   Stack=3, Locals=3, Args_size=3
   0:	aload_0
   1:	aload_1
   2:	aload_2
   3:	invokestatic	#957; //Method scala/collection/SeqLike$class.union:(Lscala/collection/SeqLike;Lscala/collection/Seq;Lscala/collection/generic/CanBuildFrom;)Ljava/lang/Object;
   6:	areturn
  LineNumberTable: 
   line 41: 0

  LocalVariableTable: 
   Start  Length  Slot  Name   Signature
   0      7      0    this       Lscala/collection/immutable/Stream;
   0      7      1    that       Lscala/collection/Seq;
   0      7      2    bf       Lscala/collection/generic/CanBuildFrom;


public boolean contains(java.lang.Object);
  Code:
   Stack=2, Locals=2, Args_size=2
   0:	aload_0
   1:	aload_1
   2:	invokestatic	#960; //Method scala/collection/SeqLike$class.contains:(Lscala/collection/SeqLike;Ljava/lang/Object;)Z
   5:	ireturn
  LineNumberTable: 
   line 41: 0

  LocalVariableTable: 
   Start  Length  Slot  Name   Signature
   0      6      0    this       Lscala/collection/immutable/Stream;
   0      6      1    elem       Ljava/lang/Object;


public int lastIndexOfSlice(scala.collection.Seq, int);
  Code:
   Stack=3, Locals=3, Args_size=3
   0:	aload_0
   1:	aload_1
   2:	iload_2
   3:	invokestatic	#965; //Method scala/collection/SeqLike$class.lastIndexOfSlice:(Lscala/collection/SeqLike;Lscala/collection/Seq;I)I
   6:	ireturn
  LineNumberTable: 
   line 41: 0

  LocalVariableTable: 
   Start  Length  Slot  Name   Signature
   0      7      0    this       Lscala/collection/immutable/Stream;
   0      7      1    that       Lscala/collection/Seq;
   0      7      2    fromIndex       I


public int lastIndexOfSlice(scala.collection.Seq);
  Code:
   Stack=2, Locals=2, Args_size=2
   0:	aload_0
   1:	aload_1
   2:	invokestatic	#970; //Method scala/collection/SeqLike$class.lastIndexOfSlice:(Lscala/collection/SeqLike;Lscala/collection/Seq;)I
   5:	ireturn
  LineNumberTable: 
   line 41: 0

  LocalVariableTable: 
   Start  Length  Slot  Name   Signature
   0      6      0    this       Lscala/collection/immutable/Stream;
   0      6      1    that       Lscala/collection/Seq;


public int indexOfSlice(scala.collection.Seq, int);
  Code:
   Stack=3, Locals=3, Args_size=3
   0:	aload_0
   1:	aload_1
   2:	iload_2
   3:	invokestatic	#973; //Method scala/collection/SeqLike$class.indexOfSlice:(Lscala/collection/SeqLike;Lscala/collection/Seq;I)I
   6:	ireturn
  LineNumberTable: 
   line 41: 0

  LocalVariableTable: 
   Start  Length  Slot  Name   Signature
   0      7      0    this       Lscala/collection/immutable/Stream;
   0      7      1    that       Lscala/collection/Seq;
   0      7      2    fromIndex       I


public int indexOfSlice(scala.collection.Seq);
  Code:
   Stack=2, Locals=2, Args_size=2
   0:	aload_0
   1:	aload_1
   2:	invokestatic	#975; //Method scala/collection/SeqLike$class.indexOfSlice:(Lscala/collection/SeqLike;Lscala/collection/Seq;)I
   5:	ireturn
  LineNumberTable: 
   line 41: 0

  LocalVariableTable: 
   Start  Length  Slot  Name   Signature
   0      6      0    this       Lscala/collection/immutable/Stream;
   0      6      1    that       Lscala/collection/Seq;


public boolean endsWith(scala.collection.Seq);
  Code:
   Stack=2, Locals=2, Args_size=2
   0:	aload_0
   1:	aload_1
   2:	invokestatic	#978; //Method scala/collection/SeqLike$class.endsWith:(Lscala/collection/SeqLike;Lscala/collection/Seq;)Z
   5:	ireturn
  LineNumberTable: 
   line 41: 0

  LocalVariableTable: 
   Start  Length  Slot  Name   Signature
   0      6      0    this       Lscala/collection/immutable/Stream;
   0      6      1    that       Lscala/collection/Seq;


public boolean startsWith(scala.collection.Seq);
  Code:
   Stack=2, Locals=2, Args_size=2
   0:	aload_0
   1:	aload_1
   2:	invokestatic	#981; //Method scala/collection/SeqLike$class.startsWith:(Lscala/collection/SeqLike;Lscala/collection/Seq;)Z
   5:	ireturn
  LineNumberTable: 
   line 41: 0

  LocalVariableTable: 
   Start  Length  Slot  Name   Signature
   0      6      0    this       Lscala/collection/immutable/Stream;
   0      6      1    that       Lscala/collection/Seq;


public boolean startsWith(scala.collection.Seq, int);
  Code:
   Stack=3, Locals=3, Args_size=3
   0:	aload_0
   1:	aload_1
   2:	iload_2
   3:	invokestatic	#985; //Method scala/collection/SeqLike$class.startsWith:(Lscala/collection/SeqLike;Lscala/collection/Seq;I)Z
   6:	ireturn
  LineNumberTable: 
   line 41: 0

  LocalVariableTable: 
   Start  Length  Slot  Name   Signature
   0      7      0    this       Lscala/collection/immutable/Stream;
   0      7      1    that       Lscala/collection/Seq;
   0      7      2    offset       I


public scala.collection.Iterator reversedElements();
  Code:
   Stack=1, Locals=1, Args_size=1
   0:	aload_0
   1:	invokestatic	#990; //Method scala/collection/SeqLike$class.reversedElements:(Lscala/collection/SeqLike;)Lscala/collection/Iterator;
   4:	areturn
  LineNumberTable: 
   line 41: 0


public scala.collection.Iterator reverseIterator();
  Code:
   Stack=1, Locals=1, Args_size=1
   0:	aload_0
   1:	invokestatic	#993; //Method scala/collection/SeqLike$class.reverseIterator:(Lscala/collection/SeqLike;)Lscala/collection/Iterator;
   4:	areturn
  LineNumberTable: 
   line 41: 0


public java.lang.Object reverseMap(scala.Function1, scala.collection.generic.CanBuildFrom);
  Code:
   Stack=3, Locals=3, Args_size=3
   0:	aload_0
   1:	aload_1
   2:	aload_2
   3:	invokestatic	#997; //Method scala/collection/SeqLike$class.reverseMap:(Lscala/collection/SeqLike;Lscala/Function1;Lscala/collection/generic/CanBuildFrom;)Ljava/lang/Object;
   6:	areturn
  LineNumberTable: 
   line 41: 0

  LocalVariableTable: 
   Start  Length  Slot  Name   Signature
   0      7      0    this       Lscala/collection/immutable/Stream;
   0      7      1    f       Lscala/Function1;
   0      7      2    bf       Lscala/collection/generic/CanBuildFrom;


public int lastIndexWhere(scala.Function1);
  Code:
   Stack=2, Locals=2, Args_size=2
   0:	aload_0
   1:	aload_1
   2:	invokestatic	#1000; //Method scala/collection/SeqLike$class.lastIndexWhere:(Lscala/collection/SeqLike;Lscala/Function1;)I
   5:	ireturn
  LineNumberTable: 
   line 41: 0

  LocalVariableTable: 
   Start  Length  Slot  Name   Signature
   0      6      0    this       Lscala/collection/immutable/Stream;
   0      6      1    p       Lscala/Function1;


public int lastIndexOf(java.lang.Object, int);
  Code:
   Stack=3, Locals=3, Args_size=3
   0:	aload_0
   1:	aload_1
   2:	iload_2
   3:	invokestatic	#1005; //Method scala/collection/SeqLike$class.lastIndexOf:(Lscala/collection/SeqLike;Ljava/lang/Object;I)I
   6:	ireturn
  LineNumberTable: 
   line 41: 0

  LocalVariableTable: 
   Start  Length  Slot  Name   Signature
   0      7      0    this       Lscala/collection/immutable/Stream;
   0      7      1    elem       Ljava/lang/Object;
   0      7      2    end       I


public int lastIndexOf(java.lang.Object);
  Code:
   Stack=2, Locals=2, Args_size=2
   0:	aload_0
   1:	aload_1
   2:	invokestatic	#1008; //Method scala/collection/SeqLike$class.lastIndexOf:(Lscala/collection/SeqLike;Ljava/lang/Object;)I
   5:	ireturn
  LineNumberTable: 
   line 41: 0

  LocalVariableTable: 
   Start  Length  Slot  Name   Signature
   0      6      0    this       Lscala/collection/immutable/Stream;
   0      6      1    elem       Ljava/lang/Object;


public int indexOf(java.lang.Object, int);
  Code:
   Stack=3, Locals=3, Args_size=3
   0:	aload_0
   1:	aload_1
   2:	iload_2
   3:	invokestatic	#1011; //Method scala/collection/SeqLike$class.indexOf:(Lscala/collection/SeqLike;Ljava/lang/Object;I)I
   6:	ireturn
  LineNumberTable: 
   line 41: 0

  LocalVariableTable: 
   Start  Length  Slot  Name   Signature
   0      7      0    this       Lscala/collection/immutable/Stream;
   0      7      1    elem       Ljava/lang/Object;
   0      7      2    from       I


public int indexOf(java.lang.Object);
  Code:
   Stack=2, Locals=2, Args_size=2
   0:	aload_0
   1:	aload_1
   2:	invokestatic	#1013; //Method scala/collection/SeqLike$class.indexOf:(Lscala/collection/SeqLike;Ljava/lang/Object;)I
   5:	ireturn
  LineNumberTable: 
   line 41: 0

  LocalVariableTable: 
   Start  Length  Slot  Name   Signature
   0      6      0    this       Lscala/collection/immutable/Stream;
   0      6      1    elem       Ljava/lang/Object;


public int findIndexOf(scala.Function1);
  Code:
   Stack=2, Locals=2, Args_size=2
   0:	aload_0
   1:	aload_1
   2:	invokestatic	#1016; //Method scala/collection/SeqLike$class.findIndexOf:(Lscala/collection/SeqLike;Lscala/Function1;)I
   5:	ireturn
  LineNumberTable: 
   line 41: 0

  LocalVariableTable: 
   Start  Length  Slot  Name   Signature
   0      6      0    this       Lscala/collection/immutable/Stream;
   0      6      1    p       Lscala/Function1;


public int indexWhere(scala.Function1);
  Code:
   Stack=2, Locals=2, Args_size=2
   0:	aload_0
   1:	aload_1
   2:	invokestatic	#1019; //Method scala/collection/SeqLike$class.indexWhere:(Lscala/collection/SeqLike;Lscala/Function1;)I
   5:	ireturn
  LineNumberTable: 
   line 41: 0

  LocalVariableTable: 
   Start  Length  Slot  Name   Signature
   0      6      0    this       Lscala/collection/immutable/Stream;
   0      6      1    p       Lscala/Function1;


public int prefixLength(scala.Function1);
  Code:
   Stack=2, Locals=2, Args_size=2
   0:	aload_0
   1:	aload_1
   2:	invokestatic	#1022; //Method scala/collection/SeqLike$class.prefixLength:(Lscala/collection/SeqLike;Lscala/Function1;)I
   5:	ireturn
  LineNumberTable: 
   line 41: 0

  LocalVariableTable: 
   Start  Length  Slot  Name   Signature
   0      6      0    this       Lscala/collection/immutable/Stream;
   0      6      1    p       Lscala/Function1;


public int size();
  Code:
   Stack=1, Locals=1, Args_size=1
   0:	aload_0
   1:	invokestatic	#1025; //Method scala/collection/SeqLike$class.size:(Lscala/collection/SeqLike;)I
   4:	ireturn
  LineNumberTable: 
   line 41: 0


public int lastIndexWhere(scala.Function1, int);
  Code:
   Stack=3, Locals=3, Args_size=3
   0:	aload_0
   1:	aload_1
   2:	iload_2
   3:	invokestatic	#1029; //Method scala/collection/LinearSeqLike$class.lastIndexWhere:(Lscala/collection/LinearSeqLike;Lscala/Function1;I)I
   6:	ireturn
  LineNumberTable: 
   line 41: 0

  LocalVariableTable: 
   Start  Length  Slot  Name   Signature
   0      7      0    this       Lscala/collection/immutable/Stream;
   0      7      1    p       Lscala/Function1;
   0      7      2    end       I


public int indexWhere(scala.Function1, int);
  Code:
   Stack=3, Locals=3, Args_size=3
   0:	aload_0
   1:	aload_1
   2:	iload_2
   3:	invokestatic	#1031; //Method scala/collection/LinearSeqLike$class.indexWhere:(Lscala/collection/LinearSeqLike;Lscala/Function1;I)I
   6:	ireturn
  LineNumberTable: 
   line 41: 0

  LocalVariableTable: 
   Start  Length  Slot  Name   Signature
   0      7      0    this       Lscala/collection/immutable/Stream;
   0      7      1    p       Lscala/Function1;
   0      7      2    from       I


public int segmentLength(scala.Function1, int);
  Code:
   Stack=3, Locals=3, Args_size=3
   0:	aload_0
   1:	aload_1
   2:	iload_2
   3:	invokestatic	#1034; //Method scala/collection/LinearSeqLike$class.segmentLength:(Lscala/collection/LinearSeqLike;Lscala/Function1;I)I
   6:	ireturn
  LineNumberTable: 
   line 41: 0

  LocalVariableTable: 
   Start  Length  Slot  Name   Signature
   0      7      0    this       Lscala/collection/immutable/Stream;
   0      7      1    p       Lscala/Function1;
   0      7      2    from       I


public boolean isDefinedAt(int);
  Code:
   Stack=2, Locals=2, Args_size=2
   0:	aload_0
   1:	iload_1
   2:	invokestatic	#1037; //Method scala/collection/LinearSeqLike$class.isDefinedAt:(Lscala/collection/LinearSeqLike;I)Z
   5:	ireturn
  LineNumberTable: 
   line 41: 0

  LocalVariableTable: 
   Start  Length  Slot  Name   Signature
   0      6      0    this       Lscala/collection/immutable/Stream;
   0      6      1    x       I


public int lengthCompare(int);
  Code:
   Stack=2, Locals=2, Args_size=2
   0:	aload_0
   1:	iload_1
   2:	invokestatic	#1042; //Method scala/collection/LinearSeqLike$class.lengthCompare:(Lscala/collection/LinearSeqLike;I)I
   5:	ireturn
  LineNumberTable: 
   line 41: 0

  LocalVariableTable: 
   Start  Length  Slot  Name   Signature
   0      6      0    this       Lscala/collection/immutable/Stream;
   0      6      1    len       I


public boolean sameElements(scala.collection.Iterable);
  Code:
   Stack=2, Locals=2, Args_size=2
   0:	aload_0
   1:	aload_1
   2:	invokestatic	#1047; //Method scala/collection/LinearSeqLike$class.sameElements:(Lscala/collection/LinearSeqLike;Lscala/collection/Iterable;)Z
   5:	ireturn
  LineNumberTable: 
   line 41: 0

  LocalVariableTable: 
   Start  Length  Slot  Name   Signature
   0      6      0    this       Lscala/collection/immutable/Stream;
   0      6      1    that       Lscala/collection/Iterable;


public scala.Tuple2 span(scala.Function1);
  Code:
   Stack=2, Locals=2, Args_size=2
   0:	aload_0
   1:	aload_1
   2:	invokestatic	#1051; //Method scala/collection/LinearSeqLike$class.span:(Lscala/collection/LinearSeqLike;Lscala/Function1;)Lscala/Tuple2;
   5:	areturn
  LineNumberTable: 
   line 41: 0

  LocalVariableTable: 
   Start  Length  Slot  Name   Signature
   0      6      0    this       Lscala/collection/immutable/Stream;
   0      6      1    p       Lscala/Function1;


public scala.collection.LinearSeqLike dropRight(int);
  Code:
   Stack=2, Locals=2, Args_size=2
   0:	aload_0
   1:	iload_1
   2:	invokestatic	#1054; //Method scala/collection/LinearSeqLike$class.dropRight:(Lscala/collection/LinearSeqLike;I)Lscala/collection/LinearSeqLike;
   5:	areturn
  LineNumberTable: 
   line 41: 0

  LocalVariableTable: 
   Start  Length  Slot  Name   Signature
   0      6      0    this       Lscala/collection/immutable/Stream;
   0      6      1    n       I


public scala.collection.LinearSeqLike drop(int);
  Code:
   Stack=2, Locals=2, Args_size=2
   0:	aload_0
   1:	iload_1
   2:	invokestatic	#1056; //Method scala/collection/LinearSeqLike$class.drop:(Lscala/collection/LinearSeqLike;I)Lscala/collection/LinearSeqLike;
   5:	areturn
  LineNumberTable: 
   line 41: 0

  LocalVariableTable: 
   Start  Length  Slot  Name   Signature
   0      6      0    this       Lscala/collection/immutable/Stream;
   0      6      1    n       I


public java.lang.Object last();
  Code:
   Stack=1, Locals=1, Args_size=1
   0:	aload_0
   1:	invokestatic	#1060; //Method scala/collection/LinearSeqLike$class.last:(Lscala/collection/LinearSeqLike;)Ljava/lang/Object;
   4:	areturn
  LineNumberTable: 
   line 41: 0


public java.lang.Object reduceRight(scala.Function2);
  Code:
   Stack=2, Locals=2, Args_size=2
   0:	aload_0
   1:	aload_1
   2:	invokestatic	#1064; //Method scala/collection/LinearSeqLike$class.reduceRight:(Lscala/collection/LinearSeqLike;Lscala/Function2;)Ljava/lang/Object;
   5:	areturn
  LineNumberTable: 
   line 41: 0

  LocalVariableTable: 
   Start  Length  Slot  Name   Signature
   0      6      0    this       Lscala/collection/immutable/Stream;
   0      6      1    op       Lscala/Function2;


public java.lang.Object reduceLeft(scala.Function2);
  Code:
   Stack=2, Locals=2, Args_size=2
   0:	aload_0
   1:	aload_1
   2:	invokestatic	#1067; //Method scala/collection/LinearSeqLike$class.reduceLeft:(Lscala/collection/LinearSeqLike;Lscala/Function2;)Ljava/lang/Object;
   5:	areturn
  LineNumberTable: 
   line 41: 0

  LocalVariableTable: 
   Start  Length  Slot  Name   Signature
   0      6      0    this       Lscala/collection/immutable/Stream;
   0      6      1    f       Lscala/Function2;


public java.lang.Object foldRight(java.lang.Object, scala.Function2);
  Code:
   Stack=3, Locals=3, Args_size=3
   0:	aload_0
   1:	aload_1
   2:	aload_2
   3:	invokestatic	#1071; //Method scala/collection/LinearSeqLike$class.foldRight:(Lscala/collection/LinearSeqLike;Ljava/lang/Object;Lscala/Function2;)Ljava/lang/Object;
   6:	areturn
  LineNumberTable: 
   line 41: 0

  LocalVariableTable: 
   Start  Length  Slot  Name   Signature
   0      7      0    this       Lscala/collection/immutable/Stream;
   0      7      1    z       Ljava/lang/Object;
   0      7      2    f       Lscala/Function2;


public scala.Option find(scala.Function1);
  Code:
   Stack=2, Locals=2, Args_size=2
   0:	aload_0
   1:	aload_1
   2:	invokestatic	#1076; //Method scala/collection/LinearSeqLike$class.find:(Lscala/collection/LinearSeqLike;Lscala/Function1;)Lscala/Option;
   5:	areturn
  LineNumberTable: 
   line 41: 0

  LocalVariableTable: 
   Start  Length  Slot  Name   Signature
   0      6      0    this       Lscala/collection/immutable/Stream;
   0      6      1    p       Lscala/Function1;


public int count(scala.Function1);
  Code:
   Stack=2, Locals=2, Args_size=2
   0:	aload_0
   1:	aload_1
   2:	invokestatic	#1080; //Method scala/collection/LinearSeqLike$class.count:(Lscala/collection/LinearSeqLike;Lscala/Function1;)I
   5:	ireturn
  LineNumberTable: 
   line 41: 0

  LocalVariableTable: 
   Start  Length  Slot  Name   Signature
   0      6      0    this       Lscala/collection/immutable/Stream;
   0      6      1    p       Lscala/Function1;


public boolean exists(scala.Function1);
  Code:
   Stack=2, Locals=2, Args_size=2
   0:	aload_0
   1:	aload_1
   2:	invokestatic	#1085; //Method scala/collection/LinearSeqLike$class.exists:(Lscala/collection/LinearSeqLike;Lscala/Function1;)Z
   5:	ireturn
  LineNumberTable: 
   line 41: 0

  LocalVariableTable: 
   Start  Length  Slot  Name   Signature
   0      6      0    this       Lscala/collection/immutable/Stream;
   0      6      1    p       Lscala/Function1;


public boolean forall(scala.Function1);
  Code:
   Stack=2, Locals=2, Args_size=2
   0:	aload_0
   1:	aload_1
   2:	invokestatic	#1088; //Method scala/collection/LinearSeqLike$class.forall:(Lscala/collection/LinearSeqLike;Lscala/Function1;)Z
   5:	ireturn
  LineNumberTable: 
   line 41: 0

  LocalVariableTable: 
   Start  Length  Slot  Name   Signature
   0      6      0    this       Lscala/collection/immutable/Stream;
   0      6      1    p       Lscala/Function1;


public scala.collection.Iterator iterator();
  Code:
   Stack=1, Locals=1, Args_size=1
   0:	aload_0
   1:	invokestatic	#1092; //Method scala/collection/LinearSeqLike$class.iterator:(Lscala/collection/LinearSeqLike;)Lscala/collection/Iterator;
   4:	areturn
  LineNumberTable: 
   line 41: 0


public java.lang.Object apply(int);
  Code:
   Stack=2, Locals=2, Args_size=2
   0:	aload_0
   1:	iload_1
   2:	invokestatic	#1095; //Method scala/collection/LinearSeqLike$class.apply:(Lscala/collection/LinearSeqLike;I)Ljava/lang/Object;
   5:	areturn
  LineNumberTable: 
   line 41: 0

  LocalVariableTable: 
   Start  Length  Slot  Name   Signature
   0      6      0    this       Lscala/collection/immutable/Stream;
   0      6      1    n       I


public int length();
  Code:
   Stack=1, Locals=1, Args_size=1
   0:	aload_0
   1:	invokestatic	#1099; //Method scala/collection/LinearSeqLike$class.length:(Lscala/collection/LinearSeqLike;)I
   4:	ireturn
  LineNumberTable: 
   line 41: 0


public scala.collection.LinearSeq toCollection(scala.collection.LinearSeqLike);
  Code:
   Stack=2, Locals=2, Args_size=2
   0:	aload_0
   1:	aload_1
   2:	invokestatic	#1102; //Method scala/collection/LinearSeqLike$class.toCollection:(Lscala/collection/LinearSeqLike;Lscala/collection/LinearSeqLike;)Lscala/collection/LinearSeq;
   5:	areturn
  LineNumberTable: 
   line 41: 0

  LocalVariableTable: 
   Start  Length  Slot  Name   Signature
   0      6      0    this       Lscala/collection/immutable/Stream;
   0      6      1    repr       Lscala/collection/LinearSeqLike;


public scala.collection.LinearSeq thisCollection();
  Code:
   Stack=1, Locals=1, Args_size=1
   0:	aload_0
   1:	invokestatic	#1105; //Method scala/collection/LinearSeqLike$class.thisCollection:(Lscala/collection/LinearSeqLike;)Lscala/collection/LinearSeq;
   4:	areturn
  LineNumberTable: 
   line 41: 0


public final boolean scala$collection$LinearSeqLike$$super$sameElements(scala.collection.Iterable);
  Code:
   Stack=2, Locals=2, Args_size=2
   0:	aload_0
   1:	aload_1
   2:	invokestatic	#1109; //Method scala/collection/IterableLike$class.sameElements:(Lscala/collection/IterableLike;Lscala/collection/Iterable;)Z
   5:	ireturn
  LineNumberTable: 
   line 41: 0

  LocalVariableTable: 
   Start  Length  Slot  Name   Signature
   0      6      0    this       Lscala/collection/immutable/Stream;
   0      6      1    that       Lscala/collection/Iterable;


}

