Compiled from "Stream.scala"
public final class scala.collection.immutable.Stream$Empty$ extends scala.collection.immutable.Stream implements scala.ScalaObject
  SourceFile: "Stream.scala"
  Scala: length = 0x
   
  Signature: length = 0x2
   00 2D 
  minor version: 0
  major version: 49
  Constant pool:
const #1 = Asciz	SourceFile;
const #2 = Asciz	Stream.scala;
const #3 = Asciz	Scala;
const #4 = Asciz	MODULE$;
const #5 = Asciz	Lscala/collection/immutable/Stream$Empty$;;
const #6 = Asciz	<clinit>;
const #7 = Asciz	()V;
const #8 = Asciz	Code;
const #9 = Asciz	scala/collection/immutable/Stream$Empty$;
const #10 = class	#9;	//  scala/collection/immutable/Stream$Empty$
const #11 = Asciz	<init>;
const #12 = NameAndType	#11:#7;//  "<init>":()V
const #13 = Method	#10.#12;	//  scala/collection/immutable/Stream$Empty$."<init>":()V
const #14 = Asciz	LineNumberTable;
const #15 = Asciz	scala/collection/immutable/Stream;
const #16 = class	#15;	//  scala/collection/immutable/Stream
const #17 = Method	#16.#12;	//  scala/collection/immutable/Stream."<init>":()V
const #18 = NameAndType	#4:#5;//  MODULE$:Lscala/collection/immutable/Stream$Empty$;
const #19 = Field	#10.#18;	//  scala/collection/immutable/Stream$Empty$.MODULE$:Lscala/collection/immutable/Stream$Empty$;
const #20 = Asciz	head;
const #21 = Asciz	()Ljava/lang/Object;;
const #22 = Asciz	()Lscala/runtime/Nothing$;;
const #23 = NameAndType	#20:#22;//  head:()Lscala/runtime/Nothing$;
const #24 = Method	#10.#23;	//  scala/collection/immutable/Stream$Empty$.head:()Lscala/runtime/Nothing$;
const #25 = Asciz	tail;
const #26 = Asciz	()Lscala/collection/generic/TraversableTemplate;;
const #27 = NameAndType	#25:#22;//  tail:()Lscala/runtime/Nothing$;
const #28 = Method	#10.#27;	//  scala/collection/immutable/Stream$Empty$.tail:()Lscala/runtime/Nothing$;
const #29 = Asciz	()Lscala/collection/generic/LinearSequenceTemplate;;
const #30 = Asciz	tailDefined;
const #31 = Asciz	()Z;
const #32 = Asciz	java/lang/UnsupportedOperationException;
const #33 = class	#32;	//  java/lang/UnsupportedOperationException
const #34 = Asciz	tail of empty stream;
const #35 = String	#34;	//  tail of empty stream
const #36 = Asciz	(Ljava/lang/String;)V;
const #37 = NameAndType	#11:#36;//  "<init>":(Ljava/lang/String;)V
const #38 = Method	#33.#37;	//  java/lang/UnsupportedOperationException."<init>":(Ljava/lang/String;)V
const #39 = Asciz	java/util/NoSuchElementException;
const #40 = class	#39;	//  java/util/NoSuchElementException
const #41 = Asciz	head of empty stream;
const #42 = String	#41;	//  head of empty stream
const #43 = Method	#40.#37;	//  java/util/NoSuchElementException."<init>":(Ljava/lang/String;)V
const #44 = Asciz	isEmpty;
const #45 = Asciz	Lscala/collection/immutable/Stream<Lscala/runtime/Nothing$;>;Lscala/ScalaObject;;
const #46 = Asciz	Signature;
const #47 = Asciz	scala/ScalaObject;
const #48 = class	#47;	//  scala/ScalaObject

{
public static final scala.collection.immutable.Stream$Empty$ MODULE$;

public static {};
  Code:
   Stack=1, Locals=0, Args_size=0
   0:	new	#10; //class scala/collection/immutable/Stream$Empty$
   3:	invokespecial	#13; //Method "<init>":()V
   6:	return

public scala.collection.immutable.Stream$Empty$();
  Code:
   Stack=1, Locals=1, Args_size=1
   0:	aload_0
   1:	invokespecial	#17; //Method scala/collection/immutable/Stream."<init>":()V
   4:	aload_0
   5:	putstatic	#19; //Field MODULE$:Lscala/collection/immutable/Stream$Empty$;
   8:	return
  LineNumberTable: 
   line 382: 0


public java.lang.Object head();
  Code:
   Stack=1, Locals=1, Args_size=1
   0:	aload_0
   1:	invokevirtual	#24; //Method head:()Lscala/runtime/Nothing$;
   4:	athrow
  LineNumberTable: 
   line 382: 0


public scala.collection.generic.TraversableTemplate tail();
  Code:
   Stack=1, Locals=1, Args_size=1
   0:	aload_0
   1:	invokevirtual	#28; //Method tail:()Lscala/runtime/Nothing$;
   4:	athrow
  LineNumberTable: 
   line 382: 0


public scala.collection.generic.LinearSequenceTemplate tail();
  Code:
   Stack=1, Locals=1, Args_size=1
   0:	aload_0
   1:	invokevirtual	#28; //Method tail:()Lscala/runtime/Nothing$;
   4:	athrow
  LineNumberTable: 
   line 382: 0


public boolean tailDefined();
  Code:
   Stack=1, Locals=1, Args_size=1
   0:	iconst_0
   1:	ireturn
  LineNumberTable: 
   line 386: 0


public scala.runtime.Nothing$ tail();
  Code:
   Stack=3, Locals=1, Args_size=1
   0:	new	#33; //class java/lang/UnsupportedOperationException
   3:	dup
   4:	ldc	#35; //String tail of empty stream
   6:	invokespecial	#38; //Method java/lang/UnsupportedOperationException."<init>":(Ljava/lang/String;)V
   9:	athrow
  LineNumberTable: 
   line 385: 0


public scala.runtime.Nothing$ head();
  Code:
   Stack=3, Locals=1, Args_size=1
   0:	new	#40; //class java/util/NoSuchElementException
   3:	dup
   4:	ldc	#42; //String head of empty stream
   6:	invokespecial	#43; //Method java/util/NoSuchElementException."<init>":(Ljava/lang/String;)V
   9:	athrow
  LineNumberTable: 
   line 384: 0


public boolean isEmpty();
  Code:
   Stack=1, Locals=1, Args_size=1
   0:	iconst_1
   1:	ireturn
  LineNumberTable: 
   line 383: 0


}

