Compiled from "StringLike.scala"
public final class scala.collection.immutable.StringLike$$anonfun$lines$1 extends scala.runtime.AbstractFunction1 implements java.io.Serializable
  SourceFile: "StringLike.scala"
  Scala: length = 0x
   
  InnerClass: 
   public final #50= #9 of #41; //$anonfun$lines$1=class scala/collection/immutable/StringLike$$anonfun$lines$1 of class scala/collection/immutable/StringLike
  minor version: 0
  major version: 49
  Constant pool:
const #1 = Asciz	SourceFile;
const #2 = Asciz	StringLike.scala;
const #3 = Asciz	<clinit>;
const #4 = Asciz	()V;
const #5 = Asciz	Code;
const #6 = Asciz	serialVersionUID;
const #7 = Asciz	J;
const #8 = Asciz	scala/collection/immutable/StringLike$$anonfun$lines$1;
const #9 = class	#8;	//  scala/collection/immutable/StringLike$$anonfun$lines$1
const #10 = NameAndType	#6:#7;//  serialVersionUID:J
const #11 = Field	#9.#10;	//  scala/collection/immutable/StringLike$$anonfun$lines$1.serialVersionUID:J
const #12 = Asciz	<init>;
const #13 = Asciz	(Lscala/collection/immutable/StringLike;)V;
const #14 = Asciz	LineNumberTable;
const #15 = Asciz	scala/runtime/AbstractFunction1;
const #16 = class	#15;	//  scala/runtime/AbstractFunction1
const #17 = NameAndType	#12:#4;//  "<init>":()V
const #18 = Method	#16.#17;	//  scala/runtime/AbstractFunction1."<init>":()V
const #19 = Asciz	this;
const #20 = Asciz	Lscala/collection/immutable/StringLike$$anonfun$lines$1;;
const #21 = Asciz	$outer;
const #22 = Asciz	Lscala/collection/immutable/StringLike;;
const #23 = Asciz	LocalVariableTable;
const #24 = Asciz	(Lscala/collection/immutable/StringLike<TRepr;>;)V;
const #25 = Asciz	Signature;
const #26 = Asciz	apply;
const #27 = Asciz	(Ljava/lang/Object;)Ljava/lang/Object;;
const #28 = Asciz	java/lang/String;
const #29 = class	#28;	//  java/lang/String
const #30 = Asciz	(Ljava/lang/String;)Ljava/lang/String;;
const #31 = NameAndType	#26:#30;//  apply:(Ljava/lang/String;)Ljava/lang/String;
const #32 = Method	#9.#31;	//  scala/collection/immutable/StringLike$$anonfun$lines$1.apply:(Ljava/lang/String;)Ljava/lang/String;
const #33 = Asciz	v1;
const #34 = Asciz	Ljava/lang/Object;;
const #35 = Asciz	scala/collection/immutable/WrappedString;
const #36 = class	#35;	//  scala/collection/immutable/WrappedString
const #37 = Asciz	(Ljava/lang/String;)V;
const #38 = NameAndType	#12:#37;//  "<init>":(Ljava/lang/String;)V
const #39 = Method	#36.#38;	//  scala/collection/immutable/WrappedString."<init>":(Ljava/lang/String;)V
const #40 = Asciz	scala/collection/immutable/StringLike;
const #41 = class	#40;	//  scala/collection/immutable/StringLike
const #42 = Asciz	stripLineEnd;
const #43 = Asciz	()Ljava/lang/String;;
const #44 = NameAndType	#42:#43;//  stripLineEnd:()Ljava/lang/String;
const #45 = InterfaceMethod	#41.#44;	//  scala/collection/immutable/StringLike.stripLineEnd:()Ljava/lang/String;
const #46 = Asciz	line;
const #47 = Asciz	Ljava/lang/String;;
const #48 = Asciz	Scala;
const #49 = Asciz	InnerClasses;
const #50 = Asciz	$anonfun$lines$1;
const #51 = Asciz	java/io/Serializable;
const #52 = class	#51;	//  java/io/Serializable

{
public static final long serialVersionUID;

public static {};
  Code:
   Stack=2, Locals=0, Args_size=0
   0:	lconst_0
   1:	putstatic	#11; //Field serialVersionUID:J
   4:	return

public scala.collection.immutable.StringLike$$anonfun$lines$1(scala.collection.immutable.StringLike);
  Code:
   Stack=1, Locals=2, Args_size=2
   0:	aload_0
   1:	invokespecial	#18; //Method scala/runtime/AbstractFunction1."<init>":()V
   4:	return
  LineNumberTable: 
   line 122: 0

  LocalVariableTable: 
   Start  Length  Slot  Name   Signature
   0      5      0    this       Lscala/collection/immutable/StringLike$$anonfun$lines$1;
   0      5      1    $outer       Lscala/collection/immutable/StringLike;

  Signature: length = 0x2
   00 18 

public final java.lang.Object apply(java.lang.Object);
  Code:
   Stack=2, Locals=2, Args_size=2
   0:	aload_0
   1:	aload_1
   2:	checkcast	#29; //class java/lang/String
   5:	invokevirtual	#32; //Method apply:(Ljava/lang/String;)Ljava/lang/String;
   8:	areturn
  LineNumberTable: 
   line 122: 0

  LocalVariableTable: 
   Start  Length  Slot  Name   Signature
   0      9      0    this       Lscala/collection/immutable/StringLike$$anonfun$lines$1;
   0      9      1    v1       Ljava/lang/Object;


public final java.lang.String apply(java.lang.String);
  Code:
   Stack=3, Locals=2, Args_size=2
   0:	new	#36; //class scala/collection/immutable/WrappedString
   3:	dup
   4:	aload_1
   5:	invokespecial	#39; //Method scala/collection/immutable/WrappedString."<init>":(Ljava/lang/String;)V
   8:	invokeinterface	#45,  1; //InterfaceMethod scala/collection/immutable/StringLike.stripLineEnd:()Ljava/lang/String;
   13:	areturn
  LineNumberTable: 
   line 122: 0

  LocalVariableTable: 
   Start  Length  Slot  Name   Signature
   0      14      0    this       Lscala/collection/immutable/StringLike$$anonfun$lines$1;
   0      14      1    line       Ljava/lang/String;


}

