Compiled from "StringLike.scala"
public final class scala.collection.immutable.StringLike$ extends java.lang.Object implements scala.ScalaObject
  SourceFile: "StringLike.scala"
  Scala: length = 0x
   
  InnerClass: 
   public final #43= #40 of #42; //$anon$1=class scala/collection/immutable/StringLike$$anon$1 of class scala/collection/immutable/StringLike
   public final #46= #45 of #42; //$anonfun$1=class scala/collection/immutable/StringLike$$anonfun$1 of class scala/collection/immutable/StringLike
   public final #49= #48 of #42; //$anonfun$lines$1=class scala/collection/immutable/StringLike$$anonfun$lines$1 of class scala/collection/immutable/StringLike
   public final #52= #51 of #42; //$anonfun$format$2=class scala/collection/immutable/StringLike$$anonfun$format$2 of class scala/collection/immutable/StringLike
   public final #55= #54 of #42; //$anonfun$format$1=class scala/collection/immutable/StringLike$$anonfun$format$1 of class scala/collection/immutable/StringLike
   public final #58= #57 of #42; //$anonfun$$times$1=class scala/collection/immutable/StringLike$$anonfun$$times$1 of class scala/collection/immutable/StringLike
   public final #61= #60 of #42; //$anonfun$stripMargin$1=class scala/collection/immutable/StringLike$$anonfun$stripMargin$1 of class scala/collection/immutable/StringLike
   public final #64= #63 of #42; //$anonfun$linesIterator$1=class scala/collection/immutable/StringLike$$anonfun$linesIterator$1 of class scala/collection/immutable/StringLike
  minor version: 0
  major version: 49
  Constant pool:
const #1 = Asciz	SourceFile;
const #2 = Asciz	StringLike.scala;
const #3 = Asciz	Scala;
const #4 = Asciz	MODULE$;
const #5 = Asciz	Lscala/collection/immutable/StringLike$;;
const #6 = Asciz	<clinit>;
const #7 = Asciz	()V;
const #8 = Asciz	Code;
const #9 = Asciz	scala/collection/immutable/StringLike$;
const #10 = class	#9;	//  scala/collection/immutable/StringLike$
const #11 = Asciz	<init>;
const #12 = NameAndType	#11:#7;//  "<init>":()V
const #13 = Method	#10.#12;	//  scala/collection/immutable/StringLike$."<init>":()V
const #14 = Asciz	SU;
const #15 = Asciz	C;
const #16 = Asciz	scala$collection$immutable$StringLike$$CR;
const #17 = Asciz	scala$collection$immutable$StringLike$$FF;
const #18 = Asciz	scala$collection$immutable$StringLike$$LF;
const #19 = Asciz	LineNumberTable;
const #20 = Asciz	java/lang/Object;
const #21 = class	#20;	//  java/lang/Object
const #22 = Method	#21.#12;	//  java/lang/Object."<init>":()V
const #23 = NameAndType	#4:#5;//  MODULE$:Lscala/collection/immutable/StringLike$;
const #24 = Field	#10.#23;	//  scala/collection/immutable/StringLike$.MODULE$:Lscala/collection/immutable/StringLike$;
const #25 = int	10;
const #26 = NameAndType	#18:#15;//  scala$collection$immutable$StringLike$$LF:C
const #27 = Field	#10.#26;	//  scala/collection/immutable/StringLike$.scala$collection$immutable$StringLike$$LF:C
const #28 = int	12;
const #29 = NameAndType	#17:#15;//  scala$collection$immutable$StringLike$$FF:C
const #30 = Field	#10.#29;	//  scala/collection/immutable/StringLike$.scala$collection$immutable$StringLike$$FF:C
const #31 = int	13;
const #32 = NameAndType	#16:#15;//  scala$collection$immutable$StringLike$$CR:C
const #33 = Field	#10.#32;	//  scala/collection/immutable/StringLike$.scala$collection$immutable$StringLike$$CR:C
const #34 = int	26;
const #35 = NameAndType	#14:#15;//  SU:C
const #36 = Field	#10.#35;	//  scala/collection/immutable/StringLike$.SU:C
const #37 = Asciz	()C;
const #38 = Asciz	InnerClasses;
const #39 = Asciz	scala/collection/immutable/StringLike$$anon$1;
const #40 = class	#39;	//  scala/collection/immutable/StringLike$$anon$1
const #41 = Asciz	scala/collection/immutable/StringLike;
const #42 = class	#41;	//  scala/collection/immutable/StringLike
const #43 = Asciz	$anon$1;
const #44 = Asciz	scala/collection/immutable/StringLike$$anonfun$1;
const #45 = class	#44;	//  scala/collection/immutable/StringLike$$anonfun$1
const #46 = Asciz	$anonfun$1;
const #47 = Asciz	scala/collection/immutable/StringLike$$anonfun$lines$1;
const #48 = class	#47;	//  scala/collection/immutable/StringLike$$anonfun$lines$1
const #49 = Asciz	$anonfun$lines$1;
const #50 = Asciz	scala/collection/immutable/StringLike$$anonfun$format$2;
const #51 = class	#50;	//  scala/collection/immutable/StringLike$$anonfun$format$2
const #52 = Asciz	$anonfun$format$2;
const #53 = Asciz	scala/collection/immutable/StringLike$$anonfun$format$1;
const #54 = class	#53;	//  scala/collection/immutable/StringLike$$anonfun$format$1
const #55 = Asciz	$anonfun$format$1;
const #56 = Asciz	scala/collection/immutable/StringLike$$anonfun$$times$1;
const #57 = class	#56;	//  scala/collection/immutable/StringLike$$anonfun$$times$1
const #58 = Asciz	$anonfun$$times$1;
const #59 = Asciz	scala/collection/immutable/StringLike$$anonfun$stripMargin$1;
const #60 = class	#59;	//  scala/collection/immutable/StringLike$$anonfun$stripMargin$1
const #61 = Asciz	$anonfun$stripMargin$1;
const #62 = Asciz	scala/collection/immutable/StringLike$$anonfun$linesIterator$1;
const #63 = class	#62;	//  scala/collection/immutable/StringLike$$anonfun$linesIterator$1
const #64 = Asciz	$anonfun$linesIterator$1;
const #65 = Asciz	scala/ScalaObject;
const #66 = class	#65;	//  scala/ScalaObject

{
public static final scala.collection.immutable.StringLike$ MODULE$;

public static {};
  Code:
   Stack=1, Locals=0, Args_size=0
   0:	new	#10; //class scala/collection/immutable/StringLike$
   3:	invokespecial	#13; //Method "<init>":()V
   6:	return

public final char scala$collection$immutable$StringLike$$CR();
  Code:
   Stack=1, Locals=1, Args_size=1
   0:	aload_0
   1:	getfield	#33; //Field scala$collection$immutable$StringLike$$CR:C
   4:	ireturn
  LineNumberTable: 
   line 28: 0


public final char scala$collection$immutable$StringLike$$FF();
  Code:
   Stack=1, Locals=1, Args_size=1
   0:	aload_0
   1:	getfield	#30; //Field scala$collection$immutable$StringLike$$FF:C
   4:	ireturn
  LineNumberTable: 
   line 27: 0


public final char scala$collection$immutable$StringLike$$LF();
  Code:
   Stack=1, Locals=1, Args_size=1
   0:	aload_0
   1:	getfield	#27; //Field scala$collection$immutable$StringLike$$LF:C
   4:	ireturn
  LineNumberTable: 
   line 26: 0


}

