Compiled from "StringLike.scala"
public final class scala.collection.immutable.StringLike$$anonfun$$times$1 extends java.lang.Object implements scala.Function1,scala.ScalaObject,java.io.Serializable
  SourceFile: "StringLike.scala"
  Scala: length = 0x
   
  InnerClass: 
   public final $anonfun$$times$1=class scala/collection/immutable/StringLike$$anonfun$$times$1 of class scala/collection/immutable/StringLike
  minor version: 0
  major version: 49
  Constant pool:
Asciz	SourceFile;
Asciz	StringLike.scala;
Asciz	<clinit>;
Asciz	()V;
Asciz	Code;
Asciz	serialVersionUID;
Asciz	J;
Asciz	scala/collection/immutable/StringLike$$anonfun$$times$1;
class	scala/collection/immutable/StringLike$$anonfun$$times$1
NameAndType	serialVersionUID:J
Field	scala/collection/immutable/StringLike$$anonfun$$times$1.serialVersionUID:J
Asciz	buf$1;
Asciz	Lscala/collection/mutable/StringBuilder;;
Asciz	$outer;
Asciz	Lscala/collection/immutable/StringLike;;
Asciz	<init>;
Asciz	(Lscala/collection/immutable/StringLike;Lscala/collection/mutable/StringBuilder;)V;
Asciz	LineNumberTable;
Asciz	java/lang/NullPointerException;
class	java/lang/NullPointerException
NameAndType	"<init>":()V
Method	java/lang/NullPointerException."<init>":()V
NameAndType	$outer:Lscala/collection/immutable/StringLike;
Field	scala/collection/immutable/StringLike$$anonfun$$times$1.$outer:Lscala/collection/immutable/StringLike;
NameAndType	buf$1:Lscala/collection/mutable/StringBuilder;
Field	scala/collection/immutable/StringLike$$anonfun$$times$1.buf$1:Lscala/collection/mutable/StringBuilder;
Asciz	java/lang/Object;
class	java/lang/Object
Method	java/lang/Object."<init>":()V
Asciz	scala/Function1$class;
class	scala/Function1$class
Asciz	$init$;
Asciz	(Lscala/Function1;)V;
NameAndType	$init$:(Lscala/Function1;)V
Method	scala/Function1$class.$init$:(Lscala/Function1;)V
Asciz	this;
Asciz	Lscala/collection/immutable/StringLike$$anonfun$$times$1;;
Asciz	LocalVariableTable;
Asciz	(Lscala/collection/immutable/StringLike<TRepr;>;)V;
Asciz	Signature;
Asciz	apply;
Asciz	(Ljava/lang/Object;)Ljava/lang/Object;;
Asciz	scala/runtime/BoxesRunTime;
class	scala/runtime/BoxesRunTime
Asciz	unboxToInt;
Asciz	(Ljava/lang/Object;)I;
NameAndType	unboxToInt:(Ljava/lang/Object;)I
Method	scala/runtime/BoxesRunTime.unboxToInt:(Ljava/lang/Object;)I
Asciz	(I)Lscala/collection/mutable/StringBuilder;;
NameAndType	apply:(I)Lscala/collection/mutable/StringBuilder;
Method	scala/collection/immutable/StringLike$$anonfun$$times$1.apply:(I)Lscala/collection/mutable/StringBuilder;
Asciz	v1;
Asciz	Ljava/lang/Object;;
Asciz	scala/collection/SeqLike;
class	scala/collection/SeqLike
Asciz	toString;
Asciz	()Ljava/lang/String;;
NameAndType	toString:()Ljava/lang/String;
InterfaceMethod	scala/collection/SeqLike.toString:()Ljava/lang/String;
Asciz	scala/collection/mutable/StringBuilder;
class	scala/collection/mutable/StringBuilder
Asciz	append;
Asciz	(Ljava/lang/String;)Lscala/collection/mutable/StringBuilder;;
NameAndType	append:(Ljava/lang/String;)Lscala/collection/mutable/StringBuilder;
Method	scala/collection/mutable/StringBuilder.append:(Ljava/lang/String;)Lscala/collection/mutable/StringBuilder;
Asciz	i;
Asciz	I;
Asciz	andThen;
Asciz	(Lscala/Function1;)Lscala/Function1;;
Asciz	(Lscala/Function1;Lscala/Function1;)Lscala/Function1;;
NameAndType	andThen:(Lscala/Function1;Lscala/Function1;)Lscala/Function1;
Method	scala/Function1$class.andThen:(Lscala/Function1;Lscala/Function1;)Lscala/Function1;
Asciz	g;
Asciz	Lscala/Function1;;
Asciz	compose;
NameAndType	compose:(Lscala/Function1;Lscala/Function1;)Lscala/Function1;
Method	scala/Function1$class.compose:(Lscala/Function1;Lscala/Function1;)Lscala/Function1;
Asciz	(Lscala/Function1;)Ljava/lang/String;;
NameAndType	toString:(Lscala/Function1;)Ljava/lang/String;
Method	scala/Function1$class.toString:(Lscala/Function1;)Ljava/lang/String;
Asciz	Scala;
Asciz	InnerClasses;
Asciz	scala/collection/immutable/StringLike;
class	scala/collection/immutable/StringLike
Asciz	$anonfun$$times$1;
Asciz	scala/Function1;
class	scala/Function1
Asciz	scala/ScalaObject;
class	scala/ScalaObject
Asciz	java/io/Serializable;
class	java/io/Serializable

{
public static final long serialVersionUID;
  Signature: J

private final scala.collection.mutable.StringBuilder buf$1;
  Signature: Lscala/collection/mutable/StringBuilder;

private final scala.collection.immutable.StringLike $outer;
  Signature: Lscala/collection/immutable/StringLike;

public static {};
  Signature: ()V
  Code:
   Stack=2, Locals=0, Args_size=0
	lconst_0
	putstatic	Field serialVersionUID:J
	return
  Labels:

public scala.collection.immutable.StringLike$$anonfun$$times$1(scala.collection.immutable.StringLike, scala.collection.mutable.StringBuilder);
  Signature: (Lscala/collection/immutable/StringLike;Lscala/collection/mutable/StringBuilder;)V
  Code:
   Stack=2, Locals=3, Args_size=3
	aload_1
	ifnonnull	l1 // aload_0
	new	class java/lang/NullPointerException
	dup
	invokespecial	Method java/lang/NullPointerException."<init>":()V
	athrow
l1	aload_0
	aload_1
	putfield	Field $outer:Lscala/collection/immutable/StringLike;
	aload_0
	aload_2
	putfield	Field buf$1:Lscala/collection/mutable/StringBuilder;
	aload_0
	invokespecial	Method java/lang/Object."<init>":()V
	aload_0
	invokestatic	Method scala/Function1$class.$init$:(Lscala/Function1;)V
	return
  Labels:
   	l1 = 12 // aload_0
  LocalVariableTable: 
   Start  Length  Slot  Name   Signature
   0      31      0    this       Lscala/collection/immutable/StringLike$$anonfun$$times$1;
   0      31      1    $outer       Lscala/collection/immutable/StringLike;

  Signature: length = 0x2
   00 27 

public final java.lang.Object apply(java.lang.Object);
  Signature: (Ljava/lang/Object;)Ljava/lang/Object;
  Code:
   Stack=2, Locals=3, Args_size=2
	aload_0
	getfield	Field $outer:Lscala/collection/immutable/StringLike;
	astore_2
	aload_0
	aload_1
	invokestatic	Method scala/runtime/BoxesRunTime.unboxToInt:(Ljava/lang/Object;)I
	invokevirtual	Method apply:(I)Lscala/collection/mutable/StringBuilder;
	areturn
  Labels:
  LocalVariableTable: 
   Start  Length  Slot  Name   Signature
   0      14      0    this       Lscala/collection/immutable/StringLike$$anonfun$$times$1;
   5      9      1    v1       Ljava/lang/Object;


public final scala.collection.mutable.StringBuilder apply(int);
  Signature: (I)Lscala/collection/mutable/StringBuilder;
  Code:
   Stack=2, Locals=3, Args_size=2
	aload_0
	getfield	Field $outer:Lscala/collection/immutable/StringLike;
	astore_2
	aload_0
	getfield	Field buf$1:Lscala/collection/mutable/StringBuilder;
	aload_0
	getfield	Field $outer:Lscala/collection/immutable/StringLike;
	invokeinterface	InterfaceMethod scala/collection/SeqLike.toString:()Ljava/lang/String;
	invokevirtual	Method scala/collection/mutable/StringBuilder.append:(Ljava/lang/String;)Lscala/collection/mutable/StringBuilder;
	areturn
  Labels:
  LocalVariableTable: 
   Start  Length  Slot  Name   Signature
   0      22      0    this       Lscala/collection/immutable/StringLike$$anonfun$$times$1;
   5      17      1    i       I


public scala.Function1 andThen(scala.Function1);
  Signature: (Lscala/Function1;)Lscala/Function1;
  Code:
   Stack=2, Locals=2, Args_size=2
	aload_0
	aload_1
	invokestatic	Method scala/Function1$class.andThen:(Lscala/Function1;Lscala/Function1;)Lscala/Function1;
	areturn
  Labels:
  LocalVariableTable: 
   Start  Length  Slot  Name   Signature
   0      6      0    this       Lscala/collection/immutable/StringLike$$anonfun$$times$1;
   0      6      1    g       Lscala/Function1;


public scala.Function1 compose(scala.Function1);
  Signature: (Lscala/Function1;)Lscala/Function1;
  Code:
   Stack=2, Locals=2, Args_size=2
	aload_0
	aload_1
	invokestatic	Method scala/Function1$class.compose:(Lscala/Function1;Lscala/Function1;)Lscala/Function1;
	areturn
  Labels:
  LocalVariableTable: 
   Start  Length  Slot  Name   Signature
   0      6      0    this       Lscala/collection/immutable/StringLike$$anonfun$$times$1;
   0      6      1    g       Lscala/Function1;


public java.lang.String toString();
  Signature: ()Ljava/lang/String;
  Code:
   Stack=1, Locals=1, Args_size=1
	aload_0
	invokestatic	Method scala/Function1$class.toString:(Lscala/Function1;)Ljava/lang/String;
	areturn
  Labels:

}

