Compiled from "StringLike.scala"
public abstract class scala.collection.immutable.StringLike$class extends java.lang.Object
  SourceFile: "StringLike.scala"
  Scala: length = 0x
   
  InnerClass: 
   public abstract #390= #372 of #389; //ByOne=class scala/collection/immutable/Range$ByOne of class scala/collection/immutable/Range
   public final #391= #323 of #246; //$anon$1=class scala/collection/immutable/StringLike$$anon$1 of class scala/collection/immutable/StringLike
   public final #392= #205 of #246; //$anonfun$1=class scala/collection/immutable/StringLike$$anonfun$1 of class scala/collection/immutable/StringLike
   public final #393= #320 of #246; //$anonfun$lines$1=class scala/collection/immutable/StringLike$$anonfun$lines$1 of class scala/collection/immutable/StringLike
   public final #394= #374 of #246; //$anonfun$$times$1=class scala/collection/immutable/StringLike$$anonfun$$times$1 of class scala/collection/immutable/StringLike
   public final #395= #65 of #246; //$anonfun$format$1=class scala/collection/immutable/StringLike$$anonfun$format$1 of class scala/collection/immutable/StringLike
   public final #396= #19 of #246; //$anonfun$format$2=class scala/collection/immutable/StringLike$$anonfun$format$2 of class scala/collection/immutable/StringLike
   public final #397= #256 of #246; //$anonfun$stripMargin$1=class scala/collection/immutable/StringLike$$anonfun$stripMargin$1 of class scala/collection/immutable/StringLike
   public final #398= #313 of #246; //$anonfun$linesIterator$1=class scala/collection/immutable/StringLike$$anonfun$linesIterator$1 of class scala/collection/immutable/StringLike
  minor version: 0
  major version: 49
  Constant pool:
const #1 = Asciz	SourceFile;
const #2 = Asciz	StringLike.scala;
const #3 = Asciz	$init$;
const #4 = Asciz	(Lscala/collection/immutable/StringLike;)V;
const #5 = Asciz	Code;
const #6 = Asciz	LineNumberTable;
const #7 = Asciz	$this;
const #8 = Asciz	Lscala/collection/immutable/StringLike;;
const #9 = Asciz	LocalVariableTable;
const #10 = Asciz	format;
const #11 = Asciz	(Lscala/collection/immutable/StringLike;Ljava/util/Locale;Lscala/collection/Seq;)Ljava/lang/String;;
const #12 = Asciz	scala/collection/SeqLike;
const #13 = class	#12;	//  scala/collection/SeqLike
const #14 = Asciz	toString;
const #15 = Asciz	()Ljava/lang/String;;
const #16 = NameAndType	#14:#15;//  toString:()Ljava/lang/String;
const #17 = InterfaceMethod	#13.#16;	//  scala/collection/SeqLike.toString:()Ljava/lang/String;
const #18 = Asciz	scala/collection/immutable/StringLike$$anonfun$format$2;
const #19 = class	#18;	//  scala/collection/immutable/StringLike$$anonfun$format$2
const #20 = Asciz	<init>;
const #21 = NameAndType	#20:#4;//  "<init>":(Lscala/collection/immutable/StringLike;)V
const #22 = Method	#19.#21;	//  scala/collection/immutable/StringLike$$anonfun$format$2."<init>":(Lscala/collection/immutable/StringLike;)V
const #23 = Asciz	scala/collection/Seq$;
const #24 = class	#23;	//  scala/collection/Seq$
const #25 = Asciz	MODULE$;
const #26 = Asciz	Lscala/collection/Seq$;;
const #27 = NameAndType	#25:#26;//  MODULE$:Lscala/collection/Seq$;
const #28 = Field	#24.#27;	//  scala/collection/Seq$.MODULE$:Lscala/collection/Seq$;
const #29 = Asciz	canBuildFrom;
const #30 = Asciz	()Lscala/collection/generic/CanBuildFrom;;
const #31 = NameAndType	#29:#30;//  canBuildFrom:()Lscala/collection/generic/CanBuildFrom;
const #32 = Method	#24.#31;	//  scala/collection/Seq$.canBuildFrom:()Lscala/collection/generic/CanBuildFrom;
const #33 = Asciz	scala/collection/TraversableLike;
const #34 = class	#33;	//  scala/collection/TraversableLike
const #35 = Asciz	map;
const #36 = Asciz	(Lscala/Function1;Lscala/collection/generic/CanBuildFrom;)Ljava/lang/Object;;
const #37 = NameAndType	#35:#36;//  map:(Lscala/Function1;Lscala/collection/generic/CanBuildFrom;)Ljava/lang/Object;
const #38 = InterfaceMethod	#34.#37;	//  scala/collection/TraversableLike.map:(Lscala/Function1;Lscala/collection/generic/CanBuildFrom;)Ljava/lang/Object;
const #39 = Asciz	scala/reflect/Manifest$;
const #40 = class	#39;	//  scala/reflect/Manifest$
const #41 = Asciz	Lscala/reflect/Manifest$;;
const #42 = NameAndType	#25:#41;//  MODULE$:Lscala/reflect/Manifest$;
const #43 = Field	#40.#42;	//  scala/reflect/Manifest$.MODULE$:Lscala/reflect/Manifest$;
const #44 = Asciz	Object;
const #45 = Asciz	()Lscala/reflect/Manifest;;
const #46 = NameAndType	#44:#45;//  Object:()Lscala/reflect/Manifest;
const #47 = Method	#40.#46;	//  scala/reflect/Manifest$.Object:()Lscala/reflect/Manifest;
const #48 = Asciz	toArray;
const #49 = Asciz	(Lscala/reflect/ClassManifest;)Ljava/lang/Object;;
const #50 = NameAndType	#48:#49;//  toArray:(Lscala/reflect/ClassManifest;)Ljava/lang/Object;
const #51 = InterfaceMethod	#34.#50;	//  scala/collection/TraversableLike.toArray:(Lscala/reflect/ClassManifest;)Ljava/lang/Object;
const #52 = Asciz	[Ljava/lang/Object;;
const #53 = class	#52;	//  "[Ljava/lang/Object;"
const #54 = Asciz	java/lang/String;
const #55 = class	#54;	//  java/lang/String
const #56 = Asciz	(Ljava/util/Locale;Ljava/lang/String;[Ljava/lang/Object;)Ljava/lang/String;;
const #57 = NameAndType	#10:#56;//  format:(Ljava/util/Locale;Ljava/lang/String;[Ljava/lang/Object;)Ljava/lang/String;
const #58 = Method	#55.#57;	//  java/lang/String.format:(Ljava/util/Locale;Ljava/lang/String;[Ljava/lang/Object;)Ljava/lang/String;
const #59 = Asciz	l;
const #60 = Asciz	Ljava/util/Locale;;
const #61 = Asciz	args;
const #62 = Asciz	Lscala/collection/Seq;;
const #63 = Asciz	(Lscala/collection/immutable/StringLike;Lscala/collection/Seq;)Ljava/lang/String;;
const #64 = Asciz	scala/collection/immutable/StringLike$$anonfun$format$1;
const #65 = class	#64;	//  scala/collection/immutable/StringLike$$anonfun$format$1
const #66 = Method	#65.#21;	//  scala/collection/immutable/StringLike$$anonfun$format$1."<init>":(Lscala/collection/immutable/StringLike;)V
const #67 = Asciz	(Ljava/lang/String;[Ljava/lang/Object;)Ljava/lang/String;;
const #68 = NameAndType	#10:#67;//  format:(Ljava/lang/String;[Ljava/lang/Object;)Ljava/lang/String;
const #69 = Method	#55.#68;	//  java/lang/String.format:(Ljava/lang/String;[Ljava/lang/Object;)Ljava/lang/String;
const #70 = Asciz	scala$collection$immutable$StringLike$$unwrapArg;
const #71 = Asciz	(Lscala/collection/immutable/StringLike;Ljava/lang/Object;)Ljava/lang/Object;;
const #72 = Asciz	scala/math/ScalaNumber;
const #73 = class	#72;	//  scala/math/ScalaNumber
const #74 = Asciz	underlying;
const #75 = Asciz	()Ljava/lang/Object;;
const #76 = NameAndType	#74:#75;//  underlying:()Ljava/lang/Object;
const #77 = Method	#73.#76;	//  scala/math/ScalaNumber.underlying:()Ljava/lang/Object;
const #78 = Asciz	scala/MatchError;
const #79 = class	#78;	//  scala/MatchError
const #80 = Asciz	java/lang/Object;
const #81 = class	#80;	//  java/lang/Object
const #82 = Method	#81.#16;	//  java/lang/Object.toString:()Ljava/lang/String;
const #83 = Asciz	(Ljava/lang/String;)V;
const #84 = NameAndType	#20:#83;//  "<init>":(Ljava/lang/String;)V
const #85 = Method	#79.#84;	//  scala/MatchError."<init>":(Ljava/lang/String;)V
const #86 = Asciz	arg;
const #87 = Asciz	Ljava/lang/Object;;
const #88 = Asciz	temp5;
const #89 = Asciz	Lscala/math/ScalaNumber;;
const #90 = Asciz	parseBoolean;
const #91 = Asciz	(Lscala/collection/immutable/StringLike;Ljava/lang/String;)Z;
const #92 = Asciz	equals;
const #93 = Asciz	(Ljava/lang/Object;)Z;
const #94 = NameAndType	#92:#93;//  equals:(Ljava/lang/Object;)Z
const #95 = Method	#81.#94;	//  java/lang/Object.equals:(Ljava/lang/Object;)Z
const #96 = Asciz	java/lang/NumberFormatException;
const #97 = class	#96;	//  java/lang/NumberFormatException
const #98 = Asciz	For input string: \"null\";
const #99 = String	#98;	//  For input string: \"null\"
const #100 = Method	#97.#84;	//  java/lang/NumberFormatException."<init>":(Ljava/lang/String;)V
const #101 = Asciz	toLowerCase;
const #102 = NameAndType	#101:#15;//  toLowerCase:()Ljava/lang/String;
const #103 = Method	#55.#102;	//  java/lang/String.toLowerCase:()Ljava/lang/String;
const #104 = Asciz	true;
const #105 = String	#104;	//  true
const #106 = Method	#55.#16;	//  java/lang/String.toString:()Ljava/lang/String;
const #107 = Asciz	false;
const #108 = String	#107;	//  false
const #109 = Asciz	scala/collection/mutable/StringBuilder;
const #110 = class	#109;	//  scala/collection/mutable/StringBuilder
const #111 = Asciz	()V;
const #112 = NameAndType	#20:#111;//  "<init>":()V
const #113 = Method	#110.#112;	//  scala/collection/mutable/StringBuilder."<init>":()V
const #114 = Asciz	For input string: \";
const #115 = String	#114;	//  For input string: \"
const #116 = Asciz	append;
const #117 = Asciz	(Ljava/lang/Object;)Lscala/collection/mutable/StringBuilder;;
const #118 = NameAndType	#116:#117;//  append:(Ljava/lang/Object;)Lscala/collection/mutable/StringBuilder;
const #119 = Method	#110.#118;	//  scala/collection/mutable/StringBuilder.append:(Ljava/lang/Object;)Lscala/collection/mutable/StringBuilder;
const #120 = Asciz	\";
const #121 = String	#120;	//  \"
const #122 = Method	#110.#16;	//  scala/collection/mutable/StringBuilder.toString:()Ljava/lang/String;
const #123 = Asciz	s;
const #124 = Asciz	Ljava/lang/String;;
const #125 = Asciz	temp1;
const #126 = Asciz	toDouble;
const #127 = Asciz	(Lscala/collection/immutable/StringLike;)D;
const #128 = Asciz	java/lang/Double;
const #129 = class	#128;	//  java/lang/Double
const #130 = Asciz	parseDouble;
const #131 = Asciz	(Ljava/lang/String;)D;
const #132 = NameAndType	#130:#131;//  parseDouble:(Ljava/lang/String;)D
const #133 = Method	#129.#132;	//  java/lang/Double.parseDouble:(Ljava/lang/String;)D
const #134 = Asciz	toFloat;
const #135 = Asciz	(Lscala/collection/immutable/StringLike;)F;
const #136 = Asciz	java/lang/Float;
const #137 = class	#136;	//  java/lang/Float
const #138 = Asciz	parseFloat;
const #139 = Asciz	(Ljava/lang/String;)F;
const #140 = NameAndType	#138:#139;//  parseFloat:(Ljava/lang/String;)F
const #141 = Method	#137.#140;	//  java/lang/Float.parseFloat:(Ljava/lang/String;)F
const #142 = Asciz	toLong;
const #143 = Asciz	(Lscala/collection/immutable/StringLike;)J;
const #144 = Asciz	java/lang/Long;
const #145 = class	#144;	//  java/lang/Long
const #146 = Asciz	parseLong;
const #147 = Asciz	(Ljava/lang/String;)J;
const #148 = NameAndType	#146:#147;//  parseLong:(Ljava/lang/String;)J
const #149 = Method	#145.#148;	//  java/lang/Long.parseLong:(Ljava/lang/String;)J
const #150 = Asciz	toInt;
const #151 = Asciz	(Lscala/collection/immutable/StringLike;)I;
const #152 = Asciz	java/lang/Integer;
const #153 = class	#152;	//  java/lang/Integer
const #154 = Asciz	parseInt;
const #155 = Asciz	(Ljava/lang/String;)I;
const #156 = NameAndType	#154:#155;//  parseInt:(Ljava/lang/String;)I
const #157 = Method	#153.#156;	//  java/lang/Integer.parseInt:(Ljava/lang/String;)I
const #158 = Asciz	toShort;
const #159 = Asciz	(Lscala/collection/immutable/StringLike;)S;
const #160 = Asciz	java/lang/Short;
const #161 = class	#160;	//  java/lang/Short
const #162 = Asciz	parseShort;
const #163 = Asciz	(Ljava/lang/String;)S;
const #164 = NameAndType	#162:#163;//  parseShort:(Ljava/lang/String;)S
const #165 = Method	#161.#164;	//  java/lang/Short.parseShort:(Ljava/lang/String;)S
const #166 = Asciz	toByte;
const #167 = Asciz	(Lscala/collection/immutable/StringLike;)B;
const #168 = Asciz	java/lang/Byte;
const #169 = class	#168;	//  java/lang/Byte
const #170 = Asciz	parseByte;
const #171 = Asciz	(Ljava/lang/String;)B;
const #172 = NameAndType	#170:#171;//  parseByte:(Ljava/lang/String;)B
const #173 = Method	#169.#172;	//  java/lang/Byte.parseByte:(Ljava/lang/String;)B
const #174 = Asciz	toBoolean;
const #175 = Asciz	(Lscala/collection/immutable/StringLike;)Z;
const #176 = Asciz	scala/collection/immutable/StringLike$class;
const #177 = class	#176;	//  scala/collection/immutable/StringLike$class
const #178 = NameAndType	#90:#91;//  parseBoolean:(Lscala/collection/immutable/StringLike;Ljava/lang/String;)Z
const #179 = Method	#177.#178;	//  scala/collection/immutable/StringLike$class.parseBoolean:(Lscala/collection/immutable/StringLike;Ljava/lang/String;)Z
const #180 = Asciz	r;
const #181 = Asciz	(Lscala/collection/immutable/StringLike;)Lscala/util/matching/Regex;;
const #182 = Asciz	scala/util/matching/Regex;
const #183 = class	#182;	//  scala/util/matching/Regex
const #184 = Asciz	scala/Predef$;
const #185 = class	#184;	//  scala/Predef$
const #186 = Asciz	Lscala/Predef$;;
const #187 = NameAndType	#25:#186;//  MODULE$:Lscala/Predef$;
const #188 = Field	#185.#187;	//  scala/Predef$.MODULE$:Lscala/Predef$;
const #189 = Asciz	wrapRefArray;
const #190 = Asciz	([Ljava/lang/Object;)Lscala/collection/mutable/WrappedArray;;
const #191 = NameAndType	#189:#190;//  wrapRefArray:([Ljava/lang/Object;)Lscala/collection/mutable/WrappedArray;
const #192 = Method	#185.#191;	//  scala/Predef$.wrapRefArray:([Ljava/lang/Object;)Lscala/collection/mutable/WrappedArray;
const #193 = Asciz	(Ljava/lang/String;Lscala/collection/Seq;)V;
const #194 = NameAndType	#20:#193;//  "<init>":(Ljava/lang/String;Lscala/collection/Seq;)V
const #195 = Method	#183.#194;	//  scala/util/matching/Regex."<init>":(Ljava/lang/String;Lscala/collection/Seq;)V
const #196 = Asciz	split;
const #197 = Asciz	(Lscala/collection/immutable/StringLike;[C)[Ljava/lang/String;;
const #198 = Asciz	charArrayOps;
const #199 = Asciz	([C)Lscala/collection/mutable/ArrayOps;;
const #200 = NameAndType	#198:#199;//  charArrayOps:([C)Lscala/collection/mutable/ArrayOps;
const #201 = Method	#185.#200;	//  scala/Predef$.charArrayOps:([C)Lscala/collection/mutable/ArrayOps;
const #202 = Asciz	[;
const #203 = String	#202;	//  [
const #204 = Asciz	scala/collection/immutable/StringLike$$anonfun$1;
const #205 = class	#204;	//  scala/collection/immutable/StringLike$$anonfun$1
const #206 = Method	#205.#21;	//  scala/collection/immutable/StringLike$$anonfun$1."<init>":(Lscala/collection/immutable/StringLike;)V
const #207 = Asciz	scala/collection/IndexedSeqLike;
const #208 = class	#207;	//  scala/collection/IndexedSeqLike
const #209 = Asciz	foldLeft;
const #210 = Asciz	(Ljava/lang/Object;Lscala/Function2;)Ljava/lang/Object;;
const #211 = NameAndType	#209:#210;//  foldLeft:(Ljava/lang/Object;Lscala/Function2;)Ljava/lang/Object;
const #212 = InterfaceMethod	#208.#211;	//  scala/collection/IndexedSeqLike.foldLeft:(Ljava/lang/Object;Lscala/Function2;)Ljava/lang/Object;
const #213 = Asciz	];
const #214 = String	#213;	//  ]
const #215 = Asciz	(Ljava/lang/String;)[Ljava/lang/String;;
const #216 = NameAndType	#196:#215;//  split:(Ljava/lang/String;)[Ljava/lang/String;
const #217 = Method	#55.#216;	//  java/lang/String.split:(Ljava/lang/String;)[Ljava/lang/String;
const #218 = Asciz	separators;
const #219 = Asciz	[C;
const #220 = Asciz	re;
const #221 = Asciz	java/util/regex/PatternSyntaxException;
const #222 = class	#221;	//  java/util/regex/PatternSyntaxException
const #223 = Asciz	Exceptions;
const #224 = Asciz	(Lscala/collection/immutable/StringLike;C)[Ljava/lang/String;;
const #225 = Asciz	scala$collection$immutable$StringLike$$escape;
const #226 = Asciz	(Lscala/collection/immutable/StringLike;C)Ljava/lang/String;;
const #227 = NameAndType	#225:#226;//  scala$collection$immutable$StringLike$$escape:(Lscala/collection/immutable/StringLike;C)Ljava/lang/String;
const #228 = Method	#177.#227;	//  scala/collection/immutable/StringLike$class.scala$collection$immutable$StringLike$$escape:(Lscala/collection/immutable/StringLike;C)Ljava/lang/String;
const #229 = Asciz	separator;
const #230 = Asciz	C;
const #231 = Asciz	\Q;
const #232 = String	#231;	//  \Q
const #233 = Asciz	scala/runtime/BoxesRunTime;
const #234 = class	#233;	//  scala/runtime/BoxesRunTime
const #235 = Asciz	boxToCharacter;
const #236 = Asciz	(C)Ljava/lang/Character;;
const #237 = NameAndType	#235:#236;//  boxToCharacter:(C)Ljava/lang/Character;
const #238 = Method	#234.#237;	//  scala/runtime/BoxesRunTime.boxToCharacter:(C)Ljava/lang/Character;
const #239 = Asciz	\E;
const #240 = String	#239;	//  \E
const #241 = Asciz	ch;
const #242 = Asciz	stripMargin;
const #243 = Asciz	(Lscala/collection/immutable/StringLike;)Ljava/lang/String;;
const #244 = int	124;
const #245 = Asciz	scala/collection/immutable/StringLike;
const #246 = class	#245;	//  scala/collection/immutable/StringLike
const #247 = Asciz	(C)Ljava/lang/String;;
const #248 = NameAndType	#242:#247;//  stripMargin:(C)Ljava/lang/String;
const #249 = InterfaceMethod	#246.#248;	//  scala/collection/immutable/StringLike.stripMargin:(C)Ljava/lang/String;
const #250 = Method	#110.#112;	//  scala/collection/mutable/StringBuilder."<init>":()V
const #251 = Asciz	linesWithSeparators;
const #252 = Asciz	()Lscala/collection/Iterator;;
const #253 = NameAndType	#251:#252;//  linesWithSeparators:()Lscala/collection/Iterator;
const #254 = InterfaceMethod	#246.#253;	//  scala/collection/immutable/StringLike.linesWithSeparators:()Lscala/collection/Iterator;
const #255 = Asciz	scala/collection/immutable/StringLike$$anonfun$stripMargin$1;
const #256 = class	#255;	//  scala/collection/immutable/StringLike$$anonfun$stripMargin$1
const #257 = Asciz	(Lscala/collection/immutable/StringLike;CLscala/collection/mutable/StringBuilder;)V;
const #258 = NameAndType	#20:#257;//  "<init>":(Lscala/collection/immutable/StringLike;CLscala/collection/mutable/StringBuilder;)V
const #259 = Method	#256.#258;	//  scala/collection/immutable/StringLike$$anonfun$stripMargin$1."<init>":(Lscala/collection/immutable/StringLike;CLscala/collection/mutable/StringBuilder;)V
const #260 = Asciz	scala/collection/Iterator;
const #261 = class	#260;	//  scala/collection/Iterator
const #262 = Asciz	foreach;
const #263 = Asciz	(Lscala/Function1;)V;
const #264 = NameAndType	#262:#263;//  foreach:(Lscala/Function1;)V
const #265 = InterfaceMethod	#261.#264;	//  scala/collection/Iterator.foreach:(Lscala/Function1;)V
const #266 = Method	#110.#16;	//  scala/collection/mutable/StringBuilder.toString:()Ljava/lang/String;
const #267 = Asciz	marginChar$1;
const #268 = Asciz	buf$2;
const #269 = Asciz	Lscala/collection/mutable/StringBuilder;;
const #270 = Asciz	stripSuffix;
const #271 = Asciz	(Lscala/collection/immutable/StringLike;Ljava/lang/String;)Ljava/lang/String;;
const #272 = Asciz	endsWith;
const #273 = Asciz	(Ljava/lang/String;)Z;
const #274 = NameAndType	#272:#273;//  endsWith:(Ljava/lang/String;)Z
const #275 = Method	#55.#274;	//  java/lang/String.endsWith:(Ljava/lang/String;)Z
const #276 = Asciz	length;
const #277 = Asciz	()I;
const #278 = NameAndType	#276:#277;//  length:()I
const #279 = Method	#55.#278;	//  java/lang/String.length:()I
const #280 = Asciz	substring;
const #281 = Asciz	(II)Ljava/lang/String;;
const #282 = NameAndType	#280:#281;//  substring:(II)Ljava/lang/String;
const #283 = Method	#55.#282;	//  java/lang/String.substring:(II)Ljava/lang/String;
const #284 = Asciz	suffix;
const #285 = Asciz	stripPrefix;
const #286 = Asciz	startsWith;
const #287 = NameAndType	#286:#273;//  startsWith:(Ljava/lang/String;)Z
const #288 = Method	#55.#287;	//  java/lang/String.startsWith:(Ljava/lang/String;)Z
const #289 = Asciz	(I)Ljava/lang/String;;
const #290 = NameAndType	#280:#289;//  substring:(I)Ljava/lang/String;
const #291 = Method	#55.#290;	//  java/lang/String.substring:(I)Ljava/lang/String;
const #292 = Asciz	prefix;
const #293 = Asciz	capitalize;
const #294 = Asciz	;
const #295 = String	#294;	//  
const #296 = Asciz	toCharArray;
const #297 = Asciz	()[C;
const #298 = NameAndType	#296:#297;//  toCharArray:()[C
const #299 = Method	#55.#298;	//  java/lang/String.toCharArray:()[C
const #300 = Asciz	java/lang/Character;
const #301 = class	#300;	//  java/lang/Character
const #302 = Asciz	toUpperCase;
const #303 = Asciz	(C)C;
const #304 = NameAndType	#302:#303;//  toUpperCase:(C)C
const #305 = Method	#301.#304;	//  java/lang/Character.toUpperCase:(C)C
const #306 = Asciz	([C)V;
const #307 = NameAndType	#20:#306;//  "<init>":([C)V
const #308 = Method	#55.#307;	//  java/lang/String."<init>":([C)V
const #309 = Asciz	chars;
const #310 = Asciz	linesIterator;
const #311 = Asciz	(Lscala/collection/immutable/StringLike;)Lscala/collection/Iterator;;
const #312 = Asciz	scala/collection/immutable/StringLike$$anonfun$linesIterator$1;
const #313 = class	#312;	//  scala/collection/immutable/StringLike$$anonfun$linesIterator$1
const #314 = Method	#313.#21;	//  scala/collection/immutable/StringLike$$anonfun$linesIterator$1."<init>":(Lscala/collection/immutable/StringLike;)V
const #315 = Asciz	(Lscala/Function1;)Lscala/collection/Iterator;;
const #316 = NameAndType	#35:#315;//  map:(Lscala/Function1;)Lscala/collection/Iterator;
const #317 = InterfaceMethod	#261.#316;	//  scala/collection/Iterator.map:(Lscala/Function1;)Lscala/collection/Iterator;
const #318 = Asciz	lines;
const #319 = Asciz	scala/collection/immutable/StringLike$$anonfun$lines$1;
const #320 = class	#319;	//  scala/collection/immutable/StringLike$$anonfun$lines$1
const #321 = Method	#320.#21;	//  scala/collection/immutable/StringLike$$anonfun$lines$1."<init>":(Lscala/collection/immutable/StringLike;)V
const #322 = Asciz	scala/collection/immutable/StringLike$$anon$1;
const #323 = class	#322;	//  scala/collection/immutable/StringLike$$anon$1
const #324 = Method	#323.#21;	//  scala/collection/immutable/StringLike$$anon$1."<init>":(Lscala/collection/immutable/StringLike;)V
const #325 = Asciz	stripLineEnd;
const #326 = Asciz	apply;
const #327 = Asciz	(I)C;
const #328 = NameAndType	#326:#327;//  apply:(I)C
const #329 = InterfaceMethod	#246.#328;	//  scala/collection/immutable/StringLike.apply:(I)C
const #330 = Asciz	scala$collection$immutable$StringLike$$isLineBreak;
const #331 = Asciz	(Lscala/collection/immutable/StringLike;C)Z;
const #332 = NameAndType	#330:#331;//  scala$collection$immutable$StringLike$$isLineBreak:(Lscala/collection/immutable/StringLike;C)Z
const #333 = Method	#177.#332;	//  scala/collection/immutable/StringLike$class.scala$collection$immutable$StringLike$$isLineBreak:(Lscala/collection/immutable/StringLike;C)Z
const #334 = Asciz	scala/collection/immutable/StringLike$;
const #335 = class	#334;	//  scala/collection/immutable/StringLike$
const #336 = Asciz	Lscala/collection/immutable/StringLike$;;
const #337 = NameAndType	#25:#336;//  MODULE$:Lscala/collection/immutable/StringLike$;
const #338 = Field	#335.#337;	//  scala/collection/immutable/StringLike$.MODULE$:Lscala/collection/immutable/StringLike$;
const #339 = Asciz	scala$collection$immutable$StringLike$$LF;
const #340 = Asciz	()C;
const #341 = NameAndType	#339:#340;//  scala$collection$immutable$StringLike$$LF:()C
const #342 = Method	#335.#341;	//  scala/collection/immutable/StringLike$.scala$collection$immutable$StringLike$$LF:()C
const #343 = Asciz	scala$collection$immutable$StringLike$$CR;
const #344 = NameAndType	#343:#340;//  scala$collection$immutable$StringLike$$CR:()C
const #345 = Method	#335.#344;	//  scala/collection/immutable/StringLike$.scala$collection$immutable$StringLike$$CR:()C
const #346 = Asciz	len;
const #347 = Asciz	I;
const #348 = Asciz	last;
const #349 = Asciz	scala$collection$immutable$StringLike$$FF;
const #350 = NameAndType	#349:#340;//  scala$collection$immutable$StringLike$$FF:()C
const #351 = Method	#335.#350;	//  scala/collection/immutable/StringLike$.scala$collection$immutable$StringLike$$FF:()C
const #352 = Asciz	c;
const #353 = Asciz	compare;
const #354 = Asciz	(Lscala/collection/immutable/StringLike;Ljava/lang/String;)I;
const #355 = Asciz	compareTo;
const #356 = NameAndType	#355:#155;//  compareTo:(Ljava/lang/String;)I
const #357 = Method	#55.#356;	//  java/lang/String.compareTo:(Ljava/lang/String;)I
const #358 = Asciz	other;
const #359 = Asciz	$times;
const #360 = Asciz	(Lscala/collection/immutable/StringLike;I)Ljava/lang/String;;
const #361 = Asciz	intWrapper;
const #362 = Asciz	(I)Lscala/runtime/RichInt;;
const #363 = NameAndType	#361:#362;//  intWrapper:(I)Lscala/runtime/RichInt;
const #364 = Method	#185.#363;	//  scala/Predef$.intWrapper:(I)Lscala/runtime/RichInt;
const #365 = Asciz	scala/runtime/RichInt;
const #366 = class	#365;	//  scala/runtime/RichInt
const #367 = Asciz	until;
const #368 = Asciz	(I)Lscala/collection/immutable/Range;;
const #369 = NameAndType	#367:#368;//  until:(I)Lscala/collection/immutable/Range;
const #370 = Method	#366.#369;	//  scala/runtime/RichInt.until:(I)Lscala/collection/immutable/Range;
const #371 = Asciz	scala/collection/immutable/Range$ByOne;
const #372 = class	#371;	//  scala/collection/immutable/Range$ByOne
const #373 = Asciz	scala/collection/immutable/StringLike$$anonfun$$times$1;
const #374 = class	#373;	//  scala/collection/immutable/StringLike$$anonfun$$times$1
const #375 = Asciz	(Lscala/collection/immutable/StringLike;Lscala/collection/mutable/StringBuilder;)V;
const #376 = NameAndType	#20:#375;//  "<init>":(Lscala/collection/immutable/StringLike;Lscala/collection/mutable/StringBuilder;)V
const #377 = Method	#374.#376;	//  scala/collection/immutable/StringLike$$anonfun$$times$1."<init>":(Lscala/collection/immutable/StringLike;Lscala/collection/mutable/StringBuilder;)V
const #378 = InterfaceMethod	#372.#264;	//  scala/collection/immutable/Range$ByOne.foreach:(Lscala/Function1;)V
const #379 = Asciz	n;
const #380 = Asciz	buf$1;
const #381 = Asciz	mkString;
const #382 = Asciz	(Lscala/collection/immutable/StringLike;I)C;
const #383 = Asciz	charAt;
const #384 = NameAndType	#383:#327;//  charAt:(I)C
const #385 = Method	#55.#384;	//  java/lang/String.charAt:(I)C
const #386 = Asciz	Scala;
const #387 = Asciz	InnerClasses;
const #388 = Asciz	scala/collection/immutable/Range;
const #389 = class	#388;	//  scala/collection/immutable/Range
const #390 = Asciz	ByOne;
const #391 = Asciz	$anon$1;
const #392 = Asciz	$anonfun$1;
const #393 = Asciz	$anonfun$lines$1;
const #394 = Asciz	$anonfun$$times$1;
const #395 = Asciz	$anonfun$format$1;
const #396 = Asciz	$anonfun$format$2;
const #397 = Asciz	$anonfun$stripMargin$1;
const #398 = Asciz	$anonfun$linesIterator$1;

{
public static void $init$(scala.collection.immutable.StringLike);
  Code:
   Stack=0, Locals=1, Args_size=1
   0:	return
  LineNumberTable: 
   line 37: 0

  LocalVariableTable: 
   Start  Length  Slot  Name   Signature
   0      1      0    $this       Lscala/collection/immutable/StringLike;


public static java.lang.String format(scala.collection.immutable.StringLike, java.util.Locale, scala.collection.Seq);
  Code:
   Stack=6, Locals=3, Args_size=3
   0:	aload_1
   1:	aload_0
   2:	invokeinterface	#17,  1; //InterfaceMethod scala/collection/SeqLike.toString:()Ljava/lang/String;
   7:	aload_2
   8:	new	#19; //class scala/collection/immutable/StringLike$$anonfun$format$2
   11:	dup
   12:	aload_0
   13:	invokespecial	#22; //Method scala/collection/immutable/StringLike$$anonfun$format$2."<init>":(Lscala/collection/immutable/StringLike;)V
   16:	getstatic	#28; //Field scala/collection/Seq$.MODULE$:Lscala/collection/Seq$;
   19:	invokevirtual	#32; //Method scala/collection/Seq$.canBuildFrom:()Lscala/collection/generic/CanBuildFrom;
   22:	invokeinterface	#38,  3; //InterfaceMethod scala/collection/TraversableLike.map:(Lscala/Function1;Lscala/collection/generic/CanBuildFrom;)Ljava/lang/Object;
   27:	checkcast	#34; //class scala/collection/TraversableLike
   30:	getstatic	#43; //Field scala/reflect/Manifest$.MODULE$:Lscala/reflect/Manifest$;
   33:	invokevirtual	#47; //Method scala/reflect/Manifest$.Object:()Lscala/reflect/Manifest;
   36:	invokeinterface	#51,  2; //InterfaceMethod scala/collection/TraversableLike.toArray:(Lscala/reflect/ClassManifest;)Ljava/lang/Object;
   41:	checkcast	#53; //class "[Ljava/lang/Object;"
   44:	invokestatic	#58; //Method java/lang/String.format:(Ljava/util/Locale;Ljava/lang/String;[Ljava/lang/Object;)Ljava/lang/String;
   47:	areturn
  LineNumberTable: 
   line 267: 0

  LocalVariableTable: 
   Start  Length  Slot  Name   Signature
   0      48      0    $this       Lscala/collection/immutable/StringLike;
   0      48      1    l       Ljava/util/Locale;
   0      48      2    args       Lscala/collection/Seq;


public static java.lang.String format(scala.collection.immutable.StringLike, scala.collection.Seq);
  Code:
   Stack=5, Locals=2, Args_size=2
   0:	aload_0
   1:	invokeinterface	#17,  1; //InterfaceMethod scala/collection/SeqLike.toString:()Ljava/lang/String;
   6:	aload_1
   7:	new	#65; //class scala/collection/immutable/StringLike$$anonfun$format$1
   10:	dup
   11:	aload_0
   12:	invokespecial	#66; //Method scala/collection/immutable/StringLike$$anonfun$format$1."<init>":(Lscala/collection/immutable/StringLike;)V
   15:	getstatic	#28; //Field scala/collection/Seq$.MODULE$:Lscala/collection/Seq$;
   18:	invokevirtual	#32; //Method scala/collection/Seq$.canBuildFrom:()Lscala/collection/generic/CanBuildFrom;
   21:	invokeinterface	#38,  3; //InterfaceMethod scala/collection/TraversableLike.map:(Lscala/Function1;Lscala/collection/generic/CanBuildFrom;)Ljava/lang/Object;
   26:	checkcast	#34; //class scala/collection/TraversableLike
   29:	getstatic	#43; //Field scala/reflect/Manifest$.MODULE$:Lscala/reflect/Manifest$;
   32:	invokevirtual	#47; //Method scala/reflect/Manifest$.Object:()Lscala/reflect/Manifest;
   35:	invokeinterface	#51,  2; //InterfaceMethod scala/collection/TraversableLike.toArray:(Lscala/reflect/ClassManifest;)Ljava/lang/Object;
   40:	checkcast	#53; //class "[Ljava/lang/Object;"
   43:	invokestatic	#69; //Method java/lang/String.format:(Ljava/lang/String;[Ljava/lang/Object;)Ljava/lang/String;
   46:	areturn
  LineNumberTable: 
   line 247: 0

  LocalVariableTable: 
   Start  Length  Slot  Name   Signature
   0      47      0    $this       Lscala/collection/immutable/StringLike;
   0      47      1    args       Lscala/collection/Seq;


public static final java.lang.Object scala$collection$immutable$StringLike$$unwrapArg(scala.collection.immutable.StringLike, java.lang.Object);
  Code:
   Stack=3, Locals=3, Args_size=2
   0:	aload_1
   1:	instanceof	#73; //class scala/math/ScalaNumber
   4:	ifeq	35
   7:	aload_1
   8:	checkcast	#73; //class scala/math/ScalaNumber
   11:	astore_2
   12:	iconst_1
   13:	ifeq	23
   16:	aload_2
   17:	invokevirtual	#77; //Method scala/math/ScalaNumber.underlying:()Ljava/lang/Object;
   20:	goto	40
   23:	new	#79; //class scala/MatchError
   26:	dup
   27:	aload_1
   28:	invokevirtual	#82; //Method java/lang/Object.toString:()Ljava/lang/String;
   31:	invokespecial	#85; //Method scala/MatchError."<init>":(Ljava/lang/String;)V
   34:	athrow
   35:	iconst_1
   36:	ifeq	41
   39:	aload_1
   40:	areturn
   41:	new	#79; //class scala/MatchError
   44:	dup
   45:	aload_1
   46:	invokevirtual	#82; //Method java/lang/Object.toString:()Ljava/lang/String;
   49:	invokespecial	#85; //Method scala/MatchError."<init>":(Ljava/lang/String;)V
   52:	athrow
  LineNumberTable: 
   line 224: 0
   line 21: 12
   line 225: 16
   line 224: 23
   line 21: 35
   line 226: 39
   line 224: 40

  LocalVariableTable: 
   Start  Length  Slot  Name   Signature
   0      53      0    $this       Lscala/collection/immutable/StringLike;
   0      53      1    arg       Ljava/lang/Object;
   12      23      2    temp5       Lscala/math/ScalaNumber;


public static double toDouble(scala.collection.immutable.StringLike);
  Code:
   Stack=2, Locals=1, Args_size=1
   0:	aload_0
   1:	invokeinterface	#17,  1; //InterfaceMethod scala/collection/SeqLike.toString:()Ljava/lang/String;
   6:	invokestatic	#133; //Method java/lang/Double.parseDouble:(Ljava/lang/String;)D
   9:	dreturn
  LineNumberTable: 
   line 205: 0

  LocalVariableTable: 
   Start  Length  Slot  Name   Signature
   0      10      0    $this       Lscala/collection/immutable/StringLike;


public static float toFloat(scala.collection.immutable.StringLike);
  Code:
   Stack=1, Locals=1, Args_size=1
   0:	aload_0
   1:	invokeinterface	#17,  1; //InterfaceMethod scala/collection/SeqLike.toString:()Ljava/lang/String;
   6:	invokestatic	#141; //Method java/lang/Float.parseFloat:(Ljava/lang/String;)F
   9:	freturn
  LineNumberTable: 
   line 204: 0

  LocalVariableTable: 
   Start  Length  Slot  Name   Signature
   0      10      0    $this       Lscala/collection/immutable/StringLike;


public static long toLong(scala.collection.immutable.StringLike);
  Code:
   Stack=2, Locals=1, Args_size=1
   0:	aload_0
   1:	invokeinterface	#17,  1; //InterfaceMethod scala/collection/SeqLike.toString:()Ljava/lang/String;
   6:	invokestatic	#149; //Method java/lang/Long.parseLong:(Ljava/lang/String;)J
   9:	lreturn
  LineNumberTable: 
   line 203: 0

  LocalVariableTable: 
   Start  Length  Slot  Name   Signature
   0      10      0    $this       Lscala/collection/immutable/StringLike;


public static int toInt(scala.collection.immutable.StringLike);
  Code:
   Stack=1, Locals=1, Args_size=1
   0:	aload_0
   1:	invokeinterface	#17,  1; //InterfaceMethod scala/collection/SeqLike.toString:()Ljava/lang/String;
   6:	invokestatic	#157; //Method java/lang/Integer.parseInt:(Ljava/lang/String;)I
   9:	ireturn
  LineNumberTable: 
   line 202: 0

  LocalVariableTable: 
   Start  Length  Slot  Name   Signature
   0      10      0    $this       Lscala/collection/immutable/StringLike;


public static short toShort(scala.collection.immutable.StringLike);
  Code:
   Stack=1, Locals=1, Args_size=1
   0:	aload_0
   1:	invokeinterface	#17,  1; //InterfaceMethod scala/collection/SeqLike.toString:()Ljava/lang/String;
   6:	invokestatic	#165; //Method java/lang/Short.parseShort:(Ljava/lang/String;)S
   9:	ireturn
  LineNumberTable: 
   line 201: 0

  LocalVariableTable: 
   Start  Length  Slot  Name   Signature
   0      10      0    $this       Lscala/collection/immutable/StringLike;


public static byte toByte(scala.collection.immutable.StringLike);
  Code:
   Stack=1, Locals=1, Args_size=1
   0:	aload_0
   1:	invokeinterface	#17,  1; //InterfaceMethod scala/collection/SeqLike.toString:()Ljava/lang/String;
   6:	invokestatic	#173; //Method java/lang/Byte.parseByte:(Ljava/lang/String;)B
   9:	ireturn
  LineNumberTable: 
   line 200: 0

  LocalVariableTable: 
   Start  Length  Slot  Name   Signature
   0      10      0    $this       Lscala/collection/immutable/StringLike;


public static boolean toBoolean(scala.collection.immutable.StringLike);
  Code:
   Stack=2, Locals=1, Args_size=1
   0:	aload_0
   1:	aload_0
   2:	invokeinterface	#17,  1; //InterfaceMethod scala/collection/SeqLike.toString:()Ljava/lang/String;
   7:	invokestatic	#179; //Method parseBoolean:(Lscala/collection/immutable/StringLike;Ljava/lang/String;)Z
   10:	ireturn
  LineNumberTable: 
   line 199: 0

  LocalVariableTable: 
   Start  Length  Slot  Name   Signature
   0      11      0    $this       Lscala/collection/immutable/StringLike;


public static scala.util.matching.Regex r(scala.collection.immutable.StringLike);
  Code:
   Stack=5, Locals=1, Args_size=1
   0:	new	#183; //class scala/util/matching/Regex
   3:	dup
   4:	aload_0
   5:	invokeinterface	#17,  1; //InterfaceMethod scala/collection/SeqLike.toString:()Ljava/lang/String;
   10:	getstatic	#188; //Field scala/Predef$.MODULE$:Lscala/Predef$;
   13:	iconst_0
   14:	anewarray	#55; //class java/lang/String
   17:	checkcast	#53; //class "[Ljava/lang/Object;"
   20:	invokevirtual	#192; //Method scala/Predef$.wrapRefArray:([Ljava/lang/Object;)Lscala/collection/mutable/WrappedArray;
   23:	invokespecial	#195; //Method scala/util/matching/Regex."<init>":(Ljava/lang/String;Lscala/collection/Seq;)V
   26:	areturn
  LineNumberTable: 
   line 197: 0

  LocalVariableTable: 
   Start  Length  Slot  Name   Signature
   0      27      0    $this       Lscala/collection/immutable/StringLike;


public static java.lang.String[] split(scala.collection.immutable.StringLike, char[])   throws java.util.regex.PatternSyntaxException;
  Code:
   Stack=6, Locals=3, Args_size=2
   0:	new	#110; //class scala/collection/mutable/StringBuilder
   3:	dup
   4:	invokespecial	#113; //Method scala/collection/mutable/StringBuilder."<init>":()V
   7:	getstatic	#188; //Field scala/Predef$.MODULE$:Lscala/Predef$;
   10:	aload_1
   11:	invokevirtual	#201; //Method scala/Predef$.charArrayOps:([C)Lscala/collection/mutable/ArrayOps;
   14:	ldc	#203; //String [
   16:	new	#205; //class scala/collection/immutable/StringLike$$anonfun$1
   19:	dup
   20:	aload_0
   21:	invokespecial	#206; //Method scala/collection/immutable/StringLike$$anonfun$1."<init>":(Lscala/collection/immutable/StringLike;)V
   24:	invokeinterface	#212,  3; //InterfaceMethod scala/collection/IndexedSeqLike.foldLeft:(Ljava/lang/Object;Lscala/Function2;)Ljava/lang/Object;
   29:	checkcast	#55; //class java/lang/String
   32:	invokevirtual	#119; //Method scala/collection/mutable/StringBuilder.append:(Ljava/lang/Object;)Lscala/collection/mutable/StringBuilder;
   35:	ldc	#214; //String ]
   37:	invokevirtual	#119; //Method scala/collection/mutable/StringBuilder.append:(Ljava/lang/Object;)Lscala/collection/mutable/StringBuilder;
   40:	invokevirtual	#122; //Method scala/collection/mutable/StringBuilder.toString:()Ljava/lang/String;
   43:	astore_2
   44:	aload_0
   45:	invokeinterface	#17,  1; //InterfaceMethod scala/collection/SeqLike.toString:()Ljava/lang/String;
   50:	aload_2
   51:	invokevirtual	#217; //Method java/lang/String.split:(Ljava/lang/String;)[Ljava/lang/String;
   54:	areturn
  LineNumberTable: 
   line 188: 0
   line 189: 44

  LocalVariableTable: 
   Start  Length  Slot  Name   Signature
   0      55      0    $this       Lscala/collection/immutable/StringLike;
   0      55      1    separators       [C
   44      10      2    re       Ljava/lang/String;

  Exceptions: 
   throws java.util.regex.PatternSyntaxException
public static java.lang.String[] split(scala.collection.immutable.StringLike, char)   throws java.util.regex.PatternSyntaxException;
  Code:
   Stack=3, Locals=2, Args_size=2
   0:	aload_0
   1:	invokeinterface	#17,  1; //InterfaceMethod scala/collection/SeqLike.toString:()Ljava/lang/String;
   6:	aload_0
   7:	iload_1
   8:	invokestatic	#228; //Method scala$collection$immutable$StringLike$$escape:(Lscala/collection/immutable/StringLike;C)Ljava/lang/String;
   11:	invokevirtual	#217; //Method java/lang/String.split:(Ljava/lang/String;)[Ljava/lang/String;
   14:	areturn
  LineNumberTable: 
   line 184: 0

  LocalVariableTable: 
   Start  Length  Slot  Name   Signature
   0      15      0    $this       Lscala/collection/immutable/StringLike;
   0      15      1    separator       C

  Exceptions: 
   throws java.util.regex.PatternSyntaxException
public static final java.lang.String scala$collection$immutable$StringLike$$escape(scala.collection.immutable.StringLike, char);
  Code:
   Stack=2, Locals=2, Args_size=2
   0:	new	#110; //class scala/collection/mutable/StringBuilder
   3:	dup
   4:	invokespecial	#113; //Method scala/collection/mutable/StringBuilder."<init>":()V
   7:	ldc	#232; //String \Q
   9:	invokevirtual	#119; //Method scala/collection/mutable/StringBuilder.append:(Ljava/lang/Object;)Lscala/collection/mutable/StringBuilder;
   12:	iload_1
   13:	invokestatic	#238; //Method scala/runtime/BoxesRunTime.boxToCharacter:(C)Ljava/lang/Character;
   16:	invokevirtual	#119; //Method scala/collection/mutable/StringBuilder.append:(Ljava/lang/Object;)Lscala/collection/mutable/StringBuilder;
   19:	ldc	#240; //String \E
   21:	invokevirtual	#119; //Method scala/collection/mutable/StringBuilder.append:(Ljava/lang/Object;)Lscala/collection/mutable/StringBuilder;
   24:	invokevirtual	#122; //Method scala/collection/mutable/StringBuilder.toString:()Ljava/lang/String;
   27:	areturn
  LineNumberTable: 
   line 181: 0

  LocalVariableTable: 
   Start  Length  Slot  Name   Signature
   0      28      0    $this       Lscala/collection/immutable/StringLike;
   0      28      1    ch       C


public static java.lang.String stripMargin(scala.collection.immutable.StringLike);
  Code:
   Stack=2, Locals=1, Args_size=1
   0:	aload_0
   1:	ldc	#244; //int 124
   3:	invokeinterface	#249,  2; //InterfaceMethod scala/collection/immutable/StringLike.stripMargin:(C)Ljava/lang/String;
   8:	areturn
  LineNumberTable: 
   line 179: 0

  LocalVariableTable: 
   Start  Length  Slot  Name   Signature
   0      9      0    $this       Lscala/collection/immutable/StringLike;


public static java.lang.String stripMargin(scala.collection.immutable.StringLike, char);
  Code:
   Stack=6, Locals=3, Args_size=2
   0:	new	#110; //class scala/collection/mutable/StringBuilder
   3:	dup
   4:	invokespecial	#250; //Method scala/collection/mutable/StringBuilder."<init>":()V
   7:	astore_2
   8:	aload_0
   9:	invokeinterface	#254,  1; //InterfaceMethod scala/collection/immutable/StringLike.linesWithSeparators:()Lscala/collection/Iterator;
   14:	new	#256; //class scala/collection/immutable/StringLike$$anonfun$stripMargin$1
   17:	dup
   18:	aload_0
   19:	iload_1
   20:	aload_2
   21:	invokespecial	#259; //Method scala/collection/immutable/StringLike$$anonfun$stripMargin$1."<init>":(Lscala/collection/immutable/StringLike;CLscala/collection/mutable/StringBuilder;)V
   24:	invokeinterface	#265,  2; //InterfaceMethod scala/collection/Iterator.foreach:(Lscala/Function1;)V
   29:	aload_2
   30:	invokevirtual	#266; //Method scala/collection/mutable/StringBuilder.toString:()Ljava/lang/String;
   33:	areturn
  LineNumberTable: 
   line 160: 0
   line 161: 8
   line 168: 20
   line 161: 21
   line 168: 29

  LocalVariableTable: 
   Start  Length  Slot  Name   Signature
   0      34      0    $this       Lscala/collection/immutable/StringLike;
   0      34      1    marginChar$1       C
   8      25      2    buf$2       Lscala/collection/mutable/StringBuilder;


public static java.lang.String stripSuffix(scala.collection.immutable.StringLike, java.lang.String);
  Code:
   Stack=4, Locals=2, Args_size=2
   0:	aload_0
   1:	invokeinterface	#17,  1; //InterfaceMethod scala/collection/SeqLike.toString:()Ljava/lang/String;
   6:	aload_1
   7:	invokevirtual	#275; //Method java/lang/String.endsWith:(Ljava/lang/String;)Z
   10:	ifeq	40
   13:	aload_0
   14:	invokeinterface	#17,  1; //InterfaceMethod scala/collection/SeqLike.toString:()Ljava/lang/String;
   19:	iconst_0
   20:	aload_0
   21:	invokeinterface	#17,  1; //InterfaceMethod scala/collection/SeqLike.toString:()Ljava/lang/String;
   26:	invokevirtual	#279; //Method java/lang/String.length:()I
   29:	aload_1
   30:	invokevirtual	#279; //Method java/lang/String.length:()I
   33:	isub
   34:	invokevirtual	#283; //Method java/lang/String.substring:(II)Ljava/lang/String;
   37:	goto	46
   40:	aload_0
   41:	invokeinterface	#17,  1; //InterfaceMethod scala/collection/SeqLike.toString:()Ljava/lang/String;
   46:	areturn
  LineNumberTable: 
   line 148: 0
   line 149: 40
   line 148: 46

  LocalVariableTable: 
   Start  Length  Slot  Name   Signature
   0      47      0    $this       Lscala/collection/immutable/StringLike;
   0      47      1    suffix       Ljava/lang/String;


public static java.lang.String stripPrefix(scala.collection.immutable.StringLike, java.lang.String);
  Code:
   Stack=2, Locals=2, Args_size=2
   0:	aload_0
   1:	invokeinterface	#17,  1; //InterfaceMethod scala/collection/SeqLike.toString:()Ljava/lang/String;
   6:	aload_1
   7:	invokevirtual	#288; //Method java/lang/String.startsWith:(Ljava/lang/String;)Z
   10:	ifeq	29
   13:	aload_0
   14:	invokeinterface	#17,  1; //InterfaceMethod scala/collection/SeqLike.toString:()Ljava/lang/String;
   19:	aload_1
   20:	invokevirtual	#279; //Method java/lang/String.length:()I
   23:	invokevirtual	#291; //Method java/lang/String.substring:(I)Ljava/lang/String;
   26:	goto	35
   29:	aload_0
   30:	invokeinterface	#17,  1; //InterfaceMethod scala/collection/SeqLike.toString:()Ljava/lang/String;
   35:	areturn
  LineNumberTable: 
   line 143: 0
   line 144: 29
   line 143: 35

  LocalVariableTable: 
   Start  Length  Slot  Name   Signature
   0      36      0    $this       Lscala/collection/immutable/StringLike;
   0      36      1    prefix       Ljava/lang/String;


public static java.lang.String capitalize(scala.collection.immutable.StringLike);
  Code:
   Stack=4, Locals=4, Args_size=1
   0:	aload_0
   1:	invokeinterface	#17,  1; //InterfaceMethod scala/collection/SeqLike.toString:()Ljava/lang/String;
   6:	dup
   7:	astore_1
   8:	ifnull	19
   11:	aload_1
   12:	aconst_null
   13:	invokevirtual	#95; //Method java/lang/Object.equals:(Ljava/lang/Object;)Z
   16:	ifeq	23
   19:	aconst_null
   20:	goto	71
   23:	aload_0
   24:	invokeinterface	#17,  1; //InterfaceMethod scala/collection/SeqLike.toString:()Ljava/lang/String;
   29:	invokevirtual	#279; //Method java/lang/String.length:()I
   32:	iconst_0
   33:	if_icmpne	42
   36:	ldc_w	#295; //String 
   39:	goto	71
   42:	aload_0
   43:	invokeinterface	#17,  1; //InterfaceMethod scala/collection/SeqLike.toString:()Ljava/lang/String;
   48:	invokevirtual	#299; //Method java/lang/String.toCharArray:()[C
   51:	astore_3
   52:	aload_3
   53:	iconst_0
   54:	aload_3
   55:	iconst_0
   56:	caload
   57:	istore_2
   58:	iload_2
   59:	invokestatic	#305; //Method java/lang/Character.toUpperCase:(C)C
   62:	castore
   63:	new	#55; //class java/lang/String
   66:	dup
   67:	aload_3
   68:	invokespecial	#308; //Method java/lang/String."<init>":([C)V
   71:	areturn
  LineNumberTable: 
   line 133: 0
   line 134: 23
   line 136: 42
   line 137: 52
   line 138: 63
   line 133: 71

  LocalVariableTable: 
   Start  Length  Slot  Name   Signature
   0      72      0    $this       Lscala/collection/immutable/StringLike;
   52      19      3    chars       [C


public static scala.collection.Iterator linesIterator(scala.collection.immutable.StringLike);
  Code:
   Stack=4, Locals=1, Args_size=1
   0:	aload_0
   1:	invokeinterface	#254,  1; //InterfaceMethod scala/collection/immutable/StringLike.linesWithSeparators:()Lscala/collection/Iterator;
   6:	new	#313; //class scala/collection/immutable/StringLike$$anonfun$linesIterator$1
   9:	dup
   10:	aload_0
   11:	invokespecial	#314; //Method scala/collection/immutable/StringLike$$anonfun$linesIterator$1."<init>":(Lscala/collection/immutable/StringLike;)V
   14:	invokeinterface	#317,  2; //InterfaceMethod scala/collection/Iterator.map:(Lscala/Function1;)Lscala/collection/Iterator;
   19:	areturn
  LineNumberTable: 
   line 129: 0

  LocalVariableTable: 
   Start  Length  Slot  Name   Signature
   0      20      0    $this       Lscala/collection/immutable/StringLike;


public static scala.collection.Iterator lines(scala.collection.immutable.StringLike);
  Code:
   Stack=4, Locals=1, Args_size=1
   0:	aload_0
   1:	invokeinterface	#254,  1; //InterfaceMethod scala/collection/immutable/StringLike.linesWithSeparators:()Lscala/collection/Iterator;
   6:	new	#320; //class scala/collection/immutable/StringLike$$anonfun$lines$1
   9:	dup
   10:	aload_0
   11:	invokespecial	#321; //Method scala/collection/immutable/StringLike$$anonfun$lines$1."<init>":(Lscala/collection/immutable/StringLike;)V
   14:	invokeinterface	#317,  2; //InterfaceMethod scala/collection/Iterator.map:(Lscala/Function1;)Lscala/collection/Iterator;
   19:	areturn
  LineNumberTable: 
   line 122: 0

  LocalVariableTable: 
   Start  Length  Slot  Name   Signature
   0      20      0    $this       Lscala/collection/immutable/StringLike;


public static scala.collection.Iterator linesWithSeparators(scala.collection.immutable.StringLike);
  Code:
   Stack=3, Locals=1, Args_size=1
   0:	new	#323; //class scala/collection/immutable/StringLike$$anon$1
   3:	dup
   4:	aload_0
   5:	invokespecial	#324; //Method scala/collection/immutable/StringLike$$anon$1."<init>":(Lscala/collection/immutable/StringLike;)V
   8:	areturn
  LineNumberTable: 
   line 103: 0

  LocalVariableTable: 
   Start  Length  Slot  Name   Signature
   0      9      0    $this       Lscala/collection/immutable/StringLike;


public static java.lang.String stripLineEnd(scala.collection.immutable.StringLike);
  Code:
   Stack=5, Locals=3, Args_size=1
   0:	aload_0
   1:	invokeinterface	#17,  1; //InterfaceMethod scala/collection/SeqLike.toString:()Ljava/lang/String;
   6:	invokevirtual	#279; //Method java/lang/String.length:()I
   9:	istore_1
   10:	iload_1
   11:	iconst_0
   12:	if_icmpne	24
   15:	aload_0
   16:	invokeinterface	#17,  1; //InterfaceMethod scala/collection/SeqLike.toString:()Ljava/lang/String;
   21:	goto	103
   24:	aload_0
   25:	iload_1
   26:	iconst_1
   27:	isub
   28:	invokeinterface	#329,  2; //InterfaceMethod scala/collection/immutable/StringLike.apply:(I)C
   33:	istore_2
   34:	aload_0
   35:	iload_2
   36:	invokestatic	#333; //Method scala$collection$immutable$StringLike$$isLineBreak:(Lscala/collection/immutable/StringLike;C)Z
   39:	ifeq	97
   42:	aload_0
   43:	invokeinterface	#17,  1; //InterfaceMethod scala/collection/SeqLike.toString:()Ljava/lang/String;
   48:	iconst_0
   49:	iload_2
   50:	getstatic	#338; //Field scala/collection/immutable/StringLike$.MODULE$:Lscala/collection/immutable/StringLike$;
   53:	invokevirtual	#342; //Method scala/collection/immutable/StringLike$.scala$collection$immutable$StringLike$$LF:()C
   56:	if_icmpne	88
   59:	iload_1
   60:	iconst_2
   61:	if_icmplt	88
   64:	aload_0
   65:	iload_1
   66:	iconst_2
   67:	isub
   68:	invokeinterface	#329,  2; //InterfaceMethod scala/collection/immutable/StringLike.apply:(I)C
   73:	getstatic	#338; //Field scala/collection/immutable/StringLike$.MODULE$:Lscala/collection/immutable/StringLike$;
   76:	invokevirtual	#345; //Method scala/collection/immutable/StringLike$.scala$collection$immutable$StringLike$$CR:()C
   79:	if_icmpne	88
   82:	iload_1
   83:	iconst_2
   84:	isub
   85:	goto	91
   88:	iload_1
   89:	iconst_1
   90:	isub
   91:	invokevirtual	#283; //Method java/lang/String.substring:(II)Ljava/lang/String;
   94:	goto	103
   97:	aload_0
   98:	invokeinterface	#17,  1; //InterfaceMethod scala/collection/SeqLike.toString:()Ljava/lang/String;
   103:	areturn
  LineNumberTable: 
   line 78: 0
   line 79: 10
   line 81: 24
   line 82: 34
   line 83: 42
   line 85: 97
   line 77: 103

  LocalVariableTable: 
   Start  Length  Slot  Name   Signature
   0      104      0    $this       Lscala/collection/immutable/StringLike;
   10      94      1    len       I
   34      69      2    last       C


public static final boolean scala$collection$immutable$StringLike$$isLineBreak(scala.collection.immutable.StringLike, char);
  Code:
   Stack=2, Locals=2, Args_size=2
   0:	iload_1
   1:	getstatic	#338; //Field scala/collection/immutable/StringLike$.MODULE$:Lscala/collection/immutable/StringLike$;
   4:	invokevirtual	#342; //Method scala/collection/immutable/StringLike$.scala$collection$immutable$StringLike$$LF:()C
   7:	if_icmpeq	20
   10:	iload_1
   11:	getstatic	#338; //Field scala/collection/immutable/StringLike$.MODULE$:Lscala/collection/immutable/StringLike$;
   14:	invokevirtual	#351; //Method scala/collection/immutable/StringLike$.scala$collection$immutable$StringLike$$FF:()C
   17:	if_icmpne	24
   20:	iconst_1
   21:	goto	25
   24:	iconst_0
   25:	ireturn
  LineNumberTable: 
   line 62: 0

  LocalVariableTable: 
   Start  Length  Slot  Name   Signature
   0      26      0    $this       Lscala/collection/immutable/StringLike;
   0      26      1    c       C


public static int compare(scala.collection.immutable.StringLike, java.lang.String);
  Code:
   Stack=2, Locals=2, Args_size=2
   0:	aload_0
   1:	invokeinterface	#17,  1; //InterfaceMethod scala/collection/SeqLike.toString:()Ljava/lang/String;
   6:	aload_1
   7:	invokevirtual	#357; //Method java/lang/String.compareTo:(Ljava/lang/String;)I
   10:	ireturn
  LineNumberTable: 
   line 60: 0

  LocalVariableTable: 
   Start  Length  Slot  Name   Signature
   0      11      0    $this       Lscala/collection/immutable/StringLike;
   0      11      1    other       Ljava/lang/String;


public static java.lang.String $times(scala.collection.immutable.StringLike, int);
  Code:
   Stack=5, Locals=3, Args_size=2
   0:	new	#110; //class scala/collection/mutable/StringBuilder
   3:	dup
   4:	invokespecial	#250; //Method scala/collection/mutable/StringBuilder."<init>":()V
   7:	astore_2
   8:	getstatic	#188; //Field scala/Predef$.MODULE$:Lscala/Predef$;
   11:	iconst_0
   12:	invokevirtual	#364; //Method scala/Predef$.intWrapper:(I)Lscala/runtime/RichInt;
   15:	iload_1
   16:	invokevirtual	#370; //Method scala/runtime/RichInt.until:(I)Lscala/collection/immutable/Range;
   19:	checkcast	#372; //class scala/collection/immutable/Range$ByOne
   22:	new	#374; //class scala/collection/immutable/StringLike$$anonfun$$times$1
   25:	dup
   26:	aload_0
   27:	aload_2
   28:	invokespecial	#377; //Method scala/collection/immutable/StringLike$$anonfun$$times$1."<init>":(Lscala/collection/immutable/StringLike;Lscala/collection/mutable/StringBuilder;)V
   31:	invokeinterface	#378,  2; //InterfaceMethod scala/collection/immutable/Range$ByOne.foreach:(Lscala/Function1;)V
   36:	aload_2
   37:	invokevirtual	#266; //Method scala/collection/mutable/StringBuilder.toString:()Ljava/lang/String;
   40:	areturn
  LineNumberTable: 
   line 55: 0
   line 56: 8
   line 57: 27
   line 56: 28
   line 57: 36

  LocalVariableTable: 
   Start  Length  Slot  Name   Signature
   0      41      0    $this       Lscala/collection/immutable/StringLike;
   0      41      1    n       I
   8      32      2    buf$1       Lscala/collection/mutable/StringBuilder;


public static java.lang.String mkString(scala.collection.immutable.StringLike);
  Code:
   Stack=1, Locals=1, Args_size=1
   0:	aload_0
   1:	invokeinterface	#17,  1; //InterfaceMethod scala/collection/SeqLike.toString:()Ljava/lang/String;
   6:	areturn
  LineNumberTable: 
   line 50: 0

  LocalVariableTable: 
   Start  Length  Slot  Name   Signature
   0      7      0    $this       Lscala/collection/immutable/StringLike;


public static int length(scala.collection.immutable.StringLike);
  Code:
   Stack=1, Locals=1, Args_size=1
   0:	aload_0
   1:	invokeinterface	#17,  1; //InterfaceMethod scala/collection/SeqLike.toString:()Ljava/lang/String;
   6:	invokevirtual	#279; //Method java/lang/String.length:()I
   9:	ireturn
  LineNumberTable: 
   line 48: 0

  LocalVariableTable: 
   Start  Length  Slot  Name   Signature
   0      10      0    $this       Lscala/collection/immutable/StringLike;


public static char apply(scala.collection.immutable.StringLike, int);
  Code:
   Stack=2, Locals=2, Args_size=2
   0:	aload_0
   1:	invokeinterface	#17,  1; //InterfaceMethod scala/collection/SeqLike.toString:()Ljava/lang/String;
   6:	iload_1
   7:	invokevirtual	#385; //Method java/lang/String.charAt:(I)C
   10:	ireturn
  LineNumberTable: 
   line 46: 0

  LocalVariableTable: 
   Start  Length  Slot  Name   Signature
   0      11      0    $this       Lscala/collection/immutable/StringLike;
   0      11      1    n       I


}

