Compiled from "StringLike.scala"
public final class scala.collection.immutable.StringLike$ extends java.lang.Object implements scala.ScalaObject
  SourceFile: "StringLike.scala"
  Scala: length = 0x
   
  InnerClass: 
   public final $anon$1=class scala/collection/immutable/StringLike$$anon$1 of class scala/collection/immutable/StringLike
   public final $anonfun$1=class scala/collection/immutable/StringLike$$anonfun$1 of class scala/collection/immutable/StringLike
   public final $anonfun$lines$1=class scala/collection/immutable/StringLike$$anonfun$lines$1 of class scala/collection/immutable/StringLike
   public final $anonfun$format$2=class scala/collection/immutable/StringLike$$anonfun$format$2 of class scala/collection/immutable/StringLike
   public final $anonfun$format$1=class scala/collection/immutable/StringLike$$anonfun$format$1 of class scala/collection/immutable/StringLike
   public final $anonfun$$times$1=class scala/collection/immutable/StringLike$$anonfun$$times$1 of class scala/collection/immutable/StringLike
   public final $anonfun$stripMargin$1=class scala/collection/immutable/StringLike$$anonfun$stripMargin$1 of class scala/collection/immutable/StringLike
   public final $anonfun$linesIterator$1=class scala/collection/immutable/StringLike$$anonfun$linesIterator$1 of class scala/collection/immutable/StringLike
  minor version: 0
  major version: 49
  Constant pool:
Asciz	SourceFile;
Asciz	StringLike.scala;
Asciz	Scala;
Asciz	MODULE$;
Asciz	Lscala/collection/immutable/StringLike$;;
Asciz	<clinit>;
Asciz	()V;
Asciz	Code;
Asciz	scala/collection/immutable/StringLike$;
class	scala/collection/immutable/StringLike$
Asciz	<init>;
NameAndType	"<init>":()V
Method	scala/collection/immutable/StringLike$."<init>":()V
Asciz	SU;
Asciz	C;
Asciz	scala$collection$immutable$StringLike$$CR;
Asciz	scala$collection$immutable$StringLike$$FF;
Asciz	scala$collection$immutable$StringLike$$LF;
Asciz	LineNumberTable;
Asciz	java/lang/Object;
class	java/lang/Object
Method	java/lang/Object."<init>":()V
NameAndType	MODULE$:Lscala/collection/immutable/StringLike$;
Field	scala/collection/immutable/StringLike$.MODULE$:Lscala/collection/immutable/StringLike$;
int	10;
NameAndType	scala$collection$immutable$StringLike$$LF:C
Field	scala/collection/immutable/StringLike$.scala$collection$immutable$StringLike$$LF:C
int	12;
NameAndType	scala$collection$immutable$StringLike$$FF:C
Field	scala/collection/immutable/StringLike$.scala$collection$immutable$StringLike$$FF:C
int	13;
NameAndType	scala$collection$immutable$StringLike$$CR:C
Field	scala/collection/immutable/StringLike$.scala$collection$immutable$StringLike$$CR:C
int	26;
NameAndType	SU:C
Field	scala/collection/immutable/StringLike$.SU:C
Asciz	()C;
Asciz	InnerClasses;
Asciz	scala/collection/immutable/StringLike$$anon$1;
class	scala/collection/immutable/StringLike$$anon$1
Asciz	scala/collection/immutable/StringLike;
class	scala/collection/immutable/StringLike
Asciz	$anon$1;
Asciz	scala/collection/immutable/StringLike$$anonfun$1;
class	scala/collection/immutable/StringLike$$anonfun$1
Asciz	$anonfun$1;
Asciz	scala/collection/immutable/StringLike$$anonfun$lines$1;
class	scala/collection/immutable/StringLike$$anonfun$lines$1
Asciz	$anonfun$lines$1;
Asciz	scala/collection/immutable/StringLike$$anonfun$format$2;
class	scala/collection/immutable/StringLike$$anonfun$format$2
Asciz	$anonfun$format$2;
Asciz	scala/collection/immutable/StringLike$$anonfun$format$1;
class	scala/collection/immutable/StringLike$$anonfun$format$1
Asciz	$anonfun$format$1;
Asciz	scala/collection/immutable/StringLike$$anonfun$$times$1;
class	scala/collection/immutable/StringLike$$anonfun$$times$1
Asciz	$anonfun$$times$1;
Asciz	scala/collection/immutable/StringLike$$anonfun$stripMargin$1;
class	scala/collection/immutable/StringLike$$anonfun$stripMargin$1
Asciz	$anonfun$stripMargin$1;
Asciz	scala/collection/immutable/StringLike$$anonfun$linesIterator$1;
class	scala/collection/immutable/StringLike$$anonfun$linesIterator$1
Asciz	$anonfun$linesIterator$1;
Asciz	scala/ScalaObject;
class	scala/ScalaObject

{
public static final scala.collection.immutable.StringLike$ MODULE$;
  Signature: Lscala/collection/immutable/StringLike$;

private final char SU;
  Signature: C

private final char scala$collection$immutable$StringLike$$CR;
  Signature: C

private final char scala$collection$immutable$StringLike$$FF;
  Signature: C

private final char scala$collection$immutable$StringLike$$LF;
  Signature: C

public static {};
  Signature: ()V
  Code:
   Stack=1, Locals=0, Args_size=0
	new	class scala/collection/immutable/StringLike$
	invokespecial	Method "<init>":()V
	return
  Labels:

private scala.collection.immutable.StringLike$();
  Signature: ()V
  Code:
   Stack=2, Locals=1, Args_size=1
	aload_0
	invokespecial	Method java/lang/Object."<init>":()V
	aload_0
	putstatic	Field MODULE$:Lscala/collection/immutable/StringLike$;
	aload_0
	ldc	int 10
	putfield	Field scala$collection$immutable$StringLike$$LF:C
	aload_0
	ldc	int 12
	putfield	Field scala$collection$immutable$StringLike$$FF:C
	aload_0
	ldc	int 13
	putfield	Field scala$collection$immutable$StringLike$$CR:C
	aload_0
	ldc	int 26
	putfield	Field SU:C
	return
  Labels:

private final char SU();
  Signature: ()C
  Code:
   Stack=1, Locals=1, Args_size=1
	aload_0
	getfield	Field SU:C
	ireturn
  Labels:

public final char scala$collection$immutable$StringLike$$CR();
  Signature: ()C
  Code:
   Stack=1, Locals=1, Args_size=1
	aload_0
	getfield	Field scala$collection$immutable$StringLike$$CR:C
	ireturn
  Labels:

public final char scala$collection$immutable$StringLike$$FF();
  Signature: ()C
  Code:
   Stack=1, Locals=1, Args_size=1
	aload_0
	getfield	Field scala$collection$immutable$StringLike$$FF:C
	ireturn
  Labels:

public final char scala$collection$immutable$StringLike$$LF();
  Signature: ()C
  Code:
   Stack=1, Locals=1, Args_size=1
	aload_0
	getfield	Field scala$collection$immutable$StringLike$$LF:C
	ireturn
  Labels:

}

