Compiled from "StringLike.scala"
public final class scala.collection.immutable.StringLike$$anonfun$stripMargin$1 extends java.lang.Object implements scala.Function1,scala.ScalaObject,java.io.Serializable
  SourceFile: "StringLike.scala"
  Scala: length = 0x
   
  InnerClass: 
   public final #91= #9 of #90; //$anonfun$stripMargin$1=class scala/collection/immutable/StringLike$$anonfun$stripMargin$1 of class scala/collection/immutable/StringLike
  minor version: 0
  major version: 49
  Constant pool:
const #1 = Asciz	SourceFile;
const #2 = Asciz	StringLike.scala;
const #3 = Asciz	<clinit>;
const #4 = Asciz	()V;
const #5 = Asciz	Code;
const #6 = Asciz	serialVersionUID;
const #7 = Asciz	J;
const #8 = Asciz	scala/collection/immutable/StringLike$$anonfun$stripMargin$1;
const #9 = class	#8;	//  scala/collection/immutable/StringLike$$anonfun$stripMargin$1
const #10 = NameAndType	#6:#7;//  serialVersionUID:J
const #11 = Field	#9.#10;	//  scala/collection/immutable/StringLike$$anonfun$stripMargin$1.serialVersionUID:J
const #12 = Asciz	buf$2;
const #13 = Asciz	Lscala/collection/mutable/StringBuilder;;
const #14 = Asciz	marginChar$1;
const #15 = Asciz	C;
const #16 = Asciz	<init>;
const #17 = Asciz	(Lscala/collection/immutable/StringLike;CLscala/collection/mutable/StringBuilder;)V;
const #18 = Asciz	LineNumberTable;
const #19 = NameAndType	#14:#15;//  marginChar$1:C
const #20 = Field	#9.#19;	//  scala/collection/immutable/StringLike$$anonfun$stripMargin$1.marginChar$1:C
const #21 = NameAndType	#12:#13;//  buf$2:Lscala/collection/mutable/StringBuilder;
const #22 = Field	#9.#21;	//  scala/collection/immutable/StringLike$$anonfun$stripMargin$1.buf$2:Lscala/collection/mutable/StringBuilder;
const #23 = Asciz	java/lang/Object;
const #24 = class	#23;	//  java/lang/Object
const #25 = NameAndType	#16:#4;//  "<init>":()V
const #26 = Method	#24.#25;	//  java/lang/Object."<init>":()V
const #27 = Asciz	scala/Function1$class;
const #28 = class	#27;	//  scala/Function1$class
const #29 = Asciz	$init$;
const #30 = Asciz	(Lscala/Function1;)V;
const #31 = NameAndType	#29:#30;//  $init$:(Lscala/Function1;)V
const #32 = Method	#28.#31;	//  scala/Function1$class.$init$:(Lscala/Function1;)V
const #33 = Asciz	this;
const #34 = Asciz	Lscala/collection/immutable/StringLike$$anonfun$stripMargin$1;;
const #35 = Asciz	$outer;
const #36 = Asciz	Lscala/collection/immutable/StringLike;;
const #37 = Asciz	LocalVariableTable;
const #38 = Asciz	(Lscala/collection/immutable/StringLike<TRepr;>;)V;
const #39 = Asciz	Signature;
const #40 = Asciz	apply;
const #41 = Asciz	(Ljava/lang/Object;)Ljava/lang/Object;;
const #42 = Asciz	java/lang/String;
const #43 = class	#42;	//  java/lang/String
const #44 = Asciz	(Ljava/lang/String;)Lscala/collection/mutable/StringBuilder;;
const #45 = NameAndType	#40:#44;//  apply:(Ljava/lang/String;)Lscala/collection/mutable/StringBuilder;
const #46 = Method	#9.#45;	//  scala/collection/immutable/StringLike$$anonfun$stripMargin$1.apply:(Ljava/lang/String;)Lscala/collection/mutable/StringBuilder;
const #47 = Asciz	v1;
const #48 = Asciz	Ljava/lang/Object;;
const #49 = Asciz	length;
const #50 = Asciz	()I;
const #51 = NameAndType	#49:#50;//  length:()I
const #52 = Method	#43.#51;	//  java/lang/String.length:()I
const #53 = Asciz	charAt;
const #54 = Asciz	(I)C;
const #55 = NameAndType	#53:#54;//  charAt:(I)C
const #56 = Method	#43.#55;	//  java/lang/String.charAt:(I)C
const #57 = int	32;
const #58 = Asciz	substring;
const #59 = Asciz	(I)Ljava/lang/String;;
const #60 = NameAndType	#58:#59;//  substring:(I)Ljava/lang/String;
const #61 = Method	#43.#60;	//  java/lang/String.substring:(I)Ljava/lang/String;
const #62 = Asciz	scala/collection/mutable/StringBuilder;
const #63 = class	#62;	//  scala/collection/mutable/StringBuilder
const #64 = Asciz	append;
const #65 = NameAndType	#64:#44;//  append:(Ljava/lang/String;)Lscala/collection/mutable/StringBuilder;
const #66 = Method	#63.#65;	//  scala/collection/mutable/StringBuilder.append:(Ljava/lang/String;)Lscala/collection/mutable/StringBuilder;
const #67 = Asciz	line;
const #68 = Asciz	Ljava/lang/String;;
const #69 = Asciz	len;
const #70 = Asciz	I;
const #71 = Asciz	index;
const #72 = Asciz	andThen;
const #73 = Asciz	(Lscala/Function1;)Lscala/Function1;;
const #74 = Asciz	(Lscala/Function1;Lscala/Function1;)Lscala/Function1;;
const #75 = NameAndType	#72:#74;//  andThen:(Lscala/Function1;Lscala/Function1;)Lscala/Function1;
const #76 = Method	#28.#75;	//  scala/Function1$class.andThen:(Lscala/Function1;Lscala/Function1;)Lscala/Function1;
const #77 = Asciz	g;
const #78 = Asciz	Lscala/Function1;;
const #79 = Asciz	compose;
const #80 = NameAndType	#79:#74;//  compose:(Lscala/Function1;Lscala/Function1;)Lscala/Function1;
const #81 = Method	#28.#80;	//  scala/Function1$class.compose:(Lscala/Function1;Lscala/Function1;)Lscala/Function1;
const #82 = Asciz	toString;
const #83 = Asciz	()Ljava/lang/String;;
const #84 = Asciz	(Lscala/Function1;)Ljava/lang/String;;
const #85 = NameAndType	#82:#84;//  toString:(Lscala/Function1;)Ljava/lang/String;
const #86 = Method	#28.#85;	//  scala/Function1$class.toString:(Lscala/Function1;)Ljava/lang/String;
const #87 = Asciz	Scala;
const #88 = Asciz	InnerClasses;
const #89 = Asciz	scala/collection/immutable/StringLike;
const #90 = class	#89;	//  scala/collection/immutable/StringLike
const #91 = Asciz	$anonfun$stripMargin$1;
const #92 = Asciz	scala/Function1;
const #93 = class	#92;	//  scala/Function1
const #94 = Asciz	scala/ScalaObject;
const #95 = class	#94;	//  scala/ScalaObject
const #96 = Asciz	java/io/Serializable;
const #97 = class	#96;	//  java/io/Serializable

{
public static final long serialVersionUID;

public static {};
  Code:
   Stack=2, Locals=0, Args_size=0
   0:	lconst_0
   1:	putstatic	#11; //Field serialVersionUID:J
   4:	return

public scala.collection.immutable.StringLike$$anonfun$stripMargin$1(scala.collection.immutable.StringLike, char, scala.collection.mutable.StringBuilder);
  Code:
   Stack=2, Locals=4, Args_size=4
   0:	aload_0
   1:	iload_2
   2:	putfield	#20; //Field marginChar$1:C
   5:	aload_0
   6:	aload_3
   7:	putfield	#22; //Field buf$2:Lscala/collection/mutable/StringBuilder;
   10:	aload_0
   11:	invokespecial	#26; //Method java/lang/Object."<init>":()V
   14:	aload_0
   15:	invokestatic	#32; //Method scala/Function1$class.$init$:(Lscala/Function1;)V
   18:	return
  LineNumberTable: 
   line 161: 0

  LocalVariableTable: 
   Start  Length  Slot  Name   Signature
   0      19      0    this       Lscala/collection/immutable/StringLike$$anonfun$stripMargin$1;
   0      19      1    $outer       Lscala/collection/immutable/StringLike;

  Signature: length = 0x2
   00 26 

public final java.lang.Object apply(java.lang.Object);
  Code:
   Stack=2, Locals=2, Args_size=2
   0:	aload_0
   1:	aload_1
   2:	checkcast	#43; //class java/lang/String
   5:	invokevirtual	#46; //Method apply:(Ljava/lang/String;)Lscala/collection/mutable/StringBuilder;
   8:	areturn
  LineNumberTable: 
   line 161: 0

  LocalVariableTable: 
   Start  Length  Slot  Name   Signature
   0      9      0    this       Lscala/collection/immutable/StringLike$$anonfun$stripMargin$1;
   0      9      1    v1       Ljava/lang/Object;


public final scala.collection.mutable.StringBuilder apply(java.lang.String);
  Code:
   Stack=4, Locals=4, Args_size=2
   0:	aload_1
   1:	invokevirtual	#52; //Method java/lang/String.length:()I
   4:	istore_2
   5:	iconst_0
   6:	istore_3
   7:	iload_3
   8:	iload_2
   9:	if_icmpge	29
   12:	aload_1
   13:	iload_3
   14:	invokevirtual	#56; //Method java/lang/String.charAt:(I)C
   17:	ldc	#57; //int 32
   19:	if_icmpgt	29
   22:	iload_3
   23:	iconst_1
   24:	iadd
   25:	istore_3
   26:	goto	7
   29:	aload_0
   30:	getfield	#22; //Field buf$2:Lscala/collection/mutable/StringBuilder;
   33:	iload_3
   34:	iload_2
   35:	if_icmpge	60
   38:	aload_1
   39:	iload_3
   40:	invokevirtual	#56; //Method java/lang/String.charAt:(I)C
   43:	aload_0
   44:	getfield	#20; //Field marginChar$1:C
   47:	if_icmpne	60
   50:	aload_1
   51:	iload_3
   52:	iconst_1
   53:	iadd
   54:	invokevirtual	#61; //Method java/lang/String.substring:(I)Ljava/lang/String;
   57:	goto	61
   60:	aload_1
   61:	invokevirtual	#66; //Method scala/collection/mutable/StringBuilder.append:(Ljava/lang/String;)Lscala/collection/mutable/StringBuilder;
   64:	areturn
  LineNumberTable: 
   line 162: 0
   line 163: 5
   line 164: 7
   line 165: 29
   line 166: 33
   line 165: 61

  LocalVariableTable: 
   Start  Length  Slot  Name   Signature
   0      65      0    this       Lscala/collection/immutable/StringLike$$anonfun$stripMargin$1;
   0      65      1    line       Ljava/lang/String;
   5      59      2    len       I
   7      57      3    index       I


public scala.Function1 andThen(scala.Function1);
  Code:
   Stack=2, Locals=2, Args_size=2
   0:	aload_0
   1:	aload_1
   2:	invokestatic	#76; //Method scala/Function1$class.andThen:(Lscala/Function1;Lscala/Function1;)Lscala/Function1;
   5:	areturn
  LineNumberTable: 
   line 161: 0

  LocalVariableTable: 
   Start  Length  Slot  Name   Signature
   0      6      0    this       Lscala/collection/immutable/StringLike$$anonfun$stripMargin$1;
   0      6      1    g       Lscala/Function1;


public scala.Function1 compose(scala.Function1);
  Code:
   Stack=2, Locals=2, Args_size=2
   0:	aload_0
   1:	aload_1
   2:	invokestatic	#81; //Method scala/Function1$class.compose:(Lscala/Function1;Lscala/Function1;)Lscala/Function1;
   5:	areturn
  LineNumberTable: 
   line 161: 0

  LocalVariableTable: 
   Start  Length  Slot  Name   Signature
   0      6      0    this       Lscala/collection/immutable/StringLike$$anonfun$stripMargin$1;
   0      6      1    g       Lscala/Function1;


public java.lang.String toString();
  Code:
   Stack=1, Locals=1, Args_size=1
   0:	aload_0
   1:	invokestatic	#86; //Method scala/Function1$class.toString:(Lscala/Function1;)Ljava/lang/String;
   4:	areturn
  LineNumberTable: 
   line 161: 0


}

