Compiled from "TreeSet.scala"
public final class scala.collection.immutable.TreeSet$$anonfun$foreach$1 extends java.lang.Object implements scala.Function2,scala.ScalaObject,java.io.Serializable
  SourceFile: "TreeSet.scala"
  Scala: length = 0x
   
  InnerClass: 
   public final $anonfun$foreach$1=class scala/collection/immutable/TreeSet$$anonfun$foreach$1 of class scala/collection/immutable/TreeSet
  minor version: 0
  major version: 49
  Constant pool:
Asciz	SourceFile;
Asciz	TreeSet.scala;
Asciz	<clinit>;
Asciz	()V;
Asciz	Code;
Asciz	serialVersionUID;
Asciz	J;
Asciz	scala/collection/immutable/TreeSet$$anonfun$foreach$1;
class	scala/collection/immutable/TreeSet$$anonfun$foreach$1
NameAndType	serialVersionUID:J
Field	scala/collection/immutable/TreeSet$$anonfun$foreach$1.serialVersionUID:J
Asciz	f$1;
Asciz	Lscala/Function1;;
Asciz	<init>;
Asciz	(Lscala/collection/immutable/TreeSet;Lscala/Function1;)V;
Asciz	LineNumberTable;
NameAndType	f$1:Lscala/Function1;
Field	scala/collection/immutable/TreeSet$$anonfun$foreach$1.f$1:Lscala/Function1;
Asciz	java/lang/Object;
class	java/lang/Object
NameAndType	"<init>":()V
Method	java/lang/Object."<init>":()V
Asciz	scala/Function2$class;
class	scala/Function2$class
Asciz	$init$;
Asciz	(Lscala/Function2;)V;
NameAndType	$init$:(Lscala/Function2;)V
Method	scala/Function2$class.$init$:(Lscala/Function2;)V
Asciz	this;
Asciz	Lscala/collection/immutable/TreeSet$$anonfun$foreach$1;;
Asciz	$outer;
Asciz	Lscala/collection/immutable/TreeSet;;
Asciz	LocalVariableTable;
Asciz	(Lscala/collection/immutable/TreeSet<TA;>;)V;
Asciz	Signature;
Asciz	apply;
Asciz	(Ljava/lang/Object;Ljava/lang/Object;)Ljava/lang/Object;;
Asciz	scala/runtime/BoxedUnit;
class	scala/runtime/BoxedUnit
Asciz	(Ljava/lang/Object;Lscala/runtime/BoxedUnit;)Ljava/lang/Object;;
NameAndType	apply:(Ljava/lang/Object;Lscala/runtime/BoxedUnit;)Ljava/lang/Object;
Method	scala/collection/immutable/TreeSet$$anonfun$foreach$1.apply:(Ljava/lang/Object;Lscala/runtime/BoxedUnit;)Ljava/lang/Object;
Asciz	v1;
Asciz	Ljava/lang/Object;;
Asciz	v2;
Asciz	scala/Function1;
class	scala/Function1
Asciz	(Ljava/lang/Object;)Ljava/lang/Object;;
NameAndType	apply:(Ljava/lang/Object;)Ljava/lang/Object;
InterfaceMethod	scala/Function1.apply:(Ljava/lang/Object;)Ljava/lang/Object;
Asciz	x;
Asciz	y;
Asciz	Lscala/runtime/BoxedUnit;;
Asciz	(TA;Lscala/runtime/BoxedUnit;)TU;;
Asciz	curry;
Asciz	()Lscala/Function1;;
Asciz	(Lscala/Function2;)Lscala/Function1;;
NameAndType	curry:(Lscala/Function2;)Lscala/Function1;
Method	scala/Function2$class.curry:(Lscala/Function2;)Lscala/Function1;
Asciz	toString;
Asciz	()Ljava/lang/String;;
Asciz	(Lscala/Function2;)Ljava/lang/String;;
NameAndType	toString:(Lscala/Function2;)Ljava/lang/String;
Method	scala/Function2$class.toString:(Lscala/Function2;)Ljava/lang/String;
Asciz	Scala;
Asciz	InnerClasses;
Asciz	scala/collection/immutable/TreeSet;
class	scala/collection/immutable/TreeSet
Asciz	$anonfun$foreach$1;
Asciz	scala/Function2;
class	scala/Function2
Asciz	scala/ScalaObject;
class	scala/ScalaObject
Asciz	java/io/Serializable;
class	java/io/Serializable

{
public static final long serialVersionUID;
  Signature: J

private final scala.Function1 f$1;
  Signature: Lscala/Function1;

public static {};
  Signature: ()V
  Code:
   Stack=2, Locals=0, Args_size=0
	lconst_0
	putstatic	Field serialVersionUID:J
	return
  Labels:

public scala.collection.immutable.TreeSet$$anonfun$foreach$1(scala.collection.immutable.TreeSet, scala.Function1);
  Signature: (Lscala/collection/immutable/TreeSet;Lscala/Function1;)V
  Code:
   Stack=2, Locals=3, Args_size=3
	aload_0
	aload_2
	putfield	Field f$1:Lscala/Function1;
	aload_0
	invokespecial	Method java/lang/Object."<init>":()V
	aload_0
	invokestatic	Method scala/Function2$class.$init$:(Lscala/Function2;)V
	return
  Labels:
  LocalVariableTable: 
   Start  Length  Slot  Name   Signature
   0      14      0    this       Lscala/collection/immutable/TreeSet$$anonfun$foreach$1;
   0      14      1    $outer       Lscala/collection/immutable/TreeSet;

  Signature: length = 0x2
   00 22 

public final java.lang.Object apply(java.lang.Object, java.lang.Object);
  Signature: (Ljava/lang/Object;Ljava/lang/Object;)Ljava/lang/Object;
  Code:
   Stack=3, Locals=3, Args_size=3
	aload_0
	aload_1
	aload_2
	checkcast	class scala/runtime/BoxedUnit
	invokevirtual	Method apply:(Ljava/lang/Object;Lscala/runtime/BoxedUnit;)Ljava/lang/Object;
	areturn
  Labels:
  LocalVariableTable: 
   Start  Length  Slot  Name   Signature
   0      10      0    this       Lscala/collection/immutable/TreeSet$$anonfun$foreach$1;
   0      10      1    v1       Ljava/lang/Object;
   0      10      2    v2       Ljava/lang/Object;


public final java.lang.Object apply(java.lang.Object, scala.runtime.BoxedUnit);
  Signature: (Ljava/lang/Object;Lscala/runtime/BoxedUnit;)Ljava/lang/Object;
  Code:
   Stack=2, Locals=3, Args_size=3
	aload_0
	getfield	Field f$1:Lscala/Function1;
	aload_1
	invokeinterface	InterfaceMethod scala/Function1.apply:(Ljava/lang/Object;)Ljava/lang/Object;
	areturn
  Labels:
  LocalVariableTable: 
   Start  Length  Slot  Name   Signature
   0      11      0    this       Lscala/collection/immutable/TreeSet$$anonfun$foreach$1;
   0      11      1    x       Ljava/lang/Object;
   0      11      2    y       Lscala/runtime/BoxedUnit;

  Signature: length = 0x2
   00 36 

public scala.Function1 curry();
  Signature: ()Lscala/Function1;
  Code:
   Stack=1, Locals=1, Args_size=1
	aload_0
	invokestatic	Method scala/Function2$class.curry:(Lscala/Function2;)Lscala/Function1;
	areturn
  Labels:

public java.lang.String toString();
  Signature: ()Ljava/lang/String;
  Code:
   Stack=1, Locals=1, Args_size=1
	aload_0
	invokestatic	Method scala/Function2$class.toString:(Lscala/Function2;)Ljava/lang/String;
	areturn
  Labels:

}

