Compiled from "Vector.scala"
public final class scala.collection.immutable.Vector extends java.lang.Object implements scala.collection.immutable.Seq,scala.collection.generic.GenericTraversableTemplate,scala.collection.SeqLike,scala.collection.immutable.VectorPointer,scala.ScalaObject,java.io.Serializable
  SourceFile: "Vector.scala"
  Signature: length = 0x2
   04 5E 
  ScalaSig: length = 0xB76
   05 00 FFFFFF82 7E 07 05 01 02 FFFFFF88 02 09 01 06 56 65 63
   74 6F 72 0A 02 03 04 01 09 69 6D 6D 75 74 61 62
   6C 65 0A 02 05 06 01 0A 63 6F 6C 6C 65 63 74 69
   6F 6E 0A 01 07 01 05 73 63 61 6C 61 03 00 10 02
   0A 0B 0D 01 02 06 08 0C 02 FFFFFF84 FFFFFF80 FFFFFF80 FFFFFF88 02 0D 02
   06 56 65 63 74 6F 72 13 03 0B 0E 44 10 03 0F 12
   14 0D 01 10 0A 02 11 04 01 07 67 65 6E 65 72 69
   63 09 02 13 10 02 0A 53 65 71 46 61 63 74 6F 72
   79 10 02 0A 15 06 04 0C 02 02 16 15 02 17 25 13
   07 15 18 20 2F 32 37 44 10 02 19 1E 0D 01 1A 0A
   02 1B 1C 01 04 6C 61 6E 67 0A 01 1D 01 04 6A 61
   76 61 09 02 1F 1A 02 06 4F 62 6A 65 63 74 10 03
   0A 21 23 09 02 22 02 02 03 53 65 71 10 02 24 25
   0C 00 04 08 26 15 FFFFFF84 FFFFFF80 FFFFFF84 FFFFFFC2 00 27 02 01 41 11
   02 28 2C 10 02 29 2A 0D 01 06 09 02 2B 06 02 07
   4E 6F 74 68 69 6E 67 10 02 29 2D 09 02 2E 06 02
   03 41 6E 79 10 04 0F 30 23 14 09 02 31 10 02 1A
   47 65 6E 65 72 69 63 54 72 61 76 65 72 73 61 62
   6C 65 54 65 6D 70 6C 61 74 65 10 04 33 34 23 36
   0D 01 04 09 02 35 04 02 07 53 65 71 4C 69 6B 65
   10 03 0A 15 23 10 03 0A 38 3A 09 02 39 02 02 0D
   56 65 63 74 6F 72 50 6F 69 6E 74 65 72 2A 02 23
   3B 2B 01 3C 10 02 3D 42 0D 01 3E 0A 02 3F 40 01
   09 75 6E 63 68 65 63 6B 65 64 0A 02 41 06 01 0A
   61 6E 6E 6F 74 61 74 69 6F 6E 09 02 43 3E 02 11
   75 6E 63 68 65 63 6B 65 64 56 61 72 69 61 6E 63
   65 10 02 29 45 09 02 46 06 02 0B 53 63 61 6C 61
   4F 62 6A 65 63 74 08 08 48 15 FFFFFF82 FFFFFF80 FFFFFFA0 FFFFFF80 04 49
   01 0A 73 74 61 72 74 49 6E 64 65 78 10 02 29 4A
   09 02 4B 06 02 03 49 6E 74 08 08 4D 15 FFFFFF82 FFFFFF80 FFFFFFA0
   FFFFFF80 04 49 01 08 65 6E 64 49 6E 64 65 78 08 08 4F
   15 FFFFFF82 FFFFFF80 FFFFFFA0 FFFFFF80 04 49 01 05 66 6F 63 75 73 08 05
   51 15 FFFFFF84 00 52 01 06 3C 69 6E 69 74 3E 14 04 36
   53 54 55 08 05 48 50 FFFFFFC0 00 49 08 05 4D 50 FFFFFFC0 00
   49 08 05 4F 50 FFFFFFC0 00 49 08 05 57 15 FFFFFF84 20 58 01
   09 63 6F 6D 70 61 6E 69 6F 6E 15 01 59 10 03 0F
   5A 14 09 02 5B 10 02 10 47 65 6E 65 72 69 63 43
   6F 6D 70 61 6E 69 6F 6E 08 07 5D 15 FFFFFFC0 FFFFFF80 FFFFFF84 00
   5E 01 05 64 69 72 74 79 15 01 5F 10 02 29 60 09
   02 61 06 02 07 42 6F 6F 6C 65 61 6E 08 07 63 15
   FFFFFFC0 FFFFFF80 FFFFFF84 00 64 01 09 64 69 72 74 79 5F 24 65 71
   14 02 65 68 10 02 29 66 09 02 67 06 02 04 55 6E
   69 74 08 07 69 62 FFFFFF81 FFFFFF80 FFFFFFC0 00 5F 01 03 78 24 31
   08 06 6B 15 FFFFFFA0 FFFFFFA0 04 5F 01 06 64 69 72 74 79 20
   08 05 6D 15 FFFFFF84 00 6E 01 06 6C 65 6E 67 74 68 15
   01 49 08 05 70 15 FFFFFF84 20 71 01 0D 6C 65 6E 67 74
   68 43 6F 6D 70 61 72 65 14 02 49 72 08 05 73 6F
   FFFFFFC0 00 49 01 03 6C 65 6E 08 05 75 15 FFFFFF84 20 76 01
   08 69 74 65 72 61 74 6F 72 15 01 77 10 03 0A 78
   23 09 02 79 02 02 0E 56 65 63 74 6F 72 49 74 65
   72 61 74 6F 72 28 02 74 7B 10 02 29 7C 09 02 7D
   06 02 06 69 6E 6C 69 6E 65 08 06 7F 15 FFFFFF84 00 FFFFFF81
   00 01 08 66 6F 72 65 61 63 68 30 15 04 FFFFFF81 01 FFFFFF81
   08 14 03 65 FFFFFF81 02 08 07 FFFFFF81 03 7E FFFFFFC0 00 FFFFFF81 04 01
   01 66 10 06 29 FFFFFF81 05 23 FFFFFF81 07 09 03 FFFFFF81 06 06 02
   09 46 75 6E 63 74 69 6F 6E 31 10 03 24 FFFFFF81 08 04
   09 FFFFFF81 09 7E FFFFFF84 FFFFFF80 FFFFFF80 FFFFFFC2 00 27 02 01 55 28 02 7E
   7B 08 07 FFFFFF81 0C 15 FFFFFF84 00 FFFFFF81 0D 01 04 6D 61 70 30
   15 06 FFFFFF81 0E FFFFFF81 19 FFFFFF81 11 14 04 FFFFFF81 0F FFFFFF81 1B 16 04
   FFFFFF81 10 FFFFFF81 13 10 03 24 FFFFFF81 11 04 0A FFFFFF81 12 FFFFFF81 0B FFFFFF84
   FFFFFF80 FFFFFF80 FFFFFFC2 00 27 02 04 54 68 61 74 08 08 FFFFFF81 14 FFFFFF81
   0B FFFFFFC0 01 FFFFFF81 15 01 02 62 66 10 08 0F FFFFFF81 16 36 FFFFFF81
   18 FFFFFF81 10 09 03 FFFFFF81 17 10 02 0C 43 61 6E 42 75 69
   6C 64 46 72 6F 6D 10 03 24 FFFFFF81 19 04 0A FFFFFF81 1A FFFFFF81
   0B FFFFFF84 FFFFFF80 FFFFFF80 FFFFFFC2 00 27 02 01 42 08 08 FFFFFF81 03 FFFFFF81 0B
   FFFFFFC0 00 FFFFFF81 1C 10 06 29 FFFFFF81 05 23 FFFFFF81 18 28 03 FFFFFF81 0B
   7B 08 07 FFFFFF81 1F 15 FFFFFF84 00 FFFFFF81 20 01 05 61 70 70 6C
   79 14 03 23 FFFFFF81 21 08 07 FFFFFF81 22 FFFFFF81 1E FFFFFFC0 00 49 01
   05 69 6E 64 65 78 08 07 FFFFFF81 24 15 FFFFFF84 04 FFFFFF81 25 01
   11 63 68 65 63 6B 52 61 6E 67 65 43 6F 6E 76 65
   72 74 14 03 49 FFFFFF81 26 08 07 FFFFFF81 22 FFFFFF81 23 FFFFFFC0 00 49
   08 07 FFFFFF81 28 15 FFFFFF84 20 FFFFFF81 29 01 07 75 70 64 61 74
   65 64 15 06 FFFFFF81 2A FFFFFF81 31 FFFFFF81 2D 14 06 FFFFFF81 2B FFFFFF81 33
   FFFFFF81 34 16 04 FFFFFF81 2C FFFFFF81 2E 10 03 24 FFFFFF81 2D 04 0A FFFFFF81
   12 FFFFFF81 27 FFFFFF84 FFFFFF80 FFFFFF80 FFFFFFC2 00 27 08 08 FFFFFF81 14 FFFFFF81 27 FFFFFFC0
   01 FFFFFF81 2F 10 08 0F FFFFFF81 16 36 FFFFFF81 30 FFFFFF81 2C 10 03 24
   FFFFFF81 31 04 0B FFFFFF81 1A FFFFFF81 27 FFFFFF84 FFFFFF80 FFFFFF80 FFFFFFC2 00 FFFFFF81 32 11
   02 23 2C 08 07 FFFFFF81 22 FFFFFF81 27 FFFFFFC0 00 49 08 08 FFFFFF81 35
   FFFFFF81 27 FFFFFFC0 00 FFFFFF81 30 01 04 65 6C 65 6D 28 03 FFFFFF81 27
   7B 08 07 FFFFFF81 38 15 FFFFFF84 20 FFFFFF81 39 01 0B 24 70 6C 75
   73 24 63 6F 6C 6F 6E 15 06 FFFFFF81 3A FFFFFF81 41 FFFFFF81 3D 14
   04 FFFFFF81 3B FFFFFF81 42 16 04 FFFFFF81 3C FFFFFF81 3E 10 03 24 FFFFFF81 3D
   04 0A FFFFFF81 12 FFFFFF81 37 FFFFFF84 FFFFFF80 FFFFFF80 FFFFFFC2 00 27 08 08 FFFFFF81 14
   FFFFFF81 37 FFFFFFC0 01 FFFFFF81 3F 10 08 0F FFFFFF81 16 36 FFFFFF81 40 FFFFFF81 3C
   10 03 24 FFFFFF81 41 04 0B FFFFFF81 1A FFFFFF81 37 FFFFFF84 FFFFFF80 FFFFFF80 FFFFFFC2 00
   FFFFFF81 32 08 08 FFFFFF81 35 FFFFFF81 37 FFFFFFC0 00 FFFFFF81 40 28 03 FFFFFF81 37
   7B 08 07 FFFFFF81 45 15 FFFFFF84 20 FFFFFF81 46 01 0B 24 63 6F 6C
   6F 6E 24 70 6C 75 73 15 06 FFFFFF81 47 FFFFFF81 4E FFFFFF81 4A 14
   04 FFFFFF81 48 FFFFFF81 4F 16 04 FFFFFF81 49 FFFFFF81 4B 10 03 24 FFFFFF81 4A
   04 0A FFFFFF81 12 FFFFFF81 44 FFFFFF84 FFFFFF80 FFFFFF80 FFFFFFC2 00 27 08 08 FFFFFF81 14
   FFFFFF81 44 FFFFFFC0 01 FFFFFF81 4C 10 08 0F FFFFFF81 16 36 FFFFFF81 4D FFFFFF81 49
   10 03 24 FFFFFF81 4E 04 0B FFFFFF81 1A FFFFFF81 44 FFFFFF84 FFFFFF80 FFFFFF80 FFFFFFC2 00
   FFFFFF81 32 08 08 FFFFFF81 35 FFFFFF81 44 FFFFFFC0 00 FFFFFF81 4D 28 03 FFFFFF81 44
   7B 08 07 FFFFFF81 52 15 FFFFFF84 20 FFFFFF81 53 01 04 74 61 6B 65
   14 03 36 FFFFFF81 54 08 07 FFFFFF81 55 FFFFFF81 51 FFFFFFC0 00 49 01 01
   6E 08 07 FFFFFF81 57 15 FFFFFF84 20 FFFFFF81 58 01 04 64 72 6F 70
   14 03 36 FFFFFF81 59 08 07 FFFFFF81 55 FFFFFF81 56 FFFFFFC0 00 49 08 07
   FFFFFF81 5B 15 FFFFFF84 20 FFFFFF81 5C 01 09 74 61 6B 65 52 69 67
   68 74 14 03 36 FFFFFF81 5D 08 07 FFFFFF81 55 FFFFFF81 5A FFFFFFC0 00 49
   08 07 FFFFFF81 5F 15 FFFFFF84 20 FFFFFF81 60 01 09 64 72 6F 70 52
   69 67 68 74 14 03 36 FFFFFF81 61 08 07 FFFFFF81 55 FFFFFF81 5E FFFFFFC0
   00 49 08 07 FFFFFF81 63 15 FFFFFF84 00 FFFFFF81 64 01 08 75 70 64
   61 74 65 41 74 15 04 FFFFFF81 65 FFFFFF81 68 14 06 FFFFFF81 66 FFFFFF81
   69 FFFFFF81 6A 10 04 0A 15 FFFFFF81 67 10 03 24 FFFFFF81 68 04 0B
   FFFFFF81 1A FFFFFF81 62 FFFFFF84 FFFFFF80 FFFFFF80 FFFFFFC2 00 FFFFFF81 32 08 07 FFFFFF81 22 FFFFFF81
   62 FFFFFFC0 00 49 08 08 FFFFFF81 35 FFFFFF81 62 FFFFFFC0 00 FFFFFF81 67 08 07
   FFFFFF81 6C 15 FFFFFF84 04 FFFFFF81 6D 01 0F 67 6F 74 6F 50 6F 73
   57 72 69 74 61 62 6C 65 14 07 65 FFFFFF81 6E FFFFFF81 70 FFFFFF81
   72 08 07 FFFFFF81 6F FFFFFF81 6B FFFFFFC0 00 49 01 08 6F 6C 64 49
   6E 64 65 78 08 07 FFFFFF81 71 FFFFFF81 6B FFFFFFC0 00 49 01 08 6E
   65 77 49 6E 64 65 78 08 07 FFFFFF81 73 FFFFFF81 6B FFFFFFC0 00 49
   01 03 78 6F 72 08 07 FFFFFF81 75 15 FFFFFF84 04 FFFFFF81 76 01 14
   67 6F 74 6F 46 72 65 73 68 50 6F 73 57 72 69 74
   61 62 6C 65 14 07 65 FFFFFF81 77 FFFFFF81 78 FFFFFF81 79 08 07 FFFFFF81
   6F FFFFFF81 74 FFFFFFC0 00 49 08 07 FFFFFF81 71 FFFFFF81 74 FFFFFFC0 00 49 08
   07 FFFFFF81 73 FFFFFF81 74 FFFFFFC0 00 49 08 07 FFFFFF81 7B 15 FFFFFF84 00 FFFFFF81
   7C 01 0B 61 70 70 65 6E 64 46 72 6F 6E 74 15 04
   FFFFFF81 7D FFFFFF82 00 14 04 FFFFFF81 7E FFFFFF82 01 10 04 0A 15 FFFFFF81 7F
   10 03 24 FFFFFF82 00 04 0B FFFFFF81 1A FFFFFF81 7A FFFFFF84 FFFFFF80 FFFFFF80 FFFFFFC2 00
   FFFFFF81 32 08 08 FFFFFF82 02 FFFFFF81 7A FFFFFFC0 00 FFFFFF81 7F 01 05 76 61
   6C 75 65 08 07 FFFFFF82 04 15 FFFFFF84 00 FFFFFF82 05 01 0A 61 70
   70 65 6E 64 42 61 63 6B 15 04 FFFFFF82 06 FFFFFF82 09 14 04
   FFFFFF82 07 FFFFFF82 0A 10 04 0A 15 FFFFFF82 08 10 03 24 FFFFFF82 09 04
   0B FFFFFF81 1A FFFFFF82 03 FFFFFF84 FFFFFF80 FFFFFF80 FFFFFFC2 00 FFFFFF81 32 08 08 FFFFFF82 02
   FFFFFF82 03 FFFFFFC0 00 FFFFFF82 08 08 07 FFFFFF82 0C 15 FFFFFF84 04 FFFFFF82 0D 01
   0D 73 68 69 66 74 54 6F 70 4C 65 76 65 6C 14 05
   65 FFFFFF82 0E FFFFFF82 10 08 07 FFFFFF82 0F FFFFFF82 0B FFFFFFC0 00 49 01 07
   6F 6C 64 4C 65 66 74 08 07 FFFFFF82 11 FFFFFF82 0B FFFFFFC0 00 49
   01 07 6E 65 77 4C 65 66 74 08 07 FFFFFF82 13 15 FFFFFF84 00
   FFFFFF82 14 01 08 7A 65 72 6F 4C 65 66 74 14 05 65 FFFFFF82
   15 FFFFFF82 1D 08 08 FFFFFF82 16 FFFFFF82 12 FFFFFFC0 00 FFFFFF82 17 01 05 61
   72 72 61 79 10 05 29 FFFFFF82 18 FFFFFF82 1A 09 03 FFFFFF82 19 06
   02 05 41 72 72 61 79 10 03 29 FFFFFF82 1B 09 03 FFFFFF82 1C
   06 02 06 41 6E 79 52 65 66 08 07 FFFFFF81 22 FFFFFF82 12 FFFFFFC0
   00 49 08 07 FFFFFF82 1F 15 FFFFFF84 00 FFFFFF82 20 01 09 7A 65 72
   6F 52 69 67 68 74 14 05 65 FFFFFF82 21 FFFFFF82 22 08 08 FFFFFF82
   16 FFFFFF82 1E FFFFFFC0 00 FFFFFF82 17 08 07 FFFFFF81 22 FFFFFF82 1E FFFFFFC0 00 49
   08 07 FFFFFF82 24 15 FFFFFF84 00 FFFFFF82 25 01 08 63 6F 70 79 4C
   65 66 74 14 06 FFFFFF82 17 FFFFFF82 26 FFFFFF82 27 08 08 FFFFFF82 16 FFFFFF82
   23 FFFFFFC0 00 FFFFFF82 17 08 07 FFFFFF82 28 FFFFFF82 23 FFFFFFC0 00 49 01 05
   72 69 67 68 74 08 07 FFFFFF82 2A 15 FFFFFF84 00 FFFFFF82 2B 01 09
   63 6F 70 79 52 69 67 68 74 14 06 FFFFFF82 17 FFFFFF82 2C FFFFFF82
   2D 08 08 FFFFFF82 16 FFFFFF82 29 FFFFFFC0 00 FFFFFF82 17 08 07 FFFFFF82 2E FFFFFF82
   29 FFFFFFC0 00 49 01 04 6C 65 66 74 08 07 FFFFFF82 30 15 FFFFFF84
   04 FFFFFF82 31 01 08 70 72 65 43 6C 65 61 6E 14 03 65
   FFFFFF82 32 08 07 FFFFFF82 33 FFFFFF82 2F FFFFFFC0 00 49 01 05 64 65 70
   74 68 08 07 FFFFFF82 35 15 FFFFFF84 04 FFFFFF82 36 01 0D 63 6C 65
   61 6E 4C 65 66 74 45 64 67 65 14 03 65 FFFFFF82 37 08
   07 FFFFFF82 38 FFFFFF82 34 FFFFFFC0 00 49 01 08 63 75 74 49 6E 64
   65 78 08 07 FFFFFF82 3A 15 FFFFFF84 04 FFFFFF82 3B 01 0E 63 6C 65
   61 6E 52 69 67 68 74 45 64 67 65 14 03 65 FFFFFF82 3C
   08 07 FFFFFF82 38 FFFFFF82 39 FFFFFFC0 00 49 08 07 FFFFFF82 3E 15 FFFFFF84 04
   FFFFFF82 3F 01 0D 72 65 71 75 69 72 65 64 44 65 70 74
   68 14 03 49 FFFFFF82 40 08 07 FFFFFF81 73 FFFFFF82 3D FFFFFFC0 00 49 08
   07 FFFFFF82 42 15 FFFFFF84 04 FFFFFF82 43 01 0A 64 72 6F 70 46 72
   6F 6E 74 30 14 03 36 FFFFFF82 44 08 07 FFFFFF82 38 FFFFFF82 41 FFFFFFC0
   00 49 08 07 FFFFFF82 46 15 FFFFFF84 04 FFFFFF82 47 01 09 64 72 6F
   70 42 61 63 6B 30 14 03 36 FFFFFF82 48 08 07 FFFFFF82 38 FFFFFF82
   45 FFFFFFC0 00 49 28 03 15 FFFFFF82 4A 10 03 29 FFFFFF82 4B 09 03
   FFFFFF82 4C 06 02 0C 73 65 72 69 61 6C 69 7A 61 62 6C
   65 08 06 51 0B FFFFFF84 00 FFFFFF82 4E 14 01 09 08 09 FFFFFF82 50
   0B FFFFFFC2 FFFFFF80 FFFFFF84 00 FFFFFF82 51 01 02 42 46 15 02 FFFFFF82 52 10
   05 FFFFFF82 53 FFFFFF82 54 28 0D 01 0B 09 04 FFFFFF82 55 FFFFFF82 56 02
   13 47 65 6E 65 72 69 63 43 61 6E 42 75 69 6C 64
   46 72 6F 6D 09 03 FFFFFF82 57 10 02 12 54 72 61 76 65
   72 73 61 62 6C 65 46 61 63 74 6F 72 79 08 08 FFFFFF82
   59 0B FFFFFFA0 FFFFFF80 04 FFFFFF82 52 01 03 42 46 20 08 07 FFFFFF82 5B
   0B FFFFFF84 01 FFFFFF82 5C 01 0C 63 61 6E 42 75 69 6C 64 46
   72 6F 6D 15 04 FFFFFF82 5D FFFFFF82 62 10 09 0F FFFFFF81 16 FFFFFF82 5E
   FFFFFF82 61 FFFFFF82 63 10 04 FFFFFF82 53 FFFFFF82 5F 09 03 FFFFFF82 60 5A 02
   04 43 6F 6C 6C 10 03 24 FFFFFF82 62 04 09 26 FFFFFF82 5A FFFFFF84
   FFFFFF80 FFFFFF80 FFFFFFC2 00 27 10 04 0A 15 FFFFFF82 61 28 03 FFFFFF82 5A 7B
   08 07 FFFFFF82 66 0B FFFFFF84 00 FFFFFF82 67 01 0A 6E 65 77 42 75
   69 6C 64 65 72 15 04 FFFFFF82 68 FFFFFF82 6F 10 08 FFFFFF82 69 FFFFFF82
   6C FFFFFF82 6E FFFFFF82 70 0D 02 FFFFFF82 6A 0A 03 FFFFFF82 6B 04 01 07
   6D 75 74 61 62 6C 65 09 04 FFFFFF82 6D FFFFFF82 6A 02 07 42
   75 69 6C 64 65 72 10 03 24 FFFFFF82 6F 04 09 26 FFFFFF82 65
   FFFFFF84 FFFFFF80 FFFFFF80 FFFFFFC2 00 27 10 04 0A 15 FFFFFF82 6E 08 09 FFFFFF82 72
   0B FFFFFFC2 FFFFFF80 FFFFFF84 00 FFFFFF82 73 01 03 4E 49 4C 15 02 FFFFFF82 74
   10 03 0A 15 28 08 08 FFFFFF82 76 0B FFFFFFA0 FFFFFF80 04 FFFFFF82 74 01
   04 4E 49 4C 20 08 07 FFFFFF82 78 0B FFFFFF84 20 FFFFFF82 79 01 05
   65 6D 70 74 79 15 04 FFFFFF82 7A FFFFFF82 7C 10 04 0A 15 FFFFFF82
   7B 10 03 24 FFFFFF82 7C 04 09 26 FFFFFF82 77 FFFFFF84 FFFFFF80 FFFFFF80 FFFFFFC2 00
   27 28 03 FFFFFF82 77 7B 
  InnerClass: 
   public final #1123= #1122 of #117; //$anon$1=class scala/collection/immutable/Vector$$anon$1 of class scala/collection/immutable/Vector
   public final #1124= #511 of #117; //$anonfun$map0$1=class scala/collection/immutable/Vector$$anonfun$map0$1 of class scala/collection/immutable/Vector
   public #1129= #1126 of #1128; //WithFilter=class scala/collection/TraversableLike$WithFilter of class scala/collection/TraversableLike
   public #1134= #1131 of #1133; //GenericCanBuildFrom=class scala/collection/generic/TraversableFactory$GenericCanBuildFrom of class scala/collection/generic/TraversableFactory
  minor version: 0
  major version: 49
  Constant pool:
const #1 = Asciz	SourceFile;
const #2 = Asciz	Vector.scala;
const #3 = Asciz	empty;
const #4 = Asciz	()Lscala/collection/immutable/Vector;;
const #5 = Asciz	Code;
const #6 = Asciz	scala/collection/immutable/Vector$;
const #7 = class	#6;	//  scala/collection/immutable/Vector$
const #8 = Asciz	MODULE$;
const #9 = Asciz	Lscala/collection/immutable/Vector$;;
const #10 = NameAndType	#8:#9;//  MODULE$:Lscala/collection/immutable/Vector$;
const #11 = Field	#7.#10;	//  scala/collection/immutable/Vector$.MODULE$:Lscala/collection/immutable/Vector$;
const #12 = NameAndType	#3:#4;//  empty:()Lscala/collection/immutable/Vector;
const #13 = Method	#7.#12;	//  scala/collection/immutable/Vector$.empty:()Lscala/collection/immutable/Vector;
const #14 = Asciz	<A:Ljava/lang/Object;>()Lscala/collection/immutable/Vector<TA;>;;
const #15 = Asciz	Signature;
const #16 = Asciz	NIL;
const #17 = NameAndType	#16:#4;//  NIL:()Lscala/collection/immutable/Vector;
const #18 = Method	#7.#17;	//  scala/collection/immutable/Vector$.NIL:()Lscala/collection/immutable/Vector;
const #19 = Asciz	()Lscala/collection/immutable/Vector<Lscala/runtime/Nothing$;>;;
const #20 = Asciz	canBuildFrom;
const #21 = Asciz	()Lscala/collection/generic/CanBuildFrom;;
const #22 = NameAndType	#20:#21;//  canBuildFrom:()Lscala/collection/generic/CanBuildFrom;
const #23 = Method	#7.#22;	//  scala/collection/immutable/Vector$.canBuildFrom:()Lscala/collection/generic/CanBuildFrom;
const #24 = Asciz	<A:Ljava/lang/Object;>()Lscala/collection/generic/CanBuildFrom<Lscala/collection/immutable/Vector<*>;TA;Lscala/collection/immutable/Vector<TA;>;>;;
const #25 = Asciz	BF;
const #26 = Asciz	()Lscala/collection/generic/TraversableFactory$GenericCanBuildFrom;;
const #27 = NameAndType	#25:#26;//  BF:()Lscala/collection/generic/TraversableFactory$GenericCanBuildFrom;
const #28 = Method	#7.#27;	//  scala/collection/immutable/Vector$.BF:()Lscala/collection/generic/TraversableFactory$GenericCanBuildFrom;
const #29 = Asciz	()Lscala/collection/generic/TraversableFactory<Lscala/collection/immutable/Vector;>.GenericCanBuildFrom<Lscala/runtime/Nothing$;>;;
const #30 = Asciz	unapplySeq;
const #31 = Asciz	(Lscala/collection/Seq;)Lscala/Some;;
const #32 = NameAndType	#30:#31;//  unapplySeq:(Lscala/collection/Seq;)Lscala/Some;
const #33 = Method	#7.#32;	//  scala/collection/immutable/Vector$.unapplySeq:(Lscala/collection/Seq;)Lscala/Some;
const #34 = Asciz	<A:Ljava/lang/Object;>(Lscala/collection/immutable/Vector<TA;>;)Lscala/Some<Lscala/collection/immutable/Vector<TA;>;>;;
const #35 = Asciz	iterate;
const #36 = Asciz	(Ljava/lang/Object;ILscala/Function1;)Lscala/collection/Traversable;;
const #37 = NameAndType	#35:#36;//  iterate:(Ljava/lang/Object;ILscala/Function1;)Lscala/collection/Traversable;
const #38 = Method	#7.#37;	//  scala/collection/immutable/Vector$.iterate:(Ljava/lang/Object;ILscala/Function1;)Lscala/collection/Traversable;
const #39 = Asciz	<A:Ljava/lang/Object;>(TA;ILscala/Function1<TA;TA;>;)Lscala/collection/immutable/Vector<TA;>;;
const #40 = Asciz	range;
const #41 = Asciz	(III)Lscala/collection/Traversable;;
const #42 = NameAndType	#40:#41;//  range:(III)Lscala/collection/Traversable;
const #43 = Method	#7.#42;	//  scala/collection/immutable/Vector$.range:(III)Lscala/collection/Traversable;
const #44 = Asciz	(III)Lscala/collection/immutable/Vector<Ljava/lang/Integer;>;;
const #45 = Asciz	(II)Lscala/collection/Traversable;;
const #46 = NameAndType	#40:#45;//  range:(II)Lscala/collection/Traversable;
const #47 = Method	#7.#46;	//  scala/collection/immutable/Vector$.range:(II)Lscala/collection/Traversable;
const #48 = Asciz	(II)Lscala/collection/immutable/Vector<Ljava/lang/Integer;>;;
const #49 = Asciz	tabulate;
const #50 = Asciz	(IIIIILscala/Function5;)Lscala/collection/Traversable;;
const #51 = NameAndType	#49:#50;//  tabulate:(IIIIILscala/Function5;)Lscala/collection/Traversable;
const #52 = Method	#7.#51;	//  scala/collection/immutable/Vector$.tabulate:(IIIIILscala/Function5;)Lscala/collection/Traversable;
const #53 = Asciz	<A:Ljava/lang/Object;>(IIIIILscala/Function5<Ljava/lang/Integer;Ljava/lang/Integer;Ljava/lang/Integer;Ljava/lang/Integer;Ljava/lang/Integer;TA;>;)Lscala/collection/immutable/Vector<Lscala/collection/immutable/Vector<Lscala/collection/immutable/Vector<Lscala/collection/immutable/Vector<Lscala/collection/immutable/Vector<TA;>;>;>;>;>;;
const #54 = Asciz	(IIIILscala/Function4;)Lscala/collection/Traversable;;
const #55 = NameAndType	#49:#54;//  tabulate:(IIIILscala/Function4;)Lscala/collection/Traversable;
const #56 = Method	#7.#55;	//  scala/collection/immutable/Vector$.tabulate:(IIIILscala/Function4;)Lscala/collection/Traversable;
const #57 = Asciz	<A:Ljava/lang/Object;>(IIIILscala/Function4<Ljava/lang/Integer;Ljava/lang/Integer;Ljava/lang/Integer;Ljava/lang/Integer;TA;>;)Lscala/collection/immutable/Vector<Lscala/collection/immutable/Vector<Lscala/collection/immutable/Vector<Lscala/collection/immutable/Vector<TA;>;>;>;>;;
const #58 = Asciz	(IIILscala/Function3;)Lscala/collection/Traversable;;
const #59 = NameAndType	#49:#58;//  tabulate:(IIILscala/Function3;)Lscala/collection/Traversable;
const #60 = Method	#7.#59;	//  scala/collection/immutable/Vector$.tabulate:(IIILscala/Function3;)Lscala/collection/Traversable;
const #61 = Asciz	<A:Ljava/lang/Object;>(IIILscala/Function3<Ljava/lang/Integer;Ljava/lang/Integer;Ljava/lang/Integer;TA;>;)Lscala/collection/immutable/Vector<Lscala/collection/immutable/Vector<Lscala/collection/immutable/Vector<TA;>;>;>;;
const #62 = Asciz	(IILscala/Function2;)Lscala/collection/Traversable;;
const #63 = NameAndType	#49:#62;//  tabulate:(IILscala/Function2;)Lscala/collection/Traversable;
const #64 = Method	#7.#63;	//  scala/collection/immutable/Vector$.tabulate:(IILscala/Function2;)Lscala/collection/Traversable;
const #65 = Asciz	<A:Ljava/lang/Object;>(IILscala/Function2<Ljava/lang/Integer;Ljava/lang/Integer;TA;>;)Lscala/collection/immutable/Vector<Lscala/collection/immutable/Vector<TA;>;>;;
const #66 = Asciz	(ILscala/Function1;)Lscala/collection/Traversable;;
const #67 = NameAndType	#49:#66;//  tabulate:(ILscala/Function1;)Lscala/collection/Traversable;
const #68 = Method	#7.#67;	//  scala/collection/immutable/Vector$.tabulate:(ILscala/Function1;)Lscala/collection/Traversable;
const #69 = Asciz	<A:Ljava/lang/Object;>(ILscala/Function1<Ljava/lang/Integer;TA;>;)Lscala/collection/immutable/Vector<TA;>;;
const #70 = Asciz	fill;
const #71 = Asciz	(IIIIILscala/Function0;)Lscala/collection/Traversable;;
const #72 = NameAndType	#70:#71;//  fill:(IIIIILscala/Function0;)Lscala/collection/Traversable;
const #73 = Method	#7.#72;	//  scala/collection/immutable/Vector$.fill:(IIIIILscala/Function0;)Lscala/collection/Traversable;
const #74 = Asciz	<A:Ljava/lang/Object;>(IIIIILscala/Function0<TA;>;)Lscala/collection/immutable/Vector<Lscala/collection/immutable/Vector<Lscala/collection/immutable/Vector<Lscala/collection/immutable/Vector<Lscala/collection/immutable/Vector<TA;>;>;>;>;>;;
const #75 = Asciz	(IIIILscala/Function0;)Lscala/collection/Traversable;;
const #76 = NameAndType	#70:#75;//  fill:(IIIILscala/Function0;)Lscala/collection/Traversable;
const #77 = Method	#7.#76;	//  scala/collection/immutable/Vector$.fill:(IIIILscala/Function0;)Lscala/collection/Traversable;
const #78 = Asciz	<A:Ljava/lang/Object;>(IIIILscala/Function0<TA;>;)Lscala/collection/immutable/Vector<Lscala/collection/immutable/Vector<Lscala/collection/immutable/Vector<Lscala/collection/immutable/Vector<TA;>;>;>;>;;
const #79 = Asciz	(IIILscala/Function0;)Lscala/collection/Traversable;;
const #80 = NameAndType	#70:#79;//  fill:(IIILscala/Function0;)Lscala/collection/Traversable;
const #81 = Method	#7.#80;	//  scala/collection/immutable/Vector$.fill:(IIILscala/Function0;)Lscala/collection/Traversable;
const #82 = Asciz	<A:Ljava/lang/Object;>(IIILscala/Function0<TA;>;)Lscala/collection/immutable/Vector<Lscala/collection/immutable/Vector<Lscala/collection/immutable/Vector<TA;>;>;>;;
const #83 = Asciz	(IILscala/Function0;)Lscala/collection/Traversable;;
const #84 = NameAndType	#70:#83;//  fill:(IILscala/Function0;)Lscala/collection/Traversable;
const #85 = Method	#7.#84;	//  scala/collection/immutable/Vector$.fill:(IILscala/Function0;)Lscala/collection/Traversable;
const #86 = Asciz	<A:Ljava/lang/Object;>(IILscala/Function0<TA;>;)Lscala/collection/immutable/Vector<Lscala/collection/immutable/Vector<TA;>;>;;
const #87 = Asciz	(ILscala/Function0;)Lscala/collection/Traversable;;
const #88 = NameAndType	#70:#87;//  fill:(ILscala/Function0;)Lscala/collection/Traversable;
const #89 = Method	#7.#88;	//  scala/collection/immutable/Vector$.fill:(ILscala/Function0;)Lscala/collection/Traversable;
const #90 = Asciz	<A:Ljava/lang/Object;>(ILscala/Function0<TA;>;)Lscala/collection/immutable/Vector<TA;>;;
const #91 = Asciz	concat;
const #92 = Asciz	(Lscala/collection/Seq;)Lscala/collection/Traversable;;
const #93 = NameAndType	#91:#92;//  concat:(Lscala/collection/Seq;)Lscala/collection/Traversable;
const #94 = Method	#7.#93;	//  scala/collection/immutable/Vector$.concat:(Lscala/collection/Seq;)Lscala/collection/Traversable;
const #95 = Asciz	<A:Ljava/lang/Object;>(Lscala/collection/Seq<Lscala/collection/Traversable<TA;>;>;)Lscala/collection/immutable/Vector<TA;>;;
const #96 = Asciz	()Lscala/collection/Traversable;;
const #97 = NameAndType	#3:#96;//  empty:()Lscala/collection/Traversable;
const #98 = Method	#7.#97;	//  scala/collection/immutable/Vector$.empty:()Lscala/collection/Traversable;
const #99 = Asciz	display5;
const #100 = Asciz	[Ljava/lang/Object;;
const #101 = Asciz	display4;
const #102 = Asciz	display3;
const #103 = Asciz	display2;
const #104 = Asciz	display1;
const #105 = Asciz	display0;
const #106 = Asciz	depth;
const #107 = Asciz	I;
const #108 = Asciz	dirty;
const #109 = Asciz	Z;
const #110 = Asciz	focus;
const #111 = Asciz	endIndex;
const #112 = Asciz	startIndex;
const #113 = Asciz	<init>;
const #114 = Asciz	(III)V;
const #115 = Asciz	LineNumberTable;
const #116 = Asciz	scala/collection/immutable/Vector;
const #117 = class	#116;	//  scala/collection/immutable/Vector
const #118 = NameAndType	#112:#107;//  startIndex:I
const #119 = Field	#117.#118;	//  scala/collection/immutable/Vector.startIndex:I
const #120 = NameAndType	#111:#107;//  endIndex:I
const #121 = Field	#117.#120;	//  scala/collection/immutable/Vector.endIndex:I
const #122 = NameAndType	#110:#107;//  focus:I
const #123 = Field	#117.#122;	//  scala/collection/immutable/Vector.focus:I
const #124 = Asciz	java/lang/Object;
const #125 = class	#124;	//  java/lang/Object
const #126 = Asciz	()V;
const #127 = NameAndType	#113:#126;//  "<init>":()V
const #128 = Method	#125.#127;	//  java/lang/Object."<init>":()V
const #129 = Asciz	scala/collection/TraversableLike$class;
const #130 = class	#129;	//  scala/collection/TraversableLike$class
const #131 = Asciz	$init$;
const #132 = Asciz	(Lscala/collection/TraversableLike;)V;
const #133 = NameAndType	#131:#132;//  $init$:(Lscala/collection/TraversableLike;)V
const #134 = Method	#130.#133;	//  scala/collection/TraversableLike$class.$init$:(Lscala/collection/TraversableLike;)V
const #135 = Asciz	scala/collection/generic/GenericTraversableTemplate$class;
const #136 = class	#135;	//  scala/collection/generic/GenericTraversableTemplate$class
const #137 = Asciz	(Lscala/collection/generic/GenericTraversableTemplate;)V;
const #138 = NameAndType	#131:#137;//  $init$:(Lscala/collection/generic/GenericTraversableTemplate;)V
const #139 = Method	#136.#138;	//  scala/collection/generic/GenericTraversableTemplate$class.$init$:(Lscala/collection/generic/GenericTraversableTemplate;)V
const #140 = Asciz	scala/collection/Traversable$class;
const #141 = class	#140;	//  scala/collection/Traversable$class
const #142 = Asciz	(Lscala/collection/Traversable;)V;
const #143 = NameAndType	#131:#142;//  $init$:(Lscala/collection/Traversable;)V
const #144 = Method	#141.#143;	//  scala/collection/Traversable$class.$init$:(Lscala/collection/Traversable;)V
const #145 = Asciz	scala/collection/immutable/Traversable$class;
const #146 = class	#145;	//  scala/collection/immutable/Traversable$class
const #147 = Asciz	(Lscala/collection/immutable/Traversable;)V;
const #148 = NameAndType	#131:#147;//  $init$:(Lscala/collection/immutable/Traversable;)V
const #149 = Method	#146.#148;	//  scala/collection/immutable/Traversable$class.$init$:(Lscala/collection/immutable/Traversable;)V
const #150 = Asciz	scala/collection/IterableLike$class;
const #151 = class	#150;	//  scala/collection/IterableLike$class
const #152 = Asciz	(Lscala/collection/IterableLike;)V;
const #153 = NameAndType	#131:#152;//  $init$:(Lscala/collection/IterableLike;)V
const #154 = Method	#151.#153;	//  scala/collection/IterableLike$class.$init$:(Lscala/collection/IterableLike;)V
const #155 = Asciz	scala/collection/Iterable$class;
const #156 = class	#155;	//  scala/collection/Iterable$class
const #157 = Asciz	(Lscala/collection/Iterable;)V;
const #158 = NameAndType	#131:#157;//  $init$:(Lscala/collection/Iterable;)V
const #159 = Method	#156.#158;	//  scala/collection/Iterable$class.$init$:(Lscala/collection/Iterable;)V
const #160 = Asciz	scala/collection/immutable/Iterable$class;
const #161 = class	#160;	//  scala/collection/immutable/Iterable$class
const #162 = Asciz	(Lscala/collection/immutable/Iterable;)V;
const #163 = NameAndType	#131:#162;//  $init$:(Lscala/collection/immutable/Iterable;)V
const #164 = Method	#161.#163;	//  scala/collection/immutable/Iterable$class.$init$:(Lscala/collection/immutable/Iterable;)V
const #165 = Asciz	scala/Function1$class;
const #166 = class	#165;	//  scala/Function1$class
const #167 = Asciz	(Lscala/Function1;)V;
const #168 = NameAndType	#131:#167;//  $init$:(Lscala/Function1;)V
const #169 = Method	#166.#168;	//  scala/Function1$class.$init$:(Lscala/Function1;)V
const #170 = Asciz	scala/PartialFunction$class;
const #171 = class	#170;	//  scala/PartialFunction$class
const #172 = Asciz	(Lscala/PartialFunction;)V;
const #173 = NameAndType	#131:#172;//  $init$:(Lscala/PartialFunction;)V
const #174 = Method	#171.#173;	//  scala/PartialFunction$class.$init$:(Lscala/PartialFunction;)V
const #175 = Asciz	scala/collection/SeqLike$class;
const #176 = class	#175;	//  scala/collection/SeqLike$class
const #177 = Asciz	(Lscala/collection/SeqLike;)V;
const #178 = NameAndType	#131:#177;//  $init$:(Lscala/collection/SeqLike;)V
const #179 = Method	#176.#178;	//  scala/collection/SeqLike$class.$init$:(Lscala/collection/SeqLike;)V
const #180 = Asciz	scala/collection/Seq$class;
const #181 = class	#180;	//  scala/collection/Seq$class
const #182 = Asciz	(Lscala/collection/Seq;)V;
const #183 = NameAndType	#131:#182;//  $init$:(Lscala/collection/Seq;)V
const #184 = Method	#181.#183;	//  scala/collection/Seq$class.$init$:(Lscala/collection/Seq;)V
const #185 = Asciz	scala/collection/immutable/Seq$class;
const #186 = class	#185;	//  scala/collection/immutable/Seq$class
const #187 = Asciz	(Lscala/collection/immutable/Seq;)V;
const #188 = NameAndType	#131:#187;//  $init$:(Lscala/collection/immutable/Seq;)V
const #189 = Method	#186.#188;	//  scala/collection/immutable/Seq$class.$init$:(Lscala/collection/immutable/Seq;)V
const #190 = Asciz	scala/collection/immutable/VectorPointer$class;
const #191 = class	#190;	//  scala/collection/immutable/VectorPointer$class
const #192 = Asciz	(Lscala/collection/immutable/VectorPointer;)V;
const #193 = NameAndType	#131:#192;//  $init$:(Lscala/collection/immutable/VectorPointer;)V
const #194 = Method	#191.#193;	//  scala/collection/immutable/VectorPointer$class.$init$:(Lscala/collection/immutable/VectorPointer;)V
const #195 = NameAndType	#108:#109;//  dirty:Z
const #196 = Field	#117.#195;	//  scala/collection/immutable/Vector.dirty:Z
const #197 = Asciz	this;
const #198 = Asciz	Lscala/collection/immutable/Vector;;
const #199 = Asciz	LocalVariableTable;
const #200 = Asciz	iterator;
const #201 = Asciz	()Lscala/collection/Iterator;;
const #202 = Asciz	()Lscala/collection/immutable/VectorIterator;;
const #203 = NameAndType	#200:#202;//  iterator:()Lscala/collection/immutable/VectorIterator;
const #204 = Method	#117.#203;	//  scala/collection/immutable/Vector.iterator:()Lscala/collection/immutable/VectorIterator;
const #205 = Asciz	apply;
const #206 = Asciz	(Ljava/lang/Object;)Ljava/lang/Object;;
const #207 = Asciz	scala/runtime/BoxesRunTime;
const #208 = class	#207;	//  scala/runtime/BoxesRunTime
const #209 = Asciz	unboxToInt;
const #210 = Asciz	(Ljava/lang/Object;)I;
const #211 = NameAndType	#209:#210;//  unboxToInt:(Ljava/lang/Object;)I
const #212 = Method	#208.#211;	//  scala/runtime/BoxesRunTime.unboxToInt:(Ljava/lang/Object;)I
const #213 = Asciz	(I)Ljava/lang/Object;;
const #214 = NameAndType	#205:#213;//  apply:(I)Ljava/lang/Object;
const #215 = Method	#117.#214;	//  scala/collection/immutable/Vector.apply:(I)Ljava/lang/Object;
const #216 = Asciz	v1;
const #217 = Asciz	Ljava/lang/Object;;
const #218 = Asciz	take;
const #219 = Asciz	(I)Lscala/collection/immutable/Vector;;
const #220 = NameAndType	#218:#219;//  take:(I)Lscala/collection/immutable/Vector;
const #221 = Method	#117.#220;	//  scala/collection/immutable/Vector.take:(I)Lscala/collection/immutable/Vector;
const #222 = Asciz	n;
const #223 = Asciz	drop;
const #224 = NameAndType	#223:#219;//  drop:(I)Lscala/collection/immutable/Vector;
const #225 = Method	#117.#224;	//  scala/collection/immutable/Vector.drop:(I)Lscala/collection/immutable/Vector;
const #226 = Asciz	takeRight;
const #227 = NameAndType	#226:#219;//  takeRight:(I)Lscala/collection/immutable/Vector;
const #228 = Method	#117.#227;	//  scala/collection/immutable/Vector.takeRight:(I)Lscala/collection/immutable/Vector;
const #229 = Asciz	dropRight;
const #230 = NameAndType	#229:#219;//  dropRight:(I)Lscala/collection/immutable/Vector;
const #231 = Method	#117.#230;	//  scala/collection/immutable/Vector.dropRight:(I)Lscala/collection/immutable/Vector;
const #232 = Asciz	thisCollection;
const #233 = Asciz	()Lscala/collection/Iterable;;
const #234 = Asciz	scala/collection/SeqLike;
const #235 = class	#234;	//  scala/collection/SeqLike
const #236 = Asciz	()Lscala/collection/Seq;;
const #237 = NameAndType	#232:#236;//  thisCollection:()Lscala/collection/Seq;
const #238 = InterfaceMethod	#235.#237;	//  scala/collection/SeqLike.thisCollection:()Lscala/collection/Seq;
const #239 = Asciz	toCollection;
const #240 = Asciz	(Ljava/lang/Object;)Lscala/collection/Iterable;;
const #241 = Asciz	(Ljava/lang/Object;)Lscala/collection/Seq;;
const #242 = NameAndType	#239:#241;//  toCollection:(Ljava/lang/Object;)Lscala/collection/Seq;
const #243 = InterfaceMethod	#235.#242;	//  scala/collection/SeqLike.toCollection:(Ljava/lang/Object;)Lscala/collection/Seq;
const #244 = Asciz	repr;
const #245 = Asciz	(Ljava/lang/Object;)Lscala/collection/Traversable;;
const #246 = Asciz	isDefinedAt;
const #247 = Asciz	(Ljava/lang/Object;)Z;
const #248 = Asciz	(I)Z;
const #249 = NameAndType	#246:#248;//  isDefinedAt:(I)Z
const #250 = InterfaceMethod	#235.#249;	//  scala/collection/SeqLike.isDefinedAt:(I)Z
const #251 = Asciz	x;
const #252 = Asciz	view;
const #253 = Asciz	(II)Lscala/collection/IterableView;;
const #254 = Asciz	(II)Lscala/collection/SeqView;;
const #255 = NameAndType	#252:#254;//  view:(II)Lscala/collection/SeqView;
const #256 = InterfaceMethod	#235.#255;	//  scala/collection/SeqLike.view:(II)Lscala/collection/SeqView;
const #257 = Asciz	from;
const #258 = Asciz	until;
const #259 = Asciz	(II)Lscala/collection/TraversableView;;
const #260 = Asciz	andThen;
const #261 = Asciz	(Lscala/Function1;)Lscala/Function1;;
const #262 = Asciz	scala/PartialFunction;
const #263 = class	#262;	//  scala/PartialFunction
const #264 = Asciz	(Lscala/Function1;)Lscala/PartialFunction;;
const #265 = NameAndType	#260:#264;//  andThen:(Lscala/Function1;)Lscala/PartialFunction;
const #266 = InterfaceMethod	#263.#265;	//  scala/PartialFunction.andThen:(Lscala/Function1;)Lscala/PartialFunction;
const #267 = Asciz	g;
const #268 = Asciz	Lscala/Function1;;
const #269 = Asciz	dropBack0;
const #270 = int	31;
const #271 = Asciz	requiredDepth;
const #272 = Asciz	(I)I;
const #273 = NameAndType	#271:#272;//  requiredDepth:(I)I
const #274 = Method	#117.#273;	//  scala/collection/immutable/Vector.requiredDepth:(I)I
const #275 = NameAndType	#113:#114;//  "<init>":(III)V
const #276 = Method	#117.#275;	//  scala/collection/immutable/Vector."<init>":(III)V
const #277 = Asciz	scala/collection/immutable/VectorPointer;
const #278 = class	#277;	//  scala/collection/immutable/VectorPointer
const #279 = Asciz	initFrom;
const #280 = NameAndType	#279:#192;//  initFrom:(Lscala/collection/immutable/VectorPointer;)V
const #281 = InterfaceMethod	#278.#280;	//  scala/collection/immutable/VectorPointer.initFrom:(Lscala/collection/immutable/VectorPointer;)V
const #282 = Asciz	()Z;
const #283 = NameAndType	#108:#282;//  dirty:()Z
const #284 = Method	#117.#283;	//  scala/collection/immutable/Vector.dirty:()Z
const #285 = Asciz	dirty_$eq;
const #286 = Asciz	(Z)V;
const #287 = NameAndType	#285:#286;//  dirty_$eq:(Z)V
const #288 = Method	#117.#287;	//  scala/collection/immutable/Vector.dirty_$eq:(Z)V
const #289 = Asciz	gotoPosWritable;
const #290 = NameAndType	#289:#114;//  gotoPosWritable:(III)V
const #291 = Method	#117.#290;	//  scala/collection/immutable/Vector.gotoPosWritable:(III)V
const #292 = Asciz	preClean;
const #293 = Asciz	(I)V;
const #294 = NameAndType	#292:#293;//  preClean:(I)V
const #295 = Method	#117.#294;	//  scala/collection/immutable/Vector.preClean:(I)V
const #296 = Asciz	cleanRightEdge;
const #297 = NameAndType	#296:#293;//  cleanRightEdge:(I)V
const #298 = Method	#117.#297;	//  scala/collection/immutable/Vector.cleanRightEdge:(I)V
const #299 = Asciz	cutIndex;
const #300 = Asciz	xor;
const #301 = Asciz	blockIndex;
const #302 = Asciz	d;
const #303 = Asciz	shift;
const #304 = Asciz	s;
const #305 = Asciz	(I)Lscala/collection/immutable/Vector<TA;>;;
const #306 = Asciz	dropFront0;
const #307 = Asciz	cleanLeftEdge;
const #308 = NameAndType	#307:#293;//  cleanLeftEdge:(I)V
const #309 = Method	#117.#308;	//  scala/collection/immutable/Vector.cleanLeftEdge:(I)V
const #310 = int	32;
const #311 = int	1024;
const #312 = int	32768;
const #313 = int	1048576;
const #314 = int	33554432;
const #315 = int	1073741824;
const #316 = int	6;
const #317 = Asciz	java/lang/IllegalArgumentException;
const #318 = class	#317;	//  java/lang/IllegalArgumentException
const #319 = Method	#318.#127;	//  java/lang/IllegalArgumentException."<init>":()V
const #320 = NameAndType	#105:#100;//  display0:[Ljava/lang/Object;
const #321 = Field	#117.#320;	//  scala/collection/immutable/Vector.display0:[Ljava/lang/Object;
const #322 = Asciz	zeroRight;
const #323 = Asciz	([Ljava/lang/Object;I)V;
const #324 = NameAndType	#322:#323;//  zeroRight:([Ljava/lang/Object;I)V
const #325 = Method	#117.#324;	//  scala/collection/immutable/Vector.zeroRight:([Ljava/lang/Object;I)V
const #326 = NameAndType	#104:#100;//  display1:[Ljava/lang/Object;
const #327 = Field	#117.#326;	//  scala/collection/immutable/Vector.display1:[Ljava/lang/Object;
const #328 = Asciz	java/lang/System;
const #329 = class	#328;	//  java/lang/System
const #330 = Asciz	arraycopy;
const #331 = Asciz	(Ljava/lang/Object;ILjava/lang/Object;II)V;
const #332 = NameAndType	#330:#331;//  arraycopy:(Ljava/lang/Object;ILjava/lang/Object;II)V
const #333 = Method	#329.#332;	//  java/lang/System.arraycopy:(Ljava/lang/Object;ILjava/lang/Object;II)V
const #334 = NameAndType	#103:#100;//  display2:[Ljava/lang/Object;
const #335 = Field	#117.#334;	//  scala/collection/immutable/Vector.display2:[Ljava/lang/Object;
const #336 = int	10;
const #337 = Asciz	()[Ljava/lang/Object;;
const #338 = NameAndType	#105:#337;//  display0:()[Ljava/lang/Object;
const #339 = InterfaceMethod	#278.#338;	//  scala/collection/immutable/VectorPointer.display0:()[Ljava/lang/Object;
const #340 = NameAndType	#104:#337;//  display1:()[Ljava/lang/Object;
const #341 = InterfaceMethod	#278.#340;	//  scala/collection/immutable/VectorPointer.display1:()[Ljava/lang/Object;
const #342 = Asciz	copyLeft;
const #343 = Asciz	([Ljava/lang/Object;I)[Ljava/lang/Object;;
const #344 = NameAndType	#342:#343;//  copyLeft:([Ljava/lang/Object;I)[Ljava/lang/Object;
const #345 = Method	#117.#344;	//  scala/collection/immutable/Vector.copyLeft:([Ljava/lang/Object;I)[Ljava/lang/Object;
const #346 = Asciz	display1_$eq;
const #347 = Asciz	([Ljava/lang/Object;)V;
const #348 = NameAndType	#346:#347;//  display1_$eq:([Ljava/lang/Object;)V
const #349 = InterfaceMethod	#278.#348;	//  scala/collection/immutable/VectorPointer.display1_$eq:([Ljava/lang/Object;)V
const #350 = NameAndType	#103:#337;//  display2:()[Ljava/lang/Object;
const #351 = InterfaceMethod	#278.#350;	//  scala/collection/immutable/VectorPointer.display2:()[Ljava/lang/Object;
const #352 = Asciz	display2_$eq;
const #353 = NameAndType	#352:#347;//  display2_$eq:([Ljava/lang/Object;)V
const #354 = InterfaceMethod	#278.#353;	//  scala/collection/immutable/VectorPointer.display2_$eq:([Ljava/lang/Object;)V
const #355 = NameAndType	#102:#337;//  display3:()[Ljava/lang/Object;
const #356 = InterfaceMethod	#278.#355;	//  scala/collection/immutable/VectorPointer.display3:()[Ljava/lang/Object;
const #357 = int	15;
const #358 = Asciz	display3_$eq;
const #359 = NameAndType	#358:#347;//  display3_$eq:([Ljava/lang/Object;)V
const #360 = InterfaceMethod	#278.#359;	//  scala/collection/immutable/VectorPointer.display3_$eq:([Ljava/lang/Object;)V
const #361 = NameAndType	#101:#337;//  display4:()[Ljava/lang/Object;
const #362 = InterfaceMethod	#278.#361;	//  scala/collection/immutable/VectorPointer.display4:()[Ljava/lang/Object;
const #363 = int	20;
const #364 = Asciz	display4_$eq;
const #365 = NameAndType	#364:#347;//  display4_$eq:([Ljava/lang/Object;)V
const #366 = InterfaceMethod	#278.#365;	//  scala/collection/immutable/VectorPointer.display4_$eq:([Ljava/lang/Object;)V
const #367 = NameAndType	#99:#337;//  display5:()[Ljava/lang/Object;
const #368 = InterfaceMethod	#278.#367;	//  scala/collection/immutable/VectorPointer.display5:()[Ljava/lang/Object;
const #369 = int	25;
const #370 = Asciz	display5_$eq;
const #371 = NameAndType	#370:#347;//  display5_$eq:([Ljava/lang/Object;)V
const #372 = InterfaceMethod	#278.#371;	//  scala/collection/immutable/VectorPointer.display5_$eq:([Ljava/lang/Object;)V
const #373 = Asciz	a20;
const #374 = Asciz	a21;
const #375 = Asciz	a22;
const #376 = Asciz	zeroLeft;
const #377 = NameAndType	#376:#323;//  zeroLeft:([Ljava/lang/Object;I)V
const #378 = Method	#117.#377;	//  scala/collection/immutable/Vector.zeroLeft:([Ljava/lang/Object;I)V
const #379 = Asciz	copyRight;
const #380 = NameAndType	#379:#343;//  copyRight:([Ljava/lang/Object;I)[Ljava/lang/Object;
const #381 = Method	#117.#380;	//  scala/collection/immutable/Vector.copyRight:([Ljava/lang/Object;I)[Ljava/lang/Object;
const #382 = NameAndType	#106:#107;//  depth:I
const #383 = Field	#117.#382;	//  scala/collection/immutable/Vector.depth:I
const #384 = Asciz	scala/MatchError;
const #385 = class	#384;	//  scala/MatchError
const #386 = Asciz	boxToInteger;
const #387 = Asciz	(I)Ljava/lang/Integer;;
const #388 = NameAndType	#386:#387;//  boxToInteger:(I)Ljava/lang/Integer;
const #389 = Method	#208.#388;	//  scala/runtime/BoxesRunTime.boxToInteger:(I)Ljava/lang/Integer;
const #390 = Asciz	toString;
const #391 = Asciz	()Ljava/lang/String;;
const #392 = NameAndType	#390:#391;//  toString:()Ljava/lang/String;
const #393 = Method	#125.#392;	//  java/lang/Object.toString:()Ljava/lang/String;
const #394 = Asciz	(Ljava/lang/String;)V;
const #395 = NameAndType	#113:#394;//  "<init>":(Ljava/lang/String;)V
const #396 = Method	#385.#395;	//  scala/MatchError."<init>":(Ljava/lang/String;)V
const #397 = NameAndType	#99:#100;//  display5:[Ljava/lang/Object;
const #398 = Field	#117.#397;	//  scala/collection/immutable/Vector.display5:[Ljava/lang/Object;
const #399 = NameAndType	#101:#100;//  display4:[Ljava/lang/Object;
const #400 = Field	#117.#399;	//  scala/collection/immutable/Vector.display4:[Ljava/lang/Object;
const #401 = NameAndType	#102:#100;//  display3:[Ljava/lang/Object;
const #402 = Field	#117.#401;	//  scala/collection/immutable/Vector.display3:[Ljava/lang/Object;
const #403 = Asciz	temp2;
const #404 = Asciz	array;
const #405 = Asciz	left;
const #406 = Asciz	a2;
const #407 = Asciz	right;
const #408 = Asciz	index;
const #409 = Asciz	i;
const #410 = Asciz	shiftTopLevel;
const #411 = Asciz	(II)V;
const #412 = Asciz	copyRange;
const #413 = Asciz	([Ljava/lang/Object;II)[Ljava/lang/Object;;
const #414 = NameAndType	#412:#413;//  copyRange:([Ljava/lang/Object;II)[Ljava/lang/Object;
const #415 = InterfaceMethod	#278.#414;	//  scala/collection/immutable/VectorPointer.copyRange:([Ljava/lang/Object;II)[Ljava/lang/Object;
const #416 = Asciz	oldLeft;
const #417 = Asciz	newLeft;
const #418 = Asciz	temp1;
const #419 = Asciz	appendBack;
const #420 = Asciz	(Ljava/lang/Object;)Lscala/collection/immutable/Vector;;
const #421 = Asciz	debug;
const #422 = NameAndType	#421:#192;//  debug:(Lscala/collection/immutable/VectorPointer;)V
const #423 = Method	#191.#422;	//  scala/collection/immutable/VectorPointer$class.debug:(Lscala/collection/immutable/VectorPointer;)V
const #424 = NameAndType	#410:#411;//  shiftTopLevel:(II)V
const #425 = Method	#117.#424;	//  scala/collection/immutable/Vector.shiftTopLevel:(II)V
const #426 = Asciz	gotoFreshPosWritable;
const #427 = NameAndType	#426:#114;//  gotoFreshPosWritable:(III)V
const #428 = Method	#117.#427;	//  scala/collection/immutable/Vector.gotoFreshPosWritable:(III)V
const #429 = NameAndType	#421:#126;//  debug:()V
const #430 = InterfaceMethod	#278.#429;	//  scala/collection/immutable/VectorPointer.debug:()V
const #431 = Asciz	()I;
const #432 = NameAndType	#106:#431;//  depth:()I
const #433 = InterfaceMethod	#278.#432;	//  scala/collection/immutable/VectorPointer.depth:()I
const #434 = Asciz	depth_$eq;
const #435 = NameAndType	#434:#293;//  depth_$eq:(I)V
const #436 = InterfaceMethod	#278.#435;	//  scala/collection/immutable/VectorPointer.depth_$eq:(I)V
const #437 = Asciz	display0_$eq;
const #438 = NameAndType	#437:#347;//  display0_$eq:([Ljava/lang/Object;)V
const #439 = InterfaceMethod	#278.#438;	//  scala/collection/immutable/VectorPointer.display0_$eq:([Ljava/lang/Object;)V
const #440 = Asciz	value;
const #441 = Asciz	newFocus;
const #442 = Asciz	newBlockIndex;
const #443 = Asciz	shiftBlocks;
const #444 = Asciz	lo;
const #445 = Asciz	elems;
const #446 = Asciz	<B:Ljava/lang/Object;>(TB;)Lscala/collection/immutable/Vector<TB;>;;
const #447 = Asciz	appendFront;
const #448 = Asciz	freeSpace;
const #449 = Asciz	move;
const #450 = Asciz	gotoFreshPosWritable1;
const #451 = NameAndType	#450:#114;//  gotoFreshPosWritable1:(III)V
const #452 = InterfaceMethod	#278.#451;	//  scala/collection/immutable/VectorPointer.gotoFreshPosWritable1:(III)V
const #453 = Asciz	gotoFreshPosWritable0;
const #454 = NameAndType	#453:#114;//  gotoFreshPosWritable0:(III)V
const #455 = InterfaceMethod	#278.#454;	//  scala/collection/immutable/VectorPointer.gotoFreshPosWritable0:(III)V
const #456 = Asciz	oldIndex;
const #457 = Asciz	newIndex;
const #458 = Asciz	gotoPosWritable1;
const #459 = NameAndType	#458:#114;//  gotoPosWritable1:(III)V
const #460 = InterfaceMethod	#278.#459;	//  scala/collection/immutable/VectorPointer.gotoPosWritable1:(III)V
const #461 = Asciz	gotoPosWritable0;
const #462 = NameAndType	#461:#411;//  gotoPosWritable0:(II)V
const #463 = InterfaceMethod	#278.#462;	//  scala/collection/immutable/VectorPointer.gotoPosWritable0:(II)V
const #464 = Asciz	updateAt;
const #465 = Asciz	(ILjava/lang/Object;)Lscala/collection/immutable/Vector;;
const #466 = Asciz	checkRangeConvert;
const #467 = NameAndType	#466:#272;//  checkRangeConvert:(I)I
const #468 = Method	#117.#467;	//  scala/collection/immutable/Vector.checkRangeConvert:(I)I
const #469 = Asciz	elem;
const #470 = Asciz	idx;
const #471 = Asciz	<B:Ljava/lang/Object;>(ITB;)Lscala/collection/immutable/Vector<TB;>;;
const #472 = Method	#318.#395;	//  java/lang/IllegalArgumentException."<init>":(Ljava/lang/String;)V
const #473 = NameAndType	#269:#219;//  dropBack0:(I)Lscala/collection/immutable/Vector;
const #474 = Method	#117.#473;	//  scala/collection/immutable/Vector.dropBack0:(I)Lscala/collection/immutable/Vector;
const #475 = NameAndType	#306:#219;//  dropFront0:(I)Lscala/collection/immutable/Vector;
const #476 = Method	#117.#475;	//  scala/collection/immutable/Vector.dropFront0:(I)Lscala/collection/immutable/Vector;
const #477 = Asciz	$colon$plus;
const #478 = Asciz	(Ljava/lang/Object;Lscala/collection/generic/CanBuildFrom;)Ljava/lang/Object;;
const #479 = NameAndType	#419:#420;//  appendBack:(Ljava/lang/Object;)Lscala/collection/immutable/Vector;
const #480 = Method	#117.#479;	//  scala/collection/immutable/Vector.appendBack:(Ljava/lang/Object;)Lscala/collection/immutable/Vector;
const #481 = Asciz	bf;
const #482 = Asciz	Lscala/collection/generic/CanBuildFrom;;
const #483 = Asciz	<B:Ljava/lang/Object;That:Ljava/lang/Object;>(TB;Lscala/collection/generic/CanBuildFrom<Lscala/collection/immutable/Vector<TA;>;TB;TThat;>;)TThat;;
const #484 = Asciz	$plus$colon;
const #485 = NameAndType	#447:#420;//  appendFront:(Ljava/lang/Object;)Lscala/collection/immutable/Vector;
const #486 = Method	#117.#485;	//  scala/collection/immutable/Vector.appendFront:(Ljava/lang/Object;)Lscala/collection/immutable/Vector;
const #487 = Asciz	updated;
const #488 = Asciz	(ILjava/lang/Object;Lscala/collection/generic/CanBuildFrom;)Ljava/lang/Object;;
const #489 = NameAndType	#464:#465;//  updateAt:(ILjava/lang/Object;)Lscala/collection/immutable/Vector;
const #490 = Method	#117.#489;	//  scala/collection/immutable/Vector.updateAt:(ILjava/lang/Object;)Lscala/collection/immutable/Vector;
const #491 = Asciz	<B:Ljava/lang/Object;That:Ljava/lang/Object;>(ITB;Lscala/collection/generic/CanBuildFrom<Lscala/collection/immutable/Vector<TA;>;TB;TThat;>;)TThat;;
const #492 = Asciz	java/lang/IndexOutOfBoundsException;
const #493 = class	#492;	//  java/lang/IndexOutOfBoundsException
const #494 = Method	#493.#395;	//  java/lang/IndexOutOfBoundsException."<init>":(Ljava/lang/String;)V
const #495 = Asciz	getElem;
const #496 = Asciz	(II)Ljava/lang/Object;;
const #497 = NameAndType	#495:#496;//  getElem:(II)Ljava/lang/Object;
const #498 = InterfaceMethod	#278.#497;	//  scala/collection/immutable/VectorPointer.getElem:(II)Ljava/lang/Object;
const #499 = Asciz	(I)TA;;
const #500 = Asciz	map0;
const #501 = Asciz	(Lscala/Function1;Lscala/collection/generic/CanBuildFrom;)Ljava/lang/Object;;
const #502 = Asciz	(Lscala/collection/TraversableLike;)Ljava/lang/Object;;
const #503 = NameAndType	#244:#502;//  repr:(Lscala/collection/TraversableLike;)Ljava/lang/Object;
const #504 = Method	#130.#503;	//  scala/collection/TraversableLike$class.repr:(Lscala/collection/TraversableLike;)Ljava/lang/Object;
const #505 = Asciz	scala/collection/generic/CanBuildFrom;
const #506 = class	#505;	//  scala/collection/generic/CanBuildFrom
const #507 = Asciz	(Ljava/lang/Object;)Lscala/collection/mutable/Builder;;
const #508 = NameAndType	#205:#507;//  apply:(Ljava/lang/Object;)Lscala/collection/mutable/Builder;
const #509 = InterfaceMethod	#506.#508;	//  scala/collection/generic/CanBuildFrom.apply:(Ljava/lang/Object;)Lscala/collection/mutable/Builder;
const #510 = Asciz	scala/collection/immutable/Vector$$anonfun$map0$1;
const #511 = class	#510;	//  scala/collection/immutable/Vector$$anonfun$map0$1
const #512 = Asciz	(Lscala/collection/immutable/Vector;Lscala/Function1;Lscala/collection/mutable/Builder;)V;
const #513 = NameAndType	#113:#512;//  "<init>":(Lscala/collection/immutable/Vector;Lscala/Function1;Lscala/collection/mutable/Builder;)V
const #514 = Method	#511.#513;	//  scala/collection/immutable/Vector$$anonfun$map0$1."<init>":(Lscala/collection/immutable/Vector;Lscala/Function1;Lscala/collection/mutable/Builder;)V
const #515 = Asciz	scala/collection/immutable/VectorIterator;
const #516 = class	#515;	//  scala/collection/immutable/VectorIterator
const #517 = NameAndType	#113:#411;//  "<init>":(II)V
const #518 = Method	#516.#517;	//  scala/collection/immutable/VectorIterator."<init>":(II)V
const #519 = Asciz	stabilize;
const #520 = NameAndType	#519:#293;//  stabilize:(I)V
const #521 = InterfaceMethod	#278.#520;	//  scala/collection/immutable/VectorPointer.stabilize:(I)V
const #522 = Asciz	gotoPos;
const #523 = NameAndType	#522:#411;//  gotoPos:(II)V
const #524 = InterfaceMethod	#278.#523;	//  scala/collection/immutable/VectorPointer.gotoPos:(II)V
const #525 = Asciz	hasNext;
const #526 = NameAndType	#525:#282;//  hasNext:()Z
const #527 = Method	#516.#526;	//  scala/collection/immutable/VectorIterator.hasNext:()Z
const #528 = Asciz	next;
const #529 = Asciz	()Ljava/lang/Object;;
const #530 = NameAndType	#528:#529;//  next:()Ljava/lang/Object;
const #531 = Method	#516.#530;	//  scala/collection/immutable/VectorIterator.next:()Ljava/lang/Object;
const #532 = Asciz	scala/Function1;
const #533 = class	#532;	//  scala/Function1
const #534 = NameAndType	#205:#206;//  apply:(Ljava/lang/Object;)Ljava/lang/Object;
const #535 = InterfaceMethod	#533.#534;	//  scala/Function1.apply:(Ljava/lang/Object;)Ljava/lang/Object;
const #536 = Asciz	scala/collection/mutable/Builder;
const #537 = class	#536;	//  scala/collection/mutable/Builder
const #538 = Asciz	$plus$eq;
const #539 = NameAndType	#538:#507;//  $plus$eq:(Ljava/lang/Object;)Lscala/collection/mutable/Builder;
const #540 = InterfaceMethod	#537.#539;	//  scala/collection/mutable/Builder.$plus$eq:(Ljava/lang/Object;)Lscala/collection/mutable/Builder;
const #541 = Asciz	result;
const #542 = NameAndType	#541:#529;//  result:()Ljava/lang/Object;
const #543 = InterfaceMethod	#537.#542;	//  scala/collection/mutable/Builder.result:()Ljava/lang/Object;
const #544 = Asciz	f$1;
const #545 = Asciz	s0;
const #546 = Asciz	Lscala/collection/immutable/VectorIterator;;
const #547 = Asciz	b$1;
const #548 = Asciz	Lscala/collection/mutable/Builder;;
const #549 = Asciz	<B:Ljava/lang/Object;That:Ljava/lang/Object;>(Lscala/Function1<TA;TB;>;Lscala/collection/generic/CanBuildFrom<Lscala/collection/immutable/Vector<TA;>;TB;TThat;>;)TThat;;
const #550 = Asciz	foreach0;
const #551 = Asciz	f;
const #552 = Asciz	<U:Ljava/lang/Object;>(Lscala/Function1<TA;TU;>;)V;
const #553 = Asciz	()Lscala/collection/immutable/VectorIterator<TA;>;;
const #554 = Asciz	lengthCompare;
const #555 = Asciz	length;
const #556 = NameAndType	#555:#431;//  length:()I
const #557 = Method	#117.#556;	//  scala/collection/immutable/Vector.length:()I
const #558 = Asciz	len;
const #559 = Asciz	companion;
const #560 = Asciz	()Lscala/collection/generic/GenericCompanion;;
const #561 = Asciz	()Lscala/collection/generic/GenericCompanion<Lscala/collection/immutable/Vector;>;;
const #562 = Asciz	withFilter;
const #563 = Asciz	(Lscala/Function1;)Lscala/collection/TraversableLike$WithFilter;;
const #564 = Asciz	(Lscala/collection/TraversableLike;Lscala/Function1;)Lscala/collection/TraversableLike$WithFilter;;
const #565 = NameAndType	#562:#564;//  withFilter:(Lscala/collection/TraversableLike;Lscala/Function1;)Lscala/collection/TraversableLike$WithFilter;
const #566 = Method	#130.#565;	//  scala/collection/TraversableLike$class.withFilter:(Lscala/collection/TraversableLike;Lscala/Function1;)Lscala/collection/TraversableLike$WithFilter;
const #567 = Asciz	p;
const #568 = Asciz	stringPrefix;
const #569 = Asciz	(Lscala/collection/TraversableLike;)Ljava/lang/String;;
const #570 = NameAndType	#568:#569;//  stringPrefix:(Lscala/collection/TraversableLike;)Ljava/lang/String;
const #571 = Method	#130.#570;	//  scala/collection/TraversableLike$class.stringPrefix:(Lscala/collection/TraversableLike;)Ljava/lang/String;
const #572 = Asciz	addString;
const #573 = Asciz	(Lscala/collection/mutable/StringBuilder;)Lscala/collection/mutable/StringBuilder;;
const #574 = Asciz	(Lscala/collection/TraversableLike;Lscala/collection/mutable/StringBuilder;)Lscala/collection/mutable/StringBuilder;;
const #575 = NameAndType	#572:#574;//  addString:(Lscala/collection/TraversableLike;Lscala/collection/mutable/StringBuilder;)Lscala/collection/mutable/StringBuilder;
const #576 = Method	#130.#575;	//  scala/collection/TraversableLike$class.addString:(Lscala/collection/TraversableLike;Lscala/collection/mutable/StringBuilder;)Lscala/collection/mutable/StringBuilder;
const #577 = Asciz	b;
const #578 = Asciz	Lscala/collection/mutable/StringBuilder;;
const #579 = Asciz	(Lscala/collection/mutable/StringBuilder;Ljava/lang/String;)Lscala/collection/mutable/StringBuilder;;
const #580 = Asciz	(Lscala/collection/TraversableLike;Lscala/collection/mutable/StringBuilder;Ljava/lang/String;)Lscala/collection/mutable/StringBuilder;;
const #581 = NameAndType	#572:#580;//  addString:(Lscala/collection/TraversableLike;Lscala/collection/mutable/StringBuilder;Ljava/lang/String;)Lscala/collection/mutable/StringBuilder;
const #582 = Method	#130.#581;	//  scala/collection/TraversableLike$class.addString:(Lscala/collection/TraversableLike;Lscala/collection/mutable/StringBuilder;Ljava/lang/String;)Lscala/collection/mutable/StringBuilder;
const #583 = Asciz	sep;
const #584 = Asciz	Ljava/lang/String;;
const #585 = Asciz	(Lscala/collection/mutable/StringBuilder;Ljava/lang/String;Ljava/lang/String;Ljava/lang/String;)Lscala/collection/mutable/StringBuilder;;
const #586 = Asciz	(Lscala/collection/TraversableLike;Lscala/collection/mutable/StringBuilder;Ljava/lang/String;Ljava/lang/String;Ljava/lang/String;)Lscala/collection/mutable/StringBuilder;;
const #587 = NameAndType	#572:#586;//  addString:(Lscala/collection/TraversableLike;Lscala/collection/mutable/StringBuilder;Ljava/lang/String;Ljava/lang/String;Ljava/lang/String;)Lscala/collection/mutable/StringBuilder;
const #588 = Method	#130.#587;	//  scala/collection/TraversableLike$class.addString:(Lscala/collection/TraversableLike;Lscala/collection/mutable/StringBuilder;Ljava/lang/String;Ljava/lang/String;Ljava/lang/String;)Lscala/collection/mutable/StringBuilder;
const #589 = Asciz	start;
const #590 = Asciz	end;
const #591 = Asciz	mkString;
const #592 = NameAndType	#591:#569;//  mkString:(Lscala/collection/TraversableLike;)Ljava/lang/String;
const #593 = Method	#130.#592;	//  scala/collection/TraversableLike$class.mkString:(Lscala/collection/TraversableLike;)Ljava/lang/String;
const #594 = Asciz	(Ljava/lang/String;)Ljava/lang/String;;
const #595 = Asciz	(Lscala/collection/TraversableLike;Ljava/lang/String;)Ljava/lang/String;;
const #596 = NameAndType	#591:#595;//  mkString:(Lscala/collection/TraversableLike;Ljava/lang/String;)Ljava/lang/String;
const #597 = Method	#130.#596;	//  scala/collection/TraversableLike$class.mkString:(Lscala/collection/TraversableLike;Ljava/lang/String;)Ljava/lang/String;
const #598 = Asciz	(Ljava/lang/String;Ljava/lang/String;Ljava/lang/String;)Ljava/lang/String;;
const #599 = Asciz	(Lscala/collection/TraversableLike;Ljava/lang/String;Ljava/lang/String;Ljava/lang/String;)Ljava/lang/String;;
const #600 = NameAndType	#591:#599;//  mkString:(Lscala/collection/TraversableLike;Ljava/lang/String;Ljava/lang/String;Ljava/lang/String;)Ljava/lang/String;
const #601 = Method	#130.#600;	//  scala/collection/TraversableLike$class.mkString:(Lscala/collection/TraversableLike;Ljava/lang/String;Ljava/lang/String;Ljava/lang/String;)Ljava/lang/String;
const #602 = Asciz	toSet;
const #603 = Asciz	()Lscala/collection/immutable/Set;;
const #604 = Asciz	(Lscala/collection/TraversableLike;)Lscala/collection/immutable/Set;;
const #605 = NameAndType	#602:#604;//  toSet:(Lscala/collection/TraversableLike;)Lscala/collection/immutable/Set;
const #606 = Method	#130.#605;	//  scala/collection/TraversableLike$class.toSet:(Lscala/collection/TraversableLike;)Lscala/collection/immutable/Set;
const #607 = Asciz	toIndexedSeq;
const #608 = Asciz	()Lscala/collection/mutable/IndexedSeq;;
const #609 = Asciz	(Lscala/collection/TraversableLike;)Lscala/collection/mutable/IndexedSeq;;
const #610 = NameAndType	#607:#609;//  toIndexedSeq:(Lscala/collection/TraversableLike;)Lscala/collection/mutable/IndexedSeq;
const #611 = Method	#130.#610;	//  scala/collection/TraversableLike$class.toIndexedSeq:(Lscala/collection/TraversableLike;)Lscala/collection/mutable/IndexedSeq;
const #612 = Asciz	toList;
const #613 = Asciz	()Lscala/collection/immutable/List;;
const #614 = Asciz	(Lscala/collection/TraversableLike;)Lscala/collection/immutable/List;;
const #615 = NameAndType	#612:#614;//  toList:(Lscala/collection/TraversableLike;)Lscala/collection/immutable/List;
const #616 = Method	#130.#615;	//  scala/collection/TraversableLike$class.toList:(Lscala/collection/TraversableLike;)Lscala/collection/immutable/List;
const #617 = Asciz	toArray;
const #618 = Asciz	(Lscala/reflect/ClassManifest;)Ljava/lang/Object;;
const #619 = Asciz	(Lscala/collection/TraversableLike;Lscala/reflect/ClassManifest;)Ljava/lang/Object;;
const #620 = NameAndType	#617:#619;//  toArray:(Lscala/collection/TraversableLike;Lscala/reflect/ClassManifest;)Ljava/lang/Object;
const #621 = Method	#130.#620;	//  scala/collection/TraversableLike$class.toArray:(Lscala/collection/TraversableLike;Lscala/reflect/ClassManifest;)Ljava/lang/Object;
const #622 = Asciz	evidence$1;
const #623 = Asciz	Lscala/reflect/ClassManifest;;
const #624 = Asciz	copyToArray;
const #625 = Asciz	(Ljava/lang/Object;I)V;
const #626 = Asciz	(Lscala/collection/TraversableLike;Ljava/lang/Object;I)V;
const #627 = NameAndType	#624:#626;//  copyToArray:(Lscala/collection/TraversableLike;Ljava/lang/Object;I)V
const #628 = Method	#130.#627;	//  scala/collection/TraversableLike$class.copyToArray:(Lscala/collection/TraversableLike;Ljava/lang/Object;I)V
const #629 = Asciz	xs;
const #630 = Asciz	copyToBuffer;
const #631 = Asciz	(Lscala/collection/mutable/Buffer;)V;
const #632 = Asciz	(Lscala/collection/TraversableLike;Lscala/collection/mutable/Buffer;)V;
const #633 = NameAndType	#630:#632;//  copyToBuffer:(Lscala/collection/TraversableLike;Lscala/collection/mutable/Buffer;)V
const #634 = Method	#130.#633;	//  scala/collection/TraversableLike$class.copyToBuffer:(Lscala/collection/TraversableLike;Lscala/collection/mutable/Buffer;)V
const #635 = Asciz	dest;
const #636 = Asciz	Lscala/collection/mutable/Buffer;;
const #637 = Asciz	splitAt;
const #638 = Asciz	(I)Lscala/Tuple2;;
const #639 = Asciz	(Lscala/collection/TraversableLike;I)Lscala/Tuple2;;
const #640 = NameAndType	#637:#639;//  splitAt:(Lscala/collection/TraversableLike;I)Lscala/Tuple2;
const #641 = Method	#130.#640;	//  scala/collection/TraversableLike$class.splitAt:(Lscala/collection/TraversableLike;I)Lscala/Tuple2;
const #642 = Asciz	span;
const #643 = Asciz	(Lscala/Function1;)Lscala/Tuple2;;
const #644 = Asciz	(Lscala/collection/TraversableLike;Lscala/Function1;)Lscala/Tuple2;;
const #645 = NameAndType	#642:#644;//  span:(Lscala/collection/TraversableLike;Lscala/Function1;)Lscala/Tuple2;
const #646 = Method	#130.#645;	//  scala/collection/TraversableLike$class.span:(Lscala/collection/TraversableLike;Lscala/Function1;)Lscala/Tuple2;
const #647 = Asciz	dropWhile;
const #648 = Asciz	(Lscala/Function1;)Ljava/lang/Object;;
const #649 = Asciz	(Lscala/collection/TraversableLike;Lscala/Function1;)Ljava/lang/Object;;
const #650 = NameAndType	#647:#649;//  dropWhile:(Lscala/collection/TraversableLike;Lscala/Function1;)Ljava/lang/Object;
const #651 = Method	#130.#650;	//  scala/collection/TraversableLike$class.dropWhile:(Lscala/collection/TraversableLike;Lscala/Function1;)Ljava/lang/Object;
const #652 = Asciz	init;
const #653 = NameAndType	#652:#502;//  init:(Lscala/collection/TraversableLike;)Ljava/lang/Object;
const #654 = Method	#130.#653;	//  scala/collection/TraversableLike$class.init:(Lscala/collection/TraversableLike;)Ljava/lang/Object;
const #655 = Asciz	lastOption;
const #656 = Asciz	()Lscala/Option;;
const #657 = Asciz	(Lscala/collection/TraversableLike;)Lscala/Option;;
const #658 = NameAndType	#655:#657;//  lastOption:(Lscala/collection/TraversableLike;)Lscala/Option;
const #659 = Method	#130.#658;	//  scala/collection/TraversableLike$class.lastOption:(Lscala/collection/TraversableLike;)Lscala/Option;
const #660 = Asciz	last;
const #661 = NameAndType	#660:#502;//  last:(Lscala/collection/TraversableLike;)Ljava/lang/Object;
const #662 = Method	#130.#661;	//  scala/collection/TraversableLike$class.last:(Lscala/collection/TraversableLike;)Ljava/lang/Object;
const #663 = Asciz	tail;
const #664 = NameAndType	#663:#502;//  tail:(Lscala/collection/TraversableLike;)Ljava/lang/Object;
const #665 = Method	#130.#664;	//  scala/collection/TraversableLike$class.tail:(Lscala/collection/TraversableLike;)Ljava/lang/Object;
const #666 = Asciz	headOption;
const #667 = NameAndType	#666:#657;//  headOption:(Lscala/collection/TraversableLike;)Lscala/Option;
const #668 = Method	#130.#667;	//  scala/collection/TraversableLike$class.headOption:(Lscala/collection/TraversableLike;)Lscala/Option;
const #669 = Asciz	max;
const #670 = Asciz	(Lscala/math/Ordering;)Ljava/lang/Object;;
const #671 = Asciz	(Lscala/collection/TraversableLike;Lscala/math/Ordering;)Ljava/lang/Object;;
const #672 = NameAndType	#669:#671;//  max:(Lscala/collection/TraversableLike;Lscala/math/Ordering;)Ljava/lang/Object;
const #673 = Method	#130.#672;	//  scala/collection/TraversableLike$class.max:(Lscala/collection/TraversableLike;Lscala/math/Ordering;)Ljava/lang/Object;
const #674 = Asciz	cmp;
const #675 = Asciz	Lscala/math/Ordering;;
const #676 = Asciz	min;
const #677 = NameAndType	#676:#671;//  min:(Lscala/collection/TraversableLike;Lscala/math/Ordering;)Ljava/lang/Object;
const #678 = Method	#130.#677;	//  scala/collection/TraversableLike$class.min:(Lscala/collection/TraversableLike;Lscala/math/Ordering;)Ljava/lang/Object;
const #679 = Asciz	product;
const #680 = Asciz	(Lscala/math/Numeric;)Ljava/lang/Object;;
const #681 = Asciz	(Lscala/collection/TraversableLike;Lscala/math/Numeric;)Ljava/lang/Object;;
const #682 = NameAndType	#679:#681;//  product:(Lscala/collection/TraversableLike;Lscala/math/Numeric;)Ljava/lang/Object;
const #683 = Method	#130.#682;	//  scala/collection/TraversableLike$class.product:(Lscala/collection/TraversableLike;Lscala/math/Numeric;)Ljava/lang/Object;
const #684 = Asciz	num;
const #685 = Asciz	Lscala/math/Numeric;;
const #686 = Asciz	sum;
const #687 = NameAndType	#686:#681;//  sum:(Lscala/collection/TraversableLike;Lscala/math/Numeric;)Ljava/lang/Object;
const #688 = Method	#130.#687;	//  scala/collection/TraversableLike$class.sum:(Lscala/collection/TraversableLike;Lscala/math/Numeric;)Ljava/lang/Object;
const #689 = Asciz	reduceRightOption;
const #690 = Asciz	(Lscala/Function2;)Lscala/Option;;
const #691 = Asciz	(Lscala/collection/TraversableLike;Lscala/Function2;)Lscala/Option;;
const #692 = NameAndType	#689:#691;//  reduceRightOption:(Lscala/collection/TraversableLike;Lscala/Function2;)Lscala/Option;
const #693 = Method	#130.#692;	//  scala/collection/TraversableLike$class.reduceRightOption:(Lscala/collection/TraversableLike;Lscala/Function2;)Lscala/Option;
const #694 = Asciz	op;
const #695 = Asciz	Lscala/Function2;;
const #696 = Asciz	reduceLeftOption;
const #697 = NameAndType	#696:#691;//  reduceLeftOption:(Lscala/collection/TraversableLike;Lscala/Function2;)Lscala/Option;
const #698 = Method	#130.#697;	//  scala/collection/TraversableLike$class.reduceLeftOption:(Lscala/collection/TraversableLike;Lscala/Function2;)Lscala/Option;
const #699 = Asciz	reduceLeft;
const #700 = Asciz	(Lscala/Function2;)Ljava/lang/Object;;
const #701 = Asciz	(Lscala/collection/TraversableLike;Lscala/Function2;)Ljava/lang/Object;;
const #702 = NameAndType	#699:#701;//  reduceLeft:(Lscala/collection/TraversableLike;Lscala/Function2;)Ljava/lang/Object;
const #703 = Method	#130.#702;	//  scala/collection/TraversableLike$class.reduceLeft:(Lscala/collection/TraversableLike;Lscala/Function2;)Ljava/lang/Object;
const #704 = Asciz	$colon$bslash;
const #705 = Asciz	(Ljava/lang/Object;Lscala/Function2;)Ljava/lang/Object;;
const #706 = Asciz	(Lscala/collection/TraversableLike;Ljava/lang/Object;Lscala/Function2;)Ljava/lang/Object;;
const #707 = NameAndType	#704:#706;//  $colon$bslash:(Lscala/collection/TraversableLike;Ljava/lang/Object;Lscala/Function2;)Ljava/lang/Object;
const #708 = Method	#130.#707;	//  scala/collection/TraversableLike$class.$colon$bslash:(Lscala/collection/TraversableLike;Ljava/lang/Object;Lscala/Function2;)Ljava/lang/Object;
const #709 = Asciz	z;
const #710 = Asciz	$div$colon;
const #711 = NameAndType	#710:#706;//  $div$colon:(Lscala/collection/TraversableLike;Ljava/lang/Object;Lscala/Function2;)Ljava/lang/Object;
const #712 = Method	#130.#711;	//  scala/collection/TraversableLike$class.$div$colon:(Lscala/collection/TraversableLike;Ljava/lang/Object;Lscala/Function2;)Ljava/lang/Object;
const #713 = Asciz	foldLeft;
const #714 = NameAndType	#713:#706;//  foldLeft:(Lscala/collection/TraversableLike;Ljava/lang/Object;Lscala/Function2;)Ljava/lang/Object;
const #715 = Method	#130.#714;	//  scala/collection/TraversableLike$class.foldLeft:(Lscala/collection/TraversableLike;Ljava/lang/Object;Lscala/Function2;)Ljava/lang/Object;
const #716 = Asciz	count;
const #717 = Asciz	(Lscala/Function1;)I;
const #718 = Asciz	(Lscala/collection/TraversableLike;Lscala/Function1;)I;
const #719 = NameAndType	#716:#718;//  count:(Lscala/collection/TraversableLike;Lscala/Function1;)I
const #720 = Method	#130.#719;	//  scala/collection/TraversableLike$class.count:(Lscala/collection/TraversableLike;Lscala/Function1;)I
const #721 = Asciz	groupBy;
const #722 = Asciz	(Lscala/Function1;)Lscala/collection/Map;;
const #723 = Asciz	(Lscala/collection/TraversableLike;Lscala/Function1;)Lscala/collection/Map;;
const #724 = NameAndType	#721:#723;//  groupBy:(Lscala/collection/TraversableLike;Lscala/Function1;)Lscala/collection/Map;
const #725 = Method	#130.#724;	//  scala/collection/TraversableLike$class.groupBy:(Lscala/collection/TraversableLike;Lscala/Function1;)Lscala/collection/Map;
const #726 = Asciz	partition;
const #727 = NameAndType	#726:#644;//  partition:(Lscala/collection/TraversableLike;Lscala/Function1;)Lscala/Tuple2;
const #728 = Method	#130.#727;	//  scala/collection/TraversableLike$class.partition:(Lscala/collection/TraversableLike;Lscala/Function1;)Lscala/Tuple2;
const #729 = Asciz	partialMap;
const #730 = Asciz	(Lscala/PartialFunction;Lscala/collection/generic/CanBuildFrom;)Ljava/lang/Object;;
const #731 = Asciz	(Lscala/collection/TraversableLike;Lscala/PartialFunction;Lscala/collection/generic/CanBuildFrom;)Ljava/lang/Object;;
const #732 = NameAndType	#729:#731;//  partialMap:(Lscala/collection/TraversableLike;Lscala/PartialFunction;Lscala/collection/generic/CanBuildFrom;)Ljava/lang/Object;
const #733 = Method	#130.#732;	//  scala/collection/TraversableLike$class.partialMap:(Lscala/collection/TraversableLike;Lscala/PartialFunction;Lscala/collection/generic/CanBuildFrom;)Ljava/lang/Object;
const #734 = Asciz	pf;
const #735 = Asciz	Lscala/PartialFunction;;
const #736 = Asciz	filterNot;
const #737 = NameAndType	#736:#649;//  filterNot:(Lscala/collection/TraversableLike;Lscala/Function1;)Ljava/lang/Object;
const #738 = Method	#130.#737;	//  scala/collection/TraversableLike$class.filterNot:(Lscala/collection/TraversableLike;Lscala/Function1;)Ljava/lang/Object;
const #739 = Asciz	filter;
const #740 = NameAndType	#739:#649;//  filter:(Lscala/collection/TraversableLike;Lscala/Function1;)Ljava/lang/Object;
const #741 = Method	#130.#740;	//  scala/collection/TraversableLike$class.filter:(Lscala/collection/TraversableLike;Lscala/Function1;)Ljava/lang/Object;
const #742 = Asciz	flatMap;
const #743 = Asciz	(Lscala/collection/TraversableLike;Lscala/Function1;Lscala/collection/generic/CanBuildFrom;)Ljava/lang/Object;;
const #744 = NameAndType	#742:#743;//  flatMap:(Lscala/collection/TraversableLike;Lscala/Function1;Lscala/collection/generic/CanBuildFrom;)Ljava/lang/Object;
const #745 = Method	#130.#744;	//  scala/collection/TraversableLike$class.flatMap:(Lscala/collection/TraversableLike;Lscala/Function1;Lscala/collection/generic/CanBuildFrom;)Ljava/lang/Object;
const #746 = Asciz	map;
const #747 = NameAndType	#746:#743;//  map:(Lscala/collection/TraversableLike;Lscala/Function1;Lscala/collection/generic/CanBuildFrom;)Ljava/lang/Object;
const #748 = Method	#130.#747;	//  scala/collection/TraversableLike$class.map:(Lscala/collection/TraversableLike;Lscala/Function1;Lscala/collection/generic/CanBuildFrom;)Ljava/lang/Object;
const #749 = Asciz	$plus$plus;
const #750 = Asciz	(Lscala/collection/Iterator;Lscala/collection/generic/CanBuildFrom;)Ljava/lang/Object;;
const #751 = Asciz	(Lscala/collection/TraversableLike;Lscala/collection/Iterator;Lscala/collection/generic/CanBuildFrom;)Ljava/lang/Object;;
const #752 = NameAndType	#749:#751;//  $plus$plus:(Lscala/collection/TraversableLike;Lscala/collection/Iterator;Lscala/collection/generic/CanBuildFrom;)Ljava/lang/Object;
const #753 = Method	#130.#752;	//  scala/collection/TraversableLike$class.$plus$plus:(Lscala/collection/TraversableLike;Lscala/collection/Iterator;Lscala/collection/generic/CanBuildFrom;)Ljava/lang/Object;
const #754 = Asciz	that;
const #755 = Asciz	Lscala/collection/Iterator;;
const #756 = Asciz	(Lscala/collection/Traversable;Lscala/collection/generic/CanBuildFrom;)Ljava/lang/Object;;
const #757 = Asciz	(Lscala/collection/TraversableLike;Lscala/collection/Traversable;Lscala/collection/generic/CanBuildFrom;)Ljava/lang/Object;;
const #758 = NameAndType	#749:#757;//  $plus$plus:(Lscala/collection/TraversableLike;Lscala/collection/Traversable;Lscala/collection/generic/CanBuildFrom;)Ljava/lang/Object;
const #759 = Method	#130.#758;	//  scala/collection/TraversableLike$class.$plus$plus:(Lscala/collection/TraversableLike;Lscala/collection/Traversable;Lscala/collection/generic/CanBuildFrom;)Ljava/lang/Object;
const #760 = Asciz	Lscala/collection/Traversable;;
const #761 = Asciz	hasDefiniteSize;
const #762 = Asciz	(Lscala/collection/TraversableLike;)Z;
const #763 = NameAndType	#761:#762;//  hasDefiniteSize:(Lscala/collection/TraversableLike;)Z
const #764 = Method	#130.#763;	//  scala/collection/TraversableLike$class.hasDefiniteSize:(Lscala/collection/TraversableLike;)Z
const #765 = Asciz	nonEmpty;
const #766 = NameAndType	#765:#762;//  nonEmpty:(Lscala/collection/TraversableLike;)Z
const #767 = Method	#130.#766;	//  scala/collection/TraversableLike$class.nonEmpty:(Lscala/collection/TraversableLike;)Z
const #768 = Asciz	transpose;
const #769 = Asciz	(Lscala/Function1;)Lscala/collection/Traversable;;
const #770 = Asciz	(Lscala/collection/generic/GenericTraversableTemplate;Lscala/Function1;)Lscala/collection/Traversable;;
const #771 = NameAndType	#768:#770;//  transpose:(Lscala/collection/generic/GenericTraversableTemplate;Lscala/Function1;)Lscala/collection/Traversable;
const #772 = Method	#136.#771;	//  scala/collection/generic/GenericTraversableTemplate$class.transpose:(Lscala/collection/generic/GenericTraversableTemplate;Lscala/Function1;)Lscala/collection/Traversable;
const #773 = Asciz	asTraversable;
const #774 = Asciz	flatten;
const #775 = NameAndType	#774:#770;//  flatten:(Lscala/collection/generic/GenericTraversableTemplate;Lscala/Function1;)Lscala/collection/Traversable;
const #776 = Method	#136.#775;	//  scala/collection/generic/GenericTraversableTemplate$class.flatten:(Lscala/collection/generic/GenericTraversableTemplate;Lscala/Function1;)Lscala/collection/Traversable;
const #777 = Asciz	unzip;
const #778 = Asciz	(Lscala/collection/generic/GenericTraversableTemplate;Lscala/Function1;)Lscala/Tuple2;;
const #779 = NameAndType	#777:#778;//  unzip:(Lscala/collection/generic/GenericTraversableTemplate;Lscala/Function1;)Lscala/Tuple2;
const #780 = Method	#136.#779;	//  scala/collection/generic/GenericTraversableTemplate$class.unzip:(Lscala/collection/generic/GenericTraversableTemplate;Lscala/Function1;)Lscala/Tuple2;
const #781 = Asciz	asPair;
const #782 = Asciz	genericBuilder;
const #783 = Asciz	()Lscala/collection/mutable/Builder;;
const #784 = Asciz	(Lscala/collection/generic/GenericTraversableTemplate;)Lscala/collection/mutable/Builder;;
const #785 = NameAndType	#782:#784;//  genericBuilder:(Lscala/collection/generic/GenericTraversableTemplate;)Lscala/collection/mutable/Builder;
const #786 = Method	#136.#785;	//  scala/collection/generic/GenericTraversableTemplate$class.genericBuilder:(Lscala/collection/generic/GenericTraversableTemplate;)Lscala/collection/mutable/Builder;
const #787 = Asciz	newBuilder;
const #788 = NameAndType	#787:#784;//  newBuilder:(Lscala/collection/generic/GenericTraversableTemplate;)Lscala/collection/mutable/Builder;
const #789 = Method	#136.#788;	//  scala/collection/generic/GenericTraversableTemplate$class.newBuilder:(Lscala/collection/generic/GenericTraversableTemplate;)Lscala/collection/mutable/Builder;
const #790 = Asciz	firstOption;
const #791 = Asciz	(Lscala/collection/IterableLike;)Lscala/Option;;
const #792 = NameAndType	#790:#791;//  firstOption:(Lscala/collection/IterableLike;)Lscala/Option;
const #793 = Method	#151.#792;	//  scala/collection/IterableLike$class.firstOption:(Lscala/collection/IterableLike;)Lscala/Option;
const #794 = Asciz	first;
const #795 = Asciz	(Lscala/collection/IterableLike;)Ljava/lang/Object;;
const #796 = NameAndType	#794:#795;//  first:(Lscala/collection/IterableLike;)Ljava/lang/Object;
const #797 = Method	#151.#796;	//  scala/collection/IterableLike$class.first:(Lscala/collection/IterableLike;)Ljava/lang/Object;
const #798 = Asciz	canEqual;
const #799 = Asciz	(Lscala/collection/IterableLike;Ljava/lang/Object;)Z;
const #800 = NameAndType	#798:#799;//  canEqual:(Lscala/collection/IterableLike;Ljava/lang/Object;)Z
const #801 = Method	#151.#800;	//  scala/collection/IterableLike$class.canEqual:(Lscala/collection/IterableLike;Ljava/lang/Object;)Z
const #802 = Asciz	toStream;
const #803 = Asciz	()Lscala/collection/immutable/Stream;;
const #804 = Asciz	(Lscala/collection/IterableLike;)Lscala/collection/immutable/Stream;;
const #805 = NameAndType	#802:#804;//  toStream:(Lscala/collection/IterableLike;)Lscala/collection/immutable/Stream;
const #806 = Method	#151.#805;	//  scala/collection/IterableLike$class.toStream:(Lscala/collection/IterableLike;)Lscala/collection/immutable/Stream;
const #807 = Asciz	sameElements;
const #808 = Asciz	(Lscala/collection/Iterable;)Z;
const #809 = Asciz	(Lscala/collection/IterableLike;Lscala/collection/Iterable;)Z;
const #810 = NameAndType	#807:#809;//  sameElements:(Lscala/collection/IterableLike;Lscala/collection/Iterable;)Z
const #811 = Method	#151.#810;	//  scala/collection/IterableLike$class.sameElements:(Lscala/collection/IterableLike;Lscala/collection/Iterable;)Z
const #812 = Asciz	Lscala/collection/Iterable;;
const #813 = Asciz	zipWithIndex;
const #814 = Asciz	(Lscala/collection/generic/CanBuildFrom;)Ljava/lang/Object;;
const #815 = Asciz	(Lscala/collection/IterableLike;Lscala/collection/generic/CanBuildFrom;)Ljava/lang/Object;;
const #816 = NameAndType	#813:#815;//  zipWithIndex:(Lscala/collection/IterableLike;Lscala/collection/generic/CanBuildFrom;)Ljava/lang/Object;
const #817 = Method	#151.#816;	//  scala/collection/IterableLike$class.zipWithIndex:(Lscala/collection/IterableLike;Lscala/collection/generic/CanBuildFrom;)Ljava/lang/Object;
const #818 = Asciz	zipAll;
const #819 = Asciz	(Lscala/collection/Iterable;Ljava/lang/Object;Ljava/lang/Object;Lscala/collection/generic/CanBuildFrom;)Ljava/lang/Object;;
const #820 = Asciz	(Lscala/collection/IterableLike;Lscala/collection/Iterable;Ljava/lang/Object;Ljava/lang/Object;Lscala/collection/generic/CanBuildFrom;)Ljava/lang/Object;;
const #821 = NameAndType	#818:#820;//  zipAll:(Lscala/collection/IterableLike;Lscala/collection/Iterable;Ljava/lang/Object;Ljava/lang/Object;Lscala/collection/generic/CanBuildFrom;)Ljava/lang/Object;
const #822 = Method	#151.#821;	//  scala/collection/IterableLike$class.zipAll:(Lscala/collection/IterableLike;Lscala/collection/Iterable;Ljava/lang/Object;Ljava/lang/Object;Lscala/collection/generic/CanBuildFrom;)Ljava/lang/Object;
const #823 = Asciz	thisElem;
const #824 = Asciz	thatElem;
const #825 = Asciz	zip;
const #826 = Asciz	(Lscala/collection/Iterable;Lscala/collection/generic/CanBuildFrom;)Ljava/lang/Object;;
const #827 = Asciz	(Lscala/collection/IterableLike;Lscala/collection/Iterable;Lscala/collection/generic/CanBuildFrom;)Ljava/lang/Object;;
const #828 = NameAndType	#825:#827;//  zip:(Lscala/collection/IterableLike;Lscala/collection/Iterable;Lscala/collection/generic/CanBuildFrom;)Ljava/lang/Object;
const #829 = Method	#151.#828;	//  scala/collection/IterableLike$class.zip:(Lscala/collection/IterableLike;Lscala/collection/Iterable;Lscala/collection/generic/CanBuildFrom;)Ljava/lang/Object;
const #830 = Asciz	(Ljava/lang/Object;II)V;
const #831 = Asciz	(Lscala/collection/IterableLike;Ljava/lang/Object;II)V;
const #832 = NameAndType	#624:#831;//  copyToArray:(Lscala/collection/IterableLike;Ljava/lang/Object;II)V
const #833 = Method	#151.#832;	//  scala/collection/IterableLike$class.copyToArray:(Lscala/collection/IterableLike;Ljava/lang/Object;II)V
const #834 = Asciz	takeWhile;
const #835 = Asciz	(Lscala/collection/IterableLike;Lscala/Function1;)Ljava/lang/Object;;
const #836 = NameAndType	#834:#835;//  takeWhile:(Lscala/collection/IterableLike;Lscala/Function1;)Ljava/lang/Object;
const #837 = Method	#151.#836;	//  scala/collection/IterableLike$class.takeWhile:(Lscala/collection/IterableLike;Lscala/Function1;)Ljava/lang/Object;
const #838 = Asciz	slice;
const #839 = Asciz	(Lscala/collection/IterableLike;II)Ljava/lang/Object;;
const #840 = NameAndType	#838:#839;//  slice:(Lscala/collection/IterableLike;II)Ljava/lang/Object;
const #841 = Method	#151.#840;	//  scala/collection/IterableLike$class.slice:(Lscala/collection/IterableLike;II)Ljava/lang/Object;
const #842 = Asciz	head;
const #843 = NameAndType	#842:#795;//  head:(Lscala/collection/IterableLike;)Ljava/lang/Object;
const #844 = Method	#151.#843;	//  scala/collection/IterableLike$class.head:(Lscala/collection/IterableLike;)Ljava/lang/Object;
const #845 = Asciz	toIterable;
const #846 = Asciz	(Lscala/collection/IterableLike;)Lscala/collection/Iterable;;
const #847 = NameAndType	#845:#846;//  toIterable:(Lscala/collection/IterableLike;)Lscala/collection/Iterable;
const #848 = Method	#151.#847;	//  scala/collection/IterableLike$class.toIterable:(Lscala/collection/IterableLike;)Lscala/collection/Iterable;
const #849 = Asciz	reduceRight;
const #850 = Asciz	(Lscala/collection/IterableLike;Lscala/Function2;)Ljava/lang/Object;;
const #851 = NameAndType	#849:#850;//  reduceRight:(Lscala/collection/IterableLike;Lscala/Function2;)Ljava/lang/Object;
const #852 = Method	#151.#851;	//  scala/collection/IterableLike$class.reduceRight:(Lscala/collection/IterableLike;Lscala/Function2;)Ljava/lang/Object;
const #853 = Asciz	foldRight;
const #854 = Asciz	(Lscala/collection/IterableLike;Ljava/lang/Object;Lscala/Function2;)Ljava/lang/Object;;
const #855 = NameAndType	#853:#854;//  foldRight:(Lscala/collection/IterableLike;Ljava/lang/Object;Lscala/Function2;)Ljava/lang/Object;
const #856 = Method	#151.#855;	//  scala/collection/IterableLike$class.foldRight:(Lscala/collection/IterableLike;Ljava/lang/Object;Lscala/Function2;)Ljava/lang/Object;
const #857 = Asciz	isEmpty;
const #858 = Asciz	(Lscala/collection/IterableLike;)Z;
const #859 = NameAndType	#857:#858;//  isEmpty:(Lscala/collection/IterableLike;)Z
const #860 = Method	#151.#859;	//  scala/collection/IterableLike$class.isEmpty:(Lscala/collection/IterableLike;)Z
const #861 = Asciz	find;
const #862 = Asciz	(Lscala/Function1;)Lscala/Option;;
const #863 = Asciz	(Lscala/collection/IterableLike;Lscala/Function1;)Lscala/Option;;
const #864 = NameAndType	#861:#863;//  find:(Lscala/collection/IterableLike;Lscala/Function1;)Lscala/Option;
const #865 = Method	#151.#864;	//  scala/collection/IterableLike$class.find:(Lscala/collection/IterableLike;Lscala/Function1;)Lscala/Option;
const #866 = Asciz	exists;
const #867 = Asciz	(Lscala/Function1;)Z;
const #868 = Asciz	(Lscala/collection/IterableLike;Lscala/Function1;)Z;
const #869 = NameAndType	#866:#868;//  exists:(Lscala/collection/IterableLike;Lscala/Function1;)Z
const #870 = Method	#151.#869;	//  scala/collection/IterableLike$class.exists:(Lscala/collection/IterableLike;Lscala/Function1;)Z
const #871 = Asciz	forall;
const #872 = NameAndType	#871:#868;//  forall:(Lscala/collection/IterableLike;Lscala/Function1;)Z
const #873 = Method	#151.#872;	//  scala/collection/IterableLike$class.forall:(Lscala/collection/IterableLike;Lscala/Function1;)Z
const #874 = Asciz	foreach;
const #875 = Asciz	(Lscala/collection/IterableLike;Lscala/Function1;)V;
const #876 = NameAndType	#874:#875;//  foreach:(Lscala/collection/IterableLike;Lscala/Function1;)V
const #877 = Method	#151.#876;	//  scala/collection/IterableLike$class.foreach:(Lscala/collection/IterableLike;Lscala/Function1;)V
const #878 = Asciz	elements;
const #879 = Asciz	(Lscala/collection/IterableLike;)Lscala/collection/Iterator;;
const #880 = NameAndType	#878:#879;//  elements:(Lscala/collection/IterableLike;)Lscala/collection/Iterator;
const #881 = Method	#151.#880;	//  scala/collection/IterableLike$class.elements:(Lscala/collection/IterableLike;)Lscala/collection/Iterator;
const #882 = Asciz	compose;
const #883 = Asciz	(Lscala/Function1;Lscala/Function1;)Lscala/Function1;;
const #884 = NameAndType	#882:#883;//  compose:(Lscala/Function1;Lscala/Function1;)Lscala/Function1;
const #885 = Method	#166.#884;	//  scala/Function1$class.compose:(Lscala/Function1;Lscala/Function1;)Lscala/Function1;
const #886 = Asciz	lift;
const #887 = Asciz	()Lscala/Function1;;
const #888 = Asciz	(Lscala/PartialFunction;)Lscala/Function1;;
const #889 = NameAndType	#886:#888;//  lift:(Lscala/PartialFunction;)Lscala/Function1;
const #890 = Method	#171.#889;	//  scala/PartialFunction$class.lift:(Lscala/PartialFunction;)Lscala/Function1;
const #891 = Asciz	(Lscala/PartialFunction;Lscala/Function1;)Lscala/PartialFunction;;
const #892 = NameAndType	#260:#891;//  andThen:(Lscala/PartialFunction;Lscala/Function1;)Lscala/PartialFunction;
const #893 = Method	#171.#892;	//  scala/PartialFunction$class.andThen:(Lscala/PartialFunction;Lscala/Function1;)Lscala/PartialFunction;
const #894 = Asciz	k;
const #895 = Asciz	orElse;
const #896 = Asciz	(Lscala/PartialFunction;)Lscala/PartialFunction;;
const #897 = Asciz	(Lscala/PartialFunction;Lscala/PartialFunction;)Lscala/PartialFunction;;
const #898 = NameAndType	#895:#897;//  orElse:(Lscala/PartialFunction;Lscala/PartialFunction;)Lscala/PartialFunction;
const #899 = Method	#171.#898;	//  scala/PartialFunction$class.orElse:(Lscala/PartialFunction;Lscala/PartialFunction;)Lscala/PartialFunction;
const #900 = Asciz	projection;
const #901 = Asciz	(Lscala/collection/SeqLike;)Ljava/lang/Object;;
const #902 = NameAndType	#900:#901;//  projection:(Lscala/collection/SeqLike;)Ljava/lang/Object;
const #903 = Method	#176.#902;	//  scala/collection/SeqLike$class.projection:(Lscala/collection/SeqLike;)Ljava/lang/Object;
const #904 = Asciz	equalsWith;
const #905 = Asciz	(Lscala/collection/Seq;Lscala/Function2;)Z;
const #906 = Asciz	(Lscala/collection/SeqLike;Lscala/collection/Seq;Lscala/Function2;)Z;
const #907 = NameAndType	#904:#906;//  equalsWith:(Lscala/collection/SeqLike;Lscala/collection/Seq;Lscala/Function2;)Z
const #908 = Method	#176.#907;	//  scala/collection/SeqLike$class.equalsWith:(Lscala/collection/SeqLike;Lscala/collection/Seq;Lscala/Function2;)Z
const #909 = Asciz	Lscala/collection/Seq;;
const #910 = Asciz	findLastIndexOf;
const #911 = Asciz	(Lscala/collection/SeqLike;Lscala/Function1;)I;
const #912 = NameAndType	#910:#911;//  findLastIndexOf:(Lscala/collection/SeqLike;Lscala/Function1;)I
const #913 = Method	#176.#912;	//  scala/collection/SeqLike$class.findLastIndexOf:(Lscala/collection/SeqLike;Lscala/Function1;)I
const #914 = Asciz	(Lscala/collection/SeqLike;)Ljava/lang/String;;
const #915 = NameAndType	#390:#914;//  toString:(Lscala/collection/SeqLike;)Ljava/lang/String;
const #916 = Method	#176.#915;	//  scala/collection/SeqLike$class.toString:(Lscala/collection/SeqLike;)Ljava/lang/String;
const #917 = Asciz	equals;
const #918 = Asciz	(Lscala/collection/SeqLike;Ljava/lang/Object;)Z;
const #919 = NameAndType	#917:#918;//  equals:(Lscala/collection/SeqLike;Ljava/lang/Object;)Z
const #920 = Method	#176.#919;	//  scala/collection/SeqLike$class.equals:(Lscala/collection/SeqLike;Ljava/lang/Object;)Z
const #921 = Asciz	hashCode;
const #922 = Asciz	(Lscala/collection/SeqLike;)I;
const #923 = NameAndType	#921:#922;//  hashCode:(Lscala/collection/SeqLike;)I
const #924 = Method	#176.#923;	//  scala/collection/SeqLike$class.hashCode:(Lscala/collection/SeqLike;)I
const #925 = Asciz	(Lscala/collection/SeqLike;II)Lscala/collection/SeqView;;
const #926 = NameAndType	#252:#925;//  view:(Lscala/collection/SeqLike;II)Lscala/collection/SeqView;
const #927 = Method	#176.#926;	//  scala/collection/SeqLike$class.view:(Lscala/collection/SeqLike;II)Lscala/collection/SeqView;
const #928 = NameAndType	#252:#901;//  view:(Lscala/collection/SeqLike;)Ljava/lang/Object;
const #929 = Method	#176.#928;	//  scala/collection/SeqLike$class.view:(Lscala/collection/SeqLike;)Ljava/lang/Object;
const #930 = Asciz	indices;
const #931 = Asciz	()Lscala/collection/immutable/Range;;
const #932 = Asciz	(Lscala/collection/SeqLike;)Lscala/collection/immutable/Range;;
const #933 = NameAndType	#930:#932;//  indices:(Lscala/collection/SeqLike;)Lscala/collection/immutable/Range;
const #934 = Method	#176.#933;	//  scala/collection/SeqLike$class.indices:(Lscala/collection/SeqLike;)Lscala/collection/immutable/Range;
const #935 = Asciz	toSeq;
const #936 = Asciz	(Lscala/collection/SeqLike;)Lscala/collection/Seq;;
const #937 = NameAndType	#935:#936;//  toSeq:(Lscala/collection/SeqLike;)Lscala/collection/Seq;
const #938 = Method	#176.#937;	//  scala/collection/SeqLike$class.toSeq:(Lscala/collection/SeqLike;)Lscala/collection/Seq;
const #939 = Asciz	sortBy;
const #940 = Asciz	(Lscala/Function1;Lscala/math/Ordering;)Ljava/lang/Object;;
const #941 = Asciz	(Lscala/collection/SeqLike;Lscala/Function1;Lscala/math/Ordering;)Ljava/lang/Object;;
const #942 = NameAndType	#939:#941;//  sortBy:(Lscala/collection/SeqLike;Lscala/Function1;Lscala/math/Ordering;)Ljava/lang/Object;
const #943 = Method	#176.#942;	//  scala/collection/SeqLike$class.sortBy:(Lscala/collection/SeqLike;Lscala/Function1;Lscala/math/Ordering;)Ljava/lang/Object;
const #944 = Asciz	ord;
const #945 = Asciz	sortWith;
const #946 = Asciz	(Lscala/collection/SeqLike;Lscala/math/Ordering;)Ljava/lang/Object;;
const #947 = NameAndType	#945:#946;//  sortWith:(Lscala/collection/SeqLike;Lscala/math/Ordering;)Ljava/lang/Object;
const #948 = Method	#176.#947;	//  scala/collection/SeqLike$class.sortWith:(Lscala/collection/SeqLike;Lscala/math/Ordering;)Ljava/lang/Object;
const #949 = Asciz	(Lscala/collection/SeqLike;Lscala/Function2;)Ljava/lang/Object;;
const #950 = NameAndType	#945:#949;//  sortWith:(Lscala/collection/SeqLike;Lscala/Function2;)Ljava/lang/Object;
const #951 = Method	#176.#950;	//  scala/collection/SeqLike$class.sortWith:(Lscala/collection/SeqLike;Lscala/Function2;)Ljava/lang/Object;
const #952 = Asciz	lt;
const #953 = Asciz	corresponds;
const #954 = NameAndType	#953:#906;//  corresponds:(Lscala/collection/SeqLike;Lscala/collection/Seq;Lscala/Function2;)Z
const #955 = Method	#176.#954;	//  scala/collection/SeqLike$class.corresponds:(Lscala/collection/SeqLike;Lscala/collection/Seq;Lscala/Function2;)Z
const #956 = Asciz	padTo;
const #957 = Asciz	(Lscala/collection/SeqLike;ILjava/lang/Object;Lscala/collection/generic/CanBuildFrom;)Ljava/lang/Object;;
const #958 = NameAndType	#956:#957;//  padTo:(Lscala/collection/SeqLike;ILjava/lang/Object;Lscala/collection/generic/CanBuildFrom;)Ljava/lang/Object;
const #959 = Method	#176.#958;	//  scala/collection/SeqLike$class.padTo:(Lscala/collection/SeqLike;ILjava/lang/Object;Lscala/collection/generic/CanBuildFrom;)Ljava/lang/Object;
const #960 = Asciz	patch;
const #961 = Asciz	(ILscala/collection/Seq;ILscala/collection/generic/CanBuildFrom;)Ljava/lang/Object;;
const #962 = Asciz	(Lscala/collection/SeqLike;ILscala/collection/Seq;ILscala/collection/generic/CanBuildFrom;)Ljava/lang/Object;;
const #963 = NameAndType	#960:#962;//  patch:(Lscala/collection/SeqLike;ILscala/collection/Seq;ILscala/collection/generic/CanBuildFrom;)Ljava/lang/Object;
const #964 = Method	#176.#963;	//  scala/collection/SeqLike$class.patch:(Lscala/collection/SeqLike;ILscala/collection/Seq;ILscala/collection/generic/CanBuildFrom;)Ljava/lang/Object;
const #965 = Asciz	replaced;
const #966 = Asciz	removeDuplicates;
const #967 = NameAndType	#966:#901;//  removeDuplicates:(Lscala/collection/SeqLike;)Ljava/lang/Object;
const #968 = Method	#176.#967;	//  scala/collection/SeqLike$class.removeDuplicates:(Lscala/collection/SeqLike;)Ljava/lang/Object;
const #969 = Asciz	intersect;
const #970 = Asciz	(Lscala/collection/Seq;)Ljava/lang/Object;;
const #971 = Asciz	(Lscala/collection/SeqLike;Lscala/collection/Seq;)Ljava/lang/Object;;
const #972 = NameAndType	#969:#971;//  intersect:(Lscala/collection/SeqLike;Lscala/collection/Seq;)Ljava/lang/Object;
const #973 = Method	#176.#972;	//  scala/collection/SeqLike$class.intersect:(Lscala/collection/SeqLike;Lscala/collection/Seq;)Ljava/lang/Object;
const #974 = Asciz	diff;
const #975 = NameAndType	#974:#971;//  diff:(Lscala/collection/SeqLike;Lscala/collection/Seq;)Ljava/lang/Object;
const #976 = Method	#176.#975;	//  scala/collection/SeqLike$class.diff:(Lscala/collection/SeqLike;Lscala/collection/Seq;)Ljava/lang/Object;
const #977 = Asciz	union;
const #978 = Asciz	(Lscala/collection/Seq;Lscala/collection/generic/CanBuildFrom;)Ljava/lang/Object;;
const #979 = Asciz	(Lscala/collection/SeqLike;Lscala/collection/Seq;Lscala/collection/generic/CanBuildFrom;)Ljava/lang/Object;;
const #980 = NameAndType	#977:#979;//  union:(Lscala/collection/SeqLike;Lscala/collection/Seq;Lscala/collection/generic/CanBuildFrom;)Ljava/lang/Object;
const #981 = Method	#176.#980;	//  scala/collection/SeqLike$class.union:(Lscala/collection/SeqLike;Lscala/collection/Seq;Lscala/collection/generic/CanBuildFrom;)Ljava/lang/Object;
const #982 = Asciz	contains;
const #983 = NameAndType	#982:#918;//  contains:(Lscala/collection/SeqLike;Ljava/lang/Object;)Z
const #984 = Method	#176.#983;	//  scala/collection/SeqLike$class.contains:(Lscala/collection/SeqLike;Ljava/lang/Object;)Z
const #985 = Asciz	containsSlice;
const #986 = Asciz	(Lscala/collection/Seq;)Z;
const #987 = Asciz	(Lscala/collection/SeqLike;Lscala/collection/Seq;)Z;
const #988 = NameAndType	#985:#987;//  containsSlice:(Lscala/collection/SeqLike;Lscala/collection/Seq;)Z
const #989 = Method	#176.#988;	//  scala/collection/SeqLike$class.containsSlice:(Lscala/collection/SeqLike;Lscala/collection/Seq;)Z
const #990 = Asciz	lastIndexOfSlice;
const #991 = Asciz	(Lscala/collection/Seq;I)I;
const #992 = Asciz	(Lscala/collection/SeqLike;Lscala/collection/Seq;I)I;
const #993 = NameAndType	#990:#992;//  lastIndexOfSlice:(Lscala/collection/SeqLike;Lscala/collection/Seq;I)I
const #994 = Method	#176.#993;	//  scala/collection/SeqLike$class.lastIndexOfSlice:(Lscala/collection/SeqLike;Lscala/collection/Seq;I)I
const #995 = Asciz	(Lscala/collection/Seq;)I;
const #996 = Asciz	(Lscala/collection/SeqLike;Lscala/collection/Seq;)I;
const #997 = NameAndType	#990:#996;//  lastIndexOfSlice:(Lscala/collection/SeqLike;Lscala/collection/Seq;)I
const #998 = Method	#176.#997;	//  scala/collection/SeqLike$class.lastIndexOfSlice:(Lscala/collection/SeqLike;Lscala/collection/Seq;)I
const #999 = Asciz	indexOfSlice;
const #1000 = NameAndType	#999:#992;//  indexOfSlice:(Lscala/collection/SeqLike;Lscala/collection/Seq;I)I
const #1001 = Method	#176.#1000;	//  scala/collection/SeqLike$class.indexOfSlice:(Lscala/collection/SeqLike;Lscala/collection/Seq;I)I
const #1002 = NameAndType	#999:#996;//  indexOfSlice:(Lscala/collection/SeqLike;Lscala/collection/Seq;)I
const #1003 = Method	#176.#1002;	//  scala/collection/SeqLike$class.indexOfSlice:(Lscala/collection/SeqLike;Lscala/collection/Seq;)I
const #1004 = Asciz	endsWith;
const #1005 = NameAndType	#1004:#987;//  endsWith:(Lscala/collection/SeqLike;Lscala/collection/Seq;)Z
const #1006 = Method	#176.#1005;	//  scala/collection/SeqLike$class.endsWith:(Lscala/collection/SeqLike;Lscala/collection/Seq;)Z
const #1007 = Asciz	startsWith;
const #1008 = NameAndType	#1007:#987;//  startsWith:(Lscala/collection/SeqLike;Lscala/collection/Seq;)Z
const #1009 = Method	#176.#1008;	//  scala/collection/SeqLike$class.startsWith:(Lscala/collection/SeqLike;Lscala/collection/Seq;)Z
const #1010 = Asciz	(Lscala/collection/Seq;I)Z;
const #1011 = Asciz	(Lscala/collection/SeqLike;Lscala/collection/Seq;I)Z;
const #1012 = NameAndType	#1007:#1011;//  startsWith:(Lscala/collection/SeqLike;Lscala/collection/Seq;I)Z
const #1013 = Method	#176.#1012;	//  scala/collection/SeqLike$class.startsWith:(Lscala/collection/SeqLike;Lscala/collection/Seq;I)Z
const #1014 = Asciz	offset;
const #1015 = Asciz	reversedElements;
const #1016 = Asciz	(Lscala/collection/SeqLike;)Lscala/collection/Iterator;;
const #1017 = NameAndType	#1015:#1016;//  reversedElements:(Lscala/collection/SeqLike;)Lscala/collection/Iterator;
const #1018 = Method	#176.#1017;	//  scala/collection/SeqLike$class.reversedElements:(Lscala/collection/SeqLike;)Lscala/collection/Iterator;
const #1019 = Asciz	reverseIterator;
const #1020 = NameAndType	#1019:#1016;//  reverseIterator:(Lscala/collection/SeqLike;)Lscala/collection/Iterator;
const #1021 = Method	#176.#1020;	//  scala/collection/SeqLike$class.reverseIterator:(Lscala/collection/SeqLike;)Lscala/collection/Iterator;
const #1022 = Asciz	reverseMap;
const #1023 = Asciz	(Lscala/collection/SeqLike;Lscala/Function1;Lscala/collection/generic/CanBuildFrom;)Ljava/lang/Object;;
const #1024 = NameAndType	#1022:#1023;//  reverseMap:(Lscala/collection/SeqLike;Lscala/Function1;Lscala/collection/generic/CanBuildFrom;)Ljava/lang/Object;
const #1025 = Method	#176.#1024;	//  scala/collection/SeqLike$class.reverseMap:(Lscala/collection/SeqLike;Lscala/Function1;Lscala/collection/generic/CanBuildFrom;)Ljava/lang/Object;
const #1026 = Asciz	reverse;
const #1027 = NameAndType	#1026:#901;//  reverse:(Lscala/collection/SeqLike;)Ljava/lang/Object;
const #1028 = Method	#176.#1027;	//  scala/collection/SeqLike$class.reverse:(Lscala/collection/SeqLike;)Ljava/lang/Object;
const #1029 = Asciz	lastIndexWhere;
const #1030 = Asciz	(Lscala/Function1;I)I;
const #1031 = Asciz	(Lscala/collection/SeqLike;Lscala/Function1;I)I;
const #1032 = NameAndType	#1029:#1031;//  lastIndexWhere:(Lscala/collection/SeqLike;Lscala/Function1;I)I
const #1033 = Method	#176.#1032;	//  scala/collection/SeqLike$class.lastIndexWhere:(Lscala/collection/SeqLike;Lscala/Function1;I)I
const #1034 = NameAndType	#1029:#911;//  lastIndexWhere:(Lscala/collection/SeqLike;Lscala/Function1;)I
const #1035 = Method	#176.#1034;	//  scala/collection/SeqLike$class.lastIndexWhere:(Lscala/collection/SeqLike;Lscala/Function1;)I
const #1036 = Asciz	lastIndexOf;
const #1037 = Asciz	(Ljava/lang/Object;I)I;
const #1038 = Asciz	(Lscala/collection/SeqLike;Ljava/lang/Object;I)I;
const #1039 = NameAndType	#1036:#1038;//  lastIndexOf:(Lscala/collection/SeqLike;Ljava/lang/Object;I)I
const #1040 = Method	#176.#1039;	//  scala/collection/SeqLike$class.lastIndexOf:(Lscala/collection/SeqLike;Ljava/lang/Object;I)I
const #1041 = Asciz	(Lscala/collection/SeqLike;Ljava/lang/Object;)I;
const #1042 = NameAndType	#1036:#1041;//  lastIndexOf:(Lscala/collection/SeqLike;Ljava/lang/Object;)I
const #1043 = Method	#176.#1042;	//  scala/collection/SeqLike$class.lastIndexOf:(Lscala/collection/SeqLike;Ljava/lang/Object;)I
const #1044 = Asciz	indexOf;
const #1045 = NameAndType	#1044:#1038;//  indexOf:(Lscala/collection/SeqLike;Ljava/lang/Object;I)I
const #1046 = Method	#176.#1045;	//  scala/collection/SeqLike$class.indexOf:(Lscala/collection/SeqLike;Ljava/lang/Object;I)I
const #1047 = NameAndType	#1044:#1041;//  indexOf:(Lscala/collection/SeqLike;Ljava/lang/Object;)I
const #1048 = Method	#176.#1047;	//  scala/collection/SeqLike$class.indexOf:(Lscala/collection/SeqLike;Ljava/lang/Object;)I
const #1049 = Asciz	findIndexOf;
const #1050 = NameAndType	#1049:#911;//  findIndexOf:(Lscala/collection/SeqLike;Lscala/Function1;)I
const #1051 = Method	#176.#1050;	//  scala/collection/SeqLike$class.findIndexOf:(Lscala/collection/SeqLike;Lscala/Function1;)I
const #1052 = Asciz	indexWhere;
const #1053 = NameAndType	#1052:#1031;//  indexWhere:(Lscala/collection/SeqLike;Lscala/Function1;I)I
const #1054 = Method	#176.#1053;	//  scala/collection/SeqLike$class.indexWhere:(Lscala/collection/SeqLike;Lscala/Function1;I)I
const #1055 = NameAndType	#1052:#911;//  indexWhere:(Lscala/collection/SeqLike;Lscala/Function1;)I
const #1056 = Method	#176.#1055;	//  scala/collection/SeqLike$class.indexWhere:(Lscala/collection/SeqLike;Lscala/Function1;)I
const #1057 = Asciz	prefixLength;
const #1058 = NameAndType	#1057:#911;//  prefixLength:(Lscala/collection/SeqLike;Lscala/Function1;)I
const #1059 = Method	#176.#1058;	//  scala/collection/SeqLike$class.prefixLength:(Lscala/collection/SeqLike;Lscala/Function1;)I
const #1060 = Asciz	segmentLength;
const #1061 = NameAndType	#1060:#1031;//  segmentLength:(Lscala/collection/SeqLike;Lscala/Function1;I)I
const #1062 = Method	#176.#1061;	//  scala/collection/SeqLike$class.segmentLength:(Lscala/collection/SeqLike;Lscala/Function1;I)I
const #1063 = Asciz	(Lscala/collection/SeqLike;I)Z;
const #1064 = NameAndType	#246:#1063;//  isDefinedAt:(Lscala/collection/SeqLike;I)Z
const #1065 = Method	#176.#1064;	//  scala/collection/SeqLike$class.isDefinedAt:(Lscala/collection/SeqLike;I)Z
const #1066 = Asciz	size;
const #1067 = NameAndType	#1066:#922;//  size:(Lscala/collection/SeqLike;)I
const #1068 = Method	#176.#1067;	//  scala/collection/SeqLike$class.size:(Lscala/collection/SeqLike;)I
const #1069 = Asciz	(Lscala/collection/SeqLike;Ljava/lang/Object;)Lscala/collection/Seq;;
const #1070 = NameAndType	#239:#1069;//  toCollection:(Lscala/collection/SeqLike;Ljava/lang/Object;)Lscala/collection/Seq;
const #1071 = Method	#176.#1070;	//  scala/collection/SeqLike$class.toCollection:(Lscala/collection/SeqLike;Ljava/lang/Object;)Lscala/collection/Seq;
const #1072 = NameAndType	#232:#936;//  thisCollection:(Lscala/collection/SeqLike;)Lscala/collection/Seq;
const #1073 = Method	#176.#1072;	//  scala/collection/SeqLike$class.thisCollection:(Lscala/collection/SeqLike;)Lscala/collection/Seq;
const #1074 = Asciz	(Lscala/collection/immutable/VectorPointer;III)V;
const #1075 = NameAndType	#450:#1074;//  gotoFreshPosWritable1:(Lscala/collection/immutable/VectorPointer;III)V
const #1076 = Method	#191.#1075;	//  scala/collection/immutable/VectorPointer$class.gotoFreshPosWritable1:(Lscala/collection/immutable/VectorPointer;III)V
const #1077 = NameAndType	#453:#1074;//  gotoFreshPosWritable0:(Lscala/collection/immutable/VectorPointer;III)V
const #1078 = Method	#191.#1077;	//  scala/collection/immutable/VectorPointer$class.gotoFreshPosWritable0:(Lscala/collection/immutable/VectorPointer;III)V
const #1079 = Asciz	(Lscala/collection/immutable/VectorPointer;[Ljava/lang/Object;II)[Ljava/lang/Object;;
const #1080 = NameAndType	#412:#1079;//  copyRange:(Lscala/collection/immutable/VectorPointer;[Ljava/lang/Object;II)[Ljava/lang/Object;
const #1081 = Method	#191.#1080;	//  scala/collection/immutable/VectorPointer$class.copyRange:(Lscala/collection/immutable/VectorPointer;[Ljava/lang/Object;II)[Ljava/lang/Object;
const #1082 = NameAndType	#458:#1074;//  gotoPosWritable1:(Lscala/collection/immutable/VectorPointer;III)V
const #1083 = Method	#191.#1082;	//  scala/collection/immutable/VectorPointer$class.gotoPosWritable1:(Lscala/collection/immutable/VectorPointer;III)V
const #1084 = Asciz	(Lscala/collection/immutable/VectorPointer;II)V;
const #1085 = NameAndType	#461:#1084;//  gotoPosWritable0:(Lscala/collection/immutable/VectorPointer;II)V
const #1086 = Method	#191.#1085;	//  scala/collection/immutable/VectorPointer$class.gotoPosWritable0:(Lscala/collection/immutable/VectorPointer;II)V
const #1087 = Asciz	(Lscala/collection/immutable/VectorPointer;I)V;
const #1088 = NameAndType	#519:#1087;//  stabilize:(Lscala/collection/immutable/VectorPointer;I)V
const #1089 = Method	#191.#1088;	//  scala/collection/immutable/VectorPointer$class.stabilize:(Lscala/collection/immutable/VectorPointer;I)V
const #1090 = Asciz	nullSlotAndCopy;
const #1091 = Asciz	(Lscala/collection/immutable/VectorPointer;[Ljava/lang/Object;I)[Ljava/lang/Object;;
const #1092 = NameAndType	#1090:#1091;//  nullSlotAndCopy:(Lscala/collection/immutable/VectorPointer;[Ljava/lang/Object;I)[Ljava/lang/Object;
const #1093 = Method	#191.#1092;	//  scala/collection/immutable/VectorPointer$class.nullSlotAndCopy:(Lscala/collection/immutable/VectorPointer;[Ljava/lang/Object;I)[Ljava/lang/Object;
const #1094 = Asciz	copyOf;
const #1095 = Asciz	([Ljava/lang/Object;)[Ljava/lang/Object;;
const #1096 = Asciz	(Lscala/collection/immutable/VectorPointer;[Ljava/lang/Object;)[Ljava/lang/Object;;
const #1097 = NameAndType	#1094:#1096;//  copyOf:(Lscala/collection/immutable/VectorPointer;[Ljava/lang/Object;)[Ljava/lang/Object;
const #1098 = Method	#191.#1097;	//  scala/collection/immutable/VectorPointer$class.copyOf:(Lscala/collection/immutable/VectorPointer;[Ljava/lang/Object;)[Ljava/lang/Object;
const #1099 = Asciz	a;
const #1100 = Asciz	gotoNextBlockStartWritable;
const #1101 = NameAndType	#1100:#1084;//  gotoNextBlockStartWritable:(Lscala/collection/immutable/VectorPointer;II)V
const #1102 = Method	#191.#1101;	//  scala/collection/immutable/VectorPointer$class.gotoNextBlockStartWritable:(Lscala/collection/immutable/VectorPointer;II)V
const #1103 = Asciz	gotoNextBlockStart;
const #1104 = NameAndType	#1103:#1084;//  gotoNextBlockStart:(Lscala/collection/immutable/VectorPointer;II)V
const #1105 = Method	#191.#1104;	//  scala/collection/immutable/VectorPointer$class.gotoNextBlockStart:(Lscala/collection/immutable/VectorPointer;II)V
const #1106 = NameAndType	#522:#1084;//  gotoPos:(Lscala/collection/immutable/VectorPointer;II)V
const #1107 = Method	#191.#1106;	//  scala/collection/immutable/VectorPointer$class.gotoPos:(Lscala/collection/immutable/VectorPointer;II)V
const #1108 = Asciz	(Lscala/collection/immutable/VectorPointer;II)Ljava/lang/Object;;
const #1109 = NameAndType	#495:#1108;//  getElem:(Lscala/collection/immutable/VectorPointer;II)Ljava/lang/Object;
const #1110 = Method	#191.#1109;	//  scala/collection/immutable/VectorPointer$class.getElem:(Lscala/collection/immutable/VectorPointer;II)Ljava/lang/Object;
const #1111 = Asciz	(Lscala/collection/immutable/VectorPointer;Lscala/collection/immutable/VectorPointer;I)V;
const #1112 = NameAndType	#279:#1111;//  initFrom:(Lscala/collection/immutable/VectorPointer;Lscala/collection/immutable/VectorPointer;I)V
const #1113 = Method	#191.#1112;	//  scala/collection/immutable/VectorPointer$class.initFrom:(Lscala/collection/immutable/VectorPointer;Lscala/collection/immutable/VectorPointer;I)V
const #1114 = Asciz	Lscala/collection/immutable/VectorPointer;;
const #1115 = Asciz	(Lscala/collection/immutable/VectorPointer;Lscala/collection/immutable/VectorPointer;)V;
const #1116 = NameAndType	#279:#1115;//  initFrom:(Lscala/collection/immutable/VectorPointer;Lscala/collection/immutable/VectorPointer;)V
const #1117 = Method	#191.#1116;	//  scala/collection/immutable/VectorPointer$class.initFrom:(Lscala/collection/immutable/VectorPointer;Lscala/collection/immutable/VectorPointer;)V
const #1118 = Asciz	<A:Ljava/lang/Object;>Ljava/lang/Object;Lscala/collection/immutable/Seq<TA;>;Lscala/collection/generic/GenericTraversableTemplate<TA;Lscala/collection/immutable/Vector;>;Lscala/collection/SeqLike<TA;Lscala/collection/immutable/Vector<TA;>;>;Lscala/collection/immutable/VectorPointer<TA;>;Lscala/ScalaObject;;
const #1119 = Asciz	ScalaSig;
const #1120 = Asciz	InnerClasses;
const #1121 = Asciz	scala/collection/immutable/Vector$$anon$1;
const #1122 = class	#1121;	//  scala/collection/immutable/Vector$$anon$1
const #1123 = Asciz	$anon$1;
const #1124 = Asciz	$anonfun$map0$1;
const #1125 = Asciz	scala/collection/TraversableLike$WithFilter;
const #1126 = class	#1125;	//  scala/collection/TraversableLike$WithFilter
const #1127 = Asciz	scala/collection/TraversableLike;
const #1128 = class	#1127;	//  scala/collection/TraversableLike
const #1129 = Asciz	WithFilter;
const #1130 = Asciz	scala/collection/generic/TraversableFactory$GenericCanBuildFrom;
const #1131 = class	#1130;	//  scala/collection/generic/TraversableFactory$GenericCanBuildFrom
const #1132 = Asciz	scala/collection/generic/TraversableFactory;
const #1133 = class	#1132;	//  scala/collection/generic/TraversableFactory
const #1134 = Asciz	GenericCanBuildFrom;
const #1135 = Asciz	scala/collection/immutable/Seq;
const #1136 = class	#1135;	//  scala/collection/immutable/Seq
const #1137 = Asciz	scala/collection/generic/GenericTraversableTemplate;
const #1138 = class	#1137;	//  scala/collection/generic/GenericTraversableTemplate
const #1139 = Asciz	scala/ScalaObject;
const #1140 = class	#1139;	//  scala/ScalaObject
const #1141 = Asciz	java/io/Serializable;
const #1142 = class	#1141;	//  java/io/Serializable

{
public final int focus;

public final int endIndex;

public final int startIndex;

public static final scala.collection.immutable.Vector empty();
  Code:
   Stack=1, Locals=0, Args_size=0
   0:	getstatic	#11; //Field scala/collection/immutable/Vector$.MODULE$:Lscala/collection/immutable/Vector$;
   3:	invokevirtual	#13; //Method scala/collection/immutable/Vector$.empty:()Lscala/collection/immutable/Vector;
   6:	areturn
  Signature: length = 0x2
   00 0E 

public static final scala.collection.immutable.Vector NIL();
  Code:
   Stack=1, Locals=0, Args_size=0
   0:	getstatic	#11; //Field scala/collection/immutable/Vector$.MODULE$:Lscala/collection/immutable/Vector$;
   3:	invokevirtual	#18; //Method scala/collection/immutable/Vector$.NIL:()Lscala/collection/immutable/Vector;
   6:	areturn
  Signature: length = 0x2
   00 13 

public static final scala.collection.generic.CanBuildFrom canBuildFrom();
  Code:
   Stack=1, Locals=0, Args_size=0
   0:	getstatic	#11; //Field scala/collection/immutable/Vector$.MODULE$:Lscala/collection/immutable/Vector$;
   3:	invokevirtual	#23; //Method scala/collection/immutable/Vector$.canBuildFrom:()Lscala/collection/generic/CanBuildFrom;
   6:	areturn
  Signature: length = 0x2
   00 18 

public static final scala.collection.generic.TraversableFactory$GenericCanBuildFrom BF();
  Code:
   Stack=1, Locals=0, Args_size=0
   0:	getstatic	#11; //Field scala/collection/immutable/Vector$.MODULE$:Lscala/collection/immutable/Vector$;
   3:	invokevirtual	#28; //Method scala/collection/immutable/Vector$.BF:()Lscala/collection/generic/TraversableFactory$GenericCanBuildFrom;
   6:	areturn
  Signature: length = 0x2
   00 1D 

public static final scala.Some unapplySeq(scala.collection.Seq);
  Code:
   Stack=2, Locals=1, Args_size=1
   0:	getstatic	#11; //Field scala/collection/immutable/Vector$.MODULE$:Lscala/collection/immutable/Vector$;
   3:	aload_0
   4:	invokevirtual	#33; //Method scala/collection/immutable/Vector$.unapplySeq:(Lscala/collection/Seq;)Lscala/Some;
   7:	areturn
  Signature: length = 0x2
   00 22 

public static final scala.collection.Traversable iterate(java.lang.Object, int, scala.Function1);
  Code:
   Stack=4, Locals=3, Args_size=3
   0:	getstatic	#11; //Field scala/collection/immutable/Vector$.MODULE$:Lscala/collection/immutable/Vector$;
   3:	aload_0
   4:	iload_1
   5:	aload_2
   6:	invokevirtual	#38; //Method scala/collection/immutable/Vector$.iterate:(Ljava/lang/Object;ILscala/Function1;)Lscala/collection/Traversable;
   9:	areturn
  Signature: length = 0x2
   00 27 

public static final scala.collection.Traversable range(int, int, int);
  Code:
   Stack=4, Locals=3, Args_size=3
   0:	getstatic	#11; //Field scala/collection/immutable/Vector$.MODULE$:Lscala/collection/immutable/Vector$;
   3:	iload_0
   4:	iload_1
   5:	iload_2
   6:	invokevirtual	#43; //Method scala/collection/immutable/Vector$.range:(III)Lscala/collection/Traversable;
   9:	areturn
  Signature: length = 0x2
   00 2C 

public static final scala.collection.Traversable range(int, int);
  Code:
   Stack=3, Locals=2, Args_size=2
   0:	getstatic	#11; //Field scala/collection/immutable/Vector$.MODULE$:Lscala/collection/immutable/Vector$;
   3:	iload_0
   4:	iload_1
   5:	invokevirtual	#47; //Method scala/collection/immutable/Vector$.range:(II)Lscala/collection/Traversable;
   8:	areturn
  Signature: length = 0x2
   00 30 

public static final scala.collection.Traversable tabulate(int, int, int, int, int, scala.Function5);
  Code:
   Stack=7, Locals=6, Args_size=6
   0:	getstatic	#11; //Field scala/collection/immutable/Vector$.MODULE$:Lscala/collection/immutable/Vector$;
   3:	iload_0
   4:	iload_1
   5:	iload_2
   6:	iload_3
   7:	iload	4
   9:	aload	5
   11:	invokevirtual	#52; //Method scala/collection/immutable/Vector$.tabulate:(IIIIILscala/Function5;)Lscala/collection/Traversable;
   14:	areturn
  Signature: length = 0x2
   00 35 

public static final scala.collection.Traversable tabulate(int, int, int, int, scala.Function4);
  Code:
   Stack=6, Locals=5, Args_size=5
   0:	getstatic	#11; //Field scala/collection/immutable/Vector$.MODULE$:Lscala/collection/immutable/Vector$;
   3:	iload_0
   4:	iload_1
   5:	iload_2
   6:	iload_3
   7:	aload	4
   9:	invokevirtual	#56; //Method scala/collection/immutable/Vector$.tabulate:(IIIILscala/Function4;)Lscala/collection/Traversable;
   12:	areturn
  Signature: length = 0x2
   00 39 

public static final scala.collection.Traversable tabulate(int, int, int, scala.Function3);
  Code:
   Stack=5, Locals=4, Args_size=4
   0:	getstatic	#11; //Field scala/collection/immutable/Vector$.MODULE$:Lscala/collection/immutable/Vector$;
   3:	iload_0
   4:	iload_1
   5:	iload_2
   6:	aload_3
   7:	invokevirtual	#60; //Method scala/collection/immutable/Vector$.tabulate:(IIILscala/Function3;)Lscala/collection/Traversable;
   10:	areturn
  Signature: length = 0x2
   00 3D 

public static final scala.collection.Traversable tabulate(int, int, scala.Function2);
  Code:
   Stack=4, Locals=3, Args_size=3
   0:	getstatic	#11; //Field scala/collection/immutable/Vector$.MODULE$:Lscala/collection/immutable/Vector$;
   3:	iload_0
   4:	iload_1
   5:	aload_2
   6:	invokevirtual	#64; //Method scala/collection/immutable/Vector$.tabulate:(IILscala/Function2;)Lscala/collection/Traversable;
   9:	areturn
  Signature: length = 0x2
   00 41 

public static final scala.collection.Traversable tabulate(int, scala.Function1);
  Code:
   Stack=3, Locals=2, Args_size=2
   0:	getstatic	#11; //Field scala/collection/immutable/Vector$.MODULE$:Lscala/collection/immutable/Vector$;
   3:	iload_0
   4:	aload_1
   5:	invokevirtual	#68; //Method scala/collection/immutable/Vector$.tabulate:(ILscala/Function1;)Lscala/collection/Traversable;
   8:	areturn
  Signature: length = 0x2
   00 45 

public static final scala.collection.Traversable fill(int, int, int, int, int, scala.Function0);
  Code:
   Stack=7, Locals=6, Args_size=6
   0:	getstatic	#11; //Field scala/collection/immutable/Vector$.MODULE$:Lscala/collection/immutable/Vector$;
   3:	iload_0
   4:	iload_1
   5:	iload_2
   6:	iload_3
   7:	iload	4
   9:	aload	5
   11:	invokevirtual	#73; //Method scala/collection/immutable/Vector$.fill:(IIIIILscala/Function0;)Lscala/collection/Traversable;
   14:	areturn
  Signature: length = 0x2
   00 4A 

public static final scala.collection.Traversable fill(int, int, int, int, scala.Function0);
  Code:
   Stack=6, Locals=5, Args_size=5
   0:	getstatic	#11; //Field scala/collection/immutable/Vector$.MODULE$:Lscala/collection/immutable/Vector$;
   3:	iload_0
   4:	iload_1
   5:	iload_2
   6:	iload_3
   7:	aload	4
   9:	invokevirtual	#77; //Method scala/collection/immutable/Vector$.fill:(IIIILscala/Function0;)Lscala/collection/Traversable;
   12:	areturn
  Signature: length = 0x2
   00 4E 

public static final scala.collection.Traversable fill(int, int, int, scala.Function0);
  Code:
   Stack=5, Locals=4, Args_size=4
   0:	getstatic	#11; //Field scala/collection/immutable/Vector$.MODULE$:Lscala/collection/immutable/Vector$;
   3:	iload_0
   4:	iload_1
   5:	iload_2
   6:	aload_3
   7:	invokevirtual	#81; //Method scala/collection/immutable/Vector$.fill:(IIILscala/Function0;)Lscala/collection/Traversable;
   10:	areturn
  Signature: length = 0x2
   00 52 

public static final scala.collection.Traversable fill(int, int, scala.Function0);
  Code:
   Stack=4, Locals=3, Args_size=3
   0:	getstatic	#11; //Field scala/collection/immutable/Vector$.MODULE$:Lscala/collection/immutable/Vector$;
   3:	iload_0
   4:	iload_1
   5:	aload_2
   6:	invokevirtual	#85; //Method scala/collection/immutable/Vector$.fill:(IILscala/Function0;)Lscala/collection/Traversable;
   9:	areturn
  Signature: length = 0x2
   00 56 

public static final scala.collection.Traversable fill(int, scala.Function0);
  Code:
   Stack=3, Locals=2, Args_size=2
   0:	getstatic	#11; //Field scala/collection/immutable/Vector$.MODULE$:Lscala/collection/immutable/Vector$;
   3:	iload_0
   4:	aload_1
   5:	invokevirtual	#89; //Method scala/collection/immutable/Vector$.fill:(ILscala/Function0;)Lscala/collection/Traversable;
   8:	areturn
  Signature: length = 0x2
   00 5A 

public static final scala.collection.Traversable concat(scala.collection.Seq);
  Code:
   Stack=2, Locals=1, Args_size=1
   0:	getstatic	#11; //Field scala/collection/immutable/Vector$.MODULE$:Lscala/collection/immutable/Vector$;
   3:	aload_0
   4:	invokevirtual	#94; //Method scala/collection/immutable/Vector$.concat:(Lscala/collection/Seq;)Lscala/collection/Traversable;
   7:	areturn
  Signature: length = 0x2
   00 5F 

public static final scala.collection.Traversable empty();
  Code:
   Stack=1, Locals=0, Args_size=0
   0:	getstatic	#11; //Field scala/collection/immutable/Vector$.MODULE$:Lscala/collection/immutable/Vector$;
   3:	invokevirtual	#98; //Method scala/collection/immutable/Vector$.empty:()Lscala/collection/Traversable;
   6:	areturn
  Signature: length = 0x2
   00 0E 

public scala.collection.immutable.Vector(int, int, int);
  Code:
   Stack=2, Locals=4, Args_size=4
   0:	aload_0
   1:	iload_1
   2:	putfield	#119; //Field startIndex:I
   5:	aload_0
   6:	iload_2
   7:	putfield	#121; //Field endIndex:I
   10:	aload_0
   11:	iload_3
   12:	putfield	#123; //Field focus:I
   15:	aload_0
   16:	invokespecial	#128; //Method java/lang/Object."<init>":()V
   19:	aload_0
   20:	invokestatic	#134; //Method scala/collection/TraversableLike$class.$init$:(Lscala/collection/TraversableLike;)V
   23:	aload_0
   24:	invokestatic	#139; //Method scala/collection/generic/GenericTraversableTemplate$class.$init$:(Lscala/collection/generic/GenericTraversableTemplate;)V
   27:	aload_0
   28:	invokestatic	#144; //Method scala/collection/Traversable$class.$init$:(Lscala/collection/Traversable;)V
   31:	aload_0
   32:	invokestatic	#149; //Method scala/collection/immutable/Traversable$class.$init$:(Lscala/collection/immutable/Traversable;)V
   35:	aload_0
   36:	invokestatic	#154; //Method scala/collection/IterableLike$class.$init$:(Lscala/collection/IterableLike;)V
   39:	aload_0
   40:	invokestatic	#159; //Method scala/collection/Iterable$class.$init$:(Lscala/collection/Iterable;)V
   43:	aload_0
   44:	invokestatic	#164; //Method scala/collection/immutable/Iterable$class.$init$:(Lscala/collection/immutable/Iterable;)V
   47:	aload_0
   48:	invokestatic	#169; //Method scala/Function1$class.$init$:(Lscala/Function1;)V
   51:	aload_0
   52:	invokestatic	#174; //Method scala/PartialFunction$class.$init$:(Lscala/PartialFunction;)V
   55:	aload_0
   56:	invokestatic	#179; //Method scala/collection/SeqLike$class.$init$:(Lscala/collection/SeqLike;)V
   59:	aload_0
   60:	invokestatic	#184; //Method scala/collection/Seq$class.$init$:(Lscala/collection/Seq;)V
   63:	aload_0
   64:	invokestatic	#189; //Method scala/collection/immutable/Seq$class.$init$:(Lscala/collection/immutable/Seq;)V
   67:	aload_0
   68:	invokestatic	#194; //Method scala/collection/immutable/VectorPointer$class.$init$:(Lscala/collection/immutable/VectorPointer;)V
   71:	aload_0
   72:	iconst_0
   73:	putfield	#196; //Field dirty:Z
   76:	return
  LineNumberTable: 
   line 36: 0
   line 48: 71

  LocalVariableTable: 
   Start  Length  Slot  Name   Signature
   0      77      0    this       Lscala/collection/immutable/Vector;
   0      77      1    startIndex       I
   0      77      2    endIndex       I
   0      77      3    focus       I

  Signature: length = 0x2
   00 72 

public scala.collection.Iterator iterator();
  Code:
   Stack=1, Locals=1, Args_size=1
   0:	aload_0
   1:	invokevirtual	#204; //Method iterator:()Lscala/collection/immutable/VectorIterator;
   4:	areturn
  LineNumberTable: 
   line 36: 0


public java.lang.Object apply(java.lang.Object);
  Code:
   Stack=2, Locals=2, Args_size=2
   0:	aload_0
   1:	aload_1
   2:	invokestatic	#212; //Method scala/runtime/BoxesRunTime.unboxToInt:(Ljava/lang/Object;)I
   5:	invokevirtual	#215; //Method apply:(I)Ljava/lang/Object;
   8:	areturn
  LineNumberTable: 
   line 36: 0

  LocalVariableTable: 
   Start  Length  Slot  Name   Signature
   0      9      0    this       Lscala/collection/immutable/Vector;
   0      9      1    v1       Ljava/lang/Object;


public java.lang.Object take(int);
  Code:
   Stack=2, Locals=2, Args_size=2
   0:	aload_0
   1:	iload_1
   2:	invokevirtual	#221; //Method take:(I)Lscala/collection/immutable/Vector;
   5:	areturn
  LineNumberTable: 
   line 36: 0

  LocalVariableTable: 
   Start  Length  Slot  Name   Signature
   0      6      0    this       Lscala/collection/immutable/Vector;
   0      6      1    n       I


public java.lang.Object drop(int);
  Code:
   Stack=2, Locals=2, Args_size=2
   0:	aload_0
   1:	iload_1
   2:	invokevirtual	#225; //Method drop:(I)Lscala/collection/immutable/Vector;
   5:	areturn
  LineNumberTable: 
   line 36: 0

  LocalVariableTable: 
   Start  Length  Slot  Name   Signature
   0      6      0    this       Lscala/collection/immutable/Vector;
   0      6      1    n       I


public java.lang.Object takeRight(int);
  Code:
   Stack=2, Locals=2, Args_size=2
   0:	aload_0
   1:	iload_1
   2:	invokevirtual	#228; //Method takeRight:(I)Lscala/collection/immutable/Vector;
   5:	areturn
  LineNumberTable: 
   line 36: 0

  LocalVariableTable: 
   Start  Length  Slot  Name   Signature
   0      6      0    this       Lscala/collection/immutable/Vector;
   0      6      1    n       I


public java.lang.Object dropRight(int);
  Code:
   Stack=2, Locals=2, Args_size=2
   0:	aload_0
   1:	iload_1
   2:	invokevirtual	#231; //Method dropRight:(I)Lscala/collection/immutable/Vector;
   5:	areturn
  LineNumberTable: 
   line 36: 0

  LocalVariableTable: 
   Start  Length  Slot  Name   Signature
   0      6      0    this       Lscala/collection/immutable/Vector;
   0      6      1    n       I


public scala.collection.Iterable thisCollection();
  Code:
   Stack=1, Locals=1, Args_size=1
   0:	aload_0
   1:	invokeinterface	#238,  1; //InterfaceMethod scala/collection/SeqLike.thisCollection:()Lscala/collection/Seq;
   6:	areturn
  LineNumberTable: 
   line 36: 0


public scala.collection.Traversable thisCollection();
  Code:
   Stack=1, Locals=1, Args_size=1
   0:	aload_0
   1:	invokeinterface	#238,  1; //InterfaceMethod scala/collection/SeqLike.thisCollection:()Lscala/collection/Seq;
   6:	areturn
  LineNumberTable: 
   line 36: 0


public scala.collection.Iterable toCollection(java.lang.Object);
  Code:
   Stack=2, Locals=2, Args_size=2
   0:	aload_0
   1:	aload_1
   2:	invokeinterface	#243,  2; //InterfaceMethod scala/collection/SeqLike.toCollection:(Ljava/lang/Object;)Lscala/collection/Seq;
   7:	areturn
  LineNumberTable: 
   line 36: 0

  LocalVariableTable: 
   Start  Length  Slot  Name   Signature
   0      8      0    this       Lscala/collection/immutable/Vector;
   0      8      1    repr       Ljava/lang/Object;


public scala.collection.Traversable toCollection(java.lang.Object);
  Code:
   Stack=2, Locals=2, Args_size=2
   0:	aload_0
   1:	aload_1
   2:	invokeinterface	#243,  2; //InterfaceMethod scala/collection/SeqLike.toCollection:(Ljava/lang/Object;)Lscala/collection/Seq;
   7:	areturn
  LineNumberTable: 
   line 36: 0

  LocalVariableTable: 
   Start  Length  Slot  Name   Signature
   0      8      0    this       Lscala/collection/immutable/Vector;
   0      8      1    repr       Ljava/lang/Object;


public boolean isDefinedAt(java.lang.Object);
  Code:
   Stack=2, Locals=2, Args_size=2
   0:	aload_0
   1:	aload_1
   2:	invokestatic	#212; //Method scala/runtime/BoxesRunTime.unboxToInt:(Ljava/lang/Object;)I
   5:	invokeinterface	#250,  2; //InterfaceMethod scala/collection/SeqLike.isDefinedAt:(I)Z
   10:	ireturn
  LineNumberTable: 
   line 36: 0

  LocalVariableTable: 
   Start  Length  Slot  Name   Signature
   0      11      0    this       Lscala/collection/immutable/Vector;
   0      11      1    x       Ljava/lang/Object;


public scala.collection.IterableView view(int, int);
  Code:
   Stack=3, Locals=3, Args_size=3
   0:	aload_0
   1:	iload_1
   2:	iload_2
   3:	invokeinterface	#256,  3; //InterfaceMethod scala/collection/SeqLike.view:(II)Lscala/collection/SeqView;
   8:	areturn
  LineNumberTable: 
   line 36: 0

  LocalVariableTable: 
   Start  Length  Slot  Name   Signature
   0      9      0    this       Lscala/collection/immutable/Vector;
   0      9      1    from       I
   0      9      2    until       I


public scala.collection.TraversableView view(int, int);
  Code:
   Stack=3, Locals=3, Args_size=3
   0:	aload_0
   1:	iload_1
   2:	iload_2
   3:	invokeinterface	#256,  3; //InterfaceMethod scala/collection/SeqLike.view:(II)Lscala/collection/SeqView;
   8:	areturn
  LineNumberTable: 
   line 36: 0

  LocalVariableTable: 
   Start  Length  Slot  Name   Signature
   0      9      0    this       Lscala/collection/immutable/Vector;
   0      9      1    from       I
   0      9      2    until       I


public scala.Function1 andThen(scala.Function1);
  Code:
   Stack=2, Locals=2, Args_size=2
   0:	aload_0
   1:	aload_1
   2:	invokeinterface	#266,  2; //InterfaceMethod scala/PartialFunction.andThen:(Lscala/Function1;)Lscala/PartialFunction;
   7:	areturn
  LineNumberTable: 
   line 36: 0

  LocalVariableTable: 
   Start  Length  Slot  Name   Signature
   0      8      0    this       Lscala/collection/immutable/Vector;
   0      8      1    g       Lscala/Function1;


public java.lang.Object[] copyRight(java.lang.Object[], int);
  Code:
   Stack=5, Locals=5, Args_size=3
   0:	aload_1
   1:	arraylength
   2:	anewarray	#125; //class java/lang/Object
   5:	astore	4
   7:	aload	4
   9:	arraylength
   10:	iload_2
   11:	isub
   12:	istore_3
   13:	aload_1
   14:	iload_2
   15:	aload	4
   17:	iload_2
   18:	iload_3
   19:	invokestatic	#333; //Method java/lang/System.arraycopy:(Ljava/lang/Object;ILjava/lang/Object;II)V
   22:	aload	4
   24:	areturn
  LineNumberTable: 
   line 380: 0
   line 381: 7
   line 382: 22

  LocalVariableTable: 
   Start  Length  Slot  Name   Signature
   0      25      0    this       Lscala/collection/immutable/Vector;
   0      25      1    array       [Ljava/lang/Object;
   0      25      2    left       I
   7      17      4    a2       [Ljava/lang/Object;


public java.lang.Object[] copyLeft(java.lang.Object[], int);
  Code:
   Stack=5, Locals=6, Args_size=3
   0:	aload_1
   1:	arraylength
   2:	anewarray	#125; //class java/lang/Object
   5:	astore	5
   7:	iconst_0
   8:	iconst_0
   9:	istore	4
   11:	istore_3
   12:	aload_1
   13:	iload_3
   14:	aload	5
   16:	iload	4
   18:	iload_2
   19:	invokestatic	#333; //Method java/lang/System.arraycopy:(Ljava/lang/Object;ILjava/lang/Object;II)V
   22:	aload	5
   24:	areturn
  LineNumberTable: 
   line 375: 0
   line 376: 7
   line 377: 22

  LocalVariableTable: 
   Start  Length  Slot  Name   Signature
   0      25      0    this       Lscala/collection/immutable/Vector;
   0      25      1    array       [Ljava/lang/Object;
   0      25      2    right       I
   7      17      5    a2       [Ljava/lang/Object;


public void zeroRight(java.lang.Object[], int);
  Code:
   Stack=3, Locals=4, Args_size=3
   0:	iload_2
   1:	istore_3
   2:	iload_3
   3:	aload_1
   4:	arraylength
   5:	if_icmpge	19
   8:	aload_1
   9:	iload_3
   10:	aconst_null
   11:	aastore
   12:	iload_3
   13:	iconst_1
   14:	iadd
   15:	istore_3
   16:	goto	2
   19:	return
  LineNumberTable: 
   line 369: 0
   line 368: 19

  LocalVariableTable: 
   Start  Length  Slot  Name   Signature
   0      20      0    this       Lscala/collection/immutable/Vector;
   0      20      1    array       [Ljava/lang/Object;
   0      20      2    index       I
   2      18      3    i       I


public void zeroLeft(java.lang.Object[], int);
  Code:
   Stack=3, Locals=4, Args_size=3
   0:	iconst_0
   1:	istore_3
   2:	iload_3
   3:	iload_2
   4:	if_icmpge	18
   7:	aload_1
   8:	iload_3
   9:	aconst_null
   10:	aastore
   11:	iload_3
   12:	iconst_1
   13:	iadd
   14:	istore_3
   15:	goto	2
   18:	return
  LineNumberTable: 
   line 365: 0
   line 364: 18

  LocalVariableTable: 
   Start  Length  Slot  Name   Signature
   0      19      0    this       Lscala/collection/immutable/Vector;
   0      19      1    array       [Ljava/lang/Object;
   0      19      2    index       I
   2      17      3    i       I


public scala.collection.immutable.Vector appendBack(java.lang.Object);
  Code:
   Stack=5, Locals=20, Args_size=2
   0:	aload_0
   1:	getfield	#121; //Field endIndex:I
   4:	aload_0
   5:	getfield	#119; //Field startIndex:I
   8:	if_icmpeq	480
   11:	aload_0
   12:	getfield	#121; //Field endIndex:I
   15:	ldc_w	#270; //int 31
   18:	iconst_m1
   19:	ixor
   20:	iand
   21:	istore	15
   23:	aload_0
   24:	getfield	#121; //Field endIndex:I
   27:	ldc_w	#270; //int 31
   30:	iand
   31:	istore	16
   33:	aload_0
   34:	getfield	#121; //Field endIndex:I
   37:	iload	15
   39:	if_icmpeq	108
   42:	new	#117; //class scala/collection/immutable/Vector
   45:	dup
   46:	aload_0
   47:	getfield	#119; //Field startIndex:I
   50:	aload_0
   51:	getfield	#121; //Field endIndex:I
   54:	iconst_1
   55:	iadd
   56:	iload	15
   58:	invokespecial	#276; //Method "<init>":(III)V
   61:	astore_3
   62:	aload_3
   63:	aload_0
   64:	invokeinterface	#281,  2; //InterfaceMethod scala/collection/immutable/VectorPointer.initFrom:(Lscala/collection/immutable/VectorPointer;)V
   69:	aload_0
   70:	getfield	#196; //Field dirty:Z
   73:	istore_2
   74:	aload_3
   75:	iload_2
   76:	putfield	#196; //Field dirty:Z
   79:	aload_3
   80:	aload_0
   81:	getfield	#123; //Field focus:I
   84:	iload	15
   86:	aload_0
   87:	getfield	#123; //Field focus:I
   90:	iload	15
   92:	ixor
   93:	invokespecial	#291; //Method gotoPosWritable:(III)V
   96:	aload_3
   97:	getfield	#321; //Field display0:[Ljava/lang/Object;
   100:	iload	16
   102:	aload_1
   103:	aastore
   104:	aload_3
   105:	goto	524
   108:	aload_0
   109:	getfield	#119; //Field startIndex:I
   112:	iconst_1
   113:	iconst_5
   114:	aload_0
   115:	getfield	#383; //Field depth:I
   118:	iconst_1
   119:	isub
   120:	imul
   121:	ishl
   122:	iconst_1
   123:	isub
   124:	iconst_m1
   125:	ixor
   126:	iand
   127:	istore	12
   129:	aload_0
   130:	getfield	#119; //Field startIndex:I
   133:	iconst_5
   134:	aload_0
   135:	getfield	#383; //Field depth:I
   138:	iconst_1
   139:	isub
   140:	imul
   141:	iushr
   142:	istore	9
   144:	iload	12
   146:	iconst_0
   147:	if_icmpeq	381
   150:	aload_0
   151:	invokestatic	#423; //Method scala/collection/immutable/VectorPointer$class.debug:(Lscala/collection/immutable/VectorPointer;)V
   154:	aload_0
   155:	getfield	#383; //Field depth:I
   158:	iconst_1
   159:	if_icmple	272
   162:	iload	15
   164:	iload	12
   166:	isub
   167:	istore	6
   169:	aload_0
   170:	getfield	#123; //Field focus:I
   173:	iload	12
   175:	isub
   176:	istore	5
   178:	new	#117; //class scala/collection/immutable/Vector
   181:	dup
   182:	aload_0
   183:	getfield	#119; //Field startIndex:I
   186:	iload	12
   188:	isub
   189:	aload_0
   190:	getfield	#121; //Field endIndex:I
   193:	iconst_1
   194:	iadd
   195:	iload	12
   197:	isub
   198:	iload	6
   200:	invokespecial	#276; //Method "<init>":(III)V
   203:	astore	7
   205:	aload	7
   207:	aload_0
   208:	invokeinterface	#281,  2; //InterfaceMethod scala/collection/immutable/VectorPointer.initFrom:(Lscala/collection/immutable/VectorPointer;)V
   213:	aload_0
   214:	getfield	#196; //Field dirty:Z
   217:	istore	4
   219:	aload	7
   221:	iload	4
   223:	putfield	#196; //Field dirty:Z
   226:	aload	7
   228:	iload	9
   230:	iconst_0
   231:	invokespecial	#425; //Method shiftTopLevel:(II)V
   234:	aload	7
   236:	invokestatic	#423; //Method scala/collection/immutable/VectorPointer$class.debug:(Lscala/collection/immutable/VectorPointer;)V
   239:	aload	7
   241:	iload	5
   243:	iload	6
   245:	iload	5
   247:	iload	6
   249:	ixor
   250:	invokespecial	#428; //Method gotoFreshPosWritable:(III)V
   253:	aload	7
   255:	getfield	#321; //Field display0:[Ljava/lang/Object;
   258:	iload	16
   260:	aload_1
   261:	aastore
   262:	aload	7
   264:	invokestatic	#423; //Method scala/collection/immutable/VectorPointer$class.debug:(Lscala/collection/immutable/VectorPointer;)V
   267:	aload	7
   269:	goto	524
   272:	iload	15
   274:	ldc_w	#310; //int 32
   277:	isub
   278:	istore	11
   280:	aload_0
   281:	getfield	#123; //Field focus:I
   284:	istore	10
   286:	new	#117; //class scala/collection/immutable/Vector
   289:	dup
   290:	aload_0
   291:	getfield	#119; //Field startIndex:I
   294:	iload	12
   296:	isub
   297:	aload_0
   298:	getfield	#121; //Field endIndex:I
   301:	iconst_1
   302:	iadd
   303:	iload	12
   305:	isub
   306:	iload	11
   308:	invokespecial	#276; //Method "<init>":(III)V
   311:	astore	13
   313:	aload	13
   315:	aload_0
   316:	invokeinterface	#281,  2; //InterfaceMethod scala/collection/immutable/VectorPointer.initFrom:(Lscala/collection/immutable/VectorPointer;)V
   321:	aload_0
   322:	getfield	#196; //Field dirty:Z
   325:	istore	8
   327:	aload	13
   329:	iload	8
   331:	putfield	#196; //Field dirty:Z
   334:	aload	13
   336:	iload	9
   338:	iconst_0
   339:	invokespecial	#425; //Method shiftTopLevel:(II)V
   342:	aload	13
   344:	iload	10
   346:	iload	11
   348:	iload	10
   350:	iload	11
   352:	ixor
   353:	invokespecial	#291; //Method gotoPosWritable:(III)V
   356:	aload	13
   358:	getfield	#321; //Field display0:[Ljava/lang/Object;
   361:	ldc_w	#310; //int 32
   364:	iload	12
   366:	isub
   367:	aload_1
   368:	aastore
   369:	aload	13
   371:	invokeinterface	#430,  1; //InterfaceMethod scala/collection/immutable/VectorPointer.debug:()V
   376:	aload	13
   378:	goto	524
   381:	aload_0
   382:	getfield	#123; //Field focus:I
   385:	istore	14
   387:	new	#117; //class scala/collection/immutable/Vector
   390:	dup
   391:	aload_0
   392:	getfield	#119; //Field startIndex:I
   395:	aload_0
   396:	getfield	#121; //Field endIndex:I
   399:	iconst_1
   400:	iadd
   401:	iload	15
   403:	invokespecial	#276; //Method "<init>":(III)V
   406:	astore	17
   408:	aload	17
   410:	aload_0
   411:	invokeinterface	#281,  2; //InterfaceMethod scala/collection/immutable/VectorPointer.initFrom:(Lscala/collection/immutable/VectorPointer;)V
   416:	aload	17
   418:	aload_0
   419:	invokevirtual	#284; //Method dirty:()Z
   422:	invokevirtual	#288; //Method dirty_$eq:(Z)V
   425:	aload	17
   427:	iload	14
   429:	iload	15
   431:	iload	14
   433:	iload	15
   435:	ixor
   436:	invokespecial	#428; //Method gotoFreshPosWritable:(III)V
   439:	aload	17
   441:	invokeinterface	#339,  1; //InterfaceMethod scala/collection/immutable/VectorPointer.display0:()[Ljava/lang/Object;
   446:	iload	16
   448:	aload_1
   449:	aastore
   450:	aload	17
   452:	invokeinterface	#433,  1; //InterfaceMethod scala/collection/immutable/VectorPointer.depth:()I
   457:	aload_0
   458:	invokeinterface	#433,  1; //InterfaceMethod scala/collection/immutable/VectorPointer.depth:()I
   463:	iconst_1
   464:	iadd
   465:	if_icmpne	475
   468:	aload	17
   470:	invokeinterface	#430,  1; //InterfaceMethod scala/collection/immutable/VectorPointer.debug:()V
   475:	aload	17
   477:	goto	524
   480:	ldc_w	#310; //int 32
   483:	anewarray	#125; //class java/lang/Object
   486:	astore	18
   488:	aload	18
   490:	iconst_0
   491:	aload_1
   492:	aastore
   493:	new	#117; //class scala/collection/immutable/Vector
   496:	dup
   497:	iconst_0
   498:	iconst_1
   499:	iconst_0
   500:	invokespecial	#276; //Method "<init>":(III)V
   503:	astore	19
   505:	aload	19
   507:	iconst_1
   508:	invokeinterface	#436,  2; //InterfaceMethod scala/collection/immutable/VectorPointer.depth_$eq:(I)V
   513:	aload	19
   515:	aload	18
   517:	invokeinterface	#439,  2; //InterfaceMethod scala/collection/immutable/VectorPointer.display0_$eq:([Ljava/lang/Object;)V
   522:	aload	19
   524:	areturn
  LineNumberTable: 
   line 269: 0
   line 270: 11
   line 271: 23
   line 273: 33
   line 275: 42
   line 280: 62
   line 276: 63
   line 277: 69
   line 278: 79
   line 279: 96
   line 280: 104
   line 282: 108
   line 283: 129
   line 287: 144
   line 288: 150
   line 290: 154
   line 291: 162
   line 292: 169
   line 293: 178
   line 302: 205
   line 294: 207
   line 295: 213
   line 296: 226
   line 297: 234
   line 298: 239
   line 299: 253
   line 300: 262
   line 302: 267
   line 304: 272
   line 305: 280
   line 310: 286
   line 317: 313
   line 311: 315
   line 312: 321
   line 313: 334
   line 314: 342
   line 315: 356
   line 316: 369
   line 317: 376
   line 290: 378
   line 321: 381
   line 323: 387
   line 329: 408
   line 324: 410
   line 325: 416
   line 326: 425
   line 327: 439
   line 329: 450
   line 331: 468
   line 333: 475
   line 287: 477
   line 337: 480
   line 338: 488
   line 339: 493
   line 342: 505
   line 340: 507
   line 341: 513
   line 342: 522
   line 269: 524

  LocalVariableTable: 
   Start  Length  Slot  Name   Signature
   0      525      0    this       Lscala/collection/immutable/Vector;
   0      525      1    value       Ljava/lang/Object;
   62      43      3    s       Lscala/collection/immutable/Vector;
   178      91      5    newFocus       I
   169      100      6    newBlockIndex       I
   205      64      7    s       Lscala/collection/immutable/Vector;
   144      336      9    shiftBlocks       I
   286      92      10    newFocus       I
   280      98      11    newBlockIndex       I
   129      351      12    shift       I
   313      65      13    s       Lscala/collection/immutable/Vector;
   387      90      14    newFocus       I
   23      457      15    blockIndex       I
   33      447      16    lo       I
   408      69      17    s       Lscala/collection/immutable/Vector;
   488      36      18    elems       [Ljava/lang/Object;
   505      19      19    s       Lscala/collection/immutable/Vector;

  Signature: length = 0x2
   01 FFFFFFBE 

public scala.collection.immutable.Vector appendFront(java.lang.Object);
  Code:
   Stack=5, Locals=25, Args_size=2
   0:	aload_0
   1:	getfield	#121; //Field endIndex:I
   4:	aload_0
   5:	getfield	#119; //Field startIndex:I
   8:	if_icmpeq	602
   11:	aload_0
   12:	getfield	#119; //Field startIndex:I
   15:	iconst_1
   16:	isub
   17:	ldc_w	#270; //int 31
   20:	iconst_m1
   21:	ixor
   22:	iand
   23:	istore	20
   25:	aload_0
   26:	getfield	#119; //Field startIndex:I
   29:	iconst_1
   30:	isub
   31:	ldc_w	#270; //int 31
   34:	iand
   35:	istore	21
   37:	aload_0
   38:	getfield	#119; //Field startIndex:I
   41:	iload	20
   43:	ldc_w	#310; //int 32
   46:	iadd
   47:	if_icmpeq	116
   50:	new	#117; //class scala/collection/immutable/Vector
   53:	dup
   54:	aload_0
   55:	getfield	#119; //Field startIndex:I
   58:	iconst_1
   59:	isub
   60:	aload_0
   61:	getfield	#121; //Field endIndex:I
   64:	iload	20
   66:	invokespecial	#276; //Method "<init>":(III)V
   69:	astore_3
   70:	aload_3
   71:	aload_0
   72:	invokeinterface	#281,  2; //InterfaceMethod scala/collection/immutable/VectorPointer.initFrom:(Lscala/collection/immutable/VectorPointer;)V
   77:	aload_0
   78:	getfield	#196; //Field dirty:Z
   81:	istore_2
   82:	aload_3
   83:	iload_2
   84:	putfield	#196; //Field dirty:Z
   87:	aload_3
   88:	aload_0
   89:	getfield	#123; //Field focus:I
   92:	iload	20
   94:	aload_0
   95:	getfield	#123; //Field focus:I
   98:	iload	20
   100:	ixor
   101:	invokespecial	#291; //Method gotoPosWritable:(III)V
   104:	aload_3
   105:	getfield	#321; //Field display0:[Ljava/lang/Object;
   108:	iload	21
   110:	aload_1
   111:	aastore
   112:	aload_3
   113:	goto	652
   116:	iconst_1
   117:	iconst_5
   118:	aload_0
   119:	getfield	#383; //Field depth:I
   122:	imul
   123:	ishl
   124:	aload_0
   125:	getfield	#121; //Field endIndex:I
   128:	isub
   129:	istore	4
   131:	iload	4
   133:	iconst_1
   134:	iconst_5
   135:	aload_0
   136:	getfield	#383; //Field depth:I
   139:	iconst_1
   140:	isub
   141:	imul
   142:	ishl
   143:	iconst_1
   144:	isub
   145:	iconst_m1
   146:	ixor
   147:	iand
   148:	istore	13
   150:	iload	4
   152:	iconst_5
   153:	aload_0
   154:	getfield	#383; //Field depth:I
   157:	iconst_1
   158:	isub
   159:	imul
   160:	iushr
   161:	istore	10
   163:	iload	13
   165:	iconst_0
   166:	if_icmpeq	393
   169:	aload_0
   170:	invokestatic	#423; //Method scala/collection/immutable/VectorPointer$class.debug:(Lscala/collection/immutable/VectorPointer;)V
   173:	aload_0
   174:	invokeinterface	#433,  1; //InterfaceMethod scala/collection/immutable/VectorPointer.depth:()I
   179:	iconst_1
   180:	if_icmple	288
   183:	iload	20
   185:	iload	13
   187:	iadd
   188:	istore	7
   190:	aload_0
   191:	getfield	#123; //Field focus:I
   194:	iload	13
   196:	iadd
   197:	istore	6
   199:	new	#117; //class scala/collection/immutable/Vector
   202:	dup
   203:	aload_0
   204:	getfield	#119; //Field startIndex:I
   207:	iconst_1
   208:	isub
   209:	iload	13
   211:	iadd
   212:	aload_0
   213:	getfield	#121; //Field endIndex:I
   216:	iload	13
   218:	iadd
   219:	iload	7
   221:	invokespecial	#276; //Method "<init>":(III)V
   224:	astore	8
   226:	aload	8
   228:	aload_0
   229:	invokeinterface	#281,  2; //InterfaceMethod scala/collection/immutable/VectorPointer.initFrom:(Lscala/collection/immutable/VectorPointer;)V
   234:	aload_0
   235:	getfield	#196; //Field dirty:Z
   238:	istore	5
   240:	aload	8
   242:	iload	5
   244:	putfield	#196; //Field dirty:Z
   247:	aload	8
   249:	iconst_0
   250:	iload	10
   252:	invokespecial	#425; //Method shiftTopLevel:(II)V
   255:	aload	8
   257:	invokestatic	#423; //Method scala/collection/immutable/VectorPointer$class.debug:(Lscala/collection/immutable/VectorPointer;)V
   260:	aload	8
   262:	iload	6
   264:	iload	7
   266:	iload	6
   268:	iload	7
   270:	ixor
   271:	invokespecial	#428; //Method gotoFreshPosWritable:(III)V
   274:	aload	8
   276:	getfield	#321; //Field display0:[Ljava/lang/Object;
   279:	iload	21
   281:	aload_1
   282:	aastore
   283:	aload	8
   285:	goto	652
   288:	iload	20
   290:	ldc_w	#310; //int 32
   293:	iadd
   294:	istore	12
   296:	aload_0
   297:	getfield	#123; //Field focus:I
   300:	istore	11
   302:	new	#117; //class scala/collection/immutable/Vector
   305:	dup
   306:	aload_0
   307:	getfield	#119; //Field startIndex:I
   310:	iconst_1
   311:	isub
   312:	iload	13
   314:	iadd
   315:	aload_0
   316:	getfield	#121; //Field endIndex:I
   319:	iload	13
   321:	iadd
   322:	iload	12
   324:	invokespecial	#276; //Method "<init>":(III)V
   327:	astore	14
   329:	aload	14
   331:	aload_0
   332:	invokeinterface	#281,  2; //InterfaceMethod scala/collection/immutable/VectorPointer.initFrom:(Lscala/collection/immutable/VectorPointer;)V
   337:	aload_0
   338:	getfield	#196; //Field dirty:Z
   341:	istore	9
   343:	aload	14
   345:	iload	9
   347:	putfield	#196; //Field dirty:Z
   350:	aload	14
   352:	iconst_0
   353:	iload	10
   355:	invokespecial	#425; //Method shiftTopLevel:(II)V
   358:	aload	14
   360:	iload	11
   362:	iload	12
   364:	iload	11
   366:	iload	12
   368:	ixor
   369:	invokespecial	#291; //Method gotoPosWritable:(III)V
   372:	aload	14
   374:	getfield	#321; //Field display0:[Ljava/lang/Object;
   377:	iload	13
   379:	iconst_1
   380:	isub
   381:	aload_1
   382:	aastore
   383:	aload	14
   385:	invokestatic	#423; //Method scala/collection/immutable/VectorPointer$class.debug:(Lscala/collection/immutable/VectorPointer;)V
   388:	aload	14
   390:	goto	652
   393:	iload	20
   395:	iconst_0
   396:	if_icmpge	528
   399:	iconst_1
   400:	iconst_5
   401:	aload_0
   402:	invokeinterface	#433,  1; //InterfaceMethod scala/collection/immutable/VectorPointer.depth:()I
   407:	iconst_1
   408:	iadd
   409:	imul
   410:	ishl
   411:	iconst_1
   412:	iconst_5
   413:	aload_0
   414:	invokeinterface	#433,  1; //InterfaceMethod scala/collection/immutable/VectorPointer.depth:()I
   419:	imul
   420:	ishl
   421:	isub
   422:	istore	15
   424:	iload	20
   426:	iload	15
   428:	iadd
   429:	istore	17
   431:	aload_0
   432:	getfield	#123; //Field focus:I
   435:	iload	15
   437:	iadd
   438:	istore	16
   440:	new	#117; //class scala/collection/immutable/Vector
   443:	dup
   444:	aload_0
   445:	getfield	#119; //Field startIndex:I
   448:	iconst_1
   449:	isub
   450:	iload	15
   452:	iadd
   453:	aload_0
   454:	getfield	#121; //Field endIndex:I
   457:	iload	15
   459:	iadd
   460:	iload	17
   462:	invokespecial	#276; //Method "<init>":(III)V
   465:	astore	18
   467:	aload	18
   469:	aload_0
   470:	invokeinterface	#281,  2; //InterfaceMethod scala/collection/immutable/VectorPointer.initFrom:(Lscala/collection/immutable/VectorPointer;)V
   475:	aload	18
   477:	aload_0
   478:	invokevirtual	#284; //Method dirty:()Z
   481:	invokevirtual	#288; //Method dirty_$eq:(Z)V
   484:	aload	18
   486:	invokeinterface	#430,  1; //InterfaceMethod scala/collection/immutable/VectorPointer.debug:()V
   491:	aload	18
   493:	iload	16
   495:	iload	17
   497:	iload	16
   499:	iload	17
   501:	ixor
   502:	invokespecial	#428; //Method gotoFreshPosWritable:(III)V
   505:	aload	18
   507:	invokeinterface	#339,  1; //InterfaceMethod scala/collection/immutable/VectorPointer.display0:()[Ljava/lang/Object;
   512:	iload	21
   514:	aload_1
   515:	aastore
   516:	aload	18
   518:	invokeinterface	#430,  1; //InterfaceMethod scala/collection/immutable/VectorPointer.debug:()V
   523:	aload	18
   525:	goto	652
   528:	aload_0
   529:	getfield	#123; //Field focus:I
   532:	istore	19
   534:	new	#117; //class scala/collection/immutable/Vector
   537:	dup
   538:	aload_0
   539:	getfield	#119; //Field startIndex:I
   542:	iconst_1
   543:	isub
   544:	aload_0
   545:	getfield	#121; //Field endIndex:I
   548:	iload	20
   550:	invokespecial	#276; //Method "<init>":(III)V
   553:	astore	22
   555:	aload	22
   557:	aload_0
   558:	invokeinterface	#281,  2; //InterfaceMethod scala/collection/immutable/VectorPointer.initFrom:(Lscala/collection/immutable/VectorPointer;)V
   563:	aload	22
   565:	aload_0
   566:	invokevirtual	#284; //Method dirty:()Z
   569:	invokevirtual	#288; //Method dirty_$eq:(Z)V
   572:	aload	22
   574:	iload	19
   576:	iload	20
   578:	iload	19
   580:	iload	20
   582:	ixor
   583:	invokespecial	#428; //Method gotoFreshPosWritable:(III)V
   586:	aload	22
   588:	invokeinterface	#339,  1; //InterfaceMethod scala/collection/immutable/VectorPointer.display0:()[Ljava/lang/Object;
   593:	iload	21
   595:	aload_1
   596:	aastore
   597:	aload	22
   599:	goto	652
   602:	ldc_w	#310; //int 32
   605:	anewarray	#125; //class java/lang/Object
   608:	astore	23
   610:	aload	23
   612:	ldc_w	#270; //int 31
   615:	aload_1
   616:	aastore
   617:	new	#117; //class scala/collection/immutable/Vector
   620:	dup
   621:	ldc_w	#270; //int 31
   624:	ldc_w	#310; //int 32
   627:	iconst_0
   628:	invokespecial	#276; //Method "<init>":(III)V
   631:	astore	24
   633:	aload	24
   635:	iconst_1
   636:	invokeinterface	#436,  2; //InterfaceMethod scala/collection/immutable/VectorPointer.depth_$eq:(I)V
   641:	aload	24
   643:	aload	23
   645:	invokeinterface	#439,  2; //InterfaceMethod scala/collection/immutable/VectorPointer.display0_$eq:([Ljava/lang/Object;)V
   650:	aload	24
   652:	areturn
  LineNumberTable: 
   line 172: 0
   line 173: 11
   line 174: 25
   line 176: 37
   line 177: 50
   line 182: 70
   line 178: 71
   line 179: 77
   line 180: 87
   line 181: 104
   line 182: 112
   line 185: 116
   line 186: 131
   line 187: 150
   line 190: 163
   line 192: 169
   line 195: 173
   line 196: 183
   line 197: 190
   line 198: 199
   line 206: 226
   line 199: 228
   line 200: 234
   line 201: 247
   line 202: 255
   line 203: 260
   line 204: 274
   line 206: 283
   line 208: 288
   line 209: 296
   line 214: 302
   line 221: 329
   line 215: 331
   line 216: 337
   line 217: 350
   line 218: 358
   line 219: 372
   line 220: 383
   line 221: 388
   line 195: 390
   line 223: 393
   line 225: 399
   line 228: 424
   line 229: 431
   line 232: 440
   line 240: 467
   line 233: 469
   line 234: 475
   line 235: 484
   line 236: 491
   line 237: 505
   line 238: 516
   line 240: 523
   line 243: 528
   line 245: 534
   line 251: 555
   line 246: 557
   line 247: 563
   line 248: 572
   line 249: 586
   line 251: 597
   line 223: 599
   line 257: 602
   line 258: 610
   line 259: 617
   line 262: 633
   line 260: 635
   line 261: 641
   line 262: 650
   line 172: 652

  LocalVariableTable: 
   Start  Length  Slot  Name   Signature
   0      653      0    this       Lscala/collection/immutable/Vector;
   0      653      1    value       Ljava/lang/Object;
   70      43      3    s       Lscala/collection/immutable/Vector;
   131      471      4    freeSpace       I
   199      86      6    newFocus       I
   190      95      7    newBlockIndex       I
   226      59      8    s       Lscala/collection/immutable/Vector;
   163      439      10    shiftBlocks       I
   302      88      11    newFocus       I
   296      94      12    newBlockIndex       I
   150      452      13    shift       I
   329      61      14    s       Lscala/collection/immutable/Vector;
   424      101      15    move       I
   440      85      16    newFocus       I
   431      94      17    newBlockIndex       I
   467      58      18    s       Lscala/collection/immutable/Vector;
   534      65      19    newFocus       I
   25      577      20    blockIndex       I
   37      565      21    lo       I
   555      44      22    s       Lscala/collection/immutable/Vector;
   610      42      23    elems       [Ljava/lang/Object;
   633      19      24    s       Lscala/collection/immutable/Vector;

  Signature: length = 0x2
   01 FFFFFFBE 

public scala.collection.immutable.Vector updateAt(int, java.lang.Object);
  Code:
   Stack=5, Locals=5, Args_size=3
   0:	aload_0
   1:	iload_1
   2:	invokespecial	#468; //Method checkRangeConvert:(I)I
   5:	istore_3
   6:	new	#117; //class scala/collection/immutable/Vector
   9:	dup
   10:	aload_0
   11:	getfield	#119; //Field startIndex:I
   14:	aload_0
   15:	getfield	#121; //Field endIndex:I
   18:	iload_3
   19:	invokespecial	#276; //Method "<init>":(III)V
   22:	astore	4
   24:	aload	4
   26:	aload_0
   27:	invokeinterface	#281,  2; //InterfaceMethod scala/collection/immutable/VectorPointer.initFrom:(Lscala/collection/immutable/VectorPointer;)V
   32:	aload	4
   34:	aload_0
   35:	invokevirtual	#284; //Method dirty:()Z
   38:	invokevirtual	#288; //Method dirty_$eq:(Z)V
   41:	aload	4
   43:	aload_0
   44:	getfield	#123; //Field focus:I
   47:	iload_3
   48:	aload_0
   49:	getfield	#123; //Field focus:I
   52:	iload_3
   53:	ixor
   54:	invokespecial	#291; //Method gotoPosWritable:(III)V
   57:	aload	4
   59:	invokeinterface	#339,  1; //InterfaceMethod scala/collection/immutable/VectorPointer.display0:()[Ljava/lang/Object;
   64:	iload_3
   65:	ldc_w	#270; //int 31
   68:	iand
   69:	aload_2
   70:	aastore
   71:	aload	4
   73:	areturn
  LineNumberTable: 
   line 146: 0
   line 147: 6
   line 152: 24
   line 148: 26
   line 149: 32
   line 150: 41
   line 151: 57
   line 152: 71

  LocalVariableTable: 
   Start  Length  Slot  Name   Signature
   0      74      0    this       Lscala/collection/immutable/Vector;
   0      74      1    index       I
   0      74      2    elem       Ljava/lang/Object;
   6      67      3    idx       I
   24      49      4    s       Lscala/collection/immutable/Vector;

  Signature: length = 0x2
   01 FFFFFFD7 

public scala.collection.immutable.Vector dropRight(int);
  Code:
   Stack=3, Locals=3, Args_size=2
   0:	iload_1
   1:	iconst_0
   2:	if_icmpge	20
   5:	new	#318; //class java/lang/IllegalArgumentException
   8:	dup
   9:	iload_1
   10:	invokestatic	#389; //Method scala/runtime/BoxesRunTime.boxToInteger:(I)Ljava/lang/Integer;
   13:	invokevirtual	#393; //Method java/lang/Object.toString:()Ljava/lang/String;
   16:	invokespecial	#472; //Method java/lang/IllegalArgumentException."<init>":(Ljava/lang/String;)V
   19:	athrow
   20:	aload_0
   21:	getfield	#121; //Field endIndex:I
   24:	iload_1
   25:	isub
   26:	aload_0
   27:	getfield	#119; //Field startIndex:I
   30:	if_icmple	46
   33:	aload_0
   34:	aload_0
   35:	getfield	#121; //Field endIndex:I
   38:	iload_1
   39:	isub
   40:	invokespecial	#474; //Method dropBack0:(I)Lscala/collection/immutable/Vector;
   43:	goto	54
   46:	getstatic	#11; //Field scala/collection/immutable/Vector$.MODULE$:Lscala/collection/immutable/Vector$;
   49:	astore_2
   50:	aload_2
   51:	invokevirtual	#18; //Method scala/collection/immutable/Vector$.NIL:()Lscala/collection/immutable/Vector;
   54:	areturn
  LineNumberTable: 
   line 135: 0
   line 136: 20
   line 137: 33
   line 139: 46
   line 134: 54

  LocalVariableTable: 
   Start  Length  Slot  Name   Signature
   0      55      0    this       Lscala/collection/immutable/Vector;
   0      55      1    n       I

  Signature: length = 0x2
   01 31 

public scala.collection.immutable.Vector takeRight(int);
  Code:
   Stack=3, Locals=2, Args_size=2
   0:	iload_1
   1:	iconst_0
   2:	if_icmpge	20
   5:	new	#318; //class java/lang/IllegalArgumentException
   8:	dup
   9:	iload_1
   10:	invokestatic	#389; //Method scala/runtime/BoxesRunTime.boxToInteger:(I)Ljava/lang/Integer;
   13:	invokevirtual	#393; //Method java/lang/Object.toString:()Ljava/lang/String;
   16:	invokespecial	#472; //Method java/lang/IllegalArgumentException."<init>":(Ljava/lang/String;)V
   19:	athrow
   20:	aload_0
   21:	getfield	#121; //Field endIndex:I
   24:	iload_1
   25:	isub
   26:	aload_0
   27:	getfield	#119; //Field startIndex:I
   30:	if_icmple	46
   33:	aload_0
   34:	aload_0
   35:	getfield	#121; //Field endIndex:I
   38:	iload_1
   39:	isub
   40:	invokespecial	#476; //Method dropFront0:(I)Lscala/collection/immutable/Vector;
   43:	goto	47
   46:	aload_0
   47:	areturn
  LineNumberTable: 
   line 127: 0
   line 128: 20
   line 129: 33
   line 131: 46
   line 126: 47

  LocalVariableTable: 
   Start  Length  Slot  Name   Signature
   0      48      0    this       Lscala/collection/immutable/Vector;
   0      48      1    n       I

  Signature: length = 0x2
   01 31 

public scala.collection.immutable.Vector drop(int);
  Code:
   Stack=3, Locals=3, Args_size=2
   0:	iload_1
   1:	iconst_0
   2:	if_icmpge	20
   5:	new	#318; //class java/lang/IllegalArgumentException
   8:	dup
   9:	iload_1
   10:	invokestatic	#389; //Method scala/runtime/BoxesRunTime.boxToInteger:(I)Ljava/lang/Integer;
   13:	invokevirtual	#393; //Method java/lang/Object.toString:()Ljava/lang/String;
   16:	invokespecial	#472; //Method java/lang/IllegalArgumentException."<init>":(Ljava/lang/String;)V
   19:	athrow
   20:	aload_0
   21:	getfield	#119; //Field startIndex:I
   24:	iload_1
   25:	iadd
   26:	aload_0
   27:	getfield	#121; //Field endIndex:I
   30:	if_icmpge	46
   33:	aload_0
   34:	aload_0
   35:	getfield	#119; //Field startIndex:I
   38:	iload_1
   39:	iadd
   40:	invokespecial	#476; //Method dropFront0:(I)Lscala/collection/immutable/Vector;
   43:	goto	54
   46:	getstatic	#11; //Field scala/collection/immutable/Vector$.MODULE$:Lscala/collection/immutable/Vector$;
   49:	astore_2
   50:	aload_2
   51:	invokevirtual	#18; //Method scala/collection/immutable/Vector$.NIL:()Lscala/collection/immutable/Vector;
   54:	areturn
  LineNumberTable: 
   line 119: 0
   line 120: 20
   line 121: 33
   line 123: 46
   line 118: 54

  LocalVariableTable: 
   Start  Length  Slot  Name   Signature
   0      55      0    this       Lscala/collection/immutable/Vector;
   0      55      1    n       I

  Signature: length = 0x2
   01 31 

public scala.collection.immutable.Vector take(int);
  Code:
   Stack=3, Locals=2, Args_size=2
   0:	iload_1
   1:	iconst_0
   2:	if_icmpge	20
   5:	new	#318; //class java/lang/IllegalArgumentException
   8:	dup
   9:	iload_1
   10:	invokestatic	#389; //Method scala/runtime/BoxesRunTime.boxToInteger:(I)Ljava/lang/Integer;
   13:	invokevirtual	#393; //Method java/lang/Object.toString:()Ljava/lang/String;
   16:	invokespecial	#472; //Method java/lang/IllegalArgumentException."<init>":(Ljava/lang/String;)V
   19:	athrow
   20:	aload_0
   21:	getfield	#119; //Field startIndex:I
   24:	iload_1
   25:	iadd
   26:	aload_0
   27:	getfield	#121; //Field endIndex:I
   30:	if_icmpge	46
   33:	aload_0
   34:	aload_0
   35:	getfield	#119; //Field startIndex:I
   38:	iload_1
   39:	iadd
   40:	invokespecial	#474; //Method dropBack0:(I)Lscala/collection/immutable/Vector;
   43:	goto	47
   46:	aload_0
   47:	areturn
  LineNumberTable: 
   line 111: 0
   line 112: 20
   line 113: 33
   line 115: 46
   line 110: 47

  LocalVariableTable: 
   Start  Length  Slot  Name   Signature
   0      48      0    this       Lscala/collection/immutable/Vector;
   0      48      1    n       I

  Signature: length = 0x2
   01 31 

public java.lang.Object $colon$plus(java.lang.Object, scala.collection.generic.CanBuildFrom);
  Code:
   Stack=2, Locals=3, Args_size=3
   0:	aload_0
   1:	aload_1
   2:	invokevirtual	#480; //Method appendBack:(Ljava/lang/Object;)Lscala/collection/immutable/Vector;
   5:	areturn
  LineNumberTable: 
   line 107: 0

  LocalVariableTable: 
   Start  Length  Slot  Name   Signature
   0      6      0    this       Lscala/collection/immutable/Vector;
   0      6      1    elem       Ljava/lang/Object;
   0      6      2    bf       Lscala/collection/generic/CanBuildFrom;

  Signature: length = 0x2
   01 FFFFFFE3 

public java.lang.Object $plus$colon(java.lang.Object, scala.collection.generic.CanBuildFrom);
  Code:
   Stack=2, Locals=3, Args_size=3
   0:	aload_0
   1:	aload_1
   2:	invokevirtual	#486; //Method appendFront:(Ljava/lang/Object;)Lscala/collection/immutable/Vector;
   5:	areturn
  LineNumberTable: 
   line 102: 0

  LocalVariableTable: 
   Start  Length  Slot  Name   Signature
   0      6      0    this       Lscala/collection/immutable/Vector;
   0      6      1    elem       Ljava/lang/Object;
   0      6      2    bf       Lscala/collection/generic/CanBuildFrom;

  Signature: length = 0x2
   01 FFFFFFE3 

public java.lang.Object updated(int, java.lang.Object, scala.collection.generic.CanBuildFrom);
  Code:
   Stack=3, Locals=4, Args_size=4
   0:	aload_0
   1:	iload_1
   2:	aload_2
   3:	invokevirtual	#490; //Method updateAt:(ILjava/lang/Object;)Lscala/collection/immutable/Vector;
   6:	areturn
  LineNumberTable: 
   line 97: 0

  LocalVariableTable: 
   Start  Length  Slot  Name   Signature
   0      7      0    this       Lscala/collection/immutable/Vector;
   0      7      1    index       I
   0      7      2    elem       Ljava/lang/Object;
   0      7      3    bf       Lscala/collection/generic/CanBuildFrom;

  Signature: length = 0x2
   01 FFFFFFEB 

public java.lang.Object apply(int);
  Code:
   Stack=4, Locals=3, Args_size=2
   0:	aload_0
   1:	iload_1
   2:	invokespecial	#468; //Method checkRangeConvert:(I)I
   5:	istore_2
   6:	aload_0
   7:	iload_2
   8:	iload_2
   9:	aload_0
   10:	getfield	#123; //Field focus:I
   13:	ixor
   14:	invokeinterface	#498,  3; //InterfaceMethod scala/collection/immutable/VectorPointer.getElem:(II)Ljava/lang/Object;
   19:	areturn
  LineNumberTable: 
   line 79: 0
   line 81: 6

  LocalVariableTable: 
   Start  Length  Slot  Name   Signature
   0      20      0    this       Lscala/collection/immutable/Vector;
   0      20      1    index       I
   6      13      2    idx       I

  Signature: length = 0x2
   01 FFFFFFF3 

public java.lang.Object map0(scala.Function1, scala.collection.generic.CanBuildFrom);
  Code:
   Stack=4, Locals=6, Args_size=3
   0:	aload_2
   1:	aload_0
   2:	invokestatic	#504; //Method scala/collection/TraversableLike$class.repr:(Lscala/collection/TraversableLike;)Ljava/lang/Object;
   5:	invokeinterface	#509,  2; //InterfaceMethod scala/collection/generic/CanBuildFrom.apply:(Ljava/lang/Object;)Lscala/collection/mutable/Builder;
   10:	astore	5
   12:	new	#511; //class scala/collection/immutable/Vector$$anonfun$map0$1
   15:	dup
   16:	pop
   17:	aload_0
   18:	aload_1
   19:	aload	5
   21:	invokespecial	#514; //Method scala/collection/immutable/Vector$$anonfun$map0$1."<init>":(Lscala/collection/immutable/Vector;Lscala/Function1;Lscala/collection/mutable/Builder;)V
   24:	new	#516; //class scala/collection/immutable/VectorIterator
   27:	dup
   28:	aload_0
   29:	getfield	#119; //Field startIndex:I
   32:	aload_0
   33:	getfield	#121; //Field endIndex:I
   36:	invokespecial	#518; //Method scala/collection/immutable/VectorIterator."<init>":(II)V
   39:	astore_3
   40:	aload_3
   41:	aload_0
   42:	invokeinterface	#281,  2; //InterfaceMethod scala/collection/immutable/VectorPointer.initFrom:(Lscala/collection/immutable/VectorPointer;)V
   47:	aload_0
   48:	getfield	#196; //Field dirty:Z
   51:	ifeq	64
   54:	aload_3
   55:	aload_0
   56:	getfield	#123; //Field focus:I
   59:	invokeinterface	#521,  2; //InterfaceMethod scala/collection/immutable/VectorPointer.stabilize:(I)V
   64:	aload_3
   65:	invokeinterface	#433,  1; //InterfaceMethod scala/collection/immutable/VectorPointer.depth:()I
   70:	iconst_1
   71:	if_icmple	93
   74:	aload_3
   75:	aload_0
   76:	getfield	#119; //Field startIndex:I
   79:	aload_0
   80:	getfield	#119; //Field startIndex:I
   83:	aload_0
   84:	getfield	#123; //Field focus:I
   87:	ixor
   88:	invokeinterface	#524,  3; //InterfaceMethod scala/collection/immutable/VectorPointer.gotoPos:(II)V
   93:	aload_3
   94:	invokevirtual	#527; //Method scala/collection/immutable/VectorIterator.hasNext:()Z
   97:	ifeq	125
   100:	aload_3
   101:	invokevirtual	#531; //Method scala/collection/immutable/VectorIterator.next:()Ljava/lang/Object;
   104:	astore	4
   106:	aload	5
   108:	aload_1
   109:	aload	4
   111:	invokeinterface	#535,  2; //InterfaceMethod scala/Function1.apply:(Ljava/lang/Object;)Ljava/lang/Object;
   116:	invokeinterface	#540,  2; //InterfaceMethod scala/collection/mutable/Builder.$plus$eq:(Ljava/lang/Object;)Lscala/collection/mutable/Builder;
   121:	pop
   122:	goto	93
   125:	aload	5
   127:	invokeinterface	#543,  1; //InterfaceMethod scala/collection/mutable/Builder.result:()Ljava/lang/Object;
   132:	areturn
  LineNumberTable: 
   line 70: 0
   line 71: 12
   line 72: 125

  LocalVariableTable: 
   Start  Length  Slot  Name   Signature
   0      133      0    this       Lscala/collection/immutable/Vector;
   0      133      1    f$1       Lscala/Function1;
   0      133      2    bf       Lscala/collection/generic/CanBuildFrom;
   40      53      3    s0       Lscala/collection/immutable/VectorIterator;
   12      120      5    b$1       Lscala/collection/mutable/Builder;

  Signature: length = 0x2
   02 25 

public void foreach0(scala.Function1);
  Code:
   Stack=4, Locals=3, Args_size=2
   0:	new	#516; //class scala/collection/immutable/VectorIterator
   3:	dup
   4:	aload_0
   5:	getfield	#119; //Field startIndex:I
   8:	aload_0
   9:	getfield	#121; //Field endIndex:I
   12:	invokespecial	#518; //Method scala/collection/immutable/VectorIterator."<init>":(II)V
   15:	astore_2
   16:	aload_2
   17:	aload_0
   18:	invokeinterface	#281,  2; //InterfaceMethod scala/collection/immutable/VectorPointer.initFrom:(Lscala/collection/immutable/VectorPointer;)V
   23:	aload_0
   24:	getfield	#196; //Field dirty:Z
   27:	ifeq	40
   30:	aload_2
   31:	aload_0
   32:	getfield	#123; //Field focus:I
   35:	invokeinterface	#521,  2; //InterfaceMethod scala/collection/immutable/VectorPointer.stabilize:(I)V
   40:	aload_2
   41:	invokeinterface	#433,  1; //InterfaceMethod scala/collection/immutable/VectorPointer.depth:()I
   46:	iconst_1
   47:	if_icmple	69
   50:	aload_2
   51:	aload_0
   52:	getfield	#119; //Field startIndex:I
   55:	aload_0
   56:	getfield	#119; //Field startIndex:I
   59:	aload_0
   60:	getfield	#123; //Field focus:I
   63:	ixor
   64:	invokeinterface	#524,  3; //InterfaceMethod scala/collection/immutable/VectorPointer.gotoPos:(II)V
   69:	aload_2
   70:	invokevirtual	#527; //Method scala/collection/immutable/VectorIterator.hasNext:()Z
   73:	ifeq	90
   76:	aload_1
   77:	aload_2
   78:	invokevirtual	#531; //Method scala/collection/immutable/VectorIterator.next:()Ljava/lang/Object;
   81:	invokeinterface	#535,  2; //InterfaceMethod scala/Function1.apply:(Ljava/lang/Object;)Ljava/lang/Object;
   86:	pop
   87:	goto	69
   90:	return
  LineNumberTable: 
   line 68: 0

  LocalVariableTable: 
   Start  Length  Slot  Name   Signature
   0      91      0    this       Lscala/collection/immutable/Vector;
   0      91      1    f       Lscala/Function1;
   16      53      2    s0       Lscala/collection/immutable/VectorIterator;

  Signature: length = 0x2
   02 28 

public scala.collection.immutable.VectorIterator iterator();
  Code:
   Stack=4, Locals=2, Args_size=1
   0:	new	#516; //class scala/collection/immutable/VectorIterator
   3:	dup
   4:	aload_0
   5:	getfield	#119; //Field startIndex:I
   8:	aload_0
   9:	getfield	#121; //Field endIndex:I
   12:	invokespecial	#518; //Method scala/collection/immutable/VectorIterator."<init>":(II)V
   15:	astore_1
   16:	aload_1
   17:	aload_0
   18:	invokeinterface	#281,  2; //InterfaceMethod scala/collection/immutable/VectorPointer.initFrom:(Lscala/collection/immutable/VectorPointer;)V
   23:	aload_0
   24:	getfield	#196; //Field dirty:Z
   27:	ifeq	40
   30:	aload_1
   31:	aload_0
   32:	getfield	#123; //Field focus:I
   35:	invokeinterface	#521,  2; //InterfaceMethod scala/collection/immutable/VectorPointer.stabilize:(I)V
   40:	aload_1
   41:	invokeinterface	#433,  1; //InterfaceMethod scala/collection/immutable/VectorPointer.depth:()I
   46:	iconst_1
   47:	if_icmple	69
   50:	aload_1
   51:	aload_0
   52:	getfield	#119; //Field startIndex:I
   55:	aload_0
   56:	getfield	#119; //Field startIndex:I
   59:	aload_0
   60:	getfield	#123; //Field focus:I
   63:	ixor
   64:	invokeinterface	#524,  3; //InterfaceMethod scala/collection/immutable/VectorPointer.gotoPos:(II)V
   69:	aload_1
   70:	areturn
  LineNumberTable: 
   line 56: 0
   line 57: 16
   line 58: 23
   line 59: 40
   line 60: 69

  LocalVariableTable: 
   Start  Length  Slot  Name   Signature
   0      71      0    this       Lscala/collection/immutable/Vector;
   16      54      1    s       Lscala/collection/immutable/VectorIterator;

  Signature: length = 0x2
   02 29 

public int lengthCompare(int);
  Code:
   Stack=2, Locals=2, Args_size=2
   0:	aload_0
   1:	invokevirtual	#557; //Method length:()I
   4:	iload_1
   5:	isub
   6:	ireturn
  LineNumberTable: 
   line 52: 0

  LocalVariableTable: 
   Start  Length  Slot  Name   Signature
   0      7      0    this       Lscala/collection/immutable/Vector;
   0      7      1    len       I


public int length();
  Code:
   Stack=2, Locals=1, Args_size=1
   0:	aload_0
   1:	getfield	#121; //Field endIndex:I
   4:	aload_0
   5:	getfield	#119; //Field startIndex:I
   8:	isub
   9:	ireturn
  LineNumberTable: 
   line 50: 0


public void dirty_$eq(boolean);
  Code:
   Stack=2, Locals=2, Args_size=2
   0:	aload_0
   1:	iload_1
   2:	putfield	#196; //Field dirty:Z
   5:	return
  LineNumberTable: 
   line 48: 0


public boolean dirty();
  Code:
   Stack=1, Locals=1, Args_size=1
   0:	aload_0
   1:	getfield	#196; //Field dirty:Z
   4:	ireturn
  LineNumberTable: 
   line 48: 0


public scala.collection.generic.GenericCompanion companion();
  Code:
   Stack=1, Locals=1, Args_size=1
   0:	getstatic	#11; //Field scala/collection/immutable/Vector$.MODULE$:Lscala/collection/immutable/Vector$;
   3:	areturn
  LineNumberTable: 
   line 41: 0

  Signature: length = 0x2
   02 31 

public scala.collection.TraversableLike$WithFilter withFilter(scala.Function1);
  Code:
   Stack=2, Locals=2, Args_size=2
   0:	aload_0
   1:	aload_1
   2:	invokestatic	#566; //Method scala/collection/TraversableLike$class.withFilter:(Lscala/collection/TraversableLike;Lscala/Function1;)Lscala/collection/TraversableLike$WithFilter;
   5:	areturn
  LineNumberTable: 
   line 36: 0

  LocalVariableTable: 
   Start  Length  Slot  Name   Signature
   0      6      0    this       Lscala/collection/immutable/Vector;
   0      6      1    p       Lscala/Function1;

  Signature: length = 0x2
   02 33 

public java.lang.String stringPrefix();
  Code:
   Stack=1, Locals=1, Args_size=1
   0:	aload_0
   1:	invokestatic	#571; //Method scala/collection/TraversableLike$class.stringPrefix:(Lscala/collection/TraversableLike;)Ljava/lang/String;
   4:	areturn
  LineNumberTable: 
   line 36: 0


public scala.collection.mutable.StringBuilder addString(scala.collection.mutable.StringBuilder);
  Code:
   Stack=2, Locals=2, Args_size=2
   0:	aload_0
   1:	aload_1
   2:	invokestatic	#576; //Method scala/collection/TraversableLike$class.addString:(Lscala/collection/TraversableLike;Lscala/collection/mutable/StringBuilder;)Lscala/collection/mutable/StringBuilder;
   5:	areturn
  LineNumberTable: 
   line 36: 0

  LocalVariableTable: 
   Start  Length  Slot  Name   Signature
   0      6      0    this       Lscala/collection/immutable/Vector;
   0      6      1    b       Lscala/collection/mutable/StringBuilder;


public scala.collection.mutable.StringBuilder addString(scala.collection.mutable.StringBuilder, java.lang.String);
  Code:
   Stack=3, Locals=3, Args_size=3
   0:	aload_0
   1:	aload_1
   2:	aload_2
   3:	invokestatic	#582; //Method scala/collection/TraversableLike$class.addString:(Lscala/collection/TraversableLike;Lscala/collection/mutable/StringBuilder;Ljava/lang/String;)Lscala/collection/mutable/StringBuilder;
   6:	areturn
  LineNumberTable: 
   line 36: 0

  LocalVariableTable: 
   Start  Length  Slot  Name   Signature
   0      7      0    this       Lscala/collection/immutable/Vector;
   0      7      1    b       Lscala/collection/mutable/StringBuilder;
   0      7      2    sep       Ljava/lang/String;


public scala.collection.mutable.StringBuilder addString(scala.collection.mutable.StringBuilder, java.lang.String, java.lang.String, java.lang.String);
  Code:
   Stack=5, Locals=5, Args_size=5
   0:	aload_0
   1:	aload_1
   2:	aload_2
   3:	aload_3
   4:	aload	4
   6:	invokestatic	#588; //Method scala/collection/TraversableLike$class.addString:(Lscala/collection/TraversableLike;Lscala/collection/mutable/StringBuilder;Ljava/lang/String;Ljava/lang/String;Ljava/lang/String;)Lscala/collection/mutable/StringBuilder;
   9:	areturn
  LineNumberTable: 
   line 36: 0

  LocalVariableTable: 
   Start  Length  Slot  Name   Signature
   0      10      0    this       Lscala/collection/immutable/Vector;
   0      10      1    b       Lscala/collection/mutable/StringBuilder;
   0      10      2    start       Ljava/lang/String;
   0      10      3    sep       Ljava/lang/String;
   0      10      4    end       Ljava/lang/String;


public java.lang.String mkString();
  Code:
   Stack=1, Locals=1, Args_size=1
   0:	aload_0
   1:	invokestatic	#593; //Method scala/collection/TraversableLike$class.mkString:(Lscala/collection/TraversableLike;)Ljava/lang/String;
   4:	areturn
  LineNumberTable: 
   line 36: 0


public java.lang.String mkString(java.lang.String);
  Code:
   Stack=2, Locals=2, Args_size=2
   0:	aload_0
   1:	aload_1
   2:	invokestatic	#597; //Method scala/collection/TraversableLike$class.mkString:(Lscala/collection/TraversableLike;Ljava/lang/String;)Ljava/lang/String;
   5:	areturn
  LineNumberTable: 
   line 36: 0

  LocalVariableTable: 
   Start  Length  Slot  Name   Signature
   0      6      0    this       Lscala/collection/immutable/Vector;
   0      6      1    sep       Ljava/lang/String;


public java.lang.String mkString(java.lang.String, java.lang.String, java.lang.String);
  Code:
   Stack=4, Locals=4, Args_size=4
   0:	aload_0
   1:	aload_1
   2:	aload_2
   3:	aload_3
   4:	invokestatic	#601; //Method scala/collection/TraversableLike$class.mkString:(Lscala/collection/TraversableLike;Ljava/lang/String;Ljava/lang/String;Ljava/lang/String;)Ljava/lang/String;
   7:	areturn
  LineNumberTable: 
   line 36: 0

  LocalVariableTable: 
   Start  Length  Slot  Name   Signature
   0      8      0    this       Lscala/collection/immutable/Vector;
   0      8      1    start       Ljava/lang/String;
   0      8      2    sep       Ljava/lang/String;
   0      8      3    end       Ljava/lang/String;


public scala.collection.immutable.Set toSet();
  Code:
   Stack=1, Locals=1, Args_size=1
   0:	aload_0
   1:	invokestatic	#606; //Method scala/collection/TraversableLike$class.toSet:(Lscala/collection/TraversableLike;)Lscala/collection/immutable/Set;
   4:	areturn
  LineNumberTable: 
   line 36: 0


public scala.collection.mutable.IndexedSeq toIndexedSeq();
  Code:
   Stack=1, Locals=1, Args_size=1
   0:	aload_0
   1:	invokestatic	#611; //Method scala/collection/TraversableLike$class.toIndexedSeq:(Lscala/collection/TraversableLike;)Lscala/collection/mutable/IndexedSeq;
   4:	areturn
  LineNumberTable: 
   line 36: 0


public scala.collection.immutable.List toList();
  Code:
   Stack=1, Locals=1, Args_size=1
   0:	aload_0
   1:	invokestatic	#616; //Method scala/collection/TraversableLike$class.toList:(Lscala/collection/TraversableLike;)Lscala/collection/immutable/List;
   4:	areturn
  LineNumberTable: 
   line 36: 0


public java.lang.Object toArray(scala.reflect.ClassManifest);
  Code:
   Stack=2, Locals=2, Args_size=2
   0:	aload_0
   1:	aload_1
   2:	invokestatic	#621; //Method scala/collection/TraversableLike$class.toArray:(Lscala/collection/TraversableLike;Lscala/reflect/ClassManifest;)Ljava/lang/Object;
   5:	areturn
  LineNumberTable: 
   line 36: 0

  LocalVariableTable: 
   Start  Length  Slot  Name   Signature
   0      6      0    this       Lscala/collection/immutable/Vector;
   0      6      1    evidence$1       Lscala/reflect/ClassManifest;


public void copyToArray(java.lang.Object, int);
  Code:
   Stack=3, Locals=3, Args_size=3
   0:	aload_0
   1:	aload_1
   2:	iload_2
   3:	invokestatic	#628; //Method scala/collection/TraversableLike$class.copyToArray:(Lscala/collection/TraversableLike;Ljava/lang/Object;I)V
   6:	return
  LineNumberTable: 
   line 36: 0

  LocalVariableTable: 
   Start  Length  Slot  Name   Signature
   0      7      0    this       Lscala/collection/immutable/Vector;
   0      7      1    xs       Ljava/lang/Object;
   0      7      2    start       I


public void copyToBuffer(scala.collection.mutable.Buffer);
  Code:
   Stack=2, Locals=2, Args_size=2
   0:	aload_0
   1:	aload_1
   2:	invokestatic	#634; //Method scala/collection/TraversableLike$class.copyToBuffer:(Lscala/collection/TraversableLike;Lscala/collection/mutable/Buffer;)V
   5:	return
  LineNumberTable: 
   line 36: 0

  LocalVariableTable: 
   Start  Length  Slot  Name   Signature
   0      6      0    this       Lscala/collection/immutable/Vector;
   0      6      1    dest       Lscala/collection/mutable/Buffer;


public scala.Tuple2 splitAt(int);
  Code:
   Stack=2, Locals=2, Args_size=2
   0:	aload_0
   1:	iload_1
   2:	invokestatic	#641; //Method scala/collection/TraversableLike$class.splitAt:(Lscala/collection/TraversableLike;I)Lscala/Tuple2;
   5:	areturn
  LineNumberTable: 
   line 36: 0

  LocalVariableTable: 
   Start  Length  Slot  Name   Signature
   0      6      0    this       Lscala/collection/immutable/Vector;
   0      6      1    n       I


public scala.Tuple2 span(scala.Function1);
  Code:
   Stack=2, Locals=2, Args_size=2
   0:	aload_0
   1:	aload_1
   2:	invokestatic	#646; //Method scala/collection/TraversableLike$class.span:(Lscala/collection/TraversableLike;Lscala/Function1;)Lscala/Tuple2;
   5:	areturn
  LineNumberTable: 
   line 36: 0

  LocalVariableTable: 
   Start  Length  Slot  Name   Signature
   0      6      0    this       Lscala/collection/immutable/Vector;
   0      6      1    p       Lscala/Function1;


public java.lang.Object dropWhile(scala.Function1);
  Code:
   Stack=2, Locals=2, Args_size=2
   0:	aload_0
   1:	aload_1
   2:	invokestatic	#651; //Method scala/collection/TraversableLike$class.dropWhile:(Lscala/collection/TraversableLike;Lscala/Function1;)Ljava/lang/Object;
   5:	areturn
  LineNumberTable: 
   line 36: 0

  LocalVariableTable: 
   Start  Length  Slot  Name   Signature
   0      6      0    this       Lscala/collection/immutable/Vector;
   0      6      1    p       Lscala/Function1;


public java.lang.Object init();
  Code:
   Stack=1, Locals=1, Args_size=1
   0:	aload_0
   1:	invokestatic	#654; //Method scala/collection/TraversableLike$class.init:(Lscala/collection/TraversableLike;)Ljava/lang/Object;
   4:	areturn
  LineNumberTable: 
   line 36: 0


public scala.Option lastOption();
  Code:
   Stack=1, Locals=1, Args_size=1
   0:	aload_0
   1:	invokestatic	#659; //Method scala/collection/TraversableLike$class.lastOption:(Lscala/collection/TraversableLike;)Lscala/Option;
   4:	areturn
  LineNumberTable: 
   line 36: 0


public java.lang.Object last();
  Code:
   Stack=1, Locals=1, Args_size=1
   0:	aload_0
   1:	invokestatic	#662; //Method scala/collection/TraversableLike$class.last:(Lscala/collection/TraversableLike;)Ljava/lang/Object;
   4:	areturn
  LineNumberTable: 
   line 36: 0


public java.lang.Object tail();
  Code:
   Stack=1, Locals=1, Args_size=1
   0:	aload_0
   1:	invokestatic	#665; //Method scala/collection/TraversableLike$class.tail:(Lscala/collection/TraversableLike;)Ljava/lang/Object;
   4:	areturn
  LineNumberTable: 
   line 36: 0


public scala.Option headOption();
  Code:
   Stack=1, Locals=1, Args_size=1
   0:	aload_0
   1:	invokestatic	#668; //Method scala/collection/TraversableLike$class.headOption:(Lscala/collection/TraversableLike;)Lscala/Option;
   4:	areturn
  LineNumberTable: 
   line 36: 0


public java.lang.Object max(scala.math.Ordering);
  Code:
   Stack=2, Locals=2, Args_size=2
   0:	aload_0
   1:	aload_1
   2:	invokestatic	#673; //Method scala/collection/TraversableLike$class.max:(Lscala/collection/TraversableLike;Lscala/math/Ordering;)Ljava/lang/Object;
   5:	areturn
  LineNumberTable: 
   line 36: 0

  LocalVariableTable: 
   Start  Length  Slot  Name   Signature
   0      6      0    this       Lscala/collection/immutable/Vector;
   0      6      1    cmp       Lscala/math/Ordering;


public java.lang.Object min(scala.math.Ordering);
  Code:
   Stack=2, Locals=2, Args_size=2
   0:	aload_0
   1:	aload_1
   2:	invokestatic	#678; //Method scala/collection/TraversableLike$class.min:(Lscala/collection/TraversableLike;Lscala/math/Ordering;)Ljava/lang/Object;
   5:	areturn
  LineNumberTable: 
   line 36: 0

  LocalVariableTable: 
   Start  Length  Slot  Name   Signature
   0      6      0    this       Lscala/collection/immutable/Vector;
   0      6      1    cmp       Lscala/math/Ordering;


public java.lang.Object product(scala.math.Numeric);
  Code:
   Stack=2, Locals=2, Args_size=2
   0:	aload_0
   1:	aload_1
   2:	invokestatic	#683; //Method scala/collection/TraversableLike$class.product:(Lscala/collection/TraversableLike;Lscala/math/Numeric;)Ljava/lang/Object;
   5:	areturn
  LineNumberTable: 
   line 36: 0

  LocalVariableTable: 
   Start  Length  Slot  Name   Signature
   0      6      0    this       Lscala/collection/immutable/Vector;
   0      6      1    num       Lscala/math/Numeric;


public java.lang.Object sum(scala.math.Numeric);
  Code:
   Stack=2, Locals=2, Args_size=2
   0:	aload_0
   1:	aload_1
   2:	invokestatic	#688; //Method scala/collection/TraversableLike$class.sum:(Lscala/collection/TraversableLike;Lscala/math/Numeric;)Ljava/lang/Object;
   5:	areturn
  LineNumberTable: 
   line 36: 0

  LocalVariableTable: 
   Start  Length  Slot  Name   Signature
   0      6      0    this       Lscala/collection/immutable/Vector;
   0      6      1    num       Lscala/math/Numeric;


public scala.Option reduceRightOption(scala.Function2);
  Code:
   Stack=2, Locals=2, Args_size=2
   0:	aload_0
   1:	aload_1
   2:	invokestatic	#693; //Method scala/collection/TraversableLike$class.reduceRightOption:(Lscala/collection/TraversableLike;Lscala/Function2;)Lscala/Option;
   5:	areturn
  LineNumberTable: 
   line 36: 0

  LocalVariableTable: 
   Start  Length  Slot  Name   Signature
   0      6      0    this       Lscala/collection/immutable/Vector;
   0      6      1    op       Lscala/Function2;


public scala.Option reduceLeftOption(scala.Function2);
  Code:
   Stack=2, Locals=2, Args_size=2
   0:	aload_0
   1:	aload_1
   2:	invokestatic	#698; //Method scala/collection/TraversableLike$class.reduceLeftOption:(Lscala/collection/TraversableLike;Lscala/Function2;)Lscala/Option;
   5:	areturn
  LineNumberTable: 
   line 36: 0

  LocalVariableTable: 
   Start  Length  Slot  Name   Signature
   0      6      0    this       Lscala/collection/immutable/Vector;
   0      6      1    op       Lscala/Function2;


public java.lang.Object reduceLeft(scala.Function2);
  Code:
   Stack=2, Locals=2, Args_size=2
   0:	aload_0
   1:	aload_1
   2:	invokestatic	#703; //Method scala/collection/TraversableLike$class.reduceLeft:(Lscala/collection/TraversableLike;Lscala/Function2;)Ljava/lang/Object;
   5:	areturn
  LineNumberTable: 
   line 36: 0

  LocalVariableTable: 
   Start  Length  Slot  Name   Signature
   0      6      0    this       Lscala/collection/immutable/Vector;
   0      6      1    op       Lscala/Function2;


public java.lang.Object $colon$bslash(java.lang.Object, scala.Function2);
  Code:
   Stack=3, Locals=3, Args_size=3
   0:	aload_0
   1:	aload_1
   2:	aload_2
   3:	invokestatic	#708; //Method scala/collection/TraversableLike$class.$colon$bslash:(Lscala/collection/TraversableLike;Ljava/lang/Object;Lscala/Function2;)Ljava/lang/Object;
   6:	areturn
  LineNumberTable: 
   line 36: 0

  LocalVariableTable: 
   Start  Length  Slot  Name   Signature
   0      7      0    this       Lscala/collection/immutable/Vector;
   0      7      1    z       Ljava/lang/Object;
   0      7      2    op       Lscala/Function2;


public java.lang.Object $div$colon(java.lang.Object, scala.Function2);
  Code:
   Stack=3, Locals=3, Args_size=3
   0:	aload_0
   1:	aload_1
   2:	aload_2
   3:	invokestatic	#712; //Method scala/collection/TraversableLike$class.$div$colon:(Lscala/collection/TraversableLike;Ljava/lang/Object;Lscala/Function2;)Ljava/lang/Object;
   6:	areturn
  LineNumberTable: 
   line 36: 0

  LocalVariableTable: 
   Start  Length  Slot  Name   Signature
   0      7      0    this       Lscala/collection/immutable/Vector;
   0      7      1    z       Ljava/lang/Object;
   0      7      2    op       Lscala/Function2;


public java.lang.Object foldLeft(java.lang.Object, scala.Function2);
  Code:
   Stack=3, Locals=3, Args_size=3
   0:	aload_0
   1:	aload_1
   2:	aload_2
   3:	invokestatic	#715; //Method scala/collection/TraversableLike$class.foldLeft:(Lscala/collection/TraversableLike;Ljava/lang/Object;Lscala/Function2;)Ljava/lang/Object;
   6:	areturn
  LineNumberTable: 
   line 36: 0

  LocalVariableTable: 
   Start  Length  Slot  Name   Signature
   0      7      0    this       Lscala/collection/immutable/Vector;
   0      7      1    z       Ljava/lang/Object;
   0      7      2    op       Lscala/Function2;


public int count(scala.Function1);
  Code:
   Stack=2, Locals=2, Args_size=2
   0:	aload_0
   1:	aload_1
   2:	invokestatic	#720; //Method scala/collection/TraversableLike$class.count:(Lscala/collection/TraversableLike;Lscala/Function1;)I
   5:	ireturn
  LineNumberTable: 
   line 36: 0

  LocalVariableTable: 
   Start  Length  Slot  Name   Signature
   0      6      0    this       Lscala/collection/immutable/Vector;
   0      6      1    p       Lscala/Function1;


public scala.collection.Map groupBy(scala.Function1);
  Code:
   Stack=2, Locals=2, Args_size=2
   0:	aload_0
   1:	aload_1
   2:	invokestatic	#725; //Method scala/collection/TraversableLike$class.groupBy:(Lscala/collection/TraversableLike;Lscala/Function1;)Lscala/collection/Map;
   5:	areturn
  LineNumberTable: 
   line 36: 0

  LocalVariableTable: 
   Start  Length  Slot  Name   Signature
   0      6      0    this       Lscala/collection/immutable/Vector;
   0      6      1    f       Lscala/Function1;


public scala.Tuple2 partition(scala.Function1);
  Code:
   Stack=2, Locals=2, Args_size=2
   0:	aload_0
   1:	aload_1
   2:	invokestatic	#728; //Method scala/collection/TraversableLike$class.partition:(Lscala/collection/TraversableLike;Lscala/Function1;)Lscala/Tuple2;
   5:	areturn
  LineNumberTable: 
   line 36: 0

  LocalVariableTable: 
   Start  Length  Slot  Name   Signature
   0      6      0    this       Lscala/collection/immutable/Vector;
   0      6      1    p       Lscala/Function1;


public java.lang.Object partialMap(scala.PartialFunction, scala.collection.generic.CanBuildFrom);
  Code:
   Stack=3, Locals=3, Args_size=3
   0:	aload_0
   1:	aload_1
   2:	aload_2
   3:	invokestatic	#733; //Method scala/collection/TraversableLike$class.partialMap:(Lscala/collection/TraversableLike;Lscala/PartialFunction;Lscala/collection/generic/CanBuildFrom;)Ljava/lang/Object;
   6:	areturn
  LineNumberTable: 
   line 36: 0

  LocalVariableTable: 
   Start  Length  Slot  Name   Signature
   0      7      0    this       Lscala/collection/immutable/Vector;
   0      7      1    pf       Lscala/PartialFunction;
   0      7      2    bf       Lscala/collection/generic/CanBuildFrom;


public java.lang.Object filterNot(scala.Function1);
  Code:
   Stack=2, Locals=2, Args_size=2
   0:	aload_0
   1:	aload_1
   2:	invokestatic	#738; //Method scala/collection/TraversableLike$class.filterNot:(Lscala/collection/TraversableLike;Lscala/Function1;)Ljava/lang/Object;
   5:	areturn
  LineNumberTable: 
   line 36: 0

  LocalVariableTable: 
   Start  Length  Slot  Name   Signature
   0      6      0    this       Lscala/collection/immutable/Vector;
   0      6      1    p       Lscala/Function1;


public java.lang.Object filter(scala.Function1);
  Code:
   Stack=2, Locals=2, Args_size=2
   0:	aload_0
   1:	aload_1
   2:	invokestatic	#741; //Method scala/collection/TraversableLike$class.filter:(Lscala/collection/TraversableLike;Lscala/Function1;)Ljava/lang/Object;
   5:	areturn
  LineNumberTable: 
   line 36: 0

  LocalVariableTable: 
   Start  Length  Slot  Name   Signature
   0      6      0    this       Lscala/collection/immutable/Vector;
   0      6      1    p       Lscala/Function1;


public java.lang.Object flatMap(scala.Function1, scala.collection.generic.CanBuildFrom);
  Code:
   Stack=3, Locals=3, Args_size=3
   0:	aload_0
   1:	aload_1
   2:	aload_2
   3:	invokestatic	#745; //Method scala/collection/TraversableLike$class.flatMap:(Lscala/collection/TraversableLike;Lscala/Function1;Lscala/collection/generic/CanBuildFrom;)Ljava/lang/Object;
   6:	areturn
  LineNumberTable: 
   line 36: 0

  LocalVariableTable: 
   Start  Length  Slot  Name   Signature
   0      7      0    this       Lscala/collection/immutable/Vector;
   0      7      1    f       Lscala/Function1;
   0      7      2    bf       Lscala/collection/generic/CanBuildFrom;


public java.lang.Object map(scala.Function1, scala.collection.generic.CanBuildFrom);
  Code:
   Stack=3, Locals=3, Args_size=3
   0:	aload_0
   1:	aload_1
   2:	aload_2
   3:	invokestatic	#748; //Method scala/collection/TraversableLike$class.map:(Lscala/collection/TraversableLike;Lscala/Function1;Lscala/collection/generic/CanBuildFrom;)Ljava/lang/Object;
   6:	areturn
  LineNumberTable: 
   line 36: 0

  LocalVariableTable: 
   Start  Length  Slot  Name   Signature
   0      7      0    this       Lscala/collection/immutable/Vector;
   0      7      1    f       Lscala/Function1;
   0      7      2    bf       Lscala/collection/generic/CanBuildFrom;


public java.lang.Object $plus$plus(scala.collection.Iterator, scala.collection.generic.CanBuildFrom);
  Code:
   Stack=3, Locals=3, Args_size=3
   0:	aload_0
   1:	aload_1
   2:	aload_2
   3:	invokestatic	#753; //Method scala/collection/TraversableLike$class.$plus$plus:(Lscala/collection/TraversableLike;Lscala/collection/Iterator;Lscala/collection/generic/CanBuildFrom;)Ljava/lang/Object;
   6:	areturn
  LineNumberTable: 
   line 36: 0

  LocalVariableTable: 
   Start  Length  Slot  Name   Signature
   0      7      0    this       Lscala/collection/immutable/Vector;
   0      7      1    that       Lscala/collection/Iterator;
   0      7      2    bf       Lscala/collection/generic/CanBuildFrom;


public java.lang.Object $plus$plus(scala.collection.Traversable, scala.collection.generic.CanBuildFrom);
  Code:
   Stack=3, Locals=3, Args_size=3
   0:	aload_0
   1:	aload_1
   2:	aload_2
   3:	invokestatic	#759; //Method scala/collection/TraversableLike$class.$plus$plus:(Lscala/collection/TraversableLike;Lscala/collection/Traversable;Lscala/collection/generic/CanBuildFrom;)Ljava/lang/Object;
   6:	areturn
  LineNumberTable: 
   line 36: 0

  LocalVariableTable: 
   Start  Length  Slot  Name   Signature
   0      7      0    this       Lscala/collection/immutable/Vector;
   0      7      1    that       Lscala/collection/Traversable;
   0      7      2    bf       Lscala/collection/generic/CanBuildFrom;


public boolean hasDefiniteSize();
  Code:
   Stack=1, Locals=1, Args_size=1
   0:	aload_0
   1:	invokestatic	#764; //Method scala/collection/TraversableLike$class.hasDefiniteSize:(Lscala/collection/TraversableLike;)Z
   4:	ireturn
  LineNumberTable: 
   line 36: 0


public boolean nonEmpty();
  Code:
   Stack=1, Locals=1, Args_size=1
   0:	aload_0
   1:	invokestatic	#767; //Method scala/collection/TraversableLike$class.nonEmpty:(Lscala/collection/TraversableLike;)Z
   4:	ireturn
  LineNumberTable: 
   line 36: 0


public java.lang.Object repr();
  Code:
   Stack=1, Locals=1, Args_size=1
   0:	aload_0
   1:	invokestatic	#504; //Method scala/collection/TraversableLike$class.repr:(Lscala/collection/TraversableLike;)Ljava/lang/Object;
   4:	areturn
  LineNumberTable: 
   line 36: 0


public scala.collection.Traversable transpose(scala.Function1);
  Code:
   Stack=2, Locals=2, Args_size=2
   0:	aload_0
   1:	aload_1
   2:	invokestatic	#772; //Method scala/collection/generic/GenericTraversableTemplate$class.transpose:(Lscala/collection/generic/GenericTraversableTemplate;Lscala/Function1;)Lscala/collection/Traversable;
   5:	areturn
  LineNumberTable: 
   line 36: 0

  LocalVariableTable: 
   Start  Length  Slot  Name   Signature
   0      6      0    this       Lscala/collection/immutable/Vector;
   0      6      1    asTraversable       Lscala/Function1;


public scala.collection.Traversable flatten(scala.Function1);
  Code:
   Stack=2, Locals=2, Args_size=2
   0:	aload_0
   1:	aload_1
   2:	invokestatic	#776; //Method scala/collection/generic/GenericTraversableTemplate$class.flatten:(Lscala/collection/generic/GenericTraversableTemplate;Lscala/Function1;)Lscala/collection/Traversable;
   5:	areturn
  LineNumberTable: 
   line 36: 0

  LocalVariableTable: 
   Start  Length  Slot  Name   Signature
   0      6      0    this       Lscala/collection/immutable/Vector;
   0      6      1    asTraversable       Lscala/Function1;


public scala.Tuple2 unzip(scala.Function1);
  Code:
   Stack=2, Locals=2, Args_size=2
   0:	aload_0
   1:	aload_1
   2:	invokestatic	#780; //Method scala/collection/generic/GenericTraversableTemplate$class.unzip:(Lscala/collection/generic/GenericTraversableTemplate;Lscala/Function1;)Lscala/Tuple2;
   5:	areturn
  LineNumberTable: 
   line 36: 0

  LocalVariableTable: 
   Start  Length  Slot  Name   Signature
   0      6      0    this       Lscala/collection/immutable/Vector;
   0      6      1    asPair       Lscala/Function1;


public scala.collection.mutable.Builder genericBuilder();
  Code:
   Stack=1, Locals=1, Args_size=1
   0:	aload_0
   1:	invokestatic	#786; //Method scala/collection/generic/GenericTraversableTemplate$class.genericBuilder:(Lscala/collection/generic/GenericTraversableTemplate;)Lscala/collection/mutable/Builder;
   4:	areturn
  LineNumberTable: 
   line 36: 0


public scala.collection.mutable.Builder newBuilder();
  Code:
   Stack=1, Locals=1, Args_size=1
   0:	aload_0
   1:	invokestatic	#789; //Method scala/collection/generic/GenericTraversableTemplate$class.newBuilder:(Lscala/collection/generic/GenericTraversableTemplate;)Lscala/collection/mutable/Builder;
   4:	areturn
  LineNumberTable: 
   line 36: 0


public scala.Option firstOption();
  Code:
   Stack=1, Locals=1, Args_size=1
   0:	aload_0
   1:	invokestatic	#793; //Method scala/collection/IterableLike$class.firstOption:(Lscala/collection/IterableLike;)Lscala/Option;
   4:	areturn
  LineNumberTable: 
   line 36: 0


public java.lang.Object first();
  Code:
   Stack=1, Locals=1, Args_size=1
   0:	aload_0
   1:	invokestatic	#797; //Method scala/collection/IterableLike$class.first:(Lscala/collection/IterableLike;)Ljava/lang/Object;
   4:	areturn
  LineNumberTable: 
   line 36: 0


public boolean canEqual(java.lang.Object);
  Code:
   Stack=2, Locals=2, Args_size=2
   0:	aload_0
   1:	aload_1
   2:	invokestatic	#801; //Method scala/collection/IterableLike$class.canEqual:(Lscala/collection/IterableLike;Ljava/lang/Object;)Z
   5:	ireturn
  LineNumberTable: 
   line 36: 0

  LocalVariableTable: 
   Start  Length  Slot  Name   Signature
   0      6      0    this       Lscala/collection/immutable/Vector;
   0      6      1    that       Ljava/lang/Object;


public scala.collection.immutable.Stream toStream();
  Code:
   Stack=1, Locals=1, Args_size=1
   0:	aload_0
   1:	invokestatic	#806; //Method scala/collection/IterableLike$class.toStream:(Lscala/collection/IterableLike;)Lscala/collection/immutable/Stream;
   4:	areturn
  LineNumberTable: 
   line 36: 0


public boolean sameElements(scala.collection.Iterable);
  Code:
   Stack=2, Locals=2, Args_size=2
   0:	aload_0
   1:	aload_1
   2:	invokestatic	#811; //Method scala/collection/IterableLike$class.sameElements:(Lscala/collection/IterableLike;Lscala/collection/Iterable;)Z
   5:	ireturn
  LineNumberTable: 
   line 36: 0

  LocalVariableTable: 
   Start  Length  Slot  Name   Signature
   0      6      0    this       Lscala/collection/immutable/Vector;
   0      6      1    that       Lscala/collection/Iterable;


public java.lang.Object zipWithIndex(scala.collection.generic.CanBuildFrom);
  Code:
   Stack=2, Locals=2, Args_size=2
   0:	aload_0
   1:	aload_1
   2:	invokestatic	#817; //Method scala/collection/IterableLike$class.zipWithIndex:(Lscala/collection/IterableLike;Lscala/collection/generic/CanBuildFrom;)Ljava/lang/Object;
   5:	areturn
  LineNumberTable: 
   line 36: 0

  LocalVariableTable: 
   Start  Length  Slot  Name   Signature
   0      6      0    this       Lscala/collection/immutable/Vector;
   0      6      1    bf       Lscala/collection/generic/CanBuildFrom;


public java.lang.Object zipAll(scala.collection.Iterable, java.lang.Object, java.lang.Object, scala.collection.generic.CanBuildFrom);
  Code:
   Stack=5, Locals=5, Args_size=5
   0:	aload_0
   1:	aload_1
   2:	aload_2
   3:	aload_3
   4:	aload	4
   6:	invokestatic	#822; //Method scala/collection/IterableLike$class.zipAll:(Lscala/collection/IterableLike;Lscala/collection/Iterable;Ljava/lang/Object;Ljava/lang/Object;Lscala/collection/generic/CanBuildFrom;)Ljava/lang/Object;
   9:	areturn
  LineNumberTable: 
   line 36: 0

  LocalVariableTable: 
   Start  Length  Slot  Name   Signature
   0      10      0    this       Lscala/collection/immutable/Vector;
   0      10      1    that       Lscala/collection/Iterable;
   0      10      2    thisElem       Ljava/lang/Object;
   0      10      3    thatElem       Ljava/lang/Object;
   0      10      4    bf       Lscala/collection/generic/CanBuildFrom;


public java.lang.Object zip(scala.collection.Iterable, scala.collection.generic.CanBuildFrom);
  Code:
   Stack=3, Locals=3, Args_size=3
   0:	aload_0
   1:	aload_1
   2:	aload_2
   3:	invokestatic	#829; //Method scala/collection/IterableLike$class.zip:(Lscala/collection/IterableLike;Lscala/collection/Iterable;Lscala/collection/generic/CanBuildFrom;)Ljava/lang/Object;
   6:	areturn
  LineNumberTable: 
   line 36: 0

  LocalVariableTable: 
   Start  Length  Slot  Name   Signature
   0      7      0    this       Lscala/collection/immutable/Vector;
   0      7      1    that       Lscala/collection/Iterable;
   0      7      2    bf       Lscala/collection/generic/CanBuildFrom;


public void copyToArray(java.lang.Object, int, int);
  Code:
   Stack=4, Locals=4, Args_size=4
   0:	aload_0
   1:	aload_1
   2:	iload_2
   3:	iload_3
   4:	invokestatic	#833; //Method scala/collection/IterableLike$class.copyToArray:(Lscala/collection/IterableLike;Ljava/lang/Object;II)V
   7:	return
  LineNumberTable: 
   line 36: 0

  LocalVariableTable: 
   Start  Length  Slot  Name   Signature
   0      8      0    this       Lscala/collection/immutable/Vector;
   0      8      1    xs       Ljava/lang/Object;
   0      8      2    start       I
   0      8      3    len       I


public java.lang.Object takeWhile(scala.Function1);
  Code:
   Stack=2, Locals=2, Args_size=2
   0:	aload_0
   1:	aload_1
   2:	invokestatic	#837; //Method scala/collection/IterableLike$class.takeWhile:(Lscala/collection/IterableLike;Lscala/Function1;)Ljava/lang/Object;
   5:	areturn
  LineNumberTable: 
   line 36: 0

  LocalVariableTable: 
   Start  Length  Slot  Name   Signature
   0      6      0    this       Lscala/collection/immutable/Vector;
   0      6      1    p       Lscala/Function1;


public java.lang.Object slice(int, int);
  Code:
   Stack=3, Locals=3, Args_size=3
   0:	aload_0
   1:	iload_1
   2:	iload_2
   3:	invokestatic	#841; //Method scala/collection/IterableLike$class.slice:(Lscala/collection/IterableLike;II)Ljava/lang/Object;
   6:	areturn
  LineNumberTable: 
   line 36: 0

  LocalVariableTable: 
   Start  Length  Slot  Name   Signature
   0      7      0    this       Lscala/collection/immutable/Vector;
   0      7      1    from       I
   0      7      2    until       I


public java.lang.Object head();
  Code:
   Stack=1, Locals=1, Args_size=1
   0:	aload_0
   1:	invokestatic	#844; //Method scala/collection/IterableLike$class.head:(Lscala/collection/IterableLike;)Ljava/lang/Object;
   4:	areturn
  LineNumberTable: 
   line 36: 0


public scala.collection.Iterable toIterable();
  Code:
   Stack=1, Locals=1, Args_size=1
   0:	aload_0
   1:	invokestatic	#848; //Method scala/collection/IterableLike$class.toIterable:(Lscala/collection/IterableLike;)Lscala/collection/Iterable;
   4:	areturn
  LineNumberTable: 
   line 36: 0


public java.lang.Object reduceRight(scala.Function2);
  Code:
   Stack=2, Locals=2, Args_size=2
   0:	aload_0
   1:	aload_1
   2:	invokestatic	#852; //Method scala/collection/IterableLike$class.reduceRight:(Lscala/collection/IterableLike;Lscala/Function2;)Ljava/lang/Object;
   5:	areturn
  LineNumberTable: 
   line 36: 0

  LocalVariableTable: 
   Start  Length  Slot  Name   Signature
   0      6      0    this       Lscala/collection/immutable/Vector;
   0      6      1    op       Lscala/Function2;


public java.lang.Object foldRight(java.lang.Object, scala.Function2);
  Code:
   Stack=3, Locals=3, Args_size=3
   0:	aload_0
   1:	aload_1
   2:	aload_2
   3:	invokestatic	#856; //Method scala/collection/IterableLike$class.foldRight:(Lscala/collection/IterableLike;Ljava/lang/Object;Lscala/Function2;)Ljava/lang/Object;
   6:	areturn
  LineNumberTable: 
   line 36: 0

  LocalVariableTable: 
   Start  Length  Slot  Name   Signature
   0      7      0    this       Lscala/collection/immutable/Vector;
   0      7      1    z       Ljava/lang/Object;
   0      7      2    op       Lscala/Function2;


public boolean isEmpty();
  Code:
   Stack=1, Locals=1, Args_size=1
   0:	aload_0
   1:	invokestatic	#860; //Method scala/collection/IterableLike$class.isEmpty:(Lscala/collection/IterableLike;)Z
   4:	ireturn
  LineNumberTable: 
   line 36: 0


public scala.Option find(scala.Function1);
  Code:
   Stack=2, Locals=2, Args_size=2
   0:	aload_0
   1:	aload_1
   2:	invokestatic	#865; //Method scala/collection/IterableLike$class.find:(Lscala/collection/IterableLike;Lscala/Function1;)Lscala/Option;
   5:	areturn
  LineNumberTable: 
   line 36: 0

  LocalVariableTable: 
   Start  Length  Slot  Name   Signature
   0      6      0    this       Lscala/collection/immutable/Vector;
   0      6      1    p       Lscala/Function1;


public boolean exists(scala.Function1);
  Code:
   Stack=2, Locals=2, Args_size=2
   0:	aload_0
   1:	aload_1
   2:	invokestatic	#870; //Method scala/collection/IterableLike$class.exists:(Lscala/collection/IterableLike;Lscala/Function1;)Z
   5:	ireturn
  LineNumberTable: 
   line 36: 0

  LocalVariableTable: 
   Start  Length  Slot  Name   Signature
   0      6      0    this       Lscala/collection/immutable/Vector;
   0      6      1    p       Lscala/Function1;


public boolean forall(scala.Function1);
  Code:
   Stack=2, Locals=2, Args_size=2
   0:	aload_0
   1:	aload_1
   2:	invokestatic	#873; //Method scala/collection/IterableLike$class.forall:(Lscala/collection/IterableLike;Lscala/Function1;)Z
   5:	ireturn
  LineNumberTable: 
   line 36: 0

  LocalVariableTable: 
   Start  Length  Slot  Name   Signature
   0      6      0    this       Lscala/collection/immutable/Vector;
   0      6      1    p       Lscala/Function1;


public void foreach(scala.Function1);
  Code:
   Stack=2, Locals=2, Args_size=2
   0:	aload_0
   1:	aload_1
   2:	invokestatic	#877; //Method scala/collection/IterableLike$class.foreach:(Lscala/collection/IterableLike;Lscala/Function1;)V
   5:	return
  LineNumberTable: 
   line 36: 0

  LocalVariableTable: 
   Start  Length  Slot  Name   Signature
   0      6      0    this       Lscala/collection/immutable/Vector;
   0      6      1    f       Lscala/Function1;


public scala.collection.Iterator elements();
  Code:
   Stack=1, Locals=1, Args_size=1
   0:	aload_0
   1:	invokestatic	#881; //Method scala/collection/IterableLike$class.elements:(Lscala/collection/IterableLike;)Lscala/collection/Iterator;
   4:	areturn
  LineNumberTable: 
   line 36: 0


public scala.Function1 compose(scala.Function1);
  Code:
   Stack=2, Locals=2, Args_size=2
   0:	aload_0
   1:	aload_1
   2:	invokestatic	#885; //Method scala/Function1$class.compose:(Lscala/Function1;Lscala/Function1;)Lscala/Function1;
   5:	areturn
  LineNumberTable: 
   line 36: 0

  LocalVariableTable: 
   Start  Length  Slot  Name   Signature
   0      6      0    this       Lscala/collection/immutable/Vector;
   0      6      1    g       Lscala/Function1;


public scala.Function1 lift();
  Code:
   Stack=1, Locals=1, Args_size=1
   0:	aload_0
   1:	invokestatic	#890; //Method scala/PartialFunction$class.lift:(Lscala/PartialFunction;)Lscala/Function1;
   4:	areturn
  LineNumberTable: 
   line 36: 0


public scala.PartialFunction andThen(scala.Function1);
  Code:
   Stack=2, Locals=2, Args_size=2
   0:	aload_0
   1:	aload_1
   2:	invokestatic	#893; //Method scala/PartialFunction$class.andThen:(Lscala/PartialFunction;Lscala/Function1;)Lscala/PartialFunction;
   5:	areturn
  LineNumberTable: 
   line 36: 0

  LocalVariableTable: 
   Start  Length  Slot  Name   Signature
   0      6      0    this       Lscala/collection/immutable/Vector;
   0      6      1    k       Lscala/Function1;


public scala.PartialFunction orElse(scala.PartialFunction);
  Code:
   Stack=2, Locals=2, Args_size=2
   0:	aload_0
   1:	aload_1
   2:	invokestatic	#899; //Method scala/PartialFunction$class.orElse:(Lscala/PartialFunction;Lscala/PartialFunction;)Lscala/PartialFunction;
   5:	areturn
  LineNumberTable: 
   line 36: 0

  LocalVariableTable: 
   Start  Length  Slot  Name   Signature
   0      6      0    this       Lscala/collection/immutable/Vector;
   0      6      1    that       Lscala/PartialFunction;


public java.lang.Object projection();
  Code:
   Stack=1, Locals=1, Args_size=1
   0:	aload_0
   1:	invokestatic	#903; //Method scala/collection/SeqLike$class.projection:(Lscala/collection/SeqLike;)Ljava/lang/Object;
   4:	areturn
  LineNumberTable: 
   line 36: 0


public boolean equalsWith(scala.collection.Seq, scala.Function2);
  Code:
   Stack=3, Locals=3, Args_size=3
   0:	aload_0
   1:	aload_1
   2:	aload_2
   3:	invokestatic	#908; //Method scala/collection/SeqLike$class.equalsWith:(Lscala/collection/SeqLike;Lscala/collection/Seq;Lscala/Function2;)Z
   6:	ireturn
  LineNumberTable: 
   line 36: 0

  LocalVariableTable: 
   Start  Length  Slot  Name   Signature
   0      7      0    this       Lscala/collection/immutable/Vector;
   0      7      1    that       Lscala/collection/Seq;
   0      7      2    f       Lscala/Function2;


public int findLastIndexOf(scala.Function1);
  Code:
   Stack=2, Locals=2, Args_size=2
   0:	aload_0
   1:	aload_1
   2:	invokestatic	#913; //Method scala/collection/SeqLike$class.findLastIndexOf:(Lscala/collection/SeqLike;Lscala/Function1;)I
   5:	ireturn
  LineNumberTable: 
   line 36: 0

  LocalVariableTable: 
   Start  Length  Slot  Name   Signature
   0      6      0    this       Lscala/collection/immutable/Vector;
   0      6      1    p       Lscala/Function1;


public java.lang.String toString();
  Code:
   Stack=1, Locals=1, Args_size=1
   0:	aload_0
   1:	invokestatic	#916; //Method scala/collection/SeqLike$class.toString:(Lscala/collection/SeqLike;)Ljava/lang/String;
   4:	areturn
  LineNumberTable: 
   line 36: 0


public boolean equals(java.lang.Object);
  Code:
   Stack=2, Locals=2, Args_size=2
   0:	aload_0
   1:	aload_1
   2:	invokestatic	#920; //Method scala/collection/SeqLike$class.equals:(Lscala/collection/SeqLike;Ljava/lang/Object;)Z
   5:	ireturn
  LineNumberTable: 
   line 36: 0

  LocalVariableTable: 
   Start  Length  Slot  Name   Signature
   0      6      0    this       Lscala/collection/immutable/Vector;
   0      6      1    that       Ljava/lang/Object;


public int hashCode();
  Code:
   Stack=1, Locals=1, Args_size=1
   0:	aload_0
   1:	invokestatic	#924; //Method scala/collection/SeqLike$class.hashCode:(Lscala/collection/SeqLike;)I
   4:	ireturn
  LineNumberTable: 
   line 36: 0


public scala.collection.SeqView view(int, int);
  Code:
   Stack=3, Locals=3, Args_size=3
   0:	aload_0
   1:	iload_1
   2:	iload_2
   3:	invokestatic	#927; //Method scala/collection/SeqLike$class.view:(Lscala/collection/SeqLike;II)Lscala/collection/SeqView;
   6:	areturn
  LineNumberTable: 
   line 36: 0

  LocalVariableTable: 
   Start  Length  Slot  Name   Signature
   0      7      0    this       Lscala/collection/immutable/Vector;
   0      7      1    from       I
   0      7      2    until       I


public java.lang.Object view();
  Code:
   Stack=1, Locals=1, Args_size=1
   0:	aload_0
   1:	invokestatic	#929; //Method scala/collection/SeqLike$class.view:(Lscala/collection/SeqLike;)Ljava/lang/Object;
   4:	areturn
  LineNumberTable: 
   line 36: 0


public scala.collection.immutable.Range indices();
  Code:
   Stack=1, Locals=1, Args_size=1
   0:	aload_0
   1:	invokestatic	#934; //Method scala/collection/SeqLike$class.indices:(Lscala/collection/SeqLike;)Lscala/collection/immutable/Range;
   4:	areturn
  LineNumberTable: 
   line 36: 0


public scala.collection.Seq toSeq();
  Code:
   Stack=1, Locals=1, Args_size=1
   0:	aload_0
   1:	invokestatic	#938; //Method scala/collection/SeqLike$class.toSeq:(Lscala/collection/SeqLike;)Lscala/collection/Seq;
   4:	areturn
  LineNumberTable: 
   line 36: 0


public java.lang.Object sortBy(scala.Function1, scala.math.Ordering);
  Code:
   Stack=3, Locals=3, Args_size=3
   0:	aload_0
   1:	aload_1
   2:	aload_2
   3:	invokestatic	#943; //Method scala/collection/SeqLike$class.sortBy:(Lscala/collection/SeqLike;Lscala/Function1;Lscala/math/Ordering;)Ljava/lang/Object;
   6:	areturn
  LineNumberTable: 
   line 36: 0

  LocalVariableTable: 
   Start  Length  Slot  Name   Signature
   0      7      0    this       Lscala/collection/immutable/Vector;
   0      7      1    f       Lscala/Function1;
   0      7      2    ord       Lscala/math/Ordering;


public java.lang.Object sortWith(scala.math.Ordering);
  Code:
   Stack=2, Locals=2, Args_size=2
   0:	aload_0
   1:	aload_1
   2:	invokestatic	#948; //Method scala/collection/SeqLike$class.sortWith:(Lscala/collection/SeqLike;Lscala/math/Ordering;)Ljava/lang/Object;
   5:	areturn
  LineNumberTable: 
   line 36: 0

  LocalVariableTable: 
   Start  Length  Slot  Name   Signature
   0      6      0    this       Lscala/collection/immutable/Vector;
   0      6      1    ord       Lscala/math/Ordering;


public java.lang.Object sortWith(scala.Function2);
  Code:
   Stack=2, Locals=2, Args_size=2
   0:	aload_0
   1:	aload_1
   2:	invokestatic	#951; //Method scala/collection/SeqLike$class.sortWith:(Lscala/collection/SeqLike;Lscala/Function2;)Ljava/lang/Object;
   5:	areturn
  LineNumberTable: 
   line 36: 0

  LocalVariableTable: 
   Start  Length  Slot  Name   Signature
   0      6      0    this       Lscala/collection/immutable/Vector;
   0      6      1    lt       Lscala/Function2;


public boolean corresponds(scala.collection.Seq, scala.Function2);
  Code:
   Stack=3, Locals=3, Args_size=3
   0:	aload_0
   1:	aload_1
   2:	aload_2
   3:	invokestatic	#955; //Method scala/collection/SeqLike$class.corresponds:(Lscala/collection/SeqLike;Lscala/collection/Seq;Lscala/Function2;)Z
   6:	ireturn
  LineNumberTable: 
   line 36: 0

  LocalVariableTable: 
   Start  Length  Slot  Name   Signature
   0      7      0    this       Lscala/collection/immutable/Vector;
   0      7      1    that       Lscala/collection/Seq;
   0      7      2    p       Lscala/Function2;


public java.lang.Object padTo(int, java.lang.Object, scala.collection.generic.CanBuildFrom);
  Code:
   Stack=4, Locals=4, Args_size=4
   0:	aload_0
   1:	iload_1
   2:	aload_2
   3:	aload_3
   4:	invokestatic	#959; //Method scala/collection/SeqLike$class.padTo:(Lscala/collection/SeqLike;ILjava/lang/Object;Lscala/collection/generic/CanBuildFrom;)Ljava/lang/Object;
   7:	areturn
  LineNumberTable: 
   line 36: 0

  LocalVariableTable: 
   Start  Length  Slot  Name   Signature
   0      8      0    this       Lscala/collection/immutable/Vector;
   0      8      1    len       I
   0      8      2    elem       Ljava/lang/Object;
   0      8      3    bf       Lscala/collection/generic/CanBuildFrom;


public java.lang.Object patch(int, scala.collection.Seq, int, scala.collection.generic.CanBuildFrom);
  Code:
   Stack=5, Locals=5, Args_size=5
   0:	aload_0
   1:	iload_1
   2:	aload_2
   3:	iload_3
   4:	aload	4
   6:	invokestatic	#964; //Method scala/collection/SeqLike$class.patch:(Lscala/collection/SeqLike;ILscala/collection/Seq;ILscala/collection/generic/CanBuildFrom;)Ljava/lang/Object;
   9:	areturn
  LineNumberTable: 
   line 36: 0

  LocalVariableTable: 
   Start  Length  Slot  Name   Signature
   0      10      0    this       Lscala/collection/immutable/Vector;
   0      10      1    from       I
   0      10      2    patch       Lscala/collection/Seq;
   0      10      3    replaced       I
   0      10      4    bf       Lscala/collection/generic/CanBuildFrom;


public java.lang.Object removeDuplicates();
  Code:
   Stack=1, Locals=1, Args_size=1
   0:	aload_0
   1:	invokestatic	#968; //Method scala/collection/SeqLike$class.removeDuplicates:(Lscala/collection/SeqLike;)Ljava/lang/Object;
   4:	areturn
  LineNumberTable: 
   line 36: 0


public java.lang.Object intersect(scala.collection.Seq);
  Code:
   Stack=2, Locals=2, Args_size=2
   0:	aload_0
   1:	aload_1
   2:	invokestatic	#973; //Method scala/collection/SeqLike$class.intersect:(Lscala/collection/SeqLike;Lscala/collection/Seq;)Ljava/lang/Object;
   5:	areturn
  LineNumberTable: 
   line 36: 0

  LocalVariableTable: 
   Start  Length  Slot  Name   Signature
   0      6      0    this       Lscala/collection/immutable/Vector;
   0      6      1    that       Lscala/collection/Seq;


public java.lang.Object diff(scala.collection.Seq);
  Code:
   Stack=2, Locals=2, Args_size=2
   0:	aload_0
   1:	aload_1
   2:	invokestatic	#976; //Method scala/collection/SeqLike$class.diff:(Lscala/collection/SeqLike;Lscala/collection/Seq;)Ljava/lang/Object;
   5:	areturn
  LineNumberTable: 
   line 36: 0

  LocalVariableTable: 
   Start  Length  Slot  Name   Signature
   0      6      0    this       Lscala/collection/immutable/Vector;
   0      6      1    that       Lscala/collection/Seq;


public java.lang.Object union(scala.collection.Seq, scala.collection.generic.CanBuildFrom);
  Code:
   Stack=3, Locals=3, Args_size=3
   0:	aload_0
   1:	aload_1
   2:	aload_2
   3:	invokestatic	#981; //Method scala/collection/SeqLike$class.union:(Lscala/collection/SeqLike;Lscala/collection/Seq;Lscala/collection/generic/CanBuildFrom;)Ljava/lang/Object;
   6:	areturn
  LineNumberTable: 
   line 36: 0

  LocalVariableTable: 
   Start  Length  Slot  Name   Signature
   0      7      0    this       Lscala/collection/immutable/Vector;
   0      7      1    that       Lscala/collection/Seq;
   0      7      2    bf       Lscala/collection/generic/CanBuildFrom;


public boolean contains(java.lang.Object);
  Code:
   Stack=2, Locals=2, Args_size=2
   0:	aload_0
   1:	aload_1
   2:	invokestatic	#984; //Method scala/collection/SeqLike$class.contains:(Lscala/collection/SeqLike;Ljava/lang/Object;)Z
   5:	ireturn
  LineNumberTable: 
   line 36: 0

  LocalVariableTable: 
   Start  Length  Slot  Name   Signature
   0      6      0    this       Lscala/collection/immutable/Vector;
   0      6      1    elem       Ljava/lang/Object;


public boolean containsSlice(scala.collection.Seq);
  Code:
   Stack=2, Locals=2, Args_size=2
   0:	aload_0
   1:	aload_1
   2:	invokestatic	#989; //Method scala/collection/SeqLike$class.containsSlice:(Lscala/collection/SeqLike;Lscala/collection/Seq;)Z
   5:	ireturn
  LineNumberTable: 
   line 36: 0

  LocalVariableTable: 
   Start  Length  Slot  Name   Signature
   0      6      0    this       Lscala/collection/immutable/Vector;
   0      6      1    that       Lscala/collection/Seq;


public int lastIndexOfSlice(scala.collection.Seq, int);
  Code:
   Stack=3, Locals=3, Args_size=3
   0:	aload_0
   1:	aload_1
   2:	iload_2
   3:	invokestatic	#994; //Method scala/collection/SeqLike$class.lastIndexOfSlice:(Lscala/collection/SeqLike;Lscala/collection/Seq;I)I
   6:	ireturn
  LineNumberTable: 
   line 36: 0

  LocalVariableTable: 
   Start  Length  Slot  Name   Signature
   0      7      0    this       Lscala/collection/immutable/Vector;
   0      7      1    that       Lscala/collection/Seq;
   0      7      2    end       I


public int lastIndexOfSlice(scala.collection.Seq);
  Code:
   Stack=2, Locals=2, Args_size=2
   0:	aload_0
   1:	aload_1
   2:	invokestatic	#998; //Method scala/collection/SeqLike$class.lastIndexOfSlice:(Lscala/collection/SeqLike;Lscala/collection/Seq;)I
   5:	ireturn
  LineNumberTable: 
   line 36: 0

  LocalVariableTable: 
   Start  Length  Slot  Name   Signature
   0      6      0    this       Lscala/collection/immutable/Vector;
   0      6      1    that       Lscala/collection/Seq;


public int indexOfSlice(scala.collection.Seq, int);
  Code:
   Stack=3, Locals=3, Args_size=3
   0:	aload_0
   1:	aload_1
   2:	iload_2
   3:	invokestatic	#1001; //Method scala/collection/SeqLike$class.indexOfSlice:(Lscala/collection/SeqLike;Lscala/collection/Seq;I)I
   6:	ireturn
  LineNumberTable: 
   line 36: 0

  LocalVariableTable: 
   Start  Length  Slot  Name   Signature
   0      7      0    this       Lscala/collection/immutable/Vector;
   0      7      1    that       Lscala/collection/Seq;
   0      7      2    from       I


public int indexOfSlice(scala.collection.Seq);
  Code:
   Stack=2, Locals=2, Args_size=2
   0:	aload_0
   1:	aload_1
   2:	invokestatic	#1003; //Method scala/collection/SeqLike$class.indexOfSlice:(Lscala/collection/SeqLike;Lscala/collection/Seq;)I
   5:	ireturn
  LineNumberTable: 
   line 36: 0

  LocalVariableTable: 
   Start  Length  Slot  Name   Signature
   0      6      0    this       Lscala/collection/immutable/Vector;
   0      6      1    that       Lscala/collection/Seq;


public boolean endsWith(scala.collection.Seq);
  Code:
   Stack=2, Locals=2, Args_size=2
   0:	aload_0
   1:	aload_1
   2:	invokestatic	#1006; //Method scala/collection/SeqLike$class.endsWith:(Lscala/collection/SeqLike;Lscala/collection/Seq;)Z
   5:	ireturn
  LineNumberTable: 
   line 36: 0

  LocalVariableTable: 
   Start  Length  Slot  Name   Signature
   0      6      0    this       Lscala/collection/immutable/Vector;
   0      6      1    that       Lscala/collection/Seq;


public boolean startsWith(scala.collection.Seq);
  Code:
   Stack=2, Locals=2, Args_size=2
   0:	aload_0
   1:	aload_1
   2:	invokestatic	#1009; //Method scala/collection/SeqLike$class.startsWith:(Lscala/collection/SeqLike;Lscala/collection/Seq;)Z
   5:	ireturn
  LineNumberTable: 
   line 36: 0

  LocalVariableTable: 
   Start  Length  Slot  Name   Signature
   0      6      0    this       Lscala/collection/immutable/Vector;
   0      6      1    that       Lscala/collection/Seq;


public boolean startsWith(scala.collection.Seq, int);
  Code:
   Stack=3, Locals=3, Args_size=3
   0:	aload_0
   1:	aload_1
   2:	iload_2
   3:	invokestatic	#1013; //Method scala/collection/SeqLike$class.startsWith:(Lscala/collection/SeqLike;Lscala/collection/Seq;I)Z
   6:	ireturn
  LineNumberTable: 
   line 36: 0

  LocalVariableTable: 
   Start  Length  Slot  Name   Signature
   0      7      0    this       Lscala/collection/immutable/Vector;
   0      7      1    that       Lscala/collection/Seq;
   0      7      2    offset       I


public scala.collection.Iterator reversedElements();
  Code:
   Stack=1, Locals=1, Args_size=1
   0:	aload_0
   1:	invokestatic	#1018; //Method scala/collection/SeqLike$class.reversedElements:(Lscala/collection/SeqLike;)Lscala/collection/Iterator;
   4:	areturn
  LineNumberTable: 
   line 36: 0


public scala.collection.Iterator reverseIterator();
  Code:
   Stack=1, Locals=1, Args_size=1
   0:	aload_0
   1:	invokestatic	#1021; //Method scala/collection/SeqLike$class.reverseIterator:(Lscala/collection/SeqLike;)Lscala/collection/Iterator;
   4:	areturn
  LineNumberTable: 
   line 36: 0


public java.lang.Object reverseMap(scala.Function1, scala.collection.generic.CanBuildFrom);
  Code:
   Stack=3, Locals=3, Args_size=3
   0:	aload_0
   1:	aload_1
   2:	aload_2
   3:	invokestatic	#1025; //Method scala/collection/SeqLike$class.reverseMap:(Lscala/collection/SeqLike;Lscala/Function1;Lscala/collection/generic/CanBuildFrom;)Ljava/lang/Object;
   6:	areturn
  LineNumberTable: 
   line 36: 0

  LocalVariableTable: 
   Start  Length  Slot  Name   Signature
   0      7      0    this       Lscala/collection/immutable/Vector;
   0      7      1    f       Lscala/Function1;
   0      7      2    bf       Lscala/collection/generic/CanBuildFrom;


public java.lang.Object reverse();
  Code:
   Stack=1, Locals=1, Args_size=1
   0:	aload_0
   1:	invokestatic	#1028; //Method scala/collection/SeqLike$class.reverse:(Lscala/collection/SeqLike;)Ljava/lang/Object;
   4:	areturn
  LineNumberTable: 
   line 36: 0


public int lastIndexWhere(scala.Function1, int);
  Code:
   Stack=3, Locals=3, Args_size=3
   0:	aload_0
   1:	aload_1
   2:	iload_2
   3:	invokestatic	#1033; //Method scala/collection/SeqLike$class.lastIndexWhere:(Lscala/collection/SeqLike;Lscala/Function1;I)I
   6:	ireturn
  LineNumberTable: 
   line 36: 0

  LocalVariableTable: 
   Start  Length  Slot  Name   Signature
   0      7      0    this       Lscala/collection/immutable/Vector;
   0      7      1    p       Lscala/Function1;
   0      7      2    end       I


public int lastIndexWhere(scala.Function1);
  Code:
   Stack=2, Locals=2, Args_size=2
   0:	aload_0
   1:	aload_1
   2:	invokestatic	#1035; //Method scala/collection/SeqLike$class.lastIndexWhere:(Lscala/collection/SeqLike;Lscala/Function1;)I
   5:	ireturn
  LineNumberTable: 
   line 36: 0

  LocalVariableTable: 
   Start  Length  Slot  Name   Signature
   0      6      0    this       Lscala/collection/immutable/Vector;
   0      6      1    p       Lscala/Function1;


public int lastIndexOf(java.lang.Object, int);
  Code:
   Stack=3, Locals=3, Args_size=3
   0:	aload_0
   1:	aload_1
   2:	iload_2
   3:	invokestatic	#1040; //Method scala/collection/SeqLike$class.lastIndexOf:(Lscala/collection/SeqLike;Ljava/lang/Object;I)I
   6:	ireturn
  LineNumberTable: 
   line 36: 0

  LocalVariableTable: 
   Start  Length  Slot  Name   Signature
   0      7      0    this       Lscala/collection/immutable/Vector;
   0      7      1    elem       Ljava/lang/Object;
   0      7      2    end       I


public int lastIndexOf(java.lang.Object);
  Code:
   Stack=2, Locals=2, Args_size=2
   0:	aload_0
   1:	aload_1
   2:	invokestatic	#1043; //Method scala/collection/SeqLike$class.lastIndexOf:(Lscala/collection/SeqLike;Ljava/lang/Object;)I
   5:	ireturn
  LineNumberTable: 
   line 36: 0

  LocalVariableTable: 
   Start  Length  Slot  Name   Signature
   0      6      0    this       Lscala/collection/immutable/Vector;
   0      6      1    elem       Ljava/lang/Object;


public int indexOf(java.lang.Object, int);
  Code:
   Stack=3, Locals=3, Args_size=3
   0:	aload_0
   1:	aload_1
   2:	iload_2
   3:	invokestatic	#1046; //Method scala/collection/SeqLike$class.indexOf:(Lscala/collection/SeqLike;Ljava/lang/Object;I)I
   6:	ireturn
  LineNumberTable: 
   line 36: 0

  LocalVariableTable: 
   Start  Length  Slot  Name   Signature
   0      7      0    this       Lscala/collection/immutable/Vector;
   0      7      1    elem       Ljava/lang/Object;
   0      7      2    from       I


public int indexOf(java.lang.Object);
  Code:
   Stack=2, Locals=2, Args_size=2
   0:	aload_0
   1:	aload_1
   2:	invokestatic	#1048; //Method scala/collection/SeqLike$class.indexOf:(Lscala/collection/SeqLike;Ljava/lang/Object;)I
   5:	ireturn
  LineNumberTable: 
   line 36: 0

  LocalVariableTable: 
   Start  Length  Slot  Name   Signature
   0      6      0    this       Lscala/collection/immutable/Vector;
   0      6      1    elem       Ljava/lang/Object;


public int findIndexOf(scala.Function1);
  Code:
   Stack=2, Locals=2, Args_size=2
   0:	aload_0
   1:	aload_1
   2:	invokestatic	#1051; //Method scala/collection/SeqLike$class.findIndexOf:(Lscala/collection/SeqLike;Lscala/Function1;)I
   5:	ireturn
  LineNumberTable: 
   line 36: 0

  LocalVariableTable: 
   Start  Length  Slot  Name   Signature
   0      6      0    this       Lscala/collection/immutable/Vector;
   0      6      1    p       Lscala/Function1;


public int indexWhere(scala.Function1, int);
  Code:
   Stack=3, Locals=3, Args_size=3
   0:	aload_0
   1:	aload_1
   2:	iload_2
   3:	invokestatic	#1054; //Method scala/collection/SeqLike$class.indexWhere:(Lscala/collection/SeqLike;Lscala/Function1;I)I
   6:	ireturn
  LineNumberTable: 
   line 36: 0

  LocalVariableTable: 
   Start  Length  Slot  Name   Signature
   0      7      0    this       Lscala/collection/immutable/Vector;
   0      7      1    p       Lscala/Function1;
   0      7      2    from       I


public int indexWhere(scala.Function1);
  Code:
   Stack=2, Locals=2, Args_size=2
   0:	aload_0
   1:	aload_1
   2:	invokestatic	#1056; //Method scala/collection/SeqLike$class.indexWhere:(Lscala/collection/SeqLike;Lscala/Function1;)I
   5:	ireturn
  LineNumberTable: 
   line 36: 0

  LocalVariableTable: 
   Start  Length  Slot  Name   Signature
   0      6      0    this       Lscala/collection/immutable/Vector;
   0      6      1    p       Lscala/Function1;


public int prefixLength(scala.Function1);
  Code:
   Stack=2, Locals=2, Args_size=2
   0:	aload_0
   1:	aload_1
   2:	invokestatic	#1059; //Method scala/collection/SeqLike$class.prefixLength:(Lscala/collection/SeqLike;Lscala/Function1;)I
   5:	ireturn
  LineNumberTable: 
   line 36: 0

  LocalVariableTable: 
   Start  Length  Slot  Name   Signature
   0      6      0    this       Lscala/collection/immutable/Vector;
   0      6      1    p       Lscala/Function1;


public int segmentLength(scala.Function1, int);
  Code:
   Stack=3, Locals=3, Args_size=3
   0:	aload_0
   1:	aload_1
   2:	iload_2
   3:	invokestatic	#1062; //Method scala/collection/SeqLike$class.segmentLength:(Lscala/collection/SeqLike;Lscala/Function1;I)I
   6:	ireturn
  LineNumberTable: 
   line 36: 0

  LocalVariableTable: 
   Start  Length  Slot  Name   Signature
   0      7      0    this       Lscala/collection/immutable/Vector;
   0      7      1    p       Lscala/Function1;
   0      7      2    from       I


public boolean isDefinedAt(int);
  Code:
   Stack=2, Locals=2, Args_size=2
   0:	aload_0
   1:	iload_1
   2:	invokestatic	#1065; //Method scala/collection/SeqLike$class.isDefinedAt:(Lscala/collection/SeqLike;I)Z
   5:	ireturn
  LineNumberTable: 
   line 36: 0

  LocalVariableTable: 
   Start  Length  Slot  Name   Signature
   0      6      0    this       Lscala/collection/immutable/Vector;
   0      6      1    idx       I


public int size();
  Code:
   Stack=1, Locals=1, Args_size=1
   0:	aload_0
   1:	invokestatic	#1068; //Method scala/collection/SeqLike$class.size:(Lscala/collection/SeqLike;)I
   4:	ireturn
  LineNumberTable: 
   line 36: 0


public scala.collection.Seq toCollection(java.lang.Object);
  Code:
   Stack=2, Locals=2, Args_size=2
   0:	aload_0
   1:	aload_1
   2:	invokestatic	#1071; //Method scala/collection/SeqLike$class.toCollection:(Lscala/collection/SeqLike;Ljava/lang/Object;)Lscala/collection/Seq;
   5:	areturn
  LineNumberTable: 
   line 36: 0

  LocalVariableTable: 
   Start  Length  Slot  Name   Signature
   0      6      0    this       Lscala/collection/immutable/Vector;
   0      6      1    repr       Ljava/lang/Object;


public scala.collection.Seq thisCollection();
  Code:
   Stack=1, Locals=1, Args_size=1
   0:	aload_0
   1:	invokestatic	#1073; //Method scala/collection/SeqLike$class.thisCollection:(Lscala/collection/SeqLike;)Lscala/collection/Seq;
   4:	areturn
  LineNumberTable: 
   line 36: 0


public void debug();
  Code:
   Stack=1, Locals=1, Args_size=1
   0:	aload_0
   1:	invokestatic	#423; //Method scala/collection/immutable/VectorPointer$class.debug:(Lscala/collection/immutable/VectorPointer;)V
   4:	return
  LineNumberTable: 
   line 36: 0


public final void gotoFreshPosWritable1(int, int, int);
  Code:
   Stack=4, Locals=4, Args_size=4
   0:	aload_0
   1:	iload_1
   2:	iload_2
   3:	iload_3
   4:	invokestatic	#1076; //Method scala/collection/immutable/VectorPointer$class.gotoFreshPosWritable1:(Lscala/collection/immutable/VectorPointer;III)V
   7:	return
  LineNumberTable: 
   line 36: 0

  LocalVariableTable: 
   Start  Length  Slot  Name   Signature
   0      8      0    this       Lscala/collection/immutable/Vector;
   0      8      1    oldIndex       I
   0      8      2    newIndex       I
   0      8      3    xor       I


public final void gotoFreshPosWritable0(int, int, int);
  Code:
   Stack=4, Locals=4, Args_size=4
   0:	aload_0
   1:	iload_1
   2:	iload_2
   3:	iload_3
   4:	invokestatic	#1078; //Method scala/collection/immutable/VectorPointer$class.gotoFreshPosWritable0:(Lscala/collection/immutable/VectorPointer;III)V
   7:	return
  LineNumberTable: 
   line 36: 0

  LocalVariableTable: 
   Start  Length  Slot  Name   Signature
   0      8      0    this       Lscala/collection/immutable/Vector;
   0      8      1    oldIndex       I
   0      8      2    newIndex       I
   0      8      3    xor       I


public final java.lang.Object[] copyRange(java.lang.Object[], int, int);
  Code:
   Stack=4, Locals=4, Args_size=4
   0:	aload_0
   1:	aload_1
   2:	iload_2
   3:	iload_3
   4:	invokestatic	#1081; //Method scala/collection/immutable/VectorPointer$class.copyRange:(Lscala/collection/immutable/VectorPointer;[Ljava/lang/Object;II)[Ljava/lang/Object;
   7:	areturn
  LineNumberTable: 
   line 36: 0

  LocalVariableTable: 
   Start  Length  Slot  Name   Signature
   0      8      0    this       Lscala/collection/immutable/Vector;
   0      8      1    array       [Ljava/lang/Object;
   0      8      2    oldLeft       I
   0      8      3    newLeft       I


public final void gotoPosWritable1(int, int, int);
  Code:
   Stack=4, Locals=4, Args_size=4
   0:	aload_0
   1:	iload_1
   2:	iload_2
   3:	iload_3
   4:	invokestatic	#1083; //Method scala/collection/immutable/VectorPointer$class.gotoPosWritable1:(Lscala/collection/immutable/VectorPointer;III)V
   7:	return
  LineNumberTable: 
   line 36: 0

  LocalVariableTable: 
   Start  Length  Slot  Name   Signature
   0      8      0    this       Lscala/collection/immutable/Vector;
   0      8      1    oldIndex       I
   0      8      2    newIndex       I
   0      8      3    xor       I


public final void gotoPosWritable0(int, int);
  Code:
   Stack=3, Locals=3, Args_size=3
   0:	aload_0
   1:	iload_1
   2:	iload_2
   3:	invokestatic	#1086; //Method scala/collection/immutable/VectorPointer$class.gotoPosWritable0:(Lscala/collection/immutable/VectorPointer;II)V
   6:	return
  LineNumberTable: 
   line 36: 0

  LocalVariableTable: 
   Start  Length  Slot  Name   Signature
   0      7      0    this       Lscala/collection/immutable/Vector;
   0      7      1    newIndex       I
   0      7      2    xor       I


public final void stabilize(int);
  Code:
   Stack=2, Locals=2, Args_size=2
   0:	aload_0
   1:	iload_1
   2:	invokestatic	#1089; //Method scala/collection/immutable/VectorPointer$class.stabilize:(Lscala/collection/immutable/VectorPointer;I)V
   5:	return
  LineNumberTable: 
   line 36: 0

  LocalVariableTable: 
   Start  Length  Slot  Name   Signature
   0      6      0    this       Lscala/collection/immutable/Vector;
   0      6      1    index       I


public final java.lang.Object[] nullSlotAndCopy(java.lang.Object[], int);
  Code:
   Stack=3, Locals=3, Args_size=3
   0:	aload_0
   1:	aload_1
   2:	iload_2
   3:	invokestatic	#1093; //Method scala/collection/immutable/VectorPointer$class.nullSlotAndCopy:(Lscala/collection/immutable/VectorPointer;[Ljava/lang/Object;I)[Ljava/lang/Object;
   6:	areturn
  LineNumberTable: 
   line 36: 0

  LocalVariableTable: 
   Start  Length  Slot  Name   Signature
   0      7      0    this       Lscala/collection/immutable/Vector;
   0      7      1    array       [Ljava/lang/Object;
   0      7      2    index       I


public final java.lang.Object[] copyOf(java.lang.Object[]);
  Code:
   Stack=2, Locals=2, Args_size=2
   0:	aload_0
   1:	aload_1
   2:	invokestatic	#1098; //Method scala/collection/immutable/VectorPointer$class.copyOf:(Lscala/collection/immutable/VectorPointer;[Ljava/lang/Object;)[Ljava/lang/Object;
   5:	areturn
  LineNumberTable: 
   line 36: 0

  LocalVariableTable: 
   Start  Length  Slot  Name   Signature
   0      6      0    this       Lscala/collection/immutable/Vector;
   0      6      1    a       [Ljava/lang/Object;


public final void gotoNextBlockStartWritable(int, int);
  Code:
   Stack=3, Locals=3, Args_size=3
   0:	aload_0
   1:	iload_1
   2:	iload_2
   3:	invokestatic	#1102; //Method scala/collection/immutable/VectorPointer$class.gotoNextBlockStartWritable:(Lscala/collection/immutable/VectorPointer;II)V
   6:	return
  LineNumberTable: 
   line 36: 0

  LocalVariableTable: 
   Start  Length  Slot  Name   Signature
   0      7      0    this       Lscala/collection/immutable/Vector;
   0      7      1    index       I
   0      7      2    xor       I


public final void gotoNextBlockStart(int, int);
  Code:
   Stack=3, Locals=3, Args_size=3
   0:	aload_0
   1:	iload_1
   2:	iload_2
   3:	invokestatic	#1105; //Method scala/collection/immutable/VectorPointer$class.gotoNextBlockStart:(Lscala/collection/immutable/VectorPointer;II)V
   6:	return
  LineNumberTable: 
   line 36: 0

  LocalVariableTable: 
   Start  Length  Slot  Name   Signature
   0      7      0    this       Lscala/collection/immutable/Vector;
   0      7      1    index       I
   0      7      2    xor       I


public final void gotoPos(int, int);
  Code:
   Stack=3, Locals=3, Args_size=3
   0:	aload_0
   1:	iload_1
   2:	iload_2
   3:	invokestatic	#1107; //Method scala/collection/immutable/VectorPointer$class.gotoPos:(Lscala/collection/immutable/VectorPointer;II)V
   6:	return
  LineNumberTable: 
   line 36: 0

  LocalVariableTable: 
   Start  Length  Slot  Name   Signature
   0      7      0    this       Lscala/collection/immutable/Vector;
   0      7      1    index       I
   0      7      2    xor       I


public final java.lang.Object getElem(int, int);
  Code:
   Stack=3, Locals=3, Args_size=3
   0:	aload_0
   1:	iload_1
   2:	iload_2
   3:	invokestatic	#1110; //Method scala/collection/immutable/VectorPointer$class.getElem:(Lscala/collection/immutable/VectorPointer;II)Ljava/lang/Object;
   6:	areturn
  LineNumberTable: 
   line 36: 0

  LocalVariableTable: 
   Start  Length  Slot  Name   Signature
   0      7      0    this       Lscala/collection/immutable/Vector;
   0      7      1    index       I
   0      7      2    xor       I


public final void initFrom(scala.collection.immutable.VectorPointer, int);
  Code:
   Stack=3, Locals=3, Args_size=3
   0:	aload_0
   1:	aload_1
   2:	iload_2
   3:	invokestatic	#1113; //Method scala/collection/immutable/VectorPointer$class.initFrom:(Lscala/collection/immutable/VectorPointer;Lscala/collection/immutable/VectorPointer;I)V
   6:	return
  LineNumberTable: 
   line 36: 0

  LocalVariableTable: 
   Start  Length  Slot  Name   Signature
   0      7      0    this       Lscala/collection/immutable/Vector;
   0      7      1    that       Lscala/collection/immutable/VectorPointer;
   0      7      2    depth       I


public final void initFrom(scala.collection.immutable.VectorPointer);
  Code:
   Stack=2, Locals=2, Args_size=2
   0:	aload_0
   1:	aload_1
   2:	invokestatic	#1117; //Method scala/collection/immutable/VectorPointer$class.initFrom:(Lscala/collection/immutable/VectorPointer;Lscala/collection/immutable/VectorPointer;)V
   5:	return
  LineNumberTable: 
   line 36: 0

  LocalVariableTable: 
   Start  Length  Slot  Name   Signature
   0      6      0    this       Lscala/collection/immutable/Vector;
   0      6      1    that       Lscala/collection/immutable/VectorPointer;


public void display5_$eq(java.lang.Object[]);
  Code:
   Stack=2, Locals=2, Args_size=2
   0:	aload_0
   1:	aload_1
   2:	putfield	#398; //Field display5:[Ljava/lang/Object;
   5:	return
  LineNumberTable: 
   line 36: 0


public java.lang.Object[] display5();
  Code:
   Stack=1, Locals=1, Args_size=1
   0:	aload_0
   1:	getfield	#398; //Field display5:[Ljava/lang/Object;
   4:	areturn
  LineNumberTable: 
   line 36: 0


public void display4_$eq(java.lang.Object[]);
  Code:
   Stack=2, Locals=2, Args_size=2
   0:	aload_0
   1:	aload_1
   2:	putfield	#400; //Field display4:[Ljava/lang/Object;
   5:	return
  LineNumberTable: 
   line 36: 0


public java.lang.Object[] display4();
  Code:
   Stack=1, Locals=1, Args_size=1
   0:	aload_0
   1:	getfield	#400; //Field display4:[Ljava/lang/Object;
   4:	areturn
  LineNumberTable: 
   line 36: 0


public void display3_$eq(java.lang.Object[]);
  Code:
   Stack=2, Locals=2, Args_size=2
   0:	aload_0
   1:	aload_1
   2:	putfield	#402; //Field display3:[Ljava/lang/Object;
   5:	return
  LineNumberTable: 
   line 36: 0


public java.lang.Object[] display3();
  Code:
   Stack=1, Locals=1, Args_size=1
   0:	aload_0
   1:	getfield	#402; //Field display3:[Ljava/lang/Object;
   4:	areturn
  LineNumberTable: 
   line 36: 0


public void display2_$eq(java.lang.Object[]);
  Code:
   Stack=2, Locals=2, Args_size=2
   0:	aload_0
   1:	aload_1
   2:	putfield	#335; //Field display2:[Ljava/lang/Object;
   5:	return
  LineNumberTable: 
   line 36: 0


public java.lang.Object[] display2();
  Code:
   Stack=1, Locals=1, Args_size=1
   0:	aload_0
   1:	getfield	#335; //Field display2:[Ljava/lang/Object;
   4:	areturn
  LineNumberTable: 
   line 36: 0


public void display1_$eq(java.lang.Object[]);
  Code:
   Stack=2, Locals=2, Args_size=2
   0:	aload_0
   1:	aload_1
   2:	putfield	#327; //Field display1:[Ljava/lang/Object;
   5:	return
  LineNumberTable: 
   line 36: 0


public java.lang.Object[] display1();
  Code:
   Stack=1, Locals=1, Args_size=1
   0:	aload_0
   1:	getfield	#327; //Field display1:[Ljava/lang/Object;
   4:	areturn
  LineNumberTable: 
   line 36: 0


public void display0_$eq(java.lang.Object[]);
  Code:
   Stack=2, Locals=2, Args_size=2
   0:	aload_0
   1:	aload_1
   2:	putfield	#321; //Field display0:[Ljava/lang/Object;
   5:	return
  LineNumberTable: 
   line 36: 0


public java.lang.Object[] display0();
  Code:
   Stack=1, Locals=1, Args_size=1
   0:	aload_0
   1:	getfield	#321; //Field display0:[Ljava/lang/Object;
   4:	areturn
  LineNumberTable: 
   line 36: 0


public void depth_$eq(int);
  Code:
   Stack=2, Locals=2, Args_size=2
   0:	aload_0
   1:	iload_1
   2:	putfield	#383; //Field depth:I
   5:	return
  LineNumberTable: 
   line 36: 0


public int depth();
  Code:
   Stack=1, Locals=1, Args_size=1
   0:	aload_0
   1:	getfield	#383; //Field depth:I
   4:	ireturn
  LineNumberTable: 
   line 36: 0


}

