Compiled from "Vector.scala"
public abstract class scala.collection.immutable.VectorPointer$class extends java.lang.Object
  SourceFile: "Vector.scala"
  Scala: length = 0x
   
  minor version: 0
  major version: 49
  Constant pool:
const #1 = Asciz	SourceFile;
const #2 = Asciz	Vector.scala;
const #3 = Asciz	$init$;
const #4 = Asciz	(Lscala/collection/immutable/VectorPointer;)V;
const #5 = Asciz	Code;
const #6 = Asciz	LineNumberTable;
const #7 = Asciz	$this;
const #8 = Asciz	Lscala/collection/immutable/VectorPointer;;
const #9 = Asciz	LocalVariableTable;
const #10 = Asciz	debug;
const #11 = Asciz	gotoFreshPosWritable1;
const #12 = Asciz	(Lscala/collection/immutable/VectorPointer;III)V;
const #13 = Asciz	scala/collection/immutable/VectorPointer;
const #14 = class	#13;	//  scala/collection/immutable/VectorPointer
const #15 = Asciz	stabilize;
const #16 = Asciz	(I)V;
const #17 = NameAndType	#15:#16;//  stabilize:(I)V
const #18 = InterfaceMethod	#14.#17;	//  scala/collection/immutable/VectorPointer.stabilize:(I)V
const #19 = Asciz	gotoFreshPosWritable0;
const #20 = Asciz	(III)V;
const #21 = NameAndType	#19:#20;//  gotoFreshPosWritable0:(III)V
const #22 = InterfaceMethod	#14.#21;	//  scala/collection/immutable/VectorPointer.gotoFreshPosWritable0:(III)V
const #23 = Asciz	oldIndex;
const #24 = Asciz	I;
const #25 = Asciz	newIndex;
const #26 = Asciz	xor;
const #27 = int	32;
const #28 = int	1024;
const #29 = Asciz	depth;
const #30 = Asciz	()I;
const #31 = NameAndType	#29:#30;//  depth:()I
const #32 = InterfaceMethod	#14.#31;	//  scala/collection/immutable/VectorPointer.depth:()I
const #33 = Asciz	java/lang/Object;
const #34 = class	#33;	//  java/lang/Object
const #35 = Asciz	display1_$eq;
const #36 = Asciz	([Ljava/lang/Object;)V;
const #37 = NameAndType	#35:#36;//  display1_$eq:([Ljava/lang/Object;)V
const #38 = InterfaceMethod	#14.#37;	//  scala/collection/immutable/VectorPointer.display1_$eq:([Ljava/lang/Object;)V
const #39 = Asciz	display1;
const #40 = Asciz	()[Ljava/lang/Object;;
const #41 = NameAndType	#39:#40;//  display1:()[Ljava/lang/Object;
const #42 = InterfaceMethod	#14.#41;	//  scala/collection/immutable/VectorPointer.display1:()[Ljava/lang/Object;
const #43 = int	31;
const #44 = Asciz	display0;
const #45 = NameAndType	#44:#40;//  display0:()[Ljava/lang/Object;
const #46 = InterfaceMethod	#14.#45;	//  scala/collection/immutable/VectorPointer.display0:()[Ljava/lang/Object;
const #47 = Asciz	depth_$eq;
const #48 = NameAndType	#47:#16;//  depth_$eq:(I)V
const #49 = InterfaceMethod	#14.#48;	//  scala/collection/immutable/VectorPointer.depth_$eq:(I)V
const #50 = Asciz	display0_$eq;
const #51 = NameAndType	#50:#36;//  display0_$eq:([Ljava/lang/Object;)V
const #52 = InterfaceMethod	#14.#51;	//  scala/collection/immutable/VectorPointer.display0_$eq:([Ljava/lang/Object;)V
const #53 = int	32768;
const #54 = Asciz	display2_$eq;
const #55 = NameAndType	#54:#36;//  display2_$eq:([Ljava/lang/Object;)V
const #56 = InterfaceMethod	#14.#55;	//  scala/collection/immutable/VectorPointer.display2_$eq:([Ljava/lang/Object;)V
const #57 = Asciz	display2;
const #58 = NameAndType	#57:#40;//  display2:()[Ljava/lang/Object;
const #59 = InterfaceMethod	#14.#58;	//  scala/collection/immutable/VectorPointer.display2:()[Ljava/lang/Object;
const #60 = int	10;
const #61 = Asciz	[Ljava/lang/Object;;
const #62 = class	#61;	//  "[Ljava/lang/Object;"
const #63 = int	1048576;
const #64 = Asciz	display3_$eq;
const #65 = NameAndType	#64:#36;//  display3_$eq:([Ljava/lang/Object;)V
const #66 = InterfaceMethod	#14.#65;	//  scala/collection/immutable/VectorPointer.display3_$eq:([Ljava/lang/Object;)V
const #67 = Asciz	display3;
const #68 = NameAndType	#67:#40;//  display3:()[Ljava/lang/Object;
const #69 = InterfaceMethod	#14.#68;	//  scala/collection/immutable/VectorPointer.display3:()[Ljava/lang/Object;
const #70 = int	15;
const #71 = int	33554432;
const #72 = Asciz	display4_$eq;
const #73 = NameAndType	#72:#36;//  display4_$eq:([Ljava/lang/Object;)V
const #74 = InterfaceMethod	#14.#73;	//  scala/collection/immutable/VectorPointer.display4_$eq:([Ljava/lang/Object;)V
const #75 = Asciz	display4;
const #76 = NameAndType	#75:#40;//  display4:()[Ljava/lang/Object;
const #77 = InterfaceMethod	#14.#76;	//  scala/collection/immutable/VectorPointer.display4:()[Ljava/lang/Object;
const #78 = int	20;
const #79 = int	1073741824;
const #80 = Asciz	display5_$eq;
const #81 = NameAndType	#80:#36;//  display5_$eq:([Ljava/lang/Object;)V
const #82 = InterfaceMethod	#14.#81;	//  scala/collection/immutable/VectorPointer.display5_$eq:([Ljava/lang/Object;)V
const #83 = Asciz	display5;
const #84 = NameAndType	#83:#40;//  display5:()[Ljava/lang/Object;
const #85 = InterfaceMethod	#14.#84;	//  scala/collection/immutable/VectorPointer.display5:()[Ljava/lang/Object;
const #86 = int	25;
const #87 = Asciz	java/lang/IllegalArgumentException;
const #88 = class	#87;	//  java/lang/IllegalArgumentException
const #89 = Asciz	<init>;
const #90 = Asciz	()V;
const #91 = NameAndType	#89:#90;//  "<init>":()V
const #92 = Method	#88.#91;	//  java/lang/IllegalArgumentException."<init>":()V
const #93 = Asciz	copyRange;
const #94 = Asciz	(Lscala/collection/immutable/VectorPointer;[Ljava/lang/Object;II)[Ljava/lang/Object;;
const #95 = Asciz	java/lang/Math;
const #96 = class	#95;	//  java/lang/Math
const #97 = Asciz	max;
const #98 = Asciz	(II)I;
const #99 = NameAndType	#97:#98;//  max:(II)I
const #100 = Method	#96.#99;	//  java/lang/Math.max:(II)I
const #101 = Asciz	java/lang/System;
const #102 = class	#101;	//  java/lang/System
const #103 = Asciz	arraycopy;
const #104 = Asciz	(Ljava/lang/Object;ILjava/lang/Object;II)V;
const #105 = NameAndType	#103:#104;//  arraycopy:(Ljava/lang/Object;ILjava/lang/Object;II)V
const #106 = Method	#102.#105;	//  java/lang/System.arraycopy:(Ljava/lang/Object;ILjava/lang/Object;II)V
const #107 = Asciz	array;
const #108 = Asciz	oldLeft;
const #109 = Asciz	newLeft;
const #110 = Asciz	elems;
const #111 = Asciz	gotoPosWritable1;
const #112 = Asciz	copyOf;
const #113 = Asciz	([Ljava/lang/Object;)[Ljava/lang/Object;;
const #114 = NameAndType	#112:#113;//  copyOf:([Ljava/lang/Object;)[Ljava/lang/Object;
const #115 = InterfaceMethod	#14.#114;	//  scala/collection/immutable/VectorPointer.copyOf:([Ljava/lang/Object;)[Ljava/lang/Object;
const #116 = Asciz	nullSlotAndCopy;
const #117 = Asciz	([Ljava/lang/Object;I)[Ljava/lang/Object;;
const #118 = NameAndType	#116:#117;//  nullSlotAndCopy:([Ljava/lang/Object;I)[Ljava/lang/Object;
const #119 = InterfaceMethod	#14.#118;	//  scala/collection/immutable/VectorPointer.nullSlotAndCopy:([Ljava/lang/Object;I)[Ljava/lang/Object;
const #120 = Asciz	gotoPosWritable0;
const #121 = Asciz	(Lscala/collection/immutable/VectorPointer;II)V;
const #122 = Asciz	scala/MatchError;
const #123 = class	#122;	//  scala/MatchError
const #124 = Asciz	scala/runtime/BoxesRunTime;
const #125 = class	#124;	//  scala/runtime/BoxesRunTime
const #126 = Asciz	boxToInteger;
const #127 = Asciz	(I)Ljava/lang/Integer;;
const #128 = NameAndType	#126:#127;//  boxToInteger:(I)Ljava/lang/Integer;
const #129 = Method	#125.#128;	//  scala/runtime/BoxesRunTime.boxToInteger:(I)Ljava/lang/Integer;
const #130 = Asciz	toString;
const #131 = Asciz	()Ljava/lang/String;;
const #132 = NameAndType	#130:#131;//  toString:()Ljava/lang/String;
const #133 = Method	#34.#132;	//  java/lang/Object.toString:()Ljava/lang/String;
const #134 = Asciz	(Ljava/lang/String;)V;
const #135 = NameAndType	#89:#134;//  "<init>":(Ljava/lang/String;)V
const #136 = Method	#123.#135;	//  scala/MatchError."<init>":(Ljava/lang/String;)V
const #137 = Asciz	temp5;
const #138 = Asciz	(Lscala/collection/immutable/VectorPointer;I)V;
const #139 = Asciz	index;
const #140 = Asciz	temp4;
const #141 = Asciz	(Lscala/collection/immutable/VectorPointer;[Ljava/lang/Object;I)[Ljava/lang/Object;;
const #142 = Asciz	x;
const #143 = Asciz	Ljava/lang/Object;;
const #144 = Asciz	(Lscala/collection/immutable/VectorPointer;[Ljava/lang/Object;)[Ljava/lang/Object;;
const #145 = Asciz	a;
const #146 = Asciz	b;
const #147 = Asciz	gotoNextBlockStartWritable;
const #148 = Asciz	gotoNextBlockStart;
const #149 = Asciz	gotoPos;
const #150 = Asciz	getElem;
const #151 = Asciz	(Lscala/collection/immutable/VectorPointer;II)Ljava/lang/Object;;
const #152 = Asciz	initFrom;
const #153 = Asciz	(Lscala/collection/immutable/VectorPointer;Lscala/collection/immutable/VectorPointer;I)V;
const #154 = Asciz	that;
const #155 = Asciz	temp3;
const #156 = Asciz	(Lscala/collection/immutable/VectorPointer;Lscala/collection/immutable/VectorPointer;)V;
const #157 = NameAndType	#152:#138;//  initFrom:(Lscala/collection/immutable/VectorPointer;I)V
const #158 = InterfaceMethod	#14.#157;	//  scala/collection/immutable/VectorPointer.initFrom:(Lscala/collection/immutable/VectorPointer;I)V
const #159 = Asciz	Scala;
const #160 = Asciz	scala/collection/immutable/VectorPointer$class;
const #161 = class	#160;	//  scala/collection/immutable/VectorPointer$class

{
public static void $init$(scala.collection.immutable.VectorPointer);
  Code:
   Stack=0, Locals=1, Args_size=1
   0:	return
  LineNumberTable: 
   line 645: 0

  LocalVariableTable: 
   Start  Length  Slot  Name   Signature
   0      1      0    $this       Lscala/collection/immutable/VectorPointer;


public static void debug(scala.collection.immutable.VectorPointer);
  Code:
   Stack=0, Locals=1, Args_size=1
   0:	return
  LineNumberTable: 
   line 1117: 0

  LocalVariableTable: 
   Start  Length  Slot  Name   Signature
   0      1      0    $this       Lscala/collection/immutable/VectorPointer;


public static final void gotoFreshPosWritable1(scala.collection.immutable.VectorPointer, int, int, int);
  Code:
   Stack=4, Locals=4, Args_size=4
   0:	aload_0
   1:	iload_1
   2:	invokeinterface	#18,  2; //InterfaceMethod scala/collection/immutable/VectorPointer.stabilize:(I)V
   7:	aload_0
   8:	iload_1
   9:	iload_2
   10:	iload_3
   11:	invokeinterface	#22,  4; //InterfaceMethod scala/collection/immutable/VectorPointer.gotoFreshPosWritable0:(III)V
   16:	return
  LineNumberTable: 
   line 1107: 0
   line 1108: 7

  LocalVariableTable: 
   Start  Length  Slot  Name   Signature
   0      17      0    $this       Lscala/collection/immutable/VectorPointer;
   0      17      1    oldIndex       I
   0      17      2    newIndex       I
   0      17      3    xor       I


public static final void gotoFreshPosWritable0(scala.collection.immutable.VectorPointer, int, int, int);
  Code:
   Stack=4, Locals=4, Args_size=4
   0:	iload_3
   1:	ldc	#27; //int 32
   3:	if_icmplt	916
   6:	iload_3
   7:	ldc	#28; //int 1024
   9:	if_icmpge	80
   12:	aload_0
   13:	invokeinterface	#32,  1; //InterfaceMethod scala/collection/immutable/VectorPointer.depth:()I
   18:	iconst_1
   19:	if_icmpne	66
   22:	aload_0
   23:	ldc	#27; //int 32
   25:	anewarray	#34; //class java/lang/Object
   28:	invokeinterface	#38,  2; //InterfaceMethod scala/collection/immutable/VectorPointer.display1_$eq:([Ljava/lang/Object;)V
   33:	aload_0
   34:	invokeinterface	#42,  1; //InterfaceMethod scala/collection/immutable/VectorPointer.display1:()[Ljava/lang/Object;
   39:	iload_1
   40:	iconst_5
   41:	ishr
   42:	ldc	#43; //int 31
   44:	iand
   45:	aload_0
   46:	invokeinterface	#46,  1; //InterfaceMethod scala/collection/immutable/VectorPointer.display0:()[Ljava/lang/Object;
   51:	aastore
   52:	aload_0
   53:	aload_0
   54:	invokeinterface	#32,  1; //InterfaceMethod scala/collection/immutable/VectorPointer.depth:()I
   59:	iconst_1
   60:	iadd
   61:	invokeinterface	#49,  2; //InterfaceMethod scala/collection/immutable/VectorPointer.depth_$eq:(I)V
   66:	aload_0
   67:	ldc	#27; //int 32
   69:	anewarray	#34; //class java/lang/Object
   72:	invokeinterface	#52,  2; //InterfaceMethod scala/collection/immutable/VectorPointer.display0_$eq:([Ljava/lang/Object;)V
   77:	goto	916
   80:	iload_3
   81:	ldc	#53; //int 32768
   83:	if_icmpge	199
   86:	aload_0
   87:	invokeinterface	#32,  1; //InterfaceMethod scala/collection/immutable/VectorPointer.depth:()I
   92:	iconst_2
   93:	if_icmpne	141
   96:	aload_0
   97:	ldc	#27; //int 32
   99:	anewarray	#34; //class java/lang/Object
   102:	invokeinterface	#56,  2; //InterfaceMethod scala/collection/immutable/VectorPointer.display2_$eq:([Ljava/lang/Object;)V
   107:	aload_0
   108:	invokeinterface	#59,  1; //InterfaceMethod scala/collection/immutable/VectorPointer.display2:()[Ljava/lang/Object;
   113:	iload_1
   114:	ldc	#60; //int 10
   116:	ishr
   117:	ldc	#43; //int 31
   119:	iand
   120:	aload_0
   121:	invokeinterface	#42,  1; //InterfaceMethod scala/collection/immutable/VectorPointer.display1:()[Ljava/lang/Object;
   126:	aastore
   127:	aload_0
   128:	aload_0
   129:	invokeinterface	#32,  1; //InterfaceMethod scala/collection/immutable/VectorPointer.depth:()I
   134:	iconst_1
   135:	iadd
   136:	invokeinterface	#49,  2; //InterfaceMethod scala/collection/immutable/VectorPointer.depth_$eq:(I)V
   141:	aload_0
   142:	aload_0
   143:	invokeinterface	#59,  1; //InterfaceMethod scala/collection/immutable/VectorPointer.display2:()[Ljava/lang/Object;
   148:	iload_2
   149:	ldc	#60; //int 10
   151:	ishr
   152:	ldc	#43; //int 31
   154:	iand
   155:	aaload
   156:	checkcast	#62; //class "[Ljava/lang/Object;"
   159:	invokeinterface	#38,  2; //InterfaceMethod scala/collection/immutable/VectorPointer.display1_$eq:([Ljava/lang/Object;)V
   164:	aload_0
   165:	invokeinterface	#42,  1; //InterfaceMethod scala/collection/immutable/VectorPointer.display1:()[Ljava/lang/Object;
   170:	aconst_null
   171:	if_acmpne	185
   174:	aload_0
   175:	ldc	#27; //int 32
   177:	anewarray	#34; //class java/lang/Object
   180:	invokeinterface	#38,  2; //InterfaceMethod scala/collection/immutable/VectorPointer.display1_$eq:([Ljava/lang/Object;)V
   185:	aload_0
   186:	ldc	#27; //int 32
   188:	anewarray	#34; //class java/lang/Object
   191:	invokeinterface	#52,  2; //InterfaceMethod scala/collection/immutable/VectorPointer.display0_$eq:([Ljava/lang/Object;)V
   196:	goto	916
   199:	iload_3
   200:	ldc	#63; //int 1048576
   202:	if_icmpge	384
   205:	aload_0
   206:	invokeinterface	#32,  1; //InterfaceMethod scala/collection/immutable/VectorPointer.depth:()I
   211:	iconst_3
   212:	if_icmpne	282
   215:	aload_0
   216:	ldc	#27; //int 32
   218:	anewarray	#34; //class java/lang/Object
   221:	invokeinterface	#66,  2; //InterfaceMethod scala/collection/immutable/VectorPointer.display3_$eq:([Ljava/lang/Object;)V
   226:	aload_0
   227:	invokeinterface	#69,  1; //InterfaceMethod scala/collection/immutable/VectorPointer.display3:()[Ljava/lang/Object;
   232:	iload_1
   233:	ldc	#70; //int 15
   235:	ishr
   236:	ldc	#43; //int 31
   238:	iand
   239:	aload_0
   240:	invokeinterface	#59,  1; //InterfaceMethod scala/collection/immutable/VectorPointer.display2:()[Ljava/lang/Object;
   245:	aastore
   246:	aload_0
   247:	ldc	#27; //int 32
   249:	anewarray	#34; //class java/lang/Object
   252:	invokeinterface	#56,  2; //InterfaceMethod scala/collection/immutable/VectorPointer.display2_$eq:([Ljava/lang/Object;)V
   257:	aload_0
   258:	ldc	#27; //int 32
   260:	anewarray	#34; //class java/lang/Object
   263:	invokeinterface	#38,  2; //InterfaceMethod scala/collection/immutable/VectorPointer.display1_$eq:([Ljava/lang/Object;)V
   268:	aload_0
   269:	aload_0
   270:	invokeinterface	#32,  1; //InterfaceMethod scala/collection/immutable/VectorPointer.depth:()I
   275:	iconst_1
   276:	iadd
   277:	invokeinterface	#49,  2; //InterfaceMethod scala/collection/immutable/VectorPointer.depth_$eq:(I)V
   282:	aload_0
   283:	aload_0
   284:	invokeinterface	#69,  1; //InterfaceMethod scala/collection/immutable/VectorPointer.display3:()[Ljava/lang/Object;
   289:	iload_2
   290:	ldc	#70; //int 15
   292:	ishr
   293:	ldc	#43; //int 31
   295:	iand
   296:	aaload
   297:	checkcast	#62; //class "[Ljava/lang/Object;"
   300:	invokeinterface	#56,  2; //InterfaceMethod scala/collection/immutable/VectorPointer.display2_$eq:([Ljava/lang/Object;)V
   305:	aload_0
   306:	invokeinterface	#59,  1; //InterfaceMethod scala/collection/immutable/VectorPointer.display2:()[Ljava/lang/Object;
   311:	aconst_null
   312:	if_acmpne	326
   315:	aload_0
   316:	ldc	#27; //int 32
   318:	anewarray	#34; //class java/lang/Object
   321:	invokeinterface	#56,  2; //InterfaceMethod scala/collection/immutable/VectorPointer.display2_$eq:([Ljava/lang/Object;)V
   326:	aload_0
   327:	aload_0
   328:	invokeinterface	#59,  1; //InterfaceMethod scala/collection/immutable/VectorPointer.display2:()[Ljava/lang/Object;
   333:	iload_2
   334:	ldc	#60; //int 10
   336:	ishr
   337:	ldc	#43; //int 31
   339:	iand
   340:	aaload
   341:	checkcast	#62; //class "[Ljava/lang/Object;"
   344:	invokeinterface	#38,  2; //InterfaceMethod scala/collection/immutable/VectorPointer.display1_$eq:([Ljava/lang/Object;)V
   349:	aload_0
   350:	invokeinterface	#42,  1; //InterfaceMethod scala/collection/immutable/VectorPointer.display1:()[Ljava/lang/Object;
   355:	aconst_null
   356:	if_acmpne	370
   359:	aload_0
   360:	ldc	#27; //int 32
   362:	anewarray	#34; //class java/lang/Object
   365:	invokeinterface	#38,  2; //InterfaceMethod scala/collection/immutable/VectorPointer.display1_$eq:([Ljava/lang/Object;)V
   370:	aload_0
   371:	ldc	#27; //int 32
   373:	anewarray	#34; //class java/lang/Object
   376:	invokeinterface	#52,  2; //InterfaceMethod scala/collection/immutable/VectorPointer.display0_$eq:([Ljava/lang/Object;)V
   381:	goto	916
   384:	iload_3
   385:	ldc	#71; //int 33554432
   387:	if_icmpge	624
   390:	aload_0
   391:	invokeinterface	#32,  1; //InterfaceMethod scala/collection/immutable/VectorPointer.depth:()I
   396:	iconst_4
   397:	if_icmpne	478
   400:	aload_0
   401:	ldc	#27; //int 32
   403:	anewarray	#34; //class java/lang/Object
   406:	invokeinterface	#74,  2; //InterfaceMethod scala/collection/immutable/VectorPointer.display4_$eq:([Ljava/lang/Object;)V
   411:	aload_0
   412:	invokeinterface	#77,  1; //InterfaceMethod scala/collection/immutable/VectorPointer.display4:()[Ljava/lang/Object;
   417:	iload_1
   418:	ldc	#78; //int 20
   420:	ishr
   421:	ldc	#43; //int 31
   423:	iand
   424:	aload_0
   425:	invokeinterface	#69,  1; //InterfaceMethod scala/collection/immutable/VectorPointer.display3:()[Ljava/lang/Object;
   430:	aastore
   431:	aload_0
   432:	ldc	#27; //int 32
   434:	anewarray	#34; //class java/lang/Object
   437:	invokeinterface	#66,  2; //InterfaceMethod scala/collection/immutable/VectorPointer.display3_$eq:([Ljava/lang/Object;)V
   442:	aload_0
   443:	ldc	#27; //int 32
   445:	anewarray	#34; //class java/lang/Object
   448:	invokeinterface	#56,  2; //InterfaceMethod scala/collection/immutable/VectorPointer.display2_$eq:([Ljava/lang/Object;)V
   453:	aload_0
   454:	ldc	#27; //int 32
   456:	anewarray	#34; //class java/lang/Object
   459:	invokeinterface	#38,  2; //InterfaceMethod scala/collection/immutable/VectorPointer.display1_$eq:([Ljava/lang/Object;)V
   464:	aload_0
   465:	aload_0
   466:	invokeinterface	#32,  1; //InterfaceMethod scala/collection/immutable/VectorPointer.depth:()I
   471:	iconst_1
   472:	iadd
   473:	invokeinterface	#49,  2; //InterfaceMethod scala/collection/immutable/VectorPointer.depth_$eq:(I)V
   478:	aload_0
   479:	aload_0
   480:	invokeinterface	#77,  1; //InterfaceMethod scala/collection/immutable/VectorPointer.display4:()[Ljava/lang/Object;
   485:	iload_2
   486:	ldc	#78; //int 20
   488:	ishr
   489:	ldc	#43; //int 31
   491:	iand
   492:	aaload
   493:	checkcast	#62; //class "[Ljava/lang/Object;"
   496:	invokeinterface	#66,  2; //InterfaceMethod scala/collection/immutable/VectorPointer.display3_$eq:([Ljava/lang/Object;)V
   501:	aload_0
   502:	invokeinterface	#69,  1; //InterfaceMethod scala/collection/immutable/VectorPointer.display3:()[Ljava/lang/Object;
   507:	aconst_null
   508:	if_acmpne	522
   511:	aload_0
   512:	ldc	#27; //int 32
   514:	anewarray	#34; //class java/lang/Object
   517:	invokeinterface	#66,  2; //InterfaceMethod scala/collection/immutable/VectorPointer.display3_$eq:([Ljava/lang/Object;)V
   522:	aload_0
   523:	aload_0
   524:	invokeinterface	#69,  1; //InterfaceMethod scala/collection/immutable/VectorPointer.display3:()[Ljava/lang/Object;
   529:	iload_2
   530:	ldc	#70; //int 15
   532:	ishr
   533:	ldc	#43; //int 31
   535:	iand
   536:	aaload
   537:	checkcast	#62; //class "[Ljava/lang/Object;"
   540:	invokeinterface	#56,  2; //InterfaceMethod scala/collection/immutable/VectorPointer.display2_$eq:([Ljava/lang/Object;)V
   545:	aload_0
   546:	invokeinterface	#59,  1; //InterfaceMethod scala/collection/immutable/VectorPointer.display2:()[Ljava/lang/Object;
   551:	aconst_null
   552:	if_acmpne	566
   555:	aload_0
   556:	ldc	#27; //int 32
   558:	anewarray	#34; //class java/lang/Object
   561:	invokeinterface	#56,  2; //InterfaceMethod scala/collection/immutable/VectorPointer.display2_$eq:([Ljava/lang/Object;)V
   566:	aload_0
   567:	aload_0
   568:	invokeinterface	#59,  1; //InterfaceMethod scala/collection/immutable/VectorPointer.display2:()[Ljava/lang/Object;
   573:	iload_2
   574:	ldc	#60; //int 10
   576:	ishr
   577:	ldc	#43; //int 31
   579:	iand
   580:	aaload
   581:	checkcast	#62; //class "[Ljava/lang/Object;"
   584:	invokeinterface	#38,  2; //InterfaceMethod scala/collection/immutable/VectorPointer.display1_$eq:([Ljava/lang/Object;)V
   589:	aload_0
   590:	invokeinterface	#42,  1; //InterfaceMethod scala/collection/immutable/VectorPointer.display1:()[Ljava/lang/Object;
   595:	aconst_null
   596:	if_acmpne	610
   599:	aload_0
   600:	ldc	#27; //int 32
   602:	anewarray	#34; //class java/lang/Object
   605:	invokeinterface	#38,  2; //InterfaceMethod scala/collection/immutable/VectorPointer.display1_$eq:([Ljava/lang/Object;)V
   610:	aload_0
   611:	ldc	#27; //int 32
   613:	anewarray	#34; //class java/lang/Object
   616:	invokeinterface	#52,  2; //InterfaceMethod scala/collection/immutable/VectorPointer.display0_$eq:([Ljava/lang/Object;)V
   621:	goto	916
   624:	iload_3
   625:	ldc	#79; //int 1073741824
   627:	if_icmpge	917
   630:	aload_0
   631:	invokeinterface	#32,  1; //InterfaceMethod scala/collection/immutable/VectorPointer.depth:()I
   636:	iconst_5
   637:	if_icmpne	729
   640:	aload_0
   641:	ldc	#27; //int 32
   643:	anewarray	#34; //class java/lang/Object
   646:	invokeinterface	#82,  2; //InterfaceMethod scala/collection/immutable/VectorPointer.display5_$eq:([Ljava/lang/Object;)V
   651:	aload_0
   652:	invokeinterface	#85,  1; //InterfaceMethod scala/collection/immutable/VectorPointer.display5:()[Ljava/lang/Object;
   657:	iload_1
   658:	ldc	#86; //int 25
   660:	ishr
   661:	ldc	#43; //int 31
   663:	iand
   664:	aload_0
   665:	invokeinterface	#77,  1; //InterfaceMethod scala/collection/immutable/VectorPointer.display4:()[Ljava/lang/Object;
   670:	aastore
   671:	aload_0
   672:	ldc	#27; //int 32
   674:	anewarray	#34; //class java/lang/Object
   677:	invokeinterface	#74,  2; //InterfaceMethod scala/collection/immutable/VectorPointer.display4_$eq:([Ljava/lang/Object;)V
   682:	aload_0
   683:	ldc	#27; //int 32
   685:	anewarray	#34; //class java/lang/Object
   688:	invokeinterface	#66,  2; //InterfaceMethod scala/collection/immutable/VectorPointer.display3_$eq:([Ljava/lang/Object;)V
   693:	aload_0
   694:	ldc	#27; //int 32
   696:	anewarray	#34; //class java/lang/Object
   699:	invokeinterface	#56,  2; //InterfaceMethod scala/collection/immutable/VectorPointer.display2_$eq:([Ljava/lang/Object;)V
   704:	aload_0
   705:	ldc	#27; //int 32
   707:	anewarray	#34; //class java/lang/Object
   710:	invokeinterface	#38,  2; //InterfaceMethod scala/collection/immutable/VectorPointer.display1_$eq:([Ljava/lang/Object;)V
   715:	aload_0
   716:	aload_0
   717:	invokeinterface	#32,  1; //InterfaceMethod scala/collection/immutable/VectorPointer.depth:()I
   722:	iconst_1
   723:	iadd
   724:	invokeinterface	#49,  2; //InterfaceMethod scala/collection/immutable/VectorPointer.depth_$eq:(I)V
   729:	aload_0
   730:	aload_0
   731:	invokeinterface	#85,  1; //InterfaceMethod scala/collection/immutable/VectorPointer.display5:()[Ljava/lang/Object;
   736:	iload_2
   737:	ldc	#78; //int 20
   739:	ishr
   740:	ldc	#43; //int 31
   742:	iand
   743:	aaload
   744:	checkcast	#62; //class "[Ljava/lang/Object;"
   747:	invokeinterface	#74,  2; //InterfaceMethod scala/collection/immutable/VectorPointer.display4_$eq:([Ljava/lang/Object;)V
   752:	aload_0
   753:	invokeinterface	#77,  1; //InterfaceMethod scala/collection/immutable/VectorPointer.display4:()[Ljava/lang/Object;
   758:	aconst_null
   759:	if_acmpne	773
   762:	aload_0
   763:	ldc	#27; //int 32
   765:	anewarray	#34; //class java/lang/Object
   768:	invokeinterface	#74,  2; //InterfaceMethod scala/collection/immutable/VectorPointer.display4_$eq:([Ljava/lang/Object;)V
   773:	aload_0
   774:	aload_0
   775:	invokeinterface	#77,  1; //InterfaceMethod scala/collection/immutable/VectorPointer.display4:()[Ljava/lang/Object;
   780:	iload_2
   781:	ldc	#78; //int 20
   783:	ishr
   784:	ldc	#43; //int 31
   786:	iand
   787:	aaload
   788:	checkcast	#62; //class "[Ljava/lang/Object;"
   791:	invokeinterface	#66,  2; //InterfaceMethod scala/collection/immutable/VectorPointer.display3_$eq:([Ljava/lang/Object;)V
   796:	aload_0
   797:	invokeinterface	#69,  1; //InterfaceMethod scala/collection/immutable/VectorPointer.display3:()[Ljava/lang/Object;
   802:	aconst_null
   803:	if_acmpne	817
   806:	aload_0
   807:	ldc	#27; //int 32
   809:	anewarray	#34; //class java/lang/Object
   812:	invokeinterface	#66,  2; //InterfaceMethod scala/collection/immutable/VectorPointer.display3_$eq:([Ljava/lang/Object;)V
   817:	aload_0
   818:	aload_0
   819:	invokeinterface	#69,  1; //InterfaceMethod scala/collection/immutable/VectorPointer.display3:()[Ljava/lang/Object;
   824:	iload_2
   825:	ldc	#70; //int 15
   827:	ishr
   828:	ldc	#43; //int 31
   830:	iand
   831:	aaload
   832:	checkcast	#62; //class "[Ljava/lang/Object;"
   835:	invokeinterface	#56,  2; //InterfaceMethod scala/collection/immutable/VectorPointer.display2_$eq:([Ljava/lang/Object;)V
   840:	aload_0
   841:	invokeinterface	#59,  1; //InterfaceMethod scala/collection/immutable/VectorPointer.display2:()[Ljava/lang/Object;
   846:	aconst_null
   847:	if_acmpne	861
   850:	aload_0
   851:	ldc	#27; //int 32
   853:	anewarray	#34; //class java/lang/Object
   856:	invokeinterface	#56,  2; //InterfaceMethod scala/collection/immutable/VectorPointer.display2_$eq:([Ljava/lang/Object;)V
   861:	aload_0
   862:	aload_0
   863:	invokeinterface	#59,  1; //InterfaceMethod scala/collection/immutable/VectorPointer.display2:()[Ljava/lang/Object;
   868:	iload_2
   869:	ldc	#60; //int 10
   871:	ishr
   872:	ldc	#43; //int 31
   874:	iand
   875:	aaload
   876:	checkcast	#62; //class "[Ljava/lang/Object;"
   879:	invokeinterface	#38,  2; //InterfaceMethod scala/collection/immutable/VectorPointer.display1_$eq:([Ljava/lang/Object;)V
   884:	aload_0
   885:	invokeinterface	#42,  1; //InterfaceMethod scala/collection/immutable/VectorPointer.display1:()[Ljava/lang/Object;
   890:	aconst_null
   891:	if_acmpne	905
   894:	aload_0
   895:	ldc	#27; //int 32
   897:	anewarray	#34; //class java/lang/Object
   900:	invokeinterface	#38,  2; //InterfaceMethod scala/collection/immutable/VectorPointer.display1_$eq:([Ljava/lang/Object;)V
   905:	aload_0
   906:	ldc	#27; //int 32
   908:	anewarray	#34; //class java/lang/Object
   911:	invokeinterface	#52,  2; //InterfaceMethod scala/collection/immutable/VectorPointer.display0_$eq:([Ljava/lang/Object;)V
   916:	return
   917:	new	#88; //class java/lang/IllegalArgumentException
   920:	dup
   921:	invokespecial	#92; //Method java/lang/IllegalArgumentException."<init>":()V
   924:	athrow
  LineNumberTable: 
   line 1027: 0
   line 1030: 6
   line 1031: 12
   line 1032: 22
   line 1033: 33
   line 1034: 52
   line 1036: 66
   line 1038: 80
   line 1039: 86
   line 1040: 96
   line 1041: 107
   line 1042: 127
   line 1044: 141
   line 1045: 164
   line 1046: 185
   line 1048: 199
   line 1049: 205
   line 1050: 215
   line 1051: 226
   line 1052: 246
   line 1053: 257
   line 1054: 268
   line 1056: 282
   line 1057: 305
   line 1058: 326
   line 1059: 349
   line 1060: 370
   line 1062: 384
   line 1063: 390
   line 1064: 400
   line 1065: 411
   line 1066: 431
   line 1067: 442
   line 1068: 453
   line 1069: 464
   line 1071: 478
   line 1072: 501
   line 1073: 522
   line 1074: 545
   line 1075: 566
   line 1076: 589
   line 1077: 610
   line 1079: 624
   line 1080: 630
   line 1081: 640
   line 1082: 651
   line 1083: 671
   line 1084: 682
   line 1085: 693
   line 1086: 704
   line 1087: 715
   line 1089: 729
   line 1090: 752
   line 1091: 773
   line 1092: 796
   line 1093: 817
   line 1094: 840
   line 1095: 861
   line 1096: 884
   line 1097: 905
   line 1027: 916
   line 1099: 917

  LocalVariableTable: 
   Start  Length  Slot  Name   Signature
   0      925      0    $this       Lscala/collection/immutable/VectorPointer;
   0      925      1    oldIndex       I
   0      925      2    newIndex       I
   0      925      3    xor       I


public static final java.lang.Object[] copyRange(scala.collection.immutable.VectorPointer, java.lang.Object[], int, int);
  Code:
   Stack=5, Locals=6, Args_size=4
   0:	ldc	#27; //int 32
   2:	anewarray	#34; //class java/lang/Object
   5:	astore	5
   7:	ldc	#27; //int 32
   9:	iload_3
   10:	iload_2
   11:	invokestatic	#100; //Method java/lang/Math.max:(II)I
   14:	isub
   15:	istore	4
   17:	aload_1
   18:	iload_2
   19:	aload	5
   21:	iload_3
   22:	iload	4
   24:	invokestatic	#106; //Method java/lang/System.arraycopy:(Ljava/lang/Object;ILjava/lang/Object;II)V
   27:	aload	5
   29:	areturn
  LineNumberTable: 
   line 1013: 0
   line 1014: 7
   line 1015: 27

  LocalVariableTable: 
   Start  Length  Slot  Name   Signature
   0      30      0    $this       Lscala/collection/immutable/VectorPointer;
   0      30      1    array       [Ljava/lang/Object;
   0      30      2    oldLeft       I
   0      30      3    newLeft       I
   7      22      5    elems       [Ljava/lang/Object;


public static final void gotoPosWritable1(scala.collection.immutable.VectorPointer, int, int, int);
  Code:
   Stack=5, Locals=4, Args_size=4
   0:	iload_3
   1:	ldc	#27; //int 32
   3:	if_icmpge	27
   6:	aload_0
   7:	aload_0
   8:	aload_0
   9:	invokeinterface	#46,  1; //InterfaceMethod scala/collection/immutable/VectorPointer.display0:()[Ljava/lang/Object;
   14:	invokeinterface	#115,  2; //InterfaceMethod scala/collection/immutable/VectorPointer.copyOf:([Ljava/lang/Object;)[Ljava/lang/Object;
   19:	invokeinterface	#52,  2; //InterfaceMethod scala/collection/immutable/VectorPointer.display0_$eq:([Ljava/lang/Object;)V
   24:	goto	1004
   27:	iload_3
   28:	ldc	#28; //int 1024
   30:	if_icmpge	97
   33:	aload_0
   34:	aload_0
   35:	aload_0
   36:	invokeinterface	#42,  1; //InterfaceMethod scala/collection/immutable/VectorPointer.display1:()[Ljava/lang/Object;
   41:	invokeinterface	#115,  2; //InterfaceMethod scala/collection/immutable/VectorPointer.copyOf:([Ljava/lang/Object;)[Ljava/lang/Object;
   46:	invokeinterface	#38,  2; //InterfaceMethod scala/collection/immutable/VectorPointer.display1_$eq:([Ljava/lang/Object;)V
   51:	aload_0
   52:	invokeinterface	#42,  1; //InterfaceMethod scala/collection/immutable/VectorPointer.display1:()[Ljava/lang/Object;
   57:	iload_1
   58:	iconst_5
   59:	ishr
   60:	ldc	#43; //int 31
   62:	iand
   63:	aload_0
   64:	invokeinterface	#46,  1; //InterfaceMethod scala/collection/immutable/VectorPointer.display0:()[Ljava/lang/Object;
   69:	aastore
   70:	aload_0
   71:	aload_0
   72:	aload_0
   73:	invokeinterface	#42,  1; //InterfaceMethod scala/collection/immutable/VectorPointer.display1:()[Ljava/lang/Object;
   78:	iload_2
   79:	iconst_5
   80:	ishr
   81:	ldc	#43; //int 31
   83:	iand
   84:	invokeinterface	#119,  3; //InterfaceMethod scala/collection/immutable/VectorPointer.nullSlotAndCopy:([Ljava/lang/Object;I)[Ljava/lang/Object;
   89:	invokeinterface	#52,  2; //InterfaceMethod scala/collection/immutable/VectorPointer.display0_$eq:([Ljava/lang/Object;)V
   94:	goto	1004
   97:	iload_3
   98:	ldc	#53; //int 32768
   100:	if_icmpge	230
   103:	aload_0
   104:	aload_0
   105:	aload_0
   106:	invokeinterface	#42,  1; //InterfaceMethod scala/collection/immutable/VectorPointer.display1:()[Ljava/lang/Object;
   111:	invokeinterface	#115,  2; //InterfaceMethod scala/collection/immutable/VectorPointer.copyOf:([Ljava/lang/Object;)[Ljava/lang/Object;
   116:	invokeinterface	#38,  2; //InterfaceMethod scala/collection/immutable/VectorPointer.display1_$eq:([Ljava/lang/Object;)V
   121:	aload_0
   122:	aload_0
   123:	aload_0
   124:	invokeinterface	#59,  1; //InterfaceMethod scala/collection/immutable/VectorPointer.display2:()[Ljava/lang/Object;
   129:	invokeinterface	#115,  2; //InterfaceMethod scala/collection/immutable/VectorPointer.copyOf:([Ljava/lang/Object;)[Ljava/lang/Object;
   134:	invokeinterface	#56,  2; //InterfaceMethod scala/collection/immutable/VectorPointer.display2_$eq:([Ljava/lang/Object;)V
   139:	aload_0
   140:	invokeinterface	#42,  1; //InterfaceMethod scala/collection/immutable/VectorPointer.display1:()[Ljava/lang/Object;
   145:	iload_1
   146:	iconst_5
   147:	ishr
   148:	ldc	#43; //int 31
   150:	iand
   151:	aload_0
   152:	invokeinterface	#46,  1; //InterfaceMethod scala/collection/immutable/VectorPointer.display0:()[Ljava/lang/Object;
   157:	aastore
   158:	aload_0
   159:	invokeinterface	#59,  1; //InterfaceMethod scala/collection/immutable/VectorPointer.display2:()[Ljava/lang/Object;
   164:	iload_1
   165:	ldc	#60; //int 10
   167:	ishr
   168:	ldc	#43; //int 31
   170:	iand
   171:	aload_0
   172:	invokeinterface	#42,  1; //InterfaceMethod scala/collection/immutable/VectorPointer.display1:()[Ljava/lang/Object;
   177:	aastore
   178:	aload_0
   179:	aload_0
   180:	aload_0
   181:	invokeinterface	#59,  1; //InterfaceMethod scala/collection/immutable/VectorPointer.display2:()[Ljava/lang/Object;
   186:	iload_2
   187:	ldc	#60; //int 10
   189:	ishr
   190:	ldc	#43; //int 31
   192:	iand
   193:	invokeinterface	#119,  3; //InterfaceMethod scala/collection/immutable/VectorPointer.nullSlotAndCopy:([Ljava/lang/Object;I)[Ljava/lang/Object;
   198:	invokeinterface	#38,  2; //InterfaceMethod scala/collection/immutable/VectorPointer.display1_$eq:([Ljava/lang/Object;)V
   203:	aload_0
   204:	aload_0
   205:	aload_0
   206:	invokeinterface	#42,  1; //InterfaceMethod scala/collection/immutable/VectorPointer.display1:()[Ljava/lang/Object;
   211:	iload_2
   212:	iconst_5
   213:	ishr
   214:	ldc	#43; //int 31
   216:	iand
   217:	invokeinterface	#119,  3; //InterfaceMethod scala/collection/immutable/VectorPointer.nullSlotAndCopy:([Ljava/lang/Object;I)[Ljava/lang/Object;
   222:	invokeinterface	#52,  2; //InterfaceMethod scala/collection/immutable/VectorPointer.display0_$eq:([Ljava/lang/Object;)V
   227:	goto	1004
   230:	iload_3
   231:	ldc	#63; //int 1048576
   233:	if_icmpge	426
   236:	aload_0
   237:	aload_0
   238:	aload_0
   239:	invokeinterface	#42,  1; //InterfaceMethod scala/collection/immutable/VectorPointer.display1:()[Ljava/lang/Object;
   244:	invokeinterface	#115,  2; //InterfaceMethod scala/collection/immutable/VectorPointer.copyOf:([Ljava/lang/Object;)[Ljava/lang/Object;
   249:	invokeinterface	#38,  2; //InterfaceMethod scala/collection/immutable/VectorPointer.display1_$eq:([Ljava/lang/Object;)V
   254:	aload_0
   255:	aload_0
   256:	aload_0
   257:	invokeinterface	#59,  1; //InterfaceMethod scala/collection/immutable/VectorPointer.display2:()[Ljava/lang/Object;
   262:	invokeinterface	#115,  2; //InterfaceMethod scala/collection/immutable/VectorPointer.copyOf:([Ljava/lang/Object;)[Ljava/lang/Object;
   267:	invokeinterface	#56,  2; //InterfaceMethod scala/collection/immutable/VectorPointer.display2_$eq:([Ljava/lang/Object;)V
   272:	aload_0
   273:	aload_0
   274:	aload_0
   275:	invokeinterface	#69,  1; //InterfaceMethod scala/collection/immutable/VectorPointer.display3:()[Ljava/lang/Object;
   280:	invokeinterface	#115,  2; //InterfaceMethod scala/collection/immutable/VectorPointer.copyOf:([Ljava/lang/Object;)[Ljava/lang/Object;
   285:	invokeinterface	#66,  2; //InterfaceMethod scala/collection/immutable/VectorPointer.display3_$eq:([Ljava/lang/Object;)V
   290:	aload_0
   291:	invokeinterface	#42,  1; //InterfaceMethod scala/collection/immutable/VectorPointer.display1:()[Ljava/lang/Object;
   296:	iload_1
   297:	iconst_5
   298:	ishr
   299:	ldc	#43; //int 31
   301:	iand
   302:	aload_0
   303:	invokeinterface	#46,  1; //InterfaceMethod scala/collection/immutable/VectorPointer.display0:()[Ljava/lang/Object;
   308:	aastore
   309:	aload_0
   310:	invokeinterface	#59,  1; //InterfaceMethod scala/collection/immutable/VectorPointer.display2:()[Ljava/lang/Object;
   315:	iload_1
   316:	ldc	#60; //int 10
   318:	ishr
   319:	ldc	#43; //int 31
   321:	iand
   322:	aload_0
   323:	invokeinterface	#42,  1; //InterfaceMethod scala/collection/immutable/VectorPointer.display1:()[Ljava/lang/Object;
   328:	aastore
   329:	aload_0
   330:	invokeinterface	#69,  1; //InterfaceMethod scala/collection/immutable/VectorPointer.display3:()[Ljava/lang/Object;
   335:	iload_1
   336:	ldc	#70; //int 15
   338:	ishr
   339:	ldc	#43; //int 31
   341:	iand
   342:	aload_0
   343:	invokeinterface	#59,  1; //InterfaceMethod scala/collection/immutable/VectorPointer.display2:()[Ljava/lang/Object;
   348:	aastore
   349:	aload_0
   350:	aload_0
   351:	aload_0
   352:	invokeinterface	#69,  1; //InterfaceMethod scala/collection/immutable/VectorPointer.display3:()[Ljava/lang/Object;
   357:	iload_2
   358:	ldc	#70; //int 15
   360:	ishr
   361:	ldc	#43; //int 31
   363:	iand
   364:	invokeinterface	#119,  3; //InterfaceMethod scala/collection/immutable/VectorPointer.nullSlotAndCopy:([Ljava/lang/Object;I)[Ljava/lang/Object;
   369:	invokeinterface	#56,  2; //InterfaceMethod scala/collection/immutable/VectorPointer.display2_$eq:([Ljava/lang/Object;)V
   374:	aload_0
   375:	aload_0
   376:	aload_0
   377:	invokeinterface	#59,  1; //InterfaceMethod scala/collection/immutable/VectorPointer.display2:()[Ljava/lang/Object;
   382:	iload_2
   383:	ldc	#60; //int 10
   385:	ishr
   386:	ldc	#43; //int 31
   388:	iand
   389:	invokeinterface	#119,  3; //InterfaceMethod scala/collection/immutable/VectorPointer.nullSlotAndCopy:([Ljava/lang/Object;I)[Ljava/lang/Object;
   394:	invokeinterface	#38,  2; //InterfaceMethod scala/collection/immutable/VectorPointer.display1_$eq:([Ljava/lang/Object;)V
   399:	aload_0
   400:	aload_0
   401:	aload_0
   402:	invokeinterface	#42,  1; //InterfaceMethod scala/collection/immutable/VectorPointer.display1:()[Ljava/lang/Object;
   407:	iload_2
   408:	iconst_5
   409:	ishr
   410:	ldc	#43; //int 31
   412:	iand
   413:	invokeinterface	#119,  3; //InterfaceMethod scala/collection/immutable/VectorPointer.nullSlotAndCopy:([Ljava/lang/Object;I)[Ljava/lang/Object;
   418:	invokeinterface	#52,  2; //InterfaceMethod scala/collection/immutable/VectorPointer.display0_$eq:([Ljava/lang/Object;)V
   423:	goto	1004
   426:	iload_3
   427:	ldc	#71; //int 33554432
   429:	if_icmpge	685
   432:	aload_0
   433:	aload_0
   434:	aload_0
   435:	invokeinterface	#42,  1; //InterfaceMethod scala/collection/immutable/VectorPointer.display1:()[Ljava/lang/Object;
   440:	invokeinterface	#115,  2; //InterfaceMethod scala/collection/immutable/VectorPointer.copyOf:([Ljava/lang/Object;)[Ljava/lang/Object;
   445:	invokeinterface	#38,  2; //InterfaceMethod scala/collection/immutable/VectorPointer.display1_$eq:([Ljava/lang/Object;)V
   450:	aload_0
   451:	aload_0
   452:	aload_0
   453:	invokeinterface	#59,  1; //InterfaceMethod scala/collection/immutable/VectorPointer.display2:()[Ljava/lang/Object;
   458:	invokeinterface	#115,  2; //InterfaceMethod scala/collection/immutable/VectorPointer.copyOf:([Ljava/lang/Object;)[Ljava/lang/Object;
   463:	invokeinterface	#56,  2; //InterfaceMethod scala/collection/immutable/VectorPointer.display2_$eq:([Ljava/lang/Object;)V
   468:	aload_0
   469:	aload_0
   470:	aload_0
   471:	invokeinterface	#69,  1; //InterfaceMethod scala/collection/immutable/VectorPointer.display3:()[Ljava/lang/Object;
   476:	invokeinterface	#115,  2; //InterfaceMethod scala/collection/immutable/VectorPointer.copyOf:([Ljava/lang/Object;)[Ljava/lang/Object;
   481:	invokeinterface	#66,  2; //InterfaceMethod scala/collection/immutable/VectorPointer.display3_$eq:([Ljava/lang/Object;)V
   486:	aload_0
   487:	aload_0
   488:	aload_0
   489:	invokeinterface	#77,  1; //InterfaceMethod scala/collection/immutable/VectorPointer.display4:()[Ljava/lang/Object;
   494:	invokeinterface	#115,  2; //InterfaceMethod scala/collection/immutable/VectorPointer.copyOf:([Ljava/lang/Object;)[Ljava/lang/Object;
   499:	invokeinterface	#74,  2; //InterfaceMethod scala/collection/immutable/VectorPointer.display4_$eq:([Ljava/lang/Object;)V
   504:	aload_0
   505:	invokeinterface	#42,  1; //InterfaceMethod scala/collection/immutable/VectorPointer.display1:()[Ljava/lang/Object;
   510:	iload_1
   511:	iconst_5
   512:	ishr
   513:	ldc	#43; //int 31
   515:	iand
   516:	aload_0
   517:	invokeinterface	#46,  1; //InterfaceMethod scala/collection/immutable/VectorPointer.display0:()[Ljava/lang/Object;
   522:	aastore
   523:	aload_0
   524:	invokeinterface	#59,  1; //InterfaceMethod scala/collection/immutable/VectorPointer.display2:()[Ljava/lang/Object;
   529:	iload_1
   530:	ldc	#60; //int 10
   532:	ishr
   533:	ldc	#43; //int 31
   535:	iand
   536:	aload_0
   537:	invokeinterface	#42,  1; //InterfaceMethod scala/collection/immutable/VectorPointer.display1:()[Ljava/lang/Object;
   542:	aastore
   543:	aload_0
   544:	invokeinterface	#69,  1; //InterfaceMethod scala/collection/immutable/VectorPointer.display3:()[Ljava/lang/Object;
   549:	iload_1
   550:	ldc	#70; //int 15
   552:	ishr
   553:	ldc	#43; //int 31
   555:	iand
   556:	aload_0
   557:	invokeinterface	#59,  1; //InterfaceMethod scala/collection/immutable/VectorPointer.display2:()[Ljava/lang/Object;
   562:	aastore
   563:	aload_0
   564:	invokeinterface	#77,  1; //InterfaceMethod scala/collection/immutable/VectorPointer.display4:()[Ljava/lang/Object;
   569:	iload_1
   570:	ldc	#78; //int 20
   572:	ishr
   573:	ldc	#43; //int 31
   575:	iand
   576:	aload_0
   577:	invokeinterface	#69,  1; //InterfaceMethod scala/collection/immutable/VectorPointer.display3:()[Ljava/lang/Object;
   582:	aastore
   583:	aload_0
   584:	aload_0
   585:	aload_0
   586:	invokeinterface	#77,  1; //InterfaceMethod scala/collection/immutable/VectorPointer.display4:()[Ljava/lang/Object;
   591:	iload_2
   592:	ldc	#78; //int 20
   594:	ishr
   595:	ldc	#43; //int 31
   597:	iand
   598:	invokeinterface	#119,  3; //InterfaceMethod scala/collection/immutable/VectorPointer.nullSlotAndCopy:([Ljava/lang/Object;I)[Ljava/lang/Object;
   603:	invokeinterface	#66,  2; //InterfaceMethod scala/collection/immutable/VectorPointer.display3_$eq:([Ljava/lang/Object;)V
   608:	aload_0
   609:	aload_0
   610:	aload_0
   611:	invokeinterface	#69,  1; //InterfaceMethod scala/collection/immutable/VectorPointer.display3:()[Ljava/lang/Object;
   616:	iload_2
   617:	ldc	#70; //int 15
   619:	ishr
   620:	ldc	#43; //int 31
   622:	iand
   623:	invokeinterface	#119,  3; //InterfaceMethod scala/collection/immutable/VectorPointer.nullSlotAndCopy:([Ljava/lang/Object;I)[Ljava/lang/Object;
   628:	invokeinterface	#56,  2; //InterfaceMethod scala/collection/immutable/VectorPointer.display2_$eq:([Ljava/lang/Object;)V
   633:	aload_0
   634:	aload_0
   635:	aload_0
   636:	invokeinterface	#59,  1; //InterfaceMethod scala/collection/immutable/VectorPointer.display2:()[Ljava/lang/Object;
   641:	iload_2
   642:	ldc	#60; //int 10
   644:	ishr
   645:	ldc	#43; //int 31
   647:	iand
   648:	invokeinterface	#119,  3; //InterfaceMethod scala/collection/immutable/VectorPointer.nullSlotAndCopy:([Ljava/lang/Object;I)[Ljava/lang/Object;
   653:	invokeinterface	#38,  2; //InterfaceMethod scala/collection/immutable/VectorPointer.display1_$eq:([Ljava/lang/Object;)V
   658:	aload_0
   659:	aload_0
   660:	aload_0
   661:	invokeinterface	#42,  1; //InterfaceMethod scala/collection/immutable/VectorPointer.display1:()[Ljava/lang/Object;
   666:	iload_2
   667:	iconst_5
   668:	ishr
   669:	ldc	#43; //int 31
   671:	iand
   672:	invokeinterface	#119,  3; //InterfaceMethod scala/collection/immutable/VectorPointer.nullSlotAndCopy:([Ljava/lang/Object;I)[Ljava/lang/Object;
   677:	invokeinterface	#52,  2; //InterfaceMethod scala/collection/immutable/VectorPointer.display0_$eq:([Ljava/lang/Object;)V
   682:	goto	1004
   685:	iload_3
   686:	ldc	#79; //int 1073741824
   688:	if_icmpge	1005
   691:	aload_0
   692:	aload_0
   693:	aload_0
   694:	invokeinterface	#42,  1; //InterfaceMethod scala/collection/immutable/VectorPointer.display1:()[Ljava/lang/Object;
   699:	invokeinterface	#115,  2; //InterfaceMethod scala/collection/immutable/VectorPointer.copyOf:([Ljava/lang/Object;)[Ljava/lang/Object;
   704:	invokeinterface	#38,  2; //InterfaceMethod scala/collection/immutable/VectorPointer.display1_$eq:([Ljava/lang/Object;)V
   709:	aload_0
   710:	aload_0
   711:	aload_0
   712:	invokeinterface	#59,  1; //InterfaceMethod scala/collection/immutable/VectorPointer.display2:()[Ljava/lang/Object;
   717:	invokeinterface	#115,  2; //InterfaceMethod scala/collection/immutable/VectorPointer.copyOf:([Ljava/lang/Object;)[Ljava/lang/Object;
   722:	invokeinterface	#56,  2; //InterfaceMethod scala/collection/immutable/VectorPointer.display2_$eq:([Ljava/lang/Object;)V
   727:	aload_0
   728:	aload_0
   729:	aload_0
   730:	invokeinterface	#69,  1; //InterfaceMethod scala/collection/immutable/VectorPointer.display3:()[Ljava/lang/Object;
   735:	invokeinterface	#115,  2; //InterfaceMethod scala/collection/immutable/VectorPointer.copyOf:([Ljava/lang/Object;)[Ljava/lang/Object;
   740:	invokeinterface	#66,  2; //InterfaceMethod scala/collection/immutable/VectorPointer.display3_$eq:([Ljava/lang/Object;)V
   745:	aload_0
   746:	aload_0
   747:	aload_0
   748:	invokeinterface	#77,  1; //InterfaceMethod scala/collection/immutable/VectorPointer.display4:()[Ljava/lang/Object;
   753:	invokeinterface	#115,  2; //InterfaceMethod scala/collection/immutable/VectorPointer.copyOf:([Ljava/lang/Object;)[Ljava/lang/Object;
   758:	invokeinterface	#74,  2; //InterfaceMethod scala/collection/immutable/VectorPointer.display4_$eq:([Ljava/lang/Object;)V
   763:	aload_0
   764:	aload_0
   765:	aload_0
   766:	invokeinterface	#85,  1; //InterfaceMethod scala/collection/immutable/VectorPointer.display5:()[Ljava/lang/Object;
   771:	invokeinterface	#115,  2; //InterfaceMethod scala/collection/immutable/VectorPointer.copyOf:([Ljava/lang/Object;)[Ljava/lang/Object;
   776:	invokeinterface	#82,  2; //InterfaceMethod scala/collection/immutable/VectorPointer.display5_$eq:([Ljava/lang/Object;)V
   781:	aload_0
   782:	invokeinterface	#42,  1; //InterfaceMethod scala/collection/immutable/VectorPointer.display1:()[Ljava/lang/Object;
   787:	iload_1
   788:	iconst_5
   789:	ishr
   790:	ldc	#43; //int 31
   792:	iand
   793:	aload_0
   794:	invokeinterface	#46,  1; //InterfaceMethod scala/collection/immutable/VectorPointer.display0:()[Ljava/lang/Object;
   799:	aastore
   800:	aload_0
   801:	invokeinterface	#59,  1; //InterfaceMethod scala/collection/immutable/VectorPointer.display2:()[Ljava/lang/Object;
   806:	iload_1
   807:	ldc	#60; //int 10
   809:	ishr
   810:	ldc	#43; //int 31
   812:	iand
   813:	aload_0
   814:	invokeinterface	#42,  1; //InterfaceMethod scala/collection/immutable/VectorPointer.display1:()[Ljava/lang/Object;
   819:	aastore
   820:	aload_0
   821:	invokeinterface	#69,  1; //InterfaceMethod scala/collection/immutable/VectorPointer.display3:()[Ljava/lang/Object;
   826:	iload_1
   827:	ldc	#70; //int 15
   829:	ishr
   830:	ldc	#43; //int 31
   832:	iand
   833:	aload_0
   834:	invokeinterface	#59,  1; //InterfaceMethod scala/collection/immutable/VectorPointer.display2:()[Ljava/lang/Object;
   839:	aastore
   840:	aload_0
   841:	invokeinterface	#77,  1; //InterfaceMethod scala/collection/immutable/VectorPointer.display4:()[Ljava/lang/Object;
   846:	iload_1
   847:	ldc	#78; //int 20
   849:	ishr
   850:	ldc	#43; //int 31
   852:	iand
   853:	aload_0
   854:	invokeinterface	#69,  1; //InterfaceMethod scala/collection/immutable/VectorPointer.display3:()[Ljava/lang/Object;
   859:	aastore
   860:	aload_0
   861:	invokeinterface	#85,  1; //InterfaceMethod scala/collection/immutable/VectorPointer.display5:()[Ljava/lang/Object;
   866:	iload_1
   867:	ldc	#86; //int 25
   869:	ishr
   870:	ldc	#43; //int 31
   872:	iand
   873:	aload_0
   874:	invokeinterface	#77,  1; //InterfaceMethod scala/collection/immutable/VectorPointer.display4:()[Ljava/lang/Object;
   879:	aastore
   880:	aload_0
   881:	aload_0
   882:	aload_0
   883:	invokeinterface	#85,  1; //InterfaceMethod scala/collection/immutable/VectorPointer.display5:()[Ljava/lang/Object;
   888:	iload_2
   889:	ldc	#86; //int 25
   891:	ishr
   892:	ldc	#43; //int 31
   894:	iand
   895:	invokeinterface	#119,  3; //InterfaceMethod scala/collection/immutable/VectorPointer.nullSlotAndCopy:([Ljava/lang/Object;I)[Ljava/lang/Object;
   900:	invokeinterface	#74,  2; //InterfaceMethod scala/collection/immutable/VectorPointer.display4_$eq:([Ljava/lang/Object;)V
   905:	aload_0
   906:	aload_0
   907:	aload_0
   908:	invokeinterface	#77,  1; //InterfaceMethod scala/collection/immutable/VectorPointer.display4:()[Ljava/lang/Object;
   913:	iload_2
   914:	ldc	#78; //int 20
   916:	ishr
   917:	ldc	#43; //int 31
   919:	iand
   920:	invokeinterface	#119,  3; //InterfaceMethod scala/collection/immutable/VectorPointer.nullSlotAndCopy:([Ljava/lang/Object;I)[Ljava/lang/Object;
   925:	invokeinterface	#66,  2; //InterfaceMethod scala/collection/immutable/VectorPointer.display3_$eq:([Ljava/lang/Object;)V
   930:	aload_0
   931:	aload_0
   932:	aload_0
   933:	invokeinterface	#69,  1; //InterfaceMethod scala/collection/immutable/VectorPointer.display3:()[Ljava/lang/Object;
   938:	iload_2
   939:	ldc	#70; //int 15
   941:	ishr
   942:	ldc	#43; //int 31
   944:	iand
   945:	invokeinterface	#119,  3; //InterfaceMethod scala/collection/immutable/VectorPointer.nullSlotAndCopy:([Ljava/lang/Object;I)[Ljava/lang/Object;
   950:	invokeinterface	#56,  2; //InterfaceMethod scala/collection/immutable/VectorPointer.display2_$eq:([Ljava/lang/Object;)V
   955:	aload_0
   956:	aload_0
   957:	aload_0
   958:	invokeinterface	#59,  1; //InterfaceMethod scala/collection/immutable/VectorPointer.display2:()[Ljava/lang/Object;
   963:	iload_2
   964:	ldc	#60; //int 10
   966:	ishr
   967:	ldc	#43; //int 31
   969:	iand
   970:	invokeinterface	#119,  3; //InterfaceMethod scala/collection/immutable/VectorPointer.nullSlotAndCopy:([Ljava/lang/Object;I)[Ljava/lang/Object;
   975:	invokeinterface	#38,  2; //InterfaceMethod scala/collection/immutable/VectorPointer.display1_$eq:([Ljava/lang/Object;)V
   980:	aload_0
   981:	aload_0
   982:	aload_0
   983:	invokeinterface	#42,  1; //InterfaceMethod scala/collection/immutable/VectorPointer.display1:()[Ljava/lang/Object;
   988:	iload_2
   989:	iconst_5
   990:	ishr
   991:	ldc	#43; //int 31
   993:	iand
   994:	invokeinterface	#119,  3; //InterfaceMethod scala/collection/immutable/VectorPointer.nullSlotAndCopy:([Ljava/lang/Object;I)[Ljava/lang/Object;
   999:	invokeinterface	#52,  2; //InterfaceMethod scala/collection/immutable/VectorPointer.display0_$eq:([Ljava/lang/Object;)V
   1004:	return
   1005:	new	#88; //class java/lang/IllegalArgumentException
   1008:	dup
   1009:	invokespecial	#92; //Method java/lang/IllegalArgumentException."<init>":()V
   1012:	athrow
  LineNumberTable: 
   line 947: 0
   line 948: 6
   line 950: 27
   line 951: 33
   line 952: 51
   line 953: 70
   line 955: 97
   line 956: 103
   line 957: 121
   line 958: 139
   line 959: 158
   line 960: 178
   line 961: 203
   line 963: 230
   line 964: 236
   line 965: 254
   line 966: 272
   line 967: 290
   line 968: 309
   line 969: 329
   line 970: 349
   line 971: 374
   line 972: 399
   line 974: 426
   line 975: 432
   line 976: 450
   line 977: 468
   line 978: 486
   line 979: 504
   line 980: 523
   line 981: 543
   line 982: 563
   line 983: 583
   line 984: 608
   line 985: 633
   line 986: 658
   line 988: 685
   line 989: 691
   line 990: 709
   line 991: 727
   line 992: 745
   line 993: 763
   line 994: 781
   line 995: 800
   line 996: 820
   line 997: 840
   line 998: 860
   line 999: 880
   line 1000: 905
   line 1001: 930
   line 1002: 955
   line 1003: 980
   line 947: 1004
   line 1005: 1005

  LocalVariableTable: 
   Start  Length  Slot  Name   Signature
   0      1013      0    $this       Lscala/collection/immutable/VectorPointer;
   0      1013      1    oldIndex       I
   0      1013      2    newIndex       I
   0      1013      3    xor       I


public static final void gotoPosWritable0(scala.collection.immutable.VectorPointer, int, int);
  Code:
   Stack=5, Locals=4, Args_size=3
   0:	aload_0
   1:	invokeinterface	#32,  1; //InterfaceMethod scala/collection/immutable/VectorPointer.depth:()I
   6:	iconst_1
   7:	isub
   8:	istore_3
   9:	iload_3
   10:	tableswitch{ //0 to 5
		0: 633;
		1: 569;
		2: 480;
		3: 366;
		4: 227;
		5: 63;
		default: 48 }
   48:	new	#123; //class scala/MatchError
   51:	dup
   52:	iload_3
   53:	invokestatic	#129; //Method scala/runtime/BoxesRunTime.boxToInteger:(I)Ljava/lang/Integer;
   56:	invokevirtual	#133; //Method java/lang/Object.toString:()Ljava/lang/String;
   59:	invokespecial	#136; //Method scala/MatchError."<init>":(Ljava/lang/String;)V
   62:	athrow
   63:	iconst_1
   64:	ifeq	212
   67:	aload_0
   68:	aload_0
   69:	aload_0
   70:	invokeinterface	#85,  1; //InterfaceMethod scala/collection/immutable/VectorPointer.display5:()[Ljava/lang/Object;
   75:	invokeinterface	#115,  2; //InterfaceMethod scala/collection/immutable/VectorPointer.copyOf:([Ljava/lang/Object;)[Ljava/lang/Object;
   80:	invokeinterface	#82,  2; //InterfaceMethod scala/collection/immutable/VectorPointer.display5_$eq:([Ljava/lang/Object;)V
   85:	aload_0
   86:	aload_0
   87:	aload_0
   88:	invokeinterface	#85,  1; //InterfaceMethod scala/collection/immutable/VectorPointer.display5:()[Ljava/lang/Object;
   93:	iload_1
   94:	ldc	#86; //int 25
   96:	ishr
   97:	ldc	#43; //int 31
   99:	iand
   100:	invokeinterface	#119,  3; //InterfaceMethod scala/collection/immutable/VectorPointer.nullSlotAndCopy:([Ljava/lang/Object;I)[Ljava/lang/Object;
   105:	invokeinterface	#74,  2; //InterfaceMethod scala/collection/immutable/VectorPointer.display4_$eq:([Ljava/lang/Object;)V
   110:	aload_0
   111:	aload_0
   112:	aload_0
   113:	invokeinterface	#77,  1; //InterfaceMethod scala/collection/immutable/VectorPointer.display4:()[Ljava/lang/Object;
   118:	iload_1
   119:	ldc	#78; //int 20
   121:	ishr
   122:	ldc	#43; //int 31
   124:	iand
   125:	invokeinterface	#119,  3; //InterfaceMethod scala/collection/immutable/VectorPointer.nullSlotAndCopy:([Ljava/lang/Object;I)[Ljava/lang/Object;
   130:	invokeinterface	#66,  2; //InterfaceMethod scala/collection/immutable/VectorPointer.display3_$eq:([Ljava/lang/Object;)V
   135:	aload_0
   136:	aload_0
   137:	aload_0
   138:	invokeinterface	#69,  1; //InterfaceMethod scala/collection/immutable/VectorPointer.display3:()[Ljava/lang/Object;
   143:	iload_1
   144:	ldc	#70; //int 15
   146:	ishr
   147:	ldc	#43; //int 31
   149:	iand
   150:	invokeinterface	#119,  3; //InterfaceMethod scala/collection/immutable/VectorPointer.nullSlotAndCopy:([Ljava/lang/Object;I)[Ljava/lang/Object;
   155:	invokeinterface	#56,  2; //InterfaceMethod scala/collection/immutable/VectorPointer.display2_$eq:([Ljava/lang/Object;)V
   160:	aload_0
   161:	aload_0
   162:	aload_0
   163:	invokeinterface	#59,  1; //InterfaceMethod scala/collection/immutable/VectorPointer.display2:()[Ljava/lang/Object;
   168:	iload_1
   169:	ldc	#60; //int 10
   171:	ishr
   172:	ldc	#43; //int 31
   174:	iand
   175:	invokeinterface	#119,  3; //InterfaceMethod scala/collection/immutable/VectorPointer.nullSlotAndCopy:([Ljava/lang/Object;I)[Ljava/lang/Object;
   180:	invokeinterface	#38,  2; //InterfaceMethod scala/collection/immutable/VectorPointer.display1_$eq:([Ljava/lang/Object;)V
   185:	aload_0
   186:	aload_0
   187:	aload_0
   188:	invokeinterface	#42,  1; //InterfaceMethod scala/collection/immutable/VectorPointer.display1:()[Ljava/lang/Object;
   193:	iload_1
   194:	iconst_5
   195:	ishr
   196:	ldc	#43; //int 31
   198:	iand
   199:	invokeinterface	#119,  3; //InterfaceMethod scala/collection/immutable/VectorPointer.nullSlotAndCopy:([Ljava/lang/Object;I)[Ljava/lang/Object;
   204:	invokeinterface	#52,  2; //InterfaceMethod scala/collection/immutable/VectorPointer.display0_$eq:([Ljava/lang/Object;)V
   209:	goto	655
   212:	new	#123; //class scala/MatchError
   215:	dup
   216:	iload_3
   217:	invokestatic	#129; //Method scala/runtime/BoxesRunTime.boxToInteger:(I)Ljava/lang/Integer;
   220:	invokevirtual	#133; //Method java/lang/Object.toString:()Ljava/lang/String;
   223:	invokespecial	#136; //Method scala/MatchError."<init>":(Ljava/lang/String;)V
   226:	athrow
   227:	iconst_1
   228:	ifeq	351
   231:	aload_0
   232:	aload_0
   233:	aload_0
   234:	invokeinterface	#77,  1; //InterfaceMethod scala/collection/immutable/VectorPointer.display4:()[Ljava/lang/Object;
   239:	invokeinterface	#115,  2; //InterfaceMethod scala/collection/immutable/VectorPointer.copyOf:([Ljava/lang/Object;)[Ljava/lang/Object;
   244:	invokeinterface	#74,  2; //InterfaceMethod scala/collection/immutable/VectorPointer.display4_$eq:([Ljava/lang/Object;)V
   249:	aload_0
   250:	aload_0
   251:	aload_0
   252:	invokeinterface	#77,  1; //InterfaceMethod scala/collection/immutable/VectorPointer.display4:()[Ljava/lang/Object;
   257:	iload_1
   258:	ldc	#78; //int 20
   260:	ishr
   261:	ldc	#43; //int 31
   263:	iand
   264:	invokeinterface	#119,  3; //InterfaceMethod scala/collection/immutable/VectorPointer.nullSlotAndCopy:([Ljava/lang/Object;I)[Ljava/lang/Object;
   269:	invokeinterface	#66,  2; //InterfaceMethod scala/collection/immutable/VectorPointer.display3_$eq:([Ljava/lang/Object;)V
   274:	aload_0
   275:	aload_0
   276:	aload_0
   277:	invokeinterface	#69,  1; //InterfaceMethod scala/collection/immutable/VectorPointer.display3:()[Ljava/lang/Object;
   282:	iload_1
   283:	ldc	#70; //int 15
   285:	ishr
   286:	ldc	#43; //int 31
   288:	iand
   289:	invokeinterface	#119,  3; //InterfaceMethod scala/collection/immutable/VectorPointer.nullSlotAndCopy:([Ljava/lang/Object;I)[Ljava/lang/Object;
   294:	invokeinterface	#56,  2; //InterfaceMethod scala/collection/immutable/VectorPointer.display2_$eq:([Ljava/lang/Object;)V
   299:	aload_0
   300:	aload_0
   301:	aload_0
   302:	invokeinterface	#59,  1; //InterfaceMethod scala/collection/immutable/VectorPointer.display2:()[Ljava/lang/Object;
   307:	iload_1
   308:	ldc	#60; //int 10
   310:	ishr
   311:	ldc	#43; //int 31
   313:	iand
   314:	invokeinterface	#119,  3; //InterfaceMethod scala/collection/immutable/VectorPointer.nullSlotAndCopy:([Ljava/lang/Object;I)[Ljava/lang/Object;
   319:	invokeinterface	#38,  2; //InterfaceMethod scala/collection/immutable/VectorPointer.display1_$eq:([Ljava/lang/Object;)V
   324:	aload_0
   325:	aload_0
   326:	aload_0
   327:	invokeinterface	#42,  1; //InterfaceMethod scala/collection/immutable/VectorPointer.display1:()[Ljava/lang/Object;
   332:	iload_1
   333:	iconst_5
   334:	ishr
   335:	ldc	#43; //int 31
   337:	iand
   338:	invokeinterface	#119,  3; //InterfaceMethod scala/collection/immutable/VectorPointer.nullSlotAndCopy:([Ljava/lang/Object;I)[Ljava/lang/Object;
   343:	invokeinterface	#52,  2; //InterfaceMethod scala/collection/immutable/VectorPointer.display0_$eq:([Ljava/lang/Object;)V
   348:	goto	655
   351:	new	#123; //class scala/MatchError
   354:	dup
   355:	iload_3
   356:	invokestatic	#129; //Method scala/runtime/BoxesRunTime.boxToInteger:(I)Ljava/lang/Integer;
   359:	invokevirtual	#133; //Method java/lang/Object.toString:()Ljava/lang/String;
   362:	invokespecial	#136; //Method scala/MatchError."<init>":(Ljava/lang/String;)V
   365:	athrow
   366:	iconst_1
   367:	ifeq	465
   370:	aload_0
   371:	aload_0
   372:	aload_0
   373:	invokeinterface	#69,  1; //InterfaceMethod scala/collection/immutable/VectorPointer.display3:()[Ljava/lang/Object;
   378:	invokeinterface	#115,  2; //InterfaceMethod scala/collection/immutable/VectorPointer.copyOf:([Ljava/lang/Object;)[Ljava/lang/Object;
   383:	invokeinterface	#66,  2; //InterfaceMethod scala/collection/immutable/VectorPointer.display3_$eq:([Ljava/lang/Object;)V
   388:	aload_0
   389:	aload_0
   390:	aload_0
   391:	invokeinterface	#69,  1; //InterfaceMethod scala/collection/immutable/VectorPointer.display3:()[Ljava/lang/Object;
   396:	iload_1
   397:	ldc	#70; //int 15
   399:	ishr
   400:	ldc	#43; //int 31
   402:	iand
   403:	invokeinterface	#119,  3; //InterfaceMethod scala/collection/immutable/VectorPointer.nullSlotAndCopy:([Ljava/lang/Object;I)[Ljava/lang/Object;
   408:	invokeinterface	#56,  2; //InterfaceMethod scala/collection/immutable/VectorPointer.display2_$eq:([Ljava/lang/Object;)V
   413:	aload_0
   414:	aload_0
   415:	aload_0
   416:	invokeinterface	#59,  1; //InterfaceMethod scala/collection/immutable/VectorPointer.display2:()[Ljava/lang/Object;
   421:	iload_1
   422:	ldc	#60; //int 10
   424:	ishr
   425:	ldc	#43; //int 31
   427:	iand
   428:	invokeinterface	#119,  3; //InterfaceMethod scala/collection/immutable/VectorPointer.nullSlotAndCopy:([Ljava/lang/Object;I)[Ljava/lang/Object;
   433:	invokeinterface	#38,  2; //InterfaceMethod scala/collection/immutable/VectorPointer.display1_$eq:([Ljava/lang/Object;)V
   438:	aload_0
   439:	aload_0
   440:	aload_0
   441:	invokeinterface	#42,  1; //InterfaceMethod scala/collection/immutable/VectorPointer.display1:()[Ljava/lang/Object;
   446:	iload_1
   447:	iconst_5
   448:	ishr
   449:	ldc	#43; //int 31
   451:	iand
   452:	invokeinterface	#119,  3; //InterfaceMethod scala/collection/immutable/VectorPointer.nullSlotAndCopy:([Ljava/lang/Object;I)[Ljava/lang/Object;
   457:	invokeinterface	#52,  2; //InterfaceMethod scala/collection/immutable/VectorPointer.display0_$eq:([Ljava/lang/Object;)V
   462:	goto	655
   465:	new	#123; //class scala/MatchError
   468:	dup
   469:	iload_3
   470:	invokestatic	#129; //Method scala/runtime/BoxesRunTime.boxToInteger:(I)Ljava/lang/Integer;
   473:	invokevirtual	#133; //Method java/lang/Object.toString:()Ljava/lang/String;
   476:	invokespecial	#136; //Method scala/MatchError."<init>":(Ljava/lang/String;)V
   479:	athrow
   480:	iconst_1
   481:	ifeq	554
   484:	aload_0
   485:	aload_0
   486:	aload_0
   487:	invokeinterface	#59,  1; //InterfaceMethod scala/collection/immutable/VectorPointer.display2:()[Ljava/lang/Object;
   492:	invokeinterface	#115,  2; //InterfaceMethod scala/collection/immutable/VectorPointer.copyOf:([Ljava/lang/Object;)[Ljava/lang/Object;
   497:	invokeinterface	#56,  2; //InterfaceMethod scala/collection/immutable/VectorPointer.display2_$eq:([Ljava/lang/Object;)V
   502:	aload_0
   503:	aload_0
   504:	aload_0
   505:	invokeinterface	#59,  1; //InterfaceMethod scala/collection/immutable/VectorPointer.display2:()[Ljava/lang/Object;
   510:	iload_1
   511:	ldc	#60; //int 10
   513:	ishr
   514:	ldc	#43; //int 31
   516:	iand
   517:	invokeinterface	#119,  3; //InterfaceMethod scala/collection/immutable/VectorPointer.nullSlotAndCopy:([Ljava/lang/Object;I)[Ljava/lang/Object;
   522:	invokeinterface	#38,  2; //InterfaceMethod scala/collection/immutable/VectorPointer.display1_$eq:([Ljava/lang/Object;)V
   527:	aload_0
   528:	aload_0
   529:	aload_0
   530:	invokeinterface	#42,  1; //InterfaceMethod scala/collection/immutable/VectorPointer.display1:()[Ljava/lang/Object;
   535:	iload_1
   536:	iconst_5
   537:	ishr
   538:	ldc	#43; //int 31
   540:	iand
   541:	invokeinterface	#119,  3; //InterfaceMethod scala/collection/immutable/VectorPointer.nullSlotAndCopy:([Ljava/lang/Object;I)[Ljava/lang/Object;
   546:	invokeinterface	#52,  2; //InterfaceMethod scala/collection/immutable/VectorPointer.display0_$eq:([Ljava/lang/Object;)V
   551:	goto	655
   554:	new	#123; //class scala/MatchError
   557:	dup
   558:	iload_3
   559:	invokestatic	#129; //Method scala/runtime/BoxesRunTime.boxToInteger:(I)Ljava/lang/Integer;
   562:	invokevirtual	#133; //Method java/lang/Object.toString:()Ljava/lang/String;
   565:	invokespecial	#136; //Method scala/MatchError."<init>":(Ljava/lang/String;)V
   568:	athrow
   569:	iconst_1
   570:	ifeq	618
   573:	aload_0
   574:	aload_0
   575:	aload_0
   576:	invokeinterface	#42,  1; //InterfaceMethod scala/collection/immutable/VectorPointer.display1:()[Ljava/lang/Object;
   581:	invokeinterface	#115,  2; //InterfaceMethod scala/collection/immutable/VectorPointer.copyOf:([Ljava/lang/Object;)[Ljava/lang/Object;
   586:	invokeinterface	#38,  2; //InterfaceMethod scala/collection/immutable/VectorPointer.display1_$eq:([Ljava/lang/Object;)V
   591:	aload_0
   592:	aload_0
   593:	aload_0
   594:	invokeinterface	#42,  1; //InterfaceMethod scala/collection/immutable/VectorPointer.display1:()[Ljava/lang/Object;
   599:	iload_1
   600:	iconst_5
   601:	ishr
   602:	ldc	#43; //int 31
   604:	iand
   605:	invokeinterface	#119,  3; //InterfaceMethod scala/collection/immutable/VectorPointer.nullSlotAndCopy:([Ljava/lang/Object;I)[Ljava/lang/Object;
   610:	invokeinterface	#52,  2; //InterfaceMethod scala/collection/immutable/VectorPointer.display0_$eq:([Ljava/lang/Object;)V
   615:	goto	655
   618:	new	#123; //class scala/MatchError
   621:	dup
   622:	iload_3
   623:	invokestatic	#129; //Method scala/runtime/BoxesRunTime.boxToInteger:(I)Ljava/lang/Integer;
   626:	invokevirtual	#133; //Method java/lang/Object.toString:()Ljava/lang/String;
   629:	invokespecial	#136; //Method scala/MatchError."<init>":(Ljava/lang/String;)V
   632:	athrow
   633:	iconst_1
   634:	ifeq	656
   637:	aload_0
   638:	aload_0
   639:	aload_0
   640:	invokeinterface	#46,  1; //InterfaceMethod scala/collection/immutable/VectorPointer.display0:()[Ljava/lang/Object;
   645:	invokeinterface	#115,  2; //InterfaceMethod scala/collection/immutable/VectorPointer.copyOf:([Ljava/lang/Object;)[Ljava/lang/Object;
   650:	invokeinterface	#52,  2; //InterfaceMethod scala/collection/immutable/VectorPointer.display0_$eq:([Ljava/lang/Object;)V
   655:	return
   656:	new	#123; //class scala/MatchError
   659:	dup
   660:	iload_3
   661:	invokestatic	#129; //Method scala/runtime/BoxesRunTime.boxToInteger:(I)Ljava/lang/Integer;
   664:	invokevirtual	#133; //Method java/lang/Object.toString:()Ljava/lang/String;
   667:	invokespecial	#136; //Method scala/MatchError."<init>":(Ljava/lang/String;)V
   670:	athrow
  LineNumberTable: 
   line 913: 0
   line 21: 63
   line 915: 67
   line 916: 85
   line 917: 110
   line 918: 135
   line 919: 160
   line 920: 185
   line 913: 212
   line 21: 227
   line 922: 231
   line 923: 249
   line 924: 274
   line 925: 299
   line 926: 324
   line 913: 351
   line 21: 366
   line 928: 370
   line 929: 388
   line 930: 413
   line 931: 438
   line 913: 465
   line 21: 480
   line 933: 484
   line 934: 502
   line 935: 527
   line 913: 554
   line 21: 569
   line 937: 573
   line 938: 591
   line 913: 618
   line 21: 633
   line 940: 637
   line 913: 655

  LocalVariableTable: 
   Start  Length  Slot  Name   Signature
   0      671      0    $this       Lscala/collection/immutable/VectorPointer;
   0      671      1    newIndex       I
   0      671      2    xor       I
   9      662      3    temp5       I


public static final void stabilize(scala.collection.immutable.VectorPointer, int);
  Code:
   Stack=3, Locals=3, Args_size=2
   0:	aload_0
   1:	invokeinterface	#32,  1; //InterfaceMethod scala/collection/immutable/VectorPointer.depth:()I
   6:	iconst_1
   7:	isub
   8:	istore_2
   9:	iload_2
   10:	tableswitch{ //0 to 5
		0: 738;
		1: 679;
		2: 582;
		3: 447;
		4: 274;
		5: 63;
		default: 48 }
   48:	new	#123; //class scala/MatchError
   51:	dup
   52:	iload_2
   53:	invokestatic	#129; //Method scala/runtime/BoxesRunTime.boxToInteger:(I)Ljava/lang/Integer;
   56:	invokevirtual	#133; //Method java/lang/Object.toString:()Ljava/lang/String;
   59:	invokespecial	#136; //Method scala/MatchError."<init>":(Ljava/lang/String;)V
   62:	athrow
   63:	iconst_1
   64:	ifeq	259
   67:	aload_0
   68:	aload_0
   69:	aload_0
   70:	invokeinterface	#85,  1; //InterfaceMethod scala/collection/immutable/VectorPointer.display5:()[Ljava/lang/Object;
   75:	invokeinterface	#115,  2; //InterfaceMethod scala/collection/immutable/VectorPointer.copyOf:([Ljava/lang/Object;)[Ljava/lang/Object;
   80:	invokeinterface	#82,  2; //InterfaceMethod scala/collection/immutable/VectorPointer.display5_$eq:([Ljava/lang/Object;)V
   85:	aload_0
   86:	aload_0
   87:	aload_0
   88:	invokeinterface	#77,  1; //InterfaceMethod scala/collection/immutable/VectorPointer.display4:()[Ljava/lang/Object;
   93:	invokeinterface	#115,  2; //InterfaceMethod scala/collection/immutable/VectorPointer.copyOf:([Ljava/lang/Object;)[Ljava/lang/Object;
   98:	invokeinterface	#74,  2; //InterfaceMethod scala/collection/immutable/VectorPointer.display4_$eq:([Ljava/lang/Object;)V
   103:	aload_0
   104:	aload_0
   105:	aload_0
   106:	invokeinterface	#69,  1; //InterfaceMethod scala/collection/immutable/VectorPointer.display3:()[Ljava/lang/Object;
   111:	invokeinterface	#115,  2; //InterfaceMethod scala/collection/immutable/VectorPointer.copyOf:([Ljava/lang/Object;)[Ljava/lang/Object;
   116:	invokeinterface	#66,  2; //InterfaceMethod scala/collection/immutable/VectorPointer.display3_$eq:([Ljava/lang/Object;)V
   121:	aload_0
   122:	aload_0
   123:	aload_0
   124:	invokeinterface	#59,  1; //InterfaceMethod scala/collection/immutable/VectorPointer.display2:()[Ljava/lang/Object;
   129:	invokeinterface	#115,  2; //InterfaceMethod scala/collection/immutable/VectorPointer.copyOf:([Ljava/lang/Object;)[Ljava/lang/Object;
   134:	invokeinterface	#56,  2; //InterfaceMethod scala/collection/immutable/VectorPointer.display2_$eq:([Ljava/lang/Object;)V
   139:	aload_0
   140:	aload_0
   141:	aload_0
   142:	invokeinterface	#42,  1; //InterfaceMethod scala/collection/immutable/VectorPointer.display1:()[Ljava/lang/Object;
   147:	invokeinterface	#115,  2; //InterfaceMethod scala/collection/immutable/VectorPointer.copyOf:([Ljava/lang/Object;)[Ljava/lang/Object;
   152:	invokeinterface	#38,  2; //InterfaceMethod scala/collection/immutable/VectorPointer.display1_$eq:([Ljava/lang/Object;)V
   157:	aload_0
   158:	invokeinterface	#85,  1; //InterfaceMethod scala/collection/immutable/VectorPointer.display5:()[Ljava/lang/Object;
   163:	iload_1
   164:	ldc	#86; //int 25
   166:	ishr
   167:	ldc	#43; //int 31
   169:	iand
   170:	aload_0
   171:	invokeinterface	#77,  1; //InterfaceMethod scala/collection/immutable/VectorPointer.display4:()[Ljava/lang/Object;
   176:	aastore
   177:	aload_0
   178:	invokeinterface	#77,  1; //InterfaceMethod scala/collection/immutable/VectorPointer.display4:()[Ljava/lang/Object;
   183:	iload_1
   184:	ldc	#78; //int 20
   186:	ishr
   187:	ldc	#43; //int 31
   189:	iand
   190:	aload_0
   191:	invokeinterface	#69,  1; //InterfaceMethod scala/collection/immutable/VectorPointer.display3:()[Ljava/lang/Object;
   196:	aastore
   197:	aload_0
   198:	invokeinterface	#69,  1; //InterfaceMethod scala/collection/immutable/VectorPointer.display3:()[Ljava/lang/Object;
   203:	iload_1
   204:	ldc	#70; //int 15
   206:	ishr
   207:	ldc	#43; //int 31
   209:	iand
   210:	aload_0
   211:	invokeinterface	#59,  1; //InterfaceMethod scala/collection/immutable/VectorPointer.display2:()[Ljava/lang/Object;
   216:	aastore
   217:	aload_0
   218:	invokeinterface	#59,  1; //InterfaceMethod scala/collection/immutable/VectorPointer.display2:()[Ljava/lang/Object;
   223:	iload_1
   224:	ldc	#60; //int 10
   226:	ishr
   227:	ldc	#43; //int 31
   229:	iand
   230:	aload_0
   231:	invokeinterface	#42,  1; //InterfaceMethod scala/collection/immutable/VectorPointer.display1:()[Ljava/lang/Object;
   236:	aastore
   237:	aload_0
   238:	invokeinterface	#42,  1; //InterfaceMethod scala/collection/immutable/VectorPointer.display1:()[Ljava/lang/Object;
   243:	iload_1
   244:	iconst_5
   245:	ishr
   246:	ldc	#43; //int 31
   248:	iand
   249:	aload_0
   250:	invokeinterface	#46,  1; //InterfaceMethod scala/collection/immutable/VectorPointer.display0:()[Ljava/lang/Object;
   255:	aastore
   256:	goto	742
   259:	new	#123; //class scala/MatchError
   262:	dup
   263:	iload_2
   264:	invokestatic	#129; //Method scala/runtime/BoxesRunTime.boxToInteger:(I)Ljava/lang/Integer;
   267:	invokevirtual	#133; //Method java/lang/Object.toString:()Ljava/lang/String;
   270:	invokespecial	#136; //Method scala/MatchError."<init>":(Ljava/lang/String;)V
   273:	athrow
   274:	iconst_1
   275:	ifeq	432
   278:	aload_0
   279:	aload_0
   280:	aload_0
   281:	invokeinterface	#77,  1; //InterfaceMethod scala/collection/immutable/VectorPointer.display4:()[Ljava/lang/Object;
   286:	invokeinterface	#115,  2; //InterfaceMethod scala/collection/immutable/VectorPointer.copyOf:([Ljava/lang/Object;)[Ljava/lang/Object;
   291:	invokeinterface	#74,  2; //InterfaceMethod scala/collection/immutable/VectorPointer.display4_$eq:([Ljava/lang/Object;)V
   296:	aload_0
   297:	aload_0
   298:	aload_0
   299:	invokeinterface	#69,  1; //InterfaceMethod scala/collection/immutable/VectorPointer.display3:()[Ljava/lang/Object;
   304:	invokeinterface	#115,  2; //InterfaceMethod scala/collection/immutable/VectorPointer.copyOf:([Ljava/lang/Object;)[Ljava/lang/Object;
   309:	invokeinterface	#66,  2; //InterfaceMethod scala/collection/immutable/VectorPointer.display3_$eq:([Ljava/lang/Object;)V
   314:	aload_0
   315:	aload_0
   316:	aload_0
   317:	invokeinterface	#59,  1; //InterfaceMethod scala/collection/immutable/VectorPointer.display2:()[Ljava/lang/Object;
   322:	invokeinterface	#115,  2; //InterfaceMethod scala/collection/immutable/VectorPointer.copyOf:([Ljava/lang/Object;)[Ljava/lang/Object;
   327:	invokeinterface	#56,  2; //InterfaceMethod scala/collection/immutable/VectorPointer.display2_$eq:([Ljava/lang/Object;)V
   332:	aload_0
   333:	aload_0
   334:	aload_0
   335:	invokeinterface	#42,  1; //InterfaceMethod scala/collection/immutable/VectorPointer.display1:()[Ljava/lang/Object;
   340:	invokeinterface	#115,  2; //InterfaceMethod scala/collection/immutable/VectorPointer.copyOf:([Ljava/lang/Object;)[Ljava/lang/Object;
   345:	invokeinterface	#38,  2; //InterfaceMethod scala/collection/immutable/VectorPointer.display1_$eq:([Ljava/lang/Object;)V
   350:	aload_0
   351:	invokeinterface	#77,  1; //InterfaceMethod scala/collection/immutable/VectorPointer.display4:()[Ljava/lang/Object;
   356:	iload_1
   357:	ldc	#78; //int 20
   359:	ishr
   360:	ldc	#43; //int 31
   362:	iand
   363:	aload_0
   364:	invokeinterface	#69,  1; //InterfaceMethod scala/collection/immutable/VectorPointer.display3:()[Ljava/lang/Object;
   369:	aastore
   370:	aload_0
   371:	invokeinterface	#69,  1; //InterfaceMethod scala/collection/immutable/VectorPointer.display3:()[Ljava/lang/Object;
   376:	iload_1
   377:	ldc	#70; //int 15
   379:	ishr
   380:	ldc	#43; //int 31
   382:	iand
   383:	aload_0
   384:	invokeinterface	#59,  1; //InterfaceMethod scala/collection/immutable/VectorPointer.display2:()[Ljava/lang/Object;
   389:	aastore
   390:	aload_0
   391:	invokeinterface	#59,  1; //InterfaceMethod scala/collection/immutable/VectorPointer.display2:()[Ljava/lang/Object;
   396:	iload_1
   397:	ldc	#60; //int 10
   399:	ishr
   400:	ldc	#43; //int 31
   402:	iand
   403:	aload_0
   404:	invokeinterface	#42,  1; //InterfaceMethod scala/collection/immutable/VectorPointer.display1:()[Ljava/lang/Object;
   409:	aastore
   410:	aload_0
   411:	invokeinterface	#42,  1; //InterfaceMethod scala/collection/immutable/VectorPointer.display1:()[Ljava/lang/Object;
   416:	iload_1
   417:	iconst_5
   418:	ishr
   419:	ldc	#43; //int 31
   421:	iand
   422:	aload_0
   423:	invokeinterface	#46,  1; //InterfaceMethod scala/collection/immutable/VectorPointer.display0:()[Ljava/lang/Object;
   428:	aastore
   429:	goto	742
   432:	new	#123; //class scala/MatchError
   435:	dup
   436:	iload_2
   437:	invokestatic	#129; //Method scala/runtime/BoxesRunTime.boxToInteger:(I)Ljava/lang/Integer;
   440:	invokevirtual	#133; //Method java/lang/Object.toString:()Ljava/lang/String;
   443:	invokespecial	#136; //Method scala/MatchError."<init>":(Ljava/lang/String;)V
   446:	athrow
   447:	iconst_1
   448:	ifeq	567
   451:	aload_0
   452:	aload_0
   453:	aload_0
   454:	invokeinterface	#69,  1; //InterfaceMethod scala/collection/immutable/VectorPointer.display3:()[Ljava/lang/Object;
   459:	invokeinterface	#115,  2; //InterfaceMethod scala/collection/immutable/VectorPointer.copyOf:([Ljava/lang/Object;)[Ljava/lang/Object;
   464:	invokeinterface	#66,  2; //InterfaceMethod scala/collection/immutable/VectorPointer.display3_$eq:([Ljava/lang/Object;)V
   469:	aload_0
   470:	aload_0
   471:	aload_0
   472:	invokeinterface	#59,  1; //InterfaceMethod scala/collection/immutable/VectorPointer.display2:()[Ljava/lang/Object;
   477:	invokeinterface	#115,  2; //InterfaceMethod scala/collection/immutable/VectorPointer.copyOf:([Ljava/lang/Object;)[Ljava/lang/Object;
   482:	invokeinterface	#56,  2; //InterfaceMethod scala/collection/immutable/VectorPointer.display2_$eq:([Ljava/lang/Object;)V
   487:	aload_0
   488:	aload_0
   489:	aload_0
   490:	invokeinterface	#42,  1; //InterfaceMethod scala/collection/immutable/VectorPointer.display1:()[Ljava/lang/Object;
   495:	invokeinterface	#115,  2; //InterfaceMethod scala/collection/immutable/VectorPointer.copyOf:([Ljava/lang/Object;)[Ljava/lang/Object;
   500:	invokeinterface	#38,  2; //InterfaceMethod scala/collection/immutable/VectorPointer.display1_$eq:([Ljava/lang/Object;)V
   505:	aload_0
   506:	invokeinterface	#69,  1; //InterfaceMethod scala/collection/immutable/VectorPointer.display3:()[Ljava/lang/Object;
   511:	iload_1
   512:	ldc	#70; //int 15
   514:	ishr
   515:	ldc	#43; //int 31
   517:	iand
   518:	aload_0
   519:	invokeinterface	#59,  1; //InterfaceMethod scala/collection/immutable/VectorPointer.display2:()[Ljava/lang/Object;
   524:	aastore
   525:	aload_0
   526:	invokeinterface	#59,  1; //InterfaceMethod scala/collection/immutable/VectorPointer.display2:()[Ljava/lang/Object;
   531:	iload_1
   532:	ldc	#60; //int 10
   534:	ishr
   535:	ldc	#43; //int 31
   537:	iand
   538:	aload_0
   539:	invokeinterface	#42,  1; //InterfaceMethod scala/collection/immutable/VectorPointer.display1:()[Ljava/lang/Object;
   544:	aastore
   545:	aload_0
   546:	invokeinterface	#42,  1; //InterfaceMethod scala/collection/immutable/VectorPointer.display1:()[Ljava/lang/Object;
   551:	iload_1
   552:	iconst_5
   553:	ishr
   554:	ldc	#43; //int 31
   556:	iand
   557:	aload_0
   558:	invokeinterface	#46,  1; //InterfaceMethod scala/collection/immutable/VectorPointer.display0:()[Ljava/lang/Object;
   563:	aastore
   564:	goto	742
   567:	new	#123; //class scala/MatchError
   570:	dup
   571:	iload_2
   572:	invokestatic	#129; //Method scala/runtime/BoxesRunTime.boxToInteger:(I)Ljava/lang/Integer;
   575:	invokevirtual	#133; //Method java/lang/Object.toString:()Ljava/lang/String;
   578:	invokespecial	#136; //Method scala/MatchError."<init>":(Ljava/lang/String;)V
   581:	athrow
   582:	iconst_1
   583:	ifeq	664
   586:	aload_0
   587:	aload_0
   588:	aload_0
   589:	invokeinterface	#59,  1; //InterfaceMethod scala/collection/immutable/VectorPointer.display2:()[Ljava/lang/Object;
   594:	invokeinterface	#115,  2; //InterfaceMethod scala/collection/immutable/VectorPointer.copyOf:([Ljava/lang/Object;)[Ljava/lang/Object;
   599:	invokeinterface	#56,  2; //InterfaceMethod scala/collection/immutable/VectorPointer.display2_$eq:([Ljava/lang/Object;)V
   604:	aload_0
   605:	aload_0
   606:	aload_0
   607:	invokeinterface	#42,  1; //InterfaceMethod scala/collection/immutable/VectorPointer.display1:()[Ljava/lang/Object;
   612:	invokeinterface	#115,  2; //InterfaceMethod scala/collection/immutable/VectorPointer.copyOf:([Ljava/lang/Object;)[Ljava/lang/Object;
   617:	invokeinterface	#38,  2; //InterfaceMethod scala/collection/immutable/VectorPointer.display1_$eq:([Ljava/lang/Object;)V
   622:	aload_0
   623:	invokeinterface	#59,  1; //InterfaceMethod scala/collection/immutable/VectorPointer.display2:()[Ljava/lang/Object;
   628:	iload_1
   629:	ldc	#60; //int 10
   631:	ishr
   632:	ldc	#43; //int 31
   634:	iand
   635:	aload_0
   636:	invokeinterface	#42,  1; //InterfaceMethod scala/collection/immutable/VectorPointer.display1:()[Ljava/lang/Object;
   641:	aastore
   642:	aload_0
   643:	invokeinterface	#42,  1; //InterfaceMethod scala/collection/immutable/VectorPointer.display1:()[Ljava/lang/Object;
   648:	iload_1
   649:	iconst_5
   650:	ishr
   651:	ldc	#43; //int 31
   653:	iand
   654:	aload_0
   655:	invokeinterface	#46,  1; //InterfaceMethod scala/collection/immutable/VectorPointer.display0:()[Ljava/lang/Object;
   660:	aastore
   661:	goto	742
   664:	new	#123; //class scala/MatchError
   667:	dup
   668:	iload_2
   669:	invokestatic	#129; //Method scala/runtime/BoxesRunTime.boxToInteger:(I)Ljava/lang/Integer;
   672:	invokevirtual	#133; //Method java/lang/Object.toString:()Ljava/lang/String;
   675:	invokespecial	#136; //Method scala/MatchError."<init>":(Ljava/lang/String;)V
   678:	athrow
   679:	iconst_1
   680:	ifeq	723
   683:	aload_0
   684:	aload_0
   685:	aload_0
   686:	invokeinterface	#42,  1; //InterfaceMethod scala/collection/immutable/VectorPointer.display1:()[Ljava/lang/Object;
   691:	invokeinterface	#115,  2; //InterfaceMethod scala/collection/immutable/VectorPointer.copyOf:([Ljava/lang/Object;)[Ljava/lang/Object;
   696:	invokeinterface	#38,  2; //InterfaceMethod scala/collection/immutable/VectorPointer.display1_$eq:([Ljava/lang/Object;)V
   701:	aload_0
   702:	invokeinterface	#42,  1; //InterfaceMethod scala/collection/immutable/VectorPointer.display1:()[Ljava/lang/Object;
   707:	iload_1
   708:	iconst_5
   709:	ishr
   710:	ldc	#43; //int 31
   712:	iand
   713:	aload_0
   714:	invokeinterface	#46,  1; //InterfaceMethod scala/collection/immutable/VectorPointer.display0:()[Ljava/lang/Object;
   719:	aastore
   720:	goto	742
   723:	new	#123; //class scala/MatchError
   726:	dup
   727:	iload_2
   728:	invokestatic	#129; //Method scala/runtime/BoxesRunTime.boxToInteger:(I)Ljava/lang/Integer;
   731:	invokevirtual	#133; //Method java/lang/Object.toString:()Ljava/lang/String;
   734:	invokespecial	#136; //Method scala/MatchError."<init>":(Ljava/lang/String;)V
   737:	athrow
   738:	iconst_1
   739:	ifeq	743
   742:	return
   743:	new	#123; //class scala/MatchError
   746:	dup
   747:	iload_2
   748:	invokestatic	#129; //Method scala/runtime/BoxesRunTime.boxToInteger:(I)Ljava/lang/Integer;
   751:	invokevirtual	#133; //Method java/lang/Object.toString:()Ljava/lang/String;
   754:	invokespecial	#136; //Method scala/MatchError."<init>":(Ljava/lang/String;)V
   757:	athrow
  LineNumberTable: 
   line 863: 0
   line 21: 63
   line 865: 67
   line 866: 85
   line 867: 103
   line 868: 121
   line 869: 139
   line 870: 157
   line 871: 177
   line 872: 197
   line 873: 217
   line 874: 237
   line 863: 259
   line 21: 274
   line 876: 278
   line 877: 296
   line 878: 314
   line 879: 332
   line 880: 350
   line 881: 370
   line 882: 390
   line 883: 410
   line 863: 432
   line 21: 447
   line 885: 451
   line 886: 469
   line 887: 487
   line 888: 505
   line 889: 525
   line 890: 545
   line 863: 567
   line 21: 582
   line 892: 586
   line 893: 604
   line 894: 622
   line 895: 642
   line 863: 664
   line 21: 679
   line 897: 683
   line 898: 701
   line 863: 723
   line 21: 738
   line 863: 742

  LocalVariableTable: 
   Start  Length  Slot  Name   Signature
   0      758      0    $this       Lscala/collection/immutable/VectorPointer;
   0      758      1    index       I
   9      749      2    temp4       I


public static final java.lang.Object[] nullSlotAndCopy(scala.collection.immutable.VectorPointer, java.lang.Object[], int);
  Code:
   Stack=3, Locals=4, Args_size=3
   0:	aload_1
   1:	iload_2
   2:	aaload
   3:	astore_3
   4:	aload_1
   5:	iload_2
   6:	aconst_null
   7:	aastore
   8:	aload_0
   9:	aload_3
   10:	checkcast	#62; //class "[Ljava/lang/Object;"
   13:	invokeinterface	#115,  2; //InterfaceMethod scala/collection/immutable/VectorPointer.copyOf:([Ljava/lang/Object;)[Ljava/lang/Object;
   18:	areturn
  LineNumberTable: 
   line 853: 0
   line 854: 4
   line 855: 8

  LocalVariableTable: 
   Start  Length  Slot  Name   Signature
   0      19      0    $this       Lscala/collection/immutable/VectorPointer;
   0      19      1    array       [Ljava/lang/Object;
   0      19      2    index       I
   4      14      3    x       Ljava/lang/Object;


public static final java.lang.Object[] copyOf(scala.collection.immutable.VectorPointer, java.lang.Object[]);
  Code:
   Stack=5, Locals=6, Args_size=2
   0:	aload_1
   1:	arraylength
   2:	anewarray	#34; //class java/lang/Object
   5:	astore	5
   7:	iconst_0
   8:	iconst_0
   9:	aload_1
   10:	arraylength
   11:	istore	4
   13:	istore_3
   14:	istore_2
   15:	aload_1
   16:	iload_2
   17:	aload	5
   19:	iload_3
   20:	iload	4
   22:	invokestatic	#106; //Method java/lang/System.arraycopy:(Ljava/lang/Object;ILjava/lang/Object;II)V
   25:	aload	5
   27:	areturn
  LineNumberTable: 
   line 846: 0
   line 847: 7
   line 848: 25

  LocalVariableTable: 
   Start  Length  Slot  Name   Signature
   0      28      0    $this       Lscala/collection/immutable/VectorPointer;
   0      28      1    a       [Ljava/lang/Object;
   7      20      5    b       [Ljava/lang/Object;


public static final void gotoNextBlockStartWritable(scala.collection.immutable.VectorPointer, int, int);
  Code:
   Stack=3, Locals=3, Args_size=3
   0:	iload_2
   1:	ldc	#28; //int 1024
   3:	if_icmpge	88
   6:	aload_0
   7:	invokeinterface	#32,  1; //InterfaceMethod scala/collection/immutable/VectorPointer.depth:()I
   12:	iconst_1
   13:	if_icmpne	55
   16:	aload_0
   17:	ldc	#27; //int 32
   19:	anewarray	#34; //class java/lang/Object
   22:	invokeinterface	#38,  2; //InterfaceMethod scala/collection/immutable/VectorPointer.display1_$eq:([Ljava/lang/Object;)V
   27:	aload_0
   28:	invokeinterface	#42,  1; //InterfaceMethod scala/collection/immutable/VectorPointer.display1:()[Ljava/lang/Object;
   33:	iconst_0
   34:	aload_0
   35:	invokeinterface	#46,  1; //InterfaceMethod scala/collection/immutable/VectorPointer.display0:()[Ljava/lang/Object;
   40:	aastore
   41:	aload_0
   42:	aload_0
   43:	invokeinterface	#32,  1; //InterfaceMethod scala/collection/immutable/VectorPointer.depth:()I
   48:	iconst_1
   49:	iadd
   50:	invokeinterface	#49,  2; //InterfaceMethod scala/collection/immutable/VectorPointer.depth_$eq:(I)V
   55:	aload_0
   56:	ldc	#27; //int 32
   58:	anewarray	#34; //class java/lang/Object
   61:	invokeinterface	#52,  2; //InterfaceMethod scala/collection/immutable/VectorPointer.display0_$eq:([Ljava/lang/Object;)V
   66:	aload_0
   67:	invokeinterface	#42,  1; //InterfaceMethod scala/collection/immutable/VectorPointer.display1:()[Ljava/lang/Object;
   72:	iload_1
   73:	iconst_5
   74:	ishr
   75:	ldc	#43; //int 31
   77:	iand
   78:	aload_0
   79:	invokeinterface	#46,  1; //InterfaceMethod scala/collection/immutable/VectorPointer.display0:()[Ljava/lang/Object;
   84:	aastore
   85:	goto	747
   88:	iload_2
   89:	ldc	#53; //int 32768
   91:	if_icmpge	207
   94:	aload_0
   95:	invokeinterface	#32,  1; //InterfaceMethod scala/collection/immutable/VectorPointer.depth:()I
   100:	iconst_2
   101:	if_icmpne	143
   104:	aload_0
   105:	ldc	#27; //int 32
   107:	anewarray	#34; //class java/lang/Object
   110:	invokeinterface	#56,  2; //InterfaceMethod scala/collection/immutable/VectorPointer.display2_$eq:([Ljava/lang/Object;)V
   115:	aload_0
   116:	invokeinterface	#59,  1; //InterfaceMethod scala/collection/immutable/VectorPointer.display2:()[Ljava/lang/Object;
   121:	iconst_0
   122:	aload_0
   123:	invokeinterface	#42,  1; //InterfaceMethod scala/collection/immutable/VectorPointer.display1:()[Ljava/lang/Object;
   128:	aastore
   129:	aload_0
   130:	aload_0
   131:	invokeinterface	#32,  1; //InterfaceMethod scala/collection/immutable/VectorPointer.depth:()I
   136:	iconst_1
   137:	iadd
   138:	invokeinterface	#49,  2; //InterfaceMethod scala/collection/immutable/VectorPointer.depth_$eq:(I)V
   143:	aload_0
   144:	ldc	#27; //int 32
   146:	anewarray	#34; //class java/lang/Object
   149:	invokeinterface	#52,  2; //InterfaceMethod scala/collection/immutable/VectorPointer.display0_$eq:([Ljava/lang/Object;)V
   154:	aload_0
   155:	ldc	#27; //int 32
   157:	anewarray	#34; //class java/lang/Object
   160:	invokeinterface	#38,  2; //InterfaceMethod scala/collection/immutable/VectorPointer.display1_$eq:([Ljava/lang/Object;)V
   165:	aload_0
   166:	invokeinterface	#42,  1; //InterfaceMethod scala/collection/immutable/VectorPointer.display1:()[Ljava/lang/Object;
   171:	iload_1
   172:	iconst_5
   173:	ishr
   174:	ldc	#43; //int 31
   176:	iand
   177:	aload_0
   178:	invokeinterface	#46,  1; //InterfaceMethod scala/collection/immutable/VectorPointer.display0:()[Ljava/lang/Object;
   183:	aastore
   184:	aload_0
   185:	invokeinterface	#59,  1; //InterfaceMethod scala/collection/immutable/VectorPointer.display2:()[Ljava/lang/Object;
   190:	iload_1
   191:	ldc	#60; //int 10
   193:	ishr
   194:	ldc	#43; //int 31
   196:	iand
   197:	aload_0
   198:	invokeinterface	#42,  1; //InterfaceMethod scala/collection/immutable/VectorPointer.display1:()[Ljava/lang/Object;
   203:	aastore
   204:	goto	747
   207:	iload_2
   208:	ldc	#63; //int 1048576
   210:	if_icmpge	357
   213:	aload_0
   214:	invokeinterface	#32,  1; //InterfaceMethod scala/collection/immutable/VectorPointer.depth:()I
   219:	iconst_3
   220:	if_icmpne	262
   223:	aload_0
   224:	ldc	#27; //int 32
   226:	anewarray	#34; //class java/lang/Object
   229:	invokeinterface	#66,  2; //InterfaceMethod scala/collection/immutable/VectorPointer.display3_$eq:([Ljava/lang/Object;)V
   234:	aload_0
   235:	invokeinterface	#69,  1; //InterfaceMethod scala/collection/immutable/VectorPointer.display3:()[Ljava/lang/Object;
   240:	iconst_0
   241:	aload_0
   242:	invokeinterface	#59,  1; //InterfaceMethod scala/collection/immutable/VectorPointer.display2:()[Ljava/lang/Object;
   247:	aastore
   248:	aload_0
   249:	aload_0
   250:	invokeinterface	#32,  1; //InterfaceMethod scala/collection/immutable/VectorPointer.depth:()I
   255:	iconst_1
   256:	iadd
   257:	invokeinterface	#49,  2; //InterfaceMethod scala/collection/immutable/VectorPointer.depth_$eq:(I)V
   262:	aload_0
   263:	ldc	#27; //int 32
   265:	anewarray	#34; //class java/lang/Object
   268:	invokeinterface	#52,  2; //InterfaceMethod scala/collection/immutable/VectorPointer.display0_$eq:([Ljava/lang/Object;)V
   273:	aload_0
   274:	ldc	#27; //int 32
   276:	anewarray	#34; //class java/lang/Object
   279:	invokeinterface	#38,  2; //InterfaceMethod scala/collection/immutable/VectorPointer.display1_$eq:([Ljava/lang/Object;)V
   284:	aload_0
   285:	ldc	#27; //int 32
   287:	anewarray	#34; //class java/lang/Object
   290:	invokeinterface	#56,  2; //InterfaceMethod scala/collection/immutable/VectorPointer.display2_$eq:([Ljava/lang/Object;)V
   295:	aload_0
   296:	invokeinterface	#42,  1; //InterfaceMethod scala/collection/immutable/VectorPointer.display1:()[Ljava/lang/Object;
   301:	iload_1
   302:	iconst_5
   303:	ishr
   304:	ldc	#43; //int 31
   306:	iand
   307:	aload_0
   308:	invokeinterface	#46,  1; //InterfaceMethod scala/collection/immutable/VectorPointer.display0:()[Ljava/lang/Object;
   313:	aastore
   314:	aload_0
   315:	invokeinterface	#59,  1; //InterfaceMethod scala/collection/immutable/VectorPointer.display2:()[Ljava/lang/Object;
   320:	iload_1
   321:	ldc	#60; //int 10
   323:	ishr
   324:	ldc	#43; //int 31
   326:	iand
   327:	aload_0
   328:	invokeinterface	#42,  1; //InterfaceMethod scala/collection/immutable/VectorPointer.display1:()[Ljava/lang/Object;
   333:	aastore
   334:	aload_0
   335:	invokeinterface	#69,  1; //InterfaceMethod scala/collection/immutable/VectorPointer.display3:()[Ljava/lang/Object;
   340:	iload_1
   341:	ldc	#70; //int 15
   343:	ishr
   344:	ldc	#43; //int 31
   346:	iand
   347:	aload_0
   348:	invokeinterface	#59,  1; //InterfaceMethod scala/collection/immutable/VectorPointer.display2:()[Ljava/lang/Object;
   353:	aastore
   354:	goto	747
   357:	iload_2
   358:	ldc	#71; //int 33554432
   360:	if_icmpge	538
   363:	aload_0
   364:	invokeinterface	#32,  1; //InterfaceMethod scala/collection/immutable/VectorPointer.depth:()I
   369:	iconst_4
   370:	if_icmpne	412
   373:	aload_0
   374:	ldc	#27; //int 32
   376:	anewarray	#34; //class java/lang/Object
   379:	invokeinterface	#74,  2; //InterfaceMethod scala/collection/immutable/VectorPointer.display4_$eq:([Ljava/lang/Object;)V
   384:	aload_0
   385:	invokeinterface	#77,  1; //InterfaceMethod scala/collection/immutable/VectorPointer.display4:()[Ljava/lang/Object;
   390:	iconst_0
   391:	aload_0
   392:	invokeinterface	#69,  1; //InterfaceMethod scala/collection/immutable/VectorPointer.display3:()[Ljava/lang/Object;
   397:	aastore
   398:	aload_0
   399:	aload_0
   400:	invokeinterface	#32,  1; //InterfaceMethod scala/collection/immutable/VectorPointer.depth:()I
   405:	iconst_1
   406:	iadd
   407:	invokeinterface	#49,  2; //InterfaceMethod scala/collection/immutable/VectorPointer.depth_$eq:(I)V
   412:	aload_0
   413:	ldc	#27; //int 32
   415:	anewarray	#34; //class java/lang/Object
   418:	invokeinterface	#52,  2; //InterfaceMethod scala/collection/immutable/VectorPointer.display0_$eq:([Ljava/lang/Object;)V
   423:	aload_0
   424:	ldc	#27; //int 32
   426:	anewarray	#34; //class java/lang/Object
   429:	invokeinterface	#38,  2; //InterfaceMethod scala/collection/immutable/VectorPointer.display1_$eq:([Ljava/lang/Object;)V
   434:	aload_0
   435:	ldc	#27; //int 32
   437:	anewarray	#34; //class java/lang/Object
   440:	invokeinterface	#56,  2; //InterfaceMethod scala/collection/immutable/VectorPointer.display2_$eq:([Ljava/lang/Object;)V
   445:	aload_0
   446:	ldc	#27; //int 32
   448:	anewarray	#34; //class java/lang/Object
   451:	invokeinterface	#66,  2; //InterfaceMethod scala/collection/immutable/VectorPointer.display3_$eq:([Ljava/lang/Object;)V
   456:	aload_0
   457:	invokeinterface	#42,  1; //InterfaceMethod scala/collection/immutable/VectorPointer.display1:()[Ljava/lang/Object;
   462:	iload_1
   463:	iconst_5
   464:	ishr
   465:	ldc	#43; //int 31
   467:	iand
   468:	aload_0
   469:	invokeinterface	#46,  1; //InterfaceMethod scala/collection/immutable/VectorPointer.display0:()[Ljava/lang/Object;
   474:	aastore
   475:	aload_0
   476:	invokeinterface	#59,  1; //InterfaceMethod scala/collection/immutable/VectorPointer.display2:()[Ljava/lang/Object;
   481:	iload_1
   482:	ldc	#60; //int 10
   484:	ishr
   485:	ldc	#43; //int 31
   487:	iand
   488:	aload_0
   489:	invokeinterface	#42,  1; //InterfaceMethod scala/collection/immutable/VectorPointer.display1:()[Ljava/lang/Object;
   494:	aastore
   495:	aload_0
   496:	invokeinterface	#69,  1; //InterfaceMethod scala/collection/immutable/VectorPointer.display3:()[Ljava/lang/Object;
   501:	iload_1
   502:	ldc	#70; //int 15
   504:	ishr
   505:	ldc	#43; //int 31
   507:	iand
   508:	aload_0
   509:	invokeinterface	#59,  1; //InterfaceMethod scala/collection/immutable/VectorPointer.display2:()[Ljava/lang/Object;
   514:	aastore
   515:	aload_0
   516:	invokeinterface	#77,  1; //InterfaceMethod scala/collection/immutable/VectorPointer.display4:()[Ljava/lang/Object;
   521:	iload_1
   522:	ldc	#78; //int 20
   524:	ishr
   525:	ldc	#43; //int 31
   527:	iand
   528:	aload_0
   529:	invokeinterface	#69,  1; //InterfaceMethod scala/collection/immutable/VectorPointer.display3:()[Ljava/lang/Object;
   534:	aastore
   535:	goto	747
   538:	iload_2
   539:	ldc	#79; //int 1073741824
   541:	if_icmpge	748
   544:	aload_0
   545:	invokeinterface	#32,  1; //InterfaceMethod scala/collection/immutable/VectorPointer.depth:()I
   550:	iconst_5
   551:	if_icmpne	593
   554:	aload_0
   555:	ldc	#27; //int 32
   557:	anewarray	#34; //class java/lang/Object
   560:	invokeinterface	#82,  2; //InterfaceMethod scala/collection/immutable/VectorPointer.display5_$eq:([Ljava/lang/Object;)V
   565:	aload_0
   566:	invokeinterface	#85,  1; //InterfaceMethod scala/collection/immutable/VectorPointer.display5:()[Ljava/lang/Object;
   571:	iconst_0
   572:	aload_0
   573:	invokeinterface	#77,  1; //InterfaceMethod scala/collection/immutable/VectorPointer.display4:()[Ljava/lang/Object;
   578:	aastore
   579:	aload_0
   580:	aload_0
   581:	invokeinterface	#32,  1; //InterfaceMethod scala/collection/immutable/VectorPointer.depth:()I
   586:	iconst_1
   587:	iadd
   588:	invokeinterface	#49,  2; //InterfaceMethod scala/collection/immutable/VectorPointer.depth_$eq:(I)V
   593:	aload_0
   594:	ldc	#27; //int 32
   596:	anewarray	#34; //class java/lang/Object
   599:	invokeinterface	#52,  2; //InterfaceMethod scala/collection/immutable/VectorPointer.display0_$eq:([Ljava/lang/Object;)V
   604:	aload_0
   605:	ldc	#27; //int 32
   607:	anewarray	#34; //class java/lang/Object
   610:	invokeinterface	#38,  2; //InterfaceMethod scala/collection/immutable/VectorPointer.display1_$eq:([Ljava/lang/Object;)V
   615:	aload_0
   616:	ldc	#27; //int 32
   618:	anewarray	#34; //class java/lang/Object
   621:	invokeinterface	#56,  2; //InterfaceMethod scala/collection/immutable/VectorPointer.display2_$eq:([Ljava/lang/Object;)V
   626:	aload_0
   627:	ldc	#27; //int 32
   629:	anewarray	#34; //class java/lang/Object
   632:	invokeinterface	#66,  2; //InterfaceMethod scala/collection/immutable/VectorPointer.display3_$eq:([Ljava/lang/Object;)V
   637:	aload_0
   638:	ldc	#27; //int 32
   640:	anewarray	#34; //class java/lang/Object
   643:	invokeinterface	#74,  2; //InterfaceMethod scala/collection/immutable/VectorPointer.display4_$eq:([Ljava/lang/Object;)V
   648:	aload_0
   649:	invokeinterface	#42,  1; //InterfaceMethod scala/collection/immutable/VectorPointer.display1:()[Ljava/lang/Object;
   654:	iload_1
   655:	iconst_5
   656:	ishr
   657:	ldc	#43; //int 31
   659:	iand
   660:	aload_0
   661:	invokeinterface	#46,  1; //InterfaceMethod scala/collection/immutable/VectorPointer.display0:()[Ljava/lang/Object;
   666:	aastore
   667:	aload_0
   668:	invokeinterface	#59,  1; //InterfaceMethod scala/collection/immutable/VectorPointer.display2:()[Ljava/lang/Object;
   673:	iload_1
   674:	ldc	#60; //int 10
   676:	ishr
   677:	ldc	#43; //int 31
   679:	iand
   680:	aload_0
   681:	invokeinterface	#42,  1; //InterfaceMethod scala/collection/immutable/VectorPointer.display1:()[Ljava/lang/Object;
   686:	aastore
   687:	aload_0
   688:	invokeinterface	#69,  1; //InterfaceMethod scala/collection/immutable/VectorPointer.display3:()[Ljava/lang/Object;
   693:	iload_1
   694:	ldc	#70; //int 15
   696:	ishr
   697:	ldc	#43; //int 31
   699:	iand
   700:	aload_0
   701:	invokeinterface	#59,  1; //InterfaceMethod scala/collection/immutable/VectorPointer.display2:()[Ljava/lang/Object;
   706:	aastore
   707:	aload_0
   708:	invokeinterface	#77,  1; //InterfaceMethod scala/collection/immutable/VectorPointer.display4:()[Ljava/lang/Object;
   713:	iload_1
   714:	ldc	#78; //int 20
   716:	ishr
   717:	ldc	#43; //int 31
   719:	iand
   720:	aload_0
   721:	invokeinterface	#69,  1; //InterfaceMethod scala/collection/immutable/VectorPointer.display3:()[Ljava/lang/Object;
   726:	aastore
   727:	aload_0
   728:	invokeinterface	#85,  1; //InterfaceMethod scala/collection/immutable/VectorPointer.display5:()[Ljava/lang/Object;
   733:	iload_1
   734:	ldc	#86; //int 25
   736:	ishr
   737:	ldc	#43; //int 31
   739:	iand
   740:	aload_0
   741:	invokeinterface	#77,  1; //InterfaceMethod scala/collection/immutable/VectorPointer.display4:()[Ljava/lang/Object;
   746:	aastore
   747:	return
   748:	new	#88; //class java/lang/IllegalArgumentException
   751:	dup
   752:	invokespecial	#92; //Method java/lang/IllegalArgumentException."<init>":()V
   755:	athrow
  LineNumberTable: 
   line 791: 0
   line 792: 6
   line 793: 55
   line 794: 66
   line 796: 88
   line 797: 94
   line 798: 143
   line 799: 154
   line 800: 165
   line 801: 184
   line 803: 207
   line 804: 213
   line 805: 262
   line 806: 273
   line 807: 284
   line 808: 295
   line 809: 314
   line 810: 334
   line 812: 357
   line 813: 363
   line 814: 412
   line 815: 423
   line 816: 434
   line 817: 445
   line 818: 456
   line 819: 475
   line 820: 495
   line 821: 515
   line 823: 538
   line 824: 544
   line 825: 593
   line 826: 604
   line 827: 615
   line 828: 626
   line 829: 637
   line 830: 648
   line 831: 667
   line 832: 687
   line 833: 707
   line 834: 727
   line 791: 747
   line 836: 748

  LocalVariableTable: 
   Start  Length  Slot  Name   Signature
   0      756      0    $this       Lscala/collection/immutable/VectorPointer;
   0      756      1    index       I
   0      756      2    xor       I


public static final void gotoNextBlockStart(scala.collection.immutable.VectorPointer, int, int);
  Code:
   Stack=4, Locals=3, Args_size=3
   0:	iload_2
   1:	ldc	#28; //int 1024
   3:	if_icmpge	31
   6:	aload_0
   7:	aload_0
   8:	invokeinterface	#42,  1; //InterfaceMethod scala/collection/immutable/VectorPointer.display1:()[Ljava/lang/Object;
   13:	iload_1
   14:	iconst_5
   15:	ishr
   16:	ldc	#43; //int 31
   18:	iand
   19:	aaload
   20:	checkcast	#62; //class "[Ljava/lang/Object;"
   23:	invokeinterface	#52,  2; //InterfaceMethod scala/collection/immutable/VectorPointer.display0_$eq:([Ljava/lang/Object;)V
   28:	goto	326
   31:	iload_2
   32:	ldc	#53; //int 32768
   34:	if_icmpge	80
   37:	aload_0
   38:	aload_0
   39:	invokeinterface	#59,  1; //InterfaceMethod scala/collection/immutable/VectorPointer.display2:()[Ljava/lang/Object;
   44:	iload_1
   45:	ldc	#60; //int 10
   47:	ishr
   48:	ldc	#43; //int 31
   50:	iand
   51:	aaload
   52:	checkcast	#62; //class "[Ljava/lang/Object;"
   55:	invokeinterface	#38,  2; //InterfaceMethod scala/collection/immutable/VectorPointer.display1_$eq:([Ljava/lang/Object;)V
   60:	aload_0
   61:	aload_0
   62:	invokeinterface	#42,  1; //InterfaceMethod scala/collection/immutable/VectorPointer.display1:()[Ljava/lang/Object;
   67:	iconst_0
   68:	aaload
   69:	checkcast	#62; //class "[Ljava/lang/Object;"
   72:	invokeinterface	#52,  2; //InterfaceMethod scala/collection/immutable/VectorPointer.display0_$eq:([Ljava/lang/Object;)V
   77:	goto	326
   80:	iload_2
   81:	ldc	#63; //int 1048576
   83:	if_icmpge	146
   86:	aload_0
   87:	aload_0
   88:	invokeinterface	#69,  1; //InterfaceMethod scala/collection/immutable/VectorPointer.display3:()[Ljava/lang/Object;
   93:	iload_1
   94:	ldc	#70; //int 15
   96:	ishr
   97:	ldc	#43; //int 31
   99:	iand
   100:	aaload
   101:	checkcast	#62; //class "[Ljava/lang/Object;"
   104:	invokeinterface	#56,  2; //InterfaceMethod scala/collection/immutable/VectorPointer.display2_$eq:([Ljava/lang/Object;)V
   109:	aload_0
   110:	aload_0
   111:	invokeinterface	#59,  1; //InterfaceMethod scala/collection/immutable/VectorPointer.display2:()[Ljava/lang/Object;
   116:	iconst_0
   117:	aaload
   118:	checkcast	#62; //class "[Ljava/lang/Object;"
   121:	invokeinterface	#38,  2; //InterfaceMethod scala/collection/immutable/VectorPointer.display1_$eq:([Ljava/lang/Object;)V
   126:	aload_0
   127:	aload_0
   128:	invokeinterface	#42,  1; //InterfaceMethod scala/collection/immutable/VectorPointer.display1:()[Ljava/lang/Object;
   133:	iconst_0
   134:	aaload
   135:	checkcast	#62; //class "[Ljava/lang/Object;"
   138:	invokeinterface	#52,  2; //InterfaceMethod scala/collection/immutable/VectorPointer.display0_$eq:([Ljava/lang/Object;)V
   143:	goto	326
   146:	iload_2
   147:	ldc	#71; //int 33554432
   149:	if_icmpge	229
   152:	aload_0
   153:	aload_0
   154:	invokeinterface	#77,  1; //InterfaceMethod scala/collection/immutable/VectorPointer.display4:()[Ljava/lang/Object;
   159:	iload_1
   160:	ldc	#78; //int 20
   162:	ishr
   163:	ldc	#43; //int 31
   165:	iand
   166:	aaload
   167:	checkcast	#62; //class "[Ljava/lang/Object;"
   170:	invokeinterface	#66,  2; //InterfaceMethod scala/collection/immutable/VectorPointer.display3_$eq:([Ljava/lang/Object;)V
   175:	aload_0
   176:	aload_0
   177:	invokeinterface	#69,  1; //InterfaceMethod scala/collection/immutable/VectorPointer.display3:()[Ljava/lang/Object;
   182:	iconst_0
   183:	aaload
   184:	checkcast	#62; //class "[Ljava/lang/Object;"
   187:	invokeinterface	#56,  2; //InterfaceMethod scala/collection/immutable/VectorPointer.display2_$eq:([Ljava/lang/Object;)V
   192:	aload_0
   193:	aload_0
   194:	invokeinterface	#59,  1; //InterfaceMethod scala/collection/immutable/VectorPointer.display2:()[Ljava/lang/Object;
   199:	iconst_0
   200:	aaload
   201:	checkcast	#62; //class "[Ljava/lang/Object;"
   204:	invokeinterface	#38,  2; //InterfaceMethod scala/collection/immutable/VectorPointer.display1_$eq:([Ljava/lang/Object;)V
   209:	aload_0
   210:	aload_0
   211:	invokeinterface	#42,  1; //InterfaceMethod scala/collection/immutable/VectorPointer.display1:()[Ljava/lang/Object;
   216:	iconst_0
   217:	aaload
   218:	checkcast	#62; //class "[Ljava/lang/Object;"
   221:	invokeinterface	#52,  2; //InterfaceMethod scala/collection/immutable/VectorPointer.display0_$eq:([Ljava/lang/Object;)V
   226:	goto	326
   229:	iload_2
   230:	ldc	#79; //int 1073741824
   232:	if_icmpge	327
   235:	aload_0
   236:	aload_0
   237:	invokeinterface	#85,  1; //InterfaceMethod scala/collection/immutable/VectorPointer.display5:()[Ljava/lang/Object;
   242:	iload_1
   243:	ldc	#86; //int 25
   245:	ishr
   246:	ldc	#43; //int 31
   248:	iand
   249:	aaload
   250:	checkcast	#62; //class "[Ljava/lang/Object;"
   253:	invokeinterface	#74,  2; //InterfaceMethod scala/collection/immutable/VectorPointer.display4_$eq:([Ljava/lang/Object;)V
   258:	aload_0
   259:	aload_0
   260:	invokeinterface	#77,  1; //InterfaceMethod scala/collection/immutable/VectorPointer.display4:()[Ljava/lang/Object;
   265:	iconst_0
   266:	aaload
   267:	checkcast	#62; //class "[Ljava/lang/Object;"
   270:	invokeinterface	#66,  2; //InterfaceMethod scala/collection/immutable/VectorPointer.display3_$eq:([Ljava/lang/Object;)V
   275:	aload_0
   276:	aload_0
   277:	invokeinterface	#69,  1; //InterfaceMethod scala/collection/immutable/VectorPointer.display3:()[Ljava/lang/Object;
   282:	iconst_0
   283:	aaload
   284:	checkcast	#62; //class "[Ljava/lang/Object;"
   287:	invokeinterface	#56,  2; //InterfaceMethod scala/collection/immutable/VectorPointer.display2_$eq:([Ljava/lang/Object;)V
   292:	aload_0
   293:	aload_0
   294:	invokeinterface	#59,  1; //InterfaceMethod scala/collection/immutable/VectorPointer.display2:()[Ljava/lang/Object;
   299:	iconst_0
   300:	aaload
   301:	checkcast	#62; //class "[Ljava/lang/Object;"
   304:	invokeinterface	#38,  2; //InterfaceMethod scala/collection/immutable/VectorPointer.display1_$eq:([Ljava/lang/Object;)V
   309:	aload_0
   310:	aload_0
   311:	invokeinterface	#42,  1; //InterfaceMethod scala/collection/immutable/VectorPointer.display1:()[Ljava/lang/Object;
   316:	iconst_0
   317:	aaload
   318:	checkcast	#62; //class "[Ljava/lang/Object;"
   321:	invokeinterface	#52,  2; //InterfaceMethod scala/collection/immutable/VectorPointer.display0_$eq:([Ljava/lang/Object;)V
   326:	return
   327:	new	#88; //class java/lang/IllegalArgumentException
   330:	dup
   331:	invokespecial	#92; //Method java/lang/IllegalArgumentException."<init>":()V
   334:	athrow
  LineNumberTable: 
   line 758: 0
   line 759: 6
   line 761: 31
   line 762: 37
   line 763: 60
   line 765: 80
   line 766: 86
   line 767: 109
   line 768: 126
   line 770: 146
   line 771: 152
   line 772: 175
   line 773: 192
   line 774: 209
   line 776: 229
   line 777: 235
   line 778: 258
   line 779: 275
   line 780: 292
   line 781: 309
   line 758: 326
   line 783: 327

  LocalVariableTable: 
   Start  Length  Slot  Name   Signature
   0      335      0    $this       Lscala/collection/immutable/VectorPointer;
   0      335      1    index       I
   0      335      2    xor       I


public static final void gotoPos(scala.collection.immutable.VectorPointer, int, int);
  Code:
   Stack=4, Locals=3, Args_size=3
   0:	iload_2
   1:	ldc	#27; //int 32
   3:	if_icmplt	388
   6:	iload_2
   7:	ldc	#28; //int 1024
   9:	if_icmpge	37
   12:	aload_0
   13:	aload_0
   14:	invokeinterface	#42,  1; //InterfaceMethod scala/collection/immutable/VectorPointer.display1:()[Ljava/lang/Object;
   19:	iload_1
   20:	iconst_5
   21:	ishr
   22:	ldc	#43; //int 31
   24:	iand
   25:	aaload
   26:	checkcast	#62; //class "[Ljava/lang/Object;"
   29:	invokeinterface	#52,  2; //InterfaceMethod scala/collection/immutable/VectorPointer.display0_$eq:([Ljava/lang/Object;)V
   34:	goto	388
   37:	iload_2
   38:	ldc	#53; //int 32768
   40:	if_icmpge	91
   43:	aload_0
   44:	aload_0
   45:	invokeinterface	#59,  1; //InterfaceMethod scala/collection/immutable/VectorPointer.display2:()[Ljava/lang/Object;
   50:	iload_1
   51:	ldc	#60; //int 10
   53:	ishr
   54:	ldc	#43; //int 31
   56:	iand
   57:	aaload
   58:	checkcast	#62; //class "[Ljava/lang/Object;"
   61:	invokeinterface	#38,  2; //InterfaceMethod scala/collection/immutable/VectorPointer.display1_$eq:([Ljava/lang/Object;)V
   66:	aload_0
   67:	aload_0
   68:	invokeinterface	#42,  1; //InterfaceMethod scala/collection/immutable/VectorPointer.display1:()[Ljava/lang/Object;
   73:	iload_1
   74:	iconst_5
   75:	ishr
   76:	ldc	#43; //int 31
   78:	iand
   79:	aaload
   80:	checkcast	#62; //class "[Ljava/lang/Object;"
   83:	invokeinterface	#52,  2; //InterfaceMethod scala/collection/immutable/VectorPointer.display0_$eq:([Ljava/lang/Object;)V
   88:	goto	388
   91:	iload_2
   92:	ldc	#63; //int 1048576
   94:	if_icmpge	168
   97:	aload_0
   98:	aload_0
   99:	invokeinterface	#69,  1; //InterfaceMethod scala/collection/immutable/VectorPointer.display3:()[Ljava/lang/Object;
   104:	iload_1
   105:	ldc	#70; //int 15
   107:	ishr
   108:	ldc	#43; //int 31
   110:	iand
   111:	aaload
   112:	checkcast	#62; //class "[Ljava/lang/Object;"
   115:	invokeinterface	#56,  2; //InterfaceMethod scala/collection/immutable/VectorPointer.display2_$eq:([Ljava/lang/Object;)V
   120:	aload_0
   121:	aload_0
   122:	invokeinterface	#59,  1; //InterfaceMethod scala/collection/immutable/VectorPointer.display2:()[Ljava/lang/Object;
   127:	iload_1
   128:	ldc	#60; //int 10
   130:	ishr
   131:	ldc	#43; //int 31
   133:	iand
   134:	aaload
   135:	checkcast	#62; //class "[Ljava/lang/Object;"
   138:	invokeinterface	#38,  2; //InterfaceMethod scala/collection/immutable/VectorPointer.display1_$eq:([Ljava/lang/Object;)V
   143:	aload_0
   144:	aload_0
   145:	invokeinterface	#42,  1; //InterfaceMethod scala/collection/immutable/VectorPointer.display1:()[Ljava/lang/Object;
   150:	iload_1
   151:	iconst_5
   152:	ishr
   153:	ldc	#43; //int 31
   155:	iand
   156:	aaload
   157:	checkcast	#62; //class "[Ljava/lang/Object;"
   160:	invokeinterface	#52,  2; //InterfaceMethod scala/collection/immutable/VectorPointer.display0_$eq:([Ljava/lang/Object;)V
   165:	goto	388
   168:	iload_2
   169:	ldc	#71; //int 33554432
   171:	if_icmpge	268
   174:	aload_0
   175:	aload_0
   176:	invokeinterface	#77,  1; //InterfaceMethod scala/collection/immutable/VectorPointer.display4:()[Ljava/lang/Object;
   181:	iload_1
   182:	ldc	#78; //int 20
   184:	ishr
   185:	ldc	#43; //int 31
   187:	iand
   188:	aaload
   189:	checkcast	#62; //class "[Ljava/lang/Object;"
   192:	invokeinterface	#66,  2; //InterfaceMethod scala/collection/immutable/VectorPointer.display3_$eq:([Ljava/lang/Object;)V
   197:	aload_0
   198:	aload_0
   199:	invokeinterface	#69,  1; //InterfaceMethod scala/collection/immutable/VectorPointer.display3:()[Ljava/lang/Object;
   204:	iload_1
   205:	ldc	#70; //int 15
   207:	ishr
   208:	ldc	#43; //int 31
   210:	iand
   211:	aaload
   212:	checkcast	#62; //class "[Ljava/lang/Object;"
   215:	invokeinterface	#56,  2; //InterfaceMethod scala/collection/immutable/VectorPointer.display2_$eq:([Ljava/lang/Object;)V
   220:	aload_0
   221:	aload_0
   222:	invokeinterface	#59,  1; //InterfaceMethod scala/collection/immutable/VectorPointer.display2:()[Ljava/lang/Object;
   227:	iload_1
   228:	ldc	#60; //int 10
   230:	ishr
   231:	ldc	#43; //int 31
   233:	iand
   234:	aaload
   235:	checkcast	#62; //class "[Ljava/lang/Object;"
   238:	invokeinterface	#38,  2; //InterfaceMethod scala/collection/immutable/VectorPointer.display1_$eq:([Ljava/lang/Object;)V
   243:	aload_0
   244:	aload_0
   245:	invokeinterface	#42,  1; //InterfaceMethod scala/collection/immutable/VectorPointer.display1:()[Ljava/lang/Object;
   250:	iload_1
   251:	iconst_5
   252:	ishr
   253:	ldc	#43; //int 31
   255:	iand
   256:	aaload
   257:	checkcast	#62; //class "[Ljava/lang/Object;"
   260:	invokeinterface	#52,  2; //InterfaceMethod scala/collection/immutable/VectorPointer.display0_$eq:([Ljava/lang/Object;)V
   265:	goto	388
   268:	iload_2
   269:	ldc	#79; //int 1073741824
   271:	if_icmpge	389
   274:	aload_0
   275:	aload_0
   276:	invokeinterface	#85,  1; //InterfaceMethod scala/collection/immutable/VectorPointer.display5:()[Ljava/lang/Object;
   281:	iload_1
   282:	ldc	#86; //int 25
   284:	ishr
   285:	ldc	#43; //int 31
   287:	iand
   288:	aaload
   289:	checkcast	#62; //class "[Ljava/lang/Object;"
   292:	invokeinterface	#74,  2; //InterfaceMethod scala/collection/immutable/VectorPointer.display4_$eq:([Ljava/lang/Object;)V
   297:	aload_0
   298:	aload_0
   299:	invokeinterface	#77,  1; //InterfaceMethod scala/collection/immutable/VectorPointer.display4:()[Ljava/lang/Object;
   304:	iload_1
   305:	ldc	#78; //int 20
   307:	ishr
   308:	ldc	#43; //int 31
   310:	iand
   311:	aaload
   312:	checkcast	#62; //class "[Ljava/lang/Object;"
   315:	invokeinterface	#66,  2; //InterfaceMethod scala/collection/immutable/VectorPointer.display3_$eq:([Ljava/lang/Object;)V
   320:	aload_0
   321:	aload_0
   322:	invokeinterface	#69,  1; //InterfaceMethod scala/collection/immutable/VectorPointer.display3:()[Ljava/lang/Object;
   327:	iload_1
   328:	ldc	#70; //int 15
   330:	ishr
   331:	ldc	#43; //int 31
   333:	iand
   334:	aaload
   335:	checkcast	#62; //class "[Ljava/lang/Object;"
   338:	invokeinterface	#56,  2; //InterfaceMethod scala/collection/immutable/VectorPointer.display2_$eq:([Ljava/lang/Object;)V
   343:	aload_0
   344:	aload_0
   345:	invokeinterface	#59,  1; //InterfaceMethod scala/collection/immutable/VectorPointer.display2:()[Ljava/lang/Object;
   350:	iload_1
   351:	ldc	#60; //int 10
   353:	ishr
   354:	ldc	#43; //int 31
   356:	iand
   357:	aaload
   358:	checkcast	#62; //class "[Ljava/lang/Object;"
   361:	invokeinterface	#38,  2; //InterfaceMethod scala/collection/immutable/VectorPointer.display1_$eq:([Ljava/lang/Object;)V
   366:	aload_0
   367:	aload_0
   368:	invokeinterface	#42,  1; //InterfaceMethod scala/collection/immutable/VectorPointer.display1:()[Ljava/lang/Object;
   373:	iload_1
   374:	iconst_5
   375:	ishr
   376:	ldc	#43; //int 31
   378:	iand
   379:	aaload
   380:	checkcast	#62; //class "[Ljava/lang/Object;"
   383:	invokeinterface	#52,  2; //InterfaceMethod scala/collection/immutable/VectorPointer.display0_$eq:([Ljava/lang/Object;)V
   388:	return
   389:	new	#88; //class java/lang/IllegalArgumentException
   392:	dup
   393:	invokespecial	#92; //Method java/lang/IllegalArgumentException."<init>":()V
   396:	athrow
  LineNumberTable: 
   line 721: 0
   line 723: 6
   line 724: 12
   line 726: 37
   line 727: 43
   line 728: 66
   line 730: 91
   line 731: 97
   line 732: 120
   line 733: 143
   line 735: 168
   line 736: 174
   line 737: 197
   line 738: 220
   line 739: 243
   line 741: 268
   line 742: 274
   line 743: 297
   line 744: 320
   line 745: 343
   line 746: 366
   line 721: 388
   line 748: 389

  LocalVariableTable: 
   Start  Length  Slot  Name   Signature
   0      397      0    $this       Lscala/collection/immutable/VectorPointer;
   0      397      1    index       I
   0      397      2    xor       I


public static final java.lang.Object getElem(scala.collection.immutable.VectorPointer, int, int);
  Code:
   Stack=3, Locals=3, Args_size=3
   0:	iload_2
   1:	ldc	#27; //int 32
   3:	if_icmpge	20
   6:	aload_0
   7:	invokeinterface	#46,  1; //InterfaceMethod scala/collection/immutable/VectorPointer.display0:()[Ljava/lang/Object;
   12:	iload_1
   13:	ldc	#43; //int 31
   15:	iand
   16:	aaload
   17:	goto	277
   20:	iload_2
   21:	ldc	#28; //int 1024
   23:	if_icmpge	50
   26:	aload_0
   27:	invokeinterface	#42,  1; //InterfaceMethod scala/collection/immutable/VectorPointer.display1:()[Ljava/lang/Object;
   32:	iload_1
   33:	iconst_5
   34:	ishr
   35:	ldc	#43; //int 31
   37:	iand
   38:	aaload
   39:	checkcast	#62; //class "[Ljava/lang/Object;"
   42:	iload_1
   43:	ldc	#43; //int 31
   45:	iand
   46:	aaload
   47:	goto	277
   50:	iload_2
   51:	ldc	#53; //int 32768
   53:	if_icmpge	91
   56:	aload_0
   57:	invokeinterface	#59,  1; //InterfaceMethod scala/collection/immutable/VectorPointer.display2:()[Ljava/lang/Object;
   62:	iload_1
   63:	ldc	#60; //int 10
   65:	ishr
   66:	ldc	#43; //int 31
   68:	iand
   69:	aaload
   70:	checkcast	#62; //class "[Ljava/lang/Object;"
   73:	iload_1
   74:	iconst_5
   75:	ishr
   76:	ldc	#43; //int 31
   78:	iand
   79:	aaload
   80:	checkcast	#62; //class "[Ljava/lang/Object;"
   83:	iload_1
   84:	ldc	#43; //int 31
   86:	iand
   87:	aaload
   88:	goto	277
   91:	iload_2
   92:	ldc	#63; //int 1048576
   94:	if_icmpge	143
   97:	aload_0
   98:	invokeinterface	#69,  1; //InterfaceMethod scala/collection/immutable/VectorPointer.display3:()[Ljava/lang/Object;
   103:	iload_1
   104:	ldc	#70; //int 15
   106:	ishr
   107:	ldc	#43; //int 31
   109:	iand
   110:	aaload
   111:	checkcast	#62; //class "[Ljava/lang/Object;"
   114:	iload_1
   115:	ldc	#60; //int 10
   117:	ishr
   118:	ldc	#43; //int 31
   120:	iand
   121:	aaload
   122:	checkcast	#62; //class "[Ljava/lang/Object;"
   125:	iload_1
   126:	iconst_5
   127:	ishr
   128:	ldc	#43; //int 31
   130:	iand
   131:	aaload
   132:	checkcast	#62; //class "[Ljava/lang/Object;"
   135:	iload_1
   136:	ldc	#43; //int 31
   138:	iand
   139:	aaload
   140:	goto	277
   143:	iload_2
   144:	ldc	#71; //int 33554432
   146:	if_icmpge	206
   149:	aload_0
   150:	invokeinterface	#77,  1; //InterfaceMethod scala/collection/immutable/VectorPointer.display4:()[Ljava/lang/Object;
   155:	iload_1
   156:	ldc	#78; //int 20
   158:	ishr
   159:	ldc	#43; //int 31
   161:	iand
   162:	aaload
   163:	checkcast	#62; //class "[Ljava/lang/Object;"
   166:	iload_1
   167:	ldc	#70; //int 15
   169:	ishr
   170:	ldc	#43; //int 31
   172:	iand
   173:	aaload
   174:	checkcast	#62; //class "[Ljava/lang/Object;"
   177:	iload_1
   178:	ldc	#60; //int 10
   180:	ishr
   181:	ldc	#43; //int 31
   183:	iand
   184:	aaload
   185:	checkcast	#62; //class "[Ljava/lang/Object;"
   188:	iload_1
   189:	iconst_5
   190:	ishr
   191:	ldc	#43; //int 31
   193:	iand
   194:	aaload
   195:	checkcast	#62; //class "[Ljava/lang/Object;"
   198:	iload_1
   199:	ldc	#43; //int 31
   201:	iand
   202:	aaload
   203:	goto	277
   206:	iload_2
   207:	ldc	#79; //int 1073741824
   209:	if_icmpge	278
   212:	aload_0
   213:	invokeinterface	#85,  1; //InterfaceMethod scala/collection/immutable/VectorPointer.display5:()[Ljava/lang/Object;
   218:	iload_1
   219:	ldc	#86; //int 25
   221:	ishr
   222:	ldc	#43; //int 31
   224:	iand
   225:	aaload
   226:	checkcast	#62; //class "[Ljava/lang/Object;"
   229:	iload_1
   230:	ldc	#78; //int 20
   232:	ishr
   233:	ldc	#43; //int 31
   235:	iand
   236:	aaload
   237:	checkcast	#62; //class "[Ljava/lang/Object;"
   240:	iload_1
   241:	ldc	#70; //int 15
   243:	ishr
   244:	ldc	#43; //int 31
   246:	iand
   247:	aaload
   248:	checkcast	#62; //class "[Ljava/lang/Object;"
   251:	iload_1
   252:	ldc	#60; //int 10
   254:	ishr
   255:	ldc	#43; //int 31
   257:	iand
   258:	aaload
   259:	checkcast	#62; //class "[Ljava/lang/Object;"
   262:	iload_1
   263:	iconst_5
   264:	ishr
   265:	ldc	#43; //int 31
   267:	iand
   268:	aaload
   269:	checkcast	#62; //class "[Ljava/lang/Object;"
   272:	iload_1
   273:	ldc	#43; //int 31
   275:	iand
   276:	aaload
   277:	areturn
   278:	new	#88; //class java/lang/IllegalArgumentException
   281:	dup
   282:	invokespecial	#92; //Method java/lang/IllegalArgumentException."<init>":()V
   285:	athrow
  LineNumberTable: 
   line 694: 0
   line 695: 6
   line 697: 20
   line 698: 26
   line 700: 50
   line 701: 56
   line 703: 91
   line 704: 97
   line 706: 143
   line 707: 149
   line 709: 206
   line 710: 212
   line 694: 277
   line 712: 278

  LocalVariableTable: 
   Start  Length  Slot  Name   Signature
   0      286      0    $this       Lscala/collection/immutable/VectorPointer;
   0      286      1    index       I
   0      286      2    xor       I


public static final void initFrom(scala.collection.immutable.VectorPointer, scala.collection.immutable.VectorPointer, int);
  Code:
   Stack=3, Locals=4, Args_size=3
   0:	aload_0
   1:	iload_2
   2:	invokeinterface	#49,  2; //InterfaceMethod scala/collection/immutable/VectorPointer.depth_$eq:(I)V
   7:	iload_2
   8:	iconst_1
   9:	isub
   10:	istore_3
   11:	iload_3
   12:	tableswitch{ //-1 to 5
		-1: 71;
		0: 440;
		1: 394;
		2: 336;
		3: 266;
		4: 184;
		5: 90;
		default: 56 }
   56:	new	#123; //class scala/MatchError
   59:	dup
   60:	iload_3
   61:	invokestatic	#129; //Method scala/runtime/BoxesRunTime.boxToInteger:(I)Ljava/lang/Integer;
   64:	invokevirtual	#133; //Method java/lang/Object.toString:()Ljava/lang/String;
   67:	invokespecial	#136; //Method scala/MatchError."<init>":(Ljava/lang/String;)V
   70:	athrow
   71:	iconst_1
   72:	ifne	456
   75:	new	#123; //class scala/MatchError
   78:	dup
   79:	iload_3
   80:	invokestatic	#129; //Method scala/runtime/BoxesRunTime.boxToInteger:(I)Ljava/lang/Integer;
   83:	invokevirtual	#133; //Method java/lang/Object.toString:()Ljava/lang/String;
   86:	invokespecial	#136; //Method scala/MatchError."<init>":(Ljava/lang/String;)V
   89:	athrow
   90:	iconst_1
   91:	ifeq	169
   94:	aload_0
   95:	aload_1
   96:	invokeinterface	#85,  1; //InterfaceMethod scala/collection/immutable/VectorPointer.display5:()[Ljava/lang/Object;
   101:	invokeinterface	#82,  2; //InterfaceMethod scala/collection/immutable/VectorPointer.display5_$eq:([Ljava/lang/Object;)V
   106:	aload_0
   107:	aload_1
   108:	invokeinterface	#77,  1; //InterfaceMethod scala/collection/immutable/VectorPointer.display4:()[Ljava/lang/Object;
   113:	invokeinterface	#74,  2; //InterfaceMethod scala/collection/immutable/VectorPointer.display4_$eq:([Ljava/lang/Object;)V
   118:	aload_0
   119:	aload_1
   120:	invokeinterface	#69,  1; //InterfaceMethod scala/collection/immutable/VectorPointer.display3:()[Ljava/lang/Object;
   125:	invokeinterface	#66,  2; //InterfaceMethod scala/collection/immutable/VectorPointer.display3_$eq:([Ljava/lang/Object;)V
   130:	aload_0
   131:	aload_1
   132:	invokeinterface	#59,  1; //InterfaceMethod scala/collection/immutable/VectorPointer.display2:()[Ljava/lang/Object;
   137:	invokeinterface	#56,  2; //InterfaceMethod scala/collection/immutable/VectorPointer.display2_$eq:([Ljava/lang/Object;)V
   142:	aload_0
   143:	aload_1
   144:	invokeinterface	#42,  1; //InterfaceMethod scala/collection/immutable/VectorPointer.display1:()[Ljava/lang/Object;
   149:	invokeinterface	#38,  2; //InterfaceMethod scala/collection/immutable/VectorPointer.display1_$eq:([Ljava/lang/Object;)V
   154:	aload_0
   155:	aload_1
   156:	invokeinterface	#46,  1; //InterfaceMethod scala/collection/immutable/VectorPointer.display0:()[Ljava/lang/Object;
   161:	invokeinterface	#52,  2; //InterfaceMethod scala/collection/immutable/VectorPointer.display0_$eq:([Ljava/lang/Object;)V
   166:	goto	456
   169:	new	#123; //class scala/MatchError
   172:	dup
   173:	iload_3
   174:	invokestatic	#129; //Method scala/runtime/BoxesRunTime.boxToInteger:(I)Ljava/lang/Integer;
   177:	invokevirtual	#133; //Method java/lang/Object.toString:()Ljava/lang/String;
   180:	invokespecial	#136; //Method scala/MatchError."<init>":(Ljava/lang/String;)V
   183:	athrow
   184:	iconst_1
   185:	ifeq	251
   188:	aload_0
   189:	aload_1
   190:	invokeinterface	#77,  1; //InterfaceMethod scala/collection/immutable/VectorPointer.display4:()[Ljava/lang/Object;
   195:	invokeinterface	#74,  2; //InterfaceMethod scala/collection/immutable/VectorPointer.display4_$eq:([Ljava/lang/Object;)V
   200:	aload_0
   201:	aload_1
   202:	invokeinterface	#69,  1; //InterfaceMethod scala/collection/immutable/VectorPointer.display3:()[Ljava/lang/Object;
   207:	invokeinterface	#66,  2; //InterfaceMethod scala/collection/immutable/VectorPointer.display3_$eq:([Ljava/lang/Object;)V
   212:	aload_0
   213:	aload_1
   214:	invokeinterface	#59,  1; //InterfaceMethod scala/collection/immutable/VectorPointer.display2:()[Ljava/lang/Object;
   219:	invokeinterface	#56,  2; //InterfaceMethod scala/collection/immutable/VectorPointer.display2_$eq:([Ljava/lang/Object;)V
   224:	aload_0
   225:	aload_1
   226:	invokeinterface	#42,  1; //InterfaceMethod scala/collection/immutable/VectorPointer.display1:()[Ljava/lang/Object;
   231:	invokeinterface	#38,  2; //InterfaceMethod scala/collection/immutable/VectorPointer.display1_$eq:([Ljava/lang/Object;)V
   236:	aload_0
   237:	aload_1
   238:	invokeinterface	#46,  1; //InterfaceMethod scala/collection/immutable/VectorPointer.display0:()[Ljava/lang/Object;
   243:	invokeinterface	#52,  2; //InterfaceMethod scala/collection/immutable/VectorPointer.display0_$eq:([Ljava/lang/Object;)V
   248:	goto	456
   251:	new	#123; //class scala/MatchError
   254:	dup
   255:	iload_3
   256:	invokestatic	#129; //Method scala/runtime/BoxesRunTime.boxToInteger:(I)Ljava/lang/Integer;
   259:	invokevirtual	#133; //Method java/lang/Object.toString:()Ljava/lang/String;
   262:	invokespecial	#136; //Method scala/MatchError."<init>":(Ljava/lang/String;)V
   265:	athrow
   266:	iconst_1
   267:	ifeq	321
   270:	aload_0
   271:	aload_1
   272:	invokeinterface	#69,  1; //InterfaceMethod scala/collection/immutable/VectorPointer.display3:()[Ljava/lang/Object;
   277:	invokeinterface	#66,  2; //InterfaceMethod scala/collection/immutable/VectorPointer.display3_$eq:([Ljava/lang/Object;)V
   282:	aload_0
   283:	aload_1
   284:	invokeinterface	#59,  1; //InterfaceMethod scala/collection/immutable/VectorPointer.display2:()[Ljava/lang/Object;
   289:	invokeinterface	#56,  2; //InterfaceMethod scala/collection/immutable/VectorPointer.display2_$eq:([Ljava/lang/Object;)V
   294:	aload_0
   295:	aload_1
   296:	invokeinterface	#42,  1; //InterfaceMethod scala/collection/immutable/VectorPointer.display1:()[Ljava/lang/Object;
   301:	invokeinterface	#38,  2; //InterfaceMethod scala/collection/immutable/VectorPointer.display1_$eq:([Ljava/lang/Object;)V
   306:	aload_0
   307:	aload_1
   308:	invokeinterface	#46,  1; //InterfaceMethod scala/collection/immutable/VectorPointer.display0:()[Ljava/lang/Object;
   313:	invokeinterface	#52,  2; //InterfaceMethod scala/collection/immutable/VectorPointer.display0_$eq:([Ljava/lang/Object;)V
   318:	goto	456
   321:	new	#123; //class scala/MatchError
   324:	dup
   325:	iload_3
   326:	invokestatic	#129; //Method scala/runtime/BoxesRunTime.boxToInteger:(I)Ljava/lang/Integer;
   329:	invokevirtual	#133; //Method java/lang/Object.toString:()Ljava/lang/String;
   332:	invokespecial	#136; //Method scala/MatchError."<init>":(Ljava/lang/String;)V
   335:	athrow
   336:	iconst_1
   337:	ifeq	379
   340:	aload_0
   341:	aload_1
   342:	invokeinterface	#59,  1; //InterfaceMethod scala/collection/immutable/VectorPointer.display2:()[Ljava/lang/Object;
   347:	invokeinterface	#56,  2; //InterfaceMethod scala/collection/immutable/VectorPointer.display2_$eq:([Ljava/lang/Object;)V
   352:	aload_0
   353:	aload_1
   354:	invokeinterface	#42,  1; //InterfaceMethod scala/collection/immutable/VectorPointer.display1:()[Ljava/lang/Object;
   359:	invokeinterface	#38,  2; //InterfaceMethod scala/collection/immutable/VectorPointer.display1_$eq:([Ljava/lang/Object;)V
   364:	aload_0
   365:	aload_1
   366:	invokeinterface	#46,  1; //InterfaceMethod scala/collection/immutable/VectorPointer.display0:()[Ljava/lang/Object;
   371:	invokeinterface	#52,  2; //InterfaceMethod scala/collection/immutable/VectorPointer.display0_$eq:([Ljava/lang/Object;)V
   376:	goto	456
   379:	new	#123; //class scala/MatchError
   382:	dup
   383:	iload_3
   384:	invokestatic	#129; //Method scala/runtime/BoxesRunTime.boxToInteger:(I)Ljava/lang/Integer;
   387:	invokevirtual	#133; //Method java/lang/Object.toString:()Ljava/lang/String;
   390:	invokespecial	#136; //Method scala/MatchError."<init>":(Ljava/lang/String;)V
   393:	athrow
   394:	iconst_1
   395:	ifeq	425
   398:	aload_0
   399:	aload_1
   400:	invokeinterface	#42,  1; //InterfaceMethod scala/collection/immutable/VectorPointer.display1:()[Ljava/lang/Object;
   405:	invokeinterface	#38,  2; //InterfaceMethod scala/collection/immutable/VectorPointer.display1_$eq:([Ljava/lang/Object;)V
   410:	aload_0
   411:	aload_1
   412:	invokeinterface	#46,  1; //InterfaceMethod scala/collection/immutable/VectorPointer.display0:()[Ljava/lang/Object;
   417:	invokeinterface	#52,  2; //InterfaceMethod scala/collection/immutable/VectorPointer.display0_$eq:([Ljava/lang/Object;)V
   422:	goto	456
   425:	new	#123; //class scala/MatchError
   428:	dup
   429:	iload_3
   430:	invokestatic	#129; //Method scala/runtime/BoxesRunTime.boxToInteger:(I)Ljava/lang/Integer;
   433:	invokevirtual	#133; //Method java/lang/Object.toString:()Ljava/lang/String;
   436:	invokespecial	#136; //Method scala/MatchError."<init>":(Ljava/lang/String;)V
   439:	athrow
   440:	iconst_1
   441:	ifeq	457
   444:	aload_0
   445:	aload_1
   446:	invokeinterface	#46,  1; //InterfaceMethod scala/collection/immutable/VectorPointer.display0:()[Ljava/lang/Object;
   451:	invokeinterface	#52,  2; //InterfaceMethod scala/collection/immutable/VectorPointer.display0_$eq:([Ljava/lang/Object;)V
   456:	return
   457:	new	#123; //class scala/MatchError
   460:	dup
   461:	iload_3
   462:	invokestatic	#129; //Method scala/runtime/BoxesRunTime.boxToInteger:(I)Ljava/lang/Integer;
   465:	invokevirtual	#133; //Method java/lang/Object.toString:()Ljava/lang/String;
   468:	invokespecial	#136; //Method scala/MatchError."<init>":(Ljava/lang/String;)V
   471:	athrow
  LineNumberTable: 
   line 658: 0
   line 659: 7
   line 21: 71
   line 659: 75
   line 21: 90
   line 682: 94
   line 683: 106
   line 684: 118
   line 685: 130
   line 686: 142
   line 687: 154
   line 659: 169
   line 21: 184
   line 676: 188
   line 677: 200
   line 678: 212
   line 679: 224
   line 680: 236
   line 659: 251
   line 21: 266
   line 671: 270
   line 672: 282
   line 673: 294
   line 674: 306
   line 659: 321
   line 21: 336
   line 667: 340
   line 668: 352
   line 669: 364
   line 659: 379
   line 21: 394
   line 664: 398
   line 665: 410
   line 659: 425
   line 21: 440
   line 662: 444
   line 657: 456
   line 659: 457

  LocalVariableTable: 
   Start  Length  Slot  Name   Signature
   0      472      0    $this       Lscala/collection/immutable/VectorPointer;
   0      472      1    that       Lscala/collection/immutable/VectorPointer;
   0      472      2    depth       I
   11      461      3    temp3       I


public static final void initFrom(scala.collection.immutable.VectorPointer, scala.collection.immutable.VectorPointer);
  Code:
   Stack=3, Locals=2, Args_size=2
   0:	aload_0
   1:	aload_1
   2:	aload_1
   3:	invokeinterface	#32,  1; //InterfaceMethod scala/collection/immutable/VectorPointer.depth:()I
   8:	invokeinterface	#158,  3; //InterfaceMethod scala/collection/immutable/VectorPointer.initFrom:(Lscala/collection/immutable/VectorPointer;I)V
   13:	return
  LineNumberTable: 
   line 655: 0

  LocalVariableTable: 
   Start  Length  Slot  Name   Signature
   0      14      0    $this       Lscala/collection/immutable/VectorPointer;
   0      14      1    that       Lscala/collection/immutable/VectorPointer;


}

