Compiled from "Vector.scala"
public final class scala.collection.immutable.VectorIterator extends java.lang.Object implements scala.collection.Iterator,scala.collection.immutable.VectorPointer,scala.ScalaObject
  SourceFile: "Vector.scala"
  Signature: length = 0x2
   01 FFFFFFF8 
  ScalaSig: length = 0x3A3
   05 00 FFFFFF81 07 06 04 01 02 02 09 02 0E 56 65 63 74
   6F 72 49 74 65 72 61 74 6F 72 0A 02 03 04 01 09
   69 6D 6D 75 74 61 62 6C 65 0A 02 05 06 01 0A 63
   6F 6C 6C 65 63 74 69 6F 6E 0A 01 07 01 05 73 63
   61 6C 61 03 00 15 02 0A 19 13 05 00 0B 13 23 31
   10 02 0C 11 0D 01 0D 0A 02 0E 0F 01 04 6C 61 6E
   67 0A 01 10 01 04 6A 61 76 61 09 02 12 0D 02 06
   4F 62 6A 65 63 74 10 03 14 15 17 0D 01 04 09 02
   16 04 02 08 49 74 65 72 61 74 6F 72 10 02 18 19
   0C 00 04 08 1A 00 FFFFFF84 FFFFFF80 FFFFFF84 FFFFFFC2 00 1B 02 01 41 11
   02 1C 20 10 02 1D 1E 0D 01 06 09 02 1F 06 02 07
   4E 6F 74 68 69 6E 67 10 02 1D 21 09 02 22 06 02
   03 41 6E 79 10 03 24 25 27 0D 01 02 09 02 26 02
   02 0D 56 65 63 74 6F 72 50 6F 69 6E 74 65 72 2A
   02 17 28 2B 01 29 10 02 2A 2F 0D 01 2B 0A 02 2C
   2D 01 09 75 6E 63 68 65 63 6B 65 64 0A 02 2E 06
   01 0A 61 6E 6E 6F 74 61 74 69 6F 6E 09 02 30 2B
   02 11 75 6E 63 68 65 63 6B 65 64 56 61 72 69 61
   6E 63 65 10 02 1D 32 09 02 33 06 02 0B 53 63 61
   6C 61 4F 62 6A 65 63 74 08 08 35 00 FFFFFF82 FFFFFF80 FFFFFFA0 FFFFFF80
   04 36 01 0B 5F 73 74 61 72 74 49 6E 64 65 78 10
   02 1D 37 09 02 38 06 02 03 49 6E 74 08 08 3A 00
   FFFFFF82 FFFFFF80 FFFFFFA0 FFFFFF80 04 36 01 09 5F 65 6E 64 49 6E 64 65
   78 08 05 3C 00 FFFFFF84 00 3D 01 06 3C 69 6E 69 74 3E
   14 03 3E 3F 40 10 03 24 00 17 08 05 35 3B FFFFFFC0 00
   36 08 05 3A 3B FFFFFFC0 00 36 08 07 42 00 FFFFFFC0 FFFFFF80 FFFFFF84 04
   43 01 0A 62 6C 6F 63 6B 49 6E 64 65 78 15 01 36
   08 07 45 00 FFFFFFC0 FFFFFF80 FFFFFF84 04 46 01 0E 62 6C 6F 63 6B
   49 6E 64 65 78 5F 24 65 71 14 02 47 4A 10 02 1D
   48 09 02 49 06 02 04 55 6E 69 74 08 07 4B 44 FFFFFF81
   FFFFFF80 FFFFFFC0 00 36 01 03 78 24 31 08 06 4D 00 FFFFFFA0 FFFFFFA0 04
   36 01 0B 62 6C 6F 63 6B 49 6E 64 65 78 20 08 07
   4F 00 FFFFFFC0 FFFFFF80 FFFFFF84 04 43 01 02 6C 6F 08 07 51 00 FFFFFFC0
   FFFFFF80 FFFFFF84 04 52 01 06 6C 6F 5F 24 65 71 14 02 47 53
   08 07 4B 50 FFFFFF81 FFFFFF80 FFFFFFC0 00 36 08 06 55 00 FFFFFFA0 FFFFFFA0 04
   36 01 03 6C 6F 20 08 07 57 00 FFFFFFC0 FFFFFF80 FFFFFF84 04 43 01
   08 65 6E 64 49 6E 64 65 78 08 07 59 00 FFFFFFC0 FFFFFF80 FFFFFF84
   04 5A 01 0C 65 6E 64 49 6E 64 65 78 5F 24 65 71
   14 02 47 5B 08 07 4B 58 FFFFFF81 FFFFFF80 FFFFFFC0 00 36 08 06 5D
   00 FFFFFFA0 FFFFFFA0 04 36 01 09 65 6E 64 49 6E 64 65 78 20
   08 07 5F 00 FFFFFFC0 FFFFFF80 FFFFFF84 04 43 01 05 65 6E 64 4C 6F
   08 07 61 00 FFFFFFC0 FFFFFF80 FFFFFF84 04 62 01 09 65 6E 64 4C 6F
   5F 24 65 71 14 02 47 63 08 07 4B 60 FFFFFF81 FFFFFF80 FFFFFFC0 00
   36 08 06 65 00 FFFFFFA0 FFFFFFA0 04 36 01 06 65 6E 64 4C 6F
   20 08 05 67 00 FFFFFF84 00 68 01 07 68 61 73 4E 65 78
   74 15 01 69 10 02 1D 6A 09 02 6B 06 02 07 42 6F
   6F 6C 65 61 6E 08 07 6D 00 FFFFFFC0 FFFFFF80 FFFFFF84 04 68 01 08
   5F 68 61 73 4E 65 78 74 08 07 6F 00 FFFFFFC0 FFFFFF80 FFFFFF84 04
   70 01 0C 5F 68 61 73 4E 65 78 74 5F 24 65 71 14
   02 47 71 08 07 4B 6E FFFFFF81 FFFFFF80 FFFFFFC0 00 69 08 06 73 00
   FFFFFFA0 FFFFFFA0 04 69 01 09 5F 68 61 73 4E 65 78 74 20 08
   05 75 00 FFFFFF84 00 76 01 04 6E 65 78 74 14 01 17 08
   05 78 00 FFFFFF84 00 79 01 08 66 6F 72 65 61 63 68 30
   15 03 7A FFFFFF81 01 14 02 47 7B 08 05 7C 77 FFFFFFC0 00 7D
   01 01 66 10 05 1D 7E 17 FFFFFF81 00 09 02 7F 06 02 09
   46 75 6E 63 74 69 6F 6E 31 10 03 18 FFFFFF81 01 04 09
   FFFFFF81 02 77 FFFFFF84 FFFFFF80 FFFFFF80 FFFFFFC2 00 1B 02 01 55 28 03 77 FFFFFF81
   04 10 03 1D FFFFFF81 05 09 03 FFFFFF81 06 06 02 06 69 6E 6C
   69 6E 65 
  InnerClass: 
   public final #511= #508 of #510; //WithFilter=class scala/collection/Iterator$WithFilter of class scala/collection/Iterator
   public #514= #513 of #510; //GroupedIterator=class scala/collection/Iterator$GroupedIterator of class scala/collection/Iterator
  minor version: 0
  major version: 49
  Constant pool:
const #1 = Asciz	SourceFile;
const #2 = Asciz	Vector.scala;
const #3 = Asciz	display5;
const #4 = Asciz	[Ljava/lang/Object;;
const #5 = Asciz	display4;
const #6 = Asciz	display3;
const #7 = Asciz	display2;
const #8 = Asciz	display1;
const #9 = Asciz	display0;
const #10 = Asciz	depth;
const #11 = Asciz	I;
const #12 = Asciz	_hasNext;
const #13 = Asciz	Z;
const #14 = Asciz	endLo;
const #15 = Asciz	endIndex;
const #16 = Asciz	lo;
const #17 = Asciz	blockIndex;
const #18 = Asciz	<init>;
const #19 = Asciz	(II)V;
const #20 = Asciz	Code;
const #21 = Asciz	LineNumberTable;
const #22 = Asciz	java/lang/Object;
const #23 = class	#22;	//  java/lang/Object
const #24 = Asciz	()V;
const #25 = NameAndType	#18:#24;//  "<init>":()V
const #26 = Method	#23.#25;	//  java/lang/Object."<init>":()V
const #27 = Asciz	scala/collection/Iterator$class;
const #28 = class	#27;	//  scala/collection/Iterator$class
const #29 = Asciz	$init$;
const #30 = Asciz	(Lscala/collection/Iterator;)V;
const #31 = NameAndType	#29:#30;//  $init$:(Lscala/collection/Iterator;)V
const #32 = Method	#28.#31;	//  scala/collection/Iterator$class.$init$:(Lscala/collection/Iterator;)V
const #33 = Asciz	scala/collection/immutable/VectorPointer$class;
const #34 = class	#33;	//  scala/collection/immutable/VectorPointer$class
const #35 = Asciz	(Lscala/collection/immutable/VectorPointer;)V;
const #36 = NameAndType	#29:#35;//  $init$:(Lscala/collection/immutable/VectorPointer;)V
const #37 = Method	#34.#36;	//  scala/collection/immutable/VectorPointer$class.$init$:(Lscala/collection/immutable/VectorPointer;)V
const #38 = int	31;
const #39 = Asciz	scala/collection/immutable/VectorIterator;
const #40 = class	#39;	//  scala/collection/immutable/VectorIterator
const #41 = NameAndType	#17:#11;//  blockIndex:I
const #42 = Field	#40.#41;	//  scala/collection/immutable/VectorIterator.blockIndex:I
const #43 = NameAndType	#16:#11;//  lo:I
const #44 = Field	#40.#43;	//  scala/collection/immutable/VectorIterator.lo:I
const #45 = NameAndType	#15:#11;//  endIndex:I
const #46 = Field	#40.#45;	//  scala/collection/immutable/VectorIterator.endIndex:I
const #47 = Asciz	scala/math/package$;
const #48 = class	#47;	//  scala/math/package$
const #49 = Asciz	MODULE$;
const #50 = Asciz	Lscala/math/package$;;
const #51 = NameAndType	#49:#50;//  MODULE$:Lscala/math/package$;
const #52 = Field	#48.#51;	//  scala/math/package$.MODULE$:Lscala/math/package$;
const #53 = Asciz	()I;
const #54 = NameAndType	#15:#53;//  endIndex:()I
const #55 = Method	#40.#54;	//  scala/collection/immutable/VectorIterator.endIndex:()I
const #56 = NameAndType	#17:#53;//  blockIndex:()I
const #57 = Method	#40.#56;	//  scala/collection/immutable/VectorIterator.blockIndex:()I
const #58 = int	32;
const #59 = Asciz	scala/MathCommon;
const #60 = class	#59;	//  scala/MathCommon
const #61 = Asciz	min;
const #62 = Asciz	(II)I;
const #63 = NameAndType	#61:#62;//  min:(II)I
const #64 = InterfaceMethod	#60.#63;	//  scala/MathCommon.min:(II)I
const #65 = NameAndType	#14:#11;//  endLo:I
const #66 = Field	#40.#65;	//  scala/collection/immutable/VectorIterator.endLo:I
const #67 = NameAndType	#16:#53;//  lo:()I
const #68 = Method	#40.#67;	//  scala/collection/immutable/VectorIterator.lo:()I
const #69 = NameAndType	#12:#13;//  _hasNext:Z
const #70 = Field	#40.#69;	//  scala/collection/immutable/VectorIterator._hasNext:Z
const #71 = Asciz	this;
const #72 = Asciz	Lscala/collection/immutable/VectorIterator;;
const #73 = Asciz	_startIndex;
const #74 = Asciz	_endIndex;
const #75 = Asciz	LocalVariableTable;
const #76 = Asciz	Signature;
const #77 = Asciz	foreach0;
const #78 = Asciz	(Lscala/Function1;)V;
const #79 = Asciz	()Z;
const #80 = NameAndType	#12:#79;//  _hasNext:()Z
const #81 = Method	#40.#80;	//  scala/collection/immutable/VectorIterator._hasNext:()Z
const #82 = Asciz	next;
const #83 = Asciz	()Ljava/lang/Object;;
const #84 = NameAndType	#82:#83;//  next:()Ljava/lang/Object;
const #85 = Method	#40.#84;	//  scala/collection/immutable/VectorIterator.next:()Ljava/lang/Object;
const #86 = Asciz	scala/Function1;
const #87 = class	#86;	//  scala/Function1
const #88 = Asciz	apply;
const #89 = Asciz	(Ljava/lang/Object;)Ljava/lang/Object;;
const #90 = NameAndType	#88:#89;//  apply:(Ljava/lang/Object;)Ljava/lang/Object;
const #91 = InterfaceMethod	#87.#90;	//  scala/Function1.apply:(Ljava/lang/Object;)Ljava/lang/Object;
const #92 = Asciz	f;
const #93 = Asciz	Lscala/Function1;;
const #94 = Asciz	<U:Ljava/lang/Object;>(Lscala/Function1<TA;TU;>;)V;
const #95 = NameAndType	#9:#4;//  display0:[Ljava/lang/Object;
const #96 = Field	#40.#95;	//  scala/collection/immutable/VectorIterator.display0:[Ljava/lang/Object;
const #97 = Asciz	lo_$eq;
const #98 = Asciz	(I)V;
const #99 = NameAndType	#97:#98;//  lo_$eq:(I)V
const #100 = Method	#40.#99;	//  scala/collection/immutable/VectorIterator.lo_$eq:(I)V
const #101 = NameAndType	#14:#53;//  endLo:()I
const #102 = Method	#40.#101;	//  scala/collection/immutable/VectorIterator.endLo:()I
const #103 = Asciz	scala/collection/immutable/VectorPointer;
const #104 = class	#103;	//  scala/collection/immutable/VectorPointer
const #105 = Asciz	gotoNextBlockStart;
const #106 = NameAndType	#105:#19;//  gotoNextBlockStart:(II)V
const #107 = InterfaceMethod	#104.#106;	//  scala/collection/immutable/VectorPointer.gotoNextBlockStart:(II)V
const #108 = Asciz	blockIndex_$eq;
const #109 = NameAndType	#108:#98;//  blockIndex_$eq:(I)V
const #110 = Method	#40.#109;	//  scala/collection/immutable/VectorIterator.blockIndex_$eq:(I)V
const #111 = Asciz	scala/MathCommon$class;
const #112 = class	#111;	//  scala/MathCommon$class
const #113 = Asciz	(Lscala/MathCommon;II)I;
const #114 = NameAndType	#61:#113;//  min:(Lscala/MathCommon;II)I
const #115 = Method	#112.#114;	//  scala/MathCommon$class.min:(Lscala/MathCommon;II)I
const #116 = Asciz	endLo_$eq;
const #117 = NameAndType	#116:#98;//  endLo_$eq:(I)V
const #118 = Method	#40.#117;	//  scala/collection/immutable/VectorIterator.endLo_$eq:(I)V
const #119 = Asciz	_hasNext_$eq;
const #120 = Asciz	(Z)V;
const #121 = NameAndType	#119:#120;//  _hasNext_$eq:(Z)V
const #122 = Method	#40.#121;	//  scala/collection/immutable/VectorIterator._hasNext_$eq:(Z)V
const #123 = Asciz	java/util/NoSuchElementException;
const #124 = class	#123;	//  java/util/NoSuchElementException
const #125 = Asciz	reached iterator end;
const #126 = String	#125;	//  reached iterator end
const #127 = Asciz	(Ljava/lang/String;)V;
const #128 = NameAndType	#18:#127;//  "<init>":(Ljava/lang/String;)V
const #129 = Method	#124.#128;	//  java/util/NoSuchElementException."<init>":(Ljava/lang/String;)V
const #130 = Asciz	newBlockIndex;
const #131 = Asciz	res;
const #132 = Asciz	Ljava/lang/Object;;
const #133 = Asciz	()TA;;
const #134 = Asciz	hasNext;
const #135 = Asciz	endIndex_$eq;
const #136 = Asciz	sliding$default$2;
const #137 = Asciz	(Lscala/collection/Iterator;)I;
const #138 = NameAndType	#136:#137;//  sliding$default$2:(Lscala/collection/Iterator;)I
const #139 = Method	#28.#138;	//  scala/collection/Iterator$class.sliding$default$2:(Lscala/collection/Iterator;)I
const #140 = Asciz	readInto;
const #141 = Asciz	(Ljava/lang/Object;)V;
const #142 = Asciz	(Lscala/collection/Iterator;Ljava/lang/Object;)V;
const #143 = NameAndType	#140:#142;//  readInto:(Lscala/collection/Iterator;Ljava/lang/Object;)V
const #144 = Method	#28.#143;	//  scala/collection/Iterator$class.readInto:(Lscala/collection/Iterator;Ljava/lang/Object;)V
const #145 = Asciz	xs;
const #146 = Asciz	(Ljava/lang/Object;I)V;
const #147 = Asciz	(Lscala/collection/Iterator;Ljava/lang/Object;I)V;
const #148 = NameAndType	#140:#147;//  readInto:(Lscala/collection/Iterator;Ljava/lang/Object;I)V
const #149 = Method	#28.#148;	//  scala/collection/Iterator$class.readInto:(Lscala/collection/Iterator;Ljava/lang/Object;I)V
const #150 = Asciz	start;
const #151 = Asciz	(Ljava/lang/Object;II)V;
const #152 = Asciz	(Lscala/collection/Iterator;Ljava/lang/Object;II)V;
const #153 = NameAndType	#140:#152;//  readInto:(Lscala/collection/Iterator;Ljava/lang/Object;II)V
const #154 = Method	#28.#153;	//  scala/collection/Iterator$class.readInto:(Lscala/collection/Iterator;Ljava/lang/Object;II)V
const #155 = Asciz	sz;
const #156 = Asciz	counted;
const #157 = Asciz	(Lscala/collection/Iterator;)Ljava/lang/Object;;
const #158 = NameAndType	#156:#157;//  counted:(Lscala/collection/Iterator;)Ljava/lang/Object;
const #159 = Method	#28.#158;	//  scala/collection/Iterator$class.counted:(Lscala/collection/Iterator;)Ljava/lang/Object;
const #160 = Asciz	collect;
const #161 = Asciz	()Lscala/collection/Seq;;
const #162 = Asciz	(Lscala/collection/Iterator;)Lscala/collection/Seq;;
const #163 = NameAndType	#160:#162;//  collect:(Lscala/collection/Iterator;)Lscala/collection/Seq;
const #164 = Method	#28.#163;	//  scala/collection/Iterator$class.collect:(Lscala/collection/Iterator;)Lscala/collection/Seq;
const #165 = Asciz	findIndexOf;
const #166 = Asciz	(Lscala/Function1;)I;
const #167 = Asciz	(Lscala/collection/Iterator;Lscala/Function1;)I;
const #168 = NameAndType	#165:#167;//  findIndexOf:(Lscala/collection/Iterator;Lscala/Function1;)I
const #169 = Method	#28.#168;	//  scala/collection/Iterator$class.findIndexOf:(Lscala/collection/Iterator;Lscala/Function1;)I
const #170 = Asciz	p;
const #171 = Asciz	append;
const #172 = Asciz	(Lscala/collection/Iterator;)Lscala/collection/Iterator;;
const #173 = Asciz	(Lscala/collection/Iterator;Lscala/collection/Iterator;)Lscala/collection/Iterator;;
const #174 = NameAndType	#171:#173;//  append:(Lscala/collection/Iterator;Lscala/collection/Iterator;)Lscala/collection/Iterator;
const #175 = Method	#28.#174;	//  scala/collection/Iterator$class.append:(Lscala/collection/Iterator;Lscala/collection/Iterator;)Lscala/collection/Iterator;
const #176 = Asciz	that;
const #177 = Asciz	Lscala/collection/Iterator;;
const #178 = Asciz	toString;
const #179 = Asciz	()Ljava/lang/String;;
const #180 = Asciz	(Lscala/collection/Iterator;)Ljava/lang/String;;
const #181 = NameAndType	#178:#180;//  toString:(Lscala/collection/Iterator;)Ljava/lang/String;
const #182 = Method	#28.#181;	//  scala/collection/Iterator$class.toString:(Lscala/collection/Iterator;)Ljava/lang/String;
const #183 = Asciz	addString;
const #184 = Asciz	(Lscala/collection/mutable/StringBuilder;)Lscala/collection/mutable/StringBuilder;;
const #185 = Asciz	(Lscala/collection/Iterator;Lscala/collection/mutable/StringBuilder;)Lscala/collection/mutable/StringBuilder;;
const #186 = NameAndType	#183:#185;//  addString:(Lscala/collection/Iterator;Lscala/collection/mutable/StringBuilder;)Lscala/collection/mutable/StringBuilder;
const #187 = Method	#28.#186;	//  scala/collection/Iterator$class.addString:(Lscala/collection/Iterator;Lscala/collection/mutable/StringBuilder;)Lscala/collection/mutable/StringBuilder;
const #188 = Asciz	buf;
const #189 = Asciz	Lscala/collection/mutable/StringBuilder;;
const #190 = Asciz	(Lscala/collection/mutable/StringBuilder;Ljava/lang/String;)Lscala/collection/mutable/StringBuilder;;
const #191 = Asciz	(Lscala/collection/Iterator;Lscala/collection/mutable/StringBuilder;Ljava/lang/String;)Lscala/collection/mutable/StringBuilder;;
const #192 = NameAndType	#183:#191;//  addString:(Lscala/collection/Iterator;Lscala/collection/mutable/StringBuilder;Ljava/lang/String;)Lscala/collection/mutable/StringBuilder;
const #193 = Method	#28.#192;	//  scala/collection/Iterator$class.addString:(Lscala/collection/Iterator;Lscala/collection/mutable/StringBuilder;Ljava/lang/String;)Lscala/collection/mutable/StringBuilder;
const #194 = Asciz	sep;
const #195 = Asciz	Ljava/lang/String;;
const #196 = Asciz	(Lscala/collection/mutable/StringBuilder;Ljava/lang/String;Ljava/lang/String;Ljava/lang/String;)Lscala/collection/mutable/StringBuilder;;
const #197 = Asciz	(Lscala/collection/Iterator;Lscala/collection/mutable/StringBuilder;Ljava/lang/String;Ljava/lang/String;Ljava/lang/String;)Lscala/collection/mutable/StringBuilder;;
const #198 = NameAndType	#183:#197;//  addString:(Lscala/collection/Iterator;Lscala/collection/mutable/StringBuilder;Ljava/lang/String;Ljava/lang/String;Ljava/lang/String;)Lscala/collection/mutable/StringBuilder;
const #199 = Method	#28.#198;	//  scala/collection/Iterator$class.addString:(Lscala/collection/Iterator;Lscala/collection/mutable/StringBuilder;Ljava/lang/String;Ljava/lang/String;Ljava/lang/String;)Lscala/collection/mutable/StringBuilder;
const #200 = Asciz	end;
const #201 = Asciz	mkString;
const #202 = NameAndType	#201:#180;//  mkString:(Lscala/collection/Iterator;)Ljava/lang/String;
const #203 = Method	#28.#202;	//  scala/collection/Iterator$class.mkString:(Lscala/collection/Iterator;)Ljava/lang/String;
const #204 = Asciz	(Ljava/lang/String;)Ljava/lang/String;;
const #205 = Asciz	(Lscala/collection/Iterator;Ljava/lang/String;)Ljava/lang/String;;
const #206 = NameAndType	#201:#205;//  mkString:(Lscala/collection/Iterator;Ljava/lang/String;)Ljava/lang/String;
const #207 = Method	#28.#206;	//  scala/collection/Iterator$class.mkString:(Lscala/collection/Iterator;Ljava/lang/String;)Ljava/lang/String;
const #208 = Asciz	(Ljava/lang/String;Ljava/lang/String;Ljava/lang/String;)Ljava/lang/String;;
const #209 = Asciz	(Lscala/collection/Iterator;Ljava/lang/String;Ljava/lang/String;Ljava/lang/String;)Ljava/lang/String;;
const #210 = NameAndType	#201:#209;//  mkString:(Lscala/collection/Iterator;Ljava/lang/String;Ljava/lang/String;Ljava/lang/String;)Ljava/lang/String;
const #211 = Method	#28.#210;	//  scala/collection/Iterator$class.mkString:(Lscala/collection/Iterator;Ljava/lang/String;Ljava/lang/String;Ljava/lang/String;)Ljava/lang/String;
const #212 = Asciz	sameElements;
const #213 = Asciz	(Lscala/collection/Iterator;)Z;
const #214 = Asciz	(Lscala/collection/Iterator;Lscala/collection/Iterator;)Z;
const #215 = NameAndType	#212:#214;//  sameElements:(Lscala/collection/Iterator;Lscala/collection/Iterator;)Z
const #216 = Method	#28.#215;	//  scala/collection/Iterator$class.sameElements:(Lscala/collection/Iterator;Lscala/collection/Iterator;)Z
const #217 = Asciz	toSeq;
const #218 = NameAndType	#217:#162;//  toSeq:(Lscala/collection/Iterator;)Lscala/collection/Seq;
const #219 = Method	#28.#218;	//  scala/collection/Iterator$class.toSeq:(Lscala/collection/Iterator;)Lscala/collection/Seq;
const #220 = Asciz	toStream;
const #221 = Asciz	()Lscala/collection/immutable/Stream;;
const #222 = Asciz	(Lscala/collection/Iterator;)Lscala/collection/immutable/Stream;;
const #223 = NameAndType	#220:#222;//  toStream:(Lscala/collection/Iterator;)Lscala/collection/immutable/Stream;
const #224 = Method	#28.#223;	//  scala/collection/Iterator$class.toStream:(Lscala/collection/Iterator;)Lscala/collection/immutable/Stream;
const #225 = Asciz	toList;
const #226 = Asciz	()Lscala/collection/immutable/List;;
const #227 = Asciz	(Lscala/collection/Iterator;)Lscala/collection/immutable/List;;
const #228 = NameAndType	#225:#227;//  toList:(Lscala/collection/Iterator;)Lscala/collection/immutable/List;
const #229 = Method	#28.#228;	//  scala/collection/Iterator$class.toList:(Lscala/collection/Iterator;)Lscala/collection/immutable/List;
const #230 = Asciz	copyToBuffer;
const #231 = Asciz	(Lscala/collection/mutable/Buffer;)V;
const #232 = Asciz	(Lscala/collection/Iterator;Lscala/collection/mutable/Buffer;)V;
const #233 = NameAndType	#230:#232;//  copyToBuffer:(Lscala/collection/Iterator;Lscala/collection/mutable/Buffer;)V
const #234 = Method	#28.#233;	//  scala/collection/Iterator$class.copyToBuffer:(Lscala/collection/Iterator;Lscala/collection/mutable/Buffer;)V
const #235 = Asciz	dest;
const #236 = Asciz	Lscala/collection/mutable/Buffer;;
const #237 = Asciz	copyToArray;
const #238 = NameAndType	#237:#142;//  copyToArray:(Lscala/collection/Iterator;Ljava/lang/Object;)V
const #239 = Method	#28.#238;	//  scala/collection/Iterator$class.copyToArray:(Lscala/collection/Iterator;Ljava/lang/Object;)V
const #240 = NameAndType	#237:#147;//  copyToArray:(Lscala/collection/Iterator;Ljava/lang/Object;I)V
const #241 = Method	#28.#240;	//  scala/collection/Iterator$class.copyToArray:(Lscala/collection/Iterator;Ljava/lang/Object;I)V
const #242 = NameAndType	#237:#152;//  copyToArray:(Lscala/collection/Iterator;Ljava/lang/Object;II)V
const #243 = Method	#28.#242;	//  scala/collection/Iterator$class.copyToArray:(Lscala/collection/Iterator;Ljava/lang/Object;II)V
const #244 = Asciz	len;
const #245 = Asciz	patch;
const #246 = Asciz	(ILscala/collection/Iterator;I)Ljava/lang/Object;;
const #247 = Asciz	(Lscala/collection/Iterator;ILscala/collection/Iterator;I)Ljava/lang/Object;;
const #248 = NameAndType	#245:#247;//  patch:(Lscala/collection/Iterator;ILscala/collection/Iterator;I)Ljava/lang/Object;
const #249 = Method	#28.#248;	//  scala/collection/Iterator$class.patch:(Lscala/collection/Iterator;ILscala/collection/Iterator;I)Ljava/lang/Object;
const #250 = Asciz	from;
const #251 = Asciz	patchElems;
const #252 = Asciz	replaced;
const #253 = Asciz	duplicate;
const #254 = Asciz	()Lscala/Tuple2;;
const #255 = Asciz	(Lscala/collection/Iterator;)Lscala/Tuple2;;
const #256 = NameAndType	#253:#255;//  duplicate:(Lscala/collection/Iterator;)Lscala/Tuple2;
const #257 = Method	#28.#256;	//  scala/collection/Iterator$class.duplicate:(Lscala/collection/Iterator;)Lscala/Tuple2;
const #258 = Asciz	length;
const #259 = NameAndType	#258:#137;//  length:(Lscala/collection/Iterator;)I
const #260 = Method	#28.#259;	//  scala/collection/Iterator$class.length:(Lscala/collection/Iterator;)I
const #261 = Asciz	sliding;
const #262 = Asciz	(II)Lscala/collection/Iterator$GroupedIterator;;
const #263 = Asciz	(Lscala/collection/Iterator;II)Lscala/collection/Iterator$GroupedIterator;;
const #264 = NameAndType	#261:#263;//  sliding:(Lscala/collection/Iterator;II)Lscala/collection/Iterator$GroupedIterator;
const #265 = Method	#28.#264;	//  scala/collection/Iterator$class.sliding:(Lscala/collection/Iterator;II)Lscala/collection/Iterator$GroupedIterator;
const #266 = Asciz	size;
const #267 = Asciz	step;
const #268 = Asciz	grouped;
const #269 = Asciz	(I)Lscala/collection/Iterator$GroupedIterator;;
const #270 = Asciz	(Lscala/collection/Iterator;I)Lscala/collection/Iterator$GroupedIterator;;
const #271 = NameAndType	#268:#270;//  grouped:(Lscala/collection/Iterator;I)Lscala/collection/Iterator$GroupedIterator;
const #272 = Method	#28.#271;	//  scala/collection/Iterator$class.grouped:(Lscala/collection/Iterator;I)Lscala/collection/Iterator$GroupedIterator;
const #273 = Asciz	buffered;
const #274 = NameAndType	#273:#157;//  buffered:(Lscala/collection/Iterator;)Ljava/lang/Object;
const #275 = Method	#28.#274;	//  scala/collection/Iterator$class.buffered:(Lscala/collection/Iterator;)Ljava/lang/Object;
const #276 = Asciz	reduceRightOption;
const #277 = Asciz	(Lscala/Function2;)Lscala/Option;;
const #278 = Asciz	(Lscala/collection/Iterator;Lscala/Function2;)Lscala/Option;;
const #279 = NameAndType	#276:#278;//  reduceRightOption:(Lscala/collection/Iterator;Lscala/Function2;)Lscala/Option;
const #280 = Method	#28.#279;	//  scala/collection/Iterator$class.reduceRightOption:(Lscala/collection/Iterator;Lscala/Function2;)Lscala/Option;
const #281 = Asciz	op;
const #282 = Asciz	Lscala/Function2;;
const #283 = Asciz	reduceLeftOption;
const #284 = NameAndType	#283:#278;//  reduceLeftOption:(Lscala/collection/Iterator;Lscala/Function2;)Lscala/Option;
const #285 = Method	#28.#284;	//  scala/collection/Iterator$class.reduceLeftOption:(Lscala/collection/Iterator;Lscala/Function2;)Lscala/Option;
const #286 = Asciz	reduceRight;
const #287 = Asciz	(Lscala/Function2;)Ljava/lang/Object;;
const #288 = Asciz	(Lscala/collection/Iterator;Lscala/Function2;)Ljava/lang/Object;;
const #289 = NameAndType	#286:#288;//  reduceRight:(Lscala/collection/Iterator;Lscala/Function2;)Ljava/lang/Object;
const #290 = Method	#28.#289;	//  scala/collection/Iterator$class.reduceRight:(Lscala/collection/Iterator;Lscala/Function2;)Ljava/lang/Object;
const #291 = Asciz	reduceLeft;
const #292 = NameAndType	#291:#288;//  reduceLeft:(Lscala/collection/Iterator;Lscala/Function2;)Ljava/lang/Object;
const #293 = Method	#28.#292;	//  scala/collection/Iterator$class.reduceLeft:(Lscala/collection/Iterator;Lscala/Function2;)Ljava/lang/Object;
const #294 = Asciz	$colon$bslash;
const #295 = Asciz	(Ljava/lang/Object;Lscala/Function2;)Ljava/lang/Object;;
const #296 = Asciz	(Lscala/collection/Iterator;Ljava/lang/Object;Lscala/Function2;)Ljava/lang/Object;;
const #297 = NameAndType	#294:#296;//  $colon$bslash:(Lscala/collection/Iterator;Ljava/lang/Object;Lscala/Function2;)Ljava/lang/Object;
const #298 = Method	#28.#297;	//  scala/collection/Iterator$class.$colon$bslash:(Lscala/collection/Iterator;Ljava/lang/Object;Lscala/Function2;)Ljava/lang/Object;
const #299 = Asciz	z;
const #300 = Asciz	$div$colon;
const #301 = NameAndType	#300:#296;//  $div$colon:(Lscala/collection/Iterator;Ljava/lang/Object;Lscala/Function2;)Ljava/lang/Object;
const #302 = Method	#28.#301;	//  scala/collection/Iterator$class.$div$colon:(Lscala/collection/Iterator;Ljava/lang/Object;Lscala/Function2;)Ljava/lang/Object;
const #303 = Asciz	foldRight;
const #304 = NameAndType	#303:#296;//  foldRight:(Lscala/collection/Iterator;Ljava/lang/Object;Lscala/Function2;)Ljava/lang/Object;
const #305 = Method	#28.#304;	//  scala/collection/Iterator$class.foldRight:(Lscala/collection/Iterator;Ljava/lang/Object;Lscala/Function2;)Ljava/lang/Object;
const #306 = Asciz	foldLeft;
const #307 = NameAndType	#306:#296;//  foldLeft:(Lscala/collection/Iterator;Ljava/lang/Object;Lscala/Function2;)Ljava/lang/Object;
const #308 = Method	#28.#307;	//  scala/collection/Iterator$class.foldLeft:(Lscala/collection/Iterator;Ljava/lang/Object;Lscala/Function2;)Ljava/lang/Object;
const #309 = Asciz	indexOf;
const #310 = Asciz	(Ljava/lang/Object;)I;
const #311 = Asciz	(Lscala/collection/Iterator;Ljava/lang/Object;)I;
const #312 = NameAndType	#309:#311;//  indexOf:(Lscala/collection/Iterator;Ljava/lang/Object;)I
const #313 = Method	#28.#312;	//  scala/collection/Iterator$class.indexOf:(Lscala/collection/Iterator;Ljava/lang/Object;)I
const #314 = Asciz	elem;
const #315 = Asciz	indexWhere;
const #316 = NameAndType	#315:#167;//  indexWhere:(Lscala/collection/Iterator;Lscala/Function1;)I
const #317 = Method	#28.#316;	//  scala/collection/Iterator$class.indexWhere:(Lscala/collection/Iterator;Lscala/Function1;)I
const #318 = Asciz	find;
const #319 = Asciz	(Lscala/Function1;)Lscala/Option;;
const #320 = Asciz	(Lscala/collection/Iterator;Lscala/Function1;)Lscala/Option;;
const #321 = NameAndType	#318:#320;//  find:(Lscala/collection/Iterator;Lscala/Function1;)Lscala/Option;
const #322 = Method	#28.#321;	//  scala/collection/Iterator$class.find:(Lscala/collection/Iterator;Lscala/Function1;)Lscala/Option;
const #323 = Asciz	contains;
const #324 = Asciz	(Ljava/lang/Object;)Z;
const #325 = Asciz	(Lscala/collection/Iterator;Ljava/lang/Object;)Z;
const #326 = NameAndType	#323:#325;//  contains:(Lscala/collection/Iterator;Ljava/lang/Object;)Z
const #327 = Method	#28.#326;	//  scala/collection/Iterator$class.contains:(Lscala/collection/Iterator;Ljava/lang/Object;)Z
const #328 = Asciz	exists;
const #329 = Asciz	(Lscala/Function1;)Z;
const #330 = Asciz	(Lscala/collection/Iterator;Lscala/Function1;)Z;
const #331 = NameAndType	#328:#330;//  exists:(Lscala/collection/Iterator;Lscala/Function1;)Z
const #332 = Method	#28.#331;	//  scala/collection/Iterator$class.exists:(Lscala/collection/Iterator;Lscala/Function1;)Z
const #333 = Asciz	forall;
const #334 = NameAndType	#333:#330;//  forall:(Lscala/collection/Iterator;Lscala/Function1;)Z
const #335 = Method	#28.#334;	//  scala/collection/Iterator$class.forall:(Lscala/collection/Iterator;Lscala/Function1;)Z
const #336 = Asciz	foreach;
const #337 = Asciz	(Lscala/collection/Iterator;Lscala/Function1;)V;
const #338 = NameAndType	#336:#337;//  foreach:(Lscala/collection/Iterator;Lscala/Function1;)V
const #339 = Method	#28.#338;	//  scala/collection/Iterator$class.foreach:(Lscala/collection/Iterator;Lscala/Function1;)V
const #340 = Asciz	zipAll;
const #341 = Asciz	(Lscala/collection/Iterator;Ljava/lang/Object;Ljava/lang/Object;)Ljava/lang/Object;;
const #342 = Asciz	(Lscala/collection/Iterator;Lscala/collection/Iterator;Ljava/lang/Object;Ljava/lang/Object;)Ljava/lang/Object;;
const #343 = NameAndType	#340:#342;//  zipAll:(Lscala/collection/Iterator;Lscala/collection/Iterator;Ljava/lang/Object;Ljava/lang/Object;)Ljava/lang/Object;
const #344 = Method	#28.#343;	//  scala/collection/Iterator$class.zipAll:(Lscala/collection/Iterator;Lscala/collection/Iterator;Ljava/lang/Object;Ljava/lang/Object;)Ljava/lang/Object;
const #345 = Asciz	thisElem;
const #346 = Asciz	thatElem;
const #347 = Asciz	zipWithIndex;
const #348 = NameAndType	#347:#157;//  zipWithIndex:(Lscala/collection/Iterator;)Ljava/lang/Object;
const #349 = Method	#28.#348;	//  scala/collection/Iterator$class.zipWithIndex:(Lscala/collection/Iterator;)Ljava/lang/Object;
const #350 = Asciz	padTo;
const #351 = Asciz	(ILjava/lang/Object;)Ljava/lang/Object;;
const #352 = Asciz	(Lscala/collection/Iterator;ILjava/lang/Object;)Ljava/lang/Object;;
const #353 = NameAndType	#350:#352;//  padTo:(Lscala/collection/Iterator;ILjava/lang/Object;)Ljava/lang/Object;
const #354 = Method	#28.#353;	//  scala/collection/Iterator$class.padTo:(Lscala/collection/Iterator;ILjava/lang/Object;)Ljava/lang/Object;
const #355 = Asciz	zip;
const #356 = Asciz	(Lscala/collection/Iterator;Lscala/collection/Iterator;)Ljava/lang/Object;;
const #357 = NameAndType	#355:#356;//  zip:(Lscala/collection/Iterator;Lscala/collection/Iterator;)Ljava/lang/Object;
const #358 = Method	#28.#357;	//  scala/collection/Iterator$class.zip:(Lscala/collection/Iterator;Lscala/collection/Iterator;)Ljava/lang/Object;
const #359 = Asciz	dropWhile;
const #360 = Asciz	(Lscala/Function1;)Lscala/collection/Iterator;;
const #361 = Asciz	(Lscala/collection/Iterator;Lscala/Function1;)Lscala/collection/Iterator;;
const #362 = NameAndType	#359:#361;//  dropWhile:(Lscala/collection/Iterator;Lscala/Function1;)Lscala/collection/Iterator;
const #363 = Method	#28.#362;	//  scala/collection/Iterator$class.dropWhile:(Lscala/collection/Iterator;Lscala/Function1;)Lscala/collection/Iterator;
const #364 = Asciz	partition;
const #365 = Asciz	(Lscala/Function1;)Lscala/Tuple2;;
const #366 = Asciz	(Lscala/collection/Iterator;Lscala/Function1;)Lscala/Tuple2;;
const #367 = NameAndType	#364:#366;//  partition:(Lscala/collection/Iterator;Lscala/Function1;)Lscala/Tuple2;
const #368 = Method	#28.#367;	//  scala/collection/Iterator$class.partition:(Lscala/collection/Iterator;Lscala/Function1;)Lscala/Tuple2;
const #369 = Asciz	takeWhile;
const #370 = NameAndType	#369:#361;//  takeWhile:(Lscala/collection/Iterator;Lscala/Function1;)Lscala/collection/Iterator;
const #371 = Method	#28.#370;	//  scala/collection/Iterator$class.takeWhile:(Lscala/collection/Iterator;Lscala/Function1;)Lscala/collection/Iterator;
const #372 = Asciz	partialMap;
const #373 = Asciz	(Lscala/PartialFunction;)Lscala/collection/Iterator;;
const #374 = Asciz	(Lscala/collection/Iterator;Lscala/PartialFunction;)Lscala/collection/Iterator;;
const #375 = NameAndType	#372:#374;//  partialMap:(Lscala/collection/Iterator;Lscala/PartialFunction;)Lscala/collection/Iterator;
const #376 = Method	#28.#375;	//  scala/collection/Iterator$class.partialMap:(Lscala/collection/Iterator;Lscala/PartialFunction;)Lscala/collection/Iterator;
const #377 = Asciz	pf;
const #378 = Asciz	Lscala/PartialFunction;;
const #379 = Asciz	filterNot;
const #380 = NameAndType	#379:#361;//  filterNot:(Lscala/collection/Iterator;Lscala/Function1;)Lscala/collection/Iterator;
const #381 = Method	#28.#380;	//  scala/collection/Iterator$class.filterNot:(Lscala/collection/Iterator;Lscala/Function1;)Lscala/collection/Iterator;
const #382 = Asciz	withFilter;
const #383 = Asciz	(Lscala/Function1;)Lscala/collection/Iterator$WithFilter;;
const #384 = Asciz	(Lscala/collection/Iterator;Lscala/Function1;)Lscala/collection/Iterator$WithFilter;;
const #385 = NameAndType	#382:#384;//  withFilter:(Lscala/collection/Iterator;Lscala/Function1;)Lscala/collection/Iterator$WithFilter;
const #386 = Method	#28.#385;	//  scala/collection/Iterator$class.withFilter:(Lscala/collection/Iterator;Lscala/Function1;)Lscala/collection/Iterator$WithFilter;
const #387 = Asciz	filter;
const #388 = NameAndType	#387:#361;//  filter:(Lscala/collection/Iterator;Lscala/Function1;)Lscala/collection/Iterator;
const #389 = Method	#28.#388;	//  scala/collection/Iterator$class.filter:(Lscala/collection/Iterator;Lscala/Function1;)Lscala/collection/Iterator;
const #390 = Asciz	flatMap;
const #391 = NameAndType	#390:#361;//  flatMap:(Lscala/collection/Iterator;Lscala/Function1;)Lscala/collection/Iterator;
const #392 = Method	#28.#391;	//  scala/collection/Iterator$class.flatMap:(Lscala/collection/Iterator;Lscala/Function1;)Lscala/collection/Iterator;
const #393 = Asciz	$plus$plus;
const #394 = Asciz	(Lscala/Function0;)Lscala/collection/Iterator;;
const #395 = Asciz	(Lscala/collection/Iterator;Lscala/Function0;)Lscala/collection/Iterator;;
const #396 = NameAndType	#393:#395;//  $plus$plus:(Lscala/collection/Iterator;Lscala/Function0;)Lscala/collection/Iterator;
const #397 = Method	#28.#396;	//  scala/collection/Iterator$class.$plus$plus:(Lscala/collection/Iterator;Lscala/Function0;)Lscala/collection/Iterator;
const #398 = Asciz	Lscala/Function0;;
const #399 = Asciz	map;
const #400 = NameAndType	#399:#361;//  map:(Lscala/collection/Iterator;Lscala/Function1;)Lscala/collection/Iterator;
const #401 = Method	#28.#400;	//  scala/collection/Iterator$class.map:(Lscala/collection/Iterator;Lscala/Function1;)Lscala/collection/Iterator;
const #402 = Asciz	slice;
const #403 = Asciz	(II)Lscala/collection/Iterator;;
const #404 = Asciz	(Lscala/collection/Iterator;II)Lscala/collection/Iterator;;
const #405 = NameAndType	#402:#404;//  slice:(Lscala/collection/Iterator;II)Lscala/collection/Iterator;
const #406 = Method	#28.#405;	//  scala/collection/Iterator$class.slice:(Lscala/collection/Iterator;II)Lscala/collection/Iterator;
const #407 = Asciz	until;
const #408 = Asciz	drop;
const #409 = Asciz	(I)Lscala/collection/Iterator;;
const #410 = Asciz	(Lscala/collection/Iterator;I)Lscala/collection/Iterator;;
const #411 = NameAndType	#408:#410;//  drop:(Lscala/collection/Iterator;I)Lscala/collection/Iterator;
const #412 = Method	#28.#411;	//  scala/collection/Iterator$class.drop:(Lscala/collection/Iterator;I)Lscala/collection/Iterator;
const #413 = Asciz	n;
const #414 = Asciz	take;
const #415 = NameAndType	#414:#410;//  take:(Lscala/collection/Iterator;I)Lscala/collection/Iterator;
const #416 = Method	#28.#415;	//  scala/collection/Iterator$class.take:(Lscala/collection/Iterator;I)Lscala/collection/Iterator;
const #417 = Asciz	debug;
const #418 = NameAndType	#417:#35;//  debug:(Lscala/collection/immutable/VectorPointer;)V
const #419 = Method	#34.#418;	//  scala/collection/immutable/VectorPointer$class.debug:(Lscala/collection/immutable/VectorPointer;)V
const #420 = Asciz	gotoFreshPosWritable1;
const #421 = Asciz	(III)V;
const #422 = Asciz	(Lscala/collection/immutable/VectorPointer;III)V;
const #423 = NameAndType	#420:#422;//  gotoFreshPosWritable1:(Lscala/collection/immutable/VectorPointer;III)V
const #424 = Method	#34.#423;	//  scala/collection/immutable/VectorPointer$class.gotoFreshPosWritable1:(Lscala/collection/immutable/VectorPointer;III)V
const #425 = Asciz	oldIndex;
const #426 = Asciz	newIndex;
const #427 = Asciz	xor;
const #428 = Asciz	gotoFreshPosWritable0;
const #429 = NameAndType	#428:#422;//  gotoFreshPosWritable0:(Lscala/collection/immutable/VectorPointer;III)V
const #430 = Method	#34.#429;	//  scala/collection/immutable/VectorPointer$class.gotoFreshPosWritable0:(Lscala/collection/immutable/VectorPointer;III)V
const #431 = Asciz	copyRange;
const #432 = Asciz	([Ljava/lang/Object;II)[Ljava/lang/Object;;
const #433 = Asciz	(Lscala/collection/immutable/VectorPointer;[Ljava/lang/Object;II)[Ljava/lang/Object;;
const #434 = NameAndType	#431:#433;//  copyRange:(Lscala/collection/immutable/VectorPointer;[Ljava/lang/Object;II)[Ljava/lang/Object;
const #435 = Method	#34.#434;	//  scala/collection/immutable/VectorPointer$class.copyRange:(Lscala/collection/immutable/VectorPointer;[Ljava/lang/Object;II)[Ljava/lang/Object;
const #436 = Asciz	array;
const #437 = Asciz	oldLeft;
const #438 = Asciz	newLeft;
const #439 = Asciz	gotoPosWritable1;
const #440 = NameAndType	#439:#422;//  gotoPosWritable1:(Lscala/collection/immutable/VectorPointer;III)V
const #441 = Method	#34.#440;	//  scala/collection/immutable/VectorPointer$class.gotoPosWritable1:(Lscala/collection/immutable/VectorPointer;III)V
const #442 = Asciz	gotoPosWritable0;
const #443 = Asciz	(Lscala/collection/immutable/VectorPointer;II)V;
const #444 = NameAndType	#442:#443;//  gotoPosWritable0:(Lscala/collection/immutable/VectorPointer;II)V
const #445 = Method	#34.#444;	//  scala/collection/immutable/VectorPointer$class.gotoPosWritable0:(Lscala/collection/immutable/VectorPointer;II)V
const #446 = Asciz	stabilize;
const #447 = Asciz	(Lscala/collection/immutable/VectorPointer;I)V;
const #448 = NameAndType	#446:#447;//  stabilize:(Lscala/collection/immutable/VectorPointer;I)V
const #449 = Method	#34.#448;	//  scala/collection/immutable/VectorPointer$class.stabilize:(Lscala/collection/immutable/VectorPointer;I)V
const #450 = Asciz	index;
const #451 = Asciz	nullSlotAndCopy;
const #452 = Asciz	([Ljava/lang/Object;I)[Ljava/lang/Object;;
const #453 = Asciz	(Lscala/collection/immutable/VectorPointer;[Ljava/lang/Object;I)[Ljava/lang/Object;;
const #454 = NameAndType	#451:#453;//  nullSlotAndCopy:(Lscala/collection/immutable/VectorPointer;[Ljava/lang/Object;I)[Ljava/lang/Object;
const #455 = Method	#34.#454;	//  scala/collection/immutable/VectorPointer$class.nullSlotAndCopy:(Lscala/collection/immutable/VectorPointer;[Ljava/lang/Object;I)[Ljava/lang/Object;
const #456 = Asciz	copyOf;
const #457 = Asciz	([Ljava/lang/Object;)[Ljava/lang/Object;;
const #458 = Asciz	(Lscala/collection/immutable/VectorPointer;[Ljava/lang/Object;)[Ljava/lang/Object;;
const #459 = NameAndType	#456:#458;//  copyOf:(Lscala/collection/immutable/VectorPointer;[Ljava/lang/Object;)[Ljava/lang/Object;
const #460 = Method	#34.#459;	//  scala/collection/immutable/VectorPointer$class.copyOf:(Lscala/collection/immutable/VectorPointer;[Ljava/lang/Object;)[Ljava/lang/Object;
const #461 = Asciz	a;
const #462 = Asciz	gotoNextBlockStartWritable;
const #463 = NameAndType	#462:#443;//  gotoNextBlockStartWritable:(Lscala/collection/immutable/VectorPointer;II)V
const #464 = Method	#34.#463;	//  scala/collection/immutable/VectorPointer$class.gotoNextBlockStartWritable:(Lscala/collection/immutable/VectorPointer;II)V
const #465 = NameAndType	#105:#443;//  gotoNextBlockStart:(Lscala/collection/immutable/VectorPointer;II)V
const #466 = Method	#34.#465;	//  scala/collection/immutable/VectorPointer$class.gotoNextBlockStart:(Lscala/collection/immutable/VectorPointer;II)V
const #467 = Asciz	gotoPos;
const #468 = NameAndType	#467:#443;//  gotoPos:(Lscala/collection/immutable/VectorPointer;II)V
const #469 = Method	#34.#468;	//  scala/collection/immutable/VectorPointer$class.gotoPos:(Lscala/collection/immutable/VectorPointer;II)V
const #470 = Asciz	getElem;
const #471 = Asciz	(II)Ljava/lang/Object;;
const #472 = Asciz	(Lscala/collection/immutable/VectorPointer;II)Ljava/lang/Object;;
const #473 = NameAndType	#470:#472;//  getElem:(Lscala/collection/immutable/VectorPointer;II)Ljava/lang/Object;
const #474 = Method	#34.#473;	//  scala/collection/immutable/VectorPointer$class.getElem:(Lscala/collection/immutable/VectorPointer;II)Ljava/lang/Object;
const #475 = Asciz	initFrom;
const #476 = Asciz	(Lscala/collection/immutable/VectorPointer;Lscala/collection/immutable/VectorPointer;I)V;
const #477 = NameAndType	#475:#476;//  initFrom:(Lscala/collection/immutable/VectorPointer;Lscala/collection/immutable/VectorPointer;I)V
const #478 = Method	#34.#477;	//  scala/collection/immutable/VectorPointer$class.initFrom:(Lscala/collection/immutable/VectorPointer;Lscala/collection/immutable/VectorPointer;I)V
const #479 = Asciz	Lscala/collection/immutable/VectorPointer;;
const #480 = Asciz	(Lscala/collection/immutable/VectorPointer;Lscala/collection/immutable/VectorPointer;)V;
const #481 = NameAndType	#475:#480;//  initFrom:(Lscala/collection/immutable/VectorPointer;Lscala/collection/immutable/VectorPointer;)V
const #482 = Method	#34.#481;	//  scala/collection/immutable/VectorPointer$class.initFrom:(Lscala/collection/immutable/VectorPointer;Lscala/collection/immutable/VectorPointer;)V
const #483 = Asciz	display5_$eq;
const #484 = Asciz	([Ljava/lang/Object;)V;
const #485 = NameAndType	#3:#4;//  display5:[Ljava/lang/Object;
const #486 = Field	#40.#485;	//  scala/collection/immutable/VectorIterator.display5:[Ljava/lang/Object;
const #487 = Asciz	()[Ljava/lang/Object;;
const #488 = Asciz	display4_$eq;
const #489 = NameAndType	#5:#4;//  display4:[Ljava/lang/Object;
const #490 = Field	#40.#489;	//  scala/collection/immutable/VectorIterator.display4:[Ljava/lang/Object;
const #491 = Asciz	display3_$eq;
const #492 = NameAndType	#6:#4;//  display3:[Ljava/lang/Object;
const #493 = Field	#40.#492;	//  scala/collection/immutable/VectorIterator.display3:[Ljava/lang/Object;
const #494 = Asciz	display2_$eq;
const #495 = NameAndType	#7:#4;//  display2:[Ljava/lang/Object;
const #496 = Field	#40.#495;	//  scala/collection/immutable/VectorIterator.display2:[Ljava/lang/Object;
const #497 = Asciz	display1_$eq;
const #498 = NameAndType	#8:#4;//  display1:[Ljava/lang/Object;
const #499 = Field	#40.#498;	//  scala/collection/immutable/VectorIterator.display1:[Ljava/lang/Object;
const #500 = Asciz	display0_$eq;
const #501 = Asciz	depth_$eq;
const #502 = NameAndType	#10:#11;//  depth:I
const #503 = Field	#40.#502;	//  scala/collection/immutable/VectorIterator.depth:I
const #504 = Asciz	<A:Ljava/lang/Object;>Ljava/lang/Object;Lscala/collection/Iterator<TA;>;Lscala/collection/immutable/VectorPointer<TA;>;Lscala/ScalaObject;;
const #505 = Asciz	ScalaSig;
const #506 = Asciz	InnerClasses;
const #507 = Asciz	scala/collection/Iterator$WithFilter;
const #508 = class	#507;	//  scala/collection/Iterator$WithFilter
const #509 = Asciz	scala/collection/Iterator;
const #510 = class	#509;	//  scala/collection/Iterator
const #511 = Asciz	WithFilter;
const #512 = Asciz	scala/collection/Iterator$GroupedIterator;
const #513 = class	#512;	//  scala/collection/Iterator$GroupedIterator
const #514 = Asciz	GroupedIterator;
const #515 = Asciz	scala/ScalaObject;
const #516 = class	#515;	//  scala/ScalaObject

{
public scala.collection.immutable.VectorIterator(int, int);
  Code:
   Stack=4, Locals=3, Args_size=3
   0:	aload_0
   1:	invokespecial	#26; //Method java/lang/Object."<init>":()V
   4:	aload_0
   5:	invokestatic	#32; //Method scala/collection/Iterator$class.$init$:(Lscala/collection/Iterator;)V
   8:	aload_0
   9:	invokestatic	#37; //Method scala/collection/immutable/VectorPointer$class.$init$:(Lscala/collection/immutable/VectorPointer;)V
   12:	aload_0
   13:	iload_1
   14:	ldc	#38; //int 31
   16:	iconst_m1
   17:	ixor
   18:	iand
   19:	putfield	#42; //Field blockIndex:I
   22:	aload_0
   23:	iload_1
   24:	ldc	#38; //int 31
   26:	iand
   27:	putfield	#44; //Field lo:I
   30:	aload_0
   31:	iload_2
   32:	putfield	#46; //Field endIndex:I
   35:	aload_0
   36:	getstatic	#52; //Field scala/math/package$.MODULE$:Lscala/math/package$;
   39:	aload_0
   40:	invokespecial	#55; //Method endIndex:()I
   43:	aload_0
   44:	invokespecial	#57; //Method blockIndex:()I
   47:	isub
   48:	ldc	#58; //int 32
   50:	invokeinterface	#64,  3; //InterfaceMethod scala/MathCommon.min:(II)I
   55:	putfield	#66; //Field endLo:I
   58:	aload_0
   59:	aload_0
   60:	invokespecial	#57; //Method blockIndex:()I
   63:	aload_0
   64:	invokespecial	#68; //Method lo:()I
   67:	iadd
   68:	aload_0
   69:	invokespecial	#55; //Method endIndex:()I
   72:	if_icmpge	79
   75:	iconst_1
   76:	goto	80
   79:	iconst_0
   80:	putfield	#70; //Field _hasNext:Z
   83:	return
  LineNumberTable: 
   line 561: 0
   line 563: 12
   line 564: 22
   line 565: 30
   line 567: 35
   line 571: 58

  LocalVariableTable: 
   Start  Length  Slot  Name   Signature
   0      84      0    this       Lscala/collection/immutable/VectorIterator;
   0      84      1    _startIndex       I
   0      84      2    _endIndex       I

  Signature: length = 0x2
   00 13 

public void foreach0(scala.Function1);
  Code:
   Stack=2, Locals=2, Args_size=2
   0:	aload_0
   1:	invokespecial	#81; //Method _hasNext:()Z
   4:	ifeq	21
   7:	aload_1
   8:	aload_0
   9:	invokevirtual	#85; //Method next:()Ljava/lang/Object;
   12:	invokeinterface	#91,  2; //InterfaceMethod scala/Function1.apply:(Ljava/lang/Object;)Ljava/lang/Object;
   17:	pop
   18:	goto	0
   21:	return
  LineNumberTable: 
   line 599: 0

  LocalVariableTable: 
   Start  Length  Slot  Name   Signature
   0      22      0    this       Lscala/collection/immutable/VectorIterator;
   0      22      1    f       Lscala/Function1;

  Signature: length = 0x2
   00 5E 

public java.lang.Object next();
  Code:
   Stack=4, Locals=6, Args_size=1
   0:	aload_0
   1:	invokespecial	#81; //Method _hasNext:()Z
   4:	ifeq	126
   7:	aload_0
   8:	getfield	#96; //Field display0:[Ljava/lang/Object;
   11:	aload_0
   12:	invokespecial	#68; //Method lo:()I
   15:	aaload
   16:	astore	5
   18:	aload_0
   19:	aload_0
   20:	invokespecial	#68; //Method lo:()I
   23:	iconst_1
   24:	iadd
   25:	invokespecial	#100; //Method lo_$eq:(I)V
   28:	aload_0
   29:	invokespecial	#68; //Method lo:()I
   32:	aload_0
   33:	invokespecial	#102; //Method endLo:()I
   36:	if_icmpne	123
   39:	aload_0
   40:	invokespecial	#57; //Method blockIndex:()I
   43:	aload_0
   44:	invokespecial	#68; //Method lo:()I
   47:	iadd
   48:	aload_0
   49:	invokespecial	#55; //Method endIndex:()I
   52:	if_icmpge	118
   55:	aload_0
   56:	invokespecial	#57; //Method blockIndex:()I
   59:	ldc	#58; //int 32
   61:	iadd
   62:	istore_1
   63:	aload_0
   64:	iload_1
   65:	aload_0
   66:	invokespecial	#57; //Method blockIndex:()I
   69:	iload_1
   70:	ixor
   71:	invokeinterface	#107,  3; //InterfaceMethod scala/collection/immutable/VectorPointer.gotoNextBlockStart:(II)V
   76:	aload_0
   77:	iload_1
   78:	invokespecial	#110; //Method blockIndex_$eq:(I)V
   81:	aload_0
   82:	getstatic	#52; //Field scala/math/package$.MODULE$:Lscala/math/package$;
   85:	aload_0
   86:	invokespecial	#55; //Method endIndex:()I
   89:	aload_0
   90:	invokespecial	#57; //Method blockIndex:()I
   93:	isub
   94:	ldc	#58; //int 32
   96:	istore	4
   98:	istore_3
   99:	astore_2
   100:	aload_2
   101:	iload_3
   102:	iload	4
   104:	invokestatic	#115; //Method scala/MathCommon$class.min:(Lscala/MathCommon;II)I
   107:	invokespecial	#118; //Method endLo_$eq:(I)V
   110:	aload_0
   111:	iconst_0
   112:	invokespecial	#100; //Method lo_$eq:(I)V
   115:	goto	123
   118:	aload_0
   119:	iconst_0
   120:	invokespecial	#122; //Method _hasNext_$eq:(Z)V
   123:	aload	5
   125:	areturn
   126:	new	#124; //class java/util/NoSuchElementException
   129:	dup
   130:	ldc	#126; //String reached iterator end
   132:	invokespecial	#129; //Method java/util/NoSuchElementException."<init>":(Ljava/lang/String;)V
   135:	athrow
  LineNumberTable: 
   line 574: 0
   line 576: 7
   line 577: 18
   line 579: 28
   line 580: 39
   line 581: 55
   line 582: 63
   line 584: 76
   line 585: 81
   line 586: 110
   line 588: 118
   line 592: 123
   line 574: 126

  LocalVariableTable: 
   Start  Length  Slot  Name   Signature
   0      136      0    this       Lscala/collection/immutable/VectorIterator;
   63      52      1    newBlockIndex       I
   18      107      5    res       Ljava/lang/Object;

  Signature: length = 0x2
   00 FFFFFF85 

public boolean hasNext();
  Code:
   Stack=1, Locals=1, Args_size=1
   0:	aload_0
   1:	invokespecial	#81; //Method _hasNext:()Z
   4:	ireturn
  LineNumberTable: 
   line 569: 0


public int sliding$default$2();
  Code:
   Stack=1, Locals=1, Args_size=1
   0:	aload_0
   1:	invokestatic	#139; //Method scala/collection/Iterator$class.sliding$default$2:(Lscala/collection/Iterator;)I
   4:	ireturn
  LineNumberTable: 
   line 561: 0


public void readInto(java.lang.Object);
  Code:
   Stack=2, Locals=2, Args_size=2
   0:	aload_0
   1:	aload_1
   2:	invokestatic	#144; //Method scala/collection/Iterator$class.readInto:(Lscala/collection/Iterator;Ljava/lang/Object;)V
   5:	return
  LineNumberTable: 
   line 561: 0

  LocalVariableTable: 
   Start  Length  Slot  Name   Signature
   0      6      0    this       Lscala/collection/immutable/VectorIterator;
   0      6      1    xs       Ljava/lang/Object;


public void readInto(java.lang.Object, int);
  Code:
   Stack=3, Locals=3, Args_size=3
   0:	aload_0
   1:	aload_1
   2:	iload_2
   3:	invokestatic	#149; //Method scala/collection/Iterator$class.readInto:(Lscala/collection/Iterator;Ljava/lang/Object;I)V
   6:	return
  LineNumberTable: 
   line 561: 0

  LocalVariableTable: 
   Start  Length  Slot  Name   Signature
   0      7      0    this       Lscala/collection/immutable/VectorIterator;
   0      7      1    xs       Ljava/lang/Object;
   0      7      2    start       I


public void readInto(java.lang.Object, int, int);
  Code:
   Stack=4, Locals=4, Args_size=4
   0:	aload_0
   1:	aload_1
   2:	iload_2
   3:	iload_3
   4:	invokestatic	#154; //Method scala/collection/Iterator$class.readInto:(Lscala/collection/Iterator;Ljava/lang/Object;II)V
   7:	return
  LineNumberTable: 
   line 561: 0

  LocalVariableTable: 
   Start  Length  Slot  Name   Signature
   0      8      0    this       Lscala/collection/immutable/VectorIterator;
   0      8      1    xs       Ljava/lang/Object;
   0      8      2    start       I
   0      8      3    sz       I


public java.lang.Object counted();
  Code:
   Stack=1, Locals=1, Args_size=1
   0:	aload_0
   1:	invokestatic	#159; //Method scala/collection/Iterator$class.counted:(Lscala/collection/Iterator;)Ljava/lang/Object;
   4:	areturn
  LineNumberTable: 
   line 561: 0


public scala.collection.Seq collect();
  Code:
   Stack=1, Locals=1, Args_size=1
   0:	aload_0
   1:	invokestatic	#164; //Method scala/collection/Iterator$class.collect:(Lscala/collection/Iterator;)Lscala/collection/Seq;
   4:	areturn
  LineNumberTable: 
   line 561: 0


public int findIndexOf(scala.Function1);
  Code:
   Stack=2, Locals=2, Args_size=2
   0:	aload_0
   1:	aload_1
   2:	invokestatic	#169; //Method scala/collection/Iterator$class.findIndexOf:(Lscala/collection/Iterator;Lscala/Function1;)I
   5:	ireturn
  LineNumberTable: 
   line 561: 0

  LocalVariableTable: 
   Start  Length  Slot  Name   Signature
   0      6      0    this       Lscala/collection/immutable/VectorIterator;
   0      6      1    p       Lscala/Function1;


public scala.collection.Iterator append(scala.collection.Iterator);
  Code:
   Stack=2, Locals=2, Args_size=2
   0:	aload_0
   1:	aload_1
   2:	invokestatic	#175; //Method scala/collection/Iterator$class.append:(Lscala/collection/Iterator;Lscala/collection/Iterator;)Lscala/collection/Iterator;
   5:	areturn
  LineNumberTable: 
   line 561: 0

  LocalVariableTable: 
   Start  Length  Slot  Name   Signature
   0      6      0    this       Lscala/collection/immutable/VectorIterator;
   0      6      1    that       Lscala/collection/Iterator;


public java.lang.String toString();
  Code:
   Stack=1, Locals=1, Args_size=1
   0:	aload_0
   1:	invokestatic	#182; //Method scala/collection/Iterator$class.toString:(Lscala/collection/Iterator;)Ljava/lang/String;
   4:	areturn
  LineNumberTable: 
   line 561: 0


public scala.collection.mutable.StringBuilder addString(scala.collection.mutable.StringBuilder);
  Code:
   Stack=2, Locals=2, Args_size=2
   0:	aload_0
   1:	aload_1
   2:	invokestatic	#187; //Method scala/collection/Iterator$class.addString:(Lscala/collection/Iterator;Lscala/collection/mutable/StringBuilder;)Lscala/collection/mutable/StringBuilder;
   5:	areturn
  LineNumberTable: 
   line 561: 0

  LocalVariableTable: 
   Start  Length  Slot  Name   Signature
   0      6      0    this       Lscala/collection/immutable/VectorIterator;
   0      6      1    buf       Lscala/collection/mutable/StringBuilder;


public scala.collection.mutable.StringBuilder addString(scala.collection.mutable.StringBuilder, java.lang.String);
  Code:
   Stack=3, Locals=3, Args_size=3
   0:	aload_0
   1:	aload_1
   2:	aload_2
   3:	invokestatic	#193; //Method scala/collection/Iterator$class.addString:(Lscala/collection/Iterator;Lscala/collection/mutable/StringBuilder;Ljava/lang/String;)Lscala/collection/mutable/StringBuilder;
   6:	areturn
  LineNumberTable: 
   line 561: 0

  LocalVariableTable: 
   Start  Length  Slot  Name   Signature
   0      7      0    this       Lscala/collection/immutable/VectorIterator;
   0      7      1    buf       Lscala/collection/mutable/StringBuilder;
   0      7      2    sep       Ljava/lang/String;


public scala.collection.mutable.StringBuilder addString(scala.collection.mutable.StringBuilder, java.lang.String, java.lang.String, java.lang.String);
  Code:
   Stack=5, Locals=5, Args_size=5
   0:	aload_0
   1:	aload_1
   2:	aload_2
   3:	aload_3
   4:	aload	4
   6:	invokestatic	#199; //Method scala/collection/Iterator$class.addString:(Lscala/collection/Iterator;Lscala/collection/mutable/StringBuilder;Ljava/lang/String;Ljava/lang/String;Ljava/lang/String;)Lscala/collection/mutable/StringBuilder;
   9:	areturn
  LineNumberTable: 
   line 561: 0

  LocalVariableTable: 
   Start  Length  Slot  Name   Signature
   0      10      0    this       Lscala/collection/immutable/VectorIterator;
   0      10      1    buf       Lscala/collection/mutable/StringBuilder;
   0      10      2    start       Ljava/lang/String;
   0      10      3    sep       Ljava/lang/String;
   0      10      4    end       Ljava/lang/String;


public java.lang.String mkString();
  Code:
   Stack=1, Locals=1, Args_size=1
   0:	aload_0
   1:	invokestatic	#203; //Method scala/collection/Iterator$class.mkString:(Lscala/collection/Iterator;)Ljava/lang/String;
   4:	areturn
  LineNumberTable: 
   line 561: 0


public java.lang.String mkString(java.lang.String);
  Code:
   Stack=2, Locals=2, Args_size=2
   0:	aload_0
   1:	aload_1
   2:	invokestatic	#207; //Method scala/collection/Iterator$class.mkString:(Lscala/collection/Iterator;Ljava/lang/String;)Ljava/lang/String;
   5:	areturn
  LineNumberTable: 
   line 561: 0

  LocalVariableTable: 
   Start  Length  Slot  Name   Signature
   0      6      0    this       Lscala/collection/immutable/VectorIterator;
   0      6      1    sep       Ljava/lang/String;


public java.lang.String mkString(java.lang.String, java.lang.String, java.lang.String);
  Code:
   Stack=4, Locals=4, Args_size=4
   0:	aload_0
   1:	aload_1
   2:	aload_2
   3:	aload_3
   4:	invokestatic	#211; //Method scala/collection/Iterator$class.mkString:(Lscala/collection/Iterator;Ljava/lang/String;Ljava/lang/String;Ljava/lang/String;)Ljava/lang/String;
   7:	areturn
  LineNumberTable: 
   line 561: 0

  LocalVariableTable: 
   Start  Length  Slot  Name   Signature
   0      8      0    this       Lscala/collection/immutable/VectorIterator;
   0      8      1    start       Ljava/lang/String;
   0      8      2    sep       Ljava/lang/String;
   0      8      3    end       Ljava/lang/String;


public boolean sameElements(scala.collection.Iterator);
  Code:
   Stack=2, Locals=2, Args_size=2
   0:	aload_0
   1:	aload_1
   2:	invokestatic	#216; //Method scala/collection/Iterator$class.sameElements:(Lscala/collection/Iterator;Lscala/collection/Iterator;)Z
   5:	ireturn
  LineNumberTable: 
   line 561: 0

  LocalVariableTable: 
   Start  Length  Slot  Name   Signature
   0      6      0    this       Lscala/collection/immutable/VectorIterator;
   0      6      1    that       Lscala/collection/Iterator;


public scala.collection.Seq toSeq();
  Code:
   Stack=1, Locals=1, Args_size=1
   0:	aload_0
   1:	invokestatic	#219; //Method scala/collection/Iterator$class.toSeq:(Lscala/collection/Iterator;)Lscala/collection/Seq;
   4:	areturn
  LineNumberTable: 
   line 561: 0


public scala.collection.immutable.Stream toStream();
  Code:
   Stack=1, Locals=1, Args_size=1
   0:	aload_0
   1:	invokestatic	#224; //Method scala/collection/Iterator$class.toStream:(Lscala/collection/Iterator;)Lscala/collection/immutable/Stream;
   4:	areturn
  LineNumberTable: 
   line 561: 0


public scala.collection.immutable.List toList();
  Code:
   Stack=1, Locals=1, Args_size=1
   0:	aload_0
   1:	invokestatic	#229; //Method scala/collection/Iterator$class.toList:(Lscala/collection/Iterator;)Lscala/collection/immutable/List;
   4:	areturn
  LineNumberTable: 
   line 561: 0


public void copyToBuffer(scala.collection.mutable.Buffer);
  Code:
   Stack=2, Locals=2, Args_size=2
   0:	aload_0
   1:	aload_1
   2:	invokestatic	#234; //Method scala/collection/Iterator$class.copyToBuffer:(Lscala/collection/Iterator;Lscala/collection/mutable/Buffer;)V
   5:	return
  LineNumberTable: 
   line 561: 0

  LocalVariableTable: 
   Start  Length  Slot  Name   Signature
   0      6      0    this       Lscala/collection/immutable/VectorIterator;
   0      6      1    dest       Lscala/collection/mutable/Buffer;


public void copyToArray(java.lang.Object);
  Code:
   Stack=2, Locals=2, Args_size=2
   0:	aload_0
   1:	aload_1
   2:	invokestatic	#239; //Method scala/collection/Iterator$class.copyToArray:(Lscala/collection/Iterator;Ljava/lang/Object;)V
   5:	return
  LineNumberTable: 
   line 561: 0

  LocalVariableTable: 
   Start  Length  Slot  Name   Signature
   0      6      0    this       Lscala/collection/immutable/VectorIterator;
   0      6      1    xs       Ljava/lang/Object;


public void copyToArray(java.lang.Object, int);
  Code:
   Stack=3, Locals=3, Args_size=3
   0:	aload_0
   1:	aload_1
   2:	iload_2
   3:	invokestatic	#241; //Method scala/collection/Iterator$class.copyToArray:(Lscala/collection/Iterator;Ljava/lang/Object;I)V
   6:	return
  LineNumberTable: 
   line 561: 0

  LocalVariableTable: 
   Start  Length  Slot  Name   Signature
   0      7      0    this       Lscala/collection/immutable/VectorIterator;
   0      7      1    xs       Ljava/lang/Object;
   0      7      2    start       I


public void copyToArray(java.lang.Object, int, int);
  Code:
   Stack=4, Locals=4, Args_size=4
   0:	aload_0
   1:	aload_1
   2:	iload_2
   3:	iload_3
   4:	invokestatic	#243; //Method scala/collection/Iterator$class.copyToArray:(Lscala/collection/Iterator;Ljava/lang/Object;II)V
   7:	return
  LineNumberTable: 
   line 561: 0

  LocalVariableTable: 
   Start  Length  Slot  Name   Signature
   0      8      0    this       Lscala/collection/immutable/VectorIterator;
   0      8      1    xs       Ljava/lang/Object;
   0      8      2    start       I
   0      8      3    len       I


public java.lang.Object patch(int, scala.collection.Iterator, int);
  Code:
   Stack=4, Locals=4, Args_size=4
   0:	aload_0
   1:	iload_1
   2:	aload_2
   3:	iload_3
   4:	invokestatic	#249; //Method scala/collection/Iterator$class.patch:(Lscala/collection/Iterator;ILscala/collection/Iterator;I)Ljava/lang/Object;
   7:	areturn
  LineNumberTable: 
   line 561: 0

  LocalVariableTable: 
   Start  Length  Slot  Name   Signature
   0      8      0    this       Lscala/collection/immutable/VectorIterator;
   0      8      1    from       I
   0      8      2    patchElems       Lscala/collection/Iterator;
   0      8      3    replaced       I


public scala.Tuple2 duplicate();
  Code:
   Stack=1, Locals=1, Args_size=1
   0:	aload_0
   1:	invokestatic	#257; //Method scala/collection/Iterator$class.duplicate:(Lscala/collection/Iterator;)Lscala/Tuple2;
   4:	areturn
  LineNumberTable: 
   line 561: 0


public int length();
  Code:
   Stack=1, Locals=1, Args_size=1
   0:	aload_0
   1:	invokestatic	#260; //Method scala/collection/Iterator$class.length:(Lscala/collection/Iterator;)I
   4:	ireturn
  LineNumberTable: 
   line 561: 0


public scala.collection.Iterator$GroupedIterator sliding(int, int);
  Code:
   Stack=3, Locals=3, Args_size=3
   0:	aload_0
   1:	iload_1
   2:	iload_2
   3:	invokestatic	#265; //Method scala/collection/Iterator$class.sliding:(Lscala/collection/Iterator;II)Lscala/collection/Iterator$GroupedIterator;
   6:	areturn
  LineNumberTable: 
   line 561: 0

  LocalVariableTable: 
   Start  Length  Slot  Name   Signature
   0      7      0    this       Lscala/collection/immutable/VectorIterator;
   0      7      1    size       I
   0      7      2    step       I

  Signature: length = 0x2
   01 06 

public scala.collection.Iterator$GroupedIterator grouped(int);
  Code:
   Stack=2, Locals=2, Args_size=2
   0:	aload_0
   1:	iload_1
   2:	invokestatic	#272; //Method scala/collection/Iterator$class.grouped:(Lscala/collection/Iterator;I)Lscala/collection/Iterator$GroupedIterator;
   5:	areturn
  LineNumberTable: 
   line 561: 0

  LocalVariableTable: 
   Start  Length  Slot  Name   Signature
   0      6      0    this       Lscala/collection/immutable/VectorIterator;
   0      6      1    size       I

  Signature: length = 0x2
   01 0D 

public java.lang.Object buffered();
  Code:
   Stack=1, Locals=1, Args_size=1
   0:	aload_0
   1:	invokestatic	#275; //Method scala/collection/Iterator$class.buffered:(Lscala/collection/Iterator;)Ljava/lang/Object;
   4:	areturn
  LineNumberTable: 
   line 561: 0


public scala.Option reduceRightOption(scala.Function2);
  Code:
   Stack=2, Locals=2, Args_size=2
   0:	aload_0
   1:	aload_1
   2:	invokestatic	#280; //Method scala/collection/Iterator$class.reduceRightOption:(Lscala/collection/Iterator;Lscala/Function2;)Lscala/Option;
   5:	areturn
  LineNumberTable: 
   line 561: 0

  LocalVariableTable: 
   Start  Length  Slot  Name   Signature
   0      6      0    this       Lscala/collection/immutable/VectorIterator;
   0      6      1    op       Lscala/Function2;


public scala.Option reduceLeftOption(scala.Function2);
  Code:
   Stack=2, Locals=2, Args_size=2
   0:	aload_0
   1:	aload_1
   2:	invokestatic	#285; //Method scala/collection/Iterator$class.reduceLeftOption:(Lscala/collection/Iterator;Lscala/Function2;)Lscala/Option;
   5:	areturn
  LineNumberTable: 
   line 561: 0

  LocalVariableTable: 
   Start  Length  Slot  Name   Signature
   0      6      0    this       Lscala/collection/immutable/VectorIterator;
   0      6      1    op       Lscala/Function2;


public java.lang.Object reduceRight(scala.Function2);
  Code:
   Stack=2, Locals=2, Args_size=2
   0:	aload_0
   1:	aload_1
   2:	invokestatic	#290; //Method scala/collection/Iterator$class.reduceRight:(Lscala/collection/Iterator;Lscala/Function2;)Ljava/lang/Object;
   5:	areturn
  LineNumberTable: 
   line 561: 0

  LocalVariableTable: 
   Start  Length  Slot  Name   Signature
   0      6      0    this       Lscala/collection/immutable/VectorIterator;
   0      6      1    op       Lscala/Function2;


public java.lang.Object reduceLeft(scala.Function2);
  Code:
   Stack=2, Locals=2, Args_size=2
   0:	aload_0
   1:	aload_1
   2:	invokestatic	#293; //Method scala/collection/Iterator$class.reduceLeft:(Lscala/collection/Iterator;Lscala/Function2;)Ljava/lang/Object;
   5:	areturn
  LineNumberTable: 
   line 561: 0

  LocalVariableTable: 
   Start  Length  Slot  Name   Signature
   0      6      0    this       Lscala/collection/immutable/VectorIterator;
   0      6      1    op       Lscala/Function2;


public java.lang.Object $colon$bslash(java.lang.Object, scala.Function2);
  Code:
   Stack=3, Locals=3, Args_size=3
   0:	aload_0
   1:	aload_1
   2:	aload_2
   3:	invokestatic	#298; //Method scala/collection/Iterator$class.$colon$bslash:(Lscala/collection/Iterator;Ljava/lang/Object;Lscala/Function2;)Ljava/lang/Object;
   6:	areturn
  LineNumberTable: 
   line 561: 0

  LocalVariableTable: 
   Start  Length  Slot  Name   Signature
   0      7      0    this       Lscala/collection/immutable/VectorIterator;
   0      7      1    z       Ljava/lang/Object;
   0      7      2    op       Lscala/Function2;


public java.lang.Object $div$colon(java.lang.Object, scala.Function2);
  Code:
   Stack=3, Locals=3, Args_size=3
   0:	aload_0
   1:	aload_1
   2:	aload_2
   3:	invokestatic	#302; //Method scala/collection/Iterator$class.$div$colon:(Lscala/collection/Iterator;Ljava/lang/Object;Lscala/Function2;)Ljava/lang/Object;
   6:	areturn
  LineNumberTable: 
   line 561: 0

  LocalVariableTable: 
   Start  Length  Slot  Name   Signature
   0      7      0    this       Lscala/collection/immutable/VectorIterator;
   0      7      1    z       Ljava/lang/Object;
   0      7      2    op       Lscala/Function2;


public java.lang.Object foldRight(java.lang.Object, scala.Function2);
  Code:
   Stack=3, Locals=3, Args_size=3
   0:	aload_0
   1:	aload_1
   2:	aload_2
   3:	invokestatic	#305; //Method scala/collection/Iterator$class.foldRight:(Lscala/collection/Iterator;Ljava/lang/Object;Lscala/Function2;)Ljava/lang/Object;
   6:	areturn
  LineNumberTable: 
   line 561: 0

  LocalVariableTable: 
   Start  Length  Slot  Name   Signature
   0      7      0    this       Lscala/collection/immutable/VectorIterator;
   0      7      1    z       Ljava/lang/Object;
   0      7      2    op       Lscala/Function2;


public java.lang.Object foldLeft(java.lang.Object, scala.Function2);
  Code:
   Stack=3, Locals=3, Args_size=3
   0:	aload_0
   1:	aload_1
   2:	aload_2
   3:	invokestatic	#308; //Method scala/collection/Iterator$class.foldLeft:(Lscala/collection/Iterator;Ljava/lang/Object;Lscala/Function2;)Ljava/lang/Object;
   6:	areturn
  LineNumberTable: 
   line 561: 0

  LocalVariableTable: 
   Start  Length  Slot  Name   Signature
   0      7      0    this       Lscala/collection/immutable/VectorIterator;
   0      7      1    z       Ljava/lang/Object;
   0      7      2    op       Lscala/Function2;


public int indexOf(java.lang.Object);
  Code:
   Stack=2, Locals=2, Args_size=2
   0:	aload_0
   1:	aload_1
   2:	invokestatic	#313; //Method scala/collection/Iterator$class.indexOf:(Lscala/collection/Iterator;Ljava/lang/Object;)I
   5:	ireturn
  LineNumberTable: 
   line 561: 0

  LocalVariableTable: 
   Start  Length  Slot  Name   Signature
   0      6      0    this       Lscala/collection/immutable/VectorIterator;
   0      6      1    elem       Ljava/lang/Object;


public int indexWhere(scala.Function1);
  Code:
   Stack=2, Locals=2, Args_size=2
   0:	aload_0
   1:	aload_1
   2:	invokestatic	#317; //Method scala/collection/Iterator$class.indexWhere:(Lscala/collection/Iterator;Lscala/Function1;)I
   5:	ireturn
  LineNumberTable: 
   line 561: 0

  LocalVariableTable: 
   Start  Length  Slot  Name   Signature
   0      6      0    this       Lscala/collection/immutable/VectorIterator;
   0      6      1    p       Lscala/Function1;


public scala.Option find(scala.Function1);
  Code:
   Stack=2, Locals=2, Args_size=2
   0:	aload_0
   1:	aload_1
   2:	invokestatic	#322; //Method scala/collection/Iterator$class.find:(Lscala/collection/Iterator;Lscala/Function1;)Lscala/Option;
   5:	areturn
  LineNumberTable: 
   line 561: 0

  LocalVariableTable: 
   Start  Length  Slot  Name   Signature
   0      6      0    this       Lscala/collection/immutable/VectorIterator;
   0      6      1    p       Lscala/Function1;


public boolean contains(java.lang.Object);
  Code:
   Stack=2, Locals=2, Args_size=2
   0:	aload_0
   1:	aload_1
   2:	invokestatic	#327; //Method scala/collection/Iterator$class.contains:(Lscala/collection/Iterator;Ljava/lang/Object;)Z
   5:	ireturn
  LineNumberTable: 
   line 561: 0

  LocalVariableTable: 
   Start  Length  Slot  Name   Signature
   0      6      0    this       Lscala/collection/immutable/VectorIterator;
   0      6      1    elem       Ljava/lang/Object;


public boolean exists(scala.Function1);
  Code:
   Stack=2, Locals=2, Args_size=2
   0:	aload_0
   1:	aload_1
   2:	invokestatic	#332; //Method scala/collection/Iterator$class.exists:(Lscala/collection/Iterator;Lscala/Function1;)Z
   5:	ireturn
  LineNumberTable: 
   line 561: 0

  LocalVariableTable: 
   Start  Length  Slot  Name   Signature
   0      6      0    this       Lscala/collection/immutable/VectorIterator;
   0      6      1    p       Lscala/Function1;


public boolean forall(scala.Function1);
  Code:
   Stack=2, Locals=2, Args_size=2
   0:	aload_0
   1:	aload_1
   2:	invokestatic	#335; //Method scala/collection/Iterator$class.forall:(Lscala/collection/Iterator;Lscala/Function1;)Z
   5:	ireturn
  LineNumberTable: 
   line 561: 0

  LocalVariableTable: 
   Start  Length  Slot  Name   Signature
   0      6      0    this       Lscala/collection/immutable/VectorIterator;
   0      6      1    p       Lscala/Function1;


public void foreach(scala.Function1);
  Code:
   Stack=2, Locals=2, Args_size=2
   0:	aload_0
   1:	aload_1
   2:	invokestatic	#339; //Method scala/collection/Iterator$class.foreach:(Lscala/collection/Iterator;Lscala/Function1;)V
   5:	return
  LineNumberTable: 
   line 561: 0

  LocalVariableTable: 
   Start  Length  Slot  Name   Signature
   0      6      0    this       Lscala/collection/immutable/VectorIterator;
   0      6      1    f       Lscala/Function1;


public java.lang.Object zipAll(scala.collection.Iterator, java.lang.Object, java.lang.Object);
  Code:
   Stack=4, Locals=4, Args_size=4
   0:	aload_0
   1:	aload_1
   2:	aload_2
   3:	aload_3
   4:	invokestatic	#344; //Method scala/collection/Iterator$class.zipAll:(Lscala/collection/Iterator;Lscala/collection/Iterator;Ljava/lang/Object;Ljava/lang/Object;)Ljava/lang/Object;
   7:	areturn
  LineNumberTable: 
   line 561: 0

  LocalVariableTable: 
   Start  Length  Slot  Name   Signature
   0      8      0    this       Lscala/collection/immutable/VectorIterator;
   0      8      1    that       Lscala/collection/Iterator;
   0      8      2    thisElem       Ljava/lang/Object;
   0      8      3    thatElem       Ljava/lang/Object;


public java.lang.Object zipWithIndex();
  Code:
   Stack=1, Locals=1, Args_size=1
   0:	aload_0
   1:	invokestatic	#349; //Method scala/collection/Iterator$class.zipWithIndex:(Lscala/collection/Iterator;)Ljava/lang/Object;
   4:	areturn
  LineNumberTable: 
   line 561: 0


public java.lang.Object padTo(int, java.lang.Object);
  Code:
   Stack=3, Locals=3, Args_size=3
   0:	aload_0
   1:	iload_1
   2:	aload_2
   3:	invokestatic	#354; //Method scala/collection/Iterator$class.padTo:(Lscala/collection/Iterator;ILjava/lang/Object;)Ljava/lang/Object;
   6:	areturn
  LineNumberTable: 
   line 561: 0

  LocalVariableTable: 
   Start  Length  Slot  Name   Signature
   0      7      0    this       Lscala/collection/immutable/VectorIterator;
   0      7      1    len       I
   0      7      2    elem       Ljava/lang/Object;


public java.lang.Object zip(scala.collection.Iterator);
  Code:
   Stack=2, Locals=2, Args_size=2
   0:	aload_0
   1:	aload_1
   2:	invokestatic	#358; //Method scala/collection/Iterator$class.zip:(Lscala/collection/Iterator;Lscala/collection/Iterator;)Ljava/lang/Object;
   5:	areturn
  LineNumberTable: 
   line 561: 0

  LocalVariableTable: 
   Start  Length  Slot  Name   Signature
   0      6      0    this       Lscala/collection/immutable/VectorIterator;
   0      6      1    that       Lscala/collection/Iterator;


public scala.collection.Iterator dropWhile(scala.Function1);
  Code:
   Stack=2, Locals=2, Args_size=2
   0:	aload_0
   1:	aload_1
   2:	invokestatic	#363; //Method scala/collection/Iterator$class.dropWhile:(Lscala/collection/Iterator;Lscala/Function1;)Lscala/collection/Iterator;
   5:	areturn
  LineNumberTable: 
   line 561: 0

  LocalVariableTable: 
   Start  Length  Slot  Name   Signature
   0      6      0    this       Lscala/collection/immutable/VectorIterator;
   0      6      1    p       Lscala/Function1;


public scala.Tuple2 partition(scala.Function1);
  Code:
   Stack=2, Locals=2, Args_size=2
   0:	aload_0
   1:	aload_1
   2:	invokestatic	#368; //Method scala/collection/Iterator$class.partition:(Lscala/collection/Iterator;Lscala/Function1;)Lscala/Tuple2;
   5:	areturn
  LineNumberTable: 
   line 561: 0

  LocalVariableTable: 
   Start  Length  Slot  Name   Signature
   0      6      0    this       Lscala/collection/immutable/VectorIterator;
   0      6      1    p       Lscala/Function1;


public scala.collection.Iterator takeWhile(scala.Function1);
  Code:
   Stack=2, Locals=2, Args_size=2
   0:	aload_0
   1:	aload_1
   2:	invokestatic	#371; //Method scala/collection/Iterator$class.takeWhile:(Lscala/collection/Iterator;Lscala/Function1;)Lscala/collection/Iterator;
   5:	areturn
  LineNumberTable: 
   line 561: 0

  LocalVariableTable: 
   Start  Length  Slot  Name   Signature
   0      6      0    this       Lscala/collection/immutable/VectorIterator;
   0      6      1    p       Lscala/Function1;


public scala.collection.Iterator partialMap(scala.PartialFunction);
  Code:
   Stack=2, Locals=2, Args_size=2
   0:	aload_0
   1:	aload_1
   2:	invokestatic	#376; //Method scala/collection/Iterator$class.partialMap:(Lscala/collection/Iterator;Lscala/PartialFunction;)Lscala/collection/Iterator;
   5:	areturn
  LineNumberTable: 
   line 561: 0

  LocalVariableTable: 
   Start  Length  Slot  Name   Signature
   0      6      0    this       Lscala/collection/immutable/VectorIterator;
   0      6      1    pf       Lscala/PartialFunction;


public scala.collection.Iterator filterNot(scala.Function1);
  Code:
   Stack=2, Locals=2, Args_size=2
   0:	aload_0
   1:	aload_1
   2:	invokestatic	#381; //Method scala/collection/Iterator$class.filterNot:(Lscala/collection/Iterator;Lscala/Function1;)Lscala/collection/Iterator;
   5:	areturn
  LineNumberTable: 
   line 561: 0

  LocalVariableTable: 
   Start  Length  Slot  Name   Signature
   0      6      0    this       Lscala/collection/immutable/VectorIterator;
   0      6      1    p       Lscala/Function1;


public scala.collection.Iterator$WithFilter withFilter(scala.Function1);
  Code:
   Stack=2, Locals=2, Args_size=2
   0:	aload_0
   1:	aload_1
   2:	invokestatic	#386; //Method scala/collection/Iterator$class.withFilter:(Lscala/collection/Iterator;Lscala/Function1;)Lscala/collection/Iterator$WithFilter;
   5:	areturn
  LineNumberTable: 
   line 561: 0

  LocalVariableTable: 
   Start  Length  Slot  Name   Signature
   0      6      0    this       Lscala/collection/immutable/VectorIterator;
   0      6      1    p       Lscala/Function1;

  Signature: length = 0x2
   01 7F 

public scala.collection.Iterator filter(scala.Function1);
  Code:
   Stack=2, Locals=2, Args_size=2
   0:	aload_0
   1:	aload_1
   2:	invokestatic	#389; //Method scala/collection/Iterator$class.filter:(Lscala/collection/Iterator;Lscala/Function1;)Lscala/collection/Iterator;
   5:	areturn
  LineNumberTable: 
   line 561: 0

  LocalVariableTable: 
   Start  Length  Slot  Name   Signature
   0      6      0    this       Lscala/collection/immutable/VectorIterator;
   0      6      1    p       Lscala/Function1;


public scala.collection.Iterator flatMap(scala.Function1);
  Code:
   Stack=2, Locals=2, Args_size=2
   0:	aload_0
   1:	aload_1
   2:	invokestatic	#392; //Method scala/collection/Iterator$class.flatMap:(Lscala/collection/Iterator;Lscala/Function1;)Lscala/collection/Iterator;
   5:	areturn
  LineNumberTable: 
   line 561: 0

  LocalVariableTable: 
   Start  Length  Slot  Name   Signature
   0      6      0    this       Lscala/collection/immutable/VectorIterator;
   0      6      1    f       Lscala/Function1;


public scala.collection.Iterator $plus$plus(scala.Function0);
  Code:
   Stack=2, Locals=2, Args_size=2
   0:	aload_0
   1:	aload_1
   2:	invokestatic	#397; //Method scala/collection/Iterator$class.$plus$plus:(Lscala/collection/Iterator;Lscala/Function0;)Lscala/collection/Iterator;
   5:	areturn
  LineNumberTable: 
   line 561: 0

  LocalVariableTable: 
   Start  Length  Slot  Name   Signature
   0      6      0    this       Lscala/collection/immutable/VectorIterator;
   0      6      1    that       Lscala/Function0;


public scala.collection.Iterator map(scala.Function1);
  Code:
   Stack=2, Locals=2, Args_size=2
   0:	aload_0
   1:	aload_1
   2:	invokestatic	#401; //Method scala/collection/Iterator$class.map:(Lscala/collection/Iterator;Lscala/Function1;)Lscala/collection/Iterator;
   5:	areturn
  LineNumberTable: 
   line 561: 0

  LocalVariableTable: 
   Start  Length  Slot  Name   Signature
   0      6      0    this       Lscala/collection/immutable/VectorIterator;
   0      6      1    f       Lscala/Function1;


public scala.collection.Iterator slice(int, int);
  Code:
   Stack=3, Locals=3, Args_size=3
   0:	aload_0
   1:	iload_1
   2:	iload_2
   3:	invokestatic	#406; //Method scala/collection/Iterator$class.slice:(Lscala/collection/Iterator;II)Lscala/collection/Iterator;
   6:	areturn
  LineNumberTable: 
   line 561: 0

  LocalVariableTable: 
   Start  Length  Slot  Name   Signature
   0      7      0    this       Lscala/collection/immutable/VectorIterator;
   0      7      1    from       I
   0      7      2    until       I


public scala.collection.Iterator drop(int);
  Code:
   Stack=2, Locals=2, Args_size=2
   0:	aload_0
   1:	iload_1
   2:	invokestatic	#412; //Method scala/collection/Iterator$class.drop:(Lscala/collection/Iterator;I)Lscala/collection/Iterator;
   5:	areturn
  LineNumberTable: 
   line 561: 0

  LocalVariableTable: 
   Start  Length  Slot  Name   Signature
   0      6      0    this       Lscala/collection/immutable/VectorIterator;
   0      6      1    n       I


public scala.collection.Iterator take(int);
  Code:
   Stack=2, Locals=2, Args_size=2
   0:	aload_0
   1:	iload_1
   2:	invokestatic	#416; //Method scala/collection/Iterator$class.take:(Lscala/collection/Iterator;I)Lscala/collection/Iterator;
   5:	areturn
  LineNumberTable: 
   line 561: 0

  LocalVariableTable: 
   Start  Length  Slot  Name   Signature
   0      6      0    this       Lscala/collection/immutable/VectorIterator;
   0      6      1    n       I


public void debug();
  Code:
   Stack=1, Locals=1, Args_size=1
   0:	aload_0
   1:	invokestatic	#419; //Method scala/collection/immutable/VectorPointer$class.debug:(Lscala/collection/immutable/VectorPointer;)V
   4:	return
  LineNumberTable: 
   line 561: 0


public final void gotoFreshPosWritable1(int, int, int);
  Code:
   Stack=4, Locals=4, Args_size=4
   0:	aload_0
   1:	iload_1
   2:	iload_2
   3:	iload_3
   4:	invokestatic	#424; //Method scala/collection/immutable/VectorPointer$class.gotoFreshPosWritable1:(Lscala/collection/immutable/VectorPointer;III)V
   7:	return
  LineNumberTable: 
   line 561: 0

  LocalVariableTable: 
   Start  Length  Slot  Name   Signature
   0      8      0    this       Lscala/collection/immutable/VectorIterator;
   0      8      1    oldIndex       I
   0      8      2    newIndex       I
   0      8      3    xor       I


public final void gotoFreshPosWritable0(int, int, int);
  Code:
   Stack=4, Locals=4, Args_size=4
   0:	aload_0
   1:	iload_1
   2:	iload_2
   3:	iload_3
   4:	invokestatic	#430; //Method scala/collection/immutable/VectorPointer$class.gotoFreshPosWritable0:(Lscala/collection/immutable/VectorPointer;III)V
   7:	return
  LineNumberTable: 
   line 561: 0

  LocalVariableTable: 
   Start  Length  Slot  Name   Signature
   0      8      0    this       Lscala/collection/immutable/VectorIterator;
   0      8      1    oldIndex       I
   0      8      2    newIndex       I
   0      8      3    xor       I


public final java.lang.Object[] copyRange(java.lang.Object[], int, int);
  Code:
   Stack=4, Locals=4, Args_size=4
   0:	aload_0
   1:	aload_1
   2:	iload_2
   3:	iload_3
   4:	invokestatic	#435; //Method scala/collection/immutable/VectorPointer$class.copyRange:(Lscala/collection/immutable/VectorPointer;[Ljava/lang/Object;II)[Ljava/lang/Object;
   7:	areturn
  LineNumberTable: 
   line 561: 0

  LocalVariableTable: 
   Start  Length  Slot  Name   Signature
   0      8      0    this       Lscala/collection/immutable/VectorIterator;
   0      8      1    array       [Ljava/lang/Object;
   0      8      2    oldLeft       I
   0      8      3    newLeft       I


public final void gotoPosWritable1(int, int, int);
  Code:
   Stack=4, Locals=4, Args_size=4
   0:	aload_0
   1:	iload_1
   2:	iload_2
   3:	iload_3
   4:	invokestatic	#441; //Method scala/collection/immutable/VectorPointer$class.gotoPosWritable1:(Lscala/collection/immutable/VectorPointer;III)V
   7:	return
  LineNumberTable: 
   line 561: 0

  LocalVariableTable: 
   Start  Length  Slot  Name   Signature
   0      8      0    this       Lscala/collection/immutable/VectorIterator;
   0      8      1    oldIndex       I
   0      8      2    newIndex       I
   0      8      3    xor       I


public final void gotoPosWritable0(int, int);
  Code:
   Stack=3, Locals=3, Args_size=3
   0:	aload_0
   1:	iload_1
   2:	iload_2
   3:	invokestatic	#445; //Method scala/collection/immutable/VectorPointer$class.gotoPosWritable0:(Lscala/collection/immutable/VectorPointer;II)V
   6:	return
  LineNumberTable: 
   line 561: 0

  LocalVariableTable: 
   Start  Length  Slot  Name   Signature
   0      7      0    this       Lscala/collection/immutable/VectorIterator;
   0      7      1    newIndex       I
   0      7      2    xor       I


public final void stabilize(int);
  Code:
   Stack=2, Locals=2, Args_size=2
   0:	aload_0
   1:	iload_1
   2:	invokestatic	#449; //Method scala/collection/immutable/VectorPointer$class.stabilize:(Lscala/collection/immutable/VectorPointer;I)V
   5:	return
  LineNumberTable: 
   line 561: 0

  LocalVariableTable: 
   Start  Length  Slot  Name   Signature
   0      6      0    this       Lscala/collection/immutable/VectorIterator;
   0      6      1    index       I


public final java.lang.Object[] nullSlotAndCopy(java.lang.Object[], int);
  Code:
   Stack=3, Locals=3, Args_size=3
   0:	aload_0
   1:	aload_1
   2:	iload_2
   3:	invokestatic	#455; //Method scala/collection/immutable/VectorPointer$class.nullSlotAndCopy:(Lscala/collection/immutable/VectorPointer;[Ljava/lang/Object;I)[Ljava/lang/Object;
   6:	areturn
  LineNumberTable: 
   line 561: 0

  LocalVariableTable: 
   Start  Length  Slot  Name   Signature
   0      7      0    this       Lscala/collection/immutable/VectorIterator;
   0      7      1    array       [Ljava/lang/Object;
   0      7      2    index       I


public final java.lang.Object[] copyOf(java.lang.Object[]);
  Code:
   Stack=2, Locals=2, Args_size=2
   0:	aload_0
   1:	aload_1
   2:	invokestatic	#460; //Method scala/collection/immutable/VectorPointer$class.copyOf:(Lscala/collection/immutable/VectorPointer;[Ljava/lang/Object;)[Ljava/lang/Object;
   5:	areturn
  LineNumberTable: 
   line 561: 0

  LocalVariableTable: 
   Start  Length  Slot  Name   Signature
   0      6      0    this       Lscala/collection/immutable/VectorIterator;
   0      6      1    a       [Ljava/lang/Object;


public final void gotoNextBlockStartWritable(int, int);
  Code:
   Stack=3, Locals=3, Args_size=3
   0:	aload_0
   1:	iload_1
   2:	iload_2
   3:	invokestatic	#464; //Method scala/collection/immutable/VectorPointer$class.gotoNextBlockStartWritable:(Lscala/collection/immutable/VectorPointer;II)V
   6:	return
  LineNumberTable: 
   line 561: 0

  LocalVariableTable: 
   Start  Length  Slot  Name   Signature
   0      7      0    this       Lscala/collection/immutable/VectorIterator;
   0      7      1    index       I
   0      7      2    xor       I


public final void gotoNextBlockStart(int, int);
  Code:
   Stack=3, Locals=3, Args_size=3
   0:	aload_0
   1:	iload_1
   2:	iload_2
   3:	invokestatic	#466; //Method scala/collection/immutable/VectorPointer$class.gotoNextBlockStart:(Lscala/collection/immutable/VectorPointer;II)V
   6:	return
  LineNumberTable: 
   line 561: 0

  LocalVariableTable: 
   Start  Length  Slot  Name   Signature
   0      7      0    this       Lscala/collection/immutable/VectorIterator;
   0      7      1    index       I
   0      7      2    xor       I


public final void gotoPos(int, int);
  Code:
   Stack=3, Locals=3, Args_size=3
   0:	aload_0
   1:	iload_1
   2:	iload_2
   3:	invokestatic	#469; //Method scala/collection/immutable/VectorPointer$class.gotoPos:(Lscala/collection/immutable/VectorPointer;II)V
   6:	return
  LineNumberTable: 
   line 561: 0

  LocalVariableTable: 
   Start  Length  Slot  Name   Signature
   0      7      0    this       Lscala/collection/immutable/VectorIterator;
   0      7      1    index       I
   0      7      2    xor       I


public final java.lang.Object getElem(int, int);
  Code:
   Stack=3, Locals=3, Args_size=3
   0:	aload_0
   1:	iload_1
   2:	iload_2
   3:	invokestatic	#474; //Method scala/collection/immutable/VectorPointer$class.getElem:(Lscala/collection/immutable/VectorPointer;II)Ljava/lang/Object;
   6:	areturn
  LineNumberTable: 
   line 561: 0

  LocalVariableTable: 
   Start  Length  Slot  Name   Signature
   0      7      0    this       Lscala/collection/immutable/VectorIterator;
   0      7      1    index       I
   0      7      2    xor       I


public final void initFrom(scala.collection.immutable.VectorPointer, int);
  Code:
   Stack=3, Locals=3, Args_size=3
   0:	aload_0
   1:	aload_1
   2:	iload_2
   3:	invokestatic	#478; //Method scala/collection/immutable/VectorPointer$class.initFrom:(Lscala/collection/immutable/VectorPointer;Lscala/collection/immutable/VectorPointer;I)V
   6:	return
  LineNumberTable: 
   line 561: 0

  LocalVariableTable: 
   Start  Length  Slot  Name   Signature
   0      7      0    this       Lscala/collection/immutable/VectorIterator;
   0      7      1    that       Lscala/collection/immutable/VectorPointer;
   0      7      2    depth       I


public final void initFrom(scala.collection.immutable.VectorPointer);
  Code:
   Stack=2, Locals=2, Args_size=2
   0:	aload_0
   1:	aload_1
   2:	invokestatic	#482; //Method scala/collection/immutable/VectorPointer$class.initFrom:(Lscala/collection/immutable/VectorPointer;Lscala/collection/immutable/VectorPointer;)V
   5:	return
  LineNumberTable: 
   line 561: 0

  LocalVariableTable: 
   Start  Length  Slot  Name   Signature
   0      6      0    this       Lscala/collection/immutable/VectorIterator;
   0      6      1    that       Lscala/collection/immutable/VectorPointer;


public void display5_$eq(java.lang.Object[]);
  Code:
   Stack=2, Locals=2, Args_size=2
   0:	aload_0
   1:	aload_1
   2:	putfield	#486; //Field display5:[Ljava/lang/Object;
   5:	return
  LineNumberTable: 
   line 561: 0


public java.lang.Object[] display5();
  Code:
   Stack=1, Locals=1, Args_size=1
   0:	aload_0
   1:	getfield	#486; //Field display5:[Ljava/lang/Object;
   4:	areturn
  LineNumberTable: 
   line 561: 0


public void display4_$eq(java.lang.Object[]);
  Code:
   Stack=2, Locals=2, Args_size=2
   0:	aload_0
   1:	aload_1
   2:	putfield	#490; //Field display4:[Ljava/lang/Object;
   5:	return
  LineNumberTable: 
   line 561: 0


public java.lang.Object[] display4();
  Code:
   Stack=1, Locals=1, Args_size=1
   0:	aload_0
   1:	getfield	#490; //Field display4:[Ljava/lang/Object;
   4:	areturn
  LineNumberTable: 
   line 561: 0


public void display3_$eq(java.lang.Object[]);
  Code:
   Stack=2, Locals=2, Args_size=2
   0:	aload_0
   1:	aload_1
   2:	putfield	#493; //Field display3:[Ljava/lang/Object;
   5:	return
  LineNumberTable: 
   line 561: 0


public java.lang.Object[] display3();
  Code:
   Stack=1, Locals=1, Args_size=1
   0:	aload_0
   1:	getfield	#493; //Field display3:[Ljava/lang/Object;
   4:	areturn
  LineNumberTable: 
   line 561: 0


public void display2_$eq(java.lang.Object[]);
  Code:
   Stack=2, Locals=2, Args_size=2
   0:	aload_0
   1:	aload_1
   2:	putfield	#496; //Field display2:[Ljava/lang/Object;
   5:	return
  LineNumberTable: 
   line 561: 0


public java.lang.Object[] display2();
  Code:
   Stack=1, Locals=1, Args_size=1
   0:	aload_0
   1:	getfield	#496; //Field display2:[Ljava/lang/Object;
   4:	areturn
  LineNumberTable: 
   line 561: 0


public void display1_$eq(java.lang.Object[]);
  Code:
   Stack=2, Locals=2, Args_size=2
   0:	aload_0
   1:	aload_1
   2:	putfield	#499; //Field display1:[Ljava/lang/Object;
   5:	return
  LineNumberTable: 
   line 561: 0


public java.lang.Object[] display1();
  Code:
   Stack=1, Locals=1, Args_size=1
   0:	aload_0
   1:	getfield	#499; //Field display1:[Ljava/lang/Object;
   4:	areturn
  LineNumberTable: 
   line 561: 0


public void display0_$eq(java.lang.Object[]);
  Code:
   Stack=2, Locals=2, Args_size=2
   0:	aload_0
   1:	aload_1
   2:	putfield	#96; //Field display0:[Ljava/lang/Object;
   5:	return
  LineNumberTable: 
   line 561: 0


public java.lang.Object[] display0();
  Code:
   Stack=1, Locals=1, Args_size=1
   0:	aload_0
   1:	getfield	#96; //Field display0:[Ljava/lang/Object;
   4:	areturn
  LineNumberTable: 
   line 561: 0


public void depth_$eq(int);
  Code:
   Stack=2, Locals=2, Args_size=2
   0:	aload_0
   1:	iload_1
   2:	putfield	#503; //Field depth:I
   5:	return
  LineNumberTable: 
   line 561: 0


public int depth();
  Code:
   Stack=1, Locals=1, Args_size=1
   0:	aload_0
   1:	getfield	#503; //Field depth:I
   4:	ireturn
  LineNumberTable: 
   line 561: 0


}

