Compiled from "Vector.scala"
public final class scala.collection.immutable.Vector$$anonfun$map0$1 extends scala.runtime.AbstractFunction1 implements java.io.Serializable
  SourceFile: "Vector.scala"
  Scala: length = 0x
   
  InnerClass: 
   public final $anonfun$map0$1=class scala/collection/immutable/Vector$$anonfun$map0$1 of class scala/collection/immutable/Vector
  minor version: 0
  major version: 49
  Constant pool:
Asciz	SourceFile;
Asciz	Vector.scala;
Asciz	<clinit>;
Asciz	()V;
Asciz	Code;
Asciz	serialVersionUID;
Asciz	J;
Asciz	scala/collection/immutable/Vector$$anonfun$map0$1;
class	scala/collection/immutable/Vector$$anonfun$map0$1
NameAndType	serialVersionUID:J
Field	scala/collection/immutable/Vector$$anonfun$map0$1.serialVersionUID:J
Asciz	b$1;
Asciz	Lscala/collection/mutable/Builder;;
Asciz	f$1;
Asciz	Lscala/Function1;;
Asciz	<init>;
Asciz	(Lscala/collection/immutable/Vector;Lscala/Function1;Lscala/collection/mutable/Builder;)V;
Asciz	LineNumberTable;
NameAndType	f$1:Lscala/Function1;
Field	scala/collection/immutable/Vector$$anonfun$map0$1.f$1:Lscala/Function1;
NameAndType	b$1:Lscala/collection/mutable/Builder;
Field	scala/collection/immutable/Vector$$anonfun$map0$1.b$1:Lscala/collection/mutable/Builder;
Asciz	scala/runtime/AbstractFunction1;
class	scala/runtime/AbstractFunction1
NameAndType	"<init>":()V
Method	scala/runtime/AbstractFunction1."<init>":()V
Asciz	this;
Asciz	Lscala/collection/immutable/Vector$$anonfun$map0$1;;
Asciz	$outer;
Asciz	Lscala/collection/immutable/Vector;;
Asciz	LocalVariableTable;
Asciz	(Lscala/collection/immutable/Vector<TA;>;)V;
Asciz	Signature;
Asciz	apply;
Asciz	(Ljava/lang/Object;)Ljava/lang/Object;;
Asciz	(Ljava/lang/Object;)Lscala/collection/mutable/Builder;;
NameAndType	apply:(Ljava/lang/Object;)Lscala/collection/mutable/Builder;
Method	scala/collection/immutable/Vector$$anonfun$map0$1.apply:(Ljava/lang/Object;)Lscala/collection/mutable/Builder;
Asciz	v1;
Asciz	Ljava/lang/Object;;
Asciz	scala/Function1;
class	scala/Function1
NameAndType	apply:(Ljava/lang/Object;)Ljava/lang/Object;
InterfaceMethod	scala/Function1.apply:(Ljava/lang/Object;)Ljava/lang/Object;
Asciz	scala/collection/mutable/Builder;
class	scala/collection/mutable/Builder
Asciz	$plus$eq;
NameAndType	$plus$eq:(Ljava/lang/Object;)Lscala/collection/mutable/Builder;
InterfaceMethod	scala/collection/mutable/Builder.$plus$eq:(Ljava/lang/Object;)Lscala/collection/mutable/Builder;
Asciz	x;
Asciz	(TA;)Lscala/collection/mutable/Builder<TB;TThat;>;;
Asciz	Scala;
Asciz	InnerClasses;
Asciz	scala/collection/immutable/Vector;
class	scala/collection/immutable/Vector
Asciz	$anonfun$map0$1;
Asciz	java/io/Serializable;
class	java/io/Serializable

{
public static final long serialVersionUID;
  Signature: J

public final scala.collection.mutable.Builder b$1;
  Signature: Lscala/collection/mutable/Builder;

public final scala.Function1 f$1;
  Signature: Lscala/Function1;

public static {};
  Signature: ()V
  Code:
   Stack=2, Locals=0, Args_size=0
	lconst_0
	putstatic	Field serialVersionUID:J
	return
  Labels:

public scala.collection.immutable.Vector$$anonfun$map0$1(scala.collection.immutable.Vector, scala.Function1, scala.collection.mutable.Builder);
  Signature: (Lscala/collection/immutable/Vector;Lscala/Function1;Lscala/collection/mutable/Builder;)V
  Code:
   Stack=2, Locals=4, Args_size=4
	aload_0
	aload_2
	putfield	Field f$1:Lscala/Function1;
	aload_0
	aload_3
	putfield	Field b$1:Lscala/collection/mutable/Builder;
	aload_0
	invokespecial	Method scala/runtime/AbstractFunction1."<init>":()V
	return
  Labels:
  LocalVariableTable: 
   Start  Length  Slot  Name   Signature
   0      15      0    this       Lscala/collection/immutable/Vector$$anonfun$map0$1;
   0      15      1    $outer       Lscala/collection/immutable/Vector;

  Signature: length = 0x2
   00 20 

public final java.lang.Object apply(java.lang.Object);
  Signature: (Ljava/lang/Object;)Ljava/lang/Object;
  Code:
   Stack=2, Locals=2, Args_size=2
	aload_0
	aload_1
	invokevirtual	Method apply:(Ljava/lang/Object;)Lscala/collection/mutable/Builder;
	areturn
  Labels:
  LocalVariableTable: 
   Start  Length  Slot  Name   Signature
   0      6      0    this       Lscala/collection/immutable/Vector$$anonfun$map0$1;
   0      6      1    v1       Ljava/lang/Object;


public final scala.collection.mutable.Builder apply(java.lang.Object);
  Signature: (Ljava/lang/Object;)Lscala/collection/mutable/Builder;
  Code:
   Stack=3, Locals=2, Args_size=2
	aload_0
	getfield	Field b$1:Lscala/collection/mutable/Builder;
	aload_0
	getfield	Field f$1:Lscala/Function1;
	aload_1
	invokeinterface	InterfaceMethod scala/Function1.apply:(Ljava/lang/Object;)Ljava/lang/Object;
	invokeinterface	InterfaceMethod scala/collection/mutable/Builder.$plus$eq:(Ljava/lang/Object;)Lscala/collection/mutable/Builder;
	areturn
  Labels:
  LocalVariableTable: 
   Start  Length  Slot  Name   Signature
   0      20      0    this       Lscala/collection/immutable/Vector$$anonfun$map0$1;
   0      20      1    x       Ljava/lang/Object;

  Signature: length = 0x2
   00 33 

}

