Compiled from "elidable.scala"
public final class scala.annotation.elidable extends scala.Annotation implements scala.StaticAnnotation,scala.ScalaObject
  SourceFile: "elidable.scala"
  ScalaSig: length = 0x331
   05 00 FFFFFF81 04 06 08 01 02 FFFFFF84 FFFFFF80 FFFFFF80 FFFFFF80 02 07 02 08
   65 6C 69 64 61 62 6C 65 0A 02 03 04 01 0A 61 6E
   6E 6F 74 61 74 69 6F 6E 0A 01 05 01 05 73 63 61
   6C 61 03 00 13 04 00 08 0C 0F 10 02 09 0A 0D 01
   04 09 02 0B 04 02 0A 41 6E 6E 6F 74 61 74 69 6F
   6E 10 02 09 0D 09 02 0E 04 02 10 53 74 61 74 69
   63 41 6E 6E 6F 74 61 74 69 6F 6E 10 02 09 10 09
   02 11 04 02 0B 53 63 61 6C 61 4F 62 6A 65 63 74
   08 08 13 00 FFFFFF82 FFFFFFC2 FFFFFF80 FFFFFF84 02 14 01 05 6C 65 76 65
   6C 15 01 15 10 02 09 16 09 02 17 04 02 03 49 6E
   74 08 08 19 00 FFFFFF82 FFFFFF80 FFFFFFA0 FFFFFF80 06 15 01 06 6C 65 76
   65 6C 20 08 05 1B 00 FFFFFF84 00 1C 01 06 3C 69 6E 69
   74 3E 14 02 1D 1F 10 02 1E 00 0D 01 02 08 05 13
   1A FFFFFFC0 00 15 07 05 21 02 FFFFFF88 02 22 01 08 65 6C 69
   64 61 62 6C 65 10 02 1E 23 06 08 01 02 FFFFFF84 FFFFFF80 FFFFFF80
   FFFFFF88 02 24 13 03 23 25 0F 10 02 26 2B 0D 01 27 0A
   02 28 29 01 04 6C 61 6E 67 0A 01 2A 01 04 6A 61
   76 61 09 02 2C 27 02 06 4F 62 6A 65 63 74 08 05
   1B 23 FFFFFF84 00 2E 14 01 22 08 07 30 23 FFFFFFC2 FFFFFF80 FFFFFF84 02
   31 01 03 41 4C 4C 15 01 32 0F 01 33 1D 04 FFFFFF80 00
   00 00 08 06 35 23 FFFFFFA0 FFFFFF80 06 32 01 04 41 4C 4C 20
   08 07 37 23 FFFFFFC2 FFFFFF80 FFFFFF84 02 38 01 06 46 49 4E 45 53
   54 15 01 39 0F 01 3A 1D 02 01 2C 08 06 3C 23 FFFFFFA0
   FFFFFF80 06 39 01 07 46 49 4E 45 53 54 20 08 07 3E 23
   FFFFFFC2 FFFFFF80 FFFFFF84 02 3F 01 05 46 49 4E 45 52 15 01 40 0F
   01 41 1D 02 01 FFFFFF90 08 06 43 23 FFFFFFA0 FFFFFF80 06 40 01 06
   46 49 4E 45 52 20 08 07 45 23 FFFFFFC2 FFFFFF80 FFFFFF84 02 46 01
   04 46 49 4E 45 15 01 47 0F 01 48 1D 02 01 FFFFFFF4 08
   06 4A 23 FFFFFFA0 FFFFFF80 06 47 01 05 46 49 4E 45 20 08 07
   4C 23 FFFFFFC2 FFFFFF80 FFFFFF84 02 4D 01 06 43 4F 4E 46 49 47 15
   01 4E 0F 01 4F 1D 02 02 FFFFFFBC 08 06 51 23 FFFFFFA0 FFFFFF80 06
   4E 01 07 43 4F 4E 46 49 47 20 08 07 53 23 FFFFFFC2 FFFFFF80
   FFFFFF84 02 54 01 04 49 4E 46 4F 15 01 55 0F 01 56 1D
   02 03 20 08 06 58 23 FFFFFFA0 FFFFFF80 06 55 01 05 49 4E 46
   4F 20 08 07 5A 23 FFFFFFC2 FFFFFF80 FFFFFF84 02 5B 01 07 57 41 52
   4E 49 4E 47 15 01 5C 0F 01 5D 1D 02 03 FFFFFF84 08 06
   5F 23 FFFFFFA0 FFFFFF80 06 5C 01 08 57 41 52 4E 49 4E 47 20
   08 07 61 23 FFFFFFC2 FFFFFF80 FFFFFF84 02 62 01 06 53 45 56 45 52
   45 15 01 63 0F 01 64 1D 02 03 FFFFFFE8 08 06 66 23 FFFFFFA0
   FFFFFF80 06 63 01 07 53 45 56 45 52 45 20 08 07 68 23
   FFFFFFC2 FFFFFF80 FFFFFF84 02 69 01 03 4F 46 46 15 01 6A 0F 01 6B
   1D 04 7F FFFFFFFF FFFFFFFF FFFFFFFF 08 06 6D 23 FFFFFFA0 FFFFFF80 06 6A 01 04
   4F 46 46 20 08 07 6F 23 FFFFFFC2 FFFFFF80 FFFFFF84 02 70 01 09 41
   53 53 45 52 54 49 4F 4E 15 01 71 0F 01 72 1D 02
   07 FFFFFFD0 08 06 74 23 FFFFFFA0 FFFFFF80 06 71 01 0A 41 53 53 45
   52 54 49 4F 4E 20 08 07 76 23 FFFFFFC2 FFFFFF80 FFFFFF84 00 77 01
   06 62 79 4E 61 6D 65 15 01 78 10 04 79 7C 7F 15
   0E 02 09 7A 09 02 7B 04 01 06 50 72 65 64 65 66
   09 02 7D 7E 02 03 4D 61 70 0A 02 7B 04 10 03 79
   FFFFFF81 00 09 03 FFFFFF81 01 7E 02 06 53 74 72 69 6E 67 08
   07 FFFFFF81 03 23 FFFFFFA0 FFFFFF80 04 78 01 07 62 79 4E 61 6D 65
   20 
  minor version: 0
  major version: 49
  Constant pool:
Asciz	SourceFile;
Asciz	elidable.scala;
Asciz	byName;
Asciz	()Lscala/collection/immutable/Map;;
Asciz	Code;
Asciz	scala/annotation/elidable$;
class	scala/annotation/elidable$
Asciz	MODULE$;
Asciz	Lscala/annotation/elidable$;;
NameAndType	MODULE$:Lscala/annotation/elidable$;
Field	scala/annotation/elidable$.MODULE$:Lscala/annotation/elidable$;
NameAndType	byName:()Lscala/collection/immutable/Map;
Method	scala/annotation/elidable$.byName:()Lscala/collection/immutable/Map;
Asciz	()Lscala/collection/immutable/Map<Ljava/lang/String;Ljava/lang/Integer;>;;
Asciz	Signature;
Asciz	ASSERTION;
Asciz	()I;
NameAndType	ASSERTION:()I
Method	scala/annotation/elidable$.ASSERTION:()I
Asciz	OFF;
NameAndType	OFF:()I
Method	scala/annotation/elidable$.OFF:()I
Asciz	SEVERE;
NameAndType	SEVERE:()I
Method	scala/annotation/elidable$.SEVERE:()I
Asciz	WARNING;
NameAndType	WARNING:()I
Method	scala/annotation/elidable$.WARNING:()I
Asciz	INFO;
NameAndType	INFO:()I
Method	scala/annotation/elidable$.INFO:()I
Asciz	CONFIG;
NameAndType	CONFIG:()I
Method	scala/annotation/elidable$.CONFIG:()I
Asciz	FINE;
NameAndType	FINE:()I
Method	scala/annotation/elidable$.FINE:()I
Asciz	FINER;
NameAndType	FINER:()I
Method	scala/annotation/elidable$.FINER:()I
Asciz	FINEST;
NameAndType	FINEST:()I
Method	scala/annotation/elidable$.FINEST:()I
Asciz	ALL;
NameAndType	ALL:()I
Method	scala/annotation/elidable$.ALL:()I
Asciz	level;
Asciz	I;
Asciz	<init>;
Asciz	(I)V;
Asciz	LineNumberTable;
Asciz	scala/annotation/elidable;
class	scala/annotation/elidable
NameAndType	level:I
Field	scala/annotation/elidable.level:I
Asciz	scala/Annotation;
class	scala/Annotation
Asciz	()V;
NameAndType	"<init>":()V
Method	scala/Annotation."<init>":()V
Asciz	this;
Asciz	Lscala/annotation/elidable;;
Asciz	LocalVariableTable;
Asciz	ScalaSig;
Asciz	scala/StaticAnnotation;
class	scala/StaticAnnotation
Asciz	scala/ScalaObject;
class	scala/ScalaObject

{
private final int level;
  Signature: I

public static final scala.collection.immutable.Map byName();
  Signature: ()Lscala/collection/immutable/Map;
  Code:
   Stack=1, Locals=0, Args_size=0
	getstatic	Field scala/annotation/elidable$.MODULE$:Lscala/annotation/elidable$;
	invokevirtual	Method scala/annotation/elidable$.byName:()Lscala/collection/immutable/Map;
	areturn
  Labels:
  Signature: length = 0x2
   00 0E 

public static final int ASSERTION();
  Signature: ()I
  Code:
   Stack=1, Locals=0, Args_size=0
	getstatic	Field scala/annotation/elidable$.MODULE$:Lscala/annotation/elidable$;
	invokevirtual	Method scala/annotation/elidable$.ASSERTION:()I
	ireturn
  Labels:

public static final int OFF();
  Signature: ()I
  Code:
   Stack=1, Locals=0, Args_size=0
	getstatic	Field scala/annotation/elidable$.MODULE$:Lscala/annotation/elidable$;
	invokevirtual	Method scala/annotation/elidable$.OFF:()I
	ireturn
  Labels:

public static final int SEVERE();
  Signature: ()I
  Code:
   Stack=1, Locals=0, Args_size=0
	getstatic	Field scala/annotation/elidable$.MODULE$:Lscala/annotation/elidable$;
	invokevirtual	Method scala/annotation/elidable$.SEVERE:()I
	ireturn
  Labels:

public static final int WARNING();
  Signature: ()I
  Code:
   Stack=1, Locals=0, Args_size=0
	getstatic	Field scala/annotation/elidable$.MODULE$:Lscala/annotation/elidable$;
	invokevirtual	Method scala/annotation/elidable$.WARNING:()I
	ireturn
  Labels:

public static final int INFO();
  Signature: ()I
  Code:
   Stack=1, Locals=0, Args_size=0
	getstatic	Field scala/annotation/elidable$.MODULE$:Lscala/annotation/elidable$;
	invokevirtual	Method scala/annotation/elidable$.INFO:()I
	ireturn
  Labels:

public static final int CONFIG();
  Signature: ()I
  Code:
   Stack=1, Locals=0, Args_size=0
	getstatic	Field scala/annotation/elidable$.MODULE$:Lscala/annotation/elidable$;
	invokevirtual	Method scala/annotation/elidable$.CONFIG:()I
	ireturn
  Labels:

public static final int FINE();
  Signature: ()I
  Code:
   Stack=1, Locals=0, Args_size=0
	getstatic	Field scala/annotation/elidable$.MODULE$:Lscala/annotation/elidable$;
	invokevirtual	Method scala/annotation/elidable$.FINE:()I
	ireturn
  Labels:

public static final int FINER();
  Signature: ()I
  Code:
   Stack=1, Locals=0, Args_size=0
	getstatic	Field scala/annotation/elidable$.MODULE$:Lscala/annotation/elidable$;
	invokevirtual	Method scala/annotation/elidable$.FINER:()I
	ireturn
  Labels:

public static final int FINEST();
  Signature: ()I
  Code:
   Stack=1, Locals=0, Args_size=0
	getstatic	Field scala/annotation/elidable$.MODULE$:Lscala/annotation/elidable$;
	invokevirtual	Method scala/annotation/elidable$.FINEST:()I
	ireturn
  Labels:

public static final int ALL();
  Signature: ()I
  Code:
   Stack=1, Locals=0, Args_size=0
	getstatic	Field scala/annotation/elidable$.MODULE$:Lscala/annotation/elidable$;
	invokevirtual	Method scala/annotation/elidable$.ALL:()I
	ireturn
  Labels:

public scala.annotation.elidable(int);
  Signature: (I)V
  Code:
   Stack=2, Locals=2, Args_size=2
	aload_0
	iload_1
	putfield	Field level:I
	aload_0
	invokespecial	Method scala/Annotation."<init>":()V
	return
  Labels:
  LocalVariableTable: 
   Start  Length  Slot  Name   Signature
   0      10      0    this       Lscala/annotation/elidable;
   0      10      1    level       I


public final int level();
  Signature: ()I
  Code:
   Stack=1, Locals=1, Args_size=1
	aload_0
	getfield	Field level:I
	ireturn
  Labels:

}

