Compiled from "experimental.scala"
public final class scala.annotation.experimental extends scala.Annotation implements scala.StaticAnnotation,scala.ScalaObject
  SourceFile: "experimental.scala"
  ScalaSig: length = 0xE5
   05 00 23 06 08 01 02 FFFFFF84 FFFFFF80 FFFFFF80 FFFFFF80 02 07 02 0C 65
   78 70 65 72 69 6D 65 6E 74 61 6C 0A 02 03 04 01
   0A 61 6E 6E 6F 74 61 74 69 6F 6E 0A 01 05 01 05
   73 63 61 6C 61 03 00 13 04 00 08 0C 0F 10 02 09
   0A 0D 01 04 09 02 0B 04 02 0A 41 6E 6E 6F 74 61
   74 69 6F 6E 10 02 09 0D 09 02 0E 04 02 10 53 74
   61 74 69 63 41 6E 6E 6F 74 61 74 69 6F 6E 10 02
   09 10 09 02 11 04 02 0B 53 63 61 6C 61 4F 62 6A
   65 63 74 08 08 13 00 FFFFFF82 FFFFFF80 FFFFFFA0 FFFFFF80 04 14 01 07 6D
   65 73 73 61 67 65 10 02 15 18 0E 02 09 16 09 02
   17 04 01 06 50 72 65 64 65 66 09 02 19 1A 02 06
   53 74 72 69 6E 67 0A 02 17 04 08 05 1C 00 FFFFFF84 00
   1D 01 06 3C 69 6E 69 74 3E 14 02 1E 20 10 02 1F
   00 0D 01 02 08 05 13 1B FFFFFFC0 00 14 08 05 1C 00 FFFFFF84
   00 22 14 01 1E 
  minor version: 0
  major version: 49
  Constant pool:
const #1 = Asciz	SourceFile;
const #2 = Asciz	experimental.scala;
const #3 = Asciz	<init>;
const #4 = Asciz	(Ljava/lang/String;)V;
const #5 = Asciz	Code;
const #6 = Asciz	LineNumberTable;
const #7 = Asciz	scala/Annotation;
const #8 = class	#7;	//  scala/Annotation
const #9 = Asciz	()V;
const #10 = NameAndType	#3:#9;//  "<init>":()V
const #11 = Method	#8.#10;	//  scala/Annotation."<init>":()V
const #12 = Asciz	this;
const #13 = Asciz	Lscala/annotation/experimental;;
const #14 = Asciz	message;
const #15 = Asciz	Ljava/lang/String;;
const #16 = Asciz	LocalVariableTable;
const #17 = Asciz	;
const #18 = String	#17;	//  
const #19 = Asciz	scala/annotation/experimental;
const #20 = class	#19;	//  scala/annotation/experimental
const #21 = NameAndType	#3:#4;//  "<init>":(Ljava/lang/String;)V
const #22 = Method	#20.#21;	//  scala/annotation/experimental."<init>":(Ljava/lang/String;)V
const #23 = Asciz	ScalaSig;
const #24 = Asciz	scala/StaticAnnotation;
const #25 = class	#24;	//  scala/StaticAnnotation
const #26 = Asciz	scala/ScalaObject;
const #27 = class	#26;	//  scala/ScalaObject

{
public scala.annotation.experimental(java.lang.String);
  Code:
   Stack=1, Locals=2, Args_size=2
   0:	aload_0
   1:	invokespecial	#11; //Method scala/Annotation."<init>":()V
   4:	return
  LineNumberTable: 
   line 14: 0

  LocalVariableTable: 
   Start  Length  Slot  Name   Signature
   0      5      0    this       Lscala/annotation/experimental;
   0      5      1    message       Ljava/lang/String;


public scala.annotation.experimental();
  Code:
   Stack=2, Locals=1, Args_size=1
   0:	aload_0
   1:	ldc	#18; //String 
   3:	invokespecial	#22; //Method "<init>":(Ljava/lang/String;)V
   6:	return
  LineNumberTable: 
   line 15: 0


}

