Compiled from "XMLEvent.scala"
public final class scala.xml.pull.EvComment$ extends scala.runtime.AbstractFunction1 implements scala.ScalaObject
  SourceFile: "XMLEvent.scala"
  Scala: length = 0x
   
  minor version: 0
  major version: 49
  Constant pool:
Asciz	SourceFile;
Asciz	XMLEvent.scala;
Asciz	MODULE$;
Asciz	Lscala/xml/pull/EvComment$;;
Asciz	<clinit>;
Asciz	()V;
Asciz	Code;
Asciz	scala/xml/pull/EvComment$;
class	scala/xml/pull/EvComment$
Asciz	<init>;
NameAndType	"<init>":()V
Method	scala/xml/pull/EvComment$."<init>":()V
Asciz	unapply;
Asciz	(Lscala/xml/pull/EvComment;)Lscala/Option;;
Asciz	LineNumberTable;
Asciz	scala/None$;
class	scala/None$
Asciz	Lscala/None$;;
NameAndType	MODULE$:Lscala/None$;
Field	scala/None$.MODULE$:Lscala/None$;
Asciz	scala/Some;
class	scala/Some
Asciz	scala/xml/pull/EvComment;
class	scala/xml/pull/EvComment
Asciz	text;
Asciz	()Ljava/lang/String;;
NameAndType	text:()Ljava/lang/String;
Method	scala/xml/pull/EvComment.text:()Ljava/lang/String;
Asciz	(Ljava/lang/Object;)V;
NameAndType	"<init>":(Ljava/lang/Object;)V
Method	scala/Some."<init>":(Ljava/lang/Object;)V
Asciz	this;
Asciz	x$0;
Asciz	Lscala/xml/pull/EvComment;;
Asciz	LocalVariableTable;
Asciz	apply;
Asciz	(Ljava/lang/String;)Lscala/xml/pull/EvComment;;
Asciz	(Ljava/lang/String;)V;
NameAndType	"<init>":(Ljava/lang/String;)V
Method	scala/xml/pull/EvComment."<init>":(Ljava/lang/String;)V
Asciz	Ljava/lang/String;;
Asciz	(Ljava/lang/Object;)Ljava/lang/Object;;
Asciz	java/lang/String;
class	java/lang/String
NameAndType	apply:(Ljava/lang/String;)Lscala/xml/pull/EvComment;
Method	scala/xml/pull/EvComment$.apply:(Ljava/lang/String;)Lscala/xml/pull/EvComment;
Asciz	v1;
Asciz	Ljava/lang/Object;;
Asciz	scala/runtime/AbstractFunction1;
class	scala/runtime/AbstractFunction1
Method	scala/runtime/AbstractFunction1."<init>":()V
NameAndType	MODULE$:Lscala/xml/pull/EvComment$;
Field	scala/xml/pull/EvComment$.MODULE$:Lscala/xml/pull/EvComment$;
Asciz	Scala;
Asciz	scala/ScalaObject;
class	scala/ScalaObject

{
public static final scala.xml.pull.EvComment$ MODULE$;
  Signature: Lscala/xml/pull/EvComment$;

public static {};
  Signature: ()V
  Code:
   Stack=1, Locals=0, Args_size=0
	new	class scala/xml/pull/EvComment$
	invokespecial	Method "<init>":()V
	return
  Labels:

public scala.Option unapply(scala.xml.pull.EvComment);
  Signature: (Lscala/xml/pull/EvComment;)Lscala/Option;
  Code:
   Stack=3, Locals=2, Args_size=2
	aload_1
	ifnonnull	l1 // new
	getstatic	Field scala/None$.MODULE$:Lscala/None$;
	goto	l2 // areturn
l1	new	class scala/Some
	dup
	aload_1
	invokevirtual	Method scala/xml/pull/EvComment.text:()Ljava/lang/String;
	invokespecial	Method scala/Some."<init>":(Ljava/lang/Object;)V
l2	areturn
  Labels:
   	l1 = 10 // new
   	l2 = 21 // areturn
  LocalVariableTable: 
   Start  Length  Slot  Name   Signature
   0      22      0    this       Lscala/xml/pull/EvComment$;
   0      22      1    x$0       Lscala/xml/pull/EvComment;


public scala.xml.pull.EvComment apply(java.lang.String);
  Signature: (Ljava/lang/String;)Lscala/xml/pull/EvComment;
  Code:
   Stack=3, Locals=2, Args_size=2
	new	class scala/xml/pull/EvComment
	dup
	aload_1
	invokespecial	Method scala/xml/pull/EvComment."<init>":(Ljava/lang/String;)V
	areturn
  Labels:
  LocalVariableTable: 
   Start  Length  Slot  Name   Signature
   0      9      0    this       Lscala/xml/pull/EvComment$;
   0      9      1    text       Ljava/lang/String;


public java.lang.Object apply(java.lang.Object);
  Signature: (Ljava/lang/Object;)Ljava/lang/Object;
  Code:
   Stack=2, Locals=2, Args_size=2
	aload_0
	aload_1
	checkcast	class java/lang/String
	invokevirtual	Method apply:(Ljava/lang/String;)Lscala/xml/pull/EvComment;
	areturn
  Labels:
  LocalVariableTable: 
   Start  Length  Slot  Name   Signature
   0      9      0    this       Lscala/xml/pull/EvComment$;
   0      9      1    v1       Ljava/lang/Object;


private scala.xml.pull.EvComment$();
  Signature: ()V
  Code:
   Stack=1, Locals=1, Args_size=1
	aload_0
	invokespecial	Method scala/runtime/AbstractFunction1."<init>":()V
	aload_0
	putstatic	Field MODULE$:Lscala/xml/pull/EvComment$;
	return
  Labels:

}

