Compiled from "XMLEvent.scala"
public class scala.xml.pull.EvElemStart extends java.lang.Object implements scala.xml.pull.XMLEvent,scala.ScalaObject,scala.Product,java.io.Serializable
  SourceFile: "XMLEvent.scala"
  ScalaSig: length = 0x4C5
   05 00 FFFFFF81 28 06 08 01 02 FFFFFF84 FFFFFF80 FFFFFF80 FFFFFF80 40 09 02 0B
   45 76 45 6C 65 6D 53 74 61 72 74 0A 02 03 04 01
   04 70 75 6C 6C 0A 02 05 06 01 03 78 6D 6C 0A 01
   07 01 05 73 63 61 6C 61 03 00 13 05 00 0A 12 16
   1A 10 02 0B 10 0D 01 0C 0A 02 0D 0E 01 04 6C 61
   6E 67 0A 01 0F 01 04 6A 61 76 61 09 02 11 0C 02
   06 4F 62 6A 65 63 74 10 02 13 14 0D 01 02 09 02
   15 02 02 08 58 4D 4C 45 76 65 6E 74 10 02 17 18
   0D 01 06 09 02 19 06 02 0B 53 63 61 6C 61 4F 62
   6A 65 63 74 10 02 17 1B 09 02 1C 06 02 07 50 72
   6F 64 75 63 74 08 08 1E 00 FFFFFF82 FFFFFFCA FFFFFF80 FFFFFF84 00 1F 01
   03 70 72 65 15 01 20 10 02 21 24 0E 02 17 22 09
   02 23 06 01 06 50 72 65 64 65 66 09 02 25 26 02
   06 53 74 72 69 6E 67 0A 02 23 06 08 08 28 00 FFFFFF82
   FFFFFF88 FFFFFFA0 FFFFFF80 04 20 01 04 70 72 65 20 08 08 2A 00 FFFFFF82
   FFFFFFCA FFFFFF80 FFFFFF84 00 1F 01 05 6C 61 62 65 6C 08 08 2C 00
   FFFFFF82 FFFFFF88 FFFFFFA0 FFFFFF80 04 20 01 06 6C 61 62 65 6C 20 08 08
   2E 00 FFFFFF82 FFFFFFCA FFFFFF80 FFFFFF84 00 2F 01 05 61 74 74 72 73 15
   01 30 10 02 31 32 0D 01 04 09 02 33 04 02 08 4D
   65 74 61 44 61 74 61 08 08 35 00 FFFFFF82 FFFFFF88 FFFFFFA0 FFFFFF80 04
   30 01 06 61 74 74 72 73 20 08 08 37 00 FFFFFF82 FFFFFFCA FFFFFF80
   FFFFFF84 00 38 01 05 73 63 6F 70 65 15 01 39 10 02 31
   3A 09 02 3B 04 02 10 4E 61 6D 65 73 70 61 63 65
   42 69 6E 64 69 6E 67 08 08 3D 00 FFFFFF82 FFFFFF88 FFFFFFA0 FFFFFF80 04
   39 01 06 73 63 6F 70 65 20 08 05 3F 00 FFFFFF84 00 40
   01 06 3C 69 6E 69 74 3E 14 05 41 42 43 44 45 10
   02 13 00 08 05 1E 3E FFFFFFC0 00 20 08 05 2A 3E FFFFFFC0 00
   20 08 05 2E 3E FFFFFFC0 00 30 08 05 37 3E FFFFFFC0 00 39 08
   07 47 00 FFFFFF81 FFFFFF80 FFFFFF84 00 48 01 04 63 6F 70 79 14 05
   41 49 57 5A 5F 08 08 4A 1E 46 FFFFFF90 FFFFFF80 FFFFFFC0 00 20 08
   07 4B 00 FFFFFF91 FFFFFF80 FFFFFF84 00 4C 01 0E 63 6F 70 79 24 64
   65 66 61 75 6C 74 24 31 15 01 4D 2A 02 20 4E 2B
   01 4F 10 02 50 55 0D 01 51 0A 02 52 53 01 09 75
   6E 63 68 65 63 6B 65 64 0A 02 54 06 01 0A 61 6E
   6E 6F 74 61 74 69 6F 6E 09 02 56 51 02 11 75 6E
   63 68 65 63 6B 65 64 56 61 72 69 61 6E 63 65 08
   08 58 2A 46 FFFFFF90 FFFFFF80 FFFFFFC0 00 20 08 07 59 00 FFFFFF91 FFFFFF80 FFFFFF84
   00 4C 01 0E 63 6F 70 79 24 64 65 66 61 75 6C 74
   24 32 08 08 5B 2E 46 FFFFFF90 FFFFFF80 FFFFFFC0 00 30 08 07 5C 00
   FFFFFF91 FFFFFF80 FFFFFF84 00 5D 01 0E 63 6F 70 79 24 64 65 66 61
   75 6C 74 24 33 15 01 5E 2A 02 30 4E 08 08 60 37
   46 FFFFFF90 FFFFFF80 FFFFFFC0 00 39 08 07 61 00 FFFFFF91 FFFFFF80 FFFFFF84 00 62 01
   0E 63 6F 70 79 24 64 65 66 61 75 6C 74 24 34 15
   01 63 2A 02 39 4E 08 08 65 00 FFFFFF84 FFFFFF80 FFFFFF80 FFFFFF84 20 66
   01 08 68 61 73 68 43 6F 64 65 14 01 67 10 02 17
   68 09 02 69 06 02 03 49 6E 74 08 08 6B 00 FFFFFF84 FFFFFF80
   FFFFFF80 FFFFFF84 20 6C 01 08 74 6F 53 74 72 69 6E 67 14 01
   20 08 08 6E 00 FFFFFF84 FFFFFF80 FFFFFF80 FFFFFF84 20 6F 01 06 65 71 75
   61 6C 73 14 02 70 73 10 02 17 71 09 02 72 06 02
   07 42 6F 6F 6C 65 61 6E 08 07 74 6D FFFFFF81 FFFFFF80 FFFFFFC0 00
   75 01 03 78 24 31 10 02 17 76 09 02 77 06 02 03
   41 6E 79 08 08 79 00 FFFFFF84 FFFFFF80 FFFFFF80 FFFFFF84 20 7A 01 0D 70
   72 6F 64 75 63 74 50 72 65 66 69 78 15 01 7B 10
   02 0B 7C 09 02 25 0C 08 08 7E 00 FFFFFF84 FFFFFF80 FFFFFF80 FFFFFF84 20
   7F 01 0C 70 72 6F 64 75 63 74 41 72 69 74 79 15
   01 67 08 0A FFFFFF81 01 00 FFFFFF84 FFFFFF80 FFFFFF80 FFFFFF84 20 FFFFFF81 02 01 0E
   70 72 6F 64 75 63 74 45 6C 65 6D 65 6E 74 14 03
   75 FFFFFF81 03 08 08 74 FFFFFF81 00 FFFFFF81 FFFFFF80 FFFFFFC0 00 67 08 0A FFFFFF81
   05 00 FFFFFF84 FFFFFF80 FFFFFF80 FFFFFF84 20 FFFFFF81 06 01 08 63 61 6E 45 71
   75 61 6C 14 03 70 FFFFFF81 07 08 08 74 FFFFFF81 04 FFFFFF81 FFFFFF80 FFFFFFC0
   00 75 28 03 00 FFFFFF81 09 10 03 17 FFFFFF81 0A 09 03 FFFFFF81 0B
   06 02 0C 73 65 72 69 61 6C 69 7A 61 62 6C 65 07
   09 FFFFFF81 0D 02 FFFFFF81 FFFFFF80 FFFFFF88 02 FFFFFF81 0E 01 0B 45 76 45 6C
   65 6D 53 74 61 72 74 10 03 13 FFFFFF81 0F 06 09 01 02
   FFFFFF84 FFFFFF81 FFFFFF80 FFFFFF88 02 FFFFFF81 10 13 06 FFFFFF81 0F 0A FFFFFF81 11 16 10
   08 17 FFFFFF81 12 20 20 30 39 41 09 03 FFFFFF81 13 06 02 09
   46 75 6E 63 74 69 6F 6E 34 08 07 3F FFFFFF81 0F FFFFFF84 00
   FFFFFF81 15 14 02 FFFFFF81 0E 08 0A FFFFFF81 17 FFFFFF81 0F FFFFFF81 FFFFFF80 FFFFFF84 40
   FFFFFF81 18 01 05 61 70 70 6C 79 14 09 41 FFFFFF81 19 FFFFFF81 1A
   FFFFFF81 1B FFFFFF81 1C 08 06 1E FFFFFF81 16 FFFFFFC0 00 20 08 06 2A FFFFFF81
   16 FFFFFFC0 00 20 08 06 2E FFFFFF81 16 FFFFFFC0 00 30 08 06 37 FFFFFF81
   16 FFFFFFC0 00 39 08 0A FFFFFF81 1E FFFFFF81 0F FFFFFF81 FFFFFF80 FFFFFF84 40 FFFFFF81 1F
   01 07 75 6E 61 70 70 6C 79 14 04 FFFFFF81 20 FFFFFF81 26 10
   05 17 FFFFFF81 21 FFFFFF81 23 09 03 FFFFFF81 22 06 02 04 53 6F 6D
   65 10 07 17 FFFFFF81 24 20 20 30 39 09 03 FFFFFF81 25 06 02
   06 54 75 70 6C 65 34 08 07 FFFFFF81 27 FFFFFF81 1D FFFFFFC0 00 41
   01 03 78 24 30 
  minor version: 0
  major version: 49
  Constant pool:
Asciz	SourceFile;
Asciz	XMLEvent.scala;
Asciz	curry;
Asciz	()Lscala/Function1;;
Asciz	Code;
Asciz	scala/xml/pull/EvElemStart$;
class	scala/xml/pull/EvElemStart$
Asciz	MODULE$;
Asciz	Lscala/xml/pull/EvElemStart$;;
NameAndType	MODULE$:Lscala/xml/pull/EvElemStart$;
Field	scala/xml/pull/EvElemStart$.MODULE$:Lscala/xml/pull/EvElemStart$;
NameAndType	curry:()Lscala/Function1;
Method	scala/xml/pull/EvElemStart$.curry:()Lscala/Function1;
Asciz	scope;
Asciz	Lscala/xml/NamespaceBinding;;
Asciz	attrs;
Asciz	Lscala/xml/MetaData;;
Asciz	label;
Asciz	Ljava/lang/String;;
Asciz	pre;
Asciz	<init>;
Asciz	(Ljava/lang/String;Ljava/lang/String;Lscala/xml/MetaData;Lscala/xml/NamespaceBinding;)V;
Asciz	LineNumberTable;
Asciz	scala/xml/pull/EvElemStart;
class	scala/xml/pull/EvElemStart
NameAndType	pre:Ljava/lang/String;
Field	scala/xml/pull/EvElemStart.pre:Ljava/lang/String;
NameAndType	label:Ljava/lang/String;
Field	scala/xml/pull/EvElemStart.label:Ljava/lang/String;
NameAndType	attrs:Lscala/xml/MetaData;
Field	scala/xml/pull/EvElemStart.attrs:Lscala/xml/MetaData;
NameAndType	scope:Lscala/xml/NamespaceBinding;
Field	scala/xml/pull/EvElemStart.scope:Lscala/xml/NamespaceBinding;
Asciz	java/lang/Object;
class	java/lang/Object
Asciz	()V;
NameAndType	"<init>":()V
Method	java/lang/Object."<init>":()V
Asciz	scala/Product$class;
class	scala/Product$class
Asciz	$init$;
Asciz	(Lscala/Product;)V;
NameAndType	$init$:(Lscala/Product;)V
Method	scala/Product$class.$init$:(Lscala/Product;)V
Asciz	this;
Asciz	Lscala/xml/pull/EvElemStart;;
Asciz	LocalVariableTable;
Asciz	gd1$1;
Asciz	(Ljava/lang/String;Ljava/lang/String;Lscala/xml/MetaData;Lscala/xml/NamespaceBinding;)Z;
Asciz	()Ljava/lang/String;;
NameAndType	pre:()Ljava/lang/String;
Method	scala/xml/pull/EvElemStart.pre:()Ljava/lang/String;
Asciz	equals;
Asciz	(Ljava/lang/Object;)Z;
NameAndType	equals:(Ljava/lang/Object;)Z
Method	java/lang/Object.equals:(Ljava/lang/Object;)Z
NameAndType	label:()Ljava/lang/String;
Method	scala/xml/pull/EvElemStart.label:()Ljava/lang/String;
Asciz	()Lscala/xml/MetaData;;
NameAndType	attrs:()Lscala/xml/MetaData;
Method	scala/xml/pull/EvElemStart.attrs:()Lscala/xml/MetaData;
Asciz	()Lscala/xml/NamespaceBinding;;
NameAndType	scope:()Lscala/xml/NamespaceBinding;
Method	scala/xml/pull/EvElemStart.scope:()Lscala/xml/NamespaceBinding;
Asciz	canEqual;
Asciz	productElement;
Asciz	(I)Ljava/lang/Object;;
Asciz	java/lang/IndexOutOfBoundsException;
class	java/lang/IndexOutOfBoundsException
Asciz	scala/runtime/BoxesRunTime;
class	scala/runtime/BoxesRunTime
Asciz	boxToInteger;
Asciz	(I)Ljava/lang/Integer;;
NameAndType	boxToInteger:(I)Ljava/lang/Integer;
Method	scala/runtime/BoxesRunTime.boxToInteger:(I)Ljava/lang/Integer;
Asciz	toString;
NameAndType	toString:()Ljava/lang/String;
Method	java/lang/Object.toString:()Ljava/lang/String;
Asciz	(Ljava/lang/String;)V;
NameAndType	"<init>":(Ljava/lang/String;)V
Method	java/lang/IndexOutOfBoundsException."<init>":(Ljava/lang/String;)V
Asciz	scala/MatchError;
class	scala/MatchError
Method	scala/MatchError."<init>":(Ljava/lang/String;)V
Asciz	productArity;
Asciz	()I;
Asciz	productPrefix;
Asciz	EvElemStart;
String	EvElemStart
NameAndType	gd1$1:(Ljava/lang/String;Ljava/lang/String;Lscala/xml/MetaData;Lscala/xml/NamespaceBinding;)Z
Method	scala/xml/pull/EvElemStart.gd1$1:(Ljava/lang/String;Ljava/lang/String;Lscala/xml/MetaData;Lscala/xml/NamespaceBinding;)Z
Asciz	scala/Equals;
class	scala/Equals
NameAndType	canEqual:(Ljava/lang/Object;)Z
InterfaceMethod	scala/Equals.canEqual:(Ljava/lang/Object;)Z
Asciz	temp2;
Asciz	temp3;
Asciz	temp4;
Asciz	temp5;
Asciz	temp6;
Asciz	scala/runtime/ScalaRunTime$;
class	scala/runtime/ScalaRunTime$
Asciz	Lscala/runtime/ScalaRunTime$;;
NameAndType	MODULE$:Lscala/runtime/ScalaRunTime$;
Field	scala/runtime/ScalaRunTime$.MODULE$:Lscala/runtime/ScalaRunTime$;
Asciz	_toString;
Asciz	(Lscala/Product;)Ljava/lang/String;;
NameAndType	_toString:(Lscala/Product;)Ljava/lang/String;
Method	scala/runtime/ScalaRunTime$._toString:(Lscala/Product;)Ljava/lang/String;
Asciz	hashCode;
Asciz	_hashCode;
Asciz	(Lscala/Product;)I;
NameAndType	_hashCode:(Lscala/Product;)I
Method	scala/runtime/ScalaRunTime$._hashCode:(Lscala/Product;)I
Asciz	copy;
Asciz	(Ljava/lang/String;Ljava/lang/String;Lscala/xml/MetaData;Lscala/xml/NamespaceBinding;)Lscala/xml/pull/EvElemStart;;
NameAndType	"<init>":(Ljava/lang/String;Ljava/lang/String;Lscala/xml/MetaData;Lscala/xml/NamespaceBinding;)V
Method	scala/xml/pull/EvElemStart."<init>":(Ljava/lang/String;Ljava/lang/String;Lscala/xml/MetaData;Lscala/xml/NamespaceBinding;)V
Asciz	copy$default$1;
Asciz	copy$default$2;
Asciz	copy$default$3;
Asciz	copy$default$4;
Asciz	productElements;
Asciz	()Lscala/collection/Iterator;;
Asciz	(Lscala/Product;)Lscala/collection/Iterator;;
NameAndType	productElements:(Lscala/Product;)Lscala/collection/Iterator;
Method	scala/Product$class.productElements:(Lscala/Product;)Lscala/collection/Iterator;
Asciz	productIterator;
NameAndType	productIterator:(Lscala/Product;)Lscala/collection/Iterator;
Method	scala/Product$class.productIterator:(Lscala/Product;)Lscala/collection/Iterator;
Asciz	ScalaSig;
Asciz	scala/xml/pull/XMLEvent;
class	scala/xml/pull/XMLEvent
Asciz	scala/ScalaObject;
class	scala/ScalaObject
Asciz	scala/Product;
class	scala/Product
Asciz	java/io/Serializable;
class	java/io/Serializable

{
private final scala.xml.NamespaceBinding scope;
  Signature: Lscala/xml/NamespaceBinding;

private final scala.xml.MetaData attrs;
  Signature: Lscala/xml/MetaData;

private final java.lang.String label;
  Signature: Ljava/lang/String;

private final java.lang.String pre;
  Signature: Ljava/lang/String;

public static final scala.Function1 curry();
  Signature: ()Lscala/Function1;
  Code:
   Stack=1, Locals=0, Args_size=0
	getstatic	Field scala/xml/pull/EvElemStart$.MODULE$:Lscala/xml/pull/EvElemStart$;
	invokevirtual	Method scala/xml/pull/EvElemStart$.curry:()Lscala/Function1;
	areturn
  Labels:

public scala.xml.pull.EvElemStart(java.lang.String, java.lang.String, scala.xml.MetaData, scala.xml.NamespaceBinding);
  Signature: (Ljava/lang/String;Ljava/lang/String;Lscala/xml/MetaData;Lscala/xml/NamespaceBinding;)V
  Code:
   Stack=2, Locals=5, Args_size=5
	aload_0
	aload_1
	putfield	Field pre:Ljava/lang/String;
	aload_0
	aload_2
	putfield	Field label:Ljava/lang/String;
	aload_0
	aload_3
	putfield	Field attrs:Lscala/xml/MetaData;
	aload_0
	aload	4
	putfield	Field scope:Lscala/xml/NamespaceBinding;
	aload_0
	invokespecial	Method java/lang/Object."<init>":()V
	aload_0
	invokestatic	Method scala/Product$class.$init$:(Lscala/Product;)V
	return
  Labels:
  LocalVariableTable: 
   Start  Length  Slot  Name   Signature
   0      30      0    this       Lscala/xml/pull/EvElemStart;
   0      30      1    pre       Ljava/lang/String;
   0      30      2    label       Ljava/lang/String;
   0      30      3    attrs       Lscala/xml/MetaData;
   0      30      4    scope       Lscala/xml/NamespaceBinding;


private final boolean gd1$1(java.lang.String, java.lang.String, scala.xml.MetaData, scala.xml.NamespaceBinding);
  Signature: (Ljava/lang/String;Ljava/lang/String;Lscala/xml/MetaData;Lscala/xml/NamespaceBinding;)Z
  Code:
   Stack=2, Locals=9, Args_size=5
	aload_1
	aload_0
	invokevirtual	Method pre:()Ljava/lang/String;
	astore	5
	dup
	ifnonnull	l1 // aload
	pop
	aload	5
	ifnull	l2 // aload_2
	goto	l3 // iconst_0
l1	aload	5
	invokevirtual	Method java/lang/Object.equals:(Ljava/lang/Object;)Z
	ifeq	l3 // iconst_0
l2	aload_2
	aload_0
	invokevirtual	Method label:()Ljava/lang/String;
	astore	6
	dup
	ifnonnull	l4 // aload
	pop
	aload	6
	ifnull	l5 // aload_3
	goto	l3 // iconst_0
l4	aload	6
	invokevirtual	Method java/lang/Object.equals:(Ljava/lang/Object;)Z
	ifeq	l3 // iconst_0
l5	aload_3
	aload_0
	invokevirtual	Method attrs:()Lscala/xml/MetaData;
	astore	7
	dup
	ifnonnull	l6 // aload
	pop
	aload	7
	ifnull	l7 // aload
	goto	l3 // iconst_0
l6	aload	7
	invokevirtual	Method java/lang/Object.equals:(Ljava/lang/Object;)Z
	ifeq	l3 // iconst_0
l7	aload	4
	aload_0
	invokevirtual	Method scope:()Lscala/xml/NamespaceBinding;
	astore	8
	dup
	ifnonnull	l8 // aload
	pop
	aload	8
	ifnull	l9 // iconst_1
	goto	l3 // iconst_0
l8	aload	8
	invokevirtual	Method java/lang/Object.equals:(Ljava/lang/Object;)Z
	ifeq	l3 // iconst_0
l9	iconst_1
	goto	l10 // ireturn
l3	iconst_0
l10	ireturn
  Labels:
   	l1 = 20 // aload
   	l2 = 28 // aload_2
   	l4 = 48 // aload
   	l5 = 56 // aload_3
   	l6 = 76 // aload
   	l7 = 84 // aload
   	l8 = 105 // aload
   	l9 = 113 // iconst_1
   	l3 = 117 // iconst_0
   	l10 = 118 // ireturn

public boolean canEqual(java.lang.Object);
  Signature: (Ljava/lang/Object;)Z
  Code:
   Stack=1, Locals=2, Args_size=2
	aload_1
	instanceof	class scala/xml/pull/EvElemStart
	ireturn
  Labels:

public java.lang.Object productElement(int);
  Signature: (I)Ljava/lang/Object;
  Code:
   Stack=3, Locals=2, Args_size=2
	iload_1
	tableswitch{ //0 to 3
		0: 144;
		1: 118;
		2: 92;
		3: 66;
		default: 32 }
	iconst_1
	ifeq	l1 // new
	new	class java/lang/IndexOutOfBoundsException
	dup
	iload_1
	invokestatic	Method scala/runtime/BoxesRunTime.boxToInteger:(I)Ljava/lang/Integer;
	invokevirtual	Method java/lang/Object.toString:()Ljava/lang/String;
	invokespecial	Method java/lang/IndexOutOfBoundsException."<init>":(Ljava/lang/String;)V
	athrow
l1	new	class scala/MatchError
	dup
	iload_1
	invokestatic	Method scala/runtime/BoxesRunTime.boxToInteger:(I)Ljava/lang/Integer;
	invokevirtual	Method java/lang/Object.toString:()Ljava/lang/String;
	invokespecial	Method scala/MatchError."<init>":(Ljava/lang/String;)V
	athrow
	iconst_1
	ifeq	l2 // new
	aload_0
	invokevirtual	Method scope:()Lscala/xml/NamespaceBinding;
	goto	l3 // areturn
l2	new	class scala/MatchError
	dup
	iload_1
	invokestatic	Method scala/runtime/BoxesRunTime.boxToInteger:(I)Ljava/lang/Integer;
	invokevirtual	Method java/lang/Object.toString:()Ljava/lang/String;
	invokespecial	Method scala/MatchError."<init>":(Ljava/lang/String;)V
	athrow
	iconst_1
	ifeq	l4 // new
	aload_0
	invokevirtual	Method attrs:()Lscala/xml/MetaData;
	goto	l3 // areturn
l4	new	class scala/MatchError
	dup
	iload_1
	invokestatic	Method scala/runtime/BoxesRunTime.boxToInteger:(I)Ljava/lang/Integer;
	invokevirtual	Method java/lang/Object.toString:()Ljava/lang/String;
	invokespecial	Method scala/MatchError."<init>":(Ljava/lang/String;)V
	athrow
	iconst_1
	ifeq	l5 // new
	aload_0
	invokevirtual	Method label:()Ljava/lang/String;
	goto	l3 // areturn
l5	new	class scala/MatchError
	dup
	iload_1
	invokestatic	Method scala/runtime/BoxesRunTime.boxToInteger:(I)Ljava/lang/Integer;
	invokevirtual	Method java/lang/Object.toString:()Ljava/lang/String;
	invokespecial	Method scala/MatchError."<init>":(Ljava/lang/String;)V
	athrow
	iconst_1
	ifeq	l6 // new
	aload_0
	invokevirtual	Method pre:()Ljava/lang/String;
l3	areturn
l6	new	class scala/MatchError
	dup
	iload_1
	invokestatic	Method scala/runtime/BoxesRunTime.boxToInteger:(I)Ljava/lang/Integer;
	invokevirtual	Method java/lang/Object.toString:()Ljava/lang/String;
	invokespecial	Method scala/MatchError."<init>":(Ljava/lang/String;)V
	athrow
  Labels:
   	l1 = 51 // new
   	l2 = 77 // new
   	l4 = 103 // new
   	l5 = 129 // new
   	l3 = 152 // areturn
   	l6 = 153 // new

public int productArity();
  Signature: ()I
  Code:
   Stack=1, Locals=1, Args_size=1
	iconst_4
	ireturn
  Labels:

public java.lang.String productPrefix();
  Signature: ()Ljava/lang/String;
  Code:
   Stack=1, Locals=1, Args_size=1
	ldc	String EvElemStart
	areturn
  Labels:

public boolean equals(java.lang.Object);
  Signature: (Ljava/lang/Object;)Z
  Code:
   Stack=5, Locals=7, Args_size=2
	aload_0
	aload_1
	if_acmpeq	l1 // iconst_1
	aload_1
	instanceof	class scala/xml/pull/EvElemStart
	ifeq	l2 // iconst_1
	aload_1
	checkcast	class scala/xml/pull/EvElemStart
	astore_2
	aload_2
	invokevirtual	Method pre:()Ljava/lang/String;
	astore_3
	aload_2
	invokevirtual	Method label:()Ljava/lang/String;
	astore	4
	aload_2
	invokevirtual	Method attrs:()Lscala/xml/MetaData;
	astore	5
	aload_2
	invokevirtual	Method scope:()Lscala/xml/NamespaceBinding;
	astore	6
	aload_0
	aload_3
	aload	4
	aload	5
	aload	6
	invokespecial	Method gd1$1:(Ljava/lang/String;Ljava/lang/String;Lscala/xml/MetaData;Lscala/xml/NamespaceBinding;)Z
	ifeq	l3 // iconst_1
	aload_1
	checkcast	class scala/xml/pull/EvElemStart
	aload_0
	invokeinterface	InterfaceMethod scala/Equals.canEqual:(Ljava/lang/Object;)Z
	goto	l4 // ifeq
l3	iconst_1
	ifeq	l5 // new
	iconst_0
	goto	l4 // ifeq
l5	new	class scala/MatchError
	dup
	aload_1
	invokevirtual	Method java/lang/Object.toString:()Ljava/lang/String;
	invokespecial	Method scala/MatchError."<init>":(Ljava/lang/String;)V
	athrow
l2	iconst_1
	ifeq	l6 // new
	iconst_0
l4	ifeq	l7 // iconst_0
l1	iconst_1
	goto	l8 // ireturn
l7	iconst_0
l8	ireturn
l6	new	class scala/MatchError
	dup
	aload_1
	invokevirtual	Method java/lang/Object.toString:()Ljava/lang/String;
	invokespecial	Method scala/MatchError."<init>":(Ljava/lang/String;)V
	athrow
  Labels:
   	l3 = 67 // iconst_1
   	l5 = 75 // new
   	l2 = 87 // iconst_1
   	l4 = 92 // ifeq
   	l1 = 95 // iconst_1
   	l7 = 99 // iconst_0
   	l8 = 100 // ireturn
   	l6 = 101 // new
  LocalVariableTable: 
   Start  Length  Slot  Name   Signature
   0      113      0    this       Lscala/xml/pull/EvElemStart;
   17      70      2    temp2       Lscala/xml/pull/EvElemStart;
   22      65      3    temp3       Ljava/lang/String;
   28      59      4    temp4       Ljava/lang/String;
   34      53      5    temp5       Lscala/xml/MetaData;
   40      47      6    temp6       Lscala/xml/NamespaceBinding;


public java.lang.String toString();
  Signature: ()Ljava/lang/String;
  Code:
   Stack=2, Locals=1, Args_size=1
	getstatic	Field scala/runtime/ScalaRunTime$.MODULE$:Lscala/runtime/ScalaRunTime$;
	aload_0
	invokevirtual	Method scala/runtime/ScalaRunTime$._toString:(Lscala/Product;)Ljava/lang/String;
	areturn
  Labels:

public int hashCode();
  Signature: ()I
  Code:
   Stack=2, Locals=1, Args_size=1
	getstatic	Field scala/runtime/ScalaRunTime$.MODULE$:Lscala/runtime/ScalaRunTime$;
	aload_0
	invokevirtual	Method scala/runtime/ScalaRunTime$._hashCode:(Lscala/Product;)I
	ireturn
  Labels:

public scala.xml.pull.EvElemStart copy(java.lang.String, java.lang.String, scala.xml.MetaData, scala.xml.NamespaceBinding);
  Signature: (Ljava/lang/String;Ljava/lang/String;Lscala/xml/MetaData;Lscala/xml/NamespaceBinding;)Lscala/xml/pull/EvElemStart;
  Code:
   Stack=6, Locals=5, Args_size=5
	new	class scala/xml/pull/EvElemStart
	dup
	aload_1
	aload_2
	aload_3
	aload	4
	invokespecial	Method "<init>":(Ljava/lang/String;Ljava/lang/String;Lscala/xml/MetaData;Lscala/xml/NamespaceBinding;)V
	areturn
  Labels:
  LocalVariableTable: 
   Start  Length  Slot  Name   Signature
   0      13      0    this       Lscala/xml/pull/EvElemStart;
   0      13      1    pre       Ljava/lang/String;
   0      13      2    label       Ljava/lang/String;
   0      13      3    attrs       Lscala/xml/MetaData;
   0      13      4    scope       Lscala/xml/NamespaceBinding;


public scala.xml.NamespaceBinding scope();
  Signature: ()Lscala/xml/NamespaceBinding;
  Code:
   Stack=1, Locals=1, Args_size=1
	aload_0
	getfield	Field scope:Lscala/xml/NamespaceBinding;
	areturn
  Labels:

public scala.xml.MetaData attrs();
  Signature: ()Lscala/xml/MetaData;
  Code:
   Stack=1, Locals=1, Args_size=1
	aload_0
	getfield	Field attrs:Lscala/xml/MetaData;
	areturn
  Labels:

public java.lang.String label();
  Signature: ()Ljava/lang/String;
  Code:
   Stack=1, Locals=1, Args_size=1
	aload_0
	getfield	Field label:Ljava/lang/String;
	areturn
  Labels:

public java.lang.String pre();
  Signature: ()Ljava/lang/String;
  Code:
   Stack=1, Locals=1, Args_size=1
	aload_0
	getfield	Field pre:Ljava/lang/String;
	areturn
  Labels:

public java.lang.String copy$default$1();
  Signature: ()Ljava/lang/String;
  Code:
   Stack=1, Locals=1, Args_size=1
	aload_0
	invokevirtual	Method pre:()Ljava/lang/String;
	areturn
  Labels:

public java.lang.String copy$default$2();
  Signature: ()Ljava/lang/String;
  Code:
   Stack=1, Locals=1, Args_size=1
	aload_0
	invokevirtual	Method label:()Ljava/lang/String;
	areturn
  Labels:

public scala.xml.MetaData copy$default$3();
  Signature: ()Lscala/xml/MetaData;
  Code:
   Stack=1, Locals=1, Args_size=1
	aload_0
	invokevirtual	Method attrs:()Lscala/xml/MetaData;
	areturn
  Labels:

public scala.xml.NamespaceBinding copy$default$4();
  Signature: ()Lscala/xml/NamespaceBinding;
  Code:
   Stack=1, Locals=1, Args_size=1
	aload_0
	invokevirtual	Method scope:()Lscala/xml/NamespaceBinding;
	areturn
  Labels:

public scala.collection.Iterator productElements();
  Signature: ()Lscala/collection/Iterator;
  Code:
   Stack=1, Locals=1, Args_size=1
	aload_0
	invokestatic	Method scala/Product$class.productElements:(Lscala/Product;)Lscala/collection/Iterator;
	areturn
  Labels:

public scala.collection.Iterator productIterator();
  Signature: ()Lscala/collection/Iterator;
  Code:
   Stack=1, Locals=1, Args_size=1
	aload_0
	invokestatic	Method scala/Product$class.productIterator:(Lscala/Product;)Lscala/collection/Iterator;
	areturn
  Labels:

}

