Compiled from "XMLEvent.scala"
public final class scala.xml.pull.EvElemStart$ extends java.lang.Object implements scala.Function4,scala.ScalaObject
  SourceFile: "XMLEvent.scala"
  Scala: length = 0x
   
  minor version: 0
  major version: 49
  Constant pool:
const #1 = Asciz	SourceFile;
const #2 = Asciz	XMLEvent.scala;
const #3 = Asciz	Scala;
const #4 = Asciz	MODULE$;
const #5 = Asciz	Lscala/xml/pull/EvElemStart$;;
const #6 = Asciz	<clinit>;
const #7 = Asciz	()V;
const #8 = Asciz	Code;
const #9 = Asciz	scala/xml/pull/EvElemStart$;
const #10 = class	#9;	//  scala/xml/pull/EvElemStart$
const #11 = Asciz	<init>;
const #12 = NameAndType	#11:#7;//  "<init>":()V
const #13 = Method	#10.#12;	//  scala/xml/pull/EvElemStart$."<init>":()V
const #14 = Asciz	LineNumberTable;
const #15 = Asciz	java/lang/Object;
const #16 = class	#15;	//  java/lang/Object
const #17 = Method	#16.#12;	//  java/lang/Object."<init>":()V
const #18 = NameAndType	#4:#5;//  MODULE$:Lscala/xml/pull/EvElemStart$;
const #19 = Field	#10.#18;	//  scala/xml/pull/EvElemStart$.MODULE$:Lscala/xml/pull/EvElemStart$;
const #20 = Asciz	scala/Function4$class;
const #21 = class	#20;	//  scala/Function4$class
const #22 = Asciz	$init$;
const #23 = Asciz	(Lscala/Function4;)V;
const #24 = NameAndType	#22:#23;//  $init$:(Lscala/Function4;)V
const #25 = Method	#21.#24;	//  scala/Function4$class.$init$:(Lscala/Function4;)V
const #26 = Asciz	apply;
const #27 = Asciz	(Ljava/lang/Object;Ljava/lang/Object;Ljava/lang/Object;Ljava/lang/Object;)Ljava/lang/Object;;
const #28 = Asciz	java/lang/String;
const #29 = class	#28;	//  java/lang/String
const #30 = Asciz	scala/xml/MetaData;
const #31 = class	#30;	//  scala/xml/MetaData
const #32 = Asciz	scala/xml/NamespaceBinding;
const #33 = class	#32;	//  scala/xml/NamespaceBinding
const #34 = Asciz	(Ljava/lang/String;Ljava/lang/String;Lscala/xml/MetaData;Lscala/xml/NamespaceBinding;)Lscala/xml/pull/EvElemStart;;
const #35 = NameAndType	#26:#34;//  apply:(Ljava/lang/String;Ljava/lang/String;Lscala/xml/MetaData;Lscala/xml/NamespaceBinding;)Lscala/xml/pull/EvElemStart;
const #36 = Method	#10.#35;	//  scala/xml/pull/EvElemStart$.apply:(Ljava/lang/String;Ljava/lang/String;Lscala/xml/MetaData;Lscala/xml/NamespaceBinding;)Lscala/xml/pull/EvElemStart;
const #37 = Asciz	this;
const #38 = Asciz	v1;
const #39 = Asciz	Ljava/lang/Object;;
const #40 = Asciz	v2;
const #41 = Asciz	v3;
const #42 = Asciz	v4;
const #43 = Asciz	LocalVariableTable;
const #44 = Asciz	scala/xml/pull/EvElemStart;
const #45 = class	#44;	//  scala/xml/pull/EvElemStart
const #46 = Asciz	(Ljava/lang/String;Ljava/lang/String;Lscala/xml/MetaData;Lscala/xml/NamespaceBinding;)V;
const #47 = NameAndType	#11:#46;//  "<init>":(Ljava/lang/String;Ljava/lang/String;Lscala/xml/MetaData;Lscala/xml/NamespaceBinding;)V
const #48 = Method	#45.#47;	//  scala/xml/pull/EvElemStart."<init>":(Ljava/lang/String;Ljava/lang/String;Lscala/xml/MetaData;Lscala/xml/NamespaceBinding;)V
const #49 = Asciz	pre;
const #50 = Asciz	Ljava/lang/String;;
const #51 = Asciz	label;
const #52 = Asciz	attrs;
const #53 = Asciz	Lscala/xml/MetaData;;
const #54 = Asciz	scope;
const #55 = Asciz	Lscala/xml/NamespaceBinding;;
const #56 = Asciz	unapply;
const #57 = Asciz	(Lscala/xml/pull/EvElemStart;)Lscala/Some;;
const #58 = Asciz	scala/Some;
const #59 = class	#58;	//  scala/Some
const #60 = Asciz	scala/Tuple4;
const #61 = class	#60;	//  scala/Tuple4
const #62 = Asciz	()Ljava/lang/String;;
const #63 = NameAndType	#49:#62;//  pre:()Ljava/lang/String;
const #64 = Method	#45.#63;	//  scala/xml/pull/EvElemStart.pre:()Ljava/lang/String;
const #65 = NameAndType	#51:#62;//  label:()Ljava/lang/String;
const #66 = Method	#45.#65;	//  scala/xml/pull/EvElemStart.label:()Ljava/lang/String;
const #67 = Asciz	()Lscala/xml/MetaData;;
const #68 = NameAndType	#52:#67;//  attrs:()Lscala/xml/MetaData;
const #69 = Method	#45.#68;	//  scala/xml/pull/EvElemStart.attrs:()Lscala/xml/MetaData;
const #70 = Asciz	()Lscala/xml/NamespaceBinding;;
const #71 = NameAndType	#54:#70;//  scope:()Lscala/xml/NamespaceBinding;
const #72 = Method	#45.#71;	//  scala/xml/pull/EvElemStart.scope:()Lscala/xml/NamespaceBinding;
const #73 = Asciz	(Ljava/lang/Object;Ljava/lang/Object;Ljava/lang/Object;Ljava/lang/Object;)V;
const #74 = NameAndType	#11:#73;//  "<init>":(Ljava/lang/Object;Ljava/lang/Object;Ljava/lang/Object;Ljava/lang/Object;)V
const #75 = Method	#61.#74;	//  scala/Tuple4."<init>":(Ljava/lang/Object;Ljava/lang/Object;Ljava/lang/Object;Ljava/lang/Object;)V
const #76 = Asciz	(Ljava/lang/Object;)V;
const #77 = NameAndType	#11:#76;//  "<init>":(Ljava/lang/Object;)V
const #78 = Method	#59.#77;	//  scala/Some."<init>":(Ljava/lang/Object;)V
const #79 = Asciz	x$0;
const #80 = Asciz	Lscala/xml/pull/EvElemStart;;
const #81 = Asciz	curry;
const #82 = Asciz	()Lscala/Function1;;
const #83 = Asciz	(Lscala/Function4;)Lscala/Function1;;
const #84 = NameAndType	#81:#83;//  curry:(Lscala/Function4;)Lscala/Function1;
const #85 = Method	#21.#84;	//  scala/Function4$class.curry:(Lscala/Function4;)Lscala/Function1;
const #86 = Asciz	toString;
const #87 = Asciz	(Lscala/Function4;)Ljava/lang/String;;
const #88 = NameAndType	#86:#87;//  toString:(Lscala/Function4;)Ljava/lang/String;
const #89 = Method	#21.#88;	//  scala/Function4$class.toString:(Lscala/Function4;)Ljava/lang/String;
const #90 = Asciz	scala/Function4;
const #91 = class	#90;	//  scala/Function4
const #92 = Asciz	scala/ScalaObject;
const #93 = class	#92;	//  scala/ScalaObject

{
public static final scala.xml.pull.EvElemStart$ MODULE$;

public static {};
  Code:
   Stack=1, Locals=0, Args_size=0
   0:	new	#10; //class scala/xml/pull/EvElemStart$
   3:	invokespecial	#13; //Method "<init>":()V
   6:	return

public java.lang.Object apply(java.lang.Object, java.lang.Object, java.lang.Object, java.lang.Object);
  Code:
   Stack=5, Locals=5, Args_size=5
   0:	aload_0
   1:	aload_1
   2:	checkcast	#29; //class java/lang/String
   5:	aload_2
   6:	checkcast	#29; //class java/lang/String
   9:	aload_3
   10:	checkcast	#31; //class scala/xml/MetaData
   13:	aload	4
   15:	checkcast	#33; //class scala/xml/NamespaceBinding
   18:	invokevirtual	#36; //Method apply:(Ljava/lang/String;Ljava/lang/String;Lscala/xml/MetaData;Lscala/xml/NamespaceBinding;)Lscala/xml/pull/EvElemStart;
   21:	areturn
  LineNumberTable: 
   line 23: 0

  LocalVariableTable: 
   Start  Length  Slot  Name   Signature
   0      22      0    this       Lscala/xml/pull/EvElemStart$;
   0      22      1    v1       Ljava/lang/Object;
   0      22      2    v2       Ljava/lang/Object;
   0      22      3    v3       Ljava/lang/Object;
   0      22      4    v4       Ljava/lang/Object;


public scala.xml.pull.EvElemStart apply(java.lang.String, java.lang.String, scala.xml.MetaData, scala.xml.NamespaceBinding);
  Code:
   Stack=6, Locals=5, Args_size=5
   0:	new	#45; //class scala/xml/pull/EvElemStart
   3:	dup
   4:	aload_1
   5:	aload_2
   6:	aload_3
   7:	aload	4
   9:	invokespecial	#48; //Method scala/xml/pull/EvElemStart."<init>":(Ljava/lang/String;Ljava/lang/String;Lscala/xml/MetaData;Lscala/xml/NamespaceBinding;)V
   12:	areturn
  LineNumberTable: 
   line 23: 0

  LocalVariableTable: 
   Start  Length  Slot  Name   Signature
   0      13      0    this       Lscala/xml/pull/EvElemStart$;
   0      13      1    pre       Ljava/lang/String;
   0      13      2    label       Ljava/lang/String;
   0      13      3    attrs       Lscala/xml/MetaData;
   0      13      4    scope       Lscala/xml/NamespaceBinding;


public scala.Some unapply(scala.xml.pull.EvElemStart);
  Code:
   Stack=8, Locals=2, Args_size=2
   0:	new	#59; //class scala/Some
   3:	dup
   4:	new	#61; //class scala/Tuple4
   7:	dup
   8:	aload_1
   9:	invokevirtual	#64; //Method scala/xml/pull/EvElemStart.pre:()Ljava/lang/String;
   12:	aload_1
   13:	invokevirtual	#66; //Method scala/xml/pull/EvElemStart.label:()Ljava/lang/String;
   16:	aload_1
   17:	invokevirtual	#69; //Method scala/xml/pull/EvElemStart.attrs:()Lscala/xml/MetaData;
   20:	aload_1
   21:	invokevirtual	#72; //Method scala/xml/pull/EvElemStart.scope:()Lscala/xml/NamespaceBinding;
   24:	invokespecial	#75; //Method scala/Tuple4."<init>":(Ljava/lang/Object;Ljava/lang/Object;Ljava/lang/Object;Ljava/lang/Object;)V
   27:	invokespecial	#78; //Method scala/Some."<init>":(Ljava/lang/Object;)V
   30:	areturn
  LineNumberTable: 
   line 23: 0

  LocalVariableTable: 
   Start  Length  Slot  Name   Signature
   0      31      0    this       Lscala/xml/pull/EvElemStart$;
   0      31      1    x$0       Lscala/xml/pull/EvElemStart;


public scala.Function1 curry();
  Code:
   Stack=1, Locals=1, Args_size=1
   0:	aload_0
   1:	invokestatic	#85; //Method scala/Function4$class.curry:(Lscala/Function4;)Lscala/Function1;
   4:	areturn
  LineNumberTable: 
   line 23: 0


public java.lang.String toString();
  Code:
   Stack=1, Locals=1, Args_size=1
   0:	aload_0
   1:	invokestatic	#89; //Method scala/Function4$class.toString:(Lscala/Function4;)Ljava/lang/String;
   4:	areturn
  LineNumberTable: 
   line 23: 0


}

