Compiled from "XMLEvent.scala"
public class scala.xml.pull.EvElemEnd extends java.lang.Object implements scala.xml.pull.XMLEvent,scala.ScalaObject,scala.Product,java.io.Serializable
  SourceFile: "XMLEvent.scala"
  ScalaSig: length = 0x3A8
   05 00 FFFFFF81 09 06 08 01 02 FFFFFF84 FFFFFF80 FFFFFF80 FFFFFF80 40 09 02 09
   45 76 45 6C 65 6D 45 6E 64 0A 02 03 04 01 04 70
   75 6C 6C 0A 02 05 06 01 03 78 6D 6C 0A 01 07 01
   05 73 63 61 6C 61 03 00 13 05 00 0A 12 16 1A 10
   02 0B 10 0D 01 0C 0A 02 0D 0E 01 04 6C 61 6E 67
   0A 01 0F 01 04 6A 61 76 61 09 02 11 0C 02 06 4F
   62 6A 65 63 74 10 02 13 14 0D 01 02 09 02 15 02
   02 08 58 4D 4C 45 76 65 6E 74 10 02 17 18 0D 01
   06 09 02 19 06 02 0B 53 63 61 6C 61 4F 62 6A 65
   63 74 10 02 17 1B 09 02 1C 06 02 07 50 72 6F 64
   75 63 74 08 08 1E 00 FFFFFF82 FFFFFFCA FFFFFF80 FFFFFF84 00 1F 01 03 70
   72 65 15 01 20 10 02 21 24 0E 02 17 22 09 02 23
   06 01 06 50 72 65 64 65 66 09 02 25 26 02 06 53
   74 72 69 6E 67 0A 02 23 06 08 08 28 00 FFFFFF82 FFFFFF88 FFFFFFA0
   FFFFFF80 04 20 01 04 70 72 65 20 08 08 2A 00 FFFFFF82 FFFFFFCA FFFFFF80
   FFFFFF84 00 1F 01 05 6C 61 62 65 6C 08 08 2C 00 FFFFFF82 FFFFFF88
   FFFFFFA0 FFFFFF80 04 20 01 06 6C 61 62 65 6C 20 08 05 2E 00
   FFFFFF84 00 2F 01 06 3C 69 6E 69 74 3E 14 03 30 31 32
   10 02 13 00 08 05 1E 2D FFFFFFC0 00 20 08 05 2A 2D FFFFFFC0
   00 20 08 07 34 00 FFFFFF81 FFFFFF80 FFFFFF84 00 35 01 04 63 6F 70
   79 14 03 30 36 44 08 08 37 1E 33 FFFFFF90 FFFFFF80 FFFFFFC0 00 20
   08 07 38 00 FFFFFF91 FFFFFF80 FFFFFF84 00 39 01 0E 63 6F 70 79 24
   64 65 66 61 75 6C 74 24 31 15 01 3A 2A 02 20 3B
   2B 01 3C 10 02 3D 42 0D 01 3E 0A 02 3F 40 01 09
   75 6E 63 68 65 63 6B 65 64 0A 02 41 06 01 0A 61
   6E 6E 6F 74 61 74 69 6F 6E 09 02 43 3E 02 11 75
   6E 63 68 65 63 6B 65 64 56 61 72 69 61 6E 63 65
   08 08 45 2A 33 FFFFFF90 FFFFFF80 FFFFFFC0 00 20 08 07 46 00 FFFFFF91 FFFFFF80
   FFFFFF84 00 39 01 0E 63 6F 70 79 24 64 65 66 61 75 6C
   74 24 32 08 08 48 00 FFFFFF84 FFFFFF80 FFFFFF80 FFFFFF84 20 49 01 08 68
   61 73 68 43 6F 64 65 14 01 4A 10 02 17 4B 09 02
   4C 06 02 03 49 6E 74 08 08 4E 00 FFFFFF84 FFFFFF80 FFFFFF80 FFFFFF84 20
   4F 01 08 74 6F 53 74 72 69 6E 67 14 01 20 08 08
   51 00 FFFFFF84 FFFFFF80 FFFFFF80 FFFFFF84 20 52 01 06 65 71 75 61 6C 73
   14 02 53 56 10 02 17 54 09 02 55 06 02 07 42 6F
   6F 6C 65 61 6E 08 07 57 50 FFFFFF81 FFFFFF80 FFFFFFC0 00 58 01 03
   78 24 31 10 02 17 59 09 02 5A 06 02 03 41 6E 79
   08 08 5C 00 FFFFFF84 FFFFFF80 FFFFFF80 FFFFFF84 20 5D 01 0D 70 72 6F 64
   75 63 74 50 72 65 66 69 78 15 01 5E 10 02 0B 5F
   09 02 25 0C 08 08 61 00 FFFFFF84 FFFFFF80 FFFFFF80 FFFFFF84 20 62 01 0C
   70 72 6F 64 75 63 74 41 72 69 74 79 15 01 4A 08
   08 64 00 FFFFFF84 FFFFFF80 FFFFFF80 FFFFFF84 20 65 01 0E 70 72 6F 64 75
   63 74 45 6C 65 6D 65 6E 74 14 02 58 66 08 07 57
   63 FFFFFF81 FFFFFF80 FFFFFFC0 00 4A 08 08 68 00 FFFFFF84 FFFFFF80 FFFFFF80 FFFFFF84 20 69
   01 08 63 61 6E 45 71 75 61 6C 14 02 53 6A 08 07
   57 67 FFFFFF81 FFFFFF80 FFFFFFC0 00 58 28 02 00 6C 10 02 17 6D 09
   02 6E 06 02 0C 73 65 72 69 61 6C 69 7A 61 62 6C
   65 07 07 70 02 FFFFFF81 FFFFFF80 FFFFFF88 02 71 01 09 45 76 45 6C
   65 6D 45 6E 64 10 02 13 72 06 08 01 02 FFFFFF84 FFFFFF81 FFFFFF80
   FFFFFF88 02 73 13 04 72 0A 74 16 10 05 17 75 20 20 30
   09 02 76 06 02 09 46 75 6E 63 74 69 6F 6E 32 08
   05 2E 72 FFFFFF84 00 78 14 01 71 08 07 7A 72 FFFFFF81 FFFFFF80 FFFFFF84
   40 7B 01 05 61 70 70 6C 79 14 03 30 7C 7D 08 05
   1E 79 FFFFFFC0 00 20 08 05 2A 79 FFFFFFC0 00 20 08 08 7F 72
   FFFFFF81 FFFFFF80 FFFFFF84 40 FFFFFF81 00 01 07 75 6E 61 70 70 6C 79 14
   04 FFFFFF81 01 FFFFFF81 07 10 05 17 FFFFFF81 02 FFFFFF81 04 09 03 FFFFFF81 03
   06 02 04 53 6F 6D 65 10 05 17 FFFFFF81 05 20 20 09 03
   FFFFFF81 06 06 02 06 54 75 70 6C 65 32 08 06 FFFFFF81 08 7E
   FFFFFFC0 00 30 01 03 78 24 30 
  minor version: 0
  major version: 49
  Constant pool:
Asciz	SourceFile;
Asciz	XMLEvent.scala;
Asciz	tuple;
Asciz	()Lscala/Function1;;
Asciz	Code;
Asciz	scala/xml/pull/EvElemEnd$;
class	scala/xml/pull/EvElemEnd$
Asciz	MODULE$;
Asciz	Lscala/xml/pull/EvElemEnd$;;
NameAndType	MODULE$:Lscala/xml/pull/EvElemEnd$;
Field	scala/xml/pull/EvElemEnd$.MODULE$:Lscala/xml/pull/EvElemEnd$;
NameAndType	tuple:()Lscala/Function1;
Method	scala/xml/pull/EvElemEnd$.tuple:()Lscala/Function1;
Asciz	curry;
NameAndType	curry:()Lscala/Function1;
Method	scala/xml/pull/EvElemEnd$.curry:()Lscala/Function1;
Asciz	label;
Asciz	Ljava/lang/String;;
Asciz	pre;
Asciz	<init>;
Asciz	(Ljava/lang/String;Ljava/lang/String;)V;
Asciz	LineNumberTable;
Asciz	scala/xml/pull/EvElemEnd;
class	scala/xml/pull/EvElemEnd
NameAndType	pre:Ljava/lang/String;
Field	scala/xml/pull/EvElemEnd.pre:Ljava/lang/String;
NameAndType	label:Ljava/lang/String;
Field	scala/xml/pull/EvElemEnd.label:Ljava/lang/String;
Asciz	java/lang/Object;
class	java/lang/Object
Asciz	()V;
NameAndType	"<init>":()V
Method	java/lang/Object."<init>":()V
Asciz	scala/Product$class;
class	scala/Product$class
Asciz	$init$;
Asciz	(Lscala/Product;)V;
NameAndType	$init$:(Lscala/Product;)V
Method	scala/Product$class.$init$:(Lscala/Product;)V
Asciz	this;
Asciz	Lscala/xml/pull/EvElemEnd;;
Asciz	LocalVariableTable;
Asciz	gd2$1;
Asciz	(Ljava/lang/String;Ljava/lang/String;)Z;
Asciz	()Ljava/lang/String;;
NameAndType	pre:()Ljava/lang/String;
Method	scala/xml/pull/EvElemEnd.pre:()Ljava/lang/String;
Asciz	equals;
Asciz	(Ljava/lang/Object;)Z;
NameAndType	equals:(Ljava/lang/Object;)Z
Method	java/lang/Object.equals:(Ljava/lang/Object;)Z
NameAndType	label:()Ljava/lang/String;
Method	scala/xml/pull/EvElemEnd.label:()Ljava/lang/String;
Asciz	canEqual;
Asciz	productElement;
Asciz	(I)Ljava/lang/Object;;
Asciz	java/lang/IndexOutOfBoundsException;
class	java/lang/IndexOutOfBoundsException
Asciz	scala/runtime/BoxesRunTime;
class	scala/runtime/BoxesRunTime
Asciz	boxToInteger;
Asciz	(I)Ljava/lang/Integer;;
NameAndType	boxToInteger:(I)Ljava/lang/Integer;
Method	scala/runtime/BoxesRunTime.boxToInteger:(I)Ljava/lang/Integer;
Asciz	toString;
NameAndType	toString:()Ljava/lang/String;
Method	java/lang/Object.toString:()Ljava/lang/String;
Asciz	(Ljava/lang/String;)V;
NameAndType	"<init>":(Ljava/lang/String;)V
Method	java/lang/IndexOutOfBoundsException."<init>":(Ljava/lang/String;)V
Asciz	scala/MatchError;
class	scala/MatchError
Method	scala/MatchError."<init>":(Ljava/lang/String;)V
Asciz	productArity;
Asciz	()I;
Asciz	productPrefix;
Asciz	EvElemEnd;
String	EvElemEnd
NameAndType	gd2$1:(Ljava/lang/String;Ljava/lang/String;)Z
Method	scala/xml/pull/EvElemEnd.gd2$1:(Ljava/lang/String;Ljava/lang/String;)Z
Asciz	scala/Equals;
class	scala/Equals
NameAndType	canEqual:(Ljava/lang/Object;)Z
InterfaceMethod	scala/Equals.canEqual:(Ljava/lang/Object;)Z
Asciz	temp9;
Asciz	temp10;
Asciz	temp11;
Asciz	scala/runtime/ScalaRunTime$;
class	scala/runtime/ScalaRunTime$
Asciz	Lscala/runtime/ScalaRunTime$;;
NameAndType	MODULE$:Lscala/runtime/ScalaRunTime$;
Field	scala/runtime/ScalaRunTime$.MODULE$:Lscala/runtime/ScalaRunTime$;
Asciz	_toString;
Asciz	(Lscala/Product;)Ljava/lang/String;;
NameAndType	_toString:(Lscala/Product;)Ljava/lang/String;
Method	scala/runtime/ScalaRunTime$._toString:(Lscala/Product;)Ljava/lang/String;
Asciz	hashCode;
Asciz	_hashCode;
Asciz	(Lscala/Product;)I;
NameAndType	_hashCode:(Lscala/Product;)I
Method	scala/runtime/ScalaRunTime$._hashCode:(Lscala/Product;)I
Asciz	copy;
Asciz	(Ljava/lang/String;Ljava/lang/String;)Lscala/xml/pull/EvElemEnd;;
NameAndType	"<init>":(Ljava/lang/String;Ljava/lang/String;)V
Method	scala/xml/pull/EvElemEnd."<init>":(Ljava/lang/String;Ljava/lang/String;)V
Asciz	copy$default$1;
Asciz	copy$default$2;
Asciz	productElements;
Asciz	()Lscala/collection/Iterator;;
Asciz	(Lscala/Product;)Lscala/collection/Iterator;;
NameAndType	productElements:(Lscala/Product;)Lscala/collection/Iterator;
Method	scala/Product$class.productElements:(Lscala/Product;)Lscala/collection/Iterator;
Asciz	Deprecated;
Asciz	productIterator;
NameAndType	productIterator:(Lscala/Product;)Lscala/collection/Iterator;
Method	scala/Product$class.productIterator:(Lscala/Product;)Lscala/collection/Iterator;
Asciz	ScalaSig;
Asciz	scala/xml/pull/XMLEvent;
class	scala/xml/pull/XMLEvent
Asciz	scala/ScalaObject;
class	scala/ScalaObject
Asciz	scala/Product;
class	scala/Product
Asciz	java/io/Serializable;
class	java/io/Serializable

{
private final java.lang.String label;
  Signature: Ljava/lang/String;

private final java.lang.String pre;
  Signature: Ljava/lang/String;

public static final scala.Function1 tuple();
  Signature: ()Lscala/Function1;
  Code:
   Stack=1, Locals=0, Args_size=0
	getstatic	Field scala/xml/pull/EvElemEnd$.MODULE$:Lscala/xml/pull/EvElemEnd$;
	invokevirtual	Method scala/xml/pull/EvElemEnd$.tuple:()Lscala/Function1;
	areturn
  Labels:

public static final scala.Function1 curry();
  Signature: ()Lscala/Function1;
  Code:
   Stack=1, Locals=0, Args_size=0
	getstatic	Field scala/xml/pull/EvElemEnd$.MODULE$:Lscala/xml/pull/EvElemEnd$;
	invokevirtual	Method scala/xml/pull/EvElemEnd$.curry:()Lscala/Function1;
	areturn
  Labels:

public scala.xml.pull.EvElemEnd(java.lang.String, java.lang.String);
  Signature: (Ljava/lang/String;Ljava/lang/String;)V
  Code:
   Stack=2, Locals=3, Args_size=3
	aload_0
	aload_1
	putfield	Field pre:Ljava/lang/String;
	aload_0
	aload_2
	putfield	Field label:Ljava/lang/String;
	aload_0
	invokespecial	Method java/lang/Object."<init>":()V
	aload_0
	invokestatic	Method scala/Product$class.$init$:(Lscala/Product;)V
	return
  Labels:
  LocalVariableTable: 
   Start  Length  Slot  Name   Signature
   0      19      0    this       Lscala/xml/pull/EvElemEnd;
   0      19      1    pre       Ljava/lang/String;
   0      19      2    label       Ljava/lang/String;


private final boolean gd2$1(java.lang.String, java.lang.String);
  Signature: (Ljava/lang/String;Ljava/lang/String;)Z
  Code:
   Stack=2, Locals=5, Args_size=3
	aload_1
	aload_0
	invokevirtual	Method pre:()Ljava/lang/String;
	astore_3
	dup
	ifnonnull	l1 // aload_3
	pop
	aload_3
	ifnull	l2 // aload_2
	goto	l3 // iconst_0
l1	aload_3
	invokevirtual	Method java/lang/Object.equals:(Ljava/lang/Object;)Z
	ifeq	l3 // iconst_0
l2	aload_2
	aload_0
	invokevirtual	Method label:()Ljava/lang/String;
	astore	4
	dup
	ifnonnull	l4 // aload
	pop
	aload	4
	ifnull	l5 // iconst_1
	goto	l3 // iconst_0
l4	aload	4
	invokevirtual	Method java/lang/Object.equals:(Ljava/lang/Object;)Z
	ifeq	l3 // iconst_0
l5	iconst_1
	goto	l6 // ireturn
l3	iconst_0
l6	ireturn
  Labels:
   	l1 = 18 // aload_3
   	l2 = 25 // aload_2
   	l4 = 45 // aload
   	l5 = 53 // iconst_1
   	l3 = 57 // iconst_0
   	l6 = 58 // ireturn

public boolean canEqual(java.lang.Object);
  Signature: (Ljava/lang/Object;)Z
  Code:
   Stack=1, Locals=2, Args_size=2
	aload_1
	instanceof	class scala/xml/pull/EvElemEnd
	ireturn
  Labels:

public java.lang.Object productElement(int);
  Signature: (I)Ljava/lang/Object;
  Code:
   Stack=3, Locals=2, Args_size=2
	iload_1
	tableswitch{ //0 to 1
		0: 84;
		1: 58;
		default: 24 }
	iconst_1
	ifeq	l1 // new
	new	class java/lang/IndexOutOfBoundsException
	dup
	iload_1
	invokestatic	Method scala/runtime/BoxesRunTime.boxToInteger:(I)Ljava/lang/Integer;
	invokevirtual	Method java/lang/Object.toString:()Ljava/lang/String;
	invokespecial	Method java/lang/IndexOutOfBoundsException."<init>":(Ljava/lang/String;)V
	athrow
l1	new	class scala/MatchError
	dup
	iload_1
	invokestatic	Method scala/runtime/BoxesRunTime.boxToInteger:(I)Ljava/lang/Integer;
	invokevirtual	Method java/lang/Object.toString:()Ljava/lang/String;
	invokespecial	Method scala/MatchError."<init>":(Ljava/lang/String;)V
	athrow
	iconst_1
	ifeq	l2 // new
	aload_0
	invokevirtual	Method label:()Ljava/lang/String;
	goto	l3 // areturn
l2	new	class scala/MatchError
	dup
	iload_1
	invokestatic	Method scala/runtime/BoxesRunTime.boxToInteger:(I)Ljava/lang/Integer;
	invokevirtual	Method java/lang/Object.toString:()Ljava/lang/String;
	invokespecial	Method scala/MatchError."<init>":(Ljava/lang/String;)V
	athrow
	iconst_1
	ifeq	l4 // new
	aload_0
	invokevirtual	Method pre:()Ljava/lang/String;
l3	areturn
l4	new	class scala/MatchError
	dup
	iload_1
	invokestatic	Method scala/runtime/BoxesRunTime.boxToInteger:(I)Ljava/lang/Integer;
	invokevirtual	Method java/lang/Object.toString:()Ljava/lang/String;
	invokespecial	Method scala/MatchError."<init>":(Ljava/lang/String;)V
	athrow
  Labels:
   	l1 = 43 // new
   	l2 = 69 // new
   	l3 = 92 // areturn
   	l4 = 93 // new

public int productArity();
  Signature: ()I
  Code:
   Stack=1, Locals=1, Args_size=1
	iconst_2
	ireturn
  Labels:

public java.lang.String productPrefix();
  Signature: ()Ljava/lang/String;
  Code:
   Stack=1, Locals=1, Args_size=1
	ldc	String EvElemEnd
	areturn
  Labels:

public boolean equals(java.lang.Object);
  Signature: (Ljava/lang/Object;)Z
  Code:
   Stack=3, Locals=5, Args_size=2
	aload_0
	aload_1
	if_acmpeq	l1 // iconst_1
	aload_1
	instanceof	class scala/xml/pull/EvElemEnd
	ifeq	l2 // iconst_1
	aload_1
	checkcast	class scala/xml/pull/EvElemEnd
	astore_2
	aload_2
	invokevirtual	Method pre:()Ljava/lang/String;
	astore_3
	aload_2
	invokevirtual	Method label:()Ljava/lang/String;
	astore	4
	aload_0
	aload_3
	aload	4
	invokespecial	Method gd2$1:(Ljava/lang/String;Ljava/lang/String;)Z
	ifeq	l3 // iconst_1
	aload_1
	checkcast	class scala/xml/pull/EvElemEnd
	aload_0
	invokeinterface	InterfaceMethod scala/Equals.canEqual:(Ljava/lang/Object;)Z
	goto	l4 // ifeq
l3	iconst_1
	ifeq	l5 // new
	iconst_0
	goto	l4 // ifeq
l5	new	class scala/MatchError
	dup
	aload_1
	invokevirtual	Method java/lang/Object.toString:()Ljava/lang/String;
	invokespecial	Method scala/MatchError."<init>":(Ljava/lang/String;)V
	athrow
l2	iconst_1
	ifeq	l6 // new
	iconst_0
l4	ifeq	l7 // iconst_0
l1	iconst_1
	goto	l8 // ireturn
l7	iconst_0
l8	ireturn
l6	new	class scala/MatchError
	dup
	aload_1
	invokevirtual	Method java/lang/Object.toString:()Ljava/lang/String;
	invokespecial	Method scala/MatchError."<init>":(Ljava/lang/String;)V
	athrow
  Labels:
   	l3 = 51 // iconst_1
   	l5 = 59 // new
   	l2 = 71 // iconst_1
   	l4 = 76 // ifeq
   	l1 = 79 // iconst_1
   	l7 = 83 // iconst_0
   	l8 = 84 // ireturn
   	l6 = 85 // new
  LocalVariableTable: 
   Start  Length  Slot  Name   Signature
   0      97      0    this       Lscala/xml/pull/EvElemEnd;
   17      54      2    temp9       Lscala/xml/pull/EvElemEnd;
   22      49      3    temp10       Ljava/lang/String;
   28      43      4    temp11       Ljava/lang/String;


public java.lang.String toString();
  Signature: ()Ljava/lang/String;
  Code:
   Stack=2, Locals=1, Args_size=1
	getstatic	Field scala/runtime/ScalaRunTime$.MODULE$:Lscala/runtime/ScalaRunTime$;
	aload_0
	invokevirtual	Method scala/runtime/ScalaRunTime$._toString:(Lscala/Product;)Ljava/lang/String;
	areturn
  Labels:

public int hashCode();
  Signature: ()I
  Code:
   Stack=2, Locals=1, Args_size=1
	getstatic	Field scala/runtime/ScalaRunTime$.MODULE$:Lscala/runtime/ScalaRunTime$;
	aload_0
	invokevirtual	Method scala/runtime/ScalaRunTime$._hashCode:(Lscala/Product;)I
	ireturn
  Labels:

public scala.xml.pull.EvElemEnd copy(java.lang.String, java.lang.String);
  Signature: (Ljava/lang/String;Ljava/lang/String;)Lscala/xml/pull/EvElemEnd;
  Code:
   Stack=4, Locals=3, Args_size=3
	new	class scala/xml/pull/EvElemEnd
	dup
	aload_1
	aload_2
	invokespecial	Method "<init>":(Ljava/lang/String;Ljava/lang/String;)V
	areturn
  Labels:
  LocalVariableTable: 
   Start  Length  Slot  Name   Signature
   0      10      0    this       Lscala/xml/pull/EvElemEnd;
   0      10      1    pre       Ljava/lang/String;
   0      10      2    label       Ljava/lang/String;


public java.lang.String label();
  Signature: ()Ljava/lang/String;
  Code:
   Stack=1, Locals=1, Args_size=1
	aload_0
	getfield	Field label:Ljava/lang/String;
	areturn
  Labels:

public java.lang.String pre();
  Signature: ()Ljava/lang/String;
  Code:
   Stack=1, Locals=1, Args_size=1
	aload_0
	getfield	Field pre:Ljava/lang/String;
	areturn
  Labels:

public java.lang.String copy$default$1();
  Signature: ()Ljava/lang/String;
  Code:
   Stack=1, Locals=1, Args_size=1
	aload_0
	invokevirtual	Method pre:()Ljava/lang/String;
	areturn
  Labels:

public java.lang.String copy$default$2();
  Signature: ()Ljava/lang/String;
  Code:
   Stack=1, Locals=1, Args_size=1
	aload_0
	invokevirtual	Method label:()Ljava/lang/String;
	areturn
  Labels:

public scala.collection.Iterator productElements();
  Signature: ()Lscala/collection/Iterator;
  Code:
   Stack=1, Locals=1, Args_size=1
	aload_0
	invokestatic	Method scala/Product$class.productElements:(Lscala/Product;)Lscala/collection/Iterator;
	areturn
  Labels:
  Deprecated: true

public scala.collection.Iterator productIterator();
  Signature: ()Lscala/collection/Iterator;
  Code:
   Stack=1, Locals=1, Args_size=1
	aload_0
	invokestatic	Method scala/Product$class.productIterator:(Lscala/Product;)Lscala/collection/Iterator;
	areturn
  Labels:

}

