Compiled from "XMLEvent.scala"
public class scala.xml.pull.EvElemStart extends java.lang.Object implements scala.xml.pull.XMLEvent,scala.ScalaObject,scala.Product,java.io.Serializable
  SourceFile: "XMLEvent.scala"
  ScalaSig: length = 0x4C5
   05 00 FFFFFF81 28 06 08 01 02 FFFFFF84 FFFFFF80 FFFFFF80 FFFFFF80 40 09 02 0B
   45 76 45 6C 65 6D 53 74 61 72 74 0A 02 03 04 01
   04 70 75 6C 6C 0A 02 05 06 01 03 78 6D 6C 0A 01
   07 01 05 73 63 61 6C 61 03 00 13 05 00 0A 12 16
   1A 10 02 0B 10 0D 01 0C 0A 02 0D 0E 01 04 6C 61
   6E 67 0A 01 0F 01 04 6A 61 76 61 09 02 11 0C 02
   06 4F 62 6A 65 63 74 10 02 13 14 0D 01 02 09 02
   15 02 02 08 58 4D 4C 45 76 65 6E 74 10 02 17 18
   0D 01 06 09 02 19 06 02 0B 53 63 61 6C 61 4F 62
   6A 65 63 74 10 02 17 1B 09 02 1C 06 02 07 50 72
   6F 64 75 63 74 08 08 1E 00 FFFFFF82 FFFFFFCA FFFFFF80 FFFFFF84 00 1F 01
   03 70 72 65 15 01 20 10 02 21 24 0E 02 17 22 09
   02 23 06 01 06 50 72 65 64 65 66 09 02 25 26 02
   06 53 74 72 69 6E 67 0A 02 23 06 08 08 28 00 FFFFFF82
   FFFFFF88 FFFFFFA0 FFFFFF80 04 20 01 04 70 72 65 20 08 08 2A 00 FFFFFF82
   FFFFFFCA FFFFFF80 FFFFFF84 00 1F 01 05 6C 61 62 65 6C 08 08 2C 00
   FFFFFF82 FFFFFF88 FFFFFFA0 FFFFFF80 04 20 01 06 6C 61 62 65 6C 20 08 08
   2E 00 FFFFFF82 FFFFFFCA FFFFFF80 FFFFFF84 00 2F 01 05 61 74 74 72 73 15
   01 30 10 02 31 32 0D 01 04 09 02 33 04 02 08 4D
   65 74 61 44 61 74 61 08 08 35 00 FFFFFF82 FFFFFF88 FFFFFFA0 FFFFFF80 04
   30 01 06 61 74 74 72 73 20 08 08 37 00 FFFFFF82 FFFFFFCA FFFFFF80
   FFFFFF84 00 38 01 05 73 63 6F 70 65 15 01 39 10 02 31
   3A 09 02 3B 04 02 10 4E 61 6D 65 73 70 61 63 65
   42 69 6E 64 69 6E 67 08 08 3D 00 FFFFFF82 FFFFFF88 FFFFFFA0 FFFFFF80 04
   39 01 06 73 63 6F 70 65 20 08 05 3F 00 FFFFFF84 00 40
   01 06 3C 69 6E 69 74 3E 14 05 41 42 43 44 45 10
   02 13 00 08 05 1E 3E FFFFFFC0 00 20 08 05 2A 3E FFFFFFC0 00
   20 08 05 2E 3E FFFFFFC0 00 30 08 05 37 3E FFFFFFC0 00 39 08
   07 47 00 FFFFFF81 FFFFFF80 FFFFFF84 00 48 01 04 63 6F 70 79 14 05
   41 49 57 5A 5F 08 08 4A 1E 46 FFFFFF90 FFFFFF80 FFFFFFC0 00 20 08
   07 4B 00 FFFFFF91 FFFFFF80 FFFFFF84 00 4C 01 0E 63 6F 70 79 24 64
   65 66 61 75 6C 74 24 31 15 01 4D 2A 02 20 4E 2B
   01 4F 10 02 50 55 0D 01 51 0A 02 52 53 01 09 75
   6E 63 68 65 63 6B 65 64 0A 02 54 06 01 0A 61 6E
   6E 6F 74 61 74 69 6F 6E 09 02 56 51 02 11 75 6E
   63 68 65 63 6B 65 64 56 61 72 69 61 6E 63 65 08
   08 58 2A 46 FFFFFF90 FFFFFF80 FFFFFFC0 00 20 08 07 59 00 FFFFFF91 FFFFFF80 FFFFFF84
   00 4C 01 0E 63 6F 70 79 24 64 65 66 61 75 6C 74
   24 32 08 08 5B 2E 46 FFFFFF90 FFFFFF80 FFFFFFC0 00 30 08 07 5C 00
   FFFFFF91 FFFFFF80 FFFFFF84 00 5D 01 0E 63 6F 70 79 24 64 65 66 61
   75 6C 74 24 33 15 01 5E 2A 02 30 4E 08 08 60 37
   46 FFFFFF90 FFFFFF80 FFFFFFC0 00 39 08 07 61 00 FFFFFF91 FFFFFF80 FFFFFF84 00 62 01
   0E 63 6F 70 79 24 64 65 66 61 75 6C 74 24 34 15
   01 63 2A 02 39 4E 08 08 65 00 FFFFFF84 FFFFFF80 FFFFFF80 FFFFFF84 20 66
   01 08 68 61 73 68 43 6F 64 65 14 01 67 10 02 17
   68 09 02 69 06 02 03 49 6E 74 08 08 6B 00 FFFFFF84 FFFFFF80
   FFFFFF80 FFFFFF84 20 6C 01 08 74 6F 53 74 72 69 6E 67 14 01
   20 08 08 6E 00 FFFFFF84 FFFFFF80 FFFFFF80 FFFFFF84 20 6F 01 06 65 71 75
   61 6C 73 14 02 70 73 10 02 17 71 09 02 72 06 02
   07 42 6F 6F 6C 65 61 6E 08 07 74 6D FFFFFF81 FFFFFF80 FFFFFFC0 00
   75 01 03 78 24 31 10 02 17 76 09 02 77 06 02 03
   41 6E 79 08 08 79 00 FFFFFF84 FFFFFF80 FFFFFF80 FFFFFF84 20 7A 01 0D 70
   72 6F 64 75 63 74 50 72 65 66 69 78 15 01 7B 10
   02 0B 7C 09 02 25 0C 08 08 7E 00 FFFFFF84 FFFFFF80 FFFFFF80 FFFFFF84 20
   7F 01 0C 70 72 6F 64 75 63 74 41 72 69 74 79 15
   01 67 08 0A FFFFFF81 01 00 FFFFFF84 FFFFFF80 FFFFFF80 FFFFFF84 20 FFFFFF81 02 01 0E
   70 72 6F 64 75 63 74 45 6C 65 6D 65 6E 74 14 03
   75 FFFFFF81 03 08 08 74 FFFFFF81 00 FFFFFF81 FFFFFF80 FFFFFFC0 00 67 08 0A FFFFFF81
   05 00 FFFFFF84 FFFFFF80 FFFFFF80 FFFFFF84 20 FFFFFF81 06 01 08 63 61 6E 45 71
   75 61 6C 14 03 70 FFFFFF81 07 08 08 74 FFFFFF81 04 FFFFFF81 FFFFFF80 FFFFFFC0
   00 75 28 03 00 FFFFFF81 09 10 03 17 FFFFFF81 0A 09 03 FFFFFF81 0B
   06 02 0C 73 65 72 69 61 6C 69 7A 61 62 6C 65 07
   09 FFFFFF81 0D 02 FFFFFF81 FFFFFF80 FFFFFF88 02 FFFFFF81 0E 01 0B 45 76 45 6C
   65 6D 53 74 61 72 74 10 03 13 FFFFFF81 0F 06 09 01 02
   FFFFFF84 FFFFFF81 FFFFFF80 FFFFFF88 02 FFFFFF81 10 13 06 FFFFFF81 0F 0A FFFFFF81 11 16 10
   08 17 FFFFFF81 12 20 20 30 39 41 09 03 FFFFFF81 13 06 02 09
   46 75 6E 63 74 69 6F 6E 34 08 07 3F FFFFFF81 0F FFFFFF84 00
   FFFFFF81 15 14 02 FFFFFF81 0E 08 0A FFFFFF81 17 FFFFFF81 0F FFFFFF81 FFFFFF80 FFFFFF84 40
   FFFFFF81 18 01 05 61 70 70 6C 79 14 09 41 FFFFFF81 19 FFFFFF81 1A
   FFFFFF81 1B FFFFFF81 1C 08 06 1E FFFFFF81 16 FFFFFFC0 00 20 08 06 2A FFFFFF81
   16 FFFFFFC0 00 20 08 06 2E FFFFFF81 16 FFFFFFC0 00 30 08 06 37 FFFFFF81
   16 FFFFFFC0 00 39 08 0A FFFFFF81 1E FFFFFF81 0F FFFFFF81 FFFFFF80 FFFFFF84 40 FFFFFF81 1F
   01 07 75 6E 61 70 70 6C 79 14 04 FFFFFF81 20 FFFFFF81 26 10
   05 17 FFFFFF81 21 FFFFFF81 23 09 03 FFFFFF81 22 06 02 04 53 6F 6D
   65 10 07 17 FFFFFF81 24 20 20 30 39 09 03 FFFFFF81 25 06 02
   06 54 75 70 6C 65 34 08 07 FFFFFF81 27 FFFFFF81 1D FFFFFFC0 00 41
   01 03 78 24 30 
  minor version: 0
  major version: 49
  Constant pool:
const #1 = Asciz	SourceFile;
const #2 = Asciz	XMLEvent.scala;
const #3 = Asciz	tuple;
const #4 = Asciz	()Lscala/Function1;;
const #5 = Asciz	Code;
const #6 = Asciz	scala/xml/pull/EvElemStart$;
const #7 = class	#6;	//  scala/xml/pull/EvElemStart$
const #8 = Asciz	MODULE$;
const #9 = Asciz	Lscala/xml/pull/EvElemStart$;;
const #10 = NameAndType	#8:#9;//  MODULE$:Lscala/xml/pull/EvElemStart$;
const #11 = Field	#7.#10;	//  scala/xml/pull/EvElemStart$.MODULE$:Lscala/xml/pull/EvElemStart$;
const #12 = NameAndType	#3:#4;//  tuple:()Lscala/Function1;
const #13 = Method	#7.#12;	//  scala/xml/pull/EvElemStart$.tuple:()Lscala/Function1;
const #14 = Asciz	curry;
const #15 = NameAndType	#14:#4;//  curry:()Lscala/Function1;
const #16 = Method	#7.#15;	//  scala/xml/pull/EvElemStart$.curry:()Lscala/Function1;
const #17 = Asciz	scope;
const #18 = Asciz	Lscala/xml/NamespaceBinding;;
const #19 = Asciz	attrs;
const #20 = Asciz	Lscala/xml/MetaData;;
const #21 = Asciz	label;
const #22 = Asciz	Ljava/lang/String;;
const #23 = Asciz	pre;
const #24 = Asciz	<init>;
const #25 = Asciz	(Ljava/lang/String;Ljava/lang/String;Lscala/xml/MetaData;Lscala/xml/NamespaceBinding;)V;
const #26 = Asciz	LineNumberTable;
const #27 = Asciz	scala/xml/pull/EvElemStart;
const #28 = class	#27;	//  scala/xml/pull/EvElemStart
const #29 = NameAndType	#23:#22;//  pre:Ljava/lang/String;
const #30 = Field	#28.#29;	//  scala/xml/pull/EvElemStart.pre:Ljava/lang/String;
const #31 = NameAndType	#21:#22;//  label:Ljava/lang/String;
const #32 = Field	#28.#31;	//  scala/xml/pull/EvElemStart.label:Ljava/lang/String;
const #33 = NameAndType	#19:#20;//  attrs:Lscala/xml/MetaData;
const #34 = Field	#28.#33;	//  scala/xml/pull/EvElemStart.attrs:Lscala/xml/MetaData;
const #35 = NameAndType	#17:#18;//  scope:Lscala/xml/NamespaceBinding;
const #36 = Field	#28.#35;	//  scala/xml/pull/EvElemStart.scope:Lscala/xml/NamespaceBinding;
const #37 = Asciz	java/lang/Object;
const #38 = class	#37;	//  java/lang/Object
const #39 = Asciz	()V;
const #40 = NameAndType	#24:#39;//  "<init>":()V
const #41 = Method	#38.#40;	//  java/lang/Object."<init>":()V
const #42 = Asciz	scala/Product$class;
const #43 = class	#42;	//  scala/Product$class
const #44 = Asciz	$init$;
const #45 = Asciz	(Lscala/Product;)V;
const #46 = NameAndType	#44:#45;//  $init$:(Lscala/Product;)V
const #47 = Method	#43.#46;	//  scala/Product$class.$init$:(Lscala/Product;)V
const #48 = Asciz	this;
const #49 = Asciz	Lscala/xml/pull/EvElemStart;;
const #50 = Asciz	LocalVariableTable;
const #51 = Asciz	gd1$1;
const #52 = Asciz	(Ljava/lang/String;Ljava/lang/String;Lscala/xml/MetaData;Lscala/xml/NamespaceBinding;)Z;
const #53 = Asciz	()Ljava/lang/String;;
const #54 = NameAndType	#23:#53;//  pre:()Ljava/lang/String;
const #55 = Method	#28.#54;	//  scala/xml/pull/EvElemStart.pre:()Ljava/lang/String;
const #56 = Asciz	equals;
const #57 = Asciz	(Ljava/lang/Object;)Z;
const #58 = NameAndType	#56:#57;//  equals:(Ljava/lang/Object;)Z
const #59 = Method	#38.#58;	//  java/lang/Object.equals:(Ljava/lang/Object;)Z
const #60 = NameAndType	#21:#53;//  label:()Ljava/lang/String;
const #61 = Method	#28.#60;	//  scala/xml/pull/EvElemStart.label:()Ljava/lang/String;
const #62 = Asciz	()Lscala/xml/MetaData;;
const #63 = NameAndType	#19:#62;//  attrs:()Lscala/xml/MetaData;
const #64 = Method	#28.#63;	//  scala/xml/pull/EvElemStart.attrs:()Lscala/xml/MetaData;
const #65 = Asciz	()Lscala/xml/NamespaceBinding;;
const #66 = NameAndType	#17:#65;//  scope:()Lscala/xml/NamespaceBinding;
const #67 = Method	#28.#66;	//  scala/xml/pull/EvElemStart.scope:()Lscala/xml/NamespaceBinding;
const #68 = Asciz	canEqual;
const #69 = Asciz	productElement;
const #70 = Asciz	(I)Ljava/lang/Object;;
const #71 = Asciz	java/lang/IndexOutOfBoundsException;
const #72 = class	#71;	//  java/lang/IndexOutOfBoundsException
const #73 = Asciz	scala/runtime/BoxesRunTime;
const #74 = class	#73;	//  scala/runtime/BoxesRunTime
const #75 = Asciz	boxToInteger;
const #76 = Asciz	(I)Ljava/lang/Integer;;
const #77 = NameAndType	#75:#76;//  boxToInteger:(I)Ljava/lang/Integer;
const #78 = Method	#74.#77;	//  scala/runtime/BoxesRunTime.boxToInteger:(I)Ljava/lang/Integer;
const #79 = Asciz	toString;
const #80 = NameAndType	#79:#53;//  toString:()Ljava/lang/String;
const #81 = Method	#38.#80;	//  java/lang/Object.toString:()Ljava/lang/String;
const #82 = Asciz	(Ljava/lang/String;)V;
const #83 = NameAndType	#24:#82;//  "<init>":(Ljava/lang/String;)V
const #84 = Method	#72.#83;	//  java/lang/IndexOutOfBoundsException."<init>":(Ljava/lang/String;)V
const #85 = Asciz	scala/MatchError;
const #86 = class	#85;	//  scala/MatchError
const #87 = Method	#86.#83;	//  scala/MatchError."<init>":(Ljava/lang/String;)V
const #88 = Asciz	productArity;
const #89 = Asciz	()I;
const #90 = Asciz	productPrefix;
const #91 = Asciz	EvElemStart;
const #92 = String	#91;	//  EvElemStart
const #93 = NameAndType	#51:#52;//  gd1$1:(Ljava/lang/String;Ljava/lang/String;Lscala/xml/MetaData;Lscala/xml/NamespaceBinding;)Z
const #94 = Method	#28.#93;	//  scala/xml/pull/EvElemStart.gd1$1:(Ljava/lang/String;Ljava/lang/String;Lscala/xml/MetaData;Lscala/xml/NamespaceBinding;)Z
const #95 = Asciz	scala/Equals;
const #96 = class	#95;	//  scala/Equals
const #97 = NameAndType	#68:#57;//  canEqual:(Ljava/lang/Object;)Z
const #98 = InterfaceMethod	#96.#97;	//  scala/Equals.canEqual:(Ljava/lang/Object;)Z
const #99 = Asciz	temp2;
const #100 = Asciz	temp3;
const #101 = Asciz	temp4;
const #102 = Asciz	temp5;
const #103 = Asciz	temp6;
const #104 = Asciz	scala/runtime/ScalaRunTime$;
const #105 = class	#104;	//  scala/runtime/ScalaRunTime$
const #106 = Asciz	Lscala/runtime/ScalaRunTime$;;
const #107 = NameAndType	#8:#106;//  MODULE$:Lscala/runtime/ScalaRunTime$;
const #108 = Field	#105.#107;	//  scala/runtime/ScalaRunTime$.MODULE$:Lscala/runtime/ScalaRunTime$;
const #109 = Asciz	_toString;
const #110 = Asciz	(Lscala/Product;)Ljava/lang/String;;
const #111 = NameAndType	#109:#110;//  _toString:(Lscala/Product;)Ljava/lang/String;
const #112 = Method	#105.#111;	//  scala/runtime/ScalaRunTime$._toString:(Lscala/Product;)Ljava/lang/String;
const #113 = Asciz	hashCode;
const #114 = Asciz	_hashCode;
const #115 = Asciz	(Lscala/Product;)I;
const #116 = NameAndType	#114:#115;//  _hashCode:(Lscala/Product;)I
const #117 = Method	#105.#116;	//  scala/runtime/ScalaRunTime$._hashCode:(Lscala/Product;)I
const #118 = Asciz	copy;
const #119 = Asciz	(Ljava/lang/String;Ljava/lang/String;Lscala/xml/MetaData;Lscala/xml/NamespaceBinding;)Lscala/xml/pull/EvElemStart;;
const #120 = NameAndType	#24:#25;//  "<init>":(Ljava/lang/String;Ljava/lang/String;Lscala/xml/MetaData;Lscala/xml/NamespaceBinding;)V
const #121 = Method	#28.#120;	//  scala/xml/pull/EvElemStart."<init>":(Ljava/lang/String;Ljava/lang/String;Lscala/xml/MetaData;Lscala/xml/NamespaceBinding;)V
const #122 = Asciz	copy$default$1;
const #123 = Asciz	copy$default$2;
const #124 = Asciz	copy$default$3;
const #125 = Asciz	copy$default$4;
const #126 = Asciz	productElements;
const #127 = Asciz	()Lscala/collection/Iterator;;
const #128 = Asciz	(Lscala/Product;)Lscala/collection/Iterator;;
const #129 = NameAndType	#126:#128;//  productElements:(Lscala/Product;)Lscala/collection/Iterator;
const #130 = Method	#43.#129;	//  scala/Product$class.productElements:(Lscala/Product;)Lscala/collection/Iterator;
const #131 = Asciz	Deprecated;
const #132 = Asciz	productIterator;
const #133 = NameAndType	#132:#128;//  productIterator:(Lscala/Product;)Lscala/collection/Iterator;
const #134 = Method	#43.#133;	//  scala/Product$class.productIterator:(Lscala/Product;)Lscala/collection/Iterator;
const #135 = Asciz	ScalaSig;
const #136 = Asciz	scala/xml/pull/XMLEvent;
const #137 = class	#136;	//  scala/xml/pull/XMLEvent
const #138 = Asciz	scala/ScalaObject;
const #139 = class	#138;	//  scala/ScalaObject
const #140 = Asciz	scala/Product;
const #141 = class	#140;	//  scala/Product
const #142 = Asciz	java/io/Serializable;
const #143 = class	#142;	//  java/io/Serializable

{
public static final scala.Function1 tuple();
  Code:
   Stack=1, Locals=0, Args_size=0
   0:	getstatic	#11; //Field scala/xml/pull/EvElemStart$.MODULE$:Lscala/xml/pull/EvElemStart$;
   3:	invokevirtual	#13; //Method scala/xml/pull/EvElemStart$.tuple:()Lscala/Function1;
   6:	areturn

public static final scala.Function1 curry();
  Code:
   Stack=1, Locals=0, Args_size=0
   0:	getstatic	#11; //Field scala/xml/pull/EvElemStart$.MODULE$:Lscala/xml/pull/EvElemStart$;
   3:	invokevirtual	#16; //Method scala/xml/pull/EvElemStart$.curry:()Lscala/Function1;
   6:	areturn

public scala.xml.pull.EvElemStart(java.lang.String, java.lang.String, scala.xml.MetaData, scala.xml.NamespaceBinding);
  Code:
   Stack=2, Locals=5, Args_size=5
   0:	aload_0
   1:	aload_1
   2:	putfield	#30; //Field pre:Ljava/lang/String;
   5:	aload_0
   6:	aload_2
   7:	putfield	#32; //Field label:Ljava/lang/String;
   10:	aload_0
   11:	aload_3
   12:	putfield	#34; //Field attrs:Lscala/xml/MetaData;
   15:	aload_0
   16:	aload	4
   18:	putfield	#36; //Field scope:Lscala/xml/NamespaceBinding;
   21:	aload_0
   22:	invokespecial	#41; //Method java/lang/Object."<init>":()V
   25:	aload_0
   26:	invokestatic	#47; //Method scala/Product$class.$init$:(Lscala/Product;)V
   29:	return
  LineNumberTable: 
   line 23: 0

  LocalVariableTable: 
   Start  Length  Slot  Name   Signature
   0      30      0    this       Lscala/xml/pull/EvElemStart;
   0      30      1    pre       Ljava/lang/String;
   0      30      2    label       Ljava/lang/String;
   0      30      3    attrs       Lscala/xml/MetaData;
   0      30      4    scope       Lscala/xml/NamespaceBinding;


public boolean canEqual(java.lang.Object);
  Code:
   Stack=1, Locals=2, Args_size=2
   0:	aload_1
   1:	instanceof	#28; //class scala/xml/pull/EvElemStart
   4:	ireturn
  LineNumberTable: 
   line 23: 0


public java.lang.Object productElement(int);
  Code:
   Stack=3, Locals=2, Args_size=2
   0:	iload_1
   1:	tableswitch{ //0 to 3
		0: 144;
		1: 118;
		2: 92;
		3: 66;
		default: 32 }
   32:	iconst_1
   33:	ifeq	51
   36:	new	#72; //class java/lang/IndexOutOfBoundsException
   39:	dup
   40:	iload_1
   41:	invokestatic	#78; //Method scala/runtime/BoxesRunTime.boxToInteger:(I)Ljava/lang/Integer;
   44:	invokevirtual	#81; //Method java/lang/Object.toString:()Ljava/lang/String;
   47:	invokespecial	#84; //Method java/lang/IndexOutOfBoundsException."<init>":(Ljava/lang/String;)V
   50:	athrow
   51:	new	#86; //class scala/MatchError
   54:	dup
   55:	iload_1
   56:	invokestatic	#78; //Method scala/runtime/BoxesRunTime.boxToInteger:(I)Ljava/lang/Integer;
   59:	invokevirtual	#81; //Method java/lang/Object.toString:()Ljava/lang/String;
   62:	invokespecial	#87; //Method scala/MatchError."<init>":(Ljava/lang/String;)V
   65:	athrow
   66:	iconst_1
   67:	ifeq	77
   70:	aload_0
   71:	invokevirtual	#67; //Method scope:()Lscala/xml/NamespaceBinding;
   74:	goto	152
   77:	new	#86; //class scala/MatchError
   80:	dup
   81:	iload_1
   82:	invokestatic	#78; //Method scala/runtime/BoxesRunTime.boxToInteger:(I)Ljava/lang/Integer;
   85:	invokevirtual	#81; //Method java/lang/Object.toString:()Ljava/lang/String;
   88:	invokespecial	#87; //Method scala/MatchError."<init>":(Ljava/lang/String;)V
   91:	athrow
   92:	iconst_1
   93:	ifeq	103
   96:	aload_0
   97:	invokevirtual	#64; //Method attrs:()Lscala/xml/MetaData;
   100:	goto	152
   103:	new	#86; //class scala/MatchError
   106:	dup
   107:	iload_1
   108:	invokestatic	#78; //Method scala/runtime/BoxesRunTime.boxToInteger:(I)Ljava/lang/Integer;
   111:	invokevirtual	#81; //Method java/lang/Object.toString:()Ljava/lang/String;
   114:	invokespecial	#87; //Method scala/MatchError."<init>":(Ljava/lang/String;)V
   117:	athrow
   118:	iconst_1
   119:	ifeq	129
   122:	aload_0
   123:	invokevirtual	#61; //Method label:()Ljava/lang/String;
   126:	goto	152
   129:	new	#86; //class scala/MatchError
   132:	dup
   133:	iload_1
   134:	invokestatic	#78; //Method scala/runtime/BoxesRunTime.boxToInteger:(I)Ljava/lang/Integer;
   137:	invokevirtual	#81; //Method java/lang/Object.toString:()Ljava/lang/String;
   140:	invokespecial	#87; //Method scala/MatchError."<init>":(Ljava/lang/String;)V
   143:	athrow
   144:	iconst_1
   145:	ifeq	153
   148:	aload_0
   149:	invokevirtual	#55; //Method pre:()Ljava/lang/String;
   152:	areturn
   153:	new	#86; //class scala/MatchError
   156:	dup
   157:	iload_1
   158:	invokestatic	#78; //Method scala/runtime/BoxesRunTime.boxToInteger:(I)Ljava/lang/Integer;
   161:	invokevirtual	#81; //Method java/lang/Object.toString:()Ljava/lang/String;
   164:	invokespecial	#87; //Method scala/MatchError."<init>":(Ljava/lang/String;)V
   167:	athrow
  LineNumberTable: 
   line 23: 0
   line 21: 32
   line 23: 36
   line 21: 66
   line 23: 70
   line 21: 92
   line 23: 96
   line 21: 118
   line 23: 122
   line 21: 144
   line 23: 148


public int productArity();
  Code:
   Stack=1, Locals=1, Args_size=1
   0:	iconst_4
   1:	ireturn
  LineNumberTable: 
   line 23: 0


public java.lang.String productPrefix();
  Code:
   Stack=1, Locals=1, Args_size=1
   0:	ldc	#92; //String EvElemStart
   2:	areturn
  LineNumberTable: 
   line 23: 0


public boolean equals(java.lang.Object);
  Code:
   Stack=5, Locals=7, Args_size=2
   0:	aload_0
   1:	aload_1
   2:	if_acmpeq	95
   5:	aload_1
   6:	instanceof	#28; //class scala/xml/pull/EvElemStart
   9:	ifeq	87
   12:	aload_1
   13:	checkcast	#28; //class scala/xml/pull/EvElemStart
   16:	astore_2
   17:	aload_2
   18:	invokevirtual	#55; //Method pre:()Ljava/lang/String;
   21:	astore_3
   22:	aload_2
   23:	invokevirtual	#61; //Method label:()Ljava/lang/String;
   26:	astore	4
   28:	aload_2
   29:	invokevirtual	#64; //Method attrs:()Lscala/xml/MetaData;
   32:	astore	5
   34:	aload_2
   35:	invokevirtual	#67; //Method scope:()Lscala/xml/NamespaceBinding;
   38:	astore	6
   40:	aload_0
   41:	aload_3
   42:	aload	4
   44:	aload	5
   46:	aload	6
   48:	invokespecial	#94; //Method gd1$1:(Ljava/lang/String;Ljava/lang/String;Lscala/xml/MetaData;Lscala/xml/NamespaceBinding;)Z
   51:	ifeq	67
   54:	aload_1
   55:	checkcast	#28; //class scala/xml/pull/EvElemStart
   58:	aload_0
   59:	invokeinterface	#98,  2; //InterfaceMethod scala/Equals.canEqual:(Ljava/lang/Object;)Z
   64:	goto	92
   67:	iconst_1
   68:	ifeq	75
   71:	iconst_0
   72:	goto	92
   75:	new	#86; //class scala/MatchError
   78:	dup
   79:	aload_1
   80:	invokevirtual	#81; //Method java/lang/Object.toString:()Ljava/lang/String;
   83:	invokespecial	#87; //Method scala/MatchError."<init>":(Ljava/lang/String;)V
   86:	athrow
   87:	iconst_1
   88:	ifeq	101
   91:	iconst_0
   92:	ifeq	99
   95:	iconst_1
   96:	goto	100
   99:	iconst_0
   100:	ireturn
   101:	new	#86; //class scala/MatchError
   104:	dup
   105:	aload_1
   106:	invokevirtual	#81; //Method java/lang/Object.toString:()Ljava/lang/String;
   109:	invokespecial	#87; //Method scala/MatchError."<init>":(Ljava/lang/String;)V
   112:	athrow
  LineNumberTable: 
   line 23: 0
   line 21: 67
   line 23: 75
   line 21: 87
   line 23: 92

  LocalVariableTable: 
   Start  Length  Slot  Name   Signature
   0      113      0    this       Lscala/xml/pull/EvElemStart;
   17      70      2    temp2       Lscala/xml/pull/EvElemStart;
   22      65      3    temp3       Ljava/lang/String;
   28      59      4    temp4       Ljava/lang/String;
   34      53      5    temp5       Lscala/xml/MetaData;
   40      47      6    temp6       Lscala/xml/NamespaceBinding;


public java.lang.String toString();
  Code:
   Stack=2, Locals=1, Args_size=1
   0:	getstatic	#108; //Field scala/runtime/ScalaRunTime$.MODULE$:Lscala/runtime/ScalaRunTime$;
   3:	aload_0
   4:	invokevirtual	#112; //Method scala/runtime/ScalaRunTime$._toString:(Lscala/Product;)Ljava/lang/String;
   7:	areturn
  LineNumberTable: 
   line 23: 0


public int hashCode();
  Code:
   Stack=2, Locals=1, Args_size=1
   0:	getstatic	#108; //Field scala/runtime/ScalaRunTime$.MODULE$:Lscala/runtime/ScalaRunTime$;
   3:	aload_0
   4:	invokevirtual	#117; //Method scala/runtime/ScalaRunTime$._hashCode:(Lscala/Product;)I
   7:	ireturn
  LineNumberTable: 
   line 23: 0


public scala.xml.pull.EvElemStart copy(java.lang.String, java.lang.String, scala.xml.MetaData, scala.xml.NamespaceBinding);
  Code:
   Stack=6, Locals=5, Args_size=5
   0:	new	#28; //class scala/xml/pull/EvElemStart
   3:	dup
   4:	aload_1
   5:	aload_2
   6:	aload_3
   7:	aload	4
   9:	invokespecial	#121; //Method "<init>":(Ljava/lang/String;Ljava/lang/String;Lscala/xml/MetaData;Lscala/xml/NamespaceBinding;)V
   12:	areturn
  LineNumberTable: 
   line 23: 0

  LocalVariableTable: 
   Start  Length  Slot  Name   Signature
   0      13      0    this       Lscala/xml/pull/EvElemStart;
   0      13      1    pre       Ljava/lang/String;
   0      13      2    label       Ljava/lang/String;
   0      13      3    attrs       Lscala/xml/MetaData;
   0      13      4    scope       Lscala/xml/NamespaceBinding;


public scala.xml.NamespaceBinding scope();
  Code:
   Stack=1, Locals=1, Args_size=1
   0:	aload_0
   1:	getfield	#36; //Field scope:Lscala/xml/NamespaceBinding;
   4:	areturn
  LineNumberTable: 
   line 23: 0


public scala.xml.MetaData attrs();
  Code:
   Stack=1, Locals=1, Args_size=1
   0:	aload_0
   1:	getfield	#34; //Field attrs:Lscala/xml/MetaData;
   4:	areturn
  LineNumberTable: 
   line 23: 0


public java.lang.String label();
  Code:
   Stack=1, Locals=1, Args_size=1
   0:	aload_0
   1:	getfield	#32; //Field label:Ljava/lang/String;
   4:	areturn
  LineNumberTable: 
   line 23: 0


public java.lang.String pre();
  Code:
   Stack=1, Locals=1, Args_size=1
   0:	aload_0
   1:	getfield	#30; //Field pre:Ljava/lang/String;
   4:	areturn
  LineNumberTable: 
   line 23: 0


public java.lang.String copy$default$1();
  Code:
   Stack=1, Locals=1, Args_size=1
   0:	aload_0
   1:	invokevirtual	#55; //Method pre:()Ljava/lang/String;
   4:	areturn
  LineNumberTable: 
   line 23: 0


public java.lang.String copy$default$2();
  Code:
   Stack=1, Locals=1, Args_size=1
   0:	aload_0
   1:	invokevirtual	#61; //Method label:()Ljava/lang/String;
   4:	areturn
  LineNumberTable: 
   line 23: 0


public scala.xml.MetaData copy$default$3();
  Code:
   Stack=1, Locals=1, Args_size=1
   0:	aload_0
   1:	invokevirtual	#64; //Method attrs:()Lscala/xml/MetaData;
   4:	areturn
  LineNumberTable: 
   line 23: 0


public scala.xml.NamespaceBinding copy$default$4();
  Code:
   Stack=1, Locals=1, Args_size=1
   0:	aload_0
   1:	invokevirtual	#67; //Method scope:()Lscala/xml/NamespaceBinding;
   4:	areturn
  LineNumberTable: 
   line 23: 0


public scala.collection.Iterator productElements();
  Code:
   Stack=1, Locals=1, Args_size=1
   0:	aload_0
   1:	invokestatic	#130; //Method scala/Product$class.productElements:(Lscala/Product;)Lscala/collection/Iterator;
   4:	areturn
  LineNumberTable: 
   line 23: 0

  Deprecated: true

public scala.collection.Iterator productIterator();
  Code:
   Stack=1, Locals=1, Args_size=1
   0:	aload_0
   1:	invokestatic	#134; //Method scala/Product$class.productIterator:(Lscala/Product;)Lscala/collection/Iterator;
   4:	areturn
  LineNumberTable: 
   line 23: 0


}

