Compiled from "XMLEvent.scala"
public class scala.xml.pull.EvEntityRef extends java.lang.Object implements scala.xml.pull.XMLEvent,scala.ScalaObject,scala.Product,java.io.Serializable
  SourceFile: "XMLEvent.scala"
  ScalaSig: length = 0x3
   05 00 00 
  RuntimeVisibleAnnotations: length = 0xB
   00 01 00 71 00 01 00 72 73 00 73 
  minor version: 0
  major version: 49
  Constant pool:
Asciz	SourceFile;
Asciz	XMLEvent.scala;
Asciz	andThen;
Asciz	(Lscala/Function1;)Lscala/Function1;;
Asciz	Code;
Asciz	scala/xml/pull/EvEntityRef$;
class	scala/xml/pull/EvEntityRef$
Asciz	MODULE$;
Asciz	Lscala/xml/pull/EvEntityRef$;;
NameAndType	MODULE$:Lscala/xml/pull/EvEntityRef$;
Field	scala/xml/pull/EvEntityRef$.MODULE$:Lscala/xml/pull/EvEntityRef$;
NameAndType	andThen:(Lscala/Function1;)Lscala/Function1;
Method	scala/xml/pull/EvEntityRef$.andThen:(Lscala/Function1;)Lscala/Function1;
Asciz	compose;
NameAndType	compose:(Lscala/Function1;)Lscala/Function1;
Method	scala/xml/pull/EvEntityRef$.compose:(Lscala/Function1;)Lscala/Function1;
Asciz	entity;
Asciz	Ljava/lang/String;;
Asciz	productElementName;
Asciz	(I)Ljava/lang/String;;
Asciz	LineNumberTable;
Asciz	scala/Product$class;
class	scala/Product$class
Asciz	(Lscala/Product;I)Ljava/lang/String;;
NameAndType	productElementName:(Lscala/Product;I)Ljava/lang/String;
Method	scala/Product$class.productElementName:(Lscala/Product;I)Ljava/lang/String;
Asciz	this;
Asciz	Lscala/xml/pull/EvEntityRef;;
Asciz	n;
Asciz	I;
Asciz	LocalVariableTable;
Asciz	productIterator;
Asciz	()Lscala/collection/Iterator;;
Asciz	(Lscala/Product;)Lscala/collection/Iterator;;
NameAndType	productIterator:(Lscala/Product;)Lscala/collection/Iterator;
Method	scala/Product$class.productIterator:(Lscala/Product;)Lscala/collection/Iterator;
Asciz	productElements;
NameAndType	productElements:(Lscala/Product;)Lscala/collection/Iterator;
Method	scala/Product$class.productElements:(Lscala/Product;)Lscala/collection/Iterator;
Asciz	Deprecated;
Asciz	copy$default$1;
Asciz	()Ljava/lang/String;;
Asciz	scala/xml/pull/EvEntityRef;
class	scala/xml/pull/EvEntityRef
NameAndType	entity:()Ljava/lang/String;
Method	scala/xml/pull/EvEntityRef.entity:()Ljava/lang/String;
NameAndType	entity:Ljava/lang/String;
Field	scala/xml/pull/EvEntityRef.entity:Ljava/lang/String;
Asciz	copy;
Asciz	(Ljava/lang/String;)Lscala/xml/pull/EvEntityRef;;
Asciz	<init>;
Asciz	(Ljava/lang/String;)V;
NameAndType	"<init>":(Ljava/lang/String;)V
Method	scala/xml/pull/EvEntityRef."<init>":(Ljava/lang/String;)V
Asciz	hashCode;
Asciz	()I;
Asciz	scala/runtime/ScalaRunTime$;
class	scala/runtime/ScalaRunTime$
Asciz	Lscala/runtime/ScalaRunTime$;;
NameAndType	MODULE$:Lscala/runtime/ScalaRunTime$;
Field	scala/runtime/ScalaRunTime$.MODULE$:Lscala/runtime/ScalaRunTime$;
Asciz	_hashCode;
Asciz	(Lscala/Product;)I;
NameAndType	_hashCode:(Lscala/Product;)I
Method	scala/runtime/ScalaRunTime$._hashCode:(Lscala/Product;)I
Asciz	toString;
Asciz	_toString;
Asciz	(Lscala/Product;)Ljava/lang/String;;
NameAndType	_toString:(Lscala/Product;)Ljava/lang/String;
Method	scala/runtime/ScalaRunTime$._toString:(Lscala/Product;)Ljava/lang/String;
Asciz	equals;
Asciz	(Ljava/lang/Object;)Z;
Asciz	gd4$1;
Asciz	(Ljava/lang/String;)Z;
NameAndType	gd4$1:(Ljava/lang/String;)Z
Method	scala/xml/pull/EvEntityRef.gd4$1:(Ljava/lang/String;)Z
Asciz	scala/Equals;
class	scala/Equals
Asciz	canEqual;
NameAndType	canEqual:(Ljava/lang/Object;)Z
InterfaceMethod	scala/Equals.canEqual:(Ljava/lang/Object;)Z
Asciz	temp18;
Asciz	temp19;
Asciz	productPrefix;
Asciz	EvEntityRef;
String	EvEntityRef
Asciz	productArity;
Asciz	productElement;
Asciz	(I)Ljava/lang/Object;;
Asciz	java/lang/IndexOutOfBoundsException;
class	java/lang/IndexOutOfBoundsException
Asciz	scala/runtime/BoxesRunTime;
class	scala/runtime/BoxesRunTime
Asciz	boxToInteger;
Asciz	(I)Ljava/lang/Integer;;
NameAndType	boxToInteger:(I)Ljava/lang/Integer;
Method	scala/runtime/BoxesRunTime.boxToInteger:(I)Ljava/lang/Integer;
Asciz	java/lang/Object;
class	java/lang/Object
NameAndType	toString:()Ljava/lang/String;
Method	java/lang/Object.toString:()Ljava/lang/String;
Method	java/lang/IndexOutOfBoundsException."<init>":(Ljava/lang/String;)V
NameAndType	equals:(Ljava/lang/Object;)Z
Method	java/lang/Object.equals:(Ljava/lang/Object;)Z
Asciz	()V;
NameAndType	"<init>":()V
Method	java/lang/Object."<init>":()V
Asciz	$init$;
Asciz	(Lscala/Product;)V;
NameAndType	$init$:(Lscala/Product;)V
Method	scala/Product$class.$init$:(Lscala/Product;)V
Asciz	ScalaSig;
Asciz	Lscala/reflect/ScalaSignature;;
Asciz	bytes;
Asciz	u4\"\t)Z,e^5usJ+gM\t!/7m\t)a!Ay[2TaBgG.Y'!B!\tY#D\r\tia\"mC:<'\"A\t)g/Y#1aa2kK$CA\nBA!AV\nT#wK:$CA1BA\r-6-7b\nTWm;]YB&o3vGRDB%\taHK:$^=\"!\t]BA&/3fM&QE\n'RN\4\r2#tG/;zA!)!CW1A(8jiz\"\"LM\"*bB%\tMG>-c!9aDIbB#%\tNG>\n3fM,H2+)$F7W9C>I$B<%)hn5fG.,GM=\rQM8pi$n8\nyJ$!E;oG\",7m[3e-.8dK\"A\tC)iCND7i3f)CAD\t!eAAJ]RDB%\teR\ti>FO]5oOR\tJ\t\"K)/^1mgR1J\t/1K!!\t{w\3b]\"9q\nSAa=%cAq#U%1!8z!!\"A\n*!9s_,8\r)sKL0FW!\tYq+&!AC#,qe>$Wo;Be&$0FC!a\"A\njA9s_,8\r^#mK6,g!zCqaT.!\ta\t\"b!M\#rkdGCA&cyu,!AAAC#3])B41XM]5bY&TM7fA'!!A\t%1\"<F]RLG/*fMB1C\t\t!!EWN!!N7!9R\t\n94!!$v]$n82Q#\"q)Ib:k%\ti]CBH.YQDQAH9ABqA6u/Av]\=a\cAzA%!PB$n8\tq,a$;
Asciz	RuntimeVisibleAnnotations;
Asciz	scala/xml/pull/XMLEvent;
class	scala/xml/pull/XMLEvent
Asciz	scala/ScalaObject;
class	scala/ScalaObject
Asciz	scala/Product;
class	scala/Product
Asciz	java/io/Serializable;
class	java/io/Serializable

{
private final java.lang.String entity;
  Signature: Ljava/lang/String;

public static final scala.Function1 andThen(scala.Function1);
  Signature: (Lscala/Function1;)Lscala/Function1;
  Code:
   Stack=2, Locals=1, Args_size=1
	getstatic	Field scala/xml/pull/EvEntityRef$.MODULE$:Lscala/xml/pull/EvEntityRef$;
	aload_0
	invokevirtual	Method scala/xml/pull/EvEntityRef$.andThen:(Lscala/Function1;)Lscala/Function1;
	areturn
  Labels:

public static final scala.Function1 compose(scala.Function1);
  Signature: (Lscala/Function1;)Lscala/Function1;
  Code:
   Stack=2, Locals=1, Args_size=1
	getstatic	Field scala/xml/pull/EvEntityRef$.MODULE$:Lscala/xml/pull/EvEntityRef$;
	aload_0
	invokevirtual	Method scala/xml/pull/EvEntityRef$.compose:(Lscala/Function1;)Lscala/Function1;
	areturn
  Labels:

public java.lang.String productElementName(int);
  Signature: (I)Ljava/lang/String;
  Code:
   Stack=2, Locals=2, Args_size=2
	aload_0
	iload_1
	invokestatic	Method scala/Product$class.productElementName:(Lscala/Product;I)Ljava/lang/String;
	areturn
  Labels:
  LocalVariableTable: 
   Start  Length  Slot  Name   Signature
   0      6      0    this       Lscala/xml/pull/EvEntityRef;
   0      6      1    n       I


public scala.collection.Iterator productIterator();
  Signature: ()Lscala/collection/Iterator;
  Code:
   Stack=1, Locals=1, Args_size=1
	aload_0
	invokestatic	Method scala/Product$class.productIterator:(Lscala/Product;)Lscala/collection/Iterator;
	areturn
  Labels:

public scala.collection.Iterator productElements();
  Signature: ()Lscala/collection/Iterator;
  Code:
   Stack=1, Locals=1, Args_size=1
	aload_0
	invokestatic	Method scala/Product$class.productElements:(Lscala/Product;)Lscala/collection/Iterator;
	areturn
  Labels:
  Deprecated: true

public java.lang.String copy$default$1();
  Signature: ()Ljava/lang/String;
  Code:
   Stack=1, Locals=1, Args_size=1
	aload_0
	invokevirtual	Method entity:()Ljava/lang/String;
	areturn
  Labels:

public java.lang.String entity();
  Signature: ()Ljava/lang/String;
  Code:
   Stack=1, Locals=1, Args_size=1
	aload_0
	getfield	Field entity:Ljava/lang/String;
	areturn
  Labels:

public scala.xml.pull.EvEntityRef copy(java.lang.String);
  Signature: (Ljava/lang/String;)Lscala/xml/pull/EvEntityRef;
  Code:
   Stack=3, Locals=2, Args_size=2
	new	class scala/xml/pull/EvEntityRef
	dup
	aload_1
	invokespecial	Method "<init>":(Ljava/lang/String;)V
	areturn
  Labels:
  LocalVariableTable: 
   Start  Length  Slot  Name   Signature
   0      9      0    this       Lscala/xml/pull/EvEntityRef;
   0      9      1    entity       Ljava/lang/String;


public int hashCode();
  Signature: ()I
  Code:
   Stack=2, Locals=1, Args_size=1
	getstatic	Field scala/runtime/ScalaRunTime$.MODULE$:Lscala/runtime/ScalaRunTime$;
	aload_0
	invokevirtual	Method scala/runtime/ScalaRunTime$._hashCode:(Lscala/Product;)I
	ireturn
  Labels:

public java.lang.String toString();
  Signature: ()Ljava/lang/String;
  Code:
   Stack=2, Locals=1, Args_size=1
	getstatic	Field scala/runtime/ScalaRunTime$.MODULE$:Lscala/runtime/ScalaRunTime$;
	aload_0
	invokevirtual	Method scala/runtime/ScalaRunTime$._toString:(Lscala/Product;)Ljava/lang/String;
	areturn
  Labels:

public boolean equals(java.lang.Object);
  Signature: (Ljava/lang/Object;)Z
  Code:
   Stack=2, Locals=4, Args_size=2
	aload_0
	aload_1
	if_acmpeq	l1 // iconst_1
	aload_1
	instanceof	class scala/xml/pull/EvEntityRef
	ifeq	l2 // iconst_0
	aload_1
	checkcast	class scala/xml/pull/EvEntityRef
	astore_2
	aload_2
	invokevirtual	Method entity:()Ljava/lang/String;
	astore_3
	aload_0
	aload_3
	invokespecial	Method gd4$1:(Ljava/lang/String;)Z
	ifeq	l3 // iconst_0
	aload_1
	checkcast	class scala/xml/pull/EvEntityRef
	aload_0
	invokeinterface	InterfaceMethod scala/Equals.canEqual:(Ljava/lang/Object;)Z
	goto	l4 // ifeq
l3	iconst_0
	goto	l4 // ifeq
l2	iconst_0
l4	ifeq	l5 // iconst_0
l1	iconst_1
	goto	l6 // ireturn
l5	iconst_0
l6	ireturn
  Labels:
   	l3 = 43 // iconst_0
   	l2 = 47 // iconst_0
   	l4 = 48 // ifeq
   	l1 = 51 // iconst_1
   	l5 = 55 // iconst_0
   	l6 = 56 // ireturn
  LocalVariableTable: 
   Start  Length  Slot  Name   Signature
   0      57      0    this       Lscala/xml/pull/EvEntityRef;
   17      30      2    temp18       Lscala/xml/pull/EvEntityRef;
   22      25      3    temp19       Ljava/lang/String;


public java.lang.String productPrefix();
  Signature: ()Ljava/lang/String;
  Code:
   Stack=1, Locals=1, Args_size=1
	ldc	String EvEntityRef
	areturn
  Labels:

public int productArity();
  Signature: ()I
  Code:
   Stack=1, Locals=1, Args_size=1
	iconst_1
	ireturn
  Labels:

public java.lang.Object productElement(int);
  Signature: (I)Ljava/lang/Object;
  Code:
   Stack=3, Locals=2, Args_size=2
	iload_1
	iconst_0
	if_icmpne	l1 // new
	aload_0
	invokevirtual	Method entity:()Ljava/lang/String;
	areturn
l1	new	class java/lang/IndexOutOfBoundsException
	dup
	iload_1
	invokestatic	Method scala/runtime/BoxesRunTime.boxToInteger:(I)Ljava/lang/Integer;
	invokevirtual	Method java/lang/Object.toString:()Ljava/lang/String;
	invokespecial	Method java/lang/IndexOutOfBoundsException."<init>":(Ljava/lang/String;)V
	athrow
  Labels:
   	l1 = 10 // new

public boolean canEqual(java.lang.Object);
  Signature: (Ljava/lang/Object;)Z
  Code:
   Stack=1, Locals=2, Args_size=2
	aload_1
	instanceof	class scala/xml/pull/EvEntityRef
	ireturn
  Labels:

private final boolean gd4$1(java.lang.String);
  Signature: (Ljava/lang/String;)Z
  Code:
   Stack=2, Locals=3, Args_size=2
	aload_1
	aload_0
	invokevirtual	Method entity:()Ljava/lang/String;
	astore_2
	dup
	ifnonnull	l1 // aload_2
	pop
	aload_2
	ifnull	l2 // iconst_1
	goto	l3 // iconst_0
l1	aload_2
	invokevirtual	Method java/lang/Object.equals:(Ljava/lang/Object;)Z
	ifeq	l3 // iconst_0
l2	iconst_1
	goto	l4 // ireturn
l3	iconst_0
l4	ireturn
  Labels:
   	l1 = 18 // aload_2
   	l2 = 25 // iconst_1
   	l3 = 29 // iconst_0
   	l4 = 30 // ireturn

public scala.xml.pull.EvEntityRef(java.lang.String);
  Signature: (Ljava/lang/String;)V
  Code:
   Stack=2, Locals=2, Args_size=2
	aload_0
	aload_1
	putfield	Field entity:Ljava/lang/String;
	aload_0
	invokespecial	Method java/lang/Object."<init>":()V
	aload_0
	invokestatic	Method scala/Product$class.$init$:(Lscala/Product;)V
	return
  Labels:
  LocalVariableTable: 
   Start  Length  Slot  Name   Signature
   0      14      0    this       Lscala/xml/pull/EvEntityRef;
   0      14      1    entity       Ljava/lang/String;


}

