Compiled from "XMLEvent.scala"
public final class scala.xml.pull.EvProcInstr$ extends scala.runtime.AbstractFunction2 implements scala.ScalaObject
  SourceFile: "XMLEvent.scala"
  Scala: length = 0x
   
  minor version: 0
  major version: 49
  Constant pool:
Asciz	SourceFile;
Asciz	XMLEvent.scala;
Asciz	MODULE$;
Asciz	Lscala/xml/pull/EvProcInstr$;;
Asciz	<clinit>;
Asciz	()V;
Asciz	Code;
Asciz	scala/xml/pull/EvProcInstr$;
class	scala/xml/pull/EvProcInstr$
Asciz	<init>;
NameAndType	"<init>":()V
Method	scala/xml/pull/EvProcInstr$."<init>":()V
Asciz	unapply;
Asciz	(Lscala/xml/pull/EvProcInstr;)Lscala/Option;;
Asciz	LineNumberTable;
Asciz	scala/None$;
class	scala/None$
Asciz	Lscala/None$;;
NameAndType	MODULE$:Lscala/None$;
Field	scala/None$.MODULE$:Lscala/None$;
Asciz	scala/Some;
class	scala/Some
Asciz	scala/Tuple2;
class	scala/Tuple2
Asciz	scala/xml/pull/EvProcInstr;
class	scala/xml/pull/EvProcInstr
Asciz	target;
Asciz	()Ljava/lang/String;;
NameAndType	target:()Ljava/lang/String;
Method	scala/xml/pull/EvProcInstr.target:()Ljava/lang/String;
Asciz	text;
NameAndType	text:()Ljava/lang/String;
Method	scala/xml/pull/EvProcInstr.text:()Ljava/lang/String;
Asciz	(Ljava/lang/Object;Ljava/lang/Object;)V;
NameAndType	"<init>":(Ljava/lang/Object;Ljava/lang/Object;)V
Method	scala/Tuple2."<init>":(Ljava/lang/Object;Ljava/lang/Object;)V
Asciz	(Ljava/lang/Object;)V;
NameAndType	"<init>":(Ljava/lang/Object;)V
Method	scala/Some."<init>":(Ljava/lang/Object;)V
Asciz	this;
Asciz	x$0;
Asciz	Lscala/xml/pull/EvProcInstr;;
Asciz	LocalVariableTable;
Asciz	apply;
Asciz	(Ljava/lang/String;Ljava/lang/String;)Lscala/xml/pull/EvProcInstr;;
Asciz	(Ljava/lang/String;Ljava/lang/String;)V;
NameAndType	"<init>":(Ljava/lang/String;Ljava/lang/String;)V
Method	scala/xml/pull/EvProcInstr."<init>":(Ljava/lang/String;Ljava/lang/String;)V
Asciz	Ljava/lang/String;;
Asciz	(Ljava/lang/Object;Ljava/lang/Object;)Ljava/lang/Object;;
Asciz	java/lang/String;
class	java/lang/String
NameAndType	apply:(Ljava/lang/String;Ljava/lang/String;)Lscala/xml/pull/EvProcInstr;
Method	scala/xml/pull/EvProcInstr$.apply:(Ljava/lang/String;Ljava/lang/String;)Lscala/xml/pull/EvProcInstr;
Asciz	v1;
Asciz	Ljava/lang/Object;;
Asciz	v2;
Asciz	scala/runtime/AbstractFunction2;
class	scala/runtime/AbstractFunction2
Method	scala/runtime/AbstractFunction2."<init>":()V
NameAndType	MODULE$:Lscala/xml/pull/EvProcInstr$;
Field	scala/xml/pull/EvProcInstr$.MODULE$:Lscala/xml/pull/EvProcInstr$;
Asciz	Scala;
Asciz	scala/ScalaObject;
class	scala/ScalaObject

{
public static final scala.xml.pull.EvProcInstr$ MODULE$;
  Signature: Lscala/xml/pull/EvProcInstr$;

public static {};
  Signature: ()V
  Code:
   Stack=1, Locals=0, Args_size=0
	new	class scala/xml/pull/EvProcInstr$
	invokespecial	Method "<init>":()V
	return
  Labels:

public scala.Option unapply(scala.xml.pull.EvProcInstr);
  Signature: (Lscala/xml/pull/EvProcInstr;)Lscala/Option;
  Code:
   Stack=6, Locals=2, Args_size=2
	aload_1
	ifnonnull	l1 // new
	getstatic	Field scala/None$.MODULE$:Lscala/None$;
	goto	l2 // areturn
l1	new	class scala/Some
	dup
	new	class scala/Tuple2
	dup
	aload_1
	invokevirtual	Method scala/xml/pull/EvProcInstr.target:()Ljava/lang/String;
	aload_1
	invokevirtual	Method scala/xml/pull/EvProcInstr.text:()Ljava/lang/String;
	invokespecial	Method scala/Tuple2."<init>":(Ljava/lang/Object;Ljava/lang/Object;)V
	invokespecial	Method scala/Some."<init>":(Ljava/lang/Object;)V
l2	areturn
  Labels:
   	l1 = 10 // new
   	l2 = 32 // areturn
  LocalVariableTable: 
   Start  Length  Slot  Name   Signature
   0      33      0    this       Lscala/xml/pull/EvProcInstr$;
   0      33      1    x$0       Lscala/xml/pull/EvProcInstr;


public scala.xml.pull.EvProcInstr apply(java.lang.String, java.lang.String);
  Signature: (Ljava/lang/String;Ljava/lang/String;)Lscala/xml/pull/EvProcInstr;
  Code:
   Stack=4, Locals=3, Args_size=3
	new	class scala/xml/pull/EvProcInstr
	dup
	aload_1
	aload_2
	invokespecial	Method scala/xml/pull/EvProcInstr."<init>":(Ljava/lang/String;Ljava/lang/String;)V
	areturn
  Labels:
  LocalVariableTable: 
   Start  Length  Slot  Name   Signature
   0      10      0    this       Lscala/xml/pull/EvProcInstr$;
   0      10      1    target       Ljava/lang/String;
   0      10      2    text       Ljava/lang/String;


public java.lang.Object apply(java.lang.Object, java.lang.Object);
  Signature: (Ljava/lang/Object;Ljava/lang/Object;)Ljava/lang/Object;
  Code:
   Stack=3, Locals=3, Args_size=3
	aload_0
	aload_1
	checkcast	class java/lang/String
	aload_2
	checkcast	class java/lang/String
	invokevirtual	Method apply:(Ljava/lang/String;Ljava/lang/String;)Lscala/xml/pull/EvProcInstr;
	areturn
  Labels:
  LocalVariableTable: 
   Start  Length  Slot  Name   Signature
   0      13      0    this       Lscala/xml/pull/EvProcInstr$;
   0      13      1    v1       Ljava/lang/Object;
   0      13      2    v2       Ljava/lang/Object;


private scala.xml.pull.EvProcInstr$();
  Signature: ()V
  Code:
   Stack=1, Locals=1, Args_size=1
	aload_0
	invokespecial	Method scala/runtime/AbstractFunction2."<init>":()V
	aload_0
	putstatic	Field MODULE$:Lscala/xml/pull/EvProcInstr$;
	return
  Labels:

}

