Compiled from "XMLEventReader.scala"
public abstract class scala.xml.pull.ProducerConsumerIterator$class extends java.lang.Object
  SourceFile: "XMLEventReader.scala"
  Scala: length = 0x
   
  InnerClass: 
   public final $anonfun$produce$1=class scala/xml/pull/ProducerConsumerIterator$$anonfun$produce$1 of class scala/xml/pull/ProducerConsumerIterator
   public final $anonfun$fillBuffer$2=class scala/xml/pull/ProducerConsumerIterator$$anonfun$fillBuffer$2 of class scala/xml/pull/ProducerConsumerIterator
   public final $anonfun$fillBuffer$1=class scala/xml/pull/ProducerConsumerIterator$$anonfun$fillBuffer$1 of class scala/xml/pull/ProducerConsumerIterator
  minor version: 0
  major version: 49
  Constant pool:
Asciz	SourceFile;
Asciz	XMLEventReader.scala;
Asciz	interruptibly;
Asciz	(Lscala/xml/pull/ProducerConsumerIterator;Lscala/Function0;)Lscala/Option;;
Asciz	Code;
Asciz	scala/Some;
class	scala/Some
Asciz	LineNumberTable;
Asciz	scala/Function0;
class	scala/Function0
Asciz	apply;
Asciz	()Ljava/lang/Object;;
NameAndType	apply:()Ljava/lang/Object;
InterfaceMethod	scala/Function0.apply:()Ljava/lang/Object;
Asciz	<init>;
Asciz	(Ljava/lang/Object;)V;
NameAndType	"<init>":(Ljava/lang/Object;)V
Method	scala/Some."<init>":(Ljava/lang/Object;)V
Asciz	scala/None$;
class	scala/None$
Asciz	MODULE$;
Asciz	Lscala/None$;;
NameAndType	MODULE$:Lscala/None$;
Field	scala/None$.MODULE$:Lscala/None$;
Asciz	java/lang/Thread;
class	java/lang/Thread
Asciz	currentThread;
Asciz	()Ljava/lang/Thread;;
NameAndType	currentThread:()Ljava/lang/Thread;
Method	java/lang/Thread.currentThread:()Ljava/lang/Thread;
Asciz	interrupt;
Asciz	()V;
NameAndType	interrupt:()V
Method	java/lang/Thread.interrupt:()V
Asciz	java/lang/InterruptedException;
class	java/lang/InterruptedException
Asciz	java/nio/channels/ClosedChannelException;
class	java/nio/channels/ClosedChannelException
Asciz	$this;
Asciz	Lscala/xml/pull/ProducerConsumerIterator;;
Asciz	body;
Asciz	Lscala/Function0;;
Asciz	exceptionResult1;
Asciz	Lscala/Option;;
Asciz	LocalVariableTable;
Asciz	scala$xml$pull$ProducerConsumerIterator$$queue;
Asciz	(Lscala/xml/pull/ProducerConsumerIterator;)Ljava/util/concurrent/LinkedBlockingQueue;;
Asciz	scala/xml/pull/ProducerConsumerIterator;
class	scala/xml/pull/ProducerConsumerIterator
Asciz	MaxQueueSize;
Asciz	()I;
NameAndType	MaxQueueSize:()I
InterfaceMethod	scala/xml/pull/ProducerConsumerIterator.MaxQueueSize:()I
Asciz	java/util/concurrent/LinkedBlockingQueue;
class	java/util/concurrent/LinkedBlockingQueue
NameAndType	"<init>":()V
Method	java/util/concurrent/LinkedBlockingQueue."<init>":()V
Asciz	(I)V;
NameAndType	"<init>":(I)V
Method	java/util/concurrent/LinkedBlockingQueue."<init>":(I)V
Asciz	fillBuffer;
Asciz	(Lscala/xml/pull/ProducerConsumerIterator;)Z;
Asciz	scala/xml/pull/ProducerConsumerIterator$$anonfun$fillBuffer$1;
class	scala/xml/pull/ProducerConsumerIterator$$anonfun$fillBuffer$1
Asciz	(Lscala/xml/pull/ProducerConsumerIterator;)V;
NameAndType	"<init>":(Lscala/xml/pull/ProducerConsumerIterator;)V
Method	scala/xml/pull/ProducerConsumerIterator$$anonfun$fillBuffer$1."<init>":(Lscala/xml/pull/ProducerConsumerIterator;)V
Asciz	(Lscala/Function0;)Lscala/Option;;
NameAndType	interruptibly:(Lscala/Function0;)Lscala/Option;
InterfaceMethod	scala/xml/pull/ProducerConsumerIterator.interruptibly:(Lscala/Function0;)Lscala/Option;
Asciz	scala/xml/pull/ProducerConsumerIterator$$anonfun$fillBuffer$2;
class	scala/xml/pull/ProducerConsumerIterator$$anonfun$fillBuffer$2
Method	scala/xml/pull/ProducerConsumerIterator$$anonfun$fillBuffer$2."<init>":(Lscala/xml/pull/ProducerConsumerIterator;)V
Asciz	scala/Option;
class	scala/Option
Asciz	getOrElse;
Asciz	(Lscala/Function0;)Ljava/lang/Object;;
NameAndType	getOrElse:(Lscala/Function0;)Ljava/lang/Object;
Method	scala/Option.getOrElse:(Lscala/Function0;)Ljava/lang/Object;
Asciz	buffer_$eq;
NameAndType	buffer_$eq:(Ljava/lang/Object;)V
InterfaceMethod	scala/xml/pull/ProducerConsumerIterator.buffer_$eq:(Ljava/lang/Object;)V
Asciz	buffer;
NameAndType	buffer:()Ljava/lang/Object;
InterfaceMethod	scala/xml/pull/ProducerConsumerIterator.buffer:()Ljava/lang/Object;
Asciz	scala/xml/pull/ProducerConsumerIterator$class;
class	scala/xml/pull/ProducerConsumerIterator$class
Asciz	isElement;
Asciz	(Lscala/xml/pull/ProducerConsumerIterator;Ljava/lang/Object;)Z;
NameAndType	isElement:(Lscala/xml/pull/ProducerConsumerIterator;Ljava/lang/Object;)Z
Method	scala/xml/pull/ProducerConsumerIterator$class.isElement:(Lscala/xml/pull/ProducerConsumerIterator;Ljava/lang/Object;)Z
Asciz	java/lang/Object;
class	java/lang/Object
Asciz	equals;
Asciz	(Ljava/lang/Object;)Z;
NameAndType	equals:(Ljava/lang/Object;)Z
Method	java/lang/Object.equals:(Ljava/lang/Object;)Z
Asciz	EndOfStream;
NameAndType	EndOfStream:()Ljava/lang/Object;
InterfaceMethod	scala/xml/pull/ProducerConsumerIterator.EndOfStream:()Ljava/lang/Object;
Asciz	java/lang/Number;
class	java/lang/Number
Asciz	java/lang/Character;
class	java/lang/Character
Asciz	scala/runtime/BoxesRunTime;
class	scala/runtime/BoxesRunTime
Asciz	equals2;
Asciz	(Ljava/lang/Object;Ljava/lang/Object;)Z;
NameAndType	equals2:(Ljava/lang/Object;Ljava/lang/Object;)Z
Method	scala/runtime/BoxesRunTime.equals2:(Ljava/lang/Object;Ljava/lang/Object;)Z
Asciz	x;
Asciz	Ljava/lang/Object;;
Asciz	y0;
Asciz	eos;
Asciz	x0;
Asciz	produce;
Asciz	(Lscala/xml/pull/ProducerConsumerIterator;Ljava/lang/Object;)V;
NameAndType	eos:(Lscala/xml/pull/ProducerConsumerIterator;)Z
Method	scala/xml/pull/ProducerConsumerIterator$class.eos:(Lscala/xml/pull/ProducerConsumerIterator;)Z
Asciz	scala/xml/pull/ProducerConsumerIterator$$anonfun$produce$1;
class	scala/xml/pull/ProducerConsumerIterator$$anonfun$produce$1
NameAndType	"<init>":(Lscala/xml/pull/ProducerConsumerIterator;Ljava/lang/Object;)V
Method	scala/xml/pull/ProducerConsumerIterator$$anonfun$produce$1."<init>":(Lscala/xml/pull/ProducerConsumerIterator;Ljava/lang/Object;)V
Asciz	x$1;
Asciz	hasNext;
NameAndType	fillBuffer:(Lscala/xml/pull/ProducerConsumerIterator;)Z
Method	scala/xml/pull/ProducerConsumerIterator$class.fillBuffer:(Lscala/xml/pull/ProducerConsumerIterator;)Z
Asciz	next;
Asciz	(Lscala/xml/pull/ProducerConsumerIterator;)Ljava/lang/Object;;
Asciz	java/util/NoSuchElementException;
class	java/util/NoSuchElementException
Asciz	ProducerConsumerIterator;
String	ProducerConsumerIterator
Asciz	(Ljava/lang/String;)V;
NameAndType	"<init>":(Ljava/lang/String;)V
Method	java/util/NoSuchElementException."<init>":(Ljava/lang/String;)V
Asciz	drainBuffer;
NameAndType	drainBuffer:(Lscala/xml/pull/ProducerConsumerIterator;)Ljava/lang/Object;
Method	scala/xml/pull/ProducerConsumerIterator$class.drainBuffer:(Lscala/xml/pull/ProducerConsumerIterator;)Ljava/lang/Object;
Asciz	available;
Asciz	()Ljava/util/concurrent/LinkedBlockingQueue;;
NameAndType	scala$xml$pull$ProducerConsumerIterator$$queue:()Ljava/util/concurrent/LinkedBlockingQueue;
InterfaceMethod	scala/xml/pull/ProducerConsumerIterator.scala$xml$pull$ProducerConsumerIterator$$queue:()Ljava/util/concurrent/LinkedBlockingQueue;
Asciz	peek;
NameAndType	peek:()Ljava/lang/Object;
Method	java/util/concurrent/LinkedBlockingQueue.peek:()Ljava/lang/Object;
Asciz	scala/Predef$;
class	scala/Predef$
Asciz	Lscala/Predef$;;
NameAndType	MODULE$:Lscala/Predef$;
Field	scala/Predef$.MODULE$:Lscala/Predef$;
Asciz	assert;
Asciz	(Z)V;
NameAndType	assert:(Z)V
Method	scala/Predef$.assert:(Z)V
Asciz	res;
Asciz	$init$;
Asciz	scala$xml$pull$ProducerConsumerIterator$_setter_$MaxQueueSize_$eq;
NameAndType	scala$xml$pull$ProducerConsumerIterator$_setter_$MaxQueueSize_$eq:(I)V
InterfaceMethod	scala/xml/pull/ProducerConsumerIterator.scala$xml$pull$ProducerConsumerIterator$_setter_$MaxQueueSize_$eq:(I)V
Asciz	Scala;
Asciz	InnerClasses;
Asciz	$anonfun$produce$1;
Asciz	$anonfun$fillBuffer$2;
Asciz	$anonfun$fillBuffer$1;

{
public static scala.Option interruptibly(scala.xml.pull.ProducerConsumerIterator, scala.Function0);
  Signature: (Lscala/xml/pull/ProducerConsumerIterator;Lscala/Function0;)Lscala/Option;
  Code:
   Stack=3, Locals=3, Args_size=2
	new	class scala/Some
	dup
	aload_1
	invokeinterface	InterfaceMethod scala/Function0.apply:()Ljava/lang/Object;
	invokespecial	Method scala/Some."<init>":(Ljava/lang/Object;)V
	astore_2
	goto	l1 // aload_2
	pop
	getstatic	Field scala/None$.MODULE$:Lscala/None$;
	astore_2
	goto	l1 // aload_2
	pop
	invokestatic	Method java/lang/Thread.currentThread:()Ljava/lang/Thread;
	invokevirtual	Method java/lang/Thread.interrupt:()V
	getstatic	Field scala/None$.MODULE$:Lscala/None$;
	astore_2
l1	aload_2
	areturn
  Labels:
   	l1 = 36 // aload_2
  Exception table:
   from   to  target type
     0    17    25   Class java/lang/InterruptedException

     0    17    17   Class java/nio/channels/ClosedChannelException

  LocalVariableTable: 
   Start  Length  Slot  Name   Signature
   0      38      0    $this       Lscala/xml/pull/ProducerConsumerIterator;
   0      38      1    body       Lscala/Function0;
   0      37      2    exceptionResult1       Lscala/Option;


public static final java.util.concurrent.LinkedBlockingQueue scala$xml$pull$ProducerConsumerIterator$$queue(scala.xml.pull.ProducerConsumerIterator);
  Signature: (Lscala/xml/pull/ProducerConsumerIterator;)Ljava/util/concurrent/LinkedBlockingQueue;
  Code:
   Stack=3, Locals=1, Args_size=1
	aload_0
	invokeinterface	InterfaceMethod scala/xml/pull/ProducerConsumerIterator.MaxQueueSize:()I
	iconst_0
	if_icmpge	l1 // new
	new	class java/util/concurrent/LinkedBlockingQueue
	dup
	invokespecial	Method java/util/concurrent/LinkedBlockingQueue."<init>":()V
	goto	l2 // areturn
l1	new	class java/util/concurrent/LinkedBlockingQueue
	dup
	aload_0
	invokeinterface	InterfaceMethod scala/xml/pull/ProducerConsumerIterator.MaxQueueSize:()I
	invokespecial	Method java/util/concurrent/LinkedBlockingQueue."<init>":(I)V
l2	areturn
  Labels:
   	l1 = 20 // new
   	l2 = 33 // areturn
  LocalVariableTable: 
   Start  Length  Slot  Name   Signature
   0      34      0    $this       Lscala/xml/pull/ProducerConsumerIterator;


private static boolean fillBuffer(scala.xml.pull.ProducerConsumerIterator);
  Signature: (Lscala/xml/pull/ProducerConsumerIterator;)Z
  Code:
   Stack=5, Locals=1, Args_size=1
	aload_0
	aload_0
	new	class scala/xml/pull/ProducerConsumerIterator$$anonfun$fillBuffer$1
	dup
	aload_0
	invokespecial	Method scala/xml/pull/ProducerConsumerIterator$$anonfun$fillBuffer$1."<init>":(Lscala/xml/pull/ProducerConsumerIterator;)V
	invokeinterface	InterfaceMethod scala/xml/pull/ProducerConsumerIterator.interruptibly:(Lscala/Function0;)Lscala/Option;
	new	class scala/xml/pull/ProducerConsumerIterator$$anonfun$fillBuffer$2
	dup
	aload_0
	invokespecial	Method scala/xml/pull/ProducerConsumerIterator$$anonfun$fillBuffer$2."<init>":(Lscala/xml/pull/ProducerConsumerIterator;)V
	invokevirtual	Method scala/Option.getOrElse:(Lscala/Function0;)Ljava/lang/Object;
	invokeinterface	InterfaceMethod scala/xml/pull/ProducerConsumerIterator.buffer_$eq:(Ljava/lang/Object;)V
	aload_0
	aload_0
	invokeinterface	InterfaceMethod scala/xml/pull/ProducerConsumerIterator.buffer:()Ljava/lang/Object;
	invokestatic	Method isElement:(Lscala/xml/pull/ProducerConsumerIterator;Ljava/lang/Object;)Z
	ireturn
  Labels:
  LocalVariableTable: 
   Start  Length  Slot  Name   Signature
   0      42      0    $this       Lscala/xml/pull/ProducerConsumerIterator;


private static boolean isElement(scala.xml.pull.ProducerConsumerIterator, java.lang.Object);
  Signature: (Lscala/xml/pull/ProducerConsumerIterator;Ljava/lang/Object;)Z
  Code:
   Stack=2, Locals=3, Args_size=2
	aload_1
	dup
	pop
	ifnull	l1 // iconst_0
	aload_1
	aconst_null
	invokevirtual	Method java/lang/Object.equals:(Ljava/lang/Object;)Z
	ifne	l1 // iconst_0
	aload_0
	invokeinterface	InterfaceMethod scala/xml/pull/ProducerConsumerIterator.EndOfStream:()Ljava/lang/Object;
	astore_2
	aload_1
	aload_2
	if_acmpne	l2 // aload_1
	iconst_1
	goto	l3 // ifeq
l2	aload_1
	ifnonnull	l4 // aload_1
	iconst_0
	goto	l3 // ifeq
l4	aload_1
	instanceof	class java/lang/Number
	ifne	l5 // aload_1
	aload_1
	instanceof	class java/lang/Character
	ifeq	l6 // aload_1
l5	aload_1
	aload_2
	invokestatic	Method scala/runtime/BoxesRunTime.equals2:(Ljava/lang/Object;Ljava/lang/Object;)Z
	goto	l3 // ifeq
l6	aload_1
	aload_2
	invokevirtual	Method java/lang/Object.equals:(Ljava/lang/Object;)Z
l3	ifeq	l7 // iconst_1
l1	iconst_0
	goto	l8 // ireturn
l7	iconst_1
l8	ireturn
  Labels:
   	l2 = 30 // aload_1
   	l4 = 38 // aload_1
   	l5 = 52 // aload_1
   	l6 = 60 // aload_1
   	l3 = 65 // ifeq
   	l1 = 68 // iconst_0
   	l7 = 72 // iconst_1
   	l8 = 73 // ireturn
  LocalVariableTable: 
   Start  Length  Slot  Name   Signature
   0      74      0    $this       Lscala/xml/pull/ProducerConsumerIterator;
   0      74      1    x       Ljava/lang/Object;
   26      42      2    y0       Ljava/lang/Object;


private static boolean eos(scala.xml.pull.ProducerConsumerIterator);
  Signature: (Lscala/xml/pull/ProducerConsumerIterator;)Z
  Code:
   Stack=2, Locals=3, Args_size=1
	aload_0
	invokeinterface	InterfaceMethod scala/xml/pull/ProducerConsumerIterator.buffer:()Ljava/lang/Object;
	aload_0
	invokeinterface	InterfaceMethod scala/xml/pull/ProducerConsumerIterator.EndOfStream:()Ljava/lang/Object;
	astore_2
	astore_1
	aload_1
	aload_2
	if_acmpne	l1 // aload_1
	iconst_1
	goto	l2 // ifeq
l1	aload_1
	ifnonnull	l3 // aload_1
	iconst_0
	goto	l2 // ifeq
l3	aload_1
	instanceof	class java/lang/Number
	ifne	l4 // aload_1
	aload_1
	instanceof	class java/lang/Character
	ifeq	l5 // aload_1
l4	aload_1
	aload_2
	invokestatic	Method scala/runtime/BoxesRunTime.equals2:(Ljava/lang/Object;Ljava/lang/Object;)Z
	goto	l2 // ifeq
l5	aload_1
	aload_2
	invokevirtual	Method java/lang/Object.equals:(Ljava/lang/Object;)Z
l2	ifeq	l6 // iconst_0
	iconst_1
	goto	l7 // ireturn
l6	iconst_0
l7	ireturn
  Labels:
   	l1 = 23 // aload_1
   	l3 = 31 // aload_1
   	l4 = 45 // aload_1
   	l5 = 53 // aload_1
   	l2 = 58 // ifeq
   	l6 = 65 // iconst_0
   	l7 = 66 // ireturn
  LocalVariableTable: 
   Start  Length  Slot  Name   Signature
   0      67      0    $this       Lscala/xml/pull/ProducerConsumerIterator;
   19      42      1    x0       Ljava/lang/Object;
   19      42      2    y0       Ljava/lang/Object;


public static void produce(scala.xml.pull.ProducerConsumerIterator, java.lang.Object);
  Signature: (Lscala/xml/pull/ProducerConsumerIterator;Ljava/lang/Object;)V
  Code:
   Stack=5, Locals=2, Args_size=2
	aload_0
	invokestatic	Method eos:(Lscala/xml/pull/ProducerConsumerIterator;)Z
	ifne	l1 // return
	aload_0
	new	class scala/xml/pull/ProducerConsumerIterator$$anonfun$produce$1
	dup
	aload_0
	aload_1
	invokespecial	Method scala/xml/pull/ProducerConsumerIterator$$anonfun$produce$1."<init>":(Lscala/xml/pull/ProducerConsumerIterator;Ljava/lang/Object;)V
	invokeinterface	InterfaceMethod scala/xml/pull/ProducerConsumerIterator.interruptibly:(Lscala/Function0;)Lscala/Option;
	pop
l1	return
  Labels:
   	l1 = 23 // return
  LocalVariableTable: 
   Start  Length  Slot  Name   Signature
   0      24      0    $this       Lscala/xml/pull/ProducerConsumerIterator;
   0      24      1    x$1       Ljava/lang/Object;


public static boolean hasNext(scala.xml.pull.ProducerConsumerIterator);
  Signature: (Lscala/xml/pull/ProducerConsumerIterator;)Z
  Code:
   Stack=2, Locals=2, Args_size=1
	aload_0
	invokestatic	Method eos:(Lscala/xml/pull/ProducerConsumerIterator;)Z
	ifne	l1 // iconst_0
	aload_0
	invokeinterface	InterfaceMethod scala/xml/pull/ProducerConsumerIterator.buffer:()Ljava/lang/Object;
	dup
	astore_1
	ifnull	l2 // aload_0
	aload_1
	aconst_null
	invokevirtual	Method java/lang/Object.equals:(Ljava/lang/Object;)Z
	ifeq	l3 // iconst_1
l2	aload_0
	invokestatic	Method fillBuffer:(Lscala/xml/pull/ProducerConsumerIterator;)Z
	ifne	l3 // iconst_1
l1	iconst_0
	goto	l4 // ireturn
l3	iconst_1
l4	ireturn
  Labels:
   	l2 = 26 // aload_0
   	l1 = 33 // iconst_0
   	l3 = 37 // iconst_1
   	l4 = 38 // ireturn
  LocalVariableTable: 
   Start  Length  Slot  Name   Signature
   0      39      0    $this       Lscala/xml/pull/ProducerConsumerIterator;


public static java.lang.Object next(scala.xml.pull.ProducerConsumerIterator);
  Signature: (Lscala/xml/pull/ProducerConsumerIterator;)Ljava/lang/Object;
  Code:
   Stack=3, Locals=2, Args_size=1
	aload_0
	invokestatic	Method eos:(Lscala/xml/pull/ProducerConsumerIterator;)Z
	ifeq	l1 // aload_0
	new	class java/util/NoSuchElementException
	dup
	ldc	String ProducerConsumerIterator
	invokespecial	Method java/util/NoSuchElementException."<init>":(Ljava/lang/String;)V
	athrow
l1	aload_0
	invokeinterface	InterfaceMethod scala/xml/pull/ProducerConsumerIterator.buffer:()Ljava/lang/Object;
	dup
	astore_1
	ifnull	l2 // aload_0
	aload_1
	aconst_null
	invokevirtual	Method java/lang/Object.equals:(Ljava/lang/Object;)Z
	ifeq	l3 // aload_0
l2	aload_0
	invokestatic	Method fillBuffer:(Lscala/xml/pull/ProducerConsumerIterator;)Z
	pop
	goto	l3 // aload_0
l3	aload_0
	invokestatic	Method drainBuffer:(Lscala/xml/pull/ProducerConsumerIterator;)Ljava/lang/Object;
	areturn
  Labels:
   	l1 = 17 // aload_0
   	l2 = 36 // aload_0
   	l3 = 44 // aload_0
  LocalVariableTable: 
   Start  Length  Slot  Name   Signature
   0      49      0    $this       Lscala/xml/pull/ProducerConsumerIterator;


public static boolean available(scala.xml.pull.ProducerConsumerIterator);
  Signature: (Lscala/xml/pull/ProducerConsumerIterator;)Z
  Code:
   Stack=2, Locals=1, Args_size=1
	aload_0
	aload_0
	invokeinterface	InterfaceMethod scala/xml/pull/ProducerConsumerIterator.buffer:()Ljava/lang/Object;
	invokestatic	Method isElement:(Lscala/xml/pull/ProducerConsumerIterator;Ljava/lang/Object;)Z
	ifne	l1 // iconst_1
	aload_0
	aload_0
	invokeinterface	InterfaceMethod scala/xml/pull/ProducerConsumerIterator.scala$xml$pull$ProducerConsumerIterator$$queue:()Ljava/util/concurrent/LinkedBlockingQueue;
	invokevirtual	Method java/util/concurrent/LinkedBlockingQueue.peek:()Ljava/lang/Object;
	invokestatic	Method isElement:(Lscala/xml/pull/ProducerConsumerIterator;Ljava/lang/Object;)Z
	ifeq	l2 // iconst_0
l1	iconst_1
	goto	l3 // ireturn
l2	iconst_0
l3	ireturn
  Labels:
   	l1 = 29 // iconst_1
   	l2 = 33 // iconst_0
   	l3 = 34 // ireturn
  LocalVariableTable: 
   Start  Length  Slot  Name   Signature
   0      35      0    $this       Lscala/xml/pull/ProducerConsumerIterator;


private static java.lang.Object drainBuffer(scala.xml.pull.ProducerConsumerIterator);
  Signature: (Lscala/xml/pull/ProducerConsumerIterator;)Ljava/lang/Object;
  Code:
   Stack=2, Locals=2, Args_size=1
	getstatic	Field scala/Predef$.MODULE$:Lscala/Predef$;
	aload_0
	invokestatic	Method eos:(Lscala/xml/pull/ProducerConsumerIterator;)Z
	ifeq	l1 // iconst_1
	iconst_0
	goto	l2 // invokevirtual
l1	iconst_1
l2	invokevirtual	Method scala/Predef$.assert:(Z)V
	aload_0
	invokeinterface	InterfaceMethod scala/xml/pull/ProducerConsumerIterator.buffer:()Ljava/lang/Object;
	astore_1
	aload_0
	aconst_null
	invokeinterface	InterfaceMethod scala/xml/pull/ProducerConsumerIterator.buffer_$eq:(Ljava/lang/Object;)V
	aload_1
	areturn
  Labels:
   	l1 = 14 // iconst_1
   	l2 = 15 // invokevirtual
  LocalVariableTable: 
   Start  Length  Slot  Name   Signature
   0      34      0    $this       Lscala/xml/pull/ProducerConsumerIterator;
   25      8      1    res       Ljava/lang/Object;


public static void $init$(scala.xml.pull.ProducerConsumerIterator);
  Signature: (Lscala/xml/pull/ProducerConsumerIterator;)V
  Code:
   Stack=2, Locals=1, Args_size=1
	aload_0
	iconst_m1
	invokeinterface	InterfaceMethod scala/xml/pull/ProducerConsumerIterator.scala$xml$pull$ProducerConsumerIterator$_setter_$MaxQueueSize_$eq:(I)V
	return
  Labels:
  LocalVariableTable: 
   Start  Length  Slot  Name   Signature
   0      8      0    $this       Lscala/xml/pull/ProducerConsumerIterator;


}

