Compiled from "XMLEventReader.scala"
public final class scala.xml.pull.ProducerConsumerIterator$$anonfun$fillBuffer$2 extends java.lang.Object implements scala.Function0,scala.ScalaObject,java.io.Serializable
  SourceFile: "XMLEventReader.scala"
  Scala: length = 0x
   
  InnerClass: 
   public final $anonfun$fillBuffer$2=class scala/xml/pull/ProducerConsumerIterator$$anonfun$fillBuffer$2 of class scala/xml/pull/ProducerConsumerIterator
  minor version: 0
  major version: 49
  Constant pool:
Asciz	SourceFile;
Asciz	XMLEventReader.scala;
Asciz	<clinit>;
Asciz	()V;
Asciz	Code;
Asciz	serialVersionUID;
Asciz	J;
Asciz	scala/xml/pull/ProducerConsumerIterator$$anonfun$fillBuffer$2;
class	scala/xml/pull/ProducerConsumerIterator$$anonfun$fillBuffer$2
NameAndType	serialVersionUID:J
Field	scala/xml/pull/ProducerConsumerIterator$$anonfun$fillBuffer$2.serialVersionUID:J
Asciz	$outer;
Asciz	Lscala/xml/pull/ProducerConsumerIterator;;
Asciz	<init>;
Asciz	(Lscala/xml/pull/ProducerConsumerIterator;)V;
Asciz	LineNumberTable;
Asciz	java/lang/NullPointerException;
class	java/lang/NullPointerException
NameAndType	"<init>":()V
Method	java/lang/NullPointerException."<init>":()V
NameAndType	$outer:Lscala/xml/pull/ProducerConsumerIterator;
Field	scala/xml/pull/ProducerConsumerIterator$$anonfun$fillBuffer$2.$outer:Lscala/xml/pull/ProducerConsumerIterator;
Asciz	java/lang/Object;
class	java/lang/Object
Method	java/lang/Object."<init>":()V
Asciz	scala/Function0$class;
class	scala/Function0$class
Asciz	$init$;
Asciz	(Lscala/Function0;)V;
NameAndType	$init$:(Lscala/Function0;)V
Method	scala/Function0$class.$init$:(Lscala/Function0;)V
Asciz	this;
Asciz	Lscala/xml/pull/ProducerConsumerIterator$$anonfun$fillBuffer$2;;
Asciz	LocalVariableTable;
Asciz	(Lscala/xml/pull/ProducerConsumerIterator<TT;>;)V;
Asciz	Signature;
Asciz	apply;
Asciz	()Ljava/lang/Object;;
Asciz	scala/xml/pull/ProducerConsumerIterator;
class	scala/xml/pull/ProducerConsumerIterator
Asciz	EndOfStream;
NameAndType	EndOfStream:()Ljava/lang/Object;
InterfaceMethod	scala/xml/pull/ProducerConsumerIterator.EndOfStream:()Ljava/lang/Object;
Asciz	()TT;;
Asciz	toString;
Asciz	()Ljava/lang/String;;
Asciz	(Lscala/Function0;)Ljava/lang/String;;
NameAndType	toString:(Lscala/Function0;)Ljava/lang/String;
Method	scala/Function0$class.toString:(Lscala/Function0;)Ljava/lang/String;
Asciz	Scala;
Asciz	InnerClasses;
Asciz	$anonfun$fillBuffer$2;
Asciz	scala/Function0;
class	scala/Function0
Asciz	scala/ScalaObject;
class	scala/ScalaObject
Asciz	java/io/Serializable;
class	java/io/Serializable

{
public static final long serialVersionUID;
  Signature: J

private final scala.xml.pull.ProducerConsumerIterator $outer;
  Signature: Lscala/xml/pull/ProducerConsumerIterator;

public static {};
  Signature: ()V
  Code:
   Stack=2, Locals=0, Args_size=0
	lconst_0
	putstatic	Field serialVersionUID:J
	return
  Labels:

public scala.xml.pull.ProducerConsumerIterator$$anonfun$fillBuffer$2(scala.xml.pull.ProducerConsumerIterator);
  Signature: (Lscala/xml/pull/ProducerConsumerIterator;)V
  Code:
   Stack=2, Locals=2, Args_size=2
	aload_1
	ifnonnull	l1 // aload_0
	new	class java/lang/NullPointerException
	dup
	invokespecial	Method java/lang/NullPointerException."<init>":()V
	athrow
l1	aload_0
	aload_1
	putfield	Field $outer:Lscala/xml/pull/ProducerConsumerIterator;
	aload_0
	invokespecial	Method java/lang/Object."<init>":()V
	aload_0
	invokestatic	Method scala/Function0$class.$init$:(Lscala/Function0;)V
	return
  Labels:
   	l1 = 12 // aload_0
  LocalVariableTable: 
   Start  Length  Slot  Name   Signature
   0      26      0    this       Lscala/xml/pull/ProducerConsumerIterator$$anonfun$fillBuffer$2;
   0      26      1    $outer       Lscala/xml/pull/ProducerConsumerIterator;

  Signature: length = 0x2
   00 23 

public final java.lang.Object apply();
  Signature: ()Ljava/lang/Object;
  Code:
   Stack=1, Locals=2, Args_size=1
	aload_0
	getfield	Field $outer:Lscala/xml/pull/ProducerConsumerIterator;
	astore_1
	aload_0
	getfield	Field $outer:Lscala/xml/pull/ProducerConsumerIterator;
	invokeinterface	InterfaceMethod scala/xml/pull/ProducerConsumerIterator.EndOfStream:()Ljava/lang/Object;
	areturn
  Labels:
  LocalVariableTable: 
   Start  Length  Slot  Name   Signature
   0      15      0    this       Lscala/xml/pull/ProducerConsumerIterator$$anonfun$fillBuffer$2;

  Signature: length = 0x2
   00 2C 

public java.lang.String toString();
  Signature: ()Ljava/lang/String;
  Code:
   Stack=1, Locals=1, Args_size=1
	aload_0
	invokestatic	Method scala/Function0$class.toString:(Lscala/Function0;)Ljava/lang/String;
	areturn
  Labels:

}

