Compiled from "XMLEventReader.scala"
public final class scala.xml.pull.ProducerConsumerIterator$$anonfun$produce$1 extends java.lang.Object implements scala.Function0,scala.ScalaObject,java.io.Serializable
  SourceFile: "XMLEventReader.scala"
  Scala: length = 0x
   
  InnerClass: 
   public final $anonfun$produce$1=class scala/xml/pull/ProducerConsumerIterator$$anonfun$produce$1 of class scala/xml/pull/ProducerConsumerIterator
  minor version: 0
  major version: 49
  Constant pool:
Asciz	SourceFile;
Asciz	XMLEventReader.scala;
Asciz	<clinit>;
Asciz	()V;
Asciz	Code;
Asciz	serialVersionUID;
Asciz	J;
Asciz	scala/xml/pull/ProducerConsumerIterator$$anonfun$produce$1;
class	scala/xml/pull/ProducerConsumerIterator$$anonfun$produce$1
NameAndType	serialVersionUID:J
Field	scala/xml/pull/ProducerConsumerIterator$$anonfun$produce$1.serialVersionUID:J
Asciz	x$1;
Asciz	Ljava/lang/Object;;
Asciz	$outer;
Asciz	Lscala/xml/pull/ProducerConsumerIterator;;
Asciz	<init>;
Asciz	(Lscala/xml/pull/ProducerConsumerIterator;Ljava/lang/Object;)V;
Asciz	LineNumberTable;
Asciz	java/lang/NullPointerException;
class	java/lang/NullPointerException
NameAndType	"<init>":()V
Method	java/lang/NullPointerException."<init>":()V
NameAndType	$outer:Lscala/xml/pull/ProducerConsumerIterator;
Field	scala/xml/pull/ProducerConsumerIterator$$anonfun$produce$1.$outer:Lscala/xml/pull/ProducerConsumerIterator;
NameAndType	x$1:Ljava/lang/Object;
Field	scala/xml/pull/ProducerConsumerIterator$$anonfun$produce$1.x$1:Ljava/lang/Object;
Asciz	java/lang/Object;
class	java/lang/Object
Method	java/lang/Object."<init>":()V
Asciz	scala/Function0$class;
class	scala/Function0$class
Asciz	$init$;
Asciz	(Lscala/Function0;)V;
NameAndType	$init$:(Lscala/Function0;)V
Method	scala/Function0$class.$init$:(Lscala/Function0;)V
Asciz	this;
Asciz	Lscala/xml/pull/ProducerConsumerIterator$$anonfun$produce$1;;
Asciz	LocalVariableTable;
Asciz	(Lscala/xml/pull/ProducerConsumerIterator<TT;>;)V;
Asciz	Signature;
Asciz	apply;
Asciz	()Ljava/lang/Object;;
NameAndType	apply:()V
Method	scala/xml/pull/ProducerConsumerIterator$$anonfun$produce$1.apply:()V
Asciz	scala/runtime/BoxedUnit;
class	scala/runtime/BoxedUnit
Asciz	UNIT;
Asciz	Lscala/runtime/BoxedUnit;;
NameAndType	UNIT:Lscala/runtime/BoxedUnit;
Field	scala/runtime/BoxedUnit.UNIT:Lscala/runtime/BoxedUnit;
Asciz	scala/xml/pull/ProducerConsumerIterator;
class	scala/xml/pull/ProducerConsumerIterator
Asciz	scala$xml$pull$ProducerConsumerIterator$$queue;
Asciz	()Ljava/util/concurrent/LinkedBlockingQueue;;
NameAndType	scala$xml$pull$ProducerConsumerIterator$$queue:()Ljava/util/concurrent/LinkedBlockingQueue;
InterfaceMethod	scala/xml/pull/ProducerConsumerIterator.scala$xml$pull$ProducerConsumerIterator$$queue:()Ljava/util/concurrent/LinkedBlockingQueue;
Asciz	java/util/concurrent/LinkedBlockingQueue;
class	java/util/concurrent/LinkedBlockingQueue
Asciz	put;
Asciz	(Ljava/lang/Object;)V;
NameAndType	put:(Ljava/lang/Object;)V
Method	java/util/concurrent/LinkedBlockingQueue.put:(Ljava/lang/Object;)V
Asciz	toString;
Asciz	()Ljava/lang/String;;
Asciz	(Lscala/Function0;)Ljava/lang/String;;
NameAndType	toString:(Lscala/Function0;)Ljava/lang/String;
Method	scala/Function0$class.toString:(Lscala/Function0;)Ljava/lang/String;
Asciz	Scala;
Asciz	InnerClasses;
Asciz	$anonfun$produce$1;
Asciz	scala/Function0;
class	scala/Function0
Asciz	scala/ScalaObject;
class	scala/ScalaObject
Asciz	java/io/Serializable;
class	java/io/Serializable

{
public static final long serialVersionUID;
  Signature: J

private final java.lang.Object x$1;
  Signature: Ljava/lang/Object;

private final scala.xml.pull.ProducerConsumerIterator $outer;
  Signature: Lscala/xml/pull/ProducerConsumerIterator;

public static {};
  Signature: ()V
  Code:
   Stack=2, Locals=0, Args_size=0
	lconst_0
	putstatic	Field serialVersionUID:J
	return
  Labels:

public scala.xml.pull.ProducerConsumerIterator$$anonfun$produce$1(scala.xml.pull.ProducerConsumerIterator, java.lang.Object);
  Signature: (Lscala/xml/pull/ProducerConsumerIterator;Ljava/lang/Object;)V
  Code:
   Stack=2, Locals=3, Args_size=3
	aload_1
	ifnonnull	l1 // aload_0
	new	class java/lang/NullPointerException
	dup
	invokespecial	Method java/lang/NullPointerException."<init>":()V
	athrow
l1	aload_0
	aload_1
	putfield	Field $outer:Lscala/xml/pull/ProducerConsumerIterator;
	aload_0
	aload_2
	putfield	Field x$1:Ljava/lang/Object;
	aload_0
	invokespecial	Method java/lang/Object."<init>":()V
	aload_0
	invokestatic	Method scala/Function0$class.$init$:(Lscala/Function0;)V
	return
  Labels:
   	l1 = 12 // aload_0
  LocalVariableTable: 
   Start  Length  Slot  Name   Signature
   0      31      0    this       Lscala/xml/pull/ProducerConsumerIterator$$anonfun$produce$1;
   0      31      1    $outer       Lscala/xml/pull/ProducerConsumerIterator;

  Signature: length = 0x2
   00 27 

public final java.lang.Object apply();
  Signature: ()Ljava/lang/Object;
  Code:
   Stack=1, Locals=2, Args_size=1
	aload_0
	getfield	Field $outer:Lscala/xml/pull/ProducerConsumerIterator;
	astore_1
	aload_0
	invokevirtual	Method apply:()V
	getstatic	Field scala/runtime/BoxedUnit.UNIT:Lscala/runtime/BoxedUnit;
	areturn
  Labels:
  LocalVariableTable: 
   Start  Length  Slot  Name   Signature
   0      13      0    this       Lscala/xml/pull/ProducerConsumerIterator$$anonfun$produce$1;


public final void apply();
  Signature: ()V
  Code:
   Stack=2, Locals=2, Args_size=1
	aload_0
	getfield	Field $outer:Lscala/xml/pull/ProducerConsumerIterator;
	astore_1
	aload_0
	getfield	Field $outer:Lscala/xml/pull/ProducerConsumerIterator;
	invokeinterface	InterfaceMethod scala/xml/pull/ProducerConsumerIterator.scala$xml$pull$ProducerConsumerIterator$$queue:()Ljava/util/concurrent/LinkedBlockingQueue;
	aload_0
	getfield	Field x$1:Ljava/lang/Object;
	invokevirtual	Method java/util/concurrent/LinkedBlockingQueue.put:(Ljava/lang/Object;)V
	return
  Labels:
  LocalVariableTable: 
   Start  Length  Slot  Name   Signature
   0      22      0    this       Lscala/xml/pull/ProducerConsumerIterator$$anonfun$produce$1;


public java.lang.String toString();
  Signature: ()Ljava/lang/String;
  Code:
   Stack=1, Locals=1, Args_size=1
	aload_0
	invokestatic	Method scala/Function0$class.toString:(Lscala/Function0;)Ljava/lang/String;
	areturn
  Labels:

}

