Compiled from "XMLEventReader.scala"
public class scala.xml.pull.XMLEventReader$Parser extends scala.xml.parsing.MarkupHandler implements scala.xml.parsing.MarkupParser,scala.xml.parsing.ExternalSources,java.lang.Runnable,scala.ScalaObject
  SourceFile: "XMLEventReader.scala"
  Scala: length = 0x
   
  InnerClass: 
   public Parser=class scala/xml/pull/XMLEventReader$Parser of class scala/xml/pull/XMLEventReader
   public final $anonfun$run$1=class scala/xml/pull/XMLEventReader$Parser$$anonfun$run$1 of class scala/xml/pull/XMLEventReader$Parser
   public final $anonfun$setEvent$1=class scala/xml/pull/XMLEventReader$Parser$$anonfun$setEvent$1 of class scala/xml/pull/XMLEventReader$Parser
  minor version: 0
  major version: 49
  Constant pool:
Asciz	SourceFile;
Asciz	XMLEventReader.scala;
Asciz	eof;
Asciz	Z;
Asciz	doc;
Asciz	Lscala/xml/Document;;
Asciz	dtd;
Asciz	Lscala/xml/dtd/DTD;;
Asciz	cbuf;
Asciz	Lscala/collection/mutable/StringBuilder;;
Asciz	ch;
Asciz	C;
Asciz	tmppos;
Asciz	I;
Asciz	extIndex;
Asciz	pos;
Asciz	inpStack;
Asciz	Lscala/collection/immutable/List;;
Asciz	scala$xml$parsing$MarkupParser$$handle;
Asciz	Lscala/xml/parsing/MarkupHandler;;
Asciz	curInput;
Asciz	Lscala/io/Source;;
Asciz	$outer;
Asciz	Lscala/xml/pull/XMLEventReader;;
Asciz	preserveWS;
Asciz	input;
Asciz	<init>;
Asciz	(Lscala/xml/pull/XMLEventReader;Lscala/io/Source;)V;
Asciz	Code;
Asciz	LineNumberTable;
Asciz	scala/xml/pull/XMLEventReader$Parser;
class	scala/xml/pull/XMLEventReader$Parser
NameAndType	input:Lscala/io/Source;
Field	scala/xml/pull/XMLEventReader$Parser.input:Lscala/io/Source;
Asciz	java/lang/NullPointerException;
class	java/lang/NullPointerException
Asciz	()V;
NameAndType	"<init>":()V
Method	java/lang/NullPointerException."<init>":()V
NameAndType	$outer:Lscala/xml/pull/XMLEventReader;
Field	scala/xml/pull/XMLEventReader$Parser.$outer:Lscala/xml/pull/XMLEventReader;
Asciz	scala/xml/parsing/MarkupHandler;
class	scala/xml/parsing/MarkupHandler
Method	scala/xml/parsing/MarkupHandler."<init>":()V
Asciz	scala/xml/parsing/TokenTests$class;
class	scala/xml/parsing/TokenTests$class
Asciz	$init$;
Asciz	(Lscala/xml/parsing/TokenTests;)V;
NameAndType	$init$:(Lscala/xml/parsing/TokenTests;)V
Method	scala/xml/parsing/TokenTests$class.$init$:(Lscala/xml/parsing/TokenTests;)V
Asciz	scala/xml/parsing/MarkupParserCommon$class;
class	scala/xml/parsing/MarkupParserCommon$class
Asciz	(Lscala/xml/parsing/MarkupParserCommon;)V;
NameAndType	$init$:(Lscala/xml/parsing/MarkupParserCommon;)V
Method	scala/xml/parsing/MarkupParserCommon$class.$init$:(Lscala/xml/parsing/MarkupParserCommon;)V
Asciz	scala/xml/parsing/MarkupParser$class;
class	scala/xml/parsing/MarkupParser$class
Asciz	(Lscala/xml/parsing/MarkupHandler;)V;
NameAndType	$init$:(Lscala/xml/parsing/MarkupHandler;)V
Method	scala/xml/parsing/MarkupParser$class.$init$:(Lscala/xml/parsing/MarkupHandler;)V
Asciz	scala/xml/parsing/ExternalSources$class;
class	scala/xml/parsing/ExternalSources$class
Method	scala/xml/parsing/ExternalSources$class.$init$:(Lscala/xml/parsing/MarkupHandler;)V
Asciz	scala/xml/pull/XMLEventReader;
class	scala/xml/pull/XMLEventReader
Asciz	()Z;
NameAndType	preserveWS:()Z
Method	scala/xml/pull/XMLEventReader.preserveWS:()Z
NameAndType	preserveWS:Z
Field	scala/xml/pull/XMLEventReader$Parser.preserveWS:Z
Asciz	this;
Asciz	Lscala/xml/pull/XMLEventReader$Parser;;
Asciz	LocalVariableTable;
Asciz	()Ljava/lang/Object;;
Asciz	scala/xml/parsing/MarkupParser;
class	scala/xml/parsing/MarkupParser
Asciz	()I;
NameAndType	tmppos:()I
InterfaceMethod	scala/xml/parsing/MarkupParser.tmppos:()I
Asciz	scala/runtime/BoxesRunTime;
class	scala/runtime/BoxesRunTime
Asciz	boxToInteger;
Asciz	(I)Ljava/lang/Integer;;
NameAndType	boxToInteger:(I)Ljava/lang/Integer;
Method	scala/runtime/BoxesRunTime.boxToInteger:(I)Ljava/lang/Integer;
Asciz	tmppos_$eq;
Asciz	(Ljava/lang/Object;)V;
Asciz	unboxToInt;
Asciz	(Ljava/lang/Object;)I;
NameAndType	unboxToInt:(Ljava/lang/Object;)I
Method	scala/runtime/BoxesRunTime.unboxToInt:(Ljava/lang/Object;)I
Asciz	(I)V;
NameAndType	tmppos_$eq:(I)V
InterfaceMethod	scala/xml/parsing/MarkupParser.tmppos_$eq:(I)V
Asciz	mkProcInstr;
Asciz	(Ljava/lang/Object;Ljava/lang/String;Ljava/lang/String;)Ljava/lang/Object;;
Asciz	(ILjava/lang/String;Ljava/lang/String;)Lscala/xml/NodeSeq;;
NameAndType	mkProcInstr:(ILjava/lang/String;Ljava/lang/String;)Lscala/xml/NodeSeq;
InterfaceMethod	scala/xml/parsing/MarkupParser.mkProcInstr:(ILjava/lang/String;Ljava/lang/String;)Lscala/xml/NodeSeq;
Asciz	position;
Asciz	Ljava/lang/Object;;
Asciz	name;
Asciz	Ljava/lang/String;;
Asciz	text;
Asciz	mkAttributes;
Asciz	(Ljava/lang/String;Ljava/lang/Object;)Ljava/lang/Object;;
Asciz	scala/xml/NamespaceBinding;
class	scala/xml/NamespaceBinding
Asciz	(Ljava/lang/String;Lscala/xml/NamespaceBinding;)Lscala/Tuple2;;
NameAndType	mkAttributes:(Ljava/lang/String;Lscala/xml/NamespaceBinding;)Lscala/Tuple2;
InterfaceMethod	scala/xml/parsing/MarkupParser.mkAttributes:(Ljava/lang/String;Lscala/xml/NamespaceBinding;)Lscala/Tuple2;
Asciz	pscope;
Asciz	scala$xml$pull$XMLEventReader$Parser$$$outer;
Asciz	()Lscala/xml/pull/XMLEventReader;;
Asciz	run;
Asciz	()Lscala/io/Source;;
NameAndType	input:()Lscala/io/Source;
Method	scala/xml/pull/XMLEventReader$Parser.input:()Lscala/io/Source;
Asciz	curInput_$eq;
Asciz	(Lscala/io/Source;)V;
NameAndType	curInput_$eq:(Lscala/io/Source;)V
InterfaceMethod	scala/xml/parsing/MarkupParser.curInput_$eq:(Lscala/io/Source;)V
NameAndType	scala$xml$pull$XMLEventReader$Parser$$$outer:()Lscala/xml/pull/XMLEventReader;
Method	scala/xml/pull/XMLEventReader$Parser.scala$xml$pull$XMLEventReader$Parser$$$outer:()Lscala/xml/pull/XMLEventReader;
Asciz	scala/xml/pull/XMLEventReader$Parser$$anonfun$run$1;
class	scala/xml/pull/XMLEventReader$Parser$$anonfun$run$1
Asciz	(Lscala/xml/pull/XMLEventReader$Parser;)V;
NameAndType	"<init>":(Lscala/xml/pull/XMLEventReader$Parser;)V
Method	scala/xml/pull/XMLEventReader$Parser$$anonfun$run$1."<init>":(Lscala/xml/pull/XMLEventReader$Parser;)V
Asciz	scala/xml/pull/ProducerConsumerIterator;
class	scala/xml/pull/ProducerConsumerIterator
Asciz	interruptibly;
Asciz	(Lscala/Function0;)Lscala/Option;;
NameAndType	interruptibly:(Lscala/Function0;)Lscala/Option;
InterfaceMethod	scala/xml/pull/ProducerConsumerIterator.interruptibly:(Lscala/Function0;)Lscala/Option;
Asciz	scala/Predef$;
class	scala/Predef$
Asciz	MODULE$;
Asciz	Lscala/Predef$;;
NameAndType	MODULE$:Lscala/Predef$;
Field	scala/Predef$.MODULE$:Lscala/Predef$;
Asciz	scala/xml/pull/XMLEvent;
class	scala/xml/pull/XMLEvent
Asciz	POISON;
Asciz	()Lscala/xml/pull/XMLEventReader$POISON$;;
NameAndType	POISON:()Lscala/xml/pull/XMLEventReader$POISON$;
Method	scala/xml/pull/XMLEventReader.POISON:()Lscala/xml/pull/XMLEventReader$POISON$;
Asciz	[Ljava/lang/Object;;
class	"[Ljava/lang/Object;"
Asciz	wrapRefArray;
Asciz	([Ljava/lang/Object;)Lscala/collection/mutable/WrappedArray;;
NameAndType	wrapRefArray:([Ljava/lang/Object;)Lscala/collection/mutable/WrappedArray;
Method	scala/Predef$.wrapRefArray:([Ljava/lang/Object;)Lscala/collection/mutable/WrappedArray;
Asciz	setEvent;
Asciz	(Lscala/collection/Seq;)Lscala/xml/NodeSeq;;
NameAndType	setEvent:(Lscala/collection/Seq;)Lscala/xml/NodeSeq;
Method	scala/xml/pull/XMLEventReader$Parser.setEvent:(Lscala/collection/Seq;)Lscala/xml/NodeSeq;
Asciz	(ILjava/lang/String;)Lscala/xml/NodeSeq;;
Asciz	scala/xml/pull/EvText;
class	scala/xml/pull/EvText
Asciz	(Ljava/lang/String;)V;
NameAndType	"<init>":(Ljava/lang/String;)V
Method	scala/xml/pull/EvText."<init>":(Ljava/lang/String;)V
Asciz	txt;
Asciz	entityRef;
Asciz	scala/xml/pull/EvEntityRef;
class	scala/xml/pull/EvEntityRef
Method	scala/xml/pull/EvEntityRef."<init>":(Ljava/lang/String;)V
Asciz	n;
Asciz	comment;
Asciz	scala/xml/pull/EvComment;
class	scala/xml/pull/EvComment
Method	scala/xml/pull/EvComment."<init>":(Ljava/lang/String;)V
Asciz	procInstr;
Asciz	scala/xml/pull/EvProcInstr;
class	scala/xml/pull/EvProcInstr
Asciz	(Ljava/lang/String;Ljava/lang/String;)V;
NameAndType	"<init>":(Ljava/lang/String;Ljava/lang/String;)V
Method	scala/xml/pull/EvProcInstr."<init>":(Ljava/lang/String;Ljava/lang/String;)V
Asciz	target;
Asciz	elem;
Asciz	(ILjava/lang/String;Ljava/lang/String;Lscala/xml/MetaData;Lscala/xml/NamespaceBinding;Lscala/xml/NodeSeq;)Lscala/xml/NodeSeq;;
Asciz	scala/xml/Elem;
class	scala/xml/Elem
Asciz	ignore;
String	ignore
Asciz	scala/xml/Null$;
class	scala/xml/Null$
Asciz	Lscala/xml/Null$;;
NameAndType	MODULE$:Lscala/xml/Null$;
Field	scala/xml/Null$.MODULE$:Lscala/xml/Null$;
Asciz	scala/package$;
class	scala/package$
Asciz	Lscala/package$;;
NameAndType	MODULE$:Lscala/package$;
Field	scala/package$.MODULE$:Lscala/package$;
Asciz	$scope;
Asciz	()Lscala/xml/TopScope$;;
NameAndType	$scope:()Lscala/xml/TopScope$;
Method	scala/package$.$scope:()Lscala/xml/TopScope$;
Asciz	scala/xml/Node;
class	scala/xml/Node
Asciz	(Ljava/lang/String;Ljava/lang/String;Lscala/xml/MetaData;Lscala/xml/NamespaceBinding;Lscala/collection/Seq;)V;
NameAndType	"<init>":(Ljava/lang/String;Ljava/lang/String;Lscala/xml/MetaData;Lscala/xml/NamespaceBinding;Lscala/collection/Seq;)V
Method	scala/xml/Elem."<init>":(Ljava/lang/String;Ljava/lang/String;Lscala/xml/MetaData;Lscala/xml/NamespaceBinding;Lscala/collection/Seq;)V
Asciz	pre;
Asciz	label;
Asciz	attrs;
Asciz	Lscala/xml/MetaData;;
Asciz	Lscala/xml/NamespaceBinding;;
Asciz	nodes;
Asciz	Lscala/xml/NodeSeq;;
Asciz	elemEnd;
Asciz	(ILjava/lang/String;Ljava/lang/String;)V;
Asciz	scala/xml/pull/EvElemEnd;
class	scala/xml/pull/EvElemEnd
Method	scala/xml/pull/EvElemEnd."<init>":(Ljava/lang/String;Ljava/lang/String;)V
Asciz	elemStart;
Asciz	(ILjava/lang/String;Ljava/lang/String;Lscala/xml/MetaData;Lscala/xml/NamespaceBinding;)V;
Asciz	scala/xml/pull/EvElemStart;
class	scala/xml/pull/EvElemStart
Asciz	(Ljava/lang/String;Ljava/lang/String;Lscala/xml/MetaData;Lscala/xml/NamespaceBinding;)V;
NameAndType	"<init>":(Ljava/lang/String;Ljava/lang/String;Lscala/xml/MetaData;Lscala/xml/NamespaceBinding;)V
Method	scala/xml/pull/EvElemStart."<init>":(Ljava/lang/String;Ljava/lang/String;Lscala/xml/MetaData;Lscala/xml/NamespaceBinding;)V
Asciz	scope;
Asciz	scala/xml/pull/XMLEventReader$Parser$$anonfun$setEvent$1;
class	scala/xml/pull/XMLEventReader$Parser$$anonfun$setEvent$1
Method	scala/xml/pull/XMLEventReader$Parser$$anonfun$setEvent$1."<init>":(Lscala/xml/pull/XMLEventReader$Parser;)V
Asciz	scala/collection/IterableLike;
class	scala/collection/IterableLike
Asciz	foreach;
Asciz	(Lscala/Function1;)V;
NameAndType	foreach:(Lscala/Function1;)V
InterfaceMethod	scala/collection/IterableLike.foreach:(Lscala/Function1;)V
Asciz	scala/xml/NodeSeq$;
class	scala/xml/NodeSeq$
Asciz	Lscala/xml/NodeSeq$;;
NameAndType	MODULE$:Lscala/xml/NodeSeq$;
Field	scala/xml/NodeSeq$.MODULE$:Lscala/xml/NodeSeq$;
Asciz	Empty;
Asciz	()Lscala/xml/NodeSeq;;
NameAndType	Empty:()Lscala/xml/NodeSeq;
Method	scala/xml/NodeSeq$.Empty:()Lscala/xml/NodeSeq;
Asciz	es;
Asciz	Lscala/collection/Seq;;
Asciz	(Lscala/collection/Seq<Lscala/xml/pull/XMLEvent;>;)Lscala/xml/NodeSeq;;
Asciz	Signature;
Asciz	checkPubID;
Asciz	(Ljava/lang/String;)Z;
Asciz	(Lscala/xml/parsing/TokenTests;Ljava/lang/String;)Z;
NameAndType	checkPubID:(Lscala/xml/parsing/TokenTests;Ljava/lang/String;)Z
Method	scala/xml/parsing/TokenTests$class.checkPubID:(Lscala/xml/parsing/TokenTests;Ljava/lang/String;)Z
Asciz	s;
Asciz	checkSysID;
NameAndType	checkSysID:(Lscala/xml/parsing/TokenTests;Ljava/lang/String;)Z
Method	scala/xml/parsing/TokenTests$class.checkSysID:(Lscala/xml/parsing/TokenTests;Ljava/lang/String;)Z
Asciz	isValidIANAEncoding;
Asciz	(Lscala/collection/Seq;)Z;
Asciz	(Lscala/xml/parsing/TokenTests;Lscala/collection/Seq;)Z;
NameAndType	isValidIANAEncoding:(Lscala/xml/parsing/TokenTests;Lscala/collection/Seq;)Z
Method	scala/xml/parsing/TokenTests$class.isValidIANAEncoding:(Lscala/xml/parsing/TokenTests;Lscala/collection/Seq;)Z
Asciz	ianaEncoding;
Asciz	isPubIDChar;
Asciz	(C)Z;
Asciz	(Lscala/xml/parsing/TokenTests;C)Z;
NameAndType	isPubIDChar:(Lscala/xml/parsing/TokenTests;C)Z
Method	scala/xml/parsing/TokenTests$class.isPubIDChar:(Lscala/xml/parsing/TokenTests;C)Z
Asciz	isName;
NameAndType	isName:(Lscala/xml/parsing/TokenTests;Ljava/lang/String;)Z
Method	scala/xml/parsing/TokenTests$class.isName:(Lscala/xml/parsing/TokenTests;Ljava/lang/String;)Z
Asciz	isNameStart;
NameAndType	isNameStart:(Lscala/xml/parsing/TokenTests;C)Z
Method	scala/xml/parsing/TokenTests$class.isNameStart:(Lscala/xml/parsing/TokenTests;C)Z
Asciz	isNameChar;
NameAndType	isNameChar:(Lscala/xml/parsing/TokenTests;C)Z
Method	scala/xml/parsing/TokenTests$class.isNameChar:(Lscala/xml/parsing/TokenTests;C)Z
Asciz	isAlphaDigit;
NameAndType	isAlphaDigit:(Lscala/xml/parsing/TokenTests;C)Z
Method	scala/xml/parsing/TokenTests$class.isAlphaDigit:(Lscala/xml/parsing/TokenTests;C)Z
Asciz	c;
Asciz	isAlpha;
NameAndType	isAlpha:(Lscala/xml/parsing/TokenTests;C)Z
Method	scala/xml/parsing/TokenTests$class.isAlpha:(Lscala/xml/parsing/TokenTests;C)Z
Asciz	isSpace;
NameAndType	isSpace:(Lscala/xml/parsing/TokenTests;Lscala/collection/Seq;)Z
Method	scala/xml/parsing/TokenTests$class.isSpace:(Lscala/xml/parsing/TokenTests;Lscala/collection/Seq;)Z
Asciz	cs;
NameAndType	isSpace:(Lscala/xml/parsing/TokenTests;C)Z
Method	scala/xml/parsing/TokenTests$class.isSpace:(Lscala/xml/parsing/TokenTests;C)Z
Asciz	xTakeUntil;
Asciz	(Lscala/Function2;Lscala/Function0;Ljava/lang/String;)Ljava/lang/Object;;
Asciz	(Lscala/xml/parsing/MarkupParserCommon;Lscala/Function2;Lscala/Function0;Ljava/lang/String;)Ljava/lang/Object;;
NameAndType	xTakeUntil:(Lscala/xml/parsing/MarkupParserCommon;Lscala/Function2;Lscala/Function0;Ljava/lang/String;)Ljava/lang/Object;
Method	scala/xml/parsing/MarkupParserCommon$class.xTakeUntil:(Lscala/xml/parsing/MarkupParserCommon;Lscala/Function2;Lscala/Function0;Ljava/lang/String;)Ljava/lang/Object;
Asciz	handler;
Asciz	Lscala/Function2;;
Asciz	positioner;
Asciz	Lscala/Function0;;
Asciz	until;
Asciz	saving;
Asciz	(Ljava/lang/Object;Lscala/Function1;Lscala/Function0;)Ljava/lang/Object;;
Asciz	(Lscala/xml/parsing/MarkupParserCommon;Ljava/lang/Object;Lscala/Function1;Lscala/Function0;)Ljava/lang/Object;;
NameAndType	saving:(Lscala/xml/parsing/MarkupParserCommon;Ljava/lang/Object;Lscala/Function1;Lscala/Function0;)Ljava/lang/Object;
Method	scala/xml/parsing/MarkupParserCommon$class.saving:(Lscala/xml/parsing/MarkupParserCommon;Ljava/lang/Object;Lscala/Function1;Lscala/Function0;)Ljava/lang/Object;
Asciz	getter;
Asciz	setter;
Asciz	Lscala/Function1;;
Asciz	body;
Asciz	returning;
Asciz	(Ljava/lang/Object;Lscala/Function1;)Ljava/lang/Object;;
Asciz	(Lscala/xml/parsing/MarkupParserCommon;Ljava/lang/Object;Lscala/Function1;)Ljava/lang/Object;;
NameAndType	returning:(Lscala/xml/parsing/MarkupParserCommon;Ljava/lang/Object;Lscala/Function1;)Ljava/lang/Object;
Method	scala/xml/parsing/MarkupParserCommon$class.returning:(Lscala/xml/parsing/MarkupParserCommon;Ljava/lang/Object;Lscala/Function1;)Ljava/lang/Object;
Asciz	x;
Asciz	f;
Asciz	xSpace;
NameAndType	xSpace:(Lscala/xml/parsing/MarkupParserCommon;)V
Method	scala/xml/parsing/MarkupParserCommon$class.xSpace:(Lscala/xml/parsing/MarkupParserCommon;)V
Asciz	xSpaceOpt;
NameAndType	xSpaceOpt:(Lscala/xml/parsing/MarkupParserCommon;)V
Method	scala/xml/parsing/MarkupParserCommon$class.xSpaceOpt:(Lscala/xml/parsing/MarkupParserCommon;)V
Asciz	xEQ;
NameAndType	xEQ:(Lscala/xml/parsing/MarkupParserCommon;)V
Method	scala/xml/parsing/MarkupParserCommon$class.xEQ:(Lscala/xml/parsing/MarkupParserCommon;)V
Asciz	xToken;
Asciz	(Lscala/collection/Seq;)V;
Asciz	(Lscala/xml/parsing/MarkupParserCommon;Lscala/collection/Seq;)V;
NameAndType	xToken:(Lscala/xml/parsing/MarkupParserCommon;Lscala/collection/Seq;)V
Method	scala/xml/parsing/MarkupParserCommon$class.xToken:(Lscala/xml/parsing/MarkupParserCommon;Lscala/collection/Seq;)V
Asciz	that;
Asciz	(C)V;
Asciz	(Lscala/xml/parsing/MarkupParserCommon;C)V;
NameAndType	xToken:(Lscala/xml/parsing/MarkupParserCommon;C)V
Method	scala/xml/parsing/MarkupParserCommon$class.xToken:(Lscala/xml/parsing/MarkupParserCommon;C)V
Asciz	errorAndResult;
Asciz	(Lscala/xml/parsing/MarkupParserCommon;Ljava/lang/String;Ljava/lang/Object;)Ljava/lang/Object;;
NameAndType	errorAndResult:(Lscala/xml/parsing/MarkupParserCommon;Ljava/lang/String;Ljava/lang/Object;)Ljava/lang/Object;
Method	scala/xml/parsing/MarkupParserCommon$class.errorAndResult:(Lscala/xml/parsing/MarkupParserCommon;Ljava/lang/String;Ljava/lang/Object;)Ljava/lang/Object;
Asciz	msg;
Asciz	xCharRef;
Asciz	()Ljava/lang/String;;
Asciz	(Lscala/xml/parsing/MarkupParserCommon;)Ljava/lang/String;;
NameAndType	xCharRef:(Lscala/xml/parsing/MarkupParserCommon;)Ljava/lang/String;
Method	scala/xml/parsing/MarkupParserCommon$class.xCharRef:(Lscala/xml/parsing/MarkupParserCommon;)Ljava/lang/String;
Asciz	(Lscala/collection/Iterator;)Ljava/lang/String;;
Asciz	(Lscala/xml/parsing/MarkupParserCommon;Lscala/collection/Iterator;)Ljava/lang/String;;
NameAndType	xCharRef:(Lscala/xml/parsing/MarkupParserCommon;Lscala/collection/Iterator;)Ljava/lang/String;
Method	scala/xml/parsing/MarkupParserCommon$class.xCharRef:(Lscala/xml/parsing/MarkupParserCommon;Lscala/collection/Iterator;)Ljava/lang/String;
Asciz	it;
Asciz	Lscala/collection/Iterator;;
Asciz	(Lscala/Function0;Lscala/Function0;)Ljava/lang/String;;
Asciz	(Lscala/xml/parsing/MarkupParserCommon;Lscala/Function0;Lscala/Function0;)Ljava/lang/String;;
NameAndType	xCharRef:(Lscala/xml/parsing/MarkupParserCommon;Lscala/Function0;Lscala/Function0;)Ljava/lang/String;
Method	scala/xml/parsing/MarkupParserCommon$class.xCharRef:(Lscala/xml/parsing/MarkupParserCommon;Lscala/Function0;Lscala/Function0;)Ljava/lang/String;
Asciz	nextch;
Asciz	xName;
NameAndType	xName:(Lscala/xml/parsing/MarkupParserCommon;)Ljava/lang/String;
Method	scala/xml/parsing/MarkupParserCommon$class.xName:(Lscala/xml/parsing/MarkupParserCommon;)Ljava/lang/String;
Asciz	xEndTag;
Asciz	(Lscala/xml/parsing/MarkupParserCommon;Ljava/lang/String;)V;
NameAndType	xEndTag:(Lscala/xml/parsing/MarkupParserCommon;Ljava/lang/String;)V
Method	scala/xml/parsing/MarkupParserCommon$class.xEndTag:(Lscala/xml/parsing/MarkupParserCommon;Ljava/lang/String;)V
Asciz	startName;
Asciz	xAttributeValue;
NameAndType	xAttributeValue:(Lscala/xml/parsing/MarkupParserCommon;)Ljava/lang/String;
Method	scala/xml/parsing/MarkupParserCommon$class.xAttributeValue:(Lscala/xml/parsing/MarkupParserCommon;)Ljava/lang/String;
Asciz	(C)Ljava/lang/String;;
Asciz	(Lscala/xml/parsing/MarkupParserCommon;C)Ljava/lang/String;;
NameAndType	xAttributeValue:(Lscala/xml/parsing/MarkupParserCommon;C)Ljava/lang/String;
Method	scala/xml/parsing/MarkupParserCommon$class.xAttributeValue:(Lscala/xml/parsing/MarkupParserCommon;C)Ljava/lang/String;
Asciz	endCh;
Asciz	xProcInstr;
Asciz	(Lscala/xml/parsing/MarkupParserCommon;)Ljava/lang/Object;;
NameAndType	xProcInstr:(Lscala/xml/parsing/MarkupParserCommon;)Ljava/lang/Object;
Method	scala/xml/parsing/MarkupParserCommon$class.xProcInstr:(Lscala/xml/parsing/MarkupParserCommon;)Ljava/lang/Object;
Asciz	xTag;
Asciz	(Ljava/lang/Object;)Lscala/Tuple2;;
Asciz	(Lscala/xml/parsing/MarkupParserCommon;Ljava/lang/Object;)Lscala/Tuple2;;
NameAndType	xTag:(Lscala/xml/parsing/MarkupParserCommon;Ljava/lang/Object;)Lscala/Tuple2;
Method	scala/xml/parsing/MarkupParserCommon$class.xTag:(Lscala/xml/parsing/MarkupParserCommon;Ljava/lang/Object;)Lscala/Tuple2;
Asciz	unreachable;
Asciz	()Lscala/runtime/Nothing$;;
Asciz	(Lscala/xml/parsing/MarkupParserCommon;)Lscala/runtime/Nothing$;;
NameAndType	unreachable:(Lscala/xml/parsing/MarkupParserCommon;)Lscala/runtime/Nothing$;
Method	scala/xml/parsing/MarkupParserCommon$class.unreachable:(Lscala/xml/parsing/MarkupParserCommon;)Lscala/runtime/Nothing$;
Asciz	pop;
NameAndType	pop:(Lscala/xml/parsing/MarkupHandler;)V
Method	scala/xml/parsing/MarkupParser$class.pop:(Lscala/xml/parsing/MarkupHandler;)V
Asciz	pushExternal;
Asciz	(Lscala/xml/parsing/MarkupHandler;Ljava/lang/String;)V;
NameAndType	pushExternal:(Lscala/xml/parsing/MarkupHandler;Ljava/lang/String;)V
Method	scala/xml/parsing/MarkupParser$class.pushExternal:(Lscala/xml/parsing/MarkupHandler;Ljava/lang/String;)V
Asciz	systemId;
Asciz	push;
NameAndType	push:(Lscala/xml/parsing/MarkupHandler;Ljava/lang/String;)V
Method	scala/xml/parsing/MarkupParser$class.push:(Lscala/xml/parsing/MarkupHandler;Ljava/lang/String;)V
Asciz	entityName;
Asciz	reportValidationError;
Asciz	(ILjava/lang/String;)V;
Asciz	(Lscala/xml/parsing/MarkupHandler;ILjava/lang/String;)V;
NameAndType	reportValidationError:(Lscala/xml/parsing/MarkupHandler;ILjava/lang/String;)V
Method	scala/xml/parsing/MarkupParser$class.reportValidationError:(Lscala/xml/parsing/MarkupHandler;ILjava/lang/String;)V
Asciz	str;
Asciz	reportSyntaxError;
NameAndType	reportSyntaxError:(Lscala/xml/parsing/MarkupHandler;Ljava/lang/String;)V
Method	scala/xml/parsing/MarkupParser$class.reportSyntaxError:(Lscala/xml/parsing/MarkupHandler;Ljava/lang/String;)V
NameAndType	reportSyntaxError:(Lscala/xml/parsing/MarkupHandler;ILjava/lang/String;)V
Method	scala/xml/parsing/MarkupParser$class.reportSyntaxError:(Lscala/xml/parsing/MarkupHandler;ILjava/lang/String;)V
Asciz	notationDecl;
NameAndType	notationDecl:(Lscala/xml/parsing/MarkupHandler;)V
Method	scala/xml/parsing/MarkupParser$class.notationDecl:(Lscala/xml/parsing/MarkupHandler;)V
Asciz	entityDecl;
NameAndType	entityDecl:(Lscala/xml/parsing/MarkupHandler;)V
Method	scala/xml/parsing/MarkupParser$class.entityDecl:(Lscala/xml/parsing/MarkupHandler;)V
Asciz	attrDecl;
NameAndType	attrDecl:(Lscala/xml/parsing/MarkupHandler;)V
Method	scala/xml/parsing/MarkupParser$class.attrDecl:(Lscala/xml/parsing/MarkupHandler;)V
Asciz	elementDecl;
NameAndType	elementDecl:(Lscala/xml/parsing/MarkupHandler;)V
Method	scala/xml/parsing/MarkupParser$class.elementDecl:(Lscala/xml/parsing/MarkupHandler;)V
Asciz	intSubset;
NameAndType	intSubset:(Lscala/xml/parsing/MarkupHandler;)V
Method	scala/xml/parsing/MarkupParser$class.intSubset:(Lscala/xml/parsing/MarkupHandler;)V
Asciz	markupDecl;
NameAndType	markupDecl:(Lscala/xml/parsing/MarkupHandler;)V
Method	scala/xml/parsing/MarkupParser$class.markupDecl:(Lscala/xml/parsing/MarkupHandler;)V
Asciz	markupDecl1;
Asciz	(Lscala/xml/parsing/MarkupHandler;)Ljava/lang/Object;;
NameAndType	markupDecl1:(Lscala/xml/parsing/MarkupHandler;)Ljava/lang/Object;
Method	scala/xml/parsing/MarkupParser$class.markupDecl1:(Lscala/xml/parsing/MarkupHandler;)Ljava/lang/Object;
Asciz	extSubset;
NameAndType	extSubset:(Lscala/xml/parsing/MarkupHandler;)V
Method	scala/xml/parsing/MarkupParser$class.extSubset:(Lscala/xml/parsing/MarkupHandler;)V
Asciz	pubidLiteral;
Asciz	(Lscala/xml/parsing/MarkupHandler;)Ljava/lang/String;;
NameAndType	pubidLiteral:(Lscala/xml/parsing/MarkupHandler;)Ljava/lang/String;
Method	scala/xml/parsing/MarkupParser$class.pubidLiteral:(Lscala/xml/parsing/MarkupHandler;)Ljava/lang/String;
Asciz	systemLiteral;
NameAndType	systemLiteral:(Lscala/xml/parsing/MarkupHandler;)Ljava/lang/String;
Method	scala/xml/parsing/MarkupParser$class.systemLiteral:(Lscala/xml/parsing/MarkupHandler;)Ljava/lang/String;
Asciz	xText;
NameAndType	xText:(Lscala/xml/parsing/MarkupHandler;)Ljava/lang/String;
Method	scala/xml/parsing/MarkupParser$class.xText:(Lscala/xml/parsing/MarkupHandler;)Ljava/lang/String;
Asciz	element1;
Asciz	(Lscala/xml/NamespaceBinding;)Lscala/xml/NodeSeq;;
Asciz	(Lscala/xml/parsing/MarkupHandler;Lscala/xml/NamespaceBinding;)Lscala/xml/NodeSeq;;
NameAndType	element1:(Lscala/xml/parsing/MarkupHandler;Lscala/xml/NamespaceBinding;)Lscala/xml/NodeSeq;
Method	scala/xml/parsing/MarkupParser$class.element1:(Lscala/xml/parsing/MarkupHandler;Lscala/xml/NamespaceBinding;)Lscala/xml/NodeSeq;
Asciz	element;
NameAndType	element:(Lscala/xml/parsing/MarkupHandler;Lscala/xml/NamespaceBinding;)Lscala/xml/NodeSeq;
Method	scala/xml/parsing/MarkupParser$class.element:(Lscala/xml/parsing/MarkupHandler;Lscala/xml/NamespaceBinding;)Lscala/xml/NodeSeq;
Asciz	parseDTD;
NameAndType	parseDTD:(Lscala/xml/parsing/MarkupHandler;)V
Method	scala/xml/parsing/MarkupParser$class.parseDTD:(Lscala/xml/parsing/MarkupHandler;)V
Asciz	externalID;
Asciz	()Lscala/xml/dtd/ExternalID;;
Asciz	(Lscala/xml/parsing/MarkupHandler;)Lscala/xml/dtd/ExternalID;;
NameAndType	externalID:(Lscala/xml/parsing/MarkupHandler;)Lscala/xml/dtd/ExternalID;
Method	scala/xml/parsing/MarkupParser$class.externalID:(Lscala/xml/parsing/MarkupHandler;)Lscala/xml/dtd/ExternalID;
Asciz	content;
NameAndType	content:(Lscala/xml/parsing/MarkupHandler;Lscala/xml/NamespaceBinding;)Lscala/xml/NodeSeq;
Method	scala/xml/parsing/MarkupParser$class.content:(Lscala/xml/parsing/MarkupHandler;Lscala/xml/NamespaceBinding;)Lscala/xml/NodeSeq;
Asciz	content1;
Asciz	(Lscala/xml/NamespaceBinding;Lscala/xml/NodeBuffer;)V;
Asciz	(Lscala/xml/parsing/MarkupHandler;Lscala/xml/NamespaceBinding;Lscala/xml/NodeBuffer;)V;
NameAndType	content1:(Lscala/xml/parsing/MarkupHandler;Lscala/xml/NamespaceBinding;Lscala/xml/NodeBuffer;)V
Method	scala/xml/parsing/MarkupParser$class.content1:(Lscala/xml/parsing/MarkupHandler;Lscala/xml/NamespaceBinding;Lscala/xml/NodeBuffer;)V
Asciz	ts;
Asciz	Lscala/xml/NodeBuffer;;
Asciz	appendText;
Asciz	(ILscala/xml/NodeBuffer;Ljava/lang/String;)V;
Asciz	(Lscala/xml/parsing/MarkupHandler;ILscala/xml/NodeBuffer;Ljava/lang/String;)V;
NameAndType	appendText:(Lscala/xml/parsing/MarkupHandler;ILscala/xml/NodeBuffer;Ljava/lang/String;)V
Method	scala/xml/parsing/MarkupParser$class.appendText:(Lscala/xml/parsing/MarkupHandler;ILscala/xml/NodeBuffer;Ljava/lang/String;)V
Asciz	xComment;
Asciz	(Lscala/xml/parsing/MarkupHandler;)Lscala/xml/NodeSeq;;
NameAndType	xComment:(Lscala/xml/parsing/MarkupHandler;)Lscala/xml/NodeSeq;
Method	scala/xml/parsing/MarkupParser$class.xComment:(Lscala/xml/parsing/MarkupHandler;)Lscala/xml/NodeSeq;
Asciz	xCharData;
NameAndType	xCharData:(Lscala/xml/parsing/MarkupHandler;)Lscala/xml/NodeSeq;
Method	scala/xml/parsing/MarkupParser$class.xCharData:(Lscala/xml/parsing/MarkupHandler;)Lscala/xml/NodeSeq;
Asciz	xEntityValue;
NameAndType	xEntityValue:(Lscala/xml/parsing/MarkupHandler;)Ljava/lang/String;
Method	scala/xml/parsing/MarkupParser$class.xEntityValue:(Lscala/xml/parsing/MarkupHandler;)Ljava/lang/String;
Asciz	xAttributes;
Asciz	(Lscala/xml/NamespaceBinding;)Lscala/Tuple2;;
Asciz	(Lscala/xml/parsing/MarkupHandler;Lscala/xml/NamespaceBinding;)Lscala/Tuple2;;
NameAndType	xAttributes:(Lscala/xml/parsing/MarkupHandler;Lscala/xml/NamespaceBinding;)Lscala/Tuple2;
Method	scala/xml/parsing/MarkupParser$class.xAttributes:(Lscala/xml/parsing/MarkupHandler;Lscala/xml/NamespaceBinding;)Lscala/Tuple2;
Asciz	()C;
Asciz	(Lscala/xml/parsing/MarkupHandler;)C;
NameAndType	nextch:(Lscala/xml/parsing/MarkupHandler;)C
Method	scala/xml/parsing/MarkupParser$class.nextch:(Lscala/xml/parsing/MarkupHandler;)C
Asciz	(Lscala/xml/parsing/MarkupHandler;Ljava/lang/String;Lscala/xml/NamespaceBinding;)Lscala/Tuple2;;
NameAndType	mkAttributes:(Lscala/xml/parsing/MarkupHandler;Ljava/lang/String;Lscala/xml/NamespaceBinding;)Lscala/Tuple2;
Method	scala/xml/parsing/MarkupParser$class.mkAttributes:(Lscala/xml/parsing/MarkupHandler;Ljava/lang/String;Lscala/xml/NamespaceBinding;)Lscala/Tuple2;
Asciz	(Lscala/xml/parsing/MarkupHandler;ILjava/lang/String;Ljava/lang/String;)Lscala/xml/NodeSeq;;
NameAndType	mkProcInstr:(Lscala/xml/parsing/MarkupHandler;ILjava/lang/String;Ljava/lang/String;)Lscala/xml/NodeSeq;
Method	scala/xml/parsing/MarkupParser$class.mkProcInstr:(Lscala/xml/parsing/MarkupHandler;ILjava/lang/String;Ljava/lang/String;)Lscala/xml/NodeSeq;
Asciz	ch_returning_nextch;
NameAndType	ch_returning_nextch:(Lscala/xml/parsing/MarkupHandler;)C
Method	scala/xml/parsing/MarkupParser$class.ch_returning_nextch:(Lscala/xml/parsing/MarkupHandler;)C
Asciz	initialize;
Asciz	()Lscala/xml/parsing/MarkupHandler;;
Asciz	(Lscala/xml/parsing/MarkupHandler;)Lscala/xml/parsing/MarkupHandler;;
NameAndType	initialize:(Lscala/xml/parsing/MarkupHandler;)Lscala/xml/parsing/MarkupHandler;
Method	scala/xml/parsing/MarkupParser$class.initialize:(Lscala/xml/parsing/MarkupHandler;)Lscala/xml/parsing/MarkupHandler;
Asciz	putChar;
Asciz	(C)Lscala/collection/mutable/StringBuilder;;
Asciz	(Lscala/xml/parsing/MarkupHandler;C)Lscala/collection/mutable/StringBuilder;;
NameAndType	putChar:(Lscala/xml/parsing/MarkupHandler;C)Lscala/collection/mutable/StringBuilder;
Method	scala/xml/parsing/MarkupParser$class.putChar:(Lscala/xml/parsing/MarkupHandler;C)Lscala/collection/mutable/StringBuilder;
Asciz	document;
Asciz	()Lscala/xml/Document;;
Asciz	(Lscala/xml/parsing/MarkupHandler;)Lscala/xml/Document;;
NameAndType	document:(Lscala/xml/parsing/MarkupHandler;)Lscala/xml/Document;
Method	scala/xml/parsing/MarkupParser$class.document:(Lscala/xml/parsing/MarkupHandler;)Lscala/xml/Document;
Asciz	textDecl;
Asciz	()Lscala/Tuple2;;
Asciz	(Lscala/xml/parsing/MarkupHandler;)Lscala/Tuple2;;
NameAndType	textDecl:(Lscala/xml/parsing/MarkupHandler;)Lscala/Tuple2;
Method	scala/xml/parsing/MarkupParser$class.textDecl:(Lscala/xml/parsing/MarkupHandler;)Lscala/Tuple2;
Asciz	prolog;
Asciz	()Lscala/Tuple3;;
Asciz	(Lscala/xml/parsing/MarkupHandler;)Lscala/Tuple3;;
NameAndType	prolog:(Lscala/xml/parsing/MarkupHandler;)Lscala/Tuple3;
Method	scala/xml/parsing/MarkupParser$class.prolog:(Lscala/xml/parsing/MarkupHandler;)Lscala/Tuple3;
Asciz	xmlProcInstr;
Asciz	()Lscala/xml/MetaData;;
Asciz	(Lscala/xml/parsing/MarkupHandler;)Lscala/xml/MetaData;;
NameAndType	xmlProcInstr:(Lscala/xml/parsing/MarkupHandler;)Lscala/xml/MetaData;
Method	scala/xml/parsing/MarkupParser$class.xmlProcInstr:(Lscala/xml/parsing/MarkupHandler;)Lscala/xml/MetaData;
Asciz	lookahead;
Asciz	()Lscala/collection/BufferedIterator;;
Asciz	(Lscala/xml/parsing/MarkupHandler;)Lscala/collection/BufferedIterator;;
NameAndType	lookahead:(Lscala/xml/parsing/MarkupHandler;)Lscala/collection/BufferedIterator;
Method	scala/xml/parsing/MarkupParser$class.lookahead:(Lscala/xml/parsing/MarkupHandler;)Lscala/collection/BufferedIterator;
Asciz	xHandleError;
Asciz	(CLjava/lang/String;)V;
Asciz	(Lscala/xml/parsing/MarkupHandler;CLjava/lang/String;)V;
NameAndType	xHandleError:(Lscala/xml/parsing/MarkupHandler;CLjava/lang/String;)V
Method	scala/xml/parsing/MarkupParser$class.xHandleError:(Lscala/xml/parsing/MarkupHandler;CLjava/lang/String;)V
Asciz	errorNoEnd;
Asciz	(Ljava/lang/String;)Lscala/runtime/Nothing$;;
Asciz	(Lscala/xml/parsing/MarkupHandler;Ljava/lang/String;)Lscala/runtime/Nothing$;;
NameAndType	errorNoEnd:(Lscala/xml/parsing/MarkupHandler;Ljava/lang/String;)Lscala/runtime/Nothing$;
Method	scala/xml/parsing/MarkupParser$class.errorNoEnd:(Lscala/xml/parsing/MarkupHandler;Ljava/lang/String;)Lscala/runtime/Nothing$;
Asciz	tag;
Asciz	truncatedError;
NameAndType	truncatedError:(Lscala/xml/parsing/MarkupHandler;Ljava/lang/String;)Lscala/runtime/Nothing$;
Method	scala/xml/parsing/MarkupParser$class.truncatedError:(Lscala/xml/parsing/MarkupHandler;Ljava/lang/String;)Lscala/runtime/Nothing$;
Asciz	scala$xml$parsing$MarkupParser$_setter_$cbuf_$eq;
Asciz	(Lscala/collection/mutable/StringBuilder;)V;
NameAndType	cbuf:Lscala/collection/mutable/StringBuilder;
Field	scala/xml/pull/XMLEventReader$Parser.cbuf:Lscala/collection/mutable/StringBuilder;
Asciz	scala$xml$parsing$MarkupParser$_setter_$scala$xml$parsing$MarkupParser$$handle_$eq;
NameAndType	scala$xml$parsing$MarkupParser$$handle:Lscala/xml/parsing/MarkupHandler;
Field	scala/xml/pull/XMLEventReader$Parser.scala$xml$parsing$MarkupParser$$handle:Lscala/xml/parsing/MarkupHandler;
Asciz	eof_$eq;
Asciz	(Z)V;
NameAndType	eof:Z
Field	scala/xml/pull/XMLEventReader$Parser.eof:Z
Asciz	doc_$eq;
Asciz	(Lscala/xml/Document;)V;
NameAndType	doc:Lscala/xml/Document;
Field	scala/xml/pull/XMLEventReader$Parser.doc:Lscala/xml/Document;
Asciz	dtd_$eq;
Asciz	(Lscala/xml/dtd/DTD;)V;
NameAndType	dtd:Lscala/xml/dtd/DTD;
Field	scala/xml/pull/XMLEventReader$Parser.dtd:Lscala/xml/dtd/DTD;
Asciz	()Lscala/xml/dtd/DTD;;
Asciz	()Lscala/collection/mutable/StringBuilder;;
Asciz	ch_$eq;
NameAndType	ch:C
Field	scala/xml/pull/XMLEventReader$Parser.ch:C
NameAndType	tmppos:I
Field	scala/xml/pull/XMLEventReader$Parser.tmppos:I
Asciz	extIndex_$eq;
NameAndType	extIndex:I
Field	scala/xml/pull/XMLEventReader$Parser.extIndex:I
Asciz	pos_$eq;
NameAndType	pos:I
Field	scala/xml/pull/XMLEventReader$Parser.pos:I
Asciz	inpStack_$eq;
Asciz	(Lscala/collection/immutable/List;)V;
NameAndType	inpStack:Lscala/collection/immutable/List;
Field	scala/xml/pull/XMLEventReader$Parser.inpStack:Lscala/collection/immutable/List;
Asciz	()Lscala/collection/immutable/List;;
NameAndType	curInput:Lscala/io/Source;
Field	scala/xml/pull/XMLEventReader$Parser.curInput:Lscala/io/Source;
Asciz	externalSource;
Asciz	(Ljava/lang/String;)Lscala/io/Source;;
Asciz	(Lscala/xml/parsing/MarkupHandler;Ljava/lang/String;)Lscala/io/Source;;
NameAndType	externalSource:(Lscala/xml/parsing/MarkupHandler;Ljava/lang/String;)Lscala/io/Source;
Method	scala/xml/parsing/ExternalSources$class.externalSource:(Lscala/xml/parsing/MarkupHandler;Ljava/lang/String;)Lscala/io/Source;
Asciz	Scala;
Asciz	InnerClasses;
Asciz	Parser;
Asciz	$anonfun$run$1;
Asciz	$anonfun$setEvent$1;
Asciz	scala/xml/parsing/ExternalSources;
class	scala/xml/parsing/ExternalSources
Asciz	java/lang/Runnable;
class	java/lang/Runnable
Asciz	scala/ScalaObject;
class	scala/ScalaObject

{
private boolean eof;
  Signature: Z

private scala.xml.Document doc;
  Signature: Lscala/xml/Document;

private scala.xml.dtd.DTD dtd;
  Signature: Lscala/xml/dtd/DTD;

private final scala.collection.mutable.StringBuilder cbuf;
  Signature: Lscala/collection/mutable/StringBuilder;

private char ch;
  Signature: C

private int tmppos;
  Signature: I

private int extIndex;
  Signature: I

private int pos;
  Signature: I

private scala.collection.immutable.List inpStack;
  Signature: Lscala/collection/immutable/List;

private final scala.xml.parsing.MarkupHandler scala$xml$parsing$MarkupParser$$handle;
  Signature: Lscala/xml/parsing/MarkupHandler;

private scala.io.Source curInput;
  Signature: Lscala/io/Source;

public final scala.xml.pull.XMLEventReader $outer;
  Signature: Lscala/xml/pull/XMLEventReader;

private final boolean preserveWS;
  Signature: Z

private final scala.io.Source input;
  Signature: Lscala/io/Source;

public scala.xml.pull.XMLEventReader$Parser(scala.xml.pull.XMLEventReader, scala.io.Source);
  Signature: (Lscala/xml/pull/XMLEventReader;Lscala/io/Source;)V
  Code:
   Stack=2, Locals=3, Args_size=3
	aload_0
	aload_2
	putfield	Field input:Lscala/io/Source;
	aload_1
	ifnonnull	l1 // aload_0
	new	class java/lang/NullPointerException
	dup
	invokespecial	Method java/lang/NullPointerException."<init>":()V
	athrow
l1	aload_0
	aload_1
	putfield	Field $outer:Lscala/xml/pull/XMLEventReader;
	aload_0
	invokespecial	Method scala/xml/parsing/MarkupHandler."<init>":()V
	aload_0
	invokestatic	Method scala/xml/parsing/TokenTests$class.$init$:(Lscala/xml/parsing/TokenTests;)V
	aload_0
	invokestatic	Method scala/xml/parsing/MarkupParserCommon$class.$init$:(Lscala/xml/parsing/MarkupParserCommon;)V
	aload_0
	invokestatic	Method scala/xml/parsing/MarkupParser$class.$init$:(Lscala/xml/parsing/MarkupHandler;)V
	aload_0
	invokestatic	Method scala/xml/parsing/ExternalSources$class.$init$:(Lscala/xml/parsing/MarkupHandler;)V
	aload_0
	aload_1
	invokevirtual	Method scala/xml/pull/XMLEventReader.preserveWS:()Z
	putfield	Field preserveWS:Z
	return
  Labels:
   	l1 = 17 // aload_0
  LocalVariableTable: 
   Start  Length  Slot  Name   Signature
   0      51      0    this       Lscala/xml/pull/XMLEventReader$Parser;
   0      51      1    $outer       Lscala/xml/pull/XMLEventReader;
   0      51      2    input       Lscala/io/Source;


public java.lang.Object tmppos();
  Signature: ()Ljava/lang/Object;
  Code:
   Stack=1, Locals=2, Args_size=1
	aload_0
	invokeinterface	InterfaceMethod scala/xml/parsing/MarkupParser.tmppos:()I
	istore_1
	iload_1
	invokestatic	Method scala/runtime/BoxesRunTime.boxToInteger:(I)Ljava/lang/Integer;
	areturn
  Labels:

public void tmppos_$eq(java.lang.Object);
  Signature: (Ljava/lang/Object;)V
  Code:
   Stack=2, Locals=2, Args_size=2
	aload_0
	aload_1
	invokestatic	Method scala/runtime/BoxesRunTime.unboxToInt:(Ljava/lang/Object;)I
	invokeinterface	InterfaceMethod scala/xml/parsing/MarkupParser.tmppos_$eq:(I)V
	return
  Labels:

public java.lang.Object mkProcInstr(java.lang.Object, java.lang.String, java.lang.String);
  Signature: (Ljava/lang/Object;Ljava/lang/String;Ljava/lang/String;)Ljava/lang/Object;
  Code:
   Stack=4, Locals=4, Args_size=4
	aload_0
	aload_1
	invokestatic	Method scala/runtime/BoxesRunTime.unboxToInt:(Ljava/lang/Object;)I
	aload_2
	aload_3
	invokeinterface	InterfaceMethod scala/xml/parsing/MarkupParser.mkProcInstr:(ILjava/lang/String;Ljava/lang/String;)Lscala/xml/NodeSeq;
	areturn
  Labels:
  LocalVariableTable: 
   Start  Length  Slot  Name   Signature
   0      13      0    this       Lscala/xml/pull/XMLEventReader$Parser;
   0      13      1    position       Ljava/lang/Object;
   0      13      2    name       Ljava/lang/String;
   0      13      3    text       Ljava/lang/String;


public java.lang.Object mkAttributes(java.lang.String, java.lang.Object);
  Signature: (Ljava/lang/String;Ljava/lang/Object;)Ljava/lang/Object;
  Code:
   Stack=3, Locals=3, Args_size=3
	aload_0
	aload_1
	aload_2
	checkcast	class scala/xml/NamespaceBinding
	invokeinterface	InterfaceMethod scala/xml/parsing/MarkupParser.mkAttributes:(Ljava/lang/String;Lscala/xml/NamespaceBinding;)Lscala/Tuple2;
	areturn
  Labels:
  LocalVariableTable: 
   Start  Length  Slot  Name   Signature
   0      12      0    this       Lscala/xml/pull/XMLEventReader$Parser;
   0      12      1    name       Ljava/lang/String;
   0      12      2    pscope       Ljava/lang/Object;


public scala.xml.pull.XMLEventReader scala$xml$pull$XMLEventReader$Parser$$$outer();
  Signature: ()Lscala/xml/pull/XMLEventReader;
  Code:
   Stack=1, Locals=1, Args_size=1
	aload_0
	getfield	Field $outer:Lscala/xml/pull/XMLEventReader;
	areturn
  Labels:

public void run();
  Signature: ()V
  Code:
   Stack=6, Locals=1, Args_size=1
	aload_0
	aload_0
	invokevirtual	Method input:()Lscala/io/Source;
	invokeinterface	InterfaceMethod scala/xml/parsing/MarkupParser.curInput_$eq:(Lscala/io/Source;)V
	aload_0
	invokevirtual	Method scala$xml$pull$XMLEventReader$Parser$$$outer:()Lscala/xml/pull/XMLEventReader;
	new	class scala/xml/pull/XMLEventReader$Parser$$anonfun$run$1
	dup
	aload_0
	invokespecial	Method scala/xml/pull/XMLEventReader$Parser$$anonfun$run$1."<init>":(Lscala/xml/pull/XMLEventReader$Parser;)V
	invokeinterface	InterfaceMethod scala/xml/pull/ProducerConsumerIterator.interruptibly:(Lscala/Function0;)Lscala/Option;
	pop
	aload_0
	getstatic	Field scala/Predef$.MODULE$:Lscala/Predef$;
	iconst_1
	anewarray	class scala/xml/pull/XMLEvent
	dup
	iconst_0
	aload_0
	invokevirtual	Method scala$xml$pull$XMLEventReader$Parser$$$outer:()Lscala/xml/pull/XMLEventReader;
	invokevirtual	Method scala/xml/pull/XMLEventReader.POISON:()Lscala/xml/pull/XMLEventReader$POISON$;
	aastore
	checkcast	class "[Ljava/lang/Object;"
	invokevirtual	Method scala/Predef$.wrapRefArray:([Ljava/lang/Object;)Lscala/collection/mutable/WrappedArray;
	invokevirtual	Method setEvent:(Lscala/collection/Seq;)Lscala/xml/NodeSeq;
	pop
	return
  Labels:

public scala.xml.NodeSeq text(int, java.lang.String);
  Signature: (ILjava/lang/String;)Lscala/xml/NodeSeq;
  Code:
   Stack=8, Locals=3, Args_size=3
	aload_0
	getstatic	Field scala/Predef$.MODULE$:Lscala/Predef$;
	iconst_1
	anewarray	class scala/xml/pull/XMLEvent
	dup
	iconst_0
	new	class scala/xml/pull/EvText
	dup
	aload_2
	invokespecial	Method scala/xml/pull/EvText."<init>":(Ljava/lang/String;)V
	aastore
	checkcast	class "[Ljava/lang/Object;"
	invokevirtual	Method scala/Predef$.wrapRefArray:([Ljava/lang/Object;)Lscala/collection/mutable/WrappedArray;
	invokevirtual	Method setEvent:(Lscala/collection/Seq;)Lscala/xml/NodeSeq;
	areturn
  Labels:
  LocalVariableTable: 
   Start  Length  Slot  Name   Signature
   0      29      0    this       Lscala/xml/pull/XMLEventReader$Parser;
   0      29      1    pos       I
   0      29      2    txt       Ljava/lang/String;


public scala.xml.NodeSeq entityRef(int, java.lang.String);
  Signature: (ILjava/lang/String;)Lscala/xml/NodeSeq;
  Code:
   Stack=8, Locals=3, Args_size=3
	aload_0
	getstatic	Field scala/Predef$.MODULE$:Lscala/Predef$;
	iconst_1
	anewarray	class scala/xml/pull/XMLEvent
	dup
	iconst_0
	new	class scala/xml/pull/EvEntityRef
	dup
	aload_2
	invokespecial	Method scala/xml/pull/EvEntityRef."<init>":(Ljava/lang/String;)V
	aastore
	checkcast	class "[Ljava/lang/Object;"
	invokevirtual	Method scala/Predef$.wrapRefArray:([Ljava/lang/Object;)Lscala/collection/mutable/WrappedArray;
	invokevirtual	Method setEvent:(Lscala/collection/Seq;)Lscala/xml/NodeSeq;
	areturn
  Labels:
  LocalVariableTable: 
   Start  Length  Slot  Name   Signature
   0      29      0    this       Lscala/xml/pull/XMLEventReader$Parser;
   0      29      1    pos       I
   0      29      2    n       Ljava/lang/String;


public scala.xml.NodeSeq comment(int, java.lang.String);
  Signature: (ILjava/lang/String;)Lscala/xml/NodeSeq;
  Code:
   Stack=8, Locals=3, Args_size=3
	aload_0
	getstatic	Field scala/Predef$.MODULE$:Lscala/Predef$;
	iconst_1
	anewarray	class scala/xml/pull/XMLEvent
	dup
	iconst_0
	new	class scala/xml/pull/EvComment
	dup
	aload_2
	invokespecial	Method scala/xml/pull/EvComment."<init>":(Ljava/lang/String;)V
	aastore
	checkcast	class "[Ljava/lang/Object;"
	invokevirtual	Method scala/Predef$.wrapRefArray:([Ljava/lang/Object;)Lscala/collection/mutable/WrappedArray;
	invokevirtual	Method setEvent:(Lscala/collection/Seq;)Lscala/xml/NodeSeq;
	areturn
  Labels:
  LocalVariableTable: 
   Start  Length  Slot  Name   Signature
   0      29      0    this       Lscala/xml/pull/XMLEventReader$Parser;
   0      29      1    pos       I
   0      29      2    txt       Ljava/lang/String;


public scala.xml.NodeSeq procInstr(int, java.lang.String, java.lang.String);
  Signature: (ILjava/lang/String;Ljava/lang/String;)Lscala/xml/NodeSeq;
  Code:
   Stack=9, Locals=4, Args_size=4
	aload_0
	getstatic	Field scala/Predef$.MODULE$:Lscala/Predef$;
	iconst_1
	anewarray	class scala/xml/pull/XMLEvent
	dup
	iconst_0
	new	class scala/xml/pull/EvProcInstr
	dup
	aload_2
	aload_3
	invokespecial	Method scala/xml/pull/EvProcInstr."<init>":(Ljava/lang/String;Ljava/lang/String;)V
	aastore
	checkcast	class "[Ljava/lang/Object;"
	invokevirtual	Method scala/Predef$.wrapRefArray:([Ljava/lang/Object;)Lscala/collection/mutable/WrappedArray;
	invokevirtual	Method setEvent:(Lscala/collection/Seq;)Lscala/xml/NodeSeq;
	areturn
  Labels:
  LocalVariableTable: 
   Start  Length  Slot  Name   Signature
   0      30      0    this       Lscala/xml/pull/XMLEventReader$Parser;
   0      30      1    pos       I
   0      30      2    target       Ljava/lang/String;
   0      30      3    txt       Ljava/lang/String;


public final scala.xml.NodeSeq elem(int, java.lang.String, java.lang.String, scala.xml.MetaData, scala.xml.NamespaceBinding, scala.xml.NodeSeq);
  Signature: (ILjava/lang/String;Ljava/lang/String;Lscala/xml/MetaData;Lscala/xml/NamespaceBinding;Lscala/xml/NodeSeq;)Lscala/xml/NodeSeq;
  Code:
   Stack=8, Locals=7, Args_size=7
	new	class scala/xml/Elem
	dup
	aconst_null
	ldc	String ignore
	getstatic	Field scala/xml/Null$.MODULE$:Lscala/xml/Null$;
	getstatic	Field scala/package$.MODULE$:Lscala/package$;
	invokevirtual	Method scala/package$.$scope:()Lscala/xml/TopScope$;
	getstatic	Field scala/Predef$.MODULE$:Lscala/Predef$;
	iconst_0
	anewarray	class scala/xml/Node
	checkcast	class "[Ljava/lang/Object;"
	invokevirtual	Method scala/Predef$.wrapRefArray:([Ljava/lang/Object;)Lscala/collection/mutable/WrappedArray;
	invokespecial	Method scala/xml/Elem."<init>":(Ljava/lang/String;Ljava/lang/String;Lscala/xml/MetaData;Lscala/xml/NamespaceBinding;Lscala/collection/Seq;)V
	areturn
  Labels:
  LocalVariableTable: 
   Start  Length  Slot  Name   Signature
   0      33      0    this       Lscala/xml/pull/XMLEventReader$Parser;
   0      33      1    pos       I
   0      33      2    pre       Ljava/lang/String;
   0      33      3    label       Ljava/lang/String;
   0      33      4    attrs       Lscala/xml/MetaData;
   0      33      5    pscope       Lscala/xml/NamespaceBinding;
   0      33      6    nodes       Lscala/xml/NodeSeq;


public void elemEnd(int, java.lang.String, java.lang.String);
  Signature: (ILjava/lang/String;Ljava/lang/String;)V
  Code:
   Stack=9, Locals=4, Args_size=4
	aload_0
	getstatic	Field scala/Predef$.MODULE$:Lscala/Predef$;
	iconst_1
	anewarray	class scala/xml/pull/XMLEvent
	dup
	iconst_0
	new	class scala/xml/pull/EvElemEnd
	dup
	aload_2
	aload_3
	invokespecial	Method scala/xml/pull/EvElemEnd."<init>":(Ljava/lang/String;Ljava/lang/String;)V
	aastore
	checkcast	class "[Ljava/lang/Object;"
	invokevirtual	Method scala/Predef$.wrapRefArray:([Ljava/lang/Object;)Lscala/collection/mutable/WrappedArray;
	invokevirtual	Method setEvent:(Lscala/collection/Seq;)Lscala/xml/NodeSeq;
	pop
	return
  Labels:
  LocalVariableTable: 
   Start  Length  Slot  Name   Signature
   0      31      0    this       Lscala/xml/pull/XMLEventReader$Parser;
   0      31      1    pos       I
   0      31      2    pre       Ljava/lang/String;
   0      31      3    label       Ljava/lang/String;


public void elemStart(int, java.lang.String, java.lang.String, scala.xml.MetaData, scala.xml.NamespaceBinding);
  Signature: (ILjava/lang/String;Ljava/lang/String;Lscala/xml/MetaData;Lscala/xml/NamespaceBinding;)V
  Code:
   Stack=11, Locals=6, Args_size=6
	aload_0
	getstatic	Field scala/Predef$.MODULE$:Lscala/Predef$;
	iconst_1
	anewarray	class scala/xml/pull/XMLEvent
	dup
	iconst_0
	new	class scala/xml/pull/EvElemStart
	dup
	aload_2
	aload_3
	aload	4
	aload	5
	invokespecial	Method scala/xml/pull/EvElemStart."<init>":(Ljava/lang/String;Ljava/lang/String;Lscala/xml/MetaData;Lscala/xml/NamespaceBinding;)V
	aastore
	checkcast	class "[Ljava/lang/Object;"
	invokevirtual	Method scala/Predef$.wrapRefArray:([Ljava/lang/Object;)Lscala/collection/mutable/WrappedArray;
	invokevirtual	Method setEvent:(Lscala/collection/Seq;)Lscala/xml/NodeSeq;
	pop
	return
  Labels:
  LocalVariableTable: 
   Start  Length  Slot  Name   Signature
   0      35      0    this       Lscala/xml/pull/XMLEventReader$Parser;
   0      35      1    pos       I
   0      35      2    pre       Ljava/lang/String;
   0      35      3    label       Ljava/lang/String;
   0      35      4    attrs       Lscala/xml/MetaData;
   0      35      5    scope       Lscala/xml/NamespaceBinding;


public scala.xml.NodeSeq setEvent(scala.collection.Seq);
  Signature: (Lscala/collection/Seq;)Lscala/xml/NodeSeq;
  Code:
   Stack=4, Locals=2, Args_size=2
	aload_1
	new	class scala/xml/pull/XMLEventReader$Parser$$anonfun$setEvent$1
	dup
	aload_0
	invokespecial	Method scala/xml/pull/XMLEventReader$Parser$$anonfun$setEvent$1."<init>":(Lscala/xml/pull/XMLEventReader$Parser;)V
	invokeinterface	InterfaceMethod scala/collection/IterableLike.foreach:(Lscala/Function1;)V
	getstatic	Field scala/xml/NodeSeq$.MODULE$:Lscala/xml/NodeSeq$;
	invokevirtual	Method scala/xml/NodeSeq$.Empty:()Lscala/xml/NodeSeq;
	areturn
  Labels:
  LocalVariableTable: 
   Start  Length  Slot  Name   Signature
   0      21      0    this       Lscala/xml/pull/XMLEventReader$Parser;
   0      21      1    es       Lscala/collection/Seq;

  Signature: length = 0x2
   00 FFFFFFF6 

public boolean preserveWS();
  Signature: ()Z
  Code:
   Stack=1, Locals=1, Args_size=1
	aload_0
	getfield	Field preserveWS:Z
	ireturn
  Labels:

public scala.io.Source input();
  Signature: ()Lscala/io/Source;
  Code:
   Stack=1, Locals=1, Args_size=1
	aload_0
	getfield	Field input:Lscala/io/Source;
	areturn
  Labels:

public boolean checkPubID(java.lang.String);
  Signature: (Ljava/lang/String;)Z
  Code:
   Stack=2, Locals=2, Args_size=2
	aload_0
	aload_1
	invokestatic	Method scala/xml/parsing/TokenTests$class.checkPubID:(Lscala/xml/parsing/TokenTests;Ljava/lang/String;)Z
	ireturn
  Labels:
  LocalVariableTable: 
   Start  Length  Slot  Name   Signature
   0      6      0    this       Lscala/xml/pull/XMLEventReader$Parser;
   0      6      1    s       Ljava/lang/String;


public boolean checkSysID(java.lang.String);
  Signature: (Ljava/lang/String;)Z
  Code:
   Stack=2, Locals=2, Args_size=2
	aload_0
	aload_1
	invokestatic	Method scala/xml/parsing/TokenTests$class.checkSysID:(Lscala/xml/parsing/TokenTests;Ljava/lang/String;)Z
	ireturn
  Labels:
  LocalVariableTable: 
   Start  Length  Slot  Name   Signature
   0      6      0    this       Lscala/xml/pull/XMLEventReader$Parser;
   0      6      1    s       Ljava/lang/String;


public boolean isValidIANAEncoding(scala.collection.Seq);
  Signature: (Lscala/collection/Seq;)Z
  Code:
   Stack=2, Locals=2, Args_size=2
	aload_0
	aload_1
	invokestatic	Method scala/xml/parsing/TokenTests$class.isValidIANAEncoding:(Lscala/xml/parsing/TokenTests;Lscala/collection/Seq;)Z
	ireturn
  Labels:
  LocalVariableTable: 
   Start  Length  Slot  Name   Signature
   0      6      0    this       Lscala/xml/pull/XMLEventReader$Parser;
   0      6      1    ianaEncoding       Lscala/collection/Seq;


public boolean isPubIDChar(char);
  Signature: (C)Z
  Code:
   Stack=2, Locals=2, Args_size=2
	aload_0
	iload_1
	invokestatic	Method scala/xml/parsing/TokenTests$class.isPubIDChar:(Lscala/xml/parsing/TokenTests;C)Z
	ireturn
  Labels:
  LocalVariableTable: 
   Start  Length  Slot  Name   Signature
   0      6      0    this       Lscala/xml/pull/XMLEventReader$Parser;
   0      6      1    ch       C


public boolean isName(java.lang.String);
  Signature: (Ljava/lang/String;)Z
  Code:
   Stack=2, Locals=2, Args_size=2
	aload_0
	aload_1
	invokestatic	Method scala/xml/parsing/TokenTests$class.isName:(Lscala/xml/parsing/TokenTests;Ljava/lang/String;)Z
	ireturn
  Labels:
  LocalVariableTable: 
   Start  Length  Slot  Name   Signature
   0      6      0    this       Lscala/xml/pull/XMLEventReader$Parser;
   0      6      1    s       Ljava/lang/String;


public boolean isNameStart(char);
  Signature: (C)Z
  Code:
   Stack=2, Locals=2, Args_size=2
	aload_0
	iload_1
	invokestatic	Method scala/xml/parsing/TokenTests$class.isNameStart:(Lscala/xml/parsing/TokenTests;C)Z
	ireturn
  Labels:
  LocalVariableTable: 
   Start  Length  Slot  Name   Signature
   0      6      0    this       Lscala/xml/pull/XMLEventReader$Parser;
   0      6      1    ch       C


public boolean isNameChar(char);
  Signature: (C)Z
  Code:
   Stack=2, Locals=2, Args_size=2
	aload_0
	iload_1
	invokestatic	Method scala/xml/parsing/TokenTests$class.isNameChar:(Lscala/xml/parsing/TokenTests;C)Z
	ireturn
  Labels:
  LocalVariableTable: 
   Start  Length  Slot  Name   Signature
   0      6      0    this       Lscala/xml/pull/XMLEventReader$Parser;
   0      6      1    ch       C


public boolean isAlphaDigit(char);
  Signature: (C)Z
  Code:
   Stack=2, Locals=2, Args_size=2
	aload_0
	iload_1
	invokestatic	Method scala/xml/parsing/TokenTests$class.isAlphaDigit:(Lscala/xml/parsing/TokenTests;C)Z
	ireturn
  Labels:
  LocalVariableTable: 
   Start  Length  Slot  Name   Signature
   0      6      0    this       Lscala/xml/pull/XMLEventReader$Parser;
   0      6      1    c       C


public boolean isAlpha(char);
  Signature: (C)Z
  Code:
   Stack=2, Locals=2, Args_size=2
	aload_0
	iload_1
	invokestatic	Method scala/xml/parsing/TokenTests$class.isAlpha:(Lscala/xml/parsing/TokenTests;C)Z
	ireturn
  Labels:
  LocalVariableTable: 
   Start  Length  Slot  Name   Signature
   0      6      0    this       Lscala/xml/pull/XMLEventReader$Parser;
   0      6      1    c       C


public final boolean isSpace(scala.collection.Seq);
  Signature: (Lscala/collection/Seq;)Z
  Code:
   Stack=2, Locals=2, Args_size=2
	aload_0
	aload_1
	invokestatic	Method scala/xml/parsing/TokenTests$class.isSpace:(Lscala/xml/parsing/TokenTests;Lscala/collection/Seq;)Z
	ireturn
  Labels:
  LocalVariableTable: 
   Start  Length  Slot  Name   Signature
   0      6      0    this       Lscala/xml/pull/XMLEventReader$Parser;
   0      6      1    cs       Lscala/collection/Seq;


public final boolean isSpace(char);
  Signature: (C)Z
  Code:
   Stack=2, Locals=2, Args_size=2
	aload_0
	iload_1
	invokestatic	Method scala/xml/parsing/TokenTests$class.isSpace:(Lscala/xml/parsing/TokenTests;C)Z
	ireturn
  Labels:
  LocalVariableTable: 
   Start  Length  Slot  Name   Signature
   0      6      0    this       Lscala/xml/pull/XMLEventReader$Parser;
   0      6      1    ch       C


public java.lang.Object xTakeUntil(scala.Function2, scala.Function0, java.lang.String);
  Signature: (Lscala/Function2;Lscala/Function0;Ljava/lang/String;)Ljava/lang/Object;
  Code:
   Stack=4, Locals=4, Args_size=4
	aload_0
	aload_1
	aload_2
	aload_3
	invokestatic	Method scala/xml/parsing/MarkupParserCommon$class.xTakeUntil:(Lscala/xml/parsing/MarkupParserCommon;Lscala/Function2;Lscala/Function0;Ljava/lang/String;)Ljava/lang/Object;
	areturn
  Labels:
  LocalVariableTable: 
   Start  Length  Slot  Name   Signature
   0      8      0    this       Lscala/xml/pull/XMLEventReader$Parser;
   0      8      1    handler       Lscala/Function2;
   0      8      2    positioner       Lscala/Function0;
   0      8      3    until       Ljava/lang/String;


public java.lang.Object saving(java.lang.Object, scala.Function1, scala.Function0);
  Signature: (Ljava/lang/Object;Lscala/Function1;Lscala/Function0;)Ljava/lang/Object;
  Code:
   Stack=4, Locals=4, Args_size=4
	aload_0
	aload_1
	aload_2
	aload_3
	invokestatic	Method scala/xml/parsing/MarkupParserCommon$class.saving:(Lscala/xml/parsing/MarkupParserCommon;Ljava/lang/Object;Lscala/Function1;Lscala/Function0;)Ljava/lang/Object;
	areturn
  Labels:
  LocalVariableTable: 
   Start  Length  Slot  Name   Signature
   0      8      0    this       Lscala/xml/pull/XMLEventReader$Parser;
   0      8      1    getter       Ljava/lang/Object;
   0      8      2    setter       Lscala/Function1;
   0      8      3    body       Lscala/Function0;


public java.lang.Object returning(java.lang.Object, scala.Function1);
  Signature: (Ljava/lang/Object;Lscala/Function1;)Ljava/lang/Object;
  Code:
   Stack=3, Locals=3, Args_size=3
	aload_0
	aload_1
	aload_2
	invokestatic	Method scala/xml/parsing/MarkupParserCommon$class.returning:(Lscala/xml/parsing/MarkupParserCommon;Ljava/lang/Object;Lscala/Function1;)Ljava/lang/Object;
	areturn
  Labels:
  LocalVariableTable: 
   Start  Length  Slot  Name   Signature
   0      7      0    this       Lscala/xml/pull/XMLEventReader$Parser;
   0      7      1    x       Ljava/lang/Object;
   0      7      2    f       Lscala/Function1;


public void xSpace();
  Signature: ()V
  Code:
   Stack=1, Locals=1, Args_size=1
	aload_0
	invokestatic	Method scala/xml/parsing/MarkupParserCommon$class.xSpace:(Lscala/xml/parsing/MarkupParserCommon;)V
	return
  Labels:

public void xSpaceOpt();
  Signature: ()V
  Code:
   Stack=1, Locals=1, Args_size=1
	aload_0
	invokestatic	Method scala/xml/parsing/MarkupParserCommon$class.xSpaceOpt:(Lscala/xml/parsing/MarkupParserCommon;)V
	return
  Labels:

public void xEQ();
  Signature: ()V
  Code:
   Stack=1, Locals=1, Args_size=1
	aload_0
	invokestatic	Method scala/xml/parsing/MarkupParserCommon$class.xEQ:(Lscala/xml/parsing/MarkupParserCommon;)V
	return
  Labels:

public void xToken(scala.collection.Seq);
  Signature: (Lscala/collection/Seq;)V
  Code:
   Stack=2, Locals=2, Args_size=2
	aload_0
	aload_1
	invokestatic	Method scala/xml/parsing/MarkupParserCommon$class.xToken:(Lscala/xml/parsing/MarkupParserCommon;Lscala/collection/Seq;)V
	return
  Labels:
  LocalVariableTable: 
   Start  Length  Slot  Name   Signature
   0      6      0    this       Lscala/xml/pull/XMLEventReader$Parser;
   0      6      1    that       Lscala/collection/Seq;


public void xToken(char);
  Signature: (C)V
  Code:
   Stack=2, Locals=2, Args_size=2
	aload_0
	iload_1
	invokestatic	Method scala/xml/parsing/MarkupParserCommon$class.xToken:(Lscala/xml/parsing/MarkupParserCommon;C)V
	return
  Labels:
  LocalVariableTable: 
   Start  Length  Slot  Name   Signature
   0      6      0    this       Lscala/xml/pull/XMLEventReader$Parser;
   0      6      1    that       C


public java.lang.Object errorAndResult(java.lang.String, java.lang.Object);
  Signature: (Ljava/lang/String;Ljava/lang/Object;)Ljava/lang/Object;
  Code:
   Stack=3, Locals=3, Args_size=3
	aload_0
	aload_1
	aload_2
	invokestatic	Method scala/xml/parsing/MarkupParserCommon$class.errorAndResult:(Lscala/xml/parsing/MarkupParserCommon;Ljava/lang/String;Ljava/lang/Object;)Ljava/lang/Object;
	areturn
  Labels:
  LocalVariableTable: 
   Start  Length  Slot  Name   Signature
   0      7      0    this       Lscala/xml/pull/XMLEventReader$Parser;
   0      7      1    msg       Ljava/lang/String;
   0      7      2    x       Ljava/lang/Object;


public java.lang.String xCharRef();
  Signature: ()Ljava/lang/String;
  Code:
   Stack=1, Locals=1, Args_size=1
	aload_0
	invokestatic	Method scala/xml/parsing/MarkupParserCommon$class.xCharRef:(Lscala/xml/parsing/MarkupParserCommon;)Ljava/lang/String;
	areturn
  Labels:

public java.lang.String xCharRef(scala.collection.Iterator);
  Signature: (Lscala/collection/Iterator;)Ljava/lang/String;
  Code:
   Stack=2, Locals=2, Args_size=2
	aload_0
	aload_1
	invokestatic	Method scala/xml/parsing/MarkupParserCommon$class.xCharRef:(Lscala/xml/parsing/MarkupParserCommon;Lscala/collection/Iterator;)Ljava/lang/String;
	areturn
  Labels:
  LocalVariableTable: 
   Start  Length  Slot  Name   Signature
   0      6      0    this       Lscala/xml/pull/XMLEventReader$Parser;
   0      6      1    it       Lscala/collection/Iterator;


public java.lang.String xCharRef(scala.Function0, scala.Function0);
  Signature: (Lscala/Function0;Lscala/Function0;)Ljava/lang/String;
  Code:
   Stack=3, Locals=3, Args_size=3
	aload_0
	aload_1
	aload_2
	invokestatic	Method scala/xml/parsing/MarkupParserCommon$class.xCharRef:(Lscala/xml/parsing/MarkupParserCommon;Lscala/Function0;Lscala/Function0;)Ljava/lang/String;
	areturn
  Labels:
  LocalVariableTable: 
   Start  Length  Slot  Name   Signature
   0      7      0    this       Lscala/xml/pull/XMLEventReader$Parser;
   0      7      1    ch       Lscala/Function0;
   0      7      2    nextch       Lscala/Function0;


public java.lang.String xName();
  Signature: ()Ljava/lang/String;
  Code:
   Stack=1, Locals=1, Args_size=1
	aload_0
	invokestatic	Method scala/xml/parsing/MarkupParserCommon$class.xName:(Lscala/xml/parsing/MarkupParserCommon;)Ljava/lang/String;
	areturn
  Labels:

public void xEndTag(java.lang.String);
  Signature: (Ljava/lang/String;)V
  Code:
   Stack=2, Locals=2, Args_size=2
	aload_0
	aload_1
	invokestatic	Method scala/xml/parsing/MarkupParserCommon$class.xEndTag:(Lscala/xml/parsing/MarkupParserCommon;Ljava/lang/String;)V
	return
  Labels:
  LocalVariableTable: 
   Start  Length  Slot  Name   Signature
   0      6      0    this       Lscala/xml/pull/XMLEventReader$Parser;
   0      6      1    startName       Ljava/lang/String;


public java.lang.String xAttributeValue();
  Signature: ()Ljava/lang/String;
  Code:
   Stack=1, Locals=1, Args_size=1
	aload_0
	invokestatic	Method scala/xml/parsing/MarkupParserCommon$class.xAttributeValue:(Lscala/xml/parsing/MarkupParserCommon;)Ljava/lang/String;
	areturn
  Labels:

public java.lang.String xAttributeValue(char);
  Signature: (C)Ljava/lang/String;
  Code:
   Stack=2, Locals=2, Args_size=2
	aload_0
	iload_1
	invokestatic	Method scala/xml/parsing/MarkupParserCommon$class.xAttributeValue:(Lscala/xml/parsing/MarkupParserCommon;C)Ljava/lang/String;
	areturn
  Labels:
  LocalVariableTable: 
   Start  Length  Slot  Name   Signature
   0      6      0    this       Lscala/xml/pull/XMLEventReader$Parser;
   0      6      1    endCh       C


public java.lang.Object xProcInstr();
  Signature: ()Ljava/lang/Object;
  Code:
   Stack=1, Locals=1, Args_size=1
	aload_0
	invokestatic	Method scala/xml/parsing/MarkupParserCommon$class.xProcInstr:(Lscala/xml/parsing/MarkupParserCommon;)Ljava/lang/Object;
	areturn
  Labels:

public scala.Tuple2 xTag(java.lang.Object);
  Signature: (Ljava/lang/Object;)Lscala/Tuple2;
  Code:
   Stack=2, Locals=2, Args_size=2
	aload_0
	aload_1
	invokestatic	Method scala/xml/parsing/MarkupParserCommon$class.xTag:(Lscala/xml/parsing/MarkupParserCommon;Ljava/lang/Object;)Lscala/Tuple2;
	areturn
  Labels:
  LocalVariableTable: 
   Start  Length  Slot  Name   Signature
   0      6      0    this       Lscala/xml/pull/XMLEventReader$Parser;
   0      6      1    pscope       Ljava/lang/Object;


public scala.runtime.Nothing$ unreachable();
  Signature: ()Lscala/runtime/Nothing$;
  Code:
   Stack=1, Locals=1, Args_size=1
	aload_0
	invokestatic	Method scala/xml/parsing/MarkupParserCommon$class.unreachable:(Lscala/xml/parsing/MarkupParserCommon;)Lscala/runtime/Nothing$;
	areturn
  Labels:

public void pop();
  Signature: ()V
  Code:
   Stack=1, Locals=1, Args_size=1
	aload_0
	invokestatic	Method scala/xml/parsing/MarkupParser$class.pop:(Lscala/xml/parsing/MarkupHandler;)V
	return
  Labels:

public void pushExternal(java.lang.String);
  Signature: (Ljava/lang/String;)V
  Code:
   Stack=2, Locals=2, Args_size=2
	aload_0
	aload_1
	invokestatic	Method scala/xml/parsing/MarkupParser$class.pushExternal:(Lscala/xml/parsing/MarkupHandler;Ljava/lang/String;)V
	return
  Labels:
  LocalVariableTable: 
   Start  Length  Slot  Name   Signature
   0      6      0    this       Lscala/xml/pull/XMLEventReader$Parser;
   0      6      1    systemId       Ljava/lang/String;


public void push(java.lang.String);
  Signature: (Ljava/lang/String;)V
  Code:
   Stack=2, Locals=2, Args_size=2
	aload_0
	aload_1
	invokestatic	Method scala/xml/parsing/MarkupParser$class.push:(Lscala/xml/parsing/MarkupHandler;Ljava/lang/String;)V
	return
  Labels:
  LocalVariableTable: 
   Start  Length  Slot  Name   Signature
   0      6      0    this       Lscala/xml/pull/XMLEventReader$Parser;
   0      6      1    entityName       Ljava/lang/String;


public void reportValidationError(int, java.lang.String);
  Signature: (ILjava/lang/String;)V
  Code:
   Stack=3, Locals=3, Args_size=3
	aload_0
	iload_1
	aload_2
	invokestatic	Method scala/xml/parsing/MarkupParser$class.reportValidationError:(Lscala/xml/parsing/MarkupHandler;ILjava/lang/String;)V
	return
  Labels:
  LocalVariableTable: 
   Start  Length  Slot  Name   Signature
   0      7      0    this       Lscala/xml/pull/XMLEventReader$Parser;
   0      7      1    pos       I
   0      7      2    str       Ljava/lang/String;


public void reportSyntaxError(java.lang.String);
  Signature: (Ljava/lang/String;)V
  Code:
   Stack=2, Locals=2, Args_size=2
	aload_0
	aload_1
	invokestatic	Method scala/xml/parsing/MarkupParser$class.reportSyntaxError:(Lscala/xml/parsing/MarkupHandler;Ljava/lang/String;)V
	return
  Labels:
  LocalVariableTable: 
   Start  Length  Slot  Name   Signature
   0      6      0    this       Lscala/xml/pull/XMLEventReader$Parser;
   0      6      1    str       Ljava/lang/String;


public void reportSyntaxError(int, java.lang.String);
  Signature: (ILjava/lang/String;)V
  Code:
   Stack=3, Locals=3, Args_size=3
	aload_0
	iload_1
	aload_2
	invokestatic	Method scala/xml/parsing/MarkupParser$class.reportSyntaxError:(Lscala/xml/parsing/MarkupHandler;ILjava/lang/String;)V
	return
  Labels:
  LocalVariableTable: 
   Start  Length  Slot  Name   Signature
   0      7      0    this       Lscala/xml/pull/XMLEventReader$Parser;
   0      7      1    pos       I
   0      7      2    str       Ljava/lang/String;


public void notationDecl();
  Signature: ()V
  Code:
   Stack=1, Locals=1, Args_size=1
	aload_0
	invokestatic	Method scala/xml/parsing/MarkupParser$class.notationDecl:(Lscala/xml/parsing/MarkupHandler;)V
	return
  Labels:

public void entityDecl();
  Signature: ()V
  Code:
   Stack=1, Locals=1, Args_size=1
	aload_0
	invokestatic	Method scala/xml/parsing/MarkupParser$class.entityDecl:(Lscala/xml/parsing/MarkupHandler;)V
	return
  Labels:

public void attrDecl();
  Signature: ()V
  Code:
   Stack=1, Locals=1, Args_size=1
	aload_0
	invokestatic	Method scala/xml/parsing/MarkupParser$class.attrDecl:(Lscala/xml/parsing/MarkupHandler;)V
	return
  Labels:

public void elementDecl();
  Signature: ()V
  Code:
   Stack=1, Locals=1, Args_size=1
	aload_0
	invokestatic	Method scala/xml/parsing/MarkupParser$class.elementDecl:(Lscala/xml/parsing/MarkupHandler;)V
	return
  Labels:

public void intSubset();
  Signature: ()V
  Code:
   Stack=1, Locals=1, Args_size=1
	aload_0
	invokestatic	Method scala/xml/parsing/MarkupParser$class.intSubset:(Lscala/xml/parsing/MarkupHandler;)V
	return
  Labels:

public void markupDecl();
  Signature: ()V
  Code:
   Stack=1, Locals=1, Args_size=1
	aload_0
	invokestatic	Method scala/xml/parsing/MarkupParser$class.markupDecl:(Lscala/xml/parsing/MarkupHandler;)V
	return
  Labels:

public java.lang.Object markupDecl1();
  Signature: ()Ljava/lang/Object;
  Code:
   Stack=1, Locals=1, Args_size=1
	aload_0
	invokestatic	Method scala/xml/parsing/MarkupParser$class.markupDecl1:(Lscala/xml/parsing/MarkupHandler;)Ljava/lang/Object;
	areturn
  Labels:

public void extSubset();
  Signature: ()V
  Code:
   Stack=1, Locals=1, Args_size=1
	aload_0
	invokestatic	Method scala/xml/parsing/MarkupParser$class.extSubset:(Lscala/xml/parsing/MarkupHandler;)V
	return
  Labels:

public java.lang.String pubidLiteral();
  Signature: ()Ljava/lang/String;
  Code:
   Stack=1, Locals=1, Args_size=1
	aload_0
	invokestatic	Method scala/xml/parsing/MarkupParser$class.pubidLiteral:(Lscala/xml/parsing/MarkupHandler;)Ljava/lang/String;
	areturn
  Labels:

public java.lang.String systemLiteral();
  Signature: ()Ljava/lang/String;
  Code:
   Stack=1, Locals=1, Args_size=1
	aload_0
	invokestatic	Method scala/xml/parsing/MarkupParser$class.systemLiteral:(Lscala/xml/parsing/MarkupHandler;)Ljava/lang/String;
	areturn
  Labels:

public java.lang.String xText();
  Signature: ()Ljava/lang/String;
  Code:
   Stack=1, Locals=1, Args_size=1
	aload_0
	invokestatic	Method scala/xml/parsing/MarkupParser$class.xText:(Lscala/xml/parsing/MarkupHandler;)Ljava/lang/String;
	areturn
  Labels:

public scala.xml.NodeSeq element1(scala.xml.NamespaceBinding);
  Signature: (Lscala/xml/NamespaceBinding;)Lscala/xml/NodeSeq;
  Code:
   Stack=2, Locals=2, Args_size=2
	aload_0
	aload_1
	invokestatic	Method scala/xml/parsing/MarkupParser$class.element1:(Lscala/xml/parsing/MarkupHandler;Lscala/xml/NamespaceBinding;)Lscala/xml/NodeSeq;
	areturn
  Labels:
  LocalVariableTable: 
   Start  Length  Slot  Name   Signature
   0      6      0    this       Lscala/xml/pull/XMLEventReader$Parser;
   0      6      1    pscope       Lscala/xml/NamespaceBinding;


public scala.xml.NodeSeq element(scala.xml.NamespaceBinding);
  Signature: (Lscala/xml/NamespaceBinding;)Lscala/xml/NodeSeq;
  Code:
   Stack=2, Locals=2, Args_size=2
	aload_0
	aload_1
	invokestatic	Method scala/xml/parsing/MarkupParser$class.element:(Lscala/xml/parsing/MarkupHandler;Lscala/xml/NamespaceBinding;)Lscala/xml/NodeSeq;
	areturn
  Labels:
  LocalVariableTable: 
   Start  Length  Slot  Name   Signature
   0      6      0    this       Lscala/xml/pull/XMLEventReader$Parser;
   0      6      1    pscope       Lscala/xml/NamespaceBinding;


public void parseDTD();
  Signature: ()V
  Code:
   Stack=1, Locals=1, Args_size=1
	aload_0
	invokestatic	Method scala/xml/parsing/MarkupParser$class.parseDTD:(Lscala/xml/parsing/MarkupHandler;)V
	return
  Labels:

public scala.xml.dtd.ExternalID externalID();
  Signature: ()Lscala/xml/dtd/ExternalID;
  Code:
   Stack=1, Locals=1, Args_size=1
	aload_0
	invokestatic	Method scala/xml/parsing/MarkupParser$class.externalID:(Lscala/xml/parsing/MarkupHandler;)Lscala/xml/dtd/ExternalID;
	areturn
  Labels:

public scala.xml.NodeSeq content(scala.xml.NamespaceBinding);
  Signature: (Lscala/xml/NamespaceBinding;)Lscala/xml/NodeSeq;
  Code:
   Stack=2, Locals=2, Args_size=2
	aload_0
	aload_1
	invokestatic	Method scala/xml/parsing/MarkupParser$class.content:(Lscala/xml/parsing/MarkupHandler;Lscala/xml/NamespaceBinding;)Lscala/xml/NodeSeq;
	areturn
  Labels:
  LocalVariableTable: 
   Start  Length  Slot  Name   Signature
   0      6      0    this       Lscala/xml/pull/XMLEventReader$Parser;
   0      6      1    pscope       Lscala/xml/NamespaceBinding;


public void content1(scala.xml.NamespaceBinding, scala.xml.NodeBuffer);
  Signature: (Lscala/xml/NamespaceBinding;Lscala/xml/NodeBuffer;)V
  Code:
   Stack=3, Locals=3, Args_size=3
	aload_0
	aload_1
	aload_2
	invokestatic	Method scala/xml/parsing/MarkupParser$class.content1:(Lscala/xml/parsing/MarkupHandler;Lscala/xml/NamespaceBinding;Lscala/xml/NodeBuffer;)V
	return
  Labels:
  LocalVariableTable: 
   Start  Length  Slot  Name   Signature
   0      7      0    this       Lscala/xml/pull/XMLEventReader$Parser;
   0      7      1    pscope       Lscala/xml/NamespaceBinding;
   0      7      2    ts       Lscala/xml/NodeBuffer;


public void appendText(int, scala.xml.NodeBuffer, java.lang.String);
  Signature: (ILscala/xml/NodeBuffer;Ljava/lang/String;)V
  Code:
   Stack=4, Locals=4, Args_size=4
	aload_0
	iload_1
	aload_2
	aload_3
	invokestatic	Method scala/xml/parsing/MarkupParser$class.appendText:(Lscala/xml/parsing/MarkupHandler;ILscala/xml/NodeBuffer;Ljava/lang/String;)V
	return
  Labels:
  LocalVariableTable: 
   Start  Length  Slot  Name   Signature
   0      8      0    this       Lscala/xml/pull/XMLEventReader$Parser;
   0      8      1    pos       I
   0      8      2    ts       Lscala/xml/NodeBuffer;
   0      8      3    txt       Ljava/lang/String;


public scala.xml.NodeSeq xComment();
  Signature: ()Lscala/xml/NodeSeq;
  Code:
   Stack=1, Locals=1, Args_size=1
	aload_0
	invokestatic	Method scala/xml/parsing/MarkupParser$class.xComment:(Lscala/xml/parsing/MarkupHandler;)Lscala/xml/NodeSeq;
	areturn
  Labels:

public scala.xml.NodeSeq xCharData();
  Signature: ()Lscala/xml/NodeSeq;
  Code:
   Stack=1, Locals=1, Args_size=1
	aload_0
	invokestatic	Method scala/xml/parsing/MarkupParser$class.xCharData:(Lscala/xml/parsing/MarkupHandler;)Lscala/xml/NodeSeq;
	areturn
  Labels:

public java.lang.String xEntityValue();
  Signature: ()Ljava/lang/String;
  Code:
   Stack=1, Locals=1, Args_size=1
	aload_0
	invokestatic	Method scala/xml/parsing/MarkupParser$class.xEntityValue:(Lscala/xml/parsing/MarkupHandler;)Ljava/lang/String;
	areturn
  Labels:

public scala.Tuple2 xAttributes(scala.xml.NamespaceBinding);
  Signature: (Lscala/xml/NamespaceBinding;)Lscala/Tuple2;
  Code:
   Stack=2, Locals=2, Args_size=2
	aload_0
	aload_1
	invokestatic	Method scala/xml/parsing/MarkupParser$class.xAttributes:(Lscala/xml/parsing/MarkupHandler;Lscala/xml/NamespaceBinding;)Lscala/Tuple2;
	areturn
  Labels:
  LocalVariableTable: 
   Start  Length  Slot  Name   Signature
   0      6      0    this       Lscala/xml/pull/XMLEventReader$Parser;
   0      6      1    pscope       Lscala/xml/NamespaceBinding;


public char nextch();
  Signature: ()C
  Code:
   Stack=1, Locals=1, Args_size=1
	aload_0
	invokestatic	Method scala/xml/parsing/MarkupParser$class.nextch:(Lscala/xml/parsing/MarkupHandler;)C
	ireturn
  Labels:

public scala.Tuple2 mkAttributes(java.lang.String, scala.xml.NamespaceBinding);
  Signature: (Ljava/lang/String;Lscala/xml/NamespaceBinding;)Lscala/Tuple2;
  Code:
   Stack=3, Locals=3, Args_size=3
	aload_0
	aload_1
	aload_2
	invokestatic	Method scala/xml/parsing/MarkupParser$class.mkAttributes:(Lscala/xml/parsing/MarkupHandler;Ljava/lang/String;Lscala/xml/NamespaceBinding;)Lscala/Tuple2;
	areturn
  Labels:
  LocalVariableTable: 
   Start  Length  Slot  Name   Signature
   0      7      0    this       Lscala/xml/pull/XMLEventReader$Parser;
   0      7      1    name       Ljava/lang/String;
   0      7      2    pscope       Lscala/xml/NamespaceBinding;


public scala.xml.NodeSeq mkProcInstr(int, java.lang.String, java.lang.String);
  Signature: (ILjava/lang/String;Ljava/lang/String;)Lscala/xml/NodeSeq;
  Code:
   Stack=4, Locals=4, Args_size=4
	aload_0
	iload_1
	aload_2
	aload_3
	invokestatic	Method scala/xml/parsing/MarkupParser$class.mkProcInstr:(Lscala/xml/parsing/MarkupHandler;ILjava/lang/String;Ljava/lang/String;)Lscala/xml/NodeSeq;
	areturn
  Labels:
  LocalVariableTable: 
   Start  Length  Slot  Name   Signature
   0      8      0    this       Lscala/xml/pull/XMLEventReader$Parser;
   0      8      1    position       I
   0      8      2    name       Ljava/lang/String;
   0      8      3    text       Ljava/lang/String;


public char ch_returning_nextch();
  Signature: ()C
  Code:
   Stack=1, Locals=1, Args_size=1
	aload_0
	invokestatic	Method scala/xml/parsing/MarkupParser$class.ch_returning_nextch:(Lscala/xml/parsing/MarkupHandler;)C
	ireturn
  Labels:

public scala.xml.parsing.MarkupHandler initialize();
  Signature: ()Lscala/xml/parsing/MarkupHandler;
  Code:
   Stack=1, Locals=1, Args_size=1
	aload_0
	invokestatic	Method scala/xml/parsing/MarkupParser$class.initialize:(Lscala/xml/parsing/MarkupHandler;)Lscala/xml/parsing/MarkupHandler;
	areturn
  Labels:

public scala.collection.mutable.StringBuilder putChar(char);
  Signature: (C)Lscala/collection/mutable/StringBuilder;
  Code:
   Stack=2, Locals=2, Args_size=2
	aload_0
	iload_1
	invokestatic	Method scala/xml/parsing/MarkupParser$class.putChar:(Lscala/xml/parsing/MarkupHandler;C)Lscala/collection/mutable/StringBuilder;
	areturn
  Labels:
  LocalVariableTable: 
   Start  Length  Slot  Name   Signature
   0      6      0    this       Lscala/xml/pull/XMLEventReader$Parser;
   0      6      1    c       C


public scala.xml.Document document();
  Signature: ()Lscala/xml/Document;
  Code:
   Stack=1, Locals=1, Args_size=1
	aload_0
	invokestatic	Method scala/xml/parsing/MarkupParser$class.document:(Lscala/xml/parsing/MarkupHandler;)Lscala/xml/Document;
	areturn
  Labels:

public scala.Tuple2 textDecl();
  Signature: ()Lscala/Tuple2;
  Code:
   Stack=1, Locals=1, Args_size=1
	aload_0
	invokestatic	Method scala/xml/parsing/MarkupParser$class.textDecl:(Lscala/xml/parsing/MarkupHandler;)Lscala/Tuple2;
	areturn
  Labels:

public scala.Tuple3 prolog();
  Signature: ()Lscala/Tuple3;
  Code:
   Stack=1, Locals=1, Args_size=1
	aload_0
	invokestatic	Method scala/xml/parsing/MarkupParser$class.prolog:(Lscala/xml/parsing/MarkupHandler;)Lscala/Tuple3;
	areturn
  Labels:

public scala.xml.MetaData xmlProcInstr();
  Signature: ()Lscala/xml/MetaData;
  Code:
   Stack=1, Locals=1, Args_size=1
	aload_0
	invokestatic	Method scala/xml/parsing/MarkupParser$class.xmlProcInstr:(Lscala/xml/parsing/MarkupHandler;)Lscala/xml/MetaData;
	areturn
  Labels:

public scala.collection.BufferedIterator lookahead();
  Signature: ()Lscala/collection/BufferedIterator;
  Code:
   Stack=1, Locals=1, Args_size=1
	aload_0
	invokestatic	Method scala/xml/parsing/MarkupParser$class.lookahead:(Lscala/xml/parsing/MarkupHandler;)Lscala/collection/BufferedIterator;
	areturn
  Labels:

public void xHandleError(char, java.lang.String);
  Signature: (CLjava/lang/String;)V
  Code:
   Stack=3, Locals=3, Args_size=3
	aload_0
	iload_1
	aload_2
	invokestatic	Method scala/xml/parsing/MarkupParser$class.xHandleError:(Lscala/xml/parsing/MarkupHandler;CLjava/lang/String;)V
	return
  Labels:
  LocalVariableTable: 
   Start  Length  Slot  Name   Signature
   0      7      0    this       Lscala/xml/pull/XMLEventReader$Parser;
   0      7      1    that       C
   0      7      2    msg       Ljava/lang/String;


public scala.runtime.Nothing$ errorNoEnd(java.lang.String);
  Signature: (Ljava/lang/String;)Lscala/runtime/Nothing$;
  Code:
   Stack=2, Locals=2, Args_size=2
	aload_0
	aload_1
	invokestatic	Method scala/xml/parsing/MarkupParser$class.errorNoEnd:(Lscala/xml/parsing/MarkupHandler;Ljava/lang/String;)Lscala/runtime/Nothing$;
	areturn
  Labels:
  LocalVariableTable: 
   Start  Length  Slot  Name   Signature
   0      6      0    this       Lscala/xml/pull/XMLEventReader$Parser;
   0      6      1    tag       Ljava/lang/String;


public scala.runtime.Nothing$ truncatedError(java.lang.String);
  Signature: (Ljava/lang/String;)Lscala/runtime/Nothing$;
  Code:
   Stack=2, Locals=2, Args_size=2
	aload_0
	aload_1
	invokestatic	Method scala/xml/parsing/MarkupParser$class.truncatedError:(Lscala/xml/parsing/MarkupHandler;Ljava/lang/String;)Lscala/runtime/Nothing$;
	areturn
  Labels:
  LocalVariableTable: 
   Start  Length  Slot  Name   Signature
   0      6      0    this       Lscala/xml/pull/XMLEventReader$Parser;
   0      6      1    msg       Ljava/lang/String;


public void scala$xml$parsing$MarkupParser$_setter_$cbuf_$eq(scala.collection.mutable.StringBuilder);
  Signature: (Lscala/collection/mutable/StringBuilder;)V
  Code:
   Stack=2, Locals=2, Args_size=2
	aload_0
	aload_1
	putfield	Field cbuf:Lscala/collection/mutable/StringBuilder;
	return
  Labels:

public void scala$xml$parsing$MarkupParser$_setter_$scala$xml$parsing$MarkupParser$$handle_$eq(scala.xml.parsing.MarkupHandler);
  Signature: (Lscala/xml/parsing/MarkupHandler;)V
  Code:
   Stack=2, Locals=2, Args_size=2
	aload_0
	aload_1
	putfield	Field scala$xml$parsing$MarkupParser$$handle:Lscala/xml/parsing/MarkupHandler;
	return
  Labels:

public void eof_$eq(boolean);
  Signature: (Z)V
  Code:
   Stack=2, Locals=2, Args_size=2
	aload_0
	iload_1
	putfield	Field eof:Z
	return
  Labels:

public boolean eof();
  Signature: ()Z
  Code:
   Stack=1, Locals=1, Args_size=1
	aload_0
	getfield	Field eof:Z
	ireturn
  Labels:

public void doc_$eq(scala.xml.Document);
  Signature: (Lscala/xml/Document;)V
  Code:
   Stack=2, Locals=2, Args_size=2
	aload_0
	aload_1
	putfield	Field doc:Lscala/xml/Document;
	return
  Labels:

public scala.xml.Document doc();
  Signature: ()Lscala/xml/Document;
  Code:
   Stack=1, Locals=1, Args_size=1
	aload_0
	getfield	Field doc:Lscala/xml/Document;
	areturn
  Labels:

public void dtd_$eq(scala.xml.dtd.DTD);
  Signature: (Lscala/xml/dtd/DTD;)V
  Code:
   Stack=2, Locals=2, Args_size=2
	aload_0
	aload_1
	putfield	Field dtd:Lscala/xml/dtd/DTD;
	return
  Labels:

public scala.xml.dtd.DTD dtd();
  Signature: ()Lscala/xml/dtd/DTD;
  Code:
   Stack=1, Locals=1, Args_size=1
	aload_0
	getfield	Field dtd:Lscala/xml/dtd/DTD;
	areturn
  Labels:

public scala.collection.mutable.StringBuilder cbuf();
  Signature: ()Lscala/collection/mutable/StringBuilder;
  Code:
   Stack=1, Locals=1, Args_size=1
	aload_0
	getfield	Field cbuf:Lscala/collection/mutable/StringBuilder;
	areturn
  Labels:

public void ch_$eq(char);
  Signature: (C)V
  Code:
   Stack=2, Locals=2, Args_size=2
	aload_0
	iload_1
	putfield	Field ch:C
	return
  Labels:

public char ch();
  Signature: ()C
  Code:
   Stack=1, Locals=1, Args_size=1
	aload_0
	getfield	Field ch:C
	ireturn
  Labels:

public void tmppos_$eq(int);
  Signature: (I)V
  Code:
   Stack=2, Locals=2, Args_size=2
	aload_0
	iload_1
	putfield	Field tmppos:I
	return
  Labels:

public int tmppos();
  Signature: ()I
  Code:
   Stack=1, Locals=1, Args_size=1
	aload_0
	getfield	Field tmppos:I
	ireturn
  Labels:

public void extIndex_$eq(int);
  Signature: (I)V
  Code:
   Stack=2, Locals=2, Args_size=2
	aload_0
	iload_1
	putfield	Field extIndex:I
	return
  Labels:

public int extIndex();
  Signature: ()I
  Code:
   Stack=1, Locals=1, Args_size=1
	aload_0
	getfield	Field extIndex:I
	ireturn
  Labels:

public void pos_$eq(int);
  Signature: (I)V
  Code:
   Stack=2, Locals=2, Args_size=2
	aload_0
	iload_1
	putfield	Field pos:I
	return
  Labels:

public int pos();
  Signature: ()I
  Code:
   Stack=1, Locals=1, Args_size=1
	aload_0
	getfield	Field pos:I
	ireturn
  Labels:

public void inpStack_$eq(scala.collection.immutable.List);
  Signature: (Lscala/collection/immutable/List;)V
  Code:
   Stack=2, Locals=2, Args_size=2
	aload_0
	aload_1
	putfield	Field inpStack:Lscala/collection/immutable/List;
	return
  Labels:

public scala.collection.immutable.List inpStack();
  Signature: ()Lscala/collection/immutable/List;
  Code:
   Stack=1, Locals=1, Args_size=1
	aload_0
	getfield	Field inpStack:Lscala/collection/immutable/List;
	areturn
  Labels:

public final scala.xml.parsing.MarkupHandler scala$xml$parsing$MarkupParser$$handle();
  Signature: ()Lscala/xml/parsing/MarkupHandler;
  Code:
   Stack=1, Locals=1, Args_size=1
	aload_0
	getfield	Field scala$xml$parsing$MarkupParser$$handle:Lscala/xml/parsing/MarkupHandler;
	areturn
  Labels:

public void curInput_$eq(scala.io.Source);
  Signature: (Lscala/io/Source;)V
  Code:
   Stack=2, Locals=2, Args_size=2
	aload_0
	aload_1
	putfield	Field curInput:Lscala/io/Source;
	return
  Labels:

public scala.io.Source curInput();
  Signature: ()Lscala/io/Source;
  Code:
   Stack=1, Locals=1, Args_size=1
	aload_0
	getfield	Field curInput:Lscala/io/Source;
	areturn
  Labels:

public scala.io.Source externalSource(java.lang.String);
  Signature: (Ljava/lang/String;)Lscala/io/Source;
  Code:
   Stack=2, Locals=2, Args_size=2
	aload_0
	aload_1
	invokestatic	Method scala/xml/parsing/ExternalSources$class.externalSource:(Lscala/xml/parsing/MarkupHandler;Ljava/lang/String;)Lscala/io/Source;
	areturn
  Labels:
  LocalVariableTable: 
   Start  Length  Slot  Name   Signature
   0      6      0    this       Lscala/xml/pull/XMLEventReader$Parser;
   0      6      1    systemId       Ljava/lang/String;


}

