Compiled from "XMLEventReader.scala"
public final class scala.xml.pull.XMLEventReader$Parser$$anonfun$setEvent$1 extends java.lang.Object implements scala.Function1,scala.ScalaObject,java.io.Serializable
  SourceFile: "XMLEventReader.scala"
  Scala: length = 0x
   
  InnerClass: 
   public Parser=class scala/xml/pull/XMLEventReader$Parser of class scala/xml/pull/XMLEventReader
   public final $anonfun$setEvent$1=class scala/xml/pull/XMLEventReader$Parser$$anonfun$setEvent$1 of class scala/xml/pull/XMLEventReader$Parser
  minor version: 0
  major version: 49
  Constant pool:
Asciz	SourceFile;
Asciz	XMLEventReader.scala;
Asciz	<clinit>;
Asciz	()V;
Asciz	Code;
Asciz	serialVersionUID;
Asciz	J;
Asciz	scala/xml/pull/XMLEventReader$Parser$$anonfun$setEvent$1;
class	scala/xml/pull/XMLEventReader$Parser$$anonfun$setEvent$1
NameAndType	serialVersionUID:J
Field	scala/xml/pull/XMLEventReader$Parser$$anonfun$setEvent$1.serialVersionUID:J
Asciz	$outer;
Asciz	Lscala/xml/pull/XMLEventReader$Parser;;
Asciz	<init>;
Asciz	(Lscala/xml/pull/XMLEventReader$Parser;)V;
Asciz	LineNumberTable;
Asciz	java/lang/NullPointerException;
class	java/lang/NullPointerException
NameAndType	"<init>":()V
Method	java/lang/NullPointerException."<init>":()V
NameAndType	$outer:Lscala/xml/pull/XMLEventReader$Parser;
Field	scala/xml/pull/XMLEventReader$Parser$$anonfun$setEvent$1.$outer:Lscala/xml/pull/XMLEventReader$Parser;
Asciz	java/lang/Object;
class	java/lang/Object
Method	java/lang/Object."<init>":()V
Asciz	scala/Function1$class;
class	scala/Function1$class
Asciz	$init$;
Asciz	(Lscala/Function1;)V;
NameAndType	$init$:(Lscala/Function1;)V
Method	scala/Function1$class.$init$:(Lscala/Function1;)V
Asciz	this;
Asciz	Lscala/xml/pull/XMLEventReader$Parser$$anonfun$setEvent$1;;
Asciz	LocalVariableTable;
Asciz	apply;
Asciz	(Ljava/lang/Object;)Ljava/lang/Object;;
Asciz	scala/xml/pull/XMLEvent;
class	scala/xml/pull/XMLEvent
Asciz	(Lscala/xml/pull/XMLEvent;)V;
NameAndType	apply:(Lscala/xml/pull/XMLEvent;)V
Method	scala/xml/pull/XMLEventReader$Parser$$anonfun$setEvent$1.apply:(Lscala/xml/pull/XMLEvent;)V
Asciz	scala/runtime/BoxedUnit;
class	scala/runtime/BoxedUnit
Asciz	UNIT;
Asciz	Lscala/runtime/BoxedUnit;;
NameAndType	UNIT:Lscala/runtime/BoxedUnit;
Field	scala/runtime/BoxedUnit.UNIT:Lscala/runtime/BoxedUnit;
Asciz	v1;
Asciz	Ljava/lang/Object;;
Asciz	scala/xml/pull/XMLEventReader$Parser;
class	scala/xml/pull/XMLEventReader$Parser
Asciz	scala$xml$pull$XMLEventReader$Parser$$$outer;
Asciz	()Lscala/xml/pull/XMLEventReader;;
NameAndType	scala$xml$pull$XMLEventReader$Parser$$$outer:()Lscala/xml/pull/XMLEventReader;
Method	scala/xml/pull/XMLEventReader$Parser.scala$xml$pull$XMLEventReader$Parser$$$outer:()Lscala/xml/pull/XMLEventReader;
Asciz	scala/xml/pull/ProducerConsumerIterator;
class	scala/xml/pull/ProducerConsumerIterator
Asciz	produce;
Asciz	(Ljava/lang/Object;)V;
NameAndType	produce:(Ljava/lang/Object;)V
InterfaceMethod	scala/xml/pull/ProducerConsumerIterator.produce:(Ljava/lang/Object;)V
Asciz	andThen;
Asciz	(Lscala/Function1;)Lscala/Function1;;
Asciz	(Lscala/Function1;Lscala/Function1;)Lscala/Function1;;
NameAndType	andThen:(Lscala/Function1;Lscala/Function1;)Lscala/Function1;
Method	scala/Function1$class.andThen:(Lscala/Function1;Lscala/Function1;)Lscala/Function1;
Asciz	g;
Asciz	Lscala/Function1;;
Asciz	compose;
NameAndType	compose:(Lscala/Function1;Lscala/Function1;)Lscala/Function1;
Method	scala/Function1$class.compose:(Lscala/Function1;Lscala/Function1;)Lscala/Function1;
Asciz	toString;
Asciz	()Ljava/lang/String;;
Asciz	(Lscala/Function1;)Ljava/lang/String;;
NameAndType	toString:(Lscala/Function1;)Ljava/lang/String;
Method	scala/Function1$class.toString:(Lscala/Function1;)Ljava/lang/String;
Asciz	Scala;
Asciz	InnerClasses;
Asciz	scala/xml/pull/XMLEventReader;
class	scala/xml/pull/XMLEventReader
Asciz	Parser;
Asciz	$anonfun$setEvent$1;
Asciz	scala/Function1;
class	scala/Function1
Asciz	scala/ScalaObject;
class	scala/ScalaObject
Asciz	java/io/Serializable;
class	java/io/Serializable

{
public static final long serialVersionUID;
  Signature: J

private final scala.xml.pull.XMLEventReader$Parser $outer;
  Signature: Lscala/xml/pull/XMLEventReader$Parser;

public static {};
  Signature: ()V
  Code:
   Stack=2, Locals=0, Args_size=0
	lconst_0
	putstatic	Field serialVersionUID:J
	return
  Labels:

public scala.xml.pull.XMLEventReader$Parser$$anonfun$setEvent$1(scala.xml.pull.XMLEventReader$Parser);
  Signature: (Lscala/xml/pull/XMLEventReader$Parser;)V
  Code:
   Stack=2, Locals=2, Args_size=2
	aload_1
	ifnonnull	l1 // aload_0
	new	class java/lang/NullPointerException
	dup
	invokespecial	Method java/lang/NullPointerException."<init>":()V
	athrow
l1	aload_0
	aload_1
	putfield	Field $outer:Lscala/xml/pull/XMLEventReader$Parser;
	aload_0
	invokespecial	Method java/lang/Object."<init>":()V
	aload_0
	invokestatic	Method scala/Function1$class.$init$:(Lscala/Function1;)V
	return
  Labels:
   	l1 = 12 // aload_0
  LocalVariableTable: 
   Start  Length  Slot  Name   Signature
   0      26      0    this       Lscala/xml/pull/XMLEventReader$Parser$$anonfun$setEvent$1;
   0      26      1    $outer       Lscala/xml/pull/XMLEventReader$Parser;


public final java.lang.Object apply(java.lang.Object);
  Signature: (Ljava/lang/Object;)Ljava/lang/Object;
  Code:
   Stack=2, Locals=3, Args_size=2
	aload_0
	getfield	Field $outer:Lscala/xml/pull/XMLEventReader$Parser;
	astore_2
	aload_0
	aload_1
	checkcast	class scala/xml/pull/XMLEvent
	invokevirtual	Method apply:(Lscala/xml/pull/XMLEvent;)V
	getstatic	Field scala/runtime/BoxedUnit.UNIT:Lscala/runtime/BoxedUnit;
	areturn
  Labels:
  LocalVariableTable: 
   Start  Length  Slot  Name   Signature
   0      17      0    this       Lscala/xml/pull/XMLEventReader$Parser$$anonfun$setEvent$1;
   5      12      1    v1       Ljava/lang/Object;


public final void apply(scala.xml.pull.XMLEvent);
  Signature: (Lscala/xml/pull/XMLEvent;)V
  Code:
   Stack=2, Locals=3, Args_size=2
	aload_0
	getfield	Field $outer:Lscala/xml/pull/XMLEventReader$Parser;
	astore_2
	aload_0
	getfield	Field $outer:Lscala/xml/pull/XMLEventReader$Parser;
	invokevirtual	Method scala/xml/pull/XMLEventReader$Parser.scala$xml$pull$XMLEventReader$Parser$$$outer:()Lscala/xml/pull/XMLEventReader;
	aload_1
	invokeinterface	InterfaceMethod scala/xml/pull/ProducerConsumerIterator.produce:(Ljava/lang/Object;)V
	return
  Labels:
  LocalVariableTable: 
   Start  Length  Slot  Name   Signature
   0      19      0    this       Lscala/xml/pull/XMLEventReader$Parser$$anonfun$setEvent$1;


public scala.Function1 andThen(scala.Function1);
  Signature: (Lscala/Function1;)Lscala/Function1;
  Code:
   Stack=2, Locals=2, Args_size=2
	aload_0
	aload_1
	invokestatic	Method scala/Function1$class.andThen:(Lscala/Function1;Lscala/Function1;)Lscala/Function1;
	areturn
  Labels:
  LocalVariableTable: 
   Start  Length  Slot  Name   Signature
   0      6      0    this       Lscala/xml/pull/XMLEventReader$Parser$$anonfun$setEvent$1;
   0      6      1    g       Lscala/Function1;


public scala.Function1 compose(scala.Function1);
  Signature: (Lscala/Function1;)Lscala/Function1;
  Code:
   Stack=2, Locals=2, Args_size=2
	aload_0
	aload_1
	invokestatic	Method scala/Function1$class.compose:(Lscala/Function1;Lscala/Function1;)Lscala/Function1;
	areturn
  Labels:
  LocalVariableTable: 
   Start  Length  Slot  Name   Signature
   0      6      0    this       Lscala/xml/pull/XMLEventReader$Parser$$anonfun$setEvent$1;
   0      6      1    g       Lscala/Function1;


public java.lang.String toString();
  Signature: ()Ljava/lang/String;
  Code:
   Stack=1, Locals=1, Args_size=1
	aload_0
	invokestatic	Method scala/Function1$class.toString:(Lscala/Function1;)Ljava/lang/String;
	areturn
  Labels:

}

