Compiled from "XMLEventReader.scala"
public final class scala.xml.pull.XMLEventReader$Parser$$anonfun$run$1 extends java.lang.Object implements scala.Function0,scala.ScalaObject,java.io.Serializable
  SourceFile: "XMLEventReader.scala"
  Scala: length = 0x
   
  InnerClass: 
   public Parser=class scala/xml/pull/XMLEventReader$Parser of class scala/xml/pull/XMLEventReader
   public final $anonfun$run$1=class scala/xml/pull/XMLEventReader$Parser$$anonfun$run$1 of class scala/xml/pull/XMLEventReader$Parser
  minor version: 0
  major version: 49
  Constant pool:
Asciz	SourceFile;
Asciz	XMLEventReader.scala;
Asciz	<clinit>;
Asciz	()V;
Asciz	Code;
Asciz	serialVersionUID;
Asciz	J;
Asciz	scala/xml/pull/XMLEventReader$Parser$$anonfun$run$1;
class	scala/xml/pull/XMLEventReader$Parser$$anonfun$run$1
NameAndType	serialVersionUID:J
Field	scala/xml/pull/XMLEventReader$Parser$$anonfun$run$1.serialVersionUID:J
Asciz	$outer;
Asciz	Lscala/xml/pull/XMLEventReader$Parser;;
Asciz	<init>;
Asciz	(Lscala/xml/pull/XMLEventReader$Parser;)V;
Asciz	LineNumberTable;
Asciz	java/lang/NullPointerException;
class	java/lang/NullPointerException
NameAndType	"<init>":()V
Method	java/lang/NullPointerException."<init>":()V
NameAndType	$outer:Lscala/xml/pull/XMLEventReader$Parser;
Field	scala/xml/pull/XMLEventReader$Parser$$anonfun$run$1.$outer:Lscala/xml/pull/XMLEventReader$Parser;
Asciz	java/lang/Object;
class	java/lang/Object
Method	java/lang/Object."<init>":()V
Asciz	scala/Function0$class;
class	scala/Function0$class
Asciz	$init$;
Asciz	(Lscala/Function0;)V;
NameAndType	$init$:(Lscala/Function0;)V
Method	scala/Function0$class.$init$:(Lscala/Function0;)V
Asciz	this;
Asciz	Lscala/xml/pull/XMLEventReader$Parser$$anonfun$run$1;;
Asciz	LocalVariableTable;
Asciz	apply;
Asciz	()Ljava/lang/Object;;
Asciz	()Lscala/xml/Document;;
NameAndType	apply:()Lscala/xml/Document;
Method	scala/xml/pull/XMLEventReader$Parser$$anonfun$run$1.apply:()Lscala/xml/Document;
Asciz	scala/xml/parsing/MarkupParser;
class	scala/xml/parsing/MarkupParser
Asciz	initialize;
Asciz	()Lscala/xml/parsing/MarkupParser;;
NameAndType	initialize:()Lscala/xml/parsing/MarkupParser;
InterfaceMethod	scala/xml/parsing/MarkupParser.initialize:()Lscala/xml/parsing/MarkupParser;
Asciz	document;
NameAndType	document:()Lscala/xml/Document;
InterfaceMethod	scala/xml/parsing/MarkupParser.document:()Lscala/xml/Document;
Asciz	toString;
Asciz	()Ljava/lang/String;;
Asciz	(Lscala/Function0;)Ljava/lang/String;;
NameAndType	toString:(Lscala/Function0;)Ljava/lang/String;
Method	scala/Function0$class.toString:(Lscala/Function0;)Ljava/lang/String;
Asciz	Scala;
Asciz	InnerClasses;
Asciz	scala/xml/pull/XMLEventReader$Parser;
class	scala/xml/pull/XMLEventReader$Parser
Asciz	scala/xml/pull/XMLEventReader;
class	scala/xml/pull/XMLEventReader
Asciz	Parser;
Asciz	$anonfun$run$1;
Asciz	scala/Function0;
class	scala/Function0
Asciz	scala/ScalaObject;
class	scala/ScalaObject
Asciz	java/io/Serializable;
class	java/io/Serializable

{
public static final long serialVersionUID;
  Signature: J

private final scala.xml.pull.XMLEventReader$Parser $outer;
  Signature: Lscala/xml/pull/XMLEventReader$Parser;

public static {};
  Signature: ()V
  Code:
   Stack=2, Locals=0, Args_size=0
	lconst_0
	putstatic	Field serialVersionUID:J
	return
  Labels:

public scala.xml.pull.XMLEventReader$Parser$$anonfun$run$1(scala.xml.pull.XMLEventReader$Parser);
  Signature: (Lscala/xml/pull/XMLEventReader$Parser;)V
  Code:
   Stack=2, Locals=2, Args_size=2
	aload_1
	ifnonnull	l1 // aload_0
	new	class java/lang/NullPointerException
	dup
	invokespecial	Method java/lang/NullPointerException."<init>":()V
	athrow
l1	aload_0
	aload_1
	putfield	Field $outer:Lscala/xml/pull/XMLEventReader$Parser;
	aload_0
	invokespecial	Method java/lang/Object."<init>":()V
	aload_0
	invokestatic	Method scala/Function0$class.$init$:(Lscala/Function0;)V
	return
  Labels:
   	l1 = 12 // aload_0
  LocalVariableTable: 
   Start  Length  Slot  Name   Signature
   0      26      0    this       Lscala/xml/pull/XMLEventReader$Parser$$anonfun$run$1;
   0      26      1    $outer       Lscala/xml/pull/XMLEventReader$Parser;


public final java.lang.Object apply();
  Signature: ()Ljava/lang/Object;
  Code:
   Stack=1, Locals=2, Args_size=1
	aload_0
	getfield	Field $outer:Lscala/xml/pull/XMLEventReader$Parser;
	astore_1
	aload_0
	invokevirtual	Method apply:()Lscala/xml/Document;
	areturn
  Labels:
  LocalVariableTable: 
   Start  Length  Slot  Name   Signature
   0      10      0    this       Lscala/xml/pull/XMLEventReader$Parser$$anonfun$run$1;


public final scala.xml.Document apply();
  Signature: ()Lscala/xml/Document;
  Code:
   Stack=1, Locals=2, Args_size=1
	aload_0
	getfield	Field $outer:Lscala/xml/pull/XMLEventReader$Parser;
	astore_1
	aload_0
	getfield	Field $outer:Lscala/xml/pull/XMLEventReader$Parser;
	invokeinterface	InterfaceMethod scala/xml/parsing/MarkupParser.initialize:()Lscala/xml/parsing/MarkupParser;
	invokeinterface	InterfaceMethod scala/xml/parsing/MarkupParser.document:()Lscala/xml/Document;
	areturn
  Labels:
  LocalVariableTable: 
   Start  Length  Slot  Name   Signature
   0      20      0    this       Lscala/xml/pull/XMLEventReader$Parser$$anonfun$run$1;


public java.lang.String toString();
  Signature: ()Ljava/lang/String;
  Code:
   Stack=1, Locals=1, Args_size=1
	aload_0
	invokestatic	Method scala/Function0$class.toString:(Lscala/Function0;)Ljava/lang/String;
	areturn
  Labels:

}

