Compiled from "XMLEventReader.scala"
public class scala.xml.pull.XMLEventReader extends java.lang.Object implements scala.xml.pull.ProducerConsumerIterator,scala.ScalaObject
  SourceFile: "XMLEventReader.scala"
  ScalaSig: length = 0x3
   05 00 00 
  Signature: length = 0x2
   01 FFFFFFF7 
  RuntimeVisibleAnnotations: length = 0xB
   00 01 01 FFFFFFF8 00 01 01 FFFFFFF9 73 01 FFFFFFFA 
  InnerClass: 
   public Parser=class scala/xml/pull/XMLEventReader$Parser of class scala/xml/pull/XMLEventReader
   public abstract $less$colon$less=class scala/Predef$$less$colon$less of class scala/Predef
   public GroupedIterator=class scala/collection/Iterator$GroupedIterator of class scala/collection/Iterator
  minor version: 0
  major version: 49
  Constant pool:
Asciz	SourceFile;
Asciz	XMLEventReader.scala;
Asciz	preserveWS;
Asciz	Z;
Asciz	MaxQueueSize;
Asciz	I;
Asciz	EndOfStream;
Asciz	Lscala/xml/pull/XMLEventReader$POISON$;;
Asciz	parser;
Asciz	Lscala/xml/pull/XMLEventReader$Parser;;
Asciz	parserThread;
Asciz	Ljava/lang/Thread;;
Asciz	POISON$module;
Asciz	scala$xml$pull$ProducerConsumerIterator$$queue;
Asciz	Ljava/util/concurrent/LinkedBlockingQueue;;
Asciz	scala$xml$pull$ProducerConsumerIterator$$buffer;
Asciz	Ljava/lang/Object;;
Asciz	bitmap$0;
Asciz	()Ljava/util/concurrent/LinkedBlockingQueue;;
Asciz	Code;
Asciz	LineNumberTable;
Asciz	scala/xml/pull/XMLEventReader;
class	scala/xml/pull/XMLEventReader
NameAndType	bitmap$0:I
Field	scala/xml/pull/XMLEventReader.bitmap$0:I
Asciz	scala/xml/pull/ProducerConsumerIterator$class;
class	scala/xml/pull/ProducerConsumerIterator$class
Asciz	(Lscala/xml/pull/ProducerConsumerIterator;)Ljava/util/concurrent/LinkedBlockingQueue;;
NameAndType	scala$xml$pull$ProducerConsumerIterator$$queue:(Lscala/xml/pull/ProducerConsumerIterator;)Ljava/util/concurrent/LinkedBlockingQueue;
Method	scala/xml/pull/ProducerConsumerIterator$class.scala$xml$pull$ProducerConsumerIterator$$queue:(Lscala/xml/pull/ProducerConsumerIterator;)Ljava/util/concurrent/LinkedBlockingQueue;
NameAndType	scala$xml$pull$ProducerConsumerIterator$$queue:Ljava/util/concurrent/LinkedBlockingQueue;
Field	scala/xml/pull/XMLEventReader.scala$xml$pull$ProducerConsumerIterator$$queue:Ljava/util/concurrent/LinkedBlockingQueue;
Asciz	scala$xml$pull$ProducerConsumerIterator$_setter_$MaxQueueSize_$eq;
Asciz	(I)V;
Asciz	()Ljava/lang/Object;;
NameAndType	scala$xml$pull$ProducerConsumerIterator$$buffer:Ljava/lang/Object;
Field	scala/xml/pull/XMLEventReader.scala$xml$pull$ProducerConsumerIterator$$buffer:Ljava/lang/Object;
Asciz	scala$xml$pull$ProducerConsumerIterator$$buffer_$eq;
Asciz	(Ljava/lang/Object;)V;
Asciz	interruptibly;
Asciz	(Lscala/Function0;)Lscala/Option;;
Asciz	(Lscala/xml/pull/ProducerConsumerIterator;Lscala/Function0;)Lscala/Option;;
NameAndType	interruptibly:(Lscala/xml/pull/ProducerConsumerIterator;Lscala/Function0;)Lscala/Option;
Method	scala/xml/pull/ProducerConsumerIterator$class.interruptibly:(Lscala/xml/pull/ProducerConsumerIterator;Lscala/Function0;)Lscala/Option;
Asciz	this;
Asciz	Lscala/xml/pull/XMLEventReader;;
Asciz	body;
Asciz	Lscala/Function0;;
Asciz	LocalVariableTable;
Asciz	produce;
Asciz	(Lscala/xml/pull/ProducerConsumerIterator;Ljava/lang/Object;)V;
NameAndType	produce:(Lscala/xml/pull/ProducerConsumerIterator;Ljava/lang/Object;)V
Method	scala/xml/pull/ProducerConsumerIterator$class.produce:(Lscala/xml/pull/ProducerConsumerIterator;Ljava/lang/Object;)V
Asciz	x;
Asciz	hasNext;
Asciz	()Z;
Asciz	(Lscala/xml/pull/ProducerConsumerIterator;)Z;
NameAndType	hasNext:(Lscala/xml/pull/ProducerConsumerIterator;)Z
Method	scala/xml/pull/ProducerConsumerIterator$class.hasNext:(Lscala/xml/pull/ProducerConsumerIterator;)Z
Asciz	next;
Asciz	(Lscala/xml/pull/ProducerConsumerIterator;)Ljava/lang/Object;;
NameAndType	next:(Lscala/xml/pull/ProducerConsumerIterator;)Ljava/lang/Object;
Method	scala/xml/pull/ProducerConsumerIterator$class.next:(Lscala/xml/pull/ProducerConsumerIterator;)Ljava/lang/Object;
Asciz	available;
NameAndType	available:(Lscala/xml/pull/ProducerConsumerIterator;)Z
Method	scala/xml/pull/ProducerConsumerIterator$class.available:(Lscala/xml/pull/ProducerConsumerIterator;)Z
Asciz	isEmpty;
Asciz	scala/collection/Iterator$class;
class	scala/collection/Iterator$class
Asciz	(Lscala/collection/Iterator;)Z;
NameAndType	isEmpty:(Lscala/collection/Iterator;)Z
Method	scala/collection/Iterator$class.isEmpty:(Lscala/collection/Iterator;)Z
Asciz	isTraversableAgain;
NameAndType	isTraversableAgain:(Lscala/collection/Iterator;)Z
Method	scala/collection/Iterator$class.isTraversableAgain:(Lscala/collection/Iterator;)Z
Asciz	hasDefiniteSize;
NameAndType	hasDefiniteSize:(Lscala/collection/Iterator;)Z
Method	scala/collection/Iterator$class.hasDefiniteSize:(Lscala/collection/Iterator;)Z
Asciz	take;
Asciz	(I)Lscala/collection/Iterator;;
Asciz	(Lscala/collection/Iterator;I)Lscala/collection/Iterator;;
NameAndType	take:(Lscala/collection/Iterator;I)Lscala/collection/Iterator;
Method	scala/collection/Iterator$class.take:(Lscala/collection/Iterator;I)Lscala/collection/Iterator;
Asciz	n;
Asciz	drop;
NameAndType	drop:(Lscala/collection/Iterator;I)Lscala/collection/Iterator;
Method	scala/collection/Iterator$class.drop:(Lscala/collection/Iterator;I)Lscala/collection/Iterator;
Asciz	slice;
Asciz	(II)Lscala/collection/Iterator;;
Asciz	(Lscala/collection/Iterator;II)Lscala/collection/Iterator;;
NameAndType	slice:(Lscala/collection/Iterator;II)Lscala/collection/Iterator;
Method	scala/collection/Iterator$class.slice:(Lscala/collection/Iterator;II)Lscala/collection/Iterator;
Asciz	from;
Asciz	until;
Asciz	map;
Asciz	(Lscala/Function1;)Lscala/collection/Iterator;;
Asciz	(Lscala/collection/Iterator;Lscala/Function1;)Lscala/collection/Iterator;;
NameAndType	map:(Lscala/collection/Iterator;Lscala/Function1;)Lscala/collection/Iterator;
Method	scala/collection/Iterator$class.map:(Lscala/collection/Iterator;Lscala/Function1;)Lscala/collection/Iterator;
Asciz	f;
Asciz	Lscala/Function1;;
Asciz	$plus$plus;
Asciz	(Lscala/Function0;)Lscala/collection/Iterator;;
Asciz	(Lscala/collection/Iterator;Lscala/Function0;)Lscala/collection/Iterator;;
NameAndType	$plus$plus:(Lscala/collection/Iterator;Lscala/Function0;)Lscala/collection/Iterator;
Method	scala/collection/Iterator$class.$plus$plus:(Lscala/collection/Iterator;Lscala/Function0;)Lscala/collection/Iterator;
Asciz	that;
Asciz	flatMap;
NameAndType	flatMap:(Lscala/collection/Iterator;Lscala/Function1;)Lscala/collection/Iterator;
Method	scala/collection/Iterator$class.flatMap:(Lscala/collection/Iterator;Lscala/Function1;)Lscala/collection/Iterator;
Asciz	filter;
NameAndType	filter:(Lscala/collection/Iterator;Lscala/Function1;)Lscala/collection/Iterator;
Method	scala/collection/Iterator$class.filter:(Lscala/collection/Iterator;Lscala/Function1;)Lscala/collection/Iterator;
Asciz	p;
Asciz	withFilter;
NameAndType	withFilter:(Lscala/collection/Iterator;Lscala/Function1;)Lscala/collection/Iterator;
Method	scala/collection/Iterator$class.withFilter:(Lscala/collection/Iterator;Lscala/Function1;)Lscala/collection/Iterator;
Asciz	filterNot;
NameAndType	filterNot:(Lscala/collection/Iterator;Lscala/Function1;)Lscala/collection/Iterator;
Method	scala/collection/Iterator$class.filterNot:(Lscala/collection/Iterator;Lscala/Function1;)Lscala/collection/Iterator;
Asciz	collect;
Asciz	(Lscala/PartialFunction;)Lscala/collection/Iterator;;
Asciz	(Lscala/collection/Iterator;Lscala/PartialFunction;)Lscala/collection/Iterator;;
NameAndType	collect:(Lscala/collection/Iterator;Lscala/PartialFunction;)Lscala/collection/Iterator;
Method	scala/collection/Iterator$class.collect:(Lscala/collection/Iterator;Lscala/PartialFunction;)Lscala/collection/Iterator;
Asciz	pf;
Asciz	Lscala/PartialFunction;;
Asciz	takeWhile;
NameAndType	takeWhile:(Lscala/collection/Iterator;Lscala/Function1;)Lscala/collection/Iterator;
Method	scala/collection/Iterator$class.takeWhile:(Lscala/collection/Iterator;Lscala/Function1;)Lscala/collection/Iterator;
Asciz	partition;
Asciz	(Lscala/Function1;)Lscala/Tuple2;;
Asciz	(Lscala/collection/Iterator;Lscala/Function1;)Lscala/Tuple2;;
NameAndType	partition:(Lscala/collection/Iterator;Lscala/Function1;)Lscala/Tuple2;
Method	scala/collection/Iterator$class.partition:(Lscala/collection/Iterator;Lscala/Function1;)Lscala/Tuple2;
Asciz	dropWhile;
NameAndType	dropWhile:(Lscala/collection/Iterator;Lscala/Function1;)Lscala/collection/Iterator;
Method	scala/collection/Iterator$class.dropWhile:(Lscala/collection/Iterator;Lscala/Function1;)Lscala/collection/Iterator;
Asciz	zip;
Asciz	(Lscala/collection/Iterator;)Lscala/collection/Iterator;;
Asciz	(Lscala/collection/Iterator;Lscala/collection/Iterator;)Lscala/collection/Iterator;;
NameAndType	zip:(Lscala/collection/Iterator;Lscala/collection/Iterator;)Lscala/collection/Iterator;
Method	scala/collection/Iterator$class.zip:(Lscala/collection/Iterator;Lscala/collection/Iterator;)Lscala/collection/Iterator;
Asciz	Lscala/collection/Iterator;;
Asciz	padTo;
Asciz	(ILjava/lang/Object;)Lscala/collection/Iterator;;
Asciz	(Lscala/collection/Iterator;ILjava/lang/Object;)Lscala/collection/Iterator;;
NameAndType	padTo:(Lscala/collection/Iterator;ILjava/lang/Object;)Lscala/collection/Iterator;
Method	scala/collection/Iterator$class.padTo:(Lscala/collection/Iterator;ILjava/lang/Object;)Lscala/collection/Iterator;
Asciz	len;
Asciz	elem;
Asciz	zipWithIndex;
Asciz	()Lscala/collection/Iterator;;
NameAndType	zipWithIndex:(Lscala/collection/Iterator;)Lscala/collection/Iterator;
Method	scala/collection/Iterator$class.zipWithIndex:(Lscala/collection/Iterator;)Lscala/collection/Iterator;
Asciz	zipAll;
Asciz	(Lscala/collection/Iterator;Ljava/lang/Object;Ljava/lang/Object;)Lscala/collection/Iterator;;
Asciz	(Lscala/collection/Iterator;Lscala/collection/Iterator;Ljava/lang/Object;Ljava/lang/Object;)Lscala/collection/Iterator;;
NameAndType	zipAll:(Lscala/collection/Iterator;Lscala/collection/Iterator;Ljava/lang/Object;Ljava/lang/Object;)Lscala/collection/Iterator;
Method	scala/collection/Iterator$class.zipAll:(Lscala/collection/Iterator;Lscala/collection/Iterator;Ljava/lang/Object;Ljava/lang/Object;)Lscala/collection/Iterator;
Asciz	thisElem;
Asciz	thatElem;
Asciz	foreach;
Asciz	(Lscala/Function1;)V;
Asciz	(Lscala/collection/Iterator;Lscala/Function1;)V;
NameAndType	foreach:(Lscala/collection/Iterator;Lscala/Function1;)V
Method	scala/collection/Iterator$class.foreach:(Lscala/collection/Iterator;Lscala/Function1;)V
Asciz	forall;
Asciz	(Lscala/Function1;)Z;
Asciz	(Lscala/collection/Iterator;Lscala/Function1;)Z;
NameAndType	forall:(Lscala/collection/Iterator;Lscala/Function1;)Z
Method	scala/collection/Iterator$class.forall:(Lscala/collection/Iterator;Lscala/Function1;)Z
Asciz	exists;
NameAndType	exists:(Lscala/collection/Iterator;Lscala/Function1;)Z
Method	scala/collection/Iterator$class.exists:(Lscala/collection/Iterator;Lscala/Function1;)Z
Asciz	contains;
Asciz	(Ljava/lang/Object;)Z;
Asciz	(Lscala/collection/Iterator;Ljava/lang/Object;)Z;
NameAndType	contains:(Lscala/collection/Iterator;Ljava/lang/Object;)Z
Method	scala/collection/Iterator$class.contains:(Lscala/collection/Iterator;Ljava/lang/Object;)Z
Asciz	find;
Asciz	(Lscala/Function1;)Lscala/Option;;
Asciz	(Lscala/collection/Iterator;Lscala/Function1;)Lscala/Option;;
NameAndType	find:(Lscala/collection/Iterator;Lscala/Function1;)Lscala/Option;
Method	scala/collection/Iterator$class.find:(Lscala/collection/Iterator;Lscala/Function1;)Lscala/Option;
Asciz	indexWhere;
Asciz	(Lscala/Function1;)I;
Asciz	(Lscala/collection/Iterator;Lscala/Function1;)I;
NameAndType	indexWhere:(Lscala/collection/Iterator;Lscala/Function1;)I
Method	scala/collection/Iterator$class.indexWhere:(Lscala/collection/Iterator;Lscala/Function1;)I
Asciz	indexOf;
Asciz	(Ljava/lang/Object;)I;
Asciz	(Lscala/collection/Iterator;Ljava/lang/Object;)I;
NameAndType	indexOf:(Lscala/collection/Iterator;Ljava/lang/Object;)I
Method	scala/collection/Iterator$class.indexOf:(Lscala/collection/Iterator;Ljava/lang/Object;)I
Asciz	buffered;
Asciz	()Lscala/collection/BufferedIterator;;
Asciz	(Lscala/collection/Iterator;)Lscala/collection/BufferedIterator;;
NameAndType	buffered:(Lscala/collection/Iterator;)Lscala/collection/BufferedIterator;
Method	scala/collection/Iterator$class.buffered:(Lscala/collection/Iterator;)Lscala/collection/BufferedIterator;
Asciz	grouped;
Asciz	(I)Lscala/collection/Iterator$GroupedIterator;;
Asciz	(Lscala/collection/Iterator;I)Lscala/collection/Iterator$GroupedIterator;;
NameAndType	grouped:(Lscala/collection/Iterator;I)Lscala/collection/Iterator$GroupedIterator;
Method	scala/collection/Iterator$class.grouped:(Lscala/collection/Iterator;I)Lscala/collection/Iterator$GroupedIterator;
Asciz	size;
Asciz	Signature;
Asciz	sliding;
Asciz	(II)Lscala/collection/Iterator$GroupedIterator;;
Asciz	(Lscala/collection/Iterator;II)Lscala/collection/Iterator$GroupedIterator;;
NameAndType	sliding:(Lscala/collection/Iterator;II)Lscala/collection/Iterator$GroupedIterator;
Method	scala/collection/Iterator$class.sliding:(Lscala/collection/Iterator;II)Lscala/collection/Iterator$GroupedIterator;
Asciz	step;
Asciz	length;
Asciz	()I;
Asciz	(Lscala/collection/Iterator;)I;
NameAndType	length:(Lscala/collection/Iterator;)I
Method	scala/collection/Iterator$class.length:(Lscala/collection/Iterator;)I
Asciz	duplicate;
Asciz	()Lscala/Tuple2;;
Asciz	(Lscala/collection/Iterator;)Lscala/Tuple2;;
NameAndType	duplicate:(Lscala/collection/Iterator;)Lscala/Tuple2;
Method	scala/collection/Iterator$class.duplicate:(Lscala/collection/Iterator;)Lscala/Tuple2;
Asciz	patch;
Asciz	(ILscala/collection/Iterator;I)Lscala/collection/Iterator;;
Asciz	(Lscala/collection/Iterator;ILscala/collection/Iterator;I)Lscala/collection/Iterator;;
NameAndType	patch:(Lscala/collection/Iterator;ILscala/collection/Iterator;I)Lscala/collection/Iterator;
Method	scala/collection/Iterator$class.patch:(Lscala/collection/Iterator;ILscala/collection/Iterator;I)Lscala/collection/Iterator;
Asciz	patchElems;
Asciz	replaced;
Asciz	copyToArray;
Asciz	(Ljava/lang/Object;II)V;
Asciz	(Lscala/collection/Iterator;Ljava/lang/Object;II)V;
NameAndType	copyToArray:(Lscala/collection/Iterator;Ljava/lang/Object;II)V
Method	scala/collection/Iterator$class.copyToArray:(Lscala/collection/Iterator;Ljava/lang/Object;II)V
Asciz	xs;
Asciz	start;
Asciz	sameElements;
Asciz	(Lscala/collection/Iterator;Lscala/collection/Iterator;)Z;
NameAndType	sameElements:(Lscala/collection/Iterator;Lscala/collection/Iterator;)Z
Method	scala/collection/Iterator$class.sameElements:(Lscala/collection/Iterator;Lscala/collection/Iterator;)Z
Asciz	toTraversable;
Asciz	()Lscala/collection/Traversable;;
Asciz	(Lscala/collection/Iterator;)Lscala/collection/Traversable;;
NameAndType	toTraversable:(Lscala/collection/Iterator;)Lscala/collection/Traversable;
Method	scala/collection/Iterator$class.toTraversable:(Lscala/collection/Iterator;)Lscala/collection/Traversable;
Asciz	toIterator;
NameAndType	toIterator:(Lscala/collection/Iterator;)Lscala/collection/Iterator;
Method	scala/collection/Iterator$class.toIterator:(Lscala/collection/Iterator;)Lscala/collection/Iterator;
Asciz	toString;
Asciz	()Ljava/lang/String;;
Asciz	(Lscala/collection/Iterator;)Ljava/lang/String;;
NameAndType	toString:(Lscala/collection/Iterator;)Ljava/lang/String;
Method	scala/collection/Iterator$class.toString:(Lscala/collection/Iterator;)Ljava/lang/String;
Asciz	append;
NameAndType	append:(Lscala/collection/Iterator;Lscala/collection/Iterator;)Lscala/collection/Iterator;
Method	scala/collection/Iterator$class.append:(Lscala/collection/Iterator;Lscala/collection/Iterator;)Lscala/collection/Iterator;
Asciz	Deprecated;
Asciz	findIndexOf;
NameAndType	findIndexOf:(Lscala/collection/Iterator;Lscala/Function1;)I
Method	scala/collection/Iterator$class.findIndexOf:(Lscala/collection/Iterator;Lscala/Function1;)I
Asciz	counted;
Asciz	()Lscala/CountedIterator;;
Asciz	(Lscala/collection/Iterator;)Lscala/CountedIterator;;
NameAndType	counted:(Lscala/collection/Iterator;)Lscala/CountedIterator;
Method	scala/collection/Iterator$class.counted:(Lscala/collection/Iterator;)Lscala/CountedIterator;
Asciz	readInto;
NameAndType	readInto:(Lscala/collection/Iterator;Ljava/lang/Object;II)V
Method	scala/collection/Iterator$class.readInto:(Lscala/collection/Iterator;Ljava/lang/Object;II)V
Asciz	sz;
Asciz	(Ljava/lang/Object;I)V;
Asciz	(Lscala/collection/Iterator;Ljava/lang/Object;I)V;
NameAndType	readInto:(Lscala/collection/Iterator;Ljava/lang/Object;I)V
Method	scala/collection/Iterator$class.readInto:(Lscala/collection/Iterator;Ljava/lang/Object;I)V
Asciz	(Lscala/collection/Iterator;Ljava/lang/Object;)V;
NameAndType	readInto:(Lscala/collection/Iterator;Ljava/lang/Object;)V
Method	scala/collection/Iterator$class.readInto:(Lscala/collection/Iterator;Ljava/lang/Object;)V
Asciz	sliding$default$2;
NameAndType	sliding$default$2:(Lscala/collection/Iterator;)I
Method	scala/collection/Iterator$class.sliding$default$2:(Lscala/collection/Iterator;)I
Asciz	reversed;
Asciz	()Lscala/collection/immutable/List;;
Asciz	scala/collection/TraversableOnce$class;
class	scala/collection/TraversableOnce$class
Asciz	(Lscala/collection/TraversableOnce;)Lscala/collection/immutable/List;;
NameAndType	reversed:(Lscala/collection/TraversableOnce;)Lscala/collection/immutable/List;
Method	scala/collection/TraversableOnce$class.reversed:(Lscala/collection/TraversableOnce;)Lscala/collection/immutable/List;
Asciz	(Lscala/collection/TraversableOnce;)I;
NameAndType	size:(Lscala/collection/TraversableOnce;)I
Method	scala/collection/TraversableOnce$class.size:(Lscala/collection/TraversableOnce;)I
Asciz	nonEmpty;
Asciz	(Lscala/collection/TraversableOnce;)Z;
NameAndType	nonEmpty:(Lscala/collection/TraversableOnce;)Z
Method	scala/collection/TraversableOnce$class.nonEmpty:(Lscala/collection/TraversableOnce;)Z
Asciz	count;
Asciz	(Lscala/collection/TraversableOnce;Lscala/Function1;)I;
NameAndType	count:(Lscala/collection/TraversableOnce;Lscala/Function1;)I
Method	scala/collection/TraversableOnce$class.count:(Lscala/collection/TraversableOnce;Lscala/Function1;)I
Asciz	$div$colon;
Asciz	(Ljava/lang/Object;Lscala/Function2;)Ljava/lang/Object;;
Asciz	(Lscala/collection/TraversableOnce;Ljava/lang/Object;Lscala/Function2;)Ljava/lang/Object;;
NameAndType	$div$colon:(Lscala/collection/TraversableOnce;Ljava/lang/Object;Lscala/Function2;)Ljava/lang/Object;
Method	scala/collection/TraversableOnce$class.$div$colon:(Lscala/collection/TraversableOnce;Ljava/lang/Object;Lscala/Function2;)Ljava/lang/Object;
Asciz	z;
Asciz	op;
Asciz	Lscala/Function2;;
Asciz	$colon$bslash;
NameAndType	$colon$bslash:(Lscala/collection/TraversableOnce;Ljava/lang/Object;Lscala/Function2;)Ljava/lang/Object;
Method	scala/collection/TraversableOnce$class.$colon$bslash:(Lscala/collection/TraversableOnce;Ljava/lang/Object;Lscala/Function2;)Ljava/lang/Object;
Asciz	foldLeft;
NameAndType	foldLeft:(Lscala/collection/TraversableOnce;Ljava/lang/Object;Lscala/Function2;)Ljava/lang/Object;
Method	scala/collection/TraversableOnce$class.foldLeft:(Lscala/collection/TraversableOnce;Ljava/lang/Object;Lscala/Function2;)Ljava/lang/Object;
Asciz	foldRight;
NameAndType	foldRight:(Lscala/collection/TraversableOnce;Ljava/lang/Object;Lscala/Function2;)Ljava/lang/Object;
Method	scala/collection/TraversableOnce$class.foldRight:(Lscala/collection/TraversableOnce;Ljava/lang/Object;Lscala/Function2;)Ljava/lang/Object;
Asciz	reduceLeft;
Asciz	(Lscala/Function2;)Ljava/lang/Object;;
Asciz	(Lscala/collection/TraversableOnce;Lscala/Function2;)Ljava/lang/Object;;
NameAndType	reduceLeft:(Lscala/collection/TraversableOnce;Lscala/Function2;)Ljava/lang/Object;
Method	scala/collection/TraversableOnce$class.reduceLeft:(Lscala/collection/TraversableOnce;Lscala/Function2;)Ljava/lang/Object;
Asciz	reduceRight;
NameAndType	reduceRight:(Lscala/collection/TraversableOnce;Lscala/Function2;)Ljava/lang/Object;
Method	scala/collection/TraversableOnce$class.reduceRight:(Lscala/collection/TraversableOnce;Lscala/Function2;)Ljava/lang/Object;
Asciz	reduceLeftOption;
Asciz	(Lscala/Function2;)Lscala/Option;;
Asciz	(Lscala/collection/TraversableOnce;Lscala/Function2;)Lscala/Option;;
NameAndType	reduceLeftOption:(Lscala/collection/TraversableOnce;Lscala/Function2;)Lscala/Option;
Method	scala/collection/TraversableOnce$class.reduceLeftOption:(Lscala/collection/TraversableOnce;Lscala/Function2;)Lscala/Option;
Asciz	reduceRightOption;
NameAndType	reduceRightOption:(Lscala/collection/TraversableOnce;Lscala/Function2;)Lscala/Option;
Method	scala/collection/TraversableOnce$class.reduceRightOption:(Lscala/collection/TraversableOnce;Lscala/Function2;)Lscala/Option;
Asciz	sum;
Asciz	(Lscala/math/Numeric;)Ljava/lang/Object;;
Asciz	(Lscala/collection/TraversableOnce;Lscala/math/Numeric;)Ljava/lang/Object;;
NameAndType	sum:(Lscala/collection/TraversableOnce;Lscala/math/Numeric;)Ljava/lang/Object;
Method	scala/collection/TraversableOnce$class.sum:(Lscala/collection/TraversableOnce;Lscala/math/Numeric;)Ljava/lang/Object;
Asciz	num;
Asciz	Lscala/math/Numeric;;
Asciz	product;
NameAndType	product:(Lscala/collection/TraversableOnce;Lscala/math/Numeric;)Ljava/lang/Object;
Method	scala/collection/TraversableOnce$class.product:(Lscala/collection/TraversableOnce;Lscala/math/Numeric;)Ljava/lang/Object;
Asciz	min;
Asciz	(Lscala/math/Ordering;)Ljava/lang/Object;;
Asciz	(Lscala/collection/TraversableOnce;Lscala/math/Ordering;)Ljava/lang/Object;;
NameAndType	min:(Lscala/collection/TraversableOnce;Lscala/math/Ordering;)Ljava/lang/Object;
Method	scala/collection/TraversableOnce$class.min:(Lscala/collection/TraversableOnce;Lscala/math/Ordering;)Ljava/lang/Object;
Asciz	cmp;
Asciz	Lscala/math/Ordering;;
Asciz	max;
NameAndType	max:(Lscala/collection/TraversableOnce;Lscala/math/Ordering;)Ljava/lang/Object;
Method	scala/collection/TraversableOnce$class.max:(Lscala/collection/TraversableOnce;Lscala/math/Ordering;)Ljava/lang/Object;
Asciz	copyToBuffer;
Asciz	(Lscala/collection/mutable/Buffer;)V;
Asciz	(Lscala/collection/TraversableOnce;Lscala/collection/mutable/Buffer;)V;
NameAndType	copyToBuffer:(Lscala/collection/TraversableOnce;Lscala/collection/mutable/Buffer;)V
Method	scala/collection/TraversableOnce$class.copyToBuffer:(Lscala/collection/TraversableOnce;Lscala/collection/mutable/Buffer;)V
Asciz	dest;
Asciz	Lscala/collection/mutable/Buffer;;
Asciz	(Lscala/collection/TraversableOnce;Ljava/lang/Object;I)V;
NameAndType	copyToArray:(Lscala/collection/TraversableOnce;Ljava/lang/Object;I)V
Method	scala/collection/TraversableOnce$class.copyToArray:(Lscala/collection/TraversableOnce;Ljava/lang/Object;I)V
Asciz	(Lscala/collection/TraversableOnce;Ljava/lang/Object;)V;
NameAndType	copyToArray:(Lscala/collection/TraversableOnce;Ljava/lang/Object;)V
Method	scala/collection/TraversableOnce$class.copyToArray:(Lscala/collection/TraversableOnce;Ljava/lang/Object;)V
Asciz	toArray;
Asciz	(Lscala/reflect/ClassManifest;)Ljava/lang/Object;;
Asciz	(Lscala/collection/TraversableOnce;Lscala/reflect/ClassManifest;)Ljava/lang/Object;;
NameAndType	toArray:(Lscala/collection/TraversableOnce;Lscala/reflect/ClassManifest;)Ljava/lang/Object;
Method	scala/collection/TraversableOnce$class.toArray:(Lscala/collection/TraversableOnce;Lscala/reflect/ClassManifest;)Ljava/lang/Object;
Asciz	evidence$1;
Asciz	Lscala/reflect/ClassManifest;;
Asciz	toList;
NameAndType	toList:(Lscala/collection/TraversableOnce;)Lscala/collection/immutable/List;
Method	scala/collection/TraversableOnce$class.toList:(Lscala/collection/TraversableOnce;)Lscala/collection/immutable/List;
Asciz	toIterable;
Asciz	()Lscala/collection/Iterable;;
Asciz	(Lscala/collection/TraversableOnce;)Lscala/collection/Iterable;;
NameAndType	toIterable:(Lscala/collection/TraversableOnce;)Lscala/collection/Iterable;
Method	scala/collection/TraversableOnce$class.toIterable:(Lscala/collection/TraversableOnce;)Lscala/collection/Iterable;
Asciz	toSeq;
Asciz	()Lscala/collection/Seq;;
Asciz	(Lscala/collection/TraversableOnce;)Lscala/collection/Seq;;
NameAndType	toSeq:(Lscala/collection/TraversableOnce;)Lscala/collection/Seq;
Method	scala/collection/TraversableOnce$class.toSeq:(Lscala/collection/TraversableOnce;)Lscala/collection/Seq;
Asciz	toIndexedSeq;
Asciz	()Lscala/collection/mutable/IndexedSeq;;
Asciz	(Lscala/collection/TraversableOnce;)Lscala/collection/mutable/IndexedSeq;;
NameAndType	toIndexedSeq:(Lscala/collection/TraversableOnce;)Lscala/collection/mutable/IndexedSeq;
Method	scala/collection/TraversableOnce$class.toIndexedSeq:(Lscala/collection/TraversableOnce;)Lscala/collection/mutable/IndexedSeq;
Asciz	toStream;
Asciz	()Lscala/collection/immutable/Stream;;
Asciz	(Lscala/collection/TraversableOnce;)Lscala/collection/immutable/Stream;;
NameAndType	toStream:(Lscala/collection/TraversableOnce;)Lscala/collection/immutable/Stream;
Method	scala/collection/TraversableOnce$class.toStream:(Lscala/collection/TraversableOnce;)Lscala/collection/immutable/Stream;
Asciz	toSet;
Asciz	()Lscala/collection/immutable/Set;;
Asciz	(Lscala/collection/TraversableOnce;)Lscala/collection/immutable/Set;;
NameAndType	toSet:(Lscala/collection/TraversableOnce;)Lscala/collection/immutable/Set;
Method	scala/collection/TraversableOnce$class.toSet:(Lscala/collection/TraversableOnce;)Lscala/collection/immutable/Set;
Asciz	toMap;
Asciz	(Lscala/Predef$$less$colon$less;)Lscala/collection/immutable/Map;;
Asciz	(Lscala/collection/TraversableOnce;Lscala/Predef$$less$colon$less;)Lscala/collection/immutable/Map;;
NameAndType	toMap:(Lscala/collection/TraversableOnce;Lscala/Predef$$less$colon$less;)Lscala/collection/immutable/Map;
Method	scala/collection/TraversableOnce$class.toMap:(Lscala/collection/TraversableOnce;Lscala/Predef$$less$colon$less;)Lscala/collection/immutable/Map;
Asciz	ev;
Asciz	Lscala/Predef$$less$colon$less;;
Asciz	mkString;
Asciz	(Ljava/lang/String;Ljava/lang/String;Ljava/lang/String;)Ljava/lang/String;;
Asciz	(Lscala/collection/TraversableOnce;Ljava/lang/String;Ljava/lang/String;Ljava/lang/String;)Ljava/lang/String;;
NameAndType	mkString:(Lscala/collection/TraversableOnce;Ljava/lang/String;Ljava/lang/String;Ljava/lang/String;)Ljava/lang/String;
Method	scala/collection/TraversableOnce$class.mkString:(Lscala/collection/TraversableOnce;Ljava/lang/String;Ljava/lang/String;Ljava/lang/String;)Ljava/lang/String;
Asciz	Ljava/lang/String;;
Asciz	sep;
Asciz	end;
Asciz	(Ljava/lang/String;)Ljava/lang/String;;
Asciz	(Lscala/collection/TraversableOnce;Ljava/lang/String;)Ljava/lang/String;;
NameAndType	mkString:(Lscala/collection/TraversableOnce;Ljava/lang/String;)Ljava/lang/String;
Method	scala/collection/TraversableOnce$class.mkString:(Lscala/collection/TraversableOnce;Ljava/lang/String;)Ljava/lang/String;
Asciz	(Lscala/collection/TraversableOnce;)Ljava/lang/String;;
NameAndType	mkString:(Lscala/collection/TraversableOnce;)Ljava/lang/String;
Method	scala/collection/TraversableOnce$class.mkString:(Lscala/collection/TraversableOnce;)Ljava/lang/String;
Asciz	addString;
Asciz	(Lscala/collection/mutable/StringBuilder;Ljava/lang/String;Ljava/lang/String;Ljava/lang/String;)Lscala/collection/mutable/StringBuilder;;
Asciz	(Lscala/collection/TraversableOnce;Lscala/collection/mutable/StringBuilder;Ljava/lang/String;Ljava/lang/String;Ljava/lang/String;)Lscala/collection/mutable/StringBuilder;;
NameAndType	addString:(Lscala/collection/TraversableOnce;Lscala/collection/mutable/StringBuilder;Ljava/lang/String;Ljava/lang/String;Ljava/lang/String;)Lscala/collection/mutable/StringBuilder;
Method	scala/collection/TraversableOnce$class.addString:(Lscala/collection/TraversableOnce;Lscala/collection/mutable/StringBuilder;Ljava/lang/String;Ljava/lang/String;Ljava/lang/String;)Lscala/collection/mutable/StringBuilder;
Asciz	b;
Asciz	Lscala/collection/mutable/StringBuilder;;
Asciz	(Lscala/collection/mutable/StringBuilder;Ljava/lang/String;)Lscala/collection/mutable/StringBuilder;;
Asciz	(Lscala/collection/TraversableOnce;Lscala/collection/mutable/StringBuilder;Ljava/lang/String;)Lscala/collection/mutable/StringBuilder;;
NameAndType	addString:(Lscala/collection/TraversableOnce;Lscala/collection/mutable/StringBuilder;Ljava/lang/String;)Lscala/collection/mutable/StringBuilder;
Method	scala/collection/TraversableOnce$class.addString:(Lscala/collection/TraversableOnce;Lscala/collection/mutable/StringBuilder;Ljava/lang/String;)Lscala/collection/mutable/StringBuilder;
Asciz	(Lscala/collection/mutable/StringBuilder;)Lscala/collection/mutable/StringBuilder;;
Asciz	(Lscala/collection/TraversableOnce;Lscala/collection/mutable/StringBuilder;)Lscala/collection/mutable/StringBuilder;;
NameAndType	addString:(Lscala/collection/TraversableOnce;Lscala/collection/mutable/StringBuilder;)Lscala/collection/mutable/StringBuilder;
Method	scala/collection/TraversableOnce$class.addString:(Lscala/collection/TraversableOnce;Lscala/collection/mutable/StringBuilder;)Lscala/collection/mutable/StringBuilder;
NameAndType	preserveWS:Z
Field	scala/xml/pull/XMLEventReader.preserveWS:Z
NameAndType	MaxQueueSize:I
Field	scala/xml/pull/XMLEventReader.MaxQueueSize:I
Asciz	POISON;
Asciz	()Lscala/xml/pull/XMLEventReader$POISON$;;
NameAndType	POISON$module:Lscala/xml/pull/XMLEventReader$POISON$;
Field	scala/xml/pull/XMLEventReader.POISON$module:Lscala/xml/pull/XMLEventReader$POISON$;
Asciz	scala/xml/pull/XMLEventReader$POISON$;
class	scala/xml/pull/XMLEventReader$POISON$
Asciz	<init>;
Asciz	(Lscala/xml/pull/XMLEventReader;)V;
NameAndType	"<init>":(Lscala/xml/pull/XMLEventReader;)V
Method	scala/xml/pull/XMLEventReader$POISON$."<init>":(Lscala/xml/pull/XMLEventReader;)V
NameAndType	EndOfStream:Lscala/xml/pull/XMLEventReader$POISON$;
Field	scala/xml/pull/XMLEventReader.EndOfStream:Lscala/xml/pull/XMLEventReader$POISON$;
Asciz	stop;
Asciz	()V;
NameAndType	POISON:()Lscala/xml/pull/XMLEventReader$POISON$;
Method	scala/xml/pull/XMLEventReader.POISON:()Lscala/xml/pull/XMLEventReader$POISON$;
Asciz	scala/xml/pull/ProducerConsumerIterator;
class	scala/xml/pull/ProducerConsumerIterator
NameAndType	produce:(Ljava/lang/Object;)V
InterfaceMethod	scala/xml/pull/ProducerConsumerIterator.produce:(Ljava/lang/Object;)V
NameAndType	parserThread:Ljava/lang/Thread;
Field	scala/xml/pull/XMLEventReader.parserThread:Ljava/lang/Thread;
Asciz	java/lang/Thread;
class	java/lang/Thread
Asciz	interrupt;
NameAndType	interrupt:()V
Method	java/lang/Thread.interrupt:()V
NameAndType	EndOfStream:()Lscala/xml/pull/XMLEventReader$POISON$;
Method	scala/xml/pull/XMLEventReader.EndOfStream:()Lscala/xml/pull/XMLEventReader$POISON$;
Asciz	(Lscala/io/Source;)V;
Asciz	java/lang/Object;
class	java/lang/Object
NameAndType	"<init>":()V
Method	java/lang/Object."<init>":()V
Asciz	$init$;
Asciz	(Lscala/collection/TraversableOnce;)V;
NameAndType	$init$:(Lscala/collection/TraversableOnce;)V
Method	scala/collection/TraversableOnce$class.$init$:(Lscala/collection/TraversableOnce;)V
Asciz	(Lscala/collection/Iterator;)V;
NameAndType	$init$:(Lscala/collection/Iterator;)V
Method	scala/collection/Iterator$class.$init$:(Lscala/collection/Iterator;)V
Asciz	(Lscala/xml/pull/ProducerConsumerIterator;)V;
NameAndType	$init$:(Lscala/xml/pull/ProducerConsumerIterator;)V
Method	scala/xml/pull/ProducerConsumerIterator$class.$init$:(Lscala/xml/pull/ProducerConsumerIterator;)V
int	1000;
Asciz	scala/xml/pull/XMLEventReader$Parser;
class	scala/xml/pull/XMLEventReader$Parser
Asciz	(Lscala/xml/pull/XMLEventReader;Lscala/io/Source;)V;
NameAndType	"<init>":(Lscala/xml/pull/XMLEventReader;Lscala/io/Source;)V
Method	scala/xml/pull/XMLEventReader$Parser."<init>":(Lscala/xml/pull/XMLEventReader;Lscala/io/Source;)V
NameAndType	parser:Lscala/xml/pull/XMLEventReader$Parser;
Field	scala/xml/pull/XMLEventReader.parser:Lscala/xml/pull/XMLEventReader$Parser;
Asciz	XMLEventReader;
String	XMLEventReader
Asciz	(Ljava/lang/Runnable;Ljava/lang/String;)V;
NameAndType	"<init>":(Ljava/lang/Runnable;Ljava/lang/String;)V
Method	java/lang/Thread."<init>":(Ljava/lang/Runnable;Ljava/lang/String;)V
NameAndType	start:()V
Method	java/lang/Thread.start:()V
Asciz	src;
Asciz	Lscala/io/Source;;
Asciz	ScalaSig;
Asciz	Ljava/lang/Object;Lscala/xml/pull/ProducerConsumerIterator<Lscala/xml/pull/XMLEvent;>;Lscala/ScalaObject;;
Asciz	Lscala/reflect/ScalaSignature;;
Asciz	bytes;
Asciz	%gC\t\tAakE*<f]RV-3fe*1BaVdGN\r07\tQa]2bYaIICAa!BAaM\4=\tAA[1wC&\nTWm;M!b#D\t)\"A\rQe>$WoY3s>t7/^7fe&#XM]1u_J\"aE\na!-N3XM;iYR\"\nq1!aC*dC2wJ6fGRDBIaHgJC$\t#B\tIw.%C\t11k\;sGDQA\n\naP5oSRtDC*!\tCKqC,\tIAXm]3sm<6+F.!\tQb&0\r\t9!i\8mKtBBA%Q&AqeXM<f/NbB%\tN\rD+^3vKNK'0ZkA!DNo1!8uI)AkiQ*=Rk,XmU5{K:Qa\tr\naU(J'>sCA?aC \t\tR!\rA{jU(O'q$BF\rB!\tQ\")D\r\t9K]8ek$\"?\t)E#\tsD!AF!^8TiJLgnB1BS2aa;sS:<C'?\tI\t(AxZ;diBXMZ5y+I)?\tI\tAxZ;di^=\tIsD!ABMa:pIVG/7f[tGU/B!$V-1!8zA+!AAU\n12!Qf\"A\nZC2b]X/75bb-Z\r\t=z\"\t!C\t?Y!/Z1e%x<f)QF b!\tQ\"-d\r\ta1/:jC2L'02mK\"9Q\rb\n1aC#oI>37:fC6,QsGm4TiJ,-\t\r)!lM]:feBQ\t[!\t!A]\n1+:tKJb\8vqnLC9t\t(B:M]:j]L!^95'o[;qtG\r\3s!\th/xc\naQ*:lkBM]:feB/_uFq\"=uKJt\r\*pkJWm\tqL!! I+hN\1cYDb 7%\t!!%t/;}A\"!mB\r%t/;!1C\"\nQ1.a\t\r}91 YCN1A1Ba!\r7!ibBA\nYQC\tg$XI^3oiR!qCA!\tI\"aI1!!quZ3TKFD\"!\t1EKNBAGA-%qqX\r]3bi$gC,1$\t%!dW-\*uCJ$HDAk\tI$!N]c2%1\tUso\tI16\rxn\tw\tI1>O]3\t}Q\t5bAA\"\r1K]3eKL1aSA$\r\tE\t\nI1>)A.2fY\"AqJA\t\t&AbiR8MbAA+\t\tAQ*;b\t$\rZ%AA.8m9f!\tI\"!\n}CA\tOC6,7]1dK\nKgZ5oO\"91\r7BaB3mK6,e\t_\t9'!l!9qGA1)CAC\r!!\t-\ra{Aq!am\t\t\t(fYlGCDAg\n)(azmqo\ti16!\tY$!AuCA&[\r!!\t=Qa#B\"! n1LaNw]3\tQa/\tQA\8eKNDq!!\"m\t\t9)Aqe>J\:ueRAqCAEy\tC8\rA\t51a{\ta^1sO$CAI\r!!QDHC2$\t!a&\r|W.\3oiR1qCAM7Cq!aQMAA\ty\nCC\"8uSRL(+4\r]1UAS\t9$!(AUB\"a*QH]\"9175;fqR$b!a0EbBAS\r!\t#I1>!9Q7B]a:v]Rq\tw!>a/:tKJ$N]3bIB1\"a0\nGBUQJ,\rAAAdHo9=;
Asciz	RuntimeVisibleAnnotations;
Asciz	InnerClasses;
Asciz	Parser;
Asciz	scala/Predef$$less$colon$less;
class	scala/Predef$$less$colon$less
Asciz	scala/Predef;
class	scala/Predef
Asciz	$less$colon$less;
Asciz	scala/collection/Iterator$GroupedIterator;
class	scala/collection/Iterator$GroupedIterator
Asciz	scala/collection/Iterator;
class	scala/collection/Iterator
Asciz	GroupedIterator;
Asciz	scala/ScalaObject;
class	scala/ScalaObject

{
private final boolean preserveWS;
  Signature: Z

private final int MaxQueueSize;
  Signature: I

private final scala.xml.pull.XMLEventReader$POISON$ EndOfStream;
  Signature: Lscala/xml/pull/XMLEventReader$POISON$;

private final scala.xml.pull.XMLEventReader$Parser parser;
  Signature: Lscala/xml/pull/XMLEventReader$Parser;

private final java.lang.Thread parserThread;
  Signature: Ljava/lang/Thread;

public scala.xml.pull.XMLEventReader$POISON$ POISON$module;
  Signature: Lscala/xml/pull/XMLEventReader$POISON$;

private final java.util.concurrent.LinkedBlockingQueue scala$xml$pull$ProducerConsumerIterator$$queue;
  Signature: Ljava/util/concurrent/LinkedBlockingQueue;

private java.lang.Object scala$xml$pull$ProducerConsumerIterator$$buffer;
  Signature: Ljava/lang/Object;

public volatile int bitmap$0;
  Signature: I

public final java.util.concurrent.LinkedBlockingQueue scala$xml$pull$ProducerConsumerIterator$$queue();
  Signature: ()Ljava/util/concurrent/LinkedBlockingQueue;
  Code:
   Stack=3, Locals=1, Args_size=1
	aload_0
	getfield	Field bitmap$0:I
	iconst_1
	iand
	iconst_0
	if_icmpne	l1 // aload_0
	aload_0
	dup
	pop
	monitorenter
	aload_0
	getfield	Field bitmap$0:I
	iconst_1
	iand
	iconst_0
	if_icmpne	l2 // aload_0
	aload_0
	aload_0
	invokestatic	Method scala/xml/pull/ProducerConsumerIterator$class.scala$xml$pull$ProducerConsumerIterator$$queue:(Lscala/xml/pull/ProducerConsumerIterator;)Ljava/util/concurrent/LinkedBlockingQueue;
	putfield	Field scala$xml$pull$ProducerConsumerIterator$$queue:Ljava/util/concurrent/LinkedBlockingQueue;
	aload_0
	aload_0
	getfield	Field bitmap$0:I
	iconst_1
	ior
	putfield	Field bitmap$0:I
l2	aload_0
	monitorexit
l1	aload_0
	getfield	Field scala$xml$pull$ProducerConsumerIterator$$queue:Ljava/util/concurrent/LinkedBlockingQueue;
	areturn
	aload_0
	monitorexit
	athrow
  Labels:
   	l2 = 42 // aload_0
   	l1 = 44 // aload_0
  Exception table:
   from   to  target type
    14    44    49   any

public void scala$xml$pull$ProducerConsumerIterator$_setter_$MaxQueueSize_$eq(int);
  Signature: (I)V
  Code:
   Stack=0, Locals=2, Args_size=2
	return
  Labels:

public java.lang.Object scala$xml$pull$ProducerConsumerIterator$$buffer();
  Signature: ()Ljava/lang/Object;
  Code:
   Stack=1, Locals=1, Args_size=1
	aload_0
	getfield	Field scala$xml$pull$ProducerConsumerIterator$$buffer:Ljava/lang/Object;
	areturn
  Labels:

public void scala$xml$pull$ProducerConsumerIterator$$buffer_$eq(java.lang.Object);
  Signature: (Ljava/lang/Object;)V
  Code:
   Stack=2, Locals=2, Args_size=2
	aload_0
	aload_1
	putfield	Field scala$xml$pull$ProducerConsumerIterator$$buffer:Ljava/lang/Object;
	return
  Labels:

public scala.Option interruptibly(scala.Function0);
  Signature: (Lscala/Function0;)Lscala/Option;
  Code:
   Stack=2, Locals=2, Args_size=2
	aload_0
	aload_1
	invokestatic	Method scala/xml/pull/ProducerConsumerIterator$class.interruptibly:(Lscala/xml/pull/ProducerConsumerIterator;Lscala/Function0;)Lscala/Option;
	areturn
  Labels:
  LocalVariableTable: 
   Start  Length  Slot  Name   Signature
   0      6      0    this       Lscala/xml/pull/XMLEventReader;
   0      6      1    body       Lscala/Function0;


public void produce(java.lang.Object);
  Signature: (Ljava/lang/Object;)V
  Code:
   Stack=2, Locals=2, Args_size=2
	aload_0
	aload_1
	invokestatic	Method scala/xml/pull/ProducerConsumerIterator$class.produce:(Lscala/xml/pull/ProducerConsumerIterator;Ljava/lang/Object;)V
	return
  Labels:
  LocalVariableTable: 
   Start  Length  Slot  Name   Signature
   0      6      0    this       Lscala/xml/pull/XMLEventReader;
   0      6      1    x       Ljava/lang/Object;


public boolean hasNext();
  Signature: ()Z
  Code:
   Stack=1, Locals=1, Args_size=1
	aload_0
	invokestatic	Method scala/xml/pull/ProducerConsumerIterator$class.hasNext:(Lscala/xml/pull/ProducerConsumerIterator;)Z
	ireturn
  Labels:

public java.lang.Object next();
  Signature: ()Ljava/lang/Object;
  Code:
   Stack=1, Locals=1, Args_size=1
	aload_0
	invokestatic	Method scala/xml/pull/ProducerConsumerIterator$class.next:(Lscala/xml/pull/ProducerConsumerIterator;)Ljava/lang/Object;
	areturn
  Labels:

public boolean available();
  Signature: ()Z
  Code:
   Stack=1, Locals=1, Args_size=1
	aload_0
	invokestatic	Method scala/xml/pull/ProducerConsumerIterator$class.available:(Lscala/xml/pull/ProducerConsumerIterator;)Z
	ireturn
  Labels:

public boolean isEmpty();
  Signature: ()Z
  Code:
   Stack=1, Locals=1, Args_size=1
	aload_0
	invokestatic	Method scala/collection/Iterator$class.isEmpty:(Lscala/collection/Iterator;)Z
	ireturn
  Labels:

public boolean isTraversableAgain();
  Signature: ()Z
  Code:
   Stack=1, Locals=1, Args_size=1
	aload_0
	invokestatic	Method scala/collection/Iterator$class.isTraversableAgain:(Lscala/collection/Iterator;)Z
	ireturn
  Labels:

public boolean hasDefiniteSize();
  Signature: ()Z
  Code:
   Stack=1, Locals=1, Args_size=1
	aload_0
	invokestatic	Method scala/collection/Iterator$class.hasDefiniteSize:(Lscala/collection/Iterator;)Z
	ireturn
  Labels:

public scala.collection.Iterator take(int);
  Signature: (I)Lscala/collection/Iterator;
  Code:
   Stack=2, Locals=2, Args_size=2
	aload_0
	iload_1
	invokestatic	Method scala/collection/Iterator$class.take:(Lscala/collection/Iterator;I)Lscala/collection/Iterator;
	areturn
  Labels:
  LocalVariableTable: 
   Start  Length  Slot  Name   Signature
   0      6      0    this       Lscala/xml/pull/XMLEventReader;
   0      6      1    n       I


public scala.collection.Iterator drop(int);
  Signature: (I)Lscala/collection/Iterator;
  Code:
   Stack=2, Locals=2, Args_size=2
	aload_0
	iload_1
	invokestatic	Method scala/collection/Iterator$class.drop:(Lscala/collection/Iterator;I)Lscala/collection/Iterator;
	areturn
  Labels:
  LocalVariableTable: 
   Start  Length  Slot  Name   Signature
   0      6      0    this       Lscala/xml/pull/XMLEventReader;
   0      6      1    n       I


public scala.collection.Iterator slice(int, int);
  Signature: (II)Lscala/collection/Iterator;
  Code:
   Stack=3, Locals=3, Args_size=3
	aload_0
	iload_1
	iload_2
	invokestatic	Method scala/collection/Iterator$class.slice:(Lscala/collection/Iterator;II)Lscala/collection/Iterator;
	areturn
  Labels:
  LocalVariableTable: 
   Start  Length  Slot  Name   Signature
   0      7      0    this       Lscala/xml/pull/XMLEventReader;
   0      7      1    from       I
   0      7      2    until       I


public scala.collection.Iterator map(scala.Function1);
  Signature: (Lscala/Function1;)Lscala/collection/Iterator;
  Code:
   Stack=2, Locals=2, Args_size=2
	aload_0
	aload_1
	invokestatic	Method scala/collection/Iterator$class.map:(Lscala/collection/Iterator;Lscala/Function1;)Lscala/collection/Iterator;
	areturn
  Labels:
  LocalVariableTable: 
   Start  Length  Slot  Name   Signature
   0      6      0    this       Lscala/xml/pull/XMLEventReader;
   0      6      1    f       Lscala/Function1;


public scala.collection.Iterator $plus$plus(scala.Function0);
  Signature: (Lscala/Function0;)Lscala/collection/Iterator;
  Code:
   Stack=2, Locals=2, Args_size=2
	aload_0
	aload_1
	invokestatic	Method scala/collection/Iterator$class.$plus$plus:(Lscala/collection/Iterator;Lscala/Function0;)Lscala/collection/Iterator;
	areturn
  Labels:
  LocalVariableTable: 
   Start  Length  Slot  Name   Signature
   0      6      0    this       Lscala/xml/pull/XMLEventReader;
   0      6      1    that       Lscala/Function0;


public scala.collection.Iterator flatMap(scala.Function1);
  Signature: (Lscala/Function1;)Lscala/collection/Iterator;
  Code:
   Stack=2, Locals=2, Args_size=2
	aload_0
	aload_1
	invokestatic	Method scala/collection/Iterator$class.flatMap:(Lscala/collection/Iterator;Lscala/Function1;)Lscala/collection/Iterator;
	areturn
  Labels:
  LocalVariableTable: 
   Start  Length  Slot  Name   Signature
   0      6      0    this       Lscala/xml/pull/XMLEventReader;
   0      6      1    f       Lscala/Function1;


public scala.collection.Iterator filter(scala.Function1);
  Signature: (Lscala/Function1;)Lscala/collection/Iterator;
  Code:
   Stack=2, Locals=2, Args_size=2
	aload_0
	aload_1
	invokestatic	Method scala/collection/Iterator$class.filter:(Lscala/collection/Iterator;Lscala/Function1;)Lscala/collection/Iterator;
	areturn
  Labels:
  LocalVariableTable: 
   Start  Length  Slot  Name   Signature
   0      6      0    this       Lscala/xml/pull/XMLEventReader;
   0      6      1    p       Lscala/Function1;


public scala.collection.Iterator withFilter(scala.Function1);
  Signature: (Lscala/Function1;)Lscala/collection/Iterator;
  Code:
   Stack=2, Locals=2, Args_size=2
	aload_0
	aload_1
	invokestatic	Method scala/collection/Iterator$class.withFilter:(Lscala/collection/Iterator;Lscala/Function1;)Lscala/collection/Iterator;
	areturn
  Labels:
  LocalVariableTable: 
   Start  Length  Slot  Name   Signature
   0      6      0    this       Lscala/xml/pull/XMLEventReader;
   0      6      1    p       Lscala/Function1;


public scala.collection.Iterator filterNot(scala.Function1);
  Signature: (Lscala/Function1;)Lscala/collection/Iterator;
  Code:
   Stack=2, Locals=2, Args_size=2
	aload_0
	aload_1
	invokestatic	Method scala/collection/Iterator$class.filterNot:(Lscala/collection/Iterator;Lscala/Function1;)Lscala/collection/Iterator;
	areturn
  Labels:
  LocalVariableTable: 
   Start  Length  Slot  Name   Signature
   0      6      0    this       Lscala/xml/pull/XMLEventReader;
   0      6      1    p       Lscala/Function1;


public scala.collection.Iterator collect(scala.PartialFunction);
  Signature: (Lscala/PartialFunction;)Lscala/collection/Iterator;
  Code:
   Stack=2, Locals=2, Args_size=2
	aload_0
	aload_1
	invokestatic	Method scala/collection/Iterator$class.collect:(Lscala/collection/Iterator;Lscala/PartialFunction;)Lscala/collection/Iterator;
	areturn
  Labels:
  LocalVariableTable: 
   Start  Length  Slot  Name   Signature
   0      6      0    this       Lscala/xml/pull/XMLEventReader;
   0      6      1    pf       Lscala/PartialFunction;


public scala.collection.Iterator takeWhile(scala.Function1);
  Signature: (Lscala/Function1;)Lscala/collection/Iterator;
  Code:
   Stack=2, Locals=2, Args_size=2
	aload_0
	aload_1
	invokestatic	Method scala/collection/Iterator$class.takeWhile:(Lscala/collection/Iterator;Lscala/Function1;)Lscala/collection/Iterator;
	areturn
  Labels:
  LocalVariableTable: 
   Start  Length  Slot  Name   Signature
   0      6      0    this       Lscala/xml/pull/XMLEventReader;
   0      6      1    p       Lscala/Function1;


public scala.Tuple2 partition(scala.Function1);
  Signature: (Lscala/Function1;)Lscala/Tuple2;
  Code:
   Stack=2, Locals=2, Args_size=2
	aload_0
	aload_1
	invokestatic	Method scala/collection/Iterator$class.partition:(Lscala/collection/Iterator;Lscala/Function1;)Lscala/Tuple2;
	areturn
  Labels:
  LocalVariableTable: 
   Start  Length  Slot  Name   Signature
   0      6      0    this       Lscala/xml/pull/XMLEventReader;
   0      6      1    p       Lscala/Function1;


public scala.collection.Iterator dropWhile(scala.Function1);
  Signature: (Lscala/Function1;)Lscala/collection/Iterator;
  Code:
   Stack=2, Locals=2, Args_size=2
	aload_0
	aload_1
	invokestatic	Method scala/collection/Iterator$class.dropWhile:(Lscala/collection/Iterator;Lscala/Function1;)Lscala/collection/Iterator;
	areturn
  Labels:
  LocalVariableTable: 
   Start  Length  Slot  Name   Signature
   0      6      0    this       Lscala/xml/pull/XMLEventReader;
   0      6      1    p       Lscala/Function1;


public scala.collection.Iterator zip(scala.collection.Iterator);
  Signature: (Lscala/collection/Iterator;)Lscala/collection/Iterator;
  Code:
   Stack=2, Locals=2, Args_size=2
	aload_0
	aload_1
	invokestatic	Method scala/collection/Iterator$class.zip:(Lscala/collection/Iterator;Lscala/collection/Iterator;)Lscala/collection/Iterator;
	areturn
  Labels:
  LocalVariableTable: 
   Start  Length  Slot  Name   Signature
   0      6      0    this       Lscala/xml/pull/XMLEventReader;
   0      6      1    that       Lscala/collection/Iterator;


public scala.collection.Iterator padTo(int, java.lang.Object);
  Signature: (ILjava/lang/Object;)Lscala/collection/Iterator;
  Code:
   Stack=3, Locals=3, Args_size=3
	aload_0
	iload_1
	aload_2
	invokestatic	Method scala/collection/Iterator$class.padTo:(Lscala/collection/Iterator;ILjava/lang/Object;)Lscala/collection/Iterator;
	areturn
  Labels:
  LocalVariableTable: 
   Start  Length  Slot  Name   Signature
   0      7      0    this       Lscala/xml/pull/XMLEventReader;
   0      7      1    len       I
   0      7      2    elem       Ljava/lang/Object;


public scala.collection.Iterator zipWithIndex();
  Signature: ()Lscala/collection/Iterator;
  Code:
   Stack=1, Locals=1, Args_size=1
	aload_0
	invokestatic	Method scala/collection/Iterator$class.zipWithIndex:(Lscala/collection/Iterator;)Lscala/collection/Iterator;
	areturn
  Labels:

public scala.collection.Iterator zipAll(scala.collection.Iterator, java.lang.Object, java.lang.Object);
  Signature: (Lscala/collection/Iterator;Ljava/lang/Object;Ljava/lang/Object;)Lscala/collection/Iterator;
  Code:
   Stack=4, Locals=4, Args_size=4
	aload_0
	aload_1
	aload_2
	aload_3
	invokestatic	Method scala/collection/Iterator$class.zipAll:(Lscala/collection/Iterator;Lscala/collection/Iterator;Ljava/lang/Object;Ljava/lang/Object;)Lscala/collection/Iterator;
	areturn
  Labels:
  LocalVariableTable: 
   Start  Length  Slot  Name   Signature
   0      8      0    this       Lscala/xml/pull/XMLEventReader;
   0      8      1    that       Lscala/collection/Iterator;
   0      8      2    thisElem       Ljava/lang/Object;
   0      8      3    thatElem       Ljava/lang/Object;


public void foreach(scala.Function1);
  Signature: (Lscala/Function1;)V
  Code:
   Stack=2, Locals=2, Args_size=2
	aload_0
	aload_1
	invokestatic	Method scala/collection/Iterator$class.foreach:(Lscala/collection/Iterator;Lscala/Function1;)V
	return
  Labels:
  LocalVariableTable: 
   Start  Length  Slot  Name   Signature
   0      6      0    this       Lscala/xml/pull/XMLEventReader;
   0      6      1    f       Lscala/Function1;


public boolean forall(scala.Function1);
  Signature: (Lscala/Function1;)Z
  Code:
   Stack=2, Locals=2, Args_size=2
	aload_0
	aload_1
	invokestatic	Method scala/collection/Iterator$class.forall:(Lscala/collection/Iterator;Lscala/Function1;)Z
	ireturn
  Labels:
  LocalVariableTable: 
   Start  Length  Slot  Name   Signature
   0      6      0    this       Lscala/xml/pull/XMLEventReader;
   0      6      1    p       Lscala/Function1;


public boolean exists(scala.Function1);
  Signature: (Lscala/Function1;)Z
  Code:
   Stack=2, Locals=2, Args_size=2
	aload_0
	aload_1
	invokestatic	Method scala/collection/Iterator$class.exists:(Lscala/collection/Iterator;Lscala/Function1;)Z
	ireturn
  Labels:
  LocalVariableTable: 
   Start  Length  Slot  Name   Signature
   0      6      0    this       Lscala/xml/pull/XMLEventReader;
   0      6      1    p       Lscala/Function1;


public boolean contains(java.lang.Object);
  Signature: (Ljava/lang/Object;)Z
  Code:
   Stack=2, Locals=2, Args_size=2
	aload_0
	aload_1
	invokestatic	Method scala/collection/Iterator$class.contains:(Lscala/collection/Iterator;Ljava/lang/Object;)Z
	ireturn
  Labels:
  LocalVariableTable: 
   Start  Length  Slot  Name   Signature
   0      6      0    this       Lscala/xml/pull/XMLEventReader;
   0      6      1    elem       Ljava/lang/Object;


public scala.Option find(scala.Function1);
  Signature: (Lscala/Function1;)Lscala/Option;
  Code:
   Stack=2, Locals=2, Args_size=2
	aload_0
	aload_1
	invokestatic	Method scala/collection/Iterator$class.find:(Lscala/collection/Iterator;Lscala/Function1;)Lscala/Option;
	areturn
  Labels:
  LocalVariableTable: 
   Start  Length  Slot  Name   Signature
   0      6      0    this       Lscala/xml/pull/XMLEventReader;
   0      6      1    p       Lscala/Function1;


public int indexWhere(scala.Function1);
  Signature: (Lscala/Function1;)I
  Code:
   Stack=2, Locals=2, Args_size=2
	aload_0
	aload_1
	invokestatic	Method scala/collection/Iterator$class.indexWhere:(Lscala/collection/Iterator;Lscala/Function1;)I
	ireturn
  Labels:
  LocalVariableTable: 
   Start  Length  Slot  Name   Signature
   0      6      0    this       Lscala/xml/pull/XMLEventReader;
   0      6      1    p       Lscala/Function1;


public int indexOf(java.lang.Object);
  Signature: (Ljava/lang/Object;)I
  Code:
   Stack=2, Locals=2, Args_size=2
	aload_0
	aload_1
	invokestatic	Method scala/collection/Iterator$class.indexOf:(Lscala/collection/Iterator;Ljava/lang/Object;)I
	ireturn
  Labels:
  LocalVariableTable: 
   Start  Length  Slot  Name   Signature
   0      6      0    this       Lscala/xml/pull/XMLEventReader;
   0      6      1    elem       Ljava/lang/Object;


public scala.collection.BufferedIterator buffered();
  Signature: ()Lscala/collection/BufferedIterator;
  Code:
   Stack=1, Locals=1, Args_size=1
	aload_0
	invokestatic	Method scala/collection/Iterator$class.buffered:(Lscala/collection/Iterator;)Lscala/collection/BufferedIterator;
	areturn
  Labels:

public scala.collection.Iterator$GroupedIterator grouped(int);
  Signature: (I)Lscala/collection/Iterator$GroupedIterator;
  Code:
   Stack=2, Locals=2, Args_size=2
	aload_0
	iload_1
	invokestatic	Method scala/collection/Iterator$class.grouped:(Lscala/collection/Iterator;I)Lscala/collection/Iterator$GroupedIterator;
	areturn
  Labels:
  LocalVariableTable: 
   Start  Length  Slot  Name   Signature
   0      6      0    this       Lscala/xml/pull/XMLEventReader;
   0      6      1    size       I

  Signature: length = 0x2
   00 FFFFFFCA 

public scala.collection.Iterator$GroupedIterator sliding(int, int);
  Signature: (II)Lscala/collection/Iterator$GroupedIterator;
  Code:
   Stack=3, Locals=3, Args_size=3
	aload_0
	iload_1
	iload_2
	invokestatic	Method scala/collection/Iterator$class.sliding:(Lscala/collection/Iterator;II)Lscala/collection/Iterator$GroupedIterator;
	areturn
  Labels:
  LocalVariableTable: 
   Start  Length  Slot  Name   Signature
   0      7      0    this       Lscala/xml/pull/XMLEventReader;
   0      7      1    size       I
   0      7      2    step       I

  Signature: length = 0x2
   00 FFFFFFD1 

public int length();
  Signature: ()I
  Code:
   Stack=1, Locals=1, Args_size=1
	aload_0
	invokestatic	Method scala/collection/Iterator$class.length:(Lscala/collection/Iterator;)I
	ireturn
  Labels:

public scala.Tuple2 duplicate();
  Signature: ()Lscala/Tuple2;
  Code:
   Stack=1, Locals=1, Args_size=1
	aload_0
	invokestatic	Method scala/collection/Iterator$class.duplicate:(Lscala/collection/Iterator;)Lscala/Tuple2;
	areturn
  Labels:

public scala.collection.Iterator patch(int, scala.collection.Iterator, int);
  Signature: (ILscala/collection/Iterator;I)Lscala/collection/Iterator;
  Code:
   Stack=4, Locals=4, Args_size=4
	aload_0
	iload_1
	aload_2
	iload_3
	invokestatic	Method scala/collection/Iterator$class.patch:(Lscala/collection/Iterator;ILscala/collection/Iterator;I)Lscala/collection/Iterator;
	areturn
  Labels:
  LocalVariableTable: 
   Start  Length  Slot  Name   Signature
   0      8      0    this       Lscala/xml/pull/XMLEventReader;
   0      8      1    from       I
   0      8      2    patchElems       Lscala/collection/Iterator;
   0      8      3    replaced       I


public void copyToArray(java.lang.Object, int, int);
  Signature: (Ljava/lang/Object;II)V
  Code:
   Stack=4, Locals=4, Args_size=4
	aload_0
	aload_1
	iload_2
	iload_3
	invokestatic	Method scala/collection/Iterator$class.copyToArray:(Lscala/collection/Iterator;Ljava/lang/Object;II)V
	return
  Labels:
  LocalVariableTable: 
   Start  Length  Slot  Name   Signature
   0      8      0    this       Lscala/xml/pull/XMLEventReader;
   0      8      1    xs       Ljava/lang/Object;
   0      8      2    start       I
   0      8      3    len       I


public boolean sameElements(scala.collection.Iterator);
  Signature: (Lscala/collection/Iterator;)Z
  Code:
   Stack=2, Locals=2, Args_size=2
	aload_0
	aload_1
	invokestatic	Method scala/collection/Iterator$class.sameElements:(Lscala/collection/Iterator;Lscala/collection/Iterator;)Z
	ireturn
  Labels:
  LocalVariableTable: 
   Start  Length  Slot  Name   Signature
   0      6      0    this       Lscala/xml/pull/XMLEventReader;
   0      6      1    that       Lscala/collection/Iterator;


public scala.collection.Traversable toTraversable();
  Signature: ()Lscala/collection/Traversable;
  Code:
   Stack=1, Locals=1, Args_size=1
	aload_0
	invokestatic	Method scala/collection/Iterator$class.toTraversable:(Lscala/collection/Iterator;)Lscala/collection/Traversable;
	areturn
  Labels:

public scala.collection.Iterator toIterator();
  Signature: ()Lscala/collection/Iterator;
  Code:
   Stack=1, Locals=1, Args_size=1
	aload_0
	invokestatic	Method scala/collection/Iterator$class.toIterator:(Lscala/collection/Iterator;)Lscala/collection/Iterator;
	areturn
  Labels:

public java.lang.String toString();
  Signature: ()Ljava/lang/String;
  Code:
   Stack=1, Locals=1, Args_size=1
	aload_0
	invokestatic	Method scala/collection/Iterator$class.toString:(Lscala/collection/Iterator;)Ljava/lang/String;
	areturn
  Labels:

public scala.collection.Iterator append(scala.collection.Iterator);
  Signature: (Lscala/collection/Iterator;)Lscala/collection/Iterator;
  Code:
   Stack=2, Locals=2, Args_size=2
	aload_0
	aload_1
	invokestatic	Method scala/collection/Iterator$class.append:(Lscala/collection/Iterator;Lscala/collection/Iterator;)Lscala/collection/Iterator;
	areturn
  Labels:
  LocalVariableTable: 
   Start  Length  Slot  Name   Signature
   0      6      0    this       Lscala/xml/pull/XMLEventReader;
   0      6      1    that       Lscala/collection/Iterator;

  Deprecated: true

public int findIndexOf(scala.Function1);
  Signature: (Lscala/Function1;)I
  Code:
   Stack=2, Locals=2, Args_size=2
	aload_0
	aload_1
	invokestatic	Method scala/collection/Iterator$class.findIndexOf:(Lscala/collection/Iterator;Lscala/Function1;)I
	ireturn
  Labels:
  LocalVariableTable: 
   Start  Length  Slot  Name   Signature
   0      6      0    this       Lscala/xml/pull/XMLEventReader;
   0      6      1    p       Lscala/Function1;

  Deprecated: true

public scala.CountedIterator counted();
  Signature: ()Lscala/CountedIterator;
  Code:
   Stack=1, Locals=1, Args_size=1
	aload_0
	invokestatic	Method scala/collection/Iterator$class.counted:(Lscala/collection/Iterator;)Lscala/CountedIterator;
	areturn
  Labels:
  Deprecated: true

public void readInto(java.lang.Object, int, int);
  Signature: (Ljava/lang/Object;II)V
  Code:
   Stack=4, Locals=4, Args_size=4
	aload_0
	aload_1
	iload_2
	iload_3
	invokestatic	Method scala/collection/Iterator$class.readInto:(Lscala/collection/Iterator;Ljava/lang/Object;II)V
	return
  Labels:
  LocalVariableTable: 
   Start  Length  Slot  Name   Signature
   0      8      0    this       Lscala/xml/pull/XMLEventReader;
   0      8      1    xs       Ljava/lang/Object;
   0      8      2    start       I
   0      8      3    sz       I

  Deprecated: true

public void readInto(java.lang.Object, int);
  Signature: (Ljava/lang/Object;I)V
  Code:
   Stack=3, Locals=3, Args_size=3
	aload_0
	aload_1
	iload_2
	invokestatic	Method scala/collection/Iterator$class.readInto:(Lscala/collection/Iterator;Ljava/lang/Object;I)V
	return
  Labels:
  LocalVariableTable: 
   Start  Length  Slot  Name   Signature
   0      7      0    this       Lscala/xml/pull/XMLEventReader;
   0      7      1    xs       Ljava/lang/Object;
   0      7      2    start       I

  Deprecated: true

public void readInto(java.lang.Object);
  Signature: (Ljava/lang/Object;)V
  Code:
   Stack=2, Locals=2, Args_size=2
	aload_0
	aload_1
	invokestatic	Method scala/collection/Iterator$class.readInto:(Lscala/collection/Iterator;Ljava/lang/Object;)V
	return
  Labels:
  LocalVariableTable: 
   Start  Length  Slot  Name   Signature
   0      6      0    this       Lscala/xml/pull/XMLEventReader;
   0      6      1    xs       Ljava/lang/Object;

  Deprecated: true

public int sliding$default$2();
  Signature: ()I
  Code:
   Stack=1, Locals=1, Args_size=1
	aload_0
	invokestatic	Method scala/collection/Iterator$class.sliding$default$2:(Lscala/collection/Iterator;)I
	ireturn
  Labels:

public scala.collection.immutable.List reversed();
  Signature: ()Lscala/collection/immutable/List;
  Code:
   Stack=1, Locals=1, Args_size=1
	aload_0
	invokestatic	Method scala/collection/TraversableOnce$class.reversed:(Lscala/collection/TraversableOnce;)Lscala/collection/immutable/List;
	areturn
  Labels:

public int size();
  Signature: ()I
  Code:
   Stack=1, Locals=1, Args_size=1
	aload_0
	invokestatic	Method scala/collection/TraversableOnce$class.size:(Lscala/collection/TraversableOnce;)I
	ireturn
  Labels:

public boolean nonEmpty();
  Signature: ()Z
  Code:
   Stack=1, Locals=1, Args_size=1
	aload_0
	invokestatic	Method scala/collection/TraversableOnce$class.nonEmpty:(Lscala/collection/TraversableOnce;)Z
	ireturn
  Labels:

public int count(scala.Function1);
  Signature: (Lscala/Function1;)I
  Code:
   Stack=2, Locals=2, Args_size=2
	aload_0
	aload_1
	invokestatic	Method scala/collection/TraversableOnce$class.count:(Lscala/collection/TraversableOnce;Lscala/Function1;)I
	ireturn
  Labels:
  LocalVariableTable: 
   Start  Length  Slot  Name   Signature
   0      6      0    this       Lscala/xml/pull/XMLEventReader;
   0      6      1    p       Lscala/Function1;


public java.lang.Object $div$colon(java.lang.Object, scala.Function2);
  Signature: (Ljava/lang/Object;Lscala/Function2;)Ljava/lang/Object;
  Code:
   Stack=3, Locals=3, Args_size=3
	aload_0
	aload_1
	aload_2
	invokestatic	Method scala/collection/TraversableOnce$class.$div$colon:(Lscala/collection/TraversableOnce;Ljava/lang/Object;Lscala/Function2;)Ljava/lang/Object;
	areturn
  Labels:
  LocalVariableTable: 
   Start  Length  Slot  Name   Signature
   0      7      0    this       Lscala/xml/pull/XMLEventReader;
   0      7      1    z       Ljava/lang/Object;
   0      7      2    op       Lscala/Function2;


public java.lang.Object $colon$bslash(java.lang.Object, scala.Function2);
  Signature: (Ljava/lang/Object;Lscala/Function2;)Ljava/lang/Object;
  Code:
   Stack=3, Locals=3, Args_size=3
	aload_0
	aload_1
	aload_2
	invokestatic	Method scala/collection/TraversableOnce$class.$colon$bslash:(Lscala/collection/TraversableOnce;Ljava/lang/Object;Lscala/Function2;)Ljava/lang/Object;
	areturn
  Labels:
  LocalVariableTable: 
   Start  Length  Slot  Name   Signature
   0      7      0    this       Lscala/xml/pull/XMLEventReader;
   0      7      1    z       Ljava/lang/Object;
   0      7      2    op       Lscala/Function2;


public java.lang.Object foldLeft(java.lang.Object, scala.Function2);
  Signature: (Ljava/lang/Object;Lscala/Function2;)Ljava/lang/Object;
  Code:
   Stack=3, Locals=3, Args_size=3
	aload_0
	aload_1
	aload_2
	invokestatic	Method scala/collection/TraversableOnce$class.foldLeft:(Lscala/collection/TraversableOnce;Ljava/lang/Object;Lscala/Function2;)Ljava/lang/Object;
	areturn
  Labels:
  LocalVariableTable: 
   Start  Length  Slot  Name   Signature
   0      7      0    this       Lscala/xml/pull/XMLEventReader;
   0      7      1    z       Ljava/lang/Object;
   0      7      2    op       Lscala/Function2;


public java.lang.Object foldRight(java.lang.Object, scala.Function2);
  Signature: (Ljava/lang/Object;Lscala/Function2;)Ljava/lang/Object;
  Code:
   Stack=3, Locals=3, Args_size=3
	aload_0
	aload_1
	aload_2
	invokestatic	Method scala/collection/TraversableOnce$class.foldRight:(Lscala/collection/TraversableOnce;Ljava/lang/Object;Lscala/Function2;)Ljava/lang/Object;
	areturn
  Labels:
  LocalVariableTable: 
   Start  Length  Slot  Name   Signature
   0      7      0    this       Lscala/xml/pull/XMLEventReader;
   0      7      1    z       Ljava/lang/Object;
   0      7      2    op       Lscala/Function2;


public java.lang.Object reduceLeft(scala.Function2);
  Signature: (Lscala/Function2;)Ljava/lang/Object;
  Code:
   Stack=2, Locals=2, Args_size=2
	aload_0
	aload_1
	invokestatic	Method scala/collection/TraversableOnce$class.reduceLeft:(Lscala/collection/TraversableOnce;Lscala/Function2;)Ljava/lang/Object;
	areturn
  Labels:
  LocalVariableTable: 
   Start  Length  Slot  Name   Signature
   0      6      0    this       Lscala/xml/pull/XMLEventReader;
   0      6      1    op       Lscala/Function2;


public java.lang.Object reduceRight(scala.Function2);
  Signature: (Lscala/Function2;)Ljava/lang/Object;
  Code:
   Stack=2, Locals=2, Args_size=2
	aload_0
	aload_1
	invokestatic	Method scala/collection/TraversableOnce$class.reduceRight:(Lscala/collection/TraversableOnce;Lscala/Function2;)Ljava/lang/Object;
	areturn
  Labels:
  LocalVariableTable: 
   Start  Length  Slot  Name   Signature
   0      6      0    this       Lscala/xml/pull/XMLEventReader;
   0      6      1    op       Lscala/Function2;


public scala.Option reduceLeftOption(scala.Function2);
  Signature: (Lscala/Function2;)Lscala/Option;
  Code:
   Stack=2, Locals=2, Args_size=2
	aload_0
	aload_1
	invokestatic	Method scala/collection/TraversableOnce$class.reduceLeftOption:(Lscala/collection/TraversableOnce;Lscala/Function2;)Lscala/Option;
	areturn
  Labels:
  LocalVariableTable: 
   Start  Length  Slot  Name   Signature
   0      6      0    this       Lscala/xml/pull/XMLEventReader;
   0      6      1    op       Lscala/Function2;


public scala.Option reduceRightOption(scala.Function2);
  Signature: (Lscala/Function2;)Lscala/Option;
  Code:
   Stack=2, Locals=2, Args_size=2
	aload_0
	aload_1
	invokestatic	Method scala/collection/TraversableOnce$class.reduceRightOption:(Lscala/collection/TraversableOnce;Lscala/Function2;)Lscala/Option;
	areturn
  Labels:
  LocalVariableTable: 
   Start  Length  Slot  Name   Signature
   0      6      0    this       Lscala/xml/pull/XMLEventReader;
   0      6      1    op       Lscala/Function2;


public java.lang.Object sum(scala.math.Numeric);
  Signature: (Lscala/math/Numeric;)Ljava/lang/Object;
  Code:
   Stack=2, Locals=2, Args_size=2
	aload_0
	aload_1
	invokestatic	Method scala/collection/TraversableOnce$class.sum:(Lscala/collection/TraversableOnce;Lscala/math/Numeric;)Ljava/lang/Object;
	areturn
  Labels:
  LocalVariableTable: 
   Start  Length  Slot  Name   Signature
   0      6      0    this       Lscala/xml/pull/XMLEventReader;
   0      6      1    num       Lscala/math/Numeric;


public java.lang.Object product(scala.math.Numeric);
  Signature: (Lscala/math/Numeric;)Ljava/lang/Object;
  Code:
   Stack=2, Locals=2, Args_size=2
	aload_0
	aload_1
	invokestatic	Method scala/collection/TraversableOnce$class.product:(Lscala/collection/TraversableOnce;Lscala/math/Numeric;)Ljava/lang/Object;
	areturn
  Labels:
  LocalVariableTable: 
   Start  Length  Slot  Name   Signature
   0      6      0    this       Lscala/xml/pull/XMLEventReader;
   0      6      1    num       Lscala/math/Numeric;


public java.lang.Object min(scala.math.Ordering);
  Signature: (Lscala/math/Ordering;)Ljava/lang/Object;
  Code:
   Stack=2, Locals=2, Args_size=2
	aload_0
	aload_1
	invokestatic	Method scala/collection/TraversableOnce$class.min:(Lscala/collection/TraversableOnce;Lscala/math/Ordering;)Ljava/lang/Object;
	areturn
  Labels:
  LocalVariableTable: 
   Start  Length  Slot  Name   Signature
   0      6      0    this       Lscala/xml/pull/XMLEventReader;
   0      6      1    cmp       Lscala/math/Ordering;


public java.lang.Object max(scala.math.Ordering);
  Signature: (Lscala/math/Ordering;)Ljava/lang/Object;
  Code:
   Stack=2, Locals=2, Args_size=2
	aload_0
	aload_1
	invokestatic	Method scala/collection/TraversableOnce$class.max:(Lscala/collection/TraversableOnce;Lscala/math/Ordering;)Ljava/lang/Object;
	areturn
  Labels:
  LocalVariableTable: 
   Start  Length  Slot  Name   Signature
   0      6      0    this       Lscala/xml/pull/XMLEventReader;
   0      6      1    cmp       Lscala/math/Ordering;


public void copyToBuffer(scala.collection.mutable.Buffer);
  Signature: (Lscala/collection/mutable/Buffer;)V
  Code:
   Stack=2, Locals=2, Args_size=2
	aload_0
	aload_1
	invokestatic	Method scala/collection/TraversableOnce$class.copyToBuffer:(Lscala/collection/TraversableOnce;Lscala/collection/mutable/Buffer;)V
	return
  Labels:
  LocalVariableTable: 
   Start  Length  Slot  Name   Signature
   0      6      0    this       Lscala/xml/pull/XMLEventReader;
   0      6      1    dest       Lscala/collection/mutable/Buffer;


public void copyToArray(java.lang.Object, int);
  Signature: (Ljava/lang/Object;I)V
  Code:
   Stack=3, Locals=3, Args_size=3
	aload_0
	aload_1
	iload_2
	invokestatic	Method scala/collection/TraversableOnce$class.copyToArray:(Lscala/collection/TraversableOnce;Ljava/lang/Object;I)V
	return
  Labels:
  LocalVariableTable: 
   Start  Length  Slot  Name   Signature
   0      7      0    this       Lscala/xml/pull/XMLEventReader;
   0      7      1    xs       Ljava/lang/Object;
   0      7      2    start       I


public void copyToArray(java.lang.Object);
  Signature: (Ljava/lang/Object;)V
  Code:
   Stack=2, Locals=2, Args_size=2
	aload_0
	aload_1
	invokestatic	Method scala/collection/TraversableOnce$class.copyToArray:(Lscala/collection/TraversableOnce;Ljava/lang/Object;)V
	return
  Labels:
  LocalVariableTable: 
   Start  Length  Slot  Name   Signature
   0      6      0    this       Lscala/xml/pull/XMLEventReader;
   0      6      1    xs       Ljava/lang/Object;


public java.lang.Object toArray(scala.reflect.ClassManifest);
  Signature: (Lscala/reflect/ClassManifest;)Ljava/lang/Object;
  Code:
   Stack=2, Locals=2, Args_size=2
	aload_0
	aload_1
	invokestatic	Method scala/collection/TraversableOnce$class.toArray:(Lscala/collection/TraversableOnce;Lscala/reflect/ClassManifest;)Ljava/lang/Object;
	areturn
  Labels:
  LocalVariableTable: 
   Start  Length  Slot  Name   Signature
   0      6      0    this       Lscala/xml/pull/XMLEventReader;
   0      6      1    evidence$1       Lscala/reflect/ClassManifest;


public scala.collection.immutable.List toList();
  Signature: ()Lscala/collection/immutable/List;
  Code:
   Stack=1, Locals=1, Args_size=1
	aload_0
	invokestatic	Method scala/collection/TraversableOnce$class.toList:(Lscala/collection/TraversableOnce;)Lscala/collection/immutable/List;
	areturn
  Labels:

public scala.collection.Iterable toIterable();
  Signature: ()Lscala/collection/Iterable;
  Code:
   Stack=1, Locals=1, Args_size=1
	aload_0
	invokestatic	Method scala/collection/TraversableOnce$class.toIterable:(Lscala/collection/TraversableOnce;)Lscala/collection/Iterable;
	areturn
  Labels:

public scala.collection.Seq toSeq();
  Signature: ()Lscala/collection/Seq;
  Code:
   Stack=1, Locals=1, Args_size=1
	aload_0
	invokestatic	Method scala/collection/TraversableOnce$class.toSeq:(Lscala/collection/TraversableOnce;)Lscala/collection/Seq;
	areturn
  Labels:

public scala.collection.mutable.IndexedSeq toIndexedSeq();
  Signature: ()Lscala/collection/mutable/IndexedSeq;
  Code:
   Stack=1, Locals=1, Args_size=1
	aload_0
	invokestatic	Method scala/collection/TraversableOnce$class.toIndexedSeq:(Lscala/collection/TraversableOnce;)Lscala/collection/mutable/IndexedSeq;
	areturn
  Labels:

public scala.collection.immutable.Stream toStream();
  Signature: ()Lscala/collection/immutable/Stream;
  Code:
   Stack=1, Locals=1, Args_size=1
	aload_0
	invokestatic	Method scala/collection/TraversableOnce$class.toStream:(Lscala/collection/TraversableOnce;)Lscala/collection/immutable/Stream;
	areturn
  Labels:

public scala.collection.immutable.Set toSet();
  Signature: ()Lscala/collection/immutable/Set;
  Code:
   Stack=1, Locals=1, Args_size=1
	aload_0
	invokestatic	Method scala/collection/TraversableOnce$class.toSet:(Lscala/collection/TraversableOnce;)Lscala/collection/immutable/Set;
	areturn
  Labels:

public scala.collection.immutable.Map toMap(scala.Predef$$less$colon$less);
  Signature: (Lscala/Predef$$less$colon$less;)Lscala/collection/immutable/Map;
  Code:
   Stack=2, Locals=2, Args_size=2
	aload_0
	aload_1
	invokestatic	Method scala/collection/TraversableOnce$class.toMap:(Lscala/collection/TraversableOnce;Lscala/Predef$$less$colon$less;)Lscala/collection/immutable/Map;
	areturn
  Labels:
  LocalVariableTable: 
   Start  Length  Slot  Name   Signature
   0      6      0    this       Lscala/xml/pull/XMLEventReader;
   0      6      1    ev       Lscala/Predef$$less$colon$less;


public java.lang.String mkString(java.lang.String, java.lang.String, java.lang.String);
  Signature: (Ljava/lang/String;Ljava/lang/String;Ljava/lang/String;)Ljava/lang/String;
  Code:
   Stack=4, Locals=4, Args_size=4
	aload_0
	aload_1
	aload_2
	aload_3
	invokestatic	Method scala/collection/TraversableOnce$class.mkString:(Lscala/collection/TraversableOnce;Ljava/lang/String;Ljava/lang/String;Ljava/lang/String;)Ljava/lang/String;
	areturn
  Labels:
  LocalVariableTable: 
   Start  Length  Slot  Name   Signature
   0      8      0    this       Lscala/xml/pull/XMLEventReader;
   0      8      1    start       Ljava/lang/String;
   0      8      2    sep       Ljava/lang/String;
   0      8      3    end       Ljava/lang/String;


public java.lang.String mkString(java.lang.String);
  Signature: (Ljava/lang/String;)Ljava/lang/String;
  Code:
   Stack=2, Locals=2, Args_size=2
	aload_0
	aload_1
	invokestatic	Method scala/collection/TraversableOnce$class.mkString:(Lscala/collection/TraversableOnce;Ljava/lang/String;)Ljava/lang/String;
	areturn
  Labels:
  LocalVariableTable: 
   Start  Length  Slot  Name   Signature
   0      6      0    this       Lscala/xml/pull/XMLEventReader;
   0      6      1    sep       Ljava/lang/String;


public java.lang.String mkString();
  Signature: ()Ljava/lang/String;
  Code:
   Stack=1, Locals=1, Args_size=1
	aload_0
	invokestatic	Method scala/collection/TraversableOnce$class.mkString:(Lscala/collection/TraversableOnce;)Ljava/lang/String;
	areturn
  Labels:

public scala.collection.mutable.StringBuilder addString(scala.collection.mutable.StringBuilder, java.lang.String, java.lang.String, java.lang.String);
  Signature: (Lscala/collection/mutable/StringBuilder;Ljava/lang/String;Ljava/lang/String;Ljava/lang/String;)Lscala/collection/mutable/StringBuilder;
  Code:
   Stack=5, Locals=5, Args_size=5
	aload_0
	aload_1
	aload_2
	aload_3
	aload	4
	invokestatic	Method scala/collection/TraversableOnce$class.addString:(Lscala/collection/TraversableOnce;Lscala/collection/mutable/StringBuilder;Ljava/lang/String;Ljava/lang/String;Ljava/lang/String;)Lscala/collection/mutable/StringBuilder;
	areturn
  Labels:
  LocalVariableTable: 
   Start  Length  Slot  Name   Signature
   0      10      0    this       Lscala/xml/pull/XMLEventReader;
   0      10      1    b       Lscala/collection/mutable/StringBuilder;
   0      10      2    start       Ljava/lang/String;
   0      10      3    sep       Ljava/lang/String;
   0      10      4    end       Ljava/lang/String;


public scala.collection.mutable.StringBuilder addString(scala.collection.mutable.StringBuilder, java.lang.String);
  Signature: (Lscala/collection/mutable/StringBuilder;Ljava/lang/String;)Lscala/collection/mutable/StringBuilder;
  Code:
   Stack=3, Locals=3, Args_size=3
	aload_0
	aload_1
	aload_2
	invokestatic	Method scala/collection/TraversableOnce$class.addString:(Lscala/collection/TraversableOnce;Lscala/collection/mutable/StringBuilder;Ljava/lang/String;)Lscala/collection/mutable/StringBuilder;
	areturn
  Labels:
  LocalVariableTable: 
   Start  Length  Slot  Name   Signature
   0      7      0    this       Lscala/xml/pull/XMLEventReader;
   0      7      1    b       Lscala/collection/mutable/StringBuilder;
   0      7      2    sep       Ljava/lang/String;


public scala.collection.mutable.StringBuilder addString(scala.collection.mutable.StringBuilder);
  Signature: (Lscala/collection/mutable/StringBuilder;)Lscala/collection/mutable/StringBuilder;
  Code:
   Stack=2, Locals=2, Args_size=2
	aload_0
	aload_1
	invokestatic	Method scala/collection/TraversableOnce$class.addString:(Lscala/collection/TraversableOnce;Lscala/collection/mutable/StringBuilder;)Lscala/collection/mutable/StringBuilder;
	areturn
  Labels:
  LocalVariableTable: 
   Start  Length  Slot  Name   Signature
   0      6      0    this       Lscala/xml/pull/XMLEventReader;
   0      6      1    b       Lscala/collection/mutable/StringBuilder;


public boolean preserveWS();
  Signature: ()Z
  Code:
   Stack=1, Locals=1, Args_size=1
	aload_0
	getfield	Field preserveWS:Z
	ireturn
  Labels:

public int MaxQueueSize();
  Signature: ()I
  Code:
   Stack=1, Locals=1, Args_size=1
	aload_0
	getfield	Field MaxQueueSize:I
	ireturn
  Labels:

public final scala.xml.pull.XMLEventReader$POISON$ POISON();
  Signature: ()Lscala/xml/pull/XMLEventReader$POISON$;
  Code:
   Stack=4, Locals=1, Args_size=1
	aload_0
	getfield	Field POISON$module:Lscala/xml/pull/XMLEventReader$POISON$;
	ifnonnull	l1 // aload_0
	aload_0
	new	class scala/xml/pull/XMLEventReader$POISON$
	dup
	aload_0
	invokespecial	Method scala/xml/pull/XMLEventReader$POISON$."<init>":(Lscala/xml/pull/XMLEventReader;)V
	putfield	Field POISON$module:Lscala/xml/pull/XMLEventReader$POISON$;
l1	aload_0
	getfield	Field POISON$module:Lscala/xml/pull/XMLEventReader$POISON$;
	areturn
  Labels:
   	l1 = 19 // aload_0

public scala.xml.pull.XMLEventReader$POISON$ EndOfStream();
  Signature: ()Lscala/xml/pull/XMLEventReader$POISON$;
  Code:
   Stack=1, Locals=1, Args_size=1
	aload_0
	getfield	Field EndOfStream:Lscala/xml/pull/XMLEventReader$POISON$;
	areturn
  Labels:

public void stop();
  Signature: ()V
  Code:
   Stack=2, Locals=1, Args_size=1
	aload_0
	aload_0
	invokevirtual	Method POISON:()Lscala/xml/pull/XMLEventReader$POISON$;
	invokeinterface	InterfaceMethod scala/xml/pull/ProducerConsumerIterator.produce:(Ljava/lang/Object;)V
	aload_0
	getfield	Field parserThread:Ljava/lang/Thread;
	invokevirtual	Method java/lang/Thread.interrupt:()V
	return
  Labels:

public java.lang.Object EndOfStream();
  Signature: ()Ljava/lang/Object;
  Code:
   Stack=1, Locals=1, Args_size=1
	aload_0
	invokevirtual	Method EndOfStream:()Lscala/xml/pull/XMLEventReader$POISON$;
	areturn
  Labels:

public scala.xml.pull.XMLEventReader(scala.io.Source);
  Signature: (Lscala/io/Source;)V
  Code:
   Stack=5, Locals=2, Args_size=2
	aload_0
	invokespecial	Method java/lang/Object."<init>":()V
	aload_0
	invokestatic	Method scala/collection/TraversableOnce$class.$init$:(Lscala/collection/TraversableOnce;)V
	aload_0
	invokestatic	Method scala/collection/Iterator$class.$init$:(Lscala/collection/Iterator;)V
	aload_0
	invokestatic	Method scala/xml/pull/ProducerConsumerIterator$class.$init$:(Lscala/xml/pull/ProducerConsumerIterator;)V
	aload_0
	iconst_1
	putfield	Field preserveWS:Z
	aload_0
	ldc_w	int 1000
	putfield	Field MaxQueueSize:I
	aload_0
	aload_0
	invokevirtual	Method POISON:()Lscala/xml/pull/XMLEventReader$POISON$;
	putfield	Field EndOfStream:Lscala/xml/pull/XMLEventReader$POISON$;
	aload_0
	new	class scala/xml/pull/XMLEventReader$Parser
	dup
	aload_0
	aload_1
	invokespecial	Method scala/xml/pull/XMLEventReader$Parser."<init>":(Lscala/xml/pull/XMLEventReader;Lscala/io/Source;)V
	putfield	Field parser:Lscala/xml/pull/XMLEventReader$Parser;
	aload_0
	new	class java/lang/Thread
	dup
	aload_0
	getfield	Field parser:Lscala/xml/pull/XMLEventReader$Parser;
	ldc_w	String XMLEventReader
	invokespecial	Method java/lang/Thread."<init>":(Ljava/lang/Runnable;Ljava/lang/String;)V
	putfield	Field parserThread:Ljava/lang/Thread;
	aload_0
	getfield	Field parserThread:Ljava/lang/Thread;
	invokevirtual	Method java/lang/Thread.start:()V
	return
  Labels:
  LocalVariableTable: 
   Start  Length  Slot  Name   Signature
   0      75      0    this       Lscala/xml/pull/XMLEventReader;
   0      75      1    src       Lscala/io/Source;


}

