Compiled from "XIncludeException.scala"
public class scala.xml.include.XIncludeException extends java.lang.Exception implements scala.ScalaObject
  SourceFile: "XIncludeException.scala"
  ScalaSig: length = 0x1D4
   05 00 48 06 08 01 02 FFFFFF84 FFFFFF80 FFFFFF80 FFFFFF80 00 09 02 11 58
   49 6E 63 6C 75 64 65 45 78 63 65 70 74 69 6F 6E
   0A 02 03 04 01 07 69 6E 63 6C 75 64 65 0A 02 05
   06 01 03 78 6D 6C 0A 01 07 01 05 73 63 61 6C 61
   03 00 13 03 00 0A 12 10 02 0B 10 0D 01 0C 0A 02
   0D 0E 01 04 6C 61 6E 67 0A 01 0F 01 04 6A 61 76
   61 09 02 11 0C 02 09 45 78 63 65 70 74 69 6F 6E
   10 02 13 14 0D 01 06 09 02 15 06 02 0B 53 63 61
   6C 61 4F 62 6A 65 63 74 08 08 17 00 FFFFFF82 FFFFFF80 FFFFFFA0 FFFFFF80
   04 18 01 07 6D 65 73 73 61 67 65 10 02 19 1C 0E
   02 13 1A 09 02 1B 06 01 06 50 72 65 64 65 66 09
   02 1D 1E 02 06 53 74 72 69 6E 67 0A 02 1B 06 08
   05 20 00 FFFFFF84 00 21 01 06 3C 69 6E 69 74 3E 14 02
   22 24 10 02 23 00 0D 01 02 08 05 17 1F FFFFFFC0 00 18
   08 05 20 00 FFFFFF84 00 26 14 01 22 08 07 28 00 FFFFFFC0 FFFFFF80
   FFFFFF84 04 29 01 09 72 6F 6F 74 43 61 75 73 65 15 01
   2A 10 02 2B 33 0E 02 2C 31 0E 02 2D 30 0D 01 2E
   0A 02 2F 08 01 06 3C 72 6F 6F 74 3E 09 01 07 09
   02 32 06 01 07 70 61 63 6B 61 67 65 09 02 34 35
   02 09 54 68 72 6F 77 61 62 6C 65 0A 02 32 06 08
   07 37 00 FFFFFFC0 FFFFFF80 FFFFFF84 04 38 01 0D 72 6F 6F 74 43 61
   75 73 65 5F 24 65 71 14 02 39 3C 10 02 13 3A 09
   02 3B 06 02 04 55 6E 69 74 08 07 3D 36 FFFFFF81 FFFFFF80 FFFFFFC0
   00 2A 01 03 78 24 31 08 06 3F 00 FFFFFFA0 FFFFFFA0 04 2A 01
   0A 72 6F 6F 74 43 61 75 73 65 20 08 05 41 00 FFFFFF84
   00 42 01 0C 73 65 74 52 6F 6F 74 43 61 75 73 65
   14 02 39 43 08 05 44 40 FFFFFFC0 00 2A 01 0F 6E 65 73
   74 65 64 45 78 63 65 70 74 69 6F 6E 08 05 46 00
   FFFFFF84 00 47 01 0C 67 65 74 52 6F 6F 74 43 61 75 73
   65 14 01 2A 
  minor version: 0
  major version: 49
  Constant pool:
Asciz	SourceFile;
Asciz	XIncludeException.scala;
Asciz	rootCause;
Asciz	Ljava/lang/Throwable;;
Asciz	<init>;
Asciz	()V;
Asciz	Code;
Asciz	LineNumberTable;
Asciz	scala/xml/include/XIncludeException;
class	scala/xml/include/XIncludeException
Asciz	(Ljava/lang/String;)V;
NameAndType	"<init>":(Ljava/lang/String;)V
Method	scala/xml/include/XIncludeException."<init>":(Ljava/lang/String;)V
Asciz	()Ljava/lang/Throwable;;
NameAndType	rootCause:Ljava/lang/Throwable;
Field	scala/xml/include/XIncludeException.rootCause:Ljava/lang/Throwable;
Asciz	rootCause_$eq;
Asciz	(Ljava/lang/Throwable;)V;
Asciz	setRootCause;
NameAndType	rootCause_$eq:(Ljava/lang/Throwable;)V
Method	scala/xml/include/XIncludeException.rootCause_$eq:(Ljava/lang/Throwable;)V
Asciz	this;
Asciz	Lscala/xml/include/XIncludeException;;
Asciz	nestedException;
Asciz	LocalVariableTable;
Asciz	getRootCause;
NameAndType	rootCause:()Ljava/lang/Throwable;
Method	scala/xml/include/XIncludeException.rootCause:()Ljava/lang/Throwable;
Asciz	java/lang/Exception;
class	java/lang/Exception
Method	java/lang/Exception."<init>":(Ljava/lang/String;)V
Asciz	message;
Asciz	Ljava/lang/String;;
Asciz	ScalaSig;
Asciz	scala/ScalaObject;
class	scala/ScalaObject

{
private java.lang.Throwable rootCause;
  Signature: Ljava/lang/Throwable;

public scala.xml.include.XIncludeException();
  Signature: ()V
  Code:
   Stack=2, Locals=1, Args_size=1
	aload_0
	aconst_null
	invokespecial	Method "<init>":(Ljava/lang/String;)V
	return
  Labels:

private java.lang.Throwable rootCause();
  Signature: ()Ljava/lang/Throwable;
  Code:
   Stack=1, Locals=1, Args_size=1
	aload_0
	getfield	Field rootCause:Ljava/lang/Throwable;
	areturn
  Labels:

private void rootCause_$eq(java.lang.Throwable);
  Signature: (Ljava/lang/Throwable;)V
  Code:
   Stack=2, Locals=2, Args_size=2
	aload_0
	aload_1
	putfield	Field rootCause:Ljava/lang/Throwable;
	return
  Labels:

public void setRootCause(java.lang.Throwable);
  Signature: (Ljava/lang/Throwable;)V
  Code:
   Stack=2, Locals=2, Args_size=2
	aload_0
	aload_1
	invokespecial	Method rootCause_$eq:(Ljava/lang/Throwable;)V
	return
  Labels:
  LocalVariableTable: 
   Start  Length  Slot  Name   Signature
   0      6      0    this       Lscala/xml/include/XIncludeException;
   0      6      1    nestedException       Ljava/lang/Throwable;


public java.lang.Throwable getRootCause();
  Signature: ()Ljava/lang/Throwable;
  Code:
   Stack=1, Locals=1, Args_size=1
	aload_0
	invokespecial	Method rootCause:()Ljava/lang/Throwable;
	areturn
  Labels:

public scala.xml.include.XIncludeException(java.lang.String);
  Signature: (Ljava/lang/String;)V
  Code:
   Stack=2, Locals=2, Args_size=2
	aload_0
	aload_1
	invokespecial	Method java/lang/Exception."<init>":(Ljava/lang/String;)V
	aload_0
	aconst_null
	putfield	Field rootCause:Ljava/lang/Throwable;
	return
  Labels:
  LocalVariableTable: 
   Start  Length  Slot  Name   Signature
   0      11      0    this       Lscala/xml/include/XIncludeException;
   0      11      1    message       Ljava/lang/String;


}

