Compiled from "Proxy.scala"
public class scala.actors.remote.Apply0 extends java.lang.Object implements scala.ScalaObject,scala.Product,java.io.Serializable
  SourceFile: "Proxy.scala"
  ScalaSig: length = 0x37B
   05 00 FFFFFF81 07 06 09 01 02 FFFFFF84 FFFFFF80 FFFFFF80 FFFFFF80 40 02 08 02
   06 41 70 70 6C 79 30 0A 02 03 04 01 06 72 65 6D
   6F 74 65 0A 02 05 06 01 06 61 63 74 6F 72 73 0A
   01 07 01 05 73 63 61 6C 61 13 04 00 09 11 15 10
   02 0A 0F 0D 01 0B 0A 02 0C 0D 01 04 6C 61 6E 67
   0A 01 0E 01 04 6A 61 76 61 09 02 10 0B 02 06 4F
   62 6A 65 63 74 10 02 12 13 0D 01 06 09 02 14 06
   02 0B 53 63 61 6C 61 4F 62 6A 65 63 74 10 02 12
   16 09 02 17 06 02 07 50 72 6F 64 75 63 74 08 08
   19 00 FFFFFF82 FFFFFFCA FFFFFF80 FFFFFF84 00 1B 01 04 72 66 75 6E 03 00
   15 01 1C 10 05 12 1D 1F 23 27 09 02 1E 06 02 09
   46 75 6E 63 74 69 6F 6E 32 10 02 20 21 0D 01 04
   09 02 22 04 02 0D 41 62 73 74 72 61 63 74 41 63
   74 6F 72 10 02 24 25 0D 01 02 09 02 26 02 02 05
   50 72 6F 78 79 10 02 12 28 09 02 29 06 02 04 55
   6E 69 74 08 08 2B 00 FFFFFF82 FFFFFF88 FFFFFFA0 FFFFFF80 04 1C 01 05 72
   66 75 6E 20 08 05 2D 00 FFFFFF84 00 2E 01 06 3C 69 6E
   69 74 3E 14 02 2F 30 10 02 24 00 08 05 19 2C FFFFFFC0
   00 1C 08 07 32 00 FFFFFF81 FFFFFF80 FFFFFF84 00 33 01 04 63 6F 70
   79 14 02 2F 34 08 07 19 31 FFFFFF90 FFFFFF80 FFFFFFC0 00 1C 08 07
   36 00 FFFFFF91 FFFFFF80 FFFFFF84 00 37 01 0E 63 6F 70 79 24 64 65
   66 61 75 6C 74 24 31 15 01 38 2A 02 1C 39 2B 01
   3A 10 02 3B 40 0D 01 3C 0A 02 3D 3E 01 09 75 6E
   63 68 65 63 6B 65 64 0A 02 3F 06 01 0A 61 6E 6E
   6F 74 61 74 69 6F 6E 09 02 41 3C 02 11 75 6E 63
   68 65 63 6B 65 64 56 61 72 69 61 6E 63 65 08 08
   43 00 FFFFFF84 FFFFFF80 FFFFFF80 FFFFFF84 20 44 01 08 68 61 73 68 43 6F
   64 65 14 01 45 10 02 12 46 09 02 47 06 02 03 49
   6E 74 08 08 49 00 FFFFFF84 FFFFFF80 FFFFFF80 FFFFFF84 20 4A 01 08 74 6F
   53 74 72 69 6E 67 14 01 4B 10 02 4C 4F 0E 02 12
   4D 09 02 4E 06 01 06 50 72 65 64 65 66 09 02 50
   51 02 06 53 74 72 69 6E 67 0A 02 4E 06 08 08 53
   00 FFFFFF84 FFFFFF80 FFFFFF80 FFFFFF84 20 54 01 06 65 71 75 61 6C 73 14
   02 55 58 10 02 12 56 09 02 57 06 02 07 42 6F 6F
   6C 65 61 6E 08 07 59 52 FFFFFF81 FFFFFF80 FFFFFFC0 00 5A 01 03 78
   24 31 10 02 12 5B 09 02 5C 06 02 03 41 6E 79 08
   08 5E 00 FFFFFF84 FFFFFF80 FFFFFF80 FFFFFF84 20 5F 01 0D 70 72 6F 64 75
   63 74 50 72 65 66 69 78 15 01 60 10 02 0A 61 09
   02 50 0B 08 08 63 00 FFFFFF84 FFFFFF80 FFFFFF80 FFFFFF84 20 64 01 0C 70
   72 6F 64 75 63 74 41 72 69 74 79 15 01 45 08 08
   66 00 FFFFFF84 FFFFFF80 FFFFFF80 FFFFFF84 20 67 01 0E 70 72 6F 64 75 63
   74 45 6C 65 6D 65 6E 74 14 02 5A 68 08 07 59 65
   FFFFFF81 FFFFFF80 FFFFFFC0 00 45 08 08 6A 00 FFFFFF84 FFFFFF80 FFFFFF80 FFFFFF84 20 6B 01
   08 63 61 6E 45 71 75 61 6C 14 02 55 6C 08 07 59
   69 FFFFFF81 FFFFFF80 FFFFFFC0 00 5A 28 02 00 6E 10 02 12 6F 09 02
   70 06 02 0C 73 65 72 69 61 6C 69 7A 61 62 6C 65
   07 08 72 02 FFFFFF81 FFFFFF80 FFFFFF88 02 02 73 01 06 41 70 70 6C
   79 30 10 02 24 74 06 09 01 02 FFFFFF84 FFFFFF81 FFFFFF80 FFFFFF88 02 02
   75 13 04 74 09 76 11 10 04 12 77 1C 2F 09 02 78
   06 02 09 46 75 6E 63 74 69 6F 6E 31 08 05 2D 74
   FFFFFF84 00 7A 14 01 73 08 07 7C 74 FFFFFF81 FFFFFF80 FFFFFF84 40 7D 01
   05 61 70 70 6C 79 14 02 2F 7E 08 05 19 7B FFFFFFC0 00
   1C 08 09 FFFFFF81 00 74 FFFFFF81 FFFFFF80 FFFFFF84 40 FFFFFF81 01 01 07 75 6E
   61 70 70 6C 79 14 04 FFFFFF81 02 FFFFFF81 05 10 04 12 FFFFFF81 03
   1C 09 03 FFFFFF81 04 06 02 06 4F 70 74 69 6F 6E 08 06
   FFFFFF81 06 7F FFFFFFC0 00 2F 01 03 78 24 30 
  minor version: 0
  major version: 49
  Constant pool:
Asciz	SourceFile;
Asciz	Proxy.scala;
Asciz	andThen;
Asciz	(Lscala/Function1;)Lscala/Function1;;
Asciz	Code;
Asciz	scala/actors/remote/Apply0$;
class	scala/actors/remote/Apply0$
Asciz	MODULE$;
Asciz	Lscala/actors/remote/Apply0$;;
NameAndType	MODULE$:Lscala/actors/remote/Apply0$;
Field	scala/actors/remote/Apply0$.MODULE$:Lscala/actors/remote/Apply0$;
NameAndType	andThen:(Lscala/Function1;)Lscala/Function1;
Method	scala/actors/remote/Apply0$.andThen:(Lscala/Function1;)Lscala/Function1;
Asciz	compose;
NameAndType	compose:(Lscala/Function1;)Lscala/Function1;
Method	scala/actors/remote/Apply0$.compose:(Lscala/Function1;)Lscala/Function1;
Asciz	rfun;
Asciz	Lscala/Function2;;
Asciz	Lscala/Function2<Lscala/actors/AbstractActor;Lscala/actors/remote/Proxy;Ljava/lang/Object;>;;
Asciz	Signature;
Asciz	productElementName;
Asciz	(I)Ljava/lang/String;;
Asciz	LineNumberTable;
Asciz	scala/Product$class;
class	scala/Product$class
Asciz	(Lscala/Product;I)Ljava/lang/String;;
NameAndType	productElementName:(Lscala/Product;I)Ljava/lang/String;
Method	scala/Product$class.productElementName:(Lscala/Product;I)Ljava/lang/String;
Asciz	this;
Asciz	Lscala/actors/remote/Apply0;;
Asciz	n;
Asciz	I;
Asciz	LocalVariableTable;
Asciz	productIterator;
Asciz	()Lscala/collection/Iterator;;
Asciz	(Lscala/Product;)Lscala/collection/Iterator;;
NameAndType	productIterator:(Lscala/Product;)Lscala/collection/Iterator;
Method	scala/Product$class.productIterator:(Lscala/Product;)Lscala/collection/Iterator;
Asciz	productElements;
NameAndType	productElements:(Lscala/Product;)Lscala/collection/Iterator;
Method	scala/Product$class.productElements:(Lscala/Product;)Lscala/collection/Iterator;
Asciz	Deprecated;
Asciz	copy$default$1;
Asciz	()Lscala/Function2;;
Asciz	scala/actors/remote/Apply0;
class	scala/actors/remote/Apply0
NameAndType	rfun:()Lscala/Function2;
Method	scala/actors/remote/Apply0.rfun:()Lscala/Function2;
NameAndType	rfun:Lscala/Function2;
Field	scala/actors/remote/Apply0.rfun:Lscala/Function2;
Asciz	()Lscala/Function2<Lscala/actors/AbstractActor;Lscala/actors/remote/Proxy;Ljava/lang/Object;>;;
Asciz	copy;
Asciz	(Lscala/Function2;)Lscala/actors/remote/Apply0;;
Asciz	<init>;
Asciz	(Lscala/Function2;)V;
NameAndType	"<init>":(Lscala/Function2;)V
Method	scala/actors/remote/Apply0."<init>":(Lscala/Function2;)V
Asciz	hashCode;
Asciz	()I;
Asciz	scala/runtime/ScalaRunTime$;
class	scala/runtime/ScalaRunTime$
Asciz	Lscala/runtime/ScalaRunTime$;;
NameAndType	MODULE$:Lscala/runtime/ScalaRunTime$;
Field	scala/runtime/ScalaRunTime$.MODULE$:Lscala/runtime/ScalaRunTime$;
Asciz	_hashCode;
Asciz	(Lscala/Product;)I;
NameAndType	_hashCode:(Lscala/Product;)I
Method	scala/runtime/ScalaRunTime$._hashCode:(Lscala/Product;)I
Asciz	toString;
Asciz	()Ljava/lang/String;;
Asciz	_toString;
Asciz	(Lscala/Product;)Ljava/lang/String;;
NameAndType	_toString:(Lscala/Product;)Ljava/lang/String;
Method	scala/runtime/ScalaRunTime$._toString:(Lscala/Product;)Ljava/lang/String;
Asciz	equals;
Asciz	(Ljava/lang/Object;)Z;
Asciz	gd1$1;
Asciz	(Lscala/Function2;)Z;
NameAndType	gd1$1:(Lscala/Function2;)Z
Method	scala/actors/remote/Apply0.gd1$1:(Lscala/Function2;)Z
Asciz	scala/Equals;
class	scala/Equals
Asciz	canEqual;
NameAndType	canEqual:(Ljava/lang/Object;)Z
InterfaceMethod	scala/Equals.canEqual:(Ljava/lang/Object;)Z
Asciz	temp2;
Asciz	temp3;
Asciz	productPrefix;
Asciz	Apply0;
String	Apply0
Asciz	productArity;
Asciz	productElement;
Asciz	(I)Ljava/lang/Object;;
Asciz	java/lang/IndexOutOfBoundsException;
class	java/lang/IndexOutOfBoundsException
Asciz	scala/runtime/BoxesRunTime;
class	scala/runtime/BoxesRunTime
Asciz	boxToInteger;
Asciz	(I)Ljava/lang/Integer;;
NameAndType	boxToInteger:(I)Ljava/lang/Integer;
Method	scala/runtime/BoxesRunTime.boxToInteger:(I)Ljava/lang/Integer;
Asciz	java/lang/Object;
class	java/lang/Object
NameAndType	toString:()Ljava/lang/String;
Method	java/lang/Object.toString:()Ljava/lang/String;
Asciz	(Ljava/lang/String;)V;
NameAndType	"<init>":(Ljava/lang/String;)V
Method	java/lang/IndexOutOfBoundsException."<init>":(Ljava/lang/String;)V
NameAndType	equals:(Ljava/lang/Object;)Z
Method	java/lang/Object.equals:(Ljava/lang/Object;)Z
Asciz	()V;
NameAndType	"<init>":()V
Method	java/lang/Object."<init>":()V
Asciz	$init$;
Asciz	(Lscala/Product;)V;
NameAndType	$init$:(Lscala/Product;)V
Method	scala/Product$class.$init$:(Lscala/Product;)V
Asciz	(Lscala/Function2<Lscala/actors/AbstractActor;Lscala/actors/remote/Proxy;Ljava/lang/Object;>;)V;
Asciz	ScalaSig;
Asciz	scala/ScalaObject;
class	scala/ScalaObject
Asciz	scala/Product;
class	scala/Product
Asciz	java/io/Serializable;
class	java/io/Serializable

{
private final scala.Function2 rfun;
  Signature: Lscala/Function2;
  Signature: length = 0x2
   00 13 

public static final scala.Function1 andThen(scala.Function1);
  Signature: (Lscala/Function1;)Lscala/Function1;
  Code:
   Stack=2, Locals=1, Args_size=1
	getstatic	Field scala/actors/remote/Apply0$.MODULE$:Lscala/actors/remote/Apply0$;
	aload_0
	invokevirtual	Method scala/actors/remote/Apply0$.andThen:(Lscala/Function1;)Lscala/Function1;
	areturn
  Labels:

public static final scala.Function1 compose(scala.Function1);
  Signature: (Lscala/Function1;)Lscala/Function1;
  Code:
   Stack=2, Locals=1, Args_size=1
	getstatic	Field scala/actors/remote/Apply0$.MODULE$:Lscala/actors/remote/Apply0$;
	aload_0
	invokevirtual	Method scala/actors/remote/Apply0$.compose:(Lscala/Function1;)Lscala/Function1;
	areturn
  Labels:

public java.lang.String productElementName(int);
  Signature: (I)Ljava/lang/String;
  Code:
   Stack=2, Locals=2, Args_size=2
	aload_0
	iload_1
	invokestatic	Method scala/Product$class.productElementName:(Lscala/Product;I)Ljava/lang/String;
	areturn
  Labels:
  LocalVariableTable: 
   Start  Length  Slot  Name   Signature
   0      6      0    this       Lscala/actors/remote/Apply0;
   0      6      1    n       I


public scala.collection.Iterator productIterator();
  Signature: ()Lscala/collection/Iterator;
  Code:
   Stack=1, Locals=1, Args_size=1
	aload_0
	invokestatic	Method scala/Product$class.productIterator:(Lscala/Product;)Lscala/collection/Iterator;
	areturn
  Labels:

public scala.collection.Iterator productElements();
  Signature: ()Lscala/collection/Iterator;
  Code:
   Stack=1, Locals=1, Args_size=1
	aload_0
	invokestatic	Method scala/Product$class.productElements:(Lscala/Product;)Lscala/collection/Iterator;
	areturn
  Labels:
  Deprecated: true

public scala.Function2 copy$default$1();
  Signature: ()Lscala/Function2;
  Code:
   Stack=1, Locals=1, Args_size=1
	aload_0
	invokevirtual	Method rfun:()Lscala/Function2;
	areturn
  Labels:

public scala.Function2 rfun();
  Signature: ()Lscala/Function2;
  Code:
   Stack=1, Locals=1, Args_size=1
	aload_0
	getfield	Field rfun:Lscala/Function2;
	areturn
  Labels:
  Signature: length = 0x2
   00 33 

public scala.actors.remote.Apply0 copy(scala.Function2);
  Signature: (Lscala/Function2;)Lscala/actors/remote/Apply0;
  Code:
   Stack=3, Locals=2, Args_size=2
	new	class scala/actors/remote/Apply0
	dup
	aload_1
	invokespecial	Method "<init>":(Lscala/Function2;)V
	areturn
  Labels:
  LocalVariableTable: 
   Start  Length  Slot  Name   Signature
   0      9      0    this       Lscala/actors/remote/Apply0;
   0      9      1    rfun       Lscala/Function2;


public int hashCode();
  Signature: ()I
  Code:
   Stack=2, Locals=1, Args_size=1
	getstatic	Field scala/runtime/ScalaRunTime$.MODULE$:Lscala/runtime/ScalaRunTime$;
	aload_0
	invokevirtual	Method scala/runtime/ScalaRunTime$._hashCode:(Lscala/Product;)I
	ireturn
  Labels:

public java.lang.String toString();
  Signature: ()Ljava/lang/String;
  Code:
   Stack=2, Locals=1, Args_size=1
	getstatic	Field scala/runtime/ScalaRunTime$.MODULE$:Lscala/runtime/ScalaRunTime$;
	aload_0
	invokevirtual	Method scala/runtime/ScalaRunTime$._toString:(Lscala/Product;)Ljava/lang/String;
	areturn
  Labels:

public boolean equals(java.lang.Object);
  Signature: (Ljava/lang/Object;)Z
  Code:
   Stack=2, Locals=4, Args_size=2
	aload_0
	aload_1
	if_acmpeq	l1 // iconst_1
	aload_1
	instanceof	class scala/actors/remote/Apply0
	ifeq	l2 // iconst_0
	aload_1
	checkcast	class scala/actors/remote/Apply0
	astore_2
	aload_2
	invokevirtual	Method rfun:()Lscala/Function2;
	astore_3
	aload_0
	aload_3
	invokespecial	Method gd1$1:(Lscala/Function2;)Z
	ifeq	l3 // iconst_0
	aload_1
	checkcast	class scala/actors/remote/Apply0
	aload_0
	invokeinterface	InterfaceMethod scala/Equals.canEqual:(Ljava/lang/Object;)Z
	goto	l4 // ifeq
l3	iconst_0
	goto	l4 // ifeq
l2	iconst_0
l4	ifeq	l5 // iconst_0
l1	iconst_1
	goto	l6 // ireturn
l5	iconst_0
l6	ireturn
  Labels:
   	l3 = 43 // iconst_0
   	l2 = 47 // iconst_0
   	l4 = 48 // ifeq
   	l1 = 51 // iconst_1
   	l5 = 55 // iconst_0
   	l6 = 56 // ireturn
  LocalVariableTable: 
   Start  Length  Slot  Name   Signature
   0      57      0    this       Lscala/actors/remote/Apply0;
   17      30      2    temp2       Lscala/actors/remote/Apply0;
   22      25      3    temp3       Lscala/Function2;


public java.lang.String productPrefix();
  Signature: ()Ljava/lang/String;
  Code:
   Stack=1, Locals=1, Args_size=1
	ldc	String Apply0
	areturn
  Labels:

public int productArity();
  Signature: ()I
  Code:
   Stack=1, Locals=1, Args_size=1
	iconst_1
	ireturn
  Labels:

public java.lang.Object productElement(int);
  Signature: (I)Ljava/lang/Object;
  Code:
   Stack=3, Locals=2, Args_size=2
	iload_1
	iconst_0
	if_icmpne	l1 // new
	aload_0
	invokevirtual	Method rfun:()Lscala/Function2;
	areturn
l1	new	class java/lang/IndexOutOfBoundsException
	dup
	iload_1
	invokestatic	Method scala/runtime/BoxesRunTime.boxToInteger:(I)Ljava/lang/Integer;
	invokevirtual	Method java/lang/Object.toString:()Ljava/lang/String;
	invokespecial	Method java/lang/IndexOutOfBoundsException."<init>":(Ljava/lang/String;)V
	athrow
  Labels:
   	l1 = 10 // new

public boolean canEqual(java.lang.Object);
  Signature: (Ljava/lang/Object;)Z
  Code:
   Stack=1, Locals=2, Args_size=2
	aload_1
	instanceof	class scala/actors/remote/Apply0
	ireturn
  Labels:

private final boolean gd1$1(scala.Function2);
  Signature: (Lscala/Function2;)Z
  Code:
   Stack=2, Locals=3, Args_size=2
	aload_1
	aload_0
	invokevirtual	Method rfun:()Lscala/Function2;
	astore_2
	dup
	ifnonnull	l1 // aload_2
	pop
	aload_2
	ifnull	l2 // iconst_1
	goto	l3 // iconst_0
l1	aload_2
	invokevirtual	Method java/lang/Object.equals:(Ljava/lang/Object;)Z
	ifeq	l3 // iconst_0
l2	iconst_1
	goto	l4 // ireturn
l3	iconst_0
l4	ireturn
  Labels:
   	l1 = 18 // aload_2
   	l2 = 25 // iconst_1
   	l3 = 29 // iconst_0
   	l4 = 30 // ireturn

public scala.actors.remote.Apply0(scala.Function2);
  Signature: (Lscala/Function2;)V
  Code:
   Stack=2, Locals=2, Args_size=2
	aload_0
	aload_1
	putfield	Field rfun:Lscala/Function2;
	aload_0
	invokespecial	Method java/lang/Object."<init>":()V
	aload_0
	invokestatic	Method scala/Product$class.$init$:(Lscala/Product;)V
	return
  Labels:
  LocalVariableTable: 
   Start  Length  Slot  Name   Signature
   0      14      0    this       Lscala/actors/remote/Apply0;
   0      14      1    rfun       Lscala/Function2;

  Signature: length = 0x2
   00 76 

}

