Compiled from "JavaSerializer.scala"
public class scala.actors.remote.CustomObjectInputStream extends java.io.ObjectInputStream implements scala.ScalaObject
  SourceFile: "JavaSerializer.scala"
  ScalaSig: length = 0x21E
   05 00 55 06 09 01 02 FFFFFF84 FFFFFF80 FFFFFF80 FFFFFF80 00 02 08 02 17
   43 75 73 74 6F 6D 4F 62 6A 65 63 74 49 6E 70 75
   74 53 74 72 65 61 6D 0A 02 03 04 01 06 72 65 6D
   6F 74 65 0A 02 05 06 01 06 61 63 74 6F 72 73 0A
   01 07 01 05 73 63 61 6C 61 13 03 00 09 11 10 02
   0A 0F 0D 01 0B 0A 02 0C 0D 01 02 69 6F 0A 01 0E
   01 04 6A 61 76 61 09 02 10 0B 02 11 4F 62 6A 65
   63 74 49 6E 70 75 74 53 74 72 65 61 6D 10 02 12
   13 0D 01 06 09 02 14 06 02 0B 53 63 61 6C 61 4F
   62 6A 65 63 74 08 08 16 00 FFFFFF82 FFFFFF80 FFFFFFA0 FFFFFF80 04 18 01
   02 69 6E 03 00 10 02 0A 19 09 02 1A 0B 02 0B 49
   6E 70 75 74 53 74 72 65 61 6D 08 08 1C 00 FFFFFF82 FFFFFF80
   FFFFFFA0 FFFFFF80 04 1D 01 02 63 6C 10 02 1E 21 0D 01 1F 0A
   02 20 0D 01 04 6C 61 6E 67 09 02 22 1F 02 0B 43
   6C 61 73 73 4C 6F 61 64 65 72 08 05 24 00 FFFFFF84 00
   25 01 06 3C 69 6E 69 74 3E 14 03 26 28 29 10 02
   27 00 0D 01 02 08 05 16 23 FFFFFFC0 00 18 08 05 1C 23
   FFFFFFC0 00 1D 08 05 2B 00 FFFFFF84 20 2C 01 0C 72 65 73 6F
   6C 76 65 43 6C 61 73 73 14 02 2D 40 30 02 2E 37
   10 03 2F 32 35 0E 02 12 30 09 02 31 06 01 06 50
   72 65 64 65 66 09 02 33 34 02 05 43 6C 61 73 73
   0A 02 31 06 10 02 36 37 0C 00 04 08 38 00 FFFFFF84 FFFFFF80
   FFFFFF80 FFFFFF82 00 39 02 03 5F 24 31 11 02 3A 3D 10 02 12
   3B 09 02 3C 06 02 07 4E 6F 74 68 69 6E 67 10 02
   12 3E 09 02 3F 06 02 03 41 6E 79 08 05 41 2A FFFFFFC0
   00 42 01 02 63 64 10 02 0A 43 09 02 44 0B 02 11
   4F 62 6A 65 63 74 53 74 72 65 61 6D 43 6C 61 73
   73 08 05 46 00 FFFFFF84 20 47 01 11 72 65 73 6F 6C 76
   65 50 72 6F 78 79 43 6C 61 73 73 14 02 48 4D 30
   02 49 4B 10 03 2F 32 4A 10 02 36 4B 04 08 4C 00
   FFFFFF84 FFFFFF80 FFFFFF80 FFFFFF82 00 39 02 03 5F 24 32 08 05 4E 45 FFFFFFC0
   00 4F 01 0A 69 6E 74 65 72 66 61 63 65 73 10 03
   12 50 52 09 02 51 06 02 05 41 72 72 61 79 10 02
   2F 53 09 02 54 34 02 06 53 74 72 69 6E 67 
  InnerClass: 
   public final #109= #37 of #10; //$anonfun$1=class scala/actors/remote/CustomObjectInputStream$$anonfun$1 of class scala/actors/remote/CustomObjectInputStream
  minor version: 0
  major version: 49
  Constant pool:
const #1 = Asciz	SourceFile;
const #2 = Asciz	JavaSerializer.scala;
const #3 = Asciz	scala$actors$remote$CustomObjectInputStream$$cl;
const #4 = Asciz	Ljava/lang/ClassLoader;;
const #5 = Asciz	<init>;
const #6 = Asciz	(Ljava/io/InputStream;Ljava/lang/ClassLoader;)V;
const #7 = Asciz	Code;
const #8 = Asciz	LineNumberTable;
const #9 = Asciz	scala/actors/remote/CustomObjectInputStream;
const #10 = class	#9;	//  scala/actors/remote/CustomObjectInputStream
const #11 = NameAndType	#3:#4;//  scala$actors$remote$CustomObjectInputStream$$cl:Ljava/lang/ClassLoader;
const #12 = Field	#10.#11;	//  scala/actors/remote/CustomObjectInputStream.scala$actors$remote$CustomObjectInputStream$$cl:Ljava/lang/ClassLoader;
const #13 = Asciz	java/io/ObjectInputStream;
const #14 = class	#13;	//  java/io/ObjectInputStream
const #15 = Asciz	(Ljava/io/InputStream;)V;
const #16 = NameAndType	#5:#15;//  "<init>":(Ljava/io/InputStream;)V
const #17 = Method	#14.#16;	//  java/io/ObjectInputStream."<init>":(Ljava/io/InputStream;)V
const #18 = Asciz	this;
const #19 = Asciz	Lscala/actors/remote/CustomObjectInputStream;;
const #20 = Asciz	in;
const #21 = Asciz	Ljava/io/InputStream;;
const #22 = Asciz	cl;
const #23 = Asciz	LocalVariableTable;
const #24 = Asciz	resolveProxyClass;
const #25 = Asciz	([Ljava/lang/String;)Ljava/lang/Class;;
const #26 = Asciz	scala/runtime/ScalaRunTime$;
const #27 = class	#26;	//  scala/runtime/ScalaRunTime$
const #28 = Asciz	MODULE$;
const #29 = Asciz	Lscala/runtime/ScalaRunTime$;;
const #30 = NameAndType	#28:#29;//  MODULE$:Lscala/runtime/ScalaRunTime$;
const #31 = Field	#27.#30;	//  scala/runtime/ScalaRunTime$.MODULE$:Lscala/runtime/ScalaRunTime$;
const #32 = Asciz	boxArray;
const #33 = Asciz	(Ljava/lang/Object;)Lscala/runtime/BoxedArray;;
const #34 = NameAndType	#32:#33;//  boxArray:(Ljava/lang/Object;)Lscala/runtime/BoxedArray;
const #35 = Method	#27.#34;	//  scala/runtime/ScalaRunTime$.boxArray:(Ljava/lang/Object;)Lscala/runtime/BoxedArray;
const #36 = Asciz	scala/actors/remote/CustomObjectInputStream$$anonfun$1;
const #37 = class	#36;	//  scala/actors/remote/CustomObjectInputStream$$anonfun$1
const #38 = Asciz	(Lscala/actors/remote/CustomObjectInputStream;)V;
const #39 = NameAndType	#5:#38;//  "<init>":(Lscala/actors/remote/CustomObjectInputStream;)V
const #40 = Method	#37.#39;	//  scala/actors/remote/CustomObjectInputStream$$anonfun$1."<init>":(Lscala/actors/remote/CustomObjectInputStream;)V
const #41 = Asciz	scala/Array$;
const #42 = class	#41;	//  scala/Array$
const #43 = Asciz	Lscala/Array$;;
const #44 = NameAndType	#28:#43;//  MODULE$:Lscala/Array$;
const #45 = Field	#42.#44;	//  scala/Array$.MODULE$:Lscala/Array$;
const #46 = Asciz	builderFactory;
const #47 = Asciz	()Lscala/collection/generic/BuilderFactory;;
const #48 = NameAndType	#46:#47;//  builderFactory:()Lscala/collection/generic/BuilderFactory;
const #49 = Method	#42.#48;	//  scala/Array$.builderFactory:()Lscala/collection/generic/BuilderFactory;
const #50 = Asciz	scala/collection/generic/TraversableTemplate;
const #51 = class	#50;	//  scala/collection/generic/TraversableTemplate
const #52 = Asciz	map;
const #53 = Asciz	(Lscala/Function1;Lscala/collection/generic/BuilderFactory;)Ljava/lang/Object;;
const #54 = NameAndType	#52:#53;//  map:(Lscala/Function1;Lscala/collection/generic/BuilderFactory;)Ljava/lang/Object;
const #55 = InterfaceMethod	#51.#54;	//  scala/collection/generic/TraversableTemplate.map:(Lscala/Function1;Lscala/collection/generic/BuilderFactory;)Ljava/lang/Object;
const #56 = Asciz	scala/runtime/BoxedArray;
const #57 = class	#56;	//  scala/runtime/BoxedArray
const #58 = Asciz	java/lang/Class;
const #59 = class	#58;	//  java/lang/Class
const #60 = Asciz	arrayValue;
const #61 = Asciz	(Lscala/runtime/BoxedArray;Ljava/lang/Class;)Ljava/lang/Object;;
const #62 = NameAndType	#60:#61;//  arrayValue:(Lscala/runtime/BoxedArray;Ljava/lang/Class;)Ljava/lang/Object;
const #63 = Method	#27.#62;	//  scala/runtime/ScalaRunTime$.arrayValue:(Lscala/runtime/BoxedArray;Ljava/lang/Class;)Ljava/lang/Object;
const #64 = Asciz	[Ljava/lang/Class;;
const #65 = class	#64;	//  "[Ljava/lang/Class;"
const #66 = Asciz	toArray;
const #67 = Asciz	()Lscala/runtime/BoxedArray;;
const #68 = NameAndType	#66:#67;//  toArray:()Lscala/runtime/BoxedArray;
const #69 = InterfaceMethod	#51.#68;	//  scala/collection/generic/TraversableTemplate.toArray:()Lscala/runtime/BoxedArray;
const #70 = Asciz	java/lang/reflect/Proxy;
const #71 = class	#70;	//  java/lang/reflect/Proxy
const #72 = Asciz	getProxyClass;
const #73 = Asciz	(Ljava/lang/ClassLoader;[Ljava/lang/Class;)Ljava/lang/Class;;
const #74 = NameAndType	#72:#73;//  getProxyClass:(Ljava/lang/ClassLoader;[Ljava/lang/Class;)Ljava/lang/Class;
const #75 = Method	#71.#74;	//  java/lang/reflect/Proxy.getProxyClass:(Ljava/lang/ClassLoader;[Ljava/lang/Class;)Ljava/lang/Class;
const #76 = NameAndType	#24:#25;//  resolveProxyClass:([Ljava/lang/String;)Ljava/lang/Class;
const #77 = Method	#14.#76;	//  java/io/ObjectInputStream.resolveProxyClass:([Ljava/lang/String;)Ljava/lang/Class;
const #78 = Asciz	java/lang/ClassNotFoundException;
const #79 = class	#78;	//  java/lang/ClassNotFoundException
const #80 = Asciz	interfaces;
const #81 = Asciz	[Ljava/lang/String;;
const #82 = Asciz	exceptionResult2;
const #83 = Asciz	Ljava/lang/Class;;
const #84 = Asciz	ifaces;
const #85 = Asciz	([Ljava/lang/String;)Ljava/lang/Class<*>;;
const #86 = Asciz	Signature;
const #87 = Asciz	resolveClass;
const #88 = Asciz	(Ljava/io/ObjectStreamClass;)Ljava/lang/Class;;
const #89 = Asciz	java/io/ObjectStreamClass;
const #90 = class	#89;	//  java/io/ObjectStreamClass
const #91 = Asciz	getName;
const #92 = Asciz	()Ljava/lang/String;;
const #93 = NameAndType	#91:#92;//  getName:()Ljava/lang/String;
const #94 = Method	#90.#93;	//  java/io/ObjectStreamClass.getName:()Ljava/lang/String;
const #95 = Asciz	java/lang/ClassLoader;
const #96 = class	#95;	//  java/lang/ClassLoader
const #97 = Asciz	loadClass;
const #98 = Asciz	(Ljava/lang/String;)Ljava/lang/Class;;
const #99 = NameAndType	#97:#98;//  loadClass:(Ljava/lang/String;)Ljava/lang/Class;
const #100 = Method	#96.#99;	//  java/lang/ClassLoader.loadClass:(Ljava/lang/String;)Ljava/lang/Class;
const #101 = NameAndType	#87:#88;//  resolveClass:(Ljava/io/ObjectStreamClass;)Ljava/lang/Class;
const #102 = Method	#14.#101;	//  java/io/ObjectInputStream.resolveClass:(Ljava/io/ObjectStreamClass;)Ljava/lang/Class;
const #103 = Asciz	cd;
const #104 = Asciz	Ljava/io/ObjectStreamClass;;
const #105 = Asciz	exceptionResult1;
const #106 = Asciz	(Ljava/io/ObjectStreamClass;)Ljava/lang/Class<*>;;
const #107 = Asciz	ScalaSig;
const #108 = Asciz	InnerClasses;
const #109 = Asciz	$anonfun$1;
const #110 = Asciz	scala/ScalaObject;
const #111 = class	#110;	//  scala/ScalaObject

{
public final java.lang.ClassLoader scala$actors$remote$CustomObjectInputStream$$cl;

public scala.actors.remote.CustomObjectInputStream(java.io.InputStream, java.lang.ClassLoader);
  Code:
   Stack=2, Locals=3, Args_size=3
   0:	aload_0
   1:	aload_2
   2:	putfield	#12; //Field scala$actors$remote$CustomObjectInputStream$$cl:Ljava/lang/ClassLoader;
   5:	aload_0
   6:	aload_1
   7:	invokespecial	#17; //Method java/io/ObjectInputStream."<init>":(Ljava/io/InputStream;)V
   10:	return
  LineNumberTable: 
   line 21: 0
   line 22: 6
   line 21: 7

  LocalVariableTable: 
   Start  Length  Slot  Name   Signature
   0      11      0    this       Lscala/actors/remote/CustomObjectInputStream;
   0      11      1    in       Ljava/io/InputStream;
   0      11      2    cl       Ljava/lang/ClassLoader;


public java.lang.Class resolveProxyClass(java.lang.String[]);
  Code:
   Stack=4, Locals=7, Args_size=2
   0:	aconst_null
   1:	astore_2
   2:	getstatic	#31; //Field scala/runtime/ScalaRunTime$.MODULE$:Lscala/runtime/ScalaRunTime$;
   5:	aload_1
   6:	invokevirtual	#35; //Method scala/runtime/ScalaRunTime$.boxArray:(Ljava/lang/Object;)Lscala/runtime/BoxedArray;
   9:	new	#37; //class scala/actors/remote/CustomObjectInputStream$$anonfun$1
   12:	dup
   13:	aload_0
   14:	invokespecial	#40; //Method scala/actors/remote/CustomObjectInputStream$$anonfun$1."<init>":(Lscala/actors/remote/CustomObjectInputStream;)V
   17:	getstatic	#45; //Field scala/Array$.MODULE$:Lscala/Array$;
   20:	invokevirtual	#49; //Method scala/Array$.builderFactory:()Lscala/collection/generic/BuilderFactory;
   23:	invokeinterface	#55,  3; //InterfaceMethod scala/collection/generic/TraversableTemplate.map:(Lscala/Function1;Lscala/collection/generic/BuilderFactory;)Ljava/lang/Object;
   28:	astore	5
   30:	aload	5
   32:	instanceof	#57; //class scala/runtime/BoxedArray
   35:	ifeq	54
   38:	getstatic	#31; //Field scala/runtime/ScalaRunTime$.MODULE$:Lscala/runtime/ScalaRunTime$;
   41:	aload	5
   43:	checkcast	#57; //class scala/runtime/BoxedArray
   46:	ldc	#59; //class java/lang/Class
   48:	invokevirtual	#63; //Method scala/runtime/ScalaRunTime$.arrayValue:(Lscala/runtime/BoxedArray;Ljava/lang/Class;)Ljava/lang/Object;
   51:	goto	56
   54:	aload	5
   56:	checkcast	#65; //class "[Ljava/lang/Class;"
   59:	astore	4
   61:	aload_0
   62:	getfield	#12; //Field scala$actors$remote$CustomObjectInputStream$$cl:Ljava/lang/ClassLoader;
   65:	getstatic	#31; //Field scala/runtime/ScalaRunTime$.MODULE$:Lscala/runtime/ScalaRunTime$;
   68:	getstatic	#31; //Field scala/runtime/ScalaRunTime$.MODULE$:Lscala/runtime/ScalaRunTime$;
   71:	aload	4
   73:	invokevirtual	#35; //Method scala/runtime/ScalaRunTime$.boxArray:(Ljava/lang/Object;)Lscala/runtime/BoxedArray;
   76:	invokeinterface	#69,  1; //InterfaceMethod scala/collection/generic/TraversableTemplate.toArray:()Lscala/runtime/BoxedArray;
   81:	ldc	#59; //class java/lang/Class
   83:	invokevirtual	#63; //Method scala/runtime/ScalaRunTime$.arrayValue:(Lscala/runtime/BoxedArray;Ljava/lang/Class;)Ljava/lang/Object;
   86:	astore	6
   88:	aload	6
   90:	instanceof	#57; //class scala/runtime/BoxedArray
   93:	ifeq	112
   96:	getstatic	#31; //Field scala/runtime/ScalaRunTime$.MODULE$:Lscala/runtime/ScalaRunTime$;
   99:	aload	6
   101:	checkcast	#57; //class scala/runtime/BoxedArray
   104:	ldc	#59; //class java/lang/Class
   106:	invokevirtual	#63; //Method scala/runtime/ScalaRunTime$.arrayValue:(Lscala/runtime/BoxedArray;Ljava/lang/Class;)Ljava/lang/Object;
   109:	goto	114
   112:	aload	6
   114:	checkcast	#65; //class "[Ljava/lang/Class;"
   117:	invokestatic	#75; //Method java/lang/reflect/Proxy.getProxyClass:(Ljava/lang/ClassLoader;[Ljava/lang/Class;)Ljava/lang/Class;
   120:	astore_2
   121:	goto	131
   124:	astore_3
   125:	aload_0
   126:	aload_1
   127:	invokespecial	#77; //Method java/io/ObjectInputStream.resolveProxyClass:([Ljava/lang/String;)Ljava/lang/Class;
   130:	astore_2
   131:	aload_2
   132:	areturn
  Exception table:
   from   to  target type
     2   124   124   Class java/lang/ClassNotFoundException

  LineNumberTable: 
   line 32: 0
   line 31: 1
   line 32: 2
   line 35: 56
   line 32: 59
   line 33: 61
   line 35: 96
   line 33: 117
   line 35: 124
   line 36: 125

  LocalVariableTable: 
   Start  Length  Slot  Name   Signature
   0      133      0    this       Lscala/actors/remote/CustomObjectInputStream;
   0      133      1    interfaces       [Ljava/lang/String;
   2      130      2    exceptionResult2       Ljava/lang/Class;
   61      59      4    ifaces       [Ljava/lang/Class;

  Signature: length = 0x2
   00 55 

public java.lang.Class resolveClass(java.io.ObjectStreamClass);
  Code:
   Stack=2, Locals=4, Args_size=2
   0:	aconst_null
   1:	astore_2
   2:	aload_0
   3:	getfield	#12; //Field scala$actors$remote$CustomObjectInputStream$$cl:Ljava/lang/ClassLoader;
   6:	aload_1
   7:	invokevirtual	#94; //Method java/io/ObjectStreamClass.getName:()Ljava/lang/String;
   10:	invokevirtual	#100; //Method java/lang/ClassLoader.loadClass:(Ljava/lang/String;)Ljava/lang/Class;
   13:	astore_2
   14:	goto	24
   17:	astore_3
   18:	aload_0
   19:	aload_1
   20:	invokespecial	#102; //Method java/io/ObjectInputStream.resolveClass:(Ljava/io/ObjectStreamClass;)Ljava/lang/Class;
   23:	astore_2
   24:	aload_2
   25:	areturn
  Exception table:
   from   to  target type
     2    17    17   Class java/lang/ClassNotFoundException

  LineNumberTable: 
   line 25: 0
   line 24: 1
   line 25: 2
   line 27: 17
   line 28: 18

  LocalVariableTable: 
   Start  Length  Slot  Name   Signature
   0      26      0    this       Lscala/actors/remote/CustomObjectInputStream;
   0      26      1    cd       Ljava/io/ObjectStreamClass;
   2      23      2    exceptionResult1       Ljava/lang/Class;

  Signature: length = 0x2
   00 6A 

}

