Compiled from "JavaSerializer.scala"
public final class scala.actors.remote.CustomObjectInputStream$$anonfun$1 extends java.lang.Object implements scala.Function1,scala.ScalaObject,java.io.Serializable
  SourceFile: "JavaSerializer.scala"
  Scala: length = 0x
   
  InnerClass: 
   public final $anonfun$1=class scala/actors/remote/CustomObjectInputStream$$anonfun$1 of class scala/actors/remote/CustomObjectInputStream
  minor version: 0
  major version: 49
  Constant pool:
Asciz	SourceFile;
Asciz	JavaSerializer.scala;
Asciz	<clinit>;
Asciz	()V;
Asciz	Code;
Asciz	serialVersionUID;
Asciz	J;
Asciz	scala/actors/remote/CustomObjectInputStream$$anonfun$1;
class	scala/actors/remote/CustomObjectInputStream$$anonfun$1
NameAndType	serialVersionUID:J
Field	scala/actors/remote/CustomObjectInputStream$$anonfun$1.serialVersionUID:J
Asciz	$outer;
Asciz	Lscala/actors/remote/CustomObjectInputStream;;
Asciz	<init>;
Asciz	(Lscala/actors/remote/CustomObjectInputStream;)V;
Asciz	LineNumberTable;
Asciz	java/lang/NullPointerException;
class	java/lang/NullPointerException
NameAndType	"<init>":()V
Method	java/lang/NullPointerException."<init>":()V
NameAndType	$outer:Lscala/actors/remote/CustomObjectInputStream;
Field	scala/actors/remote/CustomObjectInputStream$$anonfun$1.$outer:Lscala/actors/remote/CustomObjectInputStream;
Asciz	java/lang/Object;
class	java/lang/Object
Method	java/lang/Object."<init>":()V
Asciz	scala/Function1$class;
class	scala/Function1$class
Asciz	$init$;
Asciz	(Lscala/Function1;)V;
NameAndType	$init$:(Lscala/Function1;)V
Method	scala/Function1$class.$init$:(Lscala/Function1;)V
Asciz	this;
Asciz	Lscala/actors/remote/CustomObjectInputStream$$anonfun$1;;
Asciz	LocalVariableTable;
Asciz	apply;
Asciz	(Ljava/lang/Object;)Ljava/lang/Object;;
Asciz	java/lang/String;
class	java/lang/String
Asciz	(Ljava/lang/String;)Ljava/lang/Class;;
NameAndType	apply:(Ljava/lang/String;)Ljava/lang/Class;
Method	scala/actors/remote/CustomObjectInputStream$$anonfun$1.apply:(Ljava/lang/String;)Ljava/lang/Class;
Asciz	v1;
Asciz	Ljava/lang/Object;;
Asciz	scala/actors/remote/CustomObjectInputStream;
class	scala/actors/remote/CustomObjectInputStream
Asciz	scala$actors$remote$CustomObjectInputStream$$cl;
Asciz	Ljava/lang/ClassLoader;;
NameAndType	scala$actors$remote$CustomObjectInputStream$$cl:Ljava/lang/ClassLoader;
Field	scala/actors/remote/CustomObjectInputStream.scala$actors$remote$CustomObjectInputStream$$cl:Ljava/lang/ClassLoader;
Asciz	java/lang/ClassLoader;
class	java/lang/ClassLoader
Asciz	loadClass;
NameAndType	loadClass:(Ljava/lang/String;)Ljava/lang/Class;
Method	java/lang/ClassLoader.loadClass:(Ljava/lang/String;)Ljava/lang/Class;
Asciz	iface;
Asciz	Ljava/lang/String;;
Asciz	(Ljava/lang/String;)Ljava/lang/Class<*>;;
Asciz	Signature;
Asciz	andThen;
Asciz	(Lscala/Function1;)Lscala/Function1;;
Asciz	(Lscala/Function1;Lscala/Function1;)Lscala/Function1;;
NameAndType	andThen:(Lscala/Function1;Lscala/Function1;)Lscala/Function1;
Method	scala/Function1$class.andThen:(Lscala/Function1;Lscala/Function1;)Lscala/Function1;
Asciz	g;
Asciz	Lscala/Function1;;
Asciz	compose;
NameAndType	compose:(Lscala/Function1;Lscala/Function1;)Lscala/Function1;
Method	scala/Function1$class.compose:(Lscala/Function1;Lscala/Function1;)Lscala/Function1;
Asciz	toString;
Asciz	()Ljava/lang/String;;
Asciz	(Lscala/Function1;)Ljava/lang/String;;
NameAndType	toString:(Lscala/Function1;)Ljava/lang/String;
Method	scala/Function1$class.toString:(Lscala/Function1;)Ljava/lang/String;
Asciz	Scala;
Asciz	InnerClasses;
Asciz	$anonfun$1;
Asciz	scala/Function1;
class	scala/Function1
Asciz	scala/ScalaObject;
class	scala/ScalaObject
Asciz	java/io/Serializable;
class	java/io/Serializable

{
public static final long serialVersionUID;
  Signature: J

private final scala.actors.remote.CustomObjectInputStream $outer;
  Signature: Lscala/actors/remote/CustomObjectInputStream;

public static {};
  Signature: ()V
  Code:
   Stack=2, Locals=0, Args_size=0
	lconst_0
	putstatic	Field serialVersionUID:J
	return
  Labels:

public scala.actors.remote.CustomObjectInputStream$$anonfun$1(scala.actors.remote.CustomObjectInputStream);
  Signature: (Lscala/actors/remote/CustomObjectInputStream;)V
  Code:
   Stack=2, Locals=2, Args_size=2
	aload_1
	ifnonnull	l1 // aload_0
	new	class java/lang/NullPointerException
	dup
	invokespecial	Method java/lang/NullPointerException."<init>":()V
	athrow
l1	aload_0
	aload_1
	putfield	Field $outer:Lscala/actors/remote/CustomObjectInputStream;
	aload_0
	invokespecial	Method java/lang/Object."<init>":()V
	aload_0
	invokestatic	Method scala/Function1$class.$init$:(Lscala/Function1;)V
	return
  Labels:
   	l1 = 12 // aload_0
  LocalVariableTable: 
   Start  Length  Slot  Name   Signature
   0      26      0    this       Lscala/actors/remote/CustomObjectInputStream$$anonfun$1;
   0      26      1    $outer       Lscala/actors/remote/CustomObjectInputStream;


public final java.lang.Object apply(java.lang.Object);
  Signature: (Ljava/lang/Object;)Ljava/lang/Object;
  Code:
   Stack=2, Locals=3, Args_size=2
	aload_0
	getfield	Field $outer:Lscala/actors/remote/CustomObjectInputStream;
	astore_2
	aload_0
	aload_1
	checkcast	class java/lang/String
	invokevirtual	Method apply:(Ljava/lang/String;)Ljava/lang/Class;
	areturn
  Labels:
  LocalVariableTable: 
   Start  Length  Slot  Name   Signature
   0      14      0    this       Lscala/actors/remote/CustomObjectInputStream$$anonfun$1;
   5      9      1    v1       Ljava/lang/Object;


public final java.lang.Class apply(java.lang.String);
  Signature: (Ljava/lang/String;)Ljava/lang/Class;
  Code:
   Stack=2, Locals=3, Args_size=2
	aload_0
	getfield	Field $outer:Lscala/actors/remote/CustomObjectInputStream;
	astore_2
	aload_0
	getfield	Field $outer:Lscala/actors/remote/CustomObjectInputStream;
	getfield	Field scala/actors/remote/CustomObjectInputStream.scala$actors$remote$CustomObjectInputStream$$cl:Ljava/lang/ClassLoader;
	aload_1
	invokevirtual	Method java/lang/ClassLoader.loadClass:(Ljava/lang/String;)Ljava/lang/Class;
	areturn
  Labels:
  LocalVariableTable: 
   Start  Length  Slot  Name   Signature
   0      17      0    this       Lscala/actors/remote/CustomObjectInputStream$$anonfun$1;
   5      12      1    iface       Ljava/lang/String;

  Signature: length = 0x2
   00 39 

public scala.Function1 andThen(scala.Function1);
  Signature: (Lscala/Function1;)Lscala/Function1;
  Code:
   Stack=2, Locals=2, Args_size=2
	aload_0
	aload_1
	invokestatic	Method scala/Function1$class.andThen:(Lscala/Function1;Lscala/Function1;)Lscala/Function1;
	areturn
  Labels:
  LocalVariableTable: 
   Start  Length  Slot  Name   Signature
   0      6      0    this       Lscala/actors/remote/CustomObjectInputStream$$anonfun$1;
   0      6      1    g       Lscala/Function1;


public scala.Function1 compose(scala.Function1);
  Signature: (Lscala/Function1;)Lscala/Function1;
  Code:
   Stack=2, Locals=2, Args_size=2
	aload_0
	aload_1
	invokestatic	Method scala/Function1$class.compose:(Lscala/Function1;Lscala/Function1;)Lscala/Function1;
	areturn
  Labels:
  LocalVariableTable: 
   Start  Length  Slot  Name   Signature
   0      6      0    this       Lscala/actors/remote/CustomObjectInputStream$$anonfun$1;
   0      6      1    g       Lscala/Function1;


public java.lang.String toString();
  Signature: ()Ljava/lang/String;
  Code:
   Stack=1, Locals=1, Args_size=1
	aload_0
	invokestatic	Method scala/Function1$class.toString:(Lscala/Function1;)Ljava/lang/String;
	areturn
  Labels:

}

