Compiled from "JavaSerializer.scala"
public class scala.actors.remote.CustomObjectInputStream extends java.io.ObjectInputStream implements scala.ScalaObject
  SourceFile: "JavaSerializer.scala"
  ScalaSig: length = 0x21E
   05 00 55 06 09 01 02 FFFFFF84 FFFFFF80 FFFFFF80 FFFFFF80 00 02 08 02 17
   43 75 73 74 6F 6D 4F 62 6A 65 63 74 49 6E 70 75
   74 53 74 72 65 61 6D 0A 02 03 04 01 06 72 65 6D
   6F 74 65 0A 02 05 06 01 06 61 63 74 6F 72 73 0A
   01 07 01 05 73 63 61 6C 61 13 03 00 09 11 10 02
   0A 0F 0D 01 0B 0A 02 0C 0D 01 02 69 6F 0A 01 0E
   01 04 6A 61 76 61 09 02 10 0B 02 11 4F 62 6A 65
   63 74 49 6E 70 75 74 53 74 72 65 61 6D 10 02 12
   13 0D 01 06 09 02 14 06 02 0B 53 63 61 6C 61 4F
   62 6A 65 63 74 08 08 16 00 FFFFFF82 FFFFFF80 FFFFFFA0 FFFFFF80 04 18 01
   02 69 6E 03 00 10 02 0A 19 09 02 1A 0B 02 0B 49
   6E 70 75 74 53 74 72 65 61 6D 08 08 1C 00 FFFFFF82 FFFFFF80
   FFFFFFA0 FFFFFF80 04 1D 01 02 63 6C 10 02 1E 21 0D 01 1F 0A
   02 20 0D 01 04 6C 61 6E 67 09 02 22 1F 02 0B 43
   6C 61 73 73 4C 6F 61 64 65 72 08 05 24 00 FFFFFF84 00
   25 01 06 3C 69 6E 69 74 3E 14 03 26 28 29 10 02
   27 00 0D 01 02 08 05 16 23 FFFFFFC0 00 18 08 05 1C 23
   FFFFFFC0 00 1D 08 05 2B 00 FFFFFF84 20 2C 01 0C 72 65 73 6F
   6C 76 65 43 6C 61 73 73 14 02 2D 40 30 02 2E 37
   10 03 2F 32 35 0E 02 12 30 09 02 31 06 01 06 50
   72 65 64 65 66 09 02 33 34 02 05 43 6C 61 73 73
   0A 02 31 06 10 02 36 37 0C 00 04 08 38 2A FFFFFF84 FFFFFF80
   FFFFFF80 FFFFFF82 00 39 02 03 5F 24 31 11 02 3A 3D 10 02 12
   3B 09 02 3C 06 02 07 4E 6F 74 68 69 6E 67 10 02
   12 3E 09 02 3F 06 02 03 41 6E 79 08 05 41 2A FFFFFFC0
   00 42 01 02 63 64 10 02 0A 43 09 02 44 0B 02 11
   4F 62 6A 65 63 74 53 74 72 65 61 6D 43 6C 61 73
   73 08 05 46 00 FFFFFF84 20 47 01 11 72 65 73 6F 6C 76
   65 50 72 6F 78 79 43 6C 61 73 73 14 02 48 4D 30
   02 49 4B 10 03 2F 32 4A 10 02 36 4B 04 08 4C 45
   FFFFFF84 FFFFFF80 FFFFFF80 FFFFFF82 00 39 02 03 5F 24 32 08 05 4E 45 FFFFFFC0
   00 4F 01 0A 69 6E 74 65 72 66 61 63 65 73 10 03
   12 50 52 09 02 51 06 02 05 41 72 72 61 79 10 02
   2F 53 09 02 54 34 02 06 53 74 72 69 6E 67 
  InnerClass: 
   public final $anonfun$1=class scala/actors/remote/CustomObjectInputStream$$anonfun$1 of class scala/actors/remote/CustomObjectInputStream
  minor version: 0
  major version: 49
  Constant pool:
Asciz	SourceFile;
Asciz	JavaSerializer.scala;
Asciz	scala$actors$remote$CustomObjectInputStream$$cl;
Asciz	Ljava/lang/ClassLoader;;
Asciz	resolveClass;
Asciz	(Ljava/io/ObjectStreamClass;)Ljava/lang/Class;;
Asciz	Code;
Asciz	LineNumberTable;
Asciz	scala/actors/remote/CustomObjectInputStream;
class	scala/actors/remote/CustomObjectInputStream
NameAndType	scala$actors$remote$CustomObjectInputStream$$cl:Ljava/lang/ClassLoader;
Field	scala/actors/remote/CustomObjectInputStream.scala$actors$remote$CustomObjectInputStream$$cl:Ljava/lang/ClassLoader;
Asciz	java/io/ObjectStreamClass;
class	java/io/ObjectStreamClass
Asciz	getName;
Asciz	()Ljava/lang/String;;
NameAndType	getName:()Ljava/lang/String;
Method	java/io/ObjectStreamClass.getName:()Ljava/lang/String;
Asciz	java/lang/ClassLoader;
class	java/lang/ClassLoader
Asciz	loadClass;
Asciz	(Ljava/lang/String;)Ljava/lang/Class;;
NameAndType	loadClass:(Ljava/lang/String;)Ljava/lang/Class;
Method	java/lang/ClassLoader.loadClass:(Ljava/lang/String;)Ljava/lang/Class;
Asciz	java/io/ObjectInputStream;
class	java/io/ObjectInputStream
NameAndType	resolveClass:(Ljava/io/ObjectStreamClass;)Ljava/lang/Class;
Method	java/io/ObjectInputStream.resolveClass:(Ljava/io/ObjectStreamClass;)Ljava/lang/Class;
Asciz	java/lang/ClassNotFoundException;
class	java/lang/ClassNotFoundException
Asciz	this;
Asciz	Lscala/actors/remote/CustomObjectInputStream;;
Asciz	cd;
Asciz	Ljava/io/ObjectStreamClass;;
Asciz	exceptionResult1;
Asciz	Ljava/lang/Class;;
Asciz	LocalVariableTable;
Asciz	(Ljava/io/ObjectStreamClass;)Ljava/lang/Class<*>;;
Asciz	Signature;
Asciz	resolveProxyClass;
Asciz	([Ljava/lang/String;)Ljava/lang/Class;;
Asciz	scala/Predef$;
class	scala/Predef$
Asciz	MODULE$;
Asciz	Lscala/Predef$;;
NameAndType	MODULE$:Lscala/Predef$;
Field	scala/Predef$.MODULE$:Lscala/Predef$;
Asciz	[Ljava/lang/Object;;
class	"[Ljava/lang/Object;"
Asciz	refArrayOps;
Asciz	([Ljava/lang/Object;)Lscala/collection/mutable/ArrayOps;;
NameAndType	refArrayOps:([Ljava/lang/Object;)Lscala/collection/mutable/ArrayOps;
Method	scala/Predef$.refArrayOps:([Ljava/lang/Object;)Lscala/collection/mutable/ArrayOps;
Asciz	scala/actors/remote/CustomObjectInputStream$$anonfun$1;
class	scala/actors/remote/CustomObjectInputStream$$anonfun$1
Asciz	<init>;
Asciz	(Lscala/actors/remote/CustomObjectInputStream;)V;
NameAndType	"<init>":(Lscala/actors/remote/CustomObjectInputStream;)V
Method	scala/actors/remote/CustomObjectInputStream$$anonfun$1."<init>":(Lscala/actors/remote/CustomObjectInputStream;)V
Asciz	scala/Array$;
class	scala/Array$
Asciz	Lscala/Array$;;
NameAndType	MODULE$:Lscala/Array$;
Field	scala/Array$.MODULE$:Lscala/Array$;
Asciz	scala/reflect/ClassManifest$;
class	scala/reflect/ClassManifest$
Asciz	Lscala/reflect/ClassManifest$;;
NameAndType	MODULE$:Lscala/reflect/ClassManifest$;
Field	scala/reflect/ClassManifest$.MODULE$:Lscala/reflect/ClassManifest$;
Asciz	java/lang/Class;
class	java/lang/Class
Asciz	scala/reflect/NoManifest$;
class	scala/reflect/NoManifest$
Asciz	Lscala/reflect/NoManifest$;;
NameAndType	MODULE$:Lscala/reflect/NoManifest$;
Field	scala/reflect/NoManifest$.MODULE$:Lscala/reflect/NoManifest$;
Asciz	scala/reflect/OptManifest;
class	scala/reflect/OptManifest
Asciz	wrapRefArray;
Asciz	([Ljava/lang/Object;)Lscala/collection/mutable/WrappedArray;;
NameAndType	wrapRefArray:([Ljava/lang/Object;)Lscala/collection/mutable/WrappedArray;
Method	scala/Predef$.wrapRefArray:([Ljava/lang/Object;)Lscala/collection/mutable/WrappedArray;
Asciz	classType;
Asciz	(Ljava/lang/Class;Lscala/reflect/OptManifest;Lscala/collection/Seq;)Lscala/reflect/ClassManifest;;
NameAndType	classType:(Ljava/lang/Class;Lscala/reflect/OptManifest;Lscala/collection/Seq;)Lscala/reflect/ClassManifest;
Method	scala/reflect/ClassManifest$.classType:(Ljava/lang/Class;Lscala/reflect/OptManifest;Lscala/collection/Seq;)Lscala/reflect/ClassManifest;
Asciz	canBuildFrom;
Asciz	(Lscala/reflect/ClassManifest;)Lscala/collection/generic/CanBuildFrom;;
NameAndType	canBuildFrom:(Lscala/reflect/ClassManifest;)Lscala/collection/generic/CanBuildFrom;
Method	scala/Array$.canBuildFrom:(Lscala/reflect/ClassManifest;)Lscala/collection/generic/CanBuildFrom;
Asciz	scala/collection/TraversableLike;
class	scala/collection/TraversableLike
Asciz	map;
Asciz	(Lscala/Function1;Lscala/collection/generic/CanBuildFrom;)Ljava/lang/Object;;
NameAndType	map:(Lscala/Function1;Lscala/collection/generic/CanBuildFrom;)Ljava/lang/Object;
InterfaceMethod	scala/collection/TraversableLike.map:(Lscala/Function1;Lscala/collection/generic/CanBuildFrom;)Ljava/lang/Object;
Asciz	[Ljava/lang/Class;;
class	"[Ljava/lang/Class;"
Asciz	java/lang/reflect/Proxy;
class	java/lang/reflect/Proxy
Asciz	getProxyClass;
Asciz	(Ljava/lang/ClassLoader;[Ljava/lang/Class;)Ljava/lang/Class;;
NameAndType	getProxyClass:(Ljava/lang/ClassLoader;[Ljava/lang/Class;)Ljava/lang/Class;
Method	java/lang/reflect/Proxy.getProxyClass:(Ljava/lang/ClassLoader;[Ljava/lang/Class;)Ljava/lang/Class;
NameAndType	resolveProxyClass:([Ljava/lang/String;)Ljava/lang/Class;
Method	java/io/ObjectInputStream.resolveProxyClass:([Ljava/lang/String;)Ljava/lang/Class;
Asciz	interfaces;
Asciz	[Ljava/lang/String;;
Asciz	exceptionResult2;
Asciz	ifaces;
Asciz	([Ljava/lang/String;)Ljava/lang/Class<*>;;
Asciz	(Ljava/io/InputStream;Ljava/lang/ClassLoader;)V;
Asciz	(Ljava/io/InputStream;)V;
NameAndType	"<init>":(Ljava/io/InputStream;)V
Method	java/io/ObjectInputStream."<init>":(Ljava/io/InputStream;)V
Asciz	in;
Asciz	Ljava/io/InputStream;;
Asciz	cl;
Asciz	ScalaSig;
Asciz	InnerClasses;
Asciz	$anonfun$1;
Asciz	scala/ScalaObject;
class	scala/ScalaObject

{
public final java.lang.ClassLoader scala$actors$remote$CustomObjectInputStream$$cl;
  Signature: Ljava/lang/ClassLoader;

public java.lang.Class resolveClass(java.io.ObjectStreamClass);
  Signature: (Ljava/io/ObjectStreamClass;)Ljava/lang/Class;
  Code:
   Stack=2, Locals=4, Args_size=2
	aconst_null
	astore_2
	aload_0
	getfield	Field scala$actors$remote$CustomObjectInputStream$$cl:Ljava/lang/ClassLoader;
	aload_1
	invokevirtual	Method java/io/ObjectStreamClass.getName:()Ljava/lang/String;
	invokevirtual	Method java/lang/ClassLoader.loadClass:(Ljava/lang/String;)Ljava/lang/Class;
	astore_2
	goto	l1 // aload_2
	astore_3
	aload_0
	aload_1
	invokespecial	Method java/io/ObjectInputStream.resolveClass:(Ljava/io/ObjectStreamClass;)Ljava/lang/Class;
	astore_2
l1	aload_2
	areturn
  Labels:
   	l1 = 24 // aload_2
  Exception table:
   from   to  target type
     2    17    17   Class java/lang/ClassNotFoundException

  LocalVariableTable: 
   Start  Length  Slot  Name   Signature
   0      26      0    this       Lscala/actors/remote/CustomObjectInputStream;
   0      26      1    cd       Ljava/io/ObjectStreamClass;
   2      23      2    exceptionResult1       Ljava/lang/Class;

  Signature: length = 0x2
   00 26 

public java.lang.Class resolveProxyClass(java.lang.String[]);
  Signature: ([Ljava/lang/String;)Ljava/lang/Class;
  Code:
   Stack=8, Locals=5, Args_size=2
	aconst_null
	astore_2
	getstatic	Field scala/Predef$.MODULE$:Lscala/Predef$;
	aload_1
	checkcast	class "[Ljava/lang/Object;"
	invokevirtual	Method scala/Predef$.refArrayOps:([Ljava/lang/Object;)Lscala/collection/mutable/ArrayOps;
	new	class scala/actors/remote/CustomObjectInputStream$$anonfun$1
	dup
	aload_0
	invokespecial	Method scala/actors/remote/CustomObjectInputStream$$anonfun$1."<init>":(Lscala/actors/remote/CustomObjectInputStream;)V
	getstatic	Field scala/Array$.MODULE$:Lscala/Array$;
	getstatic	Field scala/reflect/ClassManifest$.MODULE$:Lscala/reflect/ClassManifest$;
	ldc	class java/lang/Class
	getstatic	Field scala/reflect/NoManifest$.MODULE$:Lscala/reflect/NoManifest$;
	getstatic	Field scala/Predef$.MODULE$:Lscala/Predef$;
	iconst_0
	anewarray	class scala/reflect/OptManifest
	checkcast	class "[Ljava/lang/Object;"
	invokevirtual	Method scala/Predef$.wrapRefArray:([Ljava/lang/Object;)Lscala/collection/mutable/WrappedArray;
	invokevirtual	Method scala/reflect/ClassManifest$.classType:(Ljava/lang/Class;Lscala/reflect/OptManifest;Lscala/collection/Seq;)Lscala/reflect/ClassManifest;
	invokevirtual	Method scala/Array$.canBuildFrom:(Lscala/reflect/ClassManifest;)Lscala/collection/generic/CanBuildFrom;
	invokeinterface	InterfaceMethod scala/collection/TraversableLike.map:(Lscala/Function1;Lscala/collection/generic/CanBuildFrom;)Ljava/lang/Object;
	checkcast	class "[Ljava/lang/Class;"
	astore	4
	aload_0
	getfield	Field scala$actors$remote$CustomObjectInputStream$$cl:Ljava/lang/ClassLoader;
	aload	4
	invokestatic	Method java/lang/reflect/Proxy.getProxyClass:(Ljava/lang/ClassLoader;[Ljava/lang/Class;)Ljava/lang/Class;
	astore_2
	goto	l1 // aload_2
	astore_3
	aload_0
	aload_1
	invokespecial	Method java/io/ObjectInputStream.resolveProxyClass:([Ljava/lang/String;)Ljava/lang/Class;
	astore_2
l1	aload_2
	areturn
  Labels:
   	l1 = 80 // aload_2
  Exception table:
   from   to  target type
     2    73    73   Class java/lang/ClassNotFoundException

  LocalVariableTable: 
   Start  Length  Slot  Name   Signature
   0      82      0    this       Lscala/actors/remote/CustomObjectInputStream;
   0      82      1    interfaces       [Ljava/lang/String;
   2      79      2    exceptionResult2       Ljava/lang/Class;
   60      9      4    ifaces       [Ljava/lang/Class;

  Signature: length = 0x2
   00 6F 

public scala.actors.remote.CustomObjectInputStream(java.io.InputStream, java.lang.ClassLoader);
  Signature: (Ljava/io/InputStream;Ljava/lang/ClassLoader;)V
  Code:
   Stack=2, Locals=3, Args_size=3
	aload_0
	aload_2
	putfield	Field scala$actors$remote$CustomObjectInputStream$$cl:Ljava/lang/ClassLoader;
	aload_0
	aload_1
	invokespecial	Method java/io/ObjectInputStream."<init>":(Ljava/io/InputStream;)V
	return
  Labels:
  LocalVariableTable: 
   Start  Length  Slot  Name   Signature
   0      11      0    this       Lscala/actors/remote/CustomObjectInputStream;
   0      11      1    in       Ljava/io/InputStream;
   0      11      2    cl       Ljava/lang/ClassLoader;


}

