Compiled from "Proxy.scala"
public class scala.actors.remote.DelegateActor extends java.lang.Object implements scala.actors.Actor,scala.ScalaObject
  SourceFile: "Proxy.scala"
  ScalaSig: length = 0x2DC
   05 00 6C 06 09 01 02 FFFFFF84 FFFFFF80 FFFFFF80 FFFFFF80 00 02 08 02 0D
   44 65 6C 65 67 61 74 65 41 63 74 6F 72 0A 02 03
   04 01 06 72 65 6D 6F 74 65 0A 02 05 06 01 06 61
   63 74 6F 72 73 0A 01 07 01 05 73 63 61 6C 61 13
   04 00 09 11 15 10 02 0A 0F 0D 01 0B 0A 02 0C 0D
   01 04 6C 61 6E 67 0A 01 0E 01 04 6A 61 76 61 09
   02 10 0B 02 06 4F 62 6A 65 63 74 10 02 12 13 0D
   01 04 09 02 14 04 02 05 41 63 74 6F 72 10 02 16
   17 0D 01 06 09 02 18 06 02 0B 53 63 61 6C 61 4F
   62 6A 65 63 74 08 08 1A 00 FFFFFF82 FFFFFF80 FFFFFFA0 FFFFFF80 04 1C 01
   07 63 72 65 61 74 6F 72 03 00 10 02 1D 1E 0D 01
   02 09 02 1F 02 02 05 50 72 6F 78 79 08 08 21 00
   FFFFFF82 FFFFFF80 FFFFFFA0 FFFFFF80 04 22 01 04 6E 6F 64 65 10 02 1D 23
   09 02 24 02 02 04 4E 6F 64 65 08 08 26 00 FFFFFF82 FFFFFF80
   FFFFFFA0 FFFFFF80 04 27 01 04 6E 61 6D 65 10 02 16 28 09 02
   29 06 02 06 53 79 6D 62 6F 6C 08 08 2B 00 FFFFFF82 FFFFFF80
   FFFFFFA0 FFFFFF80 04 2C 01 06 6B 65 72 6E 65 6C 10 02 1D 2D
   09 02 2E 02 02 09 4E 65 74 4B 65 72 6E 65 6C 08
   05 30 00 FFFFFF84 00 31 01 06 3C 69 6E 69 74 3E 14 05
   32 33 34 35 36 10 02 1D 00 08 05 1A 2F FFFFFFC0 00 1C
   08 05 21 2F FFFFFFC0 00 22 08 05 26 2F FFFFFFC0 00 27 08 05
   2B 2F FFFFFFC0 00 2C 08 07 38 00 FFFFFFC0 FFFFFF80 FFFFFF84 00 39 01 0A
   63 68 61 6E 6E 65 6C 4D 61 70 15 01 3A 10 04 3B
   40 27 42 0D 01 3C 0A 02 3D 3E 01 07 6D 75 74 61
   62 6C 65 0A 02 3F 06 01 0A 63 6F 6C 6C 65 63 74
   69 6F 6E 09 02 41 3C 02 07 48 61 73 68 4D 61 70
   10 03 12 43 45 09 02 44 04 02 0D 4F 75 74 70 75
   74 43 68 61 6E 6E 65 6C 10 02 16 46 09 02 47 06
   02 03 41 6E 79 08 07 49 00 FFFFFFC0 FFFFFF80 FFFFFF84 00 4A 01 0E
   63 68 61 6E 6E 65 6C 4D 61 70 5F 24 65 71 14 02
   4B 4E 10 02 16 4C 09 02 4D 06 02 04 55 6E 69 74
   08 07 4F 48 FFFFFF81 FFFFFF80 FFFFFFC0 00 3A 01 03 78 24 31 08 06
   51 00 FFFFFFA0 FFFFFFA0 04 3A 01 0B 63 68 61 6E 6E 65 6C 4D
   61 70 20 08 07 53 00 FFFFFFC0 FFFFFF80 FFFFFF84 00 54 01 0A 73 65
   73 73 69 6F 6E 4D 61 70 15 01 55 10 04 3B 40 42
   27 08 07 57 00 FFFFFFC0 FFFFFF80 FFFFFF84 00 58 01 0E 73 65 73 73
   69 6F 6E 4D 61 70 5F 24 65 71 14 02 4B 59 08 07
   4F 56 FFFFFF81 FFFFFF80 FFFFFFC0 00 55 08 06 5B 00 FFFFFFA0 FFFFFFA0 04 55 01
   0B 73 65 73 73 69 6F 6E 4D 61 70 20 08 05 5D 00
   FFFFFF84 00 5E 01 03 61 63 74 14 01 4B 08 05 60 00 FFFFFF84
   00 61 01 10 70 72 6F 74 65 63 74 65 64 24 73 65
   6E 64 65 72 15 01 62 14 02 42 63 08 07 4F 5F FFFFFF81
   FFFFFF80 FFFFFFC0 00 32 08 05 65 00 FFFFFF84 00 66 01 0E 70 72 6F
   74 65 63 74 65 64 24 65 78 69 74 14 02 67 6B 14
   01 68 10 02 16 69 09 02 6A 06 02 07 4E 6F 74 68
   69 6E 67 08 07 4F 64 FFFFFF81 FFFFFF80 FFFFFFC0 00 32 
  InnerClass: 
   public final $anon$7=class scala/actors/Actor$$anon$7 of class scala/actors/Actor
   public final $anonfun$loop$1=class scala/actors/Actor$$anonfun$loop$1 of class scala/actors/Actor
   public final $anonfun$act$1=class scala/actors/remote/DelegateActor$$anonfun$act$1 of class scala/actors/remote/DelegateActor
  minor version: 0
  major version: 49
  Constant pool:
Asciz	SourceFile;
Asciz	Proxy.scala;
Asciz	scala$actors$Actor$$blocker$module;
Asciz	Lscala/actors/Actor$blocker$;;
Asciz	exiting;
Asciz	Z;
Asciz	kill;
Asciz	Lscala/Function0;;
Asciz	waitingFor;
Asciz	Lscala/PartialFunction;;
Asciz	waitingForNone;
Asciz	sendBuffer;
Asciz	Lscala/actors/MQueue;;
Asciz	mailbox;
Asciz	senders;
Asciz	Lscala/collection/immutable/List;;
Asciz	shouldExit;
Asciz	exitReason;
Asciz	Ljava/lang/Object;;
Asciz	trapExit;
Asciz	links;
Asciz	scala$actors$Actor$$onTimeout;
Asciz	Lscala/Option;;
Asciz	scala$actors$Actor$$received;
Asciz	scala$actors$Actor$$isSuspended;
Asciz	sessionMap;
Asciz	Lscala/collection/mutable/HashMap;;
Asciz	Lscala/collection/mutable/HashMap<Lscala/actors/OutputChannel<Ljava/lang/Object;>;Lscala/Symbol;>;;
Asciz	Signature;
Asciz	channelMap;
Asciz	Lscala/collection/mutable/HashMap<Lscala/Symbol;Lscala/actors/OutputChannel<Ljava/lang/Object;>;>;;
Asciz	scala$actors$remote$DelegateActor$$kernel;
Asciz	Lscala/actors/remote/NetKernel;;
Asciz	scala$actors$remote$DelegateActor$$name;
Asciz	Lscala/Symbol;;
Asciz	scala$actors$remote$DelegateActor$$node;
Asciz	Lscala/actors/remote/Node;;
Asciz	scala$actors$remote$DelegateActor$$creator;
Asciz	Lscala/actors/remote/Proxy;;
Asciz	<init>;
Asciz	(Lscala/actors/remote/Proxy;Lscala/actors/remote/Node;Lscala/Symbol;Lscala/actors/remote/NetKernel;)V;
Asciz	Code;
Asciz	LineNumberTable;
Asciz	scala/actors/remote/DelegateActor;
class	scala/actors/remote/DelegateActor
NameAndType	scala$actors$remote$DelegateActor$$creator:Lscala/actors/remote/Proxy;
Field	scala/actors/remote/DelegateActor.scala$actors$remote$DelegateActor$$creator:Lscala/actors/remote/Proxy;
NameAndType	scala$actors$remote$DelegateActor$$node:Lscala/actors/remote/Node;
Field	scala/actors/remote/DelegateActor.scala$actors$remote$DelegateActor$$node:Lscala/actors/remote/Node;
NameAndType	scala$actors$remote$DelegateActor$$name:Lscala/Symbol;
Field	scala/actors/remote/DelegateActor.scala$actors$remote$DelegateActor$$name:Lscala/Symbol;
NameAndType	scala$actors$remote$DelegateActor$$kernel:Lscala/actors/remote/NetKernel;
Field	scala/actors/remote/DelegateActor.scala$actors$remote$DelegateActor$$kernel:Lscala/actors/remote/NetKernel;
Asciz	java/lang/Object;
class	java/lang/Object
Asciz	()V;
NameAndType	"<init>":()V
Method	java/lang/Object."<init>":()V
Asciz	scala/actors/Replyable$class;
class	scala/actors/Replyable$class
Asciz	$init$;
Asciz	(Lscala/actors/Replyable;)V;
NameAndType	$init$:(Lscala/actors/Replyable;)V
Method	scala/actors/Replyable$class.$init$:(Lscala/actors/Replyable;)V
Asciz	scala/actors/AbstractActor$class;
class	scala/actors/AbstractActor$class
Asciz	(Lscala/actors/AbstractActor;)V;
NameAndType	$init$:(Lscala/actors/AbstractActor;)V
Method	scala/actors/AbstractActor$class.$init$:(Lscala/actors/AbstractActor;)V
Asciz	scala/actors/Reactor$class;
class	scala/actors/Reactor$class
Asciz	(Lscala/actors/Reactor;)V;
NameAndType	$init$:(Lscala/actors/Reactor;)V
Method	scala/actors/Reactor$class.$init$:(Lscala/actors/Reactor;)V
Asciz	scala/actors/ReplyableReactor$class;
class	scala/actors/ReplyableReactor$class
Asciz	(Lscala/actors/ReplyReactor;)V;
NameAndType	$init$:(Lscala/actors/ReplyReactor;)V
Method	scala/actors/ReplyableReactor$class.$init$:(Lscala/actors/ReplyReactor;)V
Asciz	scala/actors/ReplyReactor$class;
class	scala/actors/ReplyReactor$class
Method	scala/actors/ReplyReactor$class.$init$:(Lscala/actors/ReplyReactor;)V
Asciz	scala/actors/ReplyableActor$class;
class	scala/actors/ReplyableActor$class
Method	scala/actors/ReplyableActor$class.$init$:(Lscala/actors/AbstractActor;)V
Asciz	scala/actors/Actor$class;
class	scala/actors/Actor$class
Asciz	(Lscala/actors/Actor;)V;
NameAndType	$init$:(Lscala/actors/Actor;)V
Method	scala/actors/Actor$class.$init$:(Lscala/actors/Actor;)V
Asciz	scala/collection/mutable/HashMap;
class	scala/collection/mutable/HashMap
Method	scala/collection/mutable/HashMap."<init>":()V
NameAndType	channelMap:Lscala/collection/mutable/HashMap;
Field	scala/actors/remote/DelegateActor.channelMap:Lscala/collection/mutable/HashMap;
NameAndType	sessionMap:Lscala/collection/mutable/HashMap;
Field	scala/actors/remote/DelegateActor.sessionMap:Lscala/collection/mutable/HashMap;
Asciz	this;
Asciz	Lscala/actors/remote/DelegateActor;;
Asciz	creator;
Asciz	node;
Asciz	name;
Asciz	kernel;
Asciz	LocalVariableTable;
Asciz	start;
Asciz	()Lscala/actors/Reactor;;
Asciz	scala/actors/Actor;
class	scala/actors/Actor
Asciz	()Lscala/actors/Actor;;
NameAndType	start:()Lscala/actors/Actor;
InterfaceMethod	scala/actors/Actor.start:()Lscala/actors/Actor;
Asciz	$bang$bang;
Asciz	(Ljava/lang/Object;Lscala/PartialFunction;)Lscala/Function0;;
Asciz	scala/actors/ReplyableActor;
class	scala/actors/ReplyableActor
Asciz	(Ljava/lang/Object;Lscala/PartialFunction;)Lscala/actors/Future;;
NameAndType	$bang$bang:(Ljava/lang/Object;Lscala/PartialFunction;)Lscala/actors/Future;
InterfaceMethod	scala/actors/ReplyableActor.$bang$bang:(Ljava/lang/Object;Lscala/PartialFunction;)Lscala/actors/Future;
Asciz	msg;
Asciz	f;
Asciz	(Ljava/lang/Object;)Lscala/Function0;;
Asciz	(Ljava/lang/Object;)Lscala/actors/Future;;
NameAndType	$bang$bang:(Ljava/lang/Object;)Lscala/actors/Future;
InterfaceMethod	scala/actors/ReplyableActor.$bang$bang:(Ljava/lang/Object;)Lscala/actors/Future;
Asciz	act;
Asciz	scala/actors/remote/DelegateActor$$anonfun$act$1;
class	scala/actors/remote/DelegateActor$$anonfun$act$1
Asciz	(Lscala/actors/remote/DelegateActor;)V;
NameAndType	"<init>":(Lscala/actors/remote/DelegateActor;)V
Method	scala/actors/remote/DelegateActor$$anonfun$act$1."<init>":(Lscala/actors/remote/DelegateActor;)V
Asciz	scala/actors/Actor$$anon$7;
class	scala/actors/Actor$$anon$7
Asciz	(Lscala/Function0;)V;
NameAndType	"<init>":(Lscala/Function0;)V
Method	scala/actors/Actor$$anon$7."<init>":(Lscala/Function0;)V
Asciz	scala/actors/Actor$$anonfun$loop$1;
class	scala/actors/Actor$$anonfun$loop$1
Method	scala/actors/Actor$$anonfun$loop$1."<init>":(Lscala/Function0;)V
Asciz	scala/actors/Actor$;
class	scala/actors/Actor$
Asciz	MODULE$;
Asciz	Lscala/actors/Actor$;;
NameAndType	MODULE$:Lscala/actors/Actor$;
Field	scala/actors/Actor$.MODULE$:Lscala/actors/Actor$;
Asciz	scala/actors/Scheduler$;
class	scala/actors/Scheduler$
Asciz	Lscala/actors/Scheduler$;;
NameAndType	MODULE$:Lscala/actors/Scheduler$;
Field	scala/actors/Scheduler$.MODULE$:Lscala/actors/Scheduler$;
Asciz	rawSelf;
Asciz	(Lscala/actors/IScheduler;)Lscala/actors/Reactor;;
NameAndType	rawSelf:(Lscala/actors/IScheduler;)Lscala/actors/Reactor;
Method	scala/actors/Actor$.rawSelf:(Lscala/actors/IScheduler;)Lscala/actors/Reactor;
Asciz	scala/actors/Reactor;
class	scala/actors/Reactor
Asciz	seq;
Asciz	(Lscala/Function0;Lscala/Function0;)V;
NameAndType	seq:(Lscala/Function0;Lscala/Function0;)V
InterfaceMethod	scala/actors/Reactor.seq:(Lscala/Function0;Lscala/Function0;)V
Asciz	sessionMap_$eq;
Asciz	(Lscala/collection/mutable/HashMap;)V;
Asciz	(Lscala/collection/mutable/HashMap<Lscala/actors/OutputChannel<Ljava/lang/Object;>;Lscala/Symbol;>;)V;
Asciz	()Lscala/collection/mutable/HashMap;;
Asciz	()Lscala/collection/mutable/HashMap<Lscala/actors/OutputChannel<Ljava/lang/Object;>;Lscala/Symbol;>;;
Asciz	channelMap_$eq;
Asciz	(Lscala/collection/mutable/HashMap<Lscala/Symbol;Lscala/actors/OutputChannel<Ljava/lang/Object;>;>;)V;
Asciz	()Lscala/collection/mutable/HashMap<Lscala/Symbol;Lscala/actors/OutputChannel<Ljava/lang/Object;>;>;;
Asciz	protected$exit;
Asciz	(Lscala/actors/remote/DelegateActor;)Lscala/runtime/Nothing$;;
Asciz	exit;
Asciz	()Lscala/runtime/Nothing$;;
NameAndType	exit:()Lscala/runtime/Nothing$;
InterfaceMethod	scala/actors/Actor.exit:()Lscala/runtime/Nothing$;
Asciz	protected$sender;
Asciz	(Lscala/actors/remote/DelegateActor;)Lscala/actors/OutputChannel;;
Asciz	scala/actors/ReplyReactor;
class	scala/actors/ReplyReactor
Asciz	sender;
Asciz	()Lscala/actors/OutputChannel;;
NameAndType	sender:()Lscala/actors/OutputChannel;
InterfaceMethod	scala/actors/ReplyReactor.sender:()Lscala/actors/OutputChannel;
Asciz	(Lscala/actors/remote/DelegateActor;)Lscala/actors/OutputChannel<Ljava/lang/Object;>;;
Asciz	exiting_$eq;
Asciz	(Z)V;
NameAndType	exiting:Z
Field	scala/actors/remote/DelegateActor.exiting:Z
Asciz	()Z;
Asciz	terminated;
NameAndType	terminated:(Lscala/actors/Reactor;)V
Method	scala/actors/Reactor$class.terminated:(Lscala/actors/Reactor;)V
Asciz	(Lscala/actors/Reactor;Lscala/Function0;Lscala/Function0;)V;
NameAndType	seq:(Lscala/actors/Reactor;Lscala/Function0;Lscala/Function0;)V
Method	scala/actors/Reactor$class.seq:(Lscala/actors/Reactor;Lscala/Function0;Lscala/Function0;)V
Asciz	first;
Asciz	next;
Asciz	drainSendBuffer;
Asciz	(Lscala/actors/MQueue;)V;
Asciz	(Lscala/actors/Reactor;Lscala/actors/MQueue;)V;
NameAndType	drainSendBuffer:(Lscala/actors/Reactor;Lscala/actors/MQueue;)V
Method	scala/actors/Reactor$class.drainSendBuffer:(Lscala/actors/Reactor;Lscala/actors/MQueue;)V
Asciz	mbox;
Asciz	receiver;
Asciz	(Lscala/actors/Reactor;)Lscala/actors/Actor;;
NameAndType	receiver:(Lscala/actors/Reactor;)Lscala/actors/Actor;
Method	scala/actors/Reactor$class.receiver:(Lscala/actors/Reactor;)Lscala/actors/Actor;
Asciz	send;
Asciz	(Ljava/lang/Object;Lscala/actors/OutputChannel;)V;
Asciz	(Lscala/actors/Reactor;Ljava/lang/Object;Lscala/actors/OutputChannel;)V;
NameAndType	send:(Lscala/actors/Reactor;Ljava/lang/Object;Lscala/actors/OutputChannel;)V
Method	scala/actors/Reactor$class.send:(Lscala/actors/Reactor;Ljava/lang/Object;Lscala/actors/OutputChannel;)V
Asciz	replyTo;
Asciz	Lscala/actors/OutputChannel;;
Asciz	mailboxSize;
Asciz	()I;
Asciz	(Lscala/actors/Reactor;)I;
NameAndType	mailboxSize:(Lscala/actors/Reactor;)I
Method	scala/actors/Reactor$class.mailboxSize:(Lscala/actors/Reactor;)I
Asciz	exceptionHandler;
Asciz	()Lscala/PartialFunction;;
Asciz	(Lscala/actors/Reactor;)Lscala/PartialFunction;;
NameAndType	exceptionHandler:(Lscala/actors/Reactor;)Lscala/PartialFunction;
Method	scala/actors/Reactor$class.exceptionHandler:(Lscala/actors/Reactor;)Lscala/PartialFunction;
Asciz	scala$actors$Reactor$_setter_$waitingForNone_$eq;
Asciz	(Lscala/PartialFunction;)V;
NameAndType	waitingForNone:Lscala/PartialFunction;
Field	scala/actors/remote/DelegateActor.waitingForNone:Lscala/PartialFunction;
Asciz	scala$actors$Reactor$_setter_$sendBuffer_$eq;
NameAndType	sendBuffer:Lscala/actors/MQueue;
Field	scala/actors/remote/DelegateActor.sendBuffer:Lscala/actors/MQueue;
Asciz	scala$actors$Reactor$_setter_$mailbox_$eq;
NameAndType	mailbox:Lscala/actors/MQueue;
Field	scala/actors/remote/DelegateActor.mailbox:Lscala/actors/MQueue;
Asciz	kill_$eq;
NameAndType	kill:Lscala/Function0;
Field	scala/actors/remote/DelegateActor.kill:Lscala/Function0;
Asciz	()Lscala/Function0;;
Asciz	waitingFor_$eq;
NameAndType	waitingFor:Lscala/PartialFunction;
Field	scala/actors/remote/DelegateActor.waitingFor:Lscala/PartialFunction;
Asciz	()Lscala/actors/MQueue;;
Asciz	searchMailbox;
Asciz	(Lscala/actors/MQueue;Lscala/PartialFunction;Z)V;
Asciz	(Lscala/actors/ReplyReactor;Lscala/actors/MQueue;Lscala/PartialFunction;Z)V;
NameAndType	searchMailbox:(Lscala/actors/ReplyReactor;Lscala/actors/MQueue;Lscala/PartialFunction;Z)V
Method	scala/actors/ReplyReactor$class.searchMailbox:(Lscala/actors/ReplyReactor;Lscala/actors/MQueue;Lscala/PartialFunction;Z)V
Asciz	startMbox;
Asciz	handler;
Asciz	resumeOnSameThread;
Asciz	forward;
Asciz	(Ljava/lang/Object;)V;
Asciz	(Lscala/actors/ReplyReactor;Ljava/lang/Object;)V;
NameAndType	forward:(Lscala/actors/ReplyReactor;Ljava/lang/Object;)V
Method	scala/actors/ReplyReactor$class.forward:(Lscala/actors/ReplyReactor;Ljava/lang/Object;)V
Asciz	$bang;
NameAndType	$bang:(Lscala/actors/ReplyReactor;Ljava/lang/Object;)V
Method	scala/actors/ReplyReactor$class.$bang:(Lscala/actors/ReplyReactor;Ljava/lang/Object;)V
Asciz	reply;
NameAndType	reply:(Lscala/actors/ReplyReactor;Ljava/lang/Object;)V
Method	scala/actors/ReplyReactor$class.reply:(Lscala/actors/ReplyReactor;Ljava/lang/Object;)V
Asciz	(Lscala/actors/ReplyReactor;)Lscala/actors/OutputChannel;;
NameAndType	sender:(Lscala/actors/ReplyReactor;)Lscala/actors/OutputChannel;
Method	scala/actors/ReplyReactor$class.sender:(Lscala/actors/ReplyReactor;)Lscala/actors/OutputChannel;
Asciz	senders_$eq;
Asciz	(Lscala/collection/immutable/List;)V;
NameAndType	senders:Lscala/collection/immutable/List;
Field	scala/actors/remote/DelegateActor.senders:Lscala/collection/immutable/List;
Asciz	()Lscala/collection/immutable/List;;
Asciz	(Lscala/actors/AbstractActor;Ljava/lang/Object;)Lscala/actors/Future;;
NameAndType	$bang$bang:(Lscala/actors/AbstractActor;Ljava/lang/Object;)Lscala/actors/Future;
Method	scala/actors/ReplyableActor$class.$bang$bang:(Lscala/actors/AbstractActor;Ljava/lang/Object;)Lscala/actors/Future;
Asciz	(Lscala/actors/AbstractActor;Ljava/lang/Object;Lscala/PartialFunction;)Lscala/actors/Future;;
NameAndType	$bang$bang:(Lscala/actors/AbstractActor;Ljava/lang/Object;Lscala/PartialFunction;)Lscala/actors/Future;
Method	scala/actors/ReplyableActor$class.$bang$bang:(Lscala/actors/AbstractActor;Ljava/lang/Object;Lscala/PartialFunction;)Lscala/actors/Future;
Asciz	$bang$qmark;
Asciz	(JLjava/lang/Object;)Lscala/Option;;
Asciz	(Lscala/actors/AbstractActor;JLjava/lang/Object;)Lscala/Option;;
NameAndType	$bang$qmark:(Lscala/actors/AbstractActor;JLjava/lang/Object;)Lscala/Option;
Method	scala/actors/ReplyableActor$class.$bang$qmark:(Lscala/actors/AbstractActor;JLjava/lang/Object;)Lscala/Option;
Asciz	msec;
Asciz	J;
Asciz	(Ljava/lang/Object;)Ljava/lang/Object;;
Asciz	(Lscala/actors/AbstractActor;Ljava/lang/Object;)Ljava/lang/Object;;
NameAndType	$bang$qmark:(Lscala/actors/AbstractActor;Ljava/lang/Object;)Ljava/lang/Object;
Method	scala/actors/ReplyableActor$class.$bang$qmark:(Lscala/actors/AbstractActor;Ljava/lang/Object;)Ljava/lang/Object;
Asciz	onTerminate;
Asciz	(Lscala/actors/Actor;Lscala/Function0;)V;
NameAndType	onTerminate:(Lscala/actors/Actor;Lscala/Function0;)V
Method	scala/actors/Actor$class.onTerminate:(Lscala/actors/Actor;Lscala/Function0;)V
Asciz	(Lscala/actors/AbstractActor;Ljava/lang/Object;)V;
Asciz	(Lscala/actors/Actor;Lscala/actors/AbstractActor;Ljava/lang/Object;)V;
NameAndType	exit:(Lscala/actors/Actor;Lscala/actors/AbstractActor;Ljava/lang/Object;)V
Method	scala/actors/Actor$class.exit:(Lscala/actors/Actor;Lscala/actors/AbstractActor;Ljava/lang/Object;)V
Asciz	from;
Asciz	Lscala/actors/AbstractActor;;
Asciz	reason;
Asciz	exitLinked;
Asciz	(Lscala/actors/Actor;Ljava/lang/Object;)V;
NameAndType	exitLinked:(Lscala/actors/Actor;Ljava/lang/Object;)V
Method	scala/actors/Actor$class.exitLinked:(Lscala/actors/Actor;Ljava/lang/Object;)V
NameAndType	exitLinked:(Lscala/actors/Actor;)V
Method	scala/actors/Actor$class.exitLinked:(Lscala/actors/Actor;)V
Asciz	(Lscala/actors/Actor;)Lscala/runtime/Nothing$;;
NameAndType	exit:(Lscala/actors/Actor;)Lscala/runtime/Nothing$;
Method	scala/actors/Actor$class.exit:(Lscala/actors/Actor;)Lscala/runtime/Nothing$;
Asciz	(Ljava/lang/Object;)Lscala/runtime/Nothing$;;
Asciz	(Lscala/actors/Actor;Ljava/lang/Object;)Lscala/runtime/Nothing$;;
NameAndType	exit:(Lscala/actors/Actor;Ljava/lang/Object;)Lscala/runtime/Nothing$;
Method	scala/actors/Actor$class.exit:(Lscala/actors/Actor;Ljava/lang/Object;)Lscala/runtime/Nothing$;
Asciz	unlinkFrom;
Asciz	(Lscala/actors/Actor;Lscala/actors/AbstractActor;)V;
NameAndType	unlinkFrom:(Lscala/actors/Actor;Lscala/actors/AbstractActor;)V
Method	scala/actors/Actor$class.unlinkFrom:(Lscala/actors/Actor;Lscala/actors/AbstractActor;)V
Asciz	unlink;
NameAndType	unlink:(Lscala/actors/Actor;Lscala/actors/AbstractActor;)V
Method	scala/actors/Actor$class.unlink:(Lscala/actors/Actor;Lscala/actors/AbstractActor;)V
Asciz	linkTo;
NameAndType	linkTo:(Lscala/actors/Actor;Lscala/actors/AbstractActor;)V
Method	scala/actors/Actor$class.linkTo:(Lscala/actors/Actor;Lscala/actors/AbstractActor;)V
Asciz	to;
Asciz	link;
Asciz	(Lscala/Function0;)Lscala/actors/Actor;;
Asciz	(Lscala/actors/Actor;Lscala/Function0;)Lscala/actors/Actor;;
NameAndType	link:(Lscala/actors/Actor;Lscala/Function0;)Lscala/actors/Actor;
Method	scala/actors/Actor$class.link:(Lscala/actors/Actor;Lscala/Function0;)Lscala/actors/Actor;
Asciz	body;
Asciz	(Lscala/actors/AbstractActor;)Lscala/actors/AbstractActor;;
Asciz	(Lscala/actors/Actor;Lscala/actors/AbstractActor;)Lscala/actors/AbstractActor;;
NameAndType	link:(Lscala/actors/Actor;Lscala/actors/AbstractActor;)Lscala/actors/AbstractActor;
Method	scala/actors/Actor$class.link:(Lscala/actors/Actor;Lscala/actors/AbstractActor;)Lscala/actors/AbstractActor;
Asciz	(Lscala/actors/Actor;)Lscala/actors/Actor;;
NameAndType	start:(Lscala/actors/Actor;)Lscala/actors/Actor;
Method	scala/actors/Actor$class.start:(Lscala/actors/Actor;)Lscala/actors/Actor;
Asciz	scheduleActor;
Asciz	(Lscala/PartialFunction;Ljava/lang/Object;)V;
Asciz	(Lscala/actors/Actor;Lscala/PartialFunction;Ljava/lang/Object;)V;
NameAndType	scheduleActor:(Lscala/actors/Actor;Lscala/PartialFunction;Ljava/lang/Object;)V
Method	scala/actors/Actor$class.scheduleActor:(Lscala/actors/Actor;Lscala/PartialFunction;Ljava/lang/Object;)V
Asciz	$qmark;
Asciz	()Ljava/lang/Object;;
Asciz	(Lscala/actors/Actor;)Ljava/lang/Object;;
NameAndType	$qmark:(Lscala/actors/Actor;)Ljava/lang/Object;
Method	scala/actors/Actor$class.$qmark:(Lscala/actors/Actor;)Ljava/lang/Object;
Asciz	reactWithin;
Asciz	(JLscala/PartialFunction;)Lscala/runtime/Nothing$;;
Asciz	(Lscala/actors/Actor;JLscala/PartialFunction;)Lscala/runtime/Nothing$;;
NameAndType	reactWithin:(Lscala/actors/Actor;JLscala/PartialFunction;)Lscala/runtime/Nothing$;
Method	scala/actors/Actor$class.reactWithin:(Lscala/actors/Actor;JLscala/PartialFunction;)Lscala/runtime/Nothing$;
Asciz	react;
Asciz	(Lscala/PartialFunction;)Lscala/runtime/Nothing$;;
Asciz	(Lscala/actors/Actor;Lscala/PartialFunction;)Lscala/runtime/Nothing$;;
NameAndType	react:(Lscala/actors/Actor;Lscala/PartialFunction;)Lscala/runtime/Nothing$;
Method	scala/actors/Actor$class.react:(Lscala/actors/Actor;Lscala/PartialFunction;)Lscala/runtime/Nothing$;
Asciz	receiveWithin;
Asciz	(JLscala/PartialFunction;)Ljava/lang/Object;;
Asciz	(Lscala/actors/Actor;JLscala/PartialFunction;)Ljava/lang/Object;;
NameAndType	receiveWithin:(Lscala/actors/Actor;JLscala/PartialFunction;)Ljava/lang/Object;
Method	scala/actors/Actor$class.receiveWithin:(Lscala/actors/Actor;JLscala/PartialFunction;)Ljava/lang/Object;
Asciz	receive;
Asciz	(Lscala/PartialFunction;)Ljava/lang/Object;;
Asciz	(Lscala/actors/Actor;Lscala/PartialFunction;)Ljava/lang/Object;;
NameAndType	receive:(Lscala/actors/Actor;Lscala/PartialFunction;)Ljava/lang/Object;
Method	scala/actors/Actor$class.receive:(Lscala/actors/Actor;Lscala/PartialFunction;)Ljava/lang/Object;
Asciz	resumeReceiver;
Asciz	(Lscala/Tuple2;Lscala/PartialFunction;Z)V;
Asciz	(Lscala/actors/Actor;Lscala/Tuple2;Lscala/PartialFunction;Z)V;
NameAndType	resumeReceiver:(Lscala/actors/Actor;Lscala/Tuple2;Lscala/PartialFunction;Z)V
Method	scala/actors/Actor$class.resumeReceiver:(Lscala/actors/Actor;Lscala/Tuple2;Lscala/PartialFunction;Z)V
Asciz	item;
Asciz	Lscala/Tuple2;;
Asciz	onSameThread;
Asciz	makeReaction;
Asciz	(Lscala/Function0;)Ljava/lang/Runnable;;
Asciz	(Lscala/actors/Actor;Lscala/Function0;)Ljava/lang/Runnable;;
NameAndType	makeReaction:(Lscala/actors/Actor;Lscala/Function0;)Ljava/lang/Runnable;
Method	scala/actors/Actor$class.makeReaction:(Lscala/actors/Actor;Lscala/Function0;)Ljava/lang/Runnable;
Asciz	fun;
Asciz	startSearch;
Asciz	(Ljava/lang/Object;Lscala/actors/OutputChannel;Lscala/PartialFunction;)Lscala/Function0;;
Asciz	(Lscala/actors/Actor;Ljava/lang/Object;Lscala/actors/OutputChannel;Lscala/PartialFunction;)Lscala/Function0;;
NameAndType	startSearch:(Lscala/actors/Actor;Ljava/lang/Object;Lscala/actors/OutputChannel;Lscala/PartialFunction;)Lscala/Function0;
Method	scala/actors/Actor$class.startSearch:(Lscala/actors/Actor;Ljava/lang/Object;Lscala/actors/OutputChannel;Lscala/PartialFunction;)Lscala/Function0;
Asciz	scheduler;
Asciz	()Lscala/actors/IScheduler;;
Asciz	(Lscala/actors/Actor;)Lscala/actors/IScheduler;;
NameAndType	scheduler:(Lscala/actors/Actor;)Lscala/actors/IScheduler;
Method	scala/actors/Actor$class.scheduler:(Lscala/actors/Actor;)Lscala/actors/IScheduler;
Asciz	scala$actors$Actor$$super$resumeReceiver;
Asciz	(Lscala/actors/ReplyReactor;Lscala/Tuple2;Lscala/PartialFunction;Z)V;
NameAndType	resumeReceiver:(Lscala/actors/ReplyReactor;Lscala/Tuple2;Lscala/PartialFunction;Z)V
Method	scala/actors/ReplyReactor$class.resumeReceiver:(Lscala/actors/ReplyReactor;Lscala/Tuple2;Lscala/PartialFunction;Z)V
Asciz	scala$actors$Actor$$super$startSearch;
Asciz	(Lscala/actors/Reactor;Ljava/lang/Object;Lscala/actors/OutputChannel;Lscala/PartialFunction;)Lscala/Function0;;
NameAndType	startSearch:(Lscala/actors/Reactor;Ljava/lang/Object;Lscala/actors/OutputChannel;Lscala/PartialFunction;)Lscala/Function0;
Method	scala/actors/Reactor$class.startSearch:(Lscala/actors/Reactor;Ljava/lang/Object;Lscala/actors/OutputChannel;Lscala/PartialFunction;)Lscala/Function0;
Asciz	shouldExit_$eq;
NameAndType	shouldExit:Z
Field	scala/actors/remote/DelegateActor.shouldExit:Z
Asciz	exitReason_$eq;
NameAndType	exitReason:Ljava/lang/Object;
Field	scala/actors/remote/DelegateActor.exitReason:Ljava/lang/Object;
Asciz	trapExit_$eq;
NameAndType	trapExit:Z
Field	scala/actors/remote/DelegateActor.trapExit:Z
Asciz	links_$eq;
NameAndType	links:Lscala/collection/immutable/List;
Field	scala/actors/remote/DelegateActor.links:Lscala/collection/immutable/List;
Asciz	scala$actors$Actor$$blocker;
Asciz	()Lscala/actors/Actor$blocker$;;
NameAndType	scala$actors$Actor$$blocker$module:Lscala/actors/Actor$blocker$;
Field	scala/actors/remote/DelegateActor.scala$actors$Actor$$blocker$module:Lscala/actors/Actor$blocker$;
Asciz	scala/actors/Actor$blocker$;
class	scala/actors/Actor$blocker$
NameAndType	"<init>":(Lscala/actors/Actor;)V
Method	scala/actors/Actor$blocker$."<init>":(Lscala/actors/Actor;)V
Asciz	scala$actors$Actor$$onTimeout_$eq;
Asciz	(Lscala/Option;)V;
NameAndType	scala$actors$Actor$$onTimeout:Lscala/Option;
Field	scala/actors/remote/DelegateActor.scala$actors$Actor$$onTimeout:Lscala/Option;
Asciz	()Lscala/Option;;
Asciz	scala$actors$Actor$$received_$eq;
NameAndType	scala$actors$Actor$$received:Lscala/Option;
Field	scala/actors/remote/DelegateActor.scala$actors$Actor$$received:Lscala/Option;
Asciz	scala$actors$Actor$$isSuspended_$eq;
NameAndType	scala$actors$Actor$$isSuspended:Z
Field	scala/actors/remote/DelegateActor.scala$actors$Actor$$isSuspended:Z
Asciz	ScalaSig;
Asciz	InnerClasses;
Asciz	$anon$7;
Asciz	$anonfun$loop$1;
Asciz	$anonfun$act$1;
Asciz	scala/ScalaObject;
class	scala/ScalaObject

{
private scala.actors.Actor$blocker$ scala$actors$Actor$$blocker$module;
  Signature: Lscala/actors/Actor$blocker$;

private boolean exiting;
  Signature: Z

private volatile scala.Function0 kill;
  Signature: Lscala/Function0;

private scala.PartialFunction waitingFor;
  Signature: Lscala/PartialFunction;

private final scala.PartialFunction waitingForNone;
  Signature: Lscala/PartialFunction;

private final scala.actors.MQueue sendBuffer;
  Signature: Lscala/actors/MQueue;

private final scala.actors.MQueue mailbox;
  Signature: Lscala/actors/MQueue;

private volatile scala.collection.immutable.List senders;
  Signature: Lscala/collection/immutable/List;

private boolean shouldExit;
  Signature: Z

private java.lang.Object exitReason;
  Signature: Ljava/lang/Object;

private boolean trapExit;
  Signature: Z

private scala.collection.immutable.List links;
  Signature: Lscala/collection/immutable/List;

private scala.Option scala$actors$Actor$$onTimeout;
  Signature: Lscala/Option;

private volatile scala.Option scala$actors$Actor$$received;
  Signature: Lscala/Option;

private volatile boolean scala$actors$Actor$$isSuspended;
  Signature: Z

private scala.collection.mutable.HashMap sessionMap;
  Signature: Lscala/collection/mutable/HashMap;
  Signature: length = 0x2
   00 1C 

private scala.collection.mutable.HashMap channelMap;
  Signature: Lscala/collection/mutable/HashMap;
  Signature: length = 0x2
   00 1F 

public final scala.actors.remote.NetKernel scala$actors$remote$DelegateActor$$kernel;
  Signature: Lscala/actors/remote/NetKernel;

public final scala.Symbol scala$actors$remote$DelegateActor$$name;
  Signature: Lscala/Symbol;

public final scala.actors.remote.Node scala$actors$remote$DelegateActor$$node;
  Signature: Lscala/actors/remote/Node;

public final scala.actors.remote.Proxy scala$actors$remote$DelegateActor$$creator;
  Signature: Lscala/actors/remote/Proxy;

public scala.actors.remote.DelegateActor(scala.actors.remote.Proxy, scala.actors.remote.Node, scala.Symbol, scala.actors.remote.NetKernel);
  Signature: (Lscala/actors/remote/Proxy;Lscala/actors/remote/Node;Lscala/Symbol;Lscala/actors/remote/NetKernel;)V
  Code:
   Stack=3, Locals=5, Args_size=5
	aload_0
	aload_1
	putfield	Field scala$actors$remote$DelegateActor$$creator:Lscala/actors/remote/Proxy;
	aload_0
	aload_2
	putfield	Field scala$actors$remote$DelegateActor$$node:Lscala/actors/remote/Node;
	aload_0
	aload_3
	putfield	Field scala$actors$remote$DelegateActor$$name:Lscala/Symbol;
	aload_0
	aload	4
	putfield	Field scala$actors$remote$DelegateActor$$kernel:Lscala/actors/remote/NetKernel;
	aload_0
	invokespecial	Method java/lang/Object."<init>":()V
	aload_0
	invokestatic	Method scala/actors/Replyable$class.$init$:(Lscala/actors/Replyable;)V
	aload_0
	invokestatic	Method scala/actors/AbstractActor$class.$init$:(Lscala/actors/AbstractActor;)V
	aload_0
	invokestatic	Method scala/actors/Reactor$class.$init$:(Lscala/actors/Reactor;)V
	aload_0
	invokestatic	Method scala/actors/ReplyableReactor$class.$init$:(Lscala/actors/ReplyReactor;)V
	aload_0
	invokestatic	Method scala/actors/ReplyReactor$class.$init$:(Lscala/actors/ReplyReactor;)V
	aload_0
	invokestatic	Method scala/actors/ReplyableActor$class.$init$:(Lscala/actors/AbstractActor;)V
	aload_0
	invokestatic	Method scala/actors/Actor$class.$init$:(Lscala/actors/Actor;)V
	aload_0
	new	class scala/collection/mutable/HashMap
	dup
	invokespecial	Method scala/collection/mutable/HashMap."<init>":()V
	putfield	Field channelMap:Lscala/collection/mutable/HashMap;
	aload_0
	new	class scala/collection/mutable/HashMap
	dup
	invokespecial	Method scala/collection/mutable/HashMap."<init>":()V
	putfield	Field sessionMap:Lscala/collection/mutable/HashMap;
	return
  Labels:
  LocalVariableTable: 
   Start  Length  Slot  Name   Signature
   0      76      0    this       Lscala/actors/remote/DelegateActor;
   0      76      1    creator       Lscala/actors/remote/Proxy;
   0      76      2    node       Lscala/actors/remote/Node;
   0      76      3    name       Lscala/Symbol;
   0      76      4    kernel       Lscala/actors/remote/NetKernel;


public scala.actors.Reactor start();
  Signature: ()Lscala/actors/Reactor;
  Code:
   Stack=1, Locals=1, Args_size=1
	aload_0
	invokeinterface	InterfaceMethod scala/actors/Actor.start:()Lscala/actors/Actor;
	areturn
  Labels:

public scala.Function0 $bang$bang(java.lang.Object, scala.PartialFunction);
  Signature: (Ljava/lang/Object;Lscala/PartialFunction;)Lscala/Function0;
  Code:
   Stack=3, Locals=3, Args_size=3
	aload_0
	aload_1
	aload_2
	invokeinterface	InterfaceMethod scala/actors/ReplyableActor.$bang$bang:(Ljava/lang/Object;Lscala/PartialFunction;)Lscala/actors/Future;
	areturn
  Labels:
  LocalVariableTable: 
   Start  Length  Slot  Name   Signature
   0      9      0    this       Lscala/actors/remote/DelegateActor;
   0      9      1    msg       Ljava/lang/Object;
   0      9      2    f       Lscala/PartialFunction;


public scala.Function0 $bang$bang(java.lang.Object);
  Signature: (Ljava/lang/Object;)Lscala/Function0;
  Code:
   Stack=2, Locals=2, Args_size=2
	aload_0
	aload_1
	invokeinterface	InterfaceMethod scala/actors/ReplyableActor.$bang$bang:(Ljava/lang/Object;)Lscala/actors/Future;
	areturn
  Labels:
  LocalVariableTable: 
   Start  Length  Slot  Name   Signature
   0      8      0    this       Lscala/actors/remote/DelegateActor;
   0      8      1    msg       Ljava/lang/Object;


public void act();
  Signature: ()V
  Code:
   Stack=3, Locals=4, Args_size=1
	new	class scala/actors/remote/DelegateActor$$anonfun$act$1
	dup
	aload_0
	invokespecial	Method scala/actors/remote/DelegateActor$$anonfun$act$1."<init>":(Lscala/actors/remote/DelegateActor;)V
	astore_2
	new	class scala/actors/Actor$$anon$7
	dup
	pop
	aload_2
	invokespecial	Method scala/actors/Actor$$anon$7."<init>":(Lscala/Function0;)V
	new	class scala/actors/Actor$$anonfun$loop$1
	dup
	aload_2
	invokespecial	Method scala/actors/Actor$$anonfun$loop$1."<init>":(Lscala/Function0;)V
	astore_3
	getstatic	Field scala/actors/Actor$.MODULE$:Lscala/actors/Actor$;
	astore_1
	aload_1
	getstatic	Field scala/actors/Scheduler$.MODULE$:Lscala/actors/Scheduler$;
	invokevirtual	Method scala/actors/Actor$.rawSelf:(Lscala/actors/IScheduler;)Lscala/actors/Reactor;
	aload_2
	aload_3
	invokeinterface	InterfaceMethod scala/actors/Reactor.seq:(Lscala/Function0;Lscala/Function0;)V
	return
  Labels:
  LocalVariableTable: 
   Start  Length  Slot  Name   Signature
   0      46      0    this       Lscala/actors/remote/DelegateActor;


public void sessionMap_$eq(scala.collection.mutable.HashMap);
  Signature: (Lscala/collection/mutable/HashMap;)V
  Code:
   Stack=2, Locals=2, Args_size=2
	aload_0
	aload_1
	putfield	Field sessionMap:Lscala/collection/mutable/HashMap;
	return
  Labels:
  Signature: length = 0x2
   00 FFFFFFA2 

public scala.collection.mutable.HashMap sessionMap();
  Signature: ()Lscala/collection/mutable/HashMap;
  Code:
   Stack=1, Locals=1, Args_size=1
	aload_0
	getfield	Field sessionMap:Lscala/collection/mutable/HashMap;
	areturn
  Labels:
  Signature: length = 0x2
   00 FFFFFFA4 

public void channelMap_$eq(scala.collection.mutable.HashMap);
  Signature: (Lscala/collection/mutable/HashMap;)V
  Code:
   Stack=2, Locals=2, Args_size=2
	aload_0
	aload_1
	putfield	Field channelMap:Lscala/collection/mutable/HashMap;
	return
  Labels:
  Signature: length = 0x2
   00 FFFFFFA6 

public scala.collection.mutable.HashMap channelMap();
  Signature: ()Lscala/collection/mutable/HashMap;
  Code:
   Stack=1, Locals=1, Args_size=1
	aload_0
	getfield	Field channelMap:Lscala/collection/mutable/HashMap;
	areturn
  Labels:
  Signature: length = 0x2
   00 FFFFFFA7 

public scala.runtime.Nothing$ protected$exit(scala.actors.remote.DelegateActor);
  Signature: (Lscala/actors/remote/DelegateActor;)Lscala/runtime/Nothing$;
  Code:
   Stack=1, Locals=2, Args_size=2
	aload_1
	invokeinterface	InterfaceMethod scala/actors/Actor.exit:()Lscala/runtime/Nothing$;
	areturn
  Labels:

public scala.actors.OutputChannel protected$sender(scala.actors.remote.DelegateActor);
  Signature: (Lscala/actors/remote/DelegateActor;)Lscala/actors/OutputChannel;
  Code:
   Stack=1, Locals=2, Args_size=2
	aload_1
	invokeinterface	InterfaceMethod scala/actors/ReplyReactor.sender:()Lscala/actors/OutputChannel;
	areturn
  Labels:
  Signature: length = 0x2
   00 FFFFFFB6 

public void exiting_$eq(boolean);
  Signature: (Z)V
  Code:
   Stack=2, Locals=2, Args_size=2
	aload_0
	iload_1
	putfield	Field exiting:Z
	return
  Labels:

public boolean exiting();
  Signature: ()Z
  Code:
   Stack=1, Locals=1, Args_size=1
	aload_0
	getfield	Field exiting:Z
	ireturn
  Labels:

public void terminated();
  Signature: ()V
  Code:
   Stack=1, Locals=1, Args_size=1
	aload_0
	invokestatic	Method scala/actors/Reactor$class.terminated:(Lscala/actors/Reactor;)V
	return
  Labels:

public void seq(scala.Function0, scala.Function0);
  Signature: (Lscala/Function0;Lscala/Function0;)V
  Code:
   Stack=3, Locals=3, Args_size=3
	aload_0
	aload_1
	aload_2
	invokestatic	Method scala/actors/Reactor$class.seq:(Lscala/actors/Reactor;Lscala/Function0;Lscala/Function0;)V
	return
  Labels:
  LocalVariableTable: 
   Start  Length  Slot  Name   Signature
   0      7      0    this       Lscala/actors/remote/DelegateActor;
   0      7      1    first       Lscala/Function0;
   0      7      2    next       Lscala/Function0;


public void drainSendBuffer(scala.actors.MQueue);
  Signature: (Lscala/actors/MQueue;)V
  Code:
   Stack=2, Locals=2, Args_size=2
	aload_0
	aload_1
	invokestatic	Method scala/actors/Reactor$class.drainSendBuffer:(Lscala/actors/Reactor;Lscala/actors/MQueue;)V
	return
  Labels:
  LocalVariableTable: 
   Start  Length  Slot  Name   Signature
   0      6      0    this       Lscala/actors/remote/DelegateActor;
   0      6      1    mbox       Lscala/actors/MQueue;


public scala.actors.Actor receiver();
  Signature: ()Lscala/actors/Actor;
  Code:
   Stack=1, Locals=1, Args_size=1
	aload_0
	invokestatic	Method scala/actors/Reactor$class.receiver:(Lscala/actors/Reactor;)Lscala/actors/Actor;
	areturn
  Labels:

public void send(java.lang.Object, scala.actors.OutputChannel);
  Signature: (Ljava/lang/Object;Lscala/actors/OutputChannel;)V
  Code:
   Stack=3, Locals=3, Args_size=3
	aload_0
	aload_1
	aload_2
	invokestatic	Method scala/actors/Reactor$class.send:(Lscala/actors/Reactor;Ljava/lang/Object;Lscala/actors/OutputChannel;)V
	return
  Labels:
  LocalVariableTable: 
   Start  Length  Slot  Name   Signature
   0      7      0    this       Lscala/actors/remote/DelegateActor;
   0      7      1    msg       Ljava/lang/Object;
   0      7      2    replyTo       Lscala/actors/OutputChannel;


public int mailboxSize();
  Signature: ()I
  Code:
   Stack=1, Locals=1, Args_size=1
	aload_0
	invokestatic	Method scala/actors/Reactor$class.mailboxSize:(Lscala/actors/Reactor;)I
	ireturn
  Labels:

public scala.PartialFunction exceptionHandler();
  Signature: ()Lscala/PartialFunction;
  Code:
   Stack=1, Locals=1, Args_size=1
	aload_0
	invokestatic	Method scala/actors/Reactor$class.exceptionHandler:(Lscala/actors/Reactor;)Lscala/PartialFunction;
	areturn
  Labels:

public void scala$actors$Reactor$_setter_$waitingForNone_$eq(scala.PartialFunction);
  Signature: (Lscala/PartialFunction;)V
  Code:
   Stack=2, Locals=2, Args_size=2
	aload_0
	aload_1
	putfield	Field waitingForNone:Lscala/PartialFunction;
	return
  Labels:

public void scala$actors$Reactor$_setter_$sendBuffer_$eq(scala.actors.MQueue);
  Signature: (Lscala/actors/MQueue;)V
  Code:
   Stack=2, Locals=2, Args_size=2
	aload_0
	aload_1
	putfield	Field sendBuffer:Lscala/actors/MQueue;
	return
  Labels:

public void scala$actors$Reactor$_setter_$mailbox_$eq(scala.actors.MQueue);
  Signature: (Lscala/actors/MQueue;)V
  Code:
   Stack=2, Locals=2, Args_size=2
	aload_0
	aload_1
	putfield	Field mailbox:Lscala/actors/MQueue;
	return
  Labels:

public void kill_$eq(scala.Function0);
  Signature: (Lscala/Function0;)V
  Code:
   Stack=2, Locals=2, Args_size=2
	aload_0
	aload_1
	putfield	Field kill:Lscala/Function0;
	return
  Labels:

public scala.Function0 kill();
  Signature: ()Lscala/Function0;
  Code:
   Stack=1, Locals=1, Args_size=1
	aload_0
	getfield	Field kill:Lscala/Function0;
	areturn
  Labels:

public void waitingFor_$eq(scala.PartialFunction);
  Signature: (Lscala/PartialFunction;)V
  Code:
   Stack=2, Locals=2, Args_size=2
	aload_0
	aload_1
	putfield	Field waitingFor:Lscala/PartialFunction;
	return
  Labels:

public scala.PartialFunction waitingFor();
  Signature: ()Lscala/PartialFunction;
  Code:
   Stack=1, Locals=1, Args_size=1
	aload_0
	getfield	Field waitingFor:Lscala/PartialFunction;
	areturn
  Labels:

public scala.PartialFunction waitingForNone();
  Signature: ()Lscala/PartialFunction;
  Code:
   Stack=1, Locals=1, Args_size=1
	aload_0
	getfield	Field waitingForNone:Lscala/PartialFunction;
	areturn
  Labels:

public scala.actors.MQueue sendBuffer();
  Signature: ()Lscala/actors/MQueue;
  Code:
   Stack=1, Locals=1, Args_size=1
	aload_0
	getfield	Field sendBuffer:Lscala/actors/MQueue;
	areturn
  Labels:

public scala.actors.MQueue mailbox();
  Signature: ()Lscala/actors/MQueue;
  Code:
   Stack=1, Locals=1, Args_size=1
	aload_0
	getfield	Field mailbox:Lscala/actors/MQueue;
	areturn
  Labels:

public void searchMailbox(scala.actors.MQueue, scala.PartialFunction, boolean);
  Signature: (Lscala/actors/MQueue;Lscala/PartialFunction;Z)V
  Code:
   Stack=4, Locals=4, Args_size=4
	aload_0
	aload_1
	aload_2
	iload_3
	invokestatic	Method scala/actors/ReplyReactor$class.searchMailbox:(Lscala/actors/ReplyReactor;Lscala/actors/MQueue;Lscala/PartialFunction;Z)V
	return
  Labels:
  LocalVariableTable: 
   Start  Length  Slot  Name   Signature
   0      8      0    this       Lscala/actors/remote/DelegateActor;
   0      8      1    startMbox       Lscala/actors/MQueue;
   0      8      2    handler       Lscala/PartialFunction;
   0      8      3    resumeOnSameThread       Z


public void forward(java.lang.Object);
  Signature: (Ljava/lang/Object;)V
  Code:
   Stack=2, Locals=2, Args_size=2
	aload_0
	aload_1
	invokestatic	Method scala/actors/ReplyReactor$class.forward:(Lscala/actors/ReplyReactor;Ljava/lang/Object;)V
	return
  Labels:
  LocalVariableTable: 
   Start  Length  Slot  Name   Signature
   0      6      0    this       Lscala/actors/remote/DelegateActor;
   0      6      1    msg       Ljava/lang/Object;


public void $bang(java.lang.Object);
  Signature: (Ljava/lang/Object;)V
  Code:
   Stack=2, Locals=2, Args_size=2
	aload_0
	aload_1
	invokestatic	Method scala/actors/ReplyReactor$class.$bang:(Lscala/actors/ReplyReactor;Ljava/lang/Object;)V
	return
  Labels:
  LocalVariableTable: 
   Start  Length  Slot  Name   Signature
   0      6      0    this       Lscala/actors/remote/DelegateActor;
   0      6      1    msg       Ljava/lang/Object;


public void reply(java.lang.Object);
  Signature: (Ljava/lang/Object;)V
  Code:
   Stack=2, Locals=2, Args_size=2
	aload_0
	aload_1
	invokestatic	Method scala/actors/ReplyReactor$class.reply:(Lscala/actors/ReplyReactor;Ljava/lang/Object;)V
	return
  Labels:
  LocalVariableTable: 
   Start  Length  Slot  Name   Signature
   0      6      0    this       Lscala/actors/remote/DelegateActor;
   0      6      1    msg       Ljava/lang/Object;


public scala.actors.OutputChannel sender();
  Signature: ()Lscala/actors/OutputChannel;
  Code:
   Stack=1, Locals=1, Args_size=1
	aload_0
	invokestatic	Method scala/actors/ReplyReactor$class.sender:(Lscala/actors/ReplyReactor;)Lscala/actors/OutputChannel;
	areturn
  Labels:

public void senders_$eq(scala.collection.immutable.List);
  Signature: (Lscala/collection/immutable/List;)V
  Code:
   Stack=2, Locals=2, Args_size=2
	aload_0
	aload_1
	putfield	Field senders:Lscala/collection/immutable/List;
	return
  Labels:

public scala.collection.immutable.List senders();
  Signature: ()Lscala/collection/immutable/List;
  Code:
   Stack=1, Locals=1, Args_size=1
	aload_0
	getfield	Field senders:Lscala/collection/immutable/List;
	areturn
  Labels:

public scala.actors.Future $bang$bang(java.lang.Object);
  Signature: (Ljava/lang/Object;)Lscala/actors/Future;
  Code:
   Stack=2, Locals=2, Args_size=2
	aload_0
	aload_1
	invokestatic	Method scala/actors/ReplyableActor$class.$bang$bang:(Lscala/actors/AbstractActor;Ljava/lang/Object;)Lscala/actors/Future;
	areturn
  Labels:
  LocalVariableTable: 
   Start  Length  Slot  Name   Signature
   0      6      0    this       Lscala/actors/remote/DelegateActor;
   0      6      1    msg       Ljava/lang/Object;


public scala.actors.Future $bang$bang(java.lang.Object, scala.PartialFunction);
  Signature: (Ljava/lang/Object;Lscala/PartialFunction;)Lscala/actors/Future;
  Code:
   Stack=3, Locals=3, Args_size=3
	aload_0
	aload_1
	aload_2
	invokestatic	Method scala/actors/ReplyableActor$class.$bang$bang:(Lscala/actors/AbstractActor;Ljava/lang/Object;Lscala/PartialFunction;)Lscala/actors/Future;
	areturn
  Labels:
  LocalVariableTable: 
   Start  Length  Slot  Name   Signature
   0      7      0    this       Lscala/actors/remote/DelegateActor;
   0      7      1    msg       Ljava/lang/Object;
   0      7      2    f       Lscala/PartialFunction;


public scala.Option $bang$qmark(long, java.lang.Object);
  Signature: (JLjava/lang/Object;)Lscala/Option;
  Code:
   Stack=4, Locals=4, Args_size=3
	aload_0
	lload_1
	aload_3
	invokestatic	Method scala/actors/ReplyableActor$class.$bang$qmark:(Lscala/actors/AbstractActor;JLjava/lang/Object;)Lscala/Option;
	areturn
  Labels:
  LocalVariableTable: 
   Start  Length  Slot  Name   Signature
   0      7      0    this       Lscala/actors/remote/DelegateActor;
   0      7      1    msec       J
   0      7      3    msg       Ljava/lang/Object;


public java.lang.Object $bang$qmark(java.lang.Object);
  Signature: (Ljava/lang/Object;)Ljava/lang/Object;
  Code:
   Stack=2, Locals=2, Args_size=2
	aload_0
	aload_1
	invokestatic	Method scala/actors/ReplyableActor$class.$bang$qmark:(Lscala/actors/AbstractActor;Ljava/lang/Object;)Ljava/lang/Object;
	areturn
  Labels:
  LocalVariableTable: 
   Start  Length  Slot  Name   Signature
   0      6      0    this       Lscala/actors/remote/DelegateActor;
   0      6      1    msg       Ljava/lang/Object;


public void onTerminate(scala.Function0);
  Signature: (Lscala/Function0;)V
  Code:
   Stack=2, Locals=2, Args_size=2
	aload_0
	aload_1
	invokestatic	Method scala/actors/Actor$class.onTerminate:(Lscala/actors/Actor;Lscala/Function0;)V
	return
  Labels:
  LocalVariableTable: 
   Start  Length  Slot  Name   Signature
   0      6      0    this       Lscala/actors/remote/DelegateActor;
   0      6      1    f       Lscala/Function0;


public void exit(scala.actors.AbstractActor, java.lang.Object);
  Signature: (Lscala/actors/AbstractActor;Ljava/lang/Object;)V
  Code:
   Stack=3, Locals=3, Args_size=3
	aload_0
	aload_1
	aload_2
	invokestatic	Method scala/actors/Actor$class.exit:(Lscala/actors/Actor;Lscala/actors/AbstractActor;Ljava/lang/Object;)V
	return
  Labels:
  LocalVariableTable: 
   Start  Length  Slot  Name   Signature
   0      7      0    this       Lscala/actors/remote/DelegateActor;
   0      7      1    from       Lscala/actors/AbstractActor;
   0      7      2    reason       Ljava/lang/Object;


public void exitLinked(java.lang.Object);
  Signature: (Ljava/lang/Object;)V
  Code:
   Stack=2, Locals=2, Args_size=2
	aload_0
	aload_1
	invokestatic	Method scala/actors/Actor$class.exitLinked:(Lscala/actors/Actor;Ljava/lang/Object;)V
	return
  Labels:
  LocalVariableTable: 
   Start  Length  Slot  Name   Signature
   0      6      0    this       Lscala/actors/remote/DelegateActor;
   0      6      1    reason       Ljava/lang/Object;


public void exitLinked();
  Signature: ()V
  Code:
   Stack=1, Locals=1, Args_size=1
	aload_0
	invokestatic	Method scala/actors/Actor$class.exitLinked:(Lscala/actors/Actor;)V
	return
  Labels:

public scala.runtime.Nothing$ exit();
  Signature: ()Lscala/runtime/Nothing$;
  Code:
   Stack=1, Locals=1, Args_size=1
	aload_0
	invokestatic	Method scala/actors/Actor$class.exit:(Lscala/actors/Actor;)Lscala/runtime/Nothing$;
	areturn
  Labels:

public scala.runtime.Nothing$ exit(java.lang.Object);
  Signature: (Ljava/lang/Object;)Lscala/runtime/Nothing$;
  Code:
   Stack=2, Locals=2, Args_size=2
	aload_0
	aload_1
	invokestatic	Method scala/actors/Actor$class.exit:(Lscala/actors/Actor;Ljava/lang/Object;)Lscala/runtime/Nothing$;
	areturn
  Labels:
  LocalVariableTable: 
   Start  Length  Slot  Name   Signature
   0      6      0    this       Lscala/actors/remote/DelegateActor;
   0      6      1    reason       Ljava/lang/Object;


public void unlinkFrom(scala.actors.AbstractActor);
  Signature: (Lscala/actors/AbstractActor;)V
  Code:
   Stack=2, Locals=2, Args_size=2
	aload_0
	aload_1
	invokestatic	Method scala/actors/Actor$class.unlinkFrom:(Lscala/actors/Actor;Lscala/actors/AbstractActor;)V
	return
  Labels:
  LocalVariableTable: 
   Start  Length  Slot  Name   Signature
   0      6      0    this       Lscala/actors/remote/DelegateActor;
   0      6      1    from       Lscala/actors/AbstractActor;


public void unlink(scala.actors.AbstractActor);
  Signature: (Lscala/actors/AbstractActor;)V
  Code:
   Stack=2, Locals=2, Args_size=2
	aload_0
	aload_1
	invokestatic	Method scala/actors/Actor$class.unlink:(Lscala/actors/Actor;Lscala/actors/AbstractActor;)V
	return
  Labels:
  LocalVariableTable: 
   Start  Length  Slot  Name   Signature
   0      6      0    this       Lscala/actors/remote/DelegateActor;
   0      6      1    from       Lscala/actors/AbstractActor;


public void linkTo(scala.actors.AbstractActor);
  Signature: (Lscala/actors/AbstractActor;)V
  Code:
   Stack=2, Locals=2, Args_size=2
	aload_0
	aload_1
	invokestatic	Method scala/actors/Actor$class.linkTo:(Lscala/actors/Actor;Lscala/actors/AbstractActor;)V
	return
  Labels:
  LocalVariableTable: 
   Start  Length  Slot  Name   Signature
   0      6      0    this       Lscala/actors/remote/DelegateActor;
   0      6      1    to       Lscala/actors/AbstractActor;


public scala.actors.Actor link(scala.Function0);
  Signature: (Lscala/Function0;)Lscala/actors/Actor;
  Code:
   Stack=2, Locals=2, Args_size=2
	aload_0
	aload_1
	invokestatic	Method scala/actors/Actor$class.link:(Lscala/actors/Actor;Lscala/Function0;)Lscala/actors/Actor;
	areturn
  Labels:
  LocalVariableTable: 
   Start  Length  Slot  Name   Signature
   0      6      0    this       Lscala/actors/remote/DelegateActor;
   0      6      1    body       Lscala/Function0;


public scala.actors.AbstractActor link(scala.actors.AbstractActor);
  Signature: (Lscala/actors/AbstractActor;)Lscala/actors/AbstractActor;
  Code:
   Stack=2, Locals=2, Args_size=2
	aload_0
	aload_1
	invokestatic	Method scala/actors/Actor$class.link:(Lscala/actors/Actor;Lscala/actors/AbstractActor;)Lscala/actors/AbstractActor;
	areturn
  Labels:
  LocalVariableTable: 
   Start  Length  Slot  Name   Signature
   0      6      0    this       Lscala/actors/remote/DelegateActor;
   0      6      1    to       Lscala/actors/AbstractActor;


public scala.actors.Actor start();
  Signature: ()Lscala/actors/Actor;
  Code:
   Stack=1, Locals=1, Args_size=1
	aload_0
	invokestatic	Method scala/actors/Actor$class.start:(Lscala/actors/Actor;)Lscala/actors/Actor;
	areturn
  Labels:

public void scheduleActor(scala.PartialFunction, java.lang.Object);
  Signature: (Lscala/PartialFunction;Ljava/lang/Object;)V
  Code:
   Stack=3, Locals=3, Args_size=3
	aload_0
	aload_1
	aload_2
	invokestatic	Method scala/actors/Actor$class.scheduleActor:(Lscala/actors/Actor;Lscala/PartialFunction;Ljava/lang/Object;)V
	return
  Labels:
  LocalVariableTable: 
   Start  Length  Slot  Name   Signature
   0      7      0    this       Lscala/actors/remote/DelegateActor;
   0      7      1    f       Lscala/PartialFunction;
   0      7      2    msg       Ljava/lang/Object;


public java.lang.Object $qmark();
  Signature: ()Ljava/lang/Object;
  Code:
   Stack=1, Locals=1, Args_size=1
	aload_0
	invokestatic	Method scala/actors/Actor$class.$qmark:(Lscala/actors/Actor;)Ljava/lang/Object;
	areturn
  Labels:

public scala.runtime.Nothing$ reactWithin(long, scala.PartialFunction);
  Signature: (JLscala/PartialFunction;)Lscala/runtime/Nothing$;
  Code:
   Stack=4, Locals=4, Args_size=3
	aload_0
	lload_1
	aload_3
	invokestatic	Method scala/actors/Actor$class.reactWithin:(Lscala/actors/Actor;JLscala/PartialFunction;)Lscala/runtime/Nothing$;
	areturn
  Labels:
  LocalVariableTable: 
   Start  Length  Slot  Name   Signature
   0      7      0    this       Lscala/actors/remote/DelegateActor;
   0      7      1    msec       J
   0      7      3    f       Lscala/PartialFunction;


public scala.runtime.Nothing$ react(scala.PartialFunction);
  Signature: (Lscala/PartialFunction;)Lscala/runtime/Nothing$;
  Code:
   Stack=2, Locals=2, Args_size=2
	aload_0
	aload_1
	invokestatic	Method scala/actors/Actor$class.react:(Lscala/actors/Actor;Lscala/PartialFunction;)Lscala/runtime/Nothing$;
	areturn
  Labels:
  LocalVariableTable: 
   Start  Length  Slot  Name   Signature
   0      6      0    this       Lscala/actors/remote/DelegateActor;
   0      6      1    f       Lscala/PartialFunction;


public java.lang.Object receiveWithin(long, scala.PartialFunction);
  Signature: (JLscala/PartialFunction;)Ljava/lang/Object;
  Code:
   Stack=4, Locals=4, Args_size=3
	aload_0
	lload_1
	aload_3
	invokestatic	Method scala/actors/Actor$class.receiveWithin:(Lscala/actors/Actor;JLscala/PartialFunction;)Ljava/lang/Object;
	areturn
  Labels:
  LocalVariableTable: 
   Start  Length  Slot  Name   Signature
   0      7      0    this       Lscala/actors/remote/DelegateActor;
   0      7      1    msec       J
   0      7      3    f       Lscala/PartialFunction;


public java.lang.Object receive(scala.PartialFunction);
  Signature: (Lscala/PartialFunction;)Ljava/lang/Object;
  Code:
   Stack=2, Locals=2, Args_size=2
	aload_0
	aload_1
	invokestatic	Method scala/actors/Actor$class.receive:(Lscala/actors/Actor;Lscala/PartialFunction;)Ljava/lang/Object;
	areturn
  Labels:
  LocalVariableTable: 
   Start  Length  Slot  Name   Signature
   0      6      0    this       Lscala/actors/remote/DelegateActor;
   0      6      1    f       Lscala/PartialFunction;


public void resumeReceiver(scala.Tuple2, scala.PartialFunction, boolean);
  Signature: (Lscala/Tuple2;Lscala/PartialFunction;Z)V
  Code:
   Stack=4, Locals=4, Args_size=4
	aload_0
	aload_1
	aload_2
	iload_3
	invokestatic	Method scala/actors/Actor$class.resumeReceiver:(Lscala/actors/Actor;Lscala/Tuple2;Lscala/PartialFunction;Z)V
	return
  Labels:
  LocalVariableTable: 
   Start  Length  Slot  Name   Signature
   0      8      0    this       Lscala/actors/remote/DelegateActor;
   0      8      1    item       Lscala/Tuple2;
   0      8      2    handler       Lscala/PartialFunction;
   0      8      3    onSameThread       Z


public java.lang.Runnable makeReaction(scala.Function0);
  Signature: (Lscala/Function0;)Ljava/lang/Runnable;
  Code:
   Stack=2, Locals=2, Args_size=2
	aload_0
	aload_1
	invokestatic	Method scala/actors/Actor$class.makeReaction:(Lscala/actors/Actor;Lscala/Function0;)Ljava/lang/Runnable;
	areturn
  Labels:
  LocalVariableTable: 
   Start  Length  Slot  Name   Signature
   0      6      0    this       Lscala/actors/remote/DelegateActor;
   0      6      1    fun       Lscala/Function0;


public scala.Function0 startSearch(java.lang.Object, scala.actors.OutputChannel, scala.PartialFunction);
  Signature: (Ljava/lang/Object;Lscala/actors/OutputChannel;Lscala/PartialFunction;)Lscala/Function0;
  Code:
   Stack=4, Locals=4, Args_size=4
	aload_0
	aload_1
	aload_2
	aload_3
	invokestatic	Method scala/actors/Actor$class.startSearch:(Lscala/actors/Actor;Ljava/lang/Object;Lscala/actors/OutputChannel;Lscala/PartialFunction;)Lscala/Function0;
	areturn
  Labels:
  LocalVariableTable: 
   Start  Length  Slot  Name   Signature
   0      8      0    this       Lscala/actors/remote/DelegateActor;
   0      8      1    msg       Ljava/lang/Object;
   0      8      2    replyTo       Lscala/actors/OutputChannel;
   0      8      3    handler       Lscala/PartialFunction;


public scala.actors.IScheduler scheduler();
  Signature: ()Lscala/actors/IScheduler;
  Code:
   Stack=1, Locals=1, Args_size=1
	aload_0
	invokestatic	Method scala/actors/Actor$class.scheduler:(Lscala/actors/Actor;)Lscala/actors/IScheduler;
	areturn
  Labels:

public final void scala$actors$Actor$$super$resumeReceiver(scala.Tuple2, scala.PartialFunction, boolean);
  Signature: (Lscala/Tuple2;Lscala/PartialFunction;Z)V
  Code:
   Stack=4, Locals=4, Args_size=4
	aload_0
	aload_1
	aload_2
	iload_3
	invokestatic	Method scala/actors/ReplyReactor$class.resumeReceiver:(Lscala/actors/ReplyReactor;Lscala/Tuple2;Lscala/PartialFunction;Z)V
	return
  Labels:
  LocalVariableTable: 
   Start  Length  Slot  Name   Signature
   0      8      0    this       Lscala/actors/remote/DelegateActor;
   0      8      1    item       Lscala/Tuple2;
   0      8      2    handler       Lscala/PartialFunction;
   0      8      3    onSameThread       Z


public final scala.Function0 scala$actors$Actor$$super$startSearch(java.lang.Object, scala.actors.OutputChannel, scala.PartialFunction);
  Signature: (Ljava/lang/Object;Lscala/actors/OutputChannel;Lscala/PartialFunction;)Lscala/Function0;
  Code:
   Stack=4, Locals=4, Args_size=4
	aload_0
	aload_1
	aload_2
	aload_3
	invokestatic	Method scala/actors/Reactor$class.startSearch:(Lscala/actors/Reactor;Ljava/lang/Object;Lscala/actors/OutputChannel;Lscala/PartialFunction;)Lscala/Function0;
	areturn
  Labels:
  LocalVariableTable: 
   Start  Length  Slot  Name   Signature
   0      8      0    this       Lscala/actors/remote/DelegateActor;
   0      8      1    msg       Ljava/lang/Object;
   0      8      2    replyTo       Lscala/actors/OutputChannel;
   0      8      3    handler       Lscala/PartialFunction;


public void shouldExit_$eq(boolean);
  Signature: (Z)V
  Code:
   Stack=2, Locals=2, Args_size=2
	aload_0
	iload_1
	putfield	Field shouldExit:Z
	return
  Labels:

public boolean shouldExit();
  Signature: ()Z
  Code:
   Stack=1, Locals=1, Args_size=1
	aload_0
	getfield	Field shouldExit:Z
	ireturn
  Labels:

public void exitReason_$eq(java.lang.Object);
  Signature: (Ljava/lang/Object;)V
  Code:
   Stack=2, Locals=2, Args_size=2
	aload_0
	aload_1
	putfield	Field exitReason:Ljava/lang/Object;
	return
  Labels:

public java.lang.Object exitReason();
  Signature: ()Ljava/lang/Object;
  Code:
   Stack=1, Locals=1, Args_size=1
	aload_0
	getfield	Field exitReason:Ljava/lang/Object;
	areturn
  Labels:

public void trapExit_$eq(boolean);
  Signature: (Z)V
  Code:
   Stack=2, Locals=2, Args_size=2
	aload_0
	iload_1
	putfield	Field trapExit:Z
	return
  Labels:

public boolean trapExit();
  Signature: ()Z
  Code:
   Stack=1, Locals=1, Args_size=1
	aload_0
	getfield	Field trapExit:Z
	ireturn
  Labels:

public void links_$eq(scala.collection.immutable.List);
  Signature: (Lscala/collection/immutable/List;)V
  Code:
   Stack=2, Locals=2, Args_size=2
	aload_0
	aload_1
	putfield	Field links:Lscala/collection/immutable/List;
	return
  Labels:

public scala.collection.immutable.List links();
  Signature: ()Lscala/collection/immutable/List;
  Code:
   Stack=1, Locals=1, Args_size=1
	aload_0
	getfield	Field links:Lscala/collection/immutable/List;
	areturn
  Labels:

public final scala.actors.Actor$blocker$ scala$actors$Actor$$blocker();
  Signature: ()Lscala/actors/Actor$blocker$;
  Code:
   Stack=4, Locals=1, Args_size=1
	aload_0
	getfield	Field scala$actors$Actor$$blocker$module:Lscala/actors/Actor$blocker$;
	ifnonnull	l1 // aload_0
	aload_0
	new	class scala/actors/Actor$blocker$
	dup
	aload_0
	invokespecial	Method scala/actors/Actor$blocker$."<init>":(Lscala/actors/Actor;)V
	putfield	Field scala$actors$Actor$$blocker$module:Lscala/actors/Actor$blocker$;
l1	aload_0
	getfield	Field scala$actors$Actor$$blocker$module:Lscala/actors/Actor$blocker$;
	areturn
  Labels:
   	l1 = 19 // aload_0

public final void scala$actors$Actor$$onTimeout_$eq(scala.Option);
  Signature: (Lscala/Option;)V
  Code:
   Stack=2, Locals=2, Args_size=2
	aload_0
	aload_1
	putfield	Field scala$actors$Actor$$onTimeout:Lscala/Option;
	return
  Labels:

public final scala.Option scala$actors$Actor$$onTimeout();
  Signature: ()Lscala/Option;
  Code:
   Stack=1, Locals=1, Args_size=1
	aload_0
	getfield	Field scala$actors$Actor$$onTimeout:Lscala/Option;
	areturn
  Labels:

public final void scala$actors$Actor$$received_$eq(scala.Option);
  Signature: (Lscala/Option;)V
  Code:
   Stack=2, Locals=2, Args_size=2
	aload_0
	aload_1
	putfield	Field scala$actors$Actor$$received:Lscala/Option;
	return
  Labels:

public final scala.Option scala$actors$Actor$$received();
  Signature: ()Lscala/Option;
  Code:
   Stack=1, Locals=1, Args_size=1
	aload_0
	getfield	Field scala$actors$Actor$$received:Lscala/Option;
	areturn
  Labels:

public final void scala$actors$Actor$$isSuspended_$eq(boolean);
  Signature: (Z)V
  Code:
   Stack=2, Locals=2, Args_size=2
	aload_0
	iload_1
	putfield	Field scala$actors$Actor$$isSuspended:Z
	return
  Labels:

public final boolean scala$actors$Actor$$isSuspended();
  Signature: ()Z
  Code:
   Stack=1, Locals=1, Args_size=1
	aload_0
	getfield	Field scala$actors$Actor$$isSuspended:Z
	ireturn
  Labels:

}

