Compiled from "Proxy.scala"
public final class scala.actors.remote.DelegateActor$$anonfun$act$1 extends java.lang.Object implements scala.Function0,scala.ScalaObject,java.io.Serializable
  SourceFile: "Proxy.scala"
  Scala: length = 0x
   
  InnerClass: 
   public final $anonfun$act$1=class scala/actors/remote/DelegateActor$$anonfun$act$1 of class scala/actors/remote/DelegateActor
   public final $anonfun$apply$1=class scala/actors/remote/DelegateActor$$anonfun$act$1$$anonfun$apply$1 of class scala/actors/remote/DelegateActor$$anonfun$act$1
  minor version: 0
  major version: 49
  Constant pool:
Asciz	SourceFile;
Asciz	Proxy.scala;
Asciz	<clinit>;
Asciz	()V;
Asciz	Code;
Asciz	serialVersionUID;
Asciz	J;
Asciz	scala/actors/remote/DelegateActor$$anonfun$act$1;
class	scala/actors/remote/DelegateActor$$anonfun$act$1
NameAndType	serialVersionUID:J
Field	scala/actors/remote/DelegateActor$$anonfun$act$1.serialVersionUID:J
Asciz	$outer;
Asciz	Lscala/actors/remote/DelegateActor;;
Asciz	<init>;
Asciz	(Lscala/actors/remote/DelegateActor;)V;
Asciz	LineNumberTable;
Asciz	java/lang/NullPointerException;
class	java/lang/NullPointerException
NameAndType	"<init>":()V
Method	java/lang/NullPointerException."<init>":()V
NameAndType	$outer:Lscala/actors/remote/DelegateActor;
Field	scala/actors/remote/DelegateActor$$anonfun$act$1.$outer:Lscala/actors/remote/DelegateActor;
Asciz	java/lang/Object;
class	java/lang/Object
Method	java/lang/Object."<init>":()V
Asciz	scala/Function0$class;
class	scala/Function0$class
Asciz	$init$;
Asciz	(Lscala/Function0;)V;
NameAndType	$init$:(Lscala/Function0;)V
Method	scala/Function0$class.$init$:(Lscala/Function0;)V
Asciz	this;
Asciz	Lscala/actors/remote/DelegateActor$$anonfun$act$1;;
Asciz	LocalVariableTable;
Asciz	apply;
Asciz	()Ljava/lang/Object;;
Asciz	()Lscala/runtime/Nothing$;;
NameAndType	apply:()Lscala/runtime/Nothing$;
Method	scala/actors/remote/DelegateActor$$anonfun$act$1.apply:()Lscala/runtime/Nothing$;
Asciz	scala$actors$remote$DelegateActor$$anonfun$$$outer;
Asciz	()Lscala/actors/remote/DelegateActor;;
Asciz	scala/actors/remote/DelegateActor$$anonfun$act$1$$anonfun$apply$1;
class	scala/actors/remote/DelegateActor$$anonfun$act$1$$anonfun$apply$1
Asciz	(Lscala/actors/remote/DelegateActor$$anonfun$act$1;)V;
NameAndType	"<init>":(Lscala/actors/remote/DelegateActor$$anonfun$act$1;)V
Method	scala/actors/remote/DelegateActor$$anonfun$act$1$$anonfun$apply$1."<init>":(Lscala/actors/remote/DelegateActor$$anonfun$act$1;)V
Asciz	scala/actors/Actor;
class	scala/actors/Actor
Asciz	react;
Asciz	(Lscala/PartialFunction;)Lscala/runtime/Nothing$;;
NameAndType	react:(Lscala/PartialFunction;)Lscala/runtime/Nothing$;
InterfaceMethod	scala/actors/Actor.react:(Lscala/PartialFunction;)Lscala/runtime/Nothing$;
Asciz	toString;
Asciz	()Ljava/lang/String;;
Asciz	(Lscala/Function0;)Ljava/lang/String;;
NameAndType	toString:(Lscala/Function0;)Ljava/lang/String;
Method	scala/Function0$class.toString:(Lscala/Function0;)Ljava/lang/String;
Asciz	Scala;
Asciz	InnerClasses;
Asciz	scala/actors/remote/DelegateActor;
class	scala/actors/remote/DelegateActor
Asciz	$anonfun$act$1;
Asciz	$anonfun$apply$1;
Asciz	scala/Function0;
class	scala/Function0
Asciz	scala/ScalaObject;
class	scala/ScalaObject
Asciz	java/io/Serializable;
class	java/io/Serializable

{
public static final long serialVersionUID;
  Signature: J

public final scala.actors.remote.DelegateActor $outer;
  Signature: Lscala/actors/remote/DelegateActor;

public static {};
  Signature: ()V
  Code:
   Stack=2, Locals=0, Args_size=0
	lconst_0
	putstatic	Field serialVersionUID:J
	return
  Labels:

public scala.actors.remote.DelegateActor$$anonfun$act$1(scala.actors.remote.DelegateActor);
  Signature: (Lscala/actors/remote/DelegateActor;)V
  Code:
   Stack=2, Locals=2, Args_size=2
	aload_1
	ifnonnull	l1 // aload_0
	new	class java/lang/NullPointerException
	dup
	invokespecial	Method java/lang/NullPointerException."<init>":()V
	athrow
l1	aload_0
	aload_1
	putfield	Field $outer:Lscala/actors/remote/DelegateActor;
	aload_0
	invokespecial	Method java/lang/Object."<init>":()V
	aload_0
	invokestatic	Method scala/Function0$class.$init$:(Lscala/Function0;)V
	return
  Labels:
   	l1 = 12 // aload_0
  LocalVariableTable: 
   Start  Length  Slot  Name   Signature
   0      26      0    this       Lscala/actors/remote/DelegateActor$$anonfun$act$1;
   0      26      1    $outer       Lscala/actors/remote/DelegateActor;


public final java.lang.Object apply();
  Signature: ()Ljava/lang/Object;
  Code:
   Stack=1, Locals=2, Args_size=1
	aload_0
	getfield	Field $outer:Lscala/actors/remote/DelegateActor;
	astore_1
	aload_0
	invokevirtual	Method apply:()Lscala/runtime/Nothing$;
	athrow
  Labels:
  LocalVariableTable: 
   Start  Length  Slot  Name   Signature
   0      10      0    this       Lscala/actors/remote/DelegateActor$$anonfun$act$1;


public scala.actors.remote.DelegateActor scala$actors$remote$DelegateActor$$anonfun$$$outer();
  Signature: ()Lscala/actors/remote/DelegateActor;
  Code:
   Stack=1, Locals=1, Args_size=1
	aload_0
	getfield	Field $outer:Lscala/actors/remote/DelegateActor;
	areturn
  Labels:

public final scala.runtime.Nothing$ apply();
  Signature: ()Lscala/runtime/Nothing$;
  Code:
   Stack=4, Locals=2, Args_size=1
	aload_0
	getfield	Field $outer:Lscala/actors/remote/DelegateActor;
	astore_1
	aload_0
	getfield	Field $outer:Lscala/actors/remote/DelegateActor;
	new	class scala/actors/remote/DelegateActor$$anonfun$act$1$$anonfun$apply$1
	dup
	aload_0
	invokespecial	Method scala/actors/remote/DelegateActor$$anonfun$act$1$$anonfun$apply$1."<init>":(Lscala/actors/remote/DelegateActor$$anonfun$act$1;)V
	invokeinterface	InterfaceMethod scala/actors/Actor.react:(Lscala/PartialFunction;)Lscala/runtime/Nothing$;
	areturn
  Labels:
  LocalVariableTable: 
   Start  Length  Slot  Name   Signature
   0      23      0    this       Lscala/actors/remote/DelegateActor$$anonfun$act$1;


public java.lang.String toString();
  Signature: ()Ljava/lang/String;
  Code:
   Stack=1, Locals=1, Args_size=1
	aload_0
	invokestatic	Method scala/Function0$class.toString:(Lscala/Function0;)Ljava/lang/String;
	areturn
  Labels:

}

