Compiled from "Proxy.scala"
public final class scala.actors.remote.DelegateActor$$anonfun$act$1$$anonfun$apply$1 extends java.lang.Object implements scala.PartialFunction,scala.ScalaObject,java.io.Serializable
  SourceFile: "Proxy.scala"
  Scala: length = 0x
   
  InnerClass: 
   public final #347= #110 of #115; //$anonfun$act$1=class scala/actors/remote/DelegateActor$$anonfun$act$1 of class scala/actors/remote/DelegateActor
   public final #348= #22 of #110; //$anonfun$apply$1=class scala/actors/remote/DelegateActor$$anonfun$act$1$$anonfun$apply$1 of class scala/actors/remote/DelegateActor$$anonfun$act$1
  minor version: 0
  major version: 49
  Constant pool:
const #1 = Asciz	SourceFile;
const #2 = Asciz	Proxy.scala;
const #3 = Asciz	<clinit>;
const #4 = Asciz	()V;
const #5 = Asciz	Code;
const #6 = Asciz	scala/Symbol$;
const #7 = class	#6;	//  scala/Symbol$
const #8 = Asciz	MODULE$;
const #9 = Asciz	Lscala/Symbol$;;
const #10 = NameAndType	#8:#9;//  MODULE$:Lscala/Symbol$;
const #11 = Field	#7.#10;	//  scala/Symbol$.MODULE$:Lscala/Symbol$;
const #12 = Asciz	LineNumberTable;
const #13 = Asciz	nosession;
const #14 = String	#13;	//  nosession
const #15 = Asciz	apply;
const #16 = Asciz	(Ljava/lang/Object;)Ljava/lang/Object;;
const #17 = NameAndType	#15:#16;//  apply:(Ljava/lang/Object;)Ljava/lang/Object;
const #18 = Method	#7.#17;	//  scala/Symbol$.apply:(Ljava/lang/Object;)Ljava/lang/Object;
const #19 = Asciz	scala/Symbol;
const #20 = class	#19;	//  scala/Symbol
const #21 = Asciz	scala/actors/remote/DelegateActor$$anonfun$act$1$$anonfun$apply$1;
const #22 = class	#21;	//  scala/actors/remote/DelegateActor$$anonfun$act$1$$anonfun$apply$1
const #23 = Asciz	symbol$1;
const #24 = Asciz	Lscala/Symbol;;
const #25 = NameAndType	#23:#24;//  symbol$1:Lscala/Symbol;
const #26 = Field	#22.#25;	//  scala/actors/remote/DelegateActor$$anonfun$act$1$$anonfun$apply$1.symbol$1:Lscala/Symbol;
const #27 = Asciz	serialVersionUID;
const #28 = Asciz	J;
const #29 = NameAndType	#27:#28;//  serialVersionUID:J
const #30 = Field	#22.#29;	//  scala/actors/remote/DelegateActor$$anonfun$act$1$$anonfun$apply$1.serialVersionUID:J
const #31 = Asciz	$outer;
const #32 = Asciz	Lscala/actors/remote/DelegateActor$$anonfun$act$1;;
const #33 = Asciz	<init>;
const #34 = Asciz	(Lscala/actors/remote/DelegateActor$$anonfun$act$1;)V;
const #35 = Asciz	java/lang/NullPointerException;
const #36 = class	#35;	//  java/lang/NullPointerException
const #37 = NameAndType	#33:#4;//  "<init>":()V
const #38 = Method	#36.#37;	//  java/lang/NullPointerException."<init>":()V
const #39 = NameAndType	#31:#32;//  $outer:Lscala/actors/remote/DelegateActor$$anonfun$act$1;
const #40 = Field	#22.#39;	//  scala/actors/remote/DelegateActor$$anonfun$act$1$$anonfun$apply$1.$outer:Lscala/actors/remote/DelegateActor$$anonfun$act$1;
const #41 = Asciz	java/lang/Object;
const #42 = class	#41;	//  java/lang/Object
const #43 = Method	#42.#37;	//  java/lang/Object."<init>":()V
const #44 = Asciz	scala/Function1$class;
const #45 = class	#44;	//  scala/Function1$class
const #46 = Asciz	$init$;
const #47 = Asciz	(Lscala/Function1;)V;
const #48 = NameAndType	#46:#47;//  $init$:(Lscala/Function1;)V
const #49 = Method	#45.#48;	//  scala/Function1$class.$init$:(Lscala/Function1;)V
const #50 = Asciz	scala/PartialFunction$class;
const #51 = class	#50;	//  scala/PartialFunction$class
const #52 = Asciz	(Lscala/PartialFunction;)V;
const #53 = NameAndType	#46:#52;//  $init$:(Lscala/PartialFunction;)V
const #54 = Method	#51.#53;	//  scala/PartialFunction$class.$init$:(Lscala/PartialFunction;)V
const #55 = Asciz	this;
const #56 = Asciz	Lscala/actors/remote/DelegateActor$$anonfun$act$1$$anonfun$apply$1;;
const #57 = Asciz	LocalVariableTable;
const #58 = Asciz	(Ljava/lang/Object;)V;
const #59 = NameAndType	#15:#58;//  apply:(Ljava/lang/Object;)V
const #60 = Method	#22.#59;	//  scala/actors/remote/DelegateActor$$anonfun$act$1$$anonfun$apply$1.apply:(Ljava/lang/Object;)V
const #61 = Asciz	scala/runtime/BoxedUnit;
const #62 = class	#61;	//  scala/runtime/BoxedUnit
const #63 = Asciz	UNIT;
const #64 = Asciz	Lscala/runtime/BoxedUnit;;
const #65 = NameAndType	#63:#64;//  UNIT:Lscala/runtime/BoxedUnit;
const #66 = Field	#62.#65;	//  scala/runtime/BoxedUnit.UNIT:Lscala/runtime/BoxedUnit;
const #67 = Asciz	v1;
const #68 = Asciz	Ljava/lang/Object;;
const #69 = Asciz	andThen;
const #70 = Asciz	(Lscala/Function1;)Lscala/Function1;;
const #71 = Asciz	scala/PartialFunction;
const #72 = class	#71;	//  scala/PartialFunction
const #73 = Asciz	(Lscala/Function1;)Lscala/PartialFunction;;
const #74 = NameAndType	#69:#73;//  andThen:(Lscala/Function1;)Lscala/PartialFunction;
const #75 = InterfaceMethod	#72.#74;	//  scala/PartialFunction.andThen:(Lscala/Function1;)Lscala/PartialFunction;
const #76 = Asciz	g;
const #77 = Asciz	Lscala/Function1;;
const #78 = Asciz	isDefinedAt;
const #79 = Asciz	(Ljava/lang/Object;)Z;
const #80 = Asciz	scala/actors/remote/Apply0;
const #81 = class	#80;	//  scala/actors/remote/Apply0
const #82 = Asciz	scala/MatchError;
const #83 = class	#82;	//  scala/MatchError
const #84 = Asciz	toString;
const #85 = Asciz	()Ljava/lang/String;;
const #86 = NameAndType	#84:#85;//  toString:()Ljava/lang/String;
const #87 = Method	#42.#86;	//  java/lang/Object.toString:()Ljava/lang/String;
const #88 = Asciz	(Ljava/lang/String;)V;
const #89 = NameAndType	#33:#88;//  "<init>":(Ljava/lang/String;)V
const #90 = Method	#83.#89;	//  scala/MatchError."<init>":(Ljava/lang/String;)V
const #91 = Asciz	scala/actors/remote/LocalApply0;
const #92 = class	#91;	//  scala/actors/remote/LocalApply0
const #93 = Asciz	scala/actors/remote/SendTo;
const #94 = class	#93;	//  scala/actors/remote/SendTo
const #95 = Asciz	scala/actors/remote/Terminate$;
const #96 = class	#95;	//  scala/actors/remote/Terminate$
const #97 = Asciz	Lscala/actors/remote/Terminate$;;
const #98 = NameAndType	#8:#97;//  MODULE$:Lscala/actors/remote/Terminate$;
const #99 = Field	#96.#98;	//  scala/actors/remote/Terminate$.MODULE$:Lscala/actors/remote/Terminate$;
const #100 = Asciz	equals;
const #101 = NameAndType	#100:#79;//  equals:(Ljava/lang/Object;)Z
const #102 = Method	#42.#101;	//  java/lang/Object.equals:(Ljava/lang/Object;)Z
const #103 = Asciz	scala/actors/$bang;
const #104 = class	#103;	//  scala/actors/$bang
const #105 = Asciz	rfun;
const #106 = Asciz	()Lscala/Function2;;
const #107 = NameAndType	#105:#106;//  rfun:()Lscala/Function2;
const #108 = Method	#81.#107;	//  scala/actors/remote/Apply0.rfun:()Lscala/Function2;
const #109 = Asciz	scala/actors/remote/DelegateActor$$anonfun$act$1;
const #110 = class	#109;	//  scala/actors/remote/DelegateActor$$anonfun$act$1
const #111 = Asciz	Lscala/actors/remote/DelegateActor;;
const #112 = NameAndType	#31:#111;//  $outer:Lscala/actors/remote/DelegateActor;
const #113 = Field	#110.#112;	//  scala/actors/remote/DelegateActor$$anonfun$act$1.$outer:Lscala/actors/remote/DelegateActor;
const #114 = Asciz	scala/actors/remote/DelegateActor;
const #115 = class	#114;	//  scala/actors/remote/DelegateActor
const #116 = Asciz	scala$actors$remote$DelegateActor$$kernel;
const #117 = Asciz	Lscala/actors/remote/NetKernel;;
const #118 = NameAndType	#116:#117;//  scala$actors$remote$DelegateActor$$kernel:Lscala/actors/remote/NetKernel;
const #119 = Field	#115.#118;	//  scala/actors/remote/DelegateActor.scala$actors$remote$DelegateActor$$kernel:Lscala/actors/remote/NetKernel;
const #120 = Asciz	scala$actors$remote$DelegateActor$$node;
const #121 = Asciz	Lscala/actors/remote/Node;;
const #122 = NameAndType	#120:#121;//  scala$actors$remote$DelegateActor$$node:Lscala/actors/remote/Node;
const #123 = Field	#115.#122;	//  scala/actors/remote/DelegateActor.scala$actors$remote$DelegateActor$$node:Lscala/actors/remote/Node;
const #124 = Asciz	scala$actors$remote$DelegateActor$$name;
const #125 = NameAndType	#124:#24;//  scala$actors$remote$DelegateActor$$name:Lscala/Symbol;
const #126 = Field	#115.#125;	//  scala/actors/remote/DelegateActor.scala$actors$remote$DelegateActor$$name:Lscala/Symbol;
const #127 = Asciz	protected$sender;
const #128 = Asciz	(Lscala/actors/remote/DelegateActor;)Lscala/actors/OutputChannel;;
const #129 = NameAndType	#127:#128;//  protected$sender:(Lscala/actors/remote/DelegateActor;)Lscala/actors/OutputChannel;
const #130 = Method	#115.#129;	//  scala/actors/remote/DelegateActor.protected$sender:(Lscala/actors/remote/DelegateActor;)Lscala/actors/OutputChannel;
const #131 = Asciz	scala/actors/remote/NetKernel;
const #132 = class	#131;	//  scala/actors/remote/NetKernel
const #133 = Asciz	remoteApply;
const #134 = Asciz	(Lscala/actors/remote/Node;Lscala/Symbol;Lscala/actors/OutputChannel;Lscala/Function2;)V;
const #135 = NameAndType	#133:#134;//  remoteApply:(Lscala/actors/remote/Node;Lscala/Symbol;Lscala/actors/OutputChannel;Lscala/Function2;)V
const #136 = Method	#132.#135;	//  scala/actors/remote/NetKernel.remoteApply:(Lscala/actors/remote/Node;Lscala/Symbol;Lscala/actors/OutputChannel;Lscala/Function2;)V
const #137 = Method	#92.#107;	//  scala/actors/remote/LocalApply0.rfun:()Lscala/Function2;
const #138 = Asciz	a;
const #139 = Asciz	()Lscala/actors/AbstractActor;;
const #140 = NameAndType	#138:#139;//  a:()Lscala/actors/AbstractActor;
const #141 = Method	#92.#140;	//  scala/actors/remote/LocalApply0.a:()Lscala/actors/AbstractActor;
const #142 = Asciz	scala$actors$remote$DelegateActor$$creator;
const #143 = Asciz	Lscala/actors/remote/Proxy;;
const #144 = NameAndType	#142:#143;//  scala$actors$remote$DelegateActor$$creator:Lscala/actors/remote/Proxy;
const #145 = Field	#115.#144;	//  scala/actors/remote/DelegateActor.scala$actors$remote$DelegateActor$$creator:Lscala/actors/remote/Proxy;
const #146 = Asciz	scala/Function2;
const #147 = class	#146;	//  scala/Function2
const #148 = Asciz	(Ljava/lang/Object;Ljava/lang/Object;)Ljava/lang/Object;;
const #149 = NameAndType	#15:#148;//  apply:(Ljava/lang/Object;Ljava/lang/Object;)Ljava/lang/Object;
const #150 = InterfaceMethod	#147.#149;	//  scala/Function2.apply:(Ljava/lang/Object;Ljava/lang/Object;)Ljava/lang/Object;
const #151 = Asciz	()Lscala/actors/OutputChannel;;
const #152 = NameAndType	#138:#151;//  a:()Lscala/actors/OutputChannel;
const #153 = Method	#94.#152;	//  scala/actors/remote/SendTo.a:()Lscala/actors/OutputChannel;
const #154 = Asciz	msg;
const #155 = Asciz	()Ljava/lang/Object;;
const #156 = NameAndType	#154:#155;//  msg:()Ljava/lang/Object;
const #157 = Method	#94.#156;	//  scala/actors/remote/SendTo.msg:()Ljava/lang/Object;
const #158 = Asciz	session;
const #159 = Asciz	()Lscala/Symbol;;
const #160 = NameAndType	#158:#159;//  session:()Lscala/Symbol;
const #161 = Method	#94.#160;	//  scala/actors/remote/SendTo.session:()Lscala/Symbol;
const #162 = Asciz	name;
const #163 = NameAndType	#162:#85;//  name:()Ljava/lang/String;
const #164 = Method	#20.#163;	//  scala/Symbol.name:()Ljava/lang/String;
const #165 = Asciz	scala/actors/OutputChannel;
const #166 = class	#165;	//  scala/actors/OutputChannel
const #167 = Asciz	send;
const #168 = Asciz	(Ljava/lang/Object;Lscala/actors/OutputChannel;)V;
const #169 = NameAndType	#167:#168;//  send:(Ljava/lang/Object;Lscala/actors/OutputChannel;)V
const #170 = InterfaceMethod	#166.#169;	//  scala/actors/OutputChannel.send:(Ljava/lang/Object;Lscala/actors/OutputChannel;)V
const #171 = Asciz	channelMap;
const #172 = Asciz	()Lscala/collection/mutable/HashMap;;
const #173 = NameAndType	#171:#172;//  channelMap:()Lscala/collection/mutable/HashMap;
const #174 = Method	#115.#173;	//  scala/actors/remote/DelegateActor.channelMap:()Lscala/collection/mutable/HashMap;
const #175 = Asciz	scala/collection/mutable/HashMap;
const #176 = class	#175;	//  scala/collection/mutable/HashMap
const #177 = Asciz	get;
const #178 = Asciz	(Ljava/lang/Object;)Lscala/Option;;
const #179 = NameAndType	#177:#178;//  get:(Ljava/lang/Object;)Lscala/Option;
const #180 = Method	#176.#179;	//  scala/collection/mutable/HashMap.get:(Ljava/lang/Object;)Lscala/Option;
const #181 = Asciz	scala/None$;
const #182 = class	#181;	//  scala/None$
const #183 = Asciz	Lscala/None$;;
const #184 = NameAndType	#8:#183;//  MODULE$:Lscala/None$;
const #185 = Field	#182.#184;	//  scala/None$.MODULE$:Lscala/None$;
const #186 = Asciz	scala/actors/Channel;
const #187 = class	#186;	//  scala/actors/Channel
const #188 = Asciz	(Lscala/actors/Actor;)V;
const #189 = NameAndType	#33:#188;//  "<init>":(Lscala/actors/Actor;)V
const #190 = Method	#187.#189;	//  scala/actors/Channel."<init>":(Lscala/actors/Actor;)V
const #191 = Asciz	sessionMap;
const #192 = NameAndType	#191:#172;//  sessionMap:()Lscala/collection/mutable/HashMap;
const #193 = Method	#115.#192;	//  scala/actors/remote/DelegateActor.sessionMap:()Lscala/collection/mutable/HashMap;
const #194 = Asciz	scala/Predef$Pair$;
const #195 = class	#194;	//  scala/Predef$Pair$
const #196 = Asciz	Lscala/Predef$Pair$;;
const #197 = NameAndType	#8:#196;//  MODULE$:Lscala/Predef$Pair$;
const #198 = Field	#195.#197;	//  scala/Predef$Pair$.MODULE$:Lscala/Predef$Pair$;
const #199 = Asciz	(Ljava/lang/Object;Ljava/lang/Object;)Lscala/Tuple2;;
const #200 = NameAndType	#15:#199;//  apply:(Ljava/lang/Object;Ljava/lang/Object;)Lscala/Tuple2;
const #201 = Method	#195.#200;	//  scala/Predef$Pair$.apply:(Ljava/lang/Object;Ljava/lang/Object;)Lscala/Tuple2;
const #202 = Asciz	$plus$eq;
const #203 = Asciz	(Lscala/Tuple2;)Lscala/collection/mutable/HashMap;;
const #204 = NameAndType	#202:#203;//  $plus$eq:(Lscala/Tuple2;)Lscala/collection/mutable/HashMap;
const #205 = Method	#176.#204;	//  scala/collection/mutable/HashMap.$plus$eq:(Lscala/Tuple2;)Lscala/collection/mutable/HashMap;
const #206 = Asciz	scala/Option;
const #207 = class	#206;	//  scala/Option
const #208 = Method	#207.#86;	//  scala/Option.toString:()Ljava/lang/String;
const #209 = Asciz	scala/Some;
const #210 = class	#209;	//  scala/Some
const #211 = Asciz	x;
const #212 = NameAndType	#211:#155;//  x:()Ljava/lang/Object;
const #213 = Method	#210.#212;	//  scala/Some.x:()Ljava/lang/Object;
const #214 = Asciz	$minus$eq;
const #215 = Asciz	(Ljava/lang/Object;)Lscala/collection/mutable/HashMap;;
const #216 = NameAndType	#214:#215;//  $minus$eq:(Ljava/lang/Object;)Lscala/collection/mutable/HashMap;
const #217 = Method	#176.#216;	//  scala/collection/mutable/HashMap.$minus$eq:(Ljava/lang/Object;)Lscala/collection/mutable/HashMap;
const #218 = Asciz	$bang;
const #219 = NameAndType	#218:#58;//  $bang:(Ljava/lang/Object;)V
const #220 = InterfaceMethod	#166.#219;	//  scala/actors/OutputChannel.$bang:(Ljava/lang/Object;)V
const #221 = Asciz	protected$exit;
const #222 = Asciz	(Lscala/actors/remote/DelegateActor;)Lscala/runtime/Nothing$;;
const #223 = NameAndType	#221:#222;//  protected$exit:(Lscala/actors/remote/DelegateActor;)Lscala/runtime/Nothing$;
const #224 = Method	#115.#223;	//  scala/actors/remote/DelegateActor.protected$exit:(Lscala/actors/remote/DelegateActor;)Lscala/runtime/Nothing$;
const #225 = Asciz	ch;
const #226 = Asciz	()Lscala/actors/Channel;;
const #227 = NameAndType	#225:#226;//  ch:()Lscala/actors/Channel;
const #228 = Method	#104.#227;	//  scala/actors/$bang.ch:()Lscala/actors/Channel;
const #229 = Method	#104.#156;	//  scala/actors/$bang.msg:()Ljava/lang/Object;
const #230 = Asciz	scala$actors$remote$DelegateActor$$anonfun$$$outer;
const #231 = Asciz	()Lscala/actors/remote/DelegateActor;;
const #232 = NameAndType	#230:#231;//  scala$actors$remote$DelegateActor$$anonfun$$$outer:()Lscala/actors/remote/DelegateActor;
const #233 = Method	#110.#232;	//  scala/actors/remote/DelegateActor$$anonfun$act$1.scala$actors$remote$DelegateActor$$anonfun$$$outer:()Lscala/actors/remote/DelegateActor;
const #234 = Asciz	forward;
const #235 = Asciz	(Lscala/actors/OutputChannel;Lscala/actors/remote/Node;Lscala/Symbol;Ljava/lang/Object;Lscala/Symbol;)V;
const #236 = NameAndType	#234:#235;//  forward:(Lscala/actors/OutputChannel;Lscala/actors/remote/Node;Lscala/Symbol;Ljava/lang/Object;Lscala/Symbol;)V
const #237 = Method	#132.#236;	//  scala/actors/remote/NetKernel.forward:(Lscala/actors/OutputChannel;Lscala/actors/remote/Node;Lscala/Symbol;Ljava/lang/Object;Lscala/Symbol;)V
const #238 = Asciz	scala/actors/Debug$;
const #239 = class	#238;	//  scala/actors/Debug$
const #240 = Asciz	Lscala/actors/Debug$;;
const #241 = NameAndType	#8:#240;//  MODULE$:Lscala/actors/Debug$;
const #242 = Field	#239.#241;	//  scala/actors/Debug$.MODULE$:Lscala/actors/Debug$;
const #243 = Asciz	scala/collection/mutable/StringBuilder;
const #244 = class	#243;	//  scala/collection/mutable/StringBuilder
const #245 = Method	#244.#37;	//  scala/collection/mutable/StringBuilder."<init>":()V
const #246 = Asciz	scala/Predef$;
const #247 = class	#246;	//  scala/Predef$
const #248 = Asciz	Lscala/Predef$;;
const #249 = NameAndType	#8:#248;//  MODULE$:Lscala/Predef$;
const #250 = Field	#247.#249;	//  scala/Predef$.MODULE$:Lscala/Predef$;
const #251 = Asciz	any2stringadd;
const #252 = Asciz	(Ljava/lang/Object;)Lscala/runtime/StringAdd;;
const #253 = NameAndType	#251:#252;//  any2stringadd:(Ljava/lang/Object;)Lscala/runtime/StringAdd;
const #254 = Method	#247.#253;	//  scala/Predef$.any2stringadd:(Ljava/lang/Object;)Lscala/runtime/StringAdd;
const #255 = Asciz	: cannot find session for ;
const #256 = String	#255;	//  : cannot find session for 
const #257 = Asciz	scala/runtime/StringAdd;
const #258 = class	#257;	//  scala/runtime/StringAdd
const #259 = Asciz	$plus;
const #260 = Asciz	(Ljava/lang/String;)Ljava/lang/String;;
const #261 = NameAndType	#259:#260;//  $plus:(Ljava/lang/String;)Ljava/lang/String;
const #262 = Method	#258.#261;	//  scala/runtime/StringAdd.$plus:(Ljava/lang/String;)Ljava/lang/String;
const #263 = Asciz	append;
const #264 = Asciz	(Ljava/lang/Object;)Lscala/collection/mutable/StringBuilder;;
const #265 = NameAndType	#263:#264;//  append:(Ljava/lang/Object;)Lscala/collection/mutable/StringBuilder;
const #266 = Method	#244.#265;	//  scala/collection/mutable/StringBuilder.append:(Ljava/lang/Object;)Lscala/collection/mutable/StringBuilder;
const #267 = Method	#244.#86;	//  scala/collection/mutable/StringBuilder.toString:()Ljava/lang/String;
const #268 = Asciz	info;
const #269 = NameAndType	#268:#88;//  info:(Ljava/lang/String;)V
const #270 = Method	#239.#269;	//  scala/actors/Debug$.info:(Ljava/lang/String;)V
const #271 = Asciz	getClass;
const #272 = Asciz	()Ljava/lang/Class;;
const #273 = NameAndType	#271:#272;//  getClass:()Ljava/lang/Class;
const #274 = Method	#42.#273;	//  java/lang/Object.getClass:()Ljava/lang/Class;
const #275 = Asciz	java/lang/Class;
const #276 = class	#275;	//  java/lang/Class
const #277 = Method	#276.#86;	//  java/lang/Class.toString:()Ljava/lang/String;
const #278 = Asciz	Channel;
const #279 = String	#278;	//  Channel
const #280 = Asciz	java/lang/String;
const #281 = class	#280;	//  java/lang/String
const #282 = Asciz	contains;
const #283 = Asciz	(Ljava/lang/CharSequence;)Z;
const #284 = NameAndType	#282:#283;//  contains:(Ljava/lang/CharSequence;)Z
const #285 = Method	#281.#284;	//  java/lang/String.contains:(Ljava/lang/CharSequence;)Z
const #286 = Asciz	scala/actors/remote/FreshNameCreator$;
const #287 = class	#286;	//  scala/actors/remote/FreshNameCreator$
const #288 = Asciz	Lscala/actors/remote/FreshNameCreator$;;
const #289 = NameAndType	#8:#288;//  MODULE$:Lscala/actors/remote/FreshNameCreator$;
const #290 = Field	#287.#289;	//  scala/actors/remote/FreshNameCreator$.MODULE$:Lscala/actors/remote/FreshNameCreator$;
const #291 = Asciz	@;
const #292 = String	#291;	//  @
const #293 = Asciz	newName;
const #294 = Asciz	(Ljava/lang/String;)Lscala/Symbol;;
const #295 = NameAndType	#293:#294;//  newName:(Ljava/lang/String;)Lscala/Symbol;
const #296 = Method	#287.#295;	//  scala/actors/remote/FreshNameCreator$.newName:(Ljava/lang/String;)Lscala/Symbol;
const #297 = Asciz	temp14;
const #298 = Asciz	Lscala/actors/remote/Apply0;;
const #299 = Asciz	temp15;
const #300 = Asciz	Lscala/Function2;;
const #301 = Asciz	temp16;
const #302 = Asciz	Lscala/actors/remote/LocalApply0;;
const #303 = Asciz	temp17;
const #304 = Asciz	temp18;
const #305 = Asciz	Lscala/actors/AbstractActor;;
const #306 = Asciz	temp19;
const #307 = Asciz	Lscala/actors/remote/SendTo;;
const #308 = Asciz	temp20;
const #309 = Asciz	Lscala/actors/OutputChannel;;
const #310 = Asciz	replyCh;
const #311 = Asciz	Lscala/actors/Channel;;
const #312 = Asciz	temp7;
const #313 = Asciz	Lscala/Some;;
const #314 = Asciz	temp22;
const #315 = Asciz	temp8;
const #316 = Asciz	temp21;
const #317 = Asciz	temp5;
const #318 = Asciz	Lscala/Option;;
const #319 = Asciz	temp24;
const #320 = Asciz	Lscala/actors/$bang;;
const #321 = Asciz	temp10;
const #322 = Asciz	temp26;
const #323 = Asciz	temp11;
const #324 = Asciz	temp25;
const #325 = Asciz	temp9;
const #326 = Asciz	fresh;
const #327 = Asciz	compose;
const #328 = Asciz	(Lscala/Function1;Lscala/Function1;)Lscala/Function1;;
const #329 = NameAndType	#327:#328;//  compose:(Lscala/Function1;Lscala/Function1;)Lscala/Function1;
const #330 = Method	#45.#329;	//  scala/Function1$class.compose:(Lscala/Function1;Lscala/Function1;)Lscala/Function1;
const #331 = Asciz	(Lscala/Function1;)Ljava/lang/String;;
const #332 = NameAndType	#84:#331;//  toString:(Lscala/Function1;)Ljava/lang/String;
const #333 = Method	#45.#332;	//  scala/Function1$class.toString:(Lscala/Function1;)Ljava/lang/String;
const #334 = Asciz	(Lscala/PartialFunction;Lscala/Function1;)Lscala/PartialFunction;;
const #335 = NameAndType	#69:#334;//  andThen:(Lscala/PartialFunction;Lscala/Function1;)Lscala/PartialFunction;
const #336 = Method	#51.#335;	//  scala/PartialFunction$class.andThen:(Lscala/PartialFunction;Lscala/Function1;)Lscala/PartialFunction;
const #337 = Asciz	k;
const #338 = Asciz	orElse;
const #339 = Asciz	(Lscala/PartialFunction;)Lscala/PartialFunction;;
const #340 = Asciz	(Lscala/PartialFunction;Lscala/PartialFunction;)Lscala/PartialFunction;;
const #341 = NameAndType	#338:#340;//  orElse:(Lscala/PartialFunction;Lscala/PartialFunction;)Lscala/PartialFunction;
const #342 = Method	#51.#341;	//  scala/PartialFunction$class.orElse:(Lscala/PartialFunction;Lscala/PartialFunction;)Lscala/PartialFunction;
const #343 = Asciz	that;
const #344 = Asciz	Lscala/PartialFunction;;
const #345 = Asciz	Scala;
const #346 = Asciz	InnerClasses;
const #347 = Asciz	$anonfun$act$1;
const #348 = Asciz	$anonfun$apply$1;
const #349 = Asciz	scala/ScalaObject;
const #350 = class	#349;	//  scala/ScalaObject
const #351 = Asciz	java/io/Serializable;
const #352 = class	#351;	//  java/io/Serializable

{
public static final long serialVersionUID;

public static {};
  Code:
   Stack=2, Locals=0, Args_size=0
   0:	getstatic	#11; //Field scala/Symbol$.MODULE$:Lscala/Symbol$;
   3:	ldc	#14; //String nosession
   5:	invokevirtual	#18; //Method scala/Symbol$.apply:(Ljava/lang/Object;)Ljava/lang/Object;
   8:	checkcast	#20; //class scala/Symbol
   11:	putstatic	#26; //Field symbol$1:Lscala/Symbol;
   14:	lconst_0
   15:	putstatic	#30; //Field serialVersionUID:J
   18:	return
  LineNumberTable: 
   line 185: 0


public scala.actors.remote.DelegateActor$$anonfun$act$1$$anonfun$apply$1(scala.actors.remote.DelegateActor$$anonfun$act$1);
  Code:
   Stack=2, Locals=2, Args_size=2
   0:	aload_1
   1:	ifnonnull	12
   4:	new	#36; //class java/lang/NullPointerException
   7:	dup
   8:	invokespecial	#38; //Method java/lang/NullPointerException."<init>":()V
   11:	athrow
   12:	aload_0
   13:	aload_1
   14:	putfield	#40; //Field $outer:Lscala/actors/remote/DelegateActor$$anonfun$act$1;
   17:	aload_0
   18:	invokespecial	#43; //Method java/lang/Object."<init>":()V
   21:	aload_0
   22:	invokestatic	#49; //Method scala/Function1$class.$init$:(Lscala/Function1;)V
   25:	aload_0
   26:	invokestatic	#54; //Method scala/PartialFunction$class.$init$:(Lscala/PartialFunction;)V
   29:	return
  LineNumberTable: 
   line 126: 0

  LocalVariableTable: 
   Start  Length  Slot  Name   Signature
   0      30      0    this       Lscala/actors/remote/DelegateActor$$anonfun$act$1$$anonfun$apply$1;
   0      30      1    $outer       Lscala/actors/remote/DelegateActor$$anonfun$act$1;


public final java.lang.Object apply(java.lang.Object);
  Code:
   Stack=2, Locals=2, Args_size=2
   0:	aload_0
   1:	aload_1
   2:	invokevirtual	#60; //Method apply:(Ljava/lang/Object;)V
   5:	getstatic	#66; //Field scala/runtime/BoxedUnit.UNIT:Lscala/runtime/BoxedUnit;
   8:	areturn
  LineNumberTable: 
   line 126: 0

  LocalVariableTable: 
   Start  Length  Slot  Name   Signature
   0      9      0    this       Lscala/actors/remote/DelegateActor$$anonfun$act$1$$anonfun$apply$1;
   0      9      1    v1       Ljava/lang/Object;


public scala.Function1 andThen(scala.Function1);
  Code:
   Stack=2, Locals=2, Args_size=2
   0:	aload_0
   1:	aload_1
   2:	invokeinterface	#75,  2; //InterfaceMethod scala/PartialFunction.andThen:(Lscala/Function1;)Lscala/PartialFunction;
   7:	areturn
  LineNumberTable: 
   line 126: 0

  LocalVariableTable: 
   Start  Length  Slot  Name   Signature
   0      8      0    this       Lscala/actors/remote/DelegateActor$$anonfun$act$1$$anonfun$apply$1;
   0      8      1    g       Lscala/Function1;


public final boolean isDefinedAt(java.lang.Object);
  Code:
   Stack=3, Locals=2, Args_size=2
   0:	aload_1
   1:	instanceof	#81; //class scala/actors/remote/Apply0
   4:	ifeq	27
   7:	iconst_1
   8:	ifeq	15
   11:	iconst_1
   12:	goto	189
   15:	new	#83; //class scala/MatchError
   18:	dup
   19:	aload_1
   20:	invokevirtual	#87; //Method java/lang/Object.toString:()Ljava/lang/String;
   23:	invokespecial	#90; //Method scala/MatchError."<init>":(Ljava/lang/String;)V
   26:	athrow
   27:	aload_1
   28:	instanceof	#92; //class scala/actors/remote/LocalApply0
   31:	ifeq	54
   34:	iconst_1
   35:	ifeq	42
   38:	iconst_1
   39:	goto	189
   42:	new	#83; //class scala/MatchError
   45:	dup
   46:	aload_1
   47:	invokevirtual	#87; //Method java/lang/Object.toString:()Ljava/lang/String;
   50:	invokespecial	#90; //Method scala/MatchError."<init>":(Ljava/lang/String;)V
   53:	athrow
   54:	aload_1
   55:	instanceof	#94; //class scala/actors/remote/SendTo
   58:	ifeq	81
   61:	iconst_1
   62:	ifeq	69
   65:	iconst_1
   66:	goto	189
   69:	new	#83; //class scala/MatchError
   72:	dup
   73:	aload_1
   74:	invokevirtual	#87; //Method java/lang/Object.toString:()Ljava/lang/String;
   77:	invokespecial	#90; //Method scala/MatchError."<init>":(Ljava/lang/String;)V
   80:	athrow
   81:	getstatic	#99; //Field scala/actors/remote/Terminate$.MODULE$:Lscala/actors/remote/Terminate$;
   84:	dup
   85:	ifnonnull	96
   88:	pop
   89:	aload_1
   90:	ifnull	103
   93:	goto	130
   96:	aload_1
   97:	invokevirtual	#102; //Method java/lang/Object.equals:(Ljava/lang/Object;)Z
   100:	ifeq	130
   103:	aload_1
   104:	instanceof	#96; //class scala/actors/remote/Terminate$
   107:	ifeq	130
   110:	iconst_1
   111:	ifeq	118
   114:	iconst_1
   115:	goto	189
   118:	new	#83; //class scala/MatchError
   121:	dup
   122:	aload_1
   123:	invokevirtual	#87; //Method java/lang/Object.toString:()Ljava/lang/String;
   126:	invokespecial	#90; //Method scala/MatchError."<init>":(Ljava/lang/String;)V
   129:	athrow
   130:	aload_1
   131:	instanceof	#104; //class scala/actors/$bang
   134:	ifeq	157
   137:	iconst_1
   138:	ifeq	145
   141:	iconst_1
   142:	goto	189
   145:	new	#83; //class scala/MatchError
   148:	dup
   149:	aload_1
   150:	invokevirtual	#87; //Method java/lang/Object.toString:()Ljava/lang/String;
   153:	invokespecial	#90; //Method scala/MatchError."<init>":(Ljava/lang/String;)V
   156:	athrow
   157:	aload_1
   158:	instanceof	#42; //class java/lang/Object
   161:	ifeq	184
   164:	iconst_1
   165:	ifeq	172
   168:	iconst_1
   169:	goto	189
   172:	new	#83; //class scala/MatchError
   175:	dup
   176:	aload_1
   177:	invokevirtual	#87; //Method java/lang/Object.toString:()Ljava/lang/String;
   180:	invokespecial	#90; //Method scala/MatchError."<init>":(Ljava/lang/String;)V
   183:	athrow
   184:	iconst_1
   185:	ifeq	190
   188:	iconst_0
   189:	ireturn
   190:	new	#83; //class scala/MatchError
   193:	dup
   194:	aload_1
   195:	invokevirtual	#87; //Method java/lang/Object.toString:()Ljava/lang/String;
   198:	invokespecial	#90; //Method scala/MatchError."<init>":(Ljava/lang/String;)V
   201:	athrow
  LineNumberTable: 
   line 126: 0
   line 644: 7
   line 126: 11
   line 644: 34
   line 126: 38
   line 644: 61
   line 126: 65
   line 644: 110
   line 126: 114
   line 644: 137
   line 126: 141
   line 644: 164
   line 126: 168
   line 644: 184
   line 126: 188


public final void apply(java.lang.Object);
  Code:
   Stack=6, Locals=38, Args_size=2
   0:	aload_1
   1:	instanceof	#81; //class scala/actors/remote/Apply0
   4:	ifeq	107
   7:	aload_1
   8:	checkcast	#81; //class scala/actors/remote/Apply0
   11:	astore_2
   12:	aload_2
   13:	invokevirtual	#108; //Method scala/actors/remote/Apply0.rfun:()Lscala/Function2;
   16:	astore	8
   18:	iconst_1
   19:	ifeq	95
   22:	aload_0
   23:	getfield	#40; //Field $outer:Lscala/actors/remote/DelegateActor$$anonfun$act$1;
   26:	astore_3
   27:	aload_3
   28:	getfield	#113; //Field scala/actors/remote/DelegateActor$$anonfun$act$1.$outer:Lscala/actors/remote/DelegateActor;
   31:	getfield	#119; //Field scala/actors/remote/DelegateActor.scala$actors$remote$DelegateActor$$kernel:Lscala/actors/remote/NetKernel;
   34:	aload_0
   35:	getfield	#40; //Field $outer:Lscala/actors/remote/DelegateActor$$anonfun$act$1;
   38:	astore	4
   40:	aload	4
   42:	getfield	#113; //Field scala/actors/remote/DelegateActor$$anonfun$act$1.$outer:Lscala/actors/remote/DelegateActor;
   45:	getfield	#123; //Field scala/actors/remote/DelegateActor.scala$actors$remote$DelegateActor$$node:Lscala/actors/remote/Node;
   48:	aload_0
   49:	getfield	#40; //Field $outer:Lscala/actors/remote/DelegateActor$$anonfun$act$1;
   52:	astore	5
   54:	aload	5
   56:	getfield	#113; //Field scala/actors/remote/DelegateActor$$anonfun$act$1.$outer:Lscala/actors/remote/DelegateActor;
   59:	getfield	#126; //Field scala/actors/remote/DelegateActor.scala$actors$remote$DelegateActor$$name:Lscala/Symbol;
   62:	aload_0
   63:	getfield	#40; //Field $outer:Lscala/actors/remote/DelegateActor$$anonfun$act$1;
   66:	astore	6
   68:	aload	6
   70:	getfield	#113; //Field scala/actors/remote/DelegateActor$$anonfun$act$1.$outer:Lscala/actors/remote/DelegateActor;
   73:	aload_0
   74:	getfield	#40; //Field $outer:Lscala/actors/remote/DelegateActor$$anonfun$act$1;
   77:	astore	7
   79:	aload	7
   81:	getfield	#113; //Field scala/actors/remote/DelegateActor$$anonfun$act$1.$outer:Lscala/actors/remote/DelegateActor;
   84:	invokevirtual	#130; //Method scala/actors/remote/DelegateActor.protected$sender:(Lscala/actors/remote/DelegateActor;)Lscala/actors/OutputChannel;
   87:	aload	8
   89:	invokevirtual	#136; //Method scala/actors/remote/NetKernel.remoteApply:(Lscala/actors/remote/Node;Lscala/Symbol;Lscala/actors/OutputChannel;Lscala/Function2;)V
   92:	goto	1096
   95:	new	#83; //class scala/MatchError
   98:	dup
   99:	aload_1
   100:	invokevirtual	#87; //Method java/lang/Object.toString:()Ljava/lang/String;
   103:	invokespecial	#90; //Method scala/MatchError."<init>":(Ljava/lang/String;)V
   106:	athrow
   107:	aload_1
   108:	instanceof	#92; //class scala/actors/remote/LocalApply0
   111:	ifeq	177
   114:	aload_1
   115:	checkcast	#92; //class scala/actors/remote/LocalApply0
   118:	astore	9
   120:	aload	9
   122:	invokevirtual	#137; //Method scala/actors/remote/LocalApply0.rfun:()Lscala/Function2;
   125:	astore	10
   127:	aload	9
   129:	invokevirtual	#141; //Method scala/actors/remote/LocalApply0.a:()Lscala/actors/AbstractActor;
   132:	astore	11
   134:	iconst_1
   135:	ifeq	165
   138:	aload	10
   140:	aload	11
   142:	aload_0
   143:	getfield	#40; //Field $outer:Lscala/actors/remote/DelegateActor$$anonfun$act$1;
   146:	astore	12
   148:	aload	12
   150:	getfield	#113; //Field scala/actors/remote/DelegateActor$$anonfun$act$1.$outer:Lscala/actors/remote/DelegateActor;
   153:	getfield	#145; //Field scala/actors/remote/DelegateActor.scala$actors$remote$DelegateActor$$creator:Lscala/actors/remote/Proxy;
   156:	invokeinterface	#150,  3; //InterfaceMethod scala/Function2.apply:(Ljava/lang/Object;Ljava/lang/Object;)Ljava/lang/Object;
   161:	pop
   162:	goto	1096
   165:	new	#83; //class scala/MatchError
   168:	dup
   169:	aload_1
   170:	invokevirtual	#87; //Method java/lang/Object.toString:()Ljava/lang/String;
   173:	invokespecial	#90; //Method scala/MatchError."<init>":(Ljava/lang/String;)V
   176:	athrow
   177:	aload_1
   178:	instanceof	#94; //class scala/actors/remote/SendTo
   181:	ifeq	491
   184:	aload_1
   185:	checkcast	#94; //class scala/actors/remote/SendTo
   188:	astore	13
   190:	aload	13
   192:	invokevirtual	#153; //Method scala/actors/remote/SendTo.a:()Lscala/actors/OutputChannel;
   195:	astore	19
   197:	aload	13
   199:	invokevirtual	#157; //Method scala/actors/remote/SendTo.msg:()Ljava/lang/Object;
   202:	astore	25
   204:	aload	13
   206:	invokevirtual	#161; //Method scala/actors/remote/SendTo.session:()Lscala/Symbol;
   209:	astore	23
   211:	iconst_1
   212:	ifeq	479
   215:	aload	23
   217:	invokevirtual	#164; //Method scala/Symbol.name:()Ljava/lang/String;
   220:	ldc	#14; //String nosession
   222:	astore	14
   224:	dup
   225:	ifnonnull	237
   228:	pop
   229:	aload	14
   231:	ifnull	245
   234:	goto	268
   237:	aload	14
   239:	invokevirtual	#102; //Method java/lang/Object.equals:(Ljava/lang/Object;)Z
   242:	ifeq	268
   245:	aload	19
   247:	aload	25
   249:	aload_0
   250:	getfield	#40; //Field $outer:Lscala/actors/remote/DelegateActor$$anonfun$act$1;
   253:	astore	15
   255:	aload	15
   257:	getfield	#113; //Field scala/actors/remote/DelegateActor$$anonfun$act$1.$outer:Lscala/actors/remote/DelegateActor;
   260:	invokeinterface	#170,  3; //InterfaceMethod scala/actors/OutputChannel.send:(Ljava/lang/Object;Lscala/actors/OutputChannel;)V
   265:	goto	1096
   268:	aload_0
   269:	getfield	#40; //Field $outer:Lscala/actors/remote/DelegateActor$$anonfun$act$1;
   272:	astore	16
   274:	aload	16
   276:	getfield	#113; //Field scala/actors/remote/DelegateActor$$anonfun$act$1.$outer:Lscala/actors/remote/DelegateActor;
   279:	invokevirtual	#174; //Method scala/actors/remote/DelegateActor.channelMap:()Lscala/collection/mutable/HashMap;
   282:	aload	23
   284:	invokevirtual	#180; //Method scala/collection/mutable/HashMap.get:(Ljava/lang/Object;)Lscala/Option;
   287:	astore	26
   289:	getstatic	#185; //Field scala/None$.MODULE$:Lscala/None$;
   292:	dup
   293:	ifnonnull	305
   296:	pop
   297:	aload	26
   299:	ifnull	313
   302:	goto	392
   305:	aload	26
   307:	invokevirtual	#102; //Method java/lang/Object.equals:(Ljava/lang/Object;)Z
   310:	ifeq	392
   313:	iconst_1
   314:	ifeq	379
   317:	new	#187; //class scala/actors/Channel
   320:	dup
   321:	aload_0
   322:	getfield	#40; //Field $outer:Lscala/actors/remote/DelegateActor$$anonfun$act$1;
   325:	astore	17
   327:	aload	17
   329:	getfield	#113; //Field scala/actors/remote/DelegateActor$$anonfun$act$1.$outer:Lscala/actors/remote/DelegateActor;
   332:	invokespecial	#190; //Method scala/actors/Channel."<init>":(Lscala/actors/Actor;)V
   335:	astore	20
   337:	aload_0
   338:	getfield	#40; //Field $outer:Lscala/actors/remote/DelegateActor$$anonfun$act$1;
   341:	astore	18
   343:	aload	18
   345:	getfield	#113; //Field scala/actors/remote/DelegateActor$$anonfun$act$1.$outer:Lscala/actors/remote/DelegateActor;
   348:	invokevirtual	#193; //Method scala/actors/remote/DelegateActor.sessionMap:()Lscala/collection/mutable/HashMap;
   351:	getstatic	#198; //Field scala/Predef$Pair$.MODULE$:Lscala/Predef$Pair$;
   354:	aload	20
   356:	aload	23
   358:	invokevirtual	#201; //Method scala/Predef$Pair$.apply:(Ljava/lang/Object;Ljava/lang/Object;)Lscala/Tuple2;
   361:	invokevirtual	#205; //Method scala/collection/mutable/HashMap.$plus$eq:(Lscala/Tuple2;)Lscala/collection/mutable/HashMap;
   364:	pop
   365:	aload	19
   367:	aload	25
   369:	aload	20
   371:	invokeinterface	#170,  3; //InterfaceMethod scala/actors/OutputChannel.send:(Ljava/lang/Object;Lscala/actors/OutputChannel;)V
   376:	goto	1096
   379:	new	#83; //class scala/MatchError
   382:	dup
   383:	aload	26
   385:	invokevirtual	#208; //Method scala/Option.toString:()Ljava/lang/String;
   388:	invokespecial	#90; //Method scala/MatchError."<init>":(Ljava/lang/String;)V
   391:	athrow
   392:	aload	26
   394:	instanceof	#210; //class scala/Some
   397:	ifeq	466
   400:	aload	26
   402:	checkcast	#210; //class scala/Some
   405:	astore	21
   407:	aload	21
   409:	invokevirtual	#213; //Method scala/Some.x:()Ljava/lang/Object;
   412:	checkcast	#166; //class scala/actors/OutputChannel
   415:	astore	24
   417:	iconst_1
   418:	ifeq	453
   421:	aload_0
   422:	getfield	#40; //Field $outer:Lscala/actors/remote/DelegateActor$$anonfun$act$1;
   425:	astore	22
   427:	aload	22
   429:	getfield	#113; //Field scala/actors/remote/DelegateActor$$anonfun$act$1.$outer:Lscala/actors/remote/DelegateActor;
   432:	invokevirtual	#174; //Method scala/actors/remote/DelegateActor.channelMap:()Lscala/collection/mutable/HashMap;
   435:	aload	23
   437:	invokevirtual	#217; //Method scala/collection/mutable/HashMap.$minus$eq:(Ljava/lang/Object;)Lscala/collection/mutable/HashMap;
   440:	pop
   441:	aload	24
   443:	aload	25
   445:	invokeinterface	#220,  2; //InterfaceMethod scala/actors/OutputChannel.$bang:(Ljava/lang/Object;)V
   450:	goto	1096
   453:	new	#83; //class scala/MatchError
   456:	dup
   457:	aload	26
   459:	invokevirtual	#208; //Method scala/Option.toString:()Ljava/lang/String;
   462:	invokespecial	#90; //Method scala/MatchError."<init>":(Ljava/lang/String;)V
   465:	athrow
   466:	new	#83; //class scala/MatchError
   469:	dup
   470:	aload	26
   472:	invokevirtual	#208; //Method scala/Option.toString:()Ljava/lang/String;
   475:	invokespecial	#90; //Method scala/MatchError."<init>":(Ljava/lang/String;)V
   478:	athrow
   479:	new	#83; //class scala/MatchError
   482:	dup
   483:	aload_1
   484:	invokevirtual	#87; //Method java/lang/Object.toString:()Ljava/lang/String;
   487:	invokespecial	#90; //Method scala/MatchError."<init>":(Ljava/lang/String;)V
   490:	athrow
   491:	getstatic	#99; //Field scala/actors/remote/Terminate$.MODULE$:Lscala/actors/remote/Terminate$;
   494:	dup
   495:	ifnonnull	506
   498:	pop
   499:	aload_1
   500:	ifnull	513
   503:	goto	562
   506:	aload_1
   507:	invokevirtual	#102; //Method java/lang/Object.equals:(Ljava/lang/Object;)Z
   510:	ifeq	562
   513:	aload_1
   514:	instanceof	#96; //class scala/actors/remote/Terminate$
   517:	ifeq	562
   520:	iconst_1
   521:	ifeq	550
   524:	aload_0
   525:	getfield	#40; //Field $outer:Lscala/actors/remote/DelegateActor$$anonfun$act$1;
   528:	astore	27
   530:	aload	27
   532:	getfield	#113; //Field scala/actors/remote/DelegateActor$$anonfun$act$1.$outer:Lscala/actors/remote/DelegateActor;
   535:	aload_0
   536:	getfield	#40; //Field $outer:Lscala/actors/remote/DelegateActor$$anonfun$act$1;
   539:	astore	28
   541:	aload	28
   543:	getfield	#113; //Field scala/actors/remote/DelegateActor$$anonfun$act$1.$outer:Lscala/actors/remote/DelegateActor;
   546:	invokevirtual	#224; //Method scala/actors/remote/DelegateActor.protected$exit:(Lscala/actors/remote/DelegateActor;)Lscala/runtime/Nothing$;
   549:	athrow
   550:	new	#83; //class scala/MatchError
   553:	dup
   554:	aload_1
   555:	invokevirtual	#87; //Method java/lang/Object.toString:()Ljava/lang/String;
   558:	invokespecial	#90; //Method scala/MatchError."<init>":(Ljava/lang/String;)V
   561:	athrow
   562:	aload_1
   563:	instanceof	#104; //class scala/actors/$bang
   566:	ifeq	845
   569:	aload_1
   570:	checkcast	#104; //class scala/actors/$bang
   573:	astore	29
   575:	aload	29
   577:	invokevirtual	#228; //Method scala/actors/$bang.ch:()Lscala/actors/Channel;
   580:	astore	35
   582:	aload	29
   584:	invokevirtual	#229; //Method scala/actors/$bang.msg:()Ljava/lang/Object;
   587:	astore	33
   589:	iconst_1
   590:	ifeq	833
   593:	aload_0
   594:	getfield	#40; //Field $outer:Lscala/actors/remote/DelegateActor$$anonfun$act$1;
   597:	astore	30
   599:	aload	30
   601:	getfield	#113; //Field scala/actors/remote/DelegateActor$$anonfun$act$1.$outer:Lscala/actors/remote/DelegateActor;
   604:	invokevirtual	#193; //Method scala/actors/remote/DelegateActor.sessionMap:()Lscala/collection/mutable/HashMap;
   607:	aload	35
   609:	invokevirtual	#180; //Method scala/collection/mutable/HashMap.get:(Ljava/lang/Object;)Lscala/Option;
   612:	astore	36
   614:	aload	36
   616:	instanceof	#210; //class scala/Some
   619:	ifeq	733
   622:	aload	36
   624:	checkcast	#210; //class scala/Some
   627:	astore	31
   629:	aload	31
   631:	invokevirtual	#213; //Method scala/Some.x:()Ljava/lang/Object;
   634:	checkcast	#20; //class scala/Symbol
   637:	astore	34
   639:	iconst_1
   640:	ifeq	720
   643:	aload_0
   644:	getfield	#40; //Field $outer:Lscala/actors/remote/DelegateActor$$anonfun$act$1;
   647:	astore	32
   649:	aload	32
   651:	getfield	#113; //Field scala/actors/remote/DelegateActor$$anonfun$act$1.$outer:Lscala/actors/remote/DelegateActor;
   654:	invokevirtual	#193; //Method scala/actors/remote/DelegateActor.sessionMap:()Lscala/collection/mutable/HashMap;
   657:	aload	35
   659:	invokevirtual	#217; //Method scala/collection/mutable/HashMap.$minus$eq:(Ljava/lang/Object;)Lscala/collection/mutable/HashMap;
   662:	pop
   663:	aload_0
   664:	getfield	#40; //Field $outer:Lscala/actors/remote/DelegateActor$$anonfun$act$1;
   667:	invokevirtual	#233; //Method scala/actors/remote/DelegateActor$$anonfun$act$1.scala$actors$remote$DelegateActor$$anonfun$$$outer:()Lscala/actors/remote/DelegateActor;
   670:	getfield	#119; //Field scala/actors/remote/DelegateActor.scala$actors$remote$DelegateActor$$kernel:Lscala/actors/remote/NetKernel;
   673:	aload_0
   674:	getfield	#40; //Field $outer:Lscala/actors/remote/DelegateActor$$anonfun$act$1;
   677:	invokevirtual	#233; //Method scala/actors/remote/DelegateActor$$anonfun$act$1.scala$actors$remote$DelegateActor$$anonfun$$$outer:()Lscala/actors/remote/DelegateActor;
   680:	aload_0
   681:	getfield	#40; //Field $outer:Lscala/actors/remote/DelegateActor$$anonfun$act$1;
   684:	invokevirtual	#233; //Method scala/actors/remote/DelegateActor$$anonfun$act$1.scala$actors$remote$DelegateActor$$anonfun$$$outer:()Lscala/actors/remote/DelegateActor;
   687:	invokevirtual	#130; //Method scala/actors/remote/DelegateActor.protected$sender:(Lscala/actors/remote/DelegateActor;)Lscala/actors/OutputChannel;
   690:	aload_0
   691:	getfield	#40; //Field $outer:Lscala/actors/remote/DelegateActor$$anonfun$act$1;
   694:	invokevirtual	#233; //Method scala/actors/remote/DelegateActor$$anonfun$act$1.scala$actors$remote$DelegateActor$$anonfun$$$outer:()Lscala/actors/remote/DelegateActor;
   697:	getfield	#123; //Field scala/actors/remote/DelegateActor.scala$actors$remote$DelegateActor$$node:Lscala/actors/remote/Node;
   700:	aload_0
   701:	getfield	#40; //Field $outer:Lscala/actors/remote/DelegateActor$$anonfun$act$1;
   704:	invokevirtual	#233; //Method scala/actors/remote/DelegateActor$$anonfun$act$1.scala$actors$remote$DelegateActor$$anonfun$$$outer:()Lscala/actors/remote/DelegateActor;
   707:	getfield	#126; //Field scala/actors/remote/DelegateActor.scala$actors$remote$DelegateActor$$name:Lscala/Symbol;
   710:	aload	33
   712:	aload	34
   714:	invokevirtual	#237; //Method scala/actors/remote/NetKernel.forward:(Lscala/actors/OutputChannel;Lscala/actors/remote/Node;Lscala/Symbol;Ljava/lang/Object;Lscala/Symbol;)V
   717:	goto	1096
   720:	new	#83; //class scala/MatchError
   723:	dup
   724:	aload	36
   726:	invokevirtual	#208; //Method scala/Option.toString:()Ljava/lang/String;
   729:	invokespecial	#90; //Method scala/MatchError."<init>":(Ljava/lang/String;)V
   732:	athrow
   733:	getstatic	#185; //Field scala/None$.MODULE$:Lscala/None$;
   736:	dup
   737:	ifnonnull	749
   740:	pop
   741:	aload	36
   743:	ifnull	757
   746:	goto	820
   749:	aload	36
   751:	invokevirtual	#102; //Method java/lang/Object.equals:(Ljava/lang/Object;)Z
   754:	ifeq	820
   757:	iconst_1
   758:	ifeq	807
   761:	getstatic	#242; //Field scala/actors/Debug$.MODULE$:Lscala/actors/Debug$;
   764:	new	#244; //class scala/collection/mutable/StringBuilder
   767:	dup
   768:	invokespecial	#245; //Method scala/collection/mutable/StringBuilder."<init>":()V
   771:	getstatic	#250; //Field scala/Predef$.MODULE$:Lscala/Predef$;
   774:	aload_0
   775:	getfield	#40; //Field $outer:Lscala/actors/remote/DelegateActor$$anonfun$act$1;
   778:	invokevirtual	#233; //Method scala/actors/remote/DelegateActor$$anonfun$act$1.scala$actors$remote$DelegateActor$$anonfun$$$outer:()Lscala/actors/remote/DelegateActor;
   781:	invokevirtual	#254; //Method scala/Predef$.any2stringadd:(Ljava/lang/Object;)Lscala/runtime/StringAdd;
   784:	ldc_w	#256; //String : cannot find session for 
   787:	invokevirtual	#262; //Method scala/runtime/StringAdd.$plus:(Ljava/lang/String;)Ljava/lang/String;
   790:	invokevirtual	#266; //Method scala/collection/mutable/StringBuilder.append:(Ljava/lang/Object;)Lscala/collection/mutable/StringBuilder;
   793:	aload	35
   795:	invokevirtual	#266; //Method scala/collection/mutable/StringBuilder.append:(Ljava/lang/Object;)Lscala/collection/mutable/StringBuilder;
   798:	invokevirtual	#267; //Method scala/collection/mutable/StringBuilder.toString:()Ljava/lang/String;
   801:	invokevirtual	#270; //Method scala/actors/Debug$.info:(Ljava/lang/String;)V
   804:	goto	1096
   807:	new	#83; //class scala/MatchError
   810:	dup
   811:	aload	36
   813:	invokevirtual	#208; //Method scala/Option.toString:()Ljava/lang/String;
   816:	invokespecial	#90; //Method scala/MatchError."<init>":(Ljava/lang/String;)V
   819:	athrow
   820:	new	#83; //class scala/MatchError
   823:	dup
   824:	aload	36
   826:	invokevirtual	#208; //Method scala/Option.toString:()Ljava/lang/String;
   829:	invokespecial	#90; //Method scala/MatchError."<init>":(Ljava/lang/String;)V
   832:	athrow
   833:	new	#83; //class scala/MatchError
   836:	dup
   837:	aload_1
   838:	invokevirtual	#87; //Method java/lang/Object.toString:()Ljava/lang/String;
   841:	invokespecial	#90; //Method scala/MatchError."<init>":(Ljava/lang/String;)V
   844:	athrow
   845:	aload_1
   846:	instanceof	#42; //class java/lang/Object
   849:	ifeq	1109
   852:	iconst_1
   853:	ifeq	1097
   856:	aload_0
   857:	getfield	#40; //Field $outer:Lscala/actors/remote/DelegateActor$$anonfun$act$1;
   860:	invokevirtual	#233; //Method scala/actors/remote/DelegateActor$$anonfun$act$1.scala$actors$remote$DelegateActor$$anonfun$$$outer:()Lscala/actors/remote/DelegateActor;
   863:	aload_0
   864:	getfield	#40; //Field $outer:Lscala/actors/remote/DelegateActor$$anonfun$act$1;
   867:	invokevirtual	#233; //Method scala/actors/remote/DelegateActor$$anonfun$act$1.scala$actors$remote$DelegateActor$$anonfun$$$outer:()Lscala/actors/remote/DelegateActor;
   870:	invokevirtual	#130; //Method scala/actors/remote/DelegateActor.protected$sender:(Lscala/actors/remote/DelegateActor;)Lscala/actors/OutputChannel;
   873:	invokevirtual	#274; //Method java/lang/Object.getClass:()Ljava/lang/Class;
   876:	invokevirtual	#277; //Method java/lang/Class.toString:()Ljava/lang/String;
   879:	ldc_w	#279; //String Channel
   882:	invokevirtual	#285; //Method java/lang/String.contains:(Ljava/lang/CharSequence;)Z
   885:	ifeq	1039
   888:	getstatic	#290; //Field scala/actors/remote/FreshNameCreator$.MODULE$:Lscala/actors/remote/FreshNameCreator$;
   891:	new	#244; //class scala/collection/mutable/StringBuilder
   894:	dup
   895:	invokespecial	#245; //Method scala/collection/mutable/StringBuilder."<init>":()V
   898:	getstatic	#250; //Field scala/Predef$.MODULE$:Lscala/Predef$;
   901:	aload_0
   902:	getfield	#40; //Field $outer:Lscala/actors/remote/DelegateActor$$anonfun$act$1;
   905:	invokevirtual	#233; //Method scala/actors/remote/DelegateActor$$anonfun$act$1.scala$actors$remote$DelegateActor$$anonfun$$$outer:()Lscala/actors/remote/DelegateActor;
   908:	getfield	#123; //Field scala/actors/remote/DelegateActor.scala$actors$remote$DelegateActor$$node:Lscala/actors/remote/Node;
   911:	invokevirtual	#254; //Method scala/Predef$.any2stringadd:(Ljava/lang/Object;)Lscala/runtime/StringAdd;
   914:	ldc_w	#292; //String @
   917:	invokevirtual	#262; //Method scala/runtime/StringAdd.$plus:(Ljava/lang/String;)Ljava/lang/String;
   920:	invokevirtual	#266; //Method scala/collection/mutable/StringBuilder.append:(Ljava/lang/Object;)Lscala/collection/mutable/StringBuilder;
   923:	aload_0
   924:	getfield	#40; //Field $outer:Lscala/actors/remote/DelegateActor$$anonfun$act$1;
   927:	invokevirtual	#233; //Method scala/actors/remote/DelegateActor$$anonfun$act$1.scala$actors$remote$DelegateActor$$anonfun$$$outer:()Lscala/actors/remote/DelegateActor;
   930:	getfield	#126; //Field scala/actors/remote/DelegateActor.scala$actors$remote$DelegateActor$$name:Lscala/Symbol;
   933:	invokevirtual	#266; //Method scala/collection/mutable/StringBuilder.append:(Ljava/lang/Object;)Lscala/collection/mutable/StringBuilder;
   936:	invokevirtual	#267; //Method scala/collection/mutable/StringBuilder.toString:()Ljava/lang/String;
   939:	invokevirtual	#296; //Method scala/actors/remote/FreshNameCreator$.newName:(Ljava/lang/String;)Lscala/Symbol;
   942:	astore	37
   944:	aload_0
   945:	getfield	#40; //Field $outer:Lscala/actors/remote/DelegateActor$$anonfun$act$1;
   948:	invokevirtual	#233; //Method scala/actors/remote/DelegateActor$$anonfun$act$1.scala$actors$remote$DelegateActor$$anonfun$$$outer:()Lscala/actors/remote/DelegateActor;
   951:	invokevirtual	#174; //Method scala/actors/remote/DelegateActor.channelMap:()Lscala/collection/mutable/HashMap;
   954:	getstatic	#198; //Field scala/Predef$Pair$.MODULE$:Lscala/Predef$Pair$;
   957:	aload	37
   959:	aload_0
   960:	getfield	#40; //Field $outer:Lscala/actors/remote/DelegateActor$$anonfun$act$1;
   963:	invokevirtual	#233; //Method scala/actors/remote/DelegateActor$$anonfun$act$1.scala$actors$remote$DelegateActor$$anonfun$$$outer:()Lscala/actors/remote/DelegateActor;
   966:	aload_0
   967:	getfield	#40; //Field $outer:Lscala/actors/remote/DelegateActor$$anonfun$act$1;
   970:	invokevirtual	#233; //Method scala/actors/remote/DelegateActor$$anonfun$act$1.scala$actors$remote$DelegateActor$$anonfun$$$outer:()Lscala/actors/remote/DelegateActor;
   973:	invokevirtual	#130; //Method scala/actors/remote/DelegateActor.protected$sender:(Lscala/actors/remote/DelegateActor;)Lscala/actors/OutputChannel;
   976:	invokevirtual	#201; //Method scala/Predef$Pair$.apply:(Ljava/lang/Object;Ljava/lang/Object;)Lscala/Tuple2;
   979:	invokevirtual	#205; //Method scala/collection/mutable/HashMap.$plus$eq:(Lscala/Tuple2;)Lscala/collection/mutable/HashMap;
   982:	pop
   983:	aload_0
   984:	getfield	#40; //Field $outer:Lscala/actors/remote/DelegateActor$$anonfun$act$1;
   987:	invokevirtual	#233; //Method scala/actors/remote/DelegateActor$$anonfun$act$1.scala$actors$remote$DelegateActor$$anonfun$$$outer:()Lscala/actors/remote/DelegateActor;
   990:	getfield	#119; //Field scala/actors/remote/DelegateActor.scala$actors$remote$DelegateActor$$kernel:Lscala/actors/remote/NetKernel;
   993:	aload_0
   994:	getfield	#40; //Field $outer:Lscala/actors/remote/DelegateActor$$anonfun$act$1;
   997:	invokevirtual	#233; //Method scala/actors/remote/DelegateActor$$anonfun$act$1.scala$actors$remote$DelegateActor$$anonfun$$$outer:()Lscala/actors/remote/DelegateActor;
   1000:	aload_0
   1001:	getfield	#40; //Field $outer:Lscala/actors/remote/DelegateActor$$anonfun$act$1;
   1004:	invokevirtual	#233; //Method scala/actors/remote/DelegateActor$$anonfun$act$1.scala$actors$remote$DelegateActor$$anonfun$$$outer:()Lscala/actors/remote/DelegateActor;
   1007:	invokevirtual	#130; //Method scala/actors/remote/DelegateActor.protected$sender:(Lscala/actors/remote/DelegateActor;)Lscala/actors/OutputChannel;
   1010:	aload_0
   1011:	getfield	#40; //Field $outer:Lscala/actors/remote/DelegateActor$$anonfun$act$1;
   1014:	invokevirtual	#233; //Method scala/actors/remote/DelegateActor$$anonfun$act$1.scala$actors$remote$DelegateActor$$anonfun$$$outer:()Lscala/actors/remote/DelegateActor;
   1017:	getfield	#123; //Field scala/actors/remote/DelegateActor.scala$actors$remote$DelegateActor$$node:Lscala/actors/remote/Node;
   1020:	aload_0
   1021:	getfield	#40; //Field $outer:Lscala/actors/remote/DelegateActor$$anonfun$act$1;
   1024:	invokevirtual	#233; //Method scala/actors/remote/DelegateActor$$anonfun$act$1.scala$actors$remote$DelegateActor$$anonfun$$$outer:()Lscala/actors/remote/DelegateActor;
   1027:	getfield	#126; //Field scala/actors/remote/DelegateActor.scala$actors$remote$DelegateActor$$name:Lscala/Symbol;
   1030:	aload_1
   1031:	aload	37
   1033:	invokevirtual	#237; //Method scala/actors/remote/NetKernel.forward:(Lscala/actors/OutputChannel;Lscala/actors/remote/Node;Lscala/Symbol;Ljava/lang/Object;Lscala/Symbol;)V
   1036:	goto	1096
   1039:	aload_0
   1040:	getfield	#40; //Field $outer:Lscala/actors/remote/DelegateActor$$anonfun$act$1;
   1043:	invokevirtual	#233; //Method scala/actors/remote/DelegateActor$$anonfun$act$1.scala$actors$remote$DelegateActor$$anonfun$$$outer:()Lscala/actors/remote/DelegateActor;
   1046:	getfield	#119; //Field scala/actors/remote/DelegateActor.scala$actors$remote$DelegateActor$$kernel:Lscala/actors/remote/NetKernel;
   1049:	aload_0
   1050:	getfield	#40; //Field $outer:Lscala/actors/remote/DelegateActor$$anonfun$act$1;
   1053:	invokevirtual	#233; //Method scala/actors/remote/DelegateActor$$anonfun$act$1.scala$actors$remote$DelegateActor$$anonfun$$$outer:()Lscala/actors/remote/DelegateActor;
   1056:	aload_0
   1057:	getfield	#40; //Field $outer:Lscala/actors/remote/DelegateActor$$anonfun$act$1;
   1060:	invokevirtual	#233; //Method scala/actors/remote/DelegateActor$$anonfun$act$1.scala$actors$remote$DelegateActor$$anonfun$$$outer:()Lscala/actors/remote/DelegateActor;
   1063:	invokevirtual	#130; //Method scala/actors/remote/DelegateActor.protected$sender:(Lscala/actors/remote/DelegateActor;)Lscala/actors/OutputChannel;
   1066:	aload_0
   1067:	getfield	#40; //Field $outer:Lscala/actors/remote/DelegateActor$$anonfun$act$1;
   1070:	invokevirtual	#233; //Method scala/actors/remote/DelegateActor$$anonfun$act$1.scala$actors$remote$DelegateActor$$anonfun$$$outer:()Lscala/actors/remote/DelegateActor;
   1073:	getfield	#123; //Field scala/actors/remote/DelegateActor.scala$actors$remote$DelegateActor$$node:Lscala/actors/remote/Node;
   1076:	aload_0
   1077:	getfield	#40; //Field $outer:Lscala/actors/remote/DelegateActor$$anonfun$act$1;
   1080:	invokevirtual	#233; //Method scala/actors/remote/DelegateActor$$anonfun$act$1.scala$actors$remote$DelegateActor$$anonfun$$$outer:()Lscala/actors/remote/DelegateActor;
   1083:	getfield	#126; //Field scala/actors/remote/DelegateActor.scala$actors$remote$DelegateActor$$name:Lscala/Symbol;
   1086:	aload_1
   1087:	getstatic	#26; //Field symbol$1:Lscala/Symbol;
   1090:	checkcast	#20; //class scala/Symbol
   1093:	invokevirtual	#237; //Method scala/actors/remote/NetKernel.forward:(Lscala/actors/OutputChannel;Lscala/actors/remote/Node;Lscala/Symbol;Ljava/lang/Object;Lscala/Symbol;)V
   1096:	return
   1097:	new	#83; //class scala/MatchError
   1100:	dup
   1101:	aload_1
   1102:	invokevirtual	#87; //Method java/lang/Object.toString:()Ljava/lang/String;
   1105:	invokespecial	#90; //Method scala/MatchError."<init>":(Ljava/lang/String;)V
   1108:	athrow
   1109:	new	#83; //class scala/MatchError
   1112:	dup
   1113:	aload_1
   1114:	invokevirtual	#87; //Method java/lang/Object.toString:()Ljava/lang/String;
   1117:	invokespecial	#90; //Method scala/MatchError."<init>":(Ljava/lang/String;)V
   1120:	athrow
  LineNumberTable: 
   line 126: 0
   line 644: 18
   line 128: 22
   line 126: 95
   line 644: 134
   line 131: 138
   line 126: 165
   line 644: 211
   line 136: 215
   line 138: 245
   line 141: 268
   line 644: 313
   line 144: 317
   line 146: 337
   line 148: 354
   line 146: 356
   line 148: 365
   line 141: 379
   line 126: 400
   line 644: 417
   line 152: 421
   line 153: 441
   line 141: 453
   line 126: 479
   line 644: 520
   line 158: 524
   line 126: 550
   line 644: 589
   line 164: 593
   line 126: 622
   line 644: 639
   line 166: 643
   line 169: 663
   line 164: 720
   line 644: 757
   line 172: 761
   line 164: 807
   line 126: 833
   line 644: 852
   line 178: 856
   line 180: 888
   line 182: 944
   line 183: 983
   line 185: 1039
   line 126: 1096

  LocalVariableTable: 
   Start  Length  Slot  Name   Signature
   0      1121      0    this       Lscala/actors/remote/DelegateActor$$anonfun$act$1$$anonfun$apply$1;
   12      95      2    temp14       Lscala/actors/remote/Apply0;
   18      89      8    temp15       Lscala/Function2;
   120      57      9    temp16       Lscala/actors/remote/LocalApply0;
   127      50      10    temp17       Lscala/Function2;
   134      43      11    temp18       Lscala/actors/AbstractActor;
   190      301      13    temp19       Lscala/actors/remote/SendTo;
   197      294      19    temp20       Lscala/actors/OutputChannel;
   337      39      20    replyCh       Lscala/actors/Channel;
   407      59      21    temp7       Lscala/Some;
   211      280      23    temp22       Lscala/Symbol;
   417      49      24    temp8       Lscala/actors/OutputChannel;
   204      287      25    temp21       Ljava/lang/Object;
   289      190      26    temp5       Lscala/Option;
   575      270      29    temp24       Lscala/actors/$bang;
   629      104      31    temp10       Lscala/Some;
   589      256      33    temp26       Ljava/lang/Object;
   639      94      34    temp11       Lscala/Symbol;
   582      263      35    temp25       Lscala/actors/Channel;
   614      219      36    temp9       Lscala/Option;
   944      92      37    fresh       Lscala/Symbol;


public scala.Function1 compose(scala.Function1);
  Code:
   Stack=2, Locals=2, Args_size=2
   0:	aload_0
   1:	aload_1
   2:	invokestatic	#330; //Method scala/Function1$class.compose:(Lscala/Function1;Lscala/Function1;)Lscala/Function1;
   5:	areturn
  LineNumberTable: 
   line 126: 0

  LocalVariableTable: 
   Start  Length  Slot  Name   Signature
   0      6      0    this       Lscala/actors/remote/DelegateActor$$anonfun$act$1$$anonfun$apply$1;
   0      6      1    g       Lscala/Function1;


public java.lang.String toString();
  Code:
   Stack=1, Locals=1, Args_size=1
   0:	aload_0
   1:	invokestatic	#333; //Method scala/Function1$class.toString:(Lscala/Function1;)Ljava/lang/String;
   4:	areturn
  LineNumberTable: 
   line 126: 0


public scala.PartialFunction andThen(scala.Function1);
  Code:
   Stack=2, Locals=2, Args_size=2
   0:	aload_0
   1:	aload_1
   2:	invokestatic	#336; //Method scala/PartialFunction$class.andThen:(Lscala/PartialFunction;Lscala/Function1;)Lscala/PartialFunction;
   5:	areturn
  LineNumberTable: 
   line 126: 0

  LocalVariableTable: 
   Start  Length  Slot  Name   Signature
   0      6      0    this       Lscala/actors/remote/DelegateActor$$anonfun$act$1$$anonfun$apply$1;
   0      6      1    k       Lscala/Function1;


public scala.PartialFunction orElse(scala.PartialFunction);
  Code:
   Stack=2, Locals=2, Args_size=2
   0:	aload_0
   1:	aload_1
   2:	invokestatic	#342; //Method scala/PartialFunction$class.orElse:(Lscala/PartialFunction;Lscala/PartialFunction;)Lscala/PartialFunction;
   5:	areturn
  LineNumberTable: 
   line 126: 0

  LocalVariableTable: 
   Start  Length  Slot  Name   Signature
   0      6      0    this       Lscala/actors/remote/DelegateActor$$anonfun$act$1$$anonfun$apply$1;
   0      6      1    that       Lscala/PartialFunction;


}

