Compiled from "Proxy.scala"
public final class scala.actors.remote.DelegateActor$$anonfun$act$1$$anonfun$apply$1 extends java.lang.Object implements scala.PartialFunction,java.io.Serializable
  SourceFile: "Proxy.scala"
  Scala: length = 0x
   
  InnerClass: 
   public final $anonfun$act$1=class scala/actors/remote/DelegateActor$$anonfun$act$1 of class scala/actors/remote/DelegateActor
   public final $anonfun$apply$1=class scala/actors/remote/DelegateActor$$anonfun$act$1$$anonfun$apply$1 of class scala/actors/remote/DelegateActor$$anonfun$act$1
  minor version: 0
  major version: 49
  Constant pool:
Asciz	SourceFile;
Asciz	Proxy.scala;
Asciz	<clinit>;
Asciz	()V;
Asciz	Code;
Asciz	scala/Symbol$;
class	scala/Symbol$
Asciz	MODULE$;
Asciz	Lscala/Symbol$;;
NameAndType	MODULE$:Lscala/Symbol$;
Field	scala/Symbol$.MODULE$:Lscala/Symbol$;
Asciz	LineNumberTable;
Asciz	nosession;
String	nosession
Asciz	apply;
Asciz	(Ljava/lang/Object;)Ljava/lang/Object;;
NameAndType	apply:(Ljava/lang/Object;)Ljava/lang/Object;
Method	scala/Symbol$.apply:(Ljava/lang/Object;)Ljava/lang/Object;
Asciz	scala/Symbol;
class	scala/Symbol
Asciz	scala/actors/remote/DelegateActor$$anonfun$act$1$$anonfun$apply$1;
class	scala/actors/remote/DelegateActor$$anonfun$act$1$$anonfun$apply$1
Asciz	symbol$1;
Asciz	Lscala/Symbol;;
NameAndType	symbol$1:Lscala/Symbol;
Field	scala/actors/remote/DelegateActor$$anonfun$act$1$$anonfun$apply$1.symbol$1:Lscala/Symbol;
Asciz	serialVersionUID;
Asciz	J;
NameAndType	serialVersionUID:J
Field	scala/actors/remote/DelegateActor$$anonfun$act$1$$anonfun$apply$1.serialVersionUID:J
Asciz	$outer;
Asciz	Lscala/actors/remote/DelegateActor$$anonfun$act$1;;
Asciz	orElse;
Asciz	(Lscala/PartialFunction;)Lscala/PartialFunction;;
Asciz	scala/PartialFunction$class;
class	scala/PartialFunction$class
Asciz	(Lscala/PartialFunction;Lscala/PartialFunction;)Lscala/PartialFunction;;
NameAndType	orElse:(Lscala/PartialFunction;Lscala/PartialFunction;)Lscala/PartialFunction;
Method	scala/PartialFunction$class.orElse:(Lscala/PartialFunction;Lscala/PartialFunction;)Lscala/PartialFunction;
Asciz	this;
Asciz	Lscala/actors/remote/DelegateActor$$anonfun$act$1$$anonfun$apply$1;;
Asciz	that;
Asciz	Lscala/PartialFunction;;
Asciz	LocalVariableTable;
Asciz	andThen;
Asciz	(Lscala/Function1;)Lscala/PartialFunction;;
Asciz	(Lscala/PartialFunction;Lscala/Function1;)Lscala/PartialFunction;;
NameAndType	andThen:(Lscala/PartialFunction;Lscala/Function1;)Lscala/PartialFunction;
Method	scala/PartialFunction$class.andThen:(Lscala/PartialFunction;Lscala/Function1;)Lscala/PartialFunction;
Asciz	k;
Asciz	Lscala/Function1;;
Asciz	lift;
Asciz	()Lscala/Function1;;
Asciz	(Lscala/PartialFunction;)Lscala/Function1;;
NameAndType	lift:(Lscala/PartialFunction;)Lscala/Function1;
Method	scala/PartialFunction$class.lift:(Lscala/PartialFunction;)Lscala/Function1;
Asciz	apply$mcVI$sp;
Asciz	(I)V;
Asciz	scala/Function1$class;
class	scala/Function1$class
Asciz	(Lscala/Function1;I)V;
NameAndType	apply$mcVI$sp:(Lscala/Function1;I)V
Method	scala/Function1$class.apply$mcVI$sp:(Lscala/Function1;I)V
Asciz	v1;
Asciz	I;
Asciz	apply$mcZI$sp;
Asciz	(I)Z;
Asciz	(Lscala/Function1;I)Z;
NameAndType	apply$mcZI$sp:(Lscala/Function1;I)Z
Method	scala/Function1$class.apply$mcZI$sp:(Lscala/Function1;I)Z
Asciz	apply$mcII$sp;
Asciz	(I)I;
Asciz	(Lscala/Function1;I)I;
NameAndType	apply$mcII$sp:(Lscala/Function1;I)I
Method	scala/Function1$class.apply$mcII$sp:(Lscala/Function1;I)I
Asciz	apply$mcLI$sp;
Asciz	(I)J;
Asciz	(Lscala/Function1;I)J;
NameAndType	apply$mcLI$sp:(Lscala/Function1;I)J
Method	scala/Function1$class.apply$mcLI$sp:(Lscala/Function1;I)J
Asciz	apply$mcDI$sp;
Asciz	(I)D;
Asciz	(Lscala/Function1;I)D;
NameAndType	apply$mcDI$sp:(Lscala/Function1;I)D
Method	scala/Function1$class.apply$mcDI$sp:(Lscala/Function1;I)D
Asciz	apply$mcVL$sp;
Asciz	(J)V;
Asciz	(Lscala/Function1;J)V;
NameAndType	apply$mcVL$sp:(Lscala/Function1;J)V
Method	scala/Function1$class.apply$mcVL$sp:(Lscala/Function1;J)V
Asciz	apply$mcZL$sp;
Asciz	(J)Z;
Asciz	(Lscala/Function1;J)Z;
NameAndType	apply$mcZL$sp:(Lscala/Function1;J)Z
Method	scala/Function1$class.apply$mcZL$sp:(Lscala/Function1;J)Z
Asciz	apply$mcIL$sp;
Asciz	(J)I;
Asciz	(Lscala/Function1;J)I;
NameAndType	apply$mcIL$sp:(Lscala/Function1;J)I
Method	scala/Function1$class.apply$mcIL$sp:(Lscala/Function1;J)I
Asciz	apply$mcLL$sp;
Asciz	(J)J;
Asciz	(Lscala/Function1;J)J;
NameAndType	apply$mcLL$sp:(Lscala/Function1;J)J
Method	scala/Function1$class.apply$mcLL$sp:(Lscala/Function1;J)J
Asciz	apply$mcDL$sp;
Asciz	(J)D;
Asciz	(Lscala/Function1;J)D;
NameAndType	apply$mcDL$sp:(Lscala/Function1;J)D
Method	scala/Function1$class.apply$mcDL$sp:(Lscala/Function1;J)D
Asciz	apply$mcVD$sp;
Asciz	(D)V;
Asciz	(Lscala/Function1;D)V;
NameAndType	apply$mcVD$sp:(Lscala/Function1;D)V
Method	scala/Function1$class.apply$mcVD$sp:(Lscala/Function1;D)V
Asciz	D;
Asciz	apply$mcZD$sp;
Asciz	(D)Z;
Asciz	(Lscala/Function1;D)Z;
NameAndType	apply$mcZD$sp:(Lscala/Function1;D)Z
Method	scala/Function1$class.apply$mcZD$sp:(Lscala/Function1;D)Z
Asciz	apply$mcID$sp;
Asciz	(D)I;
Asciz	(Lscala/Function1;D)I;
NameAndType	apply$mcID$sp:(Lscala/Function1;D)I
Method	scala/Function1$class.apply$mcID$sp:(Lscala/Function1;D)I
Asciz	apply$mcLD$sp;
Asciz	(D)J;
Asciz	(Lscala/Function1;D)J;
NameAndType	apply$mcLD$sp:(Lscala/Function1;D)J
Method	scala/Function1$class.apply$mcLD$sp:(Lscala/Function1;D)J
Asciz	apply$mcDD$sp;
Asciz	(D)D;
Asciz	(Lscala/Function1;D)D;
NameAndType	apply$mcDD$sp:(Lscala/Function1;D)D
Method	scala/Function1$class.apply$mcDD$sp:(Lscala/Function1;D)D
Asciz	toString;
Asciz	()Ljava/lang/String;;
Asciz	(Lscala/Function1;)Ljava/lang/String;;
NameAndType	toString:(Lscala/Function1;)Ljava/lang/String;
Method	scala/Function1$class.toString:(Lscala/Function1;)Ljava/lang/String;
Asciz	compose;
Asciz	(Lscala/Function1;)Lscala/Function1;;
Asciz	(Lscala/Function1;Lscala/Function1;)Lscala/Function1;;
NameAndType	compose:(Lscala/Function1;Lscala/Function1;)Lscala/Function1;
Method	scala/Function1$class.compose:(Lscala/Function1;Lscala/Function1;)Lscala/Function1;
Asciz	g;
Asciz	compose$mcVI$sp;
NameAndType	compose$mcVI$sp:(Lscala/Function1;Lscala/Function1;)Lscala/Function1;
Method	scala/Function1$class.compose$mcVI$sp:(Lscala/Function1;Lscala/Function1;)Lscala/Function1;
Asciz	compose$mcZI$sp;
NameAndType	compose$mcZI$sp:(Lscala/Function1;Lscala/Function1;)Lscala/Function1;
Method	scala/Function1$class.compose$mcZI$sp:(Lscala/Function1;Lscala/Function1;)Lscala/Function1;
Asciz	compose$mcII$sp;
NameAndType	compose$mcII$sp:(Lscala/Function1;Lscala/Function1;)Lscala/Function1;
Method	scala/Function1$class.compose$mcII$sp:(Lscala/Function1;Lscala/Function1;)Lscala/Function1;
Asciz	compose$mcLI$sp;
NameAndType	compose$mcLI$sp:(Lscala/Function1;Lscala/Function1;)Lscala/Function1;
Method	scala/Function1$class.compose$mcLI$sp:(Lscala/Function1;Lscala/Function1;)Lscala/Function1;
Asciz	compose$mcDI$sp;
NameAndType	compose$mcDI$sp:(Lscala/Function1;Lscala/Function1;)Lscala/Function1;
Method	scala/Function1$class.compose$mcDI$sp:(Lscala/Function1;Lscala/Function1;)Lscala/Function1;
Asciz	compose$mcVL$sp;
NameAndType	compose$mcVL$sp:(Lscala/Function1;Lscala/Function1;)Lscala/Function1;
Method	scala/Function1$class.compose$mcVL$sp:(Lscala/Function1;Lscala/Function1;)Lscala/Function1;
Asciz	compose$mcZL$sp;
NameAndType	compose$mcZL$sp:(Lscala/Function1;Lscala/Function1;)Lscala/Function1;
Method	scala/Function1$class.compose$mcZL$sp:(Lscala/Function1;Lscala/Function1;)Lscala/Function1;
Asciz	compose$mcIL$sp;
NameAndType	compose$mcIL$sp:(Lscala/Function1;Lscala/Function1;)Lscala/Function1;
Method	scala/Function1$class.compose$mcIL$sp:(Lscala/Function1;Lscala/Function1;)Lscala/Function1;
Asciz	compose$mcLL$sp;
NameAndType	compose$mcLL$sp:(Lscala/Function1;Lscala/Function1;)Lscala/Function1;
Method	scala/Function1$class.compose$mcLL$sp:(Lscala/Function1;Lscala/Function1;)Lscala/Function1;
Asciz	compose$mcDL$sp;
NameAndType	compose$mcDL$sp:(Lscala/Function1;Lscala/Function1;)Lscala/Function1;
Method	scala/Function1$class.compose$mcDL$sp:(Lscala/Function1;Lscala/Function1;)Lscala/Function1;
Asciz	compose$mcVD$sp;
NameAndType	compose$mcVD$sp:(Lscala/Function1;Lscala/Function1;)Lscala/Function1;
Method	scala/Function1$class.compose$mcVD$sp:(Lscala/Function1;Lscala/Function1;)Lscala/Function1;
Asciz	compose$mcZD$sp;
NameAndType	compose$mcZD$sp:(Lscala/Function1;Lscala/Function1;)Lscala/Function1;
Method	scala/Function1$class.compose$mcZD$sp:(Lscala/Function1;Lscala/Function1;)Lscala/Function1;
Asciz	compose$mcID$sp;
NameAndType	compose$mcID$sp:(Lscala/Function1;Lscala/Function1;)Lscala/Function1;
Method	scala/Function1$class.compose$mcID$sp:(Lscala/Function1;Lscala/Function1;)Lscala/Function1;
Asciz	compose$mcLD$sp;
NameAndType	compose$mcLD$sp:(Lscala/Function1;Lscala/Function1;)Lscala/Function1;
Method	scala/Function1$class.compose$mcLD$sp:(Lscala/Function1;Lscala/Function1;)Lscala/Function1;
Asciz	compose$mcDD$sp;
NameAndType	compose$mcDD$sp:(Lscala/Function1;Lscala/Function1;)Lscala/Function1;
Method	scala/Function1$class.compose$mcDD$sp:(Lscala/Function1;Lscala/Function1;)Lscala/Function1;
Asciz	andThen$mcVI$sp;
NameAndType	andThen$mcVI$sp:(Lscala/Function1;Lscala/Function1;)Lscala/Function1;
Method	scala/Function1$class.andThen$mcVI$sp:(Lscala/Function1;Lscala/Function1;)Lscala/Function1;
Asciz	andThen$mcZI$sp;
NameAndType	andThen$mcZI$sp:(Lscala/Function1;Lscala/Function1;)Lscala/Function1;
Method	scala/Function1$class.andThen$mcZI$sp:(Lscala/Function1;Lscala/Function1;)Lscala/Function1;
Asciz	andThen$mcII$sp;
NameAndType	andThen$mcII$sp:(Lscala/Function1;Lscala/Function1;)Lscala/Function1;
Method	scala/Function1$class.andThen$mcII$sp:(Lscala/Function1;Lscala/Function1;)Lscala/Function1;
Asciz	andThen$mcLI$sp;
NameAndType	andThen$mcLI$sp:(Lscala/Function1;Lscala/Function1;)Lscala/Function1;
Method	scala/Function1$class.andThen$mcLI$sp:(Lscala/Function1;Lscala/Function1;)Lscala/Function1;
Asciz	andThen$mcDI$sp;
NameAndType	andThen$mcDI$sp:(Lscala/Function1;Lscala/Function1;)Lscala/Function1;
Method	scala/Function1$class.andThen$mcDI$sp:(Lscala/Function1;Lscala/Function1;)Lscala/Function1;
Asciz	andThen$mcVL$sp;
NameAndType	andThen$mcVL$sp:(Lscala/Function1;Lscala/Function1;)Lscala/Function1;
Method	scala/Function1$class.andThen$mcVL$sp:(Lscala/Function1;Lscala/Function1;)Lscala/Function1;
Asciz	andThen$mcZL$sp;
NameAndType	andThen$mcZL$sp:(Lscala/Function1;Lscala/Function1;)Lscala/Function1;
Method	scala/Function1$class.andThen$mcZL$sp:(Lscala/Function1;Lscala/Function1;)Lscala/Function1;
Asciz	andThen$mcIL$sp;
NameAndType	andThen$mcIL$sp:(Lscala/Function1;Lscala/Function1;)Lscala/Function1;
Method	scala/Function1$class.andThen$mcIL$sp:(Lscala/Function1;Lscala/Function1;)Lscala/Function1;
Asciz	andThen$mcLL$sp;
NameAndType	andThen$mcLL$sp:(Lscala/Function1;Lscala/Function1;)Lscala/Function1;
Method	scala/Function1$class.andThen$mcLL$sp:(Lscala/Function1;Lscala/Function1;)Lscala/Function1;
Asciz	andThen$mcDL$sp;
NameAndType	andThen$mcDL$sp:(Lscala/Function1;Lscala/Function1;)Lscala/Function1;
Method	scala/Function1$class.andThen$mcDL$sp:(Lscala/Function1;Lscala/Function1;)Lscala/Function1;
Asciz	andThen$mcVD$sp;
NameAndType	andThen$mcVD$sp:(Lscala/Function1;Lscala/Function1;)Lscala/Function1;
Method	scala/Function1$class.andThen$mcVD$sp:(Lscala/Function1;Lscala/Function1;)Lscala/Function1;
Asciz	andThen$mcZD$sp;
NameAndType	andThen$mcZD$sp:(Lscala/Function1;Lscala/Function1;)Lscala/Function1;
Method	scala/Function1$class.andThen$mcZD$sp:(Lscala/Function1;Lscala/Function1;)Lscala/Function1;
Asciz	andThen$mcID$sp;
NameAndType	andThen$mcID$sp:(Lscala/Function1;Lscala/Function1;)Lscala/Function1;
Method	scala/Function1$class.andThen$mcID$sp:(Lscala/Function1;Lscala/Function1;)Lscala/Function1;
Asciz	andThen$mcLD$sp;
NameAndType	andThen$mcLD$sp:(Lscala/Function1;Lscala/Function1;)Lscala/Function1;
Method	scala/Function1$class.andThen$mcLD$sp:(Lscala/Function1;Lscala/Function1;)Lscala/Function1;
Asciz	andThen$mcDD$sp;
NameAndType	andThen$mcDD$sp:(Lscala/Function1;Lscala/Function1;)Lscala/Function1;
Method	scala/Function1$class.andThen$mcDD$sp:(Lscala/Function1;Lscala/Function1;)Lscala/Function1;
Asciz	(Ljava/lang/Object;)V;
Asciz	scala/actors/remote/Apply0;
class	scala/actors/remote/Apply0
NameAndType	$outer:Lscala/actors/remote/DelegateActor$$anonfun$act$1;
Field	scala/actors/remote/DelegateActor$$anonfun$act$1$$anonfun$apply$1.$outer:Lscala/actors/remote/DelegateActor$$anonfun$act$1;
Asciz	scala/actors/remote/DelegateActor$$anonfun$act$1;
class	scala/actors/remote/DelegateActor$$anonfun$act$1
Asciz	Lscala/actors/remote/DelegateActor;;
NameAndType	$outer:Lscala/actors/remote/DelegateActor;
Field	scala/actors/remote/DelegateActor$$anonfun$act$1.$outer:Lscala/actors/remote/DelegateActor;
Asciz	scala/actors/remote/DelegateActor;
class	scala/actors/remote/DelegateActor
Asciz	scala$actors$remote$DelegateActor$$kernel;
Asciz	Lscala/actors/remote/NetKernel;;
NameAndType	scala$actors$remote$DelegateActor$$kernel:Lscala/actors/remote/NetKernel;
Field	scala/actors/remote/DelegateActor.scala$actors$remote$DelegateActor$$kernel:Lscala/actors/remote/NetKernel;
Asciz	scala$actors$remote$DelegateActor$$node;
Asciz	Lscala/actors/remote/Node;;
NameAndType	scala$actors$remote$DelegateActor$$node:Lscala/actors/remote/Node;
Field	scala/actors/remote/DelegateActor.scala$actors$remote$DelegateActor$$node:Lscala/actors/remote/Node;
Asciz	scala$actors$remote$DelegateActor$$name;
NameAndType	scala$actors$remote$DelegateActor$$name:Lscala/Symbol;
Field	scala/actors/remote/DelegateActor.scala$actors$remote$DelegateActor$$name:Lscala/Symbol;
Asciz	protected$sender;
Asciz	(Lscala/actors/remote/DelegateActor;)Lscala/actors/OutputChannel;;
NameAndType	protected$sender:(Lscala/actors/remote/DelegateActor;)Lscala/actors/OutputChannel;
Method	scala/actors/remote/DelegateActor.protected$sender:(Lscala/actors/remote/DelegateActor;)Lscala/actors/OutputChannel;
Asciz	rfun;
Asciz	()Lscala/Function2;;
NameAndType	rfun:()Lscala/Function2;
Method	scala/actors/remote/Apply0.rfun:()Lscala/Function2;
Asciz	scala/actors/remote/NetKernel;
class	scala/actors/remote/NetKernel
Asciz	remoteApply;
Asciz	(Lscala/actors/remote/Node;Lscala/Symbol;Lscala/actors/OutputChannel;Lscala/Function2;)V;
NameAndType	remoteApply:(Lscala/actors/remote/Node;Lscala/Symbol;Lscala/actors/OutputChannel;Lscala/Function2;)V
Method	scala/actors/remote/NetKernel.remoteApply:(Lscala/actors/remote/Node;Lscala/Symbol;Lscala/actors/OutputChannel;Lscala/Function2;)V
Asciz	scala/actors/remote/LocalApply0;
class	scala/actors/remote/LocalApply0
Method	scala/actors/remote/LocalApply0.rfun:()Lscala/Function2;
Asciz	a;
Asciz	()Lscala/actors/AbstractActor;;
NameAndType	a:()Lscala/actors/AbstractActor;
Method	scala/actors/remote/LocalApply0.a:()Lscala/actors/AbstractActor;
Asciz	scala$actors$remote$DelegateActor$$creator;
Asciz	Lscala/actors/remote/Proxy;;
NameAndType	scala$actors$remote$DelegateActor$$creator:Lscala/actors/remote/Proxy;
Field	scala/actors/remote/DelegateActor.scala$actors$remote$DelegateActor$$creator:Lscala/actors/remote/Proxy;
Asciz	scala/Function2;
class	scala/Function2
Asciz	(Ljava/lang/Object;Ljava/lang/Object;)Ljava/lang/Object;;
NameAndType	apply:(Ljava/lang/Object;Ljava/lang/Object;)Ljava/lang/Object;
InterfaceMethod	scala/Function2.apply:(Ljava/lang/Object;Ljava/lang/Object;)Ljava/lang/Object;
Asciz	scala/actors/remote/SendTo;
class	scala/actors/remote/SendTo
Asciz	()Lscala/actors/OutputChannel;;
NameAndType	a:()Lscala/actors/OutputChannel;
Method	scala/actors/remote/SendTo.a:()Lscala/actors/OutputChannel;
Asciz	msg;
Asciz	()Ljava/lang/Object;;
NameAndType	msg:()Ljava/lang/Object;
Method	scala/actors/remote/SendTo.msg:()Ljava/lang/Object;
Asciz	session;
Asciz	()Lscala/Symbol;;
NameAndType	session:()Lscala/Symbol;
Method	scala/actors/remote/SendTo.session:()Lscala/Symbol;
Asciz	name;
NameAndType	name:()Ljava/lang/String;
Method	scala/Symbol.name:()Ljava/lang/String;
Asciz	java/lang/Object;
class	java/lang/Object
Asciz	equals;
Asciz	(Ljava/lang/Object;)Z;
NameAndType	equals:(Ljava/lang/Object;)Z
Method	java/lang/Object.equals:(Ljava/lang/Object;)Z
Asciz	scala/actors/OutputChannel;
class	scala/actors/OutputChannel
Asciz	send;
Asciz	(Ljava/lang/Object;Lscala/actors/OutputChannel;)V;
NameAndType	send:(Ljava/lang/Object;Lscala/actors/OutputChannel;)V
InterfaceMethod	scala/actors/OutputChannel.send:(Ljava/lang/Object;Lscala/actors/OutputChannel;)V
Asciz	channelMap;
Asciz	()Lscala/collection/mutable/HashMap;;
NameAndType	channelMap:()Lscala/collection/mutable/HashMap;
Method	scala/actors/remote/DelegateActor.channelMap:()Lscala/collection/mutable/HashMap;
Asciz	scala/collection/mutable/HashMap;
class	scala/collection/mutable/HashMap
Asciz	get;
Asciz	(Ljava/lang/Object;)Lscala/Option;;
NameAndType	get:(Ljava/lang/Object;)Lscala/Option;
Method	scala/collection/mutable/HashMap.get:(Ljava/lang/Object;)Lscala/Option;
Asciz	scala/None$;
class	scala/None$
Asciz	Lscala/None$;;
NameAndType	MODULE$:Lscala/None$;
Field	scala/None$.MODULE$:Lscala/None$;
Asciz	scala/actors/Channel;
class	scala/actors/Channel
Asciz	<init>;
Asciz	(Lscala/actors/Actor;)V;
NameAndType	"<init>":(Lscala/actors/Actor;)V
Method	scala/actors/Channel."<init>":(Lscala/actors/Actor;)V
Asciz	sessionMap;
NameAndType	sessionMap:()Lscala/collection/mutable/HashMap;
Method	scala/actors/remote/DelegateActor.sessionMap:()Lscala/collection/mutable/HashMap;
Asciz	scala/Predef$Pair$;
class	scala/Predef$Pair$
Asciz	Lscala/Predef$Pair$;;
NameAndType	MODULE$:Lscala/Predef$Pair$;
Field	scala/Predef$Pair$.MODULE$:Lscala/Predef$Pair$;
Asciz	(Ljava/lang/Object;Ljava/lang/Object;)Lscala/Tuple2;;
NameAndType	apply:(Ljava/lang/Object;Ljava/lang/Object;)Lscala/Tuple2;
Method	scala/Predef$Pair$.apply:(Ljava/lang/Object;Ljava/lang/Object;)Lscala/Tuple2;
Asciz	$plus$eq;
Asciz	(Lscala/Tuple2;)Lscala/collection/mutable/HashMap;;
NameAndType	$plus$eq:(Lscala/Tuple2;)Lscala/collection/mutable/HashMap;
Method	scala/collection/mutable/HashMap.$plus$eq:(Lscala/Tuple2;)Lscala/collection/mutable/HashMap;
Asciz	scala/Some;
class	scala/Some
Asciz	$minus$eq;
Asciz	(Ljava/lang/Object;)Lscala/collection/mutable/HashMap;;
NameAndType	$minus$eq:(Ljava/lang/Object;)Lscala/collection/mutable/HashMap;
Method	scala/collection/mutable/HashMap.$minus$eq:(Ljava/lang/Object;)Lscala/collection/mutable/HashMap;
Asciz	x;
NameAndType	x:()Ljava/lang/Object;
Method	scala/Some.x:()Ljava/lang/Object;
Asciz	$bang;
NameAndType	$bang:(Ljava/lang/Object;)V
InterfaceMethod	scala/actors/OutputChannel.$bang:(Ljava/lang/Object;)V
Asciz	scala/MatchError;
class	scala/MatchError
NameAndType	"<init>":(Ljava/lang/Object;)V
Method	scala/MatchError."<init>":(Ljava/lang/Object;)V
Asciz	scala/actors/remote/Terminate$;
class	scala/actors/remote/Terminate$
Asciz	Lscala/actors/remote/Terminate$;;
NameAndType	MODULE$:Lscala/actors/remote/Terminate$;
Field	scala/actors/remote/Terminate$.MODULE$:Lscala/actors/remote/Terminate$;
Asciz	protected$exit;
Asciz	(Lscala/actors/remote/DelegateActor;)Lscala/runtime/Nothing$;;
NameAndType	protected$exit:(Lscala/actors/remote/DelegateActor;)Lscala/runtime/Nothing$;
Method	scala/actors/remote/DelegateActor.protected$exit:(Lscala/actors/remote/DelegateActor;)Lscala/runtime/Nothing$;
Asciz	scala/actors/$bang;
class	scala/actors/$bang
Asciz	ch;
Asciz	()Lscala/actors/Channel;;
NameAndType	ch:()Lscala/actors/Channel;
Method	scala/actors/$bang.ch:()Lscala/actors/Channel;
Method	scala/actors/$bang.msg:()Ljava/lang/Object;
Asciz	scala$actors$remote$DelegateActor$$anonfun$$$outer;
Asciz	()Lscala/actors/remote/DelegateActor;;
NameAndType	scala$actors$remote$DelegateActor$$anonfun$$$outer:()Lscala/actors/remote/DelegateActor;
Method	scala/actors/remote/DelegateActor$$anonfun$act$1.scala$actors$remote$DelegateActor$$anonfun$$$outer:()Lscala/actors/remote/DelegateActor;
Asciz	forward;
Asciz	(Lscala/actors/OutputChannel;Lscala/actors/remote/Node;Lscala/Symbol;Ljava/lang/Object;Lscala/Symbol;)V;
NameAndType	forward:(Lscala/actors/OutputChannel;Lscala/actors/remote/Node;Lscala/Symbol;Ljava/lang/Object;Lscala/Symbol;)V
Method	scala/actors/remote/NetKernel.forward:(Lscala/actors/OutputChannel;Lscala/actors/remote/Node;Lscala/Symbol;Ljava/lang/Object;Lscala/Symbol;)V
Asciz	scala/actors/Debug$;
class	scala/actors/Debug$
Asciz	Lscala/actors/Debug$;;
NameAndType	MODULE$:Lscala/actors/Debug$;
Field	scala/actors/Debug$.MODULE$:Lscala/actors/Debug$;
Asciz	scala/collection/mutable/StringBuilder;
class	scala/collection/mutable/StringBuilder
NameAndType	"<init>":()V
Method	scala/collection/mutable/StringBuilder."<init>":()V
Asciz	scala/Predef$;
class	scala/Predef$
Asciz	Lscala/Predef$;;
NameAndType	MODULE$:Lscala/Predef$;
Field	scala/Predef$.MODULE$:Lscala/Predef$;
Asciz	any2stringadd;
Asciz	(Ljava/lang/Object;)Lscala/runtime/StringAdd;;
NameAndType	any2stringadd:(Ljava/lang/Object;)Lscala/runtime/StringAdd;
Method	scala/Predef$.any2stringadd:(Ljava/lang/Object;)Lscala/runtime/StringAdd;
Asciz	: cannot find session for ;
String	: cannot find session for 
Asciz	scala/runtime/StringAdd;
class	scala/runtime/StringAdd
Asciz	$plus;
Asciz	(Ljava/lang/String;)Ljava/lang/String;;
NameAndType	$plus:(Ljava/lang/String;)Ljava/lang/String;
Method	scala/runtime/StringAdd.$plus:(Ljava/lang/String;)Ljava/lang/String;
Asciz	append;
Asciz	(Ljava/lang/Object;)Lscala/collection/mutable/StringBuilder;;
NameAndType	append:(Ljava/lang/Object;)Lscala/collection/mutable/StringBuilder;
Method	scala/collection/mutable/StringBuilder.append:(Ljava/lang/Object;)Lscala/collection/mutable/StringBuilder;
NameAndType	toString:()Ljava/lang/String;
Method	scala/collection/mutable/StringBuilder.toString:()Ljava/lang/String;
Asciz	info;
Asciz	(Ljava/lang/String;)V;
NameAndType	info:(Ljava/lang/String;)V
Method	scala/actors/Debug$.info:(Ljava/lang/String;)V
Asciz	getClass;
Asciz	()Ljava/lang/Class;;
NameAndType	getClass:()Ljava/lang/Class;
Method	java/lang/Object.getClass:()Ljava/lang/Class;
Asciz	java/lang/Class;
class	java/lang/Class
Method	java/lang/Class.toString:()Ljava/lang/String;
Asciz	Channel;
String	Channel
Asciz	java/lang/String;
class	java/lang/String
Asciz	contains;
Asciz	(Ljava/lang/CharSequence;)Z;
NameAndType	contains:(Ljava/lang/CharSequence;)Z
Method	java/lang/String.contains:(Ljava/lang/CharSequence;)Z
Asciz	scala/actors/remote/FreshNameCreator$;
class	scala/actors/remote/FreshNameCreator$
Asciz	Lscala/actors/remote/FreshNameCreator$;;
NameAndType	MODULE$:Lscala/actors/remote/FreshNameCreator$;
Field	scala/actors/remote/FreshNameCreator$.MODULE$:Lscala/actors/remote/FreshNameCreator$;
Asciz	@;
String	@
Asciz	newName;
Asciz	(Ljava/lang/String;)Lscala/Symbol;;
NameAndType	newName:(Ljava/lang/String;)Lscala/Symbol;
Method	scala/actors/remote/FreshNameCreator$.newName:(Ljava/lang/String;)Lscala/Symbol;
Asciz	temp16;
Asciz	Lscala/actors/remote/LocalApply0;;
Asciz	temp19;
Asciz	Lscala/actors/remote/SendTo;;
Asciz	temp20;
Asciz	Lscala/actors/OutputChannel;;
Asciz	replyCh;
Asciz	Lscala/actors/Channel;;
Asciz	temp22;
Asciz	temp21;
Asciz	Ljava/lang/Object;;
Asciz	temp5;
Asciz	Lscala/Option;;
Asciz	temp24;
Asciz	Lscala/actors/$bang;;
Asciz	temp26;
Asciz	temp25;
Asciz	temp9;
Asciz	fresh;
Asciz	isDefinedAt;
Asciz	scala/PartialFunction;
class	scala/PartialFunction
NameAndType	andThen:(Lscala/Function1;)Lscala/PartialFunction;
InterfaceMethod	scala/PartialFunction.andThen:(Lscala/Function1;)Lscala/PartialFunction;
NameAndType	apply:(Ljava/lang/Object;)V
Method	scala/actors/remote/DelegateActor$$anonfun$act$1$$anonfun$apply$1.apply:(Ljava/lang/Object;)V
Asciz	scala/runtime/BoxedUnit;
class	scala/runtime/BoxedUnit
Asciz	UNIT;
Asciz	Lscala/runtime/BoxedUnit;;
NameAndType	UNIT:Lscala/runtime/BoxedUnit;
Field	scala/runtime/BoxedUnit.UNIT:Lscala/runtime/BoxedUnit;
Asciz	(Lscala/actors/remote/DelegateActor$$anonfun$act$1;)V;
Asciz	java/lang/NullPointerException;
class	java/lang/NullPointerException
Method	java/lang/NullPointerException."<init>":()V
Method	java/lang/Object."<init>":()V
Asciz	$init$;
Asciz	(Lscala/Function1;)V;
NameAndType	$init$:(Lscala/Function1;)V
Method	scala/Function1$class.$init$:(Lscala/Function1;)V
Asciz	(Lscala/PartialFunction;)V;
NameAndType	$init$:(Lscala/PartialFunction;)V
Method	scala/PartialFunction$class.$init$:(Lscala/PartialFunction;)V
Asciz	Scala;
Asciz	InnerClasses;
Asciz	$anonfun$act$1;
Asciz	$anonfun$apply$1;
Asciz	java/io/Serializable;
class	java/io/Serializable

{
public static final long serialVersionUID;
  Signature: J

public final scala.actors.remote.DelegateActor$$anonfun$act$1 $outer;
  Signature: Lscala/actors/remote/DelegateActor$$anonfun$act$1;

public static final scala.Symbol symbol$1;
  Signature: Lscala/Symbol;

public static {};
  Signature: ()V
  Code:
   Stack=2, Locals=0, Args_size=0
	getstatic	Field scala/Symbol$.MODULE$:Lscala/Symbol$;
	ldc	String nosession
	invokevirtual	Method scala/Symbol$.apply:(Ljava/lang/Object;)Ljava/lang/Object;
	checkcast	class scala/Symbol
	putstatic	Field symbol$1:Lscala/Symbol;
	lconst_0
	putstatic	Field serialVersionUID:J
	return
  Labels:

public scala.PartialFunction orElse(scala.PartialFunction);
  Signature: (Lscala/PartialFunction;)Lscala/PartialFunction;
  Code:
   Stack=2, Locals=2, Args_size=2
	aload_0
	aload_1
	invokestatic	Method scala/PartialFunction$class.orElse:(Lscala/PartialFunction;Lscala/PartialFunction;)Lscala/PartialFunction;
	areturn
  Labels:
  LocalVariableTable: 
   Start  Length  Slot  Name   Signature
   0      6      0    this       Lscala/actors/remote/DelegateActor$$anonfun$act$1$$anonfun$apply$1;
   0      6      1    that       Lscala/PartialFunction;


public scala.PartialFunction andThen(scala.Function1);
  Signature: (Lscala/Function1;)Lscala/PartialFunction;
  Code:
   Stack=2, Locals=2, Args_size=2
	aload_0
	aload_1
	invokestatic	Method scala/PartialFunction$class.andThen:(Lscala/PartialFunction;Lscala/Function1;)Lscala/PartialFunction;
	areturn
  Labels:
  LocalVariableTable: 
   Start  Length  Slot  Name   Signature
   0      6      0    this       Lscala/actors/remote/DelegateActor$$anonfun$act$1$$anonfun$apply$1;
   0      6      1    k       Lscala/Function1;


public scala.Function1 lift();
  Signature: ()Lscala/Function1;
  Code:
   Stack=1, Locals=1, Args_size=1
	aload_0
	invokestatic	Method scala/PartialFunction$class.lift:(Lscala/PartialFunction;)Lscala/Function1;
	areturn
  Labels:

public void apply$mcVI$sp(int);
  Signature: (I)V
  Code:
   Stack=2, Locals=2, Args_size=2
	aload_0
	iload_1
	invokestatic	Method scala/Function1$class.apply$mcVI$sp:(Lscala/Function1;I)V
	return
  Labels:
  LocalVariableTable: 
   Start  Length  Slot  Name   Signature
   0      6      0    this       Lscala/actors/remote/DelegateActor$$anonfun$act$1$$anonfun$apply$1;
   0      6      1    v1       I


public boolean apply$mcZI$sp(int);
  Signature: (I)Z
  Code:
   Stack=2, Locals=2, Args_size=2
	aload_0
	iload_1
	invokestatic	Method scala/Function1$class.apply$mcZI$sp:(Lscala/Function1;I)Z
	ireturn
  Labels:
  LocalVariableTable: 
   Start  Length  Slot  Name   Signature
   0      6      0    this       Lscala/actors/remote/DelegateActor$$anonfun$act$1$$anonfun$apply$1;
   0      6      1    v1       I


public int apply$mcII$sp(int);
  Signature: (I)I
  Code:
   Stack=2, Locals=2, Args_size=2
	aload_0
	iload_1
	invokestatic	Method scala/Function1$class.apply$mcII$sp:(Lscala/Function1;I)I
	ireturn
  Labels:
  LocalVariableTable: 
   Start  Length  Slot  Name   Signature
   0      6      0    this       Lscala/actors/remote/DelegateActor$$anonfun$act$1$$anonfun$apply$1;
   0      6      1    v1       I


public long apply$mcLI$sp(int);
  Signature: (I)J
  Code:
   Stack=2, Locals=2, Args_size=2
	aload_0
	iload_1
	invokestatic	Method scala/Function1$class.apply$mcLI$sp:(Lscala/Function1;I)J
	lreturn
  Labels:
  LocalVariableTable: 
   Start  Length  Slot  Name   Signature
   0      6      0    this       Lscala/actors/remote/DelegateActor$$anonfun$act$1$$anonfun$apply$1;
   0      6      1    v1       I


public double apply$mcDI$sp(int);
  Signature: (I)D
  Code:
   Stack=2, Locals=2, Args_size=2
	aload_0
	iload_1
	invokestatic	Method scala/Function1$class.apply$mcDI$sp:(Lscala/Function1;I)D
	dreturn
  Labels:
  LocalVariableTable: 
   Start  Length  Slot  Name   Signature
   0      6      0    this       Lscala/actors/remote/DelegateActor$$anonfun$act$1$$anonfun$apply$1;
   0      6      1    v1       I


public void apply$mcVL$sp(long);
  Signature: (J)V
  Code:
   Stack=3, Locals=3, Args_size=2
	aload_0
	lload_1
	invokestatic	Method scala/Function1$class.apply$mcVL$sp:(Lscala/Function1;J)V
	return
  Labels:
  LocalVariableTable: 
   Start  Length  Slot  Name   Signature
   0      6      0    this       Lscala/actors/remote/DelegateActor$$anonfun$act$1$$anonfun$apply$1;
   0      6      1    v1       J


public boolean apply$mcZL$sp(long);
  Signature: (J)Z
  Code:
   Stack=3, Locals=3, Args_size=2
	aload_0
	lload_1
	invokestatic	Method scala/Function1$class.apply$mcZL$sp:(Lscala/Function1;J)Z
	ireturn
  Labels:
  LocalVariableTable: 
   Start  Length  Slot  Name   Signature
   0      6      0    this       Lscala/actors/remote/DelegateActor$$anonfun$act$1$$anonfun$apply$1;
   0      6      1    v1       J


public int apply$mcIL$sp(long);
  Signature: (J)I
  Code:
   Stack=3, Locals=3, Args_size=2
	aload_0
	lload_1
	invokestatic	Method scala/Function1$class.apply$mcIL$sp:(Lscala/Function1;J)I
	ireturn
  Labels:
  LocalVariableTable: 
   Start  Length  Slot  Name   Signature
   0      6      0    this       Lscala/actors/remote/DelegateActor$$anonfun$act$1$$anonfun$apply$1;
   0      6      1    v1       J


public long apply$mcLL$sp(long);
  Signature: (J)J
  Code:
   Stack=3, Locals=3, Args_size=2
	aload_0
	lload_1
	invokestatic	Method scala/Function1$class.apply$mcLL$sp:(Lscala/Function1;J)J
	lreturn
  Labels:
  LocalVariableTable: 
   Start  Length  Slot  Name   Signature
   0      6      0    this       Lscala/actors/remote/DelegateActor$$anonfun$act$1$$anonfun$apply$1;
   0      6      1    v1       J


public double apply$mcDL$sp(long);
  Signature: (J)D
  Code:
   Stack=3, Locals=3, Args_size=2
	aload_0
	lload_1
	invokestatic	Method scala/Function1$class.apply$mcDL$sp:(Lscala/Function1;J)D
	dreturn
  Labels:
  LocalVariableTable: 
   Start  Length  Slot  Name   Signature
   0      6      0    this       Lscala/actors/remote/DelegateActor$$anonfun$act$1$$anonfun$apply$1;
   0      6      1    v1       J


public void apply$mcVD$sp(double);
  Signature: (D)V
  Code:
   Stack=3, Locals=3, Args_size=2
	aload_0
	dload_1
	invokestatic	Method scala/Function1$class.apply$mcVD$sp:(Lscala/Function1;D)V
	return
  Labels:
  LocalVariableTable: 
   Start  Length  Slot  Name   Signature
   0      6      0    this       Lscala/actors/remote/DelegateActor$$anonfun$act$1$$anonfun$apply$1;
   0      6      1    v1       D


public boolean apply$mcZD$sp(double);
  Signature: (D)Z
  Code:
   Stack=3, Locals=3, Args_size=2
	aload_0
	dload_1
	invokestatic	Method scala/Function1$class.apply$mcZD$sp:(Lscala/Function1;D)Z
	ireturn
  Labels:
  LocalVariableTable: 
   Start  Length  Slot  Name   Signature
   0      6      0    this       Lscala/actors/remote/DelegateActor$$anonfun$act$1$$anonfun$apply$1;
   0      6      1    v1       D


public int apply$mcID$sp(double);
  Signature: (D)I
  Code:
   Stack=3, Locals=3, Args_size=2
	aload_0
	dload_1
	invokestatic	Method scala/Function1$class.apply$mcID$sp:(Lscala/Function1;D)I
	ireturn
  Labels:
  LocalVariableTable: 
   Start  Length  Slot  Name   Signature
   0      6      0    this       Lscala/actors/remote/DelegateActor$$anonfun$act$1$$anonfun$apply$1;
   0      6      1    v1       D


public long apply$mcLD$sp(double);
  Signature: (D)J
  Code:
   Stack=3, Locals=3, Args_size=2
	aload_0
	dload_1
	invokestatic	Method scala/Function1$class.apply$mcLD$sp:(Lscala/Function1;D)J
	lreturn
  Labels:
  LocalVariableTable: 
   Start  Length  Slot  Name   Signature
   0      6      0    this       Lscala/actors/remote/DelegateActor$$anonfun$act$1$$anonfun$apply$1;
   0      6      1    v1       D


public double apply$mcDD$sp(double);
  Signature: (D)D
  Code:
   Stack=3, Locals=3, Args_size=2
	aload_0
	dload_1
	invokestatic	Method scala/Function1$class.apply$mcDD$sp:(Lscala/Function1;D)D
	dreturn
  Labels:
  LocalVariableTable: 
   Start  Length  Slot  Name   Signature
   0      6      0    this       Lscala/actors/remote/DelegateActor$$anonfun$act$1$$anonfun$apply$1;
   0      6      1    v1       D


public java.lang.String toString();
  Signature: ()Ljava/lang/String;
  Code:
   Stack=1, Locals=1, Args_size=1
	aload_0
	invokestatic	Method scala/Function1$class.toString:(Lscala/Function1;)Ljava/lang/String;
	areturn
  Labels:

public scala.Function1 compose(scala.Function1);
  Signature: (Lscala/Function1;)Lscala/Function1;
  Code:
   Stack=2, Locals=2, Args_size=2
	aload_0
	aload_1
	invokestatic	Method scala/Function1$class.compose:(Lscala/Function1;Lscala/Function1;)Lscala/Function1;
	areturn
  Labels:
  LocalVariableTable: 
   Start  Length  Slot  Name   Signature
   0      6      0    this       Lscala/actors/remote/DelegateActor$$anonfun$act$1$$anonfun$apply$1;
   0      6      1    g       Lscala/Function1;


public scala.Function1 compose$mcVI$sp(scala.Function1);
  Signature: (Lscala/Function1;)Lscala/Function1;
  Code:
   Stack=2, Locals=2, Args_size=2
	aload_0
	aload_1
	invokestatic	Method scala/Function1$class.compose$mcVI$sp:(Lscala/Function1;Lscala/Function1;)Lscala/Function1;
	areturn
  Labels:
  LocalVariableTable: 
   Start  Length  Slot  Name   Signature
   0      6      0    this       Lscala/actors/remote/DelegateActor$$anonfun$act$1$$anonfun$apply$1;
   0      6      1    g       Lscala/Function1;


public scala.Function1 compose$mcZI$sp(scala.Function1);
  Signature: (Lscala/Function1;)Lscala/Function1;
  Code:
   Stack=2, Locals=2, Args_size=2
	aload_0
	aload_1
	invokestatic	Method scala/Function1$class.compose$mcZI$sp:(Lscala/Function1;Lscala/Function1;)Lscala/Function1;
	areturn
  Labels:
  LocalVariableTable: 
   Start  Length  Slot  Name   Signature
   0      6      0    this       Lscala/actors/remote/DelegateActor$$anonfun$act$1$$anonfun$apply$1;
   0      6      1    g       Lscala/Function1;


public scala.Function1 compose$mcII$sp(scala.Function1);
  Signature: (Lscala/Function1;)Lscala/Function1;
  Code:
   Stack=2, Locals=2, Args_size=2
	aload_0
	aload_1
	invokestatic	Method scala/Function1$class.compose$mcII$sp:(Lscala/Function1;Lscala/Function1;)Lscala/Function1;
	areturn
  Labels:
  LocalVariableTable: 
   Start  Length  Slot  Name   Signature
   0      6      0    this       Lscala/actors/remote/DelegateActor$$anonfun$act$1$$anonfun$apply$1;
   0      6      1    g       Lscala/Function1;


public scala.Function1 compose$mcLI$sp(scala.Function1);
  Signature: (Lscala/Function1;)Lscala/Function1;
  Code:
   Stack=2, Locals=2, Args_size=2
	aload_0
	aload_1
	invokestatic	Method scala/Function1$class.compose$mcLI$sp:(Lscala/Function1;Lscala/Function1;)Lscala/Function1;
	areturn
  Labels:
  LocalVariableTable: 
   Start  Length  Slot  Name   Signature
   0      6      0    this       Lscala/actors/remote/DelegateActor$$anonfun$act$1$$anonfun$apply$1;
   0      6      1    g       Lscala/Function1;


public scala.Function1 compose$mcDI$sp(scala.Function1);
  Signature: (Lscala/Function1;)Lscala/Function1;
  Code:
   Stack=2, Locals=2, Args_size=2
	aload_0
	aload_1
	invokestatic	Method scala/Function1$class.compose$mcDI$sp:(Lscala/Function1;Lscala/Function1;)Lscala/Function1;
	areturn
  Labels:
  LocalVariableTable: 
   Start  Length  Slot  Name   Signature
   0      6      0    this       Lscala/actors/remote/DelegateActor$$anonfun$act$1$$anonfun$apply$1;
   0      6      1    g       Lscala/Function1;


public scala.Function1 compose$mcVL$sp(scala.Function1);
  Signature: (Lscala/Function1;)Lscala/Function1;
  Code:
   Stack=2, Locals=2, Args_size=2
	aload_0
	aload_1
	invokestatic	Method scala/Function1$class.compose$mcVL$sp:(Lscala/Function1;Lscala/Function1;)Lscala/Function1;
	areturn
  Labels:
  LocalVariableTable: 
   Start  Length  Slot  Name   Signature
   0      6      0    this       Lscala/actors/remote/DelegateActor$$anonfun$act$1$$anonfun$apply$1;
   0      6      1    g       Lscala/Function1;


public scala.Function1 compose$mcZL$sp(scala.Function1);
  Signature: (Lscala/Function1;)Lscala/Function1;
  Code:
   Stack=2, Locals=2, Args_size=2
	aload_0
	aload_1
	invokestatic	Method scala/Function1$class.compose$mcZL$sp:(Lscala/Function1;Lscala/Function1;)Lscala/Function1;
	areturn
  Labels:
  LocalVariableTable: 
   Start  Length  Slot  Name   Signature
   0      6      0    this       Lscala/actors/remote/DelegateActor$$anonfun$act$1$$anonfun$apply$1;
   0      6      1    g       Lscala/Function1;


public scala.Function1 compose$mcIL$sp(scala.Function1);
  Signature: (Lscala/Function1;)Lscala/Function1;
  Code:
   Stack=2, Locals=2, Args_size=2
	aload_0
	aload_1
	invokestatic	Method scala/Function1$class.compose$mcIL$sp:(Lscala/Function1;Lscala/Function1;)Lscala/Function1;
	areturn
  Labels:
  LocalVariableTable: 
   Start  Length  Slot  Name   Signature
   0      6      0    this       Lscala/actors/remote/DelegateActor$$anonfun$act$1$$anonfun$apply$1;
   0      6      1    g       Lscala/Function1;


public scala.Function1 compose$mcLL$sp(scala.Function1);
  Signature: (Lscala/Function1;)Lscala/Function1;
  Code:
   Stack=2, Locals=2, Args_size=2
	aload_0
	aload_1
	invokestatic	Method scala/Function1$class.compose$mcLL$sp:(Lscala/Function1;Lscala/Function1;)Lscala/Function1;
	areturn
  Labels:
  LocalVariableTable: 
   Start  Length  Slot  Name   Signature
   0      6      0    this       Lscala/actors/remote/DelegateActor$$anonfun$act$1$$anonfun$apply$1;
   0      6      1    g       Lscala/Function1;


public scala.Function1 compose$mcDL$sp(scala.Function1);
  Signature: (Lscala/Function1;)Lscala/Function1;
  Code:
   Stack=2, Locals=2, Args_size=2
	aload_0
	aload_1
	invokestatic	Method scala/Function1$class.compose$mcDL$sp:(Lscala/Function1;Lscala/Function1;)Lscala/Function1;
	areturn
  Labels:
  LocalVariableTable: 
   Start  Length  Slot  Name   Signature
   0      6      0    this       Lscala/actors/remote/DelegateActor$$anonfun$act$1$$anonfun$apply$1;
   0      6      1    g       Lscala/Function1;


public scala.Function1 compose$mcVD$sp(scala.Function1);
  Signature: (Lscala/Function1;)Lscala/Function1;
  Code:
   Stack=2, Locals=2, Args_size=2
	aload_0
	aload_1
	invokestatic	Method scala/Function1$class.compose$mcVD$sp:(Lscala/Function1;Lscala/Function1;)Lscala/Function1;
	areturn
  Labels:
  LocalVariableTable: 
   Start  Length  Slot  Name   Signature
   0      6      0    this       Lscala/actors/remote/DelegateActor$$anonfun$act$1$$anonfun$apply$1;
   0      6      1    g       Lscala/Function1;


public scala.Function1 compose$mcZD$sp(scala.Function1);
  Signature: (Lscala/Function1;)Lscala/Function1;
  Code:
   Stack=2, Locals=2, Args_size=2
	aload_0
	aload_1
	invokestatic	Method scala/Function1$class.compose$mcZD$sp:(Lscala/Function1;Lscala/Function1;)Lscala/Function1;
	areturn
  Labels:
  LocalVariableTable: 
   Start  Length  Slot  Name   Signature
   0      6      0    this       Lscala/actors/remote/DelegateActor$$anonfun$act$1$$anonfun$apply$1;
   0      6      1    g       Lscala/Function1;


public scala.Function1 compose$mcID$sp(scala.Function1);
  Signature: (Lscala/Function1;)Lscala/Function1;
  Code:
   Stack=2, Locals=2, Args_size=2
	aload_0
	aload_1
	invokestatic	Method scala/Function1$class.compose$mcID$sp:(Lscala/Function1;Lscala/Function1;)Lscala/Function1;
	areturn
  Labels:
  LocalVariableTable: 
   Start  Length  Slot  Name   Signature
   0      6      0    this       Lscala/actors/remote/DelegateActor$$anonfun$act$1$$anonfun$apply$1;
   0      6      1    g       Lscala/Function1;


public scala.Function1 compose$mcLD$sp(scala.Function1);
  Signature: (Lscala/Function1;)Lscala/Function1;
  Code:
   Stack=2, Locals=2, Args_size=2
	aload_0
	aload_1
	invokestatic	Method scala/Function1$class.compose$mcLD$sp:(Lscala/Function1;Lscala/Function1;)Lscala/Function1;
	areturn
  Labels:
  LocalVariableTable: 
   Start  Length  Slot  Name   Signature
   0      6      0    this       Lscala/actors/remote/DelegateActor$$anonfun$act$1$$anonfun$apply$1;
   0      6      1    g       Lscala/Function1;


public scala.Function1 compose$mcDD$sp(scala.Function1);
  Signature: (Lscala/Function1;)Lscala/Function1;
  Code:
   Stack=2, Locals=2, Args_size=2
	aload_0
	aload_1
	invokestatic	Method scala/Function1$class.compose$mcDD$sp:(Lscala/Function1;Lscala/Function1;)Lscala/Function1;
	areturn
  Labels:
  LocalVariableTable: 
   Start  Length  Slot  Name   Signature
   0      6      0    this       Lscala/actors/remote/DelegateActor$$anonfun$act$1$$anonfun$apply$1;
   0      6      1    g       Lscala/Function1;


public scala.Function1 andThen$mcVI$sp(scala.Function1);
  Signature: (Lscala/Function1;)Lscala/Function1;
  Code:
   Stack=2, Locals=2, Args_size=2
	aload_0
	aload_1
	invokestatic	Method scala/Function1$class.andThen$mcVI$sp:(Lscala/Function1;Lscala/Function1;)Lscala/Function1;
	areturn
  Labels:
  LocalVariableTable: 
   Start  Length  Slot  Name   Signature
   0      6      0    this       Lscala/actors/remote/DelegateActor$$anonfun$act$1$$anonfun$apply$1;
   0      6      1    g       Lscala/Function1;


public scala.Function1 andThen$mcZI$sp(scala.Function1);
  Signature: (Lscala/Function1;)Lscala/Function1;
  Code:
   Stack=2, Locals=2, Args_size=2
	aload_0
	aload_1
	invokestatic	Method scala/Function1$class.andThen$mcZI$sp:(Lscala/Function1;Lscala/Function1;)Lscala/Function1;
	areturn
  Labels:
  LocalVariableTable: 
   Start  Length  Slot  Name   Signature
   0      6      0    this       Lscala/actors/remote/DelegateActor$$anonfun$act$1$$anonfun$apply$1;
   0      6      1    g       Lscala/Function1;


public scala.Function1 andThen$mcII$sp(scala.Function1);
  Signature: (Lscala/Function1;)Lscala/Function1;
  Code:
   Stack=2, Locals=2, Args_size=2
	aload_0
	aload_1
	invokestatic	Method scala/Function1$class.andThen$mcII$sp:(Lscala/Function1;Lscala/Function1;)Lscala/Function1;
	areturn
  Labels:
  LocalVariableTable: 
   Start  Length  Slot  Name   Signature
   0      6      0    this       Lscala/actors/remote/DelegateActor$$anonfun$act$1$$anonfun$apply$1;
   0      6      1    g       Lscala/Function1;


public scala.Function1 andThen$mcLI$sp(scala.Function1);
  Signature: (Lscala/Function1;)Lscala/Function1;
  Code:
   Stack=2, Locals=2, Args_size=2
	aload_0
	aload_1
	invokestatic	Method scala/Function1$class.andThen$mcLI$sp:(Lscala/Function1;Lscala/Function1;)Lscala/Function1;
	areturn
  Labels:
  LocalVariableTable: 
   Start  Length  Slot  Name   Signature
   0      6      0    this       Lscala/actors/remote/DelegateActor$$anonfun$act$1$$anonfun$apply$1;
   0      6      1    g       Lscala/Function1;


public scala.Function1 andThen$mcDI$sp(scala.Function1);
  Signature: (Lscala/Function1;)Lscala/Function1;
  Code:
   Stack=2, Locals=2, Args_size=2
	aload_0
	aload_1
	invokestatic	Method scala/Function1$class.andThen$mcDI$sp:(Lscala/Function1;Lscala/Function1;)Lscala/Function1;
	areturn
  Labels:
  LocalVariableTable: 
   Start  Length  Slot  Name   Signature
   0      6      0    this       Lscala/actors/remote/DelegateActor$$anonfun$act$1$$anonfun$apply$1;
   0      6      1    g       Lscala/Function1;


public scala.Function1 andThen$mcVL$sp(scala.Function1);
  Signature: (Lscala/Function1;)Lscala/Function1;
  Code:
   Stack=2, Locals=2, Args_size=2
	aload_0
	aload_1
	invokestatic	Method scala/Function1$class.andThen$mcVL$sp:(Lscala/Function1;Lscala/Function1;)Lscala/Function1;
	areturn
  Labels:
  LocalVariableTable: 
   Start  Length  Slot  Name   Signature
   0      6      0    this       Lscala/actors/remote/DelegateActor$$anonfun$act$1$$anonfun$apply$1;
   0      6      1    g       Lscala/Function1;


public scala.Function1 andThen$mcZL$sp(scala.Function1);
  Signature: (Lscala/Function1;)Lscala/Function1;
  Code:
   Stack=2, Locals=2, Args_size=2
	aload_0
	aload_1
	invokestatic	Method scala/Function1$class.andThen$mcZL$sp:(Lscala/Function1;Lscala/Function1;)Lscala/Function1;
	areturn
  Labels:
  LocalVariableTable: 
   Start  Length  Slot  Name   Signature
   0      6      0    this       Lscala/actors/remote/DelegateActor$$anonfun$act$1$$anonfun$apply$1;
   0      6      1    g       Lscala/Function1;


public scala.Function1 andThen$mcIL$sp(scala.Function1);
  Signature: (Lscala/Function1;)Lscala/Function1;
  Code:
   Stack=2, Locals=2, Args_size=2
	aload_0
	aload_1
	invokestatic	Method scala/Function1$class.andThen$mcIL$sp:(Lscala/Function1;Lscala/Function1;)Lscala/Function1;
	areturn
  Labels:
  LocalVariableTable: 
   Start  Length  Slot  Name   Signature
   0      6      0    this       Lscala/actors/remote/DelegateActor$$anonfun$act$1$$anonfun$apply$1;
   0      6      1    g       Lscala/Function1;


public scala.Function1 andThen$mcLL$sp(scala.Function1);
  Signature: (Lscala/Function1;)Lscala/Function1;
  Code:
   Stack=2, Locals=2, Args_size=2
	aload_0
	aload_1
	invokestatic	Method scala/Function1$class.andThen$mcLL$sp:(Lscala/Function1;Lscala/Function1;)Lscala/Function1;
	areturn
  Labels:
  LocalVariableTable: 
   Start  Length  Slot  Name   Signature
   0      6      0    this       Lscala/actors/remote/DelegateActor$$anonfun$act$1$$anonfun$apply$1;
   0      6      1    g       Lscala/Function1;


public scala.Function1 andThen$mcDL$sp(scala.Function1);
  Signature: (Lscala/Function1;)Lscala/Function1;
  Code:
   Stack=2, Locals=2, Args_size=2
	aload_0
	aload_1
	invokestatic	Method scala/Function1$class.andThen$mcDL$sp:(Lscala/Function1;Lscala/Function1;)Lscala/Function1;
	areturn
  Labels:
  LocalVariableTable: 
   Start  Length  Slot  Name   Signature
   0      6      0    this       Lscala/actors/remote/DelegateActor$$anonfun$act$1$$anonfun$apply$1;
   0      6      1    g       Lscala/Function1;


public scala.Function1 andThen$mcVD$sp(scala.Function1);
  Signature: (Lscala/Function1;)Lscala/Function1;
  Code:
   Stack=2, Locals=2, Args_size=2
	aload_0
	aload_1
	invokestatic	Method scala/Function1$class.andThen$mcVD$sp:(Lscala/Function1;Lscala/Function1;)Lscala/Function1;
	areturn
  Labels:
  LocalVariableTable: 
   Start  Length  Slot  Name   Signature
   0      6      0    this       Lscala/actors/remote/DelegateActor$$anonfun$act$1$$anonfun$apply$1;
   0      6      1    g       Lscala/Function1;


public scala.Function1 andThen$mcZD$sp(scala.Function1);
  Signature: (Lscala/Function1;)Lscala/Function1;
  Code:
   Stack=2, Locals=2, Args_size=2
	aload_0
	aload_1
	invokestatic	Method scala/Function1$class.andThen$mcZD$sp:(Lscala/Function1;Lscala/Function1;)Lscala/Function1;
	areturn
  Labels:
  LocalVariableTable: 
   Start  Length  Slot  Name   Signature
   0      6      0    this       Lscala/actors/remote/DelegateActor$$anonfun$act$1$$anonfun$apply$1;
   0      6      1    g       Lscala/Function1;


public scala.Function1 andThen$mcID$sp(scala.Function1);
  Signature: (Lscala/Function1;)Lscala/Function1;
  Code:
   Stack=2, Locals=2, Args_size=2
	aload_0
	aload_1
	invokestatic	Method scala/Function1$class.andThen$mcID$sp:(Lscala/Function1;Lscala/Function1;)Lscala/Function1;
	areturn
  Labels:
  LocalVariableTable: 
   Start  Length  Slot  Name   Signature
   0      6      0    this       Lscala/actors/remote/DelegateActor$$anonfun$act$1$$anonfun$apply$1;
   0      6      1    g       Lscala/Function1;


public scala.Function1 andThen$mcLD$sp(scala.Function1);
  Signature: (Lscala/Function1;)Lscala/Function1;
  Code:
   Stack=2, Locals=2, Args_size=2
	aload_0
	aload_1
	invokestatic	Method scala/Function1$class.andThen$mcLD$sp:(Lscala/Function1;Lscala/Function1;)Lscala/Function1;
	areturn
  Labels:
  LocalVariableTable: 
   Start  Length  Slot  Name   Signature
   0      6      0    this       Lscala/actors/remote/DelegateActor$$anonfun$act$1$$anonfun$apply$1;
   0      6      1    g       Lscala/Function1;


public scala.Function1 andThen$mcDD$sp(scala.Function1);
  Signature: (Lscala/Function1;)Lscala/Function1;
  Code:
   Stack=2, Locals=2, Args_size=2
	aload_0
	aload_1
	invokestatic	Method scala/Function1$class.andThen$mcDD$sp:(Lscala/Function1;Lscala/Function1;)Lscala/Function1;
	areturn
  Labels:
  LocalVariableTable: 
   Start  Length  Slot  Name   Signature
   0      6      0    this       Lscala/actors/remote/DelegateActor$$anonfun$act$1$$anonfun$apply$1;
   0      6      1    g       Lscala/Function1;


public final void apply(java.lang.Object);
  Signature: (Ljava/lang/Object;)V
  Code:
   Stack=6, Locals=30, Args_size=2
	aload_1
	instanceof	class scala/actors/remote/Apply0
	ifeq	l1 // aload_1
	aload_0
	getfield	Field $outer:Lscala/actors/remote/DelegateActor$$anonfun$act$1;
	astore_2
	aload_2
	getfield	Field scala/actors/remote/DelegateActor$$anonfun$act$1.$outer:Lscala/actors/remote/DelegateActor;
	getfield	Field scala/actors/remote/DelegateActor.scala$actors$remote$DelegateActor$$kernel:Lscala/actors/remote/NetKernel;
	aload_0
	getfield	Field $outer:Lscala/actors/remote/DelegateActor$$anonfun$act$1;
	astore_3
	aload_3
	getfield	Field scala/actors/remote/DelegateActor$$anonfun$act$1.$outer:Lscala/actors/remote/DelegateActor;
	getfield	Field scala/actors/remote/DelegateActor.scala$actors$remote$DelegateActor$$node:Lscala/actors/remote/Node;
	aload_0
	getfield	Field $outer:Lscala/actors/remote/DelegateActor$$anonfun$act$1;
	astore	4
	aload	4
	getfield	Field scala/actors/remote/DelegateActor$$anonfun$act$1.$outer:Lscala/actors/remote/DelegateActor;
	getfield	Field scala/actors/remote/DelegateActor.scala$actors$remote$DelegateActor$$name:Lscala/Symbol;
	aload_0
	getfield	Field $outer:Lscala/actors/remote/DelegateActor$$anonfun$act$1;
	astore	5
	aload	5
	getfield	Field scala/actors/remote/DelegateActor$$anonfun$act$1.$outer:Lscala/actors/remote/DelegateActor;
	aload_0
	getfield	Field $outer:Lscala/actors/remote/DelegateActor$$anonfun$act$1;
	astore	6
	aload	6
	getfield	Field scala/actors/remote/DelegateActor$$anonfun$act$1.$outer:Lscala/actors/remote/DelegateActor;
	invokevirtual	Method scala/actors/remote/DelegateActor.protected$sender:(Lscala/actors/remote/DelegateActor;)Lscala/actors/OutputChannel;
	aload_1
	checkcast	class scala/actors/remote/Apply0
	invokevirtual	Method scala/actors/remote/Apply0.rfun:()Lscala/Function2;
	invokevirtual	Method scala/actors/remote/NetKernel.remoteApply:(Lscala/actors/remote/Node;Lscala/Symbol;Lscala/actors/OutputChannel;Lscala/Function2;)V
	goto	l2 // return
l1	aload_1
	instanceof	class scala/actors/remote/LocalApply0
	ifeq	l3 // aload_1
	aload_1
	checkcast	class scala/actors/remote/LocalApply0
	astore	7
	aload	7
	invokevirtual	Method scala/actors/remote/LocalApply0.rfun:()Lscala/Function2;
	aload	7
	invokevirtual	Method scala/actors/remote/LocalApply0.a:()Lscala/actors/AbstractActor;
	aload_0
	getfield	Field $outer:Lscala/actors/remote/DelegateActor$$anonfun$act$1;
	astore	8
	aload	8
	getfield	Field scala/actors/remote/DelegateActor$$anonfun$act$1.$outer:Lscala/actors/remote/DelegateActor;
	getfield	Field scala/actors/remote/DelegateActor.scala$actors$remote$DelegateActor$$creator:Lscala/actors/remote/Proxy;
	invokeinterface	InterfaceMethod scala/Function2.apply:(Ljava/lang/Object;Ljava/lang/Object;)Ljava/lang/Object;
	pop
	goto	l2 // return
l3	aload_1
	instanceof	class scala/actors/remote/SendTo
	ifeq	l4 // getstatic
	aload_1
	checkcast	class scala/actors/remote/SendTo
	astore	9
	aload	9
	invokevirtual	Method scala/actors/remote/SendTo.a:()Lscala/actors/OutputChannel;
	astore	15
	aload	9
	invokevirtual	Method scala/actors/remote/SendTo.msg:()Ljava/lang/Object;
	astore	19
	aload	9
	invokevirtual	Method scala/actors/remote/SendTo.session:()Lscala/Symbol;
	astore	18
	aload	18
	invokevirtual	Method scala/Symbol.name:()Ljava/lang/String;
	ldc	String nosession
	astore	10
	dup
	ifnonnull	l5 // aload
	pop
	aload	10
	ifnull	l6 // aload
	goto	l7 // aload_0
l5	aload	10
	invokevirtual	Method java/lang/Object.equals:(Ljava/lang/Object;)Z
	ifeq	l7 // aload_0
l6	aload	15
	aload	19
	aload_0
	getfield	Field $outer:Lscala/actors/remote/DelegateActor$$anonfun$act$1;
	astore	11
	aload	11
	getfield	Field scala/actors/remote/DelegateActor$$anonfun$act$1.$outer:Lscala/actors/remote/DelegateActor;
	invokeinterface	InterfaceMethod scala/actors/OutputChannel.send:(Ljava/lang/Object;Lscala/actors/OutputChannel;)V
	goto	l2 // return
l7	aload_0
	getfield	Field $outer:Lscala/actors/remote/DelegateActor$$anonfun$act$1;
	astore	12
	aload	12
	getfield	Field scala/actors/remote/DelegateActor$$anonfun$act$1.$outer:Lscala/actors/remote/DelegateActor;
	invokevirtual	Method scala/actors/remote/DelegateActor.channelMap:()Lscala/collection/mutable/HashMap;
	aload	18
	invokevirtual	Method scala/collection/mutable/HashMap.get:(Ljava/lang/Object;)Lscala/Option;
	astore	20
	getstatic	Field scala/None$.MODULE$:Lscala/None$;
	dup
	ifnonnull	l8 // aload
	pop
	aload	20
	ifnull	l9 // new
	goto	l10 // aload
l8	aload	20
	invokevirtual	Method java/lang/Object.equals:(Ljava/lang/Object;)Z
	ifeq	l10 // aload
l9	new	class scala/actors/Channel
	dup
	aload_0
	getfield	Field $outer:Lscala/actors/remote/DelegateActor$$anonfun$act$1;
	astore	13
	aload	13
	getfield	Field scala/actors/remote/DelegateActor$$anonfun$act$1.$outer:Lscala/actors/remote/DelegateActor;
	invokespecial	Method scala/actors/Channel."<init>":(Lscala/actors/Actor;)V
	astore	16
	aload_0
	getfield	Field $outer:Lscala/actors/remote/DelegateActor$$anonfun$act$1;
	astore	14
	aload	14
	getfield	Field scala/actors/remote/DelegateActor$$anonfun$act$1.$outer:Lscala/actors/remote/DelegateActor;
	invokevirtual	Method scala/actors/remote/DelegateActor.sessionMap:()Lscala/collection/mutable/HashMap;
	getstatic	Field scala/Predef$Pair$.MODULE$:Lscala/Predef$Pair$;
	aload	16
	aload	18
	invokevirtual	Method scala/Predef$Pair$.apply:(Ljava/lang/Object;Ljava/lang/Object;)Lscala/Tuple2;
	invokevirtual	Method scala/collection/mutable/HashMap.$plus$eq:(Lscala/Tuple2;)Lscala/collection/mutable/HashMap;
	pop
	aload	15
	aload	19
	aload	16
	invokeinterface	InterfaceMethod scala/actors/OutputChannel.send:(Ljava/lang/Object;Lscala/actors/OutputChannel;)V
	goto	l2 // return
l10	aload	20
	instanceof	class scala/Some
	ifeq	l11 // new
	aload_0
	getfield	Field $outer:Lscala/actors/remote/DelegateActor$$anonfun$act$1;
	astore	17
	aload	17
	getfield	Field scala/actors/remote/DelegateActor$$anonfun$act$1.$outer:Lscala/actors/remote/DelegateActor;
	invokevirtual	Method scala/actors/remote/DelegateActor.channelMap:()Lscala/collection/mutable/HashMap;
	aload	18
	invokevirtual	Method scala/collection/mutable/HashMap.$minus$eq:(Ljava/lang/Object;)Lscala/collection/mutable/HashMap;
	pop
	aload	20
	checkcast	class scala/Some
	invokevirtual	Method scala/Some.x:()Ljava/lang/Object;
	checkcast	class scala/actors/OutputChannel
	aload	19
	invokeinterface	InterfaceMethod scala/actors/OutputChannel.$bang:(Ljava/lang/Object;)V
	goto	l2 // return
l11	new	class scala/MatchError
	dup
	aload	20
	invokespecial	Method scala/MatchError."<init>":(Ljava/lang/Object;)V
	athrow
l4	getstatic	Field scala/actors/remote/Terminate$.MODULE$:Lscala/actors/remote/Terminate$;
	dup
	ifnonnull	l12 // aload_1
	pop
	aload_1
	ifnull	l13 // aload_1
	goto	l14 // aload_1
l12	aload_1
	invokevirtual	Method java/lang/Object.equals:(Ljava/lang/Object;)Z
	ifeq	l14 // aload_1
l13	aload_1
	instanceof	class scala/actors/remote/Terminate$
	ifeq	l14 // aload_1
	aload_0
	getfield	Field $outer:Lscala/actors/remote/DelegateActor$$anonfun$act$1;
	astore	21
	aload	21
	getfield	Field scala/actors/remote/DelegateActor$$anonfun$act$1.$outer:Lscala/actors/remote/DelegateActor;
	aload_0
	getfield	Field $outer:Lscala/actors/remote/DelegateActor$$anonfun$act$1;
	astore	22
	aload	22
	getfield	Field scala/actors/remote/DelegateActor$$anonfun$act$1.$outer:Lscala/actors/remote/DelegateActor;
	invokevirtual	Method scala/actors/remote/DelegateActor.protected$exit:(Lscala/actors/remote/DelegateActor;)Lscala/runtime/Nothing$;
	athrow
l14	aload_1
	instanceof	class scala/actors/$bang
	ifeq	l15 // aload_1
	aload_1
	checkcast	class scala/actors/$bang
	astore	23
	aload	23
	invokevirtual	Method scala/actors/$bang.ch:()Lscala/actors/Channel;
	astore	27
	aload	23
	invokevirtual	Method scala/actors/$bang.msg:()Ljava/lang/Object;
	astore	26
	aload_0
	getfield	Field $outer:Lscala/actors/remote/DelegateActor$$anonfun$act$1;
	astore	24
	aload	24
	getfield	Field scala/actors/remote/DelegateActor$$anonfun$act$1.$outer:Lscala/actors/remote/DelegateActor;
	invokevirtual	Method scala/actors/remote/DelegateActor.sessionMap:()Lscala/collection/mutable/HashMap;
	aload	27
	invokevirtual	Method scala/collection/mutable/HashMap.get:(Ljava/lang/Object;)Lscala/Option;
	astore	28
	aload	28
	instanceof	class scala/Some
	ifeq	l16 // getstatic
	aload_0
	getfield	Field $outer:Lscala/actors/remote/DelegateActor$$anonfun$act$1;
	astore	25
	aload	25
	getfield	Field scala/actors/remote/DelegateActor$$anonfun$act$1.$outer:Lscala/actors/remote/DelegateActor;
	invokevirtual	Method scala/actors/remote/DelegateActor.sessionMap:()Lscala/collection/mutable/HashMap;
	aload	27
	invokevirtual	Method scala/collection/mutable/HashMap.$minus$eq:(Ljava/lang/Object;)Lscala/collection/mutable/HashMap;
	pop
	aload_0
	getfield	Field $outer:Lscala/actors/remote/DelegateActor$$anonfun$act$1;
	invokevirtual	Method scala/actors/remote/DelegateActor$$anonfun$act$1.scala$actors$remote$DelegateActor$$anonfun$$$outer:()Lscala/actors/remote/DelegateActor;
	getfield	Field scala/actors/remote/DelegateActor.scala$actors$remote$DelegateActor$$kernel:Lscala/actors/remote/NetKernel;
	aload_0
	getfield	Field $outer:Lscala/actors/remote/DelegateActor$$anonfun$act$1;
	invokevirtual	Method scala/actors/remote/DelegateActor$$anonfun$act$1.scala$actors$remote$DelegateActor$$anonfun$$$outer:()Lscala/actors/remote/DelegateActor;
	aload_0
	getfield	Field $outer:Lscala/actors/remote/DelegateActor$$anonfun$act$1;
	invokevirtual	Method scala/actors/remote/DelegateActor$$anonfun$act$1.scala$actors$remote$DelegateActor$$anonfun$$$outer:()Lscala/actors/remote/DelegateActor;
	invokevirtual	Method scala/actors/remote/DelegateActor.protected$sender:(Lscala/actors/remote/DelegateActor;)Lscala/actors/OutputChannel;
	aload_0
	getfield	Field $outer:Lscala/actors/remote/DelegateActor$$anonfun$act$1;
	invokevirtual	Method scala/actors/remote/DelegateActor$$anonfun$act$1.scala$actors$remote$DelegateActor$$anonfun$$$outer:()Lscala/actors/remote/DelegateActor;
	getfield	Field scala/actors/remote/DelegateActor.scala$actors$remote$DelegateActor$$node:Lscala/actors/remote/Node;
	aload_0
	getfield	Field $outer:Lscala/actors/remote/DelegateActor$$anonfun$act$1;
	invokevirtual	Method scala/actors/remote/DelegateActor$$anonfun$act$1.scala$actors$remote$DelegateActor$$anonfun$$$outer:()Lscala/actors/remote/DelegateActor;
	getfield	Field scala/actors/remote/DelegateActor.scala$actors$remote$DelegateActor$$name:Lscala/Symbol;
	aload	26
	aload	28
	checkcast	class scala/Some
	invokevirtual	Method scala/Some.x:()Ljava/lang/Object;
	checkcast	class scala/Symbol
	invokevirtual	Method scala/actors/remote/NetKernel.forward:(Lscala/actors/OutputChannel;Lscala/actors/remote/Node;Lscala/Symbol;Ljava/lang/Object;Lscala/Symbol;)V
	goto	l2 // return
l16	getstatic	Field scala/None$.MODULE$:Lscala/None$;
	dup
	ifnonnull	l17 // aload
	pop
	aload	28
	ifnull	l18 // getstatic
	goto	l19 // new
l17	aload	28
	invokevirtual	Method java/lang/Object.equals:(Ljava/lang/Object;)Z
	ifeq	l19 // new
l18	getstatic	Field scala/actors/Debug$.MODULE$:Lscala/actors/Debug$;
	new	class scala/collection/mutable/StringBuilder
	dup
	invokespecial	Method scala/collection/mutable/StringBuilder."<init>":()V
	getstatic	Field scala/Predef$.MODULE$:Lscala/Predef$;
	aload_0
	getfield	Field $outer:Lscala/actors/remote/DelegateActor$$anonfun$act$1;
	invokevirtual	Method scala/actors/remote/DelegateActor$$anonfun$act$1.scala$actors$remote$DelegateActor$$anonfun$$$outer:()Lscala/actors/remote/DelegateActor;
	invokevirtual	Method scala/Predef$.any2stringadd:(Ljava/lang/Object;)Lscala/runtime/StringAdd;
	ldc_w	String : cannot find session for 
	invokevirtual	Method scala/runtime/StringAdd.$plus:(Ljava/lang/String;)Ljava/lang/String;
	invokevirtual	Method scala/collection/mutable/StringBuilder.append:(Ljava/lang/Object;)Lscala/collection/mutable/StringBuilder;
	aload	27
	invokevirtual	Method scala/collection/mutable/StringBuilder.append:(Ljava/lang/Object;)Lscala/collection/mutable/StringBuilder;
	invokevirtual	Method scala/collection/mutable/StringBuilder.toString:()Ljava/lang/String;
	invokevirtual	Method scala/actors/Debug$.info:(Ljava/lang/String;)V
	goto	l2 // return
l19	new	class scala/MatchError
	dup
	aload	28
	invokespecial	Method scala/MatchError."<init>":(Ljava/lang/Object;)V
	athrow
l15	aload_1
	instanceof	class java/lang/Object
	ifeq	l20 // new
	aload_0
	getfield	Field $outer:Lscala/actors/remote/DelegateActor$$anonfun$act$1;
	invokevirtual	Method scala/actors/remote/DelegateActor$$anonfun$act$1.scala$actors$remote$DelegateActor$$anonfun$$$outer:()Lscala/actors/remote/DelegateActor;
	aload_0
	getfield	Field $outer:Lscala/actors/remote/DelegateActor$$anonfun$act$1;
	invokevirtual	Method scala/actors/remote/DelegateActor$$anonfun$act$1.scala$actors$remote$DelegateActor$$anonfun$$$outer:()Lscala/actors/remote/DelegateActor;
	invokevirtual	Method scala/actors/remote/DelegateActor.protected$sender:(Lscala/actors/remote/DelegateActor;)Lscala/actors/OutputChannel;
	invokevirtual	Method java/lang/Object.getClass:()Ljava/lang/Class;
	invokevirtual	Method java/lang/Class.toString:()Ljava/lang/String;
	ldc_w	String Channel
	invokevirtual	Method java/lang/String.contains:(Ljava/lang/CharSequence;)Z
	ifeq	l21 // aload_0
	getstatic	Field scala/actors/remote/FreshNameCreator$.MODULE$:Lscala/actors/remote/FreshNameCreator$;
	new	class scala/collection/mutable/StringBuilder
	dup
	invokespecial	Method scala/collection/mutable/StringBuilder."<init>":()V
	getstatic	Field scala/Predef$.MODULE$:Lscala/Predef$;
	aload_0
	getfield	Field $outer:Lscala/actors/remote/DelegateActor$$anonfun$act$1;
	invokevirtual	Method scala/actors/remote/DelegateActor$$anonfun$act$1.scala$actors$remote$DelegateActor$$anonfun$$$outer:()Lscala/actors/remote/DelegateActor;
	getfield	Field scala/actors/remote/DelegateActor.scala$actors$remote$DelegateActor$$node:Lscala/actors/remote/Node;
	invokevirtual	Method scala/Predef$.any2stringadd:(Ljava/lang/Object;)Lscala/runtime/StringAdd;
	ldc_w	String @
	invokevirtual	Method scala/runtime/StringAdd.$plus:(Ljava/lang/String;)Ljava/lang/String;
	invokevirtual	Method scala/collection/mutable/StringBuilder.append:(Ljava/lang/Object;)Lscala/collection/mutable/StringBuilder;
	aload_0
	getfield	Field $outer:Lscala/actors/remote/DelegateActor$$anonfun$act$1;
	invokevirtual	Method scala/actors/remote/DelegateActor$$anonfun$act$1.scala$actors$remote$DelegateActor$$anonfun$$$outer:()Lscala/actors/remote/DelegateActor;
	getfield	Field scala/actors/remote/DelegateActor.scala$actors$remote$DelegateActor$$name:Lscala/Symbol;
	invokevirtual	Method scala/collection/mutable/StringBuilder.append:(Ljava/lang/Object;)Lscala/collection/mutable/StringBuilder;
	invokevirtual	Method scala/collection/mutable/StringBuilder.toString:()Ljava/lang/String;
	invokevirtual	Method scala/actors/remote/FreshNameCreator$.newName:(Ljava/lang/String;)Lscala/Symbol;
	astore	29
	aload_0
	getfield	Field $outer:Lscala/actors/remote/DelegateActor$$anonfun$act$1;
	invokevirtual	Method scala/actors/remote/DelegateActor$$anonfun$act$1.scala$actors$remote$DelegateActor$$anonfun$$$outer:()Lscala/actors/remote/DelegateActor;
	invokevirtual	Method scala/actors/remote/DelegateActor.channelMap:()Lscala/collection/mutable/HashMap;
	getstatic	Field scala/Predef$Pair$.MODULE$:Lscala/Predef$Pair$;
	aload	29
	aload_0
	getfield	Field $outer:Lscala/actors/remote/DelegateActor$$anonfun$act$1;
	invokevirtual	Method scala/actors/remote/DelegateActor$$anonfun$act$1.scala$actors$remote$DelegateActor$$anonfun$$$outer:()Lscala/actors/remote/DelegateActor;
	aload_0
	getfield	Field $outer:Lscala/actors/remote/DelegateActor$$anonfun$act$1;
	invokevirtual	Method scala/actors/remote/DelegateActor$$anonfun$act$1.scala$actors$remote$DelegateActor$$anonfun$$$outer:()Lscala/actors/remote/DelegateActor;
	invokevirtual	Method scala/actors/remote/DelegateActor.protected$sender:(Lscala/actors/remote/DelegateActor;)Lscala/actors/OutputChannel;
	invokevirtual	Method scala/Predef$Pair$.apply:(Ljava/lang/Object;Ljava/lang/Object;)Lscala/Tuple2;
	invokevirtual	Method scala/collection/mutable/HashMap.$plus$eq:(Lscala/Tuple2;)Lscala/collection/mutable/HashMap;
	pop
	aload_0
	getfield	Field $outer:Lscala/actors/remote/DelegateActor$$anonfun$act$1;
	invokevirtual	Method scala/actors/remote/DelegateActor$$anonfun$act$1.scala$actors$remote$DelegateActor$$anonfun$$$outer:()Lscala/actors/remote/DelegateActor;
	getfield	Field scala/actors/remote/DelegateActor.scala$actors$remote$DelegateActor$$kernel:Lscala/actors/remote/NetKernel;
	aload_0
	getfield	Field $outer:Lscala/actors/remote/DelegateActor$$anonfun$act$1;
	invokevirtual	Method scala/actors/remote/DelegateActor$$anonfun$act$1.scala$actors$remote$DelegateActor$$anonfun$$$outer:()Lscala/actors/remote/DelegateActor;
	aload_0
	getfield	Field $outer:Lscala/actors/remote/DelegateActor$$anonfun$act$1;
	invokevirtual	Method scala/actors/remote/DelegateActor$$anonfun$act$1.scala$actors$remote$DelegateActor$$anonfun$$$outer:()Lscala/actors/remote/DelegateActor;
	invokevirtual	Method scala/actors/remote/DelegateActor.protected$sender:(Lscala/actors/remote/DelegateActor;)Lscala/actors/OutputChannel;
	aload_0
	getfield	Field $outer:Lscala/actors/remote/DelegateActor$$anonfun$act$1;
	invokevirtual	Method scala/actors/remote/DelegateActor$$anonfun$act$1.scala$actors$remote$DelegateActor$$anonfun$$$outer:()Lscala/actors/remote/DelegateActor;
	getfield	Field scala/actors/remote/DelegateActor.scala$actors$remote$DelegateActor$$node:Lscala/actors/remote/Node;
	aload_0
	getfield	Field $outer:Lscala/actors/remote/DelegateActor$$anonfun$act$1;
	invokevirtual	Method scala/actors/remote/DelegateActor$$anonfun$act$1.scala$actors$remote$DelegateActor$$anonfun$$$outer:()Lscala/actors/remote/DelegateActor;
	getfield	Field scala/actors/remote/DelegateActor.scala$actors$remote$DelegateActor$$name:Lscala/Symbol;
	aload_1
	aload	29
	invokevirtual	Method scala/actors/remote/NetKernel.forward:(Lscala/actors/OutputChannel;Lscala/actors/remote/Node;Lscala/Symbol;Ljava/lang/Object;Lscala/Symbol;)V
	goto	l2 // return
l21	aload_0
	getfield	Field $outer:Lscala/actors/remote/DelegateActor$$anonfun$act$1;
	invokevirtual	Method scala/actors/remote/DelegateActor$$anonfun$act$1.scala$actors$remote$DelegateActor$$anonfun$$$outer:()Lscala/actors/remote/DelegateActor;
	getfield	Field scala/actors/remote/DelegateActor.scala$actors$remote$DelegateActor$$kernel:Lscala/actors/remote/NetKernel;
	aload_0
	getfield	Field $outer:Lscala/actors/remote/DelegateActor$$anonfun$act$1;
	invokevirtual	Method scala/actors/remote/DelegateActor$$anonfun$act$1.scala$actors$remote$DelegateActor$$anonfun$$$outer:()Lscala/actors/remote/DelegateActor;
	aload_0
	getfield	Field $outer:Lscala/actors/remote/DelegateActor$$anonfun$act$1;
	invokevirtual	Method scala/actors/remote/DelegateActor$$anonfun$act$1.scala$actors$remote$DelegateActor$$anonfun$$$outer:()Lscala/actors/remote/DelegateActor;
	invokevirtual	Method scala/actors/remote/DelegateActor.protected$sender:(Lscala/actors/remote/DelegateActor;)Lscala/actors/OutputChannel;
	aload_0
	getfield	Field $outer:Lscala/actors/remote/DelegateActor$$anonfun$act$1;
	invokevirtual	Method scala/actors/remote/DelegateActor$$anonfun$act$1.scala$actors$remote$DelegateActor$$anonfun$$$outer:()Lscala/actors/remote/DelegateActor;
	getfield	Field scala/actors/remote/DelegateActor.scala$actors$remote$DelegateActor$$node:Lscala/actors/remote/Node;
	aload_0
	getfield	Field $outer:Lscala/actors/remote/DelegateActor$$anonfun$act$1;
	invokevirtual	Method scala/actors/remote/DelegateActor$$anonfun$act$1.scala$actors$remote$DelegateActor$$anonfun$$$outer:()Lscala/actors/remote/DelegateActor;
	getfield	Field scala/actors/remote/DelegateActor.scala$actors$remote$DelegateActor$$name:Lscala/Symbol;
	aload_1
	getstatic	Field symbol$1:Lscala/Symbol;
	checkcast	class scala/Symbol
	invokevirtual	Method scala/actors/remote/NetKernel.forward:(Lscala/actors/OutputChannel;Lscala/actors/remote/Node;Lscala/Symbol;Ljava/lang/Object;Lscala/Symbol;)V
l2	return
l20	new	class scala/MatchError
	dup
	aload_1
	invokespecial	Method scala/MatchError."<init>":(Ljava/lang/Object;)V
	athrow
  Labels:
   	l1 = 83 // aload_1
   	l3 = 129 // aload_1
   	l5 = 185 // aload
   	l6 = 193 // aload
   	l7 = 216 // aload_0
   	l8 = 253 // aload
   	l9 = 261 // new
   	l10 = 323 // aload
   	l11 = 372 // new
   	l4 = 382 // getstatic
   	l12 = 397 // aload_1
   	l13 = 404 // aload_1
   	l14 = 437 // aload_1
   	l16 = 579 // getstatic
   	l17 = 595 // aload
   	l18 = 603 // getstatic
   	l19 = 649 // new
   	l15 = 659 // aload_1
   	l21 = 849 // aload_0
   	l2 = 906 // return
   	l20 = 907 // new
  LocalVariableTable: 
   Start  Length  Slot  Name   Signature
   0      916      0    this       Lscala/actors/remote/DelegateActor$$anonfun$act$1$$anonfun$apply$1;
   96      30      7    temp16       Lscala/actors/remote/LocalApply0;
   142      240      9    temp19       Lscala/actors/remote/SendTo;
   149      233      15    temp20       Lscala/actors/OutputChannel;
   281      39      16    replyCh       Lscala/actors/Channel;
   163      219      18    temp22       Lscala/Symbol;
   156      226      19    temp21       Ljava/lang/Object;
   237      145      20    temp5       Lscala/Option;
   450      209      23    temp24       Lscala/actors/$bang;
   464      195      26    temp26       Ljava/lang/Object;
   457      202      27    temp25       Lscala/actors/Channel;
   485      174      28    temp9       Lscala/Option;
   754      92      29    fresh       Lscala/Symbol;


public final boolean isDefinedAt(java.lang.Object);
  Signature: (Ljava/lang/Object;)Z
  Code:
   Stack=2, Locals=2, Args_size=2
	aload_1
	instanceof	class scala/actors/remote/Apply0
	ifeq	l1 // aload_1
	iconst_1
	goto	l2 // ireturn
l1	aload_1
	instanceof	class scala/actors/remote/LocalApply0
	ifeq	l3 // aload_1
	iconst_1
	goto	l2 // ireturn
l3	aload_1
	instanceof	class scala/actors/remote/SendTo
	ifeq	l4 // getstatic
	iconst_1
	goto	l2 // ireturn
l4	getstatic	Field scala/actors/remote/Terminate$.MODULE$:Lscala/actors/remote/Terminate$;
	dup
	ifnonnull	l5 // aload_1
	pop
	aload_1
	ifnull	l6 // aload_1
	goto	l7 // aload_1
l5	aload_1
	invokevirtual	Method java/lang/Object.equals:(Ljava/lang/Object;)Z
	ifeq	l7 // aload_1
l6	aload_1
	instanceof	class scala/actors/remote/Terminate$
	ifeq	l7 // aload_1
	iconst_1
	goto	l2 // ireturn
l7	aload_1
	instanceof	class scala/actors/$bang
	ifeq	l8 // aload_1
	iconst_1
	goto	l2 // ireturn
l8	aload_1
	instanceof	class java/lang/Object
l2	ireturn
  Labels:
   	l1 = 11 // aload_1
   	l3 = 22 // aload_1
   	l4 = 33 // getstatic
   	l5 = 48 // aload_1
   	l6 = 55 // aload_1
   	l7 = 66 // aload_1
   	l8 = 77 // aload_1
   	l2 = 81 // ireturn

public scala.Function1 andThen(scala.Function1);
  Signature: (Lscala/Function1;)Lscala/Function1;
  Code:
   Stack=2, Locals=2, Args_size=2
	aload_0
	aload_1
	invokeinterface	InterfaceMethod scala/PartialFunction.andThen:(Lscala/Function1;)Lscala/PartialFunction;
	areturn
  Labels:
  LocalVariableTable: 
   Start  Length  Slot  Name   Signature
   0      8      0    this       Lscala/actors/remote/DelegateActor$$anonfun$act$1$$anonfun$apply$1;
   0      8      1    g       Lscala/Function1;


public final java.lang.Object apply(java.lang.Object);
  Signature: (Ljava/lang/Object;)Ljava/lang/Object;
  Code:
   Stack=2, Locals=2, Args_size=2
	aload_0
	aload_1
	invokevirtual	Method apply:(Ljava/lang/Object;)V
	getstatic	Field scala/runtime/BoxedUnit.UNIT:Lscala/runtime/BoxedUnit;
	areturn
  Labels:
  LocalVariableTable: 
   Start  Length  Slot  Name   Signature
   0      9      0    this       Lscala/actors/remote/DelegateActor$$anonfun$act$1$$anonfun$apply$1;
   0      9      1    v1       Ljava/lang/Object;


public scala.actors.remote.DelegateActor$$anonfun$act$1$$anonfun$apply$1(scala.actors.remote.DelegateActor$$anonfun$act$1);
  Signature: (Lscala/actors/remote/DelegateActor$$anonfun$act$1;)V
  Code:
   Stack=2, Locals=2, Args_size=2
	aload_1
	ifnonnull	l1 // aload_0
	new	class java/lang/NullPointerException
	dup
	invokespecial	Method java/lang/NullPointerException."<init>":()V
	athrow
l1	aload_0
	aload_1
	putfield	Field $outer:Lscala/actors/remote/DelegateActor$$anonfun$act$1;
	aload_0
	invokespecial	Method java/lang/Object."<init>":()V
	aload_0
	invokestatic	Method scala/Function1$class.$init$:(Lscala/Function1;)V
	aload_0
	invokestatic	Method scala/PartialFunction$class.$init$:(Lscala/PartialFunction;)V
	return
  Labels:
   	l1 = 12 // aload_0
  LocalVariableTable: 
   Start  Length  Slot  Name   Signature
   0      30      0    this       Lscala/actors/remote/DelegateActor$$anonfun$act$1$$anonfun$apply$1;
   0      30      1    $outer       Lscala/actors/remote/DelegateActor$$anonfun$act$1;


}

