Compiled from "Proxy.scala"
public class scala.actors.remote.DelegateActor extends java.lang.Object implements scala.actors.Actor,scala.ScalaObject
  SourceFile: "Proxy.scala"
  ScalaSig: length = 0x2DC
   05 00 6C 06 09 01 02 FFFFFF84 FFFFFF80 FFFFFF80 FFFFFF80 00 02 08 02 0D
   44 65 6C 65 67 61 74 65 41 63 74 6F 72 0A 02 03
   04 01 06 72 65 6D 6F 74 65 0A 02 05 06 01 06 61
   63 74 6F 72 73 0A 01 07 01 05 73 63 61 6C 61 13
   04 00 09 11 15 10 02 0A 0F 0D 01 0B 0A 02 0C 0D
   01 04 6C 61 6E 67 0A 01 0E 01 04 6A 61 76 61 09
   02 10 0B 02 06 4F 62 6A 65 63 74 10 02 12 13 0D
   01 04 09 02 14 04 02 05 41 63 74 6F 72 10 02 16
   17 0D 01 06 09 02 18 06 02 0B 53 63 61 6C 61 4F
   62 6A 65 63 74 08 08 1A 00 FFFFFF82 FFFFFF80 FFFFFFA0 FFFFFF80 04 1C 01
   07 63 72 65 61 74 6F 72 03 00 10 02 1D 1E 0D 01
   02 09 02 1F 02 02 05 50 72 6F 78 79 08 08 21 00
   FFFFFF82 FFFFFF80 FFFFFFA0 FFFFFF80 04 22 01 04 6E 6F 64 65 10 02 1D 23
   09 02 24 02 02 04 4E 6F 64 65 08 08 26 00 FFFFFF82 FFFFFF80
   FFFFFFA0 FFFFFF80 04 27 01 04 6E 61 6D 65 10 02 16 28 09 02
   29 06 02 06 53 79 6D 62 6F 6C 08 08 2B 00 FFFFFF82 FFFFFF80
   FFFFFFA0 FFFFFF80 04 2C 01 06 6B 65 72 6E 65 6C 10 02 1D 2D
   09 02 2E 02 02 09 4E 65 74 4B 65 72 6E 65 6C 08
   05 30 00 FFFFFF84 00 31 01 06 3C 69 6E 69 74 3E 14 05
   32 33 34 35 36 10 02 1D 00 08 05 1A 2F FFFFFFC0 00 1C
   08 05 21 2F FFFFFFC0 00 22 08 05 26 2F FFFFFFC0 00 27 08 05
   2B 2F FFFFFFC0 00 2C 08 07 38 00 FFFFFFC0 FFFFFF80 FFFFFF84 00 39 01 0A
   63 68 61 6E 6E 65 6C 4D 61 70 15 01 3A 10 04 3B
   40 27 42 0D 01 3C 0A 02 3D 3E 01 07 6D 75 74 61
   62 6C 65 0A 02 3F 06 01 0A 63 6F 6C 6C 65 63 74
   69 6F 6E 09 02 41 3C 02 07 48 61 73 68 4D 61 70
   10 03 12 43 45 09 02 44 04 02 0D 4F 75 74 70 75
   74 43 68 61 6E 6E 65 6C 10 02 16 46 09 02 47 06
   02 03 41 6E 79 08 07 49 00 FFFFFFC0 FFFFFF80 FFFFFF84 00 4A 01 0E
   63 68 61 6E 6E 65 6C 4D 61 70 5F 24 65 71 14 02
   4B 4E 10 02 16 4C 09 02 4D 06 02 04 55 6E 69 74
   08 07 4F 48 FFFFFF81 FFFFFF80 FFFFFFC0 00 3A 01 03 78 24 31 08 06
   51 00 FFFFFFA0 FFFFFFA0 04 3A 01 0B 63 68 61 6E 6E 65 6C 4D
   61 70 20 08 07 53 00 FFFFFFC0 FFFFFF80 FFFFFF84 00 54 01 0A 73 65
   73 73 69 6F 6E 4D 61 70 15 01 55 10 04 3B 40 42
   27 08 07 57 00 FFFFFFC0 FFFFFF80 FFFFFF84 00 58 01 0E 73 65 73 73
   69 6F 6E 4D 61 70 5F 24 65 71 14 02 4B 59 08 07
   4F 56 FFFFFF81 FFFFFF80 FFFFFFC0 00 55 08 06 5B 00 FFFFFFA0 FFFFFFA0 04 55 01
   0B 73 65 73 73 69 6F 6E 4D 61 70 20 08 05 5D 00
   FFFFFF84 00 5E 01 03 61 63 74 14 01 4B 08 05 60 00 FFFFFF84
   00 61 01 10 70 72 6F 74 65 63 74 65 64 24 73 65
   6E 64 65 72 15 01 62 14 02 42 63 08 07 4F 5F FFFFFF81
   FFFFFF80 FFFFFFC0 00 32 08 05 65 00 FFFFFF84 00 66 01 0E 70 72 6F
   74 65 63 74 65 64 24 65 78 69 74 14 02 67 6B 14
   01 68 10 02 16 69 09 02 6A 06 02 07 4E 6F 74 68
   69 6E 67 08 07 4F 64 FFFFFF81 FFFFFF80 FFFFFFC0 00 32 
  InnerClass: 
   public abstract #427= #142 of #113; //Body=class scala/actors/Actor$Body of class scala/actors/Actor
   public final #428= #137 of #113; //$anon$7=class scala/actors/Actor$$anon$7 of class scala/actors/Actor
   public final #429= #144 of #113; //$anonfun$loop$1=class scala/actors/Actor$$anonfun$loop$1 of class scala/actors/Actor
   public final #430= #132 of #48; //$anonfun$act$1=class scala/actors/remote/DelegateActor$$anonfun$act$1 of class scala/actors/remote/DelegateActor
  minor version: 0
  major version: 49
  Constant pool:
const #1 = Asciz	SourceFile;
const #2 = Asciz	Proxy.scala;
const #3 = Asciz	scala$actors$Actor$$blocker$module;
const #4 = Asciz	Lscala/actors/Actor$blocker$;;
const #5 = Asciz	exiting;
const #6 = Asciz	Z;
const #7 = Asciz	kill;
const #8 = Asciz	Lscala/Function0;;
const #9 = Asciz	waitingFor;
const #10 = Asciz	Lscala/Function1;;
const #11 = Asciz	waitingForNone;
const #12 = Asciz	continuation;
const #13 = Asciz	Lscala/PartialFunction;;
const #14 = Asciz	sendBuffer;
const #15 = Asciz	Lscala/collection/mutable/Queue;;
const #16 = Asciz	mailbox;
const #17 = Asciz	Lscala/actors/MQueue;;
const #18 = Asciz	senders;
const #19 = Asciz	Lscala/collection/immutable/List;;
const #20 = Asciz	shouldExit;
const #21 = Asciz	exitReason;
const #22 = Asciz	Ljava/lang/Object;;
const #23 = Asciz	trapExit;
const #24 = Asciz	links;
const #25 = Asciz	scala$actors$Actor$$onTimeout;
const #26 = Asciz	Lscala/Option;;
const #27 = Asciz	scala$actors$Actor$$received;
const #28 = Asciz	scala$actors$Actor$$isSuspended;
const #29 = Asciz	sessionMap;
const #30 = Asciz	Lscala/collection/mutable/HashMap;;
const #31 = Asciz	Lscala/collection/mutable/HashMap<Lscala/actors/OutputChannel<Ljava/lang/Object;>;Lscala/Symbol;>;;
const #32 = Asciz	Signature;
const #33 = Asciz	channelMap;
const #34 = Asciz	Lscala/collection/mutable/HashMap<Lscala/Symbol;Lscala/actors/OutputChannel<Ljava/lang/Object;>;>;;
const #35 = Asciz	scala$actors$remote$DelegateActor$$kernel;
const #36 = Asciz	Lscala/actors/remote/NetKernel;;
const #37 = Asciz	scala$actors$remote$DelegateActor$$name;
const #38 = Asciz	Lscala/Symbol;;
const #39 = Asciz	scala$actors$remote$DelegateActor$$node;
const #40 = Asciz	Lscala/actors/remote/Node;;
const #41 = Asciz	scala$actors$remote$DelegateActor$$creator;
const #42 = Asciz	Lscala/actors/remote/Proxy;;
const #43 = Asciz	<init>;
const #44 = Asciz	(Lscala/actors/remote/Proxy;Lscala/actors/remote/Node;Lscala/Symbol;Lscala/actors/remote/NetKernel;)V;
const #45 = Asciz	Code;
const #46 = Asciz	LineNumberTable;
const #47 = Asciz	scala/actors/remote/DelegateActor;
const #48 = class	#47;	//  scala/actors/remote/DelegateActor
const #49 = NameAndType	#41:#42;//  scala$actors$remote$DelegateActor$$creator:Lscala/actors/remote/Proxy;
const #50 = Field	#48.#49;	//  scala/actors/remote/DelegateActor.scala$actors$remote$DelegateActor$$creator:Lscala/actors/remote/Proxy;
const #51 = NameAndType	#39:#40;//  scala$actors$remote$DelegateActor$$node:Lscala/actors/remote/Node;
const #52 = Field	#48.#51;	//  scala/actors/remote/DelegateActor.scala$actors$remote$DelegateActor$$node:Lscala/actors/remote/Node;
const #53 = NameAndType	#37:#38;//  scala$actors$remote$DelegateActor$$name:Lscala/Symbol;
const #54 = Field	#48.#53;	//  scala/actors/remote/DelegateActor.scala$actors$remote$DelegateActor$$name:Lscala/Symbol;
const #55 = NameAndType	#35:#36;//  scala$actors$remote$DelegateActor$$kernel:Lscala/actors/remote/NetKernel;
const #56 = Field	#48.#55;	//  scala/actors/remote/DelegateActor.scala$actors$remote$DelegateActor$$kernel:Lscala/actors/remote/NetKernel;
const #57 = Asciz	java/lang/Object;
const #58 = class	#57;	//  java/lang/Object
const #59 = Asciz	()V;
const #60 = NameAndType	#43:#59;//  "<init>":()V
const #61 = Method	#58.#60;	//  java/lang/Object."<init>":()V
const #62 = Asciz	scala/actors/Replyable$class;
const #63 = class	#62;	//  scala/actors/Replyable$class
const #64 = Asciz	$init$;
const #65 = Asciz	(Lscala/actors/Replyable;)V;
const #66 = NameAndType	#64:#65;//  $init$:(Lscala/actors/Replyable;)V
const #67 = Method	#63.#66;	//  scala/actors/Replyable$class.$init$:(Lscala/actors/Replyable;)V
const #68 = Asciz	scala/actors/AbstractActor$class;
const #69 = class	#68;	//  scala/actors/AbstractActor$class
const #70 = Asciz	(Lscala/actors/AbstractActor;)V;
const #71 = NameAndType	#64:#70;//  $init$:(Lscala/actors/AbstractActor;)V
const #72 = Method	#69.#71;	//  scala/actors/AbstractActor$class.$init$:(Lscala/actors/AbstractActor;)V
const #73 = Asciz	scala/actors/Reactor$class;
const #74 = class	#73;	//  scala/actors/Reactor$class
const #75 = Asciz	(Lscala/actors/Reactor;)V;
const #76 = NameAndType	#64:#75;//  $init$:(Lscala/actors/Reactor;)V
const #77 = Method	#74.#76;	//  scala/actors/Reactor$class.$init$:(Lscala/actors/Reactor;)V
const #78 = Asciz	scala/actors/ReplyableReactor$class;
const #79 = class	#78;	//  scala/actors/ReplyableReactor$class
const #80 = Asciz	(Lscala/actors/ReplyReactor;)V;
const #81 = NameAndType	#64:#80;//  $init$:(Lscala/actors/ReplyReactor;)V
const #82 = Method	#79.#81;	//  scala/actors/ReplyableReactor$class.$init$:(Lscala/actors/ReplyReactor;)V
const #83 = Asciz	scala/actors/ReplyReactor$class;
const #84 = class	#83;	//  scala/actors/ReplyReactor$class
const #85 = Method	#84.#81;	//  scala/actors/ReplyReactor$class.$init$:(Lscala/actors/ReplyReactor;)V
const #86 = Asciz	scala/actors/ReplyableActor$class;
const #87 = class	#86;	//  scala/actors/ReplyableActor$class
const #88 = Asciz	(Lscala/actors/ReplyableActor;)V;
const #89 = NameAndType	#64:#88;//  $init$:(Lscala/actors/ReplyableActor;)V
const #90 = Method	#87.#89;	//  scala/actors/ReplyableActor$class.$init$:(Lscala/actors/ReplyableActor;)V
const #91 = Asciz	scala/actors/Actor$class;
const #92 = class	#91;	//  scala/actors/Actor$class
const #93 = Asciz	(Lscala/actors/Actor;)V;
const #94 = NameAndType	#64:#93;//  $init$:(Lscala/actors/Actor;)V
const #95 = Method	#92.#94;	//  scala/actors/Actor$class.$init$:(Lscala/actors/Actor;)V
const #96 = Asciz	scala/collection/mutable/HashMap;
const #97 = class	#96;	//  scala/collection/mutable/HashMap
const #98 = Method	#97.#60;	//  scala/collection/mutable/HashMap."<init>":()V
const #99 = NameAndType	#33:#30;//  channelMap:Lscala/collection/mutable/HashMap;
const #100 = Field	#48.#99;	//  scala/actors/remote/DelegateActor.channelMap:Lscala/collection/mutable/HashMap;
const #101 = NameAndType	#29:#30;//  sessionMap:Lscala/collection/mutable/HashMap;
const #102 = Field	#48.#101;	//  scala/actors/remote/DelegateActor.sessionMap:Lscala/collection/mutable/HashMap;
const #103 = Asciz	this;
const #104 = Asciz	Lscala/actors/remote/DelegateActor;;
const #105 = Asciz	creator;
const #106 = Asciz	node;
const #107 = Asciz	name;
const #108 = Asciz	kernel;
const #109 = Asciz	LocalVariableTable;
const #110 = Asciz	start;
const #111 = Asciz	()Lscala/actors/Reactor;;
const #112 = Asciz	scala/actors/Actor;
const #113 = class	#112;	//  scala/actors/Actor
const #114 = Asciz	()Lscala/actors/Actor;;
const #115 = NameAndType	#110:#114;//  start:()Lscala/actors/Actor;
const #116 = InterfaceMethod	#113.#115;	//  scala/actors/Actor.start:()Lscala/actors/Actor;
const #117 = Asciz	$bang$bang;
const #118 = Asciz	(Ljava/lang/Object;Lscala/PartialFunction;)Lscala/Function0;;
const #119 = Asciz	scala/actors/ReplyableActor;
const #120 = class	#119;	//  scala/actors/ReplyableActor
const #121 = Asciz	(Ljava/lang/Object;Lscala/PartialFunction;)Lscala/actors/Future;;
const #122 = NameAndType	#117:#121;//  $bang$bang:(Ljava/lang/Object;Lscala/PartialFunction;)Lscala/actors/Future;
const #123 = InterfaceMethod	#120.#122;	//  scala/actors/ReplyableActor.$bang$bang:(Ljava/lang/Object;Lscala/PartialFunction;)Lscala/actors/Future;
const #124 = Asciz	msg;
const #125 = Asciz	f;
const #126 = Asciz	(Ljava/lang/Object;)Lscala/Function0;;
const #127 = Asciz	(Ljava/lang/Object;)Lscala/actors/Future;;
const #128 = NameAndType	#117:#127;//  $bang$bang:(Ljava/lang/Object;)Lscala/actors/Future;
const #129 = InterfaceMethod	#120.#128;	//  scala/actors/ReplyableActor.$bang$bang:(Ljava/lang/Object;)Lscala/actors/Future;
const #130 = Asciz	act;
const #131 = Asciz	scala/actors/remote/DelegateActor$$anonfun$act$1;
const #132 = class	#131;	//  scala/actors/remote/DelegateActor$$anonfun$act$1
const #133 = Asciz	(Lscala/actors/remote/DelegateActor;)V;
const #134 = NameAndType	#43:#133;//  "<init>":(Lscala/actors/remote/DelegateActor;)V
const #135 = Method	#132.#134;	//  scala/actors/remote/DelegateActor$$anonfun$act$1."<init>":(Lscala/actors/remote/DelegateActor;)V
const #136 = Asciz	scala/actors/Actor$$anon$7;
const #137 = class	#136;	//  scala/actors/Actor$$anon$7
const #138 = Asciz	(Lscala/Function0;)V;
const #139 = NameAndType	#43:#138;//  "<init>":(Lscala/Function0;)V
const #140 = Method	#137.#139;	//  scala/actors/Actor$$anon$7."<init>":(Lscala/Function0;)V
const #141 = Asciz	scala/actors/Actor$Body;
const #142 = class	#141;	//  scala/actors/Actor$Body
const #143 = Asciz	scala/actors/Actor$$anonfun$loop$1;
const #144 = class	#143;	//  scala/actors/Actor$$anonfun$loop$1
const #145 = Method	#144.#139;	//  scala/actors/Actor$$anonfun$loop$1."<init>":(Lscala/Function0;)V
const #146 = Asciz	andThen;
const #147 = NameAndType	#146:#138;//  andThen:(Lscala/Function0;)V
const #148 = InterfaceMethod	#142.#147;	//  scala/actors/Actor$Body.andThen:(Lscala/Function0;)V
const #149 = Asciz	sessionMap_$eq;
const #150 = Asciz	(Lscala/collection/mutable/HashMap;)V;
const #151 = Asciz	(Lscala/collection/mutable/HashMap<Lscala/actors/OutputChannel<Ljava/lang/Object;>;Lscala/Symbol;>;)V;
const #152 = Asciz	()Lscala/collection/mutable/HashMap;;
const #153 = Asciz	()Lscala/collection/mutable/HashMap<Lscala/actors/OutputChannel<Ljava/lang/Object;>;Lscala/Symbol;>;;
const #154 = Asciz	channelMap_$eq;
const #155 = Asciz	(Lscala/collection/mutable/HashMap<Lscala/Symbol;Lscala/actors/OutputChannel<Ljava/lang/Object;>;>;)V;
const #156 = Asciz	()Lscala/collection/mutable/HashMap<Lscala/Symbol;Lscala/actors/OutputChannel<Ljava/lang/Object;>;>;;
const #157 = Asciz	protected$exit;
const #158 = Asciz	(Lscala/actors/remote/DelegateActor;)Lscala/runtime/Nothing$;;
const #159 = Asciz	exit;
const #160 = Asciz	()Lscala/runtime/Nothing$;;
const #161 = NameAndType	#159:#160;//  exit:()Lscala/runtime/Nothing$;
const #162 = InterfaceMethod	#113.#161;	//  scala/actors/Actor.exit:()Lscala/runtime/Nothing$;
const #163 = Asciz	protected$sender;
const #164 = Asciz	(Lscala/actors/remote/DelegateActor;)Lscala/actors/OutputChannel;;
const #165 = Asciz	scala/actors/ReplyReactor;
const #166 = class	#165;	//  scala/actors/ReplyReactor
const #167 = Asciz	sender;
const #168 = Asciz	()Lscala/actors/OutputChannel;;
const #169 = NameAndType	#167:#168;//  sender:()Lscala/actors/OutputChannel;
const #170 = InterfaceMethod	#166.#169;	//  scala/actors/ReplyReactor.sender:()Lscala/actors/OutputChannel;
const #171 = Asciz	(Lscala/actors/remote/DelegateActor;)Lscala/actors/OutputChannel<Ljava/lang/Object;>;;
const #172 = Asciz	exiting_$eq;
const #173 = Asciz	(Z)V;
const #174 = NameAndType	#5:#6;//  exiting:Z
const #175 = Field	#48.#174;	//  scala/actors/remote/DelegateActor.exiting:Z
const #176 = Asciz	()Z;
const #177 = Asciz	terminated;
const #178 = NameAndType	#177:#75;//  terminated:(Lscala/actors/Reactor;)V
const #179 = Method	#74.#178;	//  scala/actors/Reactor$class.terminated:(Lscala/actors/Reactor;)V
const #180 = Asciz	seq;
const #181 = Asciz	(Lscala/Function0;Lscala/Function0;)V;
const #182 = Asciz	(Lscala/actors/Reactor;Lscala/Function0;Lscala/Function0;)V;
const #183 = NameAndType	#180:#182;//  seq:(Lscala/actors/Reactor;Lscala/Function0;Lscala/Function0;)V
const #184 = Method	#74.#183;	//  scala/actors/Reactor$class.seq:(Lscala/actors/Reactor;Lscala/Function0;Lscala/Function0;)V
const #185 = Asciz	first;
const #186 = Asciz	next;
const #187 = Asciz	drainSendBuffer;
const #188 = Asciz	(Lscala/actors/MQueue;)V;
const #189 = Asciz	(Lscala/actors/Reactor;Lscala/actors/MQueue;)V;
const #190 = NameAndType	#187:#189;//  drainSendBuffer:(Lscala/actors/Reactor;Lscala/actors/MQueue;)V
const #191 = Method	#74.#190;	//  scala/actors/Reactor$class.drainSendBuffer:(Lscala/actors/Reactor;Lscala/actors/MQueue;)V
const #192 = Asciz	mbox;
const #193 = Asciz	receiver;
const #194 = Asciz	(Lscala/actors/Reactor;)Lscala/actors/Actor;;
const #195 = NameAndType	#193:#194;//  receiver:(Lscala/actors/Reactor;)Lscala/actors/Actor;
const #196 = Method	#74.#195;	//  scala/actors/Reactor$class.receiver:(Lscala/actors/Reactor;)Lscala/actors/Actor;
const #197 = Asciz	send;
const #198 = Asciz	(Ljava/lang/Object;Lscala/actors/OutputChannel;)V;
const #199 = Asciz	(Lscala/actors/Reactor;Ljava/lang/Object;Lscala/actors/OutputChannel;)V;
const #200 = NameAndType	#197:#199;//  send:(Lscala/actors/Reactor;Ljava/lang/Object;Lscala/actors/OutputChannel;)V
const #201 = Method	#74.#200;	//  scala/actors/Reactor$class.send:(Lscala/actors/Reactor;Ljava/lang/Object;Lscala/actors/OutputChannel;)V
const #202 = Asciz	replyTo;
const #203 = Asciz	Lscala/actors/OutputChannel;;
const #204 = Asciz	mailboxSize;
const #205 = Asciz	()I;
const #206 = Asciz	(Lscala/actors/Reactor;)I;
const #207 = NameAndType	#204:#206;//  mailboxSize:(Lscala/actors/Reactor;)I
const #208 = Method	#74.#207;	//  scala/actors/Reactor$class.mailboxSize:(Lscala/actors/Reactor;)I
const #209 = Asciz	exceptionHandler;
const #210 = Asciz	()Lscala/PartialFunction;;
const #211 = Asciz	(Lscala/actors/Reactor;)Lscala/PartialFunction;;
const #212 = NameAndType	#209:#211;//  exceptionHandler:(Lscala/actors/Reactor;)Lscala/PartialFunction;
const #213 = Method	#74.#212;	//  scala/actors/Reactor$class.exceptionHandler:(Lscala/actors/Reactor;)Lscala/PartialFunction;
const #214 = Asciz	scala$actors$Reactor$_setter_$waitingForNone_$eq;
const #215 = Asciz	(Lscala/Function1;)V;
const #216 = NameAndType	#11:#10;//  waitingForNone:Lscala/Function1;
const #217 = Field	#48.#216;	//  scala/actors/remote/DelegateActor.waitingForNone:Lscala/Function1;
const #218 = Asciz	scala$actors$Reactor$_setter_$sendBuffer_$eq;
const #219 = Asciz	(Lscala/collection/mutable/Queue;)V;
const #220 = NameAndType	#14:#15;//  sendBuffer:Lscala/collection/mutable/Queue;
const #221 = Field	#48.#220;	//  scala/actors/remote/DelegateActor.sendBuffer:Lscala/collection/mutable/Queue;
const #222 = Asciz	scala$actors$Reactor$_setter_$mailbox_$eq;
const #223 = NameAndType	#16:#17;//  mailbox:Lscala/actors/MQueue;
const #224 = Field	#48.#223;	//  scala/actors/remote/DelegateActor.mailbox:Lscala/actors/MQueue;
const #225 = Asciz	kill_$eq;
const #226 = NameAndType	#7:#8;//  kill:Lscala/Function0;
const #227 = Field	#48.#226;	//  scala/actors/remote/DelegateActor.kill:Lscala/Function0;
const #228 = Asciz	()Lscala/Function0;;
const #229 = Asciz	waitingFor_$eq;
const #230 = NameAndType	#9:#10;//  waitingFor:Lscala/Function1;
const #231 = Field	#48.#230;	//  scala/actors/remote/DelegateActor.waitingFor:Lscala/Function1;
const #232 = Asciz	()Lscala/Function1;;
const #233 = Asciz	continuation_$eq;
const #234 = Asciz	(Lscala/PartialFunction;)V;
const #235 = NameAndType	#12:#13;//  continuation:Lscala/PartialFunction;
const #236 = Field	#48.#235;	//  scala/actors/remote/DelegateActor.continuation:Lscala/PartialFunction;
const #237 = Asciz	()Lscala/collection/mutable/Queue;;
const #238 = Asciz	()Lscala/actors/MQueue;;
const #239 = Asciz	searchMailbox;
const #240 = Asciz	(Lscala/actors/MQueue;Lscala/Function1;Z)V;
const #241 = Asciz	(Lscala/actors/ReplyReactor;Lscala/actors/MQueue;Lscala/Function1;Z)V;
const #242 = NameAndType	#239:#241;//  searchMailbox:(Lscala/actors/ReplyReactor;Lscala/actors/MQueue;Lscala/Function1;Z)V
const #243 = Method	#84.#242;	//  scala/actors/ReplyReactor$class.searchMailbox:(Lscala/actors/ReplyReactor;Lscala/actors/MQueue;Lscala/Function1;Z)V
const #244 = Asciz	startMbox;
const #245 = Asciz	handlesMessage;
const #246 = Asciz	resumeOnSameThread;
const #247 = Asciz	forward;
const #248 = Asciz	(Ljava/lang/Object;)V;
const #249 = Asciz	(Lscala/actors/ReplyReactor;Ljava/lang/Object;)V;
const #250 = NameAndType	#247:#249;//  forward:(Lscala/actors/ReplyReactor;Ljava/lang/Object;)V
const #251 = Method	#84.#250;	//  scala/actors/ReplyReactor$class.forward:(Lscala/actors/ReplyReactor;Ljava/lang/Object;)V
const #252 = Asciz	$bang;
const #253 = NameAndType	#252:#249;//  $bang:(Lscala/actors/ReplyReactor;Ljava/lang/Object;)V
const #254 = Method	#84.#253;	//  scala/actors/ReplyReactor$class.$bang:(Lscala/actors/ReplyReactor;Ljava/lang/Object;)V
const #255 = Asciz	reply;
const #256 = NameAndType	#255:#249;//  reply:(Lscala/actors/ReplyReactor;Ljava/lang/Object;)V
const #257 = Method	#84.#256;	//  scala/actors/ReplyReactor$class.reply:(Lscala/actors/ReplyReactor;Ljava/lang/Object;)V
const #258 = Asciz	(Lscala/actors/ReplyReactor;)Lscala/actors/OutputChannel;;
const #259 = NameAndType	#167:#258;//  sender:(Lscala/actors/ReplyReactor;)Lscala/actors/OutputChannel;
const #260 = Method	#84.#259;	//  scala/actors/ReplyReactor$class.sender:(Lscala/actors/ReplyReactor;)Lscala/actors/OutputChannel;
const #261 = Asciz	senders_$eq;
const #262 = Asciz	(Lscala/collection/immutable/List;)V;
const #263 = NameAndType	#18:#19;//  senders:Lscala/collection/immutable/List;
const #264 = Field	#48.#263;	//  scala/actors/remote/DelegateActor.senders:Lscala/collection/immutable/List;
const #265 = Asciz	()Lscala/collection/immutable/List;;
const #266 = Asciz	(Lscala/actors/ReplyableActor;Ljava/lang/Object;)Lscala/actors/Future;;
const #267 = NameAndType	#117:#266;//  $bang$bang:(Lscala/actors/ReplyableActor;Ljava/lang/Object;)Lscala/actors/Future;
const #268 = Method	#87.#267;	//  scala/actors/ReplyableActor$class.$bang$bang:(Lscala/actors/ReplyableActor;Ljava/lang/Object;)Lscala/actors/Future;
const #269 = Asciz	(Lscala/actors/ReplyableActor;Ljava/lang/Object;Lscala/PartialFunction;)Lscala/actors/Future;;
const #270 = NameAndType	#117:#269;//  $bang$bang:(Lscala/actors/ReplyableActor;Ljava/lang/Object;Lscala/PartialFunction;)Lscala/actors/Future;
const #271 = Method	#87.#270;	//  scala/actors/ReplyableActor$class.$bang$bang:(Lscala/actors/ReplyableActor;Ljava/lang/Object;Lscala/PartialFunction;)Lscala/actors/Future;
const #272 = Asciz	$bang$qmark;
const #273 = Asciz	(JLjava/lang/Object;)Lscala/Option;;
const #274 = Asciz	(Lscala/actors/ReplyableActor;JLjava/lang/Object;)Lscala/Option;;
const #275 = NameAndType	#272:#274;//  $bang$qmark:(Lscala/actors/ReplyableActor;JLjava/lang/Object;)Lscala/Option;
const #276 = Method	#87.#275;	//  scala/actors/ReplyableActor$class.$bang$qmark:(Lscala/actors/ReplyableActor;JLjava/lang/Object;)Lscala/Option;
const #277 = Asciz	msec;
const #278 = Asciz	J;
const #279 = Asciz	(Ljava/lang/Object;)Ljava/lang/Object;;
const #280 = Asciz	(Lscala/actors/ReplyableActor;Ljava/lang/Object;)Ljava/lang/Object;;
const #281 = NameAndType	#272:#280;//  $bang$qmark:(Lscala/actors/ReplyableActor;Ljava/lang/Object;)Ljava/lang/Object;
const #282 = Method	#87.#281;	//  scala/actors/ReplyableActor$class.$bang$qmark:(Lscala/actors/ReplyableActor;Ljava/lang/Object;)Ljava/lang/Object;
const #283 = Asciz	onTerminate;
const #284 = Asciz	(Lscala/actors/Actor;Lscala/Function0;)V;
const #285 = NameAndType	#283:#284;//  onTerminate:(Lscala/actors/Actor;Lscala/Function0;)V
const #286 = Method	#92.#285;	//  scala/actors/Actor$class.onTerminate:(Lscala/actors/Actor;Lscala/Function0;)V
const #287 = Asciz	(Lscala/actors/AbstractActor;Ljava/lang/Object;)V;
const #288 = Asciz	(Lscala/actors/Actor;Lscala/actors/AbstractActor;Ljava/lang/Object;)V;
const #289 = NameAndType	#159:#288;//  exit:(Lscala/actors/Actor;Lscala/actors/AbstractActor;Ljava/lang/Object;)V
const #290 = Method	#92.#289;	//  scala/actors/Actor$class.exit:(Lscala/actors/Actor;Lscala/actors/AbstractActor;Ljava/lang/Object;)V
const #291 = Asciz	from;
const #292 = Asciz	Lscala/actors/AbstractActor;;
const #293 = Asciz	reason;
const #294 = Asciz	exitLinked;
const #295 = Asciz	(Lscala/actors/Actor;Ljava/lang/Object;)V;
const #296 = NameAndType	#294:#295;//  exitLinked:(Lscala/actors/Actor;Ljava/lang/Object;)V
const #297 = Method	#92.#296;	//  scala/actors/Actor$class.exitLinked:(Lscala/actors/Actor;Ljava/lang/Object;)V
const #298 = NameAndType	#294:#93;//  exitLinked:(Lscala/actors/Actor;)V
const #299 = Method	#92.#298;	//  scala/actors/Actor$class.exitLinked:(Lscala/actors/Actor;)V
const #300 = Asciz	(Lscala/actors/Actor;)Lscala/runtime/Nothing$;;
const #301 = NameAndType	#159:#300;//  exit:(Lscala/actors/Actor;)Lscala/runtime/Nothing$;
const #302 = Method	#92.#301;	//  scala/actors/Actor$class.exit:(Lscala/actors/Actor;)Lscala/runtime/Nothing$;
const #303 = Asciz	(Ljava/lang/Object;)Lscala/runtime/Nothing$;;
const #304 = Asciz	(Lscala/actors/Actor;Ljava/lang/Object;)Lscala/runtime/Nothing$;;
const #305 = NameAndType	#159:#304;//  exit:(Lscala/actors/Actor;Ljava/lang/Object;)Lscala/runtime/Nothing$;
const #306 = Method	#92.#305;	//  scala/actors/Actor$class.exit:(Lscala/actors/Actor;Ljava/lang/Object;)Lscala/runtime/Nothing$;
const #307 = Asciz	unlinkFrom;
const #308 = Asciz	(Lscala/actors/Actor;Lscala/actors/AbstractActor;)V;
const #309 = NameAndType	#307:#308;//  unlinkFrom:(Lscala/actors/Actor;Lscala/actors/AbstractActor;)V
const #310 = Method	#92.#309;	//  scala/actors/Actor$class.unlinkFrom:(Lscala/actors/Actor;Lscala/actors/AbstractActor;)V
const #311 = Asciz	unlink;
const #312 = NameAndType	#311:#308;//  unlink:(Lscala/actors/Actor;Lscala/actors/AbstractActor;)V
const #313 = Method	#92.#312;	//  scala/actors/Actor$class.unlink:(Lscala/actors/Actor;Lscala/actors/AbstractActor;)V
const #314 = Asciz	linkTo;
const #315 = NameAndType	#314:#308;//  linkTo:(Lscala/actors/Actor;Lscala/actors/AbstractActor;)V
const #316 = Method	#92.#315;	//  scala/actors/Actor$class.linkTo:(Lscala/actors/Actor;Lscala/actors/AbstractActor;)V
const #317 = Asciz	to;
const #318 = Asciz	link;
const #319 = Asciz	(Lscala/Function0;)Lscala/actors/Actor;;
const #320 = Asciz	(Lscala/actors/Actor;Lscala/Function0;)Lscala/actors/Actor;;
const #321 = NameAndType	#318:#320;//  link:(Lscala/actors/Actor;Lscala/Function0;)Lscala/actors/Actor;
const #322 = Method	#92.#321;	//  scala/actors/Actor$class.link:(Lscala/actors/Actor;Lscala/Function0;)Lscala/actors/Actor;
const #323 = Asciz	body;
const #324 = Asciz	(Lscala/actors/AbstractActor;)Lscala/actors/AbstractActor;;
const #325 = Asciz	(Lscala/actors/Actor;Lscala/actors/AbstractActor;)Lscala/actors/AbstractActor;;
const #326 = NameAndType	#318:#325;//  link:(Lscala/actors/Actor;Lscala/actors/AbstractActor;)Lscala/actors/AbstractActor;
const #327 = Method	#92.#326;	//  scala/actors/Actor$class.link:(Lscala/actors/Actor;Lscala/actors/AbstractActor;)Lscala/actors/AbstractActor;
const #328 = Asciz	(Lscala/actors/Actor;)Lscala/actors/Actor;;
const #329 = NameAndType	#110:#328;//  start:(Lscala/actors/Actor;)Lscala/actors/Actor;
const #330 = Method	#92.#329;	//  scala/actors/Actor$class.start:(Lscala/actors/Actor;)Lscala/actors/Actor;
const #331 = Asciz	scheduleActor;
const #332 = Asciz	(Lscala/PartialFunction;Ljava/lang/Object;)V;
const #333 = Asciz	(Lscala/actors/Actor;Lscala/PartialFunction;Ljava/lang/Object;)V;
const #334 = NameAndType	#331:#333;//  scheduleActor:(Lscala/actors/Actor;Lscala/PartialFunction;Ljava/lang/Object;)V
const #335 = Method	#92.#334;	//  scala/actors/Actor$class.scheduleActor:(Lscala/actors/Actor;Lscala/PartialFunction;Ljava/lang/Object;)V
const #336 = Asciz	$qmark;
const #337 = Asciz	()Ljava/lang/Object;;
const #338 = Asciz	(Lscala/actors/Actor;)Ljava/lang/Object;;
const #339 = NameAndType	#336:#338;//  $qmark:(Lscala/actors/Actor;)Ljava/lang/Object;
const #340 = Method	#92.#339;	//  scala/actors/Actor$class.$qmark:(Lscala/actors/Actor;)Ljava/lang/Object;
const #341 = Asciz	reactWithin;
const #342 = Asciz	(JLscala/PartialFunction;)Lscala/runtime/Nothing$;;
const #343 = Asciz	(Lscala/actors/Actor;JLscala/PartialFunction;)Lscala/runtime/Nothing$;;
const #344 = NameAndType	#341:#343;//  reactWithin:(Lscala/actors/Actor;JLscala/PartialFunction;)Lscala/runtime/Nothing$;
const #345 = Method	#92.#344;	//  scala/actors/Actor$class.reactWithin:(Lscala/actors/Actor;JLscala/PartialFunction;)Lscala/runtime/Nothing$;
const #346 = Asciz	react;
const #347 = Asciz	(Lscala/PartialFunction;)Lscala/runtime/Nothing$;;
const #348 = Asciz	(Lscala/actors/Actor;Lscala/PartialFunction;)Lscala/runtime/Nothing$;;
const #349 = NameAndType	#346:#348;//  react:(Lscala/actors/Actor;Lscala/PartialFunction;)Lscala/runtime/Nothing$;
const #350 = Method	#92.#349;	//  scala/actors/Actor$class.react:(Lscala/actors/Actor;Lscala/PartialFunction;)Lscala/runtime/Nothing$;
const #351 = Asciz	receiveWithin;
const #352 = Asciz	(JLscala/PartialFunction;)Ljava/lang/Object;;
const #353 = Asciz	(Lscala/actors/Actor;JLscala/PartialFunction;)Ljava/lang/Object;;
const #354 = NameAndType	#351:#353;//  receiveWithin:(Lscala/actors/Actor;JLscala/PartialFunction;)Ljava/lang/Object;
const #355 = Method	#92.#354;	//  scala/actors/Actor$class.receiveWithin:(Lscala/actors/Actor;JLscala/PartialFunction;)Ljava/lang/Object;
const #356 = Asciz	receive;
const #357 = Asciz	(Lscala/PartialFunction;)Ljava/lang/Object;;
const #358 = Asciz	(Lscala/actors/Actor;Lscala/PartialFunction;)Ljava/lang/Object;;
const #359 = NameAndType	#356:#358;//  receive:(Lscala/actors/Actor;Lscala/PartialFunction;)Ljava/lang/Object;
const #360 = Method	#92.#359;	//  scala/actors/Actor$class.receive:(Lscala/actors/Actor;Lscala/PartialFunction;)Ljava/lang/Object;
const #361 = Asciz	resumeReceiver;
const #362 = Asciz	(Lscala/Tuple2;Z)V;
const #363 = Asciz	(Lscala/actors/Actor;Lscala/Tuple2;Z)V;
const #364 = NameAndType	#361:#363;//  resumeReceiver:(Lscala/actors/Actor;Lscala/Tuple2;Z)V
const #365 = Method	#92.#364;	//  scala/actors/Actor$class.resumeReceiver:(Lscala/actors/Actor;Lscala/Tuple2;Z)V
const #366 = Asciz	item;
const #367 = Asciz	Lscala/Tuple2;;
const #368 = Asciz	onSameThread;
const #369 = Asciz	makeReaction;
const #370 = Asciz	(Lscala/Function0;)Ljava/lang/Runnable;;
const #371 = Asciz	(Lscala/actors/Actor;Lscala/Function0;)Ljava/lang/Runnable;;
const #372 = NameAndType	#369:#371;//  makeReaction:(Lscala/actors/Actor;Lscala/Function0;)Ljava/lang/Runnable;
const #373 = Method	#92.#372;	//  scala/actors/Actor$class.makeReaction:(Lscala/actors/Actor;Lscala/Function0;)Ljava/lang/Runnable;
const #374 = Asciz	fun;
const #375 = Asciz	startSearch;
const #376 = Asciz	(Ljava/lang/Object;Lscala/actors/OutputChannel;Lscala/Function1;)Lscala/Function0;;
const #377 = Asciz	(Lscala/actors/Actor;Ljava/lang/Object;Lscala/actors/OutputChannel;Lscala/Function1;)Lscala/Function0;;
const #378 = NameAndType	#375:#377;//  startSearch:(Lscala/actors/Actor;Ljava/lang/Object;Lscala/actors/OutputChannel;Lscala/Function1;)Lscala/Function0;
const #379 = Method	#92.#378;	//  scala/actors/Actor$class.startSearch:(Lscala/actors/Actor;Ljava/lang/Object;Lscala/actors/OutputChannel;Lscala/Function1;)Lscala/Function0;
const #380 = Asciz	handler;
const #381 = Asciz	scheduler;
const #382 = Asciz	()Lscala/actors/IScheduler;;
const #383 = Asciz	(Lscala/actors/Actor;)Lscala/actors/IScheduler;;
const #384 = NameAndType	#381:#383;//  scheduler:(Lscala/actors/Actor;)Lscala/actors/IScheduler;
const #385 = Method	#92.#384;	//  scala/actors/Actor$class.scheduler:(Lscala/actors/Actor;)Lscala/actors/IScheduler;
const #386 = Asciz	scala$actors$Actor$$super$resumeReceiver;
const #387 = Asciz	(Lscala/actors/ReplyReactor;Lscala/Tuple2;Z)V;
const #388 = NameAndType	#361:#387;//  resumeReceiver:(Lscala/actors/ReplyReactor;Lscala/Tuple2;Z)V
const #389 = Method	#84.#388;	//  scala/actors/ReplyReactor$class.resumeReceiver:(Lscala/actors/ReplyReactor;Lscala/Tuple2;Z)V
const #390 = Asciz	scala$actors$Actor$$super$startSearch;
const #391 = Asciz	(Lscala/actors/Reactor;Ljava/lang/Object;Lscala/actors/OutputChannel;Lscala/Function1;)Lscala/Function0;;
const #392 = NameAndType	#375:#391;//  startSearch:(Lscala/actors/Reactor;Ljava/lang/Object;Lscala/actors/OutputChannel;Lscala/Function1;)Lscala/Function0;
const #393 = Method	#74.#392;	//  scala/actors/Reactor$class.startSearch:(Lscala/actors/Reactor;Ljava/lang/Object;Lscala/actors/OutputChannel;Lscala/Function1;)Lscala/Function0;
const #394 = Asciz	shouldExit_$eq;
const #395 = NameAndType	#20:#6;//  shouldExit:Z
const #396 = Field	#48.#395;	//  scala/actors/remote/DelegateActor.shouldExit:Z
const #397 = Asciz	exitReason_$eq;
const #398 = NameAndType	#21:#22;//  exitReason:Ljava/lang/Object;
const #399 = Field	#48.#398;	//  scala/actors/remote/DelegateActor.exitReason:Ljava/lang/Object;
const #400 = Asciz	trapExit_$eq;
const #401 = NameAndType	#23:#6;//  trapExit:Z
const #402 = Field	#48.#401;	//  scala/actors/remote/DelegateActor.trapExit:Z
const #403 = Asciz	links_$eq;
const #404 = NameAndType	#24:#19;//  links:Lscala/collection/immutable/List;
const #405 = Field	#48.#404;	//  scala/actors/remote/DelegateActor.links:Lscala/collection/immutable/List;
const #406 = Asciz	scala$actors$Actor$$blocker;
const #407 = Asciz	()Lscala/actors/Actor$blocker$;;
const #408 = NameAndType	#3:#4;//  scala$actors$Actor$$blocker$module:Lscala/actors/Actor$blocker$;
const #409 = Field	#48.#408;	//  scala/actors/remote/DelegateActor.scala$actors$Actor$$blocker$module:Lscala/actors/Actor$blocker$;
const #410 = Asciz	scala/actors/Actor$blocker$;
const #411 = class	#410;	//  scala/actors/Actor$blocker$
const #412 = NameAndType	#43:#93;//  "<init>":(Lscala/actors/Actor;)V
const #413 = Method	#411.#412;	//  scala/actors/Actor$blocker$."<init>":(Lscala/actors/Actor;)V
const #414 = Asciz	scala$actors$Actor$$onTimeout_$eq;
const #415 = Asciz	(Lscala/Option;)V;
const #416 = NameAndType	#25:#26;//  scala$actors$Actor$$onTimeout:Lscala/Option;
const #417 = Field	#48.#416;	//  scala/actors/remote/DelegateActor.scala$actors$Actor$$onTimeout:Lscala/Option;
const #418 = Asciz	()Lscala/Option;;
const #419 = Asciz	scala$actors$Actor$$received_$eq;
const #420 = NameAndType	#27:#26;//  scala$actors$Actor$$received:Lscala/Option;
const #421 = Field	#48.#420;	//  scala/actors/remote/DelegateActor.scala$actors$Actor$$received:Lscala/Option;
const #422 = Asciz	scala$actors$Actor$$isSuspended_$eq;
const #423 = NameAndType	#28:#6;//  scala$actors$Actor$$isSuspended:Z
const #424 = Field	#48.#423;	//  scala/actors/remote/DelegateActor.scala$actors$Actor$$isSuspended:Z
const #425 = Asciz	ScalaSig;
const #426 = Asciz	InnerClasses;
const #427 = Asciz	Body;
const #428 = Asciz	$anon$7;
const #429 = Asciz	$anonfun$loop$1;
const #430 = Asciz	$anonfun$act$1;
const #431 = Asciz	scala/ScalaObject;
const #432 = class	#431;	//  scala/ScalaObject

{
public final scala.actors.remote.NetKernel scala$actors$remote$DelegateActor$$kernel;

public final scala.Symbol scala$actors$remote$DelegateActor$$name;

public final scala.actors.remote.Node scala$actors$remote$DelegateActor$$node;

public final scala.actors.remote.Proxy scala$actors$remote$DelegateActor$$creator;

public scala.actors.remote.DelegateActor(scala.actors.remote.Proxy, scala.actors.remote.Node, scala.Symbol, scala.actors.remote.NetKernel);
  Code:
   Stack=3, Locals=5, Args_size=5
   0:	aload_0
   1:	aload_1
   2:	putfield	#50; //Field scala$actors$remote$DelegateActor$$creator:Lscala/actors/remote/Proxy;
   5:	aload_0
   6:	aload_2
   7:	putfield	#52; //Field scala$actors$remote$DelegateActor$$node:Lscala/actors/remote/Node;
   10:	aload_0
   11:	aload_3
   12:	putfield	#54; //Field scala$actors$remote$DelegateActor$$name:Lscala/Symbol;
   15:	aload_0
   16:	aload	4
   18:	putfield	#56; //Field scala$actors$remote$DelegateActor$$kernel:Lscala/actors/remote/NetKernel;
   21:	aload_0
   22:	invokespecial	#61; //Method java/lang/Object."<init>":()V
   25:	aload_0
   26:	invokestatic	#67; //Method scala/actors/Replyable$class.$init$:(Lscala/actors/Replyable;)V
   29:	aload_0
   30:	invokestatic	#72; //Method scala/actors/AbstractActor$class.$init$:(Lscala/actors/AbstractActor;)V
   33:	aload_0
   34:	invokestatic	#77; //Method scala/actors/Reactor$class.$init$:(Lscala/actors/Reactor;)V
   37:	aload_0
   38:	invokestatic	#82; //Method scala/actors/ReplyableReactor$class.$init$:(Lscala/actors/ReplyReactor;)V
   41:	aload_0
   42:	invokestatic	#85; //Method scala/actors/ReplyReactor$class.$init$:(Lscala/actors/ReplyReactor;)V
   45:	aload_0
   46:	invokestatic	#90; //Method scala/actors/ReplyableActor$class.$init$:(Lscala/actors/ReplyableActor;)V
   49:	aload_0
   50:	invokestatic	#95; //Method scala/actors/Actor$class.$init$:(Lscala/actors/Actor;)V
   53:	aload_0
   54:	new	#97; //class scala/collection/mutable/HashMap
   57:	dup
   58:	invokespecial	#98; //Method scala/collection/mutable/HashMap."<init>":()V
   61:	putfield	#100; //Field channelMap:Lscala/collection/mutable/HashMap;
   64:	aload_0
   65:	new	#97; //class scala/collection/mutable/HashMap
   68:	dup
   69:	invokespecial	#98; //Method scala/collection/mutable/HashMap."<init>":()V
   72:	putfield	#102; //Field sessionMap:Lscala/collection/mutable/HashMap;
   75:	return
  LineNumberTable: 
   line 120: 0
   line 121: 53
   line 122: 64

  LocalVariableTable: 
   Start  Length  Slot  Name   Signature
   0      76      0    this       Lscala/actors/remote/DelegateActor;
   0      76      1    creator       Lscala/actors/remote/Proxy;
   0      76      2    node       Lscala/actors/remote/Node;
   0      76      3    name       Lscala/Symbol;
   0      76      4    kernel       Lscala/actors/remote/NetKernel;


public scala.actors.Reactor start();
  Code:
   Stack=1, Locals=1, Args_size=1
   0:	aload_0
   1:	invokeinterface	#116,  1; //InterfaceMethod scala/actors/Actor.start:()Lscala/actors/Actor;
   6:	areturn
  LineNumberTable: 
   line 120: 0


public scala.Function0 $bang$bang(java.lang.Object, scala.PartialFunction);
  Code:
   Stack=3, Locals=3, Args_size=3
   0:	aload_0
   1:	aload_1
   2:	aload_2
   3:	invokeinterface	#123,  3; //InterfaceMethod scala/actors/ReplyableActor.$bang$bang:(Ljava/lang/Object;Lscala/PartialFunction;)Lscala/actors/Future;
   8:	areturn
  LineNumberTable: 
   line 120: 0

  LocalVariableTable: 
   Start  Length  Slot  Name   Signature
   0      9      0    this       Lscala/actors/remote/DelegateActor;
   0      9      1    msg       Ljava/lang/Object;
   0      9      2    f       Lscala/PartialFunction;


public scala.Function0 $bang$bang(java.lang.Object);
  Code:
   Stack=2, Locals=2, Args_size=2
   0:	aload_0
   1:	aload_1
   2:	invokeinterface	#129,  2; //InterfaceMethod scala/actors/ReplyableActor.$bang$bang:(Ljava/lang/Object;)Lscala/actors/Future;
   7:	areturn
  LineNumberTable: 
   line 120: 0

  LocalVariableTable: 
   Start  Length  Slot  Name   Signature
   0      8      0    this       Lscala/actors/remote/DelegateActor;
   0      8      1    msg       Ljava/lang/Object;


public void act();
  Code:
   Stack=4, Locals=2, Args_size=1
   0:	new	#132; //class scala/actors/remote/DelegateActor$$anonfun$act$1
   3:	dup
   4:	aload_0
   5:	invokespecial	#135; //Method scala/actors/remote/DelegateActor$$anonfun$act$1."<init>":(Lscala/actors/remote/DelegateActor;)V
   8:	astore_1
   9:	new	#137; //class scala/actors/Actor$$anon$7
   12:	dup
   13:	aload_1
   14:	invokespecial	#140; //Method scala/actors/Actor$$anon$7."<init>":(Lscala/Function0;)V
   17:	checkcast	#142; //class scala/actors/Actor$Body
   20:	new	#144; //class scala/actors/Actor$$anonfun$loop$1
   23:	dup
   24:	aload_1
   25:	invokespecial	#145; //Method scala/actors/Actor$$anonfun$loop$1."<init>":(Lscala/Function0;)V
   28:	invokeinterface	#148,  2; //InterfaceMethod scala/actors/Actor$Body.andThen:(Lscala/Function0;)V
   33:	return
  LineNumberTable: 
   line 126: 0
   line 125: 8

  LocalVariableTable: 
   Start  Length  Slot  Name   Signature
   0      34      0    this       Lscala/actors/remote/DelegateActor;


public void sessionMap_$eq(scala.collection.mutable.HashMap);
  Code:
   Stack=2, Locals=2, Args_size=2
   0:	aload_0
   1:	aload_1
   2:	putfield	#102; //Field sessionMap:Lscala/collection/mutable/HashMap;
   5:	return
  LineNumberTable: 
   line 122: 0

  Signature: length = 0x2
   00 FFFFFF97 

public scala.collection.mutable.HashMap sessionMap();
  Code:
   Stack=1, Locals=1, Args_size=1
   0:	aload_0
   1:	getfield	#102; //Field sessionMap:Lscala/collection/mutable/HashMap;
   4:	areturn
  LineNumberTable: 
   line 122: 0

  Signature: length = 0x2
   00 FFFFFF99 

public void channelMap_$eq(scala.collection.mutable.HashMap);
  Code:
   Stack=2, Locals=2, Args_size=2
   0:	aload_0
   1:	aload_1
   2:	putfield	#100; //Field channelMap:Lscala/collection/mutable/HashMap;
   5:	return
  LineNumberTable: 
   line 121: 0

  Signature: length = 0x2
   00 FFFFFF9B 

public scala.collection.mutable.HashMap channelMap();
  Code:
   Stack=1, Locals=1, Args_size=1
   0:	aload_0
   1:	getfield	#100; //Field channelMap:Lscala/collection/mutable/HashMap;
   4:	areturn
  LineNumberTable: 
   line 121: 0

  Signature: length = 0x2
   00 FFFFFF9C 

public scala.runtime.Nothing$ protected$exit(scala.actors.remote.DelegateActor);
  Code:
   Stack=1, Locals=2, Args_size=2
   0:	aload_1
   1:	invokeinterface	#162,  1; //InterfaceMethod scala/actors/Actor.exit:()Lscala/runtime/Nothing$;
   6:	areturn
  LineNumberTable: 
   line 158: 0


public scala.actors.OutputChannel protected$sender(scala.actors.remote.DelegateActor);
  Code:
   Stack=1, Locals=2, Args_size=2
   0:	aload_1
   1:	invokeinterface	#170,  1; //InterfaceMethod scala/actors/ReplyReactor.sender:()Lscala/actors/OutputChannel;
   6:	areturn
  LineNumberTable: 
   line 128: 0

  Signature: length = 0x2
   00 FFFFFFAB 

public void exiting_$eq(boolean);
  Code:
   Stack=2, Locals=2, Args_size=2
   0:	aload_0
   1:	iload_1
   2:	putfield	#175; //Field exiting:Z
   5:	return
  LineNumberTable: 
   line 120: 0


public boolean exiting();
  Code:
   Stack=1, Locals=1, Args_size=1
   0:	aload_0
   1:	getfield	#175; //Field exiting:Z
   4:	ireturn
  LineNumberTable: 
   line 120: 0


public void terminated();
  Code:
   Stack=1, Locals=1, Args_size=1
   0:	aload_0
   1:	invokestatic	#179; //Method scala/actors/Reactor$class.terminated:(Lscala/actors/Reactor;)V
   4:	return
  LineNumberTable: 
   line 120: 0


public void seq(scala.Function0, scala.Function0);
  Code:
   Stack=3, Locals=3, Args_size=3
   0:	aload_0
   1:	aload_1
   2:	aload_2
   3:	invokestatic	#184; //Method scala/actors/Reactor$class.seq:(Lscala/actors/Reactor;Lscala/Function0;Lscala/Function0;)V
   6:	return
  LineNumberTable: 
   line 120: 0

  LocalVariableTable: 
   Start  Length  Slot  Name   Signature
   0      7      0    this       Lscala/actors/remote/DelegateActor;
   0      7      1    first       Lscala/Function0;
   0      7      2    next       Lscala/Function0;


public void drainSendBuffer(scala.actors.MQueue);
  Code:
   Stack=2, Locals=2, Args_size=2
   0:	aload_0
   1:	aload_1
   2:	invokestatic	#191; //Method scala/actors/Reactor$class.drainSendBuffer:(Lscala/actors/Reactor;Lscala/actors/MQueue;)V
   5:	return
  LineNumberTable: 
   line 120: 0

  LocalVariableTable: 
   Start  Length  Slot  Name   Signature
   0      6      0    this       Lscala/actors/remote/DelegateActor;
   0      6      1    mbox       Lscala/actors/MQueue;


public scala.actors.Actor receiver();
  Code:
   Stack=1, Locals=1, Args_size=1
   0:	aload_0
   1:	invokestatic	#196; //Method scala/actors/Reactor$class.receiver:(Lscala/actors/Reactor;)Lscala/actors/Actor;
   4:	areturn
  LineNumberTable: 
   line 120: 0


public void send(java.lang.Object, scala.actors.OutputChannel);
  Code:
   Stack=3, Locals=3, Args_size=3
   0:	aload_0
   1:	aload_1
   2:	aload_2
   3:	invokestatic	#201; //Method scala/actors/Reactor$class.send:(Lscala/actors/Reactor;Ljava/lang/Object;Lscala/actors/OutputChannel;)V
   6:	return
  LineNumberTable: 
   line 120: 0

  LocalVariableTable: 
   Start  Length  Slot  Name   Signature
   0      7      0    this       Lscala/actors/remote/DelegateActor;
   0      7      1    msg       Ljava/lang/Object;
   0      7      2    replyTo       Lscala/actors/OutputChannel;


public int mailboxSize();
  Code:
   Stack=1, Locals=1, Args_size=1
   0:	aload_0
   1:	invokestatic	#208; //Method scala/actors/Reactor$class.mailboxSize:(Lscala/actors/Reactor;)I
   4:	ireturn
  LineNumberTable: 
   line 120: 0


public scala.PartialFunction exceptionHandler();
  Code:
   Stack=1, Locals=1, Args_size=1
   0:	aload_0
   1:	invokestatic	#213; //Method scala/actors/Reactor$class.exceptionHandler:(Lscala/actors/Reactor;)Lscala/PartialFunction;
   4:	areturn
  LineNumberTable: 
   line 120: 0


public void scala$actors$Reactor$_setter_$waitingForNone_$eq(scala.Function1);
  Code:
   Stack=2, Locals=2, Args_size=2
   0:	aload_0
   1:	aload_1
   2:	putfield	#217; //Field waitingForNone:Lscala/Function1;
   5:	return
  LineNumberTable: 
   line 120: 0


public void scala$actors$Reactor$_setter_$sendBuffer_$eq(scala.collection.mutable.Queue);
  Code:
   Stack=2, Locals=2, Args_size=2
   0:	aload_0
   1:	aload_1
   2:	putfield	#221; //Field sendBuffer:Lscala/collection/mutable/Queue;
   5:	return
  LineNumberTable: 
   line 120: 0


public void scala$actors$Reactor$_setter_$mailbox_$eq(scala.actors.MQueue);
  Code:
   Stack=2, Locals=2, Args_size=2
   0:	aload_0
   1:	aload_1
   2:	putfield	#224; //Field mailbox:Lscala/actors/MQueue;
   5:	return
  LineNumberTable: 
   line 120: 0


public void kill_$eq(scala.Function0);
  Code:
   Stack=2, Locals=2, Args_size=2
   0:	aload_0
   1:	aload_1
   2:	putfield	#227; //Field kill:Lscala/Function0;
   5:	return
  LineNumberTable: 
   line 120: 0


public scala.Function0 kill();
  Code:
   Stack=1, Locals=1, Args_size=1
   0:	aload_0
   1:	getfield	#227; //Field kill:Lscala/Function0;
   4:	areturn
  LineNumberTable: 
   line 120: 0


public void waitingFor_$eq(scala.Function1);
  Code:
   Stack=2, Locals=2, Args_size=2
   0:	aload_0
   1:	aload_1
   2:	putfield	#231; //Field waitingFor:Lscala/Function1;
   5:	return
  LineNumberTable: 
   line 120: 0


public scala.Function1 waitingFor();
  Code:
   Stack=1, Locals=1, Args_size=1
   0:	aload_0
   1:	getfield	#231; //Field waitingFor:Lscala/Function1;
   4:	areturn
  LineNumberTable: 
   line 120: 0


public scala.Function1 waitingForNone();
  Code:
   Stack=1, Locals=1, Args_size=1
   0:	aload_0
   1:	getfield	#217; //Field waitingForNone:Lscala/Function1;
   4:	areturn
  LineNumberTable: 
   line 120: 0


public void continuation_$eq(scala.PartialFunction);
  Code:
   Stack=2, Locals=2, Args_size=2
   0:	aload_0
   1:	aload_1
   2:	putfield	#236; //Field continuation:Lscala/PartialFunction;
   5:	return
  LineNumberTable: 
   line 120: 0


public scala.PartialFunction continuation();
  Code:
   Stack=1, Locals=1, Args_size=1
   0:	aload_0
   1:	getfield	#236; //Field continuation:Lscala/PartialFunction;
   4:	areturn
  LineNumberTable: 
   line 120: 0


public scala.collection.mutable.Queue sendBuffer();
  Code:
   Stack=1, Locals=1, Args_size=1
   0:	aload_0
   1:	getfield	#221; //Field sendBuffer:Lscala/collection/mutable/Queue;
   4:	areturn
  LineNumberTable: 
   line 120: 0


public scala.actors.MQueue mailbox();
  Code:
   Stack=1, Locals=1, Args_size=1
   0:	aload_0
   1:	getfield	#224; //Field mailbox:Lscala/actors/MQueue;
   4:	areturn
  LineNumberTable: 
   line 120: 0


public void searchMailbox(scala.actors.MQueue, scala.Function1, boolean);
  Code:
   Stack=4, Locals=4, Args_size=4
   0:	aload_0
   1:	aload_1
   2:	aload_2
   3:	iload_3
   4:	invokestatic	#243; //Method scala/actors/ReplyReactor$class.searchMailbox:(Lscala/actors/ReplyReactor;Lscala/actors/MQueue;Lscala/Function1;Z)V
   7:	return
  LineNumberTable: 
   line 120: 0

  LocalVariableTable: 
   Start  Length  Slot  Name   Signature
   0      8      0    this       Lscala/actors/remote/DelegateActor;
   0      8      1    startMbox       Lscala/actors/MQueue;
   0      8      2    handlesMessage       Lscala/Function1;
   0      8      3    resumeOnSameThread       Z


public void forward(java.lang.Object);
  Code:
   Stack=2, Locals=2, Args_size=2
   0:	aload_0
   1:	aload_1
   2:	invokestatic	#251; //Method scala/actors/ReplyReactor$class.forward:(Lscala/actors/ReplyReactor;Ljava/lang/Object;)V
   5:	return
  LineNumberTable: 
   line 120: 0

  LocalVariableTable: 
   Start  Length  Slot  Name   Signature
   0      6      0    this       Lscala/actors/remote/DelegateActor;
   0      6      1    msg       Ljava/lang/Object;


public void $bang(java.lang.Object);
  Code:
   Stack=2, Locals=2, Args_size=2
   0:	aload_0
   1:	aload_1
   2:	invokestatic	#254; //Method scala/actors/ReplyReactor$class.$bang:(Lscala/actors/ReplyReactor;Ljava/lang/Object;)V
   5:	return
  LineNumberTable: 
   line 120: 0

  LocalVariableTable: 
   Start  Length  Slot  Name   Signature
   0      6      0    this       Lscala/actors/remote/DelegateActor;
   0      6      1    msg       Ljava/lang/Object;


public void reply(java.lang.Object);
  Code:
   Stack=2, Locals=2, Args_size=2
   0:	aload_0
   1:	aload_1
   2:	invokestatic	#257; //Method scala/actors/ReplyReactor$class.reply:(Lscala/actors/ReplyReactor;Ljava/lang/Object;)V
   5:	return
  LineNumberTable: 
   line 120: 0

  LocalVariableTable: 
   Start  Length  Slot  Name   Signature
   0      6      0    this       Lscala/actors/remote/DelegateActor;
   0      6      1    msg       Ljava/lang/Object;


public scala.actors.OutputChannel sender();
  Code:
   Stack=1, Locals=1, Args_size=1
   0:	aload_0
   1:	invokestatic	#260; //Method scala/actors/ReplyReactor$class.sender:(Lscala/actors/ReplyReactor;)Lscala/actors/OutputChannel;
   4:	areturn
  LineNumberTable: 
   line 120: 0


public void senders_$eq(scala.collection.immutable.List);
  Code:
   Stack=2, Locals=2, Args_size=2
   0:	aload_0
   1:	aload_1
   2:	putfield	#264; //Field senders:Lscala/collection/immutable/List;
   5:	return
  LineNumberTable: 
   line 120: 0


public scala.collection.immutable.List senders();
  Code:
   Stack=1, Locals=1, Args_size=1
   0:	aload_0
   1:	getfield	#264; //Field senders:Lscala/collection/immutable/List;
   4:	areturn
  LineNumberTable: 
   line 120: 0


public scala.actors.Future $bang$bang(java.lang.Object);
  Code:
   Stack=2, Locals=2, Args_size=2
   0:	aload_0
   1:	aload_1
   2:	invokestatic	#268; //Method scala/actors/ReplyableActor$class.$bang$bang:(Lscala/actors/ReplyableActor;Ljava/lang/Object;)Lscala/actors/Future;
   5:	areturn
  LineNumberTable: 
   line 120: 0

  LocalVariableTable: 
   Start  Length  Slot  Name   Signature
   0      6      0    this       Lscala/actors/remote/DelegateActor;
   0      6      1    msg       Ljava/lang/Object;


public scala.actors.Future $bang$bang(java.lang.Object, scala.PartialFunction);
  Code:
   Stack=3, Locals=3, Args_size=3
   0:	aload_0
   1:	aload_1
   2:	aload_2
   3:	invokestatic	#271; //Method scala/actors/ReplyableActor$class.$bang$bang:(Lscala/actors/ReplyableActor;Ljava/lang/Object;Lscala/PartialFunction;)Lscala/actors/Future;
   6:	areturn
  LineNumberTable: 
   line 120: 0

  LocalVariableTable: 
   Start  Length  Slot  Name   Signature
   0      7      0    this       Lscala/actors/remote/DelegateActor;
   0      7      1    msg       Ljava/lang/Object;
   0      7      2    f       Lscala/PartialFunction;


public scala.Option $bang$qmark(long, java.lang.Object);
  Code:
   Stack=4, Locals=4, Args_size=3
   0:	aload_0
   1:	lload_1
   2:	aload_3
   3:	invokestatic	#276; //Method scala/actors/ReplyableActor$class.$bang$qmark:(Lscala/actors/ReplyableActor;JLjava/lang/Object;)Lscala/Option;
   6:	areturn
  LineNumberTable: 
   line 120: 0

  LocalVariableTable: 
   Start  Length  Slot  Name   Signature
   0      7      0    this       Lscala/actors/remote/DelegateActor;
   0      7      1    msec       J
   0      7      3    msg       Ljava/lang/Object;


public java.lang.Object $bang$qmark(java.lang.Object);
  Code:
   Stack=2, Locals=2, Args_size=2
   0:	aload_0
   1:	aload_1
   2:	invokestatic	#282; //Method scala/actors/ReplyableActor$class.$bang$qmark:(Lscala/actors/ReplyableActor;Ljava/lang/Object;)Ljava/lang/Object;
   5:	areturn
  LineNumberTable: 
   line 120: 0

  LocalVariableTable: 
   Start  Length  Slot  Name   Signature
   0      6      0    this       Lscala/actors/remote/DelegateActor;
   0      6      1    msg       Ljava/lang/Object;


public void onTerminate(scala.Function0);
  Code:
   Stack=2, Locals=2, Args_size=2
   0:	aload_0
   1:	aload_1
   2:	invokestatic	#286; //Method scala/actors/Actor$class.onTerminate:(Lscala/actors/Actor;Lscala/Function0;)V
   5:	return
  LineNumberTable: 
   line 120: 0

  LocalVariableTable: 
   Start  Length  Slot  Name   Signature
   0      6      0    this       Lscala/actors/remote/DelegateActor;
   0      6      1    f       Lscala/Function0;


public void exit(scala.actors.AbstractActor, java.lang.Object);
  Code:
   Stack=3, Locals=3, Args_size=3
   0:	aload_0
   1:	aload_1
   2:	aload_2
   3:	invokestatic	#290; //Method scala/actors/Actor$class.exit:(Lscala/actors/Actor;Lscala/actors/AbstractActor;Ljava/lang/Object;)V
   6:	return
  LineNumberTable: 
   line 120: 0

  LocalVariableTable: 
   Start  Length  Slot  Name   Signature
   0      7      0    this       Lscala/actors/remote/DelegateActor;
   0      7      1    from       Lscala/actors/AbstractActor;
   0      7      2    reason       Ljava/lang/Object;


public void exitLinked(java.lang.Object);
  Code:
   Stack=2, Locals=2, Args_size=2
   0:	aload_0
   1:	aload_1
   2:	invokestatic	#297; //Method scala/actors/Actor$class.exitLinked:(Lscala/actors/Actor;Ljava/lang/Object;)V
   5:	return
  LineNumberTable: 
   line 120: 0

  LocalVariableTable: 
   Start  Length  Slot  Name   Signature
   0      6      0    this       Lscala/actors/remote/DelegateActor;
   0      6      1    reason       Ljava/lang/Object;


public void exitLinked();
  Code:
   Stack=1, Locals=1, Args_size=1
   0:	aload_0
   1:	invokestatic	#299; //Method scala/actors/Actor$class.exitLinked:(Lscala/actors/Actor;)V
   4:	return
  LineNumberTable: 
   line 120: 0


public scala.runtime.Nothing$ exit();
  Code:
   Stack=1, Locals=1, Args_size=1
   0:	aload_0
   1:	invokestatic	#302; //Method scala/actors/Actor$class.exit:(Lscala/actors/Actor;)Lscala/runtime/Nothing$;
   4:	areturn
  LineNumberTable: 
   line 120: 0


public scala.runtime.Nothing$ exit(java.lang.Object);
  Code:
   Stack=2, Locals=2, Args_size=2
   0:	aload_0
   1:	aload_1
   2:	invokestatic	#306; //Method scala/actors/Actor$class.exit:(Lscala/actors/Actor;Ljava/lang/Object;)Lscala/runtime/Nothing$;
   5:	areturn
  LineNumberTable: 
   line 120: 0

  LocalVariableTable: 
   Start  Length  Slot  Name   Signature
   0      6      0    this       Lscala/actors/remote/DelegateActor;
   0      6      1    reason       Ljava/lang/Object;


public void unlinkFrom(scala.actors.AbstractActor);
  Code:
   Stack=2, Locals=2, Args_size=2
   0:	aload_0
   1:	aload_1
   2:	invokestatic	#310; //Method scala/actors/Actor$class.unlinkFrom:(Lscala/actors/Actor;Lscala/actors/AbstractActor;)V
   5:	return
  LineNumberTable: 
   line 120: 0

  LocalVariableTable: 
   Start  Length  Slot  Name   Signature
   0      6      0    this       Lscala/actors/remote/DelegateActor;
   0      6      1    from       Lscala/actors/AbstractActor;


public void unlink(scala.actors.AbstractActor);
  Code:
   Stack=2, Locals=2, Args_size=2
   0:	aload_0
   1:	aload_1
   2:	invokestatic	#313; //Method scala/actors/Actor$class.unlink:(Lscala/actors/Actor;Lscala/actors/AbstractActor;)V
   5:	return
  LineNumberTable: 
   line 120: 0

  LocalVariableTable: 
   Start  Length  Slot  Name   Signature
   0      6      0    this       Lscala/actors/remote/DelegateActor;
   0      6      1    from       Lscala/actors/AbstractActor;


public void linkTo(scala.actors.AbstractActor);
  Code:
   Stack=2, Locals=2, Args_size=2
   0:	aload_0
   1:	aload_1
   2:	invokestatic	#316; //Method scala/actors/Actor$class.linkTo:(Lscala/actors/Actor;Lscala/actors/AbstractActor;)V
   5:	return
  LineNumberTable: 
   line 120: 0

  LocalVariableTable: 
   Start  Length  Slot  Name   Signature
   0      6      0    this       Lscala/actors/remote/DelegateActor;
   0      6      1    to       Lscala/actors/AbstractActor;


public scala.actors.Actor link(scala.Function0);
  Code:
   Stack=2, Locals=2, Args_size=2
   0:	aload_0
   1:	aload_1
   2:	invokestatic	#322; //Method scala/actors/Actor$class.link:(Lscala/actors/Actor;Lscala/Function0;)Lscala/actors/Actor;
   5:	areturn
  LineNumberTable: 
   line 120: 0

  LocalVariableTable: 
   Start  Length  Slot  Name   Signature
   0      6      0    this       Lscala/actors/remote/DelegateActor;
   0      6      1    body       Lscala/Function0;


public scala.actors.AbstractActor link(scala.actors.AbstractActor);
  Code:
   Stack=2, Locals=2, Args_size=2
   0:	aload_0
   1:	aload_1
   2:	invokestatic	#327; //Method scala/actors/Actor$class.link:(Lscala/actors/Actor;Lscala/actors/AbstractActor;)Lscala/actors/AbstractActor;
   5:	areturn
  LineNumberTable: 
   line 120: 0

  LocalVariableTable: 
   Start  Length  Slot  Name   Signature
   0      6      0    this       Lscala/actors/remote/DelegateActor;
   0      6      1    to       Lscala/actors/AbstractActor;


public scala.actors.Actor start();
  Code:
   Stack=1, Locals=1, Args_size=1
   0:	aload_0
   1:	invokestatic	#330; //Method scala/actors/Actor$class.start:(Lscala/actors/Actor;)Lscala/actors/Actor;
   4:	areturn
  LineNumberTable: 
   line 120: 0


public void scheduleActor(scala.PartialFunction, java.lang.Object);
  Code:
   Stack=3, Locals=3, Args_size=3
   0:	aload_0
   1:	aload_1
   2:	aload_2
   3:	invokestatic	#335; //Method scala/actors/Actor$class.scheduleActor:(Lscala/actors/Actor;Lscala/PartialFunction;Ljava/lang/Object;)V
   6:	return
  LineNumberTable: 
   line 120: 0

  LocalVariableTable: 
   Start  Length  Slot  Name   Signature
   0      7      0    this       Lscala/actors/remote/DelegateActor;
   0      7      1    f       Lscala/PartialFunction;
   0      7      2    msg       Ljava/lang/Object;


public java.lang.Object $qmark();
  Code:
   Stack=1, Locals=1, Args_size=1
   0:	aload_0
   1:	invokestatic	#340; //Method scala/actors/Actor$class.$qmark:(Lscala/actors/Actor;)Ljava/lang/Object;
   4:	areturn
  LineNumberTable: 
   line 120: 0


public scala.runtime.Nothing$ reactWithin(long, scala.PartialFunction);
  Code:
   Stack=4, Locals=4, Args_size=3
   0:	aload_0
   1:	lload_1
   2:	aload_3
   3:	invokestatic	#345; //Method scala/actors/Actor$class.reactWithin:(Lscala/actors/Actor;JLscala/PartialFunction;)Lscala/runtime/Nothing$;
   6:	areturn
  LineNumberTable: 
   line 120: 0

  LocalVariableTable: 
   Start  Length  Slot  Name   Signature
   0      7      0    this       Lscala/actors/remote/DelegateActor;
   0      7      1    msec       J
   0      7      3    f       Lscala/PartialFunction;


public scala.runtime.Nothing$ react(scala.PartialFunction);
  Code:
   Stack=2, Locals=2, Args_size=2
   0:	aload_0
   1:	aload_1
   2:	invokestatic	#350; //Method scala/actors/Actor$class.react:(Lscala/actors/Actor;Lscala/PartialFunction;)Lscala/runtime/Nothing$;
   5:	areturn
  LineNumberTable: 
   line 120: 0

  LocalVariableTable: 
   Start  Length  Slot  Name   Signature
   0      6      0    this       Lscala/actors/remote/DelegateActor;
   0      6      1    f       Lscala/PartialFunction;


public java.lang.Object receiveWithin(long, scala.PartialFunction);
  Code:
   Stack=4, Locals=4, Args_size=3
   0:	aload_0
   1:	lload_1
   2:	aload_3
   3:	invokestatic	#355; //Method scala/actors/Actor$class.receiveWithin:(Lscala/actors/Actor;JLscala/PartialFunction;)Ljava/lang/Object;
   6:	areturn
  LineNumberTable: 
   line 120: 0

  LocalVariableTable: 
   Start  Length  Slot  Name   Signature
   0      7      0    this       Lscala/actors/remote/DelegateActor;
   0      7      1    msec       J
   0      7      3    f       Lscala/PartialFunction;


public java.lang.Object receive(scala.PartialFunction);
  Code:
   Stack=2, Locals=2, Args_size=2
   0:	aload_0
   1:	aload_1
   2:	invokestatic	#360; //Method scala/actors/Actor$class.receive:(Lscala/actors/Actor;Lscala/PartialFunction;)Ljava/lang/Object;
   5:	areturn
  LineNumberTable: 
   line 120: 0

  LocalVariableTable: 
   Start  Length  Slot  Name   Signature
   0      6      0    this       Lscala/actors/remote/DelegateActor;
   0      6      1    f       Lscala/PartialFunction;


public void resumeReceiver(scala.Tuple2, boolean);
  Code:
   Stack=3, Locals=3, Args_size=3
   0:	aload_0
   1:	aload_1
   2:	iload_2
   3:	invokestatic	#365; //Method scala/actors/Actor$class.resumeReceiver:(Lscala/actors/Actor;Lscala/Tuple2;Z)V
   6:	return
  LineNumberTable: 
   line 120: 0

  LocalVariableTable: 
   Start  Length  Slot  Name   Signature
   0      7      0    this       Lscala/actors/remote/DelegateActor;
   0      7      1    item       Lscala/Tuple2;
   0      7      2    onSameThread       Z


public java.lang.Runnable makeReaction(scala.Function0);
  Code:
   Stack=2, Locals=2, Args_size=2
   0:	aload_0
   1:	aload_1
   2:	invokestatic	#373; //Method scala/actors/Actor$class.makeReaction:(Lscala/actors/Actor;Lscala/Function0;)Ljava/lang/Runnable;
   5:	areturn
  LineNumberTable: 
   line 120: 0

  LocalVariableTable: 
   Start  Length  Slot  Name   Signature
   0      6      0    this       Lscala/actors/remote/DelegateActor;
   0      6      1    fun       Lscala/Function0;


public scala.Function0 startSearch(java.lang.Object, scala.actors.OutputChannel, scala.Function1);
  Code:
   Stack=4, Locals=4, Args_size=4
   0:	aload_0
   1:	aload_1
   2:	aload_2
   3:	aload_3
   4:	invokestatic	#379; //Method scala/actors/Actor$class.startSearch:(Lscala/actors/Actor;Ljava/lang/Object;Lscala/actors/OutputChannel;Lscala/Function1;)Lscala/Function0;
   7:	areturn
  LineNumberTable: 
   line 120: 0

  LocalVariableTable: 
   Start  Length  Slot  Name   Signature
   0      8      0    this       Lscala/actors/remote/DelegateActor;
   0      8      1    msg       Ljava/lang/Object;
   0      8      2    replyTo       Lscala/actors/OutputChannel;
   0      8      3    handler       Lscala/Function1;


public scala.actors.IScheduler scheduler();
  Code:
   Stack=1, Locals=1, Args_size=1
   0:	aload_0
   1:	invokestatic	#385; //Method scala/actors/Actor$class.scheduler:(Lscala/actors/Actor;)Lscala/actors/IScheduler;
   4:	areturn
  LineNumberTable: 
   line 120: 0


public final void scala$actors$Actor$$super$resumeReceiver(scala.Tuple2, boolean);
  Code:
   Stack=3, Locals=3, Args_size=3
   0:	aload_0
   1:	aload_1
   2:	iload_2
   3:	invokestatic	#389; //Method scala/actors/ReplyReactor$class.resumeReceiver:(Lscala/actors/ReplyReactor;Lscala/Tuple2;Z)V
   6:	return
  LineNumberTable: 
   line 120: 0

  LocalVariableTable: 
   Start  Length  Slot  Name   Signature
   0      7      0    this       Lscala/actors/remote/DelegateActor;
   0      7      1    item       Lscala/Tuple2;
   0      7      2    onSameThread       Z


public final scala.Function0 scala$actors$Actor$$super$startSearch(java.lang.Object, scala.actors.OutputChannel, scala.Function1);
  Code:
   Stack=4, Locals=4, Args_size=4
   0:	aload_0
   1:	aload_1
   2:	aload_2
   3:	aload_3
   4:	invokestatic	#393; //Method scala/actors/Reactor$class.startSearch:(Lscala/actors/Reactor;Ljava/lang/Object;Lscala/actors/OutputChannel;Lscala/Function1;)Lscala/Function0;
   7:	areturn
  LineNumberTable: 
   line 120: 0

  LocalVariableTable: 
   Start  Length  Slot  Name   Signature
   0      8      0    this       Lscala/actors/remote/DelegateActor;
   0      8      1    msg       Ljava/lang/Object;
   0      8      2    replyTo       Lscala/actors/OutputChannel;
   0      8      3    handler       Lscala/Function1;


public void shouldExit_$eq(boolean);
  Code:
   Stack=2, Locals=2, Args_size=2
   0:	aload_0
   1:	iload_1
   2:	putfield	#396; //Field shouldExit:Z
   5:	return
  LineNumberTable: 
   line 120: 0


public boolean shouldExit();
  Code:
   Stack=1, Locals=1, Args_size=1
   0:	aload_0
   1:	getfield	#396; //Field shouldExit:Z
   4:	ireturn
  LineNumberTable: 
   line 120: 0


public void exitReason_$eq(java.lang.Object);
  Code:
   Stack=2, Locals=2, Args_size=2
   0:	aload_0
   1:	aload_1
   2:	putfield	#399; //Field exitReason:Ljava/lang/Object;
   5:	return
  LineNumberTable: 
   line 120: 0


public java.lang.Object exitReason();
  Code:
   Stack=1, Locals=1, Args_size=1
   0:	aload_0
   1:	getfield	#399; //Field exitReason:Ljava/lang/Object;
   4:	areturn
  LineNumberTable: 
   line 120: 0


public void trapExit_$eq(boolean);
  Code:
   Stack=2, Locals=2, Args_size=2
   0:	aload_0
   1:	iload_1
   2:	putfield	#402; //Field trapExit:Z
   5:	return
  LineNumberTable: 
   line 120: 0


public boolean trapExit();
  Code:
   Stack=1, Locals=1, Args_size=1
   0:	aload_0
   1:	getfield	#402; //Field trapExit:Z
   4:	ireturn
  LineNumberTable: 
   line 120: 0


public void links_$eq(scala.collection.immutable.List);
  Code:
   Stack=2, Locals=2, Args_size=2
   0:	aload_0
   1:	aload_1
   2:	putfield	#405; //Field links:Lscala/collection/immutable/List;
   5:	return
  LineNumberTable: 
   line 120: 0


public scala.collection.immutable.List links();
  Code:
   Stack=1, Locals=1, Args_size=1
   0:	aload_0
   1:	getfield	#405; //Field links:Lscala/collection/immutable/List;
   4:	areturn
  LineNumberTable: 
   line 120: 0


public final scala.actors.Actor$blocker$ scala$actors$Actor$$blocker();
  Code:
   Stack=4, Locals=1, Args_size=1
   0:	aload_0
   1:	getfield	#409; //Field scala$actors$Actor$$blocker$module:Lscala/actors/Actor$blocker$;
   4:	ifnonnull	19
   7:	aload_0
   8:	new	#411; //class scala/actors/Actor$blocker$
   11:	dup
   12:	aload_0
   13:	invokespecial	#413; //Method scala/actors/Actor$blocker$."<init>":(Lscala/actors/Actor;)V
   16:	putfield	#409; //Field scala$actors$Actor$$blocker$module:Lscala/actors/Actor$blocker$;
   19:	aload_0
   20:	getfield	#409; //Field scala$actors$Actor$$blocker$module:Lscala/actors/Actor$blocker$;
   23:	areturn
  LineNumberTable: 
   line 120: 0


public final void scala$actors$Actor$$onTimeout_$eq(scala.Option);
  Code:
   Stack=2, Locals=2, Args_size=2
   0:	aload_0
   1:	aload_1
   2:	putfield	#417; //Field scala$actors$Actor$$onTimeout:Lscala/Option;
   5:	return
  LineNumberTable: 
   line 120: 0


public final scala.Option scala$actors$Actor$$onTimeout();
  Code:
   Stack=1, Locals=1, Args_size=1
   0:	aload_0
   1:	getfield	#417; //Field scala$actors$Actor$$onTimeout:Lscala/Option;
   4:	areturn
  LineNumberTable: 
   line 120: 0


public final void scala$actors$Actor$$received_$eq(scala.Option);
  Code:
   Stack=2, Locals=2, Args_size=2
   0:	aload_0
   1:	aload_1
   2:	putfield	#421; //Field scala$actors$Actor$$received:Lscala/Option;
   5:	return
  LineNumberTable: 
   line 120: 0


public final scala.Option scala$actors$Actor$$received();
  Code:
   Stack=1, Locals=1, Args_size=1
   0:	aload_0
   1:	getfield	#421; //Field scala$actors$Actor$$received:Lscala/Option;
   4:	areturn
  LineNumberTable: 
   line 120: 0


public final void scala$actors$Actor$$isSuspended_$eq(boolean);
  Code:
   Stack=2, Locals=2, Args_size=2
   0:	aload_0
   1:	iload_1
   2:	putfield	#424; //Field scala$actors$Actor$$isSuspended:Z
   5:	return
  LineNumberTable: 
   line 120: 0


public final boolean scala$actors$Actor$$isSuspended();
  Code:
   Stack=1, Locals=1, Args_size=1
   0:	aload_0
   1:	getfield	#424; //Field scala$actors$Actor$$isSuspended:Z
   4:	ireturn
  LineNumberTable: 
   line 120: 0


}

