Compiled from "Proxy.scala"
public class scala.actors.remote.ExitFun extends java.lang.Object implements scala.Function2,scala.ScalaObject,java.io.Serializable
  SourceFile: "Proxy.scala"
  Signature: length = 0x2
   00 4C 
  ScalaSig: length = 0x17E
   05 00 3F 06 08 01 02 FFFFFF84 FFFFFF80 FFFFFF80 FFFFFF80 00 09 02 07 45
   78 69 74 46 75 6E 0A 02 03 04 01 06 72 65 6D 6F
   74 65 0A 02 05 06 01 06 61 63 74 6F 72 73 0A 01
   07 01 05 73 63 61 6C 61 03 00 13 04 00 0A 12 21
   10 02 0B 10 0D 01 0C 0A 02 0D 0E 01 04 6C 61 6E
   67 0A 01 0F 01 04 6A 61 76 61 09 02 11 0C 02 06
   4F 62 6A 65 63 74 10 05 13 14 16 1A 1E 0D 01 06
   09 02 15 06 02 09 46 75 6E 63 74 69 6F 6E 32 10
   02 17 18 0D 01 04 09 02 19 04 02 0D 41 62 73 74
   72 61 63 74 41 63 74 6F 72 10 02 1B 1C 0D 01 02
   09 02 1D 02 02 05 50 72 6F 78 79 10 02 13 1F 09
   02 20 06 02 04 55 6E 69 74 10 02 13 22 09 02 23
   06 02 0B 53 63 61 6C 61 4F 62 6A 65 63 74 08 08
   25 00 FFFFFF82 FFFFFF80 FFFFFFA0 FFFFFF80 04 26 01 06 72 65 61 73 6F 6E
   10 02 13 27 09 02 28 06 02 06 41 6E 79 52 65 66
   08 05 2A 00 FFFFFF84 00 2B 01 06 3C 69 6E 69 74 3E 14
   02 2C 2D 10 02 1B 00 08 05 25 29 FFFFFFC0 00 26 08 05
   2F 00 FFFFFF84 00 30 01 05 61 70 70 6C 79 14 03 1E 31
   33 08 05 32 2E FFFFFFC0 00 16 01 06 74 61 72 67 65 74
   08 05 34 2E FFFFFFC0 00 1A 01 07 63 72 65 61 74 6F 72
   08 05 36 00 FFFFFF84 20 37 01 08 74 6F 53 74 72 69 6E
   67 14 01 38 10 02 0B 39 09 02 3A 0C 02 06 53 74
   72 69 6E 67 28 02 00 3C 10 02 13 3D 09 02 3E 06
   02 0C 73 65 72 69 61 6C 69 7A 61 62 6C 65 
  minor version: 0
  major version: 49
  Constant pool:
const #1 = Asciz	SourceFile;
const #2 = Asciz	Proxy.scala;
const #3 = Asciz	reason;
const #4 = Asciz	Ljava/lang/Object;;
const #5 = Asciz	<init>;
const #6 = Asciz	(Ljava/lang/Object;)V;
const #7 = Asciz	Code;
const #8 = Asciz	LineNumberTable;
const #9 = Asciz	scala/actors/remote/ExitFun;
const #10 = class	#9;	//  scala/actors/remote/ExitFun
const #11 = NameAndType	#3:#4;//  reason:Ljava/lang/Object;
const #12 = Field	#10.#11;	//  scala/actors/remote/ExitFun.reason:Ljava/lang/Object;
const #13 = Asciz	java/lang/Object;
const #14 = class	#13;	//  java/lang/Object
const #15 = Asciz	()V;
const #16 = NameAndType	#5:#15;//  "<init>":()V
const #17 = Method	#14.#16;	//  java/lang/Object."<init>":()V
const #18 = Asciz	scala/Function2$class;
const #19 = class	#18;	//  scala/Function2$class
const #20 = Asciz	$init$;
const #21 = Asciz	(Lscala/Function2;)V;
const #22 = NameAndType	#20:#21;//  $init$:(Lscala/Function2;)V
const #23 = Method	#19.#22;	//  scala/Function2$class.$init$:(Lscala/Function2;)V
const #24 = Asciz	this;
const #25 = Asciz	Lscala/actors/remote/ExitFun;;
const #26 = Asciz	LocalVariableTable;
const #27 = Asciz	apply;
const #28 = Asciz	(Ljava/lang/Object;Ljava/lang/Object;)Ljava/lang/Object;;
const #29 = Asciz	scala/actors/AbstractActor;
const #30 = class	#29;	//  scala/actors/AbstractActor
const #31 = Asciz	scala/actors/remote/Proxy;
const #32 = class	#31;	//  scala/actors/remote/Proxy
const #33 = Asciz	(Lscala/actors/AbstractActor;Lscala/actors/remote/Proxy;)V;
const #34 = NameAndType	#27:#33;//  apply:(Lscala/actors/AbstractActor;Lscala/actors/remote/Proxy;)V
const #35 = Method	#10.#34;	//  scala/actors/remote/ExitFun.apply:(Lscala/actors/AbstractActor;Lscala/actors/remote/Proxy;)V
const #36 = Asciz	scala/runtime/BoxedUnit;
const #37 = class	#36;	//  scala/runtime/BoxedUnit
const #38 = Asciz	UNIT;
const #39 = Asciz	Lscala/runtime/BoxedUnit;;
const #40 = NameAndType	#38:#39;//  UNIT:Lscala/runtime/BoxedUnit;
const #41 = Field	#37.#40;	//  scala/runtime/BoxedUnit.UNIT:Lscala/runtime/BoxedUnit;
const #42 = Asciz	v1;
const #43 = Asciz	v2;
const #44 = Asciz	toString;
const #45 = Asciz	()Ljava/lang/String;;
const #46 = Asciz	scala/collection/mutable/StringBuilder;
const #47 = class	#46;	//  scala/collection/mutable/StringBuilder
const #48 = Method	#47.#16;	//  scala/collection/mutable/StringBuilder."<init>":()V
const #49 = Asciz	<ExitFun>(;
const #50 = String	#49;	//  <ExitFun>(
const #51 = Asciz	append;
const #52 = Asciz	(Ljava/lang/Object;)Lscala/collection/mutable/StringBuilder;;
const #53 = NameAndType	#51:#52;//  append:(Ljava/lang/Object;)Lscala/collection/mutable/StringBuilder;
const #54 = Method	#47.#53;	//  scala/collection/mutable/StringBuilder.append:(Ljava/lang/Object;)Lscala/collection/mutable/StringBuilder;
const #55 = NameAndType	#44:#45;//  toString:()Ljava/lang/String;
const #56 = Method	#14.#55;	//  java/lang/Object.toString:()Ljava/lang/String;
const #57 = Asciz	);
const #58 = String	#57;	//  )
const #59 = Method	#47.#55;	//  scala/collection/mutable/StringBuilder.toString:()Ljava/lang/String;
const #60 = Asciz	exit;
const #61 = Asciz	(Lscala/actors/AbstractActor;Ljava/lang/Object;)V;
const #62 = NameAndType	#60:#61;//  exit:(Lscala/actors/AbstractActor;Ljava/lang/Object;)V
const #63 = InterfaceMethod	#30.#62;	//  scala/actors/AbstractActor.exit:(Lscala/actors/AbstractActor;Ljava/lang/Object;)V
const #64 = Asciz	target;
const #65 = Asciz	Lscala/actors/AbstractActor;;
const #66 = Asciz	creator;
const #67 = Asciz	Lscala/actors/remote/Proxy;;
const #68 = Asciz	tuple;
const #69 = Asciz	()Lscala/Function1;;
const #70 = Asciz	(Lscala/Function2;)Lscala/Function1;;
const #71 = NameAndType	#68:#70;//  tuple:(Lscala/Function2;)Lscala/Function1;
const #72 = Method	#19.#71;	//  scala/Function2$class.tuple:(Lscala/Function2;)Lscala/Function1;
const #73 = Asciz	curry;
const #74 = NameAndType	#73:#70;//  curry:(Lscala/Function2;)Lscala/Function1;
const #75 = Method	#19.#74;	//  scala/Function2$class.curry:(Lscala/Function2;)Lscala/Function1;
const #76 = Asciz	Ljava/lang/Object;Lscala/Function2<Lscala/actors/AbstractActor;Lscala/actors/remote/Proxy;Ljava/lang/Object;>;Lscala/ScalaObject;;
const #77 = Asciz	Signature;
const #78 = Asciz	ScalaSig;
const #79 = Asciz	scala/Function2;
const #80 = class	#79;	//  scala/Function2
const #81 = Asciz	scala/ScalaObject;
const #82 = class	#81;	//  scala/ScalaObject
const #83 = Asciz	java/io/Serializable;
const #84 = class	#83;	//  java/io/Serializable

{
public scala.actors.remote.ExitFun(java.lang.Object);
  Code:
   Stack=2, Locals=2, Args_size=2
   0:	aload_0
   1:	aload_1
   2:	putfield	#12; //Field reason:Ljava/lang/Object;
   5:	aload_0
   6:	invokespecial	#17; //Method java/lang/Object."<init>":()V
   9:	aload_0
   10:	invokestatic	#23; //Method scala/Function2$class.$init$:(Lscala/Function2;)V
   13:	return
  LineNumberTable: 
   line 107: 0

  LocalVariableTable: 
   Start  Length  Slot  Name   Signature
   0      14      0    this       Lscala/actors/remote/ExitFun;
   0      14      1    reason       Ljava/lang/Object;


public java.lang.Object apply(java.lang.Object, java.lang.Object);
  Code:
   Stack=3, Locals=3, Args_size=3
   0:	aload_0
   1:	aload_1
   2:	checkcast	#30; //class scala/actors/AbstractActor
   5:	aload_2
   6:	checkcast	#32; //class scala/actors/remote/Proxy
   9:	invokevirtual	#35; //Method apply:(Lscala/actors/AbstractActor;Lscala/actors/remote/Proxy;)V
   12:	getstatic	#41; //Field scala/runtime/BoxedUnit.UNIT:Lscala/runtime/BoxedUnit;
   15:	areturn
  LineNumberTable: 
   line 107: 0

  LocalVariableTable: 
   Start  Length  Slot  Name   Signature
   0      16      0    this       Lscala/actors/remote/ExitFun;
   0      16      1    v1       Ljava/lang/Object;
   0      16      2    v2       Ljava/lang/Object;


public java.lang.String toString();
  Code:
   Stack=2, Locals=1, Args_size=1
   0:	new	#47; //class scala/collection/mutable/StringBuilder
   3:	dup
   4:	invokespecial	#48; //Method scala/collection/mutable/StringBuilder."<init>":()V
   7:	ldc	#50; //String <ExitFun>(
   9:	invokevirtual	#54; //Method scala/collection/mutable/StringBuilder.append:(Ljava/lang/Object;)Lscala/collection/mutable/StringBuilder;
   12:	aload_0
   13:	getfield	#12; //Field reason:Ljava/lang/Object;
   16:	invokevirtual	#56; //Method java/lang/Object.toString:()Ljava/lang/String;
   19:	invokevirtual	#54; //Method scala/collection/mutable/StringBuilder.append:(Ljava/lang/Object;)Lscala/collection/mutable/StringBuilder;
   22:	ldc	#58; //String )
   24:	invokevirtual	#54; //Method scala/collection/mutable/StringBuilder.append:(Ljava/lang/Object;)Lscala/collection/mutable/StringBuilder;
   27:	invokevirtual	#59; //Method scala/collection/mutable/StringBuilder.toString:()Ljava/lang/String;
   30:	areturn
  LineNumberTable: 
   line 112: 0


public void apply(scala.actors.AbstractActor, scala.actors.remote.Proxy);
  Code:
   Stack=3, Locals=3, Args_size=3
   0:	aload_1
   1:	aload_2
   2:	aload_0
   3:	getfield	#12; //Field reason:Ljava/lang/Object;
   6:	invokeinterface	#63,  3; //InterfaceMethod scala/actors/AbstractActor.exit:(Lscala/actors/AbstractActor;Ljava/lang/Object;)V
   11:	return
  LineNumberTable: 
   line 109: 0

  LocalVariableTable: 
   Start  Length  Slot  Name   Signature
   0      12      0    this       Lscala/actors/remote/ExitFun;
   0      12      1    target       Lscala/actors/AbstractActor;
   0      12      2    creator       Lscala/actors/remote/Proxy;


public scala.Function1 tuple();
  Code:
   Stack=1, Locals=1, Args_size=1
   0:	aload_0
   1:	invokestatic	#72; //Method scala/Function2$class.tuple:(Lscala/Function2;)Lscala/Function1;
   4:	areturn
  LineNumberTable: 
   line 107: 0


public scala.Function1 curry();
  Code:
   Stack=1, Locals=1, Args_size=1
   0:	aload_0
   1:	invokestatic	#75; //Method scala/Function2$class.curry:(Lscala/Function2;)Lscala/Function1;
   4:	areturn
  LineNumberTable: 
   line 107: 0


}

