Compiled from "Proxy.scala"
public class scala.actors.remote.ExitFun extends java.lang.Object implements scala.Function2,scala.ScalaObject,java.io.Serializable
  SourceFile: "Proxy.scala"
  Signature: length = 0x2
   00 50 
  ScalaSig: length = 0x17E
   05 00 3F 06 08 01 02 FFFFFF84 FFFFFF80 FFFFFF80 FFFFFF80 00 09 02 07 45
   78 69 74 46 75 6E 0A 02 03 04 01 06 72 65 6D 6F
   74 65 0A 02 05 06 01 06 61 63 74 6F 72 73 0A 01
   07 01 05 73 63 61 6C 61 03 00 13 04 00 0A 12 21
   10 02 0B 10 0D 01 0C 0A 02 0D 0E 01 04 6C 61 6E
   67 0A 01 0F 01 04 6A 61 76 61 09 02 11 0C 02 06
   4F 62 6A 65 63 74 10 05 13 14 16 1A 1E 0D 01 06
   09 02 15 06 02 09 46 75 6E 63 74 69 6F 6E 32 10
   02 17 18 0D 01 04 09 02 19 04 02 0D 41 62 73 74
   72 61 63 74 41 63 74 6F 72 10 02 1B 1C 0D 01 02
   09 02 1D 02 02 05 50 72 6F 78 79 10 02 13 1F 09
   02 20 06 02 04 55 6E 69 74 10 02 13 22 09 02 23
   06 02 0B 53 63 61 6C 61 4F 62 6A 65 63 74 08 08
   25 00 FFFFFF82 FFFFFF80 FFFFFFA0 FFFFFF80 04 26 01 06 72 65 61 73 6F 6E
   10 02 13 27 09 02 28 06 02 06 41 6E 79 52 65 66
   08 05 2A 00 FFFFFF84 00 2B 01 06 3C 69 6E 69 74 3E 14
   02 2C 2D 10 02 1B 00 08 05 25 29 FFFFFFC0 00 26 08 05
   2F 00 FFFFFF84 00 30 01 05 61 70 70 6C 79 14 03 1E 31
   33 08 05 32 2E FFFFFFC0 00 16 01 06 74 61 72 67 65 74
   08 05 34 2E FFFFFFC0 00 1A 01 07 63 72 65 61 74 6F 72
   08 05 36 00 FFFFFF84 20 37 01 08 74 6F 53 74 72 69 6E
   67 14 01 38 10 02 0B 39 09 02 3A 0C 02 06 53 74
   72 69 6E 67 28 02 00 3C 10 02 13 3D 09 02 3E 06
   02 0C 73 65 72 69 61 6C 69 7A 61 62 6C 65 
  minor version: 0
  major version: 49
  Constant pool:
Asciz	SourceFile;
Asciz	Proxy.scala;
Asciz	reason;
Asciz	Ljava/lang/Object;;
Asciz	curried;
Asciz	()Lscala/Function1;;
Asciz	Code;
Asciz	LineNumberTable;
Asciz	scala/Function2$class;
class	scala/Function2$class
Asciz	(Lscala/Function2;)Lscala/Function1;;
NameAndType	curried:(Lscala/Function2;)Lscala/Function1;
Method	scala/Function2$class.curried:(Lscala/Function2;)Lscala/Function1;
Asciz	curry;
NameAndType	curry:(Lscala/Function2;)Lscala/Function1;
Method	scala/Function2$class.curry:(Lscala/Function2;)Lscala/Function1;
Asciz	Deprecated;
Asciz	tupled;
NameAndType	tupled:(Lscala/Function2;)Lscala/Function1;
Method	scala/Function2$class.tupled:(Lscala/Function2;)Lscala/Function1;
Asciz	apply;
Asciz	(Lscala/actors/AbstractActor;Lscala/actors/remote/Proxy;)V;
Asciz	scala/actors/remote/ExitFun;
class	scala/actors/remote/ExitFun
NameAndType	reason:Ljava/lang/Object;
Field	scala/actors/remote/ExitFun.reason:Ljava/lang/Object;
Asciz	scala/actors/AbstractActor;
class	scala/actors/AbstractActor
Asciz	exit;
Asciz	(Lscala/actors/AbstractActor;Ljava/lang/Object;)V;
NameAndType	exit:(Lscala/actors/AbstractActor;Ljava/lang/Object;)V
InterfaceMethod	scala/actors/AbstractActor.exit:(Lscala/actors/AbstractActor;Ljava/lang/Object;)V
Asciz	this;
Asciz	Lscala/actors/remote/ExitFun;;
Asciz	target;
Asciz	Lscala/actors/AbstractActor;;
Asciz	creator;
Asciz	Lscala/actors/remote/Proxy;;
Asciz	LocalVariableTable;
Asciz	toString;
Asciz	()Ljava/lang/String;;
Asciz	scala/collection/mutable/StringBuilder;
class	scala/collection/mutable/StringBuilder
Asciz	<init>;
Asciz	()V;
NameAndType	"<init>":()V
Method	scala/collection/mutable/StringBuilder."<init>":()V
Asciz	<ExitFun>(;
String	<ExitFun>(
Asciz	append;
Asciz	(Ljava/lang/Object;)Lscala/collection/mutable/StringBuilder;;
NameAndType	append:(Ljava/lang/Object;)Lscala/collection/mutable/StringBuilder;
Method	scala/collection/mutable/StringBuilder.append:(Ljava/lang/Object;)Lscala/collection/mutable/StringBuilder;
Asciz	java/lang/Object;
class	java/lang/Object
NameAndType	toString:()Ljava/lang/String;
Method	java/lang/Object.toString:()Ljava/lang/String;
Asciz	);
String	)
Method	scala/collection/mutable/StringBuilder.toString:()Ljava/lang/String;
Asciz	(Ljava/lang/Object;Ljava/lang/Object;)Ljava/lang/Object;;
Asciz	scala/actors/remote/Proxy;
class	scala/actors/remote/Proxy
NameAndType	apply:(Lscala/actors/AbstractActor;Lscala/actors/remote/Proxy;)V
Method	scala/actors/remote/ExitFun.apply:(Lscala/actors/AbstractActor;Lscala/actors/remote/Proxy;)V
Asciz	scala/runtime/BoxedUnit;
class	scala/runtime/BoxedUnit
Asciz	UNIT;
Asciz	Lscala/runtime/BoxedUnit;;
NameAndType	UNIT:Lscala/runtime/BoxedUnit;
Field	scala/runtime/BoxedUnit.UNIT:Lscala/runtime/BoxedUnit;
Asciz	v1;
Asciz	v2;
Asciz	(Ljava/lang/Object;)V;
Method	java/lang/Object."<init>":()V
Asciz	$init$;
Asciz	(Lscala/Function2;)V;
NameAndType	$init$:(Lscala/Function2;)V
Method	scala/Function2$class.$init$:(Lscala/Function2;)V
Asciz	Ljava/lang/Object;Lscala/Function2<Lscala/actors/AbstractActor;Lscala/actors/remote/Proxy;Ljava/lang/Object;>;Lscala/ScalaObject;;
Asciz	Signature;
Asciz	ScalaSig;
Asciz	scala/Function2;
class	scala/Function2
Asciz	scala/ScalaObject;
class	scala/ScalaObject
Asciz	java/io/Serializable;
class	java/io/Serializable

{
private final java.lang.Object reason;
  Signature: Ljava/lang/Object;

public scala.Function1 curried();
  Signature: ()Lscala/Function1;
  Code:
   Stack=1, Locals=1, Args_size=1
	aload_0
	invokestatic	Method scala/Function2$class.curried:(Lscala/Function2;)Lscala/Function1;
	areturn
  Labels:

public scala.Function1 curry();
  Signature: ()Lscala/Function1;
  Code:
   Stack=1, Locals=1, Args_size=1
	aload_0
	invokestatic	Method scala/Function2$class.curry:(Lscala/Function2;)Lscala/Function1;
	areturn
  Labels:
  Deprecated: true

public scala.Function1 tupled();
  Signature: ()Lscala/Function1;
  Code:
   Stack=1, Locals=1, Args_size=1
	aload_0
	invokestatic	Method scala/Function2$class.tupled:(Lscala/Function2;)Lscala/Function1;
	areturn
  Labels:

public void apply(scala.actors.AbstractActor, scala.actors.remote.Proxy);
  Signature: (Lscala/actors/AbstractActor;Lscala/actors/remote/Proxy;)V
  Code:
   Stack=3, Locals=3, Args_size=3
	aload_1
	aload_2
	aload_0
	getfield	Field reason:Ljava/lang/Object;
	invokeinterface	InterfaceMethod scala/actors/AbstractActor.exit:(Lscala/actors/AbstractActor;Ljava/lang/Object;)V
	return
  Labels:
  LocalVariableTable: 
   Start  Length  Slot  Name   Signature
   0      12      0    this       Lscala/actors/remote/ExitFun;
   0      12      1    target       Lscala/actors/AbstractActor;
   0      12      2    creator       Lscala/actors/remote/Proxy;


public java.lang.String toString();
  Signature: ()Ljava/lang/String;
  Code:
   Stack=2, Locals=1, Args_size=1
	new	class scala/collection/mutable/StringBuilder
	dup
	invokespecial	Method scala/collection/mutable/StringBuilder."<init>":()V
	ldc	String <ExitFun>(
	invokevirtual	Method scala/collection/mutable/StringBuilder.append:(Ljava/lang/Object;)Lscala/collection/mutable/StringBuilder;
	aload_0
	getfield	Field reason:Ljava/lang/Object;
	invokevirtual	Method java/lang/Object.toString:()Ljava/lang/String;
	invokevirtual	Method scala/collection/mutable/StringBuilder.append:(Ljava/lang/Object;)Lscala/collection/mutable/StringBuilder;
	ldc	String )
	invokevirtual	Method scala/collection/mutable/StringBuilder.append:(Ljava/lang/Object;)Lscala/collection/mutable/StringBuilder;
	invokevirtual	Method scala/collection/mutable/StringBuilder.toString:()Ljava/lang/String;
	areturn
  Labels:

public java.lang.Object apply(java.lang.Object, java.lang.Object);
  Signature: (Ljava/lang/Object;Ljava/lang/Object;)Ljava/lang/Object;
  Code:
   Stack=3, Locals=3, Args_size=3
	aload_0
	aload_1
	checkcast	class scala/actors/AbstractActor
	aload_2
	checkcast	class scala/actors/remote/Proxy
	invokevirtual	Method apply:(Lscala/actors/AbstractActor;Lscala/actors/remote/Proxy;)V
	getstatic	Field scala/runtime/BoxedUnit.UNIT:Lscala/runtime/BoxedUnit;
	areturn
  Labels:
  LocalVariableTable: 
   Start  Length  Slot  Name   Signature
   0      16      0    this       Lscala/actors/remote/ExitFun;
   0      16      1    v1       Ljava/lang/Object;
   0      16      2    v2       Ljava/lang/Object;


public scala.actors.remote.ExitFun(java.lang.Object);
  Signature: (Ljava/lang/Object;)V
  Code:
   Stack=2, Locals=2, Args_size=2
	aload_0
	aload_1
	putfield	Field reason:Ljava/lang/Object;
	aload_0
	invokespecial	Method java/lang/Object."<init>":()V
	aload_0
	invokestatic	Method scala/Function2$class.$init$:(Lscala/Function2;)V
	return
  Labels:
  LocalVariableTable: 
   Start  Length  Slot  Name   Signature
   0      14      0    this       Lscala/actors/remote/ExitFun;
   0      14      1    reason       Ljava/lang/Object;


}

