Compiled from "FreshNameCreator.scala"
public final class scala.actors.remote.FreshNameCreator$ extends java.lang.Object implements scala.ScalaObject
  SourceFile: "FreshNameCreator.scala"
  Scala: length = 0x
   
  minor version: 0
  major version: 49
  Constant pool:
const #1 = Asciz	SourceFile;
const #2 = Asciz	FreshNameCreator.scala;
const #3 = Asciz	Scala;
const #4 = Asciz	MODULE$;
const #5 = Asciz	Lscala/actors/remote/FreshNameCreator$;;
const #6 = Asciz	<clinit>;
const #7 = Asciz	()V;
const #8 = Asciz	Code;
const #9 = Asciz	scala/actors/remote/FreshNameCreator$;
const #10 = class	#9;	//  scala/actors/remote/FreshNameCreator$
const #11 = Asciz	<init>;
const #12 = NameAndType	#11:#7;//  "<init>":()V
const #13 = Method	#10.#12;	//  scala/actors/remote/FreshNameCreator$."<init>":()V
const #14 = Asciz	counters;
const #15 = Asciz	Lscala/collection/mutable/HashMap;;
const #16 = Asciz	Lscala/collection/mutable/HashMap<Ljava/lang/String;Ljava/lang/Integer;>;;
const #17 = Asciz	Signature;
const #18 = Asciz	counter;
const #19 = Asciz	I;
const #20 = Asciz	LineNumberTable;
const #21 = Asciz	java/lang/Object;
const #22 = class	#21;	//  java/lang/Object
const #23 = Method	#22.#12;	//  java/lang/Object."<init>":()V
const #24 = NameAndType	#4:#5;//  MODULE$:Lscala/actors/remote/FreshNameCreator$;
const #25 = Field	#10.#24;	//  scala/actors/remote/FreshNameCreator$.MODULE$:Lscala/actors/remote/FreshNameCreator$;
const #26 = NameAndType	#18:#19;//  counter:I
const #27 = Field	#10.#26;	//  scala/actors/remote/FreshNameCreator$.counter:I
const #28 = Asciz	scala/collection/mutable/HashMap;
const #29 = class	#28;	//  scala/collection/mutable/HashMap
const #30 = Method	#29.#12;	//  scala/collection/mutable/HashMap."<init>":()V
const #31 = NameAndType	#14:#15;//  counters:Lscala/collection/mutable/HashMap;
const #32 = Field	#10.#31;	//  scala/actors/remote/FreshNameCreator$.counters:Lscala/collection/mutable/HashMap;
const #33 = Asciz	newName;
const #34 = Asciz	()Lscala/Symbol;;
const #35 = Asciz	()I;
const #36 = NameAndType	#18:#35;//  counter:()I
const #37 = Method	#10.#36;	//  scala/actors/remote/FreshNameCreator$.counter:()I
const #38 = Asciz	counter_$eq;
const #39 = Asciz	(I)V;
const #40 = NameAndType	#38:#39;//  counter_$eq:(I)V
const #41 = Method	#10.#40;	//  scala/actors/remote/FreshNameCreator$.counter_$eq:(I)V
const #42 = Asciz	scala/Symbol$;
const #43 = class	#42;	//  scala/Symbol$
const #44 = Asciz	Lscala/Symbol$;;
const #45 = NameAndType	#4:#44;//  MODULE$:Lscala/Symbol$;
const #46 = Field	#43.#45;	//  scala/Symbol$.MODULE$:Lscala/Symbol$;
const #47 = Asciz	scala/collection/mutable/StringBuilder;
const #48 = class	#47;	//  scala/collection/mutable/StringBuilder
const #49 = Method	#48.#12;	//  scala/collection/mutable/StringBuilder."<init>":()V
const #50 = Asciz	$;
const #51 = String	#50;	//  $
const #52 = Asciz	append;
const #53 = Asciz	(Ljava/lang/Object;)Lscala/collection/mutable/StringBuilder;;
const #54 = NameAndType	#52:#53;//  append:(Ljava/lang/Object;)Lscala/collection/mutable/StringBuilder;
const #55 = Method	#48.#54;	//  scala/collection/mutable/StringBuilder.append:(Ljava/lang/Object;)Lscala/collection/mutable/StringBuilder;
const #56 = Asciz	scala/runtime/BoxesRunTime;
const #57 = class	#56;	//  scala/runtime/BoxesRunTime
const #58 = Asciz	boxToInteger;
const #59 = Asciz	(I)Ljava/lang/Integer;;
const #60 = NameAndType	#58:#59;//  boxToInteger:(I)Ljava/lang/Integer;
const #61 = Method	#57.#60;	//  scala/runtime/BoxesRunTime.boxToInteger:(I)Ljava/lang/Integer;
const #62 = Asciz	toString;
const #63 = Asciz	()Ljava/lang/String;;
const #64 = NameAndType	#62:#63;//  toString:()Ljava/lang/String;
const #65 = Method	#48.#64;	//  scala/collection/mutable/StringBuilder.toString:()Ljava/lang/String;
const #66 = Asciz	apply;
const #67 = Asciz	(Ljava/lang/Object;)Ljava/lang/Object;;
const #68 = NameAndType	#66:#67;//  apply:(Ljava/lang/Object;)Ljava/lang/Object;
const #69 = Method	#43.#68;	//  scala/Symbol$.apply:(Ljava/lang/Object;)Ljava/lang/Object;
const #70 = Asciz	scala/Symbol;
const #71 = class	#70;	//  scala/Symbol
const #72 = Asciz	(Ljava/lang/String;)Lscala/Symbol;;
const #73 = Asciz	get;
const #74 = Asciz	(Ljava/lang/Object;)Lscala/Option;;
const #75 = NameAndType	#73:#74;//  get:(Ljava/lang/Object;)Lscala/Option;
const #76 = Method	#29.#75;	//  scala/collection/mutable/HashMap.get:(Ljava/lang/Object;)Lscala/Option;
const #77 = Asciz	scala/Some;
const #78 = class	#77;	//  scala/Some
const #79 = Asciz	x;
const #80 = Asciz	()Ljava/lang/Object;;
const #81 = NameAndType	#79:#80;//  x:()Ljava/lang/Object;
const #82 = Method	#78.#81;	//  scala/Some.x:()Ljava/lang/Object;
const #83 = Asciz	unboxToInt;
const #84 = Asciz	(Ljava/lang/Object;)I;
const #85 = NameAndType	#83:#84;//  unboxToInt:(Ljava/lang/Object;)I
const #86 = Method	#57.#85;	//  scala/runtime/BoxesRunTime.unboxToInt:(Ljava/lang/Object;)I
const #87 = Asciz	scala/MatchError;
const #88 = class	#87;	//  scala/MatchError
const #89 = Asciz	scala/Option;
const #90 = class	#89;	//  scala/Option
const #91 = Method	#90.#64;	//  scala/Option.toString:()Ljava/lang/String;
const #92 = Asciz	(Ljava/lang/String;)V;
const #93 = NameAndType	#11:#92;//  "<init>":(Ljava/lang/String;)V
const #94 = Method	#88.#93;	//  scala/MatchError."<init>":(Ljava/lang/String;)V
const #95 = Asciz	scala/None$;
const #96 = class	#95;	//  scala/None$
const #97 = Asciz	Lscala/None$;;
const #98 = NameAndType	#4:#97;//  MODULE$:Lscala/None$;
const #99 = Field	#96.#98;	//  scala/None$.MODULE$:Lscala/None$;
const #100 = Asciz	equals;
const #101 = Asciz	(Ljava/lang/Object;)Z;
const #102 = NameAndType	#100:#101;//  equals:(Ljava/lang/Object;)Z
const #103 = Method	#22.#102;	//  java/lang/Object.equals:(Ljava/lang/Object;)Z
const #104 = Asciz	update;
const #105 = Asciz	(Ljava/lang/Object;Ljava/lang/Object;)V;
const #106 = NameAndType	#104:#105;//  update:(Ljava/lang/Object;Ljava/lang/Object;)V
const #107 = Method	#29.#106;	//  scala/collection/mutable/HashMap.update:(Ljava/lang/Object;Ljava/lang/Object;)V
const #108 = Asciz	this;
const #109 = Asciz	prefix;
const #110 = Asciz	Ljava/lang/String;;
const #111 = Asciz	temp2;
const #112 = Asciz	Lscala/Some;;
const #113 = Asciz	temp3;
const #114 = Asciz	count;
const #115 = Asciz	temp1;
const #116 = Asciz	Lscala/Option;;
const #117 = Asciz	LocalVariableTable;
const #118 = Asciz	()Lscala/collection/mutable/HashMap;;
const #119 = Asciz	()Lscala/collection/mutable/HashMap<Ljava/lang/String;Ljava/lang/Integer;>;;
const #120 = Asciz	scala/ScalaObject;
const #121 = class	#120;	//  scala/ScalaObject

{
public static final scala.actors.remote.FreshNameCreator$ MODULE$;

public static {};
  Code:
   Stack=1, Locals=0, Args_size=0
   0:	new	#10; //class scala/actors/remote/FreshNameCreator$
   3:	invokespecial	#13; //Method "<init>":()V
   6:	return

public scala.Symbol newName();
  Code:
   Stack=3, Locals=2, Args_size=1
   0:	aload_0
   1:	aload_0
   2:	invokevirtual	#37; //Method counter:()I
   5:	iconst_1
   6:	iadd
   7:	invokevirtual	#41; //Method counter_$eq:(I)V
   10:	getstatic	#46; //Field scala/Symbol$.MODULE$:Lscala/Symbol$;
   13:	new	#48; //class scala/collection/mutable/StringBuilder
   16:	dup
   17:	invokespecial	#49; //Method scala/collection/mutable/StringBuilder."<init>":()V
   20:	ldc	#51; //String $
   22:	invokevirtual	#55; //Method scala/collection/mutable/StringBuilder.append:(Ljava/lang/Object;)Lscala/collection/mutable/StringBuilder;
   25:	aload_0
   26:	invokevirtual	#37; //Method counter:()I
   29:	istore_1
   30:	iload_1
   31:	invokestatic	#61; //Method scala/runtime/BoxesRunTime.boxToInteger:(I)Ljava/lang/Integer;
   34:	invokevirtual	#55; //Method scala/collection/mutable/StringBuilder.append:(Ljava/lang/Object;)Lscala/collection/mutable/StringBuilder;
   37:	ldc	#51; //String $
   39:	invokevirtual	#55; //Method scala/collection/mutable/StringBuilder.append:(Ljava/lang/Object;)Lscala/collection/mutable/StringBuilder;
   42:	invokevirtual	#65; //Method scala/collection/mutable/StringBuilder.toString:()Ljava/lang/String;
   45:	invokevirtual	#69; //Method scala/Symbol$.apply:(Ljava/lang/Object;)Ljava/lang/Object;
   48:	checkcast	#71; //class scala/Symbol
   51:	areturn
  LineNumberTable: 
   line 34: 0
   line 35: 10


public scala.Symbol newName(java.lang.String);
  Code:
   Stack=3, Locals=6, Args_size=2
   0:	aload_0
   1:	getfield	#32; //Field counters:Lscala/collection/mutable/HashMap;
   4:	aload_1
   5:	invokevirtual	#76; //Method scala/collection/mutable/HashMap.get:(Ljava/lang/Object;)Lscala/Option;
   8:	astore	5
   10:	aload	5
   12:	instanceof	#78; //class scala/Some
   15:	ifeq	55
   18:	aload	5
   20:	checkcast	#78; //class scala/Some
   23:	astore_2
   24:	aload_2
   25:	invokevirtual	#82; //Method scala/Some.x:()Ljava/lang/Object;
   28:	invokestatic	#86; //Method scala/runtime/BoxesRunTime.unboxToInt:(Ljava/lang/Object;)I
   31:	istore_3
   32:	iconst_1
   33:	ifeq	42
   36:	iload_3
   37:	iconst_1
   38:	iadd
   39:	goto	84
   42:	new	#88; //class scala/MatchError
   45:	dup
   46:	aload	5
   48:	invokevirtual	#91; //Method scala/Option.toString:()Ljava/lang/String;
   51:	invokespecial	#94; //Method scala/MatchError."<init>":(Ljava/lang/String;)V
   54:	athrow
   55:	getstatic	#99; //Field scala/None$.MODULE$:Lscala/None$;
   58:	dup
   59:	ifnonnull	71
   62:	pop
   63:	aload	5
   65:	ifnull	79
   68:	goto	144
   71:	aload	5
   73:	invokevirtual	#103; //Method java/lang/Object.equals:(Ljava/lang/Object;)Z
   76:	ifeq	144
   79:	iconst_1
   80:	ifeq	131
   83:	iconst_0
   84:	istore	4
   86:	aload_0
   87:	getfield	#32; //Field counters:Lscala/collection/mutable/HashMap;
   90:	aload_1
   91:	iload	4
   93:	invokestatic	#61; //Method scala/runtime/BoxesRunTime.boxToInteger:(I)Ljava/lang/Integer;
   96:	invokevirtual	#107; //Method scala/collection/mutable/HashMap.update:(Ljava/lang/Object;Ljava/lang/Object;)V
   99:	getstatic	#46; //Field scala/Symbol$.MODULE$:Lscala/Symbol$;
   102:	new	#48; //class scala/collection/mutable/StringBuilder
   105:	dup
   106:	invokespecial	#49; //Method scala/collection/mutable/StringBuilder."<init>":()V
   109:	aload_1
   110:	invokevirtual	#55; //Method scala/collection/mutable/StringBuilder.append:(Ljava/lang/Object;)Lscala/collection/mutable/StringBuilder;
   113:	iload	4
   115:	invokestatic	#61; //Method scala/runtime/BoxesRunTime.boxToInteger:(I)Ljava/lang/Integer;
   118:	invokevirtual	#55; //Method scala/collection/mutable/StringBuilder.append:(Ljava/lang/Object;)Lscala/collection/mutable/StringBuilder;
   121:	invokevirtual	#65; //Method scala/collection/mutable/StringBuilder.toString:()Ljava/lang/String;
   124:	invokevirtual	#69; //Method scala/Symbol$.apply:(Ljava/lang/Object;)Ljava/lang/Object;
   127:	checkcast	#71; //class scala/Symbol
   130:	areturn
   131:	new	#88; //class scala/MatchError
   134:	dup
   135:	aload	5
   137:	invokevirtual	#91; //Method scala/Option.toString:()Ljava/lang/String;
   140:	invokespecial	#94; //Method scala/MatchError."<init>":(Ljava/lang/String;)V
   143:	athrow
   144:	new	#88; //class scala/MatchError
   147:	dup
   148:	aload	5
   150:	invokevirtual	#91; //Method scala/Option.toString:()Ljava/lang/String;
   153:	invokespecial	#94; //Method scala/MatchError."<init>":(Ljava/lang/String;)V
   156:	athrow
  LineNumberTable: 
   line 25: 0
   line 644: 32
   line 26: 36
   line 25: 42
   line 644: 79
   line 27: 83
   line 25: 84
   line 29: 86
   line 30: 99
   line 25: 131

  LocalVariableTable: 
   Start  Length  Slot  Name   Signature
   0      157      0    this       Lscala/actors/remote/FreshNameCreator$;
   0      157      1    prefix       Ljava/lang/String;
   24      31      2    temp2       Lscala/Some;
   32      23      3    temp3       I
   86      44      4    count       I
   10      147      5    temp1       Lscala/Option;


public scala.collection.mutable.HashMap counters();
  Code:
   Stack=1, Locals=1, Args_size=1
   0:	aload_0
   1:	getfield	#32; //Field counters:Lscala/collection/mutable/HashMap;
   4:	areturn
  LineNumberTable: 
   line 17: 0

  Signature: length = 0x2
   00 77 

public void counter_$eq(int);
  Code:
   Stack=2, Locals=2, Args_size=2
   0:	aload_0
   1:	iload_1
   2:	putfield	#27; //Field counter:I
   5:	return
  LineNumberTable: 
   line 16: 0


public int counter();
  Code:
   Stack=1, Locals=1, Args_size=1
   0:	aload_0
   1:	getfield	#27; //Field counter:I
   4:	ireturn
  LineNumberTable: 
   line 16: 0


}

