Compiled from "JavaSerializer.scala"
public class scala.actors.remote.JavaSerializer extends scala.actors.remote.Serializer implements scala.ScalaObject
  SourceFile: "JavaSerializer.scala"
  ScalaSig: length = 0x177
   05 00 3C 06 08 01 02 FFFFFF84 FFFFFF80 FFFFFF80 FFFFFF80 00 09 02 0E 4A
   61 76 61 53 65 72 69 61 6C 69 7A 65 72 0A 02 03
   04 01 06 72 65 6D 6F 74 65 0A 02 05 06 01 06 61
   63 74 6F 72 73 0A 01 07 01 05 73 63 61 6C 61 03
   00 13 03 00 0A 0E 10 02 0B 0C 0D 01 02 09 02 0D
   02 02 0A 53 65 72 69 61 6C 69 7A 65 72 10 02 0F
   10 0D 01 06 09 02 11 06 02 0B 53 63 61 6C 61 4F
   62 6A 65 63 74 08 09 13 00 FFFFFF82 FFFFFF80 FFFFFFA0 FFFFFF80 04 14 17
   01 04 73 65 72 76 10 02 0B 15 09 02 16 02 02 07
   53 65 72 76 69 63 65 09 02 18 0C 01 07 73 65 72
   76 69 63 65 08 08 1A 00 FFFFFF82 FFFFFF80 FFFFFFA0 FFFFFF80 04 1B 01 02
   63 6C 10 02 1C 21 0D 01 1D 0A 02 1E 1F 01 04 6C
   61 6E 67 0A 01 20 01 04 6A 61 76 61 09 02 22 1D
   02 0B 43 6C 61 73 73 4C 6F 61 64 65 72 08 05 24
   00 FFFFFF84 00 25 01 06 3C 69 6E 69 74 3E 14 03 26 27
   28 10 02 0B 00 08 05 13 23 FFFFFFC0 00 14 08 05 1A 23
   FFFFFFC0 00 1B 08 05 2A 00 FFFFFF84 00 2B 01 09 73 65 72 69
   61 6C 69 7A 65 14 02 2C 32 10 03 0F 2D 2F 09 02
   2E 06 02 05 41 72 72 61 79 10 02 0F 30 09 02 31
   06 02 04 42 79 74 65 08 05 33 29 FFFFFFC0 00 34 01 01
   6F 10 02 0F 35 09 02 36 06 02 06 41 6E 79 52 65
   66 08 05 38 00 FFFFFF84 00 39 01 0B 64 65 73 65 72 69
   61 6C 69 7A 65 14 02 34 3A 08 05 3B 37 FFFFFFC0 00 2C
   01 05 62 79 74 65 73 
  minor version: 0
  major version: 49
  Constant pool:
const #1 = Asciz	SourceFile;
const #2 = Asciz	JavaSerializer.scala;
const #3 = Asciz	cl;
const #4 = Asciz	Ljava/lang/ClassLoader;;
const #5 = Asciz	<init>;
const #6 = Asciz	(Lscala/actors/remote/Service;Ljava/lang/ClassLoader;)V;
const #7 = Asciz	Code;
const #8 = Asciz	LineNumberTable;
const #9 = Asciz	scala/actors/remote/JavaSerializer;
const #10 = class	#9;	//  scala/actors/remote/JavaSerializer
const #11 = NameAndType	#3:#4;//  cl:Ljava/lang/ClassLoader;
const #12 = Field	#10.#11;	//  scala/actors/remote/JavaSerializer.cl:Ljava/lang/ClassLoader;
const #13 = Asciz	scala/actors/remote/Serializer;
const #14 = class	#13;	//  scala/actors/remote/Serializer
const #15 = Asciz	(Lscala/actors/remote/Service;)V;
const #16 = NameAndType	#5:#15;//  "<init>":(Lscala/actors/remote/Service;)V
const #17 = Method	#14.#16;	//  scala/actors/remote/Serializer."<init>":(Lscala/actors/remote/Service;)V
const #18 = Asciz	this;
const #19 = Asciz	Lscala/actors/remote/JavaSerializer;;
const #20 = Asciz	serv;
const #21 = Asciz	Lscala/actors/remote/Service;;
const #22 = Asciz	LocalVariableTable;
const #23 = Asciz	deserialize;
const #24 = Asciz	([B)Ljava/lang/Object;;
const #25 = Asciz	java/io/ByteArrayInputStream;
const #26 = class	#25;	//  java/io/ByteArrayInputStream
const #27 = Asciz	([B)V;
const #28 = NameAndType	#5:#27;//  "<init>":([B)V
const #29 = Method	#26.#28;	//  java/io/ByteArrayInputStream."<init>":([B)V
const #30 = Asciz	java/lang/Object;
const #31 = class	#30;	//  java/lang/Object
const #32 = Asciz	equals;
const #33 = Asciz	(Ljava/lang/Object;)Z;
const #34 = NameAndType	#32:#33;//  equals:(Ljava/lang/Object;)Z
const #35 = Method	#31.#34;	//  java/lang/Object.equals:(Ljava/lang/Object;)Z
const #36 = Asciz	java/io/ObjectInputStream;
const #37 = class	#36;	//  java/io/ObjectInputStream
const #38 = Asciz	(Ljava/io/InputStream;)V;
const #39 = NameAndType	#5:#38;//  "<init>":(Ljava/io/InputStream;)V
const #40 = Method	#37.#39;	//  java/io/ObjectInputStream."<init>":(Ljava/io/InputStream;)V
const #41 = Asciz	scala/actors/remote/CustomObjectInputStream;
const #42 = class	#41;	//  scala/actors/remote/CustomObjectInputStream
const #43 = Asciz	(Ljava/io/InputStream;Ljava/lang/ClassLoader;)V;
const #44 = NameAndType	#5:#43;//  "<init>":(Ljava/io/InputStream;Ljava/lang/ClassLoader;)V
const #45 = Method	#42.#44;	//  scala/actors/remote/CustomObjectInputStream."<init>":(Ljava/io/InputStream;Ljava/lang/ClassLoader;)V
const #46 = Asciz	readObject;
const #47 = Asciz	()Ljava/lang/Object;;
const #48 = NameAndType	#46:#47;//  readObject:()Ljava/lang/Object;
const #49 = Method	#37.#48;	//  java/io/ObjectInputStream.readObject:()Ljava/lang/Object;
const #50 = Asciz	bytes;
const #51 = Asciz	[B;
const #52 = Asciz	bis;
const #53 = Asciz	Ljava/io/ByteArrayInputStream;;
const #54 = Asciz	in;
const #55 = Asciz	Ljava/io/ObjectInputStream;;
const #56 = Asciz	serialize;
const #57 = Asciz	(Ljava/lang/Object;)[B;
const #58 = Asciz	java/io/ByteArrayOutputStream;
const #59 = class	#58;	//  java/io/ByteArrayOutputStream
const #60 = Asciz	()V;
const #61 = NameAndType	#5:#60;//  "<init>":()V
const #62 = Method	#59.#61;	//  java/io/ByteArrayOutputStream."<init>":()V
const #63 = Asciz	java/io/ObjectOutputStream;
const #64 = class	#63;	//  java/io/ObjectOutputStream
const #65 = Asciz	(Ljava/io/OutputStream;)V;
const #66 = NameAndType	#5:#65;//  "<init>":(Ljava/io/OutputStream;)V
const #67 = Method	#64.#66;	//  java/io/ObjectOutputStream."<init>":(Ljava/io/OutputStream;)V
const #68 = Asciz	writeObject;
const #69 = Asciz	(Ljava/lang/Object;)V;
const #70 = NameAndType	#68:#69;//  writeObject:(Ljava/lang/Object;)V
const #71 = Method	#64.#70;	//  java/io/ObjectOutputStream.writeObject:(Ljava/lang/Object;)V
const #72 = Asciz	flush;
const #73 = NameAndType	#72:#60;//  flush:()V
const #74 = Method	#64.#73;	//  java/io/ObjectOutputStream.flush:()V
const #75 = Asciz	toByteArray;
const #76 = Asciz	()[B;
const #77 = NameAndType	#75:#76;//  toByteArray:()[B
const #78 = Method	#59.#77;	//  java/io/ByteArrayOutputStream.toByteArray:()[B
const #79 = Asciz	o;
const #80 = Asciz	Ljava/lang/Object;;
const #81 = Asciz	bos;
const #82 = Asciz	Ljava/io/ByteArrayOutputStream;;
const #83 = Asciz	out;
const #84 = Asciz	Ljava/io/ObjectOutputStream;;
const #85 = Asciz	ScalaSig;
const #86 = Asciz	scala/ScalaObject;
const #87 = class	#86;	//  scala/ScalaObject

{
public scala.actors.remote.JavaSerializer(scala.actors.remote.Service, java.lang.ClassLoader);
  Code:
   Stack=2, Locals=3, Args_size=3
   0:	aload_0
   1:	aload_2
   2:	putfield	#12; //Field cl:Ljava/lang/ClassLoader;
   5:	aload_0
   6:	aload_1
   7:	invokespecial	#17; //Method scala/actors/remote/Serializer."<init>":(Lscala/actors/remote/Service;)V
   10:	return
  LineNumberTable: 
   line 43: 0

  LocalVariableTable: 
   Start  Length  Slot  Name   Signature
   0      11      0    this       Lscala/actors/remote/JavaSerializer;
   0      11      1    serv       Lscala/actors/remote/Service;
   0      11      2    cl       Ljava/lang/ClassLoader;


public java.lang.Object deserialize(byte[]);
  Code:
   Stack=4, Locals=5, Args_size=2
   0:	new	#26; //class java/io/ByteArrayInputStream
   3:	dup
   4:	aload_1
   5:	invokespecial	#29; //Method java/io/ByteArrayInputStream."<init>":([B)V
   8:	astore_2
   9:	aload_0
   10:	getfield	#12; //Field cl:Ljava/lang/ClassLoader;
   13:	dup
   14:	astore	4
   16:	ifnull	28
   19:	aload	4
   21:	aconst_null
   22:	invokevirtual	#35; //Method java/lang/Object.equals:(Ljava/lang/Object;)Z
   25:	ifeq	39
   28:	new	#37; //class java/io/ObjectInputStream
   31:	dup
   32:	aload_2
   33:	invokespecial	#40; //Method java/io/ObjectInputStream."<init>":(Ljava/io/InputStream;)V
   36:	goto	51
   39:	new	#42; //class scala/actors/remote/CustomObjectInputStream
   42:	dup
   43:	aload_2
   44:	aload_0
   45:	getfield	#12; //Field cl:Ljava/lang/ClassLoader;
   48:	invokespecial	#45; //Method scala/actors/remote/CustomObjectInputStream."<init>":(Ljava/io/InputStream;Ljava/lang/ClassLoader;)V
   51:	astore_3
   52:	aload_3
   53:	invokevirtual	#49; //Method java/io/ObjectInputStream.readObject:()Ljava/lang/Object;
   56:	areturn
  LineNumberTable: 
   line 53: 0
   line 56: 9
   line 59: 28
   line 57: 39
   line 56: 51
   line 61: 52

  LocalVariableTable: 
   Start  Length  Slot  Name   Signature
   0      57      0    this       Lscala/actors/remote/JavaSerializer;
   0      57      1    bytes       [B
   9      47      2    bis       Ljava/io/ByteArrayInputStream;
   52      4      3    in       Ljava/io/ObjectInputStream;


public byte[] serialize(java.lang.Object);
  Code:
   Stack=3, Locals=4, Args_size=2
   0:	new	#59; //class java/io/ByteArrayOutputStream
   3:	dup
   4:	invokespecial	#62; //Method java/io/ByteArrayOutputStream."<init>":()V
   7:	astore_2
   8:	new	#64; //class java/io/ObjectOutputStream
   11:	dup
   12:	aload_2
   13:	invokespecial	#67; //Method java/io/ObjectOutputStream."<init>":(Ljava/io/OutputStream;)V
   16:	astore_3
   17:	aload_3
   18:	aload_1
   19:	invokevirtual	#71; //Method java/io/ObjectOutputStream.writeObject:(Ljava/lang/Object;)V
   22:	aload_3
   23:	invokevirtual	#74; //Method java/io/ObjectOutputStream.flush:()V
   26:	aload_2
   27:	invokevirtual	#78; //Method java/io/ByteArrayOutputStream.toByteArray:()[B
   30:	areturn
  LineNumberTable: 
   line 45: 0
   line 46: 8
   line 47: 17
   line 48: 22
   line 49: 26

  LocalVariableTable: 
   Start  Length  Slot  Name   Signature
   0      31      0    this       Lscala/actors/remote/JavaSerializer;
   0      31      1    o       Ljava/lang/Object;
   8      22      2    bos       Ljava/io/ByteArrayOutputStream;
   17      13      3    out       Ljava/io/ObjectOutputStream;


}

