Compiled from "Proxy.scala"
public class scala.actors.remote.LinkToFun extends java.lang.Object implements scala.Function2,scala.ScalaObject,java.io.Serializable
  SourceFile: "Proxy.scala"
  ScalaSig: length = 0x3
   05 00 00 
  Signature: length = 0x2
   02 FFFFFFBA 
  RuntimeVisibleAnnotations: length = 0xB
   00 01 02 FFFFFFBC 00 01 02 FFFFFFBD 73 02 FFFFFFBE 
  minor version: 0
  major version: 49
  Constant pool:
Asciz	SourceFile;
Asciz	Proxy.scala;
Asciz	apply$mcVII$sp;
Asciz	(II)V;
Asciz	Code;
Asciz	LineNumberTable;
Asciz	scala/Function2$class;
class	scala/Function2$class
Asciz	(Lscala/Function2;II)V;
NameAndType	apply$mcVII$sp:(Lscala/Function2;II)V
Method	scala/Function2$class.apply$mcVII$sp:(Lscala/Function2;II)V
Asciz	this;
Asciz	Lscala/actors/remote/LinkToFun;;
Asciz	v1;
Asciz	I;
Asciz	v2;
Asciz	LocalVariableTable;
Asciz	apply$mcZII$sp;
Asciz	(II)Z;
Asciz	(Lscala/Function2;II)Z;
NameAndType	apply$mcZII$sp:(Lscala/Function2;II)Z
Method	scala/Function2$class.apply$mcZII$sp:(Lscala/Function2;II)Z
Asciz	apply$mcIII$sp;
Asciz	(II)I;
Asciz	(Lscala/Function2;II)I;
NameAndType	apply$mcIII$sp:(Lscala/Function2;II)I
Method	scala/Function2$class.apply$mcIII$sp:(Lscala/Function2;II)I
Asciz	apply$mcLII$sp;
Asciz	(II)J;
Asciz	(Lscala/Function2;II)J;
NameAndType	apply$mcLII$sp:(Lscala/Function2;II)J
Method	scala/Function2$class.apply$mcLII$sp:(Lscala/Function2;II)J
Asciz	apply$mcDII$sp;
Asciz	(II)D;
Asciz	(Lscala/Function2;II)D;
NameAndType	apply$mcDII$sp:(Lscala/Function2;II)D
Method	scala/Function2$class.apply$mcDII$sp:(Lscala/Function2;II)D
Asciz	apply$mcVIL$sp;
Asciz	(IJ)V;
Asciz	(Lscala/Function2;IJ)V;
NameAndType	apply$mcVIL$sp:(Lscala/Function2;IJ)V
Method	scala/Function2$class.apply$mcVIL$sp:(Lscala/Function2;IJ)V
Asciz	J;
Asciz	apply$mcZIL$sp;
Asciz	(IJ)Z;
Asciz	(Lscala/Function2;IJ)Z;
NameAndType	apply$mcZIL$sp:(Lscala/Function2;IJ)Z
Method	scala/Function2$class.apply$mcZIL$sp:(Lscala/Function2;IJ)Z
Asciz	apply$mcIIL$sp;
Asciz	(IJ)I;
Asciz	(Lscala/Function2;IJ)I;
NameAndType	apply$mcIIL$sp:(Lscala/Function2;IJ)I
Method	scala/Function2$class.apply$mcIIL$sp:(Lscala/Function2;IJ)I
Asciz	apply$mcLIL$sp;
Asciz	(IJ)J;
Asciz	(Lscala/Function2;IJ)J;
NameAndType	apply$mcLIL$sp:(Lscala/Function2;IJ)J
Method	scala/Function2$class.apply$mcLIL$sp:(Lscala/Function2;IJ)J
Asciz	apply$mcDIL$sp;
Asciz	(IJ)D;
Asciz	(Lscala/Function2;IJ)D;
NameAndType	apply$mcDIL$sp:(Lscala/Function2;IJ)D
Method	scala/Function2$class.apply$mcDIL$sp:(Lscala/Function2;IJ)D
Asciz	apply$mcVID$sp;
Asciz	(ID)V;
Asciz	(Lscala/Function2;ID)V;
NameAndType	apply$mcVID$sp:(Lscala/Function2;ID)V
Method	scala/Function2$class.apply$mcVID$sp:(Lscala/Function2;ID)V
Asciz	D;
Asciz	apply$mcZID$sp;
Asciz	(ID)Z;
Asciz	(Lscala/Function2;ID)Z;
NameAndType	apply$mcZID$sp:(Lscala/Function2;ID)Z
Method	scala/Function2$class.apply$mcZID$sp:(Lscala/Function2;ID)Z
Asciz	apply$mcIID$sp;
Asciz	(ID)I;
Asciz	(Lscala/Function2;ID)I;
NameAndType	apply$mcIID$sp:(Lscala/Function2;ID)I
Method	scala/Function2$class.apply$mcIID$sp:(Lscala/Function2;ID)I
Asciz	apply$mcLID$sp;
Asciz	(ID)J;
Asciz	(Lscala/Function2;ID)J;
NameAndType	apply$mcLID$sp:(Lscala/Function2;ID)J
Method	scala/Function2$class.apply$mcLID$sp:(Lscala/Function2;ID)J
Asciz	apply$mcDID$sp;
Asciz	(ID)D;
Asciz	(Lscala/Function2;ID)D;
NameAndType	apply$mcDID$sp:(Lscala/Function2;ID)D
Method	scala/Function2$class.apply$mcDID$sp:(Lscala/Function2;ID)D
Asciz	apply$mcVLI$sp;
Asciz	(JI)V;
Asciz	(Lscala/Function2;JI)V;
NameAndType	apply$mcVLI$sp:(Lscala/Function2;JI)V
Method	scala/Function2$class.apply$mcVLI$sp:(Lscala/Function2;JI)V
Asciz	apply$mcZLI$sp;
Asciz	(JI)Z;
Asciz	(Lscala/Function2;JI)Z;
NameAndType	apply$mcZLI$sp:(Lscala/Function2;JI)Z
Method	scala/Function2$class.apply$mcZLI$sp:(Lscala/Function2;JI)Z
Asciz	apply$mcILI$sp;
Asciz	(JI)I;
Asciz	(Lscala/Function2;JI)I;
NameAndType	apply$mcILI$sp:(Lscala/Function2;JI)I
Method	scala/Function2$class.apply$mcILI$sp:(Lscala/Function2;JI)I
Asciz	apply$mcLLI$sp;
Asciz	(JI)J;
Asciz	(Lscala/Function2;JI)J;
NameAndType	apply$mcLLI$sp:(Lscala/Function2;JI)J
Method	scala/Function2$class.apply$mcLLI$sp:(Lscala/Function2;JI)J
Asciz	apply$mcDLI$sp;
Asciz	(JI)D;
Asciz	(Lscala/Function2;JI)D;
NameAndType	apply$mcDLI$sp:(Lscala/Function2;JI)D
Method	scala/Function2$class.apply$mcDLI$sp:(Lscala/Function2;JI)D
Asciz	apply$mcVLL$sp;
Asciz	(JJ)V;
Asciz	(Lscala/Function2;JJ)V;
NameAndType	apply$mcVLL$sp:(Lscala/Function2;JJ)V
Method	scala/Function2$class.apply$mcVLL$sp:(Lscala/Function2;JJ)V
Asciz	apply$mcZLL$sp;
Asciz	(JJ)Z;
Asciz	(Lscala/Function2;JJ)Z;
NameAndType	apply$mcZLL$sp:(Lscala/Function2;JJ)Z
Method	scala/Function2$class.apply$mcZLL$sp:(Lscala/Function2;JJ)Z
Asciz	apply$mcILL$sp;
Asciz	(JJ)I;
Asciz	(Lscala/Function2;JJ)I;
NameAndType	apply$mcILL$sp:(Lscala/Function2;JJ)I
Method	scala/Function2$class.apply$mcILL$sp:(Lscala/Function2;JJ)I
Asciz	apply$mcLLL$sp;
Asciz	(JJ)J;
Asciz	(Lscala/Function2;JJ)J;
NameAndType	apply$mcLLL$sp:(Lscala/Function2;JJ)J
Method	scala/Function2$class.apply$mcLLL$sp:(Lscala/Function2;JJ)J
Asciz	apply$mcDLL$sp;
Asciz	(JJ)D;
Asciz	(Lscala/Function2;JJ)D;
NameAndType	apply$mcDLL$sp:(Lscala/Function2;JJ)D
Method	scala/Function2$class.apply$mcDLL$sp:(Lscala/Function2;JJ)D
Asciz	apply$mcVLD$sp;
Asciz	(JD)V;
Asciz	(Lscala/Function2;JD)V;
NameAndType	apply$mcVLD$sp:(Lscala/Function2;JD)V
Method	scala/Function2$class.apply$mcVLD$sp:(Lscala/Function2;JD)V
Asciz	apply$mcZLD$sp;
Asciz	(JD)Z;
Asciz	(Lscala/Function2;JD)Z;
NameAndType	apply$mcZLD$sp:(Lscala/Function2;JD)Z
Method	scala/Function2$class.apply$mcZLD$sp:(Lscala/Function2;JD)Z
Asciz	apply$mcILD$sp;
Asciz	(JD)I;
Asciz	(Lscala/Function2;JD)I;
NameAndType	apply$mcILD$sp:(Lscala/Function2;JD)I
Method	scala/Function2$class.apply$mcILD$sp:(Lscala/Function2;JD)I
Asciz	apply$mcLLD$sp;
Asciz	(JD)J;
Asciz	(Lscala/Function2;JD)J;
NameAndType	apply$mcLLD$sp:(Lscala/Function2;JD)J
Method	scala/Function2$class.apply$mcLLD$sp:(Lscala/Function2;JD)J
Asciz	apply$mcDLD$sp;
Asciz	(JD)D;
Asciz	(Lscala/Function2;JD)D;
NameAndType	apply$mcDLD$sp:(Lscala/Function2;JD)D
Method	scala/Function2$class.apply$mcDLD$sp:(Lscala/Function2;JD)D
Asciz	apply$mcVDI$sp;
Asciz	(DI)V;
Asciz	(Lscala/Function2;DI)V;
NameAndType	apply$mcVDI$sp:(Lscala/Function2;DI)V
Method	scala/Function2$class.apply$mcVDI$sp:(Lscala/Function2;DI)V
Asciz	apply$mcZDI$sp;
Asciz	(DI)Z;
Asciz	(Lscala/Function2;DI)Z;
NameAndType	apply$mcZDI$sp:(Lscala/Function2;DI)Z
Method	scala/Function2$class.apply$mcZDI$sp:(Lscala/Function2;DI)Z
Asciz	apply$mcIDI$sp;
Asciz	(DI)I;
Asciz	(Lscala/Function2;DI)I;
NameAndType	apply$mcIDI$sp:(Lscala/Function2;DI)I
Method	scala/Function2$class.apply$mcIDI$sp:(Lscala/Function2;DI)I
Asciz	apply$mcLDI$sp;
Asciz	(DI)J;
Asciz	(Lscala/Function2;DI)J;
NameAndType	apply$mcLDI$sp:(Lscala/Function2;DI)J
Method	scala/Function2$class.apply$mcLDI$sp:(Lscala/Function2;DI)J
Asciz	apply$mcDDI$sp;
Asciz	(DI)D;
Asciz	(Lscala/Function2;DI)D;
NameAndType	apply$mcDDI$sp:(Lscala/Function2;DI)D
Method	scala/Function2$class.apply$mcDDI$sp:(Lscala/Function2;DI)D
Asciz	apply$mcVDL$sp;
Asciz	(DJ)V;
Asciz	(Lscala/Function2;DJ)V;
NameAndType	apply$mcVDL$sp:(Lscala/Function2;DJ)V
Method	scala/Function2$class.apply$mcVDL$sp:(Lscala/Function2;DJ)V
Asciz	apply$mcZDL$sp;
Asciz	(DJ)Z;
Asciz	(Lscala/Function2;DJ)Z;
NameAndType	apply$mcZDL$sp:(Lscala/Function2;DJ)Z
Method	scala/Function2$class.apply$mcZDL$sp:(Lscala/Function2;DJ)Z
Asciz	apply$mcIDL$sp;
Asciz	(DJ)I;
Asciz	(Lscala/Function2;DJ)I;
NameAndType	apply$mcIDL$sp:(Lscala/Function2;DJ)I
Method	scala/Function2$class.apply$mcIDL$sp:(Lscala/Function2;DJ)I
Asciz	apply$mcLDL$sp;
Asciz	(DJ)J;
Asciz	(Lscala/Function2;DJ)J;
NameAndType	apply$mcLDL$sp:(Lscala/Function2;DJ)J
Method	scala/Function2$class.apply$mcLDL$sp:(Lscala/Function2;DJ)J
Asciz	apply$mcDDL$sp;
Asciz	(DJ)D;
Asciz	(Lscala/Function2;DJ)D;
NameAndType	apply$mcDDL$sp:(Lscala/Function2;DJ)D
Method	scala/Function2$class.apply$mcDDL$sp:(Lscala/Function2;DJ)D
Asciz	apply$mcVDD$sp;
Asciz	(DD)V;
Asciz	(Lscala/Function2;DD)V;
NameAndType	apply$mcVDD$sp:(Lscala/Function2;DD)V
Method	scala/Function2$class.apply$mcVDD$sp:(Lscala/Function2;DD)V
Asciz	apply$mcZDD$sp;
Asciz	(DD)Z;
Asciz	(Lscala/Function2;DD)Z;
NameAndType	apply$mcZDD$sp:(Lscala/Function2;DD)Z
Method	scala/Function2$class.apply$mcZDD$sp:(Lscala/Function2;DD)Z
Asciz	apply$mcIDD$sp;
Asciz	(DD)I;
Asciz	(Lscala/Function2;DD)I;
NameAndType	apply$mcIDD$sp:(Lscala/Function2;DD)I
Method	scala/Function2$class.apply$mcIDD$sp:(Lscala/Function2;DD)I
Asciz	apply$mcLDD$sp;
Asciz	(DD)J;
Asciz	(Lscala/Function2;DD)J;
NameAndType	apply$mcLDD$sp:(Lscala/Function2;DD)J
Method	scala/Function2$class.apply$mcLDD$sp:(Lscala/Function2;DD)J
Asciz	apply$mcDDD$sp;
Asciz	(DD)D;
Asciz	(Lscala/Function2;DD)D;
NameAndType	apply$mcDDD$sp:(Lscala/Function2;DD)D
Method	scala/Function2$class.apply$mcDDD$sp:(Lscala/Function2;DD)D
Asciz	curried;
Asciz	()Lscala/Function1;;
Asciz	(Lscala/Function2;)Lscala/Function1;;
NameAndType	curried:(Lscala/Function2;)Lscala/Function1;
Method	scala/Function2$class.curried:(Lscala/Function2;)Lscala/Function1;
Asciz	curried$mcVII$sp;
NameAndType	curried$mcVII$sp:(Lscala/Function2;)Lscala/Function1;
Method	scala/Function2$class.curried$mcVII$sp:(Lscala/Function2;)Lscala/Function1;
Asciz	curried$mcZII$sp;
NameAndType	curried$mcZII$sp:(Lscala/Function2;)Lscala/Function1;
Method	scala/Function2$class.curried$mcZII$sp:(Lscala/Function2;)Lscala/Function1;
Asciz	curried$mcIII$sp;
NameAndType	curried$mcIII$sp:(Lscala/Function2;)Lscala/Function1;
Method	scala/Function2$class.curried$mcIII$sp:(Lscala/Function2;)Lscala/Function1;
Asciz	curried$mcLII$sp;
NameAndType	curried$mcLII$sp:(Lscala/Function2;)Lscala/Function1;
Method	scala/Function2$class.curried$mcLII$sp:(Lscala/Function2;)Lscala/Function1;
Asciz	curried$mcDII$sp;
NameAndType	curried$mcDII$sp:(Lscala/Function2;)Lscala/Function1;
Method	scala/Function2$class.curried$mcDII$sp:(Lscala/Function2;)Lscala/Function1;
Asciz	curried$mcVIL$sp;
NameAndType	curried$mcVIL$sp:(Lscala/Function2;)Lscala/Function1;
Method	scala/Function2$class.curried$mcVIL$sp:(Lscala/Function2;)Lscala/Function1;
Asciz	curried$mcZIL$sp;
NameAndType	curried$mcZIL$sp:(Lscala/Function2;)Lscala/Function1;
Method	scala/Function2$class.curried$mcZIL$sp:(Lscala/Function2;)Lscala/Function1;
Asciz	curried$mcIIL$sp;
NameAndType	curried$mcIIL$sp:(Lscala/Function2;)Lscala/Function1;
Method	scala/Function2$class.curried$mcIIL$sp:(Lscala/Function2;)Lscala/Function1;
Asciz	curried$mcLIL$sp;
NameAndType	curried$mcLIL$sp:(Lscala/Function2;)Lscala/Function1;
Method	scala/Function2$class.curried$mcLIL$sp:(Lscala/Function2;)Lscala/Function1;
Asciz	curried$mcDIL$sp;
NameAndType	curried$mcDIL$sp:(Lscala/Function2;)Lscala/Function1;
Method	scala/Function2$class.curried$mcDIL$sp:(Lscala/Function2;)Lscala/Function1;
Asciz	curried$mcVID$sp;
NameAndType	curried$mcVID$sp:(Lscala/Function2;)Lscala/Function1;
Method	scala/Function2$class.curried$mcVID$sp:(Lscala/Function2;)Lscala/Function1;
Asciz	curried$mcZID$sp;
NameAndType	curried$mcZID$sp:(Lscala/Function2;)Lscala/Function1;
Method	scala/Function2$class.curried$mcZID$sp:(Lscala/Function2;)Lscala/Function1;
Asciz	curried$mcIID$sp;
NameAndType	curried$mcIID$sp:(Lscala/Function2;)Lscala/Function1;
Method	scala/Function2$class.curried$mcIID$sp:(Lscala/Function2;)Lscala/Function1;
Asciz	curried$mcLID$sp;
NameAndType	curried$mcLID$sp:(Lscala/Function2;)Lscala/Function1;
Method	scala/Function2$class.curried$mcLID$sp:(Lscala/Function2;)Lscala/Function1;
Asciz	curried$mcDID$sp;
NameAndType	curried$mcDID$sp:(Lscala/Function2;)Lscala/Function1;
Method	scala/Function2$class.curried$mcDID$sp:(Lscala/Function2;)Lscala/Function1;
Asciz	curried$mcVLI$sp;
NameAndType	curried$mcVLI$sp:(Lscala/Function2;)Lscala/Function1;
Method	scala/Function2$class.curried$mcVLI$sp:(Lscala/Function2;)Lscala/Function1;
Asciz	curried$mcZLI$sp;
NameAndType	curried$mcZLI$sp:(Lscala/Function2;)Lscala/Function1;
Method	scala/Function2$class.curried$mcZLI$sp:(Lscala/Function2;)Lscala/Function1;
Asciz	curried$mcILI$sp;
NameAndType	curried$mcILI$sp:(Lscala/Function2;)Lscala/Function1;
Method	scala/Function2$class.curried$mcILI$sp:(Lscala/Function2;)Lscala/Function1;
Asciz	curried$mcLLI$sp;
NameAndType	curried$mcLLI$sp:(Lscala/Function2;)Lscala/Function1;
Method	scala/Function2$class.curried$mcLLI$sp:(Lscala/Function2;)Lscala/Function1;
Asciz	curried$mcDLI$sp;
NameAndType	curried$mcDLI$sp:(Lscala/Function2;)Lscala/Function1;
Method	scala/Function2$class.curried$mcDLI$sp:(Lscala/Function2;)Lscala/Function1;
Asciz	curried$mcVLL$sp;
NameAndType	curried$mcVLL$sp:(Lscala/Function2;)Lscala/Function1;
Method	scala/Function2$class.curried$mcVLL$sp:(Lscala/Function2;)Lscala/Function1;
Asciz	curried$mcZLL$sp;
NameAndType	curried$mcZLL$sp:(Lscala/Function2;)Lscala/Function1;
Method	scala/Function2$class.curried$mcZLL$sp:(Lscala/Function2;)Lscala/Function1;
Asciz	curried$mcILL$sp;
NameAndType	curried$mcILL$sp:(Lscala/Function2;)Lscala/Function1;
Method	scala/Function2$class.curried$mcILL$sp:(Lscala/Function2;)Lscala/Function1;
Asciz	curried$mcLLL$sp;
NameAndType	curried$mcLLL$sp:(Lscala/Function2;)Lscala/Function1;
Method	scala/Function2$class.curried$mcLLL$sp:(Lscala/Function2;)Lscala/Function1;
Asciz	curried$mcDLL$sp;
NameAndType	curried$mcDLL$sp:(Lscala/Function2;)Lscala/Function1;
Method	scala/Function2$class.curried$mcDLL$sp:(Lscala/Function2;)Lscala/Function1;
Asciz	curried$mcVLD$sp;
NameAndType	curried$mcVLD$sp:(Lscala/Function2;)Lscala/Function1;
Method	scala/Function2$class.curried$mcVLD$sp:(Lscala/Function2;)Lscala/Function1;
Asciz	curried$mcZLD$sp;
NameAndType	curried$mcZLD$sp:(Lscala/Function2;)Lscala/Function1;
Method	scala/Function2$class.curried$mcZLD$sp:(Lscala/Function2;)Lscala/Function1;
Asciz	curried$mcILD$sp;
NameAndType	curried$mcILD$sp:(Lscala/Function2;)Lscala/Function1;
Method	scala/Function2$class.curried$mcILD$sp:(Lscala/Function2;)Lscala/Function1;
Asciz	curried$mcLLD$sp;
NameAndType	curried$mcLLD$sp:(Lscala/Function2;)Lscala/Function1;
Method	scala/Function2$class.curried$mcLLD$sp:(Lscala/Function2;)Lscala/Function1;
Asciz	curried$mcDLD$sp;
NameAndType	curried$mcDLD$sp:(Lscala/Function2;)Lscala/Function1;
Method	scala/Function2$class.curried$mcDLD$sp:(Lscala/Function2;)Lscala/Function1;
Asciz	curried$mcVDI$sp;
NameAndType	curried$mcVDI$sp:(Lscala/Function2;)Lscala/Function1;
Method	scala/Function2$class.curried$mcVDI$sp:(Lscala/Function2;)Lscala/Function1;
Asciz	curried$mcZDI$sp;
NameAndType	curried$mcZDI$sp:(Lscala/Function2;)Lscala/Function1;
Method	scala/Function2$class.curried$mcZDI$sp:(Lscala/Function2;)Lscala/Function1;
Asciz	curried$mcIDI$sp;
NameAndType	curried$mcIDI$sp:(Lscala/Function2;)Lscala/Function1;
Method	scala/Function2$class.curried$mcIDI$sp:(Lscala/Function2;)Lscala/Function1;
Asciz	curried$mcLDI$sp;
NameAndType	curried$mcLDI$sp:(Lscala/Function2;)Lscala/Function1;
Method	scala/Function2$class.curried$mcLDI$sp:(Lscala/Function2;)Lscala/Function1;
Asciz	curried$mcDDI$sp;
NameAndType	curried$mcDDI$sp:(Lscala/Function2;)Lscala/Function1;
Method	scala/Function2$class.curried$mcDDI$sp:(Lscala/Function2;)Lscala/Function1;
Asciz	curried$mcVDL$sp;
NameAndType	curried$mcVDL$sp:(Lscala/Function2;)Lscala/Function1;
Method	scala/Function2$class.curried$mcVDL$sp:(Lscala/Function2;)Lscala/Function1;
Asciz	curried$mcZDL$sp;
NameAndType	curried$mcZDL$sp:(Lscala/Function2;)Lscala/Function1;
Method	scala/Function2$class.curried$mcZDL$sp:(Lscala/Function2;)Lscala/Function1;
Asciz	curried$mcIDL$sp;
NameAndType	curried$mcIDL$sp:(Lscala/Function2;)Lscala/Function1;
Method	scala/Function2$class.curried$mcIDL$sp:(Lscala/Function2;)Lscala/Function1;
Asciz	curried$mcLDL$sp;
NameAndType	curried$mcLDL$sp:(Lscala/Function2;)Lscala/Function1;
Method	scala/Function2$class.curried$mcLDL$sp:(Lscala/Function2;)Lscala/Function1;
Asciz	curried$mcDDL$sp;
NameAndType	curried$mcDDL$sp:(Lscala/Function2;)Lscala/Function1;
Method	scala/Function2$class.curried$mcDDL$sp:(Lscala/Function2;)Lscala/Function1;
Asciz	curried$mcVDD$sp;
NameAndType	curried$mcVDD$sp:(Lscala/Function2;)Lscala/Function1;
Method	scala/Function2$class.curried$mcVDD$sp:(Lscala/Function2;)Lscala/Function1;
Asciz	curried$mcZDD$sp;
NameAndType	curried$mcZDD$sp:(Lscala/Function2;)Lscala/Function1;
Method	scala/Function2$class.curried$mcZDD$sp:(Lscala/Function2;)Lscala/Function1;
Asciz	curried$mcIDD$sp;
NameAndType	curried$mcIDD$sp:(Lscala/Function2;)Lscala/Function1;
Method	scala/Function2$class.curried$mcIDD$sp:(Lscala/Function2;)Lscala/Function1;
Asciz	curried$mcLDD$sp;
NameAndType	curried$mcLDD$sp:(Lscala/Function2;)Lscala/Function1;
Method	scala/Function2$class.curried$mcLDD$sp:(Lscala/Function2;)Lscala/Function1;
Asciz	curried$mcDDD$sp;
NameAndType	curried$mcDDD$sp:(Lscala/Function2;)Lscala/Function1;
Method	scala/Function2$class.curried$mcDDD$sp:(Lscala/Function2;)Lscala/Function1;
Asciz	curry;
NameAndType	curry:(Lscala/Function2;)Lscala/Function1;
Method	scala/Function2$class.curry:(Lscala/Function2;)Lscala/Function1;
Asciz	Deprecated;
Asciz	curry$mcVII$sp;
NameAndType	curry$mcVII$sp:(Lscala/Function2;)Lscala/Function1;
Method	scala/Function2$class.curry$mcVII$sp:(Lscala/Function2;)Lscala/Function1;
Asciz	curry$mcZII$sp;
NameAndType	curry$mcZII$sp:(Lscala/Function2;)Lscala/Function1;
Method	scala/Function2$class.curry$mcZII$sp:(Lscala/Function2;)Lscala/Function1;
Asciz	curry$mcIII$sp;
NameAndType	curry$mcIII$sp:(Lscala/Function2;)Lscala/Function1;
Method	scala/Function2$class.curry$mcIII$sp:(Lscala/Function2;)Lscala/Function1;
Asciz	curry$mcLII$sp;
NameAndType	curry$mcLII$sp:(Lscala/Function2;)Lscala/Function1;
Method	scala/Function2$class.curry$mcLII$sp:(Lscala/Function2;)Lscala/Function1;
Asciz	curry$mcDII$sp;
NameAndType	curry$mcDII$sp:(Lscala/Function2;)Lscala/Function1;
Method	scala/Function2$class.curry$mcDII$sp:(Lscala/Function2;)Lscala/Function1;
Asciz	curry$mcVIL$sp;
NameAndType	curry$mcVIL$sp:(Lscala/Function2;)Lscala/Function1;
Method	scala/Function2$class.curry$mcVIL$sp:(Lscala/Function2;)Lscala/Function1;
Asciz	curry$mcZIL$sp;
NameAndType	curry$mcZIL$sp:(Lscala/Function2;)Lscala/Function1;
Method	scala/Function2$class.curry$mcZIL$sp:(Lscala/Function2;)Lscala/Function1;
Asciz	curry$mcIIL$sp;
NameAndType	curry$mcIIL$sp:(Lscala/Function2;)Lscala/Function1;
Method	scala/Function2$class.curry$mcIIL$sp:(Lscala/Function2;)Lscala/Function1;
Asciz	curry$mcLIL$sp;
NameAndType	curry$mcLIL$sp:(Lscala/Function2;)Lscala/Function1;
Method	scala/Function2$class.curry$mcLIL$sp:(Lscala/Function2;)Lscala/Function1;
Asciz	curry$mcDIL$sp;
NameAndType	curry$mcDIL$sp:(Lscala/Function2;)Lscala/Function1;
Method	scala/Function2$class.curry$mcDIL$sp:(Lscala/Function2;)Lscala/Function1;
Asciz	curry$mcVID$sp;
NameAndType	curry$mcVID$sp:(Lscala/Function2;)Lscala/Function1;
Method	scala/Function2$class.curry$mcVID$sp:(Lscala/Function2;)Lscala/Function1;
Asciz	curry$mcZID$sp;
NameAndType	curry$mcZID$sp:(Lscala/Function2;)Lscala/Function1;
Method	scala/Function2$class.curry$mcZID$sp:(Lscala/Function2;)Lscala/Function1;
Asciz	curry$mcIID$sp;
NameAndType	curry$mcIID$sp:(Lscala/Function2;)Lscala/Function1;
Method	scala/Function2$class.curry$mcIID$sp:(Lscala/Function2;)Lscala/Function1;
Asciz	curry$mcLID$sp;
NameAndType	curry$mcLID$sp:(Lscala/Function2;)Lscala/Function1;
Method	scala/Function2$class.curry$mcLID$sp:(Lscala/Function2;)Lscala/Function1;
Asciz	curry$mcDID$sp;
NameAndType	curry$mcDID$sp:(Lscala/Function2;)Lscala/Function1;
Method	scala/Function2$class.curry$mcDID$sp:(Lscala/Function2;)Lscala/Function1;
Asciz	curry$mcVLI$sp;
NameAndType	curry$mcVLI$sp:(Lscala/Function2;)Lscala/Function1;
Method	scala/Function2$class.curry$mcVLI$sp:(Lscala/Function2;)Lscala/Function1;
Asciz	curry$mcZLI$sp;
NameAndType	curry$mcZLI$sp:(Lscala/Function2;)Lscala/Function1;
Method	scala/Function2$class.curry$mcZLI$sp:(Lscala/Function2;)Lscala/Function1;
Asciz	curry$mcILI$sp;
NameAndType	curry$mcILI$sp:(Lscala/Function2;)Lscala/Function1;
Method	scala/Function2$class.curry$mcILI$sp:(Lscala/Function2;)Lscala/Function1;
Asciz	curry$mcLLI$sp;
NameAndType	curry$mcLLI$sp:(Lscala/Function2;)Lscala/Function1;
Method	scala/Function2$class.curry$mcLLI$sp:(Lscala/Function2;)Lscala/Function1;
Asciz	curry$mcDLI$sp;
NameAndType	curry$mcDLI$sp:(Lscala/Function2;)Lscala/Function1;
Method	scala/Function2$class.curry$mcDLI$sp:(Lscala/Function2;)Lscala/Function1;
Asciz	curry$mcVLL$sp;
NameAndType	curry$mcVLL$sp:(Lscala/Function2;)Lscala/Function1;
Method	scala/Function2$class.curry$mcVLL$sp:(Lscala/Function2;)Lscala/Function1;
Asciz	curry$mcZLL$sp;
NameAndType	curry$mcZLL$sp:(Lscala/Function2;)Lscala/Function1;
Method	scala/Function2$class.curry$mcZLL$sp:(Lscala/Function2;)Lscala/Function1;
Asciz	curry$mcILL$sp;
NameAndType	curry$mcILL$sp:(Lscala/Function2;)Lscala/Function1;
Method	scala/Function2$class.curry$mcILL$sp:(Lscala/Function2;)Lscala/Function1;
Asciz	curry$mcLLL$sp;
NameAndType	curry$mcLLL$sp:(Lscala/Function2;)Lscala/Function1;
Method	scala/Function2$class.curry$mcLLL$sp:(Lscala/Function2;)Lscala/Function1;
Asciz	curry$mcDLL$sp;
NameAndType	curry$mcDLL$sp:(Lscala/Function2;)Lscala/Function1;
Method	scala/Function2$class.curry$mcDLL$sp:(Lscala/Function2;)Lscala/Function1;
Asciz	curry$mcVLD$sp;
NameAndType	curry$mcVLD$sp:(Lscala/Function2;)Lscala/Function1;
Method	scala/Function2$class.curry$mcVLD$sp:(Lscala/Function2;)Lscala/Function1;
Asciz	curry$mcZLD$sp;
NameAndType	curry$mcZLD$sp:(Lscala/Function2;)Lscala/Function1;
Method	scala/Function2$class.curry$mcZLD$sp:(Lscala/Function2;)Lscala/Function1;
Asciz	curry$mcILD$sp;
NameAndType	curry$mcILD$sp:(Lscala/Function2;)Lscala/Function1;
Method	scala/Function2$class.curry$mcILD$sp:(Lscala/Function2;)Lscala/Function1;
Asciz	curry$mcLLD$sp;
NameAndType	curry$mcLLD$sp:(Lscala/Function2;)Lscala/Function1;
Method	scala/Function2$class.curry$mcLLD$sp:(Lscala/Function2;)Lscala/Function1;
Asciz	curry$mcDLD$sp;
NameAndType	curry$mcDLD$sp:(Lscala/Function2;)Lscala/Function1;
Method	scala/Function2$class.curry$mcDLD$sp:(Lscala/Function2;)Lscala/Function1;
Asciz	curry$mcVDI$sp;
NameAndType	curry$mcVDI$sp:(Lscala/Function2;)Lscala/Function1;
Method	scala/Function2$class.curry$mcVDI$sp:(Lscala/Function2;)Lscala/Function1;
Asciz	curry$mcZDI$sp;
NameAndType	curry$mcZDI$sp:(Lscala/Function2;)Lscala/Function1;
Method	scala/Function2$class.curry$mcZDI$sp:(Lscala/Function2;)Lscala/Function1;
Asciz	curry$mcIDI$sp;
NameAndType	curry$mcIDI$sp:(Lscala/Function2;)Lscala/Function1;
Method	scala/Function2$class.curry$mcIDI$sp:(Lscala/Function2;)Lscala/Function1;
Asciz	curry$mcLDI$sp;
NameAndType	curry$mcLDI$sp:(Lscala/Function2;)Lscala/Function1;
Method	scala/Function2$class.curry$mcLDI$sp:(Lscala/Function2;)Lscala/Function1;
Asciz	curry$mcDDI$sp;
NameAndType	curry$mcDDI$sp:(Lscala/Function2;)Lscala/Function1;
Method	scala/Function2$class.curry$mcDDI$sp:(Lscala/Function2;)Lscala/Function1;
Asciz	curry$mcVDL$sp;
NameAndType	curry$mcVDL$sp:(Lscala/Function2;)Lscala/Function1;
Method	scala/Function2$class.curry$mcVDL$sp:(Lscala/Function2;)Lscala/Function1;
Asciz	curry$mcZDL$sp;
NameAndType	curry$mcZDL$sp:(Lscala/Function2;)Lscala/Function1;
Method	scala/Function2$class.curry$mcZDL$sp:(Lscala/Function2;)Lscala/Function1;
Asciz	curry$mcIDL$sp;
NameAndType	curry$mcIDL$sp:(Lscala/Function2;)Lscala/Function1;
Method	scala/Function2$class.curry$mcIDL$sp:(Lscala/Function2;)Lscala/Function1;
Asciz	curry$mcLDL$sp;
NameAndType	curry$mcLDL$sp:(Lscala/Function2;)Lscala/Function1;
Method	scala/Function2$class.curry$mcLDL$sp:(Lscala/Function2;)Lscala/Function1;
Asciz	curry$mcDDL$sp;
NameAndType	curry$mcDDL$sp:(Lscala/Function2;)Lscala/Function1;
Method	scala/Function2$class.curry$mcDDL$sp:(Lscala/Function2;)Lscala/Function1;
Asciz	curry$mcVDD$sp;
NameAndType	curry$mcVDD$sp:(Lscala/Function2;)Lscala/Function1;
Method	scala/Function2$class.curry$mcVDD$sp:(Lscala/Function2;)Lscala/Function1;
Asciz	curry$mcZDD$sp;
NameAndType	curry$mcZDD$sp:(Lscala/Function2;)Lscala/Function1;
Method	scala/Function2$class.curry$mcZDD$sp:(Lscala/Function2;)Lscala/Function1;
Asciz	curry$mcIDD$sp;
NameAndType	curry$mcIDD$sp:(Lscala/Function2;)Lscala/Function1;
Method	scala/Function2$class.curry$mcIDD$sp:(Lscala/Function2;)Lscala/Function1;
Asciz	curry$mcLDD$sp;
NameAndType	curry$mcLDD$sp:(Lscala/Function2;)Lscala/Function1;
Method	scala/Function2$class.curry$mcLDD$sp:(Lscala/Function2;)Lscala/Function1;
Asciz	curry$mcDDD$sp;
NameAndType	curry$mcDDD$sp:(Lscala/Function2;)Lscala/Function1;
Method	scala/Function2$class.curry$mcDDD$sp:(Lscala/Function2;)Lscala/Function1;
Asciz	tupled;
NameAndType	tupled:(Lscala/Function2;)Lscala/Function1;
Method	scala/Function2$class.tupled:(Lscala/Function2;)Lscala/Function1;
Asciz	tupled$mcVII$sp;
NameAndType	tupled$mcVII$sp:(Lscala/Function2;)Lscala/Function1;
Method	scala/Function2$class.tupled$mcVII$sp:(Lscala/Function2;)Lscala/Function1;
Asciz	tupled$mcZII$sp;
NameAndType	tupled$mcZII$sp:(Lscala/Function2;)Lscala/Function1;
Method	scala/Function2$class.tupled$mcZII$sp:(Lscala/Function2;)Lscala/Function1;
Asciz	tupled$mcIII$sp;
NameAndType	tupled$mcIII$sp:(Lscala/Function2;)Lscala/Function1;
Method	scala/Function2$class.tupled$mcIII$sp:(Lscala/Function2;)Lscala/Function1;
Asciz	tupled$mcLII$sp;
NameAndType	tupled$mcLII$sp:(Lscala/Function2;)Lscala/Function1;
Method	scala/Function2$class.tupled$mcLII$sp:(Lscala/Function2;)Lscala/Function1;
Asciz	tupled$mcDII$sp;
NameAndType	tupled$mcDII$sp:(Lscala/Function2;)Lscala/Function1;
Method	scala/Function2$class.tupled$mcDII$sp:(Lscala/Function2;)Lscala/Function1;
Asciz	tupled$mcVIL$sp;
NameAndType	tupled$mcVIL$sp:(Lscala/Function2;)Lscala/Function1;
Method	scala/Function2$class.tupled$mcVIL$sp:(Lscala/Function2;)Lscala/Function1;
Asciz	tupled$mcZIL$sp;
NameAndType	tupled$mcZIL$sp:(Lscala/Function2;)Lscala/Function1;
Method	scala/Function2$class.tupled$mcZIL$sp:(Lscala/Function2;)Lscala/Function1;
Asciz	tupled$mcIIL$sp;
NameAndType	tupled$mcIIL$sp:(Lscala/Function2;)Lscala/Function1;
Method	scala/Function2$class.tupled$mcIIL$sp:(Lscala/Function2;)Lscala/Function1;
Asciz	tupled$mcLIL$sp;
NameAndType	tupled$mcLIL$sp:(Lscala/Function2;)Lscala/Function1;
Method	scala/Function2$class.tupled$mcLIL$sp:(Lscala/Function2;)Lscala/Function1;
Asciz	tupled$mcDIL$sp;
NameAndType	tupled$mcDIL$sp:(Lscala/Function2;)Lscala/Function1;
Method	scala/Function2$class.tupled$mcDIL$sp:(Lscala/Function2;)Lscala/Function1;
Asciz	tupled$mcVID$sp;
NameAndType	tupled$mcVID$sp:(Lscala/Function2;)Lscala/Function1;
Method	scala/Function2$class.tupled$mcVID$sp:(Lscala/Function2;)Lscala/Function1;
Asciz	tupled$mcZID$sp;
NameAndType	tupled$mcZID$sp:(Lscala/Function2;)Lscala/Function1;
Method	scala/Function2$class.tupled$mcZID$sp:(Lscala/Function2;)Lscala/Function1;
Asciz	tupled$mcIID$sp;
NameAndType	tupled$mcIID$sp:(Lscala/Function2;)Lscala/Function1;
Method	scala/Function2$class.tupled$mcIID$sp:(Lscala/Function2;)Lscala/Function1;
Asciz	tupled$mcLID$sp;
NameAndType	tupled$mcLID$sp:(Lscala/Function2;)Lscala/Function1;
Method	scala/Function2$class.tupled$mcLID$sp:(Lscala/Function2;)Lscala/Function1;
Asciz	tupled$mcDID$sp;
NameAndType	tupled$mcDID$sp:(Lscala/Function2;)Lscala/Function1;
Method	scala/Function2$class.tupled$mcDID$sp:(Lscala/Function2;)Lscala/Function1;
Asciz	tupled$mcVLI$sp;
NameAndType	tupled$mcVLI$sp:(Lscala/Function2;)Lscala/Function1;
Method	scala/Function2$class.tupled$mcVLI$sp:(Lscala/Function2;)Lscala/Function1;
Asciz	tupled$mcZLI$sp;
NameAndType	tupled$mcZLI$sp:(Lscala/Function2;)Lscala/Function1;
Method	scala/Function2$class.tupled$mcZLI$sp:(Lscala/Function2;)Lscala/Function1;
Asciz	tupled$mcILI$sp;
NameAndType	tupled$mcILI$sp:(Lscala/Function2;)Lscala/Function1;
Method	scala/Function2$class.tupled$mcILI$sp:(Lscala/Function2;)Lscala/Function1;
Asciz	tupled$mcLLI$sp;
NameAndType	tupled$mcLLI$sp:(Lscala/Function2;)Lscala/Function1;
Method	scala/Function2$class.tupled$mcLLI$sp:(Lscala/Function2;)Lscala/Function1;
Asciz	tupled$mcDLI$sp;
NameAndType	tupled$mcDLI$sp:(Lscala/Function2;)Lscala/Function1;
Method	scala/Function2$class.tupled$mcDLI$sp:(Lscala/Function2;)Lscala/Function1;
Asciz	tupled$mcVLL$sp;
NameAndType	tupled$mcVLL$sp:(Lscala/Function2;)Lscala/Function1;
Method	scala/Function2$class.tupled$mcVLL$sp:(Lscala/Function2;)Lscala/Function1;
Asciz	tupled$mcZLL$sp;
NameAndType	tupled$mcZLL$sp:(Lscala/Function2;)Lscala/Function1;
Method	scala/Function2$class.tupled$mcZLL$sp:(Lscala/Function2;)Lscala/Function1;
Asciz	tupled$mcILL$sp;
NameAndType	tupled$mcILL$sp:(Lscala/Function2;)Lscala/Function1;
Method	scala/Function2$class.tupled$mcILL$sp:(Lscala/Function2;)Lscala/Function1;
Asciz	tupled$mcLLL$sp;
NameAndType	tupled$mcLLL$sp:(Lscala/Function2;)Lscala/Function1;
Method	scala/Function2$class.tupled$mcLLL$sp:(Lscala/Function2;)Lscala/Function1;
Asciz	tupled$mcDLL$sp;
NameAndType	tupled$mcDLL$sp:(Lscala/Function2;)Lscala/Function1;
Method	scala/Function2$class.tupled$mcDLL$sp:(Lscala/Function2;)Lscala/Function1;
Asciz	tupled$mcVLD$sp;
NameAndType	tupled$mcVLD$sp:(Lscala/Function2;)Lscala/Function1;
Method	scala/Function2$class.tupled$mcVLD$sp:(Lscala/Function2;)Lscala/Function1;
Asciz	tupled$mcZLD$sp;
NameAndType	tupled$mcZLD$sp:(Lscala/Function2;)Lscala/Function1;
Method	scala/Function2$class.tupled$mcZLD$sp:(Lscala/Function2;)Lscala/Function1;
Asciz	tupled$mcILD$sp;
NameAndType	tupled$mcILD$sp:(Lscala/Function2;)Lscala/Function1;
Method	scala/Function2$class.tupled$mcILD$sp:(Lscala/Function2;)Lscala/Function1;
Asciz	tupled$mcLLD$sp;
NameAndType	tupled$mcLLD$sp:(Lscala/Function2;)Lscala/Function1;
Method	scala/Function2$class.tupled$mcLLD$sp:(Lscala/Function2;)Lscala/Function1;
Asciz	tupled$mcDLD$sp;
NameAndType	tupled$mcDLD$sp:(Lscala/Function2;)Lscala/Function1;
Method	scala/Function2$class.tupled$mcDLD$sp:(Lscala/Function2;)Lscala/Function1;
Asciz	tupled$mcVDI$sp;
NameAndType	tupled$mcVDI$sp:(Lscala/Function2;)Lscala/Function1;
Method	scala/Function2$class.tupled$mcVDI$sp:(Lscala/Function2;)Lscala/Function1;
Asciz	tupled$mcZDI$sp;
NameAndType	tupled$mcZDI$sp:(Lscala/Function2;)Lscala/Function1;
Method	scala/Function2$class.tupled$mcZDI$sp:(Lscala/Function2;)Lscala/Function1;
Asciz	tupled$mcIDI$sp;
NameAndType	tupled$mcIDI$sp:(Lscala/Function2;)Lscala/Function1;
Method	scala/Function2$class.tupled$mcIDI$sp:(Lscala/Function2;)Lscala/Function1;
Asciz	tupled$mcLDI$sp;
NameAndType	tupled$mcLDI$sp:(Lscala/Function2;)Lscala/Function1;
Method	scala/Function2$class.tupled$mcLDI$sp:(Lscala/Function2;)Lscala/Function1;
Asciz	tupled$mcDDI$sp;
NameAndType	tupled$mcDDI$sp:(Lscala/Function2;)Lscala/Function1;
Method	scala/Function2$class.tupled$mcDDI$sp:(Lscala/Function2;)Lscala/Function1;
Asciz	tupled$mcVDL$sp;
NameAndType	tupled$mcVDL$sp:(Lscala/Function2;)Lscala/Function1;
Method	scala/Function2$class.tupled$mcVDL$sp:(Lscala/Function2;)Lscala/Function1;
Asciz	tupled$mcZDL$sp;
NameAndType	tupled$mcZDL$sp:(Lscala/Function2;)Lscala/Function1;
Method	scala/Function2$class.tupled$mcZDL$sp:(Lscala/Function2;)Lscala/Function1;
Asciz	tupled$mcIDL$sp;
NameAndType	tupled$mcIDL$sp:(Lscala/Function2;)Lscala/Function1;
Method	scala/Function2$class.tupled$mcIDL$sp:(Lscala/Function2;)Lscala/Function1;
Asciz	tupled$mcLDL$sp;
NameAndType	tupled$mcLDL$sp:(Lscala/Function2;)Lscala/Function1;
Method	scala/Function2$class.tupled$mcLDL$sp:(Lscala/Function2;)Lscala/Function1;
Asciz	tupled$mcDDL$sp;
NameAndType	tupled$mcDDL$sp:(Lscala/Function2;)Lscala/Function1;
Method	scala/Function2$class.tupled$mcDDL$sp:(Lscala/Function2;)Lscala/Function1;
Asciz	tupled$mcVDD$sp;
NameAndType	tupled$mcVDD$sp:(Lscala/Function2;)Lscala/Function1;
Method	scala/Function2$class.tupled$mcVDD$sp:(Lscala/Function2;)Lscala/Function1;
Asciz	tupled$mcZDD$sp;
NameAndType	tupled$mcZDD$sp:(Lscala/Function2;)Lscala/Function1;
Method	scala/Function2$class.tupled$mcZDD$sp:(Lscala/Function2;)Lscala/Function1;
Asciz	tupled$mcIDD$sp;
NameAndType	tupled$mcIDD$sp:(Lscala/Function2;)Lscala/Function1;
Method	scala/Function2$class.tupled$mcIDD$sp:(Lscala/Function2;)Lscala/Function1;
Asciz	tupled$mcLDD$sp;
NameAndType	tupled$mcLDD$sp:(Lscala/Function2;)Lscala/Function1;
Method	scala/Function2$class.tupled$mcLDD$sp:(Lscala/Function2;)Lscala/Function1;
Asciz	tupled$mcDDD$sp;
NameAndType	tupled$mcDDD$sp:(Lscala/Function2;)Lscala/Function1;
Method	scala/Function2$class.tupled$mcDDD$sp:(Lscala/Function2;)Lscala/Function1;
Asciz	apply;
Asciz	(Lscala/actors/AbstractActor;Lscala/actors/remote/Proxy;)V;
Asciz	scala/actors/AbstractActor;
class	scala/actors/AbstractActor
Asciz	linkTo;
Asciz	(Lscala/actors/AbstractActor;)V;
NameAndType	linkTo:(Lscala/actors/AbstractActor;)V
InterfaceMethod	scala/actors/AbstractActor.linkTo:(Lscala/actors/AbstractActor;)V
Asciz	target;
Asciz	Lscala/actors/AbstractActor;;
Asciz	creator;
Asciz	Lscala/actors/remote/Proxy;;
Asciz	toString;
Asciz	()Ljava/lang/String;;
Asciz	<LinkToFun>;
String	<LinkToFun>
Asciz	(Ljava/lang/Object;Ljava/lang/Object;)Ljava/lang/Object;;
Asciz	scala/actors/remote/Proxy;
class	scala/actors/remote/Proxy
Asciz	scala/actors/remote/LinkToFun;
class	scala/actors/remote/LinkToFun
NameAndType	apply:(Lscala/actors/AbstractActor;Lscala/actors/remote/Proxy;)V
Method	scala/actors/remote/LinkToFun.apply:(Lscala/actors/AbstractActor;Lscala/actors/remote/Proxy;)V
Asciz	scala/runtime/BoxedUnit;
class	scala/runtime/BoxedUnit
Asciz	UNIT;
Asciz	Lscala/runtime/BoxedUnit;;
NameAndType	UNIT:Lscala/runtime/BoxedUnit;
Field	scala/runtime/BoxedUnit.UNIT:Lscala/runtime/BoxedUnit;
Asciz	Ljava/lang/Object;;
Asciz	<init>;
Asciz	()V;
Asciz	java/lang/Object;
class	java/lang/Object
NameAndType	"<init>":()V
Method	java/lang/Object."<init>":()V
Asciz	$init$;
Asciz	(Lscala/Function2;)V;
NameAndType	$init$:(Lscala/Function2;)V
Method	scala/Function2$class.$init$:(Lscala/Function2;)V
Asciz	ScalaSig;
Asciz	Ljava/lang/Object;Lscala/Function2<Lscala/actors/AbstractActor;Lscala/actors/remote/Proxy;Ljava/lang/Object;>;Lscala/ScalaObject;;
Asciz	Signature;
Asciz	Lscala/reflect/ScalaSignature;;
Asciz	bytes;
Asciz	e2\"\t!\n&t7V8Gk:T!a\rI,Wn;f\t)a!bGR|'o)1oY1mC1%\"a\t1Q!!\t1gn!!.<b\t\tBBPE*,7\r\t'Q1\"DH\r%QC\n\rVt7\r^5p]J\"a\rI!!7:bGR5\r^8s!\tYB$D\ti\"AAQe>D?%E+:LGE%1E'G.Y(cUGC&a%=S:LGOOA1S!\tAKCBH.=-j\")1A;be,GC/Q!$AdeGo:\tAAIQ|7:j]$A\r\tMJ!\rM#(/8hQ\tao%H\rg.7juG.;
Asciz	RuntimeVisibleAnnotations;
Asciz	scala/Function2;
class	scala/Function2
Asciz	scala/ScalaObject;
class	scala/ScalaObject
Asciz	java/io/Serializable;
class	java/io/Serializable

{
public void apply$mcVII$sp(int, int);
  Signature: (II)V
  Code:
   Stack=3, Locals=3, Args_size=3
	aload_0
	iload_1
	iload_2
	invokestatic	Method scala/Function2$class.apply$mcVII$sp:(Lscala/Function2;II)V
	return
  Labels:
  LocalVariableTable: 
   Start  Length  Slot  Name   Signature
   0      7      0    this       Lscala/actors/remote/LinkToFun;
   0      7      1    v1       I
   0      7      2    v2       I


public boolean apply$mcZII$sp(int, int);
  Signature: (II)Z
  Code:
   Stack=3, Locals=3, Args_size=3
	aload_0
	iload_1
	iload_2
	invokestatic	Method scala/Function2$class.apply$mcZII$sp:(Lscala/Function2;II)Z
	ireturn
  Labels:
  LocalVariableTable: 
   Start  Length  Slot  Name   Signature
   0      7      0    this       Lscala/actors/remote/LinkToFun;
   0      7      1    v1       I
   0      7      2    v2       I


public int apply$mcIII$sp(int, int);
  Signature: (II)I
  Code:
   Stack=3, Locals=3, Args_size=3
	aload_0
	iload_1
	iload_2
	invokestatic	Method scala/Function2$class.apply$mcIII$sp:(Lscala/Function2;II)I
	ireturn
  Labels:
  LocalVariableTable: 
   Start  Length  Slot  Name   Signature
   0      7      0    this       Lscala/actors/remote/LinkToFun;
   0      7      1    v1       I
   0      7      2    v2       I


public long apply$mcLII$sp(int, int);
  Signature: (II)J
  Code:
   Stack=3, Locals=3, Args_size=3
	aload_0
	iload_1
	iload_2
	invokestatic	Method scala/Function2$class.apply$mcLII$sp:(Lscala/Function2;II)J
	lreturn
  Labels:
  LocalVariableTable: 
   Start  Length  Slot  Name   Signature
   0      7      0    this       Lscala/actors/remote/LinkToFun;
   0      7      1    v1       I
   0      7      2    v2       I


public double apply$mcDII$sp(int, int);
  Signature: (II)D
  Code:
   Stack=3, Locals=3, Args_size=3
	aload_0
	iload_1
	iload_2
	invokestatic	Method scala/Function2$class.apply$mcDII$sp:(Lscala/Function2;II)D
	dreturn
  Labels:
  LocalVariableTable: 
   Start  Length  Slot  Name   Signature
   0      7      0    this       Lscala/actors/remote/LinkToFun;
   0      7      1    v1       I
   0      7      2    v2       I


public void apply$mcVIL$sp(int, long);
  Signature: (IJ)V
  Code:
   Stack=4, Locals=4, Args_size=3
	aload_0
	iload_1
	lload_2
	invokestatic	Method scala/Function2$class.apply$mcVIL$sp:(Lscala/Function2;IJ)V
	return
  Labels:
  LocalVariableTable: 
   Start  Length  Slot  Name   Signature
   0      7      0    this       Lscala/actors/remote/LinkToFun;
   0      7      1    v1       I
   0      7      2    v2       J


public boolean apply$mcZIL$sp(int, long);
  Signature: (IJ)Z
  Code:
   Stack=4, Locals=4, Args_size=3
	aload_0
	iload_1
	lload_2
	invokestatic	Method scala/Function2$class.apply$mcZIL$sp:(Lscala/Function2;IJ)Z
	ireturn
  Labels:
  LocalVariableTable: 
   Start  Length  Slot  Name   Signature
   0      7      0    this       Lscala/actors/remote/LinkToFun;
   0      7      1    v1       I
   0      7      2    v2       J


public int apply$mcIIL$sp(int, long);
  Signature: (IJ)I
  Code:
   Stack=4, Locals=4, Args_size=3
	aload_0
	iload_1
	lload_2
	invokestatic	Method scala/Function2$class.apply$mcIIL$sp:(Lscala/Function2;IJ)I
	ireturn
  Labels:
  LocalVariableTable: 
   Start  Length  Slot  Name   Signature
   0      7      0    this       Lscala/actors/remote/LinkToFun;
   0      7      1    v1       I
   0      7      2    v2       J


public long apply$mcLIL$sp(int, long);
  Signature: (IJ)J
  Code:
   Stack=4, Locals=4, Args_size=3
	aload_0
	iload_1
	lload_2
	invokestatic	Method scala/Function2$class.apply$mcLIL$sp:(Lscala/Function2;IJ)J
	lreturn
  Labels:
  LocalVariableTable: 
   Start  Length  Slot  Name   Signature
   0      7      0    this       Lscala/actors/remote/LinkToFun;
   0      7      1    v1       I
   0      7      2    v2       J


public double apply$mcDIL$sp(int, long);
  Signature: (IJ)D
  Code:
   Stack=4, Locals=4, Args_size=3
	aload_0
	iload_1
	lload_2
	invokestatic	Method scala/Function2$class.apply$mcDIL$sp:(Lscala/Function2;IJ)D
	dreturn
  Labels:
  LocalVariableTable: 
   Start  Length  Slot  Name   Signature
   0      7      0    this       Lscala/actors/remote/LinkToFun;
   0      7      1    v1       I
   0      7      2    v2       J


public void apply$mcVID$sp(int, double);
  Signature: (ID)V
  Code:
   Stack=4, Locals=4, Args_size=3
	aload_0
	iload_1
	dload_2
	invokestatic	Method scala/Function2$class.apply$mcVID$sp:(Lscala/Function2;ID)V
	return
  Labels:
  LocalVariableTable: 
   Start  Length  Slot  Name   Signature
   0      7      0    this       Lscala/actors/remote/LinkToFun;
   0      7      1    v1       I
   0      7      2    v2       D


public boolean apply$mcZID$sp(int, double);
  Signature: (ID)Z
  Code:
   Stack=4, Locals=4, Args_size=3
	aload_0
	iload_1
	dload_2
	invokestatic	Method scala/Function2$class.apply$mcZID$sp:(Lscala/Function2;ID)Z
	ireturn
  Labels:
  LocalVariableTable: 
   Start  Length  Slot  Name   Signature
   0      7      0    this       Lscala/actors/remote/LinkToFun;
   0      7      1    v1       I
   0      7      2    v2       D


public int apply$mcIID$sp(int, double);
  Signature: (ID)I
  Code:
   Stack=4, Locals=4, Args_size=3
	aload_0
	iload_1
	dload_2
	invokestatic	Method scala/Function2$class.apply$mcIID$sp:(Lscala/Function2;ID)I
	ireturn
  Labels:
  LocalVariableTable: 
   Start  Length  Slot  Name   Signature
   0      7      0    this       Lscala/actors/remote/LinkToFun;
   0      7      1    v1       I
   0      7      2    v2       D


public long apply$mcLID$sp(int, double);
  Signature: (ID)J
  Code:
   Stack=4, Locals=4, Args_size=3
	aload_0
	iload_1
	dload_2
	invokestatic	Method scala/Function2$class.apply$mcLID$sp:(Lscala/Function2;ID)J
	lreturn
  Labels:
  LocalVariableTable: 
   Start  Length  Slot  Name   Signature
   0      7      0    this       Lscala/actors/remote/LinkToFun;
   0      7      1    v1       I
   0      7      2    v2       D


public double apply$mcDID$sp(int, double);
  Signature: (ID)D
  Code:
   Stack=4, Locals=4, Args_size=3
	aload_0
	iload_1
	dload_2
	invokestatic	Method scala/Function2$class.apply$mcDID$sp:(Lscala/Function2;ID)D
	dreturn
  Labels:
  LocalVariableTable: 
   Start  Length  Slot  Name   Signature
   0      7      0    this       Lscala/actors/remote/LinkToFun;
   0      7      1    v1       I
   0      7      2    v2       D


public void apply$mcVLI$sp(long, int);
  Signature: (JI)V
  Code:
   Stack=4, Locals=4, Args_size=3
	aload_0
	lload_1
	iload_3
	invokestatic	Method scala/Function2$class.apply$mcVLI$sp:(Lscala/Function2;JI)V
	return
  Labels:
  LocalVariableTable: 
   Start  Length  Slot  Name   Signature
   0      7      0    this       Lscala/actors/remote/LinkToFun;
   0      7      1    v1       J
   0      7      3    v2       I


public boolean apply$mcZLI$sp(long, int);
  Signature: (JI)Z
  Code:
   Stack=4, Locals=4, Args_size=3
	aload_0
	lload_1
	iload_3
	invokestatic	Method scala/Function2$class.apply$mcZLI$sp:(Lscala/Function2;JI)Z
	ireturn
  Labels:
  LocalVariableTable: 
   Start  Length  Slot  Name   Signature
   0      7      0    this       Lscala/actors/remote/LinkToFun;
   0      7      1    v1       J
   0      7      3    v2       I


public int apply$mcILI$sp(long, int);
  Signature: (JI)I
  Code:
   Stack=4, Locals=4, Args_size=3
	aload_0
	lload_1
	iload_3
	invokestatic	Method scala/Function2$class.apply$mcILI$sp:(Lscala/Function2;JI)I
	ireturn
  Labels:
  LocalVariableTable: 
   Start  Length  Slot  Name   Signature
   0      7      0    this       Lscala/actors/remote/LinkToFun;
   0      7      1    v1       J
   0      7      3    v2       I


public long apply$mcLLI$sp(long, int);
  Signature: (JI)J
  Code:
   Stack=4, Locals=4, Args_size=3
	aload_0
	lload_1
	iload_3
	invokestatic	Method scala/Function2$class.apply$mcLLI$sp:(Lscala/Function2;JI)J
	lreturn
  Labels:
  LocalVariableTable: 
   Start  Length  Slot  Name   Signature
   0      7      0    this       Lscala/actors/remote/LinkToFun;
   0      7      1    v1       J
   0      7      3    v2       I


public double apply$mcDLI$sp(long, int);
  Signature: (JI)D
  Code:
   Stack=4, Locals=4, Args_size=3
	aload_0
	lload_1
	iload_3
	invokestatic	Method scala/Function2$class.apply$mcDLI$sp:(Lscala/Function2;JI)D
	dreturn
  Labels:
  LocalVariableTable: 
   Start  Length  Slot  Name   Signature
   0      7      0    this       Lscala/actors/remote/LinkToFun;
   0      7      1    v1       J
   0      7      3    v2       I


public void apply$mcVLL$sp(long, long);
  Signature: (JJ)V
  Code:
   Stack=5, Locals=5, Args_size=3
	aload_0
	lload_1
	lload_3
	invokestatic	Method scala/Function2$class.apply$mcVLL$sp:(Lscala/Function2;JJ)V
	return
  Labels:
  LocalVariableTable: 
   Start  Length  Slot  Name   Signature
   0      7      0    this       Lscala/actors/remote/LinkToFun;
   0      7      1    v1       J
   0      7      3    v2       J


public boolean apply$mcZLL$sp(long, long);
  Signature: (JJ)Z
  Code:
   Stack=5, Locals=5, Args_size=3
	aload_0
	lload_1
	lload_3
	invokestatic	Method scala/Function2$class.apply$mcZLL$sp:(Lscala/Function2;JJ)Z
	ireturn
  Labels:
  LocalVariableTable: 
   Start  Length  Slot  Name   Signature
   0      7      0    this       Lscala/actors/remote/LinkToFun;
   0      7      1    v1       J
   0      7      3    v2       J


public int apply$mcILL$sp(long, long);
  Signature: (JJ)I
  Code:
   Stack=5, Locals=5, Args_size=3
	aload_0
	lload_1
	lload_3
	invokestatic	Method scala/Function2$class.apply$mcILL$sp:(Lscala/Function2;JJ)I
	ireturn
  Labels:
  LocalVariableTable: 
   Start  Length  Slot  Name   Signature
   0      7      0    this       Lscala/actors/remote/LinkToFun;
   0      7      1    v1       J
   0      7      3    v2       J


public long apply$mcLLL$sp(long, long);
  Signature: (JJ)J
  Code:
   Stack=5, Locals=5, Args_size=3
	aload_0
	lload_1
	lload_3
	invokestatic	Method scala/Function2$class.apply$mcLLL$sp:(Lscala/Function2;JJ)J
	lreturn
  Labels:
  LocalVariableTable: 
   Start  Length  Slot  Name   Signature
   0      7      0    this       Lscala/actors/remote/LinkToFun;
   0      7      1    v1       J
   0      7      3    v2       J


public double apply$mcDLL$sp(long, long);
  Signature: (JJ)D
  Code:
   Stack=5, Locals=5, Args_size=3
	aload_0
	lload_1
	lload_3
	invokestatic	Method scala/Function2$class.apply$mcDLL$sp:(Lscala/Function2;JJ)D
	dreturn
  Labels:
  LocalVariableTable: 
   Start  Length  Slot  Name   Signature
   0      7      0    this       Lscala/actors/remote/LinkToFun;
   0      7      1    v1       J
   0      7      3    v2       J


public void apply$mcVLD$sp(long, double);
  Signature: (JD)V
  Code:
   Stack=5, Locals=5, Args_size=3
	aload_0
	lload_1
	dload_3
	invokestatic	Method scala/Function2$class.apply$mcVLD$sp:(Lscala/Function2;JD)V
	return
  Labels:
  LocalVariableTable: 
   Start  Length  Slot  Name   Signature
   0      7      0    this       Lscala/actors/remote/LinkToFun;
   0      7      1    v1       J
   0      7      3    v2       D


public boolean apply$mcZLD$sp(long, double);
  Signature: (JD)Z
  Code:
   Stack=5, Locals=5, Args_size=3
	aload_0
	lload_1
	dload_3
	invokestatic	Method scala/Function2$class.apply$mcZLD$sp:(Lscala/Function2;JD)Z
	ireturn
  Labels:
  LocalVariableTable: 
   Start  Length  Slot  Name   Signature
   0      7      0    this       Lscala/actors/remote/LinkToFun;
   0      7      1    v1       J
   0      7      3    v2       D


public int apply$mcILD$sp(long, double);
  Signature: (JD)I
  Code:
   Stack=5, Locals=5, Args_size=3
	aload_0
	lload_1
	dload_3
	invokestatic	Method scala/Function2$class.apply$mcILD$sp:(Lscala/Function2;JD)I
	ireturn
  Labels:
  LocalVariableTable: 
   Start  Length  Slot  Name   Signature
   0      7      0    this       Lscala/actors/remote/LinkToFun;
   0      7      1    v1       J
   0      7      3    v2       D


public long apply$mcLLD$sp(long, double);
  Signature: (JD)J
  Code:
   Stack=5, Locals=5, Args_size=3
	aload_0
	lload_1
	dload_3
	invokestatic	Method scala/Function2$class.apply$mcLLD$sp:(Lscala/Function2;JD)J
	lreturn
  Labels:
  LocalVariableTable: 
   Start  Length  Slot  Name   Signature
   0      7      0    this       Lscala/actors/remote/LinkToFun;
   0      7      1    v1       J
   0      7      3    v2       D


public double apply$mcDLD$sp(long, double);
  Signature: (JD)D
  Code:
   Stack=5, Locals=5, Args_size=3
	aload_0
	lload_1
	dload_3
	invokestatic	Method scala/Function2$class.apply$mcDLD$sp:(Lscala/Function2;JD)D
	dreturn
  Labels:
  LocalVariableTable: 
   Start  Length  Slot  Name   Signature
   0      7      0    this       Lscala/actors/remote/LinkToFun;
   0      7      1    v1       J
   0      7      3    v2       D


public void apply$mcVDI$sp(double, int);
  Signature: (DI)V
  Code:
   Stack=4, Locals=4, Args_size=3
	aload_0
	dload_1
	iload_3
	invokestatic	Method scala/Function2$class.apply$mcVDI$sp:(Lscala/Function2;DI)V
	return
  Labels:
  LocalVariableTable: 
   Start  Length  Slot  Name   Signature
   0      7      0    this       Lscala/actors/remote/LinkToFun;
   0      7      1    v1       D
   0      7      3    v2       I


public boolean apply$mcZDI$sp(double, int);
  Signature: (DI)Z
  Code:
   Stack=4, Locals=4, Args_size=3
	aload_0
	dload_1
	iload_3
	invokestatic	Method scala/Function2$class.apply$mcZDI$sp:(Lscala/Function2;DI)Z
	ireturn
  Labels:
  LocalVariableTable: 
   Start  Length  Slot  Name   Signature
   0      7      0    this       Lscala/actors/remote/LinkToFun;
   0      7      1    v1       D
   0      7      3    v2       I


public int apply$mcIDI$sp(double, int);
  Signature: (DI)I
  Code:
   Stack=4, Locals=4, Args_size=3
	aload_0
	dload_1
	iload_3
	invokestatic	Method scala/Function2$class.apply$mcIDI$sp:(Lscala/Function2;DI)I
	ireturn
  Labels:
  LocalVariableTable: 
   Start  Length  Slot  Name   Signature
   0      7      0    this       Lscala/actors/remote/LinkToFun;
   0      7      1    v1       D
   0      7      3    v2       I


public long apply$mcLDI$sp(double, int);
  Signature: (DI)J
  Code:
   Stack=4, Locals=4, Args_size=3
	aload_0
	dload_1
	iload_3
	invokestatic	Method scala/Function2$class.apply$mcLDI$sp:(Lscala/Function2;DI)J
	lreturn
  Labels:
  LocalVariableTable: 
   Start  Length  Slot  Name   Signature
   0      7      0    this       Lscala/actors/remote/LinkToFun;
   0      7      1    v1       D
   0      7      3    v2       I


public double apply$mcDDI$sp(double, int);
  Signature: (DI)D
  Code:
   Stack=4, Locals=4, Args_size=3
	aload_0
	dload_1
	iload_3
	invokestatic	Method scala/Function2$class.apply$mcDDI$sp:(Lscala/Function2;DI)D
	dreturn
  Labels:
  LocalVariableTable: 
   Start  Length  Slot  Name   Signature
   0      7      0    this       Lscala/actors/remote/LinkToFun;
   0      7      1    v1       D
   0      7      3    v2       I


public void apply$mcVDL$sp(double, long);
  Signature: (DJ)V
  Code:
   Stack=5, Locals=5, Args_size=3
	aload_0
	dload_1
	lload_3
	invokestatic	Method scala/Function2$class.apply$mcVDL$sp:(Lscala/Function2;DJ)V
	return
  Labels:
  LocalVariableTable: 
   Start  Length  Slot  Name   Signature
   0      7      0    this       Lscala/actors/remote/LinkToFun;
   0      7      1    v1       D
   0      7      3    v2       J


public boolean apply$mcZDL$sp(double, long);
  Signature: (DJ)Z
  Code:
   Stack=5, Locals=5, Args_size=3
	aload_0
	dload_1
	lload_3
	invokestatic	Method scala/Function2$class.apply$mcZDL$sp:(Lscala/Function2;DJ)Z
	ireturn
  Labels:
  LocalVariableTable: 
   Start  Length  Slot  Name   Signature
   0      7      0    this       Lscala/actors/remote/LinkToFun;
   0      7      1    v1       D
   0      7      3    v2       J


public int apply$mcIDL$sp(double, long);
  Signature: (DJ)I
  Code:
   Stack=5, Locals=5, Args_size=3
	aload_0
	dload_1
	lload_3
	invokestatic	Method scala/Function2$class.apply$mcIDL$sp:(Lscala/Function2;DJ)I
	ireturn
  Labels:
  LocalVariableTable: 
   Start  Length  Slot  Name   Signature
   0      7      0    this       Lscala/actors/remote/LinkToFun;
   0      7      1    v1       D
   0      7      3    v2       J


public long apply$mcLDL$sp(double, long);
  Signature: (DJ)J
  Code:
   Stack=5, Locals=5, Args_size=3
	aload_0
	dload_1
	lload_3
	invokestatic	Method scala/Function2$class.apply$mcLDL$sp:(Lscala/Function2;DJ)J
	lreturn
  Labels:
  LocalVariableTable: 
   Start  Length  Slot  Name   Signature
   0      7      0    this       Lscala/actors/remote/LinkToFun;
   0      7      1    v1       D
   0      7      3    v2       J


public double apply$mcDDL$sp(double, long);
  Signature: (DJ)D
  Code:
   Stack=5, Locals=5, Args_size=3
	aload_0
	dload_1
	lload_3
	invokestatic	Method scala/Function2$class.apply$mcDDL$sp:(Lscala/Function2;DJ)D
	dreturn
  Labels:
  LocalVariableTable: 
   Start  Length  Slot  Name   Signature
   0      7      0    this       Lscala/actors/remote/LinkToFun;
   0      7      1    v1       D
   0      7      3    v2       J


public void apply$mcVDD$sp(double, double);
  Signature: (DD)V
  Code:
   Stack=5, Locals=5, Args_size=3
	aload_0
	dload_1
	dload_3
	invokestatic	Method scala/Function2$class.apply$mcVDD$sp:(Lscala/Function2;DD)V
	return
  Labels:
  LocalVariableTable: 
   Start  Length  Slot  Name   Signature
   0      7      0    this       Lscala/actors/remote/LinkToFun;
   0      7      1    v1       D
   0      7      3    v2       D


public boolean apply$mcZDD$sp(double, double);
  Signature: (DD)Z
  Code:
   Stack=5, Locals=5, Args_size=3
	aload_0
	dload_1
	dload_3
	invokestatic	Method scala/Function2$class.apply$mcZDD$sp:(Lscala/Function2;DD)Z
	ireturn
  Labels:
  LocalVariableTable: 
   Start  Length  Slot  Name   Signature
   0      7      0    this       Lscala/actors/remote/LinkToFun;
   0      7      1    v1       D
   0      7      3    v2       D


public int apply$mcIDD$sp(double, double);
  Signature: (DD)I
  Code:
   Stack=5, Locals=5, Args_size=3
	aload_0
	dload_1
	dload_3
	invokestatic	Method scala/Function2$class.apply$mcIDD$sp:(Lscala/Function2;DD)I
	ireturn
  Labels:
  LocalVariableTable: 
   Start  Length  Slot  Name   Signature
   0      7      0    this       Lscala/actors/remote/LinkToFun;
   0      7      1    v1       D
   0      7      3    v2       D


public long apply$mcLDD$sp(double, double);
  Signature: (DD)J
  Code:
   Stack=5, Locals=5, Args_size=3
	aload_0
	dload_1
	dload_3
	invokestatic	Method scala/Function2$class.apply$mcLDD$sp:(Lscala/Function2;DD)J
	lreturn
  Labels:
  LocalVariableTable: 
   Start  Length  Slot  Name   Signature
   0      7      0    this       Lscala/actors/remote/LinkToFun;
   0      7      1    v1       D
   0      7      3    v2       D


public double apply$mcDDD$sp(double, double);
  Signature: (DD)D
  Code:
   Stack=5, Locals=5, Args_size=3
	aload_0
	dload_1
	dload_3
	invokestatic	Method scala/Function2$class.apply$mcDDD$sp:(Lscala/Function2;DD)D
	dreturn
  Labels:
  LocalVariableTable: 
   Start  Length  Slot  Name   Signature
   0      7      0    this       Lscala/actors/remote/LinkToFun;
   0      7      1    v1       D
   0      7      3    v2       D


public scala.Function1 curried();
  Signature: ()Lscala/Function1;
  Code:
   Stack=1, Locals=1, Args_size=1
	aload_0
	invokestatic	Method scala/Function2$class.curried:(Lscala/Function2;)Lscala/Function1;
	areturn
  Labels:

public scala.Function1 curried$mcVII$sp();
  Signature: ()Lscala/Function1;
  Code:
   Stack=1, Locals=1, Args_size=1
	aload_0
	invokestatic	Method scala/Function2$class.curried$mcVII$sp:(Lscala/Function2;)Lscala/Function1;
	areturn
  Labels:

public scala.Function1 curried$mcZII$sp();
  Signature: ()Lscala/Function1;
  Code:
   Stack=1, Locals=1, Args_size=1
	aload_0
	invokestatic	Method scala/Function2$class.curried$mcZII$sp:(Lscala/Function2;)Lscala/Function1;
	areturn
  Labels:

public scala.Function1 curried$mcIII$sp();
  Signature: ()Lscala/Function1;
  Code:
   Stack=1, Locals=1, Args_size=1
	aload_0
	invokestatic	Method scala/Function2$class.curried$mcIII$sp:(Lscala/Function2;)Lscala/Function1;
	areturn
  Labels:

public scala.Function1 curried$mcLII$sp();
  Signature: ()Lscala/Function1;
  Code:
   Stack=1, Locals=1, Args_size=1
	aload_0
	invokestatic	Method scala/Function2$class.curried$mcLII$sp:(Lscala/Function2;)Lscala/Function1;
	areturn
  Labels:

public scala.Function1 curried$mcDII$sp();
  Signature: ()Lscala/Function1;
  Code:
   Stack=1, Locals=1, Args_size=1
	aload_0
	invokestatic	Method scala/Function2$class.curried$mcDII$sp:(Lscala/Function2;)Lscala/Function1;
	areturn
  Labels:

public scala.Function1 curried$mcVIL$sp();
  Signature: ()Lscala/Function1;
  Code:
   Stack=1, Locals=1, Args_size=1
	aload_0
	invokestatic	Method scala/Function2$class.curried$mcVIL$sp:(Lscala/Function2;)Lscala/Function1;
	areturn
  Labels:

public scala.Function1 curried$mcZIL$sp();
  Signature: ()Lscala/Function1;
  Code:
   Stack=1, Locals=1, Args_size=1
	aload_0
	invokestatic	Method scala/Function2$class.curried$mcZIL$sp:(Lscala/Function2;)Lscala/Function1;
	areturn
  Labels:

public scala.Function1 curried$mcIIL$sp();
  Signature: ()Lscala/Function1;
  Code:
   Stack=1, Locals=1, Args_size=1
	aload_0
	invokestatic	Method scala/Function2$class.curried$mcIIL$sp:(Lscala/Function2;)Lscala/Function1;
	areturn
  Labels:

public scala.Function1 curried$mcLIL$sp();
  Signature: ()Lscala/Function1;
  Code:
   Stack=1, Locals=1, Args_size=1
	aload_0
	invokestatic	Method scala/Function2$class.curried$mcLIL$sp:(Lscala/Function2;)Lscala/Function1;
	areturn
  Labels:

public scala.Function1 curried$mcDIL$sp();
  Signature: ()Lscala/Function1;
  Code:
   Stack=1, Locals=1, Args_size=1
	aload_0
	invokestatic	Method scala/Function2$class.curried$mcDIL$sp:(Lscala/Function2;)Lscala/Function1;
	areturn
  Labels:

public scala.Function1 curried$mcVID$sp();
  Signature: ()Lscala/Function1;
  Code:
   Stack=1, Locals=1, Args_size=1
	aload_0
	invokestatic	Method scala/Function2$class.curried$mcVID$sp:(Lscala/Function2;)Lscala/Function1;
	areturn
  Labels:

public scala.Function1 curried$mcZID$sp();
  Signature: ()Lscala/Function1;
  Code:
   Stack=1, Locals=1, Args_size=1
	aload_0
	invokestatic	Method scala/Function2$class.curried$mcZID$sp:(Lscala/Function2;)Lscala/Function1;
	areturn
  Labels:

public scala.Function1 curried$mcIID$sp();
  Signature: ()Lscala/Function1;
  Code:
   Stack=1, Locals=1, Args_size=1
	aload_0
	invokestatic	Method scala/Function2$class.curried$mcIID$sp:(Lscala/Function2;)Lscala/Function1;
	areturn
  Labels:

public scala.Function1 curried$mcLID$sp();
  Signature: ()Lscala/Function1;
  Code:
   Stack=1, Locals=1, Args_size=1
	aload_0
	invokestatic	Method scala/Function2$class.curried$mcLID$sp:(Lscala/Function2;)Lscala/Function1;
	areturn
  Labels:

public scala.Function1 curried$mcDID$sp();
  Signature: ()Lscala/Function1;
  Code:
   Stack=1, Locals=1, Args_size=1
	aload_0
	invokestatic	Method scala/Function2$class.curried$mcDID$sp:(Lscala/Function2;)Lscala/Function1;
	areturn
  Labels:

public scala.Function1 curried$mcVLI$sp();
  Signature: ()Lscala/Function1;
  Code:
   Stack=1, Locals=1, Args_size=1
	aload_0
	invokestatic	Method scala/Function2$class.curried$mcVLI$sp:(Lscala/Function2;)Lscala/Function1;
	areturn
  Labels:

public scala.Function1 curried$mcZLI$sp();
  Signature: ()Lscala/Function1;
  Code:
   Stack=1, Locals=1, Args_size=1
	aload_0
	invokestatic	Method scala/Function2$class.curried$mcZLI$sp:(Lscala/Function2;)Lscala/Function1;
	areturn
  Labels:

public scala.Function1 curried$mcILI$sp();
  Signature: ()Lscala/Function1;
  Code:
   Stack=1, Locals=1, Args_size=1
	aload_0
	invokestatic	Method scala/Function2$class.curried$mcILI$sp:(Lscala/Function2;)Lscala/Function1;
	areturn
  Labels:

public scala.Function1 curried$mcLLI$sp();
  Signature: ()Lscala/Function1;
  Code:
   Stack=1, Locals=1, Args_size=1
	aload_0
	invokestatic	Method scala/Function2$class.curried$mcLLI$sp:(Lscala/Function2;)Lscala/Function1;
	areturn
  Labels:

public scala.Function1 curried$mcDLI$sp();
  Signature: ()Lscala/Function1;
  Code:
   Stack=1, Locals=1, Args_size=1
	aload_0
	invokestatic	Method scala/Function2$class.curried$mcDLI$sp:(Lscala/Function2;)Lscala/Function1;
	areturn
  Labels:

public scala.Function1 curried$mcVLL$sp();
  Signature: ()Lscala/Function1;
  Code:
   Stack=1, Locals=1, Args_size=1
	aload_0
	invokestatic	Method scala/Function2$class.curried$mcVLL$sp:(Lscala/Function2;)Lscala/Function1;
	areturn
  Labels:

public scala.Function1 curried$mcZLL$sp();
  Signature: ()Lscala/Function1;
  Code:
   Stack=1, Locals=1, Args_size=1
	aload_0
	invokestatic	Method scala/Function2$class.curried$mcZLL$sp:(Lscala/Function2;)Lscala/Function1;
	areturn
  Labels:

public scala.Function1 curried$mcILL$sp();
  Signature: ()Lscala/Function1;
  Code:
   Stack=1, Locals=1, Args_size=1
	aload_0
	invokestatic	Method scala/Function2$class.curried$mcILL$sp:(Lscala/Function2;)Lscala/Function1;
	areturn
  Labels:

public scala.Function1 curried$mcLLL$sp();
  Signature: ()Lscala/Function1;
  Code:
   Stack=1, Locals=1, Args_size=1
	aload_0
	invokestatic	Method scala/Function2$class.curried$mcLLL$sp:(Lscala/Function2;)Lscala/Function1;
	areturn
  Labels:

public scala.Function1 curried$mcDLL$sp();
  Signature: ()Lscala/Function1;
  Code:
   Stack=1, Locals=1, Args_size=1
	aload_0
	invokestatic	Method scala/Function2$class.curried$mcDLL$sp:(Lscala/Function2;)Lscala/Function1;
	areturn
  Labels:

public scala.Function1 curried$mcVLD$sp();
  Signature: ()Lscala/Function1;
  Code:
   Stack=1, Locals=1, Args_size=1
	aload_0
	invokestatic	Method scala/Function2$class.curried$mcVLD$sp:(Lscala/Function2;)Lscala/Function1;
	areturn
  Labels:

public scala.Function1 curried$mcZLD$sp();
  Signature: ()Lscala/Function1;
  Code:
   Stack=1, Locals=1, Args_size=1
	aload_0
	invokestatic	Method scala/Function2$class.curried$mcZLD$sp:(Lscala/Function2;)Lscala/Function1;
	areturn
  Labels:

public scala.Function1 curried$mcILD$sp();
  Signature: ()Lscala/Function1;
  Code:
   Stack=1, Locals=1, Args_size=1
	aload_0
	invokestatic	Method scala/Function2$class.curried$mcILD$sp:(Lscala/Function2;)Lscala/Function1;
	areturn
  Labels:

public scala.Function1 curried$mcLLD$sp();
  Signature: ()Lscala/Function1;
  Code:
   Stack=1, Locals=1, Args_size=1
	aload_0
	invokestatic	Method scala/Function2$class.curried$mcLLD$sp:(Lscala/Function2;)Lscala/Function1;
	areturn
  Labels:

public scala.Function1 curried$mcDLD$sp();
  Signature: ()Lscala/Function1;
  Code:
   Stack=1, Locals=1, Args_size=1
	aload_0
	invokestatic	Method scala/Function2$class.curried$mcDLD$sp:(Lscala/Function2;)Lscala/Function1;
	areturn
  Labels:

public scala.Function1 curried$mcVDI$sp();
  Signature: ()Lscala/Function1;
  Code:
   Stack=1, Locals=1, Args_size=1
	aload_0
	invokestatic	Method scala/Function2$class.curried$mcVDI$sp:(Lscala/Function2;)Lscala/Function1;
	areturn
  Labels:

public scala.Function1 curried$mcZDI$sp();
  Signature: ()Lscala/Function1;
  Code:
   Stack=1, Locals=1, Args_size=1
	aload_0
	invokestatic	Method scala/Function2$class.curried$mcZDI$sp:(Lscala/Function2;)Lscala/Function1;
	areturn
  Labels:

public scala.Function1 curried$mcIDI$sp();
  Signature: ()Lscala/Function1;
  Code:
   Stack=1, Locals=1, Args_size=1
	aload_0
	invokestatic	Method scala/Function2$class.curried$mcIDI$sp:(Lscala/Function2;)Lscala/Function1;
	areturn
  Labels:

public scala.Function1 curried$mcLDI$sp();
  Signature: ()Lscala/Function1;
  Code:
   Stack=1, Locals=1, Args_size=1
	aload_0
	invokestatic	Method scala/Function2$class.curried$mcLDI$sp:(Lscala/Function2;)Lscala/Function1;
	areturn
  Labels:

public scala.Function1 curried$mcDDI$sp();
  Signature: ()Lscala/Function1;
  Code:
   Stack=1, Locals=1, Args_size=1
	aload_0
	invokestatic	Method scala/Function2$class.curried$mcDDI$sp:(Lscala/Function2;)Lscala/Function1;
	areturn
  Labels:

public scala.Function1 curried$mcVDL$sp();
  Signature: ()Lscala/Function1;
  Code:
   Stack=1, Locals=1, Args_size=1
	aload_0
	invokestatic	Method scala/Function2$class.curried$mcVDL$sp:(Lscala/Function2;)Lscala/Function1;
	areturn
  Labels:

public scala.Function1 curried$mcZDL$sp();
  Signature: ()Lscala/Function1;
  Code:
   Stack=1, Locals=1, Args_size=1
	aload_0
	invokestatic	Method scala/Function2$class.curried$mcZDL$sp:(Lscala/Function2;)Lscala/Function1;
	areturn
  Labels:

public scala.Function1 curried$mcIDL$sp();
  Signature: ()Lscala/Function1;
  Code:
   Stack=1, Locals=1, Args_size=1
	aload_0
	invokestatic	Method scala/Function2$class.curried$mcIDL$sp:(Lscala/Function2;)Lscala/Function1;
	areturn
  Labels:

public scala.Function1 curried$mcLDL$sp();
  Signature: ()Lscala/Function1;
  Code:
   Stack=1, Locals=1, Args_size=1
	aload_0
	invokestatic	Method scala/Function2$class.curried$mcLDL$sp:(Lscala/Function2;)Lscala/Function1;
	areturn
  Labels:

public scala.Function1 curried$mcDDL$sp();
  Signature: ()Lscala/Function1;
  Code:
   Stack=1, Locals=1, Args_size=1
	aload_0
	invokestatic	Method scala/Function2$class.curried$mcDDL$sp:(Lscala/Function2;)Lscala/Function1;
	areturn
  Labels:

public scala.Function1 curried$mcVDD$sp();
  Signature: ()Lscala/Function1;
  Code:
   Stack=1, Locals=1, Args_size=1
	aload_0
	invokestatic	Method scala/Function2$class.curried$mcVDD$sp:(Lscala/Function2;)Lscala/Function1;
	areturn
  Labels:

public scala.Function1 curried$mcZDD$sp();
  Signature: ()Lscala/Function1;
  Code:
   Stack=1, Locals=1, Args_size=1
	aload_0
	invokestatic	Method scala/Function2$class.curried$mcZDD$sp:(Lscala/Function2;)Lscala/Function1;
	areturn
  Labels:

public scala.Function1 curried$mcIDD$sp();
  Signature: ()Lscala/Function1;
  Code:
   Stack=1, Locals=1, Args_size=1
	aload_0
	invokestatic	Method scala/Function2$class.curried$mcIDD$sp:(Lscala/Function2;)Lscala/Function1;
	areturn
  Labels:

public scala.Function1 curried$mcLDD$sp();
  Signature: ()Lscala/Function1;
  Code:
   Stack=1, Locals=1, Args_size=1
	aload_0
	invokestatic	Method scala/Function2$class.curried$mcLDD$sp:(Lscala/Function2;)Lscala/Function1;
	areturn
  Labels:

public scala.Function1 curried$mcDDD$sp();
  Signature: ()Lscala/Function1;
  Code:
   Stack=1, Locals=1, Args_size=1
	aload_0
	invokestatic	Method scala/Function2$class.curried$mcDDD$sp:(Lscala/Function2;)Lscala/Function1;
	areturn
  Labels:

public scala.Function1 curry();
  Signature: ()Lscala/Function1;
  Code:
   Stack=1, Locals=1, Args_size=1
	aload_0
	invokestatic	Method scala/Function2$class.curry:(Lscala/Function2;)Lscala/Function1;
	areturn
  Labels:
  Deprecated: true

public scala.Function1 curry$mcVII$sp();
  Signature: ()Lscala/Function1;
  Code:
   Stack=1, Locals=1, Args_size=1
	aload_0
	invokestatic	Method scala/Function2$class.curry$mcVII$sp:(Lscala/Function2;)Lscala/Function1;
	areturn
  Labels:
  Deprecated: true

public scala.Function1 curry$mcZII$sp();
  Signature: ()Lscala/Function1;
  Code:
   Stack=1, Locals=1, Args_size=1
	aload_0
	invokestatic	Method scala/Function2$class.curry$mcZII$sp:(Lscala/Function2;)Lscala/Function1;
	areturn
  Labels:
  Deprecated: true

public scala.Function1 curry$mcIII$sp();
  Signature: ()Lscala/Function1;
  Code:
   Stack=1, Locals=1, Args_size=1
	aload_0
	invokestatic	Method scala/Function2$class.curry$mcIII$sp:(Lscala/Function2;)Lscala/Function1;
	areturn
  Labels:
  Deprecated: true

public scala.Function1 curry$mcLII$sp();
  Signature: ()Lscala/Function1;
  Code:
   Stack=1, Locals=1, Args_size=1
	aload_0
	invokestatic	Method scala/Function2$class.curry$mcLII$sp:(Lscala/Function2;)Lscala/Function1;
	areturn
  Labels:
  Deprecated: true

public scala.Function1 curry$mcDII$sp();
  Signature: ()Lscala/Function1;
  Code:
   Stack=1, Locals=1, Args_size=1
	aload_0
	invokestatic	Method scala/Function2$class.curry$mcDII$sp:(Lscala/Function2;)Lscala/Function1;
	areturn
  Labels:
  Deprecated: true

public scala.Function1 curry$mcVIL$sp();
  Signature: ()Lscala/Function1;
  Code:
   Stack=1, Locals=1, Args_size=1
	aload_0
	invokestatic	Method scala/Function2$class.curry$mcVIL$sp:(Lscala/Function2;)Lscala/Function1;
	areturn
  Labels:
  Deprecated: true

public scala.Function1 curry$mcZIL$sp();
  Signature: ()Lscala/Function1;
  Code:
   Stack=1, Locals=1, Args_size=1
	aload_0
	invokestatic	Method scala/Function2$class.curry$mcZIL$sp:(Lscala/Function2;)Lscala/Function1;
	areturn
  Labels:
  Deprecated: true

public scala.Function1 curry$mcIIL$sp();
  Signature: ()Lscala/Function1;
  Code:
   Stack=1, Locals=1, Args_size=1
	aload_0
	invokestatic	Method scala/Function2$class.curry$mcIIL$sp:(Lscala/Function2;)Lscala/Function1;
	areturn
  Labels:
  Deprecated: true

public scala.Function1 curry$mcLIL$sp();
  Signature: ()Lscala/Function1;
  Code:
   Stack=1, Locals=1, Args_size=1
	aload_0
	invokestatic	Method scala/Function2$class.curry$mcLIL$sp:(Lscala/Function2;)Lscala/Function1;
	areturn
  Labels:
  Deprecated: true

public scala.Function1 curry$mcDIL$sp();
  Signature: ()Lscala/Function1;
  Code:
   Stack=1, Locals=1, Args_size=1
	aload_0
	invokestatic	Method scala/Function2$class.curry$mcDIL$sp:(Lscala/Function2;)Lscala/Function1;
	areturn
  Labels:
  Deprecated: true

public scala.Function1 curry$mcVID$sp();
  Signature: ()Lscala/Function1;
  Code:
   Stack=1, Locals=1, Args_size=1
	aload_0
	invokestatic	Method scala/Function2$class.curry$mcVID$sp:(Lscala/Function2;)Lscala/Function1;
	areturn
  Labels:
  Deprecated: true

public scala.Function1 curry$mcZID$sp();
  Signature: ()Lscala/Function1;
  Code:
   Stack=1, Locals=1, Args_size=1
	aload_0
	invokestatic	Method scala/Function2$class.curry$mcZID$sp:(Lscala/Function2;)Lscala/Function1;
	areturn
  Labels:
  Deprecated: true

public scala.Function1 curry$mcIID$sp();
  Signature: ()Lscala/Function1;
  Code:
   Stack=1, Locals=1, Args_size=1
	aload_0
	invokestatic	Method scala/Function2$class.curry$mcIID$sp:(Lscala/Function2;)Lscala/Function1;
	areturn
  Labels:
  Deprecated: true

public scala.Function1 curry$mcLID$sp();
  Signature: ()Lscala/Function1;
  Code:
   Stack=1, Locals=1, Args_size=1
	aload_0
	invokestatic	Method scala/Function2$class.curry$mcLID$sp:(Lscala/Function2;)Lscala/Function1;
	areturn
  Labels:
  Deprecated: true

public scala.Function1 curry$mcDID$sp();
  Signature: ()Lscala/Function1;
  Code:
   Stack=1, Locals=1, Args_size=1
	aload_0
	invokestatic	Method scala/Function2$class.curry$mcDID$sp:(Lscala/Function2;)Lscala/Function1;
	areturn
  Labels:
  Deprecated: true

public scala.Function1 curry$mcVLI$sp();
  Signature: ()Lscala/Function1;
  Code:
   Stack=1, Locals=1, Args_size=1
	aload_0
	invokestatic	Method scala/Function2$class.curry$mcVLI$sp:(Lscala/Function2;)Lscala/Function1;
	areturn
  Labels:
  Deprecated: true

public scala.Function1 curry$mcZLI$sp();
  Signature: ()Lscala/Function1;
  Code:
   Stack=1, Locals=1, Args_size=1
	aload_0
	invokestatic	Method scala/Function2$class.curry$mcZLI$sp:(Lscala/Function2;)Lscala/Function1;
	areturn
  Labels:
  Deprecated: true

public scala.Function1 curry$mcILI$sp();
  Signature: ()Lscala/Function1;
  Code:
   Stack=1, Locals=1, Args_size=1
	aload_0
	invokestatic	Method scala/Function2$class.curry$mcILI$sp:(Lscala/Function2;)Lscala/Function1;
	areturn
  Labels:
  Deprecated: true

public scala.Function1 curry$mcLLI$sp();
  Signature: ()Lscala/Function1;
  Code:
   Stack=1, Locals=1, Args_size=1
	aload_0
	invokestatic	Method scala/Function2$class.curry$mcLLI$sp:(Lscala/Function2;)Lscala/Function1;
	areturn
  Labels:
  Deprecated: true

public scala.Function1 curry$mcDLI$sp();
  Signature: ()Lscala/Function1;
  Code:
   Stack=1, Locals=1, Args_size=1
	aload_0
	invokestatic	Method scala/Function2$class.curry$mcDLI$sp:(Lscala/Function2;)Lscala/Function1;
	areturn
  Labels:
  Deprecated: true

public scala.Function1 curry$mcVLL$sp();
  Signature: ()Lscala/Function1;
  Code:
   Stack=1, Locals=1, Args_size=1
	aload_0
	invokestatic	Method scala/Function2$class.curry$mcVLL$sp:(Lscala/Function2;)Lscala/Function1;
	areturn
  Labels:
  Deprecated: true

public scala.Function1 curry$mcZLL$sp();
  Signature: ()Lscala/Function1;
  Code:
   Stack=1, Locals=1, Args_size=1
	aload_0
	invokestatic	Method scala/Function2$class.curry$mcZLL$sp:(Lscala/Function2;)Lscala/Function1;
	areturn
  Labels:
  Deprecated: true

public scala.Function1 curry$mcILL$sp();
  Signature: ()Lscala/Function1;
  Code:
   Stack=1, Locals=1, Args_size=1
	aload_0
	invokestatic	Method scala/Function2$class.curry$mcILL$sp:(Lscala/Function2;)Lscala/Function1;
	areturn
  Labels:
  Deprecated: true

public scala.Function1 curry$mcLLL$sp();
  Signature: ()Lscala/Function1;
  Code:
   Stack=1, Locals=1, Args_size=1
	aload_0
	invokestatic	Method scala/Function2$class.curry$mcLLL$sp:(Lscala/Function2;)Lscala/Function1;
	areturn
  Labels:
  Deprecated: true

public scala.Function1 curry$mcDLL$sp();
  Signature: ()Lscala/Function1;
  Code:
   Stack=1, Locals=1, Args_size=1
	aload_0
	invokestatic	Method scala/Function2$class.curry$mcDLL$sp:(Lscala/Function2;)Lscala/Function1;
	areturn
  Labels:
  Deprecated: true

public scala.Function1 curry$mcVLD$sp();
  Signature: ()Lscala/Function1;
  Code:
   Stack=1, Locals=1, Args_size=1
	aload_0
	invokestatic	Method scala/Function2$class.curry$mcVLD$sp:(Lscala/Function2;)Lscala/Function1;
	areturn
  Labels:
  Deprecated: true

public scala.Function1 curry$mcZLD$sp();
  Signature: ()Lscala/Function1;
  Code:
   Stack=1, Locals=1, Args_size=1
	aload_0
	invokestatic	Method scala/Function2$class.curry$mcZLD$sp:(Lscala/Function2;)Lscala/Function1;
	areturn
  Labels:
  Deprecated: true

public scala.Function1 curry$mcILD$sp();
  Signature: ()Lscala/Function1;
  Code:
   Stack=1, Locals=1, Args_size=1
	aload_0
	invokestatic	Method scala/Function2$class.curry$mcILD$sp:(Lscala/Function2;)Lscala/Function1;
	areturn
  Labels:
  Deprecated: true

public scala.Function1 curry$mcLLD$sp();
  Signature: ()Lscala/Function1;
  Code:
   Stack=1, Locals=1, Args_size=1
	aload_0
	invokestatic	Method scala/Function2$class.curry$mcLLD$sp:(Lscala/Function2;)Lscala/Function1;
	areturn
  Labels:
  Deprecated: true

public scala.Function1 curry$mcDLD$sp();
  Signature: ()Lscala/Function1;
  Code:
   Stack=1, Locals=1, Args_size=1
	aload_0
	invokestatic	Method scala/Function2$class.curry$mcDLD$sp:(Lscala/Function2;)Lscala/Function1;
	areturn
  Labels:
  Deprecated: true

public scala.Function1 curry$mcVDI$sp();
  Signature: ()Lscala/Function1;
  Code:
   Stack=1, Locals=1, Args_size=1
	aload_0
	invokestatic	Method scala/Function2$class.curry$mcVDI$sp:(Lscala/Function2;)Lscala/Function1;
	areturn
  Labels:
  Deprecated: true

public scala.Function1 curry$mcZDI$sp();
  Signature: ()Lscala/Function1;
  Code:
   Stack=1, Locals=1, Args_size=1
	aload_0
	invokestatic	Method scala/Function2$class.curry$mcZDI$sp:(Lscala/Function2;)Lscala/Function1;
	areturn
  Labels:
  Deprecated: true

public scala.Function1 curry$mcIDI$sp();
  Signature: ()Lscala/Function1;
  Code:
   Stack=1, Locals=1, Args_size=1
	aload_0
	invokestatic	Method scala/Function2$class.curry$mcIDI$sp:(Lscala/Function2;)Lscala/Function1;
	areturn
  Labels:
  Deprecated: true

public scala.Function1 curry$mcLDI$sp();
  Signature: ()Lscala/Function1;
  Code:
   Stack=1, Locals=1, Args_size=1
	aload_0
	invokestatic	Method scala/Function2$class.curry$mcLDI$sp:(Lscala/Function2;)Lscala/Function1;
	areturn
  Labels:
  Deprecated: true

public scala.Function1 curry$mcDDI$sp();
  Signature: ()Lscala/Function1;
  Code:
   Stack=1, Locals=1, Args_size=1
	aload_0
	invokestatic	Method scala/Function2$class.curry$mcDDI$sp:(Lscala/Function2;)Lscala/Function1;
	areturn
  Labels:
  Deprecated: true

public scala.Function1 curry$mcVDL$sp();
  Signature: ()Lscala/Function1;
  Code:
   Stack=1, Locals=1, Args_size=1
	aload_0
	invokestatic	Method scala/Function2$class.curry$mcVDL$sp:(Lscala/Function2;)Lscala/Function1;
	areturn
  Labels:
  Deprecated: true

public scala.Function1 curry$mcZDL$sp();
  Signature: ()Lscala/Function1;
  Code:
   Stack=1, Locals=1, Args_size=1
	aload_0
	invokestatic	Method scala/Function2$class.curry$mcZDL$sp:(Lscala/Function2;)Lscala/Function1;
	areturn
  Labels:
  Deprecated: true

public scala.Function1 curry$mcIDL$sp();
  Signature: ()Lscala/Function1;
  Code:
   Stack=1, Locals=1, Args_size=1
	aload_0
	invokestatic	Method scala/Function2$class.curry$mcIDL$sp:(Lscala/Function2;)Lscala/Function1;
	areturn
  Labels:
  Deprecated: true

public scala.Function1 curry$mcLDL$sp();
  Signature: ()Lscala/Function1;
  Code:
   Stack=1, Locals=1, Args_size=1
	aload_0
	invokestatic	Method scala/Function2$class.curry$mcLDL$sp:(Lscala/Function2;)Lscala/Function1;
	areturn
  Labels:
  Deprecated: true

public scala.Function1 curry$mcDDL$sp();
  Signature: ()Lscala/Function1;
  Code:
   Stack=1, Locals=1, Args_size=1
	aload_0
	invokestatic	Method scala/Function2$class.curry$mcDDL$sp:(Lscala/Function2;)Lscala/Function1;
	areturn
  Labels:
  Deprecated: true

public scala.Function1 curry$mcVDD$sp();
  Signature: ()Lscala/Function1;
  Code:
   Stack=1, Locals=1, Args_size=1
	aload_0
	invokestatic	Method scala/Function2$class.curry$mcVDD$sp:(Lscala/Function2;)Lscala/Function1;
	areturn
  Labels:
  Deprecated: true

public scala.Function1 curry$mcZDD$sp();
  Signature: ()Lscala/Function1;
  Code:
   Stack=1, Locals=1, Args_size=1
	aload_0
	invokestatic	Method scala/Function2$class.curry$mcZDD$sp:(Lscala/Function2;)Lscala/Function1;
	areturn
  Labels:
  Deprecated: true

public scala.Function1 curry$mcIDD$sp();
  Signature: ()Lscala/Function1;
  Code:
   Stack=1, Locals=1, Args_size=1
	aload_0
	invokestatic	Method scala/Function2$class.curry$mcIDD$sp:(Lscala/Function2;)Lscala/Function1;
	areturn
  Labels:
  Deprecated: true

public scala.Function1 curry$mcLDD$sp();
  Signature: ()Lscala/Function1;
  Code:
   Stack=1, Locals=1, Args_size=1
	aload_0
	invokestatic	Method scala/Function2$class.curry$mcLDD$sp:(Lscala/Function2;)Lscala/Function1;
	areturn
  Labels:
  Deprecated: true

public scala.Function1 curry$mcDDD$sp();
  Signature: ()Lscala/Function1;
  Code:
   Stack=1, Locals=1, Args_size=1
	aload_0
	invokestatic	Method scala/Function2$class.curry$mcDDD$sp:(Lscala/Function2;)Lscala/Function1;
	areturn
  Labels:
  Deprecated: true

public scala.Function1 tupled();
  Signature: ()Lscala/Function1;
  Code:
   Stack=1, Locals=1, Args_size=1
	aload_0
	invokestatic	Method scala/Function2$class.tupled:(Lscala/Function2;)Lscala/Function1;
	areturn
  Labels:

public scala.Function1 tupled$mcVII$sp();
  Signature: ()Lscala/Function1;
  Code:
   Stack=1, Locals=1, Args_size=1
	aload_0
	invokestatic	Method scala/Function2$class.tupled$mcVII$sp:(Lscala/Function2;)Lscala/Function1;
	areturn
  Labels:

public scala.Function1 tupled$mcZII$sp();
  Signature: ()Lscala/Function1;
  Code:
   Stack=1, Locals=1, Args_size=1
	aload_0
	invokestatic	Method scala/Function2$class.tupled$mcZII$sp:(Lscala/Function2;)Lscala/Function1;
	areturn
  Labels:

public scala.Function1 tupled$mcIII$sp();
  Signature: ()Lscala/Function1;
  Code:
   Stack=1, Locals=1, Args_size=1
	aload_0
	invokestatic	Method scala/Function2$class.tupled$mcIII$sp:(Lscala/Function2;)Lscala/Function1;
	areturn
  Labels:

public scala.Function1 tupled$mcLII$sp();
  Signature: ()Lscala/Function1;
  Code:
   Stack=1, Locals=1, Args_size=1
	aload_0
	invokestatic	Method scala/Function2$class.tupled$mcLII$sp:(Lscala/Function2;)Lscala/Function1;
	areturn
  Labels:

public scala.Function1 tupled$mcDII$sp();
  Signature: ()Lscala/Function1;
  Code:
   Stack=1, Locals=1, Args_size=1
	aload_0
	invokestatic	Method scala/Function2$class.tupled$mcDII$sp:(Lscala/Function2;)Lscala/Function1;
	areturn
  Labels:

public scala.Function1 tupled$mcVIL$sp();
  Signature: ()Lscala/Function1;
  Code:
   Stack=1, Locals=1, Args_size=1
	aload_0
	invokestatic	Method scala/Function2$class.tupled$mcVIL$sp:(Lscala/Function2;)Lscala/Function1;
	areturn
  Labels:

public scala.Function1 tupled$mcZIL$sp();
  Signature: ()Lscala/Function1;
  Code:
   Stack=1, Locals=1, Args_size=1
	aload_0
	invokestatic	Method scala/Function2$class.tupled$mcZIL$sp:(Lscala/Function2;)Lscala/Function1;
	areturn
  Labels:

public scala.Function1 tupled$mcIIL$sp();
  Signature: ()Lscala/Function1;
  Code:
   Stack=1, Locals=1, Args_size=1
	aload_0
	invokestatic	Method scala/Function2$class.tupled$mcIIL$sp:(Lscala/Function2;)Lscala/Function1;
	areturn
  Labels:

public scala.Function1 tupled$mcLIL$sp();
  Signature: ()Lscala/Function1;
  Code:
   Stack=1, Locals=1, Args_size=1
	aload_0
	invokestatic	Method scala/Function2$class.tupled$mcLIL$sp:(Lscala/Function2;)Lscala/Function1;
	areturn
  Labels:

public scala.Function1 tupled$mcDIL$sp();
  Signature: ()Lscala/Function1;
  Code:
   Stack=1, Locals=1, Args_size=1
	aload_0
	invokestatic	Method scala/Function2$class.tupled$mcDIL$sp:(Lscala/Function2;)Lscala/Function1;
	areturn
  Labels:

public scala.Function1 tupled$mcVID$sp();
  Signature: ()Lscala/Function1;
  Code:
   Stack=1, Locals=1, Args_size=1
	aload_0
	invokestatic	Method scala/Function2$class.tupled$mcVID$sp:(Lscala/Function2;)Lscala/Function1;
	areturn
  Labels:

public scala.Function1 tupled$mcZID$sp();
  Signature: ()Lscala/Function1;
  Code:
   Stack=1, Locals=1, Args_size=1
	aload_0
	invokestatic	Method scala/Function2$class.tupled$mcZID$sp:(Lscala/Function2;)Lscala/Function1;
	areturn
  Labels:

public scala.Function1 tupled$mcIID$sp();
  Signature: ()Lscala/Function1;
  Code:
   Stack=1, Locals=1, Args_size=1
	aload_0
	invokestatic	Method scala/Function2$class.tupled$mcIID$sp:(Lscala/Function2;)Lscala/Function1;
	areturn
  Labels:

public scala.Function1 tupled$mcLID$sp();
  Signature: ()Lscala/Function1;
  Code:
   Stack=1, Locals=1, Args_size=1
	aload_0
	invokestatic	Method scala/Function2$class.tupled$mcLID$sp:(Lscala/Function2;)Lscala/Function1;
	areturn
  Labels:

public scala.Function1 tupled$mcDID$sp();
  Signature: ()Lscala/Function1;
  Code:
   Stack=1, Locals=1, Args_size=1
	aload_0
	invokestatic	Method scala/Function2$class.tupled$mcDID$sp:(Lscala/Function2;)Lscala/Function1;
	areturn
  Labels:

public scala.Function1 tupled$mcVLI$sp();
  Signature: ()Lscala/Function1;
  Code:
   Stack=1, Locals=1, Args_size=1
	aload_0
	invokestatic	Method scala/Function2$class.tupled$mcVLI$sp:(Lscala/Function2;)Lscala/Function1;
	areturn
  Labels:

public scala.Function1 tupled$mcZLI$sp();
  Signature: ()Lscala/Function1;
  Code:
   Stack=1, Locals=1, Args_size=1
	aload_0
	invokestatic	Method scala/Function2$class.tupled$mcZLI$sp:(Lscala/Function2;)Lscala/Function1;
	areturn
  Labels:

public scala.Function1 tupled$mcILI$sp();
  Signature: ()Lscala/Function1;
  Code:
   Stack=1, Locals=1, Args_size=1
	aload_0
	invokestatic	Method scala/Function2$class.tupled$mcILI$sp:(Lscala/Function2;)Lscala/Function1;
	areturn
  Labels:

public scala.Function1 tupled$mcLLI$sp();
  Signature: ()Lscala/Function1;
  Code:
   Stack=1, Locals=1, Args_size=1
	aload_0
	invokestatic	Method scala/Function2$class.tupled$mcLLI$sp:(Lscala/Function2;)Lscala/Function1;
	areturn
  Labels:

public scala.Function1 tupled$mcDLI$sp();
  Signature: ()Lscala/Function1;
  Code:
   Stack=1, Locals=1, Args_size=1
	aload_0
	invokestatic	Method scala/Function2$class.tupled$mcDLI$sp:(Lscala/Function2;)Lscala/Function1;
	areturn
  Labels:

public scala.Function1 tupled$mcVLL$sp();
  Signature: ()Lscala/Function1;
  Code:
   Stack=1, Locals=1, Args_size=1
	aload_0
	invokestatic	Method scala/Function2$class.tupled$mcVLL$sp:(Lscala/Function2;)Lscala/Function1;
	areturn
  Labels:

public scala.Function1 tupled$mcZLL$sp();
  Signature: ()Lscala/Function1;
  Code:
   Stack=1, Locals=1, Args_size=1
	aload_0
	invokestatic	Method scala/Function2$class.tupled$mcZLL$sp:(Lscala/Function2;)Lscala/Function1;
	areturn
  Labels:

public scala.Function1 tupled$mcILL$sp();
  Signature: ()Lscala/Function1;
  Code:
   Stack=1, Locals=1, Args_size=1
	aload_0
	invokestatic	Method scala/Function2$class.tupled$mcILL$sp:(Lscala/Function2;)Lscala/Function1;
	areturn
  Labels:

public scala.Function1 tupled$mcLLL$sp();
  Signature: ()Lscala/Function1;
  Code:
   Stack=1, Locals=1, Args_size=1
	aload_0
	invokestatic	Method scala/Function2$class.tupled$mcLLL$sp:(Lscala/Function2;)Lscala/Function1;
	areturn
  Labels:

public scala.Function1 tupled$mcDLL$sp();
  Signature: ()Lscala/Function1;
  Code:
   Stack=1, Locals=1, Args_size=1
	aload_0
	invokestatic	Method scala/Function2$class.tupled$mcDLL$sp:(Lscala/Function2;)Lscala/Function1;
	areturn
  Labels:

public scala.Function1 tupled$mcVLD$sp();
  Signature: ()Lscala/Function1;
  Code:
   Stack=1, Locals=1, Args_size=1
	aload_0
	invokestatic	Method scala/Function2$class.tupled$mcVLD$sp:(Lscala/Function2;)Lscala/Function1;
	areturn
  Labels:

public scala.Function1 tupled$mcZLD$sp();
  Signature: ()Lscala/Function1;
  Code:
   Stack=1, Locals=1, Args_size=1
	aload_0
	invokestatic	Method scala/Function2$class.tupled$mcZLD$sp:(Lscala/Function2;)Lscala/Function1;
	areturn
  Labels:

public scala.Function1 tupled$mcILD$sp();
  Signature: ()Lscala/Function1;
  Code:
   Stack=1, Locals=1, Args_size=1
	aload_0
	invokestatic	Method scala/Function2$class.tupled$mcILD$sp:(Lscala/Function2;)Lscala/Function1;
	areturn
  Labels:

public scala.Function1 tupled$mcLLD$sp();
  Signature: ()Lscala/Function1;
  Code:
   Stack=1, Locals=1, Args_size=1
	aload_0
	invokestatic	Method scala/Function2$class.tupled$mcLLD$sp:(Lscala/Function2;)Lscala/Function1;
	areturn
  Labels:

public scala.Function1 tupled$mcDLD$sp();
  Signature: ()Lscala/Function1;
  Code:
   Stack=1, Locals=1, Args_size=1
	aload_0
	invokestatic	Method scala/Function2$class.tupled$mcDLD$sp:(Lscala/Function2;)Lscala/Function1;
	areturn
  Labels:

public scala.Function1 tupled$mcVDI$sp();
  Signature: ()Lscala/Function1;
  Code:
   Stack=1, Locals=1, Args_size=1
	aload_0
	invokestatic	Method scala/Function2$class.tupled$mcVDI$sp:(Lscala/Function2;)Lscala/Function1;
	areturn
  Labels:

public scala.Function1 tupled$mcZDI$sp();
  Signature: ()Lscala/Function1;
  Code:
   Stack=1, Locals=1, Args_size=1
	aload_0
	invokestatic	Method scala/Function2$class.tupled$mcZDI$sp:(Lscala/Function2;)Lscala/Function1;
	areturn
  Labels:

public scala.Function1 tupled$mcIDI$sp();
  Signature: ()Lscala/Function1;
  Code:
   Stack=1, Locals=1, Args_size=1
	aload_0
	invokestatic	Method scala/Function2$class.tupled$mcIDI$sp:(Lscala/Function2;)Lscala/Function1;
	areturn
  Labels:

public scala.Function1 tupled$mcLDI$sp();
  Signature: ()Lscala/Function1;
  Code:
   Stack=1, Locals=1, Args_size=1
	aload_0
	invokestatic	Method scala/Function2$class.tupled$mcLDI$sp:(Lscala/Function2;)Lscala/Function1;
	areturn
  Labels:

public scala.Function1 tupled$mcDDI$sp();
  Signature: ()Lscala/Function1;
  Code:
   Stack=1, Locals=1, Args_size=1
	aload_0
	invokestatic	Method scala/Function2$class.tupled$mcDDI$sp:(Lscala/Function2;)Lscala/Function1;
	areturn
  Labels:

public scala.Function1 tupled$mcVDL$sp();
  Signature: ()Lscala/Function1;
  Code:
   Stack=1, Locals=1, Args_size=1
	aload_0
	invokestatic	Method scala/Function2$class.tupled$mcVDL$sp:(Lscala/Function2;)Lscala/Function1;
	areturn
  Labels:

public scala.Function1 tupled$mcZDL$sp();
  Signature: ()Lscala/Function1;
  Code:
   Stack=1, Locals=1, Args_size=1
	aload_0
	invokestatic	Method scala/Function2$class.tupled$mcZDL$sp:(Lscala/Function2;)Lscala/Function1;
	areturn
  Labels:

public scala.Function1 tupled$mcIDL$sp();
  Signature: ()Lscala/Function1;
  Code:
   Stack=1, Locals=1, Args_size=1
	aload_0
	invokestatic	Method scala/Function2$class.tupled$mcIDL$sp:(Lscala/Function2;)Lscala/Function1;
	areturn
  Labels:

public scala.Function1 tupled$mcLDL$sp();
  Signature: ()Lscala/Function1;
  Code:
   Stack=1, Locals=1, Args_size=1
	aload_0
	invokestatic	Method scala/Function2$class.tupled$mcLDL$sp:(Lscala/Function2;)Lscala/Function1;
	areturn
  Labels:

public scala.Function1 tupled$mcDDL$sp();
  Signature: ()Lscala/Function1;
  Code:
   Stack=1, Locals=1, Args_size=1
	aload_0
	invokestatic	Method scala/Function2$class.tupled$mcDDL$sp:(Lscala/Function2;)Lscala/Function1;
	areturn
  Labels:

public scala.Function1 tupled$mcVDD$sp();
  Signature: ()Lscala/Function1;
  Code:
   Stack=1, Locals=1, Args_size=1
	aload_0
	invokestatic	Method scala/Function2$class.tupled$mcVDD$sp:(Lscala/Function2;)Lscala/Function1;
	areturn
  Labels:

public scala.Function1 tupled$mcZDD$sp();
  Signature: ()Lscala/Function1;
  Code:
   Stack=1, Locals=1, Args_size=1
	aload_0
	invokestatic	Method scala/Function2$class.tupled$mcZDD$sp:(Lscala/Function2;)Lscala/Function1;
	areturn
  Labels:

public scala.Function1 tupled$mcIDD$sp();
  Signature: ()Lscala/Function1;
  Code:
   Stack=1, Locals=1, Args_size=1
	aload_0
	invokestatic	Method scala/Function2$class.tupled$mcIDD$sp:(Lscala/Function2;)Lscala/Function1;
	areturn
  Labels:

public scala.Function1 tupled$mcLDD$sp();
  Signature: ()Lscala/Function1;
  Code:
   Stack=1, Locals=1, Args_size=1
	aload_0
	invokestatic	Method scala/Function2$class.tupled$mcLDD$sp:(Lscala/Function2;)Lscala/Function1;
	areturn
  Labels:

public scala.Function1 tupled$mcDDD$sp();
  Signature: ()Lscala/Function1;
  Code:
   Stack=1, Locals=1, Args_size=1
	aload_0
	invokestatic	Method scala/Function2$class.tupled$mcDDD$sp:(Lscala/Function2;)Lscala/Function1;
	areturn
  Labels:

public void apply(scala.actors.AbstractActor, scala.actors.remote.Proxy);
  Signature: (Lscala/actors/AbstractActor;Lscala/actors/remote/Proxy;)V
  Code:
   Stack=2, Locals=3, Args_size=3
	aload_1
	aload_2
	invokeinterface	InterfaceMethod scala/actors/AbstractActor.linkTo:(Lscala/actors/AbstractActor;)V
	return
  Labels:
  LocalVariableTable: 
   Start  Length  Slot  Name   Signature
   0      8      0    this       Lscala/actors/remote/LinkToFun;
   0      8      1    target       Lscala/actors/AbstractActor;
   0      8      2    creator       Lscala/actors/remote/Proxy;


public java.lang.String toString();
  Signature: ()Ljava/lang/String;
  Code:
   Stack=1, Locals=1, Args_size=1
	ldc_w	String <LinkToFun>
	areturn
  Labels:

public java.lang.Object apply(java.lang.Object, java.lang.Object);
  Signature: (Ljava/lang/Object;Ljava/lang/Object;)Ljava/lang/Object;
  Code:
   Stack=3, Locals=3, Args_size=3
	aload_0
	aload_1
	checkcast	class scala/actors/AbstractActor
	aload_2
	checkcast	class scala/actors/remote/Proxy
	invokevirtual	Method apply:(Lscala/actors/AbstractActor;Lscala/actors/remote/Proxy;)V
	getstatic	Field scala/runtime/BoxedUnit.UNIT:Lscala/runtime/BoxedUnit;
	areturn
  Labels:
  LocalVariableTable: 
   Start  Length  Slot  Name   Signature
   0      16      0    this       Lscala/actors/remote/LinkToFun;
   0      16      1    v1       Ljava/lang/Object;
   0      16      2    v2       Ljava/lang/Object;


public scala.actors.remote.LinkToFun();
  Signature: ()V
  Code:
   Stack=1, Locals=1, Args_size=1
	aload_0
	invokespecial	Method java/lang/Object."<init>":()V
	aload_0
	invokestatic	Method scala/Function2$class.$init$:(Lscala/Function2;)V
	return
  Labels:

}

