Compiled from "NetKernel.scala"
public final class scala.actors.remote.NamedSend$ extends java.lang.Object implements scala.Function4,scala.ScalaObject
  SourceFile: "NetKernel.scala"
  Scala: length = 0x
   
  minor version: 0
  major version: 49
  Constant pool:
const #1 = Asciz	SourceFile;
const #2 = Asciz	NetKernel.scala;
const #3 = Asciz	Scala;
const #4 = Asciz	MODULE$;
const #5 = Asciz	Lscala/actors/remote/NamedSend$;;
const #6 = Asciz	<clinit>;
const #7 = Asciz	()V;
const #8 = Asciz	Code;
const #9 = Asciz	scala/actors/remote/NamedSend$;
const #10 = class	#9;	//  scala/actors/remote/NamedSend$
const #11 = Asciz	<init>;
const #12 = NameAndType	#11:#7;//  "<init>":()V
const #13 = Method	#10.#12;	//  scala/actors/remote/NamedSend$."<init>":()V
const #14 = Asciz	LineNumberTable;
const #15 = Asciz	java/lang/Object;
const #16 = class	#15;	//  java/lang/Object
const #17 = Method	#16.#12;	//  java/lang/Object."<init>":()V
const #18 = NameAndType	#4:#5;//  MODULE$:Lscala/actors/remote/NamedSend$;
const #19 = Field	#10.#18;	//  scala/actors/remote/NamedSend$.MODULE$:Lscala/actors/remote/NamedSend$;
const #20 = Asciz	scala/Function4$class;
const #21 = class	#20;	//  scala/Function4$class
const #22 = Asciz	$init$;
const #23 = Asciz	(Lscala/Function4;)V;
const #24 = NameAndType	#22:#23;//  $init$:(Lscala/Function4;)V
const #25 = Method	#21.#24;	//  scala/Function4$class.$init$:(Lscala/Function4;)V
const #26 = Asciz	apply;
const #27 = Asciz	(Ljava/lang/Object;Ljava/lang/Object;Ljava/lang/Object;Ljava/lang/Object;)Ljava/lang/Object;;
const #28 = Asciz	scala/actors/remote/Locator;
const #29 = class	#28;	//  scala/actors/remote/Locator
const #30 = Asciz	scala/runtime/BoxedArray;
const #31 = class	#30;	//  scala/runtime/BoxedArray
const #32 = Asciz	scala/runtime/ScalaRunTime$;
const #33 = class	#32;	//  scala/runtime/ScalaRunTime$
const #34 = Asciz	Lscala/runtime/ScalaRunTime$;;
const #35 = NameAndType	#4:#34;//  MODULE$:Lscala/runtime/ScalaRunTime$;
const #36 = Field	#33.#35;	//  scala/runtime/ScalaRunTime$.MODULE$:Lscala/runtime/ScalaRunTime$;
const #37 = Asciz	java/lang/Byte;
const #38 = class	#37;	//  java/lang/Byte
const #39 = Asciz	TYPE;
const #40 = Asciz	Ljava/lang/Class;;
const #41 = NameAndType	#39:#40;//  TYPE:Ljava/lang/Class;
const #42 = Field	#38.#41;	//  java/lang/Byte.TYPE:Ljava/lang/Class;
const #43 = Asciz	arrayValue;
const #44 = Asciz	(Lscala/runtime/BoxedArray;Ljava/lang/Class;)Ljava/lang/Object;;
const #45 = NameAndType	#43:#44;//  arrayValue:(Lscala/runtime/BoxedArray;Ljava/lang/Class;)Ljava/lang/Object;
const #46 = Method	#33.#45;	//  scala/runtime/ScalaRunTime$.arrayValue:(Lscala/runtime/BoxedArray;Ljava/lang/Class;)Ljava/lang/Object;
const #47 = Asciz	[B;
const #48 = class	#47;	//  "[B"
const #49 = Asciz	scala/Symbol;
const #50 = class	#49;	//  scala/Symbol
const #51 = Asciz	(Lscala/actors/remote/Locator;Lscala/actors/remote/Locator;[BLscala/Symbol;)Lscala/actors/remote/NamedSend;;
const #52 = NameAndType	#26:#51;//  apply:(Lscala/actors/remote/Locator;Lscala/actors/remote/Locator;[BLscala/Symbol;)Lscala/actors/remote/NamedSend;
const #53 = Method	#10.#52;	//  scala/actors/remote/NamedSend$.apply:(Lscala/actors/remote/Locator;Lscala/actors/remote/Locator;[BLscala/Symbol;)Lscala/actors/remote/NamedSend;
const #54 = Asciz	this;
const #55 = Asciz	v1;
const #56 = Asciz	Ljava/lang/Object;;
const #57 = Asciz	v2;
const #58 = Asciz	v3;
const #59 = Asciz	v4;
const #60 = Asciz	LocalVariableTable;
const #61 = Asciz	scala/actors/remote/NamedSend;
const #62 = class	#61;	//  scala/actors/remote/NamedSend
const #63 = Asciz	(Lscala/actors/remote/Locator;Lscala/actors/remote/Locator;[BLscala/Symbol;)V;
const #64 = NameAndType	#11:#63;//  "<init>":(Lscala/actors/remote/Locator;Lscala/actors/remote/Locator;[BLscala/Symbol;)V
const #65 = Method	#62.#64;	//  scala/actors/remote/NamedSend."<init>":(Lscala/actors/remote/Locator;Lscala/actors/remote/Locator;[BLscala/Symbol;)V
const #66 = Asciz	senderLoc;
const #67 = Asciz	Lscala/actors/remote/Locator;;
const #68 = Asciz	receiverLoc;
const #69 = Asciz	data;
const #70 = Asciz	session;
const #71 = Asciz	Lscala/Symbol;;
const #72 = Asciz	unapply;
const #73 = Asciz	(Lscala/actors/remote/NamedSend;)Lscala/Some;;
const #74 = Asciz	scala/Some;
const #75 = class	#74;	//  scala/Some
const #76 = Asciz	scala/Tuple4;
const #77 = class	#76;	//  scala/Tuple4
const #78 = Asciz	()Lscala/actors/remote/Locator;;
const #79 = NameAndType	#66:#78;//  senderLoc:()Lscala/actors/remote/Locator;
const #80 = Method	#62.#79;	//  scala/actors/remote/NamedSend.senderLoc:()Lscala/actors/remote/Locator;
const #81 = NameAndType	#68:#78;//  receiverLoc:()Lscala/actors/remote/Locator;
const #82 = Method	#62.#81;	//  scala/actors/remote/NamedSend.receiverLoc:()Lscala/actors/remote/Locator;
const #83 = Asciz	()[B;
const #84 = NameAndType	#69:#83;//  data:()[B
const #85 = Method	#62.#84;	//  scala/actors/remote/NamedSend.data:()[B
const #86 = Asciz	()Lscala/Symbol;;
const #87 = NameAndType	#70:#86;//  session:()Lscala/Symbol;
const #88 = Method	#62.#87;	//  scala/actors/remote/NamedSend.session:()Lscala/Symbol;
const #89 = Asciz	(Ljava/lang/Object;Ljava/lang/Object;Ljava/lang/Object;Ljava/lang/Object;)V;
const #90 = NameAndType	#11:#89;//  "<init>":(Ljava/lang/Object;Ljava/lang/Object;Ljava/lang/Object;Ljava/lang/Object;)V
const #91 = Method	#77.#90;	//  scala/Tuple4."<init>":(Ljava/lang/Object;Ljava/lang/Object;Ljava/lang/Object;Ljava/lang/Object;)V
const #92 = Asciz	(Ljava/lang/Object;)V;
const #93 = NameAndType	#11:#92;//  "<init>":(Ljava/lang/Object;)V
const #94 = Method	#75.#93;	//  scala/Some."<init>":(Ljava/lang/Object;)V
const #95 = Asciz	x$0;
const #96 = Asciz	Lscala/actors/remote/NamedSend;;
const #97 = Asciz	curry;
const #98 = Asciz	()Lscala/Function1;;
const #99 = Asciz	(Lscala/Function4;)Lscala/Function1;;
const #100 = NameAndType	#97:#99;//  curry:(Lscala/Function4;)Lscala/Function1;
const #101 = Method	#21.#100;	//  scala/Function4$class.curry:(Lscala/Function4;)Lscala/Function1;
const #102 = Asciz	toString;
const #103 = Asciz	()Ljava/lang/String;;
const #104 = Asciz	(Lscala/Function4;)Ljava/lang/String;;
const #105 = NameAndType	#102:#104;//  toString:(Lscala/Function4;)Ljava/lang/String;
const #106 = Method	#21.#105;	//  scala/Function4$class.toString:(Lscala/Function4;)Ljava/lang/String;
const #107 = Asciz	scala/Function4;
const #108 = class	#107;	//  scala/Function4
const #109 = Asciz	scala/ScalaObject;
const #110 = class	#109;	//  scala/ScalaObject

{
public static final scala.actors.remote.NamedSend$ MODULE$;

public static {};
  Code:
   Stack=1, Locals=0, Args_size=0
   0:	new	#10; //class scala/actors/remote/NamedSend$
   3:	invokespecial	#13; //Method "<init>":()V
   6:	return

public java.lang.Object apply(java.lang.Object, java.lang.Object, java.lang.Object, java.lang.Object);
  Code:
   Stack=6, Locals=5, Args_size=5
   0:	aload_0
   1:	aload_1
   2:	checkcast	#29; //class scala/actors/remote/Locator
   5:	aload_2
   6:	checkcast	#29; //class scala/actors/remote/Locator
   9:	aload_3
   10:	instanceof	#31; //class scala/runtime/BoxedArray
   13:	ifeq	32
   16:	getstatic	#36; //Field scala/runtime/ScalaRunTime$.MODULE$:Lscala/runtime/ScalaRunTime$;
   19:	aload_3
   20:	checkcast	#31; //class scala/runtime/BoxedArray
   23:	getstatic	#42; //Field java/lang/Byte.TYPE:Ljava/lang/Class;
   26:	invokevirtual	#46; //Method scala/runtime/ScalaRunTime$.arrayValue:(Lscala/runtime/BoxedArray;Ljava/lang/Class;)Ljava/lang/Object;
   29:	goto	33
   32:	aload_3
   33:	checkcast	#48; //class "[B"
   36:	aload	4
   38:	checkcast	#50; //class scala/Symbol
   41:	invokevirtual	#53; //Method apply:(Lscala/actors/remote/Locator;Lscala/actors/remote/Locator;[BLscala/Symbol;)Lscala/actors/remote/NamedSend;
   44:	areturn
  LineNumberTable: 
   line 16: 0

  LocalVariableTable: 
   Start  Length  Slot  Name   Signature
   0      45      0    this       Lscala/actors/remote/NamedSend$;
   0      45      1    v1       Ljava/lang/Object;
   0      45      2    v2       Ljava/lang/Object;
   0      45      3    v3       Ljava/lang/Object;
   0      45      4    v4       Ljava/lang/Object;


public scala.actors.remote.NamedSend apply(scala.actors.remote.Locator, scala.actors.remote.Locator, byte[], scala.Symbol);
  Code:
   Stack=6, Locals=5, Args_size=5
   0:	new	#62; //class scala/actors/remote/NamedSend
   3:	dup
   4:	aload_1
   5:	aload_2
   6:	aload_3
   7:	aload	4
   9:	invokespecial	#65; //Method scala/actors/remote/NamedSend."<init>":(Lscala/actors/remote/Locator;Lscala/actors/remote/Locator;[BLscala/Symbol;)V
   12:	areturn
  LineNumberTable: 
   line 16: 0

  LocalVariableTable: 
   Start  Length  Slot  Name   Signature
   0      13      0    this       Lscala/actors/remote/NamedSend$;
   0      13      1    senderLoc       Lscala/actors/remote/Locator;
   0      13      2    receiverLoc       Lscala/actors/remote/Locator;
   0      13      3    data       [B
   0      13      4    session       Lscala/Symbol;


public scala.Some unapply(scala.actors.remote.NamedSend);
  Code:
   Stack=8, Locals=2, Args_size=2
   0:	new	#75; //class scala/Some
   3:	dup
   4:	new	#77; //class scala/Tuple4
   7:	dup
   8:	aload_1
   9:	invokevirtual	#80; //Method scala/actors/remote/NamedSend.senderLoc:()Lscala/actors/remote/Locator;
   12:	aload_1
   13:	invokevirtual	#82; //Method scala/actors/remote/NamedSend.receiverLoc:()Lscala/actors/remote/Locator;
   16:	aload_1
   17:	invokevirtual	#85; //Method scala/actors/remote/NamedSend.data:()[B
   20:	aload_1
   21:	invokevirtual	#88; //Method scala/actors/remote/NamedSend.session:()Lscala/Symbol;
   24:	invokespecial	#91; //Method scala/Tuple4."<init>":(Ljava/lang/Object;Ljava/lang/Object;Ljava/lang/Object;Ljava/lang/Object;)V
   27:	invokespecial	#94; //Method scala/Some."<init>":(Ljava/lang/Object;)V
   30:	areturn
  LineNumberTable: 
   line 16: 0

  LocalVariableTable: 
   Start  Length  Slot  Name   Signature
   0      31      0    this       Lscala/actors/remote/NamedSend$;
   0      31      1    x$0       Lscala/actors/remote/NamedSend;


public scala.Function1 curry();
  Code:
   Stack=1, Locals=1, Args_size=1
   0:	aload_0
   1:	invokestatic	#101; //Method scala/Function4$class.curry:(Lscala/Function4;)Lscala/Function1;
   4:	areturn
  LineNumberTable: 
   line 16: 0


public java.lang.String toString();
  Code:
   Stack=1, Locals=1, Args_size=1
   0:	aload_0
   1:	invokestatic	#106; //Method scala/Function4$class.toString:(Lscala/Function4;)Ljava/lang/String;
   4:	areturn
  LineNumberTable: 
   line 16: 0


}

