Compiled from "NetKernel.scala"
public class scala.actors.remote.NamedSend extends java.lang.Object implements scala.ScalaObject,scala.Product,java.io.Serializable
  SourceFile: "NetKernel.scala"
  ScalaSig: length = 0x4DF
   05 00 FFFFFF81 2A 06 08 01 02 FFFFFF84 FFFFFF80 FFFFFF80 FFFFFF80 40 09 02 09
   4E 61 6D 65 64 53 65 6E 64 0A 02 03 04 01 06 72
   65 6D 6F 74 65 0A 02 05 06 01 06 61 63 74 6F 72
   73 0A 01 07 01 05 73 63 61 6C 61 03 00 13 04 00
   0A 12 16 10 02 0B 10 0D 01 0C 0A 02 0D 0E 01 04
   6C 61 6E 67 0A 01 0F 01 04 6A 61 76 61 09 02 11
   0C 02 06 4F 62 6A 65 63 74 10 02 13 14 0D 01 06
   09 02 15 06 02 0B 53 63 61 6C 61 4F 62 6A 65 63
   74 10 02 13 17 09 02 18 06 02 07 50 72 6F 64 75
   63 74 08 08 1A 00 FFFFFF82 FFFFFFCA FFFFFF80 FFFFFF84 00 1B 01 09 73 65
   6E 64 65 72 4C 6F 63 15 01 1C 10 02 1D 1E 0D 01
   02 09 02 1F 02 02 07 4C 6F 63 61 74 6F 72 08 08
   21 00 FFFFFF82 FFFFFF88 FFFFFFA0 FFFFFF80 04 1C 01 0A 73 65 6E 64 65 72
   4C 6F 63 20 08 08 23 00 FFFFFF82 FFFFFFCA FFFFFF80 FFFFFF84 00 1B 01 0B
   72 65 63 65 69 76 65 72 4C 6F 63 08 08 25 00 FFFFFF82
   FFFFFF88 FFFFFFA0 FFFFFF80 04 1C 01 0C 72 65 63 65 69 76 65 72 4C
   6F 63 20 08 08 27 00 FFFFFF82 FFFFFFCA FFFFFF80 FFFFFF84 00 28 01 04 64
   61 74 61 15 01 29 10 03 13 2A 2C 09 02 2B 06 02
   05 41 72 72 61 79 10 02 13 2D 09 02 2E 06 02 04
   42 79 74 65 08 08 30 00 FFFFFF82 FFFFFF88 FFFFFFA0 FFFFFF80 04 29 01 05
   64 61 74 61 20 08 08 32 00 FFFFFF82 FFFFFFCA FFFFFF80 FFFFFF84 00 33 01
   07 73 65 73 73 69 6F 6E 15 01 34 10 02 13 35 09
   02 36 06 02 06 53 79 6D 62 6F 6C 08 08 38 00 FFFFFF82
   FFFFFF88 FFFFFFA0 FFFFFF80 04 34 01 08 73 65 73 73 69 6F 6E 20 08
   05 3A 00 FFFFFF84 00 3B 01 06 3C 69 6E 69 74 3E 14 05
   3C 3D 3E 3F 40 10 02 1D 00 08 05 1A 39 FFFFFFC0 00 1C
   08 05 23 39 FFFFFFC0 00 1C 08 05 27 39 FFFFFFC0 00 29 08 05
   32 39 FFFFFFC0 00 34 08 07 42 00 FFFFFF81 FFFFFF80 FFFFFF84 00 43 01 04
   63 6F 70 79 14 05 3C 44 52 55 5A 08 08 45 1A 41
   FFFFFF90 FFFFFF80 FFFFFFC0 00 1C 08 07 46 00 FFFFFF91 FFFFFF80 FFFFFF84 00 47 01 0E
   63 6F 70 79 24 64 65 66 61 75 6C 74 24 31 15 01
   48 2A 02 1C 49 2B 01 4A 10 02 4B 50 0D 01 4C 0A
   02 4D 4E 01 09 75 6E 63 68 65 63 6B 65 64 0A 02
   4F 06 01 0A 61 6E 6E 6F 74 61 74 69 6F 6E 09 02
   51 4C 02 11 75 6E 63 68 65 63 6B 65 64 56 61 72
   69 61 6E 63 65 08 08 53 23 41 FFFFFF90 FFFFFF80 FFFFFFC0 00 1C 08
   07 54 00 FFFFFF91 FFFFFF80 FFFFFF84 00 47 01 0E 63 6F 70 79 24 64
   65 66 61 75 6C 74 24 32 08 08 56 27 41 FFFFFF90 FFFFFF80 FFFFFFC0
   00 29 08 07 57 00 FFFFFF91 FFFFFF80 FFFFFF84 00 58 01 0E 63 6F 70
   79 24 64 65 66 61 75 6C 74 24 33 15 01 59 2A 02
   29 49 08 08 5B 32 41 FFFFFF90 FFFFFF80 FFFFFFC0 00 34 08 07 5C 00
   FFFFFF91 FFFFFF80 FFFFFF84 00 5D 01 0E 63 6F 70 79 24 64 65 66 61
   75 6C 74 24 34 15 01 5E 2A 02 34 49 08 08 60 00
   FFFFFF84 FFFFFF80 FFFFFF80 FFFFFF84 20 61 01 08 68 61 73 68 43 6F 64 65
   14 01 62 10 02 13 63 09 02 64 06 02 03 49 6E 74
   08 08 66 00 FFFFFF84 FFFFFF80 FFFFFF80 FFFFFF84 20 67 01 08 74 6F 53 74
   72 69 6E 67 14 01 68 10 02 69 6C 0E 02 13 6A 09
   02 6B 06 01 06 50 72 65 64 65 66 09 02 6D 6E 02
   06 53 74 72 69 6E 67 0A 02 6B 06 08 08 70 00 FFFFFF84
   FFFFFF80 FFFFFF80 FFFFFF84 20 71 01 06 65 71 75 61 6C 73 14 02 72
   75 10 02 13 73 09 02 74 06 02 07 42 6F 6F 6C 65
   61 6E 08 07 76 6F FFFFFF81 FFFFFF80 FFFFFFC0 00 77 01 03 78 24 31
   10 02 13 78 09 02 79 06 02 03 41 6E 79 08 08 7B
   00 FFFFFF84 FFFFFF80 FFFFFF80 FFFFFF84 20 7C 01 0D 70 72 6F 64 75 63 74
   50 72 65 66 69 78 15 01 7D 10 02 0B 7E 09 02 6D
   0C 08 0A FFFFFF81 00 00 FFFFFF84 FFFFFF80 FFFFFF80 FFFFFF84 20 FFFFFF81 01 01 0C 70
   72 6F 64 75 63 74 41 72 69 74 79 15 01 62 08 0A
   FFFFFF81 03 00 FFFFFF84 FFFFFF80 FFFFFF80 FFFFFF84 20 FFFFFF81 04 01 0E 70 72 6F 64
   75 63 74 45 6C 65 6D 65 6E 74 14 03 77 FFFFFF81 05 08
   08 76 FFFFFF81 02 FFFFFF81 FFFFFF80 FFFFFFC0 00 62 08 0A FFFFFF81 07 00 FFFFFF84 FFFFFF80
   FFFFFF80 FFFFFF84 20 FFFFFF81 08 01 08 63 61 6E 45 71 75 61 6C 14
   03 72 FFFFFF81 09 08 08 76 FFFFFF81 06 FFFFFF81 FFFFFF80 FFFFFFC0 00 77 28 03
   00 FFFFFF81 0B 10 03 13 FFFFFF81 0C 09 03 FFFFFF81 0D 06 02 0C 73
   65 72 69 61 6C 69 7A 61 62 6C 65 07 09 FFFFFF81 0F 02
   FFFFFF81 FFFFFF80 FFFFFF88 02 FFFFFF81 10 01 09 4E 61 6D 65 64 53 65 6E
   64 10 03 1D FFFFFF81 11 06 09 01 02 FFFFFF84 FFFFFF81 FFFFFF80 FFFFFF88 02 FFFFFF81
   12 13 06 FFFFFF81 11 0A FFFFFF81 13 12 10 08 13 FFFFFF81 14 1C 1C
   29 34 3C 09 03 FFFFFF81 15 06 02 09 46 75 6E 63 74 69
   6F 6E 34 08 07 3A FFFFFF81 11 FFFFFF84 00 FFFFFF81 17 14 02 FFFFFF81 10
   08 0A FFFFFF81 19 FFFFFF81 11 FFFFFF81 FFFFFF80 FFFFFF84 40 FFFFFF81 1A 01 05 61 70
   70 6C 79 14 09 3C FFFFFF81 1B FFFFFF81 1C FFFFFF81 1D FFFFFF81 1E 08 06
   1A FFFFFF81 18 FFFFFFC0 00 1C 08 06 23 FFFFFF81 18 FFFFFFC0 00 1C 08 06
   27 FFFFFF81 18 FFFFFFC0 00 29 08 06 32 FFFFFF81 18 FFFFFFC0 00 34 08 0A
   FFFFFF81 20 FFFFFF81 11 FFFFFF81 FFFFFF80 FFFFFF84 40 FFFFFF81 21 01 07 75 6E 61 70
   70 6C 79 14 04 FFFFFF81 22 FFFFFF81 28 10 05 13 FFFFFF81 23 FFFFFF81 25
   09 03 FFFFFF81 24 06 02 04 53 6F 6D 65 10 07 13 FFFFFF81 26
   1C 1C 29 34 09 03 FFFFFF81 27 06 02 06 54 75 70 6C 65
   34 08 07 FFFFFF81 29 FFFFFF81 1F FFFFFFC0 00 3C 01 03 78 24 30 
  minor version: 0
  major version: 49
  Constant pool:
Asciz	SourceFile;
Asciz	NetKernel.scala;
Asciz	tuple;
Asciz	()Lscala/Function1;;
Asciz	Code;
Asciz	scala/actors/remote/NamedSend$;
class	scala/actors/remote/NamedSend$
Asciz	MODULE$;
Asciz	Lscala/actors/remote/NamedSend$;;
NameAndType	MODULE$:Lscala/actors/remote/NamedSend$;
Field	scala/actors/remote/NamedSend$.MODULE$:Lscala/actors/remote/NamedSend$;
NameAndType	tuple:()Lscala/Function1;
Method	scala/actors/remote/NamedSend$.tuple:()Lscala/Function1;
Asciz	curry;
NameAndType	curry:()Lscala/Function1;
Method	scala/actors/remote/NamedSend$.curry:()Lscala/Function1;
Asciz	session;
Asciz	Lscala/Symbol;;
Asciz	data;
Asciz	[B;
Asciz	receiverLoc;
Asciz	Lscala/actors/remote/Locator;;
Asciz	senderLoc;
Asciz	<init>;
Asciz	(Lscala/actors/remote/Locator;Lscala/actors/remote/Locator;[BLscala/Symbol;)V;
Asciz	LineNumberTable;
Asciz	scala/actors/remote/NamedSend;
class	scala/actors/remote/NamedSend
NameAndType	senderLoc:Lscala/actors/remote/Locator;
Field	scala/actors/remote/NamedSend.senderLoc:Lscala/actors/remote/Locator;
NameAndType	receiverLoc:Lscala/actors/remote/Locator;
Field	scala/actors/remote/NamedSend.receiverLoc:Lscala/actors/remote/Locator;
NameAndType	data:[B
Field	scala/actors/remote/NamedSend.data:[B
NameAndType	session:Lscala/Symbol;
Field	scala/actors/remote/NamedSend.session:Lscala/Symbol;
Asciz	java/lang/Object;
class	java/lang/Object
Asciz	()V;
NameAndType	"<init>":()V
Method	java/lang/Object."<init>":()V
Asciz	scala/Product$class;
class	scala/Product$class
Asciz	$init$;
Asciz	(Lscala/Product;)V;
NameAndType	$init$:(Lscala/Product;)V
Method	scala/Product$class.$init$:(Lscala/Product;)V
Asciz	this;
Asciz	Lscala/actors/remote/NamedSend;;
Asciz	LocalVariableTable;
Asciz	gd1$1;
Asciz	(Lscala/actors/remote/Locator;Lscala/actors/remote/Locator;[BLscala/Symbol;)Z;
Asciz	()Lscala/actors/remote/Locator;;
NameAndType	senderLoc:()Lscala/actors/remote/Locator;
Method	scala/actors/remote/NamedSend.senderLoc:()Lscala/actors/remote/Locator;
Asciz	equals;
Asciz	(Ljava/lang/Object;)Z;
NameAndType	equals:(Ljava/lang/Object;)Z
Method	java/lang/Object.equals:(Ljava/lang/Object;)Z
NameAndType	receiverLoc:()Lscala/actors/remote/Locator;
Method	scala/actors/remote/NamedSend.receiverLoc:()Lscala/actors/remote/Locator;
Asciz	()[B;
NameAndType	data:()[B
Method	scala/actors/remote/NamedSend.data:()[B
Asciz	()Lscala/Symbol;;
NameAndType	session:()Lscala/Symbol;
Method	scala/actors/remote/NamedSend.session:()Lscala/Symbol;
Asciz	canEqual;
Asciz	productElement;
Asciz	(I)Ljava/lang/Object;;
Asciz	java/lang/IndexOutOfBoundsException;
class	java/lang/IndexOutOfBoundsException
Asciz	scala/runtime/BoxesRunTime;
class	scala/runtime/BoxesRunTime
Asciz	boxToInteger;
Asciz	(I)Ljava/lang/Integer;;
NameAndType	boxToInteger:(I)Ljava/lang/Integer;
Method	scala/runtime/BoxesRunTime.boxToInteger:(I)Ljava/lang/Integer;
Asciz	toString;
Asciz	()Ljava/lang/String;;
NameAndType	toString:()Ljava/lang/String;
Method	java/lang/Object.toString:()Ljava/lang/String;
Asciz	(Ljava/lang/String;)V;
NameAndType	"<init>":(Ljava/lang/String;)V
Method	java/lang/IndexOutOfBoundsException."<init>":(Ljava/lang/String;)V
Asciz	scala/MatchError;
class	scala/MatchError
Method	scala/MatchError."<init>":(Ljava/lang/String;)V
Asciz	productArity;
Asciz	()I;
Asciz	productPrefix;
Asciz	NamedSend;
String	NamedSend
NameAndType	gd1$1:(Lscala/actors/remote/Locator;Lscala/actors/remote/Locator;[BLscala/Symbol;)Z
Method	scala/actors/remote/NamedSend.gd1$1:(Lscala/actors/remote/Locator;Lscala/actors/remote/Locator;[BLscala/Symbol;)Z
Asciz	scala/Equals;
class	scala/Equals
NameAndType	canEqual:(Ljava/lang/Object;)Z
InterfaceMethod	scala/Equals.canEqual:(Ljava/lang/Object;)Z
Asciz	temp2;
Asciz	temp3;
Asciz	temp4;
Asciz	temp5;
Asciz	temp6;
Asciz	scala/runtime/ScalaRunTime$;
class	scala/runtime/ScalaRunTime$
Asciz	Lscala/runtime/ScalaRunTime$;;
NameAndType	MODULE$:Lscala/runtime/ScalaRunTime$;
Field	scala/runtime/ScalaRunTime$.MODULE$:Lscala/runtime/ScalaRunTime$;
Asciz	_toString;
Asciz	(Lscala/Product;)Ljava/lang/String;;
NameAndType	_toString:(Lscala/Product;)Ljava/lang/String;
Method	scala/runtime/ScalaRunTime$._toString:(Lscala/Product;)Ljava/lang/String;
Asciz	hashCode;
Asciz	_hashCode;
Asciz	(Lscala/Product;)I;
NameAndType	_hashCode:(Lscala/Product;)I
Method	scala/runtime/ScalaRunTime$._hashCode:(Lscala/Product;)I
Asciz	copy;
Asciz	(Lscala/actors/remote/Locator;Lscala/actors/remote/Locator;[BLscala/Symbol;)Lscala/actors/remote/NamedSend;;
NameAndType	"<init>":(Lscala/actors/remote/Locator;Lscala/actors/remote/Locator;[BLscala/Symbol;)V
Method	scala/actors/remote/NamedSend."<init>":(Lscala/actors/remote/Locator;Lscala/actors/remote/Locator;[BLscala/Symbol;)V
Asciz	copy$default$1;
Asciz	copy$default$2;
Asciz	copy$default$3;
Asciz	copy$default$4;
Asciz	productElements;
Asciz	()Lscala/collection/Iterator;;
Asciz	(Lscala/Product;)Lscala/collection/Iterator;;
NameAndType	productElements:(Lscala/Product;)Lscala/collection/Iterator;
Method	scala/Product$class.productElements:(Lscala/Product;)Lscala/collection/Iterator;
Asciz	productIterator;
NameAndType	productIterator:(Lscala/Product;)Lscala/collection/Iterator;
Method	scala/Product$class.productIterator:(Lscala/Product;)Lscala/collection/Iterator;
Asciz	ScalaSig;
Asciz	scala/ScalaObject;
class	scala/ScalaObject
Asciz	scala/Product;
class	scala/Product
Asciz	java/io/Serializable;
class	java/io/Serializable

{
private final scala.Symbol session;
  Signature: Lscala/Symbol;

private final byte[] data;
  Signature: [B

private final scala.actors.remote.Locator receiverLoc;
  Signature: Lscala/actors/remote/Locator;

private final scala.actors.remote.Locator senderLoc;
  Signature: Lscala/actors/remote/Locator;

public static final scala.Function1 tuple();
  Signature: ()Lscala/Function1;
  Code:
   Stack=1, Locals=0, Args_size=0
	getstatic	Field scala/actors/remote/NamedSend$.MODULE$:Lscala/actors/remote/NamedSend$;
	invokevirtual	Method scala/actors/remote/NamedSend$.tuple:()Lscala/Function1;
	areturn
  Labels:

public static final scala.Function1 curry();
  Signature: ()Lscala/Function1;
  Code:
   Stack=1, Locals=0, Args_size=0
	getstatic	Field scala/actors/remote/NamedSend$.MODULE$:Lscala/actors/remote/NamedSend$;
	invokevirtual	Method scala/actors/remote/NamedSend$.curry:()Lscala/Function1;
	areturn
  Labels:

public scala.actors.remote.NamedSend(scala.actors.remote.Locator, scala.actors.remote.Locator, byte[], scala.Symbol);
  Signature: (Lscala/actors/remote/Locator;Lscala/actors/remote/Locator;[BLscala/Symbol;)V
  Code:
   Stack=2, Locals=5, Args_size=5
	aload_0
	aload_1
	putfield	Field senderLoc:Lscala/actors/remote/Locator;
	aload_0
	aload_2
	putfield	Field receiverLoc:Lscala/actors/remote/Locator;
	aload_0
	aload_3
	putfield	Field data:[B
	aload_0
	aload	4
	putfield	Field session:Lscala/Symbol;
	aload_0
	invokespecial	Method java/lang/Object."<init>":()V
	aload_0
	invokestatic	Method scala/Product$class.$init$:(Lscala/Product;)V
	return
  Labels:
  LocalVariableTable: 
   Start  Length  Slot  Name   Signature
   0      30      0    this       Lscala/actors/remote/NamedSend;
   0      30      1    senderLoc       Lscala/actors/remote/Locator;
   0      30      2    receiverLoc       Lscala/actors/remote/Locator;
   0      30      3    data       [B
   0      30      4    session       Lscala/Symbol;


private final boolean gd1$1(scala.actors.remote.Locator, scala.actors.remote.Locator, byte[], scala.Symbol);
  Signature: (Lscala/actors/remote/Locator;Lscala/actors/remote/Locator;[BLscala/Symbol;)Z
  Code:
   Stack=2, Locals=8, Args_size=5
	aload_1
	aload_0
	invokevirtual	Method senderLoc:()Lscala/actors/remote/Locator;
	astore	5
	dup
	ifnonnull	l1 // aload
	pop
	aload	5
	ifnull	l2 // aload_2
	goto	l3 // iconst_0
l1	aload	5
	invokevirtual	Method java/lang/Object.equals:(Ljava/lang/Object;)Z
	ifeq	l3 // iconst_0
l2	aload_2
	aload_0
	invokevirtual	Method receiverLoc:()Lscala/actors/remote/Locator;
	astore	6
	dup
	ifnonnull	l4 // aload
	pop
	aload	6
	ifnull	l5 // aload_3
	goto	l3 // iconst_0
l4	aload	6
	invokevirtual	Method java/lang/Object.equals:(Ljava/lang/Object;)Z
	ifeq	l3 // iconst_0
l5	aload_3
	aload_0
	invokevirtual	Method data:()[B
	if_acmpne	l3 // iconst_0
	aload	4
	aload_0
	invokevirtual	Method session:()Lscala/Symbol;
	astore	7
	dup
	ifnonnull	l6 // aload
	pop
	aload	7
	ifnull	l7 // iconst_1
	goto	l3 // iconst_0
l6	aload	7
	invokevirtual	Method java/lang/Object.equals:(Ljava/lang/Object;)Z
	ifeq	l3 // iconst_0
l7	iconst_1
	goto	l8 // ireturn
l3	iconst_0
l8	ireturn
  Labels:
   	l1 = 20 // aload
   	l2 = 28 // aload_2
   	l4 = 48 // aload
   	l5 = 56 // aload_3
   	l6 = 85 // aload
   	l7 = 93 // iconst_1
   	l3 = 97 // iconst_0
   	l8 = 98 // ireturn

public boolean canEqual(java.lang.Object);
  Signature: (Ljava/lang/Object;)Z
  Code:
   Stack=1, Locals=2, Args_size=2
	aload_1
	instanceof	class scala/actors/remote/NamedSend
	ireturn
  Labels:

public java.lang.Object productElement(int);
  Signature: (I)Ljava/lang/Object;
  Code:
   Stack=3, Locals=2, Args_size=2
	iload_1
	tableswitch{ //0 to 3
		0: 144;
		1: 118;
		2: 92;
		3: 66;
		default: 32 }
	iconst_1
	ifeq	l1 // new
	new	class java/lang/IndexOutOfBoundsException
	dup
	iload_1
	invokestatic	Method scala/runtime/BoxesRunTime.boxToInteger:(I)Ljava/lang/Integer;
	invokevirtual	Method java/lang/Object.toString:()Ljava/lang/String;
	invokespecial	Method java/lang/IndexOutOfBoundsException."<init>":(Ljava/lang/String;)V
	athrow
l1	new	class scala/MatchError
	dup
	iload_1
	invokestatic	Method scala/runtime/BoxesRunTime.boxToInteger:(I)Ljava/lang/Integer;
	invokevirtual	Method java/lang/Object.toString:()Ljava/lang/String;
	invokespecial	Method scala/MatchError."<init>":(Ljava/lang/String;)V
	athrow
	iconst_1
	ifeq	l2 // new
	aload_0
	invokevirtual	Method session:()Lscala/Symbol;
	goto	l3 // areturn
l2	new	class scala/MatchError
	dup
	iload_1
	invokestatic	Method scala/runtime/BoxesRunTime.boxToInteger:(I)Ljava/lang/Integer;
	invokevirtual	Method java/lang/Object.toString:()Ljava/lang/String;
	invokespecial	Method scala/MatchError."<init>":(Ljava/lang/String;)V
	athrow
	iconst_1
	ifeq	l4 // new
	aload_0
	invokevirtual	Method data:()[B
	goto	l3 // areturn
l4	new	class scala/MatchError
	dup
	iload_1
	invokestatic	Method scala/runtime/BoxesRunTime.boxToInteger:(I)Ljava/lang/Integer;
	invokevirtual	Method java/lang/Object.toString:()Ljava/lang/String;
	invokespecial	Method scala/MatchError."<init>":(Ljava/lang/String;)V
	athrow
	iconst_1
	ifeq	l5 // new
	aload_0
	invokevirtual	Method receiverLoc:()Lscala/actors/remote/Locator;
	goto	l3 // areturn
l5	new	class scala/MatchError
	dup
	iload_1
	invokestatic	Method scala/runtime/BoxesRunTime.boxToInteger:(I)Ljava/lang/Integer;
	invokevirtual	Method java/lang/Object.toString:()Ljava/lang/String;
	invokespecial	Method scala/MatchError."<init>":(Ljava/lang/String;)V
	athrow
	iconst_1
	ifeq	l6 // new
	aload_0
	invokevirtual	Method senderLoc:()Lscala/actors/remote/Locator;
l3	areturn
l6	new	class scala/MatchError
	dup
	iload_1
	invokestatic	Method scala/runtime/BoxesRunTime.boxToInteger:(I)Ljava/lang/Integer;
	invokevirtual	Method java/lang/Object.toString:()Ljava/lang/String;
	invokespecial	Method scala/MatchError."<init>":(Ljava/lang/String;)V
	athrow
  Labels:
   	l1 = 51 // new
   	l2 = 77 // new
   	l4 = 103 // new
   	l5 = 129 // new
   	l3 = 152 // areturn
   	l6 = 153 // new

public int productArity();
  Signature: ()I
  Code:
   Stack=1, Locals=1, Args_size=1
	iconst_4
	ireturn
  Labels:

public java.lang.String productPrefix();
  Signature: ()Ljava/lang/String;
  Code:
   Stack=1, Locals=1, Args_size=1
	ldc	String NamedSend
	areturn
  Labels:

public boolean equals(java.lang.Object);
  Signature: (Ljava/lang/Object;)Z
  Code:
   Stack=5, Locals=7, Args_size=2
	aload_0
	aload_1
	if_acmpeq	l1 // iconst_1
	aload_1
	instanceof	class scala/actors/remote/NamedSend
	ifeq	l2 // iconst_1
	aload_1
	checkcast	class scala/actors/remote/NamedSend
	astore_2
	aload_2
	invokevirtual	Method senderLoc:()Lscala/actors/remote/Locator;
	astore_3
	aload_2
	invokevirtual	Method receiverLoc:()Lscala/actors/remote/Locator;
	astore	4
	aload_2
	invokevirtual	Method data:()[B
	astore	5
	aload_2
	invokevirtual	Method session:()Lscala/Symbol;
	astore	6
	aload_0
	aload_3
	aload	4
	aload	5
	aload	6
	invokespecial	Method gd1$1:(Lscala/actors/remote/Locator;Lscala/actors/remote/Locator;[BLscala/Symbol;)Z
	ifeq	l3 // iconst_1
	aload_1
	checkcast	class scala/actors/remote/NamedSend
	aload_0
	invokeinterface	InterfaceMethod scala/Equals.canEqual:(Ljava/lang/Object;)Z
	goto	l4 // ifeq
l3	iconst_1
	ifeq	l5 // new
	iconst_0
	goto	l4 // ifeq
l5	new	class scala/MatchError
	dup
	aload_1
	invokevirtual	Method java/lang/Object.toString:()Ljava/lang/String;
	invokespecial	Method scala/MatchError."<init>":(Ljava/lang/String;)V
	athrow
l2	iconst_1
	ifeq	l6 // new
	iconst_0
l4	ifeq	l7 // iconst_0
l1	iconst_1
	goto	l8 // ireturn
l7	iconst_0
l8	ireturn
l6	new	class scala/MatchError
	dup
	aload_1
	invokevirtual	Method java/lang/Object.toString:()Ljava/lang/String;
	invokespecial	Method scala/MatchError."<init>":(Ljava/lang/String;)V
	athrow
  Labels:
   	l3 = 67 // iconst_1
   	l5 = 75 // new
   	l2 = 87 // iconst_1
   	l4 = 92 // ifeq
   	l1 = 95 // iconst_1
   	l7 = 99 // iconst_0
   	l8 = 100 // ireturn
   	l6 = 101 // new
  LocalVariableTable: 
   Start  Length  Slot  Name   Signature
   0      113      0    this       Lscala/actors/remote/NamedSend;
   17      70      2    temp2       Lscala/actors/remote/NamedSend;
   22      65      3    temp3       Lscala/actors/remote/Locator;
   28      59      4    temp4       Lscala/actors/remote/Locator;
   34      53      5    temp5       [B
   40      47      6    temp6       Lscala/Symbol;


public java.lang.String toString();
  Signature: ()Ljava/lang/String;
  Code:
   Stack=2, Locals=1, Args_size=1
	getstatic	Field scala/runtime/ScalaRunTime$.MODULE$:Lscala/runtime/ScalaRunTime$;
	aload_0
	invokevirtual	Method scala/runtime/ScalaRunTime$._toString:(Lscala/Product;)Ljava/lang/String;
	areturn
  Labels:

public int hashCode();
  Signature: ()I
  Code:
   Stack=2, Locals=1, Args_size=1
	getstatic	Field scala/runtime/ScalaRunTime$.MODULE$:Lscala/runtime/ScalaRunTime$;
	aload_0
	invokevirtual	Method scala/runtime/ScalaRunTime$._hashCode:(Lscala/Product;)I
	ireturn
  Labels:

public scala.actors.remote.NamedSend copy(scala.actors.remote.Locator, scala.actors.remote.Locator, byte[], scala.Symbol);
  Signature: (Lscala/actors/remote/Locator;Lscala/actors/remote/Locator;[BLscala/Symbol;)Lscala/actors/remote/NamedSend;
  Code:
   Stack=6, Locals=5, Args_size=5
	new	class scala/actors/remote/NamedSend
	dup
	aload_1
	aload_2
	aload_3
	aload	4
	invokespecial	Method "<init>":(Lscala/actors/remote/Locator;Lscala/actors/remote/Locator;[BLscala/Symbol;)V
	areturn
  Labels:
  LocalVariableTable: 
   Start  Length  Slot  Name   Signature
   0      13      0    this       Lscala/actors/remote/NamedSend;
   0      13      1    senderLoc       Lscala/actors/remote/Locator;
   0      13      2    receiverLoc       Lscala/actors/remote/Locator;
   0      13      3    data       [B
   0      13      4    session       Lscala/Symbol;


public scala.Symbol session();
  Signature: ()Lscala/Symbol;
  Code:
   Stack=1, Locals=1, Args_size=1
	aload_0
	getfield	Field session:Lscala/Symbol;
	areturn
  Labels:

public byte[] data();
  Signature: ()[B
  Code:
   Stack=1, Locals=1, Args_size=1
	aload_0
	getfield	Field data:[B
	areturn
  Labels:

public scala.actors.remote.Locator receiverLoc();
  Signature: ()Lscala/actors/remote/Locator;
  Code:
   Stack=1, Locals=1, Args_size=1
	aload_0
	getfield	Field receiverLoc:Lscala/actors/remote/Locator;
	areturn
  Labels:

public scala.actors.remote.Locator senderLoc();
  Signature: ()Lscala/actors/remote/Locator;
  Code:
   Stack=1, Locals=1, Args_size=1
	aload_0
	getfield	Field senderLoc:Lscala/actors/remote/Locator;
	areturn
  Labels:

public scala.actors.remote.Locator copy$default$1();
  Signature: ()Lscala/actors/remote/Locator;
  Code:
   Stack=1, Locals=1, Args_size=1
	aload_0
	invokevirtual	Method senderLoc:()Lscala/actors/remote/Locator;
	areturn
  Labels:

public scala.actors.remote.Locator copy$default$2();
  Signature: ()Lscala/actors/remote/Locator;
  Code:
   Stack=1, Locals=1, Args_size=1
	aload_0
	invokevirtual	Method receiverLoc:()Lscala/actors/remote/Locator;
	areturn
  Labels:

public byte[] copy$default$3();
  Signature: ()[B
  Code:
   Stack=1, Locals=1, Args_size=1
	aload_0
	invokevirtual	Method data:()[B
	areturn
  Labels:

public scala.Symbol copy$default$4();
  Signature: ()Lscala/Symbol;
  Code:
   Stack=1, Locals=1, Args_size=1
	aload_0
	invokevirtual	Method session:()Lscala/Symbol;
	areturn
  Labels:

public scala.collection.Iterator productElements();
  Signature: ()Lscala/collection/Iterator;
  Code:
   Stack=1, Locals=1, Args_size=1
	aload_0
	invokestatic	Method scala/Product$class.productElements:(Lscala/Product;)Lscala/collection/Iterator;
	areturn
  Labels:

public scala.collection.Iterator productIterator();
  Signature: ()Lscala/collection/Iterator;
  Code:
   Stack=1, Locals=1, Args_size=1
	aload_0
	invokestatic	Method scala/Product$class.productIterator:(Lscala/Product;)Lscala/collection/Iterator;
	areturn
  Labels:

}

