Compiled from "NetKernel.scala"
public final class scala.actors.remote.NetKernel$$anonfun$terminate$1 extends java.lang.Object implements scala.Function1,scala.ScalaObject,java.io.Serializable
  SourceFile: "NetKernel.scala"
  Scala: length = 0x
   
  InnerClass: 
   public final $anonfun$terminate$1=class scala/actors/remote/NetKernel$$anonfun$terminate$1 of class scala/actors/remote/NetKernel
  minor version: 0
  major version: 49
  Constant pool:
Asciz	SourceFile;
Asciz	NetKernel.scala;
Asciz	<clinit>;
Asciz	()V;
Asciz	Code;
Asciz	serialVersionUID;
Asciz	J;
Asciz	scala/actors/remote/NetKernel$$anonfun$terminate$1;
class	scala/actors/remote/NetKernel$$anonfun$terminate$1
NameAndType	serialVersionUID:J
Field	scala/actors/remote/NetKernel$$anonfun$terminate$1.serialVersionUID:J
Asciz	<init>;
Asciz	(Lscala/actors/remote/NetKernel;)V;
Asciz	LineNumberTable;
Asciz	java/lang/Object;
class	java/lang/Object
NameAndType	"<init>":()V
Method	java/lang/Object."<init>":()V
Asciz	scala/Function1$class;
class	scala/Function1$class
Asciz	$init$;
Asciz	(Lscala/Function1;)V;
NameAndType	$init$:(Lscala/Function1;)V
Method	scala/Function1$class.$init$:(Lscala/Function1;)V
Asciz	this;
Asciz	Lscala/actors/remote/NetKernel$$anonfun$terminate$1;;
Asciz	$outer;
Asciz	Lscala/actors/remote/NetKernel;;
Asciz	LocalVariableTable;
Asciz	apply;
Asciz	(Ljava/lang/Object;)Ljava/lang/Object;;
Asciz	scala/actors/remote/Proxy;
class	scala/actors/remote/Proxy
Asciz	(Lscala/actors/remote/Proxy;)V;
NameAndType	apply:(Lscala/actors/remote/Proxy;)V
Method	scala/actors/remote/NetKernel$$anonfun$terminate$1.apply:(Lscala/actors/remote/Proxy;)V
Asciz	scala/runtime/BoxedUnit;
class	scala/runtime/BoxedUnit
Asciz	UNIT;
Asciz	Lscala/runtime/BoxedUnit;;
NameAndType	UNIT:Lscala/runtime/BoxedUnit;
Field	scala/runtime/BoxedUnit.UNIT:Lscala/runtime/BoxedUnit;
Asciz	v1;
Asciz	Ljava/lang/Object;;
Asciz	scala/actors/remote/Terminate$;
class	scala/actors/remote/Terminate$
Asciz	MODULE$;
Asciz	Lscala/actors/remote/Terminate$;;
NameAndType	MODULE$:Lscala/actors/remote/Terminate$;
Field	scala/actors/remote/Terminate$.MODULE$:Lscala/actors/remote/Terminate$;
Asciz	send;
Asciz	(Ljava/lang/Object;Lscala/actors/OutputChannel;)V;
NameAndType	send:(Ljava/lang/Object;Lscala/actors/OutputChannel;)V
Method	scala/actors/remote/Proxy.send:(Ljava/lang/Object;Lscala/actors/OutputChannel;)V
Asciz	p;
Asciz	Lscala/actors/remote/Proxy;;
Asciz	andThen;
Asciz	(Lscala/Function1;)Lscala/Function1;;
Asciz	(Lscala/Function1;Lscala/Function1;)Lscala/Function1;;
NameAndType	andThen:(Lscala/Function1;Lscala/Function1;)Lscala/Function1;
Method	scala/Function1$class.andThen:(Lscala/Function1;Lscala/Function1;)Lscala/Function1;
Asciz	g;
Asciz	Lscala/Function1;;
Asciz	compose;
NameAndType	compose:(Lscala/Function1;Lscala/Function1;)Lscala/Function1;
Method	scala/Function1$class.compose:(Lscala/Function1;Lscala/Function1;)Lscala/Function1;
Asciz	toString;
Asciz	()Ljava/lang/String;;
Asciz	(Lscala/Function1;)Ljava/lang/String;;
NameAndType	toString:(Lscala/Function1;)Ljava/lang/String;
Method	scala/Function1$class.toString:(Lscala/Function1;)Ljava/lang/String;
Asciz	Scala;
Asciz	InnerClasses;
Asciz	scala/actors/remote/NetKernel;
class	scala/actors/remote/NetKernel
Asciz	$anonfun$terminate$1;
Asciz	scala/Function1;
class	scala/Function1
Asciz	scala/ScalaObject;
class	scala/ScalaObject
Asciz	java/io/Serializable;
class	java/io/Serializable

{
public static final long serialVersionUID;
  Signature: J

public static {};
  Signature: ()V
  Code:
   Stack=2, Locals=0, Args_size=0
	lconst_0
	putstatic	Field serialVersionUID:J
	return
  Labels:

public scala.actors.remote.NetKernel$$anonfun$terminate$1(scala.actors.remote.NetKernel);
  Signature: (Lscala/actors/remote/NetKernel;)V
  Code:
   Stack=1, Locals=2, Args_size=2
	aload_0
	invokespecial	Method java/lang/Object."<init>":()V
	aload_0
	invokestatic	Method scala/Function1$class.$init$:(Lscala/Function1;)V
	return
  Labels:
  LocalVariableTable: 
   Start  Length  Slot  Name   Signature
   0      9      0    this       Lscala/actors/remote/NetKernel$$anonfun$terminate$1;
   0      9      1    $outer       Lscala/actors/remote/NetKernel;


public final java.lang.Object apply(java.lang.Object);
  Signature: (Ljava/lang/Object;)Ljava/lang/Object;
  Code:
   Stack=2, Locals=2, Args_size=2
	aload_0
	aload_1
	checkcast	class scala/actors/remote/Proxy
	invokevirtual	Method apply:(Lscala/actors/remote/Proxy;)V
	getstatic	Field scala/runtime/BoxedUnit.UNIT:Lscala/runtime/BoxedUnit;
	areturn
  Labels:
  LocalVariableTable: 
   Start  Length  Slot  Name   Signature
   0      12      0    this       Lscala/actors/remote/NetKernel$$anonfun$terminate$1;
   0      12      1    v1       Ljava/lang/Object;


public final void apply(scala.actors.remote.Proxy);
  Signature: (Lscala/actors/remote/Proxy;)V
  Code:
   Stack=3, Locals=2, Args_size=2
	aload_1
	getstatic	Field scala/actors/remote/Terminate$.MODULE$:Lscala/actors/remote/Terminate$;
	aconst_null
	invokevirtual	Method scala/actors/remote/Proxy.send:(Ljava/lang/Object;Lscala/actors/OutputChannel;)V
	return
  Labels:
  LocalVariableTable: 
   Start  Length  Slot  Name   Signature
   0      9      0    this       Lscala/actors/remote/NetKernel$$anonfun$terminate$1;
   0      9      1    p       Lscala/actors/remote/Proxy;


public scala.Function1 andThen(scala.Function1);
  Signature: (Lscala/Function1;)Lscala/Function1;
  Code:
   Stack=2, Locals=2, Args_size=2
	aload_0
	aload_1
	invokestatic	Method scala/Function1$class.andThen:(Lscala/Function1;Lscala/Function1;)Lscala/Function1;
	areturn
  Labels:
  LocalVariableTable: 
   Start  Length  Slot  Name   Signature
   0      6      0    this       Lscala/actors/remote/NetKernel$$anonfun$terminate$1;
   0      6      1    g       Lscala/Function1;


public scala.Function1 compose(scala.Function1);
  Signature: (Lscala/Function1;)Lscala/Function1;
  Code:
   Stack=2, Locals=2, Args_size=2
	aload_0
	aload_1
	invokestatic	Method scala/Function1$class.compose:(Lscala/Function1;Lscala/Function1;)Lscala/Function1;
	areturn
  Labels:
  LocalVariableTable: 
   Start  Length  Slot  Name   Signature
   0      6      0    this       Lscala/actors/remote/NetKernel$$anonfun$terminate$1;
   0      6      1    g       Lscala/Function1;


public java.lang.String toString();
  Signature: ()Ljava/lang/String;
  Code:
   Stack=1, Locals=1, Args_size=1
	aload_0
	invokestatic	Method scala/Function1$class.toString:(Lscala/Function1;)Ljava/lang/String;
	areturn
  Labels:

}

