Compiled from "NetKernel.scala"
public class scala.actors.remote.NetKernel extends java.lang.Object implements scala.ScalaObject
  SourceFile: "NetKernel.scala"
  ScalaSig: length = 0x4EF
   05 00 FFFFFF81 30 06 09 01 02 FFFFFF84 FFFFFF80 FFFFFF80 FFFFFF80 00 02 08 02
   09 4E 65 74 4B 65 72 6E 65 6C 0A 02 03 04 01 06
   72 65 6D 6F 74 65 0A 02 05 06 01 06 61 63 74 6F
   72 73 0A 01 07 01 05 73 63 61 6C 61 13 03 00 09
   11 10 02 0A 0F 0D 01 0B 0A 02 0C 0D 01 04 6C 61
   6E 67 0A 01 0E 01 04 6A 61 76 61 09 02 10 0B 02
   06 4F 62 6A 65 63 74 10 02 12 13 0D 01 06 09 02
   14 06 02 0B 53 63 61 6C 61 4F 62 6A 65 63 74 08
   08 16 00 FFFFFF82 FFFFFF80 FFFFFFA0 FFFFFF80 04 18 01 07 73 65 72 76 69
   63 65 03 00 10 02 19 1A 0D 01 02 09 02 1B 02 02
   07 53 65 72 76 69 63 65 08 05 1D 00 FFFFFF84 00 1E 01
   06 3C 69 6E 69 74 3E 14 02 1F 20 10 02 19 00 08
   05 16 1C FFFFFFC0 00 18 08 05 22 00 FFFFFF84 00 23 01 0A 73
   65 6E 64 54 6F 4E 6F 64 65 14 03 24 27 2C 10 02
   12 25 09 02 26 06 02 04 55 6E 69 74 08 05 28 21
   FFFFFFC0 00 29 01 04 6E 6F 64 65 10 02 19 2A 09 02 2B
   02 02 04 4E 6F 64 65 08 05 2D 21 FFFFFFC0 00 2E 01 03
   6D 73 67 10 02 12 2F 09 02 30 06 02 06 41 6E 79
   52 65 66 08 05 32 00 FFFFFF84 00 33 01 09 6E 61 6D 65
   64 53 65 6E 64 14 05 24 34 39 3B 3C 08 05 35 31
   FFFFFFC0 00 36 01 09 73 65 6E 64 65 72 4C 6F 63 10 02
   19 37 09 02 38 02 02 07 4C 6F 63 61 74 6F 72 08
   05 3A 31 FFFFFFC0 00 36 01 0B 72 65 63 65 69 76 65 72
   4C 6F 63 08 05 2D 31 FFFFFFC0 00 2E 08 05 3D 31 FFFFFFC0 00
   3E 01 07 73 65 73 73 69 6F 6E 10 02 12 3F 09 02
   40 06 02 06 53 79 6D 62 6F 6C 08 07 05 00 FFFFFFC2 FFFFFF80
   FFFFFF84 04 42 15 01 43 10 04 44 49 3E 4B 0D 01 45 0A
   02 46 47 01 07 6D 75 74 61 62 6C 65 0A 02 48 06
   01 0A 63 6F 6C 6C 65 63 74 69 6F 6E 09 02 4A 45
   02 07 48 61 73 68 4D 61 70 10 03 4C 4D 4F 0D 01
   04 09 02 4E 04 02 0D 4F 75 74 70 75 74 43 68 61
   6E 6E 65 6C 10 02 12 50 09 02 51 06 02 03 41 6E
   79 08 06 53 00 FFFFFFA0 FFFFFF80 04 43 01 07 61 63 74 6F 72
   73 20 08 07 55 00 FFFFFFC2 FFFFFF80 FFFFFF84 04 56 01 05 6E 61 6D
   65 73 15 01 57 10 04 44 49 4B 3E 08 06 59 00 FFFFFFA0
   FFFFFF80 04 57 01 06 6E 61 6D 65 73 20 08 05 5B 00 FFFFFF84
   00 5C 01 08 72 65 67 69 73 74 65 72 14 03 24 5D
   5F 08 05 5E 5A FFFFFFC0 00 3E 01 04 6E 61 6D 65 08 05
   60 5A FFFFFFC0 00 4B 01 01 61 08 05 62 00 FFFFFF84 00 63 01
   0F 67 65 74 4F 72 43 72 65 61 74 65 4E 61 6D 65
   14 02 3E 64 08 05 65 61 FFFFFFC0 00 4B 01 04 66 72 6F
   6D 08 05 67 00 FFFFFF84 00 68 01 04 73 65 6E 64 14 04
   24 69 6A 6B 08 05 28 66 FFFFFFC0 00 29 08 05 5E 66 FFFFFFC0
   00 3E 08 05 2D 66 FFFFFFC0 00 2E 08 05 67 00 FFFFFF84 00 6D
   14 05 24 6E 6F 70 71 08 05 28 6C FFFFFFC0 00 29 08 05
   5E 6C FFFFFFC0 00 3E 08 05 2D 6C FFFFFFC0 00 2E 08 05 3D 6C
   FFFFFFC0 00 3E 08 05 73 00 FFFFFF84 00 74 01 07 66 6F 72 77
   61 72 64 14 06 24 75 76 77 78 79 08 05 65 72 FFFFFFC0
   00 4B 08 05 28 72 FFFFFFC0 00 29 08 05 5E 72 FFFFFFC0 00 3E
   08 05 2D 72 FFFFFFC0 00 2E 08 05 3D 72 FFFFFFC0 00 3E 08 05
   7B 00 FFFFFF84 00 7C 01 0B 72 65 6D 6F 74 65 41 70 70
   6C 79 14 06 24 7D 7E 7F FFFFFF81 00 08 05 28 7A FFFFFFC0 00
   29 08 05 5E 7A FFFFFFC0 00 3E 08 05 65 7A FFFFFFC0 00 4B 08
   07 FFFFFF81 01 7A FFFFFFC0 00 FFFFFF81 02 01 04 72 66 75 6E 10 08
   12 FFFFFF81 03 FFFFFF81 05 FFFFFF81 08 24 09 03 FFFFFF81 04 06 02 09 46
   75 6E 63 74 69 6F 6E 32 10 03 4C FFFFFF81 06 09 03 FFFFFF81
   07 04 02 0D 41 62 73 74 72 61 63 74 41 63 74 6F
   72 10 03 19 FFFFFF81 09 09 03 FFFFFF81 0A 02 02 05 50 72 6F
   78 79 08 07 FFFFFF81 0C 00 FFFFFF84 00 FFFFFF81 0D 01 0B 63 72 65
   61 74 65 50 72 6F 78 79 14 06 FFFFFF81 08 FFFFFF81 0E FFFFFF81 0F
   08 06 28 FFFFFF81 0B FFFFFFC0 00 29 08 07 FFFFFF81 10 FFFFFF81 0B FFFFFFC0 00
   3E 01 03 73 79 6D 08 09 FFFFFF81 12 00 FFFFFFC2 FFFFFF80 FFFFFF84 00 FFFFFF81
   13 01 07 70 72 6F 78 69 65 73 15 02 FFFFFF81 14 10 06
   44 49 FFFFFF81 15 FFFFFF81 08 10 05 12 FFFFFF81 16 29 3E 09 03 FFFFFF81
   17 06 02 06 54 75 70 6C 65 32 08 08 FFFFFF81 19 00 FFFFFFA0
   FFFFFF80 04 FFFFFF81 14 01 08 70 72 6F 78 69 65 73 20 08 07
   FFFFFF81 1B 00 FFFFFF84 00 FFFFFF81 1C 01 10 67 65 74 4F 72 43 72
   65 61 74 65 50 72 6F 78 79 14 06 FFFFFF81 08 FFFFFF81 1D FFFFFF81
   1F 08 07 FFFFFF81 1E FFFFFF81 1A FFFFFFC0 00 29 01 0A 73 65 6E 64
   65 72 4E 6F 64 65 08 07 FFFFFF81 20 FFFFFF81 1A FFFFFFC0 00 3E 01
   0A 73 65 6E 64 65 72 4E 61 6D 65 08 07 FFFFFF81 22 00
   FFFFFF84 00 FFFFFF81 23 01 0D 72 65 67 69 73 74 65 72 50 72
   6F 78 79 14 07 24 FFFFFF81 24 FFFFFF81 25 FFFFFF81 26 08 07 FFFFFF81 1E
   FFFFFF81 21 FFFFFFC0 00 29 08 07 FFFFFF81 20 FFFFFF81 21 FFFFFFC0 00 3E 08 08
   FFFFFF81 27 FFFFFF81 21 FFFFFFC0 00 FFFFFF81 08 01 01 70 08 07 FFFFFF81 29 00
   FFFFFF84 00 FFFFFF81 2A 01 0A 70 72 6F 63 65 73 73 4D 73 67
   14 05 24 FFFFFF81 2B FFFFFF81 2C 08 07 FFFFFF81 1E FFFFFF81 28 FFFFFFC0 00 29
   08 06 2D FFFFFF81 28 FFFFFFC0 00 2E 08 07 FFFFFF81 2E 00 FFFFFF84 00 FFFFFF81
   2F 01 09 74 65 72 6D 69 6E 61 74 65 14 01 24 
  InnerClass: 
   public final #379= #142 of #22; //$anonfun$terminate$1=class scala/actors/remote/NetKernel$$anonfun$terminate$1 of class scala/actors/remote/NetKernel
  minor version: 0
  major version: 49
  Constant pool:
const #1 = Asciz	SourceFile;
const #2 = Asciz	NetKernel.scala;
const #3 = Asciz	<clinit>;
const #4 = Asciz	()V;
const #5 = Asciz	Code;
const #6 = Asciz	scala/Symbol$;
const #7 = class	#6;	//  scala/Symbol$
const #8 = Asciz	MODULE$;
const #9 = Asciz	Lscala/Symbol$;;
const #10 = NameAndType	#8:#9;//  MODULE$:Lscala/Symbol$;
const #11 = Field	#7.#10;	//  scala/Symbol$.MODULE$:Lscala/Symbol$;
const #12 = Asciz	LineNumberTable;
const #13 = Asciz	nosession;
const #14 = String	#13;	//  nosession
const #15 = Asciz	apply;
const #16 = Asciz	(Ljava/lang/Object;)Ljava/lang/Object;;
const #17 = NameAndType	#15:#16;//  apply:(Ljava/lang/Object;)Ljava/lang/Object;
const #18 = Method	#7.#17;	//  scala/Symbol$.apply:(Ljava/lang/Object;)Ljava/lang/Object;
const #19 = Asciz	scala/Symbol;
const #20 = class	#19;	//  scala/Symbol
const #21 = Asciz	scala/actors/remote/NetKernel;
const #22 = class	#21;	//  scala/actors/remote/NetKernel
const #23 = Asciz	symbol$1;
const #24 = Asciz	Lscala/Symbol;;
const #25 = NameAndType	#23:#24;//  symbol$1:Lscala/Symbol;
const #26 = Field	#22.#25;	//  scala/actors/remote/NetKernel.symbol$1:Lscala/Symbol;
const #27 = Asciz	proxies;
const #28 = Asciz	Lscala/collection/mutable/HashMap;;
const #29 = Asciz	Lscala/collection/mutable/HashMap<Lscala/Tuple2<Lscala/actors/remote/Node;Lscala/Symbol;>;Lscala/actors/remote/Proxy;>;;
const #30 = Asciz	Signature;
const #31 = Asciz	names;
const #32 = Asciz	Lscala/collection/mutable/HashMap<Lscala/actors/OutputChannel<Ljava/lang/Object;>;Lscala/Symbol;>;;
const #33 = Asciz	actors;
const #34 = Asciz	Lscala/collection/mutable/HashMap<Lscala/Symbol;Lscala/actors/OutputChannel<Ljava/lang/Object;>;>;;
const #35 = Asciz	service;
const #36 = Asciz	Lscala/actors/remote/Service;;
const #37 = Asciz	<init>;
const #38 = Asciz	(Lscala/actors/remote/Service;)V;
const #39 = NameAndType	#35:#36;//  service:Lscala/actors/remote/Service;
const #40 = Field	#22.#39;	//  scala/actors/remote/NetKernel.service:Lscala/actors/remote/Service;
const #41 = Asciz	java/lang/Object;
const #42 = class	#41;	//  java/lang/Object
const #43 = NameAndType	#37:#4;//  "<init>":()V
const #44 = Method	#42.#43;	//  java/lang/Object."<init>":()V
const #45 = Asciz	scala/collection/mutable/HashMap;
const #46 = class	#45;	//  scala/collection/mutable/HashMap
const #47 = Method	#46.#43;	//  scala/collection/mutable/HashMap."<init>":()V
const #48 = NameAndType	#33:#28;//  actors:Lscala/collection/mutable/HashMap;
const #49 = Field	#22.#48;	//  scala/actors/remote/NetKernel.actors:Lscala/collection/mutable/HashMap;
const #50 = NameAndType	#31:#28;//  names:Lscala/collection/mutable/HashMap;
const #51 = Field	#22.#50;	//  scala/actors/remote/NetKernel.names:Lscala/collection/mutable/HashMap;
const #52 = NameAndType	#27:#28;//  proxies:Lscala/collection/mutable/HashMap;
const #53 = Field	#22.#52;	//  scala/actors/remote/NetKernel.proxies:Lscala/collection/mutable/HashMap;
const #54 = Asciz	this;
const #55 = Asciz	Lscala/actors/remote/NetKernel;;
const #56 = Asciz	LocalVariableTable;
const #57 = Asciz	liftedTree1$1;
const #58 = Asciz	(Lscala/actors/remote/Locator;[BLscala/Symbol;Lscala/actors/OutputChannel;)V;
const #59 = Asciz	scala/actors/remote/Service;
const #60 = class	#59;	//  scala/actors/remote/Service
const #61 = Asciz	serializer;
const #62 = Asciz	()Lscala/actors/remote/Serializer;;
const #63 = NameAndType	#61:#62;//  serializer:()Lscala/actors/remote/Serializer;
const #64 = InterfaceMethod	#60.#63;	//  scala/actors/remote/Service.serializer:()Lscala/actors/remote/Serializer;
const #65 = Asciz	scala/actors/remote/Serializer;
const #66 = class	#65;	//  scala/actors/remote/Serializer
const #67 = Asciz	deserialize;
const #68 = Asciz	([B)Ljava/lang/Object;;
const #69 = NameAndType	#67:#68;//  deserialize:([B)Ljava/lang/Object;
const #70 = Method	#66.#69;	//  scala/actors/remote/Serializer.deserialize:([B)Ljava/lang/Object;
const #71 = Asciz	scala/actors/remote/Locator;
const #72 = class	#71;	//  scala/actors/remote/Locator
const #73 = Asciz	node;
const #74 = Asciz	()Lscala/actors/remote/Node;;
const #75 = NameAndType	#73:#74;//  node:()Lscala/actors/remote/Node;
const #76 = Method	#72.#75;	//  scala/actors/remote/Locator.node:()Lscala/actors/remote/Node;
const #77 = Asciz	name;
const #78 = Asciz	()Lscala/Symbol;;
const #79 = NameAndType	#77:#78;//  name:()Lscala/Symbol;
const #80 = Method	#72.#79;	//  scala/actors/remote/Locator.name:()Lscala/Symbol;
const #81 = Asciz	getOrCreateProxy;
const #82 = Asciz	(Lscala/actors/remote/Node;Lscala/Symbol;)Lscala/actors/remote/Proxy;;
const #83 = NameAndType	#81:#82;//  getOrCreateProxy:(Lscala/actors/remote/Node;Lscala/Symbol;)Lscala/actors/remote/Proxy;
const #84 = Method	#22.#83;	//  scala/actors/remote/NetKernel.getOrCreateProxy:(Lscala/actors/remote/Node;Lscala/Symbol;)Lscala/actors/remote/Proxy;
const #85 = Asciz	scala/actors/remote/SendTo;
const #86 = class	#85;	//  scala/actors/remote/SendTo
const #87 = Asciz	(Lscala/actors/OutputChannel;Ljava/lang/Object;Lscala/Symbol;)V;
const #88 = NameAndType	#37:#87;//  "<init>":(Lscala/actors/OutputChannel;Ljava/lang/Object;Lscala/Symbol;)V
const #89 = Method	#86.#88;	//  scala/actors/remote/SendTo."<init>":(Lscala/actors/OutputChannel;Ljava/lang/Object;Lscala/Symbol;)V
const #90 = Asciz	scala/actors/remote/Proxy;
const #91 = class	#90;	//  scala/actors/remote/Proxy
const #92 = Asciz	send;
const #93 = Asciz	(Ljava/lang/Object;Lscala/actors/OutputChannel;)V;
const #94 = NameAndType	#92:#93;//  send:(Ljava/lang/Object;Lscala/actors/OutputChannel;)V
const #95 = Method	#91.#94;	//  scala/actors/remote/Proxy.send:(Ljava/lang/Object;Lscala/actors/OutputChannel;)V
const #96 = Asciz	scala/actors/Debug$;
const #97 = class	#96;	//  scala/actors/Debug$
const #98 = Asciz	Lscala/actors/Debug$;;
const #99 = NameAndType	#8:#98;//  MODULE$:Lscala/actors/Debug$;
const #100 = Field	#97.#99;	//  scala/actors/Debug$.MODULE$:Lscala/actors/Debug$;
const #101 = Asciz	scala/collection/mutable/StringBuilder;
const #102 = class	#101;	//  scala/collection/mutable/StringBuilder
const #103 = Method	#102.#43;	//  scala/collection/mutable/StringBuilder."<init>":()V
const #104 = Asciz	scala/runtime/StringAdd;
const #105 = class	#104;	//  scala/runtime/StringAdd
const #106 = Asciz	(Ljava/lang/Object;)V;
const #107 = NameAndType	#37:#106;//  "<init>":(Ljava/lang/Object;)V
const #108 = Method	#105.#107;	//  scala/runtime/StringAdd."<init>":(Ljava/lang/Object;)V
const #109 = Asciz	: caught ;
const #110 = String	#109;	//  : caught 
const #111 = Asciz	$plus;
const #112 = Asciz	(Ljava/lang/String;)Ljava/lang/String;;
const #113 = NameAndType	#111:#112;//  $plus:(Ljava/lang/String;)Ljava/lang/String;
const #114 = Method	#105.#113;	//  scala/runtime/StringAdd.$plus:(Ljava/lang/String;)Ljava/lang/String;
const #115 = Asciz	append;
const #116 = Asciz	(Ljava/lang/Object;)Lscala/collection/mutable/StringBuilder;;
const #117 = NameAndType	#115:#116;//  append:(Ljava/lang/Object;)Lscala/collection/mutable/StringBuilder;
const #118 = Method	#102.#117;	//  scala/collection/mutable/StringBuilder.append:(Ljava/lang/Object;)Lscala/collection/mutable/StringBuilder;
const #119 = Asciz	toString;
const #120 = Asciz	()Ljava/lang/String;;
const #121 = NameAndType	#119:#120;//  toString:()Ljava/lang/String;
const #122 = Method	#102.#121;	//  scala/collection/mutable/StringBuilder.toString:()Ljava/lang/String;
const #123 = Asciz	error;
const #124 = Asciz	(Ljava/lang/String;)V;
const #125 = NameAndType	#123:#124;//  error:(Ljava/lang/String;)V
const #126 = Method	#97.#125;	//  scala/actors/Debug$.error:(Ljava/lang/String;)V
const #127 = Asciz	java/lang/Exception;
const #128 = class	#127;	//  java/lang/Exception
const #129 = Asciz	senderProxy;
const #130 = Asciz	Lscala/actors/remote/Proxy;;
const #131 = Asciz	msg;
const #132 = Asciz	Ljava/lang/Object;;
const #133 = Asciz	terminate;
const #134 = Asciz	()Lscala/collection/mutable/HashMap;;
const #135 = NameAndType	#27:#134;//  proxies:()Lscala/collection/mutable/HashMap;
const #136 = Method	#22.#135;	//  scala/actors/remote/NetKernel.proxies:()Lscala/collection/mutable/HashMap;
const #137 = Asciz	valuesIterator;
const #138 = Asciz	()Lscala/collection/Iterator;;
const #139 = NameAndType	#137:#138;//  valuesIterator:()Lscala/collection/Iterator;
const #140 = Method	#46.#139;	//  scala/collection/mutable/HashMap.valuesIterator:()Lscala/collection/Iterator;
const #141 = Asciz	scala/actors/remote/NetKernel$$anonfun$terminate$1;
const #142 = class	#141;	//  scala/actors/remote/NetKernel$$anonfun$terminate$1
const #143 = Asciz	(Lscala/actors/remote/NetKernel;)V;
const #144 = NameAndType	#37:#143;//  "<init>":(Lscala/actors/remote/NetKernel;)V
const #145 = Method	#142.#144;	//  scala/actors/remote/NetKernel$$anonfun$terminate$1."<init>":(Lscala/actors/remote/NetKernel;)V
const #146 = Asciz	scala/collection/Iterator;
const #147 = class	#146;	//  scala/collection/Iterator
const #148 = Asciz	foreach;
const #149 = Asciz	(Lscala/Function1;)V;
const #150 = NameAndType	#148:#149;//  foreach:(Lscala/Function1;)V
const #151 = InterfaceMethod	#147.#150;	//  scala/collection/Iterator.foreach:(Lscala/Function1;)V
const #152 = NameAndType	#133:#4;//  terminate:()V
const #153 = InterfaceMethod	#60.#152;	//  scala/actors/remote/Service.terminate:()V
const #154 = Asciz	processMsg;
const #155 = Asciz	(Lscala/actors/remote/Node;Ljava/lang/Object;)V;
const #156 = Asciz	scala/actors/remote/RemoteApply0;
const #157 = class	#156;	//  scala/actors/remote/RemoteApply0
const #158 = Asciz	senderLoc;
const #159 = Asciz	()Lscala/actors/remote/Locator;;
const #160 = NameAndType	#158:#159;//  senderLoc:()Lscala/actors/remote/Locator;
const #161 = Method	#157.#160;	//  scala/actors/remote/RemoteApply0.senderLoc:()Lscala/actors/remote/Locator;
const #162 = Asciz	receiverLoc;
const #163 = NameAndType	#162:#159;//  receiverLoc:()Lscala/actors/remote/Locator;
const #164 = Method	#157.#163;	//  scala/actors/remote/RemoteApply0.receiverLoc:()Lscala/actors/remote/Locator;
const #165 = Asciz	rfun;
const #166 = Asciz	()Lscala/Function2;;
const #167 = NameAndType	#165:#166;//  rfun:()Lscala/Function2;
const #168 = Method	#157.#167;	//  scala/actors/remote/RemoteApply0.rfun:()Lscala/Function2;
const #169 = Asciz	: processing ;
const #170 = String	#169;	//  : processing 
const #171 = Asciz	info;
const #172 = NameAndType	#171:#124;//  info:(Ljava/lang/String;)V
const #173 = Method	#97.#172;	//  scala/actors/Debug$.info:(Ljava/lang/String;)V
const #174 = NameAndType	#33:#134;//  actors:()Lscala/collection/mutable/HashMap;
const #175 = Method	#22.#174;	//  scala/actors/remote/NetKernel.actors:()Lscala/collection/mutable/HashMap;
const #176 = Asciz	get;
const #177 = Asciz	(Ljava/lang/Object;)Lscala/Option;;
const #178 = NameAndType	#176:#177;//  get:(Ljava/lang/Object;)Lscala/Option;
const #179 = Method	#46.#178;	//  scala/collection/mutable/HashMap.get:(Ljava/lang/Object;)Lscala/Option;
const #180 = Asciz	scala/Some;
const #181 = class	#180;	//  scala/Some
const #182 = Asciz	x;
const #183 = Asciz	()Ljava/lang/Object;;
const #184 = NameAndType	#182:#183;//  x:()Ljava/lang/Object;
const #185 = Method	#181.#184;	//  scala/Some.x:()Ljava/lang/Object;
const #186 = Asciz	scala/actors/OutputChannel;
const #187 = class	#186;	//  scala/actors/OutputChannel
const #188 = Asciz	scala/actors/remote/LocalApply0;
const #189 = class	#188;	//  scala/actors/remote/LocalApply0
const #190 = Asciz	scala/actors/AbstractActor;
const #191 = class	#190;	//  scala/actors/AbstractActor
const #192 = Asciz	(Lscala/Function2;Lscala/actors/AbstractActor;)V;
const #193 = NameAndType	#37:#192;//  "<init>":(Lscala/Function2;Lscala/actors/AbstractActor;)V
const #194 = Method	#189.#193;	//  scala/actors/remote/LocalApply0."<init>":(Lscala/Function2;Lscala/actors/AbstractActor;)V
const #195 = Asciz	scala/MatchError;
const #196 = class	#195;	//  scala/MatchError
const #197 = Asciz	scala/Option;
const #198 = class	#197;	//  scala/Option
const #199 = Method	#198.#121;	//  scala/Option.toString:()Ljava/lang/String;
const #200 = NameAndType	#37:#124;//  "<init>":(Ljava/lang/String;)V
const #201 = Method	#196.#200;	//  scala/MatchError."<init>":(Ljava/lang/String;)V
const #202 = Asciz	scala/None$;
const #203 = class	#202;	//  scala/None$
const #204 = Asciz	Lscala/None$;;
const #205 = NameAndType	#8:#204;//  MODULE$:Lscala/None$;
const #206 = Field	#203.#205;	//  scala/None$.MODULE$:Lscala/None$;
const #207 = Asciz	equals;
const #208 = Asciz	(Ljava/lang/Object;)Z;
const #209 = NameAndType	#207:#208;//  equals:(Ljava/lang/Object;)Z
const #210 = Method	#42.#209;	//  java/lang/Object.equals:(Ljava/lang/Object;)Z
const #211 = Asciz	: lost message;
const #212 = String	#211;	//  : lost message
const #213 = Method	#42.#121;	//  java/lang/Object.toString:()Ljava/lang/String;
const #214 = Asciz	scala/actors/remote/NamedSend;
const #215 = class	#214;	//  scala/actors/remote/NamedSend
const #216 = Method	#215.#160;	//  scala/actors/remote/NamedSend.senderLoc:()Lscala/actors/remote/Locator;
const #217 = Method	#215.#163;	//  scala/actors/remote/NamedSend.receiverLoc:()Lscala/actors/remote/Locator;
const #218 = Asciz	data;
const #219 = Asciz	()[B;
const #220 = NameAndType	#218:#219;//  data:()[B
const #221 = Method	#215.#220;	//  scala/actors/remote/NamedSend.data:()[B
const #222 = Asciz	session;
const #223 = NameAndType	#222:#78;//  session:()Lscala/Symbol;
const #224 = Method	#215.#223;	//  scala/actors/remote/NamedSend.session:()Lscala/Symbol;
const #225 = NameAndType	#57:#58;//  liftedTree1$1:(Lscala/actors/remote/Locator;[BLscala/Symbol;Lscala/actors/OutputChannel;)V
const #226 = Method	#22.#225;	//  scala/actors/remote/NetKernel.liftedTree1$1:(Lscala/actors/remote/Locator;[BLscala/Symbol;Lscala/actors/OutputChannel;)V
const #227 = Asciz	scala/Predef$;
const #228 = class	#227;	//  scala/Predef$
const #229 = Asciz	Lscala/Predef$;;
const #230 = NameAndType	#8:#229;//  MODULE$:Lscala/Predef$;
const #231 = Field	#228.#230;	//  scala/Predef$.MODULE$:Lscala/Predef$;
const #232 = Asciz	any2stringadd;
const #233 = Asciz	(Ljava/lang/Object;)Lscala/runtime/StringAdd;;
const #234 = NameAndType	#232:#233;//  any2stringadd:(Ljava/lang/Object;)Lscala/runtime/StringAdd;
const #235 = Method	#228.#234;	//  scala/Predef$.any2stringadd:(Ljava/lang/Object;)Lscala/runtime/StringAdd;
const #236 = Asciz	java/lang/Throwable;
const #237 = class	#236;	//  java/lang/Throwable
const #238 = Asciz	senderNode;
const #239 = Asciz	Lscala/actors/remote/Node;;
const #240 = Asciz	temp52;
const #241 = Asciz	Lscala/actors/remote/RemoteApply0;;
const #242 = Asciz	temp54;
const #243 = Asciz	Lscala/actors/remote/Locator;;
const #244 = Asciz	temp44;
const #245 = Asciz	Lscala/Some;;
const #246 = Asciz	temp53;
const #247 = Asciz	temp55;
const #248 = Asciz	Lscala/Function2;;
const #249 = Asciz	temp45;
const #250 = Asciz	Lscala/actors/OutputChannel;;
const #251 = Asciz	temp43;
const #252 = Asciz	Lscala/Option;;
const #253 = Asciz	temp56;
const #254 = Asciz	Lscala/actors/remote/NamedSend;;
const #255 = Asciz	temp58;
const #256 = Asciz	temp48;
const #257 = Asciz	temp57;
const #258 = Asciz	temp59;
const #259 = Asciz	[B;
const #260 = Asciz	temp60;
const #261 = Asciz	temp49;
const #262 = Asciz	temp47;
const #263 = Asciz	registerProxy;
const #264 = Asciz	(Lscala/actors/remote/Node;Lscala/Symbol;Lscala/actors/remote/Proxy;)V;
const #265 = Asciz	scala/Tuple2;
const #266 = class	#265;	//  scala/Tuple2
const #267 = Asciz	(Ljava/lang/Object;Ljava/lang/Object;)V;
const #268 = NameAndType	#37:#267;//  "<init>":(Ljava/lang/Object;Ljava/lang/Object;)V
const #269 = Method	#266.#268;	//  scala/Tuple2."<init>":(Ljava/lang/Object;Ljava/lang/Object;)V
const #270 = Asciz	scala/runtime/BoxedUnit;
const #271 = class	#270;	//  scala/runtime/BoxedUnit
const #272 = Asciz	UNIT;
const #273 = Asciz	Lscala/runtime/BoxedUnit;;
const #274 = NameAndType	#272:#273;//  UNIT:Lscala/runtime/BoxedUnit;
const #275 = Field	#271.#274;	//  scala/runtime/BoxedUnit.UNIT:Lscala/runtime/BoxedUnit;
const #276 = Asciz	scala/Predef$Pair$;
const #277 = class	#276;	//  scala/Predef$Pair$
const #278 = Asciz	Lscala/Predef$Pair$;;
const #279 = NameAndType	#8:#278;//  MODULE$:Lscala/Predef$Pair$;
const #280 = Field	#277.#279;	//  scala/Predef$Pair$.MODULE$:Lscala/Predef$Pair$;
const #281 = Asciz	(Ljava/lang/Object;Ljava/lang/Object;)Lscala/Tuple2;;
const #282 = NameAndType	#15:#281;//  apply:(Ljava/lang/Object;Ljava/lang/Object;)Lscala/Tuple2;
const #283 = Method	#277.#282;	//  scala/Predef$Pair$.apply:(Ljava/lang/Object;Ljava/lang/Object;)Lscala/Tuple2;
const #284 = Asciz	$plus$eq;
const #285 = Asciz	(Lscala/Tuple2;)Lscala/collection/mutable/HashMap;;
const #286 = NameAndType	#284:#285;//  $plus$eq:(Lscala/Tuple2;)Lscala/collection/mutable/HashMap;
const #287 = Method	#46.#286;	//  scala/collection/mutable/HashMap.$plus$eq:(Lscala/Tuple2;)Lscala/collection/mutable/HashMap;
const #288 = Asciz	senderName;
const #289 = Asciz	p;
const #290 = Asciz	temp39;
const #291 = Asciz	createProxy;
const #292 = NameAndType	#291:#82;//  createProxy:(Lscala/actors/remote/Node;Lscala/Symbol;)Lscala/actors/remote/Proxy;
const #293 = Method	#22.#292;	//  scala/actors/remote/NetKernel.createProxy:(Lscala/actors/remote/Node;Lscala/Symbol;)Lscala/actors/remote/Proxy;
const #294 = Asciz	temp36;
const #295 = Asciz	temp37;
const #296 = Asciz	temp35;
const #297 = Asciz	()Lscala/collection/mutable/HashMap<Lscala/Tuple2<Lscala/actors/remote/Node;Lscala/Symbol;>;Lscala/actors/remote/Proxy;>;;
const #298 = Asciz	(Lscala/actors/remote/Node;Lscala/Symbol;Lscala/actors/remote/NetKernel;)V;
const #299 = NameAndType	#37:#298;//  "<init>":(Lscala/actors/remote/Node;Lscala/Symbol;Lscala/actors/remote/NetKernel;)V
const #300 = Method	#91.#299;	//  scala/actors/remote/Proxy."<init>":(Lscala/actors/remote/Node;Lscala/Symbol;Lscala/actors/remote/NetKernel;)V
const #301 = Asciz	sym;
const #302 = Asciz	remoteApply;
const #303 = Asciz	(Lscala/actors/remote/Node;Lscala/Symbol;Lscala/actors/OutputChannel;Lscala/Function2;)V;
const #304 = InterfaceMethod	#60.#75;	//  scala/actors/remote/Service.node:()Lscala/actors/remote/Node;
const #305 = Asciz	getOrCreateName;
const #306 = Asciz	(Lscala/actors/OutputChannel;)Lscala/Symbol;;
const #307 = NameAndType	#305:#306;//  getOrCreateName:(Lscala/actors/OutputChannel;)Lscala/Symbol;
const #308 = Method	#22.#307;	//  scala/actors/remote/NetKernel.getOrCreateName:(Lscala/actors/OutputChannel;)Lscala/Symbol;
const #309 = Asciz	(Lscala/actors/remote/Node;Lscala/Symbol;)V;
const #310 = NameAndType	#37:#309;//  "<init>":(Lscala/actors/remote/Node;Lscala/Symbol;)V
const #311 = Method	#72.#310;	//  scala/actors/remote/Locator."<init>":(Lscala/actors/remote/Node;Lscala/Symbol;)V
const #312 = Asciz	(Lscala/actors/remote/Locator;Lscala/actors/remote/Locator;Lscala/Function2;)V;
const #313 = NameAndType	#37:#312;//  "<init>":(Lscala/actors/remote/Locator;Lscala/actors/remote/Locator;Lscala/Function2;)V
const #314 = Method	#157.#313;	//  scala/actors/remote/RemoteApply0."<init>":(Lscala/actors/remote/Locator;Lscala/actors/remote/Locator;Lscala/Function2;)V
const #315 = Asciz	sendToNode;
const #316 = NameAndType	#315:#155;//  sendToNode:(Lscala/actors/remote/Node;Ljava/lang/Object;)V
const #317 = Method	#22.#316;	//  scala/actors/remote/NetKernel.sendToNode:(Lscala/actors/remote/Node;Ljava/lang/Object;)V
const #318 = Asciz	from;
const #319 = Asciz	(Lscala/actors/remote/Node;Lscala/Symbol;Lscala/actors/OutputChannel<Ljava/lang/Object;>;Lscala/Function2<Lscala/actors/AbstractActor;Lscala/actors/remote/Proxy;Ljava/lang/Object;>;)V;
const #320 = Asciz	forward;
const #321 = Asciz	(Lscala/actors/OutputChannel;Lscala/actors/remote/Node;Lscala/Symbol;Ljava/lang/Object;Lscala/Symbol;)V;
const #322 = Asciz	namedSend;
const #323 = Asciz	(Lscala/actors/remote/Locator;Lscala/actors/remote/Locator;Ljava/lang/Object;Lscala/Symbol;)V;
const #324 = NameAndType	#322:#323;//  namedSend:(Lscala/actors/remote/Locator;Lscala/actors/remote/Locator;Ljava/lang/Object;Lscala/Symbol;)V
const #325 = Method	#22.#324;	//  scala/actors/remote/NetKernel.namedSend:(Lscala/actors/remote/Locator;Lscala/actors/remote/Locator;Ljava/lang/Object;Lscala/Symbol;)V
const #326 = Asciz	(Lscala/actors/OutputChannel<Ljava/lang/Object;>;Lscala/actors/remote/Node;Lscala/Symbol;Ljava/lang/Object;Lscala/Symbol;)V;
const #327 = Asciz	(Lscala/actors/remote/Node;Lscala/Symbol;Ljava/lang/Object;Lscala/Symbol;)V;
const #328 = Asciz	scala/actors/Actor$;
const #329 = class	#328;	//  scala/actors/Actor$
const #330 = Asciz	Lscala/actors/Actor$;;
const #331 = NameAndType	#8:#330;//  MODULE$:Lscala/actors/Actor$;
const #332 = Field	#329.#331;	//  scala/actors/Actor$.MODULE$:Lscala/actors/Actor$;
const #333 = Asciz	self;
const #334 = Asciz	()Lscala/actors/Actor;;
const #335 = NameAndType	#333:#334;//  self:()Lscala/actors/Actor;
const #336 = Method	#329.#335;	//  scala/actors/Actor$.self:()Lscala/actors/Actor;
const #337 = Asciz	(Lscala/actors/remote/Node;Lscala/Symbol;Ljava/lang/Object;)V;
const #338 = NameAndType	#92:#327;//  send:(Lscala/actors/remote/Node;Lscala/Symbol;Ljava/lang/Object;Lscala/Symbol;)V
const #339 = Method	#22.#338;	//  scala/actors/remote/NetKernel.send:(Lscala/actors/remote/Node;Lscala/Symbol;Ljava/lang/Object;Lscala/Symbol;)V
const #340 = NameAndType	#31:#134;//  names:()Lscala/collection/mutable/HashMap;
const #341 = Method	#22.#340;	//  scala/actors/remote/NetKernel.names:()Lscala/collection/mutable/HashMap;
const #342 = Asciz	scala/actors/remote/FreshNameCreator$;
const #343 = class	#342;	//  scala/actors/remote/FreshNameCreator$
const #344 = Asciz	Lscala/actors/remote/FreshNameCreator$;;
const #345 = NameAndType	#8:#344;//  MODULE$:Lscala/actors/remote/FreshNameCreator$;
const #346 = Field	#343.#345;	//  scala/actors/remote/FreshNameCreator$.MODULE$:Lscala/actors/remote/FreshNameCreator$;
const #347 = Asciz	remotesender;
const #348 = String	#347;	//  remotesender
const #349 = Asciz	newName;
const #350 = Asciz	(Ljava/lang/String;)Lscala/Symbol;;
const #351 = NameAndType	#349:#350;//  newName:(Ljava/lang/String;)Lscala/Symbol;
const #352 = Method	#343.#351;	//  scala/actors/remote/FreshNameCreator$.newName:(Ljava/lang/String;)Lscala/Symbol;
const #353 = Asciz	register;
const #354 = Asciz	(Lscala/Symbol;Lscala/actors/OutputChannel;)V;
const #355 = NameAndType	#353:#354;//  register:(Lscala/Symbol;Lscala/actors/OutputChannel;)V
const #356 = Method	#22.#355;	//  scala/actors/remote/NetKernel.register:(Lscala/Symbol;Lscala/actors/OutputChannel;)V
const #357 = Asciz	freshName;
const #358 = Asciz	temp33;
const #359 = Asciz	temp34;
const #360 = Asciz	temp31;
const #361 = Asciz	(Lscala/actors/OutputChannel<Ljava/lang/Object;>;)Lscala/Symbol;;
const #362 = Asciz	a;
const #363 = Asciz	(Lscala/Symbol;Lscala/actors/OutputChannel<Ljava/lang/Object;>;)V;
const #364 = Asciz	()Lscala/collection/mutable/HashMap<Lscala/actors/OutputChannel<Ljava/lang/Object;>;Lscala/Symbol;>;;
const #365 = Asciz	()Lscala/collection/mutable/HashMap<Lscala/Symbol;Lscala/actors/OutputChannel<Ljava/lang/Object;>;>;;
const #366 = Asciz	serialize;
const #367 = Asciz	(Ljava/lang/Object;)[B;
const #368 = NameAndType	#366:#367;//  serialize:(Ljava/lang/Object;)[B
const #369 = Method	#66.#368;	//  scala/actors/remote/Serializer.serialize:(Ljava/lang/Object;)[B
const #370 = Asciz	(Lscala/actors/remote/Locator;Lscala/actors/remote/Locator;[BLscala/Symbol;)V;
const #371 = NameAndType	#37:#370;//  "<init>":(Lscala/actors/remote/Locator;Lscala/actors/remote/Locator;[BLscala/Symbol;)V
const #372 = Method	#215.#371;	//  scala/actors/remote/NamedSend."<init>":(Lscala/actors/remote/Locator;Lscala/actors/remote/Locator;[BLscala/Symbol;)V
const #373 = Asciz	bytes;
const #374 = Asciz	(Lscala/actors/remote/Node;[B)V;
const #375 = NameAndType	#92:#374;//  send:(Lscala/actors/remote/Node;[B)V
const #376 = InterfaceMethod	#60.#375;	//  scala/actors/remote/Service.send:(Lscala/actors/remote/Node;[B)V
const #377 = Asciz	ScalaSig;
const #378 = Asciz	InnerClasses;
const #379 = Asciz	$anonfun$terminate$1;
const #380 = Asciz	scala/ScalaObject;
const #381 = class	#380;	//  scala/ScalaObject

{
public static {};
  Code:
   Stack=2, Locals=0, Args_size=0
   0:	getstatic	#11; //Field scala/Symbol$.MODULE$:Lscala/Symbol$;
   3:	ldc	#14; //String nosession
   5:	invokevirtual	#18; //Method scala/Symbol$.apply:(Ljava/lang/Object;)Ljava/lang/Object;
   8:	checkcast	#20; //class scala/Symbol
   11:	putstatic	#26; //Field symbol$1:Lscala/Symbol;
   14:	return
  LineNumberTable: 
   line 61: 0


public scala.actors.remote.NetKernel(scala.actors.remote.Service);
  Code:
   Stack=3, Locals=2, Args_size=2
   0:	aload_0
   1:	aload_1
   2:	putfield	#40; //Field service:Lscala/actors/remote/Service;
   5:	aload_0
   6:	invokespecial	#44; //Method java/lang/Object."<init>":()V
   9:	aload_0
   10:	new	#46; //class scala/collection/mutable/HashMap
   13:	dup
   14:	invokespecial	#47; //Method scala/collection/mutable/HashMap."<init>":()V
   17:	putfield	#49; //Field actors:Lscala/collection/mutable/HashMap;
   20:	aload_0
   21:	new	#46; //class scala/collection/mutable/HashMap
   24:	dup
   25:	invokespecial	#47; //Method scala/collection/mutable/HashMap."<init>":()V
   28:	putfield	#51; //Field names:Lscala/collection/mutable/HashMap;
   31:	aload_0
   32:	new	#46; //class scala/collection/mutable/HashMap
   35:	dup
   36:	invokespecial	#47; //Method scala/collection/mutable/HashMap."<init>":()V
   39:	putfield	#53; //Field proxies:Lscala/collection/mutable/HashMap;
   42:	return
  LineNumberTable: 
   line 30: 0
   line 43: 9
   line 44: 20
   line 87: 31

  LocalVariableTable: 
   Start  Length  Slot  Name   Signature
   0      43      0    this       Lscala/actors/remote/NetKernel;
   0      43      1    service       Lscala/actors/remote/Service;


public void terminate();
  Code:
   Stack=4, Locals=1, Args_size=1
   0:	aload_0
   1:	invokevirtual	#136; //Method proxies:()Lscala/collection/mutable/HashMap;
   4:	invokevirtual	#140; //Method scala/collection/mutable/HashMap.valuesIterator:()Lscala/collection/Iterator;
   7:	new	#142; //class scala/actors/remote/NetKernel$$anonfun$terminate$1
   10:	dup
   11:	aload_0
   12:	invokespecial	#145; //Method scala/actors/remote/NetKernel$$anonfun$terminate$1."<init>":(Lscala/actors/remote/NetKernel;)V
   15:	invokeinterface	#151,  2; //InterfaceMethod scala/collection/Iterator.foreach:(Lscala/Function1;)V
   20:	aload_0
   21:	getfield	#40; //Field service:Lscala/actors/remote/Service;
   24:	invokeinterface	#153,  1; //InterfaceMethod scala/actors/remote/Service.terminate:()V
   29:	return
  LineNumberTable: 
   line 143: 0
   line 146: 20


public void processMsg(scala.actors.remote.Node, java.lang.Object);
  Code:
   Stack=5, Locals=19, Args_size=3
   0:	aload_0
   1:	dup
   2:	pop
   3:	monitorenter
   4:	aload_2
   5:	instanceof	#157; //class scala/actors/remote/RemoteApply0
   8:	ifeq	257
   11:	aload_2
   12:	checkcast	#157; //class scala/actors/remote/RemoteApply0
   15:	astore_3
   16:	aload_3
   17:	invokevirtual	#161; //Method scala/actors/remote/RemoteApply0.senderLoc:()Lscala/actors/remote/Locator;
   20:	astore	6
   22:	aload_3
   23:	invokevirtual	#164; //Method scala/actors/remote/RemoteApply0.receiverLoc:()Lscala/actors/remote/Locator;
   26:	astore	4
   28:	aload_3
   29:	invokevirtual	#168; //Method scala/actors/remote/RemoteApply0.rfun:()Lscala/Function2;
   32:	astore	8
   34:	iconst_1
   35:	ifeq	245
   38:	getstatic	#100; //Field scala/actors/Debug$.MODULE$:Lscala/actors/Debug$;
   41:	new	#102; //class scala/collection/mutable/StringBuilder
   44:	dup
   45:	invokespecial	#103; //Method scala/collection/mutable/StringBuilder."<init>":()V
   48:	new	#105; //class scala/runtime/StringAdd
   51:	dup
   52:	aload_0
   53:	invokespecial	#108; //Method scala/runtime/StringAdd."<init>":(Ljava/lang/Object;)V
   56:	ldc	#170; //String : processing 
   58:	invokevirtual	#114; //Method scala/runtime/StringAdd.$plus:(Ljava/lang/String;)Ljava/lang/String;
   61:	invokevirtual	#118; //Method scala/collection/mutable/StringBuilder.append:(Ljava/lang/Object;)Lscala/collection/mutable/StringBuilder;
   64:	aload_3
   65:	invokevirtual	#118; //Method scala/collection/mutable/StringBuilder.append:(Ljava/lang/Object;)Lscala/collection/mutable/StringBuilder;
   68:	invokevirtual	#122; //Method scala/collection/mutable/StringBuilder.toString:()Ljava/lang/String;
   71:	invokevirtual	#173; //Method scala/actors/Debug$.info:(Ljava/lang/String;)V
   74:	aload_0
   75:	invokespecial	#175; //Method actors:()Lscala/collection/mutable/HashMap;
   78:	aload	4
   80:	invokevirtual	#80; //Method scala/actors/remote/Locator.name:()Lscala/Symbol;
   83:	invokevirtual	#179; //Method scala/collection/mutable/HashMap.get:(Ljava/lang/Object;)Lscala/Option;
   86:	astore	10
   88:	aload	10
   90:	instanceof	#181; //class scala/Some
   93:	ifeq	169
   96:	aload	10
   98:	checkcast	#181; //class scala/Some
   101:	astore	5
   103:	aload	5
   105:	invokevirtual	#185; //Method scala/Some.x:()Ljava/lang/Object;
   108:	checkcast	#187; //class scala/actors/OutputChannel
   111:	astore	9
   113:	iconst_1
   114:	ifeq	156
   117:	aload_0
   118:	aload	6
   120:	invokevirtual	#76; //Method scala/actors/remote/Locator.node:()Lscala/actors/remote/Node;
   123:	aload	6
   125:	invokevirtual	#80; //Method scala/actors/remote/Locator.name:()Lscala/Symbol;
   128:	invokevirtual	#84; //Method getOrCreateProxy:(Lscala/actors/remote/Node;Lscala/Symbol;)Lscala/actors/remote/Proxy;
   131:	astore	7
   133:	aload	7
   135:	new	#189; //class scala/actors/remote/LocalApply0
   138:	dup
   139:	aload	8
   141:	aload	9
   143:	checkcast	#191; //class scala/actors/AbstractActor
   146:	invokespecial	#194; //Method scala/actors/remote/LocalApply0."<init>":(Lscala/Function2;Lscala/actors/AbstractActor;)V
   149:	aconst_null
   150:	invokevirtual	#95; //Method scala/actors/remote/Proxy.send:(Ljava/lang/Object;Lscala/actors/OutputChannel;)V
   153:	goto	216
   156:	new	#196; //class scala/MatchError
   159:	dup
   160:	aload	10
   162:	invokevirtual	#199; //Method scala/Option.toString:()Ljava/lang/String;
   165:	invokespecial	#201; //Method scala/MatchError."<init>":(Ljava/lang/String;)V
   168:	athrow
   169:	getstatic	#206; //Field scala/None$.MODULE$:Lscala/None$;
   172:	dup
   173:	ifnonnull	185
   176:	pop
   177:	aload	10
   179:	ifnull	193
   182:	goto	232
   185:	aload	10
   187:	invokevirtual	#210; //Method java/lang/Object.equals:(Ljava/lang/Object;)Z
   190:	ifeq	232
   193:	iconst_1
   194:	ifeq	219
   197:	getstatic	#100; //Field scala/actors/Debug$.MODULE$:Lscala/actors/Debug$;
   200:	new	#105; //class scala/runtime/StringAdd
   203:	dup
   204:	aload_0
   205:	invokespecial	#108; //Method scala/runtime/StringAdd."<init>":(Ljava/lang/Object;)V
   208:	ldc	#212; //String : lost message
   210:	invokevirtual	#114; //Method scala/runtime/StringAdd.$plus:(Ljava/lang/String;)Ljava/lang/String;
   213:	invokevirtual	#173; //Method scala/actors/Debug$.info:(Ljava/lang/String;)V
   216:	goto	456
   219:	new	#196; //class scala/MatchError
   222:	dup
   223:	aload	10
   225:	invokevirtual	#199; //Method scala/Option.toString:()Ljava/lang/String;
   228:	invokespecial	#201; //Method scala/MatchError."<init>":(Ljava/lang/String;)V
   231:	athrow
   232:	new	#196; //class scala/MatchError
   235:	dup
   236:	aload	10
   238:	invokevirtual	#199; //Method scala/Option.toString:()Ljava/lang/String;
   241:	invokespecial	#201; //Method scala/MatchError."<init>":(Ljava/lang/String;)V
   244:	athrow
   245:	new	#196; //class scala/MatchError
   248:	dup
   249:	aload_2
   250:	invokevirtual	#213; //Method java/lang/Object.toString:()Ljava/lang/String;
   253:	invokespecial	#201; //Method scala/MatchError."<init>":(Ljava/lang/String;)V
   256:	athrow
   257:	aload_2
   258:	instanceof	#215; //class scala/actors/remote/NamedSend
   261:	ifeq	497
   264:	aload_2
   265:	checkcast	#215; //class scala/actors/remote/NamedSend
   268:	astore	11
   270:	aload	11
   272:	invokevirtual	#216; //Method scala/actors/remote/NamedSend.senderLoc:()Lscala/actors/remote/Locator;
   275:	astore	14
   277:	aload	11
   279:	invokevirtual	#217; //Method scala/actors/remote/NamedSend.receiverLoc:()Lscala/actors/remote/Locator;
   282:	astore	12
   284:	aload	11
   286:	invokevirtual	#221; //Method scala/actors/remote/NamedSend.data:()[B
   289:	astore	15
   291:	aload	11
   293:	invokevirtual	#224; //Method scala/actors/remote/NamedSend.session:()Lscala/Symbol;
   296:	astore	16
   298:	iconst_1
   299:	ifeq	485
   302:	getstatic	#100; //Field scala/actors/Debug$.MODULE$:Lscala/actors/Debug$;
   305:	new	#102; //class scala/collection/mutable/StringBuilder
   308:	dup
   309:	invokespecial	#103; //Method scala/collection/mutable/StringBuilder."<init>":()V
   312:	new	#105; //class scala/runtime/StringAdd
   315:	dup
   316:	aload_0
   317:	invokespecial	#108; //Method scala/runtime/StringAdd."<init>":(Ljava/lang/Object;)V
   320:	ldc	#170; //String : processing 
   322:	invokevirtual	#114; //Method scala/runtime/StringAdd.$plus:(Ljava/lang/String;)Ljava/lang/String;
   325:	invokevirtual	#118; //Method scala/collection/mutable/StringBuilder.append:(Ljava/lang/Object;)Lscala/collection/mutable/StringBuilder;
   328:	aload	11
   330:	invokevirtual	#118; //Method scala/collection/mutable/StringBuilder.append:(Ljava/lang/Object;)Lscala/collection/mutable/StringBuilder;
   333:	invokevirtual	#122; //Method scala/collection/mutable/StringBuilder.toString:()Ljava/lang/String;
   336:	invokevirtual	#173; //Method scala/actors/Debug$.info:(Ljava/lang/String;)V
   339:	aload_0
   340:	invokespecial	#175; //Method actors:()Lscala/collection/mutable/HashMap;
   343:	aload	12
   345:	invokevirtual	#80; //Method scala/actors/remote/Locator.name:()Lscala/Symbol;
   348:	invokevirtual	#179; //Method scala/collection/mutable/HashMap.get:(Ljava/lang/Object;)Lscala/Option;
   351:	astore	18
   353:	aload	18
   355:	instanceof	#181; //class scala/Some
   358:	ifeq	410
   361:	aload	18
   363:	checkcast	#181; //class scala/Some
   366:	astore	13
   368:	aload	13
   370:	invokevirtual	#185; //Method scala/Some.x:()Ljava/lang/Object;
   373:	checkcast	#187; //class scala/actors/OutputChannel
   376:	astore	17
   378:	iconst_1
   379:	ifeq	397
   382:	aload_0
   383:	aload	14
   385:	aload	15
   387:	aload	16
   389:	aload	17
   391:	invokespecial	#226; //Method liftedTree1$1:(Lscala/actors/remote/Locator;[BLscala/Symbol;Lscala/actors/OutputChannel;)V
   394:	goto	456
   397:	new	#196; //class scala/MatchError
   400:	dup
   401:	aload	18
   403:	invokevirtual	#199; //Method scala/Option.toString:()Ljava/lang/String;
   406:	invokespecial	#201; //Method scala/MatchError."<init>":(Ljava/lang/String;)V
   409:	athrow
   410:	getstatic	#206; //Field scala/None$.MODULE$:Lscala/None$;
   413:	dup
   414:	ifnonnull	426
   417:	pop
   418:	aload	18
   420:	ifnull	434
   423:	goto	472
   426:	aload	18
   428:	invokevirtual	#210; //Method java/lang/Object.equals:(Ljava/lang/Object;)Z
   431:	ifeq	472
   434:	iconst_1
   435:	ifeq	459
   438:	getstatic	#100; //Field scala/actors/Debug$.MODULE$:Lscala/actors/Debug$;
   441:	getstatic	#231; //Field scala/Predef$.MODULE$:Lscala/Predef$;
   444:	aload_0
   445:	invokevirtual	#235; //Method scala/Predef$.any2stringadd:(Ljava/lang/Object;)Lscala/runtime/StringAdd;
   448:	ldc	#212; //String : lost message
   450:	invokevirtual	#114; //Method scala/runtime/StringAdd.$plus:(Ljava/lang/String;)Ljava/lang/String;
   453:	invokevirtual	#173; //Method scala/actors/Debug$.info:(Ljava/lang/String;)V
   456:	aload_0
   457:	monitorexit
   458:	return
   459:	new	#196; //class scala/MatchError
   462:	dup
   463:	aload	18
   465:	invokevirtual	#199; //Method scala/Option.toString:()Ljava/lang/String;
   468:	invokespecial	#201; //Method scala/MatchError."<init>":(Ljava/lang/String;)V
   471:	athrow
   472:	new	#196; //class scala/MatchError
   475:	dup
   476:	aload	18
   478:	invokevirtual	#199; //Method scala/Option.toString:()Ljava/lang/String;
   481:	invokespecial	#201; //Method scala/MatchError."<init>":(Ljava/lang/String;)V
   484:	athrow
   485:	new	#196; //class scala/MatchError
   488:	dup
   489:	aload_2
   490:	invokevirtual	#213; //Method java/lang/Object.toString:()Ljava/lang/String;
   493:	invokespecial	#201; //Method scala/MatchError."<init>":(Ljava/lang/String;)V
   496:	athrow
   497:	new	#196; //class scala/MatchError
   500:	dup
   501:	aload_2
   502:	invokevirtual	#213; //Method java/lang/Object.toString:()Ljava/lang/String;
   505:	invokespecial	#201; //Method scala/MatchError."<init>":(Ljava/lang/String;)V
   508:	athrow
   509:	aload_0
   510:	monitorexit
   511:	athrow
  Exception table:
   from   to  target type
     4   458   509   Class java/lang/Throwable

   459   509   509   Class java/lang/Throwable

  LineNumberTable: 
   line 107: 0
   line 108: 4
   line 107: 11
   line 644: 34
   line 110: 38
   line 111: 74
   line 107: 96
   line 644: 113
   line 113: 117
   line 114: 133
   line 111: 156
   line 644: 193
   line 118: 197
   line 109: 216
   line 111: 219
   line 108: 245
   line 107: 264
   line 644: 298
   line 122: 302
   line 123: 339
   line 107: 361
   line 644: 378
   line 125: 382
   line 123: 397
   line 644: 434
   line 136: 438
   line 108: 456
   line 107: 457
   line 123: 459
   line 108: 485
   line 107: 510

  LocalVariableTable: 
   Start  Length  Slot  Name   Signature
   0      512      0    this       Lscala/actors/remote/NetKernel;
   0      512      1    senderNode       Lscala/actors/remote/Node;
   0      512      2    msg       Ljava/lang/Object;
   16      241      3    temp52       Lscala/actors/remote/RemoteApply0;
   28      229      4    temp54       Lscala/actors/remote/Locator;
   103      66      5    temp44       Lscala/Some;
   22      235      6    temp53       Lscala/actors/remote/Locator;
   133      20      7    senderProxy       Lscala/actors/remote/Proxy;
   34      223      8    temp55       Lscala/Function2;
   113      56      9    temp45       Lscala/actors/OutputChannel;
   88      157      10    temp43       Lscala/Option;
   270      186      11    temp56       Lscala/actors/remote/NamedSend;
   459      38      11    temp56       Lscala/actors/remote/NamedSend;
   284      172      12    temp58       Lscala/actors/remote/Locator;
   459      38      12    temp58       Lscala/actors/remote/Locator;
   368      42      13    temp48       Lscala/Some;
   277      179      14    temp57       Lscala/actors/remote/Locator;
   459      38      14    temp57       Lscala/actors/remote/Locator;
   291      165      15    temp59       [B
   459      38      15    temp59       [B
   298      158      16    temp60       Lscala/Symbol;
   459      38      16    temp60       Lscala/Symbol;
   378      32      17    temp49       Lscala/actors/OutputChannel;
   353      103      18    temp47       Lscala/Option;
   459      26      18    temp47       Lscala/Option;


public void registerProxy(scala.actors.remote.Node, scala.Symbol, scala.actors.remote.Proxy);
  Code:
   Stack=6, Locals=6, Args_size=4
   0:	aload_0
   1:	invokevirtual	#136; //Method proxies:()Lscala/collection/mutable/HashMap;
   4:	dup
   5:	astore	5
   7:	monitorenter
   8:	aload_0
   9:	invokevirtual	#136; //Method proxies:()Lscala/collection/mutable/HashMap;
   12:	new	#266; //class scala/Tuple2
   15:	dup
   16:	aload_1
   17:	aload_2
   18:	invokespecial	#269; //Method scala/Tuple2."<init>":(Ljava/lang/Object;Ljava/lang/Object;)V
   21:	invokevirtual	#179; //Method scala/collection/mutable/HashMap.get:(Ljava/lang/Object;)Lscala/Option;
   24:	astore	4
   26:	aload	4
   28:	instanceof	#181; //class scala/Some
   31:	ifeq	57
   34:	iconst_1
   35:	ifeq	44
   38:	getstatic	#275; //Field scala/runtime/BoxedUnit.UNIT:Lscala/runtime/BoxedUnit;
   41:	goto	108
   44:	new	#196; //class scala/MatchError
   47:	dup
   48:	aload	4
   50:	invokevirtual	#199; //Method scala/Option.toString:()Ljava/lang/String;
   53:	invokespecial	#201; //Method scala/MatchError."<init>":(Ljava/lang/String;)V
   56:	athrow
   57:	getstatic	#206; //Field scala/None$.MODULE$:Lscala/None$;
   60:	dup
   61:	ifnonnull	73
   64:	pop
   65:	aload	4
   67:	ifnull	81
   70:	goto	126
   73:	aload	4
   75:	invokevirtual	#210; //Method java/lang/Object.equals:(Ljava/lang/Object;)Z
   78:	ifeq	126
   81:	iconst_1
   82:	ifeq	113
   85:	aload_0
   86:	invokevirtual	#136; //Method proxies:()Lscala/collection/mutable/HashMap;
   89:	getstatic	#280; //Field scala/Predef$Pair$.MODULE$:Lscala/Predef$Pair$;
   92:	new	#266; //class scala/Tuple2
   95:	dup
   96:	aload_1
   97:	aload_2
   98:	invokespecial	#269; //Method scala/Tuple2."<init>":(Ljava/lang/Object;Ljava/lang/Object;)V
   101:	aload_3
   102:	invokevirtual	#283; //Method scala/Predef$Pair$.apply:(Ljava/lang/Object;Ljava/lang/Object;)Lscala/Tuple2;
   105:	invokevirtual	#287; //Method scala/collection/mutable/HashMap.$plus$eq:(Lscala/Tuple2;)Lscala/collection/mutable/HashMap;
   108:	pop
   109:	aload	5
   111:	monitorexit
   112:	return
   113:	new	#196; //class scala/MatchError
   116:	dup
   117:	aload	4
   119:	invokevirtual	#199; //Method scala/Option.toString:()Ljava/lang/String;
   122:	invokespecial	#201; //Method scala/MatchError."<init>":(Ljava/lang/String;)V
   125:	athrow
   126:	new	#196; //class scala/MatchError
   129:	dup
   130:	aload	4
   132:	invokevirtual	#199; //Method scala/Option.toString:()Ljava/lang/String;
   135:	invokespecial	#201; //Method scala/MatchError."<init>":(Ljava/lang/String;)V
   138:	athrow
   139:	aload	5
   141:	monitorexit
   142:	athrow
  Exception table:
   from   to  target type
     8   112   139   Class java/lang/Throwable

   113   139   139   Class java/lang/Throwable

  LineNumberTable: 
   line 100: 0
   line 101: 8
   line 644: 34
   line 102: 38
   line 101: 44
   line 644: 81
   line 103: 85
   line 101: 108
   line 100: 111
   line 101: 113
   line 100: 141

  LocalVariableTable: 
   Start  Length  Slot  Name   Signature
   0      143      0    this       Lscala/actors/remote/NetKernel;
   0      143      1    senderNode       Lscala/actors/remote/Node;
   0      143      2    senderName       Lscala/Symbol;
   0      143      3    p       Lscala/actors/remote/Proxy;
   26      83      4    temp39       Lscala/Option;
   113      26      4    temp39       Lscala/Option;


public scala.actors.remote.Proxy getOrCreateProxy(scala.actors.remote.Node, scala.Symbol);
  Code:
   Stack=5, Locals=7, Args_size=3
   0:	aload_0
   1:	invokevirtual	#136; //Method proxies:()Lscala/collection/mutable/HashMap;
   4:	dup
   5:	astore	6
   7:	monitorenter
   8:	aload_0
   9:	invokevirtual	#136; //Method proxies:()Lscala/collection/mutable/HashMap;
   12:	new	#266; //class scala/Tuple2
   15:	dup
   16:	aload_1
   17:	aload_2
   18:	invokespecial	#269; //Method scala/Tuple2."<init>":(Ljava/lang/Object;Ljava/lang/Object;)V
   21:	invokevirtual	#179; //Method scala/collection/mutable/HashMap.get:(Ljava/lang/Object;)Lscala/Option;
   24:	astore	5
   26:	aload	5
   28:	instanceof	#181; //class scala/Some
   31:	ifeq	71
   34:	aload	5
   36:	checkcast	#181; //class scala/Some
   39:	astore_3
   40:	aload_3
   41:	invokevirtual	#185; //Method scala/Some.x:()Ljava/lang/Object;
   44:	checkcast	#91; //class scala/actors/remote/Proxy
   47:	astore	4
   49:	iconst_1
   50:	ifeq	58
   53:	aload	4
   55:	goto	105
   58:	new	#196; //class scala/MatchError
   61:	dup
   62:	aload	5
   64:	invokevirtual	#199; //Method scala/Option.toString:()Ljava/lang/String;
   67:	invokespecial	#201; //Method scala/MatchError."<init>":(Ljava/lang/String;)V
   70:	athrow
   71:	getstatic	#206; //Field scala/None$.MODULE$:Lscala/None$;
   74:	dup
   75:	ifnonnull	87
   78:	pop
   79:	aload	5
   81:	ifnull	95
   84:	goto	125
   87:	aload	5
   89:	invokevirtual	#210; //Method java/lang/Object.equals:(Ljava/lang/Object;)Z
   92:	ifeq	125
   95:	iconst_1
   96:	ifeq	112
   99:	aload_0
   100:	aload_1
   101:	aload_2
   102:	invokevirtual	#293; //Method createProxy:(Lscala/actors/remote/Node;Lscala/Symbol;)Lscala/actors/remote/Proxy;
   105:	aload	6
   107:	monitorexit
   108:	checkcast	#91; //class scala/actors/remote/Proxy
   111:	areturn
   112:	new	#196; //class scala/MatchError
   115:	dup
   116:	aload	5
   118:	invokevirtual	#199; //Method scala/Option.toString:()Ljava/lang/String;
   121:	invokespecial	#201; //Method scala/MatchError."<init>":(Ljava/lang/String;)V
   124:	athrow
   125:	new	#196; //class scala/MatchError
   128:	dup
   129:	aload	5
   131:	invokevirtual	#199; //Method scala/Option.toString:()Ljava/lang/String;
   134:	invokespecial	#201; //Method scala/MatchError."<init>":(Ljava/lang/String;)V
   137:	athrow
   138:	aload	6
   140:	monitorexit
   141:	athrow
  Exception table:
   from   to  target type
     8   108   138   Class java/lang/Throwable

   112   138   138   Class java/lang/Throwable

  LineNumberTable: 
   line 90: 0
   line 91: 8
   line 89: 34
   line 644: 49
   line 92: 53
   line 91: 58
   line 644: 95
   line 93: 99
   line 91: 105
   line 90: 107
   line 91: 108
   line 90: 140

  LocalVariableTable: 
   Start  Length  Slot  Name   Signature
   0      142      0    this       Lscala/actors/remote/NetKernel;
   0      142      1    senderNode       Lscala/actors/remote/Node;
   0      142      2    senderName       Lscala/Symbol;
   40      31      3    temp36       Lscala/Some;
   49      22      4    temp37       Lscala/actors/remote/Proxy;
   26      82      5    temp35       Lscala/Option;
   112      26      5    temp35       Lscala/Option;


public scala.collection.mutable.HashMap proxies();
  Code:
   Stack=1, Locals=1, Args_size=1
   0:	aload_0
   1:	getfield	#53; //Field proxies:Lscala/collection/mutable/HashMap;
   4:	areturn
  LineNumberTable: 
   line 87: 0

  Signature: length = 0x2
   01 29 

public scala.actors.remote.Proxy createProxy(scala.actors.remote.Node, scala.Symbol);
  Code:
   Stack=6, Locals=4, Args_size=3
   0:	new	#91; //class scala/actors/remote/Proxy
   3:	dup
   4:	aload_1
   5:	aload_2
   6:	aload_0
   7:	invokespecial	#300; //Method scala/actors/remote/Proxy."<init>":(Lscala/actors/remote/Node;Lscala/Symbol;Lscala/actors/remote/NetKernel;)V
   10:	astore_3
   11:	aload_0
   12:	invokevirtual	#136; //Method proxies:()Lscala/collection/mutable/HashMap;
   15:	getstatic	#280; //Field scala/Predef$Pair$.MODULE$:Lscala/Predef$Pair$;
   18:	new	#266; //class scala/Tuple2
   21:	dup
   22:	aload_1
   23:	aload_2
   24:	invokespecial	#269; //Method scala/Tuple2."<init>":(Ljava/lang/Object;Ljava/lang/Object;)V
   27:	aload_3
   28:	invokevirtual	#283; //Method scala/Predef$Pair$.apply:(Ljava/lang/Object;Ljava/lang/Object;)Lscala/Tuple2;
   31:	invokevirtual	#287; //Method scala/collection/mutable/HashMap.$plus$eq:(Lscala/Tuple2;)Lscala/collection/mutable/HashMap;
   34:	pop
   35:	aload_3
   36:	areturn
  LineNumberTable: 
   line 82: 0
   line 83: 11
   line 84: 27
   line 83: 28
   line 84: 35

  LocalVariableTable: 
   Start  Length  Slot  Name   Signature
   0      37      0    this       Lscala/actors/remote/NetKernel;
   0      37      1    node       Lscala/actors/remote/Node;
   0      37      2    sym       Lscala/Symbol;
   11      25      3    p       Lscala/actors/remote/Proxy;


public void remoteApply(scala.actors.remote.Node, scala.Symbol, scala.actors.OutputChannel, scala.Function2);
  Code:
   Stack=7, Locals=7, Args_size=5
   0:	new	#72; //class scala/actors/remote/Locator
   3:	dup
   4:	aload_0
   5:	getfield	#40; //Field service:Lscala/actors/remote/Service;
   8:	invokeinterface	#304,  1; //InterfaceMethod scala/actors/remote/Service.node:()Lscala/actors/remote/Node;
   13:	aload_0
   14:	aload_3
   15:	invokevirtual	#308; //Method getOrCreateName:(Lscala/actors/OutputChannel;)Lscala/Symbol;
   18:	invokespecial	#311; //Method scala/actors/remote/Locator."<init>":(Lscala/actors/remote/Node;Lscala/Symbol;)V
   21:	astore	5
   23:	new	#72; //class scala/actors/remote/Locator
   26:	dup
   27:	aload_1
   28:	aload_2
   29:	invokespecial	#311; //Method scala/actors/remote/Locator."<init>":(Lscala/actors/remote/Node;Lscala/Symbol;)V
   32:	astore	6
   34:	aload_0
   35:	aload	6
   37:	invokevirtual	#76; //Method scala/actors/remote/Locator.node:()Lscala/actors/remote/Node;
   40:	new	#157; //class scala/actors/remote/RemoteApply0
   43:	dup
   44:	aload	5
   46:	aload	6
   48:	aload	4
   50:	invokespecial	#314; //Method scala/actors/remote/RemoteApply0."<init>":(Lscala/actors/remote/Locator;Lscala/actors/remote/Locator;Lscala/Function2;)V
   53:	invokevirtual	#317; //Method sendToNode:(Lscala/actors/remote/Node;Ljava/lang/Object;)V
   56:	return
  LineNumberTable: 
   line 76: 0
   line 77: 23
   line 78: 34

  LocalVariableTable: 
   Start  Length  Slot  Name   Signature
   0      57      0    this       Lscala/actors/remote/NetKernel;
   0      57      1    node       Lscala/actors/remote/Node;
   0      57      2    name       Lscala/Symbol;
   0      57      3    from       Lscala/actors/OutputChannel;
   0      57      4    rfun       Lscala/Function2;
   23      33      5    senderLoc       Lscala/actors/remote/Locator;
   34      22      6    receiverLoc       Lscala/actors/remote/Locator;

  Signature: length = 0x2
   01 3F 

public void forward(scala.actors.OutputChannel, scala.actors.remote.Node, scala.Symbol, java.lang.Object, scala.Symbol);
  Code:
   Stack=5, Locals=8, Args_size=6
   0:	new	#72; //class scala/actors/remote/Locator
   3:	dup
   4:	aload_0
   5:	getfield	#40; //Field service:Lscala/actors/remote/Service;
   8:	invokeinterface	#304,  1; //InterfaceMethod scala/actors/remote/Service.node:()Lscala/actors/remote/Node;
   13:	aload_0
   14:	aload_1
   15:	invokevirtual	#308; //Method getOrCreateName:(Lscala/actors/OutputChannel;)Lscala/Symbol;
   18:	invokespecial	#311; //Method scala/actors/remote/Locator."<init>":(Lscala/actors/remote/Node;Lscala/Symbol;)V
   21:	astore	6
   23:	new	#72; //class scala/actors/remote/Locator
   26:	dup
   27:	aload_2
   28:	aload_3
   29:	invokespecial	#311; //Method scala/actors/remote/Locator."<init>":(Lscala/actors/remote/Node;Lscala/Symbol;)V
   32:	astore	7
   34:	aload_0
   35:	aload	6
   37:	aload	7
   39:	aload	4
   41:	aload	5
   43:	invokevirtual	#325; //Method namedSend:(Lscala/actors/remote/Locator;Lscala/actors/remote/Locator;Ljava/lang/Object;Lscala/Symbol;)V
   46:	return
  LineNumberTable: 
   line 70: 0
   line 71: 23
   line 72: 34

  LocalVariableTable: 
   Start  Length  Slot  Name   Signature
   0      47      0    this       Lscala/actors/remote/NetKernel;
   0      47      1    from       Lscala/actors/OutputChannel;
   0      47      2    node       Lscala/actors/remote/Node;
   0      47      3    name       Lscala/Symbol;
   0      47      4    msg       Ljava/lang/Object;
   0      47      5    session       Lscala/Symbol;
   23      23      6    senderLoc       Lscala/actors/remote/Locator;
   34      12      7    receiverLoc       Lscala/actors/remote/Locator;

  Signature: length = 0x2
   01 46 

public void send(scala.actors.remote.Node, scala.Symbol, java.lang.Object, scala.Symbol);
  Code:
   Stack=5, Locals=7, Args_size=5
   0:	new	#72; //class scala/actors/remote/Locator
   3:	dup
   4:	aload_0
   5:	getfield	#40; //Field service:Lscala/actors/remote/Service;
   8:	invokeinterface	#304,  1; //InterfaceMethod scala/actors/remote/Service.node:()Lscala/actors/remote/Node;
   13:	aload_0
   14:	getstatic	#332; //Field scala/actors/Actor$.MODULE$:Lscala/actors/Actor$;
   17:	invokevirtual	#336; //Method scala/actors/Actor$.self:()Lscala/actors/Actor;
   20:	invokevirtual	#308; //Method getOrCreateName:(Lscala/actors/OutputChannel;)Lscala/Symbol;
   23:	invokespecial	#311; //Method scala/actors/remote/Locator."<init>":(Lscala/actors/remote/Node;Lscala/Symbol;)V
   26:	astore	5
   28:	new	#72; //class scala/actors/remote/Locator
   31:	dup
   32:	aload_1
   33:	aload_2
   34:	invokespecial	#311; //Method scala/actors/remote/Locator."<init>":(Lscala/actors/remote/Node;Lscala/Symbol;)V
   37:	astore	6
   39:	aload_0
   40:	aload	5
   42:	aload	6
   44:	aload_3
   45:	aload	4
   47:	invokevirtual	#325; //Method namedSend:(Lscala/actors/remote/Locator;Lscala/actors/remote/Locator;Ljava/lang/Object;Lscala/Symbol;)V
   50:	return
  LineNumberTable: 
   line 64: 0
   line 65: 28
   line 66: 39

  LocalVariableTable: 
   Start  Length  Slot  Name   Signature
   0      51      0    this       Lscala/actors/remote/NetKernel;
   0      51      1    node       Lscala/actors/remote/Node;
   0      51      2    name       Lscala/Symbol;
   0      51      3    msg       Ljava/lang/Object;
   0      51      4    session       Lscala/Symbol;
   28      22      5    senderLoc       Lscala/actors/remote/Locator;
   39      11      6    receiverLoc       Lscala/actors/remote/Locator;


public void send(scala.actors.remote.Node, scala.Symbol, java.lang.Object);
  Code:
   Stack=5, Locals=4, Args_size=4
   0:	aload_0
   1:	aload_1
   2:	aload_2
   3:	aload_3
   4:	getstatic	#26; //Field symbol$1:Lscala/Symbol;
   7:	checkcast	#20; //class scala/Symbol
   10:	invokevirtual	#339; //Method send:(Lscala/actors/remote/Node;Lscala/Symbol;Ljava/lang/Object;Lscala/Symbol;)V
   13:	return
  LineNumberTable: 
   line 61: 0

  LocalVariableTable: 
   Start  Length  Slot  Name   Signature
   0      14      0    this       Lscala/actors/remote/NetKernel;
   0      14      1    node       Lscala/actors/remote/Node;
   0      14      2    name       Lscala/Symbol;
   0      14      3    msg       Ljava/lang/Object;


public scala.Symbol getOrCreateName(scala.actors.OutputChannel);
  Code:
   Stack=3, Locals=6, Args_size=2
   0:	aload_0
   1:	invokespecial	#341; //Method names:()Lscala/collection/mutable/HashMap;
   4:	aload_1
   5:	invokevirtual	#179; //Method scala/collection/mutable/HashMap.get:(Ljava/lang/Object;)Lscala/Option;
   8:	astore	5
   10:	getstatic	#206; //Field scala/None$.MODULE$:Lscala/None$;
   13:	dup
   14:	ifnonnull	26
   17:	pop
   18:	aload	5
   20:	ifnull	34
   23:	goto	71
   26:	aload	5
   28:	invokevirtual	#210; //Method java/lang/Object.equals:(Ljava/lang/Object;)Z
   31:	ifeq	71
   34:	iconst_1
   35:	ifeq	58
   38:	getstatic	#346; //Field scala/actors/remote/FreshNameCreator$.MODULE$:Lscala/actors/remote/FreshNameCreator$;
   41:	ldc_w	#348; //String remotesender
   44:	invokevirtual	#352; //Method scala/actors/remote/FreshNameCreator$.newName:(Ljava/lang/String;)Lscala/Symbol;
   47:	astore_2
   48:	aload_0
   49:	aload_2
   50:	aload_1
   51:	invokevirtual	#356; //Method register:(Lscala/Symbol;Lscala/actors/OutputChannel;)V
   54:	aload_2
   55:	goto	100
   58:	new	#196; //class scala/MatchError
   61:	dup
   62:	aload	5
   64:	invokevirtual	#199; //Method scala/Option.toString:()Ljava/lang/String;
   67:	invokespecial	#201; //Method scala/MatchError."<init>":(Ljava/lang/String;)V
   70:	athrow
   71:	aload	5
   73:	instanceof	#181; //class scala/Some
   76:	ifeq	114
   79:	aload	5
   81:	checkcast	#181; //class scala/Some
   84:	astore_3
   85:	aload_3
   86:	invokevirtual	#185; //Method scala/Some.x:()Ljava/lang/Object;
   89:	checkcast	#20; //class scala/Symbol
   92:	astore	4
   94:	iconst_1
   95:	ifeq	101
   98:	aload	4
   100:	areturn
   101:	new	#196; //class scala/MatchError
   104:	dup
   105:	aload	5
   107:	invokevirtual	#199; //Method scala/Option.toString:()Ljava/lang/String;
   110:	invokespecial	#201; //Method scala/MatchError."<init>":(Ljava/lang/String;)V
   113:	athrow
   114:	new	#196; //class scala/MatchError
   117:	dup
   118:	aload	5
   120:	invokevirtual	#199; //Method scala/Option.toString:()Ljava/lang/String;
   123:	invokespecial	#201; //Method scala/MatchError."<init>":(Ljava/lang/String;)V
   126:	athrow
  LineNumberTable: 
   line 51: 0
   line 644: 34
   line 53: 38
   line 54: 48
   line 55: 54
   line 51: 58
   line 644: 94
   line 57: 98
   line 51: 100

  LocalVariableTable: 
   Start  Length  Slot  Name   Signature
   0      127      0    this       Lscala/actors/remote/NetKernel;
   0      127      1    from       Lscala/actors/OutputChannel;
   48      7      2    freshName       Lscala/Symbol;
   85      15      3    temp33       Lscala/Some;
   101      13      3    temp33       Lscala/Some;
   94      6      4    temp34       Lscala/Symbol;
   101      13      4    temp34       Lscala/Symbol;
   10      117      5    temp31       Lscala/Option;

  Signature: length = 0x2
   01 69 

public void register(scala.Symbol, scala.actors.OutputChannel);
  Code:
   Stack=4, Locals=3, Args_size=3
   0:	aload_0
   1:	dup
   2:	pop
   3:	monitorenter
   4:	aload_0
   5:	invokespecial	#175; //Method actors:()Lscala/collection/mutable/HashMap;
   8:	getstatic	#280; //Field scala/Predef$Pair$.MODULE$:Lscala/Predef$Pair$;
   11:	aload_1
   12:	aload_2
   13:	invokevirtual	#283; //Method scala/Predef$Pair$.apply:(Ljava/lang/Object;Ljava/lang/Object;)Lscala/Tuple2;
   16:	invokevirtual	#287; //Method scala/collection/mutable/HashMap.$plus$eq:(Lscala/Tuple2;)Lscala/collection/mutable/HashMap;
   19:	pop
   20:	aload_0
   21:	invokespecial	#341; //Method names:()Lscala/collection/mutable/HashMap;
   24:	getstatic	#280; //Field scala/Predef$Pair$.MODULE$:Lscala/Predef$Pair$;
   27:	aload_2
   28:	aload_1
   29:	invokevirtual	#283; //Method scala/Predef$Pair$.apply:(Ljava/lang/Object;Ljava/lang/Object;)Lscala/Tuple2;
   32:	invokevirtual	#287; //Method scala/collection/mutable/HashMap.$plus$eq:(Lscala/Tuple2;)Lscala/collection/mutable/HashMap;
   35:	pop
   36:	aload_0
   37:	monitorexit
   38:	return
   39:	aload_0
   40:	monitorexit
   41:	athrow
  Exception table:
   from   to  target type
     4    38    39   Class java/lang/Throwable

  LineNumberTable: 
   line 46: 0
   line 47: 4
   line 48: 20
   line 46: 37

  LocalVariableTable: 
   Start  Length  Slot  Name   Signature
   0      42      0    this       Lscala/actors/remote/NetKernel;
   0      42      1    name       Lscala/Symbol;
   0      42      2    a       Lscala/actors/OutputChannel;

  Signature: length = 0x2
   01 6B 

public void namedSend(scala.actors.remote.Locator, scala.actors.remote.Locator, java.lang.Object, scala.Symbol);
  Code:
   Stack=8, Locals=6, Args_size=5
   0:	aload_0
   1:	getfield	#40; //Field service:Lscala/actors/remote/Service;
   4:	invokeinterface	#64,  1; //InterfaceMethod scala/actors/remote/Service.serializer:()Lscala/actors/remote/Serializer;
   9:	aload_3
   10:	invokevirtual	#369; //Method scala/actors/remote/Serializer.serialize:(Ljava/lang/Object;)[B
   13:	astore	5
   15:	aload_0
   16:	aload_2
   17:	invokevirtual	#76; //Method scala/actors/remote/Locator.node:()Lscala/actors/remote/Node;
   20:	new	#215; //class scala/actors/remote/NamedSend
   23:	dup
   24:	aload_1
   25:	aload_2
   26:	aload	5
   28:	aload	4
   30:	invokespecial	#372; //Method scala/actors/remote/NamedSend."<init>":(Lscala/actors/remote/Locator;Lscala/actors/remote/Locator;[BLscala/Symbol;)V
   33:	invokevirtual	#317; //Method sendToNode:(Lscala/actors/remote/Node;Ljava/lang/Object;)V
   36:	return
  LineNumberTable: 
   line 39: 0
   line 40: 15

  LocalVariableTable: 
   Start  Length  Slot  Name   Signature
   0      37      0    this       Lscala/actors/remote/NetKernel;
   0      37      1    senderLoc       Lscala/actors/remote/Locator;
   0      37      2    receiverLoc       Lscala/actors/remote/Locator;
   0      37      3    msg       Ljava/lang/Object;
   0      37      4    session       Lscala/Symbol;
   15      21      5    bytes       [B


public void sendToNode(scala.actors.remote.Node, java.lang.Object);
  Code:
   Stack=3, Locals=4, Args_size=3
   0:	aload_0
   1:	getfield	#40; //Field service:Lscala/actors/remote/Service;
   4:	invokeinterface	#64,  1; //InterfaceMethod scala/actors/remote/Service.serializer:()Lscala/actors/remote/Serializer;
   9:	aload_2
   10:	invokevirtual	#369; //Method scala/actors/remote/Serializer.serialize:(Ljava/lang/Object;)[B
   13:	astore_3
   14:	aload_0
   15:	getfield	#40; //Field service:Lscala/actors/remote/Service;
   18:	aload_1
   19:	aload_3
   20:	invokeinterface	#376,  3; //InterfaceMethod scala/actors/remote/Service.send:(Lscala/actors/remote/Node;[B)V
   25:	return
  LineNumberTable: 
   line 33: 0
   line 34: 14

  LocalVariableTable: 
   Start  Length  Slot  Name   Signature
   0      26      0    this       Lscala/actors/remote/NetKernel;
   0      26      1    node       Lscala/actors/remote/Node;
   0      26      2    msg       Ljava/lang/Object;
   14      11      3    bytes       [B


}

