Compiled from "NetKernel.scala"
public class scala.actors.remote.NetKernel extends java.lang.Object implements scala.ScalaObject
  SourceFile: "NetKernel.scala"
  ScalaSig: length = 0x4EF
   05 00 FFFFFF81 30 06 09 01 02 FFFFFF84 FFFFFF80 FFFFFF80 FFFFFF80 00 02 08 02
   09 4E 65 74 4B 65 72 6E 65 6C 0A 02 03 04 01 06
   72 65 6D 6F 74 65 0A 02 05 06 01 06 61 63 74 6F
   72 73 0A 01 07 01 05 73 63 61 6C 61 13 03 00 09
   11 10 02 0A 0F 0D 01 0B 0A 02 0C 0D 01 04 6C 61
   6E 67 0A 01 0E 01 04 6A 61 76 61 09 02 10 0B 02
   06 4F 62 6A 65 63 74 10 02 12 13 0D 01 06 09 02
   14 06 02 0B 53 63 61 6C 61 4F 62 6A 65 63 74 08
   08 16 00 FFFFFF82 FFFFFF80 FFFFFFA0 FFFFFF80 04 18 01 07 73 65 72 76 69
   63 65 03 00 10 02 19 1A 0D 01 02 09 02 1B 02 02
   07 53 65 72 76 69 63 65 08 05 1D 00 FFFFFF84 00 1E 01
   06 3C 69 6E 69 74 3E 14 02 1F 20 10 02 19 00 08
   05 16 1C FFFFFFC0 00 18 08 05 22 00 FFFFFF84 00 23 01 0A 73
   65 6E 64 54 6F 4E 6F 64 65 14 03 24 27 2C 10 02
   12 25 09 02 26 06 02 04 55 6E 69 74 08 05 28 21
   FFFFFFC0 00 29 01 04 6E 6F 64 65 10 02 19 2A 09 02 2B
   02 02 04 4E 6F 64 65 08 05 2D 21 FFFFFFC0 00 2E 01 03
   6D 73 67 10 02 12 2F 09 02 30 06 02 06 41 6E 79
   52 65 66 08 05 32 00 FFFFFF84 00 33 01 09 6E 61 6D 65
   64 53 65 6E 64 14 05 24 34 39 3B 3C 08 05 35 31
   FFFFFFC0 00 36 01 09 73 65 6E 64 65 72 4C 6F 63 10 02
   19 37 09 02 38 02 02 07 4C 6F 63 61 74 6F 72 08
   05 3A 31 FFFFFFC0 00 36 01 0B 72 65 63 65 69 76 65 72
   4C 6F 63 08 05 2D 31 FFFFFFC0 00 2E 08 05 3D 31 FFFFFFC0 00
   3E 01 07 73 65 73 73 69 6F 6E 10 02 12 3F 09 02
   40 06 02 06 53 79 6D 62 6F 6C 08 07 05 00 FFFFFFC2 FFFFFF80
   FFFFFF84 04 42 15 01 43 10 04 44 49 3E 4B 0D 01 45 0A
   02 46 47 01 07 6D 75 74 61 62 6C 65 0A 02 48 06
   01 0A 63 6F 6C 6C 65 63 74 69 6F 6E 09 02 4A 45
   02 07 48 61 73 68 4D 61 70 10 03 4C 4D 4F 0D 01
   04 09 02 4E 04 02 0D 4F 75 74 70 75 74 43 68 61
   6E 6E 65 6C 10 02 12 50 09 02 51 06 02 03 41 6E
   79 08 06 53 00 FFFFFFA0 FFFFFF80 04 43 01 07 61 63 74 6F 72
   73 20 08 07 55 00 FFFFFFC2 FFFFFF80 FFFFFF84 04 56 01 05 6E 61 6D
   65 73 15 01 57 10 04 44 49 4B 3E 08 06 59 00 FFFFFFA0
   FFFFFF80 04 57 01 06 6E 61 6D 65 73 20 08 05 5B 00 FFFFFF84
   00 5C 01 08 72 65 67 69 73 74 65 72 14 03 24 5D
   5F 08 05 5E 5A FFFFFFC0 00 3E 01 04 6E 61 6D 65 08 05
   60 5A FFFFFFC0 00 4B 01 01 61 08 05 62 00 FFFFFF84 00 63 01
   0F 67 65 74 4F 72 43 72 65 61 74 65 4E 61 6D 65
   14 02 3E 64 08 05 65 61 FFFFFFC0 00 4B 01 04 66 72 6F
   6D 08 05 67 00 FFFFFF84 00 68 01 04 73 65 6E 64 14 04
   24 69 6A 6B 08 05 28 66 FFFFFFC0 00 29 08 05 5E 66 FFFFFFC0
   00 3E 08 05 2D 66 FFFFFFC0 00 2E 08 05 67 00 FFFFFF84 00 6D
   14 05 24 6E 6F 70 71 08 05 28 6C FFFFFFC0 00 29 08 05
   5E 6C FFFFFFC0 00 3E 08 05 2D 6C FFFFFFC0 00 2E 08 05 3D 6C
   FFFFFFC0 00 3E 08 05 73 00 FFFFFF84 00 74 01 07 66 6F 72 77
   61 72 64 14 06 24 75 76 77 78 79 08 05 65 72 FFFFFFC0
   00 4B 08 05 28 72 FFFFFFC0 00 29 08 05 5E 72 FFFFFFC0 00 3E
   08 05 2D 72 FFFFFFC0 00 2E 08 05 3D 72 FFFFFFC0 00 3E 08 05
   7B 00 FFFFFF84 00 7C 01 0B 72 65 6D 6F 74 65 41 70 70
   6C 79 14 06 24 7D 7E 7F FFFFFF81 00 08 05 28 7A FFFFFFC0 00
   29 08 05 5E 7A FFFFFFC0 00 3E 08 05 65 7A FFFFFFC0 00 4B 08
   07 FFFFFF81 01 7A FFFFFFC0 00 FFFFFF81 02 01 04 72 66 75 6E 10 08
   12 FFFFFF81 03 FFFFFF81 05 FFFFFF81 08 24 09 03 FFFFFF81 04 06 02 09 46
   75 6E 63 74 69 6F 6E 32 10 03 4C FFFFFF81 06 09 03 FFFFFF81
   07 04 02 0D 41 62 73 74 72 61 63 74 41 63 74 6F
   72 10 03 19 FFFFFF81 09 09 03 FFFFFF81 0A 02 02 05 50 72 6F
   78 79 08 07 FFFFFF81 0C 00 FFFFFF84 00 FFFFFF81 0D 01 0B 63 72 65
   61 74 65 50 72 6F 78 79 14 06 FFFFFF81 08 FFFFFF81 0E FFFFFF81 0F
   08 06 28 FFFFFF81 0B FFFFFFC0 00 29 08 07 FFFFFF81 10 FFFFFF81 0B FFFFFFC0 00
   3E 01 03 73 79 6D 08 09 FFFFFF81 12 00 FFFFFFC2 FFFFFF80 FFFFFF84 00 FFFFFF81
   13 01 07 70 72 6F 78 69 65 73 15 02 FFFFFF81 14 10 06
   44 49 FFFFFF81 15 FFFFFF81 08 10 05 12 FFFFFF81 16 29 3E 09 03 FFFFFF81
   17 06 02 06 54 75 70 6C 65 32 08 08 FFFFFF81 19 00 FFFFFFA0
   FFFFFF80 04 FFFFFF81 14 01 08 70 72 6F 78 69 65 73 20 08 07
   FFFFFF81 1B 00 FFFFFF84 00 FFFFFF81 1C 01 10 67 65 74 4F 72 43 72
   65 61 74 65 50 72 6F 78 79 14 06 FFFFFF81 08 FFFFFF81 1D FFFFFF81
   1F 08 07 FFFFFF81 1E FFFFFF81 1A FFFFFFC0 00 29 01 0A 73 65 6E 64
   65 72 4E 6F 64 65 08 07 FFFFFF81 20 FFFFFF81 1A FFFFFFC0 00 3E 01
   0A 73 65 6E 64 65 72 4E 61 6D 65 08 07 FFFFFF81 22 00
   FFFFFF84 00 FFFFFF81 23 01 0D 72 65 67 69 73 74 65 72 50 72
   6F 78 79 14 07 24 FFFFFF81 24 FFFFFF81 25 FFFFFF81 26 08 07 FFFFFF81 1E
   FFFFFF81 21 FFFFFFC0 00 29 08 07 FFFFFF81 20 FFFFFF81 21 FFFFFFC0 00 3E 08 08
   FFFFFF81 27 FFFFFF81 21 FFFFFFC0 00 FFFFFF81 08 01 01 70 08 07 FFFFFF81 29 00
   FFFFFF84 00 FFFFFF81 2A 01 0A 70 72 6F 63 65 73 73 4D 73 67
   14 05 24 FFFFFF81 2B FFFFFF81 2C 08 07 FFFFFF81 1E FFFFFF81 28 FFFFFFC0 00 29
   08 06 2D FFFFFF81 28 FFFFFFC0 00 2E 08 07 FFFFFF81 2E 00 FFFFFF84 00 FFFFFF81
   2F 01 09 74 65 72 6D 69 6E 61 74 65 14 01 24 
  InnerClass: 
   public final $anonfun$terminate$1=class scala/actors/remote/NetKernel$$anonfun$terminate$1 of class scala/actors/remote/NetKernel
  minor version: 0
  major version: 49
  Constant pool:
Asciz	SourceFile;
Asciz	NetKernel.scala;
Asciz	<clinit>;
Asciz	()V;
Asciz	Code;
Asciz	scala/Symbol$;
class	scala/Symbol$
Asciz	MODULE$;
Asciz	Lscala/Symbol$;;
NameAndType	MODULE$:Lscala/Symbol$;
Field	scala/Symbol$.MODULE$:Lscala/Symbol$;
Asciz	LineNumberTable;
Asciz	nosession;
String	nosession
Asciz	apply;
Asciz	(Ljava/lang/Object;)Ljava/lang/Object;;
NameAndType	apply:(Ljava/lang/Object;)Ljava/lang/Object;
Method	scala/Symbol$.apply:(Ljava/lang/Object;)Ljava/lang/Object;
Asciz	scala/Symbol;
class	scala/Symbol
Asciz	scala/actors/remote/NetKernel;
class	scala/actors/remote/NetKernel
Asciz	symbol$1;
Asciz	Lscala/Symbol;;
NameAndType	symbol$1:Lscala/Symbol;
Field	scala/actors/remote/NetKernel.symbol$1:Lscala/Symbol;
Asciz	proxies;
Asciz	Lscala/collection/mutable/HashMap;;
Asciz	Lscala/collection/mutable/HashMap<Lscala/Tuple2<Lscala/actors/remote/Node;Lscala/Symbol;>;Lscala/actors/remote/Proxy;>;;
Asciz	Signature;
Asciz	names;
Asciz	Lscala/collection/mutable/HashMap<Lscala/actors/OutputChannel<Ljava/lang/Object;>;Lscala/Symbol;>;;
Asciz	actors;
Asciz	Lscala/collection/mutable/HashMap<Lscala/Symbol;Lscala/actors/OutputChannel<Ljava/lang/Object;>;>;;
Asciz	service;
Asciz	Lscala/actors/remote/Service;;
Asciz	sendToNode;
Asciz	(Lscala/actors/remote/Node;Ljava/lang/Object;)V;
NameAndType	service:Lscala/actors/remote/Service;
Field	scala/actors/remote/NetKernel.service:Lscala/actors/remote/Service;
Asciz	scala/actors/remote/Service;
class	scala/actors/remote/Service
Asciz	serializer;
Asciz	()Lscala/actors/remote/Serializer;;
NameAndType	serializer:()Lscala/actors/remote/Serializer;
InterfaceMethod	scala/actors/remote/Service.serializer:()Lscala/actors/remote/Serializer;
Asciz	scala/actors/remote/Serializer;
class	scala/actors/remote/Serializer
Asciz	serialize;
Asciz	(Ljava/lang/Object;)[B;
NameAndType	serialize:(Ljava/lang/Object;)[B
Method	scala/actors/remote/Serializer.serialize:(Ljava/lang/Object;)[B
Asciz	send;
Asciz	(Lscala/actors/remote/Node;[B)V;
NameAndType	send:(Lscala/actors/remote/Node;[B)V
InterfaceMethod	scala/actors/remote/Service.send:(Lscala/actors/remote/Node;[B)V
Asciz	this;
Asciz	Lscala/actors/remote/NetKernel;;
Asciz	node;
Asciz	Lscala/actors/remote/Node;;
Asciz	msg;
Asciz	Ljava/lang/Object;;
Asciz	bytes;
Asciz	[B;
Asciz	LocalVariableTable;
Asciz	namedSend;
Asciz	(Lscala/actors/remote/Locator;Lscala/actors/remote/Locator;Ljava/lang/Object;Lscala/Symbol;)V;
Asciz	scala/actors/remote/Locator;
class	scala/actors/remote/Locator
Asciz	()Lscala/actors/remote/Node;;
NameAndType	node:()Lscala/actors/remote/Node;
Method	scala/actors/remote/Locator.node:()Lscala/actors/remote/Node;
Asciz	scala/actors/remote/NamedSend;
class	scala/actors/remote/NamedSend
Asciz	<init>;
Asciz	(Lscala/actors/remote/Locator;Lscala/actors/remote/Locator;[BLscala/Symbol;)V;
NameAndType	"<init>":(Lscala/actors/remote/Locator;Lscala/actors/remote/Locator;[BLscala/Symbol;)V
Method	scala/actors/remote/NamedSend."<init>":(Lscala/actors/remote/Locator;Lscala/actors/remote/Locator;[BLscala/Symbol;)V
NameAndType	sendToNode:(Lscala/actors/remote/Node;Ljava/lang/Object;)V
Method	scala/actors/remote/NetKernel.sendToNode:(Lscala/actors/remote/Node;Ljava/lang/Object;)V
Asciz	senderLoc;
Asciz	Lscala/actors/remote/Locator;;
Asciz	receiverLoc;
Asciz	session;
Asciz	()Lscala/collection/mutable/HashMap;;
NameAndType	actors:Lscala/collection/mutable/HashMap;
Field	scala/actors/remote/NetKernel.actors:Lscala/collection/mutable/HashMap;
Asciz	()Lscala/collection/mutable/HashMap<Lscala/Symbol;Lscala/actors/OutputChannel<Ljava/lang/Object;>;>;;
NameAndType	names:Lscala/collection/mutable/HashMap;
Field	scala/actors/remote/NetKernel.names:Lscala/collection/mutable/HashMap;
Asciz	()Lscala/collection/mutable/HashMap<Lscala/actors/OutputChannel<Ljava/lang/Object;>;Lscala/Symbol;>;;
Asciz	register;
Asciz	(Lscala/Symbol;Lscala/actors/OutputChannel;)V;
NameAndType	actors:()Lscala/collection/mutable/HashMap;
Method	scala/actors/remote/NetKernel.actors:()Lscala/collection/mutable/HashMap;
Asciz	scala/Predef$Pair$;
class	scala/Predef$Pair$
Asciz	Lscala/Predef$Pair$;;
NameAndType	MODULE$:Lscala/Predef$Pair$;
Field	scala/Predef$Pair$.MODULE$:Lscala/Predef$Pair$;
Asciz	(Ljava/lang/Object;Ljava/lang/Object;)Lscala/Tuple2;;
NameAndType	apply:(Ljava/lang/Object;Ljava/lang/Object;)Lscala/Tuple2;
Method	scala/Predef$Pair$.apply:(Ljava/lang/Object;Ljava/lang/Object;)Lscala/Tuple2;
Asciz	scala/collection/mutable/HashMap;
class	scala/collection/mutable/HashMap
Asciz	$plus$eq;
Asciz	(Lscala/Tuple2;)Lscala/collection/mutable/HashMap;;
NameAndType	$plus$eq:(Lscala/Tuple2;)Lscala/collection/mutable/HashMap;
Method	scala/collection/mutable/HashMap.$plus$eq:(Lscala/Tuple2;)Lscala/collection/mutable/HashMap;
NameAndType	names:()Lscala/collection/mutable/HashMap;
Method	scala/actors/remote/NetKernel.names:()Lscala/collection/mutable/HashMap;
Asciz	name;
Asciz	a;
Asciz	Lscala/actors/OutputChannel;;
Asciz	(Lscala/Symbol;Lscala/actors/OutputChannel<Ljava/lang/Object;>;)V;
Asciz	getOrCreateName;
Asciz	(Lscala/actors/OutputChannel;)Lscala/Symbol;;
Asciz	get;
Asciz	(Ljava/lang/Object;)Lscala/Option;;
NameAndType	get:(Ljava/lang/Object;)Lscala/Option;
Method	scala/collection/mutable/HashMap.get:(Ljava/lang/Object;)Lscala/Option;
Asciz	scala/None$;
class	scala/None$
Asciz	Lscala/None$;;
NameAndType	MODULE$:Lscala/None$;
Field	scala/None$.MODULE$:Lscala/None$;
Asciz	java/lang/Object;
class	java/lang/Object
Asciz	equals;
Asciz	(Ljava/lang/Object;)Z;
NameAndType	equals:(Ljava/lang/Object;)Z
Method	java/lang/Object.equals:(Ljava/lang/Object;)Z
Asciz	scala/actors/remote/FreshNameCreator$;
class	scala/actors/remote/FreshNameCreator$
Asciz	Lscala/actors/remote/FreshNameCreator$;;
NameAndType	MODULE$:Lscala/actors/remote/FreshNameCreator$;
Field	scala/actors/remote/FreshNameCreator$.MODULE$:Lscala/actors/remote/FreshNameCreator$;
Asciz	remotesender;
String	remotesender
Asciz	newName;
Asciz	(Ljava/lang/String;)Lscala/Symbol;;
NameAndType	newName:(Ljava/lang/String;)Lscala/Symbol;
Method	scala/actors/remote/FreshNameCreator$.newName:(Ljava/lang/String;)Lscala/Symbol;
NameAndType	register:(Lscala/Symbol;Lscala/actors/OutputChannel;)V
Method	scala/actors/remote/NetKernel.register:(Lscala/Symbol;Lscala/actors/OutputChannel;)V
Asciz	scala/Some;
class	scala/Some
Asciz	x;
Asciz	()Ljava/lang/Object;;
NameAndType	x:()Ljava/lang/Object;
Method	scala/Some.x:()Ljava/lang/Object;
Asciz	scala/MatchError;
class	scala/MatchError
Asciz	(Ljava/lang/Object;)V;
NameAndType	"<init>":(Ljava/lang/Object;)V
Method	scala/MatchError."<init>":(Ljava/lang/Object;)V
Asciz	from;
Asciz	temp37;
Asciz	Lscala/Option;;
Asciz	freshName;
Asciz	(Lscala/actors/OutputChannel<Ljava/lang/Object;>;)Lscala/Symbol;;
Asciz	(Lscala/actors/remote/Node;Lscala/Symbol;Ljava/lang/Object;)V;
Asciz	(Lscala/actors/remote/Node;Lscala/Symbol;Ljava/lang/Object;Lscala/Symbol;)V;
NameAndType	send:(Lscala/actors/remote/Node;Lscala/Symbol;Ljava/lang/Object;Lscala/Symbol;)V
Method	scala/actors/remote/NetKernel.send:(Lscala/actors/remote/Node;Lscala/Symbol;Ljava/lang/Object;Lscala/Symbol;)V
InterfaceMethod	scala/actors/remote/Service.node:()Lscala/actors/remote/Node;
Asciz	scala/actors/Actor$;
class	scala/actors/Actor$
Asciz	Lscala/actors/Actor$;;
NameAndType	MODULE$:Lscala/actors/Actor$;
Field	scala/actors/Actor$.MODULE$:Lscala/actors/Actor$;
Asciz	self;
Asciz	()Lscala/actors/Actor;;
NameAndType	self:()Lscala/actors/Actor;
Method	scala/actors/Actor$.self:()Lscala/actors/Actor;
NameAndType	getOrCreateName:(Lscala/actors/OutputChannel;)Lscala/Symbol;
Method	scala/actors/remote/NetKernel.getOrCreateName:(Lscala/actors/OutputChannel;)Lscala/Symbol;
Asciz	(Lscala/actors/remote/Node;Lscala/Symbol;)V;
NameAndType	"<init>":(Lscala/actors/remote/Node;Lscala/Symbol;)V
Method	scala/actors/remote/Locator."<init>":(Lscala/actors/remote/Node;Lscala/Symbol;)V
NameAndType	namedSend:(Lscala/actors/remote/Locator;Lscala/actors/remote/Locator;Ljava/lang/Object;Lscala/Symbol;)V
Method	scala/actors/remote/NetKernel.namedSend:(Lscala/actors/remote/Locator;Lscala/actors/remote/Locator;Ljava/lang/Object;Lscala/Symbol;)V
Asciz	forward;
Asciz	(Lscala/actors/OutputChannel;Lscala/actors/remote/Node;Lscala/Symbol;Ljava/lang/Object;Lscala/Symbol;)V;
Asciz	(Lscala/actors/OutputChannel<Ljava/lang/Object;>;Lscala/actors/remote/Node;Lscala/Symbol;Ljava/lang/Object;Lscala/Symbol;)V;
Asciz	remoteApply;
Asciz	(Lscala/actors/remote/Node;Lscala/Symbol;Lscala/actors/OutputChannel;Lscala/Function2;)V;
Asciz	scala/actors/remote/RemoteApply0;
class	scala/actors/remote/RemoteApply0
Asciz	(Lscala/actors/remote/Locator;Lscala/actors/remote/Locator;Lscala/Function2;)V;
NameAndType	"<init>":(Lscala/actors/remote/Locator;Lscala/actors/remote/Locator;Lscala/Function2;)V
Method	scala/actors/remote/RemoteApply0."<init>":(Lscala/actors/remote/Locator;Lscala/actors/remote/Locator;Lscala/Function2;)V
Asciz	rfun;
Asciz	Lscala/Function2;;
Asciz	(Lscala/actors/remote/Node;Lscala/Symbol;Lscala/actors/OutputChannel<Ljava/lang/Object;>;Lscala/Function2<Lscala/actors/AbstractActor;Lscala/actors/remote/Proxy;Ljava/lang/Object;>;)V;
Asciz	createProxy;
Asciz	(Lscala/actors/remote/Node;Lscala/Symbol;)Lscala/actors/remote/Proxy;;
Asciz	scala/actors/remote/Proxy;
class	scala/actors/remote/Proxy
Asciz	(Lscala/actors/remote/Node;Lscala/Symbol;Lscala/actors/remote/NetKernel;)V;
NameAndType	"<init>":(Lscala/actors/remote/Node;Lscala/Symbol;Lscala/actors/remote/NetKernel;)V
Method	scala/actors/remote/Proxy."<init>":(Lscala/actors/remote/Node;Lscala/Symbol;Lscala/actors/remote/NetKernel;)V
NameAndType	proxies:()Lscala/collection/mutable/HashMap;
Method	scala/actors/remote/NetKernel.proxies:()Lscala/collection/mutable/HashMap;
Asciz	scala/Tuple2;
class	scala/Tuple2
Asciz	(Ljava/lang/Object;Ljava/lang/Object;)V;
NameAndType	"<init>":(Ljava/lang/Object;Ljava/lang/Object;)V
Method	scala/Tuple2."<init>":(Ljava/lang/Object;Ljava/lang/Object;)V
Asciz	sym;
Asciz	p;
Asciz	Lscala/actors/remote/Proxy;;
NameAndType	proxies:Lscala/collection/mutable/HashMap;
Field	scala/actors/remote/NetKernel.proxies:Lscala/collection/mutable/HashMap;
Asciz	()Lscala/collection/mutable/HashMap<Lscala/Tuple2<Lscala/actors/remote/Node;Lscala/Symbol;>;Lscala/actors/remote/Proxy;>;;
Asciz	getOrCreateProxy;
NameAndType	createProxy:(Lscala/actors/remote/Node;Lscala/Symbol;)Lscala/actors/remote/Proxy;
Method	scala/actors/remote/NetKernel.createProxy:(Lscala/actors/remote/Node;Lscala/Symbol;)Lscala/actors/remote/Proxy;
Asciz	senderNode;
Asciz	senderName;
Asciz	temp41;
Asciz	registerProxy;
Asciz	(Lscala/actors/remote/Node;Lscala/Symbol;Lscala/actors/remote/Proxy;)V;
Asciz	scala/runtime/BoxedUnit;
class	scala/runtime/BoxedUnit
Asciz	UNIT;
Asciz	Lscala/runtime/BoxedUnit;;
NameAndType	UNIT:Lscala/runtime/BoxedUnit;
Field	scala/runtime/BoxedUnit.UNIT:Lscala/runtime/BoxedUnit;
Asciz	temp45;
Asciz	processMsg;
Asciz	()Lscala/actors/remote/Locator;;
NameAndType	senderLoc:()Lscala/actors/remote/Locator;
Method	scala/actors/remote/RemoteApply0.senderLoc:()Lscala/actors/remote/Locator;
NameAndType	receiverLoc:()Lscala/actors/remote/Locator;
Method	scala/actors/remote/RemoteApply0.receiverLoc:()Lscala/actors/remote/Locator;
Asciz	scala/actors/Debug$;
class	scala/actors/Debug$
Asciz	Lscala/actors/Debug$;;
NameAndType	MODULE$:Lscala/actors/Debug$;
Field	scala/actors/Debug$.MODULE$:Lscala/actors/Debug$;
Asciz	scala/collection/mutable/StringBuilder;
class	scala/collection/mutable/StringBuilder
NameAndType	"<init>":()V
Method	scala/collection/mutable/StringBuilder."<init>":()V
Asciz	scala/Predef$;
class	scala/Predef$
Asciz	Lscala/Predef$;;
NameAndType	MODULE$:Lscala/Predef$;
Field	scala/Predef$.MODULE$:Lscala/Predef$;
Asciz	any2stringadd;
Asciz	(Ljava/lang/Object;)Lscala/runtime/StringAdd;;
NameAndType	any2stringadd:(Ljava/lang/Object;)Lscala/runtime/StringAdd;
Method	scala/Predef$.any2stringadd:(Ljava/lang/Object;)Lscala/runtime/StringAdd;
Asciz	: processing ;
String	: processing 
Asciz	scala/runtime/StringAdd;
class	scala/runtime/StringAdd
Asciz	$plus;
Asciz	(Ljava/lang/String;)Ljava/lang/String;;
NameAndType	$plus:(Ljava/lang/String;)Ljava/lang/String;
Method	scala/runtime/StringAdd.$plus:(Ljava/lang/String;)Ljava/lang/String;
Asciz	append;
Asciz	(Ljava/lang/Object;)Lscala/collection/mutable/StringBuilder;;
NameAndType	append:(Ljava/lang/Object;)Lscala/collection/mutable/StringBuilder;
Method	scala/collection/mutable/StringBuilder.append:(Ljava/lang/Object;)Lscala/collection/mutable/StringBuilder;
Asciz	toString;
Asciz	()Ljava/lang/String;;
NameAndType	toString:()Ljava/lang/String;
Method	scala/collection/mutable/StringBuilder.toString:()Ljava/lang/String;
Asciz	info;
Asciz	(Ljava/lang/String;)V;
NameAndType	info:(Ljava/lang/String;)V
Method	scala/actors/Debug$.info:(Ljava/lang/String;)V
Asciz	()Lscala/Symbol;;
NameAndType	name:()Lscala/Symbol;
Method	scala/actors/remote/Locator.name:()Lscala/Symbol;
NameAndType	getOrCreateProxy:(Lscala/actors/remote/Node;Lscala/Symbol;)Lscala/actors/remote/Proxy;
Method	scala/actors/remote/NetKernel.getOrCreateProxy:(Lscala/actors/remote/Node;Lscala/Symbol;)Lscala/actors/remote/Proxy;
Asciz	scala/actors/remote/LocalApply0;
class	scala/actors/remote/LocalApply0
Asciz	()Lscala/Function2;;
NameAndType	rfun:()Lscala/Function2;
Method	scala/actors/remote/RemoteApply0.rfun:()Lscala/Function2;
Asciz	scala/actors/AbstractActor;
class	scala/actors/AbstractActor
Asciz	(Lscala/Function2;Lscala/actors/AbstractActor;)V;
NameAndType	"<init>":(Lscala/Function2;Lscala/actors/AbstractActor;)V
Method	scala/actors/remote/LocalApply0."<init>":(Lscala/Function2;Lscala/actors/AbstractActor;)V
Asciz	(Ljava/lang/Object;Lscala/actors/OutputChannel;)V;
NameAndType	send:(Ljava/lang/Object;Lscala/actors/OutputChannel;)V
Method	scala/actors/remote/Proxy.send:(Ljava/lang/Object;Lscala/actors/OutputChannel;)V
Asciz	: lost message;
String	: lost message
Method	scala/actors/remote/NamedSend.senderLoc:()Lscala/actors/remote/Locator;
Method	scala/actors/remote/NamedSend.receiverLoc:()Lscala/actors/remote/Locator;
Asciz	data;
Asciz	()[B;
NameAndType	data:()[B
Method	scala/actors/remote/NamedSend.data:()[B
NameAndType	session:()Lscala/Symbol;
Method	scala/actors/remote/NamedSend.session:()Lscala/Symbol;
Asciz	scala/actors/OutputChannel;
class	scala/actors/OutputChannel
Asciz	liftedTree1$1;
Asciz	(Lscala/actors/remote/Locator;[BLscala/Symbol;Lscala/actors/OutputChannel;)V;
NameAndType	liftedTree1$1:(Lscala/actors/remote/Locator;[BLscala/Symbol;Lscala/actors/OutputChannel;)V
Method	scala/actors/remote/NetKernel.liftedTree1$1:(Lscala/actors/remote/Locator;[BLscala/Symbol;Lscala/actors/OutputChannel;)V
Asciz	temp57;
Asciz	temp58;
Asciz	Lscala/actors/remote/RemoteApply0;;
Asciz	temp59;
Asciz	temp60;
Asciz	temp49;
Asciz	senderProxy;
Asciz	temp62;
Asciz	Lscala/actors/remote/NamedSend;;
Asciz	temp63;
Asciz	temp64;
Asciz	temp65;
Asciz	temp66;
Asciz	senderLoc$3;
Asciz	data$2;
Asciz	session$3;
Asciz	temp53;
Asciz	temp54;
Asciz	Lscala/Some;;
Asciz	temp55;
Asciz	a$3;
Asciz	terminate;
Asciz	valuesIterator;
Asciz	()Lscala/collection/Iterator;;
NameAndType	valuesIterator:()Lscala/collection/Iterator;
Method	scala/collection/mutable/HashMap.valuesIterator:()Lscala/collection/Iterator;
Asciz	scala/actors/remote/NetKernel$$anonfun$terminate$1;
class	scala/actors/remote/NetKernel$$anonfun$terminate$1
Asciz	(Lscala/actors/remote/NetKernel;)V;
NameAndType	"<init>":(Lscala/actors/remote/NetKernel;)V
Method	scala/actors/remote/NetKernel$$anonfun$terminate$1."<init>":(Lscala/actors/remote/NetKernel;)V
Asciz	scala/collection/Iterator;
class	scala/collection/Iterator
Asciz	foreach;
Asciz	(Lscala/Function1;)V;
NameAndType	foreach:(Lscala/Function1;)V
InterfaceMethod	scala/collection/Iterator.foreach:(Lscala/Function1;)V
NameAndType	terminate:()V
InterfaceMethod	scala/actors/remote/Service.terminate:()V
Asciz	deserialize;
Asciz	([B)Ljava/lang/Object;;
NameAndType	deserialize:([B)Ljava/lang/Object;
Method	scala/actors/remote/Serializer.deserialize:([B)Ljava/lang/Object;
Asciz	scala/actors/remote/SendTo;
class	scala/actors/remote/SendTo
Asciz	(Lscala/actors/OutputChannel;Ljava/lang/Object;Lscala/Symbol;)V;
NameAndType	"<init>":(Lscala/actors/OutputChannel;Ljava/lang/Object;Lscala/Symbol;)V
Method	scala/actors/remote/SendTo."<init>":(Lscala/actors/OutputChannel;Ljava/lang/Object;Lscala/Symbol;)V
Asciz	: caught ;
String	: caught 
Asciz	error;
NameAndType	error:(Ljava/lang/String;)V
Method	scala/actors/Debug$.error:(Ljava/lang/String;)V
Asciz	java/lang/Exception;
class	java/lang/Exception
Asciz	(Lscala/actors/remote/Service;)V;
Method	java/lang/Object."<init>":()V
Method	scala/collection/mutable/HashMap."<init>":()V
Asciz	ScalaSig;
Asciz	InnerClasses;
Asciz	$anonfun$terminate$1;
Asciz	scala/ScalaObject;
class	scala/ScalaObject

{
private static final scala.Symbol symbol$1;
  Signature: Lscala/Symbol;

private final scala.collection.mutable.HashMap proxies;
  Signature: Lscala/collection/mutable/HashMap;
  Signature: length = 0x2
   00 1D 

private final scala.collection.mutable.HashMap names;
  Signature: Lscala/collection/mutable/HashMap;
  Signature: length = 0x2
   00 20 

private final scala.collection.mutable.HashMap actors;
  Signature: Lscala/collection/mutable/HashMap;
  Signature: length = 0x2
   00 22 

private final scala.actors.remote.Service service;
  Signature: Lscala/actors/remote/Service;

public static {};
  Signature: ()V
  Code:
   Stack=2, Locals=0, Args_size=0
	getstatic	Field scala/Symbol$.MODULE$:Lscala/Symbol$;
	ldc	String nosession
	invokevirtual	Method scala/Symbol$.apply:(Ljava/lang/Object;)Ljava/lang/Object;
	checkcast	class scala/Symbol
	putstatic	Field symbol$1:Lscala/Symbol;
	return
  Labels:

public void sendToNode(scala.actors.remote.Node, java.lang.Object);
  Signature: (Lscala/actors/remote/Node;Ljava/lang/Object;)V
  Code:
   Stack=3, Locals=4, Args_size=3
	aload_0
	getfield	Field service:Lscala/actors/remote/Service;
	invokeinterface	InterfaceMethod scala/actors/remote/Service.serializer:()Lscala/actors/remote/Serializer;
	aload_2
	invokevirtual	Method scala/actors/remote/Serializer.serialize:(Ljava/lang/Object;)[B
	astore_3
	aload_0
	getfield	Field service:Lscala/actors/remote/Service;
	aload_1
	aload_3
	invokeinterface	InterfaceMethod scala/actors/remote/Service.send:(Lscala/actors/remote/Node;[B)V
	return
  Labels:
  LocalVariableTable: 
   Start  Length  Slot  Name   Signature
   0      26      0    this       Lscala/actors/remote/NetKernel;
   0      26      1    node       Lscala/actors/remote/Node;
   0      26      2    msg       Ljava/lang/Object;
   14      11      3    bytes       [B


public void namedSend(scala.actors.remote.Locator, scala.actors.remote.Locator, java.lang.Object, scala.Symbol);
  Signature: (Lscala/actors/remote/Locator;Lscala/actors/remote/Locator;Ljava/lang/Object;Lscala/Symbol;)V
  Code:
   Stack=8, Locals=6, Args_size=5
	aload_0
	getfield	Field service:Lscala/actors/remote/Service;
	invokeinterface	InterfaceMethod scala/actors/remote/Service.serializer:()Lscala/actors/remote/Serializer;
	aload_3
	invokevirtual	Method scala/actors/remote/Serializer.serialize:(Ljava/lang/Object;)[B
	astore	5
	aload_0
	aload_2
	invokevirtual	Method scala/actors/remote/Locator.node:()Lscala/actors/remote/Node;
	new	class scala/actors/remote/NamedSend
	dup
	aload_1
	aload_2
	aload	5
	aload	4
	invokespecial	Method scala/actors/remote/NamedSend."<init>":(Lscala/actors/remote/Locator;Lscala/actors/remote/Locator;[BLscala/Symbol;)V
	invokevirtual	Method sendToNode:(Lscala/actors/remote/Node;Ljava/lang/Object;)V
	return
  Labels:
  LocalVariableTable: 
   Start  Length  Slot  Name   Signature
   0      37      0    this       Lscala/actors/remote/NetKernel;
   0      37      1    senderLoc       Lscala/actors/remote/Locator;
   0      37      2    receiverLoc       Lscala/actors/remote/Locator;
   0      37      3    msg       Ljava/lang/Object;
   0      37      4    session       Lscala/Symbol;
   15      21      5    bytes       [B


private scala.collection.mutable.HashMap actors();
  Signature: ()Lscala/collection/mutable/HashMap;
  Code:
   Stack=1, Locals=1, Args_size=1
	aload_0
	getfield	Field actors:Lscala/collection/mutable/HashMap;
	areturn
  Labels:
  Signature: length = 0x2
   00 58 

private scala.collection.mutable.HashMap names();
  Signature: ()Lscala/collection/mutable/HashMap;
  Code:
   Stack=1, Locals=1, Args_size=1
	aload_0
	getfield	Field names:Lscala/collection/mutable/HashMap;
	areturn
  Labels:
  Signature: length = 0x2
   00 5B 

public void register(scala.Symbol, scala.actors.OutputChannel);
  Signature: (Lscala/Symbol;Lscala/actors/OutputChannel;)V
  Code:
   Stack=4, Locals=4, Args_size=3
	aload_0
	dup
	astore_3
	monitorenter
	aload_0
	invokespecial	Method actors:()Lscala/collection/mutable/HashMap;
	getstatic	Field scala/Predef$Pair$.MODULE$:Lscala/Predef$Pair$;
	aload_1
	aload_2
	invokevirtual	Method scala/Predef$Pair$.apply:(Ljava/lang/Object;Ljava/lang/Object;)Lscala/Tuple2;
	invokevirtual	Method scala/collection/mutable/HashMap.$plus$eq:(Lscala/Tuple2;)Lscala/collection/mutable/HashMap;
	pop
	aload_0
	invokespecial	Method names:()Lscala/collection/mutable/HashMap;
	getstatic	Field scala/Predef$Pair$.MODULE$:Lscala/Predef$Pair$;
	aload_2
	aload_1
	invokevirtual	Method scala/Predef$Pair$.apply:(Ljava/lang/Object;Ljava/lang/Object;)Lscala/Tuple2;
	invokevirtual	Method scala/collection/mutable/HashMap.$plus$eq:(Lscala/Tuple2;)Lscala/collection/mutable/HashMap;
	pop
	aload_3
	monitorexit
	return
	aload_3
	monitorexit
	athrow
  Labels:
  Exception table:
   from   to  target type
     4    38    39   any
  LocalVariableTable: 
   Start  Length  Slot  Name   Signature
   0      42      0    this       Lscala/actors/remote/NetKernel;
   0      42      1    name       Lscala/Symbol;
   0      42      2    a       Lscala/actors/OutputChannel;

  Signature: length = 0x2
   00 73 

public scala.Symbol getOrCreateName(scala.actors.OutputChannel);
  Signature: (Lscala/actors/OutputChannel;)Lscala/Symbol;
  Code:
   Stack=3, Locals=5, Args_size=2
	aload_0
	invokespecial	Method names:()Lscala/collection/mutable/HashMap;
	aload_1
	invokevirtual	Method scala/collection/mutable/HashMap.get:(Ljava/lang/Object;)Lscala/Option;
	astore_2
	getstatic	Field scala/None$.MODULE$:Lscala/None$;
	aload_2
	astore_3
	dup
	ifnonnull	l1 // aload_3
	pop
	aload_3
	ifnull	l2 // getstatic
	goto	l3 // aload_2
l1	aload_3
	invokevirtual	Method java/lang/Object.equals:(Ljava/lang/Object;)Z
	ifeq	l3 // aload_2
l2	getstatic	Field scala/actors/remote/FreshNameCreator$.MODULE$:Lscala/actors/remote/FreshNameCreator$;
	ldc	String remotesender
	invokevirtual	Method scala/actors/remote/FreshNameCreator$.newName:(Ljava/lang/String;)Lscala/Symbol;
	astore	4
	aload_0
	aload	4
	aload_1
	invokevirtual	Method register:(Lscala/Symbol;Lscala/actors/OutputChannel;)V
	aload	4
	goto	l4 // areturn
l3	aload_2
	instanceof	class scala/Some
	ifeq	l5 // new
	aload_2
	checkcast	class scala/Some
	invokevirtual	Method scala/Some.x:()Ljava/lang/Object;
	checkcast	class scala/Symbol
l4	areturn
l5	new	class scala/MatchError
	dup
	aload_2
	invokespecial	Method scala/MatchError."<init>":(Ljava/lang/Object;)V
	athrow
  Labels:
   	l1 = 26 // aload_3
   	l2 = 33 // getstatic
   	l3 = 55 // aload_2
   	l4 = 72 // areturn
   	l5 = 73 // new
  LocalVariableTable: 
   Start  Length  Slot  Name   Signature
   0      82      0    this       Lscala/actors/remote/NetKernel;
   0      82      1    from       Lscala/actors/OutputChannel;
   9      73      2    temp37       Lscala/Option;
   43      9      4    freshName       Lscala/Symbol;

  Signature: length = 0x2
   00 FFFFFFA1 

public void send(scala.actors.remote.Node, scala.Symbol, java.lang.Object);
  Signature: (Lscala/actors/remote/Node;Lscala/Symbol;Ljava/lang/Object;)V
  Code:
   Stack=5, Locals=4, Args_size=4
	aload_0
	aload_1
	aload_2
	aload_3
	getstatic	Field symbol$1:Lscala/Symbol;
	checkcast	class scala/Symbol
	invokevirtual	Method send:(Lscala/actors/remote/Node;Lscala/Symbol;Ljava/lang/Object;Lscala/Symbol;)V
	return
  Labels:
  LocalVariableTable: 
   Start  Length  Slot  Name   Signature
   0      14      0    this       Lscala/actors/remote/NetKernel;
   0      14      1    node       Lscala/actors/remote/Node;
   0      14      2    name       Lscala/Symbol;
   0      14      3    msg       Ljava/lang/Object;


public void send(scala.actors.remote.Node, scala.Symbol, java.lang.Object, scala.Symbol);
  Signature: (Lscala/actors/remote/Node;Lscala/Symbol;Ljava/lang/Object;Lscala/Symbol;)V
  Code:
   Stack=5, Locals=7, Args_size=5
	new	class scala/actors/remote/Locator
	dup
	aload_0
	getfield	Field service:Lscala/actors/remote/Service;
	invokeinterface	InterfaceMethod scala/actors/remote/Service.node:()Lscala/actors/remote/Node;
	aload_0
	getstatic	Field scala/actors/Actor$.MODULE$:Lscala/actors/Actor$;
	invokevirtual	Method scala/actors/Actor$.self:()Lscala/actors/Actor;
	invokevirtual	Method getOrCreateName:(Lscala/actors/OutputChannel;)Lscala/Symbol;
	invokespecial	Method scala/actors/remote/Locator."<init>":(Lscala/actors/remote/Node;Lscala/Symbol;)V
	astore	5
	new	class scala/actors/remote/Locator
	dup
	aload_1
	aload_2
	invokespecial	Method scala/actors/remote/Locator."<init>":(Lscala/actors/remote/Node;Lscala/Symbol;)V
	astore	6
	aload_0
	aload	5
	aload	6
	aload_3
	aload	4
	invokevirtual	Method namedSend:(Lscala/actors/remote/Locator;Lscala/actors/remote/Locator;Ljava/lang/Object;Lscala/Symbol;)V
	return
  Labels:
  LocalVariableTable: 
   Start  Length  Slot  Name   Signature
   0      51      0    this       Lscala/actors/remote/NetKernel;
   0      51      1    node       Lscala/actors/remote/Node;
   0      51      2    name       Lscala/Symbol;
   0      51      3    msg       Ljava/lang/Object;
   0      51      4    session       Lscala/Symbol;
   28      22      5    senderLoc       Lscala/actors/remote/Locator;
   39      11      6    receiverLoc       Lscala/actors/remote/Locator;


public void forward(scala.actors.OutputChannel, scala.actors.remote.Node, scala.Symbol, java.lang.Object, scala.Symbol);
  Signature: (Lscala/actors/OutputChannel;Lscala/actors/remote/Node;Lscala/Symbol;Ljava/lang/Object;Lscala/Symbol;)V
  Code:
   Stack=5, Locals=8, Args_size=6
	new	class scala/actors/remote/Locator
	dup
	aload_0
	getfield	Field service:Lscala/actors/remote/Service;
	invokeinterface	InterfaceMethod scala/actors/remote/Service.node:()Lscala/actors/remote/Node;
	aload_0
	aload_1
	invokevirtual	Method getOrCreateName:(Lscala/actors/OutputChannel;)Lscala/Symbol;
	invokespecial	Method scala/actors/remote/Locator."<init>":(Lscala/actors/remote/Node;Lscala/Symbol;)V
	astore	6
	new	class scala/actors/remote/Locator
	dup
	aload_2
	aload_3
	invokespecial	Method scala/actors/remote/Locator."<init>":(Lscala/actors/remote/Node;Lscala/Symbol;)V
	astore	7
	aload_0
	aload	6
	aload	7
	aload	4
	aload	5
	invokevirtual	Method namedSend:(Lscala/actors/remote/Locator;Lscala/actors/remote/Locator;Ljava/lang/Object;Lscala/Symbol;)V
	return
  Labels:
  LocalVariableTable: 
   Start  Length  Slot  Name   Signature
   0      47      0    this       Lscala/actors/remote/NetKernel;
   0      47      1    from       Lscala/actors/OutputChannel;
   0      47      2    node       Lscala/actors/remote/Node;
   0      47      3    name       Lscala/Symbol;
   0      47      4    msg       Ljava/lang/Object;
   0      47      5    session       Lscala/Symbol;
   23      23      6    senderLoc       Lscala/actors/remote/Locator;
   34      12      7    receiverLoc       Lscala/actors/remote/Locator;

  Signature: length = 0x2
   00 FFFFFFB9 

public void remoteApply(scala.actors.remote.Node, scala.Symbol, scala.actors.OutputChannel, scala.Function2);
  Signature: (Lscala/actors/remote/Node;Lscala/Symbol;Lscala/actors/OutputChannel;Lscala/Function2;)V
  Code:
   Stack=7, Locals=7, Args_size=5
	new	class scala/actors/remote/Locator
	dup
	aload_0
	getfield	Field service:Lscala/actors/remote/Service;
	invokeinterface	InterfaceMethod scala/actors/remote/Service.node:()Lscala/actors/remote/Node;
	aload_0
	aload_3
	invokevirtual	Method getOrCreateName:(Lscala/actors/OutputChannel;)Lscala/Symbol;
	invokespecial	Method scala/actors/remote/Locator."<init>":(Lscala/actors/remote/Node;Lscala/Symbol;)V
	astore	5
	new	class scala/actors/remote/Locator
	dup
	aload_1
	aload_2
	invokespecial	Method scala/actors/remote/Locator."<init>":(Lscala/actors/remote/Node;Lscala/Symbol;)V
	astore	6
	aload_0
	aload	6
	invokevirtual	Method scala/actors/remote/Locator.node:()Lscala/actors/remote/Node;
	new	class scala/actors/remote/RemoteApply0
	dup
	aload	5
	aload	6
	aload	4
	invokespecial	Method scala/actors/remote/RemoteApply0."<init>":(Lscala/actors/remote/Locator;Lscala/actors/remote/Locator;Lscala/Function2;)V
	invokevirtual	Method sendToNode:(Lscala/actors/remote/Node;Ljava/lang/Object;)V
	return
  Labels:
  LocalVariableTable: 
   Start  Length  Slot  Name   Signature
   0      57      0    this       Lscala/actors/remote/NetKernel;
   0      57      1    node       Lscala/actors/remote/Node;
   0      57      2    name       Lscala/Symbol;
   0      57      3    from       Lscala/actors/OutputChannel;
   0      57      4    rfun       Lscala/Function2;
   23      33      5    senderLoc       Lscala/actors/remote/Locator;
   34      22      6    receiverLoc       Lscala/actors/remote/Locator;

  Signature: length = 0x2
   00 FFFFFFC3 

public scala.actors.remote.Proxy createProxy(scala.actors.remote.Node, scala.Symbol);
  Signature: (Lscala/actors/remote/Node;Lscala/Symbol;)Lscala/actors/remote/Proxy;
  Code:
   Stack=6, Locals=4, Args_size=3
	new	class scala/actors/remote/Proxy
	dup
	aload_1
	aload_2
	aload_0
	invokespecial	Method scala/actors/remote/Proxy."<init>":(Lscala/actors/remote/Node;Lscala/Symbol;Lscala/actors/remote/NetKernel;)V
	astore_3
	aload_0
	invokevirtual	Method proxies:()Lscala/collection/mutable/HashMap;
	getstatic	Field scala/Predef$Pair$.MODULE$:Lscala/Predef$Pair$;
	new	class scala/Tuple2
	dup
	aload_1
	aload_2
	invokespecial	Method scala/Tuple2."<init>":(Ljava/lang/Object;Ljava/lang/Object;)V
	aload_3
	invokevirtual	Method scala/Predef$Pair$.apply:(Ljava/lang/Object;Ljava/lang/Object;)Lscala/Tuple2;
	invokevirtual	Method scala/collection/mutable/HashMap.$plus$eq:(Lscala/Tuple2;)Lscala/collection/mutable/HashMap;
	pop
	aload_3
	areturn
  Labels:
  LocalVariableTable: 
   Start  Length  Slot  Name   Signature
   0      37      0    this       Lscala/actors/remote/NetKernel;
   0      37      1    node       Lscala/actors/remote/Node;
   0      37      2    sym       Lscala/Symbol;
   11      25      3    p       Lscala/actors/remote/Proxy;


public scala.collection.mutable.HashMap proxies();
  Signature: ()Lscala/collection/mutable/HashMap;
  Code:
   Stack=1, Locals=1, Args_size=1
	aload_0
	getfield	Field proxies:Lscala/collection/mutable/HashMap;
	areturn
  Labels:
  Signature: length = 0x2
   00 FFFFFFD7 

public scala.actors.remote.Proxy getOrCreateProxy(scala.actors.remote.Node, scala.Symbol);
  Signature: (Lscala/actors/remote/Node;Lscala/Symbol;)Lscala/actors/remote/Proxy;
  Code:
   Stack=5, Locals=7, Args_size=3
	aload_0
	invokevirtual	Method proxies:()Lscala/collection/mutable/HashMap;
	dup
	astore_3
	monitorenter
	aload_0
	invokevirtual	Method proxies:()Lscala/collection/mutable/HashMap;
	new	class scala/Tuple2
	dup
	aload_1
	aload_2
	invokespecial	Method scala/Tuple2."<init>":(Ljava/lang/Object;Ljava/lang/Object;)V
	invokevirtual	Method scala/collection/mutable/HashMap.get:(Ljava/lang/Object;)Lscala/Option;
	astore	5
	aload	5
	instanceof	class scala/Some
	ifeq	l1 // getstatic
	aload	5
	checkcast	class scala/Some
	invokevirtual	Method scala/Some.x:()Ljava/lang/Object;
	goto	l2 // astore
l1	getstatic	Field scala/None$.MODULE$:Lscala/None$;
	aload	5
	astore	6
	dup
	ifnonnull	l3 // aload
	pop
	aload	6
	ifnull	l4 // aload_0
	goto	l5 // new
l3	aload	6
	invokevirtual	Method java/lang/Object.equals:(Ljava/lang/Object;)Z
	ifeq	l5 // new
l4	aload_0
	aload_1
	aload_2
	invokevirtual	Method createProxy:(Lscala/actors/remote/Node;Lscala/Symbol;)Lscala/actors/remote/Proxy;
l2	astore	4
	aload_3
	monitorexit
	aload	4
	checkcast	class scala/actors/remote/Proxy
	areturn
l5	new	class scala/MatchError
	dup
	aload	5
	invokespecial	Method scala/MatchError."<init>":(Ljava/lang/Object;)V
	athrow
	aload_3
	monitorexit
	athrow
  Labels:
   	l1 = 44 // getstatic
   	l3 = 64 // aload
   	l4 = 72 // aload_0
   	l2 = 78 // astore
   	l5 = 88 // new
  Exception table:
   from   to  target type
     7    82    98   any
    88    98    98   any
  LocalVariableTable: 
   Start  Length  Slot  Name   Signature
   0      101      0    this       Lscala/actors/remote/NetKernel;
   0      101      1    senderNode       Lscala/actors/remote/Node;
   0      101      2    senderName       Lscala/Symbol;
   25      57      5    temp41       Lscala/Option;
   88      10      5    temp41       Lscala/Option;


public void registerProxy(scala.actors.remote.Node, scala.Symbol, scala.actors.remote.Proxy);
  Signature: (Lscala/actors/remote/Node;Lscala/Symbol;Lscala/actors/remote/Proxy;)V
  Code:
   Stack=6, Locals=7, Args_size=4
	aload_0
	invokevirtual	Method proxies:()Lscala/collection/mutable/HashMap;
	dup
	astore	4
	monitorenter
	aload_0
	invokevirtual	Method proxies:()Lscala/collection/mutable/HashMap;
	new	class scala/Tuple2
	dup
	aload_1
	aload_2
	invokespecial	Method scala/Tuple2."<init>":(Ljava/lang/Object;Ljava/lang/Object;)V
	invokevirtual	Method scala/collection/mutable/HashMap.get:(Ljava/lang/Object;)Lscala/Option;
	astore	5
	aload	5
	instanceof	class scala/Some
	ifeq	l1 // getstatic
	getstatic	Field scala/runtime/BoxedUnit.UNIT:Lscala/runtime/BoxedUnit;
	goto	l2 // pop
l1	getstatic	Field scala/None$.MODULE$:Lscala/None$;
	aload	5
	astore	6
	dup
	ifnonnull	l3 // aload
	pop
	aload	6
	ifnull	l4 // aload_0
	goto	l5 // new
l3	aload	6
	invokevirtual	Method java/lang/Object.equals:(Ljava/lang/Object;)Z
	ifeq	l5 // new
l4	aload_0
	invokevirtual	Method proxies:()Lscala/collection/mutable/HashMap;
	getstatic	Field scala/Predef$Pair$.MODULE$:Lscala/Predef$Pair$;
	new	class scala/Tuple2
	dup
	aload_1
	aload_2
	invokespecial	Method scala/Tuple2."<init>":(Ljava/lang/Object;Ljava/lang/Object;)V
	aload_3
	invokevirtual	Method scala/Predef$Pair$.apply:(Ljava/lang/Object;Ljava/lang/Object;)Lscala/Tuple2;
	invokevirtual	Method scala/collection/mutable/HashMap.$plus$eq:(Lscala/Tuple2;)Lscala/collection/mutable/HashMap;
l2	pop
	aload	4
	monitorexit
	return
l5	new	class scala/MatchError
	dup
	aload	5
	invokespecial	Method scala/MatchError."<init>":(Ljava/lang/Object;)V
	athrow
	aload	4
	monitorexit
	athrow
  Labels:
   	l1 = 40 // getstatic
   	l3 = 60 // aload
   	l4 = 68 // aload_0
   	l2 = 91 // pop
   	l5 = 96 // new
  Exception table:
   from   to  target type
     8    95   106   any
    96   106   106   any
  LocalVariableTable: 
   Start  Length  Slot  Name   Signature
   0      110      0    this       Lscala/actors/remote/NetKernel;
   0      110      1    senderNode       Lscala/actors/remote/Node;
   0      110      2    senderName       Lscala/Symbol;
   0      110      3    p       Lscala/actors/remote/Proxy;
   26      66      5    temp45       Lscala/Option;
   96      10      5    temp45       Lscala/Option;


public void processMsg(scala.actors.remote.Node, java.lang.Object);
  Signature: (Lscala/actors/remote/Node;Ljava/lang/Object;)V
  Code:
   Stack=5, Locals=27, Args_size=3
	aload_0
	dup
	astore_3
	monitorenter
	aload_2
	astore	4
	aload	4
	instanceof	class scala/actors/remote/RemoteApply0
	ifeq	l1 // aload
	aload	4
	checkcast	class scala/actors/remote/RemoteApply0
	astore	5
	aload	5
	invokevirtual	Method scala/actors/remote/RemoteApply0.senderLoc:()Lscala/actors/remote/Locator;
	astore	6
	aload	5
	invokevirtual	Method scala/actors/remote/RemoteApply0.receiverLoc:()Lscala/actors/remote/Locator;
	astore	7
	aload	6
	astore	8
	aload	7
	astore	9
	getstatic	Field scala/actors/Debug$.MODULE$:Lscala/actors/Debug$;
	new	class scala/collection/mutable/StringBuilder
	dup
	invokespecial	Method scala/collection/mutable/StringBuilder."<init>":()V
	getstatic	Field scala/Predef$.MODULE$:Lscala/Predef$;
	aload_0
	invokevirtual	Method scala/Predef$.any2stringadd:(Ljava/lang/Object;)Lscala/runtime/StringAdd;
	ldc_w	String : processing 
	invokevirtual	Method scala/runtime/StringAdd.$plus:(Ljava/lang/String;)Ljava/lang/String;
	invokevirtual	Method scala/collection/mutable/StringBuilder.append:(Ljava/lang/Object;)Lscala/collection/mutable/StringBuilder;
	aload	5
	invokevirtual	Method scala/collection/mutable/StringBuilder.append:(Ljava/lang/Object;)Lscala/collection/mutable/StringBuilder;
	invokevirtual	Method scala/collection/mutable/StringBuilder.toString:()Ljava/lang/String;
	invokevirtual	Method scala/actors/Debug$.info:(Ljava/lang/String;)V
	aload_0
	invokespecial	Method actors:()Lscala/collection/mutable/HashMap;
	aload	9
	invokevirtual	Method scala/actors/remote/Locator.name:()Lscala/Symbol;
	invokevirtual	Method scala/collection/mutable/HashMap.get:(Ljava/lang/Object;)Lscala/Option;
	astore	10
	aload	10
	instanceof	class scala/Some
	ifeq	l2 // getstatic
	aload_0
	aload	8
	invokevirtual	Method scala/actors/remote/Locator.node:()Lscala/actors/remote/Node;
	aload	8
	invokevirtual	Method scala/actors/remote/Locator.name:()Lscala/Symbol;
	invokevirtual	Method getOrCreateProxy:(Lscala/actors/remote/Node;Lscala/Symbol;)Lscala/actors/remote/Proxy;
	astore	11
	aload	11
	new	class scala/actors/remote/LocalApply0
	dup
	aload	5
	invokevirtual	Method scala/actors/remote/RemoteApply0.rfun:()Lscala/Function2;
	aload	10
	checkcast	class scala/Some
	invokevirtual	Method scala/Some.x:()Ljava/lang/Object;
	checkcast	class scala/actors/AbstractActor
	invokespecial	Method scala/actors/remote/LocalApply0."<init>":(Lscala/Function2;Lscala/actors/AbstractActor;)V
	aconst_null
	pop
	aconst_null
	invokevirtual	Method scala/actors/remote/Proxy.send:(Ljava/lang/Object;Lscala/actors/OutputChannel;)V
	getstatic	Field scala/runtime/BoxedUnit.UNIT:Lscala/runtime/BoxedUnit;
	goto	l3 // pop
l2	getstatic	Field scala/None$.MODULE$:Lscala/None$;
	aload	10
	astore	12
	dup
	ifnonnull	l4 // aload
	pop
	aload	12
	ifnull	l5 // getstatic
	goto	l6 // new
l4	aload	12
	invokevirtual	Method java/lang/Object.equals:(Ljava/lang/Object;)Z
	ifeq	l6 // new
l5	getstatic	Field scala/actors/Debug$.MODULE$:Lscala/actors/Debug$;
	getstatic	Field scala/Predef$.MODULE$:Lscala/Predef$;
	aload_0
	invokevirtual	Method scala/Predef$.any2stringadd:(Ljava/lang/Object;)Lscala/runtime/StringAdd;
	ldc_w	String : lost message
	invokevirtual	Method scala/runtime/StringAdd.$plus:(Ljava/lang/String;)Ljava/lang/String;
	invokevirtual	Method scala/actors/Debug$.info:(Ljava/lang/String;)V
	getstatic	Field scala/runtime/BoxedUnit.UNIT:Lscala/runtime/BoxedUnit;
	goto	l3 // pop
l6	new	class scala/MatchError
	dup
	aload	10
	invokespecial	Method scala/MatchError."<init>":(Ljava/lang/Object;)V
	athrow
l1	aload	4
	instanceof	class scala/actors/remote/NamedSend
	ifeq	l7 // new
	aload	4
	checkcast	class scala/actors/remote/NamedSend
	astore	13
	aload	13
	invokevirtual	Method scala/actors/remote/NamedSend.senderLoc:()Lscala/actors/remote/Locator;
	astore	14
	aload	13
	invokevirtual	Method scala/actors/remote/NamedSend.receiverLoc:()Lscala/actors/remote/Locator;
	astore	15
	aload	13
	invokevirtual	Method scala/actors/remote/NamedSend.data:()[B
	astore	16
	aload	13
	invokevirtual	Method scala/actors/remote/NamedSend.session:()Lscala/Symbol;
	astore	17
	aload	14
	astore	18
	aload	15
	astore	19
	aload	16
	astore	20
	aload	17
	astore	21
	getstatic	Field scala/actors/Debug$.MODULE$:Lscala/actors/Debug$;
	new	class scala/collection/mutable/StringBuilder
	dup
	invokespecial	Method scala/collection/mutable/StringBuilder."<init>":()V
	getstatic	Field scala/Predef$.MODULE$:Lscala/Predef$;
	aload_0
	invokevirtual	Method scala/Predef$.any2stringadd:(Ljava/lang/Object;)Lscala/runtime/StringAdd;
	ldc_w	String : processing 
	invokevirtual	Method scala/runtime/StringAdd.$plus:(Ljava/lang/String;)Ljava/lang/String;
	invokevirtual	Method scala/collection/mutable/StringBuilder.append:(Ljava/lang/Object;)Lscala/collection/mutable/StringBuilder;
	aload	13
	invokevirtual	Method scala/collection/mutable/StringBuilder.append:(Ljava/lang/Object;)Lscala/collection/mutable/StringBuilder;
	invokevirtual	Method scala/collection/mutable/StringBuilder.toString:()Ljava/lang/String;
	invokevirtual	Method scala/actors/Debug$.info:(Ljava/lang/String;)V
	aload_0
	invokespecial	Method actors:()Lscala/collection/mutable/HashMap;
	aload	19
	invokevirtual	Method scala/actors/remote/Locator.name:()Lscala/Symbol;
	invokevirtual	Method scala/collection/mutable/HashMap.get:(Ljava/lang/Object;)Lscala/Option;
	astore	22
	aload	22
	instanceof	class scala/Some
	ifeq	l8 // getstatic
	aload	22
	checkcast	class scala/Some
	astore	23
	aload	23
	invokevirtual	Method scala/Some.x:()Ljava/lang/Object;
	checkcast	class scala/actors/OutputChannel
	astore	24
	aload	24
	astore	25
	aload_0
	aload	18
	aload	20
	aload	21
	aload	25
	invokespecial	Method liftedTree1$1:(Lscala/actors/remote/Locator;[BLscala/Symbol;Lscala/actors/OutputChannel;)V
	getstatic	Field scala/runtime/BoxedUnit.UNIT:Lscala/runtime/BoxedUnit;
	goto	l3 // pop
l8	getstatic	Field scala/None$.MODULE$:Lscala/None$;
	aload	22
	astore	26
	dup
	ifnonnull	l9 // aload
	pop
	aload	26
	ifnull	l10 // getstatic
	goto	l11 // new
l9	aload	26
	invokevirtual	Method java/lang/Object.equals:(Ljava/lang/Object;)Z
	ifeq	l11 // new
l10	getstatic	Field scala/actors/Debug$.MODULE$:Lscala/actors/Debug$;
	getstatic	Field scala/Predef$.MODULE$:Lscala/Predef$;
	aload_0
	invokevirtual	Method scala/Predef$.any2stringadd:(Ljava/lang/Object;)Lscala/runtime/StringAdd;
	ldc_w	String : lost message
	invokevirtual	Method scala/runtime/StringAdd.$plus:(Ljava/lang/String;)Ljava/lang/String;
	invokevirtual	Method scala/actors/Debug$.info:(Ljava/lang/String;)V
	getstatic	Field scala/runtime/BoxedUnit.UNIT:Lscala/runtime/BoxedUnit;
l3	pop
	aload_3
	monitorexit
	return
l11	new	class scala/MatchError
	dup
	aload	22
	invokespecial	Method scala/MatchError."<init>":(Ljava/lang/Object;)V
	athrow
l7	new	class scala/MatchError
	dup
	aload	4
	invokespecial	Method scala/MatchError."<init>":(Ljava/lang/Object;)V
	athrow
	aload_3
	monitorexit
	athrow
  Labels:
   	l2 = 156 // getstatic
   	l4 = 176 // aload
   	l5 = 184 // getstatic
   	l6 = 209 // new
   	l1 = 219 // aload
   	l8 = 376 // getstatic
   	l9 = 396 // aload
   	l10 = 404 // getstatic
   	l3 = 426 // pop
   	l11 = 430 // new
   	l7 = 440 // new
  Exception table:
   from   to  target type
     4   429   450   any
   430   450   450   any
  LocalVariableTable: 
   Start  Length  Slot  Name   Signature
   0      453      0    this       Lscala/actors/remote/NetKernel;
   0      453      1    senderNode       Lscala/actors/remote/Node;
   0      453      2    msg       Ljava/lang/Object;
   7      420      4    temp57       Ljava/lang/Object;
   430      20      4    temp57       Ljava/lang/Object;
   22      197      5    temp58       Lscala/actors/remote/RemoteApply0;
   29      190      6    temp59       Lscala/actors/remote/Locator;
   36      183      7    temp60       Lscala/actors/remote/Locator;
   40      179      8    senderLoc       Lscala/actors/remote/Locator;
   44      175      9    receiverLoc       Lscala/actors/remote/Locator;
   95      124      10    temp49       Lscala/Option;
   119      34      11    senderProxy       Lscala/actors/remote/Proxy;
   234      192      13    temp62       Lscala/actors/remote/NamedSend;
   430      10      13    temp62       Lscala/actors/remote/NamedSend;
   241      185      14    temp63       Lscala/actors/remote/Locator;
   430      10      14    temp63       Lscala/actors/remote/Locator;
   248      178      15    temp64       Lscala/actors/remote/Locator;
   430      10      15    temp64       Lscala/actors/remote/Locator;
   255      171      16    temp65       [B
   430      10      16    temp65       [B
   262      164      17    temp66       Lscala/Symbol;
   430      10      17    temp66       Lscala/Symbol;
   266      160      18    senderLoc$3       Lscala/actors/remote/Locator;
   430      10      18    senderLoc$3       Lscala/actors/remote/Locator;
   270      156      19    receiverLoc       Lscala/actors/remote/Locator;
   430      10      19    receiverLoc       Lscala/actors/remote/Locator;
   274      152      20    data$2       [B
   430      10      20    data$2       [B
   278      148      21    session$3       Lscala/Symbol;
   430      10      21    session$3       Lscala/Symbol;
   329      97      22    temp53       Lscala/Option;
   430      10      22    temp53       Lscala/Option;
   344      29      23    temp54       Lscala/Some;
   354      19      24    temp55       Lscala/actors/OutputChannel;
   358      15      25    a$3       Lscala/actors/OutputChannel;


public void terminate();
  Signature: ()V
  Code:
   Stack=4, Locals=1, Args_size=1
	aload_0
	invokevirtual	Method proxies:()Lscala/collection/mutable/HashMap;
	invokevirtual	Method scala/collection/mutable/HashMap.valuesIterator:()Lscala/collection/Iterator;
	new	class scala/actors/remote/NetKernel$$anonfun$terminate$1
	dup
	aload_0
	invokespecial	Method scala/actors/remote/NetKernel$$anonfun$terminate$1."<init>":(Lscala/actors/remote/NetKernel;)V
	invokeinterface	InterfaceMethod scala/collection/Iterator.foreach:(Lscala/Function1;)V
	aload_0
	getfield	Field service:Lscala/actors/remote/Service;
	invokeinterface	InterfaceMethod scala/actors/remote/Service.terminate:()V
	return
  Labels:

private final void liftedTree1$1(scala.actors.remote.Locator, byte[], scala.Symbol, scala.actors.OutputChannel);
  Signature: (Lscala/actors/remote/Locator;[BLscala/Symbol;Lscala/actors/OutputChannel;)V
  Code:
   Stack=6, Locals=8, Args_size=5
	aload_0
	getfield	Field service:Lscala/actors/remote/Service;
	invokeinterface	InterfaceMethod scala/actors/remote/Service.serializer:()Lscala/actors/remote/Serializer;
	aload_2
	invokevirtual	Method scala/actors/remote/Serializer.deserialize:([B)Ljava/lang/Object;
	astore	6
	aload_0
	aload_1
	invokevirtual	Method scala/actors/remote/Locator.node:()Lscala/actors/remote/Node;
	aload_1
	invokevirtual	Method scala/actors/remote/Locator.name:()Lscala/Symbol;
	invokevirtual	Method getOrCreateProxy:(Lscala/actors/remote/Node;Lscala/Symbol;)Lscala/actors/remote/Proxy;
	astore	7
	aload	7
	new	class scala/actors/remote/SendTo
	dup
	aload	4
	aload	6
	aload_3
	invokespecial	Method scala/actors/remote/SendTo."<init>":(Lscala/actors/OutputChannel;Ljava/lang/Object;Lscala/Symbol;)V
	aconst_null
	pop
	aconst_null
	invokevirtual	Method scala/actors/remote/Proxy.send:(Ljava/lang/Object;Lscala/actors/OutputChannel;)V
	goto	l1 // return
	astore	5
	getstatic	Field scala/actors/Debug$.MODULE$:Lscala/actors/Debug$;
	new	class scala/collection/mutable/StringBuilder
	dup
	invokespecial	Method scala/collection/mutable/StringBuilder."<init>":()V
	getstatic	Field scala/Predef$.MODULE$:Lscala/Predef$;
	aload_0
	invokevirtual	Method scala/Predef$.any2stringadd:(Ljava/lang/Object;)Lscala/runtime/StringAdd;
	ldc_w	String : caught 
	invokevirtual	Method scala/runtime/StringAdd.$plus:(Ljava/lang/String;)Ljava/lang/String;
	invokevirtual	Method scala/collection/mutable/StringBuilder.append:(Ljava/lang/Object;)Lscala/collection/mutable/StringBuilder;
	aload	5
	invokevirtual	Method scala/collection/mutable/StringBuilder.append:(Ljava/lang/Object;)Lscala/collection/mutable/StringBuilder;
	invokevirtual	Method scala/collection/mutable/StringBuilder.toString:()Ljava/lang/String;
	invokevirtual	Method scala/actors/Debug$.error:(Ljava/lang/String;)V
l1	return
  Labels:
   	l1 = 91 // return
  Exception table:
   from   to  target type
     0    52    52   Class java/lang/Exception

  LocalVariableTable: 
   Start  Length  Slot  Name   Signature
   0      92      0    this       Lscala/actors/remote/NetKernel;
   15      34      6    msg       Ljava/lang/Object;
   29      20      7    senderProxy       Lscala/actors/remote/Proxy;


public scala.actors.remote.NetKernel(scala.actors.remote.Service);
  Signature: (Lscala/actors/remote/Service;)V
  Code:
   Stack=3, Locals=2, Args_size=2
	aload_0
	aload_1
	putfield	Field service:Lscala/actors/remote/Service;
	aload_0
	invokespecial	Method java/lang/Object."<init>":()V
	aload_0
	new	class scala/collection/mutable/HashMap
	dup
	invokespecial	Method scala/collection/mutable/HashMap."<init>":()V
	putfield	Field actors:Lscala/collection/mutable/HashMap;
	aload_0
	new	class scala/collection/mutable/HashMap
	dup
	invokespecial	Method scala/collection/mutable/HashMap."<init>":()V
	putfield	Field names:Lscala/collection/mutable/HashMap;
	aload_0
	new	class scala/collection/mutable/HashMap
	dup
	invokespecial	Method scala/collection/mutable/HashMap."<init>":()V
	putfield	Field proxies:Lscala/collection/mutable/HashMap;
	return
  Labels:
  LocalVariableTable: 
   Start  Length  Slot  Name   Signature
   0      43      0    this       Lscala/actors/remote/NetKernel;
   0      43      1    service       Lscala/actors/remote/Service;


}

