Compiled from "Proxy.scala"
public class scala.actors.remote.Proxy extends java.lang.Object implements scala.actors.AbstractActor,scala.ScalaObject,java.io.Serializable
  SourceFile: "Proxy.scala"
  ScalaSig: length = 0x5A7
   05 00 FFFFFF81 54 06 09 01 02 FFFFFF84 FFFFFF80 FFFFFF80 FFFFFF80 00 02 08 02
   05 50 72 6F 78 79 0A 02 03 04 01 06 72 65 6D 6F
   74 65 0A 02 05 06 01 06 61 63 74 6F 72 73 0A 01
   07 01 05 73 63 61 6C 61 13 04 00 09 11 15 10 02
   0A 0F 0D 01 0B 0A 02 0C 0D 01 04 6C 61 6E 67 0A
   01 0E 01 04 6A 61 76 61 09 02 10 0B 02 06 4F 62
   6A 65 63 74 10 02 12 13 0D 01 04 09 02 14 04 02
   0D 41 62 73 74 72 61 63 74 41 63 74 6F 72 10 02
   16 17 0D 01 06 09 02 18 06 02 0B 53 63 61 6C 61
   4F 62 6A 65 63 74 08 08 1A 00 FFFFFF82 FFFFFF80 FFFFFFA0 FFFFFF80 04 1C
   01 04 6E 6F 64 65 03 00 10 02 1D 1E 0D 01 02 09
   02 1F 02 02 04 4E 6F 64 65 08 08 21 00 FFFFFF82 FFFFFF80 FFFFFFA0
   FFFFFF80 04 22 01 04 6E 61 6D 65 10 02 16 23 09 02 24
   06 02 06 53 79 6D 62 6F 6C 08 08 26 00 FFFFFF82 FFFFFFC0 FFFFFF80
   FFFFFF84 00 27 01 06 6B 65 72 6E 65 6C 15 01 28 10 02
   1D 29 09 02 2A 02 02 09 4E 65 74 4B 65 72 6E 65
   6C 28 02 25 2C 10 02 16 2D 09 02 2E 06 02 09 74
   72 61 6E 73 69 65 6E 74 08 08 30 00 FFFFFF82 FFFFFFC0 FFFFFF80 FFFFFF84
   00 31 01 0A 6B 65 72 6E 65 6C 5F 24 65 71 14 02
   32 35 10 02 16 33 09 02 34 06 02 04 55 6E 69 74
   08 07 36 2F FFFFFF81 FFFFFF80 FFFFFFC0 00 28 01 03 78 24 31 28 02
   2F 2C 08 08 39 00 FFFFFF82 FFFFFF80 FFFFFFA0 FFFFFFA0 04 28 01 07 6B 65
   72 6E 65 6C 20 28 02 38 2C 08 05 3C 00 FFFFFF84 00 3D
   01 06 3C 69 6E 69 74 3E 14 04 3E 3F 40 41 10 02
   1D 00 08 05 1A 3B FFFFFFC0 00 1C 08 05 21 3B FFFFFFC0 00 22
   08 05 26 3B FFFFFFC0 00 28 28 02 41 2C 08 08 44 00 FFFFFFC0
   FFFFFF80 FFFFFF84 00 02 45 01 03 64 65 6C 15 01 46 10 02 12
   47 09 02 48 04 02 05 41 63 74 6F 72 28 02 43 2C
   08 08 4B 00 FFFFFFC0 FFFFFF80 FFFFFF84 00 02 4C 01 07 64 65 6C 5F
   24 65 71 14 02 32 4D 08 07 36 4A FFFFFF81 FFFFFF80 FFFFFFC0 00 46
   28 02 4A 2C 08 06 50 00 FFFFFFA0 FFFFFFA0 04 46 01 04 64 65
   6C 20 28 02 4F 2C 08 05 53 00 FFFFFF84 04 54 01 0B 77
   72 69 74 65 4F 62 6A 65 63 74 14 02 32 55 08 05
   56 52 FFFFFFC0 00 57 01 03 6F 75 74 10 02 58 5B 0D 01
   59 0A 02 5A 0D 01 02 69 6F 09 02 5C 59 02 12 4F
   62 6A 65 63 74 4F 75 74 70 75 74 53 74 72 65 61
   6D 28 03 52 5E 61 10 02 16 5F 09 02 60 06 02 06
   74 68 72 6F 77 73 23 01 62 10 02 58 63 09 02 64
   59 02 0B 49 4F 45 78 63 65 70 74 69 6F 6E 08 05
   66 00 FFFFFF84 04 67 01 0A 72 65 61 64 4F 62 6A 65 63
   74 14 02 32 68 08 05 69 65 FFFFFFC0 00 6A 01 02 69 6E
   10 02 58 6B 09 02 6C 59 02 11 4F 62 6A 65 63 74
   49 6E 70 75 74 53 74 72 65 61 6D 28 03 65 5E 61
   28 03 65 5E 6F 23 01 70 10 02 0A 71 09 02 72 0B
   02 16 43 6C 61 73 73 4E 6F 74 46 6F 75 6E 64 45
   78 63 65 70 74 69 6F 6E 08 05 74 00 FFFFFF84 04 75 01
   0D 73 74 61 72 74 44 65 6C 65 67 61 74 65 14 01
   32 08 05 77 00 FFFFFF84 04 75 01 0B 73 65 74 75 70 4B
   65 72 6E 65 6C 08 05 79 00 FFFFFF84 00 7A 01 05 24 62
   61 6E 67 14 02 32 7B 08 05 7C 78 FFFFFFC0 00 7D 01 03
   6D 73 67 10 02 16 7E 09 02 7F 06 02 03 41 6E 79
   08 07 FFFFFF81 01 00 FFFFFF84 00 FFFFFF81 02 01 04 73 65 6E 64 14
   05 32 FFFFFF81 03 FFFFFF81 04 08 06 7C FFFFFF81 00 FFFFFFC0 00 7D 08 08
   FFFFFF81 05 FFFFFF81 00 FFFFFFC0 00 FFFFFF81 06 01 07 72 65 70 6C 79 43
   68 10 04 12 FFFFFF81 07 7D 09 03 FFFFFF81 08 04 02 0D 4F 75
   74 70 75 74 43 68 61 6E 6E 65 6C 08 07 FFFFFF81 0A 00
   FFFFFF84 00 FFFFFF81 0B 01 07 66 6F 72 77 61 72 64 14 03 32
   FFFFFF81 0C 08 06 7C FFFFFF81 09 FFFFFFC0 00 7D 08 06 FFFFFF81 0E 00 FFFFFF84
   00 45 01 08 72 65 63 65 69 76 65 72 08 07 FFFFFF81 10
   00 FFFFFF84 00 FFFFFF81 11 01 0B 24 62 61 6E 67 24 71 6D 61
   72 6B 14 03 7D FFFFFF81 12 08 06 7C FFFFFF81 0F FFFFFFC0 00 7D 08
   07 FFFFFF81 10 00 FFFFFF84 00 FFFFFF81 14 14 06 FFFFFF81 15 FFFFFF81 18 FFFFFF81 1D
   10 04 16 FFFFFF81 16 7D 09 03 FFFFFF81 17 06 02 06 4F 70 74
   69 6F 6E 08 08 FFFFFF81 19 FFFFFF81 13 FFFFFFC0 00 FFFFFF81 1A 01 04 6D
   73 65 63 10 03 16 FFFFFF81 1B 09 03 FFFFFF81 1C 06 02 04 4C
   6F 6E 67 08 06 7C FFFFFF81 13 FFFFFFC0 00 7D 08 07 FFFFFF81 1F 00
   FFFFFF84 20 FFFFFF81 20 01 0A 24 62 61 6E 67 24 62 61 6E 67
   14 04 FFFFFF81 21 FFFFFF81 24 10 04 12 FFFFFF81 22 7D 09 03 FFFFFF81 23
   04 02 06 46 75 74 75 72 65 08 06 7C FFFFFF81 1E FFFFFFC0 00
   7D 08 07 FFFFFF81 1F 00 FFFFFF84 20 FFFFFF81 26 15 04 FFFFFF81 27 FFFFFF81 2B
   14 06 FFFFFF81 28 FFFFFF81 31 FFFFFF81 32 10 05 12 FFFFFF81 22 FFFFFF81 29 10
   04 FFFFFF81 2A FFFFFF81 2B 0C 00 04 0B FFFFFF81 2C FFFFFF81 25 FFFFFF84 FFFFFF80 FFFFFF80
   FFFFFFC2 00 FFFFFF81 2D 02 01 41 11 03 FFFFFF81 2E 7D 10 03 16 FFFFFF81
   2F 09 03 FFFFFF81 30 06 02 07 4E 6F 74 68 69 6E 67 08
   06 7C FFFFFF81 25 FFFFFFC0 00 7D 08 08 FFFFFF81 33 FFFFFF81 25 FFFFFFC0 00 FFFFFF81
   34 01 01 66 10 06 16 FFFFFF81 35 7D FFFFFF81 29 09 03 FFFFFF81 36
   06 02 0F 50 61 72 74 69 61 6C 46 75 6E 63 74 69
   6F 6E 08 07 FFFFFF81 38 00 FFFFFF84 00 FFFFFF81 39 01 06 6C 69 6E
   6B 54 6F 14 03 32 FFFFFF81 3A 08 07 FFFFFF81 3B FFFFFF81 37 FFFFFFC0 00
   11 01 02 74 6F 08 07 FFFFFF81 3D 00 FFFFFF84 00 FFFFFF81 3E 01 0A
   75 6E 6C 69 6E 6B 46 72 6F 6D 14 03 32 FFFFFF81 3F 08
   07 FFFFFF81 40 FFFFFF81 3C FFFFFFC0 00 11 01 04 66 72 6F 6D 08 07
   FFFFFF81 42 00 FFFFFF84 00 FFFFFF81 43 01 04 65 78 69 74 14 05 32
   FFFFFF81 44 FFFFFF81 45 08 07 FFFFFF81 40 FFFFFF81 41 FFFFFFC0 00 11 08 08 FFFFFF81
   46 FFFFFF81 41 FFFFFFC0 00 FFFFFF81 47 01 06 72 65 61 73 6F 6E 10
   03 16 FFFFFF81 48 09 03 FFFFFF81 49 06 02 06 41 6E 79 52 65
   66 08 07 FFFFFF81 4B 00 FFFFFF84 20 FFFFFF81 4C 01 08 74 6F 53 74
   72 69 6E 67 14 02 FFFFFF81 4D 10 03 0A FFFFFF81 4E 09 03 FFFFFF81
   4F 0B 02 06 53 74 72 69 6E 67 28 03 00 FFFFFF81 51 10
   03 16 FFFFFF81 52 09 03 FFFFFF81 53 06 02 0C 73 65 72 69 61
   6C 69 7A 61 62 6C 65 
  minor version: 0
  major version: 49
  Constant pool:
const #1 = Asciz	SourceFile;
const #2 = Asciz	Proxy.scala;
const #3 = Asciz	exiting;
const #4 = Asciz	Z;
const #5 = Asciz	del;
const #6 = Asciz	Lscala/actors/Actor;;
const #7 = Asciz	kernel;
const #8 = Asciz	Lscala/actors/remote/NetKernel;;
const #9 = Asciz	name;
const #10 = Asciz	Lscala/Symbol;;
const #11 = Asciz	node;
const #12 = Asciz	Lscala/actors/remote/Node;;
const #13 = Asciz	<init>;
const #14 = Asciz	(Lscala/actors/remote/Node;Lscala/Symbol;Lscala/actors/remote/NetKernel;)V;
const #15 = Asciz	Code;
const #16 = Asciz	LineNumberTable;
const #17 = Asciz	scala/actors/remote/Proxy;
const #18 = class	#17;	//  scala/actors/remote/Proxy
const #19 = NameAndType	#11:#12;//  node:Lscala/actors/remote/Node;
const #20 = Field	#18.#19;	//  scala/actors/remote/Proxy.node:Lscala/actors/remote/Node;
const #21 = NameAndType	#9:#10;//  name:Lscala/Symbol;
const #22 = Field	#18.#21;	//  scala/actors/remote/Proxy.name:Lscala/Symbol;
const #23 = NameAndType	#7:#8;//  kernel:Lscala/actors/remote/NetKernel;
const #24 = Field	#18.#23;	//  scala/actors/remote/Proxy.kernel:Lscala/actors/remote/NetKernel;
const #25 = Asciz	java/lang/Object;
const #26 = class	#25;	//  java/lang/Object
const #27 = Asciz	()V;
const #28 = NameAndType	#13:#27;//  "<init>":()V
const #29 = Method	#26.#28;	//  java/lang/Object."<init>":()V
const #30 = Asciz	scala/actors/Replyable$class;
const #31 = class	#30;	//  scala/actors/Replyable$class
const #32 = Asciz	$init$;
const #33 = Asciz	(Lscala/actors/Replyable;)V;
const #34 = NameAndType	#32:#33;//  $init$:(Lscala/actors/Replyable;)V
const #35 = Method	#31.#34;	//  scala/actors/Replyable$class.$init$:(Lscala/actors/Replyable;)V
const #36 = Asciz	scala/actors/AbstractActor$class;
const #37 = class	#36;	//  scala/actors/AbstractActor$class
const #38 = Asciz	(Lscala/actors/AbstractActor;)V;
const #39 = NameAndType	#32:#38;//  $init$:(Lscala/actors/AbstractActor;)V
const #40 = Method	#37.#39;	//  scala/actors/AbstractActor$class.$init$:(Lscala/actors/AbstractActor;)V
const #41 = NameAndType	#5:#6;//  del:Lscala/actors/Actor;
const #42 = Field	#18.#41;	//  scala/actors/remote/Proxy.del:Lscala/actors/Actor;
const #43 = Asciz	startDelegate;
const #44 = NameAndType	#43:#27;//  startDelegate:()V
const #45 = Method	#18.#44;	//  scala/actors/remote/Proxy.startDelegate:()V
const #46 = Asciz	this;
const #47 = Asciz	Lscala/actors/remote/Proxy;;
const #48 = Asciz	LocalVariableTable;
const #49 = Asciz	receiver;
const #50 = Asciz	()Lscala/actors/Reactor;;
const #51 = Asciz	()Lscala/actors/Actor;;
const #52 = NameAndType	#49:#51;//  receiver:()Lscala/actors/Actor;
const #53 = Method	#18.#52;	//  scala/actors/remote/Proxy.receiver:()Lscala/actors/Actor;
const #54 = Asciz	$bang$bang;
const #55 = Asciz	(Ljava/lang/Object;)Lscala/Function0;;
const #56 = Asciz	(Ljava/lang/Object;)Lscala/actors/Future;;
const #57 = NameAndType	#54:#56;//  $bang$bang:(Ljava/lang/Object;)Lscala/actors/Future;
const #58 = Method	#18.#57;	//  scala/actors/remote/Proxy.$bang$bang:(Ljava/lang/Object;)Lscala/actors/Future;
const #59 = Asciz	msg;
const #60 = Asciz	Ljava/lang/Object;;
const #61 = Asciz	(Ljava/lang/Object;Lscala/PartialFunction;)Lscala/Function0;;
const #62 = Asciz	(Ljava/lang/Object;Lscala/PartialFunction;)Lscala/actors/Future;;
const #63 = NameAndType	#54:#62;//  $bang$bang:(Ljava/lang/Object;Lscala/PartialFunction;)Lscala/actors/Future;
const #64 = Method	#18.#63;	//  scala/actors/remote/Proxy.$bang$bang:(Ljava/lang/Object;Lscala/PartialFunction;)Lscala/actors/Future;
const #65 = Asciz	f;
const #66 = Asciz	Lscala/PartialFunction;;
const #67 = Asciz	toString;
const #68 = Asciz	()Ljava/lang/String;;
const #69 = Asciz	scala/collection/mutable/StringBuilder;
const #70 = class	#69;	//  scala/collection/mutable/StringBuilder
const #71 = Method	#70.#28;	//  scala/collection/mutable/StringBuilder."<init>":()V
const #72 = Asciz	scala/Predef$;
const #73 = class	#72;	//  scala/Predef$
const #74 = Asciz	MODULE$;
const #75 = Asciz	Lscala/Predef$;;
const #76 = NameAndType	#74:#75;//  MODULE$:Lscala/Predef$;
const #77 = Field	#73.#76;	//  scala/Predef$.MODULE$:Lscala/Predef$;
const #78 = Asciz	any2stringadd;
const #79 = Asciz	(Ljava/lang/Object;)Lscala/runtime/StringAdd;;
const #80 = NameAndType	#78:#79;//  any2stringadd:(Ljava/lang/Object;)Lscala/runtime/StringAdd;
const #81 = Method	#73.#80;	//  scala/Predef$.any2stringadd:(Ljava/lang/Object;)Lscala/runtime/StringAdd;
const #82 = Asciz	@;
const #83 = String	#82;	//  @
const #84 = Asciz	scala/runtime/StringAdd;
const #85 = class	#84;	//  scala/runtime/StringAdd
const #86 = Asciz	$plus;
const #87 = Asciz	(Ljava/lang/String;)Ljava/lang/String;;
const #88 = NameAndType	#86:#87;//  $plus:(Ljava/lang/String;)Ljava/lang/String;
const #89 = Method	#85.#88;	//  scala/runtime/StringAdd.$plus:(Ljava/lang/String;)Ljava/lang/String;
const #90 = Asciz	append;
const #91 = Asciz	(Ljava/lang/Object;)Lscala/collection/mutable/StringBuilder;;
const #92 = NameAndType	#90:#91;//  append:(Ljava/lang/Object;)Lscala/collection/mutable/StringBuilder;
const #93 = Method	#70.#92;	//  scala/collection/mutable/StringBuilder.append:(Ljava/lang/Object;)Lscala/collection/mutable/StringBuilder;
const #94 = NameAndType	#67:#68;//  toString:()Ljava/lang/String;
const #95 = Method	#70.#94;	//  scala/collection/mutable/StringBuilder.toString:()Ljava/lang/String;
const #96 = Asciz	exit;
const #97 = Asciz	(Lscala/actors/AbstractActor;Ljava/lang/Object;)V;
const #98 = NameAndType	#5:#51;//  del:()Lscala/actors/Actor;
const #99 = Method	#18.#98;	//  scala/actors/remote/Proxy.del:()Lscala/actors/Actor;
const #100 = Asciz	scala/actors/remote/Apply0;
const #101 = class	#100;	//  scala/actors/remote/Apply0
const #102 = Asciz	scala/actors/remote/ExitFun;
const #103 = class	#102;	//  scala/actors/remote/ExitFun
const #104 = Asciz	(Ljava/lang/Object;)V;
const #105 = NameAndType	#13:#104;//  "<init>":(Ljava/lang/Object;)V
const #106 = Method	#103.#105;	//  scala/actors/remote/ExitFun."<init>":(Ljava/lang/Object;)V
const #107 = Asciz	(Lscala/Function2;)V;
const #108 = NameAndType	#13:#107;//  "<init>":(Lscala/Function2;)V
const #109 = Method	#101.#108;	//  scala/actors/remote/Apply0."<init>":(Lscala/Function2;)V
const #110 = Asciz	scala/actors/ReplyReactor;
const #111 = class	#110;	//  scala/actors/ReplyReactor
const #112 = Asciz	$bang;
const #113 = NameAndType	#112:#104;//  $bang:(Ljava/lang/Object;)V
const #114 = InterfaceMethod	#111.#113;	//  scala/actors/ReplyReactor.$bang:(Ljava/lang/Object;)V
const #115 = Asciz	from;
const #116 = Asciz	Lscala/actors/AbstractActor;;
const #117 = Asciz	reason;
const #118 = Asciz	unlinkFrom;
const #119 = Asciz	scala/actors/remote/UnlinkFromFun;
const #120 = class	#119;	//  scala/actors/remote/UnlinkFromFun
const #121 = Method	#120.#28;	//  scala/actors/remote/UnlinkFromFun."<init>":()V
const #122 = Asciz	linkTo;
const #123 = Asciz	scala/actors/remote/LinkToFun;
const #124 = class	#123;	//  scala/actors/remote/LinkToFun
const #125 = Method	#124.#28;	//  scala/actors/remote/LinkToFun."<init>":()V
const #126 = Asciz	to;
const #127 = Asciz	scala/actors/ReplyableActor;
const #128 = class	#127;	//  scala/actors/ReplyableActor
const #129 = InterfaceMethod	#128.#63;	//  scala/actors/ReplyableActor.$bang$bang:(Ljava/lang/Object;Lscala/PartialFunction;)Lscala/actors/Future;
const #130 = Asciz	<A:Ljava/lang/Object;>(Ljava/lang/Object;Lscala/PartialFunction<Ljava/lang/Object;TA;>;)Lscala/actors/Future<TA;>;;
const #131 = Asciz	Signature;
const #132 = InterfaceMethod	#128.#57;	//  scala/actors/ReplyableActor.$bang$bang:(Ljava/lang/Object;)Lscala/actors/Future;
const #133 = Asciz	(Ljava/lang/Object;)Lscala/actors/Future<Ljava/lang/Object;>;;
const #134 = Asciz	$bang$qmark;
const #135 = Asciz	(JLjava/lang/Object;)Lscala/Option;;
const #136 = NameAndType	#134:#135;//  $bang$qmark:(JLjava/lang/Object;)Lscala/Option;
const #137 = InterfaceMethod	#128.#136;	//  scala/actors/ReplyableActor.$bang$qmark:(JLjava/lang/Object;)Lscala/Option;
const #138 = Asciz	msec;
const #139 = Asciz	J;
const #140 = Asciz	(JLjava/lang/Object;)Lscala/Option<Ljava/lang/Object;>;;
const #141 = Asciz	(Ljava/lang/Object;)Ljava/lang/Object;;
const #142 = NameAndType	#134:#141;//  $bang$qmark:(Ljava/lang/Object;)Ljava/lang/Object;
const #143 = InterfaceMethod	#128.#142;	//  scala/actors/ReplyableActor.$bang$qmark:(Ljava/lang/Object;)Ljava/lang/Object;
const #144 = Asciz	forward;
const #145 = NameAndType	#144:#104;//  forward:(Ljava/lang/Object;)V
const #146 = InterfaceMethod	#111.#145;	//  scala/actors/ReplyReactor.forward:(Ljava/lang/Object;)V
const #147 = Asciz	send;
const #148 = Asciz	(Ljava/lang/Object;Lscala/actors/OutputChannel;)V;
const #149 = Asciz	scala/actors/Reactor;
const #150 = class	#149;	//  scala/actors/Reactor
const #151 = NameAndType	#147:#148;//  send:(Ljava/lang/Object;Lscala/actors/OutputChannel;)V
const #152 = InterfaceMethod	#150.#151;	//  scala/actors/Reactor.send:(Ljava/lang/Object;Lscala/actors/OutputChannel;)V
const #153 = Asciz	replyCh;
const #154 = Asciz	Lscala/actors/OutputChannel;;
const #155 = Asciz	(Ljava/lang/Object;Lscala/actors/OutputChannel<Ljava/lang/Object;>;)V;
const #156 = Asciz	setupKernel;
const #157 = Asciz	scala/actors/remote/RemoteActor$;
const #158 = class	#157;	//  scala/actors/remote/RemoteActor$
const #159 = Asciz	Lscala/actors/remote/RemoteActor$;;
const #160 = NameAndType	#74:#159;//  MODULE$:Lscala/actors/remote/RemoteActor$;
const #161 = Field	#158.#160;	//  scala/actors/remote/RemoteActor$.MODULE$:Lscala/actors/remote/RemoteActor$;
const #162 = Asciz	someKernel;
const #163 = Asciz	()Lscala/actors/remote/NetKernel;;
const #164 = NameAndType	#162:#163;//  someKernel:()Lscala/actors/remote/NetKernel;
const #165 = Method	#158.#164;	//  scala/actors/remote/RemoteActor$.someKernel:()Lscala/actors/remote/NetKernel;
const #166 = Asciz	kernel_$eq;
const #167 = Asciz	(Lscala/actors/remote/NetKernel;)V;
const #168 = NameAndType	#166:#167;//  kernel_$eq:(Lscala/actors/remote/NetKernel;)V
const #169 = Method	#18.#168;	//  scala/actors/remote/Proxy.kernel_$eq:(Lscala/actors/remote/NetKernel;)V
const #170 = NameAndType	#7:#163;//  kernel:()Lscala/actors/remote/NetKernel;
const #171 = Method	#18.#170;	//  scala/actors/remote/Proxy.kernel:()Lscala/actors/remote/NetKernel;
const #172 = Asciz	scala/actors/remote/NetKernel;
const #173 = class	#172;	//  scala/actors/remote/NetKernel
const #174 = Asciz	registerProxy;
const #175 = Asciz	(Lscala/actors/remote/Node;Lscala/Symbol;Lscala/actors/remote/Proxy;)V;
const #176 = NameAndType	#174:#175;//  registerProxy:(Lscala/actors/remote/Node;Lscala/Symbol;Lscala/actors/remote/Proxy;)V
const #177 = Method	#173.#176;	//  scala/actors/remote/NetKernel.registerProxy:(Lscala/actors/remote/Node;Lscala/Symbol;Lscala/actors/remote/Proxy;)V
const #178 = Asciz	scala/actors/remote/DelegateActor;
const #179 = class	#178;	//  scala/actors/remote/DelegateActor
const #180 = Asciz	(Lscala/actors/remote/Proxy;Lscala/actors/remote/Node;Lscala/Symbol;Lscala/actors/remote/NetKernel;)V;
const #181 = NameAndType	#13:#180;//  "<init>":(Lscala/actors/remote/Proxy;Lscala/actors/remote/Node;Lscala/Symbol;Lscala/actors/remote/NetKernel;)V
const #182 = Method	#179.#181;	//  scala/actors/remote/DelegateActor."<init>":(Lscala/actors/remote/Proxy;Lscala/actors/remote/Node;Lscala/Symbol;Lscala/actors/remote/NetKernel;)V
const #183 = Asciz	del_$eq;
const #184 = Asciz	(Lscala/actors/Actor;)V;
const #185 = NameAndType	#183:#184;//  del_$eq:(Lscala/actors/Actor;)V
const #186 = Method	#18.#185;	//  scala/actors/remote/Proxy.del_$eq:(Lscala/actors/Actor;)V
const #187 = Asciz	scala/actors/Actor;
const #188 = class	#187;	//  scala/actors/Actor
const #189 = Asciz	start;
const #190 = NameAndType	#189:#51;//  start:()Lscala/actors/Actor;
const #191 = InterfaceMethod	#188.#190;	//  scala/actors/Actor.start:()Lscala/actors/Actor;
const #192 = Asciz	readObject;
const #193 = Asciz	(Ljava/io/ObjectInputStream;)V;
const #194 = Asciz	java/io/ObjectInputStream;
const #195 = class	#194;	//  java/io/ObjectInputStream
const #196 = Asciz	defaultReadObject;
const #197 = NameAndType	#196:#27;//  defaultReadObject:()V
const #198 = Method	#195.#197;	//  java/io/ObjectInputStream.defaultReadObject:()V
const #199 = NameAndType	#156:#27;//  setupKernel:()V
const #200 = Method	#18.#199;	//  scala/actors/remote/Proxy.setupKernel:()V
const #201 = Asciz	in;
const #202 = Asciz	Ljava/io/ObjectInputStream;;
const #203 = Asciz	java/lang/ClassNotFoundException;
const #204 = class	#203;	//  java/lang/ClassNotFoundException
const #205 = Asciz	java/io/IOException;
const #206 = class	#205;	//  java/io/IOException
const #207 = Asciz	Exceptions;
const #208 = Asciz	writeObject;
const #209 = Asciz	(Ljava/io/ObjectOutputStream;)V;
const #210 = Asciz	java/io/ObjectOutputStream;
const #211 = class	#210;	//  java/io/ObjectOutputStream
const #212 = Asciz	defaultWriteObject;
const #213 = NameAndType	#212:#27;//  defaultWriteObject:()V
const #214 = Method	#211.#213;	//  java/io/ObjectOutputStream.defaultWriteObject:()V
const #215 = Asciz	out;
const #216 = Asciz	Ljava/io/ObjectOutputStream;;
const #217 = Asciz	exiting_$eq;
const #218 = Asciz	(Z)V;
const #219 = NameAndType	#3:#4;//  exiting:Z
const #220 = Field	#18.#219;	//  scala/actors/remote/Proxy.exiting:Z
const #221 = Asciz	()Z;
const #222 = Asciz	ScalaSig;
const #223 = Asciz	scala/actors/AbstractActor;
const #224 = class	#223;	//  scala/actors/AbstractActor
const #225 = Asciz	scala/ScalaObject;
const #226 = class	#225;	//  scala/ScalaObject
const #227 = Asciz	java/io/Serializable;
const #228 = class	#227;	//  java/io/Serializable

{
public scala.actors.remote.Proxy(scala.actors.remote.Node, scala.Symbol, scala.actors.remote.NetKernel);
  Code:
   Stack=2, Locals=4, Args_size=4
   0:	aload_0
   1:	aload_1
   2:	putfield	#20; //Field node:Lscala/actors/remote/Node;
   5:	aload_0
   6:	aload_2
   7:	putfield	#22; //Field name:Lscala/Symbol;
   10:	aload_0
   11:	aload_3
   12:	putfield	#24; //Field kernel:Lscala/actors/remote/NetKernel;
   15:	aload_0
   16:	invokespecial	#29; //Method java/lang/Object."<init>":()V
   19:	aload_0
   20:	invokestatic	#35; //Method scala/actors/Replyable$class.$init$:(Lscala/actors/Replyable;)V
   23:	aload_0
   24:	invokestatic	#40; //Method scala/actors/AbstractActor$class.$init$:(Lscala/actors/AbstractActor;)V
   27:	aload_0
   28:	aconst_null
   29:	pop
   30:	aconst_null
   31:	putfield	#42; //Field del:Lscala/actors/Actor;
   34:	aload_0
   35:	invokespecial	#45; //Method startDelegate:()V
   38:	return
  LineNumberTable: 
   line 20: 0
   line 24: 27
   line 25: 34

  LocalVariableTable: 
   Start  Length  Slot  Name   Signature
   0      39      0    this       Lscala/actors/remote/Proxy;
   0      39      1    node       Lscala/actors/remote/Node;
   0      39      2    name       Lscala/Symbol;
   0      39      3    kernel       Lscala/actors/remote/NetKernel;


public scala.actors.Reactor receiver();
  Code:
   Stack=1, Locals=1, Args_size=1
   0:	aload_0
   1:	invokevirtual	#53; //Method receiver:()Lscala/actors/Actor;
   4:	areturn
  LineNumberTable: 
   line 20: 0


public scala.Function0 $bang$bang(java.lang.Object);
  Code:
   Stack=2, Locals=2, Args_size=2
   0:	aload_0
   1:	aload_1
   2:	invokevirtual	#58; //Method $bang$bang:(Ljava/lang/Object;)Lscala/actors/Future;
   5:	areturn
  LineNumberTable: 
   line 20: 0

  LocalVariableTable: 
   Start  Length  Slot  Name   Signature
   0      6      0    this       Lscala/actors/remote/Proxy;
   0      6      1    msg       Ljava/lang/Object;


public scala.Function0 $bang$bang(java.lang.Object, scala.PartialFunction);
  Code:
   Stack=3, Locals=3, Args_size=3
   0:	aload_0
   1:	aload_1
   2:	aload_2
   3:	invokevirtual	#64; //Method $bang$bang:(Ljava/lang/Object;Lscala/PartialFunction;)Lscala/actors/Future;
   6:	areturn
  LineNumberTable: 
   line 20: 0

  LocalVariableTable: 
   Start  Length  Slot  Name   Signature
   0      7      0    this       Lscala/actors/remote/Proxy;
   0      7      1    msg       Ljava/lang/Object;
   0      7      2    f       Lscala/PartialFunction;


public java.lang.String toString();
  Code:
   Stack=3, Locals=1, Args_size=1
   0:	new	#70; //class scala/collection/mutable/StringBuilder
   3:	dup
   4:	invokespecial	#71; //Method scala/collection/mutable/StringBuilder."<init>":()V
   7:	getstatic	#77; //Field scala/Predef$.MODULE$:Lscala/Predef$;
   10:	aload_0
   11:	getfield	#22; //Field name:Lscala/Symbol;
   14:	invokevirtual	#81; //Method scala/Predef$.any2stringadd:(Ljava/lang/Object;)Lscala/runtime/StringAdd;
   17:	ldc	#83; //String @
   19:	invokevirtual	#89; //Method scala/runtime/StringAdd.$plus:(Ljava/lang/String;)Ljava/lang/String;
   22:	invokevirtual	#93; //Method scala/collection/mutable/StringBuilder.append:(Ljava/lang/Object;)Lscala/collection/mutable/StringBuilder;
   25:	aload_0
   26:	getfield	#20; //Field node:Lscala/actors/remote/Node;
   29:	invokevirtual	#93; //Method scala/collection/mutable/StringBuilder.append:(Ljava/lang/Object;)Lscala/collection/mutable/StringBuilder;
   32:	invokevirtual	#95; //Method scala/collection/mutable/StringBuilder.toString:()Ljava/lang/String;
   35:	areturn
  LineNumberTable: 
   line 83: 0


public void exit(scala.actors.AbstractActor, java.lang.Object);
  Code:
   Stack=6, Locals=3, Args_size=3
   0:	aload_0
   1:	invokevirtual	#99; //Method del:()Lscala/actors/Actor;
   4:	new	#101; //class scala/actors/remote/Apply0
   7:	dup
   8:	new	#103; //class scala/actors/remote/ExitFun
   11:	dup
   12:	aload_2
   13:	invokespecial	#106; //Method scala/actors/remote/ExitFun."<init>":(Ljava/lang/Object;)V
   16:	invokespecial	#109; //Method scala/actors/remote/Apply0."<init>":(Lscala/Function2;)V
   19:	invokeinterface	#114,  2; //InterfaceMethod scala/actors/ReplyReactor.$bang:(Ljava/lang/Object;)V
   24:	return
  LineNumberTable: 
   line 80: 0

  LocalVariableTable: 
   Start  Length  Slot  Name   Signature
   0      25      0    this       Lscala/actors/remote/Proxy;
   0      25      1    from       Lscala/actors/AbstractActor;
   0      25      2    reason       Ljava/lang/Object;


public void unlinkFrom(scala.actors.AbstractActor);
  Code:
   Stack=5, Locals=2, Args_size=2
   0:	aload_0
   1:	invokevirtual	#99; //Method del:()Lscala/actors/Actor;
   4:	new	#101; //class scala/actors/remote/Apply0
   7:	dup
   8:	new	#120; //class scala/actors/remote/UnlinkFromFun
   11:	dup
   12:	invokespecial	#121; //Method scala/actors/remote/UnlinkFromFun."<init>":()V
   15:	invokespecial	#109; //Method scala/actors/remote/Apply0."<init>":(Lscala/Function2;)V
   18:	invokeinterface	#114,  2; //InterfaceMethod scala/actors/ReplyReactor.$bang:(Ljava/lang/Object;)V
   23:	return
  LineNumberTable: 
   line 77: 0

  LocalVariableTable: 
   Start  Length  Slot  Name   Signature
   0      24      0    this       Lscala/actors/remote/Proxy;
   0      24      1    from       Lscala/actors/AbstractActor;


public void linkTo(scala.actors.AbstractActor);
  Code:
   Stack=5, Locals=2, Args_size=2
   0:	aload_0
   1:	invokevirtual	#99; //Method del:()Lscala/actors/Actor;
   4:	new	#101; //class scala/actors/remote/Apply0
   7:	dup
   8:	new	#124; //class scala/actors/remote/LinkToFun
   11:	dup
   12:	invokespecial	#125; //Method scala/actors/remote/LinkToFun."<init>":()V
   15:	invokespecial	#109; //Method scala/actors/remote/Apply0."<init>":(Lscala/Function2;)V
   18:	invokeinterface	#114,  2; //InterfaceMethod scala/actors/ReplyReactor.$bang:(Ljava/lang/Object;)V
   23:	return
  LineNumberTable: 
   line 74: 0

  LocalVariableTable: 
   Start  Length  Slot  Name   Signature
   0      24      0    this       Lscala/actors/remote/Proxy;
   0      24      1    to       Lscala/actors/AbstractActor;


public scala.actors.Future $bang$bang(java.lang.Object, scala.PartialFunction);
  Code:
   Stack=3, Locals=3, Args_size=3
   0:	aload_0
   1:	invokevirtual	#99; //Method del:()Lscala/actors/Actor;
   4:	aload_1
   5:	aload_2
   6:	invokeinterface	#129,  3; //InterfaceMethod scala/actors/ReplyableActor.$bang$bang:(Ljava/lang/Object;Lscala/PartialFunction;)Lscala/actors/Future;
   11:	areturn
  LineNumberTable: 
   line 71: 0

  LocalVariableTable: 
   Start  Length  Slot  Name   Signature
   0      12      0    this       Lscala/actors/remote/Proxy;
   0      12      1    msg       Ljava/lang/Object;
   0      12      2    f       Lscala/PartialFunction;

  Signature: length = 0x2
   00 FFFFFF82 

public scala.actors.Future $bang$bang(java.lang.Object);
  Code:
   Stack=2, Locals=2, Args_size=2
   0:	aload_0
   1:	invokevirtual	#99; //Method del:()Lscala/actors/Actor;
   4:	aload_1
   5:	invokeinterface	#132,  2; //InterfaceMethod scala/actors/ReplyableActor.$bang$bang:(Ljava/lang/Object;)Lscala/actors/Future;
   10:	areturn
  LineNumberTable: 
   line 68: 0

  LocalVariableTable: 
   Start  Length  Slot  Name   Signature
   0      11      0    this       Lscala/actors/remote/Proxy;
   0      11      1    msg       Ljava/lang/Object;

  Signature: length = 0x2
   00 FFFFFF85 

public scala.Option $bang$qmark(long, java.lang.Object);
  Code:
   Stack=4, Locals=4, Args_size=3
   0:	aload_0
   1:	invokevirtual	#99; //Method del:()Lscala/actors/Actor;
   4:	lload_1
   5:	aload_3
   6:	invokeinterface	#137,  4; //InterfaceMethod scala/actors/ReplyableActor.$bang$qmark:(JLjava/lang/Object;)Lscala/Option;
   11:	areturn
  LineNumberTable: 
   line 65: 0

  LocalVariableTable: 
   Start  Length  Slot  Name   Signature
   0      12      0    this       Lscala/actors/remote/Proxy;
   0      12      1    msec       J
   0      12      3    msg       Ljava/lang/Object;

  Signature: length = 0x2
   00 FFFFFF8C 

public java.lang.Object $bang$qmark(java.lang.Object);
  Code:
   Stack=2, Locals=2, Args_size=2
   0:	aload_0
   1:	invokevirtual	#99; //Method del:()Lscala/actors/Actor;
   4:	aload_1
   5:	invokeinterface	#143,  2; //InterfaceMethod scala/actors/ReplyableActor.$bang$qmark:(Ljava/lang/Object;)Ljava/lang/Object;
   10:	areturn
  LineNumberTable: 
   line 62: 0

  LocalVariableTable: 
   Start  Length  Slot  Name   Signature
   0      11      0    this       Lscala/actors/remote/Proxy;
   0      11      1    msg       Ljava/lang/Object;


public scala.actors.Actor receiver();
  Code:
   Stack=1, Locals=1, Args_size=1
   0:	aload_0
   1:	invokevirtual	#99; //Method del:()Lscala/actors/Actor;
   4:	areturn
  LineNumberTable: 
   line 59: 0


public void forward(java.lang.Object);
  Code:
   Stack=2, Locals=2, Args_size=2
   0:	aload_0
   1:	invokevirtual	#99; //Method del:()Lscala/actors/Actor;
   4:	aload_1
   5:	invokeinterface	#146,  2; //InterfaceMethod scala/actors/ReplyReactor.forward:(Ljava/lang/Object;)V
   10:	return
  LineNumberTable: 
   line 56: 0

  LocalVariableTable: 
   Start  Length  Slot  Name   Signature
   0      11      0    this       Lscala/actors/remote/Proxy;
   0      11      1    msg       Ljava/lang/Object;


public void send(java.lang.Object, scala.actors.OutputChannel);
  Code:
   Stack=3, Locals=3, Args_size=3
   0:	aload_0
   1:	invokevirtual	#99; //Method del:()Lscala/actors/Actor;
   4:	aload_1
   5:	aload_2
   6:	invokeinterface	#152,  3; //InterfaceMethod scala/actors/Reactor.send:(Ljava/lang/Object;Lscala/actors/OutputChannel;)V
   11:	return
  LineNumberTable: 
   line 53: 0

  LocalVariableTable: 
   Start  Length  Slot  Name   Signature
   0      12      0    this       Lscala/actors/remote/Proxy;
   0      12      1    msg       Ljava/lang/Object;
   0      12      2    replyCh       Lscala/actors/OutputChannel;

  Signature: length = 0x2
   00 FFFFFF9B 

public void $bang(java.lang.Object);
  Code:
   Stack=2, Locals=2, Args_size=2
   0:	aload_0
   1:	invokevirtual	#99; //Method del:()Lscala/actors/Actor;
   4:	aload_1
   5:	invokeinterface	#114,  2; //InterfaceMethod scala/actors/ReplyReactor.$bang:(Ljava/lang/Object;)V
   10:	return
  LineNumberTable: 
   line 50: 0

  LocalVariableTable: 
   Start  Length  Slot  Name   Signature
   0      11      0    this       Lscala/actors/remote/Proxy;
   0      11      1    msg       Ljava/lang/Object;


public void del_$eq(scala.actors.Actor);
  Code:
   Stack=2, Locals=2, Args_size=2
   0:	aload_0
   1:	aload_1
   2:	putfield	#42; //Field del:Lscala/actors/Actor;
   5:	return
  LineNumberTable: 
   line 24: 0


public scala.actors.Actor del();
  Code:
   Stack=1, Locals=1, Args_size=1
   0:	aload_0
   1:	getfield	#42; //Field del:Lscala/actors/Actor;
   4:	areturn
  LineNumberTable: 
   line 24: 0


public void kernel_$eq(scala.actors.remote.NetKernel);
  Code:
   Stack=2, Locals=2, Args_size=2
   0:	aload_0
   1:	aload_1
   2:	putfield	#24; //Field kernel:Lscala/actors/remote/NetKernel;
   5:	return
  LineNumberTable: 
   line 20: 0


public scala.actors.remote.NetKernel kernel();
  Code:
   Stack=1, Locals=1, Args_size=1
   0:	aload_0
   1:	getfield	#24; //Field kernel:Lscala/actors/remote/NetKernel;
   4:	areturn
  LineNumberTable: 
   line 20: 0


public void exiting_$eq(boolean);
  Code:
   Stack=2, Locals=2, Args_size=2
   0:	aload_0
   1:	iload_1
   2:	putfield	#220; //Field exiting:Z
   5:	return
  LineNumberTable: 
   line 20: 0


public boolean exiting();
  Code:
   Stack=1, Locals=1, Args_size=1
   0:	aload_0
   1:	getfield	#220; //Field exiting:Z
   4:	ireturn
  LineNumberTable: 
   line 20: 0


}

