Compiled from "Proxy.scala"
public class scala.actors.remote.Proxy extends java.lang.Object implements scala.actors.AbstractActor,scala.ScalaObject,java.io.Serializable
  SourceFile: "Proxy.scala"
  ScalaSig: length = 0x5BE
   05 00 FFFFFF81 56 06 09 01 02 FFFFFF84 FFFFFF80 FFFFFF80 FFFFFF80 00 02 08 02
   05 50 72 6F 78 79 0A 02 03 04 01 06 72 65 6D 6F
   74 65 0A 02 05 06 01 06 61 63 74 6F 72 73 0A 01
   07 01 05 73 63 61 6C 61 13 04 00 09 11 15 10 02
   0A 0F 0D 01 0B 0A 02 0C 0D 01 04 6C 61 6E 67 0A
   01 0E 01 04 6A 61 76 61 09 02 10 0B 02 06 4F 62
   6A 65 63 74 10 02 12 13 0D 01 04 09 02 14 04 02
   0D 41 62 73 74 72 61 63 74 41 63 74 6F 72 10 02
   16 17 0D 01 06 09 02 18 06 02 0B 53 63 61 6C 61
   4F 62 6A 65 63 74 08 08 1A 00 FFFFFF82 FFFFFF80 FFFFFFA0 FFFFFF80 04 1C
   01 04 6E 6F 64 65 03 00 10 02 1D 1E 0D 01 02 09
   02 1F 02 02 04 4E 6F 64 65 08 08 21 00 FFFFFF82 FFFFFF80 FFFFFFA0
   FFFFFF80 04 22 01 04 6E 61 6D 65 10 02 16 23 09 02 24
   06 02 06 53 79 6D 62 6F 6C 08 08 26 00 FFFFFF82 FFFFFFC0 FFFFFF80
   FFFFFF84 00 27 01 06 6B 65 72 6E 65 6C 15 01 28 10 02
   1D 29 09 02 2A 02 02 09 4E 65 74 4B 65 72 6E 65
   6C 08 08 2C 00 FFFFFF82 FFFFFFC0 FFFFFF80 FFFFFF84 00 2D 01 0A 6B 65 72
   6E 65 6C 5F 24 65 71 14 02 2E 31 10 02 16 2F 09
   02 30 06 02 04 55 6E 69 74 08 07 32 2B FFFFFF81 FFFFFF80 FFFFFFC0
   00 28 01 03 78 24 31 08 08 34 00 FFFFFF82 FFFFFF80 FFFFFFA0 FFFFFFA0 04
   28 01 07 6B 65 72 6E 65 6C 20 28 02 33 36 10 02
   16 37 09 02 38 06 02 09 74 72 61 6E 73 69 65 6E
   74 08 05 3A 00 FFFFFF84 00 3B 01 06 3C 69 6E 69 74 3E
   14 04 3C 3D 3E 3F 10 02 1D 00 08 05 1A 39 FFFFFFC0 00
   1C 08 05 21 39 FFFFFFC0 00 22 08 05 26 39 FFFFFFC0 00 28 05
   04 41 00 00 42 02 06 46 75 74 75 72 65 15 02 43
   47 10 03 12 44 45 09 02 41 04 10 02 46 47 0C 00
   04 08 48 40 FFFFFF84 FFFFFF80 FFFFFF84 FFFFFFC2 00 49 02 01 52 11 02 4A
   4D 10 02 16 4B 09 02 4C 06 02 07 4E 6F 74 68 69
   6E 67 10 02 16 4E 09 02 4F 06 02 03 41 6E 79 08
   08 51 00 FFFFFFC0 FFFFFF80 FFFFFF84 00 02 52 01 03 64 65 6C 15 01
   53 10 02 12 54 09 02 55 04 02 05 41 63 74 6F 72
   08 08 57 00 FFFFFFC0 FFFFFF80 FFFFFF84 00 02 58 01 07 64 65 6C 5F
   24 65 71 14 02 2E 59 08 07 32 56 FFFFFF81 FFFFFF80 FFFFFFC0 00 53
   08 06 5B 00 FFFFFFA0 FFFFFFA0 04 53 01 04 64 65 6C 20 28 02
   5A 36 08 05 5E 00 FFFFFF84 04 5F 01 0B 77 72 69 74 65
   4F 62 6A 65 63 74 14 02 2E 60 08 05 61 5D FFFFFFC0 00
   62 01 03 6F 75 74 10 02 63 66 0D 01 64 0A 02 65
   0D 01 02 69 6F 09 02 67 64 02 12 4F 62 6A 65 63
   74 4F 75 74 70 75 74 53 74 72 65 61 6D 28 03 5D
   69 6C 10 02 16 6A 09 02 6B 06 02 06 74 68 72 6F
   77 73 23 01 6D 10 02 63 6E 09 02 6F 64 02 0B 49
   4F 45 78 63 65 70 74 69 6F 6E 08 05 71 00 FFFFFF84 04
   72 01 0A 72 65 61 64 4F 62 6A 65 63 74 14 02 2E
   73 08 05 74 70 FFFFFFC0 00 75 01 02 69 6E 10 02 63 76
   09 02 77 64 02 11 4F 62 6A 65 63 74 49 6E 70 75
   74 53 74 72 65 61 6D 28 03 70 69 6C 28 03 70 69
   7A 23 01 7B 10 02 0A 7C 09 02 7D 0B 02 16 43 6C
   61 73 73 4E 6F 74 46 6F 75 6E 64 45 78 63 65 70
   74 69 6F 6E 08 06 7F 00 FFFFFF84 04 FFFFFF81 00 01 0D 73 74
   61 72 74 44 65 6C 65 67 61 74 65 14 01 2E 08 07
   FFFFFF81 02 00 FFFFFF84 04 FFFFFF81 00 01 0B 73 65 74 75 70 4B 65
   72 6E 65 6C 08 07 FFFFFF81 04 00 FFFFFF84 00 FFFFFF81 05 01 05 24
   62 61 6E 67 14 03 2E FFFFFF81 06 08 07 FFFFFF81 07 FFFFFF81 03 FFFFFFC0
   00 4D 01 03 6D 73 67 08 07 FFFFFF81 09 00 FFFFFF84 00 FFFFFF81 0A
   01 04 73 65 6E 64 14 05 2E FFFFFF81 0B FFFFFF81 0C 08 07 FFFFFF81
   07 FFFFFF81 08 FFFFFFC0 00 4D 08 08 FFFFFF81 0D FFFFFF81 08 FFFFFFC0 00 FFFFFF81 0E
   01 07 72 65 70 6C 79 43 68 10 04 12 FFFFFF81 0F 4D 09
   03 FFFFFF81 10 04 02 0D 4F 75 74 70 75 74 43 68 61 6E
   6E 65 6C 08 07 FFFFFF81 12 00 FFFFFF84 00 FFFFFF81 13 01 07 66 6F
   72 77 61 72 64 14 03 2E FFFFFF81 14 08 07 FFFFFF81 07 FFFFFF81 11
   FFFFFFC0 00 4D 08 06 FFFFFF81 16 00 FFFFFF84 00 52 01 08 72 65 63
   65 69 76 65 72 08 07 FFFFFF81 18 00 FFFFFF84 00 FFFFFF81 19 01 0B
   24 62 61 6E 67 24 71 6D 61 72 6B 14 03 4D FFFFFF81 1A
   08 07 FFFFFF81 07 FFFFFF81 17 FFFFFFC0 00 4D 08 07 FFFFFF81 18 00 FFFFFF84 00
   FFFFFF81 1C 14 06 FFFFFF81 1D FFFFFF81 20 FFFFFF81 25 10 04 16 FFFFFF81 1E 4D
   09 03 FFFFFF81 1F 06 02 06 4F 70 74 69 6F 6E 08 08 FFFFFF81
   21 FFFFFF81 1B FFFFFFC0 00 FFFFFF81 22 01 04 6D 73 65 63 10 03 16
   FFFFFF81 23 09 03 FFFFFF81 24 06 02 04 4C 6F 6E 67 08 07 FFFFFF81
   07 FFFFFF81 1B FFFFFFC0 00 4D 08 07 FFFFFF81 27 00 FFFFFF84 20 FFFFFF81 28 01
   0A 24 62 61 6E 67 24 62 61 6E 67 14 04 FFFFFF81 29 FFFFFF81
   2B 10 04 FFFFFF81 2A 40 4D 0D 01 00 08 07 FFFFFF81 07 FFFFFF81 26
   FFFFFFC0 00 4D 08 07 FFFFFF81 27 00 FFFFFF84 20 FFFFFF81 2D 15 04 FFFFFF81 2E
   FFFFFF81 31 14 06 FFFFFF81 2F FFFFFF81 33 FFFFFF81 34 10 05 FFFFFF81 2A 40 FFFFFF81
   30 10 03 46 FFFFFF81 31 04 0A FFFFFF81 32 FFFFFF81 2C FFFFFF84 FFFFFF80 FFFFFF80 FFFFFFC2
   00 49 02 01 41 08 07 FFFFFF81 07 FFFFFF81 2C FFFFFFC0 00 4D 08 08
   FFFFFF81 35 FFFFFF81 2C FFFFFFC0 00 FFFFFF81 36 01 01 66 10 06 16 FFFFFF81 37
   4D FFFFFF81 30 09 03 FFFFFF81 38 06 02 0F 50 61 72 74 69 61
   6C 46 75 6E 63 74 69 6F 6E 08 07 FFFFFF81 3A 00 FFFFFF84 00
   FFFFFF81 3B 01 06 6C 69 6E 6B 54 6F 14 03 2E FFFFFF81 3C 08
   07 FFFFFF81 3D FFFFFF81 39 FFFFFFC0 00 11 01 02 74 6F 08 07 FFFFFF81 3F
   00 FFFFFF84 00 FFFFFF81 40 01 0A 75 6E 6C 69 6E 6B 46 72 6F
   6D 14 03 2E FFFFFF81 41 08 07 FFFFFF81 42 FFFFFF81 3E FFFFFFC0 00 11 01
   04 66 72 6F 6D 08 07 FFFFFF81 44 00 FFFFFF84 00 FFFFFF81 45 01 04
   65 78 69 74 14 05 2E FFFFFF81 46 FFFFFF81 47 08 07 FFFFFF81 42 FFFFFF81
   43 FFFFFFC0 00 11 08 08 FFFFFF81 48 FFFFFF81 43 FFFFFFC0 00 FFFFFF81 49 01 06
   72 65 61 73 6F 6E 10 03 16 FFFFFF81 4A 09 03 FFFFFF81 4B 06
   02 06 41 6E 79 52 65 66 08 07 FFFFFF81 4D 00 FFFFFF84 20 FFFFFF81
   4E 01 08 74 6F 53 74 72 69 6E 67 14 02 FFFFFF81 4F 10
   03 0A FFFFFF81 50 09 03 FFFFFF81 51 0B 02 06 53 74 72 69 6E
   67 28 03 00 FFFFFF81 53 10 03 16 FFFFFF81 54 09 03 FFFFFF81 55 06
   02 0C 73 65 72 69 61 6C 69 7A 61 62 6C 65 
  minor version: 0
  major version: 49
  Constant pool:
Asciz	SourceFile;
Asciz	Proxy.scala;
Asciz	exiting;
Asciz	Z;
Asciz	del;
Asciz	Lscala/actors/Actor;;
Asciz	kernel;
Asciz	Lscala/actors/remote/NetKernel;;
Asciz	name;
Asciz	Lscala/Symbol;;
Asciz	node;
Asciz	Lscala/actors/remote/Node;;
Asciz	<init>;
Asciz	(Lscala/actors/remote/Node;Lscala/Symbol;Lscala/actors/remote/NetKernel;)V;
Asciz	Code;
Asciz	LineNumberTable;
Asciz	scala/actors/remote/Proxy;
class	scala/actors/remote/Proxy
NameAndType	node:Lscala/actors/remote/Node;
Field	scala/actors/remote/Proxy.node:Lscala/actors/remote/Node;
NameAndType	name:Lscala/Symbol;
Field	scala/actors/remote/Proxy.name:Lscala/Symbol;
NameAndType	kernel:Lscala/actors/remote/NetKernel;
Field	scala/actors/remote/Proxy.kernel:Lscala/actors/remote/NetKernel;
Asciz	java/lang/Object;
class	java/lang/Object
Asciz	()V;
NameAndType	"<init>":()V
Method	java/lang/Object."<init>":()V
Asciz	scala/actors/Replyable$class;
class	scala/actors/Replyable$class
Asciz	$init$;
Asciz	(Lscala/actors/Replyable;)V;
NameAndType	$init$:(Lscala/actors/Replyable;)V
Method	scala/actors/Replyable$class.$init$:(Lscala/actors/Replyable;)V
Asciz	scala/actors/AbstractActor$class;
class	scala/actors/AbstractActor$class
Asciz	(Lscala/actors/AbstractActor;)V;
NameAndType	$init$:(Lscala/actors/AbstractActor;)V
Method	scala/actors/AbstractActor$class.$init$:(Lscala/actors/AbstractActor;)V
NameAndType	del:Lscala/actors/Actor;
Field	scala/actors/remote/Proxy.del:Lscala/actors/Actor;
Asciz	startDelegate;
NameAndType	startDelegate:()V
Method	scala/actors/remote/Proxy.startDelegate:()V
Asciz	this;
Asciz	Lscala/actors/remote/Proxy;;
Asciz	LocalVariableTable;
Asciz	$bang$bang;
Asciz	(Ljava/lang/Object;)Lscala/Function0;;
Asciz	(Ljava/lang/Object;)Lscala/actors/Future;;
NameAndType	$bang$bang:(Ljava/lang/Object;)Lscala/actors/Future;
Method	scala/actors/remote/Proxy.$bang$bang:(Ljava/lang/Object;)Lscala/actors/Future;
Asciz	msg;
Asciz	Ljava/lang/Object;;
Asciz	(Ljava/lang/Object;Lscala/PartialFunction;)Lscala/Function0;;
Asciz	(Ljava/lang/Object;Lscala/PartialFunction;)Lscala/actors/Future;;
NameAndType	$bang$bang:(Ljava/lang/Object;Lscala/PartialFunction;)Lscala/actors/Future;
Method	scala/actors/remote/Proxy.$bang$bang:(Ljava/lang/Object;Lscala/PartialFunction;)Lscala/actors/Future;
Asciz	f;
Asciz	Lscala/PartialFunction;;
Asciz	toString;
Asciz	()Ljava/lang/String;;
Asciz	scala/collection/mutable/StringBuilder;
class	scala/collection/mutable/StringBuilder
Method	scala/collection/mutable/StringBuilder."<init>":()V
Asciz	scala/Predef$;
class	scala/Predef$
Asciz	MODULE$;
Asciz	Lscala/Predef$;;
NameAndType	MODULE$:Lscala/Predef$;
Field	scala/Predef$.MODULE$:Lscala/Predef$;
Asciz	any2stringadd;
Asciz	(Ljava/lang/Object;)Lscala/runtime/StringAdd;;
NameAndType	any2stringadd:(Ljava/lang/Object;)Lscala/runtime/StringAdd;
Method	scala/Predef$.any2stringadd:(Ljava/lang/Object;)Lscala/runtime/StringAdd;
Asciz	@;
String	@
Asciz	scala/runtime/StringAdd;
class	scala/runtime/StringAdd
Asciz	$plus;
Asciz	(Ljava/lang/String;)Ljava/lang/String;;
NameAndType	$plus:(Ljava/lang/String;)Ljava/lang/String;
Method	scala/runtime/StringAdd.$plus:(Ljava/lang/String;)Ljava/lang/String;
Asciz	append;
Asciz	(Ljava/lang/Object;)Lscala/collection/mutable/StringBuilder;;
NameAndType	append:(Ljava/lang/Object;)Lscala/collection/mutable/StringBuilder;
Method	scala/collection/mutable/StringBuilder.append:(Ljava/lang/Object;)Lscala/collection/mutable/StringBuilder;
NameAndType	toString:()Ljava/lang/String;
Method	scala/collection/mutable/StringBuilder.toString:()Ljava/lang/String;
Asciz	exit;
Asciz	(Lscala/actors/AbstractActor;Ljava/lang/Object;)V;
Asciz	()Lscala/actors/Actor;;
NameAndType	del:()Lscala/actors/Actor;
Method	scala/actors/remote/Proxy.del:()Lscala/actors/Actor;
Asciz	scala/actors/remote/Apply0;
class	scala/actors/remote/Apply0
Asciz	scala/actors/remote/ExitFun;
class	scala/actors/remote/ExitFun
Asciz	(Ljava/lang/Object;)V;
NameAndType	"<init>":(Ljava/lang/Object;)V
Method	scala/actors/remote/ExitFun."<init>":(Ljava/lang/Object;)V
Asciz	(Lscala/Function2;)V;
NameAndType	"<init>":(Lscala/Function2;)V
Method	scala/actors/remote/Apply0."<init>":(Lscala/Function2;)V
Asciz	scala/actors/ReplyReactor;
class	scala/actors/ReplyReactor
Asciz	$bang;
NameAndType	$bang:(Ljava/lang/Object;)V
InterfaceMethod	scala/actors/ReplyReactor.$bang:(Ljava/lang/Object;)V
Asciz	from;
Asciz	Lscala/actors/AbstractActor;;
Asciz	reason;
Asciz	unlinkFrom;
Asciz	scala/actors/remote/UnlinkFromFun;
class	scala/actors/remote/UnlinkFromFun
Method	scala/actors/remote/UnlinkFromFun."<init>":()V
Asciz	linkTo;
Asciz	scala/actors/remote/LinkToFun;
class	scala/actors/remote/LinkToFun
Method	scala/actors/remote/LinkToFun."<init>":()V
Asciz	to;
Asciz	scala/actors/ReplyableActor;
class	scala/actors/ReplyableActor
InterfaceMethod	scala/actors/ReplyableActor.$bang$bang:(Ljava/lang/Object;Lscala/PartialFunction;)Lscala/actors/Future;
Asciz	<A:Ljava/lang/Object;>(Ljava/lang/Object;Lscala/PartialFunction<Ljava/lang/Object;TA;>;)Lscala/actors/Future<TA;>;;
Asciz	Signature;
InterfaceMethod	scala/actors/ReplyableActor.$bang$bang:(Ljava/lang/Object;)Lscala/actors/Future;
Asciz	(Ljava/lang/Object;)Lscala/actors/Future<Ljava/lang/Object;>;;
Asciz	$bang$qmark;
Asciz	(JLjava/lang/Object;)Lscala/Option;;
NameAndType	$bang$qmark:(JLjava/lang/Object;)Lscala/Option;
InterfaceMethod	scala/actors/ReplyableActor.$bang$qmark:(JLjava/lang/Object;)Lscala/Option;
Asciz	msec;
Asciz	J;
Asciz	(JLjava/lang/Object;)Lscala/Option<Ljava/lang/Object;>;;
Asciz	(Ljava/lang/Object;)Ljava/lang/Object;;
NameAndType	$bang$qmark:(Ljava/lang/Object;)Ljava/lang/Object;
InterfaceMethod	scala/actors/ReplyableActor.$bang$qmark:(Ljava/lang/Object;)Ljava/lang/Object;
Asciz	receiver;
Asciz	forward;
NameAndType	forward:(Ljava/lang/Object;)V
InterfaceMethod	scala/actors/ReplyReactor.forward:(Ljava/lang/Object;)V
Asciz	send;
Asciz	(Ljava/lang/Object;Lscala/actors/OutputChannel;)V;
Asciz	scala/actors/Reactor;
class	scala/actors/Reactor
NameAndType	send:(Ljava/lang/Object;Lscala/actors/OutputChannel;)V
InterfaceMethod	scala/actors/Reactor.send:(Ljava/lang/Object;Lscala/actors/OutputChannel;)V
Asciz	replyCh;
Asciz	Lscala/actors/OutputChannel;;
Asciz	(Ljava/lang/Object;Lscala/actors/OutputChannel<Ljava/lang/Object;>;)V;
Asciz	setupKernel;
Asciz	scala/actors/remote/RemoteActor$;
class	scala/actors/remote/RemoteActor$
Asciz	Lscala/actors/remote/RemoteActor$;;
NameAndType	MODULE$:Lscala/actors/remote/RemoteActor$;
Field	scala/actors/remote/RemoteActor$.MODULE$:Lscala/actors/remote/RemoteActor$;
Asciz	someKernel;
Asciz	()Lscala/actors/remote/NetKernel;;
NameAndType	someKernel:()Lscala/actors/remote/NetKernel;
Method	scala/actors/remote/RemoteActor$.someKernel:()Lscala/actors/remote/NetKernel;
Asciz	kernel_$eq;
Asciz	(Lscala/actors/remote/NetKernel;)V;
NameAndType	kernel_$eq:(Lscala/actors/remote/NetKernel;)V
Method	scala/actors/remote/Proxy.kernel_$eq:(Lscala/actors/remote/NetKernel;)V
NameAndType	kernel:()Lscala/actors/remote/NetKernel;
Method	scala/actors/remote/Proxy.kernel:()Lscala/actors/remote/NetKernel;
Asciz	scala/actors/remote/NetKernel;
class	scala/actors/remote/NetKernel
Asciz	registerProxy;
Asciz	(Lscala/actors/remote/Node;Lscala/Symbol;Lscala/actors/remote/Proxy;)V;
NameAndType	registerProxy:(Lscala/actors/remote/Node;Lscala/Symbol;Lscala/actors/remote/Proxy;)V
Method	scala/actors/remote/NetKernel.registerProxy:(Lscala/actors/remote/Node;Lscala/Symbol;Lscala/actors/remote/Proxy;)V
Asciz	scala/actors/remote/DelegateActor;
class	scala/actors/remote/DelegateActor
Asciz	(Lscala/actors/remote/Proxy;Lscala/actors/remote/Node;Lscala/Symbol;Lscala/actors/remote/NetKernel;)V;
NameAndType	"<init>":(Lscala/actors/remote/Proxy;Lscala/actors/remote/Node;Lscala/Symbol;Lscala/actors/remote/NetKernel;)V
Method	scala/actors/remote/DelegateActor."<init>":(Lscala/actors/remote/Proxy;Lscala/actors/remote/Node;Lscala/Symbol;Lscala/actors/remote/NetKernel;)V
Asciz	del_$eq;
Asciz	(Lscala/actors/Actor;)V;
NameAndType	del_$eq:(Lscala/actors/Actor;)V
Method	scala/actors/remote/Proxy.del_$eq:(Lscala/actors/Actor;)V
Asciz	scala/actors/Actor;
class	scala/actors/Actor
Asciz	start;
NameAndType	start:()Lscala/actors/Actor;
InterfaceMethod	scala/actors/Actor.start:()Lscala/actors/Actor;
Asciz	readObject;
Asciz	(Ljava/io/ObjectInputStream;)V;
Asciz	java/io/ObjectInputStream;
class	java/io/ObjectInputStream
Asciz	defaultReadObject;
NameAndType	defaultReadObject:()V
Method	java/io/ObjectInputStream.defaultReadObject:()V
NameAndType	setupKernel:()V
Method	scala/actors/remote/Proxy.setupKernel:()V
Asciz	in;
Asciz	Ljava/io/ObjectInputStream;;
Asciz	java/lang/ClassNotFoundException;
class	java/lang/ClassNotFoundException
Asciz	java/io/IOException;
class	java/io/IOException
Asciz	Exceptions;
Asciz	writeObject;
Asciz	(Ljava/io/ObjectOutputStream;)V;
Asciz	java/io/ObjectOutputStream;
class	java/io/ObjectOutputStream
Asciz	defaultWriteObject;
NameAndType	defaultWriteObject:()V
Method	java/io/ObjectOutputStream.defaultWriteObject:()V
Asciz	out;
Asciz	Ljava/io/ObjectOutputStream;;
Asciz	exiting_$eq;
Asciz	(Z)V;
NameAndType	exiting:Z
Field	scala/actors/remote/Proxy.exiting:Z
Asciz	()Z;
Asciz	ScalaSig;
Asciz	scala/actors/AbstractActor;
class	scala/actors/AbstractActor
Asciz	scala/ScalaObject;
class	scala/ScalaObject
Asciz	java/io/Serializable;
class	java/io/Serializable

{
private boolean exiting;
  Signature: Z

private transient scala.actors.Actor del;
  Signature: Lscala/actors/Actor;

private transient scala.actors.remote.NetKernel kernel;
  Signature: Lscala/actors/remote/NetKernel;

private final scala.Symbol name;
  Signature: Lscala/Symbol;

private final scala.actors.remote.Node node;
  Signature: Lscala/actors/remote/Node;

public scala.actors.remote.Proxy(scala.actors.remote.Node, scala.Symbol, scala.actors.remote.NetKernel);
  Signature: (Lscala/actors/remote/Node;Lscala/Symbol;Lscala/actors/remote/NetKernel;)V
  Code:
   Stack=2, Locals=4, Args_size=4
	aload_0
	aload_1
	putfield	Field node:Lscala/actors/remote/Node;
	aload_0
	aload_2
	putfield	Field name:Lscala/Symbol;
	aload_0
	aload_3
	putfield	Field kernel:Lscala/actors/remote/NetKernel;
	aload_0
	invokespecial	Method java/lang/Object."<init>":()V
	aload_0
	invokestatic	Method scala/actors/Replyable$class.$init$:(Lscala/actors/Replyable;)V
	aload_0
	invokestatic	Method scala/actors/AbstractActor$class.$init$:(Lscala/actors/AbstractActor;)V
	aload_0
	aconst_null
	putfield	Field del:Lscala/actors/Actor;
	aload_0
	invokespecial	Method startDelegate:()V
	return
  Labels:
  LocalVariableTable: 
   Start  Length  Slot  Name   Signature
   0      37      0    this       Lscala/actors/remote/Proxy;
   0      37      1    node       Lscala/actors/remote/Node;
   0      37      2    name       Lscala/Symbol;
   0      37      3    kernel       Lscala/actors/remote/NetKernel;


public scala.Function0 $bang$bang(java.lang.Object);
  Signature: (Ljava/lang/Object;)Lscala/Function0;
  Code:
   Stack=2, Locals=2, Args_size=2
	aload_0
	aload_1
	invokevirtual	Method $bang$bang:(Ljava/lang/Object;)Lscala/actors/Future;
	areturn
  Labels:
  LocalVariableTable: 
   Start  Length  Slot  Name   Signature
   0      6      0    this       Lscala/actors/remote/Proxy;
   0      6      1    msg       Ljava/lang/Object;


public scala.Function0 $bang$bang(java.lang.Object, scala.PartialFunction);
  Signature: (Ljava/lang/Object;Lscala/PartialFunction;)Lscala/Function0;
  Code:
   Stack=3, Locals=3, Args_size=3
	aload_0
	aload_1
	aload_2
	invokevirtual	Method $bang$bang:(Ljava/lang/Object;Lscala/PartialFunction;)Lscala/actors/Future;
	areturn
  Labels:
  LocalVariableTable: 
   Start  Length  Slot  Name   Signature
   0      7      0    this       Lscala/actors/remote/Proxy;
   0      7      1    msg       Ljava/lang/Object;
   0      7      2    f       Lscala/PartialFunction;


public java.lang.String toString();
  Signature: ()Ljava/lang/String;
  Code:
   Stack=3, Locals=1, Args_size=1
	new	class scala/collection/mutable/StringBuilder
	dup
	invokespecial	Method scala/collection/mutable/StringBuilder."<init>":()V
	getstatic	Field scala/Predef$.MODULE$:Lscala/Predef$;
	aload_0
	getfield	Field name:Lscala/Symbol;
	invokevirtual	Method scala/Predef$.any2stringadd:(Ljava/lang/Object;)Lscala/runtime/StringAdd;
	ldc	String @
	invokevirtual	Method scala/runtime/StringAdd.$plus:(Ljava/lang/String;)Ljava/lang/String;
	invokevirtual	Method scala/collection/mutable/StringBuilder.append:(Ljava/lang/Object;)Lscala/collection/mutable/StringBuilder;
	aload_0
	getfield	Field node:Lscala/actors/remote/Node;
	invokevirtual	Method scala/collection/mutable/StringBuilder.append:(Ljava/lang/Object;)Lscala/collection/mutable/StringBuilder;
	invokevirtual	Method scala/collection/mutable/StringBuilder.toString:()Ljava/lang/String;
	areturn
  Labels:

public void exit(scala.actors.AbstractActor, java.lang.Object);
  Signature: (Lscala/actors/AbstractActor;Ljava/lang/Object;)V
  Code:
   Stack=6, Locals=3, Args_size=3
	aload_0
	invokevirtual	Method del:()Lscala/actors/Actor;
	new	class scala/actors/remote/Apply0
	dup
	new	class scala/actors/remote/ExitFun
	dup
	aload_2
	invokespecial	Method scala/actors/remote/ExitFun."<init>":(Ljava/lang/Object;)V
	invokespecial	Method scala/actors/remote/Apply0."<init>":(Lscala/Function2;)V
	invokeinterface	InterfaceMethod scala/actors/ReplyReactor.$bang:(Ljava/lang/Object;)V
	return
  Labels:
  LocalVariableTable: 
   Start  Length  Slot  Name   Signature
   0      25      0    this       Lscala/actors/remote/Proxy;
   0      25      1    from       Lscala/actors/AbstractActor;
   0      25      2    reason       Ljava/lang/Object;


public void unlinkFrom(scala.actors.AbstractActor);
  Signature: (Lscala/actors/AbstractActor;)V
  Code:
   Stack=5, Locals=2, Args_size=2
	aload_0
	invokevirtual	Method del:()Lscala/actors/Actor;
	new	class scala/actors/remote/Apply0
	dup
	new	class scala/actors/remote/UnlinkFromFun
	dup
	invokespecial	Method scala/actors/remote/UnlinkFromFun."<init>":()V
	invokespecial	Method scala/actors/remote/Apply0."<init>":(Lscala/Function2;)V
	invokeinterface	InterfaceMethod scala/actors/ReplyReactor.$bang:(Ljava/lang/Object;)V
	return
  Labels:
  LocalVariableTable: 
   Start  Length  Slot  Name   Signature
   0      24      0    this       Lscala/actors/remote/Proxy;
   0      24      1    from       Lscala/actors/AbstractActor;


public void linkTo(scala.actors.AbstractActor);
  Signature: (Lscala/actors/AbstractActor;)V
  Code:
   Stack=5, Locals=2, Args_size=2
	aload_0
	invokevirtual	Method del:()Lscala/actors/Actor;
	new	class scala/actors/remote/Apply0
	dup
	new	class scala/actors/remote/LinkToFun
	dup
	invokespecial	Method scala/actors/remote/LinkToFun."<init>":()V
	invokespecial	Method scala/actors/remote/Apply0."<init>":(Lscala/Function2;)V
	invokeinterface	InterfaceMethod scala/actors/ReplyReactor.$bang:(Ljava/lang/Object;)V
	return
  Labels:
  LocalVariableTable: 
   Start  Length  Slot  Name   Signature
   0      24      0    this       Lscala/actors/remote/Proxy;
   0      24      1    to       Lscala/actors/AbstractActor;


public scala.actors.Future $bang$bang(java.lang.Object, scala.PartialFunction);
  Signature: (Ljava/lang/Object;Lscala/PartialFunction;)Lscala/actors/Future;
  Code:
   Stack=3, Locals=3, Args_size=3
	aload_0
	invokevirtual	Method del:()Lscala/actors/Actor;
	aload_1
	aload_2
	invokeinterface	InterfaceMethod scala/actors/ReplyableActor.$bang$bang:(Ljava/lang/Object;Lscala/PartialFunction;)Lscala/actors/Future;
	areturn
  Labels:
  LocalVariableTable: 
   Start  Length  Slot  Name   Signature
   0      12      0    this       Lscala/actors/remote/Proxy;
   0      12      1    msg       Ljava/lang/Object;
   0      12      2    f       Lscala/PartialFunction;

  Signature: length = 0x2
   00 7E 

public scala.actors.Future $bang$bang(java.lang.Object);
  Signature: (Ljava/lang/Object;)Lscala/actors/Future;
  Code:
   Stack=2, Locals=2, Args_size=2
	aload_0
	invokevirtual	Method del:()Lscala/actors/Actor;
	aload_1
	invokeinterface	InterfaceMethod scala/actors/ReplyableActor.$bang$bang:(Ljava/lang/Object;)Lscala/actors/Future;
	areturn
  Labels:
  LocalVariableTable: 
   Start  Length  Slot  Name   Signature
   0      11      0    this       Lscala/actors/remote/Proxy;
   0      11      1    msg       Ljava/lang/Object;

  Signature: length = 0x2
   00 FFFFFF81 

public scala.Option $bang$qmark(long, java.lang.Object);
  Signature: (JLjava/lang/Object;)Lscala/Option;
  Code:
   Stack=4, Locals=4, Args_size=3
	aload_0
	invokevirtual	Method del:()Lscala/actors/Actor;
	lload_1
	aload_3
	invokeinterface	InterfaceMethod scala/actors/ReplyableActor.$bang$qmark:(JLjava/lang/Object;)Lscala/Option;
	areturn
  Labels:
  LocalVariableTable: 
   Start  Length  Slot  Name   Signature
   0      12      0    this       Lscala/actors/remote/Proxy;
   0      12      1    msec       J
   0      12      3    msg       Ljava/lang/Object;

  Signature: length = 0x2
   00 FFFFFF88 

public java.lang.Object $bang$qmark(java.lang.Object);
  Signature: (Ljava/lang/Object;)Ljava/lang/Object;
  Code:
   Stack=2, Locals=2, Args_size=2
	aload_0
	invokevirtual	Method del:()Lscala/actors/Actor;
	aload_1
	invokeinterface	InterfaceMethod scala/actors/ReplyableActor.$bang$qmark:(Ljava/lang/Object;)Ljava/lang/Object;
	areturn
  Labels:
  LocalVariableTable: 
   Start  Length  Slot  Name   Signature
   0      11      0    this       Lscala/actors/remote/Proxy;
   0      11      1    msg       Ljava/lang/Object;


public scala.actors.Actor receiver();
  Signature: ()Lscala/actors/Actor;
  Code:
   Stack=1, Locals=1, Args_size=1
	aload_0
	invokevirtual	Method del:()Lscala/actors/Actor;
	areturn
  Labels:

public void forward(java.lang.Object);
  Signature: (Ljava/lang/Object;)V
  Code:
   Stack=2, Locals=2, Args_size=2
	aload_0
	invokevirtual	Method del:()Lscala/actors/Actor;
	aload_1
	invokeinterface	InterfaceMethod scala/actors/ReplyReactor.forward:(Ljava/lang/Object;)V
	return
  Labels:
  LocalVariableTable: 
   Start  Length  Slot  Name   Signature
   0      11      0    this       Lscala/actors/remote/Proxy;
   0      11      1    msg       Ljava/lang/Object;


public void send(java.lang.Object, scala.actors.OutputChannel);
  Signature: (Ljava/lang/Object;Lscala/actors/OutputChannel;)V
  Code:
   Stack=3, Locals=3, Args_size=3
	aload_0
	invokevirtual	Method del:()Lscala/actors/Actor;
	aload_1
	aload_2
	invokeinterface	InterfaceMethod scala/actors/Reactor.send:(Ljava/lang/Object;Lscala/actors/OutputChannel;)V
	return
  Labels:
  LocalVariableTable: 
   Start  Length  Slot  Name   Signature
   0      12      0    this       Lscala/actors/remote/Proxy;
   0      12      1    msg       Ljava/lang/Object;
   0      12      2    replyCh       Lscala/actors/OutputChannel;

  Signature: length = 0x2
   00 FFFFFF98 

public void $bang(java.lang.Object);
  Signature: (Ljava/lang/Object;)V
  Code:
   Stack=2, Locals=2, Args_size=2
	aload_0
	invokevirtual	Method del:()Lscala/actors/Actor;
	aload_1
	invokeinterface	InterfaceMethod scala/actors/ReplyReactor.$bang:(Ljava/lang/Object;)V
	return
  Labels:
  LocalVariableTable: 
   Start  Length  Slot  Name   Signature
   0      11      0    this       Lscala/actors/remote/Proxy;
   0      11      1    msg       Ljava/lang/Object;


private void setupKernel();
  Signature: ()V
  Code:
   Stack=4, Locals=1, Args_size=1
	aload_0
	getstatic	Field scala/actors/remote/RemoteActor$.MODULE$:Lscala/actors/remote/RemoteActor$;
	invokevirtual	Method scala/actors/remote/RemoteActor$.someKernel:()Lscala/actors/remote/NetKernel;
	invokevirtual	Method kernel_$eq:(Lscala/actors/remote/NetKernel;)V
	aload_0
	invokevirtual	Method kernel:()Lscala/actors/remote/NetKernel;
	aload_0
	getfield	Field node:Lscala/actors/remote/Node;
	aload_0
	getfield	Field name:Lscala/Symbol;
	aload_0
	invokevirtual	Method scala/actors/remote/NetKernel.registerProxy:(Lscala/actors/remote/Node;Lscala/Symbol;Lscala/actors/remote/Proxy;)V
	return
  Labels:

private void startDelegate();
  Signature: ()V
  Code:
   Stack=7, Locals=1, Args_size=1
	aload_0
	new	class scala/actors/remote/DelegateActor
	dup
	aload_0
	aload_0
	getfield	Field node:Lscala/actors/remote/Node;
	aload_0
	getfield	Field name:Lscala/Symbol;
	aload_0
	invokevirtual	Method kernel:()Lscala/actors/remote/NetKernel;
	invokespecial	Method scala/actors/remote/DelegateActor."<init>":(Lscala/actors/remote/Proxy;Lscala/actors/remote/Node;Lscala/Symbol;Lscala/actors/remote/NetKernel;)V
	invokevirtual	Method del_$eq:(Lscala/actors/Actor;)V
	aload_0
	invokevirtual	Method del:()Lscala/actors/Actor;
	invokeinterface	InterfaceMethod scala/actors/Actor.start:()Lscala/actors/Actor;
	pop
	return
  Labels:

private void readObject(java.io.ObjectInputStream)   throws java.lang.ClassNotFoundException, java.io.IOException;
  Signature: (Ljava/io/ObjectInputStream;)V
  Code:
   Stack=1, Locals=2, Args_size=2
	aload_1
	invokevirtual	Method java/io/ObjectInputStream.defaultReadObject:()V
	aload_0
	invokespecial	Method setupKernel:()V
	aload_0
	invokespecial	Method startDelegate:()V
	return
  Labels:
  LocalVariableTable: 
   Start  Length  Slot  Name   Signature
   0      13      0    this       Lscala/actors/remote/Proxy;
   0      13      1    in       Ljava/io/ObjectInputStream;

  Exceptions: 
   throws java.lang.ClassNotFoundException, java.io.IOException
private void writeObject(java.io.ObjectOutputStream)   throws java.io.IOException;
  Signature: (Ljava/io/ObjectOutputStream;)V
  Code:
   Stack=1, Locals=2, Args_size=2
	aload_1
	invokevirtual	Method java/io/ObjectOutputStream.defaultWriteObject:()V
	return
  Labels:
  LocalVariableTable: 
   Start  Length  Slot  Name   Signature
   0      5      0    this       Lscala/actors/remote/Proxy;
   0      5      1    out       Ljava/io/ObjectOutputStream;

  Exceptions: 
   throws java.io.IOException
public void del_$eq(scala.actors.Actor);
  Signature: (Lscala/actors/Actor;)V
  Code:
   Stack=2, Locals=2, Args_size=2
	aload_0
	aload_1
	putfield	Field del:Lscala/actors/Actor;
	return
  Labels:

public scala.actors.Actor del();
  Signature: ()Lscala/actors/Actor;
  Code:
   Stack=1, Locals=1, Args_size=1
	aload_0
	getfield	Field del:Lscala/actors/Actor;
	areturn
  Labels:

public void kernel_$eq(scala.actors.remote.NetKernel);
  Signature: (Lscala/actors/remote/NetKernel;)V
  Code:
   Stack=2, Locals=2, Args_size=2
	aload_0
	aload_1
	putfield	Field kernel:Lscala/actors/remote/NetKernel;
	return
  Labels:

public scala.actors.remote.NetKernel kernel();
  Signature: ()Lscala/actors/remote/NetKernel;
  Code:
   Stack=1, Locals=1, Args_size=1
	aload_0
	getfield	Field kernel:Lscala/actors/remote/NetKernel;
	areturn
  Labels:

public void exiting_$eq(boolean);
  Signature: (Z)V
  Code:
   Stack=2, Locals=2, Args_size=2
	aload_0
	iload_1
	putfield	Field exiting:Z
	return
  Labels:

public boolean exiting();
  Signature: ()Z
  Code:
   Stack=1, Locals=1, Args_size=1
	aload_0
	getfield	Field exiting:Z
	ireturn
  Labels:

}

