Compiled from "RemoteActor.scala"
public final class scala.actors.remote.RemoteActor$ extends java.lang.Object implements scala.ScalaObject
  SourceFile: "RemoteActor.scala"
  Scala: length = 0x
   
  InnerClass: 
   public final $anonfun$createKernelOnPort$1=class scala/actors/remote/RemoteActor$$anonfun$createKernelOnPort$1 of class scala/actors/remote/RemoteActor
  minor version: 0
  major version: 49
  Constant pool:
Asciz	SourceFile;
Asciz	RemoteActor.scala;
Asciz	Scala;
Asciz	MODULE$;
Asciz	Lscala/actors/remote/RemoteActor$;;
Asciz	<clinit>;
Asciz	()V;
Asciz	Code;
Asciz	scala/actors/remote/RemoteActor$;
class	scala/actors/remote/RemoteActor$
Asciz	<init>;
NameAndType	"<init>":()V
Method	scala/actors/remote/RemoteActor$."<init>":()V
Asciz	cl;
Asciz	Ljava/lang/ClassLoader;;
Asciz	scala$actors$remote$RemoteActor$$kernels;
Asciz	Lscala/collection/mutable/HashMap;;
Asciz	LineNumberTable;
Asciz	java/lang/Object;
class	java/lang/Object
Method	java/lang/Object."<init>":()V
NameAndType	MODULE$:Lscala/actors/remote/RemoteActor$;
Field	scala/actors/remote/RemoteActor$.MODULE$:Lscala/actors/remote/RemoteActor$;
Asciz	scala/collection/mutable/HashMap;
class	scala/collection/mutable/HashMap
Method	scala/collection/mutable/HashMap."<init>":()V
NameAndType	scala$actors$remote$RemoteActor$$kernels:Lscala/collection/mutable/HashMap;
Field	scala/actors/remote/RemoteActor$.scala$actors$remote$RemoteActor$$kernels:Lscala/collection/mutable/HashMap;
NameAndType	cl:Ljava/lang/ClassLoader;
Field	scala/actors/remote/RemoteActor$.cl:Ljava/lang/ClassLoader;
Asciz	someKernel;
Asciz	()Lscala/actors/remote/NetKernel;;
Asciz	()Lscala/collection/mutable/HashMap;;
NameAndType	scala$actors$remote$RemoteActor$$kernels:()Lscala/collection/mutable/HashMap;
Method	scala/actors/remote/RemoteActor$.scala$actors$remote$RemoteActor$$kernels:()Lscala/collection/mutable/HashMap;
Asciz	valuesIterator;
Asciz	()Lscala/collection/Iterator;;
NameAndType	valuesIterator:()Lscala/collection/Iterator;
Method	scala/collection/mutable/HashMap.valuesIterator:()Lscala/collection/Iterator;
Asciz	scala/collection/Iterator;
class	scala/collection/Iterator
Asciz	next;
Asciz	()Ljava/lang/Object;;
NameAndType	next:()Ljava/lang/Object;
InterfaceMethod	scala/collection/Iterator.next:()Ljava/lang/Object;
Asciz	scala/actors/remote/NetKernel;
class	scala/actors/remote/NetKernel
Asciz	select;
Asciz	(Lscala/actors/remote/Node;Lscala/Symbol;)Lscala/actors/AbstractActor;;
Asciz	selfKernel;
NameAndType	selfKernel:()Lscala/actors/remote/NetKernel;
Method	scala/actors/remote/RemoteActor$.selfKernel:()Lscala/actors/remote/NetKernel;
Asciz	getOrCreateProxy;
Asciz	(Lscala/actors/remote/Node;Lscala/Symbol;)Lscala/actors/remote/Proxy;;
NameAndType	getOrCreateProxy:(Lscala/actors/remote/Node;Lscala/Symbol;)Lscala/actors/remote/Proxy;
Method	scala/actors/remote/NetKernel.getOrCreateProxy:(Lscala/actors/remote/Node;Lscala/Symbol;)Lscala/actors/remote/Proxy;
Asciz	scala/actors/AbstractActor;
class	scala/actors/AbstractActor
Asciz	this;
Asciz	node;
Asciz	Lscala/actors/remote/Node;;
Asciz	sym;
Asciz	Lscala/Symbol;;
Asciz	LocalVariableTable;
Asciz	scala/actors/Actor$;
class	scala/actors/Actor$
Asciz	Lscala/actors/Actor$;;
NameAndType	MODULE$:Lscala/actors/Actor$;
Field	scala/actors/Actor$.MODULE$:Lscala/actors/Actor$;
Asciz	scala/actors/Scheduler$;
class	scala/actors/Scheduler$
Asciz	Lscala/actors/Scheduler$;;
NameAndType	MODULE$:Lscala/actors/Scheduler$;
Field	scala/actors/Scheduler$.MODULE$:Lscala/actors/Scheduler$;
Asciz	rawSelf;
Asciz	(Lscala/actors/IScheduler;)Lscala/actors/Reactor;;
NameAndType	rawSelf:(Lscala/actors/IScheduler;)Lscala/actors/Reactor;
Method	scala/actors/Actor$.rawSelf:(Lscala/actors/IScheduler;)Lscala/actors/Reactor;
Asciz	scala/actors/Actor;
class	scala/actors/Actor
Asciz	get;
Asciz	(Ljava/lang/Object;)Lscala/Option;;
NameAndType	get:(Ljava/lang/Object;)Lscala/Option;
Method	scala/collection/mutable/HashMap.get:(Ljava/lang/Object;)Lscala/Option;
Asciz	scala/None$;
class	scala/None$
Asciz	Lscala/None$;;
NameAndType	MODULE$:Lscala/None$;
Field	scala/None$.MODULE$:Lscala/None$;
Asciz	equals;
Asciz	(Ljava/lang/Object;)Z;
NameAndType	equals:(Ljava/lang/Object;)Z
Method	java/lang/Object.equals:(Ljava/lang/Object;)Z
Asciz	scala/actors/remote/TcpService$;
class	scala/actors/remote/TcpService$
Asciz	Lscala/actors/remote/TcpService$;;
NameAndType	MODULE$:Lscala/actors/remote/TcpService$;
Field	scala/actors/remote/TcpService$.MODULE$:Lscala/actors/remote/TcpService$;
Asciz	generatePort;
Asciz	()I;
NameAndType	generatePort:()I
Method	scala/actors/remote/TcpService$.generatePort:()I
Asciz	()Ljava/lang/ClassLoader;;
NameAndType	cl:()Ljava/lang/ClassLoader;
Method	scala/actors/remote/RemoteActor$.cl:()Ljava/lang/ClassLoader;
Asciz	apply;
Asciz	(ILjava/lang/ClassLoader;)Lscala/actors/remote/TcpService;;
NameAndType	apply:(ILjava/lang/ClassLoader;)Lscala/actors/remote/TcpService;
Method	scala/actors/remote/TcpService$.apply:(ILjava/lang/ClassLoader;)Lscala/actors/remote/TcpService;
Asciz	scala/actors/remote/Service;
class	scala/actors/remote/Service
Asciz	kernel;
NameAndType	kernel:()Lscala/actors/remote/NetKernel;
InterfaceMethod	scala/actors/remote/Service.kernel:()Lscala/actors/remote/NetKernel;
Asciz	scala/Predef$Pair$;
class	scala/Predef$Pair$
Asciz	Lscala/Predef$Pair$;;
NameAndType	MODULE$:Lscala/Predef$Pair$;
Field	scala/Predef$Pair$.MODULE$:Lscala/Predef$Pair$;
Asciz	(Ljava/lang/Object;Ljava/lang/Object;)Lscala/Tuple2;;
NameAndType	apply:(Ljava/lang/Object;Ljava/lang/Object;)Lscala/Tuple2;
Method	scala/Predef$Pair$.apply:(Ljava/lang/Object;Ljava/lang/Object;)Lscala/Tuple2;
Asciz	$plus$eq;
Asciz	(Lscala/Tuple2;)Lscala/collection/mutable/HashMap;;
NameAndType	$plus$eq:(Lscala/Tuple2;)Lscala/collection/mutable/HashMap;
Method	scala/collection/mutable/HashMap.$plus$eq:(Lscala/Tuple2;)Lscala/collection/mutable/HashMap;
Asciz	scala/actors/remote/RemoteActor$$anonfun$createKernelOnPort$1;
class	scala/actors/remote/RemoteActor$$anonfun$createKernelOnPort$1
Asciz	(Lscala/actors/remote/NetKernel;Lscala/actors/Actor;)V;
NameAndType	"<init>":(Lscala/actors/remote/NetKernel;Lscala/actors/Actor;)V
Method	scala/actors/remote/RemoteActor$$anonfun$createKernelOnPort$1."<init>":(Lscala/actors/remote/NetKernel;Lscala/actors/Actor;)V
Asciz	onTerminate;
Asciz	(Lscala/Function0;)V;
NameAndType	onTerminate:(Lscala/Function0;)V
InterfaceMethod	scala/actors/Actor.onTerminate:(Lscala/Function0;)V
Asciz	scala/Some;
class	scala/Some
Asciz	x;
NameAndType	x:()Ljava/lang/Object;
Method	scala/Some.x:()Ljava/lang/Object;
Asciz	scala/MatchError;
class	scala/MatchError
Asciz	scala/Option;
class	scala/Option
Asciz	toString;
Asciz	()Ljava/lang/String;;
NameAndType	toString:()Ljava/lang/String;
Method	scala/Option.toString:()Ljava/lang/String;
Asciz	(Ljava/lang/String;)V;
NameAndType	"<init>":(Ljava/lang/String;)V
Method	scala/MatchError."<init>":(Ljava/lang/String;)V
Asciz	serv0;
Asciz	Lscala/actors/remote/TcpService;;
Asciz	s$10;
Asciz	Lscala/actors/Actor;;
Asciz	kern$10;
Asciz	Lscala/actors/remote/NetKernel;;
Asciz	temp7;
Asciz	Lscala/Some;;
Asciz	temp8;
Asciz	temp5;
Asciz	Lscala/Option;;
Asciz	register;
Asciz	(Lscala/Symbol;Lscala/actors/Actor;)V;
Asciz	(Lscala/Symbol;Lscala/actors/OutputChannel;)V;
NameAndType	register:(Lscala/Symbol;Lscala/actors/OutputChannel;)V
Method	scala/actors/remote/NetKernel.register:(Lscala/Symbol;Lscala/actors/OutputChannel;)V
Asciz	name;
Asciz	a;
Asciz	$inlThis1;
Asciz	Ljava/lang/Object;;
Asciz	sched0;
Asciz	Lscala/actors/IScheduler;;
Asciz	$inlThis4;
Asciz	sched1;
Asciz	serv;
Asciz	temp3;
Asciz	temp4;
Asciz	temp1;
Asciz	createKernelOnPort;
Asciz	(I)Lscala/actors/remote/NetKernel;;
Asciz	self;
Asciz	()Lscala/actors/Actor;;
NameAndType	self:()Lscala/actors/Actor;
Method	scala/actors/Actor$.self:()Lscala/actors/Actor;
Asciz	port;
Asciz	I;
Asciz	kern$1;
Asciz	s$1;
Asciz	alive;
Asciz	(I)V;
Asciz	classLoader_$eq;
Asciz	(Ljava/lang/ClassLoader;)V;
Asciz	cl_$eq;
NameAndType	cl_$eq:(Ljava/lang/ClassLoader;)V
Method	scala/actors/remote/RemoteActor$.cl_$eq:(Ljava/lang/ClassLoader;)V
Asciz	classLoader;
Asciz	InnerClasses;
Asciz	scala/actors/remote/RemoteActor;
class	scala/actors/remote/RemoteActor
Asciz	$anonfun$createKernelOnPort$1;
Asciz	scala/ScalaObject;
class	scala/ScalaObject

{
public static final scala.actors.remote.RemoteActor$ MODULE$;
  Signature: Lscala/actors/remote/RemoteActor$;

private java.lang.ClassLoader cl;
  Signature: Ljava/lang/ClassLoader;

private final scala.collection.mutable.HashMap scala$actors$remote$RemoteActor$$kernels;
  Signature: Lscala/collection/mutable/HashMap;

public static {};
  Signature: ()V
  Code:
   Stack=1, Locals=0, Args_size=0
	new	class scala/actors/remote/RemoteActor$
	invokespecial	Method "<init>":()V
	return
  Labels:

private scala.actors.remote.RemoteActor$();
  Signature: ()V
  Code:
   Stack=3, Locals=1, Args_size=1
	aload_0
	invokespecial	Method java/lang/Object."<init>":()V
	aload_0
	putstatic	Field MODULE$:Lscala/actors/remote/RemoteActor$;
	aload_0
	new	class scala/collection/mutable/HashMap
	dup
	invokespecial	Method scala/collection/mutable/HashMap."<init>":()V
	putfield	Field scala$actors$remote$RemoteActor$$kernels:Lscala/collection/mutable/HashMap;
	aload_0
	aconst_null
	putfield	Field cl:Ljava/lang/ClassLoader;
	return
  Labels:

public scala.actors.remote.NetKernel someKernel();
  Signature: ()Lscala/actors/remote/NetKernel;
  Code:
   Stack=1, Locals=1, Args_size=1
	aload_0
	invokevirtual	Method scala$actors$remote$RemoteActor$$kernels:()Lscala/collection/mutable/HashMap;
	invokevirtual	Method scala/collection/mutable/HashMap.valuesIterator:()Lscala/collection/Iterator;
	invokeinterface	InterfaceMethod scala/collection/Iterator.next:()Ljava/lang/Object;
	checkcast	class scala/actors/remote/NetKernel
	areturn
  Labels:

public scala.actors.AbstractActor select(scala.actors.remote.Node, scala.Symbol);
  Signature: (Lscala/actors/remote/Node;Lscala/Symbol;)Lscala/actors/AbstractActor;
  Code:
   Stack=3, Locals=3, Args_size=3
	aload_0
	dup
	pop
	monitorenter
	aload_0
	invokespecial	Method selfKernel:()Lscala/actors/remote/NetKernel;
	aload_1
	aload_2
	invokevirtual	Method scala/actors/remote/NetKernel.getOrCreateProxy:(Lscala/actors/remote/Node;Lscala/Symbol;)Lscala/actors/remote/Proxy;
	aload_0
	monitorexit
	checkcast	class scala/actors/AbstractActor
	areturn
	aload_0
	monitorexit
	athrow
  Labels:
  Exception table:
   from   to  target type
     4    15    19   any
  LocalVariableTable: 
   Start  Length  Slot  Name   Signature
   0      22      0    this       Lscala/actors/remote/RemoteActor$;
   0      22      1    node       Lscala/actors/remote/Node;
   0      22      2    sym       Lscala/Symbol;


private scala.actors.remote.NetKernel selfKernel();
  Signature: ()Lscala/actors/remote/NetKernel;
  Code:
   Stack=5, Locals=12, Args_size=1
	aload_0
	getfield	Field scala$actors$remote$RemoteActor$$kernels:Lscala/collection/mutable/HashMap;
	getstatic	Field scala/actors/Actor$.MODULE$:Lscala/actors/Actor$;
	astore_1
	getstatic	Field scala/actors/Scheduler$.MODULE$:Lscala/actors/Scheduler$;
	astore_2
	aload_1
	aload_2
	invokevirtual	Method scala/actors/Actor$.rawSelf:(Lscala/actors/IScheduler;)Lscala/actors/Reactor;
	checkcast	class scala/actors/Actor
	invokevirtual	Method scala/collection/mutable/HashMap.get:(Ljava/lang/Object;)Lscala/Option;
	astore	11
	getstatic	Field scala/None$.MODULE$:Lscala/None$;
	dup
	ifnonnull	l1 // aload
	pop
	aload	11
	ifnull	l2 // getstatic
	goto	l3 // aload
l1	aload	11
	invokevirtual	Method java/lang/Object.equals:(Ljava/lang/Object;)Z
	ifeq	l3 // aload
l2	getstatic	Field scala/actors/remote/TcpService$.MODULE$:Lscala/actors/remote/TcpService$;
	invokevirtual	Method scala/actors/remote/TcpService$.generatePort:()I
	istore_3
	getstatic	Field scala/actors/remote/TcpService$.MODULE$:Lscala/actors/remote/TcpService$;
	iload_3
	aload_0
	invokespecial	Method cl:()Ljava/lang/ClassLoader;
	invokevirtual	Method scala/actors/remote/TcpService$.apply:(ILjava/lang/ClassLoader;)Lscala/actors/remote/TcpService;
	astore	4
	aload	4
	invokeinterface	InterfaceMethod scala/actors/remote/Service.kernel:()Lscala/actors/remote/NetKernel;
	astore	8
	getstatic	Field scala/actors/Actor$.MODULE$:Lscala/actors/Actor$;
	astore	5
	getstatic	Field scala/actors/Scheduler$.MODULE$:Lscala/actors/Scheduler$;
	astore	6
	aload	5
	aload	6
	invokevirtual	Method scala/actors/Actor$.rawSelf:(Lscala/actors/IScheduler;)Lscala/actors/Reactor;
	checkcast	class scala/actors/Actor
	astore	7
	aload_0
	getfield	Field scala$actors$remote$RemoteActor$$kernels:Lscala/collection/mutable/HashMap;
	getstatic	Field scala/Predef$Pair$.MODULE$:Lscala/Predef$Pair$;
	aload	7
	aload	8
	invokevirtual	Method scala/Predef$Pair$.apply:(Ljava/lang/Object;Ljava/lang/Object;)Lscala/Tuple2;
	invokevirtual	Method scala/collection/mutable/HashMap.$plus$eq:(Lscala/Tuple2;)Lscala/collection/mutable/HashMap;
	pop
	aload	7
	new	class scala/actors/remote/RemoteActor$$anonfun$createKernelOnPort$1
	dup
	aload	8
	aload	7
	invokespecial	Method scala/actors/remote/RemoteActor$$anonfun$createKernelOnPort$1."<init>":(Lscala/actors/remote/NetKernel;Lscala/actors/Actor;)V
	invokeinterface	InterfaceMethod scala/actors/Actor.onTerminate:(Lscala/Function0;)V
	aload	8
	goto	l4 // areturn
l3	aload	11
	instanceof	class scala/Some
	ifeq	l5 // new
	aload	11
	checkcast	class scala/Some
	astore	9
	aload	9
	invokevirtual	Method scala/Some.x:()Ljava/lang/Object;
	checkcast	class scala/actors/remote/NetKernel
	astore	10
	aload	10
l4	areturn
l5	new	class scala/MatchError
	dup
	aload	11
	invokevirtual	Method scala/Option.toString:()Ljava/lang/String;
	invokespecial	Method scala/MatchError."<init>":(Ljava/lang/String;)V
	athrow
  Labels:
   	l1 = 41 // aload
   	l2 = 49 // getstatic
   	l3 = 141 // aload
   	l4 = 168 // areturn
   	l5 = 169 // new
  LocalVariableTable: 
   Start  Length  Slot  Name   Signature
   0      182      0    this       Lscala/actors/remote/RemoteActor$;
   69      69      4    serv0       Lscala/actors/remote/TcpService;
   100      38      7    s$10       Lscala/actors/Actor;
   78      60      8    kern$10       Lscala/actors/remote/NetKernel;
   156      12      9    temp7       Lscala/Some;
   166      2      10    temp8       Lscala/actors/remote/NetKernel;
   25      157      11    temp5       Lscala/Option;


public void register(scala.Symbol, scala.actors.Actor);
  Signature: (Lscala/Symbol;Lscala/actors/Actor;)V
  Code:
   Stack=4, Locals=12, Args_size=3
	aload_0
	dup
	pop
	monitorenter
	aload_0
	getfield	Field scala$actors$remote$RemoteActor$$kernels:Lscala/collection/mutable/HashMap;
	getstatic	Field scala/actors/Actor$.MODULE$:Lscala/actors/Actor$;
	astore_3
	getstatic	Field scala/actors/Scheduler$.MODULE$:Lscala/actors/Scheduler$;
	astore	4
	aload_3
	aload	4
	invokevirtual	Method scala/actors/Actor$.rawSelf:(Lscala/actors/IScheduler;)Lscala/actors/Reactor;
	checkcast	class scala/actors/Actor
	invokevirtual	Method scala/collection/mutable/HashMap.get:(Ljava/lang/Object;)Lscala/Option;
	astore	11
	getstatic	Field scala/None$.MODULE$:Lscala/None$;
	dup
	ifnonnull	l1 // aload
	pop
	aload	11
	ifnull	l2 // getstatic
	goto	l3 // aload
l1	aload	11
	invokevirtual	Method java/lang/Object.equals:(Ljava/lang/Object;)Z
	ifeq	l3 // aload
l2	getstatic	Field scala/actors/remote/TcpService$.MODULE$:Lscala/actors/remote/TcpService$;
	getstatic	Field scala/actors/remote/TcpService$.MODULE$:Lscala/actors/remote/TcpService$;
	invokevirtual	Method scala/actors/remote/TcpService$.generatePort:()I
	aload_0
	invokespecial	Method cl:()Ljava/lang/ClassLoader;
	invokevirtual	Method scala/actors/remote/TcpService$.apply:(ILjava/lang/ClassLoader;)Lscala/actors/remote/TcpService;
	astore	7
	aload_0
	getfield	Field scala$actors$remote$RemoteActor$$kernels:Lscala/collection/mutable/HashMap;
	getstatic	Field scala/Predef$Pair$.MODULE$:Lscala/Predef$Pair$;
	getstatic	Field scala/actors/Actor$.MODULE$:Lscala/actors/Actor$;
	astore	5
	getstatic	Field scala/actors/Scheduler$.MODULE$:Lscala/actors/Scheduler$;
	astore	6
	aload	5
	aload	6
	invokevirtual	Method scala/actors/Actor$.rawSelf:(Lscala/actors/IScheduler;)Lscala/actors/Reactor;
	checkcast	class scala/actors/Actor
	aload	7
	invokeinterface	InterfaceMethod scala/actors/remote/Service.kernel:()Lscala/actors/remote/NetKernel;
	invokevirtual	Method scala/Predef$Pair$.apply:(Ljava/lang/Object;Ljava/lang/Object;)Lscala/Tuple2;
	invokevirtual	Method scala/collection/mutable/HashMap.$plus$eq:(Lscala/Tuple2;)Lscala/collection/mutable/HashMap;
	pop
	aload	7
	invokeinterface	InterfaceMethod scala/actors/remote/Service.kernel:()Lscala/actors/remote/NetKernel;
	goto	l4 // astore
l3	aload	11
	instanceof	class scala/Some
	ifeq	l5 // new
	aload	11
	checkcast	class scala/Some
	astore	8
	aload	8
	invokevirtual	Method scala/Some.x:()Ljava/lang/Object;
	checkcast	class scala/actors/remote/NetKernel
	astore	9
	aload	9
l4	astore	10
	aload	10
	aload_1
	aload_2
	invokevirtual	Method scala/actors/remote/NetKernel.register:(Lscala/Symbol;Lscala/actors/OutputChannel;)V
	aload_0
	monitorexit
	return
l5	new	class scala/MatchError
	dup
	aload	11
	invokevirtual	Method scala/Option.toString:()Ljava/lang/String;
	invokespecial	Method scala/MatchError."<init>":(Ljava/lang/String;)V
	athrow
	aload_0
	monitorexit
	athrow
  Labels:
   	l1 = 47 // aload
   	l2 = 55 // getstatic
   	l3 = 124 // aload
   	l4 = 151 // astore
   	l5 = 163 // new
  Exception table:
   from   to  target type
     4   162   176   any
   163   176   176   any
  LocalVariableTable: 
   Start  Length  Slot  Name   Signature
   0      179      0    this       Lscala/actors/remote/RemoteActor$;
   0      179      1    name       Lscala/Symbol;
   0      179      2    a       Lscala/actors/Actor;
   12      26      3    $inlThis1       Ljava/lang/Object;
   17      9      4    sched0       Lscala/actors/IScheduler;
   85      39      5    $inlThis4       Ljava/lang/Object;
   90      10      6    sched1       Lscala/actors/IScheduler;
   73      48      7    serv       Lscala/actors/remote/TcpService;
   139      12      8    temp3       Lscala/Some;
   149      2      9    temp4       Lscala/actors/remote/NetKernel;
   153      7      10    kernel       Lscala/actors/remote/NetKernel;
   31      131      11    temp1       Lscala/Option;
   163      13      11    temp1       Lscala/Option;


public scala.actors.remote.NetKernel createKernelOnPort(int);
  Signature: (I)Lscala/actors/remote/NetKernel;
  Code:
   Stack=5, Locals=5, Args_size=2
	getstatic	Field scala/actors/remote/TcpService$.MODULE$:Lscala/actors/remote/TcpService$;
	iload_1
	aload_0
	invokespecial	Method cl:()Ljava/lang/ClassLoader;
	invokevirtual	Method scala/actors/remote/TcpService$.apply:(ILjava/lang/ClassLoader;)Lscala/actors/remote/TcpService;
	astore_2
	aload_2
	invokeinterface	InterfaceMethod scala/actors/remote/Service.kernel:()Lscala/actors/remote/NetKernel;
	astore_3
	getstatic	Field scala/actors/Actor$.MODULE$:Lscala/actors/Actor$;
	invokevirtual	Method scala/actors/Actor$.self:()Lscala/actors/Actor;
	astore	4
	aload_0
	invokevirtual	Method scala$actors$remote$RemoteActor$$kernels:()Lscala/collection/mutable/HashMap;
	getstatic	Field scala/Predef$Pair$.MODULE$:Lscala/Predef$Pair$;
	aload	4
	aload_3
	invokevirtual	Method scala/Predef$Pair$.apply:(Ljava/lang/Object;Ljava/lang/Object;)Lscala/Tuple2;
	invokevirtual	Method scala/collection/mutable/HashMap.$plus$eq:(Lscala/Tuple2;)Lscala/collection/mutable/HashMap;
	pop
	aload	4
	new	class scala/actors/remote/RemoteActor$$anonfun$createKernelOnPort$1
	dup
	aload_3
	aload	4
	invokespecial	Method scala/actors/remote/RemoteActor$$anonfun$createKernelOnPort$1."<init>":(Lscala/actors/remote/NetKernel;Lscala/actors/Actor;)V
	invokeinterface	InterfaceMethod scala/actors/Actor.onTerminate:(Lscala/Function0;)V
	aload_3
	areturn
  Labels:
  LocalVariableTable: 
   Start  Length  Slot  Name   Signature
   0      63      0    this       Lscala/actors/remote/RemoteActor$;
   0      63      1    port       I
   12      50      2    serv       Lscala/actors/remote/TcpService;
   19      43      3    kern$1       Lscala/actors/remote/NetKernel;
   27      35      4    s$1       Lscala/actors/Actor;


public void alive(int);
  Signature: (I)V
  Code:
   Stack=5, Locals=7, Args_size=2
	aload_0
	dup
	pop
	monitorenter
	getstatic	Field scala/actors/remote/TcpService$.MODULE$:Lscala/actors/remote/TcpService$;
	iload_1
	aload_0
	invokespecial	Method cl:()Ljava/lang/ClassLoader;
	invokevirtual	Method scala/actors/remote/TcpService$.apply:(ILjava/lang/ClassLoader;)Lscala/actors/remote/TcpService;
	astore_2
	aload_2
	invokeinterface	InterfaceMethod scala/actors/remote/Service.kernel:()Lscala/actors/remote/NetKernel;
	astore	5
	getstatic	Field scala/actors/Actor$.MODULE$:Lscala/actors/Actor$;
	astore_3
	getstatic	Field scala/actors/Scheduler$.MODULE$:Lscala/actors/Scheduler$;
	astore	4
	aload_3
	aload	4
	invokevirtual	Method scala/actors/Actor$.rawSelf:(Lscala/actors/IScheduler;)Lscala/actors/Reactor;
	checkcast	class scala/actors/Actor
	astore	6
	aload_0
	getfield	Field scala$actors$remote$RemoteActor$$kernels:Lscala/collection/mutable/HashMap;
	getstatic	Field scala/Predef$Pair$.MODULE$:Lscala/Predef$Pair$;
	aload	6
	aload	5
	invokevirtual	Method scala/Predef$Pair$.apply:(Ljava/lang/Object;Ljava/lang/Object;)Lscala/Tuple2;
	invokevirtual	Method scala/collection/mutable/HashMap.$plus$eq:(Lscala/Tuple2;)Lscala/collection/mutable/HashMap;
	pop
	aload	6
	new	class scala/actors/remote/RemoteActor$$anonfun$createKernelOnPort$1
	dup
	aload	5
	aload	6
	invokespecial	Method scala/actors/remote/RemoteActor$$anonfun$createKernelOnPort$1."<init>":(Lscala/actors/remote/NetKernel;Lscala/actors/Actor;)V
	invokeinterface	InterfaceMethod scala/actors/Actor.onTerminate:(Lscala/Function0;)V
	aload_0
	monitorexit
	return
	aload_0
	monitorexit
	athrow
  Labels:
  Exception table:
   from   to  target type
     4    82    83   any
  LocalVariableTable: 
   Start  Length  Slot  Name   Signature
   0      86      0    this       Lscala/actors/remote/RemoteActor$;
   0      86      1    port       I
   16      64      2    serv0       Lscala/actors/remote/TcpService;
   28      52      3    $inlThis1       Ljava/lang/Object;
   33      9      4    sched0       Lscala/actors/IScheduler;
   24      56      5    kern$10       Lscala/actors/remote/NetKernel;
   44      36      6    s$10       Lscala/actors/Actor;


public void classLoader_$eq(java.lang.ClassLoader);
  Signature: (Ljava/lang/ClassLoader;)V
  Code:
   Stack=2, Locals=2, Args_size=2
	aload_0
	aload_1
	invokespecial	Method cl_$eq:(Ljava/lang/ClassLoader;)V
	return
  Labels:
  LocalVariableTable: 
   Start  Length  Slot  Name   Signature
   0      6      0    this       Lscala/actors/remote/RemoteActor$;
   0      6      1    x       Ljava/lang/ClassLoader;


public java.lang.ClassLoader classLoader();
  Signature: ()Ljava/lang/ClassLoader;
  Code:
   Stack=1, Locals=1, Args_size=1
	aload_0
	invokespecial	Method cl:()Ljava/lang/ClassLoader;
	areturn
  Labels:

private void cl_$eq(java.lang.ClassLoader);
  Signature: (Ljava/lang/ClassLoader;)V
  Code:
   Stack=2, Locals=2, Args_size=2
	aload_0
	aload_1
	putfield	Field cl:Ljava/lang/ClassLoader;
	return
  Labels:

private java.lang.ClassLoader cl();
  Signature: ()Ljava/lang/ClassLoader;
  Code:
   Stack=1, Locals=1, Args_size=1
	aload_0
	getfield	Field cl:Ljava/lang/ClassLoader;
	areturn
  Labels:

public final scala.collection.mutable.HashMap scala$actors$remote$RemoteActor$$kernels();
  Signature: ()Lscala/collection/mutable/HashMap;
  Code:
   Stack=1, Locals=1, Args_size=1
	aload_0
	getfield	Field scala$actors$remote$RemoteActor$$kernels:Lscala/collection/mutable/HashMap;
	areturn
  Labels:

}

