Compiled from "NetKernel.scala"
public class scala.actors.remote.RemoteApply0 extends java.lang.Object implements scala.ScalaObject,scala.Product,java.io.Serializable
  SourceFile: "NetKernel.scala"
  ScalaSig: length = 0x4C2
   05 00 FFFFFF81 26 06 08 01 02 FFFFFF84 FFFFFF80 FFFFFF80 FFFFFF80 40 09 02 0C
   52 65 6D 6F 74 65 41 70 70 6C 79 30 0A 02 03 04
   01 06 72 65 6D 6F 74 65 0A 02 05 06 01 06 61 63
   74 6F 72 73 0A 01 07 01 05 73 63 61 6C 61 03 00
   13 04 00 0A 12 16 10 02 0B 10 0D 01 0C 0A 02 0D
   0E 01 04 6C 61 6E 67 0A 01 0F 01 04 6A 61 76 61
   09 02 11 0C 02 06 4F 62 6A 65 63 74 10 02 13 14
   0D 01 06 09 02 15 06 02 0B 53 63 61 6C 61 4F 62
   6A 65 63 74 10 02 13 17 09 02 18 06 02 07 50 72
   6F 64 75 63 74 08 08 1A 00 FFFFFF82 FFFFFFCA FFFFFF80 FFFFFF84 00 1B 01
   09 73 65 6E 64 65 72 4C 6F 63 15 01 1C 10 02 1D
   1E 0D 01 02 09 02 1F 02 02 07 4C 6F 63 61 74 6F
   72 08 08 21 00 FFFFFF82 FFFFFF88 FFFFFFA0 FFFFFF80 04 1C 01 0A 73 65 6E
   64 65 72 4C 6F 63 20 08 08 23 00 FFFFFF82 FFFFFFCA FFFFFF80 FFFFFF84 00
   1B 01 0B 72 65 63 65 69 76 65 72 4C 6F 63 08 08
   25 00 FFFFFF82 FFFFFF88 FFFFFFA0 FFFFFF80 04 1C 01 0C 72 65 63 65 69 76
   65 72 4C 6F 63 20 08 08 27 00 FFFFFF82 FFFFFFCA FFFFFF80 FFFFFF84 00 28
   01 04 72 66 75 6E 15 01 29 10 05 13 2A 2C 30 33
   09 02 2B 06 02 09 46 75 6E 63 74 69 6F 6E 32 10
   02 2D 2E 0D 01 04 09 02 2F 04 02 0D 41 62 73 74
   72 61 63 74 41 63 74 6F 72 10 02 1D 31 09 02 32
   02 02 05 50 72 6F 78 79 10 02 13 34 09 02 35 06
   02 04 55 6E 69 74 08 08 37 00 FFFFFF82 FFFFFF88 FFFFFFA0 FFFFFF80 04 29
   01 05 72 66 75 6E 20 08 05 39 00 FFFFFF84 00 3A 01 06
   3C 69 6E 69 74 3E 14 04 3B 3C 3D 3E 10 02 1D 00
   08 05 1A 38 FFFFFFC0 00 1C 08 05 23 38 FFFFFFC0 00 1C 08 05
   27 38 FFFFFFC0 00 29 08 07 40 00 FFFFFF81 FFFFFF80 FFFFFF84 00 41 01 04
   63 6F 70 79 14 04 3B 42 43 44 08 07 1A 3F FFFFFF90 FFFFFF80
   FFFFFFC0 00 1C 08 07 23 3F FFFFFF90 FFFFFF80 FFFFFFC0 00 1C 08 07 27 3F
   FFFFFF90 FFFFFF80 FFFFFFC0 00 29 08 07 46 00 FFFFFF91 FFFFFF80 FFFFFF84 00 47 01 0E
   63 6F 70 79 24 64 65 66 61 75 6C 74 24 31 15 01
   48 2A 02 1C 49 2B 01 4A 10 02 4B 50 0D 01 4C 0A
   02 4D 4E 01 09 75 6E 63 68 65 63 6B 65 64 0A 02
   4F 06 01 0A 61 6E 6E 6F 74 61 74 69 6F 6E 09 02
   51 4C 02 11 75 6E 63 68 65 63 6B 65 64 56 61 72
   69 61 6E 63 65 08 07 53 00 FFFFFF91 FFFFFF80 FFFFFF84 00 47 01 0E
   63 6F 70 79 24 64 65 66 61 75 6C 74 24 32 08 07
   55 00 FFFFFF91 FFFFFF80 FFFFFF84 00 56 01 0E 63 6F 70 79 24 64 65
   66 61 75 6C 74 24 33 15 01 57 2A 02 29 49 08 08
   59 00 FFFFFF84 FFFFFF80 FFFFFF80 FFFFFF84 20 5A 01 08 68 61 73 68 43 6F
   64 65 14 01 5B 10 02 13 5C 09 02 5D 06 02 03 49
   6E 74 08 08 5F 00 FFFFFF84 FFFFFF80 FFFFFF80 FFFFFF84 20 60 01 08 74 6F
   53 74 72 69 6E 67 14 01 61 10 02 62 65 0E 02 13
   63 09 02 64 06 01 06 50 72 65 64 65 66 09 02 66
   67 02 06 53 74 72 69 6E 67 0A 02 64 06 08 08 69
   00 FFFFFF84 FFFFFF80 FFFFFF80 FFFFFF84 20 6A 01 06 65 71 75 61 6C 73 14
   02 6B 6E 10 02 13 6C 09 02 6D 06 02 07 42 6F 6F
   6C 65 61 6E 08 07 6F 68 FFFFFF81 FFFFFF80 FFFFFFC0 00 70 01 03 78
   24 31 10 02 13 71 09 02 72 06 02 03 41 6E 79 08
   08 74 00 FFFFFF84 FFFFFF80 FFFFFF80 FFFFFF84 20 75 01 0D 70 72 6F 64 75
   63 74 50 72 65 66 69 78 15 01 76 10 02 0B 77 09
   02 66 0C 08 08 79 00 FFFFFF84 FFFFFF80 FFFFFF80 FFFFFF84 20 7A 01 0C 70
   72 6F 64 75 63 74 41 72 69 74 79 15 01 5B 08 08
   7C 00 FFFFFF84 FFFFFF80 FFFFFF80 FFFFFF84 20 7D 01 0E 70 72 6F 64 75 63
   74 45 6C 65 6D 65 6E 74 14 02 70 7E 08 07 6F 7B
   FFFFFF81 FFFFFF80 FFFFFFC0 00 5B 08 0A FFFFFF81 00 00 FFFFFF84 FFFFFF80 FFFFFF80 FFFFFF84 20 FFFFFF81
   01 01 12 70 72 6F 64 75 63 74 45 6C 65 6D 65 6E
   74 4E 61 6D 65 14 03 76 FFFFFF81 02 08 07 6F 7F FFFFFF81 FFFFFF80
   FFFFFFC0 00 5B 08 0A FFFFFF81 04 00 FFFFFF84 FFFFFF80 FFFFFF80 FFFFFF84 20 FFFFFF81 05 01
   08 63 61 6E 45 71 75 61 6C 14 03 6B FFFFFF81 06 08 08
   6F FFFFFF81 03 FFFFFF81 FFFFFF80 FFFFFFC0 00 70 28 03 00 FFFFFF81 08 10 03 13
   FFFFFF81 09 09 03 FFFFFF81 0A 06 02 0C 73 65 72 69 61 6C 69
   7A 61 62 6C 65 07 09 FFFFFF81 0C 02 FFFFFF81 FFFFFF80 FFFFFF88 02 FFFFFF81 0D
   01 0C 52 65 6D 6F 74 65 41 70 70 6C 79 30 10 03
   1D FFFFFF81 0E 06 09 01 02 FFFFFF84 FFFFFF81 FFFFFF80 FFFFFF88 02 FFFFFF81 0F 13 06
   FFFFFF81 0E 0A FFFFFF81 10 12 10 07 13 FFFFFF81 11 1C 1C 29 3B 09
   03 FFFFFF81 12 06 02 09 46 75 6E 63 74 69 6F 6E 33 08
   07 39 FFFFFF81 0E FFFFFF84 00 FFFFFF81 14 14 02 FFFFFF81 0D 08 0A FFFFFF81 16
   FFFFFF81 0E FFFFFF81 FFFFFF80 FFFFFF84 40 FFFFFF81 17 01 05 61 70 70 6C 79 14
   07 3B FFFFFF81 18 FFFFFF81 19 FFFFFF81 1A 08 06 1A FFFFFF81 15 FFFFFFC0 00 1C
   08 06 23 FFFFFF81 15 FFFFFFC0 00 1C 08 06 27 FFFFFF81 15 FFFFFFC0 00 29
   08 0A FFFFFF81 1C FFFFFF81 0E FFFFFF81 FFFFFF80 FFFFFF84 40 FFFFFF81 1D 01 07 75 6E
   61 70 70 6C 79 14 04 FFFFFF81 1E FFFFFF81 24 10 05 13 FFFFFF81 1F
   FFFFFF81 21 09 03 FFFFFF81 20 06 02 06 4F 70 74 69 6F 6E 10
   06 13 FFFFFF81 22 1C 1C 29 09 03 FFFFFF81 23 06 02 06 54 75
   70 6C 65 33 08 07 FFFFFF81 25 FFFFFF81 1B FFFFFFC0 00 3B 01 03 78
   24 30 
  minor version: 0
  major version: 49
  Constant pool:
Asciz	SourceFile;
Asciz	NetKernel.scala;
Asciz	tupled;
Asciz	()Lscala/Function1;;
Asciz	Code;
Asciz	scala/actors/remote/RemoteApply0$;
class	scala/actors/remote/RemoteApply0$
Asciz	MODULE$;
Asciz	Lscala/actors/remote/RemoteApply0$;;
NameAndType	MODULE$:Lscala/actors/remote/RemoteApply0$;
Field	scala/actors/remote/RemoteApply0$.MODULE$:Lscala/actors/remote/RemoteApply0$;
NameAndType	tupled:()Lscala/Function1;
Method	scala/actors/remote/RemoteApply0$.tupled:()Lscala/Function1;
Asciz	curry;
NameAndType	curry:()Lscala/Function1;
Method	scala/actors/remote/RemoteApply0$.curry:()Lscala/Function1;
Asciz	Deprecated;
Asciz	curried;
NameAndType	curried:()Lscala/Function1;
Method	scala/actors/remote/RemoteApply0$.curried:()Lscala/Function1;
Asciz	rfun;
Asciz	Lscala/Function2;;
Asciz	Lscala/Function2<Lscala/actors/AbstractActor;Lscala/actors/remote/Proxy;Ljava/lang/Object;>;;
Asciz	Signature;
Asciz	receiverLoc;
Asciz	Lscala/actors/remote/Locator;;
Asciz	senderLoc;
Asciz	productIterator;
Asciz	()Lscala/collection/Iterator;;
Asciz	LineNumberTable;
Asciz	scala/Product$class;
class	scala/Product$class
Asciz	(Lscala/Product;)Lscala/collection/Iterator;;
NameAndType	productIterator:(Lscala/Product;)Lscala/collection/Iterator;
Method	scala/Product$class.productIterator:(Lscala/Product;)Lscala/collection/Iterator;
Asciz	productElements;
NameAndType	productElements:(Lscala/Product;)Lscala/collection/Iterator;
Method	scala/Product$class.productElements:(Lscala/Product;)Lscala/collection/Iterator;
Asciz	copy$default$3;
Asciz	()Lscala/Function2;;
Asciz	scala/actors/remote/RemoteApply0;
class	scala/actors/remote/RemoteApply0
NameAndType	rfun:()Lscala/Function2;
Method	scala/actors/remote/RemoteApply0.rfun:()Lscala/Function2;
Asciz	copy$default$2;
Asciz	()Lscala/actors/remote/Locator;;
NameAndType	receiverLoc:()Lscala/actors/remote/Locator;
Method	scala/actors/remote/RemoteApply0.receiverLoc:()Lscala/actors/remote/Locator;
Asciz	copy$default$1;
NameAndType	senderLoc:()Lscala/actors/remote/Locator;
Method	scala/actors/remote/RemoteApply0.senderLoc:()Lscala/actors/remote/Locator;
NameAndType	senderLoc:Lscala/actors/remote/Locator;
Field	scala/actors/remote/RemoteApply0.senderLoc:Lscala/actors/remote/Locator;
NameAndType	receiverLoc:Lscala/actors/remote/Locator;
Field	scala/actors/remote/RemoteApply0.receiverLoc:Lscala/actors/remote/Locator;
NameAndType	rfun:Lscala/Function2;
Field	scala/actors/remote/RemoteApply0.rfun:Lscala/Function2;
Asciz	()Lscala/Function2<Lscala/actors/AbstractActor;Lscala/actors/remote/Proxy;Ljava/lang/Object;>;;
Asciz	copy;
Asciz	(Lscala/actors/remote/Locator;Lscala/actors/remote/Locator;Lscala/Function2;)Lscala/actors/remote/RemoteApply0;;
Asciz	<init>;
Asciz	(Lscala/actors/remote/Locator;Lscala/actors/remote/Locator;Lscala/Function2;)V;
NameAndType	"<init>":(Lscala/actors/remote/Locator;Lscala/actors/remote/Locator;Lscala/Function2;)V
Method	scala/actors/remote/RemoteApply0."<init>":(Lscala/actors/remote/Locator;Lscala/actors/remote/Locator;Lscala/Function2;)V
Asciz	this;
Asciz	Lscala/actors/remote/RemoteApply0;;
Asciz	LocalVariableTable;
Asciz	hashCode;
Asciz	()I;
Asciz	scala/runtime/ScalaRunTime$;
class	scala/runtime/ScalaRunTime$
Asciz	Lscala/runtime/ScalaRunTime$;;
NameAndType	MODULE$:Lscala/runtime/ScalaRunTime$;
Field	scala/runtime/ScalaRunTime$.MODULE$:Lscala/runtime/ScalaRunTime$;
Asciz	_hashCode;
Asciz	(Lscala/Product;)I;
NameAndType	_hashCode:(Lscala/Product;)I
Method	scala/runtime/ScalaRunTime$._hashCode:(Lscala/Product;)I
Asciz	toString;
Asciz	()Ljava/lang/String;;
Asciz	_toString;
Asciz	(Lscala/Product;)Ljava/lang/String;;
NameAndType	_toString:(Lscala/Product;)Ljava/lang/String;
Method	scala/runtime/ScalaRunTime$._toString:(Lscala/Product;)Ljava/lang/String;
Asciz	equals;
Asciz	(Ljava/lang/Object;)Z;
Asciz	gd2$1;
Asciz	(Lscala/actors/remote/Locator;Lscala/actors/remote/Locator;Lscala/Function2;)Z;
NameAndType	gd2$1:(Lscala/actors/remote/Locator;Lscala/actors/remote/Locator;Lscala/Function2;)Z
Method	scala/actors/remote/RemoteApply0.gd2$1:(Lscala/actors/remote/Locator;Lscala/actors/remote/Locator;Lscala/Function2;)Z
Asciz	scala/Equals;
class	scala/Equals
Asciz	canEqual;
NameAndType	canEqual:(Ljava/lang/Object;)Z
InterfaceMethod	scala/Equals.canEqual:(Ljava/lang/Object;)Z
Asciz	temp10;
Asciz	temp11;
Asciz	temp12;
Asciz	temp13;
Asciz	productPrefix;
Asciz	RemoteApply0;
String	RemoteApply0
Asciz	productArity;
Asciz	productElement;
Asciz	(I)Ljava/lang/Object;;
Asciz	java/lang/IndexOutOfBoundsException;
class	java/lang/IndexOutOfBoundsException
Asciz	scala/runtime/BoxesRunTime;
class	scala/runtime/BoxesRunTime
Asciz	boxToInteger;
Asciz	(I)Ljava/lang/Integer;;
NameAndType	boxToInteger:(I)Ljava/lang/Integer;
Method	scala/runtime/BoxesRunTime.boxToInteger:(I)Ljava/lang/Integer;
Asciz	java/lang/Object;
class	java/lang/Object
NameAndType	toString:()Ljava/lang/String;
Method	java/lang/Object.toString:()Ljava/lang/String;
Asciz	(Ljava/lang/String;)V;
NameAndType	"<init>":(Ljava/lang/String;)V
Method	java/lang/IndexOutOfBoundsException."<init>":(Ljava/lang/String;)V
Asciz	productElementName;
Asciz	(I)Ljava/lang/String;;
String	rfun
String	receiverLoc
String	senderLoc
NameAndType	equals:(Ljava/lang/Object;)Z
Method	java/lang/Object.equals:(Ljava/lang/Object;)Z
Asciz	()V;
NameAndType	"<init>":()V
Method	java/lang/Object."<init>":()V
Asciz	$init$;
Asciz	(Lscala/Product;)V;
NameAndType	$init$:(Lscala/Product;)V
Method	scala/Product$class.$init$:(Lscala/Product;)V
Asciz	(Lscala/actors/remote/Locator;Lscala/actors/remote/Locator;Lscala/Function2<Lscala/actors/AbstractActor;Lscala/actors/remote/Proxy;Ljava/lang/Object;>;)V;
Asciz	ScalaSig;
Asciz	scala/ScalaObject;
class	scala/ScalaObject
Asciz	scala/Product;
class	scala/Product
Asciz	java/io/Serializable;
class	java/io/Serializable

{
private final scala.Function2 rfun;
  Signature: Lscala/Function2;
  Signature: length = 0x2
   00 17 

private final scala.actors.remote.Locator receiverLoc;
  Signature: Lscala/actors/remote/Locator;

private final scala.actors.remote.Locator senderLoc;
  Signature: Lscala/actors/remote/Locator;

public static final scala.Function1 tupled();
  Signature: ()Lscala/Function1;
  Code:
   Stack=1, Locals=0, Args_size=0
	getstatic	Field scala/actors/remote/RemoteApply0$.MODULE$:Lscala/actors/remote/RemoteApply0$;
	invokevirtual	Method scala/actors/remote/RemoteApply0$.tupled:()Lscala/Function1;
	areturn
  Labels:

public static final scala.Function1 curry();
  Signature: ()Lscala/Function1;
  Code:
   Stack=1, Locals=0, Args_size=0
	getstatic	Field scala/actors/remote/RemoteApply0$.MODULE$:Lscala/actors/remote/RemoteApply0$;
	invokevirtual	Method scala/actors/remote/RemoteApply0$.curry:()Lscala/Function1;
	areturn
  Labels:
  Deprecated: true

public static final scala.Function1 curried();
  Signature: ()Lscala/Function1;
  Code:
   Stack=1, Locals=0, Args_size=0
	getstatic	Field scala/actors/remote/RemoteApply0$.MODULE$:Lscala/actors/remote/RemoteApply0$;
	invokevirtual	Method scala/actors/remote/RemoteApply0$.curried:()Lscala/Function1;
	areturn
  Labels:

public scala.collection.Iterator productIterator();
  Signature: ()Lscala/collection/Iterator;
  Code:
   Stack=1, Locals=1, Args_size=1
	aload_0
	invokestatic	Method scala/Product$class.productIterator:(Lscala/Product;)Lscala/collection/Iterator;
	areturn
  Labels:

public scala.collection.Iterator productElements();
  Signature: ()Lscala/collection/Iterator;
  Code:
   Stack=1, Locals=1, Args_size=1
	aload_0
	invokestatic	Method scala/Product$class.productElements:(Lscala/Product;)Lscala/collection/Iterator;
	areturn
  Labels:
  Deprecated: true

public scala.Function2 copy$default$3();
  Signature: ()Lscala/Function2;
  Code:
   Stack=1, Locals=1, Args_size=1
	aload_0
	invokevirtual	Method rfun:()Lscala/Function2;
	areturn
  Labels:

public scala.actors.remote.Locator copy$default$2();
  Signature: ()Lscala/actors/remote/Locator;
  Code:
   Stack=1, Locals=1, Args_size=1
	aload_0
	invokevirtual	Method receiverLoc:()Lscala/actors/remote/Locator;
	areturn
  Labels:

public scala.actors.remote.Locator copy$default$1();
  Signature: ()Lscala/actors/remote/Locator;
  Code:
   Stack=1, Locals=1, Args_size=1
	aload_0
	invokevirtual	Method senderLoc:()Lscala/actors/remote/Locator;
	areturn
  Labels:

public scala.actors.remote.Locator senderLoc();
  Signature: ()Lscala/actors/remote/Locator;
  Code:
   Stack=1, Locals=1, Args_size=1
	aload_0
	getfield	Field senderLoc:Lscala/actors/remote/Locator;
	areturn
  Labels:

public scala.actors.remote.Locator receiverLoc();
  Signature: ()Lscala/actors/remote/Locator;
  Code:
   Stack=1, Locals=1, Args_size=1
	aload_0
	getfield	Field receiverLoc:Lscala/actors/remote/Locator;
	areturn
  Labels:

public scala.Function2 rfun();
  Signature: ()Lscala/Function2;
  Code:
   Stack=1, Locals=1, Args_size=1
	aload_0
	getfield	Field rfun:Lscala/Function2;
	areturn
  Labels:
  Signature: length = 0x2
   00 3A 

public scala.actors.remote.RemoteApply0 copy(scala.actors.remote.Locator, scala.actors.remote.Locator, scala.Function2);
  Signature: (Lscala/actors/remote/Locator;Lscala/actors/remote/Locator;Lscala/Function2;)Lscala/actors/remote/RemoteApply0;
  Code:
   Stack=5, Locals=4, Args_size=4
	new	class scala/actors/remote/RemoteApply0
	dup
	aload_1
	aload_2
	aload_3
	invokespecial	Method "<init>":(Lscala/actors/remote/Locator;Lscala/actors/remote/Locator;Lscala/Function2;)V
	areturn
  Labels:
  LocalVariableTable: 
   Start  Length  Slot  Name   Signature
   0      11      0    this       Lscala/actors/remote/RemoteApply0;
   0      11      1    senderLoc       Lscala/actors/remote/Locator;
   0      11      2    receiverLoc       Lscala/actors/remote/Locator;
   0      11      3    rfun       Lscala/Function2;


public int hashCode();
  Signature: ()I
  Code:
   Stack=2, Locals=1, Args_size=1
	getstatic	Field scala/runtime/ScalaRunTime$.MODULE$:Lscala/runtime/ScalaRunTime$;
	aload_0
	invokevirtual	Method scala/runtime/ScalaRunTime$._hashCode:(Lscala/Product;)I
	ireturn
  Labels:

public java.lang.String toString();
  Signature: ()Ljava/lang/String;
  Code:
   Stack=2, Locals=1, Args_size=1
	getstatic	Field scala/runtime/ScalaRunTime$.MODULE$:Lscala/runtime/ScalaRunTime$;
	aload_0
	invokevirtual	Method scala/runtime/ScalaRunTime$._toString:(Lscala/Product;)Ljava/lang/String;
	areturn
  Labels:

public boolean equals(java.lang.Object);
  Signature: (Ljava/lang/Object;)Z
  Code:
   Stack=4, Locals=6, Args_size=2
	aload_0
	aload_1
	if_acmpeq	l1 // iconst_1
	aload_1
	instanceof	class scala/actors/remote/RemoteApply0
	ifeq	l2 // iconst_0
	aload_1
	checkcast	class scala/actors/remote/RemoteApply0
	astore_2
	aload_2
	invokevirtual	Method senderLoc:()Lscala/actors/remote/Locator;
	astore_3
	aload_2
	invokevirtual	Method receiverLoc:()Lscala/actors/remote/Locator;
	astore	4
	aload_2
	invokevirtual	Method rfun:()Lscala/Function2;
	astore	5
	aload_0
	aload_3
	aload	4
	aload	5
	invokespecial	Method gd2$1:(Lscala/actors/remote/Locator;Lscala/actors/remote/Locator;Lscala/Function2;)Z
	ifeq	l3 // iconst_0
	aload_1
	checkcast	class scala/actors/remote/RemoteApply0
	aload_0
	invokeinterface	InterfaceMethod scala/Equals.canEqual:(Ljava/lang/Object;)Z
	goto	l4 // ifeq
l3	iconst_0
	goto	l4 // ifeq
l2	iconst_0
l4	ifeq	l5 // iconst_0
l1	iconst_1
	goto	l6 // ireturn
l5	iconst_0
l6	ireturn
  Labels:
   	l3 = 59 // iconst_0
   	l2 = 63 // iconst_0
   	l4 = 64 // ifeq
   	l1 = 67 // iconst_1
   	l5 = 71 // iconst_0
   	l6 = 72 // ireturn
  LocalVariableTable: 
   Start  Length  Slot  Name   Signature
   0      73      0    this       Lscala/actors/remote/RemoteApply0;
   17      46      2    temp10       Lscala/actors/remote/RemoteApply0;
   22      41      3    temp11       Lscala/actors/remote/Locator;
   28      35      4    temp12       Lscala/actors/remote/Locator;
   34      29      5    temp13       Lscala/Function2;


public java.lang.String productPrefix();
  Signature: ()Ljava/lang/String;
  Code:
   Stack=1, Locals=1, Args_size=1
	ldc	String RemoteApply0
	areturn
  Labels:

public int productArity();
  Signature: ()I
  Code:
   Stack=1, Locals=1, Args_size=1
	iconst_3
	ireturn
  Labels:

public java.lang.Object productElement(int);
  Signature: (I)Ljava/lang/Object;
  Code:
   Stack=3, Locals=2, Args_size=2
	iload_1
	tableswitch{ //0 to 2
		0: 57;
		1: 50;
		2: 43;
		default: 28 }
	new	class java/lang/IndexOutOfBoundsException
	dup
	iload_1
	invokestatic	Method scala/runtime/BoxesRunTime.boxToInteger:(I)Ljava/lang/Integer;
	invokevirtual	Method java/lang/Object.toString:()Ljava/lang/String;
	invokespecial	Method java/lang/IndexOutOfBoundsException."<init>":(Ljava/lang/String;)V
	athrow
	aload_0
	invokevirtual	Method rfun:()Lscala/Function2;
	goto	l1 // areturn
	aload_0
	invokevirtual	Method receiverLoc:()Lscala/actors/remote/Locator;
	goto	l1 // areturn
	aload_0
	invokevirtual	Method senderLoc:()Lscala/actors/remote/Locator;
l1	areturn
  Labels:
   	l1 = 61 // areturn

public java.lang.String productElementName(int);
  Signature: (I)Ljava/lang/String;
  Code:
   Stack=3, Locals=2, Args_size=2
	iload_1
	tableswitch{ //0 to 2
		0: 53;
		1: 48;
		2: 43;
		default: 28 }
	new	class java/lang/IndexOutOfBoundsException
	dup
	iload_1
	invokestatic	Method scala/runtime/BoxesRunTime.boxToInteger:(I)Ljava/lang/Integer;
	invokevirtual	Method java/lang/Object.toString:()Ljava/lang/String;
	invokespecial	Method java/lang/IndexOutOfBoundsException."<init>":(Ljava/lang/String;)V
	athrow
	ldc	String rfun
	goto	l1 // areturn
	ldc	String receiverLoc
	goto	l1 // areturn
	ldc	String senderLoc
l1	areturn
  Labels:
   	l1 = 55 // areturn

public boolean canEqual(java.lang.Object);
  Signature: (Ljava/lang/Object;)Z
  Code:
   Stack=1, Locals=2, Args_size=2
	aload_1
	instanceof	class scala/actors/remote/RemoteApply0
	ireturn
  Labels:

private final boolean gd2$1(scala.actors.remote.Locator, scala.actors.remote.Locator, scala.Function2);
  Signature: (Lscala/actors/remote/Locator;Lscala/actors/remote/Locator;Lscala/Function2;)Z
  Code:
   Stack=2, Locals=7, Args_size=4
	aload_1
	aload_0
	invokevirtual	Method senderLoc:()Lscala/actors/remote/Locator;
	astore	4
	dup
	ifnonnull	l1 // aload
	pop
	aload	4
	ifnull	l2 // aload_2
	goto	l3 // iconst_0
l1	aload	4
	invokevirtual	Method java/lang/Object.equals:(Ljava/lang/Object;)Z
	ifeq	l3 // iconst_0
l2	aload_2
	aload_0
	invokevirtual	Method receiverLoc:()Lscala/actors/remote/Locator;
	astore	5
	dup
	ifnonnull	l4 // aload
	pop
	aload	5
	ifnull	l5 // aload_3
	goto	l3 // iconst_0
l4	aload	5
	invokevirtual	Method java/lang/Object.equals:(Ljava/lang/Object;)Z
	ifeq	l3 // iconst_0
l5	aload_3
	aload_0
	invokevirtual	Method rfun:()Lscala/Function2;
	astore	6
	dup
	ifnonnull	l6 // aload
	pop
	aload	6
	ifnull	l7 // iconst_1
	goto	l3 // iconst_0
l6	aload	6
	invokevirtual	Method java/lang/Object.equals:(Ljava/lang/Object;)Z
	ifeq	l3 // iconst_0
l7	iconst_1
	goto	l8 // ireturn
l3	iconst_0
l8	ireturn
  Labels:
   	l1 = 20 // aload
   	l2 = 28 // aload_2
   	l4 = 48 // aload
   	l5 = 56 // aload_3
   	l6 = 76 // aload
   	l7 = 84 // iconst_1
   	l3 = 88 // iconst_0
   	l8 = 89 // ireturn

public scala.actors.remote.RemoteApply0(scala.actors.remote.Locator, scala.actors.remote.Locator, scala.Function2);
  Signature: (Lscala/actors/remote/Locator;Lscala/actors/remote/Locator;Lscala/Function2;)V
  Code:
   Stack=2, Locals=4, Args_size=4
	aload_0
	aload_1
	putfield	Field senderLoc:Lscala/actors/remote/Locator;
	aload_0
	aload_2
	putfield	Field receiverLoc:Lscala/actors/remote/Locator;
	aload_0
	aload_3
	putfield	Field rfun:Lscala/Function2;
	aload_0
	invokespecial	Method java/lang/Object."<init>":()V
	aload_0
	invokestatic	Method scala/Product$class.$init$:(Lscala/Product;)V
	return
  Labels:
  LocalVariableTable: 
   Start  Length  Slot  Name   Signature
   0      24      0    this       Lscala/actors/remote/RemoteApply0;
   0      24      1    senderLoc       Lscala/actors/remote/Locator;
   0      24      2    receiverLoc       Lscala/actors/remote/Locator;
   0      24      3    rfun       Lscala/Function2;

  Signature: length = 0x2
   00 FFFFFF87 

}

