Compiled from "RemoteActor.scala"
public final class scala.actors.remote.RemoteActor$$anonfun$createKernelOnPort$1 extends java.lang.Object implements scala.Function0,scala.ScalaObject,java.io.Serializable
  SourceFile: "RemoteActor.scala"
  Scala: length = 0x
   
  InnerClass: 
   public final #107= #9 of #106; //$anonfun$createKernelOnPort$1=class scala/actors/remote/RemoteActor$$anonfun$createKernelOnPort$1 of class scala/actors/remote/RemoteActor
  minor version: 0
  major version: 49
  Constant pool:
const #1 = Asciz	SourceFile;
const #2 = Asciz	RemoteActor.scala;
const #3 = Asciz	<clinit>;
const #4 = Asciz	()V;
const #5 = Asciz	Code;
const #6 = Asciz	serialVersionUID;
const #7 = Asciz	J;
const #8 = Asciz	scala/actors/remote/RemoteActor$$anonfun$createKernelOnPort$1;
const #9 = class	#8;	//  scala/actors/remote/RemoteActor$$anonfun$createKernelOnPort$1
const #10 = NameAndType	#6:#7;//  serialVersionUID:J
const #11 = Field	#9.#10;	//  scala/actors/remote/RemoteActor$$anonfun$createKernelOnPort$1.serialVersionUID:J
const #12 = Asciz	s$1;
const #13 = Asciz	Lscala/actors/Actor;;
const #14 = Asciz	kern$1;
const #15 = Asciz	Lscala/actors/remote/NetKernel;;
const #16 = Asciz	<init>;
const #17 = Asciz	(Lscala/actors/remote/NetKernel;Lscala/actors/Actor;)V;
const #18 = Asciz	LineNumberTable;
const #19 = NameAndType	#14:#15;//  kern$1:Lscala/actors/remote/NetKernel;
const #20 = Field	#9.#19;	//  scala/actors/remote/RemoteActor$$anonfun$createKernelOnPort$1.kern$1:Lscala/actors/remote/NetKernel;
const #21 = NameAndType	#12:#13;//  s$1:Lscala/actors/Actor;
const #22 = Field	#9.#21;	//  scala/actors/remote/RemoteActor$$anonfun$createKernelOnPort$1.s$1:Lscala/actors/Actor;
const #23 = Asciz	java/lang/Object;
const #24 = class	#23;	//  java/lang/Object
const #25 = NameAndType	#16:#4;//  "<init>":()V
const #26 = Method	#24.#25;	//  java/lang/Object."<init>":()V
const #27 = Asciz	scala/Function0$class;
const #28 = class	#27;	//  scala/Function0$class
const #29 = Asciz	$init$;
const #30 = Asciz	(Lscala/Function0;)V;
const #31 = NameAndType	#29:#30;//  $init$:(Lscala/Function0;)V
const #32 = Method	#28.#31;	//  scala/Function0$class.$init$:(Lscala/Function0;)V
const #33 = Asciz	apply;
const #34 = Asciz	()Ljava/lang/Object;;
const #35 = NameAndType	#33:#4;//  apply:()V
const #36 = Method	#9.#35;	//  scala/actors/remote/RemoteActor$$anonfun$createKernelOnPort$1.apply:()V
const #37 = Asciz	scala/runtime/BoxedUnit;
const #38 = class	#37;	//  scala/runtime/BoxedUnit
const #39 = Asciz	UNIT;
const #40 = Asciz	Lscala/runtime/BoxedUnit;;
const #41 = NameAndType	#39:#40;//  UNIT:Lscala/runtime/BoxedUnit;
const #42 = Field	#38.#41;	//  scala/runtime/BoxedUnit.UNIT:Lscala/runtime/BoxedUnit;
const #43 = Asciz	scala/actors/Debug$;
const #44 = class	#43;	//  scala/actors/Debug$
const #45 = Asciz	MODULE$;
const #46 = Asciz	Lscala/actors/Debug$;;
const #47 = NameAndType	#45:#46;//  MODULE$:Lscala/actors/Debug$;
const #48 = Field	#44.#47;	//  scala/actors/Debug$.MODULE$:Lscala/actors/Debug$;
const #49 = Asciz	scala/collection/mutable/StringBuilder;
const #50 = class	#49;	//  scala/collection/mutable/StringBuilder
const #51 = Method	#50.#25;	//  scala/collection/mutable/StringBuilder."<init>":()V
const #52 = Asciz	alive actor ;
const #53 = String	#52;	//  alive actor 
const #54 = Asciz	append;
const #55 = Asciz	(Ljava/lang/Object;)Lscala/collection/mutable/StringBuilder;;
const #56 = NameAndType	#54:#55;//  append:(Ljava/lang/Object;)Lscala/collection/mutable/StringBuilder;
const #57 = Method	#50.#56;	//  scala/collection/mutable/StringBuilder.append:(Ljava/lang/Object;)Lscala/collection/mutable/StringBuilder;
const #58 = Asciz	 terminated;
const #59 = String	#58;	//   terminated
const #60 = Asciz	toString;
const #61 = Asciz	()Ljava/lang/String;;
const #62 = NameAndType	#60:#61;//  toString:()Ljava/lang/String;
const #63 = Method	#50.#62;	//  scala/collection/mutable/StringBuilder.toString:()Ljava/lang/String;
const #64 = Asciz	info;
const #65 = Asciz	(Ljava/lang/String;)V;
const #66 = NameAndType	#64:#65;//  info:(Ljava/lang/String;)V
const #67 = Method	#44.#66;	//  scala/actors/Debug$.info:(Ljava/lang/String;)V
const #68 = Asciz	scala/actors/remote/RemoteActor$;
const #69 = class	#68;	//  scala/actors/remote/RemoteActor$
const #70 = Asciz	Lscala/actors/remote/RemoteActor$;;
const #71 = NameAndType	#45:#70;//  MODULE$:Lscala/actors/remote/RemoteActor$;
const #72 = Field	#69.#71;	//  scala/actors/remote/RemoteActor$.MODULE$:Lscala/actors/remote/RemoteActor$;
const #73 = Asciz	scala$actors$remote$RemoteActor$$kernels;
const #74 = Asciz	()Lscala/collection/mutable/HashMap;;
const #75 = NameAndType	#73:#74;//  scala$actors$remote$RemoteActor$$kernels:()Lscala/collection/mutable/HashMap;
const #76 = Method	#69.#75;	//  scala/actors/remote/RemoteActor$.scala$actors$remote$RemoteActor$$kernels:()Lscala/collection/mutable/HashMap;
const #77 = Asciz	scala/collection/mutable/HashMap;
const #78 = class	#77;	//  scala/collection/mutable/HashMap
const #79 = Asciz	$minus$eq;
const #80 = Asciz	(Ljava/lang/Object;)Lscala/collection/mutable/HashMap;;
const #81 = NameAndType	#79:#80;//  $minus$eq:(Ljava/lang/Object;)Lscala/collection/mutable/HashMap;
const #82 = Method	#78.#81;	//  scala/collection/mutable/HashMap.$minus$eq:(Ljava/lang/Object;)Lscala/collection/mutable/HashMap;
const #83 = Asciz	valuesIterator;
const #84 = Asciz	()Lscala/collection/Iterator;;
const #85 = NameAndType	#83:#84;//  valuesIterator:()Lscala/collection/Iterator;
const #86 = Method	#78.#85;	//  scala/collection/mutable/HashMap.valuesIterator:()Lscala/collection/Iterator;
const #87 = Asciz	scala/collection/Iterator;
const #88 = class	#87;	//  scala/collection/Iterator
const #89 = Asciz	contains;
const #90 = Asciz	(Ljava/lang/Object;)Z;
const #91 = NameAndType	#89:#90;//  contains:(Ljava/lang/Object;)Z
const #92 = InterfaceMethod	#88.#91;	//  scala/collection/Iterator.contains:(Ljava/lang/Object;)Z
const #93 = Asciz	terminating ;
const #94 = String	#93;	//  terminating 
const #95 = Asciz	scala/actors/remote/NetKernel;
const #96 = class	#95;	//  scala/actors/remote/NetKernel
const #97 = Asciz	terminate;
const #98 = NameAndType	#97:#4;//  terminate:()V
const #99 = Method	#96.#98;	//  scala/actors/remote/NetKernel.terminate:()V
const #100 = Asciz	(Lscala/Function0;)Ljava/lang/String;;
const #101 = NameAndType	#60:#100;//  toString:(Lscala/Function0;)Ljava/lang/String;
const #102 = Method	#28.#101;	//  scala/Function0$class.toString:(Lscala/Function0;)Ljava/lang/String;
const #103 = Asciz	Scala;
const #104 = Asciz	InnerClasses;
const #105 = Asciz	scala/actors/remote/RemoteActor;
const #106 = class	#105;	//  scala/actors/remote/RemoteActor
const #107 = Asciz	$anonfun$createKernelOnPort$1;
const #108 = Asciz	scala/Function0;
const #109 = class	#108;	//  scala/Function0
const #110 = Asciz	scala/ScalaObject;
const #111 = class	#110;	//  scala/ScalaObject
const #112 = Asciz	java/io/Serializable;
const #113 = class	#112;	//  java/io/Serializable

{
public static final long serialVersionUID;

public static {};
  Code:
   Stack=2, Locals=0, Args_size=0
   0:	lconst_0
   1:	putstatic	#11; //Field serialVersionUID:J
   4:	return

public scala.actors.remote.RemoteActor$$anonfun$createKernelOnPort$1(scala.actors.remote.NetKernel, scala.actors.Actor);
  Code:
   Stack=2, Locals=3, Args_size=3
   0:	aload_0
   1:	aload_1
   2:	putfield	#20; //Field kern$1:Lscala/actors/remote/NetKernel;
   5:	aload_0
   6:	aload_2
   7:	putfield	#22; //Field s$1:Lscala/actors/Actor;
   10:	aload_0
   11:	invokespecial	#26; //Method java/lang/Object."<init>":()V
   14:	aload_0
   15:	invokestatic	#32; //Method scala/Function0$class.$init$:(Lscala/Function0;)V
   18:	return
  LineNumberTable: 
   line 72: 0


public final java.lang.Object apply();
  Code:
   Stack=1, Locals=1, Args_size=1
   0:	aload_0
   1:	invokevirtual	#36; //Method apply:()V
   4:	getstatic	#42; //Field scala/runtime/BoxedUnit.UNIT:Lscala/runtime/BoxedUnit;
   7:	areturn
  LineNumberTable: 
   line 72: 0


public final void apply();
  Code:
   Stack=3, Locals=1, Args_size=1
   0:	getstatic	#48; //Field scala/actors/Debug$.MODULE$:Lscala/actors/Debug$;
   3:	new	#50; //class scala/collection/mutable/StringBuilder
   6:	dup
   7:	invokespecial	#51; //Method scala/collection/mutable/StringBuilder."<init>":()V
   10:	ldc	#53; //String alive actor 
   12:	invokevirtual	#57; //Method scala/collection/mutable/StringBuilder.append:(Ljava/lang/Object;)Lscala/collection/mutable/StringBuilder;
   15:	aload_0
   16:	getfield	#22; //Field s$1:Lscala/actors/Actor;
   19:	invokevirtual	#57; //Method scala/collection/mutable/StringBuilder.append:(Ljava/lang/Object;)Lscala/collection/mutable/StringBuilder;
   22:	ldc	#59; //String  terminated
   24:	invokevirtual	#57; //Method scala/collection/mutable/StringBuilder.append:(Ljava/lang/Object;)Lscala/collection/mutable/StringBuilder;
   27:	invokevirtual	#63; //Method scala/collection/mutable/StringBuilder.toString:()Ljava/lang/String;
   30:	invokevirtual	#67; //Method scala/actors/Debug$.info:(Ljava/lang/String;)V
   33:	getstatic	#72; //Field scala/actors/remote/RemoteActor$.MODULE$:Lscala/actors/remote/RemoteActor$;
   36:	invokevirtual	#76; //Method scala/actors/remote/RemoteActor$.scala$actors$remote$RemoteActor$$kernels:()Lscala/collection/mutable/HashMap;
   39:	aload_0
   40:	getfield	#22; //Field s$1:Lscala/actors/Actor;
   43:	invokevirtual	#82; //Method scala/collection/mutable/HashMap.$minus$eq:(Ljava/lang/Object;)Lscala/collection/mutable/HashMap;
   46:	pop
   47:	getstatic	#72; //Field scala/actors/remote/RemoteActor$.MODULE$:Lscala/actors/remote/RemoteActor$;
   50:	invokevirtual	#76; //Method scala/actors/remote/RemoteActor$.scala$actors$remote$RemoteActor$$kernels:()Lscala/collection/mutable/HashMap;
   53:	invokevirtual	#86; //Method scala/collection/mutable/HashMap.valuesIterator:()Lscala/collection/Iterator;
   56:	aload_0
   57:	getfield	#20; //Field kern$1:Lscala/actors/remote/NetKernel;
   60:	invokeinterface	#92,  2; //InterfaceMethod scala/collection/Iterator.contains:(Ljava/lang/Object;)Z
   65:	ifne	103
   68:	getstatic	#48; //Field scala/actors/Debug$.MODULE$:Lscala/actors/Debug$;
   71:	new	#50; //class scala/collection/mutable/StringBuilder
   74:	dup
   75:	invokespecial	#51; //Method scala/collection/mutable/StringBuilder."<init>":()V
   78:	ldc	#94; //String terminating 
   80:	invokevirtual	#57; //Method scala/collection/mutable/StringBuilder.append:(Ljava/lang/Object;)Lscala/collection/mutable/StringBuilder;
   83:	aload_0
   84:	getfield	#20; //Field kern$1:Lscala/actors/remote/NetKernel;
   87:	invokevirtual	#57; //Method scala/collection/mutable/StringBuilder.append:(Ljava/lang/Object;)Lscala/collection/mutable/StringBuilder;
   90:	invokevirtual	#63; //Method scala/collection/mutable/StringBuilder.toString:()Ljava/lang/String;
   93:	invokevirtual	#67; //Method scala/actors/Debug$.info:(Ljava/lang/String;)V
   96:	aload_0
   97:	getfield	#20; //Field kern$1:Lscala/actors/remote/NetKernel;
   100:	invokevirtual	#99; //Method scala/actors/remote/NetKernel.terminate:()V
   103:	return
  LineNumberTable: 
   line 73: 0
   line 75: 33
   line 78: 47
   line 79: 68
   line 81: 96
   line 72: 103


public java.lang.String toString();
  Code:
   Stack=1, Locals=1, Args_size=1
   0:	aload_0
   1:	invokestatic	#102; //Method scala/Function0$class.toString:(Lscala/Function0;)Ljava/lang/String;
   4:	areturn
  LineNumberTable: 
   line 72: 0


}

