Compiled from "RemoteActor.scala"
public final class scala.actors.remote.RemoteActor$ extends java.lang.Object implements scala.ScalaObject
  SourceFile: "RemoteActor.scala"
  Scala: length = 0x
   
  InnerClass: 
   public final #203= #130 of #202; //$anonfun$createKernelOnPort$1=class scala/actors/remote/RemoteActor$$anonfun$createKernelOnPort$1 of class scala/actors/remote/RemoteActor
  minor version: 0
  major version: 49
  Constant pool:
const #1 = Asciz	SourceFile;
const #2 = Asciz	RemoteActor.scala;
const #3 = Asciz	Scala;
const #4 = Asciz	MODULE$;
const #5 = Asciz	Lscala/actors/remote/RemoteActor$;;
const #6 = Asciz	<clinit>;
const #7 = Asciz	()V;
const #8 = Asciz	Code;
const #9 = Asciz	scala/actors/remote/RemoteActor$;
const #10 = class	#9;	//  scala/actors/remote/RemoteActor$
const #11 = Asciz	<init>;
const #12 = NameAndType	#11:#7;//  "<init>":()V
const #13 = Method	#10.#12;	//  scala/actors/remote/RemoteActor$."<init>":()V
const #14 = Asciz	cl;
const #15 = Asciz	Ljava/lang/ClassLoader;;
const #16 = Asciz	scala$actors$remote$RemoteActor$$kernels;
const #17 = Asciz	Lscala/collection/mutable/HashMap;;
const #18 = Asciz	LineNumberTable;
const #19 = Asciz	java/lang/Object;
const #20 = class	#19;	//  java/lang/Object
const #21 = Method	#20.#12;	//  java/lang/Object."<init>":()V
const #22 = NameAndType	#4:#5;//  MODULE$:Lscala/actors/remote/RemoteActor$;
const #23 = Field	#10.#22;	//  scala/actors/remote/RemoteActor$.MODULE$:Lscala/actors/remote/RemoteActor$;
const #24 = Asciz	scala/collection/mutable/HashMap;
const #25 = class	#24;	//  scala/collection/mutable/HashMap
const #26 = Method	#25.#12;	//  scala/collection/mutable/HashMap."<init>":()V
const #27 = NameAndType	#16:#17;//  scala$actors$remote$RemoteActor$$kernels:Lscala/collection/mutable/HashMap;
const #28 = Field	#10.#27;	//  scala/actors/remote/RemoteActor$.scala$actors$remote$RemoteActor$$kernels:Lscala/collection/mutable/HashMap;
const #29 = NameAndType	#14:#15;//  cl:Ljava/lang/ClassLoader;
const #30 = Field	#10.#29;	//  scala/actors/remote/RemoteActor$.cl:Ljava/lang/ClassLoader;
const #31 = Asciz	someKernel;
const #32 = Asciz	()Lscala/actors/remote/NetKernel;;
const #33 = Asciz	()Lscala/collection/mutable/HashMap;;
const #34 = NameAndType	#16:#33;//  scala$actors$remote$RemoteActor$$kernels:()Lscala/collection/mutable/HashMap;
const #35 = Method	#10.#34;	//  scala/actors/remote/RemoteActor$.scala$actors$remote$RemoteActor$$kernels:()Lscala/collection/mutable/HashMap;
const #36 = Asciz	valuesIterator;
const #37 = Asciz	()Lscala/collection/Iterator;;
const #38 = NameAndType	#36:#37;//  valuesIterator:()Lscala/collection/Iterator;
const #39 = Method	#25.#38;	//  scala/collection/mutable/HashMap.valuesIterator:()Lscala/collection/Iterator;
const #40 = Asciz	scala/collection/Iterator;
const #41 = class	#40;	//  scala/collection/Iterator
const #42 = Asciz	next;
const #43 = Asciz	()Ljava/lang/Object;;
const #44 = NameAndType	#42:#43;//  next:()Ljava/lang/Object;
const #45 = InterfaceMethod	#41.#44;	//  scala/collection/Iterator.next:()Ljava/lang/Object;
const #46 = Asciz	scala/actors/remote/NetKernel;
const #47 = class	#46;	//  scala/actors/remote/NetKernel
const #48 = Asciz	select;
const #49 = Asciz	(Lscala/actors/remote/Node;Lscala/Symbol;)Lscala/actors/AbstractActor;;
const #50 = Asciz	selfKernel;
const #51 = NameAndType	#50:#32;//  selfKernel:()Lscala/actors/remote/NetKernel;
const #52 = Method	#10.#51;	//  scala/actors/remote/RemoteActor$.selfKernel:()Lscala/actors/remote/NetKernel;
const #53 = Asciz	getOrCreateProxy;
const #54 = Asciz	(Lscala/actors/remote/Node;Lscala/Symbol;)Lscala/actors/remote/Proxy;;
const #55 = NameAndType	#53:#54;//  getOrCreateProxy:(Lscala/actors/remote/Node;Lscala/Symbol;)Lscala/actors/remote/Proxy;
const #56 = Method	#47.#55;	//  scala/actors/remote/NetKernel.getOrCreateProxy:(Lscala/actors/remote/Node;Lscala/Symbol;)Lscala/actors/remote/Proxy;
const #57 = Asciz	scala/actors/AbstractActor;
const #58 = class	#57;	//  scala/actors/AbstractActor
const #59 = Asciz	java/lang/Throwable;
const #60 = class	#59;	//  java/lang/Throwable
const #61 = Asciz	this;
const #62 = Asciz	node;
const #63 = Asciz	Lscala/actors/remote/Node;;
const #64 = Asciz	sym;
const #65 = Asciz	Lscala/Symbol;;
const #66 = Asciz	LocalVariableTable;
const #67 = Asciz	scala/actors/Actor$;
const #68 = class	#67;	//  scala/actors/Actor$
const #69 = Asciz	Lscala/actors/Actor$;;
const #70 = NameAndType	#4:#69;//  MODULE$:Lscala/actors/Actor$;
const #71 = Field	#68.#70;	//  scala/actors/Actor$.MODULE$:Lscala/actors/Actor$;
const #72 = Asciz	scala/actors/Scheduler$;
const #73 = class	#72;	//  scala/actors/Scheduler$
const #74 = Asciz	Lscala/actors/Scheduler$;;
const #75 = NameAndType	#4:#74;//  MODULE$:Lscala/actors/Scheduler$;
const #76 = Field	#73.#75;	//  scala/actors/Scheduler$.MODULE$:Lscala/actors/Scheduler$;
const #77 = Asciz	rawSelf;
const #78 = Asciz	(Lscala/actors/IScheduler;)Lscala/actors/Reactor;;
const #79 = NameAndType	#77:#78;//  rawSelf:(Lscala/actors/IScheduler;)Lscala/actors/Reactor;
const #80 = Method	#68.#79;	//  scala/actors/Actor$.rawSelf:(Lscala/actors/IScheduler;)Lscala/actors/Reactor;
const #81 = Asciz	scala/actors/Actor;
const #82 = class	#81;	//  scala/actors/Actor
const #83 = Asciz	get;
const #84 = Asciz	(Ljava/lang/Object;)Lscala/Option;;
const #85 = NameAndType	#83:#84;//  get:(Ljava/lang/Object;)Lscala/Option;
const #86 = Method	#25.#85;	//  scala/collection/mutable/HashMap.get:(Ljava/lang/Object;)Lscala/Option;
const #87 = Asciz	scala/None$;
const #88 = class	#87;	//  scala/None$
const #89 = Asciz	Lscala/None$;;
const #90 = NameAndType	#4:#89;//  MODULE$:Lscala/None$;
const #91 = Field	#88.#90;	//  scala/None$.MODULE$:Lscala/None$;
const #92 = Asciz	equals;
const #93 = Asciz	(Ljava/lang/Object;)Z;
const #94 = NameAndType	#92:#93;//  equals:(Ljava/lang/Object;)Z
const #95 = Method	#20.#94;	//  java/lang/Object.equals:(Ljava/lang/Object;)Z
const #96 = Asciz	scala/actors/remote/TcpService$;
const #97 = class	#96;	//  scala/actors/remote/TcpService$
const #98 = Asciz	Lscala/actors/remote/TcpService$;;
const #99 = NameAndType	#4:#98;//  MODULE$:Lscala/actors/remote/TcpService$;
const #100 = Field	#97.#99;	//  scala/actors/remote/TcpService$.MODULE$:Lscala/actors/remote/TcpService$;
const #101 = Asciz	generatePort;
const #102 = Asciz	()I;
const #103 = NameAndType	#101:#102;//  generatePort:()I
const #104 = Method	#97.#103;	//  scala/actors/remote/TcpService$.generatePort:()I
const #105 = Asciz	()Ljava/lang/ClassLoader;;
const #106 = NameAndType	#14:#105;//  cl:()Ljava/lang/ClassLoader;
const #107 = Method	#10.#106;	//  scala/actors/remote/RemoteActor$.cl:()Ljava/lang/ClassLoader;
const #108 = Asciz	apply;
const #109 = Asciz	(ILjava/lang/ClassLoader;)Lscala/actors/remote/TcpService;;
const #110 = NameAndType	#108:#109;//  apply:(ILjava/lang/ClassLoader;)Lscala/actors/remote/TcpService;
const #111 = Method	#97.#110;	//  scala/actors/remote/TcpService$.apply:(ILjava/lang/ClassLoader;)Lscala/actors/remote/TcpService;
const #112 = Asciz	scala/actors/remote/Service;
const #113 = class	#112;	//  scala/actors/remote/Service
const #114 = Asciz	kernel;
const #115 = NameAndType	#114:#32;//  kernel:()Lscala/actors/remote/NetKernel;
const #116 = InterfaceMethod	#113.#115;	//  scala/actors/remote/Service.kernel:()Lscala/actors/remote/NetKernel;
const #117 = Asciz	scala/Predef$Pair$;
const #118 = class	#117;	//  scala/Predef$Pair$
const #119 = Asciz	Lscala/Predef$Pair$;;
const #120 = NameAndType	#4:#119;//  MODULE$:Lscala/Predef$Pair$;
const #121 = Field	#118.#120;	//  scala/Predef$Pair$.MODULE$:Lscala/Predef$Pair$;
const #122 = Asciz	(Ljava/lang/Object;Ljava/lang/Object;)Lscala/Tuple2;;
const #123 = NameAndType	#108:#122;//  apply:(Ljava/lang/Object;Ljava/lang/Object;)Lscala/Tuple2;
const #124 = Method	#118.#123;	//  scala/Predef$Pair$.apply:(Ljava/lang/Object;Ljava/lang/Object;)Lscala/Tuple2;
const #125 = Asciz	$plus$eq;
const #126 = Asciz	(Lscala/Tuple2;)Lscala/collection/mutable/HashMap;;
const #127 = NameAndType	#125:#126;//  $plus$eq:(Lscala/Tuple2;)Lscala/collection/mutable/HashMap;
const #128 = Method	#25.#127;	//  scala/collection/mutable/HashMap.$plus$eq:(Lscala/Tuple2;)Lscala/collection/mutable/HashMap;
const #129 = Asciz	scala/actors/remote/RemoteActor$$anonfun$createKernelOnPort$1;
const #130 = class	#129;	//  scala/actors/remote/RemoteActor$$anonfun$createKernelOnPort$1
const #131 = Asciz	(Lscala/actors/remote/NetKernel;Lscala/actors/Actor;)V;
const #132 = NameAndType	#11:#131;//  "<init>":(Lscala/actors/remote/NetKernel;Lscala/actors/Actor;)V
const #133 = Method	#130.#132;	//  scala/actors/remote/RemoteActor$$anonfun$createKernelOnPort$1."<init>":(Lscala/actors/remote/NetKernel;Lscala/actors/Actor;)V
const #134 = Asciz	onTerminate;
const #135 = Asciz	(Lscala/Function0;)V;
const #136 = NameAndType	#134:#135;//  onTerminate:(Lscala/Function0;)V
const #137 = InterfaceMethod	#82.#136;	//  scala/actors/Actor.onTerminate:(Lscala/Function0;)V
const #138 = Asciz	scala/MatchError;
const #139 = class	#138;	//  scala/MatchError
const #140 = Asciz	scala/Option;
const #141 = class	#140;	//  scala/Option
const #142 = Asciz	toString;
const #143 = Asciz	()Ljava/lang/String;;
const #144 = NameAndType	#142:#143;//  toString:()Ljava/lang/String;
const #145 = Method	#141.#144;	//  scala/Option.toString:()Ljava/lang/String;
const #146 = Asciz	(Ljava/lang/String;)V;
const #147 = NameAndType	#11:#146;//  "<init>":(Ljava/lang/String;)V
const #148 = Method	#139.#147;	//  scala/MatchError."<init>":(Ljava/lang/String;)V
const #149 = Asciz	scala/Some;
const #150 = class	#149;	//  scala/Some
const #151 = Asciz	x;
const #152 = NameAndType	#151:#43;//  x:()Ljava/lang/Object;
const #153 = Method	#150.#152;	//  scala/Some.x:()Ljava/lang/Object;
const #154 = Asciz	serv0;
const #155 = Asciz	Lscala/actors/remote/TcpService;;
const #156 = Asciz	s$10;
const #157 = Asciz	Lscala/actors/Actor;;
const #158 = Asciz	kern$10;
const #159 = Asciz	Lscala/actors/remote/NetKernel;;
const #160 = Asciz	temp7;
const #161 = Asciz	Lscala/Some;;
const #162 = Asciz	temp8;
const #163 = Asciz	temp5;
const #164 = Asciz	Lscala/Option;;
const #165 = Asciz	register;
const #166 = Asciz	(Lscala/Symbol;Lscala/actors/Actor;)V;
const #167 = Asciz	(Lscala/Symbol;Lscala/actors/OutputChannel;)V;
const #168 = NameAndType	#165:#167;//  register:(Lscala/Symbol;Lscala/actors/OutputChannel;)V
const #169 = Method	#47.#168;	//  scala/actors/remote/NetKernel.register:(Lscala/Symbol;Lscala/actors/OutputChannel;)V
const #170 = Asciz	name;
const #171 = Asciz	a;
const #172 = Asciz	$inlThis1;
const #173 = Asciz	Ljava/lang/Object;;
const #174 = Asciz	sched0;
const #175 = Asciz	Lscala/actors/IScheduler;;
const #176 = Asciz	$inlThis4;
const #177 = Asciz	sched1;
const #178 = Asciz	serv;
const #179 = Asciz	temp3;
const #180 = Asciz	temp4;
const #181 = Asciz	temp1;
const #182 = Asciz	createKernelOnPort;
const #183 = Asciz	(I)Lscala/actors/remote/NetKernel;;
const #184 = Asciz	self;
const #185 = Asciz	()Lscala/actors/Actor;;
const #186 = NameAndType	#184:#185;//  self:()Lscala/actors/Actor;
const #187 = Method	#68.#186;	//  scala/actors/Actor$.self:()Lscala/actors/Actor;
const #188 = Asciz	port;
const #189 = Asciz	I;
const #190 = Asciz	kern$1;
const #191 = Asciz	s$1;
const #192 = Asciz	alive;
const #193 = Asciz	(I)V;
const #194 = Asciz	classLoader_$eq;
const #195 = Asciz	(Ljava/lang/ClassLoader;)V;
const #196 = Asciz	cl_$eq;
const #197 = NameAndType	#196:#195;//  cl_$eq:(Ljava/lang/ClassLoader;)V
const #198 = Method	#10.#197;	//  scala/actors/remote/RemoteActor$.cl_$eq:(Ljava/lang/ClassLoader;)V
const #199 = Asciz	classLoader;
const #200 = Asciz	InnerClasses;
const #201 = Asciz	scala/actors/remote/RemoteActor;
const #202 = class	#201;	//  scala/actors/remote/RemoteActor
const #203 = Asciz	$anonfun$createKernelOnPort$1;
const #204 = Asciz	scala/ScalaObject;
const #205 = class	#204;	//  scala/ScalaObject

{
public static final scala.actors.remote.RemoteActor$ MODULE$;

public static {};
  Code:
   Stack=1, Locals=0, Args_size=0
   0:	new	#10; //class scala/actors/remote/RemoteActor$
   3:	invokespecial	#13; //Method "<init>":()V
   6:	return

public scala.actors.remote.NetKernel someKernel();
  Code:
   Stack=1, Locals=1, Args_size=1
   0:	aload_0
   1:	invokevirtual	#35; //Method scala$actors$remote$RemoteActor$$kernels:()Lscala/collection/mutable/HashMap;
   4:	invokevirtual	#39; //Method scala/collection/mutable/HashMap.valuesIterator:()Lscala/collection/Iterator;
   7:	invokeinterface	#45,  1; //InterfaceMethod scala/collection/Iterator.next:()Ljava/lang/Object;
   12:	checkcast	#47; //class scala/actors/remote/NetKernel
   15:	areturn
  LineNumberTable: 
   line 122: 0


public scala.actors.AbstractActor select(scala.actors.remote.Node, scala.Symbol);
  Code:
   Stack=3, Locals=3, Args_size=3
   0:	aload_0
   1:	dup
   2:	pop
   3:	monitorenter
   4:	aload_0
   5:	invokespecial	#52; //Method selfKernel:()Lscala/actors/remote/NetKernel;
   8:	aload_1
   9:	aload_2
   10:	invokevirtual	#56; //Method scala/actors/remote/NetKernel.getOrCreateProxy:(Lscala/actors/remote/Node;Lscala/Symbol;)Lscala/actors/remote/Proxy;
   13:	aload_0
   14:	monitorexit
   15:	checkcast	#58; //class scala/actors/AbstractActor
   18:	areturn
   19:	aload_0
   20:	monitorexit
   21:	athrow
  Exception table:
   from   to  target type
     4    15    19   Class java/lang/Throwable

  LineNumberTable: 
   line 117: 0
   line 118: 4
   line 117: 14

  LocalVariableTable: 
   Start  Length  Slot  Name   Signature
   0      22      0    this       Lscala/actors/remote/RemoteActor$;
   0      22      1    node       Lscala/actors/remote/Node;
   0      22      2    sym       Lscala/Symbol;


public void register(scala.Symbol, scala.actors.Actor);
  Code:
   Stack=4, Locals=12, Args_size=3
   0:	aload_0
   1:	dup
   2:	pop
   3:	monitorenter
   4:	aload_0
   5:	getfield	#28; //Field scala$actors$remote$RemoteActor$$kernels:Lscala/collection/mutable/HashMap;
   8:	getstatic	#71; //Field scala/actors/Actor$.MODULE$:Lscala/actors/Actor$;
   11:	astore_3
   12:	getstatic	#76; //Field scala/actors/Scheduler$.MODULE$:Lscala/actors/Scheduler$;
   15:	astore	4
   17:	aload_3
   18:	aload	4
   20:	invokevirtual	#80; //Method scala/actors/Actor$.rawSelf:(Lscala/actors/IScheduler;)Lscala/actors/Reactor;
   23:	checkcast	#82; //class scala/actors/Actor
   26:	invokevirtual	#86; //Method scala/collection/mutable/HashMap.get:(Ljava/lang/Object;)Lscala/Option;
   29:	astore	11
   31:	getstatic	#91; //Field scala/None$.MODULE$:Lscala/None$;
   34:	dup
   35:	ifnonnull	47
   38:	pop
   39:	aload	11
   41:	ifnull	55
   44:	goto	141
   47:	aload	11
   49:	invokevirtual	#95; //Method java/lang/Object.equals:(Ljava/lang/Object;)Z
   52:	ifeq	141
   55:	iconst_1
   56:	ifeq	128
   59:	getstatic	#100; //Field scala/actors/remote/TcpService$.MODULE$:Lscala/actors/remote/TcpService$;
   62:	getstatic	#100; //Field scala/actors/remote/TcpService$.MODULE$:Lscala/actors/remote/TcpService$;
   65:	invokevirtual	#104; //Method scala/actors/remote/TcpService$.generatePort:()I
   68:	aload_0
   69:	invokespecial	#107; //Method cl:()Ljava/lang/ClassLoader;
   72:	invokevirtual	#111; //Method scala/actors/remote/TcpService$.apply:(ILjava/lang/ClassLoader;)Lscala/actors/remote/TcpService;
   75:	astore	7
   77:	aload_0
   78:	getfield	#28; //Field scala$actors$remote$RemoteActor$$kernels:Lscala/collection/mutable/HashMap;
   81:	getstatic	#121; //Field scala/Predef$Pair$.MODULE$:Lscala/Predef$Pair$;
   84:	getstatic	#71; //Field scala/actors/Actor$.MODULE$:Lscala/actors/Actor$;
   87:	astore	5
   89:	getstatic	#76; //Field scala/actors/Scheduler$.MODULE$:Lscala/actors/Scheduler$;
   92:	astore	6
   94:	aload	5
   96:	aload	6
   98:	invokevirtual	#80; //Method scala/actors/Actor$.rawSelf:(Lscala/actors/IScheduler;)Lscala/actors/Reactor;
   101:	checkcast	#82; //class scala/actors/Actor
   104:	aload	7
   106:	invokeinterface	#116,  1; //InterfaceMethod scala/actors/remote/Service.kernel:()Lscala/actors/remote/NetKernel;
   111:	invokevirtual	#124; //Method scala/Predef$Pair$.apply:(Ljava/lang/Object;Ljava/lang/Object;)Lscala/Tuple2;
   114:	invokevirtual	#128; //Method scala/collection/mutable/HashMap.$plus$eq:(Lscala/Tuple2;)Lscala/collection/mutable/HashMap;
   117:	pop
   118:	aload	7
   120:	invokeinterface	#116,  1; //InterfaceMethod scala/actors/remote/Service.kernel:()Lscala/actors/remote/NetKernel;
   125:	goto	172
   128:	new	#139; //class scala/MatchError
   131:	dup
   132:	aload	11
   134:	invokevirtual	#145; //Method scala/Option.toString:()Ljava/lang/String;
   137:	invokespecial	#148; //Method scala/MatchError."<init>":(Ljava/lang/String;)V
   140:	athrow
   141:	aload	11
   143:	instanceof	#150; //class scala/Some
   146:	ifeq	197
   149:	aload	11
   151:	checkcast	#150; //class scala/Some
   154:	astore	8
   156:	aload	8
   158:	invokevirtual	#153; //Method scala/Some.x:()Ljava/lang/Object;
   161:	checkcast	#47; //class scala/actors/remote/NetKernel
   164:	astore	9
   166:	iconst_1
   167:	ifeq	184
   170:	aload	9
   172:	astore	10
   174:	aload	10
   176:	aload_1
   177:	aload_2
   178:	invokevirtual	#169; //Method scala/actors/remote/NetKernel.register:(Lscala/Symbol;Lscala/actors/OutputChannel;)V
   181:	aload_0
   182:	monitorexit
   183:	return
   184:	new	#139; //class scala/MatchError
   187:	dup
   188:	aload	11
   190:	invokevirtual	#145; //Method scala/Option.toString:()Ljava/lang/String;
   193:	invokespecial	#148; //Method scala/MatchError."<init>":(Ljava/lang/String;)V
   196:	athrow
   197:	new	#139; //class scala/MatchError
   200:	dup
   201:	aload	11
   203:	invokevirtual	#145; //Method scala/Option.toString:()Ljava/lang/String;
   206:	invokespecial	#148; //Method scala/MatchError."<init>":(Ljava/lang/String;)V
   209:	athrow
   210:	aload_0
   211:	monitorexit
   212:	athrow
  Exception table:
   from   to  target type
     4   183   210   Class java/lang/Throwable

   184   210   210   Class java/lang/Throwable

  LineNumberTable: 
   line 92: 0
   line 93: 4
   line 644: 55
   line 95: 59
   line 96: 77
   line 97: 118
   line 93: 128
   line 644: 166
   line 99: 170
   line 93: 172
   line 101: 174
   line 92: 182
   line 93: 184
   line 92: 211

  LocalVariableTable: 
   Start  Length  Slot  Name   Signature
   0      213      0    this       Lscala/actors/remote/RemoteActor$;
   0      213      1    name       Lscala/Symbol;
   0      213      2    a       Lscala/actors/Actor;
   12      26      3    $inlThis1       Ljava/lang/Object;
   17      9      4    sched0       Lscala/actors/IScheduler;
   89      39      5    $inlThis4       Ljava/lang/Object;
   94      10      6    sched1       Lscala/actors/IScheduler;
   77      48      7    serv       Lscala/actors/remote/TcpService;
   156      16      8    temp3       Lscala/Some;
   184      13      8    temp3       Lscala/Some;
   166      6      9    temp4       Lscala/actors/remote/NetKernel;
   184      13      9    temp4       Lscala/actors/remote/NetKernel;
   174      7      10    kernel       Lscala/actors/remote/NetKernel;
   31      152      11    temp1       Lscala/Option;
   184      26      11    temp1       Lscala/Option;


public scala.actors.remote.NetKernel createKernelOnPort(int);
  Code:
   Stack=5, Locals=5, Args_size=2
   0:	getstatic	#100; //Field scala/actors/remote/TcpService$.MODULE$:Lscala/actors/remote/TcpService$;
   3:	iload_1
   4:	aload_0
   5:	invokespecial	#107; //Method cl:()Ljava/lang/ClassLoader;
   8:	invokevirtual	#111; //Method scala/actors/remote/TcpService$.apply:(ILjava/lang/ClassLoader;)Lscala/actors/remote/TcpService;
   11:	astore_2
   12:	aload_2
   13:	invokeinterface	#116,  1; //InterfaceMethod scala/actors/remote/Service.kernel:()Lscala/actors/remote/NetKernel;
   18:	astore_3
   19:	getstatic	#71; //Field scala/actors/Actor$.MODULE$:Lscala/actors/Actor$;
   22:	invokevirtual	#187; //Method scala/actors/Actor$.self:()Lscala/actors/Actor;
   25:	astore	4
   27:	aload_0
   28:	invokevirtual	#35; //Method scala$actors$remote$RemoteActor$$kernels:()Lscala/collection/mutable/HashMap;
   31:	getstatic	#121; //Field scala/Predef$Pair$.MODULE$:Lscala/Predef$Pair$;
   34:	aload	4
   36:	aload_3
   37:	invokevirtual	#124; //Method scala/Predef$Pair$.apply:(Ljava/lang/Object;Ljava/lang/Object;)Lscala/Tuple2;
   40:	invokevirtual	#128; //Method scala/collection/mutable/HashMap.$plus$eq:(Lscala/Tuple2;)Lscala/collection/mutable/HashMap;
   43:	pop
   44:	aload	4
   46:	new	#130; //class scala/actors/remote/RemoteActor$$anonfun$createKernelOnPort$1
   49:	dup
   50:	aload_3
   51:	aload	4
   53:	invokespecial	#133; //Method scala/actors/remote/RemoteActor$$anonfun$createKernelOnPort$1."<init>":(Lscala/actors/remote/NetKernel;Lscala/actors/Actor;)V
   56:	invokeinterface	#137,  2; //InterfaceMethod scala/actors/Actor.onTerminate:(Lscala/Function0;)V
   61:	aload_3
   62:	areturn
  LineNumberTable: 
   line 67: 0
   line 68: 12
   line 69: 19
   line 70: 27
   line 72: 44
   line 85: 61

  LocalVariableTable: 
   Start  Length  Slot  Name   Signature
   0      63      0    this       Lscala/actors/remote/RemoteActor$;
   0      63      1    port       I
   12      50      2    serv       Lscala/actors/remote/TcpService;
   19      43      3    kern$1       Lscala/actors/remote/NetKernel;
   27      35      4    s$1       Lscala/actors/Actor;


public void alive(int);
  Code:
   Stack=5, Locals=7, Args_size=2
   0:	aload_0
   1:	dup
   2:	pop
   3:	monitorenter
   4:	getstatic	#100; //Field scala/actors/remote/TcpService$.MODULE$:Lscala/actors/remote/TcpService$;
   7:	iload_1
   8:	aload_0
   9:	invokespecial	#107; //Method cl:()Ljava/lang/ClassLoader;
   12:	invokevirtual	#111; //Method scala/actors/remote/TcpService$.apply:(ILjava/lang/ClassLoader;)Lscala/actors/remote/TcpService;
   15:	astore_2
   16:	aload_2
   17:	invokeinterface	#116,  1; //InterfaceMethod scala/actors/remote/Service.kernel:()Lscala/actors/remote/NetKernel;
   22:	astore	5
   24:	getstatic	#71; //Field scala/actors/Actor$.MODULE$:Lscala/actors/Actor$;
   27:	astore_3
   28:	getstatic	#76; //Field scala/actors/Scheduler$.MODULE$:Lscala/actors/Scheduler$;
   31:	astore	4
   33:	aload_3
   34:	aload	4
   36:	invokevirtual	#80; //Method scala/actors/Actor$.rawSelf:(Lscala/actors/IScheduler;)Lscala/actors/Reactor;
   39:	checkcast	#82; //class scala/actors/Actor
   42:	astore	6
   44:	aload_0
   45:	getfield	#28; //Field scala$actors$remote$RemoteActor$$kernels:Lscala/collection/mutable/HashMap;
   48:	getstatic	#121; //Field scala/Predef$Pair$.MODULE$:Lscala/Predef$Pair$;
   51:	aload	6
   53:	aload	5
   55:	invokevirtual	#124; //Method scala/Predef$Pair$.apply:(Ljava/lang/Object;Ljava/lang/Object;)Lscala/Tuple2;
   58:	invokevirtual	#128; //Method scala/collection/mutable/HashMap.$plus$eq:(Lscala/Tuple2;)Lscala/collection/mutable/HashMap;
   61:	pop
   62:	aload	6
   64:	new	#130; //class scala/actors/remote/RemoteActor$$anonfun$createKernelOnPort$1
   67:	dup
   68:	aload	5
   70:	aload	6
   72:	invokespecial	#133; //Method scala/actors/remote/RemoteActor$$anonfun$createKernelOnPort$1."<init>":(Lscala/actors/remote/NetKernel;Lscala/actors/Actor;)V
   75:	invokeinterface	#137,  2; //InterfaceMethod scala/actors/Actor.onTerminate:(Lscala/Function0;)V
   80:	aload_0
   81:	monitorexit
   82:	return
   83:	aload_0
   84:	monitorexit
   85:	athrow
  Exception table:
   from   to  target type
     4    82    83   Class java/lang/Throwable

  LineNumberTable: 
   line 62: 0
   line 63: 4
   line 62: 80

  LocalVariableTable: 
   Start  Length  Slot  Name   Signature
   0      86      0    this       Lscala/actors/remote/RemoteActor$;
   0      86      1    port       I
   16      64      2    serv0       Lscala/actors/remote/TcpService;
   28      52      3    $inlThis1       Ljava/lang/Object;
   33      9      4    sched0       Lscala/actors/IScheduler;
   24      56      5    kern$10       Lscala/actors/remote/NetKernel;
   44      36      6    s$10       Lscala/actors/Actor;


public void classLoader_$eq(java.lang.ClassLoader);
  Code:
   Stack=2, Locals=2, Args_size=2
   0:	aload_0
   1:	aload_1
   2:	invokespecial	#198; //Method cl_$eq:(Ljava/lang/ClassLoader;)V
   5:	return
  LineNumberTable: 
   line 56: 0

  LocalVariableTable: 
   Start  Length  Slot  Name   Signature
   0      6      0    this       Lscala/actors/remote/RemoteActor$;
   0      6      1    x       Ljava/lang/ClassLoader;


public java.lang.ClassLoader classLoader();
  Code:
   Stack=1, Locals=1, Args_size=1
   0:	aload_0
   1:	invokespecial	#107; //Method cl:()Ljava/lang/ClassLoader;
   4:	areturn
  LineNumberTable: 
   line 55: 0


public final scala.collection.mutable.HashMap scala$actors$remote$RemoteActor$$kernels();
  Code:
   Stack=1, Locals=1, Args_size=1
   0:	aload_0
   1:	getfield	#28; //Field scala$actors$remote$RemoteActor$$kernels:Lscala/collection/mutable/HashMap;
   4:	areturn
  LineNumberTable: 
   line 47: 0


}

