Compiled from "RemoteActor.scala"
public final class scala.actors.remote.RemoteActor extends java.lang.Object
  SourceFile: "RemoteActor.scala"
  ScalaSig: length = 0x2D4
   05 00 70 07 05 01 02 FFFFFF88 02 09 01 0B 52 65 6D 6F
   74 65 41 63 74 6F 72 0A 02 03 04 01 06 72 65 6D
   6F 74 65 0A 02 05 06 01 06 61 63 74 6F 72 73 0A
   01 07 01 05 73 63 61 6C 61 03 00 10 02 0A 0B 0D
   01 02 06 08 0C 02 FFFFFF84 FFFFFF80 FFFFFF80 FFFFFF88 02 0D 02 0B 52 65
   6D 6F 74 65 41 63 74 6F 72 13 03 0B 0E 16 10 02
   0F 14 0D 01 10 0A 02 11 12 01 04 6C 61 6E 67 0A
   01 13 01 04 6A 61 76 61 09 02 15 10 02 06 4F 62
   6A 65 63 74 10 02 17 18 0D 01 06 09 02 19 06 02
   0B 53 63 61 6C 61 4F 62 6A 65 63 74 08 05 1B 0B
   FFFFFF84 00 1C 01 06 3C 69 6E 69 74 3E 14 01 09 08 07
   1E 0B FFFFFFC2 FFFFFF80 FFFFFF84 04 1F 01 07 6B 65 72 6E 65 6C 73
   15 01 20 10 04 21 26 28 2C 0D 01 22 0A 02 23 24
   01 07 6D 75 74 61 62 6C 65 0A 02 25 06 01 0A 63
   6F 6C 6C 65 63 74 69 6F 6E 09 02 27 22 02 07 48
   61 73 68 4D 61 70 10 02 29 2A 0D 01 04 09 02 2B
   04 02 05 41 63 74 6F 72 10 02 0A 2D 09 02 2E 02
   02 09 4E 65 74 4B 65 72 6E 65 6C 08 06 30 0B FFFFFFA0
   FFFFFF80 04 20 01 08 6B 65 72 6E 65 6C 73 20 08 07 32
   0B FFFFFFC0 FFFFFF80 FFFFFF84 04 33 01 02 63 6C 15 01 34 10 02 0F
   35 09 02 36 10 02 0B 43 6C 61 73 73 4C 6F 61 64
   65 72 08 07 38 0B FFFFFFC0 FFFFFF80 FFFFFF84 04 39 01 06 63 6C 5F
   24 65 71 14 02 3A 3D 10 02 17 3B 09 02 3C 06 02
   04 55 6E 69 74 08 07 3E 37 FFFFFF81 FFFFFF80 FFFFFFC0 00 34 01 03
   78 24 31 08 06 40 0B FFFFFFA0 FFFFFFA0 04 34 01 03 63 6C 20
   08 05 42 0B FFFFFF84 00 33 01 0B 63 6C 61 73 73 4C 6F
   61 64 65 72 08 05 44 0B FFFFFF84 00 45 01 0F 63 6C 61
   73 73 4C 6F 61 64 65 72 5F 24 65 71 14 02 3A 46
   08 05 47 43 FFFFFFC0 00 34 01 01 78 08 05 49 0B FFFFFF84 00
   4A 01 05 61 6C 69 76 65 14 02 3A 4B 08 05 4C 48
   FFFFFFC0 00 4D 01 04 70 6F 72 74 10 02 17 4E 09 02 4F
   06 02 03 49 6E 74 08 05 51 0B FFFFFF84 00 52 01 12 63
   72 65 61 74 65 4B 65 72 6E 65 6C 4F 6E 50 6F 72
   74 14 02 2C 53 08 05 4C 50 FFFFFFC0 00 4D 08 05 55 0B
   FFFFFF84 00 56 01 08 72 65 67 69 73 74 65 72 14 03 3A
   57 5C 08 05 58 54 FFFFFFC0 00 59 01 04 6E 61 6D 65 10
   02 17 5A 09 02 5B 06 02 06 53 79 6D 62 6F 6C 08
   05 5D 54 FFFFFFC0 00 28 01 01 61 08 05 5F 0B FFFFFF84 04 60
   01 0A 73 65 6C 66 4B 65 72 6E 65 6C 15 01 2C 08
   05 62 0B FFFFFF84 00 63 01 06 73 65 6C 65 63 74 14 03
   64 67 6C 10 02 29 65 09 02 66 04 02 0D 41 62 73
   74 72 61 63 74 41 63 74 6F 72 08 05 68 61 FFFFFFC0 00
   69 01 04 6E 6F 64 65 10 02 0A 6A 09 02 6B 02 02
   04 4E 6F 64 65 08 05 6D 61 FFFFFFC0 00 59 01 03 73 79
   6D 08 05 6F 0B FFFFFF84 00 60 01 0A 73 6F 6D 65 4B 65
   72 6E 65 6C 
  InnerClass: 
   public final $anonfun$createKernelOnPort$1=class scala/actors/remote/RemoteActor$$anonfun$createKernelOnPort$1 of class scala/actors/remote/RemoteActor
  minor version: 0
  major version: 49
  Constant pool:
Asciz	SourceFile;
Asciz	RemoteActor.scala;
Asciz	someKernel;
Asciz	()Lscala/actors/remote/NetKernel;;
Asciz	Code;
Asciz	scala/actors/remote/RemoteActor$;
class	scala/actors/remote/RemoteActor$
Asciz	MODULE$;
Asciz	Lscala/actors/remote/RemoteActor$;;
NameAndType	MODULE$:Lscala/actors/remote/RemoteActor$;
Field	scala/actors/remote/RemoteActor$.MODULE$:Lscala/actors/remote/RemoteActor$;
NameAndType	someKernel:()Lscala/actors/remote/NetKernel;
Method	scala/actors/remote/RemoteActor$.someKernel:()Lscala/actors/remote/NetKernel;
Asciz	select;
Asciz	(Lscala/actors/remote/Node;Lscala/Symbol;)Lscala/actors/AbstractActor;;
NameAndType	select:(Lscala/actors/remote/Node;Lscala/Symbol;)Lscala/actors/AbstractActor;
Method	scala/actors/remote/RemoteActor$.select:(Lscala/actors/remote/Node;Lscala/Symbol;)Lscala/actors/AbstractActor;
Asciz	register;
Asciz	(Lscala/Symbol;Lscala/actors/Actor;)V;
NameAndType	register:(Lscala/Symbol;Lscala/actors/Actor;)V
Method	scala/actors/remote/RemoteActor$.register:(Lscala/Symbol;Lscala/actors/Actor;)V
Asciz	createKernelOnPort;
Asciz	(I)Lscala/actors/remote/NetKernel;;
NameAndType	createKernelOnPort:(I)Lscala/actors/remote/NetKernel;
Method	scala/actors/remote/RemoteActor$.createKernelOnPort:(I)Lscala/actors/remote/NetKernel;
Asciz	alive;
Asciz	(I)V;
NameAndType	alive:(I)V
Method	scala/actors/remote/RemoteActor$.alive:(I)V
Asciz	classLoader_$eq;
Asciz	(Ljava/lang/ClassLoader;)V;
NameAndType	classLoader_$eq:(Ljava/lang/ClassLoader;)V
Method	scala/actors/remote/RemoteActor$.classLoader_$eq:(Ljava/lang/ClassLoader;)V
Asciz	classLoader;
Asciz	()Ljava/lang/ClassLoader;;
NameAndType	classLoader:()Ljava/lang/ClassLoader;
Method	scala/actors/remote/RemoteActor$.classLoader:()Ljava/lang/ClassLoader;
Asciz	scala$actors$remote$RemoteActor$$kernels;
Asciz	()Lscala/collection/mutable/HashMap;;
NameAndType	scala$actors$remote$RemoteActor$$kernels:()Lscala/collection/mutable/HashMap;
Method	scala/actors/remote/RemoteActor$.scala$actors$remote$RemoteActor$$kernels:()Lscala/collection/mutable/HashMap;
Asciz	ScalaSig;
Asciz	InnerClasses;
Asciz	scala/actors/remote/RemoteActor$$anonfun$createKernelOnPort$1;
class	scala/actors/remote/RemoteActor$$anonfun$createKernelOnPort$1
Asciz	scala/actors/remote/RemoteActor;
class	scala/actors/remote/RemoteActor
Asciz	$anonfun$createKernelOnPort$1;
Asciz	java/lang/Object;
class	java/lang/Object

{
public static final scala.actors.remote.NetKernel someKernel();
  Signature: ()Lscala/actors/remote/NetKernel;
  Code:
   Stack=1, Locals=0, Args_size=0
	getstatic	Field scala/actors/remote/RemoteActor$.MODULE$:Lscala/actors/remote/RemoteActor$;
	invokevirtual	Method scala/actors/remote/RemoteActor$.someKernel:()Lscala/actors/remote/NetKernel;
	areturn
  Labels:

public static final scala.actors.AbstractActor select(scala.actors.remote.Node, scala.Symbol);
  Signature: (Lscala/actors/remote/Node;Lscala/Symbol;)Lscala/actors/AbstractActor;
  Code:
   Stack=3, Locals=2, Args_size=2
	getstatic	Field scala/actors/remote/RemoteActor$.MODULE$:Lscala/actors/remote/RemoteActor$;
	aload_0
	aload_1
	invokevirtual	Method scala/actors/remote/RemoteActor$.select:(Lscala/actors/remote/Node;Lscala/Symbol;)Lscala/actors/AbstractActor;
	areturn
  Labels:

public static final void register(scala.Symbol, scala.actors.Actor);
  Signature: (Lscala/Symbol;Lscala/actors/Actor;)V
  Code:
   Stack=3, Locals=2, Args_size=2
	getstatic	Field scala/actors/remote/RemoteActor$.MODULE$:Lscala/actors/remote/RemoteActor$;
	aload_0
	aload_1
	invokevirtual	Method scala/actors/remote/RemoteActor$.register:(Lscala/Symbol;Lscala/actors/Actor;)V
	return
  Labels:

public static final scala.actors.remote.NetKernel createKernelOnPort(int);
  Signature: (I)Lscala/actors/remote/NetKernel;
  Code:
   Stack=2, Locals=1, Args_size=1
	getstatic	Field scala/actors/remote/RemoteActor$.MODULE$:Lscala/actors/remote/RemoteActor$;
	iload_0
	invokevirtual	Method scala/actors/remote/RemoteActor$.createKernelOnPort:(I)Lscala/actors/remote/NetKernel;
	areturn
  Labels:

public static final void alive(int);
  Signature: (I)V
  Code:
   Stack=2, Locals=1, Args_size=1
	getstatic	Field scala/actors/remote/RemoteActor$.MODULE$:Lscala/actors/remote/RemoteActor$;
	iload_0
	invokevirtual	Method scala/actors/remote/RemoteActor$.alive:(I)V
	return
  Labels:

public static final void classLoader_$eq(java.lang.ClassLoader);
  Signature: (Ljava/lang/ClassLoader;)V
  Code:
   Stack=2, Locals=1, Args_size=1
	getstatic	Field scala/actors/remote/RemoteActor$.MODULE$:Lscala/actors/remote/RemoteActor$;
	aload_0
	invokevirtual	Method scala/actors/remote/RemoteActor$.classLoader_$eq:(Ljava/lang/ClassLoader;)V
	return
  Labels:

public static final java.lang.ClassLoader classLoader();
  Signature: ()Ljava/lang/ClassLoader;
  Code:
   Stack=1, Locals=0, Args_size=0
	getstatic	Field scala/actors/remote/RemoteActor$.MODULE$:Lscala/actors/remote/RemoteActor$;
	invokevirtual	Method scala/actors/remote/RemoteActor$.classLoader:()Ljava/lang/ClassLoader;
	areturn
  Labels:

public static final scala.collection.mutable.HashMap scala$actors$remote$RemoteActor$$kernels();
  Signature: ()Lscala/collection/mutable/HashMap;
  Code:
   Stack=1, Locals=0, Args_size=0
	getstatic	Field scala/actors/remote/RemoteActor$.MODULE$:Lscala/actors/remote/RemoteActor$;
	invokevirtual	Method scala/actors/remote/RemoteActor$.scala$actors$remote$RemoteActor$$kernels:()Lscala/collection/mutable/HashMap;
	areturn
  Labels:

}

