Compiled from "RemoteActor.scala"
public final class scala.actors.remote.RemoteActor$$anonfun$createKernelOnPort$1 extends scala.runtime.AbstractFunction0 implements java.io.Serializable
  SourceFile: "RemoteActor.scala"
  Scala: length = 0x
   
  InnerClass: 
   public final $anonfun$createKernelOnPort$1=class scala/actors/remote/RemoteActor$$anonfun$createKernelOnPort$1 of class scala/actors/remote/RemoteActor
  minor version: 0
  major version: 49
  Constant pool:
Asciz	SourceFile;
Asciz	RemoteActor.scala;
Asciz	<clinit>;
Asciz	()V;
Asciz	Code;
Asciz	serialVersionUID;
Asciz	J;
Asciz	scala/actors/remote/RemoteActor$$anonfun$createKernelOnPort$1;
class	scala/actors/remote/RemoteActor$$anonfun$createKernelOnPort$1
NameAndType	serialVersionUID:J
Field	scala/actors/remote/RemoteActor$$anonfun$createKernelOnPort$1.serialVersionUID:J
Asciz	s$1;
Asciz	Lscala/actors/Actor;;
Asciz	kern$1;
Asciz	Lscala/actors/remote/NetKernel;;
Asciz	apply;
Asciz	scala/actors/Debug$;
class	scala/actors/Debug$
Asciz	MODULE$;
Asciz	Lscala/actors/Debug$;;
NameAndType	MODULE$:Lscala/actors/Debug$;
Field	scala/actors/Debug$.MODULE$:Lscala/actors/Debug$;
Asciz	LineNumberTable;
Asciz	scala/collection/mutable/StringBuilder;
class	scala/collection/mutable/StringBuilder
Asciz	<init>;
NameAndType	"<init>":()V
Method	scala/collection/mutable/StringBuilder."<init>":()V
Asciz	alive actor ;
String	alive actor 
Asciz	append;
Asciz	(Ljava/lang/Object;)Lscala/collection/mutable/StringBuilder;;
NameAndType	append:(Ljava/lang/Object;)Lscala/collection/mutable/StringBuilder;
Method	scala/collection/mutable/StringBuilder.append:(Ljava/lang/Object;)Lscala/collection/mutable/StringBuilder;
NameAndType	s$1:Lscala/actors/Actor;
Field	scala/actors/remote/RemoteActor$$anonfun$createKernelOnPort$1.s$1:Lscala/actors/Actor;
Asciz	 terminated;
String	 terminated
Asciz	toString;
Asciz	()Ljava/lang/String;;
NameAndType	toString:()Ljava/lang/String;
Method	scala/collection/mutable/StringBuilder.toString:()Ljava/lang/String;
Asciz	info;
Asciz	(Ljava/lang/String;)V;
NameAndType	info:(Ljava/lang/String;)V
Method	scala/actors/Debug$.info:(Ljava/lang/String;)V
Asciz	scala/actors/remote/RemoteActor$;
class	scala/actors/remote/RemoteActor$
Asciz	Lscala/actors/remote/RemoteActor$;;
NameAndType	MODULE$:Lscala/actors/remote/RemoteActor$;
Field	scala/actors/remote/RemoteActor$.MODULE$:Lscala/actors/remote/RemoteActor$;
Asciz	scala$actors$remote$RemoteActor$$kernels;
Asciz	()Lscala/collection/mutable/HashMap;;
NameAndType	scala$actors$remote$RemoteActor$$kernels:()Lscala/collection/mutable/HashMap;
Method	scala/actors/remote/RemoteActor$.scala$actors$remote$RemoteActor$$kernels:()Lscala/collection/mutable/HashMap;
Asciz	scala/collection/mutable/HashMap;
class	scala/collection/mutable/HashMap
Asciz	$minus$eq;
Asciz	(Ljava/lang/Object;)Lscala/collection/mutable/HashMap;;
NameAndType	$minus$eq:(Ljava/lang/Object;)Lscala/collection/mutable/HashMap;
Method	scala/collection/mutable/HashMap.$minus$eq:(Ljava/lang/Object;)Lscala/collection/mutable/HashMap;
Asciz	valuesIterator;
Asciz	()Lscala/collection/Iterator;;
NameAndType	valuesIterator:()Lscala/collection/Iterator;
Method	scala/collection/mutable/HashMap.valuesIterator:()Lscala/collection/Iterator;
NameAndType	kern$1:Lscala/actors/remote/NetKernel;
Field	scala/actors/remote/RemoteActor$$anonfun$createKernelOnPort$1.kern$1:Lscala/actors/remote/NetKernel;
Asciz	scala/collection/Iterator;
class	scala/collection/Iterator
Asciz	contains;
Asciz	(Ljava/lang/Object;)Z;
NameAndType	contains:(Ljava/lang/Object;)Z
InterfaceMethod	scala/collection/Iterator.contains:(Ljava/lang/Object;)Z
Asciz	terminating ;
String	terminating 
Asciz	scala/actors/remote/NetKernel;
class	scala/actors/remote/NetKernel
Asciz	terminate;
NameAndType	terminate:()V
Method	scala/actors/remote/NetKernel.terminate:()V
Asciz	()Ljava/lang/Object;;
NameAndType	apply:()V
Method	scala/actors/remote/RemoteActor$$anonfun$createKernelOnPort$1.apply:()V
Asciz	scala/runtime/BoxedUnit;
class	scala/runtime/BoxedUnit
Asciz	UNIT;
Asciz	Lscala/runtime/BoxedUnit;;
NameAndType	UNIT:Lscala/runtime/BoxedUnit;
Field	scala/runtime/BoxedUnit.UNIT:Lscala/runtime/BoxedUnit;
Asciz	(Lscala/actors/remote/NetKernel;Lscala/actors/Actor;)V;
Asciz	scala/runtime/AbstractFunction0;
class	scala/runtime/AbstractFunction0
Method	scala/runtime/AbstractFunction0."<init>":()V
Asciz	Scala;
Asciz	InnerClasses;
Asciz	scala/actors/remote/RemoteActor;
class	scala/actors/remote/RemoteActor
Asciz	$anonfun$createKernelOnPort$1;
Asciz	java/io/Serializable;
class	java/io/Serializable

{
public static final long serialVersionUID;
  Signature: J

public final scala.actors.Actor s$1;
  Signature: Lscala/actors/Actor;

public final scala.actors.remote.NetKernel kern$1;
  Signature: Lscala/actors/remote/NetKernel;

public static {};
  Signature: ()V
  Code:
   Stack=2, Locals=0, Args_size=0
	lconst_0
	putstatic	Field serialVersionUID:J
	return
  Labels:

public final void apply();
  Signature: ()V
  Code:
   Stack=3, Locals=1, Args_size=1
	getstatic	Field scala/actors/Debug$.MODULE$:Lscala/actors/Debug$;
	new	class scala/collection/mutable/StringBuilder
	dup
	invokespecial	Method scala/collection/mutable/StringBuilder."<init>":()V
	ldc	String alive actor 
	invokevirtual	Method scala/collection/mutable/StringBuilder.append:(Ljava/lang/Object;)Lscala/collection/mutable/StringBuilder;
	aload_0
	getfield	Field s$1:Lscala/actors/Actor;
	invokevirtual	Method scala/collection/mutable/StringBuilder.append:(Ljava/lang/Object;)Lscala/collection/mutable/StringBuilder;
	ldc	String  terminated
	invokevirtual	Method scala/collection/mutable/StringBuilder.append:(Ljava/lang/Object;)Lscala/collection/mutable/StringBuilder;
	invokevirtual	Method scala/collection/mutable/StringBuilder.toString:()Ljava/lang/String;
	invokevirtual	Method scala/actors/Debug$.info:(Ljava/lang/String;)V
	getstatic	Field scala/actors/remote/RemoteActor$.MODULE$:Lscala/actors/remote/RemoteActor$;
	invokevirtual	Method scala/actors/remote/RemoteActor$.scala$actors$remote$RemoteActor$$kernels:()Lscala/collection/mutable/HashMap;
	aload_0
	getfield	Field s$1:Lscala/actors/Actor;
	invokevirtual	Method scala/collection/mutable/HashMap.$minus$eq:(Ljava/lang/Object;)Lscala/collection/mutable/HashMap;
	pop
	getstatic	Field scala/actors/remote/RemoteActor$.MODULE$:Lscala/actors/remote/RemoteActor$;
	invokevirtual	Method scala/actors/remote/RemoteActor$.scala$actors$remote$RemoteActor$$kernels:()Lscala/collection/mutable/HashMap;
	invokevirtual	Method scala/collection/mutable/HashMap.valuesIterator:()Lscala/collection/Iterator;
	aload_0
	getfield	Field kern$1:Lscala/actors/remote/NetKernel;
	invokeinterface	InterfaceMethod scala/collection/Iterator.contains:(Ljava/lang/Object;)Z
	ifne	l1 // return
	getstatic	Field scala/actors/Debug$.MODULE$:Lscala/actors/Debug$;
	new	class scala/collection/mutable/StringBuilder
	dup
	invokespecial	Method scala/collection/mutable/StringBuilder."<init>":()V
	ldc	String terminating 
	invokevirtual	Method scala/collection/mutable/StringBuilder.append:(Ljava/lang/Object;)Lscala/collection/mutable/StringBuilder;
	aload_0
	getfield	Field kern$1:Lscala/actors/remote/NetKernel;
	invokevirtual	Method scala/collection/mutable/StringBuilder.append:(Ljava/lang/Object;)Lscala/collection/mutable/StringBuilder;
	invokevirtual	Method scala/collection/mutable/StringBuilder.toString:()Ljava/lang/String;
	invokevirtual	Method scala/actors/Debug$.info:(Ljava/lang/String;)V
	aload_0
	getfield	Field kern$1:Lscala/actors/remote/NetKernel;
	invokevirtual	Method scala/actors/remote/NetKernel.terminate:()V
l1	return
  Labels:
   	l1 = 103 // return

public final java.lang.Object apply();
  Signature: ()Ljava/lang/Object;
  Code:
   Stack=1, Locals=1, Args_size=1
	aload_0
	invokevirtual	Method apply:()V
	getstatic	Field scala/runtime/BoxedUnit.UNIT:Lscala/runtime/BoxedUnit;
	areturn
  Labels:

public scala.actors.remote.RemoteActor$$anonfun$createKernelOnPort$1(scala.actors.remote.NetKernel, scala.actors.Actor);
  Signature: (Lscala/actors/remote/NetKernel;Lscala/actors/Actor;)V
  Code:
   Stack=2, Locals=3, Args_size=3
	aload_0
	aload_1
	putfield	Field kern$1:Lscala/actors/remote/NetKernel;
	aload_0
	aload_2
	putfield	Field s$1:Lscala/actors/Actor;
	aload_0
	invokespecial	Method scala/runtime/AbstractFunction0."<init>":()V
	return
  Labels:

}

