Compiled from "NetKernel.scala"
public final class scala.actors.remote.SendTo$ extends java.lang.Object implements scala.Function3,scala.ScalaObject
  SourceFile: "NetKernel.scala"
  Scala: length = 0x
   
  minor version: 0
  major version: 49
  Constant pool:
Asciz	SourceFile;
Asciz	NetKernel.scala;
Asciz	Scala;
Asciz	MODULE$;
Asciz	Lscala/actors/remote/SendTo$;;
Asciz	<clinit>;
Asciz	()V;
Asciz	Code;
Asciz	scala/actors/remote/SendTo$;
class	scala/actors/remote/SendTo$
Asciz	<init>;
NameAndType	"<init>":()V
Method	scala/actors/remote/SendTo$."<init>":()V
Asciz	toString;
Asciz	()Ljava/lang/String;;
Asciz	LineNumberTable;
Asciz	scala/Function3$class;
class	scala/Function3$class
Asciz	(Lscala/Function3;)Ljava/lang/String;;
NameAndType	toString:(Lscala/Function3;)Ljava/lang/String;
Method	scala/Function3$class.toString:(Lscala/Function3;)Ljava/lang/String;
Asciz	curried;
Asciz	()Lscala/Function1;;
Asciz	(Lscala/Function3;)Lscala/Function1;;
NameAndType	curried:(Lscala/Function3;)Lscala/Function1;
Method	scala/Function3$class.curried:(Lscala/Function3;)Lscala/Function1;
Asciz	curry;
NameAndType	curry:(Lscala/Function3;)Lscala/Function1;
Method	scala/Function3$class.curry:(Lscala/Function3;)Lscala/Function1;
Asciz	Deprecated;
Asciz	tupled;
NameAndType	tupled:(Lscala/Function3;)Lscala/Function1;
Method	scala/Function3$class.tupled:(Lscala/Function3;)Lscala/Function1;
Asciz	unapply;
Asciz	(Lscala/actors/remote/SendTo;)Lscala/Option;;
Asciz	java/lang/Object;
class	java/lang/Object
Asciz	equals;
Asciz	(Ljava/lang/Object;)Z;
NameAndType	equals:(Ljava/lang/Object;)Z
Method	java/lang/Object.equals:(Ljava/lang/Object;)Z
Asciz	scala/None$;
class	scala/None$
Asciz	Lscala/None$;;
NameAndType	MODULE$:Lscala/None$;
Field	scala/None$.MODULE$:Lscala/None$;
Asciz	scala/Some;
class	scala/Some
Asciz	scala/Tuple3;
class	scala/Tuple3
Asciz	scala/actors/remote/SendTo;
class	scala/actors/remote/SendTo
Asciz	a;
Asciz	()Lscala/actors/OutputChannel;;
NameAndType	a:()Lscala/actors/OutputChannel;
Method	scala/actors/remote/SendTo.a:()Lscala/actors/OutputChannel;
Asciz	msg;
Asciz	()Ljava/lang/Object;;
NameAndType	msg:()Ljava/lang/Object;
Method	scala/actors/remote/SendTo.msg:()Ljava/lang/Object;
Asciz	session;
Asciz	()Lscala/Symbol;;
NameAndType	session:()Lscala/Symbol;
Method	scala/actors/remote/SendTo.session:()Lscala/Symbol;
Asciz	(Ljava/lang/Object;Ljava/lang/Object;Ljava/lang/Object;)V;
NameAndType	"<init>":(Ljava/lang/Object;Ljava/lang/Object;Ljava/lang/Object;)V
Method	scala/Tuple3."<init>":(Ljava/lang/Object;Ljava/lang/Object;Ljava/lang/Object;)V
Asciz	(Ljava/lang/Object;)V;
NameAndType	"<init>":(Ljava/lang/Object;)V
Method	scala/Some."<init>":(Ljava/lang/Object;)V
Asciz	this;
Asciz	x$0;
Asciz	Lscala/actors/remote/SendTo;;
Asciz	LocalVariableTable;
Asciz	apply;
Asciz	(Lscala/actors/OutputChannel;Ljava/lang/Object;Lscala/Symbol;)Lscala/actors/remote/SendTo;;
Asciz	(Lscala/actors/OutputChannel;Ljava/lang/Object;Lscala/Symbol;)V;
NameAndType	"<init>":(Lscala/actors/OutputChannel;Ljava/lang/Object;Lscala/Symbol;)V
Method	scala/actors/remote/SendTo."<init>":(Lscala/actors/OutputChannel;Ljava/lang/Object;Lscala/Symbol;)V
Asciz	Lscala/actors/OutputChannel;;
Asciz	Ljava/lang/Object;;
Asciz	Lscala/Symbol;;
Asciz	(Ljava/lang/Object;Ljava/lang/Object;Ljava/lang/Object;)Ljava/lang/Object;;
Asciz	scala/actors/OutputChannel;
class	scala/actors/OutputChannel
Asciz	scala/Symbol;
class	scala/Symbol
NameAndType	apply:(Lscala/actors/OutputChannel;Ljava/lang/Object;Lscala/Symbol;)Lscala/actors/remote/SendTo;
Method	scala/actors/remote/SendTo$.apply:(Lscala/actors/OutputChannel;Ljava/lang/Object;Lscala/Symbol;)Lscala/actors/remote/SendTo;
Asciz	v1;
Asciz	v2;
Asciz	v3;
Method	java/lang/Object."<init>":()V
NameAndType	MODULE$:Lscala/actors/remote/SendTo$;
Field	scala/actors/remote/SendTo$.MODULE$:Lscala/actors/remote/SendTo$;
Asciz	$init$;
Asciz	(Lscala/Function3;)V;
NameAndType	$init$:(Lscala/Function3;)V
Method	scala/Function3$class.$init$:(Lscala/Function3;)V
Asciz	scala/Function3;
class	scala/Function3
Asciz	scala/ScalaObject;
class	scala/ScalaObject

{
public static final scala.actors.remote.SendTo$ MODULE$;
  Signature: Lscala/actors/remote/SendTo$;

public static {};
  Signature: ()V
  Code:
   Stack=1, Locals=0, Args_size=0
	new	class scala/actors/remote/SendTo$
	invokespecial	Method "<init>":()V
	return
  Labels:

public java.lang.String toString();
  Signature: ()Ljava/lang/String;
  Code:
   Stack=1, Locals=1, Args_size=1
	aload_0
	invokestatic	Method scala/Function3$class.toString:(Lscala/Function3;)Ljava/lang/String;
	areturn
  Labels:

public scala.Function1 curried();
  Signature: ()Lscala/Function1;
  Code:
   Stack=1, Locals=1, Args_size=1
	aload_0
	invokestatic	Method scala/Function3$class.curried:(Lscala/Function3;)Lscala/Function1;
	areturn
  Labels:

public scala.Function1 curry();
  Signature: ()Lscala/Function1;
  Code:
   Stack=1, Locals=1, Args_size=1
	aload_0
	invokestatic	Method scala/Function3$class.curry:(Lscala/Function3;)Lscala/Function1;
	areturn
  Labels:
  Deprecated: true

public scala.Function1 tupled();
  Signature: ()Lscala/Function1;
  Code:
   Stack=1, Locals=1, Args_size=1
	aload_0
	invokestatic	Method scala/Function3$class.tupled:(Lscala/Function3;)Lscala/Function1;
	areturn
  Labels:

public scala.Option unapply(scala.actors.remote.SendTo);
  Signature: (Lscala/actors/remote/SendTo;)Lscala/Option;
  Code:
   Stack=7, Locals=2, Args_size=2
	aload_1
	dup
	pop
	ifnull	l1 // getstatic
	aload_1
	aconst_null
	invokevirtual	Method java/lang/Object.equals:(Ljava/lang/Object;)Z
	ifeq	l2 // new
l1	getstatic	Field scala/None$.MODULE$:Lscala/None$;
	goto	l3 // areturn
l2	new	class scala/Some
	dup
	new	class scala/Tuple3
	dup
	aload_1
	invokevirtual	Method scala/actors/remote/SendTo.a:()Lscala/actors/OutputChannel;
	aload_1
	invokevirtual	Method scala/actors/remote/SendTo.msg:()Ljava/lang/Object;
	aload_1
	invokevirtual	Method scala/actors/remote/SendTo.session:()Lscala/Symbol;
	invokespecial	Method scala/Tuple3."<init>":(Ljava/lang/Object;Ljava/lang/Object;Ljava/lang/Object;)V
	invokespecial	Method scala/Some."<init>":(Ljava/lang/Object;)V
l3	areturn
  Labels:
   	l1 = 14 // getstatic
   	l2 = 20 // new
   	l3 = 46 // areturn
  LocalVariableTable: 
   Start  Length  Slot  Name   Signature
   0      47      0    this       Lscala/actors/remote/SendTo$;
   0      47      1    x$0       Lscala/actors/remote/SendTo;


public scala.actors.remote.SendTo apply(scala.actors.OutputChannel, java.lang.Object, scala.Symbol);
  Signature: (Lscala/actors/OutputChannel;Ljava/lang/Object;Lscala/Symbol;)Lscala/actors/remote/SendTo;
  Code:
   Stack=5, Locals=4, Args_size=4
	new	class scala/actors/remote/SendTo
	dup
	aload_1
	aload_2
	aload_3
	invokespecial	Method scala/actors/remote/SendTo."<init>":(Lscala/actors/OutputChannel;Ljava/lang/Object;Lscala/Symbol;)V
	areturn
  Labels:
  LocalVariableTable: 
   Start  Length  Slot  Name   Signature
   0      11      0    this       Lscala/actors/remote/SendTo$;
   0      11      1    a       Lscala/actors/OutputChannel;
   0      11      2    msg       Ljava/lang/Object;
   0      11      3    session       Lscala/Symbol;


public java.lang.Object apply(java.lang.Object, java.lang.Object, java.lang.Object);
  Signature: (Ljava/lang/Object;Ljava/lang/Object;Ljava/lang/Object;)Ljava/lang/Object;
  Code:
   Stack=4, Locals=4, Args_size=4
	aload_0
	aload_1
	checkcast	class scala/actors/OutputChannel
	aload_2
	aload_3
	checkcast	class scala/Symbol
	invokevirtual	Method apply:(Lscala/actors/OutputChannel;Ljava/lang/Object;Lscala/Symbol;)Lscala/actors/remote/SendTo;
	areturn
  Labels:
  LocalVariableTable: 
   Start  Length  Slot  Name   Signature
   0      14      0    this       Lscala/actors/remote/SendTo$;
   0      14      1    v1       Ljava/lang/Object;
   0      14      2    v2       Ljava/lang/Object;
   0      14      3    v3       Ljava/lang/Object;


private scala.actors.remote.SendTo$();
  Signature: ()V
  Code:
   Stack=1, Locals=1, Args_size=1
	aload_0
	invokespecial	Method java/lang/Object."<init>":()V
	aload_0
	putstatic	Field MODULE$:Lscala/actors/remote/SendTo$;
	aload_0
	invokestatic	Method scala/Function3$class.$init$:(Lscala/Function3;)V
	return
  Labels:

}

