Compiled from "Serializer.scala"
public abstract class scala.actors.remote.Serializer extends java.lang.Object implements scala.ScalaObject
  SourceFile: "Serializer.scala"
  ScalaSig: length = 0x2AB
   05 00 69 06 08 01 02 FFFFFF84 FFFFFF80 FFFFFF80 FFFFFF81 00 09 02 0A 53
   65 72 69 61 6C 69 7A 65 72 0A 02 03 04 01 06 72
   65 6D 6F 74 65 0A 02 05 06 01 06 61 63 74 6F 72
   73 0A 01 07 01 05 73 63 61 6C 61 03 00 13 03 00
   0A 12 10 02 0B 10 0D 01 0C 0A 02 0D 0E 01 04 6C
   61 6E 67 0A 01 0F 01 04 6A 61 76 61 09 02 11 0C
   02 06 4F 62 6A 65 63 74 10 02 13 14 0D 01 06 09
   02 15 06 02 0B 53 63 61 6C 61 4F 62 6A 65 63 74
   08 08 17 00 FFFFFF82 FFFFFFC2 FFFFFF80 FFFFFF84 00 18 01 07 73 65 72 76
   69 63 65 15 01 19 10 02 1A 1B 0D 01 02 09 02 1C
   02 02 07 53 65 72 76 69 63 65 08 08 1E 00 FFFFFF82 FFFFFF80
   FFFFFFA0 FFFFFF80 04 19 01 08 73 65 72 76 69 63 65 20 08 05
   20 00 FFFFFF84 00 21 01 06 3C 69 6E 69 74 3E 14 02 22
   23 10 02 1A 00 08 05 17 1F FFFFFFC0 00 19 08 05 25 00
   FFFFFF86 00 26 01 09 73 65 72 69 61 6C 69 7A 65 14 02
   27 2D 10 03 13 28 2A 09 02 29 06 02 05 41 72 72
   61 79 10 02 13 2B 09 02 2C 06 02 04 42 79 74 65
   08 05 2E 24 FFFFFFC0 00 2F 01 01 6F 10 02 13 30 09 02
   31 06 02 06 41 6E 79 52 65 66 08 05 33 00 FFFFFF86 00
   34 01 0B 64 65 73 65 72 69 61 6C 69 7A 65 14 02
   2F 35 08 05 36 32 FFFFFFC0 00 27 01 01 61 08 05 38 00
   FFFFFF84 04 39 01 09 72 65 61 64 42 79 74 65 73 14 02
   27 3A 08 05 3B 37 FFFFFFC0 00 3C 01 0B 69 6E 70 75 74
   53 74 72 65 61 6D 10 02 3D 40 0D 01 3E 0A 02 3F
   0E 01 02 69 6F 09 02 41 3E 02 0F 44 61 74 61 49
   6E 70 75 74 53 74 72 65 61 6D 28 03 37 43 46 10
   02 13 44 09 02 45 06 02 06 74 68 72 6F 77 73 23
   01 47 10 02 3D 48 09 02 49 3E 02 0B 49 4F 45 78
   63 65 70 74 69 6F 6E 08 05 4B 00 FFFFFF84 00 4C 01 0A
   72 65 61 64 4F 62 6A 65 63 74 14 02 2F 4D 08 05
   3B 4A FFFFFFC0 00 3C 28 03 4A 43 4F 23 01 50 10 02 0B
   51 09 02 52 0C 02 16 43 6C 61 73 73 4E 6F 74 46
   6F 75 6E 64 45 78 63 65 70 74 69 6F 6E 28 03 4A
   43 46 08 05 55 00 FFFFFF84 04 56 01 0A 77 72 69 74 65
   42 79 74 65 73 14 03 57 5A 5F 10 02 13 58 09 02
   59 06 02 04 55 6E 69 74 08 05 5B 54 FFFFFFC0 00 5C 01
   0C 6F 75 74 70 75 74 53 74 72 65 61 6D 10 02 3D
   5D 09 02 5E 3E 02 10 44 61 74 61 4F 75 74 70 75
   74 53 74 72 65 61 6D 08 05 60 54 FFFFFFC0 00 27 01 05
   62 79 74 65 73 28 03 54 43 46 08 05 63 00 FFFFFF84 00
   64 01 0B 77 72 69 74 65 4F 62 6A 65 63 74 14 03
   57 65 66 08 05 5B 62 FFFFFFC0 00 5C 08 05 67 62 FFFFFFC0 00
   2F 01 03 6F 62 6A 28 03 62 43 46 
  minor version: 0
  major version: 49
  Constant pool:
Asciz	SourceFile;
Asciz	Serializer.scala;
Asciz	service;
Asciz	Lscala/actors/remote/Service;;
Asciz	()Lscala/actors/remote/Service;;
Asciz	Code;
Asciz	LineNumberTable;
Asciz	scala/actors/remote/Serializer;
class	scala/actors/remote/Serializer
NameAndType	service:Lscala/actors/remote/Service;
Field	scala/actors/remote/Serializer.service:Lscala/actors/remote/Service;
Asciz	serialize;
Asciz	(Ljava/lang/Object;)[B;
Asciz	deserialize;
Asciz	([B)Ljava/lang/Object;;
Asciz	readBytes;
Asciz	(Ljava/io/DataInputStream;)[B;
Asciz	java/io/DataInputStream;
class	java/io/DataInputStream
Asciz	readInt;
Asciz	()I;
NameAndType	readInt:()I
Method	java/io/DataInputStream.readInt:()I
Asciz	readFully;
Asciz	([BII)V;
NameAndType	readFully:([BII)V
Method	java/io/DataInputStream.readFully:([BII)V
Asciz	java/io/EOFException;
class	java/io/EOFException
Asciz	Connection closed.;
String	Connection closed.
Asciz	<init>;
Asciz	(Ljava/lang/String;)V;
NameAndType	"<init>":(Ljava/lang/String;)V
Method	java/io/EOFException."<init>":(Ljava/lang/String;)V
Asciz	java/lang/NullPointerException;
class	java/lang/NullPointerException
Asciz	this;
Asciz	Lscala/actors/remote/Serializer;;
Asciz	inputStream;
Asciz	Ljava/io/DataInputStream;;
Asciz	exceptionResult1;
Asciz	[B;
Asciz	length;
Asciz	I;
Asciz	bytes;
Asciz	LocalVariableTable;
Asciz	java/io/IOException;
class	java/io/IOException
Asciz	Exceptions;
Asciz	readObject;
Asciz	(Ljava/io/DataInputStream;)Ljava/lang/Object;;
NameAndType	readBytes:(Ljava/io/DataInputStream;)[B
Method	scala/actors/remote/Serializer.readBytes:(Ljava/io/DataInputStream;)[B
NameAndType	deserialize:([B)Ljava/lang/Object;
Method	scala/actors/remote/Serializer.deserialize:([B)Ljava/lang/Object;
Asciz	java/lang/ClassNotFoundException;
class	java/lang/ClassNotFoundException
Asciz	writeBytes;
Asciz	(Ljava/io/DataOutputStream;[B)V;
Asciz	java/io/DataOutputStream;
class	java/io/DataOutputStream
Asciz	writeInt;
Asciz	(I)V;
NameAndType	writeInt:(I)V
Method	java/io/DataOutputStream.writeInt:(I)V
Asciz	write;
NameAndType	write:([BII)V
Method	java/io/DataOutputStream.write:([BII)V
Asciz	flush;
Asciz	()V;
NameAndType	flush:()V
Method	java/io/DataOutputStream.flush:()V
Asciz	outputStream;
Asciz	Ljava/io/DataOutputStream;;
Asciz	writeObject;
Asciz	(Ljava/io/DataOutputStream;Ljava/lang/Object;)V;
NameAndType	serialize:(Ljava/lang/Object;)[B
Method	scala/actors/remote/Serializer.serialize:(Ljava/lang/Object;)[B
NameAndType	writeBytes:(Ljava/io/DataOutputStream;[B)V
Method	scala/actors/remote/Serializer.writeBytes:(Ljava/io/DataOutputStream;[B)V
Asciz	obj;
Asciz	Ljava/lang/Object;;
Asciz	(Lscala/actors/remote/Service;)V;
Asciz	java/lang/Object;
class	java/lang/Object
NameAndType	"<init>":()V
Method	java/lang/Object."<init>":()V
Asciz	ScalaSig;
Asciz	scala/ScalaObject;
class	scala/ScalaObject

{
private final scala.actors.remote.Service service;
  Signature: Lscala/actors/remote/Service;

public scala.actors.remote.Service service();
  Signature: ()Lscala/actors/remote/Service;
  Code:
   Stack=1, Locals=1, Args_size=1
	aload_0
	getfield	Field service:Lscala/actors/remote/Service;
	areturn
  Labels:

public abstract byte[] serialize(java.lang.Object);
  Signature: (Ljava/lang/Object;)[B

public abstract java.lang.Object deserialize(byte[]);
  Signature: ([B)Ljava/lang/Object;

private byte[] readBytes(java.io.DataInputStream)   throws java.io.IOException;
  Signature: (Ljava/io/DataInputStream;)[B
  Code:
   Stack=4, Locals=6, Args_size=2
	aconst_null
	astore_2
	aload_1
	invokevirtual	Method java/io/DataInputStream.readInt:()I
	istore	4
	iload	4
	newarray byte
	astore	5
	aload_1
	aload	5
	iconst_0
	iload	4
	invokevirtual	Method java/io/DataInputStream.readFully:([BII)V
	aload	5
	astore_2
	aload_2
	areturn
	astore_3
	new	class java/io/EOFException
	dup
	ldc	String Connection closed.
	invokespecial	Method java/io/EOFException."<init>":(Ljava/lang/String;)V
	athrow
  Labels:
  Exception table:
   from   to  target type
     2    26    28   Class java/lang/NullPointerException

  LocalVariableTable: 
   Start  Length  Slot  Name   Signature
   0      39      0    this       Lscala/actors/remote/Serializer;
   0      39      1    inputStream       Ljava/io/DataInputStream;
   2      25      2    exceptionResult1       [B
   28      11      2    exceptionResult1       [B
   8      17      4    length       I
   14      11      5    bytes       [B

  Exceptions: 
   throws java.io.IOException
public java.lang.Object readObject(java.io.DataInputStream)   throws java.io.IOException, java.lang.ClassNotFoundException;
  Signature: (Ljava/io/DataInputStream;)Ljava/lang/Object;
  Code:
   Stack=2, Locals=3, Args_size=2
	aload_0
	aload_1
	invokespecial	Method readBytes:(Ljava/io/DataInputStream;)[B
	astore_2
	aload_0
	aload_2
	invokevirtual	Method deserialize:([B)Ljava/lang/Object;
	areturn
  Labels:
  LocalVariableTable: 
   Start  Length  Slot  Name   Signature
   0      12      0    this       Lscala/actors/remote/Serializer;
   0      12      1    inputStream       Ljava/io/DataInputStream;
   6      5      2    bytes       [B

  Exceptions: 
   throws java.io.IOException, java.lang.ClassNotFoundException
private void writeBytes(java.io.DataOutputStream, byte[])   throws java.io.IOException;
  Signature: (Ljava/io/DataOutputStream;[B)V
  Code:
   Stack=4, Locals=4, Args_size=3
	aload_2
	arraylength
	istore_3
	aload_1
	iload_3
	invokevirtual	Method java/io/DataOutputStream.writeInt:(I)V
	aload_1
	aload_2
	iconst_0
	iload_3
	invokevirtual	Method java/io/DataOutputStream.write:([BII)V
	aload_1
	invokevirtual	Method java/io/DataOutputStream.flush:()V
	return
  Labels:
  LocalVariableTable: 
   Start  Length  Slot  Name   Signature
   0      20      0    this       Lscala/actors/remote/Serializer;
   0      20      1    outputStream       Ljava/io/DataOutputStream;
   0      20      2    bytes       [B
   3      16      3    length       I

  Exceptions: 
   throws java.io.IOException
public void writeObject(java.io.DataOutputStream, java.lang.Object)   throws java.io.IOException;
  Signature: (Ljava/io/DataOutputStream;Ljava/lang/Object;)V
  Code:
   Stack=3, Locals=4, Args_size=3
	aload_0
	aload_2
	invokevirtual	Method serialize:(Ljava/lang/Object;)[B
	astore_3
	aload_0
	aload_1
	aload_3
	invokespecial	Method writeBytes:(Ljava/io/DataOutputStream;[B)V
	return
  Labels:
  LocalVariableTable: 
   Start  Length  Slot  Name   Signature
   0      13      0    this       Lscala/actors/remote/Serializer;
   0      13      1    outputStream       Ljava/io/DataOutputStream;
   0      13      2    obj       Ljava/lang/Object;
   6      6      3    bytes       [B

  Exceptions: 
   throws java.io.IOException
public scala.actors.remote.Serializer(scala.actors.remote.Service);
  Signature: (Lscala/actors/remote/Service;)V
  Code:
   Stack=2, Locals=2, Args_size=2
	aload_0
	aload_1
	putfield	Field service:Lscala/actors/remote/Service;
	aload_0
	invokespecial	Method java/lang/Object."<init>":()V
	return
  Labels:
  LocalVariableTable: 
   Start  Length  Slot  Name   Signature
   0      10      0    this       Lscala/actors/remote/Serializer;
   0      10      1    service       Lscala/actors/remote/Service;


}

