Compiled from "Serializer.scala"
public abstract class scala.actors.remote.Serializer extends java.lang.Object implements scala.ScalaObject
  SourceFile: "Serializer.scala"
  ScalaSig: length = 0x2AB
   05 00 69 06 08 01 02 FFFFFF84 FFFFFF80 FFFFFF80 FFFFFF81 00 09 02 0A 53
   65 72 69 61 6C 69 7A 65 72 0A 02 03 04 01 06 72
   65 6D 6F 74 65 0A 02 05 06 01 06 61 63 74 6F 72
   73 0A 01 07 01 05 73 63 61 6C 61 03 00 13 03 00
   0A 12 10 02 0B 10 0D 01 0C 0A 02 0D 0E 01 04 6C
   61 6E 67 0A 01 0F 01 04 6A 61 76 61 09 02 11 0C
   02 06 4F 62 6A 65 63 74 10 02 13 14 0D 01 06 09
   02 15 06 02 0B 53 63 61 6C 61 4F 62 6A 65 63 74
   08 08 17 00 FFFFFF82 FFFFFFC2 FFFFFF80 FFFFFF84 00 18 01 07 73 65 72 76
   69 63 65 15 01 19 10 02 1A 1B 0D 01 02 09 02 1C
   02 02 07 53 65 72 76 69 63 65 08 08 1E 00 FFFFFF82 FFFFFF80
   FFFFFFA0 FFFFFF80 04 19 01 08 73 65 72 76 69 63 65 20 08 05
   20 00 FFFFFF84 00 21 01 06 3C 69 6E 69 74 3E 14 02 22
   23 10 02 1A 00 08 05 17 1F FFFFFFC0 00 19 08 05 25 00
   FFFFFF86 00 26 01 09 73 65 72 69 61 6C 69 7A 65 14 02
   27 2D 10 03 13 28 2A 09 02 29 06 02 05 41 72 72
   61 79 10 02 13 2B 09 02 2C 06 02 04 42 79 74 65
   08 05 2E 24 FFFFFFC0 00 2F 01 01 6F 10 02 13 30 09 02
   31 06 02 06 41 6E 79 52 65 66 08 05 33 00 FFFFFF86 00
   34 01 0B 64 65 73 65 72 69 61 6C 69 7A 65 14 02
   2F 35 08 05 36 32 FFFFFFC0 00 27 01 01 61 08 05 38 00
   FFFFFF84 04 39 01 09 72 65 61 64 42 79 74 65 73 14 02
   27 3A 08 05 3B 37 FFFFFFC0 00 3C 01 0B 69 6E 70 75 74
   53 74 72 65 61 6D 10 02 3D 40 0D 01 3E 0A 02 3F
   0E 01 02 69 6F 09 02 41 3E 02 0F 44 61 74 61 49
   6E 70 75 74 53 74 72 65 61 6D 28 03 37 43 46 10
   02 13 44 09 02 45 06 02 06 74 68 72 6F 77 73 23
   01 47 10 02 3D 48 09 02 49 3E 02 0B 49 4F 45 78
   63 65 70 74 69 6F 6E 08 05 4B 00 FFFFFF84 00 4C 01 0A
   72 65 61 64 4F 62 6A 65 63 74 14 02 2F 4D 08 05
   3B 4A FFFFFFC0 00 3C 28 03 4A 43 4F 23 01 50 10 02 0B
   51 09 02 52 0C 02 16 43 6C 61 73 73 4E 6F 74 46
   6F 75 6E 64 45 78 63 65 70 74 69 6F 6E 28 03 4A
   43 46 08 05 55 00 FFFFFF84 04 56 01 0A 77 72 69 74 65
   42 79 74 65 73 14 03 57 5A 5F 10 02 13 58 09 02
   59 06 02 04 55 6E 69 74 08 05 5B 54 FFFFFFC0 00 5C 01
   0C 6F 75 74 70 75 74 53 74 72 65 61 6D 10 02 3D
   5D 09 02 5E 3E 02 10 44 61 74 61 4F 75 74 70 75
   74 53 74 72 65 61 6D 08 05 60 54 FFFFFFC0 00 27 01 05
   62 79 74 65 73 28 03 54 43 46 08 05 63 00 FFFFFF84 00
   64 01 0B 77 72 69 74 65 4F 62 6A 65 63 74 14 03
   57 65 66 08 05 5B 62 FFFFFFC0 00 5C 08 05 67 62 FFFFFFC0 00
   2F 01 03 6F 62 6A 28 03 62 43 46 
  minor version: 0
  major version: 49
  Constant pool:
const #1 = Asciz	SourceFile;
const #2 = Asciz	Serializer.scala;
const #3 = Asciz	service;
const #4 = Asciz	Lscala/actors/remote/Service;;
const #5 = Asciz	<init>;
const #6 = Asciz	(Lscala/actors/remote/Service;)V;
const #7 = Asciz	Code;
const #8 = Asciz	LineNumberTable;
const #9 = Asciz	scala/actors/remote/Serializer;
const #10 = class	#9;	//  scala/actors/remote/Serializer
const #11 = NameAndType	#3:#4;//  service:Lscala/actors/remote/Service;
const #12 = Field	#10.#11;	//  scala/actors/remote/Serializer.service:Lscala/actors/remote/Service;
const #13 = Asciz	java/lang/Object;
const #14 = class	#13;	//  java/lang/Object
const #15 = Asciz	()V;
const #16 = NameAndType	#5:#15;//  "<init>":()V
const #17 = Method	#14.#16;	//  java/lang/Object."<init>":()V
const #18 = Asciz	this;
const #19 = Asciz	Lscala/actors/remote/Serializer;;
const #20 = Asciz	LocalVariableTable;
const #21 = Asciz	writeObject;
const #22 = Asciz	(Ljava/io/DataOutputStream;Ljava/lang/Object;)V;
const #23 = Asciz	serialize;
const #24 = Asciz	(Ljava/lang/Object;)[B;
const #25 = NameAndType	#23:#24;//  serialize:(Ljava/lang/Object;)[B
const #26 = Method	#10.#25;	//  scala/actors/remote/Serializer.serialize:(Ljava/lang/Object;)[B
const #27 = Asciz	writeBytes;
const #28 = Asciz	(Ljava/io/DataOutputStream;[B)V;
const #29 = NameAndType	#27:#28;//  writeBytes:(Ljava/io/DataOutputStream;[B)V
const #30 = Method	#10.#29;	//  scala/actors/remote/Serializer.writeBytes:(Ljava/io/DataOutputStream;[B)V
const #31 = Asciz	outputStream;
const #32 = Asciz	Ljava/io/DataOutputStream;;
const #33 = Asciz	obj;
const #34 = Asciz	Ljava/lang/Object;;
const #35 = Asciz	bytes;
const #36 = Asciz	[B;
const #37 = Asciz	java/io/IOException;
const #38 = class	#37;	//  java/io/IOException
const #39 = Asciz	Exceptions;
const #40 = Asciz	java/io/DataOutputStream;
const #41 = class	#40;	//  java/io/DataOutputStream
const #42 = Asciz	writeInt;
const #43 = Asciz	(I)V;
const #44 = NameAndType	#42:#43;//  writeInt:(I)V
const #45 = Method	#41.#44;	//  java/io/DataOutputStream.writeInt:(I)V
const #46 = Asciz	write;
const #47 = Asciz	([BII)V;
const #48 = NameAndType	#46:#47;//  write:([BII)V
const #49 = Method	#41.#48;	//  java/io/DataOutputStream.write:([BII)V
const #50 = Asciz	flush;
const #51 = NameAndType	#50:#15;//  flush:()V
const #52 = Method	#41.#51;	//  java/io/DataOutputStream.flush:()V
const #53 = Asciz	length;
const #54 = Asciz	I;
const #55 = Asciz	readObject;
const #56 = Asciz	(Ljava/io/DataInputStream;)Ljava/lang/Object;;
const #57 = Asciz	readBytes;
const #58 = Asciz	(Ljava/io/DataInputStream;)[B;
const #59 = NameAndType	#57:#58;//  readBytes:(Ljava/io/DataInputStream;)[B
const #60 = Method	#10.#59;	//  scala/actors/remote/Serializer.readBytes:(Ljava/io/DataInputStream;)[B
const #61 = Asciz	deserialize;
const #62 = Asciz	([B)Ljava/lang/Object;;
const #63 = NameAndType	#61:#62;//  deserialize:([B)Ljava/lang/Object;
const #64 = Method	#10.#63;	//  scala/actors/remote/Serializer.deserialize:([B)Ljava/lang/Object;
const #65 = Asciz	inputStream;
const #66 = Asciz	Ljava/io/DataInputStream;;
const #67 = Asciz	java/lang/ClassNotFoundException;
const #68 = class	#67;	//  java/lang/ClassNotFoundException
const #69 = Asciz	java/io/DataInputStream;
const #70 = class	#69;	//  java/io/DataInputStream
const #71 = Asciz	readInt;
const #72 = Asciz	()I;
const #73 = NameAndType	#71:#72;//  readInt:()I
const #74 = Method	#70.#73;	//  java/io/DataInputStream.readInt:()I
const #75 = Asciz	readFully;
const #76 = NameAndType	#75:#47;//  readFully:([BII)V
const #77 = Method	#70.#76;	//  java/io/DataInputStream.readFully:([BII)V
const #78 = Asciz	java/io/EOFException;
const #79 = class	#78;	//  java/io/EOFException
const #80 = Asciz	Connection closed.;
const #81 = String	#80;	//  Connection closed.
const #82 = Asciz	(Ljava/lang/String;)V;
const #83 = NameAndType	#5:#82;//  "<init>":(Ljava/lang/String;)V
const #84 = Method	#79.#83;	//  java/io/EOFException."<init>":(Ljava/lang/String;)V
const #85 = Asciz	java/lang/NullPointerException;
const #86 = class	#85;	//  java/lang/NullPointerException
const #87 = Asciz	()Lscala/actors/remote/Service;;
const #88 = Asciz	ScalaSig;
const #89 = Asciz	scala/ScalaObject;
const #90 = class	#89;	//  scala/ScalaObject

{
public scala.actors.remote.Serializer(scala.actors.remote.Service);
  Code:
   Stack=2, Locals=2, Args_size=2
   0:	aload_0
   1:	aload_1
   2:	putfield	#12; //Field service:Lscala/actors/remote/Service;
   5:	aload_0
   6:	invokespecial	#17; //Method java/lang/Object."<init>":()V
   9:	return
  LineNumberTable: 
   line 20: 0

  LocalVariableTable: 
   Start  Length  Slot  Name   Signature
   0      10      0    this       Lscala/actors/remote/Serializer;
   0      10      1    service       Lscala/actors/remote/Service;


public void writeObject(java.io.DataOutputStream, java.lang.Object)   throws java.io.IOException;
  Code:
   Stack=3, Locals=4, Args_size=3
   0:	aload_0
   1:	aload_2
   2:	invokevirtual	#26; //Method serialize:(Ljava/lang/Object;)[B
   5:	astore_3
   6:	aload_0
   7:	aload_1
   8:	aload_3
   9:	invokespecial	#30; //Method writeBytes:(Ljava/io/DataOutputStream;[B)V
   12:	return
  LineNumberTable: 
   line 55: 0
   line 56: 6

  LocalVariableTable: 
   Start  Length  Slot  Name   Signature
   0      13      0    this       Lscala/actors/remote/Serializer;
   0      13      1    outputStream       Ljava/io/DataOutputStream;
   0      13      2    obj       Ljava/lang/Object;
   6      6      3    bytes       [B

  Exceptions: 
   throws java.io.IOException
public java.lang.Object readObject(java.io.DataInputStream)   throws java.io.IOException, java.lang.ClassNotFoundException;
  Code:
   Stack=2, Locals=3, Args_size=2
   0:	aload_0
   1:	aload_1
   2:	invokespecial	#60; //Method readBytes:(Ljava/io/DataInputStream;)[B
   5:	astore_2
   6:	aload_0
   7:	aload_2
   8:	invokevirtual	#64; //Method deserialize:([B)Ljava/lang/Object;
   11:	areturn
  LineNumberTable: 
   line 40: 0
   line 41: 6

  LocalVariableTable: 
   Start  Length  Slot  Name   Signature
   0      12      0    this       Lscala/actors/remote/Serializer;
   0      12      1    inputStream       Ljava/io/DataInputStream;
   6      5      2    bytes       [B

  Exceptions: 
   throws java.io.IOException, java.lang.ClassNotFoundException
public abstract java.lang.Object deserialize(byte[]);

public abstract byte[] serialize(java.lang.Object);

public scala.actors.remote.Service service();
  Code:
   Stack=1, Locals=1, Args_size=1
   0:	aload_0
   1:	getfield	#12; //Field service:Lscala/actors/remote/Service;
   4:	areturn
  LineNumberTable: 
   line 20: 0


}

