Compiled from "Service.scala"
public abstract class scala.actors.remote.Service$class extends java.lang.Object
  SourceFile: "Service.scala"
  Scala: length = 0x
   
  minor version: 0
  major version: 49
  Constant pool:
const #1 = Asciz	SourceFile;
const #2 = Asciz	Service.scala;
const #3 = Asciz	$init$;
const #4 = Asciz	(Lscala/actors/remote/Service;)V;
const #5 = Asciz	Code;
const #6 = Asciz	LineNumberTable;
const #7 = Asciz	scala/actors/remote/NetKernel;
const #8 = class	#7;	//  scala/actors/remote/NetKernel
const #9 = Asciz	<init>;
const #10 = NameAndType	#9:#4;//  "<init>":(Lscala/actors/remote/Service;)V
const #11 = Method	#8.#10;	//  scala/actors/remote/NetKernel."<init>":(Lscala/actors/remote/Service;)V
const #12 = Asciz	scala/actors/remote/Service;
const #13 = class	#12;	//  scala/actors/remote/Service
const #14 = Asciz	scala$actors$remote$Service$_setter_$kernel_$eq;
const #15 = Asciz	(Lscala/actors/remote/NetKernel;)V;
const #16 = NameAndType	#14:#15;//  scala$actors$remote$Service$_setter_$kernel_$eq:(Lscala/actors/remote/NetKernel;)V
const #17 = InterfaceMethod	#13.#16;	//  scala/actors/remote/Service.scala$actors$remote$Service$_setter_$kernel_$eq:(Lscala/actors/remote/NetKernel;)V
const #18 = Asciz	$this;
const #19 = Asciz	Lscala/actors/remote/Service;;
const #20 = Asciz	LocalVariableTable;
const #21 = Asciz	Scala;
const #22 = Asciz	scala/actors/remote/Service$class;
const #23 = class	#22;	//  scala/actors/remote/Service$class
const #24 = Asciz	java/lang/Object;
const #25 = class	#24;	//  java/lang/Object

{
public static void $init$(scala.actors.remote.Service);
  Code:
   Stack=4, Locals=1, Args_size=1
   0:	aload_0
   1:	new	#8; //class scala/actors/remote/NetKernel
   4:	dup
   5:	aload_0
   6:	invokespecial	#11; //Method scala/actors/remote/NetKernel."<init>":(Lscala/actors/remote/Service;)V
   9:	invokeinterface	#17,  2; //InterfaceMethod scala/actors/remote/Service.scala$actors$remote$Service$_setter_$kernel_$eq:(Lscala/actors/remote/NetKernel;)V
   14:	return
  LineNumberTable: 
   line 19: 0

  LocalVariableTable: 
   Start  Length  Slot  Name   Signature
   0      15      0    $this       Lscala/actors/remote/Service;


}

