Compiled from "TcpService.scala"
public class scala.actors.remote.TcpServiceWorker extends java.lang.Thread implements scala.ScalaObject
  SourceFile: "TcpService.scala"
  ScalaSig: length = 0x2F1
   05 00 71 06 09 01 02 FFFFFF84 FFFFFF80 FFFFFF80 FFFFFF80 00 04 08 02 10
   54 63 70 53 65 72 76 69 63 65 57 6F 72 6B 65 72
   0A 02 03 04 01 06 72 65 6D 6F 74 65 0A 02 05 06
   01 06 61 63 74 6F 72 73 0A 01 07 01 05 73 63 61
   6C 61 13 03 00 09 11 10 02 0A 0F 0D 01 0B 0A 02
   0C 0D 01 04 6C 61 6E 67 0A 01 0E 01 04 6A 61 76
   61 09 02 10 0B 02 06 54 68 72 65 61 64 10 02 12
   13 0D 01 06 09 02 14 06 02 0B 53 63 61 6C 61 4F
   62 6A 65 63 74 08 08 16 00 FFFFFF82 FFFFFF80 FFFFFFA0 FFFFFF80 04 18 01
   06 70 61 72 65 6E 74 03 00 10 02 19 1A 0D 01 02
   09 02 1B 02 02 0A 54 63 70 53 65 72 76 69 63 65
   08 08 1D 00 FFFFFF82 FFFFFF80 FFFFFFA0 FFFFFF80 04 1E 01 02 73 6F 10 02
   1F 22 0D 01 20 0A 02 21 0D 01 03 6E 65 74 09 02
   23 20 02 06 53 6F 63 6B 65 74 08 05 25 00 FFFFFF84 00
   26 01 06 3C 69 6E 69 74 3E 14 03 27 28 29 10 02
   19 00 08 05 16 24 FFFFFFC0 00 18 08 05 1D 24 FFFFFFC0 00 1E
   08 07 2B 00 FFFFFFC2 FFFFFF80 FFFFFF84 00 2C 01 06 64 61 74 61 69
   6E 15 01 2D 10 02 2E 31 0D 01 2F 0A 02 30 0D 01
   02 69 6F 09 02 32 2F 02 0F 44 61 74 61 49 6E 70
   75 74 53 74 72 65 61 6D 08 06 34 00 FFFFFFA0 FFFFFF80 04 2D
   01 07 64 61 74 61 69 6E 20 08 07 36 00 FFFFFFC2 FFFFFF80 FFFFFF84
   00 37 01 07 64 61 74 61 6F 75 74 15 01 38 10 02
   2E 39 09 02 3A 2F 02 10 44 61 74 61 4F 75 74 70
   75 74 53 74 72 65 61 6D 08 06 3C 00 FFFFFFA0 FFFFFF80 04 38
   01 08 64 61 74 61 6F 75 74 20 08 07 3E 00 FFFFFFC0 FFFFFF80
   FFFFFF84 00 3F 01 0D 63 6F 6E 6E 65 63 74 65 64 4E 6F
   64 65 15 01 40 10 02 19 41 09 02 42 02 02 04 4E
   6F 64 65 08 07 44 00 FFFFFFC0 FFFFFF80 FFFFFF84 00 45 01 11 63 6F
   6E 6E 65 63 74 65 64 4E 6F 64 65 5F 24 65 71 14
   02 46 49 10 02 12 47 09 02 48 06 02 04 55 6E 69
   74 08 07 4A 43 FFFFFF81 FFFFFF80 FFFFFFC0 00 40 01 03 78 24 31 08
   06 4C 00 FFFFFFA0 FFFFFFA0 04 40 01 0E 63 6F 6E 6E 65 63 74
   65 64 4E 6F 64 65 20 08 05 4E 00 FFFFFF84 00 4F 01 08
   73 65 6E 64 4E 6F 64 65 14 02 46 50 08 05 51 4D
   FFFFFFC0 00 40 01 01 6E 08 05 53 00 FFFFFF84 00 54 01 08 72
   65 61 64 4E 6F 64 65 15 01 46 08 05 56 00 FFFFFF84 00
   57 01 08 74 72 61 6E 73 6D 69 74 14 02 46 58 08
   05 59 55 FFFFFFC0 00 5A 01 04 64 61 74 61 10 03 12 5B
   5D 09 02 5C 06 02 05 41 72 72 61 79 10 02 12 5E
   09 02 5F 06 02 04 42 79 74 65 08 07 61 00 FFFFFFC0 FFFFFF80
   FFFFFF84 00 62 01 07 72 75 6E 6E 69 6E 67 15 01 63 10
   02 12 64 09 02 65 06 02 07 42 6F 6F 6C 65 61 6E
   08 07 67 00 FFFFFFC0 FFFFFF80 FFFFFF84 00 68 01 0B 72 75 6E 6E 69
   6E 67 5F 24 65 71 14 02 46 69 08 07 4A 66 FFFFFF81 FFFFFF80
   FFFFFFC0 00 63 08 06 6B 00 FFFFFFA0 FFFFFFA0 04 63 01 08 72 75 6E
   6E 69 6E 67 20 08 05 6D 00 FFFFFF84 00 54 01 04 68 61
   6C 74 08 05 6F 00 FFFFFF84 20 70 01 03 72 75 6E 14 01
   46 
  minor version: 0
  major version: 49
  Constant pool:
const #1 = Asciz	SourceFile;
const #2 = Asciz	TcpService.scala;
const #3 = Asciz	running;
const #4 = Asciz	Z;
const #5 = Asciz	connectedNode;
const #6 = Asciz	Lscala/actors/remote/Node;;
const #7 = Asciz	dataout;
const #8 = Asciz	Ljava/io/DataOutputStream;;
const #9 = Asciz	datain;
const #10 = Asciz	Ljava/io/DataInputStream;;
const #11 = Asciz	so;
const #12 = Asciz	Ljava/net/Socket;;
const #13 = Asciz	parent;
const #14 = Asciz	Lscala/actors/remote/TcpService;;
const #15 = Asciz	<init>;
const #16 = Asciz	(Lscala/actors/remote/TcpService;Ljava/net/Socket;)V;
const #17 = Asciz	Code;
const #18 = Asciz	LineNumberTable;
const #19 = Asciz	scala/actors/remote/TcpServiceWorker;
const #20 = class	#19;	//  scala/actors/remote/TcpServiceWorker
const #21 = NameAndType	#13:#14;//  parent:Lscala/actors/remote/TcpService;
const #22 = Field	#20.#21;	//  scala/actors/remote/TcpServiceWorker.parent:Lscala/actors/remote/TcpService;
const #23 = NameAndType	#11:#12;//  so:Ljava/net/Socket;
const #24 = Field	#20.#23;	//  scala/actors/remote/TcpServiceWorker.so:Ljava/net/Socket;
const #25 = Asciz	java/lang/Thread;
const #26 = class	#25;	//  java/lang/Thread
const #27 = Asciz	()V;
const #28 = NameAndType	#15:#27;//  "<init>":()V
const #29 = Method	#26.#28;	//  java/lang/Thread."<init>":()V
const #30 = Asciz	java/io/DataInputStream;
const #31 = class	#30;	//  java/io/DataInputStream
const #32 = Asciz	java/net/Socket;
const #33 = class	#32;	//  java/net/Socket
const #34 = Asciz	getInputStream;
const #35 = Asciz	()Ljava/io/InputStream;;
const #36 = NameAndType	#34:#35;//  getInputStream:()Ljava/io/InputStream;
const #37 = Method	#33.#36;	//  java/net/Socket.getInputStream:()Ljava/io/InputStream;
const #38 = Asciz	(Ljava/io/InputStream;)V;
const #39 = NameAndType	#15:#38;//  "<init>":(Ljava/io/InputStream;)V
const #40 = Method	#31.#39;	//  java/io/DataInputStream."<init>":(Ljava/io/InputStream;)V
const #41 = NameAndType	#9:#10;//  datain:Ljava/io/DataInputStream;
const #42 = Field	#20.#41;	//  scala/actors/remote/TcpServiceWorker.datain:Ljava/io/DataInputStream;
const #43 = Asciz	java/io/DataOutputStream;
const #44 = class	#43;	//  java/io/DataOutputStream
const #45 = Asciz	getOutputStream;
const #46 = Asciz	()Ljava/io/OutputStream;;
const #47 = NameAndType	#45:#46;//  getOutputStream:()Ljava/io/OutputStream;
const #48 = Method	#33.#47;	//  java/net/Socket.getOutputStream:()Ljava/io/OutputStream;
const #49 = Asciz	(Ljava/io/OutputStream;)V;
const #50 = NameAndType	#15:#49;//  "<init>":(Ljava/io/OutputStream;)V
const #51 = Method	#44.#50;	//  java/io/DataOutputStream."<init>":(Ljava/io/OutputStream;)V
const #52 = NameAndType	#7:#8;//  dataout:Ljava/io/DataOutputStream;
const #53 = Field	#20.#52;	//  scala/actors/remote/TcpServiceWorker.dataout:Ljava/io/DataOutputStream;
const #54 = NameAndType	#3:#4;//  running:Z
const #55 = Field	#20.#54;	//  scala/actors/remote/TcpServiceWorker.running:Z
const #56 = Asciz	this;
const #57 = Asciz	Lscala/actors/remote/TcpServiceWorker;;
const #58 = Asciz	LocalVariableTable;
const #59 = Asciz	run;
const #60 = Asciz	()Z;
const #61 = NameAndType	#3:#60;//  running:()Z
const #62 = Method	#20.#61;	//  scala/actors/remote/TcpServiceWorker.running:()Z
const #63 = Asciz	scala/actors/remote/TcpService;
const #64 = class	#63;	//  scala/actors/remote/TcpService
const #65 = Asciz	serializer;
const #66 = Asciz	()Lscala/actors/remote/JavaSerializer;;
const #67 = NameAndType	#65:#66;//  serializer:()Lscala/actors/remote/JavaSerializer;
const #68 = Method	#64.#67;	//  scala/actors/remote/TcpService.serializer:()Lscala/actors/remote/JavaSerializer;
const #69 = Asciz	()Ljava/io/DataInputStream;;
const #70 = NameAndType	#9:#69;//  datain:()Ljava/io/DataInputStream;
const #71 = Method	#20.#70;	//  scala/actors/remote/TcpServiceWorker.datain:()Ljava/io/DataInputStream;
const #72 = Asciz	scala/actors/remote/JavaSerializer;
const #73 = class	#72;	//  scala/actors/remote/JavaSerializer
const #74 = Asciz	readObject;
const #75 = Asciz	(Ljava/io/DataInputStream;)Ljava/lang/Object;;
const #76 = NameAndType	#74:#75;//  readObject:(Ljava/io/DataInputStream;)Ljava/lang/Object;
const #77 = Method	#73.#76;	//  scala/actors/remote/JavaSerializer.readObject:(Ljava/io/DataInputStream;)Ljava/lang/Object;
const #78 = Asciz	scala/actors/remote/Service;
const #79 = class	#78;	//  scala/actors/remote/Service
const #80 = Asciz	kernel;
const #81 = Asciz	()Lscala/actors/remote/NetKernel;;
const #82 = NameAndType	#80:#81;//  kernel:()Lscala/actors/remote/NetKernel;
const #83 = InterfaceMethod	#79.#82;	//  scala/actors/remote/Service.kernel:()Lscala/actors/remote/NetKernel;
const #84 = Asciz	()Lscala/actors/remote/Node;;
const #85 = NameAndType	#5:#84;//  connectedNode:()Lscala/actors/remote/Node;
const #86 = Method	#20.#85;	//  scala/actors/remote/TcpServiceWorker.connectedNode:()Lscala/actors/remote/Node;
const #87 = Asciz	scala/actors/remote/NetKernel;
const #88 = class	#87;	//  scala/actors/remote/NetKernel
const #89 = Asciz	processMsg;
const #90 = Asciz	(Lscala/actors/remote/Node;Ljava/lang/Object;)V;
const #91 = NameAndType	#89:#90;//  processMsg:(Lscala/actors/remote/Node;Ljava/lang/Object;)V
const #92 = Method	#88.#91;	//  scala/actors/remote/NetKernel.processMsg:(Lscala/actors/remote/Node;Ljava/lang/Object;)V
const #93 = Asciz	scala/actors/Debug$;
const #94 = class	#93;	//  scala/actors/Debug$
const #95 = Asciz	MODULE$;
const #96 = Asciz	Lscala/actors/Debug$;;
const #97 = NameAndType	#95:#96;//  MODULE$:Lscala/actors/Debug$;
const #98 = Field	#94.#97;	//  scala/actors/Debug$.MODULE$:Lscala/actors/Debug$;
const #99 = Asciz	scala/collection/mutable/StringBuilder;
const #100 = class	#99;	//  scala/collection/mutable/StringBuilder
const #101 = Method	#100.#28;	//  scala/collection/mutable/StringBuilder."<init>":()V
const #102 = Asciz	scala/Predef$;
const #103 = class	#102;	//  scala/Predef$
const #104 = Asciz	Lscala/Predef$;;
const #105 = NameAndType	#95:#104;//  MODULE$:Lscala/Predef$;
const #106 = Field	#103.#105;	//  scala/Predef$.MODULE$:Lscala/Predef$;
const #107 = Asciz	any2stringadd;
const #108 = Asciz	(Ljava/lang/Object;)Lscala/runtime/StringAdd;;
const #109 = NameAndType	#107:#108;//  any2stringadd:(Ljava/lang/Object;)Lscala/runtime/StringAdd;
const #110 = Method	#103.#109;	//  scala/Predef$.any2stringadd:(Ljava/lang/Object;)Lscala/runtime/StringAdd;
const #111 = Asciz	: caught ;
const #112 = String	#111;	//  : caught 
const #113 = Asciz	scala/runtime/StringAdd;
const #114 = class	#113;	//  scala/runtime/StringAdd
const #115 = Asciz	$plus;
const #116 = Asciz	(Ljava/lang/String;)Ljava/lang/String;;
const #117 = NameAndType	#115:#116;//  $plus:(Ljava/lang/String;)Ljava/lang/String;
const #118 = Method	#114.#117;	//  scala/runtime/StringAdd.$plus:(Ljava/lang/String;)Ljava/lang/String;
const #119 = Asciz	append;
const #120 = Asciz	(Ljava/lang/Object;)Lscala/collection/mutable/StringBuilder;;
const #121 = NameAndType	#119:#120;//  append:(Ljava/lang/Object;)Lscala/collection/mutable/StringBuilder;
const #122 = Method	#100.#121;	//  scala/collection/mutable/StringBuilder.append:(Ljava/lang/Object;)Lscala/collection/mutable/StringBuilder;
const #123 = Asciz	toString;
const #124 = Asciz	()Ljava/lang/String;;
const #125 = NameAndType	#123:#124;//  toString:()Ljava/lang/String;
const #126 = Method	#100.#125;	//  scala/collection/mutable/StringBuilder.toString:()Ljava/lang/String;
const #127 = Asciz	info;
const #128 = Asciz	(Ljava/lang/String;)V;
const #129 = NameAndType	#127:#128;//  info:(Ljava/lang/String;)V
const #130 = Method	#94.#129;	//  scala/actors/Debug$.info:(Ljava/lang/String;)V
const #131 = Asciz	nodeDown;
const #132 = Asciz	(Lscala/actors/remote/Node;)V;
const #133 = NameAndType	#131:#132;//  nodeDown:(Lscala/actors/remote/Node;)V
const #134 = Method	#64.#133;	//  scala/actors/remote/TcpService.nodeDown:(Lscala/actors/remote/Node;)V
const #135 = Asciz	: service terminated at ;
const #136 = String	#135;	//  : service terminated at 
const #137 = Asciz	node;
const #138 = NameAndType	#137:#84;//  node:()Lscala/actors/remote/Node;
const #139 = Method	#64.#138;	//  scala/actors/remote/TcpService.node:()Lscala/actors/remote/Node;
const #140 = Asciz	java/io/IOException;
const #141 = class	#140;	//  java/io/IOException
const #142 = Asciz	java/lang/Exception;
const #143 = class	#142;	//  java/lang/Exception
const #144 = Asciz	msg;
const #145 = Asciz	Ljava/lang/Object;;
const #146 = Asciz	halt;
const #147 = Asciz	close;
const #148 = NameAndType	#147:#27;//  close:()V
const #149 = Method	#33.#148;	//  java/net/Socket.close:()V
const #150 = Asciz	running_$eq;
const #151 = Asciz	(Z)V;
const #152 = NameAndType	#150:#151;//  running_$eq:(Z)V
const #153 = Method	#20.#152;	//  scala/actors/remote/TcpServiceWorker.running_$eq:(Z)V
const #154 = Asciz	scala/runtime/BoxedUnit;
const #155 = class	#154;	//  scala/runtime/BoxedUnit
const #156 = Asciz	UNIT;
const #157 = Asciz	Lscala/runtime/BoxedUnit;;
const #158 = NameAndType	#156:#157;//  UNIT:Lscala/runtime/BoxedUnit;
const #159 = Field	#155.#158;	//  scala/runtime/BoxedUnit.UNIT:Lscala/runtime/BoxedUnit;
const #160 = Asciz	transmit;
const #161 = Asciz	([B)V;
const #162 = Asciz	: transmitting data...;
const #163 = String	#162;	//  : transmitting data...
const #164 = Asciz	()Ljava/io/DataOutputStream;;
const #165 = NameAndType	#7:#164;//  dataout:()Ljava/io/DataOutputStream;
const #166 = Method	#20.#165;	//  scala/actors/remote/TcpServiceWorker.dataout:()Ljava/io/DataOutputStream;
const #167 = Asciz	writeInt;
const #168 = Asciz	(I)V;
const #169 = NameAndType	#167:#168;//  writeInt:(I)V
const #170 = Method	#44.#169;	//  java/io/DataOutputStream.writeInt:(I)V
const #171 = Asciz	write;
const #172 = NameAndType	#171:#161;//  write:([B)V
const #173 = Method	#44.#172;	//  java/io/DataOutputStream.write:([B)V
const #174 = Asciz	flush;
const #175 = NameAndType	#174:#27;//  flush:()V
const #176 = Method	#44.#175;	//  java/io/DataOutputStream.flush:()V
const #177 = Asciz	data;
const #178 = Asciz	[B;
const #179 = Asciz	readNode;
const #180 = Asciz	scala/actors/remote/Node;
const #181 = class	#180;	//  scala/actors/remote/Node
const #182 = Asciz	connectedNode_$eq;
const #183 = NameAndType	#182:#132;//  connectedNode_$eq:(Lscala/actors/remote/Node;)V
const #184 = Method	#20.#183;	//  scala/actors/remote/TcpServiceWorker.connectedNode_$eq:(Lscala/actors/remote/Node;)V
const #185 = Asciz	addConnection;
const #186 = Asciz	(Lscala/actors/remote/Node;Lscala/actors/remote/TcpServiceWorker;)Lscala/collection/mutable/HashMap;;
const #187 = NameAndType	#185:#186;//  addConnection:(Lscala/actors/remote/Node;Lscala/actors/remote/TcpServiceWorker;)Lscala/collection/mutable/HashMap;
const #188 = Method	#64.#187;	//  scala/actors/remote/TcpService.addConnection:(Lscala/actors/remote/Node;Lscala/actors/remote/TcpServiceWorker;)Lscala/collection/mutable/HashMap;
const #189 = Asciz	scala/MatchError;
const #190 = class	#189;	//  scala/MatchError
const #191 = Asciz	java/lang/Object;
const #192 = class	#191;	//  java/lang/Object
const #193 = Method	#192.#125;	//  java/lang/Object.toString:()Ljava/lang/String;
const #194 = NameAndType	#15:#128;//  "<init>":(Ljava/lang/String;)V
const #195 = Method	#190.#194;	//  scala/MatchError."<init>":(Ljava/lang/String;)V
const #196 = Asciz	temp21;
const #197 = Asciz	temp22;
const #198 = Asciz	n;
const #199 = Asciz	sendNode;
const #200 = Asciz	writeObject;
const #201 = Asciz	(Ljava/io/DataOutputStream;Ljava/lang/Object;)V;
const #202 = NameAndType	#200:#201;//  writeObject:(Ljava/io/DataOutputStream;Ljava/lang/Object;)V
const #203 = Method	#73.#202;	//  scala/actors/remote/JavaSerializer.writeObject:(Ljava/io/DataOutputStream;Ljava/lang/Object;)V
const #204 = NameAndType	#5:#6;//  connectedNode:Lscala/actors/remote/Node;
const #205 = Field	#20.#204;	//  scala/actors/remote/TcpServiceWorker.connectedNode:Lscala/actors/remote/Node;
const #206 = Asciz	ScalaSig;
const #207 = Asciz	scala/ScalaObject;
const #208 = class	#207;	//  scala/ScalaObject

{
public scala.actors.remote.TcpServiceWorker(scala.actors.remote.TcpService, java.net.Socket);
  Code:
   Stack=4, Locals=3, Args_size=3
   0:	aload_0
   1:	aload_1
   2:	putfield	#22; //Field parent:Lscala/actors/remote/TcpService;
   5:	aload_0
   6:	aload_2
   7:	putfield	#24; //Field so:Ljava/net/Socket;
   10:	aload_0
   11:	invokespecial	#29; //Method java/lang/Thread."<init>":()V
   14:	aload_0
   15:	new	#31; //class java/io/DataInputStream
   18:	dup
   19:	aload_2
   20:	invokevirtual	#37; //Method java/net/Socket.getInputStream:()Ljava/io/InputStream;
   23:	invokespecial	#40; //Method java/io/DataInputStream."<init>":(Ljava/io/InputStream;)V
   26:	putfield	#42; //Field datain:Ljava/io/DataInputStream;
   29:	aload_0
   30:	new	#44; //class java/io/DataOutputStream
   33:	dup
   34:	aload_2
   35:	invokevirtual	#48; //Method java/net/Socket.getOutputStream:()Ljava/io/OutputStream;
   38:	invokespecial	#51; //Method java/io/DataOutputStream."<init>":(Ljava/io/OutputStream;)V
   41:	putfield	#53; //Field dataout:Ljava/io/DataOutputStream;
   44:	aload_0
   45:	iconst_1
   46:	putfield	#55; //Field running:Z
   49:	return
  LineNumberTable: 
   line 221: 0
   line 222: 14
   line 223: 29
   line 248: 44

  LocalVariableTable: 
   Start  Length  Slot  Name   Signature
   0      50      0    this       Lscala/actors/remote/TcpServiceWorker;
   0      50      1    parent       Lscala/actors/remote/TcpService;
   0      50      2    so       Ljava/net/Socket;


public void run();
  Code:
   Stack=4, Locals=4, Args_size=1
   0:	aload_0
   1:	invokevirtual	#62; //Method running:()Z
   4:	ifeq	139
   7:	aload_0
   8:	getfield	#22; //Field parent:Lscala/actors/remote/TcpService;
   11:	invokevirtual	#68; //Method scala/actors/remote/TcpService.serializer:()Lscala/actors/remote/JavaSerializer;
   14:	aload_0
   15:	invokevirtual	#71; //Method datain:()Ljava/io/DataInputStream;
   18:	invokevirtual	#77; //Method scala/actors/remote/JavaSerializer.readObject:(Ljava/io/DataInputStream;)Ljava/lang/Object;
   21:	astore_3
   22:	aload_0
   23:	getfield	#22; //Field parent:Lscala/actors/remote/TcpService;
   26:	invokeinterface	#83,  1; //InterfaceMethod scala/actors/remote/Service.kernel:()Lscala/actors/remote/NetKernel;
   31:	aload_0
   32:	invokevirtual	#86; //Method connectedNode:()Lscala/actors/remote/Node;
   35:	aload_3
   36:	invokevirtual	#92; //Method scala/actors/remote/NetKernel.processMsg:(Lscala/actors/remote/Node;Ljava/lang/Object;)V
   39:	goto	0
   42:	astore_1
   43:	getstatic	#98; //Field scala/actors/Debug$.MODULE$:Lscala/actors/Debug$;
   46:	new	#100; //class scala/collection/mutable/StringBuilder
   49:	dup
   50:	invokespecial	#101; //Method scala/collection/mutable/StringBuilder."<init>":()V
   53:	getstatic	#106; //Field scala/Predef$.MODULE$:Lscala/Predef$;
   56:	aload_0
   57:	invokevirtual	#110; //Method scala/Predef$.any2stringadd:(Ljava/lang/Object;)Lscala/runtime/StringAdd;
   60:	ldc	#112; //String : caught 
   62:	invokevirtual	#118; //Method scala/runtime/StringAdd.$plus:(Ljava/lang/String;)Ljava/lang/String;
   65:	invokevirtual	#122; //Method scala/collection/mutable/StringBuilder.append:(Ljava/lang/Object;)Lscala/collection/mutable/StringBuilder;
   68:	aload_1
   69:	invokevirtual	#122; //Method scala/collection/mutable/StringBuilder.append:(Ljava/lang/Object;)Lscala/collection/mutable/StringBuilder;
   72:	invokevirtual	#126; //Method scala/collection/mutable/StringBuilder.toString:()Ljava/lang/String;
   75:	invokevirtual	#130; //Method scala/actors/Debug$.info:(Ljava/lang/String;)V
   78:	aload_0
   79:	getfield	#22; //Field parent:Lscala/actors/remote/TcpService;
   82:	aload_0
   83:	invokevirtual	#86; //Method connectedNode:()Lscala/actors/remote/Node;
   86:	invokevirtual	#134; //Method scala/actors/remote/TcpService.nodeDown:(Lscala/actors/remote/Node;)V
   89:	goto	139
   92:	astore_2
   93:	getstatic	#98; //Field scala/actors/Debug$.MODULE$:Lscala/actors/Debug$;
   96:	new	#100; //class scala/collection/mutable/StringBuilder
   99:	dup
   100:	invokespecial	#101; //Method scala/collection/mutable/StringBuilder."<init>":()V
   103:	getstatic	#106; //Field scala/Predef$.MODULE$:Lscala/Predef$;
   106:	aload_0
   107:	invokevirtual	#110; //Method scala/Predef$.any2stringadd:(Ljava/lang/Object;)Lscala/runtime/StringAdd;
   110:	ldc	#112; //String : caught 
   112:	invokevirtual	#118; //Method scala/runtime/StringAdd.$plus:(Ljava/lang/String;)Ljava/lang/String;
   115:	invokevirtual	#122; //Method scala/collection/mutable/StringBuilder.append:(Ljava/lang/Object;)Lscala/collection/mutable/StringBuilder;
   118:	aload_2
   119:	invokevirtual	#122; //Method scala/collection/mutable/StringBuilder.append:(Ljava/lang/Object;)Lscala/collection/mutable/StringBuilder;
   122:	invokevirtual	#126; //Method scala/collection/mutable/StringBuilder.toString:()Ljava/lang/String;
   125:	invokevirtual	#130; //Method scala/actors/Debug$.info:(Ljava/lang/String;)V
   128:	aload_0
   129:	getfield	#22; //Field parent:Lscala/actors/remote/TcpService;
   132:	aload_0
   133:	invokevirtual	#86; //Method connectedNode:()Lscala/actors/remote/Node;
   136:	invokevirtual	#134; //Method scala/actors/remote/TcpService.nodeDown:(Lscala/actors/remote/Node;)V
   139:	getstatic	#98; //Field scala/actors/Debug$.MODULE$:Lscala/actors/Debug$;
   142:	new	#100; //class scala/collection/mutable/StringBuilder
   145:	dup
   146:	invokespecial	#101; //Method scala/collection/mutable/StringBuilder."<init>":()V
   149:	getstatic	#106; //Field scala/Predef$.MODULE$:Lscala/Predef$;
   152:	aload_0
   153:	invokevirtual	#110; //Method scala/Predef$.any2stringadd:(Ljava/lang/Object;)Lscala/runtime/StringAdd;
   156:	ldc	#136; //String : service terminated at 
   158:	invokevirtual	#118; //Method scala/runtime/StringAdd.$plus:(Ljava/lang/String;)Ljava/lang/String;
   161:	invokevirtual	#122; //Method scala/collection/mutable/StringBuilder.append:(Ljava/lang/Object;)Lscala/collection/mutable/StringBuilder;
   164:	aload_0
   165:	getfield	#22; //Field parent:Lscala/actors/remote/TcpService;
   168:	invokevirtual	#139; //Method scala/actors/remote/TcpService.node:()Lscala/actors/remote/Node;
   171:	invokevirtual	#122; //Method scala/collection/mutable/StringBuilder.append:(Ljava/lang/Object;)Lscala/collection/mutable/StringBuilder;
   174:	invokevirtual	#126; //Method scala/collection/mutable/StringBuilder.toString:()Ljava/lang/String;
   177:	invokevirtual	#130; //Method scala/actors/Debug$.info:(Ljava/lang/String;)V
   180:	return
  Exception table:
   from   to  target type
     0    42    92   Class java/io/IOException

     0    42    42   Class java/lang/Exception

  LineNumberTable: 
   line 257: 0
   line 258: 7
   line 259: 22
   line 257: 39
   line 266: 42
   line 267: 43
   line 268: 78
   line 263: 92
   line 264: 93
   line 265: 128
   line 270: 139

  LocalVariableTable: 
   Start  Length  Slot  Name   Signature
   0      181      0    this       Lscala/actors/remote/TcpServiceWorker;
   22      17      3    msg       Ljava/lang/Object;


public void halt();
  Code:
   Stack=2, Locals=2, Args_size=1
   0:	aload_0
   1:	dup
   2:	astore_1
   3:	monitorenter
   4:	aload_0
   5:	getfield	#24; //Field so:Ljava/net/Socket;
   8:	invokevirtual	#149; //Method java/net/Socket.close:()V
   11:	aload_0
   12:	iconst_0
   13:	invokevirtual	#153; //Method running_$eq:(Z)V
   16:	getstatic	#159; //Field scala/runtime/BoxedUnit.UNIT:Lscala/runtime/BoxedUnit;
   19:	pop
   20:	aload_1
   21:	monitorexit
   22:	return
   23:	aload_1
   24:	monitorexit
   25:	athrow
  Exception table:
   from   to  target type
     4    22    23   any
  LineNumberTable: 
   line 250: 0
   line 251: 4
   line 252: 11
   line 250: 21


public void running_$eq(boolean);
  Code:
   Stack=2, Locals=2, Args_size=2
   0:	aload_0
   1:	iload_1
   2:	putfield	#55; //Field running:Z
   5:	return
  LineNumberTable: 
   line 248: 0


public boolean running();
  Code:
   Stack=1, Locals=1, Args_size=1
   0:	aload_0
   1:	getfield	#55; //Field running:Z
   4:	ireturn
  LineNumberTable: 
   line 248: 0


public void transmit(byte[]);
  Code:
   Stack=3, Locals=3, Args_size=2
   0:	aload_0
   1:	dup
   2:	astore_2
   3:	monitorenter
   4:	getstatic	#98; //Field scala/actors/Debug$.MODULE$:Lscala/actors/Debug$;
   7:	getstatic	#106; //Field scala/Predef$.MODULE$:Lscala/Predef$;
   10:	aload_0
   11:	invokevirtual	#110; //Method scala/Predef$.any2stringadd:(Ljava/lang/Object;)Lscala/runtime/StringAdd;
   14:	ldc	#163; //String : transmitting data...
   16:	invokevirtual	#118; //Method scala/runtime/StringAdd.$plus:(Ljava/lang/String;)Ljava/lang/String;
   19:	invokevirtual	#130; //Method scala/actors/Debug$.info:(Ljava/lang/String;)V
   22:	aload_0
   23:	invokevirtual	#166; //Method dataout:()Ljava/io/DataOutputStream;
   26:	aload_1
   27:	arraylength
   28:	invokevirtual	#170; //Method java/io/DataOutputStream.writeInt:(I)V
   31:	aload_0
   32:	invokevirtual	#166; //Method dataout:()Ljava/io/DataOutputStream;
   35:	aload_1
   36:	invokevirtual	#173; //Method java/io/DataOutputStream.write:([B)V
   39:	aload_0
   40:	invokevirtual	#166; //Method dataout:()Ljava/io/DataOutputStream;
   43:	invokevirtual	#176; //Method java/io/DataOutputStream.flush:()V
   46:	getstatic	#159; //Field scala/runtime/BoxedUnit.UNIT:Lscala/runtime/BoxedUnit;
   49:	pop
   50:	aload_2
   51:	monitorexit
   52:	return
   53:	aload_2
   54:	monitorexit
   55:	athrow
  Exception table:
   from   to  target type
     4    52    53   any
  LineNumberTable: 
   line 241: 0
   line 242: 4
   line 243: 22
   line 244: 31
   line 245: 39
   line 241: 51

  LocalVariableTable: 
   Start  Length  Slot  Name   Signature
   0      56      0    this       Lscala/actors/remote/TcpServiceWorker;
   0      56      1    data       [B


public void readNode();
  Code:
   Stack=3, Locals=5, Args_size=1
   0:	aload_0
   1:	getfield	#22; //Field parent:Lscala/actors/remote/TcpService;
   4:	invokevirtual	#68; //Method scala/actors/remote/TcpService.serializer:()Lscala/actors/remote/JavaSerializer;
   7:	aload_0
   8:	invokevirtual	#71; //Method datain:()Ljava/io/DataInputStream;
   11:	invokevirtual	#77; //Method scala/actors/remote/JavaSerializer.readObject:(Ljava/io/DataInputStream;)Ljava/lang/Object;
   14:	astore_1
   15:	aload_1
   16:	astore_2
   17:	aload_2
   18:	instanceof	#181; //class scala/actors/remote/Node
   21:	ifeq	50
   24:	aload_2
   25:	checkcast	#181; //class scala/actors/remote/Node
   28:	astore_3
   29:	aload_3
   30:	astore	4
   32:	aload_0
   33:	aload	4
   35:	invokevirtual	#184; //Method connectedNode_$eq:(Lscala/actors/remote/Node;)V
   38:	aload_0
   39:	getfield	#22; //Field parent:Lscala/actors/remote/TcpService;
   42:	aload	4
   44:	aload_0
   45:	invokevirtual	#188; //Method scala/actors/remote/TcpService.addConnection:(Lscala/actors/remote/Node;Lscala/actors/remote/TcpServiceWorker;)Lscala/collection/mutable/HashMap;
   48:	pop
   49:	return
   50:	new	#190; //class scala/MatchError
   53:	dup
   54:	aload_2
   55:	invokevirtual	#193; //Method java/lang/Object.toString:()Ljava/lang/String;
   58:	invokespecial	#195; //Method scala/MatchError."<init>":(Ljava/lang/String;)V
   61:	athrow
  LineNumberTable: 
   line 233: 0
   line 234: 15
   line 235: 29
   line 236: 32
   line 237: 38
   line 232: 49
   line 234: 50

  LocalVariableTable: 
   Start  Length  Slot  Name   Signature
   0      62      0    this       Lscala/actors/remote/TcpServiceWorker;
   15      47      1    node       Ljava/lang/Object;
   17      45      2    temp21       Ljava/lang/Object;
   29      20      3    temp22       Lscala/actors/remote/Node;
   32      17      4    n       Lscala/actors/remote/Node;


public void sendNode(scala.actors.remote.Node);
  Code:
   Stack=3, Locals=2, Args_size=2
   0:	aload_0
   1:	aload_1
   2:	invokevirtual	#184; //Method connectedNode_$eq:(Lscala/actors/remote/Node;)V
   5:	aload_0
   6:	getfield	#22; //Field parent:Lscala/actors/remote/TcpService;
   9:	invokevirtual	#68; //Method scala/actors/remote/TcpService.serializer:()Lscala/actors/remote/JavaSerializer;
   12:	aload_0
   13:	invokevirtual	#166; //Method dataout:()Ljava/io/DataOutputStream;
   16:	aload_0
   17:	getfield	#22; //Field parent:Lscala/actors/remote/TcpService;
   20:	invokevirtual	#139; //Method scala/actors/remote/TcpService.node:()Lscala/actors/remote/Node;
   23:	invokevirtual	#203; //Method scala/actors/remote/JavaSerializer.writeObject:(Ljava/io/DataOutputStream;Ljava/lang/Object;)V
   26:	return
  LineNumberTable: 
   line 228: 0
   line 229: 5

  LocalVariableTable: 
   Start  Length  Slot  Name   Signature
   0      27      0    this       Lscala/actors/remote/TcpServiceWorker;
   0      27      1    n       Lscala/actors/remote/Node;


public void connectedNode_$eq(scala.actors.remote.Node);
  Code:
   Stack=2, Locals=2, Args_size=2
   0:	aload_0
   1:	aload_1
   2:	putfield	#205; //Field connectedNode:Lscala/actors/remote/Node;
   5:	return
  LineNumberTable: 
   line 225: 0


public scala.actors.remote.Node connectedNode();
  Code:
   Stack=1, Locals=1, Args_size=1
   0:	aload_0
   1:	getfield	#205; //Field connectedNode:Lscala/actors/remote/Node;
   4:	areturn
  LineNumberTable: 
   line 225: 0


public java.io.DataOutputStream dataout();
  Code:
   Stack=1, Locals=1, Args_size=1
   0:	aload_0
   1:	getfield	#53; //Field dataout:Ljava/io/DataOutputStream;
   4:	areturn
  LineNumberTable: 
   line 223: 0


public java.io.DataInputStream datain();
  Code:
   Stack=1, Locals=1, Args_size=1
   0:	aload_0
   1:	getfield	#42; //Field datain:Ljava/io/DataInputStream;
   4:	areturn
  LineNumberTable: 
   line 222: 0


}

