Compiled from "TcpService.scala"
public class scala.actors.remote.TcpServiceWorker extends java.lang.Thread implements scala.ScalaObject
  SourceFile: "TcpService.scala"
  ScalaSig: length = 0x2F1
   05 00 71 06 09 01 02 FFFFFF84 FFFFFF80 FFFFFF80 FFFFFF80 00 04 08 02 10
   54 63 70 53 65 72 76 69 63 65 57 6F 72 6B 65 72
   0A 02 03 04 01 06 72 65 6D 6F 74 65 0A 02 05 06
   01 06 61 63 74 6F 72 73 0A 01 07 01 05 73 63 61
   6C 61 13 03 00 09 11 10 02 0A 0F 0D 01 0B 0A 02
   0C 0D 01 04 6C 61 6E 67 0A 01 0E 01 04 6A 61 76
   61 09 02 10 0B 02 06 54 68 72 65 61 64 10 02 12
   13 0D 01 06 09 02 14 06 02 0B 53 63 61 6C 61 4F
   62 6A 65 63 74 08 08 16 00 FFFFFF82 FFFFFF80 FFFFFFA0 FFFFFF80 04 18 01
   06 70 61 72 65 6E 74 03 00 10 02 19 1A 0D 01 02
   09 02 1B 02 02 0A 54 63 70 53 65 72 76 69 63 65
   08 08 1D 00 FFFFFF82 FFFFFF80 FFFFFFA0 FFFFFF80 04 1E 01 02 73 6F 10 02
   1F 22 0D 01 20 0A 02 21 0D 01 03 6E 65 74 09 02
   23 20 02 06 53 6F 63 6B 65 74 08 05 25 00 FFFFFF84 00
   26 01 06 3C 69 6E 69 74 3E 14 03 27 28 29 10 02
   19 00 08 05 16 24 FFFFFFC0 00 18 08 05 1D 24 FFFFFFC0 00 1E
   08 07 2B 00 FFFFFFC2 FFFFFF80 FFFFFF84 00 2C 01 06 64 61 74 61 69
   6E 15 01 2D 10 02 2E 31 0D 01 2F 0A 02 30 0D 01
   02 69 6F 09 02 32 2F 02 0F 44 61 74 61 49 6E 70
   75 74 53 74 72 65 61 6D 08 06 34 00 FFFFFFA0 FFFFFF80 04 2D
   01 07 64 61 74 61 69 6E 20 08 07 36 00 FFFFFFC2 FFFFFF80 FFFFFF84
   00 37 01 07 64 61 74 61 6F 75 74 15 01 38 10 02
   2E 39 09 02 3A 2F 02 10 44 61 74 61 4F 75 74 70
   75 74 53 74 72 65 61 6D 08 06 3C 00 FFFFFFA0 FFFFFF80 04 38
   01 08 64 61 74 61 6F 75 74 20 08 07 3E 00 FFFFFFC0 FFFFFF80
   FFFFFF84 00 3F 01 0D 63 6F 6E 6E 65 63 74 65 64 4E 6F
   64 65 15 01 40 10 02 19 41 09 02 42 02 02 04 4E
   6F 64 65 08 07 44 00 FFFFFFC0 FFFFFF80 FFFFFF84 00 45 01 11 63 6F
   6E 6E 65 63 74 65 64 4E 6F 64 65 5F 24 65 71 14
   02 46 49 10 02 12 47 09 02 48 06 02 04 55 6E 69
   74 08 07 4A 43 FFFFFF81 FFFFFF80 FFFFFFC0 00 40 01 03 78 24 31 08
   06 4C 00 FFFFFFA0 FFFFFFA0 04 40 01 0E 63 6F 6E 6E 65 63 74
   65 64 4E 6F 64 65 20 08 05 4E 00 FFFFFF84 00 4F 01 08
   73 65 6E 64 4E 6F 64 65 14 02 46 50 08 05 51 4D
   FFFFFFC0 00 40 01 01 6E 08 05 53 00 FFFFFF84 00 54 01 08 72
   65 61 64 4E 6F 64 65 15 01 46 08 05 56 00 FFFFFF84 00
   57 01 08 74 72 61 6E 73 6D 69 74 14 02 46 58 08
   05 59 55 FFFFFFC0 00 5A 01 04 64 61 74 61 10 03 12 5B
   5D 09 02 5C 06 02 05 41 72 72 61 79 10 02 12 5E
   09 02 5F 06 02 04 42 79 74 65 08 07 61 00 FFFFFFC0 FFFFFF80
   FFFFFF84 00 62 01 07 72 75 6E 6E 69 6E 67 15 01 63 10
   02 12 64 09 02 65 06 02 07 42 6F 6F 6C 65 61 6E
   08 07 67 00 FFFFFFC0 FFFFFF80 FFFFFF84 00 68 01 0B 72 75 6E 6E 69
   6E 67 5F 24 65 71 14 02 46 69 08 07 4A 66 FFFFFF81 FFFFFF80
   FFFFFFC0 00 63 08 06 6B 00 FFFFFFA0 FFFFFFA0 04 63 01 08 72 75 6E
   6E 69 6E 67 20 08 05 6D 00 FFFFFF84 00 54 01 04 68 61
   6C 74 08 05 6F 00 FFFFFF84 20 70 01 03 72 75 6E 14 01
   46 
  minor version: 0
  major version: 49
  Constant pool:
Asciz	SourceFile;
Asciz	TcpService.scala;
Asciz	running;
Asciz	Z;
Asciz	connectedNode;
Asciz	Lscala/actors/remote/Node;;
Asciz	dataout;
Asciz	Ljava/io/DataOutputStream;;
Asciz	datain;
Asciz	Ljava/io/DataInputStream;;
Asciz	so;
Asciz	Ljava/net/Socket;;
Asciz	parent;
Asciz	Lscala/actors/remote/TcpService;;
Asciz	()Ljava/io/DataInputStream;;
Asciz	Code;
Asciz	LineNumberTable;
Asciz	scala/actors/remote/TcpServiceWorker;
class	scala/actors/remote/TcpServiceWorker
NameAndType	datain:Ljava/io/DataInputStream;
Field	scala/actors/remote/TcpServiceWorker.datain:Ljava/io/DataInputStream;
Asciz	()Ljava/io/DataOutputStream;;
NameAndType	dataout:Ljava/io/DataOutputStream;
Field	scala/actors/remote/TcpServiceWorker.dataout:Ljava/io/DataOutputStream;
Asciz	()Lscala/actors/remote/Node;;
NameAndType	connectedNode:Lscala/actors/remote/Node;
Field	scala/actors/remote/TcpServiceWorker.connectedNode:Lscala/actors/remote/Node;
Asciz	connectedNode_$eq;
Asciz	(Lscala/actors/remote/Node;)V;
Asciz	sendNode;
NameAndType	connectedNode_$eq:(Lscala/actors/remote/Node;)V
Method	scala/actors/remote/TcpServiceWorker.connectedNode_$eq:(Lscala/actors/remote/Node;)V
NameAndType	parent:Lscala/actors/remote/TcpService;
Field	scala/actors/remote/TcpServiceWorker.parent:Lscala/actors/remote/TcpService;
Asciz	scala/actors/remote/TcpService;
class	scala/actors/remote/TcpService
Asciz	serializer;
Asciz	()Lscala/actors/remote/JavaSerializer;;
NameAndType	serializer:()Lscala/actors/remote/JavaSerializer;
Method	scala/actors/remote/TcpService.serializer:()Lscala/actors/remote/JavaSerializer;
NameAndType	dataout:()Ljava/io/DataOutputStream;
Method	scala/actors/remote/TcpServiceWorker.dataout:()Ljava/io/DataOutputStream;
Asciz	node;
NameAndType	node:()Lscala/actors/remote/Node;
Method	scala/actors/remote/TcpService.node:()Lscala/actors/remote/Node;
Asciz	scala/actors/remote/JavaSerializer;
class	scala/actors/remote/JavaSerializer
Asciz	writeObject;
Asciz	(Ljava/io/DataOutputStream;Ljava/lang/Object;)V;
NameAndType	writeObject:(Ljava/io/DataOutputStream;Ljava/lang/Object;)V
Method	scala/actors/remote/JavaSerializer.writeObject:(Ljava/io/DataOutputStream;Ljava/lang/Object;)V
Asciz	this;
Asciz	Lscala/actors/remote/TcpServiceWorker;;
Asciz	n;
Asciz	LocalVariableTable;
Asciz	readNode;
Asciz	()V;
NameAndType	datain:()Ljava/io/DataInputStream;
Method	scala/actors/remote/TcpServiceWorker.datain:()Ljava/io/DataInputStream;
Asciz	readObject;
Asciz	(Ljava/io/DataInputStream;)Ljava/lang/Object;;
NameAndType	readObject:(Ljava/io/DataInputStream;)Ljava/lang/Object;
Method	scala/actors/remote/JavaSerializer.readObject:(Ljava/io/DataInputStream;)Ljava/lang/Object;
Asciz	scala/actors/remote/Node;
class	scala/actors/remote/Node
Asciz	addConnection;
Asciz	(Lscala/actors/remote/Node;Lscala/actors/remote/TcpServiceWorker;)Lscala/collection/mutable/HashMap;;
NameAndType	addConnection:(Lscala/actors/remote/Node;Lscala/actors/remote/TcpServiceWorker;)Lscala/collection/mutable/HashMap;
Method	scala/actors/remote/TcpService.addConnection:(Lscala/actors/remote/Node;Lscala/actors/remote/TcpServiceWorker;)Lscala/collection/mutable/HashMap;
Asciz	scala/MatchError;
class	scala/MatchError
Asciz	<init>;
Asciz	(Ljava/lang/Object;)V;
NameAndType	"<init>":(Ljava/lang/Object;)V
Method	scala/MatchError."<init>":(Ljava/lang/Object;)V
Asciz	Ljava/lang/Object;;
Asciz	temp24;
Asciz	temp25;
Asciz	transmit;
Asciz	([B)V;
Asciz	scala/actors/Debug$;
class	scala/actors/Debug$
Asciz	MODULE$;
Asciz	Lscala/actors/Debug$;;
NameAndType	MODULE$:Lscala/actors/Debug$;
Field	scala/actors/Debug$.MODULE$:Lscala/actors/Debug$;
Asciz	scala/Predef$;
class	scala/Predef$
Asciz	Lscala/Predef$;;
NameAndType	MODULE$:Lscala/Predef$;
Field	scala/Predef$.MODULE$:Lscala/Predef$;
Asciz	any2stringadd;
Asciz	(Ljava/lang/Object;)Lscala/runtime/StringAdd;;
NameAndType	any2stringadd:(Ljava/lang/Object;)Lscala/runtime/StringAdd;
Method	scala/Predef$.any2stringadd:(Ljava/lang/Object;)Lscala/runtime/StringAdd;
Asciz	: transmitting data...;
String	: transmitting data...
Asciz	scala/runtime/StringAdd;
class	scala/runtime/StringAdd
Asciz	$plus;
Asciz	(Ljava/lang/String;)Ljava/lang/String;;
NameAndType	$plus:(Ljava/lang/String;)Ljava/lang/String;
Method	scala/runtime/StringAdd.$plus:(Ljava/lang/String;)Ljava/lang/String;
Asciz	info;
Asciz	(Ljava/lang/String;)V;
NameAndType	info:(Ljava/lang/String;)V
Method	scala/actors/Debug$.info:(Ljava/lang/String;)V
Asciz	java/io/DataOutputStream;
class	java/io/DataOutputStream
Asciz	writeInt;
Asciz	(I)V;
NameAndType	writeInt:(I)V
Method	java/io/DataOutputStream.writeInt:(I)V
Asciz	write;
NameAndType	write:([B)V
Method	java/io/DataOutputStream.write:([B)V
Asciz	flush;
NameAndType	flush:()V
Method	java/io/DataOutputStream.flush:()V
Asciz	scala/runtime/BoxedUnit;
class	scala/runtime/BoxedUnit
Asciz	UNIT;
Asciz	Lscala/runtime/BoxedUnit;;
NameAndType	UNIT:Lscala/runtime/BoxedUnit;
Field	scala/runtime/BoxedUnit.UNIT:Lscala/runtime/BoxedUnit;
Asciz	data;
Asciz	[B;
Asciz	()Z;
NameAndType	running:Z
Field	scala/actors/remote/TcpServiceWorker.running:Z
Asciz	running_$eq;
Asciz	(Z)V;
Asciz	halt;
NameAndType	so:Ljava/net/Socket;
Field	scala/actors/remote/TcpServiceWorker.so:Ljava/net/Socket;
Asciz	java/net/Socket;
class	java/net/Socket
Asciz	close;
NameAndType	close:()V
Method	java/net/Socket.close:()V
NameAndType	running_$eq:(Z)V
Method	scala/actors/remote/TcpServiceWorker.running_$eq:(Z)V
Asciz	run;
NameAndType	running:()Z
Method	scala/actors/remote/TcpServiceWorker.running:()Z
Asciz	scala/actors/remote/Service;
class	scala/actors/remote/Service
Asciz	kernel;
Asciz	()Lscala/actors/remote/NetKernel;;
NameAndType	kernel:()Lscala/actors/remote/NetKernel;
InterfaceMethod	scala/actors/remote/Service.kernel:()Lscala/actors/remote/NetKernel;
NameAndType	connectedNode:()Lscala/actors/remote/Node;
Method	scala/actors/remote/TcpServiceWorker.connectedNode:()Lscala/actors/remote/Node;
Asciz	scala/actors/remote/NetKernel;
class	scala/actors/remote/NetKernel
Asciz	processMsg;
Asciz	(Lscala/actors/remote/Node;Ljava/lang/Object;)V;
NameAndType	processMsg:(Lscala/actors/remote/Node;Ljava/lang/Object;)V
Method	scala/actors/remote/NetKernel.processMsg:(Lscala/actors/remote/Node;Ljava/lang/Object;)V
Asciz	scala/collection/mutable/StringBuilder;
class	scala/collection/mutable/StringBuilder
NameAndType	"<init>":()V
Method	scala/collection/mutable/StringBuilder."<init>":()V
Asciz	: caught ;
String	: caught 
Asciz	append;
Asciz	(Ljava/lang/Object;)Lscala/collection/mutable/StringBuilder;;
NameAndType	append:(Ljava/lang/Object;)Lscala/collection/mutable/StringBuilder;
Method	scala/collection/mutable/StringBuilder.append:(Ljava/lang/Object;)Lscala/collection/mutable/StringBuilder;
Asciz	toString;
Asciz	()Ljava/lang/String;;
NameAndType	toString:()Ljava/lang/String;
Method	scala/collection/mutable/StringBuilder.toString:()Ljava/lang/String;
Asciz	nodeDown;
NameAndType	nodeDown:(Lscala/actors/remote/Node;)V
Method	scala/actors/remote/TcpService.nodeDown:(Lscala/actors/remote/Node;)V
Asciz	: service terminated at ;
String	: service terminated at 
Asciz	java/io/IOException;
class	java/io/IOException
Asciz	java/lang/Exception;
class	java/lang/Exception
Asciz	msg;
Asciz	(Lscala/actors/remote/TcpService;Ljava/net/Socket;)V;
Asciz	java/lang/Thread;
class	java/lang/Thread
Method	java/lang/Thread."<init>":()V
Asciz	java/io/DataInputStream;
class	java/io/DataInputStream
Asciz	getInputStream;
Asciz	()Ljava/io/InputStream;;
NameAndType	getInputStream:()Ljava/io/InputStream;
Method	java/net/Socket.getInputStream:()Ljava/io/InputStream;
Asciz	(Ljava/io/InputStream;)V;
NameAndType	"<init>":(Ljava/io/InputStream;)V
Method	java/io/DataInputStream."<init>":(Ljava/io/InputStream;)V
Asciz	getOutputStream;
Asciz	()Ljava/io/OutputStream;;
NameAndType	getOutputStream:()Ljava/io/OutputStream;
Method	java/net/Socket.getOutputStream:()Ljava/io/OutputStream;
Asciz	(Ljava/io/OutputStream;)V;
NameAndType	"<init>":(Ljava/io/OutputStream;)V
Method	java/io/DataOutputStream."<init>":(Ljava/io/OutputStream;)V
Asciz	ScalaSig;
Asciz	scala/ScalaObject;
class	scala/ScalaObject

{
private boolean running;
  Signature: Z

private scala.actors.remote.Node connectedNode;
  Signature: Lscala/actors/remote/Node;

private final java.io.DataOutputStream dataout;
  Signature: Ljava/io/DataOutputStream;

private final java.io.DataInputStream datain;
  Signature: Ljava/io/DataInputStream;

private final java.net.Socket so;
  Signature: Ljava/net/Socket;

private final scala.actors.remote.TcpService parent;
  Signature: Lscala/actors/remote/TcpService;

public java.io.DataInputStream datain();
  Signature: ()Ljava/io/DataInputStream;
  Code:
   Stack=1, Locals=1, Args_size=1
	aload_0
	getfield	Field datain:Ljava/io/DataInputStream;
	areturn
  Labels:

public java.io.DataOutputStream dataout();
  Signature: ()Ljava/io/DataOutputStream;
  Code:
   Stack=1, Locals=1, Args_size=1
	aload_0
	getfield	Field dataout:Ljava/io/DataOutputStream;
	areturn
  Labels:

public scala.actors.remote.Node connectedNode();
  Signature: ()Lscala/actors/remote/Node;
  Code:
   Stack=1, Locals=1, Args_size=1
	aload_0
	getfield	Field connectedNode:Lscala/actors/remote/Node;
	areturn
  Labels:

public void connectedNode_$eq(scala.actors.remote.Node);
  Signature: (Lscala/actors/remote/Node;)V
  Code:
   Stack=2, Locals=2, Args_size=2
	aload_0
	aload_1
	putfield	Field connectedNode:Lscala/actors/remote/Node;
	return
  Labels:

public void sendNode(scala.actors.remote.Node);
  Signature: (Lscala/actors/remote/Node;)V
  Code:
   Stack=3, Locals=2, Args_size=2
	aload_0
	aload_1
	invokevirtual	Method connectedNode_$eq:(Lscala/actors/remote/Node;)V
	aload_0
	getfield	Field parent:Lscala/actors/remote/TcpService;
	invokevirtual	Method scala/actors/remote/TcpService.serializer:()Lscala/actors/remote/JavaSerializer;
	aload_0
	invokevirtual	Method dataout:()Ljava/io/DataOutputStream;
	aload_0
	getfield	Field parent:Lscala/actors/remote/TcpService;
	invokevirtual	Method scala/actors/remote/TcpService.node:()Lscala/actors/remote/Node;
	invokevirtual	Method scala/actors/remote/JavaSerializer.writeObject:(Ljava/io/DataOutputStream;Ljava/lang/Object;)V
	return
  Labels:
  LocalVariableTable: 
   Start  Length  Slot  Name   Signature
   0      27      0    this       Lscala/actors/remote/TcpServiceWorker;
   0      27      1    n       Lscala/actors/remote/Node;


public void readNode();
  Signature: ()V
  Code:
   Stack=3, Locals=5, Args_size=1
	aload_0
	getfield	Field parent:Lscala/actors/remote/TcpService;
	invokevirtual	Method scala/actors/remote/TcpService.serializer:()Lscala/actors/remote/JavaSerializer;
	aload_0
	invokevirtual	Method datain:()Ljava/io/DataInputStream;
	invokevirtual	Method scala/actors/remote/JavaSerializer.readObject:(Ljava/io/DataInputStream;)Ljava/lang/Object;
	astore_1
	aload_1
	astore_2
	aload_2
	instanceof	class scala/actors/remote/Node
	ifeq	l1 // new
	aload_2
	checkcast	class scala/actors/remote/Node
	astore_3
	aload_3
	astore	4
	aload_0
	aload	4
	invokevirtual	Method connectedNode_$eq:(Lscala/actors/remote/Node;)V
	aload_0
	getfield	Field parent:Lscala/actors/remote/TcpService;
	aload	4
	aload_0
	invokevirtual	Method scala/actors/remote/TcpService.addConnection:(Lscala/actors/remote/Node;Lscala/actors/remote/TcpServiceWorker;)Lscala/collection/mutable/HashMap;
	pop
	return
l1	new	class scala/MatchError
	dup
	aload_2
	invokespecial	Method scala/MatchError."<init>":(Ljava/lang/Object;)V
	athrow
  Labels:
   	l1 = 50 // new
  LocalVariableTable: 
   Start  Length  Slot  Name   Signature
   0      59      0    this       Lscala/actors/remote/TcpServiceWorker;
   15      44      1    node       Ljava/lang/Object;
   17      42      2    temp24       Ljava/lang/Object;
   29      20      3    temp25       Lscala/actors/remote/Node;
   32      17      4    n       Lscala/actors/remote/Node;


public void transmit(byte[]);
  Signature: ([B)V
  Code:
   Stack=3, Locals=3, Args_size=2
	aload_0
	dup
	astore_2
	monitorenter
	getstatic	Field scala/actors/Debug$.MODULE$:Lscala/actors/Debug$;
	getstatic	Field scala/Predef$.MODULE$:Lscala/Predef$;
	aload_0
	invokevirtual	Method scala/Predef$.any2stringadd:(Ljava/lang/Object;)Lscala/runtime/StringAdd;
	ldc	String : transmitting data...
	invokevirtual	Method scala/runtime/StringAdd.$plus:(Ljava/lang/String;)Ljava/lang/String;
	invokevirtual	Method scala/actors/Debug$.info:(Ljava/lang/String;)V
	aload_0
	invokevirtual	Method dataout:()Ljava/io/DataOutputStream;
	aload_1
	arraylength
	invokevirtual	Method java/io/DataOutputStream.writeInt:(I)V
	aload_0
	invokevirtual	Method dataout:()Ljava/io/DataOutputStream;
	aload_1
	invokevirtual	Method java/io/DataOutputStream.write:([B)V
	aload_0
	invokevirtual	Method dataout:()Ljava/io/DataOutputStream;
	invokevirtual	Method java/io/DataOutputStream.flush:()V
	getstatic	Field scala/runtime/BoxedUnit.UNIT:Lscala/runtime/BoxedUnit;
	pop
	aload_2
	monitorexit
	return
	aload_2
	monitorexit
	athrow
  Labels:
  Exception table:
   from   to  target type
     4    52    53   any
  LocalVariableTable: 
   Start  Length  Slot  Name   Signature
   0      56      0    this       Lscala/actors/remote/TcpServiceWorker;
   0      56      1    data       [B


public boolean running();
  Signature: ()Z
  Code:
   Stack=1, Locals=1, Args_size=1
	aload_0
	getfield	Field running:Z
	ireturn
  Labels:

public void running_$eq(boolean);
  Signature: (Z)V
  Code:
   Stack=2, Locals=2, Args_size=2
	aload_0
	iload_1
	putfield	Field running:Z
	return
  Labels:

public void halt();
  Signature: ()V
  Code:
   Stack=2, Locals=2, Args_size=1
	aload_0
	dup
	astore_1
	monitorenter
	aload_0
	getfield	Field so:Ljava/net/Socket;
	invokevirtual	Method java/net/Socket.close:()V
	aload_0
	iconst_0
	invokevirtual	Method running_$eq:(Z)V
	getstatic	Field scala/runtime/BoxedUnit.UNIT:Lscala/runtime/BoxedUnit;
	pop
	aload_1
	monitorexit
	return
	aload_1
	monitorexit
	athrow
  Labels:
  Exception table:
   from   to  target type
     4    22    23   any

public void run();
  Signature: ()V
  Code:
   Stack=4, Locals=4, Args_size=1
l2	aload_0
	invokevirtual	Method running:()Z
	ifeq	l1 // getstatic
	aload_0
	getfield	Field parent:Lscala/actors/remote/TcpService;
	invokevirtual	Method scala/actors/remote/TcpService.serializer:()Lscala/actors/remote/JavaSerializer;
	aload_0
	invokevirtual	Method datain:()Ljava/io/DataInputStream;
	invokevirtual	Method scala/actors/remote/JavaSerializer.readObject:(Ljava/io/DataInputStream;)Ljava/lang/Object;
	astore_3
	aload_0
	getfield	Field parent:Lscala/actors/remote/TcpService;
	invokeinterface	InterfaceMethod scala/actors/remote/Service.kernel:()Lscala/actors/remote/NetKernel;
	aload_0
	invokevirtual	Method connectedNode:()Lscala/actors/remote/Node;
	aload_3
	invokevirtual	Method scala/actors/remote/NetKernel.processMsg:(Lscala/actors/remote/Node;Ljava/lang/Object;)V
	goto	l2 // aload_0
	astore_1
	getstatic	Field scala/actors/Debug$.MODULE$:Lscala/actors/Debug$;
	new	class scala/collection/mutable/StringBuilder
	dup
	invokespecial	Method scala/collection/mutable/StringBuilder."<init>":()V
	getstatic	Field scala/Predef$.MODULE$:Lscala/Predef$;
	aload_0
	invokevirtual	Method scala/Predef$.any2stringadd:(Ljava/lang/Object;)Lscala/runtime/StringAdd;
	ldc	String : caught 
	invokevirtual	Method scala/runtime/StringAdd.$plus:(Ljava/lang/String;)Ljava/lang/String;
	invokevirtual	Method scala/collection/mutable/StringBuilder.append:(Ljava/lang/Object;)Lscala/collection/mutable/StringBuilder;
	aload_1
	invokevirtual	Method scala/collection/mutable/StringBuilder.append:(Ljava/lang/Object;)Lscala/collection/mutable/StringBuilder;
	invokevirtual	Method scala/collection/mutable/StringBuilder.toString:()Ljava/lang/String;
	invokevirtual	Method scala/actors/Debug$.info:(Ljava/lang/String;)V
	aload_0
	getfield	Field parent:Lscala/actors/remote/TcpService;
	aload_0
	invokevirtual	Method connectedNode:()Lscala/actors/remote/Node;
	invokevirtual	Method scala/actors/remote/TcpService.nodeDown:(Lscala/actors/remote/Node;)V
	goto	l1 // getstatic
	astore_2
	getstatic	Field scala/actors/Debug$.MODULE$:Lscala/actors/Debug$;
	new	class scala/collection/mutable/StringBuilder
	dup
	invokespecial	Method scala/collection/mutable/StringBuilder."<init>":()V
	getstatic	Field scala/Predef$.MODULE$:Lscala/Predef$;
	aload_0
	invokevirtual	Method scala/Predef$.any2stringadd:(Ljava/lang/Object;)Lscala/runtime/StringAdd;
	ldc	String : caught 
	invokevirtual	Method scala/runtime/StringAdd.$plus:(Ljava/lang/String;)Ljava/lang/String;
	invokevirtual	Method scala/collection/mutable/StringBuilder.append:(Ljava/lang/Object;)Lscala/collection/mutable/StringBuilder;
	aload_2
	invokevirtual	Method scala/collection/mutable/StringBuilder.append:(Ljava/lang/Object;)Lscala/collection/mutable/StringBuilder;
	invokevirtual	Method scala/collection/mutable/StringBuilder.toString:()Ljava/lang/String;
	invokevirtual	Method scala/actors/Debug$.info:(Ljava/lang/String;)V
	aload_0
	getfield	Field parent:Lscala/actors/remote/TcpService;
	aload_0
	invokevirtual	Method connectedNode:()Lscala/actors/remote/Node;
	invokevirtual	Method scala/actors/remote/TcpService.nodeDown:(Lscala/actors/remote/Node;)V
l1	getstatic	Field scala/actors/Debug$.MODULE$:Lscala/actors/Debug$;
	new	class scala/collection/mutable/StringBuilder
	dup
	invokespecial	Method scala/collection/mutable/StringBuilder."<init>":()V
	getstatic	Field scala/Predef$.MODULE$:Lscala/Predef$;
	aload_0
	invokevirtual	Method scala/Predef$.any2stringadd:(Ljava/lang/Object;)Lscala/runtime/StringAdd;
	ldc	String : service terminated at 
	invokevirtual	Method scala/runtime/StringAdd.$plus:(Ljava/lang/String;)Ljava/lang/String;
	invokevirtual	Method scala/collection/mutable/StringBuilder.append:(Ljava/lang/Object;)Lscala/collection/mutable/StringBuilder;
	aload_0
	getfield	Field parent:Lscala/actors/remote/TcpService;
	invokevirtual	Method scala/actors/remote/TcpService.node:()Lscala/actors/remote/Node;
	invokevirtual	Method scala/collection/mutable/StringBuilder.append:(Ljava/lang/Object;)Lscala/collection/mutable/StringBuilder;
	invokevirtual	Method scala/collection/mutable/StringBuilder.toString:()Ljava/lang/String;
	invokevirtual	Method scala/actors/Debug$.info:(Ljava/lang/String;)V
	return
  Labels:
   	l2 = 0 // aload_0
   	l1 = 139 // getstatic
  Exception table:
   from   to  target type
     0    42    92   Class java/io/IOException

     0    42    42   Class java/lang/Exception

  LocalVariableTable: 
   Start  Length  Slot  Name   Signature
   0      181      0    this       Lscala/actors/remote/TcpServiceWorker;
   22      17      3    msg       Ljava/lang/Object;


public scala.actors.remote.TcpServiceWorker(scala.actors.remote.TcpService, java.net.Socket);
  Signature: (Lscala/actors/remote/TcpService;Ljava/net/Socket;)V
  Code:
   Stack=4, Locals=3, Args_size=3
	aload_0
	aload_1
	putfield	Field parent:Lscala/actors/remote/TcpService;
	aload_0
	aload_2
	putfield	Field so:Ljava/net/Socket;
	aload_0
	invokespecial	Method java/lang/Thread."<init>":()V
	aload_0
	new	class java/io/DataInputStream
	dup
	aload_2
	invokevirtual	Method java/net/Socket.getInputStream:()Ljava/io/InputStream;
	invokespecial	Method java/io/DataInputStream."<init>":(Ljava/io/InputStream;)V
	putfield	Field datain:Ljava/io/DataInputStream;
	aload_0
	new	class java/io/DataOutputStream
	dup
	aload_2
	invokevirtual	Method java/net/Socket.getOutputStream:()Ljava/io/OutputStream;
	invokespecial	Method java/io/DataOutputStream."<init>":(Ljava/io/OutputStream;)V
	putfield	Field dataout:Ljava/io/DataOutputStream;
	aload_0
	iconst_1
	putfield	Field running:Z
	return
  Labels:
  LocalVariableTable: 
   Start  Length  Slot  Name   Signature
   0      50      0    this       Lscala/actors/remote/TcpServiceWorker;
   0      50      1    parent       Lscala/actors/remote/TcpService;
   0      50      2    so       Ljava/net/Socket;


}

