Compiled from "TcpService.scala"
public final class scala.actors.remote.TcpService$ extends java.lang.Object implements scala.ScalaObject
  SourceFile: "TcpService.scala"
  Scala: length = 0x
   
  InnerClass: 
   public final $anonfun$run$1=class scala/actors/remote/TcpService$$anonfun$run$1 of class scala/actors/remote/TcpService
   public final $anonfun$liftedTree1$1$1=class scala/actors/remote/TcpService$$anonfun$liftedTree1$1$1 of class scala/actors/remote/TcpService
  minor version: 0
  major version: 49
  Constant pool:
Asciz	SourceFile;
Asciz	TcpService.scala;
Asciz	Scala;
Asciz	MODULE$;
Asciz	Lscala/actors/remote/TcpService$;;
Asciz	<clinit>;
Asciz	()V;
Asciz	Code;
Asciz	scala/actors/remote/TcpService$;
class	scala/actors/remote/TcpService$
Asciz	<init>;
NameAndType	"<init>":()V
Method	scala/actors/remote/TcpService$."<init>":()V
Asciz	BufSize;
Asciz	I;
Asciz	ports;
Asciz	Lscala/collection/mutable/HashMap;;
Asciz	Lscala/collection/mutable/HashMap<Ljava/lang/Integer;Lscala/actors/remote/TcpService;>;;
Asciz	Signature;
Asciz	random;
Asciz	Lscala/util/Random;;
Asciz	()Lscala/util/Random;;
Asciz	LineNumberTable;
NameAndType	random:Lscala/util/Random;
Field	scala/actors/remote/TcpService$.random:Lscala/util/Random;
Asciz	()Lscala/collection/mutable/HashMap;;
NameAndType	ports:Lscala/collection/mutable/HashMap;
Field	scala/actors/remote/TcpService$.ports:Lscala/collection/mutable/HashMap;
Asciz	()Lscala/collection/mutable/HashMap<Ljava/lang/Integer;Lscala/actors/remote/TcpService;>;;
Asciz	apply;
Asciz	(ILjava/lang/ClassLoader;)Lscala/actors/remote/TcpService;;
NameAndType	ports:()Lscala/collection/mutable/HashMap;
Method	scala/actors/remote/TcpService$.ports:()Lscala/collection/mutable/HashMap;
Asciz	scala/runtime/BoxesRunTime;
class	scala/runtime/BoxesRunTime
Asciz	boxToInteger;
Asciz	(I)Ljava/lang/Integer;;
NameAndType	boxToInteger:(I)Ljava/lang/Integer;
Method	scala/runtime/BoxesRunTime.boxToInteger:(I)Ljava/lang/Integer;
Asciz	scala/collection/mutable/HashMap;
class	scala/collection/mutable/HashMap
Asciz	get;
Asciz	(Ljava/lang/Object;)Lscala/Option;;
NameAndType	get:(Ljava/lang/Object;)Lscala/Option;
Method	scala/collection/mutable/HashMap.get:(Ljava/lang/Object;)Lscala/Option;
Asciz	scala/Some;
class	scala/Some
Asciz	x;
Asciz	()Ljava/lang/Object;;
NameAndType	x:()Ljava/lang/Object;
Method	scala/Some.x:()Ljava/lang/Object;
Asciz	scala/actors/remote/TcpService;
class	scala/actors/remote/TcpService
Asciz	scala/None$;
class	scala/None$
Asciz	Lscala/None$;;
NameAndType	MODULE$:Lscala/None$;
Field	scala/None$.MODULE$:Lscala/None$;
Asciz	java/lang/Object;
class	java/lang/Object
Asciz	equals;
Asciz	(Ljava/lang/Object;)Z;
NameAndType	equals:(Ljava/lang/Object;)Z
Method	java/lang/Object.equals:(Ljava/lang/Object;)Z
Asciz	(ILjava/lang/ClassLoader;)V;
NameAndType	"<init>":(ILjava/lang/ClassLoader;)V
Method	scala/actors/remote/TcpService."<init>":(ILjava/lang/ClassLoader;)V
Asciz	scala/Predef$Pair$;
class	scala/Predef$Pair$
Asciz	Lscala/Predef$Pair$;;
NameAndType	MODULE$:Lscala/Predef$Pair$;
Field	scala/Predef$Pair$.MODULE$:Lscala/Predef$Pair$;
Asciz	(Ljava/lang/Object;Ljava/lang/Object;)Lscala/Tuple2;;
NameAndType	apply:(Ljava/lang/Object;Ljava/lang/Object;)Lscala/Tuple2;
Method	scala/Predef$Pair$.apply:(Ljava/lang/Object;Ljava/lang/Object;)Lscala/Tuple2;
Asciz	$plus$eq;
Asciz	(Lscala/Tuple2;)Lscala/collection/mutable/HashMap;;
NameAndType	$plus$eq:(Lscala/Tuple2;)Lscala/collection/mutable/HashMap;
Method	scala/collection/mutable/HashMap.$plus$eq:(Lscala/Tuple2;)Lscala/collection/mutable/HashMap;
Asciz	start;
NameAndType	start:()V
Method	scala/actors/remote/TcpService.start:()V
Asciz	scala/actors/Debug$;
class	scala/actors/Debug$
Asciz	Lscala/actors/Debug$;;
NameAndType	MODULE$:Lscala/actors/Debug$;
Field	scala/actors/Debug$.MODULE$:Lscala/actors/Debug$;
Asciz	scala/collection/mutable/StringBuilder;
class	scala/collection/mutable/StringBuilder
Method	scala/collection/mutable/StringBuilder."<init>":()V
Asciz	created service at ;
String	created service at 
Asciz	append;
Asciz	(Ljava/lang/Object;)Lscala/collection/mutable/StringBuilder;;
NameAndType	append:(Ljava/lang/Object;)Lscala/collection/mutable/StringBuilder;
Method	scala/collection/mutable/StringBuilder.append:(Ljava/lang/Object;)Lscala/collection/mutable/StringBuilder;
Asciz	node;
Asciz	()Lscala/actors/remote/Node;;
NameAndType	node:()Lscala/actors/remote/Node;
Method	scala/actors/remote/TcpService.node:()Lscala/actors/remote/Node;
Asciz	toString;
Asciz	()Ljava/lang/String;;
NameAndType	toString:()Ljava/lang/String;
Method	scala/collection/mutable/StringBuilder.toString:()Ljava/lang/String;
Asciz	info;
Asciz	(Ljava/lang/String;)V;
NameAndType	info:(Ljava/lang/String;)V
Method	scala/actors/Debug$.info:(Ljava/lang/String;)V
Asciz	scala/MatchError;
class	scala/MatchError
Asciz	scala/Option;
class	scala/Option
Method	scala/Option.toString:()Ljava/lang/String;
NameAndType	"<init>":(Ljava/lang/String;)V
Method	scala/MatchError."<init>":(Ljava/lang/String;)V
Asciz	this;
Asciz	port;
Asciz	cl;
Asciz	Ljava/lang/ClassLoader;;
Asciz	service;
Asciz	Lscala/actors/remote/TcpService;;
Asciz	temp1;
Asciz	Lscala/Option;;
Asciz	LocalVariableTable;
Asciz	generatePort;
Asciz	()I;
int	8000;
NameAndType	random:()Lscala/util/Random;
Method	scala/actors/remote/TcpService$.random:()Lscala/util/Random;
int	500;
Asciz	scala/util/Random;
class	scala/util/Random
Asciz	nextInt;
Asciz	(I)I;
NameAndType	nextInt:(I)I
Method	scala/util/Random.nextInt:(I)I
Asciz	java/net/ServerSocket;
class	java/net/ServerSocket
Asciz	(I)V;
NameAndType	"<init>":(I)V
Method	java/net/ServerSocket."<init>":(I)V
Asciz	close;
NameAndType	close:()V
Method	java/net/ServerSocket.close:()V
NameAndType	generatePort:()I
Method	scala/actors/remote/TcpService$.generatePort:()I
Asciz	java/io/IOException;
class	java/io/IOException
Asciz	java/lang/SecurityException;
class	java/lang/SecurityException
Asciz	socket;
Asciz	Ljava/net/ServerSocket;;
Asciz	portnum;
NameAndType	BufSize:I
Field	scala/actors/remote/TcpService$.BufSize:I
Asciz	BufSize_$eq;
Method	java/lang/Object."<init>":()V
NameAndType	MODULE$:Lscala/actors/remote/TcpService$;
Field	scala/actors/remote/TcpService$.MODULE$:Lscala/actors/remote/TcpService$;
Method	scala/util/Random."<init>":()V
Method	scala/collection/mutable/HashMap."<init>":()V
int	65536;
Asciz	InnerClasses;
Asciz	scala/actors/remote/TcpService$$anonfun$run$1;
class	scala/actors/remote/TcpService$$anonfun$run$1
Asciz	$anonfun$run$1;
Asciz	scala/actors/remote/TcpService$$anonfun$liftedTree1$1$1;
class	scala/actors/remote/TcpService$$anonfun$liftedTree1$1$1
Asciz	$anonfun$liftedTree1$1$1;
Asciz	scala/ScalaObject;
class	scala/ScalaObject

{
public static final scala.actors.remote.TcpService$ MODULE$;
  Signature: Lscala/actors/remote/TcpService$;

private int BufSize;
  Signature: I

private final scala.collection.mutable.HashMap ports;
  Signature: Lscala/collection/mutable/HashMap;
  Signature: length = 0x2
   00 12 

private final scala.util.Random random;
  Signature: Lscala/util/Random;

public static {};
  Signature: ()V
  Code:
   Stack=1, Locals=0, Args_size=0
	new	class scala/actors/remote/TcpService$
	invokespecial	Method "<init>":()V
	return
  Labels:

private scala.util.Random random();
  Signature: ()Lscala/util/Random;
  Code:
   Stack=1, Locals=1, Args_size=1
	aload_0
	getfield	Field random:Lscala/util/Random;
	areturn
  Labels:

private scala.collection.mutable.HashMap ports();
  Signature: ()Lscala/collection/mutable/HashMap;
  Code:
   Stack=1, Locals=1, Args_size=1
	aload_0
	getfield	Field ports:Lscala/collection/mutable/HashMap;
	areturn
  Labels:
  Signature: length = 0x2
   00 1D 

public scala.actors.remote.TcpService apply(int, java.lang.ClassLoader);
  Signature: (ILjava/lang/ClassLoader;)Lscala/actors/remote/TcpService;
  Code:
   Stack=4, Locals=5, Args_size=3
	aload_0
	invokespecial	Method ports:()Lscala/collection/mutable/HashMap;
	iload_1
	invokestatic	Method scala/runtime/BoxesRunTime.boxToInteger:(I)Ljava/lang/Integer;
	invokevirtual	Method scala/collection/mutable/HashMap.get:(Ljava/lang/Object;)Lscala/Option;
	astore	4
	aload	4
	instanceof	class scala/Some
	ifeq	l1 // getstatic
	aload	4
	checkcast	class scala/Some
	invokevirtual	Method scala/Some.x:()Ljava/lang/Object;
	checkcast	class scala/actors/remote/TcpService
	goto	l2 // areturn
l1	getstatic	Field scala/None$.MODULE$:Lscala/None$;
	dup
	ifnonnull	l3 // aload
	pop
	aload	4
	ifnull	l4 // new
	goto	l5 // new
l3	aload	4
	invokevirtual	Method java/lang/Object.equals:(Ljava/lang/Object;)Z
	ifeq	l5 // new
l4	new	class scala/actors/remote/TcpService
	dup
	iload_1
	aload_2
	invokespecial	Method scala/actors/remote/TcpService."<init>":(ILjava/lang/ClassLoader;)V
	astore_3
	aload_0
	invokespecial	Method ports:()Lscala/collection/mutable/HashMap;
	getstatic	Field scala/Predef$Pair$.MODULE$:Lscala/Predef$Pair$;
	iload_1
	invokestatic	Method scala/runtime/BoxesRunTime.boxToInteger:(I)Ljava/lang/Integer;
	aload_3
	invokevirtual	Method scala/Predef$Pair$.apply:(Ljava/lang/Object;Ljava/lang/Object;)Lscala/Tuple2;
	invokevirtual	Method scala/collection/mutable/HashMap.$plus$eq:(Lscala/Tuple2;)Lscala/collection/mutable/HashMap;
	pop
	aload_3
	invokevirtual	Method scala/actors/remote/TcpService.start:()V
	getstatic	Field scala/actors/Debug$.MODULE$:Lscala/actors/Debug$;
	new	class scala/collection/mutable/StringBuilder
	dup
	invokespecial	Method scala/collection/mutable/StringBuilder."<init>":()V
	ldc	String created service at 
	invokevirtual	Method scala/collection/mutable/StringBuilder.append:(Ljava/lang/Object;)Lscala/collection/mutable/StringBuilder;
	aload_3
	invokevirtual	Method scala/actors/remote/TcpService.node:()Lscala/actors/remote/Node;
	invokevirtual	Method scala/collection/mutable/StringBuilder.append:(Ljava/lang/Object;)Lscala/collection/mutable/StringBuilder;
	invokevirtual	Method scala/collection/mutable/StringBuilder.toString:()Ljava/lang/String;
	invokevirtual	Method scala/actors/Debug$.info:(Ljava/lang/String;)V
	aload_3
l2	areturn
l5	new	class scala/MatchError
	dup
	aload	4
	invokevirtual	Method scala/Option.toString:()Ljava/lang/String;
	invokespecial	Method scala/MatchError."<init>":(Ljava/lang/String;)V
	athrow
  Labels:
   	l1 = 35 // getstatic
   	l3 = 51 // aload
   	l4 = 59 // new
   	l2 = 121 // areturn
   	l5 = 122 // new
  LocalVariableTable: 
   Start  Length  Slot  Name   Signature
   0      135      0    this       Lscala/actors/remote/TcpService$;
   0      135      1    port       I
   0      135      2    cl       Ljava/lang/ClassLoader;
   69      52      3    service       Lscala/actors/remote/TcpService;
   13      122      4    temp1       Lscala/Option;


public int generatePort();
  Signature: ()I
  Code:
   Stack=3, Locals=3, Args_size=1
	iconst_0
	istore_2
	ldc	int 8000
	aload_0
	invokespecial	Method random:()Lscala/util/Random;
	ldc	int 500
	invokevirtual	Method scala/util/Random.nextInt:(I)I
	iadd
	istore_2
	new	class java/net/ServerSocket
	dup
	iload_2
	invokespecial	Method java/net/ServerSocket."<init>":(I)V
	astore_1
	aload_1
	invokevirtual	Method java/net/ServerSocket.close:()V
	goto	l1 // iload_2
	pop
	goto	l1 // iload_2
	pop
	aload_0
	invokevirtual	Method generatePort:()I
	pop
l1	iload_2
	ireturn
  Labels:
   	l1 = 41 // iload_2
  Exception table:
   from   to  target type
     2    31    35   Class java/io/IOException

     2    31    31   Class java/lang/SecurityException

  LocalVariableTable: 
   Start  Length  Slot  Name   Signature
   0      43      0    this       Lscala/actors/remote/TcpService$;
   24      4      1    socket       Ljava/net/ServerSocket;
   2      40      2    portnum       I


public int BufSize();
  Signature: ()I
  Code:
   Stack=1, Locals=1, Args_size=1
	aload_0
	getfield	Field BufSize:I
	ireturn
  Labels:

public void BufSize_$eq(int);
  Signature: (I)V
  Code:
   Stack=2, Locals=2, Args_size=2
	aload_0
	iload_1
	putfield	Field BufSize:I
	return
  Labels:

private scala.actors.remote.TcpService$();
  Signature: ()V
  Code:
   Stack=3, Locals=1, Args_size=1
	aload_0
	invokespecial	Method java/lang/Object."<init>":()V
	aload_0
	putstatic	Field MODULE$:Lscala/actors/remote/TcpService$;
	aload_0
	new	class scala/util/Random
	dup
	invokespecial	Method scala/util/Random."<init>":()V
	putfield	Field random:Lscala/util/Random;
	aload_0
	new	class scala/collection/mutable/HashMap
	dup
	invokespecial	Method scala/collection/mutable/HashMap."<init>":()V
	putfield	Field ports:Lscala/collection/mutable/HashMap;
	aload_0
	ldc	int 65536
	putfield	Field BufSize:I
	return
  Labels:

}

