Compiled from "TcpService.scala"
public class scala.actors.remote.TcpService extends java.lang.Thread implements scala.actors.remote.Service,scala.ScalaObject
  SourceFile: "TcpService.scala"
  ScalaSig: length = 0x5E9
   05 00 FFFFFF81 4D 07 05 01 02 FFFFFF88 02 09 01 0A 54 63 70
   53 65 72 76 69 63 65 0A 02 03 04 01 06 72 65 6D
   6F 74 65 0A 02 05 06 01 06 61 63 74 6F 72 73 0A
   01 07 01 05 73 63 61 6C 61 03 00 10 02 0A 0B 0D
   01 02 06 08 0C 02 FFFFFF84 FFFFFF80 FFFFFF80 FFFFFF88 02 0D 02 0A 54 63
   70 53 65 72 76 69 63 65 13 03 0B 0E 16 10 02 0F
   14 0D 01 10 0A 02 11 12 01 04 6C 61 6E 67 0A 01
   13 01 04 6A 61 76 61 09 02 15 10 02 06 4F 62 6A
   65 63 74 10 02 17 18 0D 01 06 09 02 19 06 02 0B
   53 63 61 6C 61 4F 62 6A 65 63 74 08 05 1B 0B FFFFFF84
   00 1C 01 06 3C 69 6E 69 74 3E 14 01 09 08 07 1E
   0B FFFFFFC2 FFFFFF80 FFFFFF84 04 1F 01 06 72 61 6E 64 6F 6D 15 01
   20 10 02 21 24 0D 01 22 0A 02 23 06 01 04 75 74
   69 6C 09 02 25 22 02 06 52 61 6E 64 6F 6D 08 06
   27 0B FFFFFFA0 FFFFFF80 04 20 01 07 72 61 6E 64 6F 6D 20 08
   07 29 0B FFFFFFC2 FFFFFF80 FFFFFF84 04 2A 01 05 70 6F 72 74 73 15
   01 2B 10 04 2C 31 33 36 0D 01 2D 0A 02 2E 2F 01
   07 6D 75 74 61 62 6C 65 0A 02 30 06 01 0A 63 6F
   6C 6C 65 63 74 69 6F 6E 09 02 32 2D 02 07 48 61
   73 68 4D 61 70 10 02 17 34 09 02 35 06 02 03 49
   6E 74 10 02 0A 37 06 08 0C 02 FFFFFF84 FFFFFF80 FFFFFF80 FFFFFF80 00 38
   13 04 37 39 3C 16 10 02 0F 3A 09 02 3B 10 02 06
   54 68 72 65 61 64 10 02 0A 3D 09 02 3E 02 02 07
   53 65 72 76 69 63 65 08 08 40 37 FFFFFF82 FFFFFF80 FFFFFFA0 FFFFFF80 04
   33 01 04 70 6F 72 74 08 08 42 37 FFFFFF82 FFFFFF80 FFFFFFA0 FFFFFF80 04
   43 01 02 63 6C 10 02 0F 44 09 02 45 10 02 0B 43
   6C 61 73 73 4C 6F 61 64 65 72 08 05 1B 37 FFFFFF84 00
   47 14 03 36 48 49 08 05 40 46 FFFFFFC0 00 33 08 05 42
   46 FFFFFFC0 00 43 08 07 4B 37 FFFFFFC2 FFFFFF80 FFFFFF84 00 4C 01 0A 73
   65 72 69 61 6C 69 7A 65 72 15 01 4D 10 02 0A 4E
   09 02 4F 02 02 0E 4A 61 76 61 53 65 72 69 61 6C
   69 7A 65 72 08 06 51 37 FFFFFFA0 FFFFFF80 04 4D 01 0B 73 65
   72 69 61 6C 69 7A 65 72 20 08 07 53 37 FFFFFFC2 FFFFFF80 FFFFFF84
   04 54 01 0C 69 6E 74 65 72 6E 61 6C 4E 6F 64 65
   15 01 55 10 02 0A 56 09 02 57 02 02 04 4E 6F 64
   65 08 06 59 37 FFFFFFA0 FFFFFF80 04 55 01 0D 69 6E 74 65 72
   6E 61 6C 4E 6F 64 65 20 08 05 5B 37 FFFFFF84 00 54 01
   04 6E 6F 64 65 08 07 5D 37 FFFFFFC2 FFFFFF80 FFFFFF84 04 5E 01 0C
   70 65 6E 64 69 6E 67 53 65 6E 64 73 15 01 5F 10
   04 2C 31 55 60 10 03 61 69 6C 0E 02 62 67 0E 02
   63 66 0D 01 64 0A 02 65 08 01 06 3C 72 6F 6F 74
   3E 09 01 07 09 02 68 06 01 07 70 61 63 6B 61 67
   65 09 02 6A 6B 02 04 4C 69 73 74 0A 02 68 06 10
   03 17 6D 6F 09 02 6E 06 02 05 41 72 72 61 79 10
   02 17 70 09 02 71 06 02 04 42 79 74 65 08 06 73
   37 FFFFFFA0 FFFFFF80 04 5F 01 0D 70 65 6E 64 69 6E 67 53 65
   6E 64 73 20 08 05 75 37 FFFFFF84 00 76 01 04 73 65 6E
   64 14 03 77 7A 7B 10 02 17 78 09 02 79 06 02 04
   55 6E 69 74 08 05 5B 74 FFFFFFC0 00 55 08 05 7C 74 FFFFFFC0
   00 6C 01 04 64 61 74 61 08 05 7E 37 FFFFFF84 00 7F 01
   09 74 65 72 6D 69 6E 61 74 65 14 01 77 08 09 FFFFFF81
   01 37 FFFFFFC0 FFFFFF80 FFFFFF84 04 FFFFFF81 02 01 0F 73 68 6F 75 6C 64
   54 65 72 6D 69 6E 61 74 65 15 02 FFFFFF81 03 10 03 17
   FFFFFF81 04 09 03 FFFFFF81 05 06 02 07 42 6F 6F 6C 65 61 6E
   08 09 FFFFFF81 07 37 FFFFFFC0 FFFFFF80 FFFFFF84 04 FFFFFF81 08 01 13 73 68 6F
   75 6C 64 54 65 72 6D 69 6E 61 74 65 5F 24 65 71
   14 03 77 FFFFFF81 09 08 0A FFFFFF81 0A FFFFFF81 06 FFFFFF81 FFFFFF80 FFFFFFC0 00 FFFFFF81
   03 01 03 78 24 31 08 08 FFFFFF81 0C 37 FFFFFFA0 FFFFFFA0 04 FFFFFF81 03
   01 10 73 68 6F 75 6C 64 54 65 72 6D 69 6E 61 74
   65 20 08 06 FFFFFF81 0E 37 FFFFFF84 20 7F 01 03 72 75 6E 08
   09 FFFFFF81 10 37 FFFFFFC2 FFFFFF80 FFFFFF84 04 FFFFFF81 11 01 0B 63 6F 6E 6E
   65 63 74 69 6F 6E 73 15 02 FFFFFF81 12 10 05 2C 31 55
   FFFFFF81 13 10 03 0A FFFFFF81 14 09 03 FFFFFF81 15 02 02 10 54 63
   70 53 65 72 76 69 63 65 57 6F 72 6B 65 72 08 08
   FFFFFF81 17 37 FFFFFFA0 FFFFFF80 04 FFFFFF81 12 01 0C 63 6F 6E 6E 65 63
   74 69 6F 6E 73 20 08 08 FFFFFF81 19 37 FFFFFF84 00 04 FFFFFF81 1A
   01 0D 61 64 64 43 6F 6E 6E 65 63 74 69 6F 6E 14
   06 FFFFFF81 12 FFFFFF81 1B FFFFFF81 1C 08 06 5B FFFFFF81 18 FFFFFFC0 00 55 08
   08 FFFFFF81 1D FFFFFF81 18 FFFFFFC0 00 FFFFFF81 13 01 06 77 6F 72 6B 65
   72 08 07 FFFFFF81 1F 37 FFFFFF84 00 FFFFFF81 20 01 0D 67 65 74 43
   6F 6E 6E 65 63 74 69 6F 6E 14 04 FFFFFF81 21 FFFFFF81 24 10
   05 17 FFFFFF81 22 FFFFFF81 13 09 03 FFFFFF81 23 06 02 06 4F 70 74
   69 6F 6E 08 07 FFFFFF81 25 FFFFFF81 1E FFFFFFC0 00 55 01 01 6E 08
   07 FFFFFF81 27 37 FFFFFF84 00 FFFFFF81 28 01 0B 69 73 43 6F 6E 6E
   65 63 74 65 64 14 04 FFFFFF81 03 FFFFFF81 29 08 07 FFFFFF81 25 FFFFFF81
   26 FFFFFFC0 00 55 08 07 FFFFFF81 2B 37 FFFFFF84 00 FFFFFF81 2C 01 07 63
   6F 6E 6E 65 63 74 14 04 FFFFFF81 13 FFFFFF81 2D 08 07 FFFFFF81 25
   FFFFFF81 2A FFFFFFC0 00 55 08 07 FFFFFF81 2F 37 FFFFFF84 00 FFFFFF81 30 01 0E
   64 69 73 63 6F 6E 6E 65 63 74 4E 6F 64 65 14 03
   77 FFFFFF81 31 08 07 FFFFFF81 25 FFFFFF81 2E FFFFFFC0 00 55 08 07 FFFFFF81 33
   37 FFFFFF84 00 FFFFFF81 34 01 0B 69 73 52 65 61 63 68 61 62
   6C 65 14 04 FFFFFF81 03 FFFFFF81 35 08 06 5B FFFFFF81 32 FFFFFFC0 00 55
   08 07 FFFFFF81 37 37 FFFFFF84 00 FFFFFF81 38 01 08 6E 6F 64 65 44
   6F 77 6E 14 03 77 FFFFFF81 39 08 07 FFFFFF81 3A FFFFFF81 36 FFFFFFC0 00
   55 01 05 6D 6E 6F 64 65 08 07 FFFFFF81 3C 0B FFFFFFA0 FFFFFF80 04
   2B 01 06 70 6F 72 74 73 20 08 07 FFFFFF81 3E 0B FFFFFF84 00
   FFFFFF81 3F 01 05 61 70 70 6C 79 14 05 36 FFFFFF81 40 FFFFFF81 41
   08 06 40 FFFFFF81 3D FFFFFFC0 00 33 08 06 42 FFFFFF81 3D FFFFFFC0 00 43
   08 07 FFFFFF81 43 0B FFFFFF84 00 FFFFFF81 44 01 0C 67 65 6E 65 72
   61 74 65 50 6F 72 74 15 01 33 08 09 FFFFFF81 46 0B FFFFFFC0
   FFFFFF80 FFFFFF84 00 FFFFFF81 44 01 07 42 75 66 53 69 7A 65 08 09
   FFFFFF81 48 0B FFFFFFC0 FFFFFF80 FFFFFF84 00 FFFFFF81 49 01 0B 42 75 66 53 69
   7A 65 5F 24 65 71 14 03 77 FFFFFF81 4A 08 09 FFFFFF81 0A FFFFFF81
   47 FFFFFF81 FFFFFF80 FFFFFFC0 00 33 08 07 FFFFFF81 4C 0B FFFFFFA0 FFFFFFA0 04 33 01
   08 42 75 66 53 69 7A 65 20 
  InnerClass: 
   public final #420= #340 of #24; //$anonfun$run$1=class scala/actors/remote/TcpService$$anonfun$run$1 of class scala/actors/remote/TcpService
   public final #421= #351 of #24; //$anonfun$run$2=class scala/actors/remote/TcpService$$anonfun$run$2 of class scala/actors/remote/TcpService
   public final #422= #122 of #24; //$anonfun$liftedTree1$1$1=class scala/actors/remote/TcpService$$anonfun$liftedTree1$1$1 of class scala/actors/remote/TcpService
  minor version: 0
  major version: 49
  Constant pool:
const #1 = Asciz	SourceFile;
const #2 = Asciz	TcpService.scala;
const #3 = Asciz	kernel;
const #4 = Asciz	Lscala/actors/remote/NetKernel;;
const #5 = Asciz	connections;
const #6 = Asciz	Lscala/collection/mutable/HashMap;;
const #7 = Asciz	Lscala/collection/mutable/HashMap<Lscala/actors/remote/Node;Lscala/actors/remote/TcpServiceWorker;>;;
const #8 = Asciz	Signature;
const #9 = Asciz	shouldTerminate;
const #10 = Asciz	Z;
const #11 = Asciz	pendingSends;
const #12 = Asciz	Lscala/collection/mutable/HashMap<Lscala/actors/remote/Node;Lscala/collection/immutable/List<[B>;>;;
const #13 = Asciz	internalNode;
const #14 = Asciz	Lscala/actors/remote/Node;;
const #15 = Asciz	serializer;
const #16 = Asciz	Lscala/actors/remote/JavaSerializer;;
const #17 = Asciz	port;
const #18 = Asciz	I;
const #19 = Asciz	<init>;
const #20 = Asciz	(ILjava/lang/ClassLoader;)V;
const #21 = Asciz	Code;
const #22 = Asciz	LineNumberTable;
const #23 = Asciz	scala/actors/remote/TcpService;
const #24 = class	#23;	//  scala/actors/remote/TcpService
const #25 = NameAndType	#17:#18;//  port:I
const #26 = Field	#24.#25;	//  scala/actors/remote/TcpService.port:I
const #27 = Asciz	java/lang/Thread;
const #28 = class	#27;	//  java/lang/Thread
const #29 = Asciz	()V;
const #30 = NameAndType	#19:#29;//  "<init>":()V
const #31 = Method	#28.#30;	//  java/lang/Thread."<init>":()V
const #32 = Asciz	scala/actors/remote/Service$class;
const #33 = class	#32;	//  scala/actors/remote/Service$class
const #34 = Asciz	$init$;
const #35 = Asciz	(Lscala/actors/remote/Service;)V;
const #36 = NameAndType	#34:#35;//  $init$:(Lscala/actors/remote/Service;)V
const #37 = Method	#33.#36;	//  scala/actors/remote/Service$class.$init$:(Lscala/actors/remote/Service;)V
const #38 = Asciz	scala/actors/remote/JavaSerializer;
const #39 = class	#38;	//  scala/actors/remote/JavaSerializer
const #40 = Asciz	(Lscala/actors/remote/Service;Ljava/lang/ClassLoader;)V;
const #41 = NameAndType	#19:#40;//  "<init>":(Lscala/actors/remote/Service;Ljava/lang/ClassLoader;)V
const #42 = Method	#39.#41;	//  scala/actors/remote/JavaSerializer."<init>":(Lscala/actors/remote/Service;Ljava/lang/ClassLoader;)V
const #43 = NameAndType	#15:#16;//  serializer:Lscala/actors/remote/JavaSerializer;
const #44 = Field	#24.#43;	//  scala/actors/remote/TcpService.serializer:Lscala/actors/remote/JavaSerializer;
const #45 = Asciz	scala/actors/remote/Node;
const #46 = class	#45;	//  scala/actors/remote/Node
const #47 = Asciz	java/net/InetAddress;
const #48 = class	#47;	//  java/net/InetAddress
const #49 = Asciz	getLocalHost;
const #50 = Asciz	()Ljava/net/InetAddress;;
const #51 = NameAndType	#49:#50;//  getLocalHost:()Ljava/net/InetAddress;
const #52 = Method	#48.#51;	//  java/net/InetAddress.getLocalHost:()Ljava/net/InetAddress;
const #53 = Asciz	getHostAddress;
const #54 = Asciz	()Ljava/lang/String;;
const #55 = NameAndType	#53:#54;//  getHostAddress:()Ljava/lang/String;
const #56 = Method	#48.#55;	//  java/net/InetAddress.getHostAddress:()Ljava/lang/String;
const #57 = Asciz	(Ljava/lang/String;I)V;
const #58 = NameAndType	#19:#57;//  "<init>":(Ljava/lang/String;I)V
const #59 = Method	#46.#58;	//  scala/actors/remote/Node."<init>":(Ljava/lang/String;I)V
const #60 = NameAndType	#13:#14;//  internalNode:Lscala/actors/remote/Node;
const #61 = Field	#24.#60;	//  scala/actors/remote/TcpService.internalNode:Lscala/actors/remote/Node;
const #62 = Asciz	scala/collection/mutable/HashMap;
const #63 = class	#62;	//  scala/collection/mutable/HashMap
const #64 = Method	#63.#30;	//  scala/collection/mutable/HashMap."<init>":()V
const #65 = NameAndType	#11:#6;//  pendingSends:Lscala/collection/mutable/HashMap;
const #66 = Field	#24.#65;	//  scala/actors/remote/TcpService.pendingSends:Lscala/collection/mutable/HashMap;
const #67 = NameAndType	#9:#10;//  shouldTerminate:Z
const #68 = Field	#24.#67;	//  scala/actors/remote/TcpService.shouldTerminate:Z
const #69 = NameAndType	#5:#6;//  connections:Lscala/collection/mutable/HashMap;
const #70 = Field	#24.#69;	//  scala/actors/remote/TcpService.connections:Lscala/collection/mutable/HashMap;
const #71 = Asciz	this;
const #72 = Asciz	Lscala/actors/remote/TcpService;;
const #73 = Asciz	cl;
const #74 = Asciz	Ljava/lang/ClassLoader;;
const #75 = Asciz	LocalVariableTable;
const #76 = Asciz	liftedTree1$1;
const #77 = Asciz	(Lscala/actors/remote/Node;[B)Ljava/lang/Object;;
const #78 = Asciz	connect;
const #79 = Asciz	(Lscala/actors/remote/Node;)Lscala/actors/remote/TcpServiceWorker;;
const #80 = NameAndType	#78:#79;//  connect:(Lscala/actors/remote/Node;)Lscala/actors/remote/TcpServiceWorker;
const #81 = Method	#24.#80;	//  scala/actors/remote/TcpService.connect:(Lscala/actors/remote/Node;)Lscala/actors/remote/TcpServiceWorker;
const #82 = Asciz	scala/actors/remote/TcpServiceWorker;
const #83 = class	#82;	//  scala/actors/remote/TcpServiceWorker
const #84 = Asciz	transmit;
const #85 = Asciz	([B)V;
const #86 = NameAndType	#84:#85;//  transmit:([B)V
const #87 = Method	#83.#86;	//  scala/actors/remote/TcpServiceWorker.transmit:([B)V
const #88 = Asciz	()Lscala/collection/mutable/HashMap;;
const #89 = NameAndType	#11:#88;//  pendingSends:()Lscala/collection/mutable/HashMap;
const #90 = Method	#24.#89;	//  scala/actors/remote/TcpService.pendingSends:()Lscala/collection/mutable/HashMap;
const #91 = Asciz	get;
const #92 = Asciz	(Ljava/lang/Object;)Lscala/Option;;
const #93 = NameAndType	#91:#92;//  get:(Ljava/lang/Object;)Lscala/Option;
const #94 = Method	#63.#93;	//  scala/collection/mutable/HashMap.get:(Ljava/lang/Object;)Lscala/Option;
const #95 = Asciz	scala/None$;
const #96 = class	#95;	//  scala/None$
const #97 = Asciz	MODULE$;
const #98 = Asciz	Lscala/None$;;
const #99 = NameAndType	#97:#98;//  MODULE$:Lscala/None$;
const #100 = Field	#96.#99;	//  scala/None$.MODULE$:Lscala/None$;
const #101 = Asciz	java/lang/Object;
const #102 = class	#101;	//  java/lang/Object
const #103 = Asciz	equals;
const #104 = Asciz	(Ljava/lang/Object;)Z;
const #105 = NameAndType	#103:#104;//  equals:(Ljava/lang/Object;)Z
const #106 = Method	#102.#105;	//  java/lang/Object.equals:(Ljava/lang/Object;)Z
const #107 = Asciz	scala/runtime/BoxedUnit;
const #108 = class	#107;	//  scala/runtime/BoxedUnit
const #109 = Asciz	UNIT;
const #110 = Asciz	Lscala/runtime/BoxedUnit;;
const #111 = NameAndType	#109:#110;//  UNIT:Lscala/runtime/BoxedUnit;
const #112 = Field	#108.#111;	//  scala/runtime/BoxedUnit.UNIT:Lscala/runtime/BoxedUnit;
const #113 = Asciz	scala/Some;
const #114 = class	#113;	//  scala/Some
const #115 = Asciz	x;
const #116 = Asciz	()Ljava/lang/Object;;
const #117 = NameAndType	#115:#116;//  x:()Ljava/lang/Object;
const #118 = Method	#114.#117;	//  scala/Some.x:()Ljava/lang/Object;
const #119 = Asciz	scala/collection/immutable/List;
const #120 = class	#119;	//  scala/collection/immutable/List
const #121 = Asciz	scala/actors/remote/TcpService$$anonfun$liftedTree1$1$1;
const #122 = class	#121;	//  scala/actors/remote/TcpService$$anonfun$liftedTree1$1$1
const #123 = Asciz	(Lscala/actors/remote/TcpService;Lscala/actors/remote/TcpServiceWorker;)V;
const #124 = NameAndType	#19:#123;//  "<init>":(Lscala/actors/remote/TcpService;Lscala/actors/remote/TcpServiceWorker;)V
const #125 = Method	#122.#124;	//  scala/actors/remote/TcpService$$anonfun$liftedTree1$1$1."<init>":(Lscala/actors/remote/TcpService;Lscala/actors/remote/TcpServiceWorker;)V
const #126 = Asciz	scala/collection/generic/LinearSequenceTemplate;
const #127 = class	#126;	//  scala/collection/generic/LinearSequenceTemplate
const #128 = Asciz	foreach;
const #129 = Asciz	(Lscala/Function1;)V;
const #130 = NameAndType	#128:#129;//  foreach:(Lscala/Function1;)V
const #131 = InterfaceMethod	#127.#130;	//  scala/collection/generic/LinearSequenceTemplate.foreach:(Lscala/Function1;)V
const #132 = Asciz	$minus$eq;
const #133 = Asciz	(Ljava/lang/Object;)Lscala/collection/mutable/HashMap;;
const #134 = NameAndType	#132:#133;//  $minus$eq:(Ljava/lang/Object;)Lscala/collection/mutable/HashMap;
const #135 = Method	#63.#134;	//  scala/collection/mutable/HashMap.$minus$eq:(Ljava/lang/Object;)Lscala/collection/mutable/HashMap;
const #136 = Asciz	scala/MatchError;
const #137 = class	#136;	//  scala/MatchError
const #138 = Asciz	scala/Option;
const #139 = class	#138;	//  scala/Option
const #140 = Asciz	toString;
const #141 = NameAndType	#140:#54;//  toString:()Ljava/lang/String;
const #142 = Method	#139.#141;	//  scala/Option.toString:()Ljava/lang/String;
const #143 = Asciz	(Ljava/lang/String;)V;
const #144 = NameAndType	#19:#143;//  "<init>":(Ljava/lang/String;)V
const #145 = Method	#137.#144;	//  scala/MatchError."<init>":(Ljava/lang/String;)V
const #146 = Asciz	bufferMsg$1;
const #147 = Asciz	(Ljava/lang/Throwable;Lscala/actors/remote/Node;[B)V;
const #148 = NameAndType	#146:#147;//  bufferMsg$1:(Ljava/lang/Throwable;Lscala/actors/remote/Node;[B)V
const #149 = Method	#24.#148;	//  scala/actors/remote/TcpService.bufferMsg$1:(Ljava/lang/Throwable;Lscala/actors/remote/Node;[B)V
const #150 = Asciz	java/net/UnknownHostException;
const #151 = class	#150;	//  java/net/UnknownHostException
const #152 = Asciz	java/io/IOException;
const #153 = class	#152;	//  java/io/IOException
const #154 = Asciz	java/lang/SecurityException;
const #155 = class	#154;	//  java/lang/SecurityException
const #156 = Asciz	exceptionResult3;
const #157 = Asciz	Ljava/lang/Object;;
const #158 = Asciz	newWorker$1;
const #159 = Asciz	Lscala/actors/remote/TcpServiceWorker;;
const #160 = Asciz	temp9;
const #161 = Asciz	Lscala/Option;;
const #162 = Asciz	temp11;
const #163 = Asciz	Lscala/Some;;
const #164 = Asciz	temp12;
const #165 = Asciz	Lscala/collection/immutable/List;;
const #166 = Asciz	scala/Predef$Pair$;
const #167 = class	#166;	//  scala/Predef$Pair$
const #168 = Asciz	Lscala/Predef$Pair$;;
const #169 = NameAndType	#97:#168;//  MODULE$:Lscala/Predef$Pair$;
const #170 = Field	#167.#169;	//  scala/Predef$Pair$.MODULE$:Lscala/Predef$Pair$;
const #171 = Asciz	scala/collection/immutable/List$;
const #172 = class	#171;	//  scala/collection/immutable/List$
const #173 = Asciz	Lscala/collection/immutable/List$;;
const #174 = NameAndType	#97:#173;//  MODULE$:Lscala/collection/immutable/List$;
const #175 = Field	#172.#174;	//  scala/collection/immutable/List$.MODULE$:Lscala/collection/immutable/List$;
const #176 = Asciz	scala/runtime/ScalaRunTime$;
const #177 = class	#176;	//  scala/runtime/ScalaRunTime$
const #178 = Asciz	Lscala/runtime/ScalaRunTime$;;
const #179 = NameAndType	#97:#178;//  MODULE$:Lscala/runtime/ScalaRunTime$;
const #180 = Field	#177.#179;	//  scala/runtime/ScalaRunTime$.MODULE$:Lscala/runtime/ScalaRunTime$;
const #181 = Asciz	[B;
const #182 = class	#181;	//  "[B"
const #183 = Asciz	boxArray;
const #184 = Asciz	(Ljava/lang/Object;)Lscala/runtime/BoxedArray;;
const #185 = NameAndType	#183:#184;//  boxArray:(Ljava/lang/Object;)Lscala/runtime/BoxedArray;
const #186 = Method	#177.#185;	//  scala/runtime/ScalaRunTime$.boxArray:(Ljava/lang/Object;)Lscala/runtime/BoxedArray;
const #187 = Asciz	apply;
const #188 = Asciz	(Lscala/collection/Sequence;)Lscala/collection/immutable/List;;
const #189 = NameAndType	#187:#188;//  apply:(Lscala/collection/Sequence;)Lscala/collection/immutable/List;
const #190 = Method	#172.#189;	//  scala/collection/immutable/List$.apply:(Lscala/collection/Sequence;)Lscala/collection/immutable/List;
const #191 = Asciz	(Ljava/lang/Object;Ljava/lang/Object;)Lscala/Tuple2;;
const #192 = NameAndType	#187:#191;//  apply:(Ljava/lang/Object;Ljava/lang/Object;)Lscala/Tuple2;
const #193 = Method	#167.#192;	//  scala/Predef$Pair$.apply:(Ljava/lang/Object;Ljava/lang/Object;)Lscala/Tuple2;
const #194 = Asciz	$plus$eq;
const #195 = Asciz	(Lscala/Tuple2;)Lscala/collection/mutable/HashMap;;
const #196 = NameAndType	#194:#195;//  $plus$eq:(Lscala/Tuple2;)Lscala/collection/mutable/HashMap;
const #197 = Method	#63.#196;	//  scala/collection/mutable/HashMap.$plus$eq:(Lscala/Tuple2;)Lscala/collection/mutable/HashMap;
const #198 = Asciz	gd1$1;
const #199 = Asciz	(Lscala/collection/immutable/List;)Z;
const #200 = NameAndType	#198:#199;//  gd1$1:(Lscala/collection/immutable/List;)Z
const #201 = Method	#24.#200;	//  scala/actors/remote/TcpService.gd1$1:(Lscala/collection/immutable/List;)Z
const #202 = Asciz	$colon$colon;
const #203 = Asciz	(Ljava/lang/Object;)Lscala/collection/immutable/List;;
const #204 = NameAndType	#202:#203;//  $colon$colon:(Ljava/lang/Object;)Lscala/collection/immutable/List;
const #205 = Method	#120.#204;	//  scala/collection/immutable/List.$colon$colon:(Ljava/lang/Object;)Lscala/collection/immutable/List;
const #206 = Asciz	t;
const #207 = Asciz	Ljava/lang/Throwable;;
const #208 = Asciz	temp5;
const #209 = Asciz	temp7;
const #210 = Asciz	temp8;
const #211 = Asciz	msgs;
const #212 = Asciz	length;
const #213 = Asciz	()I;
const #214 = NameAndType	#212:#213;//  length:()I
const #215 = InterfaceMethod	#127.#214;	//  scala/collection/generic/LinearSequenceTemplate.length:()I
const #216 = Asciz	scala/actors/remote/TcpService$;
const #217 = class	#216;	//  scala/actors/remote/TcpService$
const #218 = Asciz	Lscala/actors/remote/TcpService$;;
const #219 = NameAndType	#97:#218;//  MODULE$:Lscala/actors/remote/TcpService$;
const #220 = Field	#217.#219;	//  scala/actors/remote/TcpService$.MODULE$:Lscala/actors/remote/TcpService$;
const #221 = Asciz	BufSize;
const #222 = NameAndType	#221:#213;//  BufSize:()I
const #223 = Method	#217.#222;	//  scala/actors/remote/TcpService$.BufSize:()I
const #224 = Asciz	()Lscala/actors/remote/Serializer;;
const #225 = Asciz	()Lscala/actors/remote/JavaSerializer;;
const #226 = NameAndType	#15:#225;//  serializer:()Lscala/actors/remote/JavaSerializer;
const #227 = Method	#24.#226;	//  scala/actors/remote/TcpService.serializer:()Lscala/actors/remote/JavaSerializer;
const #228 = Asciz	nodeDown;
const #229 = Asciz	(Lscala/actors/remote/Node;)V;
const #230 = NameAndType	#5:#88;//  connections:()Lscala/collection/mutable/HashMap;
const #231 = Method	#24.#230;	//  scala/actors/remote/TcpService.connections:()Lscala/collection/mutable/HashMap;
const #232 = Asciz	mnode;
const #233 = Asciz	isReachable;
const #234 = Asciz	(Lscala/actors/remote/Node;)Z;
const #235 = Asciz	isConnected;
const #236 = NameAndType	#235:#234;//  isConnected:(Lscala/actors/remote/Node;)Z
const #237 = Method	#24.#236;	//  scala/actors/remote/TcpService.isConnected:(Lscala/actors/remote/Node;)Z
const #238 = Asciz	node;
const #239 = Asciz	exceptionResult2;
const #240 = Asciz	disconnectNode;
const #241 = Asciz	halt;
const #242 = NameAndType	#241:#29;//  halt:()V
const #243 = Method	#83.#242;	//  scala/actors/remote/TcpServiceWorker.halt:()V
const #244 = Asciz	n;
const #245 = Asciz	temp17;
const #246 = Asciz	temp19;
const #247 = Asciz	temp20;
const #248 = Asciz	java/net/Socket;
const #249 = class	#248;	//  java/net/Socket
const #250 = Asciz	address;
const #251 = NameAndType	#250:#54;//  address:()Ljava/lang/String;
const #252 = Method	#46.#251;	//  scala/actors/remote/Node.address:()Ljava/lang/String;
const #253 = NameAndType	#17:#213;//  port:()I
const #254 = Method	#46.#253;	//  scala/actors/remote/Node.port:()I
const #255 = Method	#249.#58;	//  java/net/Socket."<init>":(Ljava/lang/String;I)V
const #256 = Asciz	(Lscala/actors/remote/TcpService;Ljava/net/Socket;)V;
const #257 = NameAndType	#19:#256;//  "<init>":(Lscala/actors/remote/TcpService;Ljava/net/Socket;)V
const #258 = Method	#83.#257;	//  scala/actors/remote/TcpServiceWorker."<init>":(Lscala/actors/remote/TcpService;Ljava/net/Socket;)V
const #259 = Asciz	sendNode;
const #260 = NameAndType	#259:#229;//  sendNode:(Lscala/actors/remote/Node;)V
const #261 = Method	#83.#260;	//  scala/actors/remote/TcpServiceWorker.sendNode:(Lscala/actors/remote/Node;)V
const #262 = Asciz	start;
const #263 = NameAndType	#262:#29;//  start:()V
const #264 = Method	#83.#263;	//  scala/actors/remote/TcpServiceWorker.start:()V
const #265 = Asciz	addConnection;
const #266 = Asciz	(Lscala/actors/remote/Node;Lscala/actors/remote/TcpServiceWorker;)Lscala/collection/mutable/HashMap;;
const #267 = NameAndType	#265:#266;//  addConnection:(Lscala/actors/remote/Node;Lscala/actors/remote/TcpServiceWorker;)Lscala/collection/mutable/HashMap;
const #268 = Method	#24.#267;	//  scala/actors/remote/TcpService.addConnection:(Lscala/actors/remote/Node;Lscala/actors/remote/TcpServiceWorker;)Lscala/collection/mutable/HashMap;
const #269 = Asciz	socket;
const #270 = Asciz	Ljava/net/Socket;;
const #271 = Asciz	worker;
const #272 = Asciz	isEmpty;
const #273 = Asciz	()Z;
const #274 = NameAndType	#272:#273;//  isEmpty:()Z
const #275 = Method	#139.#274;	//  scala/Option.isEmpty:()Z
const #276 = Asciz	scala/runtime/BoxesRunTime;
const #277 = class	#276;	//  scala/runtime/BoxesRunTime
const #278 = Asciz	boxToBoolean;
const #279 = Asciz	(Z)Ljava/lang/Boolean;;
const #280 = NameAndType	#278:#279;//  boxToBoolean:(Z)Ljava/lang/Boolean;
const #281 = Method	#277.#280;	//  scala/runtime/BoxesRunTime.boxToBoolean:(Z)Ljava/lang/Boolean;
const #282 = Asciz	unboxToBoolean;
const #283 = NameAndType	#282:#104;//  unboxToBoolean:(Ljava/lang/Object;)Z
const #284 = Method	#277.#283;	//  scala/runtime/BoxesRunTime.unboxToBoolean:(Ljava/lang/Object;)Z
const #285 = Asciz	getConnection;
const #286 = Asciz	(Lscala/actors/remote/Node;)Lscala/Option;;
const #287 = Asciz	(Lscala/actors/remote/Node;)Lscala/Option<Lscala/actors/remote/TcpServiceWorker;>;;
const #288 = Asciz	(Lscala/actors/remote/Node;Lscala/actors/remote/TcpServiceWorker;)Lscala/collection/mutable/HashMap<Lscala/actors/remote/Node;Lscala/actors/remote/TcpServiceWorker;>;;
const #289 = Asciz	()Lscala/collection/mutable/HashMap<Lscala/actors/remote/Node;Lscala/actors/remote/TcpServiceWorker;>;;
const #290 = Asciz	run;
const #291 = Asciz	java/net/ServerSocket;
const #292 = class	#291;	//  java/net/ServerSocket
const #293 = Asciz	(I)V;
const #294 = NameAndType	#19:#293;//  "<init>":(I)V
const #295 = Method	#292.#294;	//  java/net/ServerSocket."<init>":(I)V
const #296 = NameAndType	#9:#273;//  shouldTerminate:()Z
const #297 = Method	#24.#296;	//  scala/actors/remote/TcpService.shouldTerminate:()Z
const #298 = Asciz	scala/actors/Debug$;
const #299 = class	#298;	//  scala/actors/Debug$
const #300 = Asciz	Lscala/actors/Debug$;;
const #301 = NameAndType	#97:#300;//  MODULE$:Lscala/actors/Debug$;
const #302 = Field	#299.#301;	//  scala/actors/Debug$.MODULE$:Lscala/actors/Debug$;
const #303 = Asciz	scala/Predef$;
const #304 = class	#303;	//  scala/Predef$
const #305 = Asciz	Lscala/Predef$;;
const #306 = NameAndType	#97:#305;//  MODULE$:Lscala/Predef$;
const #307 = Field	#304.#306;	//  scala/Predef$.MODULE$:Lscala/Predef$;
const #308 = Asciz	any2stringadd;
const #309 = Asciz	(Ljava/lang/Object;)Lscala/runtime/StringAdd;;
const #310 = NameAndType	#308:#309;//  any2stringadd:(Ljava/lang/Object;)Lscala/runtime/StringAdd;
const #311 = Method	#304.#310;	//  scala/Predef$.any2stringadd:(Ljava/lang/Object;)Lscala/runtime/StringAdd;
const #312 = Asciz	: shutting down...;
const #313 = String	#312;	//  : shutting down...
const #314 = Asciz	scala/runtime/StringAdd;
const #315 = class	#314;	//  scala/runtime/StringAdd
const #316 = Asciz	$plus;
const #317 = Asciz	(Ljava/lang/String;)Ljava/lang/String;;
const #318 = NameAndType	#316:#317;//  $plus:(Ljava/lang/String;)Ljava/lang/String;
const #319 = Method	#315.#318;	//  scala/runtime/StringAdd.$plus:(Ljava/lang/String;)Ljava/lang/String;
const #320 = Asciz	info;
const #321 = NameAndType	#320:#143;//  info:(Ljava/lang/String;)V
const #322 = Method	#299.#321;	//  scala/actors/Debug$.info:(Ljava/lang/String;)V
const #323 = Asciz	scala/runtime/ObjectRef;
const #324 = class	#323;	//  scala/runtime/ObjectRef
const #325 = Asciz	scala/collection/immutable/Nil$;
const #326 = class	#325;	//  scala/collection/immutable/Nil$
const #327 = Asciz	Lscala/collection/immutable/Nil$;;
const #328 = NameAndType	#97:#327;//  MODULE$:Lscala/collection/immutable/Nil$;
const #329 = Field	#326.#328;	//  scala/collection/immutable/Nil$.MODULE$:Lscala/collection/immutable/Nil$;
const #330 = Asciz	(Ljava/lang/Object;)V;
const #331 = NameAndType	#19:#330;//  "<init>":(Ljava/lang/Object;)V
const #332 = Method	#324.#331;	//  scala/runtime/ObjectRef."<init>":(Ljava/lang/Object;)V
const #333 = Asciz	scala/collection/generic/MapTemplate;
const #334 = class	#333;	//  scala/collection/generic/MapTemplate
const #335 = Asciz	values;
const #336 = Asciz	()Lscala/collection/Iterator;;
const #337 = NameAndType	#335:#336;//  values:()Lscala/collection/Iterator;
const #338 = InterfaceMethod	#334.#337;	//  scala/collection/generic/MapTemplate.values:()Lscala/collection/Iterator;
const #339 = Asciz	scala/actors/remote/TcpService$$anonfun$run$1;
const #340 = class	#339;	//  scala/actors/remote/TcpService$$anonfun$run$1
const #341 = Asciz	(Lscala/actors/remote/TcpService;Lscala/runtime/ObjectRef;)V;
const #342 = NameAndType	#19:#341;//  "<init>":(Lscala/actors/remote/TcpService;Lscala/runtime/ObjectRef;)V
const #343 = Method	#340.#342;	//  scala/actors/remote/TcpService$$anonfun$run$1."<init>":(Lscala/actors/remote/TcpService;Lscala/runtime/ObjectRef;)V
const #344 = Asciz	scala/collection/Iterator;
const #345 = class	#344;	//  scala/collection/Iterator
const #346 = InterfaceMethod	#345.#130;	//  scala/collection/Iterator.foreach:(Lscala/Function1;)V
const #347 = Asciz	elem;
const #348 = NameAndType	#347:#157;//  elem:Ljava/lang/Object;
const #349 = Field	#324.#348;	//  scala/runtime/ObjectRef.elem:Ljava/lang/Object;
const #350 = Asciz	scala/actors/remote/TcpService$$anonfun$run$2;
const #351 = class	#350;	//  scala/actors/remote/TcpService$$anonfun$run$2
const #352 = Asciz	(Lscala/actors/remote/TcpService;)V;
const #353 = NameAndType	#19:#352;//  "<init>":(Lscala/actors/remote/TcpService;)V
const #354 = Method	#351.#353;	//  scala/actors/remote/TcpService$$anonfun$run$2."<init>":(Lscala/actors/remote/TcpService;)V
const #355 = Asciz	scala/collection/mutable/StringBuilder;
const #356 = class	#355;	//  scala/collection/mutable/StringBuilder
const #357 = Method	#356.#30;	//  scala/collection/mutable/StringBuilder."<init>":()V
const #358 = Asciz	: waiting for new connection on port ;
const #359 = String	#358;	//  : waiting for new connection on port 
const #360 = Asciz	append;
const #361 = Asciz	(Ljava/lang/Object;)Lscala/collection/mutable/StringBuilder;;
const #362 = NameAndType	#360:#361;//  append:(Ljava/lang/Object;)Lscala/collection/mutable/StringBuilder;
const #363 = Method	#356.#362;	//  scala/collection/mutable/StringBuilder.append:(Ljava/lang/Object;)Lscala/collection/mutable/StringBuilder;
const #364 = Asciz	boxToInteger;
const #365 = Asciz	(I)Ljava/lang/Integer;;
const #366 = NameAndType	#364:#365;//  boxToInteger:(I)Ljava/lang/Integer;
const #367 = Method	#277.#366;	//  scala/runtime/BoxesRunTime.boxToInteger:(I)Ljava/lang/Integer;
const #368 = Asciz	...;
const #369 = String	#368;	//  ...
const #370 = Method	#356.#141;	//  scala/collection/mutable/StringBuilder.toString:()Ljava/lang/String;
const #371 = Asciz	accept;
const #372 = Asciz	()Ljava/net/Socket;;
const #373 = NameAndType	#371:#372;//  accept:()Ljava/net/Socket;
const #374 = Method	#292.#373;	//  java/net/ServerSocket.accept:()Ljava/net/Socket;
const #375 = Asciz	close;
const #376 = NameAndType	#375:#29;//  close:()V
const #377 = Method	#249.#376;	//  java/net/Socket.close:()V
const #378 = Asciz	Started new ;
const #379 = String	#378;	//  Started new 
const #380 = Asciz	readNode;
const #381 = NameAndType	#380:#29;//  readNode:()V
const #382 = Method	#83.#381;	//  scala/actors/remote/TcpServiceWorker.readNode:()V
const #383 = Asciz	: caught ;
const #384 = String	#383;	//  : caught 
const #385 = Asciz	java/lang/Exception;
const #386 = class	#385;	//  java/lang/Exception
const #387 = Asciz	workers$1;
const #388 = Asciz	Lscala/runtime/ObjectRef;;
const #389 = Asciz	Ljava/net/ServerSocket;;
const #390 = Asciz	nextClient;
const #391 = Asciz	shouldTerminate_$eq;
const #392 = Asciz	(Z)V;
const #393 = Asciz	terminate;
const #394 = NameAndType	#391:#392;//  shouldTerminate_$eq:(Z)V
const #395 = Method	#24.#394;	//  scala/actors/remote/TcpService.shouldTerminate_$eq:(Z)V
const #396 = Asciz	()Lscala/actors/remote/Node;;
const #397 = NameAndType	#13:#396;//  internalNode:()Lscala/actors/remote/Node;
const #398 = Method	#24.#397;	//  scala/actors/remote/TcpService.internalNode:()Lscala/actors/remote/Node;
const #399 = Asciz	java/net/ConnectException;
const #400 = class	#399;	//  java/net/ConnectException
const #401 = Asciz	send;
const #402 = Asciz	(Lscala/actors/remote/Node;[B)V;
const #403 = NameAndType	#285:#286;//  getConnection:(Lscala/actors/remote/Node;)Lscala/Option;
const #404 = Method	#24.#403;	//  scala/actors/remote/TcpService.getConnection:(Lscala/actors/remote/Node;)Lscala/Option;
const #405 = NameAndType	#76:#77;//  liftedTree1$1:(Lscala/actors/remote/Node;[B)Ljava/lang/Object;
const #406 = Method	#24.#405;	//  scala/actors/remote/TcpService.liftedTree1$1:(Lscala/actors/remote/Node;[B)Ljava/lang/Object;
const #407 = Asciz	node$1;
const #408 = Asciz	data$1;
const #409 = Asciz	temp13;
const #410 = Asciz	temp15;
const #411 = Asciz	temp16;
const #412 = Asciz	()Lscala/collection/mutable/HashMap<Lscala/actors/remote/Node;Lscala/collection/immutable/List<[B>;>;;
const #413 = Asciz	scala$actors$remote$Service$_setter_$kernel_$eq;
const #414 = Asciz	(Lscala/actors/remote/NetKernel;)V;
const #415 = NameAndType	#3:#4;//  kernel:Lscala/actors/remote/NetKernel;
const #416 = Field	#24.#415;	//  scala/actors/remote/TcpService.kernel:Lscala/actors/remote/NetKernel;
const #417 = Asciz	()Lscala/actors/remote/NetKernel;;
const #418 = Asciz	ScalaSig;
const #419 = Asciz	InnerClasses;
const #420 = Asciz	$anonfun$run$1;
const #421 = Asciz	$anonfun$run$2;
const #422 = Asciz	$anonfun$liftedTree1$1$1;
const #423 = Asciz	scala/actors/remote/Service;
const #424 = class	#423;	//  scala/actors/remote/Service
const #425 = Asciz	scala/ScalaObject;
const #426 = class	#425;	//  scala/ScalaObject

{
public scala.actors.remote.TcpService(int, java.lang.ClassLoader);
  Code:
   Stack=5, Locals=3, Args_size=3
   0:	aload_0
   1:	iload_1
   2:	putfield	#26; //Field port:I
   5:	aload_0
   6:	invokespecial	#31; //Method java/lang/Thread."<init>":()V
   9:	aload_0
   10:	invokestatic	#37; //Method scala/actors/remote/Service$class.$init$:(Lscala/actors/remote/Service;)V
   13:	aload_0
   14:	new	#39; //class scala/actors/remote/JavaSerializer
   17:	dup
   18:	aload_0
   19:	aload_2
   20:	invokespecial	#42; //Method scala/actors/remote/JavaSerializer."<init>":(Lscala/actors/remote/Service;Ljava/lang/ClassLoader;)V
   23:	putfield	#44; //Field serializer:Lscala/actors/remote/JavaSerializer;
   26:	aload_0
   27:	new	#46; //class scala/actors/remote/Node
   30:	dup
   31:	invokestatic	#52; //Method java/net/InetAddress.getLocalHost:()Ljava/net/InetAddress;
   34:	invokevirtual	#56; //Method java/net/InetAddress.getHostAddress:()Ljava/lang/String;
   37:	iload_1
   38:	invokespecial	#59; //Method scala/actors/remote/Node."<init>":(Ljava/lang/String;I)V
   41:	putfield	#61; //Field internalNode:Lscala/actors/remote/Node;
   44:	aload_0
   45:	new	#63; //class scala/collection/mutable/HashMap
   48:	dup
   49:	invokespecial	#64; //Method scala/collection/mutable/HashMap."<init>":()V
   52:	putfield	#66; //Field pendingSends:Lscala/collection/mutable/HashMap;
   55:	aload_0
   56:	iconst_0
   57:	putfield	#68; //Field shouldTerminate:Z
   60:	aload_0
   61:	new	#63; //class scala/collection/mutable/HashMap
   64:	dup
   65:	invokespecial	#64; //Method scala/collection/mutable/HashMap."<init>":()V
   68:	putfield	#70; //Field connections:Lscala/collection/mutable/HashMap;
   71:	return
  LineNumberTable: 
   line 71: 0
   line 72: 13
   line 74: 26
   line 77: 44
   line 136: 55
   line 170: 60
   line 171: 61
   line 170: 68

  LocalVariableTable: 
   Start  Length  Slot  Name   Signature
   0      72      0    this       Lscala/actors/remote/TcpService;
   0      72      1    port       I
   0      72      2    cl       Ljava/lang/ClassLoader;


public scala.actors.remote.Serializer serializer();
  Code:
   Stack=1, Locals=1, Args_size=1
   0:	aload_0
   1:	invokevirtual	#227; //Method serializer:()Lscala/actors/remote/JavaSerializer;
   4:	areturn
  LineNumberTable: 
   line 71: 0


public void nodeDown(scala.actors.remote.Node);
  Code:
   Stack=2, Locals=3, Args_size=2
   0:	aload_0
   1:	dup
   2:	astore_2
   3:	monitorenter
   4:	aload_0
   5:	invokespecial	#231; //Method connections:()Lscala/collection/mutable/HashMap;
   8:	aload_1
   9:	invokevirtual	#135; //Method scala/collection/mutable/HashMap.$minus$eq:(Ljava/lang/Object;)Lscala/collection/mutable/HashMap;
   12:	pop
   13:	aload_2
   14:	monitorexit
   15:	return
   16:	aload_2
   17:	monitorexit
   18:	athrow
  Exception table:
   from   to  target type
     4    15    16   any
  LineNumberTable: 
   line 215: 0
   line 216: 4
   line 215: 14

  LocalVariableTable: 
   Start  Length  Slot  Name   Signature
   0      19      0    this       Lscala/actors/remote/TcpService;
   0      19      1    mnode       Lscala/actors/remote/Node;


public boolean isReachable(scala.actors.remote.Node);
  Code:
   Stack=2, Locals=6, Args_size=2
   0:	aload_0
   1:	aload_1
   2:	invokevirtual	#237; //Method isConnected:(Lscala/actors/remote/Node;)Z
   5:	ifeq	12
   8:	iconst_1
   9:	goto	40
   12:	iconst_0
   13:	istore_2
   14:	aload_0
   15:	aload_1
   16:	invokevirtual	#81; //Method connect:(Lscala/actors/remote/Node;)Lscala/actors/remote/TcpServiceWorker;
   19:	pop
   20:	iconst_1
   21:	ireturn
   22:	astore_3
   23:	iconst_0
   24:	istore_2
   25:	goto	39
   28:	astore	4
   30:	iconst_0
   31:	istore_2
   32:	goto	39
   35:	astore	5
   37:	iconst_0
   38:	istore_2
   39:	iload_2
   40:	ireturn
  Exception table:
   from   to  target type
    14    22    35   Class java/net/UnknownHostException

    14    22    28   Class java/io/IOException

    14    22    22   Class java/lang/SecurityException

  LineNumberTable: 
   line 205: 0
   line 207: 12
   line 206: 13
   line 207: 14
   line 208: 20
   line 212: 22
   line 211: 28
   line 210: 35
   line 205: 39

  LocalVariableTable: 
   Start  Length  Slot  Name   Signature
   0      41      0    this       Lscala/actors/remote/TcpService;
   0      41      1    node       Lscala/actors/remote/Node;
   14      26      2    exceptionResult2       Z


public void disconnectNode(scala.actors.remote.Node);
  Code:
   Stack=3, Locals=7, Args_size=2
   0:	aload_0
   1:	dup
   2:	astore_2
   3:	monitorenter
   4:	aload_0
   5:	invokespecial	#231; //Method connections:()Lscala/collection/mutable/HashMap;
   8:	aload_1
   9:	invokevirtual	#94; //Method scala/collection/mutable/HashMap.get:(Ljava/lang/Object;)Lscala/Option;
   12:	astore_3
   13:	getstatic	#100; //Field scala/None$.MODULE$:Lscala/None$;
   16:	aload_3
   17:	astore	4
   19:	dup
   20:	ifnonnull	32
   23:	pop
   24:	aload	4
   26:	ifnull	40
   29:	goto	53
   32:	aload	4
   34:	invokevirtual	#106; //Method java/lang/Object.equals:(Ljava/lang/Object;)Z
   37:	ifeq	53
   40:	aload_3
   41:	instanceof	#96; //class scala/None$
   44:	ifeq	53
   47:	getstatic	#112; //Field scala/runtime/BoxedUnit.UNIT:Lscala/runtime/BoxedUnit;
   50:	goto	93
   53:	aload_3
   54:	instanceof	#114; //class scala/Some
   57:	ifeq	97
   60:	aload_3
   61:	checkcast	#114; //class scala/Some
   64:	astore	5
   66:	aload	5
   68:	invokevirtual	#118; //Method scala/Some.x:()Ljava/lang/Object;
   71:	checkcast	#83; //class scala/actors/remote/TcpServiceWorker
   74:	astore	6
   76:	aload_0
   77:	invokespecial	#231; //Method connections:()Lscala/collection/mutable/HashMap;
   80:	aload_1
   81:	invokevirtual	#135; //Method scala/collection/mutable/HashMap.$minus$eq:(Ljava/lang/Object;)Lscala/collection/mutable/HashMap;
   84:	pop
   85:	aload	6
   87:	invokevirtual	#243; //Method scala/actors/remote/TcpServiceWorker.halt:()V
   90:	getstatic	#112; //Field scala/runtime/BoxedUnit.UNIT:Lscala/runtime/BoxedUnit;
   93:	pop
   94:	aload_2
   95:	monitorexit
   96:	return
   97:	new	#137; //class scala/MatchError
   100:	dup
   101:	aload_3
   102:	invokevirtual	#142; //Method scala/Option.toString:()Ljava/lang/String;
   105:	invokespecial	#145; //Method scala/MatchError."<init>":(Ljava/lang/String;)V
   108:	athrow
   109:	aload_2
   110:	monitorexit
   111:	athrow
  Exception table:
   from   to  target type
     4    96   109   any
    97   109   109   any
  LineNumberTable: 
   line 194: 0
   line 195: 4
   line 196: 47
   line 195: 53
   line 199: 76
   line 198: 85
   line 200: 87
   line 195: 93
   line 194: 95
   line 195: 97
   line 194: 110

  LocalVariableTable: 
   Start  Length  Slot  Name   Signature
   0      112      0    this       Lscala/actors/remote/TcpService;
   0      112      1    n       Lscala/actors/remote/Node;
   13      81      3    temp17       Lscala/Option;
   97      12      3    temp17       Lscala/Option;
   66      27      5    temp19       Lscala/Some;
   76      17      6    temp20       Lscala/actors/remote/TcpServiceWorker;


public scala.actors.remote.TcpServiceWorker connect(scala.actors.remote.Node);
  Code:
   Stack=4, Locals=5, Args_size=2
   0:	aload_0
   1:	dup
   2:	astore_2
   3:	monitorenter
   4:	new	#249; //class java/net/Socket
   7:	dup
   8:	aload_1
   9:	invokevirtual	#252; //Method scala/actors/remote/Node.address:()Ljava/lang/String;
   12:	aload_1
   13:	invokevirtual	#254; //Method scala/actors/remote/Node.port:()I
   16:	invokespecial	#255; //Method java/net/Socket."<init>":(Ljava/lang/String;I)V
   19:	astore_3
   20:	new	#83; //class scala/actors/remote/TcpServiceWorker
   23:	dup
   24:	aload_0
   25:	aload_3
   26:	invokespecial	#258; //Method scala/actors/remote/TcpServiceWorker."<init>":(Lscala/actors/remote/TcpService;Ljava/net/Socket;)V
   29:	astore	4
   31:	aload	4
   33:	aload_1
   34:	invokevirtual	#261; //Method scala/actors/remote/TcpServiceWorker.sendNode:(Lscala/actors/remote/Node;)V
   37:	aload	4
   39:	invokevirtual	#264; //Method scala/actors/remote/TcpServiceWorker.start:()V
   42:	aload_0
   43:	aload_1
   44:	aload	4
   46:	invokevirtual	#268; //Method addConnection:(Lscala/actors/remote/Node;Lscala/actors/remote/TcpServiceWorker;)Lscala/collection/mutable/HashMap;
   49:	pop
   50:	aload	4
   52:	aload_2
   53:	monitorexit
   54:	checkcast	#83; //class scala/actors/remote/TcpServiceWorker
   57:	areturn
   58:	aload_2
   59:	monitorexit
   60:	athrow
  Exception table:
   from   to  target type
     4    54    58   any
  LineNumberTable: 
   line 185: 0
   line 186: 4
   line 187: 20
   line 188: 31
   line 189: 37
   line 190: 42
   line 191: 50
   line 185: 53

  LocalVariableTable: 
   Start  Length  Slot  Name   Signature
   0      61      0    this       Lscala/actors/remote/TcpService;
   0      61      1    n       Lscala/actors/remote/Node;
   20      32      3    socket       Ljava/net/Socket;
   31      21      4    worker       Lscala/actors/remote/TcpServiceWorker;


public boolean isConnected(scala.actors.remote.Node);
  Code:
   Stack=2, Locals=3, Args_size=2
   0:	aload_0
   1:	dup
   2:	astore_2
   3:	monitorenter
   4:	aload_0
   5:	invokespecial	#231; //Method connections:()Lscala/collection/mutable/HashMap;
   8:	aload_1
   9:	invokevirtual	#94; //Method scala/collection/mutable/HashMap.get:(Ljava/lang/Object;)Lscala/Option;
   12:	invokevirtual	#275; //Method scala/Option.isEmpty:()Z
   15:	ifeq	22
   18:	iconst_0
   19:	goto	23
   22:	iconst_1
   23:	invokestatic	#281; //Method scala/runtime/BoxesRunTime.boxToBoolean:(Z)Ljava/lang/Boolean;
   26:	aload_2
   27:	monitorexit
   28:	invokestatic	#284; //Method scala/runtime/BoxesRunTime.unboxToBoolean:(Ljava/lang/Object;)Z
   31:	ireturn
   32:	aload_2
   33:	monitorexit
   34:	athrow
  Exception table:
   from   to  target type
     4    28    32   any
  LineNumberTable: 
   line 181: 0
   line 182: 4
   line 181: 27

  LocalVariableTable: 
   Start  Length  Slot  Name   Signature
   0      35      0    this       Lscala/actors/remote/TcpService;
   0      35      1    n       Lscala/actors/remote/Node;


public scala.Option getConnection(scala.actors.remote.Node);
  Code:
   Stack=2, Locals=3, Args_size=2
   0:	aload_0
   1:	dup
   2:	astore_2
   3:	monitorenter
   4:	aload_0
   5:	invokespecial	#231; //Method connections:()Lscala/collection/mutable/HashMap;
   8:	aload_1
   9:	invokevirtual	#94; //Method scala/collection/mutable/HashMap.get:(Ljava/lang/Object;)Lscala/Option;
   12:	aload_2
   13:	monitorexit
   14:	checkcast	#139; //class scala/Option
   17:	areturn
   18:	aload_2
   19:	monitorexit
   20:	athrow
  Exception table:
   from   to  target type
     4    14    18   any
  LineNumberTable: 
   line 177: 0
   line 178: 4
   line 177: 13

  LocalVariableTable: 
   Start  Length  Slot  Name   Signature
   0      21      0    this       Lscala/actors/remote/TcpService;
   0      21      1    n       Lscala/actors/remote/Node;

  Signature: length = 0x2
   01 1F 

public scala.collection.mutable.HashMap addConnection(scala.actors.remote.Node, scala.actors.remote.TcpServiceWorker);
  Code:
   Stack=4, Locals=4, Args_size=3
   0:	aload_0
   1:	dup
   2:	astore_3
   3:	monitorenter
   4:	aload_0
   5:	invokespecial	#231; //Method connections:()Lscala/collection/mutable/HashMap;
   8:	getstatic	#170; //Field scala/Predef$Pair$.MODULE$:Lscala/Predef$Pair$;
   11:	aload_1
   12:	aload_2
   13:	invokevirtual	#193; //Method scala/Predef$Pair$.apply:(Ljava/lang/Object;Ljava/lang/Object;)Lscala/Tuple2;
   16:	invokevirtual	#197; //Method scala/collection/mutable/HashMap.$plus$eq:(Lscala/Tuple2;)Lscala/collection/mutable/HashMap;
   19:	aload_3
   20:	monitorexit
   21:	checkcast	#63; //class scala/collection/mutable/HashMap
   24:	areturn
   25:	aload_3
   26:	monitorexit
   27:	athrow
  Exception table:
   from   to  target type
     4    21    25   any
  LineNumberTable: 
   line 173: 0
   line 174: 4
   line 173: 20

  LocalVariableTable: 
   Start  Length  Slot  Name   Signature
   0      28      0    this       Lscala/actors/remote/TcpService;
   0      28      1    node       Lscala/actors/remote/Node;
   0      28      2    worker       Lscala/actors/remote/TcpServiceWorker;

  Signature: length = 0x2
   01 20 

public void run();
  Code:
   Stack=5, Locals=9, Args_size=1
   0:	new	#292; //class java/net/ServerSocket
   3:	dup
   4:	aload_0
   5:	getfield	#26; //Field port:I
   8:	invokespecial	#295; //Method java/net/ServerSocket."<init>":(I)V
   11:	astore	6
   13:	aload_0
   14:	invokespecial	#297; //Method shouldTerminate:()Z
   17:	ifeq	99
   20:	getstatic	#302; //Field scala/actors/Debug$.MODULE$:Lscala/actors/Debug$;
   23:	getstatic	#307; //Field scala/Predef$.MODULE$:Lscala/Predef$;
   26:	aload_0
   27:	invokevirtual	#311; //Method scala/Predef$.any2stringadd:(Ljava/lang/Object;)Lscala/runtime/StringAdd;
   30:	ldc_w	#313; //String : shutting down...
   33:	invokevirtual	#319; //Method scala/runtime/StringAdd.$plus:(Ljava/lang/String;)Ljava/lang/String;
   36:	invokevirtual	#322; //Method scala/actors/Debug$.info:(Ljava/lang/String;)V
   39:	new	#324; //class scala/runtime/ObjectRef
   42:	dup
   43:	getstatic	#329; //Field scala/collection/immutable/Nil$.MODULE$:Lscala/collection/immutable/Nil$;
   46:	invokespecial	#332; //Method scala/runtime/ObjectRef."<init>":(Ljava/lang/Object;)V
   49:	astore	5
   51:	aload_0
   52:	invokespecial	#231; //Method connections:()Lscala/collection/mutable/HashMap;
   55:	invokeinterface	#338,  1; //InterfaceMethod scala/collection/generic/MapTemplate.values:()Lscala/collection/Iterator;
   60:	new	#340; //class scala/actors/remote/TcpService$$anonfun$run$1
   63:	dup
   64:	aload_0
   65:	aload	5
   67:	invokespecial	#343; //Method scala/actors/remote/TcpService$$anonfun$run$1."<init>":(Lscala/actors/remote/TcpService;Lscala/runtime/ObjectRef;)V
   70:	invokeinterface	#346,  2; //InterfaceMethod scala/collection/Iterator.foreach:(Lscala/Function1;)V
   75:	aload	5
   77:	getfield	#349; //Field scala/runtime/ObjectRef.elem:Ljava/lang/Object;
   80:	checkcast	#120; //class scala/collection/immutable/List
   83:	new	#351; //class scala/actors/remote/TcpService$$anonfun$run$2
   86:	dup
   87:	aload_0
   88:	invokespecial	#354; //Method scala/actors/remote/TcpService$$anonfun$run$2."<init>":(Lscala/actors/remote/TcpService;)V
   91:	invokeinterface	#131,  2; //InterfaceMethod scala/collection/generic/LinearSequenceTemplate.foreach:(Lscala/Function1;)V
   96:	goto	566
   99:	getstatic	#302; //Field scala/actors/Debug$.MODULE$:Lscala/actors/Debug$;
   102:	new	#356; //class scala/collection/mutable/StringBuilder
   105:	dup
   106:	invokespecial	#357; //Method scala/collection/mutable/StringBuilder."<init>":()V
   109:	getstatic	#307; //Field scala/Predef$.MODULE$:Lscala/Predef$;
   112:	aload_0
   113:	invokevirtual	#311; //Method scala/Predef$.any2stringadd:(Ljava/lang/Object;)Lscala/runtime/StringAdd;
   116:	ldc_w	#359; //String : waiting for new connection on port 
   119:	invokevirtual	#319; //Method scala/runtime/StringAdd.$plus:(Ljava/lang/String;)Ljava/lang/String;
   122:	invokevirtual	#363; //Method scala/collection/mutable/StringBuilder.append:(Ljava/lang/Object;)Lscala/collection/mutable/StringBuilder;
   125:	aload_0
   126:	getfield	#26; //Field port:I
   129:	invokestatic	#367; //Method scala/runtime/BoxesRunTime.boxToInteger:(I)Ljava/lang/Integer;
   132:	invokevirtual	#363; //Method scala/collection/mutable/StringBuilder.append:(Ljava/lang/Object;)Lscala/collection/mutable/StringBuilder;
   135:	ldc_w	#369; //String ...
   138:	invokevirtual	#363; //Method scala/collection/mutable/StringBuilder.append:(Ljava/lang/Object;)Lscala/collection/mutable/StringBuilder;
   141:	invokevirtual	#370; //Method scala/collection/mutable/StringBuilder.toString:()Ljava/lang/String;
   144:	invokevirtual	#322; //Method scala/actors/Debug$.info:(Ljava/lang/String;)V
   147:	aload	6
   149:	invokevirtual	#374; //Method java/net/ServerSocket.accept:()Ljava/net/Socket;
   152:	astore	7
   154:	aload_0
   155:	invokespecial	#297; //Method shouldTerminate:()Z
   158:	ifeq	169
   161:	aload	7
   163:	invokevirtual	#377; //Method java/net/Socket.close:()V
   166:	goto	13
   169:	new	#83; //class scala/actors/remote/TcpServiceWorker
   172:	dup
   173:	aload_0
   174:	aload	7
   176:	invokespecial	#258; //Method scala/actors/remote/TcpServiceWorker."<init>":(Lscala/actors/remote/TcpService;Ljava/net/Socket;)V
   179:	astore	8
   181:	getstatic	#302; //Field scala/actors/Debug$.MODULE$:Lscala/actors/Debug$;
   184:	new	#356; //class scala/collection/mutable/StringBuilder
   187:	dup
   188:	invokespecial	#357; //Method scala/collection/mutable/StringBuilder."<init>":()V
   191:	ldc_w	#379; //String Started new 
   194:	invokevirtual	#363; //Method scala/collection/mutable/StringBuilder.append:(Ljava/lang/Object;)Lscala/collection/mutable/StringBuilder;
   197:	aload	8
   199:	invokevirtual	#363; //Method scala/collection/mutable/StringBuilder.append:(Ljava/lang/Object;)Lscala/collection/mutable/StringBuilder;
   202:	invokevirtual	#370; //Method scala/collection/mutable/StringBuilder.toString:()Ljava/lang/String;
   205:	invokevirtual	#322; //Method scala/actors/Debug$.info:(Ljava/lang/String;)V
   208:	aload	8
   210:	invokevirtual	#382; //Method scala/actors/remote/TcpServiceWorker.readNode:()V
   213:	aload	8
   215:	invokevirtual	#264; //Method scala/actors/remote/TcpServiceWorker.start:()V
   218:	goto	13
   221:	astore_1
   222:	getstatic	#302; //Field scala/actors/Debug$.MODULE$:Lscala/actors/Debug$;
   225:	new	#356; //class scala/collection/mutable/StringBuilder
   228:	dup
   229:	invokespecial	#357; //Method scala/collection/mutable/StringBuilder."<init>":()V
   232:	getstatic	#307; //Field scala/Predef$.MODULE$:Lscala/Predef$;
   235:	aload_0
   236:	invokevirtual	#311; //Method scala/Predef$.any2stringadd:(Ljava/lang/Object;)Lscala/runtime/StringAdd;
   239:	ldc_w	#384; //String : caught 
   242:	invokevirtual	#319; //Method scala/runtime/StringAdd.$plus:(Ljava/lang/String;)Ljava/lang/String;
   245:	invokevirtual	#363; //Method scala/collection/mutable/StringBuilder.append:(Ljava/lang/Object;)Lscala/collection/mutable/StringBuilder;
   248:	aload_1
   249:	invokevirtual	#363; //Method scala/collection/mutable/StringBuilder.append:(Ljava/lang/Object;)Lscala/collection/mutable/StringBuilder;
   252:	invokevirtual	#370; //Method scala/collection/mutable/StringBuilder.toString:()Ljava/lang/String;
   255:	invokevirtual	#322; //Method scala/actors/Debug$.info:(Ljava/lang/String;)V
   258:	getstatic	#302; //Field scala/actors/Debug$.MODULE$:Lscala/actors/Debug$;
   261:	getstatic	#307; //Field scala/Predef$.MODULE$:Lscala/Predef$;
   264:	aload_0
   265:	invokevirtual	#311; //Method scala/Predef$.any2stringadd:(Ljava/lang/Object;)Lscala/runtime/StringAdd;
   268:	ldc_w	#313; //String : shutting down...
   271:	invokevirtual	#319; //Method scala/runtime/StringAdd.$plus:(Ljava/lang/String;)Ljava/lang/String;
   274:	invokevirtual	#322; //Method scala/actors/Debug$.info:(Ljava/lang/String;)V
   277:	new	#324; //class scala/runtime/ObjectRef
   280:	dup
   281:	getstatic	#329; //Field scala/collection/immutable/Nil$.MODULE$:Lscala/collection/immutable/Nil$;
   284:	invokespecial	#332; //Method scala/runtime/ObjectRef."<init>":(Ljava/lang/Object;)V
   287:	astore	5
   289:	aload_0
   290:	invokespecial	#231; //Method connections:()Lscala/collection/mutable/HashMap;
   293:	invokeinterface	#338,  1; //InterfaceMethod scala/collection/generic/MapTemplate.values:()Lscala/collection/Iterator;
   298:	new	#340; //class scala/actors/remote/TcpService$$anonfun$run$1
   301:	dup
   302:	aload_0
   303:	aload	5
   305:	invokespecial	#343; //Method scala/actors/remote/TcpService$$anonfun$run$1."<init>":(Lscala/actors/remote/TcpService;Lscala/runtime/ObjectRef;)V
   308:	invokeinterface	#346,  2; //InterfaceMethod scala/collection/Iterator.foreach:(Lscala/Function1;)V
   313:	aload	5
   315:	getfield	#349; //Field scala/runtime/ObjectRef.elem:Ljava/lang/Object;
   318:	checkcast	#120; //class scala/collection/immutable/List
   321:	new	#351; //class scala/actors/remote/TcpService$$anonfun$run$2
   324:	dup
   325:	aload_0
   326:	invokespecial	#354; //Method scala/actors/remote/TcpService$$anonfun$run$2."<init>":(Lscala/actors/remote/TcpService;)V
   329:	invokeinterface	#131,  2; //InterfaceMethod scala/collection/generic/LinearSequenceTemplate.foreach:(Lscala/Function1;)V
   334:	goto	566
   337:	astore_2
   338:	getstatic	#302; //Field scala/actors/Debug$.MODULE$:Lscala/actors/Debug$;
   341:	new	#356; //class scala/collection/mutable/StringBuilder
   344:	dup
   345:	invokespecial	#357; //Method scala/collection/mutable/StringBuilder."<init>":()V
   348:	getstatic	#307; //Field scala/Predef$.MODULE$:Lscala/Predef$;
   351:	aload_0
   352:	invokevirtual	#311; //Method scala/Predef$.any2stringadd:(Ljava/lang/Object;)Lscala/runtime/StringAdd;
   355:	ldc_w	#384; //String : caught 
   358:	invokevirtual	#319; //Method scala/runtime/StringAdd.$plus:(Ljava/lang/String;)Ljava/lang/String;
   361:	invokevirtual	#363; //Method scala/collection/mutable/StringBuilder.append:(Ljava/lang/Object;)Lscala/collection/mutable/StringBuilder;
   364:	aload_2
   365:	invokevirtual	#363; //Method scala/collection/mutable/StringBuilder.append:(Ljava/lang/Object;)Lscala/collection/mutable/StringBuilder;
   368:	invokevirtual	#370; //Method scala/collection/mutable/StringBuilder.toString:()Ljava/lang/String;
   371:	invokevirtual	#322; //Method scala/actors/Debug$.info:(Ljava/lang/String;)V
   374:	getstatic	#302; //Field scala/actors/Debug$.MODULE$:Lscala/actors/Debug$;
   377:	getstatic	#307; //Field scala/Predef$.MODULE$:Lscala/Predef$;
   380:	aload_0
   381:	invokevirtual	#311; //Method scala/Predef$.any2stringadd:(Ljava/lang/Object;)Lscala/runtime/StringAdd;
   384:	ldc_w	#313; //String : shutting down...
   387:	invokevirtual	#319; //Method scala/runtime/StringAdd.$plus:(Ljava/lang/String;)Ljava/lang/String;
   390:	invokevirtual	#322; //Method scala/actors/Debug$.info:(Ljava/lang/String;)V
   393:	new	#324; //class scala/runtime/ObjectRef
   396:	dup
   397:	getstatic	#329; //Field scala/collection/immutable/Nil$.MODULE$:Lscala/collection/immutable/Nil$;
   400:	invokespecial	#332; //Method scala/runtime/ObjectRef."<init>":(Ljava/lang/Object;)V
   403:	astore	5
   405:	aload_0
   406:	invokespecial	#231; //Method connections:()Lscala/collection/mutable/HashMap;
   409:	invokeinterface	#338,  1; //InterfaceMethod scala/collection/generic/MapTemplate.values:()Lscala/collection/Iterator;
   414:	new	#340; //class scala/actors/remote/TcpService$$anonfun$run$1
   417:	dup
   418:	aload_0
   419:	aload	5
   421:	invokespecial	#343; //Method scala/actors/remote/TcpService$$anonfun$run$1."<init>":(Lscala/actors/remote/TcpService;Lscala/runtime/ObjectRef;)V
   424:	invokeinterface	#346,  2; //InterfaceMethod scala/collection/Iterator.foreach:(Lscala/Function1;)V
   429:	aload	5
   431:	getfield	#349; //Field scala/runtime/ObjectRef.elem:Ljava/lang/Object;
   434:	checkcast	#120; //class scala/collection/immutable/List
   437:	new	#351; //class scala/actors/remote/TcpService$$anonfun$run$2
   440:	dup
   441:	aload_0
   442:	invokespecial	#354; //Method scala/actors/remote/TcpService$$anonfun$run$2."<init>":(Lscala/actors/remote/TcpService;)V
   445:	invokeinterface	#131,  2; //InterfaceMethod scala/collection/generic/LinearSequenceTemplate.foreach:(Lscala/Function1;)V
   450:	goto	566
   453:	astore_3
   454:	getstatic	#302; //Field scala/actors/Debug$.MODULE$:Lscala/actors/Debug$;
   457:	new	#356; //class scala/collection/mutable/StringBuilder
   460:	dup
   461:	invokespecial	#357; //Method scala/collection/mutable/StringBuilder."<init>":()V
   464:	getstatic	#307; //Field scala/Predef$.MODULE$:Lscala/Predef$;
   467:	aload_0
   468:	invokevirtual	#311; //Method scala/Predef$.any2stringadd:(Ljava/lang/Object;)Lscala/runtime/StringAdd;
   471:	ldc_w	#384; //String : caught 
   474:	invokevirtual	#319; //Method scala/runtime/StringAdd.$plus:(Ljava/lang/String;)Ljava/lang/String;
   477:	invokevirtual	#363; //Method scala/collection/mutable/StringBuilder.append:(Ljava/lang/Object;)Lscala/collection/mutable/StringBuilder;
   480:	aload_3
   481:	invokevirtual	#363; //Method scala/collection/mutable/StringBuilder.append:(Ljava/lang/Object;)Lscala/collection/mutable/StringBuilder;
   484:	invokevirtual	#370; //Method scala/collection/mutable/StringBuilder.toString:()Ljava/lang/String;
   487:	invokevirtual	#322; //Method scala/actors/Debug$.info:(Ljava/lang/String;)V
   490:	getstatic	#302; //Field scala/actors/Debug$.MODULE$:Lscala/actors/Debug$;
   493:	getstatic	#307; //Field scala/Predef$.MODULE$:Lscala/Predef$;
   496:	aload_0
   497:	invokevirtual	#311; //Method scala/Predef$.any2stringadd:(Ljava/lang/Object;)Lscala/runtime/StringAdd;
   500:	ldc_w	#313; //String : shutting down...
   503:	invokevirtual	#319; //Method scala/runtime/StringAdd.$plus:(Ljava/lang/String;)Ljava/lang/String;
   506:	invokevirtual	#322; //Method scala/actors/Debug$.info:(Ljava/lang/String;)V
   509:	new	#324; //class scala/runtime/ObjectRef
   512:	dup
   513:	getstatic	#329; //Field scala/collection/immutable/Nil$.MODULE$:Lscala/collection/immutable/Nil$;
   516:	invokespecial	#332; //Method scala/runtime/ObjectRef."<init>":(Ljava/lang/Object;)V
   519:	astore	5
   521:	aload_0
   522:	invokespecial	#231; //Method connections:()Lscala/collection/mutable/HashMap;
   525:	invokeinterface	#338,  1; //InterfaceMethod scala/collection/generic/MapTemplate.values:()Lscala/collection/Iterator;
   530:	new	#340; //class scala/actors/remote/TcpService$$anonfun$run$1
   533:	dup
   534:	aload_0
   535:	aload	5
   537:	invokespecial	#343; //Method scala/actors/remote/TcpService$$anonfun$run$1."<init>":(Lscala/actors/remote/TcpService;Lscala/runtime/ObjectRef;)V
   540:	invokeinterface	#346,  2; //InterfaceMethod scala/collection/Iterator.foreach:(Lscala/Function1;)V
   545:	aload	5
   547:	getfield	#349; //Field scala/runtime/ObjectRef.elem:Ljava/lang/Object;
   550:	checkcast	#120; //class scala/collection/immutable/List
   553:	new	#351; //class scala/actors/remote/TcpService$$anonfun$run$2
   556:	dup
   557:	aload_0
   558:	invokespecial	#354; //Method scala/actors/remote/TcpService$$anonfun$run$2."<init>":(Lscala/actors/remote/TcpService;)V
   561:	invokeinterface	#131,  2; //InterfaceMethod scala/collection/generic/LinearSequenceTemplate.foreach:(Lscala/Function1;)V
   566:	return
   567:	astore	4
   569:	getstatic	#302; //Field scala/actors/Debug$.MODULE$:Lscala/actors/Debug$;
   572:	getstatic	#307; //Field scala/Predef$.MODULE$:Lscala/Predef$;
   575:	aload_0
   576:	invokevirtual	#311; //Method scala/Predef$.any2stringadd:(Ljava/lang/Object;)Lscala/runtime/StringAdd;
   579:	ldc_w	#313; //String : shutting down...
   582:	invokevirtual	#319; //Method scala/runtime/StringAdd.$plus:(Ljava/lang/String;)Ljava/lang/String;
   585:	invokevirtual	#322; //Method scala/actors/Debug$.info:(Ljava/lang/String;)V
   588:	new	#324; //class scala/runtime/ObjectRef
   591:	dup
   592:	getstatic	#329; //Field scala/collection/immutable/Nil$.MODULE$:Lscala/collection/immutable/Nil$;
   595:	invokespecial	#332; //Method scala/runtime/ObjectRef."<init>":(Ljava/lang/Object;)V
   598:	astore	5
   600:	aload_0
   601:	invokespecial	#231; //Method connections:()Lscala/collection/mutable/HashMap;
   604:	invokeinterface	#338,  1; //InterfaceMethod scala/collection/generic/MapTemplate.values:()Lscala/collection/Iterator;
   609:	new	#340; //class scala/actors/remote/TcpService$$anonfun$run$1
   612:	dup
   613:	aload_0
   614:	aload	5
   616:	invokespecial	#343; //Method scala/actors/remote/TcpService$$anonfun$run$1."<init>":(Lscala/actors/remote/TcpService;Lscala/runtime/ObjectRef;)V
   619:	invokeinterface	#346,  2; //InterfaceMethod scala/collection/Iterator.foreach:(Lscala/Function1;)V
   624:	aload	5
   626:	getfield	#349; //Field scala/runtime/ObjectRef.elem:Ljava/lang/Object;
   629:	checkcast	#120; //class scala/collection/immutable/List
   632:	new	#351; //class scala/actors/remote/TcpService$$anonfun$run$2
   635:	dup
   636:	aload_0
   637:	invokespecial	#354; //Method scala/actors/remote/TcpService$$anonfun$run$2."<init>":(Lscala/actors/remote/TcpService;)V
   640:	invokeinterface	#131,  2; //InterfaceMethod scala/collection/generic/LinearSequenceTemplate.foreach:(Lscala/Function1;)V
   645:	aload	4
   647:	athrow
  Exception table:
   from   to  target type
     0   221   453   Class java/io/IOException

     0   221   337   Class java/lang/SecurityException

     0   221   221   Class java/lang/Exception

     0   566   567   any
  LineNumberTable: 
   line 140: 0
   line 141: 13
   line 160: 20
   line 162: 39
   line 163: 51
   line 164: 75
   line 142: 99
   line 143: 147
   line 144: 154
   line 150: 161
   line 145: 169
   line 146: 181
   line 147: 208
   line 148: 213
   line 157: 221
   line 158: 222
   line 160: 258
   line 162: 277
   line 163: 289
   line 164: 313
   line 155: 337
   line 156: 338
   line 160: 374
   line 162: 393
   line 163: 405
   line 164: 429
   line 153: 453
   line 154: 454
   line 160: 490
   line 162: 509
   line 163: 521
   line 164: 545
   line 139: 566
   line 160: 569
   line 162: 588
   line 163: 600
   line 164: 624

  LocalVariableTable: 
   Start  Length  Slot  Name   Signature
   0      648      0    this       Lscala/actors/remote/TcpService;
   51      45      5    workers$1       Lscala/runtime/ObjectRef;
   289      45      5    workers$1       Lscala/runtime/ObjectRef;
   405      45      5    workers$1       Lscala/runtime/ObjectRef;
   521      45      5    workers$1       Lscala/runtime/ObjectRef;
   600      45      5    workers$1       Lscala/runtime/ObjectRef;
   13      208      6    socket       Ljava/net/ServerSocket;
   154      67      7    nextClient       Ljava/net/Socket;
   181      37      8    worker       Lscala/actors/remote/TcpServiceWorker;


public void terminate();
  Code:
   Stack=4, Locals=2, Args_size=1
   0:	aload_0
   1:	iconst_1
   2:	invokespecial	#395; //Method shouldTerminate_$eq:(Z)V
   5:	new	#249; //class java/net/Socket
   8:	dup
   9:	aload_0
   10:	invokespecial	#398; //Method internalNode:()Lscala/actors/remote/Node;
   13:	invokevirtual	#252; //Method scala/actors/remote/Node.address:()Ljava/lang/String;
   16:	aload_0
   17:	invokespecial	#398; //Method internalNode:()Lscala/actors/remote/Node;
   20:	invokevirtual	#254; //Method scala/actors/remote/Node.port:()I
   23:	invokespecial	#255; //Method java/net/Socket."<init>":(Ljava/lang/String;I)V
   26:	pop
   27:	goto	67
   30:	astore_1
   31:	getstatic	#302; //Field scala/actors/Debug$.MODULE$:Lscala/actors/Debug$;
   34:	new	#356; //class scala/collection/mutable/StringBuilder
   37:	dup
   38:	invokespecial	#357; //Method scala/collection/mutable/StringBuilder."<init>":()V
   41:	getstatic	#307; //Field scala/Predef$.MODULE$:Lscala/Predef$;
   44:	aload_0
   45:	invokevirtual	#311; //Method scala/Predef$.any2stringadd:(Ljava/lang/Object;)Lscala/runtime/StringAdd;
   48:	ldc_w	#384; //String : caught 
   51:	invokevirtual	#319; //Method scala/runtime/StringAdd.$plus:(Ljava/lang/String;)Ljava/lang/String;
   54:	invokevirtual	#363; //Method scala/collection/mutable/StringBuilder.append:(Ljava/lang/Object;)Lscala/collection/mutable/StringBuilder;
   57:	aload_1
   58:	invokevirtual	#363; //Method scala/collection/mutable/StringBuilder.append:(Ljava/lang/Object;)Lscala/collection/mutable/StringBuilder;
   61:	invokevirtual	#370; //Method scala/collection/mutable/StringBuilder.toString:()Ljava/lang/String;
   64:	invokevirtual	#322; //Method scala/actors/Debug$.info:(Ljava/lang/String;)V
   67:	return
  Exception table:
   from   to  target type
     5    30    30   Class java/net/ConnectException

  LineNumberTable: 
   line 127: 0
   line 129: 5
   line 131: 30
   line 132: 31
   line 126: 67

  LocalVariableTable: 
   Start  Length  Slot  Name   Signature
   0      68      0    this       Lscala/actors/remote/TcpService;


public void send(scala.actors.remote.Node, byte[]);
  Code:
   Stack=3, Locals=8, Args_size=3
   0:	aload_0
   1:	dup
   2:	astore_3
   3:	monitorenter
   4:	aload_0
   5:	aload_1
   6:	invokevirtual	#404; //Method getConnection:(Lscala/actors/remote/Node;)Lscala/Option;
   9:	astore	4
   11:	getstatic	#100; //Field scala/None$.MODULE$:Lscala/None$;
   14:	aload	4
   16:	astore	5
   18:	dup
   19:	ifnonnull	31
   22:	pop
   23:	aload	5
   25:	ifnull	39
   28:	goto	56
   31:	aload	5
   33:	invokevirtual	#106; //Method java/lang/Object.equals:(Ljava/lang/Object;)Z
   36:	ifeq	56
   39:	aload	4
   41:	instanceof	#96; //class scala/None$
   44:	ifeq	56
   47:	aload_0
   48:	aload_1
   49:	aload_2
   50:	invokespecial	#406; //Method liftedTree1$1:(Lscala/actors/remote/Node;[B)Ljava/lang/Object;
   53:	goto	90
   56:	aload	4
   58:	instanceof	#114; //class scala/Some
   61:	ifeq	94
   64:	aload	4
   66:	checkcast	#114; //class scala/Some
   69:	astore	6
   71:	aload	6
   73:	invokevirtual	#118; //Method scala/Some.x:()Ljava/lang/Object;
   76:	checkcast	#83; //class scala/actors/remote/TcpServiceWorker
   79:	astore	7
   81:	aload	7
   83:	aload_2
   84:	invokevirtual	#87; //Method scala/actors/remote/TcpServiceWorker.transmit:([B)V
   87:	getstatic	#112; //Field scala/runtime/BoxedUnit.UNIT:Lscala/runtime/BoxedUnit;
   90:	pop
   91:	aload_3
   92:	monitorexit
   93:	return
   94:	new	#137; //class scala/MatchError
   97:	dup
   98:	aload	4
   100:	invokevirtual	#142; //Method scala/Option.toString:()Ljava/lang/String;
   103:	invokespecial	#145; //Method scala/MatchError."<init>":(Ljava/lang/String;)V
   106:	athrow
   107:	aload_3
   108:	monitorexit
   109:	athrow
  Exception table:
   from   to  target type
     4    93   107   any
    94   107   107   any
  LineNumberTable: 
   line 84: 0
   line 98: 4
   line 101: 47
   line 98: 56
   line 121: 81
   line 122: 83
   line 98: 90
   line 84: 92
   line 98: 94
   line 84: 108

  LocalVariableTable: 
   Start  Length  Slot  Name   Signature
   0      110      0    this       Lscala/actors/remote/TcpService;
   0      110      1    node$1       Lscala/actors/remote/Node;
   0      110      2    data$1       [B
   11      80      4    temp13       Lscala/Option;
   94      13      4    temp13       Lscala/Option;
   71      19      6    temp15       Lscala/Some;
   81      9      7    temp16       Lscala/actors/remote/TcpServiceWorker;


public scala.actors.remote.Node node();
  Code:
   Stack=1, Locals=1, Args_size=1
   0:	aload_0
   1:	invokespecial	#398; //Method internalNode:()Lscala/actors/remote/Node;
   4:	areturn
  LineNumberTable: 
   line 75: 0


public scala.actors.remote.JavaSerializer serializer();
  Code:
   Stack=1, Locals=1, Args_size=1
   0:	aload_0
   1:	getfield	#44; //Field serializer:Lscala/actors/remote/JavaSerializer;
   4:	areturn
  LineNumberTable: 
   line 72: 0


public void scala$actors$remote$Service$_setter_$kernel_$eq(scala.actors.remote.NetKernel);
  Code:
   Stack=2, Locals=2, Args_size=2
   0:	aload_0
   1:	aload_1
   2:	putfield	#416; //Field kernel:Lscala/actors/remote/NetKernel;
   5:	return
  LineNumberTable: 
   line 71: 0


public scala.actors.remote.NetKernel kernel();
  Code:
   Stack=1, Locals=1, Args_size=1
   0:	aload_0
   1:	getfield	#416; //Field kernel:Lscala/actors/remote/NetKernel;
   4:	areturn
  LineNumberTable: 
   line 71: 0


}

