Compiled from "TcpService.scala"
public final class scala.actors.remote.TcpService$ extends java.lang.Object implements scala.ScalaObject
  SourceFile: "TcpService.scala"
  Scala: length = 0x
   
  InnerClass: 
   public final #177= #176 of #102; //$anonfun$run$1=class scala/actors/remote/TcpService$$anonfun$run$1 of class scala/actors/remote/TcpService
   public final #180= #179 of #102; //$anonfun$run$2=class scala/actors/remote/TcpService$$anonfun$run$2 of class scala/actors/remote/TcpService
   public final #183= #182 of #102; //$anonfun$liftedTree1$1$1=class scala/actors/remote/TcpService$$anonfun$liftedTree1$1$1 of class scala/actors/remote/TcpService
  minor version: 0
  major version: 49
  Constant pool:
const #1 = Asciz	SourceFile;
const #2 = Asciz	TcpService.scala;
const #3 = Asciz	Scala;
const #4 = Asciz	MODULE$;
const #5 = Asciz	Lscala/actors/remote/TcpService$;;
const #6 = Asciz	<clinit>;
const #7 = Asciz	()V;
const #8 = Asciz	Code;
const #9 = Asciz	scala/actors/remote/TcpService$;
const #10 = class	#9;	//  scala/actors/remote/TcpService$
const #11 = Asciz	<init>;
const #12 = NameAndType	#11:#7;//  "<init>":()V
const #13 = Method	#10.#12;	//  scala/actors/remote/TcpService$."<init>":()V
const #14 = Asciz	BufSize;
const #15 = Asciz	I;
const #16 = Asciz	ports;
const #17 = Asciz	Lscala/collection/mutable/HashMap;;
const #18 = Asciz	Lscala/collection/mutable/HashMap<Ljava/lang/Integer;Lscala/actors/remote/TcpService;>;;
const #19 = Asciz	Signature;
const #20 = Asciz	random;
const #21 = Asciz	Lscala/util/Random;;
const #22 = Asciz	LineNumberTable;
const #23 = Asciz	java/lang/Object;
const #24 = class	#23;	//  java/lang/Object
const #25 = Method	#24.#12;	//  java/lang/Object."<init>":()V
const #26 = NameAndType	#4:#5;//  MODULE$:Lscala/actors/remote/TcpService$;
const #27 = Field	#10.#26;	//  scala/actors/remote/TcpService$.MODULE$:Lscala/actors/remote/TcpService$;
const #28 = Asciz	scala/util/Random;
const #29 = class	#28;	//  scala/util/Random
const #30 = Method	#29.#12;	//  scala/util/Random."<init>":()V
const #31 = NameAndType	#20:#21;//  random:Lscala/util/Random;
const #32 = Field	#10.#31;	//  scala/actors/remote/TcpService$.random:Lscala/util/Random;
const #33 = Asciz	scala/collection/mutable/HashMap;
const #34 = class	#33;	//  scala/collection/mutable/HashMap
const #35 = Method	#34.#12;	//  scala/collection/mutable/HashMap."<init>":()V
const #36 = NameAndType	#16:#17;//  ports:Lscala/collection/mutable/HashMap;
const #37 = Field	#10.#36;	//  scala/actors/remote/TcpService$.ports:Lscala/collection/mutable/HashMap;
const #38 = int	65536;
const #39 = NameAndType	#14:#15;//  BufSize:I
const #40 = Field	#10.#39;	//  scala/actors/remote/TcpService$.BufSize:I
const #41 = Asciz	BufSize_$eq;
const #42 = Asciz	(I)V;
const #43 = Asciz	()I;
const #44 = Asciz	generatePort;
const #45 = int	8000;
const #46 = Asciz	()Lscala/util/Random;;
const #47 = NameAndType	#20:#46;//  random:()Lscala/util/Random;
const #48 = Method	#10.#47;	//  scala/actors/remote/TcpService$.random:()Lscala/util/Random;
const #49 = int	500;
const #50 = Asciz	nextInt;
const #51 = Asciz	(I)I;
const #52 = NameAndType	#50:#51;//  nextInt:(I)I
const #53 = Method	#29.#52;	//  scala/util/Random.nextInt:(I)I
const #54 = Asciz	java/net/ServerSocket;
const #55 = class	#54;	//  java/net/ServerSocket
const #56 = NameAndType	#11:#42;//  "<init>":(I)V
const #57 = Method	#55.#56;	//  java/net/ServerSocket."<init>":(I)V
const #58 = Asciz	close;
const #59 = NameAndType	#58:#7;//  close:()V
const #60 = Method	#55.#59;	//  java/net/ServerSocket.close:()V
const #61 = Asciz	scala/runtime/BoxedUnit;
const #62 = class	#61;	//  scala/runtime/BoxedUnit
const #63 = Asciz	UNIT;
const #64 = Asciz	Lscala/runtime/BoxedUnit;;
const #65 = NameAndType	#63:#64;//  UNIT:Lscala/runtime/BoxedUnit;
const #66 = Field	#62.#65;	//  scala/runtime/BoxedUnit.UNIT:Lscala/runtime/BoxedUnit;
const #67 = NameAndType	#44:#43;//  generatePort:()I
const #68 = Method	#10.#67;	//  scala/actors/remote/TcpService$.generatePort:()I
const #69 = Asciz	scala/runtime/BoxesRunTime;
const #70 = class	#69;	//  scala/runtime/BoxesRunTime
const #71 = Asciz	boxToInteger;
const #72 = Asciz	(I)Ljava/lang/Integer;;
const #73 = NameAndType	#71:#72;//  boxToInteger:(I)Ljava/lang/Integer;
const #74 = Method	#70.#73;	//  scala/runtime/BoxesRunTime.boxToInteger:(I)Ljava/lang/Integer;
const #75 = Asciz	java/io/IOException;
const #76 = class	#75;	//  java/io/IOException
const #77 = Asciz	java/lang/SecurityException;
const #78 = class	#77;	//  java/lang/SecurityException
const #79 = Asciz	this;
const #80 = Asciz	portnum;
const #81 = Asciz	exceptionResult1;
const #82 = Asciz	Ljava/lang/Object;;
const #83 = Asciz	socket;
const #84 = Asciz	Ljava/net/ServerSocket;;
const #85 = Asciz	LocalVariableTable;
const #86 = Asciz	apply;
const #87 = Asciz	(ILjava/lang/ClassLoader;)Lscala/actors/remote/TcpService;;
const #88 = Asciz	()Lscala/collection/mutable/HashMap;;
const #89 = NameAndType	#16:#88;//  ports:()Lscala/collection/mutable/HashMap;
const #90 = Method	#10.#89;	//  scala/actors/remote/TcpService$.ports:()Lscala/collection/mutable/HashMap;
const #91 = Asciz	get;
const #92 = Asciz	(Ljava/lang/Object;)Lscala/Option;;
const #93 = NameAndType	#91:#92;//  get:(Ljava/lang/Object;)Lscala/Option;
const #94 = Method	#34.#93;	//  scala/collection/mutable/HashMap.get:(Ljava/lang/Object;)Lscala/Option;
const #95 = Asciz	scala/Some;
const #96 = class	#95;	//  scala/Some
const #97 = Asciz	x;
const #98 = Asciz	()Ljava/lang/Object;;
const #99 = NameAndType	#97:#98;//  x:()Ljava/lang/Object;
const #100 = Method	#96.#99;	//  scala/Some.x:()Ljava/lang/Object;
const #101 = Asciz	scala/actors/remote/TcpService;
const #102 = class	#101;	//  scala/actors/remote/TcpService
const #103 = Asciz	scala/None$;
const #104 = class	#103;	//  scala/None$
const #105 = Asciz	Lscala/None$;;
const #106 = NameAndType	#4:#105;//  MODULE$:Lscala/None$;
const #107 = Field	#104.#106;	//  scala/None$.MODULE$:Lscala/None$;
const #108 = Asciz	equals;
const #109 = Asciz	(Ljava/lang/Object;)Z;
const #110 = NameAndType	#108:#109;//  equals:(Ljava/lang/Object;)Z
const #111 = Method	#24.#110;	//  java/lang/Object.equals:(Ljava/lang/Object;)Z
const #112 = Asciz	(ILjava/lang/ClassLoader;)V;
const #113 = NameAndType	#11:#112;//  "<init>":(ILjava/lang/ClassLoader;)V
const #114 = Method	#102.#113;	//  scala/actors/remote/TcpService."<init>":(ILjava/lang/ClassLoader;)V
const #115 = Asciz	scala/Predef$Pair$;
const #116 = class	#115;	//  scala/Predef$Pair$
const #117 = Asciz	Lscala/Predef$Pair$;;
const #118 = NameAndType	#4:#117;//  MODULE$:Lscala/Predef$Pair$;
const #119 = Field	#116.#118;	//  scala/Predef$Pair$.MODULE$:Lscala/Predef$Pair$;
const #120 = Asciz	(Ljava/lang/Object;Ljava/lang/Object;)Lscala/Tuple2;;
const #121 = NameAndType	#86:#120;//  apply:(Ljava/lang/Object;Ljava/lang/Object;)Lscala/Tuple2;
const #122 = Method	#116.#121;	//  scala/Predef$Pair$.apply:(Ljava/lang/Object;Ljava/lang/Object;)Lscala/Tuple2;
const #123 = Asciz	$plus$eq;
const #124 = Asciz	(Lscala/Tuple2;)Lscala/collection/mutable/HashMap;;
const #125 = NameAndType	#123:#124;//  $plus$eq:(Lscala/Tuple2;)Lscala/collection/mutable/HashMap;
const #126 = Method	#34.#125;	//  scala/collection/mutable/HashMap.$plus$eq:(Lscala/Tuple2;)Lscala/collection/mutable/HashMap;
const #127 = Asciz	start;
const #128 = NameAndType	#127:#7;//  start:()V
const #129 = Method	#102.#128;	//  scala/actors/remote/TcpService.start:()V
const #130 = Asciz	scala/actors/Debug$;
const #131 = class	#130;	//  scala/actors/Debug$
const #132 = Asciz	Lscala/actors/Debug$;;
const #133 = NameAndType	#4:#132;//  MODULE$:Lscala/actors/Debug$;
const #134 = Field	#131.#133;	//  scala/actors/Debug$.MODULE$:Lscala/actors/Debug$;
const #135 = Asciz	scala/collection/mutable/StringBuilder;
const #136 = class	#135;	//  scala/collection/mutable/StringBuilder
const #137 = Method	#136.#12;	//  scala/collection/mutable/StringBuilder."<init>":()V
const #138 = Asciz	created service at ;
const #139 = String	#138;	//  created service at 
const #140 = Asciz	append;
const #141 = Asciz	(Ljava/lang/Object;)Lscala/collection/mutable/StringBuilder;;
const #142 = NameAndType	#140:#141;//  append:(Ljava/lang/Object;)Lscala/collection/mutable/StringBuilder;
const #143 = Method	#136.#142;	//  scala/collection/mutable/StringBuilder.append:(Ljava/lang/Object;)Lscala/collection/mutable/StringBuilder;
const #144 = Asciz	node;
const #145 = Asciz	()Lscala/actors/remote/Node;;
const #146 = NameAndType	#144:#145;//  node:()Lscala/actors/remote/Node;
const #147 = Method	#102.#146;	//  scala/actors/remote/TcpService.node:()Lscala/actors/remote/Node;
const #148 = Asciz	toString;
const #149 = Asciz	()Ljava/lang/String;;
const #150 = NameAndType	#148:#149;//  toString:()Ljava/lang/String;
const #151 = Method	#136.#150;	//  scala/collection/mutable/StringBuilder.toString:()Ljava/lang/String;
const #152 = Asciz	info;
const #153 = Asciz	(Ljava/lang/String;)V;
const #154 = NameAndType	#152:#153;//  info:(Ljava/lang/String;)V
const #155 = Method	#131.#154;	//  scala/actors/Debug$.info:(Ljava/lang/String;)V
const #156 = Asciz	scala/MatchError;
const #157 = class	#156;	//  scala/MatchError
const #158 = Asciz	scala/Option;
const #159 = class	#158;	//  scala/Option
const #160 = Method	#159.#150;	//  scala/Option.toString:()Ljava/lang/String;
const #161 = NameAndType	#11:#153;//  "<init>":(Ljava/lang/String;)V
const #162 = Method	#157.#161;	//  scala/MatchError."<init>":(Ljava/lang/String;)V
const #163 = Asciz	port;
const #164 = Asciz	cl;
const #165 = Asciz	Ljava/lang/ClassLoader;;
const #166 = Asciz	temp1;
const #167 = Asciz	Lscala/Option;;
const #168 = Asciz	temp2;
const #169 = Asciz	Lscala/Some;;
const #170 = Asciz	temp3;
const #171 = Asciz	Lscala/actors/remote/TcpService;;
const #172 = Asciz	service;
const #173 = Asciz	()Lscala/collection/mutable/HashMap<Ljava/lang/Integer;Lscala/actors/remote/TcpService;>;;
const #174 = Asciz	InnerClasses;
const #175 = Asciz	scala/actors/remote/TcpService$$anonfun$run$1;
const #176 = class	#175;	//  scala/actors/remote/TcpService$$anonfun$run$1
const #177 = Asciz	$anonfun$run$1;
const #178 = Asciz	scala/actors/remote/TcpService$$anonfun$run$2;
const #179 = class	#178;	//  scala/actors/remote/TcpService$$anonfun$run$2
const #180 = Asciz	$anonfun$run$2;
const #181 = Asciz	scala/actors/remote/TcpService$$anonfun$liftedTree1$1$1;
const #182 = class	#181;	//  scala/actors/remote/TcpService$$anonfun$liftedTree1$1$1
const #183 = Asciz	$anonfun$liftedTree1$1$1;
const #184 = Asciz	scala/ScalaObject;
const #185 = class	#184;	//  scala/ScalaObject

{
public static final scala.actors.remote.TcpService$ MODULE$;

public static {};
  Code:
   Stack=1, Locals=0, Args_size=0
   0:	new	#10; //class scala/actors/remote/TcpService$
   3:	invokespecial	#13; //Method "<init>":()V
   6:	return

public void BufSize_$eq(int);
  Code:
   Stack=2, Locals=2, Args_size=2
   0:	aload_0
   1:	iload_1
   2:	putfield	#40; //Field BufSize:I
   5:	return
  LineNumberTable: 
   line 63: 0


public int BufSize();
  Code:
   Stack=1, Locals=1, Args_size=1
   0:	aload_0
   1:	getfield	#40; //Field BufSize:I
   4:	ireturn
  LineNumberTable: 
   line 63: 0


public int generatePort();
  Code:
   Stack=3, Locals=6, Args_size=1
   0:	iconst_0
   1:	istore_1
   2:	aconst_null
   3:	astore_2
   4:	ldc	#45; //int 8000
   6:	aload_0
   7:	invokespecial	#48; //Method random:()Lscala/util/Random;
   10:	ldc	#49; //int 500
   12:	invokevirtual	#53; //Method scala/util/Random.nextInt:(I)I
   15:	iadd
   16:	istore_1
   17:	new	#55; //class java/net/ServerSocket
   20:	dup
   21:	iload_1
   22:	invokespecial	#57; //Method java/net/ServerSocket."<init>":(I)V
   25:	astore	5
   27:	aload	5
   29:	invokevirtual	#60; //Method java/net/ServerSocket.close:()V
   32:	getstatic	#66; //Field scala/runtime/BoxedUnit.UNIT:Lscala/runtime/BoxedUnit;
   35:	astore_2
   36:	goto	57
   39:	astore_3
   40:	getstatic	#66; //Field scala/runtime/BoxedUnit.UNIT:Lscala/runtime/BoxedUnit;
   43:	astore_2
   44:	goto	57
   47:	astore	4
   49:	aload_0
   50:	invokevirtual	#68; //Method generatePort:()I
   53:	invokestatic	#74; //Method scala/runtime/BoxesRunTime.boxToInteger:(I)Ljava/lang/Integer;
   56:	astore_2
   57:	aload_2
   58:	pop
   59:	iload_1
   60:	ireturn
  Exception table:
   from   to  target type
     4    39    47   Class java/io/IOException

     4    39    39   Class java/lang/SecurityException

  LineNumberTable: 
   line 45: 0
   line 46: 3
   line 47: 4
   line 48: 17
   line 49: 27
   line 46: 32
   line 57: 39
   line 52: 47
   line 56: 49
   line 60: 59

  LocalVariableTable: 
   Start  Length  Slot  Name   Signature
   0      61      0    this       Lscala/actors/remote/TcpService$;
   2      58      1    portnum       I
   4      55      2    exceptionResult1       Ljava/lang/Object;
   27      5      5    socket       Ljava/net/ServerSocket;


public scala.actors.remote.TcpService apply(int, java.lang.ClassLoader);
  Code:
   Stack=4, Locals=8, Args_size=3
   0:	aload_0
   1:	invokespecial	#90; //Method ports:()Lscala/collection/mutable/HashMap;
   4:	iload_1
   5:	invokestatic	#74; //Method scala/runtime/BoxesRunTime.boxToInteger:(I)Ljava/lang/Integer;
   8:	invokevirtual	#94; //Method scala/collection/mutable/HashMap.get:(Ljava/lang/Object;)Lscala/Option;
   11:	astore_3
   12:	aload_3
   13:	instanceof	#96; //class scala/Some
   16:	ifeq	40
   19:	aload_3
   20:	checkcast	#96; //class scala/Some
   23:	astore	4
   25:	aload	4
   27:	invokevirtual	#100; //Method scala/Some.x:()Ljava/lang/Object;
   30:	checkcast	#102; //class scala/actors/remote/TcpService
   33:	astore	5
   35:	aload	5
   37:	goto	141
   40:	getstatic	#107; //Field scala/None$.MODULE$:Lscala/None$;
   43:	aload_3
   44:	astore	6
   46:	dup
   47:	ifnonnull	59
   50:	pop
   51:	aload	6
   53:	ifnull	67
   56:	goto	142
   59:	aload	6
   61:	invokevirtual	#111; //Method java/lang/Object.equals:(Ljava/lang/Object;)Z
   64:	ifeq	142
   67:	aload_3
   68:	instanceof	#104; //class scala/None$
   71:	ifeq	142
   74:	new	#102; //class scala/actors/remote/TcpService
   77:	dup
   78:	iload_1
   79:	aload_2
   80:	invokespecial	#114; //Method scala/actors/remote/TcpService."<init>":(ILjava/lang/ClassLoader;)V
   83:	astore	7
   85:	aload_0
   86:	invokespecial	#90; //Method ports:()Lscala/collection/mutable/HashMap;
   89:	getstatic	#119; //Field scala/Predef$Pair$.MODULE$:Lscala/Predef$Pair$;
   92:	iload_1
   93:	invokestatic	#74; //Method scala/runtime/BoxesRunTime.boxToInteger:(I)Ljava/lang/Integer;
   96:	aload	7
   98:	invokevirtual	#122; //Method scala/Predef$Pair$.apply:(Ljava/lang/Object;Ljava/lang/Object;)Lscala/Tuple2;
   101:	invokevirtual	#126; //Method scala/collection/mutable/HashMap.$plus$eq:(Lscala/Tuple2;)Lscala/collection/mutable/HashMap;
   104:	pop
   105:	aload	7
   107:	invokevirtual	#129; //Method scala/actors/remote/TcpService.start:()V
   110:	getstatic	#134; //Field scala/actors/Debug$.MODULE$:Lscala/actors/Debug$;
   113:	new	#136; //class scala/collection/mutable/StringBuilder
   116:	dup
   117:	invokespecial	#137; //Method scala/collection/mutable/StringBuilder."<init>":()V
   120:	ldc	#139; //String created service at 
   122:	invokevirtual	#143; //Method scala/collection/mutable/StringBuilder.append:(Ljava/lang/Object;)Lscala/collection/mutable/StringBuilder;
   125:	aload	7
   127:	invokevirtual	#147; //Method scala/actors/remote/TcpService.node:()Lscala/actors/remote/Node;
   130:	invokevirtual	#143; //Method scala/collection/mutable/StringBuilder.append:(Ljava/lang/Object;)Lscala/collection/mutable/StringBuilder;
   133:	invokevirtual	#151; //Method scala/collection/mutable/StringBuilder.toString:()Ljava/lang/String;
   136:	invokevirtual	#155; //Method scala/actors/Debug$.info:(Ljava/lang/String;)V
   139:	aload	7
   141:	areturn
   142:	new	#157; //class scala/MatchError
   145:	dup
   146:	aload_3
   147:	invokevirtual	#160; //Method scala/Option.toString:()Ljava/lang/String;
   150:	invokespecial	#162; //Method scala/MatchError."<init>":(Ljava/lang/String;)V
   153:	athrow
  LineNumberTable: 
   line 33: 0
   line 34: 35
   line 33: 40
   line 37: 74
   line 38: 85
   line 39: 105
   line 40: 110
   line 41: 139
   line 33: 141

  LocalVariableTable: 
   Start  Length  Slot  Name   Signature
   0      154      0    this       Lscala/actors/remote/TcpService$;
   0      154      1    port       I
   0      154      2    cl       Ljava/lang/ClassLoader;
   12      142      3    temp1       Lscala/Option;
   25      12      4    temp2       Lscala/Some;
   35      2      5    temp3       Lscala/actors/remote/TcpService;
   85      56      7    service       Lscala/actors/remote/TcpService;


}

