Compiled from "TcpService.scala"
public final class scala.actors.remote.TcpService$$anonfun$liftedTree1$1$1 extends java.lang.Object implements scala.Function1,scala.ScalaObject,java.io.Serializable
  SourceFile: "TcpService.scala"
  Scala: length = 0x
   
  InnerClass: 
   public final $anonfun$liftedTree1$1$1=class scala/actors/remote/TcpService$$anonfun$liftedTree1$1$1 of class scala/actors/remote/TcpService
  minor version: 0
  major version: 49
  Constant pool:
Asciz	SourceFile;
Asciz	TcpService.scala;
Asciz	<clinit>;
Asciz	()V;
Asciz	Code;
Asciz	serialVersionUID;
Asciz	J;
Asciz	scala/actors/remote/TcpService$$anonfun$liftedTree1$1$1;
class	scala/actors/remote/TcpService$$anonfun$liftedTree1$1$1
NameAndType	serialVersionUID:J
Field	scala/actors/remote/TcpService$$anonfun$liftedTree1$1$1.serialVersionUID:J
Asciz	newWorker$1;
Asciz	Lscala/actors/remote/TcpServiceWorker;;
Asciz	<init>;
Asciz	(Lscala/actors/remote/TcpService;Lscala/actors/remote/TcpServiceWorker;)V;
Asciz	LineNumberTable;
NameAndType	newWorker$1:Lscala/actors/remote/TcpServiceWorker;
Field	scala/actors/remote/TcpService$$anonfun$liftedTree1$1$1.newWorker$1:Lscala/actors/remote/TcpServiceWorker;
Asciz	java/lang/Object;
class	java/lang/Object
NameAndType	"<init>":()V
Method	java/lang/Object."<init>":()V
Asciz	scala/Function1$class;
class	scala/Function1$class
Asciz	$init$;
Asciz	(Lscala/Function1;)V;
NameAndType	$init$:(Lscala/Function1;)V
Method	scala/Function1$class.$init$:(Lscala/Function1;)V
Asciz	this;
Asciz	Lscala/actors/remote/TcpService$$anonfun$liftedTree1$1$1;;
Asciz	$outer;
Asciz	Lscala/actors/remote/TcpService;;
Asciz	LocalVariableTable;
Asciz	apply;
Asciz	(Ljava/lang/Object;)Ljava/lang/Object;;
Asciz	[B;
class	"[B"
Asciz	([B)V;
NameAndType	apply:([B)V
Method	scala/actors/remote/TcpService$$anonfun$liftedTree1$1$1.apply:([B)V
Asciz	scala/runtime/BoxedUnit;
class	scala/runtime/BoxedUnit
Asciz	UNIT;
Asciz	Lscala/runtime/BoxedUnit;;
NameAndType	UNIT:Lscala/runtime/BoxedUnit;
Field	scala/runtime/BoxedUnit.UNIT:Lscala/runtime/BoxedUnit;
Asciz	v1;
Asciz	Ljava/lang/Object;;
Asciz	scala/actors/remote/TcpServiceWorker;
class	scala/actors/remote/TcpServiceWorker
Asciz	transmit;
NameAndType	transmit:([B)V
Method	scala/actors/remote/TcpServiceWorker.transmit:([B)V
Asciz	andThen;
Asciz	(Lscala/Function1;)Lscala/Function1;;
Asciz	(Lscala/Function1;Lscala/Function1;)Lscala/Function1;;
NameAndType	andThen:(Lscala/Function1;Lscala/Function1;)Lscala/Function1;
Method	scala/Function1$class.andThen:(Lscala/Function1;Lscala/Function1;)Lscala/Function1;
Asciz	g;
Asciz	Lscala/Function1;;
Asciz	compose;
NameAndType	compose:(Lscala/Function1;Lscala/Function1;)Lscala/Function1;
Method	scala/Function1$class.compose:(Lscala/Function1;Lscala/Function1;)Lscala/Function1;
Asciz	toString;
Asciz	()Ljava/lang/String;;
Asciz	(Lscala/Function1;)Ljava/lang/String;;
NameAndType	toString:(Lscala/Function1;)Ljava/lang/String;
Method	scala/Function1$class.toString:(Lscala/Function1;)Ljava/lang/String;
Asciz	Scala;
Asciz	InnerClasses;
Asciz	scala/actors/remote/TcpService;
class	scala/actors/remote/TcpService
Asciz	$anonfun$liftedTree1$1$1;
Asciz	scala/Function1;
class	scala/Function1
Asciz	scala/ScalaObject;
class	scala/ScalaObject
Asciz	java/io/Serializable;
class	java/io/Serializable

{
public static final long serialVersionUID;
  Signature: J

private final scala.actors.remote.TcpServiceWorker newWorker$1;
  Signature: Lscala/actors/remote/TcpServiceWorker;

public static {};
  Signature: ()V
  Code:
   Stack=2, Locals=0, Args_size=0
	lconst_0
	putstatic	Field serialVersionUID:J
	return
  Labels:

public scala.actors.remote.TcpService$$anonfun$liftedTree1$1$1(scala.actors.remote.TcpService, scala.actors.remote.TcpServiceWorker);
  Signature: (Lscala/actors/remote/TcpService;Lscala/actors/remote/TcpServiceWorker;)V
  Code:
   Stack=2, Locals=3, Args_size=3
	aload_0
	aload_2
	putfield	Field newWorker$1:Lscala/actors/remote/TcpServiceWorker;
	aload_0
	invokespecial	Method java/lang/Object."<init>":()V
	aload_0
	invokestatic	Method scala/Function1$class.$init$:(Lscala/Function1;)V
	return
  Labels:
  LocalVariableTable: 
   Start  Length  Slot  Name   Signature
   0      14      0    this       Lscala/actors/remote/TcpService$$anonfun$liftedTree1$1$1;
   0      14      1    $outer       Lscala/actors/remote/TcpService;


public final java.lang.Object apply(java.lang.Object);
  Signature: (Ljava/lang/Object;)Ljava/lang/Object;
  Code:
   Stack=2, Locals=2, Args_size=2
	aload_0
	aload_1
	checkcast	class "[B"
	invokevirtual	Method apply:([B)V
	getstatic	Field scala/runtime/BoxedUnit.UNIT:Lscala/runtime/BoxedUnit;
	areturn
  Labels:
  LocalVariableTable: 
   Start  Length  Slot  Name   Signature
   0      12      0    this       Lscala/actors/remote/TcpService$$anonfun$liftedTree1$1$1;
   0      12      1    v1       Ljava/lang/Object;


public final void apply(byte[]);
  Signature: ([B)V
  Code:
   Stack=2, Locals=2, Args_size=2
	aload_0
	getfield	Field newWorker$1:Lscala/actors/remote/TcpServiceWorker;
	aload_1
	invokevirtual	Method scala/actors/remote/TcpServiceWorker.transmit:([B)V
	return
  Labels:

public scala.Function1 andThen(scala.Function1);
  Signature: (Lscala/Function1;)Lscala/Function1;
  Code:
   Stack=2, Locals=2, Args_size=2
	aload_0
	aload_1
	invokestatic	Method scala/Function1$class.andThen:(Lscala/Function1;Lscala/Function1;)Lscala/Function1;
	areturn
  Labels:
  LocalVariableTable: 
   Start  Length  Slot  Name   Signature
   0      6      0    this       Lscala/actors/remote/TcpService$$anonfun$liftedTree1$1$1;
   0      6      1    g       Lscala/Function1;


public scala.Function1 compose(scala.Function1);
  Signature: (Lscala/Function1;)Lscala/Function1;
  Code:
   Stack=2, Locals=2, Args_size=2
	aload_0
	aload_1
	invokestatic	Method scala/Function1$class.compose:(Lscala/Function1;Lscala/Function1;)Lscala/Function1;
	areturn
  Labels:
  LocalVariableTable: 
   Start  Length  Slot  Name   Signature
   0      6      0    this       Lscala/actors/remote/TcpService$$anonfun$liftedTree1$1$1;
   0      6      1    g       Lscala/Function1;


public java.lang.String toString();
  Signature: ()Ljava/lang/String;
  Code:
   Stack=1, Locals=1, Args_size=1
	aload_0
	invokestatic	Method scala/Function1$class.toString:(Lscala/Function1;)Ljava/lang/String;
	areturn
  Labels:

}

