Compiled from "TcpService.scala"
public class scala.actors.remote.TcpService extends java.lang.Thread implements scala.actors.remote.Service,scala.ScalaObject
  SourceFile: "TcpService.scala"
  ScalaSig: length = 0x5E9
   05 00 FFFFFF81 4D 07 05 01 02 FFFFFF88 02 09 01 0A 54 63 70
   53 65 72 76 69 63 65 0A 02 03 04 01 06 72 65 6D
   6F 74 65 0A 02 05 06 01 06 61 63 74 6F 72 73 0A
   01 07 01 05 73 63 61 6C 61 03 00 10 02 0A 0B 0D
   01 02 06 08 0C 02 FFFFFF84 FFFFFF80 FFFFFF80 FFFFFF88 02 0D 02 0A 54 63
   70 53 65 72 76 69 63 65 13 03 0B 0E 16 10 02 0F
   14 0D 01 10 0A 02 11 12 01 04 6C 61 6E 67 0A 01
   13 01 04 6A 61 76 61 09 02 15 10 02 06 4F 62 6A
   65 63 74 10 02 17 18 0D 01 06 09 02 19 06 02 0B
   53 63 61 6C 61 4F 62 6A 65 63 74 08 05 1B 0B FFFFFF84
   00 1C 01 06 3C 69 6E 69 74 3E 14 01 09 08 07 1E
   0B FFFFFFC2 FFFFFF80 FFFFFF84 04 1F 01 06 72 61 6E 64 6F 6D 15 01
   20 10 02 21 24 0D 01 22 0A 02 23 06 01 04 75 74
   69 6C 09 02 25 22 02 06 52 61 6E 64 6F 6D 08 06
   27 0B FFFFFFA0 FFFFFF80 04 20 01 07 72 61 6E 64 6F 6D 20 08
   07 29 0B FFFFFFC2 FFFFFF80 FFFFFF84 04 2A 01 05 70 6F 72 74 73 15
   01 2B 10 04 2C 31 33 36 0D 01 2D 0A 02 2E 2F 01
   07 6D 75 74 61 62 6C 65 0A 02 30 06 01 0A 63 6F
   6C 6C 65 63 74 69 6F 6E 09 02 32 2D 02 07 48 61
   73 68 4D 61 70 10 02 17 34 09 02 35 06 02 03 49
   6E 74 10 02 0A 37 06 08 0C 02 FFFFFF84 FFFFFF80 FFFFFF80 FFFFFF80 00 38
   13 04 37 39 3C 16 10 02 0F 3A 09 02 3B 10 02 06
   54 68 72 65 61 64 10 02 0A 3D 09 02 3E 02 02 07
   53 65 72 76 69 63 65 08 08 40 37 FFFFFF82 FFFFFF80 FFFFFFA0 FFFFFF80 04
   33 01 04 70 6F 72 74 08 08 42 37 FFFFFF82 FFFFFF80 FFFFFFA0 FFFFFF80 04
   43 01 02 63 6C 10 02 0F 44 09 02 45 10 02 0B 43
   6C 61 73 73 4C 6F 61 64 65 72 08 05 1B 37 FFFFFF84 00
   47 14 03 36 48 49 08 05 40 46 FFFFFFC0 00 33 08 05 42
   46 FFFFFFC0 00 43 08 07 4B 37 FFFFFFC2 FFFFFF80 FFFFFF84 00 4C 01 0A 73
   65 72 69 61 6C 69 7A 65 72 15 01 4D 10 02 0A 4E
   09 02 4F 02 02 0E 4A 61 76 61 53 65 72 69 61 6C
   69 7A 65 72 08 06 51 37 FFFFFFA0 FFFFFF80 04 4D 01 0B 73 65
   72 69 61 6C 69 7A 65 72 20 08 07 53 37 FFFFFFC2 FFFFFF80 FFFFFF84
   04 54 01 0C 69 6E 74 65 72 6E 61 6C 4E 6F 64 65
   15 01 55 10 02 0A 56 09 02 57 02 02 04 4E 6F 64
   65 08 06 59 37 FFFFFFA0 FFFFFF80 04 55 01 0D 69 6E 74 65 72
   6E 61 6C 4E 6F 64 65 20 08 05 5B 37 FFFFFF84 00 54 01
   04 6E 6F 64 65 08 07 5D 37 FFFFFFC2 FFFFFF80 FFFFFF84 04 5E 01 0C
   70 65 6E 64 69 6E 67 53 65 6E 64 73 15 01 5F 10
   04 2C 31 55 60 10 03 61 69 6C 0E 02 62 67 0E 02
   63 66 0D 01 64 0A 02 65 08 01 06 3C 72 6F 6F 74
   3E 09 01 07 09 02 68 06 01 07 70 61 63 6B 61 67
   65 09 02 6A 6B 02 04 4C 69 73 74 0A 02 68 06 10
   03 17 6D 6F 09 02 6E 06 02 05 41 72 72 61 79 10
   02 17 70 09 02 71 06 02 04 42 79 74 65 08 06 73
   37 FFFFFFA0 FFFFFF80 04 5F 01 0D 70 65 6E 64 69 6E 67 53 65
   6E 64 73 20 08 05 75 37 FFFFFF84 00 76 01 04 73 65 6E
   64 14 03 77 7A 7B 10 02 17 78 09 02 79 06 02 04
   55 6E 69 74 08 05 5B 74 FFFFFFC0 00 55 08 05 7C 74 FFFFFFC0
   00 6C 01 04 64 61 74 61 08 05 7E 37 FFFFFF84 00 7F 01
   09 74 65 72 6D 69 6E 61 74 65 14 01 77 08 09 FFFFFF81
   01 37 FFFFFFC0 FFFFFF80 FFFFFF84 04 FFFFFF81 02 01 0F 73 68 6F 75 6C 64
   54 65 72 6D 69 6E 61 74 65 15 02 FFFFFF81 03 10 03 17
   FFFFFF81 04 09 03 FFFFFF81 05 06 02 07 42 6F 6F 6C 65 61 6E
   08 09 FFFFFF81 07 37 FFFFFFC0 FFFFFF80 FFFFFF84 04 FFFFFF81 08 01 13 73 68 6F
   75 6C 64 54 65 72 6D 69 6E 61 74 65 5F 24 65 71
   14 03 77 FFFFFF81 09 08 0A FFFFFF81 0A FFFFFF81 06 FFFFFF81 FFFFFF80 FFFFFFC0 00 FFFFFF81
   03 01 03 78 24 31 08 08 FFFFFF81 0C 37 FFFFFFA0 FFFFFFA0 04 FFFFFF81 03
   01 10 73 68 6F 75 6C 64 54 65 72 6D 69 6E 61 74
   65 20 08 06 FFFFFF81 0E 37 FFFFFF84 20 7F 01 03 72 75 6E 08
   09 FFFFFF81 10 37 FFFFFFC2 FFFFFF80 FFFFFF84 04 FFFFFF81 11 01 0B 63 6F 6E 6E
   65 63 74 69 6F 6E 73 15 02 FFFFFF81 12 10 05 2C 31 55
   FFFFFF81 13 10 03 0A FFFFFF81 14 09 03 FFFFFF81 15 02 02 10 54 63
   70 53 65 72 76 69 63 65 57 6F 72 6B 65 72 08 08
   FFFFFF81 17 37 FFFFFFA0 FFFFFF80 04 FFFFFF81 12 01 0C 63 6F 6E 6E 65 63
   74 69 6F 6E 73 20 08 08 FFFFFF81 19 37 FFFFFF84 00 04 FFFFFF81 1A
   01 0D 61 64 64 43 6F 6E 6E 65 63 74 69 6F 6E 14
   06 FFFFFF81 12 FFFFFF81 1B FFFFFF81 1C 08 06 5B FFFFFF81 18 FFFFFFC0 00 55 08
   08 FFFFFF81 1D FFFFFF81 18 FFFFFFC0 00 FFFFFF81 13 01 06 77 6F 72 6B 65
   72 08 07 FFFFFF81 1F 37 FFFFFF84 00 FFFFFF81 20 01 0D 67 65 74 43
   6F 6E 6E 65 63 74 69 6F 6E 14 04 FFFFFF81 21 FFFFFF81 24 10
   05 17 FFFFFF81 22 FFFFFF81 13 09 03 FFFFFF81 23 06 02 06 4F 70 74
   69 6F 6E 08 07 FFFFFF81 25 FFFFFF81 1E FFFFFFC0 00 55 01 01 6E 08
   07 FFFFFF81 27 37 FFFFFF84 00 FFFFFF81 28 01 0B 69 73 43 6F 6E 6E
   65 63 74 65 64 14 04 FFFFFF81 03 FFFFFF81 29 08 07 FFFFFF81 25 FFFFFF81
   26 FFFFFFC0 00 55 08 07 FFFFFF81 2B 37 FFFFFF84 00 FFFFFF81 2C 01 07 63
   6F 6E 6E 65 63 74 14 04 FFFFFF81 13 FFFFFF81 2D 08 07 FFFFFF81 25
   FFFFFF81 2A FFFFFFC0 00 55 08 07 FFFFFF81 2F 37 FFFFFF84 00 FFFFFF81 30 01 0E
   64 69 73 63 6F 6E 6E 65 63 74 4E 6F 64 65 14 03
   77 FFFFFF81 31 08 07 FFFFFF81 25 FFFFFF81 2E FFFFFFC0 00 55 08 07 FFFFFF81 33
   37 FFFFFF84 00 FFFFFF81 34 01 0B 69 73 52 65 61 63 68 61 62
   6C 65 14 04 FFFFFF81 03 FFFFFF81 35 08 06 5B FFFFFF81 32 FFFFFFC0 00 55
   08 07 FFFFFF81 37 37 FFFFFF84 00 FFFFFF81 38 01 08 6E 6F 64 65 44
   6F 77 6E 14 03 77 FFFFFF81 39 08 07 FFFFFF81 3A FFFFFF81 36 FFFFFFC0 00
   55 01 05 6D 6E 6F 64 65 08 07 FFFFFF81 3C 0B FFFFFFA0 FFFFFF80 04
   2B 01 06 70 6F 72 74 73 20 08 07 FFFFFF81 3E 0B FFFFFF84 00
   FFFFFF81 3F 01 05 61 70 70 6C 79 14 05 36 FFFFFF81 40 FFFFFF81 41
   08 06 40 FFFFFF81 3D FFFFFFC0 00 33 08 06 42 FFFFFF81 3D FFFFFFC0 00 43
   08 07 FFFFFF81 43 0B FFFFFF84 00 FFFFFF81 44 01 0C 67 65 6E 65 72
   61 74 65 50 6F 72 74 15 01 33 08 09 FFFFFF81 46 0B FFFFFFC0
   FFFFFF80 FFFFFF84 00 FFFFFF81 44 01 07 42 75 66 53 69 7A 65 08 09
   FFFFFF81 48 0B FFFFFFC0 FFFFFF80 FFFFFF84 00 FFFFFF81 49 01 0B 42 75 66 53 69
   7A 65 5F 24 65 71 14 03 77 FFFFFF81 4A 08 09 FFFFFF81 0A FFFFFF81
   47 FFFFFF81 FFFFFF80 FFFFFFC0 00 33 08 07 FFFFFF81 4C 0B FFFFFFA0 FFFFFFA0 04 33 01
   08 42 75 66 53 69 7A 65 20 
  InnerClass: 
   public final $anonfun$run$1=class scala/actors/remote/TcpService$$anonfun$run$1 of class scala/actors/remote/TcpService
   public final $anonfun$liftedTree1$1$1=class scala/actors/remote/TcpService$$anonfun$liftedTree1$1$1 of class scala/actors/remote/TcpService
  minor version: 0
  major version: 49
  Constant pool:
Asciz	SourceFile;
Asciz	TcpService.scala;
Asciz	BufSize_$eq;
Asciz	(I)V;
Asciz	Code;
Asciz	scala/actors/remote/TcpService$;
class	scala/actors/remote/TcpService$
Asciz	MODULE$;
Asciz	Lscala/actors/remote/TcpService$;;
NameAndType	MODULE$:Lscala/actors/remote/TcpService$;
Field	scala/actors/remote/TcpService$.MODULE$:Lscala/actors/remote/TcpService$;
NameAndType	BufSize_$eq:(I)V
Method	scala/actors/remote/TcpService$.BufSize_$eq:(I)V
Asciz	BufSize;
Asciz	()I;
NameAndType	BufSize:()I
Method	scala/actors/remote/TcpService$.BufSize:()I
Asciz	generatePort;
NameAndType	generatePort:()I
Method	scala/actors/remote/TcpService$.generatePort:()I
Asciz	apply;
Asciz	(ILjava/lang/ClassLoader;)Lscala/actors/remote/TcpService;;
NameAndType	apply:(ILjava/lang/ClassLoader;)Lscala/actors/remote/TcpService;
Method	scala/actors/remote/TcpService$.apply:(ILjava/lang/ClassLoader;)Lscala/actors/remote/TcpService;
Asciz	kernel;
Asciz	Lscala/actors/remote/NetKernel;;
Asciz	connections;
Asciz	Lscala/collection/mutable/HashMap;;
Asciz	Lscala/collection/mutable/HashMap<Lscala/actors/remote/Node;Lscala/actors/remote/TcpServiceWorker;>;;
Asciz	Signature;
Asciz	shouldTerminate;
Asciz	Z;
Asciz	pendingSends;
Asciz	Lscala/collection/mutable/HashMap<Lscala/actors/remote/Node;Lscala/collection/immutable/List<[B>;>;;
Asciz	internalNode;
Asciz	Lscala/actors/remote/Node;;
Asciz	serializer;
Asciz	Lscala/actors/remote/JavaSerializer;;
Asciz	port;
Asciz	I;
Asciz	<init>;
Asciz	(ILjava/lang/ClassLoader;)V;
Asciz	LineNumberTable;
Asciz	scala/actors/remote/TcpService;
class	scala/actors/remote/TcpService
NameAndType	port:I
Field	scala/actors/remote/TcpService.port:I
Asciz	java/lang/Thread;
class	java/lang/Thread
Asciz	()V;
NameAndType	"<init>":()V
Method	java/lang/Thread."<init>":()V
Asciz	scala/actors/remote/Service$class;
class	scala/actors/remote/Service$class
Asciz	$init$;
Asciz	(Lscala/actors/remote/Service;)V;
NameAndType	$init$:(Lscala/actors/remote/Service;)V
Method	scala/actors/remote/Service$class.$init$:(Lscala/actors/remote/Service;)V
Asciz	scala/actors/remote/JavaSerializer;
class	scala/actors/remote/JavaSerializer
Asciz	(Lscala/actors/remote/Service;Ljava/lang/ClassLoader;)V;
NameAndType	"<init>":(Lscala/actors/remote/Service;Ljava/lang/ClassLoader;)V
Method	scala/actors/remote/JavaSerializer."<init>":(Lscala/actors/remote/Service;Ljava/lang/ClassLoader;)V
NameAndType	serializer:Lscala/actors/remote/JavaSerializer;
Field	scala/actors/remote/TcpService.serializer:Lscala/actors/remote/JavaSerializer;
Asciz	scala/actors/remote/Node;
class	scala/actors/remote/Node
Asciz	java/net/InetAddress;
class	java/net/InetAddress
Asciz	getLocalHost;
Asciz	()Ljava/net/InetAddress;;
NameAndType	getLocalHost:()Ljava/net/InetAddress;
Method	java/net/InetAddress.getLocalHost:()Ljava/net/InetAddress;
Asciz	getHostAddress;
Asciz	()Ljava/lang/String;;
NameAndType	getHostAddress:()Ljava/lang/String;
Method	java/net/InetAddress.getHostAddress:()Ljava/lang/String;
Asciz	(Ljava/lang/String;I)V;
NameAndType	"<init>":(Ljava/lang/String;I)V
Method	scala/actors/remote/Node."<init>":(Ljava/lang/String;I)V
NameAndType	internalNode:Lscala/actors/remote/Node;
Field	scala/actors/remote/TcpService.internalNode:Lscala/actors/remote/Node;
Asciz	scala/collection/mutable/HashMap;
class	scala/collection/mutable/HashMap
Method	scala/collection/mutable/HashMap."<init>":()V
NameAndType	pendingSends:Lscala/collection/mutable/HashMap;
Field	scala/actors/remote/TcpService.pendingSends:Lscala/collection/mutable/HashMap;
NameAndType	shouldTerminate:Z
Field	scala/actors/remote/TcpService.shouldTerminate:Z
NameAndType	connections:Lscala/collection/mutable/HashMap;
Field	scala/actors/remote/TcpService.connections:Lscala/collection/mutable/HashMap;
Asciz	this;
Asciz	Lscala/actors/remote/TcpService;;
Asciz	cl;
Asciz	Ljava/lang/ClassLoader;;
Asciz	LocalVariableTable;
Asciz	liftedTree1$1;
Asciz	(Lscala/actors/remote/Node;[B)Ljava/lang/Object;;
Asciz	connect;
Asciz	(Lscala/actors/remote/Node;)Lscala/actors/remote/TcpServiceWorker;;
NameAndType	connect:(Lscala/actors/remote/Node;)Lscala/actors/remote/TcpServiceWorker;
Method	scala/actors/remote/TcpService.connect:(Lscala/actors/remote/Node;)Lscala/actors/remote/TcpServiceWorker;
Asciz	scala/actors/remote/TcpServiceWorker;
class	scala/actors/remote/TcpServiceWorker
Asciz	transmit;
Asciz	([B)V;
NameAndType	transmit:([B)V
Method	scala/actors/remote/TcpServiceWorker.transmit:([B)V
Asciz	()Lscala/collection/mutable/HashMap;;
NameAndType	pendingSends:()Lscala/collection/mutable/HashMap;
Method	scala/actors/remote/TcpService.pendingSends:()Lscala/collection/mutable/HashMap;
Asciz	get;
Asciz	(Ljava/lang/Object;)Lscala/Option;;
NameAndType	get:(Ljava/lang/Object;)Lscala/Option;
Method	scala/collection/mutable/HashMap.get:(Ljava/lang/Object;)Lscala/Option;
Asciz	scala/None$;
class	scala/None$
Asciz	Lscala/None$;;
NameAndType	MODULE$:Lscala/None$;
Field	scala/None$.MODULE$:Lscala/None$;
Asciz	java/lang/Object;
class	java/lang/Object
Asciz	equals;
Asciz	(Ljava/lang/Object;)Z;
NameAndType	equals:(Ljava/lang/Object;)Z
Method	java/lang/Object.equals:(Ljava/lang/Object;)Z
Asciz	scala/runtime/BoxedUnit;
class	scala/runtime/BoxedUnit
Asciz	UNIT;
Asciz	Lscala/runtime/BoxedUnit;;
NameAndType	UNIT:Lscala/runtime/BoxedUnit;
Field	scala/runtime/BoxedUnit.UNIT:Lscala/runtime/BoxedUnit;
Asciz	scala/Some;
class	scala/Some
Asciz	x;
Asciz	()Ljava/lang/Object;;
NameAndType	x:()Ljava/lang/Object;
Method	scala/Some.x:()Ljava/lang/Object;
Asciz	scala/collection/immutable/List;
class	scala/collection/immutable/List
Asciz	scala/actors/remote/TcpService$$anonfun$liftedTree1$1$1;
class	scala/actors/remote/TcpService$$anonfun$liftedTree1$1$1
Asciz	(Lscala/actors/remote/TcpService;Lscala/actors/remote/TcpServiceWorker;)V;
NameAndType	"<init>":(Lscala/actors/remote/TcpService;Lscala/actors/remote/TcpServiceWorker;)V
Method	scala/actors/remote/TcpService$$anonfun$liftedTree1$1$1."<init>":(Lscala/actors/remote/TcpService;Lscala/actors/remote/TcpServiceWorker;)V
Asciz	scala/collection/LinearSeqLike;
class	scala/collection/LinearSeqLike
Asciz	foreach;
Asciz	(Lscala/Function1;)V;
NameAndType	foreach:(Lscala/Function1;)V
InterfaceMethod	scala/collection/LinearSeqLike.foreach:(Lscala/Function1;)V
Asciz	$minus$eq;
Asciz	(Ljava/lang/Object;)Lscala/collection/mutable/HashMap;;
NameAndType	$minus$eq:(Ljava/lang/Object;)Lscala/collection/mutable/HashMap;
Method	scala/collection/mutable/HashMap.$minus$eq:(Ljava/lang/Object;)Lscala/collection/mutable/HashMap;
Asciz	scala/MatchError;
class	scala/MatchError
Asciz	scala/Option;
class	scala/Option
Asciz	toString;
NameAndType	toString:()Ljava/lang/String;
Method	scala/Option.toString:()Ljava/lang/String;
Asciz	(Ljava/lang/String;)V;
NameAndType	"<init>":(Ljava/lang/String;)V
Method	scala/MatchError."<init>":(Ljava/lang/String;)V
Asciz	bufferMsg$1;
Asciz	(Ljava/lang/Throwable;Lscala/actors/remote/Node;[B)V;
NameAndType	bufferMsg$1:(Ljava/lang/Throwable;Lscala/actors/remote/Node;[B)V
Method	scala/actors/remote/TcpService.bufferMsg$1:(Ljava/lang/Throwable;Lscala/actors/remote/Node;[B)V
Asciz	java/net/UnknownHostException;
class	java/net/UnknownHostException
Asciz	java/io/IOException;
class	java/io/IOException
Asciz	java/lang/SecurityException;
class	java/lang/SecurityException
Asciz	temp11;
Asciz	Lscala/Some;;
Asciz	temp12;
Asciz	Lscala/collection/immutable/List;;
Asciz	newWorker$1;
Asciz	Lscala/actors/remote/TcpServiceWorker;;
Asciz	temp9;
Asciz	Lscala/Option;;
Asciz	exceptionResult3;
Asciz	Ljava/lang/Object;;
Asciz	scala/Predef$Pair$;
class	scala/Predef$Pair$
Asciz	Lscala/Predef$Pair$;;
NameAndType	MODULE$:Lscala/Predef$Pair$;
Field	scala/Predef$Pair$.MODULE$:Lscala/Predef$Pair$;
Asciz	scala/collection/immutable/List$;
class	scala/collection/immutable/List$
Asciz	Lscala/collection/immutable/List$;;
NameAndType	MODULE$:Lscala/collection/immutable/List$;
Field	scala/collection/immutable/List$.MODULE$:Lscala/collection/immutable/List$;
Asciz	scala/Predef$;
class	scala/Predef$
Asciz	Lscala/Predef$;;
NameAndType	MODULE$:Lscala/Predef$;
Field	scala/Predef$.MODULE$:Lscala/Predef$;
Asciz	[B;
class	"[B"
Asciz	[Ljava/lang/Object;;
class	"[Ljava/lang/Object;"
Asciz	wrapRefArray;
Asciz	([Ljava/lang/Object;)Lscala/collection/mutable/WrappedArray;;
NameAndType	wrapRefArray:([Ljava/lang/Object;)Lscala/collection/mutable/WrappedArray;
Method	scala/Predef$.wrapRefArray:([Ljava/lang/Object;)Lscala/collection/mutable/WrappedArray;
Asciz	(Lscala/collection/Seq;)Lscala/collection/immutable/List;;
NameAndType	apply:(Lscala/collection/Seq;)Lscala/collection/immutable/List;
Method	scala/collection/immutable/List$.apply:(Lscala/collection/Seq;)Lscala/collection/immutable/List;
Asciz	(Ljava/lang/Object;Ljava/lang/Object;)Lscala/Tuple2;;
NameAndType	apply:(Ljava/lang/Object;Ljava/lang/Object;)Lscala/Tuple2;
Method	scala/Predef$Pair$.apply:(Ljava/lang/Object;Ljava/lang/Object;)Lscala/Tuple2;
Asciz	$plus$eq;
Asciz	(Lscala/Tuple2;)Lscala/collection/mutable/HashMap;;
NameAndType	$plus$eq:(Lscala/Tuple2;)Lscala/collection/mutable/HashMap;
Method	scala/collection/mutable/HashMap.$plus$eq:(Lscala/Tuple2;)Lscala/collection/mutable/HashMap;
Asciz	gd1$1;
Asciz	(Lscala/collection/immutable/List;)Z;
NameAndType	gd1$1:(Lscala/collection/immutable/List;)Z
Method	scala/actors/remote/TcpService.gd1$1:(Lscala/collection/immutable/List;)Z
Asciz	$colon$colon;
Asciz	(Ljava/lang/Object;)Lscala/collection/immutable/List;;
NameAndType	$colon$colon:(Ljava/lang/Object;)Lscala/collection/immutable/List;
Method	scala/collection/immutable/List.$colon$colon:(Ljava/lang/Object;)Lscala/collection/immutable/List;
Asciz	t;
Asciz	Ljava/lang/Throwable;;
Asciz	temp7;
Asciz	temp8;
Asciz	temp5;
Asciz	length;
NameAndType	length:()I
InterfaceMethod	scala/collection/LinearSeqLike.length:()I
Asciz	()Lscala/actors/remote/Serializer;;
Asciz	()Lscala/actors/remote/JavaSerializer;;
NameAndType	serializer:()Lscala/actors/remote/JavaSerializer;
Method	scala/actors/remote/TcpService.serializer:()Lscala/actors/remote/JavaSerializer;
Asciz	nodeDown;
Asciz	(Lscala/actors/remote/Node;)V;
NameAndType	connections:()Lscala/collection/mutable/HashMap;
Method	scala/actors/remote/TcpService.connections:()Lscala/collection/mutable/HashMap;
Asciz	mnode;
Asciz	isReachable;
Asciz	(Lscala/actors/remote/Node;)Z;
Asciz	isConnected;
NameAndType	isConnected:(Lscala/actors/remote/Node;)Z
Method	scala/actors/remote/TcpService.isConnected:(Lscala/actors/remote/Node;)Z
Asciz	node;
Asciz	exceptionResult2;
Asciz	disconnectNode;
Asciz	halt;
NameAndType	halt:()V
Method	scala/actors/remote/TcpServiceWorker.halt:()V
Asciz	n;
Asciz	temp22;
Asciz	temp23;
Asciz	temp20;
Asciz	java/net/Socket;
class	java/net/Socket
Asciz	address;
NameAndType	address:()Ljava/lang/String;
Method	scala/actors/remote/Node.address:()Ljava/lang/String;
NameAndType	port:()I
Method	scala/actors/remote/Node.port:()I
Method	java/net/Socket."<init>":(Ljava/lang/String;I)V
Asciz	(Lscala/actors/remote/TcpService;Ljava/net/Socket;)V;
NameAndType	"<init>":(Lscala/actors/remote/TcpService;Ljava/net/Socket;)V
Method	scala/actors/remote/TcpServiceWorker."<init>":(Lscala/actors/remote/TcpService;Ljava/net/Socket;)V
Asciz	sendNode;
NameAndType	sendNode:(Lscala/actors/remote/Node;)V
Method	scala/actors/remote/TcpServiceWorker.sendNode:(Lscala/actors/remote/Node;)V
Asciz	start;
NameAndType	start:()V
Method	scala/actors/remote/TcpServiceWorker.start:()V
Asciz	addConnection;
Asciz	(Lscala/actors/remote/Node;Lscala/actors/remote/TcpServiceWorker;)Lscala/collection/mutable/HashMap;;
NameAndType	addConnection:(Lscala/actors/remote/Node;Lscala/actors/remote/TcpServiceWorker;)Lscala/collection/mutable/HashMap;
Method	scala/actors/remote/TcpService.addConnection:(Lscala/actors/remote/Node;Lscala/actors/remote/TcpServiceWorker;)Lscala/collection/mutable/HashMap;
Asciz	socket;
Asciz	Ljava/net/Socket;;
Asciz	worker;
Asciz	isEmpty;
Asciz	()Z;
NameAndType	isEmpty:()Z
Method	scala/Option.isEmpty:()Z
Asciz	getConnection;
Asciz	(Lscala/actors/remote/Node;)Lscala/Option;;
Asciz	(Lscala/actors/remote/Node;)Lscala/Option<Lscala/actors/remote/TcpServiceWorker;>;;
Asciz	(Lscala/actors/remote/Node;Lscala/actors/remote/TcpServiceWorker;)Lscala/collection/mutable/HashMap<Lscala/actors/remote/Node;Lscala/actors/remote/TcpServiceWorker;>;;
Asciz	()Lscala/collection/mutable/HashMap<Lscala/actors/remote/Node;Lscala/actors/remote/TcpServiceWorker;>;;
Asciz	run;
Asciz	java/net/ServerSocket;
class	java/net/ServerSocket
NameAndType	"<init>":(I)V
Method	java/net/ServerSocket."<init>":(I)V
NameAndType	shouldTerminate:()Z
Method	scala/actors/remote/TcpService.shouldTerminate:()Z
Asciz	scala/actors/Debug$;
class	scala/actors/Debug$
Asciz	Lscala/actors/Debug$;;
NameAndType	MODULE$:Lscala/actors/Debug$;
Field	scala/actors/Debug$.MODULE$:Lscala/actors/Debug$;
Asciz	scala/runtime/StringAdd;
class	scala/runtime/StringAdd
Asciz	(Ljava/lang/Object;)V;
NameAndType	"<init>":(Ljava/lang/Object;)V
Method	scala/runtime/StringAdd."<init>":(Ljava/lang/Object;)V
Asciz	: shutting down...;
String	: shutting down...
Asciz	$plus;
Asciz	(Ljava/lang/String;)Ljava/lang/String;;
NameAndType	$plus:(Ljava/lang/String;)Ljava/lang/String;
Method	scala/runtime/StringAdd.$plus:(Ljava/lang/String;)Ljava/lang/String;
Asciz	info;
NameAndType	info:(Ljava/lang/String;)V
Method	scala/actors/Debug$.info:(Ljava/lang/String;)V
Asciz	scala/actors/remote/TcpService$$anonfun$run$1;
class	scala/actors/remote/TcpService$$anonfun$run$1
Asciz	(Lscala/actors/remote/TcpService;)V;
NameAndType	"<init>":(Lscala/actors/remote/TcpService;)V
Method	scala/actors/remote/TcpService$$anonfun$run$1."<init>":(Lscala/actors/remote/TcpService;)V
Method	scala/collection/mutable/HashMap.foreach:(Lscala/Function1;)V
Asciz	scala/collection/mutable/StringBuilder;
class	scala/collection/mutable/StringBuilder
Method	scala/collection/mutable/StringBuilder."<init>":()V
Asciz	: waiting for new connection on port ;
String	: waiting for new connection on port 
Asciz	append;
Asciz	(Ljava/lang/Object;)Lscala/collection/mutable/StringBuilder;;
NameAndType	append:(Ljava/lang/Object;)Lscala/collection/mutable/StringBuilder;
Method	scala/collection/mutable/StringBuilder.append:(Ljava/lang/Object;)Lscala/collection/mutable/StringBuilder;
Asciz	scala/runtime/BoxesRunTime;
class	scala/runtime/BoxesRunTime
Asciz	boxToInteger;
Asciz	(I)Ljava/lang/Integer;;
NameAndType	boxToInteger:(I)Ljava/lang/Integer;
Method	scala/runtime/BoxesRunTime.boxToInteger:(I)Ljava/lang/Integer;
Asciz	...;
String	...
Method	scala/collection/mutable/StringBuilder.toString:()Ljava/lang/String;
Asciz	accept;
Asciz	()Ljava/net/Socket;;
NameAndType	accept:()Ljava/net/Socket;
Method	java/net/ServerSocket.accept:()Ljava/net/Socket;
Asciz	close;
NameAndType	close:()V
Method	java/net/Socket.close:()V
Asciz	Started new ;
String	Started new 
Asciz	readNode;
NameAndType	readNode:()V
Method	scala/actors/remote/TcpServiceWorker.readNode:()V
Asciz	: caught ;
String	: caught 
Asciz	any2stringadd;
Asciz	(Ljava/lang/Object;)Lscala/runtime/StringAdd;;
NameAndType	any2stringadd:(Ljava/lang/Object;)Lscala/runtime/StringAdd;
Method	scala/Predef$.any2stringadd:(Ljava/lang/Object;)Lscala/runtime/StringAdd;
Asciz	java/lang/Exception;
class	java/lang/Exception
Asciz	Ljava/net/ServerSocket;;
Asciz	nextClient;
Asciz	shouldTerminate_$eq;
Asciz	(Z)V;
Asciz	terminate;
NameAndType	shouldTerminate_$eq:(Z)V
Method	scala/actors/remote/TcpService.shouldTerminate_$eq:(Z)V
Asciz	()Lscala/actors/remote/Node;;
NameAndType	internalNode:()Lscala/actors/remote/Node;
Method	scala/actors/remote/TcpService.internalNode:()Lscala/actors/remote/Node;
Asciz	java/net/ConnectException;
class	java/net/ConnectException
Asciz	send;
Asciz	(Lscala/actors/remote/Node;[B)V;
NameAndType	getConnection:(Lscala/actors/remote/Node;)Lscala/Option;
Method	scala/actors/remote/TcpService.getConnection:(Lscala/actors/remote/Node;)Lscala/Option;
NameAndType	liftedTree1$1:(Lscala/actors/remote/Node;[B)Ljava/lang/Object;
Method	scala/actors/remote/TcpService.liftedTree1$1:(Lscala/actors/remote/Node;[B)Ljava/lang/Object;
Asciz	node$1;
Asciz	data$1;
Asciz	temp15;
Asciz	temp16;
Asciz	temp13;
Asciz	()Lscala/collection/mutable/HashMap<Lscala/actors/remote/Node;Lscala/collection/immutable/List<[B>;>;;
Asciz	scala$actors$remote$Service$_setter_$kernel_$eq;
Asciz	(Lscala/actors/remote/NetKernel;)V;
NameAndType	kernel:Lscala/actors/remote/NetKernel;
Field	scala/actors/remote/TcpService.kernel:Lscala/actors/remote/NetKernel;
Asciz	()Lscala/actors/remote/NetKernel;;
Asciz	ScalaSig;
Asciz	InnerClasses;
Asciz	$anonfun$run$1;
Asciz	$anonfun$liftedTree1$1$1;
Asciz	scala/actors/remote/Service;
class	scala/actors/remote/Service
Asciz	scala/ScalaObject;
class	scala/ScalaObject

{
private final scala.actors.remote.NetKernel kernel;
  Signature: Lscala/actors/remote/NetKernel;

private final scala.collection.mutable.HashMap connections;
  Signature: Lscala/collection/mutable/HashMap;
  Signature: length = 0x2
   00 1D 

private boolean shouldTerminate;
  Signature: Z

private final scala.collection.mutable.HashMap pendingSends;
  Signature: Lscala/collection/mutable/HashMap;
  Signature: length = 0x2
   00 22 

private final scala.actors.remote.Node internalNode;
  Signature: Lscala/actors/remote/Node;

private final scala.actors.remote.JavaSerializer serializer;
  Signature: Lscala/actors/remote/JavaSerializer;

private final int port;
  Signature: I

public static final void BufSize_$eq(int);
  Signature: (I)V
  Code:
   Stack=2, Locals=1, Args_size=1
	getstatic	Field scala/actors/remote/TcpService$.MODULE$:Lscala/actors/remote/TcpService$;
	iload_0
	invokevirtual	Method scala/actors/remote/TcpService$.BufSize_$eq:(I)V
	return
  Labels:

public static final int BufSize();
  Signature: ()I
  Code:
   Stack=1, Locals=0, Args_size=0
	getstatic	Field scala/actors/remote/TcpService$.MODULE$:Lscala/actors/remote/TcpService$;
	invokevirtual	Method scala/actors/remote/TcpService$.BufSize:()I
	ireturn
  Labels:

public static final int generatePort();
  Signature: ()I
  Code:
   Stack=1, Locals=0, Args_size=0
	getstatic	Field scala/actors/remote/TcpService$.MODULE$:Lscala/actors/remote/TcpService$;
	invokevirtual	Method scala/actors/remote/TcpService$.generatePort:()I
	ireturn
  Labels:

public static final scala.actors.remote.TcpService apply(int, java.lang.ClassLoader);
  Signature: (ILjava/lang/ClassLoader;)Lscala/actors/remote/TcpService;
  Code:
   Stack=3, Locals=2, Args_size=2
	getstatic	Field scala/actors/remote/TcpService$.MODULE$:Lscala/actors/remote/TcpService$;
	iload_0
	aload_1
	invokevirtual	Method scala/actors/remote/TcpService$.apply:(ILjava/lang/ClassLoader;)Lscala/actors/remote/TcpService;
	areturn
  Labels:

public scala.actors.remote.TcpService(int, java.lang.ClassLoader);
  Signature: (ILjava/lang/ClassLoader;)V
  Code:
   Stack=5, Locals=3, Args_size=3
	aload_0
	iload_1
	putfield	Field port:I
	aload_0
	invokespecial	Method java/lang/Thread."<init>":()V
	aload_0
	invokestatic	Method scala/actors/remote/Service$class.$init$:(Lscala/actors/remote/Service;)V
	aload_0
	new	class scala/actors/remote/JavaSerializer
	dup
	aload_0
	aload_2
	invokespecial	Method scala/actors/remote/JavaSerializer."<init>":(Lscala/actors/remote/Service;Ljava/lang/ClassLoader;)V
	putfield	Field serializer:Lscala/actors/remote/JavaSerializer;
	aload_0
	new	class scala/actors/remote/Node
	dup
	invokestatic	Method java/net/InetAddress.getLocalHost:()Ljava/net/InetAddress;
	invokevirtual	Method java/net/InetAddress.getHostAddress:()Ljava/lang/String;
	iload_1
	invokespecial	Method scala/actors/remote/Node."<init>":(Ljava/lang/String;I)V
	putfield	Field internalNode:Lscala/actors/remote/Node;
	aload_0
	new	class scala/collection/mutable/HashMap
	dup
	invokespecial	Method scala/collection/mutable/HashMap."<init>":()V
	putfield	Field pendingSends:Lscala/collection/mutable/HashMap;
	aload_0
	iconst_0
	putfield	Field shouldTerminate:Z
	aload_0
	new	class scala/collection/mutable/HashMap
	dup
	invokespecial	Method scala/collection/mutable/HashMap."<init>":()V
	putfield	Field connections:Lscala/collection/mutable/HashMap;
	return
  Labels:
  LocalVariableTable: 
   Start  Length  Slot  Name   Signature
   0      72      0    this       Lscala/actors/remote/TcpService;
   0      72      1    port       I
   0      72      2    cl       Ljava/lang/ClassLoader;


private final java.lang.Object liftedTree1$1(scala.actors.remote.Node, byte[]);
  Signature: (Lscala/actors/remote/Node;[B)Ljava/lang/Object;
  Code:
   Stack=5, Locals=10, Args_size=3
	aload_0
	aload_1
	invokevirtual	Method connect:(Lscala/actors/remote/Node;)Lscala/actors/remote/TcpServiceWorker;
	astore	5
	aload	5
	aload_2
	invokevirtual	Method scala/actors/remote/TcpServiceWorker.transmit:([B)V
	aload_0
	invokespecial	Method pendingSends:()Lscala/collection/mutable/HashMap;
	aload_1
	invokevirtual	Method scala/collection/mutable/HashMap.get:(Ljava/lang/Object;)Lscala/Option;
	astore	6
	getstatic	Field scala/None$.MODULE$:Lscala/None$;
	dup
	ifnonnull	l1 // aload
	pop
	aload	6
	ifnull	l2 // getstatic
	goto	l3 // aload
l1	aload	6
	invokevirtual	Method java/lang/Object.equals:(Ljava/lang/Object;)Z
	ifeq	l3 // aload
l2	getstatic	Field scala/runtime/BoxedUnit.UNIT:Lscala/runtime/BoxedUnit;
	goto	l4 // astore
l3	aload	6
	instanceof	class scala/Some
	ifeq	l5 // new
	aload	6
	checkcast	class scala/Some
	astore_3
	aload_3
	invokevirtual	Method scala/Some.x:()Ljava/lang/Object;
	checkcast	class scala/collection/immutable/List
	astore	4
	aload	4
	new	class scala/actors/remote/TcpService$$anonfun$liftedTree1$1$1
	dup
	aload_0
	aload	5
	invokespecial	Method scala/actors/remote/TcpService$$anonfun$liftedTree1$1$1."<init>":(Lscala/actors/remote/TcpService;Lscala/actors/remote/TcpServiceWorker;)V
	invokeinterface	InterfaceMethod scala/collection/LinearSeqLike.foreach:(Lscala/Function1;)V
	aload_0
	invokespecial	Method pendingSends:()Lscala/collection/mutable/HashMap;
	aload_1
	invokevirtual	Method scala/collection/mutable/HashMap.$minus$eq:(Ljava/lang/Object;)Lscala/collection/mutable/HashMap;
l4	astore	9
	goto	l6 // aload
l5	new	class scala/MatchError
	dup
	aload	6
	invokevirtual	Method scala/Option.toString:()Ljava/lang/String;
	invokespecial	Method scala/MatchError."<init>":(Ljava/lang/String;)V
	athrow
	pop
	getstatic	Field scala/runtime/BoxedUnit.UNIT:Lscala/runtime/BoxedUnit;
	astore	9
	goto	l6 // aload
	astore	7
	aload_0
	aload	7
	aload_1
	aload_2
	invokespecial	Method bufferMsg$1:(Ljava/lang/Throwable;Lscala/actors/remote/Node;[B)V
	getstatic	Field scala/runtime/BoxedUnit.UNIT:Lscala/runtime/BoxedUnit;
	astore	9
	goto	l6 // aload
	astore	8
	aload_0
	aload	8
	aload_1
	aload_2
	invokespecial	Method bufferMsg$1:(Ljava/lang/Throwable;Lscala/actors/remote/Node;[B)V
	getstatic	Field scala/runtime/BoxedUnit.UNIT:Lscala/runtime/BoxedUnit;
	astore	9
l6	aload	9
	areturn
  Labels:
   	l1 = 39 // aload
   	l2 = 47 // getstatic
   	l3 = 53 // aload
   	l4 = 101 // astore
   	l5 = 106 // new
   	l6 = 161 // aload
  Exception table:
   from   to  target type
     0   119   146   Class java/net/UnknownHostException

     0   119   128   Class java/io/IOException

     0   119   119   Class java/lang/SecurityException

  LocalVariableTable: 
   Start  Length  Slot  Name   Signature
   0      164      0    this       Lscala/actors/remote/TcpService;
   67      34      3    temp11       Lscala/Some;
   76      25      4    temp12       Lscala/collection/immutable/List;
   7      112      5    newWorker$1       Lscala/actors/remote/TcpServiceWorker;
   23      96      6    temp9       Lscala/Option;
   0      163      9    exceptionResult3       Ljava/lang/Object;


private final void bufferMsg$1(java.lang.Throwable, scala.actors.remote.Node, byte[]);
  Signature: (Ljava/lang/Throwable;Lscala/actors/remote/Node;[B)V
  Code:
   Stack=9, Locals=7, Args_size=4
	aload_0
	invokespecial	Method pendingSends:()Lscala/collection/mutable/HashMap;
	aload_2
	invokevirtual	Method scala/collection/mutable/HashMap.get:(Ljava/lang/Object;)Lscala/Option;
	astore	6
	getstatic	Field scala/None$.MODULE$:Lscala/None$;
	dup
	ifnonnull	l1 // aload
	pop
	aload	6
	ifnull	l2 // aload_0
	goto	l3 // aload
l1	aload	6
	invokevirtual	Method java/lang/Object.equals:(Ljava/lang/Object;)Z
	ifeq	l3 // aload
l2	aload_0
	invokespecial	Method pendingSends:()Lscala/collection/mutable/HashMap;
	getstatic	Field scala/Predef$Pair$.MODULE$:Lscala/Predef$Pair$;
	aload_2
	getstatic	Field scala/collection/immutable/List$.MODULE$:Lscala/collection/immutable/List$;
	getstatic	Field scala/Predef$.MODULE$:Lscala/Predef$;
	iconst_1
	anewarray	class "[B"
	dup
	iconst_0
	aload_3
	aastore
	checkcast	class "[Ljava/lang/Object;"
	invokevirtual	Method scala/Predef$.wrapRefArray:([Ljava/lang/Object;)Lscala/collection/mutable/WrappedArray;
	invokevirtual	Method scala/collection/immutable/List$.apply:(Lscala/collection/Seq;)Lscala/collection/immutable/List;
	invokevirtual	Method scala/Predef$Pair$.apply:(Ljava/lang/Object;Ljava/lang/Object;)Lscala/Tuple2;
	invokevirtual	Method scala/collection/mutable/HashMap.$plus$eq:(Lscala/Tuple2;)Lscala/collection/mutable/HashMap;
	pop
	goto	l4 // return
l3	aload	6
	instanceof	class scala/Some
	ifeq	l5 // new
	aload	6
	checkcast	class scala/Some
	astore	4
	aload	4
	invokevirtual	Method scala/Some.x:()Ljava/lang/Object;
	checkcast	class scala/collection/immutable/List
	astore	5
	aload_0
	aload	5
	invokespecial	Method gd1$1:(Lscala/collection/immutable/List;)Z
	ifeq	l6 // new
	aload_0
	invokespecial	Method pendingSends:()Lscala/collection/mutable/HashMap;
	getstatic	Field scala/Predef$Pair$.MODULE$:Lscala/Predef$Pair$;
	aload_2
	aload	5
	aload_3
	invokevirtual	Method scala/collection/immutable/List.$colon$colon:(Ljava/lang/Object;)Lscala/collection/immutable/List;
	invokevirtual	Method scala/Predef$Pair$.apply:(Ljava/lang/Object;Ljava/lang/Object;)Lscala/Tuple2;
	invokevirtual	Method scala/collection/mutable/HashMap.$plus$eq:(Lscala/Tuple2;)Lscala/collection/mutable/HashMap;
	pop
l4	return
l6	new	class scala/MatchError
	dup
	aload	6
	invokevirtual	Method scala/Option.toString:()Ljava/lang/String;
	invokespecial	Method scala/MatchError."<init>":(Ljava/lang/String;)V
	athrow
l5	new	class scala/MatchError
	dup
	aload	6
	invokevirtual	Method scala/Option.toString:()Ljava/lang/String;
	invokespecial	Method scala/MatchError."<init>":(Ljava/lang/String;)V
	athrow
  Labels:
   	l1 = 26 // aload
   	l2 = 34 // aload_0
   	l3 = 75 // aload
   	l4 = 130 // return
   	l6 = 131 // new
   	l5 = 144 // new
  LocalVariableTable: 
   Start  Length  Slot  Name   Signature
   0      157      0    this       Lscala/actors/remote/TcpService;
   0      157      1    t       Ljava/lang/Throwable;
   90      40      4    temp7       Lscala/Some;
   131      13      4    temp7       Lscala/Some;
   100      30      5    temp8       Lscala/collection/immutable/List;
   131      13      5    temp8       Lscala/collection/immutable/List;
   10      147      6    temp5       Lscala/Option;


private final boolean gd1$1(scala.collection.immutable.List);
  Signature: (Lscala/collection/immutable/List;)Z
  Code:
   Stack=2, Locals=2, Args_size=2
	aload_1
	invokeinterface	InterfaceMethod scala/collection/LinearSeqLike.length:()I
	getstatic	Field scala/actors/remote/TcpService$.MODULE$:Lscala/actors/remote/TcpService$;
	invokevirtual	Method scala/actors/remote/TcpService$.BufSize:()I
	if_icmpge	l1 // iconst_0
	iconst_1
	goto	l2 // ireturn
l1	iconst_0
l2	ireturn
  Labels:
   	l1 = 19 // iconst_0
   	l2 = 20 // ireturn

public scala.actors.remote.Serializer serializer();
  Signature: ()Lscala/actors/remote/Serializer;
  Code:
   Stack=1, Locals=1, Args_size=1
	aload_0
	invokevirtual	Method serializer:()Lscala/actors/remote/JavaSerializer;
	areturn
  Labels:

public void nodeDown(scala.actors.remote.Node);
  Signature: (Lscala/actors/remote/Node;)V
  Code:
   Stack=2, Locals=2, Args_size=2
	aload_0
	dup
	pop
	monitorenter
	aload_0
	invokespecial	Method connections:()Lscala/collection/mutable/HashMap;
	aload_1
	invokevirtual	Method scala/collection/mutable/HashMap.$minus$eq:(Ljava/lang/Object;)Lscala/collection/mutable/HashMap;
	pop
	aload_0
	monitorexit
	return
	aload_0
	monitorexit
	athrow
  Labels:
  Exception table:
   from   to  target type
     4    15    16   any
  LocalVariableTable: 
   Start  Length  Slot  Name   Signature
   0      19      0    this       Lscala/actors/remote/TcpService;
   0      19      1    mnode       Lscala/actors/remote/Node;


public boolean isReachable(scala.actors.remote.Node);
  Signature: (Lscala/actors/remote/Node;)Z
  Code:
   Stack=2, Locals=3, Args_size=2
	aload_0
	aload_1
	invokevirtual	Method isConnected:(Lscala/actors/remote/Node;)Z
	ifeq	l1 // aload_0
	iconst_1
	goto	l2 // ireturn
l1	aload_0
	aload_1
	invokevirtual	Method connect:(Lscala/actors/remote/Node;)Lscala/actors/remote/TcpServiceWorker;
	pop
	iconst_1
	ireturn
	pop
	iconst_0
	istore_2
	goto	l3 // iload_2
	pop
	iconst_0
	istore_2
	goto	l3 // iload_2
	pop
	iconst_0
	istore_2
l3	iload_2
l2	ireturn
  Labels:
   	l1 = 12 // aload_0
   	l3 = 35 // iload_2
   	l2 = 36 // ireturn
  Exception table:
   from   to  target type
    12    20    32   Class java/net/UnknownHostException

    12    20    26   Class java/io/IOException

    12    20    20   Class java/lang/SecurityException

  LocalVariableTable: 
   Start  Length  Slot  Name   Signature
   0      37      0    this       Lscala/actors/remote/TcpService;
   0      37      1    node       Lscala/actors/remote/Node;
   12      24      2    exceptionResult2       Z


public void disconnectNode(scala.actors.remote.Node);
  Signature: (Lscala/actors/remote/Node;)V
  Code:
   Stack=3, Locals=5, Args_size=2
	aload_0
	dup
	pop
	monitorenter
	aload_0
	invokespecial	Method connections:()Lscala/collection/mutable/HashMap;
	aload_1
	invokevirtual	Method scala/collection/mutable/HashMap.get:(Ljava/lang/Object;)Lscala/Option;
	astore	4
	getstatic	Field scala/None$.MODULE$:Lscala/None$;
	dup
	ifnonnull	l1 // aload
	pop
	aload	4
	ifnull	l2 // goto
	goto	l3 // aload
l1	aload	4
	invokevirtual	Method java/lang/Object.equals:(Ljava/lang/Object;)Z
	ifeq	l3 // aload
l2	goto	l4 // aload_0
l3	aload	4
	instanceof	class scala/Some
	ifeq	l5 // new
	aload	4
	checkcast	class scala/Some
	astore_2
	aload_2
	invokevirtual	Method scala/Some.x:()Ljava/lang/Object;
	checkcast	class scala/actors/remote/TcpServiceWorker
	astore_3
	aload_0
	invokespecial	Method connections:()Lscala/collection/mutable/HashMap;
	aload_1
	invokevirtual	Method scala/collection/mutable/HashMap.$minus$eq:(Ljava/lang/Object;)Lscala/collection/mutable/HashMap;
	pop
	aload_3
	invokevirtual	Method scala/actors/remote/TcpServiceWorker.halt:()V
l4	aload_0
	monitorexit
	return
l5	new	class scala/MatchError
	dup
	aload	4
	invokevirtual	Method scala/Option.toString:()Ljava/lang/String;
	invokespecial	Method scala/MatchError."<init>":(Ljava/lang/String;)V
	athrow
	aload_0
	monitorexit
	athrow
  Labels:
   	l1 = 30 // aload
   	l2 = 38 // goto
   	l3 = 41 // aload
   	l4 = 76 // aload_0
   	l5 = 79 // new
  Exception table:
   from   to  target type
     4    78    92   any
    79    92    92   any
  LocalVariableTable: 
   Start  Length  Slot  Name   Signature
   0      95      0    this       Lscala/actors/remote/TcpService;
   0      95      1    n       Lscala/actors/remote/Node;
   55      21      2    temp22       Lscala/Some;
   63      13      3    temp23       Lscala/actors/remote/TcpServiceWorker;
   14      62      4    temp20       Lscala/Option;
   79      13      4    temp20       Lscala/Option;


public scala.actors.remote.TcpServiceWorker connect(scala.actors.remote.Node);
  Signature: (Lscala/actors/remote/Node;)Lscala/actors/remote/TcpServiceWorker;
  Code:
   Stack=4, Locals=4, Args_size=2
	aload_0
	dup
	pop
	monitorenter
	new	class java/net/Socket
	dup
	aload_1
	invokevirtual	Method scala/actors/remote/Node.address:()Ljava/lang/String;
	aload_1
	invokevirtual	Method scala/actors/remote/Node.port:()I
	invokespecial	Method java/net/Socket."<init>":(Ljava/lang/String;I)V
	astore_2
	new	class scala/actors/remote/TcpServiceWorker
	dup
	aload_0
	aload_2
	invokespecial	Method scala/actors/remote/TcpServiceWorker."<init>":(Lscala/actors/remote/TcpService;Ljava/net/Socket;)V
	astore_3
	aload_3
	aload_1
	invokevirtual	Method scala/actors/remote/TcpServiceWorker.sendNode:(Lscala/actors/remote/Node;)V
	aload_3
	invokevirtual	Method scala/actors/remote/TcpServiceWorker.start:()V
	aload_0
	aload_1
	aload_3
	invokevirtual	Method addConnection:(Lscala/actors/remote/Node;Lscala/actors/remote/TcpServiceWorker;)Lscala/collection/mutable/HashMap;
	pop
	aload_0
	monitorexit
	aload_3
	checkcast	class scala/actors/remote/TcpServiceWorker
	areturn
	aload_0
	monitorexit
	athrow
  Labels:
  Exception table:
   from   to  target type
     4    48    53   any
  LocalVariableTable: 
   Start  Length  Slot  Name   Signature
   0      56      0    this       Lscala/actors/remote/TcpService;
   0      56      1    n       Lscala/actors/remote/Node;
   20      26      2    socket       Ljava/net/Socket;
   30      16      3    worker       Lscala/actors/remote/TcpServiceWorker;


public boolean isConnected(scala.actors.remote.Node);
  Signature: (Lscala/actors/remote/Node;)Z
  Code:
   Stack=2, Locals=3, Args_size=2
	aload_0
	dup
	pop
	monitorenter
	aload_0
	invokespecial	Method connections:()Lscala/collection/mutable/HashMap;
	aload_1
	invokevirtual	Method scala/collection/mutable/HashMap.get:(Ljava/lang/Object;)Lscala/Option;
	invokevirtual	Method scala/Option.isEmpty:()Z
	ifeq	l1 // iconst_1
	iconst_0
	goto	l2 // istore_2
l1	iconst_1
l2	istore_2
	aload_0
	monitorexit
	iload_2
	ireturn
	aload_0
	monitorexit
	athrow
  Labels:
   	l1 = 22 // iconst_1
   	l2 = 23 // istore_2
  Exception table:
   from   to  target type
     4    26    28   any
  LocalVariableTable: 
   Start  Length  Slot  Name   Signature
   0      31      0    this       Lscala/actors/remote/TcpService;
   0      31      1    n       Lscala/actors/remote/Node;


public scala.Option getConnection(scala.actors.remote.Node);
  Signature: (Lscala/actors/remote/Node;)Lscala/Option;
  Code:
   Stack=2, Locals=3, Args_size=2
	aload_0
	dup
	pop
	monitorenter
	aload_0
	invokespecial	Method connections:()Lscala/collection/mutable/HashMap;
	aload_1
	invokevirtual	Method scala/collection/mutable/HashMap.get:(Ljava/lang/Object;)Lscala/Option;
	astore_2
	aload_0
	monitorexit
	aload_2
	checkcast	class scala/Option
	areturn
	aload_0
	monitorexit
	athrow
  Labels:
  Exception table:
   from   to  target type
     4    15    20   any
  LocalVariableTable: 
   Start  Length  Slot  Name   Signature
   0      23      0    this       Lscala/actors/remote/TcpService;
   0      23      1    n       Lscala/actors/remote/Node;

  Signature: length = 0x2
   01 21 

public scala.collection.mutable.HashMap addConnection(scala.actors.remote.Node, scala.actors.remote.TcpServiceWorker);
  Signature: (Lscala/actors/remote/Node;Lscala/actors/remote/TcpServiceWorker;)Lscala/collection/mutable/HashMap;
  Code:
   Stack=4, Locals=4, Args_size=3
	aload_0
	dup
	pop
	monitorenter
	aload_0
	invokespecial	Method connections:()Lscala/collection/mutable/HashMap;
	getstatic	Field scala/Predef$Pair$.MODULE$:Lscala/Predef$Pair$;
	aload_1
	aload_2
	invokevirtual	Method scala/Predef$Pair$.apply:(Ljava/lang/Object;Ljava/lang/Object;)Lscala/Tuple2;
	invokevirtual	Method scala/collection/mutable/HashMap.$plus$eq:(Lscala/Tuple2;)Lscala/collection/mutable/HashMap;
	astore_3
	aload_0
	monitorexit
	aload_3
	checkcast	class scala/collection/mutable/HashMap
	areturn
	aload_0
	monitorexit
	athrow
  Labels:
  Exception table:
   from   to  target type
     4    22    27   any
  LocalVariableTable: 
   Start  Length  Slot  Name   Signature
   0      30      0    this       Lscala/actors/remote/TcpService;
   0      30      1    node       Lscala/actors/remote/Node;
   0      30      2    worker       Lscala/actors/remote/TcpServiceWorker;

  Signature: length = 0x2
   01 22 

private scala.collection.mutable.HashMap connections();
  Signature: ()Lscala/collection/mutable/HashMap;
  Code:
   Stack=1, Locals=1, Args_size=1
	aload_0
	getfield	Field connections:Lscala/collection/mutable/HashMap;
	areturn
  Labels:
  Signature: length = 0x2
   01 23 

public void run();
  Signature: ()V
  Code:
   Stack=5, Locals=7, Args_size=1
	new	class java/net/ServerSocket
	dup
	aload_0
	getfield	Field port:I
	invokespecial	Method java/net/ServerSocket."<init>":(I)V
	astore_2
l4	aload_0
	invokespecial	Method shouldTerminate:()Z
	ifeq	l1 // getstatic
	getstatic	Field scala/actors/Debug$.MODULE$:Lscala/actors/Debug$;
	new	class scala/runtime/StringAdd
	dup
	aload_0
	invokespecial	Method scala/runtime/StringAdd."<init>":(Ljava/lang/Object;)V
	ldc_w	String : shutting down...
	invokevirtual	Method scala/runtime/StringAdd.$plus:(Ljava/lang/String;)Ljava/lang/String;
	invokevirtual	Method scala/actors/Debug$.info:(Ljava/lang/String;)V
	aload_0
	invokespecial	Method connections:()Lscala/collection/mutable/HashMap;
	new	class scala/actors/remote/TcpService$$anonfun$run$1
	dup
	aload_0
	invokespecial	Method scala/actors/remote/TcpService$$anonfun$run$1."<init>":(Lscala/actors/remote/TcpService;)V
	invokevirtual	Method scala/collection/mutable/HashMap.foreach:(Lscala/Function1;)V
	goto	l2 // return
l1	getstatic	Field scala/actors/Debug$.MODULE$:Lscala/actors/Debug$;
	new	class scala/collection/mutable/StringBuilder
	dup
	invokespecial	Method scala/collection/mutable/StringBuilder."<init>":()V
	new	class scala/runtime/StringAdd
	dup
	aload_0
	invokespecial	Method scala/runtime/StringAdd."<init>":(Ljava/lang/Object;)V
	ldc_w	String : waiting for new connection on port 
	invokevirtual	Method scala/runtime/StringAdd.$plus:(Ljava/lang/String;)Ljava/lang/String;
	invokevirtual	Method scala/collection/mutable/StringBuilder.append:(Ljava/lang/Object;)Lscala/collection/mutable/StringBuilder;
	aload_0
	getfield	Field port:I
	istore_1
	iload_1
	invokestatic	Method scala/runtime/BoxesRunTime.boxToInteger:(I)Ljava/lang/Integer;
	invokevirtual	Method scala/collection/mutable/StringBuilder.append:(Ljava/lang/Object;)Lscala/collection/mutable/StringBuilder;
	ldc_w	String ...
	invokevirtual	Method scala/collection/mutable/StringBuilder.append:(Ljava/lang/Object;)Lscala/collection/mutable/StringBuilder;
	invokevirtual	Method scala/collection/mutable/StringBuilder.toString:()Ljava/lang/String;
	invokevirtual	Method scala/actors/Debug$.info:(Ljava/lang/String;)V
	aload_2
	invokevirtual	Method java/net/ServerSocket.accept:()Ljava/net/Socket;
	astore_3
	aload_0
	invokespecial	Method shouldTerminate:()Z
	ifeq	l3 // new
	aload_3
	invokevirtual	Method java/net/Socket.close:()V
	goto	l4 // aload_0
l3	new	class scala/actors/remote/TcpServiceWorker
	dup
	aload_0
	aload_3
	invokespecial	Method scala/actors/remote/TcpServiceWorker."<init>":(Lscala/actors/remote/TcpService;Ljava/net/Socket;)V
	astore	4
	getstatic	Field scala/actors/Debug$.MODULE$:Lscala/actors/Debug$;
	new	class scala/collection/mutable/StringBuilder
	dup
	invokespecial	Method scala/collection/mutable/StringBuilder."<init>":()V
	ldc_w	String Started new 
	invokevirtual	Method scala/collection/mutable/StringBuilder.append:(Ljava/lang/Object;)Lscala/collection/mutable/StringBuilder;
	aload	4
	invokevirtual	Method scala/collection/mutable/StringBuilder.append:(Ljava/lang/Object;)Lscala/collection/mutable/StringBuilder;
	invokevirtual	Method scala/collection/mutable/StringBuilder.toString:()Ljava/lang/String;
	invokevirtual	Method scala/actors/Debug$.info:(Ljava/lang/String;)V
	aload	4
	invokevirtual	Method scala/actors/remote/TcpServiceWorker.readNode:()V
	aload	4
	invokevirtual	Method scala/actors/remote/TcpServiceWorker.start:()V
	goto	l4 // aload_0
	astore	5
	getstatic	Field scala/actors/Debug$.MODULE$:Lscala/actors/Debug$;
	new	class scala/collection/mutable/StringBuilder
	dup
	invokespecial	Method scala/collection/mutable/StringBuilder."<init>":()V
	new	class scala/runtime/StringAdd
	dup
	aload_0
	invokespecial	Method scala/runtime/StringAdd."<init>":(Ljava/lang/Object;)V
	ldc_w	String : caught 
	invokevirtual	Method scala/runtime/StringAdd.$plus:(Ljava/lang/String;)Ljava/lang/String;
	invokevirtual	Method scala/collection/mutable/StringBuilder.append:(Ljava/lang/Object;)Lscala/collection/mutable/StringBuilder;
	aload	5
	invokevirtual	Method scala/collection/mutable/StringBuilder.append:(Ljava/lang/Object;)Lscala/collection/mutable/StringBuilder;
	invokevirtual	Method scala/collection/mutable/StringBuilder.toString:()Ljava/lang/String;
	invokevirtual	Method scala/actors/Debug$.info:(Ljava/lang/String;)V
	getstatic	Field scala/actors/Debug$.MODULE$:Lscala/actors/Debug$;
	getstatic	Field scala/Predef$.MODULE$:Lscala/Predef$;
	aload_0
	invokevirtual	Method scala/Predef$.any2stringadd:(Ljava/lang/Object;)Lscala/runtime/StringAdd;
	ldc_w	String : shutting down...
	invokevirtual	Method scala/runtime/StringAdd.$plus:(Ljava/lang/String;)Ljava/lang/String;
	invokevirtual	Method scala/actors/Debug$.info:(Ljava/lang/String;)V
	aload_0
	invokespecial	Method connections:()Lscala/collection/mutable/HashMap;
	new	class scala/actors/remote/TcpService$$anonfun$run$1
	dup
	aload_0
	invokespecial	Method scala/actors/remote/TcpService$$anonfun$run$1."<init>":(Lscala/actors/remote/TcpService;)V
	invokevirtual	Method scala/collection/mutable/HashMap.foreach:(Lscala/Function1;)V
l2	return
	astore	6
	getstatic	Field scala/actors/Debug$.MODULE$:Lscala/actors/Debug$;
	getstatic	Field scala/Predef$.MODULE$:Lscala/Predef$;
	aload_0
	invokevirtual	Method scala/Predef$.any2stringadd:(Ljava/lang/Object;)Lscala/runtime/StringAdd;
	ldc_w	String : shutting down...
	invokevirtual	Method scala/runtime/StringAdd.$plus:(Ljava/lang/String;)Ljava/lang/String;
	invokevirtual	Method scala/actors/Debug$.info:(Ljava/lang/String;)V
	aload_0
	invokespecial	Method connections:()Lscala/collection/mutable/HashMap;
	new	class scala/actors/remote/TcpService$$anonfun$run$1
	dup
	aload_0
	invokespecial	Method scala/actors/remote/TcpService$$anonfun$run$1."<init>":(Lscala/actors/remote/TcpService;)V
	invokevirtual	Method scala/collection/mutable/HashMap.foreach:(Lscala/Function1;)V
	aload	6
	athrow
  Labels:
   	l4 = 12 // aload_0
   	l1 = 57 // getstatic
   	l3 = 127 // new
   	l2 = 252 // return
  Exception table:
   from   to  target type
     0    19   178   Class java/lang/Exception

    57   178   178   Class java/lang/Exception

     0    19   253   any
    57   218   253   any
  LocalVariableTable: 
   Start  Length  Slot  Name   Signature
   0      292      0    this       Lscala/actors/remote/TcpService;
   12      7      2    socket       Ljava/net/ServerSocket;
   57      121      2    socket       Ljava/net/ServerSocket;
   113      65      3    nextClient       Ljava/net/Socket;
   138      37      4    worker       Lscala/actors/remote/TcpServiceWorker;


private void shouldTerminate_$eq(boolean);
  Signature: (Z)V
  Code:
   Stack=2, Locals=2, Args_size=2
	aload_0
	iload_1
	putfield	Field shouldTerminate:Z
	return
  Labels:

private boolean shouldTerminate();
  Signature: ()Z
  Code:
   Stack=1, Locals=1, Args_size=1
	aload_0
	getfield	Field shouldTerminate:Z
	ireturn
  Labels:

public void terminate();
  Signature: ()V
  Code:
   Stack=5, Locals=2, Args_size=1
	aload_0
	iconst_1
	invokespecial	Method shouldTerminate_$eq:(Z)V
	new	class java/net/Socket
	dup
	aload_0
	invokespecial	Method internalNode:()Lscala/actors/remote/Node;
	invokevirtual	Method scala/actors/remote/Node.address:()Ljava/lang/String;
	aload_0
	invokespecial	Method internalNode:()Lscala/actors/remote/Node;
	invokevirtual	Method scala/actors/remote/Node.port:()I
	invokespecial	Method java/net/Socket."<init>":(Ljava/lang/String;I)V
	pop
	goto	l1 // return
	astore_1
	getstatic	Field scala/actors/Debug$.MODULE$:Lscala/actors/Debug$;
	new	class scala/collection/mutable/StringBuilder
	dup
	invokespecial	Method scala/collection/mutable/StringBuilder."<init>":()V
	new	class scala/runtime/StringAdd
	dup
	aload_0
	invokespecial	Method scala/runtime/StringAdd."<init>":(Ljava/lang/Object;)V
	ldc_w	String : caught 
	invokevirtual	Method scala/runtime/StringAdd.$plus:(Ljava/lang/String;)Ljava/lang/String;
	invokevirtual	Method scala/collection/mutable/StringBuilder.append:(Ljava/lang/Object;)Lscala/collection/mutable/StringBuilder;
	aload_1
	invokevirtual	Method scala/collection/mutable/StringBuilder.append:(Ljava/lang/Object;)Lscala/collection/mutable/StringBuilder;
	invokevirtual	Method scala/collection/mutable/StringBuilder.toString:()Ljava/lang/String;
	invokevirtual	Method scala/actors/Debug$.info:(Ljava/lang/String;)V
l1	return
  Labels:
   	l1 = 68 // return
  Exception table:
   from   to  target type
     5    30    30   Class java/net/ConnectException

  LocalVariableTable: 
   Start  Length  Slot  Name   Signature
   0      69      0    this       Lscala/actors/remote/TcpService;


public void send(scala.actors.remote.Node, byte[]);
  Signature: (Lscala/actors/remote/Node;[B)V
  Code:
   Stack=3, Locals=6, Args_size=3
	aload_0
	dup
	pop
	monitorenter
	aload_0
	aload_1
	invokevirtual	Method getConnection:(Lscala/actors/remote/Node;)Lscala/Option;
	astore	5
	getstatic	Field scala/None$.MODULE$:Lscala/None$;
	dup
	ifnonnull	l1 // aload
	pop
	aload	5
	ifnull	l2 // aload_0
	goto	l3 // aload
l1	aload	5
	invokevirtual	Method java/lang/Object.equals:(Ljava/lang/Object;)Z
	ifeq	l3 // aload
l2	aload_0
	aload_1
	aload_2
	invokespecial	Method liftedTree1$1:(Lscala/actors/remote/Node;[B)Ljava/lang/Object;
	goto	l4 // pop
l3	aload	5
	instanceof	class scala/Some
	ifeq	l5 // new
	aload	5
	checkcast	class scala/Some
	astore_3
	aload_3
	invokevirtual	Method scala/Some.x:()Ljava/lang/Object;
	checkcast	class scala/actors/remote/TcpServiceWorker
	astore	4
	aload	4
	aload_2
	invokevirtual	Method scala/actors/remote/TcpServiceWorker.transmit:([B)V
	getstatic	Field scala/runtime/BoxedUnit.UNIT:Lscala/runtime/BoxedUnit;
l4	pop
	aload_0
	monitorexit
	return
l5	new	class scala/MatchError
	dup
	aload	5
	invokevirtual	Method scala/Option.toString:()Ljava/lang/String;
	invokespecial	Method scala/MatchError."<init>":(Ljava/lang/String;)V
	athrow
	aload_0
	monitorexit
	athrow
  Labels:
   	l1 = 27 // aload
   	l2 = 35 // aload_0
   	l3 = 44 // aload
   	l4 = 76 // pop
   	l5 = 80 // new
  Exception table:
   from   to  target type
     4    79    93   any
    80    93    93   any
  LocalVariableTable: 
   Start  Length  Slot  Name   Signature
   0      96      0    this       Lscala/actors/remote/TcpService;
   0      96      1    node$1       Lscala/actors/remote/Node;
   0      96      2    data$1       [B
   58      18      3    temp15       Lscala/Some;
   67      9      4    temp16       Lscala/actors/remote/TcpServiceWorker;
   11      66      5    temp13       Lscala/Option;
   80      13      5    temp13       Lscala/Option;


private scala.collection.mutable.HashMap pendingSends();
  Signature: ()Lscala/collection/mutable/HashMap;
  Code:
   Stack=1, Locals=1, Args_size=1
	aload_0
	getfield	Field pendingSends:Lscala/collection/mutable/HashMap;
	areturn
  Labels:
  Signature: length = 0x2
   01 FFFFFF81 

public scala.actors.remote.Node node();
  Signature: ()Lscala/actors/remote/Node;
  Code:
   Stack=1, Locals=1, Args_size=1
	aload_0
	invokespecial	Method internalNode:()Lscala/actors/remote/Node;
	areturn
  Labels:

private scala.actors.remote.Node internalNode();
  Signature: ()Lscala/actors/remote/Node;
  Code:
   Stack=1, Locals=1, Args_size=1
	aload_0
	getfield	Field internalNode:Lscala/actors/remote/Node;
	areturn
  Labels:

public scala.actors.remote.JavaSerializer serializer();
  Signature: ()Lscala/actors/remote/JavaSerializer;
  Code:
   Stack=1, Locals=1, Args_size=1
	aload_0
	getfield	Field serializer:Lscala/actors/remote/JavaSerializer;
	areturn
  Labels:

public void scala$actors$remote$Service$_setter_$kernel_$eq(scala.actors.remote.NetKernel);
  Signature: (Lscala/actors/remote/NetKernel;)V
  Code:
   Stack=2, Locals=2, Args_size=2
	aload_0
	aload_1
	putfield	Field kernel:Lscala/actors/remote/NetKernel;
	return
  Labels:

public scala.actors.remote.NetKernel kernel();
  Signature: ()Lscala/actors/remote/NetKernel;
  Code:
   Stack=1, Locals=1, Args_size=1
	aload_0
	getfield	Field kernel:Lscala/actors/remote/NetKernel;
	areturn
  Labels:

}

