Compiled from "TcpService.scala"
public final class scala.actors.remote.TcpService$$anonfun$liftedTree1$1$1 extends java.lang.Object implements scala.Function1,scala.ScalaObject,java.io.Serializable
  SourceFile: "TcpService.scala"
  Scala: length = 0x
   
  InnerClass: 
   public final #86= #10 of #85; //$anonfun$liftedTree1$1$1=class scala/actors/remote/TcpService$$anonfun$liftedTree1$1$1 of class scala/actors/remote/TcpService
  minor version: 0
  major version: 49
  Constant pool:
const #1 = Asciz	SourceFile;
const #2 = Asciz	TcpService.scala;
const #3 = Asciz	newWorker$1;
const #4 = Asciz	Lscala/actors/remote/TcpServiceWorker;;
const #5 = Asciz	<init>;
const #6 = Asciz	(Lscala/actors/remote/TcpService;Lscala/actors/remote/TcpServiceWorker;)V;
const #7 = Asciz	Code;
const #8 = Asciz	LineNumberTable;
const #9 = Asciz	scala/actors/remote/TcpService$$anonfun$liftedTree1$1$1;
const #10 = class	#9;	//  scala/actors/remote/TcpService$$anonfun$liftedTree1$1$1
const #11 = NameAndType	#3:#4;//  newWorker$1:Lscala/actors/remote/TcpServiceWorker;
const #12 = Field	#10.#11;	//  scala/actors/remote/TcpService$$anonfun$liftedTree1$1$1.newWorker$1:Lscala/actors/remote/TcpServiceWorker;
const #13 = Asciz	java/lang/Object;
const #14 = class	#13;	//  java/lang/Object
const #15 = Asciz	()V;
const #16 = NameAndType	#5:#15;//  "<init>":()V
const #17 = Method	#14.#16;	//  java/lang/Object."<init>":()V
const #18 = Asciz	scala/Function1$class;
const #19 = class	#18;	//  scala/Function1$class
const #20 = Asciz	$init$;
const #21 = Asciz	(Lscala/Function1;)V;
const #22 = NameAndType	#20:#21;//  $init$:(Lscala/Function1;)V
const #23 = Method	#19.#22;	//  scala/Function1$class.$init$:(Lscala/Function1;)V
const #24 = Asciz	this;
const #25 = Asciz	Lscala/actors/remote/TcpService$$anonfun$liftedTree1$1$1;;
const #26 = Asciz	$outer;
const #27 = Asciz	Lscala/actors/remote/TcpService;;
const #28 = Asciz	LocalVariableTable;
const #29 = Asciz	apply;
const #30 = Asciz	(Ljava/lang/Object;)Ljava/lang/Object;;
const #31 = Asciz	scala/runtime/BoxedArray;
const #32 = class	#31;	//  scala/runtime/BoxedArray
const #33 = Asciz	scala/runtime/ScalaRunTime$;
const #34 = class	#33;	//  scala/runtime/ScalaRunTime$
const #35 = Asciz	MODULE$;
const #36 = Asciz	Lscala/runtime/ScalaRunTime$;;
const #37 = NameAndType	#35:#36;//  MODULE$:Lscala/runtime/ScalaRunTime$;
const #38 = Field	#34.#37;	//  scala/runtime/ScalaRunTime$.MODULE$:Lscala/runtime/ScalaRunTime$;
const #39 = Asciz	java/lang/Byte;
const #40 = class	#39;	//  java/lang/Byte
const #41 = Asciz	TYPE;
const #42 = Asciz	Ljava/lang/Class;;
const #43 = NameAndType	#41:#42;//  TYPE:Ljava/lang/Class;
const #44 = Field	#40.#43;	//  java/lang/Byte.TYPE:Ljava/lang/Class;
const #45 = Asciz	arrayValue;
const #46 = Asciz	(Lscala/runtime/BoxedArray;Ljava/lang/Class;)Ljava/lang/Object;;
const #47 = NameAndType	#45:#46;//  arrayValue:(Lscala/runtime/BoxedArray;Ljava/lang/Class;)Ljava/lang/Object;
const #48 = Method	#34.#47;	//  scala/runtime/ScalaRunTime$.arrayValue:(Lscala/runtime/BoxedArray;Ljava/lang/Class;)Ljava/lang/Object;
const #49 = Asciz	[B;
const #50 = class	#49;	//  "[B"
const #51 = Asciz	([B)V;
const #52 = NameAndType	#29:#51;//  apply:([B)V
const #53 = Method	#10.#52;	//  scala/actors/remote/TcpService$$anonfun$liftedTree1$1$1.apply:([B)V
const #54 = Asciz	scala/runtime/BoxedUnit;
const #55 = class	#54;	//  scala/runtime/BoxedUnit
const #56 = Asciz	UNIT;
const #57 = Asciz	Lscala/runtime/BoxedUnit;;
const #58 = NameAndType	#56:#57;//  UNIT:Lscala/runtime/BoxedUnit;
const #59 = Field	#55.#58;	//  scala/runtime/BoxedUnit.UNIT:Lscala/runtime/BoxedUnit;
const #60 = Asciz	v1;
const #61 = Asciz	Ljava/lang/Object;;
const #62 = Asciz	scala/actors/remote/TcpServiceWorker;
const #63 = class	#62;	//  scala/actors/remote/TcpServiceWorker
const #64 = Asciz	transmit;
const #65 = NameAndType	#64:#51;//  transmit:([B)V
const #66 = Method	#63.#65;	//  scala/actors/remote/TcpServiceWorker.transmit:([B)V
const #67 = Asciz	andThen;
const #68 = Asciz	(Lscala/Function1;)Lscala/Function1;;
const #69 = Asciz	(Lscala/Function1;Lscala/Function1;)Lscala/Function1;;
const #70 = NameAndType	#67:#69;//  andThen:(Lscala/Function1;Lscala/Function1;)Lscala/Function1;
const #71 = Method	#19.#70;	//  scala/Function1$class.andThen:(Lscala/Function1;Lscala/Function1;)Lscala/Function1;
const #72 = Asciz	g;
const #73 = Asciz	Lscala/Function1;;
const #74 = Asciz	compose;
const #75 = NameAndType	#74:#69;//  compose:(Lscala/Function1;Lscala/Function1;)Lscala/Function1;
const #76 = Method	#19.#75;	//  scala/Function1$class.compose:(Lscala/Function1;Lscala/Function1;)Lscala/Function1;
const #77 = Asciz	toString;
const #78 = Asciz	()Ljava/lang/String;;
const #79 = Asciz	(Lscala/Function1;)Ljava/lang/String;;
const #80 = NameAndType	#77:#79;//  toString:(Lscala/Function1;)Ljava/lang/String;
const #81 = Method	#19.#80;	//  scala/Function1$class.toString:(Lscala/Function1;)Ljava/lang/String;
const #82 = Asciz	Scala;
const #83 = Asciz	InnerClasses;
const #84 = Asciz	scala/actors/remote/TcpService;
const #85 = class	#84;	//  scala/actors/remote/TcpService
const #86 = Asciz	$anonfun$liftedTree1$1$1;
const #87 = Asciz	scala/Function1;
const #88 = class	#87;	//  scala/Function1
const #89 = Asciz	scala/ScalaObject;
const #90 = class	#89;	//  scala/ScalaObject
const #91 = Asciz	java/io/Serializable;
const #92 = class	#91;	//  java/io/Serializable

{
public scala.actors.remote.TcpService$$anonfun$liftedTree1$1$1(scala.actors.remote.TcpService, scala.actors.remote.TcpServiceWorker);
  Code:
   Stack=2, Locals=3, Args_size=3
   0:	aload_0
   1:	aload_2
   2:	putfield	#12; //Field newWorker$1:Lscala/actors/remote/TcpServiceWorker;
   5:	aload_0
   6:	invokespecial	#17; //Method java/lang/Object."<init>":()V
   9:	aload_0
   10:	invokestatic	#23; //Method scala/Function1$class.$init$:(Lscala/Function1;)V
   13:	return
  LineNumberTable: 
   line 110: 0

  LocalVariableTable: 
   Start  Length  Slot  Name   Signature
   0      14      0    this       Lscala/actors/remote/TcpService$$anonfun$liftedTree1$1$1;
   0      14      1    $outer       Lscala/actors/remote/TcpService;


public final java.lang.Object apply(java.lang.Object);
  Code:
   Stack=4, Locals=2, Args_size=2
   0:	aload_0
   1:	aload_1
   2:	instanceof	#32; //class scala/runtime/BoxedArray
   5:	ifeq	24
   8:	getstatic	#38; //Field scala/runtime/ScalaRunTime$.MODULE$:Lscala/runtime/ScalaRunTime$;
   11:	aload_1
   12:	checkcast	#32; //class scala/runtime/BoxedArray
   15:	getstatic	#44; //Field java/lang/Byte.TYPE:Ljava/lang/Class;
   18:	invokevirtual	#48; //Method scala/runtime/ScalaRunTime$.arrayValue:(Lscala/runtime/BoxedArray;Ljava/lang/Class;)Ljava/lang/Object;
   21:	goto	25
   24:	aload_1
   25:	checkcast	#50; //class "[B"
   28:	invokevirtual	#53; //Method apply:([B)V
   31:	getstatic	#59; //Field scala/runtime/BoxedUnit.UNIT:Lscala/runtime/BoxedUnit;
   34:	areturn
  LineNumberTable: 
   line 110: 0

  LocalVariableTable: 
   Start  Length  Slot  Name   Signature
   0      35      0    this       Lscala/actors/remote/TcpService$$anonfun$liftedTree1$1$1;
   0      35      1    v1       Ljava/lang/Object;


public final void apply(byte[]);
  Code:
   Stack=2, Locals=2, Args_size=2
   0:	aload_0
   1:	getfield	#12; //Field newWorker$1:Lscala/actors/remote/TcpServiceWorker;
   4:	aload_1
   5:	invokevirtual	#66; //Method scala/actors/remote/TcpServiceWorker.transmit:([B)V
   8:	return
  LineNumberTable: 
   line 110: 0


public scala.Function1 andThen(scala.Function1);
  Code:
   Stack=2, Locals=2, Args_size=2
   0:	aload_0
   1:	aload_1
   2:	invokestatic	#71; //Method scala/Function1$class.andThen:(Lscala/Function1;Lscala/Function1;)Lscala/Function1;
   5:	areturn
  LineNumberTable: 
   line 110: 0

  LocalVariableTable: 
   Start  Length  Slot  Name   Signature
   0      6      0    this       Lscala/actors/remote/TcpService$$anonfun$liftedTree1$1$1;
   0      6      1    g       Lscala/Function1;


public scala.Function1 compose(scala.Function1);
  Code:
   Stack=2, Locals=2, Args_size=2
   0:	aload_0
   1:	aload_1
   2:	invokestatic	#76; //Method scala/Function1$class.compose:(Lscala/Function1;Lscala/Function1;)Lscala/Function1;
   5:	areturn
  LineNumberTable: 
   line 110: 0

  LocalVariableTable: 
   Start  Length  Slot  Name   Signature
   0      6      0    this       Lscala/actors/remote/TcpService$$anonfun$liftedTree1$1$1;
   0      6      1    g       Lscala/Function1;


public java.lang.String toString();
  Code:
   Stack=1, Locals=1, Args_size=1
   0:	aload_0
   1:	invokestatic	#81; //Method scala/Function1$class.toString:(Lscala/Function1;)Ljava/lang/String;
   4:	areturn
  LineNumberTable: 
   line 110: 0


}

