Compiled from "NetKernel.scala"
public final class scala.actors.remote.Terminate extends java.lang.Object
  SourceFile: "NetKernel.scala"
  ScalaSig: length = 0x3
   05 00 00 
  RuntimeVisibleAnnotations: length = 0xB
   00 01 00 27 00 01 00 28 73 00 29 
  minor version: 0
  major version: 49
  Constant pool:
Asciz	SourceFile;
Asciz	NetKernel.scala;
Asciz	productElements;
Asciz	()Lscala/collection/Iterator;;
Asciz	Code;
Asciz	scala/actors/remote/Terminate$;
class	scala/actors/remote/Terminate$
Asciz	MODULE$;
Asciz	Lscala/actors/remote/Terminate$;;
NameAndType	MODULE$:Lscala/actors/remote/Terminate$;
Field	scala/actors/remote/Terminate$.MODULE$:Lscala/actors/remote/Terminate$;
NameAndType	productElements:()Lscala/collection/Iterator;
Method	scala/actors/remote/Terminate$.productElements:()Lscala/collection/Iterator;
Asciz	Deprecated;
Asciz	productIterator;
NameAndType	productIterator:()Lscala/collection/Iterator;
Method	scala/actors/remote/Terminate$.productIterator:()Lscala/collection/Iterator;
Asciz	productElementName;
Asciz	(I)Ljava/lang/String;;
NameAndType	productElementName:(I)Ljava/lang/String;
Method	scala/actors/remote/Terminate$.productElementName:(I)Ljava/lang/String;
Asciz	canEqual;
Asciz	(Ljava/lang/Object;)Z;
NameAndType	canEqual:(Ljava/lang/Object;)Z
Method	scala/actors/remote/Terminate$.canEqual:(Ljava/lang/Object;)Z
Asciz	productElement;
Asciz	(I)Ljava/lang/Object;;
NameAndType	productElement:(I)Ljava/lang/Object;
Method	scala/actors/remote/Terminate$.productElement:(I)Ljava/lang/Object;
Asciz	productArity;
Asciz	()I;
NameAndType	productArity:()I
Method	scala/actors/remote/Terminate$.productArity:()I
Asciz	productPrefix;
Asciz	()Ljava/lang/String;;
NameAndType	productPrefix:()Ljava/lang/String;
Method	scala/actors/remote/Terminate$.productPrefix:()Ljava/lang/String;
Asciz	ScalaSig;
Asciz	Lscala/reflect/ScalaSignature;;
Asciz	bytes;
Asciz	;Q!\t&\tV3s[&t\r^3\r!A:f[>$XM\r1m;peNTaBgG.Y!\tQ1\"D\r!a!\"Ak!!+fe6Lg.;f'YaB=!R\"\tE7b]TaEU4-!\t1qJ6fGR\"a\rI!!M\r\1PE*,7\r\t/mI!AxZ;di\")adC?1A(8jiz\"!\tC-!\t!C#EAAo\*ue&tw\rF$!\tyA%&!\t11:j]DbJ%\tKaJ|G-^2u!J,g-=\rBBK%\teK\raJ|G-^2uJLG/_YAq#L]1!8u!4\"A\n\nA9s_,8\r^#mK6,geU\"aF\nQ2!aA!os\"9agLAaa=%c!AhC(dC:,/^1m)\tQTw%AH>|G.Z1o1t'!AAIBbP%\tQeGMU3t_24X\rFQ\tY!\t&AI\rg.7juG.;
Asciz	RuntimeVisibleAnnotations;
Asciz	scala/actors/remote/Terminate;
class	scala/actors/remote/Terminate
Asciz	java/lang/Object;
class	java/lang/Object

{
public static final scala.collection.Iterator productElements();
  Signature: ()Lscala/collection/Iterator;
  Code:
   Stack=1, Locals=0, Args_size=0
	getstatic	Field scala/actors/remote/Terminate$.MODULE$:Lscala/actors/remote/Terminate$;
	invokevirtual	Method scala/actors/remote/Terminate$.productElements:()Lscala/collection/Iterator;
	areturn
  Labels:
  Deprecated: true

public static final scala.collection.Iterator productIterator();
  Signature: ()Lscala/collection/Iterator;
  Code:
   Stack=1, Locals=0, Args_size=0
	getstatic	Field scala/actors/remote/Terminate$.MODULE$:Lscala/actors/remote/Terminate$;
	invokevirtual	Method scala/actors/remote/Terminate$.productIterator:()Lscala/collection/Iterator;
	areturn
  Labels:

public static final java.lang.String productElementName(int);
  Signature: (I)Ljava/lang/String;
  Code:
   Stack=2, Locals=1, Args_size=1
	getstatic	Field scala/actors/remote/Terminate$.MODULE$:Lscala/actors/remote/Terminate$;
	iload_0
	invokevirtual	Method scala/actors/remote/Terminate$.productElementName:(I)Ljava/lang/String;
	areturn
  Labels:

public static final boolean canEqual(java.lang.Object);
  Signature: (Ljava/lang/Object;)Z
  Code:
   Stack=2, Locals=1, Args_size=1
	getstatic	Field scala/actors/remote/Terminate$.MODULE$:Lscala/actors/remote/Terminate$;
	aload_0
	invokevirtual	Method scala/actors/remote/Terminate$.canEqual:(Ljava/lang/Object;)Z
	ireturn
  Labels:

public static final java.lang.Object productElement(int);
  Signature: (I)Ljava/lang/Object;
  Code:
   Stack=2, Locals=1, Args_size=1
	getstatic	Field scala/actors/remote/Terminate$.MODULE$:Lscala/actors/remote/Terminate$;
	iload_0
	invokevirtual	Method scala/actors/remote/Terminate$.productElement:(I)Ljava/lang/Object;
	areturn
  Labels:

public static final int productArity();
  Signature: ()I
  Code:
   Stack=1, Locals=0, Args_size=0
	getstatic	Field scala/actors/remote/Terminate$.MODULE$:Lscala/actors/remote/Terminate$;
	invokevirtual	Method scala/actors/remote/Terminate$.productArity:()I
	ireturn
  Labels:

public static final java.lang.String productPrefix();
  Signature: ()Ljava/lang/String;
  Code:
   Stack=1, Locals=0, Args_size=0
	getstatic	Field scala/actors/remote/Terminate$.MODULE$:Lscala/actors/remote/Terminate$;
	invokevirtual	Method scala/actors/remote/Terminate$.productPrefix:()Ljava/lang/String;
	areturn
  Labels:

}

