Compiled from "Proxy.scala"
public class scala.actors.remote.UnlinkFromFun extends java.lang.Object implements scala.Function2,scala.ScalaObject,java.io.Serializable
  SourceFile: "Proxy.scala"
  ScalaSig: length = 0x3
   05 00 00 
  Signature: length = 0x2
   00 41 
  RuntimeVisibleAnnotations: length = 0xB
   00 01 00 43 00 01 00 44 73 00 45 
  minor version: 0
  major version: 49
  Constant pool:
Asciz	SourceFile;
Asciz	Proxy.scala;
Asciz	curried;
Asciz	()Lscala/Function1;;
Asciz	Code;
Asciz	LineNumberTable;
Asciz	scala/Function2$class;
class	scala/Function2$class
Asciz	(Lscala/Function2;)Lscala/Function1;;
NameAndType	curried:(Lscala/Function2;)Lscala/Function1;
Method	scala/Function2$class.curried:(Lscala/Function2;)Lscala/Function1;
Asciz	curry;
NameAndType	curry:(Lscala/Function2;)Lscala/Function1;
Method	scala/Function2$class.curry:(Lscala/Function2;)Lscala/Function1;
Asciz	Deprecated;
Asciz	tupled;
NameAndType	tupled:(Lscala/Function2;)Lscala/Function1;
Method	scala/Function2$class.tupled:(Lscala/Function2;)Lscala/Function1;
Asciz	apply;
Asciz	(Lscala/actors/AbstractActor;Lscala/actors/remote/Proxy;)V;
Asciz	scala/actors/AbstractActor;
class	scala/actors/AbstractActor
Asciz	unlinkFrom;
Asciz	(Lscala/actors/AbstractActor;)V;
NameAndType	unlinkFrom:(Lscala/actors/AbstractActor;)V
InterfaceMethod	scala/actors/AbstractActor.unlinkFrom:(Lscala/actors/AbstractActor;)V
Asciz	this;
Asciz	Lscala/actors/remote/UnlinkFromFun;;
Asciz	target;
Asciz	Lscala/actors/AbstractActor;;
Asciz	creator;
Asciz	Lscala/actors/remote/Proxy;;
Asciz	LocalVariableTable;
Asciz	toString;
Asciz	()Ljava/lang/String;;
Asciz	<UnlinkFromFun>;
String	<UnlinkFromFun>
Asciz	(Ljava/lang/Object;Ljava/lang/Object;)Ljava/lang/Object;;
Asciz	scala/actors/remote/Proxy;
class	scala/actors/remote/Proxy
Asciz	scala/actors/remote/UnlinkFromFun;
class	scala/actors/remote/UnlinkFromFun
NameAndType	apply:(Lscala/actors/AbstractActor;Lscala/actors/remote/Proxy;)V
Method	scala/actors/remote/UnlinkFromFun.apply:(Lscala/actors/AbstractActor;Lscala/actors/remote/Proxy;)V
Asciz	scala/runtime/BoxedUnit;
class	scala/runtime/BoxedUnit
Asciz	UNIT;
Asciz	Lscala/runtime/BoxedUnit;;
NameAndType	UNIT:Lscala/runtime/BoxedUnit;
Field	scala/runtime/BoxedUnit.UNIT:Lscala/runtime/BoxedUnit;
Asciz	v1;
Asciz	Ljava/lang/Object;;
Asciz	v2;
Asciz	<init>;
Asciz	()V;
Asciz	java/lang/Object;
class	java/lang/Object
NameAndType	"<init>":()V
Method	java/lang/Object."<init>":()V
Asciz	$init$;
Asciz	(Lscala/Function2;)V;
NameAndType	$init$:(Lscala/Function2;)V
Method	scala/Function2$class.$init$:(Lscala/Function2;)V
Asciz	ScalaSig;
Asciz	Ljava/lang/Object;Lscala/Function2<Lscala/actors/AbstractActor;Lscala/actors/remote/Proxy;Ljava/lang/Object;>;Lscala/ScalaObject;;
Asciz	Signature;
Asciz	Lscala/reflect/ScalaSignature;;
Asciz	bytes;
Asciz	e2\"\t!+:dN\6Ge>lg)8\r!A:f[>$XM\r1m;peNTaBgG.Y'!BE-R\"5q7b]TaDU4-\t1qJ6fGRRa5yiAB+BR;oGRLwN]AR\"\ne!!!D!cgRm;BGR|'95\t!!\t)K]8ysB1cHAA!8jiB1CIG1bU2bY|%M[3di\")QCM1A(8jiz\"a\n\t7AQ!)\nQ!9qYf$2AH.a1!M]4fi\")aa591M]3bi>\"\t\n;p'RN\4I\"aC\nQb!AB*ue&tw\rmA1cNqAb]3sSdN_1cY;
Asciz	RuntimeVisibleAnnotations;
Asciz	scala/Function2;
class	scala/Function2
Asciz	scala/ScalaObject;
class	scala/ScalaObject
Asciz	java/io/Serializable;
class	java/io/Serializable

{
public scala.Function1 curried();
  Signature: ()Lscala/Function1;
  Code:
   Stack=1, Locals=1, Args_size=1
	aload_0
	invokestatic	Method scala/Function2$class.curried:(Lscala/Function2;)Lscala/Function1;
	areturn
  Labels:

public scala.Function1 curry();
  Signature: ()Lscala/Function1;
  Code:
   Stack=1, Locals=1, Args_size=1
	aload_0
	invokestatic	Method scala/Function2$class.curry:(Lscala/Function2;)Lscala/Function1;
	areturn
  Labels:
  Deprecated: true

public scala.Function1 tupled();
  Signature: ()Lscala/Function1;
  Code:
   Stack=1, Locals=1, Args_size=1
	aload_0
	invokestatic	Method scala/Function2$class.tupled:(Lscala/Function2;)Lscala/Function1;
	areturn
  Labels:

public void apply(scala.actors.AbstractActor, scala.actors.remote.Proxy);
  Signature: (Lscala/actors/AbstractActor;Lscala/actors/remote/Proxy;)V
  Code:
   Stack=2, Locals=3, Args_size=3
	aload_1
	aload_2
	invokeinterface	InterfaceMethod scala/actors/AbstractActor.unlinkFrom:(Lscala/actors/AbstractActor;)V
	return
  Labels:
  LocalVariableTable: 
   Start  Length  Slot  Name   Signature
   0      8      0    this       Lscala/actors/remote/UnlinkFromFun;
   0      8      1    target       Lscala/actors/AbstractActor;
   0      8      2    creator       Lscala/actors/remote/Proxy;


public java.lang.String toString();
  Signature: ()Ljava/lang/String;
  Code:
   Stack=1, Locals=1, Args_size=1
	ldc	String <UnlinkFromFun>
	areturn
  Labels:

public java.lang.Object apply(java.lang.Object, java.lang.Object);
  Signature: (Ljava/lang/Object;Ljava/lang/Object;)Ljava/lang/Object;
  Code:
   Stack=3, Locals=3, Args_size=3
	aload_0
	aload_1
	checkcast	class scala/actors/AbstractActor
	aload_2
	checkcast	class scala/actors/remote/Proxy
	invokevirtual	Method apply:(Lscala/actors/AbstractActor;Lscala/actors/remote/Proxy;)V
	getstatic	Field scala/runtime/BoxedUnit.UNIT:Lscala/runtime/BoxedUnit;
	areturn
  Labels:
  LocalVariableTable: 
   Start  Length  Slot  Name   Signature
   0      16      0    this       Lscala/actors/remote/UnlinkFromFun;
   0      16      1    v1       Ljava/lang/Object;
   0      16      2    v2       Ljava/lang/Object;


public scala.actors.remote.UnlinkFromFun();
  Signature: ()V
  Code:
   Stack=1, Locals=1, Args_size=1
	aload_0
	invokespecial	Method java/lang/Object."<init>":()V
	aload_0
	invokestatic	Method scala/Function2$class.$init$:(Lscala/Function2;)V
	return
  Labels:

}

