Compiled from "Regex.scala"
public final class scala.util.matching.Regex$Match$ extends java.lang.Object implements scala.ScalaObject
  SourceFile: "Regex.scala"
  Scala: length = 0x
   
  InnerClass: 
   public #44= #41 of #43; //Match=class scala/util/matching/Regex$Match of class scala/util/matching/Regex
   public abstract #45= #25 of #43; //MatchData=class scala/util/matching/Regex$MatchData of class scala/util/matching/Regex
   public final #48= #47 of #41; //$anonfun$ends$1=class scala/util/matching/Regex$Match$$anonfun$ends$1 of class scala/util/matching/Regex$Match
   public final #51= #50 of #41; //$anonfun$starts$1=class scala/util/matching/Regex$Match$$anonfun$starts$1 of class scala/util/matching/Regex$Match
  minor version: 0
  major version: 49
  Constant pool:
const #1 = Asciz	SourceFile;
const #2 = Asciz	Regex.scala;
const #3 = Asciz	Scala;
const #4 = Asciz	MODULE$;
const #5 = Asciz	Lscala/util/matching/Regex$Match$;;
const #6 = Asciz	<clinit>;
const #7 = Asciz	()V;
const #8 = Asciz	Code;
const #9 = Asciz	scala/util/matching/Regex$Match$;
const #10 = class	#9;	//  scala/util/matching/Regex$Match$
const #11 = Asciz	<init>;
const #12 = NameAndType	#11:#7;//  "<init>":()V
const #13 = Method	#10.#12;	//  scala/util/matching/Regex$Match$."<init>":()V
const #14 = Asciz	LineNumberTable;
const #15 = Asciz	java/lang/Object;
const #16 = class	#15;	//  java/lang/Object
const #17 = Method	#16.#12;	//  java/lang/Object."<init>":()V
const #18 = NameAndType	#4:#5;//  MODULE$:Lscala/util/matching/Regex$Match$;
const #19 = Field	#10.#18;	//  scala/util/matching/Regex$Match$.MODULE$:Lscala/util/matching/Regex$Match$;
const #20 = Asciz	unapply;
const #21 = Asciz	(Lscala/util/matching/Regex$Match;)Lscala/Some;;
const #22 = Asciz	scala/Some;
const #23 = class	#22;	//  scala/Some
const #24 = Asciz	scala/util/matching/Regex$MatchData;
const #25 = class	#24;	//  scala/util/matching/Regex$MatchData
const #26 = Asciz	matched;
const #27 = Asciz	()Ljava/lang/String;;
const #28 = NameAndType	#26:#27;//  matched:()Ljava/lang/String;
const #29 = InterfaceMethod	#25.#28;	//  scala/util/matching/Regex$MatchData.matched:()Ljava/lang/String;
const #30 = Asciz	(Ljava/lang/Object;)V;
const #31 = NameAndType	#11:#30;//  "<init>":(Ljava/lang/Object;)V
const #32 = Method	#23.#31;	//  scala/Some."<init>":(Ljava/lang/Object;)V
const #33 = Asciz	this;
const #34 = Asciz	m;
const #35 = Asciz	Lscala/util/matching/Regex$Match;;
const #36 = Asciz	LocalVariableTable;
const #37 = Asciz	(Lscala/util/matching/Regex$Match;)Lscala/Some<Ljava/lang/String;>;;
const #38 = Asciz	Signature;
const #39 = Asciz	InnerClasses;
const #40 = Asciz	scala/util/matching/Regex$Match;
const #41 = class	#40;	//  scala/util/matching/Regex$Match
const #42 = Asciz	scala/util/matching/Regex;
const #43 = class	#42;	//  scala/util/matching/Regex
const #44 = Asciz	Match;
const #45 = Asciz	MatchData;
const #46 = Asciz	scala/util/matching/Regex$Match$$anonfun$ends$1;
const #47 = class	#46;	//  scala/util/matching/Regex$Match$$anonfun$ends$1
const #48 = Asciz	$anonfun$ends$1;
const #49 = Asciz	scala/util/matching/Regex$Match$$anonfun$starts$1;
const #50 = class	#49;	//  scala/util/matching/Regex$Match$$anonfun$starts$1
const #51 = Asciz	$anonfun$starts$1;
const #52 = Asciz	scala/ScalaObject;
const #53 = class	#52;	//  scala/ScalaObject

{
public static final scala.util.matching.Regex$Match$ MODULE$;

public static {};
  Code:
   Stack=1, Locals=0, Args_size=0
   0:	new	#10; //class scala/util/matching/Regex$Match$
   3:	invokespecial	#13; //Method "<init>":()V
   6:	return

public scala.util.matching.Regex$Match$();
  Code:
   Stack=1, Locals=1, Args_size=1
   0:	aload_0
   1:	invokespecial	#17; //Method java/lang/Object."<init>":()V
   4:	aload_0
   5:	putstatic	#19; //Field MODULE$:Lscala/util/matching/Regex$Match$;
   8:	return
  LineNumberTable: 
   line 249: 0


public scala.Some unapply(scala.util.matching.Regex$Match);
  Code:
   Stack=3, Locals=2, Args_size=2
   0:	new	#23; //class scala/Some
   3:	dup
   4:	aload_1
   5:	invokeinterface	#29,  1; //InterfaceMethod scala/util/matching/Regex$MatchData.matched:()Ljava/lang/String;
   10:	invokespecial	#32; //Method scala/Some."<init>":(Ljava/lang/Object;)V
   13:	areturn
  LineNumberTable: 
   line 250: 0

  LocalVariableTable: 
   Start  Length  Slot  Name   Signature
   0      14      0    this       Lscala/util/matching/Regex$Match$;
   0      14      1    m       Lscala/util/matching/Regex$Match;

  Signature: length = 0x2
   00 25 

}

