Compiled from "Regex.scala"
public final class scala.util.matching.Regex$$anonfun$unapplySeq$1 extends scala.runtime.AbstractFunction1 implements java.io.Serializable
  SourceFile: "Regex.scala"
  Scala: length = 0x
   
  InnerClass: 
   public final $anonfun$unapplySeq$1=class scala/util/matching/Regex$$anonfun$unapplySeq$1 of class scala/util/matching/Regex
  minor version: 0
  major version: 49
  Constant pool:
Asciz	SourceFile;
Asciz	Regex.scala;
Asciz	<clinit>;
Asciz	()V;
Asciz	Code;
Asciz	serialVersionUID;
Asciz	J;
Asciz	scala/util/matching/Regex$$anonfun$unapplySeq$1;
class	scala/util/matching/Regex$$anonfun$unapplySeq$1
NameAndType	serialVersionUID:J
Field	scala/util/matching/Regex$$anonfun$unapplySeq$1.serialVersionUID:J
Asciz	m$1;
Asciz	Ljava/util/regex/Matcher;;
Asciz	apply;
Asciz	(I)Ljava/lang/String;;
Asciz	LineNumberTable;
NameAndType	m$1:Ljava/util/regex/Matcher;
Field	scala/util/matching/Regex$$anonfun$unapplySeq$1.m$1:Ljava/util/regex/Matcher;
Asciz	java/util/regex/Matcher;
class	java/util/regex/Matcher
Asciz	group;
NameAndType	group:(I)Ljava/lang/String;
Method	java/util/regex/Matcher.group:(I)Ljava/lang/String;
Asciz	(Ljava/lang/Object;)Ljava/lang/Object;;
Asciz	scala/runtime/BoxesRunTime;
class	scala/runtime/BoxesRunTime
Asciz	unboxToInt;
Asciz	(Ljava/lang/Object;)I;
NameAndType	unboxToInt:(Ljava/lang/Object;)I
Method	scala/runtime/BoxesRunTime.unboxToInt:(Ljava/lang/Object;)I
NameAndType	apply:(I)Ljava/lang/String;
Method	scala/util/matching/Regex$$anonfun$unapplySeq$1.apply:(I)Ljava/lang/String;
Asciz	this;
Asciz	Lscala/util/matching/Regex$$anonfun$unapplySeq$1;;
Asciz	v1;
Asciz	Ljava/lang/Object;;
Asciz	LocalVariableTable;
Asciz	<init>;
Asciz	(Lscala/util/matching/Regex;Ljava/util/regex/Matcher;)V;
Asciz	scala/runtime/AbstractFunction1;
class	scala/runtime/AbstractFunction1
NameAndType	"<init>":()V
Method	scala/runtime/AbstractFunction1."<init>":()V
Asciz	$outer;
Asciz	Lscala/util/matching/Regex;;
Asciz	Scala;
Asciz	InnerClasses;
Asciz	scala/util/matching/Regex;
class	scala/util/matching/Regex
Asciz	$anonfun$unapplySeq$1;
Asciz	java/io/Serializable;
class	java/io/Serializable

{
public static final long serialVersionUID;
  Signature: J

private final java.util.regex.Matcher m$1;
  Signature: Ljava/util/regex/Matcher;

public static {};
  Signature: ()V
  Code:
   Stack=2, Locals=0, Args_size=0
	lconst_0
	putstatic	Field serialVersionUID:J
	return
  Labels:

public final java.lang.String apply(int);
  Signature: (I)Ljava/lang/String;
  Code:
   Stack=2, Locals=2, Args_size=2
	aload_0
	getfield	Field m$1:Ljava/util/regex/Matcher;
	iload_1
	invokevirtual	Method java/util/regex/Matcher.group:(I)Ljava/lang/String;
	areturn
  Labels:

public final java.lang.Object apply(java.lang.Object);
  Signature: (Ljava/lang/Object;)Ljava/lang/Object;
  Code:
   Stack=2, Locals=2, Args_size=2
	aload_0
	aload_1
	invokestatic	Method scala/runtime/BoxesRunTime.unboxToInt:(Ljava/lang/Object;)I
	invokevirtual	Method apply:(I)Ljava/lang/String;
	areturn
  Labels:
  LocalVariableTable: 
   Start  Length  Slot  Name   Signature
   0      9      0    this       Lscala/util/matching/Regex$$anonfun$unapplySeq$1;
   0      9      1    v1       Ljava/lang/Object;


public scala.util.matching.Regex$$anonfun$unapplySeq$1(scala.util.matching.Regex, java.util.regex.Matcher);
  Signature: (Lscala/util/matching/Regex;Ljava/util/regex/Matcher;)V
  Code:
   Stack=2, Locals=3, Args_size=3
	aload_0
	aload_2
	putfield	Field m$1:Ljava/util/regex/Matcher;
	aload_0
	invokespecial	Method scala/runtime/AbstractFunction1."<init>":()V
	return
  Labels:
  LocalVariableTable: 
   Start  Length  Slot  Name   Signature
   0      10      0    this       Lscala/util/matching/Regex$$anonfun$unapplySeq$1;
   0      10      1    $outer       Lscala/util/matching/Regex;


}

