Compiled from "Regex.scala"
public final class scala.util.matching.Regex$$anon$1 extends scala.util.matching.Regex$MatchIterator implements scala.util.matching.Regex$Replacement
  SourceFile: "Regex.scala"
  Scala: length = 0x
   
  InnerClass: 
   public final $anon$1=class scala/util/matching/Regex$$anon$1 of class scala/util/matching/Regex
   public abstract Replacement=class scala/util/matching/Regex$Replacement of class scala/util/matching/Regex
   public MatchIterator=class scala/util/matching/Regex$MatchIterator of class scala/util/matching/Regex
  minor version: 0
  major version: 49
  Constant pool:
Asciz	SourceFile;
Asciz	Regex.scala;
Asciz	scala$util$matching$Regex$Replacement$$sb;
Asciz	Ljava/lang/StringBuffer;;
Asciz	<init>;
Asciz	(Lscala/util/matching/Regex;Ljava/lang/CharSequence;)V;
Asciz	Code;
Asciz	LineNumberTable;
Asciz	scala/util/matching/Regex;
class	scala/util/matching/Regex
Asciz	scala$util$matching$Regex$$groupNames;
Asciz	Lscala/collection/Seq;;
NameAndType	scala$util$matching$Regex$$groupNames:Lscala/collection/Seq;
Field	scala/util/matching/Regex.scala$util$matching$Regex$$groupNames:Lscala/collection/Seq;
Asciz	scala/util/matching/Regex$MatchIterator;
class	scala/util/matching/Regex$MatchIterator
Asciz	(Ljava/lang/CharSequence;Lscala/util/matching/Regex;Lscala/collection/Seq;)V;
NameAndType	"<init>":(Ljava/lang/CharSequence;Lscala/util/matching/Regex;Lscala/collection/Seq;)V
Method	scala/util/matching/Regex$MatchIterator."<init>":(Ljava/lang/CharSequence;Lscala/util/matching/Regex;Lscala/collection/Seq;)V
Asciz	scala/util/matching/Regex$Replacement$class;
class	scala/util/matching/Regex$Replacement$class
Asciz	$init$;
Asciz	(Lscala/util/matching/Regex$Replacement;)V;
NameAndType	$init$:(Lscala/util/matching/Regex$Replacement;)V
Method	scala/util/matching/Regex$Replacement$class.$init$:(Lscala/util/matching/Regex$Replacement;)V
Asciz	this;
Asciz	Lscala/util/matching/Regex$$anon$1;;
Asciz	$outer;
Asciz	Lscala/util/matching/Regex;;
Asciz	LocalVariableTable;
Asciz	replace;
Asciz	(Ljava/lang/String;)Ljava/util/regex/Matcher;;
Asciz	(Lscala/util/matching/Regex$Replacement;Ljava/lang/String;)Ljava/util/regex/Matcher;;
NameAndType	replace:(Lscala/util/matching/Regex$Replacement;Ljava/lang/String;)Ljava/util/regex/Matcher;
Method	scala/util/matching/Regex$Replacement$class.replace:(Lscala/util/matching/Regex$Replacement;Ljava/lang/String;)Ljava/util/regex/Matcher;
Asciz	rs;
Asciz	Ljava/lang/String;;
Asciz	replaced;
Asciz	()Ljava/lang/String;;
Asciz	(Lscala/util/matching/Regex$Replacement;)Ljava/lang/String;;
NameAndType	replaced:(Lscala/util/matching/Regex$Replacement;)Ljava/lang/String;
Method	scala/util/matching/Regex$Replacement$class.replaced:(Lscala/util/matching/Regex$Replacement;)Ljava/lang/String;
Asciz	scala$util$matching$Regex$Replacement$$sb_$eq;
Asciz	(Ljava/lang/StringBuffer;)V;
Asciz	scala/util/matching/Regex$$anon$1;
class	scala/util/matching/Regex$$anon$1
NameAndType	scala$util$matching$Regex$Replacement$$sb:Ljava/lang/StringBuffer;
Field	scala/util/matching/Regex$$anon$1.scala$util$matching$Regex$Replacement$$sb:Ljava/lang/StringBuffer;
Asciz	()Ljava/lang/StringBuffer;;
Asciz	Scala;
Asciz	InnerClasses;
Asciz	$anon$1;
Asciz	scala/util/matching/Regex$Replacement;
class	scala/util/matching/Regex$Replacement
Asciz	Replacement;
Asciz	MatchIterator;

{
private java.lang.StringBuffer scala$util$matching$Regex$Replacement$$sb;
  Signature: Ljava/lang/StringBuffer;

public scala.util.matching.Regex$$anon$1(scala.util.matching.Regex, java.lang.CharSequence);
  Signature: (Lscala/util/matching/Regex;Ljava/lang/CharSequence;)V
  Code:
   Stack=4, Locals=3, Args_size=3
	aload_0
	aload_2
	aload_1
	aload_1
	getfield	Field scala/util/matching/Regex.scala$util$matching$Regex$$groupNames:Lscala/collection/Seq;
	invokespecial	Method scala/util/matching/Regex$MatchIterator."<init>":(Ljava/lang/CharSequence;Lscala/util/matching/Regex;Lscala/collection/Seq;)V
	aload_0
	invokestatic	Method scala/util/matching/Regex$Replacement$class.$init$:(Lscala/util/matching/Regex$Replacement;)V
	return
  Labels:
  LocalVariableTable: 
   Start  Length  Slot  Name   Signature
   0      15      0    this       Lscala/util/matching/Regex$$anon$1;
   0      15      1    $outer       Lscala/util/matching/Regex;


public java.util.regex.Matcher replace(java.lang.String);
  Signature: (Ljava/lang/String;)Ljava/util/regex/Matcher;
  Code:
   Stack=2, Locals=2, Args_size=2
	aload_0
	aload_1
	invokestatic	Method scala/util/matching/Regex$Replacement$class.replace:(Lscala/util/matching/Regex$Replacement;Ljava/lang/String;)Ljava/util/regex/Matcher;
	areturn
  Labels:
  LocalVariableTable: 
   Start  Length  Slot  Name   Signature
   0      6      0    this       Lscala/util/matching/Regex$$anon$1;
   0      6      1    rs       Ljava/lang/String;


public java.lang.String replaced();
  Signature: ()Ljava/lang/String;
  Code:
   Stack=1, Locals=1, Args_size=1
	aload_0
	invokestatic	Method scala/util/matching/Regex$Replacement$class.replaced:(Lscala/util/matching/Regex$Replacement;)Ljava/lang/String;
	areturn
  Labels:

public final void scala$util$matching$Regex$Replacement$$sb_$eq(java.lang.StringBuffer);
  Signature: (Ljava/lang/StringBuffer;)V
  Code:
   Stack=2, Locals=2, Args_size=2
	aload_0
	aload_1
	putfield	Field scala$util$matching$Regex$Replacement$$sb:Ljava/lang/StringBuffer;
	return
  Labels:

public final java.lang.StringBuffer scala$util$matching$Regex$Replacement$$sb();
  Signature: ()Ljava/lang/StringBuffer;
  Code:
   Stack=1, Locals=1, Args_size=1
	aload_0
	getfield	Field scala$util$matching$Regex$Replacement$$sb:Ljava/lang/StringBuffer;
	areturn
  Labels:

}

