Compiled from "Regex.scala"
public class scala.util.matching.Regex$MatchIterator extends java.lang.Object implements scala.collection.Iterator,scala.util.matching.Regex$MatchData,scala.ScalaObject
  SourceFile: "Regex.scala"
  Signature: length = 0x2
   01 FFFFFFB7 
  Scala: length = 0x
   
  InnerClass: 
   public abstract #444= #443 of #48; //MatchData=class scala/util/matching/Regex$MatchData of class scala/util/matching/Regex
   public final #449= #446 of #448; //WithFilter=class scala/collection/Iterator$WithFilter of class scala/collection/Iterator
   public #450= #24 of #48; //MatchIterator=class scala/util/matching/Regex$MatchIterator of class scala/util/matching/Regex
   public #453= #452 of #448; //GroupedIterator=class scala/collection/Iterator$GroupedIterator of class scala/collection/Iterator
   public final #454= #74 of #24; //$anon$1=class scala/util/matching/Regex$MatchIterator$$anon$1 of class scala/util/matching/Regex$MatchIterator
  minor version: 0
  major version: 49
  Constant pool:
const #1 = Asciz	SourceFile;
const #2 = Asciz	Regex.scala;
const #3 = Asciz	bitmap$0;
const #4 = Asciz	I;
const #5 = Asciz	scala$util$matching$Regex$MatchData$$nameToIndex;
const #6 = Asciz	Lscala/collection/immutable/Map;;
const #7 = Asciz	nextSeen;
const #8 = Asciz	Z;
const #9 = Asciz	scala$util$matching$Regex$MatchIterator$$matcher;
const #10 = Asciz	Ljava/util/regex/Matcher;;
const #11 = Asciz	groupNames;
const #12 = Asciz	Lscala/collection/Seq;;
const #13 = Asciz	Lscala/collection/Seq<Ljava/lang/String;>;;
const #14 = Asciz	Signature;
const #15 = Asciz	regex;
const #16 = Asciz	Lscala/util/matching/Regex;;
const #17 = Asciz	source;
const #18 = Asciz	Ljava/lang/CharSequence;;
const #19 = Asciz	<init>;
const #20 = Asciz	(Ljava/lang/CharSequence;Lscala/util/matching/Regex;Lscala/collection/Seq;)V;
const #21 = Asciz	Code;
const #22 = Asciz	LineNumberTable;
const #23 = Asciz	scala/util/matching/Regex$MatchIterator;
const #24 = class	#23;	//  scala/util/matching/Regex$MatchIterator
const #25 = NameAndType	#17:#18;//  source:Ljava/lang/CharSequence;
const #26 = Field	#24.#25;	//  scala/util/matching/Regex$MatchIterator.source:Ljava/lang/CharSequence;
const #27 = NameAndType	#15:#16;//  regex:Lscala/util/matching/Regex;
const #28 = Field	#24.#27;	//  scala/util/matching/Regex$MatchIterator.regex:Lscala/util/matching/Regex;
const #29 = NameAndType	#11:#12;//  groupNames:Lscala/collection/Seq;
const #30 = Field	#24.#29;	//  scala/util/matching/Regex$MatchIterator.groupNames:Lscala/collection/Seq;
const #31 = Asciz	java/lang/Object;
const #32 = class	#31;	//  java/lang/Object
const #33 = Asciz	()V;
const #34 = NameAndType	#19:#33;//  "<init>":()V
const #35 = Method	#32.#34;	//  java/lang/Object."<init>":()V
const #36 = Asciz	scala/collection/Iterator$class;
const #37 = class	#36;	//  scala/collection/Iterator$class
const #38 = Asciz	$init$;
const #39 = Asciz	(Lscala/collection/Iterator;)V;
const #40 = NameAndType	#38:#39;//  $init$:(Lscala/collection/Iterator;)V
const #41 = Method	#37.#40;	//  scala/collection/Iterator$class.$init$:(Lscala/collection/Iterator;)V
const #42 = Asciz	scala/util/matching/Regex$MatchData$class;
const #43 = class	#42;	//  scala/util/matching/Regex$MatchData$class
const #44 = Asciz	(Lscala/util/matching/Regex$MatchData;)V;
const #45 = NameAndType	#38:#44;//  $init$:(Lscala/util/matching/Regex$MatchData;)V
const #46 = Method	#43.#45;	//  scala/util/matching/Regex$MatchData$class.$init$:(Lscala/util/matching/Regex$MatchData;)V
const #47 = Asciz	scala/util/matching/Regex;
const #48 = class	#47;	//  scala/util/matching/Regex
const #49 = Asciz	pattern;
const #50 = Asciz	()Ljava/util/regex/Pattern;;
const #51 = NameAndType	#49:#50;//  pattern:()Ljava/util/regex/Pattern;
const #52 = Method	#48.#51;	//  scala/util/matching/Regex.pattern:()Ljava/util/regex/Pattern;
const #53 = Asciz	java/util/regex/Pattern;
const #54 = class	#53;	//  java/util/regex/Pattern
const #55 = Asciz	matcher;
const #56 = Asciz	(Ljava/lang/CharSequence;)Ljava/util/regex/Matcher;;
const #57 = NameAndType	#55:#56;//  matcher:(Ljava/lang/CharSequence;)Ljava/util/regex/Matcher;
const #58 = Method	#54.#57;	//  java/util/regex/Pattern.matcher:(Ljava/lang/CharSequence;)Ljava/util/regex/Matcher;
const #59 = NameAndType	#9:#10;//  scala$util$matching$Regex$MatchIterator$$matcher:Ljava/util/regex/Matcher;
const #60 = Field	#24.#59;	//  scala/util/matching/Regex$MatchIterator.scala$util$matching$Regex$MatchIterator$$matcher:Ljava/util/regex/Matcher;
const #61 = NameAndType	#7:#8;//  nextSeen:Z
const #62 = Field	#24.#61;	//  scala/util/matching/Regex$MatchIterator.nextSeen:Z
const #63 = Asciz	this;
const #64 = Asciz	Lscala/util/matching/Regex$MatchIterator;;
const #65 = Asciz	LocalVariableTable;
const #66 = Asciz	(Ljava/lang/CharSequence;Lscala/util/matching/Regex;Lscala/collection/Seq<Ljava/lang/String;>;)V;
const #67 = Asciz	next;
const #68 = Asciz	()Ljava/lang/Object;;
const #69 = Asciz	()Ljava/lang/String;;
const #70 = NameAndType	#67:#69;//  next:()Ljava/lang/String;
const #71 = Method	#24.#70;	//  scala/util/matching/Regex$MatchIterator.next:()Ljava/lang/String;
const #72 = Asciz	matchData;
const #73 = Asciz	scala/util/matching/Regex$MatchIterator$$anon$1;
const #74 = class	#73;	//  scala/util/matching/Regex$MatchIterator$$anon$1
const #75 = Asciz	(Lscala/util/matching/Regex$MatchIterator;)V;
const #76 = NameAndType	#19:#75;//  "<init>":(Lscala/util/matching/Regex$MatchIterator;)V
const #77 = Method	#74.#76;	//  scala/util/matching/Regex$MatchIterator$$anon$1."<init>":(Lscala/util/matching/Regex$MatchIterator;)V
const #78 = Asciz	groupCount;
const #79 = Asciz	()I;
const #80 = Asciz	()Ljava/util/regex/Matcher;;
const #81 = NameAndType	#9:#80;//  scala$util$matching$Regex$MatchIterator$$matcher:()Ljava/util/regex/Matcher;
const #82 = Method	#24.#81;	//  scala/util/matching/Regex$MatchIterator.scala$util$matching$Regex$MatchIterator$$matcher:()Ljava/util/regex/Matcher;
const #83 = Asciz	java/util/regex/Matcher;
const #84 = class	#83;	//  java/util/regex/Matcher
const #85 = NameAndType	#78:#79;//  groupCount:()I
const #86 = Method	#84.#85;	//  java/util/regex/Matcher.groupCount:()I
const #87 = Asciz	end;
const #88 = Asciz	(I)I;
const #89 = NameAndType	#87:#88;//  end:(I)I
const #90 = Method	#84.#89;	//  java/util/regex/Matcher.end:(I)I
const #91 = Asciz	i;
const #92 = NameAndType	#87:#79;//  end:()I
const #93 = Method	#84.#92;	//  java/util/regex/Matcher.end:()I
const #94 = Asciz	start;
const #95 = NameAndType	#94:#88;//  start:(I)I
const #96 = Method	#84.#95;	//  java/util/regex/Matcher.start:(I)I
const #97 = NameAndType	#94:#79;//  start:()I
const #98 = Method	#84.#97;	//  java/util/regex/Matcher.start:()I
const #99 = Asciz	toString;
const #100 = Asciz	(Lscala/collection/Iterator;)Ljava/lang/String;;
const #101 = NameAndType	#99:#100;//  toString:(Lscala/collection/Iterator;)Ljava/lang/String;
const #102 = Method	#37.#101;	//  scala/collection/Iterator$class.toString:(Lscala/collection/Iterator;)Ljava/lang/String;
const #103 = Asciz	hasNext;
const #104 = Asciz	()Z;
const #105 = NameAndType	#103:#104;//  hasNext:()Z
const #106 = Method	#24.#105;	//  scala/util/matching/Regex$MatchIterator.hasNext:()Z
const #107 = Asciz	nextSeen_$eq;
const #108 = Asciz	(Z)V;
const #109 = NameAndType	#107:#108;//  nextSeen_$eq:(Z)V
const #110 = Method	#24.#109;	//  scala/util/matching/Regex$MatchIterator.nextSeen_$eq:(Z)V
const #111 = Asciz	group;
const #112 = NameAndType	#111:#69;//  group:()Ljava/lang/String;
const #113 = Method	#84.#112;	//  java/util/regex/Matcher.group:()Ljava/lang/String;
const #114 = Asciz	java/util/NoSuchElementException;
const #115 = class	#114;	//  java/util/NoSuchElementException
const #116 = Method	#115.#34;	//  java/util/NoSuchElementException."<init>":()V
const #117 = NameAndType	#7:#104;//  nextSeen:()Z
const #118 = Method	#24.#117;	//  scala/util/matching/Regex$MatchIterator.nextSeen:()Z
const #119 = Asciz	find;
const #120 = NameAndType	#119:#104;//  find:()Z
const #121 = Method	#84.#120;	//  java/util/regex/Matcher.find:()Z
const #122 = Asciz	()Lscala/collection/Seq;;
const #123 = Asciz	()Lscala/collection/Seq<Ljava/lang/String;>;;
const #124 = Asciz	()Lscala/util/matching/Regex;;
const #125 = Asciz	()Ljava/lang/CharSequence;;
const #126 = Asciz	sliding$default$2;
const #127 = Asciz	(Lscala/collection/Iterator;)I;
const #128 = NameAndType	#126:#127;//  sliding$default$2:(Lscala/collection/Iterator;)I
const #129 = Method	#37.#128;	//  scala/collection/Iterator$class.sliding$default$2:(Lscala/collection/Iterator;)I
const #130 = Asciz	readInto;
const #131 = Asciz	(Ljava/lang/Object;)V;
const #132 = Asciz	(Lscala/collection/Iterator;Ljava/lang/Object;)V;
const #133 = NameAndType	#130:#132;//  readInto:(Lscala/collection/Iterator;Ljava/lang/Object;)V
const #134 = Method	#37.#133;	//  scala/collection/Iterator$class.readInto:(Lscala/collection/Iterator;Ljava/lang/Object;)V
const #135 = Asciz	xs;
const #136 = Asciz	Ljava/lang/Object;;
const #137 = Asciz	(Ljava/lang/Object;I)V;
const #138 = Asciz	(Lscala/collection/Iterator;Ljava/lang/Object;I)V;
const #139 = NameAndType	#130:#138;//  readInto:(Lscala/collection/Iterator;Ljava/lang/Object;I)V
const #140 = Method	#37.#139;	//  scala/collection/Iterator$class.readInto:(Lscala/collection/Iterator;Ljava/lang/Object;I)V
const #141 = Asciz	(Ljava/lang/Object;II)V;
const #142 = Asciz	(Lscala/collection/Iterator;Ljava/lang/Object;II)V;
const #143 = NameAndType	#130:#142;//  readInto:(Lscala/collection/Iterator;Ljava/lang/Object;II)V
const #144 = Method	#37.#143;	//  scala/collection/Iterator$class.readInto:(Lscala/collection/Iterator;Ljava/lang/Object;II)V
const #145 = Asciz	sz;
const #146 = Asciz	counted;
const #147 = Asciz	(Lscala/collection/Iterator;)Ljava/lang/Object;;
const #148 = NameAndType	#146:#147;//  counted:(Lscala/collection/Iterator;)Ljava/lang/Object;
const #149 = Method	#37.#148;	//  scala/collection/Iterator$class.counted:(Lscala/collection/Iterator;)Ljava/lang/Object;
const #150 = Asciz	collect;
const #151 = Asciz	(Lscala/collection/Iterator;)Lscala/collection/Seq;;
const #152 = NameAndType	#150:#151;//  collect:(Lscala/collection/Iterator;)Lscala/collection/Seq;
const #153 = Method	#37.#152;	//  scala/collection/Iterator$class.collect:(Lscala/collection/Iterator;)Lscala/collection/Seq;
const #154 = Asciz	findIndexOf;
const #155 = Asciz	(Lscala/Function1;)I;
const #156 = Asciz	(Lscala/collection/Iterator;Lscala/Function1;)I;
const #157 = NameAndType	#154:#156;//  findIndexOf:(Lscala/collection/Iterator;Lscala/Function1;)I
const #158 = Method	#37.#157;	//  scala/collection/Iterator$class.findIndexOf:(Lscala/collection/Iterator;Lscala/Function1;)I
const #159 = Asciz	p;
const #160 = Asciz	Lscala/Function1;;
const #161 = Asciz	append;
const #162 = Asciz	(Lscala/collection/Iterator;)Lscala/collection/Iterator;;
const #163 = Asciz	(Lscala/collection/Iterator;Lscala/collection/Iterator;)Lscala/collection/Iterator;;
const #164 = NameAndType	#161:#163;//  append:(Lscala/collection/Iterator;Lscala/collection/Iterator;)Lscala/collection/Iterator;
const #165 = Method	#37.#164;	//  scala/collection/Iterator$class.append:(Lscala/collection/Iterator;Lscala/collection/Iterator;)Lscala/collection/Iterator;
const #166 = Asciz	that;
const #167 = Asciz	Lscala/collection/Iterator;;
const #168 = Asciz	addString;
const #169 = Asciz	(Lscala/collection/mutable/StringBuilder;)Lscala/collection/mutable/StringBuilder;;
const #170 = Asciz	(Lscala/collection/Iterator;Lscala/collection/mutable/StringBuilder;)Lscala/collection/mutable/StringBuilder;;
const #171 = NameAndType	#168:#170;//  addString:(Lscala/collection/Iterator;Lscala/collection/mutable/StringBuilder;)Lscala/collection/mutable/StringBuilder;
const #172 = Method	#37.#171;	//  scala/collection/Iterator$class.addString:(Lscala/collection/Iterator;Lscala/collection/mutable/StringBuilder;)Lscala/collection/mutable/StringBuilder;
const #173 = Asciz	buf;
const #174 = Asciz	Lscala/collection/mutable/StringBuilder;;
const #175 = Asciz	(Lscala/collection/mutable/StringBuilder;Ljava/lang/String;)Lscala/collection/mutable/StringBuilder;;
const #176 = Asciz	(Lscala/collection/Iterator;Lscala/collection/mutable/StringBuilder;Ljava/lang/String;)Lscala/collection/mutable/StringBuilder;;
const #177 = NameAndType	#168:#176;//  addString:(Lscala/collection/Iterator;Lscala/collection/mutable/StringBuilder;Ljava/lang/String;)Lscala/collection/mutable/StringBuilder;
const #178 = Method	#37.#177;	//  scala/collection/Iterator$class.addString:(Lscala/collection/Iterator;Lscala/collection/mutable/StringBuilder;Ljava/lang/String;)Lscala/collection/mutable/StringBuilder;
const #179 = Asciz	sep;
const #180 = Asciz	Ljava/lang/String;;
const #181 = Asciz	(Lscala/collection/mutable/StringBuilder;Ljava/lang/String;Ljava/lang/String;Ljava/lang/String;)Lscala/collection/mutable/StringBuilder;;
const #182 = Asciz	(Lscala/collection/Iterator;Lscala/collection/mutable/StringBuilder;Ljava/lang/String;Ljava/lang/String;Ljava/lang/String;)Lscala/collection/mutable/StringBuilder;;
const #183 = NameAndType	#168:#182;//  addString:(Lscala/collection/Iterator;Lscala/collection/mutable/StringBuilder;Ljava/lang/String;Ljava/lang/String;Ljava/lang/String;)Lscala/collection/mutable/StringBuilder;
const #184 = Method	#37.#183;	//  scala/collection/Iterator$class.addString:(Lscala/collection/Iterator;Lscala/collection/mutable/StringBuilder;Ljava/lang/String;Ljava/lang/String;Ljava/lang/String;)Lscala/collection/mutable/StringBuilder;
const #185 = Asciz	mkString;
const #186 = NameAndType	#185:#100;//  mkString:(Lscala/collection/Iterator;)Ljava/lang/String;
const #187 = Method	#37.#186;	//  scala/collection/Iterator$class.mkString:(Lscala/collection/Iterator;)Ljava/lang/String;
const #188 = Asciz	(Ljava/lang/String;)Ljava/lang/String;;
const #189 = Asciz	(Lscala/collection/Iterator;Ljava/lang/String;)Ljava/lang/String;;
const #190 = NameAndType	#185:#189;//  mkString:(Lscala/collection/Iterator;Ljava/lang/String;)Ljava/lang/String;
const #191 = Method	#37.#190;	//  scala/collection/Iterator$class.mkString:(Lscala/collection/Iterator;Ljava/lang/String;)Ljava/lang/String;
const #192 = Asciz	(Ljava/lang/String;Ljava/lang/String;Ljava/lang/String;)Ljava/lang/String;;
const #193 = Asciz	(Lscala/collection/Iterator;Ljava/lang/String;Ljava/lang/String;Ljava/lang/String;)Ljava/lang/String;;
const #194 = NameAndType	#185:#193;//  mkString:(Lscala/collection/Iterator;Ljava/lang/String;Ljava/lang/String;Ljava/lang/String;)Ljava/lang/String;
const #195 = Method	#37.#194;	//  scala/collection/Iterator$class.mkString:(Lscala/collection/Iterator;Ljava/lang/String;Ljava/lang/String;Ljava/lang/String;)Ljava/lang/String;
const #196 = Asciz	sameElements;
const #197 = Asciz	(Lscala/collection/Iterator;)Z;
const #198 = Asciz	(Lscala/collection/Iterator;Lscala/collection/Iterator;)Z;
const #199 = NameAndType	#196:#198;//  sameElements:(Lscala/collection/Iterator;Lscala/collection/Iterator;)Z
const #200 = Method	#37.#199;	//  scala/collection/Iterator$class.sameElements:(Lscala/collection/Iterator;Lscala/collection/Iterator;)Z
const #201 = Asciz	toSeq;
const #202 = NameAndType	#201:#151;//  toSeq:(Lscala/collection/Iterator;)Lscala/collection/Seq;
const #203 = Method	#37.#202;	//  scala/collection/Iterator$class.toSeq:(Lscala/collection/Iterator;)Lscala/collection/Seq;
const #204 = Asciz	toStream;
const #205 = Asciz	()Lscala/collection/immutable/Stream;;
const #206 = Asciz	(Lscala/collection/Iterator;)Lscala/collection/immutable/Stream;;
const #207 = NameAndType	#204:#206;//  toStream:(Lscala/collection/Iterator;)Lscala/collection/immutable/Stream;
const #208 = Method	#37.#207;	//  scala/collection/Iterator$class.toStream:(Lscala/collection/Iterator;)Lscala/collection/immutable/Stream;
const #209 = Asciz	toList;
const #210 = Asciz	()Lscala/collection/immutable/List;;
const #211 = Asciz	(Lscala/collection/Iterator;)Lscala/collection/immutable/List;;
const #212 = NameAndType	#209:#211;//  toList:(Lscala/collection/Iterator;)Lscala/collection/immutable/List;
const #213 = Method	#37.#212;	//  scala/collection/Iterator$class.toList:(Lscala/collection/Iterator;)Lscala/collection/immutable/List;
const #214 = Asciz	copyToBuffer;
const #215 = Asciz	(Lscala/collection/mutable/Buffer;)V;
const #216 = Asciz	(Lscala/collection/Iterator;Lscala/collection/mutable/Buffer;)V;
const #217 = NameAndType	#214:#216;//  copyToBuffer:(Lscala/collection/Iterator;Lscala/collection/mutable/Buffer;)V
const #218 = Method	#37.#217;	//  scala/collection/Iterator$class.copyToBuffer:(Lscala/collection/Iterator;Lscala/collection/mutable/Buffer;)V
const #219 = Asciz	dest;
const #220 = Asciz	Lscala/collection/mutable/Buffer;;
const #221 = Asciz	copyToArray;
const #222 = NameAndType	#221:#132;//  copyToArray:(Lscala/collection/Iterator;Ljava/lang/Object;)V
const #223 = Method	#37.#222;	//  scala/collection/Iterator$class.copyToArray:(Lscala/collection/Iterator;Ljava/lang/Object;)V
const #224 = NameAndType	#221:#138;//  copyToArray:(Lscala/collection/Iterator;Ljava/lang/Object;I)V
const #225 = Method	#37.#224;	//  scala/collection/Iterator$class.copyToArray:(Lscala/collection/Iterator;Ljava/lang/Object;I)V
const #226 = NameAndType	#221:#142;//  copyToArray:(Lscala/collection/Iterator;Ljava/lang/Object;II)V
const #227 = Method	#37.#226;	//  scala/collection/Iterator$class.copyToArray:(Lscala/collection/Iterator;Ljava/lang/Object;II)V
const #228 = Asciz	len;
const #229 = Asciz	patch;
const #230 = Asciz	(ILscala/collection/Iterator;I)Ljava/lang/Object;;
const #231 = Asciz	(Lscala/collection/Iterator;ILscala/collection/Iterator;I)Ljava/lang/Object;;
const #232 = NameAndType	#229:#231;//  patch:(Lscala/collection/Iterator;ILscala/collection/Iterator;I)Ljava/lang/Object;
const #233 = Method	#37.#232;	//  scala/collection/Iterator$class.patch:(Lscala/collection/Iterator;ILscala/collection/Iterator;I)Ljava/lang/Object;
const #234 = Asciz	from;
const #235 = Asciz	patchElems;
const #236 = Asciz	replaced;
const #237 = Asciz	duplicate;
const #238 = Asciz	()Lscala/Tuple2;;
const #239 = Asciz	(Lscala/collection/Iterator;)Lscala/Tuple2;;
const #240 = NameAndType	#237:#239;//  duplicate:(Lscala/collection/Iterator;)Lscala/Tuple2;
const #241 = Method	#37.#240;	//  scala/collection/Iterator$class.duplicate:(Lscala/collection/Iterator;)Lscala/Tuple2;
const #242 = Asciz	length;
const #243 = NameAndType	#242:#127;//  length:(Lscala/collection/Iterator;)I
const #244 = Method	#37.#243;	//  scala/collection/Iterator$class.length:(Lscala/collection/Iterator;)I
const #245 = Asciz	sliding;
const #246 = Asciz	(II)Lscala/collection/Iterator$GroupedIterator;;
const #247 = Asciz	(Lscala/collection/Iterator;II)Lscala/collection/Iterator$GroupedIterator;;
const #248 = NameAndType	#245:#247;//  sliding:(Lscala/collection/Iterator;II)Lscala/collection/Iterator$GroupedIterator;
const #249 = Method	#37.#248;	//  scala/collection/Iterator$class.sliding:(Lscala/collection/Iterator;II)Lscala/collection/Iterator$GroupedIterator;
const #250 = Asciz	size;
const #251 = Asciz	step;
const #252 = Asciz	grouped;
const #253 = Asciz	(I)Lscala/collection/Iterator$GroupedIterator;;
const #254 = Asciz	(Lscala/collection/Iterator;I)Lscala/collection/Iterator$GroupedIterator;;
const #255 = NameAndType	#252:#254;//  grouped:(Lscala/collection/Iterator;I)Lscala/collection/Iterator$GroupedIterator;
const #256 = Method	#37.#255;	//  scala/collection/Iterator$class.grouped:(Lscala/collection/Iterator;I)Lscala/collection/Iterator$GroupedIterator;
const #257 = Asciz	buffered;
const #258 = NameAndType	#257:#147;//  buffered:(Lscala/collection/Iterator;)Ljava/lang/Object;
const #259 = Method	#37.#258;	//  scala/collection/Iterator$class.buffered:(Lscala/collection/Iterator;)Ljava/lang/Object;
const #260 = Asciz	reduceRightOption;
const #261 = Asciz	(Lscala/Function2;)Lscala/Option;;
const #262 = Asciz	(Lscala/collection/Iterator;Lscala/Function2;)Lscala/Option;;
const #263 = NameAndType	#260:#262;//  reduceRightOption:(Lscala/collection/Iterator;Lscala/Function2;)Lscala/Option;
const #264 = Method	#37.#263;	//  scala/collection/Iterator$class.reduceRightOption:(Lscala/collection/Iterator;Lscala/Function2;)Lscala/Option;
const #265 = Asciz	op;
const #266 = Asciz	Lscala/Function2;;
const #267 = Asciz	reduceLeftOption;
const #268 = NameAndType	#267:#262;//  reduceLeftOption:(Lscala/collection/Iterator;Lscala/Function2;)Lscala/Option;
const #269 = Method	#37.#268;	//  scala/collection/Iterator$class.reduceLeftOption:(Lscala/collection/Iterator;Lscala/Function2;)Lscala/Option;
const #270 = Asciz	reduceRight;
const #271 = Asciz	(Lscala/Function2;)Ljava/lang/Object;;
const #272 = Asciz	(Lscala/collection/Iterator;Lscala/Function2;)Ljava/lang/Object;;
const #273 = NameAndType	#270:#272;//  reduceRight:(Lscala/collection/Iterator;Lscala/Function2;)Ljava/lang/Object;
const #274 = Method	#37.#273;	//  scala/collection/Iterator$class.reduceRight:(Lscala/collection/Iterator;Lscala/Function2;)Ljava/lang/Object;
const #275 = Asciz	reduceLeft;
const #276 = NameAndType	#275:#272;//  reduceLeft:(Lscala/collection/Iterator;Lscala/Function2;)Ljava/lang/Object;
const #277 = Method	#37.#276;	//  scala/collection/Iterator$class.reduceLeft:(Lscala/collection/Iterator;Lscala/Function2;)Ljava/lang/Object;
const #278 = Asciz	$colon$bslash;
const #279 = Asciz	(Ljava/lang/Object;Lscala/Function2;)Ljava/lang/Object;;
const #280 = Asciz	(Lscala/collection/Iterator;Ljava/lang/Object;Lscala/Function2;)Ljava/lang/Object;;
const #281 = NameAndType	#278:#280;//  $colon$bslash:(Lscala/collection/Iterator;Ljava/lang/Object;Lscala/Function2;)Ljava/lang/Object;
const #282 = Method	#37.#281;	//  scala/collection/Iterator$class.$colon$bslash:(Lscala/collection/Iterator;Ljava/lang/Object;Lscala/Function2;)Ljava/lang/Object;
const #283 = Asciz	z;
const #284 = Asciz	$div$colon;
const #285 = NameAndType	#284:#280;//  $div$colon:(Lscala/collection/Iterator;Ljava/lang/Object;Lscala/Function2;)Ljava/lang/Object;
const #286 = Method	#37.#285;	//  scala/collection/Iterator$class.$div$colon:(Lscala/collection/Iterator;Ljava/lang/Object;Lscala/Function2;)Ljava/lang/Object;
const #287 = Asciz	foldRight;
const #288 = NameAndType	#287:#280;//  foldRight:(Lscala/collection/Iterator;Ljava/lang/Object;Lscala/Function2;)Ljava/lang/Object;
const #289 = Method	#37.#288;	//  scala/collection/Iterator$class.foldRight:(Lscala/collection/Iterator;Ljava/lang/Object;Lscala/Function2;)Ljava/lang/Object;
const #290 = Asciz	foldLeft;
const #291 = NameAndType	#290:#280;//  foldLeft:(Lscala/collection/Iterator;Ljava/lang/Object;Lscala/Function2;)Ljava/lang/Object;
const #292 = Method	#37.#291;	//  scala/collection/Iterator$class.foldLeft:(Lscala/collection/Iterator;Ljava/lang/Object;Lscala/Function2;)Ljava/lang/Object;
const #293 = Asciz	indexOf;
const #294 = Asciz	(Ljava/lang/Object;)I;
const #295 = Asciz	(Lscala/collection/Iterator;Ljava/lang/Object;)I;
const #296 = NameAndType	#293:#295;//  indexOf:(Lscala/collection/Iterator;Ljava/lang/Object;)I
const #297 = Method	#37.#296;	//  scala/collection/Iterator$class.indexOf:(Lscala/collection/Iterator;Ljava/lang/Object;)I
const #298 = Asciz	elem;
const #299 = Asciz	indexWhere;
const #300 = NameAndType	#299:#156;//  indexWhere:(Lscala/collection/Iterator;Lscala/Function1;)I
const #301 = Method	#37.#300;	//  scala/collection/Iterator$class.indexWhere:(Lscala/collection/Iterator;Lscala/Function1;)I
const #302 = Asciz	(Lscala/Function1;)Lscala/Option;;
const #303 = Asciz	(Lscala/collection/Iterator;Lscala/Function1;)Lscala/Option;;
const #304 = NameAndType	#119:#303;//  find:(Lscala/collection/Iterator;Lscala/Function1;)Lscala/Option;
const #305 = Method	#37.#304;	//  scala/collection/Iterator$class.find:(Lscala/collection/Iterator;Lscala/Function1;)Lscala/Option;
const #306 = Asciz	contains;
const #307 = Asciz	(Ljava/lang/Object;)Z;
const #308 = Asciz	(Lscala/collection/Iterator;Ljava/lang/Object;)Z;
const #309 = NameAndType	#306:#308;//  contains:(Lscala/collection/Iterator;Ljava/lang/Object;)Z
const #310 = Method	#37.#309;	//  scala/collection/Iterator$class.contains:(Lscala/collection/Iterator;Ljava/lang/Object;)Z
const #311 = Asciz	exists;
const #312 = Asciz	(Lscala/Function1;)Z;
const #313 = Asciz	(Lscala/collection/Iterator;Lscala/Function1;)Z;
const #314 = NameAndType	#311:#313;//  exists:(Lscala/collection/Iterator;Lscala/Function1;)Z
const #315 = Method	#37.#314;	//  scala/collection/Iterator$class.exists:(Lscala/collection/Iterator;Lscala/Function1;)Z
const #316 = Asciz	forall;
const #317 = NameAndType	#316:#313;//  forall:(Lscala/collection/Iterator;Lscala/Function1;)Z
const #318 = Method	#37.#317;	//  scala/collection/Iterator$class.forall:(Lscala/collection/Iterator;Lscala/Function1;)Z
const #319 = Asciz	foreach;
const #320 = Asciz	(Lscala/Function1;)V;
const #321 = Asciz	(Lscala/collection/Iterator;Lscala/Function1;)V;
const #322 = NameAndType	#319:#321;//  foreach:(Lscala/collection/Iterator;Lscala/Function1;)V
const #323 = Method	#37.#322;	//  scala/collection/Iterator$class.foreach:(Lscala/collection/Iterator;Lscala/Function1;)V
const #324 = Asciz	f;
const #325 = Asciz	zipAll;
const #326 = Asciz	(Lscala/collection/Iterator;Ljava/lang/Object;Ljava/lang/Object;)Ljava/lang/Object;;
const #327 = Asciz	(Lscala/collection/Iterator;Lscala/collection/Iterator;Ljava/lang/Object;Ljava/lang/Object;)Ljava/lang/Object;;
const #328 = NameAndType	#325:#327;//  zipAll:(Lscala/collection/Iterator;Lscala/collection/Iterator;Ljava/lang/Object;Ljava/lang/Object;)Ljava/lang/Object;
const #329 = Method	#37.#328;	//  scala/collection/Iterator$class.zipAll:(Lscala/collection/Iterator;Lscala/collection/Iterator;Ljava/lang/Object;Ljava/lang/Object;)Ljava/lang/Object;
const #330 = Asciz	thisElem;
const #331 = Asciz	thatElem;
const #332 = Asciz	zipWithIndex;
const #333 = NameAndType	#332:#147;//  zipWithIndex:(Lscala/collection/Iterator;)Ljava/lang/Object;
const #334 = Method	#37.#333;	//  scala/collection/Iterator$class.zipWithIndex:(Lscala/collection/Iterator;)Ljava/lang/Object;
const #335 = Asciz	padTo;
const #336 = Asciz	(ILjava/lang/Object;)Ljava/lang/Object;;
const #337 = Asciz	(Lscala/collection/Iterator;ILjava/lang/Object;)Ljava/lang/Object;;
const #338 = NameAndType	#335:#337;//  padTo:(Lscala/collection/Iterator;ILjava/lang/Object;)Ljava/lang/Object;
const #339 = Method	#37.#338;	//  scala/collection/Iterator$class.padTo:(Lscala/collection/Iterator;ILjava/lang/Object;)Ljava/lang/Object;
const #340 = Asciz	zip;
const #341 = Asciz	(Lscala/collection/Iterator;Lscala/collection/Iterator;)Ljava/lang/Object;;
const #342 = NameAndType	#340:#341;//  zip:(Lscala/collection/Iterator;Lscala/collection/Iterator;)Ljava/lang/Object;
const #343 = Method	#37.#342;	//  scala/collection/Iterator$class.zip:(Lscala/collection/Iterator;Lscala/collection/Iterator;)Ljava/lang/Object;
const #344 = Asciz	dropWhile;
const #345 = Asciz	(Lscala/Function1;)Lscala/collection/Iterator;;
const #346 = Asciz	(Lscala/collection/Iterator;Lscala/Function1;)Lscala/collection/Iterator;;
const #347 = NameAndType	#344:#346;//  dropWhile:(Lscala/collection/Iterator;Lscala/Function1;)Lscala/collection/Iterator;
const #348 = Method	#37.#347;	//  scala/collection/Iterator$class.dropWhile:(Lscala/collection/Iterator;Lscala/Function1;)Lscala/collection/Iterator;
const #349 = Asciz	partition;
const #350 = Asciz	(Lscala/Function1;)Lscala/Tuple2;;
const #351 = Asciz	(Lscala/collection/Iterator;Lscala/Function1;)Lscala/Tuple2;;
const #352 = NameAndType	#349:#351;//  partition:(Lscala/collection/Iterator;Lscala/Function1;)Lscala/Tuple2;
const #353 = Method	#37.#352;	//  scala/collection/Iterator$class.partition:(Lscala/collection/Iterator;Lscala/Function1;)Lscala/Tuple2;
const #354 = Asciz	takeWhile;
const #355 = NameAndType	#354:#346;//  takeWhile:(Lscala/collection/Iterator;Lscala/Function1;)Lscala/collection/Iterator;
const #356 = Method	#37.#355;	//  scala/collection/Iterator$class.takeWhile:(Lscala/collection/Iterator;Lscala/Function1;)Lscala/collection/Iterator;
const #357 = Asciz	partialMap;
const #358 = Asciz	(Lscala/PartialFunction;)Lscala/collection/Iterator;;
const #359 = Asciz	(Lscala/collection/Iterator;Lscala/PartialFunction;)Lscala/collection/Iterator;;
const #360 = NameAndType	#357:#359;//  partialMap:(Lscala/collection/Iterator;Lscala/PartialFunction;)Lscala/collection/Iterator;
const #361 = Method	#37.#360;	//  scala/collection/Iterator$class.partialMap:(Lscala/collection/Iterator;Lscala/PartialFunction;)Lscala/collection/Iterator;
const #362 = Asciz	pf;
const #363 = Asciz	Lscala/PartialFunction;;
const #364 = Asciz	filterNot;
const #365 = NameAndType	#364:#346;//  filterNot:(Lscala/collection/Iterator;Lscala/Function1;)Lscala/collection/Iterator;
const #366 = Method	#37.#365;	//  scala/collection/Iterator$class.filterNot:(Lscala/collection/Iterator;Lscala/Function1;)Lscala/collection/Iterator;
const #367 = Asciz	withFilter;
const #368 = Asciz	(Lscala/Function1;)Lscala/collection/Iterator$WithFilter;;
const #369 = Asciz	(Lscala/collection/Iterator;Lscala/Function1;)Lscala/collection/Iterator$WithFilter;;
const #370 = NameAndType	#367:#369;//  withFilter:(Lscala/collection/Iterator;Lscala/Function1;)Lscala/collection/Iterator$WithFilter;
const #371 = Method	#37.#370;	//  scala/collection/Iterator$class.withFilter:(Lscala/collection/Iterator;Lscala/Function1;)Lscala/collection/Iterator$WithFilter;
const #372 = Asciz	filter;
const #373 = NameAndType	#372:#346;//  filter:(Lscala/collection/Iterator;Lscala/Function1;)Lscala/collection/Iterator;
const #374 = Method	#37.#373;	//  scala/collection/Iterator$class.filter:(Lscala/collection/Iterator;Lscala/Function1;)Lscala/collection/Iterator;
const #375 = Asciz	flatMap;
const #376 = NameAndType	#375:#346;//  flatMap:(Lscala/collection/Iterator;Lscala/Function1;)Lscala/collection/Iterator;
const #377 = Method	#37.#376;	//  scala/collection/Iterator$class.flatMap:(Lscala/collection/Iterator;Lscala/Function1;)Lscala/collection/Iterator;
const #378 = Asciz	$plus$plus;
const #379 = Asciz	(Lscala/Function0;)Lscala/collection/Iterator;;
const #380 = Asciz	(Lscala/collection/Iterator;Lscala/Function0;)Lscala/collection/Iterator;;
const #381 = NameAndType	#378:#380;//  $plus$plus:(Lscala/collection/Iterator;Lscala/Function0;)Lscala/collection/Iterator;
const #382 = Method	#37.#381;	//  scala/collection/Iterator$class.$plus$plus:(Lscala/collection/Iterator;Lscala/Function0;)Lscala/collection/Iterator;
const #383 = Asciz	Lscala/Function0;;
const #384 = Asciz	map;
const #385 = NameAndType	#384:#346;//  map:(Lscala/collection/Iterator;Lscala/Function1;)Lscala/collection/Iterator;
const #386 = Method	#37.#385;	//  scala/collection/Iterator$class.map:(Lscala/collection/Iterator;Lscala/Function1;)Lscala/collection/Iterator;
const #387 = Asciz	slice;
const #388 = Asciz	(II)Lscala/collection/Iterator;;
const #389 = Asciz	(Lscala/collection/Iterator;II)Lscala/collection/Iterator;;
const #390 = NameAndType	#387:#389;//  slice:(Lscala/collection/Iterator;II)Lscala/collection/Iterator;
const #391 = Method	#37.#390;	//  scala/collection/Iterator$class.slice:(Lscala/collection/Iterator;II)Lscala/collection/Iterator;
const #392 = Asciz	until;
const #393 = Asciz	drop;
const #394 = Asciz	(I)Lscala/collection/Iterator;;
const #395 = Asciz	(Lscala/collection/Iterator;I)Lscala/collection/Iterator;;
const #396 = NameAndType	#393:#395;//  drop:(Lscala/collection/Iterator;I)Lscala/collection/Iterator;
const #397 = Method	#37.#396;	//  scala/collection/Iterator$class.drop:(Lscala/collection/Iterator;I)Lscala/collection/Iterator;
const #398 = Asciz	n;
const #399 = Asciz	take;
const #400 = NameAndType	#399:#395;//  take:(Lscala/collection/Iterator;I)Lscala/collection/Iterator;
const #401 = Method	#37.#400;	//  scala/collection/Iterator$class.take:(Lscala/collection/Iterator;I)Lscala/collection/Iterator;
const #402 = Asciz	(Lscala/util/matching/Regex$MatchData;Ljava/lang/String;)Ljava/lang/String;;
const #403 = NameAndType	#111:#402;//  group:(Lscala/util/matching/Regex$MatchData;Ljava/lang/String;)Ljava/lang/String;
const #404 = Method	#43.#403;	//  scala/util/matching/Regex$MatchData$class.group:(Lscala/util/matching/Regex$MatchData;Ljava/lang/String;)Ljava/lang/String;
const #405 = Asciz	id;
const #406 = Asciz	after;
const #407 = Asciz	(I)Ljava/lang/CharSequence;;
const #408 = Asciz	(Lscala/util/matching/Regex$MatchData;I)Ljava/lang/CharSequence;;
const #409 = NameAndType	#406:#408;//  after:(Lscala/util/matching/Regex$MatchData;I)Ljava/lang/CharSequence;
const #410 = Method	#43.#409;	//  scala/util/matching/Regex$MatchData$class.after:(Lscala/util/matching/Regex$MatchData;I)Ljava/lang/CharSequence;
const #411 = Asciz	(Lscala/util/matching/Regex$MatchData;)Ljava/lang/CharSequence;;
const #412 = NameAndType	#406:#411;//  after:(Lscala/util/matching/Regex$MatchData;)Ljava/lang/CharSequence;
const #413 = Method	#43.#412;	//  scala/util/matching/Regex$MatchData$class.after:(Lscala/util/matching/Regex$MatchData;)Ljava/lang/CharSequence;
const #414 = Asciz	before;
const #415 = NameAndType	#414:#408;//  before:(Lscala/util/matching/Regex$MatchData;I)Ljava/lang/CharSequence;
const #416 = Method	#43.#415;	//  scala/util/matching/Regex$MatchData$class.before:(Lscala/util/matching/Regex$MatchData;I)Ljava/lang/CharSequence;
const #417 = NameAndType	#414:#411;//  before:(Lscala/util/matching/Regex$MatchData;)Ljava/lang/CharSequence;
const #418 = Method	#43.#417;	//  scala/util/matching/Regex$MatchData$class.before:(Lscala/util/matching/Regex$MatchData;)Ljava/lang/CharSequence;
const #419 = Asciz	subgroups;
const #420 = Asciz	(Lscala/util/matching/Regex$MatchData;)Lscala/collection/immutable/List;;
const #421 = NameAndType	#419:#420;//  subgroups:(Lscala/util/matching/Regex$MatchData;)Lscala/collection/immutable/List;
const #422 = Method	#43.#421;	//  scala/util/matching/Regex$MatchData$class.subgroups:(Lscala/util/matching/Regex$MatchData;)Lscala/collection/immutable/List;
const #423 = Asciz	(I)Ljava/lang/String;;
const #424 = Asciz	(Lscala/util/matching/Regex$MatchData;I)Ljava/lang/String;;
const #425 = NameAndType	#111:#424;//  group:(Lscala/util/matching/Regex$MatchData;I)Ljava/lang/String;
const #426 = Method	#43.#425;	//  scala/util/matching/Regex$MatchData$class.group:(Lscala/util/matching/Regex$MatchData;I)Ljava/lang/String;
const #427 = Asciz	matched;
const #428 = Asciz	(Lscala/util/matching/Regex$MatchData;)Ljava/lang/String;;
const #429 = NameAndType	#427:#428;//  matched:(Lscala/util/matching/Regex$MatchData;)Ljava/lang/String;
const #430 = Method	#43.#429;	//  scala/util/matching/Regex$MatchData$class.matched:(Lscala/util/matching/Regex$MatchData;)Ljava/lang/String;
const #431 = Asciz	()Lscala/collection/immutable/Map;;
const #432 = NameAndType	#3:#4;//  bitmap$0:I
const #433 = Field	#24.#432;	//  scala/util/matching/Regex$MatchIterator.bitmap$0:I
const #434 = Asciz	(Lscala/util/matching/Regex$MatchData;)Lscala/collection/immutable/Map;;
const #435 = NameAndType	#5:#434;//  scala$util$matching$Regex$MatchData$$nameToIndex:(Lscala/util/matching/Regex$MatchData;)Lscala/collection/immutable/Map;
const #436 = Method	#43.#435;	//  scala/util/matching/Regex$MatchData$class.scala$util$matching$Regex$MatchData$$nameToIndex:(Lscala/util/matching/Regex$MatchData;)Lscala/collection/immutable/Map;
const #437 = NameAndType	#5:#6;//  scala$util$matching$Regex$MatchData$$nameToIndex:Lscala/collection/immutable/Map;
const #438 = Field	#24.#437;	//  scala/util/matching/Regex$MatchIterator.scala$util$matching$Regex$MatchData$$nameToIndex:Lscala/collection/immutable/Map;
const #439 = Asciz	Ljava/lang/Object;Lscala/collection/Iterator<Ljava/lang/String;>;Lscala/util/matching/Regex$MatchData;Lscala/ScalaObject;;
const #440 = Asciz	Scala;
const #441 = Asciz	InnerClasses;
const #442 = Asciz	scala/util/matching/Regex$MatchData;
const #443 = class	#442;	//  scala/util/matching/Regex$MatchData
const #444 = Asciz	MatchData;
const #445 = Asciz	scala/collection/Iterator$WithFilter;
const #446 = class	#445;	//  scala/collection/Iterator$WithFilter
const #447 = Asciz	scala/collection/Iterator;
const #448 = class	#447;	//  scala/collection/Iterator
const #449 = Asciz	WithFilter;
const #450 = Asciz	MatchIterator;
const #451 = Asciz	scala/collection/Iterator$GroupedIterator;
const #452 = class	#451;	//  scala/collection/Iterator$GroupedIterator
const #453 = Asciz	GroupedIterator;
const #454 = Asciz	$anon$1;
const #455 = Asciz	scala/ScalaObject;
const #456 = class	#455;	//  scala/ScalaObject

{
public volatile int bitmap$0;

public scala.util.matching.Regex$MatchIterator(java.lang.CharSequence, scala.util.matching.Regex, scala.collection.Seq);
  Code:
   Stack=3, Locals=4, Args_size=4
   0:	aload_0
   1:	aload_1
   2:	putfield	#26; //Field source:Ljava/lang/CharSequence;
   5:	aload_0
   6:	aload_2
   7:	putfield	#28; //Field regex:Lscala/util/matching/Regex;
   10:	aload_0
   11:	aload_3
   12:	putfield	#30; //Field groupNames:Lscala/collection/Seq;
   15:	aload_0
   16:	invokespecial	#35; //Method java/lang/Object."<init>":()V
   19:	aload_0
   20:	invokestatic	#41; //Method scala/collection/Iterator$class.$init$:(Lscala/collection/Iterator;)V
   23:	aload_0
   24:	invokestatic	#46; //Method scala/util/matching/Regex$MatchData$class.$init$:(Lscala/util/matching/Regex$MatchData;)V
   27:	aload_0
   28:	aload_2
   29:	invokevirtual	#52; //Method scala/util/matching/Regex.pattern:()Ljava/util/regex/Pattern;
   32:	aload_1
   33:	invokevirtual	#58; //Method java/util/regex/Pattern.matcher:(Ljava/lang/CharSequence;)Ljava/util/regex/Matcher;
   36:	putfield	#60; //Field scala$util$matching$Regex$MatchIterator$$matcher:Ljava/util/regex/Matcher;
   39:	aload_0
   40:	iconst_0
   41:	putfield	#62; //Field nextSeen:Z
   44:	return
  LineNumberTable: 
   line 269: 0
   line 272: 27
   line 273: 39

  LocalVariableTable: 
   Start  Length  Slot  Name   Signature
   0      45      0    this       Lscala/util/matching/Regex$MatchIterator;
   0      45      1    source       Ljava/lang/CharSequence;
   0      45      2    regex       Lscala/util/matching/Regex;
   0      45      3    groupNames       Lscala/collection/Seq;

  Signature: length = 0x2
   00 42 

public java.lang.Object next();
  Code:
   Stack=1, Locals=1, Args_size=1
   0:	aload_0
   1:	invokevirtual	#71; //Method next:()Ljava/lang/String;
   4:	areturn
  LineNumberTable: 
   line 269: 0


public java.lang.Object matchData();
  Code:
   Stack=3, Locals=1, Args_size=1
   0:	new	#74; //class scala/util/matching/Regex$MatchIterator$$anon$1
   3:	dup
   4:	aload_0
   5:	invokespecial	#77; //Method scala/util/matching/Regex$MatchIterator$$anon$1."<init>":(Lscala/util/matching/Regex$MatchIterator;)V
   8:	areturn
  LineNumberTable: 
   line 306: 0


public int groupCount();
  Code:
   Stack=1, Locals=1, Args_size=1
   0:	aload_0
   1:	invokevirtual	#82; //Method scala$util$matching$Regex$MatchIterator$$matcher:()Ljava/util/regex/Matcher;
   4:	invokevirtual	#86; //Method java/util/regex/Matcher.groupCount:()I
   7:	ireturn
  LineNumberTable: 
   line 303: 0


public int end(int);
  Code:
   Stack=2, Locals=2, Args_size=2
   0:	aload_0
   1:	invokevirtual	#82; //Method scala$util$matching$Regex$MatchIterator$$matcher:()Ljava/util/regex/Matcher;
   4:	iload_1
   5:	invokevirtual	#90; //Method java/util/regex/Matcher.end:(I)I
   8:	ireturn
  LineNumberTable: 
   line 300: 0

  LocalVariableTable: 
   Start  Length  Slot  Name   Signature
   0      9      0    this       Lscala/util/matching/Regex$MatchIterator;
   0      9      1    i       I


public int end();
  Code:
   Stack=1, Locals=1, Args_size=1
   0:	aload_0
   1:	invokevirtual	#82; //Method scala$util$matching$Regex$MatchIterator$$matcher:()Ljava/util/regex/Matcher;
   4:	invokevirtual	#93; //Method java/util/regex/Matcher.end:()I
   7:	ireturn
  LineNumberTable: 
   line 297: 0


public int start(int);
  Code:
   Stack=2, Locals=2, Args_size=2
   0:	aload_0
   1:	invokevirtual	#82; //Method scala$util$matching$Regex$MatchIterator$$matcher:()Ljava/util/regex/Matcher;
   4:	iload_1
   5:	invokevirtual	#96; //Method java/util/regex/Matcher.start:(I)I
   8:	ireturn
  LineNumberTable: 
   line 294: 0

  LocalVariableTable: 
   Start  Length  Slot  Name   Signature
   0      9      0    this       Lscala/util/matching/Regex$MatchIterator;
   0      9      1    i       I


public int start();
  Code:
   Stack=1, Locals=1, Args_size=1
   0:	aload_0
   1:	invokevirtual	#82; //Method scala$util$matching$Regex$MatchIterator$$matcher:()Ljava/util/regex/Matcher;
   4:	invokevirtual	#98; //Method java/util/regex/Matcher.start:()I
   7:	ireturn
  LineNumberTable: 
   line 291: 0


public java.lang.String toString();
  Code:
   Stack=1, Locals=1, Args_size=1
   0:	aload_0
   1:	invokestatic	#102; //Method scala/collection/Iterator$class.toString:(Lscala/collection/Iterator;)Ljava/lang/String;
   4:	areturn
  LineNumberTable: 
   line 288: 0


public java.lang.String next();
  Code:
   Stack=2, Locals=1, Args_size=1
   0:	aload_0
   1:	invokevirtual	#106; //Method hasNext:()Z
   4:	ifeq	20
   7:	aload_0
   8:	iconst_0
   9:	invokespecial	#110; //Method nextSeen_$eq:(Z)V
   12:	aload_0
   13:	getfield	#60; //Field scala$util$matching$Regex$MatchIterator$$matcher:Ljava/util/regex/Matcher;
   16:	invokevirtual	#113; //Method java/util/regex/Matcher.group:()Ljava/lang/String;
   19:	areturn
   20:	new	#115; //class java/util/NoSuchElementException
   23:	dup
   24:	invokespecial	#116; //Method java/util/NoSuchElementException."<init>":()V
   27:	athrow
  LineNumberTable: 
   line 283: 0
   line 284: 7
   line 285: 12
   line 283: 20


public boolean hasNext();
  Code:
   Stack=2, Locals=1, Args_size=1
   0:	aload_0
   1:	invokespecial	#118; //Method nextSeen:()Z
   4:	ifne	18
   7:	aload_0
   8:	aload_0
   9:	getfield	#60; //Field scala$util$matching$Regex$MatchIterator$$matcher:Ljava/util/regex/Matcher;
   12:	invokevirtual	#121; //Method java/util/regex/Matcher.find:()Z
   15:	invokespecial	#110; //Method nextSeen_$eq:(Z)V
   18:	aload_0
   19:	invokespecial	#118; //Method nextSeen:()Z
   22:	ireturn
  LineNumberTable: 
   line 277: 0
   line 278: 18


public final java.util.regex.Matcher scala$util$matching$Regex$MatchIterator$$matcher();
  Code:
   Stack=1, Locals=1, Args_size=1
   0:	aload_0
   1:	getfield	#60; //Field scala$util$matching$Regex$MatchIterator$$matcher:Ljava/util/regex/Matcher;
   4:	areturn
  LineNumberTable: 
   line 272: 0


public scala.collection.Seq groupNames();
  Code:
   Stack=1, Locals=1, Args_size=1
   0:	aload_0
   1:	getfield	#30; //Field groupNames:Lscala/collection/Seq;
   4:	areturn
  LineNumberTable: 
   line 269: 0

  Signature: length = 0x2
   00 7B 

public scala.util.matching.Regex regex();
  Code:
   Stack=1, Locals=1, Args_size=1
   0:	aload_0
   1:	getfield	#28; //Field regex:Lscala/util/matching/Regex;
   4:	areturn
  LineNumberTable: 
   line 269: 0


public java.lang.CharSequence source();
  Code:
   Stack=1, Locals=1, Args_size=1
   0:	aload_0
   1:	getfield	#26; //Field source:Ljava/lang/CharSequence;
   4:	areturn
  LineNumberTable: 
   line 269: 0


public int sliding$default$2();
  Code:
   Stack=1, Locals=1, Args_size=1
   0:	aload_0
   1:	invokestatic	#129; //Method scala/collection/Iterator$class.sliding$default$2:(Lscala/collection/Iterator;)I
   4:	ireturn
  LineNumberTable: 
   line 269: 0


public void readInto(java.lang.Object);
  Code:
   Stack=2, Locals=2, Args_size=2
   0:	aload_0
   1:	aload_1
   2:	invokestatic	#134; //Method scala/collection/Iterator$class.readInto:(Lscala/collection/Iterator;Ljava/lang/Object;)V
   5:	return
  LineNumberTable: 
   line 269: 0

  LocalVariableTable: 
   Start  Length  Slot  Name   Signature
   0      6      0    this       Lscala/util/matching/Regex$MatchIterator;
   0      6      1    xs       Ljava/lang/Object;


public void readInto(java.lang.Object, int);
  Code:
   Stack=3, Locals=3, Args_size=3
   0:	aload_0
   1:	aload_1
   2:	iload_2
   3:	invokestatic	#140; //Method scala/collection/Iterator$class.readInto:(Lscala/collection/Iterator;Ljava/lang/Object;I)V
   6:	return
  LineNumberTable: 
   line 269: 0

  LocalVariableTable: 
   Start  Length  Slot  Name   Signature
   0      7      0    this       Lscala/util/matching/Regex$MatchIterator;
   0      7      1    xs       Ljava/lang/Object;
   0      7      2    start       I


public void readInto(java.lang.Object, int, int);
  Code:
   Stack=4, Locals=4, Args_size=4
   0:	aload_0
   1:	aload_1
   2:	iload_2
   3:	iload_3
   4:	invokestatic	#144; //Method scala/collection/Iterator$class.readInto:(Lscala/collection/Iterator;Ljava/lang/Object;II)V
   7:	return
  LineNumberTable: 
   line 269: 0

  LocalVariableTable: 
   Start  Length  Slot  Name   Signature
   0      8      0    this       Lscala/util/matching/Regex$MatchIterator;
   0      8      1    xs       Ljava/lang/Object;
   0      8      2    start       I
   0      8      3    sz       I


public java.lang.Object counted();
  Code:
   Stack=1, Locals=1, Args_size=1
   0:	aload_0
   1:	invokestatic	#149; //Method scala/collection/Iterator$class.counted:(Lscala/collection/Iterator;)Ljava/lang/Object;
   4:	areturn
  LineNumberTable: 
   line 269: 0


public scala.collection.Seq collect();
  Code:
   Stack=1, Locals=1, Args_size=1
   0:	aload_0
   1:	invokestatic	#153; //Method scala/collection/Iterator$class.collect:(Lscala/collection/Iterator;)Lscala/collection/Seq;
   4:	areturn
  LineNumberTable: 
   line 269: 0


public int findIndexOf(scala.Function1);
  Code:
   Stack=2, Locals=2, Args_size=2
   0:	aload_0
   1:	aload_1
   2:	invokestatic	#158; //Method scala/collection/Iterator$class.findIndexOf:(Lscala/collection/Iterator;Lscala/Function1;)I
   5:	ireturn
  LineNumberTable: 
   line 269: 0

  LocalVariableTable: 
   Start  Length  Slot  Name   Signature
   0      6      0    this       Lscala/util/matching/Regex$MatchIterator;
   0      6      1    p       Lscala/Function1;


public scala.collection.Iterator append(scala.collection.Iterator);
  Code:
   Stack=2, Locals=2, Args_size=2
   0:	aload_0
   1:	aload_1
   2:	invokestatic	#165; //Method scala/collection/Iterator$class.append:(Lscala/collection/Iterator;Lscala/collection/Iterator;)Lscala/collection/Iterator;
   5:	areturn
  LineNumberTable: 
   line 269: 0

  LocalVariableTable: 
   Start  Length  Slot  Name   Signature
   0      6      0    this       Lscala/util/matching/Regex$MatchIterator;
   0      6      1    that       Lscala/collection/Iterator;


public scala.collection.mutable.StringBuilder addString(scala.collection.mutable.StringBuilder);
  Code:
   Stack=2, Locals=2, Args_size=2
   0:	aload_0
   1:	aload_1
   2:	invokestatic	#172; //Method scala/collection/Iterator$class.addString:(Lscala/collection/Iterator;Lscala/collection/mutable/StringBuilder;)Lscala/collection/mutable/StringBuilder;
   5:	areturn
  LineNumberTable: 
   line 269: 0

  LocalVariableTable: 
   Start  Length  Slot  Name   Signature
   0      6      0    this       Lscala/util/matching/Regex$MatchIterator;
   0      6      1    buf       Lscala/collection/mutable/StringBuilder;


public scala.collection.mutable.StringBuilder addString(scala.collection.mutable.StringBuilder, java.lang.String);
  Code:
   Stack=3, Locals=3, Args_size=3
   0:	aload_0
   1:	aload_1
   2:	aload_2
   3:	invokestatic	#178; //Method scala/collection/Iterator$class.addString:(Lscala/collection/Iterator;Lscala/collection/mutable/StringBuilder;Ljava/lang/String;)Lscala/collection/mutable/StringBuilder;
   6:	areturn
  LineNumberTable: 
   line 269: 0

  LocalVariableTable: 
   Start  Length  Slot  Name   Signature
   0      7      0    this       Lscala/util/matching/Regex$MatchIterator;
   0      7      1    buf       Lscala/collection/mutable/StringBuilder;
   0      7      2    sep       Ljava/lang/String;


public scala.collection.mutable.StringBuilder addString(scala.collection.mutable.StringBuilder, java.lang.String, java.lang.String, java.lang.String);
  Code:
   Stack=5, Locals=5, Args_size=5
   0:	aload_0
   1:	aload_1
   2:	aload_2
   3:	aload_3
   4:	aload	4
   6:	invokestatic	#184; //Method scala/collection/Iterator$class.addString:(Lscala/collection/Iterator;Lscala/collection/mutable/StringBuilder;Ljava/lang/String;Ljava/lang/String;Ljava/lang/String;)Lscala/collection/mutable/StringBuilder;
   9:	areturn
  LineNumberTable: 
   line 269: 0

  LocalVariableTable: 
   Start  Length  Slot  Name   Signature
   0      10      0    this       Lscala/util/matching/Regex$MatchIterator;
   0      10      1    buf       Lscala/collection/mutable/StringBuilder;
   0      10      2    start       Ljava/lang/String;
   0      10      3    sep       Ljava/lang/String;
   0      10      4    end       Ljava/lang/String;


public java.lang.String mkString();
  Code:
   Stack=1, Locals=1, Args_size=1
   0:	aload_0
   1:	invokestatic	#187; //Method scala/collection/Iterator$class.mkString:(Lscala/collection/Iterator;)Ljava/lang/String;
   4:	areturn
  LineNumberTable: 
   line 269: 0


public java.lang.String mkString(java.lang.String);
  Code:
   Stack=2, Locals=2, Args_size=2
   0:	aload_0
   1:	aload_1
   2:	invokestatic	#191; //Method scala/collection/Iterator$class.mkString:(Lscala/collection/Iterator;Ljava/lang/String;)Ljava/lang/String;
   5:	areturn
  LineNumberTable: 
   line 269: 0

  LocalVariableTable: 
   Start  Length  Slot  Name   Signature
   0      6      0    this       Lscala/util/matching/Regex$MatchIterator;
   0      6      1    sep       Ljava/lang/String;


public java.lang.String mkString(java.lang.String, java.lang.String, java.lang.String);
  Code:
   Stack=4, Locals=4, Args_size=4
   0:	aload_0
   1:	aload_1
   2:	aload_2
   3:	aload_3
   4:	invokestatic	#195; //Method scala/collection/Iterator$class.mkString:(Lscala/collection/Iterator;Ljava/lang/String;Ljava/lang/String;Ljava/lang/String;)Ljava/lang/String;
   7:	areturn
  LineNumberTable: 
   line 269: 0

  LocalVariableTable: 
   Start  Length  Slot  Name   Signature
   0      8      0    this       Lscala/util/matching/Regex$MatchIterator;
   0      8      1    start       Ljava/lang/String;
   0      8      2    sep       Ljava/lang/String;
   0      8      3    end       Ljava/lang/String;


public boolean sameElements(scala.collection.Iterator);
  Code:
   Stack=2, Locals=2, Args_size=2
   0:	aload_0
   1:	aload_1
   2:	invokestatic	#200; //Method scala/collection/Iterator$class.sameElements:(Lscala/collection/Iterator;Lscala/collection/Iterator;)Z
   5:	ireturn
  LineNumberTable: 
   line 269: 0

  LocalVariableTable: 
   Start  Length  Slot  Name   Signature
   0      6      0    this       Lscala/util/matching/Regex$MatchIterator;
   0      6      1    that       Lscala/collection/Iterator;


public scala.collection.Seq toSeq();
  Code:
   Stack=1, Locals=1, Args_size=1
   0:	aload_0
   1:	invokestatic	#203; //Method scala/collection/Iterator$class.toSeq:(Lscala/collection/Iterator;)Lscala/collection/Seq;
   4:	areturn
  LineNumberTable: 
   line 269: 0


public scala.collection.immutable.Stream toStream();
  Code:
   Stack=1, Locals=1, Args_size=1
   0:	aload_0
   1:	invokestatic	#208; //Method scala/collection/Iterator$class.toStream:(Lscala/collection/Iterator;)Lscala/collection/immutable/Stream;
   4:	areturn
  LineNumberTable: 
   line 269: 0


public scala.collection.immutable.List toList();
  Code:
   Stack=1, Locals=1, Args_size=1
   0:	aload_0
   1:	invokestatic	#213; //Method scala/collection/Iterator$class.toList:(Lscala/collection/Iterator;)Lscala/collection/immutable/List;
   4:	areturn
  LineNumberTable: 
   line 269: 0


public void copyToBuffer(scala.collection.mutable.Buffer);
  Code:
   Stack=2, Locals=2, Args_size=2
   0:	aload_0
   1:	aload_1
   2:	invokestatic	#218; //Method scala/collection/Iterator$class.copyToBuffer:(Lscala/collection/Iterator;Lscala/collection/mutable/Buffer;)V
   5:	return
  LineNumberTable: 
   line 269: 0

  LocalVariableTable: 
   Start  Length  Slot  Name   Signature
   0      6      0    this       Lscala/util/matching/Regex$MatchIterator;
   0      6      1    dest       Lscala/collection/mutable/Buffer;


public void copyToArray(java.lang.Object);
  Code:
   Stack=2, Locals=2, Args_size=2
   0:	aload_0
   1:	aload_1
   2:	invokestatic	#223; //Method scala/collection/Iterator$class.copyToArray:(Lscala/collection/Iterator;Ljava/lang/Object;)V
   5:	return
  LineNumberTable: 
   line 269: 0

  LocalVariableTable: 
   Start  Length  Slot  Name   Signature
   0      6      0    this       Lscala/util/matching/Regex$MatchIterator;
   0      6      1    xs       Ljava/lang/Object;


public void copyToArray(java.lang.Object, int);
  Code:
   Stack=3, Locals=3, Args_size=3
   0:	aload_0
   1:	aload_1
   2:	iload_2
   3:	invokestatic	#225; //Method scala/collection/Iterator$class.copyToArray:(Lscala/collection/Iterator;Ljava/lang/Object;I)V
   6:	return
  LineNumberTable: 
   line 269: 0

  LocalVariableTable: 
   Start  Length  Slot  Name   Signature
   0      7      0    this       Lscala/util/matching/Regex$MatchIterator;
   0      7      1    xs       Ljava/lang/Object;
   0      7      2    start       I


public void copyToArray(java.lang.Object, int, int);
  Code:
   Stack=4, Locals=4, Args_size=4
   0:	aload_0
   1:	aload_1
   2:	iload_2
   3:	iload_3
   4:	invokestatic	#227; //Method scala/collection/Iterator$class.copyToArray:(Lscala/collection/Iterator;Ljava/lang/Object;II)V
   7:	return
  LineNumberTable: 
   line 269: 0

  LocalVariableTable: 
   Start  Length  Slot  Name   Signature
   0      8      0    this       Lscala/util/matching/Regex$MatchIterator;
   0      8      1    xs       Ljava/lang/Object;
   0      8      2    start       I
   0      8      3    len       I


public java.lang.Object patch(int, scala.collection.Iterator, int);
  Code:
   Stack=4, Locals=4, Args_size=4
   0:	aload_0
   1:	iload_1
   2:	aload_2
   3:	iload_3
   4:	invokestatic	#233; //Method scala/collection/Iterator$class.patch:(Lscala/collection/Iterator;ILscala/collection/Iterator;I)Ljava/lang/Object;
   7:	areturn
  LineNumberTable: 
   line 269: 0

  LocalVariableTable: 
   Start  Length  Slot  Name   Signature
   0      8      0    this       Lscala/util/matching/Regex$MatchIterator;
   0      8      1    from       I
   0      8      2    patchElems       Lscala/collection/Iterator;
   0      8      3    replaced       I


public scala.Tuple2 duplicate();
  Code:
   Stack=1, Locals=1, Args_size=1
   0:	aload_0
   1:	invokestatic	#241; //Method scala/collection/Iterator$class.duplicate:(Lscala/collection/Iterator;)Lscala/Tuple2;
   4:	areturn
  LineNumberTable: 
   line 269: 0


public int length();
  Code:
   Stack=1, Locals=1, Args_size=1
   0:	aload_0
   1:	invokestatic	#244; //Method scala/collection/Iterator$class.length:(Lscala/collection/Iterator;)I
   4:	ireturn
  LineNumberTable: 
   line 269: 0


public scala.collection.Iterator$GroupedIterator sliding(int, int);
  Code:
   Stack=3, Locals=3, Args_size=3
   0:	aload_0
   1:	iload_1
   2:	iload_2
   3:	invokestatic	#249; //Method scala/collection/Iterator$class.sliding:(Lscala/collection/Iterator;II)Lscala/collection/Iterator$GroupedIterator;
   6:	areturn
  LineNumberTable: 
   line 269: 0

  LocalVariableTable: 
   Start  Length  Slot  Name   Signature
   0      7      0    this       Lscala/util/matching/Regex$MatchIterator;
   0      7      1    size       I
   0      7      2    step       I

  Signature: length = 0x2
   00 FFFFFFF6 

public scala.collection.Iterator$GroupedIterator grouped(int);
  Code:
   Stack=2, Locals=2, Args_size=2
   0:	aload_0
   1:	iload_1
   2:	invokestatic	#256; //Method scala/collection/Iterator$class.grouped:(Lscala/collection/Iterator;I)Lscala/collection/Iterator$GroupedIterator;
   5:	areturn
  LineNumberTable: 
   line 269: 0

  LocalVariableTable: 
   Start  Length  Slot  Name   Signature
   0      6      0    this       Lscala/util/matching/Regex$MatchIterator;
   0      6      1    size       I

  Signature: length = 0x2
   00 FFFFFFFD 

public java.lang.Object buffered();
  Code:
   Stack=1, Locals=1, Args_size=1
   0:	aload_0
   1:	invokestatic	#259; //Method scala/collection/Iterator$class.buffered:(Lscala/collection/Iterator;)Ljava/lang/Object;
   4:	areturn
  LineNumberTable: 
   line 269: 0


public scala.Option reduceRightOption(scala.Function2);
  Code:
   Stack=2, Locals=2, Args_size=2
   0:	aload_0
   1:	aload_1
   2:	invokestatic	#264; //Method scala/collection/Iterator$class.reduceRightOption:(Lscala/collection/Iterator;Lscala/Function2;)Lscala/Option;
   5:	areturn
  LineNumberTable: 
   line 269: 0

  LocalVariableTable: 
   Start  Length  Slot  Name   Signature
   0      6      0    this       Lscala/util/matching/Regex$MatchIterator;
   0      6      1    op       Lscala/Function2;


public scala.Option reduceLeftOption(scala.Function2);
  Code:
   Stack=2, Locals=2, Args_size=2
   0:	aload_0
   1:	aload_1
   2:	invokestatic	#269; //Method scala/collection/Iterator$class.reduceLeftOption:(Lscala/collection/Iterator;Lscala/Function2;)Lscala/Option;
   5:	areturn
  LineNumberTable: 
   line 269: 0

  LocalVariableTable: 
   Start  Length  Slot  Name   Signature
   0      6      0    this       Lscala/util/matching/Regex$MatchIterator;
   0      6      1    op       Lscala/Function2;


public java.lang.Object reduceRight(scala.Function2);
  Code:
   Stack=2, Locals=2, Args_size=2
   0:	aload_0
   1:	aload_1
   2:	invokestatic	#274; //Method scala/collection/Iterator$class.reduceRight:(Lscala/collection/Iterator;Lscala/Function2;)Ljava/lang/Object;
   5:	areturn
  LineNumberTable: 
   line 269: 0

  LocalVariableTable: 
   Start  Length  Slot  Name   Signature
   0      6      0    this       Lscala/util/matching/Regex$MatchIterator;
   0      6      1    op       Lscala/Function2;


public java.lang.Object reduceLeft(scala.Function2);
  Code:
   Stack=2, Locals=2, Args_size=2
   0:	aload_0
   1:	aload_1
   2:	invokestatic	#277; //Method scala/collection/Iterator$class.reduceLeft:(Lscala/collection/Iterator;Lscala/Function2;)Ljava/lang/Object;
   5:	areturn
  LineNumberTable: 
   line 269: 0

  LocalVariableTable: 
   Start  Length  Slot  Name   Signature
   0      6      0    this       Lscala/util/matching/Regex$MatchIterator;
   0      6      1    op       Lscala/Function2;


public java.lang.Object $colon$bslash(java.lang.Object, scala.Function2);
  Code:
   Stack=3, Locals=3, Args_size=3
   0:	aload_0
   1:	aload_1
   2:	aload_2
   3:	invokestatic	#282; //Method scala/collection/Iterator$class.$colon$bslash:(Lscala/collection/Iterator;Ljava/lang/Object;Lscala/Function2;)Ljava/lang/Object;
   6:	areturn
  LineNumberTable: 
   line 269: 0

  LocalVariableTable: 
   Start  Length  Slot  Name   Signature
   0      7      0    this       Lscala/util/matching/Regex$MatchIterator;
   0      7      1    z       Ljava/lang/Object;
   0      7      2    op       Lscala/Function2;


public java.lang.Object $div$colon(java.lang.Object, scala.Function2);
  Code:
   Stack=3, Locals=3, Args_size=3
   0:	aload_0
   1:	aload_1
   2:	aload_2
   3:	invokestatic	#286; //Method scala/collection/Iterator$class.$div$colon:(Lscala/collection/Iterator;Ljava/lang/Object;Lscala/Function2;)Ljava/lang/Object;
   6:	areturn
  LineNumberTable: 
   line 269: 0

  LocalVariableTable: 
   Start  Length  Slot  Name   Signature
   0      7      0    this       Lscala/util/matching/Regex$MatchIterator;
   0      7      1    z       Ljava/lang/Object;
   0      7      2    op       Lscala/Function2;


public java.lang.Object foldRight(java.lang.Object, scala.Function2);
  Code:
   Stack=3, Locals=3, Args_size=3
   0:	aload_0
   1:	aload_1
   2:	aload_2
   3:	invokestatic	#289; //Method scala/collection/Iterator$class.foldRight:(Lscala/collection/Iterator;Ljava/lang/Object;Lscala/Function2;)Ljava/lang/Object;
   6:	areturn
  LineNumberTable: 
   line 269: 0

  LocalVariableTable: 
   Start  Length  Slot  Name   Signature
   0      7      0    this       Lscala/util/matching/Regex$MatchIterator;
   0      7      1    z       Ljava/lang/Object;
   0      7      2    op       Lscala/Function2;


public java.lang.Object foldLeft(java.lang.Object, scala.Function2);
  Code:
   Stack=3, Locals=3, Args_size=3
   0:	aload_0
   1:	aload_1
   2:	aload_2
   3:	invokestatic	#292; //Method scala/collection/Iterator$class.foldLeft:(Lscala/collection/Iterator;Ljava/lang/Object;Lscala/Function2;)Ljava/lang/Object;
   6:	areturn
  LineNumberTable: 
   line 269: 0

  LocalVariableTable: 
   Start  Length  Slot  Name   Signature
   0      7      0    this       Lscala/util/matching/Regex$MatchIterator;
   0      7      1    z       Ljava/lang/Object;
   0      7      2    op       Lscala/Function2;


public int indexOf(java.lang.Object);
  Code:
   Stack=2, Locals=2, Args_size=2
   0:	aload_0
   1:	aload_1
   2:	invokestatic	#297; //Method scala/collection/Iterator$class.indexOf:(Lscala/collection/Iterator;Ljava/lang/Object;)I
   5:	ireturn
  LineNumberTable: 
   line 269: 0

  LocalVariableTable: 
   Start  Length  Slot  Name   Signature
   0      6      0    this       Lscala/util/matching/Regex$MatchIterator;
   0      6      1    elem       Ljava/lang/Object;


public int indexWhere(scala.Function1);
  Code:
   Stack=2, Locals=2, Args_size=2
   0:	aload_0
   1:	aload_1
   2:	invokestatic	#301; //Method scala/collection/Iterator$class.indexWhere:(Lscala/collection/Iterator;Lscala/Function1;)I
   5:	ireturn
  LineNumberTable: 
   line 269: 0

  LocalVariableTable: 
   Start  Length  Slot  Name   Signature
   0      6      0    this       Lscala/util/matching/Regex$MatchIterator;
   0      6      1    p       Lscala/Function1;


public scala.Option find(scala.Function1);
  Code:
   Stack=2, Locals=2, Args_size=2
   0:	aload_0
   1:	aload_1
   2:	invokestatic	#305; //Method scala/collection/Iterator$class.find:(Lscala/collection/Iterator;Lscala/Function1;)Lscala/Option;
   5:	areturn
  LineNumberTable: 
   line 269: 0

  LocalVariableTable: 
   Start  Length  Slot  Name   Signature
   0      6      0    this       Lscala/util/matching/Regex$MatchIterator;
   0      6      1    p       Lscala/Function1;


public boolean contains(java.lang.Object);
  Code:
   Stack=2, Locals=2, Args_size=2
   0:	aload_0
   1:	aload_1
   2:	invokestatic	#310; //Method scala/collection/Iterator$class.contains:(Lscala/collection/Iterator;Ljava/lang/Object;)Z
   5:	ireturn
  LineNumberTable: 
   line 269: 0

  LocalVariableTable: 
   Start  Length  Slot  Name   Signature
   0      6      0    this       Lscala/util/matching/Regex$MatchIterator;
   0      6      1    elem       Ljava/lang/Object;


public boolean exists(scala.Function1);
  Code:
   Stack=2, Locals=2, Args_size=2
   0:	aload_0
   1:	aload_1
   2:	invokestatic	#315; //Method scala/collection/Iterator$class.exists:(Lscala/collection/Iterator;Lscala/Function1;)Z
   5:	ireturn
  LineNumberTable: 
   line 269: 0

  LocalVariableTable: 
   Start  Length  Slot  Name   Signature
   0      6      0    this       Lscala/util/matching/Regex$MatchIterator;
   0      6      1    p       Lscala/Function1;


public boolean forall(scala.Function1);
  Code:
   Stack=2, Locals=2, Args_size=2
   0:	aload_0
   1:	aload_1
   2:	invokestatic	#318; //Method scala/collection/Iterator$class.forall:(Lscala/collection/Iterator;Lscala/Function1;)Z
   5:	ireturn
  LineNumberTable: 
   line 269: 0

  LocalVariableTable: 
   Start  Length  Slot  Name   Signature
   0      6      0    this       Lscala/util/matching/Regex$MatchIterator;
   0      6      1    p       Lscala/Function1;


public void foreach(scala.Function1);
  Code:
   Stack=2, Locals=2, Args_size=2
   0:	aload_0
   1:	aload_1
   2:	invokestatic	#323; //Method scala/collection/Iterator$class.foreach:(Lscala/collection/Iterator;Lscala/Function1;)V
   5:	return
  LineNumberTable: 
   line 269: 0

  LocalVariableTable: 
   Start  Length  Slot  Name   Signature
   0      6      0    this       Lscala/util/matching/Regex$MatchIterator;
   0      6      1    f       Lscala/Function1;


public java.lang.Object zipAll(scala.collection.Iterator, java.lang.Object, java.lang.Object);
  Code:
   Stack=4, Locals=4, Args_size=4
   0:	aload_0
   1:	aload_1
   2:	aload_2
   3:	aload_3
   4:	invokestatic	#329; //Method scala/collection/Iterator$class.zipAll:(Lscala/collection/Iterator;Lscala/collection/Iterator;Ljava/lang/Object;Ljava/lang/Object;)Ljava/lang/Object;
   7:	areturn
  LineNumberTable: 
   line 269: 0

  LocalVariableTable: 
   Start  Length  Slot  Name   Signature
   0      8      0    this       Lscala/util/matching/Regex$MatchIterator;
   0      8      1    that       Lscala/collection/Iterator;
   0      8      2    thisElem       Ljava/lang/Object;
   0      8      3    thatElem       Ljava/lang/Object;


public java.lang.Object zipWithIndex();
  Code:
   Stack=1, Locals=1, Args_size=1
   0:	aload_0
   1:	invokestatic	#334; //Method scala/collection/Iterator$class.zipWithIndex:(Lscala/collection/Iterator;)Ljava/lang/Object;
   4:	areturn
  LineNumberTable: 
   line 269: 0


public java.lang.Object padTo(int, java.lang.Object);
  Code:
   Stack=3, Locals=3, Args_size=3
   0:	aload_0
   1:	iload_1
   2:	aload_2
   3:	invokestatic	#339; //Method scala/collection/Iterator$class.padTo:(Lscala/collection/Iterator;ILjava/lang/Object;)Ljava/lang/Object;
   6:	areturn
  LineNumberTable: 
   line 269: 0

  LocalVariableTable: 
   Start  Length  Slot  Name   Signature
   0      7      0    this       Lscala/util/matching/Regex$MatchIterator;
   0      7      1    len       I
   0      7      2    elem       Ljava/lang/Object;


public java.lang.Object zip(scala.collection.Iterator);
  Code:
   Stack=2, Locals=2, Args_size=2
   0:	aload_0
   1:	aload_1
   2:	invokestatic	#343; //Method scala/collection/Iterator$class.zip:(Lscala/collection/Iterator;Lscala/collection/Iterator;)Ljava/lang/Object;
   5:	areturn
  LineNumberTable: 
   line 269: 0

  LocalVariableTable: 
   Start  Length  Slot  Name   Signature
   0      6      0    this       Lscala/util/matching/Regex$MatchIterator;
   0      6      1    that       Lscala/collection/Iterator;


public scala.collection.Iterator dropWhile(scala.Function1);
  Code:
   Stack=2, Locals=2, Args_size=2
   0:	aload_0
   1:	aload_1
   2:	invokestatic	#348; //Method scala/collection/Iterator$class.dropWhile:(Lscala/collection/Iterator;Lscala/Function1;)Lscala/collection/Iterator;
   5:	areturn
  LineNumberTable: 
   line 269: 0

  LocalVariableTable: 
   Start  Length  Slot  Name   Signature
   0      6      0    this       Lscala/util/matching/Regex$MatchIterator;
   0      6      1    p       Lscala/Function1;


public scala.Tuple2 partition(scala.Function1);
  Code:
   Stack=2, Locals=2, Args_size=2
   0:	aload_0
   1:	aload_1
   2:	invokestatic	#353; //Method scala/collection/Iterator$class.partition:(Lscala/collection/Iterator;Lscala/Function1;)Lscala/Tuple2;
   5:	areturn
  LineNumberTable: 
   line 269: 0

  LocalVariableTable: 
   Start  Length  Slot  Name   Signature
   0      6      0    this       Lscala/util/matching/Regex$MatchIterator;
   0      6      1    p       Lscala/Function1;


public scala.collection.Iterator takeWhile(scala.Function1);
  Code:
   Stack=2, Locals=2, Args_size=2
   0:	aload_0
   1:	aload_1
   2:	invokestatic	#356; //Method scala/collection/Iterator$class.takeWhile:(Lscala/collection/Iterator;Lscala/Function1;)Lscala/collection/Iterator;
   5:	areturn
  LineNumberTable: 
   line 269: 0

  LocalVariableTable: 
   Start  Length  Slot  Name   Signature
   0      6      0    this       Lscala/util/matching/Regex$MatchIterator;
   0      6      1    p       Lscala/Function1;


public scala.collection.Iterator partialMap(scala.PartialFunction);
  Code:
   Stack=2, Locals=2, Args_size=2
   0:	aload_0
   1:	aload_1
   2:	invokestatic	#361; //Method scala/collection/Iterator$class.partialMap:(Lscala/collection/Iterator;Lscala/PartialFunction;)Lscala/collection/Iterator;
   5:	areturn
  LineNumberTable: 
   line 269: 0

  LocalVariableTable: 
   Start  Length  Slot  Name   Signature
   0      6      0    this       Lscala/util/matching/Regex$MatchIterator;
   0      6      1    pf       Lscala/PartialFunction;


public scala.collection.Iterator filterNot(scala.Function1);
  Code:
   Stack=2, Locals=2, Args_size=2
   0:	aload_0
   1:	aload_1
   2:	invokestatic	#366; //Method scala/collection/Iterator$class.filterNot:(Lscala/collection/Iterator;Lscala/Function1;)Lscala/collection/Iterator;
   5:	areturn
  LineNumberTable: 
   line 269: 0

  LocalVariableTable: 
   Start  Length  Slot  Name   Signature
   0      6      0    this       Lscala/util/matching/Regex$MatchIterator;
   0      6      1    p       Lscala/Function1;


public scala.collection.Iterator$WithFilter withFilter(scala.Function1);
  Code:
   Stack=2, Locals=2, Args_size=2
   0:	aload_0
   1:	aload_1
   2:	invokestatic	#371; //Method scala/collection/Iterator$class.withFilter:(Lscala/collection/Iterator;Lscala/Function1;)Lscala/collection/Iterator$WithFilter;
   5:	areturn
  LineNumberTable: 
   line 269: 0

  LocalVariableTable: 
   Start  Length  Slot  Name   Signature
   0      6      0    this       Lscala/util/matching/Regex$MatchIterator;
   0      6      1    p       Lscala/Function1;

  Signature: length = 0x2
   01 70 

public scala.collection.Iterator filter(scala.Function1);
  Code:
   Stack=2, Locals=2, Args_size=2
   0:	aload_0
   1:	aload_1
   2:	invokestatic	#374; //Method scala/collection/Iterator$class.filter:(Lscala/collection/Iterator;Lscala/Function1;)Lscala/collection/Iterator;
   5:	areturn
  LineNumberTable: 
   line 269: 0

  LocalVariableTable: 
   Start  Length  Slot  Name   Signature
   0      6      0    this       Lscala/util/matching/Regex$MatchIterator;
   0      6      1    p       Lscala/Function1;


public scala.collection.Iterator flatMap(scala.Function1);
  Code:
   Stack=2, Locals=2, Args_size=2
   0:	aload_0
   1:	aload_1
   2:	invokestatic	#377; //Method scala/collection/Iterator$class.flatMap:(Lscala/collection/Iterator;Lscala/Function1;)Lscala/collection/Iterator;
   5:	areturn
  LineNumberTable: 
   line 269: 0

  LocalVariableTable: 
   Start  Length  Slot  Name   Signature
   0      6      0    this       Lscala/util/matching/Regex$MatchIterator;
   0      6      1    f       Lscala/Function1;


public scala.collection.Iterator $plus$plus(scala.Function0);
  Code:
   Stack=2, Locals=2, Args_size=2
   0:	aload_0
   1:	aload_1
   2:	invokestatic	#382; //Method scala/collection/Iterator$class.$plus$plus:(Lscala/collection/Iterator;Lscala/Function0;)Lscala/collection/Iterator;
   5:	areturn
  LineNumberTable: 
   line 269: 0

  LocalVariableTable: 
   Start  Length  Slot  Name   Signature
   0      6      0    this       Lscala/util/matching/Regex$MatchIterator;
   0      6      1    that       Lscala/Function0;


public scala.collection.Iterator map(scala.Function1);
  Code:
   Stack=2, Locals=2, Args_size=2
   0:	aload_0
   1:	aload_1
   2:	invokestatic	#386; //Method scala/collection/Iterator$class.map:(Lscala/collection/Iterator;Lscala/Function1;)Lscala/collection/Iterator;
   5:	areturn
  LineNumberTable: 
   line 269: 0

  LocalVariableTable: 
   Start  Length  Slot  Name   Signature
   0      6      0    this       Lscala/util/matching/Regex$MatchIterator;
   0      6      1    f       Lscala/Function1;


public scala.collection.Iterator slice(int, int);
  Code:
   Stack=3, Locals=3, Args_size=3
   0:	aload_0
   1:	iload_1
   2:	iload_2
   3:	invokestatic	#391; //Method scala/collection/Iterator$class.slice:(Lscala/collection/Iterator;II)Lscala/collection/Iterator;
   6:	areturn
  LineNumberTable: 
   line 269: 0

  LocalVariableTable: 
   Start  Length  Slot  Name   Signature
   0      7      0    this       Lscala/util/matching/Regex$MatchIterator;
   0      7      1    from       I
   0      7      2    until       I


public scala.collection.Iterator drop(int);
  Code:
   Stack=2, Locals=2, Args_size=2
   0:	aload_0
   1:	iload_1
   2:	invokestatic	#397; //Method scala/collection/Iterator$class.drop:(Lscala/collection/Iterator;I)Lscala/collection/Iterator;
   5:	areturn
  LineNumberTable: 
   line 269: 0

  LocalVariableTable: 
   Start  Length  Slot  Name   Signature
   0      6      0    this       Lscala/util/matching/Regex$MatchIterator;
   0      6      1    n       I


public scala.collection.Iterator take(int);
  Code:
   Stack=2, Locals=2, Args_size=2
   0:	aload_0
   1:	iload_1
   2:	invokestatic	#401; //Method scala/collection/Iterator$class.take:(Lscala/collection/Iterator;I)Lscala/collection/Iterator;
   5:	areturn
  LineNumberTable: 
   line 269: 0

  LocalVariableTable: 
   Start  Length  Slot  Name   Signature
   0      6      0    this       Lscala/util/matching/Regex$MatchIterator;
   0      6      1    n       I


public java.lang.String group(java.lang.String);
  Code:
   Stack=2, Locals=2, Args_size=2
   0:	aload_0
   1:	aload_1
   2:	invokestatic	#404; //Method scala/util/matching/Regex$MatchData$class.group:(Lscala/util/matching/Regex$MatchData;Ljava/lang/String;)Ljava/lang/String;
   5:	areturn
  LineNumberTable: 
   line 269: 0

  LocalVariableTable: 
   Start  Length  Slot  Name   Signature
   0      6      0    this       Lscala/util/matching/Regex$MatchIterator;
   0      6      1    id       Ljava/lang/String;


public java.lang.CharSequence after(int);
  Code:
   Stack=2, Locals=2, Args_size=2
   0:	aload_0
   1:	iload_1
   2:	invokestatic	#410; //Method scala/util/matching/Regex$MatchData$class.after:(Lscala/util/matching/Regex$MatchData;I)Ljava/lang/CharSequence;
   5:	areturn
  LineNumberTable: 
   line 269: 0

  LocalVariableTable: 
   Start  Length  Slot  Name   Signature
   0      6      0    this       Lscala/util/matching/Regex$MatchIterator;
   0      6      1    i       I


public java.lang.CharSequence after();
  Code:
   Stack=1, Locals=1, Args_size=1
   0:	aload_0
   1:	invokestatic	#413; //Method scala/util/matching/Regex$MatchData$class.after:(Lscala/util/matching/Regex$MatchData;)Ljava/lang/CharSequence;
   4:	areturn
  LineNumberTable: 
   line 269: 0


public java.lang.CharSequence before(int);
  Code:
   Stack=2, Locals=2, Args_size=2
   0:	aload_0
   1:	iload_1
   2:	invokestatic	#416; //Method scala/util/matching/Regex$MatchData$class.before:(Lscala/util/matching/Regex$MatchData;I)Ljava/lang/CharSequence;
   5:	areturn
  LineNumberTable: 
   line 269: 0

  LocalVariableTable: 
   Start  Length  Slot  Name   Signature
   0      6      0    this       Lscala/util/matching/Regex$MatchIterator;
   0      6      1    i       I


public java.lang.CharSequence before();
  Code:
   Stack=1, Locals=1, Args_size=1
   0:	aload_0
   1:	invokestatic	#418; //Method scala/util/matching/Regex$MatchData$class.before:(Lscala/util/matching/Regex$MatchData;)Ljava/lang/CharSequence;
   4:	areturn
  LineNumberTable: 
   line 269: 0


public scala.collection.immutable.List subgroups();
  Code:
   Stack=1, Locals=1, Args_size=1
   0:	aload_0
   1:	invokestatic	#422; //Method scala/util/matching/Regex$MatchData$class.subgroups:(Lscala/util/matching/Regex$MatchData;)Lscala/collection/immutable/List;
   4:	areturn
  LineNumberTable: 
   line 269: 0


public java.lang.String group(int);
  Code:
   Stack=2, Locals=2, Args_size=2
   0:	aload_0
   1:	iload_1
   2:	invokestatic	#426; //Method scala/util/matching/Regex$MatchData$class.group:(Lscala/util/matching/Regex$MatchData;I)Ljava/lang/String;
   5:	areturn
  LineNumberTable: 
   line 269: 0

  LocalVariableTable: 
   Start  Length  Slot  Name   Signature
   0      6      0    this       Lscala/util/matching/Regex$MatchIterator;
   0      6      1    i       I


public java.lang.String matched();
  Code:
   Stack=1, Locals=1, Args_size=1
   0:	aload_0
   1:	invokestatic	#430; //Method scala/util/matching/Regex$MatchData$class.matched:(Lscala/util/matching/Regex$MatchData;)Ljava/lang/String;
   4:	areturn
  LineNumberTable: 
   line 269: 0


public final scala.collection.immutable.Map scala$util$matching$Regex$MatchData$$nameToIndex();
  Code:
   Stack=3, Locals=1, Args_size=1
   0:	aload_0
   1:	getfield	#433; //Field bitmap$0:I
   4:	iconst_1
   5:	iand
   6:	iconst_0
   7:	if_icmpne	44
   10:	aload_0
   11:	dup
   12:	pop
   13:	monitorenter
   14:	aload_0
   15:	getfield	#433; //Field bitmap$0:I
   18:	iconst_1
   19:	iand
   20:	iconst_0
   21:	if_icmpne	42
   24:	aload_0
   25:	aload_0
   26:	invokestatic	#436; //Method scala/util/matching/Regex$MatchData$class.scala$util$matching$Regex$MatchData$$nameToIndex:(Lscala/util/matching/Regex$MatchData;)Lscala/collection/immutable/Map;
   29:	putfield	#438; //Field scala$util$matching$Regex$MatchData$$nameToIndex:Lscala/collection/immutable/Map;
   32:	aload_0
   33:	aload_0
   34:	getfield	#433; //Field bitmap$0:I
   37:	iconst_1
   38:	ior
   39:	putfield	#433; //Field bitmap$0:I
   42:	aload_0
   43:	monitorexit
   44:	aload_0
   45:	getfield	#438; //Field scala$util$matching$Regex$MatchData$$nameToIndex:Lscala/collection/immutable/Map;
   48:	areturn
   49:	aload_0
   50:	monitorexit
   51:	athrow
  Exception table:
   from   to  target type
    14    44    49   any
  LineNumberTable: 
   line 269: 0
   line 275: 6
   line 269: 10
   line 275: 20
   line 269: 24


}

