Compiled from "Regex.scala"
public final class scala.util.matching.Regex$Groups$$anonfun$unapplySeq$2 extends scala.runtime.AbstractFunction1 implements java.io.Serializable
  SourceFile: "Regex.scala"
  Scala: length = 0x
   
  InnerClass: 
   public Match=class scala/util/matching/Regex$Match of class scala/util/matching/Regex
   public abstract MatchData=class scala/util/matching/Regex$MatchData of class scala/util/matching/Regex
   public final $anonfun$unapplySeq$2=class scala/util/matching/Regex$Groups$$anonfun$unapplySeq$2 of class scala/util/matching/Regex$Groups$
  minor version: 0
  major version: 49
  Constant pool:
Asciz	SourceFile;
Asciz	Regex.scala;
Asciz	<clinit>;
Asciz	()V;
Asciz	Code;
Asciz	serialVersionUID;
Asciz	J;
Asciz	scala/util/matching/Regex$Groups$$anonfun$unapplySeq$2;
class	scala/util/matching/Regex$Groups$$anonfun$unapplySeq$2
NameAndType	serialVersionUID:J
Field	scala/util/matching/Regex$Groups$$anonfun$unapplySeq$2.serialVersionUID:J
Asciz	m$2;
Asciz	Lscala/util/matching/Regex$Match;;
Asciz	apply;
Asciz	(I)Ljava/lang/String;;
Asciz	LineNumberTable;
NameAndType	m$2:Lscala/util/matching/Regex$Match;
Field	scala/util/matching/Regex$Groups$$anonfun$unapplySeq$2.m$2:Lscala/util/matching/Regex$Match;
Asciz	scala/util/matching/Regex$MatchData;
class	scala/util/matching/Regex$MatchData
Asciz	group;
NameAndType	group:(I)Ljava/lang/String;
InterfaceMethod	scala/util/matching/Regex$MatchData.group:(I)Ljava/lang/String;
Asciz	(Ljava/lang/Object;)Ljava/lang/Object;;
Asciz	scala/runtime/BoxesRunTime;
class	scala/runtime/BoxesRunTime
Asciz	unboxToInt;
Asciz	(Ljava/lang/Object;)I;
NameAndType	unboxToInt:(Ljava/lang/Object;)I
Method	scala/runtime/BoxesRunTime.unboxToInt:(Ljava/lang/Object;)I
NameAndType	apply:(I)Ljava/lang/String;
Method	scala/util/matching/Regex$Groups$$anonfun$unapplySeq$2.apply:(I)Ljava/lang/String;
Asciz	this;
Asciz	Lscala/util/matching/Regex$Groups$$anonfun$unapplySeq$2;;
Asciz	v1;
Asciz	Ljava/lang/Object;;
Asciz	LocalVariableTable;
Asciz	<init>;
Asciz	(Lscala/util/matching/Regex$Match;)V;
Asciz	scala/runtime/AbstractFunction1;
class	scala/runtime/AbstractFunction1
NameAndType	"<init>":()V
Method	scala/runtime/AbstractFunction1."<init>":()V
Asciz	Scala;
Asciz	InnerClasses;
Asciz	scala/util/matching/Regex$Match;
class	scala/util/matching/Regex$Match
Asciz	scala/util/matching/Regex;
class	scala/util/matching/Regex
Asciz	Match;
Asciz	MatchData;
Asciz	scala/util/matching/Regex$Groups$;
class	scala/util/matching/Regex$Groups$
Asciz	$anonfun$unapplySeq$2;
Asciz	java/io/Serializable;
class	java/io/Serializable

{
public static final long serialVersionUID;
  Signature: J

public final scala.util.matching.Regex$Match m$2;
  Signature: Lscala/util/matching/Regex$Match;

public static {};
  Signature: ()V
  Code:
   Stack=2, Locals=0, Args_size=0
	lconst_0
	putstatic	Field serialVersionUID:J
	return
  Labels:

public final java.lang.String apply(int);
  Signature: (I)Ljava/lang/String;
  Code:
   Stack=2, Locals=2, Args_size=2
	aload_0
	getfield	Field m$2:Lscala/util/matching/Regex$Match;
	iload_1
	invokeinterface	InterfaceMethod scala/util/matching/Regex$MatchData.group:(I)Ljava/lang/String;
	areturn
  Labels:

public final java.lang.Object apply(java.lang.Object);
  Signature: (Ljava/lang/Object;)Ljava/lang/Object;
  Code:
   Stack=2, Locals=2, Args_size=2
	aload_0
	aload_1
	invokestatic	Method scala/runtime/BoxesRunTime.unboxToInt:(Ljava/lang/Object;)I
	invokevirtual	Method apply:(I)Ljava/lang/String;
	areturn
  Labels:
  LocalVariableTable: 
   Start  Length  Slot  Name   Signature
   0      9      0    this       Lscala/util/matching/Regex$Groups$$anonfun$unapplySeq$2;
   0      9      1    v1       Ljava/lang/Object;


public scala.util.matching.Regex$Groups$$anonfun$unapplySeq$2(scala.util.matching.Regex$Match);
  Signature: (Lscala/util/matching/Regex$Match;)V
  Code:
   Stack=2, Locals=2, Args_size=2
	aload_0
	aload_1
	putfield	Field m$2:Lscala/util/matching/Regex$Match;
	aload_0
	invokespecial	Method scala/runtime/AbstractFunction1."<init>":()V
	return
  Labels:

}

