Compiled from "Regex.scala"
public abstract class scala.util.matching.Regex$MatchData$class extends java.lang.Object
  SourceFile: "Regex.scala"
  Scala: length = 0x
   
  InnerClass: 
   public #218= #215 of #217; //Inclusive=class scala/collection/immutable/Range$Inclusive of class scala/collection/immutable/Range
   public abstract #221= #13 of #220; //MatchData=class scala/util/matching/Regex$MatchData of class scala/util/matching/Regex
   public final #222= #203 of #13; //$anonfun$subgroups$1=class scala/util/matching/Regex$MatchData$$anonfun$subgroups$1 of class scala/util/matching/Regex$MatchData
  minor version: 0
  major version: 49
  Constant pool:
const #1 = Asciz	SourceFile;
const #2 = Asciz	Regex.scala;
const #3 = Asciz	$init$;
const #4 = Asciz	(Lscala/util/matching/Regex$MatchData;)V;
const #5 = Asciz	Code;
const #6 = Asciz	LineNumberTable;
const #7 = Asciz	$this;
const #8 = Asciz	Lscala/util/matching/Regex$MatchData;;
const #9 = Asciz	LocalVariableTable;
const #10 = Asciz	toString;
const #11 = Asciz	(Lscala/util/matching/Regex$MatchData;)Ljava/lang/String;;
const #12 = Asciz	scala/util/matching/Regex$MatchData;
const #13 = class	#12;	//  scala/util/matching/Regex$MatchData
const #14 = Asciz	matched;
const #15 = Asciz	()Ljava/lang/String;;
const #16 = NameAndType	#14:#15;//  matched:()Ljava/lang/String;
const #17 = InterfaceMethod	#13.#16;	//  scala/util/matching/Regex$MatchData.matched:()Ljava/lang/String;
const #18 = Asciz	group;
const #19 = Asciz	(Lscala/util/matching/Regex$MatchData;Ljava/lang/String;)Ljava/lang/String;;
const #20 = Asciz	scala$util$matching$Regex$MatchData$$nameToIndex;
const #21 = Asciz	()Lscala/collection/immutable/Map;;
const #22 = NameAndType	#20:#21;//  scala$util$matching$Regex$MatchData$$nameToIndex:()Lscala/collection/immutable/Map;
const #23 = InterfaceMethod	#13.#22;	//  scala/util/matching/Regex$MatchData.scala$util$matching$Regex$MatchData$$nameToIndex:()Lscala/collection/immutable/Map;
const #24 = Asciz	scala/collection/MapLike;
const #25 = class	#24;	//  scala/collection/MapLike
const #26 = Asciz	get;
const #27 = Asciz	(Ljava/lang/Object;)Lscala/Option;;
const #28 = NameAndType	#26:#27;//  get:(Ljava/lang/Object;)Lscala/Option;
const #29 = InterfaceMethod	#25.#28;	//  scala/collection/MapLike.get:(Ljava/lang/Object;)Lscala/Option;
const #30 = Asciz	scala/None$;
const #31 = class	#30;	//  scala/None$
const #32 = Asciz	MODULE$;
const #33 = Asciz	Lscala/None$;;
const #34 = NameAndType	#32:#33;//  MODULE$:Lscala/None$;
const #35 = Field	#31.#34;	//  scala/None$.MODULE$:Lscala/None$;
const #36 = Asciz	java/lang/Object;
const #37 = class	#36;	//  java/lang/Object
const #38 = Asciz	equals;
const #39 = Asciz	(Ljava/lang/Object;)Z;
const #40 = NameAndType	#38:#39;//  equals:(Ljava/lang/Object;)Z
const #41 = Method	#37.#40;	//  java/lang/Object.equals:(Ljava/lang/Object;)Z
const #42 = Asciz	java/util/NoSuchElementException;
const #43 = class	#42;	//  java/util/NoSuchElementException
const #44 = Asciz	scala/collection/mutable/StringBuilder;
const #45 = class	#44;	//  scala/collection/mutable/StringBuilder
const #46 = Asciz	<init>;
const #47 = Asciz	()V;
const #48 = NameAndType	#46:#47;//  "<init>":()V
const #49 = Method	#45.#48;	//  scala/collection/mutable/StringBuilder."<init>":()V
const #50 = Asciz	group name ;
const #51 = String	#50;	//  group name 
const #52 = Asciz	append;
const #53 = Asciz	(Ljava/lang/Object;)Lscala/collection/mutable/StringBuilder;;
const #54 = NameAndType	#52:#53;//  append:(Ljava/lang/Object;)Lscala/collection/mutable/StringBuilder;
const #55 = Method	#45.#54;	//  scala/collection/mutable/StringBuilder.append:(Ljava/lang/Object;)Lscala/collection/mutable/StringBuilder;
const #56 = Asciz	 not defined;
const #57 = String	#56;	//   not defined
const #58 = NameAndType	#10:#15;//  toString:()Ljava/lang/String;
const #59 = Method	#45.#58;	//  scala/collection/mutable/StringBuilder.toString:()Ljava/lang/String;
const #60 = Asciz	(Ljava/lang/String;)V;
const #61 = NameAndType	#46:#60;//  "<init>":(Ljava/lang/String;)V
const #62 = Method	#43.#61;	//  java/util/NoSuchElementException."<init>":(Ljava/lang/String;)V
const #63 = Asciz	scala/MatchError;
const #64 = class	#63;	//  scala/MatchError
const #65 = Asciz	scala/Option;
const #66 = class	#65;	//  scala/Option
const #67 = Method	#66.#58;	//  scala/Option.toString:()Ljava/lang/String;
const #68 = Method	#64.#61;	//  scala/MatchError."<init>":(Ljava/lang/String;)V
const #69 = Asciz	scala/Some;
const #70 = class	#69;	//  scala/Some
const #71 = Asciz	x;
const #72 = Asciz	Ljava/lang/Object;;
const #73 = NameAndType	#71:#72;//  x:Ljava/lang/Object;
const #74 = Field	#70.#73;	//  scala/Some.x:Ljava/lang/Object;
const #75 = Asciz	scala/runtime/BoxesRunTime;
const #76 = class	#75;	//  scala/runtime/BoxesRunTime
const #77 = Asciz	unboxToInt;
const #78 = Asciz	(Ljava/lang/Object;)I;
const #79 = NameAndType	#77:#78;//  unboxToInt:(Ljava/lang/Object;)I
const #80 = Method	#76.#79;	//  scala/runtime/BoxesRunTime.unboxToInt:(Ljava/lang/Object;)I
const #81 = Asciz	(I)Ljava/lang/String;;
const #82 = NameAndType	#18:#81;//  group:(I)Ljava/lang/String;
const #83 = InterfaceMethod	#13.#82;	//  scala/util/matching/Regex$MatchData.group:(I)Ljava/lang/String;
const #84 = Asciz	id;
const #85 = Asciz	Ljava/lang/String;;
const #86 = Asciz	temp8;
const #87 = Asciz	Lscala/Some;;
const #88 = Asciz	temp9;
const #89 = Asciz	I;
const #90 = Asciz	temp6;
const #91 = Asciz	Lscala/Option;;
const #92 = Asciz	(Lscala/util/matching/Regex$MatchData;)Lscala/collection/immutable/Map;;
const #93 = Asciz	scala/Predef$;
const #94 = class	#93;	//  scala/Predef$
const #95 = Asciz	Lscala/Predef$;;
const #96 = NameAndType	#32:#95;//  MODULE$:Lscala/Predef$;
const #97 = Field	#94.#96;	//  scala/Predef$.MODULE$:Lscala/Predef$;
const #98 = Asciz	Map;
const #99 = Asciz	()Lscala/collection/immutable/Map$;;
const #100 = NameAndType	#98:#99;//  Map:()Lscala/collection/immutable/Map$;
const #101 = Method	#94.#100;	//  scala/Predef$.Map:()Lscala/collection/immutable/Map$;
const #102 = Asciz	scala/Tuple2;
const #103 = class	#102;	//  scala/Tuple2
const #104 = Asciz	[Ljava/lang/Object;;
const #105 = class	#104;	//  "[Ljava/lang/Object;"
const #106 = Asciz	wrapRefArray;
const #107 = Asciz	([Ljava/lang/Object;)Lscala/collection/mutable/WrappedArray;;
const #108 = NameAndType	#106:#107;//  wrapRefArray:([Ljava/lang/Object;)Lscala/collection/mutable/WrappedArray;
const #109 = Method	#94.#108;	//  scala/Predef$.wrapRefArray:([Ljava/lang/Object;)Lscala/collection/mutable/WrappedArray;
const #110 = Asciz	scala/collection/immutable/Map$;
const #111 = class	#110;	//  scala/collection/immutable/Map$
const #112 = Asciz	apply;
const #113 = Asciz	(Lscala/collection/Seq;)Lscala/collection/Map;;
const #114 = NameAndType	#112:#113;//  apply:(Lscala/collection/Seq;)Lscala/collection/Map;
const #115 = Method	#111.#114;	//  scala/collection/immutable/Map$.apply:(Lscala/collection/Seq;)Lscala/collection/Map;
const #116 = Asciz	scala/collection/immutable/MapLike;
const #117 = class	#116;	//  scala/collection/immutable/MapLike
const #118 = Asciz	;
const #119 = String	#118;	//  
const #120 = Asciz	groupNames;
const #121 = Asciz	()Lscala/collection/Seq;;
const #122 = NameAndType	#120:#121;//  groupNames:()Lscala/collection/Seq;
const #123 = InterfaceMethod	#13.#122;	//  scala/util/matching/Regex$MatchData.groupNames:()Lscala/collection/Seq;
const #124 = Asciz	scala/collection/TraversableLike;
const #125 = class	#124;	//  scala/collection/TraversableLike
const #126 = Asciz	toList;
const #127 = Asciz	()Lscala/collection/immutable/List;;
const #128 = NameAndType	#126:#127;//  toList:()Lscala/collection/immutable/List;
const #129 = InterfaceMethod	#125.#128;	//  scala/collection/TraversableLike.toList:()Lscala/collection/immutable/List;
const #130 = Asciz	scala/collection/immutable/List;
const #131 = class	#130;	//  scala/collection/immutable/List
const #132 = Asciz	$colon$colon;
const #133 = Asciz	(Ljava/lang/Object;)Lscala/collection/immutable/List;;
const #134 = NameAndType	#132:#133;//  $colon$colon:(Ljava/lang/Object;)Lscala/collection/immutable/List;
const #135 = Method	#131.#134;	//  scala/collection/immutable/List.$colon$colon:(Ljava/lang/Object;)Lscala/collection/immutable/List;
const #136 = Asciz	scala/collection/immutable/List$;
const #137 = class	#136;	//  scala/collection/immutable/List$
const #138 = Asciz	Lscala/collection/immutable/List$;;
const #139 = NameAndType	#32:#138;//  MODULE$:Lscala/collection/immutable/List$;
const #140 = Field	#137.#139;	//  scala/collection/immutable/List$.MODULE$:Lscala/collection/immutable/List$;
const #141 = Asciz	canBuildFrom;
const #142 = Asciz	()Lscala/collection/generic/CanBuildFrom;;
const #143 = NameAndType	#141:#142;//  canBuildFrom:()Lscala/collection/generic/CanBuildFrom;
const #144 = Method	#137.#143;	//  scala/collection/immutable/List$.canBuildFrom:()Lscala/collection/generic/CanBuildFrom;
const #145 = Asciz	scala/collection/IterableLike;
const #146 = class	#145;	//  scala/collection/IterableLike
const #147 = Asciz	zipWithIndex;
const #148 = Asciz	(Lscala/collection/generic/CanBuildFrom;)Ljava/lang/Object;;
const #149 = NameAndType	#147:#148;//  zipWithIndex:(Lscala/collection/generic/CanBuildFrom;)Ljava/lang/Object;
const #150 = InterfaceMethod	#146.#149;	//  scala/collection/IterableLike.zipWithIndex:(Lscala/collection/generic/CanBuildFrom;)Ljava/lang/Object;
const #151 = Asciz	scala/collection/Traversable;
const #152 = class	#151;	//  scala/collection/Traversable
const #153 = Asciz	$plus$plus;
const #154 = Asciz	(Lscala/collection/Traversable;)Lscala/collection/immutable/Map;;
const #155 = NameAndType	#153:#154;//  $plus$plus:(Lscala/collection/Traversable;)Lscala/collection/immutable/Map;
const #156 = InterfaceMethod	#117.#155;	//  scala/collection/immutable/MapLike.$plus$plus:(Lscala/collection/Traversable;)Lscala/collection/immutable/Map;
const #157 = Asciz	after;
const #158 = Asciz	(Lscala/util/matching/Regex$MatchData;I)Ljava/lang/CharSequence;;
const #159 = Asciz	end;
const #160 = Asciz	(I)I;
const #161 = NameAndType	#159:#160;//  end:(I)I
const #162 = InterfaceMethod	#13.#161;	//  scala/util/matching/Regex$MatchData.end:(I)I
const #163 = Asciz	source;
const #164 = Asciz	()Ljava/lang/CharSequence;;
const #165 = NameAndType	#163:#164;//  source:()Ljava/lang/CharSequence;
const #166 = InterfaceMethod	#13.#165;	//  scala/util/matching/Regex$MatchData.source:()Ljava/lang/CharSequence;
const #167 = Asciz	java/lang/CharSequence;
const #168 = class	#167;	//  java/lang/CharSequence
const #169 = Asciz	length;
const #170 = Asciz	()I;
const #171 = NameAndType	#169:#170;//  length:()I
const #172 = InterfaceMethod	#168.#171;	//  java/lang/CharSequence.length:()I
const #173 = Asciz	subSequence;
const #174 = Asciz	(II)Ljava/lang/CharSequence;;
const #175 = NameAndType	#173:#174;//  subSequence:(II)Ljava/lang/CharSequence;
const #176 = InterfaceMethod	#168.#175;	//  java/lang/CharSequence.subSequence:(II)Ljava/lang/CharSequence;
const #177 = Asciz	i;
const #178 = Asciz	(Lscala/util/matching/Regex$MatchData;)Ljava/lang/CharSequence;;
const #179 = NameAndType	#159:#170;//  end:()I
const #180 = InterfaceMethod	#13.#179;	//  scala/util/matching/Regex$MatchData.end:()I
const #181 = Asciz	before;
const #182 = Asciz	start;
const #183 = NameAndType	#182:#160;//  start:(I)I
const #184 = InterfaceMethod	#13.#183;	//  scala/util/matching/Regex$MatchData.start:(I)I
const #185 = NameAndType	#182:#170;//  start:()I
const #186 = InterfaceMethod	#13.#185;	//  scala/util/matching/Regex$MatchData.start:()I
const #187 = Asciz	subgroups;
const #188 = Asciz	(Lscala/util/matching/Regex$MatchData;)Lscala/collection/immutable/List;;
const #189 = Asciz	intWrapper;
const #190 = Asciz	(I)Lscala/runtime/RichInt;;
const #191 = NameAndType	#189:#190;//  intWrapper:(I)Lscala/runtime/RichInt;
const #192 = Method	#94.#191;	//  scala/Predef$.intWrapper:(I)Lscala/runtime/RichInt;
const #193 = Asciz	groupCount;
const #194 = NameAndType	#193:#170;//  groupCount:()I
const #195 = InterfaceMethod	#13.#194;	//  scala/util/matching/Regex$MatchData.groupCount:()I
const #196 = Asciz	scala/runtime/RichInt;
const #197 = class	#196;	//  scala/runtime/RichInt
const #198 = Asciz	to;
const #199 = Asciz	(I)Lscala/collection/immutable/Range$Inclusive;;
const #200 = NameAndType	#198:#199;//  to:(I)Lscala/collection/immutable/Range$Inclusive;
const #201 = Method	#197.#200;	//  scala/runtime/RichInt.to:(I)Lscala/collection/immutable/Range$Inclusive;
const #202 = Asciz	scala/util/matching/Regex$MatchData$$anonfun$subgroups$1;
const #203 = class	#202;	//  scala/util/matching/Regex$MatchData$$anonfun$subgroups$1
const #204 = NameAndType	#46:#4;//  "<init>":(Lscala/util/matching/Regex$MatchData;)V
const #205 = Method	#203.#204;	//  scala/util/matching/Regex$MatchData$$anonfun$subgroups$1."<init>":(Lscala/util/matching/Regex$MatchData;)V
const #206 = Asciz	map;
const #207 = Asciz	(Lscala/Function1;Lscala/collection/generic/CanBuildFrom;)Ljava/lang/Object;;
const #208 = NameAndType	#206:#207;//  map:(Lscala/Function1;Lscala/collection/generic/CanBuildFrom;)Ljava/lang/Object;
const #209 = InterfaceMethod	#125.#208;	//  scala/collection/TraversableLike.map:(Lscala/Function1;Lscala/collection/generic/CanBuildFrom;)Ljava/lang/Object;
const #210 = Asciz	(Lscala/util/matching/Regex$MatchData;I)Ljava/lang/String;;
const #211 = Method	#37.#58;	//  java/lang/Object.toString:()Ljava/lang/String;
const #212 = Asciz	Scala;
const #213 = Asciz	InnerClasses;
const #214 = Asciz	scala/collection/immutable/Range$Inclusive;
const #215 = class	#214;	//  scala/collection/immutable/Range$Inclusive
const #216 = Asciz	scala/collection/immutable/Range;
const #217 = class	#216;	//  scala/collection/immutable/Range
const #218 = Asciz	Inclusive;
const #219 = Asciz	scala/util/matching/Regex;
const #220 = class	#219;	//  scala/util/matching/Regex
const #221 = Asciz	MatchData;
const #222 = Asciz	$anonfun$subgroups$1;
const #223 = Asciz	scala/util/matching/Regex$MatchData$class;
const #224 = class	#223;	//  scala/util/matching/Regex$MatchData$class

{
public static void $init$(scala.util.matching.Regex$MatchData);
  Code:
   Stack=0, Locals=1, Args_size=1
   0:	return
  LineNumberTable: 
   line 147: 0

  LocalVariableTable: 
   Start  Length  Slot  Name   Signature
   0      1      0    $this       Lscala/util/matching/Regex$MatchData;


public static java.lang.String toString(scala.util.matching.Regex$MatchData);
  Code:
   Stack=1, Locals=1, Args_size=1
   0:	aload_0
   1:	invokeinterface	#17,  1; //InterfaceMethod scala/util/matching/Regex$MatchData.matched:()Ljava/lang/String;
   6:	areturn
  LineNumberTable: 
   line 226: 0

  LocalVariableTable: 
   Start  Length  Slot  Name   Signature
   0      7      0    $this       Lscala/util/matching/Regex$MatchData;


public static java.lang.String group(scala.util.matching.Regex$MatchData, java.lang.String);
  Code:
   Stack=4, Locals=5, Args_size=2
   0:	aload_0
   1:	invokeinterface	#23,  1; //InterfaceMethod scala/util/matching/Regex$MatchData.scala$util$matching$Regex$MatchData$$nameToIndex:()Lscala/collection/immutable/Map;
   6:	aload_1
   7:	invokeinterface	#29,  2; //InterfaceMethod scala/collection/MapLike.get:(Ljava/lang/Object;)Lscala/Option;
   12:	astore	4
   14:	getstatic	#35; //Field scala/None$.MODULE$:Lscala/None$;
   17:	dup
   18:	ifnonnull	30
   21:	pop
   22:	aload	4
   24:	ifnull	38
   27:	goto	87
   30:	aload	4
   32:	invokevirtual	#41; //Method java/lang/Object.equals:(Ljava/lang/Object;)Z
   35:	ifeq	87
   38:	iconst_1
   39:	ifeq	74
   42:	new	#43; //class java/util/NoSuchElementException
   45:	dup
   46:	new	#45; //class scala/collection/mutable/StringBuilder
   49:	dup
   50:	invokespecial	#49; //Method scala/collection/mutable/StringBuilder."<init>":()V
   53:	ldc	#51; //String group name 
   55:	invokevirtual	#55; //Method scala/collection/mutable/StringBuilder.append:(Ljava/lang/Object;)Lscala/collection/mutable/StringBuilder;
   58:	aload_1
   59:	invokevirtual	#55; //Method scala/collection/mutable/StringBuilder.append:(Ljava/lang/Object;)Lscala/collection/mutable/StringBuilder;
   62:	ldc	#57; //String  not defined
   64:	invokevirtual	#55; //Method scala/collection/mutable/StringBuilder.append:(Ljava/lang/Object;)Lscala/collection/mutable/StringBuilder;
   67:	invokevirtual	#59; //Method scala/collection/mutable/StringBuilder.toString:()Ljava/lang/String;
   70:	invokespecial	#62; //Method java/util/NoSuchElementException."<init>":(Ljava/lang/String;)V
   73:	athrow
   74:	new	#64; //class scala/MatchError
   77:	dup
   78:	aload	4
   80:	invokevirtual	#67; //Method scala/Option.toString:()Ljava/lang/String;
   83:	invokespecial	#68; //Method scala/MatchError."<init>":(Ljava/lang/String;)V
   86:	athrow
   87:	aload	4
   89:	instanceof	#70; //class scala/Some
   92:	ifeq	134
   95:	aload	4
   97:	checkcast	#70; //class scala/Some
   100:	astore_2
   101:	aload_2
   102:	getfield	#74; //Field scala/Some.x:Ljava/lang/Object;
   105:	invokestatic	#80; //Method scala/runtime/BoxesRunTime.unboxToInt:(Ljava/lang/Object;)I
   108:	istore_3
   109:	iconst_1
   110:	ifeq	121
   113:	aload_0
   114:	iload_3
   115:	invokeinterface	#83,  2; //InterfaceMethod scala/util/matching/Regex$MatchData.group:(I)Ljava/lang/String;
   120:	areturn
   121:	new	#64; //class scala/MatchError
   124:	dup
   125:	aload	4
   127:	invokevirtual	#67; //Method scala/Option.toString:()Ljava/lang/String;
   130:	invokespecial	#68; //Method scala/MatchError."<init>":(Ljava/lang/String;)V
   133:	athrow
   134:	new	#64; //class scala/MatchError
   137:	dup
   138:	aload	4
   140:	invokevirtual	#67; //Method scala/Option.toString:()Ljava/lang/String;
   143:	invokespecial	#68; //Method scala/MatchError."<init>":(Ljava/lang/String;)V
   146:	athrow
  LineNumberTable: 
   line 220: 0
   line 21: 38
   line 221: 42
   line 220: 74
   line 21: 109
   line 222: 113
   line 220: 120

  LocalVariableTable: 
   Start  Length  Slot  Name   Signature
   0      147      0    $this       Lscala/util/matching/Regex$MatchData;
   0      147      1    id       Ljava/lang/String;
   101      19      2    temp8       Lscala/Some;
   121      13      2    temp8       Lscala/Some;
   109      11      3    temp9       I
   121      13      3    temp9       I
   14      133      4    temp6       Lscala/Option;


public static final scala.collection.immutable.Map scala$util$matching$Regex$MatchData$$nameToIndex(scala.util.matching.Regex$MatchData);
  Code:
   Stack=3, Locals=2, Args_size=1
   0:	getstatic	#97; //Field scala/Predef$.MODULE$:Lscala/Predef$;
   3:	invokevirtual	#101; //Method scala/Predef$.Map:()Lscala/collection/immutable/Map$;
   6:	getstatic	#97; //Field scala/Predef$.MODULE$:Lscala/Predef$;
   9:	iconst_0
   10:	anewarray	#103; //class scala/Tuple2
   13:	checkcast	#105; //class "[Ljava/lang/Object;"
   16:	invokevirtual	#109; //Method scala/Predef$.wrapRefArray:([Ljava/lang/Object;)Lscala/collection/mutable/WrappedArray;
   19:	invokevirtual	#115; //Method scala/collection/immutable/Map$.apply:(Lscala/collection/Seq;)Lscala/collection/Map;
   22:	checkcast	#117; //class scala/collection/immutable/MapLike
   25:	ldc	#119; //String 
   27:	astore_1
   28:	aload_0
   29:	invokeinterface	#123,  1; //InterfaceMethod scala/util/matching/Regex$MatchData.groupNames:()Lscala/collection/Seq;
   34:	invokeinterface	#129,  1; //InterfaceMethod scala/collection/TraversableLike.toList:()Lscala/collection/immutable/List;
   39:	aload_1
   40:	invokevirtual	#135; //Method scala/collection/immutable/List.$colon$colon:(Ljava/lang/Object;)Lscala/collection/immutable/List;
   43:	getstatic	#140; //Field scala/collection/immutable/List$.MODULE$:Lscala/collection/immutable/List$;
   46:	invokevirtual	#144; //Method scala/collection/immutable/List$.canBuildFrom:()Lscala/collection/generic/CanBuildFrom;
   49:	invokeinterface	#150,  2; //InterfaceMethod scala/collection/IterableLike.zipWithIndex:(Lscala/collection/generic/CanBuildFrom;)Ljava/lang/Object;
   54:	checkcast	#152; //class scala/collection/Traversable
   57:	invokeinterface	#156,  2; //InterfaceMethod scala/collection/immutable/MapLike.$plus$plus:(Lscala/collection/Traversable;)Lscala/collection/immutable/Map;
   62:	areturn
  LineNumberTable: 
   line 211: 0

  LocalVariableTable: 
   Start  Length  Slot  Name   Signature
   0      63      0    $this       Lscala/util/matching/Regex$MatchData;


public static java.lang.CharSequence after(scala.util.matching.Regex$MatchData, int);
  Code:
   Stack=3, Locals=2, Args_size=2
   0:	aload_0
   1:	iload_1
   2:	invokeinterface	#162,  2; //InterfaceMethod scala/util/matching/Regex$MatchData.end:(I)I
   7:	iconst_0
   8:	if_icmplt	43
   11:	aload_0
   12:	invokeinterface	#166,  1; //InterfaceMethod scala/util/matching/Regex$MatchData.source:()Ljava/lang/CharSequence;
   17:	aload_0
   18:	iload_1
   19:	invokeinterface	#162,  2; //InterfaceMethod scala/util/matching/Regex$MatchData.end:(I)I
   24:	aload_0
   25:	invokeinterface	#166,  1; //InterfaceMethod scala/util/matching/Regex$MatchData.source:()Ljava/lang/CharSequence;
   30:	invokeinterface	#172,  1; //InterfaceMethod java/lang/CharSequence.length:()I
   35:	invokeinterface	#176,  3; //InterfaceMethod java/lang/CharSequence.subSequence:(II)Ljava/lang/CharSequence;
   40:	goto	44
   43:	aconst_null
   44:	areturn
  LineNumberTable: 
   line 208: 0
   line 209: 43
   line 208: 44

  LocalVariableTable: 
   Start  Length  Slot  Name   Signature
   0      45      0    $this       Lscala/util/matching/Regex$MatchData;
   0      45      1    i       I


public static java.lang.CharSequence after(scala.util.matching.Regex$MatchData);
  Code:
   Stack=3, Locals=1, Args_size=1
   0:	aload_0
   1:	invokeinterface	#180,  1; //InterfaceMethod scala/util/matching/Regex$MatchData.end:()I
   6:	iconst_0
   7:	if_icmplt	41
   10:	aload_0
   11:	invokeinterface	#166,  1; //InterfaceMethod scala/util/matching/Regex$MatchData.source:()Ljava/lang/CharSequence;
   16:	aload_0
   17:	invokeinterface	#180,  1; //InterfaceMethod scala/util/matching/Regex$MatchData.end:()I
   22:	aload_0
   23:	invokeinterface	#166,  1; //InterfaceMethod scala/util/matching/Regex$MatchData.source:()Ljava/lang/CharSequence;
   28:	invokeinterface	#172,  1; //InterfaceMethod java/lang/CharSequence.length:()I
   33:	invokeinterface	#176,  3; //InterfaceMethod java/lang/CharSequence.subSequence:(II)Ljava/lang/CharSequence;
   38:	goto	42
   41:	aconst_null
   42:	areturn
  LineNumberTable: 
   line 202: 0
   line 203: 41
   line 202: 42

  LocalVariableTable: 
   Start  Length  Slot  Name   Signature
   0      43      0    $this       Lscala/util/matching/Regex$MatchData;


public static java.lang.CharSequence before(scala.util.matching.Regex$MatchData, int);
  Code:
   Stack=4, Locals=2, Args_size=2
   0:	aload_0
   1:	iload_1
   2:	invokeinterface	#184,  2; //InterfaceMethod scala/util/matching/Regex$MatchData.start:(I)I
   7:	iconst_0
   8:	if_icmplt	33
   11:	aload_0
   12:	invokeinterface	#166,  1; //InterfaceMethod scala/util/matching/Regex$MatchData.source:()Ljava/lang/CharSequence;
   17:	iconst_0
   18:	aload_0
   19:	iload_1
   20:	invokeinterface	#184,  2; //InterfaceMethod scala/util/matching/Regex$MatchData.start:(I)I
   25:	invokeinterface	#176,  3; //InterfaceMethod java/lang/CharSequence.subSequence:(II)Ljava/lang/CharSequence;
   30:	goto	34
   33:	aconst_null
   34:	areturn
  LineNumberTable: 
   line 196: 0
   line 197: 33
   line 196: 34

  LocalVariableTable: 
   Start  Length  Slot  Name   Signature
   0      35      0    $this       Lscala/util/matching/Regex$MatchData;
   0      35      1    i       I


public static java.lang.CharSequence before(scala.util.matching.Regex$MatchData);
  Code:
   Stack=3, Locals=1, Args_size=1
   0:	aload_0
   1:	invokeinterface	#186,  1; //InterfaceMethod scala/util/matching/Regex$MatchData.start:()I
   6:	iconst_0
   7:	if_icmplt	31
   10:	aload_0
   11:	invokeinterface	#166,  1; //InterfaceMethod scala/util/matching/Regex$MatchData.source:()Ljava/lang/CharSequence;
   16:	iconst_0
   17:	aload_0
   18:	invokeinterface	#186,  1; //InterfaceMethod scala/util/matching/Regex$MatchData.start:()I
   23:	invokeinterface	#176,  3; //InterfaceMethod java/lang/CharSequence.subSequence:(II)Ljava/lang/CharSequence;
   28:	goto	32
   31:	aconst_null
   32:	areturn
  LineNumberTable: 
   line 190: 0
   line 191: 31
   line 190: 32

  LocalVariableTable: 
   Start  Length  Slot  Name   Signature
   0      33      0    $this       Lscala/util/matching/Regex$MatchData;


public static scala.collection.immutable.List subgroups(scala.util.matching.Regex$MatchData);
  Code:
   Stack=4, Locals=1, Args_size=1
   0:	getstatic	#97; //Field scala/Predef$.MODULE$:Lscala/Predef$;
   3:	iconst_1
   4:	invokevirtual	#192; //Method scala/Predef$.intWrapper:(I)Lscala/runtime/RichInt;
   7:	aload_0
   8:	invokeinterface	#195,  1; //InterfaceMethod scala/util/matching/Regex$MatchData.groupCount:()I
   13:	invokevirtual	#201; //Method scala/runtime/RichInt.to:(I)Lscala/collection/immutable/Range$Inclusive;
   16:	invokeinterface	#129,  1; //InterfaceMethod scala/collection/TraversableLike.toList:()Lscala/collection/immutable/List;
   21:	new	#203; //class scala/util/matching/Regex$MatchData$$anonfun$subgroups$1
   24:	dup
   25:	aload_0
   26:	invokespecial	#205; //Method scala/util/matching/Regex$MatchData$$anonfun$subgroups$1."<init>":(Lscala/util/matching/Regex$MatchData;)V
   29:	getstatic	#140; //Field scala/collection/immutable/List$.MODULE$:Lscala/collection/immutable/List$;
   32:	invokevirtual	#144; //Method scala/collection/immutable/List$.canBuildFrom:()Lscala/collection/generic/CanBuildFrom;
   35:	invokeinterface	#209,  3; //InterfaceMethod scala/collection/TraversableLike.map:(Lscala/Function1;Lscala/collection/generic/CanBuildFrom;)Ljava/lang/Object;
   40:	checkcast	#131; //class scala/collection/immutable/List
   43:	areturn
  LineNumberTable: 
   line 185: 0

  LocalVariableTable: 
   Start  Length  Slot  Name   Signature
   0      44      0    $this       Lscala/util/matching/Regex$MatchData;


public static java.lang.String group(scala.util.matching.Regex$MatchData, int);
  Code:
   Stack=4, Locals=2, Args_size=2
   0:	aload_0
   1:	iload_1
   2:	invokeinterface	#184,  2; //InterfaceMethod scala/util/matching/Regex$MatchData.start:(I)I
   7:	iconst_0
   8:	if_icmplt	42
   11:	aload_0
   12:	invokeinterface	#166,  1; //InterfaceMethod scala/util/matching/Regex$MatchData.source:()Ljava/lang/CharSequence;
   17:	aload_0
   18:	iload_1
   19:	invokeinterface	#184,  2; //InterfaceMethod scala/util/matching/Regex$MatchData.start:(I)I
   24:	aload_0
   25:	iload_1
   26:	invokeinterface	#162,  2; //InterfaceMethod scala/util/matching/Regex$MatchData.end:(I)I
   31:	invokeinterface	#176,  3; //InterfaceMethod java/lang/CharSequence.subSequence:(II)Ljava/lang/CharSequence;
   36:	invokevirtual	#211; //Method java/lang/Object.toString:()Ljava/lang/String;
   39:	goto	43
   42:	aconst_null
   43:	areturn
  LineNumberTable: 
   line 181: 0
   line 182: 42
   line 181: 43

  LocalVariableTable: 
   Start  Length  Slot  Name   Signature
   0      44      0    $this       Lscala/util/matching/Regex$MatchData;
   0      44      1    i       I


public static java.lang.String matched(scala.util.matching.Regex$MatchData);
  Code:
   Stack=3, Locals=1, Args_size=1
   0:	aload_0
   1:	invokeinterface	#186,  1; //InterfaceMethod scala/util/matching/Regex$MatchData.start:()I
   6:	iconst_0
   7:	if_icmplt	39
   10:	aload_0
   11:	invokeinterface	#166,  1; //InterfaceMethod scala/util/matching/Regex$MatchData.source:()Ljava/lang/CharSequence;
   16:	aload_0
   17:	invokeinterface	#186,  1; //InterfaceMethod scala/util/matching/Regex$MatchData.start:()I
   22:	aload_0
   23:	invokeinterface	#180,  1; //InterfaceMethod scala/util/matching/Regex$MatchData.end:()I
   28:	invokeinterface	#176,  3; //InterfaceMethod java/lang/CharSequence.subSequence:(II)Ljava/lang/CharSequence;
   33:	invokevirtual	#211; //Method java/lang/Object.toString:()Ljava/lang/String;
   36:	goto	40
   39:	aconst_null
   40:	areturn
  LineNumberTable: 
   line 175: 0
   line 176: 39
   line 175: 40

  LocalVariableTable: 
   Start  Length  Slot  Name   Signature
   0      41      0    $this       Lscala/util/matching/Regex$MatchData;


}

