Compiled from "Document.scala"
public final class scala.text.DocBreak extends java.lang.Object
  SourceFile: "Document.scala"
  ScalaSig: length = 0x3
   05 00 00 
  RuntimeVisibleAnnotations: length = 0xB
   00 01 00 37 00 01 00 38 73 00 39 
  minor version: 0
  major version: 49
  Constant pool:
Asciz	SourceFile;
Asciz	Document.scala;
Asciz	productElements;
Asciz	()Lscala/collection/Iterator;;
Asciz	Code;
Asciz	scala/text/DocBreak$;
class	scala/text/DocBreak$
Asciz	MODULE$;
Asciz	Lscala/text/DocBreak$;;
NameAndType	MODULE$:Lscala/text/DocBreak$;
Field	scala/text/DocBreak$.MODULE$:Lscala/text/DocBreak$;
NameAndType	productElements:()Lscala/collection/Iterator;
Method	scala/text/DocBreak$.productElements:()Lscala/collection/Iterator;
Asciz	Deprecated;
Asciz	productIterator;
NameAndType	productIterator:()Lscala/collection/Iterator;
Method	scala/text/DocBreak$.productIterator:()Lscala/collection/Iterator;
Asciz	productElementName;
Asciz	(I)Ljava/lang/String;;
NameAndType	productElementName:(I)Ljava/lang/String;
Method	scala/text/DocBreak$.productElementName:(I)Ljava/lang/String;
Asciz	canEqual;
Asciz	(Ljava/lang/Object;)Z;
NameAndType	canEqual:(Ljava/lang/Object;)Z
Method	scala/text/DocBreak$.canEqual:(Ljava/lang/Object;)Z
Asciz	productElement;
Asciz	(I)Ljava/lang/Object;;
NameAndType	productElement:(I)Ljava/lang/Object;
Method	scala/text/DocBreak$.productElement:(I)Ljava/lang/Object;
Asciz	productArity;
Asciz	()I;
NameAndType	productArity:()I
Method	scala/text/DocBreak$.productArity:()I
Asciz	productPrefix;
Asciz	()Ljava/lang/String;;
NameAndType	productPrefix:()Ljava/lang/String;
Method	scala/text/DocBreak$.productPrefix:()Ljava/lang/String;
Asciz	format;
Asciz	(ILjava/io/Writer;)V;
NameAndType	format:(ILjava/io/Writer;)V
Method	scala/text/DocBreak$.format:(ILjava/io/Writer;)V
Asciz	$colon$div$colon;
Asciz	(Ljava/lang/String;)Lscala/text/Document;;
NameAndType	$colon$div$colon:(Ljava/lang/String;)Lscala/text/Document;
Method	scala/text/DocBreak$.$colon$div$colon:(Ljava/lang/String;)Lscala/text/Document;
Asciz	(Lscala/text/Document;)Lscala/text/Document;;
NameAndType	$colon$div$colon:(Lscala/text/Document;)Lscala/text/Document;
Method	scala/text/DocBreak$.$colon$div$colon:(Lscala/text/Document;)Lscala/text/Document;
Asciz	$colon$colon;
NameAndType	$colon$colon:(Ljava/lang/String;)Lscala/text/Document;
Method	scala/text/DocBreak$.$colon$colon:(Ljava/lang/String;)Lscala/text/Document;
NameAndType	$colon$colon:(Lscala/text/Document;)Lscala/text/Document;
Method	scala/text/DocBreak$.$colon$colon:(Lscala/text/Document;)Lscala/text/Document;
Asciz	ScalaSig;
Asciz	Lscala/reflect/ScalaSignature;;
Asciz	bytes;
Asciz	;Q!\t\tR8dJ,m\tA^3yi*\tQ!AtGdm!IQ\")A!A\t.R8dJ,m[\n1y1\t%aB\t\t>W/\3oiB#E\t%!'G.Y(cUG)%Q!J|G-^2u9\"aN\5u}Q\tq\t\"!!xn;sS:<G#uS\"}7b]T!IU4-$=\t11:j]D\"J%\tEJaJ|G-^2u!J,g-=qAK%\t%K\raJ|G-^2uJLG/_UAcKY1!8u!q\"A\nzA9s_,8\r^#mK6,gaM\"E\nI\"!aA!os\"9A'LAQa=%c!Aa'Cs'dC:,/^1m)\tA4s%!>|G.Z1o!T'!AAAB\"P%\tBPeGMU3t_24X\rF@!\ti)B=\t1qJ6fGRD#!C\"A!BA#1XM]5bY&TM7f;
Asciz	RuntimeVisibleAnnotations;
Asciz	scala/text/DocBreak;
class	scala/text/DocBreak
Asciz	java/lang/Object;
class	java/lang/Object

{
public static final scala.collection.Iterator productElements();
  Signature: ()Lscala/collection/Iterator;
  Code:
   Stack=1, Locals=0, Args_size=0
	getstatic	Field scala/text/DocBreak$.MODULE$:Lscala/text/DocBreak$;
	invokevirtual	Method scala/text/DocBreak$.productElements:()Lscala/collection/Iterator;
	areturn
  Labels:
  Deprecated: true

public static final scala.collection.Iterator productIterator();
  Signature: ()Lscala/collection/Iterator;
  Code:
   Stack=1, Locals=0, Args_size=0
	getstatic	Field scala/text/DocBreak$.MODULE$:Lscala/text/DocBreak$;
	invokevirtual	Method scala/text/DocBreak$.productIterator:()Lscala/collection/Iterator;
	areturn
  Labels:

public static final java.lang.String productElementName(int);
  Signature: (I)Ljava/lang/String;
  Code:
   Stack=2, Locals=1, Args_size=1
	getstatic	Field scala/text/DocBreak$.MODULE$:Lscala/text/DocBreak$;
	iload_0
	invokevirtual	Method scala/text/DocBreak$.productElementName:(I)Ljava/lang/String;
	areturn
  Labels:

public static final boolean canEqual(java.lang.Object);
  Signature: (Ljava/lang/Object;)Z
  Code:
   Stack=2, Locals=1, Args_size=1
	getstatic	Field scala/text/DocBreak$.MODULE$:Lscala/text/DocBreak$;
	aload_0
	invokevirtual	Method scala/text/DocBreak$.canEqual:(Ljava/lang/Object;)Z
	ireturn
  Labels:

public static final java.lang.Object productElement(int);
  Signature: (I)Ljava/lang/Object;
  Code:
   Stack=2, Locals=1, Args_size=1
	getstatic	Field scala/text/DocBreak$.MODULE$:Lscala/text/DocBreak$;
	iload_0
	invokevirtual	Method scala/text/DocBreak$.productElement:(I)Ljava/lang/Object;
	areturn
  Labels:

public static final int productArity();
  Signature: ()I
  Code:
   Stack=1, Locals=0, Args_size=0
	getstatic	Field scala/text/DocBreak$.MODULE$:Lscala/text/DocBreak$;
	invokevirtual	Method scala/text/DocBreak$.productArity:()I
	ireturn
  Labels:

public static final java.lang.String productPrefix();
  Signature: ()Ljava/lang/String;
  Code:
   Stack=1, Locals=0, Args_size=0
	getstatic	Field scala/text/DocBreak$.MODULE$:Lscala/text/DocBreak$;
	invokevirtual	Method scala/text/DocBreak$.productPrefix:()Ljava/lang/String;
	areturn
  Labels:

public static final void format(int, java.io.Writer);
  Signature: (ILjava/io/Writer;)V
  Code:
   Stack=3, Locals=2, Args_size=2
	getstatic	Field scala/text/DocBreak$.MODULE$:Lscala/text/DocBreak$;
	iload_0
	aload_1
	invokevirtual	Method scala/text/DocBreak$.format:(ILjava/io/Writer;)V
	return
  Labels:

public static final scala.text.Document $colon$div$colon(java.lang.String);
  Signature: (Ljava/lang/String;)Lscala/text/Document;
  Code:
   Stack=2, Locals=1, Args_size=1
	getstatic	Field scala/text/DocBreak$.MODULE$:Lscala/text/DocBreak$;
	aload_0
	invokevirtual	Method scala/text/DocBreak$.$colon$div$colon:(Ljava/lang/String;)Lscala/text/Document;
	areturn
  Labels:

public static final scala.text.Document $colon$div$colon(scala.text.Document);
  Signature: (Lscala/text/Document;)Lscala/text/Document;
  Code:
   Stack=2, Locals=1, Args_size=1
	getstatic	Field scala/text/DocBreak$.MODULE$:Lscala/text/DocBreak$;
	aload_0
	invokevirtual	Method scala/text/DocBreak$.$colon$div$colon:(Lscala/text/Document;)Lscala/text/Document;
	areturn
  Labels:

public static final scala.text.Document $colon$colon(java.lang.String);
  Signature: (Ljava/lang/String;)Lscala/text/Document;
  Code:
   Stack=2, Locals=1, Args_size=1
	getstatic	Field scala/text/DocBreak$.MODULE$:Lscala/text/DocBreak$;
	aload_0
	invokevirtual	Method scala/text/DocBreak$.$colon$colon:(Ljava/lang/String;)Lscala/text/Document;
	areturn
  Labels:

public static final scala.text.Document $colon$colon(scala.text.Document);
  Signature: (Lscala/text/Document;)Lscala/text/Document;
  Code:
   Stack=2, Locals=1, Args_size=1
	getstatic	Field scala/text/DocBreak$.MODULE$:Lscala/text/DocBreak$;
	aload_0
	invokevirtual	Method scala/text/DocBreak$.$colon$colon:(Lscala/text/Document;)Lscala/text/Document;
	areturn
  Labels:

}

