Compiled from "Document.scala"
public final class scala.text.DocNest$ extends java.lang.Object implements scala.Function2,scala.ScalaObject
  SourceFile: "Document.scala"
  Scala: length = 0x
   
  minor version: 0
  major version: 49
  Constant pool:
const #1 = Asciz	SourceFile;
const #2 = Asciz	Document.scala;
const #3 = Asciz	Scala;
const #4 = Asciz	MODULE$;
const #5 = Asciz	Lscala/text/DocNest$;;
const #6 = Asciz	<clinit>;
const #7 = Asciz	()V;
const #8 = Asciz	Code;
const #9 = Asciz	scala/text/DocNest$;
const #10 = class	#9;	//  scala/text/DocNest$
const #11 = Asciz	<init>;
const #12 = NameAndType	#11:#7;//  "<init>":()V
const #13 = Method	#10.#12;	//  scala/text/DocNest$."<init>":()V
const #14 = Asciz	LineNumberTable;
const #15 = Asciz	java/lang/Object;
const #16 = class	#15;	//  java/lang/Object
const #17 = Method	#16.#12;	//  java/lang/Object."<init>":()V
const #18 = NameAndType	#4:#5;//  MODULE$:Lscala/text/DocNest$;
const #19 = Field	#10.#18;	//  scala/text/DocNest$.MODULE$:Lscala/text/DocNest$;
const #20 = Asciz	scala/Function2$class;
const #21 = class	#20;	//  scala/Function2$class
const #22 = Asciz	$init$;
const #23 = Asciz	(Lscala/Function2;)V;
const #24 = NameAndType	#22:#23;//  $init$:(Lscala/Function2;)V
const #25 = Method	#21.#24;	//  scala/Function2$class.$init$:(Lscala/Function2;)V
const #26 = Asciz	apply;
const #27 = Asciz	(Ljava/lang/Object;Ljava/lang/Object;)Ljava/lang/Object;;
const #28 = Asciz	scala/runtime/BoxesRunTime;
const #29 = class	#28;	//  scala/runtime/BoxesRunTime
const #30 = Asciz	unboxToInt;
const #31 = Asciz	(Ljava/lang/Object;)I;
const #32 = NameAndType	#30:#31;//  unboxToInt:(Ljava/lang/Object;)I
const #33 = Method	#29.#32;	//  scala/runtime/BoxesRunTime.unboxToInt:(Ljava/lang/Object;)I
const #34 = Asciz	scala/text/Document;
const #35 = class	#34;	//  scala/text/Document
const #36 = Asciz	(ILscala/text/Document;)Lscala/text/DocNest;;
const #37 = NameAndType	#26:#36;//  apply:(ILscala/text/Document;)Lscala/text/DocNest;
const #38 = Method	#10.#37;	//  scala/text/DocNest$.apply:(ILscala/text/Document;)Lscala/text/DocNest;
const #39 = Asciz	this;
const #40 = Asciz	v1;
const #41 = Asciz	Ljava/lang/Object;;
const #42 = Asciz	v2;
const #43 = Asciz	LocalVariableTable;
const #44 = Asciz	scala/text/DocNest;
const #45 = class	#44;	//  scala/text/DocNest
const #46 = Asciz	(ILscala/text/Document;)V;
const #47 = NameAndType	#11:#46;//  "<init>":(ILscala/text/Document;)V
const #48 = Method	#45.#47;	//  scala/text/DocNest."<init>":(ILscala/text/Document;)V
const #49 = Asciz	indent;
const #50 = Asciz	I;
const #51 = Asciz	doc;
const #52 = Asciz	Lscala/text/Document;;
const #53 = Asciz	unapply;
const #54 = Asciz	(Lscala/text/DocNest;)Lscala/Some;;
const #55 = Asciz	scala/Some;
const #56 = class	#55;	//  scala/Some
const #57 = Asciz	scala/Tuple2;
const #58 = class	#57;	//  scala/Tuple2
const #59 = Asciz	()I;
const #60 = NameAndType	#49:#59;//  indent:()I
const #61 = Method	#45.#60;	//  scala/text/DocNest.indent:()I
const #62 = Asciz	boxToInteger;
const #63 = Asciz	(I)Ljava/lang/Integer;;
const #64 = NameAndType	#62:#63;//  boxToInteger:(I)Ljava/lang/Integer;
const #65 = Method	#29.#64;	//  scala/runtime/BoxesRunTime.boxToInteger:(I)Ljava/lang/Integer;
const #66 = Asciz	()Lscala/text/Document;;
const #67 = NameAndType	#51:#66;//  doc:()Lscala/text/Document;
const #68 = Method	#45.#67;	//  scala/text/DocNest.doc:()Lscala/text/Document;
const #69 = Asciz	(Ljava/lang/Object;Ljava/lang/Object;)V;
const #70 = NameAndType	#11:#69;//  "<init>":(Ljava/lang/Object;Ljava/lang/Object;)V
const #71 = Method	#58.#70;	//  scala/Tuple2."<init>":(Ljava/lang/Object;Ljava/lang/Object;)V
const #72 = Asciz	(Ljava/lang/Object;)V;
const #73 = NameAndType	#11:#72;//  "<init>":(Ljava/lang/Object;)V
const #74 = Method	#56.#73;	//  scala/Some."<init>":(Ljava/lang/Object;)V
const #75 = Asciz	x$0;
const #76 = Asciz	Lscala/text/DocNest;;
const #77 = Asciz	tuple;
const #78 = Asciz	()Lscala/Function1;;
const #79 = Asciz	(Lscala/Function2;)Lscala/Function1;;
const #80 = NameAndType	#77:#79;//  tuple:(Lscala/Function2;)Lscala/Function1;
const #81 = Method	#21.#80;	//  scala/Function2$class.tuple:(Lscala/Function2;)Lscala/Function1;
const #82 = Asciz	curry;
const #83 = NameAndType	#82:#79;//  curry:(Lscala/Function2;)Lscala/Function1;
const #84 = Method	#21.#83;	//  scala/Function2$class.curry:(Lscala/Function2;)Lscala/Function1;
const #85 = Asciz	toString;
const #86 = Asciz	()Ljava/lang/String;;
const #87 = Asciz	(Lscala/Function2;)Ljava/lang/String;;
const #88 = NameAndType	#85:#87;//  toString:(Lscala/Function2;)Ljava/lang/String;
const #89 = Method	#21.#88;	//  scala/Function2$class.toString:(Lscala/Function2;)Ljava/lang/String;
const #90 = Asciz	scala/Function2;
const #91 = class	#90;	//  scala/Function2
const #92 = Asciz	scala/ScalaObject;
const #93 = class	#92;	//  scala/ScalaObject

{
public static final scala.text.DocNest$ MODULE$;

public static {};
  Code:
   Stack=1, Locals=0, Args_size=0
   0:	new	#10; //class scala/text/DocNest$
   3:	invokespecial	#13; //Method "<init>":()V
   6:	return

public java.lang.Object apply(java.lang.Object, java.lang.Object);
  Code:
   Stack=3, Locals=3, Args_size=3
   0:	aload_0
   1:	aload_1
   2:	invokestatic	#33; //Method scala/runtime/BoxesRunTime.unboxToInt:(Ljava/lang/Object;)I
   5:	aload_2
   6:	checkcast	#35; //class scala/text/Document
   9:	invokevirtual	#38; //Method apply:(ILscala/text/Document;)Lscala/text/DocNest;
   12:	areturn
  LineNumberTable: 
   line 21: 0

  LocalVariableTable: 
   Start  Length  Slot  Name   Signature
   0      13      0    this       Lscala/text/DocNest$;
   0      13      1    v1       Ljava/lang/Object;
   0      13      2    v2       Ljava/lang/Object;


public scala.text.DocNest apply(int, scala.text.Document);
  Code:
   Stack=4, Locals=3, Args_size=3
   0:	new	#45; //class scala/text/DocNest
   3:	dup
   4:	iload_1
   5:	aload_2
   6:	invokespecial	#48; //Method scala/text/DocNest."<init>":(ILscala/text/Document;)V
   9:	areturn
  LineNumberTable: 
   line 21: 0

  LocalVariableTable: 
   Start  Length  Slot  Name   Signature
   0      10      0    this       Lscala/text/DocNest$;
   0      10      1    indent       I
   0      10      2    doc       Lscala/text/Document;


public scala.Some unapply(scala.text.DocNest);
  Code:
   Stack=6, Locals=3, Args_size=2
   0:	new	#56; //class scala/Some
   3:	dup
   4:	new	#58; //class scala/Tuple2
   7:	dup
   8:	aload_1
   9:	invokevirtual	#61; //Method scala/text/DocNest.indent:()I
   12:	istore_2
   13:	iload_2
   14:	invokestatic	#65; //Method scala/runtime/BoxesRunTime.boxToInteger:(I)Ljava/lang/Integer;
   17:	aload_1
   18:	invokevirtual	#68; //Method scala/text/DocNest.doc:()Lscala/text/Document;
   21:	invokespecial	#71; //Method scala/Tuple2."<init>":(Ljava/lang/Object;Ljava/lang/Object;)V
   24:	invokespecial	#74; //Method scala/Some."<init>":(Ljava/lang/Object;)V
   27:	areturn
  LineNumberTable: 
   line 21: 0

  LocalVariableTable: 
   Start  Length  Slot  Name   Signature
   0      28      0    this       Lscala/text/DocNest$;
   0      28      1    x$0       Lscala/text/DocNest;


public scala.Function1 tuple();
  Code:
   Stack=1, Locals=1, Args_size=1
   0:	aload_0
   1:	invokestatic	#81; //Method scala/Function2$class.tuple:(Lscala/Function2;)Lscala/Function1;
   4:	areturn
  LineNumberTable: 
   line 21: 0


public scala.Function1 curry();
  Code:
   Stack=1, Locals=1, Args_size=1
   0:	aload_0
   1:	invokestatic	#84; //Method scala/Function2$class.curry:(Lscala/Function2;)Lscala/Function1;
   4:	areturn
  LineNumberTable: 
   line 21: 0


public java.lang.String toString();
  Code:
   Stack=1, Locals=1, Args_size=1
   0:	aload_0
   1:	invokestatic	#89; //Method scala/Function2$class.toString:(Lscala/Function2;)Ljava/lang/String;
   4:	areturn
  LineNumberTable: 
   line 21: 0


}

