Compiled from "Document.scala"
public final class scala.text.DocNil extends java.lang.Object
  SourceFile: "Document.scala"
  ScalaSig: length = 0x1C4
   05 00 46 07 05 01 02 FFFFFF88 42 07 01 06 44 6F 63 4E
   69 6C 0A 02 03 04 01 04 74 65 78 74 0A 01 05 01
   05 73 63 61 6C 61 03 00 10 02 08 09 0D 01 02 06
   08 0A 02 FFFFFF84 FFFFFF80 FFFFFF80 FFFFFF88 42 0B 02 06 44 6F 63 4E 69
   6C 13 04 09 0C 0F 13 10 02 08 0D 09 02 0E 02 02
   08 44 6F 63 75 6D 65 6E 74 10 02 10 11 0D 01 04
   09 02 12 04 02 0B 53 63 61 6C 61 4F 62 6A 65 63
   74 10 02 10 14 09 02 15 04 02 07 50 72 6F 64 75
   63 74 08 05 17 09 FFFFFF84 00 18 01 06 3C 69 6E 69 74
   3E 14 01 07 08 08 1A 09 FFFFFF84 FFFFFF80 FFFFFF80 FFFFFF84 22 1B 01 08
   74 6F 53 74 72 69 6E 67 14 01 1C 10 02 1D 22 0D
   01 1E 0A 02 1F 20 01 04 6C 61 6E 67 0A 01 21 01
   04 6A 61 76 61 09 02 23 1E 02 06 53 74 72 69 6E
   67 08 08 25 09 FFFFFF84 FFFFFF80 FFFFFF80 FFFFFF84 20 26 01 0D 70 72 6F
   64 75 63 74 50 72 65 66 69 78 15 01 1C 08 08 28
   09 FFFFFF84 FFFFFF80 FFFFFF80 FFFFFF84 20 29 01 0C 70 72 6F 64 75 63 74
   41 72 69 74 79 15 01 2A 10 02 10 2B 09 02 2C 04
   02 03 49 6E 74 08 08 2E 09 FFFFFF84 FFFFFF80 FFFFFF80 FFFFFF84 20 2F 01
   0E 70 72 6F 64 75 63 74 45 6C 65 6D 65 6E 74 14
   02 30 33 10 02 10 31 09 02 32 04 02 03 41 6E 79
   08 07 34 2D FFFFFF81 FFFFFF80 FFFFFFC0 00 2A 01 03 78 24 31 08 08
   36 09 FFFFFF84 FFFFFF80 FFFFFF80 FFFFFF84 20 37 01 08 63 61 6E 45 71 75
   61 6C 14 02 38 3B 10 02 10 39 09 02 3A 04 02 07
   42 6F 6F 6C 65 61 6E 08 07 34 35 FFFFFF81 FFFFFF80 FFFFFFC0 00 30
   08 08 3D 09 FFFFFF84 FFFFFF80 FFFFFF80 FFFFFF84 08 3E 01 0B 72 65 61 64
   52 65 73 6F 6C 76 65 14 01 3F 10 02 1D 40 09 02
   41 1E 02 06 4F 62 6A 65 63 74 28 02 09 43 10 02
   10 44 09 02 45 04 02 0C 73 65 72 69 61 6C 69 7A
   61 62 6C 65 
  minor version: 0
  major version: 49
  Constant pool:
Asciz	SourceFile;
Asciz	Document.scala;
Asciz	productElements;
Asciz	()Lscala/collection/Iterator;;
Asciz	Code;
Asciz	scala/text/DocNil$;
class	scala/text/DocNil$
Asciz	MODULE$;
Asciz	Lscala/text/DocNil$;;
NameAndType	MODULE$:Lscala/text/DocNil$;
Field	scala/text/DocNil$.MODULE$:Lscala/text/DocNil$;
NameAndType	productElements:()Lscala/collection/Iterator;
Method	scala/text/DocNil$.productElements:()Lscala/collection/Iterator;
Asciz	productIterator;
NameAndType	productIterator:()Lscala/collection/Iterator;
Method	scala/text/DocNil$.productIterator:()Lscala/collection/Iterator;
Asciz	canEqual;
Asciz	(Ljava/lang/Object;)Z;
NameAndType	canEqual:(Ljava/lang/Object;)Z
Method	scala/text/DocNil$.canEqual:(Ljava/lang/Object;)Z
Asciz	productElement;
Asciz	(I)Ljava/lang/Object;;
NameAndType	productElement:(I)Ljava/lang/Object;
Method	scala/text/DocNil$.productElement:(I)Ljava/lang/Object;
Asciz	productArity;
Asciz	()I;
NameAndType	productArity:()I
Method	scala/text/DocNil$.productArity:()I
Asciz	productPrefix;
Asciz	()Ljava/lang/String;;
NameAndType	productPrefix:()Ljava/lang/String;
Method	scala/text/DocNil$.productPrefix:()Ljava/lang/String;
Asciz	format;
Asciz	(ILjava/io/Writer;)V;
NameAndType	format:(ILjava/io/Writer;)V
Method	scala/text/DocNil$.format:(ILjava/io/Writer;)V
Asciz	$colon$div$colon;
Asciz	(Ljava/lang/String;)Lscala/text/Document;;
NameAndType	$colon$div$colon:(Ljava/lang/String;)Lscala/text/Document;
Method	scala/text/DocNil$.$colon$div$colon:(Ljava/lang/String;)Lscala/text/Document;
Asciz	(Lscala/text/Document;)Lscala/text/Document;;
NameAndType	$colon$div$colon:(Lscala/text/Document;)Lscala/text/Document;
Method	scala/text/DocNil$.$colon$div$colon:(Lscala/text/Document;)Lscala/text/Document;
Asciz	$colon$colon;
NameAndType	$colon$colon:(Ljava/lang/String;)Lscala/text/Document;
Method	scala/text/DocNil$.$colon$colon:(Ljava/lang/String;)Lscala/text/Document;
NameAndType	$colon$colon:(Lscala/text/Document;)Lscala/text/Document;
Method	scala/text/DocNil$.$colon$colon:(Lscala/text/Document;)Lscala/text/Document;
Asciz	ScalaSig;
Asciz	scala/text/DocNil;
class	scala/text/DocNil
Asciz	java/lang/Object;
class	java/lang/Object

{
public static final scala.collection.Iterator productElements();
  Signature: ()Lscala/collection/Iterator;
  Code:
   Stack=1, Locals=0, Args_size=0
	getstatic	Field scala/text/DocNil$.MODULE$:Lscala/text/DocNil$;
	invokevirtual	Method scala/text/DocNil$.productElements:()Lscala/collection/Iterator;
	areturn
  Labels:

public static final scala.collection.Iterator productIterator();
  Signature: ()Lscala/collection/Iterator;
  Code:
   Stack=1, Locals=0, Args_size=0
	getstatic	Field scala/text/DocNil$.MODULE$:Lscala/text/DocNil$;
	invokevirtual	Method scala/text/DocNil$.productIterator:()Lscala/collection/Iterator;
	areturn
  Labels:

public static final boolean canEqual(java.lang.Object);
  Signature: (Ljava/lang/Object;)Z
  Code:
   Stack=2, Locals=1, Args_size=1
	getstatic	Field scala/text/DocNil$.MODULE$:Lscala/text/DocNil$;
	aload_0
	invokevirtual	Method scala/text/DocNil$.canEqual:(Ljava/lang/Object;)Z
	ireturn
  Labels:

public static final java.lang.Object productElement(int);
  Signature: (I)Ljava/lang/Object;
  Code:
   Stack=2, Locals=1, Args_size=1
	getstatic	Field scala/text/DocNil$.MODULE$:Lscala/text/DocNil$;
	iload_0
	invokevirtual	Method scala/text/DocNil$.productElement:(I)Ljava/lang/Object;
	areturn
  Labels:

public static final int productArity();
  Signature: ()I
  Code:
   Stack=1, Locals=0, Args_size=0
	getstatic	Field scala/text/DocNil$.MODULE$:Lscala/text/DocNil$;
	invokevirtual	Method scala/text/DocNil$.productArity:()I
	ireturn
  Labels:

public static final java.lang.String productPrefix();
  Signature: ()Ljava/lang/String;
  Code:
   Stack=1, Locals=0, Args_size=0
	getstatic	Field scala/text/DocNil$.MODULE$:Lscala/text/DocNil$;
	invokevirtual	Method scala/text/DocNil$.productPrefix:()Ljava/lang/String;
	areturn
  Labels:

public static final void format(int, java.io.Writer);
  Signature: (ILjava/io/Writer;)V
  Code:
   Stack=3, Locals=2, Args_size=2
	getstatic	Field scala/text/DocNil$.MODULE$:Lscala/text/DocNil$;
	iload_0
	aload_1
	invokevirtual	Method scala/text/DocNil$.format:(ILjava/io/Writer;)V
	return
  Labels:

public static final scala.text.Document $colon$div$colon(java.lang.String);
  Signature: (Ljava/lang/String;)Lscala/text/Document;
  Code:
   Stack=2, Locals=1, Args_size=1
	getstatic	Field scala/text/DocNil$.MODULE$:Lscala/text/DocNil$;
	aload_0
	invokevirtual	Method scala/text/DocNil$.$colon$div$colon:(Ljava/lang/String;)Lscala/text/Document;
	areturn
  Labels:

public static final scala.text.Document $colon$div$colon(scala.text.Document);
  Signature: (Lscala/text/Document;)Lscala/text/Document;
  Code:
   Stack=2, Locals=1, Args_size=1
	getstatic	Field scala/text/DocNil$.MODULE$:Lscala/text/DocNil$;
	aload_0
	invokevirtual	Method scala/text/DocNil$.$colon$div$colon:(Lscala/text/Document;)Lscala/text/Document;
	areturn
  Labels:

public static final scala.text.Document $colon$colon(java.lang.String);
  Signature: (Ljava/lang/String;)Lscala/text/Document;
  Code:
   Stack=2, Locals=1, Args_size=1
	getstatic	Field scala/text/DocNil$.MODULE$:Lscala/text/DocNil$;
	aload_0
	invokevirtual	Method scala/text/DocNil$.$colon$colon:(Ljava/lang/String;)Lscala/text/Document;
	areturn
  Labels:

public static final scala.text.Document $colon$colon(scala.text.Document);
  Signature: (Lscala/text/Document;)Lscala/text/Document;
  Code:
   Stack=2, Locals=1, Args_size=1
	getstatic	Field scala/text/DocNil$.MODULE$:Lscala/text/DocNil$;
	aload_0
	invokevirtual	Method scala/text/DocNil$.$colon$colon:(Lscala/text/Document;)Lscala/text/Document;
	areturn
  Labels:

}

