Compiled from "Document.scala"
public final class scala.text.DocNil extends java.lang.Object
  SourceFile: "Document.scala"
  ScalaSig: length = 0x1C4
   05 00 46 07 05 01 02 FFFFFF88 42 07 01 06 44 6F 63 4E
   69 6C 0A 02 03 04 01 04 74 65 78 74 0A 01 05 01
   05 73 63 61 6C 61 03 00 10 02 08 09 0D 01 02 06
   08 0A 02 FFFFFF84 FFFFFF80 FFFFFF80 FFFFFF88 42 0B 02 06 44 6F 63 4E 69
   6C 13 04 09 0C 0F 13 10 02 08 0D 09 02 0E 02 02
   08 44 6F 63 75 6D 65 6E 74 10 02 10 11 0D 01 04
   09 02 12 04 02 0B 53 63 61 6C 61 4F 62 6A 65 63
   74 10 02 10 14 09 02 15 04 02 07 50 72 6F 64 75
   63 74 08 05 17 09 FFFFFF84 00 18 01 06 3C 69 6E 69 74
   3E 14 01 07 08 08 1A 09 FFFFFF84 FFFFFF80 FFFFFF80 FFFFFF84 22 1B 01 08
   74 6F 53 74 72 69 6E 67 14 01 1C 10 02 1D 22 0D
   01 1E 0A 02 1F 20 01 04 6C 61 6E 67 0A 01 21 01
   04 6A 61 76 61 09 02 23 1E 02 06 53 74 72 69 6E
   67 08 08 25 09 FFFFFF84 FFFFFF80 FFFFFF80 FFFFFF84 20 26 01 0D 70 72 6F
   64 75 63 74 50 72 65 66 69 78 15 01 1C 08 08 28
   09 FFFFFF84 FFFFFF80 FFFFFF80 FFFFFF84 20 29 01 0C 70 72 6F 64 75 63 74
   41 72 69 74 79 15 01 2A 10 02 10 2B 09 02 2C 04
   02 03 49 6E 74 08 08 2E 09 FFFFFF84 FFFFFF80 FFFFFF80 FFFFFF84 20 2F 01
   0E 70 72 6F 64 75 63 74 45 6C 65 6D 65 6E 74 14
   02 30 33 10 02 10 31 09 02 32 04 02 03 41 6E 79
   08 07 34 2D FFFFFF81 FFFFFF80 FFFFFFC0 00 2A 01 03 78 24 31 08 08
   36 09 FFFFFF84 FFFFFF80 FFFFFF80 FFFFFF84 20 37 01 08 63 61 6E 45 71 75
   61 6C 14 02 38 3B 10 02 10 39 09 02 3A 04 02 07
   42 6F 6F 6C 65 61 6E 08 07 34 35 FFFFFF81 FFFFFF80 FFFFFFC0 00 30
   08 08 3D 09 FFFFFF84 FFFFFF80 FFFFFF80 FFFFFF84 08 3E 01 0B 72 65 61 64
   52 65 73 6F 6C 76 65 14 01 3F 10 02 1D 40 09 02
   41 1E 02 06 4F 62 6A 65 63 74 28 02 09 43 10 02
   10 44 09 02 45 04 02 0C 73 65 72 69 61 6C 69 7A
   61 62 6C 65 
  minor version: 0
  major version: 49
  Constant pool:
const #1 = Asciz	SourceFile;
const #2 = Asciz	Document.scala;
const #3 = Asciz	productElements;
const #4 = Asciz	()Lscala/collection/Iterator;;
const #5 = Asciz	Code;
const #6 = Asciz	scala/text/DocNil$;
const #7 = class	#6;	//  scala/text/DocNil$
const #8 = Asciz	MODULE$;
const #9 = Asciz	Lscala/text/DocNil$;;
const #10 = NameAndType	#8:#9;//  MODULE$:Lscala/text/DocNil$;
const #11 = Field	#7.#10;	//  scala/text/DocNil$.MODULE$:Lscala/text/DocNil$;
const #12 = NameAndType	#3:#4;//  productElements:()Lscala/collection/Iterator;
const #13 = Method	#7.#12;	//  scala/text/DocNil$.productElements:()Lscala/collection/Iterator;
const #14 = Asciz	productIterator;
const #15 = NameAndType	#14:#4;//  productIterator:()Lscala/collection/Iterator;
const #16 = Method	#7.#15;	//  scala/text/DocNil$.productIterator:()Lscala/collection/Iterator;
const #17 = Asciz	canEqual;
const #18 = Asciz	(Ljava/lang/Object;)Z;
const #19 = NameAndType	#17:#18;//  canEqual:(Ljava/lang/Object;)Z
const #20 = Method	#7.#19;	//  scala/text/DocNil$.canEqual:(Ljava/lang/Object;)Z
const #21 = Asciz	productElement;
const #22 = Asciz	(I)Ljava/lang/Object;;
const #23 = NameAndType	#21:#22;//  productElement:(I)Ljava/lang/Object;
const #24 = Method	#7.#23;	//  scala/text/DocNil$.productElement:(I)Ljava/lang/Object;
const #25 = Asciz	productArity;
const #26 = Asciz	()I;
const #27 = NameAndType	#25:#26;//  productArity:()I
const #28 = Method	#7.#27;	//  scala/text/DocNil$.productArity:()I
const #29 = Asciz	productPrefix;
const #30 = Asciz	()Ljava/lang/String;;
const #31 = NameAndType	#29:#30;//  productPrefix:()Ljava/lang/String;
const #32 = Method	#7.#31;	//  scala/text/DocNil$.productPrefix:()Ljava/lang/String;
const #33 = Asciz	format;
const #34 = Asciz	(ILjava/io/Writer;)V;
const #35 = NameAndType	#33:#34;//  format:(ILjava/io/Writer;)V
const #36 = Method	#7.#35;	//  scala/text/DocNil$.format:(ILjava/io/Writer;)V
const #37 = Asciz	$colon$div$colon;
const #38 = Asciz	(Ljava/lang/String;)Lscala/text/Document;;
const #39 = NameAndType	#37:#38;//  $colon$div$colon:(Ljava/lang/String;)Lscala/text/Document;
const #40 = Method	#7.#39;	//  scala/text/DocNil$.$colon$div$colon:(Ljava/lang/String;)Lscala/text/Document;
const #41 = Asciz	(Lscala/text/Document;)Lscala/text/Document;;
const #42 = NameAndType	#37:#41;//  $colon$div$colon:(Lscala/text/Document;)Lscala/text/Document;
const #43 = Method	#7.#42;	//  scala/text/DocNil$.$colon$div$colon:(Lscala/text/Document;)Lscala/text/Document;
const #44 = Asciz	$colon$colon;
const #45 = NameAndType	#44:#38;//  $colon$colon:(Ljava/lang/String;)Lscala/text/Document;
const #46 = Method	#7.#45;	//  scala/text/DocNil$.$colon$colon:(Ljava/lang/String;)Lscala/text/Document;
const #47 = NameAndType	#44:#41;//  $colon$colon:(Lscala/text/Document;)Lscala/text/Document;
const #48 = Method	#7.#47;	//  scala/text/DocNil$.$colon$colon:(Lscala/text/Document;)Lscala/text/Document;
const #49 = Asciz	ScalaSig;
const #50 = Asciz	scala/text/DocNil;
const #51 = class	#50;	//  scala/text/DocNil
const #52 = Asciz	java/lang/Object;
const #53 = class	#52;	//  java/lang/Object

{
public static final scala.collection.Iterator productElements();
  Code:
   Stack=1, Locals=0, Args_size=0
   0:	getstatic	#11; //Field scala/text/DocNil$.MODULE$:Lscala/text/DocNil$;
   3:	invokevirtual	#13; //Method scala/text/DocNil$.productElements:()Lscala/collection/Iterator;
   6:	areturn

public static final scala.collection.Iterator productIterator();
  Code:
   Stack=1, Locals=0, Args_size=0
   0:	getstatic	#11; //Field scala/text/DocNil$.MODULE$:Lscala/text/DocNil$;
   3:	invokevirtual	#16; //Method scala/text/DocNil$.productIterator:()Lscala/collection/Iterator;
   6:	areturn

public static final boolean canEqual(java.lang.Object);
  Code:
   Stack=2, Locals=1, Args_size=1
   0:	getstatic	#11; //Field scala/text/DocNil$.MODULE$:Lscala/text/DocNil$;
   3:	aload_0
   4:	invokevirtual	#20; //Method scala/text/DocNil$.canEqual:(Ljava/lang/Object;)Z
   7:	ireturn

public static final java.lang.Object productElement(int);
  Code:
   Stack=2, Locals=1, Args_size=1
   0:	getstatic	#11; //Field scala/text/DocNil$.MODULE$:Lscala/text/DocNil$;
   3:	iload_0
   4:	invokevirtual	#24; //Method scala/text/DocNil$.productElement:(I)Ljava/lang/Object;
   7:	areturn

public static final int productArity();
  Code:
   Stack=1, Locals=0, Args_size=0
   0:	getstatic	#11; //Field scala/text/DocNil$.MODULE$:Lscala/text/DocNil$;
   3:	invokevirtual	#28; //Method scala/text/DocNil$.productArity:()I
   6:	ireturn

public static final java.lang.String productPrefix();
  Code:
   Stack=1, Locals=0, Args_size=0
   0:	getstatic	#11; //Field scala/text/DocNil$.MODULE$:Lscala/text/DocNil$;
   3:	invokevirtual	#32; //Method scala/text/DocNil$.productPrefix:()Ljava/lang/String;
   6:	areturn

public static final void format(int, java.io.Writer);
  Code:
   Stack=3, Locals=2, Args_size=2
   0:	getstatic	#11; //Field scala/text/DocNil$.MODULE$:Lscala/text/DocNil$;
   3:	iload_0
   4:	aload_1
   5:	invokevirtual	#36; //Method scala/text/DocNil$.format:(ILjava/io/Writer;)V
   8:	return

public static final scala.text.Document $colon$div$colon(java.lang.String);
  Code:
   Stack=2, Locals=1, Args_size=1
   0:	getstatic	#11; //Field scala/text/DocNil$.MODULE$:Lscala/text/DocNil$;
   3:	aload_0
   4:	invokevirtual	#40; //Method scala/text/DocNil$.$colon$div$colon:(Ljava/lang/String;)Lscala/text/Document;
   7:	areturn

public static final scala.text.Document $colon$div$colon(scala.text.Document);
  Code:
   Stack=2, Locals=1, Args_size=1
   0:	getstatic	#11; //Field scala/text/DocNil$.MODULE$:Lscala/text/DocNil$;
   3:	aload_0
   4:	invokevirtual	#43; //Method scala/text/DocNil$.$colon$div$colon:(Lscala/text/Document;)Lscala/text/Document;
   7:	areturn

public static final scala.text.Document $colon$colon(java.lang.String);
  Code:
   Stack=2, Locals=1, Args_size=1
   0:	getstatic	#11; //Field scala/text/DocNil$.MODULE$:Lscala/text/DocNil$;
   3:	aload_0
   4:	invokevirtual	#46; //Method scala/text/DocNil$.$colon$colon:(Ljava/lang/String;)Lscala/text/Document;
   7:	areturn

public static final scala.text.Document $colon$colon(scala.text.Document);
  Code:
   Stack=2, Locals=1, Args_size=1
   0:	getstatic	#11; //Field scala/text/DocNil$.MODULE$:Lscala/text/DocNil$;
   3:	aload_0
   4:	invokevirtual	#48; //Method scala/text/DocNil$.$colon$colon:(Lscala/text/Document;)Lscala/text/Document;
   7:	areturn

}

