Compiled from "Document.scala"
public final class scala.text.Document$ extends java.lang.Object implements scala.ScalaObject
  SourceFile: "Document.scala"
  Scala: length = 0x
   
  minor version: 0
  major version: 49
  Constant pool:
const #1 = Asciz	SourceFile;
const #2 = Asciz	Document.scala;
const #3 = Asciz	Scala;
const #4 = Asciz	MODULE$;
const #5 = Asciz	Lscala/text/Document$;;
const #6 = Asciz	<clinit>;
const #7 = Asciz	()V;
const #8 = Asciz	Code;
const #9 = Asciz	scala/text/Document$;
const #10 = class	#9;	//  scala/text/Document$
const #11 = Asciz	<init>;
const #12 = NameAndType	#11:#7;//  "<init>":()V
const #13 = Method	#10.#12;	//  scala/text/Document$."<init>":()V
const #14 = Asciz	LineNumberTable;
const #15 = Asciz	java/lang/Object;
const #16 = class	#15;	//  java/lang/Object
const #17 = Method	#16.#12;	//  java/lang/Object."<init>":()V
const #18 = NameAndType	#4:#5;//  MODULE$:Lscala/text/Document$;
const #19 = Field	#10.#18;	//  scala/text/Document$.MODULE$:Lscala/text/Document$;
const #20 = Asciz	nest;
const #21 = Asciz	(ILscala/text/Document;)Lscala/text/Document;;
const #22 = Asciz	scala/text/DocNest;
const #23 = class	#22;	//  scala/text/DocNest
const #24 = Asciz	(ILscala/text/Document;)V;
const #25 = NameAndType	#11:#24;//  "<init>":(ILscala/text/Document;)V
const #26 = Method	#23.#25;	//  scala/text/DocNest."<init>":(ILscala/text/Document;)V
const #27 = Asciz	this;
const #28 = Asciz	i;
const #29 = Asciz	I;
const #30 = Asciz	d;
const #31 = Asciz	Lscala/text/Document;;
const #32 = Asciz	LocalVariableTable;
const #33 = Asciz	group;
const #34 = Asciz	(Lscala/text/Document;)Lscala/text/Document;;
const #35 = Asciz	scala/text/DocGroup;
const #36 = class	#35;	//  scala/text/DocGroup
const #37 = Asciz	(Lscala/text/Document;)V;
const #38 = NameAndType	#11:#37;//  "<init>":(Lscala/text/Document;)V
const #39 = Method	#36.#38;	//  scala/text/DocGroup."<init>":(Lscala/text/Document;)V
const #40 = Asciz	text;
const #41 = Asciz	(Ljava/lang/String;)Lscala/text/Document;;
const #42 = Asciz	scala/text/DocText;
const #43 = class	#42;	//  scala/text/DocText
const #44 = Asciz	(Ljava/lang/String;)V;
const #45 = NameAndType	#11:#44;//  "<init>":(Ljava/lang/String;)V
const #46 = Method	#43.#45;	//  scala/text/DocText."<init>":(Ljava/lang/String;)V
const #47 = Asciz	s;
const #48 = Asciz	Ljava/lang/String;;
const #49 = Asciz	break;
const #50 = Asciz	()Lscala/text/DocBreak$;;
const #51 = Asciz	scala/text/DocBreak$;
const #52 = class	#51;	//  scala/text/DocBreak$
const #53 = Asciz	Lscala/text/DocBreak$;;
const #54 = NameAndType	#4:#53;//  MODULE$:Lscala/text/DocBreak$;
const #55 = Field	#52.#54;	//  scala/text/DocBreak$.MODULE$:Lscala/text/DocBreak$;
const #56 = Asciz	empty;
const #57 = Asciz	()Lscala/text/DocNil$;;
const #58 = Asciz	scala/text/DocNil$;
const #59 = class	#58;	//  scala/text/DocNil$
const #60 = Asciz	Lscala/text/DocNil$;;
const #61 = NameAndType	#4:#60;//  MODULE$:Lscala/text/DocNil$;
const #62 = Field	#59.#61;	//  scala/text/DocNil$.MODULE$:Lscala/text/DocNil$;
const #63 = Asciz	scala/ScalaObject;
const #64 = class	#63;	//  scala/ScalaObject

{
public static final scala.text.Document$ MODULE$;

public static {};
  Code:
   Stack=1, Locals=0, Args_size=0
   0:	new	#10; //class scala/text/Document$
   3:	invokespecial	#13; //Method "<init>":()V
   6:	return

public scala.text.Document nest(int, scala.text.Document);
  Code:
   Stack=4, Locals=3, Args_size=3
   0:	new	#23; //class scala/text/DocNest
   3:	dup
   4:	iload_1
   5:	aload_2
   6:	invokespecial	#26; //Method scala/text/DocNest."<init>":(ILscala/text/Document;)V
   9:	areturn
  LineNumberTable: 
   line 121: 0

  LocalVariableTable: 
   Start  Length  Slot  Name   Signature
   0      10      0    this       Lscala/text/Document$;
   0      10      1    i       I
   0      10      2    d       Lscala/text/Document;


public scala.text.Document group(scala.text.Document);
  Code:
   Stack=3, Locals=2, Args_size=2
   0:	new	#36; //class scala/text/DocGroup
   3:	dup
   4:	aload_1
   5:	invokespecial	#39; //Method scala/text/DocGroup."<init>":(Lscala/text/Document;)V
   8:	areturn
  LineNumberTable: 
   line 118: 0

  LocalVariableTable: 
   Start  Length  Slot  Name   Signature
   0      9      0    this       Lscala/text/Document$;
   0      9      1    d       Lscala/text/Document;


public scala.text.Document text(java.lang.String);
  Code:
   Stack=3, Locals=2, Args_size=2
   0:	new	#43; //class scala/text/DocText
   3:	dup
   4:	aload_1
   5:	invokespecial	#46; //Method scala/text/DocText."<init>":(Ljava/lang/String;)V
   8:	areturn
  LineNumberTable: 
   line 112: 0

  LocalVariableTable: 
   Start  Length  Slot  Name   Signature
   0      9      0    this       Lscala/text/Document$;
   0      9      1    s       Ljava/lang/String;


public scala.text.DocBreak$ break();
  Code:
   Stack=1, Locals=1, Args_size=1
   0:	getstatic	#55; //Field scala/text/DocBreak$.MODULE$:Lscala/text/DocBreak$;
   3:	areturn
  LineNumberTable: 
   line 109: 0


public scala.text.DocNil$ empty();
  Code:
   Stack=1, Locals=1, Args_size=1
   0:	getstatic	#62; //Field scala/text/DocNil$.MODULE$:Lscala/text/DocNil$;
   3:	areturn
  LineNumberTable: 
   line 106: 0


}

