Compiled from "BufferedSource.scala"
public final class scala.io.BufferedSource$$anonfun$1$$anonfun$apply$1 extends java.lang.Object implements scala.Function0,scala.ScalaObject,java.io.Serializable
  SourceFile: "BufferedSource.scala"
  Scala: length = 0x
   
  InnerClass: 
   public final $anonfun$1=class scala/io/BufferedSource$$anonfun$1 of class scala/io/BufferedSource
   public final $anonfun$apply$1=class scala/io/BufferedSource$$anonfun$1$$anonfun$apply$1 of class scala/io/BufferedSource$$anonfun$1
  minor version: 0
  major version: 49
  Constant pool:
Asciz	SourceFile;
Asciz	BufferedSource.scala;
Asciz	<clinit>;
Asciz	()V;
Asciz	Code;
Asciz	serialVersionUID;
Asciz	J;
Asciz	scala/io/BufferedSource$$anonfun$1$$anonfun$apply$1;
class	scala/io/BufferedSource$$anonfun$1$$anonfun$apply$1
NameAndType	serialVersionUID:J
Field	scala/io/BufferedSource$$anonfun$1$$anonfun$apply$1.serialVersionUID:J
Asciz	$outer;
Asciz	Lscala/io/BufferedSource$$anonfun$1;;
Asciz	<init>;
Asciz	(Lscala/io/BufferedSource$$anonfun$1;)V;
Asciz	LineNumberTable;
Asciz	java/lang/NullPointerException;
class	java/lang/NullPointerException
NameAndType	"<init>":()V
Method	java/lang/NullPointerException."<init>":()V
NameAndType	$outer:Lscala/io/BufferedSource$$anonfun$1;
Field	scala/io/BufferedSource$$anonfun$1$$anonfun$apply$1.$outer:Lscala/io/BufferedSource$$anonfun$1;
Asciz	java/lang/Object;
class	java/lang/Object
Method	java/lang/Object."<init>":()V
Asciz	scala/Function0$class;
class	scala/Function0$class
Asciz	$init$;
Asciz	(Lscala/Function0;)V;
NameAndType	$init$:(Lscala/Function0;)V
Method	scala/Function0$class.$init$:(Lscala/Function0;)V
Asciz	this;
Asciz	Lscala/io/BufferedSource$$anonfun$1$$anonfun$apply$1;;
Asciz	LocalVariableTable;
Asciz	apply;
Asciz	()Ljava/lang/Object;;
Asciz	()I;
NameAndType	apply:()I
Method	scala/io/BufferedSource$$anonfun$1$$anonfun$apply$1.apply:()I
Asciz	scala/runtime/BoxesRunTime;
class	scala/runtime/BoxesRunTime
Asciz	boxToInteger;
Asciz	(I)Ljava/lang/Integer;;
NameAndType	boxToInteger:(I)Ljava/lang/Integer;
Method	scala/runtime/BoxesRunTime.boxToInteger:(I)Ljava/lang/Integer;
Asciz	scala/io/BufferedSource$$anonfun$1;
class	scala/io/BufferedSource$$anonfun$1
Asciz	reader$1;
Asciz	Ljava/io/BufferedReader;;
NameAndType	reader$1:Ljava/io/BufferedReader;
Field	scala/io/BufferedSource$$anonfun$1.reader$1:Ljava/io/BufferedReader;
Asciz	java/io/BufferedReader;
class	java/io/BufferedReader
Asciz	read;
NameAndType	read:()I
Method	java/io/BufferedReader.read:()I
Asciz	toString;
Asciz	()Ljava/lang/String;;
Asciz	(Lscala/Function0;)Ljava/lang/String;;
NameAndType	toString:(Lscala/Function0;)Ljava/lang/String;
Method	scala/Function0$class.toString:(Lscala/Function0;)Ljava/lang/String;
Asciz	Scala;
Asciz	InnerClasses;
Asciz	scala/io/BufferedSource;
class	scala/io/BufferedSource
Asciz	$anonfun$1;
Asciz	$anonfun$apply$1;
Asciz	scala/Function0;
class	scala/Function0
Asciz	scala/ScalaObject;
class	scala/ScalaObject
Asciz	java/io/Serializable;
class	java/io/Serializable

{
public static final long serialVersionUID;
  Signature: J

private final scala.io.BufferedSource$$anonfun$1 $outer;
  Signature: Lscala/io/BufferedSource$$anonfun$1;

public static {};
  Signature: ()V
  Code:
   Stack=2, Locals=0, Args_size=0
	lconst_0
	putstatic	Field serialVersionUID:J
	return
  Labels:

public scala.io.BufferedSource$$anonfun$1$$anonfun$apply$1(scala.io.BufferedSource$$anonfun$1);
  Signature: (Lscala/io/BufferedSource$$anonfun$1;)V
  Code:
   Stack=2, Locals=2, Args_size=2
	aload_1
	ifnonnull	l1 // aload_0
	new	class java/lang/NullPointerException
	dup
	invokespecial	Method java/lang/NullPointerException."<init>":()V
	athrow
l1	aload_0
	aload_1
	putfield	Field $outer:Lscala/io/BufferedSource$$anonfun$1;
	aload_0
	invokespecial	Method java/lang/Object."<init>":()V
	aload_0
	invokestatic	Method scala/Function0$class.$init$:(Lscala/Function0;)V
	return
  Labels:
   	l1 = 12 // aload_0
  LocalVariableTable: 
   Start  Length  Slot  Name   Signature
   0      26      0    this       Lscala/io/BufferedSource$$anonfun$1$$anonfun$apply$1;
   0      26      1    $outer       Lscala/io/BufferedSource$$anonfun$1;


public final java.lang.Object apply();
  Signature: ()Ljava/lang/Object;
  Code:
   Stack=1, Locals=3, Args_size=1
	aload_0
	getfield	Field $outer:Lscala/io/BufferedSource$$anonfun$1;
	astore_2
	aload_0
	invokevirtual	Method apply:()I
	istore_1
	iload_1
	invokestatic	Method scala/runtime/BoxesRunTime.boxToInteger:(I)Ljava/lang/Integer;
	areturn
  Labels:
  LocalVariableTable: 
   Start  Length  Slot  Name   Signature
   0      15      0    this       Lscala/io/BufferedSource$$anonfun$1$$anonfun$apply$1;


public final int apply();
  Signature: ()I
  Code:
   Stack=1, Locals=2, Args_size=1
	aload_0
	getfield	Field $outer:Lscala/io/BufferedSource$$anonfun$1;
	astore_1
	aload_0
	getfield	Field $outer:Lscala/io/BufferedSource$$anonfun$1;
	getfield	Field scala/io/BufferedSource$$anonfun$1.reader$1:Ljava/io/BufferedReader;
	invokevirtual	Method java/io/BufferedReader.read:()I
	ireturn
  Labels:
  LocalVariableTable: 
   Start  Length  Slot  Name   Signature
   0      16      0    this       Lscala/io/BufferedSource$$anonfun$1$$anonfun$apply$1;


public java.lang.String toString();
  Signature: ()Ljava/lang/String;
  Code:
   Stack=1, Locals=1, Args_size=1
	aload_0
	invokestatic	Method scala/Function0$class.toString:(Lscala/Function0;)Ljava/lang/String;
	areturn
  Labels:

}

