Compiled from "BufferedSource.scala"
public final class scala.io.BufferedSource$$anon$1 extends scala.io.BufferedSource
  SourceFile: "BufferedSource.scala"
  Scala: length = 0x
   
  InnerClass: 
   public final #40= #10 of #14; //$anon$1=class scala/io/BufferedSource$$anon$1 of class scala/io/BufferedSource
  minor version: 0
  major version: 49
  Constant pool:
const #1 = Asciz	SourceFile;
const #2 = Asciz	BufferedSource.scala;
const #3 = Asciz	reset$1;
const #4 = Asciz	Lscala/Function0;;
const #5 = Asciz	<init>;
const #6 = Asciz	(Ljava/io/InputStream;ILscala/Function0;Lscala/io/Codec;)V;
const #7 = Asciz	Code;
const #8 = Asciz	LineNumberTable;
const #9 = Asciz	scala/io/BufferedSource$$anon$1;
const #10 = class	#9;	//  scala/io/BufferedSource$$anon$1
const #11 = NameAndType	#3:#4;//  reset$1:Lscala/Function0;
const #12 = Field	#10.#11;	//  scala/io/BufferedSource$$anon$1.reset$1:Lscala/Function0;
const #13 = Asciz	scala/io/BufferedSource;
const #14 = class	#13;	//  scala/io/BufferedSource
const #15 = Asciz	(Ljava/io/InputStream;ILscala/io/Codec;)V;
const #16 = NameAndType	#5:#15;//  "<init>":(Ljava/io/InputStream;ILscala/io/Codec;)V
const #17 = Method	#14.#16;	//  scala/io/BufferedSource."<init>":(Ljava/io/InputStream;ILscala/io/Codec;)V
const #18 = Asciz	reset;
const #19 = Asciz	()Lscala/io/Source;;
const #20 = Asciz	scala/io/BufferedSource$;
const #21 = class	#20;	//  scala/io/BufferedSource$
const #22 = Asciz	MODULE$;
const #23 = Asciz	Lscala/io/BufferedSource$;;
const #24 = NameAndType	#22:#23;//  MODULE$:Lscala/io/BufferedSource$;
const #25 = Field	#21.#24;	//  scala/io/BufferedSource$.MODULE$:Lscala/io/BufferedSource$;
const #26 = Asciz	_reset$1;
const #27 = Asciz	(Lscala/Function0;)Lscala/Function0;;
const #28 = NameAndType	#26:#27;//  _reset$1:(Lscala/Function0;)Lscala/Function0;
const #29 = Method	#21.#28;	//  scala/io/BufferedSource$._reset$1:(Lscala/Function0;)Lscala/Function0;
const #30 = Asciz	scala/Function0;
const #31 = class	#30;	//  scala/Function0
const #32 = Asciz	apply;
const #33 = Asciz	()Ljava/lang/Object;;
const #34 = NameAndType	#32:#33;//  apply:()Ljava/lang/Object;
const #35 = InterfaceMethod	#31.#34;	//  scala/Function0.apply:()Ljava/lang/Object;
const #36 = Asciz	scala/io/Source;
const #37 = class	#36;	//  scala/io/Source
const #38 = Asciz	Scala;
const #39 = Asciz	InnerClasses;
const #40 = Asciz	$anon$1;

{
public scala.io.BufferedSource$$anon$1(java.io.InputStream, int, scala.Function0, scala.io.Codec);
  Code:
   Stack=4, Locals=5, Args_size=5
   0:	aload_0
   1:	aload_3
   2:	putfield	#12; //Field reset$1:Lscala/Function0;
   5:	aload_0
   6:	aload_1
   7:	iload_2
   8:	aload	4
   10:	invokespecial	#17; //Method scala/io/BufferedSource."<init>":(Ljava/io/InputStream;ILscala/io/Codec;)V
   13:	return
  LineNumberTable: 
   line 39: 0


public scala.io.Source reset();
  Code:
   Stack=2, Locals=1, Args_size=1
   0:	getstatic	#25; //Field scala/io/BufferedSource$.MODULE$:Lscala/io/BufferedSource$;
   3:	aload_0
   4:	getfield	#12; //Field reset$1:Lscala/Function0;
   7:	invokevirtual	#29; //Method scala/io/BufferedSource$._reset$1:(Lscala/Function0;)Lscala/Function0;
   10:	invokeinterface	#35,  1; //InterfaceMethod scala/Function0.apply:()Ljava/lang/Object;
   15:	checkcast	#37; //class scala/io/Source
   18:	areturn
  LineNumberTable: 
   line 40: 0


}

