Compiled from "BytePickle.scala"
public class scala.io.BytePickle$UnPicklerState extends java.lang.Object implements scala.ScalaObject
  SourceFile: "BytePickle.scala"
  Scala: length = 0x
   
  InnerClass: 
   public #33= #30 of #32; //UnPicklerEnv=class scala/io/BytePickle$UnPicklerEnv of class scala/io/BytePickle
   public #34= #12 of #32; //UnPicklerState=class scala/io/BytePickle$UnPicklerState of class scala/io/BytePickle
  minor version: 0
  major version: 49
  Constant pool:
const #1 = Asciz	SourceFile;
const #2 = Asciz	BytePickle.scala;
const #3 = Asciz	dict;
const #4 = Asciz	Lscala/io/BytePickle$UnPicklerEnv;;
const #5 = Asciz	stream;
const #6 = Asciz	[B;
const #7 = Asciz	<init>;
const #8 = Asciz	([BLscala/io/BytePickle$UnPicklerEnv;)V;
const #9 = Asciz	Code;
const #10 = Asciz	LineNumberTable;
const #11 = Asciz	scala/io/BytePickle$UnPicklerState;
const #12 = class	#11;	//  scala/io/BytePickle$UnPicklerState
const #13 = NameAndType	#5:#6;//  stream:[B
const #14 = Field	#12.#13;	//  scala/io/BytePickle$UnPicklerState.stream:[B
const #15 = NameAndType	#3:#4;//  dict:Lscala/io/BytePickle$UnPicklerEnv;
const #16 = Field	#12.#15;	//  scala/io/BytePickle$UnPicklerState.dict:Lscala/io/BytePickle$UnPicklerEnv;
const #17 = Asciz	java/lang/Object;
const #18 = class	#17;	//  java/lang/Object
const #19 = Asciz	()V;
const #20 = NameAndType	#7:#19;//  "<init>":()V
const #21 = Method	#18.#20;	//  java/lang/Object."<init>":()V
const #22 = Asciz	this;
const #23 = Asciz	Lscala/io/BytePickle$UnPicklerState;;
const #24 = Asciz	LocalVariableTable;
const #25 = Asciz	()Lscala/io/BytePickle$UnPicklerEnv;;
const #26 = Asciz	()[B;
const #27 = Asciz	Scala;
const #28 = Asciz	InnerClasses;
const #29 = Asciz	scala/io/BytePickle$UnPicklerEnv;
const #30 = class	#29;	//  scala/io/BytePickle$UnPicklerEnv
const #31 = Asciz	scala/io/BytePickle;
const #32 = class	#31;	//  scala/io/BytePickle
const #33 = Asciz	UnPicklerEnv;
const #34 = Asciz	UnPicklerState;
const #35 = Asciz	scala/ScalaObject;
const #36 = class	#35;	//  scala/ScalaObject

{
public scala.io.BytePickle$UnPicklerState(byte[], scala.io.BytePickle$UnPicklerEnv);
  Code:
   Stack=2, Locals=3, Args_size=3
   0:	aload_0
   1:	aload_1
   2:	putfield	#14; //Field stream:[B
   5:	aload_0
   6:	aload_2
   7:	putfield	#16; //Field dict:Lscala/io/BytePickle$UnPicklerEnv;
   10:	aload_0
   11:	invokespecial	#21; //Method java/lang/Object."<init>":()V
   14:	return
  LineNumberTable: 
   line 59: 0

  LocalVariableTable: 
   Start  Length  Slot  Name   Signature
   0      15      0    this       Lscala/io/BytePickle$UnPicklerState;
   0      15      1    stream       [B
   0      15      2    dict       Lscala/io/BytePickle$UnPicklerEnv;


public scala.io.BytePickle$UnPicklerEnv dict();
  Code:
   Stack=1, Locals=1, Args_size=1
   0:	aload_0
   1:	getfield	#16; //Field dict:Lscala/io/BytePickle$UnPicklerEnv;
   4:	areturn
  LineNumberTable: 
   line 59: 0


public byte[] stream();
  Code:
   Stack=1, Locals=1, Args_size=1
   0:	aload_0
   1:	getfield	#14; //Field stream:[B
   4:	areturn
  LineNumberTable: 
   line 59: 0


}

