Compiled from "BytePickle.scala"
public final class scala.io.BytePickle extends java.lang.Object
  SourceFile: "BytePickle.scala"
  ScalaSig: length = 0x1052
   05 00 FFFFFF84 33 07 05 01 02 FFFFFF88 02 07 01 0A 42 79 74
   65 50 69 63 6B 6C 65 0A 02 03 04 01 02 69 6F 0A
   01 05 01 05 73 63 61 6C 61 03 00 10 02 08 09 0D
   01 02 06 08 0A 02 FFFFFF84 FFFFFF80 FFFFFF80 FFFFFF88 02 0B 02 0A 42 79
   74 65 50 69 63 6B 6C 65 13 03 09 0C 14 10 02 0D
   12 0D 01 0E 0A 02 0F 10 01 04 6C 61 6E 67 0A 01
   11 01 04 6A 61 76 61 09 02 13 0E 02 06 4F 62 6A
   65 63 74 10 02 15 16 0D 01 04 09 02 17 04 02 0B
   53 63 61 6C 61 4F 62 6A 65 63 74 08 05 19 09 FFFFFF84
   00 1A 01 06 3C 69 6E 69 74 3E 14 01 07 06 05 1C
   09 FFFFFF81 00 1D 02 03 53 50 55 15 02 1E 25 13 03 1B
   0C 14 08 05 19 1B FFFFFF84 00 20 14 01 21 10 03 22 1B
   23 0D 01 09 10 02 24 25 0C 00 04 08 26 1B FFFFFF84 FFFFFF80
   FFFFFF80 FFFFFFC2 00 27 02 01 54 11 02 28 2B 10 02 15 29 09
   02 2A 04 02 07 4E 6F 74 68 69 6E 67 10 02 15 2C
   09 02 2D 04 02 03 41 6E 79 08 05 2F 1B FFFFFF86 00 30
   01 04 61 70 70 50 14 03 31 6A 6C 10 02 22 32 06
   08 33 09 FFFFFF84 FFFFFF80 FFFFFF80 FFFFFF80 00 34 02 0C 50 69 63 6B 6C
   65 72 53 74 61 74 65 13 03 32 0C 14 08 08 36 32
   FFFFFF82 FFFFFFC2 FFFFFF80 FFFFFF84 00 37 01 06 73 74 72 65 61 6D 15 01
   38 10 03 15 39 3B 09 02 3A 04 02 05 41 72 72 61
   79 10 02 15 3C 09 02 3D 04 02 04 42 79 74 65 08
   08 3F 32 FFFFFF82 FFFFFF80 FFFFFFA0 FFFFFF80 04 38 01 07 73 74 72 65 61
   6D 20 08 08 41 32 FFFFFF82 FFFFFFC2 FFFFFF80 FFFFFF84 00 42 01 04 64 69
   63 74 15 01 43 10 02 22 44 06 08 45 09 FFFFFF84 FFFFFF80 FFFFFF80
   FFFFFF80 00 46 02 0A 50 69 63 6B 6C 65 72 45 6E 76 13
   03 44 47 14 10 04 48 4D 2B 4F 0D 01 49 0A 02 4A
   4B 01 07 6D 75 74 61 62 6C 65 0A 02 4C 04 01 0A
   63 6F 6C 6C 65 63 74 69 6F 6E 09 02 4E 49 02 07
   48 61 73 68 4D 61 70 10 02 15 50 09 02 51 04 02
   03 49 6E 74 08 05 19 44 FFFFFF84 00 53 14 01 43 08 07
   55 44 FFFFFFC0 FFFFFF80 FFFFFF84 04 56 01 03 63 6E 74 15 01 4F 08
   07 58 44 FFFFFFC0 FFFFFF80 FFFFFF84 04 59 01 07 63 6E 74 5F 24 65
   71 14 02 5A 5D 10 02 15 5B 09 02 5C 04 02 04 55
   6E 69 74 08 07 5E 57 FFFFFF81 FFFFFF80 FFFFFFC0 00 4F 01 03 78 24
   31 08 06 60 44 FFFFFFA0 FFFFFFA0 04 4F 01 04 63 6E 74 20 08
   05 62 44 FFFFFF84 00 63 01 07 6E 65 78 74 4C 6F 63 14
   01 4F 08 08 65 32 FFFFFF82 FFFFFF80 FFFFFFA0 FFFFFF80 04 43 01 05 64 69
   63 74 20 08 05 19 32 FFFFFF84 00 67 14 03 31 68 69 08
   05 36 66 FFFFFFC0 00 38 08 05 41 66 FFFFFFC0 00 43 08 05 6B
   2E FFFFFFC0 00 23 01 01 61 08 05 6D 2E FFFFFFC0 00 31 01 05
   73 74 61 74 65 08 05 6F 1B FFFFFF86 00 70 01 04 61 70
   70 55 14 03 71 FFFFFF81 0E 10 04 15 72 23 74 09 02 73
   04 02 06 54 75 70 6C 65 32 10 02 22 75 06 08 76
   09 FFFFFF84 FFFFFF80 FFFFFF80 FFFFFF80 00 77 02 0E 55 6E 50 69 63 6B 6C
   65 72 53 74 61 74 65 13 03 75 0C 14 08 08 36 75
   FFFFFF82 FFFFFFC2 FFFFFF80 FFFFFF84 00 37 08 08 3F 75 FFFFFF82 FFFFFF80 FFFFFFA0 FFFFFF80 04 38
   08 08 41 75 FFFFFF82 FFFFFFC2 FFFFFF80 FFFFFF84 00 7B 15 01 7C 10 02 22
   7D 06 08 7E 09 FFFFFF84 FFFFFF80 FFFFFF80 FFFFFF80 00 7F 02 0C 55 6E 50
   69 63 6B 6C 65 72 45 6E 76 13 04 7D FFFFFF81 00 14 10
   04 48 4D 4F 2B 08 06 19 7D FFFFFF84 00 FFFFFF81 02 14 01 7C
   08 07 55 7D FFFFFFC0 FFFFFF80 FFFFFF84 04 56 08 08 58 7D FFFFFFC0 FFFFFF80 FFFFFF84
   04 FFFFFF81 05 14 03 5A FFFFFF81 06 08 08 5E FFFFFF81 04 FFFFFF81 FFFFFF80 FFFFFFC0
   00 4F 08 06 60 7D FFFFFFA0 FFFFFFA0 04 4F 08 05 62 7D FFFFFF84 00
   63 08 08 65 75 FFFFFF82 FFFFFF80 FFFFFFA0 FFFFFF80 04 7C 08 06 19 75 FFFFFF84
   00 FFFFFF81 0B 14 05 74 FFFFFF81 0C FFFFFF81 0D 08 06 36 FFFFFF81 0A FFFFFFC0
   00 38 08 06 41 FFFFFF81 0A FFFFFFC0 00 7C 08 05 6D 6E FFFFFFC0 00
   74 08 07 FFFFFF81 10 09 FFFFFF84 00 FFFFFF81 11 01 06 70 69 63 6B
   6C 65 15 04 FFFFFF81 12 FFFFFF81 17 14 05 38 FFFFFF81 13 FFFFFF81 18 08
   08 FFFFFF81 14 FFFFFF81 0F FFFFFFC0 00 FFFFFF81 15 01 01 70 10 04 22 1B
   FFFFFF81 16 10 03 24 FFFFFF81 17 04 09 26 FFFFFF81 0F FFFFFF84 FFFFFF80 FFFFFF80 FFFFFFC2
   00 27 08 07 6B FFFFFF81 0F FFFFFFC0 00 FFFFFF81 16 08 07 FFFFFF81 1A 09
   FFFFFF84 00 FFFFFF81 1B 01 08 75 6E 70 69 63 6B 6C 65 15 04
   FFFFFF81 1C FFFFFF81 1E 14 06 FFFFFF81 1D FFFFFF81 1F FFFFFF81 21 10 03 24 FFFFFF81
   1E 04 09 26 FFFFFF81 19 FFFFFF84 FFFFFF80 FFFFFF80 FFFFFFC2 00 27 08 08 FFFFFF81 14
   FFFFFF81 19 FFFFFFC0 00 FFFFFF81 20 10 04 22 1B FFFFFF81 1D 08 06 36 FFFFFF81
   19 FFFFFFC0 00 38 06 07 FFFFFF81 23 09 FFFFFF81 00 FFFFFF81 24 02 02 50
   55 15 04 FFFFFF81 25 FFFFFF81 2A 13 04 FFFFFF81 22 0C 14 08 07 19
   FFFFFF81 22 FFFFFF84 00 FFFFFF81 27 14 02 FFFFFF81 28 10 05 22 FFFFFF81 22 FFFFFF81
   29 10 03 24 FFFFFF81 2A 04 09 26 FFFFFF81 22 FFFFFF84 FFFFFF80 FFFFFF80 FFFFFFC2 00
   27 08 07 2F FFFFFF81 22 FFFFFF86 00 FFFFFF81 2C 14 05 38 FFFFFF81 2D FFFFFF81
   2E 08 07 6B FFFFFF81 2B FFFFFFC0 00 FFFFFF81 29 08 06 6D FFFFFF81 2B FFFFFFC0
   00 38 08 07 6F FFFFFF81 22 FFFFFF86 00 FFFFFF81 30 14 04 FFFFFF81 31 FFFFFF81
   32 10 05 15 72 FFFFFF81 29 38 08 06 6D FFFFFF81 2F FFFFFFC0 00 38
   08 07 FFFFFF81 34 09 FFFFFF84 00 FFFFFF81 35 01 07 75 70 69 63 6B
   6C 65 15 04 FFFFFF81 36 FFFFFF81 3A 14 05 38 FFFFFF81 37 FFFFFF81 3B 08
   08 FFFFFF81 14 FFFFFF81 33 FFFFFFC0 00 FFFFFF81 38 10 05 22 FFFFFF81 22 FFFFFF81 39
   10 03 24 FFFFFF81 3A 04 09 26 FFFFFF81 33 FFFFFF84 FFFFFF80 FFFFFF80 FFFFFFC2 00 27
   08 07 6B FFFFFF81 33 FFFFFFC0 00 FFFFFF81 39 08 07 FFFFFF81 3D 09 FFFFFF84 00
   FFFFFF81 3E 01 09 75 75 6E 70 69 63 6B 6C 65 15 04 FFFFFF81
   3F FFFFFF81 41 14 06 FFFFFF81 40 FFFFFF81 42 FFFFFF81 44 10 03 24 FFFFFF81 41
   04 09 26 FFFFFF81 3C FFFFFF84 FFFFFF80 FFFFFF80 FFFFFFC2 00 27 08 08 FFFFFF81 14 FFFFFF81
   3C FFFFFFC0 00 FFFFFF81 43 10 05 22 FFFFFF81 22 FFFFFF81 40 08 06 36 FFFFFF81
   3C FFFFFFC0 00 38 06 0A FFFFFF81 46 09 FFFFFF84 FFFFFF80 FFFFFF80 FFFFFF81 00 FFFFFF81 47
   02 06 52 65 66 44 65 66 13 04 FFFFFF81 45 0C 14 08 07
   19 FFFFFF81 45 FFFFFF84 00 FFFFFF81 49 14 02 FFFFFF81 4A 10 03 22 FFFFFF81 45
   06 0A FFFFFF81 4C 09 FFFFFF84 FFFFFF80 FFFFFF80 FFFFFF80 40 FFFFFF81 4D 02 03 52 65
   66 13 07 FFFFFF81 4B FFFFFF81 4A 14 FFFFFF81 4E 10 03 15 FFFFFF81 4F 09
   03 FFFFFF81 50 04 02 07 50 72 6F 64 75 63 74 08 07 19
   FFFFFF81 4B FFFFFF84 00 FFFFFF81 52 14 02 FFFFFF81 53 10 03 22 FFFFFF81 4B 08
   0A FFFFFF81 55 FFFFFF81 4B FFFFFF84 FFFFFF80 FFFFFF80 FFFFFF84 20 63 01 08 68 61 73
   68 43 6F 64 65 08 0B FFFFFF81 57 FFFFFF81 4B FFFFFF84 FFFFFF80 FFFFFF80 FFFFFF84 20
   FFFFFF81 58 01 08 74 6F 53 74 72 69 6E 67 14 02 FFFFFF81 59
   10 04 FFFFFF81 5A FFFFFF81 5D 0E 03 15 FFFFFF81 5B 09 03 FFFFFF81 5C 04
   01 06 50 72 65 64 65 66 09 04 FFFFFF81 5E FFFFFF81 5F 02 06
   53 74 72 69 6E 67 0A 03 FFFFFF81 5C 04 08 0B FFFFFF81 61 FFFFFF81
   4B FFFFFF84 FFFFFF80 FFFFFF80 FFFFFF84 20 FFFFFF81 62 01 06 65 71 75 61 6C 73
   14 04 FFFFFF81 63 FFFFFF81 66 10 03 15 FFFFFF81 64 09 03 FFFFFF81 65 04
   02 07 42 6F 6F 6C 65 61 6E 08 08 5E FFFFFF81 60 FFFFFF81 FFFFFF80
   FFFFFFC0 00 2B 08 0B FFFFFF81 68 FFFFFF81 4B FFFFFF84 FFFFFF80 FFFFFF80 FFFFFF84 20 FFFFFF81 69
   01 0D 70 72 6F 64 75 63 74 50 72 65 66 69 78 15
   02 FFFFFF81 6A 10 03 0D FFFFFF81 6B 09 03 FFFFFF81 5E 0E 08 0A FFFFFF81
   6D FFFFFF81 4B FFFFFF84 FFFFFF80 FFFFFF80 FFFFFF84 20 56 01 0C 70 72 6F 64 75
   63 74 41 72 69 74 79 08 0B FFFFFF81 6F FFFFFF81 4B FFFFFF84 FFFFFF80 FFFFFF80
   FFFFFF84 20 FFFFFF81 70 01 0E 70 72 6F 64 75 63 74 45 6C 65
   6D 65 6E 74 14 03 2B FFFFFF81 71 08 08 5E FFFFFF81 6E FFFFFF81 FFFFFF80
   FFFFFFC0 00 4F 08 0B FFFFFF81 73 FFFFFF81 4B FFFFFF84 FFFFFF80 FFFFFF80 FFFFFF84 20 FFFFFF81 74
   01 08 63 61 6E 45 71 75 61 6C 14 04 FFFFFF81 63 FFFFFF81 75
   08 08 5E FFFFFF81 72 FFFFFF81 FFFFFF80 FFFFFFC0 00 2B 28 04 FFFFFF81 4B FFFFFF81 77
   10 03 15 FFFFFF81 78 09 03 FFFFFF81 79 04 02 0C 73 65 72 69
   61 6C 69 7A 61 62 6C 65 07 09 FFFFFF81 7B 09 FFFFFF81 FFFFFF80 FFFFFF88
   02 FFFFFF81 7C 01 03 52 65 66 10 03 22 FFFFFF81 7D 06 0A FFFFFF81
   4C 09 FFFFFF84 FFFFFF81 FFFFFF80 FFFFFF88 02 FFFFFF81 7E 13 06 FFFFFF81 7D 0C FFFFFF81 7F
   14 10 05 15 FFFFFF82 00 FFFFFF81 53 09 03 FFFFFF82 01 04 02 09 46
   75 6E 63 74 69 6F 6E 30 08 07 19 FFFFFF81 7D FFFFFF84 00 FFFFFF82
   03 14 02 FFFFFF81 7C 08 0A FFFFFF82 05 FFFFFF81 7D FFFFFF81 FFFFFF80 FFFFFF84 40 FFFFFF81
   52 01 05 61 70 70 6C 79 08 0A FFFFFF82 07 FFFFFF81 7D FFFFFF81 FFFFFF80
   FFFFFF84 40 FFFFFF82 08 01 07 75 6E 61 70 70 6C 79 14 04 FFFFFF81
   63 FFFFFF82 09 08 08 FFFFFF82 0A FFFFFF82 06 FFFFFFC0 00 FFFFFF81 53 01 03 78
   24 30 06 0A FFFFFF82 0C 09 FFFFFF84 FFFFFF80 FFFFFF80 FFFFFF80 40 FFFFFF82 0D 02 03
   44 65 66 13 07 FFFFFF82 0B FFFFFF81 4A 14 FFFFFF81 4E 08 07 19 FFFFFF82
   0B FFFFFF84 00 FFFFFF82 0F 14 02 FFFFFF82 10 10 03 22 FFFFFF82 0B 08 0A
   FFFFFF81 55 FFFFFF82 0B FFFFFF84 FFFFFF80 FFFFFF80 FFFFFF84 20 63 08 0B FFFFFF81 57 FFFFFF82 0B
   FFFFFF84 FFFFFF80 FFFFFF80 FFFFFF84 20 FFFFFF81 58 08 0B FFFFFF81 61 FFFFFF82 0B FFFFFF84 FFFFFF80 FFFFFF80
   FFFFFF84 20 FFFFFF82 14 14 04 FFFFFF81 63 FFFFFF82 15 08 08 5E FFFFFF82 13 FFFFFF81
   FFFFFF80 FFFFFFC0 00 2B 08 0B FFFFFF81 68 FFFFFF82 0B FFFFFF84 FFFFFF80 FFFFFF80 FFFFFF84 20 FFFFFF81
   69 08 0A FFFFFF81 6D FFFFFF82 0B FFFFFF84 FFFFFF80 FFFFFF80 FFFFFF84 20 56 08 0B FFFFFF81
   6F FFFFFF82 0B FFFFFF84 FFFFFF80 FFFFFF80 FFFFFF84 20 FFFFFF82 19 14 03 2B FFFFFF82 1A 08
   08 5E FFFFFF82 18 FFFFFF81 FFFFFF80 FFFFFFC0 00 4F 08 0B FFFFFF81 73 FFFFFF82 0B FFFFFF84
   FFFFFF80 FFFFFF80 FFFFFF84 20 FFFFFF82 1C 14 04 FFFFFF81 63 FFFFFF82 1D 08 08 5E FFFFFF82
   1B FFFFFF81 FFFFFF80 FFFFFFC0 00 2B 28 04 FFFFFF82 0B FFFFFF81 77 07 09 FFFFFF82 20
   09 FFFFFF81 FFFFFF80 FFFFFF88 02 FFFFFF82 21 01 03 44 65 66 10 03 22 FFFFFF82
   22 06 0A FFFFFF82 0C 09 FFFFFF84 FFFFFF81 FFFFFF80 FFFFFF88 02 FFFFFF82 23 13 06 FFFFFF82
   22 0C FFFFFF82 24 14 10 05 15 FFFFFF82 00 FFFFFF82 10 08 07 19 FFFFFF82
   22 FFFFFF84 00 FFFFFF82 26 14 02 FFFFFF82 21 08 0A FFFFFF82 05 FFFFFF82 22 FFFFFF81
   FFFFFF80 FFFFFF84 40 FFFFFF82 0F 08 0A FFFFFF82 07 FFFFFF82 22 FFFFFF81 FFFFFF80 FFFFFF84 40 FFFFFF82
   29 14 04 FFFFFF81 63 FFFFFF82 2A 08 08 FFFFFF82 0A FFFFFF82 28 FFFFFFC0 00 FFFFFF82
   10 08 07 FFFFFF82 2C 09 FFFFFF84 00 FFFFFF82 2D 01 06 72 65 66 44
   65 66 15 02 FFFFFF82 2E 10 05 22 FFFFFF81 22 FFFFFF81 4A 08 08 FFFFFF82
   30 09 FFFFFFC2 FFFFFF80 FFFFFF84 00 56 01 03 52 45 46 08 07 FFFFFF82 32
   09 FFFFFFA0 FFFFFF80 04 4F 01 04 52 45 46 20 08 08 FFFFFF82 34 09
   FFFFFFC2 FFFFFF80 FFFFFF84 00 56 01 03 44 45 46 08 07 FFFFFF82 36 09 FFFFFFA0
   FFFFFF80 04 4F 01 04 44 45 46 20 08 07 FFFFFF82 38 09 FFFFFF84 00
   FFFFFF82 39 01 04 75 6E 61 74 15 02 FFFFFF82 3A 10 04 22 FFFFFF81
   22 4F 08 07 FFFFFF82 3C 09 FFFFFF84 00 FFFFFF82 3D 01 05 73 68 61
   72 65 15 04 FFFFFF82 3E FFFFFF82 41 14 04 FFFFFF82 3F FFFFFF82 43 10 04
   22 1B FFFFFF82 40 10 03 24 FFFFFF82 41 04 0A FFFFFF82 42 FFFFFF82 3B FFFFFF84
   FFFFFF80 FFFFFF80 FFFFFFC2 00 27 02 01 61 08 08 FFFFFF82 44 FFFFFF82 3B FFFFFFC0 00
   FFFFFF82 3F 01 02 70 61 08 07 FFFFFF82 46 09 FFFFFF84 00 FFFFFF82 47 01
   05 75 6C 69 66 74 15 04 FFFFFF82 48 FFFFFF82 4B 14 04 FFFFFF82 49
   FFFFFF82 4D 10 05 22 FFFFFF81 22 FFFFFF82 4A 10 03 24 FFFFFF82 4B 04 0A
   FFFFFF82 4C FFFFFF82 45 FFFFFF84 FFFFFF80 FFFFFF80 FFFFFFC2 00 27 02 01 74 08 08 FFFFFF82
   4E FFFFFF82 45 FFFFFFC0 00 FFFFFF82 4A 01 01 78 08 07 FFFFFF82 50 09 FFFFFF84
   00 FFFFFF82 51 01 04 6C 69 66 74 15 04 FFFFFF82 52 FFFFFF82 55 14
   04 FFFFFF82 53 FFFFFF82 56 10 04 22 1B FFFFFF82 54 10 03 24 FFFFFF82 55
   04 0A FFFFFF82 4C FFFFFF82 4F FFFFFF84 FFFFFF80 FFFFFF80 FFFFFFC2 00 27 08 08 FFFFFF82 4E
   FFFFFF82 4F FFFFFFC0 00 FFFFFF82 54 08 07 FFFFFF82 58 09 FFFFFF84 00 FFFFFF82 59 01
   05 75 73 65 71 75 15 06 FFFFFF82 5A FFFFFF82 65 FFFFFF82 5D 14 08
   FFFFFF82 5B FFFFFF82 5F FFFFFF82 66 FFFFFF82 68 10 05 22 FFFFFF81 22 FFFFFF82 5C 10
   03 24 FFFFFF82 5D 04 0A FFFFFF82 5E FFFFFF82 57 FFFFFF84 FFFFFF80 FFFFFF80 FFFFFFC2 00 27
   02 01 75 08 08 FFFFFF82 60 FFFFFF82 57 FFFFFFC0 00 FFFFFF82 61 01 01 66
   10 07 15 FFFFFF82 62 FFFFFF82 5C FFFFFF82 64 09 03 FFFFFF82 63 04 02 09
   46 75 6E 63 74 69 6F 6E 31 10 03 24 FFFFFF82 65 04 0A
   FFFFFF82 4C FFFFFF82 57 FFFFFF84 FFFFFF80 FFFFFF80 FFFFFFC2 00 27 08 08 FFFFFF82 44 FFFFFF82 57
   FFFFFFC0 00 FFFFFF82 67 10 05 22 FFFFFF81 22 FFFFFF82 64 08 08 FFFFFF82 69 FFFFFF82
   57 FFFFFFC0 00 FFFFFF82 6A 01 01 6B 10 07 15 FFFFFF82 62 FFFFFF82 64 FFFFFF82
   5B 08 07 FFFFFF82 6C 09 FFFFFF84 00 FFFFFF82 6D 01 04 73 65 71 75
   15 06 FFFFFF82 6E FFFFFF82 75 FFFFFF82 71 14 08 FFFFFF82 6F FFFFFF82 72 FFFFFF82 76
   FFFFFF82 78 10 04 22 1B FFFFFF82 70 10 03 24 FFFFFF82 71 04 0A FFFFFF82
   5E FFFFFF82 6B FFFFFF84 FFFFFF80 FFFFFF80 FFFFFFC2 00 27 08 08 FFFFFF82 60 FFFFFF82 6B FFFFFFC0
   00 FFFFFF82 73 10 07 15 FFFFFF82 62 FFFFFF82 70 FFFFFF82 74 10 03 24 FFFFFF82
   75 04 0A FFFFFF82 4C FFFFFF82 6B FFFFFF84 FFFFFF80 FFFFFF80 FFFFFFC2 00 27 08 08 FFFFFF82
   44 FFFFFF82 6B FFFFFFC0 00 FFFFFF82 77 10 04 22 1B FFFFFF82 74 08 08 FFFFFF82
   69 FFFFFF82 6B FFFFFFC0 00 FFFFFF82 79 10 07 15 FFFFFF82 62 FFFFFF82 74 FFFFFF82 6F
   08 07 FFFFFF82 7B 09 FFFFFF84 00 FFFFFF82 7C 01 05 75 70 61 69 72
   15 06 FFFFFF82 7D FFFFFF83 01 FFFFFF83 03 14 06 FFFFFF82 7E FFFFFF83 05 FFFFFF83 07
   10 05 22 FFFFFF81 22 FFFFFF82 7F 10 06 15 72 FFFFFF83 00 FFFFFF83 02 10
   03 24 FFFFFF83 01 04 0A FFFFFF82 42 FFFFFF82 7A FFFFFF84 FFFFFF80 FFFFFF80 FFFFFFC2 00 27
   10 03 24 FFFFFF83 03 04 0A FFFFFF83 04 FFFFFF82 7A FFFFFF84 FFFFFF80 FFFFFF80 FFFFFFC2 00
   27 02 01 62 08 08 FFFFFF82 44 FFFFFF82 7A FFFFFFC0 00 FFFFFF83 06 10 05
   22 FFFFFF81 22 FFFFFF83 00 08 08 FFFFFF83 08 FFFFFF82 7A FFFFFFC0 00 FFFFFF83 09 01
   02 70 62 10 05 22 FFFFFF81 22 FFFFFF83 02 08 07 FFFFFF83 0B 09 FFFFFF84
   00 FFFFFF83 0C 01 04 70 61 69 72 15 06 FFFFFF83 0D FFFFFF83 11 FFFFFF83
   13 14 06 FFFFFF83 0E FFFFFF83 14 FFFFFF83 16 10 04 22 1B FFFFFF83 0F 10
   06 15 72 FFFFFF83 10 FFFFFF83 12 10 03 24 FFFFFF83 11 04 0A FFFFFF82 42
   FFFFFF83 0A FFFFFF84 FFFFFF80 FFFFFF80 FFFFFFC2 00 27 10 03 24 FFFFFF83 13 04 0A FFFFFF83
   04 FFFFFF83 0A FFFFFF84 FFFFFF80 FFFFFF80 FFFFFFC2 00 27 08 08 FFFFFF82 44 FFFFFF83 0A FFFFFFC0
   00 FFFFFF83 15 10 04 22 1B FFFFFF83 10 08 08 FFFFFF83 08 FFFFFF83 0A FFFFFFC0
   00 FFFFFF83 17 10 04 22 1B FFFFFF83 12 08 07 FFFFFF83 19 09 FFFFFF84 00
   FFFFFF83 1A 01 06 74 72 69 70 6C 65 15 08 FFFFFF83 1B FFFFFF83 21
   FFFFFF83 23 FFFFFF83 25 14 08 FFFFFF83 1C FFFFFF83 27 FFFFFF83 29 FFFFFF83 2B 10 04
   22 1B FFFFFF83 1D 10 09 15 FFFFFF83 1E FFFFFF83 20 FFFFFF83 22 FFFFFF83 24 09
   03 FFFFFF83 1F 04 02 06 54 75 70 6C 65 33 10 03 24 FFFFFF83
   21 04 0A FFFFFF82 42 FFFFFF83 18 FFFFFF84 FFFFFF80 FFFFFF80 FFFFFFC2 00 27 10 03 24
   FFFFFF83 23 04 0A FFFFFF83 04 FFFFFF83 18 FFFFFF84 FFFFFF80 FFFFFF80 FFFFFFC2 00 27 10 03
   24 FFFFFF83 25 04 0A FFFFFF83 26 FFFFFF83 18 FFFFFF84 FFFFFF80 FFFFFF80 FFFFFFC2 00 27 02
   01 63 08 08 FFFFFF82 44 FFFFFF83 18 FFFFFFC0 00 FFFFFF83 28 10 04 22 1B
   FFFFFF83 20 08 08 FFFFFF83 08 FFFFFF83 18 FFFFFFC0 00 FFFFFF83 2A 10 04 22 1B
   FFFFFF83 22 08 08 FFFFFF83 2C FFFFFF83 18 FFFFFFC0 00 FFFFFF83 2D 01 02 70 63
   10 04 22 1B FFFFFF83 24 08 07 FFFFFF83 2F 09 FFFFFF84 00 FFFFFF83 30 01
   05 75 77 72 61 70 15 06 FFFFFF83 31 FFFFFF83 39 FFFFFF83 34 14 08
   FFFFFF83 32 FFFFFF83 35 FFFFFF83 3A FFFFFF83 3D 10 05 22 FFFFFF81 22 FFFFFF83 33 10
   03 24 FFFFFF83 34 04 0A FFFFFF83 04 FFFFFF83 2E FFFFFF84 FFFFFF80 FFFFFF80 FFFFFFC2 00 27
   08 08 FFFFFF83 36 FFFFFF83 2E FFFFFFC0 00 FFFFFF83 37 01 01 69 10 07 15
   FFFFFF82 62 FFFFFF83 38 FFFFFF83 33 10 03 24 FFFFFF83 39 04 0A FFFFFF82 42 FFFFFF83
   2E FFFFFF84 FFFFFF80 FFFFFF80 FFFFFFC2 00 27 08 08 FFFFFF83 3B FFFFFF83 2E FFFFFFC0 00 FFFFFF83
   3C 01 01 6A 10 07 15 FFFFFF82 62 FFFFFF83 33 FFFFFF83 38 08 08 FFFFFF82
   44 FFFFFF83 2E FFFFFFC0 00 FFFFFF83 3E 10 05 22 FFFFFF81 22 FFFFFF83 38 08 07
   FFFFFF83 40 09 FFFFFF84 00 FFFFFF83 41 01 04 77 72 61 70 15 06 FFFFFF83
   42 FFFFFF83 49 FFFFFF83 45 14 08 FFFFFF83 43 FFFFFF83 46 FFFFFF83 4A FFFFFF83 4C 10
   04 22 1B FFFFFF83 44 10 03 24 FFFFFF83 45 04 0A FFFFFF83 04 FFFFFF83 3F
   FFFFFF84 FFFFFF80 FFFFFF80 FFFFFFC2 00 27 08 08 FFFFFF83 36 FFFFFF83 3F FFFFFFC0 00 FFFFFF83 47
   10 07 15 FFFFFF82 62 FFFFFF83 48 FFFFFF83 44 10 03 24 FFFFFF83 49 04 0A
   FFFFFF82 42 FFFFFF83 3F FFFFFF84 FFFFFF80 FFFFFF80 FFFFFFC2 00 27 08 08 FFFFFF83 3B FFFFFF83 3F
   FFFFFFC0 00 FFFFFF83 4B 10 07 15 FFFFFF82 62 FFFFFF83 44 FFFFFF83 48 08 08 FFFFFF82
   44 FFFFFF83 3F FFFFFFC0 00 FFFFFF83 4D 10 04 22 1B FFFFFF83 48 08 07 FFFFFF83
   4F 09 FFFFFF84 00 FFFFFF83 50 01 0A 61 70 70 65 6E 64 42 79
   74 65 14 05 38 FFFFFF83 51 FFFFFF83 52 08 06 6B FFFFFF83 4E FFFFFFC0 00
   38 08 07 FFFFFF83 53 FFFFFF83 4E FFFFFFC0 00 4F 01 01 62 08 07 FFFFFF83
   55 09 FFFFFF84 00 FFFFFF83 56 01 09 6E 61 74 32 42 79 74 65
   73 14 03 38 FFFFFF83 57 08 07 FFFFFF82 4E FFFFFF83 54 FFFFFFC0 00 4F 08
   07 FFFFFF83 59 09 FFFFFF84 00 FFFFFF83 5A 01 03 6E 61 74 15 02 FFFFFF83
   5B 10 03 22 1B 4F 08 07 FFFFFF83 5D 09 FFFFFF84 00 FFFFFF83 5E 01
   04 62 79 74 65 15 02 FFFFFF83 5F 10 03 22 1B 3B 08 07
   FFFFFF83 61 09 FFFFFF84 00 FFFFFF83 62 01 06 73 74 72 69 6E 67 15
   02 FFFFFF83 63 10 04 22 1B FFFFFF81 59 08 07 FFFFFF83 65 09 FFFFFF84 00
   FFFFFF83 66 01 09 62 79 74 65 61 72 72 61 79 15 02 FFFFFF83
   67 10 03 22 1B 38 08 07 FFFFFF83 69 09 FFFFFF84 00 FFFFFF83 6A 01
   04 62 6F 6F 6C 15 02 FFFFFF83 6B 10 04 22 1B FFFFFF81 63 08
   07 FFFFFF83 6D 09 FFFFFF84 00 FFFFFF83 6E 01 0A 75 66 69 78 65 64
   4C 69 73 74 15 04 FFFFFF83 6F FFFFFF83 7F 14 04 FFFFFF83 70 FFFFFF84 03
   14 04 FFFFFF83 71 FFFFFF84 01 10 05 22 FFFFFF81 22 FFFFFF83 72 10 06 FFFFFF83
   73 FFFFFF83 7B FFFFFF83 7E 0E 04 FFFFFF83 74 FFFFFF83 79 0E 04 FFFFFF83 75 FFFFFF83
   78 0D 02 FFFFFF83 76 0A 03 FFFFFF83 77 06 01 06 3C 72 6F 6F
   74 3E 09 01 05 09 03 FFFFFF83 7A 04 01 07 70 61 63 6B
   61 67 65 09 04 FFFFFF83 7C FFFFFF83 7D 02 04 4C 69 73 74 0A
   03 FFFFFF83 7A 04 10 03 24 FFFFFF83 7F 04 0A FFFFFF84 00 FFFFFF83 6C FFFFFF84
   FFFFFF80 FFFFFF80 FFFFFFC2 00 27 02 01 41 08 07 FFFFFF84 02 FFFFFF83 6C FFFFFFC0 00
   4F 01 01 6E 08 08 FFFFFF82 44 FFFFFF83 6C FFFFFFC0 00 FFFFFF84 04 10 05
   22 FFFFFF81 22 FFFFFF83 7E 08 07 FFFFFF84 06 09 FFFFFF84 00 FFFFFF84 07 01 09
   66 69 78 65 64 4C 69 73 74 15 04 FFFFFF84 08 FFFFFF84 0D 14
   04 FFFFFF84 09 FFFFFF84 0F 14 04 FFFFFF84 0A FFFFFF84 0E 10 04 22 1B FFFFFF84
   0B 10 06 FFFFFF83 73 FFFFFF83 7B FFFFFF84 0C 10 03 24 FFFFFF84 0D 04 0A
   FFFFFF82 42 FFFFFF84 05 FFFFFF84 FFFFFF80 FFFFFF80 FFFFFFC2 00 27 08 07 FFFFFF84 02 FFFFFF84 05
   FFFFFFC0 00 4F 08 08 FFFFFF82 44 FFFFFF84 05 FFFFFFC0 00 FFFFFF84 10 10 04 22
   1B FFFFFF84 0C 08 07 FFFFFF84 12 09 FFFFFF84 00 FFFFFF84 13 01 04 6C 69
   73 74 15 04 FFFFFF84 14 FFFFFF84 18 14 04 FFFFFF84 15 FFFFFF84 19 10 04
   22 1B FFFFFF84 16 10 06 FFFFFF83 73 FFFFFF83 7B FFFFFF84 17 10 03 24 FFFFFF84
   18 04 0A FFFFFF82 42 FFFFFF84 11 FFFFFF84 FFFFFF80 FFFFFF80 FFFFFFC2 00 27 08 08 FFFFFF82
   44 FFFFFF84 11 FFFFFFC0 00 FFFFFF84 1A 10 04 22 1B FFFFFF84 17 08 07 FFFFFF84
   1C 09 FFFFFF84 00 FFFFFF84 1D 01 05 75 6C 69 73 74 15 04 FFFFFF84
   1E FFFFFF84 22 14 04 FFFFFF84 1F FFFFFF84 23 10 05 22 FFFFFF81 22 FFFFFF84 20
   10 06 FFFFFF83 73 FFFFFF83 7B FFFFFF84 21 10 03 24 FFFFFF84 22 04 0A FFFFFF82
   42 FFFFFF84 1B FFFFFF84 FFFFFF80 FFFFFF80 FFFFFFC2 00 27 08 08 FFFFFF82 44 FFFFFF84 1B FFFFFFC0
   00 FFFFFF84 24 10 05 22 FFFFFF81 22 FFFFFF84 21 08 07 FFFFFF84 26 09 FFFFFF84
   00 FFFFFF84 27 01 04 64 61 74 61 15 04 FFFFFF84 28 FFFFFF84 2B 14
   06 FFFFFF84 29 FFFFFF84 2C FFFFFF84 2F 10 04 22 1B FFFFFF84 2A 10 03 24
   FFFFFF84 2B 04 0A FFFFFF82 42 FFFFFF84 25 FFFFFF84 FFFFFF80 FFFFFF80 FFFFFFC2 00 27 08 08
   FFFFFF84 2D FFFFFF84 25 FFFFFFC0 00 FFFFFF84 2E 01 03 74 61 67 10 06 15
   FFFFFF82 62 FFFFFF84 2A 4F 08 08 FFFFFF84 30 FFFFFF84 25 FFFFFFC0 00 FFFFFF84 31 01
   02 70 73 10 06 FFFFFF83 73 FFFFFF83 7B FFFFFF84 32 10 05 15 FFFFFF82 00
   FFFFFF84 29 
  InnerClass: 
   public abstract #201= #198 of #200; //PU=class scala/io/BytePickle$PU of class scala/io/BytePickle
   public #204= #203 of #200; //Def=class scala/io/BytePickle$Def of class scala/io/BytePickle
   public #207= #206 of #200; //Ref=class scala/io/BytePickle$Ref of class scala/io/BytePickle
   public abstract #210= #209 of #200; //SPU=class scala/io/BytePickle$SPU of class scala/io/BytePickle
   public abstract #213= #212 of #200; //RefDef=class scala/io/BytePickle$RefDef of class scala/io/BytePickle
   public final #216= #215 of #200; //$anon$9=class scala/io/BytePickle$$anon$9 of class scala/io/BytePickle
   public final #219= #218 of #200; //$anon$8=class scala/io/BytePickle$$anon$8 of class scala/io/BytePickle
   public final #222= #221 of #200; //$anon$7=class scala/io/BytePickle$$anon$7 of class scala/io/BytePickle
   public final #225= #224 of #200; //$anon$6=class scala/io/BytePickle$$anon$6 of class scala/io/BytePickle
   public final #228= #227 of #200; //$anon$5=class scala/io/BytePickle$$anon$5 of class scala/io/BytePickle
   public final #231= #230 of #200; //$anon$4=class scala/io/BytePickle$$anon$4 of class scala/io/BytePickle
   public final #234= #233 of #200; //$anon$3=class scala/io/BytePickle$$anon$3 of class scala/io/BytePickle
   public final #237= #236 of #200; //$anon$2=class scala/io/BytePickle$$anon$2 of class scala/io/BytePickle
   public final #240= #239 of #200; //$anon$1=class scala/io/BytePickle$$anon$1 of class scala/io/BytePickle
   public #243= #242 of #200; //PicklerEnv=class scala/io/BytePickle$PicklerEnv of class scala/io/BytePickle
   public #246= #245 of #200; //PicklerState=class scala/io/BytePickle$PicklerState of class scala/io/BytePickle
   public #249= #248 of #200; //UnPicklerEnv=class scala/io/BytePickle$UnPicklerEnv of class scala/io/BytePickle
   public #252= #251 of #200; //UnPicklerState=class scala/io/BytePickle$UnPicklerState of class scala/io/BytePickle
   public final #255= #254 of #200; //$anonfun$data$1=class scala/io/BytePickle$$anonfun$data$1 of class scala/io/BytePickle
   public final #258= #257 of #200; //$anonfun$list$2=class scala/io/BytePickle$$anonfun$list$2 of class scala/io/BytePickle
   public final #261= #260 of #200; //$anonfun$list$1=class scala/io/BytePickle$$anonfun$list$1 of class scala/io/BytePickle
   public final #264= #263 of #200; //$anonfun$bool$2=class scala/io/BytePickle$$anonfun$bool$2 of class scala/io/BytePickle
   public final #267= #266 of #200; //$anonfun$bool$1=class scala/io/BytePickle$$anonfun$bool$1 of class scala/io/BytePickle
   public final #270= #269 of #200; //$anonfun$wrap$1=class scala/io/BytePickle$$anonfun$wrap$1 of class scala/io/BytePickle
   public final #273= #272 of #200; //$anonfun$pair$2=class scala/io/BytePickle$$anonfun$pair$2 of class scala/io/BytePickle
   public final #276= #275 of #200; //$anonfun$pair$1=class scala/io/BytePickle$$anonfun$pair$1 of class scala/io/BytePickle
   public final #279= #278 of #200; //$anonfun$ulist$2=class scala/io/BytePickle$$anonfun$ulist$2 of class scala/io/BytePickle
   public final #282= #281 of #200; //$anonfun$ulist$1=class scala/io/BytePickle$$anonfun$ulist$1 of class scala/io/BytePickle
   public final #285= #284 of #200; //$anonfun$uwrap$1=class scala/io/BytePickle$$anonfun$uwrap$1 of class scala/io/BytePickle
   public final #288= #287 of #200; //$anonfun$upair$2=class scala/io/BytePickle$$anonfun$upair$2 of class scala/io/BytePickle
   public final #291= #290 of #200; //$anonfun$upair$1=class scala/io/BytePickle$$anonfun$upair$1 of class scala/io/BytePickle
   public final #294= #293 of #200; //$anonfun$string$2=class scala/io/BytePickle$$anonfun$string$2 of class scala/io/BytePickle
   public final #297= #296 of #200; //$anonfun$string$1=class scala/io/BytePickle$$anonfun$string$1 of class scala/io/BytePickle
   public final #300= #299 of #200; //$anonfun$triple$2=class scala/io/BytePickle$$anonfun$triple$2 of class scala/io/BytePickle
   public final #303= #302 of #200; //$anonfun$triple$1=class scala/io/BytePickle$$anonfun$triple$1 of class scala/io/BytePickle
   public final #306= #305 of #200; //$anonfun$fixedList$2=class scala/io/BytePickle$$anonfun$fixedList$2 of class scala/io/BytePickle
   public final #309= #308 of #200; //$anonfun$fixedList$1=class scala/io/BytePickle$$anonfun$fixedList$1 of class scala/io/BytePickle
   public final #312= #311 of #200; //$anonfun$bytearray$2=class scala/io/BytePickle$$anonfun$bytearray$2 of class scala/io/BytePickle
   public final #315= #314 of #200; //$anonfun$bytearray$1=class scala/io/BytePickle$$anonfun$bytearray$1 of class scala/io/BytePickle
   public final #318= #317 of #200; //$anonfun$ufixedList$2=class scala/io/BytePickle$$anonfun$ufixedList$2 of class scala/io/BytePickle
   public final #321= #320 of #200; //$anonfun$ufixedList$1=class scala/io/BytePickle$$anonfun$ufixedList$1 of class scala/io/BytePickle
  minor version: 0
  major version: 49
  Constant pool:
const #1 = Asciz	SourceFile;
const #2 = Asciz	BytePickle.scala;
const #3 = Asciz	listToPair$2;
const #4 = Asciz	(Lscala/collection/immutable/List;)Lscala/Tuple2;;
const #5 = Asciz	Code;
const #6 = Asciz	scala/io/BytePickle$;
const #7 = class	#6;	//  scala/io/BytePickle$
const #8 = Asciz	MODULE$;
const #9 = Asciz	Lscala/io/BytePickle$;;
const #10 = NameAndType	#8:#9;//  MODULE$:Lscala/io/BytePickle$;
const #11 = Field	#7.#10;	//  scala/io/BytePickle$.MODULE$:Lscala/io/BytePickle$;
const #12 = NameAndType	#3:#4;//  listToPair$2:(Lscala/collection/immutable/List;)Lscala/Tuple2;
const #13 = Method	#7.#12;	//  scala/io/BytePickle$.listToPair$2:(Lscala/collection/immutable/List;)Lscala/Tuple2;
const #14 = Asciz	pairToList$2;
const #15 = Asciz	(Lscala/Tuple2;)Lscala/collection/immutable/List;;
const #16 = NameAndType	#14:#15;//  pairToList$2:(Lscala/Tuple2;)Lscala/collection/immutable/List;
const #17 = Method	#7.#16;	//  scala/io/BytePickle$.pairToList$2:(Lscala/Tuple2;)Lscala/collection/immutable/List;
const #18 = Asciz	listToPair$1;
const #19 = NameAndType	#18:#4;//  listToPair$1:(Lscala/collection/immutable/List;)Lscala/Tuple2;
const #20 = Method	#7.#19;	//  scala/io/BytePickle$.listToPair$1:(Lscala/collection/immutable/List;)Lscala/Tuple2;
const #21 = Asciz	pairToList$1;
const #22 = NameAndType	#21:#15;//  pairToList$1:(Lscala/Tuple2;)Lscala/collection/immutable/List;
const #23 = Method	#7.#22;	//  scala/io/BytePickle$.pairToList$1:(Lscala/Tuple2;)Lscala/collection/immutable/List;
const #24 = Asciz	fromEnum$1;
const #25 = Asciz	(I)Z;
const #26 = NameAndType	#24:#25;//  fromEnum$1:(I)Z
const #27 = Method	#7.#26;	//  scala/io/BytePickle$.fromEnum$1:(I)Z
const #28 = Asciz	toEnum$1;
const #29 = Asciz	(Z)I;
const #30 = NameAndType	#28:#29;//  toEnum$1:(Z)I
const #31 = Method	#7.#30;	//  scala/io/BytePickle$.toEnum$1:(Z)I
const #32 = Asciz	trd$1;
const #33 = Asciz	(Lscala/Tuple3;)Ljava/lang/Object;;
const #34 = NameAndType	#32:#33;//  trd$1:(Lscala/Tuple3;)Ljava/lang/Object;
const #35 = Method	#7.#34;	//  scala/io/BytePickle$.trd$1:(Lscala/Tuple3;)Ljava/lang/Object;
const #36 = Asciz	snd$3;
const #37 = NameAndType	#36:#33;//  snd$3:(Lscala/Tuple3;)Ljava/lang/Object;
const #38 = Method	#7.#37;	//  scala/io/BytePickle$.snd$3:(Lscala/Tuple3;)Ljava/lang/Object;
const #39 = Asciz	fst$3;
const #40 = NameAndType	#39:#33;//  fst$3:(Lscala/Tuple3;)Ljava/lang/Object;
const #41 = Method	#7.#40;	//  scala/io/BytePickle$.fst$3:(Lscala/Tuple3;)Ljava/lang/Object;
const #42 = Asciz	snd$2;
const #43 = Asciz	(Lscala/Tuple2;)Ljava/lang/Object;;
const #44 = NameAndType	#42:#43;//  snd$2:(Lscala/Tuple2;)Ljava/lang/Object;
const #45 = Method	#7.#44;	//  scala/io/BytePickle$.snd$2:(Lscala/Tuple2;)Ljava/lang/Object;
const #46 = Asciz	fst$2;
const #47 = NameAndType	#46:#43;//  fst$2:(Lscala/Tuple2;)Ljava/lang/Object;
const #48 = Method	#7.#47;	//  scala/io/BytePickle$.fst$2:(Lscala/Tuple2;)Ljava/lang/Object;
const #49 = Asciz	snd$1;
const #50 = NameAndType	#49:#43;//  snd$1:(Lscala/Tuple2;)Ljava/lang/Object;
const #51 = Method	#7.#50;	//  scala/io/BytePickle$.snd$1:(Lscala/Tuple2;)Ljava/lang/Object;
const #52 = Asciz	fst$1;
const #53 = NameAndType	#52:#43;//  fst$1:(Lscala/Tuple2;)Ljava/lang/Object;
const #54 = Method	#7.#53;	//  scala/io/BytePickle$.fst$1:(Lscala/Tuple2;)Ljava/lang/Object;
const #55 = Asciz	data;
const #56 = Asciz	(Lscala/Function1;Lscala/collection/immutable/List;)Lscala/io/BytePickle$SPU;;
const #57 = NameAndType	#55:#56;//  data:(Lscala/Function1;Lscala/collection/immutable/List;)Lscala/io/BytePickle$SPU;
const #58 = Method	#7.#57;	//  scala/io/BytePickle$.data:(Lscala/Function1;Lscala/collection/immutable/List;)Lscala/io/BytePickle$SPU;
const #59 = Asciz	<a:Ljava/lang/Object;>(Lscala/Function1<Ta;Ljava/lang/Integer;>;Lscala/collection/immutable/List<Lscala/Function0<Lscala/io/BytePickle$SPU<Ta;>;>;>;)Lscala/io/BytePickle$SPU<Ta;>;;
const #60 = Asciz	Signature;
const #61 = Asciz	ulist;
const #62 = Asciz	(Lscala/io/BytePickle$PU;)Lscala/io/BytePickle$PU;;
const #63 = NameAndType	#61:#62;//  ulist:(Lscala/io/BytePickle$PU;)Lscala/io/BytePickle$PU;
const #64 = Method	#7.#63;	//  scala/io/BytePickle$.ulist:(Lscala/io/BytePickle$PU;)Lscala/io/BytePickle$PU;
const #65 = Asciz	<a:Ljava/lang/Object;>(Lscala/io/BytePickle$PU<Ta;>;)Lscala/io/BytePickle$PU<Lscala/collection/immutable/List<Ta;>;>;;
const #66 = Asciz	list;
const #67 = Asciz	(Lscala/io/BytePickle$SPU;)Lscala/io/BytePickle$SPU;;
const #68 = NameAndType	#66:#67;//  list:(Lscala/io/BytePickle$SPU;)Lscala/io/BytePickle$SPU;
const #69 = Method	#7.#68;	//  scala/io/BytePickle$.list:(Lscala/io/BytePickle$SPU;)Lscala/io/BytePickle$SPU;
const #70 = Asciz	<a:Ljava/lang/Object;>(Lscala/io/BytePickle$SPU<Ta;>;)Lscala/io/BytePickle$SPU<Lscala/collection/immutable/List<Ta;>;>;;
const #71 = Asciz	fixedList;
const #72 = Asciz	(Lscala/io/BytePickle$SPU;I)Lscala/io/BytePickle$SPU;;
const #73 = NameAndType	#71:#72;//  fixedList:(Lscala/io/BytePickle$SPU;I)Lscala/io/BytePickle$SPU;
const #74 = Method	#7.#73;	//  scala/io/BytePickle$.fixedList:(Lscala/io/BytePickle$SPU;I)Lscala/io/BytePickle$SPU;
const #75 = Asciz	<a:Ljava/lang/Object;>(Lscala/io/BytePickle$SPU<Ta;>;I)Lscala/io/BytePickle$SPU<Lscala/collection/immutable/List<Ta;>;>;;
const #76 = Asciz	ufixedList;
const #77 = Asciz	(Lscala/io/BytePickle$PU;I)Lscala/io/BytePickle$PU;;
const #78 = NameAndType	#76:#77;//  ufixedList:(Lscala/io/BytePickle$PU;I)Lscala/io/BytePickle$PU;
const #79 = Method	#7.#78;	//  scala/io/BytePickle$.ufixedList:(Lscala/io/BytePickle$PU;I)Lscala/io/BytePickle$PU;
const #80 = Asciz	<A:Ljava/lang/Object;>(Lscala/io/BytePickle$PU<TA;>;I)Lscala/io/BytePickle$PU<Lscala/collection/immutable/List<TA;>;>;;
const #81 = Asciz	bool;
const #82 = Asciz	()Lscala/io/BytePickle$SPU;;
const #83 = NameAndType	#81:#82;//  bool:()Lscala/io/BytePickle$SPU;
const #84 = Method	#7.#83;	//  scala/io/BytePickle$.bool:()Lscala/io/BytePickle$SPU;
const #85 = Asciz	()Lscala/io/BytePickle$SPU<Ljava/lang/Boolean;>;;
const #86 = Asciz	bytearray;
const #87 = NameAndType	#86:#82;//  bytearray:()Lscala/io/BytePickle$SPU;
const #88 = Method	#7.#87;	//  scala/io/BytePickle$.bytearray:()Lscala/io/BytePickle$SPU;
const #89 = Asciz	()Lscala/io/BytePickle$SPU<[B>;;
const #90 = Asciz	string;
const #91 = NameAndType	#90:#82;//  string:()Lscala/io/BytePickle$SPU;
const #92 = Method	#7.#91;	//  scala/io/BytePickle$.string:()Lscala/io/BytePickle$SPU;
const #93 = Asciz	()Lscala/io/BytePickle$SPU<Ljava/lang/String;>;;
const #94 = Asciz	byte;
const #95 = NameAndType	#94:#82;//  byte:()Lscala/io/BytePickle$SPU;
const #96 = Method	#7.#95;	//  scala/io/BytePickle$.byte:()Lscala/io/BytePickle$SPU;
const #97 = Asciz	()Lscala/io/BytePickle$SPU<Ljava/lang/Byte;>;;
const #98 = Asciz	nat;
const #99 = NameAndType	#98:#82;//  nat:()Lscala/io/BytePickle$SPU;
const #100 = Method	#7.#99;	//  scala/io/BytePickle$.nat:()Lscala/io/BytePickle$SPU;
const #101 = Asciz	()Lscala/io/BytePickle$SPU<Ljava/lang/Integer;>;;
const #102 = Asciz	nat2Bytes;
const #103 = Asciz	(I)[B;
const #104 = NameAndType	#102:#103;//  nat2Bytes:(I)[B
const #105 = Method	#7.#104;	//  scala/io/BytePickle$.nat2Bytes:(I)[B
const #106 = Asciz	appendByte;
const #107 = Asciz	([BI)[B;
const #108 = NameAndType	#106:#107;//  appendByte:([BI)[B
const #109 = Method	#7.#108;	//  scala/io/BytePickle$.appendByte:([BI)[B
const #110 = Asciz	wrap;
const #111 = Asciz	(Lscala/Function1;Lscala/Function1;Lscala/io/BytePickle$SPU;)Lscala/io/BytePickle$SPU;;
const #112 = NameAndType	#110:#111;//  wrap:(Lscala/Function1;Lscala/Function1;Lscala/io/BytePickle$SPU;)Lscala/io/BytePickle$SPU;
const #113 = Method	#7.#112;	//  scala/io/BytePickle$.wrap:(Lscala/Function1;Lscala/Function1;Lscala/io/BytePickle$SPU;)Lscala/io/BytePickle$SPU;
const #114 = Asciz	<a:Ljava/lang/Object;b:Ljava/lang/Object;>(Lscala/Function1<Ta;Tb;>;Lscala/Function1<Tb;Ta;>;Lscala/io/BytePickle$SPU<Ta;>;)Lscala/io/BytePickle$SPU<Tb;>;;
const #115 = Asciz	uwrap;
const #116 = Asciz	(Lscala/Function1;Lscala/Function1;Lscala/io/BytePickle$PU;)Lscala/io/BytePickle$PU;;
const #117 = NameAndType	#115:#116;//  uwrap:(Lscala/Function1;Lscala/Function1;Lscala/io/BytePickle$PU;)Lscala/io/BytePickle$PU;
const #118 = Method	#7.#117;	//  scala/io/BytePickle$.uwrap:(Lscala/Function1;Lscala/Function1;Lscala/io/BytePickle$PU;)Lscala/io/BytePickle$PU;
const #119 = Asciz	<a:Ljava/lang/Object;b:Ljava/lang/Object;>(Lscala/Function1<Ta;Tb;>;Lscala/Function1<Tb;Ta;>;Lscala/io/BytePickle$PU<Ta;>;)Lscala/io/BytePickle$PU<Tb;>;;
const #120 = Asciz	triple;
const #121 = Asciz	(Lscala/io/BytePickle$SPU;Lscala/io/BytePickle$SPU;Lscala/io/BytePickle$SPU;)Lscala/io/BytePickle$SPU;;
const #122 = NameAndType	#120:#121;//  triple:(Lscala/io/BytePickle$SPU;Lscala/io/BytePickle$SPU;Lscala/io/BytePickle$SPU;)Lscala/io/BytePickle$SPU;
const #123 = Method	#7.#122;	//  scala/io/BytePickle$.triple:(Lscala/io/BytePickle$SPU;Lscala/io/BytePickle$SPU;Lscala/io/BytePickle$SPU;)Lscala/io/BytePickle$SPU;
const #124 = Asciz	<a:Ljava/lang/Object;b:Ljava/lang/Object;c:Ljava/lang/Object;>(Lscala/io/BytePickle$SPU<Ta;>;Lscala/io/BytePickle$SPU<Tb;>;Lscala/io/BytePickle$SPU<Tc;>;)Lscala/io/BytePickle$SPU<Lscala/Tuple3<Ta;Tb;Tc;>;>;;
const #125 = Asciz	pair;
const #126 = Asciz	(Lscala/io/BytePickle$SPU;Lscala/io/BytePickle$SPU;)Lscala/io/BytePickle$SPU;;
const #127 = NameAndType	#125:#126;//  pair:(Lscala/io/BytePickle$SPU;Lscala/io/BytePickle$SPU;)Lscala/io/BytePickle$SPU;
const #128 = Method	#7.#127;	//  scala/io/BytePickle$.pair:(Lscala/io/BytePickle$SPU;Lscala/io/BytePickle$SPU;)Lscala/io/BytePickle$SPU;
const #129 = Asciz	<a:Ljava/lang/Object;b:Ljava/lang/Object;>(Lscala/io/BytePickle$SPU<Ta;>;Lscala/io/BytePickle$SPU<Tb;>;)Lscala/io/BytePickle$SPU<Lscala/Tuple2<Ta;Tb;>;>;;
const #130 = Asciz	upair;
const #131 = Asciz	(Lscala/io/BytePickle$PU;Lscala/io/BytePickle$PU;)Lscala/io/BytePickle$PU;;
const #132 = NameAndType	#130:#131;//  upair:(Lscala/io/BytePickle$PU;Lscala/io/BytePickle$PU;)Lscala/io/BytePickle$PU;
const #133 = Method	#7.#132;	//  scala/io/BytePickle$.upair:(Lscala/io/BytePickle$PU;Lscala/io/BytePickle$PU;)Lscala/io/BytePickle$PU;
const #134 = Asciz	<a:Ljava/lang/Object;b:Ljava/lang/Object;>(Lscala/io/BytePickle$PU<Ta;>;Lscala/io/BytePickle$PU<Tb;>;)Lscala/io/BytePickle$PU<Lscala/Tuple2<Ta;Tb;>;>;;
const #135 = Asciz	sequ;
const #136 = Asciz	(Lscala/Function1;Lscala/io/BytePickle$SPU;Lscala/Function1;)Lscala/io/BytePickle$SPU;;
const #137 = NameAndType	#135:#136;//  sequ:(Lscala/Function1;Lscala/io/BytePickle$SPU;Lscala/Function1;)Lscala/io/BytePickle$SPU;
const #138 = Method	#7.#137;	//  scala/io/BytePickle$.sequ:(Lscala/Function1;Lscala/io/BytePickle$SPU;Lscala/Function1;)Lscala/io/BytePickle$SPU;
const #139 = Asciz	<t:Ljava/lang/Object;u:Ljava/lang/Object;>(Lscala/Function1<Tu;Tt;>;Lscala/io/BytePickle$SPU<Tt;>;Lscala/Function1<Tt;Lscala/io/BytePickle$SPU<Tu;>;>;)Lscala/io/BytePickle$SPU<Tu;>;;
const #140 = Asciz	usequ;
const #141 = Asciz	(Lscala/Function1;Lscala/io/BytePickle$PU;Lscala/Function1;)Lscala/io/BytePickle$PU;;
const #142 = NameAndType	#140:#141;//  usequ:(Lscala/Function1;Lscala/io/BytePickle$PU;Lscala/Function1;)Lscala/io/BytePickle$PU;
const #143 = Method	#7.#142;	//  scala/io/BytePickle$.usequ:(Lscala/Function1;Lscala/io/BytePickle$PU;Lscala/Function1;)Lscala/io/BytePickle$PU;
const #144 = Asciz	<t:Ljava/lang/Object;u:Ljava/lang/Object;>(Lscala/Function1<Tu;Tt;>;Lscala/io/BytePickle$PU<Tt;>;Lscala/Function1<Tt;Lscala/io/BytePickle$PU<Tu;>;>;)Lscala/io/BytePickle$PU<Tu;>;;
const #145 = Asciz	lift;
const #146 = Asciz	(Ljava/lang/Object;)Lscala/io/BytePickle$SPU;;
const #147 = NameAndType	#145:#146;//  lift:(Ljava/lang/Object;)Lscala/io/BytePickle$SPU;
const #148 = Method	#7.#147;	//  scala/io/BytePickle$.lift:(Ljava/lang/Object;)Lscala/io/BytePickle$SPU;
const #149 = Asciz	<t:Ljava/lang/Object;>(Tt;)Lscala/io/BytePickle$SPU<Tt;>;;
const #150 = Asciz	ulift;
const #151 = Asciz	(Ljava/lang/Object;)Lscala/io/BytePickle$PU;;
const #152 = NameAndType	#150:#151;//  ulift:(Ljava/lang/Object;)Lscala/io/BytePickle$PU;
const #153 = Method	#7.#152;	//  scala/io/BytePickle$.ulift:(Ljava/lang/Object;)Lscala/io/BytePickle$PU;
const #154 = Asciz	<t:Ljava/lang/Object;>(Tt;)Lscala/io/BytePickle$PU<Tt;>;;
const #155 = Asciz	share;
const #156 = NameAndType	#155:#67;//  share:(Lscala/io/BytePickle$SPU;)Lscala/io/BytePickle$SPU;
const #157 = Method	#7.#156;	//  scala/io/BytePickle$.share:(Lscala/io/BytePickle$SPU;)Lscala/io/BytePickle$SPU;
const #158 = Asciz	<a:Ljava/lang/Object;>(Lscala/io/BytePickle$SPU<Ta;>;)Lscala/io/BytePickle$SPU<Ta;>;;
const #159 = Asciz	unat;
const #160 = Asciz	()Lscala/io/BytePickle$PU;;
const #161 = NameAndType	#159:#160;//  unat:()Lscala/io/BytePickle$PU;
const #162 = Method	#7.#161;	//  scala/io/BytePickle$.unat:()Lscala/io/BytePickle$PU;
const #163 = Asciz	()Lscala/io/BytePickle$PU<Ljava/lang/Integer;>;;
const #164 = Asciz	DEF;
const #165 = Asciz	()I;
const #166 = NameAndType	#164:#165;//  DEF:()I
const #167 = Method	#7.#166;	//  scala/io/BytePickle$.DEF:()I
const #168 = Asciz	REF;
const #169 = NameAndType	#168:#165;//  REF:()I
const #170 = Method	#7.#169;	//  scala/io/BytePickle$.REF:()I
const #171 = Asciz	refDef;
const #172 = NameAndType	#171:#160;//  refDef:()Lscala/io/BytePickle$PU;
const #173 = Method	#7.#172;	//  scala/io/BytePickle$.refDef:()Lscala/io/BytePickle$PU;
const #174 = Asciz	()Lscala/io/BytePickle$PU<Lscala/io/BytePickle$RefDef;>;;
const #175 = Asciz	uunpickle;
const #176 = Asciz	(Lscala/io/BytePickle$PU;[B)Ljava/lang/Object;;
const #177 = NameAndType	#175:#176;//  uunpickle:(Lscala/io/BytePickle$PU;[B)Ljava/lang/Object;
const #178 = Method	#7.#177;	//  scala/io/BytePickle$.uunpickle:(Lscala/io/BytePickle$PU;[B)Ljava/lang/Object;
const #179 = Asciz	<T:Ljava/lang/Object;>(Lscala/io/BytePickle$PU<TT;>;[B)TT;;
const #180 = Asciz	upickle;
const #181 = Asciz	(Lscala/io/BytePickle$PU;Ljava/lang/Object;)[B;
const #182 = NameAndType	#180:#181;//  upickle:(Lscala/io/BytePickle$PU;Ljava/lang/Object;)[B
const #183 = Method	#7.#182;	//  scala/io/BytePickle$.upickle:(Lscala/io/BytePickle$PU;Ljava/lang/Object;)[B
const #184 = Asciz	<T:Ljava/lang/Object;>(Lscala/io/BytePickle$PU<TT;>;TT;)[B;
const #185 = Asciz	unpickle;
const #186 = Asciz	(Lscala/io/BytePickle$SPU;[B)Ljava/lang/Object;;
const #187 = NameAndType	#185:#186;//  unpickle:(Lscala/io/BytePickle$SPU;[B)Ljava/lang/Object;
const #188 = Method	#7.#187;	//  scala/io/BytePickle$.unpickle:(Lscala/io/BytePickle$SPU;[B)Ljava/lang/Object;
const #189 = Asciz	<T:Ljava/lang/Object;>(Lscala/io/BytePickle$SPU<TT;>;[B)TT;;
const #190 = Asciz	pickle;
const #191 = Asciz	(Lscala/io/BytePickle$SPU;Ljava/lang/Object;)[B;
const #192 = NameAndType	#190:#191;//  pickle:(Lscala/io/BytePickle$SPU;Ljava/lang/Object;)[B
const #193 = Method	#7.#192;	//  scala/io/BytePickle$.pickle:(Lscala/io/BytePickle$SPU;Ljava/lang/Object;)[B
const #194 = Asciz	<T:Ljava/lang/Object;>(Lscala/io/BytePickle$SPU<TT;>;TT;)[B;
const #195 = Asciz	ScalaSig;
const #196 = Asciz	InnerClasses;
const #197 = Asciz	scala/io/BytePickle$PU;
const #198 = class	#197;	//  scala/io/BytePickle$PU
const #199 = Asciz	scala/io/BytePickle;
const #200 = class	#199;	//  scala/io/BytePickle
const #201 = Asciz	PU;
const #202 = Asciz	scala/io/BytePickle$Def;
const #203 = class	#202;	//  scala/io/BytePickle$Def
const #204 = Asciz	Def;
const #205 = Asciz	scala/io/BytePickle$Ref;
const #206 = class	#205;	//  scala/io/BytePickle$Ref
const #207 = Asciz	Ref;
const #208 = Asciz	scala/io/BytePickle$SPU;
const #209 = class	#208;	//  scala/io/BytePickle$SPU
const #210 = Asciz	SPU;
const #211 = Asciz	scala/io/BytePickle$RefDef;
const #212 = class	#211;	//  scala/io/BytePickle$RefDef
const #213 = Asciz	RefDef;
const #214 = Asciz	scala/io/BytePickle$$anon$9;
const #215 = class	#214;	//  scala/io/BytePickle$$anon$9
const #216 = Asciz	$anon$9;
const #217 = Asciz	scala/io/BytePickle$$anon$8;
const #218 = class	#217;	//  scala/io/BytePickle$$anon$8
const #219 = Asciz	$anon$8;
const #220 = Asciz	scala/io/BytePickle$$anon$7;
const #221 = class	#220;	//  scala/io/BytePickle$$anon$7
const #222 = Asciz	$anon$7;
const #223 = Asciz	scala/io/BytePickle$$anon$6;
const #224 = class	#223;	//  scala/io/BytePickle$$anon$6
const #225 = Asciz	$anon$6;
const #226 = Asciz	scala/io/BytePickle$$anon$5;
const #227 = class	#226;	//  scala/io/BytePickle$$anon$5
const #228 = Asciz	$anon$5;
const #229 = Asciz	scala/io/BytePickle$$anon$4;
const #230 = class	#229;	//  scala/io/BytePickle$$anon$4
const #231 = Asciz	$anon$4;
const #232 = Asciz	scala/io/BytePickle$$anon$3;
const #233 = class	#232;	//  scala/io/BytePickle$$anon$3
const #234 = Asciz	$anon$3;
const #235 = Asciz	scala/io/BytePickle$$anon$2;
const #236 = class	#235;	//  scala/io/BytePickle$$anon$2
const #237 = Asciz	$anon$2;
const #238 = Asciz	scala/io/BytePickle$$anon$1;
const #239 = class	#238;	//  scala/io/BytePickle$$anon$1
const #240 = Asciz	$anon$1;
const #241 = Asciz	scala/io/BytePickle$PicklerEnv;
const #242 = class	#241;	//  scala/io/BytePickle$PicklerEnv
const #243 = Asciz	PicklerEnv;
const #244 = Asciz	scala/io/BytePickle$PicklerState;
const #245 = class	#244;	//  scala/io/BytePickle$PicklerState
const #246 = Asciz	PicklerState;
const #247 = Asciz	scala/io/BytePickle$UnPicklerEnv;
const #248 = class	#247;	//  scala/io/BytePickle$UnPicklerEnv
const #249 = Asciz	UnPicklerEnv;
const #250 = Asciz	scala/io/BytePickle$UnPicklerState;
const #251 = class	#250;	//  scala/io/BytePickle$UnPicklerState
const #252 = Asciz	UnPicklerState;
const #253 = Asciz	scala/io/BytePickle$$anonfun$data$1;
const #254 = class	#253;	//  scala/io/BytePickle$$anonfun$data$1
const #255 = Asciz	$anonfun$data$1;
const #256 = Asciz	scala/io/BytePickle$$anonfun$list$2;
const #257 = class	#256;	//  scala/io/BytePickle$$anonfun$list$2
const #258 = Asciz	$anonfun$list$2;
const #259 = Asciz	scala/io/BytePickle$$anonfun$list$1;
const #260 = class	#259;	//  scala/io/BytePickle$$anonfun$list$1
const #261 = Asciz	$anonfun$list$1;
const #262 = Asciz	scala/io/BytePickle$$anonfun$bool$2;
const #263 = class	#262;	//  scala/io/BytePickle$$anonfun$bool$2
const #264 = Asciz	$anonfun$bool$2;
const #265 = Asciz	scala/io/BytePickle$$anonfun$bool$1;
const #266 = class	#265;	//  scala/io/BytePickle$$anonfun$bool$1
const #267 = Asciz	$anonfun$bool$1;
const #268 = Asciz	scala/io/BytePickle$$anonfun$wrap$1;
const #269 = class	#268;	//  scala/io/BytePickle$$anonfun$wrap$1
const #270 = Asciz	$anonfun$wrap$1;
const #271 = Asciz	scala/io/BytePickle$$anonfun$pair$2;
const #272 = class	#271;	//  scala/io/BytePickle$$anonfun$pair$2
const #273 = Asciz	$anonfun$pair$2;
const #274 = Asciz	scala/io/BytePickle$$anonfun$pair$1;
const #275 = class	#274;	//  scala/io/BytePickle$$anonfun$pair$1
const #276 = Asciz	$anonfun$pair$1;
const #277 = Asciz	scala/io/BytePickle$$anonfun$ulist$2;
const #278 = class	#277;	//  scala/io/BytePickle$$anonfun$ulist$2
const #279 = Asciz	$anonfun$ulist$2;
const #280 = Asciz	scala/io/BytePickle$$anonfun$ulist$1;
const #281 = class	#280;	//  scala/io/BytePickle$$anonfun$ulist$1
const #282 = Asciz	$anonfun$ulist$1;
const #283 = Asciz	scala/io/BytePickle$$anonfun$uwrap$1;
const #284 = class	#283;	//  scala/io/BytePickle$$anonfun$uwrap$1
const #285 = Asciz	$anonfun$uwrap$1;
const #286 = Asciz	scala/io/BytePickle$$anonfun$upair$2;
const #287 = class	#286;	//  scala/io/BytePickle$$anonfun$upair$2
const #288 = Asciz	$anonfun$upair$2;
const #289 = Asciz	scala/io/BytePickle$$anonfun$upair$1;
const #290 = class	#289;	//  scala/io/BytePickle$$anonfun$upair$1
const #291 = Asciz	$anonfun$upair$1;
const #292 = Asciz	scala/io/BytePickle$$anonfun$string$2;
const #293 = class	#292;	//  scala/io/BytePickle$$anonfun$string$2
const #294 = Asciz	$anonfun$string$2;
const #295 = Asciz	scala/io/BytePickle$$anonfun$string$1;
const #296 = class	#295;	//  scala/io/BytePickle$$anonfun$string$1
const #297 = Asciz	$anonfun$string$1;
const #298 = Asciz	scala/io/BytePickle$$anonfun$triple$2;
const #299 = class	#298;	//  scala/io/BytePickle$$anonfun$triple$2
const #300 = Asciz	$anonfun$triple$2;
const #301 = Asciz	scala/io/BytePickle$$anonfun$triple$1;
const #302 = class	#301;	//  scala/io/BytePickle$$anonfun$triple$1
const #303 = Asciz	$anonfun$triple$1;
const #304 = Asciz	scala/io/BytePickle$$anonfun$fixedList$2;
const #305 = class	#304;	//  scala/io/BytePickle$$anonfun$fixedList$2
const #306 = Asciz	$anonfun$fixedList$2;
const #307 = Asciz	scala/io/BytePickle$$anonfun$fixedList$1;
const #308 = class	#307;	//  scala/io/BytePickle$$anonfun$fixedList$1
const #309 = Asciz	$anonfun$fixedList$1;
const #310 = Asciz	scala/io/BytePickle$$anonfun$bytearray$2;
const #311 = class	#310;	//  scala/io/BytePickle$$anonfun$bytearray$2
const #312 = Asciz	$anonfun$bytearray$2;
const #313 = Asciz	scala/io/BytePickle$$anonfun$bytearray$1;
const #314 = class	#313;	//  scala/io/BytePickle$$anonfun$bytearray$1
const #315 = Asciz	$anonfun$bytearray$1;
const #316 = Asciz	scala/io/BytePickle$$anonfun$ufixedList$2;
const #317 = class	#316;	//  scala/io/BytePickle$$anonfun$ufixedList$2
const #318 = Asciz	$anonfun$ufixedList$2;
const #319 = Asciz	scala/io/BytePickle$$anonfun$ufixedList$1;
const #320 = class	#319;	//  scala/io/BytePickle$$anonfun$ufixedList$1
const #321 = Asciz	$anonfun$ufixedList$1;
const #322 = Asciz	java/lang/Object;
const #323 = class	#322;	//  java/lang/Object

{
public static final scala.Tuple2 listToPair$2(scala.collection.immutable.List);
  Code:
   Stack=2, Locals=1, Args_size=1
   0:	getstatic	#11; //Field scala/io/BytePickle$.MODULE$:Lscala/io/BytePickle$;
   3:	aload_0
   4:	invokevirtual	#13; //Method scala/io/BytePickle$.listToPair$2:(Lscala/collection/immutable/List;)Lscala/Tuple2;
   7:	areturn

public static final scala.collection.immutable.List pairToList$2(scala.Tuple2);
  Code:
   Stack=2, Locals=1, Args_size=1
   0:	getstatic	#11; //Field scala/io/BytePickle$.MODULE$:Lscala/io/BytePickle$;
   3:	aload_0
   4:	invokevirtual	#17; //Method scala/io/BytePickle$.pairToList$2:(Lscala/Tuple2;)Lscala/collection/immutable/List;
   7:	areturn

public static final scala.Tuple2 listToPair$1(scala.collection.immutable.List);
  Code:
   Stack=2, Locals=1, Args_size=1
   0:	getstatic	#11; //Field scala/io/BytePickle$.MODULE$:Lscala/io/BytePickle$;
   3:	aload_0
   4:	invokevirtual	#20; //Method scala/io/BytePickle$.listToPair$1:(Lscala/collection/immutable/List;)Lscala/Tuple2;
   7:	areturn

public static final scala.collection.immutable.List pairToList$1(scala.Tuple2);
  Code:
   Stack=2, Locals=1, Args_size=1
   0:	getstatic	#11; //Field scala/io/BytePickle$.MODULE$:Lscala/io/BytePickle$;
   3:	aload_0
   4:	invokevirtual	#23; //Method scala/io/BytePickle$.pairToList$1:(Lscala/Tuple2;)Lscala/collection/immutable/List;
   7:	areturn

public static final boolean fromEnum$1(int);
  Code:
   Stack=2, Locals=1, Args_size=1
   0:	getstatic	#11; //Field scala/io/BytePickle$.MODULE$:Lscala/io/BytePickle$;
   3:	iload_0
   4:	invokevirtual	#27; //Method scala/io/BytePickle$.fromEnum$1:(I)Z
   7:	ireturn

public static final int toEnum$1(boolean);
  Code:
   Stack=2, Locals=1, Args_size=1
   0:	getstatic	#11; //Field scala/io/BytePickle$.MODULE$:Lscala/io/BytePickle$;
   3:	iload_0
   4:	invokevirtual	#31; //Method scala/io/BytePickle$.toEnum$1:(Z)I
   7:	ireturn

public static final java.lang.Object trd$1(scala.Tuple3);
  Code:
   Stack=2, Locals=1, Args_size=1
   0:	getstatic	#11; //Field scala/io/BytePickle$.MODULE$:Lscala/io/BytePickle$;
   3:	aload_0
   4:	invokevirtual	#35; //Method scala/io/BytePickle$.trd$1:(Lscala/Tuple3;)Ljava/lang/Object;
   7:	areturn

public static final java.lang.Object snd$3(scala.Tuple3);
  Code:
   Stack=2, Locals=1, Args_size=1
   0:	getstatic	#11; //Field scala/io/BytePickle$.MODULE$:Lscala/io/BytePickle$;
   3:	aload_0
   4:	invokevirtual	#38; //Method scala/io/BytePickle$.snd$3:(Lscala/Tuple3;)Ljava/lang/Object;
   7:	areturn

public static final java.lang.Object fst$3(scala.Tuple3);
  Code:
   Stack=2, Locals=1, Args_size=1
   0:	getstatic	#11; //Field scala/io/BytePickle$.MODULE$:Lscala/io/BytePickle$;
   3:	aload_0
   4:	invokevirtual	#41; //Method scala/io/BytePickle$.fst$3:(Lscala/Tuple3;)Ljava/lang/Object;
   7:	areturn

public static final java.lang.Object snd$2(scala.Tuple2);
  Code:
   Stack=2, Locals=1, Args_size=1
   0:	getstatic	#11; //Field scala/io/BytePickle$.MODULE$:Lscala/io/BytePickle$;
   3:	aload_0
   4:	invokevirtual	#45; //Method scala/io/BytePickle$.snd$2:(Lscala/Tuple2;)Ljava/lang/Object;
   7:	areturn

public static final java.lang.Object fst$2(scala.Tuple2);
  Code:
   Stack=2, Locals=1, Args_size=1
   0:	getstatic	#11; //Field scala/io/BytePickle$.MODULE$:Lscala/io/BytePickle$;
   3:	aload_0
   4:	invokevirtual	#48; //Method scala/io/BytePickle$.fst$2:(Lscala/Tuple2;)Ljava/lang/Object;
   7:	areturn

public static final java.lang.Object snd$1(scala.Tuple2);
  Code:
   Stack=2, Locals=1, Args_size=1
   0:	getstatic	#11; //Field scala/io/BytePickle$.MODULE$:Lscala/io/BytePickle$;
   3:	aload_0
   4:	invokevirtual	#51; //Method scala/io/BytePickle$.snd$1:(Lscala/Tuple2;)Ljava/lang/Object;
   7:	areturn

public static final java.lang.Object fst$1(scala.Tuple2);
  Code:
   Stack=2, Locals=1, Args_size=1
   0:	getstatic	#11; //Field scala/io/BytePickle$.MODULE$:Lscala/io/BytePickle$;
   3:	aload_0
   4:	invokevirtual	#54; //Method scala/io/BytePickle$.fst$1:(Lscala/Tuple2;)Ljava/lang/Object;
   7:	areturn

public static final scala.io.BytePickle$SPU data(scala.Function1, scala.collection.immutable.List);
  Code:
   Stack=3, Locals=2, Args_size=2
   0:	getstatic	#11; //Field scala/io/BytePickle$.MODULE$:Lscala/io/BytePickle$;
   3:	aload_0
   4:	aload_1
   5:	invokevirtual	#58; //Method scala/io/BytePickle$.data:(Lscala/Function1;Lscala/collection/immutable/List;)Lscala/io/BytePickle$SPU;
   8:	areturn
  Signature: length = 0x2
   00 3B 

public static final scala.io.BytePickle$PU ulist(scala.io.BytePickle$PU);
  Code:
   Stack=2, Locals=1, Args_size=1
   0:	getstatic	#11; //Field scala/io/BytePickle$.MODULE$:Lscala/io/BytePickle$;
   3:	aload_0
   4:	invokevirtual	#64; //Method scala/io/BytePickle$.ulist:(Lscala/io/BytePickle$PU;)Lscala/io/BytePickle$PU;
   7:	areturn
  Signature: length = 0x2
   00 41 

public static final scala.io.BytePickle$SPU list(scala.io.BytePickle$SPU);
  Code:
   Stack=2, Locals=1, Args_size=1
   0:	getstatic	#11; //Field scala/io/BytePickle$.MODULE$:Lscala/io/BytePickle$;
   3:	aload_0
   4:	invokevirtual	#69; //Method scala/io/BytePickle$.list:(Lscala/io/BytePickle$SPU;)Lscala/io/BytePickle$SPU;
   7:	areturn
  Signature: length = 0x2
   00 46 

public static final scala.io.BytePickle$SPU fixedList(scala.io.BytePickle$SPU, int);
  Code:
   Stack=3, Locals=2, Args_size=2
   0:	getstatic	#11; //Field scala/io/BytePickle$.MODULE$:Lscala/io/BytePickle$;
   3:	aload_0
   4:	iload_1
   5:	invokevirtual	#74; //Method scala/io/BytePickle$.fixedList:(Lscala/io/BytePickle$SPU;I)Lscala/io/BytePickle$SPU;
   8:	areturn
  Signature: length = 0x2
   00 4B 

public static final scala.io.BytePickle$PU ufixedList(scala.io.BytePickle$PU, int);
  Code:
   Stack=3, Locals=2, Args_size=2
   0:	getstatic	#11; //Field scala/io/BytePickle$.MODULE$:Lscala/io/BytePickle$;
   3:	aload_0
   4:	iload_1
   5:	invokevirtual	#79; //Method scala/io/BytePickle$.ufixedList:(Lscala/io/BytePickle$PU;I)Lscala/io/BytePickle$PU;
   8:	areturn
  Signature: length = 0x2
   00 50 

public static final scala.io.BytePickle$SPU bool();
  Code:
   Stack=1, Locals=0, Args_size=0
   0:	getstatic	#11; //Field scala/io/BytePickle$.MODULE$:Lscala/io/BytePickle$;
   3:	invokevirtual	#84; //Method scala/io/BytePickle$.bool:()Lscala/io/BytePickle$SPU;
   6:	areturn
  Signature: length = 0x2
   00 55 

public static final scala.io.BytePickle$SPU bytearray();
  Code:
   Stack=1, Locals=0, Args_size=0
   0:	getstatic	#11; //Field scala/io/BytePickle$.MODULE$:Lscala/io/BytePickle$;
   3:	invokevirtual	#88; //Method scala/io/BytePickle$.bytearray:()Lscala/io/BytePickle$SPU;
   6:	areturn
  Signature: length = 0x2
   00 59 

public static final scala.io.BytePickle$SPU string();
  Code:
   Stack=1, Locals=0, Args_size=0
   0:	getstatic	#11; //Field scala/io/BytePickle$.MODULE$:Lscala/io/BytePickle$;
   3:	invokevirtual	#92; //Method scala/io/BytePickle$.string:()Lscala/io/BytePickle$SPU;
   6:	areturn
  Signature: length = 0x2
   00 5D 

public static final scala.io.BytePickle$SPU byte();
  Code:
   Stack=1, Locals=0, Args_size=0
   0:	getstatic	#11; //Field scala/io/BytePickle$.MODULE$:Lscala/io/BytePickle$;
   3:	invokevirtual	#96; //Method scala/io/BytePickle$.byte:()Lscala/io/BytePickle$SPU;
   6:	areturn
  Signature: length = 0x2
   00 61 

public static final scala.io.BytePickle$SPU nat();
  Code:
   Stack=1, Locals=0, Args_size=0
   0:	getstatic	#11; //Field scala/io/BytePickle$.MODULE$:Lscala/io/BytePickle$;
   3:	invokevirtual	#100; //Method scala/io/BytePickle$.nat:()Lscala/io/BytePickle$SPU;
   6:	areturn
  Signature: length = 0x2
   00 65 

public static final byte[] nat2Bytes(int);
  Code:
   Stack=2, Locals=1, Args_size=1
   0:	getstatic	#11; //Field scala/io/BytePickle$.MODULE$:Lscala/io/BytePickle$;
   3:	iload_0
   4:	invokevirtual	#105; //Method scala/io/BytePickle$.nat2Bytes:(I)[B
   7:	areturn

public static final byte[] appendByte(byte[], int);
  Code:
   Stack=3, Locals=2, Args_size=2
   0:	getstatic	#11; //Field scala/io/BytePickle$.MODULE$:Lscala/io/BytePickle$;
   3:	aload_0
   4:	iload_1
   5:	invokevirtual	#109; //Method scala/io/BytePickle$.appendByte:([BI)[B
   8:	areturn

public static final scala.io.BytePickle$SPU wrap(scala.Function1, scala.Function1, scala.io.BytePickle$SPU);
  Code:
   Stack=4, Locals=3, Args_size=3
   0:	getstatic	#11; //Field scala/io/BytePickle$.MODULE$:Lscala/io/BytePickle$;
   3:	aload_0
   4:	aload_1
   5:	aload_2
   6:	invokevirtual	#113; //Method scala/io/BytePickle$.wrap:(Lscala/Function1;Lscala/Function1;Lscala/io/BytePickle$SPU;)Lscala/io/BytePickle$SPU;
   9:	areturn
  Signature: length = 0x2
   00 72 

public static final scala.io.BytePickle$PU uwrap(scala.Function1, scala.Function1, scala.io.BytePickle$PU);
  Code:
   Stack=4, Locals=3, Args_size=3
   0:	getstatic	#11; //Field scala/io/BytePickle$.MODULE$:Lscala/io/BytePickle$;
   3:	aload_0
   4:	aload_1
   5:	aload_2
   6:	invokevirtual	#118; //Method scala/io/BytePickle$.uwrap:(Lscala/Function1;Lscala/Function1;Lscala/io/BytePickle$PU;)Lscala/io/BytePickle$PU;
   9:	areturn
  Signature: length = 0x2
   00 77 

public static final scala.io.BytePickle$SPU triple(scala.io.BytePickle$SPU, scala.io.BytePickle$SPU, scala.io.BytePickle$SPU);
  Code:
   Stack=4, Locals=3, Args_size=3
   0:	getstatic	#11; //Field scala/io/BytePickle$.MODULE$:Lscala/io/BytePickle$;
   3:	aload_0
   4:	aload_1
   5:	aload_2
   6:	invokevirtual	#123; //Method scala/io/BytePickle$.triple:(Lscala/io/BytePickle$SPU;Lscala/io/BytePickle$SPU;Lscala/io/BytePickle$SPU;)Lscala/io/BytePickle$SPU;
   9:	areturn
  Signature: length = 0x2
   00 7C 

public static final scala.io.BytePickle$SPU pair(scala.io.BytePickle$SPU, scala.io.BytePickle$SPU);
  Code:
   Stack=3, Locals=2, Args_size=2
   0:	getstatic	#11; //Field scala/io/BytePickle$.MODULE$:Lscala/io/BytePickle$;
   3:	aload_0
   4:	aload_1
   5:	invokevirtual	#128; //Method scala/io/BytePickle$.pair:(Lscala/io/BytePickle$SPU;Lscala/io/BytePickle$SPU;)Lscala/io/BytePickle$SPU;
   8:	areturn
  Signature: length = 0x2
   00 FFFFFF81 

public static final scala.io.BytePickle$PU upair(scala.io.BytePickle$PU, scala.io.BytePickle$PU);
  Code:
   Stack=3, Locals=2, Args_size=2
   0:	getstatic	#11; //Field scala/io/BytePickle$.MODULE$:Lscala/io/BytePickle$;
   3:	aload_0
   4:	aload_1
   5:	invokevirtual	#133; //Method scala/io/BytePickle$.upair:(Lscala/io/BytePickle$PU;Lscala/io/BytePickle$PU;)Lscala/io/BytePickle$PU;
   8:	areturn
  Signature: length = 0x2
   00 FFFFFF86 

public static final scala.io.BytePickle$SPU sequ(scala.Function1, scala.io.BytePickle$SPU, scala.Function1);
  Code:
   Stack=4, Locals=3, Args_size=3
   0:	getstatic	#11; //Field scala/io/BytePickle$.MODULE$:Lscala/io/BytePickle$;
   3:	aload_0
   4:	aload_1
   5:	aload_2
   6:	invokevirtual	#138; //Method scala/io/BytePickle$.sequ:(Lscala/Function1;Lscala/io/BytePickle$SPU;Lscala/Function1;)Lscala/io/BytePickle$SPU;
   9:	areturn
  Signature: length = 0x2
   00 FFFFFF8B 

public static final scala.io.BytePickle$PU usequ(scala.Function1, scala.io.BytePickle$PU, scala.Function1);
  Code:
   Stack=4, Locals=3, Args_size=3
   0:	getstatic	#11; //Field scala/io/BytePickle$.MODULE$:Lscala/io/BytePickle$;
   3:	aload_0
   4:	aload_1
   5:	aload_2
   6:	invokevirtual	#143; //Method scala/io/BytePickle$.usequ:(Lscala/Function1;Lscala/io/BytePickle$PU;Lscala/Function1;)Lscala/io/BytePickle$PU;
   9:	areturn
  Signature: length = 0x2
   00 FFFFFF90 

public static final scala.io.BytePickle$SPU lift(java.lang.Object);
  Code:
   Stack=2, Locals=1, Args_size=1
   0:	getstatic	#11; //Field scala/io/BytePickle$.MODULE$:Lscala/io/BytePickle$;
   3:	aload_0
   4:	invokevirtual	#148; //Method scala/io/BytePickle$.lift:(Ljava/lang/Object;)Lscala/io/BytePickle$SPU;
   7:	areturn
  Signature: length = 0x2
   00 FFFFFF95 

public static final scala.io.BytePickle$PU ulift(java.lang.Object);
  Code:
   Stack=2, Locals=1, Args_size=1
   0:	getstatic	#11; //Field scala/io/BytePickle$.MODULE$:Lscala/io/BytePickle$;
   3:	aload_0
   4:	invokevirtual	#153; //Method scala/io/BytePickle$.ulift:(Ljava/lang/Object;)Lscala/io/BytePickle$PU;
   7:	areturn
  Signature: length = 0x2
   00 FFFFFF9A 

public static final scala.io.BytePickle$SPU share(scala.io.BytePickle$SPU);
  Code:
   Stack=2, Locals=1, Args_size=1
   0:	getstatic	#11; //Field scala/io/BytePickle$.MODULE$:Lscala/io/BytePickle$;
   3:	aload_0
   4:	invokevirtual	#157; //Method scala/io/BytePickle$.share:(Lscala/io/BytePickle$SPU;)Lscala/io/BytePickle$SPU;
   7:	areturn
  Signature: length = 0x2
   00 FFFFFF9E 

public static final scala.io.BytePickle$PU unat();
  Code:
   Stack=1, Locals=0, Args_size=0
   0:	getstatic	#11; //Field scala/io/BytePickle$.MODULE$:Lscala/io/BytePickle$;
   3:	invokevirtual	#162; //Method scala/io/BytePickle$.unat:()Lscala/io/BytePickle$PU;
   6:	areturn
  Signature: length = 0x2
   00 FFFFFFA3 

public static final int DEF();
  Code:
   Stack=1, Locals=0, Args_size=0
   0:	getstatic	#11; //Field scala/io/BytePickle$.MODULE$:Lscala/io/BytePickle$;
   3:	invokevirtual	#167; //Method scala/io/BytePickle$.DEF:()I
   6:	ireturn

public static final int REF();
  Code:
   Stack=1, Locals=0, Args_size=0
   0:	getstatic	#11; //Field scala/io/BytePickle$.MODULE$:Lscala/io/BytePickle$;
   3:	invokevirtual	#170; //Method scala/io/BytePickle$.REF:()I
   6:	ireturn

public static final scala.io.BytePickle$PU refDef();
  Code:
   Stack=1, Locals=0, Args_size=0
   0:	getstatic	#11; //Field scala/io/BytePickle$.MODULE$:Lscala/io/BytePickle$;
   3:	invokevirtual	#173; //Method scala/io/BytePickle$.refDef:()Lscala/io/BytePickle$PU;
   6:	areturn
  Signature: length = 0x2
   00 FFFFFFAE 

public static final java.lang.Object uunpickle(scala.io.BytePickle$PU, byte[]);
  Code:
   Stack=3, Locals=2, Args_size=2
   0:	getstatic	#11; //Field scala/io/BytePickle$.MODULE$:Lscala/io/BytePickle$;
   3:	aload_0
   4:	aload_1
   5:	invokevirtual	#178; //Method scala/io/BytePickle$.uunpickle:(Lscala/io/BytePickle$PU;[B)Ljava/lang/Object;
   8:	areturn
  Signature: length = 0x2
   00 FFFFFFB3 

public static final byte[] upickle(scala.io.BytePickle$PU, java.lang.Object);
  Code:
   Stack=3, Locals=2, Args_size=2
   0:	getstatic	#11; //Field scala/io/BytePickle$.MODULE$:Lscala/io/BytePickle$;
   3:	aload_0
   4:	aload_1
   5:	invokevirtual	#183; //Method scala/io/BytePickle$.upickle:(Lscala/io/BytePickle$PU;Ljava/lang/Object;)[B
   8:	areturn
  Signature: length = 0x2
   00 FFFFFFB8 

public static final java.lang.Object unpickle(scala.io.BytePickle$SPU, byte[]);
  Code:
   Stack=3, Locals=2, Args_size=2
   0:	getstatic	#11; //Field scala/io/BytePickle$.MODULE$:Lscala/io/BytePickle$;
   3:	aload_0
   4:	aload_1
   5:	invokevirtual	#188; //Method scala/io/BytePickle$.unpickle:(Lscala/io/BytePickle$SPU;[B)Ljava/lang/Object;
   8:	areturn
  Signature: length = 0x2
   00 FFFFFFBD 

public static final byte[] pickle(scala.io.BytePickle$SPU, java.lang.Object);
  Code:
   Stack=3, Locals=2, Args_size=2
   0:	getstatic	#11; //Field scala/io/BytePickle$.MODULE$:Lscala/io/BytePickle$;
   3:	aload_0
   4:	aload_1
   5:	invokevirtual	#193; //Method scala/io/BytePickle$.pickle:(Lscala/io/BytePickle$SPU;Ljava/lang/Object;)[B
   8:	areturn
  Signature: length = 0x2
   00 FFFFFFC2 

}

