Compiled from "BytePickle.scala"
public final class scala.io.BytePickle$$anon$7 extends scala.io.BytePickle$SPU
  SourceFile: "BytePickle.scala"
  Signature: length = 0x2
   00 42 
  Scala: length = 0x
   
  InnerClass: 
   public abstract #71= #21 of #70; //SPU=class scala/io/BytePickle$SPU of class scala/io/BytePickle
   public final #72= #13 of #70; //$anon$7=class scala/io/BytePickle$$anon$7 of class scala/io/BytePickle
   public #75= #74 of #70; //PicklerState=class scala/io/BytePickle$PicklerState of class scala/io/BytePickle
   public #76= #39 of #70; //UnPicklerState=class scala/io/BytePickle$UnPicklerState of class scala/io/BytePickle
  minor version: 0
  major version: 49
  Constant pool:
const #1 = Asciz	SourceFile;
const #2 = Asciz	BytePickle.scala;
const #3 = Asciz	k$2;
const #4 = Asciz	Lscala/Function1;;
const #5 = Asciz	pa$3;
const #6 = Asciz	Lscala/io/BytePickle$SPU;;
const #7 = Asciz	f$2;
const #8 = Asciz	<init>;
const #9 = Asciz	(Lscala/Function1;Lscala/io/BytePickle$SPU;Lscala/Function1;)V;
const #10 = Asciz	Code;
const #11 = Asciz	LineNumberTable;
const #12 = Asciz	scala/io/BytePickle$$anon$7;
const #13 = class	#12;	//  scala/io/BytePickle$$anon$7
const #14 = NameAndType	#7:#4;//  f$2:Lscala/Function1;
const #15 = Field	#13.#14;	//  scala/io/BytePickle$$anon$7.f$2:Lscala/Function1;
const #16 = NameAndType	#5:#6;//  pa$3:Lscala/io/BytePickle$SPU;
const #17 = Field	#13.#16;	//  scala/io/BytePickle$$anon$7.pa$3:Lscala/io/BytePickle$SPU;
const #18 = NameAndType	#3:#4;//  k$2:Lscala/Function1;
const #19 = Field	#13.#18;	//  scala/io/BytePickle$$anon$7.k$2:Lscala/Function1;
const #20 = Asciz	scala/io/BytePickle$SPU;
const #21 = class	#20;	//  scala/io/BytePickle$SPU
const #22 = Asciz	()V;
const #23 = NameAndType	#8:#22;//  "<init>":()V
const #24 = Method	#21.#23;	//  scala/io/BytePickle$SPU."<init>":()V
const #25 = Asciz	appU;
const #26 = Asciz	(Lscala/io/BytePickle$UnPicklerState;)Lscala/Tuple2;;
const #27 = NameAndType	#25:#26;//  appU:(Lscala/io/BytePickle$UnPicklerState;)Lscala/Tuple2;
const #28 = Method	#21.#27;	//  scala/io/BytePickle$SPU.appU:(Lscala/io/BytePickle$UnPicklerState;)Lscala/Tuple2;
const #29 = Asciz	scala/Tuple2;
const #30 = class	#29;	//  scala/Tuple2
const #31 = Asciz	_1;
const #32 = Asciz	()Ljava/lang/Object;;
const #33 = NameAndType	#31:#32;//  _1:()Ljava/lang/Object;
const #34 = Method	#30.#33;	//  scala/Tuple2._1:()Ljava/lang/Object;
const #35 = Asciz	_2;
const #36 = NameAndType	#35:#32;//  _2:()Ljava/lang/Object;
const #37 = Method	#30.#36;	//  scala/Tuple2._2:()Ljava/lang/Object;
const #38 = Asciz	scala/io/BytePickle$UnPicklerState;
const #39 = class	#38;	//  scala/io/BytePickle$UnPicklerState
const #40 = Asciz	scala/Function1;
const #41 = class	#40;	//  scala/Function1
const #42 = Asciz	apply;
const #43 = Asciz	(Ljava/lang/Object;)Ljava/lang/Object;;
const #44 = NameAndType	#42:#43;//  apply:(Ljava/lang/Object;)Ljava/lang/Object;
const #45 = InterfaceMethod	#41.#44;	//  scala/Function1.apply:(Ljava/lang/Object;)Ljava/lang/Object;
const #46 = Asciz	this;
const #47 = Asciz	Lscala/io/BytePickle$$anon$7;;
const #48 = Asciz	s;
const #49 = Asciz	Lscala/io/BytePickle$UnPicklerState;;
const #50 = Asciz	resPa;
const #51 = Asciz	Lscala/Tuple2;;
const #52 = Asciz	a;
const #53 = Asciz	Ljava/lang/Object;;
const #54 = Asciz	sPrime;
const #55 = Asciz	pb;
const #56 = Asciz	LocalVariableTable;
const #57 = Asciz	(Lscala/io/BytePickle$UnPicklerState;)Lscala/Tuple2<Tu;Lscala/io/BytePickle$UnPicklerState;>;;
const #58 = Asciz	Signature;
const #59 = Asciz	appP;
const #60 = Asciz	(Ljava/lang/Object;Lscala/io/BytePickle$PicklerState;)Lscala/io/BytePickle$PicklerState;;
const #61 = NameAndType	#59:#60;//  appP:(Ljava/lang/Object;Lscala/io/BytePickle$PicklerState;)Lscala/io/BytePickle$PicklerState;
const #62 = Method	#21.#61;	//  scala/io/BytePickle$SPU.appP:(Ljava/lang/Object;Lscala/io/BytePickle$PicklerState;)Lscala/io/BytePickle$PicklerState;
const #63 = Asciz	b;
const #64 = Asciz	Lscala/io/BytePickle$PicklerState;;
const #65 = Asciz	(Tu;Lscala/io/BytePickle$PicklerState;)Lscala/io/BytePickle$PicklerState;;
const #66 = Asciz	Lscala/io/BytePickle$SPU<Tu;>;;
const #67 = Asciz	Scala;
const #68 = Asciz	InnerClasses;
const #69 = Asciz	scala/io/BytePickle;
const #70 = class	#69;	//  scala/io/BytePickle
const #71 = Asciz	SPU;
const #72 = Asciz	$anon$7;
const #73 = Asciz	scala/io/BytePickle$PicklerState;
const #74 = class	#73;	//  scala/io/BytePickle$PicklerState
const #75 = Asciz	PicklerState;
const #76 = Asciz	UnPicklerState;

{
public scala.io.BytePickle$$anon$7(scala.Function1, scala.io.BytePickle$SPU, scala.Function1);
  Code:
   Stack=2, Locals=4, Args_size=4
   0:	aload_0
   1:	aload_1
   2:	putfield	#15; //Field f$2:Lscala/Function1;
   5:	aload_0
   6:	aload_2
   7:	putfield	#17; //Field pa$3:Lscala/io/BytePickle$SPU;
   10:	aload_0
   11:	aload_3
   12:	putfield	#19; //Field k$2:Lscala/Function1;
   15:	aload_0
   16:	invokespecial	#24; //Method scala/io/BytePickle$SPU."<init>":()V
   19:	return
  LineNumberTable: 
   line 186: 0


public scala.Tuple2 appU(scala.io.BytePickle$UnPicklerState);
  Code:
   Stack=2, Locals=6, Args_size=2
   0:	aload_0
   1:	getfield	#17; //Field pa$3:Lscala/io/BytePickle$SPU;
   4:	aload_1
   5:	invokevirtual	#28; //Method scala/io/BytePickle$SPU.appU:(Lscala/io/BytePickle$UnPicklerState;)Lscala/Tuple2;
   8:	astore_2
   9:	aload_2
   10:	invokevirtual	#34; //Method scala/Tuple2._1:()Ljava/lang/Object;
   13:	astore_3
   14:	aload_2
   15:	invokevirtual	#37; //Method scala/Tuple2._2:()Ljava/lang/Object;
   18:	checkcast	#39; //class scala/io/BytePickle$UnPicklerState
   21:	astore	4
   23:	aload_0
   24:	getfield	#19; //Field k$2:Lscala/Function1;
   27:	aload_3
   28:	invokeinterface	#45,  2; //InterfaceMethod scala/Function1.apply:(Ljava/lang/Object;)Ljava/lang/Object;
   33:	checkcast	#21; //class scala/io/BytePickle$SPU
   36:	astore	5
   38:	aload	5
   40:	aload	4
   42:	invokevirtual	#28; //Method scala/io/BytePickle$SPU.appU:(Lscala/io/BytePickle$UnPicklerState;)Lscala/Tuple2;
   45:	areturn
  LineNumberTable: 
   line 194: 0
   line 195: 9
   line 196: 14
   line 197: 23
   line 198: 38

  LocalVariableTable: 
   Start  Length  Slot  Name   Signature
   0      46      0    this       Lscala/io/BytePickle$$anon$7;
   0      46      1    s       Lscala/io/BytePickle$UnPicklerState;
   9      36      2    resPa       Lscala/Tuple2;
   14      31      3    a       Ljava/lang/Object;
   23      22      4    sPrime       Lscala/io/BytePickle$UnPicklerState;
   38      7      5    pb       Lscala/io/BytePickle$SPU;

  Signature: length = 0x2
   00 39 

public scala.io.BytePickle$PicklerState appP(java.lang.Object, scala.io.BytePickle$PicklerState);
  Code:
   Stack=3, Locals=6, Args_size=3
   0:	aload_0
   1:	getfield	#15; //Field f$2:Lscala/Function1;
   4:	aload_1
   5:	invokeinterface	#45,  2; //InterfaceMethod scala/Function1.apply:(Ljava/lang/Object;)Ljava/lang/Object;
   10:	astore_3
   11:	aload_0
   12:	getfield	#17; //Field pa$3:Lscala/io/BytePickle$SPU;
   15:	aload_3
   16:	aload_2
   17:	invokevirtual	#62; //Method scala/io/BytePickle$SPU.appP:(Ljava/lang/Object;Lscala/io/BytePickle$PicklerState;)Lscala/io/BytePickle$PicklerState;
   20:	astore	4
   22:	aload_0
   23:	getfield	#19; //Field k$2:Lscala/Function1;
   26:	aload_3
   27:	invokeinterface	#45,  2; //InterfaceMethod scala/Function1.apply:(Ljava/lang/Object;)Ljava/lang/Object;
   32:	checkcast	#21; //class scala/io/BytePickle$SPU
   35:	astore	5
   37:	aload	5
   39:	aload_1
   40:	aload	4
   42:	invokevirtual	#62; //Method scala/io/BytePickle$SPU.appP:(Ljava/lang/Object;Lscala/io/BytePickle$PicklerState;)Lscala/io/BytePickle$PicklerState;
   45:	areturn
  LineNumberTable: 
   line 188: 0
   line 189: 11
   line 190: 22
   line 191: 37

  LocalVariableTable: 
   Start  Length  Slot  Name   Signature
   0      46      0    this       Lscala/io/BytePickle$$anon$7;
   0      46      1    b       Ljava/lang/Object;
   0      46      2    s       Lscala/io/BytePickle$PicklerState;
   11      34      3    a       Ljava/lang/Object;
   22      23      4    sPrime       Lscala/io/BytePickle$PicklerState;
   37      8      5    pb       Lscala/io/BytePickle$SPU;

  Signature: length = 0x2
   00 41 

}

