Compiled from "BytePickle.scala"
public final class scala.io.BytePickle$$anonfun$upair$2 extends scala.runtime.AbstractFunction1 implements java.io.Serializable
  SourceFile: "BytePickle.scala"
  Scala: length = 0x
   
  InnerClass: 
   public abstract #57= #54 of #56; //PU=class scala/io/BytePickle$PU of class scala/io/BytePickle
   public final #58= #44 of #56; //$anon$6=class scala/io/BytePickle$$anon$6 of class scala/io/BytePickle
   public final #59= #9 of #56; //$anonfun$upair$2=class scala/io/BytePickle$$anonfun$upair$2 of class scala/io/BytePickle
   public final #60= #39 of #9; //$anonfun$apply$2=class scala/io/BytePickle$$anonfun$upair$2$$anonfun$apply$2 of class scala/io/BytePickle$$anonfun$upair$2
   public final #61= #34 of #9; //$anonfun$apply$1=class scala/io/BytePickle$$anonfun$upair$2$$anonfun$apply$1 of class scala/io/BytePickle$$anonfun$upair$2
  minor version: 0
  major version: 49
  Constant pool:
const #1 = Asciz	SourceFile;
const #2 = Asciz	BytePickle.scala;
const #3 = Asciz	<clinit>;
const #4 = Asciz	()V;
const #5 = Asciz	Code;
const #6 = Asciz	serialVersionUID;
const #7 = Asciz	J;
const #8 = Asciz	scala/io/BytePickle$$anonfun$upair$2;
const #9 = class	#8;	//  scala/io/BytePickle$$anonfun$upair$2
const #10 = NameAndType	#6:#7;//  serialVersionUID:J
const #11 = Field	#9.#10;	//  scala/io/BytePickle$$anonfun$upair$2.serialVersionUID:J
const #12 = Asciz	pb$1;
const #13 = Asciz	Lscala/io/BytePickle$PU;;
const #14 = Asciz	<init>;
const #15 = Asciz	(Lscala/io/BytePickle$PU;)V;
const #16 = Asciz	LineNumberTable;
const #17 = NameAndType	#12:#13;//  pb$1:Lscala/io/BytePickle$PU;
const #18 = Field	#9.#17;	//  scala/io/BytePickle$$anonfun$upair$2.pb$1:Lscala/io/BytePickle$PU;
const #19 = Asciz	scala/runtime/AbstractFunction1;
const #20 = class	#19;	//  scala/runtime/AbstractFunction1
const #21 = NameAndType	#14:#4;//  "<init>":()V
const #22 = Method	#20.#21;	//  scala/runtime/AbstractFunction1."<init>":()V
const #23 = Asciz	apply;
const #24 = Asciz	(Ljava/lang/Object;)Ljava/lang/Object;;
const #25 = Asciz	(Ljava/lang/Object;)Lscala/io/BytePickle$PU;;
const #26 = NameAndType	#23:#25;//  apply:(Ljava/lang/Object;)Lscala/io/BytePickle$PU;
const #27 = Method	#9.#26;	//  scala/io/BytePickle$$anonfun$upair$2.apply:(Ljava/lang/Object;)Lscala/io/BytePickle$PU;
const #28 = Asciz	this;
const #29 = Asciz	Lscala/io/BytePickle$$anonfun$upair$2;;
const #30 = Asciz	v1;
const #31 = Asciz	Ljava/lang/Object;;
const #32 = Asciz	LocalVariableTable;
const #33 = Asciz	scala/io/BytePickle$$anonfun$upair$2$$anonfun$apply$1;
const #34 = class	#33;	//  scala/io/BytePickle$$anonfun$upair$2$$anonfun$apply$1
const #35 = Asciz	(Lscala/io/BytePickle$$anonfun$upair$2;)V;
const #36 = NameAndType	#14:#35;//  "<init>":(Lscala/io/BytePickle$$anonfun$upair$2;)V
const #37 = Method	#34.#36;	//  scala/io/BytePickle$$anonfun$upair$2$$anonfun$apply$1."<init>":(Lscala/io/BytePickle$$anonfun$upair$2;)V
const #38 = Asciz	scala/io/BytePickle$$anonfun$upair$2$$anonfun$apply$2;
const #39 = class	#38;	//  scala/io/BytePickle$$anonfun$upair$2$$anonfun$apply$2
const #40 = Asciz	(Lscala/io/BytePickle$$anonfun$upair$2;Ljava/lang/Object;)V;
const #41 = NameAndType	#14:#40;//  "<init>":(Lscala/io/BytePickle$$anonfun$upair$2;Ljava/lang/Object;)V
const #42 = Method	#39.#41;	//  scala/io/BytePickle$$anonfun$upair$2$$anonfun$apply$2."<init>":(Lscala/io/BytePickle$$anonfun$upair$2;Ljava/lang/Object;)V
const #43 = Asciz	scala/io/BytePickle$$anon$6;
const #44 = class	#43;	//  scala/io/BytePickle$$anon$6
const #45 = Asciz	(Lscala/Function1;Lscala/io/BytePickle$PU;Lscala/Function1;)V;
const #46 = NameAndType	#14:#45;//  "<init>":(Lscala/Function1;Lscala/io/BytePickle$PU;Lscala/Function1;)V
const #47 = Method	#44.#46;	//  scala/io/BytePickle$$anon$6."<init>":(Lscala/Function1;Lscala/io/BytePickle$PU;Lscala/Function1;)V
const #48 = Asciz	x$6;
const #49 = Asciz	(Ta;)Lscala/io/BytePickle$PU<Lscala/Tuple2<Ta;Tb;>;>;;
const #50 = Asciz	Signature;
const #51 = Asciz	Scala;
const #52 = Asciz	InnerClasses;
const #53 = Asciz	scala/io/BytePickle$PU;
const #54 = class	#53;	//  scala/io/BytePickle$PU
const #55 = Asciz	scala/io/BytePickle;
const #56 = class	#55;	//  scala/io/BytePickle
const #57 = Asciz	PU;
const #58 = Asciz	$anon$6;
const #59 = Asciz	$anonfun$upair$2;
const #60 = Asciz	$anonfun$apply$2;
const #61 = Asciz	$anonfun$apply$1;
const #62 = Asciz	java/io/Serializable;
const #63 = class	#62;	//  java/io/Serializable

{
public static final long serialVersionUID;

public static {};
  Code:
   Stack=2, Locals=0, Args_size=0
   0:	lconst_0
   1:	putstatic	#11; //Field serialVersionUID:J
   4:	return

public scala.io.BytePickle$$anonfun$upair$2(scala.io.BytePickle$PU);
  Code:
   Stack=2, Locals=2, Args_size=2
   0:	aload_0
   1:	aload_1
   2:	putfield	#18; //Field pb$1:Lscala/io/BytePickle$PU;
   5:	aload_0
   6:	invokespecial	#22; //Method scala/runtime/AbstractFunction1."<init>":()V
   9:	return
  LineNumberTable: 
   line 205: 0


public final java.lang.Object apply(java.lang.Object);
  Code:
   Stack=2, Locals=2, Args_size=2
   0:	aload_0
   1:	aload_1
   2:	invokevirtual	#27; //Method apply:(Ljava/lang/Object;)Lscala/io/BytePickle$PU;
   5:	areturn
  LineNumberTable: 
   line 205: 0

  LocalVariableTable: 
   Start  Length  Slot  Name   Signature
   0      6      0    this       Lscala/io/BytePickle$$anonfun$upair$2;
   0      6      1    v1       Ljava/lang/Object;


public final scala.io.BytePickle$PU apply(java.lang.Object);
  Code:
   Stack=6, Locals=5, Args_size=2
   0:	new	#34; //class scala/io/BytePickle$$anonfun$upair$2$$anonfun$apply$1
   3:	dup
   4:	aload_0
   5:	invokespecial	#37; //Method scala/io/BytePickle$$anonfun$upair$2$$anonfun$apply$1."<init>":(Lscala/io/BytePickle$$anonfun$upair$2;)V
   8:	aload_0
   9:	getfield	#18; //Field pb$1:Lscala/io/BytePickle$PU;
   12:	new	#39; //class scala/io/BytePickle$$anonfun$upair$2$$anonfun$apply$2
   15:	dup
   16:	aload_0
   17:	aload_1
   18:	invokespecial	#42; //Method scala/io/BytePickle$$anonfun$upair$2$$anonfun$apply$2."<init>":(Lscala/io/BytePickle$$anonfun$upair$2;Ljava/lang/Object;)V
   21:	astore	4
   23:	astore_3
   24:	astore_2
   25:	new	#44; //class scala/io/BytePickle$$anon$6
   28:	dup
   29:	aload_2
   30:	aload_3
   31:	aload	4
   33:	invokespecial	#47; //Method scala/io/BytePickle$$anon$6."<init>":(Lscala/Function1;Lscala/io/BytePickle$PU;Lscala/Function1;)V
   36:	areturn
  LineNumberTable: 
   line 205: 0

  LocalVariableTable: 
   Start  Length  Slot  Name   Signature
   0      37      0    this       Lscala/io/BytePickle$$anonfun$upair$2;
   0      37      1    x$6       Ljava/lang/Object;

  Signature: length = 0x2
   00 31 

}

