Compiled from "BytePickle.scala"
public final class scala.io.BytePickle$$anon$8 extends scala.io.BytePickle$SPU
  SourceFile: "BytePickle.scala"
  Signature: length = 0x2
   00 FFFFFF8D 
  Scala: length = 0x
   
  InnerClass: 
   public abstract SPU=class scala/io/BytePickle$SPU of class scala/io/BytePickle
   public final $anon$8=class scala/io/BytePickle$$anon$8 of class scala/io/BytePickle
   public PicklerEnv=class scala/io/BytePickle$PicklerEnv of class scala/io/BytePickle
   public UnPicklerEnv=class scala/io/BytePickle$UnPicklerEnv of class scala/io/BytePickle
   public PicklerState=class scala/io/BytePickle$PicklerState of class scala/io/BytePickle
   public UnPicklerState=class scala/io/BytePickle$UnPicklerState of class scala/io/BytePickle
  minor version: 0
  major version: 49
  Constant pool:
Asciz	SourceFile;
Asciz	BytePickle.scala;
Asciz	appP;
Asciz	(ILscala/io/BytePickle$PicklerState;)Lscala/io/BytePickle$PicklerState;;
Asciz	Code;
Asciz	scala/io/BytePickle$PicklerState;
class	scala/io/BytePickle$PicklerState
Asciz	LineNumberTable;
Asciz	scala/Array$;
class	scala/Array$
Asciz	MODULE$;
Asciz	Lscala/Array$;;
NameAndType	MODULE$:Lscala/Array$;
Field	scala/Array$.MODULE$:Lscala/Array$;
Asciz	scala/Predef$;
class	scala/Predef$
Asciz	Lscala/Predef$;;
NameAndType	MODULE$:Lscala/Predef$;
Field	scala/Predef$.MODULE$:Lscala/Predef$;
Asciz	[B;
class	"[B"
Asciz	stream;
Asciz	()[B;
NameAndType	stream:()[B
Method	scala/io/BytePickle$PicklerState.stream:()[B
Asciz	scala/io/BytePickle$;
class	scala/io/BytePickle$
Asciz	Lscala/io/BytePickle$;;
NameAndType	MODULE$:Lscala/io/BytePickle$;
Field	scala/io/BytePickle$.MODULE$:Lscala/io/BytePickle$;
Asciz	nat2Bytes;
Asciz	(I)[B;
NameAndType	nat2Bytes:(I)[B
Method	scala/io/BytePickle$.nat2Bytes:(I)[B
Asciz	[Ljava/lang/Object;;
class	"[Ljava/lang/Object;"
Asciz	wrapRefArray;
Asciz	([Ljava/lang/Object;)Lscala/collection/mutable/WrappedArray;;
NameAndType	wrapRefArray:([Ljava/lang/Object;)Lscala/collection/mutable/WrappedArray;
Method	scala/Predef$.wrapRefArray:([Ljava/lang/Object;)Lscala/collection/mutable/WrappedArray;
Asciz	scala/reflect/Manifest$;
class	scala/reflect/Manifest$
Asciz	Lscala/reflect/Manifest$;;
NameAndType	MODULE$:Lscala/reflect/Manifest$;
Field	scala/reflect/Manifest$.MODULE$:Lscala/reflect/Manifest$;
Asciz	Byte;
Asciz	()Lscala/reflect/AnyValManifest;;
NameAndType	Byte:()Lscala/reflect/AnyValManifest;
Method	scala/reflect/Manifest$.Byte:()Lscala/reflect/AnyValManifest;
Asciz	concat;
Asciz	(Lscala/collection/Seq;Lscala/reflect/ClassManifest;)Ljava/lang/Object;;
NameAndType	concat:(Lscala/collection/Seq;Lscala/reflect/ClassManifest;)Ljava/lang/Object;
Method	scala/Array$.concat:(Lscala/collection/Seq;Lscala/reflect/ClassManifest;)Ljava/lang/Object;
Asciz	dict;
Asciz	()Lscala/io/BytePickle$PicklerEnv;;
NameAndType	dict:()Lscala/io/BytePickle$PicklerEnv;
Method	scala/io/BytePickle$PicklerState.dict:()Lscala/io/BytePickle$PicklerEnv;
Asciz	<init>;
Asciz	([BLscala/io/BytePickle$PicklerEnv;)V;
NameAndType	"<init>":([BLscala/io/BytePickle$PicklerEnv;)V
Method	scala/io/BytePickle$PicklerState."<init>":([BLscala/io/BytePickle$PicklerEnv;)V
Asciz	this;
Asciz	Lscala/io/BytePickle$$anon$8;;
Asciz	n;
Asciz	I;
Asciz	s;
Asciz	Lscala/io/BytePickle$PicklerState;;
Asciz	LocalVariableTable;
Asciz	appU;
Asciz	(Lscala/io/BytePickle$UnPicklerState;)Lscala/Tuple2;;
Asciz	scala/runtime/IntRef;
class	scala/runtime/IntRef
Asciz	(I)V;
NameAndType	"<init>":(I)V
Method	scala/runtime/IntRef."<init>":(I)V
Asciz	scala/Tuple2;
class	scala/Tuple2
Asciz	scala/io/BytePickle$$anon$8;
class	scala/io/BytePickle$$anon$8
Asciz	readNat$2;
Asciz	(Lscala/io/BytePickle$UnPicklerState;Lscala/runtime/IntRef;)I;
NameAndType	readNat$2:(Lscala/io/BytePickle$UnPicklerState;Lscala/runtime/IntRef;)I
Method	scala/io/BytePickle$$anon$8.readNat$2:(Lscala/io/BytePickle$UnPicklerState;Lscala/runtime/IntRef;)I
Asciz	scala/runtime/BoxesRunTime;
class	scala/runtime/BoxesRunTime
Asciz	boxToInteger;
Asciz	(I)Ljava/lang/Integer;;
NameAndType	boxToInteger:(I)Ljava/lang/Integer;
Method	scala/runtime/BoxesRunTime.boxToInteger:(I)Ljava/lang/Integer;
Asciz	scala/io/BytePickle$UnPicklerState;
class	scala/io/BytePickle$UnPicklerState
Method	scala/io/BytePickle$UnPicklerState.stream:()[B
Asciz	byteArrayOps;
Asciz	([B)Lscala/collection/mutable/ArrayOps;;
NameAndType	byteArrayOps:([B)Lscala/collection/mutable/ArrayOps;
Method	scala/Predef$.byteArrayOps:([B)Lscala/collection/mutable/ArrayOps;
Asciz	elem;
NameAndType	elem:I
Field	scala/runtime/IntRef.elem:I
Asciz	scala/collection/IndexedSeqLike;
class	scala/collection/IndexedSeqLike
Asciz	slice;
Asciz	(II)Ljava/lang/Object;;
NameAndType	slice:(II)Ljava/lang/Object;
InterfaceMethod	scala/collection/IndexedSeqLike.slice:(II)Ljava/lang/Object;
Asciz	()Lscala/io/BytePickle$UnPicklerEnv;;
NameAndType	dict:()Lscala/io/BytePickle$UnPicklerEnv;
Method	scala/io/BytePickle$UnPicklerState.dict:()Lscala/io/BytePickle$UnPicklerEnv;
Asciz	([BLscala/io/BytePickle$UnPicklerEnv;)V;
NameAndType	"<init>":([BLscala/io/BytePickle$UnPicklerEnv;)V
Method	scala/io/BytePickle$UnPicklerState."<init>":([BLscala/io/BytePickle$UnPicklerEnv;)V
Asciz	(Ljava/lang/Object;Ljava/lang/Object;)V;
NameAndType	"<init>":(Ljava/lang/Object;Ljava/lang/Object;)V
Method	scala/Tuple2."<init>":(Ljava/lang/Object;Ljava/lang/Object;)V
Asciz	s$2;
Asciz	Lscala/io/BytePickle$UnPicklerState;;
Asciz	num$2;
Asciz	Lscala/runtime/IntRef;;
Asciz	(Lscala/io/BytePickle$UnPicklerState;)Lscala/Tuple2<Ljava/lang/Integer;Lscala/io/BytePickle$UnPicklerState;>;;
Asciz	Signature;
Asciz	(Ljava/lang/Object;Lscala/io/BytePickle$PicklerState;)Lscala/io/BytePickle$PicklerState;;
Asciz	unboxToInt;
Asciz	(Ljava/lang/Object;)I;
NameAndType	unboxToInt:(Ljava/lang/Object;)I
Method	scala/runtime/BoxesRunTime.unboxToInt:(Ljava/lang/Object;)I
NameAndType	appP:(ILscala/io/BytePickle$PicklerState;)Lscala/io/BytePickle$PicklerState;
Method	scala/io/BytePickle$$anon$8.appP:(ILscala/io/BytePickle$PicklerState;)Lscala/io/BytePickle$PicklerState;
Asciz	a;
Asciz	Ljava/lang/Object;;
Asciz	state;
int	7;
int	127;
int	128;
Asciz	b;
Asciz	x;
Asciz	()V;
Asciz	scala/io/BytePickle$SPU;
class	scala/io/BytePickle$SPU
NameAndType	"<init>":()V
Method	scala/io/BytePickle$SPU."<init>":()V
Asciz	Lscala/io/BytePickle$SPU<Ljava/lang/Integer;>;;
Asciz	Scala;
Asciz	InnerClasses;
Asciz	scala/io/BytePickle;
class	scala/io/BytePickle
Asciz	SPU;
Asciz	$anon$8;
Asciz	scala/io/BytePickle$PicklerEnv;
class	scala/io/BytePickle$PicklerEnv
Asciz	PicklerEnv;
Asciz	scala/io/BytePickle$UnPicklerEnv;
class	scala/io/BytePickle$UnPicklerEnv
Asciz	UnPicklerEnv;
Asciz	PicklerState;
Asciz	UnPicklerState;

{
public scala.io.BytePickle$PicklerState appP(int, scala.io.BytePickle$PicklerState);
  Signature: (ILscala/io/BytePickle$PicklerState;)Lscala/io/BytePickle$PicklerState;
  Code:
   Stack=9, Locals=3, Args_size=3
	new	class scala/io/BytePickle$PicklerState
	dup
	getstatic	Field scala/Array$.MODULE$:Lscala/Array$;
	getstatic	Field scala/Predef$.MODULE$:Lscala/Predef$;
	iconst_2
	anewarray	class "[B"
	dup
	iconst_0
	aload_2
	invokevirtual	Method scala/io/BytePickle$PicklerState.stream:()[B
	aastore
	dup
	iconst_1
	getstatic	Field scala/io/BytePickle$.MODULE$:Lscala/io/BytePickle$;
	iload_1
	invokevirtual	Method scala/io/BytePickle$.nat2Bytes:(I)[B
	aastore
	checkcast	class "[Ljava/lang/Object;"
	invokevirtual	Method scala/Predef$.wrapRefArray:([Ljava/lang/Object;)Lscala/collection/mutable/WrappedArray;
	getstatic	Field scala/reflect/Manifest$.MODULE$:Lscala/reflect/Manifest$;
	invokevirtual	Method scala/reflect/Manifest$.Byte:()Lscala/reflect/AnyValManifest;
	invokevirtual	Method scala/Array$.concat:(Lscala/collection/Seq;Lscala/reflect/ClassManifest;)Ljava/lang/Object;
	checkcast	class "[B"
	aload_2
	invokevirtual	Method scala/io/BytePickle$PicklerState.dict:()Lscala/io/BytePickle$PicklerEnv;
	invokespecial	Method scala/io/BytePickle$PicklerState."<init>":([BLscala/io/BytePickle$PicklerEnv;)V
	areturn
  Labels:
  LocalVariableTable: 
   Start  Length  Slot  Name   Signature
   0      57      0    this       Lscala/io/BytePickle$$anon$8;
   0      57      1    n       I
   0      57      2    s       Lscala/io/BytePickle$PicklerState;


public scala.Tuple2 appU(scala.io.BytePickle$UnPicklerState);
  Signature: (Lscala/io/BytePickle$UnPicklerState;)Lscala/Tuple2;
  Code:
   Stack=8, Locals=4, Args_size=2
	new	class scala/runtime/IntRef
	dup
	iconst_0
	invokespecial	Method scala/runtime/IntRef."<init>":(I)V
	astore_2
	new	class scala/Tuple2
	dup
	aload_0
	aload_1
	aload_2
	invokespecial	Method readNat$2:(Lscala/io/BytePickle$UnPicklerState;Lscala/runtime/IntRef;)I
	istore_3
	iload_3
	invokestatic	Method scala/runtime/BoxesRunTime.boxToInteger:(I)Ljava/lang/Integer;
	new	class scala/io/BytePickle$UnPicklerState
	dup
	getstatic	Field scala/Predef$.MODULE$:Lscala/Predef$;
	aload_1
	invokevirtual	Method scala/io/BytePickle$UnPicklerState.stream:()[B
	invokevirtual	Method scala/Predef$.byteArrayOps:([B)Lscala/collection/mutable/ArrayOps;
	aload_2
	getfield	Field scala/runtime/IntRef.elem:I
	aload_1
	invokevirtual	Method scala/io/BytePickle$UnPicklerState.stream:()[B
	arraylength
	invokeinterface	InterfaceMethod scala/collection/IndexedSeqLike.slice:(II)Ljava/lang/Object;
	checkcast	class "[B"
	aload_1
	invokevirtual	Method scala/io/BytePickle$UnPicklerState.dict:()Lscala/io/BytePickle$UnPicklerEnv;
	invokespecial	Method scala/io/BytePickle$UnPicklerState."<init>":([BLscala/io/BytePickle$UnPicklerEnv;)V
	invokespecial	Method scala/Tuple2."<init>":(Ljava/lang/Object;Ljava/lang/Object;)V
	areturn
  Labels:
  LocalVariableTable: 
   Start  Length  Slot  Name   Signature
   0      66      0    this       Lscala/io/BytePickle$$anon$8;
   0      66      1    s$2       Lscala/io/BytePickle$UnPicklerState;
   9      56      2    num$2       Lscala/runtime/IntRef;

  Signature: length = 0x2
   00 77 

public scala.io.BytePickle$PicklerState appP(java.lang.Object, scala.io.BytePickle$PicklerState);
  Signature: (Ljava/lang/Object;Lscala/io/BytePickle$PicklerState;)Lscala/io/BytePickle$PicklerState;
  Code:
   Stack=3, Locals=3, Args_size=3
	aload_0
	aload_1
	invokestatic	Method scala/runtime/BoxesRunTime.unboxToInt:(Ljava/lang/Object;)I
	aload_2
	invokevirtual	Method appP:(ILscala/io/BytePickle$PicklerState;)Lscala/io/BytePickle$PicklerState;
	areturn
  Labels:
  LocalVariableTable: 
   Start  Length  Slot  Name   Signature
   0      10      0    this       Lscala/io/BytePickle$$anon$8;
   0      10      1    a       Ljava/lang/Object;
   0      10      2    state       Lscala/io/BytePickle$PicklerState;


private final int readNat$2(scala.io.BytePickle$UnPicklerState, scala.runtime.IntRef);
  Signature: (Lscala/io/BytePickle$UnPicklerState;Lscala/runtime/IntRef;)I
  Code:
   Stack=3, Locals=5, Args_size=3
	iconst_0
	istore	4
l1	aload_1
	invokevirtual	Method scala/io/BytePickle$UnPicklerState.stream:()[B
	aload_2
	getfield	Field scala/runtime/IntRef.elem:I
	baload
	istore_3
	aload_2
	aload_2
	getfield	Field scala/runtime/IntRef.elem:I
	iconst_1
	iadd
	putfield	Field scala/runtime/IntRef.elem:I
	iload	4
	ldc	int 7
	ishl
	iload_3
	ldc	int 127
	iand
	iadd
	istore	4
	iload_3
	ldc	int 128
	iand
	iconst_0
	if_icmpne	l1 // aload_1
	iload	4
	ireturn
  Labels:
   	l1 = 3 // aload_1
  LocalVariableTable: 
   Start  Length  Slot  Name   Signature
   0      46      0    this       Lscala/io/BytePickle$$anon$8;
   0      45      3    b       I
   3      42      4    x       I


public scala.io.BytePickle$$anon$8();
  Signature: ()V
  Code:
   Stack=1, Locals=1, Args_size=1
	aload_0
	invokespecial	Method scala/io/BytePickle$SPU."<init>":()V
	return
  Labels:

}

