Compiled from "BytePickle.scala"
public final class scala.io.BytePickle$$anon$6 extends scala.io.BytePickle$PU
  SourceFile: "BytePickle.scala"
  Scala: length = 0x
   
  Signature: length = 0x2
   00 42 
  InnerClass: 
   public abstract PU=class scala/io/BytePickle$PU of class scala/io/BytePickle
   public final $anon$6=class scala/io/BytePickle$$anon$6 of class scala/io/BytePickle
  minor version: 0
  major version: 49
  Constant pool:
Asciz	SourceFile;
Asciz	BytePickle.scala;
Asciz	f$1;
Asciz	Lscala/Function1;;
Asciz	pa$2;
Asciz	Lscala/io/BytePickle$PU;;
Asciz	k$1;
Asciz	appP;
Asciz	(Ljava/lang/Object;[B)[B;
Asciz	Code;
Asciz	LineNumberTable;
Asciz	scala/io/BytePickle$$anon$6;
class	scala/io/BytePickle$$anon$6
NameAndType	f$1:Lscala/Function1;
Field	scala/io/BytePickle$$anon$6.f$1:Lscala/Function1;
Asciz	scala/Function1;
class	scala/Function1
Asciz	apply;
Asciz	(Ljava/lang/Object;)Ljava/lang/Object;;
NameAndType	apply:(Ljava/lang/Object;)Ljava/lang/Object;
InterfaceMethod	scala/Function1.apply:(Ljava/lang/Object;)Ljava/lang/Object;
NameAndType	pa$2:Lscala/io/BytePickle$PU;
Field	scala/io/BytePickle$$anon$6.pa$2:Lscala/io/BytePickle$PU;
Asciz	scala/io/BytePickle$PU;
class	scala/io/BytePickle$PU
NameAndType	appP:(Ljava/lang/Object;[B)[B
Method	scala/io/BytePickle$PU.appP:(Ljava/lang/Object;[B)[B
NameAndType	k$1:Lscala/Function1;
Field	scala/io/BytePickle$$anon$6.k$1:Lscala/Function1;
Asciz	this;
Asciz	Lscala/io/BytePickle$$anon$6;;
Asciz	b;
Asciz	Ljava/lang/Object;;
Asciz	s;
Asciz	[B;
Asciz	a;
Asciz	sPrime;
Asciz	pb;
Asciz	sPrimePrime;
Asciz	LocalVariableTable;
Asciz	(Tu;[B)[B;
Asciz	Signature;
Asciz	appU;
Asciz	([B)Lscala/Tuple2;;
NameAndType	appU:([B)Lscala/Tuple2;
Method	scala/io/BytePickle$PU.appU:([B)Lscala/Tuple2;
Asciz	scala/Tuple2;
class	scala/Tuple2
Asciz	_1;
Asciz	()Ljava/lang/Object;;
NameAndType	_1:()Ljava/lang/Object;
Method	scala/Tuple2._1:()Ljava/lang/Object;
Asciz	_2;
NameAndType	_2:()Ljava/lang/Object;
Method	scala/Tuple2._2:()Ljava/lang/Object;
class	"[B"
Asciz	resPa;
Asciz	Lscala/Tuple2;;
Asciz	([B)Lscala/Tuple2<Tu;[B>;;
Asciz	<init>;
Asciz	(Lscala/Function1;Lscala/io/BytePickle$PU;Lscala/Function1;)V;
Asciz	()V;
NameAndType	"<init>":()V
Method	scala/io/BytePickle$PU."<init>":()V
Asciz	Scala;
Asciz	Lscala/io/BytePickle$PU<Tu;>;;
Asciz	InnerClasses;
Asciz	scala/io/BytePickle;
class	scala/io/BytePickle
Asciz	PU;
Asciz	$anon$6;

{
private final scala.Function1 f$1;
  Signature: Lscala/Function1;

private final scala.io.BytePickle$PU pa$2;
  Signature: Lscala/io/BytePickle$PU;

private final scala.Function1 k$1;
  Signature: Lscala/Function1;

public byte[] appP(java.lang.Object, byte[]);
  Signature: (Ljava/lang/Object;[B)[B
  Code:
   Stack=3, Locals=7, Args_size=3
	aload_0
	getfield	Field f$1:Lscala/Function1;
	aload_1
	invokeinterface	InterfaceMethod scala/Function1.apply:(Ljava/lang/Object;)Ljava/lang/Object;
	astore_3
	aload_0
	getfield	Field pa$2:Lscala/io/BytePickle$PU;
	aload_3
	aload_2
	invokevirtual	Method scala/io/BytePickle$PU.appP:(Ljava/lang/Object;[B)[B
	astore	4
	aload_0
	getfield	Field k$1:Lscala/Function1;
	aload_3
	invokeinterface	InterfaceMethod scala/Function1.apply:(Ljava/lang/Object;)Ljava/lang/Object;
	checkcast	class scala/io/BytePickle$PU
	astore	5
	aload	5
	aload_1
	aload	4
	invokevirtual	Method scala/io/BytePickle$PU.appP:(Ljava/lang/Object;[B)[B
	astore	6
	aload	6
	areturn
  Labels:
  LocalVariableTable: 
   Start  Length  Slot  Name   Signature
   0      50      0    this       Lscala/io/BytePickle$$anon$6;
   0      50      1    b       Ljava/lang/Object;
   0      50      2    s       [B
   11      38      3    a       Ljava/lang/Object;
   22      27      4    sPrime       [B
   37      12      5    pb       Lscala/io/BytePickle$PU;
   47      2      6    sPrimePrime       [B

  Signature: length = 0x2
   00 29 

public scala.Tuple2 appU(byte[]);
  Signature: ([B)Lscala/Tuple2;
  Code:
   Stack=2, Locals=6, Args_size=2
	aload_0
	getfield	Field pa$2:Lscala/io/BytePickle$PU;
	aload_1
	invokevirtual	Method scala/io/BytePickle$PU.appU:([B)Lscala/Tuple2;
	astore_2
	aload_2
	invokevirtual	Method scala/Tuple2._1:()Ljava/lang/Object;
	astore_3
	aload_2
	invokevirtual	Method scala/Tuple2._2:()Ljava/lang/Object;
	checkcast	class "[B"
	astore	4
	aload_0
	getfield	Field k$1:Lscala/Function1;
	aload_3
	invokeinterface	InterfaceMethod scala/Function1.apply:(Ljava/lang/Object;)Ljava/lang/Object;
	checkcast	class scala/io/BytePickle$PU
	astore	5
	aload	5
	aload	4
	invokevirtual	Method scala/io/BytePickle$PU.appU:([B)Lscala/Tuple2;
	areturn
  Labels:
  LocalVariableTable: 
   Start  Length  Slot  Name   Signature
   0      46      0    this       Lscala/io/BytePickle$$anon$6;
   0      46      1    s       [B
   9      36      2    resPa       Lscala/Tuple2;
   14      31      3    a       Ljava/lang/Object;
   23      22      4    sPrime       [B
   38      7      5    pb       Lscala/io/BytePickle$PU;

  Signature: length = 0x2
   00 3B 

public scala.io.BytePickle$$anon$6(scala.Function1, scala.io.BytePickle$PU, scala.Function1);
  Signature: (Lscala/Function1;Lscala/io/BytePickle$PU;Lscala/Function1;)V
  Code:
   Stack=2, Locals=4, Args_size=4
	aload_0
	aload_1
	putfield	Field f$1:Lscala/Function1;
	aload_0
	aload_2
	putfield	Field pa$2:Lscala/io/BytePickle$PU;
	aload_0
	aload_3
	putfield	Field k$1:Lscala/Function1;
	aload_0
	invokespecial	Method scala/io/BytePickle$PU."<init>":()V
	return
  Labels:

}

