Compiled from "BytePickle.scala"
public final class scala.io.BytePickle$ extends java.lang.Object implements scala.ScalaObject
  SourceFile: "BytePickle.scala"
  Scala: length = 0x
   
  InnerClass: 
   public abstract #443= #393 of #442; //PU=class scala/io/BytePickle$PU of class scala/io/BytePickle
   public #446= #445 of #442; //Def=class scala/io/BytePickle$Def of class scala/io/BytePickle
   public #449= #448 of #442; //Ref=class scala/io/BytePickle$Ref of class scala/io/BytePickle
   public abstract #450= #418 of #442; //SPU=class scala/io/BytePickle$SPU of class scala/io/BytePickle
   public abstract #453= #452 of #442; //RefDef=class scala/io/BytePickle$RefDef of class scala/io/BytePickle
   public final #454= #256 of #442; //$anon$9=class scala/io/BytePickle$$anon$9 of class scala/io/BytePickle
   public final #455= #132 of #442; //$anon$8=class scala/io/BytePickle$$anon$8 of class scala/io/BytePickle
   public final #456= #140 of #442; //$anon$7=class scala/io/BytePickle$$anon$7 of class scala/io/BytePickle
   public final #457= #163 of #442; //$anon$6=class scala/io/BytePickle$$anon$6 of class scala/io/BytePickle
   public final #458= #191 of #442; //$anon$5=class scala/io/BytePickle$$anon$5 of class scala/io/BytePickle
   public final #459= #219 of #442; //$anon$4=class scala/io/BytePickle$$anon$4 of class scala/io/BytePickle
   public final #460= #267 of #442; //$anon$3=class scala/io/BytePickle$$anon$3 of class scala/io/BytePickle
   public final #461= #155 of #442; //$anon$2=class scala/io/BytePickle$$anon$2 of class scala/io/BytePickle
   public final #462= #387 of #442; //$anon$1=class scala/io/BytePickle$$anon$1 of class scala/io/BytePickle
   public #463= #428 of #442; //PicklerEnv=class scala/io/BytePickle$PicklerEnv of class scala/io/BytePickle
   public #464= #426 of #442; //PicklerState=class scala/io/BytePickle$PicklerState of class scala/io/BytePickle
   public #465= #412 of #442; //UnPicklerEnv=class scala/io/BytePickle$UnPicklerEnv of class scala/io/BytePickle
   public #466= #410 of #442; //UnPicklerState=class scala/io/BytePickle$UnPicklerState of class scala/io/BytePickle
   public final #467= #135 of #442; //$anonfun$data$1=class scala/io/BytePickle$$anonfun$data$1 of class scala/io/BytePickle
   public final #468= #176 of #442; //$anonfun$list$2=class scala/io/BytePickle$$anonfun$list$2 of class scala/io/BytePickle
   public final #469= #173 of #442; //$anonfun$list$1=class scala/io/BytePickle$$anonfun$list$1 of class scala/io/BytePickle
   public final #470= #245 of #442; //$anonfun$bool$2=class scala/io/BytePickle$$anonfun$bool$2 of class scala/io/BytePickle
   public final #471= #242 of #442; //$anonfun$bool$1=class scala/io/BytePickle$$anonfun$bool$1 of class scala/io/BytePickle
   public final #472= #210 of #442; //$anonfun$wrap$1=class scala/io/BytePickle$$anonfun$wrap$1 of class scala/io/BytePickle
   public final #473= #207 of #442; //$anonfun$pair$2=class scala/io/BytePickle$$anonfun$pair$2 of class scala/io/BytePickle
   public final #474= #204 of #442; //$anonfun$pair$1=class scala/io/BytePickle$$anonfun$pair$1 of class scala/io/BytePickle
   public final #475= #158 of #442; //$anonfun$ulist$2=class scala/io/BytePickle$$anonfun$ulist$2 of class scala/io/BytePickle
   public final #476= #152 of #442; //$anonfun$ulist$1=class scala/io/BytePickle$$anonfun$ulist$1 of class scala/io/BytePickle
   public final #477= #236 of #442; //$anonfun$uwrap$1=class scala/io/BytePickle$$anonfun$uwrap$1 of class scala/io/BytePickle
   public final #478= #233 of #442; //$anonfun$upair$2=class scala/io/BytePickle$$anonfun$upair$2 of class scala/io/BytePickle
   public final #479= #230 of #442; //$anonfun$upair$1=class scala/io/BytePickle$$anonfun$upair$1 of class scala/io/BytePickle
   public final #480= #264 of #442; //$anonfun$string$2=class scala/io/BytePickle$$anonfun$string$2 of class scala/io/BytePickle
   public final #481= #261 of #442; //$anonfun$string$1=class scala/io/BytePickle$$anonfun$string$1 of class scala/io/BytePickle
   public final #482= #343 of #442; //$anonfun$triple$2=class scala/io/BytePickle$$anonfun$triple$2 of class scala/io/BytePickle
   public final #483= #340 of #442; //$anonfun$triple$1=class scala/io/BytePickle$$anonfun$triple$1 of class scala/io/BytePickle
   public final #484= #199 of #442; //$anonfun$fixedList$2=class scala/io/BytePickle$$anonfun$fixedList$2 of class scala/io/BytePickle
   public final #485= #196 of #442; //$anonfun$fixedList$1=class scala/io/BytePickle$$anonfun$fixedList$1 of class scala/io/BytePickle
   public final #486= #253 of #442; //$anonfun$bytearray$2=class scala/io/BytePickle$$anonfun$bytearray$2 of class scala/io/BytePickle
   public final #487= #250 of #442; //$anonfun$bytearray$1=class scala/io/BytePickle$$anonfun$bytearray$1 of class scala/io/BytePickle
   public final #488= #225 of #442; //$anonfun$ufixedList$2=class scala/io/BytePickle$$anonfun$ufixedList$2 of class scala/io/BytePickle
   public final #489= #222 of #442; //$anonfun$ufixedList$1=class scala/io/BytePickle$$anonfun$ufixedList$1 of class scala/io/BytePickle
  minor version: 0
  major version: 49
  Constant pool:
const #1 = Asciz	SourceFile;
const #2 = Asciz	BytePickle.scala;
const #3 = Asciz	Scala;
const #4 = Asciz	MODULE$;
const #5 = Asciz	Lscala/io/BytePickle$;;
const #6 = Asciz	<clinit>;
const #7 = Asciz	()V;
const #8 = Asciz	Code;
const #9 = Asciz	scala/io/BytePickle$;
const #10 = class	#9;	//  scala/io/BytePickle$
const #11 = Asciz	<init>;
const #12 = NameAndType	#11:#7;//  "<init>":()V
const #13 = Method	#10.#12;	//  scala/io/BytePickle$."<init>":()V
const #14 = Asciz	DEF;
const #15 = Asciz	I;
const #16 = Asciz	REF;
const #17 = Asciz	LineNumberTable;
const #18 = Asciz	java/lang/Object;
const #19 = class	#18;	//  java/lang/Object
const #20 = Method	#19.#12;	//  java/lang/Object."<init>":()V
const #21 = NameAndType	#4:#5;//  MODULE$:Lscala/io/BytePickle$;
const #22 = Field	#10.#21;	//  scala/io/BytePickle$.MODULE$:Lscala/io/BytePickle$;
const #23 = NameAndType	#16:#15;//  REF:I
const #24 = Field	#10.#23;	//  scala/io/BytePickle$.REF:I
const #25 = NameAndType	#14:#15;//  DEF:I
const #26 = Field	#10.#25;	//  scala/io/BytePickle$.DEF:I
const #27 = Asciz	listToPair$2;
const #28 = Asciz	(Lscala/collection/immutable/List;)Lscala/Tuple2;;
const #29 = Asciz	scala/collection/immutable/$colon$colon;
const #30 = class	#29;	//  scala/collection/immutable/$colon$colon
const #31 = Asciz	scala$collection$immutable$$colon$colon$$hd;
const #32 = Asciz	Ljava/lang/Object;;
const #33 = NameAndType	#31:#32;//  scala$collection$immutable$$colon$colon$$hd:Ljava/lang/Object;
const #34 = Field	#30.#33;	//  scala/collection/immutable/$colon$colon.scala$collection$immutable$$colon$colon$$hd:Ljava/lang/Object;
const #35 = Asciz	tl;
const #36 = Asciz	Lscala/collection/immutable/List;;
const #37 = NameAndType	#35:#36;//  tl:Lscala/collection/immutable/List;
const #38 = Field	#30.#37;	//  scala/collection/immutable/$colon$colon.tl:Lscala/collection/immutable/List;
const #39 = Asciz	scala/Tuple2;
const #40 = class	#39;	//  scala/Tuple2
const #41 = Asciz	(Ljava/lang/Object;Ljava/lang/Object;)V;
const #42 = NameAndType	#11:#41;//  "<init>":(Ljava/lang/Object;Ljava/lang/Object;)V
const #43 = Method	#40.#42;	//  scala/Tuple2."<init>":(Ljava/lang/Object;Ljava/lang/Object;)V
const #44 = Asciz	scala/MatchError;
const #45 = class	#44;	//  scala/MatchError
const #46 = Asciz	scala/collection/SeqLike;
const #47 = class	#46;	//  scala/collection/SeqLike
const #48 = Asciz	toString;
const #49 = Asciz	()Ljava/lang/String;;
const #50 = NameAndType	#48:#49;//  toString:()Ljava/lang/String;
const #51 = InterfaceMethod	#47.#50;	//  scala/collection/SeqLike.toString:()Ljava/lang/String;
const #52 = Asciz	(Ljava/lang/String;)V;
const #53 = NameAndType	#11:#52;//  "<init>":(Ljava/lang/String;)V
const #54 = Method	#45.#53;	//  scala/MatchError."<init>":(Ljava/lang/String;)V
const #55 = Asciz	this;
const #56 = Asciz	l;
const #57 = Asciz	temp26;
const #58 = Asciz	Lscala/collection/immutable/$colon$colon;;
const #59 = Asciz	temp27;
const #60 = Asciz	temp28;
const #61 = Asciz	LocalVariableTable;
const #62 = Asciz	pairToList$2;
const #63 = Asciz	(Lscala/Tuple2;)Lscala/collection/immutable/List;;
const #64 = Asciz	_1;
const #65 = Asciz	()Ljava/lang/Object;;
const #66 = NameAndType	#64:#65;//  _1:()Ljava/lang/Object;
const #67 = Method	#40.#66;	//  scala/Tuple2._1:()Ljava/lang/Object;
const #68 = Asciz	_2;
const #69 = NameAndType	#68:#65;//  _2:()Ljava/lang/Object;
const #70 = Method	#40.#69;	//  scala/Tuple2._2:()Ljava/lang/Object;
const #71 = Asciz	scala/collection/immutable/List;
const #72 = class	#71;	//  scala/collection/immutable/List
const #73 = Asciz	$colon$colon;
const #74 = Asciz	(Ljava/lang/Object;)Lscala/collection/immutable/List;;
const #75 = NameAndType	#73:#74;//  $colon$colon:(Ljava/lang/Object;)Lscala/collection/immutable/List;
const #76 = Method	#72.#75;	//  scala/collection/immutable/List.$colon$colon:(Ljava/lang/Object;)Lscala/collection/immutable/List;
const #77 = Asciz	p;
const #78 = Asciz	Lscala/Tuple2;;
const #79 = Asciz	listToPair$1;
const #80 = Asciz	temp22;
const #81 = Asciz	temp23;
const #82 = Asciz	temp24;
const #83 = Asciz	pairToList$1;
const #84 = Asciz	fromEnum$1;
const #85 = Asciz	(I)Z;
const #86 = Asciz	n;
const #87 = Asciz	toEnum$1;
const #88 = Asciz	(Z)I;
const #89 = Asciz	b;
const #90 = Asciz	Z;
const #91 = Asciz	writeNatPrefix$1;
const #92 = Asciz	(ILscala/collection/mutable/ArrayBuffer;)V;
const #93 = int	7;
const #94 = NameAndType	#91:#92;//  writeNatPrefix$1:(ILscala/collection/mutable/ArrayBuffer;)V
const #95 = Method	#10.#94;	//  scala/io/BytePickle$.writeNatPrefix$1:(ILscala/collection/mutable/ArrayBuffer;)V
const #96 = int	127;
const #97 = int	128;
const #98 = Asciz	scala/runtime/BoxesRunTime;
const #99 = class	#98;	//  scala/runtime/BoxesRunTime
const #100 = Asciz	boxToByte;
const #101 = Asciz	(B)Ljava/lang/Byte;;
const #102 = NameAndType	#100:#101;//  boxToByte:(B)Ljava/lang/Byte;
const #103 = Method	#99.#102;	//  scala/runtime/BoxesRunTime.boxToByte:(B)Ljava/lang/Byte;
const #104 = Asciz	scala/collection/mutable/ArrayBuffer;
const #105 = class	#104;	//  scala/collection/mutable/ArrayBuffer
const #106 = Asciz	$plus$eq;
const #107 = Asciz	(Ljava/lang/Object;)Lscala/collection/mutable/ArrayBuffer;;
const #108 = NameAndType	#106:#107;//  $plus$eq:(Ljava/lang/Object;)Lscala/collection/mutable/ArrayBuffer;
const #109 = Method	#105.#108;	//  scala/collection/mutable/ArrayBuffer.$plus$eq:(Ljava/lang/Object;)Lscala/collection/mutable/ArrayBuffer;
const #110 = Asciz	x;
const #111 = Asciz	y;
const #112 = Asciz	trd$1;
const #113 = Asciz	(Lscala/Tuple3;)Ljava/lang/Object;;
const #114 = Asciz	scala/Tuple3;
const #115 = class	#114;	//  scala/Tuple3
const #116 = Asciz	_3;
const #117 = NameAndType	#116:#65;//  _3:()Ljava/lang/Object;
const #118 = Method	#115.#117;	//  scala/Tuple3._3:()Ljava/lang/Object;
const #119 = Asciz	Lscala/Tuple3;;
const #120 = Asciz	snd$3;
const #121 = Method	#115.#69;	//  scala/Tuple3._2:()Ljava/lang/Object;
const #122 = Asciz	fst$3;
const #123 = Method	#115.#66;	//  scala/Tuple3._1:()Ljava/lang/Object;
const #124 = Asciz	snd$2;
const #125 = Asciz	(Lscala/Tuple2;)Ljava/lang/Object;;
const #126 = Asciz	fst$2;
const #127 = Asciz	snd$1;
const #128 = Asciz	fst$1;
const #129 = Asciz	data;
const #130 = Asciz	(Lscala/Function1;Lscala/collection/immutable/List;)Lscala/io/BytePickle$SPU;;
const #131 = Asciz	scala/io/BytePickle$$anon$8;
const #132 = class	#131;	//  scala/io/BytePickle$$anon$8
const #133 = Method	#132.#12;	//  scala/io/BytePickle$$anon$8."<init>":()V
const #134 = Asciz	scala/io/BytePickle$$anonfun$data$1;
const #135 = class	#134;	//  scala/io/BytePickle$$anonfun$data$1
const #136 = Asciz	(Lscala/collection/immutable/List;)V;
const #137 = NameAndType	#11:#136;//  "<init>":(Lscala/collection/immutable/List;)V
const #138 = Method	#135.#137;	//  scala/io/BytePickle$$anonfun$data$1."<init>":(Lscala/collection/immutable/List;)V
const #139 = Asciz	scala/io/BytePickle$$anon$7;
const #140 = class	#139;	//  scala/io/BytePickle$$anon$7
const #141 = Asciz	(Lscala/Function1;Lscala/io/BytePickle$SPU;Lscala/Function1;)V;
const #142 = NameAndType	#11:#141;//  "<init>":(Lscala/Function1;Lscala/io/BytePickle$SPU;Lscala/Function1;)V
const #143 = Method	#140.#142;	//  scala/io/BytePickle$$anon$7."<init>":(Lscala/Function1;Lscala/io/BytePickle$SPU;Lscala/Function1;)V
const #144 = Asciz	tag;
const #145 = Asciz	Lscala/Function1;;
const #146 = Asciz	ps$1;
const #147 = Asciz	<a:Ljava/lang/Object;>(Lscala/Function1<Ta;Ljava/lang/Integer;>;Lscala/collection/immutable/List<Lscala/Function0<Lscala/io/BytePickle$SPU<Ta;>;>;>;)Lscala/io/BytePickle$SPU<Ta;>;;
const #148 = Asciz	Signature;
const #149 = Asciz	ulist;
const #150 = Asciz	(Lscala/io/BytePickle$PU;)Lscala/io/BytePickle$PU;;
const #151 = Asciz	scala/io/BytePickle$$anonfun$ulist$1;
const #152 = class	#151;	//  scala/io/BytePickle$$anonfun$ulist$1
const #153 = Method	#152.#12;	//  scala/io/BytePickle$$anonfun$ulist$1."<init>":()V
const #154 = Asciz	scala/io/BytePickle$$anon$2;
const #155 = class	#154;	//  scala/io/BytePickle$$anon$2
const #156 = Method	#155.#12;	//  scala/io/BytePickle$$anon$2."<init>":()V
const #157 = Asciz	scala/io/BytePickle$$anonfun$ulist$2;
const #158 = class	#157;	//  scala/io/BytePickle$$anonfun$ulist$2
const #159 = Asciz	(Lscala/io/BytePickle$PU;)V;
const #160 = NameAndType	#11:#159;//  "<init>":(Lscala/io/BytePickle$PU;)V
const #161 = Method	#158.#160;	//  scala/io/BytePickle$$anonfun$ulist$2."<init>":(Lscala/io/BytePickle$PU;)V
const #162 = Asciz	scala/io/BytePickle$$anon$6;
const #163 = class	#162;	//  scala/io/BytePickle$$anon$6
const #164 = Asciz	(Lscala/Function1;Lscala/io/BytePickle$PU;Lscala/Function1;)V;
const #165 = NameAndType	#11:#164;//  "<init>":(Lscala/Function1;Lscala/io/BytePickle$PU;Lscala/Function1;)V
const #166 = Method	#163.#165;	//  scala/io/BytePickle$$anon$6."<init>":(Lscala/Function1;Lscala/io/BytePickle$PU;Lscala/Function1;)V
const #167 = Asciz	pa$5;
const #168 = Asciz	Lscala/io/BytePickle$PU;;
const #169 = Asciz	<a:Ljava/lang/Object;>(Lscala/io/BytePickle$PU<Ta;>;)Lscala/io/BytePickle$PU<Lscala/collection/immutable/List<Ta;>;>;;
const #170 = Asciz	list;
const #171 = Asciz	(Lscala/io/BytePickle$SPU;)Lscala/io/BytePickle$SPU;;
const #172 = Asciz	scala/io/BytePickle$$anonfun$list$1;
const #173 = class	#172;	//  scala/io/BytePickle$$anonfun$list$1
const #174 = Method	#173.#12;	//  scala/io/BytePickle$$anonfun$list$1."<init>":()V
const #175 = Asciz	scala/io/BytePickle$$anonfun$list$2;
const #176 = class	#175;	//  scala/io/BytePickle$$anonfun$list$2
const #177 = Asciz	(Lscala/io/BytePickle$SPU;)V;
const #178 = NameAndType	#11:#177;//  "<init>":(Lscala/io/BytePickle$SPU;)V
const #179 = Method	#176.#178;	//  scala/io/BytePickle$$anonfun$list$2."<init>":(Lscala/io/BytePickle$SPU;)V
const #180 = Asciz	pa$4;
const #181 = Asciz	Lscala/io/BytePickle$SPU;;
const #182 = Asciz	<a:Ljava/lang/Object;>(Lscala/io/BytePickle$SPU<Ta;>;)Lscala/io/BytePickle$SPU<Lscala/collection/immutable/List<Ta;>;>;;
const #183 = Asciz	fixedList;
const #184 = Asciz	(Lscala/io/BytePickle$SPU;I)Lscala/io/BytePickle$SPU;;
const #185 = Asciz	scala/collection/immutable/Nil$;
const #186 = class	#185;	//  scala/collection/immutable/Nil$
const #187 = Asciz	Lscala/collection/immutable/Nil$;;
const #188 = NameAndType	#4:#187;//  MODULE$:Lscala/collection/immutable/Nil$;
const #189 = Field	#186.#188;	//  scala/collection/immutable/Nil$.MODULE$:Lscala/collection/immutable/Nil$;
const #190 = Asciz	scala/io/BytePickle$$anon$5;
const #191 = class	#190;	//  scala/io/BytePickle$$anon$5
const #192 = Asciz	(Ljava/lang/Object;)V;
const #193 = NameAndType	#11:#192;//  "<init>":(Ljava/lang/Object;)V
const #194 = Method	#191.#193;	//  scala/io/BytePickle$$anon$5."<init>":(Ljava/lang/Object;)V
const #195 = Asciz	scala/io/BytePickle$$anonfun$fixedList$1;
const #196 = class	#195;	//  scala/io/BytePickle$$anonfun$fixedList$1
const #197 = Method	#196.#12;	//  scala/io/BytePickle$$anonfun$fixedList$1."<init>":()V
const #198 = Asciz	scala/io/BytePickle$$anonfun$fixedList$2;
const #199 = class	#198;	//  scala/io/BytePickle$$anonfun$fixedList$2
const #200 = Method	#199.#12;	//  scala/io/BytePickle$$anonfun$fixedList$2."<init>":()V
const #201 = NameAndType	#183:#184;//  fixedList:(Lscala/io/BytePickle$SPU;I)Lscala/io/BytePickle$SPU;
const #202 = Method	#10.#201;	//  scala/io/BytePickle$.fixedList:(Lscala/io/BytePickle$SPU;I)Lscala/io/BytePickle$SPU;
const #203 = Asciz	scala/io/BytePickle$$anonfun$pair$1;
const #204 = class	#203;	//  scala/io/BytePickle$$anonfun$pair$1
const #205 = Method	#204.#12;	//  scala/io/BytePickle$$anonfun$pair$1."<init>":()V
const #206 = Asciz	scala/io/BytePickle$$anonfun$pair$2;
const #207 = class	#206;	//  scala/io/BytePickle$$anonfun$pair$2
const #208 = Method	#207.#178;	//  scala/io/BytePickle$$anonfun$pair$2."<init>":(Lscala/io/BytePickle$SPU;)V
const #209 = Asciz	scala/io/BytePickle$$anonfun$wrap$1;
const #210 = class	#209;	//  scala/io/BytePickle$$anonfun$wrap$1
const #211 = Asciz	(Lscala/Function1;)V;
const #212 = NameAndType	#11:#211;//  "<init>":(Lscala/Function1;)V
const #213 = Method	#210.#212;	//  scala/io/BytePickle$$anonfun$wrap$1."<init>":(Lscala/Function1;)V
const #214 = Asciz	pa;
const #215 = Asciz	<a:Ljava/lang/Object;>(Lscala/io/BytePickle$SPU<Ta;>;I)Lscala/io/BytePickle$SPU<Lscala/collection/immutable/List<Ta;>;>;;
const #216 = Asciz	ufixedList;
const #217 = Asciz	(Lscala/io/BytePickle$PU;I)Lscala/io/BytePickle$PU;;
const #218 = Asciz	scala/io/BytePickle$$anon$4;
const #219 = class	#218;	//  scala/io/BytePickle$$anon$4
const #220 = Method	#219.#193;	//  scala/io/BytePickle$$anon$4."<init>":(Ljava/lang/Object;)V
const #221 = Asciz	scala/io/BytePickle$$anonfun$ufixedList$1;
const #222 = class	#221;	//  scala/io/BytePickle$$anonfun$ufixedList$1
const #223 = Method	#222.#12;	//  scala/io/BytePickle$$anonfun$ufixedList$1."<init>":()V
const #224 = Asciz	scala/io/BytePickle$$anonfun$ufixedList$2;
const #225 = class	#224;	//  scala/io/BytePickle$$anonfun$ufixedList$2
const #226 = Method	#225.#12;	//  scala/io/BytePickle$$anonfun$ufixedList$2."<init>":()V
const #227 = NameAndType	#216:#217;//  ufixedList:(Lscala/io/BytePickle$PU;I)Lscala/io/BytePickle$PU;
const #228 = Method	#10.#227;	//  scala/io/BytePickle$.ufixedList:(Lscala/io/BytePickle$PU;I)Lscala/io/BytePickle$PU;
const #229 = Asciz	scala/io/BytePickle$$anonfun$upair$1;
const #230 = class	#229;	//  scala/io/BytePickle$$anonfun$upair$1
const #231 = Method	#230.#12;	//  scala/io/BytePickle$$anonfun$upair$1."<init>":()V
const #232 = Asciz	scala/io/BytePickle$$anonfun$upair$2;
const #233 = class	#232;	//  scala/io/BytePickle$$anonfun$upair$2
const #234 = Method	#233.#160;	//  scala/io/BytePickle$$anonfun$upair$2."<init>":(Lscala/io/BytePickle$PU;)V
const #235 = Asciz	scala/io/BytePickle$$anonfun$uwrap$1;
const #236 = class	#235;	//  scala/io/BytePickle$$anonfun$uwrap$1
const #237 = Method	#236.#212;	//  scala/io/BytePickle$$anonfun$uwrap$1."<init>":(Lscala/Function1;)V
const #238 = Asciz	<A:Ljava/lang/Object;>(Lscala/io/BytePickle$PU<TA;>;I)Lscala/io/BytePickle$PU<Lscala/collection/immutable/List<TA;>;>;;
const #239 = Asciz	bool;
const #240 = Asciz	()Lscala/io/BytePickle$SPU;;
const #241 = Asciz	scala/io/BytePickle$$anonfun$bool$1;
const #242 = class	#241;	//  scala/io/BytePickle$$anonfun$bool$1
const #243 = Method	#242.#12;	//  scala/io/BytePickle$$anonfun$bool$1."<init>":()V
const #244 = Asciz	scala/io/BytePickle$$anonfun$bool$2;
const #245 = class	#244;	//  scala/io/BytePickle$$anonfun$bool$2
const #246 = Method	#245.#12;	//  scala/io/BytePickle$$anonfun$bool$2."<init>":()V
const #247 = Asciz	()Lscala/io/BytePickle$SPU<Ljava/lang/Boolean;>;;
const #248 = Asciz	bytearray;
const #249 = Asciz	scala/io/BytePickle$$anonfun$bytearray$1;
const #250 = class	#249;	//  scala/io/BytePickle$$anonfun$bytearray$1
const #251 = Method	#250.#12;	//  scala/io/BytePickle$$anonfun$bytearray$1."<init>":()V
const #252 = Asciz	scala/io/BytePickle$$anonfun$bytearray$2;
const #253 = class	#252;	//  scala/io/BytePickle$$anonfun$bytearray$2
const #254 = Method	#253.#12;	//  scala/io/BytePickle$$anonfun$bytearray$2."<init>":()V
const #255 = Asciz	scala/io/BytePickle$$anon$9;
const #256 = class	#255;	//  scala/io/BytePickle$$anon$9
const #257 = Method	#256.#12;	//  scala/io/BytePickle$$anon$9."<init>":()V
const #258 = Asciz	()Lscala/io/BytePickle$SPU<[B>;;
const #259 = Asciz	string;
const #260 = Asciz	scala/io/BytePickle$$anonfun$string$1;
const #261 = class	#260;	//  scala/io/BytePickle$$anonfun$string$1
const #262 = Method	#261.#12;	//  scala/io/BytePickle$$anonfun$string$1."<init>":()V
const #263 = Asciz	scala/io/BytePickle$$anonfun$string$2;
const #264 = class	#263;	//  scala/io/BytePickle$$anonfun$string$2
const #265 = Method	#264.#12;	//  scala/io/BytePickle$$anonfun$string$2."<init>":()V
const #266 = Asciz	scala/io/BytePickle$$anon$3;
const #267 = class	#266;	//  scala/io/BytePickle$$anon$3
const #268 = Method	#267.#178;	//  scala/io/BytePickle$$anon$3."<init>":(Lscala/io/BytePickle$SPU;)V
const #269 = Asciz	()Lscala/io/BytePickle$SPU<Ljava/lang/String;>;;
const #270 = Asciz	byte;
const #271 = Asciz	()Lscala/io/BytePickle$SPU<Ljava/lang/Byte;>;;
const #272 = Asciz	nat;
const #273 = Asciz	()Lscala/io/BytePickle$SPU<Ljava/lang/Integer;>;;
const #274 = Asciz	nat2Bytes;
const #275 = Asciz	(I)[B;
const #276 = Method	#105.#12;	//  scala/collection/mutable/ArrayBuffer."<init>":()V
const #277 = Asciz	scala/reflect/Manifest$;
const #278 = class	#277;	//  scala/reflect/Manifest$
const #279 = Asciz	Lscala/reflect/Manifest$;;
const #280 = NameAndType	#4:#279;//  MODULE$:Lscala/reflect/Manifest$;
const #281 = Field	#278.#280;	//  scala/reflect/Manifest$.MODULE$:Lscala/reflect/Manifest$;
const #282 = Asciz	Byte;
const #283 = NameAndType	#282:#65;//  Byte:()Ljava/lang/Object;
const #284 = Method	#278.#283;	//  scala/reflect/Manifest$.Byte:()Ljava/lang/Object;
const #285 = Asciz	scala/reflect/ClassManifest;
const #286 = class	#285;	//  scala/reflect/ClassManifest
const #287 = Asciz	scala/collection/TraversableLike;
const #288 = class	#287;	//  scala/collection/TraversableLike
const #289 = Asciz	toArray;
const #290 = Asciz	(Lscala/reflect/ClassManifest;)Ljava/lang/Object;;
const #291 = NameAndType	#289:#290;//  toArray:(Lscala/reflect/ClassManifest;)Ljava/lang/Object;
const #292 = InterfaceMethod	#288.#291;	//  scala/collection/TraversableLike.toArray:(Lscala/reflect/ClassManifest;)Ljava/lang/Object;
const #293 = Asciz	[B;
const #294 = class	#293;	//  "[B"
const #295 = Asciz	buf$1;
const #296 = Asciz	Lscala/collection/mutable/ArrayBuffer;;
const #297 = Asciz	appendByte;
const #298 = Asciz	([BI)[B;
const #299 = Asciz	scala/Array$;
const #300 = class	#299;	//  scala/Array$
const #301 = Asciz	Lscala/Array$;;
const #302 = NameAndType	#4:#301;//  MODULE$:Lscala/Array$;
const #303 = Field	#300.#302;	//  scala/Array$.MODULE$:Lscala/Array$;
const #304 = Asciz	scala/Predef$;
const #305 = class	#304;	//  scala/Predef$
const #306 = Asciz	Lscala/Predef$;;
const #307 = NameAndType	#4:#306;//  MODULE$:Lscala/Predef$;
const #308 = Field	#305.#307;	//  scala/Predef$.MODULE$:Lscala/Predef$;
const #309 = Asciz	wrapByteArray;
const #310 = Asciz	([B)Lscala/collection/mutable/WrappedArray;;
const #311 = NameAndType	#309:#310;//  wrapByteArray:([B)Lscala/collection/mutable/WrappedArray;
const #312 = Method	#305.#311;	//  scala/Predef$.wrapByteArray:([B)Lscala/collection/mutable/WrappedArray;
const #313 = Asciz	apply;
const #314 = Asciz	(BLscala/collection/Seq;)[B;
const #315 = NameAndType	#313:#314;//  apply:(BLscala/collection/Seq;)[B
const #316 = Method	#300.#315;	//  scala/Array$.apply:(BLscala/collection/Seq;)[B
const #317 = Asciz	[Ljava/lang/Object;;
const #318 = class	#317;	//  "[Ljava/lang/Object;"
const #319 = Asciz	wrapRefArray;
const #320 = Asciz	([Ljava/lang/Object;)Lscala/collection/mutable/WrappedArray;;
const #321 = NameAndType	#319:#320;//  wrapRefArray:([Ljava/lang/Object;)Lscala/collection/mutable/WrappedArray;
const #322 = Method	#305.#321;	//  scala/Predef$.wrapRefArray:([Ljava/lang/Object;)Lscala/collection/mutable/WrappedArray;
const #323 = Asciz	concat;
const #324 = Asciz	(Lscala/collection/Seq;Lscala/reflect/ClassManifest;)Ljava/lang/Object;;
const #325 = NameAndType	#323:#324;//  concat:(Lscala/collection/Seq;Lscala/reflect/ClassManifest;)Ljava/lang/Object;
const #326 = Method	#300.#325;	//  scala/Array$.concat:(Lscala/collection/Seq;Lscala/reflect/ClassManifest;)Ljava/lang/Object;
const #327 = Asciz	a;
const #328 = Asciz	wrap;
const #329 = Asciz	(Lscala/Function1;Lscala/Function1;Lscala/io/BytePickle$SPU;)Lscala/io/BytePickle$SPU;;
const #330 = Asciz	i$2;
const #331 = Asciz	j;
const #332 = Asciz	<a:Ljava/lang/Object;b:Ljava/lang/Object;>(Lscala/Function1<Ta;Tb;>;Lscala/Function1<Tb;Ta;>;Lscala/io/BytePickle$SPU<Ta;>;)Lscala/io/BytePickle$SPU<Tb;>;;
const #333 = Asciz	uwrap;
const #334 = Asciz	(Lscala/Function1;Lscala/Function1;Lscala/io/BytePickle$PU;)Lscala/io/BytePickle$PU;;
const #335 = Asciz	i$1;
const #336 = Asciz	<a:Ljava/lang/Object;b:Ljava/lang/Object;>(Lscala/Function1<Ta;Tb;>;Lscala/Function1<Tb;Ta;>;Lscala/io/BytePickle$PU<Ta;>;)Lscala/io/BytePickle$PU<Tb;>;;
const #337 = Asciz	triple;
const #338 = Asciz	(Lscala/io/BytePickle$SPU;Lscala/io/BytePickle$SPU;Lscala/io/BytePickle$SPU;)Lscala/io/BytePickle$SPU;;
const #339 = Asciz	scala/io/BytePickle$$anonfun$triple$1;
const #340 = class	#339;	//  scala/io/BytePickle$$anonfun$triple$1
const #341 = Method	#340.#12;	//  scala/io/BytePickle$$anonfun$triple$1."<init>":()V
const #342 = Asciz	scala/io/BytePickle$$anonfun$triple$2;
const #343 = class	#342;	//  scala/io/BytePickle$$anonfun$triple$2
const #344 = Asciz	(Lscala/io/BytePickle$SPU;Lscala/io/BytePickle$SPU;)V;
const #345 = NameAndType	#11:#344;//  "<init>":(Lscala/io/BytePickle$SPU;Lscala/io/BytePickle$SPU;)V
const #346 = Method	#343.#345;	//  scala/io/BytePickle$$anonfun$triple$2."<init>":(Lscala/io/BytePickle$SPU;Lscala/io/BytePickle$SPU;)V
const #347 = Asciz	pb$3;
const #348 = Asciz	pc$1;
const #349 = Asciz	<a:Ljava/lang/Object;b:Ljava/lang/Object;c:Ljava/lang/Object;>(Lscala/io/BytePickle$SPU<Ta;>;Lscala/io/BytePickle$SPU<Tb;>;Lscala/io/BytePickle$SPU<Tc;>;)Lscala/io/BytePickle$SPU<Lscala/Tuple3<Ta;Tb;Tc;>;>;;
const #350 = Asciz	pair;
const #351 = Asciz	(Lscala/io/BytePickle$SPU;Lscala/io/BytePickle$SPU;)Lscala/io/BytePickle$SPU;;
const #352 = Asciz	pb$2;
const #353 = Asciz	<a:Ljava/lang/Object;b:Ljava/lang/Object;>(Lscala/io/BytePickle$SPU<Ta;>;Lscala/io/BytePickle$SPU<Tb;>;)Lscala/io/BytePickle$SPU<Lscala/Tuple2<Ta;Tb;>;>;;
const #354 = Asciz	upair;
const #355 = Asciz	(Lscala/io/BytePickle$PU;Lscala/io/BytePickle$PU;)Lscala/io/BytePickle$PU;;
const #356 = Asciz	pb$1;
const #357 = Asciz	<a:Ljava/lang/Object;b:Ljava/lang/Object;>(Lscala/io/BytePickle$PU<Ta;>;Lscala/io/BytePickle$PU<Tb;>;)Lscala/io/BytePickle$PU<Lscala/Tuple2<Ta;Tb;>;>;;
const #358 = Asciz	sequ;
const #359 = Asciz	(Lscala/Function1;Lscala/io/BytePickle$SPU;Lscala/Function1;)Lscala/io/BytePickle$SPU;;
const #360 = Asciz	f$2;
const #361 = Asciz	pa$3;
const #362 = Asciz	k$2;
const #363 = Asciz	<t:Ljava/lang/Object;u:Ljava/lang/Object;>(Lscala/Function1<Tu;Tt;>;Lscala/io/BytePickle$SPU<Tt;>;Lscala/Function1<Tt;Lscala/io/BytePickle$SPU<Tu;>;>;)Lscala/io/BytePickle$SPU<Tu;>;;
const #364 = Asciz	usequ;
const #365 = Asciz	(Lscala/Function1;Lscala/io/BytePickle$PU;Lscala/Function1;)Lscala/io/BytePickle$PU;;
const #366 = Asciz	f$1;
const #367 = Asciz	pa$2;
const #368 = Asciz	k$1;
const #369 = Asciz	<t:Ljava/lang/Object;u:Ljava/lang/Object;>(Lscala/Function1<Tu;Tt;>;Lscala/io/BytePickle$PU<Tt;>;Lscala/Function1<Tt;Lscala/io/BytePickle$PU<Tu;>;>;)Lscala/io/BytePickle$PU<Tu;>;;
const #370 = Asciz	lift;
const #371 = Asciz	(Ljava/lang/Object;)Lscala/io/BytePickle$SPU;;
const #372 = Asciz	x$5;
const #373 = Asciz	<t:Ljava/lang/Object;>(Tt;)Lscala/io/BytePickle$SPU<Tt;>;;
const #374 = Asciz	ulift;
const #375 = Asciz	(Ljava/lang/Object;)Lscala/io/BytePickle$PU;;
const #376 = Asciz	x$4;
const #377 = Asciz	<t:Ljava/lang/Object;>(Tt;)Lscala/io/BytePickle$PU<Tt;>;;
const #378 = Asciz	share;
const #379 = Asciz	pa$1;
const #380 = Asciz	<a:Ljava/lang/Object;>(Lscala/io/BytePickle$SPU<Ta;>;)Lscala/io/BytePickle$SPU<Ta;>;;
const #381 = Asciz	unat;
const #382 = Asciz	()Lscala/io/BytePickle$PU;;
const #383 = Asciz	()Lscala/io/BytePickle$PU<Ljava/lang/Integer;>;;
const #384 = Asciz	()I;
const #385 = Asciz	refDef;
const #386 = Asciz	scala/io/BytePickle$$anon$1;
const #387 = class	#386;	//  scala/io/BytePickle$$anon$1
const #388 = Method	#387.#12;	//  scala/io/BytePickle$$anon$1."<init>":()V
const #389 = Asciz	()Lscala/io/BytePickle$PU<Lscala/io/BytePickle$RefDef;>;;
const #390 = Asciz	uunpickle;
const #391 = Asciz	(Lscala/io/BytePickle$PU;[B)Ljava/lang/Object;;
const #392 = Asciz	scala/io/BytePickle$PU;
const #393 = class	#392;	//  scala/io/BytePickle$PU
const #394 = Asciz	appU;
const #395 = Asciz	([B)Lscala/Tuple2;;
const #396 = NameAndType	#394:#395;//  appU:([B)Lscala/Tuple2;
const #397 = Method	#393.#396;	//  scala/io/BytePickle$PU.appU:([B)Lscala/Tuple2;
const #398 = Asciz	stream;
const #399 = Asciz	<T:Ljava/lang/Object;>(Lscala/io/BytePickle$PU<TT;>;[B)TT;;
const #400 = Asciz	upickle;
const #401 = Asciz	(Lscala/io/BytePickle$PU;Ljava/lang/Object;)[B;
const #402 = Asciz	appP;
const #403 = Asciz	(Ljava/lang/Object;[B)[B;
const #404 = NameAndType	#402:#403;//  appP:(Ljava/lang/Object;[B)[B
const #405 = Method	#393.#404;	//  scala/io/BytePickle$PU.appP:(Ljava/lang/Object;[B)[B
const #406 = Asciz	<T:Ljava/lang/Object;>(Lscala/io/BytePickle$PU<TT;>;TT;)[B;
const #407 = Asciz	unpickle;
const #408 = Asciz	(Lscala/io/BytePickle$SPU;[B)Ljava/lang/Object;;
const #409 = Asciz	scala/io/BytePickle$UnPicklerState;
const #410 = class	#409;	//  scala/io/BytePickle$UnPicklerState
const #411 = Asciz	scala/io/BytePickle$UnPicklerEnv;
const #412 = class	#411;	//  scala/io/BytePickle$UnPicklerEnv
const #413 = Method	#412.#12;	//  scala/io/BytePickle$UnPicklerEnv."<init>":()V
const #414 = Asciz	([BLscala/io/BytePickle$UnPicklerEnv;)V;
const #415 = NameAndType	#11:#414;//  "<init>":([BLscala/io/BytePickle$UnPicklerEnv;)V
const #416 = Method	#410.#415;	//  scala/io/BytePickle$UnPicklerState."<init>":([BLscala/io/BytePickle$UnPicklerEnv;)V
const #417 = Asciz	scala/io/BytePickle$SPU;
const #418 = class	#417;	//  scala/io/BytePickle$SPU
const #419 = Asciz	(Lscala/io/BytePickle$UnPicklerState;)Lscala/Tuple2;;
const #420 = NameAndType	#394:#419;//  appU:(Lscala/io/BytePickle$UnPicklerState;)Lscala/Tuple2;
const #421 = Method	#418.#420;	//  scala/io/BytePickle$SPU.appU:(Lscala/io/BytePickle$UnPicklerState;)Lscala/Tuple2;
const #422 = Asciz	<T:Ljava/lang/Object;>(Lscala/io/BytePickle$SPU<TT;>;[B)TT;;
const #423 = Asciz	pickle;
const #424 = Asciz	(Lscala/io/BytePickle$SPU;Ljava/lang/Object;)[B;
const #425 = Asciz	scala/io/BytePickle$PicklerState;
const #426 = class	#425;	//  scala/io/BytePickle$PicklerState
const #427 = Asciz	scala/io/BytePickle$PicklerEnv;
const #428 = class	#427;	//  scala/io/BytePickle$PicklerEnv
const #429 = Method	#428.#12;	//  scala/io/BytePickle$PicklerEnv."<init>":()V
const #430 = Asciz	([BLscala/io/BytePickle$PicklerEnv;)V;
const #431 = NameAndType	#11:#430;//  "<init>":([BLscala/io/BytePickle$PicklerEnv;)V
const #432 = Method	#426.#431;	//  scala/io/BytePickle$PicklerState."<init>":([BLscala/io/BytePickle$PicklerEnv;)V
const #433 = Asciz	(Ljava/lang/Object;Lscala/io/BytePickle$PicklerState;)Lscala/io/BytePickle$PicklerState;;
const #434 = NameAndType	#402:#433;//  appP:(Ljava/lang/Object;Lscala/io/BytePickle$PicklerState;)Lscala/io/BytePickle$PicklerState;
const #435 = Method	#418.#434;	//  scala/io/BytePickle$SPU.appP:(Ljava/lang/Object;Lscala/io/BytePickle$PicklerState;)Lscala/io/BytePickle$PicklerState;
const #436 = Asciz	()[B;
const #437 = NameAndType	#398:#436;//  stream:()[B
const #438 = Method	#426.#437;	//  scala/io/BytePickle$PicklerState.stream:()[B
const #439 = Asciz	<T:Ljava/lang/Object;>(Lscala/io/BytePickle$SPU<TT;>;TT;)[B;
const #440 = Asciz	InnerClasses;
const #441 = Asciz	scala/io/BytePickle;
const #442 = class	#441;	//  scala/io/BytePickle
const #443 = Asciz	PU;
const #444 = Asciz	scala/io/BytePickle$Def;
const #445 = class	#444;	//  scala/io/BytePickle$Def
const #446 = Asciz	Def;
const #447 = Asciz	scala/io/BytePickle$Ref;
const #448 = class	#447;	//  scala/io/BytePickle$Ref
const #449 = Asciz	Ref;
const #450 = Asciz	SPU;
const #451 = Asciz	scala/io/BytePickle$RefDef;
const #452 = class	#451;	//  scala/io/BytePickle$RefDef
const #453 = Asciz	RefDef;
const #454 = Asciz	$anon$9;
const #455 = Asciz	$anon$8;
const #456 = Asciz	$anon$7;
const #457 = Asciz	$anon$6;
const #458 = Asciz	$anon$5;
const #459 = Asciz	$anon$4;
const #460 = Asciz	$anon$3;
const #461 = Asciz	$anon$2;
const #462 = Asciz	$anon$1;
const #463 = Asciz	PicklerEnv;
const #464 = Asciz	PicklerState;
const #465 = Asciz	UnPicklerEnv;
const #466 = Asciz	UnPicklerState;
const #467 = Asciz	$anonfun$data$1;
const #468 = Asciz	$anonfun$list$2;
const #469 = Asciz	$anonfun$list$1;
const #470 = Asciz	$anonfun$bool$2;
const #471 = Asciz	$anonfun$bool$1;
const #472 = Asciz	$anonfun$wrap$1;
const #473 = Asciz	$anonfun$pair$2;
const #474 = Asciz	$anonfun$pair$1;
const #475 = Asciz	$anonfun$ulist$2;
const #476 = Asciz	$anonfun$ulist$1;
const #477 = Asciz	$anonfun$uwrap$1;
const #478 = Asciz	$anonfun$upair$2;
const #479 = Asciz	$anonfun$upair$1;
const #480 = Asciz	$anonfun$string$2;
const #481 = Asciz	$anonfun$string$1;
const #482 = Asciz	$anonfun$triple$2;
const #483 = Asciz	$anonfun$triple$1;
const #484 = Asciz	$anonfun$fixedList$2;
const #485 = Asciz	$anonfun$fixedList$1;
const #486 = Asciz	$anonfun$bytearray$2;
const #487 = Asciz	$anonfun$bytearray$1;
const #488 = Asciz	$anonfun$ufixedList$2;
const #489 = Asciz	$anonfun$ufixedList$1;
const #490 = Asciz	scala/ScalaObject;
const #491 = class	#490;	//  scala/ScalaObject

{
public static final scala.io.BytePickle$ MODULE$;

public static {};
  Code:
   Stack=1, Locals=0, Args_size=0
   0:	new	#10; //class scala/io/BytePickle$
   3:	invokespecial	#13; //Method "<init>":()V
   6:	return

public final scala.Tuple2 listToPair$2(scala.collection.immutable.List);
  Code:
   Stack=4, Locals=5, Args_size=2
   0:	aload_1
   1:	instanceof	#30; //class scala/collection/immutable/$colon$colon
   4:	ifeq	52
   7:	aload_1
   8:	checkcast	#30; //class scala/collection/immutable/$colon$colon
   11:	astore_2
   12:	aload_2
   13:	getfield	#34; //Field scala/collection/immutable/$colon$colon.scala$collection$immutable$$colon$colon$$hd:Ljava/lang/Object;
   16:	astore_3
   17:	aload_2
   18:	getfield	#38; //Field scala/collection/immutable/$colon$colon.tl:Lscala/collection/immutable/List;
   21:	astore	4
   23:	iconst_1
   24:	ifeq	38
   27:	new	#40; //class scala/Tuple2
   30:	dup
   31:	aload_3
   32:	aload	4
   34:	invokespecial	#43; //Method scala/Tuple2."<init>":(Ljava/lang/Object;Ljava/lang/Object;)V
   37:	areturn
   38:	new	#45; //class scala/MatchError
   41:	dup
   42:	aload_1
   43:	invokeinterface	#51,  1; //InterfaceMethod scala/collection/SeqLike.toString:()Ljava/lang/String;
   48:	invokespecial	#54; //Method scala/MatchError."<init>":(Ljava/lang/String;)V
   51:	athrow
   52:	new	#45; //class scala/MatchError
   55:	dup
   56:	aload_1
   57:	invokeinterface	#51,  1; //InterfaceMethod scala/collection/SeqLike.toString:()Ljava/lang/String;
   62:	invokespecial	#54; //Method scala/MatchError."<init>":(Ljava/lang/String;)V
   65:	athrow
  LineNumberTable: 
   line 305: 0
   line 304: 7
   line 21: 23
   line 305: 27

  LocalVariableTable: 
   Start  Length  Slot  Name   Signature
   0      66      0    this       Lscala/io/BytePickle$;
   0      66      1    l       Lscala/collection/immutable/List;
   12      40      2    temp26       Lscala/collection/immutable/$colon$colon;
   17      35      3    temp27       Ljava/lang/Object;
   23      29      4    temp28       Lscala/collection/immutable/List;


public final scala.collection.immutable.List pairToList$2(scala.Tuple2);
  Code:
   Stack=2, Locals=3, Args_size=2
   0:	aload_1
   1:	invokevirtual	#67; //Method scala/Tuple2._1:()Ljava/lang/Object;
   4:	astore_2
   5:	aload_1
   6:	invokevirtual	#70; //Method scala/Tuple2._2:()Ljava/lang/Object;
   9:	checkcast	#72; //class scala/collection/immutable/List
   12:	aload_2
   13:	invokevirtual	#76; //Method scala/collection/immutable/List.$colon$colon:(Ljava/lang/Object;)Lscala/collection/immutable/List;
   16:	areturn
  LineNumberTable: 
   line 303: 0

  LocalVariableTable: 
   Start  Length  Slot  Name   Signature
   0      17      0    this       Lscala/io/BytePickle$;
   0      17      1    p       Lscala/Tuple2;


public final scala.Tuple2 listToPair$1(scala.collection.immutable.List);
  Code:
   Stack=4, Locals=5, Args_size=2
   0:	aload_1
   1:	instanceof	#30; //class scala/collection/immutable/$colon$colon
   4:	ifeq	52
   7:	aload_1
   8:	checkcast	#30; //class scala/collection/immutable/$colon$colon
   11:	astore_2
   12:	aload_2
   13:	getfield	#34; //Field scala/collection/immutable/$colon$colon.scala$collection$immutable$$colon$colon$$hd:Ljava/lang/Object;
   16:	astore_3
   17:	aload_2
   18:	getfield	#38; //Field scala/collection/immutable/$colon$colon.tl:Lscala/collection/immutable/List;
   21:	astore	4
   23:	iconst_1
   24:	ifeq	38
   27:	new	#40; //class scala/Tuple2
   30:	dup
   31:	aload_3
   32:	aload	4
   34:	invokespecial	#43; //Method scala/Tuple2."<init>":(Ljava/lang/Object;Ljava/lang/Object;)V
   37:	areturn
   38:	new	#45; //class scala/MatchError
   41:	dup
   42:	aload_1
   43:	invokeinterface	#51,  1; //InterfaceMethod scala/collection/SeqLike.toString:()Ljava/lang/String;
   48:	invokespecial	#54; //Method scala/MatchError."<init>":(Ljava/lang/String;)V
   51:	athrow
   52:	new	#45; //class scala/MatchError
   55:	dup
   56:	aload_1
   57:	invokeinterface	#51,  1; //InterfaceMethod scala/collection/SeqLike.toString:()Ljava/lang/String;
   62:	invokespecial	#54; //Method scala/MatchError."<init>":(Ljava/lang/String;)V
   65:	athrow
  LineNumberTable: 
   line 294: 0
   line 293: 7
   line 21: 23
   line 294: 27

  LocalVariableTable: 
   Start  Length  Slot  Name   Signature
   0      66      0    this       Lscala/io/BytePickle$;
   0      66      1    l       Lscala/collection/immutable/List;
   12      40      2    temp22       Lscala/collection/immutable/$colon$colon;
   17      35      3    temp23       Ljava/lang/Object;
   23      29      4    temp24       Lscala/collection/immutable/List;


public final scala.collection.immutable.List pairToList$1(scala.Tuple2);
  Code:
   Stack=2, Locals=3, Args_size=2
   0:	aload_1
   1:	invokevirtual	#67; //Method scala/Tuple2._1:()Ljava/lang/Object;
   4:	astore_2
   5:	aload_1
   6:	invokevirtual	#70; //Method scala/Tuple2._2:()Ljava/lang/Object;
   9:	checkcast	#72; //class scala/collection/immutable/List
   12:	aload_2
   13:	invokevirtual	#76; //Method scala/collection/immutable/List.$colon$colon:(Ljava/lang/Object;)Lscala/collection/immutable/List;
   16:	areturn
  LineNumberTable: 
   line 292: 0

  LocalVariableTable: 
   Start  Length  Slot  Name   Signature
   0      17      0    this       Lscala/io/BytePickle$;
   0      17      1    p       Lscala/Tuple2;


public final boolean fromEnum$1(int);
  Code:
   Stack=2, Locals=2, Args_size=2
   0:	iload_1
   1:	iconst_0
   2:	if_icmpne	9
   5:	iconst_0
   6:	goto	10
   9:	iconst_1
   10:	ireturn
  LineNumberTable: 
   line 286: 0

  LocalVariableTable: 
   Start  Length  Slot  Name   Signature
   0      11      0    this       Lscala/io/BytePickle$;
   0      11      1    n       I


public final int toEnum$1(boolean);
  Code:
   Stack=1, Locals=2, Args_size=2
   0:	iload_1
   1:	ifeq	8
   4:	iconst_1
   5:	goto	9
   8:	iconst_0
   9:	ireturn
  LineNumberTable: 
   line 285: 0

  LocalVariableTable: 
   Start  Length  Slot  Name   Signature
   0      10      0    this       Lscala/io/BytePickle$;
   0      10      1    b       Z


public final java.lang.Object trd$1(scala.Tuple3);
  Code:
   Stack=1, Locals=2, Args_size=2
   0:	aload_1
   1:	invokevirtual	#118; //Method scala/Tuple3._3:()Ljava/lang/Object;
   4:	areturn
  LineNumberTable: 
   line 217: 0

  LocalVariableTable: 
   Start  Length  Slot  Name   Signature
   0      5      0    this       Lscala/io/BytePickle$;
   0      5      1    p       Lscala/Tuple3;


public final java.lang.Object snd$3(scala.Tuple3);
  Code:
   Stack=1, Locals=2, Args_size=2
   0:	aload_1
   1:	invokevirtual	#121; //Method scala/Tuple3._2:()Ljava/lang/Object;
   4:	areturn
  LineNumberTable: 
   line 216: 0

  LocalVariableTable: 
   Start  Length  Slot  Name   Signature
   0      5      0    this       Lscala/io/BytePickle$;
   0      5      1    p       Lscala/Tuple3;


public final java.lang.Object fst$3(scala.Tuple3);
  Code:
   Stack=1, Locals=2, Args_size=2
   0:	aload_1
   1:	invokevirtual	#123; //Method scala/Tuple3._1:()Ljava/lang/Object;
   4:	areturn
  LineNumberTable: 
   line 215: 0

  LocalVariableTable: 
   Start  Length  Slot  Name   Signature
   0      5      0    this       Lscala/io/BytePickle$;
   0      5      1    p       Lscala/Tuple3;


public final java.lang.Object snd$2(scala.Tuple2);
  Code:
   Stack=1, Locals=2, Args_size=2
   0:	aload_1
   1:	invokevirtual	#70; //Method scala/Tuple2._2:()Ljava/lang/Object;
   4:	areturn
  LineNumberTable: 
   line 210: 0

  LocalVariableTable: 
   Start  Length  Slot  Name   Signature
   0      5      0    this       Lscala/io/BytePickle$;
   0      5      1    p       Lscala/Tuple2;


public final java.lang.Object fst$2(scala.Tuple2);
  Code:
   Stack=1, Locals=2, Args_size=2
   0:	aload_1
   1:	invokevirtual	#67; //Method scala/Tuple2._1:()Ljava/lang/Object;
   4:	areturn
  LineNumberTable: 
   line 209: 0

  LocalVariableTable: 
   Start  Length  Slot  Name   Signature
   0      5      0    this       Lscala/io/BytePickle$;
   0      5      1    p       Lscala/Tuple2;


public final java.lang.Object snd$1(scala.Tuple2);
  Code:
   Stack=1, Locals=2, Args_size=2
   0:	aload_1
   1:	invokevirtual	#70; //Method scala/Tuple2._2:()Ljava/lang/Object;
   4:	areturn
  LineNumberTable: 
   line 204: 0

  LocalVariableTable: 
   Start  Length  Slot  Name   Signature
   0      5      0    this       Lscala/io/BytePickle$;
   0      5      1    p       Lscala/Tuple2;


public final java.lang.Object fst$1(scala.Tuple2);
  Code:
   Stack=1, Locals=2, Args_size=2
   0:	aload_1
   1:	invokevirtual	#67; //Method scala/Tuple2._1:()Ljava/lang/Object;
   4:	areturn
  LineNumberTable: 
   line 203: 0

  LocalVariableTable: 
   Start  Length  Slot  Name   Signature
   0      5      0    this       Lscala/io/BytePickle$;
   0      5      1    p       Lscala/Tuple2;


public scala.io.BytePickle$SPU data(scala.Function1, scala.collection.immutable.List);
  Code:
   Stack=5, Locals=5, Args_size=3
   0:	new	#132; //class scala/io/BytePickle$$anon$8
   3:	dup
   4:	invokespecial	#133; //Method scala/io/BytePickle$$anon$8."<init>":()V
   7:	new	#135; //class scala/io/BytePickle$$anonfun$data$1
   10:	dup
   11:	aload_2
   12:	invokespecial	#138; //Method scala/io/BytePickle$$anonfun$data$1."<init>":(Lscala/collection/immutable/List;)V
   15:	astore	4
   17:	astore_3
   18:	new	#140; //class scala/io/BytePickle$$anon$7
   21:	dup
   22:	aload_1
   23:	aload_3
   24:	aload	4
   26:	invokespecial	#143; //Method scala/io/BytePickle$$anon$7."<init>":(Lscala/Function1;Lscala/io/BytePickle$SPU;Lscala/Function1;)V
   29:	areturn
  LineNumberTable: 
   line 319: 0

  LocalVariableTable: 
   Start  Length  Slot  Name   Signature
   0      30      0    this       Lscala/io/BytePickle$;
   0      30      1    tag       Lscala/Function1;
   0      30      2    ps$1       Lscala/collection/immutable/List;

  Signature: length = 0x2
   00 FFFFFF93 

public scala.io.BytePickle$PU ulist(scala.io.BytePickle$PU);
  Code:
   Stack=5, Locals=5, Args_size=2
   0:	new	#152; //class scala/io/BytePickle$$anonfun$ulist$1
   3:	dup
   4:	invokespecial	#153; //Method scala/io/BytePickle$$anonfun$ulist$1."<init>":()V
   7:	new	#155; //class scala/io/BytePickle$$anon$2
   10:	dup
   11:	invokespecial	#156; //Method scala/io/BytePickle$$anon$2."<init>":()V
   14:	new	#158; //class scala/io/BytePickle$$anonfun$ulist$2
   17:	dup
   18:	aload_1
   19:	invokespecial	#161; //Method scala/io/BytePickle$$anonfun$ulist$2."<init>":(Lscala/io/BytePickle$PU;)V
   22:	astore	4
   24:	astore_3
   25:	astore_2
   26:	new	#163; //class scala/io/BytePickle$$anon$6
   29:	dup
   30:	aload_2
   31:	aload_3
   32:	aload	4
   34:	invokespecial	#166; //Method scala/io/BytePickle$$anon$6."<init>":(Lscala/Function1;Lscala/io/BytePickle$PU;Lscala/Function1;)V
   37:	areturn
  LineNumberTable: 
   line 316: 0

  LocalVariableTable: 
   Start  Length  Slot  Name   Signature
   0      38      0    this       Lscala/io/BytePickle$;
   0      38      1    pa$5       Lscala/io/BytePickle$PU;

  Signature: length = 0x2
   00 FFFFFFA9 

public scala.io.BytePickle$SPU list(scala.io.BytePickle$SPU);
  Code:
   Stack=5, Locals=5, Args_size=2
   0:	new	#173; //class scala/io/BytePickle$$anonfun$list$1
   3:	dup
   4:	invokespecial	#174; //Method scala/io/BytePickle$$anonfun$list$1."<init>":()V
   7:	new	#132; //class scala/io/BytePickle$$anon$8
   10:	dup
   11:	invokespecial	#133; //Method scala/io/BytePickle$$anon$8."<init>":()V
   14:	new	#176; //class scala/io/BytePickle$$anonfun$list$2
   17:	dup
   18:	aload_1
   19:	invokespecial	#179; //Method scala/io/BytePickle$$anonfun$list$2."<init>":(Lscala/io/BytePickle$SPU;)V
   22:	astore	4
   24:	astore_3
   25:	astore_2
   26:	new	#140; //class scala/io/BytePickle$$anon$7
   29:	dup
   30:	aload_2
   31:	aload_3
   32:	aload	4
   34:	invokespecial	#143; //Method scala/io/BytePickle$$anon$7."<init>":(Lscala/Function1;Lscala/io/BytePickle$SPU;Lscala/Function1;)V
   37:	areturn
  LineNumberTable: 
   line 313: 0

  LocalVariableTable: 
   Start  Length  Slot  Name   Signature
   0      38      0    this       Lscala/io/BytePickle$;
   0      38      1    pa$4       Lscala/io/BytePickle$SPU;

  Signature: length = 0x2
   00 FFFFFFB6 

public scala.io.BytePickle$SPU fixedList(scala.io.BytePickle$SPU, int);
  Code:
   Stack=7, Locals=11, Args_size=3
   0:	iload_2
   1:	iconst_0
   2:	if_icmpne	20
   5:	getstatic	#189; //Field scala/collection/immutable/Nil$.MODULE$:Lscala/collection/immutable/Nil$;
   8:	astore_3
   9:	new	#191; //class scala/io/BytePickle$$anon$5
   12:	dup
   13:	aload_3
   14:	invokespecial	#194; //Method scala/io/BytePickle$$anon$5."<init>":(Ljava/lang/Object;)V
   17:	goto	106
   20:	new	#196; //class scala/io/BytePickle$$anonfun$fixedList$1
   23:	dup
   24:	invokespecial	#197; //Method scala/io/BytePickle$$anonfun$fixedList$1."<init>":()V
   27:	new	#199; //class scala/io/BytePickle$$anonfun$fixedList$2
   30:	dup
   31:	invokespecial	#200; //Method scala/io/BytePickle$$anonfun$fixedList$2."<init>":()V
   34:	aload_0
   35:	aload_1
   36:	iload_2
   37:	iconst_1
   38:	isub
   39:	invokevirtual	#202; //Method fixedList:(Lscala/io/BytePickle$SPU;I)Lscala/io/BytePickle$SPU;
   42:	astore	4
   44:	new	#204; //class scala/io/BytePickle$$anonfun$pair$1
   47:	dup
   48:	invokespecial	#205; //Method scala/io/BytePickle$$anonfun$pair$1."<init>":()V
   51:	new	#207; //class scala/io/BytePickle$$anonfun$pair$2
   54:	dup
   55:	aload	4
   57:	invokespecial	#208; //Method scala/io/BytePickle$$anonfun$pair$2."<init>":(Lscala/io/BytePickle$SPU;)V
   60:	astore	6
   62:	astore	5
   64:	new	#140; //class scala/io/BytePickle$$anon$7
   67:	dup
   68:	aload	5
   70:	aload_1
   71:	aload	6
   73:	invokespecial	#143; //Method scala/io/BytePickle$$anon$7."<init>":(Lscala/Function1;Lscala/io/BytePickle$SPU;Lscala/Function1;)V
   76:	astore	9
   78:	astore	8
   80:	astore	7
   82:	new	#210; //class scala/io/BytePickle$$anonfun$wrap$1
   85:	dup
   86:	aload	7
   88:	invokespecial	#213; //Method scala/io/BytePickle$$anonfun$wrap$1."<init>":(Lscala/Function1;)V
   91:	astore	10
   93:	new	#140; //class scala/io/BytePickle$$anon$7
   96:	dup
   97:	aload	8
   99:	aload	9
   101:	aload	10
   103:	invokespecial	#143; //Method scala/io/BytePickle$$anon$7."<init>":(Lscala/Function1;Lscala/io/BytePickle$SPU;Lscala/Function1;)V
   106:	areturn
  LineNumberTable: 
   line 307: 0
   line 309: 20
   line 307: 106

  LocalVariableTable: 
   Start  Length  Slot  Name   Signature
   0      107      0    this       Lscala/io/BytePickle$;
   0      107      1    pa       Lscala/io/BytePickle$SPU;
   0      107      2    n       I

  Signature: length = 0x2
   00 FFFFFFD7 

public scala.io.BytePickle$PU ufixedList(scala.io.BytePickle$PU, int);
  Code:
   Stack=7, Locals=11, Args_size=3
   0:	iload_2
   1:	iconst_0
   2:	if_icmpne	20
   5:	getstatic	#189; //Field scala/collection/immutable/Nil$.MODULE$:Lscala/collection/immutable/Nil$;
   8:	astore_3
   9:	new	#219; //class scala/io/BytePickle$$anon$4
   12:	dup
   13:	aload_3
   14:	invokespecial	#220; //Method scala/io/BytePickle$$anon$4."<init>":(Ljava/lang/Object;)V
   17:	goto	106
   20:	new	#222; //class scala/io/BytePickle$$anonfun$ufixedList$1
   23:	dup
   24:	invokespecial	#223; //Method scala/io/BytePickle$$anonfun$ufixedList$1."<init>":()V
   27:	new	#225; //class scala/io/BytePickle$$anonfun$ufixedList$2
   30:	dup
   31:	invokespecial	#226; //Method scala/io/BytePickle$$anonfun$ufixedList$2."<init>":()V
   34:	aload_0
   35:	aload_1
   36:	iload_2
   37:	iconst_1
   38:	isub
   39:	invokevirtual	#228; //Method ufixedList:(Lscala/io/BytePickle$PU;I)Lscala/io/BytePickle$PU;
   42:	astore	4
   44:	new	#230; //class scala/io/BytePickle$$anonfun$upair$1
   47:	dup
   48:	invokespecial	#231; //Method scala/io/BytePickle$$anonfun$upair$1."<init>":()V
   51:	new	#233; //class scala/io/BytePickle$$anonfun$upair$2
   54:	dup
   55:	aload	4
   57:	invokespecial	#234; //Method scala/io/BytePickle$$anonfun$upair$2."<init>":(Lscala/io/BytePickle$PU;)V
   60:	astore	6
   62:	astore	5
   64:	new	#163; //class scala/io/BytePickle$$anon$6
   67:	dup
   68:	aload	5
   70:	aload_1
   71:	aload	6
   73:	invokespecial	#166; //Method scala/io/BytePickle$$anon$6."<init>":(Lscala/Function1;Lscala/io/BytePickle$PU;Lscala/Function1;)V
   76:	astore	9
   78:	astore	8
   80:	astore	7
   82:	new	#236; //class scala/io/BytePickle$$anonfun$uwrap$1
   85:	dup
   86:	aload	7
   88:	invokespecial	#237; //Method scala/io/BytePickle$$anonfun$uwrap$1."<init>":(Lscala/Function1;)V
   91:	astore	10
   93:	new	#163; //class scala/io/BytePickle$$anon$6
   96:	dup
   97:	aload	8
   99:	aload	9
   101:	aload	10
   103:	invokespecial	#166; //Method scala/io/BytePickle$$anon$6."<init>":(Lscala/Function1;Lscala/io/BytePickle$PU;Lscala/Function1;)V
   106:	areturn
  LineNumberTable: 
   line 296: 0
   line 298: 20
   line 296: 106

  LocalVariableTable: 
   Start  Length  Slot  Name   Signature
   0      107      0    this       Lscala/io/BytePickle$;
   0      107      1    pa       Lscala/io/BytePickle$PU;
   0      107      2    n       I

  Signature: length = 0x2
   00 FFFFFFEE 

public scala.io.BytePickle$SPU bool();
  Code:
   Stack=5, Locals=5, Args_size=1
   0:	new	#242; //class scala/io/BytePickle$$anonfun$bool$1
   3:	dup
   4:	invokespecial	#243; //Method scala/io/BytePickle$$anonfun$bool$1."<init>":()V
   7:	new	#245; //class scala/io/BytePickle$$anonfun$bool$2
   10:	dup
   11:	invokespecial	#246; //Method scala/io/BytePickle$$anonfun$bool$2."<init>":()V
   14:	new	#132; //class scala/io/BytePickle$$anon$8
   17:	dup
   18:	invokespecial	#133; //Method scala/io/BytePickle$$anon$8."<init>":()V
   21:	astore_3
   22:	astore_2
   23:	astore_1
   24:	new	#210; //class scala/io/BytePickle$$anonfun$wrap$1
   27:	dup
   28:	aload_1
   29:	invokespecial	#213; //Method scala/io/BytePickle$$anonfun$wrap$1."<init>":(Lscala/Function1;)V
   32:	astore	4
   34:	new	#140; //class scala/io/BytePickle$$anon$7
   37:	dup
   38:	aload_2
   39:	aload_3
   40:	aload	4
   42:	invokespecial	#143; //Method scala/io/BytePickle$$anon$7."<init>":(Lscala/Function1;Lscala/io/BytePickle$SPU;Lscala/Function1;)V
   45:	areturn
  LineNumberTable: 
   line 287: 0

  LocalVariableTable: 
   Start  Length  Slot  Name   Signature
   0      46      0    this       Lscala/io/BytePickle$;

  Signature: length = 0x2
   00 FFFFFFF7 

public scala.io.BytePickle$SPU bytearray();
  Code:
   Stack=7, Locals=9, Args_size=1
   0:	new	#250; //class scala/io/BytePickle$$anonfun$bytearray$1
   3:	dup
   4:	invokespecial	#251; //Method scala/io/BytePickle$$anonfun$bytearray$1."<init>":()V
   7:	new	#253; //class scala/io/BytePickle$$anonfun$bytearray$2
   10:	dup
   11:	invokespecial	#254; //Method scala/io/BytePickle$$anonfun$bytearray$2."<init>":()V
   14:	new	#256; //class scala/io/BytePickle$$anon$9
   17:	dup
   18:	invokespecial	#257; //Method scala/io/BytePickle$$anon$9."<init>":()V
   21:	astore_1
   22:	new	#173; //class scala/io/BytePickle$$anonfun$list$1
   25:	dup
   26:	invokespecial	#174; //Method scala/io/BytePickle$$anonfun$list$1."<init>":()V
   29:	new	#132; //class scala/io/BytePickle$$anon$8
   32:	dup
   33:	invokespecial	#133; //Method scala/io/BytePickle$$anon$8."<init>":()V
   36:	new	#176; //class scala/io/BytePickle$$anonfun$list$2
   39:	dup
   40:	aload_1
   41:	invokespecial	#179; //Method scala/io/BytePickle$$anonfun$list$2."<init>":(Lscala/io/BytePickle$SPU;)V
   44:	astore	4
   46:	astore_3
   47:	astore_2
   48:	new	#140; //class scala/io/BytePickle$$anon$7
   51:	dup
   52:	aload_2
   53:	aload_3
   54:	aload	4
   56:	invokespecial	#143; //Method scala/io/BytePickle$$anon$7."<init>":(Lscala/Function1;Lscala/io/BytePickle$SPU;Lscala/Function1;)V
   59:	astore	7
   61:	astore	6
   63:	astore	5
   65:	new	#210; //class scala/io/BytePickle$$anonfun$wrap$1
   68:	dup
   69:	aload	5
   71:	invokespecial	#213; //Method scala/io/BytePickle$$anonfun$wrap$1."<init>":(Lscala/Function1;)V
   74:	astore	8
   76:	new	#140; //class scala/io/BytePickle$$anon$7
   79:	dup
   80:	aload	6
   82:	aload	7
   84:	aload	8
   86:	invokespecial	#143; //Method scala/io/BytePickle$$anon$7."<init>":(Lscala/Function1;Lscala/io/BytePickle$SPU;Lscala/Function1;)V
   89:	areturn
  LineNumberTable: 
   line 281: 0

  LocalVariableTable: 
   Start  Length  Slot  Name   Signature
   0      90      0    this       Lscala/io/BytePickle$;

  Signature: length = 0x2
   01 02 

public scala.io.BytePickle$SPU string();
  Code:
   Stack=9, Locals=14, Args_size=1
   0:	new	#261; //class scala/io/BytePickle$$anonfun$string$1
   3:	dup
   4:	invokespecial	#262; //Method scala/io/BytePickle$$anonfun$string$1."<init>":()V
   7:	new	#264; //class scala/io/BytePickle$$anonfun$string$2
   10:	dup
   11:	invokespecial	#265; //Method scala/io/BytePickle$$anonfun$string$2."<init>":()V
   14:	new	#250; //class scala/io/BytePickle$$anonfun$bytearray$1
   17:	dup
   18:	invokespecial	#251; //Method scala/io/BytePickle$$anonfun$bytearray$1."<init>":()V
   21:	new	#253; //class scala/io/BytePickle$$anonfun$bytearray$2
   24:	dup
   25:	invokespecial	#254; //Method scala/io/BytePickle$$anonfun$bytearray$2."<init>":()V
   28:	new	#256; //class scala/io/BytePickle$$anon$9
   31:	dup
   32:	invokespecial	#257; //Method scala/io/BytePickle$$anon$9."<init>":()V
   35:	astore_1
   36:	new	#173; //class scala/io/BytePickle$$anonfun$list$1
   39:	dup
   40:	invokespecial	#174; //Method scala/io/BytePickle$$anonfun$list$1."<init>":()V
   43:	new	#132; //class scala/io/BytePickle$$anon$8
   46:	dup
   47:	invokespecial	#133; //Method scala/io/BytePickle$$anon$8."<init>":()V
   50:	new	#176; //class scala/io/BytePickle$$anonfun$list$2
   53:	dup
   54:	aload_1
   55:	invokespecial	#179; //Method scala/io/BytePickle$$anonfun$list$2."<init>":(Lscala/io/BytePickle$SPU;)V
   58:	astore	4
   60:	astore_3
   61:	astore_2
   62:	new	#140; //class scala/io/BytePickle$$anon$7
   65:	dup
   66:	aload_2
   67:	aload_3
   68:	aload	4
   70:	invokespecial	#143; //Method scala/io/BytePickle$$anon$7."<init>":(Lscala/Function1;Lscala/io/BytePickle$SPU;Lscala/Function1;)V
   73:	astore	7
   75:	astore	6
   77:	astore	5
   79:	new	#210; //class scala/io/BytePickle$$anonfun$wrap$1
   82:	dup
   83:	aload	5
   85:	invokespecial	#213; //Method scala/io/BytePickle$$anonfun$wrap$1."<init>":(Lscala/Function1;)V
   88:	astore	8
   90:	new	#140; //class scala/io/BytePickle$$anon$7
   93:	dup
   94:	aload	6
   96:	aload	7
   98:	aload	8
   100:	invokespecial	#143; //Method scala/io/BytePickle$$anon$7."<init>":(Lscala/Function1;Lscala/io/BytePickle$SPU;Lscala/Function1;)V
   103:	astore	11
   105:	astore	10
   107:	astore	9
   109:	new	#210; //class scala/io/BytePickle$$anonfun$wrap$1
   112:	dup
   113:	aload	9
   115:	invokespecial	#213; //Method scala/io/BytePickle$$anonfun$wrap$1."<init>":(Lscala/Function1;)V
   118:	astore	12
   120:	new	#140; //class scala/io/BytePickle$$anon$7
   123:	dup
   124:	aload	10
   126:	aload	11
   128:	aload	12
   130:	invokespecial	#143; //Method scala/io/BytePickle$$anon$7."<init>":(Lscala/Function1;Lscala/io/BytePickle$SPU;Lscala/Function1;)V
   133:	astore	13
   135:	new	#267; //class scala/io/BytePickle$$anon$3
   138:	dup
   139:	aload	13
   141:	invokespecial	#268; //Method scala/io/BytePickle$$anon$3."<init>":(Lscala/io/BytePickle$SPU;)V
   144:	areturn
  LineNumberTable: 
   line 275: 0
   line 276: 7
   line 277: 14
   line 274: 103

  LocalVariableTable: 
   Start  Length  Slot  Name   Signature
   0      145      0    this       Lscala/io/BytePickle$;

  Signature: length = 0x2
   01 0D 

public scala.io.BytePickle$SPU byte();
  Code:
   Stack=2, Locals=1, Args_size=1
   0:	new	#256; //class scala/io/BytePickle$$anon$9
   3:	dup
   4:	invokespecial	#257; //Method scala/io/BytePickle$$anon$9."<init>":()V
   7:	areturn
  LineNumberTable: 
   line 267: 0

  Signature: length = 0x2
   01 0F 

public scala.io.BytePickle$SPU nat();
  Code:
   Stack=2, Locals=1, Args_size=1
   0:	new	#132; //class scala/io/BytePickle$$anon$8
   3:	dup
   4:	invokespecial	#133; //Method scala/io/BytePickle$$anon$8."<init>":()V
   7:	areturn
  LineNumberTable: 
   line 247: 0

  Signature: length = 0x2
   01 11 

public byte[] nat2Bytes(int);
  Code:
   Stack=3, Locals=5, Args_size=2
   0:	new	#105; //class scala/collection/mutable/ArrayBuffer
   3:	dup
   4:	invokespecial	#276; //Method scala/collection/mutable/ArrayBuffer."<init>":()V
   7:	astore_2
   8:	iload_1
   9:	ldc	#93; //int 7
   11:	iushr
   12:	istore_3
   13:	iload_3
   14:	iconst_0
   15:	if_icmpeq	24
   18:	aload_0
   19:	iload_3
   20:	aload_2
   21:	invokespecial	#95; //Method writeNatPrefix$1:(ILscala/collection/mutable/ArrayBuffer;)V
   24:	aload_2
   25:	iload_1
   26:	ldc	#96; //int 127
   28:	iand
   29:	i2b
   30:	istore	4
   32:	iload	4
   34:	invokestatic	#103; //Method scala/runtime/BoxesRunTime.boxToByte:(B)Ljava/lang/Byte;
   37:	invokevirtual	#109; //Method scala/collection/mutable/ArrayBuffer.$plus$eq:(Ljava/lang/Object;)Lscala/collection/mutable/ArrayBuffer;
   40:	pop
   41:	aload_2
   42:	getstatic	#281; //Field scala/reflect/Manifest$.MODULE$:Lscala/reflect/Manifest$;
   45:	invokevirtual	#284; //Method scala/reflect/Manifest$.Byte:()Ljava/lang/Object;
   48:	checkcast	#286; //class scala/reflect/ClassManifest
   51:	invokeinterface	#292,  2; //InterfaceMethod scala/collection/TraversableLike.toArray:(Lscala/reflect/ClassManifest;)Ljava/lang/Object;
   56:	checkcast	#294; //class "[B"
   59:	areturn
  LineNumberTable: 
   line 235: 0
   line 241: 8
   line 242: 13
   line 244: 24
   line 243: 25
   line 244: 41

  LocalVariableTable: 
   Start  Length  Slot  Name   Signature
   0      60      0    this       Lscala/io/BytePickle$;
   0      60      1    x       I
   8      51      2    buf$1       Lscala/collection/mutable/ArrayBuffer;
   13      46      3    y       I


public byte[] appendByte(byte[], int);
  Code:
   Stack=9, Locals=3, Args_size=3
   0:	getstatic	#303; //Field scala/Array$.MODULE$:Lscala/Array$;
   3:	getstatic	#308; //Field scala/Predef$.MODULE$:Lscala/Predef$;
   6:	iconst_2
   7:	anewarray	#294; //class "[B"
   10:	dup
   11:	iconst_0
   12:	aload_1
   13:	aastore
   14:	dup
   15:	iconst_1
   16:	getstatic	#303; //Field scala/Array$.MODULE$:Lscala/Array$;
   19:	iload_2
   20:	i2b
   21:	getstatic	#308; //Field scala/Predef$.MODULE$:Lscala/Predef$;
   24:	iconst_0
   25:	newarray byte
   27:	invokevirtual	#312; //Method scala/Predef$.wrapByteArray:([B)Lscala/collection/mutable/WrappedArray;
   30:	invokevirtual	#316; //Method scala/Array$.apply:(BLscala/collection/Seq;)[B
   33:	aastore
   34:	checkcast	#318; //class "[Ljava/lang/Object;"
   37:	invokevirtual	#322; //Method scala/Predef$.wrapRefArray:([Ljava/lang/Object;)Lscala/collection/mutable/WrappedArray;
   40:	getstatic	#281; //Field scala/reflect/Manifest$.MODULE$:Lscala/reflect/Manifest$;
   43:	invokevirtual	#284; //Method scala/reflect/Manifest$.Byte:()Ljava/lang/Object;
   46:	checkcast	#286; //class scala/reflect/ClassManifest
   49:	invokevirtual	#326; //Method scala/Array$.concat:(Lscala/collection/Seq;Lscala/reflect/ClassManifest;)Ljava/lang/Object;
   52:	checkcast	#294; //class "[B"
   55:	areturn
  LineNumberTable: 
   line 232: 0

  LocalVariableTable: 
   Start  Length  Slot  Name   Signature
   0      56      0    this       Lscala/io/BytePickle$;
   0      56      1    a       [B
   0      56      2    b       I


public scala.io.BytePickle$SPU wrap(scala.Function1, scala.Function1, scala.io.BytePickle$SPU);
  Code:
   Stack=5, Locals=5, Args_size=4
   0:	new	#210; //class scala/io/BytePickle$$anonfun$wrap$1
   3:	dup
   4:	aload_1
   5:	invokespecial	#213; //Method scala/io/BytePickle$$anonfun$wrap$1."<init>":(Lscala/Function1;)V
   8:	astore	4
   10:	new	#140; //class scala/io/BytePickle$$anon$7
   13:	dup
   14:	aload_2
   15:	aload_3
   16:	aload	4
   18:	invokespecial	#143; //Method scala/io/BytePickle$$anon$7."<init>":(Lscala/Function1;Lscala/io/BytePickle$SPU;Lscala/Function1;)V
   21:	areturn
  LineNumberTable: 
   line 229: 0

  LocalVariableTable: 
   Start  Length  Slot  Name   Signature
   0      22      0    this       Lscala/io/BytePickle$;
   0      22      1    i$2       Lscala/Function1;
   0      22      2    j       Lscala/Function1;
   0      22      3    pa       Lscala/io/BytePickle$SPU;

  Signature: length = 0x2
   01 4C 

public scala.io.BytePickle$PU uwrap(scala.Function1, scala.Function1, scala.io.BytePickle$PU);
  Code:
   Stack=5, Locals=5, Args_size=4
   0:	new	#236; //class scala/io/BytePickle$$anonfun$uwrap$1
   3:	dup
   4:	aload_1
   5:	invokespecial	#237; //Method scala/io/BytePickle$$anonfun$uwrap$1."<init>":(Lscala/Function1;)V
   8:	astore	4
   10:	new	#163; //class scala/io/BytePickle$$anon$6
   13:	dup
   14:	aload_2
   15:	aload_3
   16:	aload	4
   18:	invokespecial	#166; //Method scala/io/BytePickle$$anon$6."<init>":(Lscala/Function1;Lscala/io/BytePickle$PU;Lscala/Function1;)V
   21:	areturn
  LineNumberTable: 
   line 226: 0

  LocalVariableTable: 
   Start  Length  Slot  Name   Signature
   0      22      0    this       Lscala/io/BytePickle$;
   0      22      1    i$1       Lscala/Function1;
   0      22      2    j       Lscala/Function1;
   0      22      3    pa       Lscala/io/BytePickle$PU;

  Signature: length = 0x2
   01 50 

public scala.io.BytePickle$SPU triple(scala.io.BytePickle$SPU, scala.io.BytePickle$SPU, scala.io.BytePickle$SPU);
  Code:
   Stack=5, Locals=6, Args_size=4
   0:	new	#340; //class scala/io/BytePickle$$anonfun$triple$1
   3:	dup
   4:	invokespecial	#341; //Method scala/io/BytePickle$$anonfun$triple$1."<init>":()V
   7:	new	#343; //class scala/io/BytePickle$$anonfun$triple$2
   10:	dup
   11:	aload_2
   12:	aload_3
   13:	invokespecial	#346; //Method scala/io/BytePickle$$anonfun$triple$2."<init>":(Lscala/io/BytePickle$SPU;Lscala/io/BytePickle$SPU;)V
   16:	astore	5
   18:	astore	4
   20:	new	#140; //class scala/io/BytePickle$$anon$7
   23:	dup
   24:	aload	4
   26:	aload_1
   27:	aload	5
   29:	invokespecial	#143; //Method scala/io/BytePickle$$anon$7."<init>":(Lscala/Function1;Lscala/io/BytePickle$SPU;Lscala/Function1;)V
   32:	areturn
  LineNumberTable: 
   line 219: 0
   line 220: 7
   line 219: 16

  LocalVariableTable: 
   Start  Length  Slot  Name   Signature
   0      33      0    this       Lscala/io/BytePickle$;
   0      33      1    pa       Lscala/io/BytePickle$SPU;
   0      33      2    pb$3       Lscala/io/BytePickle$SPU;
   0      33      3    pc$1       Lscala/io/BytePickle$SPU;

  Signature: length = 0x2
   01 5D 

public scala.io.BytePickle$SPU pair(scala.io.BytePickle$SPU, scala.io.BytePickle$SPU);
  Code:
   Stack=5, Locals=5, Args_size=3
   0:	new	#204; //class scala/io/BytePickle$$anonfun$pair$1
   3:	dup
   4:	invokespecial	#205; //Method scala/io/BytePickle$$anonfun$pair$1."<init>":()V
   7:	new	#207; //class scala/io/BytePickle$$anonfun$pair$2
   10:	dup
   11:	aload_2
   12:	invokespecial	#208; //Method scala/io/BytePickle$$anonfun$pair$2."<init>":(Lscala/io/BytePickle$SPU;)V
   15:	astore	4
   17:	astore_3
   18:	new	#140; //class scala/io/BytePickle$$anon$7
   21:	dup
   22:	aload_3
   23:	aload_1
   24:	aload	4
   26:	invokespecial	#143; //Method scala/io/BytePickle$$anon$7."<init>":(Lscala/Function1;Lscala/io/BytePickle$SPU;Lscala/Function1;)V
   29:	areturn
  LineNumberTable: 
   line 211: 0

  LocalVariableTable: 
   Start  Length  Slot  Name   Signature
   0      30      0    this       Lscala/io/BytePickle$;
   0      30      1    pa       Lscala/io/BytePickle$SPU;
   0      30      2    pb$2       Lscala/io/BytePickle$SPU;

  Signature: length = 0x2
   01 61 

public scala.io.BytePickle$PU upair(scala.io.BytePickle$PU, scala.io.BytePickle$PU);
  Code:
   Stack=5, Locals=5, Args_size=3
   0:	new	#230; //class scala/io/BytePickle$$anonfun$upair$1
   3:	dup
   4:	invokespecial	#231; //Method scala/io/BytePickle$$anonfun$upair$1."<init>":()V
   7:	new	#233; //class scala/io/BytePickle$$anonfun$upair$2
   10:	dup
   11:	aload_2
   12:	invokespecial	#234; //Method scala/io/BytePickle$$anonfun$upair$2."<init>":(Lscala/io/BytePickle$PU;)V
   15:	astore	4
   17:	astore_3
   18:	new	#163; //class scala/io/BytePickle$$anon$6
   21:	dup
   22:	aload_3
   23:	aload_1
   24:	aload	4
   26:	invokespecial	#166; //Method scala/io/BytePickle$$anon$6."<init>":(Lscala/Function1;Lscala/io/BytePickle$PU;Lscala/Function1;)V
   29:	areturn
  LineNumberTable: 
   line 205: 0

  LocalVariableTable: 
   Start  Length  Slot  Name   Signature
   0      30      0    this       Lscala/io/BytePickle$;
   0      30      1    pa       Lscala/io/BytePickle$PU;
   0      30      2    pb$1       Lscala/io/BytePickle$PU;

  Signature: length = 0x2
   01 65 

public scala.io.BytePickle$SPU sequ(scala.Function1, scala.io.BytePickle$SPU, scala.Function1);
  Code:
   Stack=5, Locals=4, Args_size=4
   0:	new	#140; //class scala/io/BytePickle$$anon$7
   3:	dup
   4:	aload_1
   5:	aload_2
   6:	aload_3
   7:	invokespecial	#143; //Method scala/io/BytePickle$$anon$7."<init>":(Lscala/Function1;Lscala/io/BytePickle$SPU;Lscala/Function1;)V
   10:	areturn
  LineNumberTable: 
   line 186: 0

  LocalVariableTable: 
   Start  Length  Slot  Name   Signature
   0      11      0    this       Lscala/io/BytePickle$;
   0      11      1    f$2       Lscala/Function1;
   0      11      2    pa$3       Lscala/io/BytePickle$SPU;
   0      11      3    k$2       Lscala/Function1;

  Signature: length = 0x2
   01 6B 

public scala.io.BytePickle$PU usequ(scala.Function1, scala.io.BytePickle$PU, scala.Function1);
  Code:
   Stack=5, Locals=4, Args_size=4
   0:	new	#163; //class scala/io/BytePickle$$anon$6
   3:	dup
   4:	aload_1
   5:	aload_2
   6:	aload_3
   7:	invokespecial	#166; //Method scala/io/BytePickle$$anon$6."<init>":(Lscala/Function1;Lscala/io/BytePickle$PU;Lscala/Function1;)V
   10:	areturn
  LineNumberTable: 
   line 169: 0

  LocalVariableTable: 
   Start  Length  Slot  Name   Signature
   0      11      0    this       Lscala/io/BytePickle$;
   0      11      1    f$1       Lscala/Function1;
   0      11      2    pa$2       Lscala/io/BytePickle$PU;
   0      11      3    k$1       Lscala/Function1;

  Signature: length = 0x2
   01 71 

public scala.io.BytePickle$SPU lift(java.lang.Object);
  Code:
   Stack=3, Locals=2, Args_size=2
   0:	new	#191; //class scala/io/BytePickle$$anon$5
   3:	dup
   4:	aload_1
   5:	invokespecial	#194; //Method scala/io/BytePickle$$anon$5."<init>":(Ljava/lang/Object;)V
   8:	areturn
  LineNumberTable: 
   line 162: 0

  LocalVariableTable: 
   Start  Length  Slot  Name   Signature
   0      9      0    this       Lscala/io/BytePickle$;
   0      9      1    x$5       Ljava/lang/Object;

  Signature: length = 0x2
   01 75 

public scala.io.BytePickle$PU ulift(java.lang.Object);
  Code:
   Stack=3, Locals=2, Args_size=2
   0:	new	#219; //class scala/io/BytePickle$$anon$4
   3:	dup
   4:	aload_1
   5:	invokespecial	#220; //Method scala/io/BytePickle$$anon$4."<init>":(Ljava/lang/Object;)V
   8:	areturn
  LineNumberTable: 
   line 155: 0

  LocalVariableTable: 
   Start  Length  Slot  Name   Signature
   0      9      0    this       Lscala/io/BytePickle$;
   0      9      1    x$4       Ljava/lang/Object;

  Signature: length = 0x2
   01 79 

public scala.io.BytePickle$SPU share(scala.io.BytePickle$SPU);
  Code:
   Stack=3, Locals=2, Args_size=2
   0:	new	#267; //class scala/io/BytePickle$$anon$3
   3:	dup
   4:	aload_1
   5:	invokespecial	#268; //Method scala/io/BytePickle$$anon$3."<init>":(Lscala/io/BytePickle$SPU;)V
   8:	areturn
  LineNumberTable: 
   line 98: 0

  LocalVariableTable: 
   Start  Length  Slot  Name   Signature
   0      9      0    this       Lscala/io/BytePickle$;
   0      9      1    pa$1       Lscala/io/BytePickle$SPU;

  Signature: length = 0x2
   01 7C 

public scala.io.BytePickle$PU unat();
  Code:
   Stack=2, Locals=1, Args_size=1
   0:	new	#155; //class scala/io/BytePickle$$anon$2
   3:	dup
   4:	invokespecial	#156; //Method scala/io/BytePickle$$anon$2."<init>":()V
   7:	areturn
  LineNumberTable: 
   line 79: 0

  Signature: length = 0x2
   01 7F 

public int DEF();
  Code:
   Stack=1, Locals=1, Args_size=1
   0:	aload_0
   1:	getfield	#26; //Field DEF:I
   4:	ireturn
  LineNumberTable: 
   line 77: 0


public int REF();
  Code:
   Stack=1, Locals=1, Args_size=1
   0:	aload_0
   1:	getfield	#24; //Field REF:I
   4:	ireturn
  LineNumberTable: 
   line 76: 0


public scala.io.BytePickle$PU refDef();
  Code:
   Stack=2, Locals=1, Args_size=1
   0:	new	#387; //class scala/io/BytePickle$$anon$1
   3:	dup
   4:	invokespecial	#388; //Method scala/io/BytePickle$$anon$1."<init>":()V
   7:	areturn
  LineNumberTable: 
   line 65: 0

  Signature: length = 0x2
   01 FFFFFF85 

public java.lang.Object uunpickle(scala.io.BytePickle$PU, byte[]);
  Code:
   Stack=2, Locals=3, Args_size=3
   0:	aload_1
   1:	aload_2
   2:	invokevirtual	#397; //Method scala/io/BytePickle$PU.appU:([B)Lscala/Tuple2;
   5:	invokevirtual	#67; //Method scala/Tuple2._1:()Ljava/lang/Object;
   8:	areturn
  LineNumberTable: 
   line 46: 0

  LocalVariableTable: 
   Start  Length  Slot  Name   Signature
   0      9      0    this       Lscala/io/BytePickle$;
   0      9      1    p       Lscala/io/BytePickle$PU;
   0      9      2    stream       [B

  Signature: length = 0x2
   01 FFFFFF8F 

public byte[] upickle(scala.io.BytePickle$PU, java.lang.Object);
  Code:
   Stack=3, Locals=3, Args_size=3
   0:	aload_1
   1:	aload_2
   2:	iconst_0
   3:	newarray byte
   5:	invokevirtual	#405; //Method scala/io/BytePickle$PU.appP:(Ljava/lang/Object;[B)[B
   8:	areturn
  LineNumberTable: 
   line 43: 0

  LocalVariableTable: 
   Start  Length  Slot  Name   Signature
   0      9      0    this       Lscala/io/BytePickle$;
   0      9      1    p       Lscala/io/BytePickle$PU;
   0      9      2    a       Ljava/lang/Object;

  Signature: length = 0x2
   01 FFFFFF96 

public java.lang.Object unpickle(scala.io.BytePickle$SPU, byte[]);
  Code:
   Stack=6, Locals=3, Args_size=3
   0:	aload_1
   1:	new	#410; //class scala/io/BytePickle$UnPicklerState
   4:	dup
   5:	aload_2
   6:	new	#412; //class scala/io/BytePickle$UnPicklerEnv
   9:	dup
   10:	invokespecial	#413; //Method scala/io/BytePickle$UnPicklerEnv."<init>":()V
   13:	invokespecial	#416; //Method scala/io/BytePickle$UnPicklerState."<init>":([BLscala/io/BytePickle$UnPicklerEnv;)V
   16:	invokevirtual	#421; //Method scala/io/BytePickle$SPU.appU:(Lscala/io/BytePickle$UnPicklerState;)Lscala/Tuple2;
   19:	invokevirtual	#67; //Method scala/Tuple2._1:()Ljava/lang/Object;
   22:	areturn
  LineNumberTable: 
   line 35: 0

  LocalVariableTable: 
   Start  Length  Slot  Name   Signature
   0      23      0    this       Lscala/io/BytePickle$;
   0      23      1    p       Lscala/io/BytePickle$SPU;
   0      23      2    stream       [B

  Signature: length = 0x2
   01 FFFFFFA6 

public byte[] pickle(scala.io.BytePickle$SPU, java.lang.Object);
  Code:
   Stack=7, Locals=3, Args_size=3
   0:	aload_1
   1:	aload_2
   2:	new	#426; //class scala/io/BytePickle$PicklerState
   5:	dup
   6:	iconst_0
   7:	newarray byte
   9:	new	#428; //class scala/io/BytePickle$PicklerEnv
   12:	dup
   13:	invokespecial	#429; //Method scala/io/BytePickle$PicklerEnv."<init>":()V
   16:	invokespecial	#432; //Method scala/io/BytePickle$PicklerState."<init>":([BLscala/io/BytePickle$PicklerEnv;)V
   19:	invokevirtual	#435; //Method scala/io/BytePickle$SPU.appP:(Ljava/lang/Object;Lscala/io/BytePickle$PicklerState;)Lscala/io/BytePickle$PicklerState;
   22:	invokevirtual	#438; //Method scala/io/BytePickle$PicklerState.stream:()[B
   25:	areturn
  LineNumberTable: 
   line 32: 0

  LocalVariableTable: 
   Start  Length  Slot  Name   Signature
   0      26      0    this       Lscala/io/BytePickle$;
   0      26      1    p       Lscala/io/BytePickle$SPU;
   0      26      2    a       Ljava/lang/Object;

  Signature: length = 0x2
   01 FFFFFFB7 

}

