Compiled from "BytePickle.scala"
public final class scala.io.BytePickle$Ref$ extends java.lang.Object implements scala.Function0,scala.ScalaObject
  SourceFile: "BytePickle.scala"
  Scala: length = 0x
   
  InnerClass: 
   public Ref=class scala/io/BytePickle$Ref of class scala/io/BytePickle
  minor version: 0
  major version: 49
  Constant pool:
Asciz	SourceFile;
Asciz	BytePickle.scala;
Asciz	Scala;
Asciz	MODULE$;
Asciz	Lscala/io/BytePickle$Ref$;;
Asciz	<clinit>;
Asciz	()V;
Asciz	Code;
Asciz	scala/io/BytePickle$Ref$;
class	scala/io/BytePickle$Ref$
Asciz	<init>;
NameAndType	"<init>":()V
Method	scala/io/BytePickle$Ref$."<init>":()V
Asciz	toString;
Asciz	()Ljava/lang/String;;
Asciz	LineNumberTable;
Asciz	scala/Function0$class;
class	scala/Function0$class
Asciz	(Lscala/Function0;)Ljava/lang/String;;
NameAndType	toString:(Lscala/Function0;)Ljava/lang/String;
Method	scala/Function0$class.toString:(Lscala/Function0;)Ljava/lang/String;
Asciz	unapply;
Asciz	(Lscala/io/BytePickle$Ref;)Z;
Asciz	java/lang/Object;
class	java/lang/Object
Asciz	equals;
Asciz	(Ljava/lang/Object;)Z;
NameAndType	equals:(Ljava/lang/Object;)Z
Method	java/lang/Object.equals:(Ljava/lang/Object;)Z
Asciz	this;
Asciz	x$0;
Asciz	Lscala/io/BytePickle$Ref;;
Asciz	LocalVariableTable;
Asciz	apply;
Asciz	()Lscala/io/BytePickle$Ref;;
Asciz	scala/io/BytePickle$Ref;
class	scala/io/BytePickle$Ref
Method	scala/io/BytePickle$Ref."<init>":()V
Asciz	()Ljava/lang/Object;;
NameAndType	apply:()Lscala/io/BytePickle$Ref;
Method	scala/io/BytePickle$Ref$.apply:()Lscala/io/BytePickle$Ref;
Method	java/lang/Object."<init>":()V
NameAndType	MODULE$:Lscala/io/BytePickle$Ref$;
Field	scala/io/BytePickle$Ref$.MODULE$:Lscala/io/BytePickle$Ref$;
Asciz	$init$;
Asciz	(Lscala/Function0;)V;
NameAndType	$init$:(Lscala/Function0;)V
Method	scala/Function0$class.$init$:(Lscala/Function0;)V
Asciz	InnerClasses;
Asciz	scala/io/BytePickle;
class	scala/io/BytePickle
Asciz	Ref;
Asciz	scala/Function0;
class	scala/Function0
Asciz	scala/ScalaObject;
class	scala/ScalaObject

{
public static final scala.io.BytePickle$Ref$ MODULE$;
  Signature: Lscala/io/BytePickle$Ref$;

public static {};
  Signature: ()V
  Code:
   Stack=1, Locals=0, Args_size=0
	new	class scala/io/BytePickle$Ref$
	invokespecial	Method "<init>":()V
	return
  Labels:

public java.lang.String toString();
  Signature: ()Ljava/lang/String;
  Code:
   Stack=1, Locals=1, Args_size=1
	aload_0
	invokestatic	Method scala/Function0$class.toString:(Lscala/Function0;)Ljava/lang/String;
	areturn
  Labels:

public boolean unapply(scala.io.BytePickle$Ref);
  Signature: (Lscala/io/BytePickle$Ref;)Z
  Code:
   Stack=2, Locals=3, Args_size=2
	aload_1
	dup
	astore_2
	ifnull	l1 // iconst_0
	aload_2
	aconst_null
	invokevirtual	Method java/lang/Object.equals:(Ljava/lang/Object;)Z
	ifeq	l2 // iconst_1
l1	iconst_0
	goto	l3 // ireturn
l2	iconst_1
l3	ireturn
  Labels:
   	l1 = 14 // iconst_0
   	l2 = 18 // iconst_1
   	l3 = 19 // ireturn
  LocalVariableTable: 
   Start  Length  Slot  Name   Signature
   0      20      0    this       Lscala/io/BytePickle$Ref$;
   0      20      1    x$0       Lscala/io/BytePickle$Ref;


public scala.io.BytePickle$Ref apply();
  Signature: ()Lscala/io/BytePickle$Ref;
  Code:
   Stack=2, Locals=1, Args_size=1
	new	class scala/io/BytePickle$Ref
	dup
	invokespecial	Method scala/io/BytePickle$Ref."<init>":()V
	areturn
  Labels:

public java.lang.Object apply();
  Signature: ()Ljava/lang/Object;
  Code:
   Stack=1, Locals=1, Args_size=1
	aload_0
	invokevirtual	Method apply:()Lscala/io/BytePickle$Ref;
	areturn
  Labels:

public scala.io.BytePickle$Ref$();
  Signature: ()V
  Code:
   Stack=1, Locals=1, Args_size=1
	aload_0
	invokespecial	Method java/lang/Object."<init>":()V
	aload_0
	putstatic	Field MODULE$:Lscala/io/BytePickle$Ref$;
	aload_0
	invokestatic	Method scala/Function0$class.$init$:(Lscala/Function0;)V
	return
  Labels:

}

