Compiled from "BytePickle.scala"
public final class scala.io.BytePickle extends java.lang.Object
  SourceFile: "BytePickle.scala"
  ScalaSig: length = 0x10A0
   05 00 FFFFFF84 3A 07 05 01 02 FFFFFF88 02 07 01 0A 42 79 74
   65 50 69 63 6B 6C 65 0A 02 03 04 01 02 69 6F 0A
   01 05 01 05 73 63 61 6C 61 03 00 10 02 08 09 0D
   01 02 06 08 0A 02 FFFFFF84 FFFFFF80 FFFFFF80 FFFFFF88 02 0B 02 0A 42 79
   74 65 50 69 63 6B 6C 65 13 03 09 0C 14 10 02 0D
   12 0D 01 0E 0A 02 0F 10 01 04 6C 61 6E 67 0A 01
   11 01 04 6A 61 76 61 09 02 13 0E 02 06 4F 62 6A
   65 63 74 10 02 15 16 0D 01 04 09 02 17 04 02 0B
   53 63 61 6C 61 4F 62 6A 65 63 74 08 05 19 09 FFFFFF84
   00 1A 01 06 3C 69 6E 69 74 3E 14 01 07 06 05 1C
   09 FFFFFF81 00 1D 02 03 53 50 55 15 02 1E 25 13 03 1B
   0C 14 08 05 19 1B FFFFFF84 00 20 14 01 21 10 03 22 1B
   23 0D 01 09 10 02 24 25 0C 00 04 08 26 1B FFFFFF84 FFFFFF80
   FFFFFF80 FFFFFFC2 00 27 02 01 54 11 02 28 2B 10 02 15 29 09
   02 2A 04 02 07 4E 6F 74 68 69 6E 67 10 02 15 2C
   09 02 2D 04 02 03 41 6E 79 08 05 2F 1B FFFFFF86 00 30
   01 04 61 70 70 50 14 03 31 6A 6C 10 02 22 32 06
   08 33 09 FFFFFF84 FFFFFF80 FFFFFF80 FFFFFF80 00 34 02 0C 50 69 63 6B 6C
   65 72 53 74 61 74 65 13 03 32 0C 14 08 08 36 32
   FFFFFF82 FFFFFFC2 FFFFFF80 FFFFFF84 00 37 01 06 73 74 72 65 61 6D 15 01
   38 10 03 15 39 3B 09 02 3A 04 02 05 41 72 72 61
   79 10 02 15 3C 09 02 3D 04 02 04 42 79 74 65 08
   08 3F 32 FFFFFF82 FFFFFF80 FFFFFFA0 FFFFFF80 04 38 01 07 73 74 72 65 61
   6D 20 08 08 41 32 FFFFFF82 FFFFFFC2 FFFFFF80 FFFFFF84 00 42 01 04 64 69
   63 74 15 01 43 10 02 22 44 06 08 45 09 FFFFFF84 FFFFFF80 FFFFFF80
   FFFFFF80 00 46 02 0A 50 69 63 6B 6C 65 72 45 6E 76 13
   03 44 47 14 10 04 48 4D 2B 4F 0D 01 49 0A 02 4A
   4B 01 07 6D 75 74 61 62 6C 65 0A 02 4C 04 01 0A
   63 6F 6C 6C 65 63 74 69 6F 6E 09 02 4E 49 02 07
   48 61 73 68 4D 61 70 10 02 15 50 09 02 51 04 02
   03 49 6E 74 08 05 19 44 FFFFFF84 00 53 14 01 43 08 07
   55 44 FFFFFFC0 FFFFFF80 FFFFFF84 04 56 01 03 63 6E 74 15 01 4F 08
   07 58 44 FFFFFFC0 FFFFFF80 FFFFFF84 04 59 01 07 63 6E 74 5F 24 65
   71 14 02 5A 5D 10 02 15 5B 09 02 5C 04 02 04 55
   6E 69 74 08 07 5E 57 FFFFFF81 FFFFFF80 FFFFFFC0 00 4F 01 03 78 24
   31 08 06 60 44 FFFFFFA0 FFFFFFA0 04 4F 01 04 63 6E 74 20 08
   05 62 44 FFFFFF84 00 63 01 07 6E 65 78 74 4C 6F 63 14
   01 4F 08 08 65 32 FFFFFF82 FFFFFF80 FFFFFFA0 FFFFFF80 04 43 01 05 64 69
   63 74 20 08 05 19 32 FFFFFF84 00 67 14 03 31 68 69 08
   05 36 66 FFFFFFC0 00 38 08 05 41 66 FFFFFFC0 00 43 08 05 6B
   2E FFFFFFC0 00 23 01 01 61 08 05 6D 2E FFFFFFC0 00 31 01 05
   73 74 61 74 65 08 05 6F 1B FFFFFF86 00 70 01 04 61 70
   70 55 14 03 71 FFFFFF81 0E 10 04 15 72 23 74 09 02 73
   04 02 06 54 75 70 6C 65 32 10 02 22 75 06 08 76
   09 FFFFFF84 FFFFFF80 FFFFFF80 FFFFFF80 00 77 02 0E 55 6E 50 69 63 6B 6C
   65 72 53 74 61 74 65 13 03 75 0C 14 08 08 36 75
   FFFFFF82 FFFFFFC2 FFFFFF80 FFFFFF84 00 37 08 08 3F 75 FFFFFF82 FFFFFF80 FFFFFFA0 FFFFFF80 04 38
   08 08 41 75 FFFFFF82 FFFFFFC2 FFFFFF80 FFFFFF84 00 7B 15 01 7C 10 02 22
   7D 06 08 7E 09 FFFFFF84 FFFFFF80 FFFFFF80 FFFFFF80 00 7F 02 0C 55 6E 50
   69 63 6B 6C 65 72 45 6E 76 13 04 7D FFFFFF81 00 14 10
   04 48 4D 4F 2B 08 06 19 7D FFFFFF84 00 FFFFFF81 02 14 01 7C
   08 07 55 7D FFFFFFC0 FFFFFF80 FFFFFF84 04 56 08 08 58 7D FFFFFFC0 FFFFFF80 FFFFFF84
   04 FFFFFF81 05 14 03 5A FFFFFF81 06 08 08 5E FFFFFF81 04 FFFFFF81 FFFFFF80 FFFFFFC0
   00 4F 08 06 60 7D FFFFFFA0 FFFFFFA0 04 4F 08 05 62 7D FFFFFF84 00
   63 08 08 65 75 FFFFFF82 FFFFFF80 FFFFFFA0 FFFFFF80 04 7C 08 06 19 75 FFFFFF84
   00 FFFFFF81 0B 14 05 74 FFFFFF81 0C FFFFFF81 0D 08 06 36 FFFFFF81 0A FFFFFFC0
   00 38 08 06 41 FFFFFF81 0A FFFFFFC0 00 7C 08 05 6D 6E FFFFFFC0 00
   74 08 07 FFFFFF81 10 09 FFFFFF84 00 FFFFFF81 11 01 06 70 69 63 6B
   6C 65 15 04 FFFFFF81 12 FFFFFF81 17 14 05 38 FFFFFF81 13 FFFFFF81 18 08
   08 FFFFFF81 14 FFFFFF81 0F FFFFFFC0 00 FFFFFF81 15 01 01 70 10 04 22 1B
   FFFFFF81 16 10 03 24 FFFFFF81 17 04 09 26 FFFFFF81 0F FFFFFF84 FFFFFF80 FFFFFF80 FFFFFFC2
   00 27 08 07 6B FFFFFF81 0F FFFFFFC0 00 FFFFFF81 16 08 07 FFFFFF81 1A 09
   FFFFFF84 00 FFFFFF81 1B 01 08 75 6E 70 69 63 6B 6C 65 15 04
   FFFFFF81 1C FFFFFF81 1E 14 06 FFFFFF81 1D FFFFFF81 1F FFFFFF81 21 10 03 24 FFFFFF81
   1E 04 09 26 FFFFFF81 19 FFFFFF84 FFFFFF80 FFFFFF80 FFFFFFC2 00 27 08 08 FFFFFF81 14
   FFFFFF81 19 FFFFFFC0 00 FFFFFF81 20 10 04 22 1B FFFFFF81 1D 08 06 36 FFFFFF81
   19 FFFFFFC0 00 38 06 07 FFFFFF81 23 09 FFFFFF81 00 FFFFFF81 24 02 02 50
   55 15 04 FFFFFF81 25 FFFFFF81 2A 13 04 FFFFFF81 22 0C 14 08 07 19
   FFFFFF81 22 FFFFFF84 00 FFFFFF81 27 14 02 FFFFFF81 28 10 05 22 FFFFFF81 22 FFFFFF81
   29 10 03 24 FFFFFF81 2A 04 09 26 FFFFFF81 22 FFFFFF84 FFFFFF80 FFFFFF80 FFFFFFC2 00
   27 08 07 2F FFFFFF81 22 FFFFFF86 00 FFFFFF81 2C 14 05 38 FFFFFF81 2D FFFFFF81
   2E 08 07 6B FFFFFF81 2B FFFFFFC0 00 FFFFFF81 29 08 06 6D FFFFFF81 2B FFFFFFC0
   00 38 08 07 6F FFFFFF81 22 FFFFFF86 00 FFFFFF81 30 14 04 FFFFFF81 31 FFFFFF81
   32 10 05 15 72 FFFFFF81 29 38 08 06 6D FFFFFF81 2F FFFFFFC0 00 38
   08 07 FFFFFF81 34 09 FFFFFF84 00 FFFFFF81 35 01 07 75 70 69 63 6B
   6C 65 15 04 FFFFFF81 36 FFFFFF81 3A 14 05 38 FFFFFF81 37 FFFFFF81 3B 08
   08 FFFFFF81 14 FFFFFF81 33 FFFFFFC0 00 FFFFFF81 38 10 05 22 FFFFFF81 22 FFFFFF81 39
   10 03 24 FFFFFF81 3A 04 09 26 FFFFFF81 33 FFFFFF84 FFFFFF80 FFFFFF80 FFFFFFC2 00 27
   08 07 6B FFFFFF81 33 FFFFFFC0 00 FFFFFF81 39 08 07 FFFFFF81 3D 09 FFFFFF84 00
   FFFFFF81 3E 01 09 75 75 6E 70 69 63 6B 6C 65 15 04 FFFFFF81
   3F FFFFFF81 41 14 06 FFFFFF81 40 FFFFFF81 42 FFFFFF81 44 10 03 24 FFFFFF81 41
   04 09 26 FFFFFF81 3C FFFFFF84 FFFFFF80 FFFFFF80 FFFFFFC2 00 27 08 08 FFFFFF81 14 FFFFFF81
   3C FFFFFFC0 00 FFFFFF81 43 10 05 22 FFFFFF81 22 FFFFFF81 40 08 06 36 FFFFFF81
   3C FFFFFFC0 00 38 06 0A FFFFFF81 46 09 FFFFFF84 FFFFFF80 FFFFFF80 FFFFFF81 00 FFFFFF81 47
   02 06 52 65 66 44 65 66 13 04 FFFFFF81 45 0C 14 08 07
   19 FFFFFF81 45 FFFFFF84 00 FFFFFF81 49 14 02 FFFFFF81 4A 10 03 22 FFFFFF81 45
   06 0A FFFFFF81 4C 09 FFFFFF84 FFFFFF80 FFFFFF80 FFFFFF80 40 FFFFFF81 4D 02 03 52 65
   66 13 07 FFFFFF81 4B FFFFFF81 4A 14 FFFFFF81 4E 10 03 15 FFFFFF81 4F 09
   03 FFFFFF81 50 04 02 07 50 72 6F 64 75 63 74 08 07 19
   FFFFFF81 4B FFFFFF84 00 FFFFFF81 52 14 02 FFFFFF81 53 10 03 22 FFFFFF81 4B 08
   0A FFFFFF81 55 FFFFFF81 4B FFFFFF84 FFFFFF80 FFFFFF80 FFFFFF84 20 63 01 08 68 61 73
   68 43 6F 64 65 08 0B FFFFFF81 57 FFFFFF81 4B FFFFFF84 FFFFFF80 FFFFFF80 FFFFFF84 20
   FFFFFF81 58 01 08 74 6F 53 74 72 69 6E 67 14 02 FFFFFF81 59
   10 04 FFFFFF81 5A FFFFFF81 5D 0E 03 15 FFFFFF81 5B 09 03 FFFFFF81 5C 04
   01 06 50 72 65 64 65 66 09 04 FFFFFF81 5E FFFFFF81 5F 02 06
   53 74 72 69 6E 67 0A 03 FFFFFF81 5C 04 08 0B FFFFFF81 61 FFFFFF81
   4B FFFFFF84 FFFFFF80 FFFFFF80 FFFFFF84 20 FFFFFF81 62 01 06 65 71 75 61 6C 73
   14 04 FFFFFF81 63 FFFFFF81 66 10 03 15 FFFFFF81 64 09 03 FFFFFF81 65 04
   02 07 42 6F 6F 6C 65 61 6E 08 08 5E FFFFFF81 60 FFFFFF81 FFFFFF80
   FFFFFFC0 00 2B 08 0B FFFFFF81 68 FFFFFF81 4B FFFFFF84 FFFFFF80 FFFFFF80 FFFFFF84 20 FFFFFF81 69
   01 0D 70 72 6F 64 75 63 74 50 72 65 66 69 78 15
   02 FFFFFF81 6A 10 03 0D FFFFFF81 6B 09 03 FFFFFF81 5E 0E 08 0A FFFFFF81
   6D FFFFFF81 4B FFFFFF84 FFFFFF80 FFFFFF80 FFFFFF84 20 56 01 0C 70 72 6F 64 75
   63 74 41 72 69 74 79 08 0B FFFFFF81 6F FFFFFF81 4B FFFFFF84 FFFFFF80 FFFFFF80
   FFFFFF84 20 FFFFFF81 70 01 0E 70 72 6F 64 75 63 74 45 6C 65
   6D 65 6E 74 14 03 2B FFFFFF81 71 08 08 5E FFFFFF81 6E FFFFFF81 FFFFFF80
   FFFFFFC0 00 4F 08 0B FFFFFF81 73 FFFFFF81 4B FFFFFF84 FFFFFF80 FFFFFF80 FFFFFF84 20 FFFFFF81 74
   01 12 70 72 6F 64 75 63 74 45 6C 65 6D 65 6E 74
   4E 61 6D 65 14 04 FFFFFF81 6A FFFFFF81 75 08 08 5E FFFFFF81 72 FFFFFF81
   FFFFFF80 FFFFFFC0 00 4F 08 0B FFFFFF81 77 FFFFFF81 4B FFFFFF84 FFFFFF80 FFFFFF80 FFFFFF84 20 FFFFFF81
   78 01 08 63 61 6E 45 71 75 61 6C 14 04 FFFFFF81 63 FFFFFF81
   79 08 08 5E FFFFFF81 76 FFFFFF81 FFFFFF80 FFFFFFC0 00 2B 28 04 FFFFFF81 4B FFFFFF81
   7B 10 03 15 FFFFFF81 7C 09 03 FFFFFF81 7D 04 02 0C 73 65 72
   69 61 6C 69 7A 61 62 6C 65 07 09 FFFFFF81 7F 09 FFFFFF81 FFFFFF80
   FFFFFF88 02 FFFFFF82 00 01 03 52 65 66 10 03 22 FFFFFF82 01 06 0A
   FFFFFF81 4C 09 FFFFFF84 FFFFFF81 FFFFFF80 FFFFFF88 02 FFFFFF82 02 13 06 FFFFFF82 01 0C FFFFFF82
   03 14 10 05 15 FFFFFF82 04 FFFFFF81 53 09 03 FFFFFF82 05 04 02 09
   46 75 6E 63 74 69 6F 6E 30 08 07 19 FFFFFF82 01 FFFFFF84 00
   FFFFFF82 07 14 02 FFFFFF82 00 08 0A FFFFFF82 09 FFFFFF82 01 FFFFFF81 FFFFFF80 FFFFFF84 40
   FFFFFF81 52 01 05 61 70 70 6C 79 08 0A FFFFFF82 0B FFFFFF82 01 FFFFFF81
   FFFFFF80 FFFFFF84 40 FFFFFF82 0C 01 07 75 6E 61 70 70 6C 79 14 04
   FFFFFF81 63 FFFFFF82 0D 08 08 FFFFFF82 0E FFFFFF82 0A FFFFFFC0 00 FFFFFF81 53 01 03
   78 24 30 06 0A FFFFFF82 10 09 FFFFFF84 FFFFFF80 FFFFFF80 FFFFFF80 40 FFFFFF82 11 02
   03 44 65 66 13 07 FFFFFF82 0F FFFFFF81 4A 14 FFFFFF81 4E 08 07 19
   FFFFFF82 0F FFFFFF84 00 FFFFFF82 13 14 02 FFFFFF82 14 10 03 22 FFFFFF82 0F 08
   0A FFFFFF81 55 FFFFFF82 0F FFFFFF84 FFFFFF80 FFFFFF80 FFFFFF84 20 63 08 0B FFFFFF81 57 FFFFFF82
   0F FFFFFF84 FFFFFF80 FFFFFF80 FFFFFF84 20 FFFFFF81 58 08 0B FFFFFF81 61 FFFFFF82 0F FFFFFF84 FFFFFF80
   FFFFFF80 FFFFFF84 20 FFFFFF82 18 14 04 FFFFFF81 63 FFFFFF82 19 08 08 5E FFFFFF82 17
   FFFFFF81 FFFFFF80 FFFFFFC0 00 2B 08 0B FFFFFF81 68 FFFFFF82 0F FFFFFF84 FFFFFF80 FFFFFF80 FFFFFF84 20
   FFFFFF81 69 08 0A FFFFFF81 6D FFFFFF82 0F FFFFFF84 FFFFFF80 FFFFFF80 FFFFFF84 20 56 08 0B
   FFFFFF81 6F FFFFFF82 0F FFFFFF84 FFFFFF80 FFFFFF80 FFFFFF84 20 FFFFFF82 1D 14 03 2B FFFFFF82 1E
   08 08 5E FFFFFF82 1C FFFFFF81 FFFFFF80 FFFFFFC0 00 4F 08 0B FFFFFF81 73 FFFFFF82 0F
   FFFFFF84 FFFFFF80 FFFFFF80 FFFFFF84 20 FFFFFF82 20 14 04 FFFFFF81 6A FFFFFF82 21 08 08 5E
   FFFFFF82 1F FFFFFF81 FFFFFF80 FFFFFFC0 00 4F 08 0B FFFFFF81 77 FFFFFF82 0F FFFFFF84 FFFFFF80 FFFFFF80
   FFFFFF84 20 FFFFFF82 23 14 04 FFFFFF81 63 FFFFFF82 24 08 08 5E FFFFFF82 22 FFFFFF81
   FFFFFF80 FFFFFFC0 00 2B 28 04 FFFFFF82 0F FFFFFF81 7B 07 09 FFFFFF82 27 09 FFFFFF81
   FFFFFF80 FFFFFF88 02 FFFFFF82 28 01 03 44 65 66 10 03 22 FFFFFF82 29 06
   0A FFFFFF82 10 09 FFFFFF84 FFFFFF81 FFFFFF80 FFFFFF88 02 FFFFFF82 2A 13 06 FFFFFF82 29 0C
   FFFFFF82 2B 14 10 05 15 FFFFFF82 04 FFFFFF82 14 08 07 19 FFFFFF82 29 FFFFFF84
   00 FFFFFF82 2D 14 02 FFFFFF82 28 08 0A FFFFFF82 09 FFFFFF82 29 FFFFFF81 FFFFFF80 FFFFFF84
   40 FFFFFF82 13 08 0A FFFFFF82 0B FFFFFF82 29 FFFFFF81 FFFFFF80 FFFFFF84 40 FFFFFF82 30 14
   04 FFFFFF81 63 FFFFFF82 31 08 08 FFFFFF82 0E FFFFFF82 2F FFFFFFC0 00 FFFFFF82 14 08
   07 FFFFFF82 33 09 FFFFFF84 00 FFFFFF82 34 01 06 72 65 66 44 65 66
   15 02 FFFFFF82 35 10 05 22 FFFFFF81 22 FFFFFF81 4A 08 08 FFFFFF82 37 09
   FFFFFFC2 FFFFFF80 FFFFFF84 00 56 01 03 52 45 46 08 07 FFFFFF82 39 09 FFFFFFA0
   FFFFFF80 04 4F 01 04 52 45 46 20 08 08 FFFFFF82 3B 09 FFFFFFC2 FFFFFF80
   FFFFFF84 00 56 01 03 44 45 46 08 07 FFFFFF82 3D 09 FFFFFFA0 FFFFFF80 04
   4F 01 04 44 45 46 20 08 07 FFFFFF82 3F 09 FFFFFF84 00 FFFFFF82 40
   01 04 75 6E 61 74 15 02 FFFFFF82 41 10 04 22 FFFFFF81 22 4F
   08 07 FFFFFF82 43 09 FFFFFF84 00 FFFFFF82 44 01 05 73 68 61 72 65
   15 04 FFFFFF82 45 FFFFFF82 48 14 04 FFFFFF82 46 FFFFFF82 4A 10 04 22 1B
   FFFFFF82 47 10 03 24 FFFFFF82 48 04 0A FFFFFF82 49 FFFFFF82 42 FFFFFF84 FFFFFF80 FFFFFF80
   FFFFFFC2 00 27 02 01 61 08 08 FFFFFF82 4B FFFFFF82 42 FFFFFFC0 00 FFFFFF82 46
   01 02 70 61 08 07 FFFFFF82 4D 09 FFFFFF84 00 FFFFFF82 4E 01 05 75
   6C 69 66 74 15 04 FFFFFF82 4F FFFFFF82 52 14 04 FFFFFF82 50 FFFFFF82 54
   10 05 22 FFFFFF81 22 FFFFFF82 51 10 03 24 FFFFFF82 52 04 0A FFFFFF82 53
   FFFFFF82 4C FFFFFF84 FFFFFF80 FFFFFF80 FFFFFFC2 00 27 02 01 74 08 08 FFFFFF82 55 FFFFFF82
   4C FFFFFFC0 00 FFFFFF82 51 01 01 78 08 07 FFFFFF82 57 09 FFFFFF84 00 FFFFFF82
   58 01 04 6C 69 66 74 15 04 FFFFFF82 59 FFFFFF82 5C 14 04 FFFFFF82
   5A FFFFFF82 5D 10 04 22 1B FFFFFF82 5B 10 03 24 FFFFFF82 5C 04 0A
   FFFFFF82 53 FFFFFF82 56 FFFFFF84 FFFFFF80 FFFFFF80 FFFFFFC2 00 27 08 08 FFFFFF82 55 FFFFFF82 56
   FFFFFFC0 00 FFFFFF82 5B 08 07 FFFFFF82 5F 09 FFFFFF84 00 FFFFFF82 60 01 05 75
   73 65 71 75 15 06 FFFFFF82 61 FFFFFF82 6C FFFFFF82 64 14 08 FFFFFF82 62
   FFFFFF82 66 FFFFFF82 6D FFFFFF82 6F 10 05 22 FFFFFF81 22 FFFFFF82 63 10 03 24
   FFFFFF82 64 04 0A FFFFFF82 65 FFFFFF82 5E FFFFFF84 FFFFFF80 FFFFFF80 FFFFFFC2 00 27 02 01
   75 08 08 FFFFFF82 67 FFFFFF82 5E FFFFFFC0 00 FFFFFF82 68 01 01 66 10 07
   15 FFFFFF82 69 FFFFFF82 63 FFFFFF82 6B 09 03 FFFFFF82 6A 04 02 09 46 75
   6E 63 74 69 6F 6E 31 10 03 24 FFFFFF82 6C 04 0A FFFFFF82 53
   FFFFFF82 5E FFFFFF84 FFFFFF80 FFFFFF80 FFFFFFC2 00 27 08 08 FFFFFF82 4B FFFFFF82 5E FFFFFFC0 00
   FFFFFF82 6E 10 05 22 FFFFFF81 22 FFFFFF82 6B 08 08 FFFFFF82 70 FFFFFF82 5E FFFFFFC0
   00 FFFFFF82 71 01 01 6B 10 07 15 FFFFFF82 69 FFFFFF82 6B FFFFFF82 62 08
   07 FFFFFF82 73 09 FFFFFF84 00 FFFFFF82 74 01 04 73 65 71 75 15 06
   FFFFFF82 75 FFFFFF82 7C FFFFFF82 78 14 08 FFFFFF82 76 FFFFFF82 79 FFFFFF82 7D FFFFFF82 7F
   10 04 22 1B FFFFFF82 77 10 03 24 FFFFFF82 78 04 0A FFFFFF82 65 FFFFFF82
   72 FFFFFF84 FFFFFF80 FFFFFF80 FFFFFFC2 00 27 08 08 FFFFFF82 67 FFFFFF82 72 FFFFFFC0 00 FFFFFF82
   7A 10 07 15 FFFFFF82 69 FFFFFF82 77 FFFFFF82 7B 10 03 24 FFFFFF82 7C 04
   0A FFFFFF82 53 FFFFFF82 72 FFFFFF84 FFFFFF80 FFFFFF80 FFFFFFC2 00 27 08 08 FFFFFF82 4B FFFFFF82
   72 FFFFFFC0 00 FFFFFF82 7E 10 04 22 1B FFFFFF82 7B 08 08 FFFFFF82 70 FFFFFF82
   72 FFFFFFC0 00 FFFFFF83 00 10 07 15 FFFFFF82 69 FFFFFF82 7B FFFFFF82 76 08 07
   FFFFFF83 02 09 FFFFFF84 00 FFFFFF83 03 01 05 75 70 61 69 72 15 06
   FFFFFF83 04 FFFFFF83 08 FFFFFF83 0A 14 06 FFFFFF83 05 FFFFFF83 0C FFFFFF83 0E 10 05
   22 FFFFFF81 22 FFFFFF83 06 10 06 15 72 FFFFFF83 07 FFFFFF83 09 10 03 24
   FFFFFF83 08 04 0A FFFFFF82 49 FFFFFF83 01 FFFFFF84 FFFFFF80 FFFFFF80 FFFFFFC2 00 27 10 03
   24 FFFFFF83 0A 04 0A FFFFFF83 0B FFFFFF83 01 FFFFFF84 FFFFFF80 FFFFFF80 FFFFFFC2 00 27 02
   01 62 08 08 FFFFFF82 4B FFFFFF83 01 FFFFFFC0 00 FFFFFF83 0D 10 05 22 FFFFFF81
   22 FFFFFF83 07 08 08 FFFFFF83 0F FFFFFF83 01 FFFFFFC0 00 FFFFFF83 10 01 02 70
   62 10 05 22 FFFFFF81 22 FFFFFF83 09 08 07 FFFFFF83 12 09 FFFFFF84 00 FFFFFF83
   13 01 04 70 61 69 72 15 06 FFFFFF83 14 FFFFFF83 18 FFFFFF83 1A 14
   06 FFFFFF83 15 FFFFFF83 1B FFFFFF83 1D 10 04 22 1B FFFFFF83 16 10 06 15
   72 FFFFFF83 17 FFFFFF83 19 10 03 24 FFFFFF83 18 04 0A FFFFFF82 49 FFFFFF83 11
   FFFFFF84 FFFFFF80 FFFFFF80 FFFFFFC2 00 27 10 03 24 FFFFFF83 1A 04 0A FFFFFF83 0B FFFFFF83
   11 FFFFFF84 FFFFFF80 FFFFFF80 FFFFFFC2 00 27 08 08 FFFFFF82 4B FFFFFF83 11 FFFFFFC0 00 FFFFFF83
   1C 10 04 22 1B FFFFFF83 17 08 08 FFFFFF83 0F FFFFFF83 11 FFFFFFC0 00 FFFFFF83
   1E 10 04 22 1B FFFFFF83 19 08 07 FFFFFF83 20 09 FFFFFF84 00 FFFFFF83 21
   01 06 74 72 69 70 6C 65 15 08 FFFFFF83 22 FFFFFF83 28 FFFFFF83 2A
   FFFFFF83 2C 14 08 FFFFFF83 23 FFFFFF83 2E FFFFFF83 30 FFFFFF83 32 10 04 22 1B
   FFFFFF83 24 10 09 15 FFFFFF83 25 FFFFFF83 27 FFFFFF83 29 FFFFFF83 2B 09 03 FFFFFF83
   26 04 02 06 54 75 70 6C 65 33 10 03 24 FFFFFF83 28 04
   0A FFFFFF82 49 FFFFFF83 1F FFFFFF84 FFFFFF80 FFFFFF80 FFFFFFC2 00 27 10 03 24 FFFFFF83 2A
   04 0A FFFFFF83 0B FFFFFF83 1F FFFFFF84 FFFFFF80 FFFFFF80 FFFFFFC2 00 27 10 03 24 FFFFFF83
   2C 04 0A FFFFFF83 2D FFFFFF83 1F FFFFFF84 FFFFFF80 FFFFFF80 FFFFFFC2 00 27 02 01 63
   08 08 FFFFFF82 4B FFFFFF83 1F FFFFFFC0 00 FFFFFF83 2F 10 04 22 1B FFFFFF83 27
   08 08 FFFFFF83 0F FFFFFF83 1F FFFFFFC0 00 FFFFFF83 31 10 04 22 1B FFFFFF83 29
   08 08 FFFFFF83 33 FFFFFF83 1F FFFFFFC0 00 FFFFFF83 34 01 02 70 63 10 04
   22 1B FFFFFF83 2B 08 07 FFFFFF83 36 09 FFFFFF84 00 FFFFFF83 37 01 05 75
   77 72 61 70 15 06 FFFFFF83 38 FFFFFF83 40 FFFFFF83 3B 14 08 FFFFFF83 39
   FFFFFF83 3C FFFFFF83 41 FFFFFF83 44 10 05 22 FFFFFF81 22 FFFFFF83 3A 10 03 24
   FFFFFF83 3B 04 0A FFFFFF83 0B FFFFFF83 35 FFFFFF84 FFFFFF80 FFFFFF80 FFFFFFC2 00 27 08 08
   FFFFFF83 3D FFFFFF83 35 FFFFFFC0 00 FFFFFF83 3E 01 01 69 10 07 15 FFFFFF82 69
   FFFFFF83 3F FFFFFF83 3A 10 03 24 FFFFFF83 40 04 0A FFFFFF82 49 FFFFFF83 35 FFFFFF84
   FFFFFF80 FFFFFF80 FFFFFFC2 00 27 08 08 FFFFFF83 42 FFFFFF83 35 FFFFFFC0 00 FFFFFF83 43 01
   01 6A 10 07 15 FFFFFF82 69 FFFFFF83 3A FFFFFF83 3F 08 08 FFFFFF82 4B FFFFFF83
   35 FFFFFFC0 00 FFFFFF83 45 10 05 22 FFFFFF81 22 FFFFFF83 3F 08 07 FFFFFF83 47
   09 FFFFFF84 00 FFFFFF83 48 01 04 77 72 61 70 15 06 FFFFFF83 49 FFFFFF83
   50 FFFFFF83 4C 14 08 FFFFFF83 4A FFFFFF83 4D FFFFFF83 51 FFFFFF83 53 10 04 22
   1B FFFFFF83 4B 10 03 24 FFFFFF83 4C 04 0A FFFFFF83 0B FFFFFF83 46 FFFFFF84 FFFFFF80
   FFFFFF80 FFFFFFC2 00 27 08 08 FFFFFF83 3D FFFFFF83 46 FFFFFFC0 00 FFFFFF83 4E 10 07
   15 FFFFFF82 69 FFFFFF83 4F FFFFFF83 4B 10 03 24 FFFFFF83 50 04 0A FFFFFF82 49
   FFFFFF83 46 FFFFFF84 FFFFFF80 FFFFFF80 FFFFFFC2 00 27 08 08 FFFFFF83 42 FFFFFF83 46 FFFFFFC0 00
   FFFFFF83 52 10 07 15 FFFFFF82 69 FFFFFF83 4B FFFFFF83 4F 08 08 FFFFFF82 4B FFFFFF83
   46 FFFFFFC0 00 FFFFFF83 54 10 04 22 1B FFFFFF83 4F 08 07 FFFFFF83 56 09
   FFFFFF84 00 FFFFFF83 57 01 0A 61 70 70 65 6E 64 42 79 74 65
   14 05 38 FFFFFF83 58 FFFFFF83 59 08 06 6B FFFFFF83 55 FFFFFFC0 00 38 08
   07 FFFFFF83 5A FFFFFF83 55 FFFFFFC0 00 4F 01 01 62 08 07 FFFFFF83 5C 09
   FFFFFF84 00 FFFFFF83 5D 01 09 6E 61 74 32 42 79 74 65 73 14
   03 38 FFFFFF83 5E 08 07 FFFFFF82 55 FFFFFF83 5B FFFFFFC0 00 4F 08 07 FFFFFF83
   60 09 FFFFFF84 00 FFFFFF83 61 01 03 6E 61 74 15 02 FFFFFF83 62 10
   03 22 1B 4F 08 07 FFFFFF83 64 09 FFFFFF84 00 FFFFFF83 65 01 04 62
   79 74 65 15 02 FFFFFF83 66 10 03 22 1B 3B 08 07 FFFFFF83 68
   09 FFFFFF84 00 FFFFFF83 69 01 06 73 74 72 69 6E 67 15 02 FFFFFF83
   6A 10 04 22 1B FFFFFF81 59 08 07 FFFFFF83 6C 09 FFFFFF84 00 FFFFFF83 6D
   01 09 62 79 74 65 61 72 72 61 79 15 02 FFFFFF83 6E 10
   03 22 1B 38 08 07 FFFFFF83 70 09 FFFFFF84 00 FFFFFF83 71 01 04 62
   6F 6F 6C 15 02 FFFFFF83 72 10 04 22 1B FFFFFF81 63 08 07 FFFFFF83
   74 09 FFFFFF84 00 FFFFFF83 75 01 0A 75 66 69 78 65 64 4C 69
   73 74 15 04 FFFFFF83 76 FFFFFF84 06 14 04 FFFFFF83 77 FFFFFF84 0A 14 04
   FFFFFF83 78 FFFFFF84 08 10 05 22 FFFFFF81 22 FFFFFF83 79 10 06 FFFFFF83 7A FFFFFF84
   02 FFFFFF84 05 0E 04 FFFFFF83 7B FFFFFF84 00 0E 04 FFFFFF83 7C FFFFFF83 7F 0D
   02 FFFFFF83 7D 0A 03 FFFFFF83 7E 06 01 06 3C 72 6F 6F 74 3E
   09 01 05 09 03 FFFFFF84 01 04 01 07 70 61 63 6B 61 67
   65 09 04 FFFFFF84 03 FFFFFF84 04 02 04 4C 69 73 74 0A 03 FFFFFF84
   01 04 10 03 24 FFFFFF84 06 04 0A FFFFFF84 07 FFFFFF83 73 FFFFFF84 FFFFFF80 FFFFFF80
   FFFFFFC2 00 27 02 01 41 08 07 FFFFFF84 09 FFFFFF83 73 FFFFFFC0 00 4F 01
   01 6E 08 08 FFFFFF82 4B FFFFFF83 73 FFFFFFC0 00 FFFFFF84 0B 10 05 22 FFFFFF81
   22 FFFFFF84 05 08 07 FFFFFF84 0D 09 FFFFFF84 00 FFFFFF84 0E 01 09 66 69
   78 65 64 4C 69 73 74 15 04 FFFFFF84 0F FFFFFF84 14 14 04 FFFFFF84
   10 FFFFFF84 16 14 04 FFFFFF84 11 FFFFFF84 15 10 04 22 1B FFFFFF84 12 10
   06 FFFFFF83 7A FFFFFF84 02 FFFFFF84 13 10 03 24 FFFFFF84 14 04 0A FFFFFF82 49
   FFFFFF84 0C FFFFFF84 FFFFFF80 FFFFFF80 FFFFFFC2 00 27 08 07 FFFFFF84 09 FFFFFF84 0C FFFFFFC0 00
   4F 08 08 FFFFFF82 4B FFFFFF84 0C FFFFFFC0 00 FFFFFF84 17 10 04 22 1B FFFFFF84
   13 08 07 FFFFFF84 19 09 FFFFFF84 00 FFFFFF84 1A 01 04 6C 69 73 74
   15 04 FFFFFF84 1B FFFFFF84 1F 14 04 FFFFFF84 1C FFFFFF84 20 10 04 22 1B
   FFFFFF84 1D 10 06 FFFFFF83 7A FFFFFF84 02 FFFFFF84 1E 10 03 24 FFFFFF84 1F 04
   0A FFFFFF82 49 FFFFFF84 18 FFFFFF84 FFFFFF80 FFFFFF80 FFFFFFC2 00 27 08 08 FFFFFF82 4B FFFFFF84
   18 FFFFFFC0 00 FFFFFF84 21 10 04 22 1B FFFFFF84 1E 08 07 FFFFFF84 23 09
   FFFFFF84 00 FFFFFF84 24 01 05 75 6C 69 73 74 15 04 FFFFFF84 25 FFFFFF84
   29 14 04 FFFFFF84 26 FFFFFF84 2A 10 05 22 FFFFFF81 22 FFFFFF84 27 10 06
   FFFFFF83 7A FFFFFF84 02 FFFFFF84 28 10 03 24 FFFFFF84 29 04 0A FFFFFF82 49 FFFFFF84
   22 FFFFFF84 FFFFFF80 FFFFFF80 FFFFFFC2 00 27 08 08 FFFFFF82 4B FFFFFF84 22 FFFFFFC0 00 FFFFFF84
   2B 10 05 22 FFFFFF81 22 FFFFFF84 28 08 07 FFFFFF84 2D 09 FFFFFF84 00 FFFFFF84
   2E 01 04 64 61 74 61 15 04 FFFFFF84 2F FFFFFF84 32 14 06 FFFFFF84
   30 FFFFFF84 33 FFFFFF84 36 10 04 22 1B FFFFFF84 31 10 03 24 FFFFFF84 32
   04 0A FFFFFF82 49 FFFFFF84 2C FFFFFF84 FFFFFF80 FFFFFF80 FFFFFFC2 00 27 08 08 FFFFFF84 34
   FFFFFF84 2C FFFFFFC0 00 FFFFFF84 35 01 03 74 61 67 10 06 15 FFFFFF82 69
   FFFFFF84 31 4F 08 08 FFFFFF84 37 FFFFFF84 2C FFFFFFC0 00 FFFFFF84 38 01 02 70
   73 10 06 FFFFFF83 7A FFFFFF84 02 FFFFFF84 39 10 05 15 FFFFFF82 04 FFFFFF84 30
   
  InnerClass: 
   public abstract PU=class scala/io/BytePickle$PU of class scala/io/BytePickle
   public Def=class scala/io/BytePickle$Def of class scala/io/BytePickle
   public Ref=class scala/io/BytePickle$Ref of class scala/io/BytePickle
   public abstract SPU=class scala/io/BytePickle$SPU of class scala/io/BytePickle
   public abstract RefDef=class scala/io/BytePickle$RefDef of class scala/io/BytePickle
   public final $anon$9=class scala/io/BytePickle$$anon$9 of class scala/io/BytePickle
   public final $anon$8=class scala/io/BytePickle$$anon$8 of class scala/io/BytePickle
   public final $anon$7=class scala/io/BytePickle$$anon$7 of class scala/io/BytePickle
   public final $anon$6=class scala/io/BytePickle$$anon$6 of class scala/io/BytePickle
   public final $anon$5=class scala/io/BytePickle$$anon$5 of class scala/io/BytePickle
   public final $anon$4=class scala/io/BytePickle$$anon$4 of class scala/io/BytePickle
   public final $anon$3=class scala/io/BytePickle$$anon$3 of class scala/io/BytePickle
   public final $anon$2=class scala/io/BytePickle$$anon$2 of class scala/io/BytePickle
   public final $anon$1=class scala/io/BytePickle$$anon$1 of class scala/io/BytePickle
   public PicklerEnv=class scala/io/BytePickle$PicklerEnv of class scala/io/BytePickle
   public PicklerState=class scala/io/BytePickle$PicklerState of class scala/io/BytePickle
   public UnPicklerEnv=class scala/io/BytePickle$UnPicklerEnv of class scala/io/BytePickle
   public UnPicklerState=class scala/io/BytePickle$UnPicklerState of class scala/io/BytePickle
   public final $anonfun$data$1=class scala/io/BytePickle$$anonfun$data$1 of class scala/io/BytePickle
   public final $anonfun$list$2=class scala/io/BytePickle$$anonfun$list$2 of class scala/io/BytePickle
   public final $anonfun$list$1=class scala/io/BytePickle$$anonfun$list$1 of class scala/io/BytePickle
   public final $anonfun$bool$2=class scala/io/BytePickle$$anonfun$bool$2 of class scala/io/BytePickle
   public final $anonfun$bool$1=class scala/io/BytePickle$$anonfun$bool$1 of class scala/io/BytePickle
   public final $anonfun$wrap$1=class scala/io/BytePickle$$anonfun$wrap$1 of class scala/io/BytePickle
   public final $anonfun$pair$2=class scala/io/BytePickle$$anonfun$pair$2 of class scala/io/BytePickle
   public final $anonfun$pair$1=class scala/io/BytePickle$$anonfun$pair$1 of class scala/io/BytePickle
   public final $anonfun$ulist$2=class scala/io/BytePickle$$anonfun$ulist$2 of class scala/io/BytePickle
   public final $anonfun$ulist$1=class scala/io/BytePickle$$anonfun$ulist$1 of class scala/io/BytePickle
   public final $anonfun$uwrap$1=class scala/io/BytePickle$$anonfun$uwrap$1 of class scala/io/BytePickle
   public final $anonfun$upair$2=class scala/io/BytePickle$$anonfun$upair$2 of class scala/io/BytePickle
   public final $anonfun$upair$1=class scala/io/BytePickle$$anonfun$upair$1 of class scala/io/BytePickle
   public final $anonfun$string$2=class scala/io/BytePickle$$anonfun$string$2 of class scala/io/BytePickle
   public final $anonfun$string$1=class scala/io/BytePickle$$anonfun$string$1 of class scala/io/BytePickle
   public final $anonfun$triple$2=class scala/io/BytePickle$$anonfun$triple$2 of class scala/io/BytePickle
   public final $anonfun$triple$1=class scala/io/BytePickle$$anonfun$triple$1 of class scala/io/BytePickle
   public final $anonfun$fixedList$2=class scala/io/BytePickle$$anonfun$fixedList$2 of class scala/io/BytePickle
   public final $anonfun$fixedList$1=class scala/io/BytePickle$$anonfun$fixedList$1 of class scala/io/BytePickle
   public final $anonfun$bytearray$2=class scala/io/BytePickle$$anonfun$bytearray$2 of class scala/io/BytePickle
   public final $anonfun$bytearray$1=class scala/io/BytePickle$$anonfun$bytearray$1 of class scala/io/BytePickle
   public final $anonfun$ufixedList$2=class scala/io/BytePickle$$anonfun$ufixedList$2 of class scala/io/BytePickle
   public final $anonfun$ufixedList$1=class scala/io/BytePickle$$anonfun$ufixedList$1 of class scala/io/BytePickle
  minor version: 0
  major version: 49
  Constant pool:
Asciz	SourceFile;
Asciz	BytePickle.scala;
Asciz	listToPair$2;
Asciz	(Lscala/collection/immutable/List;)Lscala/Tuple2;;
Asciz	Code;
Asciz	scala/io/BytePickle$;
class	scala/io/BytePickle$
Asciz	MODULE$;
Asciz	Lscala/io/BytePickle$;;
NameAndType	MODULE$:Lscala/io/BytePickle$;
Field	scala/io/BytePickle$.MODULE$:Lscala/io/BytePickle$;
NameAndType	listToPair$2:(Lscala/collection/immutable/List;)Lscala/Tuple2;
Method	scala/io/BytePickle$.listToPair$2:(Lscala/collection/immutable/List;)Lscala/Tuple2;
Asciz	pairToList$2;
Asciz	(Lscala/Tuple2;)Lscala/collection/immutable/List;;
NameAndType	pairToList$2:(Lscala/Tuple2;)Lscala/collection/immutable/List;
Method	scala/io/BytePickle$.pairToList$2:(Lscala/Tuple2;)Lscala/collection/immutable/List;
Asciz	listToPair$1;
NameAndType	listToPair$1:(Lscala/collection/immutable/List;)Lscala/Tuple2;
Method	scala/io/BytePickle$.listToPair$1:(Lscala/collection/immutable/List;)Lscala/Tuple2;
Asciz	pairToList$1;
NameAndType	pairToList$1:(Lscala/Tuple2;)Lscala/collection/immutable/List;
Method	scala/io/BytePickle$.pairToList$1:(Lscala/Tuple2;)Lscala/collection/immutable/List;
Asciz	fromEnum$1;
Asciz	(I)Z;
NameAndType	fromEnum$1:(I)Z
Method	scala/io/BytePickle$.fromEnum$1:(I)Z
Asciz	toEnum$1;
Asciz	(Z)I;
NameAndType	toEnum$1:(Z)I
Method	scala/io/BytePickle$.toEnum$1:(Z)I
Asciz	trd$1;
Asciz	(Lscala/Tuple3;)Ljava/lang/Object;;
NameAndType	trd$1:(Lscala/Tuple3;)Ljava/lang/Object;
Method	scala/io/BytePickle$.trd$1:(Lscala/Tuple3;)Ljava/lang/Object;
Asciz	snd$3;
NameAndType	snd$3:(Lscala/Tuple3;)Ljava/lang/Object;
Method	scala/io/BytePickle$.snd$3:(Lscala/Tuple3;)Ljava/lang/Object;
Asciz	fst$3;
NameAndType	fst$3:(Lscala/Tuple3;)Ljava/lang/Object;
Method	scala/io/BytePickle$.fst$3:(Lscala/Tuple3;)Ljava/lang/Object;
Asciz	snd$2;
Asciz	(Lscala/Tuple2;)Ljava/lang/Object;;
NameAndType	snd$2:(Lscala/Tuple2;)Ljava/lang/Object;
Method	scala/io/BytePickle$.snd$2:(Lscala/Tuple2;)Ljava/lang/Object;
Asciz	fst$2;
NameAndType	fst$2:(Lscala/Tuple2;)Ljava/lang/Object;
Method	scala/io/BytePickle$.fst$2:(Lscala/Tuple2;)Ljava/lang/Object;
Asciz	snd$1;
NameAndType	snd$1:(Lscala/Tuple2;)Ljava/lang/Object;
Method	scala/io/BytePickle$.snd$1:(Lscala/Tuple2;)Ljava/lang/Object;
Asciz	fst$1;
NameAndType	fst$1:(Lscala/Tuple2;)Ljava/lang/Object;
Method	scala/io/BytePickle$.fst$1:(Lscala/Tuple2;)Ljava/lang/Object;
Asciz	data;
Asciz	(Lscala/Function1;Lscala/collection/immutable/List;)Lscala/io/BytePickle$SPU;;
NameAndType	data:(Lscala/Function1;Lscala/collection/immutable/List;)Lscala/io/BytePickle$SPU;
Method	scala/io/BytePickle$.data:(Lscala/Function1;Lscala/collection/immutable/List;)Lscala/io/BytePickle$SPU;
Asciz	<a:Ljava/lang/Object;>(Lscala/Function1<Ta;Ljava/lang/Integer;>;Lscala/collection/immutable/List<Lscala/Function0<Lscala/io/BytePickle$SPU<Ta;>;>;>;)Lscala/io/BytePickle$SPU<Ta;>;;
Asciz	Signature;
Asciz	ulist;
Asciz	(Lscala/io/BytePickle$PU;)Lscala/io/BytePickle$PU;;
NameAndType	ulist:(Lscala/io/BytePickle$PU;)Lscala/io/BytePickle$PU;
Method	scala/io/BytePickle$.ulist:(Lscala/io/BytePickle$PU;)Lscala/io/BytePickle$PU;
Asciz	<a:Ljava/lang/Object;>(Lscala/io/BytePickle$PU<Ta;>;)Lscala/io/BytePickle$PU<Lscala/collection/immutable/List<Ta;>;>;;
Asciz	list;
Asciz	(Lscala/io/BytePickle$SPU;)Lscala/io/BytePickle$SPU;;
NameAndType	list:(Lscala/io/BytePickle$SPU;)Lscala/io/BytePickle$SPU;
Method	scala/io/BytePickle$.list:(Lscala/io/BytePickle$SPU;)Lscala/io/BytePickle$SPU;
Asciz	<a:Ljava/lang/Object;>(Lscala/io/BytePickle$SPU<Ta;>;)Lscala/io/BytePickle$SPU<Lscala/collection/immutable/List<Ta;>;>;;
Asciz	fixedList;
Asciz	(Lscala/io/BytePickle$SPU;I)Lscala/io/BytePickle$SPU;;
NameAndType	fixedList:(Lscala/io/BytePickle$SPU;I)Lscala/io/BytePickle$SPU;
Method	scala/io/BytePickle$.fixedList:(Lscala/io/BytePickle$SPU;I)Lscala/io/BytePickle$SPU;
Asciz	<a:Ljava/lang/Object;>(Lscala/io/BytePickle$SPU<Ta;>;I)Lscala/io/BytePickle$SPU<Lscala/collection/immutable/List<Ta;>;>;;
Asciz	ufixedList;
Asciz	(Lscala/io/BytePickle$PU;I)Lscala/io/BytePickle$PU;;
NameAndType	ufixedList:(Lscala/io/BytePickle$PU;I)Lscala/io/BytePickle$PU;
Method	scala/io/BytePickle$.ufixedList:(Lscala/io/BytePickle$PU;I)Lscala/io/BytePickle$PU;
Asciz	<A:Ljava/lang/Object;>(Lscala/io/BytePickle$PU<TA;>;I)Lscala/io/BytePickle$PU<Lscala/collection/immutable/List<TA;>;>;;
Asciz	bool;
Asciz	()Lscala/io/BytePickle$SPU;;
NameAndType	bool:()Lscala/io/BytePickle$SPU;
Method	scala/io/BytePickle$.bool:()Lscala/io/BytePickle$SPU;
Asciz	()Lscala/io/BytePickle$SPU<Ljava/lang/Boolean;>;;
Asciz	bytearray;
NameAndType	bytearray:()Lscala/io/BytePickle$SPU;
Method	scala/io/BytePickle$.bytearray:()Lscala/io/BytePickle$SPU;
Asciz	()Lscala/io/BytePickle$SPU<[B>;;
Asciz	string;
NameAndType	string:()Lscala/io/BytePickle$SPU;
Method	scala/io/BytePickle$.string:()Lscala/io/BytePickle$SPU;
Asciz	()Lscala/io/BytePickle$SPU<Ljava/lang/String;>;;
Asciz	byte;
NameAndType	byte:()Lscala/io/BytePickle$SPU;
Method	scala/io/BytePickle$.byte:()Lscala/io/BytePickle$SPU;
Asciz	()Lscala/io/BytePickle$SPU<Ljava/lang/Byte;>;;
Asciz	nat;
NameAndType	nat:()Lscala/io/BytePickle$SPU;
Method	scala/io/BytePickle$.nat:()Lscala/io/BytePickle$SPU;
Asciz	()Lscala/io/BytePickle$SPU<Ljava/lang/Integer;>;;
Asciz	nat2Bytes;
Asciz	(I)[B;
NameAndType	nat2Bytes:(I)[B
Method	scala/io/BytePickle$.nat2Bytes:(I)[B
Asciz	appendByte;
Asciz	([BI)[B;
NameAndType	appendByte:([BI)[B
Method	scala/io/BytePickle$.appendByte:([BI)[B
Asciz	wrap;
Asciz	(Lscala/Function1;Lscala/Function1;Lscala/io/BytePickle$SPU;)Lscala/io/BytePickle$SPU;;
NameAndType	wrap:(Lscala/Function1;Lscala/Function1;Lscala/io/BytePickle$SPU;)Lscala/io/BytePickle$SPU;
Method	scala/io/BytePickle$.wrap:(Lscala/Function1;Lscala/Function1;Lscala/io/BytePickle$SPU;)Lscala/io/BytePickle$SPU;
Asciz	<a:Ljava/lang/Object;b:Ljava/lang/Object;>(Lscala/Function1<Ta;Tb;>;Lscala/Function1<Tb;Ta;>;Lscala/io/BytePickle$SPU<Ta;>;)Lscala/io/BytePickle$SPU<Tb;>;;
Asciz	uwrap;
Asciz	(Lscala/Function1;Lscala/Function1;Lscala/io/BytePickle$PU;)Lscala/io/BytePickle$PU;;
NameAndType	uwrap:(Lscala/Function1;Lscala/Function1;Lscala/io/BytePickle$PU;)Lscala/io/BytePickle$PU;
Method	scala/io/BytePickle$.uwrap:(Lscala/Function1;Lscala/Function1;Lscala/io/BytePickle$PU;)Lscala/io/BytePickle$PU;
Asciz	<a:Ljava/lang/Object;b:Ljava/lang/Object;>(Lscala/Function1<Ta;Tb;>;Lscala/Function1<Tb;Ta;>;Lscala/io/BytePickle$PU<Ta;>;)Lscala/io/BytePickle$PU<Tb;>;;
Asciz	triple;
Asciz	(Lscala/io/BytePickle$SPU;Lscala/io/BytePickle$SPU;Lscala/io/BytePickle$SPU;)Lscala/io/BytePickle$SPU;;
NameAndType	triple:(Lscala/io/BytePickle$SPU;Lscala/io/BytePickle$SPU;Lscala/io/BytePickle$SPU;)Lscala/io/BytePickle$SPU;
Method	scala/io/BytePickle$.triple:(Lscala/io/BytePickle$SPU;Lscala/io/BytePickle$SPU;Lscala/io/BytePickle$SPU;)Lscala/io/BytePickle$SPU;
Asciz	<a:Ljava/lang/Object;b:Ljava/lang/Object;c:Ljava/lang/Object;>(Lscala/io/BytePickle$SPU<Ta;>;Lscala/io/BytePickle$SPU<Tb;>;Lscala/io/BytePickle$SPU<Tc;>;)Lscala/io/BytePickle$SPU<Lscala/Tuple3<Ta;Tb;Tc;>;>;;
Asciz	pair;
Asciz	(Lscala/io/BytePickle$SPU;Lscala/io/BytePickle$SPU;)Lscala/io/BytePickle$SPU;;
NameAndType	pair:(Lscala/io/BytePickle$SPU;Lscala/io/BytePickle$SPU;)Lscala/io/BytePickle$SPU;
Method	scala/io/BytePickle$.pair:(Lscala/io/BytePickle$SPU;Lscala/io/BytePickle$SPU;)Lscala/io/BytePickle$SPU;
Asciz	<a:Ljava/lang/Object;b:Ljava/lang/Object;>(Lscala/io/BytePickle$SPU<Ta;>;Lscala/io/BytePickle$SPU<Tb;>;)Lscala/io/BytePickle$SPU<Lscala/Tuple2<Ta;Tb;>;>;;
Asciz	upair;
Asciz	(Lscala/io/BytePickle$PU;Lscala/io/BytePickle$PU;)Lscala/io/BytePickle$PU;;
NameAndType	upair:(Lscala/io/BytePickle$PU;Lscala/io/BytePickle$PU;)Lscala/io/BytePickle$PU;
Method	scala/io/BytePickle$.upair:(Lscala/io/BytePickle$PU;Lscala/io/BytePickle$PU;)Lscala/io/BytePickle$PU;
Asciz	<a:Ljava/lang/Object;b:Ljava/lang/Object;>(Lscala/io/BytePickle$PU<Ta;>;Lscala/io/BytePickle$PU<Tb;>;)Lscala/io/BytePickle$PU<Lscala/Tuple2<Ta;Tb;>;>;;
Asciz	sequ;
Asciz	(Lscala/Function1;Lscala/io/BytePickle$SPU;Lscala/Function1;)Lscala/io/BytePickle$SPU;;
NameAndType	sequ:(Lscala/Function1;Lscala/io/BytePickle$SPU;Lscala/Function1;)Lscala/io/BytePickle$SPU;
Method	scala/io/BytePickle$.sequ:(Lscala/Function1;Lscala/io/BytePickle$SPU;Lscala/Function1;)Lscala/io/BytePickle$SPU;
Asciz	<t:Ljava/lang/Object;u:Ljava/lang/Object;>(Lscala/Function1<Tu;Tt;>;Lscala/io/BytePickle$SPU<Tt;>;Lscala/Function1<Tt;Lscala/io/BytePickle$SPU<Tu;>;>;)Lscala/io/BytePickle$SPU<Tu;>;;
Asciz	usequ;
Asciz	(Lscala/Function1;Lscala/io/BytePickle$PU;Lscala/Function1;)Lscala/io/BytePickle$PU;;
NameAndType	usequ:(Lscala/Function1;Lscala/io/BytePickle$PU;Lscala/Function1;)Lscala/io/BytePickle$PU;
Method	scala/io/BytePickle$.usequ:(Lscala/Function1;Lscala/io/BytePickle$PU;Lscala/Function1;)Lscala/io/BytePickle$PU;
Asciz	<t:Ljava/lang/Object;u:Ljava/lang/Object;>(Lscala/Function1<Tu;Tt;>;Lscala/io/BytePickle$PU<Tt;>;Lscala/Function1<Tt;Lscala/io/BytePickle$PU<Tu;>;>;)Lscala/io/BytePickle$PU<Tu;>;;
Asciz	lift;
Asciz	(Ljava/lang/Object;)Lscala/io/BytePickle$SPU;;
NameAndType	lift:(Ljava/lang/Object;)Lscala/io/BytePickle$SPU;
Method	scala/io/BytePickle$.lift:(Ljava/lang/Object;)Lscala/io/BytePickle$SPU;
Asciz	<t:Ljava/lang/Object;>(Tt;)Lscala/io/BytePickle$SPU<Tt;>;;
Asciz	ulift;
Asciz	(Ljava/lang/Object;)Lscala/io/BytePickle$PU;;
NameAndType	ulift:(Ljava/lang/Object;)Lscala/io/BytePickle$PU;
Method	scala/io/BytePickle$.ulift:(Ljava/lang/Object;)Lscala/io/BytePickle$PU;
Asciz	<t:Ljava/lang/Object;>(Tt;)Lscala/io/BytePickle$PU<Tt;>;;
Asciz	share;
NameAndType	share:(Lscala/io/BytePickle$SPU;)Lscala/io/BytePickle$SPU;
Method	scala/io/BytePickle$.share:(Lscala/io/BytePickle$SPU;)Lscala/io/BytePickle$SPU;
Asciz	<a:Ljava/lang/Object;>(Lscala/io/BytePickle$SPU<Ta;>;)Lscala/io/BytePickle$SPU<Ta;>;;
Asciz	unat;
Asciz	()Lscala/io/BytePickle$PU;;
NameAndType	unat:()Lscala/io/BytePickle$PU;
Method	scala/io/BytePickle$.unat:()Lscala/io/BytePickle$PU;
Asciz	()Lscala/io/BytePickle$PU<Ljava/lang/Integer;>;;
Asciz	DEF;
Asciz	()I;
NameAndType	DEF:()I
Method	scala/io/BytePickle$.DEF:()I
Asciz	REF;
NameAndType	REF:()I
Method	scala/io/BytePickle$.REF:()I
Asciz	refDef;
NameAndType	refDef:()Lscala/io/BytePickle$PU;
Method	scala/io/BytePickle$.refDef:()Lscala/io/BytePickle$PU;
Asciz	()Lscala/io/BytePickle$PU<Lscala/io/BytePickle$RefDef;>;;
Asciz	uunpickle;
Asciz	(Lscala/io/BytePickle$PU;[B)Ljava/lang/Object;;
NameAndType	uunpickle:(Lscala/io/BytePickle$PU;[B)Ljava/lang/Object;
Method	scala/io/BytePickle$.uunpickle:(Lscala/io/BytePickle$PU;[B)Ljava/lang/Object;
Asciz	<T:Ljava/lang/Object;>(Lscala/io/BytePickle$PU<TT;>;[B)TT;;
Asciz	upickle;
Asciz	(Lscala/io/BytePickle$PU;Ljava/lang/Object;)[B;
NameAndType	upickle:(Lscala/io/BytePickle$PU;Ljava/lang/Object;)[B
Method	scala/io/BytePickle$.upickle:(Lscala/io/BytePickle$PU;Ljava/lang/Object;)[B
Asciz	<T:Ljava/lang/Object;>(Lscala/io/BytePickle$PU<TT;>;TT;)[B;
Asciz	unpickle;
Asciz	(Lscala/io/BytePickle$SPU;[B)Ljava/lang/Object;;
NameAndType	unpickle:(Lscala/io/BytePickle$SPU;[B)Ljava/lang/Object;
Method	scala/io/BytePickle$.unpickle:(Lscala/io/BytePickle$SPU;[B)Ljava/lang/Object;
Asciz	<T:Ljava/lang/Object;>(Lscala/io/BytePickle$SPU<TT;>;[B)TT;;
Asciz	pickle;
Asciz	(Lscala/io/BytePickle$SPU;Ljava/lang/Object;)[B;
NameAndType	pickle:(Lscala/io/BytePickle$SPU;Ljava/lang/Object;)[B
Method	scala/io/BytePickle$.pickle:(Lscala/io/BytePickle$SPU;Ljava/lang/Object;)[B
Asciz	<T:Ljava/lang/Object;>(Lscala/io/BytePickle$SPU<TT;>;TT;)[B;
Asciz	ScalaSig;
Asciz	InnerClasses;
Asciz	scala/io/BytePickle$PU;
class	scala/io/BytePickle$PU
Asciz	scala/io/BytePickle;
class	scala/io/BytePickle
Asciz	PU;
Asciz	scala/io/BytePickle$Def;
class	scala/io/BytePickle$Def
Asciz	Def;
Asciz	scala/io/BytePickle$Ref;
class	scala/io/BytePickle$Ref
Asciz	Ref;
Asciz	scala/io/BytePickle$SPU;
class	scala/io/BytePickle$SPU
Asciz	SPU;
Asciz	scala/io/BytePickle$RefDef;
class	scala/io/BytePickle$RefDef
Asciz	RefDef;
Asciz	scala/io/BytePickle$$anon$9;
class	scala/io/BytePickle$$anon$9
Asciz	$anon$9;
Asciz	scala/io/BytePickle$$anon$8;
class	scala/io/BytePickle$$anon$8
Asciz	$anon$8;
Asciz	scala/io/BytePickle$$anon$7;
class	scala/io/BytePickle$$anon$7
Asciz	$anon$7;
Asciz	scala/io/BytePickle$$anon$6;
class	scala/io/BytePickle$$anon$6
Asciz	$anon$6;
Asciz	scala/io/BytePickle$$anon$5;
class	scala/io/BytePickle$$anon$5
Asciz	$anon$5;
Asciz	scala/io/BytePickle$$anon$4;
class	scala/io/BytePickle$$anon$4
Asciz	$anon$4;
Asciz	scala/io/BytePickle$$anon$3;
class	scala/io/BytePickle$$anon$3
Asciz	$anon$3;
Asciz	scala/io/BytePickle$$anon$2;
class	scala/io/BytePickle$$anon$2
Asciz	$anon$2;
Asciz	scala/io/BytePickle$$anon$1;
class	scala/io/BytePickle$$anon$1
Asciz	$anon$1;
Asciz	scala/io/BytePickle$PicklerEnv;
class	scala/io/BytePickle$PicklerEnv
Asciz	PicklerEnv;
Asciz	scala/io/BytePickle$PicklerState;
class	scala/io/BytePickle$PicklerState
Asciz	PicklerState;
Asciz	scala/io/BytePickle$UnPicklerEnv;
class	scala/io/BytePickle$UnPicklerEnv
Asciz	UnPicklerEnv;
Asciz	scala/io/BytePickle$UnPicklerState;
class	scala/io/BytePickle$UnPicklerState
Asciz	UnPicklerState;
Asciz	scala/io/BytePickle$$anonfun$data$1;
class	scala/io/BytePickle$$anonfun$data$1
Asciz	$anonfun$data$1;
Asciz	scala/io/BytePickle$$anonfun$list$2;
class	scala/io/BytePickle$$anonfun$list$2
Asciz	$anonfun$list$2;
Asciz	scala/io/BytePickle$$anonfun$list$1;
class	scala/io/BytePickle$$anonfun$list$1
Asciz	$anonfun$list$1;
Asciz	scala/io/BytePickle$$anonfun$bool$2;
class	scala/io/BytePickle$$anonfun$bool$2
Asciz	$anonfun$bool$2;
Asciz	scala/io/BytePickle$$anonfun$bool$1;
class	scala/io/BytePickle$$anonfun$bool$1
Asciz	$anonfun$bool$1;
Asciz	scala/io/BytePickle$$anonfun$wrap$1;
class	scala/io/BytePickle$$anonfun$wrap$1
Asciz	$anonfun$wrap$1;
Asciz	scala/io/BytePickle$$anonfun$pair$2;
class	scala/io/BytePickle$$anonfun$pair$2
Asciz	$anonfun$pair$2;
Asciz	scala/io/BytePickle$$anonfun$pair$1;
class	scala/io/BytePickle$$anonfun$pair$1
Asciz	$anonfun$pair$1;
Asciz	scala/io/BytePickle$$anonfun$ulist$2;
class	scala/io/BytePickle$$anonfun$ulist$2
Asciz	$anonfun$ulist$2;
Asciz	scala/io/BytePickle$$anonfun$ulist$1;
class	scala/io/BytePickle$$anonfun$ulist$1
Asciz	$anonfun$ulist$1;
Asciz	scala/io/BytePickle$$anonfun$uwrap$1;
class	scala/io/BytePickle$$anonfun$uwrap$1
Asciz	$anonfun$uwrap$1;
Asciz	scala/io/BytePickle$$anonfun$upair$2;
class	scala/io/BytePickle$$anonfun$upair$2
Asciz	$anonfun$upair$2;
Asciz	scala/io/BytePickle$$anonfun$upair$1;
class	scala/io/BytePickle$$anonfun$upair$1
Asciz	$anonfun$upair$1;
Asciz	scala/io/BytePickle$$anonfun$string$2;
class	scala/io/BytePickle$$anonfun$string$2
Asciz	$anonfun$string$2;
Asciz	scala/io/BytePickle$$anonfun$string$1;
class	scala/io/BytePickle$$anonfun$string$1
Asciz	$anonfun$string$1;
Asciz	scala/io/BytePickle$$anonfun$triple$2;
class	scala/io/BytePickle$$anonfun$triple$2
Asciz	$anonfun$triple$2;
Asciz	scala/io/BytePickle$$anonfun$triple$1;
class	scala/io/BytePickle$$anonfun$triple$1
Asciz	$anonfun$triple$1;
Asciz	scala/io/BytePickle$$anonfun$fixedList$2;
class	scala/io/BytePickle$$anonfun$fixedList$2
Asciz	$anonfun$fixedList$2;
Asciz	scala/io/BytePickle$$anonfun$fixedList$1;
class	scala/io/BytePickle$$anonfun$fixedList$1
Asciz	$anonfun$fixedList$1;
Asciz	scala/io/BytePickle$$anonfun$bytearray$2;
class	scala/io/BytePickle$$anonfun$bytearray$2
Asciz	$anonfun$bytearray$2;
Asciz	scala/io/BytePickle$$anonfun$bytearray$1;
class	scala/io/BytePickle$$anonfun$bytearray$1
Asciz	$anonfun$bytearray$1;
Asciz	scala/io/BytePickle$$anonfun$ufixedList$2;
class	scala/io/BytePickle$$anonfun$ufixedList$2
Asciz	$anonfun$ufixedList$2;
Asciz	scala/io/BytePickle$$anonfun$ufixedList$1;
class	scala/io/BytePickle$$anonfun$ufixedList$1
Asciz	$anonfun$ufixedList$1;
Asciz	java/lang/Object;
class	java/lang/Object

{
public static final scala.Tuple2 listToPair$2(scala.collection.immutable.List);
  Signature: (Lscala/collection/immutable/List;)Lscala/Tuple2;
  Code:
   Stack=2, Locals=1, Args_size=1
	getstatic	Field scala/io/BytePickle$.MODULE$:Lscala/io/BytePickle$;
	aload_0
	invokevirtual	Method scala/io/BytePickle$.listToPair$2:(Lscala/collection/immutable/List;)Lscala/Tuple2;
	areturn
  Labels:

public static final scala.collection.immutable.List pairToList$2(scala.Tuple2);
  Signature: (Lscala/Tuple2;)Lscala/collection/immutable/List;
  Code:
   Stack=2, Locals=1, Args_size=1
	getstatic	Field scala/io/BytePickle$.MODULE$:Lscala/io/BytePickle$;
	aload_0
	invokevirtual	Method scala/io/BytePickle$.pairToList$2:(Lscala/Tuple2;)Lscala/collection/immutable/List;
	areturn
  Labels:

public static final scala.Tuple2 listToPair$1(scala.collection.immutable.List);
  Signature: (Lscala/collection/immutable/List;)Lscala/Tuple2;
  Code:
   Stack=2, Locals=1, Args_size=1
	getstatic	Field scala/io/BytePickle$.MODULE$:Lscala/io/BytePickle$;
	aload_0
	invokevirtual	Method scala/io/BytePickle$.listToPair$1:(Lscala/collection/immutable/List;)Lscala/Tuple2;
	areturn
  Labels:

public static final scala.collection.immutable.List pairToList$1(scala.Tuple2);
  Signature: (Lscala/Tuple2;)Lscala/collection/immutable/List;
  Code:
   Stack=2, Locals=1, Args_size=1
	getstatic	Field scala/io/BytePickle$.MODULE$:Lscala/io/BytePickle$;
	aload_0
	invokevirtual	Method scala/io/BytePickle$.pairToList$1:(Lscala/Tuple2;)Lscala/collection/immutable/List;
	areturn
  Labels:

public static final boolean fromEnum$1(int);
  Signature: (I)Z
  Code:
   Stack=2, Locals=1, Args_size=1
	getstatic	Field scala/io/BytePickle$.MODULE$:Lscala/io/BytePickle$;
	iload_0
	invokevirtual	Method scala/io/BytePickle$.fromEnum$1:(I)Z
	ireturn
  Labels:

public static final int toEnum$1(boolean);
  Signature: (Z)I
  Code:
   Stack=2, Locals=1, Args_size=1
	getstatic	Field scala/io/BytePickle$.MODULE$:Lscala/io/BytePickle$;
	iload_0
	invokevirtual	Method scala/io/BytePickle$.toEnum$1:(Z)I
	ireturn
  Labels:

public static final java.lang.Object trd$1(scala.Tuple3);
  Signature: (Lscala/Tuple3;)Ljava/lang/Object;
  Code:
   Stack=2, Locals=1, Args_size=1
	getstatic	Field scala/io/BytePickle$.MODULE$:Lscala/io/BytePickle$;
	aload_0
	invokevirtual	Method scala/io/BytePickle$.trd$1:(Lscala/Tuple3;)Ljava/lang/Object;
	areturn
  Labels:

public static final java.lang.Object snd$3(scala.Tuple3);
  Signature: (Lscala/Tuple3;)Ljava/lang/Object;
  Code:
   Stack=2, Locals=1, Args_size=1
	getstatic	Field scala/io/BytePickle$.MODULE$:Lscala/io/BytePickle$;
	aload_0
	invokevirtual	Method scala/io/BytePickle$.snd$3:(Lscala/Tuple3;)Ljava/lang/Object;
	areturn
  Labels:

public static final java.lang.Object fst$3(scala.Tuple3);
  Signature: (Lscala/Tuple3;)Ljava/lang/Object;
  Code:
   Stack=2, Locals=1, Args_size=1
	getstatic	Field scala/io/BytePickle$.MODULE$:Lscala/io/BytePickle$;
	aload_0
	invokevirtual	Method scala/io/BytePickle$.fst$3:(Lscala/Tuple3;)Ljava/lang/Object;
	areturn
  Labels:

public static final java.lang.Object snd$2(scala.Tuple2);
  Signature: (Lscala/Tuple2;)Ljava/lang/Object;
  Code:
   Stack=2, Locals=1, Args_size=1
	getstatic	Field scala/io/BytePickle$.MODULE$:Lscala/io/BytePickle$;
	aload_0
	invokevirtual	Method scala/io/BytePickle$.snd$2:(Lscala/Tuple2;)Ljava/lang/Object;
	areturn
  Labels:

public static final java.lang.Object fst$2(scala.Tuple2);
  Signature: (Lscala/Tuple2;)Ljava/lang/Object;
  Code:
   Stack=2, Locals=1, Args_size=1
	getstatic	Field scala/io/BytePickle$.MODULE$:Lscala/io/BytePickle$;
	aload_0
	invokevirtual	Method scala/io/BytePickle$.fst$2:(Lscala/Tuple2;)Ljava/lang/Object;
	areturn
  Labels:

public static final java.lang.Object snd$1(scala.Tuple2);
  Signature: (Lscala/Tuple2;)Ljava/lang/Object;
  Code:
   Stack=2, Locals=1, Args_size=1
	getstatic	Field scala/io/BytePickle$.MODULE$:Lscala/io/BytePickle$;
	aload_0
	invokevirtual	Method scala/io/BytePickle$.snd$1:(Lscala/Tuple2;)Ljava/lang/Object;
	areturn
  Labels:

public static final java.lang.Object fst$1(scala.Tuple2);
  Signature: (Lscala/Tuple2;)Ljava/lang/Object;
  Code:
   Stack=2, Locals=1, Args_size=1
	getstatic	Field scala/io/BytePickle$.MODULE$:Lscala/io/BytePickle$;
	aload_0
	invokevirtual	Method scala/io/BytePickle$.fst$1:(Lscala/Tuple2;)Ljava/lang/Object;
	areturn
  Labels:

public static final scala.io.BytePickle$SPU data(scala.Function1, scala.collection.immutable.List);
  Signature: (Lscala/Function1;Lscala/collection/immutable/List;)Lscala/io/BytePickle$SPU;
  Code:
   Stack=3, Locals=2, Args_size=2
	getstatic	Field scala/io/BytePickle$.MODULE$:Lscala/io/BytePickle$;
	aload_0
	aload_1
	invokevirtual	Method scala/io/BytePickle$.data:(Lscala/Function1;Lscala/collection/immutable/List;)Lscala/io/BytePickle$SPU;
	areturn
  Labels:
  Signature: length = 0x2
   00 3B 

public static final scala.io.BytePickle$PU ulist(scala.io.BytePickle$PU);
  Signature: (Lscala/io/BytePickle$PU;)Lscala/io/BytePickle$PU;
  Code:
   Stack=2, Locals=1, Args_size=1
	getstatic	Field scala/io/BytePickle$.MODULE$:Lscala/io/BytePickle$;
	aload_0
	invokevirtual	Method scala/io/BytePickle$.ulist:(Lscala/io/BytePickle$PU;)Lscala/io/BytePickle$PU;
	areturn
  Labels:
  Signature: length = 0x2
   00 41 

public static final scala.io.BytePickle$SPU list(scala.io.BytePickle$SPU);
  Signature: (Lscala/io/BytePickle$SPU;)Lscala/io/BytePickle$SPU;
  Code:
   Stack=2, Locals=1, Args_size=1
	getstatic	Field scala/io/BytePickle$.MODULE$:Lscala/io/BytePickle$;
	aload_0
	invokevirtual	Method scala/io/BytePickle$.list:(Lscala/io/BytePickle$SPU;)Lscala/io/BytePickle$SPU;
	areturn
  Labels:
  Signature: length = 0x2
   00 46 

public static final scala.io.BytePickle$SPU fixedList(scala.io.BytePickle$SPU, int);
  Signature: (Lscala/io/BytePickle$SPU;I)Lscala/io/BytePickle$SPU;
  Code:
   Stack=3, Locals=2, Args_size=2
	getstatic	Field scala/io/BytePickle$.MODULE$:Lscala/io/BytePickle$;
	aload_0
	iload_1
	invokevirtual	Method scala/io/BytePickle$.fixedList:(Lscala/io/BytePickle$SPU;I)Lscala/io/BytePickle$SPU;
	areturn
  Labels:
  Signature: length = 0x2
   00 4B 

public static final scala.io.BytePickle$PU ufixedList(scala.io.BytePickle$PU, int);
  Signature: (Lscala/io/BytePickle$PU;I)Lscala/io/BytePickle$PU;
  Code:
   Stack=3, Locals=2, Args_size=2
	getstatic	Field scala/io/BytePickle$.MODULE$:Lscala/io/BytePickle$;
	aload_0
	iload_1
	invokevirtual	Method scala/io/BytePickle$.ufixedList:(Lscala/io/BytePickle$PU;I)Lscala/io/BytePickle$PU;
	areturn
  Labels:
  Signature: length = 0x2
   00 50 

public static final scala.io.BytePickle$SPU bool();
  Signature: ()Lscala/io/BytePickle$SPU;
  Code:
   Stack=1, Locals=0, Args_size=0
	getstatic	Field scala/io/BytePickle$.MODULE$:Lscala/io/BytePickle$;
	invokevirtual	Method scala/io/BytePickle$.bool:()Lscala/io/BytePickle$SPU;
	areturn
  Labels:
  Signature: length = 0x2
   00 55 

public static final scala.io.BytePickle$SPU bytearray();
  Signature: ()Lscala/io/BytePickle$SPU;
  Code:
   Stack=1, Locals=0, Args_size=0
	getstatic	Field scala/io/BytePickle$.MODULE$:Lscala/io/BytePickle$;
	invokevirtual	Method scala/io/BytePickle$.bytearray:()Lscala/io/BytePickle$SPU;
	areturn
  Labels:
  Signature: length = 0x2
   00 59 

public static final scala.io.BytePickle$SPU string();
  Signature: ()Lscala/io/BytePickle$SPU;
  Code:
   Stack=1, Locals=0, Args_size=0
	getstatic	Field scala/io/BytePickle$.MODULE$:Lscala/io/BytePickle$;
	invokevirtual	Method scala/io/BytePickle$.string:()Lscala/io/BytePickle$SPU;
	areturn
  Labels:
  Signature: length = 0x2
   00 5D 

public static final scala.io.BytePickle$SPU byte();
  Signature: ()Lscala/io/BytePickle$SPU;
  Code:
   Stack=1, Locals=0, Args_size=0
	getstatic	Field scala/io/BytePickle$.MODULE$:Lscala/io/BytePickle$;
	invokevirtual	Method scala/io/BytePickle$.byte:()Lscala/io/BytePickle$SPU;
	areturn
  Labels:
  Signature: length = 0x2
   00 61 

public static final scala.io.BytePickle$SPU nat();
  Signature: ()Lscala/io/BytePickle$SPU;
  Code:
   Stack=1, Locals=0, Args_size=0
	getstatic	Field scala/io/BytePickle$.MODULE$:Lscala/io/BytePickle$;
	invokevirtual	Method scala/io/BytePickle$.nat:()Lscala/io/BytePickle$SPU;
	areturn
  Labels:
  Signature: length = 0x2
   00 65 

public static final byte[] nat2Bytes(int);
  Signature: (I)[B
  Code:
   Stack=2, Locals=1, Args_size=1
	getstatic	Field scala/io/BytePickle$.MODULE$:Lscala/io/BytePickle$;
	iload_0
	invokevirtual	Method scala/io/BytePickle$.nat2Bytes:(I)[B
	areturn
  Labels:

public static final byte[] appendByte(byte[], int);
  Signature: ([BI)[B
  Code:
   Stack=3, Locals=2, Args_size=2
	getstatic	Field scala/io/BytePickle$.MODULE$:Lscala/io/BytePickle$;
	aload_0
	iload_1
	invokevirtual	Method scala/io/BytePickle$.appendByte:([BI)[B
	areturn
  Labels:

public static final scala.io.BytePickle$SPU wrap(scala.Function1, scala.Function1, scala.io.BytePickle$SPU);
  Signature: (Lscala/Function1;Lscala/Function1;Lscala/io/BytePickle$SPU;)Lscala/io/BytePickle$SPU;
  Code:
   Stack=4, Locals=3, Args_size=3
	getstatic	Field scala/io/BytePickle$.MODULE$:Lscala/io/BytePickle$;
	aload_0
	aload_1
	aload_2
	invokevirtual	Method scala/io/BytePickle$.wrap:(Lscala/Function1;Lscala/Function1;Lscala/io/BytePickle$SPU;)Lscala/io/BytePickle$SPU;
	areturn
  Labels:
  Signature: length = 0x2
   00 72 

public static final scala.io.BytePickle$PU uwrap(scala.Function1, scala.Function1, scala.io.BytePickle$PU);
  Signature: (Lscala/Function1;Lscala/Function1;Lscala/io/BytePickle$PU;)Lscala/io/BytePickle$PU;
  Code:
   Stack=4, Locals=3, Args_size=3
	getstatic	Field scala/io/BytePickle$.MODULE$:Lscala/io/BytePickle$;
	aload_0
	aload_1
	aload_2
	invokevirtual	Method scala/io/BytePickle$.uwrap:(Lscala/Function1;Lscala/Function1;Lscala/io/BytePickle$PU;)Lscala/io/BytePickle$PU;
	areturn
  Labels:
  Signature: length = 0x2
   00 77 

public static final scala.io.BytePickle$SPU triple(scala.io.BytePickle$SPU, scala.io.BytePickle$SPU, scala.io.BytePickle$SPU);
  Signature: (Lscala/io/BytePickle$SPU;Lscala/io/BytePickle$SPU;Lscala/io/BytePickle$SPU;)Lscala/io/BytePickle$SPU;
  Code:
   Stack=4, Locals=3, Args_size=3
	getstatic	Field scala/io/BytePickle$.MODULE$:Lscala/io/BytePickle$;
	aload_0
	aload_1
	aload_2
	invokevirtual	Method scala/io/BytePickle$.triple:(Lscala/io/BytePickle$SPU;Lscala/io/BytePickle$SPU;Lscala/io/BytePickle$SPU;)Lscala/io/BytePickle$SPU;
	areturn
  Labels:
  Signature: length = 0x2
   00 7C 

public static final scala.io.BytePickle$SPU pair(scala.io.BytePickle$SPU, scala.io.BytePickle$SPU);
  Signature: (Lscala/io/BytePickle$SPU;Lscala/io/BytePickle$SPU;)Lscala/io/BytePickle$SPU;
  Code:
   Stack=3, Locals=2, Args_size=2
	getstatic	Field scala/io/BytePickle$.MODULE$:Lscala/io/BytePickle$;
	aload_0
	aload_1
	invokevirtual	Method scala/io/BytePickle$.pair:(Lscala/io/BytePickle$SPU;Lscala/io/BytePickle$SPU;)Lscala/io/BytePickle$SPU;
	areturn
  Labels:
  Signature: length = 0x2
   00 FFFFFF81 

public static final scala.io.BytePickle$PU upair(scala.io.BytePickle$PU, scala.io.BytePickle$PU);
  Signature: (Lscala/io/BytePickle$PU;Lscala/io/BytePickle$PU;)Lscala/io/BytePickle$PU;
  Code:
   Stack=3, Locals=2, Args_size=2
	getstatic	Field scala/io/BytePickle$.MODULE$:Lscala/io/BytePickle$;
	aload_0
	aload_1
	invokevirtual	Method scala/io/BytePickle$.upair:(Lscala/io/BytePickle$PU;Lscala/io/BytePickle$PU;)Lscala/io/BytePickle$PU;
	areturn
  Labels:
  Signature: length = 0x2
   00 FFFFFF86 

public static final scala.io.BytePickle$SPU sequ(scala.Function1, scala.io.BytePickle$SPU, scala.Function1);
  Signature: (Lscala/Function1;Lscala/io/BytePickle$SPU;Lscala/Function1;)Lscala/io/BytePickle$SPU;
  Code:
   Stack=4, Locals=3, Args_size=3
	getstatic	Field scala/io/BytePickle$.MODULE$:Lscala/io/BytePickle$;
	aload_0
	aload_1
	aload_2
	invokevirtual	Method scala/io/BytePickle$.sequ:(Lscala/Function1;Lscala/io/BytePickle$SPU;Lscala/Function1;)Lscala/io/BytePickle$SPU;
	areturn
  Labels:
  Signature: length = 0x2
   00 FFFFFF8B 

public static final scala.io.BytePickle$PU usequ(scala.Function1, scala.io.BytePickle$PU, scala.Function1);
  Signature: (Lscala/Function1;Lscala/io/BytePickle$PU;Lscala/Function1;)Lscala/io/BytePickle$PU;
  Code:
   Stack=4, Locals=3, Args_size=3
	getstatic	Field scala/io/BytePickle$.MODULE$:Lscala/io/BytePickle$;
	aload_0
	aload_1
	aload_2
	invokevirtual	Method scala/io/BytePickle$.usequ:(Lscala/Function1;Lscala/io/BytePickle$PU;Lscala/Function1;)Lscala/io/BytePickle$PU;
	areturn
  Labels:
  Signature: length = 0x2
   00 FFFFFF90 

public static final scala.io.BytePickle$SPU lift(java.lang.Object);
  Signature: (Ljava/lang/Object;)Lscala/io/BytePickle$SPU;
  Code:
   Stack=2, Locals=1, Args_size=1
	getstatic	Field scala/io/BytePickle$.MODULE$:Lscala/io/BytePickle$;
	aload_0
	invokevirtual	Method scala/io/BytePickle$.lift:(Ljava/lang/Object;)Lscala/io/BytePickle$SPU;
	areturn
  Labels:
  Signature: length = 0x2
   00 FFFFFF95 

public static final scala.io.BytePickle$PU ulift(java.lang.Object);
  Signature: (Ljava/lang/Object;)Lscala/io/BytePickle$PU;
  Code:
   Stack=2, Locals=1, Args_size=1
	getstatic	Field scala/io/BytePickle$.MODULE$:Lscala/io/BytePickle$;
	aload_0
	invokevirtual	Method scala/io/BytePickle$.ulift:(Ljava/lang/Object;)Lscala/io/BytePickle$PU;
	areturn
  Labels:
  Signature: length = 0x2
   00 FFFFFF9A 

public static final scala.io.BytePickle$SPU share(scala.io.BytePickle$SPU);
  Signature: (Lscala/io/BytePickle$SPU;)Lscala/io/BytePickle$SPU;
  Code:
   Stack=2, Locals=1, Args_size=1
	getstatic	Field scala/io/BytePickle$.MODULE$:Lscala/io/BytePickle$;
	aload_0
	invokevirtual	Method scala/io/BytePickle$.share:(Lscala/io/BytePickle$SPU;)Lscala/io/BytePickle$SPU;
	areturn
  Labels:
  Signature: length = 0x2
   00 FFFFFF9E 

public static final scala.io.BytePickle$PU unat();
  Signature: ()Lscala/io/BytePickle$PU;
  Code:
   Stack=1, Locals=0, Args_size=0
	getstatic	Field scala/io/BytePickle$.MODULE$:Lscala/io/BytePickle$;
	invokevirtual	Method scala/io/BytePickle$.unat:()Lscala/io/BytePickle$PU;
	areturn
  Labels:
  Signature: length = 0x2
   00 FFFFFFA3 

public static final int DEF();
  Signature: ()I
  Code:
   Stack=1, Locals=0, Args_size=0
	getstatic	Field scala/io/BytePickle$.MODULE$:Lscala/io/BytePickle$;
	invokevirtual	Method scala/io/BytePickle$.DEF:()I
	ireturn
  Labels:

public static final int REF();
  Signature: ()I
  Code:
   Stack=1, Locals=0, Args_size=0
	getstatic	Field scala/io/BytePickle$.MODULE$:Lscala/io/BytePickle$;
	invokevirtual	Method scala/io/BytePickle$.REF:()I
	ireturn
  Labels:

public static final scala.io.BytePickle$PU refDef();
  Signature: ()Lscala/io/BytePickle$PU;
  Code:
   Stack=1, Locals=0, Args_size=0
	getstatic	Field scala/io/BytePickle$.MODULE$:Lscala/io/BytePickle$;
	invokevirtual	Method scala/io/BytePickle$.refDef:()Lscala/io/BytePickle$PU;
	areturn
  Labels:
  Signature: length = 0x2
   00 FFFFFFAE 

public static final java.lang.Object uunpickle(scala.io.BytePickle$PU, byte[]);
  Signature: (Lscala/io/BytePickle$PU;[B)Ljava/lang/Object;
  Code:
   Stack=3, Locals=2, Args_size=2
	getstatic	Field scala/io/BytePickle$.MODULE$:Lscala/io/BytePickle$;
	aload_0
	aload_1
	invokevirtual	Method scala/io/BytePickle$.uunpickle:(Lscala/io/BytePickle$PU;[B)Ljava/lang/Object;
	areturn
  Labels:
  Signature: length = 0x2
   00 FFFFFFB3 

public static final byte[] upickle(scala.io.BytePickle$PU, java.lang.Object);
  Signature: (Lscala/io/BytePickle$PU;Ljava/lang/Object;)[B
  Code:
   Stack=3, Locals=2, Args_size=2
	getstatic	Field scala/io/BytePickle$.MODULE$:Lscala/io/BytePickle$;
	aload_0
	aload_1
	invokevirtual	Method scala/io/BytePickle$.upickle:(Lscala/io/BytePickle$PU;Ljava/lang/Object;)[B
	areturn
  Labels:
  Signature: length = 0x2
   00 FFFFFFB8 

public static final java.lang.Object unpickle(scala.io.BytePickle$SPU, byte[]);
  Signature: (Lscala/io/BytePickle$SPU;[B)Ljava/lang/Object;
  Code:
   Stack=3, Locals=2, Args_size=2
	getstatic	Field scala/io/BytePickle$.MODULE$:Lscala/io/BytePickle$;
	aload_0
	aload_1
	invokevirtual	Method scala/io/BytePickle$.unpickle:(Lscala/io/BytePickle$SPU;[B)Ljava/lang/Object;
	areturn
  Labels:
  Signature: length = 0x2
   00 FFFFFFBD 

public static final byte[] pickle(scala.io.BytePickle$SPU, java.lang.Object);
  Signature: (Lscala/io/BytePickle$SPU;Ljava/lang/Object;)[B
  Code:
   Stack=3, Locals=2, Args_size=2
	getstatic	Field scala/io/BytePickle$.MODULE$:Lscala/io/BytePickle$;
	aload_0
	aload_1
	invokevirtual	Method scala/io/BytePickle$.pickle:(Lscala/io/BytePickle$SPU;Ljava/lang/Object;)[B
	areturn
  Labels:
  Signature: length = 0x2
   00 FFFFFFC2 

}

