Compiled from "BytePickle.scala"
public final class scala.io.BytePickle$$anonfun$triple$2$$anonfun$apply$6 extends scala.runtime.AbstractFunction1 implements java.io.Serializable
  SourceFile: "BytePickle.scala"
  Scala: length = 0x
   
  InnerClass: 
   public abstract SPU=class scala/io/BytePickle$SPU of class scala/io/BytePickle
   public final $anon$7=class scala/io/BytePickle$$anon$7 of class scala/io/BytePickle
   public final $anonfun$triple$2=class scala/io/BytePickle$$anonfun$triple$2 of class scala/io/BytePickle
   public final $anonfun$apply$6=class scala/io/BytePickle$$anonfun$triple$2$$anonfun$apply$6 of class scala/io/BytePickle$$anonfun$triple$2
   public final $anonfun$apply$8=class scala/io/BytePickle$$anonfun$triple$2$$anonfun$apply$6$$anonfun$apply$8 of class scala/io/BytePickle$$anonfun$triple$2$$anonfun$apply$6
   public final $anonfun$apply$7=class scala/io/BytePickle$$anonfun$triple$2$$anonfun$apply$6$$anonfun$apply$7 of class scala/io/BytePickle$$anonfun$triple$2$$anonfun$apply$6
  minor version: 0
  major version: 49
  Constant pool:
Asciz	SourceFile;
Asciz	BytePickle.scala;
Asciz	<clinit>;
Asciz	()V;
Asciz	Code;
Asciz	serialVersionUID;
Asciz	J;
Asciz	scala/io/BytePickle$$anonfun$triple$2$$anonfun$apply$6;
class	scala/io/BytePickle$$anonfun$triple$2$$anonfun$apply$6
NameAndType	serialVersionUID:J
Field	scala/io/BytePickle$$anonfun$triple$2$$anonfun$apply$6.serialVersionUID:J
Asciz	x$8;
Asciz	Ljava/lang/Object;;
Asciz	$outer;
Asciz	Lscala/io/BytePickle$$anonfun$triple$2;;
Asciz	<init>;
Asciz	(Lscala/io/BytePickle$$anonfun$triple$2;Ljava/lang/Object;)V;
Asciz	LineNumberTable;
Asciz	java/lang/NullPointerException;
class	java/lang/NullPointerException
NameAndType	"<init>":()V
Method	java/lang/NullPointerException."<init>":()V
NameAndType	$outer:Lscala/io/BytePickle$$anonfun$triple$2;
Field	scala/io/BytePickle$$anonfun$triple$2$$anonfun$apply$6.$outer:Lscala/io/BytePickle$$anonfun$triple$2;
NameAndType	x$8:Ljava/lang/Object;
Field	scala/io/BytePickle$$anonfun$triple$2$$anonfun$apply$6.x$8:Ljava/lang/Object;
Asciz	scala/runtime/AbstractFunction1;
class	scala/runtime/AbstractFunction1
Method	scala/runtime/AbstractFunction1."<init>":()V
Asciz	this;
Asciz	Lscala/io/BytePickle$$anonfun$triple$2$$anonfun$apply$6;;
Asciz	LocalVariableTable;
Asciz	apply;
Asciz	(Ljava/lang/Object;)Ljava/lang/Object;;
Asciz	(Ljava/lang/Object;)Lscala/io/BytePickle$SPU;;
NameAndType	apply:(Ljava/lang/Object;)Lscala/io/BytePickle$SPU;
Method	scala/io/BytePickle$$anonfun$triple$2$$anonfun$apply$6.apply:(Ljava/lang/Object;)Lscala/io/BytePickle$SPU;
Asciz	v1;
Asciz	scala/io/BytePickle$$anonfun$triple$2$$anonfun$apply$6$$anonfun$apply$7;
class	scala/io/BytePickle$$anonfun$triple$2$$anonfun$apply$6$$anonfun$apply$7
Asciz	(Lscala/io/BytePickle$$anonfun$triple$2$$anonfun$apply$6;)V;
NameAndType	"<init>":(Lscala/io/BytePickle$$anonfun$triple$2$$anonfun$apply$6;)V
Method	scala/io/BytePickle$$anonfun$triple$2$$anonfun$apply$6$$anonfun$apply$7."<init>":(Lscala/io/BytePickle$$anonfun$triple$2$$anonfun$apply$6;)V
Asciz	scala/io/BytePickle$$anonfun$triple$2;
class	scala/io/BytePickle$$anonfun$triple$2
Asciz	pc$1;
Asciz	Lscala/io/BytePickle$SPU;;
NameAndType	pc$1:Lscala/io/BytePickle$SPU;
Field	scala/io/BytePickle$$anonfun$triple$2.pc$1:Lscala/io/BytePickle$SPU;
Asciz	scala/io/BytePickle$$anonfun$triple$2$$anonfun$apply$6$$anonfun$apply$8;
class	scala/io/BytePickle$$anonfun$triple$2$$anonfun$apply$6$$anonfun$apply$8
Asciz	(Lscala/io/BytePickle$$anonfun$triple$2$$anonfun$apply$6;Ljava/lang/Object;)V;
NameAndType	"<init>":(Lscala/io/BytePickle$$anonfun$triple$2$$anonfun$apply$6;Ljava/lang/Object;)V
Method	scala/io/BytePickle$$anonfun$triple$2$$anonfun$apply$6$$anonfun$apply$8."<init>":(Lscala/io/BytePickle$$anonfun$triple$2$$anonfun$apply$6;Ljava/lang/Object;)V
Asciz	scala/io/BytePickle$$anon$7;
class	scala/io/BytePickle$$anon$7
Asciz	(Lscala/Function1;Lscala/io/BytePickle$SPU;Lscala/Function1;)V;
NameAndType	"<init>":(Lscala/Function1;Lscala/io/BytePickle$SPU;Lscala/Function1;)V
Method	scala/io/BytePickle$$anon$7."<init>":(Lscala/Function1;Lscala/io/BytePickle$SPU;Lscala/Function1;)V
Asciz	y$1;
Asciz	(Tb;)Lscala/io/BytePickle$SPU<Lscala/Tuple3<Ta;Tb;Tc;>;>;;
Asciz	Signature;
Asciz	Scala;
Asciz	InnerClasses;
Asciz	scala/io/BytePickle$SPU;
class	scala/io/BytePickle$SPU
Asciz	scala/io/BytePickle;
class	scala/io/BytePickle
Asciz	SPU;
Asciz	$anon$7;
Asciz	$anonfun$triple$2;
Asciz	$anonfun$apply$6;
Asciz	$anonfun$apply$8;
Asciz	$anonfun$apply$7;
Asciz	java/io/Serializable;
class	java/io/Serializable

{
public static final long serialVersionUID;
  Signature: J

public final java.lang.Object x$8;
  Signature: Ljava/lang/Object;

public final scala.io.BytePickle$$anonfun$triple$2 $outer;
  Signature: Lscala/io/BytePickle$$anonfun$triple$2;

public static {};
  Signature: ()V
  Code:
   Stack=2, Locals=0, Args_size=0
	lconst_0
	putstatic	Field serialVersionUID:J
	return
  Labels:

public scala.io.BytePickle$$anonfun$triple$2$$anonfun$apply$6(scala.io.BytePickle$$anonfun$triple$2, java.lang.Object);
  Signature: (Lscala/io/BytePickle$$anonfun$triple$2;Ljava/lang/Object;)V
  Code:
   Stack=2, Locals=3, Args_size=3
	aload_1
	ifnonnull	l1 // aload_0
	new	class java/lang/NullPointerException
	dup
	invokespecial	Method java/lang/NullPointerException."<init>":()V
	athrow
l1	aload_0
	aload_1
	putfield	Field $outer:Lscala/io/BytePickle$$anonfun$triple$2;
	aload_0
	aload_2
	putfield	Field x$8:Ljava/lang/Object;
	aload_0
	invokespecial	Method scala/runtime/AbstractFunction1."<init>":()V
	return
  Labels:
   	l1 = 12 // aload_0
  LocalVariableTable: 
   Start  Length  Slot  Name   Signature
   0      27      0    this       Lscala/io/BytePickle$$anonfun$triple$2$$anonfun$apply$6;
   0      27      1    $outer       Lscala/io/BytePickle$$anonfun$triple$2;


public final java.lang.Object apply(java.lang.Object);
  Signature: (Ljava/lang/Object;)Ljava/lang/Object;
  Code:
   Stack=2, Locals=2, Args_size=2
	aload_0
	aload_1
	invokevirtual	Method apply:(Ljava/lang/Object;)Lscala/io/BytePickle$SPU;
	areturn
  Labels:
  LocalVariableTable: 
   Start  Length  Slot  Name   Signature
   0      6      0    this       Lscala/io/BytePickle$$anonfun$triple$2$$anonfun$apply$6;
   0      6      1    v1       Ljava/lang/Object;


public final scala.io.BytePickle$SPU apply(java.lang.Object);
  Signature: (Ljava/lang/Object;)Lscala/io/BytePickle$SPU;
  Code:
   Stack=6, Locals=5, Args_size=2
	new	class scala/io/BytePickle$$anonfun$triple$2$$anonfun$apply$6$$anonfun$apply$7
	dup
	aload_0
	invokespecial	Method scala/io/BytePickle$$anonfun$triple$2$$anonfun$apply$6$$anonfun$apply$7."<init>":(Lscala/io/BytePickle$$anonfun$triple$2$$anonfun$apply$6;)V
	aload_0
	getfield	Field $outer:Lscala/io/BytePickle$$anonfun$triple$2;
	getfield	Field scala/io/BytePickle$$anonfun$triple$2.pc$1:Lscala/io/BytePickle$SPU;
	new	class scala/io/BytePickle$$anonfun$triple$2$$anonfun$apply$6$$anonfun$apply$8
	dup
	aload_0
	aload_1
	invokespecial	Method scala/io/BytePickle$$anonfun$triple$2$$anonfun$apply$6$$anonfun$apply$8."<init>":(Lscala/io/BytePickle$$anonfun$triple$2$$anonfun$apply$6;Ljava/lang/Object;)V
	astore	4
	astore_3
	astore_2
	new	class scala/io/BytePickle$$anon$7
	dup
	aload_2
	aload_3
	aload	4
	invokespecial	Method scala/io/BytePickle$$anon$7."<init>":(Lscala/Function1;Lscala/io/BytePickle$SPU;Lscala/Function1;)V
	areturn
  Labels:
  LocalVariableTable: 
   Start  Length  Slot  Name   Signature
   0      40      0    this       Lscala/io/BytePickle$$anonfun$triple$2$$anonfun$apply$6;
   0      40      1    y$1       Ljava/lang/Object;

  Signature: length = 0x2
   00 3D 

}

