Compiled from "BytePickle.scala"
public final class scala.io.BytePickle$$anonfun$upair$2 extends java.lang.Object implements scala.Function1,scala.ScalaObject,java.io.Serializable
  SourceFile: "BytePickle.scala"
  Scala: length = 0x
   
  InnerClass: 
   public abstract PU=class scala/io/BytePickle$PU of class scala/io/BytePickle
   public final $anon$6=class scala/io/BytePickle$$anon$6 of class scala/io/BytePickle
   public final $anonfun$upair$2=class scala/io/BytePickle$$anonfun$upair$2 of class scala/io/BytePickle
   public final $anonfun$apply$2=class scala/io/BytePickle$$anonfun$upair$2$$anonfun$apply$2 of class scala/io/BytePickle$$anonfun$upair$2
   public final $anonfun$apply$1=class scala/io/BytePickle$$anonfun$upair$2$$anonfun$apply$1 of class scala/io/BytePickle$$anonfun$upair$2
  minor version: 0
  major version: 49
  Constant pool:
Asciz	SourceFile;
Asciz	BytePickle.scala;
Asciz	<clinit>;
Asciz	()V;
Asciz	Code;
Asciz	serialVersionUID;
Asciz	J;
Asciz	scala/io/BytePickle$$anonfun$upair$2;
class	scala/io/BytePickle$$anonfun$upair$2
NameAndType	serialVersionUID:J
Field	scala/io/BytePickle$$anonfun$upair$2.serialVersionUID:J
Asciz	pb$1;
Asciz	Lscala/io/BytePickle$PU;;
Asciz	<init>;
Asciz	(Lscala/io/BytePickle$PU;)V;
Asciz	LineNumberTable;
NameAndType	pb$1:Lscala/io/BytePickle$PU;
Field	scala/io/BytePickle$$anonfun$upair$2.pb$1:Lscala/io/BytePickle$PU;
Asciz	java/lang/Object;
class	java/lang/Object
NameAndType	"<init>":()V
Method	java/lang/Object."<init>":()V
Asciz	scala/Function1$class;
class	scala/Function1$class
Asciz	$init$;
Asciz	(Lscala/Function1;)V;
NameAndType	$init$:(Lscala/Function1;)V
Method	scala/Function1$class.$init$:(Lscala/Function1;)V
Asciz	apply;
Asciz	(Ljava/lang/Object;)Ljava/lang/Object;;
Asciz	(Ljava/lang/Object;)Lscala/io/BytePickle$PU;;
NameAndType	apply:(Ljava/lang/Object;)Lscala/io/BytePickle$PU;
Method	scala/io/BytePickle$$anonfun$upair$2.apply:(Ljava/lang/Object;)Lscala/io/BytePickle$PU;
Asciz	this;
Asciz	Lscala/io/BytePickle$$anonfun$upair$2;;
Asciz	v1;
Asciz	Ljava/lang/Object;;
Asciz	LocalVariableTable;
Asciz	scala/io/BytePickle$$anonfun$upair$2$$anonfun$apply$1;
class	scala/io/BytePickle$$anonfun$upair$2$$anonfun$apply$1
Asciz	(Lscala/io/BytePickle$$anonfun$upair$2;)V;
NameAndType	"<init>":(Lscala/io/BytePickle$$anonfun$upair$2;)V
Method	scala/io/BytePickle$$anonfun$upair$2$$anonfun$apply$1."<init>":(Lscala/io/BytePickle$$anonfun$upair$2;)V
Asciz	scala/io/BytePickle$$anonfun$upair$2$$anonfun$apply$2;
class	scala/io/BytePickle$$anonfun$upair$2$$anonfun$apply$2
Asciz	(Lscala/io/BytePickle$$anonfun$upair$2;Ljava/lang/Object;)V;
NameAndType	"<init>":(Lscala/io/BytePickle$$anonfun$upair$2;Ljava/lang/Object;)V
Method	scala/io/BytePickle$$anonfun$upair$2$$anonfun$apply$2."<init>":(Lscala/io/BytePickle$$anonfun$upair$2;Ljava/lang/Object;)V
Asciz	scala/io/BytePickle$$anon$6;
class	scala/io/BytePickle$$anon$6
Asciz	(Lscala/Function1;Lscala/io/BytePickle$PU;Lscala/Function1;)V;
NameAndType	"<init>":(Lscala/Function1;Lscala/io/BytePickle$PU;Lscala/Function1;)V
Method	scala/io/BytePickle$$anon$6."<init>":(Lscala/Function1;Lscala/io/BytePickle$PU;Lscala/Function1;)V
Asciz	x$6;
Asciz	(Ta;)Lscala/io/BytePickle$PU<Lscala/Tuple2<Ta;Tb;>;>;;
Asciz	Signature;
Asciz	andThen;
Asciz	(Lscala/Function1;)Lscala/Function1;;
Asciz	(Lscala/Function1;Lscala/Function1;)Lscala/Function1;;
NameAndType	andThen:(Lscala/Function1;Lscala/Function1;)Lscala/Function1;
Method	scala/Function1$class.andThen:(Lscala/Function1;Lscala/Function1;)Lscala/Function1;
Asciz	g;
Asciz	Lscala/Function1;;
Asciz	compose;
NameAndType	compose:(Lscala/Function1;Lscala/Function1;)Lscala/Function1;
Method	scala/Function1$class.compose:(Lscala/Function1;Lscala/Function1;)Lscala/Function1;
Asciz	toString;
Asciz	()Ljava/lang/String;;
Asciz	(Lscala/Function1;)Ljava/lang/String;;
NameAndType	toString:(Lscala/Function1;)Ljava/lang/String;
Method	scala/Function1$class.toString:(Lscala/Function1;)Ljava/lang/String;
Asciz	Scala;
Asciz	InnerClasses;
Asciz	scala/io/BytePickle$PU;
class	scala/io/BytePickle$PU
Asciz	scala/io/BytePickle;
class	scala/io/BytePickle
Asciz	PU;
Asciz	$anon$6;
Asciz	$anonfun$upair$2;
Asciz	$anonfun$apply$2;
Asciz	$anonfun$apply$1;
Asciz	scala/Function1;
class	scala/Function1
Asciz	scala/ScalaObject;
class	scala/ScalaObject
Asciz	java/io/Serializable;
class	java/io/Serializable

{
public static final long serialVersionUID;
  Signature: J

private final scala.io.BytePickle$PU pb$1;
  Signature: Lscala/io/BytePickle$PU;

public static {};
  Signature: ()V
  Code:
   Stack=2, Locals=0, Args_size=0
	lconst_0
	putstatic	Field serialVersionUID:J
	return
  Labels:

public scala.io.BytePickle$$anonfun$upair$2(scala.io.BytePickle$PU);
  Signature: (Lscala/io/BytePickle$PU;)V
  Code:
   Stack=2, Locals=2, Args_size=2
	aload_0
	aload_1
	putfield	Field pb$1:Lscala/io/BytePickle$PU;
	aload_0
	invokespecial	Method java/lang/Object."<init>":()V
	aload_0
	invokestatic	Method scala/Function1$class.$init$:(Lscala/Function1;)V
	return
  Labels:

public final java.lang.Object apply(java.lang.Object);
  Signature: (Ljava/lang/Object;)Ljava/lang/Object;
  Code:
   Stack=2, Locals=2, Args_size=2
	aload_0
	aload_1
	invokevirtual	Method apply:(Ljava/lang/Object;)Lscala/io/BytePickle$PU;
	areturn
  Labels:
  LocalVariableTable: 
   Start  Length  Slot  Name   Signature
   0      6      0    this       Lscala/io/BytePickle$$anonfun$upair$2;
   0      6      1    v1       Ljava/lang/Object;


public final scala.io.BytePickle$PU apply(java.lang.Object);
  Signature: (Ljava/lang/Object;)Lscala/io/BytePickle$PU;
  Code:
   Stack=6, Locals=5, Args_size=2
	new	class scala/io/BytePickle$$anonfun$upair$2$$anonfun$apply$1
	dup
	aload_0
	invokespecial	Method scala/io/BytePickle$$anonfun$upair$2$$anonfun$apply$1."<init>":(Lscala/io/BytePickle$$anonfun$upair$2;)V
	aload_0
	getfield	Field pb$1:Lscala/io/BytePickle$PU;
	new	class scala/io/BytePickle$$anonfun$upair$2$$anonfun$apply$2
	dup
	aload_0
	aload_1
	invokespecial	Method scala/io/BytePickle$$anonfun$upair$2$$anonfun$apply$2."<init>":(Lscala/io/BytePickle$$anonfun$upair$2;Ljava/lang/Object;)V
	astore	4
	astore_3
	astore_2
	new	class scala/io/BytePickle$$anon$6
	dup
	aload_2
	aload_3
	aload	4
	invokespecial	Method scala/io/BytePickle$$anon$6."<init>":(Lscala/Function1;Lscala/io/BytePickle$PU;Lscala/Function1;)V
	areturn
  Labels:
  LocalVariableTable: 
   Start  Length  Slot  Name   Signature
   0      37      0    this       Lscala/io/BytePickle$$anonfun$upair$2;
   0      37      1    x$6       Ljava/lang/Object;

  Signature: length = 0x2
   00 37 

public scala.Function1 andThen(scala.Function1);
  Signature: (Lscala/Function1;)Lscala/Function1;
  Code:
   Stack=2, Locals=2, Args_size=2
	aload_0
	aload_1
	invokestatic	Method scala/Function1$class.andThen:(Lscala/Function1;Lscala/Function1;)Lscala/Function1;
	areturn
  Labels:
  LocalVariableTable: 
   Start  Length  Slot  Name   Signature
   0      6      0    this       Lscala/io/BytePickle$$anonfun$upair$2;
   0      6      1    g       Lscala/Function1;


public scala.Function1 compose(scala.Function1);
  Signature: (Lscala/Function1;)Lscala/Function1;
  Code:
   Stack=2, Locals=2, Args_size=2
	aload_0
	aload_1
	invokestatic	Method scala/Function1$class.compose:(Lscala/Function1;Lscala/Function1;)Lscala/Function1;
	areturn
  Labels:
  LocalVariableTable: 
   Start  Length  Slot  Name   Signature
   0      6      0    this       Lscala/io/BytePickle$$anonfun$upair$2;
   0      6      1    g       Lscala/Function1;


public java.lang.String toString();
  Signature: ()Ljava/lang/String;
  Code:
   Stack=1, Locals=1, Args_size=1
	aload_0
	invokestatic	Method scala/Function1$class.toString:(Lscala/Function1;)Ljava/lang/String;
	areturn
  Labels:

}

