Compiled from "BytePickle.scala"
public final class scala.io.BytePickle$$anon$7 extends scala.io.BytePickle$SPU
  SourceFile: "BytePickle.scala"
  Scala: length = 0x
   
  Signature: length = 0x2
   00 43 
  InnerClass: 
   public abstract SPU=class scala/io/BytePickle$SPU of class scala/io/BytePickle
   public final $anon$7=class scala/io/BytePickle$$anon$7 of class scala/io/BytePickle
   public PicklerState=class scala/io/BytePickle$PicklerState of class scala/io/BytePickle
   public UnPicklerState=class scala/io/BytePickle$UnPicklerState of class scala/io/BytePickle
  minor version: 0
  major version: 49
  Constant pool:
Asciz	SourceFile;
Asciz	BytePickle.scala;
Asciz	f$2;
Asciz	Lscala/Function1;;
Asciz	pa$3;
Asciz	Lscala/io/BytePickle$SPU;;
Asciz	k$2;
Asciz	appP;
Asciz	(Ljava/lang/Object;Lscala/io/BytePickle$PicklerState;)Lscala/io/BytePickle$PicklerState;;
Asciz	Code;
Asciz	LineNumberTable;
Asciz	scala/io/BytePickle$$anon$7;
class	scala/io/BytePickle$$anon$7
NameAndType	f$2:Lscala/Function1;
Field	scala/io/BytePickle$$anon$7.f$2:Lscala/Function1;
Asciz	scala/Function1;
class	scala/Function1
Asciz	apply;
Asciz	(Ljava/lang/Object;)Ljava/lang/Object;;
NameAndType	apply:(Ljava/lang/Object;)Ljava/lang/Object;
InterfaceMethod	scala/Function1.apply:(Ljava/lang/Object;)Ljava/lang/Object;
NameAndType	pa$3:Lscala/io/BytePickle$SPU;
Field	scala/io/BytePickle$$anon$7.pa$3:Lscala/io/BytePickle$SPU;
Asciz	scala/io/BytePickle$SPU;
class	scala/io/BytePickle$SPU
NameAndType	appP:(Ljava/lang/Object;Lscala/io/BytePickle$PicklerState;)Lscala/io/BytePickle$PicklerState;
Method	scala/io/BytePickle$SPU.appP:(Ljava/lang/Object;Lscala/io/BytePickle$PicklerState;)Lscala/io/BytePickle$PicklerState;
NameAndType	k$2:Lscala/Function1;
Field	scala/io/BytePickle$$anon$7.k$2:Lscala/Function1;
Asciz	this;
Asciz	Lscala/io/BytePickle$$anon$7;;
Asciz	b;
Asciz	Ljava/lang/Object;;
Asciz	s;
Asciz	Lscala/io/BytePickle$PicklerState;;
Asciz	a;
Asciz	sPrime;
Asciz	pb;
Asciz	LocalVariableTable;
Asciz	(Tu;Lscala/io/BytePickle$PicklerState;)Lscala/io/BytePickle$PicklerState;;
Asciz	Signature;
Asciz	appU;
Asciz	(Lscala/io/BytePickle$UnPicklerState;)Lscala/Tuple2;;
NameAndType	appU:(Lscala/io/BytePickle$UnPicklerState;)Lscala/Tuple2;
Method	scala/io/BytePickle$SPU.appU:(Lscala/io/BytePickle$UnPicklerState;)Lscala/Tuple2;
Asciz	scala/Tuple2;
class	scala/Tuple2
Asciz	_1;
Asciz	()Ljava/lang/Object;;
NameAndType	_1:()Ljava/lang/Object;
Method	scala/Tuple2._1:()Ljava/lang/Object;
Asciz	_2;
NameAndType	_2:()Ljava/lang/Object;
Method	scala/Tuple2._2:()Ljava/lang/Object;
Asciz	scala/io/BytePickle$UnPicklerState;
class	scala/io/BytePickle$UnPicklerState
Asciz	Lscala/io/BytePickle$UnPicklerState;;
Asciz	resPa;
Asciz	Lscala/Tuple2;;
Asciz	(Lscala/io/BytePickle$UnPicklerState;)Lscala/Tuple2<Tu;Lscala/io/BytePickle$UnPicklerState;>;;
Asciz	<init>;
Asciz	(Lscala/Function1;Lscala/io/BytePickle$SPU;Lscala/Function1;)V;
Asciz	()V;
NameAndType	"<init>":()V
Method	scala/io/BytePickle$SPU."<init>":()V
Asciz	Scala;
Asciz	Lscala/io/BytePickle$SPU<Tu;>;;
Asciz	InnerClasses;
Asciz	scala/io/BytePickle;
class	scala/io/BytePickle
Asciz	SPU;
Asciz	$anon$7;
Asciz	scala/io/BytePickle$PicklerState;
class	scala/io/BytePickle$PicklerState
Asciz	PicklerState;
Asciz	UnPicklerState;

{
private final scala.Function1 f$2;
  Signature: Lscala/Function1;

private final scala.io.BytePickle$SPU pa$3;
  Signature: Lscala/io/BytePickle$SPU;

private final scala.Function1 k$2;
  Signature: Lscala/Function1;

public scala.io.BytePickle$PicklerState appP(java.lang.Object, scala.io.BytePickle$PicklerState);
  Signature: (Ljava/lang/Object;Lscala/io/BytePickle$PicklerState;)Lscala/io/BytePickle$PicklerState;
  Code:
   Stack=3, Locals=6, Args_size=3
	aload_0
	getfield	Field f$2:Lscala/Function1;
	aload_1
	invokeinterface	InterfaceMethod scala/Function1.apply:(Ljava/lang/Object;)Ljava/lang/Object;
	astore_3
	aload_0
	getfield	Field pa$3:Lscala/io/BytePickle$SPU;
	aload_3
	aload_2
	invokevirtual	Method scala/io/BytePickle$SPU.appP:(Ljava/lang/Object;Lscala/io/BytePickle$PicklerState;)Lscala/io/BytePickle$PicklerState;
	astore	4
	aload_0
	getfield	Field k$2:Lscala/Function1;
	aload_3
	invokeinterface	InterfaceMethod scala/Function1.apply:(Ljava/lang/Object;)Ljava/lang/Object;
	checkcast	class scala/io/BytePickle$SPU
	astore	5
	aload	5
	aload_1
	aload	4
	invokevirtual	Method scala/io/BytePickle$SPU.appP:(Ljava/lang/Object;Lscala/io/BytePickle$PicklerState;)Lscala/io/BytePickle$PicklerState;
	areturn
  Labels:
  LocalVariableTable: 
   Start  Length  Slot  Name   Signature
   0      46      0    this       Lscala/io/BytePickle$$anon$7;
   0      46      1    b       Ljava/lang/Object;
   0      46      2    s       Lscala/io/BytePickle$PicklerState;
   11      34      3    a       Ljava/lang/Object;
   22      23      4    sPrime       Lscala/io/BytePickle$PicklerState;
   37      8      5    pb       Lscala/io/BytePickle$SPU;

  Signature: length = 0x2
   00 28 

public scala.Tuple2 appU(scala.io.BytePickle$UnPicklerState);
  Signature: (Lscala/io/BytePickle$UnPicklerState;)Lscala/Tuple2;
  Code:
   Stack=2, Locals=6, Args_size=2
	aload_0
	getfield	Field pa$3:Lscala/io/BytePickle$SPU;
	aload_1
	invokevirtual	Method scala/io/BytePickle$SPU.appU:(Lscala/io/BytePickle$UnPicklerState;)Lscala/Tuple2;
	astore_2
	aload_2
	invokevirtual	Method scala/Tuple2._1:()Ljava/lang/Object;
	astore_3
	aload_2
	invokevirtual	Method scala/Tuple2._2:()Ljava/lang/Object;
	checkcast	class scala/io/BytePickle$UnPicklerState
	astore	4
	aload_0
	getfield	Field k$2:Lscala/Function1;
	aload_3
	invokeinterface	InterfaceMethod scala/Function1.apply:(Ljava/lang/Object;)Ljava/lang/Object;
	checkcast	class scala/io/BytePickle$SPU
	astore	5
	aload	5
	aload	4
	invokevirtual	Method scala/io/BytePickle$SPU.appU:(Lscala/io/BytePickle$UnPicklerState;)Lscala/Tuple2;
	areturn
  Labels:
  LocalVariableTable: 
   Start  Length  Slot  Name   Signature
   0      46      0    this       Lscala/io/BytePickle$$anon$7;
   0      46      1    s       Lscala/io/BytePickle$UnPicklerState;
   9      36      2    resPa       Lscala/Tuple2;
   14      31      3    a       Ljava/lang/Object;
   23      22      4    sPrime       Lscala/io/BytePickle$UnPicklerState;
   38      7      5    pb       Lscala/io/BytePickle$SPU;

  Signature: length = 0x2
   00 3C 

public scala.io.BytePickle$$anon$7(scala.Function1, scala.io.BytePickle$SPU, scala.Function1);
  Signature: (Lscala/Function1;Lscala/io/BytePickle$SPU;Lscala/Function1;)V
  Code:
   Stack=2, Locals=4, Args_size=4
	aload_0
	aload_1
	putfield	Field f$2:Lscala/Function1;
	aload_0
	aload_2
	putfield	Field pa$3:Lscala/io/BytePickle$SPU;
	aload_0
	aload_3
	putfield	Field k$2:Lscala/Function1;
	aload_0
	invokespecial	Method scala/io/BytePickle$SPU."<init>":()V
	return
  Labels:

}

