Compiled from "BytePickle.scala"
public class scala.io.BytePickle$PicklerEnv extends scala.collection.mutable.HashMap implements scala.ScalaObject
  SourceFile: "BytePickle.scala"
  Signature: length = 0x2
   00 1A 
  Scala: length = 0x
   
  InnerClass: 
   public PicklerEnv=class scala/io/BytePickle$PicklerEnv of class scala/io/BytePickle
  minor version: 0
  major version: 49
  Constant pool:
Asciz	SourceFile;
Asciz	BytePickle.scala;
Asciz	cnt;
Asciz	I;
Asciz	<init>;
Asciz	()V;
Asciz	Code;
Asciz	LineNumberTable;
Asciz	scala/collection/mutable/HashMap;
class	scala/collection/mutable/HashMap
NameAndType	"<init>":()V
Method	scala/collection/mutable/HashMap."<init>":()V
int	64;
Asciz	scala/io/BytePickle$PicklerEnv;
class	scala/io/BytePickle$PicklerEnv
NameAndType	cnt:I
Field	scala/io/BytePickle$PicklerEnv.cnt:I
Asciz	nextLoc;
Asciz	()I;
NameAndType	cnt:()I
Method	scala/io/BytePickle$PicklerEnv.cnt:()I
Asciz	cnt_$eq;
Asciz	(I)V;
NameAndType	cnt_$eq:(I)V
Method	scala/io/BytePickle$PicklerEnv.cnt_$eq:(I)V
Asciz	Lscala/collection/mutable/HashMap<Ljava/lang/Object;Ljava/lang/Integer;>;Lscala/ScalaObject;;
Asciz	Signature;
Asciz	Scala;
Asciz	InnerClasses;
Asciz	scala/io/BytePickle;
class	scala/io/BytePickle
Asciz	PicklerEnv;
Asciz	scala/ScalaObject;
class	scala/ScalaObject

{
private int cnt;
  Signature: I

public scala.io.BytePickle$PicklerEnv();
  Signature: ()V
  Code:
   Stack=2, Locals=1, Args_size=1
	aload_0
	invokespecial	Method scala/collection/mutable/HashMap."<init>":()V
	aload_0
	ldc	int 64
	putfield	Field cnt:I
	return
  Labels:

public int nextLoc();
  Signature: ()I
  Code:
   Stack=3, Locals=1, Args_size=1
	aload_0
	aload_0
	invokespecial	Method cnt:()I
	iconst_1
	iadd
	invokespecial	Method cnt_$eq:(I)V
	aload_0
	invokespecial	Method cnt:()I
	ireturn
  Labels:

private void cnt_$eq(int);
  Signature: (I)V
  Code:
   Stack=2, Locals=2, Args_size=2
	aload_0
	iload_1
	putfield	Field cnt:I
	return
  Labels:

private int cnt();
  Signature: ()I
  Code:
   Stack=1, Locals=1, Args_size=1
	aload_0
	getfield	Field cnt:I
	ireturn
  Labels:

}

