Compiled from "BytePickle.scala"
public final class scala.io.BytePickle$$anonfun$fixedList$2 extends scala.runtime.AbstractFunction1 implements java.io.Serializable
  SourceFile: "BytePickle.scala"
  Scala: length = 0x
   
  InnerClass: 
   public final #45= #9 of #44; //$anonfun$fixedList$2=class scala/io/BytePickle$$anonfun$fixedList$2 of class scala/io/BytePickle
  minor version: 0
  major version: 49
  Constant pool:
const #1 = Asciz	SourceFile;
const #2 = Asciz	BytePickle.scala;
const #3 = Asciz	<clinit>;
const #4 = Asciz	()V;
const #5 = Asciz	Code;
const #6 = Asciz	serialVersionUID;
const #7 = Asciz	J;
const #8 = Asciz	scala/io/BytePickle$$anonfun$fixedList$2;
const #9 = class	#8;	//  scala/io/BytePickle$$anonfun$fixedList$2
const #10 = NameAndType	#6:#7;//  serialVersionUID:J
const #11 = Field	#9.#10;	//  scala/io/BytePickle$$anonfun$fixedList$2.serialVersionUID:J
const #12 = Asciz	<init>;
const #13 = Asciz	LineNumberTable;
const #14 = Asciz	scala/runtime/AbstractFunction1;
const #15 = class	#14;	//  scala/runtime/AbstractFunction1
const #16 = NameAndType	#12:#4;//  "<init>":()V
const #17 = Method	#15.#16;	//  scala/runtime/AbstractFunction1."<init>":()V
const #18 = Asciz	apply;
const #19 = Asciz	(Ljava/lang/Object;)Ljava/lang/Object;;
const #20 = Asciz	scala/collection/immutable/List;
const #21 = class	#20;	//  scala/collection/immutable/List
const #22 = Asciz	(Lscala/collection/immutable/List;)Lscala/Tuple2;;
const #23 = NameAndType	#18:#22;//  apply:(Lscala/collection/immutable/List;)Lscala/Tuple2;
const #24 = Method	#9.#23;	//  scala/io/BytePickle$$anonfun$fixedList$2.apply:(Lscala/collection/immutable/List;)Lscala/Tuple2;
const #25 = Asciz	this;
const #26 = Asciz	Lscala/io/BytePickle$$anonfun$fixedList$2;;
const #27 = Asciz	v1;
const #28 = Asciz	Ljava/lang/Object;;
const #29 = Asciz	LocalVariableTable;
const #30 = Asciz	scala/io/BytePickle$;
const #31 = class	#30;	//  scala/io/BytePickle$
const #32 = Asciz	MODULE$;
const #33 = Asciz	Lscala/io/BytePickle$;;
const #34 = NameAndType	#32:#33;//  MODULE$:Lscala/io/BytePickle$;
const #35 = Field	#31.#34;	//  scala/io/BytePickle$.MODULE$:Lscala/io/BytePickle$;
const #36 = Asciz	listToPair$2;
const #37 = NameAndType	#36:#22;//  listToPair$2:(Lscala/collection/immutable/List;)Lscala/Tuple2;
const #38 = Method	#31.#37;	//  scala/io/BytePickle$.listToPair$2:(Lscala/collection/immutable/List;)Lscala/Tuple2;
const #39 = Asciz	(Lscala/collection/immutable/List<Ta;>;)Lscala/Tuple2<Ta;Lscala/collection/immutable/List<Ta;>;>;;
const #40 = Asciz	Signature;
const #41 = Asciz	Scala;
const #42 = Asciz	InnerClasses;
const #43 = Asciz	scala/io/BytePickle;
const #44 = class	#43;	//  scala/io/BytePickle
const #45 = Asciz	$anonfun$fixedList$2;
const #46 = Asciz	java/io/Serializable;
const #47 = class	#46;	//  java/io/Serializable

{
public static final long serialVersionUID;

public static {};
  Code:
   Stack=2, Locals=0, Args_size=0
   0:	lconst_0
   1:	putstatic	#11; //Field serialVersionUID:J
   4:	return

public scala.io.BytePickle$$anonfun$fixedList$2();
  Code:
   Stack=1, Locals=1, Args_size=1
   0:	aload_0
   1:	invokespecial	#17; //Method scala/runtime/AbstractFunction1."<init>":()V
   4:	return
  LineNumberTable: 
   line 309: 0


public final java.lang.Object apply(java.lang.Object);
  Code:
   Stack=2, Locals=2, Args_size=2
   0:	aload_0
   1:	aload_1
   2:	checkcast	#21; //class scala/collection/immutable/List
   5:	invokevirtual	#24; //Method apply:(Lscala/collection/immutable/List;)Lscala/Tuple2;
   8:	areturn
  LineNumberTable: 
   line 309: 0

  LocalVariableTable: 
   Start  Length  Slot  Name   Signature
   0      9      0    this       Lscala/io/BytePickle$$anonfun$fixedList$2;
   0      9      1    v1       Ljava/lang/Object;


public final scala.Tuple2 apply(scala.collection.immutable.List);
  Code:
   Stack=2, Locals=2, Args_size=2
   0:	getstatic	#35; //Field scala/io/BytePickle$.MODULE$:Lscala/io/BytePickle$;
   3:	aload_1
   4:	invokevirtual	#38; //Method scala/io/BytePickle$.listToPair$2:(Lscala/collection/immutable/List;)Lscala/Tuple2;
   7:	areturn
  LineNumberTable: 
   line 309: 0

  Signature: length = 0x2
   00 27 

}

