Compiled from "BytePickle.scala"
public final class scala.io.BytePickle$$anon$4 extends scala.io.BytePickle$PU
  SourceFile: "BytePickle.scala"
  Signature: length = 0x2
   00 49 
  Scala: length = 0x
   
  InnerClass: 
   public abstract #78= #14 of #77; //PU=class scala/io/BytePickle$PU of class scala/io/BytePickle
   public final #79= #10 of #77; //$anon$4=class scala/io/BytePickle$$anon$4 of class scala/io/BytePickle
  minor version: 0
  major version: 49
  Constant pool:
const #1 = Asciz	SourceFile;
const #2 = Asciz	BytePickle.scala;
const #3 = Asciz	x$4;
const #4 = Asciz	Ljava/lang/Object;;
const #5 = Asciz	<init>;
const #6 = Asciz	(Ljava/lang/Object;)V;
const #7 = Asciz	Code;
const #8 = Asciz	LineNumberTable;
const #9 = Asciz	scala/io/BytePickle$$anon$4;
const #10 = class	#9;	//  scala/io/BytePickle$$anon$4
const #11 = NameAndType	#3:#4;//  x$4:Ljava/lang/Object;
const #12 = Field	#10.#11;	//  scala/io/BytePickle$$anon$4.x$4:Ljava/lang/Object;
const #13 = Asciz	scala/io/BytePickle$PU;
const #14 = class	#13;	//  scala/io/BytePickle$PU
const #15 = Asciz	()V;
const #16 = NameAndType	#5:#15;//  "<init>":()V
const #17 = Method	#14.#16;	//  scala/io/BytePickle$PU."<init>":()V
const #18 = Asciz	appU;
const #19 = Asciz	([B)Lscala/Tuple2;;
const #20 = Asciz	scala/Tuple2;
const #21 = class	#20;	//  scala/Tuple2
const #22 = Asciz	(Ljava/lang/Object;Ljava/lang/Object;)V;
const #23 = NameAndType	#5:#22;//  "<init>":(Ljava/lang/Object;Ljava/lang/Object;)V
const #24 = Method	#21.#23;	//  scala/Tuple2."<init>":(Ljava/lang/Object;Ljava/lang/Object;)V
const #25 = Asciz	this;
const #26 = Asciz	Lscala/io/BytePickle$$anon$4;;
const #27 = Asciz	state;
const #28 = Asciz	[B;
const #29 = Asciz	LocalVariableTable;
const #30 = Asciz	([B)Lscala/Tuple2<Tt;[B>;;
const #31 = Asciz	Signature;
const #32 = Asciz	appP;
const #33 = Asciz	(Ljava/lang/Object;[B)[B;
const #34 = Asciz	java/lang/Number;
const #35 = class	#34;	//  java/lang/Number
const #36 = Asciz	java/lang/Character;
const #37 = class	#36;	//  java/lang/Character
const #38 = Asciz	scala/runtime/BoxesRunTime;
const #39 = class	#38;	//  scala/runtime/BoxesRunTime
const #40 = Asciz	equals2;
const #41 = Asciz	(Ljava/lang/Object;Ljava/lang/Object;)Z;
const #42 = NameAndType	#40:#41;//  equals2:(Ljava/lang/Object;Ljava/lang/Object;)Z
const #43 = Method	#39.#42;	//  scala/runtime/BoxesRunTime.equals2:(Ljava/lang/Object;Ljava/lang/Object;)Z
const #44 = Asciz	java/lang/Object;
const #45 = class	#44;	//  java/lang/Object
const #46 = Asciz	equals;
const #47 = Asciz	(Ljava/lang/Object;)Z;
const #48 = NameAndType	#46:#47;//  equals:(Ljava/lang/Object;)Z
const #49 = Method	#45.#48;	//  java/lang/Object.equals:(Ljava/lang/Object;)Z
const #50 = Asciz	java/lang/IllegalArgumentException;
const #51 = class	#50;	//  java/lang/IllegalArgumentException
const #52 = Asciz	scala/collection/mutable/StringBuilder;
const #53 = class	#52;	//  scala/collection/mutable/StringBuilder
const #54 = Method	#53.#16;	//  scala/collection/mutable/StringBuilder."<init>":()V
const #55 = Asciz	value to be pickled (;
const #56 = String	#55;	//  value to be pickled (
const #57 = Asciz	append;
const #58 = Asciz	(Ljava/lang/Object;)Lscala/collection/mutable/StringBuilder;;
const #59 = NameAndType	#57:#58;//  append:(Ljava/lang/Object;)Lscala/collection/mutable/StringBuilder;
const #60 = Method	#53.#59;	//  scala/collection/mutable/StringBuilder.append:(Ljava/lang/Object;)Lscala/collection/mutable/StringBuilder;
const #61 = Asciz	) != ;
const #62 = String	#61;	//  ) != 
const #63 = Asciz	toString;
const #64 = Asciz	()Ljava/lang/String;;
const #65 = NameAndType	#63:#64;//  toString:()Ljava/lang/String;
const #66 = Method	#53.#65;	//  scala/collection/mutable/StringBuilder.toString:()Ljava/lang/String;
const #67 = Asciz	(Ljava/lang/String;)V;
const #68 = NameAndType	#5:#67;//  "<init>":(Ljava/lang/String;)V
const #69 = Method	#51.#68;	//  java/lang/IllegalArgumentException."<init>":(Ljava/lang/String;)V
const #70 = Asciz	a;
const #71 = Asciz	x0;
const #72 = Asciz	(Tt;[B)[B;
const #73 = Asciz	Lscala/io/BytePickle$PU<Tt;>;;
const #74 = Asciz	Scala;
const #75 = Asciz	InnerClasses;
const #76 = Asciz	scala/io/BytePickle;
const #77 = class	#76;	//  scala/io/BytePickle
const #78 = Asciz	PU;
const #79 = Asciz	$anon$4;

{
public scala.io.BytePickle$$anon$4(java.lang.Object);
  Code:
   Stack=2, Locals=2, Args_size=2
   0:	aload_0
   1:	aload_1
   2:	putfield	#12; //Field x$4:Ljava/lang/Object;
   5:	aload_0
   6:	invokespecial	#17; //Method scala/io/BytePickle$PU."<init>":()V
   9:	return
  LineNumberTable: 
   line 155: 0


public scala.Tuple2 appU(byte[]);
  Code:
   Stack=4, Locals=2, Args_size=2
   0:	new	#21; //class scala/Tuple2
   3:	dup
   4:	aload_0
   5:	getfield	#12; //Field x$4:Ljava/lang/Object;
   8:	aload_1
   9:	invokespecial	#24; //Method scala/Tuple2."<init>":(Ljava/lang/Object;Ljava/lang/Object;)V
   12:	areturn
  LineNumberTable: 
   line 159: 0

  LocalVariableTable: 
   Start  Length  Slot  Name   Signature
   0      13      0    this       Lscala/io/BytePickle$$anon$4;
   0      13      1    state       [B

  Signature: length = 0x2
   00 1E 

public byte[] appP(java.lang.Object, byte[]);
  Code:
   Stack=4, Locals=4, Args_size=3
   0:	aload_0
   1:	getfield	#12; //Field x$4:Ljava/lang/Object;
   4:	astore_3
   5:	aload_3
   6:	aload_1
   7:	if_acmpne	14
   10:	iconst_1
   11:	goto	49
   14:	aload_3
   15:	ifnonnull	22
   18:	iconst_0
   19:	goto	49
   22:	aload_3
   23:	instanceof	#35; //class java/lang/Number
   26:	ifne	36
   29:	aload_3
   30:	instanceof	#37; //class java/lang/Character
   33:	ifeq	44
   36:	aload_3
   37:	aload_1
   38:	invokestatic	#43; //Method scala/runtime/BoxesRunTime.equals2:(Ljava/lang/Object;Ljava/lang/Object;)Z
   41:	goto	49
   44:	aload_3
   45:	aload_1
   46:	invokevirtual	#49; //Method java/lang/Object.equals:(Ljava/lang/Object;)Z
   49:	ifeq	54
   52:	aload_2
   53:	areturn
   54:	new	#51; //class java/lang/IllegalArgumentException
   57:	dup
   58:	new	#53; //class scala/collection/mutable/StringBuilder
   61:	dup
   62:	invokespecial	#54; //Method scala/collection/mutable/StringBuilder."<init>":()V
   65:	ldc	#56; //String value to be pickled (
   67:	invokevirtual	#60; //Method scala/collection/mutable/StringBuilder.append:(Ljava/lang/Object;)Lscala/collection/mutable/StringBuilder;
   70:	aload_1
   71:	invokevirtual	#60; //Method scala/collection/mutable/StringBuilder.append:(Ljava/lang/Object;)Lscala/collection/mutable/StringBuilder;
   74:	ldc	#62; //String ) != 
   76:	invokevirtual	#60; //Method scala/collection/mutable/StringBuilder.append:(Ljava/lang/Object;)Lscala/collection/mutable/StringBuilder;
   79:	aload_0
   80:	getfield	#12; //Field x$4:Ljava/lang/Object;
   83:	invokevirtual	#60; //Method scala/collection/mutable/StringBuilder.append:(Ljava/lang/Object;)Lscala/collection/mutable/StringBuilder;
   86:	invokevirtual	#66; //Method scala/collection/mutable/StringBuilder.toString:()Ljava/lang/String;
   89:	invokespecial	#69; //Method java/lang/IllegalArgumentException."<init>":(Ljava/lang/String;)V
   92:	athrow
  LineNumberTable: 
   line 157: 0
   line 158: 52
   line 157: 53

  LocalVariableTable: 
   Start  Length  Slot  Name   Signature
   0      93      0    this       Lscala/io/BytePickle$$anon$4;
   0      93      1    a       Ljava/lang/Object;
   0      93      2    state       [B
   10      42      3    x0       Ljava/lang/Object;

  Signature: length = 0x2
   00 48 

}

