Compiled from "BytePickle.scala"
public final class scala.io.BytePickle$$anon$2 extends scala.io.BytePickle$PU
  SourceFile: "BytePickle.scala"
  Signature: length = 0x2
   00 77 
  Scala: length = 0x
   
  InnerClass: 
   public abstract PU=class scala/io/BytePickle$PU of class scala/io/BytePickle
   public final $anon$2=class scala/io/BytePickle$$anon$2 of class scala/io/BytePickle
  minor version: 0
  major version: 49
  Constant pool:
Asciz	SourceFile;
Asciz	BytePickle.scala;
Asciz	<init>;
Asciz	()V;
Asciz	Code;
Asciz	LineNumberTable;
Asciz	scala/io/BytePickle$PU;
class	scala/io/BytePickle$PU
NameAndType	"<init>":()V
Method	scala/io/BytePickle$PU."<init>":()V
Asciz	readNat$1;
Asciz	([BLscala/runtime/IntRef;)I;
Asciz	scala/runtime/IntRef;
class	scala/runtime/IntRef
Asciz	elem;
Asciz	I;
NameAndType	elem:I
Field	scala/runtime/IntRef.elem:I
int	7;
int	127;
int	128;
Asciz	this;
Asciz	Lscala/io/BytePickle$$anon$2;;
Asciz	b;
Asciz	x;
Asciz	LocalVariableTable;
Asciz	appP;
Asciz	(Ljava/lang/Object;[B)[B;
Asciz	scala/runtime/BoxesRunTime;
class	scala/runtime/BoxesRunTime
Asciz	unboxToInt;
Asciz	(Ljava/lang/Object;)I;
NameAndType	unboxToInt:(Ljava/lang/Object;)I
Method	scala/runtime/BoxesRunTime.unboxToInt:(Ljava/lang/Object;)I
Asciz	scala/io/BytePickle$$anon$2;
class	scala/io/BytePickle$$anon$2
Asciz	(I[B)[B;
NameAndType	appP:(I[B)[B
Method	scala/io/BytePickle$$anon$2.appP:(I[B)[B
Asciz	a;
Asciz	Ljava/lang/Object;;
Asciz	state;
Asciz	[B;
Asciz	appU;
Asciz	([B)Lscala/Tuple2;;
Asciz	(I)V;
NameAndType	"<init>":(I)V
Method	scala/runtime/IntRef."<init>":(I)V
Asciz	scala/Tuple2;
class	scala/Tuple2
NameAndType	readNat$1:([BLscala/runtime/IntRef;)I
Method	scala/io/BytePickle$$anon$2.readNat$1:([BLscala/runtime/IntRef;)I
Asciz	boxToInteger;
Asciz	(I)Ljava/lang/Integer;;
NameAndType	boxToInteger:(I)Ljava/lang/Integer;
Method	scala/runtime/BoxesRunTime.boxToInteger:(I)Ljava/lang/Integer;
Asciz	scala/Predef$;
class	scala/Predef$
Asciz	MODULE$;
Asciz	Lscala/Predef$;;
NameAndType	MODULE$:Lscala/Predef$;
Field	scala/Predef$.MODULE$:Lscala/Predef$;
Asciz	byteArrayOps;
Asciz	([B)Lscala/collection/mutable/ArrayOps;;
NameAndType	byteArrayOps:([B)Lscala/collection/mutable/ArrayOps;
Method	scala/Predef$.byteArrayOps:([B)Lscala/collection/mutable/ArrayOps;
Asciz	scala/collection/IndexedSeqLike;
class	scala/collection/IndexedSeqLike
Asciz	slice;
Asciz	(II)Ljava/lang/Object;;
NameAndType	slice:(II)Ljava/lang/Object;
InterfaceMethod	scala/collection/IndexedSeqLike.slice:(II)Ljava/lang/Object;
Asciz	(Ljava/lang/Object;Ljava/lang/Object;)V;
NameAndType	"<init>":(Ljava/lang/Object;Ljava/lang/Object;)V
Method	scala/Tuple2."<init>":(Ljava/lang/Object;Ljava/lang/Object;)V
Asciz	s$1;
Asciz	num$1;
Asciz	Lscala/runtime/IntRef;;
Asciz	([B)Lscala/Tuple2<Ljava/lang/Integer;[B>;;
Asciz	Signature;
Asciz	scala/Array$;
class	scala/Array$
Asciz	Lscala/Array$;;
NameAndType	MODULE$:Lscala/Array$;
Field	scala/Array$.MODULE$:Lscala/Array$;
class	"[B"
Asciz	scala/io/BytePickle$;
class	scala/io/BytePickle$
Asciz	Lscala/io/BytePickle$;;
NameAndType	MODULE$:Lscala/io/BytePickle$;
Field	scala/io/BytePickle$.MODULE$:Lscala/io/BytePickle$;
Asciz	nat2Bytes;
Asciz	(I)[B;
NameAndType	nat2Bytes:(I)[B
Method	scala/io/BytePickle$.nat2Bytes:(I)[B
Asciz	[Ljava/lang/Object;;
class	"[Ljava/lang/Object;"
Asciz	wrapRefArray;
Asciz	([Ljava/lang/Object;)Lscala/collection/mutable/WrappedArray;;
NameAndType	wrapRefArray:([Ljava/lang/Object;)Lscala/collection/mutable/WrappedArray;
Method	scala/Predef$.wrapRefArray:([Ljava/lang/Object;)Lscala/collection/mutable/WrappedArray;
Asciz	scala/reflect/Manifest$;
class	scala/reflect/Manifest$
Asciz	Lscala/reflect/Manifest$;;
NameAndType	MODULE$:Lscala/reflect/Manifest$;
Field	scala/reflect/Manifest$.MODULE$:Lscala/reflect/Manifest$;
Asciz	Byte;
Asciz	()Ljava/lang/Object;;
NameAndType	Byte:()Ljava/lang/Object;
Method	scala/reflect/Manifest$.Byte:()Ljava/lang/Object;
Asciz	scala/reflect/ClassManifest;
class	scala/reflect/ClassManifest
Asciz	concat;
Asciz	(Lscala/collection/Seq;Lscala/reflect/ClassManifest;)Ljava/lang/Object;;
NameAndType	concat:(Lscala/collection/Seq;Lscala/reflect/ClassManifest;)Ljava/lang/Object;
Method	scala/Array$.concat:(Lscala/collection/Seq;Lscala/reflect/ClassManifest;)Ljava/lang/Object;
Asciz	n;
Asciz	s;
Asciz	Lscala/io/BytePickle$PU<Ljava/lang/Integer;>;;
Asciz	Scala;
Asciz	InnerClasses;
Asciz	scala/io/BytePickle;
class	scala/io/BytePickle
Asciz	PU;
Asciz	$anon$2;

{
public scala.io.BytePickle$$anon$2();
  Signature: ()V
  Code:
   Stack=1, Locals=1, Args_size=1
	aload_0
	invokespecial	Method scala/io/BytePickle$PU."<init>":()V
	return
  Labels:

private final int readNat$1(byte[], scala.runtime.IntRef);
  Signature: ([BLscala/runtime/IntRef;)I
  Code:
   Stack=3, Locals=5, Args_size=3
	iconst_0
	istore	4
l1	aload_1
	aload_2
	getfield	Field scala/runtime/IntRef.elem:I
	baload
	istore_3
	aload_2
	aload_2
	getfield	Field scala/runtime/IntRef.elem:I
	iconst_1
	iadd
	putfield	Field scala/runtime/IntRef.elem:I
	iload	4
	ldc	int 7
	ishl
	iload_3
	ldc	int 127
	iand
	iadd
	istore	4
	iload_3
	ldc	int 128
	iand
	iconst_0
	if_icmpne	l1 // aload_1
	iload	4
	ireturn
  Labels:
   	l1 = 3 // aload_1
  LocalVariableTable: 
   Start  Length  Slot  Name   Signature
   0      43      0    this       Lscala/io/BytePickle$$anon$2;
   0      42      3    b       I
   3      39      4    x       I


public byte[] appP(java.lang.Object, byte[]);
  Signature: (Ljava/lang/Object;[B)[B
  Code:
   Stack=3, Locals=3, Args_size=3
	aload_0
	aload_1
	invokestatic	Method scala/runtime/BoxesRunTime.unboxToInt:(Ljava/lang/Object;)I
	aload_2
	invokevirtual	Method appP:(I[B)[B
	areturn
  Labels:
  LocalVariableTable: 
   Start  Length  Slot  Name   Signature
   0      10      0    this       Lscala/io/BytePickle$$anon$2;
   0      10      1    a       Ljava/lang/Object;
   0      10      2    state       [B


public scala.Tuple2 appU(byte[]);
  Signature: ([B)Lscala/Tuple2;
  Code:
   Stack=6, Locals=4, Args_size=2
	new	class scala/runtime/IntRef
	dup
	iconst_0
	invokespecial	Method scala/runtime/IntRef."<init>":(I)V
	astore_2
	new	class scala/Tuple2
	dup
	aload_0
	aload_1
	aload_2
	invokespecial	Method readNat$1:([BLscala/runtime/IntRef;)I
	istore_3
	iload_3
	invokestatic	Method scala/runtime/BoxesRunTime.boxToInteger:(I)Ljava/lang/Integer;
	getstatic	Field scala/Predef$.MODULE$:Lscala/Predef$;
	aload_1
	invokevirtual	Method scala/Predef$.byteArrayOps:([B)Lscala/collection/mutable/ArrayOps;
	aload_2
	getfield	Field scala/runtime/IntRef.elem:I
	aload_1
	arraylength
	invokeinterface	InterfaceMethod scala/collection/IndexedSeqLike.slice:(II)Ljava/lang/Object;
	invokespecial	Method scala/Tuple2."<init>":(Ljava/lang/Object;Ljava/lang/Object;)V
	areturn
  Labels:
  LocalVariableTable: 
   Start  Length  Slot  Name   Signature
   0      46      0    this       Lscala/io/BytePickle$$anon$2;
   0      46      1    s$1       [B
   9      36      2    num$1       Lscala/runtime/IntRef;

  Signature: length = 0x2
   00 4F 

public byte[] appP(int, byte[]);
  Signature: (I[B)[B
  Code:
   Stack=7, Locals=3, Args_size=3
	getstatic	Field scala/Array$.MODULE$:Lscala/Array$;
	getstatic	Field scala/Predef$.MODULE$:Lscala/Predef$;
	iconst_2
	anewarray	class "[B"
	dup
	iconst_0
	aload_2
	aastore
	dup
	iconst_1
	getstatic	Field scala/io/BytePickle$.MODULE$:Lscala/io/BytePickle$;
	iload_1
	invokevirtual	Method scala/io/BytePickle$.nat2Bytes:(I)[B
	aastore
	checkcast	class "[Ljava/lang/Object;"
	invokevirtual	Method scala/Predef$.wrapRefArray:([Ljava/lang/Object;)Lscala/collection/mutable/WrappedArray;
	getstatic	Field scala/reflect/Manifest$.MODULE$:Lscala/reflect/Manifest$;
	invokevirtual	Method scala/reflect/Manifest$.Byte:()Ljava/lang/Object;
	checkcast	class scala/reflect/ClassManifest
	invokevirtual	Method scala/Array$.concat:(Lscala/collection/Seq;Lscala/reflect/ClassManifest;)Ljava/lang/Object;
	checkcast	class "[B"
	areturn
  Labels:
  LocalVariableTable: 
   Start  Length  Slot  Name   Signature
   0      46      0    this       Lscala/io/BytePickle$$anon$2;
   0      46      1    n       I
   0      46      2    s       [B


}

