Compiled from "BytePickle.scala"
public final class scala.io.BytePickle$$anon$3 extends scala.io.BytePickle$SPU
  SourceFile: "BytePickle.scala"
  Signature: length = 0x2
   01 07 
  Scala: length = 0x
   
  InnerClass: 
   public abstract PU=class scala/io/BytePickle$PU of class scala/io/BytePickle
   public Ref=class scala/io/BytePickle$Ref of class scala/io/BytePickle
   public Def=class scala/io/BytePickle$Def of class scala/io/BytePickle
   public abstract SPU=class scala/io/BytePickle$SPU of class scala/io/BytePickle
   public abstract RefDef=class scala/io/BytePickle$RefDef of class scala/io/BytePickle
   public final $anon$2=class scala/io/BytePickle$$anon$2 of class scala/io/BytePickle
   public final $anon$1=class scala/io/BytePickle$$anon$1 of class scala/io/BytePickle
   public final $anon$3=class scala/io/BytePickle$$anon$3 of class scala/io/BytePickle
   public PicklerEnv=class scala/io/BytePickle$PicklerEnv of class scala/io/BytePickle
   public final $anonfun$concat$2=class scala/Array$$anonfun$concat$2 of class scala/Array
   public final $anonfun$concat$1=class scala/Array$$anonfun$concat$1 of class scala/Array
   public PicklerState=class scala/io/BytePickle$PicklerState of class scala/io/BytePickle
   public UnPicklerEnv=class scala/io/BytePickle$UnPicklerEnv of class scala/io/BytePickle
   public UnPicklerState=class scala/io/BytePickle$UnPicklerState of class scala/io/BytePickle
   public GenericCanBuildFrom=class scala/collection/generic/TraversableFactory$GenericCanBuildFrom of class scala/collection/generic/TraversableFactory
  minor version: 0
  major version: 49
  Constant pool:
Asciz	SourceFile;
Asciz	BytePickle.scala;
Asciz	pa$1;
Asciz	Lscala/io/BytePickle$SPU;;
Asciz	<init>;
Asciz	(Lscala/io/BytePickle$SPU;)V;
Asciz	Code;
Asciz	LineNumberTable;
Asciz	scala/io/BytePickle$$anon$3;
class	scala/io/BytePickle$$anon$3
NameAndType	pa$1:Lscala/io/BytePickle$SPU;
Field	scala/io/BytePickle$$anon$3.pa$1:Lscala/io/BytePickle$SPU;
Asciz	scala/io/BytePickle$SPU;
class	scala/io/BytePickle$SPU
Asciz	()V;
NameAndType	"<init>":()V
Method	scala/io/BytePickle$SPU."<init>":()V
Asciz	appU;
Asciz	(Lscala/io/BytePickle$UnPicklerState;)Lscala/Tuple2;;
Asciz	scala/io/BytePickle$UnPicklerState;
class	scala/io/BytePickle$UnPicklerState
Asciz	dict;
Asciz	()Lscala/io/BytePickle$UnPicklerEnv;;
NameAndType	dict:()Lscala/io/BytePickle$UnPicklerEnv;
Method	scala/io/BytePickle$UnPicklerState.dict:()Lscala/io/BytePickle$UnPicklerEnv;
Asciz	scala/io/BytePickle$$anon$1;
class	scala/io/BytePickle$$anon$1
Method	scala/io/BytePickle$$anon$1."<init>":()V
Asciz	stream;
Asciz	()[B;
NameAndType	stream:()[B
Method	scala/io/BytePickle$UnPicklerState.stream:()[B
Asciz	scala/io/BytePickle$PU;
class	scala/io/BytePickle$PU
Asciz	([B)Lscala/Tuple2;;
NameAndType	appU:([B)Lscala/Tuple2;
Method	scala/io/BytePickle$PU.appU:([B)Lscala/Tuple2;
Asciz	scala/Tuple2;
class	scala/Tuple2
Asciz	_1;
Asciz	()Ljava/lang/Object;;
NameAndType	_1:()Ljava/lang/Object;
Method	scala/Tuple2._1:()Ljava/lang/Object;
Asciz	scala/io/BytePickle$RefDef;
class	scala/io/BytePickle$RefDef
Asciz	scala/io/BytePickle$Def;
class	scala/io/BytePickle$Def
Asciz	scala/io/BytePickle$UnPicklerEnv;
class	scala/io/BytePickle$UnPicklerEnv
Asciz	nextLoc;
Asciz	()I;
NameAndType	nextLoc:()I
Method	scala/io/BytePickle$UnPicklerEnv.nextLoc:()I
Asciz	_2;
NameAndType	_2:()Ljava/lang/Object;
Method	scala/Tuple2._2:()Ljava/lang/Object;
Asciz	[B;
class	"[B"
Asciz	([BLscala/io/BytePickle$UnPicklerEnv;)V;
NameAndType	"<init>":([BLscala/io/BytePickle$UnPicklerEnv;)V
Method	scala/io/BytePickle$UnPicklerState."<init>":([BLscala/io/BytePickle$UnPicklerEnv;)V
NameAndType	appU:(Lscala/io/BytePickle$UnPicklerState;)Lscala/Tuple2;
Method	scala/io/BytePickle$SPU.appU:(Lscala/io/BytePickle$UnPicklerState;)Lscala/Tuple2;
Asciz	scala/runtime/BoxesRunTime;
class	scala/runtime/BoxesRunTime
Asciz	boxToInteger;
Asciz	(I)Ljava/lang/Integer;;
NameAndType	boxToInteger:(I)Ljava/lang/Integer;
Method	scala/runtime/BoxesRunTime.boxToInteger:(I)Ljava/lang/Integer;
Asciz	update;
Asciz	(Ljava/lang/Object;Ljava/lang/Object;)V;
NameAndType	update:(Ljava/lang/Object;Ljava/lang/Object;)V
Method	scala/io/BytePickle$UnPicklerEnv.update:(Ljava/lang/Object;Ljava/lang/Object;)V
Asciz	scala/MatchError;
class	scala/MatchError
Asciz	toString;
Asciz	()Ljava/lang/String;;
NameAndType	toString:()Ljava/lang/String;
Method	scala/io/BytePickle$RefDef.toString:()Ljava/lang/String;
Asciz	(Ljava/lang/String;)V;
NameAndType	"<init>":(Ljava/lang/String;)V
Method	scala/MatchError."<init>":(Ljava/lang/String;)V
Asciz	scala/io/BytePickle$Ref;
class	scala/io/BytePickle$Ref
Asciz	scala/io/BytePickle$$anon$2;
class	scala/io/BytePickle$$anon$2
Method	scala/io/BytePickle$$anon$2."<init>":()V
Asciz	get;
Asciz	(Ljava/lang/Object;)Lscala/Option;;
NameAndType	get:(Ljava/lang/Object;)Lscala/Option;
Method	scala/io/BytePickle$UnPicklerEnv.get:(Ljava/lang/Object;)Lscala/Option;
Asciz	scala/None$;
class	scala/None$
Asciz	MODULE$;
Asciz	Lscala/None$;;
NameAndType	MODULE$:Lscala/None$;
Field	scala/None$.MODULE$:Lscala/None$;
Asciz	java/lang/Object;
class	java/lang/Object
Asciz	equals;
Asciz	(Ljava/lang/Object;)Z;
NameAndType	equals:(Ljava/lang/Object;)Z
Method	java/lang/Object.equals:(Ljava/lang/Object;)Z
Asciz	java/lang/IllegalArgumentException;
class	java/lang/IllegalArgumentException
Asciz	invalid unpickler environment;
String	invalid unpickler environment
Method	java/lang/IllegalArgumentException."<init>":(Ljava/lang/String;)V
Asciz	scala/Option;
class	scala/Option
Method	scala/Option.toString:()Ljava/lang/String;
Asciz	scala/Some;
class	scala/Some
Asciz	x;
Asciz	Ljava/lang/Object;;
NameAndType	x:Ljava/lang/Object;
Field	scala/Some.x:Ljava/lang/Object;
NameAndType	"<init>":(Ljava/lang/Object;Ljava/lang/Object;)V
Method	scala/Tuple2."<init>":(Ljava/lang/Object;Ljava/lang/Object;)V
Asciz	this;
Asciz	Lscala/io/BytePickle$$anon$3;;
Asciz	state;
Asciz	Lscala/io/BytePickle$UnPicklerState;;
Asciz	l;
Asciz	I;
Asciz	res2;
Asciz	Lscala/Tuple2;;
Asciz	res;
Asciz	temp16;
Asciz	Lscala/Some;;
Asciz	temp17;
Asciz	upe;
Asciz	Lscala/io/BytePickle$UnPicklerEnv;;
Asciz	temp14;
Asciz	Lscala/Option;;
Asciz	temp18;
Asciz	Lscala/io/BytePickle$RefDef;;
Asciz	LocalVariableTable;
Asciz	(Lscala/io/BytePickle$UnPicklerState;)Lscala/Tuple2<Ta;Lscala/io/BytePickle$UnPicklerState;>;;
Asciz	Signature;
Asciz	appP;
Asciz	(Ljava/lang/Object;Lscala/io/BytePickle$PicklerState;)Lscala/io/BytePickle$PicklerState;;
Asciz	scala/io/BytePickle$PicklerState;
class	scala/io/BytePickle$PicklerState
Asciz	()Lscala/io/BytePickle$PicklerEnv;;
NameAndType	dict:()Lscala/io/BytePickle$PicklerEnv;
Method	scala/io/BytePickle$PicklerState.dict:()Lscala/io/BytePickle$PicklerEnv;
Asciz	scala/io/BytePickle$PicklerEnv;
class	scala/io/BytePickle$PicklerEnv
Method	scala/io/BytePickle$PicklerEnv.get:(Ljava/lang/Object;)Lscala/Option;
Method	scala/io/BytePickle$Def."<init>":()V
Method	scala/io/BytePickle$PicklerState.stream:()[B
Asciz	(Lscala/io/BytePickle$RefDef;[B)[B;
NameAndType	appP:(Lscala/io/BytePickle$RefDef;[B)[B
Method	scala/io/BytePickle$$anon$1.appP:(Lscala/io/BytePickle$RefDef;[B)[B
Method	scala/io/BytePickle$PicklerEnv.nextLoc:()I
Asciz	([BLscala/io/BytePickle$PicklerEnv;)V;
NameAndType	"<init>":([BLscala/io/BytePickle$PicklerEnv;)V
Method	scala/io/BytePickle$PicklerState."<init>":([BLscala/io/BytePickle$PicklerEnv;)V
NameAndType	appP:(Ljava/lang/Object;Lscala/io/BytePickle$PicklerState;)Lscala/io/BytePickle$PicklerState;
Method	scala/io/BytePickle$SPU.appP:(Ljava/lang/Object;Lscala/io/BytePickle$PicklerState;)Lscala/io/BytePickle$PicklerState;
Method	scala/io/BytePickle$PicklerEnv.update:(Ljava/lang/Object;Ljava/lang/Object;)V
Asciz	unboxToInt;
Asciz	(Ljava/lang/Object;)I;
NameAndType	unboxToInt:(Ljava/lang/Object;)I
Method	scala/runtime/BoxesRunTime.unboxToInt:(Ljava/lang/Object;)I
Method	scala/io/BytePickle$Ref."<init>":()V
Asciz	scala/Predef$;
class	scala/Predef$
Asciz	Lscala/Predef$;;
NameAndType	MODULE$:Lscala/Predef$;
Field	scala/Predef$.MODULE$:Lscala/Predef$;
Asciz	scala/io/BytePickle$;
class	scala/io/BytePickle$
Asciz	Lscala/io/BytePickle$;;
NameAndType	MODULE$:Lscala/io/BytePickle$;
Field	scala/io/BytePickle$.MODULE$:Lscala/io/BytePickle$;
Asciz	nat2Bytes;
Asciz	(I)[B;
NameAndType	nat2Bytes:(I)[B
Method	scala/io/BytePickle$.nat2Bytes:(I)[B
Asciz	[Ljava/lang/Object;;
class	"[Ljava/lang/Object;"
Asciz	wrapRefArray;
Asciz	([Ljava/lang/Object;)Lscala/collection/mutable/WrappedArray;;
NameAndType	wrapRefArray:([Ljava/lang/Object;)Lscala/collection/mutable/WrappedArray;
Method	scala/Predef$.wrapRefArray:([Ljava/lang/Object;)Lscala/collection/mutable/WrappedArray;
Asciz	scala/reflect/Manifest$;
class	scala/reflect/Manifest$
Asciz	Lscala/reflect/Manifest$;;
NameAndType	MODULE$:Lscala/reflect/Manifest$;
Field	scala/reflect/Manifest$.MODULE$:Lscala/reflect/Manifest$;
Asciz	Byte;
Asciz	()Lscala/reflect/AnyValManifest;;
NameAndType	Byte:()Lscala/reflect/AnyValManifest;
Method	scala/reflect/Manifest$.Byte:()Lscala/reflect/AnyValManifest;
Asciz	scala/reflect/ClassManifest;
class	scala/reflect/ClassManifest
Asciz	newArrayBuilder;
Asciz	()Lscala/collection/mutable/ArrayBuilder;;
NameAndType	newArrayBuilder:()Lscala/collection/mutable/ArrayBuilder;
InterfaceMethod	scala/reflect/ClassManifest.newArrayBuilder:()Lscala/collection/mutable/ArrayBuilder;
Asciz	scala/Array$$anonfun$concat$1;
class	scala/Array$$anonfun$concat$1
Method	scala/Array$$anonfun$concat$1."<init>":()V
Asciz	scala/collection/Seq$;
class	scala/collection/Seq$
Asciz	Lscala/collection/Seq$;;
NameAndType	MODULE$:Lscala/collection/Seq$;
Field	scala/collection/Seq$.MODULE$:Lscala/collection/Seq$;
Asciz	scala/collection/generic/TraversableFactory$GenericCanBuildFrom;
class	scala/collection/generic/TraversableFactory$GenericCanBuildFrom
Asciz	(Lscala/collection/generic/TraversableFactory;)V;
NameAndType	"<init>":(Lscala/collection/generic/TraversableFactory;)V
Method	scala/collection/generic/TraversableFactory$GenericCanBuildFrom."<init>":(Lscala/collection/generic/TraversableFactory;)V
Asciz	scala/collection/TraversableLike;
class	scala/collection/TraversableLike
Asciz	map;
Asciz	(Lscala/Function1;Lscala/collection/generic/CanBuildFrom;)Ljava/lang/Object;;
NameAndType	map:(Lscala/Function1;Lscala/collection/generic/CanBuildFrom;)Ljava/lang/Object;
InterfaceMethod	scala/collection/TraversableLike.map:(Lscala/Function1;Lscala/collection/generic/CanBuildFrom;)Ljava/lang/Object;
Asciz	scala/math/Numeric$IntIsIntegral$;
class	scala/math/Numeric$IntIsIntegral$
Asciz	Lscala/math/Numeric$IntIsIntegral$;;
NameAndType	MODULE$:Lscala/math/Numeric$IntIsIntegral$;
Field	scala/math/Numeric$IntIsIntegral$.MODULE$:Lscala/math/Numeric$IntIsIntegral$;
Asciz	sum;
Asciz	(Lscala/math/Numeric;)Ljava/lang/Object;;
NameAndType	sum:(Lscala/math/Numeric;)Ljava/lang/Object;
InterfaceMethod	scala/collection/TraversableLike.sum:(Lscala/math/Numeric;)Ljava/lang/Object;
Asciz	scala/collection/mutable/Builder;
class	scala/collection/mutable/Builder
Asciz	sizeHint;
Asciz	(I)V;
NameAndType	sizeHint:(I)V
InterfaceMethod	scala/collection/mutable/Builder.sizeHint:(I)V
Asciz	scala/Array$$anonfun$concat$2;
class	scala/Array$$anonfun$concat$2
Asciz	(Lscala/collection/mutable/ArrayBuilder;)V;
NameAndType	"<init>":(Lscala/collection/mutable/ArrayBuilder;)V
Method	scala/Array$$anonfun$concat$2."<init>":(Lscala/collection/mutable/ArrayBuilder;)V
Asciz	scala/collection/IterableLike;
class	scala/collection/IterableLike
Asciz	foreach;
Asciz	(Lscala/Function1;)V;
NameAndType	foreach:(Lscala/Function1;)V
InterfaceMethod	scala/collection/IterableLike.foreach:(Lscala/Function1;)V
Asciz	result;
NameAndType	result:()Ljava/lang/Object;
InterfaceMethod	scala/collection/mutable/Builder.result:()Ljava/lang/Object;
Asciz	v;
Asciz	Lscala/io/BytePickle$PicklerState;;
Asciz	sPrime;
Asciz	sPrimePrime;
Asciz	temp12;
Asciz	temp13;
Asciz	b$10;
Asciz	Lscala/collection/mutable/ArrayBuilder;;
Asciz	pe;
Asciz	Lscala/io/BytePickle$PicklerEnv;;
Asciz	temp10;
Asciz	(Ta;Lscala/io/BytePickle$PicklerState;)Lscala/io/BytePickle$PicklerState;;
Asciz	Lscala/io/BytePickle$SPU<Ta;>;;
Asciz	Scala;
Asciz	InnerClasses;
Asciz	scala/io/BytePickle;
class	scala/io/BytePickle
Asciz	PU;
Asciz	Ref;
Asciz	Def;
Asciz	SPU;
Asciz	RefDef;
Asciz	$anon$2;
Asciz	$anon$1;
Asciz	$anon$3;
Asciz	PicklerEnv;
Asciz	scala/Array;
class	scala/Array
Asciz	$anonfun$concat$2;
Asciz	$anonfun$concat$1;
Asciz	PicklerState;
Asciz	UnPicklerEnv;
Asciz	UnPicklerState;
Asciz	scala/collection/generic/TraversableFactory;
class	scala/collection/generic/TraversableFactory
Asciz	GenericCanBuildFrom;

{
private final scala.io.BytePickle$SPU pa$1;
  Signature: Lscala/io/BytePickle$SPU;

public scala.io.BytePickle$$anon$3(scala.io.BytePickle$SPU);
  Signature: (Lscala/io/BytePickle$SPU;)V
  Code:
   Stack=2, Locals=2, Args_size=2
	aload_0
	aload_1
	putfield	Field pa$1:Lscala/io/BytePickle$SPU;
	aload_0
	invokespecial	Method scala/io/BytePickle$SPU."<init>":()V
	return
  Labels:

public scala.Tuple2 appU(scala.io.BytePickle$UnPicklerState);
  Signature: (Lscala/io/BytePickle$UnPicklerState;)Lscala/Tuple2;
  Code:
   Stack=7, Locals=11, Args_size=2
	aload_1
	invokevirtual	Method scala/io/BytePickle$UnPicklerState.dict:()Lscala/io/BytePickle$UnPicklerEnv;
	astore	8
	new	class scala/io/BytePickle$$anon$1
	dup
	invokespecial	Method scala/io/BytePickle$$anon$1."<init>":()V
	aload_1
	invokevirtual	Method scala/io/BytePickle$UnPicklerState.stream:()[B
	invokevirtual	Method scala/io/BytePickle$PU.appU:([B)Lscala/Tuple2;
	astore	4
	aload	4
	invokevirtual	Method scala/Tuple2._1:()Ljava/lang/Object;
	checkcast	class scala/io/BytePickle$RefDef
	astore	10
	aload	10
	instanceof	class scala/io/BytePickle$Def
	ifeq	l1 // aload
	iconst_1
	ifeq	l2 // new
	aload	8
	invokevirtual	Method scala/io/BytePickle$UnPicklerEnv.nextLoc:()I
	istore_2
	aload_0
	getfield	Field pa$1:Lscala/io/BytePickle$SPU;
	new	class scala/io/BytePickle$UnPicklerState
	dup
	aload	4
	invokevirtual	Method scala/Tuple2._2:()Ljava/lang/Object;
	checkcast	class "[B"
	aload	8
	invokespecial	Method scala/io/BytePickle$UnPicklerState."<init>":([BLscala/io/BytePickle$UnPicklerEnv;)V
	invokevirtual	Method scala/io/BytePickle$SPU.appU:(Lscala/io/BytePickle$UnPicklerState;)Lscala/Tuple2;
	astore_3
	aload	8
	iload_2
	invokestatic	Method scala/runtime/BoxesRunTime.boxToInteger:(I)Ljava/lang/Integer;
	aload_3
	invokevirtual	Method scala/Tuple2._1:()Ljava/lang/Object;
	invokevirtual	Method scala/io/BytePickle$UnPicklerEnv.update:(Ljava/lang/Object;Ljava/lang/Object;)V
	aload_3
	areturn
l2	new	class scala/MatchError
	dup
	aload	10
	invokevirtual	Method scala/io/BytePickle$RefDef.toString:()Ljava/lang/String;
	invokespecial	Method scala/MatchError."<init>":(Ljava/lang/String;)V
	athrow
l1	aload	10
	instanceof	class scala/io/BytePickle$Ref
	ifeq	l3 // new
	iconst_1
	ifeq	l4 // new
	new	class scala/io/BytePickle$$anon$2
	dup
	invokespecial	Method scala/io/BytePickle$$anon$2."<init>":()V
	aload	4
	invokevirtual	Method scala/Tuple2._2:()Ljava/lang/Object;
	checkcast	class "[B"
	invokevirtual	Method scala/io/BytePickle$PU.appU:([B)Lscala/Tuple2;
	astore	7
	aload	8
	aload	7
	invokevirtual	Method scala/Tuple2._1:()Ljava/lang/Object;
	invokevirtual	Method scala/io/BytePickle$UnPicklerEnv.get:(Ljava/lang/Object;)Lscala/Option;
	astore	9
	getstatic	Field scala/None$.MODULE$:Lscala/None$;
	dup
	ifnonnull	l5 // aload
	pop
	aload	9
	ifnull	l6 // iconst_1
	goto	l7 // aload
l5	aload	9
	invokevirtual	Method java/lang/Object.equals:(Ljava/lang/Object;)Z
	ifeq	l7 // aload
l6	iconst_1
	ifeq	l8 // new
	new	class java/lang/IllegalArgumentException
	dup
	ldc	String invalid unpickler environment
	invokespecial	Method java/lang/IllegalArgumentException."<init>":(Ljava/lang/String;)V
	athrow
l8	new	class scala/MatchError
	dup
	aload	9
	invokevirtual	Method scala/Option.toString:()Ljava/lang/String;
	invokespecial	Method scala/MatchError."<init>":(Ljava/lang/String;)V
	athrow
l7	aload	9
	instanceof	class scala/Some
	ifeq	l9 // new
	aload	9
	checkcast	class scala/Some
	astore	5
	aload	5
	getfield	Field scala/Some.x:Ljava/lang/Object;
	astore	6
	iconst_1
	ifeq	l10 // new
	new	class scala/Tuple2
	dup
	aload	6
	new	class scala/io/BytePickle$UnPicklerState
	dup
	aload	7
	invokevirtual	Method scala/Tuple2._2:()Ljava/lang/Object;
	checkcast	class "[B"
	aload	8
	invokespecial	Method scala/io/BytePickle$UnPicklerState."<init>":([BLscala/io/BytePickle$UnPicklerEnv;)V
	invokespecial	Method scala/Tuple2."<init>":(Ljava/lang/Object;Ljava/lang/Object;)V
	areturn
l10	new	class scala/MatchError
	dup
	aload	9
	invokevirtual	Method scala/Option.toString:()Ljava/lang/String;
	invokespecial	Method scala/MatchError."<init>":(Ljava/lang/String;)V
	athrow
l9	new	class scala/MatchError
	dup
	aload	9
	invokevirtual	Method scala/Option.toString:()Ljava/lang/String;
	invokespecial	Method scala/MatchError."<init>":(Ljava/lang/String;)V
	athrow
l4	new	class scala/MatchError
	dup
	aload	10
	invokevirtual	Method scala/io/BytePickle$RefDef.toString:()Ljava/lang/String;
	invokespecial	Method scala/MatchError."<init>":(Ljava/lang/String;)V
	athrow
l3	new	class scala/MatchError
	dup
	aload	10
	invokevirtual	Method scala/io/BytePickle$RefDef.toString:()Ljava/lang/String;
	invokespecial	Method scala/MatchError."<init>":(Ljava/lang/String;)V
	athrow
  Labels:
   	l2 = 90 // new
   	l1 = 103 // aload
   	l5 = 163 // aload
   	l6 = 171 // iconst_1
   	l8 = 185 // new
   	l7 = 198 // aload
   	l10 = 251 // new
   	l9 = 264 // new
   	l4 = 277 // new
   	l3 = 290 // new
  LocalVariableTable: 
   Start  Length  Slot  Name   Signature
   0      303      0    this       Lscala/io/BytePickle$$anon$3;
   0      303      1    state       Lscala/io/BytePickle$UnPicklerState;
   50      40      2    l       I
   75      15      3    res2       Lscala/Tuple2;
   22      281      4    res       Lscala/Tuple2;
   213      51      5    temp16       Lscala/Some;
   220      44      6    temp17       Ljava/lang/Object;
   135      142      7    res2       Lscala/Tuple2;
   6      297      8    upe       Lscala/io/BytePickle$UnPicklerEnv;
   147      130      9    temp14       Lscala/Option;
   32      271      10    temp18       Lscala/io/BytePickle$RefDef;

  Signature: length = 0x2
   00 FFFFFF8B 

public scala.io.BytePickle$PicklerState appP(java.lang.Object, scala.io.BytePickle$PicklerState);
  Signature: (Ljava/lang/Object;Lscala/io/BytePickle$PicklerState;)Lscala/io/BytePickle$PicklerState;
  Code:
   Stack=8, Locals=22, Args_size=3
	aload_2
	invokevirtual	Method scala/io/BytePickle$PicklerState.dict:()Lscala/io/BytePickle$PicklerEnv;
	astore	20
	aload	20
	aload_1
	invokevirtual	Method scala/io/BytePickle$PicklerEnv.get:(Ljava/lang/Object;)Lscala/Option;
	astore	21
	getstatic	Field scala/None$.MODULE$:Lscala/None$;
	dup
	ifnonnull	l1 // aload
	pop
	aload	21
	ifnull	l2 // iconst_1
	goto	l3 // aload
l1	aload	21
	invokevirtual	Method java/lang/Object.equals:(Ljava/lang/Object;)Z
	ifeq	l3 // aload
l2	iconst_1
	ifeq	l4 // new
	new	class scala/io/BytePickle$$anon$1
	dup
	invokespecial	Method scala/io/BytePickle$$anon$1."<init>":()V
	new	class scala/io/BytePickle$Def
	dup
	invokespecial	Method scala/io/BytePickle$Def."<init>":()V
	aload_2
	invokevirtual	Method scala/io/BytePickle$PicklerState.stream:()[B
	astore	5
	astore	4
	astore_3
	aload_3
	aload	4
	checkcast	class scala/io/BytePickle$RefDef
	aload	5
	invokevirtual	Method scala/io/BytePickle$$anon$1.appP:(Lscala/io/BytePickle$RefDef;[B)[B
	astore	6
	aload	20
	invokevirtual	Method scala/io/BytePickle$PicklerEnv.nextLoc:()I
	istore	7
	aload_0
	getfield	Field pa$1:Lscala/io/BytePickle$SPU;
	aload_1
	new	class scala/io/BytePickle$PicklerState
	dup
	aload	6
	aload	20
	invokespecial	Method scala/io/BytePickle$PicklerState."<init>":([BLscala/io/BytePickle$PicklerEnv;)V
	invokevirtual	Method scala/io/BytePickle$SPU.appP:(Ljava/lang/Object;Lscala/io/BytePickle$PicklerState;)Lscala/io/BytePickle$PicklerState;
	astore	8
	aload	20
	aload_1
	iload	7
	invokestatic	Method scala/runtime/BoxesRunTime.boxToInteger:(I)Ljava/lang/Integer;
	invokevirtual	Method scala/io/BytePickle$PicklerEnv.update:(Ljava/lang/Object;Ljava/lang/Object;)V
	aload	8
	areturn
l4	new	class scala/MatchError
	dup
	aload	21
	invokevirtual	Method scala/Option.toString:()Ljava/lang/String;
	invokespecial	Method scala/MatchError."<init>":(Ljava/lang/String;)V
	athrow
l3	aload	21
	instanceof	class scala/Some
	ifeq	l5 // new
	aload	21
	checkcast	class scala/Some
	astore	9
	aload	9
	getfield	Field scala/Some.x:Ljava/lang/Object;
	invokestatic	Method scala/runtime/BoxesRunTime.unboxToInt:(Ljava/lang/Object;)I
	istore	13
	iconst_1
	ifeq	l6 // new
	new	class scala/io/BytePickle$$anon$1
	dup
	invokespecial	Method scala/io/BytePickle$$anon$1."<init>":()V
	new	class scala/io/BytePickle$Ref
	dup
	invokespecial	Method scala/io/BytePickle$Ref."<init>":()V
	aload_2
	invokevirtual	Method scala/io/BytePickle$PicklerState.stream:()[B
	astore	12
	astore	11
	astore	10
	aload	10
	aload	11
	checkcast	class scala/io/BytePickle$RefDef
	aload	12
	invokevirtual	Method scala/io/BytePickle$$anon$1.appP:(Lscala/io/BytePickle$RefDef;[B)[B
	astore	14
	new	class scala/io/BytePickle$PicklerState
	dup
	new	class scala/io/BytePickle$$anon$2
	dup
	pop
	invokespecial	Method scala/io/BytePickle$$anon$2."<init>":()V
	iload	13
	istore	15
	getstatic	Field scala/Predef$.MODULE$:Lscala/Predef$;
	iconst_2
	anewarray	class "[B"
	dup
	iconst_0
	aload	14
	aastore
	dup
	iconst_1
	getstatic	Field scala/io/BytePickle$.MODULE$:Lscala/io/BytePickle$;
	iload	15
	invokevirtual	Method scala/io/BytePickle$.nat2Bytes:(I)[B
	aastore
	checkcast	class "[Ljava/lang/Object;"
	invokevirtual	Method scala/Predef$.wrapRefArray:([Ljava/lang/Object;)Lscala/collection/mutable/WrappedArray;
	getstatic	Field scala/reflect/Manifest$.MODULE$:Lscala/reflect/Manifest$;
	invokevirtual	Method scala/reflect/Manifest$.Byte:()Lscala/reflect/AnyValManifest;
	astore	16
	astore	18
	aload	16
	checkcast	class scala/reflect/ClassManifest
	invokeinterface	InterfaceMethod scala/reflect/ClassManifest.newArrayBuilder:()Lscala/collection/mutable/ArrayBuilder;
	astore	19
	aload	19
	aload	18
	new	class scala/Array$$anonfun$concat$1
	dup
	invokespecial	Method scala/Array$$anonfun$concat$1."<init>":()V
	getstatic	Field scala/collection/Seq$.MODULE$:Lscala/collection/Seq$;
	astore	17
	new	class scala/collection/generic/TraversableFactory$GenericCanBuildFrom
	dup
	aload	17
	invokespecial	Method scala/collection/generic/TraversableFactory$GenericCanBuildFrom."<init>":(Lscala/collection/generic/TraversableFactory;)V
	invokeinterface	InterfaceMethod scala/collection/TraversableLike.map:(Lscala/Function1;Lscala/collection/generic/CanBuildFrom;)Ljava/lang/Object;
	checkcast	class scala/collection/TraversableLike
	getstatic	Field scala/math/Numeric$IntIsIntegral$.MODULE$:Lscala/math/Numeric$IntIsIntegral$;
	invokeinterface	InterfaceMethod scala/collection/TraversableLike.sum:(Lscala/math/Numeric;)Ljava/lang/Object;
	invokestatic	Method scala/runtime/BoxesRunTime.unboxToInt:(Ljava/lang/Object;)I
	invokeinterface	InterfaceMethod scala/collection/mutable/Builder.sizeHint:(I)V
	aload	18
	new	class scala/Array$$anonfun$concat$2
	dup
	aload	19
	invokespecial	Method scala/Array$$anonfun$concat$2."<init>":(Lscala/collection/mutable/ArrayBuilder;)V
	invokeinterface	InterfaceMethod scala/collection/IterableLike.foreach:(Lscala/Function1;)V
	aload	19
	invokeinterface	InterfaceMethod scala/collection/mutable/Builder.result:()Ljava/lang/Object;
	checkcast	class "[B"
	aload	20
	invokespecial	Method scala/io/BytePickle$PicklerState."<init>":([BLscala/io/BytePickle$PicklerEnv;)V
	areturn
l6	new	class scala/MatchError
	dup
	aload	21
	invokevirtual	Method scala/Option.toString:()Ljava/lang/String;
	invokespecial	Method scala/MatchError."<init>":(Ljava/lang/String;)V
	athrow
l5	new	class scala/MatchError
	dup
	aload	21
	invokevirtual	Method scala/Option.toString:()Ljava/lang/String;
	invokespecial	Method scala/MatchError."<init>":(Ljava/lang/String;)V
	athrow
  Labels:
   	l1 = 30 // aload
   	l2 = 38 // iconst_1
   	l4 = 120 // new
   	l3 = 133 // aload
   	l6 = 348 // new
   	l5 = 361 // new
  LocalVariableTable: 
   Start  Length  Slot  Name   Signature
   0      374      0    this       Lscala/io/BytePickle$$anon$3;
   0      374      1    v       Ljava/lang/Object;
   0      374      2    state       Lscala/io/BytePickle$PicklerState;
   78      42      6    sPrime       [B
   85      35      7    l       I
   106      14      8    sPrimePrime       Lscala/io/BytePickle$PicklerState;
   148      213      9    temp12       Lscala/Some;
   158      203      13    temp13       I
   200      148      14    sPrime       [B
   267      72      19    b$10       Lscala/collection/mutable/ArrayBuilder;
   6      368      20    pe       Lscala/io/BytePickle$PicklerEnv;
   14      360      21    temp10       Lscala/Option;

  Signature: length = 0x2
   01 06 

}

