Compiled from "BytePickle.scala"
public final class scala.io.BytePickle$$anon$1 extends scala.io.BytePickle$PU
  SourceFile: "BytePickle.scala"
  Signature: length = 0x2
   00 FFFFFFBA 
  Scala: length = 0x
   
  InnerClass: 
   public abstract PU=class scala/io/BytePickle$PU of class scala/io/BytePickle
   public Def=class scala/io/BytePickle$Def of class scala/io/BytePickle
   public Ref=class scala/io/BytePickle$Ref of class scala/io/BytePickle
   public ofByte=class scala/collection/mutable/ArrayOps$ofByte of class scala/collection/mutable/ArrayOps
   public abstract RefDef=class scala/io/BytePickle$RefDef of class scala/io/BytePickle
   public final $anon$1=class scala/io/BytePickle$$anon$1 of class scala/io/BytePickle
   public final $anonfun$apply$1=class scala/Array$$anonfun$apply$1 of class scala/Array
   public final $anonfun$concat$2=class scala/Array$$anonfun$concat$2 of class scala/Array
   public final $anonfun$concat$1=class scala/Array$$anonfun$concat$1 of class scala/Array
   public GenericCanBuildFrom=class scala/collection/generic/TraversableFactory$GenericCanBuildFrom of class scala/collection/generic/TraversableFactory
  minor version: 0
  major version: 49
  Constant pool:
Asciz	SourceFile;
Asciz	BytePickle.scala;
Asciz	<init>;
Asciz	()V;
Asciz	Code;
Asciz	LineNumberTable;
Asciz	scala/io/BytePickle$PU;
class	scala/io/BytePickle$PU
NameAndType	"<init>":()V
Method	scala/io/BytePickle$PU."<init>":()V
Asciz	appP;
Asciz	(Ljava/lang/Object;[B)[B;
Asciz	scala/io/BytePickle$RefDef;
class	scala/io/BytePickle$RefDef
Asciz	scala/io/BytePickle$$anon$1;
class	scala/io/BytePickle$$anon$1
Asciz	(Lscala/io/BytePickle$RefDef;[B)[B;
NameAndType	appP:(Lscala/io/BytePickle$RefDef;[B)[B
Method	scala/io/BytePickle$$anon$1.appP:(Lscala/io/BytePickle$RefDef;[B)[B
Asciz	this;
Asciz	Lscala/io/BytePickle$$anon$1;;
Asciz	a;
Asciz	Ljava/lang/Object;;
Asciz	state;
Asciz	[B;
Asciz	LocalVariableTable;
Asciz	appU;
Asciz	([B)Lscala/Tuple2;;
Asciz	scala/Tuple2;
class	scala/Tuple2
Asciz	scala/io/BytePickle$Ref;
class	scala/io/BytePickle$Ref
Method	scala/io/BytePickle$Ref."<init>":()V
Asciz	scala/collection/mutable/ArrayOps$ofByte;
class	scala/collection/mutable/ArrayOps$ofByte
Asciz	([B)V;
NameAndType	"<init>":([B)V
Method	scala/collection/mutable/ArrayOps$ofByte."<init>":([B)V
Asciz	scala/collection/IndexedSeqLike;
class	scala/collection/IndexedSeqLike
Asciz	slice;
Asciz	(II)Ljava/lang/Object;;
NameAndType	slice:(II)Ljava/lang/Object;
InterfaceMethod	scala/collection/IndexedSeqLike.slice:(II)Ljava/lang/Object;
Asciz	(Ljava/lang/Object;Ljava/lang/Object;)V;
NameAndType	"<init>":(Ljava/lang/Object;Ljava/lang/Object;)V
Method	scala/Tuple2."<init>":(Ljava/lang/Object;Ljava/lang/Object;)V
Asciz	scala/io/BytePickle$Def;
class	scala/io/BytePickle$Def
Method	scala/io/BytePickle$Def."<init>":()V
Asciz	s;
Asciz	([B)Lscala/Tuple2<Lscala/io/BytePickle$RefDef;[B>;;
Asciz	Signature;
Asciz	scala/Predef$;
class	scala/Predef$
Asciz	MODULE$;
Asciz	Lscala/Predef$;;
NameAndType	MODULE$:Lscala/Predef$;
Field	scala/Predef$.MODULE$:Lscala/Predef$;
class	"[B"
Asciz	wrapByteArray;
Asciz	([B)Lscala/collection/mutable/WrappedArray;;
NameAndType	wrapByteArray:([B)Lscala/collection/mutable/WrappedArray;
Method	scala/Predef$.wrapByteArray:([B)Lscala/collection/mutable/WrappedArray;
Asciz	scala/reflect/Manifest$;
class	scala/reflect/Manifest$
Asciz	Lscala/reflect/Manifest$;;
NameAndType	MODULE$:Lscala/reflect/Manifest$;
Field	scala/reflect/Manifest$.MODULE$:Lscala/reflect/Manifest$;
Asciz	Byte;
Asciz	()Lscala/reflect/AnyValManifest;;
NameAndType	Byte:()Lscala/reflect/AnyValManifest;
Method	scala/reflect/Manifest$.Byte:()Lscala/reflect/AnyValManifest;
Asciz	scala/collection/SeqLike;
class	scala/collection/SeqLike
Asciz	length;
Asciz	()I;
NameAndType	length:()I
InterfaceMethod	scala/collection/SeqLike.length:()I
Asciz	scala/reflect/ClassManifest;
class	scala/reflect/ClassManifest
Asciz	newArray;
Asciz	(I)Ljava/lang/Object;;
NameAndType	newArray:(I)Ljava/lang/Object;
InterfaceMethod	scala/reflect/ClassManifest.newArray:(I)Ljava/lang/Object;
Asciz	scala/runtime/IntRef;
class	scala/runtime/IntRef
Asciz	(I)V;
NameAndType	"<init>":(I)V
Method	scala/runtime/IntRef."<init>":(I)V
Asciz	scala/collection/IterableLike;
class	scala/collection/IterableLike
Asciz	iterator;
Asciz	()Lscala/collection/Iterator;;
NameAndType	iterator:()Lscala/collection/Iterator;
InterfaceMethod	scala/collection/IterableLike.iterator:()Lscala/collection/Iterator;
Asciz	scala/Array$$anonfun$apply$1;
class	scala/Array$$anonfun$apply$1
Asciz	(Ljava/lang/Object;Lscala/runtime/IntRef;)V;
NameAndType	"<init>":(Ljava/lang/Object;Lscala/runtime/IntRef;)V
Method	scala/Array$$anonfun$apply$1."<init>":(Ljava/lang/Object;Lscala/runtime/IntRef;)V
Asciz	scala/collection/Iterator;
class	scala/collection/Iterator
Asciz	foreach;
Asciz	(Lscala/Function1;)V;
NameAndType	foreach:(Lscala/Function1;)V
InterfaceMethod	scala/collection/Iterator.foreach:(Lscala/Function1;)V
Asciz	[Ljava/lang/Object;;
class	"[Ljava/lang/Object;"
Asciz	wrapRefArray;
Asciz	([Ljava/lang/Object;)Lscala/collection/mutable/WrappedArray;;
NameAndType	wrapRefArray:([Ljava/lang/Object;)Lscala/collection/mutable/WrappedArray;
Method	scala/Predef$.wrapRefArray:([Ljava/lang/Object;)Lscala/collection/mutable/WrappedArray;
Asciz	newArrayBuilder;
Asciz	()Lscala/collection/mutable/ArrayBuilder;;
NameAndType	newArrayBuilder:()Lscala/collection/mutable/ArrayBuilder;
InterfaceMethod	scala/reflect/ClassManifest.newArrayBuilder:()Lscala/collection/mutable/ArrayBuilder;
Asciz	scala/Array$$anonfun$concat$1;
class	scala/Array$$anonfun$concat$1
Method	scala/Array$$anonfun$concat$1."<init>":()V
Asciz	scala/collection/Seq$;
class	scala/collection/Seq$
Asciz	Lscala/collection/Seq$;;
NameAndType	MODULE$:Lscala/collection/Seq$;
Field	scala/collection/Seq$.MODULE$:Lscala/collection/Seq$;
Asciz	scala/collection/generic/TraversableFactory$GenericCanBuildFrom;
class	scala/collection/generic/TraversableFactory$GenericCanBuildFrom
Asciz	(Lscala/collection/generic/TraversableFactory;)V;
NameAndType	"<init>":(Lscala/collection/generic/TraversableFactory;)V
Method	scala/collection/generic/TraversableFactory$GenericCanBuildFrom."<init>":(Lscala/collection/generic/TraversableFactory;)V
Asciz	scala/collection/TraversableLike;
class	scala/collection/TraversableLike
Asciz	map;
Asciz	(Lscala/Function1;Lscala/collection/generic/CanBuildFrom;)Ljava/lang/Object;;
NameAndType	map:(Lscala/Function1;Lscala/collection/generic/CanBuildFrom;)Ljava/lang/Object;
InterfaceMethod	scala/collection/TraversableLike.map:(Lscala/Function1;Lscala/collection/generic/CanBuildFrom;)Ljava/lang/Object;
Asciz	scala/math/Numeric$IntIsIntegral$;
class	scala/math/Numeric$IntIsIntegral$
Asciz	Lscala/math/Numeric$IntIsIntegral$;;
NameAndType	MODULE$:Lscala/math/Numeric$IntIsIntegral$;
Field	scala/math/Numeric$IntIsIntegral$.MODULE$:Lscala/math/Numeric$IntIsIntegral$;
Asciz	sum;
Asciz	(Lscala/math/Numeric;)Ljava/lang/Object;;
NameAndType	sum:(Lscala/math/Numeric;)Ljava/lang/Object;
InterfaceMethod	scala/collection/TraversableLike.sum:(Lscala/math/Numeric;)Ljava/lang/Object;
Asciz	scala/runtime/BoxesRunTime;
class	scala/runtime/BoxesRunTime
Asciz	unboxToInt;
Asciz	(Ljava/lang/Object;)I;
NameAndType	unboxToInt:(Ljava/lang/Object;)I
Method	scala/runtime/BoxesRunTime.unboxToInt:(Ljava/lang/Object;)I
Asciz	scala/collection/mutable/Builder;
class	scala/collection/mutable/Builder
Asciz	sizeHint;
NameAndType	sizeHint:(I)V
InterfaceMethod	scala/collection/mutable/Builder.sizeHint:(I)V
Asciz	scala/Array$$anonfun$concat$2;
class	scala/Array$$anonfun$concat$2
Asciz	(Lscala/collection/mutable/ArrayBuilder;)V;
NameAndType	"<init>":(Lscala/collection/mutable/ArrayBuilder;)V
Method	scala/Array$$anonfun$concat$2."<init>":(Lscala/collection/mutable/ArrayBuilder;)V
InterfaceMethod	scala/collection/IterableLike.foreach:(Lscala/Function1;)V
Asciz	result;
Asciz	()Ljava/lang/Object;;
NameAndType	result:()Ljava/lang/Object;
InterfaceMethod	scala/collection/mutable/Builder.result:()Ljava/lang/Object;
Asciz	scala/MatchError;
class	scala/MatchError
Asciz	toString;
Asciz	()Ljava/lang/String;;
NameAndType	toString:()Ljava/lang/String;
Method	scala/io/BytePickle$RefDef.toString:()Ljava/lang/String;
Asciz	(Ljava/lang/String;)V;
NameAndType	"<init>":(Ljava/lang/String;)V
Method	scala/MatchError."<init>":(Ljava/lang/String;)V
Asciz	b;
Asciz	Lscala/io/BytePickle$RefDef;;
Asciz	i$10;
Asciz	Lscala/runtime/IntRef;;
Asciz	array$10;
Asciz	b$10;
Asciz	Lscala/collection/mutable/ArrayBuilder;;
Asciz	i$11;
Asciz	array$11;
Asciz	b$11;
Asciz	Lscala/io/BytePickle$PU<Lscala/io/BytePickle$RefDef;>;;
Asciz	Scala;
Asciz	InnerClasses;
Asciz	scala/io/BytePickle;
class	scala/io/BytePickle
Asciz	PU;
Asciz	Def;
Asciz	Ref;
Asciz	scala/collection/mutable/ArrayOps;
class	scala/collection/mutable/ArrayOps
Asciz	ofByte;
Asciz	RefDef;
Asciz	$anon$1;
Asciz	scala/Array;
class	scala/Array
Asciz	$anonfun$apply$1;
Asciz	$anonfun$concat$2;
Asciz	$anonfun$concat$1;
Asciz	scala/collection/generic/TraversableFactory;
class	scala/collection/generic/TraversableFactory
Asciz	GenericCanBuildFrom;

{
public scala.io.BytePickle$$anon$1();
  Signature: ()V
  Code:
   Stack=1, Locals=1, Args_size=1
	aload_0
	invokespecial	Method scala/io/BytePickle$PU."<init>":()V
	return
  Labels:

public byte[] appP(java.lang.Object, byte[]);
  Signature: (Ljava/lang/Object;[B)[B
  Code:
   Stack=3, Locals=3, Args_size=3
	aload_0
	aload_1
	checkcast	class scala/io/BytePickle$RefDef
	aload_2
	invokevirtual	Method appP:(Lscala/io/BytePickle$RefDef;[B)[B
	areturn
  Labels:
  LocalVariableTable: 
   Start  Length  Slot  Name   Signature
   0      10      0    this       Lscala/io/BytePickle$$anon$1;
   0      10      1    a       Ljava/lang/Object;
   0      10      2    state       [B


public scala.Tuple2 appU(byte[]);
  Signature: ([B)Lscala/Tuple2;
  Code:
   Stack=6, Locals=2, Args_size=2
	aload_1
	iconst_0
	baload
	bipush	0
	if_icmpne	l1 // new
	new	class scala/Tuple2
	dup
	new	class scala/io/BytePickle$Ref
	dup
	invokespecial	Method scala/io/BytePickle$Ref."<init>":()V
	new	class scala/collection/mutable/ArrayOps$ofByte
	dup
	aload_1
	invokespecial	Method scala/collection/mutable/ArrayOps$ofByte."<init>":([B)V
	iconst_1
	aload_1
	arraylength
	invokeinterface	InterfaceMethod scala/collection/IndexedSeqLike.slice:(II)Ljava/lang/Object;
	invokespecial	Method scala/Tuple2."<init>":(Ljava/lang/Object;Ljava/lang/Object;)V
	goto	l2 // areturn
l1	new	class scala/Tuple2
	dup
	new	class scala/io/BytePickle$Def
	dup
	invokespecial	Method scala/io/BytePickle$Def."<init>":()V
	new	class scala/collection/mutable/ArrayOps$ofByte
	dup
	aload_1
	invokespecial	Method scala/collection/mutable/ArrayOps$ofByte."<init>":([B)V
	iconst_1
	aload_1
	arraylength
	invokeinterface	InterfaceMethod scala/collection/IndexedSeqLike.slice:(II)Ljava/lang/Object;
	invokespecial	Method scala/Tuple2."<init>":(Ljava/lang/Object;Ljava/lang/Object;)V
l2	areturn
  Labels:
   	l1 = 41 // new
   	l2 = 71 // areturn
  LocalVariableTable: 
   Start  Length  Slot  Name   Signature
   0      72      0    this       Lscala/io/BytePickle$$anon$1;
   0      72      1    s       [B

  Signature: length = 0x2
   00 34 

public byte[] appP(scala.io.BytePickle$RefDef, byte[]);
  Signature: (Lscala/io/BytePickle$RefDef;[B)[B
  Code:
   Stack=9, Locals=19, Args_size=3
	aload_1
	instanceof	class scala/io/BytePickle$Ref
	ifeq	l1 // aload_1
	iconst_1
	ifeq	l2 // new
	getstatic	Field scala/Predef$.MODULE$:Lscala/Predef$;
	iconst_2
	anewarray	class "[B"
	dup
	iconst_0
	aload_2
	aastore
	dup
	iconst_1
	getstatic	Field scala/Predef$.MODULE$:Lscala/Predef$;
	iconst_1
	newarray byte
	dup
	iconst_0
	bipush	0
	bastore
	invokevirtual	Method scala/Predef$.wrapByteArray:([B)Lscala/collection/mutable/WrappedArray;
	getstatic	Field scala/reflect/Manifest$.MODULE$:Lscala/reflect/Manifest$;
	invokevirtual	Method scala/reflect/Manifest$.Byte:()Lscala/reflect/AnyValManifest;
	astore_3
	astore	4
	aload_3
	aload	4
	invokeinterface	InterfaceMethod scala/collection/SeqLike.length:()I
	invokeinterface	InterfaceMethod scala/reflect/ClassManifest.newArray:(I)Ljava/lang/Object;
	astore	6
	new	class scala/runtime/IntRef
	dup
	iconst_0
	invokespecial	Method scala/runtime/IntRef."<init>":(I)V
	astore	5
	aload	4
	invokeinterface	InterfaceMethod scala/collection/IterableLike.iterator:()Lscala/collection/Iterator;
	new	class scala/Array$$anonfun$apply$1
	dup
	aload	6
	aload	5
	invokespecial	Method scala/Array$$anonfun$apply$1."<init>":(Ljava/lang/Object;Lscala/runtime/IntRef;)V
	invokeinterface	InterfaceMethod scala/collection/Iterator.foreach:(Lscala/Function1;)V
	aload	6
	checkcast	class "[B"
	aastore
	checkcast	class "[Ljava/lang/Object;"
	invokevirtual	Method scala/Predef$.wrapRefArray:([Ljava/lang/Object;)Lscala/collection/mutable/WrappedArray;
	getstatic	Field scala/reflect/Manifest$.MODULE$:Lscala/reflect/Manifest$;
	invokevirtual	Method scala/reflect/Manifest$.Byte:()Lscala/reflect/AnyValManifest;
	astore	7
	astore	9
	aload	7
	checkcast	class scala/reflect/ClassManifest
	invokeinterface	InterfaceMethod scala/reflect/ClassManifest.newArrayBuilder:()Lscala/collection/mutable/ArrayBuilder;
	astore	10
	aload	10
	aload	9
	new	class scala/Array$$anonfun$concat$1
	dup
	invokespecial	Method scala/Array$$anonfun$concat$1."<init>":()V
	getstatic	Field scala/collection/Seq$.MODULE$:Lscala/collection/Seq$;
	astore	8
	new	class scala/collection/generic/TraversableFactory$GenericCanBuildFrom
	dup
	aload	8
	invokespecial	Method scala/collection/generic/TraversableFactory$GenericCanBuildFrom."<init>":(Lscala/collection/generic/TraversableFactory;)V
	invokeinterface	InterfaceMethod scala/collection/TraversableLike.map:(Lscala/Function1;Lscala/collection/generic/CanBuildFrom;)Ljava/lang/Object;
	checkcast	class scala/collection/TraversableLike
	getstatic	Field scala/math/Numeric$IntIsIntegral$.MODULE$:Lscala/math/Numeric$IntIsIntegral$;
	invokeinterface	InterfaceMethod scala/collection/TraversableLike.sum:(Lscala/math/Numeric;)Ljava/lang/Object;
	invokestatic	Method scala/runtime/BoxesRunTime.unboxToInt:(Ljava/lang/Object;)I
	invokeinterface	InterfaceMethod scala/collection/mutable/Builder.sizeHint:(I)V
	aload	9
	new	class scala/Array$$anonfun$concat$2
	dup
	aload	10
	invokespecial	Method scala/Array$$anonfun$concat$2."<init>":(Lscala/collection/mutable/ArrayBuilder;)V
	invokeinterface	InterfaceMethod scala/collection/IterableLike.foreach:(Lscala/Function1;)V
	aload	10
	invokeinterface	InterfaceMethod scala/collection/mutable/Builder.result:()Ljava/lang/Object;
	checkcast	class "[B"
	goto	l3 // areturn
l2	new	class scala/MatchError
	dup
	aload_1
	invokevirtual	Method scala/io/BytePickle$RefDef.toString:()Ljava/lang/String;
	invokespecial	Method scala/MatchError."<init>":(Ljava/lang/String;)V
	athrow
l1	aload_1
	instanceof	class scala/io/BytePickle$Def
	ifeq	l4 // new
	iconst_1
	ifeq	l5 // new
	getstatic	Field scala/Predef$.MODULE$:Lscala/Predef$;
	iconst_2
	anewarray	class "[B"
	dup
	iconst_0
	aload_2
	aastore
	dup
	iconst_1
	getstatic	Field scala/Predef$.MODULE$:Lscala/Predef$;
	iconst_1
	newarray byte
	dup
	iconst_0
	bipush	1
	bastore
	invokevirtual	Method scala/Predef$.wrapByteArray:([B)Lscala/collection/mutable/WrappedArray;
	getstatic	Field scala/reflect/Manifest$.MODULE$:Lscala/reflect/Manifest$;
	invokevirtual	Method scala/reflect/Manifest$.Byte:()Lscala/reflect/AnyValManifest;
	astore	11
	astore	12
	aload	11
	aload	12
	invokeinterface	InterfaceMethod scala/collection/SeqLike.length:()I
	invokeinterface	InterfaceMethod scala/reflect/ClassManifest.newArray:(I)Ljava/lang/Object;
	astore	14
	new	class scala/runtime/IntRef
	dup
	iconst_0
	invokespecial	Method scala/runtime/IntRef."<init>":(I)V
	astore	13
	aload	12
	invokeinterface	InterfaceMethod scala/collection/IterableLike.iterator:()Lscala/collection/Iterator;
	new	class scala/Array$$anonfun$apply$1
	dup
	aload	14
	aload	13
	invokespecial	Method scala/Array$$anonfun$apply$1."<init>":(Ljava/lang/Object;Lscala/runtime/IntRef;)V
	invokeinterface	InterfaceMethod scala/collection/Iterator.foreach:(Lscala/Function1;)V
	aload	14
	checkcast	class "[B"
	aastore
	checkcast	class "[Ljava/lang/Object;"
	invokevirtual	Method scala/Predef$.wrapRefArray:([Ljava/lang/Object;)Lscala/collection/mutable/WrappedArray;
	getstatic	Field scala/reflect/Manifest$.MODULE$:Lscala/reflect/Manifest$;
	invokevirtual	Method scala/reflect/Manifest$.Byte:()Lscala/reflect/AnyValManifest;
	astore	15
	astore	17
	aload	15
	checkcast	class scala/reflect/ClassManifest
	invokeinterface	InterfaceMethod scala/reflect/ClassManifest.newArrayBuilder:()Lscala/collection/mutable/ArrayBuilder;
	astore	18
	aload	18
	aload	17
	new	class scala/Array$$anonfun$concat$1
	dup
	invokespecial	Method scala/Array$$anonfun$concat$1."<init>":()V
	getstatic	Field scala/collection/Seq$.MODULE$:Lscala/collection/Seq$;
	astore	16
	new	class scala/collection/generic/TraversableFactory$GenericCanBuildFrom
	dup
	aload	16
	invokespecial	Method scala/collection/generic/TraversableFactory$GenericCanBuildFrom."<init>":(Lscala/collection/generic/TraversableFactory;)V
	invokeinterface	InterfaceMethod scala/collection/TraversableLike.map:(Lscala/Function1;Lscala/collection/generic/CanBuildFrom;)Ljava/lang/Object;
	checkcast	class scala/collection/TraversableLike
	getstatic	Field scala/math/Numeric$IntIsIntegral$.MODULE$:Lscala/math/Numeric$IntIsIntegral$;
	invokeinterface	InterfaceMethod scala/collection/TraversableLike.sum:(Lscala/math/Numeric;)Ljava/lang/Object;
	invokestatic	Method scala/runtime/BoxesRunTime.unboxToInt:(Ljava/lang/Object;)I
	invokeinterface	InterfaceMethod scala/collection/mutable/Builder.sizeHint:(I)V
	aload	17
	new	class scala/Array$$anonfun$concat$2
	dup
	aload	18
	invokespecial	Method scala/Array$$anonfun$concat$2."<init>":(Lscala/collection/mutable/ArrayBuilder;)V
	invokeinterface	InterfaceMethod scala/collection/IterableLike.foreach:(Lscala/Function1;)V
	aload	18
	invokeinterface	InterfaceMethod scala/collection/mutable/Builder.result:()Ljava/lang/Object;
	checkcast	class "[B"
l3	areturn
l5	new	class scala/MatchError
	dup
	aload_1
	invokevirtual	Method scala/io/BytePickle$RefDef.toString:()Ljava/lang/String;
	invokespecial	Method scala/MatchError."<init>":(Ljava/lang/String;)V
	athrow
l4	new	class scala/MatchError
	dup
	aload_1
	invokevirtual	Method scala/io/BytePickle$RefDef.toString:()Ljava/lang/String;
	invokespecial	Method scala/MatchError."<init>":(Ljava/lang/String;)V
	athrow
  Labels:
   	l2 = 207 // new
   	l1 = 219 // aload_1
   	l3 = 425 // areturn
   	l5 = 426 // new
   	l4 = 438 // new
  LocalVariableTable: 
   Start  Length  Slot  Name   Signature
   0      450      0    this       Lscala/io/BytePickle$$anon$1;
   0      450      1    b       Lscala/io/BytePickle$RefDef;
   0      450      2    s       [B
   72      25      5    i$10       Lscala/runtime/IntRef;
   62      35      6    array$10       Ljava/lang/Object;
   129      72      10    b$10       Lscala/collection/mutable/ArrayBuilder;
   293      25      13    i$11       Lscala/runtime/IntRef;
   283      35      14    array$11       Ljava/lang/Object;
   350      72      18    b$11       Lscala/collection/mutable/ArrayBuilder;


}

