Compiled from "BytePickle.scala"
public final class scala.io.BytePickle$$anonfun$list$1 extends scala.runtime.AbstractFunction1 implements java.io.Serializable
  SourceFile: "BytePickle.scala"
  Scala: length = 0x
   
  InnerClass: 
   public final #50= #9 of #49; //$anonfun$list$1=class scala/io/BytePickle$$anonfun$list$1 of class scala/io/BytePickle
  minor version: 0
  major version: 49
  Constant pool:
const #1 = Asciz	SourceFile;
const #2 = Asciz	BytePickle.scala;
const #3 = Asciz	<clinit>;
const #4 = Asciz	()V;
const #5 = Asciz	Code;
const #6 = Asciz	serialVersionUID;
const #7 = Asciz	J;
const #8 = Asciz	scala/io/BytePickle$$anonfun$list$1;
const #9 = class	#8;	//  scala/io/BytePickle$$anonfun$list$1
const #10 = NameAndType	#6:#7;//  serialVersionUID:J
const #11 = Field	#9.#10;	//  scala/io/BytePickle$$anonfun$list$1.serialVersionUID:J
const #12 = Asciz	<init>;
const #13 = Asciz	LineNumberTable;
const #14 = Asciz	scala/runtime/AbstractFunction1;
const #15 = class	#14;	//  scala/runtime/AbstractFunction1
const #16 = NameAndType	#12:#4;//  "<init>":()V
const #17 = Method	#15.#16;	//  scala/runtime/AbstractFunction1."<init>":()V
const #18 = Asciz	apply;
const #19 = Asciz	(Ljava/lang/Object;)Ljava/lang/Object;;
const #20 = Asciz	scala/collection/immutable/List;
const #21 = class	#20;	//  scala/collection/immutable/List
const #22 = Asciz	(Lscala/collection/immutable/List;)I;
const #23 = NameAndType	#18:#22;//  apply:(Lscala/collection/immutable/List;)I
const #24 = Method	#9.#23;	//  scala/io/BytePickle$$anonfun$list$1.apply:(Lscala/collection/immutable/List;)I
const #25 = Asciz	scala/runtime/BoxesRunTime;
const #26 = class	#25;	//  scala/runtime/BoxesRunTime
const #27 = Asciz	boxToInteger;
const #28 = Asciz	(I)Ljava/lang/Integer;;
const #29 = NameAndType	#27:#28;//  boxToInteger:(I)Ljava/lang/Integer;
const #30 = Method	#26.#29;	//  scala/runtime/BoxesRunTime.boxToInteger:(I)Ljava/lang/Integer;
const #31 = Asciz	this;
const #32 = Asciz	Lscala/io/BytePickle$$anonfun$list$1;;
const #33 = Asciz	v1;
const #34 = Asciz	Ljava/lang/Object;;
const #35 = Asciz	LocalVariableTable;
const #36 = Asciz	scala/collection/LinearSeqLike;
const #37 = class	#36;	//  scala/collection/LinearSeqLike
const #38 = Asciz	length;
const #39 = Asciz	()I;
const #40 = NameAndType	#38:#39;//  length:()I
const #41 = InterfaceMethod	#37.#40;	//  scala/collection/LinearSeqLike.length:()I
const #42 = Asciz	l;
const #43 = Asciz	Lscala/collection/immutable/List;;
const #44 = Asciz	(Lscala/collection/immutable/List<Ta;>;)I;
const #45 = Asciz	Signature;
const #46 = Asciz	Scala;
const #47 = Asciz	InnerClasses;
const #48 = Asciz	scala/io/BytePickle;
const #49 = class	#48;	//  scala/io/BytePickle
const #50 = Asciz	$anonfun$list$1;
const #51 = Asciz	java/io/Serializable;
const #52 = class	#51;	//  java/io/Serializable

{
public static final long serialVersionUID;

public static {};
  Code:
   Stack=2, Locals=0, Args_size=0
   0:	lconst_0
   1:	putstatic	#11; //Field serialVersionUID:J
   4:	return

public scala.io.BytePickle$$anonfun$list$1();
  Code:
   Stack=1, Locals=1, Args_size=1
   0:	aload_0
   1:	invokespecial	#17; //Method scala/runtime/AbstractFunction1."<init>":()V
   4:	return
  LineNumberTable: 
   line 313: 0


public final java.lang.Object apply(java.lang.Object);
  Code:
   Stack=2, Locals=3, Args_size=2
   0:	aload_0
   1:	aload_1
   2:	checkcast	#21; //class scala/collection/immutable/List
   5:	invokevirtual	#24; //Method apply:(Lscala/collection/immutable/List;)I
   8:	istore_2
   9:	iload_2
   10:	invokestatic	#30; //Method scala/runtime/BoxesRunTime.boxToInteger:(I)Ljava/lang/Integer;
   13:	areturn
  LineNumberTable: 
   line 313: 0

  LocalVariableTable: 
   Start  Length  Slot  Name   Signature
   0      14      0    this       Lscala/io/BytePickle$$anonfun$list$1;
   0      14      1    v1       Ljava/lang/Object;


public final int apply(scala.collection.immutable.List);
  Code:
   Stack=1, Locals=2, Args_size=2
   0:	aload_1
   1:	invokeinterface	#41,  1; //InterfaceMethod scala/collection/LinearSeqLike.length:()I
   6:	ireturn
  LineNumberTable: 
   line 313: 0

  LocalVariableTable: 
   Start  Length  Slot  Name   Signature
   0      7      0    this       Lscala/io/BytePickle$$anonfun$list$1;
   0      7      1    l       Lscala/collection/immutable/List;

  Signature: length = 0x2
   00 2C 

}

