Compiled from "BytePickle.scala"
public final class scala.io.BytePickle$$anon$4 extends scala.io.BytePickle$PU
  SourceFile: "BytePickle.scala"
  Scala: length = 0x
   
  Signature: length = 0x2
   00 4E 
  InnerClass: 
   public abstract PU=class scala/io/BytePickle$PU of class scala/io/BytePickle
   public final $anon$4=class scala/io/BytePickle$$anon$4 of class scala/io/BytePickle
  minor version: 0
  major version: 49
  Constant pool:
Asciz	SourceFile;
Asciz	BytePickle.scala;
Asciz	x$4;
Asciz	Ljava/lang/Object;;
Asciz	appP;
Asciz	(Ljava/lang/Object;[B)[B;
Asciz	Code;
Asciz	LineNumberTable;
Asciz	scala/io/BytePickle$$anon$4;
class	scala/io/BytePickle$$anon$4
NameAndType	x$4:Ljava/lang/Object;
Field	scala/io/BytePickle$$anon$4.x$4:Ljava/lang/Object;
Asciz	java/lang/Number;
class	java/lang/Number
Asciz	scala/runtime/BoxesRunTime;
class	scala/runtime/BoxesRunTime
Asciz	equalsNumObject;
Asciz	(Ljava/lang/Number;Ljava/lang/Object;)Z;
NameAndType	equalsNumObject:(Ljava/lang/Number;Ljava/lang/Object;)Z
Method	scala/runtime/BoxesRunTime.equalsNumObject:(Ljava/lang/Number;Ljava/lang/Object;)Z
Asciz	java/lang/Character;
class	java/lang/Character
Asciz	equalsCharObject;
Asciz	(Ljava/lang/Character;Ljava/lang/Object;)Z;
NameAndType	equalsCharObject:(Ljava/lang/Character;Ljava/lang/Object;)Z
Method	scala/runtime/BoxesRunTime.equalsCharObject:(Ljava/lang/Character;Ljava/lang/Object;)Z
Asciz	java/lang/Object;
class	java/lang/Object
Asciz	equals;
Asciz	(Ljava/lang/Object;)Z;
NameAndType	equals:(Ljava/lang/Object;)Z
Method	java/lang/Object.equals:(Ljava/lang/Object;)Z
Asciz	java/lang/IllegalArgumentException;
class	java/lang/IllegalArgumentException
Asciz	scala/collection/mutable/StringBuilder;
class	scala/collection/mutable/StringBuilder
Asciz	<init>;
Asciz	()V;
NameAndType	"<init>":()V
Method	scala/collection/mutable/StringBuilder."<init>":()V
Asciz	value to be pickled (;
String	value to be pickled (
Asciz	append;
Asciz	(Ljava/lang/Object;)Lscala/collection/mutable/StringBuilder;;
NameAndType	append:(Ljava/lang/Object;)Lscala/collection/mutable/StringBuilder;
Method	scala/collection/mutable/StringBuilder.append:(Ljava/lang/Object;)Lscala/collection/mutable/StringBuilder;
Asciz	) != ;
String	) != 
Asciz	toString;
Asciz	()Ljava/lang/String;;
NameAndType	toString:()Ljava/lang/String;
Method	scala/collection/mutable/StringBuilder.toString:()Ljava/lang/String;
Asciz	(Ljava/lang/String;)V;
NameAndType	"<init>":(Ljava/lang/String;)V
Method	java/lang/IllegalArgumentException."<init>":(Ljava/lang/String;)V
Asciz	this;
Asciz	Lscala/io/BytePickle$$anon$4;;
Asciz	a;
Asciz	state;
Asciz	[B;
Asciz	x0;
Asciz	LocalVariableTable;
Asciz	(Tt;[B)[B;
Asciz	Signature;
Asciz	appU;
Asciz	([B)Lscala/Tuple2;;
Asciz	scala/Tuple2;
class	scala/Tuple2
Asciz	(Ljava/lang/Object;Ljava/lang/Object;)V;
NameAndType	"<init>":(Ljava/lang/Object;Ljava/lang/Object;)V
Method	scala/Tuple2."<init>":(Ljava/lang/Object;Ljava/lang/Object;)V
Asciz	([B)Lscala/Tuple2<Tt;[B>;;
Asciz	(Ljava/lang/Object;)V;
Asciz	scala/io/BytePickle$PU;
class	scala/io/BytePickle$PU
Method	scala/io/BytePickle$PU."<init>":()V
Asciz	Scala;
Asciz	Lscala/io/BytePickle$PU<Tt;>;;
Asciz	InnerClasses;
Asciz	scala/io/BytePickle;
class	scala/io/BytePickle
Asciz	PU;
Asciz	$anon$4;

{
private final java.lang.Object x$4;
  Signature: Ljava/lang/Object;

public byte[] appP(java.lang.Object, byte[]);
  Signature: (Ljava/lang/Object;[B)[B
  Code:
   Stack=4, Locals=4, Args_size=3
	aload_0
	getfield	Field x$4:Ljava/lang/Object;
	astore_3
	aload_3
	aload_1
	if_acmpne	l1 // aload_3
	iconst_1
	goto	l2 // ifeq
l1	aload_3
	ifnonnull	l3 // aload_3
	iconst_0
	goto	l2 // ifeq
l3	aload_3
	instanceof	class java/lang/Number
	ifeq	l4 // aload_3
	aload_3
	checkcast	class java/lang/Number
	aload_1
	invokestatic	Method scala/runtime/BoxesRunTime.equalsNumObject:(Ljava/lang/Number;Ljava/lang/Object;)Z
	goto	l2 // ifeq
l4	aload_3
	instanceof	class java/lang/Character
	ifeq	l5 // aload_3
	aload_3
	checkcast	class java/lang/Character
	aload_1
	invokestatic	Method scala/runtime/BoxesRunTime.equalsCharObject:(Ljava/lang/Character;Ljava/lang/Object;)Z
	goto	l2 // ifeq
l5	aload_3
	aload_1
	invokevirtual	Method java/lang/Object.equals:(Ljava/lang/Object;)Z
l2	ifeq	l6 // new
	aload_2
	areturn
l6	new	class java/lang/IllegalArgumentException
	dup
	new	class scala/collection/mutable/StringBuilder
	dup
	invokespecial	Method scala/collection/mutable/StringBuilder."<init>":()V
	ldc	String value to be pickled (
	invokevirtual	Method scala/collection/mutable/StringBuilder.append:(Ljava/lang/Object;)Lscala/collection/mutable/StringBuilder;
	aload_1
	invokevirtual	Method scala/collection/mutable/StringBuilder.append:(Ljava/lang/Object;)Lscala/collection/mutable/StringBuilder;
	ldc	String ) != 
	invokevirtual	Method scala/collection/mutable/StringBuilder.append:(Ljava/lang/Object;)Lscala/collection/mutable/StringBuilder;
	aload_0
	getfield	Field x$4:Ljava/lang/Object;
	invokevirtual	Method scala/collection/mutable/StringBuilder.append:(Ljava/lang/Object;)Lscala/collection/mutable/StringBuilder;
	invokevirtual	Method scala/collection/mutable/StringBuilder.toString:()Ljava/lang/String;
	invokespecial	Method java/lang/IllegalArgumentException."<init>":(Ljava/lang/String;)V
	athrow
  Labels:
   	l1 = 14 // aload_3
   	l3 = 22 // aload_3
   	l4 = 40 // aload_3
   	l5 = 58 // aload_3
   	l2 = 63 // ifeq
   	l6 = 68 // new
  LocalVariableTable: 
   Start  Length  Slot  Name   Signature
   0      107      0    this       Lscala/io/BytePickle$$anon$4;
   0      107      1    a       Ljava/lang/Object;
   0      107      2    state       [B
   10      56      3    x0       Ljava/lang/Object;

  Signature: length = 0x2
   00 3F 

public scala.Tuple2 appU(byte[]);
  Signature: ([B)Lscala/Tuple2;
  Code:
   Stack=4, Locals=2, Args_size=2
	new	class scala/Tuple2
	dup
	aload_0
	getfield	Field x$4:Ljava/lang/Object;
	aload_1
	invokespecial	Method scala/Tuple2."<init>":(Ljava/lang/Object;Ljava/lang/Object;)V
	areturn
  Labels:
  LocalVariableTable: 
   Start  Length  Slot  Name   Signature
   0      13      0    this       Lscala/io/BytePickle$$anon$4;
   0      13      1    state       [B

  Signature: length = 0x2
   00 48 

public scala.io.BytePickle$$anon$4(java.lang.Object);
  Signature: (Ljava/lang/Object;)V
  Code:
   Stack=2, Locals=2, Args_size=2
	aload_0
	aload_1
	putfield	Field x$4:Ljava/lang/Object;
	aload_0
	invokespecial	Method scala/io/BytePickle$PU."<init>":()V
	return
  Labels:

}

