Compiled from "BytePickle.scala"
public final class scala.io.BytePickle$$anon$6 extends scala.io.BytePickle$PU
  SourceFile: "BytePickle.scala"
  Signature: length = 0x2
   00 53 
  Scala: length = 0x
   
  InnerClass: 
   public abstract #88= #21 of #87; //PU=class scala/io/BytePickle$PU of class scala/io/BytePickle
   public final #89= #13 of #87; //$anon$6=class scala/io/BytePickle$$anon$6 of class scala/io/BytePickle
  minor version: 0
  major version: 49
  Constant pool:
const #1 = Asciz	SourceFile;
const #2 = Asciz	BytePickle.scala;
const #3 = Asciz	k$1;
const #4 = Asciz	Lscala/Function1;;
const #5 = Asciz	pa$2;
const #6 = Asciz	Lscala/io/BytePickle$PU;;
const #7 = Asciz	f$1;
const #8 = Asciz	<init>;
const #9 = Asciz	(Lscala/Function1;Lscala/io/BytePickle$PU;Lscala/Function1;)V;
const #10 = Asciz	Code;
const #11 = Asciz	LineNumberTable;
const #12 = Asciz	scala/io/BytePickle$$anon$6;
const #13 = class	#12;	//  scala/io/BytePickle$$anon$6
const #14 = NameAndType	#7:#4;//  f$1:Lscala/Function1;
const #15 = Field	#13.#14;	//  scala/io/BytePickle$$anon$6.f$1:Lscala/Function1;
const #16 = NameAndType	#5:#6;//  pa$2:Lscala/io/BytePickle$PU;
const #17 = Field	#13.#16;	//  scala/io/BytePickle$$anon$6.pa$2:Lscala/io/BytePickle$PU;
const #18 = NameAndType	#3:#4;//  k$1:Lscala/Function1;
const #19 = Field	#13.#18;	//  scala/io/BytePickle$$anon$6.k$1:Lscala/Function1;
const #20 = Asciz	scala/io/BytePickle$PU;
const #21 = class	#20;	//  scala/io/BytePickle$PU
const #22 = Asciz	()V;
const #23 = NameAndType	#8:#22;//  "<init>":()V
const #24 = Method	#21.#23;	//  scala/io/BytePickle$PU."<init>":()V
const #25 = Asciz	appU;
const #26 = Asciz	([B)Lscala/Tuple2;;
const #27 = NameAndType	#25:#26;//  appU:([B)Lscala/Tuple2;
const #28 = Method	#21.#27;	//  scala/io/BytePickle$PU.appU:([B)Lscala/Tuple2;
const #29 = Asciz	scala/Tuple2;
const #30 = class	#29;	//  scala/Tuple2
const #31 = Asciz	_1;
const #32 = Asciz	()Ljava/lang/Object;;
const #33 = NameAndType	#31:#32;//  _1:()Ljava/lang/Object;
const #34 = Method	#30.#33;	//  scala/Tuple2._1:()Ljava/lang/Object;
const #35 = Asciz	_2;
const #36 = NameAndType	#35:#32;//  _2:()Ljava/lang/Object;
const #37 = Method	#30.#36;	//  scala/Tuple2._2:()Ljava/lang/Object;
const #38 = Asciz	scala/runtime/BoxedArray;
const #39 = class	#38;	//  scala/runtime/BoxedArray
const #40 = Asciz	scala/runtime/ScalaRunTime$;
const #41 = class	#40;	//  scala/runtime/ScalaRunTime$
const #42 = Asciz	MODULE$;
const #43 = Asciz	Lscala/runtime/ScalaRunTime$;;
const #44 = NameAndType	#42:#43;//  MODULE$:Lscala/runtime/ScalaRunTime$;
const #45 = Field	#41.#44;	//  scala/runtime/ScalaRunTime$.MODULE$:Lscala/runtime/ScalaRunTime$;
const #46 = Asciz	java/lang/Byte;
const #47 = class	#46;	//  java/lang/Byte
const #48 = Asciz	TYPE;
const #49 = Asciz	Ljava/lang/Class;;
const #50 = NameAndType	#48:#49;//  TYPE:Ljava/lang/Class;
const #51 = Field	#47.#50;	//  java/lang/Byte.TYPE:Ljava/lang/Class;
const #52 = Asciz	arrayValue;
const #53 = Asciz	(Lscala/runtime/BoxedArray;Ljava/lang/Class;)Ljava/lang/Object;;
const #54 = NameAndType	#52:#53;//  arrayValue:(Lscala/runtime/BoxedArray;Ljava/lang/Class;)Ljava/lang/Object;
const #55 = Method	#41.#54;	//  scala/runtime/ScalaRunTime$.arrayValue:(Lscala/runtime/BoxedArray;Ljava/lang/Class;)Ljava/lang/Object;
const #56 = Asciz	[B;
const #57 = class	#56;	//  "[B"
const #58 = Asciz	scala/Function1;
const #59 = class	#58;	//  scala/Function1
const #60 = Asciz	apply;
const #61 = Asciz	(Ljava/lang/Object;)Ljava/lang/Object;;
const #62 = NameAndType	#60:#61;//  apply:(Ljava/lang/Object;)Ljava/lang/Object;
const #63 = InterfaceMethod	#59.#62;	//  scala/Function1.apply:(Ljava/lang/Object;)Ljava/lang/Object;
const #64 = Asciz	this;
const #65 = Asciz	Lscala/io/BytePickle$$anon$6;;
const #66 = Asciz	s;
const #67 = Asciz	resPa;
const #68 = Asciz	Lscala/Tuple2;;
const #69 = Asciz	a;
const #70 = Asciz	Ljava/lang/Object;;
const #71 = Asciz	sPrime;
const #72 = Asciz	pb;
const #73 = Asciz	LocalVariableTable;
const #74 = Asciz	([B)Lscala/Tuple2<Tu;[B>;;
const #75 = Asciz	Signature;
const #76 = Asciz	appP;
const #77 = Asciz	(Ljava/lang/Object;[B)[B;
const #78 = NameAndType	#76:#77;//  appP:(Ljava/lang/Object;[B)[B
const #79 = Method	#21.#78;	//  scala/io/BytePickle$PU.appP:(Ljava/lang/Object;[B)[B
const #80 = Asciz	b;
const #81 = Asciz	sPrimePrime;
const #82 = Asciz	(Tu;[B)[B;
const #83 = Asciz	Lscala/io/BytePickle$PU<Tu;>;;
const #84 = Asciz	Scala;
const #85 = Asciz	InnerClasses;
const #86 = Asciz	scala/io/BytePickle;
const #87 = class	#86;	//  scala/io/BytePickle
const #88 = Asciz	PU;
const #89 = Asciz	$anon$6;

{
public scala.io.BytePickle$$anon$6(scala.Function1, scala.io.BytePickle$PU, scala.Function1);
  Code:
   Stack=2, Locals=4, Args_size=4
   0:	aload_0
   1:	aload_1
   2:	putfield	#15; //Field f$1:Lscala/Function1;
   5:	aload_0
   6:	aload_2
   7:	putfield	#17; //Field pa$2:Lscala/io/BytePickle$PU;
   10:	aload_0
   11:	aload_3
   12:	putfield	#19; //Field k$1:Lscala/Function1;
   15:	aload_0
   16:	invokespecial	#24; //Method scala/io/BytePickle$PU."<init>":()V
   19:	return
  LineNumberTable: 
   line 169: 0


public scala.Tuple2 appU(byte[]);
  Code:
   Stack=3, Locals=6, Args_size=2
   0:	aload_0
   1:	getfield	#17; //Field pa$2:Lscala/io/BytePickle$PU;
   4:	aload_1
   5:	invokevirtual	#28; //Method scala/io/BytePickle$PU.appU:([B)Lscala/Tuple2;
   8:	astore_2
   9:	aload_2
   10:	invokevirtual	#34; //Method scala/Tuple2._1:()Ljava/lang/Object;
   13:	astore_3
   14:	aload_2
   15:	invokevirtual	#37; //Method scala/Tuple2._2:()Ljava/lang/Object;
   18:	instanceof	#39; //class scala/runtime/BoxedArray
   21:	ifeq	43
   24:	getstatic	#45; //Field scala/runtime/ScalaRunTime$.MODULE$:Lscala/runtime/ScalaRunTime$;
   27:	aload_2
   28:	invokevirtual	#37; //Method scala/Tuple2._2:()Ljava/lang/Object;
   31:	checkcast	#39; //class scala/runtime/BoxedArray
   34:	getstatic	#51; //Field java/lang/Byte.TYPE:Ljava/lang/Class;
   37:	invokevirtual	#55; //Method scala/runtime/ScalaRunTime$.arrayValue:(Lscala/runtime/BoxedArray;Ljava/lang/Class;)Ljava/lang/Object;
   40:	goto	47
   43:	aload_2
   44:	invokevirtual	#37; //Method scala/Tuple2._2:()Ljava/lang/Object;
   47:	checkcast	#57; //class "[B"
   50:	astore	4
   52:	aload_0
   53:	getfield	#19; //Field k$1:Lscala/Function1;
   56:	aload_3
   57:	invokeinterface	#63,  2; //InterfaceMethod scala/Function1.apply:(Ljava/lang/Object;)Ljava/lang/Object;
   62:	checkcast	#21; //class scala/io/BytePickle$PU
   65:	astore	5
   67:	aload	5
   69:	aload	4
   71:	invokevirtual	#28; //Method scala/io/BytePickle$PU.appU:([B)Lscala/Tuple2;
   74:	areturn
  LineNumberTable: 
   line 178: 0
   line 179: 9
   line 180: 14
   line 181: 52
   line 182: 67

  LocalVariableTable: 
   Start  Length  Slot  Name   Signature
   0      75      0    this       Lscala/io/BytePickle$$anon$6;
   0      75      1    s       [B
   9      65      2    resPa       Lscala/Tuple2;
   14      60      3    a       Ljava/lang/Object;
   52      22      4    sPrime       [B
   67      7      5    pb       Lscala/io/BytePickle$PU;

  Signature: length = 0x2
   00 4A 

public byte[] appP(java.lang.Object, byte[]);
  Code:
   Stack=3, Locals=7, Args_size=3
   0:	aload_0
   1:	getfield	#15; //Field f$1:Lscala/Function1;
   4:	aload_1
   5:	invokeinterface	#63,  2; //InterfaceMethod scala/Function1.apply:(Ljava/lang/Object;)Ljava/lang/Object;
   10:	astore_3
   11:	aload_0
   12:	getfield	#17; //Field pa$2:Lscala/io/BytePickle$PU;
   15:	aload_3
   16:	aload_2
   17:	invokevirtual	#79; //Method scala/io/BytePickle$PU.appP:(Ljava/lang/Object;[B)[B
   20:	astore	4
   22:	aload_0
   23:	getfield	#19; //Field k$1:Lscala/Function1;
   26:	aload_3
   27:	invokeinterface	#63,  2; //InterfaceMethod scala/Function1.apply:(Ljava/lang/Object;)Ljava/lang/Object;
   32:	checkcast	#21; //class scala/io/BytePickle$PU
   35:	astore	5
   37:	aload	5
   39:	aload_1
   40:	aload	4
   42:	invokevirtual	#79; //Method scala/io/BytePickle$PU.appP:(Ljava/lang/Object;[B)[B
   45:	astore	6
   47:	aload	6
   49:	areturn
  LineNumberTable: 
   line 171: 0
   line 172: 11
   line 173: 22
   line 174: 37
   line 175: 47

  LocalVariableTable: 
   Start  Length  Slot  Name   Signature
   0      50      0    this       Lscala/io/BytePickle$$anon$6;
   0      50      1    b       Ljava/lang/Object;
   0      50      2    s       [B
   11      38      3    a       Ljava/lang/Object;
   22      27      4    sPrime       [B
   37      12      5    pb       Lscala/io/BytePickle$PU;
   47      2      6    sPrimePrime       [B

  Signature: length = 0x2
   00 52 

}

