Compiled from "BytePickle.scala"
public final class scala.io.BytePickle$Ref$ extends java.lang.Object implements scala.Function0,scala.ScalaObject
  SourceFile: "BytePickle.scala"
  Scala: length = 0x
   
  InnerClass: 
   public #48= #32 of #47; //Ref=class scala/io/BytePickle$Ref of class scala/io/BytePickle
  minor version: 0
  major version: 49
  Constant pool:
const #1 = Asciz	SourceFile;
const #2 = Asciz	BytePickle.scala;
const #3 = Asciz	Scala;
const #4 = Asciz	MODULE$;
const #5 = Asciz	Lscala/io/BytePickle$Ref$;;
const #6 = Asciz	<clinit>;
const #7 = Asciz	()V;
const #8 = Asciz	Code;
const #9 = Asciz	scala/io/BytePickle$Ref$;
const #10 = class	#9;	//  scala/io/BytePickle$Ref$
const #11 = Asciz	<init>;
const #12 = NameAndType	#11:#7;//  "<init>":()V
const #13 = Method	#10.#12;	//  scala/io/BytePickle$Ref$."<init>":()V
const #14 = Asciz	LineNumberTable;
const #15 = Asciz	java/lang/Object;
const #16 = class	#15;	//  java/lang/Object
const #17 = Method	#16.#12;	//  java/lang/Object."<init>":()V
const #18 = NameAndType	#4:#5;//  MODULE$:Lscala/io/BytePickle$Ref$;
const #19 = Field	#10.#18;	//  scala/io/BytePickle$Ref$.MODULE$:Lscala/io/BytePickle$Ref$;
const #20 = Asciz	scala/Function0$class;
const #21 = class	#20;	//  scala/Function0$class
const #22 = Asciz	$init$;
const #23 = Asciz	(Lscala/Function0;)V;
const #24 = NameAndType	#22:#23;//  $init$:(Lscala/Function0;)V
const #25 = Method	#21.#24;	//  scala/Function0$class.$init$:(Lscala/Function0;)V
const #26 = Asciz	apply;
const #27 = Asciz	()Ljava/lang/Object;;
const #28 = Asciz	()Lscala/io/BytePickle$Ref;;
const #29 = NameAndType	#26:#28;//  apply:()Lscala/io/BytePickle$Ref;
const #30 = Method	#10.#29;	//  scala/io/BytePickle$Ref$.apply:()Lscala/io/BytePickle$Ref;
const #31 = Asciz	scala/io/BytePickle$Ref;
const #32 = class	#31;	//  scala/io/BytePickle$Ref
const #33 = Method	#32.#12;	//  scala/io/BytePickle$Ref."<init>":()V
const #34 = Asciz	unapply;
const #35 = Asciz	(Lscala/io/BytePickle$Ref;)Z;
const #36 = Asciz	this;
const #37 = Asciz	x$0;
const #38 = Asciz	Lscala/io/BytePickle$Ref;;
const #39 = Asciz	LocalVariableTable;
const #40 = Asciz	toString;
const #41 = Asciz	()Ljava/lang/String;;
const #42 = Asciz	(Lscala/Function0;)Ljava/lang/String;;
const #43 = NameAndType	#40:#42;//  toString:(Lscala/Function0;)Ljava/lang/String;
const #44 = Method	#21.#43;	//  scala/Function0$class.toString:(Lscala/Function0;)Ljava/lang/String;
const #45 = Asciz	InnerClasses;
const #46 = Asciz	scala/io/BytePickle;
const #47 = class	#46;	//  scala/io/BytePickle
const #48 = Asciz	Ref;
const #49 = Asciz	scala/Function0;
const #50 = class	#49;	//  scala/Function0
const #51 = Asciz	scala/ScalaObject;
const #52 = class	#51;	//  scala/ScalaObject

{
public static final scala.io.BytePickle$Ref$ MODULE$;

public static {};
  Code:
   Stack=1, Locals=0, Args_size=0
   0:	new	#10; //class scala/io/BytePickle$Ref$
   3:	invokespecial	#13; //Method "<init>":()V
   6:	return

public scala.io.BytePickle$Ref$();
  Code:
   Stack=1, Locals=1, Args_size=1
   0:	aload_0
   1:	invokespecial	#17; //Method java/lang/Object."<init>":()V
   4:	aload_0
   5:	putstatic	#19; //Field MODULE$:Lscala/io/BytePickle$Ref$;
   8:	aload_0
   9:	invokestatic	#25; //Method scala/Function0$class.$init$:(Lscala/Function0;)V
   12:	return
  LineNumberTable: 
   line 62: 0


public java.lang.Object apply();
  Code:
   Stack=1, Locals=1, Args_size=1
   0:	aload_0
   1:	invokevirtual	#30; //Method apply:()Lscala/io/BytePickle$Ref;
   4:	areturn
  LineNumberTable: 
   line 62: 0


public scala.io.BytePickle$Ref apply();
  Code:
   Stack=2, Locals=1, Args_size=1
   0:	new	#32; //class scala/io/BytePickle$Ref
   3:	dup
   4:	invokespecial	#33; //Method scala/io/BytePickle$Ref."<init>":()V
   7:	areturn
  LineNumberTable: 
   line 62: 0


public boolean unapply(scala.io.BytePickle$Ref);
  Code:
   Stack=1, Locals=2, Args_size=2
   0:	iconst_1
   1:	ireturn
  LineNumberTable: 
   line 64: 0

  LocalVariableTable: 
   Start  Length  Slot  Name   Signature
   0      2      0    this       Lscala/io/BytePickle$Ref$;
   0      2      1    x$0       Lscala/io/BytePickle$Ref;


public java.lang.String toString();
  Code:
   Stack=1, Locals=1, Args_size=1
   0:	aload_0
   1:	invokestatic	#44; //Method scala/Function0$class.toString:(Lscala/Function0;)Ljava/lang/String;
   4:	areturn
  LineNumberTable: 
   line 62: 0


}

