Compiled from "BytePickle.scala"
public abstract class scala.io.BytePickle$SPU extends java.lang.Object implements scala.ScalaObject
  SourceFile: "BytePickle.scala"
  Signature: length = 0x2
   00 12 
  Scala: length = 0x
   
  InnerClass: 
   public abstract #25= #22 of #24; //SPU=class scala/io/BytePickle$SPU of class scala/io/BytePickle
   public #28= #27 of #24; //PicklerState=class scala/io/BytePickle$PicklerState of class scala/io/BytePickle
   public #31= #30 of #24; //UnPicklerState=class scala/io/BytePickle$UnPicklerState of class scala/io/BytePickle
  minor version: 0
  major version: 49
  Constant pool:
const #1 = Asciz	SourceFile;
const #2 = Asciz	BytePickle.scala;
const #3 = Asciz	<init>;
const #4 = Asciz	()V;
const #5 = Asciz	Code;
const #6 = Asciz	LineNumberTable;
const #7 = Asciz	java/lang/Object;
const #8 = class	#7;	//  java/lang/Object
const #9 = NameAndType	#3:#4;//  "<init>":()V
const #10 = Method	#8.#9;	//  java/lang/Object."<init>":()V
const #11 = Asciz	Signature;
const #12 = Asciz	appU;
const #13 = Asciz	(Lscala/io/BytePickle$UnPicklerState;)Lscala/Tuple2;;
const #14 = Asciz	(Lscala/io/BytePickle$UnPicklerState;)Lscala/Tuple2<TT;Lscala/io/BytePickle$UnPicklerState;>;;
const #15 = Asciz	appP;
const #16 = Asciz	(Ljava/lang/Object;Lscala/io/BytePickle$PicklerState;)Lscala/io/BytePickle$PicklerState;;
const #17 = Asciz	(TT;Lscala/io/BytePickle$PicklerState;)Lscala/io/BytePickle$PicklerState;;
const #18 = Asciz	<T:Ljava/lang/Object;>Ljava/lang/Object;Lscala/ScalaObject;;
const #19 = Asciz	Scala;
const #20 = Asciz	InnerClasses;
const #21 = Asciz	scala/io/BytePickle$SPU;
const #22 = class	#21;	//  scala/io/BytePickle$SPU
const #23 = Asciz	scala/io/BytePickle;
const #24 = class	#23;	//  scala/io/BytePickle
const #25 = Asciz	SPU;
const #26 = Asciz	scala/io/BytePickle$PicklerState;
const #27 = class	#26;	//  scala/io/BytePickle$PicklerState
const #28 = Asciz	PicklerState;
const #29 = Asciz	scala/io/BytePickle$UnPicklerState;
const #30 = class	#29;	//  scala/io/BytePickle$UnPicklerState
const #31 = Asciz	UnPicklerState;
const #32 = Asciz	scala/ScalaObject;
const #33 = class	#32;	//  scala/ScalaObject

{
public scala.io.BytePickle$SPU();
  Code:
   Stack=1, Locals=1, Args_size=1
   0:	aload_0
   1:	invokespecial	#10; //Method java/lang/Object."<init>":()V
   4:	return
  LineNumberTable: 
   line 26: 0

  Signature: length = 0x2
   00 04 

public abstract scala.Tuple2 appU(scala.io.BytePickle$UnPicklerState);
  Signature: length = 0x2
   00 0E 

public abstract scala.io.BytePickle$PicklerState appP(java.lang.Object, scala.io.BytePickle$PicklerState);
  Signature: length = 0x2
   00 11 

}

