Compiled from "BytePickle.scala"
public final class scala.io.BytePickle$$anon$5 extends scala.io.BytePickle$SPU
  SourceFile: "BytePickle.scala"
  Scala: length = 0x
   
  Signature: length = 0x2
   00 3B 
  InnerClass: 
   public abstract SPU=class scala/io/BytePickle$SPU of class scala/io/BytePickle
   public final $anon$5=class scala/io/BytePickle$$anon$5 of class scala/io/BytePickle
   public PicklerState=class scala/io/BytePickle$PicklerState of class scala/io/BytePickle
   public UnPicklerState=class scala/io/BytePickle$UnPicklerState of class scala/io/BytePickle
  minor version: 0
  major version: 49
  Constant pool:
Asciz	SourceFile;
Asciz	BytePickle.scala;
Asciz	x$5;
Asciz	Ljava/lang/Object;;
Asciz	appP;
Asciz	(Ljava/lang/Object;Lscala/io/BytePickle$PicklerState;)Lscala/io/BytePickle$PicklerState;;
Asciz	Code;
Asciz	LineNumberTable;
Asciz	scala/io/BytePickle$$anon$5;
class	scala/io/BytePickle$$anon$5
NameAndType	x$5:Ljava/lang/Object;
Field	scala/io/BytePickle$$anon$5.x$5:Ljava/lang/Object;
Asciz	java/lang/Number;
class	java/lang/Number
Asciz	scala/runtime/BoxesRunTime;
class	scala/runtime/BoxesRunTime
Asciz	equalsNumObject;
Asciz	(Ljava/lang/Number;Ljava/lang/Object;)Z;
NameAndType	equalsNumObject:(Ljava/lang/Number;Ljava/lang/Object;)Z
Method	scala/runtime/BoxesRunTime.equalsNumObject:(Ljava/lang/Number;Ljava/lang/Object;)Z
Asciz	java/lang/Character;
class	java/lang/Character
Asciz	equalsCharObject;
Asciz	(Ljava/lang/Character;Ljava/lang/Object;)Z;
NameAndType	equalsCharObject:(Ljava/lang/Character;Ljava/lang/Object;)Z
Method	scala/runtime/BoxesRunTime.equalsCharObject:(Ljava/lang/Character;Ljava/lang/Object;)Z
Asciz	java/lang/Object;
class	java/lang/Object
Asciz	equals;
Asciz	(Ljava/lang/Object;)Z;
NameAndType	equals:(Ljava/lang/Object;)Z
Method	java/lang/Object.equals:(Ljava/lang/Object;)Z
Asciz	this;
Asciz	Lscala/io/BytePickle$$anon$5;;
Asciz	a;
Asciz	state;
Asciz	Lscala/io/BytePickle$PicklerState;;
Asciz	x0;
Asciz	LocalVariableTable;
Asciz	(Tt;Lscala/io/BytePickle$PicklerState;)Lscala/io/BytePickle$PicklerState;;
Asciz	Signature;
Asciz	appU;
Asciz	(Lscala/io/BytePickle$UnPicklerState;)Lscala/Tuple2;;
Asciz	scala/Tuple2;
class	scala/Tuple2
Asciz	<init>;
Asciz	(Ljava/lang/Object;Ljava/lang/Object;)V;
NameAndType	"<init>":(Ljava/lang/Object;Ljava/lang/Object;)V
Method	scala/Tuple2."<init>":(Ljava/lang/Object;Ljava/lang/Object;)V
Asciz	Lscala/io/BytePickle$UnPicklerState;;
Asciz	(Lscala/io/BytePickle$UnPicklerState;)Lscala/Tuple2<Tt;Lscala/io/BytePickle$UnPicklerState;>;;
Asciz	(Ljava/lang/Object;)V;
Asciz	scala/io/BytePickle$SPU;
class	scala/io/BytePickle$SPU
Asciz	()V;
NameAndType	"<init>":()V
Method	scala/io/BytePickle$SPU."<init>":()V
Asciz	Scala;
Asciz	Lscala/io/BytePickle$SPU<Tt;>;;
Asciz	InnerClasses;
Asciz	scala/io/BytePickle;
class	scala/io/BytePickle
Asciz	SPU;
Asciz	$anon$5;
Asciz	scala/io/BytePickle$PicklerState;
class	scala/io/BytePickle$PicklerState
Asciz	PicklerState;
Asciz	scala/io/BytePickle$UnPicklerState;
class	scala/io/BytePickle$UnPicklerState
Asciz	UnPicklerState;

{
private final java.lang.Object x$5;
  Signature: Ljava/lang/Object;

public scala.io.BytePickle$PicklerState appP(java.lang.Object, scala.io.BytePickle$PicklerState);
  Signature: (Ljava/lang/Object;Lscala/io/BytePickle$PicklerState;)Lscala/io/BytePickle$PicklerState;
  Code:
   Stack=2, Locals=4, Args_size=3
	aload_0
	getfield	Field x$5:Ljava/lang/Object;
	astore_3
	aload_3
	aload_1
	if_acmpne	l1 // aload_3
	iconst_1
	goto	l2 // ifeq
l1	aload_3
	ifnonnull	l3 // aload_3
	iconst_0
	goto	l2 // ifeq
l3	aload_3
	instanceof	class java/lang/Number
	ifeq	l4 // aload_3
	aload_3
	checkcast	class java/lang/Number
	aload_1
	invokestatic	Method scala/runtime/BoxesRunTime.equalsNumObject:(Ljava/lang/Number;Ljava/lang/Object;)Z
	goto	l2 // ifeq
l4	aload_3
	instanceof	class java/lang/Character
	ifeq	l5 // aload_3
	aload_3
	checkcast	class java/lang/Character
	aload_1
	invokestatic	Method scala/runtime/BoxesRunTime.equalsCharObject:(Ljava/lang/Character;Ljava/lang/Object;)Z
	goto	l2 // ifeq
l5	aload_3
	aload_1
	invokevirtual	Method java/lang/Object.equals:(Ljava/lang/Object;)Z
l2	ifeq	l6 // aload_2
	aload_2
	goto	l7 // areturn
l6	aload_2
l7	areturn
  Labels:
   	l1 = 14 // aload_3
   	l3 = 22 // aload_3
   	l4 = 40 // aload_3
   	l5 = 58 // aload_3
   	l2 = 63 // ifeq
   	l6 = 70 // aload_2
   	l7 = 71 // areturn
  LocalVariableTable: 
   Start  Length  Slot  Name   Signature
   0      72      0    this       Lscala/io/BytePickle$$anon$5;
   0      72      1    a       Ljava/lang/Object;
   0      72      2    state       Lscala/io/BytePickle$PicklerState;
   10      56      3    x0       Ljava/lang/Object;

  Signature: length = 0x2
   00 28 

public scala.Tuple2 appU(scala.io.BytePickle$UnPicklerState);
  Signature: (Lscala/io/BytePickle$UnPicklerState;)Lscala/Tuple2;
  Code:
   Stack=4, Locals=2, Args_size=2
	new	class scala/Tuple2
	dup
	aload_0
	getfield	Field x$5:Ljava/lang/Object;
	aload_1
	invokespecial	Method scala/Tuple2."<init>":(Ljava/lang/Object;Ljava/lang/Object;)V
	areturn
  Labels:
  LocalVariableTable: 
   Start  Length  Slot  Name   Signature
   0      13      0    this       Lscala/io/BytePickle$$anon$5;
   0      13      1    state       Lscala/io/BytePickle$UnPicklerState;

  Signature: length = 0x2
   00 33 

public scala.io.BytePickle$$anon$5(java.lang.Object);
  Signature: (Ljava/lang/Object;)V
  Code:
   Stack=2, Locals=2, Args_size=2
	aload_0
	aload_1
	putfield	Field x$5:Ljava/lang/Object;
	aload_0
	invokespecial	Method scala/io/BytePickle$SPU."<init>":()V
	return
  Labels:

}

