Compiled from "BytePickle.scala"
public final class scala.io.BytePickle$$anonfun$list$2 extends scala.runtime.AbstractFunction1 implements java.io.Serializable
  SourceFile: "BytePickle.scala"
  Scala: length = 0x
   
  InnerClass: 
   public abstract SPU=class scala/io/BytePickle$SPU of class scala/io/BytePickle
   public final $anonfun$list$2=class scala/io/BytePickle$$anonfun$list$2 of class scala/io/BytePickle
  minor version: 0
  major version: 49
  Constant pool:
Asciz	SourceFile;
Asciz	BytePickle.scala;
Asciz	<clinit>;
Asciz	()V;
Asciz	Code;
Asciz	serialVersionUID;
Asciz	J;
Asciz	scala/io/BytePickle$$anonfun$list$2;
class	scala/io/BytePickle$$anonfun$list$2
NameAndType	serialVersionUID:J
Field	scala/io/BytePickle$$anonfun$list$2.serialVersionUID:J
Asciz	pa$4;
Asciz	Lscala/io/BytePickle$SPU;;
Asciz	<init>;
Asciz	(Lscala/io/BytePickle$SPU;)V;
Asciz	LineNumberTable;
NameAndType	pa$4:Lscala/io/BytePickle$SPU;
Field	scala/io/BytePickle$$anonfun$list$2.pa$4:Lscala/io/BytePickle$SPU;
Asciz	scala/runtime/AbstractFunction1;
class	scala/runtime/AbstractFunction1
NameAndType	"<init>":()V
Method	scala/runtime/AbstractFunction1."<init>":()V
Asciz	apply;
Asciz	(Ljava/lang/Object;)Ljava/lang/Object;;
Asciz	scala/runtime/BoxesRunTime;
class	scala/runtime/BoxesRunTime
Asciz	unboxToInt;
Asciz	(Ljava/lang/Object;)I;
NameAndType	unboxToInt:(Ljava/lang/Object;)I
Method	scala/runtime/BoxesRunTime.unboxToInt:(Ljava/lang/Object;)I
Asciz	(I)Lscala/io/BytePickle$SPU;;
NameAndType	apply:(I)Lscala/io/BytePickle$SPU;
Method	scala/io/BytePickle$$anonfun$list$2.apply:(I)Lscala/io/BytePickle$SPU;
Asciz	this;
Asciz	Lscala/io/BytePickle$$anonfun$list$2;;
Asciz	v1;
Asciz	Ljava/lang/Object;;
Asciz	LocalVariableTable;
Asciz	scala/io/BytePickle$;
class	scala/io/BytePickle$
Asciz	MODULE$;
Asciz	Lscala/io/BytePickle$;;
NameAndType	MODULE$:Lscala/io/BytePickle$;
Field	scala/io/BytePickle$.MODULE$:Lscala/io/BytePickle$;
Asciz	fixedList;
Asciz	(Lscala/io/BytePickle$SPU;I)Lscala/io/BytePickle$SPU;;
NameAndType	fixedList:(Lscala/io/BytePickle$SPU;I)Lscala/io/BytePickle$SPU;
Method	scala/io/BytePickle$.fixedList:(Lscala/io/BytePickle$SPU;I)Lscala/io/BytePickle$SPU;
Asciz	(I)Lscala/io/BytePickle$SPU<Lscala/collection/immutable/List<Ta;>;>;;
Asciz	Signature;
Asciz	Scala;
Asciz	InnerClasses;
Asciz	scala/io/BytePickle$SPU;
class	scala/io/BytePickle$SPU
Asciz	scala/io/BytePickle;
class	scala/io/BytePickle
Asciz	SPU;
Asciz	$anonfun$list$2;
Asciz	java/io/Serializable;
class	java/io/Serializable

{
public static final long serialVersionUID;
  Signature: J

private final scala.io.BytePickle$SPU pa$4;
  Signature: Lscala/io/BytePickle$SPU;

public static {};
  Signature: ()V
  Code:
   Stack=2, Locals=0, Args_size=0
	lconst_0
	putstatic	Field serialVersionUID:J
	return
  Labels:

public scala.io.BytePickle$$anonfun$list$2(scala.io.BytePickle$SPU);
  Signature: (Lscala/io/BytePickle$SPU;)V
  Code:
   Stack=2, Locals=2, Args_size=2
	aload_0
	aload_1
	putfield	Field pa$4:Lscala/io/BytePickle$SPU;
	aload_0
	invokespecial	Method scala/runtime/AbstractFunction1."<init>":()V
	return
  Labels:

public final java.lang.Object apply(java.lang.Object);
  Signature: (Ljava/lang/Object;)Ljava/lang/Object;
  Code:
   Stack=2, Locals=2, Args_size=2
	aload_0
	aload_1
	invokestatic	Method scala/runtime/BoxesRunTime.unboxToInt:(Ljava/lang/Object;)I
	invokevirtual	Method apply:(I)Lscala/io/BytePickle$SPU;
	areturn
  Labels:
  LocalVariableTable: 
   Start  Length  Slot  Name   Signature
   0      9      0    this       Lscala/io/BytePickle$$anonfun$list$2;
   0      9      1    v1       Ljava/lang/Object;


public final scala.io.BytePickle$SPU apply(int);
  Signature: (I)Lscala/io/BytePickle$SPU;
  Code:
   Stack=3, Locals=2, Args_size=2
	getstatic	Field scala/io/BytePickle$.MODULE$:Lscala/io/BytePickle$;
	aload_0
	getfield	Field pa$4:Lscala/io/BytePickle$SPU;
	iload_1
	invokevirtual	Method scala/io/BytePickle$.fixedList:(Lscala/io/BytePickle$SPU;I)Lscala/io/BytePickle$SPU;
	areturn
  Labels:
  Signature: length = 0x2
   00 31 

}

