Compiled from "BytePickle.scala"
public final class scala.io.BytePickle$$anon$3 extends scala.io.BytePickle$SPU
  SourceFile: "BytePickle.scala"
  Signature: length = 0x2
   01 06 
  Scala: length = 0x
   
  InnerClass: 
   public abstract #267= #34 of #266; //PU=class scala/io/BytePickle$PU of class scala/io/BytePickle
   public #268= #84 of #266; //Ref=class scala/io/BytePickle$Ref of class scala/io/BytePickle
   public #269= #47 of #266; //Def=class scala/io/BytePickle$Def of class scala/io/BytePickle
   public abstract #270= #14 of #266; //SPU=class scala/io/BytePickle$SPU of class scala/io/BytePickle
   public abstract #271= #45 of #266; //RefDef=class scala/io/BytePickle$RefDef of class scala/io/BytePickle
   public final #272= #86 of #266; //$anon$2=class scala/io/BytePickle$$anon$2 of class scala/io/BytePickle
   public final #273= #27 of #266; //$anon$1=class scala/io/BytePickle$$anon$1 of class scala/io/BytePickle
   public final #274= #10 of #266; //$anon$3=class scala/io/BytePickle$$anon$3 of class scala/io/BytePickle
   public #275= #149 of #266; //PicklerEnv=class scala/io/BytePickle$PicklerEnv of class scala/io/BytePickle
   public final #278= #237 of #277; //$anonfun$concat$2=class scala/Array$$anonfun$concat$2 of class scala/Array
   public final #279= #203 of #277; //$anonfun$concat$1=class scala/Array$$anonfun$concat$1 of class scala/Array
   public #280= #144 of #266; //PicklerState=class scala/io/BytePickle$PicklerState of class scala/io/BytePickle
   public #281= #49 of #266; //UnPicklerEnv=class scala/io/BytePickle$UnPicklerEnv of class scala/io/BytePickle
   public #282= #21 of #266; //UnPicklerState=class scala/io/BytePickle$UnPicklerState of class scala/io/BytePickle
   public #285= #211 of #284; //GenericCanBuildFrom=class scala/collection/generic/TraversableFactory$GenericCanBuildFrom of class scala/collection/generic/TraversableFactory
  minor version: 0
  major version: 49
  Constant pool:
const #1 = Asciz	SourceFile;
const #2 = Asciz	BytePickle.scala;
const #3 = Asciz	pa$1;
const #4 = Asciz	Lscala/io/BytePickle$SPU;;
const #5 = Asciz	<init>;
const #6 = Asciz	(Lscala/io/BytePickle$SPU;)V;
const #7 = Asciz	Code;
const #8 = Asciz	LineNumberTable;
const #9 = Asciz	scala/io/BytePickle$$anon$3;
const #10 = class	#9;	//  scala/io/BytePickle$$anon$3
const #11 = NameAndType	#3:#4;//  pa$1:Lscala/io/BytePickle$SPU;
const #12 = Field	#10.#11;	//  scala/io/BytePickle$$anon$3.pa$1:Lscala/io/BytePickle$SPU;
const #13 = Asciz	scala/io/BytePickle$SPU;
const #14 = class	#13;	//  scala/io/BytePickle$SPU
const #15 = Asciz	()V;
const #16 = NameAndType	#5:#15;//  "<init>":()V
const #17 = Method	#14.#16;	//  scala/io/BytePickle$SPU."<init>":()V
const #18 = Asciz	appU;
const #19 = Asciz	(Lscala/io/BytePickle$UnPicklerState;)Lscala/Tuple2;;
const #20 = Asciz	scala/io/BytePickle$UnPicklerState;
const #21 = class	#20;	//  scala/io/BytePickle$UnPicklerState
const #22 = Asciz	dict;
const #23 = Asciz	()Lscala/io/BytePickle$UnPicklerEnv;;
const #24 = NameAndType	#22:#23;//  dict:()Lscala/io/BytePickle$UnPicklerEnv;
const #25 = Method	#21.#24;	//  scala/io/BytePickle$UnPicklerState.dict:()Lscala/io/BytePickle$UnPicklerEnv;
const #26 = Asciz	scala/io/BytePickle$$anon$1;
const #27 = class	#26;	//  scala/io/BytePickle$$anon$1
const #28 = Method	#27.#16;	//  scala/io/BytePickle$$anon$1."<init>":()V
const #29 = Asciz	stream;
const #30 = Asciz	()[B;
const #31 = NameAndType	#29:#30;//  stream:()[B
const #32 = Method	#21.#31;	//  scala/io/BytePickle$UnPicklerState.stream:()[B
const #33 = Asciz	scala/io/BytePickle$PU;
const #34 = class	#33;	//  scala/io/BytePickle$PU
const #35 = Asciz	([B)Lscala/Tuple2;;
const #36 = NameAndType	#18:#35;//  appU:([B)Lscala/Tuple2;
const #37 = Method	#34.#36;	//  scala/io/BytePickle$PU.appU:([B)Lscala/Tuple2;
const #38 = Asciz	scala/Tuple2;
const #39 = class	#38;	//  scala/Tuple2
const #40 = Asciz	_1;
const #41 = Asciz	()Ljava/lang/Object;;
const #42 = NameAndType	#40:#41;//  _1:()Ljava/lang/Object;
const #43 = Method	#39.#42;	//  scala/Tuple2._1:()Ljava/lang/Object;
const #44 = Asciz	scala/io/BytePickle$RefDef;
const #45 = class	#44;	//  scala/io/BytePickle$RefDef
const #46 = Asciz	scala/io/BytePickle$Def;
const #47 = class	#46;	//  scala/io/BytePickle$Def
const #48 = Asciz	scala/io/BytePickle$UnPicklerEnv;
const #49 = class	#48;	//  scala/io/BytePickle$UnPicklerEnv
const #50 = Asciz	nextLoc;
const #51 = Asciz	()I;
const #52 = NameAndType	#50:#51;//  nextLoc:()I
const #53 = Method	#49.#52;	//  scala/io/BytePickle$UnPicklerEnv.nextLoc:()I
const #54 = Asciz	_2;
const #55 = NameAndType	#54:#41;//  _2:()Ljava/lang/Object;
const #56 = Method	#39.#55;	//  scala/Tuple2._2:()Ljava/lang/Object;
const #57 = Asciz	[B;
const #58 = class	#57;	//  "[B"
const #59 = Asciz	([BLscala/io/BytePickle$UnPicklerEnv;)V;
const #60 = NameAndType	#5:#59;//  "<init>":([BLscala/io/BytePickle$UnPicklerEnv;)V
const #61 = Method	#21.#60;	//  scala/io/BytePickle$UnPicklerState."<init>":([BLscala/io/BytePickle$UnPicklerEnv;)V
const #62 = NameAndType	#18:#19;//  appU:(Lscala/io/BytePickle$UnPicklerState;)Lscala/Tuple2;
const #63 = Method	#14.#62;	//  scala/io/BytePickle$SPU.appU:(Lscala/io/BytePickle$UnPicklerState;)Lscala/Tuple2;
const #64 = Asciz	scala/runtime/BoxesRunTime;
const #65 = class	#64;	//  scala/runtime/BoxesRunTime
const #66 = Asciz	boxToInteger;
const #67 = Asciz	(I)Ljava/lang/Integer;;
const #68 = NameAndType	#66:#67;//  boxToInteger:(I)Ljava/lang/Integer;
const #69 = Method	#65.#68;	//  scala/runtime/BoxesRunTime.boxToInteger:(I)Ljava/lang/Integer;
const #70 = Asciz	update;
const #71 = Asciz	(Ljava/lang/Object;Ljava/lang/Object;)V;
const #72 = NameAndType	#70:#71;//  update:(Ljava/lang/Object;Ljava/lang/Object;)V
const #73 = Method	#49.#72;	//  scala/io/BytePickle$UnPicklerEnv.update:(Ljava/lang/Object;Ljava/lang/Object;)V
const #74 = Asciz	scala/MatchError;
const #75 = class	#74;	//  scala/MatchError
const #76 = Asciz	toString;
const #77 = Asciz	()Ljava/lang/String;;
const #78 = NameAndType	#76:#77;//  toString:()Ljava/lang/String;
const #79 = Method	#45.#78;	//  scala/io/BytePickle$RefDef.toString:()Ljava/lang/String;
const #80 = Asciz	(Ljava/lang/String;)V;
const #81 = NameAndType	#5:#80;//  "<init>":(Ljava/lang/String;)V
const #82 = Method	#75.#81;	//  scala/MatchError."<init>":(Ljava/lang/String;)V
const #83 = Asciz	scala/io/BytePickle$Ref;
const #84 = class	#83;	//  scala/io/BytePickle$Ref
const #85 = Asciz	scala/io/BytePickle$$anon$2;
const #86 = class	#85;	//  scala/io/BytePickle$$anon$2
const #87 = Method	#86.#16;	//  scala/io/BytePickle$$anon$2."<init>":()V
const #88 = Asciz	get;
const #89 = Asciz	(Ljava/lang/Object;)Lscala/Option;;
const #90 = NameAndType	#88:#89;//  get:(Ljava/lang/Object;)Lscala/Option;
const #91 = Method	#49.#90;	//  scala/io/BytePickle$UnPicklerEnv.get:(Ljava/lang/Object;)Lscala/Option;
const #92 = Asciz	scala/None$;
const #93 = class	#92;	//  scala/None$
const #94 = Asciz	MODULE$;
const #95 = Asciz	Lscala/None$;;
const #96 = NameAndType	#94:#95;//  MODULE$:Lscala/None$;
const #97 = Field	#93.#96;	//  scala/None$.MODULE$:Lscala/None$;
const #98 = Asciz	java/lang/Object;
const #99 = class	#98;	//  java/lang/Object
const #100 = Asciz	equals;
const #101 = Asciz	(Ljava/lang/Object;)Z;
const #102 = NameAndType	#100:#101;//  equals:(Ljava/lang/Object;)Z
const #103 = Method	#99.#102;	//  java/lang/Object.equals:(Ljava/lang/Object;)Z
const #104 = Asciz	java/lang/IllegalArgumentException;
const #105 = class	#104;	//  java/lang/IllegalArgumentException
const #106 = Asciz	invalid unpickler environment;
const #107 = String	#106;	//  invalid unpickler environment
const #108 = Method	#105.#81;	//  java/lang/IllegalArgumentException."<init>":(Ljava/lang/String;)V
const #109 = Asciz	scala/Option;
const #110 = class	#109;	//  scala/Option
const #111 = Method	#110.#78;	//  scala/Option.toString:()Ljava/lang/String;
const #112 = Asciz	scala/Some;
const #113 = class	#112;	//  scala/Some
const #114 = Asciz	x;
const #115 = Asciz	Ljava/lang/Object;;
const #116 = NameAndType	#114:#115;//  x:Ljava/lang/Object;
const #117 = Field	#113.#116;	//  scala/Some.x:Ljava/lang/Object;
const #118 = NameAndType	#5:#71;//  "<init>":(Ljava/lang/Object;Ljava/lang/Object;)V
const #119 = Method	#39.#118;	//  scala/Tuple2."<init>":(Ljava/lang/Object;Ljava/lang/Object;)V
const #120 = Asciz	this;
const #121 = Asciz	Lscala/io/BytePickle$$anon$3;;
const #122 = Asciz	state;
const #123 = Asciz	Lscala/io/BytePickle$UnPicklerState;;
const #124 = Asciz	l;
const #125 = Asciz	I;
const #126 = Asciz	res2;
const #127 = Asciz	Lscala/Tuple2;;
const #128 = Asciz	res;
const #129 = Asciz	temp16;
const #130 = Asciz	Lscala/Some;;
const #131 = Asciz	temp17;
const #132 = Asciz	upe;
const #133 = Asciz	Lscala/io/BytePickle$UnPicklerEnv;;
const #134 = Asciz	temp14;
const #135 = Asciz	Lscala/Option;;
const #136 = Asciz	temp18;
const #137 = Asciz	Lscala/io/BytePickle$RefDef;;
const #138 = Asciz	LocalVariableTable;
const #139 = Asciz	(Lscala/io/BytePickle$UnPicklerState;)Lscala/Tuple2<Ta;Lscala/io/BytePickle$UnPicklerState;>;;
const #140 = Asciz	Signature;
const #141 = Asciz	appP;
const #142 = Asciz	(Ljava/lang/Object;Lscala/io/BytePickle$PicklerState;)Lscala/io/BytePickle$PicklerState;;
const #143 = Asciz	scala/io/BytePickle$PicklerState;
const #144 = class	#143;	//  scala/io/BytePickle$PicklerState
const #145 = Asciz	()Lscala/io/BytePickle$PicklerEnv;;
const #146 = NameAndType	#22:#145;//  dict:()Lscala/io/BytePickle$PicklerEnv;
const #147 = Method	#144.#146;	//  scala/io/BytePickle$PicklerState.dict:()Lscala/io/BytePickle$PicklerEnv;
const #148 = Asciz	scala/io/BytePickle$PicklerEnv;
const #149 = class	#148;	//  scala/io/BytePickle$PicklerEnv
const #150 = Method	#149.#90;	//  scala/io/BytePickle$PicklerEnv.get:(Ljava/lang/Object;)Lscala/Option;
const #151 = Method	#47.#16;	//  scala/io/BytePickle$Def."<init>":()V
const #152 = Method	#144.#31;	//  scala/io/BytePickle$PicklerState.stream:()[B
const #153 = Asciz	(Lscala/io/BytePickle$RefDef;[B)[B;
const #154 = NameAndType	#141:#153;//  appP:(Lscala/io/BytePickle$RefDef;[B)[B
const #155 = Method	#27.#154;	//  scala/io/BytePickle$$anon$1.appP:(Lscala/io/BytePickle$RefDef;[B)[B
const #156 = Method	#149.#52;	//  scala/io/BytePickle$PicklerEnv.nextLoc:()I
const #157 = Asciz	([BLscala/io/BytePickle$PicklerEnv;)V;
const #158 = NameAndType	#5:#157;//  "<init>":([BLscala/io/BytePickle$PicklerEnv;)V
const #159 = Method	#144.#158;	//  scala/io/BytePickle$PicklerState."<init>":([BLscala/io/BytePickle$PicklerEnv;)V
const #160 = NameAndType	#141:#142;//  appP:(Ljava/lang/Object;Lscala/io/BytePickle$PicklerState;)Lscala/io/BytePickle$PicklerState;
const #161 = Method	#14.#160;	//  scala/io/BytePickle$SPU.appP:(Ljava/lang/Object;Lscala/io/BytePickle$PicklerState;)Lscala/io/BytePickle$PicklerState;
const #162 = Method	#149.#72;	//  scala/io/BytePickle$PicklerEnv.update:(Ljava/lang/Object;Ljava/lang/Object;)V
const #163 = Asciz	unboxToInt;
const #164 = Asciz	(Ljava/lang/Object;)I;
const #165 = NameAndType	#163:#164;//  unboxToInt:(Ljava/lang/Object;)I
const #166 = Method	#65.#165;	//  scala/runtime/BoxesRunTime.unboxToInt:(Ljava/lang/Object;)I
const #167 = Method	#84.#16;	//  scala/io/BytePickle$Ref."<init>":()V
const #168 = Asciz	scala/Predef$;
const #169 = class	#168;	//  scala/Predef$
const #170 = Asciz	Lscala/Predef$;;
const #171 = NameAndType	#94:#170;//  MODULE$:Lscala/Predef$;
const #172 = Field	#169.#171;	//  scala/Predef$.MODULE$:Lscala/Predef$;
const #173 = Asciz	scala/io/BytePickle$;
const #174 = class	#173;	//  scala/io/BytePickle$
const #175 = Asciz	Lscala/io/BytePickle$;;
const #176 = NameAndType	#94:#175;//  MODULE$:Lscala/io/BytePickle$;
const #177 = Field	#174.#176;	//  scala/io/BytePickle$.MODULE$:Lscala/io/BytePickle$;
const #178 = Asciz	nat2Bytes;
const #179 = Asciz	(I)[B;
const #180 = NameAndType	#178:#179;//  nat2Bytes:(I)[B
const #181 = Method	#174.#180;	//  scala/io/BytePickle$.nat2Bytes:(I)[B
const #182 = Asciz	[Ljava/lang/Object;;
const #183 = class	#182;	//  "[Ljava/lang/Object;"
const #184 = Asciz	wrapRefArray;
const #185 = Asciz	([Ljava/lang/Object;)Lscala/collection/mutable/WrappedArray;;
const #186 = NameAndType	#184:#185;//  wrapRefArray:([Ljava/lang/Object;)Lscala/collection/mutable/WrappedArray;
const #187 = Method	#169.#186;	//  scala/Predef$.wrapRefArray:([Ljava/lang/Object;)Lscala/collection/mutable/WrappedArray;
const #188 = Asciz	scala/reflect/Manifest$;
const #189 = class	#188;	//  scala/reflect/Manifest$
const #190 = Asciz	Lscala/reflect/Manifest$;;
const #191 = NameAndType	#94:#190;//  MODULE$:Lscala/reflect/Manifest$;
const #192 = Field	#189.#191;	//  scala/reflect/Manifest$.MODULE$:Lscala/reflect/Manifest$;
const #193 = Asciz	Byte;
const #194 = NameAndType	#193:#41;//  Byte:()Ljava/lang/Object;
const #195 = Method	#189.#194;	//  scala/reflect/Manifest$.Byte:()Ljava/lang/Object;
const #196 = Asciz	scala/reflect/ClassManifest;
const #197 = class	#196;	//  scala/reflect/ClassManifest
const #198 = Asciz	newArrayBuilder;
const #199 = Asciz	()Lscala/collection/mutable/ArrayBuilder;;
const #200 = NameAndType	#198:#199;//  newArrayBuilder:()Lscala/collection/mutable/ArrayBuilder;
const #201 = InterfaceMethod	#197.#200;	//  scala/reflect/ClassManifest.newArrayBuilder:()Lscala/collection/mutable/ArrayBuilder;
const #202 = Asciz	scala/Array$$anonfun$concat$1;
const #203 = class	#202;	//  scala/Array$$anonfun$concat$1
const #204 = Method	#203.#16;	//  scala/Array$$anonfun$concat$1."<init>":()V
const #205 = Asciz	scala/collection/Seq$;
const #206 = class	#205;	//  scala/collection/Seq$
const #207 = Asciz	Lscala/collection/Seq$;;
const #208 = NameAndType	#94:#207;//  MODULE$:Lscala/collection/Seq$;
const #209 = Field	#206.#208;	//  scala/collection/Seq$.MODULE$:Lscala/collection/Seq$;
const #210 = Asciz	scala/collection/generic/TraversableFactory$GenericCanBuildFrom;
const #211 = class	#210;	//  scala/collection/generic/TraversableFactory$GenericCanBuildFrom
const #212 = Asciz	(Lscala/collection/generic/TraversableFactory;)V;
const #213 = NameAndType	#5:#212;//  "<init>":(Lscala/collection/generic/TraversableFactory;)V
const #214 = Method	#211.#213;	//  scala/collection/generic/TraversableFactory$GenericCanBuildFrom."<init>":(Lscala/collection/generic/TraversableFactory;)V
const #215 = Asciz	scala/collection/TraversableLike;
const #216 = class	#215;	//  scala/collection/TraversableLike
const #217 = Asciz	map;
const #218 = Asciz	(Lscala/Function1;Lscala/collection/generic/CanBuildFrom;)Ljava/lang/Object;;
const #219 = NameAndType	#217:#218;//  map:(Lscala/Function1;Lscala/collection/generic/CanBuildFrom;)Ljava/lang/Object;
const #220 = InterfaceMethod	#216.#219;	//  scala/collection/TraversableLike.map:(Lscala/Function1;Lscala/collection/generic/CanBuildFrom;)Ljava/lang/Object;
const #221 = Asciz	scala/math/Numeric$IntIsIntegral$;
const #222 = class	#221;	//  scala/math/Numeric$IntIsIntegral$
const #223 = Asciz	Lscala/math/Numeric$IntIsIntegral$;;
const #224 = NameAndType	#94:#223;//  MODULE$:Lscala/math/Numeric$IntIsIntegral$;
const #225 = Field	#222.#224;	//  scala/math/Numeric$IntIsIntegral$.MODULE$:Lscala/math/Numeric$IntIsIntegral$;
const #226 = Asciz	sum;
const #227 = Asciz	(Lscala/math/Numeric;)Ljava/lang/Object;;
const #228 = NameAndType	#226:#227;//  sum:(Lscala/math/Numeric;)Ljava/lang/Object;
const #229 = InterfaceMethod	#216.#228;	//  scala/collection/TraversableLike.sum:(Lscala/math/Numeric;)Ljava/lang/Object;
const #230 = Asciz	scala/collection/mutable/Builder;
const #231 = class	#230;	//  scala/collection/mutable/Builder
const #232 = Asciz	sizeHint;
const #233 = Asciz	(I)V;
const #234 = NameAndType	#232:#233;//  sizeHint:(I)V
const #235 = InterfaceMethod	#231.#234;	//  scala/collection/mutable/Builder.sizeHint:(I)V
const #236 = Asciz	scala/Array$$anonfun$concat$2;
const #237 = class	#236;	//  scala/Array$$anonfun$concat$2
const #238 = Asciz	(Lscala/collection/mutable/ArrayBuilder;)V;
const #239 = NameAndType	#5:#238;//  "<init>":(Lscala/collection/mutable/ArrayBuilder;)V
const #240 = Method	#237.#239;	//  scala/Array$$anonfun$concat$2."<init>":(Lscala/collection/mutable/ArrayBuilder;)V
const #241 = Asciz	scala/collection/IterableLike;
const #242 = class	#241;	//  scala/collection/IterableLike
const #243 = Asciz	foreach;
const #244 = Asciz	(Lscala/Function1;)V;
const #245 = NameAndType	#243:#244;//  foreach:(Lscala/Function1;)V
const #246 = InterfaceMethod	#242.#245;	//  scala/collection/IterableLike.foreach:(Lscala/Function1;)V
const #247 = Asciz	result;
const #248 = NameAndType	#247:#41;//  result:()Ljava/lang/Object;
const #249 = InterfaceMethod	#231.#248;	//  scala/collection/mutable/Builder.result:()Ljava/lang/Object;
const #250 = Asciz	v;
const #251 = Asciz	Lscala/io/BytePickle$PicklerState;;
const #252 = Asciz	sPrime;
const #253 = Asciz	sPrimePrime;
const #254 = Asciz	temp12;
const #255 = Asciz	temp13;
const #256 = Asciz	b$10;
const #257 = Asciz	Lscala/collection/mutable/ArrayBuilder;;
const #258 = Asciz	pe;
const #259 = Asciz	Lscala/io/BytePickle$PicklerEnv;;
const #260 = Asciz	temp10;
const #261 = Asciz	(Ta;Lscala/io/BytePickle$PicklerState;)Lscala/io/BytePickle$PicklerState;;
const #262 = Asciz	Lscala/io/BytePickle$SPU<Ta;>;;
const #263 = Asciz	Scala;
const #264 = Asciz	InnerClasses;
const #265 = Asciz	scala/io/BytePickle;
const #266 = class	#265;	//  scala/io/BytePickle
const #267 = Asciz	PU;
const #268 = Asciz	Ref;
const #269 = Asciz	Def;
const #270 = Asciz	SPU;
const #271 = Asciz	RefDef;
const #272 = Asciz	$anon$2;
const #273 = Asciz	$anon$1;
const #274 = Asciz	$anon$3;
const #275 = Asciz	PicklerEnv;
const #276 = Asciz	scala/Array;
const #277 = class	#276;	//  scala/Array
const #278 = Asciz	$anonfun$concat$2;
const #279 = Asciz	$anonfun$concat$1;
const #280 = Asciz	PicklerState;
const #281 = Asciz	UnPicklerEnv;
const #282 = Asciz	UnPicklerState;
const #283 = Asciz	scala/collection/generic/TraversableFactory;
const #284 = class	#283;	//  scala/collection/generic/TraversableFactory
const #285 = Asciz	GenericCanBuildFrom;

{
public scala.io.BytePickle$$anon$3(scala.io.BytePickle$SPU);
  Code:
   Stack=2, Locals=2, Args_size=2
   0:	aload_0
   1:	aload_1
   2:	putfield	#12; //Field pa$1:Lscala/io/BytePickle$SPU;
   5:	aload_0
   6:	invokespecial	#17; //Method scala/io/BytePickle$SPU."<init>":()V
   9:	return
  LineNumberTable: 
   line 98: 0


public scala.Tuple2 appU(scala.io.BytePickle$UnPicklerState);
  Code:
   Stack=7, Locals=11, Args_size=2
   0:	aload_1
   1:	invokevirtual	#25; //Method scala/io/BytePickle$UnPicklerState.dict:()Lscala/io/BytePickle$UnPicklerEnv;
   4:	astore	8
   6:	new	#27; //class scala/io/BytePickle$$anon$1
   9:	dup
   10:	invokespecial	#28; //Method scala/io/BytePickle$$anon$1."<init>":()V
   13:	aload_1
   14:	invokevirtual	#32; //Method scala/io/BytePickle$UnPicklerState.stream:()[B
   17:	invokevirtual	#37; //Method scala/io/BytePickle$PU.appU:([B)Lscala/Tuple2;
   20:	astore	4
   22:	aload	4
   24:	invokevirtual	#43; //Method scala/Tuple2._1:()Ljava/lang/Object;
   27:	checkcast	#45; //class scala/io/BytePickle$RefDef
   30:	astore	10
   32:	aload	10
   34:	instanceof	#47; //class scala/io/BytePickle$Def
   37:	ifeq	103
   40:	iconst_1
   41:	ifeq	90
   44:	aload	8
   46:	invokevirtual	#53; //Method scala/io/BytePickle$UnPicklerEnv.nextLoc:()I
   49:	istore_2
   50:	aload_0
   51:	getfield	#12; //Field pa$1:Lscala/io/BytePickle$SPU;
   54:	new	#21; //class scala/io/BytePickle$UnPicklerState
   57:	dup
   58:	aload	4
   60:	invokevirtual	#56; //Method scala/Tuple2._2:()Ljava/lang/Object;
   63:	checkcast	#58; //class "[B"
   66:	aload	8
   68:	invokespecial	#61; //Method scala/io/BytePickle$UnPicklerState."<init>":([BLscala/io/BytePickle$UnPicklerEnv;)V
   71:	invokevirtual	#63; //Method scala/io/BytePickle$SPU.appU:(Lscala/io/BytePickle$UnPicklerState;)Lscala/Tuple2;
   74:	astore_3
   75:	aload	8
   77:	iload_2
   78:	invokestatic	#69; //Method scala/runtime/BoxesRunTime.boxToInteger:(I)Ljava/lang/Integer;
   81:	aload_3
   82:	invokevirtual	#43; //Method scala/Tuple2._1:()Ljava/lang/Object;
   85:	invokevirtual	#73; //Method scala/io/BytePickle$UnPicklerEnv.update:(Ljava/lang/Object;Ljava/lang/Object;)V
   88:	aload_3
   89:	areturn
   90:	new	#75; //class scala/MatchError
   93:	dup
   94:	aload	10
   96:	invokevirtual	#79; //Method scala/io/BytePickle$RefDef.toString:()Ljava/lang/String;
   99:	invokespecial	#82; //Method scala/MatchError."<init>":(Ljava/lang/String;)V
   102:	athrow
   103:	aload	10
   105:	instanceof	#84; //class scala/io/BytePickle$Ref
   108:	ifeq	290
   111:	iconst_1
   112:	ifeq	277
   115:	new	#86; //class scala/io/BytePickle$$anon$2
   118:	dup
   119:	invokespecial	#87; //Method scala/io/BytePickle$$anon$2."<init>":()V
   122:	aload	4
   124:	invokevirtual	#56; //Method scala/Tuple2._2:()Ljava/lang/Object;
   127:	checkcast	#58; //class "[B"
   130:	invokevirtual	#37; //Method scala/io/BytePickle$PU.appU:([B)Lscala/Tuple2;
   133:	astore	7
   135:	aload	8
   137:	aload	7
   139:	invokevirtual	#43; //Method scala/Tuple2._1:()Ljava/lang/Object;
   142:	invokevirtual	#91; //Method scala/io/BytePickle$UnPicklerEnv.get:(Ljava/lang/Object;)Lscala/Option;
   145:	astore	9
   147:	getstatic	#97; //Field scala/None$.MODULE$:Lscala/None$;
   150:	dup
   151:	ifnonnull	163
   154:	pop
   155:	aload	9
   157:	ifnull	171
   160:	goto	198
   163:	aload	9
   165:	invokevirtual	#103; //Method java/lang/Object.equals:(Ljava/lang/Object;)Z
   168:	ifeq	198
   171:	iconst_1
   172:	ifeq	185
   175:	new	#105; //class java/lang/IllegalArgumentException
   178:	dup
   179:	ldc	#107; //String invalid unpickler environment
   181:	invokespecial	#108; //Method java/lang/IllegalArgumentException."<init>":(Ljava/lang/String;)V
   184:	athrow
   185:	new	#75; //class scala/MatchError
   188:	dup
   189:	aload	9
   191:	invokevirtual	#111; //Method scala/Option.toString:()Ljava/lang/String;
   194:	invokespecial	#82; //Method scala/MatchError."<init>":(Ljava/lang/String;)V
   197:	athrow
   198:	aload	9
   200:	instanceof	#113; //class scala/Some
   203:	ifeq	264
   206:	aload	9
   208:	checkcast	#113; //class scala/Some
   211:	astore	5
   213:	aload	5
   215:	getfield	#117; //Field scala/Some.x:Ljava/lang/Object;
   218:	astore	6
   220:	iconst_1
   221:	ifeq	251
   224:	new	#39; //class scala/Tuple2
   227:	dup
   228:	aload	6
   230:	new	#21; //class scala/io/BytePickle$UnPicklerState
   233:	dup
   234:	aload	7
   236:	invokevirtual	#56; //Method scala/Tuple2._2:()Ljava/lang/Object;
   239:	checkcast	#58; //class "[B"
   242:	aload	8
   244:	invokespecial	#61; //Method scala/io/BytePickle$UnPicklerState."<init>":([BLscala/io/BytePickle$UnPicklerEnv;)V
   247:	invokespecial	#119; //Method scala/Tuple2."<init>":(Ljava/lang/Object;Ljava/lang/Object;)V
   250:	areturn
   251:	new	#75; //class scala/MatchError
   254:	dup
   255:	aload	9
   257:	invokevirtual	#111; //Method scala/Option.toString:()Ljava/lang/String;
   260:	invokespecial	#82; //Method scala/MatchError."<init>":(Ljava/lang/String;)V
   263:	athrow
   264:	new	#75; //class scala/MatchError
   267:	dup
   268:	aload	9
   270:	invokevirtual	#111; //Method scala/Option.toString:()Ljava/lang/String;
   273:	invokespecial	#82; //Method scala/MatchError."<init>":(Ljava/lang/String;)V
   276:	athrow
   277:	new	#75; //class scala/MatchError
   280:	dup
   281:	aload	10
   283:	invokevirtual	#79; //Method scala/io/BytePickle$RefDef.toString:()Ljava/lang/String;
   286:	invokespecial	#82; //Method scala/MatchError."<init>":(Ljava/lang/String;)V
   289:	athrow
   290:	new	#75; //class scala/MatchError
   293:	dup
   294:	aload	10
   296:	invokevirtual	#79; //Method scala/io/BytePickle$RefDef.toString:()Ljava/lang/String;
   299:	invokespecial	#82; //Method scala/MatchError."<init>":(Ljava/lang/String;)V
   302:	athrow
  LineNumberTable: 
   line 137: 0
   line 138: 6
   line 139: 22
   line 21: 40
   line 141: 44
   line 142: 50
   line 143: 75
   line 144: 88
   line 139: 90
   line 21: 111
   line 146: 115
   line 147: 135
   line 21: 171
   line 148: 175
   line 147: 185
   line 126: 206
   line 21: 220
   line 149: 224
   line 147: 251
   line 139: 277

  LocalVariableTable: 
   Start  Length  Slot  Name   Signature
   0      303      0    this       Lscala/io/BytePickle$$anon$3;
   0      303      1    state       Lscala/io/BytePickle$UnPicklerState;
   50      40      2    l       I
   75      15      3    res2       Lscala/Tuple2;
   22      281      4    res       Lscala/Tuple2;
   213      51      5    temp16       Lscala/Some;
   220      44      6    temp17       Ljava/lang/Object;
   135      142      7    res2       Lscala/Tuple2;
   6      297      8    upe       Lscala/io/BytePickle$UnPicklerEnv;
   147      130      9    temp14       Lscala/Option;
   32      271      10    temp18       Lscala/io/BytePickle$RefDef;

  Signature: length = 0x2
   00 FFFFFF8B 

public scala.io.BytePickle$PicklerState appP(java.lang.Object, scala.io.BytePickle$PicklerState);
  Code:
   Stack=8, Locals=22, Args_size=3
   0:	aload_2
   1:	invokevirtual	#147; //Method scala/io/BytePickle$PicklerState.dict:()Lscala/io/BytePickle$PicklerEnv;
   4:	astore	20
   6:	aload	20
   8:	aload_1
   9:	invokevirtual	#150; //Method scala/io/BytePickle$PicklerEnv.get:(Ljava/lang/Object;)Lscala/Option;
   12:	astore	21
   14:	getstatic	#97; //Field scala/None$.MODULE$:Lscala/None$;
   17:	dup
   18:	ifnonnull	30
   21:	pop
   22:	aload	21
   24:	ifnull	38
   27:	goto	133
   30:	aload	21
   32:	invokevirtual	#103; //Method java/lang/Object.equals:(Ljava/lang/Object;)Z
   35:	ifeq	133
   38:	iconst_1
   39:	ifeq	120
   42:	new	#27; //class scala/io/BytePickle$$anon$1
   45:	dup
   46:	invokespecial	#28; //Method scala/io/BytePickle$$anon$1."<init>":()V
   49:	new	#47; //class scala/io/BytePickle$Def
   52:	dup
   53:	invokespecial	#151; //Method scala/io/BytePickle$Def."<init>":()V
   56:	aload_2
   57:	invokevirtual	#152; //Method scala/io/BytePickle$PicklerState.stream:()[B
   60:	astore	5
   62:	astore	4
   64:	astore_3
   65:	aload_3
   66:	aload	4
   68:	checkcast	#45; //class scala/io/BytePickle$RefDef
   71:	aload	5
   73:	invokevirtual	#155; //Method scala/io/BytePickle$$anon$1.appP:(Lscala/io/BytePickle$RefDef;[B)[B
   76:	astore	6
   78:	aload	20
   80:	invokevirtual	#156; //Method scala/io/BytePickle$PicklerEnv.nextLoc:()I
   83:	istore	7
   85:	aload_0
   86:	getfield	#12; //Field pa$1:Lscala/io/BytePickle$SPU;
   89:	aload_1
   90:	new	#144; //class scala/io/BytePickle$PicklerState
   93:	dup
   94:	aload	6
   96:	aload	20
   98:	invokespecial	#159; //Method scala/io/BytePickle$PicklerState."<init>":([BLscala/io/BytePickle$PicklerEnv;)V
   101:	invokevirtual	#161; //Method scala/io/BytePickle$SPU.appP:(Ljava/lang/Object;Lscala/io/BytePickle$PicklerState;)Lscala/io/BytePickle$PicklerState;
   104:	astore	8
   106:	aload	20
   108:	aload_1
   109:	iload	7
   111:	invokestatic	#69; //Method scala/runtime/BoxesRunTime.boxToInteger:(I)Ljava/lang/Integer;
   114:	invokevirtual	#162; //Method scala/io/BytePickle$PicklerEnv.update:(Ljava/lang/Object;Ljava/lang/Object;)V
   117:	aload	8
   119:	areturn
   120:	new	#75; //class scala/MatchError
   123:	dup
   124:	aload	21
   126:	invokevirtual	#111; //Method scala/Option.toString:()Ljava/lang/String;
   129:	invokespecial	#82; //Method scala/MatchError."<init>":(Ljava/lang/String;)V
   132:	athrow
   133:	aload	21
   135:	instanceof	#113; //class scala/Some
   138:	ifeq	364
   141:	aload	21
   143:	checkcast	#113; //class scala/Some
   146:	astore	9
   148:	aload	9
   150:	getfield	#117; //Field scala/Some.x:Ljava/lang/Object;
   153:	invokestatic	#166; //Method scala/runtime/BoxesRunTime.unboxToInt:(Ljava/lang/Object;)I
   156:	istore	13
   158:	iconst_1
   159:	ifeq	351
   162:	new	#27; //class scala/io/BytePickle$$anon$1
   165:	dup
   166:	invokespecial	#28; //Method scala/io/BytePickle$$anon$1."<init>":()V
   169:	new	#84; //class scala/io/BytePickle$Ref
   172:	dup
   173:	invokespecial	#167; //Method scala/io/BytePickle$Ref."<init>":()V
   176:	aload_2
   177:	invokevirtual	#152; //Method scala/io/BytePickle$PicklerState.stream:()[B
   180:	astore	12
   182:	astore	11
   184:	astore	10
   186:	aload	10
   188:	aload	11
   190:	checkcast	#45; //class scala/io/BytePickle$RefDef
   193:	aload	12
   195:	invokevirtual	#155; //Method scala/io/BytePickle$$anon$1.appP:(Lscala/io/BytePickle$RefDef;[B)[B
   198:	astore	14
   200:	new	#144; //class scala/io/BytePickle$PicklerState
   203:	dup
   204:	new	#86; //class scala/io/BytePickle$$anon$2
   207:	dup
   208:	pop
   209:	invokespecial	#87; //Method scala/io/BytePickle$$anon$2."<init>":()V
   212:	iload	13
   214:	istore	15
   216:	getstatic	#172; //Field scala/Predef$.MODULE$:Lscala/Predef$;
   219:	iconst_2
   220:	anewarray	#58; //class "[B"
   223:	dup
   224:	iconst_0
   225:	aload	14
   227:	aastore
   228:	dup
   229:	iconst_1
   230:	getstatic	#177; //Field scala/io/BytePickle$.MODULE$:Lscala/io/BytePickle$;
   233:	iload	15
   235:	invokevirtual	#181; //Method scala/io/BytePickle$.nat2Bytes:(I)[B
   238:	aastore
   239:	checkcast	#183; //class "[Ljava/lang/Object;"
   242:	invokevirtual	#187; //Method scala/Predef$.wrapRefArray:([Ljava/lang/Object;)Lscala/collection/mutable/WrappedArray;
   245:	getstatic	#192; //Field scala/reflect/Manifest$.MODULE$:Lscala/reflect/Manifest$;
   248:	invokevirtual	#195; //Method scala/reflect/Manifest$.Byte:()Ljava/lang/Object;
   251:	checkcast	#197; //class scala/reflect/ClassManifest
   254:	astore	16
   256:	astore	18
   258:	aload	16
   260:	checkcast	#197; //class scala/reflect/ClassManifest
   263:	invokeinterface	#201,  1; //InterfaceMethod scala/reflect/ClassManifest.newArrayBuilder:()Lscala/collection/mutable/ArrayBuilder;
   268:	astore	19
   270:	aload	19
   272:	aload	18
   274:	new	#203; //class scala/Array$$anonfun$concat$1
   277:	dup
   278:	invokespecial	#204; //Method scala/Array$$anonfun$concat$1."<init>":()V
   281:	getstatic	#209; //Field scala/collection/Seq$.MODULE$:Lscala/collection/Seq$;
   284:	astore	17
   286:	new	#211; //class scala/collection/generic/TraversableFactory$GenericCanBuildFrom
   289:	dup
   290:	aload	17
   292:	invokespecial	#214; //Method scala/collection/generic/TraversableFactory$GenericCanBuildFrom."<init>":(Lscala/collection/generic/TraversableFactory;)V
   295:	invokeinterface	#220,  3; //InterfaceMethod scala/collection/TraversableLike.map:(Lscala/Function1;Lscala/collection/generic/CanBuildFrom;)Ljava/lang/Object;
   300:	checkcast	#216; //class scala/collection/TraversableLike
   303:	getstatic	#225; //Field scala/math/Numeric$IntIsIntegral$.MODULE$:Lscala/math/Numeric$IntIsIntegral$;
   306:	invokeinterface	#229,  2; //InterfaceMethod scala/collection/TraversableLike.sum:(Lscala/math/Numeric;)Ljava/lang/Object;
   311:	invokestatic	#166; //Method scala/runtime/BoxesRunTime.unboxToInt:(Ljava/lang/Object;)I
   314:	invokeinterface	#235,  2; //InterfaceMethod scala/collection/mutable/Builder.sizeHint:(I)V
   319:	aload	18
   321:	new	#237; //class scala/Array$$anonfun$concat$2
   324:	dup
   325:	aload	19
   327:	invokespecial	#240; //Method scala/Array$$anonfun$concat$2."<init>":(Lscala/collection/mutable/ArrayBuilder;)V
   330:	invokeinterface	#246,  2; //InterfaceMethod scala/collection/IterableLike.foreach:(Lscala/Function1;)V
   335:	aload	19
   337:	invokeinterface	#249,  1; //InterfaceMethod scala/collection/mutable/Builder.result:()Ljava/lang/Object;
   342:	checkcast	#58; //class "[B"
   345:	aload	20
   347:	invokespecial	#159; //Method scala/io/BytePickle$PicklerState."<init>":([BLscala/io/BytePickle$PicklerEnv;)V
   350:	areturn
   351:	new	#75; //class scala/MatchError
   354:	dup
   355:	aload	21
   357:	invokevirtual	#111; //Method scala/Option.toString:()Ljava/lang/String;
   360:	invokespecial	#82; //Method scala/MatchError."<init>":(Ljava/lang/String;)V
   363:	athrow
   364:	new	#75; //class scala/MatchError
   367:	dup
   368:	aload	21
   370:	invokevirtual	#111; //Method scala/Option.toString:()Ljava/lang/String;
   373:	invokespecial	#82; //Method scala/MatchError."<init>":(Ljava/lang/String;)V
   376:	athrow
  LineNumberTable: 
   line 109: 0
   line 110: 6
   line 21: 38
   line 112: 42
   line 113: 78
   line 115: 85
   line 117: 106
   line 119: 117
   line 110: 120
   line 99: 141
   line 21: 158
   line 121: 162
   line 123: 200
   line 110: 351

  LocalVariableTable: 
   Start  Length  Slot  Name   Signature
   0      377      0    this       Lscala/io/BytePickle$$anon$3;
   0      377      1    v       Ljava/lang/Object;
   0      377      2    state       Lscala/io/BytePickle$PicklerState;
   78      42      6    sPrime       [B
   85      35      7    l       I
   106      14      8    sPrimePrime       Lscala/io/BytePickle$PicklerState;
   148      216      9    temp12       Lscala/Some;
   158      206      13    temp13       I
   200      151      14    sPrime       [B
   270      72      19    b$10       Lscala/collection/mutable/ArrayBuilder;
   6      371      20    pe       Lscala/io/BytePickle$PicklerEnv;
   14      363      21    temp10       Lscala/Option;

  Signature: length = 0x2
   01 05 

}

