Compiled from "BytePickle.scala"
public final class scala.io.BytePickle$$anon$1 extends scala.io.BytePickle$PU
  SourceFile: "BytePickle.scala"
  Signature: length = 0x2
   00 FFFFFFB9 
  Scala: length = 0x
   
  InnerClass: 
   public abstract #190= #8 of #189; //PU=class scala/io/BytePickle$PU of class scala/io/BytePickle
   public #191= #49 of #189; //Def=class scala/io/BytePickle$Def of class scala/io/BytePickle
   public #192= #32 of #189; //Ref=class scala/io/BytePickle$Ref of class scala/io/BytePickle
   public #195= #35 of #194; //ofByte=class scala/collection/mutable/ArrayOps$ofByte of class scala/collection/mutable/ArrayOps
   public abstract #196= #14 of #189; //RefDef=class scala/io/BytePickle$RefDef of class scala/io/BytePickle
   public final #197= #16 of #189; //$anon$1=class scala/io/BytePickle$$anon$1 of class scala/io/BytePickle
   public final #200= #98 of #199; //$anonfun$apply$1=class scala/Array$$anonfun$apply$1 of class scala/Array
   public final #201= #158 of #199; //$anonfun$concat$2=class scala/Array$$anonfun$concat$2 of class scala/Array
   public final #202= #119 of #199; //$anonfun$concat$1=class scala/Array$$anonfun$concat$1 of class scala/Array
   public #205= #127 of #204; //GenericCanBuildFrom=class scala/collection/generic/TraversableFactory$GenericCanBuildFrom of class scala/collection/generic/TraversableFactory
  minor version: 0
  major version: 49
  Constant pool:
const #1 = Asciz	SourceFile;
const #2 = Asciz	BytePickle.scala;
const #3 = Asciz	<init>;
const #4 = Asciz	()V;
const #5 = Asciz	Code;
const #6 = Asciz	LineNumberTable;
const #7 = Asciz	scala/io/BytePickle$PU;
const #8 = class	#7;	//  scala/io/BytePickle$PU
const #9 = NameAndType	#3:#4;//  "<init>":()V
const #10 = Method	#8.#9;	//  scala/io/BytePickle$PU."<init>":()V
const #11 = Asciz	appP;
const #12 = Asciz	(Ljava/lang/Object;[B)[B;
const #13 = Asciz	scala/io/BytePickle$RefDef;
const #14 = class	#13;	//  scala/io/BytePickle$RefDef
const #15 = Asciz	scala/io/BytePickle$$anon$1;
const #16 = class	#15;	//  scala/io/BytePickle$$anon$1
const #17 = Asciz	(Lscala/io/BytePickle$RefDef;[B)[B;
const #18 = NameAndType	#11:#17;//  appP:(Lscala/io/BytePickle$RefDef;[B)[B
const #19 = Method	#16.#18;	//  scala/io/BytePickle$$anon$1.appP:(Lscala/io/BytePickle$RefDef;[B)[B
const #20 = Asciz	this;
const #21 = Asciz	Lscala/io/BytePickle$$anon$1;;
const #22 = Asciz	a;
const #23 = Asciz	Ljava/lang/Object;;
const #24 = Asciz	state;
const #25 = Asciz	[B;
const #26 = Asciz	LocalVariableTable;
const #27 = Asciz	appU;
const #28 = Asciz	([B)Lscala/Tuple2;;
const #29 = Asciz	scala/Tuple2;
const #30 = class	#29;	//  scala/Tuple2
const #31 = Asciz	scala/io/BytePickle$Ref;
const #32 = class	#31;	//  scala/io/BytePickle$Ref
const #33 = Method	#32.#9;	//  scala/io/BytePickle$Ref."<init>":()V
const #34 = Asciz	scala/collection/mutable/ArrayOps$ofByte;
const #35 = class	#34;	//  scala/collection/mutable/ArrayOps$ofByte
const #36 = Asciz	([B)V;
const #37 = NameAndType	#3:#36;//  "<init>":([B)V
const #38 = Method	#35.#37;	//  scala/collection/mutable/ArrayOps$ofByte."<init>":([B)V
const #39 = Asciz	scala/collection/IndexedSeqLike;
const #40 = class	#39;	//  scala/collection/IndexedSeqLike
const #41 = Asciz	slice;
const #42 = Asciz	(II)Ljava/lang/Object;;
const #43 = NameAndType	#41:#42;//  slice:(II)Ljava/lang/Object;
const #44 = InterfaceMethod	#40.#43;	//  scala/collection/IndexedSeqLike.slice:(II)Ljava/lang/Object;
const #45 = Asciz	(Ljava/lang/Object;Ljava/lang/Object;)V;
const #46 = NameAndType	#3:#45;//  "<init>":(Ljava/lang/Object;Ljava/lang/Object;)V
const #47 = Method	#30.#46;	//  scala/Tuple2."<init>":(Ljava/lang/Object;Ljava/lang/Object;)V
const #48 = Asciz	scala/io/BytePickle$Def;
const #49 = class	#48;	//  scala/io/BytePickle$Def
const #50 = Method	#49.#9;	//  scala/io/BytePickle$Def."<init>":()V
const #51 = Asciz	s;
const #52 = Asciz	([B)Lscala/Tuple2<Lscala/io/BytePickle$RefDef;[B>;;
const #53 = Asciz	Signature;
const #54 = Asciz	scala/Predef$;
const #55 = class	#54;	//  scala/Predef$
const #56 = Asciz	MODULE$;
const #57 = Asciz	Lscala/Predef$;;
const #58 = NameAndType	#56:#57;//  MODULE$:Lscala/Predef$;
const #59 = Field	#55.#58;	//  scala/Predef$.MODULE$:Lscala/Predef$;
const #60 = class	#25;	//  "[B"
const #61 = Asciz	wrapByteArray;
const #62 = Asciz	([B)Lscala/collection/mutable/WrappedArray;;
const #63 = NameAndType	#61:#62;//  wrapByteArray:([B)Lscala/collection/mutable/WrappedArray;
const #64 = Method	#55.#63;	//  scala/Predef$.wrapByteArray:([B)Lscala/collection/mutable/WrappedArray;
const #65 = Asciz	scala/reflect/Manifest$;
const #66 = class	#65;	//  scala/reflect/Manifest$
const #67 = Asciz	Lscala/reflect/Manifest$;;
const #68 = NameAndType	#56:#67;//  MODULE$:Lscala/reflect/Manifest$;
const #69 = Field	#66.#68;	//  scala/reflect/Manifest$.MODULE$:Lscala/reflect/Manifest$;
const #70 = Asciz	Byte;
const #71 = Asciz	()Ljava/lang/Object;;
const #72 = NameAndType	#70:#71;//  Byte:()Ljava/lang/Object;
const #73 = Method	#66.#72;	//  scala/reflect/Manifest$.Byte:()Ljava/lang/Object;
const #74 = Asciz	scala/reflect/ClassManifest;
const #75 = class	#74;	//  scala/reflect/ClassManifest
const #76 = Asciz	scala/collection/SeqLike;
const #77 = class	#76;	//  scala/collection/SeqLike
const #78 = Asciz	length;
const #79 = Asciz	()I;
const #80 = NameAndType	#78:#79;//  length:()I
const #81 = InterfaceMethod	#77.#80;	//  scala/collection/SeqLike.length:()I
const #82 = Asciz	newArray;
const #83 = Asciz	(I)Ljava/lang/Object;;
const #84 = NameAndType	#82:#83;//  newArray:(I)Ljava/lang/Object;
const #85 = InterfaceMethod	#75.#84;	//  scala/reflect/ClassManifest.newArray:(I)Ljava/lang/Object;
const #86 = Asciz	scala/runtime/IntRef;
const #87 = class	#86;	//  scala/runtime/IntRef
const #88 = Asciz	(I)V;
const #89 = NameAndType	#3:#88;//  "<init>":(I)V
const #90 = Method	#87.#89;	//  scala/runtime/IntRef."<init>":(I)V
const #91 = Asciz	scala/collection/IterableLike;
const #92 = class	#91;	//  scala/collection/IterableLike
const #93 = Asciz	iterator;
const #94 = Asciz	()Lscala/collection/Iterator;;
const #95 = NameAndType	#93:#94;//  iterator:()Lscala/collection/Iterator;
const #96 = InterfaceMethod	#92.#95;	//  scala/collection/IterableLike.iterator:()Lscala/collection/Iterator;
const #97 = Asciz	scala/Array$$anonfun$apply$1;
const #98 = class	#97;	//  scala/Array$$anonfun$apply$1
const #99 = Asciz	(Ljava/lang/Object;Lscala/runtime/IntRef;)V;
const #100 = NameAndType	#3:#99;//  "<init>":(Ljava/lang/Object;Lscala/runtime/IntRef;)V
const #101 = Method	#98.#100;	//  scala/Array$$anonfun$apply$1."<init>":(Ljava/lang/Object;Lscala/runtime/IntRef;)V
const #102 = Asciz	scala/collection/Iterator;
const #103 = class	#102;	//  scala/collection/Iterator
const #104 = Asciz	foreach;
const #105 = Asciz	(Lscala/Function1;)V;
const #106 = NameAndType	#104:#105;//  foreach:(Lscala/Function1;)V
const #107 = InterfaceMethod	#103.#106;	//  scala/collection/Iterator.foreach:(Lscala/Function1;)V
const #108 = Asciz	[Ljava/lang/Object;;
const #109 = class	#108;	//  "[Ljava/lang/Object;"
const #110 = Asciz	wrapRefArray;
const #111 = Asciz	([Ljava/lang/Object;)Lscala/collection/mutable/WrappedArray;;
const #112 = NameAndType	#110:#111;//  wrapRefArray:([Ljava/lang/Object;)Lscala/collection/mutable/WrappedArray;
const #113 = Method	#55.#112;	//  scala/Predef$.wrapRefArray:([Ljava/lang/Object;)Lscala/collection/mutable/WrappedArray;
const #114 = Asciz	newArrayBuilder;
const #115 = Asciz	()Lscala/collection/mutable/ArrayBuilder;;
const #116 = NameAndType	#114:#115;//  newArrayBuilder:()Lscala/collection/mutable/ArrayBuilder;
const #117 = InterfaceMethod	#75.#116;	//  scala/reflect/ClassManifest.newArrayBuilder:()Lscala/collection/mutable/ArrayBuilder;
const #118 = Asciz	scala/Array$$anonfun$concat$1;
const #119 = class	#118;	//  scala/Array$$anonfun$concat$1
const #120 = Method	#119.#9;	//  scala/Array$$anonfun$concat$1."<init>":()V
const #121 = Asciz	scala/collection/Seq$;
const #122 = class	#121;	//  scala/collection/Seq$
const #123 = Asciz	Lscala/collection/Seq$;;
const #124 = NameAndType	#56:#123;//  MODULE$:Lscala/collection/Seq$;
const #125 = Field	#122.#124;	//  scala/collection/Seq$.MODULE$:Lscala/collection/Seq$;
const #126 = Asciz	scala/collection/generic/TraversableFactory$GenericCanBuildFrom;
const #127 = class	#126;	//  scala/collection/generic/TraversableFactory$GenericCanBuildFrom
const #128 = Asciz	(Lscala/collection/generic/TraversableFactory;)V;
const #129 = NameAndType	#3:#128;//  "<init>":(Lscala/collection/generic/TraversableFactory;)V
const #130 = Method	#127.#129;	//  scala/collection/generic/TraversableFactory$GenericCanBuildFrom."<init>":(Lscala/collection/generic/TraversableFactory;)V
const #131 = Asciz	scala/collection/TraversableLike;
const #132 = class	#131;	//  scala/collection/TraversableLike
const #133 = Asciz	map;
const #134 = Asciz	(Lscala/Function1;Lscala/collection/generic/CanBuildFrom;)Ljava/lang/Object;;
const #135 = NameAndType	#133:#134;//  map:(Lscala/Function1;Lscala/collection/generic/CanBuildFrom;)Ljava/lang/Object;
const #136 = InterfaceMethod	#132.#135;	//  scala/collection/TraversableLike.map:(Lscala/Function1;Lscala/collection/generic/CanBuildFrom;)Ljava/lang/Object;
const #137 = Asciz	scala/math/Numeric$IntIsIntegral$;
const #138 = class	#137;	//  scala/math/Numeric$IntIsIntegral$
const #139 = Asciz	Lscala/math/Numeric$IntIsIntegral$;;
const #140 = NameAndType	#56:#139;//  MODULE$:Lscala/math/Numeric$IntIsIntegral$;
const #141 = Field	#138.#140;	//  scala/math/Numeric$IntIsIntegral$.MODULE$:Lscala/math/Numeric$IntIsIntegral$;
const #142 = Asciz	sum;
const #143 = Asciz	(Lscala/math/Numeric;)Ljava/lang/Object;;
const #144 = NameAndType	#142:#143;//  sum:(Lscala/math/Numeric;)Ljava/lang/Object;
const #145 = InterfaceMethod	#132.#144;	//  scala/collection/TraversableLike.sum:(Lscala/math/Numeric;)Ljava/lang/Object;
const #146 = Asciz	scala/runtime/BoxesRunTime;
const #147 = class	#146;	//  scala/runtime/BoxesRunTime
const #148 = Asciz	unboxToInt;
const #149 = Asciz	(Ljava/lang/Object;)I;
const #150 = NameAndType	#148:#149;//  unboxToInt:(Ljava/lang/Object;)I
const #151 = Method	#147.#150;	//  scala/runtime/BoxesRunTime.unboxToInt:(Ljava/lang/Object;)I
const #152 = Asciz	scala/collection/mutable/Builder;
const #153 = class	#152;	//  scala/collection/mutable/Builder
const #154 = Asciz	sizeHint;
const #155 = NameAndType	#154:#88;//  sizeHint:(I)V
const #156 = InterfaceMethod	#153.#155;	//  scala/collection/mutable/Builder.sizeHint:(I)V
const #157 = Asciz	scala/Array$$anonfun$concat$2;
const #158 = class	#157;	//  scala/Array$$anonfun$concat$2
const #159 = Asciz	(Lscala/collection/mutable/ArrayBuilder;)V;
const #160 = NameAndType	#3:#159;//  "<init>":(Lscala/collection/mutable/ArrayBuilder;)V
const #161 = Method	#158.#160;	//  scala/Array$$anonfun$concat$2."<init>":(Lscala/collection/mutable/ArrayBuilder;)V
const #162 = InterfaceMethod	#92.#106;	//  scala/collection/IterableLike.foreach:(Lscala/Function1;)V
const #163 = Asciz	result;
const #164 = NameAndType	#163:#71;//  result:()Ljava/lang/Object;
const #165 = InterfaceMethod	#153.#164;	//  scala/collection/mutable/Builder.result:()Ljava/lang/Object;
const #166 = Asciz	scala/MatchError;
const #167 = class	#166;	//  scala/MatchError
const #168 = Asciz	toString;
const #169 = Asciz	()Ljava/lang/String;;
const #170 = NameAndType	#168:#169;//  toString:()Ljava/lang/String;
const #171 = Method	#14.#170;	//  scala/io/BytePickle$RefDef.toString:()Ljava/lang/String;
const #172 = Asciz	(Ljava/lang/String;)V;
const #173 = NameAndType	#3:#172;//  "<init>":(Ljava/lang/String;)V
const #174 = Method	#167.#173;	//  scala/MatchError."<init>":(Ljava/lang/String;)V
const #175 = Asciz	b;
const #176 = Asciz	Lscala/io/BytePickle$RefDef;;
const #177 = Asciz	i$10;
const #178 = Asciz	Lscala/runtime/IntRef;;
const #179 = Asciz	array$10;
const #180 = Asciz	b$10;
const #181 = Asciz	Lscala/collection/mutable/ArrayBuilder;;
const #182 = Asciz	i$11;
const #183 = Asciz	array$11;
const #184 = Asciz	b$11;
const #185 = Asciz	Lscala/io/BytePickle$PU<Lscala/io/BytePickle$RefDef;>;;
const #186 = Asciz	Scala;
const #187 = Asciz	InnerClasses;
const #188 = Asciz	scala/io/BytePickle;
const #189 = class	#188;	//  scala/io/BytePickle
const #190 = Asciz	PU;
const #191 = Asciz	Def;
const #192 = Asciz	Ref;
const #193 = Asciz	scala/collection/mutable/ArrayOps;
const #194 = class	#193;	//  scala/collection/mutable/ArrayOps
const #195 = Asciz	ofByte;
const #196 = Asciz	RefDef;
const #197 = Asciz	$anon$1;
const #198 = Asciz	scala/Array;
const #199 = class	#198;	//  scala/Array
const #200 = Asciz	$anonfun$apply$1;
const #201 = Asciz	$anonfun$concat$2;
const #202 = Asciz	$anonfun$concat$1;
const #203 = Asciz	scala/collection/generic/TraversableFactory;
const #204 = class	#203;	//  scala/collection/generic/TraversableFactory
const #205 = Asciz	GenericCanBuildFrom;

{
public scala.io.BytePickle$$anon$1();
  Code:
   Stack=1, Locals=1, Args_size=1
   0:	aload_0
   1:	invokespecial	#10; //Method scala/io/BytePickle$PU."<init>":()V
   4:	return
  LineNumberTable: 
   line 65: 0


public byte[] appP(java.lang.Object, byte[]);
  Code:
   Stack=3, Locals=3, Args_size=3
   0:	aload_0
   1:	aload_1
   2:	checkcast	#14; //class scala/io/BytePickle$RefDef
   5:	aload_2
   6:	invokevirtual	#19; //Method appP:(Lscala/io/BytePickle$RefDef;[B)[B
   9:	areturn
  LineNumberTable: 
   line 65: 0

  LocalVariableTable: 
   Start  Length  Slot  Name   Signature
   0      10      0    this       Lscala/io/BytePickle$$anon$1;
   0      10      1    a       Ljava/lang/Object;
   0      10      2    state       [B


public scala.Tuple2 appU(byte[]);
  Code:
   Stack=6, Locals=2, Args_size=2
   0:	aload_1
   1:	iconst_0
   2:	baload
   3:	bipush	0
   5:	if_icmpne	41
   8:	new	#30; //class scala/Tuple2
   11:	dup
   12:	new	#32; //class scala/io/BytePickle$Ref
   15:	dup
   16:	invokespecial	#33; //Method scala/io/BytePickle$Ref."<init>":()V
   19:	new	#35; //class scala/collection/mutable/ArrayOps$ofByte
   22:	dup
   23:	aload_1
   24:	invokespecial	#38; //Method scala/collection/mutable/ArrayOps$ofByte."<init>":([B)V
   27:	iconst_1
   28:	aload_1
   29:	arraylength
   30:	invokeinterface	#44,  3; //InterfaceMethod scala/collection/IndexedSeqLike.slice:(II)Ljava/lang/Object;
   35:	invokespecial	#47; //Method scala/Tuple2."<init>":(Ljava/lang/Object;Ljava/lang/Object;)V
   38:	goto	71
   41:	new	#30; //class scala/Tuple2
   44:	dup
   45:	new	#49; //class scala/io/BytePickle$Def
   48:	dup
   49:	invokespecial	#50; //Method scala/io/BytePickle$Def."<init>":()V
   52:	new	#35; //class scala/collection/mutable/ArrayOps$ofByte
   55:	dup
   56:	aload_1
   57:	invokespecial	#38; //Method scala/collection/mutable/ArrayOps$ofByte."<init>":([B)V
   60:	iconst_1
   61:	aload_1
   62:	arraylength
   63:	invokeinterface	#44,  3; //InterfaceMethod scala/collection/IndexedSeqLike.slice:(II)Ljava/lang/Object;
   68:	invokespecial	#47; //Method scala/Tuple2."<init>":(Ljava/lang/Object;Ljava/lang/Object;)V
   71:	areturn
  LineNumberTable: 
   line 72: 0
   line 73: 41
   line 72: 71

  LocalVariableTable: 
   Start  Length  Slot  Name   Signature
   0      72      0    this       Lscala/io/BytePickle$$anon$1;
   0      72      1    s       [B

  Signature: length = 0x2
   00 34 

public byte[] appP(scala.io.BytePickle$RefDef, byte[]);
  Code:
   Stack=9, Locals=19, Args_size=3
   0:	aload_1
   1:	instanceof	#32; //class scala/io/BytePickle$Ref
   4:	ifeq	225
   7:	iconst_1
   8:	ifeq	213
   11:	getstatic	#59; //Field scala/Predef$.MODULE$:Lscala/Predef$;
   14:	iconst_2
   15:	anewarray	#60; //class "[B"
   18:	dup
   19:	iconst_0
   20:	aload_2
   21:	aastore
   22:	dup
   23:	iconst_1
   24:	getstatic	#59; //Field scala/Predef$.MODULE$:Lscala/Predef$;
   27:	iconst_1
   28:	newarray byte
   30:	dup
   31:	iconst_0
   32:	bipush	0
   34:	bastore
   35:	invokevirtual	#64; //Method scala/Predef$.wrapByteArray:([B)Lscala/collection/mutable/WrappedArray;
   38:	getstatic	#69; //Field scala/reflect/Manifest$.MODULE$:Lscala/reflect/Manifest$;
   41:	invokevirtual	#73; //Method scala/reflect/Manifest$.Byte:()Ljava/lang/Object;
   44:	checkcast	#75; //class scala/reflect/ClassManifest
   47:	astore_3
   48:	astore	4
   50:	aload_3
   51:	aload	4
   53:	invokeinterface	#81,  1; //InterfaceMethod scala/collection/SeqLike.length:()I
   58:	invokeinterface	#85,  2; //InterfaceMethod scala/reflect/ClassManifest.newArray:(I)Ljava/lang/Object;
   63:	astore	6
   65:	new	#87; //class scala/runtime/IntRef
   68:	dup
   69:	iconst_0
   70:	invokespecial	#90; //Method scala/runtime/IntRef."<init>":(I)V
   73:	astore	5
   75:	aload	4
   77:	invokeinterface	#96,  1; //InterfaceMethod scala/collection/IterableLike.iterator:()Lscala/collection/Iterator;
   82:	new	#98; //class scala/Array$$anonfun$apply$1
   85:	dup
   86:	aload	6
   88:	aload	5
   90:	invokespecial	#101; //Method scala/Array$$anonfun$apply$1."<init>":(Ljava/lang/Object;Lscala/runtime/IntRef;)V
   93:	invokeinterface	#107,  2; //InterfaceMethod scala/collection/Iterator.foreach:(Lscala/Function1;)V
   98:	aload	6
   100:	checkcast	#60; //class "[B"
   103:	aastore
   104:	checkcast	#109; //class "[Ljava/lang/Object;"
   107:	invokevirtual	#113; //Method scala/Predef$.wrapRefArray:([Ljava/lang/Object;)Lscala/collection/mutable/WrappedArray;
   110:	getstatic	#69; //Field scala/reflect/Manifest$.MODULE$:Lscala/reflect/Manifest$;
   113:	invokevirtual	#73; //Method scala/reflect/Manifest$.Byte:()Ljava/lang/Object;
   116:	checkcast	#75; //class scala/reflect/ClassManifest
   119:	astore	7
   121:	astore	9
   123:	aload	7
   125:	checkcast	#75; //class scala/reflect/ClassManifest
   128:	invokeinterface	#117,  1; //InterfaceMethod scala/reflect/ClassManifest.newArrayBuilder:()Lscala/collection/mutable/ArrayBuilder;
   133:	astore	10
   135:	aload	10
   137:	aload	9
   139:	new	#119; //class scala/Array$$anonfun$concat$1
   142:	dup
   143:	invokespecial	#120; //Method scala/Array$$anonfun$concat$1."<init>":()V
   146:	getstatic	#125; //Field scala/collection/Seq$.MODULE$:Lscala/collection/Seq$;
   149:	astore	8
   151:	new	#127; //class scala/collection/generic/TraversableFactory$GenericCanBuildFrom
   154:	dup
   155:	aload	8
   157:	invokespecial	#130; //Method scala/collection/generic/TraversableFactory$GenericCanBuildFrom."<init>":(Lscala/collection/generic/TraversableFactory;)V
   160:	invokeinterface	#136,  3; //InterfaceMethod scala/collection/TraversableLike.map:(Lscala/Function1;Lscala/collection/generic/CanBuildFrom;)Ljava/lang/Object;
   165:	checkcast	#132; //class scala/collection/TraversableLike
   168:	getstatic	#141; //Field scala/math/Numeric$IntIsIntegral$.MODULE$:Lscala/math/Numeric$IntIsIntegral$;
   171:	invokeinterface	#145,  2; //InterfaceMethod scala/collection/TraversableLike.sum:(Lscala/math/Numeric;)Ljava/lang/Object;
   176:	invokestatic	#151; //Method scala/runtime/BoxesRunTime.unboxToInt:(Ljava/lang/Object;)I
   179:	invokeinterface	#156,  2; //InterfaceMethod scala/collection/mutable/Builder.sizeHint:(I)V
   184:	aload	9
   186:	new	#158; //class scala/Array$$anonfun$concat$2
   189:	dup
   190:	aload	10
   192:	invokespecial	#161; //Method scala/Array$$anonfun$concat$2."<init>":(Lscala/collection/mutable/ArrayBuilder;)V
   195:	invokeinterface	#162,  2; //InterfaceMethod scala/collection/IterableLike.foreach:(Lscala/Function1;)V
   200:	aload	10
   202:	invokeinterface	#165,  1; //InterfaceMethod scala/collection/mutable/Builder.result:()Ljava/lang/Object;
   207:	checkcast	#60; //class "[B"
   210:	goto	437
   213:	new	#167; //class scala/MatchError
   216:	dup
   217:	aload_1
   218:	invokevirtual	#171; //Method scala/io/BytePickle$RefDef.toString:()Ljava/lang/String;
   221:	invokespecial	#174; //Method scala/MatchError."<init>":(Ljava/lang/String;)V
   224:	athrow
   225:	aload_1
   226:	instanceof	#49; //class scala/io/BytePickle$Def
   229:	ifeq	450
   232:	iconst_1
   233:	ifeq	438
   236:	getstatic	#59; //Field scala/Predef$.MODULE$:Lscala/Predef$;
   239:	iconst_2
   240:	anewarray	#60; //class "[B"
   243:	dup
   244:	iconst_0
   245:	aload_2
   246:	aastore
   247:	dup
   248:	iconst_1
   249:	getstatic	#59; //Field scala/Predef$.MODULE$:Lscala/Predef$;
   252:	iconst_1
   253:	newarray byte
   255:	dup
   256:	iconst_0
   257:	bipush	1
   259:	bastore
   260:	invokevirtual	#64; //Method scala/Predef$.wrapByteArray:([B)Lscala/collection/mutable/WrappedArray;
   263:	getstatic	#69; //Field scala/reflect/Manifest$.MODULE$:Lscala/reflect/Manifest$;
   266:	invokevirtual	#73; //Method scala/reflect/Manifest$.Byte:()Ljava/lang/Object;
   269:	checkcast	#75; //class scala/reflect/ClassManifest
   272:	astore	11
   274:	astore	12
   276:	aload	11
   278:	aload	12
   280:	invokeinterface	#81,  1; //InterfaceMethod scala/collection/SeqLike.length:()I
   285:	invokeinterface	#85,  2; //InterfaceMethod scala/reflect/ClassManifest.newArray:(I)Ljava/lang/Object;
   290:	astore	14
   292:	new	#87; //class scala/runtime/IntRef
   295:	dup
   296:	iconst_0
   297:	invokespecial	#90; //Method scala/runtime/IntRef."<init>":(I)V
   300:	astore	13
   302:	aload	12
   304:	invokeinterface	#96,  1; //InterfaceMethod scala/collection/IterableLike.iterator:()Lscala/collection/Iterator;
   309:	new	#98; //class scala/Array$$anonfun$apply$1
   312:	dup
   313:	aload	14
   315:	aload	13
   317:	invokespecial	#101; //Method scala/Array$$anonfun$apply$1."<init>":(Ljava/lang/Object;Lscala/runtime/IntRef;)V
   320:	invokeinterface	#107,  2; //InterfaceMethod scala/collection/Iterator.foreach:(Lscala/Function1;)V
   325:	aload	14
   327:	checkcast	#60; //class "[B"
   330:	aastore
   331:	checkcast	#109; //class "[Ljava/lang/Object;"
   334:	invokevirtual	#113; //Method scala/Predef$.wrapRefArray:([Ljava/lang/Object;)Lscala/collection/mutable/WrappedArray;
   337:	getstatic	#69; //Field scala/reflect/Manifest$.MODULE$:Lscala/reflect/Manifest$;
   340:	invokevirtual	#73; //Method scala/reflect/Manifest$.Byte:()Ljava/lang/Object;
   343:	checkcast	#75; //class scala/reflect/ClassManifest
   346:	astore	15
   348:	astore	17
   350:	aload	15
   352:	checkcast	#75; //class scala/reflect/ClassManifest
   355:	invokeinterface	#117,  1; //InterfaceMethod scala/reflect/ClassManifest.newArrayBuilder:()Lscala/collection/mutable/ArrayBuilder;
   360:	astore	18
   362:	aload	18
   364:	aload	17
   366:	new	#119; //class scala/Array$$anonfun$concat$1
   369:	dup
   370:	invokespecial	#120; //Method scala/Array$$anonfun$concat$1."<init>":()V
   373:	getstatic	#125; //Field scala/collection/Seq$.MODULE$:Lscala/collection/Seq$;
   376:	astore	16
   378:	new	#127; //class scala/collection/generic/TraversableFactory$GenericCanBuildFrom
   381:	dup
   382:	aload	16
   384:	invokespecial	#130; //Method scala/collection/generic/TraversableFactory$GenericCanBuildFrom."<init>":(Lscala/collection/generic/TraversableFactory;)V
   387:	invokeinterface	#136,  3; //InterfaceMethod scala/collection/TraversableLike.map:(Lscala/Function1;Lscala/collection/generic/CanBuildFrom;)Ljava/lang/Object;
   392:	checkcast	#132; //class scala/collection/TraversableLike
   395:	getstatic	#141; //Field scala/math/Numeric$IntIsIntegral$.MODULE$:Lscala/math/Numeric$IntIsIntegral$;
   398:	invokeinterface	#145,  2; //InterfaceMethod scala/collection/TraversableLike.sum:(Lscala/math/Numeric;)Ljava/lang/Object;
   403:	invokestatic	#151; //Method scala/runtime/BoxesRunTime.unboxToInt:(Ljava/lang/Object;)I
   406:	invokeinterface	#156,  2; //InterfaceMethod scala/collection/mutable/Builder.sizeHint:(I)V
   411:	aload	17
   413:	new	#158; //class scala/Array$$anonfun$concat$2
   416:	dup
   417:	aload	18
   419:	invokespecial	#161; //Method scala/Array$$anonfun$concat$2."<init>":(Lscala/collection/mutable/ArrayBuilder;)V
   422:	invokeinterface	#162,  2; //InterfaceMethod scala/collection/IterableLike.foreach:(Lscala/Function1;)V
   427:	aload	18
   429:	invokeinterface	#165,  1; //InterfaceMethod scala/collection/mutable/Builder.result:()Ljava/lang/Object;
   434:	checkcast	#60; //class "[B"
   437:	areturn
   438:	new	#167; //class scala/MatchError
   441:	dup
   442:	aload_1
   443:	invokevirtual	#171; //Method scala/io/BytePickle$RefDef.toString:()Ljava/lang/String;
   446:	invokespecial	#174; //Method scala/MatchError."<init>":(Ljava/lang/String;)V
   449:	athrow
   450:	new	#167; //class scala/MatchError
   453:	dup
   454:	aload_1
   455:	invokevirtual	#171; //Method scala/io/BytePickle$RefDef.toString:()Ljava/lang/String;
   458:	invokespecial	#174; //Method scala/MatchError."<init>":(Ljava/lang/String;)V
   461:	athrow
  LineNumberTable: 
   line 67: 0
   line 21: 7
   line 68: 11
   line 67: 213
   line 21: 232
   line 69: 236
   line 67: 437

  LocalVariableTable: 
   Start  Length  Slot  Name   Signature
   0      462      0    this       Lscala/io/BytePickle$$anon$1;
   0      462      1    b       Lscala/io/BytePickle$RefDef;
   0      462      2    s       [B
   75      25      5    i$10       Lscala/runtime/IntRef;
   65      35      6    array$10       Ljava/lang/Object;
   135      72      10    b$10       Lscala/collection/mutable/ArrayBuilder;
   302      25      13    i$11       Lscala/runtime/IntRef;
   292      35      14    array$11       Ljava/lang/Object;
   362      72      18    b$11       Lscala/collection/mutable/ArrayBuilder;


}

