Compiled from "BytePickle.scala"
public final class scala.io.BytePickle$$anon$5 extends scala.io.BytePickle$SPU
  SourceFile: "BytePickle.scala"
  Signature: length = 0x2
   00 36 
  Scala: length = 0x
   
  InnerClass: 
   public abstract #59= #14 of #58; //SPU=class scala/io/BytePickle$SPU of class scala/io/BytePickle
   public final #60= #10 of #58; //$anon$5=class scala/io/BytePickle$$anon$5 of class scala/io/BytePickle
   public #63= #62 of #58; //PicklerState=class scala/io/BytePickle$PicklerState of class scala/io/BytePickle
   public #66= #65 of #58; //UnPicklerState=class scala/io/BytePickle$UnPicklerState of class scala/io/BytePickle
  minor version: 0
  major version: 49
  Constant pool:
const #1 = Asciz	SourceFile;
const #2 = Asciz	BytePickle.scala;
const #3 = Asciz	x$5;
const #4 = Asciz	Ljava/lang/Object;;
const #5 = Asciz	<init>;
const #6 = Asciz	(Ljava/lang/Object;)V;
const #7 = Asciz	Code;
const #8 = Asciz	LineNumberTable;
const #9 = Asciz	scala/io/BytePickle$$anon$5;
const #10 = class	#9;	//  scala/io/BytePickle$$anon$5
const #11 = NameAndType	#3:#4;//  x$5:Ljava/lang/Object;
const #12 = Field	#10.#11;	//  scala/io/BytePickle$$anon$5.x$5:Ljava/lang/Object;
const #13 = Asciz	scala/io/BytePickle$SPU;
const #14 = class	#13;	//  scala/io/BytePickle$SPU
const #15 = Asciz	()V;
const #16 = NameAndType	#5:#15;//  "<init>":()V
const #17 = Method	#14.#16;	//  scala/io/BytePickle$SPU."<init>":()V
const #18 = Asciz	appU;
const #19 = Asciz	(Lscala/io/BytePickle$UnPicklerState;)Lscala/Tuple2;;
const #20 = Asciz	scala/Tuple2;
const #21 = class	#20;	//  scala/Tuple2
const #22 = Asciz	(Ljava/lang/Object;Ljava/lang/Object;)V;
const #23 = NameAndType	#5:#22;//  "<init>":(Ljava/lang/Object;Ljava/lang/Object;)V
const #24 = Method	#21.#23;	//  scala/Tuple2."<init>":(Ljava/lang/Object;Ljava/lang/Object;)V
const #25 = Asciz	this;
const #26 = Asciz	Lscala/io/BytePickle$$anon$5;;
const #27 = Asciz	state;
const #28 = Asciz	Lscala/io/BytePickle$UnPicklerState;;
const #29 = Asciz	LocalVariableTable;
const #30 = Asciz	(Lscala/io/BytePickle$UnPicklerState;)Lscala/Tuple2<Tt;Lscala/io/BytePickle$UnPicklerState;>;;
const #31 = Asciz	Signature;
const #32 = Asciz	appP;
const #33 = Asciz	(Ljava/lang/Object;Lscala/io/BytePickle$PicklerState;)Lscala/io/BytePickle$PicklerState;;
const #34 = Asciz	java/lang/Number;
const #35 = class	#34;	//  java/lang/Number
const #36 = Asciz	java/lang/Character;
const #37 = class	#36;	//  java/lang/Character
const #38 = Asciz	scala/runtime/BoxesRunTime;
const #39 = class	#38;	//  scala/runtime/BoxesRunTime
const #40 = Asciz	equals2;
const #41 = Asciz	(Ljava/lang/Object;Ljava/lang/Object;)Z;
const #42 = NameAndType	#40:#41;//  equals2:(Ljava/lang/Object;Ljava/lang/Object;)Z
const #43 = Method	#39.#42;	//  scala/runtime/BoxesRunTime.equals2:(Ljava/lang/Object;Ljava/lang/Object;)Z
const #44 = Asciz	java/lang/Object;
const #45 = class	#44;	//  java/lang/Object
const #46 = Asciz	equals;
const #47 = Asciz	(Ljava/lang/Object;)Z;
const #48 = NameAndType	#46:#47;//  equals:(Ljava/lang/Object;)Z
const #49 = Method	#45.#48;	//  java/lang/Object.equals:(Ljava/lang/Object;)Z
const #50 = Asciz	a;
const #51 = Asciz	Lscala/io/BytePickle$PicklerState;;
const #52 = Asciz	x0;
const #53 = Asciz	(Tt;Lscala/io/BytePickle$PicklerState;)Lscala/io/BytePickle$PicklerState;;
const #54 = Asciz	Lscala/io/BytePickle$SPU<Tt;>;;
const #55 = Asciz	Scala;
const #56 = Asciz	InnerClasses;
const #57 = Asciz	scala/io/BytePickle;
const #58 = class	#57;	//  scala/io/BytePickle
const #59 = Asciz	SPU;
const #60 = Asciz	$anon$5;
const #61 = Asciz	scala/io/BytePickle$PicklerState;
const #62 = class	#61;	//  scala/io/BytePickle$PicklerState
const #63 = Asciz	PicklerState;
const #64 = Asciz	scala/io/BytePickle$UnPicklerState;
const #65 = class	#64;	//  scala/io/BytePickle$UnPicklerState
const #66 = Asciz	UnPicklerState;

{
public scala.io.BytePickle$$anon$5(java.lang.Object);
  Code:
   Stack=2, Locals=2, Args_size=2
   0:	aload_0
   1:	aload_1
   2:	putfield	#12; //Field x$5:Ljava/lang/Object;
   5:	aload_0
   6:	invokespecial	#17; //Method scala/io/BytePickle$SPU."<init>":()V
   9:	return
  LineNumberTable: 
   line 162: 0


public scala.Tuple2 appU(scala.io.BytePickle$UnPicklerState);
  Code:
   Stack=4, Locals=2, Args_size=2
   0:	new	#21; //class scala/Tuple2
   3:	dup
   4:	aload_0
   5:	getfield	#12; //Field x$5:Ljava/lang/Object;
   8:	aload_1
   9:	invokespecial	#24; //Method scala/Tuple2."<init>":(Ljava/lang/Object;Ljava/lang/Object;)V
   12:	areturn
  LineNumberTable: 
   line 166: 0

  LocalVariableTable: 
   Start  Length  Slot  Name   Signature
   0      13      0    this       Lscala/io/BytePickle$$anon$5;
   0      13      1    state       Lscala/io/BytePickle$UnPicklerState;

  Signature: length = 0x2
   00 1E 

public scala.io.BytePickle$PicklerState appP(java.lang.Object, scala.io.BytePickle$PicklerState);
  Code:
   Stack=2, Locals=4, Args_size=3
   0:	aload_0
   1:	getfield	#12; //Field x$5:Ljava/lang/Object;
   4:	astore_3
   5:	aload_3
   6:	aload_1
   7:	if_acmpne	14
   10:	iconst_1
   11:	goto	49
   14:	aload_3
   15:	ifnonnull	22
   18:	iconst_0
   19:	goto	49
   22:	aload_3
   23:	instanceof	#35; //class java/lang/Number
   26:	ifne	36
   29:	aload_3
   30:	instanceof	#37; //class java/lang/Character
   33:	ifeq	44
   36:	aload_3
   37:	aload_1
   38:	invokestatic	#43; //Method scala/runtime/BoxesRunTime.equals2:(Ljava/lang/Object;Ljava/lang/Object;)Z
   41:	goto	49
   44:	aload_3
   45:	aload_1
   46:	invokevirtual	#49; //Method java/lang/Object.equals:(Ljava/lang/Object;)Z
   49:	ifeq	56
   52:	aload_2
   53:	goto	57
   56:	aload_2
   57:	areturn
  LineNumberTable: 
   line 164: 0
   line 165: 52
   line 164: 53

  LocalVariableTable: 
   Start  Length  Slot  Name   Signature
   0      58      0    this       Lscala/io/BytePickle$$anon$5;
   0      58      1    a       Ljava/lang/Object;
   0      58      2    state       Lscala/io/BytePickle$PicklerState;
   10      42      3    x0       Ljava/lang/Object;

  Signature: length = 0x2
   00 35 

}

