Compiled from "BytePickle.scala"
public final class scala.io.BytePickle$ extends java.lang.Object implements scala.ScalaObject
  SourceFile: "BytePickle.scala"
  Scala: length = 0x
   
  InnerClass: 
   public abstract PU=class scala/io/BytePickle$PU of class scala/io/BytePickle
   public Def=class scala/io/BytePickle$Def of class scala/io/BytePickle
   public Ref=class scala/io/BytePickle$Ref of class scala/io/BytePickle
   public abstract SPU=class scala/io/BytePickle$SPU of class scala/io/BytePickle
   public abstract RefDef=class scala/io/BytePickle$RefDef of class scala/io/BytePickle
   public final $anon$9=class scala/io/BytePickle$$anon$9 of class scala/io/BytePickle
   public final $anon$8=class scala/io/BytePickle$$anon$8 of class scala/io/BytePickle
   public final $anon$7=class scala/io/BytePickle$$anon$7 of class scala/io/BytePickle
   public final $anon$6=class scala/io/BytePickle$$anon$6 of class scala/io/BytePickle
   public final $anon$5=class scala/io/BytePickle$$anon$5 of class scala/io/BytePickle
   public final $anon$4=class scala/io/BytePickle$$anon$4 of class scala/io/BytePickle
   public final $anon$3=class scala/io/BytePickle$$anon$3 of class scala/io/BytePickle
   public final $anon$2=class scala/io/BytePickle$$anon$2 of class scala/io/BytePickle
   public final $anon$1=class scala/io/BytePickle$$anon$1 of class scala/io/BytePickle
   public PicklerEnv=class scala/io/BytePickle$PicklerEnv of class scala/io/BytePickle
   public PicklerState=class scala/io/BytePickle$PicklerState of class scala/io/BytePickle
   public UnPicklerEnv=class scala/io/BytePickle$UnPicklerEnv of class scala/io/BytePickle
   public UnPicklerState=class scala/io/BytePickle$UnPicklerState of class scala/io/BytePickle
   public final $anonfun$data$1=class scala/io/BytePickle$$anonfun$data$1 of class scala/io/BytePickle
   public final $anonfun$list$2=class scala/io/BytePickle$$anonfun$list$2 of class scala/io/BytePickle
   public final $anonfun$list$1=class scala/io/BytePickle$$anonfun$list$1 of class scala/io/BytePickle
   public final $anonfun$bool$2=class scala/io/BytePickle$$anonfun$bool$2 of class scala/io/BytePickle
   public final $anonfun$bool$1=class scala/io/BytePickle$$anonfun$bool$1 of class scala/io/BytePickle
   public final $anonfun$wrap$1=class scala/io/BytePickle$$anonfun$wrap$1 of class scala/io/BytePickle
   public final $anonfun$pair$2=class scala/io/BytePickle$$anonfun$pair$2 of class scala/io/BytePickle
   public final $anonfun$pair$1=class scala/io/BytePickle$$anonfun$pair$1 of class scala/io/BytePickle
   public final $anonfun$ulist$2=class scala/io/BytePickle$$anonfun$ulist$2 of class scala/io/BytePickle
   public final $anonfun$ulist$1=class scala/io/BytePickle$$anonfun$ulist$1 of class scala/io/BytePickle
   public final $anonfun$uwrap$1=class scala/io/BytePickle$$anonfun$uwrap$1 of class scala/io/BytePickle
   public final $anonfun$upair$2=class scala/io/BytePickle$$anonfun$upair$2 of class scala/io/BytePickle
   public final $anonfun$upair$1=class scala/io/BytePickle$$anonfun$upair$1 of class scala/io/BytePickle
   public final $anonfun$string$2=class scala/io/BytePickle$$anonfun$string$2 of class scala/io/BytePickle
   public final $anonfun$string$1=class scala/io/BytePickle$$anonfun$string$1 of class scala/io/BytePickle
   public final $anonfun$triple$2=class scala/io/BytePickle$$anonfun$triple$2 of class scala/io/BytePickle
   public final $anonfun$triple$1=class scala/io/BytePickle$$anonfun$triple$1 of class scala/io/BytePickle
   public final $anonfun$fixedList$2=class scala/io/BytePickle$$anonfun$fixedList$2 of class scala/io/BytePickle
   public final $anonfun$fixedList$1=class scala/io/BytePickle$$anonfun$fixedList$1 of class scala/io/BytePickle
   public final $anonfun$bytearray$2=class scala/io/BytePickle$$anonfun$bytearray$2 of class scala/io/BytePickle
   public final $anonfun$bytearray$1=class scala/io/BytePickle$$anonfun$bytearray$1 of class scala/io/BytePickle
   public final $anonfun$ufixedList$2=class scala/io/BytePickle$$anonfun$ufixedList$2 of class scala/io/BytePickle
   public final $anonfun$ufixedList$1=class scala/io/BytePickle$$anonfun$ufixedList$1 of class scala/io/BytePickle
  minor version: 0
  major version: 49
  Constant pool:
Asciz	SourceFile;
Asciz	BytePickle.scala;
Asciz	Scala;
Asciz	MODULE$;
Asciz	Lscala/io/BytePickle$;;
Asciz	<clinit>;
Asciz	()V;
Asciz	Code;
Asciz	scala/io/BytePickle$;
class	scala/io/BytePickle$
Asciz	<init>;
NameAndType	"<init>":()V
Method	scala/io/BytePickle$."<init>":()V
Asciz	DEF;
Asciz	I;
Asciz	REF;
Asciz	LineNumberTable;
Asciz	java/lang/Object;
class	java/lang/Object
Method	java/lang/Object."<init>":()V
NameAndType	MODULE$:Lscala/io/BytePickle$;
Field	scala/io/BytePickle$.MODULE$:Lscala/io/BytePickle$;
NameAndType	REF:I
Field	scala/io/BytePickle$.REF:I
NameAndType	DEF:I
Field	scala/io/BytePickle$.DEF:I
Asciz	listToPair$2;
Asciz	(Lscala/collection/immutable/List;)Lscala/Tuple2;;
Asciz	scala/collection/immutable/$colon$colon;
class	scala/collection/immutable/$colon$colon
Asciz	scala$collection$immutable$$colon$colon$$hd;
Asciz	Ljava/lang/Object;;
NameAndType	scala$collection$immutable$$colon$colon$$hd:Ljava/lang/Object;
Field	scala/collection/immutable/$colon$colon.scala$collection$immutable$$colon$colon$$hd:Ljava/lang/Object;
Asciz	tl;
Asciz	Lscala/collection/immutable/List;;
NameAndType	tl:Lscala/collection/immutable/List;
Field	scala/collection/immutable/$colon$colon.tl:Lscala/collection/immutable/List;
Asciz	scala/Tuple2;
class	scala/Tuple2
Asciz	(Ljava/lang/Object;Ljava/lang/Object;)V;
NameAndType	"<init>":(Ljava/lang/Object;Ljava/lang/Object;)V
Method	scala/Tuple2."<init>":(Ljava/lang/Object;Ljava/lang/Object;)V
Asciz	scala/MatchError;
class	scala/MatchError
Asciz	scala/collection/SeqLike;
class	scala/collection/SeqLike
Asciz	toString;
Asciz	()Ljava/lang/String;;
NameAndType	toString:()Ljava/lang/String;
InterfaceMethod	scala/collection/SeqLike.toString:()Ljava/lang/String;
Asciz	(Ljava/lang/String;)V;
NameAndType	"<init>":(Ljava/lang/String;)V
Method	scala/MatchError."<init>":(Ljava/lang/String;)V
Asciz	this;
Asciz	l;
Asciz	temp26;
Asciz	Lscala/collection/immutable/$colon$colon;;
Asciz	temp27;
Asciz	temp28;
Asciz	LocalVariableTable;
Asciz	pairToList$2;
Asciz	(Lscala/Tuple2;)Lscala/collection/immutable/List;;
Asciz	_1;
Asciz	()Ljava/lang/Object;;
NameAndType	_1:()Ljava/lang/Object;
Method	scala/Tuple2._1:()Ljava/lang/Object;
Asciz	_2;
NameAndType	_2:()Ljava/lang/Object;
Method	scala/Tuple2._2:()Ljava/lang/Object;
Asciz	scala/collection/immutable/List;
class	scala/collection/immutable/List
Asciz	$colon$colon;
Asciz	(Ljava/lang/Object;)Lscala/collection/immutable/List;;
NameAndType	$colon$colon:(Ljava/lang/Object;)Lscala/collection/immutable/List;
Method	scala/collection/immutable/List.$colon$colon:(Ljava/lang/Object;)Lscala/collection/immutable/List;
Asciz	p;
Asciz	Lscala/Tuple2;;
Asciz	listToPair$1;
Asciz	temp22;
Asciz	temp23;
Asciz	temp24;
Asciz	pairToList$1;
Asciz	fromEnum$1;
Asciz	(I)Z;
Asciz	n;
Asciz	toEnum$1;
Asciz	(Z)I;
Asciz	b;
Asciz	Z;
Asciz	writeNatPrefix$1;
Asciz	(ILscala/collection/mutable/ArrayBuffer;)V;
int	7;
NameAndType	writeNatPrefix$1:(ILscala/collection/mutable/ArrayBuffer;)V
Method	scala/io/BytePickle$.writeNatPrefix$1:(ILscala/collection/mutable/ArrayBuffer;)V
int	127;
int	128;
Asciz	scala/runtime/BoxesRunTime;
class	scala/runtime/BoxesRunTime
Asciz	boxToByte;
Asciz	(B)Ljava/lang/Byte;;
NameAndType	boxToByte:(B)Ljava/lang/Byte;
Method	scala/runtime/BoxesRunTime.boxToByte:(B)Ljava/lang/Byte;
Asciz	scala/collection/mutable/ArrayBuffer;
class	scala/collection/mutable/ArrayBuffer
Asciz	$plus$eq;
Asciz	(Ljava/lang/Object;)Lscala/collection/mutable/ArrayBuffer;;
NameAndType	$plus$eq:(Ljava/lang/Object;)Lscala/collection/mutable/ArrayBuffer;
Method	scala/collection/mutable/ArrayBuffer.$plus$eq:(Ljava/lang/Object;)Lscala/collection/mutable/ArrayBuffer;
Asciz	x;
Asciz	y;
Asciz	trd$1;
Asciz	(Lscala/Tuple3;)Ljava/lang/Object;;
Asciz	scala/Tuple3;
class	scala/Tuple3
Asciz	_3;
NameAndType	_3:()Ljava/lang/Object;
Method	scala/Tuple3._3:()Ljava/lang/Object;
Asciz	Lscala/Tuple3;;
Asciz	snd$3;
Method	scala/Tuple3._2:()Ljava/lang/Object;
Asciz	fst$3;
Method	scala/Tuple3._1:()Ljava/lang/Object;
Asciz	snd$2;
Asciz	(Lscala/Tuple2;)Ljava/lang/Object;;
Asciz	fst$2;
Asciz	snd$1;
Asciz	fst$1;
Asciz	data;
Asciz	(Lscala/Function1;Lscala/collection/immutable/List;)Lscala/io/BytePickle$SPU;;
Asciz	scala/io/BytePickle$$anon$8;
class	scala/io/BytePickle$$anon$8
Method	scala/io/BytePickle$$anon$8."<init>":()V
Asciz	scala/io/BytePickle$$anonfun$data$1;
class	scala/io/BytePickle$$anonfun$data$1
Asciz	(Lscala/collection/immutable/List;)V;
NameAndType	"<init>":(Lscala/collection/immutable/List;)V
Method	scala/io/BytePickle$$anonfun$data$1."<init>":(Lscala/collection/immutable/List;)V
Asciz	scala/io/BytePickle$$anon$7;
class	scala/io/BytePickle$$anon$7
Asciz	(Lscala/Function1;Lscala/io/BytePickle$SPU;Lscala/Function1;)V;
NameAndType	"<init>":(Lscala/Function1;Lscala/io/BytePickle$SPU;Lscala/Function1;)V
Method	scala/io/BytePickle$$anon$7."<init>":(Lscala/Function1;Lscala/io/BytePickle$SPU;Lscala/Function1;)V
Asciz	tag;
Asciz	Lscala/Function1;;
Asciz	ps$1;
Asciz	<a:Ljava/lang/Object;>(Lscala/Function1<Ta;Ljava/lang/Integer;>;Lscala/collection/immutable/List<Lscala/Function0<Lscala/io/BytePickle$SPU<Ta;>;>;>;)Lscala/io/BytePickle$SPU<Ta;>;;
Asciz	Signature;
Asciz	ulist;
Asciz	(Lscala/io/BytePickle$PU;)Lscala/io/BytePickle$PU;;
Asciz	scala/io/BytePickle$$anonfun$ulist$1;
class	scala/io/BytePickle$$anonfun$ulist$1
Method	scala/io/BytePickle$$anonfun$ulist$1."<init>":()V
Asciz	scala/io/BytePickle$$anon$2;
class	scala/io/BytePickle$$anon$2
Method	scala/io/BytePickle$$anon$2."<init>":()V
Asciz	scala/io/BytePickle$$anonfun$ulist$2;
class	scala/io/BytePickle$$anonfun$ulist$2
Asciz	(Lscala/io/BytePickle$PU;)V;
NameAndType	"<init>":(Lscala/io/BytePickle$PU;)V
Method	scala/io/BytePickle$$anonfun$ulist$2."<init>":(Lscala/io/BytePickle$PU;)V
Asciz	scala/io/BytePickle$$anon$6;
class	scala/io/BytePickle$$anon$6
Asciz	(Lscala/Function1;Lscala/io/BytePickle$PU;Lscala/Function1;)V;
NameAndType	"<init>":(Lscala/Function1;Lscala/io/BytePickle$PU;Lscala/Function1;)V
Method	scala/io/BytePickle$$anon$6."<init>":(Lscala/Function1;Lscala/io/BytePickle$PU;Lscala/Function1;)V
Asciz	pa$5;
Asciz	Lscala/io/BytePickle$PU;;
Asciz	<a:Ljava/lang/Object;>(Lscala/io/BytePickle$PU<Ta;>;)Lscala/io/BytePickle$PU<Lscala/collection/immutable/List<Ta;>;>;;
Asciz	list;
Asciz	(Lscala/io/BytePickle$SPU;)Lscala/io/BytePickle$SPU;;
Asciz	scala/io/BytePickle$$anonfun$list$1;
class	scala/io/BytePickle$$anonfun$list$1
Method	scala/io/BytePickle$$anonfun$list$1."<init>":()V
Asciz	scala/io/BytePickle$$anonfun$list$2;
class	scala/io/BytePickle$$anonfun$list$2
Asciz	(Lscala/io/BytePickle$SPU;)V;
NameAndType	"<init>":(Lscala/io/BytePickle$SPU;)V
Method	scala/io/BytePickle$$anonfun$list$2."<init>":(Lscala/io/BytePickle$SPU;)V
Asciz	pa$4;
Asciz	Lscala/io/BytePickle$SPU;;
Asciz	<a:Ljava/lang/Object;>(Lscala/io/BytePickle$SPU<Ta;>;)Lscala/io/BytePickle$SPU<Lscala/collection/immutable/List<Ta;>;>;;
Asciz	fixedList;
Asciz	(Lscala/io/BytePickle$SPU;I)Lscala/io/BytePickle$SPU;;
Asciz	scala/collection/immutable/Nil$;
class	scala/collection/immutable/Nil$
Asciz	Lscala/collection/immutable/Nil$;;
NameAndType	MODULE$:Lscala/collection/immutable/Nil$;
Field	scala/collection/immutable/Nil$.MODULE$:Lscala/collection/immutable/Nil$;
Asciz	scala/io/BytePickle$$anon$5;
class	scala/io/BytePickle$$anon$5
Asciz	(Ljava/lang/Object;)V;
NameAndType	"<init>":(Ljava/lang/Object;)V
Method	scala/io/BytePickle$$anon$5."<init>":(Ljava/lang/Object;)V
Asciz	scala/io/BytePickle$$anonfun$fixedList$1;
class	scala/io/BytePickle$$anonfun$fixedList$1
Method	scala/io/BytePickle$$anonfun$fixedList$1."<init>":()V
Asciz	scala/io/BytePickle$$anonfun$fixedList$2;
class	scala/io/BytePickle$$anonfun$fixedList$2
Method	scala/io/BytePickle$$anonfun$fixedList$2."<init>":()V
NameAndType	fixedList:(Lscala/io/BytePickle$SPU;I)Lscala/io/BytePickle$SPU;
Method	scala/io/BytePickle$.fixedList:(Lscala/io/BytePickle$SPU;I)Lscala/io/BytePickle$SPU;
Asciz	scala/io/BytePickle$$anonfun$pair$1;
class	scala/io/BytePickle$$anonfun$pair$1
Method	scala/io/BytePickle$$anonfun$pair$1."<init>":()V
Asciz	scala/io/BytePickle$$anonfun$pair$2;
class	scala/io/BytePickle$$anonfun$pair$2
Method	scala/io/BytePickle$$anonfun$pair$2."<init>":(Lscala/io/BytePickle$SPU;)V
Asciz	scala/io/BytePickle$$anonfun$wrap$1;
class	scala/io/BytePickle$$anonfun$wrap$1
Asciz	(Lscala/Function1;)V;
NameAndType	"<init>":(Lscala/Function1;)V
Method	scala/io/BytePickle$$anonfun$wrap$1."<init>":(Lscala/Function1;)V
Asciz	pa;
Asciz	<a:Ljava/lang/Object;>(Lscala/io/BytePickle$SPU<Ta;>;I)Lscala/io/BytePickle$SPU<Lscala/collection/immutable/List<Ta;>;>;;
Asciz	ufixedList;
Asciz	(Lscala/io/BytePickle$PU;I)Lscala/io/BytePickle$PU;;
Asciz	scala/io/BytePickle$$anon$4;
class	scala/io/BytePickle$$anon$4
Method	scala/io/BytePickle$$anon$4."<init>":(Ljava/lang/Object;)V
Asciz	scala/io/BytePickle$$anonfun$ufixedList$1;
class	scala/io/BytePickle$$anonfun$ufixedList$1
Method	scala/io/BytePickle$$anonfun$ufixedList$1."<init>":()V
Asciz	scala/io/BytePickle$$anonfun$ufixedList$2;
class	scala/io/BytePickle$$anonfun$ufixedList$2
Method	scala/io/BytePickle$$anonfun$ufixedList$2."<init>":()V
NameAndType	ufixedList:(Lscala/io/BytePickle$PU;I)Lscala/io/BytePickle$PU;
Method	scala/io/BytePickle$.ufixedList:(Lscala/io/BytePickle$PU;I)Lscala/io/BytePickle$PU;
Asciz	scala/io/BytePickle$$anonfun$upair$1;
class	scala/io/BytePickle$$anonfun$upair$1
Method	scala/io/BytePickle$$anonfun$upair$1."<init>":()V
Asciz	scala/io/BytePickle$$anonfun$upair$2;
class	scala/io/BytePickle$$anonfun$upair$2
Method	scala/io/BytePickle$$anonfun$upair$2."<init>":(Lscala/io/BytePickle$PU;)V
Asciz	scala/io/BytePickle$$anonfun$uwrap$1;
class	scala/io/BytePickle$$anonfun$uwrap$1
Method	scala/io/BytePickle$$anonfun$uwrap$1."<init>":(Lscala/Function1;)V
Asciz	<A:Ljava/lang/Object;>(Lscala/io/BytePickle$PU<TA;>;I)Lscala/io/BytePickle$PU<Lscala/collection/immutable/List<TA;>;>;;
Asciz	bool;
Asciz	()Lscala/io/BytePickle$SPU;;
Asciz	scala/io/BytePickle$$anonfun$bool$1;
class	scala/io/BytePickle$$anonfun$bool$1
Method	scala/io/BytePickle$$anonfun$bool$1."<init>":()V
Asciz	scala/io/BytePickle$$anonfun$bool$2;
class	scala/io/BytePickle$$anonfun$bool$2
Method	scala/io/BytePickle$$anonfun$bool$2."<init>":()V
Asciz	()Lscala/io/BytePickle$SPU<Ljava/lang/Boolean;>;;
Asciz	bytearray;
Asciz	scala/io/BytePickle$$anonfun$bytearray$1;
class	scala/io/BytePickle$$anonfun$bytearray$1
Method	scala/io/BytePickle$$anonfun$bytearray$1."<init>":()V
Asciz	scala/io/BytePickle$$anonfun$bytearray$2;
class	scala/io/BytePickle$$anonfun$bytearray$2
Method	scala/io/BytePickle$$anonfun$bytearray$2."<init>":()V
Asciz	scala/io/BytePickle$$anon$9;
class	scala/io/BytePickle$$anon$9
Method	scala/io/BytePickle$$anon$9."<init>":()V
Asciz	()Lscala/io/BytePickle$SPU<[B>;;
Asciz	string;
Asciz	scala/io/BytePickle$$anonfun$string$1;
class	scala/io/BytePickle$$anonfun$string$1
Method	scala/io/BytePickle$$anonfun$string$1."<init>":()V
Asciz	scala/io/BytePickle$$anonfun$string$2;
class	scala/io/BytePickle$$anonfun$string$2
Method	scala/io/BytePickle$$anonfun$string$2."<init>":()V
Asciz	scala/io/BytePickle$$anon$3;
class	scala/io/BytePickle$$anon$3
Method	scala/io/BytePickle$$anon$3."<init>":(Lscala/io/BytePickle$SPU;)V
Asciz	()Lscala/io/BytePickle$SPU<Ljava/lang/String;>;;
Asciz	byte;
Asciz	()Lscala/io/BytePickle$SPU<Ljava/lang/Byte;>;;
Asciz	nat;
Asciz	()Lscala/io/BytePickle$SPU<Ljava/lang/Integer;>;;
Asciz	nat2Bytes;
Asciz	(I)[B;
Method	scala/collection/mutable/ArrayBuffer."<init>":()V
Asciz	scala/reflect/Manifest$;
class	scala/reflect/Manifest$
Asciz	Lscala/reflect/Manifest$;;
NameAndType	MODULE$:Lscala/reflect/Manifest$;
Field	scala/reflect/Manifest$.MODULE$:Lscala/reflect/Manifest$;
Asciz	Byte;
Asciz	()Lscala/reflect/AnyValManifest;;
NameAndType	Byte:()Lscala/reflect/AnyValManifest;
Method	scala/reflect/Manifest$.Byte:()Lscala/reflect/AnyValManifest;
Asciz	scala/collection/TraversableLike;
class	scala/collection/TraversableLike
Asciz	toArray;
Asciz	(Lscala/reflect/ClassManifest;)Ljava/lang/Object;;
NameAndType	toArray:(Lscala/reflect/ClassManifest;)Ljava/lang/Object;
InterfaceMethod	scala/collection/TraversableLike.toArray:(Lscala/reflect/ClassManifest;)Ljava/lang/Object;
Asciz	[B;
class	"[B"
Asciz	buf$1;
Asciz	Lscala/collection/mutable/ArrayBuffer;;
Asciz	appendByte;
Asciz	([BI)[B;
Asciz	scala/Array$;
class	scala/Array$
Asciz	Lscala/Array$;;
NameAndType	MODULE$:Lscala/Array$;
Field	scala/Array$.MODULE$:Lscala/Array$;
Asciz	scala/Predef$;
class	scala/Predef$
Asciz	Lscala/Predef$;;
NameAndType	MODULE$:Lscala/Predef$;
Field	scala/Predef$.MODULE$:Lscala/Predef$;
Asciz	wrapByteArray;
Asciz	([B)Lscala/collection/mutable/WrappedArray;;
NameAndType	wrapByteArray:([B)Lscala/collection/mutable/WrappedArray;
Method	scala/Predef$.wrapByteArray:([B)Lscala/collection/mutable/WrappedArray;
Asciz	apply;
Asciz	(BLscala/collection/Seq;)[B;
NameAndType	apply:(BLscala/collection/Seq;)[B
Method	scala/Array$.apply:(BLscala/collection/Seq;)[B
Asciz	[Ljava/lang/Object;;
class	"[Ljava/lang/Object;"
Asciz	wrapRefArray;
Asciz	([Ljava/lang/Object;)Lscala/collection/mutable/WrappedArray;;
NameAndType	wrapRefArray:([Ljava/lang/Object;)Lscala/collection/mutable/WrappedArray;
Method	scala/Predef$.wrapRefArray:([Ljava/lang/Object;)Lscala/collection/mutable/WrappedArray;
Asciz	concat;
Asciz	(Lscala/collection/Seq;Lscala/reflect/ClassManifest;)Ljava/lang/Object;;
NameAndType	concat:(Lscala/collection/Seq;Lscala/reflect/ClassManifest;)Ljava/lang/Object;
Method	scala/Array$.concat:(Lscala/collection/Seq;Lscala/reflect/ClassManifest;)Ljava/lang/Object;
Asciz	a;
Asciz	wrap;
Asciz	(Lscala/Function1;Lscala/Function1;Lscala/io/BytePickle$SPU;)Lscala/io/BytePickle$SPU;;
Asciz	i$2;
Asciz	j;
Asciz	<a:Ljava/lang/Object;b:Ljava/lang/Object;>(Lscala/Function1<Ta;Tb;>;Lscala/Function1<Tb;Ta;>;Lscala/io/BytePickle$SPU<Ta;>;)Lscala/io/BytePickle$SPU<Tb;>;;
Asciz	uwrap;
Asciz	(Lscala/Function1;Lscala/Function1;Lscala/io/BytePickle$PU;)Lscala/io/BytePickle$PU;;
Asciz	i$1;
Asciz	<a:Ljava/lang/Object;b:Ljava/lang/Object;>(Lscala/Function1<Ta;Tb;>;Lscala/Function1<Tb;Ta;>;Lscala/io/BytePickle$PU<Ta;>;)Lscala/io/BytePickle$PU<Tb;>;;
Asciz	triple;
Asciz	(Lscala/io/BytePickle$SPU;Lscala/io/BytePickle$SPU;Lscala/io/BytePickle$SPU;)Lscala/io/BytePickle$SPU;;
Asciz	scala/io/BytePickle$$anonfun$triple$1;
class	scala/io/BytePickle$$anonfun$triple$1
Method	scala/io/BytePickle$$anonfun$triple$1."<init>":()V
Asciz	scala/io/BytePickle$$anonfun$triple$2;
class	scala/io/BytePickle$$anonfun$triple$2
Asciz	(Lscala/io/BytePickle$SPU;Lscala/io/BytePickle$SPU;)V;
NameAndType	"<init>":(Lscala/io/BytePickle$SPU;Lscala/io/BytePickle$SPU;)V
Method	scala/io/BytePickle$$anonfun$triple$2."<init>":(Lscala/io/BytePickle$SPU;Lscala/io/BytePickle$SPU;)V
Asciz	pb$3;
Asciz	pc$1;
Asciz	<a:Ljava/lang/Object;b:Ljava/lang/Object;c:Ljava/lang/Object;>(Lscala/io/BytePickle$SPU<Ta;>;Lscala/io/BytePickle$SPU<Tb;>;Lscala/io/BytePickle$SPU<Tc;>;)Lscala/io/BytePickle$SPU<Lscala/Tuple3<Ta;Tb;Tc;>;>;;
Asciz	pair;
Asciz	(Lscala/io/BytePickle$SPU;Lscala/io/BytePickle$SPU;)Lscala/io/BytePickle$SPU;;
Asciz	pb$2;
Asciz	<a:Ljava/lang/Object;b:Ljava/lang/Object;>(Lscala/io/BytePickle$SPU<Ta;>;Lscala/io/BytePickle$SPU<Tb;>;)Lscala/io/BytePickle$SPU<Lscala/Tuple2<Ta;Tb;>;>;;
Asciz	upair;
Asciz	(Lscala/io/BytePickle$PU;Lscala/io/BytePickle$PU;)Lscala/io/BytePickle$PU;;
Asciz	pb$1;
Asciz	<a:Ljava/lang/Object;b:Ljava/lang/Object;>(Lscala/io/BytePickle$PU<Ta;>;Lscala/io/BytePickle$PU<Tb;>;)Lscala/io/BytePickle$PU<Lscala/Tuple2<Ta;Tb;>;>;;
Asciz	sequ;
Asciz	(Lscala/Function1;Lscala/io/BytePickle$SPU;Lscala/Function1;)Lscala/io/BytePickle$SPU;;
Asciz	f$2;
Asciz	pa$3;
Asciz	k$2;
Asciz	<t:Ljava/lang/Object;u:Ljava/lang/Object;>(Lscala/Function1<Tu;Tt;>;Lscala/io/BytePickle$SPU<Tt;>;Lscala/Function1<Tt;Lscala/io/BytePickle$SPU<Tu;>;>;)Lscala/io/BytePickle$SPU<Tu;>;;
Asciz	usequ;
Asciz	(Lscala/Function1;Lscala/io/BytePickle$PU;Lscala/Function1;)Lscala/io/BytePickle$PU;;
Asciz	f$1;
Asciz	pa$2;
Asciz	k$1;
Asciz	<t:Ljava/lang/Object;u:Ljava/lang/Object;>(Lscala/Function1<Tu;Tt;>;Lscala/io/BytePickle$PU<Tt;>;Lscala/Function1<Tt;Lscala/io/BytePickle$PU<Tu;>;>;)Lscala/io/BytePickle$PU<Tu;>;;
Asciz	lift;
Asciz	(Ljava/lang/Object;)Lscala/io/BytePickle$SPU;;
Asciz	x$5;
Asciz	<t:Ljava/lang/Object;>(Tt;)Lscala/io/BytePickle$SPU<Tt;>;;
Asciz	ulift;
Asciz	(Ljava/lang/Object;)Lscala/io/BytePickle$PU;;
Asciz	x$4;
Asciz	<t:Ljava/lang/Object;>(Tt;)Lscala/io/BytePickle$PU<Tt;>;;
Asciz	share;
Asciz	pa$1;
Asciz	<a:Ljava/lang/Object;>(Lscala/io/BytePickle$SPU<Ta;>;)Lscala/io/BytePickle$SPU<Ta;>;;
Asciz	unat;
Asciz	()Lscala/io/BytePickle$PU;;
Asciz	()Lscala/io/BytePickle$PU<Ljava/lang/Integer;>;;
Asciz	()I;
Asciz	refDef;
Asciz	scala/io/BytePickle$$anon$1;
class	scala/io/BytePickle$$anon$1
Method	scala/io/BytePickle$$anon$1."<init>":()V
Asciz	()Lscala/io/BytePickle$PU<Lscala/io/BytePickle$RefDef;>;;
Asciz	uunpickle;
Asciz	(Lscala/io/BytePickle$PU;[B)Ljava/lang/Object;;
Asciz	scala/io/BytePickle$PU;
class	scala/io/BytePickle$PU
Asciz	appU;
Asciz	([B)Lscala/Tuple2;;
NameAndType	appU:([B)Lscala/Tuple2;
Method	scala/io/BytePickle$PU.appU:([B)Lscala/Tuple2;
Asciz	stream;
Asciz	<T:Ljava/lang/Object;>(Lscala/io/BytePickle$PU<TT;>;[B)TT;;
Asciz	upickle;
Asciz	(Lscala/io/BytePickle$PU;Ljava/lang/Object;)[B;
Asciz	appP;
Asciz	(Ljava/lang/Object;[B)[B;
NameAndType	appP:(Ljava/lang/Object;[B)[B
Method	scala/io/BytePickle$PU.appP:(Ljava/lang/Object;[B)[B
Asciz	<T:Ljava/lang/Object;>(Lscala/io/BytePickle$PU<TT;>;TT;)[B;
Asciz	unpickle;
Asciz	(Lscala/io/BytePickle$SPU;[B)Ljava/lang/Object;;
Asciz	scala/io/BytePickle$UnPicklerState;
class	scala/io/BytePickle$UnPicklerState
Asciz	scala/io/BytePickle$UnPicklerEnv;
class	scala/io/BytePickle$UnPicklerEnv
Method	scala/io/BytePickle$UnPicklerEnv."<init>":()V
Asciz	([BLscala/io/BytePickle$UnPicklerEnv;)V;
NameAndType	"<init>":([BLscala/io/BytePickle$UnPicklerEnv;)V
Method	scala/io/BytePickle$UnPicklerState."<init>":([BLscala/io/BytePickle$UnPicklerEnv;)V
Asciz	scala/io/BytePickle$SPU;
class	scala/io/BytePickle$SPU
Asciz	(Lscala/io/BytePickle$UnPicklerState;)Lscala/Tuple2;;
NameAndType	appU:(Lscala/io/BytePickle$UnPicklerState;)Lscala/Tuple2;
Method	scala/io/BytePickle$SPU.appU:(Lscala/io/BytePickle$UnPicklerState;)Lscala/Tuple2;
Asciz	<T:Ljava/lang/Object;>(Lscala/io/BytePickle$SPU<TT;>;[B)TT;;
Asciz	pickle;
Asciz	(Lscala/io/BytePickle$SPU;Ljava/lang/Object;)[B;
Asciz	scala/io/BytePickle$PicklerState;
class	scala/io/BytePickle$PicklerState
Asciz	scala/io/BytePickle$PicklerEnv;
class	scala/io/BytePickle$PicklerEnv
Method	scala/io/BytePickle$PicklerEnv."<init>":()V
Asciz	([BLscala/io/BytePickle$PicklerEnv;)V;
NameAndType	"<init>":([BLscala/io/BytePickle$PicklerEnv;)V
Method	scala/io/BytePickle$PicklerState."<init>":([BLscala/io/BytePickle$PicklerEnv;)V
Asciz	(Ljava/lang/Object;Lscala/io/BytePickle$PicklerState;)Lscala/io/BytePickle$PicklerState;;
NameAndType	appP:(Ljava/lang/Object;Lscala/io/BytePickle$PicklerState;)Lscala/io/BytePickle$PicklerState;
Method	scala/io/BytePickle$SPU.appP:(Ljava/lang/Object;Lscala/io/BytePickle$PicklerState;)Lscala/io/BytePickle$PicklerState;
Asciz	()[B;
NameAndType	stream:()[B
Method	scala/io/BytePickle$PicklerState.stream:()[B
Asciz	<T:Ljava/lang/Object;>(Lscala/io/BytePickle$SPU<TT;>;TT;)[B;
Asciz	InnerClasses;
Asciz	scala/io/BytePickle;
class	scala/io/BytePickle
Asciz	PU;
Asciz	scala/io/BytePickle$Def;
class	scala/io/BytePickle$Def
Asciz	Def;
Asciz	scala/io/BytePickle$Ref;
class	scala/io/BytePickle$Ref
Asciz	Ref;
Asciz	SPU;
Asciz	scala/io/BytePickle$RefDef;
class	scala/io/BytePickle$RefDef
Asciz	RefDef;
Asciz	$anon$9;
Asciz	$anon$8;
Asciz	$anon$7;
Asciz	$anon$6;
Asciz	$anon$5;
Asciz	$anon$4;
Asciz	$anon$3;
Asciz	$anon$2;
Asciz	$anon$1;
Asciz	PicklerEnv;
Asciz	PicklerState;
Asciz	UnPicklerEnv;
Asciz	UnPicklerState;
Asciz	$anonfun$data$1;
Asciz	$anonfun$list$2;
Asciz	$anonfun$list$1;
Asciz	$anonfun$bool$2;
Asciz	$anonfun$bool$1;
Asciz	$anonfun$wrap$1;
Asciz	$anonfun$pair$2;
Asciz	$anonfun$pair$1;
Asciz	$anonfun$ulist$2;
Asciz	$anonfun$ulist$1;
Asciz	$anonfun$uwrap$1;
Asciz	$anonfun$upair$2;
Asciz	$anonfun$upair$1;
Asciz	$anonfun$string$2;
Asciz	$anonfun$string$1;
Asciz	$anonfun$triple$2;
Asciz	$anonfun$triple$1;
Asciz	$anonfun$fixedList$2;
Asciz	$anonfun$fixedList$1;
Asciz	$anonfun$bytearray$2;
Asciz	$anonfun$bytearray$1;
Asciz	$anonfun$ufixedList$2;
Asciz	$anonfun$ufixedList$1;
Asciz	scala/ScalaObject;
class	scala/ScalaObject

{
public static final scala.io.BytePickle$ MODULE$;
  Signature: Lscala/io/BytePickle$;

private final int DEF;
  Signature: I

private final int REF;
  Signature: I

public static {};
  Signature: ()V
  Code:
   Stack=1, Locals=0, Args_size=0
	new	class scala/io/BytePickle$
	invokespecial	Method "<init>":()V
	return
  Labels:

private scala.io.BytePickle$();
  Signature: ()V
  Code:
   Stack=2, Locals=1, Args_size=1
	aload_0
	invokespecial	Method java/lang/Object."<init>":()V
	aload_0
	putstatic	Field MODULE$:Lscala/io/BytePickle$;
	aload_0
	iconst_0
	putfield	Field REF:I
	aload_0
	iconst_1
	putfield	Field DEF:I
	return
  Labels:

public final scala.Tuple2 listToPair$2(scala.collection.immutable.List);
  Signature: (Lscala/collection/immutable/List;)Lscala/Tuple2;
  Code:
   Stack=4, Locals=5, Args_size=2
	aload_1
	instanceof	class scala/collection/immutable/$colon$colon
	ifeq	l1 // new
	aload_1
	checkcast	class scala/collection/immutable/$colon$colon
	astore_2
	aload_2
	getfield	Field scala/collection/immutable/$colon$colon.scala$collection$immutable$$colon$colon$$hd:Ljava/lang/Object;
	astore_3
	aload_2
	getfield	Field scala/collection/immutable/$colon$colon.tl:Lscala/collection/immutable/List;
	astore	4
	new	class scala/Tuple2
	dup
	aload_3
	aload	4
	invokespecial	Method scala/Tuple2."<init>":(Ljava/lang/Object;Ljava/lang/Object;)V
	areturn
l1	new	class scala/MatchError
	dup
	aload_1
	invokeinterface	InterfaceMethod scala/collection/SeqLike.toString:()Ljava/lang/String;
	invokespecial	Method scala/MatchError."<init>":(Ljava/lang/String;)V
	athrow
  Labels:
   	l1 = 34 // new
  LocalVariableTable: 
   Start  Length  Slot  Name   Signature
   0      48      0    this       Lscala/io/BytePickle$;
   0      48      1    l       Lscala/collection/immutable/List;
   12      21      2    temp26       Lscala/collection/immutable/$colon$colon;
   17      16      3    temp27       Ljava/lang/Object;
   23      10      4    temp28       Lscala/collection/immutable/List;


public final scala.collection.immutable.List pairToList$2(scala.Tuple2);
  Signature: (Lscala/Tuple2;)Lscala/collection/immutable/List;
  Code:
   Stack=2, Locals=3, Args_size=2
	aload_1
	invokevirtual	Method scala/Tuple2._1:()Ljava/lang/Object;
	astore_2
	aload_1
	invokevirtual	Method scala/Tuple2._2:()Ljava/lang/Object;
	checkcast	class scala/collection/immutable/List
	aload_2
	invokevirtual	Method scala/collection/immutable/List.$colon$colon:(Ljava/lang/Object;)Lscala/collection/immutable/List;
	areturn
  Labels:
  LocalVariableTable: 
   Start  Length  Slot  Name   Signature
   0      17      0    this       Lscala/io/BytePickle$;
   0      17      1    p       Lscala/Tuple2;


public final scala.Tuple2 listToPair$1(scala.collection.immutable.List);
  Signature: (Lscala/collection/immutable/List;)Lscala/Tuple2;
  Code:
   Stack=4, Locals=5, Args_size=2
	aload_1
	instanceof	class scala/collection/immutable/$colon$colon
	ifeq	l1 // new
	aload_1
	checkcast	class scala/collection/immutable/$colon$colon
	astore_2
	aload_2
	getfield	Field scala/collection/immutable/$colon$colon.scala$collection$immutable$$colon$colon$$hd:Ljava/lang/Object;
	astore_3
	aload_2
	getfield	Field scala/collection/immutable/$colon$colon.tl:Lscala/collection/immutable/List;
	astore	4
	new	class scala/Tuple2
	dup
	aload_3
	aload	4
	invokespecial	Method scala/Tuple2."<init>":(Ljava/lang/Object;Ljava/lang/Object;)V
	areturn
l1	new	class scala/MatchError
	dup
	aload_1
	invokeinterface	InterfaceMethod scala/collection/SeqLike.toString:()Ljava/lang/String;
	invokespecial	Method scala/MatchError."<init>":(Ljava/lang/String;)V
	athrow
  Labels:
   	l1 = 34 // new
  LocalVariableTable: 
   Start  Length  Slot  Name   Signature
   0      48      0    this       Lscala/io/BytePickle$;
   0      48      1    l       Lscala/collection/immutable/List;
   12      21      2    temp22       Lscala/collection/immutable/$colon$colon;
   17      16      3    temp23       Ljava/lang/Object;
   23      10      4    temp24       Lscala/collection/immutable/List;


public final scala.collection.immutable.List pairToList$1(scala.Tuple2);
  Signature: (Lscala/Tuple2;)Lscala/collection/immutable/List;
  Code:
   Stack=2, Locals=3, Args_size=2
	aload_1
	invokevirtual	Method scala/Tuple2._1:()Ljava/lang/Object;
	astore_2
	aload_1
	invokevirtual	Method scala/Tuple2._2:()Ljava/lang/Object;
	checkcast	class scala/collection/immutable/List
	aload_2
	invokevirtual	Method scala/collection/immutable/List.$colon$colon:(Ljava/lang/Object;)Lscala/collection/immutable/List;
	areturn
  Labels:
  LocalVariableTable: 
   Start  Length  Slot  Name   Signature
   0      17      0    this       Lscala/io/BytePickle$;
   0      17      1    p       Lscala/Tuple2;


public final boolean fromEnum$1(int);
  Signature: (I)Z
  Code:
   Stack=2, Locals=2, Args_size=2
	iload_1
	iconst_0
	if_icmpne	l1 // iconst_1
	iconst_0
	goto	l2 // ireturn
l1	iconst_1
l2	ireturn
  Labels:
   	l1 = 9 // iconst_1
   	l2 = 10 // ireturn
  LocalVariableTable: 
   Start  Length  Slot  Name   Signature
   0      11      0    this       Lscala/io/BytePickle$;
   0      11      1    n       I


public final int toEnum$1(boolean);
  Signature: (Z)I
  Code:
   Stack=1, Locals=2, Args_size=2
	iload_1
	ifeq	l1 // iconst_0
	iconst_1
	goto	l2 // ireturn
l1	iconst_0
l2	ireturn
  Labels:
   	l1 = 8 // iconst_0
   	l2 = 9 // ireturn
  LocalVariableTable: 
   Start  Length  Slot  Name   Signature
   0      10      0    this       Lscala/io/BytePickle$;
   0      10      1    b       Z


private final void writeNatPrefix$1(int, scala.collection.mutable.ArrayBuffer);
  Signature: (ILscala/collection/mutable/ArrayBuffer;)V
  Code:
   Stack=3, Locals=5, Args_size=3
	iload_1
	ldc	int 7
	iushr
	istore_3
	iload_3
	iconst_0
	if_icmpeq	l1 // aload_2
	aload_0
	iload_3
	aload_2
	invokespecial	Method writeNatPrefix$1:(ILscala/collection/mutable/ArrayBuffer;)V
l1	aload_2
	iload_1
	ldc	int 127
	iand
	ldc	int 128
	ior
	i2b
	istore	4
	iload	4
	invokestatic	Method scala/runtime/BoxesRunTime.boxToByte:(B)Ljava/lang/Byte;
	invokevirtual	Method scala/collection/mutable/ArrayBuffer.$plus$eq:(Ljava/lang/Object;)Lscala/collection/mutable/ArrayBuffer;
	pop
	return
  Labels:
   	l1 = 16 // aload_2
  LocalVariableTable: 
   Start  Length  Slot  Name   Signature
   0      37      0    this       Lscala/io/BytePickle$;
   0      37      1    x       I
   5      31      3    y       I


public final java.lang.Object trd$1(scala.Tuple3);
  Signature: (Lscala/Tuple3;)Ljava/lang/Object;
  Code:
   Stack=1, Locals=2, Args_size=2
	aload_1
	invokevirtual	Method scala/Tuple3._3:()Ljava/lang/Object;
	areturn
  Labels:
  LocalVariableTable: 
   Start  Length  Slot  Name   Signature
   0      5      0    this       Lscala/io/BytePickle$;
   0      5      1    p       Lscala/Tuple3;


public final java.lang.Object snd$3(scala.Tuple3);
  Signature: (Lscala/Tuple3;)Ljava/lang/Object;
  Code:
   Stack=1, Locals=2, Args_size=2
	aload_1
	invokevirtual	Method scala/Tuple3._2:()Ljava/lang/Object;
	areturn
  Labels:
  LocalVariableTable: 
   Start  Length  Slot  Name   Signature
   0      5      0    this       Lscala/io/BytePickle$;
   0      5      1    p       Lscala/Tuple3;


public final java.lang.Object fst$3(scala.Tuple3);
  Signature: (Lscala/Tuple3;)Ljava/lang/Object;
  Code:
   Stack=1, Locals=2, Args_size=2
	aload_1
	invokevirtual	Method scala/Tuple3._1:()Ljava/lang/Object;
	areturn
  Labels:
  LocalVariableTable: 
   Start  Length  Slot  Name   Signature
   0      5      0    this       Lscala/io/BytePickle$;
   0      5      1    p       Lscala/Tuple3;


public final java.lang.Object snd$2(scala.Tuple2);
  Signature: (Lscala/Tuple2;)Ljava/lang/Object;
  Code:
   Stack=1, Locals=2, Args_size=2
	aload_1
	invokevirtual	Method scala/Tuple2._2:()Ljava/lang/Object;
	areturn
  Labels:
  LocalVariableTable: 
   Start  Length  Slot  Name   Signature
   0      5      0    this       Lscala/io/BytePickle$;
   0      5      1    p       Lscala/Tuple2;


public final java.lang.Object fst$2(scala.Tuple2);
  Signature: (Lscala/Tuple2;)Ljava/lang/Object;
  Code:
   Stack=1, Locals=2, Args_size=2
	aload_1
	invokevirtual	Method scala/Tuple2._1:()Ljava/lang/Object;
	areturn
  Labels:
  LocalVariableTable: 
   Start  Length  Slot  Name   Signature
   0      5      0    this       Lscala/io/BytePickle$;
   0      5      1    p       Lscala/Tuple2;


public final java.lang.Object snd$1(scala.Tuple2);
  Signature: (Lscala/Tuple2;)Ljava/lang/Object;
  Code:
   Stack=1, Locals=2, Args_size=2
	aload_1
	invokevirtual	Method scala/Tuple2._2:()Ljava/lang/Object;
	areturn
  Labels:
  LocalVariableTable: 
   Start  Length  Slot  Name   Signature
   0      5      0    this       Lscala/io/BytePickle$;
   0      5      1    p       Lscala/Tuple2;


public final java.lang.Object fst$1(scala.Tuple2);
  Signature: (Lscala/Tuple2;)Ljava/lang/Object;
  Code:
   Stack=1, Locals=2, Args_size=2
	aload_1
	invokevirtual	Method scala/Tuple2._1:()Ljava/lang/Object;
	areturn
  Labels:
  LocalVariableTable: 
   Start  Length  Slot  Name   Signature
   0      5      0    this       Lscala/io/BytePickle$;
   0      5      1    p       Lscala/Tuple2;


public scala.io.BytePickle$SPU data(scala.Function1, scala.collection.immutable.List);
  Signature: (Lscala/Function1;Lscala/collection/immutable/List;)Lscala/io/BytePickle$SPU;
  Code:
   Stack=5, Locals=5, Args_size=3
	new	class scala/io/BytePickle$$anon$8
	dup
	invokespecial	Method scala/io/BytePickle$$anon$8."<init>":()V
	new	class scala/io/BytePickle$$anonfun$data$1
	dup
	aload_2
	invokespecial	Method scala/io/BytePickle$$anonfun$data$1."<init>":(Lscala/collection/immutable/List;)V
	astore	4
	astore_3
	new	class scala/io/BytePickle$$anon$7
	dup
	aload_1
	aload_3
	aload	4
	invokespecial	Method scala/io/BytePickle$$anon$7."<init>":(Lscala/Function1;Lscala/io/BytePickle$SPU;Lscala/Function1;)V
	areturn
  Labels:
  LocalVariableTable: 
   Start  Length  Slot  Name   Signature
   0      30      0    this       Lscala/io/BytePickle$;
   0      30      1    tag       Lscala/Function1;
   0      30      2    ps$1       Lscala/collection/immutable/List;

  Signature: length = 0x2
   00 FFFFFF93 

public scala.io.BytePickle$PU ulist(scala.io.BytePickle$PU);
  Signature: (Lscala/io/BytePickle$PU;)Lscala/io/BytePickle$PU;
  Code:
   Stack=5, Locals=5, Args_size=2
	new	class scala/io/BytePickle$$anonfun$ulist$1
	dup
	invokespecial	Method scala/io/BytePickle$$anonfun$ulist$1."<init>":()V
	new	class scala/io/BytePickle$$anon$2
	dup
	invokespecial	Method scala/io/BytePickle$$anon$2."<init>":()V
	new	class scala/io/BytePickle$$anonfun$ulist$2
	dup
	aload_1
	invokespecial	Method scala/io/BytePickle$$anonfun$ulist$2."<init>":(Lscala/io/BytePickle$PU;)V
	astore	4
	astore_3
	astore_2
	new	class scala/io/BytePickle$$anon$6
	dup
	aload_2
	aload_3
	aload	4
	invokespecial	Method scala/io/BytePickle$$anon$6."<init>":(Lscala/Function1;Lscala/io/BytePickle$PU;Lscala/Function1;)V
	areturn
  Labels:
  LocalVariableTable: 
   Start  Length  Slot  Name   Signature
   0      38      0    this       Lscala/io/BytePickle$;
   0      38      1    pa$5       Lscala/io/BytePickle$PU;

  Signature: length = 0x2
   00 FFFFFFA9 

public scala.io.BytePickle$SPU list(scala.io.BytePickle$SPU);
  Signature: (Lscala/io/BytePickle$SPU;)Lscala/io/BytePickle$SPU;
  Code:
   Stack=5, Locals=5, Args_size=2
	new	class scala/io/BytePickle$$anonfun$list$1
	dup
	invokespecial	Method scala/io/BytePickle$$anonfun$list$1."<init>":()V
	new	class scala/io/BytePickle$$anon$8
	dup
	invokespecial	Method scala/io/BytePickle$$anon$8."<init>":()V
	new	class scala/io/BytePickle$$anonfun$list$2
	dup
	aload_1
	invokespecial	Method scala/io/BytePickle$$anonfun$list$2."<init>":(Lscala/io/BytePickle$SPU;)V
	astore	4
	astore_3
	astore_2
	new	class scala/io/BytePickle$$anon$7
	dup
	aload_2
	aload_3
	aload	4
	invokespecial	Method scala/io/BytePickle$$anon$7."<init>":(Lscala/Function1;Lscala/io/BytePickle$SPU;Lscala/Function1;)V
	areturn
  Labels:
  LocalVariableTable: 
   Start  Length  Slot  Name   Signature
   0      38      0    this       Lscala/io/BytePickle$;
   0      38      1    pa$4       Lscala/io/BytePickle$SPU;

  Signature: length = 0x2
   00 FFFFFFB6 

public scala.io.BytePickle$SPU fixedList(scala.io.BytePickle$SPU, int);
  Signature: (Lscala/io/BytePickle$SPU;I)Lscala/io/BytePickle$SPU;
  Code:
   Stack=7, Locals=11, Args_size=3
	iload_2
	iconst_0
	if_icmpne	l1 // new
	getstatic	Field scala/collection/immutable/Nil$.MODULE$:Lscala/collection/immutable/Nil$;
	astore_3
	new	class scala/io/BytePickle$$anon$5
	dup
	aload_3
	invokespecial	Method scala/io/BytePickle$$anon$5."<init>":(Ljava/lang/Object;)V
	goto	l2 // areturn
l1	new	class scala/io/BytePickle$$anonfun$fixedList$1
	dup
	invokespecial	Method scala/io/BytePickle$$anonfun$fixedList$1."<init>":()V
	new	class scala/io/BytePickle$$anonfun$fixedList$2
	dup
	invokespecial	Method scala/io/BytePickle$$anonfun$fixedList$2."<init>":()V
	aload_0
	aload_1
	iload_2
	iconst_1
	isub
	invokevirtual	Method fixedList:(Lscala/io/BytePickle$SPU;I)Lscala/io/BytePickle$SPU;
	astore	4
	new	class scala/io/BytePickle$$anonfun$pair$1
	dup
	invokespecial	Method scala/io/BytePickle$$anonfun$pair$1."<init>":()V
	new	class scala/io/BytePickle$$anonfun$pair$2
	dup
	aload	4
	invokespecial	Method scala/io/BytePickle$$anonfun$pair$2."<init>":(Lscala/io/BytePickle$SPU;)V
	astore	6
	astore	5
	new	class scala/io/BytePickle$$anon$7
	dup
	aload	5
	aload_1
	aload	6
	invokespecial	Method scala/io/BytePickle$$anon$7."<init>":(Lscala/Function1;Lscala/io/BytePickle$SPU;Lscala/Function1;)V
	astore	9
	astore	8
	astore	7
	new	class scala/io/BytePickle$$anonfun$wrap$1
	dup
	aload	7
	invokespecial	Method scala/io/BytePickle$$anonfun$wrap$1."<init>":(Lscala/Function1;)V
	astore	10
	new	class scala/io/BytePickle$$anon$7
	dup
	aload	8
	aload	9
	aload	10
	invokespecial	Method scala/io/BytePickle$$anon$7."<init>":(Lscala/Function1;Lscala/io/BytePickle$SPU;Lscala/Function1;)V
l2	areturn
  Labels:
   	l1 = 20 // new
   	l2 = 106 // areturn
  LocalVariableTable: 
   Start  Length  Slot  Name   Signature
   0      107      0    this       Lscala/io/BytePickle$;
   0      107      1    pa       Lscala/io/BytePickle$SPU;
   0      107      2    n       I

  Signature: length = 0x2
   00 FFFFFFD7 

public scala.io.BytePickle$PU ufixedList(scala.io.BytePickle$PU, int);
  Signature: (Lscala/io/BytePickle$PU;I)Lscala/io/BytePickle$PU;
  Code:
   Stack=7, Locals=11, Args_size=3
	iload_2
	iconst_0
	if_icmpne	l1 // new
	getstatic	Field scala/collection/immutable/Nil$.MODULE$:Lscala/collection/immutable/Nil$;
	astore_3
	new	class scala/io/BytePickle$$anon$4
	dup
	aload_3
	invokespecial	Method scala/io/BytePickle$$anon$4."<init>":(Ljava/lang/Object;)V
	goto	l2 // areturn
l1	new	class scala/io/BytePickle$$anonfun$ufixedList$1
	dup
	invokespecial	Method scala/io/BytePickle$$anonfun$ufixedList$1."<init>":()V
	new	class scala/io/BytePickle$$anonfun$ufixedList$2
	dup
	invokespecial	Method scala/io/BytePickle$$anonfun$ufixedList$2."<init>":()V
	aload_0
	aload_1
	iload_2
	iconst_1
	isub
	invokevirtual	Method ufixedList:(Lscala/io/BytePickle$PU;I)Lscala/io/BytePickle$PU;
	astore	4
	new	class scala/io/BytePickle$$anonfun$upair$1
	dup
	invokespecial	Method scala/io/BytePickle$$anonfun$upair$1."<init>":()V
	new	class scala/io/BytePickle$$anonfun$upair$2
	dup
	aload	4
	invokespecial	Method scala/io/BytePickle$$anonfun$upair$2."<init>":(Lscala/io/BytePickle$PU;)V
	astore	6
	astore	5
	new	class scala/io/BytePickle$$anon$6
	dup
	aload	5
	aload_1
	aload	6
	invokespecial	Method scala/io/BytePickle$$anon$6."<init>":(Lscala/Function1;Lscala/io/BytePickle$PU;Lscala/Function1;)V
	astore	9
	astore	8
	astore	7
	new	class scala/io/BytePickle$$anonfun$uwrap$1
	dup
	aload	7
	invokespecial	Method scala/io/BytePickle$$anonfun$uwrap$1."<init>":(Lscala/Function1;)V
	astore	10
	new	class scala/io/BytePickle$$anon$6
	dup
	aload	8
	aload	9
	aload	10
	invokespecial	Method scala/io/BytePickle$$anon$6."<init>":(Lscala/Function1;Lscala/io/BytePickle$PU;Lscala/Function1;)V
l2	areturn
  Labels:
   	l1 = 20 // new
   	l2 = 106 // areturn
  LocalVariableTable: 
   Start  Length  Slot  Name   Signature
   0      107      0    this       Lscala/io/BytePickle$;
   0      107      1    pa       Lscala/io/BytePickle$PU;
   0      107      2    n       I

  Signature: length = 0x2
   00 FFFFFFEE 

public scala.io.BytePickle$SPU bool();
  Signature: ()Lscala/io/BytePickle$SPU;
  Code:
   Stack=5, Locals=5, Args_size=1
	new	class scala/io/BytePickle$$anonfun$bool$1
	dup
	invokespecial	Method scala/io/BytePickle$$anonfun$bool$1."<init>":()V
	new	class scala/io/BytePickle$$anonfun$bool$2
	dup
	invokespecial	Method scala/io/BytePickle$$anonfun$bool$2."<init>":()V
	new	class scala/io/BytePickle$$anon$8
	dup
	invokespecial	Method scala/io/BytePickle$$anon$8."<init>":()V
	astore_3
	astore_2
	astore_1
	new	class scala/io/BytePickle$$anonfun$wrap$1
	dup
	aload_1
	invokespecial	Method scala/io/BytePickle$$anonfun$wrap$1."<init>":(Lscala/Function1;)V
	astore	4
	new	class scala/io/BytePickle$$anon$7
	dup
	aload_2
	aload_3
	aload	4
	invokespecial	Method scala/io/BytePickle$$anon$7."<init>":(Lscala/Function1;Lscala/io/BytePickle$SPU;Lscala/Function1;)V
	areturn
  Labels:
  LocalVariableTable: 
   Start  Length  Slot  Name   Signature
   0      46      0    this       Lscala/io/BytePickle$;

  Signature: length = 0x2
   00 FFFFFFF7 

public scala.io.BytePickle$SPU bytearray();
  Signature: ()Lscala/io/BytePickle$SPU;
  Code:
   Stack=7, Locals=9, Args_size=1
	new	class scala/io/BytePickle$$anonfun$bytearray$1
	dup
	invokespecial	Method scala/io/BytePickle$$anonfun$bytearray$1."<init>":()V
	new	class scala/io/BytePickle$$anonfun$bytearray$2
	dup
	invokespecial	Method scala/io/BytePickle$$anonfun$bytearray$2."<init>":()V
	new	class scala/io/BytePickle$$anon$9
	dup
	invokespecial	Method scala/io/BytePickle$$anon$9."<init>":()V
	astore_1
	new	class scala/io/BytePickle$$anonfun$list$1
	dup
	invokespecial	Method scala/io/BytePickle$$anonfun$list$1."<init>":()V
	new	class scala/io/BytePickle$$anon$8
	dup
	invokespecial	Method scala/io/BytePickle$$anon$8."<init>":()V
	new	class scala/io/BytePickle$$anonfun$list$2
	dup
	aload_1
	invokespecial	Method scala/io/BytePickle$$anonfun$list$2."<init>":(Lscala/io/BytePickle$SPU;)V
	astore	4
	astore_3
	astore_2
	new	class scala/io/BytePickle$$anon$7
	dup
	aload_2
	aload_3
	aload	4
	invokespecial	Method scala/io/BytePickle$$anon$7."<init>":(Lscala/Function1;Lscala/io/BytePickle$SPU;Lscala/Function1;)V
	astore	7
	astore	6
	astore	5
	new	class scala/io/BytePickle$$anonfun$wrap$1
	dup
	aload	5
	invokespecial	Method scala/io/BytePickle$$anonfun$wrap$1."<init>":(Lscala/Function1;)V
	astore	8
	new	class scala/io/BytePickle$$anon$7
	dup
	aload	6
	aload	7
	aload	8
	invokespecial	Method scala/io/BytePickle$$anon$7."<init>":(Lscala/Function1;Lscala/io/BytePickle$SPU;Lscala/Function1;)V
	areturn
  Labels:
  LocalVariableTable: 
   Start  Length  Slot  Name   Signature
   0      90      0    this       Lscala/io/BytePickle$;

  Signature: length = 0x2
   01 02 

public scala.io.BytePickle$SPU string();
  Signature: ()Lscala/io/BytePickle$SPU;
  Code:
   Stack=9, Locals=14, Args_size=1
	new	class scala/io/BytePickle$$anonfun$string$1
	dup
	invokespecial	Method scala/io/BytePickle$$anonfun$string$1."<init>":()V
	new	class scala/io/BytePickle$$anonfun$string$2
	dup
	invokespecial	Method scala/io/BytePickle$$anonfun$string$2."<init>":()V
	new	class scala/io/BytePickle$$anonfun$bytearray$1
	dup
	invokespecial	Method scala/io/BytePickle$$anonfun$bytearray$1."<init>":()V
	new	class scala/io/BytePickle$$anonfun$bytearray$2
	dup
	invokespecial	Method scala/io/BytePickle$$anonfun$bytearray$2."<init>":()V
	new	class scala/io/BytePickle$$anon$9
	dup
	invokespecial	Method scala/io/BytePickle$$anon$9."<init>":()V
	astore_1
	new	class scala/io/BytePickle$$anonfun$list$1
	dup
	invokespecial	Method scala/io/BytePickle$$anonfun$list$1."<init>":()V
	new	class scala/io/BytePickle$$anon$8
	dup
	invokespecial	Method scala/io/BytePickle$$anon$8."<init>":()V
	new	class scala/io/BytePickle$$anonfun$list$2
	dup
	aload_1
	invokespecial	Method scala/io/BytePickle$$anonfun$list$2."<init>":(Lscala/io/BytePickle$SPU;)V
	astore	4
	astore_3
	astore_2
	new	class scala/io/BytePickle$$anon$7
	dup
	aload_2
	aload_3
	aload	4
	invokespecial	Method scala/io/BytePickle$$anon$7."<init>":(Lscala/Function1;Lscala/io/BytePickle$SPU;Lscala/Function1;)V
	astore	7
	astore	6
	astore	5
	new	class scala/io/BytePickle$$anonfun$wrap$1
	dup
	aload	5
	invokespecial	Method scala/io/BytePickle$$anonfun$wrap$1."<init>":(Lscala/Function1;)V
	astore	8
	new	class scala/io/BytePickle$$anon$7
	dup
	aload	6
	aload	7
	aload	8
	invokespecial	Method scala/io/BytePickle$$anon$7."<init>":(Lscala/Function1;Lscala/io/BytePickle$SPU;Lscala/Function1;)V
	astore	11
	astore	10
	astore	9
	new	class scala/io/BytePickle$$anonfun$wrap$1
	dup
	aload	9
	invokespecial	Method scala/io/BytePickle$$anonfun$wrap$1."<init>":(Lscala/Function1;)V
	astore	12
	new	class scala/io/BytePickle$$anon$7
	dup
	aload	10
	aload	11
	aload	12
	invokespecial	Method scala/io/BytePickle$$anon$7."<init>":(Lscala/Function1;Lscala/io/BytePickle$SPU;Lscala/Function1;)V
	astore	13
	new	class scala/io/BytePickle$$anon$3
	dup
	aload	13
	invokespecial	Method scala/io/BytePickle$$anon$3."<init>":(Lscala/io/BytePickle$SPU;)V
	areturn
  Labels:
  LocalVariableTable: 
   Start  Length  Slot  Name   Signature
   0      145      0    this       Lscala/io/BytePickle$;

  Signature: length = 0x2
   01 0D 

public scala.io.BytePickle$SPU byte();
  Signature: ()Lscala/io/BytePickle$SPU;
  Code:
   Stack=2, Locals=1, Args_size=1
	new	class scala/io/BytePickle$$anon$9
	dup
	invokespecial	Method scala/io/BytePickle$$anon$9."<init>":()V
	areturn
  Labels:
  Signature: length = 0x2
   01 0F 

public scala.io.BytePickle$SPU nat();
  Signature: ()Lscala/io/BytePickle$SPU;
  Code:
   Stack=2, Locals=1, Args_size=1
	new	class scala/io/BytePickle$$anon$8
	dup
	invokespecial	Method scala/io/BytePickle$$anon$8."<init>":()V
	areturn
  Labels:
  Signature: length = 0x2
   01 11 

public byte[] nat2Bytes(int);
  Signature: (I)[B
  Code:
   Stack=3, Locals=5, Args_size=2
	new	class scala/collection/mutable/ArrayBuffer
	dup
	invokespecial	Method scala/collection/mutable/ArrayBuffer."<init>":()V
	astore_2
	iload_1
	ldc	int 7
	iushr
	istore_3
	iload_3
	iconst_0
	if_icmpeq	l1 // aload_2
	aload_0
	iload_3
	aload_2
	invokespecial	Method writeNatPrefix$1:(ILscala/collection/mutable/ArrayBuffer;)V
l1	aload_2
	iload_1
	ldc	int 127
	iand
	i2b
	istore	4
	iload	4
	invokestatic	Method scala/runtime/BoxesRunTime.boxToByte:(B)Ljava/lang/Byte;
	invokevirtual	Method scala/collection/mutable/ArrayBuffer.$plus$eq:(Ljava/lang/Object;)Lscala/collection/mutable/ArrayBuffer;
	pop
	aload_2
	getstatic	Field scala/reflect/Manifest$.MODULE$:Lscala/reflect/Manifest$;
	invokevirtual	Method scala/reflect/Manifest$.Byte:()Lscala/reflect/AnyValManifest;
	invokeinterface	InterfaceMethod scala/collection/TraversableLike.toArray:(Lscala/reflect/ClassManifest;)Ljava/lang/Object;
	checkcast	class "[B"
	areturn
  Labels:
   	l1 = 24 // aload_2
  LocalVariableTable: 
   Start  Length  Slot  Name   Signature
   0      57      0    this       Lscala/io/BytePickle$;
   0      57      1    x       I
   8      48      2    buf$1       Lscala/collection/mutable/ArrayBuffer;
   13      43      3    y       I


public byte[] appendByte(byte[], int);
  Signature: ([BI)[B
  Code:
   Stack=9, Locals=3, Args_size=3
	getstatic	Field scala/Array$.MODULE$:Lscala/Array$;
	getstatic	Field scala/Predef$.MODULE$:Lscala/Predef$;
	iconst_2
	anewarray	class "[B"
	dup
	iconst_0
	aload_1
	aastore
	dup
	iconst_1
	getstatic	Field scala/Array$.MODULE$:Lscala/Array$;
	iload_2
	i2b
	getstatic	Field scala/Predef$.MODULE$:Lscala/Predef$;
	iconst_0
	newarray byte
	invokevirtual	Method scala/Predef$.wrapByteArray:([B)Lscala/collection/mutable/WrappedArray;
	invokevirtual	Method scala/Array$.apply:(BLscala/collection/Seq;)[B
	aastore
	checkcast	class "[Ljava/lang/Object;"
	invokevirtual	Method scala/Predef$.wrapRefArray:([Ljava/lang/Object;)Lscala/collection/mutable/WrappedArray;
	getstatic	Field scala/reflect/Manifest$.MODULE$:Lscala/reflect/Manifest$;
	invokevirtual	Method scala/reflect/Manifest$.Byte:()Lscala/reflect/AnyValManifest;
	invokevirtual	Method scala/Array$.concat:(Lscala/collection/Seq;Lscala/reflect/ClassManifest;)Ljava/lang/Object;
	checkcast	class "[B"
	areturn
  Labels:
  LocalVariableTable: 
   Start  Length  Slot  Name   Signature
   0      53      0    this       Lscala/io/BytePickle$;
   0      53      1    a       [B
   0      53      2    b       I


public scala.io.BytePickle$SPU wrap(scala.Function1, scala.Function1, scala.io.BytePickle$SPU);
  Signature: (Lscala/Function1;Lscala/Function1;Lscala/io/BytePickle$SPU;)Lscala/io/BytePickle$SPU;
  Code:
   Stack=5, Locals=5, Args_size=4
	new	class scala/io/BytePickle$$anonfun$wrap$1
	dup
	aload_1
	invokespecial	Method scala/io/BytePickle$$anonfun$wrap$1."<init>":(Lscala/Function1;)V
	astore	4
	new	class scala/io/BytePickle$$anon$7
	dup
	aload_2
	aload_3
	aload	4
	invokespecial	Method scala/io/BytePickle$$anon$7."<init>":(Lscala/Function1;Lscala/io/BytePickle$SPU;Lscala/Function1;)V
	areturn
  Labels:
  LocalVariableTable: 
   Start  Length  Slot  Name   Signature
   0      22      0    this       Lscala/io/BytePickle$;
   0      22      1    i$2       Lscala/Function1;
   0      22      2    j       Lscala/Function1;
   0      22      3    pa       Lscala/io/BytePickle$SPU;

  Signature: length = 0x2
   01 4B 

public scala.io.BytePickle$PU uwrap(scala.Function1, scala.Function1, scala.io.BytePickle$PU);
  Signature: (Lscala/Function1;Lscala/Function1;Lscala/io/BytePickle$PU;)Lscala/io/BytePickle$PU;
  Code:
   Stack=5, Locals=5, Args_size=4
	new	class scala/io/BytePickle$$anonfun$uwrap$1
	dup
	aload_1
	invokespecial	Method scala/io/BytePickle$$anonfun$uwrap$1."<init>":(Lscala/Function1;)V
	astore	4
	new	class scala/io/BytePickle$$anon$6
	dup
	aload_2
	aload_3
	aload	4
	invokespecial	Method scala/io/BytePickle$$anon$6."<init>":(Lscala/Function1;Lscala/io/BytePickle$PU;Lscala/Function1;)V
	areturn
  Labels:
  LocalVariableTable: 
   Start  Length  Slot  Name   Signature
   0      22      0    this       Lscala/io/BytePickle$;
   0      22      1    i$1       Lscala/Function1;
   0      22      2    j       Lscala/Function1;
   0      22      3    pa       Lscala/io/BytePickle$PU;

  Signature: length = 0x2
   01 4F 

public scala.io.BytePickle$SPU triple(scala.io.BytePickle$SPU, scala.io.BytePickle$SPU, scala.io.BytePickle$SPU);
  Signature: (Lscala/io/BytePickle$SPU;Lscala/io/BytePickle$SPU;Lscala/io/BytePickle$SPU;)Lscala/io/BytePickle$SPU;
  Code:
   Stack=5, Locals=6, Args_size=4
	new	class scala/io/BytePickle$$anonfun$triple$1
	dup
	invokespecial	Method scala/io/BytePickle$$anonfun$triple$1."<init>":()V
	new	class scala/io/BytePickle$$anonfun$triple$2
	dup
	aload_2
	aload_3
	invokespecial	Method scala/io/BytePickle$$anonfun$triple$2."<init>":(Lscala/io/BytePickle$SPU;Lscala/io/BytePickle$SPU;)V
	astore	5
	astore	4
	new	class scala/io/BytePickle$$anon$7
	dup
	aload	4
	aload_1
	aload	5
	invokespecial	Method scala/io/BytePickle$$anon$7."<init>":(Lscala/Function1;Lscala/io/BytePickle$SPU;Lscala/Function1;)V
	areturn
  Labels:
  LocalVariableTable: 
   Start  Length  Slot  Name   Signature
   0      33      0    this       Lscala/io/BytePickle$;
   0      33      1    pa       Lscala/io/BytePickle$SPU;
   0      33      2    pb$3       Lscala/io/BytePickle$SPU;
   0      33      3    pc$1       Lscala/io/BytePickle$SPU;

  Signature: length = 0x2
   01 5C 

public scala.io.BytePickle$SPU pair(scala.io.BytePickle$SPU, scala.io.BytePickle$SPU);
  Signature: (Lscala/io/BytePickle$SPU;Lscala/io/BytePickle$SPU;)Lscala/io/BytePickle$SPU;
  Code:
   Stack=5, Locals=5, Args_size=3
	new	class scala/io/BytePickle$$anonfun$pair$1
	dup
	invokespecial	Method scala/io/BytePickle$$anonfun$pair$1."<init>":()V
	new	class scala/io/BytePickle$$anonfun$pair$2
	dup
	aload_2
	invokespecial	Method scala/io/BytePickle$$anonfun$pair$2."<init>":(Lscala/io/BytePickle$SPU;)V
	astore	4
	astore_3
	new	class scala/io/BytePickle$$anon$7
	dup
	aload_3
	aload_1
	aload	4
	invokespecial	Method scala/io/BytePickle$$anon$7."<init>":(Lscala/Function1;Lscala/io/BytePickle$SPU;Lscala/Function1;)V
	areturn
  Labels:
  LocalVariableTable: 
   Start  Length  Slot  Name   Signature
   0      30      0    this       Lscala/io/BytePickle$;
   0      30      1    pa       Lscala/io/BytePickle$SPU;
   0      30      2    pb$2       Lscala/io/BytePickle$SPU;

  Signature: length = 0x2
   01 60 

public scala.io.BytePickle$PU upair(scala.io.BytePickle$PU, scala.io.BytePickle$PU);
  Signature: (Lscala/io/BytePickle$PU;Lscala/io/BytePickle$PU;)Lscala/io/BytePickle$PU;
  Code:
   Stack=5, Locals=5, Args_size=3
	new	class scala/io/BytePickle$$anonfun$upair$1
	dup
	invokespecial	Method scala/io/BytePickle$$anonfun$upair$1."<init>":()V
	new	class scala/io/BytePickle$$anonfun$upair$2
	dup
	aload_2
	invokespecial	Method scala/io/BytePickle$$anonfun$upair$2."<init>":(Lscala/io/BytePickle$PU;)V
	astore	4
	astore_3
	new	class scala/io/BytePickle$$anon$6
	dup
	aload_3
	aload_1
	aload	4
	invokespecial	Method scala/io/BytePickle$$anon$6."<init>":(Lscala/Function1;Lscala/io/BytePickle$PU;Lscala/Function1;)V
	areturn
  Labels:
  LocalVariableTable: 
   Start  Length  Slot  Name   Signature
   0      30      0    this       Lscala/io/BytePickle$;
   0      30      1    pa       Lscala/io/BytePickle$PU;
   0      30      2    pb$1       Lscala/io/BytePickle$PU;

  Signature: length = 0x2
   01 64 

public scala.io.BytePickle$SPU sequ(scala.Function1, scala.io.BytePickle$SPU, scala.Function1);
  Signature: (Lscala/Function1;Lscala/io/BytePickle$SPU;Lscala/Function1;)Lscala/io/BytePickle$SPU;
  Code:
   Stack=5, Locals=4, Args_size=4
	new	class scala/io/BytePickle$$anon$7
	dup
	aload_1
	aload_2
	aload_3
	invokespecial	Method scala/io/BytePickle$$anon$7."<init>":(Lscala/Function1;Lscala/io/BytePickle$SPU;Lscala/Function1;)V
	areturn
  Labels:
  LocalVariableTable: 
   Start  Length  Slot  Name   Signature
   0      11      0    this       Lscala/io/BytePickle$;
   0      11      1    f$2       Lscala/Function1;
   0      11      2    pa$3       Lscala/io/BytePickle$SPU;
   0      11      3    k$2       Lscala/Function1;

  Signature: length = 0x2
   01 6A 

public scala.io.BytePickle$PU usequ(scala.Function1, scala.io.BytePickle$PU, scala.Function1);
  Signature: (Lscala/Function1;Lscala/io/BytePickle$PU;Lscala/Function1;)Lscala/io/BytePickle$PU;
  Code:
   Stack=5, Locals=4, Args_size=4
	new	class scala/io/BytePickle$$anon$6
	dup
	aload_1
	aload_2
	aload_3
	invokespecial	Method scala/io/BytePickle$$anon$6."<init>":(Lscala/Function1;Lscala/io/BytePickle$PU;Lscala/Function1;)V
	areturn
  Labels:
  LocalVariableTable: 
   Start  Length  Slot  Name   Signature
   0      11      0    this       Lscala/io/BytePickle$;
   0      11      1    f$1       Lscala/Function1;
   0      11      2    pa$2       Lscala/io/BytePickle$PU;
   0      11      3    k$1       Lscala/Function1;

  Signature: length = 0x2
   01 70 

public scala.io.BytePickle$SPU lift(java.lang.Object);
  Signature: (Ljava/lang/Object;)Lscala/io/BytePickle$SPU;
  Code:
   Stack=3, Locals=2, Args_size=2
	new	class scala/io/BytePickle$$anon$5
	dup
	aload_1
	invokespecial	Method scala/io/BytePickle$$anon$5."<init>":(Ljava/lang/Object;)V
	areturn
  Labels:
  LocalVariableTable: 
   Start  Length  Slot  Name   Signature
   0      9      0    this       Lscala/io/BytePickle$;
   0      9      1    x$5       Ljava/lang/Object;

  Signature: length = 0x2
   01 74 

public scala.io.BytePickle$PU ulift(java.lang.Object);
  Signature: (Ljava/lang/Object;)Lscala/io/BytePickle$PU;
  Code:
   Stack=3, Locals=2, Args_size=2
	new	class scala/io/BytePickle$$anon$4
	dup
	aload_1
	invokespecial	Method scala/io/BytePickle$$anon$4."<init>":(Ljava/lang/Object;)V
	areturn
  Labels:
  LocalVariableTable: 
   Start  Length  Slot  Name   Signature
   0      9      0    this       Lscala/io/BytePickle$;
   0      9      1    x$4       Ljava/lang/Object;

  Signature: length = 0x2
   01 78 

public scala.io.BytePickle$SPU share(scala.io.BytePickle$SPU);
  Signature: (Lscala/io/BytePickle$SPU;)Lscala/io/BytePickle$SPU;
  Code:
   Stack=3, Locals=2, Args_size=2
	new	class scala/io/BytePickle$$anon$3
	dup
	aload_1
	invokespecial	Method scala/io/BytePickle$$anon$3."<init>":(Lscala/io/BytePickle$SPU;)V
	areturn
  Labels:
  LocalVariableTable: 
   Start  Length  Slot  Name   Signature
   0      9      0    this       Lscala/io/BytePickle$;
   0      9      1    pa$1       Lscala/io/BytePickle$SPU;

  Signature: length = 0x2
   01 7B 

public scala.io.BytePickle$PU unat();
  Signature: ()Lscala/io/BytePickle$PU;
  Code:
   Stack=2, Locals=1, Args_size=1
	new	class scala/io/BytePickle$$anon$2
	dup
	invokespecial	Method scala/io/BytePickle$$anon$2."<init>":()V
	areturn
  Labels:
  Signature: length = 0x2
   01 7E 

public int DEF();
  Signature: ()I
  Code:
   Stack=1, Locals=1, Args_size=1
	aload_0
	getfield	Field DEF:I
	ireturn
  Labels:

public int REF();
  Signature: ()I
  Code:
   Stack=1, Locals=1, Args_size=1
	aload_0
	getfield	Field REF:I
	ireturn
  Labels:

public scala.io.BytePickle$PU refDef();
  Signature: ()Lscala/io/BytePickle$PU;
  Code:
   Stack=2, Locals=1, Args_size=1
	new	class scala/io/BytePickle$$anon$1
	dup
	invokespecial	Method scala/io/BytePickle$$anon$1."<init>":()V
	areturn
  Labels:
  Signature: length = 0x2
   01 FFFFFF84 

public java.lang.Object uunpickle(scala.io.BytePickle$PU, byte[]);
  Signature: (Lscala/io/BytePickle$PU;[B)Ljava/lang/Object;
  Code:
   Stack=2, Locals=3, Args_size=3
	aload_1
	aload_2
	invokevirtual	Method scala/io/BytePickle$PU.appU:([B)Lscala/Tuple2;
	invokevirtual	Method scala/Tuple2._1:()Ljava/lang/Object;
	areturn
  Labels:
  LocalVariableTable: 
   Start  Length  Slot  Name   Signature
   0      9      0    this       Lscala/io/BytePickle$;
   0      9      1    p       Lscala/io/BytePickle$PU;
   0      9      2    stream       [B

  Signature: length = 0x2
   01 FFFFFF8E 

public byte[] upickle(scala.io.BytePickle$PU, java.lang.Object);
  Signature: (Lscala/io/BytePickle$PU;Ljava/lang/Object;)[B
  Code:
   Stack=3, Locals=3, Args_size=3
	aload_1
	aload_2
	iconst_0
	newarray byte
	invokevirtual	Method scala/io/BytePickle$PU.appP:(Ljava/lang/Object;[B)[B
	areturn
  Labels:
  LocalVariableTable: 
   Start  Length  Slot  Name   Signature
   0      9      0    this       Lscala/io/BytePickle$;
   0      9      1    p       Lscala/io/BytePickle$PU;
   0      9      2    a       Ljava/lang/Object;

  Signature: length = 0x2
   01 FFFFFF95 

public java.lang.Object unpickle(scala.io.BytePickle$SPU, byte[]);
  Signature: (Lscala/io/BytePickle$SPU;[B)Ljava/lang/Object;
  Code:
   Stack=6, Locals=3, Args_size=3
	aload_1
	new	class scala/io/BytePickle$UnPicklerState
	dup
	aload_2
	new	class scala/io/BytePickle$UnPicklerEnv
	dup
	invokespecial	Method scala/io/BytePickle$UnPicklerEnv."<init>":()V
	invokespecial	Method scala/io/BytePickle$UnPicklerState."<init>":([BLscala/io/BytePickle$UnPicklerEnv;)V
	invokevirtual	Method scala/io/BytePickle$SPU.appU:(Lscala/io/BytePickle$UnPicklerState;)Lscala/Tuple2;
	invokevirtual	Method scala/Tuple2._1:()Ljava/lang/Object;
	areturn
  Labels:
  LocalVariableTable: 
   Start  Length  Slot  Name   Signature
   0      23      0    this       Lscala/io/BytePickle$;
   0      23      1    p       Lscala/io/BytePickle$SPU;
   0      23      2    stream       [B

  Signature: length = 0x2
   01 FFFFFFA5 

public byte[] pickle(scala.io.BytePickle$SPU, java.lang.Object);
  Signature: (Lscala/io/BytePickle$SPU;Ljava/lang/Object;)[B
  Code:
   Stack=7, Locals=3, Args_size=3
	aload_1
	aload_2
	new	class scala/io/BytePickle$PicklerState
	dup
	iconst_0
	newarray byte
	new	class scala/io/BytePickle$PicklerEnv
	dup
	invokespecial	Method scala/io/BytePickle$PicklerEnv."<init>":()V
	invokespecial	Method scala/io/BytePickle$PicklerState."<init>":([BLscala/io/BytePickle$PicklerEnv;)V
	invokevirtual	Method scala/io/BytePickle$SPU.appP:(Ljava/lang/Object;Lscala/io/BytePickle$PicklerState;)Lscala/io/BytePickle$PicklerState;
	invokevirtual	Method scala/io/BytePickle$PicklerState.stream:()[B
	areturn
  Labels:
  LocalVariableTable: 
   Start  Length  Slot  Name   Signature
   0      26      0    this       Lscala/io/BytePickle$;
   0      26      1    p       Lscala/io/BytePickle$SPU;
   0      26      2    a       Ljava/lang/Object;

  Signature: length = 0x2
   01 FFFFFFB6 

}

