Compiled from "Codec.scala"
public final class scala.io.Codec$$anonfun$encoder$2 extends scala.runtime.AbstractFunction1 implements java.io.Serializable
  SourceFile: "Codec.scala"
  Scala: length = 0x
   
  InnerClass: 
   public final #50= #9 of #39; //$anonfun$encoder$2=class scala/io/Codec$$anonfun$encoder$2 of class scala/io/Codec
  minor version: 0
  major version: 49
  Constant pool:
const #1 = Asciz	SourceFile;
const #2 = Asciz	Codec.scala;
const #3 = Asciz	<clinit>;
const #4 = Asciz	()V;
const #5 = Asciz	Code;
const #6 = Asciz	serialVersionUID;
const #7 = Asciz	J;
const #8 = Asciz	scala/io/Codec$$anonfun$encoder$2;
const #9 = class	#8;	//  scala/io/Codec$$anonfun$encoder$2
const #10 = NameAndType	#6:#7;//  serialVersionUID:J
const #11 = Field	#9.#10;	//  scala/io/Codec$$anonfun$encoder$2.serialVersionUID:J
const #12 = Asciz	$outer;
const #13 = Asciz	Lscala/io/Codec;;
const #14 = Asciz	<init>;
const #15 = Asciz	(Lscala/io/Codec;)V;
const #16 = Asciz	LineNumberTable;
const #17 = Asciz	java/lang/NullPointerException;
const #18 = class	#17;	//  java/lang/NullPointerException
const #19 = NameAndType	#14:#4;//  "<init>":()V
const #20 = Method	#18.#19;	//  java/lang/NullPointerException."<init>":()V
const #21 = NameAndType	#12:#13;//  $outer:Lscala/io/Codec;
const #22 = Field	#9.#21;	//  scala/io/Codec$$anonfun$encoder$2.$outer:Lscala/io/Codec;
const #23 = Asciz	scala/runtime/AbstractFunction1;
const #24 = class	#23;	//  scala/runtime/AbstractFunction1
const #25 = Method	#24.#19;	//  scala/runtime/AbstractFunction1."<init>":()V
const #26 = Asciz	this;
const #27 = Asciz	Lscala/io/Codec$$anonfun$encoder$2;;
const #28 = Asciz	LocalVariableTable;
const #29 = Asciz	apply;
const #30 = Asciz	(Ljava/lang/Object;)Ljava/lang/Object;;
const #31 = Asciz	java/nio/charset/CharsetEncoder;
const #32 = class	#31;	//  java/nio/charset/CharsetEncoder
const #33 = Asciz	(Ljava/nio/charset/CharsetEncoder;)Ljava/nio/charset/CharsetEncoder;;
const #34 = NameAndType	#29:#33;//  apply:(Ljava/nio/charset/CharsetEncoder;)Ljava/nio/charset/CharsetEncoder;
const #35 = Method	#9.#34;	//  scala/io/Codec$$anonfun$encoder$2.apply:(Ljava/nio/charset/CharsetEncoder;)Ljava/nio/charset/CharsetEncoder;
const #36 = Asciz	v1;
const #37 = Asciz	Ljava/lang/Object;;
const #38 = Asciz	scala/io/Codec;
const #39 = class	#38;	//  scala/io/Codec
const #40 = Asciz	scala$io$Codec$$_onUnmappableCharacter;
const #41 = Asciz	Ljava/nio/charset/CodingErrorAction;;
const #42 = NameAndType	#40:#41;//  scala$io$Codec$$_onUnmappableCharacter:Ljava/nio/charset/CodingErrorAction;
const #43 = Field	#39.#42;	//  scala/io/Codec.scala$io$Codec$$_onUnmappableCharacter:Ljava/nio/charset/CodingErrorAction;
const #44 = Asciz	onUnmappableCharacter;
const #45 = Asciz	(Ljava/nio/charset/CodingErrorAction;)Ljava/nio/charset/CharsetEncoder;;
const #46 = NameAndType	#44:#45;//  onUnmappableCharacter:(Ljava/nio/charset/CodingErrorAction;)Ljava/nio/charset/CharsetEncoder;
const #47 = Method	#32.#46;	//  java/nio/charset/CharsetEncoder.onUnmappableCharacter:(Ljava/nio/charset/CodingErrorAction;)Ljava/nio/charset/CharsetEncoder;
const #48 = Asciz	Scala;
const #49 = Asciz	InnerClasses;
const #50 = Asciz	$anonfun$encoder$2;
const #51 = Asciz	java/io/Serializable;
const #52 = class	#51;	//  java/io/Serializable

{
public static final long serialVersionUID;

public static {};
  Code:
   Stack=2, Locals=0, Args_size=0
   0:	lconst_0
   1:	putstatic	#11; //Field serialVersionUID:J
   4:	return

public scala.io.Codec$$anonfun$encoder$2(scala.io.Codec);
  Code:
   Stack=2, Locals=2, Args_size=2
   0:	aload_1
   1:	ifnonnull	12
   4:	new	#18; //class java/lang/NullPointerException
   7:	dup
   8:	invokespecial	#20; //Method java/lang/NullPointerException."<init>":()V
   11:	athrow
   12:	aload_0
   13:	aload_1
   14:	putfield	#22; //Field $outer:Lscala/io/Codec;
   17:	aload_0
   18:	invokespecial	#25; //Method scala/runtime/AbstractFunction1."<init>":()V
   21:	return
  LineNumberTable: 
   line 53: 0

  LocalVariableTable: 
   Start  Length  Slot  Name   Signature
   0      22      0    this       Lscala/io/Codec$$anonfun$encoder$2;
   0      22      1    $outer       Lscala/io/Codec;


public final java.lang.Object apply(java.lang.Object);
  Code:
   Stack=2, Locals=2, Args_size=2
   0:	aload_0
   1:	aload_1
   2:	checkcast	#32; //class java/nio/charset/CharsetEncoder
   5:	invokevirtual	#35; //Method apply:(Ljava/nio/charset/CharsetEncoder;)Ljava/nio/charset/CharsetEncoder;
   8:	areturn
  LineNumberTable: 
   line 53: 0

  LocalVariableTable: 
   Start  Length  Slot  Name   Signature
   0      9      0    this       Lscala/io/Codec$$anonfun$encoder$2;
   0      9      1    v1       Ljava/lang/Object;


public final java.nio.charset.CharsetEncoder apply(java.nio.charset.CharsetEncoder);
  Code:
   Stack=2, Locals=2, Args_size=2
   0:	aload_1
   1:	aload_0
   2:	getfield	#22; //Field $outer:Lscala/io/Codec;
   5:	getfield	#43; //Field scala/io/Codec.scala$io$Codec$$_onUnmappableCharacter:Ljava/nio/charset/CodingErrorAction;
   8:	invokevirtual	#47; //Method java/nio/charset/CharsetEncoder.onUnmappableCharacter:(Ljava/nio/charset/CodingErrorAction;)Ljava/nio/charset/CharsetEncoder;
   11:	areturn
  LineNumberTable: 
   line 53: 0


}

