Compiled from "Codec.scala"
public final class scala.io.Codec$$anonfun$encoder$2 extends scala.runtime.AbstractFunction1 implements java.io.Serializable
  SourceFile: "Codec.scala"
  Scala: length = 0x
   
  InnerClass: 
   public final $anonfun$encoder$2=class scala/io/Codec$$anonfun$encoder$2 of class scala/io/Codec
  minor version: 0
  major version: 49
  Constant pool:
Asciz	SourceFile;
Asciz	Codec.scala;
Asciz	<clinit>;
Asciz	()V;
Asciz	Code;
Asciz	serialVersionUID;
Asciz	J;
Asciz	scala/io/Codec$$anonfun$encoder$2;
class	scala/io/Codec$$anonfun$encoder$2
NameAndType	serialVersionUID:J
Field	scala/io/Codec$$anonfun$encoder$2.serialVersionUID:J
Asciz	$outer;
Asciz	Lscala/io/Codec;;
Asciz	apply;
Asciz	(Ljava/nio/charset/CharsetEncoder;)Ljava/nio/charset/CharsetEncoder;;
Asciz	LineNumberTable;
NameAndType	$outer:Lscala/io/Codec;
Field	scala/io/Codec$$anonfun$encoder$2.$outer:Lscala/io/Codec;
Asciz	scala/io/Codec;
class	scala/io/Codec
Asciz	scala$io$Codec$$_onUnmappableCharacter;
Asciz	Ljava/nio/charset/CodingErrorAction;;
NameAndType	scala$io$Codec$$_onUnmappableCharacter:Ljava/nio/charset/CodingErrorAction;
Field	scala/io/Codec.scala$io$Codec$$_onUnmappableCharacter:Ljava/nio/charset/CodingErrorAction;
Asciz	java/nio/charset/CharsetEncoder;
class	java/nio/charset/CharsetEncoder
Asciz	onUnmappableCharacter;
Asciz	(Ljava/nio/charset/CodingErrorAction;)Ljava/nio/charset/CharsetEncoder;;
NameAndType	onUnmappableCharacter:(Ljava/nio/charset/CodingErrorAction;)Ljava/nio/charset/CharsetEncoder;
Method	java/nio/charset/CharsetEncoder.onUnmappableCharacter:(Ljava/nio/charset/CodingErrorAction;)Ljava/nio/charset/CharsetEncoder;
Asciz	(Ljava/lang/Object;)Ljava/lang/Object;;
NameAndType	apply:(Ljava/nio/charset/CharsetEncoder;)Ljava/nio/charset/CharsetEncoder;
Method	scala/io/Codec$$anonfun$encoder$2.apply:(Ljava/nio/charset/CharsetEncoder;)Ljava/nio/charset/CharsetEncoder;
Asciz	this;
Asciz	Lscala/io/Codec$$anonfun$encoder$2;;
Asciz	v1;
Asciz	Ljava/lang/Object;;
Asciz	LocalVariableTable;
Asciz	<init>;
Asciz	(Lscala/io/Codec;)V;
Asciz	java/lang/NullPointerException;
class	java/lang/NullPointerException
NameAndType	"<init>":()V
Method	java/lang/NullPointerException."<init>":()V
Asciz	scala/runtime/AbstractFunction1;
class	scala/runtime/AbstractFunction1
Method	scala/runtime/AbstractFunction1."<init>":()V
Asciz	Scala;
Asciz	InnerClasses;
Asciz	$anonfun$encoder$2;
Asciz	java/io/Serializable;
class	java/io/Serializable

{
public static final long serialVersionUID;
  Signature: J

public final scala.io.Codec $outer;
  Signature: Lscala/io/Codec;

public static {};
  Signature: ()V
  Code:
   Stack=2, Locals=0, Args_size=0
	lconst_0
	putstatic	Field serialVersionUID:J
	return
  Labels:

public final java.nio.charset.CharsetEncoder apply(java.nio.charset.CharsetEncoder);
  Signature: (Ljava/nio/charset/CharsetEncoder;)Ljava/nio/charset/CharsetEncoder;
  Code:
   Stack=2, Locals=2, Args_size=2
	aload_1
	aload_0
	getfield	Field $outer:Lscala/io/Codec;
	getfield	Field scala/io/Codec.scala$io$Codec$$_onUnmappableCharacter:Ljava/nio/charset/CodingErrorAction;
	invokevirtual	Method java/nio/charset/CharsetEncoder.onUnmappableCharacter:(Ljava/nio/charset/CodingErrorAction;)Ljava/nio/charset/CharsetEncoder;
	areturn
  Labels:

public final java.lang.Object apply(java.lang.Object);
  Signature: (Ljava/lang/Object;)Ljava/lang/Object;
  Code:
   Stack=2, Locals=2, Args_size=2
	aload_0
	aload_1
	checkcast	class java/nio/charset/CharsetEncoder
	invokevirtual	Method apply:(Ljava/nio/charset/CharsetEncoder;)Ljava/nio/charset/CharsetEncoder;
	areturn
  Labels:
  LocalVariableTable: 
   Start  Length  Slot  Name   Signature
   0      9      0    this       Lscala/io/Codec$$anonfun$encoder$2;
   0      9      1    v1       Ljava/lang/Object;


public scala.io.Codec$$anonfun$encoder$2(scala.io.Codec);
  Signature: (Lscala/io/Codec;)V
  Code:
   Stack=2, Locals=2, Args_size=2
	aload_1
	ifnonnull	l1 // aload_0
	new	class java/lang/NullPointerException
	dup
	invokespecial	Method java/lang/NullPointerException."<init>":()V
	athrow
l1	aload_0
	aload_1
	putfield	Field $outer:Lscala/io/Codec;
	aload_0
	invokespecial	Method scala/runtime/AbstractFunction1."<init>":()V
	return
  Labels:
   	l1 = 12 // aload_0
  LocalVariableTable: 
   Start  Length  Slot  Name   Signature
   0      22      0    this       Lscala/io/Codec$$anonfun$encoder$2;
   0      22      1    $outer       Lscala/io/Codec;


}

