Compiled from "Codec.scala"
public final class scala.io.Codec$$anonfun$applyFunctions$1 extends scala.runtime.AbstractFunction2 implements java.io.Serializable
  SourceFile: "Codec.scala"
  Scala: length = 0x
   
  InnerClass: 
   public final $anonfun$applyFunctions$1=class scala/io/Codec$$anonfun$applyFunctions$1 of class scala/io/Codec
  minor version: 0
  major version: 49
  Constant pool:
Asciz	SourceFile;
Asciz	Codec.scala;
Asciz	<clinit>;
Asciz	()V;
Asciz	Code;
Asciz	serialVersionUID;
Asciz	J;
Asciz	scala/io/Codec$$anonfun$applyFunctions$1;
class	scala/io/Codec$$anonfun$applyFunctions$1
NameAndType	serialVersionUID:J
Field	scala/io/Codec$$anonfun$applyFunctions$1.serialVersionUID:J
Asciz	apply;
Asciz	(Ljava/lang/Object;Lscala/Tuple2;)Ljava/lang/Object;;
Asciz	LineNumberTable;
Asciz	scala/Tuple2;
class	scala/Tuple2
Asciz	_2;
Asciz	()Ljava/lang/Object;;
NameAndType	_2:()Ljava/lang/Object;
Method	scala/Tuple2._2:()Ljava/lang/Object;
Asciz	scala/runtime/BoxesRunTime;
class	scala/runtime/BoxesRunTime
Asciz	unboxToBoolean;
Asciz	(Ljava/lang/Object;)Z;
NameAndType	unboxToBoolean:(Ljava/lang/Object;)Z
Method	scala/runtime/BoxesRunTime.unboxToBoolean:(Ljava/lang/Object;)Z
Asciz	_1;
NameAndType	_1:()Ljava/lang/Object;
Method	scala/Tuple2._1:()Ljava/lang/Object;
Asciz	scala/Function1;
class	scala/Function1
Asciz	(Ljava/lang/Object;)Ljava/lang/Object;;
NameAndType	apply:(Ljava/lang/Object;)Ljava/lang/Object;
InterfaceMethod	scala/Function1.apply:(Ljava/lang/Object;)Ljava/lang/Object;
Asciz	scala/MatchError;
class	scala/MatchError
Asciz	toString;
Asciz	()Ljava/lang/String;;
NameAndType	toString:()Ljava/lang/String;
Method	scala/Tuple2.toString:()Ljava/lang/String;
Asciz	<init>;
Asciz	(Ljava/lang/String;)V;
NameAndType	"<init>":(Ljava/lang/String;)V
Method	scala/MatchError."<init>":(Ljava/lang/String;)V
Asciz	this;
Asciz	Lscala/io/Codec$$anonfun$applyFunctions$1;;
Asciz	x;
Asciz	Ljava/lang/Object;;
Asciz	pair;
Asciz	Lscala/Tuple2;;
Asciz	LocalVariableTable;
Asciz	(TT;Lscala/Tuple2<Lscala/Function1<TT;TT;>;Ljava/lang/Boolean;>;)TT;;
Asciz	Signature;
Asciz	(Ljava/lang/Object;Ljava/lang/Object;)Ljava/lang/Object;;
NameAndType	apply:(Ljava/lang/Object;Lscala/Tuple2;)Ljava/lang/Object;
Method	scala/io/Codec$$anonfun$applyFunctions$1.apply:(Ljava/lang/Object;Lscala/Tuple2;)Ljava/lang/Object;
Asciz	v1;
Asciz	v2;
Asciz	(Lscala/io/Codec;)V;
Asciz	scala/runtime/AbstractFunction2;
class	scala/runtime/AbstractFunction2
NameAndType	"<init>":()V
Method	scala/runtime/AbstractFunction2."<init>":()V
Asciz	$outer;
Asciz	Lscala/io/Codec;;
Asciz	Scala;
Asciz	InnerClasses;
Asciz	scala/io/Codec;
class	scala/io/Codec
Asciz	$anonfun$applyFunctions$1;
Asciz	java/io/Serializable;
class	java/io/Serializable

{
public static final long serialVersionUID;
  Signature: J

public static {};
  Signature: ()V
  Code:
   Stack=2, Locals=0, Args_size=0
	lconst_0
	putstatic	Field serialVersionUID:J
	return
  Labels:

public final java.lang.Object apply(java.lang.Object, scala.Tuple2);
  Signature: (Ljava/lang/Object;Lscala/Tuple2;)Ljava/lang/Object;
  Code:
   Stack=3, Locals=3, Args_size=3
	aload_2
	ifnull	l1 // new
	aload_2
	invokevirtual	Method scala/Tuple2._2:()Ljava/lang/Object;
	invokestatic	Method scala/runtime/BoxesRunTime.unboxToBoolean:(Ljava/lang/Object;)Z
	ifeq	l2 // aload_1
	aload_2
	invokevirtual	Method scala/Tuple2._1:()Ljava/lang/Object;
	checkcast	class scala/Function1
	aload_1
	invokeinterface	InterfaceMethod scala/Function1.apply:(Ljava/lang/Object;)Ljava/lang/Object;
	goto	l3 // areturn
l2	aload_1
l3	areturn
l1	new	class scala/MatchError
	dup
	aload_2
	invokevirtual	Method scala/Tuple2.toString:()Ljava/lang/String;
	invokespecial	Method scala/MatchError."<init>":(Ljava/lang/String;)V
	athrow
  Labels:
   	l2 = 30 // aload_1
   	l3 = 31 // areturn
   	l1 = 32 // new
  LocalVariableTable: 
   Start  Length  Slot  Name   Signature
   0      44      0    this       Lscala/io/Codec$$anonfun$applyFunctions$1;
   0      44      1    x       Ljava/lang/Object;
   0      44      2    pair       Lscala/Tuple2;

  Signature: length = 0x2
   00 34 

public final java.lang.Object apply(java.lang.Object, java.lang.Object);
  Signature: (Ljava/lang/Object;Ljava/lang/Object;)Ljava/lang/Object;
  Code:
   Stack=3, Locals=3, Args_size=3
	aload_0
	aload_1
	aload_2
	checkcast	class scala/Tuple2
	invokevirtual	Method apply:(Ljava/lang/Object;Lscala/Tuple2;)Ljava/lang/Object;
	areturn
  Labels:
  LocalVariableTable: 
   Start  Length  Slot  Name   Signature
   0      10      0    this       Lscala/io/Codec$$anonfun$applyFunctions$1;
   0      10      1    v1       Ljava/lang/Object;
   0      10      2    v2       Ljava/lang/Object;


public scala.io.Codec$$anonfun$applyFunctions$1(scala.io.Codec);
  Signature: (Lscala/io/Codec;)V
  Code:
   Stack=1, Locals=2, Args_size=2
	aload_0
	invokespecial	Method scala/runtime/AbstractFunction2."<init>":()V
	return
  Labels:
  LocalVariableTable: 
   Start  Length  Slot  Name   Signature
   0      5      0    this       Lscala/io/Codec$$anonfun$applyFunctions$1;
   0      5      1    $outer       Lscala/io/Codec;


}

