Compiled from "File.scala"
public final class scala.io.File$ extends java.lang.Object implements scala.ScalaObject
  SourceFile: "File.scala"
  Scala: length = 0x
   
  InnerClass: 
   public final #64= #63 of #44; //$anonfun$iterator$1=class scala/io/File$$anonfun$iterator$1 of class scala/io/File
   public final #67= #66 of #44; //$anonfun$scala$io$File$$deleteRecursively$1=class scala/io/File$$anonfun$scala$io$File$$deleteRecursively$1 of class scala/io/File
  minor version: 0
  major version: 49
  Constant pool:
const #1 = Asciz	SourceFile;
const #2 = Asciz	File.scala;
const #3 = Asciz	Scala;
const #4 = Asciz	MODULE$;
const #5 = Asciz	Lscala/io/File$;;
const #6 = Asciz	<clinit>;
const #7 = Asciz	()V;
const #8 = Asciz	Code;
const #9 = Asciz	scala/io/File$;
const #10 = class	#9;	//  scala/io/File$
const #11 = Asciz	<init>;
const #12 = NameAndType	#11:#7;//  "<init>":()V
const #13 = Method	#10.#12;	//  scala/io/File$."<init>":()V
const #14 = Asciz	extensionRegex;
const #15 = Asciz	Lscala/util/matching/Regex;;
const #16 = Asciz	LineNumberTable;
const #17 = Asciz	java/lang/Object;
const #18 = class	#17;	//  java/lang/Object
const #19 = Method	#18.#12;	//  java/lang/Object."<init>":()V
const #20 = NameAndType	#4:#5;//  MODULE$:Lscala/io/File$;
const #21 = Field	#10.#20;	//  scala/io/File$.MODULE$:Lscala/io/File$;
const #22 = Asciz	scala/Predef$;
const #23 = class	#22;	//  scala/Predef$
const #24 = Asciz	Lscala/Predef$;;
const #25 = NameAndType	#4:#24;//  MODULE$:Lscala/Predef$;
const #26 = Field	#23.#25;	//  scala/Predef$.MODULE$:Lscala/Predef$;
const #27 = Asciz	^.*\.([^.]+)$;
const #28 = String	#27;	//  ^.*\.([^.]+)$
const #29 = Asciz	stringWrapper;
const #30 = Asciz	(Ljava/lang/String;)Lscala/runtime/RichString;;
const #31 = NameAndType	#29:#30;//  stringWrapper:(Ljava/lang/String;)Lscala/runtime/RichString;
const #32 = Method	#23.#31;	//  scala/Predef$.stringWrapper:(Ljava/lang/String;)Lscala/runtime/RichString;
const #33 = Asciz	scala/runtime/RichString;
const #34 = class	#33;	//  scala/runtime/RichString
const #35 = Asciz	r;
const #36 = Asciz	()Lscala/util/matching/Regex;;
const #37 = NameAndType	#35:#36;//  r:()Lscala/util/matching/Regex;
const #38 = Method	#34.#37;	//  scala/runtime/RichString.r:()Lscala/util/matching/Regex;
const #39 = NameAndType	#14:#15;//  extensionRegex:Lscala/util/matching/Regex;
const #40 = Field	#10.#39;	//  scala/io/File$.extensionRegex:Lscala/util/matching/Regex;
const #41 = Asciz	apply;
const #42 = Asciz	(Ljava/io/File;)Lscala/io/File;;
const #43 = Asciz	scala/io/File;
const #44 = class	#43;	//  scala/io/File
const #45 = Asciz	(Ljava/io/File;)V;
const #46 = NameAndType	#11:#45;//  "<init>":(Ljava/io/File;)V
const #47 = Method	#44.#46;	//  scala/io/File."<init>":(Ljava/io/File;)V
const #48 = Asciz	this;
const #49 = Asciz	file;
const #50 = Asciz	Ljava/io/File;;
const #51 = Asciz	LocalVariableTable;
const #52 = Asciz	(Ljava/lang/String;)Lscala/io/File;;
const #53 = Asciz	java/io/File;
const #54 = class	#53;	//  java/io/File
const #55 = Asciz	(Ljava/lang/String;)V;
const #56 = NameAndType	#11:#55;//  "<init>":(Ljava/lang/String;)V
const #57 = Method	#54.#56;	//  java/io/File."<init>":(Ljava/lang/String;)V
const #58 = Asciz	fileName;
const #59 = Asciz	Ljava/lang/String;;
const #60 = Asciz	fileWrapper;
const #61 = Asciz	InnerClasses;
const #62 = Asciz	scala/io/File$$anonfun$iterator$1;
const #63 = class	#62;	//  scala/io/File$$anonfun$iterator$1
const #64 = Asciz	$anonfun$iterator$1;
const #65 = Asciz	scala/io/File$$anonfun$scala$io$File$$deleteRecursively$1;
const #66 = class	#65;	//  scala/io/File$$anonfun$scala$io$File$$deleteRecursively$1
const #67 = Asciz	$anonfun$scala$io$File$$deleteRecursively$1;
const #68 = Asciz	scala/ScalaObject;
const #69 = class	#68;	//  scala/ScalaObject

{
public static final scala.io.File$ MODULE$;

public static {};
  Code:
   Stack=1, Locals=0, Args_size=0
   0:	new	#10; //class scala/io/File$
   3:	invokespecial	#13; //Method "<init>":()V
   6:	return

public scala.io.File apply(java.io.File);
  Code:
   Stack=3, Locals=2, Args_size=2
   0:	new	#44; //class scala/io/File
   3:	dup
   4:	aload_1
   5:	invokespecial	#47; //Method scala/io/File."<init>":(Ljava/io/File;)V
   8:	areturn
  LineNumberTable: 
   line 21: 0

  LocalVariableTable: 
   Start  Length  Slot  Name   Signature
   0      9      0    this       Lscala/io/File$;
   0      9      1    file       Ljava/io/File;


public scala.io.File apply(java.lang.String);
  Code:
   Stack=5, Locals=2, Args_size=2
   0:	new	#44; //class scala/io/File
   3:	dup
   4:	new	#54; //class java/io/File
   7:	dup
   8:	aload_1
   9:	invokespecial	#57; //Method java/io/File."<init>":(Ljava/lang/String;)V
   12:	invokespecial	#47; //Method scala/io/File."<init>":(Ljava/io/File;)V
   15:	areturn
  LineNumberTable: 
   line 20: 0

  LocalVariableTable: 
   Start  Length  Slot  Name   Signature
   0      16      0    this       Lscala/io/File$;
   0      16      1    fileName       Ljava/lang/String;


public scala.io.File fileWrapper(java.io.File);
  Code:
   Stack=3, Locals=2, Args_size=2
   0:	new	#44; //class scala/io/File
   3:	dup
   4:	aload_1
   5:	invokespecial	#47; //Method scala/io/File."<init>":(Ljava/io/File;)V
   8:	areturn
  LineNumberTable: 
   line 18: 0

  LocalVariableTable: 
   Start  Length  Slot  Name   Signature
   0      9      0    this       Lscala/io/File$;
   0      9      1    file       Ljava/io/File;


public final scala.util.matching.Regex extensionRegex();
  Code:
   Stack=1, Locals=1, Args_size=1
   0:	aload_0
   1:	getfield	#40; //Field extensionRegex:Lscala/util/matching/Regex;
   4:	areturn
  LineNumberTable: 
   line 17: 0


}

