Compiled from "File.scala"
public class scala.io.File extends java.lang.Object implements scala.collection.Iterable,scala.ScalaObject
  SourceFile: "File.scala"
  Signature: length = 0x2
   02 49 
  ScalaSig: length = 0x406
   05 00 FFFFFF81 1E 07 05 01 02 FFFFFF88 02 07 01 04 46 69 6C
   65 0A 02 03 04 01 02 69 6F 0A 01 05 01 05 73 63
   61 6C 61 03 00 10 02 08 09 0D 01 02 06 08 0A 02
   FFFFFF84 FFFFFF80 FFFFFF80 FFFFFF88 02 0B 02 04 46 69 6C 65 13 03 09 0C
   14 10 02 0D 12 0D 01 0E 0A 02 0F 10 01 04 6C 61
   6E 67 0A 01 11 01 04 6A 61 76 61 09 02 13 0E 02
   06 4F 62 6A 65 63 74 10 02 15 16 0D 01 04 09 02
   17 04 02 0B 53 63 61 6C 61 4F 62 6A 65 63 74 08
   05 19 09 FFFFFF84 00 1A 01 06 3C 69 6E 69 74 3E 14 01
   07 08 07 1C 09 FFFFFFC2 FFFFFF80 FFFFFF84 02 1D 01 0E 65 78 74 65
   6E 73 69 6F 6E 52 65 67 65 78 15 01 1E 10 02 1F
   24 0D 01 20 0A 02 21 22 01 08 6D 61 74 63 68 69
   6E 67 0A 02 23 04 01 04 75 74 69 6C 09 02 25 20
   02 05 52 65 67 65 78 08 06 27 09 FFFFFFA0 FFFFFF80 06 1E 01
   0F 65 78 74 65 6E 73 69 6F 6E 52 65 67 65 78 20
   08 05 29 09 FFFFFF84 01 2A 01 0B 66 69 6C 65 57 72 61
   70 70 65 72 14 03 2B FFFFFF81 15 10 02 08 2C 06 08 0A
   02 FFFFFF84 FFFFFF80 FFFFFF80 FFFFFF80 00 2D 13 04 2C 0C 2E 14 10 03 2F
   32 2B 0D 01 30 0A 02 31 04 01 0A 63 6F 6C 6C 65
   63 74 69 6F 6E 09 02 33 30 02 08 49 74 65 72 61
   62 6C 65 08 08 35 2C FFFFFF82 FFFFFFC2 FFFFFF80 FFFFFF84 00 36 01 04 66
   69 6C 65 15 01 37 10 02 38 3A 0D 01 39 0A 02 03
   10 09 02 0A 39 08 08 3C 2C FFFFFF82 FFFFFF80 FFFFFFA0 FFFFFF80 04 37 01
   05 66 69 6C 65 20 08 05 19 2C FFFFFF84 00 3E 14 02 2B
   3F 08 05 35 3D FFFFFFC0 00 37 08 05 41 2C FFFFFF84 00 42 01
   08 69 74 65 72 61 74 6F 72 15 01 43 10 03 44 4C
   2B 0E 02 45 4A 0E 02 46 49 0D 01 47 0A 02 48 06
   01 06 3C 72 6F 6F 74 3E 09 01 05 09 02 4B 04 01
   07 70 61 63 6B 61 67 65 09 02 4D 4E 02 08 49 74
   65 72 61 74 6F 72 0A 02 4B 04 08 05 50 2C FFFFFF84 00
   51 01 11 64 65 6C 65 74 65 52 65 63 75 72 73 69
   76 65 6C 79 14 01 52 10 02 15 53 09 02 54 04 02
   07 42 6F 6F 6C 65 61 6E 08 05 50 2C FFFFFF84 04 56 14
   02 52 57 08 05 58 55 FFFFFFC0 00 37 01 01 66 08 05 5A
   2C FFFFFF84 00 5B 01 0B 69 6E 70 75 74 53 74 72 65 61
   6D 15 01 5C 10 02 38 5D 09 02 5E 39 02 0F 46 69
   6C 65 49 6E 70 75 74 53 74 72 65 61 6D 08 05 60
   2C FFFFFF84 00 61 01 0C 6F 75 74 70 75 74 53 74 72 65
   61 6D 14 02 62 65 10 02 38 63 09 02 64 39 02 10
   46 69 6C 65 4F 75 74 70 75 74 53 74 72 65 61 6D
   08 08 67 66 5F FFFFFF90 FFFFFF80 FFFFFFC0 00 52 01 06 61 70 70 65
   6E 64 08 07 68 2C FFFFFF91 FFFFFF80 FFFFFF84 00 69 01 16 6F 75 74
   70 75 74 53 74 72 65 61 6D 24 64 65 66 61 75 6C
   74 24 31 15 01 52 08 05 6B 2C FFFFFF84 00 6C 01 09 65
   78 74 65 6E 73 69 6F 6E 15 01 6D 10 03 15 6E 70
   09 02 6F 04 02 06 4F 70 74 69 6F 6E 10 02 71 74
   0E 02 15 72 09 02 73 04 01 06 50 72 65 64 65 66
   09 02 75 76 02 06 53 74 72 69 6E 67 0A 02 73 04
   08 05 78 2C FFFFFF84 00 79 01 08 74 6F 53 6F 75 72 63
   65 15 01 7A 10 02 08 7B 09 02 7C 02 02 06 53 6F
   75 72 63 65 08 05 7E 2C FFFFFF84 00 7F 01 04 24 64 69
   76 14 03 2B FFFFFF81 00 08 06 FFFFFF81 01 7D FFFFFFC0 00 70 01 05
   63 68 69 6C 64 08 07 FFFFFF81 03 2C FFFFFF84 20 FFFFFF81 04 01 08
   74 6F 53 74 72 69 6E 67 14 02 FFFFFF81 05 10 03 0D FFFFFF81
   06 09 02 75 0E 08 07 FFFFFF81 08 2C FFFFFF84 20 FFFFFF81 09 01 06
   65 71 75 61 6C 73 14 03 52 FFFFFF81 0A 08 08 FFFFFF81 0B FFFFFF81
   07 FFFFFFC0 00 FFFFFF81 0C 01 05 6F 74 68 65 72 10 03 15 FFFFFF81
   0D 09 03 FFFFFF81 0E 04 02 03 41 6E 79 08 07 FFFFFF81 10 2C
   FFFFFF84 20 FFFFFF81 11 01 08 68 61 73 68 43 6F 64 65 14 02
   FFFFFF81 12 10 03 15 FFFFFF81 13 09 03 FFFFFF81 14 04 02 03 49 6E
   74 08 05 35 28 FFFFFFC0 00 37 08 07 FFFFFF81 17 09 FFFFFF84 00 FFFFFF81
   18 01 05 61 70 70 6C 79 14 03 2B FFFFFF81 19 08 07 FFFFFF81
   1A FFFFFF81 16 FFFFFFC0 00 70 01 08 66 69 6C 65 4E 61 6D 65
   08 07 FFFFFF81 17 09 FFFFFF84 00 FFFFFF81 1C 14 03 2B FFFFFF81 1D 08 06
   35 FFFFFF81 1B FFFFFFC0 00 37 
  InnerClass: 
   public final #588= #241 of #10; //$anonfun$iterator$1=class scala/io/File$$anonfun$iterator$1 of class scala/io/File
   public final #589= #217 of #10; //$anonfun$scala$io$File$$deleteRecursively$1=class scala/io/File$$anonfun$scala$io$File$$deleteRecursively$1 of class scala/io/File
  minor version: 0
  major version: 49
  Constant pool:
const #1 = Asciz	SourceFile;
const #2 = Asciz	File.scala;
const #3 = Asciz	file;
const #4 = Asciz	Ljava/io/File;;
const #5 = Asciz	<init>;
const #6 = Asciz	(Ljava/io/File;)V;
const #7 = Asciz	Code;
const #8 = Asciz	LineNumberTable;
const #9 = Asciz	scala/io/File;
const #10 = class	#9;	//  scala/io/File
const #11 = NameAndType	#3:#4;//  file:Ljava/io/File;
const #12 = Field	#10.#11;	//  scala/io/File.file:Ljava/io/File;
const #13 = Asciz	java/lang/Object;
const #14 = class	#13;	//  java/lang/Object
const #15 = Asciz	()V;
const #16 = NameAndType	#5:#15;//  "<init>":()V
const #17 = Method	#14.#16;	//  java/lang/Object."<init>":()V
const #18 = Asciz	scala/collection/generic/TraversableTemplate$class;
const #19 = class	#18;	//  scala/collection/generic/TraversableTemplate$class
const #20 = Asciz	$init$;
const #21 = Asciz	(Lscala/collection/generic/TraversableTemplate;)V;
const #22 = NameAndType	#20:#21;//  $init$:(Lscala/collection/generic/TraversableTemplate;)V
const #23 = Method	#19.#22;	//  scala/collection/generic/TraversableTemplate$class.$init$:(Lscala/collection/generic/TraversableTemplate;)V
const #24 = Asciz	scala/collection/generic/TraversableClass$class;
const #25 = class	#24;	//  scala/collection/generic/TraversableClass$class
const #26 = Asciz	(Lscala/collection/generic/TraversableClass;)V;
const #27 = NameAndType	#20:#26;//  $init$:(Lscala/collection/generic/TraversableClass;)V
const #28 = Method	#25.#27;	//  scala/collection/generic/TraversableClass$class.$init$:(Lscala/collection/generic/TraversableClass;)V
const #29 = Asciz	scala/collection/Traversable$class;
const #30 = class	#29;	//  scala/collection/Traversable$class
const #31 = Asciz	(Lscala/collection/Traversable;)V;
const #32 = NameAndType	#20:#31;//  $init$:(Lscala/collection/Traversable;)V
const #33 = Method	#30.#32;	//  scala/collection/Traversable$class.$init$:(Lscala/collection/Traversable;)V
const #34 = Asciz	scala/collection/generic/IterableTemplate$class;
const #35 = class	#34;	//  scala/collection/generic/IterableTemplate$class
const #36 = Asciz	(Lscala/collection/generic/IterableTemplate;)V;
const #37 = NameAndType	#20:#36;//  $init$:(Lscala/collection/generic/IterableTemplate;)V
const #38 = Method	#35.#37;	//  scala/collection/generic/IterableTemplate$class.$init$:(Lscala/collection/generic/IterableTemplate;)V
const #39 = Asciz	scala/collection/Iterable$class;
const #40 = class	#39;	//  scala/collection/Iterable$class
const #41 = Asciz	(Lscala/collection/Iterable;)V;
const #42 = NameAndType	#20:#41;//  $init$:(Lscala/collection/Iterable;)V
const #43 = Method	#40.#42;	//  scala/collection/Iterable$class.$init$:(Lscala/collection/Iterable;)V
const #44 = Asciz	this;
const #45 = Asciz	Lscala/io/File;;
const #46 = Asciz	LocalVariableTable;
const #47 = Asciz	view;
const #48 = Asciz	(II)Lscala/collection/generic/TraversableView;;
const #49 = Asciz	scala/collection/generic/IterableTemplate;
const #50 = class	#49;	//  scala/collection/generic/IterableTemplate
const #51 = Asciz	(II)Lscala/collection/generic/IterableView;;
const #52 = NameAndType	#47:#51;//  view:(II)Lscala/collection/generic/IterableView;
const #53 = InterfaceMethod	#50.#52;	//  scala/collection/generic/IterableTemplate.view:(II)Lscala/collection/generic/IterableView;
const #54 = Asciz	from;
const #55 = Asciz	I;
const #56 = Asciz	until;
const #57 = Asciz	outputStream$default$1;
const #58 = Asciz	()Z;
const #59 = Asciz	hashCode;
const #60 = Asciz	()I;
const #61 = Asciz	()Ljava/io/File;;
const #62 = NameAndType	#3:#61;//  file:()Ljava/io/File;
const #63 = Method	#10.#62;	//  scala/io/File.file:()Ljava/io/File;
const #64 = Asciz	java/io/File;
const #65 = class	#64;	//  java/io/File
const #66 = NameAndType	#59:#60;//  hashCode:()I
const #67 = Method	#65.#66;	//  java/io/File.hashCode:()I
const #68 = Asciz	equals;
const #69 = Asciz	(Ljava/lang/Object;)Z;
const #70 = NameAndType	#68:#69;//  equals:(Ljava/lang/Object;)Z
const #71 = Method	#14.#70;	//  java/lang/Object.equals:(Ljava/lang/Object;)Z
const #72 = Asciz	other;
const #73 = Asciz	Ljava/lang/Object;;
const #74 = Asciz	temp8;
const #75 = Asciz	temp9;
const #76 = Asciz	toString;
const #77 = Asciz	()Ljava/lang/String;;
const #78 = NameAndType	#76:#77;//  toString:()Ljava/lang/String;
const #79 = Method	#65.#78;	//  java/io/File.toString:()Ljava/lang/String;
const #80 = Asciz	$div;
const #81 = Asciz	(Ljava/lang/String;)Lscala/io/File;;
const #82 = Asciz	(Ljava/io/File;Ljava/lang/String;)V;
const #83 = NameAndType	#5:#82;//  "<init>":(Ljava/io/File;Ljava/lang/String;)V
const #84 = Method	#65.#83;	//  java/io/File."<init>":(Ljava/io/File;Ljava/lang/String;)V
const #85 = NameAndType	#5:#6;//  "<init>":(Ljava/io/File;)V
const #86 = Method	#10.#85;	//  scala/io/File."<init>":(Ljava/io/File;)V
const #87 = Asciz	child;
const #88 = Asciz	Ljava/lang/String;;
const #89 = Asciz	toSource;
const #90 = Asciz	()Lscala/io/Source;;
const #91 = Asciz	scala/io/Source$;
const #92 = class	#91;	//  scala/io/Source$
const #93 = Asciz	MODULE$;
const #94 = Asciz	Lscala/io/Source$;;
const #95 = NameAndType	#93:#94;//  MODULE$:Lscala/io/Source$;
const #96 = Field	#92.#95;	//  scala/io/Source$.MODULE$:Lscala/io/Source$;
const #97 = Asciz	fromFile$default$2;
const #98 = NameAndType	#97:#60;//  fromFile$default$2:()I
const #99 = Method	#92.#98;	//  scala/io/Source$.fromFile$default$2:()I
const #100 = Asciz	fromFile$default$3;
const #101 = Asciz	(Ljava/io/File;I)Lscala/io/Codec;;
const #102 = NameAndType	#100:#101;//  fromFile$default$3:(Ljava/io/File;I)Lscala/io/Codec;
const #103 = Method	#92.#102;	//  scala/io/Source$.fromFile$default$3:(Ljava/io/File;I)Lscala/io/Codec;
const #104 = Asciz	fromFile;
const #105 = Asciz	(Ljava/io/File;ILscala/io/Codec;)Lscala/io/Source;;
const #106 = NameAndType	#104:#105;//  fromFile:(Ljava/io/File;ILscala/io/Codec;)Lscala/io/Source;
const #107 = Method	#92.#106;	//  scala/io/Source$.fromFile:(Ljava/io/File;ILscala/io/Codec;)Lscala/io/Source;
const #108 = Asciz	x$1;
const #109 = Asciz	x$2;
const #110 = Asciz	x$3;
const #111 = Asciz	Lscala/io/Codec;;
const #112 = Asciz	extension;
const #113 = Asciz	()Lscala/Option;;
const #114 = Asciz	getName;
const #115 = NameAndType	#114:#77;//  getName:()Ljava/lang/String;
const #116 = Method	#65.#115;	//  java/io/File.getName:()Ljava/lang/String;
const #117 = Asciz	scala/io/File$;
const #118 = class	#117;	//  scala/io/File$
const #119 = Asciz	Lscala/io/File$;;
const #120 = NameAndType	#93:#119;//  MODULE$:Lscala/io/File$;
const #121 = Field	#118.#120;	//  scala/io/File$.MODULE$:Lscala/io/File$;
const #122 = Asciz	extensionRegex;
const #123 = Asciz	()Lscala/util/matching/Regex;;
const #124 = NameAndType	#122:#123;//  extensionRegex:()Lscala/util/matching/Regex;
const #125 = Method	#118.#124;	//  scala/io/File$.extensionRegex:()Lscala/util/matching/Regex;
const #126 = Asciz	scala/util/matching/Regex;
const #127 = class	#126;	//  scala/util/matching/Regex
const #128 = Asciz	unapplySeq;
const #129 = Asciz	(Ljava/lang/Object;)Lscala/Option;;
const #130 = NameAndType	#128:#129;//  unapplySeq:(Ljava/lang/Object;)Lscala/Option;
const #131 = Method	#127.#130;	//  scala/util/matching/Regex.unapplySeq:(Ljava/lang/Object;)Lscala/Option;
const #132 = Asciz	scala/Option;
const #133 = class	#132;	//  scala/Option
const #134 = Asciz	isEmpty;
const #135 = NameAndType	#134:#58;//  isEmpty:()Z
const #136 = Method	#133.#135;	//  scala/Option.isEmpty:()Z
const #137 = Asciz	get;
const #138 = Asciz	()Ljava/lang/Object;;
const #139 = NameAndType	#137:#138;//  get:()Ljava/lang/Object;
const #140 = Method	#133.#139;	//  scala/Option.get:()Ljava/lang/Object;
const #141 = Asciz	scala/collection/immutable/List;
const #142 = class	#141;	//  scala/collection/immutable/List
const #143 = Asciz	scala/collection/generic/SequenceTemplate;
const #144 = class	#143;	//  scala/collection/generic/SequenceTemplate
const #145 = Asciz	lengthCompare;
const #146 = Asciz	(I)I;
const #147 = NameAndType	#145:#146;//  lengthCompare:(I)I
const #148 = InterfaceMethod	#144.#147;	//  scala/collection/generic/SequenceTemplate.lengthCompare:(I)I
const #149 = Asciz	scala/runtime/BoxesRunTime;
const #150 = class	#149;	//  scala/runtime/BoxesRunTime
const #151 = Asciz	boxToInteger;
const #152 = Asciz	(I)Ljava/lang/Integer;;
const #153 = NameAndType	#151:#152;//  boxToInteger:(I)Ljava/lang/Integer;
const #154 = Method	#150.#153;	//  scala/runtime/BoxesRunTime.boxToInteger:(I)Ljava/lang/Integer;
const #155 = Asciz	(Ljava/lang/Object;Ljava/lang/Object;)Z;
const #156 = NameAndType	#68:#155;//  equals:(Ljava/lang/Object;Ljava/lang/Object;)Z
const #157 = Method	#150.#156;	//  scala/runtime/BoxesRunTime.equals:(Ljava/lang/Object;Ljava/lang/Object;)Z
const #158 = Asciz	scala/collection/generic/LinearSequenceTemplate;
const #159 = class	#158;	//  scala/collection/generic/LinearSequenceTemplate
const #160 = Asciz	apply;
const #161 = Asciz	(I)Ljava/lang/Object;;
const #162 = NameAndType	#160:#161;//  apply:(I)Ljava/lang/Object;
const #163 = InterfaceMethod	#159.#162;	//  scala/collection/generic/LinearSequenceTemplate.apply:(I)Ljava/lang/Object;
const #164 = Asciz	java/lang/String;
const #165 = class	#164;	//  java/lang/String
const #166 = Asciz	scala/Some;
const #167 = class	#166;	//  scala/Some
const #168 = Asciz	(Ljava/lang/Object;)V;
const #169 = NameAndType	#5:#168;//  "<init>":(Ljava/lang/Object;)V
const #170 = Method	#167.#169;	//  scala/Some."<init>":(Ljava/lang/Object;)V
const #171 = Asciz	scala/None$;
const #172 = class	#171;	//  scala/None$
const #173 = Asciz	Lscala/None$;;
const #174 = NameAndType	#93:#173;//  MODULE$:Lscala/None$;
const #175 = Field	#172.#174;	//  scala/None$.MODULE$:Lscala/None$;
const #176 = Asciz	temp3;
const #177 = Asciz	temp4;
const #178 = Asciz	Lscala/Option;;
const #179 = Asciz	temp5;
const #180 = Asciz	Lscala/collection/immutable/List;;
const #181 = Asciz	temp6;
const #182 = Asciz	()Lscala/Option<Ljava/lang/String;>;;
const #183 = Asciz	Signature;
const #184 = Asciz	outputStream;
const #185 = Asciz	(Z)Ljava/io/FileOutputStream;;
const #186 = Asciz	java/io/FileOutputStream;
const #187 = class	#186;	//  java/io/FileOutputStream
const #188 = Asciz	(Ljava/io/File;Z)V;
const #189 = NameAndType	#5:#188;//  "<init>":(Ljava/io/File;Z)V
const #190 = Method	#187.#189;	//  java/io/FileOutputStream."<init>":(Ljava/io/File;Z)V
const #191 = Asciz	append;
const #192 = Asciz	Z;
const #193 = Asciz	inputStream;
const #194 = Asciz	()Ljava/io/FileInputStream;;
const #195 = Asciz	java/io/FileInputStream;
const #196 = class	#195;	//  java/io/FileInputStream
const #197 = Method	#196.#85;	//  java/io/FileInputStream."<init>":(Ljava/io/File;)V
const #198 = Asciz	scala$io$File$$deleteRecursively;
const #199 = Asciz	(Ljava/io/File;)Z;
const #200 = Asciz	isDirectory;
const #201 = NameAndType	#200:#58;//  isDirectory:()Z
const #202 = Method	#65.#201;	//  java/io/File.isDirectory:()Z
const #203 = Asciz	listFiles;
const #204 = Asciz	()[Ljava/io/File;;
const #205 = NameAndType	#203:#204;//  listFiles:()[Ljava/io/File;
const #206 = Method	#65.#205;	//  java/io/File.listFiles:()[Ljava/io/File;
const #207 = Asciz	scala/runtime/ScalaRunTime$;
const #208 = class	#207;	//  scala/runtime/ScalaRunTime$
const #209 = Asciz	Lscala/runtime/ScalaRunTime$;;
const #210 = NameAndType	#93:#209;//  MODULE$:Lscala/runtime/ScalaRunTime$;
const #211 = Field	#208.#210;	//  scala/runtime/ScalaRunTime$.MODULE$:Lscala/runtime/ScalaRunTime$;
const #212 = Asciz	boxArray;
const #213 = Asciz	(Ljava/lang/Object;)Lscala/runtime/BoxedArray;;
const #214 = NameAndType	#212:#213;//  boxArray:(Ljava/lang/Object;)Lscala/runtime/BoxedArray;
const #215 = Method	#208.#214;	//  scala/runtime/ScalaRunTime$.boxArray:(Ljava/lang/Object;)Lscala/runtime/BoxedArray;
const #216 = Asciz	scala/io/File$$anonfun$scala$io$File$$deleteRecursively$1;
const #217 = class	#216;	//  scala/io/File$$anonfun$scala$io$File$$deleteRecursively$1
const #218 = Asciz	(Lscala/io/File;)V;
const #219 = NameAndType	#5:#218;//  "<init>":(Lscala/io/File;)V
const #220 = Method	#217.#219;	//  scala/io/File$$anonfun$scala$io$File$$deleteRecursively$1."<init>":(Lscala/io/File;)V
const #221 = Asciz	scala/collection/generic/VectorTemplate;
const #222 = class	#221;	//  scala/collection/generic/VectorTemplate
const #223 = Asciz	foreach;
const #224 = Asciz	(Lscala/Function1;)V;
const #225 = NameAndType	#223:#224;//  foreach:(Lscala/Function1;)V
const #226 = InterfaceMethod	#222.#225;	//  scala/collection/generic/VectorTemplate.foreach:(Lscala/Function1;)V
const #227 = Asciz	delete;
const #228 = NameAndType	#227:#58;//  delete:()Z
const #229 = Method	#65.#228;	//  java/io/File.delete:()Z
const #230 = Asciz	f;
const #231 = Asciz	temp1;
const #232 = Asciz	[Ljava/io/File;;
const #233 = Asciz	deleteRecursively;
const #234 = NameAndType	#198:#199;//  scala$io$File$$deleteRecursively:(Ljava/io/File;)Z
const #235 = Method	#10.#234;	//  scala/io/File.scala$io$File$$deleteRecursively:(Ljava/io/File;)Z
const #236 = Asciz	iterator;
const #237 = Asciz	()Lscala/collection/Iterator;;
const #238 = NameAndType	#236:#237;//  iterator:()Lscala/collection/Iterator;
const #239 = InterfaceMethod	#222.#238;	//  scala/collection/generic/VectorTemplate.iterator:()Lscala/collection/Iterator;
const #240 = Asciz	scala/io/File$$anonfun$iterator$1;
const #241 = class	#240;	//  scala/io/File$$anonfun$iterator$1
const #242 = Method	#241.#219;	//  scala/io/File$$anonfun$iterator$1."<init>":(Lscala/io/File;)V
const #243 = Asciz	scala/collection/Iterator;
const #244 = class	#243;	//  scala/collection/Iterator
const #245 = Asciz	map;
const #246 = Asciz	(Lscala/Function1;)Lscala/collection/Iterator;;
const #247 = NameAndType	#245:#246;//  map:(Lscala/Function1;)Lscala/collection/Iterator;
const #248 = InterfaceMethod	#244.#247;	//  scala/collection/Iterator.map:(Lscala/Function1;)Lscala/collection/Iterator;
const #249 = Asciz	scala/package$;
const #250 = class	#249;	//  scala/package$
const #251 = Asciz	Lscala/package$;;
const #252 = NameAndType	#93:#251;//  MODULE$:Lscala/package$;
const #253 = Field	#250.#252;	//  scala/package$.MODULE$:Lscala/package$;
const #254 = Asciz	Iterator;
const #255 = Asciz	()Lscala/collection/Iterator$;;
const #256 = NameAndType	#254:#255;//  Iterator:()Lscala/collection/Iterator$;
const #257 = Method	#250.#256;	//  scala/package$.Iterator:()Lscala/collection/Iterator$;
const #258 = Asciz	scala/collection/Iterator$;
const #259 = class	#258;	//  scala/collection/Iterator$
const #260 = Asciz	empty;
const #261 = NameAndType	#260:#138;//  empty:()Ljava/lang/Object;
const #262 = Method	#259.#261;	//  scala/collection/Iterator$.empty:()Ljava/lang/Object;
const #263 = Asciz	()Lscala/collection/Iterator<Lscala/io/File;>;;
const #264 = Asciz	stringPrefix;
const #265 = Asciz	(Lscala/collection/generic/TraversableTemplate;)Ljava/lang/String;;
const #266 = NameAndType	#264:#265;//  stringPrefix:(Lscala/collection/generic/TraversableTemplate;)Ljava/lang/String;
const #267 = Method	#19.#266;	//  scala/collection/generic/TraversableTemplate$class.stringPrefix:(Lscala/collection/generic/TraversableTemplate;)Ljava/lang/String;
const #268 = Asciz	addString;
const #269 = Asciz	(Lscala/collection/mutable/StringBuilder;)Lscala/collection/mutable/StringBuilder;;
const #270 = Asciz	(Lscala/collection/generic/TraversableTemplate;Lscala/collection/mutable/StringBuilder;)Lscala/collection/mutable/StringBuilder;;
const #271 = NameAndType	#268:#270;//  addString:(Lscala/collection/generic/TraversableTemplate;Lscala/collection/mutable/StringBuilder;)Lscala/collection/mutable/StringBuilder;
const #272 = Method	#19.#271;	//  scala/collection/generic/TraversableTemplate$class.addString:(Lscala/collection/generic/TraversableTemplate;Lscala/collection/mutable/StringBuilder;)Lscala/collection/mutable/StringBuilder;
const #273 = Asciz	b;
const #274 = Asciz	Lscala/collection/mutable/StringBuilder;;
const #275 = Asciz	(Lscala/collection/mutable/StringBuilder;Ljava/lang/String;)Lscala/collection/mutable/StringBuilder;;
const #276 = Asciz	(Lscala/collection/generic/TraversableTemplate;Lscala/collection/mutable/StringBuilder;Ljava/lang/String;)Lscala/collection/mutable/StringBuilder;;
const #277 = NameAndType	#268:#276;//  addString:(Lscala/collection/generic/TraversableTemplate;Lscala/collection/mutable/StringBuilder;Ljava/lang/String;)Lscala/collection/mutable/StringBuilder;
const #278 = Method	#19.#277;	//  scala/collection/generic/TraversableTemplate$class.addString:(Lscala/collection/generic/TraversableTemplate;Lscala/collection/mutable/StringBuilder;Ljava/lang/String;)Lscala/collection/mutable/StringBuilder;
const #279 = Asciz	sep;
const #280 = Asciz	(Lscala/collection/mutable/StringBuilder;Ljava/lang/String;Ljava/lang/String;Ljava/lang/String;)Lscala/collection/mutable/StringBuilder;;
const #281 = Asciz	(Lscala/collection/generic/TraversableTemplate;Lscala/collection/mutable/StringBuilder;Ljava/lang/String;Ljava/lang/String;Ljava/lang/String;)Lscala/collection/mutable/StringBuilder;;
const #282 = NameAndType	#268:#281;//  addString:(Lscala/collection/generic/TraversableTemplate;Lscala/collection/mutable/StringBuilder;Ljava/lang/String;Ljava/lang/String;Ljava/lang/String;)Lscala/collection/mutable/StringBuilder;
const #283 = Method	#19.#282;	//  scala/collection/generic/TraversableTemplate$class.addString:(Lscala/collection/generic/TraversableTemplate;Lscala/collection/mutable/StringBuilder;Ljava/lang/String;Ljava/lang/String;Ljava/lang/String;)Lscala/collection/mutable/StringBuilder;
const #284 = Asciz	start;
const #285 = Asciz	end;
const #286 = Asciz	mkString;
const #287 = NameAndType	#286:#265;//  mkString:(Lscala/collection/generic/TraversableTemplate;)Ljava/lang/String;
const #288 = Method	#19.#287;	//  scala/collection/generic/TraversableTemplate$class.mkString:(Lscala/collection/generic/TraversableTemplate;)Ljava/lang/String;
const #289 = Asciz	(Ljava/lang/String;)Ljava/lang/String;;
const #290 = Asciz	(Lscala/collection/generic/TraversableTemplate;Ljava/lang/String;)Ljava/lang/String;;
const #291 = NameAndType	#286:#290;//  mkString:(Lscala/collection/generic/TraversableTemplate;Ljava/lang/String;)Ljava/lang/String;
const #292 = Method	#19.#291;	//  scala/collection/generic/TraversableTemplate$class.mkString:(Lscala/collection/generic/TraversableTemplate;Ljava/lang/String;)Ljava/lang/String;
const #293 = Asciz	(Ljava/lang/String;Ljava/lang/String;Ljava/lang/String;)Ljava/lang/String;;
const #294 = Asciz	(Lscala/collection/generic/TraversableTemplate;Ljava/lang/String;Ljava/lang/String;Ljava/lang/String;)Ljava/lang/String;;
const #295 = NameAndType	#286:#294;//  mkString:(Lscala/collection/generic/TraversableTemplate;Ljava/lang/String;Ljava/lang/String;Ljava/lang/String;)Ljava/lang/String;
const #296 = Method	#19.#295;	//  scala/collection/generic/TraversableTemplate$class.mkString:(Lscala/collection/generic/TraversableTemplate;Ljava/lang/String;Ljava/lang/String;Ljava/lang/String;)Ljava/lang/String;
const #297 = Asciz	toSet;
const #298 = Asciz	()Lscala/collection/immutable/Set;;
const #299 = Asciz	(Lscala/collection/generic/TraversableTemplate;)Lscala/collection/immutable/Set;;
const #300 = NameAndType	#297:#299;//  toSet:(Lscala/collection/generic/TraversableTemplate;)Lscala/collection/immutable/Set;
const #301 = Method	#19.#300;	//  scala/collection/generic/TraversableTemplate$class.toSet:(Lscala/collection/generic/TraversableTemplate;)Lscala/collection/immutable/Set;
const #302 = Asciz	toSequence;
const #303 = Asciz	()Lscala/collection/Sequence;;
const #304 = Asciz	(Lscala/collection/generic/TraversableTemplate;)Lscala/collection/Sequence;;
const #305 = NameAndType	#302:#304;//  toSequence:(Lscala/collection/generic/TraversableTemplate;)Lscala/collection/Sequence;
const #306 = Method	#19.#305;	//  scala/collection/generic/TraversableTemplate$class.toSequence:(Lscala/collection/generic/TraversableTemplate;)Lscala/collection/Sequence;
const #307 = Asciz	toList;
const #308 = Asciz	()Lscala/collection/immutable/List;;
const #309 = Asciz	(Lscala/collection/generic/TraversableTemplate;)Lscala/collection/immutable/List;;
const #310 = NameAndType	#307:#309;//  toList:(Lscala/collection/generic/TraversableTemplate;)Lscala/collection/immutable/List;
const #311 = Method	#19.#310;	//  scala/collection/generic/TraversableTemplate$class.toList:(Lscala/collection/generic/TraversableTemplate;)Lscala/collection/immutable/List;
const #312 = Asciz	toArray;
const #313 = Asciz	()Lscala/runtime/BoxedArray;;
const #314 = Asciz	(Lscala/collection/generic/TraversableTemplate;)Lscala/runtime/BoxedArray;;
const #315 = NameAndType	#312:#314;//  toArray:(Lscala/collection/generic/TraversableTemplate;)Lscala/runtime/BoxedArray;
const #316 = Method	#19.#315;	//  scala/collection/generic/TraversableTemplate$class.toArray:(Lscala/collection/generic/TraversableTemplate;)Lscala/runtime/BoxedArray;
const #317 = Asciz	copyToArray;
const #318 = Asciz	(Lscala/runtime/BoxedArray;I)V;
const #319 = Asciz	(Lscala/collection/generic/TraversableTemplate;Lscala/runtime/BoxedArray;I)V;
const #320 = NameAndType	#317:#319;//  copyToArray:(Lscala/collection/generic/TraversableTemplate;Lscala/runtime/BoxedArray;I)V
const #321 = Method	#19.#320;	//  scala/collection/generic/TraversableTemplate$class.copyToArray:(Lscala/collection/generic/TraversableTemplate;Lscala/runtime/BoxedArray;I)V
const #322 = Asciz	xs;
const #323 = Asciz	Lscala/runtime/BoxedArray;;
const #324 = Asciz	(Lscala/runtime/BoxedArray;II)V;
const #325 = Asciz	(Lscala/collection/generic/TraversableTemplate;Lscala/runtime/BoxedArray;II)V;
const #326 = NameAndType	#317:#325;//  copyToArray:(Lscala/collection/generic/TraversableTemplate;Lscala/runtime/BoxedArray;II)V
const #327 = Method	#19.#326;	//  scala/collection/generic/TraversableTemplate$class.copyToArray:(Lscala/collection/generic/TraversableTemplate;Lscala/runtime/BoxedArray;II)V
const #328 = Asciz	len;
const #329 = Asciz	copyToBuffer;
const #330 = Asciz	(Lscala/collection/mutable/Buffer;)V;
const #331 = Asciz	(Lscala/collection/generic/TraversableTemplate;Lscala/collection/mutable/Buffer;)V;
const #332 = NameAndType	#329:#331;//  copyToBuffer:(Lscala/collection/generic/TraversableTemplate;Lscala/collection/mutable/Buffer;)V
const #333 = Method	#19.#332;	//  scala/collection/generic/TraversableTemplate$class.copyToBuffer:(Lscala/collection/generic/TraversableTemplate;Lscala/collection/mutable/Buffer;)V
const #334 = Asciz	dest;
const #335 = Asciz	Lscala/collection/mutable/Buffer;;
const #336 = Asciz	splitAt;
const #337 = Asciz	(I)Lscala/Tuple2;;
const #338 = Asciz	(Lscala/collection/generic/TraversableTemplate;I)Lscala/Tuple2;;
const #339 = NameAndType	#336:#338;//  splitAt:(Lscala/collection/generic/TraversableTemplate;I)Lscala/Tuple2;
const #340 = Method	#19.#339;	//  scala/collection/generic/TraversableTemplate$class.splitAt:(Lscala/collection/generic/TraversableTemplate;I)Lscala/Tuple2;
const #341 = Asciz	n;
const #342 = Asciz	span;
const #343 = Asciz	(Lscala/Function1;)Lscala/Tuple2;;
const #344 = Asciz	(Lscala/collection/generic/TraversableTemplate;Lscala/Function1;)Lscala/Tuple2;;
const #345 = NameAndType	#342:#344;//  span:(Lscala/collection/generic/TraversableTemplate;Lscala/Function1;)Lscala/Tuple2;
const #346 = Method	#19.#345;	//  scala/collection/generic/TraversableTemplate$class.span:(Lscala/collection/generic/TraversableTemplate;Lscala/Function1;)Lscala/Tuple2;
const #347 = Asciz	p;
const #348 = Asciz	Lscala/Function1;;
const #349 = Asciz	dropWhile;
const #350 = Asciz	(Lscala/Function1;)Lscala/collection/generic/TraversableTemplate;;
const #351 = Asciz	(Lscala/collection/generic/TraversableTemplate;Lscala/Function1;)Lscala/collection/generic/TraversableTemplate;;
const #352 = NameAndType	#349:#351;//  dropWhile:(Lscala/collection/generic/TraversableTemplate;Lscala/Function1;)Lscala/collection/generic/TraversableTemplate;
const #353 = Method	#19.#352;	//  scala/collection/generic/TraversableTemplate$class.dropWhile:(Lscala/collection/generic/TraversableTemplate;Lscala/Function1;)Lscala/collection/generic/TraversableTemplate;
const #354 = Asciz	takeWhile;
const #355 = NameAndType	#354:#351;//  takeWhile:(Lscala/collection/generic/TraversableTemplate;Lscala/Function1;)Lscala/collection/generic/TraversableTemplate;
const #356 = Method	#19.#355;	//  scala/collection/generic/TraversableTemplate$class.takeWhile:(Lscala/collection/generic/TraversableTemplate;Lscala/Function1;)Lscala/collection/generic/TraversableTemplate;
const #357 = Asciz	slice;
const #358 = Asciz	(II)Lscala/collection/generic/TraversableTemplate;;
const #359 = Asciz	(Lscala/collection/generic/TraversableTemplate;II)Lscala/collection/generic/TraversableTemplate;;
const #360 = NameAndType	#357:#359;//  slice:(Lscala/collection/generic/TraversableTemplate;II)Lscala/collection/generic/TraversableTemplate;
const #361 = Method	#19.#360;	//  scala/collection/generic/TraversableTemplate$class.slice:(Lscala/collection/generic/TraversableTemplate;II)Lscala/collection/generic/TraversableTemplate;
const #362 = Asciz	drop;
const #363 = Asciz	(I)Lscala/collection/generic/TraversableTemplate;;
const #364 = Asciz	(Lscala/collection/generic/TraversableTemplate;I)Lscala/collection/generic/TraversableTemplate;;
const #365 = NameAndType	#362:#364;//  drop:(Lscala/collection/generic/TraversableTemplate;I)Lscala/collection/generic/TraversableTemplate;
const #366 = Method	#19.#365;	//  scala/collection/generic/TraversableTemplate$class.drop:(Lscala/collection/generic/TraversableTemplate;I)Lscala/collection/generic/TraversableTemplate;
const #367 = Asciz	take;
const #368 = NameAndType	#367:#364;//  take:(Lscala/collection/generic/TraversableTemplate;I)Lscala/collection/generic/TraversableTemplate;
const #369 = Method	#19.#368;	//  scala/collection/generic/TraversableTemplate$class.take:(Lscala/collection/generic/TraversableTemplate;I)Lscala/collection/generic/TraversableTemplate;
const #370 = Asciz	init;
const #371 = Asciz	()Lscala/collection/generic/TraversableTemplate;;
const #372 = Asciz	(Lscala/collection/generic/TraversableTemplate;)Lscala/collection/generic/TraversableTemplate;;
const #373 = NameAndType	#370:#372;//  init:(Lscala/collection/generic/TraversableTemplate;)Lscala/collection/generic/TraversableTemplate;
const #374 = Method	#19.#373;	//  scala/collection/generic/TraversableTemplate$class.init:(Lscala/collection/generic/TraversableTemplate;)Lscala/collection/generic/TraversableTemplate;
const #375 = Asciz	lastOption;
const #376 = Asciz	(Lscala/collection/generic/TraversableTemplate;)Lscala/Option;;
const #377 = NameAndType	#375:#376;//  lastOption:(Lscala/collection/generic/TraversableTemplate;)Lscala/Option;
const #378 = Method	#19.#377;	//  scala/collection/generic/TraversableTemplate$class.lastOption:(Lscala/collection/generic/TraversableTemplate;)Lscala/Option;
const #379 = Asciz	last;
const #380 = Asciz	(Lscala/collection/generic/TraversableTemplate;)Ljava/lang/Object;;
const #381 = NameAndType	#379:#380;//  last:(Lscala/collection/generic/TraversableTemplate;)Ljava/lang/Object;
const #382 = Method	#19.#381;	//  scala/collection/generic/TraversableTemplate$class.last:(Lscala/collection/generic/TraversableTemplate;)Ljava/lang/Object;
const #383 = Asciz	tail;
const #384 = NameAndType	#383:#372;//  tail:(Lscala/collection/generic/TraversableTemplate;)Lscala/collection/generic/TraversableTemplate;
const #385 = Method	#19.#384;	//  scala/collection/generic/TraversableTemplate$class.tail:(Lscala/collection/generic/TraversableTemplate;)Lscala/collection/generic/TraversableTemplate;
const #386 = Asciz	headOption;
const #387 = NameAndType	#386:#376;//  headOption:(Lscala/collection/generic/TraversableTemplate;)Lscala/Option;
const #388 = Method	#19.#387;	//  scala/collection/generic/TraversableTemplate$class.headOption:(Lscala/collection/generic/TraversableTemplate;)Lscala/Option;
const #389 = Asciz	reduceRightOption;
const #390 = Asciz	(Lscala/Function2;)Lscala/Option;;
const #391 = Asciz	(Lscala/collection/generic/TraversableTemplate;Lscala/Function2;)Lscala/Option;;
const #392 = NameAndType	#389:#391;//  reduceRightOption:(Lscala/collection/generic/TraversableTemplate;Lscala/Function2;)Lscala/Option;
const #393 = Method	#19.#392;	//  scala/collection/generic/TraversableTemplate$class.reduceRightOption:(Lscala/collection/generic/TraversableTemplate;Lscala/Function2;)Lscala/Option;
const #394 = Asciz	op;
const #395 = Asciz	Lscala/Function2;;
const #396 = Asciz	reduceLeftOption;
const #397 = NameAndType	#396:#391;//  reduceLeftOption:(Lscala/collection/generic/TraversableTemplate;Lscala/Function2;)Lscala/Option;
const #398 = Method	#19.#397;	//  scala/collection/generic/TraversableTemplate$class.reduceLeftOption:(Lscala/collection/generic/TraversableTemplate;Lscala/Function2;)Lscala/Option;
const #399 = Asciz	reduceLeft;
const #400 = Asciz	(Lscala/Function2;)Ljava/lang/Object;;
const #401 = Asciz	(Lscala/collection/generic/TraversableTemplate;Lscala/Function2;)Ljava/lang/Object;;
const #402 = NameAndType	#399:#401;//  reduceLeft:(Lscala/collection/generic/TraversableTemplate;Lscala/Function2;)Ljava/lang/Object;
const #403 = Method	#19.#402;	//  scala/collection/generic/TraversableTemplate$class.reduceLeft:(Lscala/collection/generic/TraversableTemplate;Lscala/Function2;)Ljava/lang/Object;
const #404 = Asciz	$colon$bslash;
const #405 = Asciz	(Ljava/lang/Object;Lscala/Function2;)Ljava/lang/Object;;
const #406 = Asciz	(Lscala/collection/generic/TraversableTemplate;Ljava/lang/Object;Lscala/Function2;)Ljava/lang/Object;;
const #407 = NameAndType	#404:#406;//  $colon$bslash:(Lscala/collection/generic/TraversableTemplate;Ljava/lang/Object;Lscala/Function2;)Ljava/lang/Object;
const #408 = Method	#19.#407;	//  scala/collection/generic/TraversableTemplate$class.$colon$bslash:(Lscala/collection/generic/TraversableTemplate;Ljava/lang/Object;Lscala/Function2;)Ljava/lang/Object;
const #409 = Asciz	z;
const #410 = Asciz	$div$colon;
const #411 = NameAndType	#410:#406;//  $div$colon:(Lscala/collection/generic/TraversableTemplate;Ljava/lang/Object;Lscala/Function2;)Ljava/lang/Object;
const #412 = Method	#19.#411;	//  scala/collection/generic/TraversableTemplate$class.$div$colon:(Lscala/collection/generic/TraversableTemplate;Ljava/lang/Object;Lscala/Function2;)Ljava/lang/Object;
const #413 = Asciz	foldLeft;
const #414 = NameAndType	#413:#406;//  foldLeft:(Lscala/collection/generic/TraversableTemplate;Ljava/lang/Object;Lscala/Function2;)Ljava/lang/Object;
const #415 = Method	#19.#414;	//  scala/collection/generic/TraversableTemplate$class.foldLeft:(Lscala/collection/generic/TraversableTemplate;Ljava/lang/Object;Lscala/Function2;)Ljava/lang/Object;
const #416 = Asciz	find;
const #417 = Asciz	(Lscala/Function1;)Lscala/Option;;
const #418 = Asciz	(Lscala/collection/generic/TraversableTemplate;Lscala/Function1;)Lscala/Option;;
const #419 = NameAndType	#416:#418;//  find:(Lscala/collection/generic/TraversableTemplate;Lscala/Function1;)Lscala/Option;
const #420 = Method	#19.#419;	//  scala/collection/generic/TraversableTemplate$class.find:(Lscala/collection/generic/TraversableTemplate;Lscala/Function1;)Lscala/Option;
const #421 = Asciz	count;
const #422 = Asciz	(Lscala/Function1;)I;
const #423 = Asciz	(Lscala/collection/generic/TraversableTemplate;Lscala/Function1;)I;
const #424 = NameAndType	#421:#423;//  count:(Lscala/collection/generic/TraversableTemplate;Lscala/Function1;)I
const #425 = Method	#19.#424;	//  scala/collection/generic/TraversableTemplate$class.count:(Lscala/collection/generic/TraversableTemplate;Lscala/Function1;)I
const #426 = Asciz	exists;
const #427 = Asciz	(Lscala/Function1;)Z;
const #428 = Asciz	(Lscala/collection/generic/TraversableTemplate;Lscala/Function1;)Z;
const #429 = NameAndType	#426:#428;//  exists:(Lscala/collection/generic/TraversableTemplate;Lscala/Function1;)Z
const #430 = Method	#19.#429;	//  scala/collection/generic/TraversableTemplate$class.exists:(Lscala/collection/generic/TraversableTemplate;Lscala/Function1;)Z
const #431 = Asciz	forall;
const #432 = NameAndType	#431:#428;//  forall:(Lscala/collection/generic/TraversableTemplate;Lscala/Function1;)Z
const #433 = Method	#19.#432;	//  scala/collection/generic/TraversableTemplate$class.forall:(Lscala/collection/generic/TraversableTemplate;Lscala/Function1;)Z
const #434 = Asciz	groupBy;
const #435 = Asciz	(Lscala/Function1;)Lscala/collection/Map;;
const #436 = Asciz	(Lscala/collection/generic/TraversableTemplate;Lscala/Function1;)Lscala/collection/Map;;
const #437 = NameAndType	#434:#436;//  groupBy:(Lscala/collection/generic/TraversableTemplate;Lscala/Function1;)Lscala/collection/Map;
const #438 = Method	#19.#437;	//  scala/collection/generic/TraversableTemplate$class.groupBy:(Lscala/collection/generic/TraversableTemplate;Lscala/Function1;)Lscala/collection/Map;
const #439 = Asciz	partition;
const #440 = NameAndType	#439:#344;//  partition:(Lscala/collection/generic/TraversableTemplate;Lscala/Function1;)Lscala/Tuple2;
const #441 = Method	#19.#440;	//  scala/collection/generic/TraversableTemplate$class.partition:(Lscala/collection/generic/TraversableTemplate;Lscala/Function1;)Lscala/Tuple2;
const #442 = Asciz	remove;
const #443 = NameAndType	#442:#351;//  remove:(Lscala/collection/generic/TraversableTemplate;Lscala/Function1;)Lscala/collection/generic/TraversableTemplate;
const #444 = Method	#19.#443;	//  scala/collection/generic/TraversableTemplate$class.remove:(Lscala/collection/generic/TraversableTemplate;Lscala/Function1;)Lscala/collection/generic/TraversableTemplate;
const #445 = Asciz	filterNot;
const #446 = NameAndType	#445:#351;//  filterNot:(Lscala/collection/generic/TraversableTemplate;Lscala/Function1;)Lscala/collection/generic/TraversableTemplate;
const #447 = Method	#19.#446;	//  scala/collection/generic/TraversableTemplate$class.filterNot:(Lscala/collection/generic/TraversableTemplate;Lscala/Function1;)Lscala/collection/generic/TraversableTemplate;
const #448 = Asciz	filterMap;
const #449 = Asciz	(Lscala/PartialFunction;Lscala/collection/generic/BuilderFactory;)Ljava/lang/Object;;
const #450 = Asciz	(Lscala/collection/generic/TraversableTemplate;Lscala/PartialFunction;Lscala/collection/generic/BuilderFactory;)Ljava/lang/Object;;
const #451 = NameAndType	#448:#450;//  filterMap:(Lscala/collection/generic/TraversableTemplate;Lscala/PartialFunction;Lscala/collection/generic/BuilderFactory;)Ljava/lang/Object;
const #452 = Method	#19.#451;	//  scala/collection/generic/TraversableTemplate$class.filterMap:(Lscala/collection/generic/TraversableTemplate;Lscala/PartialFunction;Lscala/collection/generic/BuilderFactory;)Ljava/lang/Object;
const #453 = Asciz	pf;
const #454 = Asciz	Lscala/PartialFunction;;
const #455 = Asciz	bf;
const #456 = Asciz	Lscala/collection/generic/BuilderFactory;;
const #457 = Asciz	filter;
const #458 = NameAndType	#457:#351;//  filter:(Lscala/collection/generic/TraversableTemplate;Lscala/Function1;)Lscala/collection/generic/TraversableTemplate;
const #459 = Method	#19.#458;	//  scala/collection/generic/TraversableTemplate$class.filter:(Lscala/collection/generic/TraversableTemplate;Lscala/Function1;)Lscala/collection/generic/TraversableTemplate;
const #460 = Asciz	flatMap;
const #461 = Asciz	(Lscala/Function1;Lscala/collection/generic/BuilderFactory;)Ljava/lang/Object;;
const #462 = Asciz	(Lscala/collection/generic/TraversableTemplate;Lscala/Function1;Lscala/collection/generic/BuilderFactory;)Ljava/lang/Object;;
const #463 = NameAndType	#460:#462;//  flatMap:(Lscala/collection/generic/TraversableTemplate;Lscala/Function1;Lscala/collection/generic/BuilderFactory;)Ljava/lang/Object;
const #464 = Method	#19.#463;	//  scala/collection/generic/TraversableTemplate$class.flatMap:(Lscala/collection/generic/TraversableTemplate;Lscala/Function1;Lscala/collection/generic/BuilderFactory;)Ljava/lang/Object;
const #465 = NameAndType	#245:#462;//  map:(Lscala/collection/generic/TraversableTemplate;Lscala/Function1;Lscala/collection/generic/BuilderFactory;)Ljava/lang/Object;
const #466 = Method	#19.#465;	//  scala/collection/generic/TraversableTemplate$class.map:(Lscala/collection/generic/TraversableTemplate;Lscala/Function1;Lscala/collection/generic/BuilderFactory;)Ljava/lang/Object;
const #467 = Asciz	$plus$plus;
const #468 = Asciz	(Lscala/collection/Iterator;Lscala/collection/generic/BuilderFactory;)Ljava/lang/Object;;
const #469 = Asciz	(Lscala/collection/generic/TraversableTemplate;Lscala/collection/Iterator;Lscala/collection/generic/BuilderFactory;)Ljava/lang/Object;;
const #470 = NameAndType	#467:#469;//  $plus$plus:(Lscala/collection/generic/TraversableTemplate;Lscala/collection/Iterator;Lscala/collection/generic/BuilderFactory;)Ljava/lang/Object;
const #471 = Method	#19.#470;	//  scala/collection/generic/TraversableTemplate$class.$plus$plus:(Lscala/collection/generic/TraversableTemplate;Lscala/collection/Iterator;Lscala/collection/generic/BuilderFactory;)Ljava/lang/Object;
const #472 = Asciz	that;
const #473 = Asciz	Lscala/collection/Iterator;;
const #474 = Asciz	(Lscala/collection/Traversable;Lscala/collection/generic/BuilderFactory;)Ljava/lang/Object;;
const #475 = Asciz	(Lscala/collection/generic/TraversableTemplate;Lscala/collection/Traversable;Lscala/collection/generic/BuilderFactory;)Ljava/lang/Object;;
const #476 = NameAndType	#467:#475;//  $plus$plus:(Lscala/collection/generic/TraversableTemplate;Lscala/collection/Traversable;Lscala/collection/generic/BuilderFactory;)Ljava/lang/Object;
const #477 = Method	#19.#476;	//  scala/collection/generic/TraversableTemplate$class.$plus$plus:(Lscala/collection/generic/TraversableTemplate;Lscala/collection/Traversable;Lscala/collection/generic/BuilderFactory;)Ljava/lang/Object;
const #478 = Asciz	Lscala/collection/Traversable;;
const #479 = Asciz	hasDefiniteSize;
const #480 = Asciz	(Lscala/collection/generic/TraversableTemplate;)Z;
const #481 = NameAndType	#479:#480;//  hasDefiniteSize:(Lscala/collection/generic/TraversableTemplate;)Z
const #482 = Method	#19.#481;	//  scala/collection/generic/TraversableTemplate$class.hasDefiniteSize:(Lscala/collection/generic/TraversableTemplate;)Z
const #483 = Asciz	size;
const #484 = Asciz	(Lscala/collection/generic/TraversableTemplate;)I;
const #485 = NameAndType	#483:#484;//  size:(Lscala/collection/generic/TraversableTemplate;)I
const #486 = Method	#19.#485;	//  scala/collection/generic/TraversableTemplate$class.size:(Lscala/collection/generic/TraversableTemplate;)I
const #487 = Asciz	nonEmpty;
const #488 = NameAndType	#487:#480;//  nonEmpty:(Lscala/collection/generic/TraversableTemplate;)Z
const #489 = Method	#19.#488;	//  scala/collection/generic/TraversableTemplate$class.nonEmpty:(Lscala/collection/generic/TraversableTemplate;)Z
const #490 = Asciz	thisCollection;
const #491 = NameAndType	#490:#372;//  thisCollection:(Lscala/collection/generic/TraversableTemplate;)Lscala/collection/generic/TraversableTemplate;
const #492 = Method	#19.#491;	//  scala/collection/generic/TraversableTemplate$class.thisCollection:(Lscala/collection/generic/TraversableTemplate;)Lscala/collection/generic/TraversableTemplate;
const #493 = Asciz	transpose;
const #494 = Asciz	(Lscala/Function1;)Lscala/collection/Traversable;;
const #495 = Asciz	(Lscala/collection/generic/TraversableClass;Lscala/Function1;)Lscala/collection/Traversable;;
const #496 = NameAndType	#493:#495;//  transpose:(Lscala/collection/generic/TraversableClass;Lscala/Function1;)Lscala/collection/Traversable;
const #497 = Method	#25.#496;	//  scala/collection/generic/TraversableClass$class.transpose:(Lscala/collection/generic/TraversableClass;Lscala/Function1;)Lscala/collection/Traversable;
const #498 = Asciz	toTraversable;
const #499 = Asciz	flatten;
const #500 = NameAndType	#499:#495;//  flatten:(Lscala/collection/generic/TraversableClass;Lscala/Function1;)Lscala/collection/Traversable;
const #501 = Method	#25.#500;	//  scala/collection/generic/TraversableClass$class.flatten:(Lscala/collection/generic/TraversableClass;Lscala/Function1;)Lscala/collection/Traversable;
const #502 = Asciz	unzip;
const #503 = Asciz	(Lscala/collection/generic/TraversableClass;Lscala/Function1;)Lscala/Tuple2;;
const #504 = NameAndType	#502:#503;//  unzip:(Lscala/collection/generic/TraversableClass;Lscala/Function1;)Lscala/Tuple2;
const #505 = Method	#25.#504;	//  scala/collection/generic/TraversableClass$class.unzip:(Lscala/collection/generic/TraversableClass;Lscala/Function1;)Lscala/Tuple2;
const #506 = Asciz	toPair;
const #507 = Asciz	genericBuilder;
const #508 = Asciz	()Lscala/collection/generic/Builder;;
const #509 = Asciz	(Lscala/collection/generic/TraversableClass;)Lscala/collection/generic/Builder;;
const #510 = NameAndType	#507:#509;//  genericBuilder:(Lscala/collection/generic/TraversableClass;)Lscala/collection/generic/Builder;
const #511 = Method	#25.#510;	//  scala/collection/generic/TraversableClass$class.genericBuilder:(Lscala/collection/generic/TraversableClass;)Lscala/collection/generic/Builder;
const #512 = Asciz	newBuilder;
const #513 = NameAndType	#512:#509;//  newBuilder:(Lscala/collection/generic/TraversableClass;)Lscala/collection/generic/Builder;
const #514 = Method	#25.#513;	//  scala/collection/generic/TraversableClass$class.newBuilder:(Lscala/collection/generic/TraversableClass;)Lscala/collection/generic/Builder;
const #515 = Asciz	projection;
const #516 = Asciz	(Lscala/collection/generic/IterableTemplate;)Ljava/lang/Object;;
const #517 = NameAndType	#515:#516;//  projection:(Lscala/collection/generic/IterableTemplate;)Ljava/lang/Object;
const #518 = Method	#35.#517;	//  scala/collection/generic/IterableTemplate$class.projection:(Lscala/collection/generic/IterableTemplate;)Ljava/lang/Object;
const #519 = Asciz	toSeq;
const #520 = Asciz	(Lscala/collection/generic/IterableTemplate;)Lscala/collection/Sequence;;
const #521 = NameAndType	#519:#520;//  toSeq:(Lscala/collection/generic/IterableTemplate;)Lscala/collection/Sequence;
const #522 = Method	#35.#521;	//  scala/collection/generic/IterableTemplate$class.toSeq:(Lscala/collection/generic/IterableTemplate;)Lscala/collection/Sequence;
const #523 = Asciz	firstOption;
const #524 = Asciz	(Lscala/collection/generic/IterableTemplate;)Lscala/Option;;
const #525 = NameAndType	#523:#524;//  firstOption:(Lscala/collection/generic/IterableTemplate;)Lscala/Option;
const #526 = Method	#35.#525;	//  scala/collection/generic/IterableTemplate$class.firstOption:(Lscala/collection/generic/IterableTemplate;)Lscala/Option;
const #527 = Asciz	first;
const #528 = NameAndType	#527:#516;//  first:(Lscala/collection/generic/IterableTemplate;)Ljava/lang/Object;
const #529 = Method	#35.#528;	//  scala/collection/generic/IterableTemplate$class.first:(Lscala/collection/generic/IterableTemplate;)Ljava/lang/Object;
const #530 = Asciz	(Lscala/collection/generic/IterableTemplate;II)Lscala/collection/generic/IterableView;;
const #531 = NameAndType	#47:#530;//  view:(Lscala/collection/generic/IterableTemplate;II)Lscala/collection/generic/IterableView;
const #532 = Method	#35.#531;	//  scala/collection/generic/IterableTemplate$class.view:(Lscala/collection/generic/IterableTemplate;II)Lscala/collection/generic/IterableView;
const #533 = NameAndType	#47:#516;//  view:(Lscala/collection/generic/IterableTemplate;)Ljava/lang/Object;
const #534 = Method	#35.#533;	//  scala/collection/generic/IterableTemplate$class.view:(Lscala/collection/generic/IterableTemplate;)Ljava/lang/Object;
const #535 = Asciz	toStream;
const #536 = Asciz	()Lscala/collection/immutable/Stream;;
const #537 = Asciz	(Lscala/collection/generic/IterableTemplate;)Lscala/collection/immutable/Stream;;
const #538 = NameAndType	#535:#537;//  toStream:(Lscala/collection/generic/IterableTemplate;)Lscala/collection/immutable/Stream;
const #539 = Method	#35.#538;	//  scala/collection/generic/IterableTemplate$class.toStream:(Lscala/collection/generic/IterableTemplate;)Lscala/collection/immutable/Stream;
const #540 = Asciz	sameElements;
const #541 = Asciz	(Lscala/collection/Iterable;)Z;
const #542 = Asciz	(Lscala/collection/generic/IterableTemplate;Lscala/collection/Iterable;)Z;
const #543 = NameAndType	#540:#542;//  sameElements:(Lscala/collection/generic/IterableTemplate;Lscala/collection/Iterable;)Z
const #544 = Method	#35.#543;	//  scala/collection/generic/IterableTemplate$class.sameElements:(Lscala/collection/generic/IterableTemplate;Lscala/collection/Iterable;)Z
const #545 = Asciz	Lscala/collection/Iterable;;
const #546 = Asciz	dropRight;
const #547 = Asciz	(I)Lscala/collection/generic/IterableTemplate;;
const #548 = Asciz	(Lscala/collection/generic/IterableTemplate;I)Lscala/collection/generic/IterableTemplate;;
const #549 = NameAndType	#546:#548;//  dropRight:(Lscala/collection/generic/IterableTemplate;I)Lscala/collection/generic/IterableTemplate;
const #550 = Method	#35.#549;	//  scala/collection/generic/IterableTemplate$class.dropRight:(Lscala/collection/generic/IterableTemplate;I)Lscala/collection/generic/IterableTemplate;
const #551 = Asciz	takeRight;
const #552 = NameAndType	#551:#548;//  takeRight:(Lscala/collection/generic/IterableTemplate;I)Lscala/collection/generic/IterableTemplate;
const #553 = Method	#35.#552;	//  scala/collection/generic/IterableTemplate$class.takeRight:(Lscala/collection/generic/IterableTemplate;I)Lscala/collection/generic/IterableTemplate;
const #554 = Asciz	head;
const #555 = NameAndType	#554:#516;//  head:(Lscala/collection/generic/IterableTemplate;)Ljava/lang/Object;
const #556 = Method	#35.#555;	//  scala/collection/generic/IterableTemplate$class.head:(Lscala/collection/generic/IterableTemplate;)Ljava/lang/Object;
const #557 = Asciz	toIterable;
const #558 = Asciz	()Lscala/collection/Iterable;;
const #559 = Asciz	(Lscala/collection/generic/IterableTemplate;)Lscala/collection/Iterable;;
const #560 = NameAndType	#557:#559;//  toIterable:(Lscala/collection/generic/IterableTemplate;)Lscala/collection/Iterable;
const #561 = Method	#35.#560;	//  scala/collection/generic/IterableTemplate$class.toIterable:(Lscala/collection/generic/IterableTemplate;)Lscala/collection/Iterable;
const #562 = Asciz	reduceRight;
const #563 = Asciz	(Lscala/collection/generic/IterableTemplate;Lscala/Function2;)Ljava/lang/Object;;
const #564 = NameAndType	#562:#563;//  reduceRight:(Lscala/collection/generic/IterableTemplate;Lscala/Function2;)Ljava/lang/Object;
const #565 = Method	#35.#564;	//  scala/collection/generic/IterableTemplate$class.reduceRight:(Lscala/collection/generic/IterableTemplate;Lscala/Function2;)Ljava/lang/Object;
const #566 = Asciz	foldRight;
const #567 = Asciz	(Lscala/collection/generic/IterableTemplate;Ljava/lang/Object;Lscala/Function2;)Ljava/lang/Object;;
const #568 = NameAndType	#566:#567;//  foldRight:(Lscala/collection/generic/IterableTemplate;Ljava/lang/Object;Lscala/Function2;)Ljava/lang/Object;
const #569 = Method	#35.#568;	//  scala/collection/generic/IterableTemplate$class.foldRight:(Lscala/collection/generic/IterableTemplate;Ljava/lang/Object;Lscala/Function2;)Ljava/lang/Object;
const #570 = Asciz	(Lscala/collection/generic/IterableTemplate;)Z;
const #571 = NameAndType	#134:#570;//  isEmpty:(Lscala/collection/generic/IterableTemplate;)Z
const #572 = Method	#35.#571;	//  scala/collection/generic/IterableTemplate$class.isEmpty:(Lscala/collection/generic/IterableTemplate;)Z
const #573 = Asciz	(Lscala/collection/generic/IterableTemplate;Lscala/Function1;)V;
const #574 = NameAndType	#223:#573;//  foreach:(Lscala/collection/generic/IterableTemplate;Lscala/Function1;)V
const #575 = Method	#35.#574;	//  scala/collection/generic/IterableTemplate$class.foreach:(Lscala/collection/generic/IterableTemplate;Lscala/Function1;)V
const #576 = Asciz	elements;
const #577 = Asciz	(Lscala/collection/generic/IterableTemplate;)Lscala/collection/Iterator;;
const #578 = NameAndType	#576:#577;//  elements:(Lscala/collection/generic/IterableTemplate;)Lscala/collection/Iterator;
const #579 = Method	#35.#578;	//  scala/collection/generic/IterableTemplate$class.elements:(Lscala/collection/generic/IterableTemplate;)Lscala/collection/Iterator;
const #580 = Asciz	companion;
const #581 = Asciz	()Lscala/collection/generic/Companion;;
const #582 = Asciz	(Lscala/collection/Iterable;)Lscala/collection/generic/Companion;;
const #583 = NameAndType	#580:#582;//  companion:(Lscala/collection/Iterable;)Lscala/collection/generic/Companion;
const #584 = Method	#40.#583;	//  scala/collection/Iterable$class.companion:(Lscala/collection/Iterable;)Lscala/collection/generic/Companion;
const #585 = Asciz	Ljava/lang/Object;Lscala/collection/Iterable<Lscala/io/File;>;Lscala/ScalaObject;;
const #586 = Asciz	ScalaSig;
const #587 = Asciz	InnerClasses;
const #588 = Asciz	$anonfun$iterator$1;
const #589 = Asciz	$anonfun$scala$io$File$$deleteRecursively$1;
const #590 = Asciz	scala/collection/Iterable;
const #591 = class	#590;	//  scala/collection/Iterable
const #592 = Asciz	scala/ScalaObject;
const #593 = class	#592;	//  scala/ScalaObject

{
public scala.io.File(java.io.File);
  Code:
   Stack=2, Locals=2, Args_size=2
   0:	aload_0
   1:	aload_1
   2:	putfield	#12; //Field file:Ljava/io/File;
   5:	aload_0
   6:	invokespecial	#17; //Method java/lang/Object."<init>":()V
   9:	aload_0
   10:	invokestatic	#23; //Method scala/collection/generic/TraversableTemplate$class.$init$:(Lscala/collection/generic/TraversableTemplate;)V
   13:	aload_0
   14:	invokestatic	#28; //Method scala/collection/generic/TraversableClass$class.$init$:(Lscala/collection/generic/TraversableClass;)V
   17:	aload_0
   18:	invokestatic	#33; //Method scala/collection/Traversable$class.$init$:(Lscala/collection/Traversable;)V
   21:	aload_0
   22:	invokestatic	#38; //Method scala/collection/generic/IterableTemplate$class.$init$:(Lscala/collection/generic/IterableTemplate;)V
   25:	aload_0
   26:	invokestatic	#43; //Method scala/collection/Iterable$class.$init$:(Lscala/collection/Iterable;)V
   29:	return
  LineNumberTable: 
   line 31: 0

  LocalVariableTable: 
   Start  Length  Slot  Name   Signature
   0      30      0    this       Lscala/io/File;
   0      30      1    file       Ljava/io/File;


public scala.collection.generic.TraversableView view(int, int);
  Code:
   Stack=3, Locals=3, Args_size=3
   0:	aload_0
   1:	iload_1
   2:	iload_2
   3:	invokeinterface	#53,  3; //InterfaceMethod scala/collection/generic/IterableTemplate.view:(II)Lscala/collection/generic/IterableView;
   8:	areturn
  LineNumberTable: 
   line 31: 0

  LocalVariableTable: 
   Start  Length  Slot  Name   Signature
   0      9      0    this       Lscala/io/File;
   0      9      1    from       I
   0      9      2    until       I


public boolean outputStream$default$1();
  Code:
   Stack=1, Locals=1, Args_size=1
   0:	iconst_0
   1:	ireturn
  LineNumberTable: 
   line 56: 0


public int hashCode();
  Code:
   Stack=1, Locals=1, Args_size=1
   0:	aload_0
   1:	invokevirtual	#63; //Method file:()Ljava/io/File;
   4:	invokevirtual	#67; //Method java/io/File.hashCode:()I
   7:	ireturn
  LineNumberTable: 
   line 75: 0


public boolean equals(java.lang.Object);
  Code:
   Stack=2, Locals=5, Args_size=2
   0:	aload_1
   1:	astore_2
   2:	aload_2
   3:	instanceof	#10; //class scala/io/File
   6:	ifeq	53
   9:	aload_2
   10:	checkcast	#10; //class scala/io/File
   13:	astore_3
   14:	aload_0
   15:	invokevirtual	#63; //Method file:()Ljava/io/File;
   18:	aload_3
   19:	invokevirtual	#63; //Method file:()Ljava/io/File;
   22:	astore	4
   24:	dup
   25:	ifnonnull	37
   28:	pop
   29:	aload	4
   31:	ifnull	45
   34:	goto	49
   37:	aload	4
   39:	invokevirtual	#71; //Method java/lang/Object.equals:(Ljava/lang/Object;)Z
   42:	ifeq	49
   45:	iconst_1
   46:	goto	54
   49:	iconst_0
   50:	goto	54
   53:	iconst_0
   54:	ireturn
  LineNumberTable: 
   line 71: 0
   line 72: 14
   line 73: 53
   line 71: 54

  LocalVariableTable: 
   Start  Length  Slot  Name   Signature
   0      55      0    this       Lscala/io/File;
   0      55      1    other       Ljava/lang/Object;
   2      53      2    temp8       Ljava/lang/Object;
   14      39      3    temp9       Lscala/io/File;


public java.lang.String toString();
  Code:
   Stack=1, Locals=1, Args_size=1
   0:	aload_0
   1:	invokevirtual	#63; //Method file:()Ljava/io/File;
   4:	invokevirtual	#79; //Method java/io/File.toString:()Ljava/lang/String;
   7:	areturn
  LineNumberTable: 
   line 70: 0


public scala.io.File $div(java.lang.String);
  Code:
   Stack=6, Locals=2, Args_size=2
   0:	new	#10; //class scala/io/File
   3:	dup
   4:	new	#65; //class java/io/File
   7:	dup
   8:	aload_0
   9:	invokevirtual	#63; //Method file:()Ljava/io/File;
   12:	aload_1
   13:	invokespecial	#84; //Method java/io/File."<init>":(Ljava/io/File;Ljava/lang/String;)V
   16:	invokespecial	#86; //Method "<init>":(Ljava/io/File;)V
   19:	areturn
  LineNumberTable: 
   line 68: 0

  LocalVariableTable: 
   Start  Length  Slot  Name   Signature
   0      20      0    this       Lscala/io/File;
   0      20      1    child       Ljava/lang/String;


public scala.io.Source toSource();
  Code:
   Stack=4, Locals=4, Args_size=1
   0:	aload_0
   1:	invokevirtual	#63; //Method file:()Ljava/io/File;
   4:	astore_1
   5:	getstatic	#96; //Field scala/io/Source$.MODULE$:Lscala/io/Source$;
   8:	invokevirtual	#99; //Method scala/io/Source$.fromFile$default$2:()I
   11:	istore_2
   12:	getstatic	#96; //Field scala/io/Source$.MODULE$:Lscala/io/Source$;
   15:	aload_1
   16:	iload_2
   17:	invokevirtual	#103; //Method scala/io/Source$.fromFile$default$3:(Ljava/io/File;I)Lscala/io/Codec;
   20:	astore_3
   21:	getstatic	#96; //Field scala/io/Source$.MODULE$:Lscala/io/Source$;
   24:	aload_1
   25:	iload_2
   26:	aload_3
   27:	invokevirtual	#107; //Method scala/io/Source$.fromFile:(Ljava/io/File;ILscala/io/Codec;)Lscala/io/Source;
   30:	areturn
  LineNumberTable: 
   line 65: 0

  LocalVariableTable: 
   Start  Length  Slot  Name   Signature
   0      31      0    this       Lscala/io/File;
   5      25      1    x$1       Ljava/io/File;
   12      18      2    x$2       I
   21      9      3    x$3       Lscala/io/Codec;


public scala.Option extension();
  Code:
   Stack=3, Locals=5, Args_size=1
   0:	aload_0
   1:	invokevirtual	#63; //Method file:()Ljava/io/File;
   4:	invokevirtual	#116; //Method java/io/File.getName:()Ljava/lang/String;
   7:	astore_1
   8:	getstatic	#121; //Field scala/io/File$.MODULE$:Lscala/io/File$;
   11:	invokevirtual	#125; //Method scala/io/File$.extensionRegex:()Lscala/util/matching/Regex;
   14:	aload_1
   15:	invokevirtual	#131; //Method scala/util/matching/Regex.unapplySeq:(Ljava/lang/Object;)Lscala/Option;
   18:	astore_2
   19:	aload_2
   20:	invokevirtual	#136; //Method scala/Option.isEmpty:()Z
   23:	ifne	78
   26:	aload_2
   27:	invokevirtual	#140; //Method scala/Option.get:()Ljava/lang/Object;
   30:	checkcast	#142; //class scala/collection/immutable/List
   33:	astore_3
   34:	aload_3
   35:	iconst_1
   36:	invokeinterface	#148,  2; //InterfaceMethod scala/collection/generic/SequenceTemplate.lengthCompare:(I)I
   41:	invokestatic	#154; //Method scala/runtime/BoxesRunTime.boxToInteger:(I)Ljava/lang/Integer;
   44:	iconst_0
   45:	invokestatic	#154; //Method scala/runtime/BoxesRunTime.boxToInteger:(I)Ljava/lang/Integer;
   48:	invokestatic	#157; //Method scala/runtime/BoxesRunTime.equals:(Ljava/lang/Object;Ljava/lang/Object;)Z
   51:	ifeq	78
   54:	aload_3
   55:	iconst_0
   56:	invokeinterface	#163,  2; //InterfaceMethod scala/collection/generic/LinearSequenceTemplate.apply:(I)Ljava/lang/Object;
   61:	checkcast	#165; //class java/lang/String
   64:	astore	4
   66:	new	#167; //class scala/Some
   69:	dup
   70:	aload	4
   72:	invokespecial	#170; //Method scala/Some."<init>":(Ljava/lang/Object;)V
   75:	goto	81
   78:	getstatic	#175; //Field scala/None$.MODULE$:Lscala/None$;
   81:	areturn
  LineNumberTable: 
   line 59: 0
   line 60: 8
   line 59: 19
   line 60: 26
   line 59: 34
   line 60: 54
   line 61: 78
   line 59: 81

  LocalVariableTable: 
   Start  Length  Slot  Name   Signature
   0      82      0    this       Lscala/io/File;
   8      74      1    temp3       Ljava/lang/String;
   19      63      2    temp4       Lscala/Option;
   34      47      3    temp5       Lscala/collection/immutable/List;
   66      9      4    temp6       Ljava/lang/String;

  Signature: length = 0x2
   00 FFFFFFB6 

public java.io.FileOutputStream outputStream(boolean);
  Code:
   Stack=4, Locals=2, Args_size=2
   0:	new	#187; //class java/io/FileOutputStream
   3:	dup
   4:	aload_0
   5:	invokevirtual	#63; //Method file:()Ljava/io/File;
   8:	iload_1
   9:	invokespecial	#190; //Method java/io/FileOutputStream."<init>":(Ljava/io/File;Z)V
   12:	areturn
  LineNumberTable: 
   line 56: 0

  LocalVariableTable: 
   Start  Length  Slot  Name   Signature
   0      13      0    this       Lscala/io/File;
   0      13      1    append       Z


public java.io.FileInputStream inputStream();
  Code:
   Stack=3, Locals=1, Args_size=1
   0:	new	#196; //class java/io/FileInputStream
   3:	dup
   4:	aload_0
   5:	invokevirtual	#63; //Method file:()Ljava/io/File;
   8:	invokespecial	#197; //Method java/io/FileInputStream."<init>":(Ljava/io/File;)V
   11:	areturn
  LineNumberTable: 
   line 53: 0


public final boolean scala$io$File$$deleteRecursively(java.io.File);
  Code:
   Stack=4, Locals=3, Args_size=2
   0:	aload_1
   1:	invokevirtual	#202; //Method java/io/File.isDirectory:()Z
   4:	ifeq	39
   7:	aload_0
   8:	invokevirtual	#63; //Method file:()Ljava/io/File;
   11:	invokevirtual	#206; //Method java/io/File.listFiles:()[Ljava/io/File;
   14:	astore_2
   15:	aload_2
   16:	ifnull	39
   19:	getstatic	#211; //Field scala/runtime/ScalaRunTime$.MODULE$:Lscala/runtime/ScalaRunTime$;
   22:	aload_2
   23:	invokevirtual	#215; //Method scala/runtime/ScalaRunTime$.boxArray:(Ljava/lang/Object;)Lscala/runtime/BoxedArray;
   26:	new	#217; //class scala/io/File$$anonfun$scala$io$File$$deleteRecursively$1
   29:	dup
   30:	aload_0
   31:	invokespecial	#220; //Method scala/io/File$$anonfun$scala$io$File$$deleteRecursively$1."<init>":(Lscala/io/File;)V
   34:	invokeinterface	#226,  2; //InterfaceMethod scala/collection/generic/VectorTemplate.foreach:(Lscala/Function1;)V
   39:	aload_1
   40:	invokevirtual	#229; //Method java/io/File.delete:()Z
   43:	ireturn
  LineNumberTable: 
   line 45: 0
   line 47: 19
   line 49: 39

  LocalVariableTable: 
   Start  Length  Slot  Name   Signature
   0      44      0    this       Lscala/io/File;
   0      44      1    f       Ljava/io/File;
   15      24      2    temp1       [Ljava/io/File;


public boolean deleteRecursively();
  Code:
   Stack=2, Locals=1, Args_size=1
   0:	aload_0
   1:	aload_0
   2:	invokevirtual	#63; //Method file:()Ljava/io/File;
   5:	invokevirtual	#235; //Method scala$io$File$$deleteRecursively:(Ljava/io/File;)Z
   8:	ireturn
  LineNumberTable: 
   line 43: 0


public scala.collection.Iterator iterator();
  Code:
   Stack=4, Locals=1, Args_size=1
   0:	aload_0
   1:	invokevirtual	#63; //Method file:()Ljava/io/File;
   4:	invokevirtual	#202; //Method java/io/File.isDirectory:()Z
   7:	ifeq	44
   10:	getstatic	#211; //Field scala/runtime/ScalaRunTime$.MODULE$:Lscala/runtime/ScalaRunTime$;
   13:	aload_0
   14:	invokevirtual	#63; //Method file:()Ljava/io/File;
   17:	invokevirtual	#206; //Method java/io/File.listFiles:()[Ljava/io/File;
   20:	invokevirtual	#215; //Method scala/runtime/ScalaRunTime$.boxArray:(Ljava/lang/Object;)Lscala/runtime/BoxedArray;
   23:	invokeinterface	#239,  1; //InterfaceMethod scala/collection/generic/VectorTemplate.iterator:()Lscala/collection/Iterator;
   28:	new	#241; //class scala/io/File$$anonfun$iterator$1
   31:	dup
   32:	aload_0
   33:	invokespecial	#242; //Method scala/io/File$$anonfun$iterator$1."<init>":(Lscala/io/File;)V
   36:	invokeinterface	#248,  2; //InterfaceMethod scala/collection/Iterator.map:(Lscala/Function1;)Lscala/collection/Iterator;
   41:	goto	56
   44:	getstatic	#253; //Field scala/package$.MODULE$:Lscala/package$;
   47:	invokevirtual	#257; //Method scala/package$.Iterator:()Lscala/collection/Iterator$;
   50:	invokevirtual	#262; //Method scala/collection/Iterator$.empty:()Ljava/lang/Object;
   53:	checkcast	#244; //class scala/collection/Iterator
   56:	areturn
  LineNumberTable: 
   line 37: 0
   line 38: 44
   line 37: 56

  Signature: length = 0x2
   01 07 

public java.io.File file();
  Code:
   Stack=1, Locals=1, Args_size=1
   0:	aload_0
   1:	getfield	#12; //Field file:Ljava/io/File;
   4:	areturn
  LineNumberTable: 
   line 31: 0


public java.lang.String stringPrefix();
  Code:
   Stack=1, Locals=1, Args_size=1
   0:	aload_0
   1:	invokestatic	#267; //Method scala/collection/generic/TraversableTemplate$class.stringPrefix:(Lscala/collection/generic/TraversableTemplate;)Ljava/lang/String;
   4:	areturn
  LineNumberTable: 
   line 31: 0


public scala.collection.mutable.StringBuilder addString(scala.collection.mutable.StringBuilder);
  Code:
   Stack=2, Locals=2, Args_size=2
   0:	aload_0
   1:	aload_1
   2:	invokestatic	#272; //Method scala/collection/generic/TraversableTemplate$class.addString:(Lscala/collection/generic/TraversableTemplate;Lscala/collection/mutable/StringBuilder;)Lscala/collection/mutable/StringBuilder;
   5:	areturn
  LineNumberTable: 
   line 31: 0

  LocalVariableTable: 
   Start  Length  Slot  Name   Signature
   0      6      0    this       Lscala/io/File;
   0      6      1    b       Lscala/collection/mutable/StringBuilder;


public scala.collection.mutable.StringBuilder addString(scala.collection.mutable.StringBuilder, java.lang.String);
  Code:
   Stack=3, Locals=3, Args_size=3
   0:	aload_0
   1:	aload_1
   2:	aload_2
   3:	invokestatic	#278; //Method scala/collection/generic/TraversableTemplate$class.addString:(Lscala/collection/generic/TraversableTemplate;Lscala/collection/mutable/StringBuilder;Ljava/lang/String;)Lscala/collection/mutable/StringBuilder;
   6:	areturn
  LineNumberTable: 
   line 31: 0

  LocalVariableTable: 
   Start  Length  Slot  Name   Signature
   0      7      0    this       Lscala/io/File;
   0      7      1    b       Lscala/collection/mutable/StringBuilder;
   0      7      2    sep       Ljava/lang/String;


public scala.collection.mutable.StringBuilder addString(scala.collection.mutable.StringBuilder, java.lang.String, java.lang.String, java.lang.String);
  Code:
   Stack=5, Locals=5, Args_size=5
   0:	aload_0
   1:	aload_1
   2:	aload_2
   3:	aload_3
   4:	aload	4
   6:	invokestatic	#283; //Method scala/collection/generic/TraversableTemplate$class.addString:(Lscala/collection/generic/TraversableTemplate;Lscala/collection/mutable/StringBuilder;Ljava/lang/String;Ljava/lang/String;Ljava/lang/String;)Lscala/collection/mutable/StringBuilder;
   9:	areturn
  LineNumberTable: 
   line 31: 0

  LocalVariableTable: 
   Start  Length  Slot  Name   Signature
   0      10      0    this       Lscala/io/File;
   0      10      1    b       Lscala/collection/mutable/StringBuilder;
   0      10      2    start       Ljava/lang/String;
   0      10      3    sep       Ljava/lang/String;
   0      10      4    end       Ljava/lang/String;


public java.lang.String mkString();
  Code:
   Stack=1, Locals=1, Args_size=1
   0:	aload_0
   1:	invokestatic	#288; //Method scala/collection/generic/TraversableTemplate$class.mkString:(Lscala/collection/generic/TraversableTemplate;)Ljava/lang/String;
   4:	areturn
  LineNumberTable: 
   line 31: 0


public java.lang.String mkString(java.lang.String);
  Code:
   Stack=2, Locals=2, Args_size=2
   0:	aload_0
   1:	aload_1
   2:	invokestatic	#292; //Method scala/collection/generic/TraversableTemplate$class.mkString:(Lscala/collection/generic/TraversableTemplate;Ljava/lang/String;)Ljava/lang/String;
   5:	areturn
  LineNumberTable: 
   line 31: 0

  LocalVariableTable: 
   Start  Length  Slot  Name   Signature
   0      6      0    this       Lscala/io/File;
   0      6      1    sep       Ljava/lang/String;


public java.lang.String mkString(java.lang.String, java.lang.String, java.lang.String);
  Code:
   Stack=4, Locals=4, Args_size=4
   0:	aload_0
   1:	aload_1
   2:	aload_2
   3:	aload_3
   4:	invokestatic	#296; //Method scala/collection/generic/TraversableTemplate$class.mkString:(Lscala/collection/generic/TraversableTemplate;Ljava/lang/String;Ljava/lang/String;Ljava/lang/String;)Ljava/lang/String;
   7:	areturn
  LineNumberTable: 
   line 31: 0

  LocalVariableTable: 
   Start  Length  Slot  Name   Signature
   0      8      0    this       Lscala/io/File;
   0      8      1    start       Ljava/lang/String;
   0      8      2    sep       Ljava/lang/String;
   0      8      3    end       Ljava/lang/String;


public scala.collection.immutable.Set toSet();
  Code:
   Stack=1, Locals=1, Args_size=1
   0:	aload_0
   1:	invokestatic	#301; //Method scala/collection/generic/TraversableTemplate$class.toSet:(Lscala/collection/generic/TraversableTemplate;)Lscala/collection/immutable/Set;
   4:	areturn
  LineNumberTable: 
   line 31: 0


public scala.collection.Sequence toSequence();
  Code:
   Stack=1, Locals=1, Args_size=1
   0:	aload_0
   1:	invokestatic	#306; //Method scala/collection/generic/TraversableTemplate$class.toSequence:(Lscala/collection/generic/TraversableTemplate;)Lscala/collection/Sequence;
   4:	areturn
  LineNumberTable: 
   line 31: 0


public scala.collection.immutable.List toList();
  Code:
   Stack=1, Locals=1, Args_size=1
   0:	aload_0
   1:	invokestatic	#311; //Method scala/collection/generic/TraversableTemplate$class.toList:(Lscala/collection/generic/TraversableTemplate;)Lscala/collection/immutable/List;
   4:	areturn
  LineNumberTable: 
   line 31: 0


public scala.runtime.BoxedArray toArray();
  Code:
   Stack=1, Locals=1, Args_size=1
   0:	aload_0
   1:	invokestatic	#316; //Method scala/collection/generic/TraversableTemplate$class.toArray:(Lscala/collection/generic/TraversableTemplate;)Lscala/runtime/BoxedArray;
   4:	areturn
  LineNumberTable: 
   line 31: 0


public void copyToArray(scala.runtime.BoxedArray, int);
  Code:
   Stack=3, Locals=3, Args_size=3
   0:	aload_0
   1:	aload_1
   2:	iload_2
   3:	invokestatic	#321; //Method scala/collection/generic/TraversableTemplate$class.copyToArray:(Lscala/collection/generic/TraversableTemplate;Lscala/runtime/BoxedArray;I)V
   6:	return
  LineNumberTable: 
   line 31: 0

  LocalVariableTable: 
   Start  Length  Slot  Name   Signature
   0      7      0    this       Lscala/io/File;
   0      7      1    xs       Lscala/runtime/BoxedArray;
   0      7      2    start       I


public void copyToArray(scala.runtime.BoxedArray, int, int);
  Code:
   Stack=4, Locals=4, Args_size=4
   0:	aload_0
   1:	aload_1
   2:	iload_2
   3:	iload_3
   4:	invokestatic	#327; //Method scala/collection/generic/TraversableTemplate$class.copyToArray:(Lscala/collection/generic/TraversableTemplate;Lscala/runtime/BoxedArray;II)V
   7:	return
  LineNumberTable: 
   line 31: 0

  LocalVariableTable: 
   Start  Length  Slot  Name   Signature
   0      8      0    this       Lscala/io/File;
   0      8      1    xs       Lscala/runtime/BoxedArray;
   0      8      2    start       I
   0      8      3    len       I


public void copyToBuffer(scala.collection.mutable.Buffer);
  Code:
   Stack=2, Locals=2, Args_size=2
   0:	aload_0
   1:	aload_1
   2:	invokestatic	#333; //Method scala/collection/generic/TraversableTemplate$class.copyToBuffer:(Lscala/collection/generic/TraversableTemplate;Lscala/collection/mutable/Buffer;)V
   5:	return
  LineNumberTable: 
   line 31: 0

  LocalVariableTable: 
   Start  Length  Slot  Name   Signature
   0      6      0    this       Lscala/io/File;
   0      6      1    dest       Lscala/collection/mutable/Buffer;


public scala.Tuple2 splitAt(int);
  Code:
   Stack=2, Locals=2, Args_size=2
   0:	aload_0
   1:	iload_1
   2:	invokestatic	#340; //Method scala/collection/generic/TraversableTemplate$class.splitAt:(Lscala/collection/generic/TraversableTemplate;I)Lscala/Tuple2;
   5:	areturn
  LineNumberTable: 
   line 31: 0

  LocalVariableTable: 
   Start  Length  Slot  Name   Signature
   0      6      0    this       Lscala/io/File;
   0      6      1    n       I


public scala.Tuple2 span(scala.Function1);
  Code:
   Stack=2, Locals=2, Args_size=2
   0:	aload_0
   1:	aload_1
   2:	invokestatic	#346; //Method scala/collection/generic/TraversableTemplate$class.span:(Lscala/collection/generic/TraversableTemplate;Lscala/Function1;)Lscala/Tuple2;
   5:	areturn
  LineNumberTable: 
   line 31: 0

  LocalVariableTable: 
   Start  Length  Slot  Name   Signature
   0      6      0    this       Lscala/io/File;
   0      6      1    p       Lscala/Function1;


public scala.collection.generic.TraversableTemplate dropWhile(scala.Function1);
  Code:
   Stack=2, Locals=2, Args_size=2
   0:	aload_0
   1:	aload_1
   2:	invokestatic	#353; //Method scala/collection/generic/TraversableTemplate$class.dropWhile:(Lscala/collection/generic/TraversableTemplate;Lscala/Function1;)Lscala/collection/generic/TraversableTemplate;
   5:	areturn
  LineNumberTable: 
   line 31: 0

  LocalVariableTable: 
   Start  Length  Slot  Name   Signature
   0      6      0    this       Lscala/io/File;
   0      6      1    p       Lscala/Function1;


public scala.collection.generic.TraversableTemplate takeWhile(scala.Function1);
  Code:
   Stack=2, Locals=2, Args_size=2
   0:	aload_0
   1:	aload_1
   2:	invokestatic	#356; //Method scala/collection/generic/TraversableTemplate$class.takeWhile:(Lscala/collection/generic/TraversableTemplate;Lscala/Function1;)Lscala/collection/generic/TraversableTemplate;
   5:	areturn
  LineNumberTable: 
   line 31: 0

  LocalVariableTable: 
   Start  Length  Slot  Name   Signature
   0      6      0    this       Lscala/io/File;
   0      6      1    p       Lscala/Function1;


public scala.collection.generic.TraversableTemplate slice(int, int);
  Code:
   Stack=3, Locals=3, Args_size=3
   0:	aload_0
   1:	iload_1
   2:	iload_2
   3:	invokestatic	#361; //Method scala/collection/generic/TraversableTemplate$class.slice:(Lscala/collection/generic/TraversableTemplate;II)Lscala/collection/generic/TraversableTemplate;
   6:	areturn
  LineNumberTable: 
   line 31: 0

  LocalVariableTable: 
   Start  Length  Slot  Name   Signature
   0      7      0    this       Lscala/io/File;
   0      7      1    from       I
   0      7      2    until       I


public scala.collection.generic.TraversableTemplate drop(int);
  Code:
   Stack=2, Locals=2, Args_size=2
   0:	aload_0
   1:	iload_1
   2:	invokestatic	#366; //Method scala/collection/generic/TraversableTemplate$class.drop:(Lscala/collection/generic/TraversableTemplate;I)Lscala/collection/generic/TraversableTemplate;
   5:	areturn
  LineNumberTable: 
   line 31: 0

  LocalVariableTable: 
   Start  Length  Slot  Name   Signature
   0      6      0    this       Lscala/io/File;
   0      6      1    n       I


public scala.collection.generic.TraversableTemplate take(int);
  Code:
   Stack=2, Locals=2, Args_size=2
   0:	aload_0
   1:	iload_1
   2:	invokestatic	#369; //Method scala/collection/generic/TraversableTemplate$class.take:(Lscala/collection/generic/TraversableTemplate;I)Lscala/collection/generic/TraversableTemplate;
   5:	areturn
  LineNumberTable: 
   line 31: 0

  LocalVariableTable: 
   Start  Length  Slot  Name   Signature
   0      6      0    this       Lscala/io/File;
   0      6      1    n       I


public scala.collection.generic.TraversableTemplate init();
  Code:
   Stack=1, Locals=1, Args_size=1
   0:	aload_0
   1:	invokestatic	#374; //Method scala/collection/generic/TraversableTemplate$class.init:(Lscala/collection/generic/TraversableTemplate;)Lscala/collection/generic/TraversableTemplate;
   4:	areturn
  LineNumberTable: 
   line 31: 0


public scala.Option lastOption();
  Code:
   Stack=1, Locals=1, Args_size=1
   0:	aload_0
   1:	invokestatic	#378; //Method scala/collection/generic/TraversableTemplate$class.lastOption:(Lscala/collection/generic/TraversableTemplate;)Lscala/Option;
   4:	areturn
  LineNumberTable: 
   line 31: 0


public java.lang.Object last();
  Code:
   Stack=1, Locals=1, Args_size=1
   0:	aload_0
   1:	invokestatic	#382; //Method scala/collection/generic/TraversableTemplate$class.last:(Lscala/collection/generic/TraversableTemplate;)Ljava/lang/Object;
   4:	areturn
  LineNumberTable: 
   line 31: 0


public scala.collection.generic.TraversableTemplate tail();
  Code:
   Stack=1, Locals=1, Args_size=1
   0:	aload_0
   1:	invokestatic	#385; //Method scala/collection/generic/TraversableTemplate$class.tail:(Lscala/collection/generic/TraversableTemplate;)Lscala/collection/generic/TraversableTemplate;
   4:	areturn
  LineNumberTable: 
   line 31: 0


public scala.Option headOption();
  Code:
   Stack=1, Locals=1, Args_size=1
   0:	aload_0
   1:	invokestatic	#388; //Method scala/collection/generic/TraversableTemplate$class.headOption:(Lscala/collection/generic/TraversableTemplate;)Lscala/Option;
   4:	areturn
  LineNumberTable: 
   line 31: 0


public scala.Option reduceRightOption(scala.Function2);
  Code:
   Stack=2, Locals=2, Args_size=2
   0:	aload_0
   1:	aload_1
   2:	invokestatic	#393; //Method scala/collection/generic/TraversableTemplate$class.reduceRightOption:(Lscala/collection/generic/TraversableTemplate;Lscala/Function2;)Lscala/Option;
   5:	areturn
  LineNumberTable: 
   line 31: 0

  LocalVariableTable: 
   Start  Length  Slot  Name   Signature
   0      6      0    this       Lscala/io/File;
   0      6      1    op       Lscala/Function2;


public scala.Option reduceLeftOption(scala.Function2);
  Code:
   Stack=2, Locals=2, Args_size=2
   0:	aload_0
   1:	aload_1
   2:	invokestatic	#398; //Method scala/collection/generic/TraversableTemplate$class.reduceLeftOption:(Lscala/collection/generic/TraversableTemplate;Lscala/Function2;)Lscala/Option;
   5:	areturn
  LineNumberTable: 
   line 31: 0

  LocalVariableTable: 
   Start  Length  Slot  Name   Signature
   0      6      0    this       Lscala/io/File;
   0      6      1    op       Lscala/Function2;


public java.lang.Object reduceLeft(scala.Function2);
  Code:
   Stack=2, Locals=2, Args_size=2
   0:	aload_0
   1:	aload_1
   2:	invokestatic	#403; //Method scala/collection/generic/TraversableTemplate$class.reduceLeft:(Lscala/collection/generic/TraversableTemplate;Lscala/Function2;)Ljava/lang/Object;
   5:	areturn
  LineNumberTable: 
   line 31: 0

  LocalVariableTable: 
   Start  Length  Slot  Name   Signature
   0      6      0    this       Lscala/io/File;
   0      6      1    op       Lscala/Function2;


public java.lang.Object $colon$bslash(java.lang.Object, scala.Function2);
  Code:
   Stack=3, Locals=3, Args_size=3
   0:	aload_0
   1:	aload_1
   2:	aload_2
   3:	invokestatic	#408; //Method scala/collection/generic/TraversableTemplate$class.$colon$bslash:(Lscala/collection/generic/TraversableTemplate;Ljava/lang/Object;Lscala/Function2;)Ljava/lang/Object;
   6:	areturn
  LineNumberTable: 
   line 31: 0

  LocalVariableTable: 
   Start  Length  Slot  Name   Signature
   0      7      0    this       Lscala/io/File;
   0      7      1    z       Ljava/lang/Object;
   0      7      2    op       Lscala/Function2;


public java.lang.Object $div$colon(java.lang.Object, scala.Function2);
  Code:
   Stack=3, Locals=3, Args_size=3
   0:	aload_0
   1:	aload_1
   2:	aload_2
   3:	invokestatic	#412; //Method scala/collection/generic/TraversableTemplate$class.$div$colon:(Lscala/collection/generic/TraversableTemplate;Ljava/lang/Object;Lscala/Function2;)Ljava/lang/Object;
   6:	areturn
  LineNumberTable: 
   line 31: 0

  LocalVariableTable: 
   Start  Length  Slot  Name   Signature
   0      7      0    this       Lscala/io/File;
   0      7      1    z       Ljava/lang/Object;
   0      7      2    op       Lscala/Function2;


public java.lang.Object foldLeft(java.lang.Object, scala.Function2);
  Code:
   Stack=3, Locals=3, Args_size=3
   0:	aload_0
   1:	aload_1
   2:	aload_2
   3:	invokestatic	#415; //Method scala/collection/generic/TraversableTemplate$class.foldLeft:(Lscala/collection/generic/TraversableTemplate;Ljava/lang/Object;Lscala/Function2;)Ljava/lang/Object;
   6:	areturn
  LineNumberTable: 
   line 31: 0

  LocalVariableTable: 
   Start  Length  Slot  Name   Signature
   0      7      0    this       Lscala/io/File;
   0      7      1    z       Ljava/lang/Object;
   0      7      2    op       Lscala/Function2;


public scala.Option find(scala.Function1);
  Code:
   Stack=2, Locals=2, Args_size=2
   0:	aload_0
   1:	aload_1
   2:	invokestatic	#420; //Method scala/collection/generic/TraversableTemplate$class.find:(Lscala/collection/generic/TraversableTemplate;Lscala/Function1;)Lscala/Option;
   5:	areturn
  LineNumberTable: 
   line 31: 0

  LocalVariableTable: 
   Start  Length  Slot  Name   Signature
   0      6      0    this       Lscala/io/File;
   0      6      1    p       Lscala/Function1;


public int count(scala.Function1);
  Code:
   Stack=2, Locals=2, Args_size=2
   0:	aload_0
   1:	aload_1
   2:	invokestatic	#425; //Method scala/collection/generic/TraversableTemplate$class.count:(Lscala/collection/generic/TraversableTemplate;Lscala/Function1;)I
   5:	ireturn
  LineNumberTable: 
   line 31: 0

  LocalVariableTable: 
   Start  Length  Slot  Name   Signature
   0      6      0    this       Lscala/io/File;
   0      6      1    p       Lscala/Function1;


public boolean exists(scala.Function1);
  Code:
   Stack=2, Locals=2, Args_size=2
   0:	aload_0
   1:	aload_1
   2:	invokestatic	#430; //Method scala/collection/generic/TraversableTemplate$class.exists:(Lscala/collection/generic/TraversableTemplate;Lscala/Function1;)Z
   5:	ireturn
  LineNumberTable: 
   line 31: 0

  LocalVariableTable: 
   Start  Length  Slot  Name   Signature
   0      6      0    this       Lscala/io/File;
   0      6      1    p       Lscala/Function1;


public boolean forall(scala.Function1);
  Code:
   Stack=2, Locals=2, Args_size=2
   0:	aload_0
   1:	aload_1
   2:	invokestatic	#433; //Method scala/collection/generic/TraversableTemplate$class.forall:(Lscala/collection/generic/TraversableTemplate;Lscala/Function1;)Z
   5:	ireturn
  LineNumberTable: 
   line 31: 0

  LocalVariableTable: 
   Start  Length  Slot  Name   Signature
   0      6      0    this       Lscala/io/File;
   0      6      1    p       Lscala/Function1;


public scala.collection.Map groupBy(scala.Function1);
  Code:
   Stack=2, Locals=2, Args_size=2
   0:	aload_0
   1:	aload_1
   2:	invokestatic	#438; //Method scala/collection/generic/TraversableTemplate$class.groupBy:(Lscala/collection/generic/TraversableTemplate;Lscala/Function1;)Lscala/collection/Map;
   5:	areturn
  LineNumberTable: 
   line 31: 0

  LocalVariableTable: 
   Start  Length  Slot  Name   Signature
   0      6      0    this       Lscala/io/File;
   0      6      1    f       Lscala/Function1;


public scala.Tuple2 partition(scala.Function1);
  Code:
   Stack=2, Locals=2, Args_size=2
   0:	aload_0
   1:	aload_1
   2:	invokestatic	#441; //Method scala/collection/generic/TraversableTemplate$class.partition:(Lscala/collection/generic/TraversableTemplate;Lscala/Function1;)Lscala/Tuple2;
   5:	areturn
  LineNumberTable: 
   line 31: 0

  LocalVariableTable: 
   Start  Length  Slot  Name   Signature
   0      6      0    this       Lscala/io/File;
   0      6      1    p       Lscala/Function1;


public scala.collection.generic.TraversableTemplate remove(scala.Function1);
  Code:
   Stack=2, Locals=2, Args_size=2
   0:	aload_0
   1:	aload_1
   2:	invokestatic	#444; //Method scala/collection/generic/TraversableTemplate$class.remove:(Lscala/collection/generic/TraversableTemplate;Lscala/Function1;)Lscala/collection/generic/TraversableTemplate;
   5:	areturn
  LineNumberTable: 
   line 31: 0

  LocalVariableTable: 
   Start  Length  Slot  Name   Signature
   0      6      0    this       Lscala/io/File;
   0      6      1    p       Lscala/Function1;


public scala.collection.generic.TraversableTemplate filterNot(scala.Function1);
  Code:
   Stack=2, Locals=2, Args_size=2
   0:	aload_0
   1:	aload_1
   2:	invokestatic	#447; //Method scala/collection/generic/TraversableTemplate$class.filterNot:(Lscala/collection/generic/TraversableTemplate;Lscala/Function1;)Lscala/collection/generic/TraversableTemplate;
   5:	areturn
  LineNumberTable: 
   line 31: 0

  LocalVariableTable: 
   Start  Length  Slot  Name   Signature
   0      6      0    this       Lscala/io/File;
   0      6      1    p       Lscala/Function1;


public java.lang.Object filterMap(scala.PartialFunction, scala.collection.generic.BuilderFactory);
  Code:
   Stack=3, Locals=3, Args_size=3
   0:	aload_0
   1:	aload_1
   2:	aload_2
   3:	invokestatic	#452; //Method scala/collection/generic/TraversableTemplate$class.filterMap:(Lscala/collection/generic/TraversableTemplate;Lscala/PartialFunction;Lscala/collection/generic/BuilderFactory;)Ljava/lang/Object;
   6:	areturn
  LineNumberTable: 
   line 31: 0

  LocalVariableTable: 
   Start  Length  Slot  Name   Signature
   0      7      0    this       Lscala/io/File;
   0      7      1    pf       Lscala/PartialFunction;
   0      7      2    bf       Lscala/collection/generic/BuilderFactory;


public scala.collection.generic.TraversableTemplate filter(scala.Function1);
  Code:
   Stack=2, Locals=2, Args_size=2
   0:	aload_0
   1:	aload_1
   2:	invokestatic	#459; //Method scala/collection/generic/TraversableTemplate$class.filter:(Lscala/collection/generic/TraversableTemplate;Lscala/Function1;)Lscala/collection/generic/TraversableTemplate;
   5:	areturn
  LineNumberTable: 
   line 31: 0

  LocalVariableTable: 
   Start  Length  Slot  Name   Signature
   0      6      0    this       Lscala/io/File;
   0      6      1    p       Lscala/Function1;


public java.lang.Object flatMap(scala.Function1, scala.collection.generic.BuilderFactory);
  Code:
   Stack=3, Locals=3, Args_size=3
   0:	aload_0
   1:	aload_1
   2:	aload_2
   3:	invokestatic	#464; //Method scala/collection/generic/TraversableTemplate$class.flatMap:(Lscala/collection/generic/TraversableTemplate;Lscala/Function1;Lscala/collection/generic/BuilderFactory;)Ljava/lang/Object;
   6:	areturn
  LineNumberTable: 
   line 31: 0

  LocalVariableTable: 
   Start  Length  Slot  Name   Signature
   0      7      0    this       Lscala/io/File;
   0      7      1    f       Lscala/Function1;
   0      7      2    bf       Lscala/collection/generic/BuilderFactory;


public java.lang.Object map(scala.Function1, scala.collection.generic.BuilderFactory);
  Code:
   Stack=3, Locals=3, Args_size=3
   0:	aload_0
   1:	aload_1
   2:	aload_2
   3:	invokestatic	#466; //Method scala/collection/generic/TraversableTemplate$class.map:(Lscala/collection/generic/TraversableTemplate;Lscala/Function1;Lscala/collection/generic/BuilderFactory;)Ljava/lang/Object;
   6:	areturn
  LineNumberTable: 
   line 31: 0

  LocalVariableTable: 
   Start  Length  Slot  Name   Signature
   0      7      0    this       Lscala/io/File;
   0      7      1    f       Lscala/Function1;
   0      7      2    bf       Lscala/collection/generic/BuilderFactory;


public java.lang.Object $plus$plus(scala.collection.Iterator, scala.collection.generic.BuilderFactory);
  Code:
   Stack=3, Locals=3, Args_size=3
   0:	aload_0
   1:	aload_1
   2:	aload_2
   3:	invokestatic	#471; //Method scala/collection/generic/TraversableTemplate$class.$plus$plus:(Lscala/collection/generic/TraversableTemplate;Lscala/collection/Iterator;Lscala/collection/generic/BuilderFactory;)Ljava/lang/Object;
   6:	areturn
  LineNumberTable: 
   line 31: 0

  LocalVariableTable: 
   Start  Length  Slot  Name   Signature
   0      7      0    this       Lscala/io/File;
   0      7      1    that       Lscala/collection/Iterator;
   0      7      2    bf       Lscala/collection/generic/BuilderFactory;


public java.lang.Object $plus$plus(scala.collection.Traversable, scala.collection.generic.BuilderFactory);
  Code:
   Stack=3, Locals=3, Args_size=3
   0:	aload_0
   1:	aload_1
   2:	aload_2
   3:	invokestatic	#477; //Method scala/collection/generic/TraversableTemplate$class.$plus$plus:(Lscala/collection/generic/TraversableTemplate;Lscala/collection/Traversable;Lscala/collection/generic/BuilderFactory;)Ljava/lang/Object;
   6:	areturn
  LineNumberTable: 
   line 31: 0

  LocalVariableTable: 
   Start  Length  Slot  Name   Signature
   0      7      0    this       Lscala/io/File;
   0      7      1    that       Lscala/collection/Traversable;
   0      7      2    bf       Lscala/collection/generic/BuilderFactory;


public boolean hasDefiniteSize();
  Code:
   Stack=1, Locals=1, Args_size=1
   0:	aload_0
   1:	invokestatic	#482; //Method scala/collection/generic/TraversableTemplate$class.hasDefiniteSize:(Lscala/collection/generic/TraversableTemplate;)Z
   4:	ireturn
  LineNumberTable: 
   line 31: 0


public int size();
  Code:
   Stack=1, Locals=1, Args_size=1
   0:	aload_0
   1:	invokestatic	#486; //Method scala/collection/generic/TraversableTemplate$class.size:(Lscala/collection/generic/TraversableTemplate;)I
   4:	ireturn
  LineNumberTable: 
   line 31: 0


public boolean nonEmpty();
  Code:
   Stack=1, Locals=1, Args_size=1
   0:	aload_0
   1:	invokestatic	#489; //Method scala/collection/generic/TraversableTemplate$class.nonEmpty:(Lscala/collection/generic/TraversableTemplate;)Z
   4:	ireturn
  LineNumberTable: 
   line 31: 0


public scala.collection.generic.TraversableTemplate thisCollection();
  Code:
   Stack=1, Locals=1, Args_size=1
   0:	aload_0
   1:	invokestatic	#492; //Method scala/collection/generic/TraversableTemplate$class.thisCollection:(Lscala/collection/generic/TraversableTemplate;)Lscala/collection/generic/TraversableTemplate;
   4:	areturn
  LineNumberTable: 
   line 31: 0


public scala.collection.Traversable transpose(scala.Function1);
  Code:
   Stack=2, Locals=2, Args_size=2
   0:	aload_0
   1:	aload_1
   2:	invokestatic	#497; //Method scala/collection/generic/TraversableClass$class.transpose:(Lscala/collection/generic/TraversableClass;Lscala/Function1;)Lscala/collection/Traversable;
   5:	areturn
  LineNumberTable: 
   line 31: 0

  LocalVariableTable: 
   Start  Length  Slot  Name   Signature
   0      6      0    this       Lscala/io/File;
   0      6      1    toTraversable       Lscala/Function1;


public scala.collection.Traversable flatten(scala.Function1);
  Code:
   Stack=2, Locals=2, Args_size=2
   0:	aload_0
   1:	aload_1
   2:	invokestatic	#501; //Method scala/collection/generic/TraversableClass$class.flatten:(Lscala/collection/generic/TraversableClass;Lscala/Function1;)Lscala/collection/Traversable;
   5:	areturn
  LineNumberTable: 
   line 31: 0

  LocalVariableTable: 
   Start  Length  Slot  Name   Signature
   0      6      0    this       Lscala/io/File;
   0      6      1    toTraversable       Lscala/Function1;


public scala.Tuple2 unzip(scala.Function1);
  Code:
   Stack=2, Locals=2, Args_size=2
   0:	aload_0
   1:	aload_1
   2:	invokestatic	#505; //Method scala/collection/generic/TraversableClass$class.unzip:(Lscala/collection/generic/TraversableClass;Lscala/Function1;)Lscala/Tuple2;
   5:	areturn
  LineNumberTable: 
   line 31: 0

  LocalVariableTable: 
   Start  Length  Slot  Name   Signature
   0      6      0    this       Lscala/io/File;
   0      6      1    toPair       Lscala/Function1;


public scala.collection.generic.Builder genericBuilder();
  Code:
   Stack=1, Locals=1, Args_size=1
   0:	aload_0
   1:	invokestatic	#511; //Method scala/collection/generic/TraversableClass$class.genericBuilder:(Lscala/collection/generic/TraversableClass;)Lscala/collection/generic/Builder;
   4:	areturn
  LineNumberTable: 
   line 31: 0


public scala.collection.generic.Builder newBuilder();
  Code:
   Stack=1, Locals=1, Args_size=1
   0:	aload_0
   1:	invokestatic	#514; //Method scala/collection/generic/TraversableClass$class.newBuilder:(Lscala/collection/generic/TraversableClass;)Lscala/collection/generic/Builder;
   4:	areturn
  LineNumberTable: 
   line 31: 0


public java.lang.Object projection();
  Code:
   Stack=1, Locals=1, Args_size=1
   0:	aload_0
   1:	invokestatic	#518; //Method scala/collection/generic/IterableTemplate$class.projection:(Lscala/collection/generic/IterableTemplate;)Ljava/lang/Object;
   4:	areturn
  LineNumberTable: 
   line 31: 0


public scala.collection.Sequence toSeq();
  Code:
   Stack=1, Locals=1, Args_size=1
   0:	aload_0
   1:	invokestatic	#522; //Method scala/collection/generic/IterableTemplate$class.toSeq:(Lscala/collection/generic/IterableTemplate;)Lscala/collection/Sequence;
   4:	areturn
  LineNumberTable: 
   line 31: 0


public scala.Option firstOption();
  Code:
   Stack=1, Locals=1, Args_size=1
   0:	aload_0
   1:	invokestatic	#526; //Method scala/collection/generic/IterableTemplate$class.firstOption:(Lscala/collection/generic/IterableTemplate;)Lscala/Option;
   4:	areturn
  LineNumberTable: 
   line 31: 0


public java.lang.Object first();
  Code:
   Stack=1, Locals=1, Args_size=1
   0:	aload_0
   1:	invokestatic	#529; //Method scala/collection/generic/IterableTemplate$class.first:(Lscala/collection/generic/IterableTemplate;)Ljava/lang/Object;
   4:	areturn
  LineNumberTable: 
   line 31: 0


public scala.collection.generic.IterableView view(int, int);
  Code:
   Stack=3, Locals=3, Args_size=3
   0:	aload_0
   1:	iload_1
   2:	iload_2
   3:	invokestatic	#532; //Method scala/collection/generic/IterableTemplate$class.view:(Lscala/collection/generic/IterableTemplate;II)Lscala/collection/generic/IterableView;
   6:	areturn
  LineNumberTable: 
   line 31: 0

  LocalVariableTable: 
   Start  Length  Slot  Name   Signature
   0      7      0    this       Lscala/io/File;
   0      7      1    from       I
   0      7      2    until       I


public java.lang.Object view();
  Code:
   Stack=1, Locals=1, Args_size=1
   0:	aload_0
   1:	invokestatic	#534; //Method scala/collection/generic/IterableTemplate$class.view:(Lscala/collection/generic/IterableTemplate;)Ljava/lang/Object;
   4:	areturn
  LineNumberTable: 
   line 31: 0


public scala.collection.immutable.Stream toStream();
  Code:
   Stack=1, Locals=1, Args_size=1
   0:	aload_0
   1:	invokestatic	#539; //Method scala/collection/generic/IterableTemplate$class.toStream:(Lscala/collection/generic/IterableTemplate;)Lscala/collection/immutable/Stream;
   4:	areturn
  LineNumberTable: 
   line 31: 0


public boolean sameElements(scala.collection.Iterable);
  Code:
   Stack=2, Locals=2, Args_size=2
   0:	aload_0
   1:	aload_1
   2:	invokestatic	#544; //Method scala/collection/generic/IterableTemplate$class.sameElements:(Lscala/collection/generic/IterableTemplate;Lscala/collection/Iterable;)Z
   5:	ireturn
  LineNumberTable: 
   line 31: 0

  LocalVariableTable: 
   Start  Length  Slot  Name   Signature
   0      6      0    this       Lscala/io/File;
   0      6      1    that       Lscala/collection/Iterable;


public scala.collection.generic.IterableTemplate dropRight(int);
  Code:
   Stack=2, Locals=2, Args_size=2
   0:	aload_0
   1:	iload_1
   2:	invokestatic	#550; //Method scala/collection/generic/IterableTemplate$class.dropRight:(Lscala/collection/generic/IterableTemplate;I)Lscala/collection/generic/IterableTemplate;
   5:	areturn
  LineNumberTable: 
   line 31: 0

  LocalVariableTable: 
   Start  Length  Slot  Name   Signature
   0      6      0    this       Lscala/io/File;
   0      6      1    n       I


public scala.collection.generic.IterableTemplate takeRight(int);
  Code:
   Stack=2, Locals=2, Args_size=2
   0:	aload_0
   1:	iload_1
   2:	invokestatic	#553; //Method scala/collection/generic/IterableTemplate$class.takeRight:(Lscala/collection/generic/IterableTemplate;I)Lscala/collection/generic/IterableTemplate;
   5:	areturn
  LineNumberTable: 
   line 31: 0

  LocalVariableTable: 
   Start  Length  Slot  Name   Signature
   0      6      0    this       Lscala/io/File;
   0      6      1    n       I


public java.lang.Object head();
  Code:
   Stack=1, Locals=1, Args_size=1
   0:	aload_0
   1:	invokestatic	#556; //Method scala/collection/generic/IterableTemplate$class.head:(Lscala/collection/generic/IterableTemplate;)Ljava/lang/Object;
   4:	areturn
  LineNumberTable: 
   line 31: 0


public scala.collection.Iterable toIterable();
  Code:
   Stack=1, Locals=1, Args_size=1
   0:	aload_0
   1:	invokestatic	#561; //Method scala/collection/generic/IterableTemplate$class.toIterable:(Lscala/collection/generic/IterableTemplate;)Lscala/collection/Iterable;
   4:	areturn
  LineNumberTable: 
   line 31: 0


public java.lang.Object reduceRight(scala.Function2);
  Code:
   Stack=2, Locals=2, Args_size=2
   0:	aload_0
   1:	aload_1
   2:	invokestatic	#565; //Method scala/collection/generic/IterableTemplate$class.reduceRight:(Lscala/collection/generic/IterableTemplate;Lscala/Function2;)Ljava/lang/Object;
   5:	areturn
  LineNumberTable: 
   line 31: 0

  LocalVariableTable: 
   Start  Length  Slot  Name   Signature
   0      6      0    this       Lscala/io/File;
   0      6      1    op       Lscala/Function2;


public java.lang.Object foldRight(java.lang.Object, scala.Function2);
  Code:
   Stack=3, Locals=3, Args_size=3
   0:	aload_0
   1:	aload_1
   2:	aload_2
   3:	invokestatic	#569; //Method scala/collection/generic/IterableTemplate$class.foldRight:(Lscala/collection/generic/IterableTemplate;Ljava/lang/Object;Lscala/Function2;)Ljava/lang/Object;
   6:	areturn
  LineNumberTable: 
   line 31: 0

  LocalVariableTable: 
   Start  Length  Slot  Name   Signature
   0      7      0    this       Lscala/io/File;
   0      7      1    z       Ljava/lang/Object;
   0      7      2    op       Lscala/Function2;


public boolean isEmpty();
  Code:
   Stack=1, Locals=1, Args_size=1
   0:	aload_0
   1:	invokestatic	#572; //Method scala/collection/generic/IterableTemplate$class.isEmpty:(Lscala/collection/generic/IterableTemplate;)Z
   4:	ireturn
  LineNumberTable: 
   line 31: 0


public void foreach(scala.Function1);
  Code:
   Stack=2, Locals=2, Args_size=2
   0:	aload_0
   1:	aload_1
   2:	invokestatic	#575; //Method scala/collection/generic/IterableTemplate$class.foreach:(Lscala/collection/generic/IterableTemplate;Lscala/Function1;)V
   5:	return
  LineNumberTable: 
   line 31: 0

  LocalVariableTable: 
   Start  Length  Slot  Name   Signature
   0      6      0    this       Lscala/io/File;
   0      6      1    f       Lscala/Function1;


public scala.collection.Iterator elements();
  Code:
   Stack=1, Locals=1, Args_size=1
   0:	aload_0
   1:	invokestatic	#579; //Method scala/collection/generic/IterableTemplate$class.elements:(Lscala/collection/generic/IterableTemplate;)Lscala/collection/Iterator;
   4:	areturn
  LineNumberTable: 
   line 31: 0


public scala.collection.generic.Companion companion();
  Code:
   Stack=1, Locals=1, Args_size=1
   0:	aload_0
   1:	invokestatic	#584; //Method scala/collection/Iterable$class.companion:(Lscala/collection/Iterable;)Lscala/collection/generic/Companion;
   4:	areturn
  LineNumberTable: 
   line 31: 0


}

