Compiled from "Position.scala"
public final class scala.io.Position$ extends java.lang.Object implements scala.ScalaObject
  SourceFile: "Position.scala"
  Scala: length = 0x
   
  minor version: 0
  major version: 49
  Constant pool:
const #1 = Asciz	SourceFile;
const #2 = Asciz	Position.scala;
const #3 = Asciz	Scala;
const #4 = Asciz	MODULE$;
const #5 = Asciz	Lscala/io/Position$;;
const #6 = Asciz	<clinit>;
const #7 = Asciz	()V;
const #8 = Asciz	Code;
const #9 = Asciz	scala/io/Position$;
const #10 = class	#9;	//  scala/io/Position$
const #11 = Asciz	<init>;
const #12 = NameAndType	#11:#7;//  "<init>":()V
const #13 = Method	#10.#12;	//  scala/io/Position$."<init>":()V
const #14 = Asciz	FIRSTPOS;
const #15 = Asciz	I;
const #16 = Asciz	NOPOS;
const #17 = Asciz	COLUMN_MASK;
const #18 = Asciz	LINE_MASK;
const #19 = Asciz	COLUMN_BITS;
const #20 = Asciz	LINE_BITS;
const #21 = Asciz	LineNumberTable;
const #22 = Asciz	java/lang/Object;
const #23 = class	#22;	//  java/lang/Object
const #24 = Method	#23.#12;	//  java/lang/Object."<init>":()V
const #25 = NameAndType	#4:#5;//  MODULE$:Lscala/io/Position$;
const #26 = Field	#10.#25;	//  scala/io/Position$.MODULE$:Lscala/io/Position$;
const #27 = Asciz	encode;
const #28 = Asciz	(II)I;
const #29 = NameAndType	#27:#28;//  encode:(II)I
const #30 = Method	#10.#29;	//  scala/io/Position$.encode:(II)I
const #31 = NameAndType	#14:#15;//  FIRSTPOS:I
const #32 = Field	#10.#31;	//  scala/io/Position$.FIRSTPOS:I
const #33 = Asciz	toString;
const #34 = Asciz	(I)Ljava/lang/String;;
const #35 = Asciz	scala/collection/mutable/StringBuilder;
const #36 = class	#35;	//  scala/collection/mutable/StringBuilder
const #37 = Method	#36.#12;	//  scala/collection/mutable/StringBuilder."<init>":()V
const #38 = Asciz	line;
const #39 = Asciz	(I)I;
const #40 = NameAndType	#38:#39;//  line:(I)I
const #41 = Method	#10.#40;	//  scala/io/Position$.line:(I)I
const #42 = Asciz	append;
const #43 = Asciz	(I)Lscala/collection/mutable/StringBuilder;;
const #44 = NameAndType	#42:#43;//  append:(I)Lscala/collection/mutable/StringBuilder;
const #45 = Method	#36.#44;	//  scala/collection/mutable/StringBuilder.append:(I)Lscala/collection/mutable/StringBuilder;
const #46 = int	58;
const #47 = Asciz	(C)Lscala/collection/mutable/StringBuilder;;
const #48 = NameAndType	#42:#47;//  append:(C)Lscala/collection/mutable/StringBuilder;
const #49 = Method	#36.#48;	//  scala/collection/mutable/StringBuilder.append:(C)Lscala/collection/mutable/StringBuilder;
const #50 = Asciz	column;
const #51 = NameAndType	#50:#39;//  column:(I)I
const #52 = Method	#10.#51;	//  scala/io/Position$.column:(I)I
const #53 = Asciz	()Ljava/lang/String;;
const #54 = NameAndType	#33:#53;//  toString:()Ljava/lang/String;
const #55 = Method	#36.#54;	//  scala/collection/mutable/StringBuilder.toString:()Ljava/lang/String;
const #56 = Asciz	this;
const #57 = Asciz	pos;
const #58 = Asciz	sb;
const #59 = Asciz	Lscala/collection/mutable/StringBuilder;;
const #60 = Asciz	LocalVariableTable;
const #61 = int	2047;
const #62 = int	11;
const #63 = int	1048575;
const #64 = Asciz	java/lang/IllegalArgumentException;
const #65 = class	#64;	//  java/lang/IllegalArgumentException
const #66 = Method	#36.#12;	//  scala/collection/mutable/StringBuilder."<init>":()V
const #67 = Method	#36.#44;	//  scala/collection/mutable/StringBuilder.append:(I)Lscala/collection/mutable/StringBuilder;
const #68 = Asciz	 < 0;
const #69 = String	#68;	//   < 0
const #70 = Asciz	(Ljava/lang/Object;)Lscala/collection/mutable/StringBuilder;;
const #71 = NameAndType	#42:#70;//  append:(Ljava/lang/Object;)Lscala/collection/mutable/StringBuilder;
const #72 = Method	#36.#71;	//  scala/collection/mutable/StringBuilder.append:(Ljava/lang/Object;)Lscala/collection/mutable/StringBuilder;
const #73 = Method	#36.#54;	//  scala/collection/mutable/StringBuilder.toString:()Ljava/lang/String;
const #74 = Asciz	(Ljava/lang/String;)V;
const #75 = NameAndType	#11:#74;//  "<init>":(Ljava/lang/String;)V
const #76 = Method	#65.#75;	//  java/lang/IllegalArgumentException."<init>":(Ljava/lang/String;)V
const #77 = Asciz	,;
const #78 = String	#77;	//  ,
const #79 = Asciz	scala/runtime/BoxesRunTime;
const #80 = class	#79;	//  scala/runtime/BoxesRunTime
const #81 = Asciz	boxToInteger;
const #82 = Asciz	(I)Ljava/lang/Integer;;
const #83 = NameAndType	#81:#82;//  boxToInteger:(I)Ljava/lang/Integer;
const #84 = Method	#80.#83;	//  scala/runtime/BoxesRunTime.boxToInteger:(I)Ljava/lang/Integer;
const #85 = Asciz	 not allowed;
const #86 = String	#85;	//   not allowed
const #87 = Asciz	line1;
const #88 = Asciz	column1;
const #89 = Asciz	()I;
const #90 = int	20;
const #91 = Asciz	scala/ScalaObject;
const #92 = class	#91;	//  scala/ScalaObject

{
public static final scala.io.Position$ MODULE$;

public static {};
  Code:
   Stack=1, Locals=0, Args_size=0
   0:	new	#10; //class scala/io/Position$
   3:	invokespecial	#13; //Method "<init>":()V
   6:	return

public java.lang.String toString(int);
  Code:
   Stack=3, Locals=3, Args_size=2
   0:	new	#36; //class scala/collection/mutable/StringBuilder
   3:	dup
   4:	invokespecial	#37; //Method scala/collection/mutable/StringBuilder."<init>":()V
   7:	astore_2
   8:	aload_2
   9:	aload_0
   10:	iload_1
   11:	invokevirtual	#41; //Method line:(I)I
   14:	invokevirtual	#45; //Method scala/collection/mutable/StringBuilder.append:(I)Lscala/collection/mutable/StringBuilder;
   17:	pop
   18:	aload_2
   19:	ldc	#46; //int 58
   21:	invokevirtual	#49; //Method scala/collection/mutable/StringBuilder.append:(C)Lscala/collection/mutable/StringBuilder;
   24:	pop
   25:	aload_2
   26:	aload_0
   27:	iload_1
   28:	invokevirtual	#52; //Method column:(I)I
   31:	invokevirtual	#45; //Method scala/collection/mutable/StringBuilder.append:(I)Lscala/collection/mutable/StringBuilder;
   34:	pop
   35:	aload_2
   36:	invokevirtual	#55; //Method scala/collection/mutable/StringBuilder.toString:()Ljava/lang/String;
   39:	areturn
  LineNumberTable: 
   line 97: 0
   line 98: 8
   line 99: 18
   line 100: 25
   line 101: 35

  LocalVariableTable: 
   Start  Length  Slot  Name   Signature
   0      40      0    this       Lscala/io/Position$;
   0      40      1    pos       I
   8      31      2    sb       Lscala/collection/mutable/StringBuilder;


public final int column(int);
  Code:
   Stack=2, Locals=2, Args_size=2
   0:	iload_1
   1:	ldc	#61; //int 2047
   3:	iand
   4:	ireturn
  LineNumberTable: 
   line 93: 0

  LocalVariableTable: 
   Start  Length  Slot  Name   Signature
   0      5      0    this       Lscala/io/Position$;
   0      5      1    pos       I


public final int line(int);
  Code:
   Stack=2, Locals=2, Args_size=2
   0:	iload_1
   1:	ldc	#62; //int 11
   3:	ishr
   4:	ldc	#63; //int 1048575
   6:	iand
   7:	ireturn
  LineNumberTable: 
   line 89: 0

  LocalVariableTable: 
   Start  Length  Slot  Name   Signature
   0      8      0    this       Lscala/io/Position$;
   0      8      1    pos       I


public final int encode(int, int);
  Code:
   Stack=4, Locals=5, Args_size=3
   0:	iconst_0
   1:	istore_3
   2:	iconst_0
   3:	istore	4
   5:	iload_1
   6:	iconst_0
   7:	if_icmpge	37
   10:	new	#65; //class java/lang/IllegalArgumentException
   13:	dup
   14:	new	#36; //class scala/collection/mutable/StringBuilder
   17:	dup
   18:	invokespecial	#66; //Method scala/collection/mutable/StringBuilder."<init>":()V
   21:	iload_1
   22:	invokevirtual	#67; //Method scala/collection/mutable/StringBuilder.append:(I)Lscala/collection/mutable/StringBuilder;
   25:	ldc	#69; //String  < 0
   27:	invokevirtual	#72; //Method scala/collection/mutable/StringBuilder.append:(Ljava/lang/Object;)Lscala/collection/mutable/StringBuilder;
   30:	invokevirtual	#73; //Method scala/collection/mutable/StringBuilder.toString:()Ljava/lang/String;
   33:	invokespecial	#76; //Method java/lang/IllegalArgumentException."<init>":(Ljava/lang/String;)V
   36:	athrow
   37:	iload_1
   38:	iconst_0
   39:	if_icmpne	86
   42:	iload_2
   43:	iconst_0
   44:	if_icmpeq	86
   47:	new	#65; //class java/lang/IllegalArgumentException
   50:	dup
   51:	new	#36; //class scala/collection/mutable/StringBuilder
   54:	dup
   55:	invokespecial	#66; //Method scala/collection/mutable/StringBuilder."<init>":()V
   58:	iload_1
   59:	invokevirtual	#67; //Method scala/collection/mutable/StringBuilder.append:(I)Lscala/collection/mutable/StringBuilder;
   62:	ldc	#78; //String ,
   64:	invokevirtual	#72; //Method scala/collection/mutable/StringBuilder.append:(Ljava/lang/Object;)Lscala/collection/mutable/StringBuilder;
   67:	iload_2
   68:	invokestatic	#84; //Method scala/runtime/BoxesRunTime.boxToInteger:(I)Ljava/lang/Integer;
   71:	invokevirtual	#72; //Method scala/collection/mutable/StringBuilder.append:(Ljava/lang/Object;)Lscala/collection/mutable/StringBuilder;
   74:	ldc	#86; //String  not allowed
   76:	invokevirtual	#72; //Method scala/collection/mutable/StringBuilder.append:(Ljava/lang/Object;)Lscala/collection/mutable/StringBuilder;
   79:	invokevirtual	#73; //Method scala/collection/mutable/StringBuilder.toString:()Ljava/lang/String;
   82:	invokespecial	#76; //Method java/lang/IllegalArgumentException."<init>":(Ljava/lang/String;)V
   85:	athrow
   86:	iload_2
   87:	iconst_0
   88:	if_icmpge	130
   91:	new	#65; //class java/lang/IllegalArgumentException
   94:	dup
   95:	new	#36; //class scala/collection/mutable/StringBuilder
   98:	dup
   99:	invokespecial	#66; //Method scala/collection/mutable/StringBuilder."<init>":()V
   102:	iload_1
   103:	invokevirtual	#67; //Method scala/collection/mutable/StringBuilder.append:(I)Lscala/collection/mutable/StringBuilder;
   106:	ldc	#78; //String ,
   108:	invokevirtual	#72; //Method scala/collection/mutable/StringBuilder.append:(Ljava/lang/Object;)Lscala/collection/mutable/StringBuilder;
   111:	iload_2
   112:	invokestatic	#84; //Method scala/runtime/BoxesRunTime.boxToInteger:(I)Ljava/lang/Integer;
   115:	invokevirtual	#72; //Method scala/collection/mutable/StringBuilder.append:(Ljava/lang/Object;)Lscala/collection/mutable/StringBuilder;
   118:	ldc	#86; //String  not allowed
   120:	invokevirtual	#72; //Method scala/collection/mutable/StringBuilder.append:(Ljava/lang/Object;)Lscala/collection/mutable/StringBuilder;
   123:	invokevirtual	#73; //Method scala/collection/mutable/StringBuilder.toString:()Ljava/lang/String;
   126:	invokespecial	#76; //Method java/lang/IllegalArgumentException."<init>":(Ljava/lang/String;)V
   129:	athrow
   130:	iload_1
   131:	ldc	#63; //int 1048575
   133:	if_icmplt	145
   136:	ldc	#63; //int 1048575
   138:	istore_3
   139:	iconst_0
   140:	istore	4
   142:	goto	163
   145:	iload_1
   146:	istore_3
   147:	iload_2
   148:	ldc	#61; //int 2047
   150:	if_icmple	160
   153:	ldc	#61; //int 2047
   155:	istore	4
   157:	goto	163
   160:	iload_2
   161:	istore	4
   163:	iload_3
   164:	ldc	#62; //int 11
   166:	ishl
   167:	iload	4
   169:	ior
   170:	ireturn
  LineNumberTable: 
   line 65: 0
   line 66: 5
   line 67: 10
   line 68: 37
   line 69: 47
   line 70: 86
   line 71: 91
   line 73: 130
   line 74: 136
   line 75: 139
   line 78: 145
   line 79: 147
   line 80: 153
   line 82: 160
   line 84: 163

  LocalVariableTable: 
   Start  Length  Slot  Name   Signature
   0      171      0    this       Lscala/io/Position$;
   0      171      1    line       I
   0      171      2    column       I
   2      168      3    line1       I
   5      165      4    column1       I


public final int FIRSTPOS();
  Code:
   Stack=1, Locals=1, Args_size=1
   0:	aload_0
   1:	getfield	#32; //Field FIRSTPOS:I
   4:	ireturn
  LineNumberTable: 
   line 61: 0


public final int NOPOS();
  Code:
   Stack=1, Locals=1, Args_size=1
   0:	iconst_0
   1:	ireturn
  LineNumberTable: 
   line 58: 0


public final int COLUMN_MASK();
  Code:
   Stack=1, Locals=1, Args_size=1
   0:	ldc	#61; //int 2047
   2:	ireturn
  LineNumberTable: 
   line 55: 0


public final int LINE_MASK();
  Code:
   Stack=1, Locals=1, Args_size=1
   0:	ldc	#63; //int 1048575
   2:	ireturn
  LineNumberTable: 
   line 53: 0


public final int COLUMN_BITS();
  Code:
   Stack=1, Locals=1, Args_size=1
   0:	ldc	#62; //int 11
   2:	ireturn
  LineNumberTable: 
   line 50: 0


public final int LINE_BITS();
  Code:
   Stack=1, Locals=1, Args_size=1
   0:	ldc	#90; //int 20
   2:	ireturn
  LineNumberTable: 
   line 48: 0


}

