Compiled from "Source.scala"
public final class scala.io.Source$LineIterator$$anonfun$4 extends java.lang.Object implements scala.Function1,scala.ScalaObject,java.io.Serializable
  SourceFile: "Source.scala"
  Scala: length = 0x
   
  InnerClass: 
   public LineIterator=class scala/io/Source$LineIterator of class scala/io/Source
   public final $anonfun$4=class scala/io/Source$LineIterator$$anonfun$4 of class scala/io/Source$LineIterator
  minor version: 0
  major version: 49
  Constant pool:
Asciz	SourceFile;
Asciz	Source.scala;
Asciz	<clinit>;
Asciz	()V;
Asciz	Code;
Asciz	serialVersionUID;
Asciz	J;
Asciz	scala/io/Source$LineIterator$$anonfun$4;
class	scala/io/Source$LineIterator$$anonfun$4
NameAndType	serialVersionUID:J
Field	scala/io/Source$LineIterator$$anonfun$4.serialVersionUID:J
Asciz	firstCh$1;
Asciz	C;
Asciz	$outer;
Asciz	Lscala/io/Source$LineIterator;;
Asciz	<init>;
Asciz	(Lscala/io/Source$LineIterator;C)V;
Asciz	LineNumberTable;
Asciz	java/lang/NullPointerException;
class	java/lang/NullPointerException
NameAndType	"<init>":()V
Method	java/lang/NullPointerException."<init>":()V
NameAndType	$outer:Lscala/io/Source$LineIterator;
Field	scala/io/Source$LineIterator$$anonfun$4.$outer:Lscala/io/Source$LineIterator;
NameAndType	firstCh$1:C
Field	scala/io/Source$LineIterator$$anonfun$4.firstCh$1:C
Asciz	java/lang/Object;
class	java/lang/Object
Method	java/lang/Object."<init>":()V
Asciz	scala/Function1$class;
class	scala/Function1$class
Asciz	$init$;
Asciz	(Lscala/Function1;)V;
NameAndType	$init$:(Lscala/Function1;)V
Method	scala/Function1$class.$init$:(Lscala/Function1;)V
Asciz	this;
Asciz	Lscala/io/Source$LineIterator$$anonfun$4;;
Asciz	LocalVariableTable;
Asciz	apply;
Asciz	(Ljava/lang/Object;)Ljava/lang/Object;;
Asciz	scala/runtime/BoxesRunTime;
class	scala/runtime/BoxesRunTime
Asciz	unboxToChar;
Asciz	(Ljava/lang/Object;)C;
NameAndType	unboxToChar:(Ljava/lang/Object;)C
Method	scala/runtime/BoxesRunTime.unboxToChar:(Ljava/lang/Object;)C
Asciz	(C)Z;
NameAndType	apply:(C)Z
Method	scala/io/Source$LineIterator$$anonfun$4.apply:(C)Z
Asciz	boxToBoolean;
Asciz	(Z)Ljava/lang/Boolean;;
NameAndType	boxToBoolean:(Z)Ljava/lang/Boolean;
Method	scala/runtime/BoxesRunTime.boxToBoolean:(Z)Ljava/lang/Boolean;
Asciz	v1;
Asciz	Ljava/lang/Object;;
Asciz	scala/io/Source$LineIterator;
class	scala/io/Source$LineIterator
Asciz	iter;
Asciz	()Lscala/collection/BufferedIterator;;
NameAndType	iter:()Lscala/collection/BufferedIterator;
Method	scala/io/Source$LineIterator.iter:()Lscala/collection/BufferedIterator;
Asciz	scala/collection/Iterator;
class	scala/collection/Iterator
Asciz	hasNext;
Asciz	()Z;
NameAndType	hasNext:()Z
InterfaceMethod	scala/collection/Iterator.hasNext:()Z
Asciz	scala/collection/BufferedIterator;
class	scala/collection/BufferedIterator
Asciz	head;
Asciz	()Ljava/lang/Object;;
NameAndType	head:()Ljava/lang/Object;
InterfaceMethod	scala/collection/BufferedIterator.head:()Ljava/lang/Object;
Asciz	scala$io$Source$LineIterator$$separator;
Asciz	Ljava/lang/String;;
NameAndType	scala$io$Source$LineIterator$$separator:Ljava/lang/String;
Field	scala/io/Source$LineIterator.scala$io$Source$LineIterator$$separator:Ljava/lang/String;
Asciz	scala/collection/immutable/StringOps;
class	scala/collection/immutable/StringOps
Asciz	(Ljava/lang/String;)V;
NameAndType	"<init>":(Ljava/lang/String;)V
Method	scala/collection/immutable/StringOps."<init>":(Ljava/lang/String;)V
Asciz	scala/collection/immutable/StringLike;
class	scala/collection/immutable/StringLike
Asciz	(I)C;
NameAndType	apply:(I)C
InterfaceMethod	scala/collection/immutable/StringLike.apply:(I)C
Asciz	next;
NameAndType	next:()Ljava/lang/Object;
InterfaceMethod	scala/collection/Iterator.next:()Ljava/lang/Object;
Asciz	scala/runtime/BoxedUnit;
class	scala/runtime/BoxedUnit
Asciz	UNIT;
Asciz	Lscala/runtime/BoxedUnit;;
NameAndType	UNIT:Lscala/runtime/BoxedUnit;
Field	scala/runtime/BoxedUnit.UNIT:Lscala/runtime/BoxedUnit;
Asciz	ch;
Asciz	res;
Asciz	Z;
Asciz	andThen;
Asciz	(Lscala/Function1;)Lscala/Function1;;
Asciz	(Lscala/Function1;Lscala/Function1;)Lscala/Function1;;
NameAndType	andThen:(Lscala/Function1;Lscala/Function1;)Lscala/Function1;
Method	scala/Function1$class.andThen:(Lscala/Function1;Lscala/Function1;)Lscala/Function1;
Asciz	g;
Asciz	Lscala/Function1;;
Asciz	compose;
NameAndType	compose:(Lscala/Function1;Lscala/Function1;)Lscala/Function1;
Method	scala/Function1$class.compose:(Lscala/Function1;Lscala/Function1;)Lscala/Function1;
Asciz	toString;
Asciz	()Ljava/lang/String;;
Asciz	(Lscala/Function1;)Ljava/lang/String;;
NameAndType	toString:(Lscala/Function1;)Ljava/lang/String;
Method	scala/Function1$class.toString:(Lscala/Function1;)Ljava/lang/String;
Asciz	Scala;
Asciz	InnerClasses;
Asciz	scala/io/Source;
class	scala/io/Source
Asciz	LineIterator;
Asciz	$anonfun$4;
Asciz	scala/Function1;
class	scala/Function1
Asciz	scala/ScalaObject;
class	scala/ScalaObject
Asciz	java/io/Serializable;
class	java/io/Serializable

{
public static final long serialVersionUID;
  Signature: J

private final char firstCh$1;
  Signature: C

private final scala.io.Source$LineIterator $outer;
  Signature: Lscala/io/Source$LineIterator;

public static {};
  Signature: ()V
  Code:
   Stack=2, Locals=0, Args_size=0
	lconst_0
	putstatic	Field serialVersionUID:J
	return
  Labels:

public scala.io.Source$LineIterator$$anonfun$4(scala.io.Source$LineIterator, char);
  Signature: (Lscala/io/Source$LineIterator;C)V
  Code:
   Stack=2, Locals=3, Args_size=3
	aload_1
	ifnonnull	l1 // aload_0
	new	class java/lang/NullPointerException
	dup
	invokespecial	Method java/lang/NullPointerException."<init>":()V
	athrow
l1	aload_0
	aload_1
	putfield	Field $outer:Lscala/io/Source$LineIterator;
	aload_0
	iload_2
	putfield	Field firstCh$1:C
	aload_0
	invokespecial	Method java/lang/Object."<init>":()V
	aload_0
	invokestatic	Method scala/Function1$class.$init$:(Lscala/Function1;)V
	return
  Labels:
   	l1 = 12 // aload_0
  LocalVariableTable: 
   Start  Length  Slot  Name   Signature
   0      31      0    this       Lscala/io/Source$LineIterator$$anonfun$4;
   0      31      1    $outer       Lscala/io/Source$LineIterator;


public final java.lang.Object apply(java.lang.Object);
  Signature: (Ljava/lang/Object;)Ljava/lang/Object;
  Code:
   Stack=2, Locals=4, Args_size=2
	aload_0
	getfield	Field $outer:Lscala/io/Source$LineIterator;
	astore_3
	aload_0
	aload_1
	invokestatic	Method scala/runtime/BoxesRunTime.unboxToChar:(Ljava/lang/Object;)C
	invokevirtual	Method apply:(C)Z
	istore_2
	iload_2
	invokestatic	Method scala/runtime/BoxesRunTime.boxToBoolean:(Z)Ljava/lang/Boolean;
	areturn
  Labels:
  LocalVariableTable: 
   Start  Length  Slot  Name   Signature
   0      19      0    this       Lscala/io/Source$LineIterator$$anonfun$4;
   5      14      1    v1       Ljava/lang/Object;


public final boolean apply(char);
  Signature: (C)Z
  Code:
   Stack=4, Locals=5, Args_size=2
	aload_0
	getfield	Field $outer:Lscala/io/Source$LineIterator;
	astore	4
	iload_1
	aload_0
	getfield	Field firstCh$1:C
	if_icmpne	l1 // iconst_0
	aload_0
	getfield	Field $outer:Lscala/io/Source$LineIterator;
	invokevirtual	Method scala/io/Source$LineIterator.iter:()Lscala/collection/BufferedIterator;
	invokeinterface	InterfaceMethod scala/collection/Iterator.hasNext:()Z
	ifeq	l1 // iconst_0
	aload_0
	getfield	Field $outer:Lscala/io/Source$LineIterator;
	invokevirtual	Method scala/io/Source$LineIterator.iter:()Lscala/collection/BufferedIterator;
	invokeinterface	InterfaceMethod scala/collection/BufferedIterator.head:()Ljava/lang/Object;
	invokestatic	Method scala/runtime/BoxesRunTime.unboxToChar:(Ljava/lang/Object;)C
	aload_0
	getfield	Field $outer:Lscala/io/Source$LineIterator;
	getfield	Field scala/io/Source$LineIterator.scala$io$Source$LineIterator$$separator:Ljava/lang/String;
	astore_2
	new	class scala/collection/immutable/StringOps
	dup
	aload_2
	invokespecial	Method scala/collection/immutable/StringOps."<init>":(Ljava/lang/String;)V
	iconst_1
	invokeinterface	InterfaceMethod scala/collection/immutable/StringLike.apply:(I)C
	if_icmpne	l2 // iconst_0
	iconst_1
	goto	l3 // istore_3
l2	iconst_0
l3	istore_3
	iload_3
	ifeq	l4 // getstatic
	aload_0
	getfield	Field $outer:Lscala/io/Source$LineIterator;
	invokevirtual	Method scala/io/Source$LineIterator.iter:()Lscala/collection/BufferedIterator;
	invokeinterface	InterfaceMethod scala/collection/Iterator.next:()Ljava/lang/Object;
	goto	l5 // pop
l4	getstatic	Field scala/runtime/BoxedUnit.UNIT:Lscala/runtime/BoxedUnit;
l5	pop
	iload_3
	ifeq	l1 // iconst_0
	iconst_1
	goto	l6 // ireturn
l1	iconst_0
l6	ireturn
  Labels:
   	l2 = 73 // iconst_0
   	l3 = 74 // istore_3
   	l4 = 94 // getstatic
   	l5 = 97 // pop
   	l1 = 106 // iconst_0
   	l6 = 107 // ireturn
  LocalVariableTable: 
   Start  Length  Slot  Name   Signature
   0      108      0    this       Lscala/io/Source$LineIterator$$anonfun$4;
   6      102      1    ch       C
   75      24      3    res       Z


public scala.Function1 andThen(scala.Function1);
  Signature: (Lscala/Function1;)Lscala/Function1;
  Code:
   Stack=2, Locals=2, Args_size=2
	aload_0
	aload_1
	invokestatic	Method scala/Function1$class.andThen:(Lscala/Function1;Lscala/Function1;)Lscala/Function1;
	areturn
  Labels:
  LocalVariableTable: 
   Start  Length  Slot  Name   Signature
   0      6      0    this       Lscala/io/Source$LineIterator$$anonfun$4;
   0      6      1    g       Lscala/Function1;


public scala.Function1 compose(scala.Function1);
  Signature: (Lscala/Function1;)Lscala/Function1;
  Code:
   Stack=2, Locals=2, Args_size=2
	aload_0
	aload_1
	invokestatic	Method scala/Function1$class.compose:(Lscala/Function1;Lscala/Function1;)Lscala/Function1;
	areturn
  Labels:
  LocalVariableTable: 
   Start  Length  Slot  Name   Signature
   0      6      0    this       Lscala/io/Source$LineIterator$$anonfun$4;
   0      6      1    g       Lscala/Function1;


public java.lang.String toString();
  Signature: ()Ljava/lang/String;
  Code:
   Stack=1, Locals=1, Args_size=1
	aload_0
	invokestatic	Method scala/Function1$class.toString:(Lscala/Function1;)Ljava/lang/String;
	areturn
  Labels:

}

