Compiled from "Source.scala"
public final class scala.io.Source$LineIterator$$anonfun$4 extends java.lang.Object implements scala.Function1,scala.ScalaObject,java.io.Serializable
  SourceFile: "Source.scala"
  Scala: length = 0x
   
  InnerClass: 
   public #119= #57 of #118; //LineIterator=class scala/io/Source$LineIterator of class scala/io/Source
   public final #120= #9 of #57; //$anonfun$4=class scala/io/Source$LineIterator$$anonfun$4 of class scala/io/Source$LineIterator
  minor version: 0
  major version: 49
  Constant pool:
const #1 = Asciz	SourceFile;
const #2 = Asciz	Source.scala;
const #3 = Asciz	<clinit>;
const #4 = Asciz	()V;
const #5 = Asciz	Code;
const #6 = Asciz	serialVersionUID;
const #7 = Asciz	J;
const #8 = Asciz	scala/io/Source$LineIterator$$anonfun$4;
const #9 = class	#8;	//  scala/io/Source$LineIterator$$anonfun$4
const #10 = NameAndType	#6:#7;//  serialVersionUID:J
const #11 = Field	#9.#10;	//  scala/io/Source$LineIterator$$anonfun$4.serialVersionUID:J
const #12 = Asciz	firstCh$1;
const #13 = Asciz	C;
const #14 = Asciz	$outer;
const #15 = Asciz	Lscala/io/Source$LineIterator;;
const #16 = Asciz	<init>;
const #17 = Asciz	(Lscala/io/Source$LineIterator;C)V;
const #18 = Asciz	LineNumberTable;
const #19 = Asciz	java/lang/NullPointerException;
const #20 = class	#19;	//  java/lang/NullPointerException
const #21 = NameAndType	#16:#4;//  "<init>":()V
const #22 = Method	#20.#21;	//  java/lang/NullPointerException."<init>":()V
const #23 = NameAndType	#14:#15;//  $outer:Lscala/io/Source$LineIterator;
const #24 = Field	#9.#23;	//  scala/io/Source$LineIterator$$anonfun$4.$outer:Lscala/io/Source$LineIterator;
const #25 = NameAndType	#12:#13;//  firstCh$1:C
const #26 = Field	#9.#25;	//  scala/io/Source$LineIterator$$anonfun$4.firstCh$1:C
const #27 = Asciz	java/lang/Object;
const #28 = class	#27;	//  java/lang/Object
const #29 = Method	#28.#21;	//  java/lang/Object."<init>":()V
const #30 = Asciz	scala/Function1$class;
const #31 = class	#30;	//  scala/Function1$class
const #32 = Asciz	$init$;
const #33 = Asciz	(Lscala/Function1;)V;
const #34 = NameAndType	#32:#33;//  $init$:(Lscala/Function1;)V
const #35 = Method	#31.#34;	//  scala/Function1$class.$init$:(Lscala/Function1;)V
const #36 = Asciz	this;
const #37 = Asciz	Lscala/io/Source$LineIterator$$anonfun$4;;
const #38 = Asciz	LocalVariableTable;
const #39 = Asciz	apply;
const #40 = Asciz	(Ljava/lang/Object;)Ljava/lang/Object;;
const #41 = Asciz	scala/runtime/BoxesRunTime;
const #42 = class	#41;	//  scala/runtime/BoxesRunTime
const #43 = Asciz	unboxToChar;
const #44 = Asciz	(Ljava/lang/Object;)C;
const #45 = NameAndType	#43:#44;//  unboxToChar:(Ljava/lang/Object;)C
const #46 = Method	#42.#45;	//  scala/runtime/BoxesRunTime.unboxToChar:(Ljava/lang/Object;)C
const #47 = Asciz	(C)Z;
const #48 = NameAndType	#39:#47;//  apply:(C)Z
const #49 = Method	#9.#48;	//  scala/io/Source$LineIterator$$anonfun$4.apply:(C)Z
const #50 = Asciz	boxToBoolean;
const #51 = Asciz	(Z)Ljava/lang/Boolean;;
const #52 = NameAndType	#50:#51;//  boxToBoolean:(Z)Ljava/lang/Boolean;
const #53 = Method	#42.#52;	//  scala/runtime/BoxesRunTime.boxToBoolean:(Z)Ljava/lang/Boolean;
const #54 = Asciz	v1;
const #55 = Asciz	Ljava/lang/Object;;
const #56 = Asciz	scala/io/Source$LineIterator;
const #57 = class	#56;	//  scala/io/Source$LineIterator
const #58 = Asciz	iter;
const #59 = Asciz	()Lscala/collection/BufferedIterator;;
const #60 = NameAndType	#58:#59;//  iter:()Lscala/collection/BufferedIterator;
const #61 = Method	#57.#60;	//  scala/io/Source$LineIterator.iter:()Lscala/collection/BufferedIterator;
const #62 = Asciz	scala/collection/Iterator;
const #63 = class	#62;	//  scala/collection/Iterator
const #64 = Asciz	hasNext;
const #65 = Asciz	()Z;
const #66 = NameAndType	#64:#65;//  hasNext:()Z
const #67 = InterfaceMethod	#63.#66;	//  scala/collection/Iterator.hasNext:()Z
const #68 = Asciz	scala/collection/BufferedIterator;
const #69 = class	#68;	//  scala/collection/BufferedIterator
const #70 = Asciz	head;
const #71 = Asciz	()Ljava/lang/Object;;
const #72 = NameAndType	#70:#71;//  head:()Ljava/lang/Object;
const #73 = InterfaceMethod	#69.#72;	//  scala/collection/BufferedIterator.head:()Ljava/lang/Object;
const #74 = Asciz	scala$io$Source$LineIterator$$separator;
const #75 = Asciz	Ljava/lang/String;;
const #76 = NameAndType	#74:#75;//  scala$io$Source$LineIterator$$separator:Ljava/lang/String;
const #77 = Field	#57.#76;	//  scala/io/Source$LineIterator.scala$io$Source$LineIterator$$separator:Ljava/lang/String;
const #78 = Asciz	scala/collection/immutable/StringOps;
const #79 = class	#78;	//  scala/collection/immutable/StringOps
const #80 = Asciz	(Ljava/lang/String;)V;
const #81 = NameAndType	#16:#80;//  "<init>":(Ljava/lang/String;)V
const #82 = Method	#79.#81;	//  scala/collection/immutable/StringOps."<init>":(Ljava/lang/String;)V
const #83 = Asciz	scala/collection/immutable/StringLike;
const #84 = class	#83;	//  scala/collection/immutable/StringLike
const #85 = Asciz	(I)C;
const #86 = NameAndType	#39:#85;//  apply:(I)C
const #87 = InterfaceMethod	#84.#86;	//  scala/collection/immutable/StringLike.apply:(I)C
const #88 = Asciz	next;
const #89 = NameAndType	#88:#71;//  next:()Ljava/lang/Object;
const #90 = InterfaceMethod	#63.#89;	//  scala/collection/Iterator.next:()Ljava/lang/Object;
const #91 = Asciz	scala/runtime/BoxedUnit;
const #92 = class	#91;	//  scala/runtime/BoxedUnit
const #93 = Asciz	UNIT;
const #94 = Asciz	Lscala/runtime/BoxedUnit;;
const #95 = NameAndType	#93:#94;//  UNIT:Lscala/runtime/BoxedUnit;
const #96 = Field	#92.#95;	//  scala/runtime/BoxedUnit.UNIT:Lscala/runtime/BoxedUnit;
const #97 = Asciz	ch;
const #98 = Asciz	res;
const #99 = Asciz	Z;
const #100 = Asciz	andThen;
const #101 = Asciz	(Lscala/Function1;)Lscala/Function1;;
const #102 = Asciz	(Lscala/Function1;Lscala/Function1;)Lscala/Function1;;
const #103 = NameAndType	#100:#102;//  andThen:(Lscala/Function1;Lscala/Function1;)Lscala/Function1;
const #104 = Method	#31.#103;	//  scala/Function1$class.andThen:(Lscala/Function1;Lscala/Function1;)Lscala/Function1;
const #105 = Asciz	g;
const #106 = Asciz	Lscala/Function1;;
const #107 = Asciz	compose;
const #108 = NameAndType	#107:#102;//  compose:(Lscala/Function1;Lscala/Function1;)Lscala/Function1;
const #109 = Method	#31.#108;	//  scala/Function1$class.compose:(Lscala/Function1;Lscala/Function1;)Lscala/Function1;
const #110 = Asciz	toString;
const #111 = Asciz	()Ljava/lang/String;;
const #112 = Asciz	(Lscala/Function1;)Ljava/lang/String;;
const #113 = NameAndType	#110:#112;//  toString:(Lscala/Function1;)Ljava/lang/String;
const #114 = Method	#31.#113;	//  scala/Function1$class.toString:(Lscala/Function1;)Ljava/lang/String;
const #115 = Asciz	Scala;
const #116 = Asciz	InnerClasses;
const #117 = Asciz	scala/io/Source;
const #118 = class	#117;	//  scala/io/Source
const #119 = Asciz	LineIterator;
const #120 = Asciz	$anonfun$4;
const #121 = Asciz	scala/Function1;
const #122 = class	#121;	//  scala/Function1
const #123 = Asciz	scala/ScalaObject;
const #124 = class	#123;	//  scala/ScalaObject
const #125 = Asciz	java/io/Serializable;
const #126 = class	#125;	//  java/io/Serializable

{
public static final long serialVersionUID;

public static {};
  Code:
   Stack=2, Locals=0, Args_size=0
   0:	lconst_0
   1:	putstatic	#11; //Field serialVersionUID:J
   4:	return

public scala.io.Source$LineIterator$$anonfun$4(scala.io.Source$LineIterator, char);
  Code:
   Stack=2, Locals=3, Args_size=3
   0:	aload_1
   1:	ifnonnull	12
   4:	new	#20; //class java/lang/NullPointerException
   7:	dup
   8:	invokespecial	#22; //Method java/lang/NullPointerException."<init>":()V
   11:	athrow
   12:	aload_0
   13:	aload_1
   14:	putfield	#24; //Field $outer:Lscala/io/Source$LineIterator;
   17:	aload_0
   18:	iload_2
   19:	putfield	#26; //Field firstCh$1:C
   22:	aload_0
   23:	invokespecial	#29; //Method java/lang/Object."<init>":()V
   26:	aload_0
   27:	invokestatic	#35; //Method scala/Function1$class.$init$:(Lscala/Function1;)V
   30:	return
  LineNumberTable: 
   line 173: 0

  LocalVariableTable: 
   Start  Length  Slot  Name   Signature
   0      31      0    this       Lscala/io/Source$LineIterator$$anonfun$4;
   0      31      1    $outer       Lscala/io/Source$LineIterator;


public final java.lang.Object apply(java.lang.Object);
  Code:
   Stack=2, Locals=4, Args_size=2
   0:	aload_0
   1:	getfield	#24; //Field $outer:Lscala/io/Source$LineIterator;
   4:	astore_3
   5:	aload_0
   6:	aload_1
   7:	invokestatic	#46; //Method scala/runtime/BoxesRunTime.unboxToChar:(Ljava/lang/Object;)C
   10:	invokevirtual	#49; //Method apply:(C)Z
   13:	istore_2
   14:	iload_2
   15:	invokestatic	#53; //Method scala/runtime/BoxesRunTime.boxToBoolean:(Z)Ljava/lang/Boolean;
   18:	areturn
  LineNumberTable: 
   line 173: 0

  LocalVariableTable: 
   Start  Length  Slot  Name   Signature
   0      19      0    this       Lscala/io/Source$LineIterator$$anonfun$4;
   5      14      1    v1       Ljava/lang/Object;


public final boolean apply(char);
  Code:
   Stack=4, Locals=5, Args_size=2
   0:	aload_0
   1:	getfield	#24; //Field $outer:Lscala/io/Source$LineIterator;
   4:	astore	4
   6:	iload_1
   7:	aload_0
   8:	getfield	#26; //Field firstCh$1:C
   11:	if_icmpne	106
   14:	aload_0
   15:	getfield	#24; //Field $outer:Lscala/io/Source$LineIterator;
   18:	invokevirtual	#61; //Method scala/io/Source$LineIterator.iter:()Lscala/collection/BufferedIterator;
   21:	invokeinterface	#67,  1; //InterfaceMethod scala/collection/Iterator.hasNext:()Z
   26:	ifeq	106
   29:	aload_0
   30:	getfield	#24; //Field $outer:Lscala/io/Source$LineIterator;
   33:	invokevirtual	#61; //Method scala/io/Source$LineIterator.iter:()Lscala/collection/BufferedIterator;
   36:	invokeinterface	#73,  1; //InterfaceMethod scala/collection/BufferedIterator.head:()Ljava/lang/Object;
   41:	invokestatic	#46; //Method scala/runtime/BoxesRunTime.unboxToChar:(Ljava/lang/Object;)C
   44:	aload_0
   45:	getfield	#24; //Field $outer:Lscala/io/Source$LineIterator;
   48:	getfield	#77; //Field scala/io/Source$LineIterator.scala$io$Source$LineIterator$$separator:Ljava/lang/String;
   51:	astore_2
   52:	new	#79; //class scala/collection/immutable/StringOps
   55:	dup
   56:	aload_2
   57:	invokespecial	#82; //Method scala/collection/immutable/StringOps."<init>":(Ljava/lang/String;)V
   60:	iconst_1
   61:	invokeinterface	#87,  2; //InterfaceMethod scala/collection/immutable/StringLike.apply:(I)C
   66:	if_icmpne	73
   69:	iconst_1
   70:	goto	74
   73:	iconst_0
   74:	istore_3
   75:	iload_3
   76:	ifeq	94
   79:	aload_0
   80:	getfield	#24; //Field $outer:Lscala/io/Source$LineIterator;
   83:	invokevirtual	#61; //Method scala/io/Source$LineIterator.iter:()Lscala/collection/BufferedIterator;
   86:	invokeinterface	#90,  1; //InterfaceMethod scala/collection/Iterator.next:()Ljava/lang/Object;
   91:	goto	97
   94:	getstatic	#96; //Field scala/runtime/BoxedUnit.UNIT:Lscala/runtime/BoxedUnit;
   97:	pop
   98:	iload_3
   99:	ifeq	106
   102:	iconst_1
   103:	goto	107
   106:	iconst_0
   107:	ireturn
  LineNumberTable: 
   line 173: 0
   line 174: 29
   line 175: 75
   line 176: 98
   line 173: 99

  LocalVariableTable: 
   Start  Length  Slot  Name   Signature
   0      108      0    this       Lscala/io/Source$LineIterator$$anonfun$4;
   6      102      1    ch       C
   75      24      3    res       Z


public scala.Function1 andThen(scala.Function1);
  Code:
   Stack=2, Locals=2, Args_size=2
   0:	aload_0
   1:	aload_1
   2:	invokestatic	#104; //Method scala/Function1$class.andThen:(Lscala/Function1;Lscala/Function1;)Lscala/Function1;
   5:	areturn
  LineNumberTable: 
   line 173: 0

  LocalVariableTable: 
   Start  Length  Slot  Name   Signature
   0      6      0    this       Lscala/io/Source$LineIterator$$anonfun$4;
   0      6      1    g       Lscala/Function1;


public scala.Function1 compose(scala.Function1);
  Code:
   Stack=2, Locals=2, Args_size=2
   0:	aload_0
   1:	aload_1
   2:	invokestatic	#109; //Method scala/Function1$class.compose:(Lscala/Function1;Lscala/Function1;)Lscala/Function1;
   5:	areturn
  LineNumberTable: 
   line 173: 0

  LocalVariableTable: 
   Start  Length  Slot  Name   Signature
   0      6      0    this       Lscala/io/Source$LineIterator$$anonfun$4;
   0      6      1    g       Lscala/Function1;


public java.lang.String toString();
  Code:
   Stack=1, Locals=1, Args_size=1
   0:	aload_0
   1:	invokestatic	#114; //Method scala/Function1$class.toString:(Lscala/Function1;)Ljava/lang/String;
   4:	areturn
  LineNumberTable: 
   line 173: 0


}

