Compiled from "Source.scala"
public final class scala.io.Source$LineIterator$$anonfun$3 extends scala.runtime.AbstractFunction1 implements java.io.Serializable
  SourceFile: "Source.scala"
  Scala: length = 0x
   
  InnerClass: 
   public LineIterator=class scala/io/Source$LineIterator of class scala/io/Source
   public final $anonfun$3=class scala/io/Source$LineIterator$$anonfun$3 of class scala/io/Source$LineIterator
  minor version: 0
  major version: 49
  Constant pool:
Asciz	SourceFile;
Asciz	Source.scala;
Asciz	<clinit>;
Asciz	()V;
Asciz	Code;
Asciz	serialVersionUID;
Asciz	J;
Asciz	scala/io/Source$LineIterator$$anonfun$3;
class	scala/io/Source$LineIterator$$anonfun$3
NameAndType	serialVersionUID:J
Field	scala/io/Source$LineIterator$$anonfun$3.serialVersionUID:J
Asciz	firstCh$1;
Asciz	C;
Asciz	<init>;
Asciz	(Lscala/io/Source$LineIterator;C)V;
Asciz	LineNumberTable;
NameAndType	firstCh$1:C
Field	scala/io/Source$LineIterator$$anonfun$3.firstCh$1:C
Asciz	scala/runtime/AbstractFunction1;
class	scala/runtime/AbstractFunction1
NameAndType	"<init>":()V
Method	scala/runtime/AbstractFunction1."<init>":()V
Asciz	this;
Asciz	Lscala/io/Source$LineIterator$$anonfun$3;;
Asciz	$outer;
Asciz	Lscala/io/Source$LineIterator;;
Asciz	LocalVariableTable;
Asciz	apply;
Asciz	(Ljava/lang/Object;)Ljava/lang/Object;;
Asciz	scala/runtime/BoxesRunTime;
class	scala/runtime/BoxesRunTime
Asciz	unboxToChar;
Asciz	(Ljava/lang/Object;)C;
NameAndType	unboxToChar:(Ljava/lang/Object;)C
Method	scala/runtime/BoxesRunTime.unboxToChar:(Ljava/lang/Object;)C
Asciz	(C)Z;
NameAndType	apply:(C)Z
Method	scala/io/Source$LineIterator$$anonfun$3.apply:(C)Z
Asciz	boxToBoolean;
Asciz	(Z)Ljava/lang/Boolean;;
NameAndType	boxToBoolean:(Z)Ljava/lang/Boolean;
Method	scala/runtime/BoxesRunTime.boxToBoolean:(Z)Ljava/lang/Boolean;
Asciz	v1;
Asciz	Ljava/lang/Object;;
Asciz	Scala;
Asciz	InnerClasses;
Asciz	scala/io/Source$LineIterator;
class	scala/io/Source$LineIterator
Asciz	scala/io/Source;
class	scala/io/Source
Asciz	LineIterator;
Asciz	$anonfun$3;
Asciz	java/io/Serializable;
class	java/io/Serializable

{
public static final long serialVersionUID;
  Signature: J

public final char firstCh$1;
  Signature: C

public static {};
  Signature: ()V
  Code:
   Stack=2, Locals=0, Args_size=0
	lconst_0
	putstatic	Field serialVersionUID:J
	return
  Labels:

public scala.io.Source$LineIterator$$anonfun$3(scala.io.Source$LineIterator, char);
  Signature: (Lscala/io/Source$LineIterator;C)V
  Code:
   Stack=2, Locals=3, Args_size=3
	aload_0
	iload_2
	putfield	Field firstCh$1:C
	aload_0
	invokespecial	Method scala/runtime/AbstractFunction1."<init>":()V
	return
  Labels:
  LocalVariableTable: 
   Start  Length  Slot  Name   Signature
   0      10      0    this       Lscala/io/Source$LineIterator$$anonfun$3;
   0      10      1    $outer       Lscala/io/Source$LineIterator;


public final java.lang.Object apply(java.lang.Object);
  Signature: (Ljava/lang/Object;)Ljava/lang/Object;
  Code:
   Stack=2, Locals=3, Args_size=2
	aload_0
	aload_1
	invokestatic	Method scala/runtime/BoxesRunTime.unboxToChar:(Ljava/lang/Object;)C
	invokevirtual	Method apply:(C)Z
	istore_2
	iload_2
	invokestatic	Method scala/runtime/BoxesRunTime.boxToBoolean:(Z)Ljava/lang/Boolean;
	areturn
  Labels:
  LocalVariableTable: 
   Start  Length  Slot  Name   Signature
   0      14      0    this       Lscala/io/Source$LineIterator$$anonfun$3;
   0      14      1    v1       Ljava/lang/Object;


public final boolean apply(char);
  Signature: (C)Z
  Code:
   Stack=2, Locals=2, Args_size=2
	iload_1
	aload_0
	getfield	Field firstCh$1:C
	if_icmpne	l1 // iconst_0
	iconst_1
	goto	l2 // ireturn
l1	iconst_0
l2	ireturn
  Labels:
   	l1 = 12 // iconst_0
   	l2 = 13 // ireturn

}

