Compiled from "Source.scala"
public final class scala.io.Source$$anonfun$fromInputStream$1 extends java.lang.Object implements scala.Function0,scala.ScalaObject,java.io.Serializable
  SourceFile: "Source.scala"
  Scala: length = 0x
   
  InnerClass: 
   public final #52= #12 of #51; //$anonfun$fromInputStream$1=class scala/io/Source$$anonfun$fromInputStream$1 of class scala/io/Source
  minor version: 0
  major version: 49
  Constant pool:
const #1 = Asciz	SourceFile;
const #2 = Asciz	Source.scala;
const #3 = Asciz	codec$2;
const #4 = Asciz	Lscala/io/Codec;;
const #5 = Asciz	inputStream$1;
const #6 = Asciz	Ljava/io/InputStream;;
const #7 = Asciz	<init>;
const #8 = Asciz	(Ljava/io/InputStream;Lscala/io/Codec;)V;
const #9 = Asciz	Code;
const #10 = Asciz	LineNumberTable;
const #11 = Asciz	scala/io/Source$$anonfun$fromInputStream$1;
const #12 = class	#11;	//  scala/io/Source$$anonfun$fromInputStream$1
const #13 = NameAndType	#5:#6;//  inputStream$1:Ljava/io/InputStream;
const #14 = Field	#12.#13;	//  scala/io/Source$$anonfun$fromInputStream$1.inputStream$1:Ljava/io/InputStream;
const #15 = NameAndType	#3:#4;//  codec$2:Lscala/io/Codec;
const #16 = Field	#12.#15;	//  scala/io/Source$$anonfun$fromInputStream$1.codec$2:Lscala/io/Codec;
const #17 = Asciz	java/lang/Object;
const #18 = class	#17;	//  java/lang/Object
const #19 = Asciz	()V;
const #20 = NameAndType	#7:#19;//  "<init>":()V
const #21 = Method	#18.#20;	//  java/lang/Object."<init>":()V
const #22 = Asciz	scala/Function0$class;
const #23 = class	#22;	//  scala/Function0$class
const #24 = Asciz	$init$;
const #25 = Asciz	(Lscala/Function0;)V;
const #26 = NameAndType	#24:#25;//  $init$:(Lscala/Function0;)V
const #27 = Method	#23.#26;	//  scala/Function0$class.$init$:(Lscala/Function0;)V
const #28 = Asciz	apply;
const #29 = Asciz	()Ljava/lang/Object;;
const #30 = Asciz	()Lscala/io/Source;;
const #31 = NameAndType	#28:#30;//  apply:()Lscala/io/Source;
const #32 = Method	#12.#31;	//  scala/io/Source$$anonfun$fromInputStream$1.apply:()Lscala/io/Source;
const #33 = Asciz	scala/io/Source$;
const #34 = class	#33;	//  scala/io/Source$
const #35 = Asciz	MODULE$;
const #36 = Asciz	Lscala/io/Source$;;
const #37 = NameAndType	#35:#36;//  MODULE$:Lscala/io/Source$;
const #38 = Field	#34.#37;	//  scala/io/Source$.MODULE$:Lscala/io/Source$;
const #39 = Asciz	fromInputStream;
const #40 = Asciz	(Ljava/io/InputStream;Lscala/io/Codec;)Lscala/io/Source;;
const #41 = NameAndType	#39:#40;//  fromInputStream:(Ljava/io/InputStream;Lscala/io/Codec;)Lscala/io/Source;
const #42 = Method	#34.#41;	//  scala/io/Source$.fromInputStream:(Ljava/io/InputStream;Lscala/io/Codec;)Lscala/io/Source;
const #43 = Asciz	toString;
const #44 = Asciz	()Ljava/lang/String;;
const #45 = Asciz	(Lscala/Function0;)Ljava/lang/String;;
const #46 = NameAndType	#43:#45;//  toString:(Lscala/Function0;)Ljava/lang/String;
const #47 = Method	#23.#46;	//  scala/Function0$class.toString:(Lscala/Function0;)Ljava/lang/String;
const #48 = Asciz	Scala;
const #49 = Asciz	InnerClasses;
const #50 = Asciz	scala/io/Source;
const #51 = class	#50;	//  scala/io/Source
const #52 = Asciz	$anonfun$fromInputStream$1;
const #53 = Asciz	scala/Function0;
const #54 = class	#53;	//  scala/Function0
const #55 = Asciz	scala/ScalaObject;
const #56 = class	#55;	//  scala/ScalaObject
const #57 = Asciz	java/io/Serializable;
const #58 = class	#57;	//  java/io/Serializable

{
public scala.io.Source$$anonfun$fromInputStream$1(java.io.InputStream, scala.io.Codec);
  Code:
   Stack=2, Locals=3, Args_size=3
   0:	aload_0
   1:	aload_1
   2:	putfield	#14; //Field inputStream$1:Ljava/io/InputStream;
   5:	aload_0
   6:	aload_2
   7:	putfield	#16; //Field codec$2:Lscala/io/Codec;
   10:	aload_0
   11:	invokespecial	#21; //Method java/lang/Object."<init>":()V
   14:	aload_0
   15:	invokestatic	#27; //Method scala/Function0$class.$init$:(Lscala/Function0;)V
   18:	return
  LineNumberTable: 
   line 100: 0


public final java.lang.Object apply();
  Code:
   Stack=1, Locals=1, Args_size=1
   0:	aload_0
   1:	invokevirtual	#32; //Method apply:()Lscala/io/Source;
   4:	areturn
  LineNumberTable: 
   line 100: 0


public final scala.io.Source apply();
  Code:
   Stack=3, Locals=1, Args_size=1
   0:	getstatic	#38; //Field scala/io/Source$.MODULE$:Lscala/io/Source$;
   3:	aload_0
   4:	getfield	#14; //Field inputStream$1:Ljava/io/InputStream;
   7:	aload_0
   8:	getfield	#16; //Field codec$2:Lscala/io/Codec;
   11:	invokevirtual	#42; //Method scala/io/Source$.fromInputStream:(Ljava/io/InputStream;Lscala/io/Codec;)Lscala/io/Source;
   14:	areturn
  LineNumberTable: 
   line 100: 0


public java.lang.String toString();
  Code:
   Stack=1, Locals=1, Args_size=1
   0:	aload_0
   1:	invokestatic	#47; //Method scala/Function0$class.toString:(Lscala/Function0;)Ljava/lang/String;
   4:	areturn
  LineNumberTable: 
   line 100: 0


}

