Compiled from "Source.scala"
public abstract class scala.io.Source extends java.lang.Object implements scala.collection.Iterator,scala.ScalaObject
  SourceFile: "Source.scala"
  Signature: length = 0x2
   02 FFFFFF84 
  ScalaSig: length = 0xE5C
   05 00 FFFFFF83 3A 07 05 01 02 FFFFFF88 02 07 01 06 53 6F 75
   72 63 65 0A 02 03 04 01 02 69 6F 0A 01 05 01 05
   73 63 61 6C 61 03 00 10 02 08 09 0D 01 02 06 08
   0A 02 FFFFFF84 FFFFFF80 FFFFFF80 FFFFFF88 02 0B 02 06 53 6F 75 72 63 65
   13 03 09 0C 14 10 02 0D 12 0D 01 0E 0A 02 0F 10
   01 04 6C 61 6E 67 0A 01 11 01 04 6A 61 76 61 09
   02 13 0E 02 06 4F 62 6A 65 63 74 10 02 15 16 0D
   01 04 09 02 17 04 02 0B 53 63 61 6C 61 4F 62 6A
   65 63 74 08 05 19 09 FFFFFF84 00 1A 01 06 3C 69 6E 69
   74 3E 14 01 07 08 07 1C 09 FFFFFFC2 FFFFFF80 FFFFFF84 00 1D 01 0E
   44 65 66 61 75 6C 74 42 75 66 53 69 7A 65 15 01
   1E 10 02 15 1F 09 02 20 04 02 03 49 6E 74 08 06
   22 09 FFFFFFA0 FFFFFF80 04 1E 01 0F 44 65 66 61 75 6C 74 42
   75 66 53 69 7A 65 20 08 05 24 09 FFFFFF84 00 25 01 05
   73 74 64 69 6E 15 01 26 10 02 08 27 06 08 0A 02
   FFFFFF84 FFFFFF80 FFFFFF80 FFFFFF81 00 28 13 04 27 0C 29 14 10 03 2A 32
   35 0E 02 2B 30 0E 02 2C 2F 0D 01 2D 0A 02 2E 06
   01 06 3C 72 6F 6F 74 3E 09 01 05 09 02 31 04 01
   07 70 61 63 6B 61 67 65 09 02 33 34 02 08 49 74
   65 72 61 74 6F 72 0A 02 31 04 10 02 15 36 09 02
   37 04 02 04 43 68 61 72 08 05 19 27 FFFFFF84 00 39 14
   01 26 08 07 3B 27 FFFFFFC2 FFFFFF80 FFFFFF86 08 3C 01 04 69 74 65
   72 15 01 29 08 07 3E 27 FFFFFFC0 FFFFFF80 FFFFFF84 00 3F 01 05 64
   65 73 63 72 15 01 40 10 02 41 44 0E 02 15 42 09
   02 43 04 01 06 50 72 65 64 65 66 09 02 45 46 02
   06 53 74 72 69 6E 67 0A 02 43 04 08 07 48 27 FFFFFFC0
   FFFFFF80 FFFFFF84 00 49 01 09 64 65 73 63 72 5F 24 65 71 14
   02 4A 4D 10 02 15 4B 09 02 4C 04 02 04 55 6E 69
   74 08 07 4E 47 FFFFFF81 FFFFFF80 FFFFFFC0 00 40 01 03 78 24 31 08
   06 50 27 FFFFFFA0 FFFFFFA0 04 40 01 06 64 65 73 63 72 20 08
   07 52 27 FFFFFFC0 FFFFFF80 FFFFFF84 00 1D 01 07 6E 65 72 72 6F 72
   73 08 07 54 27 FFFFFFC0 FFFFFF80 FFFFFF84 00 55 01 0B 6E 65 72 72
   6F 72 73 5F 24 65 71 14 02 4A 56 08 07 4E 53 FFFFFF81
   FFFFFF80 FFFFFFC0 00 1E 08 06 58 27 FFFFFFA0 FFFFFFA0 04 1E 01 08 6E 65
   72 72 6F 72 73 20 08 07 5A 27 FFFFFFC0 FFFFFF80 FFFFFF84 00 1D 01
   09 6E 77 61 72 6E 69 6E 67 73 08 07 5C 27 FFFFFFC0 FFFFFF80
   FFFFFF84 00 5D 01 0D 6E 77 61 72 6E 69 6E 67 73 5F 24
   65 71 14 02 4A 5E 08 07 4E 5B FFFFFF81 FFFFFF80 FFFFFFC0 00 1E 08
   06 60 27 FFFFFFA0 FFFFFFA0 04 1E 01 0A 6E 77 61 72 6E 69 6E
   67 73 20 08 05 62 27 FFFFFF84 00 63 01 07 67 65 74 4C
   69 6E 65 14 02 40 64 08 05 65 61 FFFFFFC0 00 1E 01 04
   6C 69 6E 65 06 08 67 27 FFFFFF84 FFFFFF80 FFFFFF80 FFFFFF80 00 68 02 0C
   4C 69 6E 65 49 74 65 72 61 74 6F 72 13 04 66 0C
   69 14 10 03 2A 32 40 08 08 6B 66 FFFFFF82 FFFFFF80 FFFFFFA0 FFFFFF80 04
   40 01 09 73 65 70 61 72 61 74 6F 72 08 05 19 66
   FFFFFF84 00 6D 14 02 6E 70 10 02 6F 66 0D 01 27 08 05
   6B 6C FFFFFFC0 00 40 08 08 3B 66 FFFFFF88 FFFFFFC2 FFFFFF80 FFFFFF84 00 72 15
   01 73 10 03 2A 74 35 09 02 75 34 02 10 42 75 66
   66 65 72 65 64 49 74 65 72 61 74 6F 72 08 08 77
   66 FFFFFF88 FFFFFF80 FFFFFFA0 FFFFFFA0 04 73 01 05 69 74 65 72 20 08 07
   79 66 FFFFFFC2 FFFFFF80 FFFFFF84 00 7A 01 09 69 73 4E 65 77 6C 69
   6E 65 15 01 7B 10 04 15 7C 35 7E 09 02 7D 04 02
   09 46 75 6E 63 74 69 6F 6E 31 10 02 15 7F 09 03
   FFFFFF81 00 04 02 07 42 6F 6F 6C 65 61 6E 08 07 FFFFFF81 02
   66 FFFFFFA0 FFFFFF80 04 7B 01 0A 69 73 4E 65 77 6C 69 6E 65
   20 08 08 FFFFFF81 04 66 FFFFFFA0 FFFFFF80 04 FFFFFF81 05 01 02 73 62 10
   04 FFFFFF81 06 FFFFFF81 0B 0D 02 FFFFFF81 07 0A 04 FFFFFF81 08 FFFFFF81 09 01
   07 6D 75 74 61 62 6C 65 0A 03 FFFFFF81 0A 04 01 0A 63
   6F 6C 6C 65 63 74 69 6F 6E 09 04 FFFFFF81 0C FFFFFF81 07 02
   0D 53 74 72 69 6E 67 42 75 69 6C 64 65 72 08 07
   FFFFFF81 0E 66 FFFFFF84 04 FFFFFF81 0F 01 04 67 65 74 63 14 01 7E
   08 07 FFFFFF81 11 66 FFFFFF84 00 FFFFFF81 12 01 07 68 61 73 4E 65
   78 74 15 01 7E 08 07 FFFFFF81 14 66 FFFFFF84 00 FFFFFF81 15 01 04
   6E 65 78 74 14 01 40 08 07 FFFFFF81 17 27 FFFFFF84 00 FFFFFF81 18
   01 08 67 65 74 4C 69 6E 65 73 14 03 69 FFFFFF81 19 08
   0A FFFFFF81 1A 6B FFFFFF81 16 FFFFFF90 FFFFFF80 FFFFFFC0 00 40 08 09 FFFFFF81 1B 27
   FFFFFF91 FFFFFF80 FFFFFF84 00 FFFFFF81 1C 01 12 67 65 74 4C 69 6E 65 73
   24 64 65 66 61 75 6C 74 24 31 15 02 FFFFFF81 1D 2A 03
   40 FFFFFF81 1E 2B 02 FFFFFF81 1F 10 04 FFFFFF81 20 FFFFFF81 25 0D 02 FFFFFF81
   21 0A 04 FFFFFF81 22 FFFFFF81 23 01 09 75 6E 63 68 65 63 6B
   65 64 0A 03 FFFFFF81 24 04 01 0A 61 6E 6E 6F 74 61 74
   69 6F 6E 09 04 FFFFFF81 26 FFFFFF81 21 02 11 75 6E 63 68 65
   63 6B 65 64 56 61 72 69 61 6E 63 65 08 07 FFFFFF81 11
   27 FFFFFF84 00 FFFFFF81 12 08 07 FFFFFF81 14 27 FFFFFF84 00 FFFFFF81 29 14 01
   35 06 0A FFFFFF81 2B 27 FFFFFF84 FFFFFF80 FFFFFF80 FFFFFF80 00 FFFFFF81 2C 02 0A 50
   6F 73 69 74 69 6F 6E 65 72 13 04 FFFFFF81 2A 0C 14 08
   07 19 FFFFFF81 2A FFFFFF84 00 FFFFFF81 2E 14 02 FFFFFF81 2F 10 03 6F FFFFFF81
   2A 08 0A FFFFFF81 31 FFFFFF81 2A FFFFFFC0 FFFFFF80 FFFFFF84 00 FFFFFF81 32 01 02 63
   68 15 01 35 08 0A FFFFFF81 34 FFFFFF81 2A FFFFFFC0 FFFFFF80 FFFFFF84 00 FFFFFF81 35
   01 06 63 68 5F 24 65 71 14 03 4A FFFFFF81 36 08 08 4E
   FFFFFF81 33 FFFFFF81 FFFFFF80 FFFFFFC0 00 35 08 08 FFFFFF81 38 FFFFFF81 2A FFFFFFA0 FFFFFFA0 04
   35 01 03 63 68 20 08 09 FFFFFF81 3A FFFFFF81 2A FFFFFFC0 FFFFFF80 FFFFFF84 00
   1D 01 03 70 6F 73 08 0A FFFFFF81 3C FFFFFF81 2A FFFFFFC0 FFFFFF80 FFFFFF84 00
   FFFFFF81 3D 01 07 70 6F 73 5F 24 65 71 14 03 4A FFFFFF81 3E
   08 08 4E FFFFFF81 3B FFFFFF81 FFFFFF80 FFFFFFC0 00 1E 08 08 FFFFFF81 40 FFFFFF81 2A
   FFFFFFA0 FFFFFFA0 04 1E 01 04 70 6F 73 20 08 09 FFFFFF81 42 FFFFFF81 2A
   FFFFFFC0 FFFFFF80 FFFFFF84 00 1D 01 05 63 6C 69 6E 65 08 0A FFFFFF81 44
   FFFFFF81 2A FFFFFFC0 FFFFFF80 FFFFFF84 00 FFFFFF81 45 01 09 63 6C 69 6E 65 5F
   24 65 71 14 03 4A FFFFFF81 46 08 08 4E FFFFFF81 43 FFFFFF81 FFFFFF80 FFFFFFC0
   00 1E 08 08 FFFFFF81 48 FFFFFF81 2A FFFFFFA0 FFFFFFA0 04 1E 01 06 63 6C
   69 6E 65 20 08 09 FFFFFF81 4A FFFFFF81 2A FFFFFFC0 FFFFFF80 FFFFFF84 00 1D 01
   04 63 63 6F 6C 08 0A FFFFFF81 4C FFFFFF81 2A FFFFFFC0 FFFFFF80 FFFFFF84 00 FFFFFF81
   4D 01 08 63 63 6F 6C 5F 24 65 71 14 03 4A FFFFFF81 4E
   08 08 4E FFFFFF81 4B FFFFFF81 FFFFFF80 FFFFFFC0 00 1E 08 08 FFFFFF81 50 FFFFFF81 2A
   FFFFFFA0 FFFFFFA0 04 1E 01 05 63 63 6F 6C 20 08 09 FFFFFF81 52 FFFFFF81
   2A FFFFFFC0 FFFFFF80 FFFFFF84 00 1D 01 06 74 61 62 69 6E 63 08 0A
   FFFFFF81 54 FFFFFF81 2A FFFFFFC0 FFFFFF80 FFFFFF84 00 FFFFFF81 55 01 0A 74 61 62 69
   6E 63 5F 24 65 71 14 03 4A FFFFFF81 56 08 08 4E FFFFFF81 53
   FFFFFF81 FFFFFF80 FFFFFFC0 00 1E 08 08 FFFFFF81 58 FFFFFF81 2A FFFFFFA0 FFFFFFA0 04 1E 01
   07 74 61 62 69 6E 63 20 08 08 FFFFFF81 14 FFFFFF81 2A FFFFFF84 00
   FFFFFF81 32 07 07 FFFFFF81 5B 27 FFFFFF88 02 FFFFFF81 5C 01 0C 4E 6F 50
   6F 73 69 74 69 6F 6E 65 72 10 03 6F FFFFFF81 5D 06 0A
   FFFFFF81 5E 27 FFFFFF84 FFFFFF80 FFFFFF80 FFFFFF88 02 FFFFFF81 5F 02 0C 4E 6F 50 6F
   73 69 74 69 6F 6E 65 72 13 05 FFFFFF81 5D FFFFFF81 2F 14 08
   07 19 FFFFFF81 5D FFFFFF84 00 FFFFFF81 61 14 02 FFFFFF81 5C 08 08 FFFFFF81 14
   FFFFFF81 5D FFFFFF84 20 FFFFFF81 32 08 07 FFFFFF81 31 27 FFFFFF84 00 FFFFFF81 32 08
   06 FFFFFF81 3A 27 FFFFFF84 00 1D 08 07 FFFFFF81 66 27 FFFFFF84 00 FFFFFF81 67
   01 0B 72 65 70 6F 72 74 45 72 72 6F 72 14 07 4A
   FFFFFF81 68 FFFFFF81 69 FFFFFF81 6B 08 07 FFFFFF81 3A FFFFFF81 65 FFFFFFC0 00 1E 08
   07 FFFFFF81 6A FFFFFF81 65 FFFFFFC0 00 40 01 03 6D 73 67 08 0C FFFFFF81
   72 FFFFFF81 6C FFFFFF81 65 FFFFFF90 FFFFFF80 FFFFFFC0 00 FFFFFF81 6D 01 03 6F 75 74
   10 04 FFFFFF81 6E FFFFFF81 70 0D 02 FFFFFF81 6F 0A 02 03 10 09 04
   FFFFFF81 71 FFFFFF81 6F 02 0B 50 72 69 6E 74 53 74 72 65 61
   6D 08 09 FFFFFF81 73 27 FFFFFF91 FFFFFF80 FFFFFF84 00 FFFFFF81 74 01 15 72 65
   70 6F 72 74 45 72 72 6F 72 24 64 65 66 61 75 6C
   74 24 33 15 02 FFFFFF81 75 2A 04 FFFFFF81 6D FFFFFF81 1E 08 07 FFFFFF81
   77 27 FFFFFF84 04 FFFFFF81 78 01 06 73 70 61 63 65 73 14 03
   40 FFFFFF81 79 08 07 FFFFFF81 7A FFFFFF81 76 FFFFFFC0 00 1E 01 01 6E 08
   07 FFFFFF81 7C 27 FFFFFF84 00 FFFFFF81 7D 01 06 72 65 70 6F 72 74
   14 07 4A FFFFFF81 7E FFFFFF81 7F FFFFFF82 00 08 07 FFFFFF81 3A FFFFFF81 7B FFFFFFC0
   00 1E 08 07 FFFFFF81 6A FFFFFF81 7B FFFFFFC0 00 40 08 08 FFFFFF81 6C FFFFFF81
   7B FFFFFFC0 00 FFFFFF81 6D 08 07 FFFFFF82 02 27 FFFFFF84 00 FFFFFF82 03 01 0D
   72 65 70 6F 72 74 57 61 72 6E 69 6E 67 14 07 4A
   FFFFFF82 04 FFFFFF82 05 FFFFFF82 06 08 07 FFFFFF81 3A FFFFFF82 01 FFFFFFC0 00 1E 08
   07 FFFFFF81 6A FFFFFF82 01 FFFFFFC0 00 40 08 0C FFFFFF82 07 FFFFFF81 6C FFFFFF82 01
   FFFFFF90 FFFFFF80 FFFFFFC0 00 FFFFFF81 6D 08 09 FFFFFF82 08 27 FFFFFF91 FFFFFF80 FFFFFF84 00 FFFFFF81
   74 01 17 72 65 70 6F 72 74 57 61 72 6E 69 6E 67
   24 64 65 66 61 75 6C 74 24 33 08 08 FFFFFF82 0A 27 FFFFFFA0
   FFFFFFA0 04 FFFFFF82 0B 01 0D 72 65 73 65 74 46 75 6E 63 74
   69 6F 6E 10 04 15 FFFFFF82 0C 26 09 03 FFFFFF82 0D 04 02 09
   46 75 6E 63 74 69 6F 6E 30 08 08 FFFFFF82 0F 27 FFFFFFA0 FFFFFFA0
   04 FFFFFF82 10 01 0D 63 6C 6F 73 65 46 75 6E 63 74 69
   6F 6E 10 04 15 FFFFFF82 0C 4A 08 08 FFFFFF82 12 27 FFFFFFA0 FFFFFFA0 04
   FFFFFF81 2F 01 0A 70 6F 73 69 74 69 6F 6E 65 72 08 07
   FFFFFF82 14 27 FFFFFF84 00 FFFFFF82 15 01 09 77 69 74 68 52 65 73
   65 74 14 03 6F FFFFFF82 16 08 08 FFFFFF82 17 FFFFFF82 13 FFFFFFC0 00 FFFFFF82
   0B 01 01 66 08 07 FFFFFF82 19 27 FFFFFF84 00 FFFFFF82 1A 01 09 77
   69 74 68 43 6C 6F 73 65 14 03 6F FFFFFF82 1B 08 08 FFFFFF82
   17 FFFFFF82 18 FFFFFFC0 00 FFFFFF82 10 08 07 FFFFFF82 1D 27 FFFFFF84 00 FFFFFF82 1E
   01 0F 77 69 74 68 44 65 73 63 72 69 70 74 69 6F
   6E 14 03 6F FFFFFF82 1F 08 07 FFFFFF82 20 FFFFFF82 1C FFFFFFC0 00 40 01
   04 74 65 78 74 08 07 FFFFFF82 22 27 FFFFFF84 00 FFFFFF82 23 01 0F
   77 69 74 68 50 6F 73 69 74 69 6F 6E 69 6E 67 14
   03 6F FFFFFF82 24 08 07 FFFFFF82 25 FFFFFF82 21 FFFFFFC0 00 7E 01 02 6F
   6E 08 07 FFFFFF82 27 27 FFFFFF84 00 FFFFFF82 28 01 05 63 6C 6F 73
   65 15 01 4A 08 06 FFFFFF82 2A 27 FFFFFF84 00 39 01 05 72 65
   73 65 74 08 07 FFFFFF82 2C 09 FFFFFF84 00 FFFFFF82 2D 01 0C 66 72
   6F 6D 49 74 65 72 61 62 6C 65 14 03 26 FFFFFF82 2E 08
   08 FFFFFF82 2F FFFFFF82 2B FFFFFFC0 00 FFFFFF82 30 01 08 69 74 65 72 61
   62 6C 65 10 04 2A FFFFFF82 31 35 09 03 FFFFFF82 32 34 02 08
   49 74 65 72 61 62 6C 65 08 07 FFFFFF82 34 09 FFFFFF84 00 FFFFFF82
   35 01 08 66 72 6F 6D 43 68 61 72 14 03 26 FFFFFF82 36
   08 07 FFFFFF82 37 FFFFFF82 33 FFFFFFC0 00 35 01 01 63 08 07 FFFFFF82 39
   09 FFFFFF84 00 FFFFFF82 3A 01 09 66 72 6F 6D 43 68 61 72 73
   14 03 26 FFFFFF82 3B 08 08 FFFFFF82 3C FFFFFF82 38 FFFFFFC0 00 FFFFFF82 3D 01
   05 63 68 61 72 73 10 04 15 FFFFFF82 3E 35 09 03 FFFFFF82 3F
   04 02 05 41 72 72 61 79 08 07 FFFFFF82 41 09 FFFFFF84 00 FFFFFF82
   42 01 0A 66 72 6F 6D 53 74 72 69 6E 67 14 03 26
   FFFFFF82 43 08 07 FFFFFF82 44 FFFFFF82 40 FFFFFFC0 00 40 01 01 73 08 07
   FFFFFF82 46 09 FFFFFF84 00 FFFFFF82 47 01 09 66 72 6F 6D 42 79 74
   65 73 14 04 FFFFFF82 48 FFFFFF82 58 16 03 26 FFFFFF82 49 08 0C FFFFFF82
   4E FFFFFF82 4A FFFFFF82 45 FFFFFF90 FFFFFF80 FFFFFFC0 01 FFFFFF82 4B 01 05 63 6F 64
   65 63 10 03 08 FFFFFF82 4C 09 03 FFFFFF82 4D 02 02 05 43 6F
   64 65 63 08 09 FFFFFF82 4F 09 FFFFFF91 FFFFFF80 FFFFFF84 00 FFFFFF82 50 01 13
   66 72 6F 6D 42 79 74 65 73 24 64 65 66 61 75 6C
   74 24 32 14 04 FFFFFF82 51 FFFFFF82 52 2A 04 FFFFFF82 4B FFFFFF81 1E 08
   08 FFFFFF82 53 FFFFFF82 4E FFFFFFC0 00 FFFFFF82 54 01 05 62 79 74 65 73
   10 05 15 FFFFFF82 3E FFFFFF82 55 10 03 15 FFFFFF82 56 09 03 FFFFFF82 57
   04 02 04 42 79 74 65 08 08 FFFFFF82 53 FFFFFF82 45 FFFFFFC0 00 FFFFFF82
   54 08 07 FFFFFF82 5A 09 FFFFFF84 00 FFFFFF82 5B 01 0C 66 72 6F 6D
   52 61 77 42 79 74 65 73 14 03 26 FFFFFF82 5C 08 08 FFFFFF82
   53 FFFFFF82 59 FFFFFFC0 00 FFFFFF82 54 08 07 FFFFFF82 5E 09 FFFFFF84 00 FFFFFF82 5F
   01 08 66 72 6F 6D 50 61 74 68 14 04 FFFFFF82 60 FFFFFF82 67
   16 03 26 FFFFFF82 61 08 0C FFFFFF82 62 FFFFFF82 4A FFFFFF82 5D FFFFFF90 FFFFFF80 FFFFFFC0
   01 FFFFFF82 4B 08 09 FFFFFF82 63 09 FFFFFF91 FFFFFF80 FFFFFF84 00 FFFFFF82 64 01 12
   66 72 6F 6D 50 61 74 68 24 64 65 66 61 75 6C 74
   24 32 14 04 FFFFFF82 51 FFFFFF82 65 08 07 FFFFFF82 66 FFFFFF82 62 FFFFFFC0 00
   40 01 04 6E 61 6D 65 08 07 FFFFFF82 66 FFFFFF82 5D FFFFFFC0 00 40
   08 07 FFFFFF82 69 09 FFFFFF84 00 FFFFFF82 6A 01 07 66 72 6F 6D 55
   52 49 14 04 FFFFFF82 6B FFFFFF82 78 16 03 26 FFFFFF82 6C 08 0C FFFFFF82
   6D FFFFFF82 4A FFFFFF82 68 FFFFFF90 FFFFFF80 FFFFFFC0 01 FFFFFF82 4B 08 09 FFFFFF82 6E 09
   FFFFFF91 FFFFFF80 FFFFFF84 00 FFFFFF82 6F 01 11 66 72 6F 6D 55 52 49 24
   64 65 66 61 75 6C 74 24 32 14 04 FFFFFF82 51 FFFFFF82 70 08
   08 FFFFFF82 71 FFFFFF82 6D FFFFFFC0 00 FFFFFF82 72 01 03 75 72 69 10 04
   FFFFFF82 73 FFFFFF82 76 0D 02 FFFFFF82 74 0A 03 FFFFFF82 75 10 01 03 6E
   65 74 09 04 FFFFFF82 77 FFFFFF82 74 02 03 55 52 49 08 08 FFFFFF82
   71 FFFFFF82 68 FFFFFFC0 00 FFFFFF82 72 08 07 FFFFFF82 7A 09 FFFFFF84 00 FFFFFF82 7B
   01 07 66 72 6F 6D 55 52 4C 14 04 FFFFFF82 7C FFFFFF83 06 16
   03 26 FFFFFF82 7D 08 0C FFFFFF82 7E FFFFFF82 4A FFFFFF82 79 FFFFFF90 FFFFFF80 FFFFFFC0 01
   FFFFFF82 4B 08 09 FFFFFF82 7F 09 FFFFFF91 FFFFFF80 FFFFFF84 00 FFFFFF83 00 01 11 66
   72 6F 6D 55 52 4C 24 64 65 66 61 75 6C 74 24 32
   14 04 FFFFFF82 51 FFFFFF83 01 08 08 FFFFFF83 02 FFFFFF82 7E FFFFFFC0 00 FFFFFF83 03
   01 03 75 72 6C 10 04 FFFFFF82 73 FFFFFF83 04 09 04 FFFFFF83 05 FFFFFF82
   74 02 03 55 52 4C 08 08 FFFFFF83 02 FFFFFF82 79 FFFFFFC0 00 FFFFFF83 03
   08 07 FFFFFF83 08 09 FFFFFF84 00 FFFFFF83 09 01 08 66 72 6F 6D 46
   69 6C 65 14 06 FFFFFF83 0A FFFFFF83 16 FFFFFF83 17 16 03 26 FFFFFF83 0B
   08 0C FFFFFF83 0C FFFFFF82 4A FFFFFF83 07 FFFFFF90 FFFFFF80 FFFFFFC0 01 FFFFFF82 4B 08 09
   FFFFFF83 0D 09 FFFFFF91 FFFFFF80 FFFFFF84 00 FFFFFF83 0E 01 12 66 72 6F 6D 46
   69 6C 65 24 64 65 66 61 75 6C 74 24 33 14 06 FFFFFF82
   51 FFFFFF83 0F FFFFFF83 14 08 08 FFFFFF83 10 FFFFFF83 0C FFFFFFC0 00 FFFFFF83 11 01
   04 66 69 6C 65 10 04 FFFFFF81 6E FFFFFF83 12 09 04 FFFFFF83 13 FFFFFF81
   6F 02 04 46 69 6C 65 08 07 FFFFFF83 15 FFFFFF83 0C FFFFFFC0 00 1E
   01 0A 62 75 66 66 65 72 53 69 7A 65 08 08 FFFFFF83 10
   FFFFFF83 07 FFFFFFC0 00 FFFFFF83 11 08 0B FFFFFF83 18 FFFFFF83 15 FFFFFF83 07 FFFFFF90 FFFFFF80
   FFFFFFC0 00 1E 08 09 FFFFFF83 19 09 FFFFFF91 FFFFFF80 FFFFFF84 00 FFFFFF83 1A 01 12
   66 72 6F 6D 46 69 6C 65 24 64 65 66 61 75 6C 74
   24 32 15 02 FFFFFF83 1B 2A 03 1E FFFFFF81 1E 08 07 FFFFFF83 1D 09
   FFFFFF84 00 FFFFFF83 1E 01 0F 66 72 6F 6D 49 6E 70 75 74 53
   74 72 65 61 6D 14 0A FFFFFF83 1F FFFFFF83 2C FFFFFF83 2D FFFFFF83 30 FFFFFF83
   35 16 03 26 FFFFFF83 20 08 0C FFFFFF83 21 FFFFFF82 4A FFFFFF83 1C FFFFFF90 FFFFFF80
   FFFFFFC0 01 FFFFFF82 4B 08 09 FFFFFF83 22 09 FFFFFF91 FFFFFF80 FFFFFF84 00 FFFFFF83 23 01
   19 66 72 6F 6D 49 6E 70 75 74 53 74 72 65 61 6D
   24 64 65 66 61 75 6C 74 24 35 14 0A FFFFFF82 51 FFFFFF83 24
   FFFFFF83 29 FFFFFF83 2A FFFFFF83 2B 08 08 FFFFFF83 25 FFFFFF83 21 FFFFFFC0 00 FFFFFF83 26
   01 0B 69 6E 70 75 74 53 74 72 65 61 6D 10 04 FFFFFF81
   6E FFFFFF83 27 09 04 FFFFFF83 28 FFFFFF81 6F 02 0B 49 6E 70 75 74
   53 74 72 65 61 6D 08 07 FFFFFF83 15 FFFFFF83 21 FFFFFFC0 00 1E 08
   08 FFFFFF82 2A FFFFFF83 21 FFFFFFC0 00 FFFFFF82 0B 08 08 FFFFFF82 27 FFFFFF83 21 FFFFFFC0
   00 FFFFFF82 10 08 08 FFFFFF83 25 FFFFFF83 1C FFFFFFC0 00 FFFFFF83 26 08 0B FFFFFF83
   2E FFFFFF83 15 FFFFFF83 1C FFFFFF90 FFFFFF80 FFFFFFC0 00 1E 08 09 FFFFFF83 2F 09 FFFFFF91
   FFFFFF80 FFFFFF84 00 FFFFFF83 1A 01 19 66 72 6F 6D 49 6E 70 75 74
   53 74 72 65 61 6D 24 64 65 66 61 75 6C 74 24 32
   08 0C FFFFFF83 31 FFFFFF82 2A FFFFFF83 1C FFFFFF90 FFFFFF80 FFFFFFC0 00 FFFFFF82 0B 08 09
   FFFFFF83 32 09 FFFFFF91 FFFFFF80 FFFFFF84 00 FFFFFF83 33 01 19 66 72 6F 6D 49
   6E 70 75 74 53 74 72 65 61 6D 24 64 65 66 61 75
   6C 74 24 33 15 02 FFFFFF83 34 2A 04 FFFFFF82 0B FFFFFF81 1E 08 0C
   FFFFFF83 36 FFFFFF82 27 FFFFFF83 1C FFFFFF90 FFFFFF80 FFFFFFC0 00 FFFFFF82 10 08 09 FFFFFF83 37
   09 FFFFFF91 FFFFFF80 FFFFFF84 00 FFFFFF83 38 01 19 66 72 6F 6D 49 6E 70
   75 74 53 74 72 65 61 6D 24 64 65 66 61 75 6C 74
   24 34 15 02 FFFFFF83 39 2A 04 FFFFFF82 10 FFFFFF81 1E 
  InnerClass: 
   public final #649= #648 of #132; //$anon$1=class scala/io/Source$$anon$1 of class scala/io/Source
   public final #652= #651 of #132; //$anonfun$1=class scala/io/Source$$anonfun$1 of class scala/io/Source
   public #653= #144 of #132; //Positioner=class scala/io/Source$Positioner of class scala/io/Source
   public #654= #330 of #132; //LineIterator=class scala/io/Source$LineIterator of class scala/io/Source
   public #657= #656 of #324; //GroupedIterator=class scala/collection/Iterator$GroupedIterator of class scala/collection/Iterator
   public final #658= #288 of #132; //$anonfun$spaces$1=class scala/io/Source$$anonfun$spaces$1 of class scala/io/Source
   public final #661= #660 of #132; //$anonfun$fromFile$2=class scala/io/Source$$anonfun$fromFile$2 of class scala/io/Source
   public final #664= #663 of #132; //$anonfun$fromFile$1=class scala/io/Source$$anonfun$fromFile$1 of class scala/io/Source
   public final #667= #666 of #132; //$anonfun$fromIterable$1=class scala/io/Source$$anonfun$fromIterable$1 of class scala/io/Source
  minor version: 0
  major version: 49
  Constant pool:
const #1 = Asciz	SourceFile;
const #2 = Asciz	Source.scala;
const #3 = Asciz	fromURL$default$2;
const #4 = Asciz	(Ljava/net/URL;)Lscala/io/Codec;;
const #5 = Asciz	Code;
const #6 = Asciz	scala/io/Source$;
const #7 = class	#6;	//  scala/io/Source$
const #8 = Asciz	MODULE$;
const #9 = Asciz	Lscala/io/Source$;;
const #10 = NameAndType	#8:#9;//  MODULE$:Lscala/io/Source$;
const #11 = Field	#7.#10;	//  scala/io/Source$.MODULE$:Lscala/io/Source$;
const #12 = NameAndType	#3:#4;//  fromURL$default$2:(Ljava/net/URL;)Lscala/io/Codec;
const #13 = Method	#7.#12;	//  scala/io/Source$.fromURL$default$2:(Ljava/net/URL;)Lscala/io/Codec;
const #14 = Asciz	fromURI$default$2;
const #15 = Asciz	(Ljava/net/URI;)Lscala/io/Codec;;
const #16 = NameAndType	#14:#15;//  fromURI$default$2:(Ljava/net/URI;)Lscala/io/Codec;
const #17 = Method	#7.#16;	//  scala/io/Source$.fromURI$default$2:(Ljava/net/URI;)Lscala/io/Codec;
const #18 = Asciz	fromFile$default$3;
const #19 = Asciz	(Ljava/io/File;I)Lscala/io/Codec;;
const #20 = NameAndType	#18:#19;//  fromFile$default$3:(Ljava/io/File;I)Lscala/io/Codec;
const #21 = Method	#7.#20;	//  scala/io/Source$.fromFile$default$3:(Ljava/io/File;I)Lscala/io/Codec;
const #22 = Asciz	fromFile$default$2;
const #23 = Asciz	()I;
const #24 = NameAndType	#22:#23;//  fromFile$default$2:()I
const #25 = Method	#7.#24;	//  scala/io/Source$.fromFile$default$2:()I
const #26 = Asciz	fromPath$default$2;
const #27 = Asciz	(Ljava/lang/String;)Lscala/io/Codec;;
const #28 = NameAndType	#26:#27;//  fromPath$default$2:(Ljava/lang/String;)Lscala/io/Codec;
const #29 = Method	#7.#28;	//  scala/io/Source$.fromPath$default$2:(Ljava/lang/String;)Lscala/io/Codec;
const #30 = Asciz	fromBytes$default$2;
const #31 = Asciz	([B)Lscala/io/Codec;;
const #32 = NameAndType	#30:#31;//  fromBytes$default$2:([B)Lscala/io/Codec;
const #33 = Method	#7.#32;	//  scala/io/Source$.fromBytes$default$2:([B)Lscala/io/Codec;
const #34 = Asciz	fromInputStream$default$5;
const #35 = Asciz	(Ljava/io/InputStream;ILscala/Function0;Lscala/Function0;)Lscala/io/Codec;;
const #36 = NameAndType	#34:#35;//  fromInputStream$default$5:(Ljava/io/InputStream;ILscala/Function0;Lscala/Function0;)Lscala/io/Codec;
const #37 = Method	#7.#36;	//  scala/io/Source$.fromInputStream$default$5:(Ljava/io/InputStream;ILscala/Function0;Lscala/Function0;)Lscala/io/Codec;
const #38 = Asciz	fromInputStream$default$4;
const #39 = Asciz	()Lscala/Function0;;
const #40 = NameAndType	#38:#39;//  fromInputStream$default$4:()Lscala/Function0;
const #41 = Method	#7.#40;	//  scala/io/Source$.fromInputStream$default$4:()Lscala/Function0;
const #42 = Asciz	fromInputStream$default$3;
const #43 = NameAndType	#42:#39;//  fromInputStream$default$3:()Lscala/Function0;
const #44 = Method	#7.#43;	//  scala/io/Source$.fromInputStream$default$3:()Lscala/Function0;
const #45 = Asciz	fromInputStream$default$2;
const #46 = NameAndType	#45:#23;//  fromInputStream$default$2:()I
const #47 = Method	#7.#46;	//  scala/io/Source$.fromInputStream$default$2:()I
const #48 = Asciz	fromInputStream;
const #49 = Asciz	(Ljava/io/InputStream;ILscala/Function0;Lscala/Function0;Lscala/io/Codec;)Lscala/io/Source;;
const #50 = NameAndType	#48:#49;//  fromInputStream:(Ljava/io/InputStream;ILscala/Function0;Lscala/Function0;Lscala/io/Codec;)Lscala/io/Source;
const #51 = Method	#7.#50;	//  scala/io/Source$.fromInputStream:(Ljava/io/InputStream;ILscala/Function0;Lscala/Function0;Lscala/io/Codec;)Lscala/io/Source;
const #52 = Asciz	(Ljava/io/InputStream;ILscala/Function0<Lscala/io/Source;>;Lscala/Function0<Ljava/lang/Object;>;Lscala/io/Codec;)Lscala/io/Source;;
const #53 = Asciz	Signature;
const #54 = Asciz	fromFile;
const #55 = Asciz	(Ljava/io/File;ILscala/io/Codec;)Lscala/io/Source;;
const #56 = NameAndType	#54:#55;//  fromFile:(Ljava/io/File;ILscala/io/Codec;)Lscala/io/Source;
const #57 = Method	#7.#56;	//  scala/io/Source$.fromFile:(Ljava/io/File;ILscala/io/Codec;)Lscala/io/Source;
const #58 = Asciz	fromURL;
const #59 = Asciz	(Ljava/net/URL;Lscala/io/Codec;)Lscala/io/Source;;
const #60 = NameAndType	#58:#59;//  fromURL:(Ljava/net/URL;Lscala/io/Codec;)Lscala/io/Source;
const #61 = Method	#7.#60;	//  scala/io/Source$.fromURL:(Ljava/net/URL;Lscala/io/Codec;)Lscala/io/Source;
const #62 = Asciz	fromURI;
const #63 = Asciz	(Ljava/net/URI;Lscala/io/Codec;)Lscala/io/Source;;
const #64 = NameAndType	#62:#63;//  fromURI:(Ljava/net/URI;Lscala/io/Codec;)Lscala/io/Source;
const #65 = Method	#7.#64;	//  scala/io/Source$.fromURI:(Ljava/net/URI;Lscala/io/Codec;)Lscala/io/Source;
const #66 = Asciz	fromPath;
const #67 = Asciz	(Ljava/lang/String;Lscala/io/Codec;)Lscala/io/Source;;
const #68 = NameAndType	#66:#67;//  fromPath:(Ljava/lang/String;Lscala/io/Codec;)Lscala/io/Source;
const #69 = Method	#7.#68;	//  scala/io/Source$.fromPath:(Ljava/lang/String;Lscala/io/Codec;)Lscala/io/Source;
const #70 = Asciz	fromRawBytes;
const #71 = Asciz	([B)Lscala/io/Source;;
const #72 = NameAndType	#70:#71;//  fromRawBytes:([B)Lscala/io/Source;
const #73 = Method	#7.#72;	//  scala/io/Source$.fromRawBytes:([B)Lscala/io/Source;
const #74 = Asciz	fromBytes;
const #75 = Asciz	([BLscala/io/Codec;)Lscala/io/Source;;
const #76 = NameAndType	#74:#75;//  fromBytes:([BLscala/io/Codec;)Lscala/io/Source;
const #77 = Method	#7.#76;	//  scala/io/Source$.fromBytes:([BLscala/io/Codec;)Lscala/io/Source;
const #78 = Asciz	fromString;
const #79 = Asciz	(Ljava/lang/String;)Lscala/io/Source;;
const #80 = NameAndType	#78:#79;//  fromString:(Ljava/lang/String;)Lscala/io/Source;
const #81 = Method	#7.#80;	//  scala/io/Source$.fromString:(Ljava/lang/String;)Lscala/io/Source;
const #82 = Asciz	fromChars;
const #83 = Asciz	([C)Lscala/io/Source;;
const #84 = NameAndType	#82:#83;//  fromChars:([C)Lscala/io/Source;
const #85 = Method	#7.#84;	//  scala/io/Source$.fromChars:([C)Lscala/io/Source;
const #86 = Asciz	fromChar;
const #87 = Asciz	(C)Lscala/io/Source;;
const #88 = NameAndType	#86:#87;//  fromChar:(C)Lscala/io/Source;
const #89 = Method	#7.#88;	//  scala/io/Source$.fromChar:(C)Lscala/io/Source;
const #90 = Asciz	fromIterable;
const #91 = Asciz	(Lscala/collection/Iterable;)Lscala/io/Source;;
const #92 = NameAndType	#90:#91;//  fromIterable:(Lscala/collection/Iterable;)Lscala/io/Source;
const #93 = Method	#7.#92;	//  scala/io/Source$.fromIterable:(Lscala/collection/Iterable;)Lscala/io/Source;
const #94 = Asciz	(Lscala/collection/Iterable<Ljava/lang/Character;>;)Lscala/io/Source;;
const #95 = Asciz	stdin;
const #96 = Asciz	()Lscala/io/Source;;
const #97 = NameAndType	#95:#96;//  stdin:()Lscala/io/Source;
const #98 = Method	#7.#97;	//  scala/io/Source$.stdin:()Lscala/io/Source;
const #99 = Asciz	DefaultBufSize;
const #100 = NameAndType	#99:#23;//  DefaultBufSize:()I
const #101 = Method	#7.#100;	//  scala/io/Source$.DefaultBufSize:()I
const #102 = Asciz	NoPositioner$module;
const #103 = Asciz	Lscala/io/Source$NoPositioner$;;
const #104 = Asciz	positioner;
const #105 = Asciz	Lscala/io/Source$Positioner;;
const #106 = Asciz	closeFunction;
const #107 = Asciz	Lscala/Function0;;
const #108 = Asciz	Lscala/Function0<Ljava/lang/Object;>;;
const #109 = Asciz	resetFunction;
const #110 = Asciz	Lscala/Function0<Lscala/io/Source;>;;
const #111 = Asciz	nwarnings;
const #112 = Asciz	I;
const #113 = Asciz	nerrors;
const #114 = Asciz	descr;
const #115 = Asciz	Ljava/lang/String;;
const #116 = Asciz	<init>;
const #117 = Asciz	()V;
const #118 = Asciz	LineNumberTable;
const #119 = Asciz	java/lang/Object;
const #120 = class	#119;	//  java/lang/Object
const #121 = NameAndType	#116:#117;//  "<init>":()V
const #122 = Method	#120.#121;	//  java/lang/Object."<init>":()V
const #123 = Asciz	scala/collection/Iterator$class;
const #124 = class	#123;	//  scala/collection/Iterator$class
const #125 = Asciz	$init$;
const #126 = Asciz	(Lscala/collection/Iterator;)V;
const #127 = NameAndType	#125:#126;//  $init$:(Lscala/collection/Iterator;)V
const #128 = Method	#124.#127;	//  scala/collection/Iterator$class.$init$:(Lscala/collection/Iterator;)V
const #129 = Asciz	;
const #130 = String	#129;	//  
const #131 = Asciz	scala/io/Source;
const #132 = class	#131;	//  scala/io/Source
const #133 = NameAndType	#114:#115;//  descr:Ljava/lang/String;
const #134 = Field	#132.#133;	//  scala/io/Source.descr:Ljava/lang/String;
const #135 = NameAndType	#113:#112;//  nerrors:I
const #136 = Field	#132.#135;	//  scala/io/Source.nerrors:I
const #137 = NameAndType	#111:#112;//  nwarnings:I
const #138 = Field	#132.#137;	//  scala/io/Source.nwarnings:I
const #139 = NameAndType	#109:#107;//  resetFunction:Lscala/Function0;
const #140 = Field	#132.#139;	//  scala/io/Source.resetFunction:Lscala/Function0;
const #141 = NameAndType	#106:#107;//  closeFunction:Lscala/Function0;
const #142 = Field	#132.#141;	//  scala/io/Source.closeFunction:Lscala/Function0;
const #143 = Asciz	scala/io/Source$Positioner;
const #144 = class	#143;	//  scala/io/Source$Positioner
const #145 = Asciz	(Lscala/io/Source;)V;
const #146 = NameAndType	#116:#145;//  "<init>":(Lscala/io/Source;)V
const #147 = Method	#144.#146;	//  scala/io/Source$Positioner."<init>":(Lscala/io/Source;)V
const #148 = NameAndType	#104:#105;//  positioner:Lscala/io/Source$Positioner;
const #149 = Field	#132.#148;	//  scala/io/Source.positioner:Lscala/io/Source$Positioner;
const #150 = Asciz	next;
const #151 = Asciz	()Ljava/lang/Object;;
const #152 = Asciz	()C;
const #153 = NameAndType	#150:#152;//  next:()C
const #154 = Method	#132.#153;	//  scala/io/Source.next:()C
const #155 = Asciz	scala/runtime/BoxesRunTime;
const #156 = class	#155;	//  scala/runtime/BoxesRunTime
const #157 = Asciz	boxToCharacter;
const #158 = Asciz	(C)Ljava/lang/Character;;
const #159 = NameAndType	#157:#158;//  boxToCharacter:(C)Ljava/lang/Character;
const #160 = Method	#156.#159;	//  scala/runtime/BoxesRunTime.boxToCharacter:(C)Ljava/lang/Character;
const #161 = Asciz	reset;
const #162 = Asciz	equals;
const #163 = Asciz	(Ljava/lang/Object;)Z;
const #164 = NameAndType	#162:#163;//  equals:(Ljava/lang/Object;)Z
const #165 = Method	#120.#164;	//  java/lang/Object.equals:(Ljava/lang/Object;)Z
const #166 = Asciz	java/lang/UnsupportedOperationException;
const #167 = class	#166;	//  java/lang/UnsupportedOperationException
const #168 = Asciz	Source's reset() method was not set.;
const #169 = String	#168;	//  Source's reset() method was not set.
const #170 = Asciz	(Ljava/lang/String;)V;
const #171 = NameAndType	#116:#170;//  "<init>":(Ljava/lang/String;)V
const #172 = Method	#167.#171;	//  java/lang/UnsupportedOperationException."<init>":(Ljava/lang/String;)V
const #173 = Asciz	scala/Function0;
const #174 = class	#173;	//  scala/Function0
const #175 = Asciz	apply;
const #176 = NameAndType	#175:#151;//  apply:()Ljava/lang/Object;
const #177 = InterfaceMethod	#174.#176;	//  scala/Function0.apply:()Ljava/lang/Object;
const #178 = Asciz	close;
const #179 = Asciz	withPositioning;
const #180 = Asciz	(Z)Lscala/io/Source;;
const #181 = Asciz	NoPositioner;
const #182 = Asciz	()Lscala/io/Source$NoPositioner$;;
const #183 = NameAndType	#181:#182;//  NoPositioner:()Lscala/io/Source$NoPositioner$;
const #184 = Method	#132.#183;	//  scala/io/Source.NoPositioner:()Lscala/io/Source$NoPositioner$;
const #185 = Asciz	this;
const #186 = Asciz	Lscala/io/Source;;
const #187 = Asciz	on;
const #188 = Asciz	Z;
const #189 = Asciz	LocalVariableTable;
const #190 = Asciz	withDescription;
const #191 = Asciz	descr_$eq;
const #192 = NameAndType	#191:#170;//  descr_$eq:(Ljava/lang/String;)V
const #193 = Method	#132.#192;	//  scala/io/Source.descr_$eq:(Ljava/lang/String;)V
const #194 = Asciz	text;
const #195 = Asciz	withClose;
const #196 = Asciz	(Lscala/Function0;)Lscala/io/Source;;
const #197 = Asciz	f;
const #198 = Asciz	(Lscala/Function0<Ljava/lang/Object;>;)Lscala/io/Source;;
const #199 = Asciz	withReset;
const #200 = Asciz	(Lscala/Function0<Lscala/io/Source;>;)Lscala/io/Source;;
const #201 = Asciz	reportWarning;
const #202 = Asciz	(ILjava/lang/String;Ljava/io/PrintStream;)V;
const #203 = NameAndType	#111:#23;//  nwarnings:()I
const #204 = Method	#132.#203;	//  scala/io/Source.nwarnings:()I
const #205 = Asciz	nwarnings_$eq;
const #206 = Asciz	(I)V;
const #207 = NameAndType	#205:#206;//  nwarnings_$eq:(I)V
const #208 = Method	#132.#207;	//  scala/io/Source.nwarnings_$eq:(I)V
const #209 = Asciz	scala/collection/mutable/StringBuilder;
const #210 = class	#209;	//  scala/collection/mutable/StringBuilder
const #211 = Method	#210.#121;	//  scala/collection/mutable/StringBuilder."<init>":()V
const #212 = Asciz	warning! ;
const #213 = String	#212;	//  warning! 
const #214 = Asciz	append;
const #215 = Asciz	(Ljava/lang/Object;)Lscala/collection/mutable/StringBuilder;;
const #216 = NameAndType	#214:#215;//  append:(Ljava/lang/Object;)Lscala/collection/mutable/StringBuilder;
const #217 = Method	#210.#216;	//  scala/collection/mutable/StringBuilder.append:(Ljava/lang/Object;)Lscala/collection/mutable/StringBuilder;
const #218 = Asciz	toString;
const #219 = Asciz	()Ljava/lang/String;;
const #220 = NameAndType	#218:#219;//  toString:()Ljava/lang/String;
const #221 = Method	#210.#220;	//  scala/collection/mutable/StringBuilder.toString:()Ljava/lang/String;
const #222 = Asciz	report;
const #223 = NameAndType	#222:#202;//  report:(ILjava/lang/String;Ljava/io/PrintStream;)V
const #224 = Method	#132.#223;	//  scala/io/Source.report:(ILjava/lang/String;Ljava/io/PrintStream;)V
const #225 = Asciz	pos;
const #226 = Asciz	msg;
const #227 = Asciz	out;
const #228 = Asciz	Ljava/io/PrintStream;;
const #229 = Asciz	scala/io/Position$;
const #230 = class	#229;	//  scala/io/Position$
const #231 = Asciz	Lscala/io/Position$;;
const #232 = NameAndType	#8:#231;//  MODULE$:Lscala/io/Position$;
const #233 = Field	#230.#232;	//  scala/io/Position$.MODULE$:Lscala/io/Position$;
const #234 = Asciz	line;
const #235 = Asciz	(I)I;
const #236 = NameAndType	#234:#235;//  line:(I)I
const #237 = Method	#230.#236;	//  scala/io/Position$.line:(I)I
const #238 = Asciz	column;
const #239 = NameAndType	#238:#235;//  column:(I)I
const #240 = Method	#230.#239;	//  scala/io/Position$.column:(I)I
const #241 = Asciz	scala/Predef$;
const #242 = class	#241;	//  scala/Predef$
const #243 = Asciz	Lscala/Predef$;;
const #244 = NameAndType	#8:#243;//  MODULE$:Lscala/Predef$;
const #245 = Field	#242.#244;	//  scala/Predef$.MODULE$:Lscala/Predef$;
const #246 = Asciz	%s:%d:%d: %s%s%s^;
const #247 = String	#246;	//  %s:%d:%d: %s%s%s^
const #248 = Asciz	augmentString;
const #249 = Asciz	(Ljava/lang/String;)Lscala/collection/immutable/StringOps;;
const #250 = NameAndType	#248:#249;//  augmentString:(Ljava/lang/String;)Lscala/collection/immutable/StringOps;
const #251 = Method	#242.#250;	//  scala/Predef$.augmentString:(Ljava/lang/String;)Lscala/collection/immutable/StringOps;
const #252 = int	6;
const #253 = NameAndType	#114:#219;//  descr:()Ljava/lang/String;
const #254 = Method	#132.#253;	//  scala/io/Source.descr:()Ljava/lang/String;
const #255 = Asciz	boxToInteger;
const #256 = Asciz	(I)Ljava/lang/Integer;;
const #257 = NameAndType	#255:#256;//  boxToInteger:(I)Ljava/lang/Integer;
const #258 = Method	#156.#257;	//  scala/runtime/BoxesRunTime.boxToInteger:(I)Ljava/lang/Integer;
const #259 = Asciz	getLine;
const #260 = Asciz	(I)Ljava/lang/String;;
const #261 = NameAndType	#259:#260;//  getLine:(I)Ljava/lang/String;
const #262 = Method	#132.#261;	//  scala/io/Source.getLine:(I)Ljava/lang/String;
const #263 = Asciz	spaces;
const #264 = NameAndType	#263:#260;//  spaces:(I)Ljava/lang/String;
const #265 = Method	#132.#264;	//  scala/io/Source.spaces:(I)Ljava/lang/String;
const #266 = Asciz	genericWrapArray;
const #267 = Asciz	(Ljava/lang/Object;)Lscala/collection/mutable/WrappedArray;;
const #268 = NameAndType	#266:#267;//  genericWrapArray:(Ljava/lang/Object;)Lscala/collection/mutable/WrappedArray;
const #269 = Method	#242.#268;	//  scala/Predef$.genericWrapArray:(Ljava/lang/Object;)Lscala/collection/mutable/WrappedArray;
const #270 = Asciz	scala/collection/immutable/StringLike;
const #271 = class	#270;	//  scala/collection/immutable/StringLike
const #272 = Asciz	format;
const #273 = Asciz	(Lscala/collection/Seq;)Ljava/lang/String;;
const #274 = NameAndType	#272:#273;//  format:(Lscala/collection/Seq;)Ljava/lang/String;
const #275 = InterfaceMethod	#271.#274;	//  scala/collection/immutable/StringLike.format:(Lscala/collection/Seq;)Ljava/lang/String;
const #276 = Asciz	java/io/PrintStream;
const #277 = class	#276;	//  java/io/PrintStream
const #278 = Asciz	println;
const #279 = NameAndType	#278:#170;//  println:(Ljava/lang/String;)V
const #280 = Method	#277.#279;	//  java/io/PrintStream.println:(Ljava/lang/String;)V
const #281 = Asciz	col;
const #282 = Asciz	scala/collection/immutable/List$;
const #283 = class	#282;	//  scala/collection/immutable/List$
const #284 = Asciz	Lscala/collection/immutable/List$;;
const #285 = NameAndType	#8:#284;//  MODULE$:Lscala/collection/immutable/List$;
const #286 = Field	#283.#285;	//  scala/collection/immutable/List$.MODULE$:Lscala/collection/immutable/List$;
const #287 = Asciz	scala/io/Source$$anonfun$spaces$1;
const #288 = class	#287;	//  scala/io/Source$$anonfun$spaces$1
const #289 = Method	#288.#146;	//  scala/io/Source$$anonfun$spaces$1."<init>":(Lscala/io/Source;)V
const #290 = Asciz	fill;
const #291 = Asciz	(ILscala/Function0;)Lscala/collection/Traversable;;
const #292 = NameAndType	#290:#291;//  fill:(ILscala/Function0;)Lscala/collection/Traversable;
const #293 = Method	#283.#292;	//  scala/collection/immutable/List$.fill:(ILscala/Function0;)Lscala/collection/Traversable;
const #294 = Asciz	scala/collection/TraversableLike;
const #295 = class	#294;	//  scala/collection/TraversableLike
const #296 = Asciz	mkString;
const #297 = NameAndType	#296:#219;//  mkString:()Ljava/lang/String;
const #298 = InterfaceMethod	#295.#297;	//  scala/collection/TraversableLike.mkString:()Ljava/lang/String;
const #299 = Asciz	n;
const #300 = Asciz	reportError;
const #301 = NameAndType	#113:#23;//  nerrors:()I
const #302 = Method	#132.#301;	//  scala/io/Source.nerrors:()I
const #303 = Asciz	nerrors_$eq;
const #304 = NameAndType	#303:#206;//  nerrors_$eq:(I)V
const #305 = Method	#132.#304;	//  scala/io/Source.nerrors_$eq:(I)V
const #306 = NameAndType	#225:#23;//  pos:()I
const #307 = Method	#144.#306;	//  scala/io/Source$Positioner.pos:()I
const #308 = Asciz	ch;
const #309 = NameAndType	#308:#152;//  ch:()C
const #310 = Method	#144.#309;	//  scala/io/Source$Positioner.ch:()C
const #311 = NameAndType	#102:#103;//  NoPositioner$module:Lscala/io/Source$NoPositioner$;
const #312 = Field	#132.#311;	//  scala/io/Source.NoPositioner$module:Lscala/io/Source$NoPositioner$;
const #313 = Asciz	scala/io/Source$NoPositioner$;
const #314 = class	#313;	//  scala/io/Source$NoPositioner$
const #315 = Method	#314.#146;	//  scala/io/Source$NoPositioner$."<init>":(Lscala/io/Source;)V
const #316 = Method	#144.#153;	//  scala/io/Source$Positioner.next:()C
const #317 = Asciz	hasNext;
const #318 = Asciz	()Z;
const #319 = Asciz	iter;
const #320 = Asciz	()Lscala/collection/Iterator;;
const #321 = NameAndType	#319:#320;//  iter:()Lscala/collection/Iterator;
const #322 = Method	#132.#321;	//  scala/io/Source.iter:()Lscala/collection/Iterator;
const #323 = Asciz	scala/collection/Iterator;
const #324 = class	#323;	//  scala/collection/Iterator
const #325 = NameAndType	#317:#318;//  hasNext:()Z
const #326 = InterfaceMethod	#324.#325;	//  scala/collection/Iterator.hasNext:()Z
const #327 = Asciz	getLines;
const #328 = Asciz	(Ljava/lang/String;)Lscala/collection/Iterator;;
const #329 = Asciz	scala/io/Source$LineIterator;
const #330 = class	#329;	//  scala/io/Source$LineIterator
const #331 = Asciz	(Lscala/io/Source;Ljava/lang/String;)V;
const #332 = NameAndType	#116:#331;//  "<init>":(Lscala/io/Source;Ljava/lang/String;)V
const #333 = Method	#330.#332;	//  scala/io/Source$LineIterator."<init>":(Lscala/io/Source;Ljava/lang/String;)V
const #334 = Asciz	separator;
const #335 = Asciz	(Ljava/lang/String;)Lscala/collection/Iterator<Ljava/lang/String;>;;
const #336 = Asciz	getLines$default$1;
const #337 = NameAndType	#336:#219;//  getLines$default$1:()Ljava/lang/String;
const #338 = Method	#132.#337;	//  scala/io/Source.getLines$default$1:()Ljava/lang/String;
const #339 = NameAndType	#327:#328;//  getLines:(Ljava/lang/String;)Lscala/collection/Iterator;
const #340 = Method	#132.#339;	//  scala/io/Source.getLines:(Ljava/lang/String;)Lscala/collection/Iterator;
const #341 = Asciz	drop;
const #342 = Asciz	(I)Lscala/collection/Iterator;;
const #343 = NameAndType	#341:#342;//  drop:(I)Lscala/collection/Iterator;
const #344 = InterfaceMethod	#324.#343;	//  scala/collection/Iterator.drop:(I)Lscala/collection/Iterator;
const #345 = NameAndType	#150:#151;//  next:()Ljava/lang/Object;
const #346 = InterfaceMethod	#324.#345;	//  scala/collection/Iterator.next:()Ljava/lang/Object;
const #347 = Asciz	java/lang/String;
const #348 = class	#347;	//  java/lang/String
const #349 = Asciz	()Lscala/collection/Iterator<Ljava/lang/Character;>;;
const #350 = Asciz	scala/compat/Platform$;
const #351 = class	#350;	//  scala/compat/Platform$
const #352 = Asciz	Lscala/compat/Platform$;;
const #353 = NameAndType	#8:#352;//  MODULE$:Lscala/compat/Platform$;
const #354 = Field	#351.#353;	//  scala/compat/Platform$.MODULE$:Lscala/compat/Platform$;
const #355 = Asciz	EOL;
const #356 = NameAndType	#355:#219;//  EOL:()Ljava/lang/String;
const #357 = Method	#351.#356;	//  scala/compat/Platform$.EOL:()Ljava/lang/String;
const #358 = Asciz	reportError$default$3;
const #359 = Asciz	()Ljava/io/PrintStream;;
const #360 = Asciz	scala/Console$;
const #361 = class	#360;	//  scala/Console$
const #362 = Asciz	Lscala/Console$;;
const #363 = NameAndType	#8:#362;//  MODULE$:Lscala/Console$;
const #364 = Field	#361.#363;	//  scala/Console$.MODULE$:Lscala/Console$;
const #365 = Asciz	err;
const #366 = NameAndType	#365:#359;//  err:()Ljava/io/PrintStream;
const #367 = Method	#361.#366;	//  scala/Console$.err:()Ljava/io/PrintStream;
const #368 = Asciz	reportWarning$default$3;
const #369 = NameAndType	#227:#359;//  out:()Ljava/io/PrintStream;
const #370 = Method	#361.#369;	//  scala/Console$.out:()Ljava/io/PrintStream;
const #371 = Asciz	sliding$default$2;
const #372 = Asciz	(Lscala/collection/Iterator;)I;
const #373 = NameAndType	#371:#372;//  sliding$default$2:(Lscala/collection/Iterator;)I
const #374 = Method	#124.#373;	//  scala/collection/Iterator$class.sliding$default$2:(Lscala/collection/Iterator;)I
const #375 = Asciz	readInto;
const #376 = Asciz	(Ljava/lang/Object;)V;
const #377 = Asciz	(Lscala/collection/Iterator;Ljava/lang/Object;)V;
const #378 = NameAndType	#375:#377;//  readInto:(Lscala/collection/Iterator;Ljava/lang/Object;)V
const #379 = Method	#124.#378;	//  scala/collection/Iterator$class.readInto:(Lscala/collection/Iterator;Ljava/lang/Object;)V
const #380 = Asciz	xs;
const #381 = Asciz	Ljava/lang/Object;;
const #382 = Asciz	Deprecated;
const #383 = Asciz	(Ljava/lang/Object;I)V;
const #384 = Asciz	(Lscala/collection/Iterator;Ljava/lang/Object;I)V;
const #385 = NameAndType	#375:#384;//  readInto:(Lscala/collection/Iterator;Ljava/lang/Object;I)V
const #386 = Method	#124.#385;	//  scala/collection/Iterator$class.readInto:(Lscala/collection/Iterator;Ljava/lang/Object;I)V
const #387 = Asciz	start;
const #388 = Asciz	(Ljava/lang/Object;II)V;
const #389 = Asciz	(Lscala/collection/Iterator;Ljava/lang/Object;II)V;
const #390 = NameAndType	#375:#389;//  readInto:(Lscala/collection/Iterator;Ljava/lang/Object;II)V
const #391 = Method	#124.#390;	//  scala/collection/Iterator$class.readInto:(Lscala/collection/Iterator;Ljava/lang/Object;II)V
const #392 = Asciz	sz;
const #393 = Asciz	counted;
const #394 = Asciz	(Lscala/collection/Iterator;)Ljava/lang/Object;;
const #395 = NameAndType	#393:#394;//  counted:(Lscala/collection/Iterator;)Ljava/lang/Object;
const #396 = Method	#124.#395;	//  scala/collection/Iterator$class.counted:(Lscala/collection/Iterator;)Ljava/lang/Object;
const #397 = Asciz	collect;
const #398 = Asciz	()Lscala/collection/Seq;;
const #399 = Asciz	(Lscala/collection/Iterator;)Lscala/collection/Seq;;
const #400 = NameAndType	#397:#399;//  collect:(Lscala/collection/Iterator;)Lscala/collection/Seq;
const #401 = Method	#124.#400;	//  scala/collection/Iterator$class.collect:(Lscala/collection/Iterator;)Lscala/collection/Seq;
const #402 = Asciz	findIndexOf;
const #403 = Asciz	(Lscala/Function1;)I;
const #404 = Asciz	(Lscala/collection/Iterator;Lscala/Function1;)I;
const #405 = NameAndType	#402:#404;//  findIndexOf:(Lscala/collection/Iterator;Lscala/Function1;)I
const #406 = Method	#124.#405;	//  scala/collection/Iterator$class.findIndexOf:(Lscala/collection/Iterator;Lscala/Function1;)I
const #407 = Asciz	p;
const #408 = Asciz	Lscala/Function1;;
const #409 = Asciz	(Lscala/collection/Iterator;)Lscala/collection/Iterator;;
const #410 = Asciz	(Lscala/collection/Iterator;Lscala/collection/Iterator;)Lscala/collection/Iterator;;
const #411 = NameAndType	#214:#410;//  append:(Lscala/collection/Iterator;Lscala/collection/Iterator;)Lscala/collection/Iterator;
const #412 = Method	#124.#411;	//  scala/collection/Iterator$class.append:(Lscala/collection/Iterator;Lscala/collection/Iterator;)Lscala/collection/Iterator;
const #413 = Asciz	that;
const #414 = Asciz	Lscala/collection/Iterator;;
const #415 = Asciz	(Lscala/collection/Iterator;)Ljava/lang/String;;
const #416 = NameAndType	#218:#415;//  toString:(Lscala/collection/Iterator;)Ljava/lang/String;
const #417 = Method	#124.#416;	//  scala/collection/Iterator$class.toString:(Lscala/collection/Iterator;)Ljava/lang/String;
const #418 = Asciz	addString;
const #419 = Asciz	(Lscala/collection/mutable/StringBuilder;)Lscala/collection/mutable/StringBuilder;;
const #420 = Asciz	(Lscala/collection/Iterator;Lscala/collection/mutable/StringBuilder;)Lscala/collection/mutable/StringBuilder;;
const #421 = NameAndType	#418:#420;//  addString:(Lscala/collection/Iterator;Lscala/collection/mutable/StringBuilder;)Lscala/collection/mutable/StringBuilder;
const #422 = Method	#124.#421;	//  scala/collection/Iterator$class.addString:(Lscala/collection/Iterator;Lscala/collection/mutable/StringBuilder;)Lscala/collection/mutable/StringBuilder;
const #423 = Asciz	buf;
const #424 = Asciz	Lscala/collection/mutable/StringBuilder;;
const #425 = Asciz	(Lscala/collection/mutable/StringBuilder;Ljava/lang/String;)Lscala/collection/mutable/StringBuilder;;
const #426 = Asciz	(Lscala/collection/Iterator;Lscala/collection/mutable/StringBuilder;Ljava/lang/String;)Lscala/collection/mutable/StringBuilder;;
const #427 = NameAndType	#418:#426;//  addString:(Lscala/collection/Iterator;Lscala/collection/mutable/StringBuilder;Ljava/lang/String;)Lscala/collection/mutable/StringBuilder;
const #428 = Method	#124.#427;	//  scala/collection/Iterator$class.addString:(Lscala/collection/Iterator;Lscala/collection/mutable/StringBuilder;Ljava/lang/String;)Lscala/collection/mutable/StringBuilder;
const #429 = Asciz	sep;
const #430 = Asciz	(Lscala/collection/mutable/StringBuilder;Ljava/lang/String;Ljava/lang/String;Ljava/lang/String;)Lscala/collection/mutable/StringBuilder;;
const #431 = Asciz	(Lscala/collection/Iterator;Lscala/collection/mutable/StringBuilder;Ljava/lang/String;Ljava/lang/String;Ljava/lang/String;)Lscala/collection/mutable/StringBuilder;;
const #432 = NameAndType	#418:#431;//  addString:(Lscala/collection/Iterator;Lscala/collection/mutable/StringBuilder;Ljava/lang/String;Ljava/lang/String;Ljava/lang/String;)Lscala/collection/mutable/StringBuilder;
const #433 = Method	#124.#432;	//  scala/collection/Iterator$class.addString:(Lscala/collection/Iterator;Lscala/collection/mutable/StringBuilder;Ljava/lang/String;Ljava/lang/String;Ljava/lang/String;)Lscala/collection/mutable/StringBuilder;
const #434 = Asciz	end;
const #435 = NameAndType	#296:#415;//  mkString:(Lscala/collection/Iterator;)Ljava/lang/String;
const #436 = Method	#124.#435;	//  scala/collection/Iterator$class.mkString:(Lscala/collection/Iterator;)Ljava/lang/String;
const #437 = Asciz	(Ljava/lang/String;)Ljava/lang/String;;
const #438 = Asciz	(Lscala/collection/Iterator;Ljava/lang/String;)Ljava/lang/String;;
const #439 = NameAndType	#296:#438;//  mkString:(Lscala/collection/Iterator;Ljava/lang/String;)Ljava/lang/String;
const #440 = Method	#124.#439;	//  scala/collection/Iterator$class.mkString:(Lscala/collection/Iterator;Ljava/lang/String;)Ljava/lang/String;
const #441 = Asciz	(Ljava/lang/String;Ljava/lang/String;Ljava/lang/String;)Ljava/lang/String;;
const #442 = Asciz	(Lscala/collection/Iterator;Ljava/lang/String;Ljava/lang/String;Ljava/lang/String;)Ljava/lang/String;;
const #443 = NameAndType	#296:#442;//  mkString:(Lscala/collection/Iterator;Ljava/lang/String;Ljava/lang/String;Ljava/lang/String;)Ljava/lang/String;
const #444 = Method	#124.#443;	//  scala/collection/Iterator$class.mkString:(Lscala/collection/Iterator;Ljava/lang/String;Ljava/lang/String;Ljava/lang/String;)Ljava/lang/String;
const #445 = Asciz	sameElements;
const #446 = Asciz	(Lscala/collection/Iterator;)Z;
const #447 = Asciz	(Lscala/collection/Iterator;Lscala/collection/Iterator;)Z;
const #448 = NameAndType	#445:#447;//  sameElements:(Lscala/collection/Iterator;Lscala/collection/Iterator;)Z
const #449 = Method	#124.#448;	//  scala/collection/Iterator$class.sameElements:(Lscala/collection/Iterator;Lscala/collection/Iterator;)Z
const #450 = Asciz	toSeq;
const #451 = NameAndType	#450:#399;//  toSeq:(Lscala/collection/Iterator;)Lscala/collection/Seq;
const #452 = Method	#124.#451;	//  scala/collection/Iterator$class.toSeq:(Lscala/collection/Iterator;)Lscala/collection/Seq;
const #453 = Asciz	toStream;
const #454 = Asciz	()Lscala/collection/immutable/Stream;;
const #455 = Asciz	(Lscala/collection/Iterator;)Lscala/collection/immutable/Stream;;
const #456 = NameAndType	#453:#455;//  toStream:(Lscala/collection/Iterator;)Lscala/collection/immutable/Stream;
const #457 = Method	#124.#456;	//  scala/collection/Iterator$class.toStream:(Lscala/collection/Iterator;)Lscala/collection/immutable/Stream;
const #458 = Asciz	toList;
const #459 = Asciz	()Lscala/collection/immutable/List;;
const #460 = Asciz	(Lscala/collection/Iterator;)Lscala/collection/immutable/List;;
const #461 = NameAndType	#458:#460;//  toList:(Lscala/collection/Iterator;)Lscala/collection/immutable/List;
const #462 = Method	#124.#461;	//  scala/collection/Iterator$class.toList:(Lscala/collection/Iterator;)Lscala/collection/immutable/List;
const #463 = Asciz	copyToBuffer;
const #464 = Asciz	(Lscala/collection/mutable/Buffer;)V;
const #465 = Asciz	(Lscala/collection/Iterator;Lscala/collection/mutable/Buffer;)V;
const #466 = NameAndType	#463:#465;//  copyToBuffer:(Lscala/collection/Iterator;Lscala/collection/mutable/Buffer;)V
const #467 = Method	#124.#466;	//  scala/collection/Iterator$class.copyToBuffer:(Lscala/collection/Iterator;Lscala/collection/mutable/Buffer;)V
const #468 = Asciz	dest;
const #469 = Asciz	Lscala/collection/mutable/Buffer;;
const #470 = Asciz	copyToArray;
const #471 = NameAndType	#470:#377;//  copyToArray:(Lscala/collection/Iterator;Ljava/lang/Object;)V
const #472 = Method	#124.#471;	//  scala/collection/Iterator$class.copyToArray:(Lscala/collection/Iterator;Ljava/lang/Object;)V
const #473 = NameAndType	#470:#384;//  copyToArray:(Lscala/collection/Iterator;Ljava/lang/Object;I)V
const #474 = Method	#124.#473;	//  scala/collection/Iterator$class.copyToArray:(Lscala/collection/Iterator;Ljava/lang/Object;I)V
const #475 = NameAndType	#470:#389;//  copyToArray:(Lscala/collection/Iterator;Ljava/lang/Object;II)V
const #476 = Method	#124.#475;	//  scala/collection/Iterator$class.copyToArray:(Lscala/collection/Iterator;Ljava/lang/Object;II)V
const #477 = Asciz	len;
const #478 = Asciz	patch;
const #479 = Asciz	(ILscala/collection/Iterator;I)Ljava/lang/Object;;
const #480 = Asciz	(Lscala/collection/Iterator;ILscala/collection/Iterator;I)Ljava/lang/Object;;
const #481 = NameAndType	#478:#480;//  patch:(Lscala/collection/Iterator;ILscala/collection/Iterator;I)Ljava/lang/Object;
const #482 = Method	#124.#481;	//  scala/collection/Iterator$class.patch:(Lscala/collection/Iterator;ILscala/collection/Iterator;I)Ljava/lang/Object;
const #483 = Asciz	from;
const #484 = Asciz	patchElems;
const #485 = Asciz	replaced;
const #486 = Asciz	duplicate;
const #487 = Asciz	()Lscala/Tuple2;;
const #488 = Asciz	(Lscala/collection/Iterator;)Lscala/Tuple2;;
const #489 = NameAndType	#486:#488;//  duplicate:(Lscala/collection/Iterator;)Lscala/Tuple2;
const #490 = Method	#124.#489;	//  scala/collection/Iterator$class.duplicate:(Lscala/collection/Iterator;)Lscala/Tuple2;
const #491 = Asciz	length;
const #492 = NameAndType	#491:#372;//  length:(Lscala/collection/Iterator;)I
const #493 = Method	#124.#492;	//  scala/collection/Iterator$class.length:(Lscala/collection/Iterator;)I
const #494 = Asciz	sliding;
const #495 = Asciz	(II)Lscala/collection/Iterator$GroupedIterator;;
const #496 = Asciz	(Lscala/collection/Iterator;II)Lscala/collection/Iterator$GroupedIterator;;
const #497 = NameAndType	#494:#496;//  sliding:(Lscala/collection/Iterator;II)Lscala/collection/Iterator$GroupedIterator;
const #498 = Method	#124.#497;	//  scala/collection/Iterator$class.sliding:(Lscala/collection/Iterator;II)Lscala/collection/Iterator$GroupedIterator;
const #499 = Asciz	size;
const #500 = Asciz	step;
const #501 = Asciz	grouped;
const #502 = Asciz	(I)Lscala/collection/Iterator$GroupedIterator;;
const #503 = Asciz	(Lscala/collection/Iterator;I)Lscala/collection/Iterator$GroupedIterator;;
const #504 = NameAndType	#501:#503;//  grouped:(Lscala/collection/Iterator;I)Lscala/collection/Iterator$GroupedIterator;
const #505 = Method	#124.#504;	//  scala/collection/Iterator$class.grouped:(Lscala/collection/Iterator;I)Lscala/collection/Iterator$GroupedIterator;
const #506 = Asciz	buffered;
const #507 = NameAndType	#506:#394;//  buffered:(Lscala/collection/Iterator;)Ljava/lang/Object;
const #508 = Method	#124.#507;	//  scala/collection/Iterator$class.buffered:(Lscala/collection/Iterator;)Ljava/lang/Object;
const #509 = Asciz	reduceRightOption;
const #510 = Asciz	(Lscala/Function2;)Lscala/Option;;
const #511 = Asciz	(Lscala/collection/Iterator;Lscala/Function2;)Lscala/Option;;
const #512 = NameAndType	#509:#511;//  reduceRightOption:(Lscala/collection/Iterator;Lscala/Function2;)Lscala/Option;
const #513 = Method	#124.#512;	//  scala/collection/Iterator$class.reduceRightOption:(Lscala/collection/Iterator;Lscala/Function2;)Lscala/Option;
const #514 = Asciz	op;
const #515 = Asciz	Lscala/Function2;;
const #516 = Asciz	reduceLeftOption;
const #517 = NameAndType	#516:#511;//  reduceLeftOption:(Lscala/collection/Iterator;Lscala/Function2;)Lscala/Option;
const #518 = Method	#124.#517;	//  scala/collection/Iterator$class.reduceLeftOption:(Lscala/collection/Iterator;Lscala/Function2;)Lscala/Option;
const #519 = Asciz	reduceRight;
const #520 = Asciz	(Lscala/Function2;)Ljava/lang/Object;;
const #521 = Asciz	(Lscala/collection/Iterator;Lscala/Function2;)Ljava/lang/Object;;
const #522 = NameAndType	#519:#521;//  reduceRight:(Lscala/collection/Iterator;Lscala/Function2;)Ljava/lang/Object;
const #523 = Method	#124.#522;	//  scala/collection/Iterator$class.reduceRight:(Lscala/collection/Iterator;Lscala/Function2;)Ljava/lang/Object;
const #524 = Asciz	reduceLeft;
const #525 = NameAndType	#524:#521;//  reduceLeft:(Lscala/collection/Iterator;Lscala/Function2;)Ljava/lang/Object;
const #526 = Method	#124.#525;	//  scala/collection/Iterator$class.reduceLeft:(Lscala/collection/Iterator;Lscala/Function2;)Ljava/lang/Object;
const #527 = Asciz	$colon$bslash;
const #528 = Asciz	(Ljava/lang/Object;Lscala/Function2;)Ljava/lang/Object;;
const #529 = Asciz	(Lscala/collection/Iterator;Ljava/lang/Object;Lscala/Function2;)Ljava/lang/Object;;
const #530 = NameAndType	#527:#529;//  $colon$bslash:(Lscala/collection/Iterator;Ljava/lang/Object;Lscala/Function2;)Ljava/lang/Object;
const #531 = Method	#124.#530;	//  scala/collection/Iterator$class.$colon$bslash:(Lscala/collection/Iterator;Ljava/lang/Object;Lscala/Function2;)Ljava/lang/Object;
const #532 = Asciz	z;
const #533 = Asciz	$div$colon;
const #534 = NameAndType	#533:#529;//  $div$colon:(Lscala/collection/Iterator;Ljava/lang/Object;Lscala/Function2;)Ljava/lang/Object;
const #535 = Method	#124.#534;	//  scala/collection/Iterator$class.$div$colon:(Lscala/collection/Iterator;Ljava/lang/Object;Lscala/Function2;)Ljava/lang/Object;
const #536 = Asciz	foldRight;
const #537 = NameAndType	#536:#529;//  foldRight:(Lscala/collection/Iterator;Ljava/lang/Object;Lscala/Function2;)Ljava/lang/Object;
const #538 = Method	#124.#537;	//  scala/collection/Iterator$class.foldRight:(Lscala/collection/Iterator;Ljava/lang/Object;Lscala/Function2;)Ljava/lang/Object;
const #539 = Asciz	foldLeft;
const #540 = NameAndType	#539:#529;//  foldLeft:(Lscala/collection/Iterator;Ljava/lang/Object;Lscala/Function2;)Ljava/lang/Object;
const #541 = Method	#124.#540;	//  scala/collection/Iterator$class.foldLeft:(Lscala/collection/Iterator;Ljava/lang/Object;Lscala/Function2;)Ljava/lang/Object;
const #542 = Asciz	indexOf;
const #543 = Asciz	(Ljava/lang/Object;)I;
const #544 = Asciz	(Lscala/collection/Iterator;Ljava/lang/Object;)I;
const #545 = NameAndType	#542:#544;//  indexOf:(Lscala/collection/Iterator;Ljava/lang/Object;)I
const #546 = Method	#124.#545;	//  scala/collection/Iterator$class.indexOf:(Lscala/collection/Iterator;Ljava/lang/Object;)I
const #547 = Asciz	elem;
const #548 = Asciz	indexWhere;
const #549 = NameAndType	#548:#404;//  indexWhere:(Lscala/collection/Iterator;Lscala/Function1;)I
const #550 = Method	#124.#549;	//  scala/collection/Iterator$class.indexWhere:(Lscala/collection/Iterator;Lscala/Function1;)I
const #551 = Asciz	find;
const #552 = Asciz	(Lscala/Function1;)Lscala/Option;;
const #553 = Asciz	(Lscala/collection/Iterator;Lscala/Function1;)Lscala/Option;;
const #554 = NameAndType	#551:#553;//  find:(Lscala/collection/Iterator;Lscala/Function1;)Lscala/Option;
const #555 = Method	#124.#554;	//  scala/collection/Iterator$class.find:(Lscala/collection/Iterator;Lscala/Function1;)Lscala/Option;
const #556 = Asciz	contains;
const #557 = Asciz	(Lscala/collection/Iterator;Ljava/lang/Object;)Z;
const #558 = NameAndType	#556:#557;//  contains:(Lscala/collection/Iterator;Ljava/lang/Object;)Z
const #559 = Method	#124.#558;	//  scala/collection/Iterator$class.contains:(Lscala/collection/Iterator;Ljava/lang/Object;)Z
const #560 = Asciz	exists;
const #561 = Asciz	(Lscala/Function1;)Z;
const #562 = Asciz	(Lscala/collection/Iterator;Lscala/Function1;)Z;
const #563 = NameAndType	#560:#562;//  exists:(Lscala/collection/Iterator;Lscala/Function1;)Z
const #564 = Method	#124.#563;	//  scala/collection/Iterator$class.exists:(Lscala/collection/Iterator;Lscala/Function1;)Z
const #565 = Asciz	forall;
const #566 = NameAndType	#565:#562;//  forall:(Lscala/collection/Iterator;Lscala/Function1;)Z
const #567 = Method	#124.#566;	//  scala/collection/Iterator$class.forall:(Lscala/collection/Iterator;Lscala/Function1;)Z
const #568 = Asciz	foreach;
const #569 = Asciz	(Lscala/Function1;)V;
const #570 = Asciz	(Lscala/collection/Iterator;Lscala/Function1;)V;
const #571 = NameAndType	#568:#570;//  foreach:(Lscala/collection/Iterator;Lscala/Function1;)V
const #572 = Method	#124.#571;	//  scala/collection/Iterator$class.foreach:(Lscala/collection/Iterator;Lscala/Function1;)V
const #573 = Asciz	zipAll;
const #574 = Asciz	(Lscala/collection/Iterator;Ljava/lang/Object;Ljava/lang/Object;)Ljava/lang/Object;;
const #575 = Asciz	(Lscala/collection/Iterator;Lscala/collection/Iterator;Ljava/lang/Object;Ljava/lang/Object;)Ljava/lang/Object;;
const #576 = NameAndType	#573:#575;//  zipAll:(Lscala/collection/Iterator;Lscala/collection/Iterator;Ljava/lang/Object;Ljava/lang/Object;)Ljava/lang/Object;
const #577 = Method	#124.#576;	//  scala/collection/Iterator$class.zipAll:(Lscala/collection/Iterator;Lscala/collection/Iterator;Ljava/lang/Object;Ljava/lang/Object;)Ljava/lang/Object;
const #578 = Asciz	thisElem;
const #579 = Asciz	thatElem;
const #580 = Asciz	zipWithIndex;
const #581 = NameAndType	#580:#394;//  zipWithIndex:(Lscala/collection/Iterator;)Ljava/lang/Object;
const #582 = Method	#124.#581;	//  scala/collection/Iterator$class.zipWithIndex:(Lscala/collection/Iterator;)Ljava/lang/Object;
const #583 = Asciz	padTo;
const #584 = Asciz	(ILjava/lang/Object;)Ljava/lang/Object;;
const #585 = Asciz	(Lscala/collection/Iterator;ILjava/lang/Object;)Ljava/lang/Object;;
const #586 = NameAndType	#583:#585;//  padTo:(Lscala/collection/Iterator;ILjava/lang/Object;)Ljava/lang/Object;
const #587 = Method	#124.#586;	//  scala/collection/Iterator$class.padTo:(Lscala/collection/Iterator;ILjava/lang/Object;)Ljava/lang/Object;
const #588 = Asciz	zip;
const #589 = Asciz	(Lscala/collection/Iterator;Lscala/collection/Iterator;)Ljava/lang/Object;;
const #590 = NameAndType	#588:#589;//  zip:(Lscala/collection/Iterator;Lscala/collection/Iterator;)Ljava/lang/Object;
const #591 = Method	#124.#590;	//  scala/collection/Iterator$class.zip:(Lscala/collection/Iterator;Lscala/collection/Iterator;)Ljava/lang/Object;
const #592 = Asciz	dropWhile;
const #593 = Asciz	(Lscala/Function1;)Lscala/collection/Iterator;;
const #594 = Asciz	(Lscala/collection/Iterator;Lscala/Function1;)Lscala/collection/Iterator;;
const #595 = NameAndType	#592:#594;//  dropWhile:(Lscala/collection/Iterator;Lscala/Function1;)Lscala/collection/Iterator;
const #596 = Method	#124.#595;	//  scala/collection/Iterator$class.dropWhile:(Lscala/collection/Iterator;Lscala/Function1;)Lscala/collection/Iterator;
const #597 = Asciz	partition;
const #598 = Asciz	(Lscala/Function1;)Lscala/Tuple2;;
const #599 = Asciz	(Lscala/collection/Iterator;Lscala/Function1;)Lscala/Tuple2;;
const #600 = NameAndType	#597:#599;//  partition:(Lscala/collection/Iterator;Lscala/Function1;)Lscala/Tuple2;
const #601 = Method	#124.#600;	//  scala/collection/Iterator$class.partition:(Lscala/collection/Iterator;Lscala/Function1;)Lscala/Tuple2;
const #602 = Asciz	takeWhile;
const #603 = NameAndType	#602:#594;//  takeWhile:(Lscala/collection/Iterator;Lscala/Function1;)Lscala/collection/Iterator;
const #604 = Method	#124.#603;	//  scala/collection/Iterator$class.takeWhile:(Lscala/collection/Iterator;Lscala/Function1;)Lscala/collection/Iterator;
const #605 = Asciz	partialMap;
const #606 = Asciz	(Lscala/PartialFunction;)Lscala/collection/Iterator;;
const #607 = Asciz	(Lscala/collection/Iterator;Lscala/PartialFunction;)Lscala/collection/Iterator;;
const #608 = NameAndType	#605:#607;//  partialMap:(Lscala/collection/Iterator;Lscala/PartialFunction;)Lscala/collection/Iterator;
const #609 = Method	#124.#608;	//  scala/collection/Iterator$class.partialMap:(Lscala/collection/Iterator;Lscala/PartialFunction;)Lscala/collection/Iterator;
const #610 = Asciz	pf;
const #611 = Asciz	Lscala/PartialFunction;;
const #612 = Asciz	filterNot;
const #613 = NameAndType	#612:#594;//  filterNot:(Lscala/collection/Iterator;Lscala/Function1;)Lscala/collection/Iterator;
const #614 = Method	#124.#613;	//  scala/collection/Iterator$class.filterNot:(Lscala/collection/Iterator;Lscala/Function1;)Lscala/collection/Iterator;
const #615 = Asciz	withFilter;
const #616 = NameAndType	#615:#594;//  withFilter:(Lscala/collection/Iterator;Lscala/Function1;)Lscala/collection/Iterator;
const #617 = Method	#124.#616;	//  scala/collection/Iterator$class.withFilter:(Lscala/collection/Iterator;Lscala/Function1;)Lscala/collection/Iterator;
const #618 = Asciz	filter;
const #619 = NameAndType	#618:#594;//  filter:(Lscala/collection/Iterator;Lscala/Function1;)Lscala/collection/Iterator;
const #620 = Method	#124.#619;	//  scala/collection/Iterator$class.filter:(Lscala/collection/Iterator;Lscala/Function1;)Lscala/collection/Iterator;
const #621 = Asciz	flatMap;
const #622 = NameAndType	#621:#594;//  flatMap:(Lscala/collection/Iterator;Lscala/Function1;)Lscala/collection/Iterator;
const #623 = Method	#124.#622;	//  scala/collection/Iterator$class.flatMap:(Lscala/collection/Iterator;Lscala/Function1;)Lscala/collection/Iterator;
const #624 = Asciz	$plus$plus;
const #625 = Asciz	(Lscala/Function0;)Lscala/collection/Iterator;;
const #626 = Asciz	(Lscala/collection/Iterator;Lscala/Function0;)Lscala/collection/Iterator;;
const #627 = NameAndType	#624:#626;//  $plus$plus:(Lscala/collection/Iterator;Lscala/Function0;)Lscala/collection/Iterator;
const #628 = Method	#124.#627;	//  scala/collection/Iterator$class.$plus$plus:(Lscala/collection/Iterator;Lscala/Function0;)Lscala/collection/Iterator;
const #629 = Asciz	map;
const #630 = NameAndType	#629:#594;//  map:(Lscala/collection/Iterator;Lscala/Function1;)Lscala/collection/Iterator;
const #631 = Method	#124.#630;	//  scala/collection/Iterator$class.map:(Lscala/collection/Iterator;Lscala/Function1;)Lscala/collection/Iterator;
const #632 = Asciz	slice;
const #633 = Asciz	(II)Lscala/collection/Iterator;;
const #634 = Asciz	(Lscala/collection/Iterator;II)Lscala/collection/Iterator;;
const #635 = NameAndType	#632:#634;//  slice:(Lscala/collection/Iterator;II)Lscala/collection/Iterator;
const #636 = Method	#124.#635;	//  scala/collection/Iterator$class.slice:(Lscala/collection/Iterator;II)Lscala/collection/Iterator;
const #637 = Asciz	until;
const #638 = Asciz	(Lscala/collection/Iterator;I)Lscala/collection/Iterator;;
const #639 = NameAndType	#341:#638;//  drop:(Lscala/collection/Iterator;I)Lscala/collection/Iterator;
const #640 = Method	#124.#639;	//  scala/collection/Iterator$class.drop:(Lscala/collection/Iterator;I)Lscala/collection/Iterator;
const #641 = Asciz	take;
const #642 = NameAndType	#641:#638;//  take:(Lscala/collection/Iterator;I)Lscala/collection/Iterator;
const #643 = Method	#124.#642;	//  scala/collection/Iterator$class.take:(Lscala/collection/Iterator;I)Lscala/collection/Iterator;
const #644 = Asciz	Ljava/lang/Object;Lscala/collection/Iterator<Ljava/lang/Character;>;Lscala/ScalaObject;;
const #645 = Asciz	ScalaSig;
const #646 = Asciz	InnerClasses;
const #647 = Asciz	scala/io/Source$$anon$1;
const #648 = class	#647;	//  scala/io/Source$$anon$1
const #649 = Asciz	$anon$1;
const #650 = Asciz	scala/io/Source$$anonfun$1;
const #651 = class	#650;	//  scala/io/Source$$anonfun$1
const #652 = Asciz	$anonfun$1;
const #653 = Asciz	Positioner;
const #654 = Asciz	LineIterator;
const #655 = Asciz	scala/collection/Iterator$GroupedIterator;
const #656 = class	#655;	//  scala/collection/Iterator$GroupedIterator
const #657 = Asciz	GroupedIterator;
const #658 = Asciz	$anonfun$spaces$1;
const #659 = Asciz	scala/io/Source$$anonfun$fromFile$2;
const #660 = class	#659;	//  scala/io/Source$$anonfun$fromFile$2
const #661 = Asciz	$anonfun$fromFile$2;
const #662 = Asciz	scala/io/Source$$anonfun$fromFile$1;
const #663 = class	#662;	//  scala/io/Source$$anonfun$fromFile$1
const #664 = Asciz	$anonfun$fromFile$1;
const #665 = Asciz	scala/io/Source$$anonfun$fromIterable$1;
const #666 = class	#665;	//  scala/io/Source$$anonfun$fromIterable$1
const #667 = Asciz	$anonfun$fromIterable$1;
const #668 = Asciz	scala/ScalaObject;
const #669 = class	#668;	//  scala/ScalaObject

{
public static final scala.io.Codec fromURL$default$2(java.net.URL);
  Code:
   Stack=2, Locals=1, Args_size=1
   0:	getstatic	#11; //Field scala/io/Source$.MODULE$:Lscala/io/Source$;
   3:	aload_0
   4:	invokevirtual	#13; //Method scala/io/Source$.fromURL$default$2:(Ljava/net/URL;)Lscala/io/Codec;
   7:	areturn

public static final scala.io.Codec fromURI$default$2(java.net.URI);
  Code:
   Stack=2, Locals=1, Args_size=1
   0:	getstatic	#11; //Field scala/io/Source$.MODULE$:Lscala/io/Source$;
   3:	aload_0
   4:	invokevirtual	#17; //Method scala/io/Source$.fromURI$default$2:(Ljava/net/URI;)Lscala/io/Codec;
   7:	areturn

public static final scala.io.Codec fromFile$default$3(java.io.File, int);
  Code:
   Stack=3, Locals=2, Args_size=2
   0:	getstatic	#11; //Field scala/io/Source$.MODULE$:Lscala/io/Source$;
   3:	aload_0
   4:	iload_1
   5:	invokevirtual	#21; //Method scala/io/Source$.fromFile$default$3:(Ljava/io/File;I)Lscala/io/Codec;
   8:	areturn

public static final int fromFile$default$2();
  Code:
   Stack=1, Locals=0, Args_size=0
   0:	getstatic	#11; //Field scala/io/Source$.MODULE$:Lscala/io/Source$;
   3:	invokevirtual	#25; //Method scala/io/Source$.fromFile$default$2:()I
   6:	ireturn

public static final scala.io.Codec fromPath$default$2(java.lang.String);
  Code:
   Stack=2, Locals=1, Args_size=1
   0:	getstatic	#11; //Field scala/io/Source$.MODULE$:Lscala/io/Source$;
   3:	aload_0
   4:	invokevirtual	#29; //Method scala/io/Source$.fromPath$default$2:(Ljava/lang/String;)Lscala/io/Codec;
   7:	areturn

public static final scala.io.Codec fromBytes$default$2(byte[]);
  Code:
   Stack=2, Locals=1, Args_size=1
   0:	getstatic	#11; //Field scala/io/Source$.MODULE$:Lscala/io/Source$;
   3:	aload_0
   4:	invokevirtual	#33; //Method scala/io/Source$.fromBytes$default$2:([B)Lscala/io/Codec;
   7:	areturn

public static final scala.io.Codec fromInputStream$default$5(java.io.InputStream, int, scala.Function0, scala.Function0);
  Code:
   Stack=5, Locals=4, Args_size=4
   0:	getstatic	#11; //Field scala/io/Source$.MODULE$:Lscala/io/Source$;
   3:	aload_0
   4:	iload_1
   5:	aload_2
   6:	aload_3
   7:	invokevirtual	#37; //Method scala/io/Source$.fromInputStream$default$5:(Ljava/io/InputStream;ILscala/Function0;Lscala/Function0;)Lscala/io/Codec;
   10:	areturn

public static final scala.Function0 fromInputStream$default$4();
  Code:
   Stack=1, Locals=0, Args_size=0
   0:	getstatic	#11; //Field scala/io/Source$.MODULE$:Lscala/io/Source$;
   3:	invokevirtual	#41; //Method scala/io/Source$.fromInputStream$default$4:()Lscala/Function0;
   6:	areturn

public static final scala.Function0 fromInputStream$default$3();
  Code:
   Stack=1, Locals=0, Args_size=0
   0:	getstatic	#11; //Field scala/io/Source$.MODULE$:Lscala/io/Source$;
   3:	invokevirtual	#44; //Method scala/io/Source$.fromInputStream$default$3:()Lscala/Function0;
   6:	areturn

public static final int fromInputStream$default$2();
  Code:
   Stack=1, Locals=0, Args_size=0
   0:	getstatic	#11; //Field scala/io/Source$.MODULE$:Lscala/io/Source$;
   3:	invokevirtual	#47; //Method scala/io/Source$.fromInputStream$default$2:()I
   6:	ireturn

public static final scala.io.Source fromInputStream(java.io.InputStream, int, scala.Function0, scala.Function0, scala.io.Codec);
  Code:
   Stack=6, Locals=5, Args_size=5
   0:	getstatic	#11; //Field scala/io/Source$.MODULE$:Lscala/io/Source$;
   3:	aload_0
   4:	iload_1
   5:	aload_2
   6:	aload_3
   7:	aload	4
   9:	invokevirtual	#51; //Method scala/io/Source$.fromInputStream:(Ljava/io/InputStream;ILscala/Function0;Lscala/Function0;Lscala/io/Codec;)Lscala/io/Source;
   12:	areturn
  Signature: length = 0x2
   00 34 

public static final scala.io.Source fromFile(java.io.File, int, scala.io.Codec);
  Code:
   Stack=4, Locals=3, Args_size=3
   0:	getstatic	#11; //Field scala/io/Source$.MODULE$:Lscala/io/Source$;
   3:	aload_0
   4:	iload_1
   5:	aload_2
   6:	invokevirtual	#57; //Method scala/io/Source$.fromFile:(Ljava/io/File;ILscala/io/Codec;)Lscala/io/Source;
   9:	areturn

public static final scala.io.Source fromURL(java.net.URL, scala.io.Codec);
  Code:
   Stack=3, Locals=2, Args_size=2
   0:	getstatic	#11; //Field scala/io/Source$.MODULE$:Lscala/io/Source$;
   3:	aload_0
   4:	aload_1
   5:	invokevirtual	#61; //Method scala/io/Source$.fromURL:(Ljava/net/URL;Lscala/io/Codec;)Lscala/io/Source;
   8:	areturn

public static final scala.io.Source fromURI(java.net.URI, scala.io.Codec);
  Code:
   Stack=3, Locals=2, Args_size=2
   0:	getstatic	#11; //Field scala/io/Source$.MODULE$:Lscala/io/Source$;
   3:	aload_0
   4:	aload_1
   5:	invokevirtual	#65; //Method scala/io/Source$.fromURI:(Ljava/net/URI;Lscala/io/Codec;)Lscala/io/Source;
   8:	areturn

public static final scala.io.Source fromPath(java.lang.String, scala.io.Codec);
  Code:
   Stack=3, Locals=2, Args_size=2
   0:	getstatic	#11; //Field scala/io/Source$.MODULE$:Lscala/io/Source$;
   3:	aload_0
   4:	aload_1
   5:	invokevirtual	#69; //Method scala/io/Source$.fromPath:(Ljava/lang/String;Lscala/io/Codec;)Lscala/io/Source;
   8:	areturn

public static final scala.io.Source fromRawBytes(byte[]);
  Code:
   Stack=2, Locals=1, Args_size=1
   0:	getstatic	#11; //Field scala/io/Source$.MODULE$:Lscala/io/Source$;
   3:	aload_0
   4:	invokevirtual	#73; //Method scala/io/Source$.fromRawBytes:([B)Lscala/io/Source;
   7:	areturn

public static final scala.io.Source fromBytes(byte[], scala.io.Codec);
  Code:
   Stack=3, Locals=2, Args_size=2
   0:	getstatic	#11; //Field scala/io/Source$.MODULE$:Lscala/io/Source$;
   3:	aload_0
   4:	aload_1
   5:	invokevirtual	#77; //Method scala/io/Source$.fromBytes:([BLscala/io/Codec;)Lscala/io/Source;
   8:	areturn

public static final scala.io.Source fromString(java.lang.String);
  Code:
   Stack=2, Locals=1, Args_size=1
   0:	getstatic	#11; //Field scala/io/Source$.MODULE$:Lscala/io/Source$;
   3:	aload_0
   4:	invokevirtual	#81; //Method scala/io/Source$.fromString:(Ljava/lang/String;)Lscala/io/Source;
   7:	areturn

public static final scala.io.Source fromChars(char[]);
  Code:
   Stack=2, Locals=1, Args_size=1
   0:	getstatic	#11; //Field scala/io/Source$.MODULE$:Lscala/io/Source$;
   3:	aload_0
   4:	invokevirtual	#85; //Method scala/io/Source$.fromChars:([C)Lscala/io/Source;
   7:	areturn

public static final scala.io.Source fromChar(char);
  Code:
   Stack=2, Locals=1, Args_size=1
   0:	getstatic	#11; //Field scala/io/Source$.MODULE$:Lscala/io/Source$;
   3:	iload_0
   4:	invokevirtual	#89; //Method scala/io/Source$.fromChar:(C)Lscala/io/Source;
   7:	areturn

public static final scala.io.Source fromIterable(scala.collection.Iterable);
  Code:
   Stack=2, Locals=1, Args_size=1
   0:	getstatic	#11; //Field scala/io/Source$.MODULE$:Lscala/io/Source$;
   3:	aload_0
   4:	invokevirtual	#93; //Method scala/io/Source$.fromIterable:(Lscala/collection/Iterable;)Lscala/io/Source;
   7:	areturn
  Signature: length = 0x2
   00 5E 

public static final scala.io.Source stdin();
  Code:
   Stack=1, Locals=0, Args_size=0
   0:	getstatic	#11; //Field scala/io/Source$.MODULE$:Lscala/io/Source$;
   3:	invokevirtual	#98; //Method scala/io/Source$.stdin:()Lscala/io/Source;
   6:	areturn

public static final int DefaultBufSize();
  Code:
   Stack=1, Locals=0, Args_size=0
   0:	getstatic	#11; //Field scala/io/Source$.MODULE$:Lscala/io/Source$;
   3:	invokevirtual	#101; //Method scala/io/Source$.DefaultBufSize:()I
   6:	ireturn

public scala.io.Source();
  Code:
   Stack=4, Locals=1, Args_size=1
   0:	aload_0
   1:	invokespecial	#122; //Method java/lang/Object."<init>":()V
   4:	aload_0
   5:	invokestatic	#128; //Method scala/collection/Iterator$class.$init$:(Lscala/collection/Iterator;)V
   8:	aload_0
   9:	ldc	#130; //String 
   11:	putfield	#134; //Field descr:Ljava/lang/String;
   14:	aload_0
   15:	iconst_0
   16:	putfield	#136; //Field nerrors:I
   19:	aload_0
   20:	iconst_0
   21:	putfield	#138; //Field nwarnings:I
   24:	aload_0
   25:	aconst_null
   26:	putfield	#140; //Field resetFunction:Lscala/Function0;
   29:	aload_0
   30:	aconst_null
   31:	putfield	#142; //Field closeFunction:Lscala/Function0;
   34:	aload_0
   35:	new	#144; //class scala/io/Source$Positioner
   38:	dup
   39:	aload_0
   40:	invokespecial	#147; //Method scala/io/Source$Positioner."<init>":(Lscala/io/Source;)V
   43:	putfield	#149; //Field positioner:Lscala/io/Source$Positioner;
   46:	return
  LineNumberTable: 
   line 143: 0
   line 151: 8
   line 153: 14
   line 154: 19
   line 292: 24
   line 293: 29
   line 294: 34


public java.lang.Object next();
  Code:
   Stack=1, Locals=2, Args_size=1
   0:	aload_0
   1:	invokevirtual	#154; //Method next:()C
   4:	istore_1
   5:	iload_1
   6:	invokestatic	#160; //Method scala/runtime/BoxesRunTime.boxToCharacter:(C)Ljava/lang/Character;
   9:	areturn
  LineNumberTable: 
   line 143: 0


public scala.io.Source reset();
  Code:
   Stack=3, Locals=2, Args_size=1
   0:	aload_0
   1:	getfield	#140; //Field resetFunction:Lscala/Function0;
   4:	dup
   5:	astore_1
   6:	ifnull	17
   9:	aload_1
   10:	aconst_null
   11:	invokevirtual	#165; //Method java/lang/Object.equals:(Ljava/lang/Object;)Z
   14:	ifeq	27
   17:	new	#167; //class java/lang/UnsupportedOperationException
   20:	dup
   21:	ldc	#169; //String Source's reset() method was not set.
   23:	invokespecial	#172; //Method java/lang/UnsupportedOperationException."<init>":(Ljava/lang/String;)V
   26:	athrow
   27:	aload_0
   28:	getfield	#140; //Field resetFunction:Lscala/Function0;
   31:	invokeinterface	#177,  1; //InterfaceMethod scala/Function0.apply:()Ljava/lang/Object;
   36:	checkcast	#132; //class scala/io/Source
   39:	areturn
  LineNumberTable: 
   line 321: 0
   line 322: 17
   line 321: 27


public void close();
  Code:
   Stack=2, Locals=2, Args_size=1
   0:	aload_0
   1:	getfield	#142; //Field closeFunction:Lscala/Function0;
   4:	dup
   5:	astore_1
   6:	ifnull	27
   9:	aload_1
   10:	aconst_null
   11:	invokevirtual	#165; //Method java/lang/Object.equals:(Ljava/lang/Object;)Z
   14:	ifne	27
   17:	aload_0
   18:	getfield	#142; //Field closeFunction:Lscala/Function0;
   21:	invokeinterface	#177,  1; //InterfaceMethod scala/Function0.apply:()Ljava/lang/Object;
   26:	pop
   27:	return
  LineNumberTable: 
   line 317: 0


public scala.io.Source withPositioning(boolean);
  Code:
   Stack=4, Locals=2, Args_size=2
   0:	aload_0
   1:	iload_1
   2:	ifeq	16
   5:	new	#144; //class scala/io/Source$Positioner
   8:	dup
   9:	aload_0
   10:	invokespecial	#147; //Method scala/io/Source$Positioner."<init>":(Lscala/io/Source;)V
   13:	goto	20
   16:	aload_0
   17:	invokevirtual	#184; //Method NoPositioner:()Lscala/io/Source$NoPositioner$;
   20:	putfield	#149; //Field positioner:Lscala/io/Source$Positioner;
   23:	aload_0
   24:	areturn
  LineNumberTable: 
   line 311: 0
   line 312: 23

  LocalVariableTable: 
   Start  Length  Slot  Name   Signature
   0      25      0    this       Lscala/io/Source;
   0      25      1    on       Z


public scala.io.Source withDescription(java.lang.String);
  Code:
   Stack=2, Locals=2, Args_size=2
   0:	aload_0
   1:	aload_1
   2:	invokevirtual	#193; //Method descr_$eq:(Ljava/lang/String;)V
   5:	aload_0
   6:	areturn
  LineNumberTable: 
   line 305: 0
   line 306: 5

  LocalVariableTable: 
   Start  Length  Slot  Name   Signature
   0      7      0    this       Lscala/io/Source;
   0      7      1    text       Ljava/lang/String;


public scala.io.Source withClose(scala.Function0);
  Code:
   Stack=2, Locals=2, Args_size=2
   0:	aload_0
   1:	aload_1
   2:	putfield	#142; //Field closeFunction:Lscala/Function0;
   5:	aload_0
   6:	areturn
  LineNumberTable: 
   line 301: 0
   line 302: 5

  LocalVariableTable: 
   Start  Length  Slot  Name   Signature
   0      7      0    this       Lscala/io/Source;
   0      7      1    f       Lscala/Function0;

  Signature: length = 0x2
   00 FFFFFFC6 

public scala.io.Source withReset(scala.Function0);
  Code:
   Stack=2, Locals=2, Args_size=2
   0:	aload_0
   1:	aload_1
   2:	putfield	#140; //Field resetFunction:Lscala/Function0;
   5:	aload_0
   6:	areturn
  LineNumberTable: 
   line 297: 0
   line 298: 5

  LocalVariableTable: 
   Start  Length  Slot  Name   Signature
   0      7      0    this       Lscala/io/Source;
   0      7      1    f       Lscala/Function0;

  Signature: length = 0x2
   00 FFFFFFC8 

public void reportWarning(int, java.lang.String, java.io.PrintStream);
  Code:
   Stack=4, Locals=4, Args_size=4
   0:	aload_0
   1:	aload_0
   2:	invokevirtual	#204; //Method nwarnings:()I
   5:	iconst_1
   6:	iadd
   7:	invokevirtual	#208; //Method nwarnings_$eq:(I)V
   10:	aload_0
   11:	iload_1
   12:	new	#210; //class scala/collection/mutable/StringBuilder
   15:	dup
   16:	invokespecial	#211; //Method scala/collection/mutable/StringBuilder."<init>":()V
   19:	ldc	#213; //String warning! 
   21:	invokevirtual	#217; //Method scala/collection/mutable/StringBuilder.append:(Ljava/lang/Object;)Lscala/collection/mutable/StringBuilder;
   24:	aload_2
   25:	invokevirtual	#217; //Method scala/collection/mutable/StringBuilder.append:(Ljava/lang/Object;)Lscala/collection/mutable/StringBuilder;
   28:	invokevirtual	#221; //Method scala/collection/mutable/StringBuilder.toString:()Ljava/lang/String;
   31:	aload_3
   32:	invokevirtual	#224; //Method report:(ILjava/lang/String;Ljava/io/PrintStream;)V
   35:	return
  LineNumberTable: 
   line 288: 0
   line 289: 10

  LocalVariableTable: 
   Start  Length  Slot  Name   Signature
   0      36      0    this       Lscala/io/Source;
   0      36      1    pos       I
   0      36      2    msg       Ljava/lang/String;
   0      36      3    out       Ljava/io/PrintStream;


public void report(int, java.lang.String, java.io.PrintStream);
  Code:
   Stack=9, Locals=6, Args_size=4
   0:	getstatic	#233; //Field scala/io/Position$.MODULE$:Lscala/io/Position$;
   3:	iload_1
   4:	invokevirtual	#237; //Method scala/io/Position$.line:(I)I
   7:	istore	4
   9:	getstatic	#233; //Field scala/io/Position$.MODULE$:Lscala/io/Position$;
   12:	iload_1
   13:	invokevirtual	#240; //Method scala/io/Position$.column:(I)I
   16:	istore	5
   18:	aload_3
   19:	getstatic	#245; //Field scala/Predef$.MODULE$:Lscala/Predef$;
   22:	ldc	#247; //String %s:%d:%d: %s%s%s^
   24:	invokevirtual	#251; //Method scala/Predef$.augmentString:(Ljava/lang/String;)Lscala/collection/immutable/StringOps;
   27:	getstatic	#245; //Field scala/Predef$.MODULE$:Lscala/Predef$;
   30:	ldc	#252; //int 6
   32:	anewarray	#120; //class java/lang/Object
   35:	dup
   36:	iconst_0
   37:	aload_0
   38:	invokevirtual	#254; //Method descr:()Ljava/lang/String;
   41:	aastore
   42:	dup
   43:	iconst_1
   44:	iload	4
   46:	invokestatic	#258; //Method scala/runtime/BoxesRunTime.boxToInteger:(I)Ljava/lang/Integer;
   49:	aastore
   50:	dup
   51:	iconst_2
   52:	iload	5
   54:	invokestatic	#258; //Method scala/runtime/BoxesRunTime.boxToInteger:(I)Ljava/lang/Integer;
   57:	aastore
   58:	dup
   59:	iconst_3
   60:	aload_2
   61:	aastore
   62:	dup
   63:	iconst_4
   64:	aload_0
   65:	iload	4
   67:	invokevirtual	#262; //Method getLine:(I)Ljava/lang/String;
   70:	aastore
   71:	dup
   72:	iconst_5
   73:	aload_0
   74:	iload	5
   76:	iconst_1
   77:	isub
   78:	invokespecial	#265; //Method spaces:(I)Ljava/lang/String;
   81:	aastore
   82:	invokevirtual	#269; //Method scala/Predef$.genericWrapArray:(Ljava/lang/Object;)Lscala/collection/mutable/WrappedArray;
   85:	invokeinterface	#275,  2; //InterfaceMethod scala/collection/immutable/StringLike.format:(Lscala/collection/Seq;)Ljava/lang/String;
   90:	invokevirtual	#280; //Method java/io/PrintStream.println:(Ljava/lang/String;)V
   93:	return
  LineNumberTable: 
   line 272: 0
   line 273: 9
   line 275: 18

  LocalVariableTable: 
   Start  Length  Slot  Name   Signature
   0      94      0    this       Lscala/io/Source;
   0      94      1    pos       I
   0      94      2    msg       Ljava/lang/String;
   0      94      3    out       Ljava/io/PrintStream;
   9      84      4    line       I
   18      75      5    col       I


public void reportError(int, java.lang.String, java.io.PrintStream);
  Code:
   Stack=4, Locals=4, Args_size=4
   0:	aload_0
   1:	aload_0
   2:	invokevirtual	#302; //Method nerrors:()I
   5:	iconst_1
   6:	iadd
   7:	invokevirtual	#305; //Method nerrors_$eq:(I)V
   10:	aload_0
   11:	iload_1
   12:	aload_2
   13:	aload_3
   14:	invokevirtual	#224; //Method report:(ILjava/lang/String;Ljava/io/PrintStream;)V
   17:	return
  LineNumberTable: 
   line 261: 0
   line 262: 10

  LocalVariableTable: 
   Start  Length  Slot  Name   Signature
   0      18      0    this       Lscala/io/Source;
   0      18      1    pos       I
   0      18      2    msg       Ljava/lang/String;
   0      18      3    out       Ljava/io/PrintStream;


public int pos();
  Code:
   Stack=1, Locals=1, Args_size=1
   0:	aload_0
   1:	getfield	#149; //Field positioner:Lscala/io/Source$Positioner;
   4:	invokevirtual	#307; //Method scala/io/Source$Positioner.pos:()I
   7:	ireturn
  LineNumberTable: 
   line 248: 0


public char ch();
  Code:
   Stack=1, Locals=1, Args_size=1
   0:	aload_0
   1:	getfield	#149; //Field positioner:Lscala/io/Source$Positioner;
   4:	invokevirtual	#310; //Method scala/io/Source$Positioner.ch:()C
   7:	ireturn
  LineNumberTable: 
   line 247: 0


public final scala.io.Source$NoPositioner$ NoPositioner();
  Code:
   Stack=4, Locals=1, Args_size=1
   0:	aload_0
   1:	getfield	#312; //Field NoPositioner$module:Lscala/io/Source$NoPositioner$;
   4:	ifnonnull	19
   7:	aload_0
   8:	new	#314; //class scala/io/Source$NoPositioner$
   11:	dup
   12:	aload_0
   13:	invokespecial	#315; //Method scala/io/Source$NoPositioner$."<init>":(Lscala/io/Source;)V
   16:	putfield	#312; //Field NoPositioner$module:Lscala/io/Source$NoPositioner$;
   19:	aload_0
   20:	getfield	#312; //Field NoPositioner$module:Lscala/io/Source$NoPositioner$;
   23:	areturn
  LineNumberTable: 
   line 244: 0


public char next();
  Code:
   Stack=1, Locals=1, Args_size=1
   0:	aload_0
   1:	getfield	#149; //Field positioner:Lscala/io/Source$Positioner;
   4:	invokevirtual	#316; //Method scala/io/Source$Positioner.next:()C
   7:	ireturn
  LineNumberTable: 
   line 213: 0


public boolean hasNext();
  Code:
   Stack=1, Locals=1, Args_size=1
   0:	aload_0
   1:	invokevirtual	#322; //Method iter:()Lscala/collection/Iterator;
   4:	invokeinterface	#326,  1; //InterfaceMethod scala/collection/Iterator.hasNext:()Z
   9:	ireturn
  LineNumberTable: 
   line 209: 0


public scala.collection.Iterator getLines(java.lang.String);
  Code:
   Stack=4, Locals=2, Args_size=2
   0:	new	#330; //class scala/io/Source$LineIterator
   3:	dup
   4:	aload_0
   5:	aload_1
   6:	invokespecial	#333; //Method scala/io/Source$LineIterator."<init>":(Lscala/io/Source;Ljava/lang/String;)V
   9:	areturn
  LineNumberTable: 
   line 205: 0

  LocalVariableTable: 
   Start  Length  Slot  Name   Signature
   0      10      0    this       Lscala/io/Source;
   0      10      1    separator       Ljava/lang/String;

  Signature: length = 0x2
   01 4F 

public java.lang.String getLine(int);
  Code:
   Stack=3, Locals=2, Args_size=2
   0:	aload_0
   1:	aload_0
   2:	invokevirtual	#338; //Method getLines$default$1:()Ljava/lang/String;
   5:	invokevirtual	#340; //Method getLines:(Ljava/lang/String;)Lscala/collection/Iterator;
   8:	iload_1
   9:	iconst_1
   10:	isub
   11:	invokeinterface	#344,  2; //InterfaceMethod scala/collection/Iterator.drop:(I)Lscala/collection/Iterator;
   16:	invokeinterface	#346,  1; //InterfaceMethod scala/collection/Iterator.next:()Ljava/lang/Object;
   21:	checkcast	#348; //class java/lang/String
   24:	areturn
  LineNumberTable: 
   line 163: 0

  LocalVariableTable: 
   Start  Length  Slot  Name   Signature
   0      25      0    this       Lscala/io/Source;
   0      25      1    line       I


public void nwarnings_$eq(int);
  Code:
   Stack=2, Locals=2, Args_size=2
   0:	aload_0
   1:	iload_1
   2:	putfield	#138; //Field nwarnings:I
   5:	return
  LineNumberTable: 
   line 154: 0


public int nwarnings();
  Code:
   Stack=1, Locals=1, Args_size=1
   0:	aload_0
   1:	getfield	#138; //Field nwarnings:I
   4:	ireturn
  LineNumberTable: 
   line 154: 0


public void nerrors_$eq(int);
  Code:
   Stack=2, Locals=2, Args_size=2
   0:	aload_0
   1:	iload_1
   2:	putfield	#136; //Field nerrors:I
   5:	return
  LineNumberTable: 
   line 153: 0


public int nerrors();
  Code:
   Stack=1, Locals=1, Args_size=1
   0:	aload_0
   1:	getfield	#136; //Field nerrors:I
   4:	ireturn
  LineNumberTable: 
   line 153: 0


public void descr_$eq(java.lang.String);
  Code:
   Stack=2, Locals=2, Args_size=2
   0:	aload_0
   1:	aload_1
   2:	putfield	#134; //Field descr:Ljava/lang/String;
   5:	return
  LineNumberTable: 
   line 151: 0


public java.lang.String descr();
  Code:
   Stack=1, Locals=1, Args_size=1
   0:	aload_0
   1:	getfield	#134; //Field descr:Ljava/lang/String;
   4:	areturn
  LineNumberTable: 
   line 151: 0


public abstract scala.collection.Iterator iter();
  Signature: length = 0x2
   01 5D 

public java.lang.String getLines$default$1();
  Code:
   Stack=1, Locals=1, Args_size=1
   0:	getstatic	#354; //Field scala/compat/Platform$.MODULE$:Lscala/compat/Platform$;
   3:	invokevirtual	#357; //Method scala/compat/Platform$.EOL:()Ljava/lang/String;
   6:	areturn
  LineNumberTable: 
   line 204: 0


public java.io.PrintStream reportError$default$3();
  Code:
   Stack=1, Locals=1, Args_size=1
   0:	getstatic	#364; //Field scala/Console$.MODULE$:Lscala/Console$;
   3:	invokevirtual	#367; //Method scala/Console$.err:()Ljava/io/PrintStream;
   6:	areturn
  LineNumberTable: 
   line 259: 0


public java.io.PrintStream reportWarning$default$3();
  Code:
   Stack=1, Locals=1, Args_size=1
   0:	getstatic	#364; //Field scala/Console$.MODULE$:Lscala/Console$;
   3:	invokevirtual	#370; //Method scala/Console$.out:()Ljava/io/PrintStream;
   6:	areturn
  LineNumberTable: 
   line 286: 0


public int sliding$default$2();
  Code:
   Stack=1, Locals=1, Args_size=1
   0:	aload_0
   1:	invokestatic	#374; //Method scala/collection/Iterator$class.sliding$default$2:(Lscala/collection/Iterator;)I
   4:	ireturn
  LineNumberTable: 
   line 143: 0


public void readInto(java.lang.Object);
  Code:
   Stack=2, Locals=2, Args_size=2
   0:	aload_0
   1:	aload_1
   2:	invokestatic	#379; //Method scala/collection/Iterator$class.readInto:(Lscala/collection/Iterator;Ljava/lang/Object;)V
   5:	return
  LineNumberTable: 
   line 143: 0

  LocalVariableTable: 
   Start  Length  Slot  Name   Signature
   0      6      0    this       Lscala/io/Source;
   0      6      1    xs       Ljava/lang/Object;

  Deprecated: true

public void readInto(java.lang.Object, int);
  Code:
   Stack=3, Locals=3, Args_size=3
   0:	aload_0
   1:	aload_1
   2:	iload_2
   3:	invokestatic	#386; //Method scala/collection/Iterator$class.readInto:(Lscala/collection/Iterator;Ljava/lang/Object;I)V
   6:	return
  LineNumberTable: 
   line 143: 0

  LocalVariableTable: 
   Start  Length  Slot  Name   Signature
   0      7      0    this       Lscala/io/Source;
   0      7      1    xs       Ljava/lang/Object;
   0      7      2    start       I

  Deprecated: true

public void readInto(java.lang.Object, int, int);
  Code:
   Stack=4, Locals=4, Args_size=4
   0:	aload_0
   1:	aload_1
   2:	iload_2
   3:	iload_3
   4:	invokestatic	#391; //Method scala/collection/Iterator$class.readInto:(Lscala/collection/Iterator;Ljava/lang/Object;II)V
   7:	return
  LineNumberTable: 
   line 143: 0

  LocalVariableTable: 
   Start  Length  Slot  Name   Signature
   0      8      0    this       Lscala/io/Source;
   0      8      1    xs       Ljava/lang/Object;
   0      8      2    start       I
   0      8      3    sz       I

  Deprecated: true

public java.lang.Object counted();
  Code:
   Stack=1, Locals=1, Args_size=1
   0:	aload_0
   1:	invokestatic	#396; //Method scala/collection/Iterator$class.counted:(Lscala/collection/Iterator;)Ljava/lang/Object;
   4:	areturn
  LineNumberTable: 
   line 143: 0

  Deprecated: true

public scala.collection.Seq collect();
  Code:
   Stack=1, Locals=1, Args_size=1
   0:	aload_0
   1:	invokestatic	#401; //Method scala/collection/Iterator$class.collect:(Lscala/collection/Iterator;)Lscala/collection/Seq;
   4:	areturn
  LineNumberTable: 
   line 143: 0

  Deprecated: true

public int findIndexOf(scala.Function1);
  Code:
   Stack=2, Locals=2, Args_size=2
   0:	aload_0
   1:	aload_1
   2:	invokestatic	#406; //Method scala/collection/Iterator$class.findIndexOf:(Lscala/collection/Iterator;Lscala/Function1;)I
   5:	ireturn
  LineNumberTable: 
   line 143: 0

  LocalVariableTable: 
   Start  Length  Slot  Name   Signature
   0      6      0    this       Lscala/io/Source;
   0      6      1    p       Lscala/Function1;

  Deprecated: true

public scala.collection.Iterator append(scala.collection.Iterator);
  Code:
   Stack=2, Locals=2, Args_size=2
   0:	aload_0
   1:	aload_1
   2:	invokestatic	#412; //Method scala/collection/Iterator$class.append:(Lscala/collection/Iterator;Lscala/collection/Iterator;)Lscala/collection/Iterator;
   5:	areturn
  LineNumberTable: 
   line 143: 0

  LocalVariableTable: 
   Start  Length  Slot  Name   Signature
   0      6      0    this       Lscala/io/Source;
   0      6      1    that       Lscala/collection/Iterator;

  Deprecated: true

public java.lang.String toString();
  Code:
   Stack=1, Locals=1, Args_size=1
   0:	aload_0
   1:	invokestatic	#417; //Method scala/collection/Iterator$class.toString:(Lscala/collection/Iterator;)Ljava/lang/String;
   4:	areturn
  LineNumberTable: 
   line 143: 0


public scala.collection.mutable.StringBuilder addString(scala.collection.mutable.StringBuilder);
  Code:
   Stack=2, Locals=2, Args_size=2
   0:	aload_0
   1:	aload_1
   2:	invokestatic	#422; //Method scala/collection/Iterator$class.addString:(Lscala/collection/Iterator;Lscala/collection/mutable/StringBuilder;)Lscala/collection/mutable/StringBuilder;
   5:	areturn
  LineNumberTable: 
   line 143: 0

  LocalVariableTable: 
   Start  Length  Slot  Name   Signature
   0      6      0    this       Lscala/io/Source;
   0      6      1    buf       Lscala/collection/mutable/StringBuilder;


public scala.collection.mutable.StringBuilder addString(scala.collection.mutable.StringBuilder, java.lang.String);
  Code:
   Stack=3, Locals=3, Args_size=3
   0:	aload_0
   1:	aload_1
   2:	aload_2
   3:	invokestatic	#428; //Method scala/collection/Iterator$class.addString:(Lscala/collection/Iterator;Lscala/collection/mutable/StringBuilder;Ljava/lang/String;)Lscala/collection/mutable/StringBuilder;
   6:	areturn
  LineNumberTable: 
   line 143: 0

  LocalVariableTable: 
   Start  Length  Slot  Name   Signature
   0      7      0    this       Lscala/io/Source;
   0      7      1    buf       Lscala/collection/mutable/StringBuilder;
   0      7      2    sep       Ljava/lang/String;


public scala.collection.mutable.StringBuilder addString(scala.collection.mutable.StringBuilder, java.lang.String, java.lang.String, java.lang.String);
  Code:
   Stack=5, Locals=5, Args_size=5
   0:	aload_0
   1:	aload_1
   2:	aload_2
   3:	aload_3
   4:	aload	4
   6:	invokestatic	#433; //Method scala/collection/Iterator$class.addString:(Lscala/collection/Iterator;Lscala/collection/mutable/StringBuilder;Ljava/lang/String;Ljava/lang/String;Ljava/lang/String;)Lscala/collection/mutable/StringBuilder;
   9:	areturn
  LineNumberTable: 
   line 143: 0

  LocalVariableTable: 
   Start  Length  Slot  Name   Signature
   0      10      0    this       Lscala/io/Source;
   0      10      1    buf       Lscala/collection/mutable/StringBuilder;
   0      10      2    start       Ljava/lang/String;
   0      10      3    sep       Ljava/lang/String;
   0      10      4    end       Ljava/lang/String;


public java.lang.String mkString();
  Code:
   Stack=1, Locals=1, Args_size=1
   0:	aload_0
   1:	invokestatic	#436; //Method scala/collection/Iterator$class.mkString:(Lscala/collection/Iterator;)Ljava/lang/String;
   4:	areturn
  LineNumberTable: 
   line 143: 0


public java.lang.String mkString(java.lang.String);
  Code:
   Stack=2, Locals=2, Args_size=2
   0:	aload_0
   1:	aload_1
   2:	invokestatic	#440; //Method scala/collection/Iterator$class.mkString:(Lscala/collection/Iterator;Ljava/lang/String;)Ljava/lang/String;
   5:	areturn
  LineNumberTable: 
   line 143: 0

  LocalVariableTable: 
   Start  Length  Slot  Name   Signature
   0      6      0    this       Lscala/io/Source;
   0      6      1    sep       Ljava/lang/String;


public java.lang.String mkString(java.lang.String, java.lang.String, java.lang.String);
  Code:
   Stack=4, Locals=4, Args_size=4
   0:	aload_0
   1:	aload_1
   2:	aload_2
   3:	aload_3
   4:	invokestatic	#444; //Method scala/collection/Iterator$class.mkString:(Lscala/collection/Iterator;Ljava/lang/String;Ljava/lang/String;Ljava/lang/String;)Ljava/lang/String;
   7:	areturn
  LineNumberTable: 
   line 143: 0

  LocalVariableTable: 
   Start  Length  Slot  Name   Signature
   0      8      0    this       Lscala/io/Source;
   0      8      1    start       Ljava/lang/String;
   0      8      2    sep       Ljava/lang/String;
   0      8      3    end       Ljava/lang/String;


public boolean sameElements(scala.collection.Iterator);
  Code:
   Stack=2, Locals=2, Args_size=2
   0:	aload_0
   1:	aload_1
   2:	invokestatic	#449; //Method scala/collection/Iterator$class.sameElements:(Lscala/collection/Iterator;Lscala/collection/Iterator;)Z
   5:	ireturn
  LineNumberTable: 
   line 143: 0

  LocalVariableTable: 
   Start  Length  Slot  Name   Signature
   0      6      0    this       Lscala/io/Source;
   0      6      1    that       Lscala/collection/Iterator;


public scala.collection.Seq toSeq();
  Code:
   Stack=1, Locals=1, Args_size=1
   0:	aload_0
   1:	invokestatic	#452; //Method scala/collection/Iterator$class.toSeq:(Lscala/collection/Iterator;)Lscala/collection/Seq;
   4:	areturn
  LineNumberTable: 
   line 143: 0


public scala.collection.immutable.Stream toStream();
  Code:
   Stack=1, Locals=1, Args_size=1
   0:	aload_0
   1:	invokestatic	#457; //Method scala/collection/Iterator$class.toStream:(Lscala/collection/Iterator;)Lscala/collection/immutable/Stream;
   4:	areturn
  LineNumberTable: 
   line 143: 0


public scala.collection.immutable.List toList();
  Code:
   Stack=1, Locals=1, Args_size=1
   0:	aload_0
   1:	invokestatic	#462; //Method scala/collection/Iterator$class.toList:(Lscala/collection/Iterator;)Lscala/collection/immutable/List;
   4:	areturn
  LineNumberTable: 
   line 143: 0


public void copyToBuffer(scala.collection.mutable.Buffer);
  Code:
   Stack=2, Locals=2, Args_size=2
   0:	aload_0
   1:	aload_1
   2:	invokestatic	#467; //Method scala/collection/Iterator$class.copyToBuffer:(Lscala/collection/Iterator;Lscala/collection/mutable/Buffer;)V
   5:	return
  LineNumberTable: 
   line 143: 0

  LocalVariableTable: 
   Start  Length  Slot  Name   Signature
   0      6      0    this       Lscala/io/Source;
   0      6      1    dest       Lscala/collection/mutable/Buffer;


public void copyToArray(java.lang.Object);
  Code:
   Stack=2, Locals=2, Args_size=2
   0:	aload_0
   1:	aload_1
   2:	invokestatic	#472; //Method scala/collection/Iterator$class.copyToArray:(Lscala/collection/Iterator;Ljava/lang/Object;)V
   5:	return
  LineNumberTable: 
   line 143: 0

  LocalVariableTable: 
   Start  Length  Slot  Name   Signature
   0      6      0    this       Lscala/io/Source;
   0      6      1    xs       Ljava/lang/Object;


public void copyToArray(java.lang.Object, int);
  Code:
   Stack=3, Locals=3, Args_size=3
   0:	aload_0
   1:	aload_1
   2:	iload_2
   3:	invokestatic	#474; //Method scala/collection/Iterator$class.copyToArray:(Lscala/collection/Iterator;Ljava/lang/Object;I)V
   6:	return
  LineNumberTable: 
   line 143: 0

  LocalVariableTable: 
   Start  Length  Slot  Name   Signature
   0      7      0    this       Lscala/io/Source;
   0      7      1    xs       Ljava/lang/Object;
   0      7      2    start       I


public void copyToArray(java.lang.Object, int, int);
  Code:
   Stack=4, Locals=4, Args_size=4
   0:	aload_0
   1:	aload_1
   2:	iload_2
   3:	iload_3
   4:	invokestatic	#476; //Method scala/collection/Iterator$class.copyToArray:(Lscala/collection/Iterator;Ljava/lang/Object;II)V
   7:	return
  LineNumberTable: 
   line 143: 0

  LocalVariableTable: 
   Start  Length  Slot  Name   Signature
   0      8      0    this       Lscala/io/Source;
   0      8      1    xs       Ljava/lang/Object;
   0      8      2    start       I
   0      8      3    len       I


public java.lang.Object patch(int, scala.collection.Iterator, int);
  Code:
   Stack=4, Locals=4, Args_size=4
   0:	aload_0
   1:	iload_1
   2:	aload_2
   3:	iload_3
   4:	invokestatic	#482; //Method scala/collection/Iterator$class.patch:(Lscala/collection/Iterator;ILscala/collection/Iterator;I)Ljava/lang/Object;
   7:	areturn
  LineNumberTable: 
   line 143: 0

  LocalVariableTable: 
   Start  Length  Slot  Name   Signature
   0      8      0    this       Lscala/io/Source;
   0      8      1    from       I
   0      8      2    patchElems       Lscala/collection/Iterator;
   0      8      3    replaced       I


public scala.Tuple2 duplicate();
  Code:
   Stack=1, Locals=1, Args_size=1
   0:	aload_0
   1:	invokestatic	#490; //Method scala/collection/Iterator$class.duplicate:(Lscala/collection/Iterator;)Lscala/Tuple2;
   4:	areturn
  LineNumberTable: 
   line 143: 0


public int length();
  Code:
   Stack=1, Locals=1, Args_size=1
   0:	aload_0
   1:	invokestatic	#493; //Method scala/collection/Iterator$class.length:(Lscala/collection/Iterator;)I
   4:	ireturn
  LineNumberTable: 
   line 143: 0


public scala.collection.Iterator$GroupedIterator sliding(int, int);
  Code:
   Stack=3, Locals=3, Args_size=3
   0:	aload_0
   1:	iload_1
   2:	iload_2
   3:	invokestatic	#498; //Method scala/collection/Iterator$class.sliding:(Lscala/collection/Iterator;II)Lscala/collection/Iterator$GroupedIterator;
   6:	areturn
  LineNumberTable: 
   line 143: 0

  LocalVariableTable: 
   Start  Length  Slot  Name   Signature
   0      7      0    this       Lscala/io/Source;
   0      7      1    size       I
   0      7      2    step       I

  Signature: length = 0x2
   01 FFFFFFEF 

public scala.collection.Iterator$GroupedIterator grouped(int);
  Code:
   Stack=2, Locals=2, Args_size=2
   0:	aload_0
   1:	iload_1
   2:	invokestatic	#505; //Method scala/collection/Iterator$class.grouped:(Lscala/collection/Iterator;I)Lscala/collection/Iterator$GroupedIterator;
   5:	areturn
  LineNumberTable: 
   line 143: 0

  LocalVariableTable: 
   Start  Length  Slot  Name   Signature
   0      6      0    this       Lscala/io/Source;
   0      6      1    size       I

  Signature: length = 0x2
   01 FFFFFFF6 

public java.lang.Object buffered();
  Code:
   Stack=1, Locals=1, Args_size=1
   0:	aload_0
   1:	invokestatic	#508; //Method scala/collection/Iterator$class.buffered:(Lscala/collection/Iterator;)Ljava/lang/Object;
   4:	areturn
  LineNumberTable: 
   line 143: 0


public scala.Option reduceRightOption(scala.Function2);
  Code:
   Stack=2, Locals=2, Args_size=2
   0:	aload_0
   1:	aload_1
   2:	invokestatic	#513; //Method scala/collection/Iterator$class.reduceRightOption:(Lscala/collection/Iterator;Lscala/Function2;)Lscala/Option;
   5:	areturn
  LineNumberTable: 
   line 143: 0

  LocalVariableTable: 
   Start  Length  Slot  Name   Signature
   0      6      0    this       Lscala/io/Source;
   0      6      1    op       Lscala/Function2;


public scala.Option reduceLeftOption(scala.Function2);
  Code:
   Stack=2, Locals=2, Args_size=2
   0:	aload_0
   1:	aload_1
   2:	invokestatic	#518; //Method scala/collection/Iterator$class.reduceLeftOption:(Lscala/collection/Iterator;Lscala/Function2;)Lscala/Option;
   5:	areturn
  LineNumberTable: 
   line 143: 0

  LocalVariableTable: 
   Start  Length  Slot  Name   Signature
   0      6      0    this       Lscala/io/Source;
   0      6      1    op       Lscala/Function2;


public java.lang.Object reduceRight(scala.Function2);
  Code:
   Stack=2, Locals=2, Args_size=2
   0:	aload_0
   1:	aload_1
   2:	invokestatic	#523; //Method scala/collection/Iterator$class.reduceRight:(Lscala/collection/Iterator;Lscala/Function2;)Ljava/lang/Object;
   5:	areturn
  LineNumberTable: 
   line 143: 0

  LocalVariableTable: 
   Start  Length  Slot  Name   Signature
   0      6      0    this       Lscala/io/Source;
   0      6      1    op       Lscala/Function2;


public java.lang.Object reduceLeft(scala.Function2);
  Code:
   Stack=2, Locals=2, Args_size=2
   0:	aload_0
   1:	aload_1
   2:	invokestatic	#526; //Method scala/collection/Iterator$class.reduceLeft:(Lscala/collection/Iterator;Lscala/Function2;)Ljava/lang/Object;
   5:	areturn
  LineNumberTable: 
   line 143: 0

  LocalVariableTable: 
   Start  Length  Slot  Name   Signature
   0      6      0    this       Lscala/io/Source;
   0      6      1    op       Lscala/Function2;


public java.lang.Object $colon$bslash(java.lang.Object, scala.Function2);
  Code:
   Stack=3, Locals=3, Args_size=3
   0:	aload_0
   1:	aload_1
   2:	aload_2
   3:	invokestatic	#531; //Method scala/collection/Iterator$class.$colon$bslash:(Lscala/collection/Iterator;Ljava/lang/Object;Lscala/Function2;)Ljava/lang/Object;
   6:	areturn
  LineNumberTable: 
   line 143: 0

  LocalVariableTable: 
   Start  Length  Slot  Name   Signature
   0      7      0    this       Lscala/io/Source;
   0      7      1    z       Ljava/lang/Object;
   0      7      2    op       Lscala/Function2;


public java.lang.Object $div$colon(java.lang.Object, scala.Function2);
  Code:
   Stack=3, Locals=3, Args_size=3
   0:	aload_0
   1:	aload_1
   2:	aload_2
   3:	invokestatic	#535; //Method scala/collection/Iterator$class.$div$colon:(Lscala/collection/Iterator;Ljava/lang/Object;Lscala/Function2;)Ljava/lang/Object;
   6:	areturn
  LineNumberTable: 
   line 143: 0

  LocalVariableTable: 
   Start  Length  Slot  Name   Signature
   0      7      0    this       Lscala/io/Source;
   0      7      1    z       Ljava/lang/Object;
   0      7      2    op       Lscala/Function2;


public java.lang.Object foldRight(java.lang.Object, scala.Function2);
  Code:
   Stack=3, Locals=3, Args_size=3
   0:	aload_0
   1:	aload_1
   2:	aload_2
   3:	invokestatic	#538; //Method scala/collection/Iterator$class.foldRight:(Lscala/collection/Iterator;Ljava/lang/Object;Lscala/Function2;)Ljava/lang/Object;
   6:	areturn
  LineNumberTable: 
   line 143: 0

  LocalVariableTable: 
   Start  Length  Slot  Name   Signature
   0      7      0    this       Lscala/io/Source;
   0      7      1    z       Ljava/lang/Object;
   0      7      2    op       Lscala/Function2;


public java.lang.Object foldLeft(java.lang.Object, scala.Function2);
  Code:
   Stack=3, Locals=3, Args_size=3
   0:	aload_0
   1:	aload_1
   2:	aload_2
   3:	invokestatic	#541; //Method scala/collection/Iterator$class.foldLeft:(Lscala/collection/Iterator;Ljava/lang/Object;Lscala/Function2;)Ljava/lang/Object;
   6:	areturn
  LineNumberTable: 
   line 143: 0

  LocalVariableTable: 
   Start  Length  Slot  Name   Signature
   0      7      0    this       Lscala/io/Source;
   0      7      1    z       Ljava/lang/Object;
   0      7      2    op       Lscala/Function2;


public int indexOf(java.lang.Object);
  Code:
   Stack=2, Locals=2, Args_size=2
   0:	aload_0
   1:	aload_1
   2:	invokestatic	#546; //Method scala/collection/Iterator$class.indexOf:(Lscala/collection/Iterator;Ljava/lang/Object;)I
   5:	ireturn
  LineNumberTable: 
   line 143: 0

  LocalVariableTable: 
   Start  Length  Slot  Name   Signature
   0      6      0    this       Lscala/io/Source;
   0      6      1    elem       Ljava/lang/Object;


public int indexWhere(scala.Function1);
  Code:
   Stack=2, Locals=2, Args_size=2
   0:	aload_0
   1:	aload_1
   2:	invokestatic	#550; //Method scala/collection/Iterator$class.indexWhere:(Lscala/collection/Iterator;Lscala/Function1;)I
   5:	ireturn
  LineNumberTable: 
   line 143: 0

  LocalVariableTable: 
   Start  Length  Slot  Name   Signature
   0      6      0    this       Lscala/io/Source;
   0      6      1    p       Lscala/Function1;


public scala.Option find(scala.Function1);
  Code:
   Stack=2, Locals=2, Args_size=2
   0:	aload_0
   1:	aload_1
   2:	invokestatic	#555; //Method scala/collection/Iterator$class.find:(Lscala/collection/Iterator;Lscala/Function1;)Lscala/Option;
   5:	areturn
  LineNumberTable: 
   line 143: 0

  LocalVariableTable: 
   Start  Length  Slot  Name   Signature
   0      6      0    this       Lscala/io/Source;
   0      6      1    p       Lscala/Function1;


public boolean contains(java.lang.Object);
  Code:
   Stack=2, Locals=2, Args_size=2
   0:	aload_0
   1:	aload_1
   2:	invokestatic	#559; //Method scala/collection/Iterator$class.contains:(Lscala/collection/Iterator;Ljava/lang/Object;)Z
   5:	ireturn
  LineNumberTable: 
   line 143: 0

  LocalVariableTable: 
   Start  Length  Slot  Name   Signature
   0      6      0    this       Lscala/io/Source;
   0      6      1    elem       Ljava/lang/Object;


public boolean exists(scala.Function1);
  Code:
   Stack=2, Locals=2, Args_size=2
   0:	aload_0
   1:	aload_1
   2:	invokestatic	#564; //Method scala/collection/Iterator$class.exists:(Lscala/collection/Iterator;Lscala/Function1;)Z
   5:	ireturn
  LineNumberTable: 
   line 143: 0

  LocalVariableTable: 
   Start  Length  Slot  Name   Signature
   0      6      0    this       Lscala/io/Source;
   0      6      1    p       Lscala/Function1;


public boolean forall(scala.Function1);
  Code:
   Stack=2, Locals=2, Args_size=2
   0:	aload_0
   1:	aload_1
   2:	invokestatic	#567; //Method scala/collection/Iterator$class.forall:(Lscala/collection/Iterator;Lscala/Function1;)Z
   5:	ireturn
  LineNumberTable: 
   line 143: 0

  LocalVariableTable: 
   Start  Length  Slot  Name   Signature
   0      6      0    this       Lscala/io/Source;
   0      6      1    p       Lscala/Function1;


public void foreach(scala.Function1);
  Code:
   Stack=2, Locals=2, Args_size=2
   0:	aload_0
   1:	aload_1
   2:	invokestatic	#572; //Method scala/collection/Iterator$class.foreach:(Lscala/collection/Iterator;Lscala/Function1;)V
   5:	return
  LineNumberTable: 
   line 143: 0

  LocalVariableTable: 
   Start  Length  Slot  Name   Signature
   0      6      0    this       Lscala/io/Source;
   0      6      1    f       Lscala/Function1;


public java.lang.Object zipAll(scala.collection.Iterator, java.lang.Object, java.lang.Object);
  Code:
   Stack=4, Locals=4, Args_size=4
   0:	aload_0
   1:	aload_1
   2:	aload_2
   3:	aload_3
   4:	invokestatic	#577; //Method scala/collection/Iterator$class.zipAll:(Lscala/collection/Iterator;Lscala/collection/Iterator;Ljava/lang/Object;Ljava/lang/Object;)Ljava/lang/Object;
   7:	areturn
  LineNumberTable: 
   line 143: 0

  LocalVariableTable: 
   Start  Length  Slot  Name   Signature
   0      8      0    this       Lscala/io/Source;
   0      8      1    that       Lscala/collection/Iterator;
   0      8      2    thisElem       Ljava/lang/Object;
   0      8      3    thatElem       Ljava/lang/Object;


public java.lang.Object zipWithIndex();
  Code:
   Stack=1, Locals=1, Args_size=1
   0:	aload_0
   1:	invokestatic	#582; //Method scala/collection/Iterator$class.zipWithIndex:(Lscala/collection/Iterator;)Ljava/lang/Object;
   4:	areturn
  LineNumberTable: 
   line 143: 0


public java.lang.Object padTo(int, java.lang.Object);
  Code:
   Stack=3, Locals=3, Args_size=3
   0:	aload_0
   1:	iload_1
   2:	aload_2
   3:	invokestatic	#587; //Method scala/collection/Iterator$class.padTo:(Lscala/collection/Iterator;ILjava/lang/Object;)Ljava/lang/Object;
   6:	areturn
  LineNumberTable: 
   line 143: 0

  LocalVariableTable: 
   Start  Length  Slot  Name   Signature
   0      7      0    this       Lscala/io/Source;
   0      7      1    len       I
   0      7      2    elem       Ljava/lang/Object;


public java.lang.Object zip(scala.collection.Iterator);
  Code:
   Stack=2, Locals=2, Args_size=2
   0:	aload_0
   1:	aload_1
   2:	invokestatic	#591; //Method scala/collection/Iterator$class.zip:(Lscala/collection/Iterator;Lscala/collection/Iterator;)Ljava/lang/Object;
   5:	areturn
  LineNumberTable: 
   line 143: 0

  LocalVariableTable: 
   Start  Length  Slot  Name   Signature
   0      6      0    this       Lscala/io/Source;
   0      6      1    that       Lscala/collection/Iterator;


public scala.collection.Iterator dropWhile(scala.Function1);
  Code:
   Stack=2, Locals=2, Args_size=2
   0:	aload_0
   1:	aload_1
   2:	invokestatic	#596; //Method scala/collection/Iterator$class.dropWhile:(Lscala/collection/Iterator;Lscala/Function1;)Lscala/collection/Iterator;
   5:	areturn
  LineNumberTable: 
   line 143: 0

  LocalVariableTable: 
   Start  Length  Slot  Name   Signature
   0      6      0    this       Lscala/io/Source;
   0      6      1    p       Lscala/Function1;


public scala.Tuple2 partition(scala.Function1);
  Code:
   Stack=2, Locals=2, Args_size=2
   0:	aload_0
   1:	aload_1
   2:	invokestatic	#601; //Method scala/collection/Iterator$class.partition:(Lscala/collection/Iterator;Lscala/Function1;)Lscala/Tuple2;
   5:	areturn
  LineNumberTable: 
   line 143: 0

  LocalVariableTable: 
   Start  Length  Slot  Name   Signature
   0      6      0    this       Lscala/io/Source;
   0      6      1    p       Lscala/Function1;


public scala.collection.Iterator takeWhile(scala.Function1);
  Code:
   Stack=2, Locals=2, Args_size=2
   0:	aload_0
   1:	aload_1
   2:	invokestatic	#604; //Method scala/collection/Iterator$class.takeWhile:(Lscala/collection/Iterator;Lscala/Function1;)Lscala/collection/Iterator;
   5:	areturn
  LineNumberTable: 
   line 143: 0

  LocalVariableTable: 
   Start  Length  Slot  Name   Signature
   0      6      0    this       Lscala/io/Source;
   0      6      1    p       Lscala/Function1;


public scala.collection.Iterator partialMap(scala.PartialFunction);
  Code:
   Stack=2, Locals=2, Args_size=2
   0:	aload_0
   1:	aload_1
   2:	invokestatic	#609; //Method scala/collection/Iterator$class.partialMap:(Lscala/collection/Iterator;Lscala/PartialFunction;)Lscala/collection/Iterator;
   5:	areturn
  LineNumberTable: 
   line 143: 0

  LocalVariableTable: 
   Start  Length  Slot  Name   Signature
   0      6      0    this       Lscala/io/Source;
   0      6      1    pf       Lscala/PartialFunction;


public scala.collection.Iterator filterNot(scala.Function1);
  Code:
   Stack=2, Locals=2, Args_size=2
   0:	aload_0
   1:	aload_1
   2:	invokestatic	#614; //Method scala/collection/Iterator$class.filterNot:(Lscala/collection/Iterator;Lscala/Function1;)Lscala/collection/Iterator;
   5:	areturn
  LineNumberTable: 
   line 143: 0

  LocalVariableTable: 
   Start  Length  Slot  Name   Signature
   0      6      0    this       Lscala/io/Source;
   0      6      1    p       Lscala/Function1;


public scala.collection.Iterator withFilter(scala.Function1);
  Code:
   Stack=2, Locals=2, Args_size=2
   0:	aload_0
   1:	aload_1
   2:	invokestatic	#617; //Method scala/collection/Iterator$class.withFilter:(Lscala/collection/Iterator;Lscala/Function1;)Lscala/collection/Iterator;
   5:	areturn
  LineNumberTable: 
   line 143: 0

  LocalVariableTable: 
   Start  Length  Slot  Name   Signature
   0      6      0    this       Lscala/io/Source;
   0      6      1    p       Lscala/Function1;


public scala.collection.Iterator filter(scala.Function1);
  Code:
   Stack=2, Locals=2, Args_size=2
   0:	aload_0
   1:	aload_1
   2:	invokestatic	#620; //Method scala/collection/Iterator$class.filter:(Lscala/collection/Iterator;Lscala/Function1;)Lscala/collection/Iterator;
   5:	areturn
  LineNumberTable: 
   line 143: 0

  LocalVariableTable: 
   Start  Length  Slot  Name   Signature
   0      6      0    this       Lscala/io/Source;
   0      6      1    p       Lscala/Function1;


public scala.collection.Iterator flatMap(scala.Function1);
  Code:
   Stack=2, Locals=2, Args_size=2
   0:	aload_0
   1:	aload_1
   2:	invokestatic	#623; //Method scala/collection/Iterator$class.flatMap:(Lscala/collection/Iterator;Lscala/Function1;)Lscala/collection/Iterator;
   5:	areturn
  LineNumberTable: 
   line 143: 0

  LocalVariableTable: 
   Start  Length  Slot  Name   Signature
   0      6      0    this       Lscala/io/Source;
   0      6      1    f       Lscala/Function1;


public scala.collection.Iterator $plus$plus(scala.Function0);
  Code:
   Stack=2, Locals=2, Args_size=2
   0:	aload_0
   1:	aload_1
   2:	invokestatic	#628; //Method scala/collection/Iterator$class.$plus$plus:(Lscala/collection/Iterator;Lscala/Function0;)Lscala/collection/Iterator;
   5:	areturn
  LineNumberTable: 
   line 143: 0

  LocalVariableTable: 
   Start  Length  Slot  Name   Signature
   0      6      0    this       Lscala/io/Source;
   0      6      1    that       Lscala/Function0;


public scala.collection.Iterator map(scala.Function1);
  Code:
   Stack=2, Locals=2, Args_size=2
   0:	aload_0
   1:	aload_1
   2:	invokestatic	#631; //Method scala/collection/Iterator$class.map:(Lscala/collection/Iterator;Lscala/Function1;)Lscala/collection/Iterator;
   5:	areturn
  LineNumberTable: 
   line 143: 0

  LocalVariableTable: 
   Start  Length  Slot  Name   Signature
   0      6      0    this       Lscala/io/Source;
   0      6      1    f       Lscala/Function1;


public scala.collection.Iterator slice(int, int);
  Code:
   Stack=3, Locals=3, Args_size=3
   0:	aload_0
   1:	iload_1
   2:	iload_2
   3:	invokestatic	#636; //Method scala/collection/Iterator$class.slice:(Lscala/collection/Iterator;II)Lscala/collection/Iterator;
   6:	areturn
  LineNumberTable: 
   line 143: 0

  LocalVariableTable: 
   Start  Length  Slot  Name   Signature
   0      7      0    this       Lscala/io/Source;
   0      7      1    from       I
   0      7      2    until       I


public scala.collection.Iterator drop(int);
  Code:
   Stack=2, Locals=2, Args_size=2
   0:	aload_0
   1:	iload_1
   2:	invokestatic	#640; //Method scala/collection/Iterator$class.drop:(Lscala/collection/Iterator;I)Lscala/collection/Iterator;
   5:	areturn
  LineNumberTable: 
   line 143: 0

  LocalVariableTable: 
   Start  Length  Slot  Name   Signature
   0      6      0    this       Lscala/io/Source;
   0      6      1    n       I


public scala.collection.Iterator take(int);
  Code:
   Stack=2, Locals=2, Args_size=2
   0:	aload_0
   1:	iload_1
   2:	invokestatic	#643; //Method scala/collection/Iterator$class.take:(Lscala/collection/Iterator;I)Lscala/collection/Iterator;
   5:	areturn
  LineNumberTable: 
   line 143: 0

  LocalVariableTable: 
   Start  Length  Slot  Name   Signature
   0      6      0    this       Lscala/io/Source;
   0      6      1    n       I


}

