Compiled from "UTF8Codec.scala"
public final class scala.io.UTF8Codec$ extends java.lang.Object implements scala.ScalaObject
  SourceFile: "UTF8Codec.scala"
  Scala: length = 0x
   
  minor version: 0
  major version: 49
  Constant pool:
const #1 = Asciz	SourceFile;
const #2 = Asciz	UTF8Codec.scala;
const #3 = Asciz	Scala;
const #4 = Asciz	MODULE$;
const #5 = Asciz	Lscala/io/UTF8Codec$;;
const #6 = Asciz	<clinit>;
const #7 = Asciz	()V;
const #8 = Asciz	Code;
const #9 = Asciz	scala/io/UTF8Codec$;
const #10 = class	#9;	//  scala/io/UTF8Codec$
const #11 = Asciz	<init>;
const #12 = NameAndType	#11:#7;//  "<init>":()V
const #13 = Method	#10.#12;	//  scala/io/UTF8Codec$."<init>":()V
const #14 = Asciz	UNI_REPLACEMENT_CHAR;
const #15 = Asciz	I;
const #16 = Asciz	LineNumberTable;
const #17 = Asciz	java/lang/Object;
const #18 = class	#17;	//  java/lang/Object
const #19 = Method	#18.#12;	//  java/lang/Object."<init>":()V
const #20 = NameAndType	#4:#5;//  MODULE$:Lscala/io/UTF8Codec$;
const #21 = Field	#10.#20;	//  scala/io/UTF8Codec$.MODULE$:Lscala/io/UTF8Codec$;
const #22 = int	65533;
const #23 = NameAndType	#14:#15;//  UNI_REPLACEMENT_CHAR:I
const #24 = Field	#10.#23;	//  scala/io/UTF8Codec$.UNI_REPLACEMENT_CHAR:I
const #25 = Asciz	decode;
const #26 = Asciz	([BII)Ljava/lang/String;;
const #27 = Asciz	java/lang/String;
const #28 = class	#27;	//  java/lang/String
const #29 = Asciz	([BI[CII)I;
const #30 = NameAndType	#25:#29;//  decode:([BI[CII)I
const #31 = Method	#10.#30;	//  scala/io/UTF8Codec$.decode:([BI[CII)I
const #32 = Asciz	([CII)V;
const #33 = NameAndType	#11:#32;//  "<init>":([CII)V
const #34 = Method	#28.#33;	//  java/lang/String."<init>":([CII)V
const #35 = Asciz	this;
const #36 = Asciz	src;
const #37 = Asciz	[B;
const #38 = Asciz	from;
const #39 = Asciz	len;
const #40 = Asciz	cs;
const #41 = Asciz	[C;
const #42 = Asciz	LocalVariableTable;
const #43 = int	255;
const #44 = int	224;
const #45 = int	15;
const #46 = int	12;
const #47 = int	63;
const #48 = int	6;
const #49 = int	192;
const #50 = int	31;
const #51 = Asciz	dst;
const #52 = Asciz	to;
const #53 = Asciz	i;
const #54 = Asciz	j;
const #55 = Asciz	end;
const #56 = Asciz	b;
const #57 = Asciz	encode;
const #58 = Asciz	(Ljava/lang/String;)[B;
const #59 = Asciz	length;
const #60 = Asciz	()I;
const #61 = NameAndType	#59:#60;//  length:()I
const #62 = Method	#28.#61;	//  java/lang/String.length:()I
const #63 = Asciz	(Ljava/lang/String;[BI)I;
const #64 = NameAndType	#57:#63;//  encode:(Ljava/lang/String;[BI)I
const #65 = Method	#10.#64;	//  scala/io/UTF8Codec$.encode:(Ljava/lang/String;[BI)I
const #66 = Asciz	scala/runtime/ScalaRunTime$;
const #67 = class	#66;	//  scala/runtime/ScalaRunTime$
const #68 = Asciz	Lscala/runtime/ScalaRunTime$;;
const #69 = NameAndType	#4:#68;//  MODULE$:Lscala/runtime/ScalaRunTime$;
const #70 = Field	#67.#69;	//  scala/runtime/ScalaRunTime$.MODULE$:Lscala/runtime/ScalaRunTime$;
const #71 = Asciz	boxArray;
const #72 = Asciz	(Ljava/lang/Object;)Lscala/runtime/BoxedArray;;
const #73 = NameAndType	#71:#72;//  boxArray:(Ljava/lang/Object;)Lscala/runtime/BoxedArray;
const #74 = Method	#67.#73;	//  scala/runtime/ScalaRunTime$.boxArray:(Ljava/lang/Object;)Lscala/runtime/BoxedArray;
const #75 = Asciz	scala/collection/generic/VectorTemplate;
const #76 = class	#75;	//  scala/collection/generic/VectorTemplate
const #77 = Asciz	slice;
const #78 = Asciz	(II)Lscala/collection/generic/VectorTemplate;;
const #79 = NameAndType	#77:#78;//  slice:(II)Lscala/collection/generic/VectorTemplate;
const #80 = InterfaceMethod	#76.#79;	//  scala/collection/generic/VectorTemplate.slice:(II)Lscala/collection/generic/VectorTemplate;
const #81 = Asciz	scala/runtime/BoxedArray;
const #82 = class	#81;	//  scala/runtime/BoxedArray
const #83 = Asciz	java/lang/Byte;
const #84 = class	#83;	//  java/lang/Byte
const #85 = Asciz	TYPE;
const #86 = Asciz	Ljava/lang/Class;;
const #87 = NameAndType	#85:#86;//  TYPE:Ljava/lang/Class;
const #88 = Field	#84.#87;	//  java/lang/Byte.TYPE:Ljava/lang/Class;
const #89 = Asciz	arrayValue;
const #90 = Asciz	(Lscala/runtime/BoxedArray;Ljava/lang/Class;)Ljava/lang/Object;;
const #91 = NameAndType	#89:#90;//  arrayValue:(Lscala/runtime/BoxedArray;Ljava/lang/Class;)Ljava/lang/Object;
const #92 = Method	#67.#91;	//  scala/runtime/ScalaRunTime$.arrayValue:(Lscala/runtime/BoxedArray;Ljava/lang/Class;)Ljava/lang/Object;
const #93 = class	#37;	//  "[B"
const #94 = Asciz	s;
const #95 = Asciz	Ljava/lang/String;;
const #96 = Asciz	toCharArray;
const #97 = Asciz	()[C;
const #98 = NameAndType	#96:#97;//  toCharArray:()[C
const #99 = Method	#28.#98;	//  java/lang/String.toCharArray:()[C
const #100 = Asciz	([CI[BII)I;
const #101 = NameAndType	#57:#100;//  encode:([CI[BII)I
const #102 = Method	#10.#101;	//  scala/io/UTF8Codec$.encode:([CI[BII)I
const #103 = int	128;
const #104 = int	1023;
const #105 = Asciz	ch;
const #106 = Asciz	C;
const #107 = Asciz	(I)[B;
const #108 = int	191;
const #109 = Asciz	scala/collection/immutable/List$;
const #110 = class	#109;	//  scala/collection/immutable/List$
const #111 = Asciz	Lscala/collection/immutable/List$;;
const #112 = NameAndType	#4:#111;//  MODULE$:Lscala/collection/immutable/List$;
const #113 = Field	#110.#112;	//  scala/collection/immutable/List$.MODULE$:Lscala/collection/immutable/List$;
const #114 = int	7;
const #115 = int	240;
const #116 = int	248;
const #117 = int	252;
const #118 = Asciz	apply;
const #119 = Asciz	(Lscala/collection/Sequence;)Lscala/collection/immutable/List;;
const #120 = NameAndType	#118:#119;//  apply:(Lscala/collection/Sequence;)Lscala/collection/immutable/List;
const #121 = Method	#110.#120;	//  scala/collection/immutable/List$.apply:(Lscala/collection/Sequence;)Lscala/collection/immutable/List;
const #122 = int	2048;
const #123 = int	65536;
const #124 = int	1114111;
const #125 = Asciz	scala/collection/generic/LinearSequenceTemplate;
const #126 = class	#125;	//  scala/collection/generic/LinearSequenceTemplate
const #127 = Asciz	(I)Ljava/lang/Object;;
const #128 = NameAndType	#118:#127;//  apply:(I)Ljava/lang/Object;
const #129 = InterfaceMethod	#126.#128;	//  scala/collection/generic/LinearSequenceTemplate.apply:(I)Ljava/lang/Object;
const #130 = Asciz	scala/runtime/BoxesRunTime;
const #131 = class	#130;	//  scala/runtime/BoxesRunTime
const #132 = Asciz	unboxToByte;
const #133 = Asciz	(Ljava/lang/Object;)B;
const #134 = NameAndType	#132:#133;//  unboxToByte:(Ljava/lang/Object;)B
const #135 = Method	#131.#134;	//  scala/runtime/BoxesRunTime.unboxToByte:(Ljava/lang/Object;)B
const #136 = NameAndType	#14:#60;//  UNI_REPLACEMENT_CHAR:()I
const #137 = Method	#10.#136;	//  scala/io/UTF8Codec$.UNI_REPLACEMENT_CHAR:()I
const #138 = NameAndType	#57:#107;//  encode:(I)[B
const #139 = Method	#10.#138;	//  scala/io/UTF8Codec$.encode:(I)[B
const #140 = Asciz	ch1;
const #141 = Asciz	byteMask;
const #142 = Asciz	byteMark;
const #143 = Asciz	bytesToWrite;
const #144 = Asciz	firstByteMark;
const #145 = Asciz	Lscala/collection/immutable/List;;
const #146 = Asciz	res;
const #147 = Asciz	bw;
const #148 = Asciz	scala/ScalaObject;
const #149 = class	#148;	//  scala/ScalaObject

{
public static final scala.io.UTF8Codec$ MODULE$;

public static {};
  Code:
   Stack=1, Locals=0, Args_size=0
   0:	new	#10; //class scala/io/UTF8Codec$
   3:	invokespecial	#13; //Method "<init>":()V
   6:	return

public java.lang.String decode(byte[], int, int);
  Code:
   Stack=10, Locals=5, Args_size=4
   0:	iload_3
   1:	newarray char
   3:	astore	4
   5:	new	#28; //class java/lang/String
   8:	dup
   9:	aload	4
   11:	iconst_0
   12:	aload_0
   13:	aload_1
   14:	iconst_0
   15:	aload	4
   17:	iconst_0
   18:	iload_3
   19:	invokevirtual	#31; //Method decode:([BI[CII)I
   22:	invokespecial	#34; //Method java/lang/String."<init>":([CII)V
   25:	areturn
  LineNumberTable: 
   line 115: 0
   line 116: 5

  LocalVariableTable: 
   Start  Length  Slot  Name   Signature
   0      26      0    this       Lscala/io/UTF8Codec$;
   0      26      1    src       [B
   0      26      2    from       I
   0      26      3    len       I
   5      20      4    cs       [C


public int decode(byte[], int, char[], int, int);
  Code:
   Stack=4, Locals=10, Args_size=6
   0:	iload_2
   1:	istore	6
   3:	iload	4
   5:	istore	7
   7:	iload_2
   8:	iload	5
   10:	iadd
   11:	istore	8
   13:	iload	6
   15:	iload	8
   17:	if_icmpge	133
   20:	aload_1
   21:	iload	6
   23:	baload
   24:	ldc	#43; //int 255
   26:	iand
   27:	istore	9
   29:	iload	6
   31:	iconst_1
   32:	iadd
   33:	istore	6
   35:	iload	9
   37:	ldc	#44; //int 224
   39:	if_icmplt	86
   42:	iload	9
   44:	ldc	#45; //int 15
   46:	iand
   47:	ldc	#46; //int 12
   49:	ishl
   50:	aload_1
   51:	iload	6
   53:	baload
   54:	ldc	#47; //int 63
   56:	iand
   57:	ldc	#48; //int 6
   59:	ishl
   60:	ior
   61:	istore	9
   63:	iload	9
   65:	aload_1
   66:	iload	6
   68:	iconst_1
   69:	iadd
   70:	baload
   71:	ldc	#47; //int 63
   73:	iand
   74:	ior
   75:	istore	9
   77:	iload	6
   79:	iconst_2
   80:	iadd
   81:	istore	6
   83:	goto	117
   86:	iload	9
   88:	ldc	#49; //int 192
   90:	if_icmplt	117
   93:	iload	9
   95:	ldc	#50; //int 31
   97:	iand
   98:	ldc	#48; //int 6
   100:	ishl
   101:	aload_1
   102:	iload	6
   104:	baload
   105:	ldc	#47; //int 63
   107:	iand
   108:	ior
   109:	istore	9
   111:	iload	6
   113:	iconst_1
   114:	iadd
   115:	istore	6
   117:	aload_3
   118:	iload	7
   120:	iload	9
   122:	i2c
   123:	castore
   124:	iload	7
   126:	iconst_1
   127:	iadd
   128:	istore	7
   130:	goto	13
   133:	iload	7
   135:	ireturn
  LineNumberTable: 
   line 94: 0
   line 95: 3
   line 96: 7
   line 97: 13
   line 98: 20
   line 99: 29
   line 100: 35
   line 101: 42
   line 102: 63
   line 103: 77
   line 104: 86
   line 105: 93
   line 106: 111
   line 108: 117
   line 109: 124
   line 97: 130
   line 111: 133

  LocalVariableTable: 
   Start  Length  Slot  Name   Signature
   0      136      0    this       Lscala/io/UTF8Codec$;
   0      136      1    src       [B
   0      136      2    from       I
   0      136      3    dst       [C
   0      136      4    to       I
   0      136      5    len       I
   3      132      6    i       I
   7      128      7    j       I
   13      122      8    end       I
   29      101      9    b       I


public byte[] encode(java.lang.String);
  Code:
   Stack=4, Locals=5, Args_size=2
   0:	aload_1
   1:	invokevirtual	#62; //Method java/lang/String.length:()I
   4:	iconst_3
   5:	imul
   6:	newarray byte
   8:	astore_2
   9:	aload_0
   10:	aload_1
   11:	aload_2
   12:	iconst_0
   13:	invokevirtual	#65; //Method encode:(Ljava/lang/String;[BI)I
   16:	istore_3
   17:	getstatic	#70; //Field scala/runtime/ScalaRunTime$.MODULE$:Lscala/runtime/ScalaRunTime$;
   20:	getstatic	#70; //Field scala/runtime/ScalaRunTime$.MODULE$:Lscala/runtime/ScalaRunTime$;
   23:	aload_2
   24:	invokevirtual	#74; //Method scala/runtime/ScalaRunTime$.boxArray:(Ljava/lang/Object;)Lscala/runtime/BoxedArray;
   27:	iconst_0
   28:	iload_3
   29:	invokeinterface	#80,  3; //InterfaceMethod scala/collection/generic/VectorTemplate.slice:(II)Lscala/collection/generic/VectorTemplate;
   34:	checkcast	#82; //class scala/runtime/BoxedArray
   37:	getstatic	#88; //Field java/lang/Byte.TYPE:Ljava/lang/Class;
   40:	invokevirtual	#92; //Method scala/runtime/ScalaRunTime$.arrayValue:(Lscala/runtime/BoxedArray;Ljava/lang/Class;)Ljava/lang/Object;
   43:	astore	4
   45:	aload	4
   47:	instanceof	#82; //class scala/runtime/BoxedArray
   50:	ifeq	70
   53:	getstatic	#70; //Field scala/runtime/ScalaRunTime$.MODULE$:Lscala/runtime/ScalaRunTime$;
   56:	aload	4
   58:	checkcast	#82; //class scala/runtime/BoxedArray
   61:	getstatic	#88; //Field java/lang/Byte.TYPE:Ljava/lang/Class;
   64:	invokevirtual	#92; //Method scala/runtime/ScalaRunTime$.arrayValue:(Lscala/runtime/BoxedArray;Ljava/lang/Class;)Ljava/lang/Object;
   67:	goto	72
   70:	aload	4
   72:	checkcast	#93; //class "[B"
   75:	areturn
  LineNumberTable: 
   line 86: 0
   line 87: 9
   line 88: 17

  LocalVariableTable: 
   Start  Length  Slot  Name   Signature
   0      76      0    this       Lscala/io/UTF8Codec$;
   0      76      1    s       Ljava/lang/String;
   9      66      2    dst       [B
   17      58      3    len       I


public int encode(java.lang.String, byte[], int);
  Code:
   Stack=6, Locals=4, Args_size=4
   0:	aload_0
   1:	aload_1
   2:	invokevirtual	#99; //Method java/lang/String.toCharArray:()[C
   5:	iconst_0
   6:	aload_2
   7:	iload_3
   8:	aload_1
   9:	invokevirtual	#62; //Method java/lang/String.length:()I
   12:	invokevirtual	#102; //Method encode:([CI[BII)I
   15:	ireturn
  LineNumberTable: 
   line 83: 0

  LocalVariableTable: 
   Start  Length  Slot  Name   Signature
   0      16      0    this       Lscala/io/UTF8Codec$;
   0      16      1    s       Ljava/lang/String;
   0      16      2    dst       [B
   0      16      3    to       I


public int encode(char[], int, byte[], int, int);
  Code:
   Stack=5, Locals=10, Args_size=6
   0:	iload_2
   1:	istore	6
   3:	iload	4
   5:	istore	7
   7:	iload_2
   8:	iload	5
   10:	iadd
   11:	istore	8
   13:	iload	6
   15:	iload	8
   17:	if_icmpge	154
   20:	aload_1
   21:	iload	6
   23:	caload
   24:	istore	9
   26:	iload	6
   28:	iconst_1
   29:	iadd
   30:	istore	6
   32:	iload	9
   34:	ldc	#103; //int 128
   36:	if_icmpge	55
   39:	aload_3
   40:	iload	7
   42:	iload	9
   44:	i2b
   45:	bastore
   46:	iload	7
   48:	iconst_1
   49:	iadd
   50:	istore	7
   52:	goto	13
   55:	iload	9
   57:	ldc	#104; //int 1023
   59:	if_icmpgt	99
   62:	aload_3
   63:	iload	7
   65:	ldc	#49; //int 192
   67:	iload	9
   69:	ldc	#48; //int 6
   71:	ishr
   72:	ior
   73:	i2b
   74:	bastore
   75:	aload_3
   76:	iload	7
   78:	iconst_1
   79:	iadd
   80:	ldc	#103; //int 128
   82:	iload	9
   84:	ldc	#47; //int 63
   86:	iand
   87:	ior
   88:	i2b
   89:	bastore
   90:	iload	7
   92:	iconst_2
   93:	iadd
   94:	istore	7
   96:	goto	13
   99:	aload_3
   100:	iload	7
   102:	ldc	#44; //int 224
   104:	iload	9
   106:	ldc	#46; //int 12
   108:	ishr
   109:	ior
   110:	i2b
   111:	bastore
   112:	aload_3
   113:	iload	7
   115:	iconst_1
   116:	iadd
   117:	ldc	#103; //int 128
   119:	iload	9
   121:	ldc	#48; //int 6
   123:	ishr
   124:	ldc	#47; //int 63
   126:	iand
   127:	ior
   128:	i2b
   129:	bastore
   130:	aload_3
   131:	iload	7
   133:	iconst_2
   134:	iadd
   135:	ldc	#103; //int 128
   137:	iload	9
   139:	ldc	#47; //int 63
   141:	iand
   142:	ior
   143:	i2b
   144:	bastore
   145:	iload	7
   147:	iconst_3
   148:	iadd
   149:	istore	7
   151:	goto	13
   154:	iload	7
   156:	ireturn
  LineNumberTable: 
   line 58: 0
   line 59: 3
   line 60: 7
   line 61: 13
   line 62: 20
   line 63: 26
   line 64: 32
   line 65: 39
   line 66: 46
   line 68: 55
   line 69: 62
   line 70: 75
   line 71: 90
   line 73: 99
   line 74: 112
   line 75: 130
   line 76: 145
   line 79: 154

  LocalVariableTable: 
   Start  Length  Slot  Name   Signature
   0      157      0    this       Lscala/io/UTF8Codec$;
   0      157      1    src       [C
   0      157      2    from       I
   0      157      3    dst       [B
   0      157      4    to       I
   0      157      5    len       I
   3      153      6    i       I
   7      149      7    j       I
   13      143      8    end       I
   26      128      9    ch       C


public byte[] encode(int);
  Code:
   Stack=6, Locals=9, Args_size=2
   0:	iload_1
   1:	istore_2
   2:	ldc	#108; //int 191
   4:	istore_3
   5:	ldc	#103; //int 128
   7:	istore	4
   9:	iconst_0
   10:	istore	5
   12:	getstatic	#113; //Field scala/collection/immutable/List$.MODULE$:Lscala/collection/immutable/List$;
   15:	getstatic	#70; //Field scala/runtime/ScalaRunTime$.MODULE$:Lscala/runtime/ScalaRunTime$;
   18:	ldc	#114; //int 7
   20:	newarray byte
   22:	dup
   23:	iconst_0
   24:	iconst_0
   25:	i2b
   26:	bastore
   27:	dup
   28:	iconst_1
   29:	iconst_0
   30:	i2b
   31:	bastore
   32:	dup
   33:	iconst_2
   34:	ldc	#49; //int 192
   36:	i2b
   37:	bastore
   38:	dup
   39:	iconst_3
   40:	ldc	#44; //int 224
   42:	i2b
   43:	bastore
   44:	dup
   45:	iconst_4
   46:	ldc	#115; //int 240
   48:	i2b
   49:	bastore
   50:	dup
   51:	iconst_5
   52:	ldc	#116; //int 248
   54:	i2b
   55:	bastore
   56:	dup
   57:	ldc	#48; //int 6
   59:	ldc	#117; //int 252
   61:	i2b
   62:	bastore
   63:	invokevirtual	#74; //Method scala/runtime/ScalaRunTime$.boxArray:(Ljava/lang/Object;)Lscala/runtime/BoxedArray;
   66:	invokevirtual	#121; //Method scala/collection/immutable/List$.apply:(Lscala/collection/Sequence;)Lscala/collection/immutable/List;
   69:	astore	6
   71:	iload_2
   72:	ldc	#103; //int 128
   74:	if_icmpge	83
   77:	iconst_1
   78:	istore	5
   80:	goto	116
   83:	iload_2
   84:	ldc	#122; //int 2048
   86:	if_icmpge	95
   89:	iconst_2
   90:	istore	5
   92:	goto	116
   95:	iload_2
   96:	ldc	#123; //int 65536
   98:	if_icmpge	107
   101:	iconst_3
   102:	istore	5
   104:	goto	116
   107:	iload_2
   108:	ldc	#124; //int 1114111
   110:	if_icmpgt	238
   113:	iconst_4
   114:	istore	5
   116:	iload	5
   118:	newarray byte
   120:	astore	7
   122:	iload	5
   124:	istore	8
   126:	iload	8
   128:	iconst_4
   129:	if_icmplt	154
   132:	aload	7
   134:	iconst_3
   135:	iload_2
   136:	iload	4
   138:	ior
   139:	iload_3
   140:	iand
   141:	i2b
   142:	bastore
   143:	iload_2
   144:	ldc	#48; //int 6
   146:	ishr
   147:	istore_2
   148:	iload	8
   150:	iconst_1
   151:	isub
   152:	istore	8
   154:	iload	8
   156:	iconst_3
   157:	if_icmplt	182
   160:	aload	7
   162:	iconst_2
   163:	iload_2
   164:	iload	4
   166:	ior
   167:	iload_3
   168:	iand
   169:	i2b
   170:	bastore
   171:	iload_2
   172:	ldc	#48; //int 6
   174:	ishr
   175:	istore_2
   176:	iload	8
   178:	iconst_1
   179:	isub
   180:	istore	8
   182:	iload	8
   184:	iconst_2
   185:	if_icmplt	210
   188:	aload	7
   190:	iconst_1
   191:	iload_2
   192:	iload	4
   194:	ior
   195:	iload_3
   196:	iand
   197:	i2b
   198:	bastore
   199:	iload_2
   200:	ldc	#48; //int 6
   202:	ishr
   203:	istore_2
   204:	iload	8
   206:	iconst_1
   207:	isub
   208:	istore	8
   210:	iload	8
   212:	iconst_1
   213:	if_icmplt	235
   216:	aload	7
   218:	iconst_0
   219:	iload_2
   220:	aload	6
   222:	iload	5
   224:	invokeinterface	#129,  2; //InterfaceMethod scala/collection/generic/LinearSequenceTemplate.apply:(I)Ljava/lang/Object;
   229:	invokestatic	#135; //Method scala/runtime/BoxesRunTime.unboxToByte:(Ljava/lang/Object;)B
   232:	ior
   233:	i2b
   234:	bastore
   235:	aload	7
   237:	areturn
   238:	aload_0
   239:	aload_0
   240:	invokevirtual	#137; //Method UNI_REPLACEMENT_CHAR:()I
   243:	invokevirtual	#139; //Method encode:(I)[B
   246:	areturn
  LineNumberTable: 
   line 27: 0
   line 28: 2
   line 29: 5
   line 30: 9
   line 31: 12
   line 33: 71
   line 34: 83
   line 35: 95
   line 36: 107
   line 39: 116
   line 41: 122
   line 42: 126
   line 43: 132
   line 45: 154
   line 46: 160
   line 48: 182
   line 49: 188
   line 51: 210
   line 52: 216
   line 54: 235
   line 37: 238

  LocalVariableTable: 
   Start  Length  Slot  Name   Signature
   0      247      0    this       Lscala/io/UTF8Codec$;
   0      247      1    ch1       I
   2      235      2    ch       I
   238      9      2    ch       I
   5      232      3    byteMask       I
   238      9      3    byteMask       I
   9      228      4    byteMark       I
   238      9      4    byteMark       I
   12      225      5    bytesToWrite       I
   238      9      5    bytesToWrite       I
   71      166      6    firstByteMark       Lscala/collection/immutable/List;
   238      9      6    firstByteMark       Lscala/collection/immutable/List;
   122      115      7    res       [B
   126      111      8    bw       I


public final int UNI_REPLACEMENT_CHAR();
  Code:
   Stack=1, Locals=1, Args_size=1
   0:	aload_0
   1:	getfield	#24; //Field UNI_REPLACEMENT_CHAR:I
   4:	ireturn
  LineNumberTable: 
   line 20: 0


}

