Compiled from "UTF8Codec.scala"
public final class scala.io.UTF8Codec$ extends java.lang.Object implements scala.ScalaObject
  SourceFile: "UTF8Codec.scala"
  Scala: length = 0x
   
  InnerClass: 
   public final $anonfun$apply$6=class scala/Array$$anonfun$apply$6 of class scala/Array
  minor version: 0
  major version: 49
  Constant pool:
Asciz	SourceFile;
Asciz	UTF8Codec.scala;
Asciz	MODULE$;
Asciz	Lscala/io/UTF8Codec$;;
Asciz	<clinit>;
Asciz	()V;
Asciz	Code;
Asciz	scala/io/UTF8Codec$;
class	scala/io/UTF8Codec$
Asciz	<init>;
NameAndType	"<init>":()V
Method	scala/io/UTF8Codec$."<init>":()V
Asciz	UNI_REPLACEMENT_CHAR;
Asciz	I;
Asciz	UNI_REPLACEMENT_BYTES;
Asciz	[B;
Asciz	()I;
Asciz	LineNumberTable;
NameAndType	UNI_REPLACEMENT_CHAR:I
Field	scala/io/UTF8Codec$.UNI_REPLACEMENT_CHAR:I
Asciz	()[B;
NameAndType	UNI_REPLACEMENT_BYTES:[B
Field	scala/io/UTF8Codec$.UNI_REPLACEMENT_BYTES:[B
Asciz	encode;
Asciz	(I)[B;
Asciz	java/lang/Character;
class	java/lang/Character
Asciz	getType;
Asciz	(I)I;
NameAndType	getType:(I)I
Method	java/lang/Character.getType:(I)I
Asciz	java/lang/String;
class	java/lang/String
Asciz	scala/Predef$;
class	scala/Predef$
Asciz	Lscala/Predef$;;
NameAndType	MODULE$:Lscala/Predef$;
Field	scala/Predef$.MODULE$:Lscala/Predef$;
Asciz	wrapIntArray;
Asciz	([I)Lscala/collection/mutable/WrappedArray;;
NameAndType	wrapIntArray:([I)Lscala/collection/mutable/WrappedArray;
Method	scala/Predef$.wrapIntArray:([I)Lscala/collection/mutable/WrappedArray;
Asciz	scala/collection/SeqLike;
class	scala/collection/SeqLike
Asciz	length;
NameAndType	length:()I
InterfaceMethod	scala/collection/SeqLike.length:()I
Asciz	scala/runtime/IntRef;
class	scala/runtime/IntRef
Asciz	(I)V;
NameAndType	"<init>":(I)V
Method	scala/runtime/IntRef."<init>":(I)V
Asciz	scala/collection/IterableLike;
class	scala/collection/IterableLike
Asciz	iterator;
Asciz	()Lscala/collection/Iterator;;
NameAndType	iterator:()Lscala/collection/Iterator;
InterfaceMethod	scala/collection/IterableLike.iterator:()Lscala/collection/Iterator;
Asciz	scala/Array$$anonfun$apply$6;
class	scala/Array$$anonfun$apply$6
Asciz	([ILscala/runtime/IntRef;)V;
NameAndType	"<init>":([ILscala/runtime/IntRef;)V
Method	scala/Array$$anonfun$apply$6."<init>":([ILscala/runtime/IntRef;)V
Asciz	scala/collection/Iterator;
class	scala/collection/Iterator
Asciz	foreach;
Asciz	(Lscala/Function1;)V;
NameAndType	foreach:(Lscala/Function1;)V
InterfaceMethod	scala/collection/Iterator.foreach:(Lscala/Function1;)V
Asciz	([III)V;
NameAndType	"<init>":([III)V
Method	java/lang/String."<init>":([III)V
Asciz	UTF-8;
String	UTF-8
Asciz	getBytes;
Asciz	(Ljava/lang/String;)[B;
NameAndType	getBytes:(Ljava/lang/String;)[B
Method	java/lang/String.getBytes:(Ljava/lang/String;)[B
Asciz	java/lang/IllegalArgumentException;
class	java/lang/IllegalArgumentException
Asciz	this;
Asciz	ch;
Asciz	xs0;
Asciz	Lscala/collection/Seq;;
Asciz	i$60;
Asciz	Lscala/runtime/IntRef;;
Asciz	array$60;
Asciz	[I;
Asciz	exceptionResult1;
Asciz	LocalVariableTable;
Asciz	Deprecated;
Asciz	([CI[BII)I;
Asciz	scala/io/Codec$;
class	scala/io/Codec$
Asciz	Lscala/io/Codec$;;
NameAndType	MODULE$:Lscala/io/Codec$;
Field	scala/io/Codec$.MODULE$:Lscala/io/Codec$;
Asciz	charArrayOps;
Asciz	([C)Lscala/collection/mutable/ArrayOps;;
NameAndType	charArrayOps:([C)Lscala/collection/mutable/ArrayOps;
Method	scala/Predef$.charArrayOps:([C)Lscala/collection/mutable/ArrayOps;
Asciz	scala/collection/IndexedSeqOptimized;
class	scala/collection/IndexedSeqOptimized
Asciz	slice;
Asciz	(II)Ljava/lang/Object;;
NameAndType	slice:(II)Ljava/lang/Object;
InterfaceMethod	scala/collection/IndexedSeqOptimized.slice:(II)Ljava/lang/Object;
Asciz	[C;
class	"[C"
Asciz	arrayToCharSequence;
Asciz	([C)Ljava/lang/CharSequence;;
NameAndType	arrayToCharSequence:([C)Ljava/lang/CharSequence;
Method	scala/Predef$.arrayToCharSequence:([C)Ljava/lang/CharSequence;
Asciz	fromUTF8;
Asciz	(Ljava/lang/CharSequence;)[B;
NameAndType	fromUTF8:(Ljava/lang/CharSequence;)[B
Method	scala/io/Codec$.fromUTF8:(Ljava/lang/CharSequence;)[B
Asciz	scala/Array$;
class	scala/Array$
Asciz	Lscala/Array$;;
NameAndType	MODULE$:Lscala/Array$;
Field	scala/Array$.MODULE$:Lscala/Array$;
Asciz	copy;
Asciz	(Ljava/lang/Object;ILjava/lang/Object;II)V;
NameAndType	copy:(Ljava/lang/Object;ILjava/lang/Object;II)V
Method	scala/Array$.copy:(Ljava/lang/Object;ILjava/lang/Object;II)V
Asciz	src;
Asciz	from;
Asciz	dst;
Asciz	to;
Asciz	len;
Asciz	bytes;
Asciz	(Ljava/lang/String;[BI)I;
Asciz	augmentString;
Asciz	(Ljava/lang/String;)Lscala/collection/immutable/StringOps;;
NameAndType	augmentString:(Ljava/lang/String;)Lscala/collection/immutable/StringOps;
Method	scala/Predef$.augmentString:(Ljava/lang/String;)Lscala/collection/immutable/StringOps;
Asciz	scala/reflect/Manifest$;
class	scala/reflect/Manifest$
Asciz	Lscala/reflect/Manifest$;;
NameAndType	MODULE$:Lscala/reflect/Manifest$;
Field	scala/reflect/Manifest$.MODULE$:Lscala/reflect/Manifest$;
Asciz	Char;
Asciz	()Lscala/reflect/AnyValManifest;;
NameAndType	Char:()Lscala/reflect/AnyValManifest;
Method	scala/reflect/Manifest$.Char:()Lscala/reflect/AnyValManifest;
Asciz	scala/collection/TraversableOnce;
class	scala/collection/TraversableOnce
Asciz	toArray;
Asciz	(Lscala/reflect/ClassManifest;)Ljava/lang/Object;;
NameAndType	toArray:(Lscala/reflect/ClassManifest;)Ljava/lang/Object;
InterfaceMethod	scala/collection/TraversableOnce.toArray:(Lscala/reflect/ClassManifest;)Ljava/lang/Object;
Method	java/lang/String.length:()I
NameAndType	encode:([CI[BII)I
Method	scala/io/UTF8Codec$.encode:([CI[BII)I
Asciz	s;
Asciz	Ljava/lang/String;;
Asciz	decode;
Asciz	([BI[CII)I;
Asciz	byteArrayOps;
Asciz	([B)Lscala/collection/mutable/ArrayOps;;
NameAndType	byteArrayOps:([B)Lscala/collection/mutable/ArrayOps;
Method	scala/Predef$.byteArrayOps:([B)Lscala/collection/mutable/ArrayOps;
class	"[B"
Asciz	toUTF8;
Asciz	([B)[C;
NameAndType	toUTF8:([B)[C
Method	scala/io/Codec$.toUTF8:([B)[C
Asciz	chars;
Asciz	([BII)Ljava/lang/String;;
Asciz	mkString;
Asciz	()Ljava/lang/String;;
NameAndType	mkString:()Ljava/lang/String;
InterfaceMethod	scala/collection/TraversableOnce.mkString:()Ljava/lang/String;
Asciz	java/lang/Object;
class	java/lang/Object
Method	java/lang/Object."<init>":()V
NameAndType	MODULE$:Lscala/io/UTF8Codec$;
Field	scala/io/UTF8Codec$.MODULE$:Lscala/io/UTF8Codec$;
int	65533;
Asciz	wrapByteArray;
Asciz	([B)Lscala/collection/mutable/WrappedArray;;
NameAndType	wrapByteArray:([B)Lscala/collection/mutable/WrappedArray;
Method	scala/Predef$.wrapByteArray:([B)Lscala/collection/mutable/WrappedArray;
Asciz	Byte;
NameAndType	Byte:()Lscala/reflect/AnyValManifest;
Method	scala/reflect/Manifest$.Byte:()Lscala/reflect/AnyValManifest;
Asciz	apply;
Asciz	(Lscala/collection/Seq;Lscala/reflect/ClassManifest;)Ljava/lang/Object;;
NameAndType	apply:(Lscala/collection/Seq;Lscala/reflect/ClassManifest;)Ljava/lang/Object;
Method	scala/Array$.apply:(Lscala/collection/Seq;Lscala/reflect/ClassManifest;)Ljava/lang/Object;
Asciz	Scala;
Asciz	InnerClasses;
Asciz	scala/Array;
class	scala/Array
Asciz	$anonfun$apply$6;
Asciz	scala/ScalaObject;
class	scala/ScalaObject

{
public static final scala.io.UTF8Codec$ MODULE$;
  Signature: Lscala/io/UTF8Codec$;

private final int UNI_REPLACEMENT_CHAR;
  Signature: I

private final byte[] UNI_REPLACEMENT_BYTES;
  Signature: [B

public static {};
  Signature: ()V
  Code:
   Stack=1, Locals=0, Args_size=0
	new	class scala/io/UTF8Codec$
	invokespecial	Method "<init>":()V
	return
  Labels:

public final int UNI_REPLACEMENT_CHAR();
  Signature: ()I
  Code:
   Stack=1, Locals=1, Args_size=1
	aload_0
	getfield	Field UNI_REPLACEMENT_CHAR:I
	ireturn
  Labels:

public final byte[] UNI_REPLACEMENT_BYTES();
  Signature: ()[B
  Code:
   Stack=1, Locals=1, Args_size=1
	aload_0
	getfield	Field UNI_REPLACEMENT_BYTES:[B
	areturn
  Labels:

public byte[] encode(int);
  Signature: (I)[B
  Code:
   Stack=7, Locals=6, Args_size=2
	iload_1
	invokestatic	Method java/lang/Character.getType:(I)I
	bipush	19
	if_icmpne	l1 // new
	aload_0
	getfield	Field UNI_REPLACEMENT_BYTES:[B
	goto	l2 // areturn
l1	new	class java/lang/String
	dup
	getstatic	Field scala/Predef$.MODULE$:Lscala/Predef$;
	iconst_0
	newarray int
	invokevirtual	Method scala/Predef$.wrapIntArray:([I)Lscala/collection/mutable/WrappedArray;
	astore_2
	aload_2
	invokeinterface	InterfaceMethod scala/collection/SeqLike.length:()I
	iconst_1
	iadd
	newarray int
	astore	4
	aload	4
	iconst_0
	iload_1
	iastore
	new	class scala/runtime/IntRef
	dup
	iconst_1
	invokespecial	Method scala/runtime/IntRef."<init>":(I)V
	astore_3
	aload_2
	invokeinterface	InterfaceMethod scala/collection/IterableLike.iterator:()Lscala/collection/Iterator;
	new	class scala/Array$$anonfun$apply$6
	dup
	aload	4
	aload_3
	invokespecial	Method scala/Array$$anonfun$apply$6."<init>":([ILscala/runtime/IntRef;)V
	invokeinterface	InterfaceMethod scala/collection/Iterator.foreach:(Lscala/Function1;)V
	aload	4
	iconst_0
	iconst_1
	invokespecial	Method java/lang/String."<init>":([III)V
	ldc	String UTF-8
	invokevirtual	Method java/lang/String.getBytes:(Ljava/lang/String;)[B
	astore	5
	goto	l3 // aload
	pop
	aload_0
	getfield	Field UNI_REPLACEMENT_BYTES:[B
	astore	5
l3	aload	5
l2	areturn
  Labels:
   	l1 = 16 // new
   	l3 = 101 // aload
   	l2 = 103 // areturn
  Exception table:
   from   to  target type
    16    94    94   Class java/lang/IllegalArgumentException

  LocalVariableTable: 
   Start  Length  Slot  Name   Signature
   0      104      0    this       Lscala/io/UTF8Codec$;
   0      104      1    ch       I
   30      49      2    xs0       Lscala/collection/Seq;
   56      23      3    i$60       Lscala/runtime/IntRef;
   42      37      4    array$60       [I
   16      87      5    exceptionResult1       [B

  Deprecated: true

public int encode(char[], int, byte[], int, int);
  Signature: ([CI[BII)I
  Code:
   Stack=6, Locals=7, Args_size=6
	getstatic	Field scala/io/Codec$.MODULE$:Lscala/io/Codec$;
	getstatic	Field scala/Predef$.MODULE$:Lscala/Predef$;
	getstatic	Field scala/Predef$.MODULE$:Lscala/Predef$;
	aload_1
	invokevirtual	Method scala/Predef$.charArrayOps:([C)Lscala/collection/mutable/ArrayOps;
	iload_2
	iload_2
	iload	5
	iadd
	invokeinterface	InterfaceMethod scala/collection/IndexedSeqOptimized.slice:(II)Ljava/lang/Object;
	checkcast	class "[C"
	invokevirtual	Method scala/Predef$.arrayToCharSequence:([C)Ljava/lang/CharSequence;
	invokevirtual	Method scala/io/Codec$.fromUTF8:(Ljava/lang/CharSequence;)[B
	astore	6
	getstatic	Field scala/Array$.MODULE$:Lscala/Array$;
	aload	6
	iconst_0
	aload_3
	iload	4
	aload	6
	arraylength
	invokevirtual	Method scala/Array$.copy:(Ljava/lang/Object;ILjava/lang/Object;II)V
	aload	6
	arraylength
	ireturn
  Labels:
  LocalVariableTable: 
   Start  Length  Slot  Name   Signature
   0      53      0    this       Lscala/io/UTF8Codec$;
   0      53      1    src       [C
   0      53      2    from       I
   0      53      3    dst       [B
   0      53      4    to       I
   0      53      5    len       I
   34      18      6    bytes       [B

  Deprecated: true

public int encode(java.lang.String, byte[], int);
  Signature: (Ljava/lang/String;[BI)I
  Code:
   Stack=6, Locals=4, Args_size=4
	aload_0
	getstatic	Field scala/Predef$.MODULE$:Lscala/Predef$;
	aload_1
	invokevirtual	Method scala/Predef$.augmentString:(Ljava/lang/String;)Lscala/collection/immutable/StringOps;
	getstatic	Field scala/reflect/Manifest$.MODULE$:Lscala/reflect/Manifest$;
	invokevirtual	Method scala/reflect/Manifest$.Char:()Lscala/reflect/AnyValManifest;
	invokeinterface	InterfaceMethod scala/collection/TraversableOnce.toArray:(Lscala/reflect/ClassManifest;)Ljava/lang/Object;
	checkcast	class "[C"
	iconst_0
	aload_2
	iload_3
	aload_1
	invokevirtual	Method java/lang/String.length:()I
	invokevirtual	Method encode:([CI[BII)I
	ireturn
  Labels:
  LocalVariableTable: 
   Start  Length  Slot  Name   Signature
   0      33      0    this       Lscala/io/UTF8Codec$;
   0      33      1    s       Ljava/lang/String;
   0      33      2    dst       [B
   0      33      3    to       I

  Deprecated: true

public byte[] encode(java.lang.String);
  Signature: (Ljava/lang/String;)[B
  Code:
   Stack=2, Locals=2, Args_size=2
	getstatic	Field scala/io/Codec$.MODULE$:Lscala/io/Codec$;
	aload_1
	invokevirtual	Method scala/io/Codec$.fromUTF8:(Ljava/lang/CharSequence;)[B
	areturn
  Labels:
  LocalVariableTable: 
   Start  Length  Slot  Name   Signature
   0      8      0    this       Lscala/io/UTF8Codec$;
   0      8      1    s       Ljava/lang/String;

  Deprecated: true

public int decode(byte[], int, char[], int, int);
  Signature: ([BI[CII)I
  Code:
   Stack=6, Locals=7, Args_size=6
	getstatic	Field scala/io/Codec$.MODULE$:Lscala/io/Codec$;
	getstatic	Field scala/Predef$.MODULE$:Lscala/Predef$;
	aload_1
	invokevirtual	Method scala/Predef$.byteArrayOps:([B)Lscala/collection/mutable/ArrayOps;
	iload_2
	iload_2
	iload	5
	iadd
	invokeinterface	InterfaceMethod scala/collection/IndexedSeqOptimized.slice:(II)Ljava/lang/Object;
	checkcast	class "[B"
	invokevirtual	Method scala/io/Codec$.toUTF8:([B)[C
	astore	6
	getstatic	Field scala/Array$.MODULE$:Lscala/Array$;
	aload	6
	iconst_0
	aload_3
	iload	4
	aload	6
	arraylength
	invokevirtual	Method scala/Array$.copy:(Ljava/lang/Object;ILjava/lang/Object;II)V
	aload	6
	arraylength
	ireturn
  Labels:
  LocalVariableTable: 
   Start  Length  Slot  Name   Signature
   0      47      0    this       Lscala/io/UTF8Codec$;
   0      47      1    src       [B
   0      47      2    from       I
   0      47      3    dst       [C
   0      47      4    to       I
   0      47      5    len       I
   28      18      6    chars       [C

  Deprecated: true

public java.lang.String decode(byte[], int, int);
  Signature: ([BII)Ljava/lang/String;
  Code:
   Stack=6, Locals=4, Args_size=4
	getstatic	Field scala/Predef$.MODULE$:Lscala/Predef$;
	getstatic	Field scala/io/Codec$.MODULE$:Lscala/io/Codec$;
	getstatic	Field scala/Predef$.MODULE$:Lscala/Predef$;
	aload_1
	invokevirtual	Method scala/Predef$.byteArrayOps:([B)Lscala/collection/mutable/ArrayOps;
	iload_2
	iload_2
	iload_3
	iadd
	invokeinterface	InterfaceMethod scala/collection/IndexedSeqOptimized.slice:(II)Ljava/lang/Object;
	checkcast	class "[B"
	invokevirtual	Method scala/io/Codec$.toUTF8:([B)[C
	invokevirtual	Method scala/Predef$.charArrayOps:([C)Lscala/collection/mutable/ArrayOps;
	invokeinterface	InterfaceMethod scala/collection/TraversableOnce.mkString:()Ljava/lang/String;
	areturn
  Labels:
  LocalVariableTable: 
   Start  Length  Slot  Name   Signature
   0      37      0    this       Lscala/io/UTF8Codec$;
   0      37      1    src       [B
   0      37      2    from       I
   0      37      3    len       I

  Deprecated: true

private scala.io.UTF8Codec$();
  Signature: ()V
  Code:
   Stack=7, Locals=1, Args_size=1
	aload_0
	invokespecial	Method java/lang/Object."<init>":()V
	aload_0
	putstatic	Field MODULE$:Lscala/io/UTF8Codec$;
	aload_0
	ldc	int 65533
	putfield	Field UNI_REPLACEMENT_CHAR:I
	aload_0
	getstatic	Field scala/Array$.MODULE$:Lscala/Array$;
	getstatic	Field scala/Predef$.MODULE$:Lscala/Predef$;
	iconst_3
	newarray byte
	dup
	iconst_0
	bipush	-17
	bastore
	dup
	iconst_1
	bipush	-65
	bastore
	dup
	iconst_2
	bipush	-67
	bastore
	invokevirtual	Method scala/Predef$.wrapByteArray:([B)Lscala/collection/mutable/WrappedArray;
	getstatic	Field scala/reflect/Manifest$.MODULE$:Lscala/reflect/Manifest$;
	invokevirtual	Method scala/reflect/Manifest$.Byte:()Lscala/reflect/AnyValManifest;
	invokevirtual	Method scala/Array$.apply:(Lscala/collection/Seq;Lscala/reflect/ClassManifest;)Ljava/lang/Object;
	checkcast	class "[B"
	putfield	Field UNI_REPLACEMENT_BYTES:[B
	return
  Labels:

}

