Compiled from "UTF8Codec.scala"
public final class scala.io.UTF8Codec extends java.lang.Object
  SourceFile: "UTF8Codec.scala"
  ScalaSig: length = 0x328
   05 00 6F 07 05 01 02 FFFFFF88 02 07 01 09 55 54 46 38
   43 6F 64 65 63 0A 02 03 04 01 02 69 6F 0A 01 05
   01 05 73 63 61 6C 61 03 00 10 02 08 09 0D 01 02
   06 08 0A 02 FFFFFF84 FFFFFF80 FFFFFF80 FFFFFF88 02 0B 02 09 55 54 46 38
   43 6F 64 65 63 13 03 09 0C 14 10 02 0D 12 0D 01
   0E 0A 02 0F 10 01 04 6C 61 6E 67 0A 01 11 01 04
   6A 61 76 61 09 02 13 0E 02 06 4F 62 6A 65 63 74
   10 02 15 16 0D 01 04 09 02 17 04 02 0B 53 63 61
   6C 61 4F 62 6A 65 63 74 08 05 19 09 FFFFFF84 00 1A 01
   06 3C 69 6E 69 74 3E 14 01 07 08 07 1C 09 FFFFFFC2 FFFFFF80
   FFFFFF84 02 1D 01 14 55 4E 49 5F 52 45 50 4C 41 43 45
   4D 45 4E 54 5F 43 48 41 52 15 01 1E 10 02 15 1F
   09 02 20 04 02 03 49 6E 74 08 06 22 09 FFFFFFA0 FFFFFF80 06
   1E 01 15 55 4E 49 5F 52 45 50 4C 41 43 45 4D 45
   4E 54 5F 43 48 41 52 20 08 07 24 09 FFFFFFC2 FFFFFF80 FFFFFF84 02
   25 01 15 55 4E 49 5F 52 45 50 4C 41 43 45 4D 45
   4E 54 5F 42 59 54 45 53 15 01 26 10 03 15 27 29
   09 02 28 04 02 05 41 72 72 61 79 10 02 15 2A 09
   02 2B 04 02 04 42 79 74 65 08 06 2D 09 FFFFFFA0 FFFFFF80 06
   26 01 16 55 4E 49 5F 52 45 50 4C 41 43 45 4D 45
   4E 54 5F 42 59 54 45 53 20 08 05 2F 09 FFFFFF84 00 30
   01 06 65 6E 63 6F 64 65 14 02 26 31 08 05 32 2E
   FFFFFFC0 00 1E 01 02 63 68 28 03 2E 34 37 10 02 15 35
   09 02 36 04 02 0A 64 65 70 72 65 63 61 74 65 64
   21 01 38 01 39 55 73 65 20 6E 65 77 20 53 74 72
   69 6E 67 28 41 72 72 61 79 28 63 68 29 2C 20 30
   2C 20 31 29 2E 67 65 74 42 79 74 65 73 28 22 55
   54 46 2D 38 22 29 20 69 6E 73 74 65 61 64 08 05
   2F 09 FFFFFF84 00 3A 14 06 1E 3B 41 43 45 47 08 05 3C
   39 FFFFFFC0 00 3D 01 03 73 72 63 10 03 15 27 3E 10 02
   15 3F 09 02 40 04 02 04 43 68 61 72 08 05 42 39
   FFFFFFC0 00 1E 01 04 66 72 6F 6D 08 05 44 39 FFFFFFC0 00 26
   01 03 64 73 74 08 05 46 39 FFFFFFC0 00 1E 01 02 74 6F
   08 05 48 39 FFFFFFC0 00 1E 01 03 6C 65 6E 28 03 39 34
   4A 21 01 4B 01 1A 55 73 65 20 43 6F 64 65 63 2E
   66 72 6F 6D 55 54 46 38 20 69 6E 73 74 65 61 64
   08 05 2F 09 FFFFFF84 00 4D 14 04 1E 4E 57 58 08 05 4F
   4C FFFFFFC0 00 50 01 01 73 10 02 51 54 0E 02 15 52 09
   02 53 04 01 06 50 72 65 64 65 66 09 02 55 56 02
   06 53 74 72 69 6E 67 0A 02 53 04 08 05 44 4C FFFFFFC0
   00 26 08 05 46 4C FFFFFFC0 00 1E 28 03 4C 34 4A 08 05
   2F 09 FFFFFF84 00 5B 14 02 26 5C 08 05 4F 5A FFFFFFC0 00 50
   28 03 5A 34 4A 08 05 5F 09 FFFFFF84 00 60 01 06 64 65
   63 6F 64 65 14 06 1E 61 62 63 64 65 08 05 3C 5E
   FFFFFFC0 00 26 08 05 42 5E FFFFFFC0 00 1E 08 05 44 5E FFFFFFC0 00
   3D 08 05 46 5E FFFFFFC0 00 1E 08 05 48 5E FFFFFFC0 00 1E 28
   03 5E 34 67 21 01 68 01 18 55 73 65 20 43 6F 64
   65 63 2E 74 6F 55 54 46 38 20 69 6E 73 74 65 61
   64 08 05 5F 09 FFFFFF84 00 6A 14 04 50 6B 6C 6D 08 05
   3C 69 FFFFFFC0 00 26 08 05 42 69 FFFFFFC0 00 1E 08 05 48 69
   FFFFFFC0 00 1E 28 03 69 34 67 
  minor version: 0
  major version: 49
  Constant pool:
const #1 = Asciz	SourceFile;
const #2 = Asciz	UTF8Codec.scala;
const #3 = Asciz	decode;
const #4 = Asciz	([BII)Ljava/lang/String;;
const #5 = Asciz	Code;
const #6 = Asciz	scala/io/UTF8Codec$;
const #7 = class	#6;	//  scala/io/UTF8Codec$
const #8 = Asciz	MODULE$;
const #9 = Asciz	Lscala/io/UTF8Codec$;;
const #10 = NameAndType	#8:#9;//  MODULE$:Lscala/io/UTF8Codec$;
const #11 = Field	#7.#10;	//  scala/io/UTF8Codec$.MODULE$:Lscala/io/UTF8Codec$;
const #12 = NameAndType	#3:#4;//  decode:([BII)Ljava/lang/String;
const #13 = Method	#7.#12;	//  scala/io/UTF8Codec$.decode:([BII)Ljava/lang/String;
const #14 = Asciz	([BI[CII)I;
const #15 = NameAndType	#3:#14;//  decode:([BI[CII)I
const #16 = Method	#7.#15;	//  scala/io/UTF8Codec$.decode:([BI[CII)I
const #17 = Asciz	encode;
const #18 = Asciz	(Ljava/lang/String;)[B;
const #19 = NameAndType	#17:#18;//  encode:(Ljava/lang/String;)[B
const #20 = Method	#7.#19;	//  scala/io/UTF8Codec$.encode:(Ljava/lang/String;)[B
const #21 = Asciz	(Ljava/lang/String;[BI)I;
const #22 = NameAndType	#17:#21;//  encode:(Ljava/lang/String;[BI)I
const #23 = Method	#7.#22;	//  scala/io/UTF8Codec$.encode:(Ljava/lang/String;[BI)I
const #24 = Asciz	([CI[BII)I;
const #25 = NameAndType	#17:#24;//  encode:([CI[BII)I
const #26 = Method	#7.#25;	//  scala/io/UTF8Codec$.encode:([CI[BII)I
const #27 = Asciz	(I)[B;
const #28 = NameAndType	#17:#27;//  encode:(I)[B
const #29 = Method	#7.#28;	//  scala/io/UTF8Codec$.encode:(I)[B
const #30 = Asciz	UNI_REPLACEMENT_BYTES;
const #31 = Asciz	()[B;
const #32 = NameAndType	#30:#31;//  UNI_REPLACEMENT_BYTES:()[B
const #33 = Method	#7.#32;	//  scala/io/UTF8Codec$.UNI_REPLACEMENT_BYTES:()[B
const #34 = Asciz	UNI_REPLACEMENT_CHAR;
const #35 = Asciz	()I;
const #36 = NameAndType	#34:#35;//  UNI_REPLACEMENT_CHAR:()I
const #37 = Method	#7.#36;	//  scala/io/UTF8Codec$.UNI_REPLACEMENT_CHAR:()I
const #38 = Asciz	ScalaSig;
const #39 = Asciz	scala/io/UTF8Codec;
const #40 = class	#39;	//  scala/io/UTF8Codec
const #41 = Asciz	java/lang/Object;
const #42 = class	#41;	//  java/lang/Object

{
public static final java.lang.String decode(byte[], int, int);
  Code:
   Stack=4, Locals=3, Args_size=3
   0:	getstatic	#11; //Field scala/io/UTF8Codec$.MODULE$:Lscala/io/UTF8Codec$;
   3:	aload_0
   4:	iload_1
   5:	iload_2
   6:	invokevirtual	#13; //Method scala/io/UTF8Codec$.decode:([BII)Ljava/lang/String;
   9:	areturn

public static final int decode(byte[], int, char[], int, int);
  Code:
   Stack=6, Locals=5, Args_size=5
   0:	getstatic	#11; //Field scala/io/UTF8Codec$.MODULE$:Lscala/io/UTF8Codec$;
   3:	aload_0
   4:	iload_1
   5:	aload_2
   6:	iload_3
   7:	iload	4
   9:	invokevirtual	#16; //Method scala/io/UTF8Codec$.decode:([BI[CII)I
   12:	ireturn

public static final byte[] encode(java.lang.String);
  Code:
   Stack=2, Locals=1, Args_size=1
   0:	getstatic	#11; //Field scala/io/UTF8Codec$.MODULE$:Lscala/io/UTF8Codec$;
   3:	aload_0
   4:	invokevirtual	#20; //Method scala/io/UTF8Codec$.encode:(Ljava/lang/String;)[B
   7:	areturn

public static final int encode(java.lang.String, byte[], int);
  Code:
   Stack=4, Locals=3, Args_size=3
   0:	getstatic	#11; //Field scala/io/UTF8Codec$.MODULE$:Lscala/io/UTF8Codec$;
   3:	aload_0
   4:	aload_1
   5:	iload_2
   6:	invokevirtual	#23; //Method scala/io/UTF8Codec$.encode:(Ljava/lang/String;[BI)I
   9:	ireturn

public static final int encode(char[], int, byte[], int, int);
  Code:
   Stack=6, Locals=5, Args_size=5
   0:	getstatic	#11; //Field scala/io/UTF8Codec$.MODULE$:Lscala/io/UTF8Codec$;
   3:	aload_0
   4:	iload_1
   5:	aload_2
   6:	iload_3
   7:	iload	4
   9:	invokevirtual	#26; //Method scala/io/UTF8Codec$.encode:([CI[BII)I
   12:	ireturn

public static final byte[] encode(int);
  Code:
   Stack=2, Locals=1, Args_size=1
   0:	getstatic	#11; //Field scala/io/UTF8Codec$.MODULE$:Lscala/io/UTF8Codec$;
   3:	iload_0
   4:	invokevirtual	#29; //Method scala/io/UTF8Codec$.encode:(I)[B
   7:	areturn

public static final byte[] UNI_REPLACEMENT_BYTES();
  Code:
   Stack=1, Locals=0, Args_size=0
   0:	getstatic	#11; //Field scala/io/UTF8Codec$.MODULE$:Lscala/io/UTF8Codec$;
   3:	invokevirtual	#33; //Method scala/io/UTF8Codec$.UNI_REPLACEMENT_BYTES:()[B
   6:	areturn

public static final int UNI_REPLACEMENT_CHAR();
  Code:
   Stack=1, Locals=0, Args_size=0
   0:	getstatic	#11; //Field scala/io/UTF8Codec$.MODULE$:Lscala/io/UTF8Codec$;
   3:	invokevirtual	#37; //Method scala/io/UTF8Codec$.UNI_REPLACEMENT_CHAR:()I
   6:	ireturn

}

