Compiled from "StdTokens.scala"
public final class scala.util.parsing.combinator.token.StdTokens$NumericLit$ extends java.lang.Object implements scala.Function1,scala.ScalaObject
  SourceFile: "StdTokens.scala"
  Scala: length = 0x
   
  InnerClass: 
   public NumericLit=class scala/util/parsing/combinator/token/StdTokens$NumericLit of class scala/util/parsing/combinator/token/StdTokens
  minor version: 0
  major version: 49
  Constant pool:
Asciz	SourceFile;
Asciz	StdTokens.scala;
Asciz	Scala;
Asciz	$outer;
Asciz	Lscala/util/parsing/combinator/token/StdTokens;;
Asciz	toString;
Asciz	()Ljava/lang/String;;
Asciz	Code;
Asciz	LineNumberTable;
Asciz	scala/Function1$class;
class	scala/Function1$class
Asciz	(Lscala/Function1;)Ljava/lang/String;;
NameAndType	toString:(Lscala/Function1;)Ljava/lang/String;
Method	scala/Function1$class.toString:(Lscala/Function1;)Ljava/lang/String;
Asciz	compose;
Asciz	(Lscala/Function1;)Lscala/Function1;;
Asciz	(Lscala/Function1;Lscala/Function1;)Lscala/Function1;;
NameAndType	compose:(Lscala/Function1;Lscala/Function1;)Lscala/Function1;
Method	scala/Function1$class.compose:(Lscala/Function1;Lscala/Function1;)Lscala/Function1;
Asciz	this;
Asciz	Lscala/util/parsing/combinator/token/StdTokens$NumericLit$;;
Asciz	g;
Asciz	Lscala/Function1;;
Asciz	LocalVariableTable;
Asciz	andThen;
NameAndType	andThen:(Lscala/Function1;Lscala/Function1;)Lscala/Function1;
Method	scala/Function1$class.andThen:(Lscala/Function1;Lscala/Function1;)Lscala/Function1;
Asciz	unapply;
Asciz	(Lscala/util/parsing/combinator/token/StdTokens$NumericLit;)Lscala/Option;;
Asciz	java/lang/Object;
class	java/lang/Object
Asciz	equals;
Asciz	(Ljava/lang/Object;)Z;
NameAndType	equals:(Ljava/lang/Object;)Z
Method	java/lang/Object.equals:(Ljava/lang/Object;)Z
Asciz	scala/None$;
class	scala/None$
Asciz	MODULE$;
Asciz	Lscala/None$;;
NameAndType	MODULE$:Lscala/None$;
Field	scala/None$.MODULE$:Lscala/None$;
Asciz	scala/Some;
class	scala/Some
Asciz	scala/util/parsing/combinator/token/StdTokens$NumericLit;
class	scala/util/parsing/combinator/token/StdTokens$NumericLit
Asciz	chars;
NameAndType	chars:()Ljava/lang/String;
Method	scala/util/parsing/combinator/token/StdTokens$NumericLit.chars:()Ljava/lang/String;
Asciz	<init>;
Asciz	(Ljava/lang/Object;)V;
NameAndType	"<init>":(Ljava/lang/Object;)V
Method	scala/Some."<init>":(Ljava/lang/Object;)V
Asciz	x$0;
Asciz	Lscala/util/parsing/combinator/token/StdTokens$NumericLit;;
Asciz	apply;
Asciz	(Ljava/lang/String;)Lscala/util/parsing/combinator/token/StdTokens$NumericLit;;
Asciz	scala/util/parsing/combinator/token/StdTokens$NumericLit$;
class	scala/util/parsing/combinator/token/StdTokens$NumericLit$
NameAndType	$outer:Lscala/util/parsing/combinator/token/StdTokens;
Field	scala/util/parsing/combinator/token/StdTokens$NumericLit$.$outer:Lscala/util/parsing/combinator/token/StdTokens;
Asciz	(Lscala/util/parsing/combinator/token/StdTokens;Ljava/lang/String;)V;
NameAndType	"<init>":(Lscala/util/parsing/combinator/token/StdTokens;Ljava/lang/String;)V
Method	scala/util/parsing/combinator/token/StdTokens$NumericLit."<init>":(Lscala/util/parsing/combinator/token/StdTokens;Ljava/lang/String;)V
Asciz	Ljava/lang/String;;
Asciz	(Ljava/lang/Object;)Ljava/lang/Object;;
Asciz	java/lang/String;
class	java/lang/String
NameAndType	apply:(Ljava/lang/String;)Lscala/util/parsing/combinator/token/StdTokens$NumericLit;
Method	scala/util/parsing/combinator/token/StdTokens$NumericLit$.apply:(Ljava/lang/String;)Lscala/util/parsing/combinator/token/StdTokens$NumericLit;
Asciz	v1;
Asciz	Ljava/lang/Object;;
Asciz	(Lscala/util/parsing/combinator/token/StdTokens;)V;
Asciz	java/lang/NullPointerException;
class	java/lang/NullPointerException
Asciz	()V;
NameAndType	"<init>":()V
Method	java/lang/NullPointerException."<init>":()V
Method	java/lang/Object."<init>":()V
Asciz	$init$;
Asciz	(Lscala/Function1;)V;
NameAndType	$init$:(Lscala/Function1;)V
Method	scala/Function1$class.$init$:(Lscala/Function1;)V
Asciz	InnerClasses;
Asciz	scala/util/parsing/combinator/token/StdTokens;
class	scala/util/parsing/combinator/token/StdTokens
Asciz	NumericLit;
Asciz	scala/Function1;
class	scala/Function1
Asciz	scala/ScalaObject;
class	scala/ScalaObject

{
public final scala.util.parsing.combinator.token.StdTokens $outer;
  Signature: Lscala/util/parsing/combinator/token/StdTokens;

public java.lang.String toString();
  Signature: ()Ljava/lang/String;
  Code:
   Stack=1, Locals=1, Args_size=1
	aload_0
	invokestatic	Method scala/Function1$class.toString:(Lscala/Function1;)Ljava/lang/String;
	areturn
  Labels:

public scala.Function1 compose(scala.Function1);
  Signature: (Lscala/Function1;)Lscala/Function1;
  Code:
   Stack=2, Locals=2, Args_size=2
	aload_0
	aload_1
	invokestatic	Method scala/Function1$class.compose:(Lscala/Function1;Lscala/Function1;)Lscala/Function1;
	areturn
  Labels:
  LocalVariableTable: 
   Start  Length  Slot  Name   Signature
   0      6      0    this       Lscala/util/parsing/combinator/token/StdTokens$NumericLit$;
   0      6      1    g       Lscala/Function1;


public scala.Function1 andThen(scala.Function1);
  Signature: (Lscala/Function1;)Lscala/Function1;
  Code:
   Stack=2, Locals=2, Args_size=2
	aload_0
	aload_1
	invokestatic	Method scala/Function1$class.andThen:(Lscala/Function1;Lscala/Function1;)Lscala/Function1;
	areturn
  Labels:
  LocalVariableTable: 
   Start  Length  Slot  Name   Signature
   0      6      0    this       Lscala/util/parsing/combinator/token/StdTokens$NumericLit$;
   0      6      1    g       Lscala/Function1;


public scala.Option unapply(scala.util.parsing.combinator.token.StdTokens$NumericLit);
  Signature: (Lscala/util/parsing/combinator/token/StdTokens$NumericLit;)Lscala/Option;
  Code:
   Stack=3, Locals=2, Args_size=2
	aload_1
	dup
	pop
	ifnull	l1 // getstatic
	aload_1
	aconst_null
	invokevirtual	Method java/lang/Object.equals:(Ljava/lang/Object;)Z
	ifeq	l2 // new
l1	getstatic	Field scala/None$.MODULE$:Lscala/None$;
	goto	l3 // areturn
l2	new	class scala/Some
	dup
	aload_1
	invokevirtual	Method scala/util/parsing/combinator/token/StdTokens$NumericLit.chars:()Ljava/lang/String;
	invokespecial	Method scala/Some."<init>":(Ljava/lang/Object;)V
l3	areturn
  Labels:
   	l1 = 14 // getstatic
   	l2 = 20 // new
   	l3 = 31 // areturn
  LocalVariableTable: 
   Start  Length  Slot  Name   Signature
   0      32      0    this       Lscala/util/parsing/combinator/token/StdTokens$NumericLit$;
   0      32      1    x$0       Lscala/util/parsing/combinator/token/StdTokens$NumericLit;


public scala.util.parsing.combinator.token.StdTokens$NumericLit apply(java.lang.String);
  Signature: (Ljava/lang/String;)Lscala/util/parsing/combinator/token/StdTokens$NumericLit;
  Code:
   Stack=4, Locals=3, Args_size=2
	aload_0
	getfield	Field $outer:Lscala/util/parsing/combinator/token/StdTokens;
	astore_2
	new	class scala/util/parsing/combinator/token/StdTokens$NumericLit
	dup
	aload_0
	getfield	Field $outer:Lscala/util/parsing/combinator/token/StdTokens;
	aload_1
	invokespecial	Method scala/util/parsing/combinator/token/StdTokens$NumericLit."<init>":(Lscala/util/parsing/combinator/token/StdTokens;Ljava/lang/String;)V
	areturn
  Labels:
  LocalVariableTable: 
   Start  Length  Slot  Name   Signature
   0      18      0    this       Lscala/util/parsing/combinator/token/StdTokens$NumericLit$;
   5      13      1    chars       Ljava/lang/String;


public java.lang.Object apply(java.lang.Object);
  Signature: (Ljava/lang/Object;)Ljava/lang/Object;
  Code:
   Stack=2, Locals=3, Args_size=2
	aload_0
	getfield	Field $outer:Lscala/util/parsing/combinator/token/StdTokens;
	astore_2
	aload_0
	aload_1
	checkcast	class java/lang/String
	invokevirtual	Method apply:(Ljava/lang/String;)Lscala/util/parsing/combinator/token/StdTokens$NumericLit;
	areturn
  Labels:
  LocalVariableTable: 
   Start  Length  Slot  Name   Signature
   0      14      0    this       Lscala/util/parsing/combinator/token/StdTokens$NumericLit$;
   5      9      1    v1       Ljava/lang/Object;


public scala.util.parsing.combinator.token.StdTokens$NumericLit$(scala.util.parsing.combinator.token.StdTokens);
  Signature: (Lscala/util/parsing/combinator/token/StdTokens;)V
  Code:
   Stack=2, Locals=2, Args_size=2
	aload_1
	ifnonnull	l1 // aload_0
	new	class java/lang/NullPointerException
	dup
	invokespecial	Method java/lang/NullPointerException."<init>":()V
	athrow
l1	aload_0
	aload_1
	putfield	Field $outer:Lscala/util/parsing/combinator/token/StdTokens;
	aload_0
	invokespecial	Method java/lang/Object."<init>":()V
	aload_0
	invokestatic	Method scala/Function1$class.$init$:(Lscala/Function1;)V
	return
  Labels:
   	l1 = 12 // aload_0
  LocalVariableTable: 
   Start  Length  Slot  Name   Signature
   0      26      0    this       Lscala/util/parsing/combinator/token/StdTokens$NumericLit$;
   0      26      1    $outer       Lscala/util/parsing/combinator/token/StdTokens;


}

