Compiled from "Tokens.scala"
public final class scala.util.parsing.combinator.token.Tokens$EOF$ extends scala.util.parsing.combinator.token.Tokens$Token implements scala.ScalaObject,scala.Product,java.io.Serializable
  SourceFile: "Tokens.scala"
  Scala: length = 0x
   
  InnerClass: 
   public abstract Token=class scala/util/parsing/combinator/token/Tokens$Token of class scala/util/parsing/combinator/token/Tokens
  minor version: 0
  major version: 49
  Constant pool:
Asciz	SourceFile;
Asciz	Tokens.scala;
Asciz	Scala;
Asciz	productIterator;
Asciz	()Lscala/collection/Iterator;;
Asciz	Code;
Asciz	LineNumberTable;
Asciz	scala/Product$class;
class	scala/Product$class
Asciz	(Lscala/Product;)Lscala/collection/Iterator;;
NameAndType	productIterator:(Lscala/Product;)Lscala/collection/Iterator;
Method	scala/Product$class.productIterator:(Lscala/Product;)Lscala/collection/Iterator;
Asciz	productElements;
NameAndType	productElements:(Lscala/Product;)Lscala/collection/Iterator;
Method	scala/Product$class.productElements:(Lscala/Product;)Lscala/collection/Iterator;
Asciz	Deprecated;
Asciz	chars;
Asciz	()Ljava/lang/String;;
Asciz	<eof>;
String	<eof>
Asciz	toString;
Asciz	EOF;
String	EOF
Asciz	productPrefix;
Asciz	productArity;
Asciz	()I;
Asciz	productElement;
Asciz	(I)Ljava/lang/Object;;
Asciz	java/lang/IndexOutOfBoundsException;
class	java/lang/IndexOutOfBoundsException
Asciz	scala/runtime/BoxesRunTime;
class	scala/runtime/BoxesRunTime
Asciz	boxToInteger;
Asciz	(I)Ljava/lang/Integer;;
NameAndType	boxToInteger:(I)Ljava/lang/Integer;
Method	scala/runtime/BoxesRunTime.boxToInteger:(I)Ljava/lang/Integer;
Asciz	java/lang/Object;
class	java/lang/Object
NameAndType	toString:()Ljava/lang/String;
Method	java/lang/Object.toString:()Ljava/lang/String;
Asciz	<init>;
Asciz	(Ljava/lang/String;)V;
NameAndType	"<init>":(Ljava/lang/String;)V
Method	java/lang/IndexOutOfBoundsException."<init>":(Ljava/lang/String;)V
Asciz	productElementName;
Asciz	(I)Ljava/lang/String;;
Asciz	canEqual;
Asciz	(Ljava/lang/Object;)Z;
Asciz	scala/util/parsing/combinator/token/Tokens$EOF$;
class	scala/util/parsing/combinator/token/Tokens$EOF$
Asciz	readResolve;
Asciz	()Ljava/lang/Object;;
Asciz	scala$util$parsing$combinator$token$Tokens$EOF$$$outer;
Asciz	()Lscala/util/parsing/combinator/token/Tokens;;
NameAndType	scala$util$parsing$combinator$token$Tokens$EOF$$$outer:()Lscala/util/parsing/combinator/token/Tokens;
Method	scala/util/parsing/combinator/token/Tokens$EOF$.scala$util$parsing$combinator$token$Tokens$EOF$$$outer:()Lscala/util/parsing/combinator/token/Tokens;
Asciz	scala/util/parsing/combinator/token/Tokens;
class	scala/util/parsing/combinator/token/Tokens
Asciz	()Lscala/util/parsing/combinator/token/Tokens$EOF$;;
NameAndType	EOF:()Lscala/util/parsing/combinator/token/Tokens$EOF$;
InterfaceMethod	scala/util/parsing/combinator/token/Tokens.EOF:()Lscala/util/parsing/combinator/token/Tokens$EOF$;
Asciz	scala/util/parsing/combinator/token/Tokens$Token;
class	scala/util/parsing/combinator/token/Tokens$Token
Asciz	$outer;
Asciz	Lscala/util/parsing/combinator/token/Tokens;;
NameAndType	$outer:Lscala/util/parsing/combinator/token/Tokens;
Field	scala/util/parsing/combinator/token/Tokens$Token.$outer:Lscala/util/parsing/combinator/token/Tokens;
Asciz	(Lscala/util/parsing/combinator/token/Tokens;)V;
NameAndType	"<init>":(Lscala/util/parsing/combinator/token/Tokens;)V
Method	scala/util/parsing/combinator/token/Tokens$Token."<init>":(Lscala/util/parsing/combinator/token/Tokens;)V
Asciz	$init$;
Asciz	(Lscala/Product;)V;
NameAndType	$init$:(Lscala/Product;)V
Method	scala/Product$class.$init$:(Lscala/Product;)V
Asciz	this;
Asciz	Lscala/util/parsing/combinator/token/Tokens$EOF$;;
Asciz	LocalVariableTable;
Asciz	InnerClasses;
Asciz	Token;
Asciz	scala/ScalaObject;
class	scala/ScalaObject
Asciz	scala/Product;
class	scala/Product
Asciz	java/io/Serializable;
class	java/io/Serializable

{
public scala.collection.Iterator productIterator();
  Signature: ()Lscala/collection/Iterator;
  Code:
   Stack=1, Locals=1, Args_size=1
	aload_0
	invokestatic	Method scala/Product$class.productIterator:(Lscala/Product;)Lscala/collection/Iterator;
	areturn
  Labels:

public scala.collection.Iterator productElements();
  Signature: ()Lscala/collection/Iterator;
  Code:
   Stack=1, Locals=1, Args_size=1
	aload_0
	invokestatic	Method scala/Product$class.productElements:(Lscala/Product;)Lscala/collection/Iterator;
	areturn
  Labels:
  Deprecated: true

public java.lang.String chars();
  Signature: ()Ljava/lang/String;
  Code:
   Stack=1, Locals=1, Args_size=1
	ldc	String <eof>
	areturn
  Labels:

public final java.lang.String toString();
  Signature: ()Ljava/lang/String;
  Code:
   Stack=1, Locals=1, Args_size=1
	ldc	String EOF
	areturn
  Labels:

public java.lang.String productPrefix();
  Signature: ()Ljava/lang/String;
  Code:
   Stack=1, Locals=1, Args_size=1
	ldc	String EOF
	areturn
  Labels:

public int productArity();
  Signature: ()I
  Code:
   Stack=1, Locals=1, Args_size=1
	iconst_0
	ireturn
  Labels:

public java.lang.Object productElement(int);
  Signature: (I)Ljava/lang/Object;
  Code:
   Stack=3, Locals=2, Args_size=2
	new	class java/lang/IndexOutOfBoundsException
	dup
	iload_1
	invokestatic	Method scala/runtime/BoxesRunTime.boxToInteger:(I)Ljava/lang/Integer;
	invokevirtual	Method java/lang/Object.toString:()Ljava/lang/String;
	invokespecial	Method java/lang/IndexOutOfBoundsException."<init>":(Ljava/lang/String;)V
	athrow
  Labels:

public java.lang.String productElementName(int);
  Signature: (I)Ljava/lang/String;
  Code:
   Stack=3, Locals=2, Args_size=2
	new	class java/lang/IndexOutOfBoundsException
	dup
	iload_1
	invokestatic	Method scala/runtime/BoxesRunTime.boxToInteger:(I)Ljava/lang/Integer;
	invokevirtual	Method java/lang/Object.toString:()Ljava/lang/String;
	invokespecial	Method java/lang/IndexOutOfBoundsException."<init>":(Ljava/lang/String;)V
	athrow
  Labels:

public boolean canEqual(java.lang.Object);
  Signature: (Ljava/lang/Object;)Z
  Code:
   Stack=1, Locals=2, Args_size=2
	aload_1
	instanceof	class scala/util/parsing/combinator/token/Tokens$EOF$
	ireturn
  Labels:

public java.lang.Object readResolve();
  Signature: ()Ljava/lang/Object;
  Code:
   Stack=1, Locals=1, Args_size=1
	aload_0
	invokevirtual	Method scala$util$parsing$combinator$token$Tokens$EOF$$$outer:()Lscala/util/parsing/combinator/token/Tokens;
	invokeinterface	InterfaceMethod scala/util/parsing/combinator/token/Tokens.EOF:()Lscala/util/parsing/combinator/token/Tokens$EOF$;
	areturn
  Labels:

public scala.util.parsing.combinator.token.Tokens scala$util$parsing$combinator$token$Tokens$EOF$$$outer();
  Signature: ()Lscala/util/parsing/combinator/token/Tokens;
  Code:
   Stack=1, Locals=1, Args_size=1
	aload_0
	getfield	Field scala/util/parsing/combinator/token/Tokens$Token.$outer:Lscala/util/parsing/combinator/token/Tokens;
	areturn
  Labels:

public scala.util.parsing.combinator.token.Tokens$EOF$(scala.util.parsing.combinator.token.Tokens);
  Signature: (Lscala/util/parsing/combinator/token/Tokens;)V
  Code:
   Stack=2, Locals=2, Args_size=2
	aload_0
	aload_1
	invokespecial	Method scala/util/parsing/combinator/token/Tokens$Token."<init>":(Lscala/util/parsing/combinator/token/Tokens;)V
	aload_0
	invokestatic	Method scala/Product$class.$init$:(Lscala/Product;)V
	return
  Labels:
  LocalVariableTable: 
   Start  Length  Slot  Name   Signature
   0      10      0    this       Lscala/util/parsing/combinator/token/Tokens$EOF$;
   0      10      1    $outer       Lscala/util/parsing/combinator/token/Tokens;


}

