class scala.actors.forkjoin.ForkJoinPool$DefaultForkJoinWorkerThreadFactory extends java.lang.Object implements scala.actors.forkjoin.ForkJoinPool$ForkJoinWorkerThreadFactory
  InnerClass: 
   #19= #5 of #17; //DefaultForkJoinWorkerThreadFactory=class scala/actors/forkjoin/ForkJoinPool$DefaultForkJoinWorkerThreadFactory of class scala/actors/forkjoin/ForkJoinPool
   public abstract #23= #7 of #17; //ForkJoinWorkerThreadFactory=class scala/actors/forkjoin/ForkJoinPool$ForkJoinWorkerThreadFactory of class scala/actors/forkjoin/ForkJoinPool
  minor version: 0
  major version: 49
  Constant pool:
const #1 = Method	#6.#13;	//  java/lang/Object."<init>":()V
const #2 = class	#14;	//  scala/actors/forkjoin/ForkJoinWorkerThread
const #3 = Method	#2.#15;	//  scala/actors/forkjoin/ForkJoinWorkerThread."<init>":(Lscala/actors/forkjoin/ForkJoinPool;)V
const #4 = class	#16;	//  java/lang/OutOfMemoryError
const #5 = class	#18;	//  scala/actors/forkjoin/ForkJoinPool$DefaultForkJoinWorkerThreadFactory
const #6 = class	#21;	//  java/lang/Object
const #7 = class	#22;	//  scala/actors/forkjoin/ForkJoinPool$ForkJoinWorkerThreadFactory
const #8 = Asciz	<init>;
const #9 = Asciz	()V;
const #10 = Asciz	Code;
const #11 = Asciz	newThread;
const #12 = Asciz	(Lscala/actors/forkjoin/ForkJoinPool;)Lscala/actors/forkjoin/ForkJoinWorkerThread;;
const #13 = NameAndType	#8:#9;//  "<init>":()V
const #14 = Asciz	scala/actors/forkjoin/ForkJoinWorkerThread;
const #15 = NameAndType	#8:#24;//  "<init>":(Lscala/actors/forkjoin/ForkJoinPool;)V
const #16 = Asciz	java/lang/OutOfMemoryError;
const #17 = class	#25;	//  scala/actors/forkjoin/ForkJoinPool
const #18 = Asciz	scala/actors/forkjoin/ForkJoinPool$DefaultForkJoinWorkerThreadFactory;
const #19 = Asciz	DefaultForkJoinWorkerThreadFactory;
const #20 = Asciz	InnerClasses;
const #21 = Asciz	java/lang/Object;
const #22 = Asciz	scala/actors/forkjoin/ForkJoinPool$ForkJoinWorkerThreadFactory;
const #23 = Asciz	ForkJoinWorkerThreadFactory;
const #24 = Asciz	(Lscala/actors/forkjoin/ForkJoinPool;)V;
const #25 = Asciz	scala/actors/forkjoin/ForkJoinPool;

{
scala.actors.forkjoin.ForkJoinPool$DefaultForkJoinWorkerThreadFactory();
  Code:
   Stack=1, Locals=1, Args_size=1
   0:	aload_0
   1:	invokespecial	#1; //Method java/lang/Object."<init>":()V
   4:	return

public scala.actors.forkjoin.ForkJoinWorkerThread newThread(scala.actors.forkjoin.ForkJoinPool);
  Code:
   Stack=3, Locals=3, Args_size=2
   0:	new	#2; //class scala/actors/forkjoin/ForkJoinWorkerThread
   3:	dup
   4:	aload_1
   5:	invokespecial	#3; //Method scala/actors/forkjoin/ForkJoinWorkerThread."<init>":(Lscala/actors/forkjoin/ForkJoinPool;)V
   8:	areturn
   9:	astore_2
   10:	aconst_null
   11:	areturn
  Exception table:
   from   to  target type
     0     8     9   Class java/lang/OutOfMemoryError


}

