class scala.actors.forkjoin.ThreadLocalRandom$1 extends java.lang.ThreadLocal
  Signature: length = 0x2
   00 0E 
  EnclosingMethod: length = 0x4
   00 02 00 00 
  InnerClass: 
   #5; //class scala/actors/forkjoin/ThreadLocalRandom$1
  minor version: 0
  major version: 49
  Constant pool:
const #1 = Method	#6.#16;	//  java/lang/ThreadLocal."<init>":()V
const #2 = class	#17;	//  scala/actors/forkjoin/ThreadLocalRandom
const #3 = Method	#2.#16;	//  scala/actors/forkjoin/ThreadLocalRandom."<init>":()V
const #4 = Method	#5.#18;	//  scala/actors/forkjoin/ThreadLocalRandom$1.initialValue:()Lscala/actors/forkjoin/ThreadLocalRandom;
const #5 = class	#19;	//  scala/actors/forkjoin/ThreadLocalRandom$1
const #6 = class	#22;	//  java/lang/ThreadLocal
const #7 = Asciz	<init>;
const #8 = Asciz	()V;
const #9 = Asciz	Code;
const #10 = Asciz	initialValue;
const #11 = Asciz	()Lscala/actors/forkjoin/ThreadLocalRandom;;
const #12 = Asciz	()Ljava/lang/Object;;
const #13 = Asciz	Signature;
const #14 = Asciz	Ljava/lang/ThreadLocal<Lscala/actors/forkjoin/ThreadLocalRandom;>;;
const #15 = Asciz	EnclosingMethod;
const #16 = NameAndType	#7:#8;//  "<init>":()V
const #17 = Asciz	scala/actors/forkjoin/ThreadLocalRandom;
const #18 = NameAndType	#10:#11;//  initialValue:()Lscala/actors/forkjoin/ThreadLocalRandom;
const #19 = Asciz	scala/actors/forkjoin/ThreadLocalRandom$1;
const #20 = Asciz	;
const #21 = Asciz	InnerClasses;
const #22 = Asciz	java/lang/ThreadLocal;

{
scala.actors.forkjoin.ThreadLocalRandom$1();
  Code:
   Stack=1, Locals=1, Args_size=1
   0:	aload_0
   1:	invokespecial	#1; //Method java/lang/ThreadLocal."<init>":()V
   4:	return

protected scala.actors.forkjoin.ThreadLocalRandom initialValue();
  Code:
   Stack=2, Locals=1, Args_size=1
   0:	new	#2; //class scala/actors/forkjoin/ThreadLocalRandom
   3:	dup
   4:	invokespecial	#3; //Method scala/actors/forkjoin/ThreadLocalRandom."<init>":()V
   7:	areturn

protected java.lang.Object initialValue();
  Code:
   Stack=1, Locals=1, Args_size=1
   0:	aload_0
   1:	invokevirtual	#4; //Method initialValue:()Lscala/actors/forkjoin/ThreadLocalRandom;
   4:	areturn

}

