Compiled from "AutoStarter.scala"
public class net.rfc1149.harassme.AutoStarter extends android.content.BroadcastReceiver implements net.rfc1149.harassme.Prefs
  ScalaSig: length = 0x12B
   05 00 30 06 08 01 02 FFFFFF84 FFFFFF80 FFFFFF80 FFFFFF80 00 09 02 0B 41
   75 74 6F 53 74 61 72 74 65 72 0A 02 03 04 01 08
   68 61 72 61 73 73 6D 65 0A 02 05 06 01 07 72 66
   63 31 31 34 39 0A 01 07 01 03 6E 65 74 03 00 13
   04 00 0A 12 16 10 02 0B 10 0D 01 0C 0A 02 0D 0E
   01 07 63 6F 6E 74 65 6E 74 0A 01 0F 01 07 61 6E
   64 72 6F 69 64 09 02 11 0C 02 11 42 72 6F 61 64
   63 61 73 74 52 65 63 65 69 76 65 72 10 02 13 14
   0D 01 02 09 02 15 02 02 05 50 72 65 66 73 10 02
   17 1A 0D 01 18 0A 01 19 01 05 73 63 61 6C 61 09
   02 1B 18 02 0B 53 63 61 6C 61 4F 62 6A 65 63 74
   08 05 1D 00 FFFFFF84 00 1E 01 06 3C 69 6E 69 74 3E 14
   01 1F 10 02 13 00 08 05 21 00 FFFFFF84 20 22 01 09 6F
   6E 52 65 63 65 69 76 65 14 03 23 26 2B 10 02 17
   24 09 02 25 18 02 04 55 6E 69 74 08 05 27 20 FFFFFFC0
   00 28 01 07 63 6F 6E 74 65 78 74 10 02 0B 29 09
   02 2A 0C 02 07 43 6F 6E 74 65 78 74 08 05 2C 20
   FFFFFFC0 00 2D 01 06 69 6E 74 65 6E 74 10 02 0B 2E 09
   02 2F 0C 02 06 49 6E 74 65 6E 74 
  SourceFile: "AutoStarter.scala"
  minor version: 0
  major version: 49
  Constant pool:
class	android/content/BroadcastReceiver
class	net/rfc1149/harassme/AutoStarter
class	net/rfc1149/harassme/HarassMeService$
class	net/rfc1149/harassme/Prefs
class	net/rfc1149/harassme/Prefs$class
Field	net/rfc1149/harassme/HarassMeService$.MODULE$:Lnet/rfc1149/harassme/HarassMeService$;
Method	android/content/BroadcastReceiver."<init>":()V
Method	net/rfc1149/harassme/HarassMeService$.startService:(Landroid/content/Context;)V
Method	net/rfc1149/harassme/Prefs$class.$init$:(Lnet/rfc1149/harassme/Prefs;)V
Method	net/rfc1149/harassme/Prefs$class.callCount:(Lnet/rfc1149/harassme/Prefs;Landroid/content/Context;)I
Method	net/rfc1149/harassme/Prefs$class.minutesCount:(Lnet/rfc1149/harassme/Prefs;Landroid/content/Context;)I
Method	net/rfc1149/harassme/Prefs$class.serviceActivated:(Lnet/rfc1149/harassme/Prefs;Landroid/content/Context;)Z
Method	net/rfc1149/harassme/Prefs$class.volume:(Lnet/rfc1149/harassme/Prefs;Landroid/content/Context;)I
InterfaceMethod	net/rfc1149/harassme/Prefs.serviceActivated:(Landroid/content/Context;)Z
NameAndType	$init$:(Lnet/rfc1149/harassme/Prefs;)V
NameAndType	"<init>":()V
NameAndType	MODULE$:Lnet/rfc1149/harassme/HarassMeService$;
NameAndType	callCount:(Lnet/rfc1149/harassme/Prefs;Landroid/content/Context;)I
NameAndType	minutesCount:(Lnet/rfc1149/harassme/Prefs;Landroid/content/Context;)I
NameAndType	serviceActivated:(Landroid/content/Context;)Z
NameAndType	serviceActivated:(Lnet/rfc1149/harassme/Prefs;Landroid/content/Context;)Z
NameAndType	startService:(Landroid/content/Context;)V
NameAndType	volume:(Lnet/rfc1149/harassme/Prefs;Landroid/content/Context;)I
Asciz	$init$;
Asciz	()V;
Asciz	(Landroid/content/Context;)I;
Asciz	(Landroid/content/Context;)V;
Asciz	(Landroid/content/Context;)Z;
Asciz	(Landroid/content/Context;Landroid/content/Intent;)V;
Asciz	(Lnet/rfc1149/harassme/Prefs;)V;
Asciz	(Lnet/rfc1149/harassme/Prefs;Landroid/content/Context;)I;
Asciz	(Lnet/rfc1149/harassme/Prefs;Landroid/content/Context;)Z;
Asciz	<init>;
Asciz	AutoStarter.scala;
Asciz	Code;
Asciz	Landroid/content/Context;;
Asciz	Landroid/content/Intent;;
Asciz	LineNumberTable;
Asciz	Lnet/rfc1149/harassme/AutoStarter;;
Asciz	Lnet/rfc1149/harassme/HarassMeService$;;
Asciz	LocalVariableTable;
Asciz	MODULE$;
Asciz	ScalaSig;
Asciz	SourceFile;
Asciz	android/content/BroadcastReceiver;
Asciz	callCount;
Asciz	context;
Asciz	intent;
Asciz	minutesCount;
Asciz	net/rfc1149/harassme/AutoStarter;
Asciz	net/rfc1149/harassme/HarassMeService$;
Asciz	net/rfc1149/harassme/Prefs;
Asciz	net/rfc1149/harassme/Prefs$class;
Asciz	onReceive;
Asciz	serviceActivated;
Asciz	startService;
Asciz	this;
Asciz	volume;

{
public net.rfc1149.harassme.AutoStarter();
  Signature: ()V
  Code:
   Stack=1, Locals=1, Args_size=1
	aload_0
	invokespecial	Method android/content/BroadcastReceiver."<init>":()V
	aload_0
	invokestatic	Method net/rfc1149/harassme/Prefs$class.$init$:(Lnet/rfc1149/harassme/Prefs;)V
	return
  Labels:

public void onReceive(android.content.Context, android.content.Intent);
  Signature: (Landroid/content/Context;Landroid/content/Intent;)V
  Code:
   Stack=2, Locals=3, Args_size=3
	aload_0
	aload_1
	invokeinterface	InterfaceMethod net/rfc1149/harassme/Prefs.serviceActivated:(Landroid/content/Context;)Z
	ifeq	l1 // return
	getstatic	Field net/rfc1149/harassme/HarassMeService$.MODULE$:Lnet/rfc1149/harassme/HarassMeService$;
	aload_1
	invokevirtual	Method net/rfc1149/harassme/HarassMeService$.startService:(Landroid/content/Context;)V
l1	return
  Labels:
   	l1 = 17 // return
  LocalVariableTable: 
   Start  Length  Slot  Name   Signature
   0      18      0    this       Lnet/rfc1149/harassme/AutoStarter;
   0      18      1    context       Landroid/content/Context;
   0      18      2    intent       Landroid/content/Intent;


public int volume(android.content.Context);
  Signature: (Landroid/content/Context;)I
  Code:
   Stack=2, Locals=2, Args_size=2
	aload_0
	aload_1
	invokestatic	Method net/rfc1149/harassme/Prefs$class.volume:(Lnet/rfc1149/harassme/Prefs;Landroid/content/Context;)I
	ireturn
  Labels:
  LocalVariableTable: 
   Start  Length  Slot  Name   Signature
   0      6      0    this       Lnet/rfc1149/harassme/AutoStarter;
   0      6      1    context       Landroid/content/Context;


public int minutesCount(android.content.Context);
  Signature: (Landroid/content/Context;)I
  Code:
   Stack=2, Locals=2, Args_size=2
	aload_0
	aload_1
	invokestatic	Method net/rfc1149/harassme/Prefs$class.minutesCount:(Lnet/rfc1149/harassme/Prefs;Landroid/content/Context;)I
	ireturn
  Labels:
  LocalVariableTable: 
   Start  Length  Slot  Name   Signature
   0      6      0    this       Lnet/rfc1149/harassme/AutoStarter;
   0      6      1    context       Landroid/content/Context;


public int callCount(android.content.Context);
  Signature: (Landroid/content/Context;)I
  Code:
   Stack=2, Locals=2, Args_size=2
	aload_0
	aload_1
	invokestatic	Method net/rfc1149/harassme/Prefs$class.callCount:(Lnet/rfc1149/harassme/Prefs;Landroid/content/Context;)I
	ireturn
  Labels:
  LocalVariableTable: 
   Start  Length  Slot  Name   Signature
   0      6      0    this       Lnet/rfc1149/harassme/AutoStarter;
   0      6      1    context       Landroid/content/Context;


public boolean serviceActivated(android.content.Context);
  Signature: (Landroid/content/Context;)Z
  Code:
   Stack=2, Locals=2, Args_size=2
	aload_0
	aload_1
	invokestatic	Method net/rfc1149/harassme/Prefs$class.serviceActivated:(Lnet/rfc1149/harassme/Prefs;Landroid/content/Context;)Z
	ireturn
  Labels:
  LocalVariableTable: 
   Start  Length  Slot  Name   Signature
   0      6      0    this       Lnet/rfc1149/harassme/AutoStarter;
   0      6      1    context       Landroid/content/Context;


}

