Compiled from "CallStatus.scala"
public class net.rfc1149.harassme.CallStatus extends android.telephony.PhoneStateListener
  ScalaSig: length = 0x35E
   05 00 71 06 08 01 02 FFFFFF84 FFFFFF80 FFFFFF80 FFFFFF80 00 09 02 0A 43
   61 6C 6C 53 74 61 74 75 73 0A 02 03 04 01 08 68
   61 72 61 73 73 6D 65 0A 02 05 06 01 07 72 66 63
   31 31 34 39 0A 01 07 01 03 6E 65 74 03 00 13 03
   00 0A 12 10 02 0B 10 0D 01 0C 0A 02 0D 0E 01 09
   74 65 6C 65 70 68 6F 6E 79 0A 01 0F 01 07 61 6E
   64 72 6F 69 64 09 02 11 0C 02 12 50 68 6F 6E 65
   53 74 61 74 65 4C 69 73 74 65 6E 65 72 10 02 13
   16 0D 01 14 0A 01 15 01 05 73 63 61 6C 61 09 02
   17 14 02 0B 53 63 61 6C 61 4F 62 6A 65 63 74 08
   05 19 00 FFFFFF84 00 1A 01 06 3C 69 6E 69 74 3E 14 01
   1B 10 02 1C 00 0D 01 02 08 07 1E 00 FFFFFFC0 FFFFFF80 FFFFFF84 04
   1F 01 0D 70 72 65 76 69 6F 75 73 53 74 61 74 65
   15 01 20 10 02 13 21 09 02 22 14 02 03 49 6E 74
   08 07 24 00 FFFFFFC0 FFFFFF80 FFFFFF84 04 25 01 11 70 72 65 76 69
   6F 75 73 53 74 61 74 65 5F 24 65 71 14 02 26 29
   10 02 13 27 09 02 28 14 02 04 55 6E 69 74 08 07
   2A 23 FFFFFF81 FFFFFF80 FFFFFFC0 00 20 01 03 78 24 31 08 06 2C 00
   FFFFFFA0 FFFFFFA0 04 20 01 0E 70 72 65 76 69 6F 75 73 53 74
   61 74 65 20 08 07 2E 00 FFFFFFC0 FFFFFF80 FFFFFF84 04 2F 01 0D 63
   75 72 72 65 6E 74 4E 75 6D 62 65 72 15 01 30 10
   02 31 36 0D 01 32 0A 02 33 34 01 04 6C 61 6E 67
   0A 01 35 01 04 6A 61 76 61 09 02 37 32 02 06 53
   74 72 69 6E 67 08 07 39 00 FFFFFFC0 FFFFFF80 FFFFFF84 04 3A 01 11
   63 75 72 72 65 6E 74 4E 75 6D 62 65 72 5F 24 65
   71 14 02 26 3B 08 07 2A 38 FFFFFF81 FFFFFF80 FFFFFFC0 00 30 08 06
   3D 00 FFFFFFA0 FFFFFFA0 04 30 01 0E 63 75 72 72 65 6E 74 4E
   75 6D 62 65 72 20 08 07 3F 00 FFFFFFC0 FFFFFF80 FFFFFF84 04 40 01
   0C 69 6E 63 6F 6D 69 6E 67 43 61 6C 6C 15 01 41
   10 02 13 42 09 02 43 14 02 07 42 6F 6F 6C 65 61
   6E 08 07 45 00 FFFFFFC0 FFFFFF80 FFFFFF84 04 46 01 10 69 6E 63 6F
   6D 69 6E 67 43 61 6C 6C 5F 24 65 71 14 02 26 47
   08 07 2A 44 FFFFFF81 FFFFFF80 FFFFFFC0 00 41 08 06 49 00 FFFFFFA0 FFFFFFA0 04
   41 01 0D 69 6E 63 6F 6D 69 6E 67 43 61 6C 6C 20
   08 05 4B 00 FFFFFF84 08 4C 01 06 6F 6E 52 69 6E 67 14
   02 26 4D 08 05 4E 4A FFFFFFC0 00 4F 01 0E 69 6E 63 6F
   6D 69 6E 67 4E 75 6D 62 65 72 10 02 50 53 0E 02
   13 51 09 02 52 14 01 06 50 72 65 64 65 66 09 02
   37 54 0A 02 52 14 08 05 56 00 FFFFFF84 08 57 01 08 6F
   6E 41 6E 73 77 65 72 14 02 26 58 08 05 4E 55 FFFFFFC0
   00 4F 08 05 5A 00 FFFFFF84 08 5B 01 10 6F 6E 49 6E 63
   6F 6D 69 6E 67 48 61 6E 67 55 70 14 02 26 5C 08
   05 4E 59 FFFFFFC0 00 4F 08 05 5E 00 FFFFFF84 08 5F 01 10 6F
   6E 4F 75 74 67 6F 69 6E 67 48 61 6E 67 55 70 14
   02 26 60 08 05 61 5D FFFFFFC0 00 4F 01 0E 6F 75 74 67
   6F 69 6E 67 4E 75 6D 62 65 72 08 05 63 00 FFFFFF84 08
   64 01 0E 6F 6E 4F 75 74 67 6F 69 6E 67 43 61 6C
   6C 14 02 26 65 08 05 61 62 FFFFFFC0 00 4F 08 05 67 00
   FFFFFF84 08 68 01 0C 6F 6E 4D 69 73 73 65 64 43 61 6C
   6C 14 02 26 69 08 05 4E 66 FFFFFFC0 00 4F 08 05 6B 00
   FFFFFF84 20 6C 01 12 6F 6E 43 61 6C 6C 53 74 61 74 65
   43 68 61 6E 67 65 64 14 03 26 6D 6F 08 05 6E 6A
   FFFFFFC0 00 20 01 05 73 74 61 74 65 08 05 70 6A FFFFFFC0 00
   4F 01 0B 70 68 6F 6E 65 4E 75 6D 62 65 72 
  SourceFile: "CallStatus.scala"
  minor version: 0
  major version: 49
  Constant pool:
String	
class	android/telephony/PhoneStateListener
class	net/rfc1149/harassme/CallStatus
Field	net/rfc1149/harassme/CallStatus.currentNumber:Ljava/lang/String;
Field	net/rfc1149/harassme/CallStatus.incomingCall:Z
Field	net/rfc1149/harassme/CallStatus.previousState:I
Method	android/telephony/PhoneStateListener."<init>":()V
Method	net/rfc1149/harassme/CallStatus.currentNumber:()Ljava/lang/String;
Method	net/rfc1149/harassme/CallStatus.currentNumber_$eq:(Ljava/lang/String;)V
Method	net/rfc1149/harassme/CallStatus.incomingCall:()Z
Method	net/rfc1149/harassme/CallStatus.incomingCall_$eq:(Z)V
Method	net/rfc1149/harassme/CallStatus.onAnswer:(Ljava/lang/String;)V
Method	net/rfc1149/harassme/CallStatus.onIncomingHangUp:(Ljava/lang/String;)V
Method	net/rfc1149/harassme/CallStatus.onMissedCall:(Ljava/lang/String;)V
Method	net/rfc1149/harassme/CallStatus.onOutgoingCall:(Ljava/lang/String;)V
Method	net/rfc1149/harassme/CallStatus.onOutgoingHangUp:(Ljava/lang/String;)V
Method	net/rfc1149/harassme/CallStatus.onRing:(Ljava/lang/String;)V
Method	net/rfc1149/harassme/CallStatus.previousState:()I
Method	net/rfc1149/harassme/CallStatus.previousState_$eq:(I)V
NameAndType	"<init>":()V
NameAndType	currentNumber:()Ljava/lang/String;
NameAndType	currentNumber:Ljava/lang/String;
NameAndType	currentNumber_$eq:(Ljava/lang/String;)V
NameAndType	incomingCall:()Z
NameAndType	incomingCall:Z
NameAndType	incomingCall_$eq:(Z)V
NameAndType	onAnswer:(Ljava/lang/String;)V
NameAndType	onIncomingHangUp:(Ljava/lang/String;)V
NameAndType	onMissedCall:(Ljava/lang/String;)V
NameAndType	onOutgoingCall:(Ljava/lang/String;)V
NameAndType	onOutgoingHangUp:(Ljava/lang/String;)V
NameAndType	onRing:(Ljava/lang/String;)V
NameAndType	previousState:()I
NameAndType	previousState:I
NameAndType	previousState_$eq:(I)V
Asciz	;
Asciz	()I;
Asciz	()Ljava/lang/String;;
Asciz	()V;
Asciz	()Z;
Asciz	(I)V;
Asciz	(ILjava/lang/String;)V;
Asciz	(Ljava/lang/String;)V;
Asciz	(Z)V;
Asciz	<init>;
Asciz	CallStatus.scala;
Asciz	Code;
Asciz	I;
Asciz	LineNumberTable;
Asciz	Ljava/lang/String;;
Asciz	Lnet/rfc1149/harassme/CallStatus;;
Asciz	LocalVariableTable;
Asciz	ScalaSig;
Asciz	SourceFile;
Asciz	Z;
Asciz	android/telephony/PhoneStateListener;
Asciz	currentNumber;
Asciz	currentNumber_$eq;
Asciz	incomingCall;
Asciz	incomingCall_$eq;
Asciz	incomingNumber;
Asciz	net/rfc1149/harassme/CallStatus;
Asciz	onAnswer;
Asciz	onCallStateChanged;
Asciz	onIncomingHangUp;
Asciz	onMissedCall;
Asciz	onOutgoingCall;
Asciz	onOutgoingHangUp;
Asciz	onRing;
Asciz	outgoingNumber;
Asciz	phoneNumber;
Asciz	previousState;
Asciz	previousState_$eq;
Asciz	state;
Asciz	this;
Asciz	tp1;
Asciz	tp2;

{
private boolean incomingCall;
  Signature: Z

private java.lang.String currentNumber;
  Signature: Ljava/lang/String;

private int previousState;
  Signature: I

public net.rfc1149.harassme.CallStatus();
  Signature: ()V
  Code:
   Stack=2, Locals=1, Args_size=1
	aload_0
	invokespecial	Method android/telephony/PhoneStateListener."<init>":()V
	aload_0
	iconst_0
	putfield	Field previousState:I
	aload_0
	ldc	String 
	putfield	Field currentNumber:Ljava/lang/String;
	aload_0
	iconst_1
	putfield	Field incomingCall:Z
	return
  Labels:

public void onCallStateChanged(int, java.lang.String);
  Signature: (ILjava/lang/String;)V
  Code:
   Stack=2, Locals=5, Args_size=3
	aload_0
	invokespecial	Method previousState:()I
	istore_3
	iload_1
	istore	4
	iload_3
	tableswitch{ //0 to 2
		0: 122;
		1: 71;
		2: 36;
		default: 171 }
	iload	4
	iconst_0
	if_icmpne	l1 // aload_0
	aload_0
	invokespecial	Method incomingCall:()Z
	ifeq	l2 // aload_0
	aload_0
	aload_0
	invokespecial	Method currentNumber:()Ljava/lang/String;
	invokevirtual	Method onIncomingHangUp:(Ljava/lang/String;)V
	goto	l1 // aload_0
l2	aload_0
	aload_0
	invokespecial	Method currentNumber:()Ljava/lang/String;
	invokevirtual	Method onOutgoingHangUp:(Ljava/lang/String;)V
	goto	l1 // aload_0
	iload	4
	lookupswitch{ //2
		0: 111;
		2: 100;
		default: 171 }
	aload_0
	aload_0
	invokespecial	Method currentNumber:()Ljava/lang/String;
	invokevirtual	Method onAnswer:(Ljava/lang/String;)V
	goto	l1 // aload_0
	aload_0
	aload_0
	invokespecial	Method currentNumber:()Ljava/lang/String;
	invokevirtual	Method onMissedCall:(Ljava/lang/String;)V
	goto	l1 // aload_0
	iload	4
	tableswitch{ //1 to 2
		1: 161;
		2: 148;
		default: 171 }
	aload_0
	aload_2
	invokevirtual	Method onOutgoingCall:(Ljava/lang/String;)V
	aload_0
	iconst_0
	invokespecial	Method incomingCall_$eq:(Z)V
	goto	l1 // aload_0
	aload_0
	aload_2
	invokevirtual	Method onRing:(Ljava/lang/String;)V
	aload_0
	iconst_1
	invokespecial	Method incomingCall_$eq:(Z)V
l1	aload_0
	aload_2
	invokespecial	Method currentNumber_$eq:(Ljava/lang/String;)V
	aload_0
	iload_1
	invokespecial	Method previousState_$eq:(I)V
	return
  Labels:
   	l2 = 60 // aload_0
   	l1 = 171 // aload_0
  LocalVariableTable: 
   Start  Length  Slot  Name   Signature
   0      182      0    this       Lnet/rfc1149/harassme/CallStatus;
   0      182      1    state       I
   0      182      2    phoneNumber       Ljava/lang/String;
   5      177      3    tp1       I
   8      174      4    tp2       I


public void onMissedCall(java.lang.String);
  Signature: (Ljava/lang/String;)V
  Code:
   Stack=0, Locals=2, Args_size=2
	return
  Labels:
  LocalVariableTable: 
   Start  Length  Slot  Name   Signature
   0      1      0    this       Lnet/rfc1149/harassme/CallStatus;
   0      1      1    incomingNumber       Ljava/lang/String;


public void onOutgoingCall(java.lang.String);
  Signature: (Ljava/lang/String;)V
  Code:
   Stack=0, Locals=2, Args_size=2
	return
  Labels:
  LocalVariableTable: 
   Start  Length  Slot  Name   Signature
   0      1      0    this       Lnet/rfc1149/harassme/CallStatus;
   0      1      1    outgoingNumber       Ljava/lang/String;


public void onOutgoingHangUp(java.lang.String);
  Signature: (Ljava/lang/String;)V
  Code:
   Stack=0, Locals=2, Args_size=2
	return
  Labels:
  LocalVariableTable: 
   Start  Length  Slot  Name   Signature
   0      1      0    this       Lnet/rfc1149/harassme/CallStatus;
   0      1      1    outgoingNumber       Ljava/lang/String;


public void onIncomingHangUp(java.lang.String);
  Signature: (Ljava/lang/String;)V
  Code:
   Stack=0, Locals=2, Args_size=2
	return
  Labels:
  LocalVariableTable: 
   Start  Length  Slot  Name   Signature
   0      1      0    this       Lnet/rfc1149/harassme/CallStatus;
   0      1      1    incomingNumber       Ljava/lang/String;


public void onAnswer(java.lang.String);
  Signature: (Ljava/lang/String;)V
  Code:
   Stack=0, Locals=2, Args_size=2
	return
  Labels:
  LocalVariableTable: 
   Start  Length  Slot  Name   Signature
   0      1      0    this       Lnet/rfc1149/harassme/CallStatus;
   0      1      1    incomingNumber       Ljava/lang/String;


public void onRing(java.lang.String);
  Signature: (Ljava/lang/String;)V
  Code:
   Stack=0, Locals=2, Args_size=2
	return
  Labels:
  LocalVariableTable: 
   Start  Length  Slot  Name   Signature
   0      1      0    this       Lnet/rfc1149/harassme/CallStatus;
   0      1      1    incomingNumber       Ljava/lang/String;


private void incomingCall_$eq(boolean);
  Signature: (Z)V
  Code:
   Stack=2, Locals=2, Args_size=2
	aload_0
	iload_1
	putfield	Field incomingCall:Z
	return
  Labels:

private boolean incomingCall();
  Signature: ()Z
  Code:
   Stack=1, Locals=1, Args_size=1
	aload_0
	getfield	Field incomingCall:Z
	ireturn
  Labels:

private void currentNumber_$eq(java.lang.String);
  Signature: (Ljava/lang/String;)V
  Code:
   Stack=2, Locals=2, Args_size=2
	aload_0
	aload_1
	putfield	Field currentNumber:Ljava/lang/String;
	return
  Labels:

private java.lang.String currentNumber();
  Signature: ()Ljava/lang/String;
  Code:
   Stack=1, Locals=1, Args_size=1
	aload_0
	getfield	Field currentNumber:Ljava/lang/String;
	areturn
  Labels:

private void previousState_$eq(int);
  Signature: (I)V
  Code:
   Stack=2, Locals=2, Args_size=2
	aload_0
	iload_1
	putfield	Field previousState:I
	return
  Labels:

private int previousState();
  Signature: ()I
  Code:
   Stack=1, Locals=1, Args_size=1
	aload_0
	getfield	Field previousState:I
	ireturn
  Labels:

}

