Compiled from "HarassMeService.scala"
public class net.rfc1149.harassme.HarassMeService extends android.app.Service
  ScalaSig: length = 0x330
   05 00 73 06 08 01 02 FFFFFF84 FFFFFF80 FFFFFF80 FFFFFF80 00 09 02 0F 48
   61 72 61 73 73 4D 65 53 65 72 76 69 63 65 0A 02
   03 04 01 08 68 61 72 61 73 73 6D 65 0A 02 05 06
   01 07 72 66 63 31 31 34 39 0A 01 07 01 03 6E 65
   74 03 00 13 03 00 0A 12 10 02 0B 10 0D 01 0C 0A
   02 0D 0E 01 03 61 70 70 0A 01 0F 01 07 61 6E 64
   72 6F 69 64 09 02 11 0C 02 07 53 65 72 76 69 63
   65 10 02 13 16 0D 01 14 0A 01 15 01 05 73 63 61
   6C 61 09 02 17 14 02 0B 53 63 61 6C 61 4F 62 6A
   65 63 74 08 05 19 00 FFFFFF84 00 1A 01 06 3C 69 6E 69
   74 3E 14 01 1B 10 02 1C 00 0D 01 02 08 08 1E 00
   FFFFFF88 FFFFFFC2 FFFFFF80 FFFFFF84 04 1F 01 10 74 65 6C 65 70 68 6F 6E
   79 4D 61 6E 61 67 65 72 15 01 20 10 02 21 24 0D
   01 22 0A 02 23 0E 01 09 74 65 6C 65 70 68 6F 6E
   79 09 02 25 22 02 10 54 65 6C 65 70 68 6F 6E 79
   4D 61 6E 61 67 65 72 08 08 27 00 FFFFFF88 FFFFFF80 FFFFFFA0 FFFFFFA0 04
   20 01 11 74 65 6C 65 70 68 6F 6E 79 4D 61 6E 61
   67 65 72 20 08 08 29 00 FFFFFF88 FFFFFFC2 FFFFFF80 FFFFFF84 04 2A 01 08
   6C 69 73 74 65 6E 65 72 15 01 2B 10 02 1C 2C 09
   02 2D 02 02 10 48 61 72 61 73 73 4D 65 4C 69 73
   74 65 6E 65 72 08 08 2F 00 FFFFFF88 FFFFFF80 FFFFFFA0 FFFFFFA0 04 2B 01
   09 6C 69 73 74 65 6E 65 72 20 08 05 31 00 FFFFFF84 20
   32 01 06 6F 6E 42 69 6E 64 14 02 33 36 10 02 13
   34 09 02 35 14 02 04 4E 75 6C 6C 08 05 37 30 FFFFFFC0
   00 38 01 06 69 6E 74 65 6E 74 10 02 39 3C 0D 01
   3A 0A 02 3B 0E 01 07 63 6F 6E 74 65 6E 74 09 02
   3D 3A 02 06 49 6E 74 65 6E 74 08 05 3F 00 FFFFFF84 20
   40 01 08 6F 6E 43 72 65 61 74 65 14 01 41 10 02
   13 42 09 02 43 14 02 04 55 6E 69 74 08 05 45 00
   FFFFFF84 20 40 01 09 6F 6E 44 65 73 74 72 6F 79 07 05
   47 02 FFFFFF88 02 48 01 0F 48 61 72 61 73 73 4D 65 53
   65 72 76 69 63 65 10 02 1C 49 06 08 01 02 FFFFFF84 FFFFFF80
   FFFFFF80 FFFFFF88 02 4A 13 03 49 4B 12 10 02 4C 51 0D 01 4D
   0A 02 4E 4F 01 04 6C 61 6E 67 0A 01 50 01 04 6A
   61 76 61 09 02 52 4D 02 06 4F 62 6A 65 63 74 08
   05 19 49 FFFFFF84 00 54 14 01 48 08 07 56 49 FFFFFFC0 FFFFFF80 FFFFFF84
   04 57 01 0E 73 65 72 76 69 63 65 53 74 61 72 74
   65 64 15 01 58 10 02 13 59 09 02 5A 14 02 07 42
   6F 6F 6C 65 61 6E 08 07 5C 49 FFFFFFC0 FFFFFF80 FFFFFF84 04 5D 01
   12 73 65 72 76 69 63 65 53 74 61 72 74 65 64 5F
   24 65 71 14 02 41 5E 08 07 5F 5B FFFFFF81 FFFFFF80 FFFFFFC0 00 58
   01 03 78 24 31 08 06 61 49 FFFFFFA0 FFFFFFA0 04 58 01 0F 73
   65 72 76 69 63 65 53 74 61 72 74 65 64 20 08 05
   37 49 FFFFFF84 04 63 14 02 38 64 08 05 65 62 FFFFFFC0 00 66
   01 07 63 6F 6E 74 65 78 74 10 02 39 67 09 02 68
   3A 02 07 43 6F 6E 74 65 78 74 08 05 6A 49 FFFFFF84 00
   6B 01 0C 73 74 61 72 74 53 65 72 76 69 63 65 14
   02 41 6C 08 05 65 69 FFFFFFC0 00 66 08 05 6E 49 FFFFFF84 00
   6F 01 0B 73 74 6F 70 53 65 72 76 69 63 65 14 02
   41 70 08 05 65 6D FFFFFFC0 00 66 08 05 72 49 FFFFFF84 00 57
   01 0E 73 65 72 76 69 63 65 52 75 6E 6E 69 6E 67
   
  SourceFile: "HarassMeService.scala"
  minor version: 0
  major version: 49
  Constant pool:
int	32;
String	phone
class	android/app/Service
class	android/telephony/TelephonyManager
class	net/rfc1149/harassme/HarassMeListener
class	net/rfc1149/harassme/HarassMeService
class	scala/runtime/BoxedUnit
Field	net/rfc1149/harassme/HarassMeService.bitmap$0:I
Field	net/rfc1149/harassme/HarassMeService.listener:Lnet/rfc1149/harassme/HarassMeListener;
Field	net/rfc1149/harassme/HarassMeService.telephonyManager:Landroid/telephony/TelephonyManager;
Field	scala/runtime/BoxedUnit.UNIT:Lscala/runtime/BoxedUnit;
Method	android/app/Service."<init>":()V
Method	android/app/Service.onCreate:()V
Method	android/app/Service.onDestroy:()V
Method	android/telephony/TelephonyManager.listen:(Landroid/telephony/PhoneStateListener;I)V
Method	net/rfc1149/harassme/HarassMeListener."<init>":(Landroid/content/Context;)V
Method	net/rfc1149/harassme/HarassMeService.getSystemService:(Ljava/lang/String;)Ljava/lang/Object;
Method	net/rfc1149/harassme/HarassMeService.listener:()Lnet/rfc1149/harassme/HarassMeListener;
Method	net/rfc1149/harassme/HarassMeService.onBind:(Landroid/content/Intent;)Lscala/runtime/Null$;
Method	net/rfc1149/harassme/HarassMeService.telephonyManager:()Landroid/telephony/TelephonyManager;
NameAndType	"<init>":()V
NameAndType	"<init>":(Landroid/content/Context;)V
NameAndType	UNIT:Lscala/runtime/BoxedUnit;
NameAndType	bitmap$0:I
NameAndType	getSystemService:(Ljava/lang/String;)Ljava/lang/Object;
NameAndType	listen:(Landroid/telephony/PhoneStateListener;I)V
NameAndType	listener:()Lnet/rfc1149/harassme/HarassMeListener;
NameAndType	listener:Lnet/rfc1149/harassme/HarassMeListener;
NameAndType	onBind:(Landroid/content/Intent;)Lscala/runtime/Null$;
NameAndType	onCreate:()V
NameAndType	onDestroy:()V
NameAndType	telephonyManager:()Landroid/telephony/TelephonyManager;
NameAndType	telephonyManager:Landroid/telephony/TelephonyManager;
Asciz	()Landroid/telephony/TelephonyManager;;
Asciz	()Lnet/rfc1149/harassme/HarassMeListener;;
Asciz	()V;
Asciz	(Landroid/content/Context;)V;
Asciz	(Landroid/content/Intent;)Landroid/os/IBinder;;
Asciz	(Landroid/content/Intent;)Lscala/runtime/Null$;;
Asciz	(Landroid/telephony/PhoneStateListener;I)V;
Asciz	(Ljava/lang/String;)Ljava/lang/Object;;
Asciz	<init>;
Asciz	Code;
Asciz	HarassMeService.scala;
Asciz	I;
Asciz	Landroid/content/Intent;;
Asciz	Landroid/telephony/TelephonyManager;;
Asciz	LineNumberTable;
Asciz	Lnet/rfc1149/harassme/HarassMeListener;;
Asciz	Lnet/rfc1149/harassme/HarassMeService;;
Asciz	LocalVariableTable;
Asciz	Lscala/runtime/BoxedUnit;;
Asciz	ScalaSig;
Asciz	SourceFile;
Asciz	UNIT;
Asciz	android/app/Service;
Asciz	android/telephony/TelephonyManager;
Asciz	bitmap$0;
Asciz	getSystemService;
Asciz	intent;
Asciz	listen;
Asciz	listener;
Asciz	net/rfc1149/harassme/HarassMeListener;
Asciz	net/rfc1149/harassme/HarassMeService;
Asciz	onBind;
Asciz	onCreate;
Asciz	onDestroy;
Asciz	phone;
Asciz	scala/runtime/BoxedUnit;
Asciz	telephonyManager;
Asciz	this;

{
public volatile int bitmap$0;
  Signature: I

private net.rfc1149.harassme.HarassMeListener listener;
  Signature: Lnet/rfc1149/harassme/HarassMeListener;

private android.telephony.TelephonyManager telephonyManager;
  Signature: Landroid/telephony/TelephonyManager;

public net.rfc1149.harassme.HarassMeService();
  Signature: ()V
  Code:
   Stack=1, Locals=1, Args_size=1
	aload_0
	invokespecial	Method android/app/Service."<init>":()V
	return
  Labels:

public android.os.IBinder onBind(android.content.Intent);
  Signature: (Landroid/content/Intent;)Landroid/os/IBinder;
  Code:
   Stack=2, Locals=2, Args_size=2
	aload_0
	aload_1
	invokevirtual	Method onBind:(Landroid/content/Intent;)Lscala/runtime/Null$;
	pop
	aconst_null
	areturn
  Labels:

public void onDestroy();
  Signature: ()V
  Code:
   Stack=3, Locals=1, Args_size=1
	aload_0
	invokespecial	Method android/app/Service.onDestroy:()V
	aload_0
	invokespecial	Method telephonyManager:()Landroid/telephony/TelephonyManager;
	aload_0
	invokespecial	Method listener:()Lnet/rfc1149/harassme/HarassMeListener;
	iconst_0
	invokevirtual	Method android/telephony/TelephonyManager.listen:(Landroid/telephony/PhoneStateListener;I)V
	return
  Labels:

public void onCreate();
  Signature: ()V
  Code:
   Stack=3, Locals=1, Args_size=1
	aload_0
	invokespecial	Method android/app/Service.onCreate:()V
	aload_0
	invokespecial	Method telephonyManager:()Landroid/telephony/TelephonyManager;
	aload_0
	invokespecial	Method listener:()Lnet/rfc1149/harassme/HarassMeListener;
	ldc	int 32
	invokevirtual	Method android/telephony/TelephonyManager.listen:(Landroid/telephony/PhoneStateListener;I)V
	return
  Labels:

public scala.runtime.Null$ onBind(android.content.Intent);
  Signature: (Landroid/content/Intent;)Lscala/runtime/Null$;
  Code:
   Stack=1, Locals=2, Args_size=2
	aconst_null
	areturn
  Labels:
  LocalVariableTable: 
   Start  Length  Slot  Name   Signature
   0      2      0    this       Lnet/rfc1149/harassme/HarassMeService;
   0      2      1    intent       Landroid/content/Intent;


private net.rfc1149.harassme.HarassMeListener listener();
  Signature: ()Lnet/rfc1149/harassme/HarassMeListener;
  Code:
   Stack=4, Locals=2, Args_size=1
	aload_0
	getfield	Field bitmap$0:I
	iconst_4
	iand
	iconst_0
	if_icmpne	l1 // aload_0
	aload_0
	dup
	astore_1
	monitorenter
	aload_0
	getfield	Field bitmap$0:I
	iconst_4
	iand
	iconst_0
	if_icmpne	l2 // getstatic
	aload_0
	new	class net/rfc1149/harassme/HarassMeListener
	dup
	aload_0
	invokespecial	Method net/rfc1149/harassme/HarassMeListener."<init>":(Landroid/content/Context;)V
	putfield	Field listener:Lnet/rfc1149/harassme/HarassMeListener;
	aload_0
	aload_0
	getfield	Field bitmap$0:I
	iconst_4
	ior
	putfield	Field bitmap$0:I
l2	getstatic	Field scala/runtime/BoxedUnit.UNIT:Lscala/runtime/BoxedUnit;
	pop
	aload_1
	monitorexit
l1	aload_0
	getfield	Field listener:Lnet/rfc1149/harassme/HarassMeListener;
	areturn
	aload_1
	monitorexit
	athrow
  Labels:
   	l2 = 46 // getstatic
   	l1 = 52 // aload_0
  Exception table:
   from   to  target type
    14    52    57   any

private android.telephony.TelephonyManager telephonyManager();
  Signature: ()Landroid/telephony/TelephonyManager;
  Code:
   Stack=3, Locals=2, Args_size=1
	aload_0
	getfield	Field bitmap$0:I
	iconst_1
	iand
	iconst_0
	if_icmpne	l1 // aload_0
	aload_0
	dup
	astore_1
	monitorenter
	aload_0
	getfield	Field bitmap$0:I
	iconst_1
	iand
	iconst_0
	if_icmpne	l2 // getstatic
	aload_0
	aload_0
	ldc	String phone
	invokevirtual	Method getSystemService:(Ljava/lang/String;)Ljava/lang/Object;
	checkcast	class android/telephony/TelephonyManager
	putfield	Field telephonyManager:Landroid/telephony/TelephonyManager;
	aload_0
	aload_0
	getfield	Field bitmap$0:I
	iconst_1
	ior
	putfield	Field bitmap$0:I
l2	getstatic	Field scala/runtime/BoxedUnit.UNIT:Lscala/runtime/BoxedUnit;
	pop
	aload_1
	monitorexit
l1	aload_0
	getfield	Field telephonyManager:Landroid/telephony/TelephonyManager;
	areturn
	aload_1
	monitorexit
	athrow
  Labels:
   	l2 = 47 // getstatic
   	l1 = 53 // aload_0
  Exception table:
   from   to  target type
    14    53    58   any

}

