Compiled from "HarassMeService.scala"
public final class net.rfc1149.harassme.HarassMeService$ extends java.lang.Object
  Scala: length = 0x
   
  SourceFile: "HarassMeService.scala"
  minor version: 0
  major version: 49
  Constant pool:
class	android/content/Context
class	android/content/Intent
class	java/lang/Object
class	net/rfc1149/harassme/HarassMeService
class	net/rfc1149/harassme/HarassMeService$
Field	net/rfc1149/harassme/HarassMeService$.MODULE$:Lnet/rfc1149/harassme/HarassMeService$;
Field	net/rfc1149/harassme/HarassMeService$.serviceStarted:Z
Method	android/content/Context.startService:(Landroid/content/Intent;)Landroid/content/ComponentName;
Method	android/content/Context.stopService:(Landroid/content/Intent;)Z
Method	android/content/Intent."<init>":(Landroid/content/Context;Ljava/lang/Class;)V
Method	java/lang/Object."<init>":()V
Method	net/rfc1149/harassme/HarassMeService$."<init>":()V
Method	net/rfc1149/harassme/HarassMeService$.intent:(Landroid/content/Context;)Landroid/content/Intent;
Method	net/rfc1149/harassme/HarassMeService$.serviceStarted:()Z
Method	net/rfc1149/harassme/HarassMeService$.serviceStarted_$eq:(Z)V
NameAndType	"<init>":()V
NameAndType	"<init>":(Landroid/content/Context;Ljava/lang/Class;)V
NameAndType	MODULE$:Lnet/rfc1149/harassme/HarassMeService$;
NameAndType	intent:(Landroid/content/Context;)Landroid/content/Intent;
NameAndType	serviceStarted:()Z
NameAndType	serviceStarted:Z
NameAndType	serviceStarted_$eq:(Z)V
NameAndType	startService:(Landroid/content/Intent;)Landroid/content/ComponentName;
NameAndType	stopService:(Landroid/content/Intent;)Z
Asciz	()V;
Asciz	()Z;
Asciz	(Landroid/content/Context;)Landroid/content/Intent;;
Asciz	(Landroid/content/Context;)V;
Asciz	(Landroid/content/Context;Ljava/lang/Class;)V;
Asciz	(Landroid/content/Intent;)Landroid/content/ComponentName;;
Asciz	(Landroid/content/Intent;)Z;
Asciz	(Z)V;
Asciz	<clinit>;
Asciz	<init>;
Asciz	Code;
Asciz	HarassMeService.scala;
Asciz	Landroid/content/Context;;
Asciz	LineNumberTable;
Asciz	Lnet/rfc1149/harassme/HarassMeService$;;
Asciz	LocalVariableTable;
Asciz	MODULE$;
Asciz	Scala;
Asciz	SourceFile;
Asciz	Z;
Asciz	android/content/Context;
Asciz	android/content/Intent;
Asciz	context;
Asciz	intent;
Asciz	java/lang/Object;
Asciz	net/rfc1149/harassme/HarassMeService;
Asciz	net/rfc1149/harassme/HarassMeService$;
Asciz	serviceRunning;
Asciz	serviceStarted;
Asciz	serviceStarted_$eq;
Asciz	startService;
Asciz	stopService;
Asciz	this;

{
public static final net.rfc1149.harassme.HarassMeService$ MODULE$;
  Signature: Lnet/rfc1149/harassme/HarassMeService$;

private boolean serviceStarted;
  Signature: Z

public static {};
  Signature: ()V
  Code:
   Stack=1, Locals=0, Args_size=0
	new	class net/rfc1149/harassme/HarassMeService$
	invokespecial	Method "<init>":()V
	return
  Labels:

private boolean serviceStarted();
  Signature: ()Z
  Code:
   Stack=1, Locals=1, Args_size=1
	aload_0
	getfield	Field serviceStarted:Z
	ireturn
  Labels:

private void serviceStarted_$eq(boolean);
  Signature: (Z)V
  Code:
   Stack=2, Locals=2, Args_size=2
	aload_0
	iload_1
	putfield	Field serviceStarted:Z
	return
  Labels:

private android.content.Intent intent(android.content.Context);
  Signature: (Landroid/content/Context;)Landroid/content/Intent;
  Code:
   Stack=4, Locals=2, Args_size=2
	new	class android/content/Intent
	dup
	aload_1
	ldc	class net/rfc1149/harassme/HarassMeService
	invokespecial	Method android/content/Intent."<init>":(Landroid/content/Context;Ljava/lang/Class;)V
	areturn
  Labels:
  LocalVariableTable: 
   Start  Length  Slot  Name   Signature
   0      11      0    this       Lnet/rfc1149/harassme/HarassMeService$;
   0      11      1    context       Landroid/content/Context;


public void startService(android.content.Context);
  Signature: (Landroid/content/Context;)V
  Code:
   Stack=3, Locals=2, Args_size=2
	aload_1
	aload_0
	aload_1
	invokespecial	Method intent:(Landroid/content/Context;)Landroid/content/Intent;
	invokevirtual	Method android/content/Context.startService:(Landroid/content/Intent;)Landroid/content/ComponentName;
	pop
	aload_0
	iconst_1
	invokespecial	Method serviceStarted_$eq:(Z)V
	return
  Labels:
  LocalVariableTable: 
   Start  Length  Slot  Name   Signature
   0      16      0    this       Lnet/rfc1149/harassme/HarassMeService$;
   0      16      1    context       Landroid/content/Context;


public void stopService(android.content.Context);
  Signature: (Landroid/content/Context;)V
  Code:
   Stack=3, Locals=2, Args_size=2
	aload_1
	aload_0
	aload_1
	invokespecial	Method intent:(Landroid/content/Context;)Landroid/content/Intent;
	invokevirtual	Method android/content/Context.stopService:(Landroid/content/Intent;)Z
	pop
	aload_0
	iconst_0
	invokespecial	Method serviceStarted_$eq:(Z)V
	return
  Labels:
  LocalVariableTable: 
   Start  Length  Slot  Name   Signature
   0      16      0    this       Lnet/rfc1149/harassme/HarassMeService$;
   0      16      1    context       Landroid/content/Context;


public boolean serviceRunning();
  Signature: ()Z
  Code:
   Stack=1, Locals=1, Args_size=1
	aload_0
	invokespecial	Method serviceStarted:()Z
	ireturn
  Labels:

private net.rfc1149.harassme.HarassMeService$();
  Signature: ()V
  Code:
   Stack=2, Locals=1, Args_size=1
	aload_0
	invokespecial	Method java/lang/Object."<init>":()V
	aload_0
	putstatic	Field MODULE$:Lnet/rfc1149/harassme/HarassMeService$;
	aload_0
	iconst_0
	putfield	Field serviceStarted:Z
	return
  Labels:

}

