Compiled from "LastCalls.scala"
public class net.rfc1149.harassme.LastCalls$Call extends java.lang.Object
  InnerClass: 
   public Call=class net/rfc1149/harassme/LastCalls$Call of class net/rfc1149/harassme/LastCalls
  Scala: length = 0x
   
  SourceFile: "LastCalls.scala"
  minor version: 0
  major version: 49
  Constant pool:
int	60000;
class	java/lang/NullPointerException
class	java/lang/Object
class	java/util/Date
class	net/rfc1149/harassme/LastCalls
class	net/rfc1149/harassme/LastCalls$Call
class	net/rfc1149/harassme/Prefs
Field	net/rfc1149/harassme/LastCalls$Call.$outer:Lnet/rfc1149/harassme/LastCalls;
Field	net/rfc1149/harassme/LastCalls$Call.date:Ljava/util/Date;
Field	net/rfc1149/harassme/LastCalls$Call.number:Ljava/lang/String;
Method	java/lang/NullPointerException."<init>":()V
Method	java/lang/Object."<init>":()V
Method	java/util/Date."<init>":()V
Method	java/util/Date.getTime:()J
Method	net/rfc1149/harassme/LastCalls$Call.date:()Ljava/util/Date;
Method	net/rfc1149/harassme/LastCalls$Call.maxMilliseconds:()I
Method	net/rfc1149/harassme/LastCalls$Call.net$rfc1149$harassme$LastCalls$Call$$$outer:()Lnet/rfc1149/harassme/LastCalls;
InterfaceMethod	net/rfc1149/harassme/LastCalls.context:()Landroid/content/Context;
InterfaceMethod	net/rfc1149/harassme/Prefs.minutesCount:(Landroid/content/Context;)I
NameAndType	$outer:Lnet/rfc1149/harassme/LastCalls;
NameAndType	"<init>":()V
NameAndType	context:()Landroid/content/Context;
NameAndType	date:()Ljava/util/Date;
NameAndType	date:Ljava/util/Date;
NameAndType	getTime:()J
NameAndType	maxMilliseconds:()I
NameAndType	minutesCount:(Landroid/content/Context;)I
NameAndType	net$rfc1149$harassme$LastCalls$Call$$$outer:()Lnet/rfc1149/harassme/LastCalls;
NameAndType	number:Ljava/lang/String;
Asciz	$outer;
Asciz	()I;
Asciz	()J;
Asciz	()Landroid/content/Context;;
Asciz	()Ljava/lang/String;;
Asciz	()Ljava/util/Date;;
Asciz	()Lnet/rfc1149/harassme/LastCalls;;
Asciz	()V;
Asciz	()Z;
Asciz	(Landroid/content/Context;)I;
Asciz	(Lnet/rfc1149/harassme/LastCalls;Ljava/lang/String;Ljava/util/Date;)V;
Asciz	<init>;
Asciz	Call;
Asciz	Code;
Asciz	InnerClasses;
Asciz	LastCalls.scala;
Asciz	LineNumberTable;
Asciz	Ljava/lang/String;;
Asciz	Ljava/util/Date;;
Asciz	Lnet/rfc1149/harassme/LastCalls$Call;;
Asciz	Lnet/rfc1149/harassme/LastCalls;;
Asciz	LocalVariableTable;
Asciz	Scala;
Asciz	SourceFile;
Asciz	context;
Asciz	date;
Asciz	getTime;
Asciz	hasExpired;
Asciz	java/lang/NullPointerException;
Asciz	java/lang/Object;
Asciz	java/util/Date;
Asciz	maxMilliseconds;
Asciz	minutesCount;
Asciz	net$rfc1149$harassme$LastCalls$Call$$$outer;
Asciz	net/rfc1149/harassme/LastCalls;
Asciz	net/rfc1149/harassme/LastCalls$Call;
Asciz	net/rfc1149/harassme/Prefs;
Asciz	number;
Asciz	this;

{
public final net.rfc1149.harassme.LastCalls $outer;
  Signature: Lnet/rfc1149/harassme/LastCalls;

private final java.util.Date date;
  Signature: Ljava/util/Date;

private final java.lang.String number;
  Signature: Ljava/lang/String;

public net.rfc1149.harassme.LastCalls$Call(net.rfc1149.harassme.LastCalls, java.lang.String, java.util.Date);
  Signature: (Lnet/rfc1149/harassme/LastCalls;Ljava/lang/String;Ljava/util/Date;)V
  Code:
   Stack=2, Locals=4, Args_size=4
	aload_0
	aload_2
	putfield	Field number:Ljava/lang/String;
	aload_0
	aload_3
	putfield	Field date:Ljava/util/Date;
	aload_1
	ifnonnull	l1 // aload_0
	new	class java/lang/NullPointerException
	dup
	invokespecial	Method java/lang/NullPointerException."<init>":()V
	athrow
l1	aload_0
	aload_1
	putfield	Field $outer:Lnet/rfc1149/harassme/LastCalls;
	aload_0
	invokespecial	Method java/lang/Object."<init>":()V
	return
  Labels:
   	l1 = 22 // aload_0
  LocalVariableTable: 
   Start  Length  Slot  Name   Signature
   0      32      0    this       Lnet/rfc1149/harassme/LastCalls$Call;
   0      32      1    $outer       Lnet/rfc1149/harassme/LastCalls;
   0      32      2    number       Ljava/lang/String;
   0      32      3    date       Ljava/util/Date;


public net.rfc1149.harassme.LastCalls net$rfc1149$harassme$LastCalls$Call$$$outer();
  Signature: ()Lnet/rfc1149/harassme/LastCalls;
  Code:
   Stack=1, Locals=1, Args_size=1
	aload_0
	getfield	Field $outer:Lnet/rfc1149/harassme/LastCalls;
	areturn
  Labels:

public boolean hasExpired();
  Signature: ()Z
  Code:
   Stack=4, Locals=1, Args_size=1
	new	class java/util/Date
	dup
	invokespecial	Method java/util/Date."<init>":()V
	invokevirtual	Method java/util/Date.getTime:()J
	aload_0
	invokevirtual	Method date:()Ljava/util/Date;
	invokevirtual	Method java/util/Date.getTime:()J
	lsub
	aload_0
	invokevirtual	Method maxMilliseconds:()I
	i2l
	lcmp
	ifle	l1 // iconst_0
	iconst_1
	goto	l2 // ireturn
l1	iconst_0
l2	ireturn
  Labels:
   	l1 = 31 // iconst_0
   	l2 = 32 // ireturn

public int maxMilliseconds();
  Signature: ()I
  Code:
   Stack=2, Locals=1, Args_size=1
	aload_0
	invokevirtual	Method net$rfc1149$harassme$LastCalls$Call$$$outer:()Lnet/rfc1149/harassme/LastCalls;
	aload_0
	invokevirtual	Method net$rfc1149$harassme$LastCalls$Call$$$outer:()Lnet/rfc1149/harassme/LastCalls;
	invokeinterface	InterfaceMethod net/rfc1149/harassme/LastCalls.context:()Landroid/content/Context;
	invokeinterface	InterfaceMethod net/rfc1149/harassme/Prefs.minutesCount:(Landroid/content/Context;)I
	ldc	int 60000
	imul
	ireturn
  Labels:

public java.util.Date date();
  Signature: ()Ljava/util/Date;
  Code:
   Stack=1, Locals=1, Args_size=1
	aload_0
	getfield	Field date:Ljava/util/Date;
	areturn
  Labels:

public java.lang.String number();
  Signature: ()Ljava/lang/String;
  Code:
   Stack=1, Locals=1, Args_size=1
	aload_0
	getfield	Field number:Ljava/lang/String;
	areturn
  Labels:

}

