Compiled from "LastCalls.scala"
public abstract class net.rfc1149.harassme.LastCalls$class extends java.lang.Object
  InnerClass: 
   public Call=class net/rfc1149/harassme/LastCalls$Call of class net/rfc1149/harassme/LastCalls
   public final $anonfun$cleanupList$1=class net/rfc1149/harassme/LastCalls$$anonfun$cleanupList$1 of class net/rfc1149/harassme/LastCalls
   public final $anonfun$shouldBeSignaled$1=class net/rfc1149/harassme/LastCalls$$anonfun$shouldBeSignaled$1 of class net/rfc1149/harassme/LastCalls
  Scala: length = 0x
   
  SourceFile: "LastCalls.scala"
  minor version: 0
  major version: 49
  Constant pool:
class	java/lang/Object
class	java/util/Date
class	net/rfc1149/harassme/LastCalls
class	net/rfc1149/harassme/LastCalls$$anonfun$cleanupList$1
class	net/rfc1149/harassme/LastCalls$$anonfun$shouldBeSignaled$1
class	net/rfc1149/harassme/LastCalls$Call
class	net/rfc1149/harassme/LastCalls$class
class	net/rfc1149/harassme/Prefs
class	scala/collection/LinearSeqOptimized
class	scala/collection/TraversableLike
class	scala/collection/immutable/List
class	scala/collection/immutable/Nil$
Field	scala/collection/immutable/Nil$.MODULE$:Lscala/collection/immutable/Nil$;
Method	java/util/Date."<init>":()V
Method	net/rfc1149/harassme/LastCalls$$anonfun$cleanupList$1."<init>":(Lnet/rfc1149/harassme/LastCalls;)V
Method	net/rfc1149/harassme/LastCalls$$anonfun$shouldBeSignaled$1."<init>":(Lnet/rfc1149/harassme/LastCalls;Ljava/lang/String;)V
Method	net/rfc1149/harassme/LastCalls$Call."<init>":(Lnet/rfc1149/harassme/LastCalls;Ljava/lang/String;Ljava/util/Date;)V
Method	net/rfc1149/harassme/LastCalls$class.cleanupList:(Lnet/rfc1149/harassme/LastCalls;)V
Method	net/rfc1149/harassme/LastCalls$class.rememberCall:(Lnet/rfc1149/harassme/LastCalls;Lnet/rfc1149/harassme/LastCalls$Call;)V
Method	scala/collection/immutable/List.$colon$colon:(Ljava/lang/Object;)Lscala/collection/immutable/List;
InterfaceMethod	net/rfc1149/harassme/LastCalls.context:()Landroid/content/Context;
InterfaceMethod	net/rfc1149/harassme/LastCalls.net$rfc1149$harassme$LastCalls$$lastCalls:()Lscala/collection/immutable/List;
InterfaceMethod	net/rfc1149/harassme/LastCalls.net$rfc1149$harassme$LastCalls$$lastCalls_$eq:(Lscala/collection/immutable/List;)V
InterfaceMethod	net/rfc1149/harassme/Prefs.callCount:(Landroid/content/Context;)I
InterfaceMethod	scala/collection/LinearSeqOptimized.count:(Lscala/Function1;)I
InterfaceMethod	scala/collection/TraversableLike.filter:(Lscala/Function1;)Ljava/lang/Object;
NameAndType	$colon$colon:(Ljava/lang/Object;)Lscala/collection/immutable/List;
NameAndType	"<init>":()V
NameAndType	"<init>":(Lnet/rfc1149/harassme/LastCalls;)V
NameAndType	"<init>":(Lnet/rfc1149/harassme/LastCalls;Ljava/lang/String;)V
NameAndType	"<init>":(Lnet/rfc1149/harassme/LastCalls;Ljava/lang/String;Ljava/util/Date;)V
NameAndType	MODULE$:Lscala/collection/immutable/Nil$;
NameAndType	callCount:(Landroid/content/Context;)I
NameAndType	cleanupList:(Lnet/rfc1149/harassme/LastCalls;)V
NameAndType	context:()Landroid/content/Context;
NameAndType	count:(Lscala/Function1;)I
NameAndType	filter:(Lscala/Function1;)Ljava/lang/Object;
NameAndType	net$rfc1149$harassme$LastCalls$$lastCalls:()Lscala/collection/immutable/List;
NameAndType	net$rfc1149$harassme$LastCalls$$lastCalls_$eq:(Lscala/collection/immutable/List;)V
NameAndType	rememberCall:(Lnet/rfc1149/harassme/LastCalls;Lnet/rfc1149/harassme/LastCalls$Call;)V
Asciz	$anonfun$cleanupList$1;
Asciz	$anonfun$shouldBeSignaled$1;
Asciz	$colon$colon;
Asciz	$init$;
Asciz	$this;
Asciz	()Landroid/content/Context;;
Asciz	()Lscala/collection/immutable/List;;
Asciz	()V;
Asciz	(Landroid/content/Context;)I;
Asciz	(Ljava/lang/Object;)Lscala/collection/immutable/List;;
Asciz	(Lnet/rfc1149/harassme/LastCalls;)V;
Asciz	(Lnet/rfc1149/harassme/LastCalls;Ljava/lang/String;)V;
Asciz	(Lnet/rfc1149/harassme/LastCalls;Ljava/lang/String;)Z;
Asciz	(Lnet/rfc1149/harassme/LastCalls;Ljava/lang/String;Ljava/util/Date;)V;
Asciz	(Lnet/rfc1149/harassme/LastCalls;Lnet/rfc1149/harassme/LastCalls$Call;)V;
Asciz	(Lscala/Function1;)I;
Asciz	(Lscala/Function1;)Ljava/lang/Object;;
Asciz	(Lscala/collection/immutable/List;)V;
Asciz	<init>;
Asciz	Call;
Asciz	Code;
Asciz	InnerClasses;
Asciz	LastCalls.scala;
Asciz	LineNumberTable;
Asciz	Ljava/lang/String;;
Asciz	Lnet/rfc1149/harassme/LastCalls$Call;;
Asciz	Lnet/rfc1149/harassme/LastCalls;;
Asciz	LocalVariableTable;
Asciz	Lscala/collection/immutable/Nil$;;
Asciz	MODULE$;
Asciz	Scala;
Asciz	SourceFile;
Asciz	c;
Asciz	callCount;
Asciz	cleanupList;
Asciz	context;
Asciz	count;
Asciz	filter;
Asciz	java/lang/Object;
Asciz	java/util/Date;
Asciz	net$rfc1149$harassme$LastCalls$$lastCalls;
Asciz	net$rfc1149$harassme$LastCalls$$lastCalls_$eq;
Asciz	net/rfc1149/harassme/LastCalls;
Asciz	net/rfc1149/harassme/LastCalls$$anonfun$cleanupList$1;
Asciz	net/rfc1149/harassme/LastCalls$$anonfun$shouldBeSignaled$1;
Asciz	net/rfc1149/harassme/LastCalls$Call;
Asciz	net/rfc1149/harassme/LastCalls$class;
Asciz	net/rfc1149/harassme/Prefs;
Asciz	number;
Asciz	number$1;
Asciz	recordMissedCall;
Asciz	rememberCall;
Asciz	resetCalls;
Asciz	scala/collection/LinearSeqOptimized;
Asciz	scala/collection/TraversableLike;
Asciz	scala/collection/immutable/List;
Asciz	scala/collection/immutable/Nil$;
Asciz	shouldBeSignaled;

{
private static void cleanupList(net.rfc1149.harassme.LastCalls);
  Signature: (Lnet/rfc1149/harassme/LastCalls;)V
  Code:
   Stack=5, Locals=1, Args_size=1
	aload_0
	aload_0
	invokeinterface	InterfaceMethod net/rfc1149/harassme/LastCalls.net$rfc1149$harassme$LastCalls$$lastCalls:()Lscala/collection/immutable/List;
	new	class net/rfc1149/harassme/LastCalls$$anonfun$cleanupList$1
	dup
	aload_0
	invokespecial	Method net/rfc1149/harassme/LastCalls$$anonfun$cleanupList$1."<init>":(Lnet/rfc1149/harassme/LastCalls;)V
	invokeinterface	InterfaceMethod scala/collection/TraversableLike.filter:(Lscala/Function1;)Ljava/lang/Object;
	checkcast	class scala/collection/immutable/List
	invokeinterface	InterfaceMethod net/rfc1149/harassme/LastCalls.net$rfc1149$harassme$LastCalls$$lastCalls_$eq:(Lscala/collection/immutable/List;)V
	return
  Labels:
  LocalVariableTable: 
   Start  Length  Slot  Name   Signature
   0      29      0    $this       Lnet/rfc1149/harassme/LastCalls;


private static void rememberCall(net.rfc1149.harassme.LastCalls, net.rfc1149.harassme.LastCalls$Call);
  Signature: (Lnet/rfc1149/harassme/LastCalls;Lnet/rfc1149/harassme/LastCalls$Call;)V
  Code:
   Stack=3, Locals=2, Args_size=2
	aload_0
	invokestatic	Method cleanupList:(Lnet/rfc1149/harassme/LastCalls;)V
	aload_0
	aload_0
	invokeinterface	InterfaceMethod net/rfc1149/harassme/LastCalls.net$rfc1149$harassme$LastCalls$$lastCalls:()Lscala/collection/immutable/List;
	aload_1
	invokevirtual	Method scala/collection/immutable/List.$colon$colon:(Ljava/lang/Object;)Lscala/collection/immutable/List;
	invokeinterface	InterfaceMethod net/rfc1149/harassme/LastCalls.net$rfc1149$harassme$LastCalls$$lastCalls_$eq:(Lscala/collection/immutable/List;)V
	return
  Labels:
  LocalVariableTable: 
   Start  Length  Slot  Name   Signature
   0      21      0    $this       Lnet/rfc1149/harassme/LastCalls;
   0      21      1    c       Lnet/rfc1149/harassme/LastCalls$Call;


public static void resetCalls(net.rfc1149.harassme.LastCalls);
  Signature: (Lnet/rfc1149/harassme/LastCalls;)V
  Code:
   Stack=2, Locals=1, Args_size=1
	aload_0
	getstatic	Field scala/collection/immutable/Nil$.MODULE$:Lscala/collection/immutable/Nil$;
	invokeinterface	InterfaceMethod net/rfc1149/harassme/LastCalls.net$rfc1149$harassme$LastCalls$$lastCalls_$eq:(Lscala/collection/immutable/List;)V
	return
  Labels:
  LocalVariableTable: 
   Start  Length  Slot  Name   Signature
   0      10      0    $this       Lnet/rfc1149/harassme/LastCalls;


public static boolean shouldBeSignaled(net.rfc1149.harassme.LastCalls, java.lang.String);
  Signature: (Lnet/rfc1149/harassme/LastCalls;Ljava/lang/String;)Z
  Code:
   Stack=5, Locals=2, Args_size=2
	aload_0
	invokestatic	Method cleanupList:(Lnet/rfc1149/harassme/LastCalls;)V
	aload_0
	invokeinterface	InterfaceMethod net/rfc1149/harassme/LastCalls.net$rfc1149$harassme$LastCalls$$lastCalls:()Lscala/collection/immutable/List;
	new	class net/rfc1149/harassme/LastCalls$$anonfun$shouldBeSignaled$1
	dup
	aload_0
	aload_1
	invokespecial	Method net/rfc1149/harassme/LastCalls$$anonfun$shouldBeSignaled$1."<init>":(Lnet/rfc1149/harassme/LastCalls;Ljava/lang/String;)V
	invokeinterface	InterfaceMethod scala/collection/LinearSeqOptimized.count:(Lscala/Function1;)I
	aload_0
	aload_0
	invokeinterface	InterfaceMethod net/rfc1149/harassme/LastCalls.context:()Landroid/content/Context;
	invokeinterface	InterfaceMethod net/rfc1149/harassme/Prefs.callCount:(Landroid/content/Context;)I
	iconst_1
	isub
	if_icmplt	l1 // iconst_0
	iconst_1
	goto	l2 // ireturn
l1	iconst_0
l2	ireturn
  Labels:
   	l1 = 45 // iconst_0
   	l2 = 46 // ireturn
  LocalVariableTable: 
   Start  Length  Slot  Name   Signature
   0      47      0    $this       Lnet/rfc1149/harassme/LastCalls;
   0      47      1    number$1       Ljava/lang/String;


public static void recordMissedCall(net.rfc1149.harassme.LastCalls, java.lang.String);
  Signature: (Lnet/rfc1149/harassme/LastCalls;Ljava/lang/String;)V
  Code:
   Stack=7, Locals=2, Args_size=2
	aload_0
	new	class net/rfc1149/harassme/LastCalls$Call
	dup
	aload_0
	aload_1
	new	class java/util/Date
	dup
	invokespecial	Method java/util/Date."<init>":()V
	invokespecial	Method net/rfc1149/harassme/LastCalls$Call."<init>":(Lnet/rfc1149/harassme/LastCalls;Ljava/lang/String;Ljava/util/Date;)V
	invokestatic	Method rememberCall:(Lnet/rfc1149/harassme/LastCalls;Lnet/rfc1149/harassme/LastCalls$Call;)V
	return
  Labels:
  LocalVariableTable: 
   Start  Length  Slot  Name   Signature
   0      21      0    $this       Lnet/rfc1149/harassme/LastCalls;
   0      21      1    number       Ljava/lang/String;


public static void $init$(net.rfc1149.harassme.LastCalls);
  Signature: (Lnet/rfc1149/harassme/LastCalls;)V
  Code:
   Stack=2, Locals=1, Args_size=1
	aload_0
	getstatic	Field scala/collection/immutable/Nil$.MODULE$:Lscala/collection/immutable/Nil$;
	invokeinterface	InterfaceMethod net/rfc1149/harassme/LastCalls.net$rfc1149$harassme$LastCalls$$lastCalls_$eq:(Lscala/collection/immutable/List;)V
	return
  Labels:
  LocalVariableTable: 
   Start  Length  Slot  Name   Signature
   0      10      0    $this       Lnet/rfc1149/harassme/LastCalls;


}

