Compiled from "LastCalls.scala"
public final class net.rfc1149.harassme.LastCalls$$anonfun$shouldBeSignaled$1 extends java.lang.Object implements java.io.Serializable,scala.Function1
  InnerClass: 
   public Call=class net/rfc1149/harassme/LastCalls$Call of class net/rfc1149/harassme/LastCalls
   public final $anonfun$shouldBeSignaled$1=class net/rfc1149/harassme/LastCalls$$anonfun$shouldBeSignaled$1 of class net/rfc1149/harassme/LastCalls
  Scala: length = 0x
   
  SourceFile: "LastCalls.scala"
  minor version: 0
  major version: 49
  Constant pool:
class	java/io/Serializable
class	java/lang/Object
class	net/rfc1149/harassme/LastCalls
class	net/rfc1149/harassme/LastCalls$$anonfun$shouldBeSignaled$1
class	net/rfc1149/harassme/LastCalls$Call
class	scala/Function1
class	scala/Function1$class
class	scala/runtime/BoxesRunTime
Field	net/rfc1149/harassme/LastCalls$$anonfun$shouldBeSignaled$1.number$1:Ljava/lang/String;
Method	java/lang/Object."<init>":()V
Method	java/lang/Object.equals:(Ljava/lang/Object;)Z
Method	net/rfc1149/harassme/LastCalls$$anonfun$shouldBeSignaled$1.apply:(Lnet/rfc1149/harassme/LastCalls$Call;)Z
Method	net/rfc1149/harassme/LastCalls$Call.number:()Ljava/lang/String;
Method	scala/Function1$class.$init$:(Lscala/Function1;)V
Method	scala/Function1$class.toString:(Lscala/Function1;)Ljava/lang/String;
Method	scala/runtime/BoxesRunTime.boxToBoolean:(Z)Ljava/lang/Boolean;
NameAndType	$init$:(Lscala/Function1;)V
NameAndType	"<init>":()V
NameAndType	apply:(Lnet/rfc1149/harassme/LastCalls$Call;)Z
NameAndType	boxToBoolean:(Z)Ljava/lang/Boolean;
NameAndType	equals:(Ljava/lang/Object;)Z
NameAndType	number:()Ljava/lang/String;
NameAndType	number$1:Ljava/lang/String;
NameAndType	toString:(Lscala/Function1;)Ljava/lang/String;
Asciz	$anonfun$shouldBeSignaled$1;
Asciz	$init$;
Asciz	$outer;
Asciz	()Ljava/lang/String;;
Asciz	()V;
Asciz	(Ljava/lang/Object;)Ljava/lang/Object;;
Asciz	(Ljava/lang/Object;)Z;
Asciz	(Lnet/rfc1149/harassme/LastCalls$Call;)Z;
Asciz	(Lnet/rfc1149/harassme/LastCalls;Ljava/lang/String;)V;
Asciz	(Lscala/Function1;)Ljava/lang/String;;
Asciz	(Lscala/Function1;)V;
Asciz	(Z)Ljava/lang/Boolean;;
Asciz	<init>;
Asciz	Call;
Asciz	Code;
Asciz	InnerClasses;
Asciz	LastCalls.scala;
Asciz	LineNumberTable;
Asciz	Ljava/lang/Object;;
Asciz	Ljava/lang/String;;
Asciz	Lnet/rfc1149/harassme/LastCalls$$anonfun$shouldBeSignaled$1;;
Asciz	Lnet/rfc1149/harassme/LastCalls;;
Asciz	LocalVariableTable;
Asciz	Scala;
Asciz	SourceFile;
Asciz	apply;
Asciz	boxToBoolean;
Asciz	equals;
Asciz	java/io/Serializable;
Asciz	java/lang/Object;
Asciz	net/rfc1149/harassme/LastCalls;
Asciz	net/rfc1149/harassme/LastCalls$$anonfun$shouldBeSignaled$1;
Asciz	net/rfc1149/harassme/LastCalls$Call;
Asciz	number;
Asciz	number$1;
Asciz	scala/Function1;
Asciz	scala/Function1$class;
Asciz	scala/runtime/BoxesRunTime;
Asciz	this;
Asciz	toString;
Asciz	x$1;

{
private final java.lang.String number$1;
  Signature: Ljava/lang/String;

public net.rfc1149.harassme.LastCalls$$anonfun$shouldBeSignaled$1(net.rfc1149.harassme.LastCalls, java.lang.String);
  Signature: (Lnet/rfc1149/harassme/LastCalls;Ljava/lang/String;)V
  Code:
   Stack=2, Locals=3, Args_size=3
	aload_0
	aload_2
	putfield	Field number$1:Ljava/lang/String;
	aload_0
	invokespecial	Method java/lang/Object."<init>":()V
	aload_0
	invokestatic	Method scala/Function1$class.$init$:(Lscala/Function1;)V
	return
  Labels:
  LocalVariableTable: 
   Start  Length  Slot  Name   Signature
   0      14      0    this       Lnet/rfc1149/harassme/LastCalls$$anonfun$shouldBeSignaled$1;
   0      14      1    $outer       Lnet/rfc1149/harassme/LastCalls;


public final java.lang.Object apply(java.lang.Object);
  Signature: (Ljava/lang/Object;)Ljava/lang/Object;
  Code:
   Stack=2, Locals=2, Args_size=2
	aload_0
	aload_1
	checkcast	class net/rfc1149/harassme/LastCalls$Call
	invokevirtual	Method apply:(Lnet/rfc1149/harassme/LastCalls$Call;)Z
	invokestatic	Method scala/runtime/BoxesRunTime.boxToBoolean:(Z)Ljava/lang/Boolean;
	areturn
  Labels:
  LocalVariableTable: 
   Start  Length  Slot  Name   Signature
   0      12      0    this       Lnet/rfc1149/harassme/LastCalls$$anonfun$shouldBeSignaled$1;
   0      12      1    x$1       Ljava/lang/Object;


public final boolean apply(net.rfc1149.harassme.LastCalls$Call);
  Signature: (Lnet/rfc1149/harassme/LastCalls$Call;)Z
  Code:
   Stack=2, Locals=3, Args_size=2
	aload_1
	invokevirtual	Method net/rfc1149/harassme/LastCalls$Call.number:()Ljava/lang/String;
	aload_0
	getfield	Field number$1:Ljava/lang/String;
	astore_2
	dup
	ifnonnull	l1 // aload_2
	pop
	aload_2
	ifnull	l2 // iconst_1
	goto	l3 // iconst_0
l1	aload_2
	invokevirtual	Method java/lang/Object.equals:(Ljava/lang/Object;)Z
	ifeq	l3 // iconst_0
l2	iconst_1
	goto	l4 // ireturn
l3	iconst_0
l4	ireturn
  Labels:
   	l1 = 21 // aload_2
   	l2 = 28 // iconst_1
   	l3 = 32 // iconst_0
   	l4 = 33 // ireturn

public java.lang.String toString();
  Signature: ()Ljava/lang/String;
  Code:
   Stack=1, Locals=1, Args_size=1
	aload_0
	invokestatic	Method scala/Function1$class.toString:(Lscala/Function1;)Ljava/lang/String;
	areturn
  Labels:

}

