Compiled from "PrefsActivity.scala"
public class net.rfc1149.harassme.PrefsActivity extends android.preference.PreferenceActivity implements net.rfc1149.harassme.Notification,net.rfc1149.harassme.Prefs
  InnerClass: 
   public final $anonfun$onCreate$1=class net/rfc1149/harassme/PrefsActivity$$anonfun$onCreate$1 of class net/rfc1149/harassme/PrefsActivity
   public abstract OnPreferenceChangeListener=class android/preference/Preference$OnPreferenceChangeListener of class android/preference/Preference
  ScalaSig: length = 0x168
   05 00 36 06 08 01 02 FFFFFF84 FFFFFF80 FFFFFF80 FFFFFF80 00 09 02 0D 50
   72 65 66 73 41 63 74 69 76 69 74 79 0A 02 03 04
   01 08 68 61 72 61 73 73 6D 65 0A 02 05 06 01 07
   72 66 63 31 31 34 39 0A 01 07 01 03 6E 65 74 03
   00 13 05 00 0A 12 16 19 10 02 0B 10 0D 01 0C 0A
   02 0D 0E 01 0A 70 72 65 66 65 72 65 6E 63 65 0A
   01 0F 01 07 61 6E 64 72 6F 69 64 09 02 11 0C 02
   12 50 72 65 66 65 72 65 6E 63 65 41 63 74 69 76
   69 74 79 10 02 13 14 0D 01 02 09 02 15 02 02 0C
   4E 6F 74 69 66 69 63 61 74 69 6F 6E 10 02 13 17
   09 02 18 02 02 05 50 72 65 66 73 10 02 1A 1D 0D
   01 1B 0A 01 1C 01 05 73 63 61 6C 61 09 02 1E 1B
   02 0B 53 63 61 6C 61 4F 62 6A 65 63 74 08 05 20
   00 FFFFFF84 00 21 01 06 3C 69 6E 69 74 3E 14 01 22 10
   02 13 00 08 05 24 00 FFFFFF84 00 25 01 0C 73 74 61 72
   74 53 65 72 76 69 63 65 15 01 26 10 02 1A 27 09
   02 28 1B 02 04 55 6E 69 74 08 05 2A 00 FFFFFF84 00 25
   01 0B 73 74 6F 70 53 65 72 76 69 63 65 08 05 2C
   00 FFFFFF84 20 2D 01 08 6F 6E 43 72 65 61 74 65 14 02
   26 2E 08 05 2F 2B FFFFFFC0 00 30 01 12 73 61 76 65 64
   49 6E 73 74 61 6E 63 65 53 74 61 74 65 10 02 31
   34 0D 01 32 0A 02 33 0E 01 02 6F 73 09 02 35 32
   02 06 42 75 6E 64 6C 65 
  SourceFile: "PrefsActivity.scala"
  minor version: 0
  major version: 49
  Constant pool:
String	serviceactivated
class	android/preference/Preference
class	android/preference/Preference$OnPreferenceChangeListener
class	android/preference/PreferenceActivity
class	net/rfc1149/harassme/HarassMeService$
class	net/rfc1149/harassme/ImplicitConversions$
class	net/rfc1149/harassme/Notification
class	net/rfc1149/harassme/Notification$class
class	net/rfc1149/harassme/Prefs
class	net/rfc1149/harassme/Prefs$class
class	net/rfc1149/harassme/PrefsActivity
class	net/rfc1149/harassme/PrefsActivity$$anonfun$onCreate$1
class	net/rfc1149/harassme/R$layout
class	net/rfc1149/harassme/R$string
Field	net/rfc1149/harassme/HarassMeService$.MODULE$:Lnet/rfc1149/harassme/HarassMeService$;
Field	net/rfc1149/harassme/ImplicitConversions$.MODULE$:Lnet/rfc1149/harassme/ImplicitConversions$;
Field	net/rfc1149/harassme/R$layout.preferences:I
Field	net/rfc1149/harassme/R$string.service_startup:I
Field	net/rfc1149/harassme/R$string.service_stop:I
Method	android/preference/Preference.setOnPreferenceChangeListener:(Landroid/preference/Preference$OnPreferenceChangeListener;)V
Method	android/preference/PreferenceActivity."<init>":()V
Method	android/preference/PreferenceActivity.onCreate:(Landroid/os/Bundle;)V
Method	net/rfc1149/harassme/HarassMeService$.serviceRunning:()Z
Method	net/rfc1149/harassme/HarassMeService$.startService:(Landroid/content/Context;)V
Method	net/rfc1149/harassme/HarassMeService$.stopService:(Landroid/content/Context;)V
Method	net/rfc1149/harassme/ImplicitConversions$.toOnPreferenceChangeListener:(Lscala/Function1;)Landroid/preference/Preference$OnPreferenceChangeListener;
Method	net/rfc1149/harassme/Notification$class.$init$:(Landroid/content/Context;)V
Method	net/rfc1149/harassme/Notification$class.short_toast:(Landroid/content/Context;I)V
Method	net/rfc1149/harassme/Prefs$class.$init$:(Lnet/rfc1149/harassme/Prefs;)V
Method	net/rfc1149/harassme/Prefs$class.callCount:(Lnet/rfc1149/harassme/Prefs;Landroid/content/Context;)I
Method	net/rfc1149/harassme/Prefs$class.minutesCount:(Lnet/rfc1149/harassme/Prefs;Landroid/content/Context;)I
Method	net/rfc1149/harassme/Prefs$class.serviceActivated:(Lnet/rfc1149/harassme/Prefs;Landroid/content/Context;)Z
Method	net/rfc1149/harassme/Prefs$class.volume:(Lnet/rfc1149/harassme/Prefs;Landroid/content/Context;)I
Method	net/rfc1149/harassme/PrefsActivity.addPreferencesFromResource:(I)V
Method	net/rfc1149/harassme/PrefsActivity.findPreference:(Ljava/lang/CharSequence;)Landroid/preference/Preference;
Method	net/rfc1149/harassme/PrefsActivity.startService:()V
Method	net/rfc1149/harassme/PrefsActivity$$anonfun$onCreate$1."<init>":(Lnet/rfc1149/harassme/PrefsActivity;)V
InterfaceMethod	net/rfc1149/harassme/Notification.short_toast:(I)V
InterfaceMethod	net/rfc1149/harassme/Prefs.serviceActivated:(Landroid/content/Context;)Z
NameAndType	$init$:(Landroid/content/Context;)V
NameAndType	$init$:(Lnet/rfc1149/harassme/Prefs;)V
NameAndType	"<init>":()V
NameAndType	"<init>":(Lnet/rfc1149/harassme/PrefsActivity;)V
NameAndType	MODULE$:Lnet/rfc1149/harassme/HarassMeService$;
NameAndType	MODULE$:Lnet/rfc1149/harassme/ImplicitConversions$;
NameAndType	addPreferencesFromResource:(I)V
NameAndType	callCount:(Lnet/rfc1149/harassme/Prefs;Landroid/content/Context;)I
NameAndType	findPreference:(Ljava/lang/CharSequence;)Landroid/preference/Preference;
NameAndType	minutesCount:(Lnet/rfc1149/harassme/Prefs;Landroid/content/Context;)I
NameAndType	onCreate:(Landroid/os/Bundle;)V
NameAndType	preferences:I
NameAndType	serviceActivated:(Landroid/content/Context;)Z
NameAndType	serviceActivated:(Lnet/rfc1149/harassme/Prefs;Landroid/content/Context;)Z
NameAndType	serviceRunning:()Z
NameAndType	service_startup:I
NameAndType	service_stop:I
NameAndType	setOnPreferenceChangeListener:(Landroid/preference/Preference$OnPreferenceChangeListener;)V
NameAndType	short_toast:(I)V
NameAndType	short_toast:(Landroid/content/Context;I)V
NameAndType	startService:()V
NameAndType	startService:(Landroid/content/Context;)V
NameAndType	stopService:(Landroid/content/Context;)V
NameAndType	toOnPreferenceChangeListener:(Lscala/Function1;)Landroid/preference/Preference$OnPreferenceChangeListener;
NameAndType	volume:(Lnet/rfc1149/harassme/Prefs;Landroid/content/Context;)I
Asciz	$anonfun$onCreate$1;
Asciz	$init$;
Asciz	()V;
Asciz	()Z;
Asciz	(I)V;
Asciz	(Landroid/content/Context;)I;
Asciz	(Landroid/content/Context;)V;
Asciz	(Landroid/content/Context;)Z;
Asciz	(Landroid/content/Context;I)V;
Asciz	(Landroid/os/Bundle;)V;
Asciz	(Landroid/preference/Preference$OnPreferenceChangeListener;)V;
Asciz	(Ljava/lang/CharSequence;)Landroid/preference/Preference;;
Asciz	(Lnet/rfc1149/harassme/Prefs;)V;
Asciz	(Lnet/rfc1149/harassme/Prefs;Landroid/content/Context;)I;
Asciz	(Lnet/rfc1149/harassme/Prefs;Landroid/content/Context;)Z;
Asciz	(Lnet/rfc1149/harassme/PrefsActivity;)V;
Asciz	(Lscala/Function1;)Landroid/preference/Preference$OnPreferenceChangeListener;;
Asciz	<init>;
Asciz	Code;
Asciz	I;
Asciz	InnerClasses;
Asciz	Landroid/content/Context;;
Asciz	Landroid/os/Bundle;;
Asciz	LineNumberTable;
Asciz	Lnet/rfc1149/harassme/HarassMeService$;;
Asciz	Lnet/rfc1149/harassme/ImplicitConversions$;;
Asciz	Lnet/rfc1149/harassme/PrefsActivity;;
Asciz	LocalVariableTable;
Asciz	MODULE$;
Asciz	OnPreferenceChangeListener;
Asciz	PrefsActivity.scala;
Asciz	ScalaSig;
Asciz	SourceFile;
Asciz	addPreferencesFromResource;
Asciz	android/preference/Preference;
Asciz	android/preference/Preference$OnPreferenceChangeListener;
Asciz	android/preference/PreferenceActivity;
Asciz	callCount;
Asciz	context;
Asciz	findPreference;
Asciz	minutesCount;
Asciz	net/rfc1149/harassme/HarassMeService$;
Asciz	net/rfc1149/harassme/ImplicitConversions$;
Asciz	net/rfc1149/harassme/Notification;
Asciz	net/rfc1149/harassme/Notification$class;
Asciz	net/rfc1149/harassme/Prefs;
Asciz	net/rfc1149/harassme/Prefs$class;
Asciz	net/rfc1149/harassme/PrefsActivity;
Asciz	net/rfc1149/harassme/PrefsActivity$$anonfun$onCreate$1;
Asciz	net/rfc1149/harassme/R$layout;
Asciz	net/rfc1149/harassme/R$string;
Asciz	onCreate;
Asciz	preferences;
Asciz	savedInstanceState;
Asciz	serviceActivated;
Asciz	serviceRunning;
Asciz	service_startup;
Asciz	service_stop;
Asciz	serviceactivated;
Asciz	setOnPreferenceChangeListener;
Asciz	short_toast;
Asciz	startService;
Asciz	stopService;
Asciz	strId;
Asciz	this;
Asciz	toOnPreferenceChangeListener;
Asciz	volume;

{
public net.rfc1149.harassme.PrefsActivity();
  Signature: ()V
  Code:
   Stack=1, Locals=1, Args_size=1
	aload_0
	invokespecial	Method android/preference/PreferenceActivity."<init>":()V
	aload_0
	invokestatic	Method net/rfc1149/harassme/Notification$class.$init$:(Landroid/content/Context;)V
	aload_0
	invokestatic	Method net/rfc1149/harassme/Prefs$class.$init$:(Lnet/rfc1149/harassme/Prefs;)V
	return
  Labels:

public void onCreate(android.os.Bundle);
  Signature: (Landroid/os/Bundle;)V
  Code:
   Stack=5, Locals=2, Args_size=2
	aload_0
	aload_1
	invokespecial	Method android/preference/PreferenceActivity.onCreate:(Landroid/os/Bundle;)V
	aload_0
	aload_0
	invokeinterface	InterfaceMethod net/rfc1149/harassme/Prefs.serviceActivated:(Landroid/content/Context;)Z
	ifeq	l1 // aload_0
	getstatic	Field net/rfc1149/harassme/HarassMeService$.MODULE$:Lnet/rfc1149/harassme/HarassMeService$;
	invokevirtual	Method net/rfc1149/harassme/HarassMeService$.serviceRunning:()Z
	ifne	l1 // aload_0
	aload_0
	invokevirtual	Method startService:()V
l1	aload_0
	getstatic	Field net/rfc1149/harassme/R$layout.preferences:I
	invokevirtual	Method addPreferencesFromResource:(I)V
	aload_0
	ldc	String serviceactivated
	invokevirtual	Method findPreference:(Ljava/lang/CharSequence;)Landroid/preference/Preference;
	getstatic	Field net/rfc1149/harassme/ImplicitConversions$.MODULE$:Lnet/rfc1149/harassme/ImplicitConversions$;
	new	class net/rfc1149/harassme/PrefsActivity$$anonfun$onCreate$1
	dup
	aload_0
	invokespecial	Method net/rfc1149/harassme/PrefsActivity$$anonfun$onCreate$1."<init>":(Lnet/rfc1149/harassme/PrefsActivity;)V
	invokevirtual	Method net/rfc1149/harassme/ImplicitConversions$.toOnPreferenceChangeListener:(Lscala/Function1;)Landroid/preference/Preference$OnPreferenceChangeListener;
	invokevirtual	Method android/preference/Preference.setOnPreferenceChangeListener:(Landroid/preference/Preference$OnPreferenceChangeListener;)V
	return
  Labels:
   	l1 = 28 // aload_0
  LocalVariableTable: 
   Start  Length  Slot  Name   Signature
   0      59      0    this       Lnet/rfc1149/harassme/PrefsActivity;
   0      59      1    savedInstanceState       Landroid/os/Bundle;


public void stopService();
  Signature: ()V
  Code:
   Stack=2, Locals=1, Args_size=1
	getstatic	Field net/rfc1149/harassme/HarassMeService$.MODULE$:Lnet/rfc1149/harassme/HarassMeService$;
	aload_0
	invokevirtual	Method net/rfc1149/harassme/HarassMeService$.stopService:(Landroid/content/Context;)V
	aload_0
	getstatic	Field net/rfc1149/harassme/R$string.service_stop:I
	invokeinterface	InterfaceMethod net/rfc1149/harassme/Notification.short_toast:(I)V
	return
  Labels:

public void startService();
  Signature: ()V
  Code:
   Stack=2, Locals=1, Args_size=1
	getstatic	Field net/rfc1149/harassme/HarassMeService$.MODULE$:Lnet/rfc1149/harassme/HarassMeService$;
	aload_0
	invokevirtual	Method net/rfc1149/harassme/HarassMeService$.startService:(Landroid/content/Context;)V
	aload_0
	getstatic	Field net/rfc1149/harassme/R$string.service_startup:I
	invokeinterface	InterfaceMethod net/rfc1149/harassme/Notification.short_toast:(I)V
	return
  Labels:

public void short_toast(int);
  Signature: (I)V
  Code:
   Stack=2, Locals=2, Args_size=2
	aload_0
	iload_1
	invokestatic	Method net/rfc1149/harassme/Notification$class.short_toast:(Landroid/content/Context;I)V
	return
  Labels:
  LocalVariableTable: 
   Start  Length  Slot  Name   Signature
   0      6      0    this       Lnet/rfc1149/harassme/PrefsActivity;
   0      6      1    strId       I


public int volume(android.content.Context);
  Signature: (Landroid/content/Context;)I
  Code:
   Stack=2, Locals=2, Args_size=2
	aload_0
	aload_1
	invokestatic	Method net/rfc1149/harassme/Prefs$class.volume:(Lnet/rfc1149/harassme/Prefs;Landroid/content/Context;)I
	ireturn
  Labels:
  LocalVariableTable: 
   Start  Length  Slot  Name   Signature
   0      6      0    this       Lnet/rfc1149/harassme/PrefsActivity;
   0      6      1    context       Landroid/content/Context;


public int minutesCount(android.content.Context);
  Signature: (Landroid/content/Context;)I
  Code:
   Stack=2, Locals=2, Args_size=2
	aload_0
	aload_1
	invokestatic	Method net/rfc1149/harassme/Prefs$class.minutesCount:(Lnet/rfc1149/harassme/Prefs;Landroid/content/Context;)I
	ireturn
  Labels:
  LocalVariableTable: 
   Start  Length  Slot  Name   Signature
   0      6      0    this       Lnet/rfc1149/harassme/PrefsActivity;
   0      6      1    context       Landroid/content/Context;


public int callCount(android.content.Context);
  Signature: (Landroid/content/Context;)I
  Code:
   Stack=2, Locals=2, Args_size=2
	aload_0
	aload_1
	invokestatic	Method net/rfc1149/harassme/Prefs$class.callCount:(Lnet/rfc1149/harassme/Prefs;Landroid/content/Context;)I
	ireturn
  Labels:
  LocalVariableTable: 
   Start  Length  Slot  Name   Signature
   0      6      0    this       Lnet/rfc1149/harassme/PrefsActivity;
   0      6      1    context       Landroid/content/Context;


public boolean serviceActivated(android.content.Context);
  Signature: (Landroid/content/Context;)Z
  Code:
   Stack=2, Locals=2, Args_size=2
	aload_0
	aload_1
	invokestatic	Method net/rfc1149/harassme/Prefs$class.serviceActivated:(Lnet/rfc1149/harassme/Prefs;Landroid/content/Context;)Z
	ireturn
  Labels:
  LocalVariableTable: 
   Start  Length  Slot  Name   Signature
   0      6      0    this       Lnet/rfc1149/harassme/PrefsActivity;
   0      6      1    context       Landroid/content/Context;


}

