Compiled from "PrefsActivity.scala"
public final class net.rfc1149.harassme.PrefsActivity$$anonfun$onCreate$1 extends java.lang.Object implements java.io.Serializable,scala.Function1
  InnerClass: 
   public final $anonfun$onCreate$1=class net/rfc1149/harassme/PrefsActivity$$anonfun$onCreate$1 of class net/rfc1149/harassme/PrefsActivity
  Scala: length = 0x
   
  SourceFile: "PrefsActivity.scala"
  minor version: 0
  major version: 49
  Constant pool:
class	java/io/Serializable
class	java/lang/NullPointerException
class	java/lang/Object
class	net/rfc1149/harassme/PrefsActivity
class	net/rfc1149/harassme/PrefsActivity$$anonfun$onCreate$1
class	scala/Function1
class	scala/Function1$class
class	scala/runtime/BoxedUnit
class	scala/runtime/BoxesRunTime
Field	net/rfc1149/harassme/PrefsActivity$$anonfun$onCreate$1.$outer:Lnet/rfc1149/harassme/PrefsActivity;
Field	scala/runtime/BoxedUnit.UNIT:Lscala/runtime/BoxedUnit;
Method	java/lang/NullPointerException."<init>":()V
Method	java/lang/Object."<init>":()V
Method	net/rfc1149/harassme/PrefsActivity.startService:()V
Method	net/rfc1149/harassme/PrefsActivity.stopService:()V
Method	net/rfc1149/harassme/PrefsActivity$$anonfun$onCreate$1.apply:(Ljava/lang/Object;)V
Method	scala/Function1$class.$init$:(Lscala/Function1;)V
Method	scala/Function1$class.toString:(Lscala/Function1;)Ljava/lang/String;
Method	scala/runtime/BoxesRunTime.unboxToBoolean:(Ljava/lang/Object;)Z
NameAndType	$init$:(Lscala/Function1;)V
NameAndType	$outer:Lnet/rfc1149/harassme/PrefsActivity;
NameAndType	"<init>":()V
NameAndType	UNIT:Lscala/runtime/BoxedUnit;
NameAndType	apply:(Ljava/lang/Object;)V
NameAndType	startService:()V
NameAndType	stopService:()V
NameAndType	toString:(Lscala/Function1;)Ljava/lang/String;
NameAndType	unboxToBoolean:(Ljava/lang/Object;)Z
Asciz	$anonfun$onCreate$1;
Asciz	$init$;
Asciz	$outer;
Asciz	()Ljava/lang/String;;
Asciz	()V;
Asciz	(Ljava/lang/Object;)Ljava/lang/Object;;
Asciz	(Ljava/lang/Object;)V;
Asciz	(Ljava/lang/Object;)Z;
Asciz	(Lnet/rfc1149/harassme/PrefsActivity;)V;
Asciz	(Lscala/Function1;)Ljava/lang/String;;
Asciz	(Lscala/Function1;)V;
Asciz	<init>;
Asciz	Code;
Asciz	InnerClasses;
Asciz	LineNumberTable;
Asciz	Ljava/lang/Object;;
Asciz	Lnet/rfc1149/harassme/PrefsActivity$$anonfun$onCreate$1;;
Asciz	Lnet/rfc1149/harassme/PrefsActivity;;
Asciz	LocalVariableTable;
Asciz	Lscala/runtime/BoxedUnit;;
Asciz	PrefsActivity.scala;
Asciz	Scala;
Asciz	SourceFile;
Asciz	UNIT;
Asciz	apply;
Asciz	java/io/Serializable;
Asciz	java/lang/NullPointerException;
Asciz	java/lang/Object;
Asciz	net/rfc1149/harassme/PrefsActivity;
Asciz	net/rfc1149/harassme/PrefsActivity$$anonfun$onCreate$1;
Asciz	scala/Function1;
Asciz	scala/Function1$class;
Asciz	scala/runtime/BoxedUnit;
Asciz	scala/runtime/BoxesRunTime;
Asciz	startService;
Asciz	stopService;
Asciz	this;
Asciz	toString;
Asciz	unboxToBoolean;
Asciz	v;
Asciz	x$1;

{
private final net.rfc1149.harassme.PrefsActivity $outer;
  Signature: Lnet/rfc1149/harassme/PrefsActivity;

public net.rfc1149.harassme.PrefsActivity$$anonfun$onCreate$1(net.rfc1149.harassme.PrefsActivity);
  Signature: (Lnet/rfc1149/harassme/PrefsActivity;)V
  Code:
   Stack=2, Locals=2, Args_size=2
	aload_1
	ifnonnull	l1 // aload_0
	new	class java/lang/NullPointerException
	dup
	invokespecial	Method java/lang/NullPointerException."<init>":()V
	athrow
l1	aload_0
	aload_1
	putfield	Field $outer:Lnet/rfc1149/harassme/PrefsActivity;
	aload_0
	invokespecial	Method java/lang/Object."<init>":()V
	aload_0
	invokestatic	Method scala/Function1$class.$init$:(Lscala/Function1;)V
	return
  Labels:
   	l1 = 12 // aload_0
  LocalVariableTable: 
   Start  Length  Slot  Name   Signature
   0      26      0    this       Lnet/rfc1149/harassme/PrefsActivity$$anonfun$onCreate$1;
   0      26      1    $outer       Lnet/rfc1149/harassme/PrefsActivity;


public final java.lang.Object apply(java.lang.Object);
  Signature: (Ljava/lang/Object;)Ljava/lang/Object;
  Code:
   Stack=2, Locals=3, Args_size=2
	aload_0
	getfield	Field $outer:Lnet/rfc1149/harassme/PrefsActivity;
	astore_2
	aload_0
	aload_1
	invokevirtual	Method apply:(Ljava/lang/Object;)V
	getstatic	Field scala/runtime/BoxedUnit.UNIT:Lscala/runtime/BoxedUnit;
	areturn
  Labels:
  LocalVariableTable: 
   Start  Length  Slot  Name   Signature
   0      14      0    this       Lnet/rfc1149/harassme/PrefsActivity$$anonfun$onCreate$1;
   5      9      1    x$1       Ljava/lang/Object;


public final void apply(java.lang.Object);
  Signature: (Ljava/lang/Object;)V
  Code:
   Stack=1, Locals=3, Args_size=2
	aload_0
	getfield	Field $outer:Lnet/rfc1149/harassme/PrefsActivity;
	astore_2
	aload_1
	invokestatic	Method scala/runtime/BoxesRunTime.unboxToBoolean:(Ljava/lang/Object;)Z
	ifeq	l1 // aload_0
	aload_0
	getfield	Field $outer:Lnet/rfc1149/harassme/PrefsActivity;
	invokevirtual	Method net/rfc1149/harassme/PrefsActivity.startService:()V
	goto	l2 // return
l1	aload_0
	getfield	Field $outer:Lnet/rfc1149/harassme/PrefsActivity;
	invokevirtual	Method net/rfc1149/harassme/PrefsActivity.stopService:()V
l2	return
  Labels:
   	l1 = 22 // aload_0
   	l2 = 29 // return
  LocalVariableTable: 
   Start  Length  Slot  Name   Signature
   0      30      0    this       Lnet/rfc1149/harassme/PrefsActivity$$anonfun$onCreate$1;
   5      25      1    v       Ljava/lang/Object;


public java.lang.String toString();
  Signature: ()Ljava/lang/String;
  Code:
   Stack=1, Locals=1, Args_size=1
	aload_0
	invokestatic	Method scala/Function1$class.toString:(Lscala/Function1;)Ljava/lang/String;
	areturn
  Labels:

}

