Compiled from "Prefs.scala"
public abstract class net.rfc1149.harassme.Prefs$class extends java.lang.Object
  Scala: length = 0x
   
  SourceFile: "Prefs.scala"
  minor version: 0
  major version: 49
  Constant pool:
String	3
String	75
String	callcount
String	minutescount
String	serviceactivated
String	volume
class	android/content/SharedPreferences
class	android/preference/PreferenceManager
class	java/lang/Object
class	net/rfc1149/harassme/Prefs$class
class	scala/Predef$
class	scala/runtime/RichString
Field	scala/Predef$.MODULE$:Lscala/Predef$;
Method	android/preference/PreferenceManager.getDefaultSharedPreferences:(Landroid/content/Context;)Landroid/content/SharedPreferences;
Method	net/rfc1149/harassme/Prefs$class.sp:(Lnet/rfc1149/harassme/Prefs;Landroid/content/Context;)Landroid/content/SharedPreferences;
Method	scala/Predef$.stringWrapper:(Ljava/lang/String;)Lscala/runtime/RichString;
Method	scala/runtime/RichString.toInt:()I
InterfaceMethod	android/content/SharedPreferences.getBoolean:(Ljava/lang/String;Z)Z
InterfaceMethod	android/content/SharedPreferences.getString:(Ljava/lang/String;Ljava/lang/String;)Ljava/lang/String;
NameAndType	MODULE$:Lscala/Predef$;
NameAndType	getBoolean:(Ljava/lang/String;Z)Z
NameAndType	getDefaultSharedPreferences:(Landroid/content/Context;)Landroid/content/SharedPreferences;
NameAndType	getString:(Ljava/lang/String;Ljava/lang/String;)Ljava/lang/String;
NameAndType	sp:(Lnet/rfc1149/harassme/Prefs;Landroid/content/Context;)Landroid/content/SharedPreferences;
NameAndType	stringWrapper:(Ljava/lang/String;)Lscala/runtime/RichString;
NameAndType	toInt:()I
Asciz	$init$;
Asciz	$this;
Asciz	()I;
Asciz	(Landroid/content/Context;)Landroid/content/SharedPreferences;;
Asciz	(Ljava/lang/String;)Lscala/runtime/RichString;;
Asciz	(Ljava/lang/String;Ljava/lang/String;)Ljava/lang/String;;
Asciz	(Ljava/lang/String;Z)Z;
Asciz	(Lnet/rfc1149/harassme/Prefs;)V;
Asciz	(Lnet/rfc1149/harassme/Prefs;Landroid/content/Context;)I;
Asciz	(Lnet/rfc1149/harassme/Prefs;Landroid/content/Context;)Landroid/content/SharedPreferences;;
Asciz	(Lnet/rfc1149/harassme/Prefs;Landroid/content/Context;)Z;
Asciz	3;
Asciz	75;
Asciz	Code;
Asciz	Landroid/content/Context;;
Asciz	LineNumberTable;
Asciz	Lnet/rfc1149/harassme/Prefs;;
Asciz	LocalVariableTable;
Asciz	Lscala/Predef$;;
Asciz	MODULE$;
Asciz	Prefs.scala;
Asciz	Scala;
Asciz	SourceFile;
Asciz	android/content/SharedPreferences;
Asciz	android/preference/PreferenceManager;
Asciz	callCount;
Asciz	callcount;
Asciz	context;
Asciz	getBoolean;
Asciz	getDefaultSharedPreferences;
Asciz	getString;
Asciz	java/lang/Object;
Asciz	minutesCount;
Asciz	minutescount;
Asciz	net/rfc1149/harassme/Prefs$class;
Asciz	scala/Predef$;
Asciz	scala/runtime/RichString;
Asciz	serviceActivated;
Asciz	serviceactivated;
Asciz	sp;
Asciz	stringWrapper;
Asciz	toInt;
Asciz	volume;

{
public static void $init$(net.rfc1149.harassme.Prefs);
  Signature: (Lnet/rfc1149/harassme/Prefs;)V
  Code:
   Stack=0, Locals=1, Args_size=1
	return
  Labels:
  LocalVariableTable: 
   Start  Length  Slot  Name   Signature
   0      1      0    $this       Lnet/rfc1149/harassme/Prefs;


public static int volume(net.rfc1149.harassme.Prefs, android.content.Context);
  Signature: (Lnet/rfc1149/harassme/Prefs;Landroid/content/Context;)I
  Code:
   Stack=4, Locals=2, Args_size=2
	getstatic	Field scala/Predef$.MODULE$:Lscala/Predef$;
	aload_0
	aload_1
	invokestatic	Method sp:(Lnet/rfc1149/harassme/Prefs;Landroid/content/Context;)Landroid/content/SharedPreferences;
	ldc	String volume
	ldc	String 75
	invokeinterface	InterfaceMethod android/content/SharedPreferences.getString:(Ljava/lang/String;Ljava/lang/String;)Ljava/lang/String;
	invokevirtual	Method scala/Predef$.stringWrapper:(Ljava/lang/String;)Lscala/runtime/RichString;
	invokevirtual	Method scala/runtime/RichString.toInt:()I
	ireturn
  Labels:
  LocalVariableTable: 
   Start  Length  Slot  Name   Signature
   0      24      0    $this       Lnet/rfc1149/harassme/Prefs;
   0      24      1    context       Landroid/content/Context;


public static int minutesCount(net.rfc1149.harassme.Prefs, android.content.Context);
  Signature: (Lnet/rfc1149/harassme/Prefs;Landroid/content/Context;)I
  Code:
   Stack=4, Locals=2, Args_size=2
	getstatic	Field scala/Predef$.MODULE$:Lscala/Predef$;
	aload_0
	aload_1
	invokestatic	Method sp:(Lnet/rfc1149/harassme/Prefs;Landroid/content/Context;)Landroid/content/SharedPreferences;
	ldc	String minutescount
	ldc	String 3
	invokeinterface	InterfaceMethod android/content/SharedPreferences.getString:(Ljava/lang/String;Ljava/lang/String;)Ljava/lang/String;
	invokevirtual	Method scala/Predef$.stringWrapper:(Ljava/lang/String;)Lscala/runtime/RichString;
	invokevirtual	Method scala/runtime/RichString.toInt:()I
	ireturn
  Labels:
  LocalVariableTable: 
   Start  Length  Slot  Name   Signature
   0      24      0    $this       Lnet/rfc1149/harassme/Prefs;
   0      24      1    context       Landroid/content/Context;


public static int callCount(net.rfc1149.harassme.Prefs, android.content.Context);
  Signature: (Lnet/rfc1149/harassme/Prefs;Landroid/content/Context;)I
  Code:
   Stack=4, Locals=2, Args_size=2
	getstatic	Field scala/Predef$.MODULE$:Lscala/Predef$;
	aload_0
	aload_1
	invokestatic	Method sp:(Lnet/rfc1149/harassme/Prefs;Landroid/content/Context;)Landroid/content/SharedPreferences;
	ldc	String callcount
	ldc	String 3
	invokeinterface	InterfaceMethod android/content/SharedPreferences.getString:(Ljava/lang/String;Ljava/lang/String;)Ljava/lang/String;
	invokevirtual	Method scala/Predef$.stringWrapper:(Ljava/lang/String;)Lscala/runtime/RichString;
	invokevirtual	Method scala/runtime/RichString.toInt:()I
	ireturn
  Labels:
  LocalVariableTable: 
   Start  Length  Slot  Name   Signature
   0      24      0    $this       Lnet/rfc1149/harassme/Prefs;
   0      24      1    context       Landroid/content/Context;


public static boolean serviceActivated(net.rfc1149.harassme.Prefs, android.content.Context);
  Signature: (Lnet/rfc1149/harassme/Prefs;Landroid/content/Context;)Z
  Code:
   Stack=3, Locals=2, Args_size=2
	aload_0
	aload_1
	invokestatic	Method sp:(Lnet/rfc1149/harassme/Prefs;Landroid/content/Context;)Landroid/content/SharedPreferences;
	ldc	String serviceactivated
	iconst_0
	invokeinterface	InterfaceMethod android/content/SharedPreferences.getBoolean:(Ljava/lang/String;Z)Z
	ireturn
  Labels:
  LocalVariableTable: 
   Start  Length  Slot  Name   Signature
   0      14      0    $this       Lnet/rfc1149/harassme/Prefs;
   0      14      1    context       Landroid/content/Context;


private static android.content.SharedPreferences sp(net.rfc1149.harassme.Prefs, android.content.Context);
  Signature: (Lnet/rfc1149/harassme/Prefs;Landroid/content/Context;)Landroid/content/SharedPreferences;
  Code:
   Stack=1, Locals=2, Args_size=2
	aload_1
	invokestatic	Method android/preference/PreferenceManager.getDefaultSharedPreferences:(Landroid/content/Context;)Landroid/content/SharedPreferences;
	areturn
  Labels:
  LocalVariableTable: 
   Start  Length  Slot  Name   Signature
   0      5      0    $this       Lnet/rfc1149/harassme/Prefs;
   0      5      1    context       Landroid/content/Context;


}

