Compiled from "Ringer.scala"
public abstract class net.rfc1149.harassme.Ringer$class extends java.lang.Object
  Scala: length = 0x
   
  SourceFile: "Ringer.scala"
  minor version: 0
  major version: 49
  Constant pool:
int	100;
String	audio
class	android/content/Context
class	android/media/AudioManager
class	java/lang/Object
class	net/rfc1149/harassme/Prefs
class	net/rfc1149/harassme/Ringer
class	net/rfc1149/harassme/Ringer$class
class	scala/MatchError
class	scala/None$
class	scala/Some
class	scala/runtime/BoxesRunTime
Field	scala/None$.MODULE$:Lscala/None$;
Method	android/content/Context.getSystemService:(Ljava/lang/String;)Ljava/lang/Object;
Method	android/media/AudioManager.getRingerMode:()I
Method	android/media/AudioManager.getStreamMaxVolume:(I)I
Method	android/media/AudioManager.getStreamVolume:(I)I
Method	android/media/AudioManager.setRingerMode:(I)V
Method	android/media/AudioManager.setStreamVolume:(III)V
Method	java/lang/Object.equals:(Ljava/lang/Object;)Z
Method	scala/MatchError."<init>":(Ljava/lang/Object;)V
Method	scala/Some."<init>":(Ljava/lang/Object;)V
Method	scala/Some.x:()Ljava/lang/Object;
Method	scala/runtime/BoxesRunTime.boxToInteger:(I)Ljava/lang/Integer;
Method	scala/runtime/BoxesRunTime.unboxToInt:(Ljava/lang/Object;)I
InterfaceMethod	net/rfc1149/harassme/Prefs.volume:(Landroid/content/Context;)I
InterfaceMethod	net/rfc1149/harassme/Ringer.context:()Landroid/content/Context;
InterfaceMethod	net/rfc1149/harassme/Ringer.net$rfc1149$harassme$Ringer$$audioManager:()Landroid/media/AudioManager;
InterfaceMethod	net/rfc1149/harassme/Ringer.net$rfc1149$harassme$Ringer$$audioManager_$eq:(Landroid/media/AudioManager;)V
InterfaceMethod	net/rfc1149/harassme/Ringer.net$rfc1149$harassme$Ringer$$maxVolume:()I
InterfaceMethod	net/rfc1149/harassme/Ringer.net$rfc1149$harassme$Ringer$$maxVolume_$eq:(I)V
InterfaceMethod	net/rfc1149/harassme/Ringer.net$rfc1149$harassme$Ringer$$previousMode:()Lscala/Option;
InterfaceMethod	net/rfc1149/harassme/Ringer.net$rfc1149$harassme$Ringer$$previousMode_$eq:(Lscala/Option;)V
InterfaceMethod	net/rfc1149/harassme/Ringer.net$rfc1149$harassme$Ringer$$previousVolume:()I
InterfaceMethod	net/rfc1149/harassme/Ringer.net$rfc1149$harassme$Ringer$$previousVolume_$eq:(I)V
NameAndType	"<init>":(Ljava/lang/Object;)V
NameAndType	MODULE$:Lscala/None$;
NameAndType	boxToInteger:(I)Ljava/lang/Integer;
NameAndType	context:()Landroid/content/Context;
NameAndType	equals:(Ljava/lang/Object;)Z
NameAndType	getRingerMode:()I
NameAndType	getStreamMaxVolume:(I)I
NameAndType	getStreamVolume:(I)I
NameAndType	getSystemService:(Ljava/lang/String;)Ljava/lang/Object;
NameAndType	net$rfc1149$harassme$Ringer$$audioManager:()Landroid/media/AudioManager;
NameAndType	net$rfc1149$harassme$Ringer$$audioManager_$eq:(Landroid/media/AudioManager;)V
NameAndType	net$rfc1149$harassme$Ringer$$maxVolume:()I
NameAndType	net$rfc1149$harassme$Ringer$$maxVolume_$eq:(I)V
NameAndType	net$rfc1149$harassme$Ringer$$previousMode:()Lscala/Option;
NameAndType	net$rfc1149$harassme$Ringer$$previousMode_$eq:(Lscala/Option;)V
NameAndType	net$rfc1149$harassme$Ringer$$previousVolume:()I
NameAndType	net$rfc1149$harassme$Ringer$$previousVolume_$eq:(I)V
NameAndType	setRingerMode:(I)V
NameAndType	setStreamVolume:(III)V
NameAndType	unboxToInt:(Ljava/lang/Object;)I
NameAndType	volume:(Landroid/content/Context;)I
NameAndType	x:()Ljava/lang/Object;
Asciz	$init$;
Asciz	$this;
Asciz	()I;
Asciz	()Landroid/content/Context;;
Asciz	()Landroid/media/AudioManager;;
Asciz	()Ljava/lang/Object;;
Asciz	()Lscala/Option;;
Asciz	(I)I;
Asciz	(I)Ljava/lang/Integer;;
Asciz	(I)V;
Asciz	(III)V;
Asciz	(Landroid/content/Context;)I;
Asciz	(Landroid/media/AudioManager;)V;
Asciz	(Ljava/lang/Object;)I;
Asciz	(Ljava/lang/Object;)V;
Asciz	(Ljava/lang/Object;)Z;
Asciz	(Ljava/lang/String;)Ljava/lang/Object;;
Asciz	(Lnet/rfc1149/harassme/Ringer;)I;
Asciz	(Lnet/rfc1149/harassme/Ringer;)V;
Asciz	(Lnet/rfc1149/harassme/Ringer;I)V;
Asciz	(Lscala/Option;)V;
Asciz	<init>;
Asciz	Code;
Asciz	I;
Asciz	LineNumberTable;
Asciz	Lnet/rfc1149/harassme/Ringer;;
Asciz	LocalVariableTable;
Asciz	Lscala/None$;;
Asciz	MODULE$;
Asciz	Ringer.scala;
Asciz	Scala;
Asciz	SourceFile;
Asciz	android/content/Context;
Asciz	android/media/AudioManager;
Asciz	audio;
Asciz	boxToInteger;
Asciz	context;
Asciz	equals;
Asciz	getRingerMode;
Asciz	getStreamMaxVolume;
Asciz	getStreamVolume;
Asciz	getSystemService;
Asciz	java/lang/Object;
Asciz	net$rfc1149$harassme$Ringer$$audioManager;
Asciz	net$rfc1149$harassme$Ringer$$audioManager_$eq;
Asciz	net$rfc1149$harassme$Ringer$$maxVolume;
Asciz	net$rfc1149$harassme$Ringer$$maxVolume_$eq;
Asciz	net$rfc1149$harassme$Ringer$$previousMode;
Asciz	net$rfc1149$harassme$Ringer$$previousMode_$eq;
Asciz	net$rfc1149$harassme$Ringer$$previousVolume;
Asciz	net$rfc1149$harassme$Ringer$$previousVolume_$eq;
Asciz	net/rfc1149/harassme/Prefs;
Asciz	net/rfc1149/harassme/Ringer;
Asciz	net/rfc1149/harassme/Ringer$class;
Asciz	newVolume;
Asciz	restoreRingerMode;
Asciz	ringPhone;
Asciz	ringerMode;
Asciz	scala/MatchError;
Asciz	scala/None$;
Asciz	scala/Some;
Asciz	scala/runtime/BoxesRunTime;
Asciz	setRingerMode;
Asciz	setStreamVolume;
Asciz	unboxToInt;
Asciz	volume;
Asciz	x;

{
public static void $init$(net.rfc1149.harassme.Ringer);
  Signature: (Lnet/rfc1149/harassme/Ringer;)V
  Code:
   Stack=3, Locals=1, Args_size=1
	aload_0
	aload_0
	invokeinterface	InterfaceMethod net/rfc1149/harassme/Ringer.context:()Landroid/content/Context;
	ldc	String audio
	invokevirtual	Method android/content/Context.getSystemService:(Ljava/lang/String;)Ljava/lang/Object;
	checkcast	class android/media/AudioManager
	invokeinterface	InterfaceMethod net/rfc1149/harassme/Ringer.net$rfc1149$harassme$Ringer$$audioManager_$eq:(Landroid/media/AudioManager;)V
	aload_0
	aload_0
	invokeinterface	InterfaceMethod net/rfc1149/harassme/Ringer.net$rfc1149$harassme$Ringer$$audioManager:()Landroid/media/AudioManager;
	iconst_2
	invokevirtual	Method android/media/AudioManager.getStreamMaxVolume:(I)I
	invokeinterface	InterfaceMethod net/rfc1149/harassme/Ringer.net$rfc1149$harassme$Ringer$$maxVolume_$eq:(I)V
	aload_0
	getstatic	Field scala/None$.MODULE$:Lscala/None$;
	invokeinterface	InterfaceMethod net/rfc1149/harassme/Ringer.net$rfc1149$harassme$Ringer$$previousMode_$eq:(Lscala/Option;)V
	aload_0
	iconst_0
	invokeinterface	InterfaceMethod net/rfc1149/harassme/Ringer.net$rfc1149$harassme$Ringer$$previousVolume_$eq:(I)V
	return
  Labels:
  LocalVariableTable: 
   Start  Length  Slot  Name   Signature
   0      53      0    $this       Lnet/rfc1149/harassme/Ringer;


public static int getRingerMode(net.rfc1149.harassme.Ringer);
  Signature: (Lnet/rfc1149/harassme/Ringer;)I
  Code:
   Stack=1, Locals=1, Args_size=1
	aload_0
	invokeinterface	InterfaceMethod net/rfc1149/harassme/Ringer.net$rfc1149$harassme$Ringer$$audioManager:()Landroid/media/AudioManager;
	invokevirtual	Method android/media/AudioManager.getRingerMode:()I
	ireturn
  Labels:
  LocalVariableTable: 
   Start  Length  Slot  Name   Signature
   0      10      0    $this       Lnet/rfc1149/harassme/Ringer;


public static void restoreRingerMode(net.rfc1149.harassme.Ringer);
  Signature: (Lnet/rfc1149/harassme/Ringer;)V
  Code:
   Stack=4, Locals=3, Args_size=1
	aload_0
	invokeinterface	InterfaceMethod net/rfc1149/harassme/Ringer.net$rfc1149$harassme$Ringer$$previousMode:()Lscala/Option;
	astore_1
	aload_1
	instanceof	class scala/Some
	ifeq	l1 // getstatic
	aload_0
	invokeinterface	InterfaceMethod net/rfc1149/harassme/Ringer.net$rfc1149$harassme$Ringer$$audioManager:()Landroid/media/AudioManager;
	aload_1
	checkcast	class scala/Some
	invokevirtual	Method scala/Some.x:()Ljava/lang/Object;
	invokestatic	Method scala/runtime/BoxesRunTime.unboxToInt:(Ljava/lang/Object;)I
	invokevirtual	Method android/media/AudioManager.setRingerMode:(I)V
	aload_0
	invokeinterface	InterfaceMethod net/rfc1149/harassme/Ringer.net$rfc1149$harassme$Ringer$$audioManager:()Landroid/media/AudioManager;
	iconst_2
	aload_0
	invokeinterface	InterfaceMethod net/rfc1149/harassme/Ringer.net$rfc1149$harassme$Ringer$$previousVolume:()I
	iconst_0
	invokevirtual	Method android/media/AudioManager.setStreamVolume:(III)V
	goto	l2 // aload_0
l1	getstatic	Field scala/None$.MODULE$:Lscala/None$;
	aload_1
	astore_2
	dup
	ifnonnull	l3 // aload_2
	pop
	aload_2
	ifnull	l2 // aload_0
	goto	l4 // new
l3	aload_2
	invokevirtual	Method java/lang/Object.equals:(Ljava/lang/Object;)Z
	ifeq	l4 // new
l2	aload_0
	getstatic	Field scala/None$.MODULE$:Lscala/None$;
	invokeinterface	InterfaceMethod net/rfc1149/harassme/Ringer.net$rfc1149$harassme$Ringer$$previousMode_$eq:(Lscala/Option;)V
	return
l4	new	class scala/MatchError
	dup
	aload_1
	invokespecial	Method scala/MatchError."<init>":(Ljava/lang/Object;)V
	athrow
  Labels:
   	l1 = 53 // getstatic
   	l3 = 70 // aload_2
   	l2 = 77 // aload_0
   	l4 = 87 // new
  LocalVariableTable: 
   Start  Length  Slot  Name   Signature
   0      96      0    $this       Lnet/rfc1149/harassme/Ringer;


public static void ringPhone(net.rfc1149.harassme.Ringer, int);
  Signature: (Lnet/rfc1149/harassme/Ringer;I)V
  Code:
   Stack=4, Locals=3, Args_size=2
	aload_0
	new	class scala/Some
	dup
	iload_1
	invokestatic	Method scala/runtime/BoxesRunTime.boxToInteger:(I)Ljava/lang/Integer;
	invokespecial	Method scala/Some."<init>":(Ljava/lang/Object;)V
	invokeinterface	InterfaceMethod net/rfc1149/harassme/Ringer.net$rfc1149$harassme$Ringer$$previousMode_$eq:(Lscala/Option;)V
	aload_0
	aload_0
	invokeinterface	InterfaceMethod net/rfc1149/harassme/Ringer.net$rfc1149$harassme$Ringer$$audioManager:()Landroid/media/AudioManager;
	iconst_2
	invokevirtual	Method android/media/AudioManager.getStreamVolume:(I)I
	invokeinterface	InterfaceMethod net/rfc1149/harassme/Ringer.net$rfc1149$harassme$Ringer$$previousVolume_$eq:(I)V
	aload_0
	invokeinterface	InterfaceMethod net/rfc1149/harassme/Ringer.net$rfc1149$harassme$Ringer$$audioManager:()Landroid/media/AudioManager;
	iconst_2
	invokevirtual	Method android/media/AudioManager.setRingerMode:(I)V
	aload_0
	invokeinterface	InterfaceMethod net/rfc1149/harassme/Ringer.net$rfc1149$harassme$Ringer$$maxVolume:()I
	aload_0
	aload_0
	invokeinterface	InterfaceMethod net/rfc1149/harassme/Ringer.context:()Landroid/content/Context;
	invokeinterface	InterfaceMethod net/rfc1149/harassme/Prefs.volume:(Landroid/content/Context;)I
	imul
	ldc	int 100
	idiv
	istore_2
	aload_0
	invokeinterface	InterfaceMethod net/rfc1149/harassme/Ringer.net$rfc1149$harassme$Ringer$$audioManager:()Landroid/media/AudioManager;
	iconst_2
	iload_2
	iconst_0
	invokevirtual	Method android/media/AudioManager.setStreamVolume:(III)V
	return
  Labels:
  LocalVariableTable: 
   Start  Length  Slot  Name   Signature
   0      79      0    $this       Lnet/rfc1149/harassme/Ringer;
   0      79      1    ringerMode       I
   43      35      2    newVolume       I


}

