Compiled from "Hashable.scala"
public final class scala.util.Hashable$$anon$1 extends java.lang.Object implements scala.util.Hashable
  SourceFile: "Hashable.scala"
  Scala: length = 0x
   
  InnerClass: 
   public final #70= #10 of #69; //$anon$1=class scala/util/Hashable$$anon$1 of class scala/util/Hashable
  minor version: 0
  major version: 49
  Constant pool:
const #1 = Asciz	SourceFile;
const #2 = Asciz	Hashable.scala;
const #3 = Asciz	x$1;
const #4 = Asciz	Ljava/lang/Object;;
const #5 = Asciz	<init>;
const #6 = Asciz	(Ljava/lang/Object;)V;
const #7 = Asciz	Code;
const #8 = Asciz	LineNumberTable;
const #9 = Asciz	scala/util/Hashable$$anon$1;
const #10 = class	#9;	//  scala/util/Hashable$$anon$1
const #11 = NameAndType	#3:#4;//  x$1:Ljava/lang/Object;
const #12 = Field	#10.#11;	//  scala/util/Hashable$$anon$1.x$1:Ljava/lang/Object;
const #13 = Asciz	java/lang/Object;
const #14 = class	#13;	//  java/lang/Object
const #15 = Asciz	()V;
const #16 = NameAndType	#5:#15;//  "<init>":()V
const #17 = Method	#14.#16;	//  java/lang/Object."<init>":()V
const #18 = Asciz	scala/util/Hashable$class;
const #19 = class	#18;	//  scala/util/Hashable$class
const #20 = Asciz	$init$;
const #21 = Asciz	(Lscala/util/Hashable;)V;
const #22 = NameAndType	#20:#21;//  $init$:(Lscala/util/Hashable;)V
const #23 = Method	#19.#22;	//  scala/util/Hashable$class.$init$:(Lscala/util/Hashable;)V
const #24 = Asciz	hashValues;
const #25 = Asciz	()Lscala/collection/Sequence;;
const #26 = Asciz	scala/collection/Sequence$;
const #27 = class	#26;	//  scala/collection/Sequence$
const #28 = Asciz	MODULE$;
const #29 = Asciz	Lscala/collection/Sequence$;;
const #30 = NameAndType	#28:#29;//  MODULE$:Lscala/collection/Sequence$;
const #31 = Field	#27.#30;	//  scala/collection/Sequence$.MODULE$:Lscala/collection/Sequence$;
const #32 = Asciz	scala/runtime/ScalaRunTime$;
const #33 = class	#32;	//  scala/runtime/ScalaRunTime$
const #34 = Asciz	Lscala/runtime/ScalaRunTime$;;
const #35 = NameAndType	#28:#34;//  MODULE$:Lscala/runtime/ScalaRunTime$;
const #36 = Field	#33.#35;	//  scala/runtime/ScalaRunTime$.MODULE$:Lscala/runtime/ScalaRunTime$;
const #37 = Asciz	boxArray;
const #38 = Asciz	(Ljava/lang/Object;)Lscala/runtime/BoxedArray;;
const #39 = NameAndType	#37:#38;//  boxArray:(Ljava/lang/Object;)Lscala/runtime/BoxedArray;
const #40 = Method	#33.#39;	//  scala/runtime/ScalaRunTime$.boxArray:(Ljava/lang/Object;)Lscala/runtime/BoxedArray;
const #41 = Asciz	apply;
const #42 = Asciz	(Lscala/collection/Sequence;)Lscala/collection/Traversable;;
const #43 = NameAndType	#41:#42;//  apply:(Lscala/collection/Sequence;)Lscala/collection/Traversable;
const #44 = Method	#27.#43;	//  scala/collection/Sequence$.apply:(Lscala/collection/Sequence;)Lscala/collection/Traversable;
const #45 = Asciz	scala/collection/Sequence;
const #46 = class	#45;	//  scala/collection/Sequence
const #47 = Asciz	()Lscala/collection/Sequence<Ljava/lang/Object;>;;
const #48 = Asciz	Signature;
const #49 = Asciz	equalHashValues;
const #50 = Asciz	(Ljava/lang/Object;)Z;
const #51 = Asciz	(Lscala/util/Hashable;Ljava/lang/Object;)Z;
const #52 = NameAndType	#49:#51;//  equalHashValues:(Lscala/util/Hashable;Ljava/lang/Object;)Z
const #53 = Method	#19.#52;	//  scala/util/Hashable$class.equalHashValues:(Lscala/util/Hashable;Ljava/lang/Object;)Z
const #54 = Asciz	this;
const #55 = Asciz	Lscala/util/Hashable$$anon$1;;
const #56 = Asciz	other;
const #57 = Asciz	LocalVariableTable;
const #58 = Asciz	hashCode;
const #59 = Asciz	()I;
const #60 = Asciz	(Lscala/util/Hashable;)I;
const #61 = NameAndType	#58:#60;//  hashCode:(Lscala/util/Hashable;)I
const #62 = Method	#19.#61;	//  scala/util/Hashable$class.hashCode:(Lscala/util/Hashable;)I
const #63 = Asciz	hashSeed;
const #64 = NameAndType	#63:#60;//  hashSeed:(Lscala/util/Hashable;)I
const #65 = Method	#19.#64;	//  scala/util/Hashable$class.hashSeed:(Lscala/util/Hashable;)I
const #66 = Asciz	Scala;
const #67 = Asciz	InnerClasses;
const #68 = Asciz	scala/util/Hashable;
const #69 = class	#68;	//  scala/util/Hashable
const #70 = Asciz	$anon$1;

{
public scala.util.Hashable$$anon$1(java.lang.Object);
  Code:
   Stack=2, Locals=2, Args_size=2
   0:	aload_0
   1:	aload_1
   2:	putfield	#12; //Field x$1:Ljava/lang/Object;
   5:	aload_0
   6:	invokespecial	#17; //Method java/lang/Object."<init>":()V
   9:	aload_0
   10:	invokestatic	#23; //Method scala/util/Hashable$class.$init$:(Lscala/util/Hashable;)V
   13:	return
  LineNumberTable: 
   line 54: 0


public scala.collection.Sequence hashValues();
  Code:
   Stack=6, Locals=1, Args_size=1
   0:	getstatic	#31; //Field scala/collection/Sequence$.MODULE$:Lscala/collection/Sequence$;
   3:	getstatic	#36; //Field scala/runtime/ScalaRunTime$.MODULE$:Lscala/runtime/ScalaRunTime$;
   6:	iconst_1
   7:	anewarray	#14; //class java/lang/Object
   10:	dup
   11:	iconst_0
   12:	aload_0
   13:	getfield	#12; //Field x$1:Ljava/lang/Object;
   16:	aastore
   17:	invokevirtual	#40; //Method scala/runtime/ScalaRunTime$.boxArray:(Ljava/lang/Object;)Lscala/runtime/BoxedArray;
   20:	invokevirtual	#44; //Method scala/collection/Sequence$.apply:(Lscala/collection/Sequence;)Lscala/collection/Traversable;
   23:	checkcast	#46; //class scala/collection/Sequence
   26:	areturn
  LineNumberTable: 
   line 54: 0

  Signature: length = 0x2
   00 2F 

public boolean equalHashValues(java.lang.Object);
  Code:
   Stack=2, Locals=2, Args_size=2
   0:	aload_0
   1:	aload_1
   2:	invokestatic	#53; //Method scala/util/Hashable$class.equalHashValues:(Lscala/util/Hashable;Ljava/lang/Object;)Z
   5:	ireturn
  LineNumberTable: 
   line 54: 0

  LocalVariableTable: 
   Start  Length  Slot  Name   Signature
   0      6      0    this       Lscala/util/Hashable$$anon$1;
   0      6      1    other       Ljava/lang/Object;


public int hashCode();
  Code:
   Stack=1, Locals=1, Args_size=1
   0:	aload_0
   1:	invokestatic	#62; //Method scala/util/Hashable$class.hashCode:(Lscala/util/Hashable;)I
   4:	ireturn
  LineNumberTable: 
   line 54: 0


public int hashSeed();
  Code:
   Stack=1, Locals=1, Args_size=1
   0:	aload_0
   1:	invokestatic	#65; //Method scala/util/Hashable$class.hashSeed:(Lscala/util/Hashable;)I
   4:	ireturn
  LineNumberTable: 
   line 54: 0


}

