Compiled from "Hashable.scala"
public abstract class scala.util.Hashable$class extends java.lang.Object
  SourceFile: "Hashable.scala"
  Scala: length = 0x
   
  InnerClass: 
   public final #83= #31 of #13; //$anonfun$hashCode$1=class scala/util/Hashable$$anonfun$hashCode$1 of class scala/util/Hashable
   public final #84= #71 of #13; //$anonfun$hashCode$2=class scala/util/Hashable$$anonfun$hashCode$2 of class scala/util/Hashable
  minor version: 0
  major version: 49
  Constant pool:
const #1 = Asciz	SourceFile;
const #2 = Asciz	Hashable.scala;
const #3 = Asciz	$init$;
const #4 = Asciz	(Lscala/util/Hashable;)V;
const #5 = Asciz	Code;
const #6 = Asciz	LineNumberTable;
const #7 = Asciz	$this;
const #8 = Asciz	Lscala/util/Hashable;;
const #9 = Asciz	LocalVariableTable;
const #10 = Asciz	equalHashValues;
const #11 = Asciz	(Lscala/util/Hashable;Ljava/lang/Object;)Z;
const #12 = Asciz	scala/util/Hashable;
const #13 = class	#12;	//  scala/util/Hashable
const #14 = Asciz	hashValues;
const #15 = Asciz	()Lscala/collection/Sequence;;
const #16 = NameAndType	#14:#15;//  hashValues:()Lscala/collection/Sequence;
const #17 = InterfaceMethod	#13.#16;	//  scala/util/Hashable.hashValues:()Lscala/collection/Sequence;
const #18 = Asciz	scala/collection/generic/IterableTemplate;
const #19 = class	#18;	//  scala/collection/generic/IterableTemplate
const #20 = Asciz	sameElements;
const #21 = Asciz	(Lscala/collection/Iterable;)Z;
const #22 = NameAndType	#20:#21;//  sameElements:(Lscala/collection/Iterable;)Z
const #23 = InterfaceMethod	#19.#22;	//  scala/collection/generic/IterableTemplate.sameElements:(Lscala/collection/Iterable;)Z
const #24 = Asciz	other;
const #25 = Asciz	Ljava/lang/Object;;
const #26 = Asciz	temp1;
const #27 = Asciz	temp2;
const #28 = Asciz	hashCode;
const #29 = Asciz	(Lscala/util/Hashable;)I;
const #30 = Asciz	scala/util/Hashable$$anonfun$hashCode$1;
const #31 = class	#30;	//  scala/util/Hashable$$anonfun$hashCode$1
const #32 = Asciz	<init>;
const #33 = NameAndType	#32:#4;//  "<init>":(Lscala/util/Hashable;)V
const #34 = Method	#31.#33;	//  scala/util/Hashable$$anonfun$hashCode$1."<init>":(Lscala/util/Hashable;)V
const #35 = Asciz	scala/collection/Sequence$;
const #36 = class	#35;	//  scala/collection/Sequence$
const #37 = Asciz	MODULE$;
const #38 = Asciz	Lscala/collection/Sequence$;;
const #39 = NameAndType	#37:#38;//  MODULE$:Lscala/collection/Sequence$;
const #40 = Field	#36.#39;	//  scala/collection/Sequence$.MODULE$:Lscala/collection/Sequence$;
const #41 = Asciz	builderFactory;
const #42 = Asciz	()Lscala/collection/generic/BuilderFactory;;
const #43 = NameAndType	#41:#42;//  builderFactory:()Lscala/collection/generic/BuilderFactory;
const #44 = Method	#36.#43;	//  scala/collection/Sequence$.builderFactory:()Lscala/collection/generic/BuilderFactory;
const #45 = Asciz	scala/collection/generic/TraversableTemplate;
const #46 = class	#45;	//  scala/collection/generic/TraversableTemplate
const #47 = Asciz	map;
const #48 = Asciz	(Lscala/Function1;Lscala/collection/generic/BuilderFactory;)Ljava/lang/Object;;
const #49 = NameAndType	#47:#48;//  map:(Lscala/Function1;Lscala/collection/generic/BuilderFactory;)Ljava/lang/Object;
const #50 = InterfaceMethod	#46.#49;	//  scala/collection/generic/TraversableTemplate.map:(Lscala/Function1;Lscala/collection/generic/BuilderFactory;)Ljava/lang/Object;
const #51 = Asciz	scala/runtime/ScalaRunTime$;
const #52 = class	#51;	//  scala/runtime/ScalaRunTime$
const #53 = Asciz	Lscala/runtime/ScalaRunTime$;;
const #54 = NameAndType	#37:#53;//  MODULE$:Lscala/runtime/ScalaRunTime$;
const #55 = Field	#52.#54;	//  scala/runtime/ScalaRunTime$.MODULE$:Lscala/runtime/ScalaRunTime$;
const #56 = Asciz	boxArray;
const #57 = Asciz	(Ljava/lang/Object;)Lscala/runtime/BoxedArray;;
const #58 = NameAndType	#56:#57;//  boxArray:(Ljava/lang/Object;)Lscala/runtime/BoxedArray;
const #59 = Method	#52.#58;	//  scala/runtime/ScalaRunTime$.boxArray:(Ljava/lang/Object;)Lscala/runtime/BoxedArray;
const #60 = Asciz	hashSeed;
const #61 = Asciz	()I;
const #62 = NameAndType	#60:#61;//  hashSeed:()I
const #63 = InterfaceMethod	#13.#62;	//  scala/util/Hashable.hashSeed:()I
const #64 = Asciz	scala/runtime/BoxesRunTime;
const #65 = class	#64;	//  scala/runtime/BoxesRunTime
const #66 = Asciz	boxToInteger;
const #67 = Asciz	(I)Ljava/lang/Integer;;
const #68 = NameAndType	#66:#67;//  boxToInteger:(I)Ljava/lang/Integer;
const #69 = Method	#65.#68;	//  scala/runtime/BoxesRunTime.boxToInteger:(I)Ljava/lang/Integer;
const #70 = Asciz	scala/util/Hashable$$anonfun$hashCode$2;
const #71 = class	#70;	//  scala/util/Hashable$$anonfun$hashCode$2
const #72 = Method	#71.#33;	//  scala/util/Hashable$$anonfun$hashCode$2."<init>":(Lscala/util/Hashable;)V
const #73 = Asciz	foldLeft;
const #74 = Asciz	(Ljava/lang/Object;Lscala/Function2;)Ljava/lang/Object;;
const #75 = NameAndType	#73:#74;//  foldLeft:(Ljava/lang/Object;Lscala/Function2;)Ljava/lang/Object;
const #76 = InterfaceMethod	#46.#75;	//  scala/collection/generic/TraversableTemplate.foldLeft:(Ljava/lang/Object;Lscala/Function2;)Ljava/lang/Object;
const #77 = Asciz	unboxToInt;
const #78 = Asciz	(Ljava/lang/Object;)I;
const #79 = NameAndType	#77:#78;//  unboxToInt:(Ljava/lang/Object;)I
const #80 = Method	#65.#79;	//  scala/runtime/BoxesRunTime.unboxToInt:(Ljava/lang/Object;)I
const #81 = Asciz	Scala;
const #82 = Asciz	InnerClasses;
const #83 = Asciz	$anonfun$hashCode$1;
const #84 = Asciz	$anonfun$hashCode$2;
const #85 = Asciz	scala/util/Hashable$class;
const #86 = class	#85;	//  scala/util/Hashable$class
const #87 = Asciz	java/lang/Object;
const #88 = class	#87;	//  java/lang/Object

{
public static void $init$(scala.util.Hashable);
  Code:
   Stack=0, Locals=1, Args_size=1
   0:	return
  LineNumberTable: 
   line 29: 0

  LocalVariableTable: 
   Start  Length  Slot  Name   Signature
   0      1      0    $this       Lscala/util/Hashable;


public static boolean equalHashValues(scala.util.Hashable, java.lang.Object);
  Code:
   Stack=2, Locals=4, Args_size=2
   0:	aload_1
   1:	astore_2
   2:	aload_2
   3:	instanceof	#13; //class scala/util/Hashable
   6:	ifeq	34
   9:	aload_2
   10:	checkcast	#13; //class scala/util/Hashable
   13:	astore_3
   14:	aload_0
   15:	invokeinterface	#17,  1; //InterfaceMethod scala/util/Hashable.hashValues:()Lscala/collection/Sequence;
   20:	aload_3
   21:	invokeinterface	#17,  1; //InterfaceMethod scala/util/Hashable.hashValues:()Lscala/collection/Sequence;
   26:	invokeinterface	#23,  2; //InterfaceMethod scala/collection/generic/IterableTemplate.sameElements:(Lscala/collection/Iterable;)Z
   31:	goto	35
   34:	iconst_0
   35:	ireturn
  LineNumberTable: 
   line 38: 0
   line 39: 14
   line 40: 34
   line 38: 35

  LocalVariableTable: 
   Start  Length  Slot  Name   Signature
   0      36      0    $this       Lscala/util/Hashable;
   0      36      1    other       Ljava/lang/Object;
   2      34      2    temp1       Ljava/lang/Object;
   14      17      3    temp2       Lscala/util/Hashable;


public static int hashCode(scala.util.Hashable);
  Code:
   Stack=5, Locals=2, Args_size=1
   0:	aload_0
   1:	invokeinterface	#17,  1; //InterfaceMethod scala/util/Hashable.hashValues:()Lscala/collection/Sequence;
   6:	new	#31; //class scala/util/Hashable$$anonfun$hashCode$1
   9:	dup
   10:	aload_0
   11:	invokespecial	#34; //Method scala/util/Hashable$$anonfun$hashCode$1."<init>":(Lscala/util/Hashable;)V
   14:	getstatic	#40; //Field scala/collection/Sequence$.MODULE$:Lscala/collection/Sequence$;
   17:	invokevirtual	#44; //Method scala/collection/Sequence$.builderFactory:()Lscala/collection/generic/BuilderFactory;
   20:	invokeinterface	#50,  3; //InterfaceMethod scala/collection/generic/TraversableTemplate.map:(Lscala/Function1;Lscala/collection/generic/BuilderFactory;)Ljava/lang/Object;
   25:	astore_1
   26:	aload_1
   27:	instanceof	#46; //class scala/collection/generic/TraversableTemplate
   30:	ifeq	37
   33:	aload_1
   34:	goto	44
   37:	getstatic	#55; //Field scala/runtime/ScalaRunTime$.MODULE$:Lscala/runtime/ScalaRunTime$;
   40:	aload_1
   41:	invokevirtual	#59; //Method scala/runtime/ScalaRunTime$.boxArray:(Ljava/lang/Object;)Lscala/runtime/BoxedArray;
   44:	checkcast	#46; //class scala/collection/generic/TraversableTemplate
   47:	aload_0
   48:	invokeinterface	#63,  1; //InterfaceMethod scala/util/Hashable.hashSeed:()I
   53:	invokestatic	#69; //Method scala/runtime/BoxesRunTime.boxToInteger:(I)Ljava/lang/Integer;
   56:	new	#71; //class scala/util/Hashable$$anonfun$hashCode$2
   59:	dup
   60:	aload_0
   61:	invokespecial	#72; //Method scala/util/Hashable$$anonfun$hashCode$2."<init>":(Lscala/util/Hashable;)V
   64:	invokeinterface	#76,  3; //InterfaceMethod scala/collection/generic/TraversableTemplate.foldLeft:(Ljava/lang/Object;Lscala/Function2;)Ljava/lang/Object;
   69:	invokestatic	#80; //Method scala/runtime/BoxesRunTime.unboxToInt:(Ljava/lang/Object;)I
   72:	ireturn
  LineNumberTable: 
   line 36: 0

  LocalVariableTable: 
   Start  Length  Slot  Name   Signature
   0      73      0    $this       Lscala/util/Hashable;


public static int hashSeed(scala.util.Hashable);
  Code:
   Stack=1, Locals=1, Args_size=1
   0:	iconst_1
   1:	ireturn
  LineNumberTable: 
   line 33: 0

  LocalVariableTable: 
   Start  Length  Slot  Name   Signature
   0      2      0    $this       Lscala/util/Hashable;


}

