Compiled from "Hashable.scala"
public final class scala.util.Hashable$ extends java.lang.Object implements scala.ScalaObject
  SourceFile: "Hashable.scala"
  Scala: length = 0x
   
  InnerClass: 
   public final #49= #41 of #48; //$anon$1=class scala/util/Hashable$$anon$1 of class scala/util/Hashable
  minor version: 0
  major version: 49
  Constant pool:
const #1 = Asciz	SourceFile;
const #2 = Asciz	Hashable.scala;
const #3 = Asciz	Scala;
const #4 = Asciz	MODULE$;
const #5 = Asciz	Lscala/util/Hashable$;;
const #6 = Asciz	<clinit>;
const #7 = Asciz	()V;
const #8 = Asciz	Code;
const #9 = Asciz	scala/util/Hashable$;
const #10 = class	#9;	//  scala/util/Hashable$
const #11 = Asciz	<init>;
const #12 = NameAndType	#11:#7;//  "<init>":()V
const #13 = Method	#10.#12;	//  scala/util/Hashable$."<init>":()V
const #14 = Asciz	LineNumberTable;
const #15 = Asciz	java/lang/Object;
const #16 = class	#15;	//  java/lang/Object
const #17 = Method	#16.#12;	//  java/lang/Object."<init>":()V
const #18 = NameAndType	#4:#5;//  MODULE$:Lscala/util/Hashable$;
const #19 = Field	#10.#18;	//  scala/util/Hashable$.MODULE$:Lscala/util/Hashable$;
const #20 = Asciz	scala$util$Hashable$$calculateHashCode;
const #21 = Asciz	(Ljava/lang/Object;)I;
const #22 = Asciz	scala/runtime/BoxesRunTime;
const #23 = class	#22;	//  scala/runtime/BoxesRunTime
const #24 = Asciz	equals;
const #25 = Asciz	(Ljava/lang/Object;Ljava/lang/Object;)Z;
const #26 = NameAndType	#24:#25;//  equals:(Ljava/lang/Object;Ljava/lang/Object;)Z
const #27 = Method	#23.#26;	//  scala/runtime/BoxesRunTime.equals:(Ljava/lang/Object;Ljava/lang/Object;)Z
const #28 = Asciz	hashCode;
const #29 = Asciz	()I;
const #30 = NameAndType	#28:#29;//  hashCode:()I
const #31 = Method	#16.#30;	//  java/lang/Object.hashCode:()I
const #32 = Asciz	this;
const #33 = Asciz	x;
const #34 = Asciz	Ljava/lang/Object;;
const #35 = Asciz	temp3;
const #36 = Asciz	temp5;
const #37 = Asciz	LocalVariableTable;
const #38 = Asciz	anyVal2Hashable;
const #39 = Asciz	(Ljava/lang/Object;)Lscala/util/Hashable;;
const #40 = Asciz	scala/util/Hashable$$anon$1;
const #41 = class	#40;	//  scala/util/Hashable$$anon$1
const #42 = Asciz	(Ljava/lang/Object;)V;
const #43 = NameAndType	#11:#42;//  "<init>":(Ljava/lang/Object;)V
const #44 = Method	#41.#43;	//  scala/util/Hashable$$anon$1."<init>":(Ljava/lang/Object;)V
const #45 = Asciz	x$1;
const #46 = Asciz	InnerClasses;
const #47 = Asciz	scala/util/Hashable;
const #48 = class	#47;	//  scala/util/Hashable
const #49 = Asciz	$anon$1;
const #50 = Asciz	scala/ScalaObject;
const #51 = class	#50;	//  scala/ScalaObject

{
public static final scala.util.Hashable$ MODULE$;

public static {};
  Code:
   Stack=1, Locals=0, Args_size=0
   0:	new	#10; //class scala/util/Hashable$
   3:	invokespecial	#13; //Method "<init>":()V
   6:	return

public final int scala$util$Hashable$$calculateHashCode(java.lang.Object);
  Code:
   Stack=2, Locals=4, Args_size=2
   0:	aload_1
   1:	astore_2
   2:	aload_2
   3:	aconst_null
   4:	pop
   5:	aconst_null
   6:	invokestatic	#27; //Method scala/runtime/BoxesRunTime.equals:(Ljava/lang/Object;Ljava/lang/Object;)Z
   9:	ifeq	16
   12:	iconst_0
   13:	goto	36
   16:	aload_2
   17:	instanceof	#16; //class java/lang/Object
   20:	ifeq	32
   23:	aload_2
   24:	astore_3
   25:	aload_3
   26:	invokevirtual	#31; //Method java/lang/Object.hashCode:()I
   29:	goto	36
   32:	aload_2
   33:	invokevirtual	#31; //Method java/lang/Object.hashCode:()I
   36:	ireturn
  LineNumberTable: 
   line 56: 0
   line 57: 12
   line 56: 16
   line 58: 25
   line 59: 32
   line 56: 36

  LocalVariableTable: 
   Start  Length  Slot  Name   Signature
   0      37      0    this       Lscala/util/Hashable$;
   0      37      1    x       Ljava/lang/Object;
   2      35      2    temp3       Ljava/lang/Object;
   25      4      3    temp5       Ljava/lang/Object;


public scala.util.Hashable anyVal2Hashable(java.lang.Object);
  Code:
   Stack=3, Locals=2, Args_size=2
   0:	new	#41; //class scala/util/Hashable$$anon$1
   3:	dup
   4:	aload_1
   5:	invokespecial	#44; //Method scala/util/Hashable$$anon$1."<init>":(Ljava/lang/Object;)V
   8:	areturn
  LineNumberTable: 
   line 54: 0

  LocalVariableTable: 
   Start  Length  Slot  Name   Signature
   0      9      0    this       Lscala/util/Hashable$;
   0      9      1    x$1       Ljava/lang/Object;


}

