Compiled from "JenkinsHash.scala"
public final class scala.util.JenkinsHash$$anonfun$partitionValuesAndRefs$2 extends java.lang.Object implements scala.Function1,scala.ScalaObject,java.io.Serializable
  SourceFile: "JenkinsHash.scala"
  Scala: length = 0x
   
  InnerClass: 
   public final $anonfun$partitionValuesAndRefs$2=class scala/util/JenkinsHash$$anonfun$partitionValuesAndRefs$2 of class scala/util/JenkinsHash
  minor version: 0
  major version: 49
  Constant pool:
Asciz	SourceFile;
Asciz	JenkinsHash.scala;
Asciz	<clinit>;
Asciz	()V;
Asciz	Code;
Asciz	serialVersionUID;
Asciz	J;
Asciz	scala/util/JenkinsHash$$anonfun$partitionValuesAndRefs$2;
class	scala/util/JenkinsHash$$anonfun$partitionValuesAndRefs$2
NameAndType	serialVersionUID:J
Field	scala/util/JenkinsHash$$anonfun$partitionValuesAndRefs$2.serialVersionUID:J
Asciz	<init>;
Asciz	LineNumberTable;
Asciz	java/lang/Object;
class	java/lang/Object
NameAndType	"<init>":()V
Method	java/lang/Object."<init>":()V
Asciz	scala/Function1$class;
class	scala/Function1$class
Asciz	$init$;
Asciz	(Lscala/Function1;)V;
NameAndType	$init$:(Lscala/Function1;)V
Method	scala/Function1$class.$init$:(Lscala/Function1;)V
Asciz	apply;
Asciz	(Ljava/lang/Object;)Ljava/lang/Object;;
Asciz	scala/Option;
class	scala/Option
Asciz	(Lscala/Option;)Lscala/collection/Iterable;;
NameAndType	apply:(Lscala/Option;)Lscala/collection/Iterable;
Method	scala/util/JenkinsHash$$anonfun$partitionValuesAndRefs$2.apply:(Lscala/Option;)Lscala/collection/Iterable;
Asciz	this;
Asciz	Lscala/util/JenkinsHash$$anonfun$partitionValuesAndRefs$2;;
Asciz	v1;
Asciz	Ljava/lang/Object;;
Asciz	LocalVariableTable;
Asciz	scala/Option$;
class	scala/Option$
Asciz	MODULE$;
Asciz	Lscala/Option$;;
NameAndType	MODULE$:Lscala/Option$;
Field	scala/Option$.MODULE$:Lscala/Option$;
Asciz	option2Iterable;
NameAndType	option2Iterable:(Lscala/Option;)Lscala/collection/Iterable;
Method	scala/Option$.option2Iterable:(Lscala/Option;)Lscala/collection/Iterable;
Asciz	(Lscala/Option<Ljava/lang/Object;>;)Lscala/collection/Iterable<Ljava/lang/Object;>;;
Asciz	Signature;
Asciz	andThen;
Asciz	(Lscala/Function1;)Lscala/Function1;;
Asciz	(Lscala/Function1;Lscala/Function1;)Lscala/Function1;;
NameAndType	andThen:(Lscala/Function1;Lscala/Function1;)Lscala/Function1;
Method	scala/Function1$class.andThen:(Lscala/Function1;Lscala/Function1;)Lscala/Function1;
Asciz	g;
Asciz	Lscala/Function1;;
Asciz	compose;
NameAndType	compose:(Lscala/Function1;Lscala/Function1;)Lscala/Function1;
Method	scala/Function1$class.compose:(Lscala/Function1;Lscala/Function1;)Lscala/Function1;
Asciz	toString;
Asciz	()Ljava/lang/String;;
Asciz	(Lscala/Function1;)Ljava/lang/String;;
NameAndType	toString:(Lscala/Function1;)Ljava/lang/String;
Method	scala/Function1$class.toString:(Lscala/Function1;)Ljava/lang/String;
Asciz	Scala;
Asciz	InnerClasses;
Asciz	scala/util/JenkinsHash;
class	scala/util/JenkinsHash
Asciz	$anonfun$partitionValuesAndRefs$2;
Asciz	scala/Function1;
class	scala/Function1
Asciz	scala/ScalaObject;
class	scala/ScalaObject
Asciz	java/io/Serializable;
class	java/io/Serializable

{
public static final long serialVersionUID;
  Signature: J

public static {};
  Signature: ()V
  Code:
   Stack=2, Locals=0, Args_size=0
	lconst_0
	putstatic	Field serialVersionUID:J
	return
  Labels:

public scala.util.JenkinsHash$$anonfun$partitionValuesAndRefs$2();
  Signature: ()V
  Code:
   Stack=1, Locals=1, Args_size=1
	aload_0
	invokespecial	Method java/lang/Object."<init>":()V
	aload_0
	invokestatic	Method scala/Function1$class.$init$:(Lscala/Function1;)V
	return
  Labels:

public final java.lang.Object apply(java.lang.Object);
  Signature: (Ljava/lang/Object;)Ljava/lang/Object;
  Code:
   Stack=2, Locals=2, Args_size=2
	aload_0
	aload_1
	checkcast	class scala/Option
	invokevirtual	Method apply:(Lscala/Option;)Lscala/collection/Iterable;
	areturn
  Labels:
  LocalVariableTable: 
   Start  Length  Slot  Name   Signature
   0      9      0    this       Lscala/util/JenkinsHash$$anonfun$partitionValuesAndRefs$2;
   0      9      1    v1       Ljava/lang/Object;


public final scala.collection.Iterable apply(scala.Option);
  Signature: (Lscala/Option;)Lscala/collection/Iterable;
  Code:
   Stack=2, Locals=2, Args_size=2
	getstatic	Field scala/Option$.MODULE$:Lscala/Option$;
	aload_1
	invokevirtual	Method scala/Option$.option2Iterable:(Lscala/Option;)Lscala/collection/Iterable;
	areturn
  Labels:
  Signature: length = 0x2
   00 2D 

public scala.Function1 andThen(scala.Function1);
  Signature: (Lscala/Function1;)Lscala/Function1;
  Code:
   Stack=2, Locals=2, Args_size=2
	aload_0
	aload_1
	invokestatic	Method scala/Function1$class.andThen:(Lscala/Function1;Lscala/Function1;)Lscala/Function1;
	areturn
  Labels:
  LocalVariableTable: 
   Start  Length  Slot  Name   Signature
   0      6      0    this       Lscala/util/JenkinsHash$$anonfun$partitionValuesAndRefs$2;
   0      6      1    g       Lscala/Function1;


public scala.Function1 compose(scala.Function1);
  Signature: (Lscala/Function1;)Lscala/Function1;
  Code:
   Stack=2, Locals=2, Args_size=2
	aload_0
	aload_1
	invokestatic	Method scala/Function1$class.compose:(Lscala/Function1;Lscala/Function1;)Lscala/Function1;
	areturn
  Labels:
  LocalVariableTable: 
   Start  Length  Slot  Name   Signature
   0      6      0    this       Lscala/util/JenkinsHash$$anonfun$partitionValuesAndRefs$2;
   0      6      1    g       Lscala/Function1;


public java.lang.String toString();
  Signature: ()Ljava/lang/String;
  Code:
   Stack=1, Locals=1, Args_size=1
	aload_0
	invokestatic	Method scala/Function1$class.toString:(Lscala/Function1;)Ljava/lang/String;
	areturn
  Labels:

}

