Compiled from "JenkinsHash.scala"
public final class scala.util.JenkinsHash$$anonfun$fourByteToLong$1 extends java.lang.Object implements scala.Function1,scala.ScalaObject,java.io.Serializable
  SourceFile: "JenkinsHash.scala"
  Scala: length = 0x
   
  InnerClass: 
   public final #84= #9 of #83; //$anonfun$fourByteToLong$1=class scala/util/JenkinsHash$$anonfun$fourByteToLong$1 of class scala/util/JenkinsHash
  minor version: 0
  major version: 49
  Constant pool:
const #1 = Asciz	SourceFile;
const #2 = Asciz	JenkinsHash.scala;
const #3 = Asciz	<clinit>;
const #4 = Asciz	()V;
const #5 = Asciz	Code;
const #6 = Asciz	serialVersionUID;
const #7 = Asciz	J;
const #8 = Asciz	scala/util/JenkinsHash$$anonfun$fourByteToLong$1;
const #9 = class	#8;	//  scala/util/JenkinsHash$$anonfun$fourByteToLong$1
const #10 = NameAndType	#6:#7;//  serialVersionUID:J
const #11 = Field	#9.#10;	//  scala/util/JenkinsHash$$anonfun$fourByteToLong$1.serialVersionUID:J
const #12 = Asciz	offset$1;
const #13 = Asciz	I;
const #14 = Asciz	bytes$1;
const #15 = Asciz	[B;
const #16 = Asciz	<init>;
const #17 = Asciz	([BI)V;
const #18 = Asciz	LineNumberTable;
const #19 = NameAndType	#14:#15;//  bytes$1:[B
const #20 = Field	#9.#19;	//  scala/util/JenkinsHash$$anonfun$fourByteToLong$1.bytes$1:[B
const #21 = NameAndType	#12:#13;//  offset$1:I
const #22 = Field	#9.#21;	//  scala/util/JenkinsHash$$anonfun$fourByteToLong$1.offset$1:I
const #23 = Asciz	java/lang/Object;
const #24 = class	#23;	//  java/lang/Object
const #25 = NameAndType	#16:#4;//  "<init>":()V
const #26 = Method	#24.#25;	//  java/lang/Object."<init>":()V
const #27 = Asciz	scala/Function1$class;
const #28 = class	#27;	//  scala/Function1$class
const #29 = Asciz	$init$;
const #30 = Asciz	(Lscala/Function1;)V;
const #31 = NameAndType	#29:#30;//  $init$:(Lscala/Function1;)V
const #32 = Method	#28.#31;	//  scala/Function1$class.$init$:(Lscala/Function1;)V
const #33 = Asciz	apply;
const #34 = Asciz	(Ljava/lang/Object;)Ljava/lang/Object;;
const #35 = Asciz	scala/runtime/BoxesRunTime;
const #36 = class	#35;	//  scala/runtime/BoxesRunTime
const #37 = Asciz	unboxToInt;
const #38 = Asciz	(Ljava/lang/Object;)I;
const #39 = NameAndType	#37:#38;//  unboxToInt:(Ljava/lang/Object;)I
const #40 = Method	#36.#39;	//  scala/runtime/BoxesRunTime.unboxToInt:(Ljava/lang/Object;)I
const #41 = Asciz	(I)J;
const #42 = NameAndType	#33:#41;//  apply:(I)J
const #43 = Method	#9.#42;	//  scala/util/JenkinsHash$$anonfun$fourByteToLong$1.apply:(I)J
const #44 = Asciz	boxToLong;
const #45 = Asciz	(J)Ljava/lang/Long;;
const #46 = NameAndType	#44:#45;//  boxToLong:(J)Ljava/lang/Long;
const #47 = Method	#36.#46;	//  scala/runtime/BoxesRunTime.boxToLong:(J)Ljava/lang/Long;
const #48 = Asciz	this;
const #49 = Asciz	Lscala/util/JenkinsHash$$anonfun$fourByteToLong$1;;
const #50 = Asciz	v1;
const #51 = Asciz	Ljava/lang/Object;;
const #52 = Asciz	LocalVariableTable;
const #53 = Asciz	scala/util/JenkinsHash$;
const #54 = class	#53;	//  scala/util/JenkinsHash$
const #55 = Asciz	MODULE$;
const #56 = Asciz	Lscala/util/JenkinsHash$;;
const #57 = NameAndType	#55:#56;//  MODULE$:Lscala/util/JenkinsHash$;
const #58 = Field	#54.#57;	//  scala/util/JenkinsHash$.MODULE$:Lscala/util/JenkinsHash$;
const #59 = Asciz	scala$util$JenkinsHash$$byteToLong;
const #60 = Asciz	(B)J;
const #61 = NameAndType	#59:#60;//  scala$util$JenkinsHash$$byteToLong:(B)J
const #62 = Method	#54.#61;	//  scala/util/JenkinsHash$.scala$util$JenkinsHash$$byteToLong:(B)J
const #63 = int	8;
const #64 = Asciz	i;
const #65 = Asciz	andThen;
const #66 = Asciz	(Lscala/Function1;)Lscala/Function1;;
const #67 = Asciz	(Lscala/Function1;Lscala/Function1;)Lscala/Function1;;
const #68 = NameAndType	#65:#67;//  andThen:(Lscala/Function1;Lscala/Function1;)Lscala/Function1;
const #69 = Method	#28.#68;	//  scala/Function1$class.andThen:(Lscala/Function1;Lscala/Function1;)Lscala/Function1;
const #70 = Asciz	g;
const #71 = Asciz	Lscala/Function1;;
const #72 = Asciz	compose;
const #73 = NameAndType	#72:#67;//  compose:(Lscala/Function1;Lscala/Function1;)Lscala/Function1;
const #74 = Method	#28.#73;	//  scala/Function1$class.compose:(Lscala/Function1;Lscala/Function1;)Lscala/Function1;
const #75 = Asciz	toString;
const #76 = Asciz	()Ljava/lang/String;;
const #77 = Asciz	(Lscala/Function1;)Ljava/lang/String;;
const #78 = NameAndType	#75:#77;//  toString:(Lscala/Function1;)Ljava/lang/String;
const #79 = Method	#28.#78;	//  scala/Function1$class.toString:(Lscala/Function1;)Ljava/lang/String;
const #80 = Asciz	Scala;
const #81 = Asciz	InnerClasses;
const #82 = Asciz	scala/util/JenkinsHash;
const #83 = class	#82;	//  scala/util/JenkinsHash
const #84 = Asciz	$anonfun$fourByteToLong$1;
const #85 = Asciz	scala/Function1;
const #86 = class	#85;	//  scala/Function1
const #87 = Asciz	scala/ScalaObject;
const #88 = class	#87;	//  scala/ScalaObject
const #89 = Asciz	java/io/Serializable;
const #90 = class	#89;	//  java/io/Serializable

{
public static final long serialVersionUID;

public static {};
  Code:
   Stack=2, Locals=0, Args_size=0
   0:	lconst_0
   1:	putstatic	#11; //Field serialVersionUID:J
   4:	return

public scala.util.JenkinsHash$$anonfun$fourByteToLong$1(byte[], int);
  Code:
   Stack=2, Locals=3, Args_size=3
   0:	aload_0
   1:	aload_1
   2:	putfield	#20; //Field bytes$1:[B
   5:	aload_0
   6:	iload_2
   7:	putfield	#22; //Field offset$1:I
   10:	aload_0
   11:	invokespecial	#26; //Method java/lang/Object."<init>":()V
   14:	aload_0
   15:	invokestatic	#32; //Method scala/Function1$class.$init$:(Lscala/Function1;)V
   18:	return
  LineNumberTable: 
   line 117: 0


public final java.lang.Object apply(java.lang.Object);
  Code:
   Stack=2, Locals=4, Args_size=2
   0:	aload_0
   1:	aload_1
   2:	invokestatic	#40; //Method scala/runtime/BoxesRunTime.unboxToInt:(Ljava/lang/Object;)I
   5:	invokevirtual	#43; //Method apply:(I)J
   8:	lstore_2
   9:	lload_2
   10:	invokestatic	#47; //Method scala/runtime/BoxesRunTime.boxToLong:(J)Ljava/lang/Long;
   13:	areturn
  LineNumberTable: 
   line 117: 0

  LocalVariableTable: 
   Start  Length  Slot  Name   Signature
   0      14      0    this       Lscala/util/JenkinsHash$$anonfun$fourByteToLong$1;
   0      14      1    v1       Ljava/lang/Object;


public final long apply(int);
  Code:
   Stack=4, Locals=2, Args_size=2
   0:	getstatic	#58; //Field scala/util/JenkinsHash$.MODULE$:Lscala/util/JenkinsHash$;
   3:	aload_0
   4:	getfield	#20; //Field bytes$1:[B
   7:	aload_0
   8:	getfield	#22; //Field offset$1:I
   11:	iload_1
   12:	iadd
   13:	baload
   14:	invokevirtual	#62; //Method scala/util/JenkinsHash$.scala$util$JenkinsHash$$byteToLong:(B)J
   17:	iload_1
   18:	ldc	#63; //int 8
   20:	imul
   21:	lshl
   22:	lreturn
  LineNumberTable: 
   line 117: 0

  LocalVariableTable: 
   Start  Length  Slot  Name   Signature
   0      23      0    this       Lscala/util/JenkinsHash$$anonfun$fourByteToLong$1;
   0      23      1    i       I


public scala.Function1 andThen(scala.Function1);
  Code:
   Stack=2, Locals=2, Args_size=2
   0:	aload_0
   1:	aload_1
   2:	invokestatic	#69; //Method scala/Function1$class.andThen:(Lscala/Function1;Lscala/Function1;)Lscala/Function1;
   5:	areturn
  LineNumberTable: 
   line 117: 0

  LocalVariableTable: 
   Start  Length  Slot  Name   Signature
   0      6      0    this       Lscala/util/JenkinsHash$$anonfun$fourByteToLong$1;
   0      6      1    g       Lscala/Function1;


public scala.Function1 compose(scala.Function1);
  Code:
   Stack=2, Locals=2, Args_size=2
   0:	aload_0
   1:	aload_1
   2:	invokestatic	#74; //Method scala/Function1$class.compose:(Lscala/Function1;Lscala/Function1;)Lscala/Function1;
   5:	areturn
  LineNumberTable: 
   line 117: 0

  LocalVariableTable: 
   Start  Length  Slot  Name   Signature
   0      6      0    this       Lscala/util/JenkinsHash$$anonfun$fourByteToLong$1;
   0      6      1    g       Lscala/Function1;


public java.lang.String toString();
  Code:
   Stack=1, Locals=1, Args_size=1
   0:	aload_0
   1:	invokestatic	#79; //Method scala/Function1$class.toString:(Lscala/Function1;)Ljava/lang/String;
   4:	areturn
  LineNumberTable: 
   line 117: 0


}

