Compiled from "JenkinsHash.scala"
public final class scala.util.JenkinsHash$$anonfun$hashAnyValSeq$1 extends java.lang.Object implements scala.Function1,scala.ScalaObject,java.io.Serializable
  SourceFile: "JenkinsHash.scala"
  Scala: length = 0x
   
  InnerClass: 
   public final $anonfun$hashAnyValSeq$1=class scala/util/JenkinsHash$$anonfun$hashAnyValSeq$1 of class scala/util/JenkinsHash
  minor version: 0
  major version: 49
  Constant pool:
Asciz	SourceFile;
Asciz	JenkinsHash.scala;
Asciz	<clinit>;
Asciz	()V;
Asciz	Code;
Asciz	serialVersionUID;
Asciz	J;
Asciz	scala/util/JenkinsHash$$anonfun$hashAnyValSeq$1;
class	scala/util/JenkinsHash$$anonfun$hashAnyValSeq$1
NameAndType	serialVersionUID:J
Field	scala/util/JenkinsHash$$anonfun$hashAnyValSeq$1.serialVersionUID:J
Asciz	bb$1;
Asciz	Ljava/nio/ByteBuffer;;
Asciz	<init>;
Asciz	(Ljava/nio/ByteBuffer;)V;
Asciz	LineNumberTable;
NameAndType	bb$1:Ljava/nio/ByteBuffer;
Field	scala/util/JenkinsHash$$anonfun$hashAnyValSeq$1.bb$1:Ljava/nio/ByteBuffer;
Asciz	java/lang/Object;
class	java/lang/Object
NameAndType	"<init>":()V
Method	java/lang/Object."<init>":()V
Asciz	scala/Function1$class;
class	scala/Function1$class
Asciz	$init$;
Asciz	(Lscala/Function1;)V;
NameAndType	$init$:(Lscala/Function1;)V
Method	scala/Function1$class.$init$:(Lscala/Function1;)V
Asciz	apply;
Asciz	(Ljava/lang/Object;)Ljava/lang/Object;;
Asciz	scala/util/JenkinsHash$;
class	scala/util/JenkinsHash$
Asciz	MODULE$;
Asciz	Lscala/util/JenkinsHash$;;
NameAndType	MODULE$:Lscala/util/JenkinsHash$;
Field	scala/util/JenkinsHash$.MODULE$:Lscala/util/JenkinsHash$;
Asciz	scala$util$JenkinsHash$$putAnyVal;
Asciz	(Ljava/nio/ByteBuffer;Ljava/lang/Object;)Ljava/lang/Object;;
NameAndType	scala$util$JenkinsHash$$putAnyVal:(Ljava/nio/ByteBuffer;Ljava/lang/Object;)Ljava/lang/Object;
Method	scala/util/JenkinsHash$.scala$util$JenkinsHash$$putAnyVal:(Ljava/nio/ByteBuffer;Ljava/lang/Object;)Ljava/lang/Object;
Asciz	this;
Asciz	Lscala/util/JenkinsHash$$anonfun$hashAnyValSeq$1;;
Asciz	x;
Asciz	Ljava/lang/Object;;
Asciz	LocalVariableTable;
Asciz	andThen;
Asciz	(Lscala/Function1;)Lscala/Function1;;
Asciz	(Lscala/Function1;Lscala/Function1;)Lscala/Function1;;
NameAndType	andThen:(Lscala/Function1;Lscala/Function1;)Lscala/Function1;
Method	scala/Function1$class.andThen:(Lscala/Function1;Lscala/Function1;)Lscala/Function1;
Asciz	g;
Asciz	Lscala/Function1;;
Asciz	compose;
NameAndType	compose:(Lscala/Function1;Lscala/Function1;)Lscala/Function1;
Method	scala/Function1$class.compose:(Lscala/Function1;Lscala/Function1;)Lscala/Function1;
Asciz	toString;
Asciz	()Ljava/lang/String;;
Asciz	(Lscala/Function1;)Ljava/lang/String;;
NameAndType	toString:(Lscala/Function1;)Ljava/lang/String;
Method	scala/Function1$class.toString:(Lscala/Function1;)Ljava/lang/String;
Asciz	Scala;
Asciz	InnerClasses;
Asciz	scala/util/JenkinsHash;
class	scala/util/JenkinsHash
Asciz	$anonfun$hashAnyValSeq$1;
Asciz	scala/Function1;
class	scala/Function1
Asciz	scala/ScalaObject;
class	scala/ScalaObject
Asciz	java/io/Serializable;
class	java/io/Serializable

{
public static final long serialVersionUID;
  Signature: J

private final java.nio.ByteBuffer bb$1;
  Signature: Ljava/nio/ByteBuffer;

public static {};
  Signature: ()V
  Code:
   Stack=2, Locals=0, Args_size=0
	lconst_0
	putstatic	Field serialVersionUID:J
	return
  Labels:

public scala.util.JenkinsHash$$anonfun$hashAnyValSeq$1(java.nio.ByteBuffer);
  Signature: (Ljava/nio/ByteBuffer;)V
  Code:
   Stack=2, Locals=2, Args_size=2
	aload_0
	aload_1
	putfield	Field bb$1:Ljava/nio/ByteBuffer;
	aload_0
	invokespecial	Method java/lang/Object."<init>":()V
	aload_0
	invokestatic	Method scala/Function1$class.$init$:(Lscala/Function1;)V
	return
  Labels:

public final java.lang.Object apply(java.lang.Object);
  Signature: (Ljava/lang/Object;)Ljava/lang/Object;
  Code:
   Stack=3, Locals=2, Args_size=2
	getstatic	Field scala/util/JenkinsHash$.MODULE$:Lscala/util/JenkinsHash$;
	aload_0
	getfield	Field bb$1:Ljava/nio/ByteBuffer;
	aload_1
	invokevirtual	Method scala/util/JenkinsHash$.scala$util$JenkinsHash$$putAnyVal:(Ljava/nio/ByteBuffer;Ljava/lang/Object;)Ljava/lang/Object;
	areturn
  Labels:
  LocalVariableTable: 
   Start  Length  Slot  Name   Signature
   0      12      0    this       Lscala/util/JenkinsHash$$anonfun$hashAnyValSeq$1;
   0      12      1    x       Ljava/lang/Object;


public scala.Function1 andThen(scala.Function1);
  Signature: (Lscala/Function1;)Lscala/Function1;
  Code:
   Stack=2, Locals=2, Args_size=2
	aload_0
	aload_1
	invokestatic	Method scala/Function1$class.andThen:(Lscala/Function1;Lscala/Function1;)Lscala/Function1;
	areturn
  Labels:
  LocalVariableTable: 
   Start  Length  Slot  Name   Signature
   0      6      0    this       Lscala/util/JenkinsHash$$anonfun$hashAnyValSeq$1;
   0      6      1    g       Lscala/Function1;


public scala.Function1 compose(scala.Function1);
  Signature: (Lscala/Function1;)Lscala/Function1;
  Code:
   Stack=2, Locals=2, Args_size=2
	aload_0
	aload_1
	invokestatic	Method scala/Function1$class.compose:(Lscala/Function1;Lscala/Function1;)Lscala/Function1;
	areturn
  Labels:
  LocalVariableTable: 
   Start  Length  Slot  Name   Signature
   0      6      0    this       Lscala/util/JenkinsHash$$anonfun$hashAnyValSeq$1;
   0      6      1    g       Lscala/Function1;


public java.lang.String toString();
  Signature: ()Ljava/lang/String;
  Code:
   Stack=1, Locals=1, Args_size=1
	aload_0
	invokestatic	Method scala/Function1$class.toString:(Lscala/Function1;)Ljava/lang/String;
	areturn
  Labels:

}

