Compiled from "JenkinsHash.scala"
public final class scala.util.JenkinsHash extends java.lang.Object
  SourceFile: "JenkinsHash.scala"
  ScalaSig: length = 0x45A
   05 00 FFFFFF81 27 07 05 01 02 FFFFFF88 02 07 01 0B 4A 65 6E
   6B 69 6E 73 48 61 73 68 0A 02 03 04 01 04 75 74
   69 6C 0A 01 05 01 05 73 63 61 6C 61 03 00 10 02
   08 09 0D 01 02 06 08 0A 02 FFFFFF84 FFFFFF80 FFFFFF80 FFFFFF88 02 0B 02
   0B 4A 65 6E 6B 69 6E 73 48 61 73 68 13 03 09 0C
   14 10 02 0D 12 0D 01 0E 0A 02 0F 10 01 04 6C 61
   6E 67 0A 01 11 01 04 6A 61 76 61 09 02 13 0E 02
   06 4F 62 6A 65 63 74 10 02 15 16 0D 01 04 09 02
   17 04 02 0B 53 63 61 6C 61 4F 62 6A 65 63 74 08
   05 19 09 FFFFFF84 00 1A 01 06 3C 69 6E 69 74 3E 14 01
   07 08 07 1C 09 FFFFFFC2 FFFFFF80 FFFFFF84 02 1D 01 09 4D 41 58 5F
   56 41 4C 55 45 15 01 1E 0F 01 1F 1E 05 00 FFFFFFFF FFFFFFFF
   FFFFFFFF FFFFFFFF 08 06 21 09 FFFFFFA0 FFFFFF80 06 1E 01 0A 4D 41 58 5F
   56 41 4C 55 45 20 08 05 23 09 FFFFFF84 04 24 01 0D 62
   79 74 65 73 50 72 6F 76 69 64 65 64 14 02 25 28
   10 02 15 26 09 02 27 04 02 03 49 6E 74 08 05 29
   22 FFFFFFC0 00 2A 01 01 76 10 02 15 2B 09 02 2C 04 02
   03 41 6E 79 08 05 2E 09 FFFFFF84 04 2F 01 09 70 75 74
   41 6E 79 56 61 6C 14 03 2A 30 38 08 05 31 2D FFFFFFC0
   00 32 01 02 62 62 10 02 33 36 0D 01 34 0A 02 35
   10 01 03 6E 69 6F 09 02 37 34 02 0A 42 79 74 65
   42 75 66 66 65 72 08 05 29 2D FFFFFFC0 00 39 10 02 15
   3A 09 02 3B 04 02 06 41 6E 79 56 61 6C 08 05 3D
   09 FFFFFF84 04 3E 01 0B 63 6C 61 73 73 69 66 79 41 6E
   79 14 02 3F 49 10 04 15 40 42 45 09 02 41 04 02
   06 54 75 70 6C 65 32 10 03 15 43 39 09 02 44 04
   02 06 4F 70 74 69 6F 6E 10 03 15 43 46 10 02 15
   47 09 02 48 04 02 06 41 6E 79 52 65 66 08 05 4A
   3C FFFFFFC0 00 2A 01 01 78 08 05 4C 09 FFFFFF84 04 4D 01 16
   70 61 72 74 69 74 69 6F 6E 56 61 6C 75 65 73 41
   6E 64 52 65 66 73 14 02 4E 5C 10 04 15 40 4F 5B
   10 03 50 58 39 0E 02 51 56 0E 02 52 55 0D 01 53
   0A 02 54 06 01 06 3C 72 6F 6F 74 3E 09 01 05 09
   02 57 04 01 07 70 61 63 6B 61 67 65 09 02 59 5A
   02 03 53 65 71 0A 02 57 04 10 03 50 58 46 08 05
   5D 4B FFFFFFC0 00 5E 01 02 78 73 10 03 50 58 2A 08 05
   60 09 FFFFFF84 04 61 01 0D 68 61 73 68 41 6E 79 56 61
   6C 53 65 71 14 02 25 62 08 05 5D 5F FFFFFFC0 00 4F 08
   05 64 09 FFFFFF84 04 65 01 0A 62 79 74 65 54 6F 4C 6F
   6E 67 14 02 66 69 10 02 15 67 09 02 68 04 02 04
   4C 6F 6E 67 08 05 6A 63 FFFFFFC0 00 6B 01 01 62 10 02
   15 6C 09 02 6D 04 02 04 42 79 74 65 08 05 6F 09
   FFFFFF84 04 70 01 03 61 64 64 14 03 66 71 73 08 05 72
   6E FFFFFFC0 00 66 01 02 78 31 08 05 74 6E FFFFFFC0 00 66 01
   02 78 32 08 05 76 09 FFFFFF84 04 77 01 08 73 75 62 74
   72 61 63 74 14 03 66 78 79 08 05 72 75 FFFFFFC0 00 66
   08 05 74 75 FFFFFFC0 00 66 08 05 7B 09 FFFFFF84 04 7C 01 03
   78 6F 72 14 03 66 7D 7E 08 05 72 7A FFFFFFC0 00 66 08
   05 74 7A FFFFFFC0 00 66 08 07 FFFFFF81 00 09 FFFFFF84 04 FFFFFF81 01 01
   09 6C 65 66 74 53 68 69 66 74 14 05 66 FFFFFF81 02 FFFFFF81
   03 08 05 4A 7F FFFFFFC0 00 66 08 06 FFFFFF81 04 7F FFFFFFC0 00 25
   01 05 73 68 69 66 74 08 07 FFFFFF81 06 09 FFFFFF84 04 FFFFFF81 07
   01 0E 66 6F 75 72 42 79 74 65 54 6F 4C 6F 6E 67
   14 05 66 FFFFFF81 08 FFFFFF81 0D 08 08 FFFFFF81 09 FFFFFF81 05 FFFFFFC0 00 FFFFFF81
   0A 01 05 62 79 74 65 73 10 04 15 FFFFFF81 0B 6B 09 03
   FFFFFF81 0C 04 02 05 41 72 72 61 79 08 07 FFFFFF81 0E FFFFFF81 05
   FFFFFFC0 00 25 01 06 6F 66 66 73 65 74 08 07 FFFFFF81 10 09
   FFFFFF84 00 FFFFFF81 11 01 07 68 61 73 68 53 65 71 14 03 25
   FFFFFF81 12 08 06 5D FFFFFF81 0F FFFFFFC0 00 5E 08 07 FFFFFF81 14 09 FFFFFF84
   00 FFFFFF81 15 01 04 68 61 73 68 14 05 66 FFFFFF81 16 FFFFFF81 18
   08 08 FFFFFF81 17 FFFFFF81 13 FFFFFFC0 00 FFFFFF81 0A 01 06 62 75 66 66
   65 72 08 0B FFFFFF81 1A FFFFFF81 19 FFFFFF81 13 FFFFFF90 FFFFFF80 FFFFFFC0 00 66 01
   0C 69 6E 69 74 69 61 6C 56 61 6C 75 65 08 09 FFFFFF81
   1B 09 FFFFFF91 FFFFFF80 FFFFFF84 00 FFFFFF81 1C 01 0E 68 61 73 68 24 64
   65 66 61 75 6C 74 24 32 15 02 FFFFFF81 1D 2A 03 66 FFFFFF81
   1E 2B 02 FFFFFF81 1F 10 04 FFFFFF81 20 FFFFFF81 25 0D 02 FFFFFF81 21 0A
   04 FFFFFF81 22 FFFFFF81 23 01 09 75 6E 63 68 65 63 6B 65 64
   0A 03 FFFFFF81 24 04 01 0A 61 6E 6E 6F 74 61 74 69 6F
   6E 09 04 FFFFFF81 26 FFFFFF81 21 02 11 75 6E 63 68 65 63 6B
   65 64 56 61 72 69 61 6E 63 65 
  InnerClass: 
   public final #49= #46 of #48; //$anonfun$3=class scala/util/JenkinsHash$$anonfun$3 of class scala/util/JenkinsHash
   public final #52= #51 of #48; //$anonfun$2=class scala/util/JenkinsHash$$anonfun$2 of class scala/util/JenkinsHash
   public final #55= #54 of #48; //$anonfun$1=class scala/util/JenkinsHash$$anonfun$1 of class scala/util/JenkinsHash
   public final #58= #57 of #48; //$anonfun$hashAnyValSeq$1=class scala/util/JenkinsHash$$anonfun$hashAnyValSeq$1 of class scala/util/JenkinsHash
   public final #61= #60 of #48; //$anonfun$fourByteToLong$1=class scala/util/JenkinsHash$$anonfun$fourByteToLong$1 of class scala/util/JenkinsHash
   public final #64= #63 of #48; //$anonfun$partitionValuesAndRefs$2=class scala/util/JenkinsHash$$anonfun$partitionValuesAndRefs$2 of class scala/util/JenkinsHash
   public final #67= #66 of #48; //$anonfun$partitionValuesAndRefs$1=class scala/util/JenkinsHash$$anonfun$partitionValuesAndRefs$1 of class scala/util/JenkinsHash
  minor version: 0
  major version: 49
  Constant pool:
const #1 = Asciz	SourceFile;
const #2 = Asciz	JenkinsHash.scala;
const #3 = Asciz	hash$default$2;
const #4 = Asciz	()J;
const #5 = Asciz	Code;
const #6 = Asciz	scala/util/JenkinsHash$;
const #7 = class	#6;	//  scala/util/JenkinsHash$
const #8 = Asciz	MODULE$;
const #9 = Asciz	Lscala/util/JenkinsHash$;;
const #10 = NameAndType	#8:#9;//  MODULE$:Lscala/util/JenkinsHash$;
const #11 = Field	#7.#10;	//  scala/util/JenkinsHash$.MODULE$:Lscala/util/JenkinsHash$;
const #12 = NameAndType	#3:#4;//  hash$default$2:()J
const #13 = Method	#7.#12;	//  scala/util/JenkinsHash$.hash$default$2:()J
const #14 = Asciz	hash;
const #15 = Asciz	([BJ)J;
const #16 = NameAndType	#14:#15;//  hash:([BJ)J
const #17 = Method	#7.#16;	//  scala/util/JenkinsHash$.hash:([BJ)J
const #18 = Asciz	hashSeq;
const #19 = Asciz	(Lscala/collection/Seq;)I;
const #20 = NameAndType	#18:#19;//  hashSeq:(Lscala/collection/Seq;)I
const #21 = Method	#7.#20;	//  scala/util/JenkinsHash$.hashSeq:(Lscala/collection/Seq;)I
const #22 = Asciz	(Lscala/collection/Seq<Ljava/lang/Object;>;)I;
const #23 = Asciz	Signature;
const #24 = Asciz	scala$util$JenkinsHash$$byteToLong;
const #25 = Asciz	(B)J;
const #26 = NameAndType	#24:#25;//  scala$util$JenkinsHash$$byteToLong:(B)J
const #27 = Method	#7.#26;	//  scala/util/JenkinsHash$.scala$util$JenkinsHash$$byteToLong:(B)J
const #28 = Asciz	scala$util$JenkinsHash$$classifyAny;
const #29 = Asciz	(Ljava/lang/Object;)Lscala/Tuple2;;
const #30 = NameAndType	#28:#29;//  scala$util$JenkinsHash$$classifyAny:(Ljava/lang/Object;)Lscala/Tuple2;
const #31 = Method	#7.#30;	//  scala/util/JenkinsHash$.scala$util$JenkinsHash$$classifyAny:(Ljava/lang/Object;)Lscala/Tuple2;
const #32 = Asciz	scala$util$JenkinsHash$$putAnyVal;
const #33 = Asciz	(Ljava/nio/ByteBuffer;Ljava/lang/Object;)Ljava/lang/Object;;
const #34 = NameAndType	#32:#33;//  scala$util$JenkinsHash$$putAnyVal:(Ljava/nio/ByteBuffer;Ljava/lang/Object;)Ljava/lang/Object;
const #35 = Method	#7.#34;	//  scala/util/JenkinsHash$.scala$util$JenkinsHash$$putAnyVal:(Ljava/nio/ByteBuffer;Ljava/lang/Object;)Ljava/lang/Object;
const #36 = Asciz	scala$util$JenkinsHash$$bytesProvided;
const #37 = Asciz	(Ljava/lang/Object;)I;
const #38 = NameAndType	#36:#37;//  scala$util$JenkinsHash$$bytesProvided:(Ljava/lang/Object;)I
const #39 = Method	#7.#38;	//  scala/util/JenkinsHash$.scala$util$JenkinsHash$$bytesProvided:(Ljava/lang/Object;)I
const #40 = Asciz	MAX_VALUE;
const #41 = NameAndType	#40:#4;//  MAX_VALUE:()J
const #42 = Method	#7.#41;	//  scala/util/JenkinsHash$.MAX_VALUE:()J
const #43 = Asciz	ScalaSig;
const #44 = Asciz	InnerClasses;
const #45 = Asciz	scala/util/JenkinsHash$$anonfun$3;
const #46 = class	#45;	//  scala/util/JenkinsHash$$anonfun$3
const #47 = Asciz	scala/util/JenkinsHash;
const #48 = class	#47;	//  scala/util/JenkinsHash
const #49 = Asciz	$anonfun$3;
const #50 = Asciz	scala/util/JenkinsHash$$anonfun$2;
const #51 = class	#50;	//  scala/util/JenkinsHash$$anonfun$2
const #52 = Asciz	$anonfun$2;
const #53 = Asciz	scala/util/JenkinsHash$$anonfun$1;
const #54 = class	#53;	//  scala/util/JenkinsHash$$anonfun$1
const #55 = Asciz	$anonfun$1;
const #56 = Asciz	scala/util/JenkinsHash$$anonfun$hashAnyValSeq$1;
const #57 = class	#56;	//  scala/util/JenkinsHash$$anonfun$hashAnyValSeq$1
const #58 = Asciz	$anonfun$hashAnyValSeq$1;
const #59 = Asciz	scala/util/JenkinsHash$$anonfun$fourByteToLong$1;
const #60 = class	#59;	//  scala/util/JenkinsHash$$anonfun$fourByteToLong$1
const #61 = Asciz	$anonfun$fourByteToLong$1;
const #62 = Asciz	scala/util/JenkinsHash$$anonfun$partitionValuesAndRefs$2;
const #63 = class	#62;	//  scala/util/JenkinsHash$$anonfun$partitionValuesAndRefs$2
const #64 = Asciz	$anonfun$partitionValuesAndRefs$2;
const #65 = Asciz	scala/util/JenkinsHash$$anonfun$partitionValuesAndRefs$1;
const #66 = class	#65;	//  scala/util/JenkinsHash$$anonfun$partitionValuesAndRefs$1
const #67 = Asciz	$anonfun$partitionValuesAndRefs$1;
const #68 = Asciz	java/lang/Object;
const #69 = class	#68;	//  java/lang/Object

{
public static final long hash$default$2();
  Code:
   Stack=2, Locals=0, Args_size=0
   0:	getstatic	#11; //Field scala/util/JenkinsHash$.MODULE$:Lscala/util/JenkinsHash$;
   3:	invokevirtual	#13; //Method scala/util/JenkinsHash$.hash$default$2:()J
   6:	lreturn

public static final long hash(byte[], long);
  Code:
   Stack=4, Locals=3, Args_size=2
   0:	getstatic	#11; //Field scala/util/JenkinsHash$.MODULE$:Lscala/util/JenkinsHash$;
   3:	aload_0
   4:	lload_1
   5:	invokevirtual	#17; //Method scala/util/JenkinsHash$.hash:([BJ)J
   8:	lreturn

public static final int hashSeq(scala.collection.Seq);
  Code:
   Stack=2, Locals=1, Args_size=1
   0:	getstatic	#11; //Field scala/util/JenkinsHash$.MODULE$:Lscala/util/JenkinsHash$;
   3:	aload_0
   4:	invokevirtual	#21; //Method scala/util/JenkinsHash$.hashSeq:(Lscala/collection/Seq;)I
   7:	ireturn
  Signature: length = 0x2
   00 16 

public static final long scala$util$JenkinsHash$$byteToLong(byte);
  Code:
   Stack=2, Locals=1, Args_size=1
   0:	getstatic	#11; //Field scala/util/JenkinsHash$.MODULE$:Lscala/util/JenkinsHash$;
   3:	iload_0
   4:	invokevirtual	#27; //Method scala/util/JenkinsHash$.scala$util$JenkinsHash$$byteToLong:(B)J
   7:	lreturn

public static final scala.Tuple2 scala$util$JenkinsHash$$classifyAny(java.lang.Object);
  Code:
   Stack=2, Locals=1, Args_size=1
   0:	getstatic	#11; //Field scala/util/JenkinsHash$.MODULE$:Lscala/util/JenkinsHash$;
   3:	aload_0
   4:	invokevirtual	#31; //Method scala/util/JenkinsHash$.scala$util$JenkinsHash$$classifyAny:(Ljava/lang/Object;)Lscala/Tuple2;
   7:	areturn

public static final java.lang.Object scala$util$JenkinsHash$$putAnyVal(java.nio.ByteBuffer, java.lang.Object);
  Code:
   Stack=3, Locals=2, Args_size=2
   0:	getstatic	#11; //Field scala/util/JenkinsHash$.MODULE$:Lscala/util/JenkinsHash$;
   3:	aload_0
   4:	aload_1
   5:	invokevirtual	#35; //Method scala/util/JenkinsHash$.scala$util$JenkinsHash$$putAnyVal:(Ljava/nio/ByteBuffer;Ljava/lang/Object;)Ljava/lang/Object;
   8:	areturn

public static final int scala$util$JenkinsHash$$bytesProvided(java.lang.Object);
  Code:
   Stack=2, Locals=1, Args_size=1
   0:	getstatic	#11; //Field scala/util/JenkinsHash$.MODULE$:Lscala/util/JenkinsHash$;
   3:	aload_0
   4:	invokevirtual	#39; //Method scala/util/JenkinsHash$.scala$util$JenkinsHash$$bytesProvided:(Ljava/lang/Object;)I
   7:	ireturn

public static final long MAX_VALUE();
  Code:
   Stack=2, Locals=0, Args_size=0
   0:	getstatic	#11; //Field scala/util/JenkinsHash$.MODULE$:Lscala/util/JenkinsHash$;
   3:	invokevirtual	#42; //Method scala/util/JenkinsHash$.MAX_VALUE:()J
   6:	lreturn

}

