Compiled from "JenkinsHash.scala"
public final class scala.util.JenkinsHash$$anonfun$fourByteToLong$1 extends scala.runtime.AbstractFunction1 implements java.io.Serializable
  SourceFile: "JenkinsHash.scala"
  Scala: length = 0x
   
  InnerClass: 
   public final $anonfun$fourByteToLong$1=class scala/util/JenkinsHash$$anonfun$fourByteToLong$1 of class scala/util/JenkinsHash
  minor version: 0
  major version: 49
  Constant pool:
Asciz	SourceFile;
Asciz	JenkinsHash.scala;
Asciz	<clinit>;
Asciz	()V;
Asciz	Code;
Asciz	serialVersionUID;
Asciz	J;
Asciz	scala/util/JenkinsHash$$anonfun$fourByteToLong$1;
class	scala/util/JenkinsHash$$anonfun$fourByteToLong$1
NameAndType	serialVersionUID:J
Field	scala/util/JenkinsHash$$anonfun$fourByteToLong$1.serialVersionUID:J
Asciz	offset$1;
Asciz	I;
Asciz	bytes$1;
Asciz	[B;
Asciz	<init>;
Asciz	([BI)V;
Asciz	LineNumberTable;
NameAndType	bytes$1:[B
Field	scala/util/JenkinsHash$$anonfun$fourByteToLong$1.bytes$1:[B
NameAndType	offset$1:I
Field	scala/util/JenkinsHash$$anonfun$fourByteToLong$1.offset$1:I
Asciz	scala/runtime/AbstractFunction1;
class	scala/runtime/AbstractFunction1
NameAndType	"<init>":()V
Method	scala/runtime/AbstractFunction1."<init>":()V
Asciz	apply;
Asciz	(Ljava/lang/Object;)Ljava/lang/Object;;
Asciz	scala/runtime/BoxesRunTime;
class	scala/runtime/BoxesRunTime
Asciz	unboxToInt;
Asciz	(Ljava/lang/Object;)I;
NameAndType	unboxToInt:(Ljava/lang/Object;)I
Method	scala/runtime/BoxesRunTime.unboxToInt:(Ljava/lang/Object;)I
Asciz	(I)J;
NameAndType	apply:(I)J
Method	scala/util/JenkinsHash$$anonfun$fourByteToLong$1.apply:(I)J
Asciz	boxToLong;
Asciz	(J)Ljava/lang/Long;;
NameAndType	boxToLong:(J)Ljava/lang/Long;
Method	scala/runtime/BoxesRunTime.boxToLong:(J)Ljava/lang/Long;
Asciz	this;
Asciz	Lscala/util/JenkinsHash$$anonfun$fourByteToLong$1;;
Asciz	v1;
Asciz	Ljava/lang/Object;;
Asciz	LocalVariableTable;
Asciz	scala/util/JenkinsHash$;
class	scala/util/JenkinsHash$
Asciz	MODULE$;
Asciz	Lscala/util/JenkinsHash$;;
NameAndType	MODULE$:Lscala/util/JenkinsHash$;
Field	scala/util/JenkinsHash$.MODULE$:Lscala/util/JenkinsHash$;
Asciz	scala$util$JenkinsHash$$byteToLong;
Asciz	(B)J;
NameAndType	scala$util$JenkinsHash$$byteToLong:(B)J
Method	scala/util/JenkinsHash$.scala$util$JenkinsHash$$byteToLong:(B)J
int	8;
Asciz	i;
Asciz	Scala;
Asciz	InnerClasses;
Asciz	scala/util/JenkinsHash;
class	scala/util/JenkinsHash
Asciz	$anonfun$fourByteToLong$1;
Asciz	java/io/Serializable;
class	java/io/Serializable

{
public static final long serialVersionUID;
  Signature: J

private final int offset$1;
  Signature: I

private final byte[] bytes$1;
  Signature: [B

public static {};
  Signature: ()V
  Code:
   Stack=2, Locals=0, Args_size=0
	lconst_0
	putstatic	Field serialVersionUID:J
	return
  Labels:

public scala.util.JenkinsHash$$anonfun$fourByteToLong$1(byte[], int);
  Signature: ([BI)V
  Code:
   Stack=2, Locals=3, Args_size=3
	aload_0
	aload_1
	putfield	Field bytes$1:[B
	aload_0
	iload_2
	putfield	Field offset$1:I
	aload_0
	invokespecial	Method scala/runtime/AbstractFunction1."<init>":()V
	return
  Labels:

public final java.lang.Object apply(java.lang.Object);
  Signature: (Ljava/lang/Object;)Ljava/lang/Object;
  Code:
   Stack=2, Locals=4, Args_size=2
	aload_0
	aload_1
	invokestatic	Method scala/runtime/BoxesRunTime.unboxToInt:(Ljava/lang/Object;)I
	invokevirtual	Method apply:(I)J
	lstore_2
	lload_2
	invokestatic	Method scala/runtime/BoxesRunTime.boxToLong:(J)Ljava/lang/Long;
	areturn
  Labels:
  LocalVariableTable: 
   Start  Length  Slot  Name   Signature
   0      14      0    this       Lscala/util/JenkinsHash$$anonfun$fourByteToLong$1;
   0      14      1    v1       Ljava/lang/Object;


public final long apply(int);
  Signature: (I)J
  Code:
   Stack=4, Locals=2, Args_size=2
	getstatic	Field scala/util/JenkinsHash$.MODULE$:Lscala/util/JenkinsHash$;
	aload_0
	getfield	Field bytes$1:[B
	aload_0
	getfield	Field offset$1:I
	iload_1
	iadd
	baload
	invokevirtual	Method scala/util/JenkinsHash$.scala$util$JenkinsHash$$byteToLong:(B)J
	iload_1
	ldc	int 8
	imul
	lshl
	lreturn
  Labels:
  LocalVariableTable: 
   Start  Length  Slot  Name   Signature
   0      23      0    this       Lscala/util/JenkinsHash$$anonfun$fourByteToLong$1;
   0      23      1    i       I


}

