Compiled from "JenkinsHash.scala"
public final class scala.util.JenkinsHash$$anonfun$3 extends scala.runtime.AbstractFunction1 implements java.io.Serializable
  SourceFile: "JenkinsHash.scala"
  Scala: length = 0x
   
  InnerClass: 
   public final #49= #9 of #48; //$anonfun$3=class scala/util/JenkinsHash$$anonfun$3 of class scala/util/JenkinsHash
  minor version: 0
  major version: 49
  Constant pool:
const #1 = Asciz	SourceFile;
const #2 = Asciz	JenkinsHash.scala;
const #3 = Asciz	<clinit>;
const #4 = Asciz	()V;
const #5 = Asciz	Code;
const #6 = Asciz	serialVersionUID;
const #7 = Asciz	J;
const #8 = Asciz	scala/util/JenkinsHash$$anonfun$3;
const #9 = class	#8;	//  scala/util/JenkinsHash$$anonfun$3
const #10 = NameAndType	#6:#7;//  serialVersionUID:J
const #11 = Field	#9.#10;	//  scala/util/JenkinsHash$$anonfun$3.serialVersionUID:J
const #12 = Asciz	<init>;
const #13 = Asciz	LineNumberTable;
const #14 = Asciz	scala/runtime/AbstractFunction1;
const #15 = class	#14;	//  scala/runtime/AbstractFunction1
const #16 = NameAndType	#12:#4;//  "<init>":()V
const #17 = Method	#15.#16;	//  scala/runtime/AbstractFunction1."<init>":()V
const #18 = Asciz	apply;
const #19 = Asciz	(Ljava/lang/Object;)Ljava/lang/Object;;
const #20 = Asciz	(Ljava/lang/Object;)I;
const #21 = NameAndType	#18:#20;//  apply:(Ljava/lang/Object;)I
const #22 = Method	#9.#21;	//  scala/util/JenkinsHash$$anonfun$3.apply:(Ljava/lang/Object;)I
const #23 = Asciz	scala/runtime/BoxesRunTime;
const #24 = class	#23;	//  scala/runtime/BoxesRunTime
const #25 = Asciz	boxToInteger;
const #26 = Asciz	(I)Ljava/lang/Integer;;
const #27 = NameAndType	#25:#26;//  boxToInteger:(I)Ljava/lang/Integer;
const #28 = Method	#24.#27;	//  scala/runtime/BoxesRunTime.boxToInteger:(I)Ljava/lang/Integer;
const #29 = Asciz	this;
const #30 = Asciz	Lscala/util/JenkinsHash$$anonfun$3;;
const #31 = Asciz	v1;
const #32 = Asciz	Ljava/lang/Object;;
const #33 = Asciz	LocalVariableTable;
const #34 = Asciz	java/lang/Object;
const #35 = class	#34;	//  java/lang/Object
const #36 = Asciz	equals;
const #37 = Asciz	(Ljava/lang/Object;)Z;
const #38 = NameAndType	#36:#37;//  equals:(Ljava/lang/Object;)Z
const #39 = Method	#35.#38;	//  java/lang/Object.equals:(Ljava/lang/Object;)Z
const #40 = Asciz	hashCode;
const #41 = Asciz	()I;
const #42 = NameAndType	#40:#41;//  hashCode:()I
const #43 = Method	#35.#42;	//  java/lang/Object.hashCode:()I
const #44 = Asciz	x;
const #45 = Asciz	Scala;
const #46 = Asciz	InnerClasses;
const #47 = Asciz	scala/util/JenkinsHash;
const #48 = class	#47;	//  scala/util/JenkinsHash
const #49 = Asciz	$anonfun$3;
const #50 = Asciz	java/io/Serializable;
const #51 = class	#50;	//  java/io/Serializable

{
public static final long serialVersionUID;

public static {};
  Code:
   Stack=2, Locals=0, Args_size=0
   0:	lconst_0
   1:	putstatic	#11; //Field serialVersionUID:J
   4:	return

public scala.util.JenkinsHash$$anonfun$3();
  Code:
   Stack=1, Locals=1, Args_size=1
   0:	aload_0
   1:	invokespecial	#17; //Method scala/runtime/AbstractFunction1."<init>":()V
   4:	return
  LineNumberTable: 
   line 127: 0


public final java.lang.Object apply(java.lang.Object);
  Code:
   Stack=2, Locals=3, Args_size=2
   0:	aload_0
   1:	aload_1
   2:	invokevirtual	#22; //Method apply:(Ljava/lang/Object;)I
   5:	istore_2
   6:	iload_2
   7:	invokestatic	#28; //Method scala/runtime/BoxesRunTime.boxToInteger:(I)Ljava/lang/Integer;
   10:	areturn
  LineNumberTable: 
   line 127: 0

  LocalVariableTable: 
   Start  Length  Slot  Name   Signature
   0      11      0    this       Lscala/util/JenkinsHash$$anonfun$3;
   0      11      1    v1       Ljava/lang/Object;


public final int apply(java.lang.Object);
  Code:
   Stack=2, Locals=2, Args_size=2
   0:	aload_1
   1:	dup
   2:	pop
   3:	ifnull	14
   6:	aload_1
   7:	aconst_null
   8:	invokevirtual	#39; //Method java/lang/Object.equals:(Ljava/lang/Object;)Z
   11:	ifeq	18
   14:	iconst_0
   15:	goto	22
   18:	aload_1
   19:	invokevirtual	#43; //Method java/lang/Object.hashCode:()I
   22:	ireturn
  LineNumberTable: 
   line 127: 0

  LocalVariableTable: 
   Start  Length  Slot  Name   Signature
   0      23      0    this       Lscala/util/JenkinsHash$$anonfun$3;
   0      23      1    x       Ljava/lang/Object;


}

