Compiled from "JenkinsHash.scala"
public final class scala.util.JenkinsHash$ extends java.lang.Object implements scala.ScalaObject
  SourceFile: "JenkinsHash.scala"
  Scala: length = 0x
   
  InnerClass: 
   public final $anon$1=class scala/Predef$$anon$1 of class scala/Predef
   public Inclusive=class scala/collection/immutable/Range$Inclusive of class scala/collection/immutable/Range
   public final $anonfun$3=class scala/util/JenkinsHash$$anonfun$3 of class scala/util/JenkinsHash
   public final $anonfun$2=class scala/util/JenkinsHash$$anonfun$2 of class scala/util/JenkinsHash
   public final $anonfun$1=class scala/util/JenkinsHash$$anonfun$1 of class scala/util/JenkinsHash
   public final $anonfun$hashAnyValSeq$1=class scala/util/JenkinsHash$$anonfun$hashAnyValSeq$1 of class scala/util/JenkinsHash
   public final $anonfun$fourByteToLong$1=class scala/util/JenkinsHash$$anonfun$fourByteToLong$1 of class scala/util/JenkinsHash
   public GenericCanBuildFrom=class scala/collection/generic/TraversableFactory$GenericCanBuildFrom of class scala/collection/generic/TraversableFactory
   public final $anonfun$partitionValuesAndRefs$2=class scala/util/JenkinsHash$$anonfun$partitionValuesAndRefs$2 of class scala/util/JenkinsHash
   public final $anonfun$partitionValuesAndRefs$1=class scala/util/JenkinsHash$$anonfun$partitionValuesAndRefs$1 of class scala/util/JenkinsHash
  minor version: 0
  major version: 49
  Constant pool:
Asciz	SourceFile;
Asciz	JenkinsHash.scala;
Asciz	Scala;
Asciz	MODULE$;
Asciz	Lscala/util/JenkinsHash$;;
Asciz	<clinit>;
Asciz	()V;
Asciz	Code;
Asciz	scala/util/JenkinsHash$;
class	scala/util/JenkinsHash$
Asciz	<init>;
NameAndType	"<init>":()V
Method	scala/util/JenkinsHash$."<init>":()V
Asciz	MAX_VALUE;
Asciz	J;
Asciz	LineNumberTable;
Asciz	java/lang/Object;
class	java/lang/Object
Method	java/lang/Object."<init>":()V
NameAndType	MODULE$:Lscala/util/JenkinsHash$;
Field	scala/util/JenkinsHash$.MODULE$:Lscala/util/JenkinsHash$;
Asciz	mixTwelve$1;
Asciz	(I[BLscala/runtime/LongRef;Lscala/runtime/LongRef;Lscala/runtime/LongRef;)J;
Asciz	scala/runtime/LongRef;
class	scala/runtime/LongRef
Asciz	elem;
NameAndType	elem:J
Field	scala/runtime/LongRef.elem:J
Asciz	fourByteToLong;
Asciz	([BI)J;
NameAndType	fourByteToLong:([BI)J
Method	scala/util/JenkinsHash$.fourByteToLong:([BI)J
Asciz	add;
Asciz	(JJ)J;
NameAndType	add:(JJ)J
Method	scala/util/JenkinsHash$.add:(JJ)J
int	8;
Asciz	hashMix$1;
Asciz	(Lscala/runtime/LongRef;Lscala/runtime/LongRef;Lscala/runtime/LongRef;)J;
NameAndType	hashMix$1:(Lscala/runtime/LongRef;Lscala/runtime/LongRef;Lscala/runtime/LongRef;)J
Method	scala/util/JenkinsHash$.hashMix$1:(Lscala/runtime/LongRef;Lscala/runtime/LongRef;Lscala/runtime/LongRef;)J
Asciz	this;
Asciz	pos;
Asciz	I;
Asciz	LocalVariableTable;
Asciz	subtract;
NameAndType	subtract:(JJ)J
Method	scala/util/JenkinsHash$.subtract:(JJ)J
int	13;
Asciz	xor;
NameAndType	xor:(JJ)J
Method	scala/util/JenkinsHash$.xor:(JJ)J
Asciz	leftShift;
Asciz	(JI)J;
NameAndType	leftShift:(JI)J
Method	scala/util/JenkinsHash$.leftShift:(JI)J
int	12;
int	16;
int	10;
int	15;
Asciz	hash;
Asciz	([BJ)J;
long	2654435769l;
Asciz	(J)V;
NameAndType	"<init>":(J)V
Method	scala/runtime/LongRef."<init>":(J)V
NameAndType	mixTwelve$1:(I[BLscala/runtime/LongRef;Lscala/runtime/LongRef;Lscala/runtime/LongRef;)J
Method	scala/util/JenkinsHash$.mixTwelve$1:(I[BLscala/runtime/LongRef;Lscala/runtime/LongRef;Lscala/runtime/LongRef;)J
Asciz	scala$util$JenkinsHash$$byteToLong;
Asciz	(B)J;
NameAndType	scala$util$JenkinsHash$$byteToLong:(B)J
Method	scala/util/JenkinsHash$.scala$util$JenkinsHash$$byteToLong:(B)J
int	24;
int	9;
int	7;
int	6;
Asciz	buffer$1;
Asciz	[B;
Asciz	initialValue;
Asciz	a$1;
Asciz	Lscala/runtime/LongRef;;
Asciz	b$1;
Asciz	c$1;
Asciz	hashSeq;
Asciz	(Lscala/collection/Seq;)I;
Asciz	partitionValuesAndRefs;
Asciz	(Lscala/collection/Seq;)Lscala/Tuple2;;
NameAndType	partitionValuesAndRefs:(Lscala/collection/Seq;)Lscala/Tuple2;
Method	scala/util/JenkinsHash$.partitionValuesAndRefs:(Lscala/collection/Seq;)Lscala/Tuple2;
Asciz	scala/Tuple2;
class	scala/Tuple2
Asciz	_1;
Asciz	()Ljava/lang/Object;;
NameAndType	_1:()Ljava/lang/Object;
Method	scala/Tuple2._1:()Ljava/lang/Object;
Asciz	scala/collection/Seq;
class	scala/collection/Seq
Asciz	_2;
NameAndType	_2:()Ljava/lang/Object;
Method	scala/Tuple2._2:()Ljava/lang/Object;
Asciz	(Ljava/lang/Object;Ljava/lang/Object;)V;
NameAndType	"<init>":(Ljava/lang/Object;Ljava/lang/Object;)V
Method	scala/Tuple2."<init>":(Ljava/lang/Object;Ljava/lang/Object;)V
Asciz	scala/util/JenkinsHash$$anonfun$3;
class	scala/util/JenkinsHash$$anonfun$3
Method	scala/util/JenkinsHash$$anonfun$3."<init>":()V
Asciz	scala/collection/Seq$;
class	scala/collection/Seq$
Asciz	Lscala/collection/Seq$;;
NameAndType	MODULE$:Lscala/collection/Seq$;
Field	scala/collection/Seq$.MODULE$:Lscala/collection/Seq$;
Asciz	scala/collection/generic/TraversableFactory$GenericCanBuildFrom;
class	scala/collection/generic/TraversableFactory$GenericCanBuildFrom
Asciz	(Lscala/collection/generic/TraversableFactory;)V;
NameAndType	"<init>":(Lscala/collection/generic/TraversableFactory;)V
Method	scala/collection/generic/TraversableFactory$GenericCanBuildFrom."<init>":(Lscala/collection/generic/TraversableFactory;)V
Asciz	scala/collection/TraversableLike;
class	scala/collection/TraversableLike
Asciz	map;
Asciz	(Lscala/Function1;Lscala/collection/generic/CanBuildFrom;)Ljava/lang/Object;;
NameAndType	map:(Lscala/Function1;Lscala/collection/generic/CanBuildFrom;)Ljava/lang/Object;
InterfaceMethod	scala/collection/TraversableLike.map:(Lscala/Function1;Lscala/collection/generic/CanBuildFrom;)Ljava/lang/Object;
Asciz	scala/math/Numeric$IntIsIntegral$;
class	scala/math/Numeric$IntIsIntegral$
Asciz	Lscala/math/Numeric$IntIsIntegral$;;
NameAndType	MODULE$:Lscala/math/Numeric$IntIsIntegral$;
Field	scala/math/Numeric$IntIsIntegral$.MODULE$:Lscala/math/Numeric$IntIsIntegral$;
Asciz	sum;
Asciz	(Lscala/math/Numeric;)Ljava/lang/Object;;
NameAndType	sum:(Lscala/math/Numeric;)Ljava/lang/Object;
InterfaceMethod	scala/collection/TraversableLike.sum:(Lscala/math/Numeric;)Ljava/lang/Object;
Asciz	scala/runtime/BoxesRunTime;
class	scala/runtime/BoxesRunTime
Asciz	unboxToInt;
Asciz	(Ljava/lang/Object;)I;
NameAndType	unboxToInt:(Ljava/lang/Object;)I
Method	scala/runtime/BoxesRunTime.unboxToInt:(Ljava/lang/Object;)I
Asciz	hashAnyValSeq;
NameAndType	hashAnyValSeq:(Lscala/collection/Seq;)I
Method	scala/util/JenkinsHash$.hashAnyValSeq:(Lscala/collection/Seq;)I
Asciz	scala/MatchError;
class	scala/MatchError
Asciz	toString;
Asciz	()Ljava/lang/String;;
NameAndType	toString:()Ljava/lang/String;
Method	scala/Tuple2.toString:()Ljava/lang/String;
Asciz	(Ljava/lang/String;)V;
NameAndType	"<init>":(Ljava/lang/String;)V
Method	scala/MatchError."<init>":(Ljava/lang/String;)V
Asciz	xs;
Asciz	Lscala/collection/Seq;;
Asciz	temp36;
Asciz	temp37;
Asciz	refs;
Asciz	values;
Asciz	refsSum;
Asciz	temp35;
Asciz	Lscala/Tuple2;;
Asciz	(Lscala/collection/Seq<Ljava/lang/Object;>;)I;
Asciz	Signature;
Asciz	scala/Predef$;
class	scala/Predef$
Asciz	Lscala/Predef$;;
NameAndType	MODULE$:Lscala/Predef$;
Field	scala/Predef$.MODULE$:Lscala/Predef$;
Asciz	intWrapper;
Asciz	(I)Lscala/runtime/RichInt;;
NameAndType	intWrapper:(I)Lscala/runtime/RichInt;
Method	scala/Predef$.intWrapper:(I)Lscala/runtime/RichInt;
Asciz	scala/runtime/RichInt;
class	scala/runtime/RichInt
Asciz	to;
Asciz	(I)Lscala/collection/immutable/Range$Inclusive;;
NameAndType	to:(I)Lscala/collection/immutable/Range$Inclusive;
Method	scala/runtime/RichInt.to:(I)Lscala/collection/immutable/Range$Inclusive;
Asciz	scala/util/JenkinsHash$$anonfun$fourByteToLong$1;
class	scala/util/JenkinsHash$$anonfun$fourByteToLong$1
Asciz	([BI)V;
NameAndType	"<init>":([BI)V
Method	scala/util/JenkinsHash$$anonfun$fourByteToLong$1."<init>":([BI)V
Asciz	scala/collection/immutable/IndexedSeq$;
class	scala/collection/immutable/IndexedSeq$
Asciz	Lscala/collection/immutable/IndexedSeq$;;
NameAndType	MODULE$:Lscala/collection/immutable/IndexedSeq$;
Field	scala/collection/immutable/IndexedSeq$.MODULE$:Lscala/collection/immutable/IndexedSeq$;
Asciz	canBuildFrom;
Asciz	()Lscala/collection/generic/CanBuildFrom;;
NameAndType	canBuildFrom:()Lscala/collection/generic/CanBuildFrom;
Method	scala/collection/immutable/IndexedSeq$.canBuildFrom:()Lscala/collection/generic/CanBuildFrom;
Asciz	scala/math/Numeric$LongIsIntegral$;
class	scala/math/Numeric$LongIsIntegral$
Asciz	Lscala/math/Numeric$LongIsIntegral$;;
NameAndType	MODULE$:Lscala/math/Numeric$LongIsIntegral$;
Field	scala/math/Numeric$LongIsIntegral$.MODULE$:Lscala/math/Numeric$LongIsIntegral$;
Asciz	unboxToLong;
Asciz	(Ljava/lang/Object;)J;
NameAndType	unboxToLong:(Ljava/lang/Object;)J
Method	scala/runtime/BoxesRunTime.unboxToLong:(Ljava/lang/Object;)J
Asciz	bytes$1;
Asciz	offset$1;
long	4294967295l;
Asciz	x;
Asciz	shift;
Asciz	x1;
Asciz	x2;
int	127;
int	128;
long	128l;
Asciz	b;
Asciz	B;
Asciz	res;
Asciz	scala/util/JenkinsHash$$anonfun$2;
class	scala/util/JenkinsHash$$anonfun$2
Method	scala/util/JenkinsHash$$anonfun$2."<init>":()V
Method	scala/collection/Seq$.canBuildFrom:()Lscala/collection/generic/CanBuildFrom;
Asciz	java/nio/ByteBuffer;
class	java/nio/ByteBuffer
Asciz	wrap;
Asciz	([B)Ljava/nio/ByteBuffer;;
NameAndType	wrap:([B)Ljava/nio/ByteBuffer;
Method	java/nio/ByteBuffer.wrap:([B)Ljava/nio/ByteBuffer;
Asciz	scala/util/JenkinsHash$$anonfun$hashAnyValSeq$1;
class	scala/util/JenkinsHash$$anonfun$hashAnyValSeq$1
Asciz	(Ljava/nio/ByteBuffer;)V;
NameAndType	"<init>":(Ljava/nio/ByteBuffer;)V
Method	scala/util/JenkinsHash$$anonfun$hashAnyValSeq$1."<init>":(Ljava/nio/ByteBuffer;)V
Asciz	scala/collection/IterableLike;
class	scala/collection/IterableLike
Asciz	foreach;
Asciz	(Lscala/Function1;)V;
NameAndType	foreach:(Lscala/Function1;)V
InterfaceMethod	scala/collection/IterableLike.foreach:(Lscala/Function1;)V
Asciz	array;
Asciz	()[B;
NameAndType	array:()[B
Method	java/nio/ByteBuffer.array:()[B
Asciz	hash$default$2;
Asciz	()J;
NameAndType	hash$default$2:()J
Method	scala/util/JenkinsHash$.hash$default$2:()J
NameAndType	hash:([BJ)J
Method	scala/util/JenkinsHash$.hash:([BJ)J
Asciz	arr;
Asciz	bb$1;
Asciz	Ljava/nio/ByteBuffer;;
Asciz	scala/util/JenkinsHash$$anonfun$1;
class	scala/util/JenkinsHash$$anonfun$1
Method	scala/util/JenkinsHash$$anonfun$1."<init>":()V
Asciz	scala/collection/generic/GenericTraversableTemplate;
class	scala/collection/generic/GenericTraversableTemplate
Asciz	scala/Predef$$anon$1;
class	scala/Predef$$anon$1
Method	scala/Predef$$anon$1."<init>":()V
Asciz	unzip;
Asciz	(Lscala/Function1;)Lscala/Tuple2;;
NameAndType	unzip:(Lscala/Function1;)Lscala/Tuple2;
InterfaceMethod	scala/collection/generic/GenericTraversableTemplate.unzip:(Lscala/Function1;)Lscala/Tuple2;
Asciz	scala/util/JenkinsHash$$anonfun$partitionValuesAndRefs$1;
class	scala/util/JenkinsHash$$anonfun$partitionValuesAndRefs$1
Method	scala/util/JenkinsHash$$anonfun$partitionValuesAndRefs$1."<init>":()V
Asciz	flatten;
Asciz	(Lscala/Function1;)Lscala/collection/Traversable;;
NameAndType	flatten:(Lscala/Function1;)Lscala/collection/Traversable;
InterfaceMethod	scala/collection/generic/GenericTraversableTemplate.flatten:(Lscala/Function1;)Lscala/collection/Traversable;
Asciz	scala/util/JenkinsHash$$anonfun$partitionValuesAndRefs$2;
class	scala/util/JenkinsHash$$anonfun$partitionValuesAndRefs$2
Method	scala/util/JenkinsHash$$anonfun$partitionValuesAndRefs$2."<init>":()V
Asciz	temp33;
Asciz	temp34;
Asciz	avs;
Asciz	ars;
Asciz	temp32;
Asciz	(Lscala/collection/Seq<Ljava/lang/Object;>;)Lscala/Tuple2<Lscala/collection/Seq<Ljava/lang/Object;>;Lscala/collection/Seq<Ljava/lang/Object;>;>;;
Asciz	scala$util$JenkinsHash$$classifyAny;
Asciz	(Ljava/lang/Object;)Lscala/Tuple2;;
Asciz	java/lang/Byte;
class	java/lang/Byte
Asciz	unboxToByte;
Asciz	(Ljava/lang/Object;)B;
NameAndType	unboxToByte:(Ljava/lang/Object;)B
Method	scala/runtime/BoxesRunTime.unboxToByte:(Ljava/lang/Object;)B
Asciz	scala/Some;
class	scala/Some
Asciz	boxToByte;
Asciz	(B)Ljava/lang/Byte;;
NameAndType	boxToByte:(B)Ljava/lang/Byte;
Method	scala/runtime/BoxesRunTime.boxToByte:(B)Ljava/lang/Byte;
Asciz	(Ljava/lang/Object;)V;
NameAndType	"<init>":(Ljava/lang/Object;)V
Method	scala/Some."<init>":(Ljava/lang/Object;)V
Asciz	scala/None$;
class	scala/None$
Asciz	Lscala/None$;;
NameAndType	MODULE$:Lscala/None$;
Field	scala/None$.MODULE$:Lscala/None$;
Asciz	java/lang/Short;
class	java/lang/Short
Asciz	unboxToShort;
Asciz	(Ljava/lang/Object;)S;
NameAndType	unboxToShort:(Ljava/lang/Object;)S
Method	scala/runtime/BoxesRunTime.unboxToShort:(Ljava/lang/Object;)S
Asciz	boxToShort;
Asciz	(S)Ljava/lang/Short;;
NameAndType	boxToShort:(S)Ljava/lang/Short;
Method	scala/runtime/BoxesRunTime.boxToShort:(S)Ljava/lang/Short;
Asciz	java/lang/Integer;
class	java/lang/Integer
Asciz	boxToInteger;
Asciz	(I)Ljava/lang/Integer;;
NameAndType	boxToInteger:(I)Ljava/lang/Integer;
Method	scala/runtime/BoxesRunTime.boxToInteger:(I)Ljava/lang/Integer;
Asciz	java/lang/Long;
class	java/lang/Long
Asciz	boxToLong;
Asciz	(J)Ljava/lang/Long;;
NameAndType	boxToLong:(J)Ljava/lang/Long;
Method	scala/runtime/BoxesRunTime.boxToLong:(J)Ljava/lang/Long;
Asciz	java/lang/Float;
class	java/lang/Float
Asciz	unboxToFloat;
Asciz	(Ljava/lang/Object;)F;
NameAndType	unboxToFloat:(Ljava/lang/Object;)F
Method	scala/runtime/BoxesRunTime.unboxToFloat:(Ljava/lang/Object;)F
Asciz	boxToFloat;
Asciz	(F)Ljava/lang/Float;;
NameAndType	boxToFloat:(F)Ljava/lang/Float;
Method	scala/runtime/BoxesRunTime.boxToFloat:(F)Ljava/lang/Float;
Asciz	java/lang/Double;
class	java/lang/Double
Asciz	unboxToDouble;
Asciz	(Ljava/lang/Object;)D;
NameAndType	unboxToDouble:(Ljava/lang/Object;)D
Method	scala/runtime/BoxesRunTime.unboxToDouble:(Ljava/lang/Object;)D
Asciz	boxToDouble;
Asciz	(D)Ljava/lang/Double;;
NameAndType	boxToDouble:(D)Ljava/lang/Double;
Method	scala/runtime/BoxesRunTime.boxToDouble:(D)Ljava/lang/Double;
Asciz	java/lang/Boolean;
class	java/lang/Boolean
Asciz	unboxToBoolean;
Asciz	(Ljava/lang/Object;)Z;
NameAndType	unboxToBoolean:(Ljava/lang/Object;)Z
Method	scala/runtime/BoxesRunTime.unboxToBoolean:(Ljava/lang/Object;)Z
Asciz	boxToBoolean;
Asciz	(Z)Ljava/lang/Boolean;;
NameAndType	boxToBoolean:(Z)Ljava/lang/Boolean;
Method	scala/runtime/BoxesRunTime.boxToBoolean:(Z)Ljava/lang/Boolean;
Asciz	java/lang/Character;
class	java/lang/Character
Asciz	unboxToChar;
Asciz	(Ljava/lang/Object;)C;
NameAndType	unboxToChar:(Ljava/lang/Object;)C
Method	scala/runtime/BoxesRunTime.unboxToChar:(Ljava/lang/Object;)C
Asciz	boxToCharacter;
Asciz	(C)Ljava/lang/Character;;
NameAndType	boxToCharacter:(C)Ljava/lang/Character;
Method	scala/runtime/BoxesRunTime.boxToCharacter:(C)Ljava/lang/Character;
Asciz	scala/runtime/BoxedUnit;
class	scala/runtime/BoxedUnit
Method	java/lang/Object.toString:()Ljava/lang/String;
Asciz	Ljava/lang/Object;;
Asciz	temp22;
Asciz	temp23;
Asciz	S;
Asciz	temp24;
Asciz	temp25;
Asciz	temp26;
Asciz	F;
Asciz	temp27;
Asciz	D;
Asciz	temp28;
Asciz	Z;
Asciz	temp29;
Asciz	C;
Asciz	temp30;
Asciz	Lscala/runtime/BoxedUnit;;
Asciz	scala$util$JenkinsHash$$putAnyVal;
Asciz	(Ljava/nio/ByteBuffer;Ljava/lang/Object;)Ljava/lang/Object;;
Asciz	put;
Asciz	(B)Ljava/nio/ByteBuffer;;
NameAndType	put:(B)Ljava/nio/ByteBuffer;
Method	java/nio/ByteBuffer.put:(B)Ljava/nio/ByteBuffer;
Asciz	putShort;
Asciz	(S)Ljava/nio/ByteBuffer;;
NameAndType	putShort:(S)Ljava/nio/ByteBuffer;
Method	java/nio/ByteBuffer.putShort:(S)Ljava/nio/ByteBuffer;
Asciz	putInt;
Asciz	(I)Ljava/nio/ByteBuffer;;
NameAndType	putInt:(I)Ljava/nio/ByteBuffer;
Method	java/nio/ByteBuffer.putInt:(I)Ljava/nio/ByteBuffer;
Asciz	putLong;
Asciz	(J)Ljava/nio/ByteBuffer;;
NameAndType	putLong:(J)Ljava/nio/ByteBuffer;
Method	java/nio/ByteBuffer.putLong:(J)Ljava/nio/ByteBuffer;
Asciz	putFloat;
Asciz	(F)Ljava/nio/ByteBuffer;;
NameAndType	putFloat:(F)Ljava/nio/ByteBuffer;
Method	java/nio/ByteBuffer.putFloat:(F)Ljava/nio/ByteBuffer;
Asciz	putDouble;
Asciz	(D)Ljava/nio/ByteBuffer;;
NameAndType	putDouble:(D)Ljava/nio/ByteBuffer;
Method	java/nio/ByteBuffer.putDouble:(D)Ljava/nio/ByteBuffer;
Asciz	putChar;
Asciz	(C)Ljava/nio/ByteBuffer;;
NameAndType	putChar:(C)Ljava/nio/ByteBuffer;
Method	java/nio/ByteBuffer.putChar:(C)Ljava/nio/ByteBuffer;
Asciz	UNIT;
NameAndType	UNIT:Lscala/runtime/BoxedUnit;
Field	scala/runtime/BoxedUnit.UNIT:Lscala/runtime/BoxedUnit;
Asciz	bb;
Asciz	v;
Asciz	temp12;
Asciz	temp13;
Asciz	temp14;
Asciz	temp15;
Asciz	temp16;
Asciz	temp17;
Asciz	temp18;
Asciz	temp19;
Asciz	scala$util$JenkinsHash$$bytesProvided;
Asciz	InnerClasses;
Asciz	scala/Predef;
class	scala/Predef
Asciz	$anon$1;
Asciz	scala/collection/immutable/Range$Inclusive;
class	scala/collection/immutable/Range$Inclusive
Asciz	scala/collection/immutable/Range;
class	scala/collection/immutable/Range
Asciz	Inclusive;
Asciz	scala/util/JenkinsHash;
class	scala/util/JenkinsHash
Asciz	$anonfun$3;
Asciz	$anonfun$2;
Asciz	$anonfun$1;
Asciz	$anonfun$hashAnyValSeq$1;
Asciz	$anonfun$fourByteToLong$1;
Asciz	scala/collection/generic/TraversableFactory;
class	scala/collection/generic/TraversableFactory
Asciz	GenericCanBuildFrom;
Asciz	$anonfun$partitionValuesAndRefs$2;
Asciz	$anonfun$partitionValuesAndRefs$1;
Asciz	scala/ScalaObject;
class	scala/ScalaObject

{
public static final scala.util.JenkinsHash$ MODULE$;
  Signature: Lscala/util/JenkinsHash$;

private final long MAX_VALUE;
  Signature: J

public static {};
  Signature: ()V
  Code:
   Stack=1, Locals=0, Args_size=0
	new	class scala/util/JenkinsHash$
	invokespecial	Method "<init>":()V
	return
  Labels:

private scala.util.JenkinsHash$();
  Signature: ()V
  Code:
   Stack=1, Locals=1, Args_size=1
	aload_0
	invokespecial	Method java/lang/Object."<init>":()V
	aload_0
	putstatic	Field MODULE$:Lscala/util/JenkinsHash$;
	return
  Labels:

private final long mixTwelve$1(int, byte[], scala.runtime.LongRef, scala.runtime.LongRef, scala.runtime.LongRef);
  Signature: (I[BLscala/runtime/LongRef;Lscala/runtime/LongRef;Lscala/runtime/LongRef;)J
  Code:
   Stack=8, Locals=6, Args_size=6
	aload_3
	aload_0
	aload_3
	getfield	Field scala/runtime/LongRef.elem:J
	aload_0
	aload_2
	iload_1
	invokespecial	Method fourByteToLong:([BI)J
	invokespecial	Method add:(JJ)J
	putfield	Field scala/runtime/LongRef.elem:J
	aload	4
	aload_0
	aload	4
	getfield	Field scala/runtime/LongRef.elem:J
	aload_0
	aload_2
	iload_1
	iconst_4
	iadd
	invokespecial	Method fourByteToLong:([BI)J
	invokespecial	Method add:(JJ)J
	putfield	Field scala/runtime/LongRef.elem:J
	aload	5
	aload_0
	aload	5
	getfield	Field scala/runtime/LongRef.elem:J
	aload_0
	aload_2
	iload_1
	ldc	int 8
	iadd
	invokespecial	Method fourByteToLong:([BI)J
	invokespecial	Method add:(JJ)J
	putfield	Field scala/runtime/LongRef.elem:J
	aload_0
	aload_3
	aload	4
	aload	5
	invokespecial	Method hashMix$1:(Lscala/runtime/LongRef;Lscala/runtime/LongRef;Lscala/runtime/LongRef;)J
	lreturn
  Labels:
  LocalVariableTable: 
   Start  Length  Slot  Name   Signature
   0      73      0    this       Lscala/util/JenkinsHash$;
   0      73      1    pos       I


private final long hashMix$1(scala.runtime.LongRef, scala.runtime.LongRef, scala.runtime.LongRef);
  Signature: (Lscala/runtime/LongRef;Lscala/runtime/LongRef;Lscala/runtime/LongRef;)J
  Code:
   Stack=8, Locals=4, Args_size=4
	aload_1
	aload_0
	aload_1
	getfield	Field scala/runtime/LongRef.elem:J
	aload_2
	getfield	Field scala/runtime/LongRef.elem:J
	invokespecial	Method subtract:(JJ)J
	putfield	Field scala/runtime/LongRef.elem:J
	aload_1
	aload_0
	aload_1
	getfield	Field scala/runtime/LongRef.elem:J
	aload_3
	getfield	Field scala/runtime/LongRef.elem:J
	invokespecial	Method subtract:(JJ)J
	putfield	Field scala/runtime/LongRef.elem:J
	aload_1
	aload_0
	aload_1
	getfield	Field scala/runtime/LongRef.elem:J
	aload_3
	getfield	Field scala/runtime/LongRef.elem:J
	ldc	int 13
	lshr
	invokespecial	Method xor:(JJ)J
	putfield	Field scala/runtime/LongRef.elem:J
	aload_2
	aload_0
	aload_2
	getfield	Field scala/runtime/LongRef.elem:J
	aload_3
	getfield	Field scala/runtime/LongRef.elem:J
	invokespecial	Method subtract:(JJ)J
	putfield	Field scala/runtime/LongRef.elem:J
	aload_2
	aload_0
	aload_2
	getfield	Field scala/runtime/LongRef.elem:J
	aload_1
	getfield	Field scala/runtime/LongRef.elem:J
	invokespecial	Method subtract:(JJ)J
	putfield	Field scala/runtime/LongRef.elem:J
	aload_2
	aload_0
	aload_2
	getfield	Field scala/runtime/LongRef.elem:J
	aload_0
	aload_1
	getfield	Field scala/runtime/LongRef.elem:J
	ldc	int 8
	invokespecial	Method leftShift:(JI)J
	invokespecial	Method xor:(JJ)J
	putfield	Field scala/runtime/LongRef.elem:J
	aload_3
	aload_0
	aload_3
	getfield	Field scala/runtime/LongRef.elem:J
	aload_1
	getfield	Field scala/runtime/LongRef.elem:J
	invokespecial	Method subtract:(JJ)J
	putfield	Field scala/runtime/LongRef.elem:J
	aload_3
	aload_0
	aload_3
	getfield	Field scala/runtime/LongRef.elem:J
	aload_2
	getfield	Field scala/runtime/LongRef.elem:J
	invokespecial	Method subtract:(JJ)J
	putfield	Field scala/runtime/LongRef.elem:J
	aload_3
	aload_0
	aload_3
	getfield	Field scala/runtime/LongRef.elem:J
	aload_2
	getfield	Field scala/runtime/LongRef.elem:J
	ldc	int 13
	lshr
	invokespecial	Method xor:(JJ)J
	putfield	Field scala/runtime/LongRef.elem:J
	aload_1
	aload_0
	aload_1
	getfield	Field scala/runtime/LongRef.elem:J
	aload_2
	getfield	Field scala/runtime/LongRef.elem:J
	invokespecial	Method subtract:(JJ)J
	putfield	Field scala/runtime/LongRef.elem:J
	aload_1
	aload_0
	aload_1
	getfield	Field scala/runtime/LongRef.elem:J
	aload_3
	getfield	Field scala/runtime/LongRef.elem:J
	invokespecial	Method subtract:(JJ)J
	putfield	Field scala/runtime/LongRef.elem:J
	aload_1
	aload_0
	aload_1
	getfield	Field scala/runtime/LongRef.elem:J
	aload_3
	getfield	Field scala/runtime/LongRef.elem:J
	ldc	int 12
	lshr
	invokespecial	Method xor:(JJ)J
	putfield	Field scala/runtime/LongRef.elem:J
	aload_2
	aload_0
	aload_2
	getfield	Field scala/runtime/LongRef.elem:J
	aload_3
	getfield	Field scala/runtime/LongRef.elem:J
	invokespecial	Method subtract:(JJ)J
	putfield	Field scala/runtime/LongRef.elem:J
	aload_2
	aload_0
	aload_2
	getfield	Field scala/runtime/LongRef.elem:J
	aload_1
	getfield	Field scala/runtime/LongRef.elem:J
	invokespecial	Method subtract:(JJ)J
	putfield	Field scala/runtime/LongRef.elem:J
	aload_2
	aload_0
	aload_2
	getfield	Field scala/runtime/LongRef.elem:J
	aload_0
	aload_1
	getfield	Field scala/runtime/LongRef.elem:J
	ldc	int 16
	invokespecial	Method leftShift:(JI)J
	invokespecial	Method xor:(JJ)J
	putfield	Field scala/runtime/LongRef.elem:J
	aload_3
	aload_0
	aload_3
	getfield	Field scala/runtime/LongRef.elem:J
	aload_1
	getfield	Field scala/runtime/LongRef.elem:J
	invokespecial	Method subtract:(JJ)J
	putfield	Field scala/runtime/LongRef.elem:J
	aload_3
	aload_0
	aload_3
	getfield	Field scala/runtime/LongRef.elem:J
	aload_2
	getfield	Field scala/runtime/LongRef.elem:J
	invokespecial	Method subtract:(JJ)J
	putfield	Field scala/runtime/LongRef.elem:J
	aload_3
	aload_0
	aload_3
	getfield	Field scala/runtime/LongRef.elem:J
	aload_2
	getfield	Field scala/runtime/LongRef.elem:J
	iconst_5
	lshr
	invokespecial	Method xor:(JJ)J
	putfield	Field scala/runtime/LongRef.elem:J
	aload_1
	aload_0
	aload_1
	getfield	Field scala/runtime/LongRef.elem:J
	aload_2
	getfield	Field scala/runtime/LongRef.elem:J
	invokespecial	Method subtract:(JJ)J
	putfield	Field scala/runtime/LongRef.elem:J
	aload_1
	aload_0
	aload_1
	getfield	Field scala/runtime/LongRef.elem:J
	aload_3
	getfield	Field scala/runtime/LongRef.elem:J
	invokespecial	Method subtract:(JJ)J
	putfield	Field scala/runtime/LongRef.elem:J
	aload_1
	aload_0
	aload_1
	getfield	Field scala/runtime/LongRef.elem:J
	aload_3
	getfield	Field scala/runtime/LongRef.elem:J
	iconst_3
	lshr
	invokespecial	Method xor:(JJ)J
	putfield	Field scala/runtime/LongRef.elem:J
	aload_2
	aload_0
	aload_2
	getfield	Field scala/runtime/LongRef.elem:J
	aload_3
	getfield	Field scala/runtime/LongRef.elem:J
	invokespecial	Method subtract:(JJ)J
	putfield	Field scala/runtime/LongRef.elem:J
	aload_2
	aload_0
	aload_2
	getfield	Field scala/runtime/LongRef.elem:J
	aload_1
	getfield	Field scala/runtime/LongRef.elem:J
	invokespecial	Method subtract:(JJ)J
	putfield	Field scala/runtime/LongRef.elem:J
	aload_2
	aload_0
	aload_2
	getfield	Field scala/runtime/LongRef.elem:J
	aload_0
	aload_1
	getfield	Field scala/runtime/LongRef.elem:J
	ldc	int 10
	invokespecial	Method leftShift:(JI)J
	invokespecial	Method xor:(JJ)J
	putfield	Field scala/runtime/LongRef.elem:J
	aload_3
	aload_0
	aload_3
	getfield	Field scala/runtime/LongRef.elem:J
	aload_1
	getfield	Field scala/runtime/LongRef.elem:J
	invokespecial	Method subtract:(JJ)J
	putfield	Field scala/runtime/LongRef.elem:J
	aload_3
	aload_0
	aload_3
	getfield	Field scala/runtime/LongRef.elem:J
	aload_2
	getfield	Field scala/runtime/LongRef.elem:J
	invokespecial	Method subtract:(JJ)J
	putfield	Field scala/runtime/LongRef.elem:J
	aload_3
	aload_0
	aload_3
	getfield	Field scala/runtime/LongRef.elem:J
	aload_2
	getfield	Field scala/runtime/LongRef.elem:J
	ldc	int 15
	lshr
	invokespecial	Method xor:(JJ)J
	putfield	Field scala/runtime/LongRef.elem:J
	aload_3
	getfield	Field scala/runtime/LongRef.elem:J
	lreturn
  Labels:

public long hash(byte[], long);
  Signature: ([BJ)J
  Code:
   Stack=8, Locals=8, Args_size=3
	new	class scala/runtime/LongRef
	dup
	ldc2_w	long 2654435769l
	invokespecial	Method scala/runtime/LongRef."<init>":(J)V
	astore	4
	new	class scala/runtime/LongRef
	dup
	ldc2_w	long 2654435769l
	invokespecial	Method scala/runtime/LongRef."<init>":(J)V
	astore	5
	new	class scala/runtime/LongRef
	dup
	lload_2
	invokespecial	Method scala/runtime/LongRef."<init>":(J)V
	astore	6
	aload_1
	arraylength
	istore	7
l2	iload	7
	ldc	int 12
	if_icmplt	l1 // aload
	iload	7
	ldc	int 12
	isub
	istore	7
	aload_0
	iload	7
	aload_1
	aload	4
	aload	5
	aload	6
	invokespecial	Method mixTwelve$1:(I[BLscala/runtime/LongRef;Lscala/runtime/LongRef;Lscala/runtime/LongRef;)J
	pop2
	goto	l2 // iload
l1	aload	6
	aload	6
	getfield	Field scala/runtime/LongRef.elem:J
	aload_1
	arraylength
	i2l
	ladd
	putfield	Field scala/runtime/LongRef.elem:J
	iload	7
	ldc	int 10
	if_icmple	l3 // iload
	aload	6
	aload_0
	aload	6
	getfield	Field scala/runtime/LongRef.elem:J
	aload_0
	aload_0
	aload_1
	ldc	int 10
	baload
	invokevirtual	Method scala$util$JenkinsHash$$byteToLong:(B)J
	ldc	int 24
	invokespecial	Method leftShift:(JI)J
	invokespecial	Method add:(JJ)J
	putfield	Field scala/runtime/LongRef.elem:J
l3	iload	7
	ldc	int 9
	if_icmple	l4 // iload
	aload	6
	aload_0
	aload	6
	getfield	Field scala/runtime/LongRef.elem:J
	aload_0
	aload_0
	aload_1
	ldc	int 9
	baload
	invokevirtual	Method scala$util$JenkinsHash$$byteToLong:(B)J
	ldc	int 16
	invokespecial	Method leftShift:(JI)J
	invokespecial	Method add:(JJ)J
	putfield	Field scala/runtime/LongRef.elem:J
l4	iload	7
	ldc	int 8
	if_icmple	l5 // iload
	aload	6
	aload_0
	aload	6
	getfield	Field scala/runtime/LongRef.elem:J
	aload_0
	aload_0
	aload_1
	ldc	int 8
	baload
	invokevirtual	Method scala$util$JenkinsHash$$byteToLong:(B)J
	ldc	int 8
	invokespecial	Method leftShift:(JI)J
	invokespecial	Method add:(JJ)J
	putfield	Field scala/runtime/LongRef.elem:J
l5	iload	7
	ldc	int 7
	if_icmple	l6 // iload
	aload	5
	aload_0
	aload	5
	getfield	Field scala/runtime/LongRef.elem:J
	aload_0
	aload_0
	aload_1
	ldc	int 7
	baload
	invokevirtual	Method scala$util$JenkinsHash$$byteToLong:(B)J
	ldc	int 24
	invokespecial	Method leftShift:(JI)J
	invokespecial	Method add:(JJ)J
	putfield	Field scala/runtime/LongRef.elem:J
l6	iload	7
	ldc	int 6
	if_icmple	l7 // iload
	aload	5
	aload_0
	aload	5
	getfield	Field scala/runtime/LongRef.elem:J
	aload_0
	aload_0
	aload_1
	ldc	int 6
	baload
	invokevirtual	Method scala$util$JenkinsHash$$byteToLong:(B)J
	ldc	int 16
	invokespecial	Method leftShift:(JI)J
	invokespecial	Method add:(JJ)J
	putfield	Field scala/runtime/LongRef.elem:J
l7	iload	7
	iconst_5
	if_icmple	l8 // iload
	aload	5
	aload_0
	aload	5
	getfield	Field scala/runtime/LongRef.elem:J
	aload_0
	aload_0
	aload_1
	iconst_5
	baload
	invokevirtual	Method scala$util$JenkinsHash$$byteToLong:(B)J
	ldc	int 8
	invokespecial	Method leftShift:(JI)J
	invokespecial	Method add:(JJ)J
	putfield	Field scala/runtime/LongRef.elem:J
l8	iload	7
	iconst_4
	if_icmple	l9 // iload
	aload	5
	aload_0
	aload	5
	getfield	Field scala/runtime/LongRef.elem:J
	aload_0
	aload_1
	iconst_4
	baload
	invokevirtual	Method scala$util$JenkinsHash$$byteToLong:(B)J
	invokespecial	Method add:(JJ)J
	putfield	Field scala/runtime/LongRef.elem:J
l9	iload	7
	iconst_3
	if_icmple	l10 // iload
	aload	4
	aload_0
	aload	4
	getfield	Field scala/runtime/LongRef.elem:J
	aload_0
	aload_0
	aload_1
	iconst_3
	baload
	invokevirtual	Method scala$util$JenkinsHash$$byteToLong:(B)J
	ldc	int 24
	invokespecial	Method leftShift:(JI)J
	invokespecial	Method add:(JJ)J
	putfield	Field scala/runtime/LongRef.elem:J
l10	iload	7
	iconst_2
	if_icmple	l11 // iload
	aload	4
	aload_0
	aload	4
	getfield	Field scala/runtime/LongRef.elem:J
	aload_0
	aload_0
	aload_1
	iconst_2
	baload
	invokevirtual	Method scala$util$JenkinsHash$$byteToLong:(B)J
	ldc	int 16
	invokespecial	Method leftShift:(JI)J
	invokespecial	Method add:(JJ)J
	putfield	Field scala/runtime/LongRef.elem:J
l11	iload	7
	iconst_1
	if_icmple	l12 // iload
	aload	4
	aload_0
	aload	4
	getfield	Field scala/runtime/LongRef.elem:J
	aload_0
	aload_0
	aload_1
	iconst_1
	baload
	invokevirtual	Method scala$util$JenkinsHash$$byteToLong:(B)J
	ldc	int 8
	invokespecial	Method leftShift:(JI)J
	invokespecial	Method add:(JJ)J
	putfield	Field scala/runtime/LongRef.elem:J
l12	iload	7
	iconst_0
	if_icmple	l13 // aload_0
	aload	4
	aload_0
	aload	4
	getfield	Field scala/runtime/LongRef.elem:J
	aload_0
	aload_1
	iconst_0
	baload
	invokevirtual	Method scala$util$JenkinsHash$$byteToLong:(B)J
	invokespecial	Method add:(JJ)J
	putfield	Field scala/runtime/LongRef.elem:J
l13	aload_0
	aload	4
	aload	5
	aload	6
	invokespecial	Method hashMix$1:(Lscala/runtime/LongRef;Lscala/runtime/LongRef;Lscala/runtime/LongRef;)J
	lreturn
  Labels:
   	l2 = 38 // iload
   	l1 = 69 // aload
   	l3 = 118 // iload
   	l4 = 153 // iload
   	l5 = 188 // iload
   	l6 = 223 // iload
   	l7 = 258 // iload
   	l8 = 291 // iload
   	l9 = 318 // iload
   	l10 = 351 // iload
   	l11 = 384 // iload
   	l12 = 417 // iload
   	l13 = 444 // aload_0
  LocalVariableTable: 
   Start  Length  Slot  Name   Signature
   0      455      0    this       Lscala/util/JenkinsHash$;
   0      455      1    buffer$1       [B
   0      455      2    initialValue       J
   12      442      4    a$1       Lscala/runtime/LongRef;
   24      430      5    b$1       Lscala/runtime/LongRef;
   34      420      6    c$1       Lscala/runtime/LongRef;
   38      416      7    pos       I


public int hashSeq(scala.collection.Seq);
  Signature: (Lscala/collection/Seq;)I
  Code:
   Stack=5, Locals=10, Args_size=2
	aload_0
	aload_1
	invokespecial	Method partitionValuesAndRefs:(Lscala/collection/Seq;)Lscala/Tuple2;
	astore	9
	aload	9
	ifnull	l1 // new
	aload	9
	invokevirtual	Method scala/Tuple2._1:()Ljava/lang/Object;
	checkcast	class scala/collection/Seq
	astore_2
	aload	9
	invokevirtual	Method scala/Tuple2._2:()Ljava/lang/Object;
	checkcast	class scala/collection/Seq
	astore_3
	new	class scala/Tuple2
	dup
	aload_2
	aload_3
	invokespecial	Method scala/Tuple2."<init>":(Ljava/lang/Object;Ljava/lang/Object;)V
	astore	4
	aload	4
	invokevirtual	Method scala/Tuple2._1:()Ljava/lang/Object;
	checkcast	class scala/collection/Seq
	astore	7
	aload	4
	invokevirtual	Method scala/Tuple2._2:()Ljava/lang/Object;
	checkcast	class scala/collection/Seq
	astore	5
	aload	5
	new	class scala/util/JenkinsHash$$anonfun$3
	dup
	invokespecial	Method scala/util/JenkinsHash$$anonfun$3."<init>":()V
	getstatic	Field scala/collection/Seq$.MODULE$:Lscala/collection/Seq$;
	astore	6
	new	class scala/collection/generic/TraversableFactory$GenericCanBuildFrom
	dup
	aload	6
	invokespecial	Method scala/collection/generic/TraversableFactory$GenericCanBuildFrom."<init>":(Lscala/collection/generic/TraversableFactory;)V
	invokeinterface	InterfaceMethod scala/collection/TraversableLike.map:(Lscala/Function1;Lscala/collection/generic/CanBuildFrom;)Ljava/lang/Object;
	checkcast	class scala/collection/TraversableLike
	getstatic	Field scala/math/Numeric$IntIsIntegral$.MODULE$:Lscala/math/Numeric$IntIsIntegral$;
	invokeinterface	InterfaceMethod scala/collection/TraversableLike.sum:(Lscala/math/Numeric;)Ljava/lang/Object;
	invokestatic	Method scala/runtime/BoxesRunTime.unboxToInt:(Ljava/lang/Object;)I
	istore	8
	aload_0
	aload	7
	invokespecial	Method hashAnyValSeq:(Lscala/collection/Seq;)I
	iload	8
	iadd
	ireturn
l1	new	class scala/MatchError
	dup
	aload	9
	invokevirtual	Method scala/Tuple2.toString:()Ljava/lang/String;
	invokespecial	Method scala/MatchError."<init>":(Ljava/lang/String;)V
	athrow
  Labels:
   	l1 = 115 // new
  LocalVariableTable: 
   Start  Length  Slot  Name   Signature
   0      128      0    this       Lscala/util/JenkinsHash$;
   0      128      1    xs       Lscala/collection/Seq;
   21      18      2    temp36       Lscala/collection/Seq;
   30      9      3    temp37       Lscala/collection/Seq;
   61      53      5    refs       Lscala/collection/Seq;
   51      63      7    values       Lscala/collection/Seq;
   105      9      8    refsSum       I
   7      121      9    temp35       Lscala/Tuple2;

  Signature: length = 0x2
   00 FFFFFFA0 

private long fourByteToLong(byte[], int);
  Signature: ([BI)J
  Code:
   Stack=5, Locals=3, Args_size=3
	getstatic	Field scala/Predef$.MODULE$:Lscala/Predef$;
	iconst_0
	invokevirtual	Method scala/Predef$.intWrapper:(I)Lscala/runtime/RichInt;
	iconst_3
	invokevirtual	Method scala/runtime/RichInt.to:(I)Lscala/collection/immutable/Range$Inclusive;
	new	class scala/util/JenkinsHash$$anonfun$fourByteToLong$1
	dup
	aload_1
	iload_2
	invokespecial	Method scala/util/JenkinsHash$$anonfun$fourByteToLong$1."<init>":([BI)V
	getstatic	Field scala/collection/immutable/IndexedSeq$.MODULE$:Lscala/collection/immutable/IndexedSeq$;
	invokevirtual	Method scala/collection/immutable/IndexedSeq$.canBuildFrom:()Lscala/collection/generic/CanBuildFrom;
	invokeinterface	InterfaceMethod scala/collection/TraversableLike.map:(Lscala/Function1;Lscala/collection/generic/CanBuildFrom;)Ljava/lang/Object;
	checkcast	class scala/collection/TraversableLike
	getstatic	Field scala/math/Numeric$LongIsIntegral$.MODULE$:Lscala/math/Numeric$LongIsIntegral$;
	invokeinterface	InterfaceMethod scala/collection/TraversableLike.sum:(Lscala/math/Numeric;)Ljava/lang/Object;
	invokestatic	Method scala/runtime/BoxesRunTime.unboxToLong:(Ljava/lang/Object;)J
	lreturn
  Labels:
  LocalVariableTable: 
   Start  Length  Slot  Name   Signature
   0      46      0    this       Lscala/util/JenkinsHash$;
   0      46      1    bytes$1       [B
   0      46      2    offset$1       I


private long leftShift(long, int);
  Signature: (JI)J
  Code:
   Stack=4, Locals=4, Args_size=3
	lload_1
	iload_3
	lshl
	ldc2_w	long 4294967295l
	land
	lreturn
  Labels:
  LocalVariableTable: 
   Start  Length  Slot  Name   Signature
   0      8      0    this       Lscala/util/JenkinsHash$;
   0      8      1    x       J
   0      8      3    shift       I


private long xor(long, long);
  Signature: (JJ)J
  Code:
   Stack=4, Locals=5, Args_size=3
	lload_1
	lload_3
	lxor
	ldc2_w	long 4294967295l
	land
	lreturn
  Labels:
  LocalVariableTable: 
   Start  Length  Slot  Name   Signature
   0      8      0    this       Lscala/util/JenkinsHash$;
   0      8      1    x1       J
   0      8      3    x2       J


private long subtract(long, long);
  Signature: (JJ)J
  Code:
   Stack=4, Locals=5, Args_size=3
	lload_1
	lload_3
	lsub
	ldc2_w	long 4294967295l
	land
	lreturn
  Labels:
  LocalVariableTable: 
   Start  Length  Slot  Name   Signature
   0      8      0    this       Lscala/util/JenkinsHash$;
   0      8      1    x1       J
   0      8      3    x2       J


private long add(long, long);
  Signature: (JJ)J
  Code:
   Stack=4, Locals=5, Args_size=3
	lload_1
	lload_3
	ladd
	ldc2_w	long 4294967295l
	land
	lreturn
  Labels:
  LocalVariableTable: 
   Start  Length  Slot  Name   Signature
   0      8      0    this       Lscala/util/JenkinsHash$;
   0      8      1    x1       J
   0      8      3    x2       J


public final long scala$util$JenkinsHash$$byteToLong(byte);
  Signature: (B)J
  Code:
   Stack=4, Locals=3, Args_size=2
	iload_1
	ldc	int 127
	iand
	istore_2
	iload_1
	ldc	int 128
	iand
	i2l
	lconst_0
	lcmp
	ifeq	l1 // iload_2
	iload_2
	i2l
	ldc2_w	long 128l
	ladd
	goto	l2 // lreturn
l1	iload_2
	i2l
l2	lreturn
  Labels:
   	l1 = 24 // iload_2
   	l2 = 26 // lreturn
  LocalVariableTable: 
   Start  Length  Slot  Name   Signature
   0      27      0    this       Lscala/util/JenkinsHash$;
   0      27      1    b       B
   5      22      2    res       I


private int hashAnyValSeq(scala.collection.Seq);
  Signature: (Lscala/collection/Seq;)I
  Code:
   Stack=4, Locals=4, Args_size=2
	aload_1
	new	class scala/util/JenkinsHash$$anonfun$2
	dup
	invokespecial	Method scala/util/JenkinsHash$$anonfun$2."<init>":()V
	getstatic	Field scala/collection/Seq$.MODULE$:Lscala/collection/Seq$;
	invokevirtual	Method scala/collection/Seq$.canBuildFrom:()Lscala/collection/generic/CanBuildFrom;
	invokeinterface	InterfaceMethod scala/collection/TraversableLike.map:(Lscala/Function1;Lscala/collection/generic/CanBuildFrom;)Ljava/lang/Object;
	checkcast	class scala/collection/TraversableLike
	getstatic	Field scala/math/Numeric$IntIsIntegral$.MODULE$:Lscala/math/Numeric$IntIsIntegral$;
	invokeinterface	InterfaceMethod scala/collection/TraversableLike.sum:(Lscala/math/Numeric;)Ljava/lang/Object;
	invokestatic	Method scala/runtime/BoxesRunTime.unboxToInt:(Ljava/lang/Object;)I
	newarray byte
	astore_2
	aload_2
	invokestatic	Method java/nio/ByteBuffer.wrap:([B)Ljava/nio/ByteBuffer;
	astore_3
	aload_1
	new	class scala/util/JenkinsHash$$anonfun$hashAnyValSeq$1
	dup
	aload_3
	invokespecial	Method scala/util/JenkinsHash$$anonfun$hashAnyValSeq$1."<init>":(Ljava/nio/ByteBuffer;)V
	invokeinterface	InterfaceMethod scala/collection/IterableLike.foreach:(Lscala/Function1;)V
	aload_0
	aload_3
	invokevirtual	Method java/nio/ByteBuffer.array:()[B
	aload_0
	invokevirtual	Method hash$default$2:()J
	invokevirtual	Method hash:([BJ)J
	l2i
	ireturn
  Labels:
  LocalVariableTable: 
   Start  Length  Slot  Name   Signature
   0      69      0    this       Lscala/util/JenkinsHash$;
   0      69      1    xs       Lscala/collection/Seq;
   36      32      2    arr       [B
   41      27      3    bb$1       Ljava/nio/ByteBuffer;

  Signature: length = 0x2
   00 FFFFFFA0 

private scala.Tuple2 partitionValuesAndRefs(scala.collection.Seq);
  Signature: (Lscala/collection/Seq;)Lscala/Tuple2;
  Code:
   Stack=6, Locals=9, Args_size=2
	aload_1
	new	class scala/util/JenkinsHash$$anonfun$1
	dup
	invokespecial	Method scala/util/JenkinsHash$$anonfun$1."<init>":()V
	getstatic	Field scala/collection/Seq$.MODULE$:Lscala/collection/Seq$;
	astore_2
	new	class scala/collection/generic/TraversableFactory$GenericCanBuildFrom
	dup
	aload_2
	invokespecial	Method scala/collection/generic/TraversableFactory$GenericCanBuildFrom."<init>":(Lscala/collection/generic/TraversableFactory;)V
	invokeinterface	InterfaceMethod scala/collection/TraversableLike.map:(Lscala/Function1;Lscala/collection/generic/CanBuildFrom;)Ljava/lang/Object;
	checkcast	class scala/collection/generic/GenericTraversableTemplate
	new	class scala/Predef$$anon$1
	dup
	invokespecial	Method scala/Predef$$anon$1."<init>":()V
	invokeinterface	InterfaceMethod scala/collection/generic/GenericTraversableTemplate.unzip:(Lscala/Function1;)Lscala/Tuple2;
	astore	8
	aload	8
	ifnull	l1 // new
	aload	8
	invokevirtual	Method scala/Tuple2._1:()Ljava/lang/Object;
	checkcast	class scala/collection/Seq
	astore_3
	aload	8
	invokevirtual	Method scala/Tuple2._2:()Ljava/lang/Object;
	checkcast	class scala/collection/Seq
	astore	4
	new	class scala/Tuple2
	dup
	aload_3
	aload	4
	invokespecial	Method scala/Tuple2."<init>":(Ljava/lang/Object;Ljava/lang/Object;)V
	astore	5
	aload	5
	invokevirtual	Method scala/Tuple2._1:()Ljava/lang/Object;
	checkcast	class scala/collection/Seq
	astore	6
	aload	5
	invokevirtual	Method scala/Tuple2._2:()Ljava/lang/Object;
	checkcast	class scala/collection/Seq
	astore	7
	new	class scala/Tuple2
	dup
	aload	6
	new	class scala/util/JenkinsHash$$anonfun$partitionValuesAndRefs$1
	dup
	invokespecial	Method scala/util/JenkinsHash$$anonfun$partitionValuesAndRefs$1."<init>":()V
	invokeinterface	InterfaceMethod scala/collection/generic/GenericTraversableTemplate.flatten:(Lscala/Function1;)Lscala/collection/Traversable;
	aload	7
	new	class scala/util/JenkinsHash$$anonfun$partitionValuesAndRefs$2
	dup
	invokespecial	Method scala/util/JenkinsHash$$anonfun$partitionValuesAndRefs$2."<init>":()V
	invokeinterface	InterfaceMethod scala/collection/generic/GenericTraversableTemplate.flatten:(Lscala/Function1;)Lscala/collection/Traversable;
	invokespecial	Method scala/Tuple2."<init>":(Ljava/lang/Object;Ljava/lang/Object;)V
	areturn
l1	new	class scala/MatchError
	dup
	aload	8
	invokevirtual	Method scala/Tuple2.toString:()Ljava/lang/String;
	invokespecial	Method scala/MatchError."<init>":(Ljava/lang/String;)V
	athrow
  Labels:
   	l1 = 134 // new
  LocalVariableTable: 
   Start  Length  Slot  Name   Signature
   0      147      0    this       Lscala/util/JenkinsHash$;
   0      147      1    xs       Lscala/collection/Seq;
   56      20      3    temp33       Lscala/collection/Seq;
   66      10      4    temp34       Lscala/collection/Seq;
   88      45      6    avs       Lscala/collection/Seq;
   98      35      7    ars       Lscala/collection/Seq;
   42      105      8    temp32       Lscala/Tuple2;

  Signature: length = 0x2
   01 14 

public final scala.Tuple2 scala$util$JenkinsHash$$classifyAny(java.lang.Object);
  Signature: (Ljava/lang/Object;)Lscala/Tuple2;
  Code:
   Stack=6, Locals=13, Args_size=2
	aload_1
	instanceof	class java/lang/Byte
	ifeq	l1 // aload_1
	aload_1
	invokestatic	Method scala/runtime/BoxesRunTime.unboxToByte:(Ljava/lang/Object;)B
	istore_2
	new	class scala/Tuple2
	dup
	new	class scala/Some
	dup
	iload_2
	invokestatic	Method scala/runtime/BoxesRunTime.boxToByte:(B)Ljava/lang/Byte;
	invokespecial	Method scala/Some."<init>":(Ljava/lang/Object;)V
	getstatic	Field scala/None$.MODULE$:Lscala/None$;
	invokespecial	Method scala/Tuple2."<init>":(Ljava/lang/Object;Ljava/lang/Object;)V
	goto	l2 // areturn
l1	aload_1
	instanceof	class java/lang/Short
	ifeq	l3 // aload_1
	aload_1
	invokestatic	Method scala/runtime/BoxesRunTime.unboxToShort:(Ljava/lang/Object;)S
	istore_3
	new	class scala/Tuple2
	dup
	new	class scala/Some
	dup
	iload_3
	invokestatic	Method scala/runtime/BoxesRunTime.boxToShort:(S)Ljava/lang/Short;
	invokespecial	Method scala/Some."<init>":(Ljava/lang/Object;)V
	getstatic	Field scala/None$.MODULE$:Lscala/None$;
	invokespecial	Method scala/Tuple2."<init>":(Ljava/lang/Object;Ljava/lang/Object;)V
	goto	l2 // areturn
l3	aload_1
	instanceof	class java/lang/Integer
	ifeq	l4 // aload_1
	aload_1
	invokestatic	Method scala/runtime/BoxesRunTime.unboxToInt:(Ljava/lang/Object;)I
	istore	4
	new	class scala/Tuple2
	dup
	new	class scala/Some
	dup
	iload	4
	invokestatic	Method scala/runtime/BoxesRunTime.boxToInteger:(I)Ljava/lang/Integer;
	invokespecial	Method scala/Some."<init>":(Ljava/lang/Object;)V
	getstatic	Field scala/None$.MODULE$:Lscala/None$;
	invokespecial	Method scala/Tuple2."<init>":(Ljava/lang/Object;Ljava/lang/Object;)V
	goto	l2 // areturn
l4	aload_1
	instanceof	class java/lang/Long
	ifeq	l5 // aload_1
	aload_1
	invokestatic	Method scala/runtime/BoxesRunTime.unboxToLong:(Ljava/lang/Object;)J
	lstore	5
	new	class scala/Tuple2
	dup
	new	class scala/Some
	dup
	lload	5
	invokestatic	Method scala/runtime/BoxesRunTime.boxToLong:(J)Ljava/lang/Long;
	invokespecial	Method scala/Some."<init>":(Ljava/lang/Object;)V
	getstatic	Field scala/None$.MODULE$:Lscala/None$;
	invokespecial	Method scala/Tuple2."<init>":(Ljava/lang/Object;Ljava/lang/Object;)V
	goto	l2 // areturn
l5	aload_1
	instanceof	class java/lang/Float
	ifeq	l6 // aload_1
	aload_1
	invokestatic	Method scala/runtime/BoxesRunTime.unboxToFloat:(Ljava/lang/Object;)F
	fstore	7
	new	class scala/Tuple2
	dup
	new	class scala/Some
	dup
	fload	7
	invokestatic	Method scala/runtime/BoxesRunTime.boxToFloat:(F)Ljava/lang/Float;
	invokespecial	Method scala/Some."<init>":(Ljava/lang/Object;)V
	getstatic	Field scala/None$.MODULE$:Lscala/None$;
	invokespecial	Method scala/Tuple2."<init>":(Ljava/lang/Object;Ljava/lang/Object;)V
	goto	l2 // areturn
l6	aload_1
	instanceof	class java/lang/Double
	ifeq	l7 // aload_1
	aload_1
	invokestatic	Method scala/runtime/BoxesRunTime.unboxToDouble:(Ljava/lang/Object;)D
	dstore	8
	new	class scala/Tuple2
	dup
	new	class scala/Some
	dup
	dload	8
	invokestatic	Method scala/runtime/BoxesRunTime.boxToDouble:(D)Ljava/lang/Double;
	invokespecial	Method scala/Some."<init>":(Ljava/lang/Object;)V
	getstatic	Field scala/None$.MODULE$:Lscala/None$;
	invokespecial	Method scala/Tuple2."<init>":(Ljava/lang/Object;Ljava/lang/Object;)V
	goto	l2 // areturn
l7	aload_1
	instanceof	class java/lang/Boolean
	ifeq	l8 // aload_1
	aload_1
	invokestatic	Method scala/runtime/BoxesRunTime.unboxToBoolean:(Ljava/lang/Object;)Z
	istore	10
	new	class scala/Tuple2
	dup
	new	class scala/Some
	dup
	iload	10
	invokestatic	Method scala/runtime/BoxesRunTime.boxToBoolean:(Z)Ljava/lang/Boolean;
	invokespecial	Method scala/Some."<init>":(Ljava/lang/Object;)V
	getstatic	Field scala/None$.MODULE$:Lscala/None$;
	invokespecial	Method scala/Tuple2."<init>":(Ljava/lang/Object;Ljava/lang/Object;)V
	goto	l2 // areturn
l8	aload_1
	instanceof	class java/lang/Character
	ifeq	l9 // aload_1
	aload_1
	invokestatic	Method scala/runtime/BoxesRunTime.unboxToChar:(Ljava/lang/Object;)C
	istore	11
	new	class scala/Tuple2
	dup
	new	class scala/Some
	dup
	iload	11
	invokestatic	Method scala/runtime/BoxesRunTime.boxToCharacter:(C)Ljava/lang/Character;
	invokespecial	Method scala/Some."<init>":(Ljava/lang/Object;)V
	getstatic	Field scala/None$.MODULE$:Lscala/None$;
	invokespecial	Method scala/Tuple2."<init>":(Ljava/lang/Object;Ljava/lang/Object;)V
	goto	l2 // areturn
l9	aload_1
	instanceof	class scala/runtime/BoxedUnit
	ifeq	l10 // aload_1
	aload_1
	checkcast	class scala/runtime/BoxedUnit
	astore	12
	new	class scala/Tuple2
	dup
	new	class scala/Some
	dup
	aload	12
	invokespecial	Method scala/Some."<init>":(Ljava/lang/Object;)V
	getstatic	Field scala/None$.MODULE$:Lscala/None$;
	invokespecial	Method scala/Tuple2."<init>":(Ljava/lang/Object;Ljava/lang/Object;)V
	goto	l2 // areturn
l10	aload_1
	instanceof	class java/lang/Object
	ifeq	l11 // new
	new	class scala/Tuple2
	dup
	getstatic	Field scala/None$.MODULE$:Lscala/None$;
	new	class scala/Some
	dup
	aload_1
	invokespecial	Method scala/Some."<init>":(Ljava/lang/Object;)V
	invokespecial	Method scala/Tuple2."<init>":(Ljava/lang/Object;Ljava/lang/Object;)V
l2	areturn
l11	new	class scala/MatchError
	dup
	aload_1
	invokevirtual	Method java/lang/Object.toString:()Ljava/lang/String;
	invokespecial	Method scala/MatchError."<init>":(Ljava/lang/String;)V
	athrow
  Labels:
   	l1 = 36 // aload_1
   	l3 = 72 // aload_1
   	l4 = 110 // aload_1
   	l5 = 148 // aload_1
   	l6 = 186 // aload_1
   	l7 = 224 // aload_1
   	l8 = 262 // aload_1
   	l9 = 300 // aload_1
   	l10 = 335 // aload_1
   	l2 = 360 // areturn
   	l11 = 361 // new
  LocalVariableTable: 
   Start  Length  Slot  Name   Signature
   0      373      0    this       Lscala/util/JenkinsHash$;
   0      373      1    x       Ljava/lang/Object;
   12      21      2    temp22       B
   48      21      3    temp23       S
   85      22      4    temp24       I
   123      22      5    temp25       J
   161      22      7    temp26       F
   199      22      8    temp27       D
   237      22      10    temp28       Z
   275      22      11    temp29       C
   313      19      12    temp30       Lscala/runtime/BoxedUnit;


public final java.lang.Object scala$util$JenkinsHash$$putAnyVal(java.nio.ByteBuffer, java.lang.Object);
  Signature: (Ljava/nio/ByteBuffer;Ljava/lang/Object;)Ljava/lang/Object;
  Code:
   Stack=3, Locals=13, Args_size=3
	aload_2
	instanceof	class java/lang/Byte
	ifeq	l1 // aload_2
	aload_2
	invokestatic	Method scala/runtime/BoxesRunTime.unboxToByte:(Ljava/lang/Object;)B
	istore_3
	aload_1
	iload_3
	invokevirtual	Method java/nio/ByteBuffer.put:(B)Ljava/nio/ByteBuffer;
	goto	l2 // areturn
l1	aload_2
	instanceof	class java/lang/Short
	ifeq	l3 // aload_2
	aload_2
	invokestatic	Method scala/runtime/BoxesRunTime.unboxToShort:(Ljava/lang/Object;)S
	istore	4
	aload_1
	iload	4
	invokevirtual	Method java/nio/ByteBuffer.putShort:(S)Ljava/nio/ByteBuffer;
	goto	l2 // areturn
l3	aload_2
	instanceof	class java/lang/Integer
	ifeq	l4 // aload_2
	aload_2
	invokestatic	Method scala/runtime/BoxesRunTime.unboxToInt:(Ljava/lang/Object;)I
	istore	5
	aload_1
	iload	5
	invokevirtual	Method java/nio/ByteBuffer.putInt:(I)Ljava/nio/ByteBuffer;
	goto	l2 // areturn
l4	aload_2
	instanceof	class java/lang/Long
	ifeq	l5 // aload_2
	aload_2
	invokestatic	Method scala/runtime/BoxesRunTime.unboxToLong:(Ljava/lang/Object;)J
	lstore	6
	aload_1
	lload	6
	invokevirtual	Method java/nio/ByteBuffer.putLong:(J)Ljava/nio/ByteBuffer;
	goto	l2 // areturn
l5	aload_2
	instanceof	class java/lang/Float
	ifeq	l6 // aload_2
	aload_2
	invokestatic	Method scala/runtime/BoxesRunTime.unboxToFloat:(Ljava/lang/Object;)F
	fstore	8
	aload_1
	fload	8
	invokevirtual	Method java/nio/ByteBuffer.putFloat:(F)Ljava/nio/ByteBuffer;
	goto	l2 // areturn
l6	aload_2
	instanceof	class java/lang/Double
	ifeq	l7 // aload_2
	aload_2
	invokestatic	Method scala/runtime/BoxesRunTime.unboxToDouble:(Ljava/lang/Object;)D
	dstore	9
	aload_1
	dload	9
	invokevirtual	Method java/nio/ByteBuffer.putDouble:(D)Ljava/nio/ByteBuffer;
	goto	l2 // areturn
l7	aload_2
	instanceof	class java/lang/Boolean
	ifeq	l8 // aload_2
	aload_2
	invokestatic	Method scala/runtime/BoxesRunTime.unboxToBoolean:(Ljava/lang/Object;)Z
	istore	11
	aload_1
	iload	11
	ifeq	l9 // bipush
	bipush	127
	goto	l10 // invokevirtual
l9	bipush	-128
l10	invokevirtual	Method java/nio/ByteBuffer.put:(B)Ljava/nio/ByteBuffer;
	goto	l2 // areturn
l8	aload_2
	instanceof	class java/lang/Character
	ifeq	l11 // aload_2
	aload_2
	invokestatic	Method scala/runtime/BoxesRunTime.unboxToChar:(Ljava/lang/Object;)C
	istore	12
	aload_1
	iload	12
	invokevirtual	Method java/nio/ByteBuffer.putChar:(C)Ljava/nio/ByteBuffer;
	goto	l2 // areturn
l11	aload_2
	instanceof	class scala/runtime/BoxedUnit
	ifeq	l12 // new
	getstatic	Field scala/runtime/BoxedUnit.UNIT:Lscala/runtime/BoxedUnit;
l2	areturn
l12	new	class scala/MatchError
	dup
	aload_2
	invokevirtual	Method java/lang/Object.toString:()Ljava/lang/String;
	invokespecial	Method scala/MatchError."<init>":(Ljava/lang/String;)V
	athrow
  Labels:
   	l1 = 20 // aload_2
   	l3 = 42 // aload_2
   	l4 = 64 // aload_2
   	l5 = 86 // aload_2
   	l6 = 108 // aload_2
   	l7 = 130 // aload_2
   	l9 = 154 // bipush
   	l10 = 156 // invokevirtual
   	l8 = 162 // aload_2
   	l11 = 184 // aload_2
   	l2 = 194 // areturn
   	l12 = 195 // new
  LocalVariableTable: 
   Start  Length  Slot  Name   Signature
   0      207      0    this       Lscala/util/JenkinsHash$;
   0      207      1    bb       Ljava/nio/ByteBuffer;
   0      207      2    v       Ljava/lang/Object;
   12      5      3    temp12       B
   33      6      4    temp13       S
   55      6      5    temp14       I
   77      6      6    temp15       J
   99      6      8    temp16       F
   121      6      9    temp17       D
   143      16      11    temp18       Z
   175      6      12    temp19       C


public final int scala$util$JenkinsHash$$bytesProvided(java.lang.Object);
  Signature: (Ljava/lang/Object;)I
  Code:
   Stack=1, Locals=2, Args_size=2
	aload_1
	instanceof	class java/lang/Byte
	ifeq	l1 // aload_1
	iconst_1
	goto	l2 // ireturn
l1	aload_1
	instanceof	class java/lang/Short
	ifeq	l3 // aload_1
	iconst_2
	goto	l2 // ireturn
l3	aload_1
	instanceof	class java/lang/Integer
	ifeq	l4 // aload_1
	iconst_4
	goto	l2 // ireturn
l4	aload_1
	instanceof	class java/lang/Long
	ifeq	l5 // aload_1
	ldc	int 8
	goto	l2 // ireturn
l5	aload_1
	instanceof	class java/lang/Float
	ifeq	l6 // aload_1
	iconst_4
	goto	l2 // ireturn
l6	aload_1
	instanceof	class java/lang/Double
	ifeq	l7 // aload_1
	ldc	int 8
	goto	l2 // ireturn
l7	aload_1
	instanceof	class java/lang/Boolean
	ifeq	l8 // aload_1
	iconst_1
	goto	l2 // ireturn
l8	aload_1
	instanceof	class java/lang/Character
	ifeq	l9 // aload_1
	iconst_2
	goto	l2 // ireturn
l9	aload_1
	instanceof	class scala/runtime/BoxedUnit
	ifeq	l10 // iconst_4
	iconst_0
	goto	l2 // ireturn
l10	iconst_4
l2	ireturn
  Labels:
   	l1 = 11 // aload_1
   	l3 = 22 // aload_1
   	l4 = 33 // aload_1
   	l5 = 45 // aload_1
   	l6 = 56 // aload_1
   	l7 = 68 // aload_1
   	l8 = 79 // aload_1
   	l9 = 90 // aload_1
   	l10 = 101 // iconst_4
   	l2 = 102 // ireturn
  LocalVariableTable: 
   Start  Length  Slot  Name   Signature
   0      103      0    this       Lscala/util/JenkinsHash$;
   0      103      1    v       Ljava/lang/Object;


public final long MAX_VALUE();
  Signature: ()J
  Code:
   Stack=2, Locals=1, Args_size=1
	ldc2_w	long 4294967295l
	lreturn
  Labels:

public long hash$default$2();
  Signature: ()J
  Code:
   Stack=2, Locals=1, Args_size=1
	lconst_0
	lreturn
  Labels:

}

