Compiled from "Marshal.scala"
public final class scala.util.Marshal$ extends java.lang.Object implements scala.ScalaObject
  SourceFile: "Marshal.scala"
  Scala: length = 0x
   
  minor version: 0
  major version: 49
  Constant pool:
const #1 = Asciz	SourceFile;
const #2 = Asciz	Marshal.scala;
const #3 = Asciz	Scala;
const #4 = Asciz	MODULE$;
const #5 = Asciz	Lscala/util/Marshal$;;
const #6 = Asciz	<clinit>;
const #7 = Asciz	()V;
const #8 = Asciz	Code;
const #9 = Asciz	scala/util/Marshal$;
const #10 = class	#9;	//  scala/util/Marshal$
const #11 = Asciz	<init>;
const #12 = NameAndType	#11:#7;//  "<init>":()V
const #13 = Method	#10.#12;	//  scala/util/Marshal$."<init>":()V
const #14 = Asciz	LineNumberTable;
const #15 = Asciz	java/lang/Object;
const #16 = class	#15;	//  java/lang/Object
const #17 = Method	#16.#12;	//  java/lang/Object."<init>":()V
const #18 = NameAndType	#4:#5;//  MODULE$:Lscala/util/Marshal$;
const #19 = Field	#10.#18;	//  scala/util/Marshal$.MODULE$:Lscala/util/Marshal$;
const #20 = Asciz	load;
const #21 = Asciz	([BLscala/reflect/Manifest;)Ljava/lang/Object;;
const #22 = Asciz	java/io/ObjectInputStream;
const #23 = class	#22;	//  java/io/ObjectInputStream
const #24 = Asciz	java/io/ByteArrayInputStream;
const #25 = class	#24;	//  java/io/ByteArrayInputStream
const #26 = Asciz	([B)V;
const #27 = NameAndType	#11:#26;//  "<init>":([B)V
const #28 = Method	#25.#27;	//  java/io/ByteArrayInputStream."<init>":([B)V
const #29 = Asciz	(Ljava/io/InputStream;)V;
const #30 = NameAndType	#11:#29;//  "<init>":(Ljava/io/InputStream;)V
const #31 = Method	#23.#30;	//  java/io/ObjectInputStream."<init>":(Ljava/io/InputStream;)V
const #32 = Asciz	readObject;
const #33 = Asciz	()Ljava/lang/Object;;
const #34 = NameAndType	#32:#33;//  readObject:()Ljava/lang/Object;
const #35 = Method	#23.#34;	//  java/io/ObjectInputStream.readObject:()Ljava/lang/Object;
const #36 = Asciz	scala/reflect/Manifest;
const #37 = class	#36;	//  scala/reflect/Manifest
const #38 = Asciz	$less$colon$less;
const #39 = Asciz	(Lscala/reflect/Manifest;)Z;
const #40 = NameAndType	#38:#39;//  $less$colon$less:(Lscala/reflect/Manifest;)Z
const #41 = InterfaceMethod	#37.#40;	//  scala/reflect/Manifest.$less$colon$less:(Lscala/reflect/Manifest;)Z
const #42 = Asciz	close;
const #43 = NameAndType	#42:#7;//  close:()V
const #44 = Method	#23.#43;	//  java/io/ObjectInputStream.close:()V
const #45 = Asciz	java/lang/ClassCastException;
const #46 = class	#45;	//  java/lang/ClassCastException
const #47 = Asciz	scala/collection/mutable/StringBuilder;
const #48 = class	#47;	//  scala/collection/mutable/StringBuilder
const #49 = Method	#48.#12;	//  scala/collection/mutable/StringBuilder."<init>":()V
const #50 = Asciz	type mismatch;\n found   : ;
const #51 = String	#50;	//  type mismatch;\n found   : 
const #52 = Asciz	append;
const #53 = Asciz	(Ljava/lang/Object;)Lscala/collection/mutable/StringBuilder;;
const #54 = NameAndType	#52:#53;//  append:(Ljava/lang/Object;)Lscala/collection/mutable/StringBuilder;
const #55 = Method	#48.#54;	//  scala/collection/mutable/StringBuilder.append:(Ljava/lang/Object;)Lscala/collection/mutable/StringBuilder;
const #56 = Asciz	\n required: ;
const #57 = String	#56;	//  \n required: 
const #58 = Asciz	toString;
const #59 = Asciz	()Ljava/lang/String;;
const #60 = NameAndType	#58:#59;//  toString:()Ljava/lang/String;
const #61 = Method	#48.#60;	//  scala/collection/mutable/StringBuilder.toString:()Ljava/lang/String;
const #62 = Asciz	(Ljava/lang/String;)V;
const #63 = NameAndType	#11:#62;//  "<init>":(Ljava/lang/String;)V
const #64 = Method	#46.#63;	//  java/lang/ClassCastException."<init>":(Ljava/lang/String;)V
const #65 = Asciz	this;
const #66 = Asciz	buffer;
const #67 = Asciz	[B;
const #68 = Asciz	expected;
const #69 = Asciz	Lscala/reflect/Manifest;;
const #70 = Asciz	in;
const #71 = Asciz	Ljava/io/ObjectInputStream;;
const #72 = Asciz	found;
const #73 = Asciz	o;
const #74 = Asciz	Ljava/lang/Object;;
const #75 = Asciz	LocalVariableTable;
const #76 = Asciz	<A:Ljava/lang/Object;>([BLscala/reflect/Manifest<TA;>;)TA;;
const #77 = Asciz	Signature;
const #78 = Asciz	java/io/IOException;
const #79 = class	#78;	//  java/io/IOException
const #80 = Asciz	java/lang/ClassNotFoundException;
const #81 = class	#80;	//  java/lang/ClassNotFoundException
const #82 = Asciz	Exceptions;
const #83 = Asciz	dump;
const #84 = Asciz	(Ljava/lang/Object;Lscala/reflect/Manifest;)[B;
const #85 = Asciz	java/io/ByteArrayOutputStream;
const #86 = class	#85;	//  java/io/ByteArrayOutputStream
const #87 = int	512;
const #88 = Asciz	(I)V;
const #89 = NameAndType	#11:#88;//  "<init>":(I)V
const #90 = Method	#86.#89;	//  java/io/ByteArrayOutputStream."<init>":(I)V
const #91 = Asciz	java/io/ObjectOutputStream;
const #92 = class	#91;	//  java/io/ObjectOutputStream
const #93 = Asciz	(Ljava/io/OutputStream;)V;
const #94 = NameAndType	#11:#93;//  "<init>":(Ljava/io/OutputStream;)V
const #95 = Method	#92.#94;	//  java/io/ObjectOutputStream."<init>":(Ljava/io/OutputStream;)V
const #96 = Asciz	writeObject;
const #97 = Asciz	(Ljava/lang/Object;)V;
const #98 = NameAndType	#96:#97;//  writeObject:(Ljava/lang/Object;)V
const #99 = Method	#92.#98;	//  java/io/ObjectOutputStream.writeObject:(Ljava/lang/Object;)V
const #100 = Method	#92.#43;	//  java/io/ObjectOutputStream.close:()V
const #101 = Asciz	toByteArray;
const #102 = Asciz	()[B;
const #103 = NameAndType	#101:#102;//  toByteArray:()[B
const #104 = Method	#86.#103;	//  java/io/ByteArrayOutputStream.toByteArray:()[B
const #105 = Asciz	m;
const #106 = Asciz	ba;
const #107 = Asciz	Ljava/io/ByteArrayOutputStream;;
const #108 = Asciz	out;
const #109 = Asciz	Ljava/io/ObjectOutputStream;;
const #110 = Asciz	<A:Ljava/lang/Object;>(TA;Lscala/reflect/Manifest<TA;>;)[B;
const #111 = Asciz	scala/ScalaObject;
const #112 = class	#111;	//  scala/ScalaObject

{
public static final scala.util.Marshal$ MODULE$;

public static {};
  Code:
   Stack=1, Locals=0, Args_size=0
   0:	new	#10; //class scala/util/Marshal$
   3:	invokespecial	#13; //Method "<init>":()V
   6:	return

public java.lang.Object load(byte[], scala.reflect.Manifest)   throws java.io.IOException, java.lang.ClassCastException, java.lang.ClassNotFoundException;
  Code:
   Stack=5, Locals=6, Args_size=3
   0:	new	#23; //class java/io/ObjectInputStream
   3:	dup
   4:	new	#25; //class java/io/ByteArrayInputStream
   7:	dup
   8:	aload_1
   9:	invokespecial	#28; //Method java/io/ByteArrayInputStream."<init>":([B)V
   12:	invokespecial	#31; //Method java/io/ObjectInputStream."<init>":(Ljava/io/InputStream;)V
   15:	astore_3
   16:	aload_3
   17:	invokevirtual	#35; //Method java/io/ObjectInputStream.readObject:()Ljava/lang/Object;
   20:	checkcast	#37; //class scala/reflect/Manifest
   23:	astore	4
   25:	aload	4
   27:	aload_2
   28:	invokeinterface	#41,  2; //InterfaceMethod scala/reflect/Manifest.$less$colon$less:(Lscala/reflect/Manifest;)Z
   33:	ifeq	49
   36:	aload_3
   37:	invokevirtual	#35; //Method java/io/ObjectInputStream.readObject:()Ljava/lang/Object;
   40:	astore	5
   42:	aload_3
   43:	invokevirtual	#44; //Method java/io/ObjectInputStream.close:()V
   46:	aload	5
   48:	areturn
   49:	aload_3
   50:	invokevirtual	#44; //Method java/io/ObjectInputStream.close:()V
   53:	new	#46; //class java/lang/ClassCastException
   56:	dup
   57:	new	#48; //class scala/collection/mutable/StringBuilder
   60:	dup
   61:	invokespecial	#49; //Method scala/collection/mutable/StringBuilder."<init>":()V
   64:	ldc	#51; //String type mismatch;\n found   : 
   66:	invokevirtual	#55; //Method scala/collection/mutable/StringBuilder.append:(Ljava/lang/Object;)Lscala/collection/mutable/StringBuilder;
   69:	aload	4
   71:	invokevirtual	#55; //Method scala/collection/mutable/StringBuilder.append:(Ljava/lang/Object;)Lscala/collection/mutable/StringBuilder;
   74:	ldc	#57; //String \n required: 
   76:	invokevirtual	#55; //Method scala/collection/mutable/StringBuilder.append:(Ljava/lang/Object;)Lscala/collection/mutable/StringBuilder;
   79:	aload_2
   80:	invokevirtual	#55; //Method scala/collection/mutable/StringBuilder.append:(Ljava/lang/Object;)Lscala/collection/mutable/StringBuilder;
   83:	invokevirtual	#61; //Method scala/collection/mutable/StringBuilder.toString:()Ljava/lang/String;
   86:	invokespecial	#64; //Method java/lang/ClassCastException."<init>":(Ljava/lang/String;)V
   89:	athrow
  LineNumberTable: 
   line 37: 0
   line 38: 16
   line 39: 25
   line 40: 36
   line 41: 42
   line 42: 46
   line 36: 48
   line 44: 49
   line 45: 53
   line 47: 57
   line 45: 64
   line 46: 69
   line 47: 74
   line 45: 86

  LocalVariableTable: 
   Start  Length  Slot  Name   Signature
   0      90      0    this       Lscala/util/Marshal$;
   0      90      1    buffer       [B
   0      90      2    expected       Lscala/reflect/Manifest;
   16      74      3    in       Ljava/io/ObjectInputStream;
   25      65      4    found       Lscala/reflect/Manifest;
   42      6      5    o       Ljava/lang/Object;

  Signature: length = 0x2
   00 4C 
  Exceptions: 
   throws java.io.IOException, java.lang.ClassCastException, java.lang.ClassNotFoundException
public byte[] dump(java.lang.Object, scala.reflect.Manifest);
  Code:
   Stack=3, Locals=5, Args_size=3
   0:	new	#86; //class java/io/ByteArrayOutputStream
   3:	dup
   4:	ldc	#87; //int 512
   6:	invokespecial	#90; //Method java/io/ByteArrayOutputStream."<init>":(I)V
   9:	astore_3
   10:	new	#92; //class java/io/ObjectOutputStream
   13:	dup
   14:	aload_3
   15:	invokespecial	#95; //Method java/io/ObjectOutputStream."<init>":(Ljava/io/OutputStream;)V
   18:	astore	4
   20:	aload	4
   22:	aload_2
   23:	invokevirtual	#99; //Method java/io/ObjectOutputStream.writeObject:(Ljava/lang/Object;)V
   26:	aload	4
   28:	aload_1
   29:	invokevirtual	#99; //Method java/io/ObjectOutputStream.writeObject:(Ljava/lang/Object;)V
   32:	aload	4
   34:	invokevirtual	#100; //Method java/io/ObjectOutputStream.close:()V
   37:	aload_3
   38:	invokevirtual	#104; //Method java/io/ByteArrayOutputStream.toByteArray:()[B
   41:	areturn
  LineNumberTable: 
   line 25: 0
   line 26: 10
   line 27: 20
   line 28: 26
   line 29: 32
   line 30: 37

  LocalVariableTable: 
   Start  Length  Slot  Name   Signature
   0      42      0    this       Lscala/util/Marshal$;
   0      42      1    o       Ljava/lang/Object;
   0      42      2    m       Lscala/reflect/Manifest;
   10      31      3    ba       Ljava/io/ByteArrayOutputStream;
   20      21      4    out       Ljava/io/ObjectOutputStream;

  Signature: length = 0x2
   00 6E 

}

