Compiled from "Marshal.scala"
public final class scala.util.Marshal$ extends java.lang.Object implements scala.ScalaObject
  SourceFile: "Marshal.scala"
  Scala: length = 0x
   
  minor version: 0
  major version: 49
  Constant pool:
Asciz	SourceFile;
Asciz	Marshal.scala;
Asciz	Scala;
Asciz	MODULE$;
Asciz	Lscala/util/Marshal$;;
Asciz	<clinit>;
Asciz	()V;
Asciz	Code;
Asciz	scala/util/Marshal$;
class	scala/util/Marshal$
Asciz	<init>;
NameAndType	"<init>":()V
Method	scala/util/Marshal$."<init>":()V
Asciz	LineNumberTable;
Asciz	java/lang/Object;
class	java/lang/Object
Method	java/lang/Object."<init>":()V
NameAndType	MODULE$:Lscala/util/Marshal$;
Field	scala/util/Marshal$.MODULE$:Lscala/util/Marshal$;
Asciz	load;
Asciz	([BLscala/reflect/ClassManifest;)Ljava/lang/Object;;
Asciz	java/io/ObjectInputStream;
class	java/io/ObjectInputStream
Asciz	java/io/ByteArrayInputStream;
class	java/io/ByteArrayInputStream
Asciz	([B)V;
NameAndType	"<init>":([B)V
Method	java/io/ByteArrayInputStream."<init>":([B)V
Asciz	(Ljava/io/InputStream;)V;
NameAndType	"<init>":(Ljava/io/InputStream;)V
Method	java/io/ObjectInputStream."<init>":(Ljava/io/InputStream;)V
Asciz	readObject;
Asciz	()Ljava/lang/Object;;
NameAndType	readObject:()Ljava/lang/Object;
Method	java/io/ObjectInputStream.readObject:()Ljava/lang/Object;
Asciz	scala/reflect/ClassManifest;
class	scala/reflect/ClassManifest
Asciz	$less$colon$less;
Asciz	(Lscala/reflect/ClassManifest;)Z;
NameAndType	$less$colon$less:(Lscala/reflect/ClassManifest;)Z
InterfaceMethod	scala/reflect/ClassManifest.$less$colon$less:(Lscala/reflect/ClassManifest;)Z
Asciz	close;
NameAndType	close:()V
Method	java/io/ObjectInputStream.close:()V
Asciz	java/lang/ClassCastException;
class	java/lang/ClassCastException
Asciz	scala/collection/mutable/StringBuilder;
class	scala/collection/mutable/StringBuilder
Method	scala/collection/mutable/StringBuilder."<init>":()V
Asciz	type mismatch;\n found   : ;
String	type mismatch;\n found   : 
Asciz	append;
Asciz	(Ljava/lang/Object;)Lscala/collection/mutable/StringBuilder;;
NameAndType	append:(Ljava/lang/Object;)Lscala/collection/mutable/StringBuilder;
Method	scala/collection/mutable/StringBuilder.append:(Ljava/lang/Object;)Lscala/collection/mutable/StringBuilder;
Asciz	\n required: ;
String	\n required: 
Asciz	toString;
Asciz	()Ljava/lang/String;;
NameAndType	toString:()Ljava/lang/String;
Method	scala/collection/mutable/StringBuilder.toString:()Ljava/lang/String;
Asciz	(Ljava/lang/String;)V;
NameAndType	"<init>":(Ljava/lang/String;)V
Method	java/lang/ClassCastException."<init>":(Ljava/lang/String;)V
Asciz	this;
Asciz	buffer;
Asciz	[B;
Asciz	expected;
Asciz	Lscala/reflect/ClassManifest;;
Asciz	in;
Asciz	Ljava/io/ObjectInputStream;;
Asciz	found;
Asciz	o;
Asciz	Ljava/lang/Object;;
Asciz	LocalVariableTable;
Asciz	<A:Ljava/lang/Object;>([BLscala/reflect/ClassManifest<TA;>;)TA;;
Asciz	Signature;
Asciz	java/io/IOException;
class	java/io/IOException
Asciz	java/lang/ClassNotFoundException;
class	java/lang/ClassNotFoundException
Asciz	Exceptions;
Asciz	dump;
Asciz	(Ljava/lang/Object;Lscala/reflect/ClassManifest;)[B;
Asciz	java/io/ByteArrayOutputStream;
class	java/io/ByteArrayOutputStream
int	512;
Asciz	(I)V;
NameAndType	"<init>":(I)V
Method	java/io/ByteArrayOutputStream."<init>":(I)V
Asciz	java/io/ObjectOutputStream;
class	java/io/ObjectOutputStream
Asciz	(Ljava/io/OutputStream;)V;
NameAndType	"<init>":(Ljava/io/OutputStream;)V
Method	java/io/ObjectOutputStream."<init>":(Ljava/io/OutputStream;)V
Asciz	writeObject;
Asciz	(Ljava/lang/Object;)V;
NameAndType	writeObject:(Ljava/lang/Object;)V
Method	java/io/ObjectOutputStream.writeObject:(Ljava/lang/Object;)V
Method	java/io/ObjectOutputStream.close:()V
Asciz	toByteArray;
Asciz	()[B;
NameAndType	toByteArray:()[B
Method	java/io/ByteArrayOutputStream.toByteArray:()[B
Asciz	m;
Asciz	ba;
Asciz	Ljava/io/ByteArrayOutputStream;;
Asciz	out;
Asciz	Ljava/io/ObjectOutputStream;;
Asciz	<A:Ljava/lang/Object;>(TA;Lscala/reflect/ClassManifest<TA;>;)[B;
Asciz	scala/ScalaObject;
class	scala/ScalaObject

{
public static final scala.util.Marshal$ MODULE$;
  Signature: Lscala/util/Marshal$;

public static {};
  Signature: ()V
  Code:
   Stack=1, Locals=0, Args_size=0
	new	class scala/util/Marshal$
	invokespecial	Method "<init>":()V
	return
  Labels:

private scala.util.Marshal$();
  Signature: ()V
  Code:
   Stack=1, Locals=1, Args_size=1
	aload_0
	invokespecial	Method java/lang/Object."<init>":()V
	aload_0
	putstatic	Field MODULE$:Lscala/util/Marshal$;
	return
  Labels:

public java.lang.Object load(byte[], scala.reflect.ClassManifest)   throws java.io.IOException, java.lang.ClassCastException, java.lang.ClassNotFoundException;
  Signature: ([BLscala/reflect/ClassManifest;)Ljava/lang/Object;
  Code:
   Stack=5, Locals=6, Args_size=3
	new	class java/io/ObjectInputStream
	dup
	new	class java/io/ByteArrayInputStream
	dup
	aload_1
	invokespecial	Method java/io/ByteArrayInputStream."<init>":([B)V
	invokespecial	Method java/io/ObjectInputStream."<init>":(Ljava/io/InputStream;)V
	astore_3
	aload_3
	invokevirtual	Method java/io/ObjectInputStream.readObject:()Ljava/lang/Object;
	checkcast	class scala/reflect/ClassManifest
	astore	4
	aload	4
	aload_2
	invokeinterface	InterfaceMethod scala/reflect/ClassManifest.$less$colon$less:(Lscala/reflect/ClassManifest;)Z
	ifeq	l1 // aload_3
	aload_3
	invokevirtual	Method java/io/ObjectInputStream.readObject:()Ljava/lang/Object;
	astore	5
	aload_3
	invokevirtual	Method java/io/ObjectInputStream.close:()V
	aload	5
	areturn
l1	aload_3
	invokevirtual	Method java/io/ObjectInputStream.close:()V
	new	class java/lang/ClassCastException
	dup
	new	class scala/collection/mutable/StringBuilder
	dup
	invokespecial	Method scala/collection/mutable/StringBuilder."<init>":()V
	ldc	String type mismatch;\n found   : 
	invokevirtual	Method scala/collection/mutable/StringBuilder.append:(Ljava/lang/Object;)Lscala/collection/mutable/StringBuilder;
	aload	4
	invokevirtual	Method scala/collection/mutable/StringBuilder.append:(Ljava/lang/Object;)Lscala/collection/mutable/StringBuilder;
	ldc	String \n required: 
	invokevirtual	Method scala/collection/mutable/StringBuilder.append:(Ljava/lang/Object;)Lscala/collection/mutable/StringBuilder;
	aload_2
	invokevirtual	Method scala/collection/mutable/StringBuilder.append:(Ljava/lang/Object;)Lscala/collection/mutable/StringBuilder;
	invokevirtual	Method scala/collection/mutable/StringBuilder.toString:()Ljava/lang/String;
	invokespecial	Method java/lang/ClassCastException."<init>":(Ljava/lang/String;)V
	athrow
  Labels:
   	l1 = 49 // aload_3
  LocalVariableTable: 
   Start  Length  Slot  Name   Signature
   0      90      0    this       Lscala/util/Marshal$;
   0      90      1    buffer       [B
   0      90      2    expected       Lscala/reflect/ClassManifest;
   16      74      3    in       Ljava/io/ObjectInputStream;
   25      65      4    found       Lscala/reflect/ClassManifest;
   42      6      5    o       Ljava/lang/Object;

  Signature: length = 0x2
   00 4C 
  Exceptions: 
   throws java.io.IOException, java.lang.ClassCastException, java.lang.ClassNotFoundException
public byte[] dump(java.lang.Object, scala.reflect.ClassManifest);
  Signature: (Ljava/lang/Object;Lscala/reflect/ClassManifest;)[B
  Code:
   Stack=3, Locals=5, Args_size=3
	new	class java/io/ByteArrayOutputStream
	dup
	ldc	int 512
	invokespecial	Method java/io/ByteArrayOutputStream."<init>":(I)V
	astore_3
	new	class java/io/ObjectOutputStream
	dup
	aload_3
	invokespecial	Method java/io/ObjectOutputStream."<init>":(Ljava/io/OutputStream;)V
	astore	4
	aload	4
	aload_2
	invokevirtual	Method java/io/ObjectOutputStream.writeObject:(Ljava/lang/Object;)V
	aload	4
	aload_1
	invokevirtual	Method java/io/ObjectOutputStream.writeObject:(Ljava/lang/Object;)V
	aload	4
	invokevirtual	Method java/io/ObjectOutputStream.close:()V
	aload_3
	invokevirtual	Method java/io/ByteArrayOutputStream.toByteArray:()[B
	areturn
  Labels:
  LocalVariableTable: 
   Start  Length  Slot  Name   Signature
   0      42      0    this       Lscala/util/Marshal$;
   0      42      1    o       Ljava/lang/Object;
   0      42      2    m       Lscala/reflect/ClassManifest;
   10      31      3    ba       Ljava/io/ByteArrayOutputStream;
   20      21      4    out       Ljava/io/ObjectOutputStream;

  Signature: length = 0x2
   00 6E 

}

