Compiled from "Marshal.scala"
public final class scala.util.Marshal extends java.lang.Object
  SourceFile: "Marshal.scala"
  ScalaSig: length = 0x23B
   05 00 65 07 05 01 02 FFFFFF88 02 07 01 07 4D 61 72 73
   68 61 6C 0A 02 03 04 01 04 75 74 69 6C 0A 01 05
   01 05 73 63 61 6C 61 03 00 10 02 08 09 0D 01 02
   06 08 0A 02 FFFFFF84 FFFFFF80 FFFFFF80 FFFFFF88 02 0B 02 07 4D 61 72 73
   68 61 6C 13 03 09 0C 14 10 02 0D 12 0D 01 0E 0A
   02 0F 10 01 04 6C 61 6E 67 0A 01 11 01 04 6A 61
   76 61 09 02 13 0E 02 06 4F 62 6A 65 63 74 10 02
   15 16 0D 01 04 09 02 17 04 02 0B 53 63 61 6C 61
   4F 62 6A 65 63 74 08 05 19 09 FFFFFF84 00 1A 01 06 3C
   69 6E 69 74 3E 14 01 07 08 05 1C 09 FFFFFF84 00 1D 01
   04 64 75 6D 70 15 02 1E 30 14 02 1F 39 16 02 20
   26 10 03 15 21 23 09 02 22 04 02 05 41 72 72 61
   79 10 02 15 24 09 02 25 04 02 04 42 79 74 65 08
   05 27 1B FFFFFFC0 01 28 01 01 6D 10 03 29 2C 2E 0D 01
   2A 0A 02 2B 04 01 07 72 65 66 6C 65 63 74 09 02
   2D 2A 02 0D 43 6C 61 73 73 4D 61 6E 69 66 65 73
   74 10 02 2F 30 0C 00 04 08 31 1B FFFFFF84 FFFFFF80 FFFFFF80 FFFFFFC2 00
   32 02 01 41 11 02 33 36 10 02 15 34 09 02 35 04
   02 07 4E 6F 74 68 69 6E 67 10 02 15 37 09 02 38
   04 02 03 41 6E 79 08 05 3A 1B FFFFFFC0 00 2E 01 01 6F
   08 05 3C 09 FFFFFF84 00 3D 01 04 6C 6F 61 64 15 02 3E
   41 14 02 3F 45 16 02 40 42 10 02 2F 41 04 08 31
   3B FFFFFF84 FFFFFF80 FFFFFF80 FFFFFFC2 00 32 08 05 43 3B FFFFFFC0 01 44 01 08
   65 78 70 65 63 74 65 64 10 03 29 2C 40 08 05 46
   3B FFFFFFC0 00 20 01 06 62 75 66 66 65 72 28 03 3B 48
   4B 10 02 15 49 09 02 4A 04 02 06 74 68 72 6F 77
   73 23 01 4C 10 02 0D 4D 09 02 4E 0E 02 16 43 6C
   61 73 73 4E 6F 74 46 6F 75 6E 64 45 78 63 65 70
   74 69 6F 6E 28 03 3B 48 50 23 01 51 10 02 52 5A
   0E 02 53 58 0E 02 54 57 0D 01 55 0A 02 56 06 01
   06 3C 72 6F 6F 74 3E 09 01 05 09 02 59 04 01 07
   70 61 63 6B 61 67 65 09 02 5B 5C 02 12 43 6C 61
   73 73 43 61 73 74 45 78 63 65 70 74 69 6F 6E 0A
   02 59 04 28 03 3B 48 5E 23 01 5F 10 02 60 63 0D
   01 61 0A 02 62 10 01 02 69 6F 09 02 64 61 02 0B
   49 4F 45 78 63 65 70 74 69 6F 6E 
  minor version: 0
  major version: 49
  Constant pool:
const #1 = Asciz	SourceFile;
const #2 = Asciz	Marshal.scala;
const #3 = Asciz	load;
const #4 = Asciz	([BLscala/reflect/ClassManifest;)Ljava/lang/Object;;
const #5 = Asciz	Code;
const #6 = Asciz	scala/util/Marshal$;
const #7 = class	#6;	//  scala/util/Marshal$
const #8 = Asciz	MODULE$;
const #9 = Asciz	Lscala/util/Marshal$;;
const #10 = NameAndType	#8:#9;//  MODULE$:Lscala/util/Marshal$;
const #11 = Field	#7.#10;	//  scala/util/Marshal$.MODULE$:Lscala/util/Marshal$;
const #12 = NameAndType	#3:#4;//  load:([BLscala/reflect/ClassManifest;)Ljava/lang/Object;
const #13 = Method	#7.#12;	//  scala/util/Marshal$.load:([BLscala/reflect/ClassManifest;)Ljava/lang/Object;
const #14 = Asciz	<A:Ljava/lang/Object;>([BLscala/reflect/ClassManifest<TA;>;)TA;;
const #15 = Asciz	Signature;
const #16 = Asciz	java/io/IOException;
const #17 = class	#16;	//  java/io/IOException
const #18 = Asciz	java/lang/ClassCastException;
const #19 = class	#18;	//  java/lang/ClassCastException
const #20 = Asciz	java/lang/ClassNotFoundException;
const #21 = class	#20;	//  java/lang/ClassNotFoundException
const #22 = Asciz	Exceptions;
const #23 = Asciz	dump;
const #24 = Asciz	(Ljava/lang/Object;Lscala/reflect/ClassManifest;)[B;
const #25 = NameAndType	#23:#24;//  dump:(Ljava/lang/Object;Lscala/reflect/ClassManifest;)[B
const #26 = Method	#7.#25;	//  scala/util/Marshal$.dump:(Ljava/lang/Object;Lscala/reflect/ClassManifest;)[B
const #27 = Asciz	<A:Ljava/lang/Object;>(TA;Lscala/reflect/ClassManifest<TA;>;)[B;
const #28 = Asciz	ScalaSig;
const #29 = Asciz	scala/util/Marshal;
const #30 = class	#29;	//  scala/util/Marshal
const #31 = Asciz	java/lang/Object;
const #32 = class	#31;	//  java/lang/Object

{
public static final java.lang.Object load(byte[], scala.reflect.ClassManifest)   throws java.io.IOException, java.lang.ClassCastException, java.lang.ClassNotFoundException;
  Code:
   Stack=3, Locals=2, Args_size=2
   0:	getstatic	#11; //Field scala/util/Marshal$.MODULE$:Lscala/util/Marshal$;
   3:	aload_0
   4:	aload_1
   5:	invokevirtual	#13; //Method scala/util/Marshal$.load:([BLscala/reflect/ClassManifest;)Ljava/lang/Object;
   8:	areturn
  Signature: length = 0x2
   00 0E 
  Exceptions: 
   throws java.io.IOException, java.lang.ClassCastException, java.lang.ClassNotFoundException
public static final byte[] dump(java.lang.Object, scala.reflect.ClassManifest);
  Code:
   Stack=3, Locals=2, Args_size=2
   0:	getstatic	#11; //Field scala/util/Marshal$.MODULE$:Lscala/util/Marshal$;
   3:	aload_0
   4:	aload_1
   5:	invokevirtual	#26; //Method scala/util/Marshal$.dump:(Ljava/lang/Object;Lscala/reflect/ClassManifest;)[B
   8:	areturn
  Signature: length = 0x2
   00 1B 

}

