Compiled from "NameTransformer.scala"
public class scala.util.NameTransformer$OpCodes extends java.lang.Object implements scala.ScalaObject
  SourceFile: "NameTransformer.scala"
  Scala: length = 0x
   
  InnerClass: 
   public #35= #14 of #34; //OpCodes=class scala/util/NameTransformer$OpCodes of class scala/util/NameTransformer
  minor version: 0
  major version: 49
  Constant pool:
const #1 = Asciz	SourceFile;
const #2 = Asciz	NameTransformer.scala;
const #3 = Asciz	next;
const #4 = Asciz	Lscala/util/NameTransformer$OpCodes;;
const #5 = Asciz	code;
const #6 = Asciz	Ljava/lang/String;;
const #7 = Asciz	op;
const #8 = Asciz	C;
const #9 = Asciz	<init>;
const #10 = Asciz	(CLjava/lang/String;Lscala/util/NameTransformer$OpCodes;)V;
const #11 = Asciz	Code;
const #12 = Asciz	LineNumberTable;
const #13 = Asciz	scala/util/NameTransformer$OpCodes;
const #14 = class	#13;	//  scala/util/NameTransformer$OpCodes
const #15 = NameAndType	#7:#8;//  op:C
const #16 = Field	#14.#15;	//  scala/util/NameTransformer$OpCodes.op:C
const #17 = NameAndType	#5:#6;//  code:Ljava/lang/String;
const #18 = Field	#14.#17;	//  scala/util/NameTransformer$OpCodes.code:Ljava/lang/String;
const #19 = NameAndType	#3:#4;//  next:Lscala/util/NameTransformer$OpCodes;
const #20 = Field	#14.#19;	//  scala/util/NameTransformer$OpCodes.next:Lscala/util/NameTransformer$OpCodes;
const #21 = Asciz	java/lang/Object;
const #22 = class	#21;	//  java/lang/Object
const #23 = Asciz	()V;
const #24 = NameAndType	#9:#23;//  "<init>":()V
const #25 = Method	#22.#24;	//  java/lang/Object."<init>":()V
const #26 = Asciz	this;
const #27 = Asciz	LocalVariableTable;
const #28 = Asciz	()Lscala/util/NameTransformer$OpCodes;;
const #29 = Asciz	()Ljava/lang/String;;
const #30 = Asciz	()C;
const #31 = Asciz	Scala;
const #32 = Asciz	InnerClasses;
const #33 = Asciz	scala/util/NameTransformer;
const #34 = class	#33;	//  scala/util/NameTransformer
const #35 = Asciz	OpCodes;
const #36 = Asciz	scala/ScalaObject;
const #37 = class	#36;	//  scala/ScalaObject

{
public scala.util.NameTransformer$OpCodes(char, java.lang.String, scala.util.NameTransformer$OpCodes);
  Code:
   Stack=2, Locals=4, Args_size=4
   0:	aload_0
   1:	iload_1
   2:	putfield	#16; //Field op:C
   5:	aload_0
   6:	aload_2
   7:	putfield	#18; //Field code:Ljava/lang/String;
   10:	aload_0
   11:	aload_3
   12:	putfield	#20; //Field next:Lscala/util/NameTransformer$OpCodes;
   15:	aload_0
   16:	invokespecial	#25; //Method java/lang/Object."<init>":()V
   19:	return
  LineNumberTable: 
   line 21: 0

  LocalVariableTable: 
   Start  Length  Slot  Name   Signature
   0      20      0    this       Lscala/util/NameTransformer$OpCodes;
   0      20      1    op       C
   0      20      2    code       Ljava/lang/String;
   0      20      3    next       Lscala/util/NameTransformer$OpCodes;


public scala.util.NameTransformer$OpCodes next();
  Code:
   Stack=1, Locals=1, Args_size=1
   0:	aload_0
   1:	getfield	#20; //Field next:Lscala/util/NameTransformer$OpCodes;
   4:	areturn
  LineNumberTable: 
   line 21: 0


public java.lang.String code();
  Code:
   Stack=1, Locals=1, Args_size=1
   0:	aload_0
   1:	getfield	#18; //Field code:Ljava/lang/String;
   4:	areturn
  LineNumberTable: 
   line 21: 0


public char op();
  Code:
   Stack=1, Locals=1, Args_size=1
   0:	aload_0
   1:	getfield	#16; //Field op:C
   4:	ireturn
  LineNumberTable: 
   line 21: 0


}

