Compiled from "NameTransformer.scala"
public class scala.util.NameTransformer$OpCodes extends java.lang.Object implements scala.ScalaObject
  SourceFile: "NameTransformer.scala"
  Scala: length = 0x
   
  InnerClass: 
   public OpCodes=class scala/util/NameTransformer$OpCodes of class scala/util/NameTransformer
  minor version: 0
  major version: 49
  Constant pool:
Asciz	SourceFile;
Asciz	NameTransformer.scala;
Asciz	next;
Asciz	Lscala/util/NameTransformer$OpCodes;;
Asciz	code;
Asciz	Ljava/lang/String;;
Asciz	op;
Asciz	C;
Asciz	<init>;
Asciz	(CLjava/lang/String;Lscala/util/NameTransformer$OpCodes;)V;
Asciz	Code;
Asciz	LineNumberTable;
Asciz	scala/util/NameTransformer$OpCodes;
class	scala/util/NameTransformer$OpCodes
NameAndType	op:C
Field	scala/util/NameTransformer$OpCodes.op:C
NameAndType	code:Ljava/lang/String;
Field	scala/util/NameTransformer$OpCodes.code:Ljava/lang/String;
NameAndType	next:Lscala/util/NameTransformer$OpCodes;
Field	scala/util/NameTransformer$OpCodes.next:Lscala/util/NameTransformer$OpCodes;
Asciz	java/lang/Object;
class	java/lang/Object
Asciz	()V;
NameAndType	"<init>":()V
Method	java/lang/Object."<init>":()V
Asciz	this;
Asciz	LocalVariableTable;
Asciz	()Lscala/util/NameTransformer$OpCodes;;
Asciz	()Ljava/lang/String;;
Asciz	()C;
Asciz	Scala;
Asciz	InnerClasses;
Asciz	scala/util/NameTransformer;
class	scala/util/NameTransformer
Asciz	OpCodes;
Asciz	scala/ScalaObject;
class	scala/ScalaObject

{
private final scala.util.NameTransformer$OpCodes next;
  Signature: Lscala/util/NameTransformer$OpCodes;

private final java.lang.String code;
  Signature: Ljava/lang/String;

private final char op;
  Signature: C

public scala.util.NameTransformer$OpCodes(char, java.lang.String, scala.util.NameTransformer$OpCodes);
  Signature: (CLjava/lang/String;Lscala/util/NameTransformer$OpCodes;)V
  Code:
   Stack=2, Locals=4, Args_size=4
	aload_0
	iload_1
	putfield	Field op:C
	aload_0
	aload_2
	putfield	Field code:Ljava/lang/String;
	aload_0
	aload_3
	putfield	Field next:Lscala/util/NameTransformer$OpCodes;
	aload_0
	invokespecial	Method java/lang/Object."<init>":()V
	return
  Labels:
  LocalVariableTable: 
   Start  Length  Slot  Name   Signature
   0      20      0    this       Lscala/util/NameTransformer$OpCodes;
   0      20      1    op       C
   0      20      2    code       Ljava/lang/String;
   0      20      3    next       Lscala/util/NameTransformer$OpCodes;


public scala.util.NameTransformer$OpCodes next();
  Signature: ()Lscala/util/NameTransformer$OpCodes;
  Code:
   Stack=1, Locals=1, Args_size=1
	aload_0
	getfield	Field next:Lscala/util/NameTransformer$OpCodes;
	areturn
  Labels:

public java.lang.String code();
  Signature: ()Ljava/lang/String;
  Code:
   Stack=1, Locals=1, Args_size=1
	aload_0
	getfield	Field code:Ljava/lang/String;
	areturn
  Labels:

public char op();
  Signature: ()C
  Code:
   Stack=1, Locals=1, Args_size=1
	aload_0
	getfield	Field op:C
	ireturn
  Labels:

}

