Compiled from "NameTransformer.scala"
public final class scala.util.NameTransformer$ extends java.lang.Object implements scala.ScalaObject
  SourceFile: "NameTransformer.scala"
  Scala: length = 0x
   
  InnerClass: 
   public #257= #43 of #256; //OpCodes=class scala/util/NameTransformer$OpCodes of class scala/util/NameTransformer
  minor version: 0
  major version: 49
  Constant pool:
const #1 = Asciz	SourceFile;
const #2 = Asciz	NameTransformer.scala;
const #3 = Asciz	Scala;
const #4 = Asciz	MODULE$;
const #5 = Asciz	Lscala/util/NameTransformer$;;
const #6 = Asciz	<clinit>;
const #7 = Asciz	()V;
const #8 = Asciz	Code;
const #9 = Asciz	scala/util/NameTransformer$;
const #10 = class	#9;	//  scala/util/NameTransformer$
const #11 = Asciz	<init>;
const #12 = NameAndType	#11:#7;//  "<init>":()V
const #13 = Method	#10.#12;	//  scala/util/NameTransformer$."<init>":()V
const #14 = Asciz	code2op;
const #15 = Asciz	[Lscala/util/NameTransformer$OpCodes;;
const #16 = Asciz	op2code;
const #17 = Asciz	[Ljava/lang/String;;
const #18 = Asciz	ncodes;
const #19 = Asciz	I;
const #20 = Asciz	nops;
const #21 = Asciz	LineNumberTable;
const #22 = Asciz	java/lang/Object;
const #23 = class	#22;	//  java/lang/Object
const #24 = Method	#23.#12;	//  java/lang/Object."<init>":()V
const #25 = NameAndType	#4:#5;//  MODULE$:Lscala/util/NameTransformer$;
const #26 = Field	#10.#25;	//  scala/util/NameTransformer$.MODULE$:Lscala/util/NameTransformer$;
const #27 = int	128;
const #28 = NameAndType	#20:#19;//  nops:I
const #29 = Field	#10.#28;	//  scala/util/NameTransformer$.nops:I
const #30 = int	676;
const #31 = NameAndType	#18:#19;//  ncodes:I
const #32 = Field	#10.#31;	//  scala/util/NameTransformer$.ncodes:I
const #33 = Asciz	()I;
const #34 = NameAndType	#20:#33;//  nops:()I
const #35 = Method	#10.#34;	//  scala/util/NameTransformer$.nops:()I
const #36 = Asciz	java/lang/String;
const #37 = class	#36;	//  java/lang/String
const #38 = NameAndType	#16:#17;//  op2code:[Ljava/lang/String;
const #39 = Field	#10.#38;	//  scala/util/NameTransformer$.op2code:[Ljava/lang/String;
const #40 = NameAndType	#18:#33;//  ncodes:()I
const #41 = Method	#10.#40;	//  scala/util/NameTransformer$.ncodes:()I
const #42 = Asciz	scala/util/NameTransformer$OpCodes;
const #43 = class	#42;	//  scala/util/NameTransformer$OpCodes
const #44 = NameAndType	#14:#15;//  code2op:[Lscala/util/NameTransformer$OpCodes;
const #45 = Field	#10.#44;	//  scala/util/NameTransformer$.code2op:[Lscala/util/NameTransformer$OpCodes;
const #46 = int	126;
const #47 = Asciz	$tilde;
const #48 = String	#47;	//  $tilde
const #49 = Asciz	enterOp;
const #50 = Asciz	(CLjava/lang/String;)V;
const #51 = NameAndType	#49:#50;//  enterOp:(CLjava/lang/String;)V
const #52 = Method	#10.#51;	//  scala/util/NameTransformer$.enterOp:(CLjava/lang/String;)V
const #53 = int	61;
const #54 = Asciz	$eq;
const #55 = String	#54;	//  $eq
const #56 = int	60;
const #57 = Asciz	$less;
const #58 = String	#57;	//  $less
const #59 = int	62;
const #60 = Asciz	$greater;
const #61 = String	#60;	//  $greater
const #62 = int	33;
const #63 = Asciz	$bang;
const #64 = String	#63;	//  $bang
const #65 = int	35;
const #66 = Asciz	$hash;
const #67 = String	#66;	//  $hash
const #68 = int	37;
const #69 = Asciz	$percent;
const #70 = String	#69;	//  $percent
const #71 = int	94;
const #72 = Asciz	$up;
const #73 = String	#72;	//  $up
const #74 = int	38;
const #75 = Asciz	$amp;
const #76 = String	#75;	//  $amp
const #77 = int	124;
const #78 = Asciz	$bar;
const #79 = String	#78;	//  $bar
const #80 = int	42;
const #81 = Asciz	$times;
const #82 = String	#81;	//  $times
const #83 = int	47;
const #84 = Asciz	$div;
const #85 = String	#84;	//  $div
const #86 = int	43;
const #87 = Asciz	$plus;
const #88 = String	#87;	//  $plus
const #89 = int	45;
const #90 = Asciz	$minus;
const #91 = String	#90;	//  $minus
const #92 = int	58;
const #93 = Asciz	$colon;
const #94 = String	#93;	//  $colon
const #95 = int	92;
const #96 = Asciz	$bslash;
const #97 = String	#96;	//  $bslash
const #98 = int	63;
const #99 = Asciz	$qmark;
const #100 = String	#99;	//  $qmark
const #101 = int	64;
const #102 = Asciz	$at;
const #103 = String	#102;	//  $at
const #104 = Asciz	decode;
const #105 = Asciz	(Ljava/lang/String;)Ljava/lang/String;;
const #106 = String	#11;	//  <init>
const #107 = Asciz	endsWith;
const #108 = Asciz	(Ljava/lang/String;)Z;
const #109 = NameAndType	#107:#108;//  endsWith:(Ljava/lang/String;)Z
const #110 = Method	#37.#109;	//  java/lang/String.endsWith:(Ljava/lang/String;)Z
const #111 = Asciz	scala/collection/mutable/StringBuilder;
const #112 = class	#111;	//  scala/collection/mutable/StringBuilder
const #113 = Method	#112.#12;	//  scala/collection/mutable/StringBuilder."<init>":()V
const #114 = Asciz	length;
const #115 = NameAndType	#114:#33;//  length:()I
const #116 = Method	#37.#115;	//  java/lang/String.length:()I
const #117 = Asciz	substring;
const #118 = Asciz	(II)Ljava/lang/String;;
const #119 = NameAndType	#117:#118;//  substring:(II)Ljava/lang/String;
const #120 = Method	#37.#119;	//  java/lang/String.substring:(II)Ljava/lang/String;
const #121 = Asciz	append;
const #122 = Asciz	(Ljava/lang/Object;)Lscala/collection/mutable/StringBuilder;;
const #123 = NameAndType	#121:#122;//  append:(Ljava/lang/Object;)Lscala/collection/mutable/StringBuilder;
const #124 = Method	#112.#123;	//  scala/collection/mutable/StringBuilder.append:(Ljava/lang/Object;)Lscala/collection/mutable/StringBuilder;
const #125 = Asciz	this;
const #126 = String	#125;	//  this
const #127 = Asciz	toString;
const #128 = Asciz	()Ljava/lang/String;;
const #129 = NameAndType	#127:#128;//  toString:()Ljava/lang/String;
const #130 = Method	#112.#129;	//  scala/collection/mutable/StringBuilder.toString:()Ljava/lang/String;
const #131 = Asciz	(C)Lscala/collection/mutable/StringBuilder;;
const #132 = NameAndType	#121:#131;//  append:(C)Lscala/collection/mutable/StringBuilder;
const #133 = Method	#112.#132;	//  scala/collection/mutable/StringBuilder.append:(C)Lscala/collection/mutable/StringBuilder;
const #134 = Asciz	scala/runtime/BoxedUnit;
const #135 = class	#134;	//  scala/runtime/BoxedUnit
const #136 = Asciz	UNIT;
const #137 = Asciz	Lscala/runtime/BoxedUnit;;
const #138 = NameAndType	#136:#137;//  UNIT:Lscala/runtime/BoxedUnit;
const #139 = Field	#135.#138;	//  scala/runtime/BoxedUnit.UNIT:Lscala/runtime/BoxedUnit;
const #140 = Asciz	charAt;
const #141 = Asciz	(I)C;
const #142 = NameAndType	#140:#141;//  charAt:(I)C
const #143 = Method	#37.#142;	//  java/lang/String.charAt:(I)C
const #144 = int	36;
const #145 = int	97;
const #146 = int	122;
const #147 = Asciz	()[Lscala/util/NameTransformer$OpCodes;;
const #148 = NameAndType	#14:#147;//  code2op:()[Lscala/util/NameTransformer$OpCodes;
const #149 = Method	#10.#148;	//  scala/util/NameTransformer$.code2op:()[Lscala/util/NameTransformer$OpCodes;
const #150 = int	26;
const #151 = Asciz	code;
const #152 = NameAndType	#151:#128;//  code:()Ljava/lang/String;
const #153 = Method	#43.#152;	//  scala/util/NameTransformer$OpCodes.code:()Ljava/lang/String;
const #154 = Asciz	startsWith;
const #155 = Asciz	(Ljava/lang/String;I)Z;
const #156 = NameAndType	#154:#155;//  startsWith:(Ljava/lang/String;I)Z
const #157 = Method	#37.#156;	//  java/lang/String.startsWith:(Ljava/lang/String;I)Z
const #158 = Asciz	next;
const #159 = Asciz	()Lscala/util/NameTransformer$OpCodes;;
const #160 = NameAndType	#158:#159;//  next:()Lscala/util/NameTransformer$OpCodes;
const #161 = Method	#43.#160;	//  scala/util/NameTransformer$OpCodes.next:()Lscala/util/NameTransformer$OpCodes;
const #162 = Method	#112.#12;	//  scala/collection/mutable/StringBuilder."<init>":()V
const #163 = Asciz	(Ljava/lang/String;)Lscala/collection/mutable/StringBuilder;;
const #164 = NameAndType	#121:#163;//  append:(Ljava/lang/String;)Lscala/collection/mutable/StringBuilder;
const #165 = Method	#112.#164;	//  scala/collection/mutable/StringBuilder.append:(Ljava/lang/String;)Lscala/collection/mutable/StringBuilder;
const #166 = Asciz	op;
const #167 = Asciz	()C;
const #168 = NameAndType	#166:#167;//  op:()C
const #169 = Method	#43.#168;	//  scala/util/NameTransformer$OpCodes.op:()C
const #170 = int	6;
const #171 = int	117;
const #172 = Asciz	java/lang/Character;
const #173 = class	#172;	//  java/lang/Character
const #174 = Asciz	isDigit;
const #175 = Asciz	(C)Z;
const #176 = NameAndType	#174:#175;//  isDigit:(C)Z
const #177 = Method	#173.#176;	//  java/lang/Character.isDigit:(C)Z
const #178 = int	65;
const #179 = int	70;
const #180 = int	16;
const #181 = Asciz	java/lang/Integer;
const #182 = class	#181;	//  java/lang/Integer
const #183 = Asciz	parseInt;
const #184 = Asciz	(Ljava/lang/String;I)I;
const #185 = NameAndType	#183:#184;//  parseInt:(Ljava/lang/String;I)I
const #186 = Method	#182.#185;	//  java/lang/Integer.parseInt:(Ljava/lang/String;I)I
const #187 = Method	#112.#129;	//  scala/collection/mutable/StringBuilder.toString:()Ljava/lang/String;
const #188 = Asciz	java/lang/NumberFormatException;
const #189 = class	#188;	//  java/lang/NumberFormatException
const #190 = Asciz	name0;
const #191 = Asciz	Ljava/lang/String;;
const #192 = Asciz	name;
const #193 = Asciz	buf;
const #194 = Asciz	Lscala/collection/mutable/StringBuilder;;
const #195 = Asciz	len;
const #196 = Asciz	i;
const #197 = Asciz	ops;
const #198 = Asciz	Lscala/util/NameTransformer$OpCodes;;
const #199 = Asciz	unicode;
const #200 = Asciz	Z;
const #201 = Asciz	c;
const #202 = Asciz	C;
const #203 = Asciz	ch1;
const #204 = Asciz	ch2;
const #205 = Asciz	hex;
const #206 = Asciz	str;
const #207 = Asciz	LocalVariableTable;
const #208 = Asciz	encode;
const #209 = Asciz	()[Ljava/lang/String;;
const #210 = NameAndType	#16:#209;//  op2code:()[Ljava/lang/String;
const #211 = Method	#10.#210;	//  scala/util/NameTransformer$.op2code:()[Ljava/lang/String;
const #212 = Asciz	scala/Predef$;
const #213 = class	#212;	//  scala/Predef$
const #214 = Asciz	Lscala/Predef$;;
const #215 = NameAndType	#4:#214;//  MODULE$:Lscala/Predef$;
const #216 = Field	#213.#215;	//  scala/Predef$.MODULE$:Lscala/Predef$;
const #217 = Asciz	char2int;
const #218 = Asciz	(C)I;
const #219 = NameAndType	#217:#218;//  char2int:(C)I
const #220 = Method	#213.#219;	//  scala/Predef$.char2int:(C)I
const #221 = Asciz	isJavaIdentifierPart;
const #222 = NameAndType	#221:#175;//  isJavaIdentifierPart:(C)Z
const #223 = Method	#173.#222;	//  java/lang/Character.isJavaIdentifierPart:(C)Z
const #224 = Asciz	$u%04X;
const #225 = String	#224;	//  $u%04X
const #226 = Asciz	stringWrapper;
const #227 = Asciz	(Ljava/lang/String;)Lscala/runtime/RichString;;
const #228 = NameAndType	#226:#227;//  stringWrapper:(Ljava/lang/String;)Lscala/runtime/RichString;
const #229 = Method	#213.#228;	//  scala/Predef$.stringWrapper:(Ljava/lang/String;)Lscala/runtime/RichString;
const #230 = Asciz	scala/runtime/ScalaRunTime$;
const #231 = class	#230;	//  scala/runtime/ScalaRunTime$
const #232 = Asciz	Lscala/runtime/ScalaRunTime$;;
const #233 = NameAndType	#4:#232;//  MODULE$:Lscala/runtime/ScalaRunTime$;
const #234 = Field	#231.#233;	//  scala/runtime/ScalaRunTime$.MODULE$:Lscala/runtime/ScalaRunTime$;
const #235 = Asciz	scala/runtime/BoxesRunTime;
const #236 = class	#235;	//  scala/runtime/BoxesRunTime
const #237 = Asciz	boxToInteger;
const #238 = Asciz	(I)Ljava/lang/Integer;;
const #239 = NameAndType	#237:#238;//  boxToInteger:(I)Ljava/lang/Integer;
const #240 = Method	#236.#239;	//  scala/runtime/BoxesRunTime.boxToInteger:(I)Ljava/lang/Integer;
const #241 = Asciz	boxArray;
const #242 = Asciz	(Ljava/lang/Object;)Lscala/runtime/BoxedArray;;
const #243 = NameAndType	#241:#242;//  boxArray:(Ljava/lang/Object;)Lscala/runtime/BoxedArray;
const #244 = Method	#231.#243;	//  scala/runtime/ScalaRunTime$.boxArray:(Ljava/lang/Object;)Lscala/runtime/BoxedArray;
const #245 = Asciz	scala/runtime/RichString;
const #246 = class	#245;	//  scala/runtime/RichString
const #247 = Asciz	format;
const #248 = Asciz	(Lscala/collection/Sequence;)Ljava/lang/String;;
const #249 = NameAndType	#247:#248;//  format:(Lscala/collection/Sequence;)Ljava/lang/String;
const #250 = Method	#246.#249;	//  scala/runtime/RichString.format:(Lscala/collection/Sequence;)Ljava/lang/String;
const #251 = Asciz	(CLjava/lang/String;Lscala/util/NameTransformer$OpCodes;)V;
const #252 = NameAndType	#11:#251;//  "<init>":(CLjava/lang/String;Lscala/util/NameTransformer$OpCodes;)V
const #253 = Method	#43.#252;	//  scala/util/NameTransformer$OpCodes."<init>":(CLjava/lang/String;Lscala/util/NameTransformer$OpCodes;)V
const #254 = Asciz	InnerClasses;
const #255 = Asciz	scala/util/NameTransformer;
const #256 = class	#255;	//  scala/util/NameTransformer
const #257 = Asciz	OpCodes;
const #258 = Asciz	scala/ScalaObject;
const #259 = class	#258;	//  scala/ScalaObject

{
public static final scala.util.NameTransformer$ MODULE$;

public static {};
  Code:
   Stack=1, Locals=0, Args_size=0
   0:	new	#10; //class scala/util/NameTransformer$
   3:	invokespecial	#13; //Method "<init>":()V
   6:	return

public java.lang.String decode(java.lang.String);
  Code:
   Stack=5, Locals=13, Args_size=2
   0:	aload_1
   1:	ldc	#106; //String <init>
   3:	invokevirtual	#110; //Method java/lang/String.endsWith:(Ljava/lang/String;)Z
   6:	ifeq	45
   9:	new	#112; //class scala/collection/mutable/StringBuilder
   12:	dup
   13:	invokespecial	#113; //Method scala/collection/mutable/StringBuilder."<init>":()V
   16:	aload_1
   17:	iconst_0
   18:	aload_1
   19:	invokevirtual	#116; //Method java/lang/String.length:()I
   22:	ldc	#106; //String <init>
   24:	invokevirtual	#116; //Method java/lang/String.length:()I
   27:	isub
   28:	invokevirtual	#120; //Method java/lang/String.substring:(II)Ljava/lang/String;
   31:	invokevirtual	#124; //Method scala/collection/mutable/StringBuilder.append:(Ljava/lang/Object;)Lscala/collection/mutable/StringBuilder;
   34:	ldc	#126; //String this
   36:	invokevirtual	#124; //Method scala/collection/mutable/StringBuilder.append:(Ljava/lang/Object;)Lscala/collection/mutable/StringBuilder;
   39:	invokevirtual	#130; //Method scala/collection/mutable/StringBuilder.toString:()Ljava/lang/String;
   42:	goto	46
   45:	aload_1
   46:	astore_2
   47:	aconst_null
   48:	pop
   49:	aconst_null
   50:	astore_3
   51:	aload_2
   52:	invokevirtual	#116; //Method java/lang/String.length:()I
   55:	istore	4
   57:	iconst_0
   58:	istore	5
   60:	goto	97
   63:	pop
   64:	aload	6
   66:	ifnonnull	97
   69:	iload	7
   71:	ifne	97
   74:	aload_3
   75:	ifnull	87
   78:	aload_3
   79:	iload	8
   81:	invokevirtual	#133; //Method scala/collection/mutable/StringBuilder.append:(C)Lscala/collection/mutable/StringBuilder;
   84:	goto	90
   87:	getstatic	#139; //Field scala/runtime/BoxedUnit.UNIT:Lscala/runtime/BoxedUnit;
   90:	pop
   91:	iload	5
   93:	iconst_1
   94:	iadd
   95:	istore	5
   97:	iload	5
   99:	iload	4
   101:	if_icmpge	409
   104:	aconst_null
   105:	pop
   106:	aconst_null
   107:	astore	6
   109:	iconst_0
   110:	istore	7
   112:	aload_2
   113:	iload	5
   115:	invokevirtual	#143; //Method java/lang/String.charAt:(I)C
   118:	istore	8
   120:	iload	8
   122:	ldc	#144; //int 36
   124:	if_icmpne	64
   127:	iload	5
   129:	iconst_2
   130:	iadd
   131:	iload	4
   133:	if_icmpge	64
   136:	aload_2
   137:	iload	5
   139:	iconst_1
   140:	iadd
   141:	invokevirtual	#143; //Method java/lang/String.charAt:(I)C
   144:	istore	9
   146:	ldc	#145; //int 97
   148:	iload	9
   150:	if_icmpgt	64
   153:	iload	9
   155:	ldc	#146; //int 122
   157:	if_icmpgt	64
   160:	aload_2
   161:	iload	5
   163:	iconst_2
   164:	iadd
   165:	invokevirtual	#143; //Method java/lang/String.charAt:(I)C
   168:	istore	10
   170:	ldc	#145; //int 97
   172:	iload	10
   174:	if_icmpgt	295
   177:	iload	10
   179:	ldc	#146; //int 122
   181:	if_icmpgt	295
   184:	aload_0
   185:	invokespecial	#149; //Method code2op:()[Lscala/util/NameTransformer$OpCodes;
   188:	iload	9
   190:	ldc	#145; //int 97
   192:	isub
   193:	ldc	#150; //int 26
   195:	imul
   196:	iload	10
   198:	iadd
   199:	ldc	#145; //int 97
   201:	isub
   202:	aaload
   203:	astore	6
   205:	aload	6
   207:	ifnull	234
   210:	aload_2
   211:	aload	6
   213:	invokevirtual	#153; //Method scala/util/NameTransformer$OpCodes.code:()Ljava/lang/String;
   216:	iload	5
   218:	invokevirtual	#157; //Method java/lang/String.startsWith:(Ljava/lang/String;I)Z
   221:	ifne	234
   224:	aload	6
   226:	invokevirtual	#161; //Method scala/util/NameTransformer$OpCodes.next:()Lscala/util/NameTransformer$OpCodes;
   229:	astore	6
   231:	goto	205
   234:	aload	6
   236:	ifnull	64
   239:	aload_3
   240:	ifnonnull	265
   243:	new	#112; //class scala/collection/mutable/StringBuilder
   246:	dup
   247:	invokespecial	#162; //Method scala/collection/mutable/StringBuilder."<init>":()V
   250:	astore_3
   251:	aload_3
   252:	aload_2
   253:	iconst_0
   254:	iload	5
   256:	invokevirtual	#120; //Method java/lang/String.substring:(II)Ljava/lang/String;
   259:	invokevirtual	#165; //Method scala/collection/mutable/StringBuilder.append:(Ljava/lang/String;)Lscala/collection/mutable/StringBuilder;
   262:	goto	268
   265:	getstatic	#139; //Field scala/runtime/BoxedUnit.UNIT:Lscala/runtime/BoxedUnit;
   268:	pop
   269:	aload_3
   270:	aload	6
   272:	invokevirtual	#169; //Method scala/util/NameTransformer$OpCodes.op:()C
   275:	invokevirtual	#133; //Method scala/collection/mutable/StringBuilder.append:(C)Lscala/collection/mutable/StringBuilder;
   278:	pop
   279:	iload	5
   281:	aload	6
   283:	invokevirtual	#153; //Method scala/util/NameTransformer$OpCodes.code:()Ljava/lang/String;
   286:	invokevirtual	#116; //Method java/lang/String.length:()I
   289:	iadd
   290:	istore	5
   292:	goto	64
   295:	iload	4
   297:	iload	5
   299:	isub
   300:	ldc	#170; //int 6
   302:	if_icmplt	64
   305:	iload	9
   307:	ldc	#171; //int 117
   309:	if_icmpne	64
   312:	iload	10
   314:	invokestatic	#177; //Method java/lang/Character.isDigit:(C)Z
   317:	ifne	334
   320:	ldc	#178; //int 65
   322:	iload	10
   324:	if_icmpgt	64
   327:	iload	10
   329:	ldc	#179; //int 70
   331:	if_icmpgt	64
   334:	aload_2
   335:	iload	5
   337:	iconst_2
   338:	iadd
   339:	iload	5
   341:	ldc	#170; //int 6
   343:	iadd
   344:	invokevirtual	#120; //Method java/lang/String.substring:(II)Ljava/lang/String;
   347:	astore	11
   349:	aload	11
   351:	ldc	#180; //int 16
   353:	invokestatic	#186; //Method java/lang/Integer.parseInt:(Ljava/lang/String;I)I
   356:	i2c
   357:	istore	12
   359:	aload_3
   360:	ifnonnull	385
   363:	new	#112; //class scala/collection/mutable/StringBuilder
   366:	dup
   367:	invokespecial	#162; //Method scala/collection/mutable/StringBuilder."<init>":()V
   370:	astore_3
   371:	aload_3
   372:	aload_2
   373:	iconst_0
   374:	iload	5
   376:	invokevirtual	#120; //Method java/lang/String.substring:(II)Ljava/lang/String;
   379:	invokevirtual	#165; //Method scala/collection/mutable/StringBuilder.append:(Ljava/lang/String;)Lscala/collection/mutable/StringBuilder;
   382:	goto	388
   385:	getstatic	#139; //Field scala/runtime/BoxedUnit.UNIT:Lscala/runtime/BoxedUnit;
   388:	pop
   389:	aload_3
   390:	iload	12
   392:	invokevirtual	#133; //Method scala/collection/mutable/StringBuilder.append:(C)Lscala/collection/mutable/StringBuilder;
   395:	pop
   396:	iload	5
   398:	ldc	#170; //int 6
   400:	iadd
   401:	istore	5
   403:	iconst_1
   404:	istore	7
   406:	goto	64
   409:	aload_3
   410:	ifnonnull	417
   413:	aload_2
   414:	goto	421
   417:	aload_3
   418:	invokevirtual	#187; //Method scala/collection/mutable/StringBuilder.toString:()Ljava/lang/String;
   421:	areturn
  Exception table:
   from   to  target type
   349   409    63   Class java/lang/NumberFormatException

  LineNumberTable: 
   line 85: 0
   line 86: 45
   line 85: 46
   line 87: 47
   line 88: 51
   line 89: 57
   line 90: 60
   line 138: 63
   line 139: 74
   line 140: 78
   line 139: 87
   line 141: 91
   line 90: 97
   line 91: 104
   line 92: 109
   line 93: 112
   line 94: 120
   line 95: 136
   line 96: 146
   line 97: 160
   line 98: 170
   line 99: 184
   line 100: 205
   line 101: 234
   line 102: 239
   line 103: 243
   line 104: 251
   line 102: 265
   line 106: 269
   line 107: 279
   line 111: 295
   line 112: 305
   line 113: 312
   line 114: 320
   line 116: 334
   line 118: 349
   line 119: 359
   line 120: 363
   line 121: 371
   line 119: 385
   line 123: 389
   line 125: 396
   line 126: 403
   line 145: 409
   line 83: 421

  LocalVariableTable: 
   Start  Length  Slot  Name   Signature
   0      422      0    this       Lscala/util/NameTransformer$;
   0      422      1    name0       Ljava/lang/String;
   47      375      2    name       Ljava/lang/String;
   51      371      3    buf       Lscala/collection/mutable/StringBuilder;
   57      365      4    len       I
   60      362      5    i       I
   63      34      6    ops       Lscala/util/NameTransformer$OpCodes;
   109      300      6    ops       Lscala/util/NameTransformer$OpCodes;
   63      34      7    unicode       Z
   112      297      7    unicode       Z
   63      34      8    c       C
   120      289      8    c       C
   63      1      9    ch1       C
   146      263      9    ch1       C
   63      1      10    ch2       C
   170      239      10    ch2       C
   63      1      11    hex       Ljava/lang/String;
   349      60      11    hex       Ljava/lang/String;
   359      47      12    str       C


public java.lang.String encode(java.lang.String);
  Code:
   Stack=7, Locals=6, Args_size=2
   0:	aconst_null
   1:	pop
   2:	aconst_null
   3:	astore_2
   4:	aload_1
   5:	invokevirtual	#116; //Method java/lang/String.length:()I
   8:	istore_3
   9:	iconst_0
   10:	istore	4
   12:	iload	4
   14:	iload_3
   15:	if_icmpge	201
   18:	aload_1
   19:	iload	4
   21:	invokevirtual	#143; //Method java/lang/String.charAt:(I)C
   24:	istore	5
   26:	iload	5
   28:	aload_0
   29:	invokespecial	#35; //Method nops:()I
   32:	if_icmpge	101
   35:	aload_0
   36:	invokespecial	#211; //Method op2code:()[Ljava/lang/String;
   39:	getstatic	#216; //Field scala/Predef$.MODULE$:Lscala/Predef$;
   42:	iload	5
   44:	invokevirtual	#220; //Method scala/Predef$.char2int:(C)I
   47:	aaload
   48:	ifnull	101
   51:	aload_2
   52:	ifnonnull	77
   55:	new	#112; //class scala/collection/mutable/StringBuilder
   58:	dup
   59:	invokespecial	#162; //Method scala/collection/mutable/StringBuilder."<init>":()V
   62:	astore_2
   63:	aload_2
   64:	aload_1
   65:	iconst_0
   66:	iload	4
   68:	invokevirtual	#120; //Method java/lang/String.substring:(II)Ljava/lang/String;
   71:	invokevirtual	#165; //Method scala/collection/mutable/StringBuilder.append:(Ljava/lang/String;)Lscala/collection/mutable/StringBuilder;
   74:	goto	80
   77:	getstatic	#139; //Field scala/runtime/BoxedUnit.UNIT:Lscala/runtime/BoxedUnit;
   80:	pop
   81:	aload_2
   82:	aload_0
   83:	invokespecial	#211; //Method op2code:()[Ljava/lang/String;
   86:	getstatic	#216; //Field scala/Predef$.MODULE$:Lscala/Predef$;
   89:	iload	5
   91:	invokevirtual	#220; //Method scala/Predef$.char2int:(C)I
   94:	aaload
   95:	invokevirtual	#165; //Method scala/collection/mutable/StringBuilder.append:(Ljava/lang/String;)Lscala/collection/mutable/StringBuilder;
   98:	goto	191
   101:	iload	5
   103:	invokestatic	#223; //Method java/lang/Character.isJavaIdentifierPart:(C)Z
   106:	ifeq	128
   109:	aload_2
   110:	ifnull	122
   113:	aload_2
   114:	iload	5
   116:	invokevirtual	#133; //Method scala/collection/mutable/StringBuilder.append:(C)Lscala/collection/mutable/StringBuilder;
   119:	goto	191
   122:	getstatic	#139; //Field scala/runtime/BoxedUnit.UNIT:Lscala/runtime/BoxedUnit;
   125:	goto	191
   128:	aload_2
   129:	ifnonnull	154
   132:	new	#112; //class scala/collection/mutable/StringBuilder
   135:	dup
   136:	invokespecial	#162; //Method scala/collection/mutable/StringBuilder."<init>":()V
   139:	astore_2
   140:	aload_2
   141:	aload_1
   142:	iconst_0
   143:	iload	4
   145:	invokevirtual	#120; //Method java/lang/String.substring:(II)Ljava/lang/String;
   148:	invokevirtual	#165; //Method scala/collection/mutable/StringBuilder.append:(Ljava/lang/String;)Lscala/collection/mutable/StringBuilder;
   151:	goto	157
   154:	getstatic	#139; //Field scala/runtime/BoxedUnit.UNIT:Lscala/runtime/BoxedUnit;
   157:	pop
   158:	aload_2
   159:	getstatic	#216; //Field scala/Predef$.MODULE$:Lscala/Predef$;
   162:	ldc	#225; //String $u%04X
   164:	invokevirtual	#229; //Method scala/Predef$.stringWrapper:(Ljava/lang/String;)Lscala/runtime/RichString;
   167:	getstatic	#234; //Field scala/runtime/ScalaRunTime$.MODULE$:Lscala/runtime/ScalaRunTime$;
   170:	iconst_1
   171:	anewarray	#23; //class java/lang/Object
   174:	dup
   175:	iconst_0
   176:	iload	5
   178:	invokestatic	#240; //Method scala/runtime/BoxesRunTime.boxToInteger:(I)Ljava/lang/Integer;
   181:	aastore
   182:	invokevirtual	#244; //Method scala/runtime/ScalaRunTime$.boxArray:(Ljava/lang/Object;)Lscala/runtime/BoxedArray;
   185:	invokevirtual	#250; //Method scala/runtime/RichString.format:(Lscala/collection/Sequence;)Ljava/lang/String;
   188:	invokevirtual	#165; //Method scala/collection/mutable/StringBuilder.append:(Ljava/lang/String;)Lscala/collection/mutable/StringBuilder;
   191:	pop
   192:	iload	4
   194:	iconst_1
   195:	iadd
   196:	istore	4
   198:	goto	12
   201:	aload_2
   202:	ifnonnull	209
   205:	aload_1
   206:	goto	213
   209:	aload_2
   210:	invokevirtual	#187; //Method scala/collection/mutable/StringBuilder.toString:()Ljava/lang/String;
   213:	areturn
  LineNumberTable: 
   line 50: 0
   line 51: 4
   line 52: 9
   line 53: 12
   line 54: 18
   line 55: 26
   line 56: 51
   line 57: 55
   line 58: 63
   line 56: 77
   line 60: 81
   line 63: 101
   line 70: 109
   line 71: 113
   line 70: 122
   line 64: 128
   line 65: 132
   line 66: 140
   line 64: 154
   line 68: 158
   line 55: 191
   line 73: 192
   line 53: 198
   line 75: 201
   line 49: 213

  LocalVariableTable: 
   Start  Length  Slot  Name   Signature
   0      214      0    this       Lscala/util/NameTransformer$;
   0      214      1    name       Ljava/lang/String;
   4      210      2    buf       Lscala/collection/mutable/StringBuilder;
   9      205      3    len       I
   12      202      4    i       I
   26      172      5    c       C


}

