Compiled from "NameTransformer.scala"
public final class scala.util.NameTransformer$ extends java.lang.Object implements scala.ScalaObject
  SourceFile: "NameTransformer.scala"
  Scala: length = 0x
   
  InnerClass: 
   public OpCodes=class scala/util/NameTransformer$OpCodes of class scala/util/NameTransformer
  minor version: 0
  major version: 49
  Constant pool:
Asciz	SourceFile;
Asciz	NameTransformer.scala;
Asciz	Scala;
Asciz	MODULE$;
Asciz	Lscala/util/NameTransformer$;;
Asciz	<clinit>;
Asciz	()V;
Asciz	Code;
Asciz	scala/util/NameTransformer$;
class	scala/util/NameTransformer$
Asciz	<init>;
NameAndType	"<init>":()V
Method	scala/util/NameTransformer$."<init>":()V
Asciz	code2op;
Asciz	[Lscala/util/NameTransformer$OpCodes;;
Asciz	op2code;
Asciz	[Ljava/lang/String;;
Asciz	ncodes;
Asciz	I;
Asciz	nops;
Asciz	LineNumberTable;
Asciz	java/lang/Object;
class	java/lang/Object
Method	java/lang/Object."<init>":()V
NameAndType	MODULE$:Lscala/util/NameTransformer$;
Field	scala/util/NameTransformer$.MODULE$:Lscala/util/NameTransformer$;
int	128;
NameAndType	nops:I
Field	scala/util/NameTransformer$.nops:I
int	676;
NameAndType	ncodes:I
Field	scala/util/NameTransformer$.ncodes:I
Asciz	()I;
NameAndType	nops:()I
Method	scala/util/NameTransformer$.nops:()I
Asciz	java/lang/String;
class	java/lang/String
NameAndType	op2code:[Ljava/lang/String;
Field	scala/util/NameTransformer$.op2code:[Ljava/lang/String;
NameAndType	ncodes:()I
Method	scala/util/NameTransformer$.ncodes:()I
Asciz	scala/util/NameTransformer$OpCodes;
class	scala/util/NameTransformer$OpCodes
NameAndType	code2op:[Lscala/util/NameTransformer$OpCodes;
Field	scala/util/NameTransformer$.code2op:[Lscala/util/NameTransformer$OpCodes;
int	126;
Asciz	$tilde;
String	$tilde
Asciz	enterOp;
Asciz	(CLjava/lang/String;)V;
NameAndType	enterOp:(CLjava/lang/String;)V
Method	scala/util/NameTransformer$.enterOp:(CLjava/lang/String;)V
int	61;
Asciz	$eq;
String	$eq
int	60;
Asciz	$less;
String	$less
int	62;
Asciz	$greater;
String	$greater
int	33;
Asciz	$bang;
String	$bang
int	35;
Asciz	$hash;
String	$hash
int	37;
Asciz	$percent;
String	$percent
int	94;
Asciz	$up;
String	$up
int	38;
Asciz	$amp;
String	$amp
int	124;
Asciz	$bar;
String	$bar
int	42;
Asciz	$times;
String	$times
int	47;
Asciz	$div;
String	$div
int	43;
Asciz	$plus;
String	$plus
int	45;
Asciz	$minus;
String	$minus
int	58;
Asciz	$colon;
String	$colon
int	92;
Asciz	$bslash;
String	$bslash
int	63;
Asciz	$qmark;
String	$qmark
int	64;
Asciz	$at;
String	$at
Asciz	decode;
Asciz	(Ljava/lang/String;)Ljava/lang/String;;
String	<init>
Asciz	endsWith;
Asciz	(Ljava/lang/String;)Z;
NameAndType	endsWith:(Ljava/lang/String;)Z
Method	java/lang/String.endsWith:(Ljava/lang/String;)Z
Asciz	scala/collection/mutable/StringBuilder;
class	scala/collection/mutable/StringBuilder
Method	scala/collection/mutable/StringBuilder."<init>":()V
Asciz	length;
NameAndType	length:()I
Method	java/lang/String.length:()I
Asciz	substring;
Asciz	(II)Ljava/lang/String;;
NameAndType	substring:(II)Ljava/lang/String;
Method	java/lang/String.substring:(II)Ljava/lang/String;
Asciz	append;
Asciz	(Ljava/lang/Object;)Lscala/collection/mutable/StringBuilder;;
NameAndType	append:(Ljava/lang/Object;)Lscala/collection/mutable/StringBuilder;
Method	scala/collection/mutable/StringBuilder.append:(Ljava/lang/Object;)Lscala/collection/mutable/StringBuilder;
Asciz	this;
String	this
Asciz	toString;
Asciz	()Ljava/lang/String;;
NameAndType	toString:()Ljava/lang/String;
Method	scala/collection/mutable/StringBuilder.toString:()Ljava/lang/String;
Asciz	(C)Lscala/collection/mutable/StringBuilder;;
NameAndType	append:(C)Lscala/collection/mutable/StringBuilder;
Method	scala/collection/mutable/StringBuilder.append:(C)Lscala/collection/mutable/StringBuilder;
Asciz	scala/runtime/BoxedUnit;
class	scala/runtime/BoxedUnit
Asciz	UNIT;
Asciz	Lscala/runtime/BoxedUnit;;
NameAndType	UNIT:Lscala/runtime/BoxedUnit;
Field	scala/runtime/BoxedUnit.UNIT:Lscala/runtime/BoxedUnit;
Asciz	charAt;
Asciz	(I)C;
NameAndType	charAt:(I)C
Method	java/lang/String.charAt:(I)C
int	36;
int	97;
int	122;
Asciz	()[Lscala/util/NameTransformer$OpCodes;;
NameAndType	code2op:()[Lscala/util/NameTransformer$OpCodes;
Method	scala/util/NameTransformer$.code2op:()[Lscala/util/NameTransformer$OpCodes;
int	26;
Asciz	code;
NameAndType	code:()Ljava/lang/String;
Method	scala/util/NameTransformer$OpCodes.code:()Ljava/lang/String;
Asciz	startsWith;
Asciz	(Ljava/lang/String;I)Z;
NameAndType	startsWith:(Ljava/lang/String;I)Z
Method	java/lang/String.startsWith:(Ljava/lang/String;I)Z
Asciz	next;
Asciz	()Lscala/util/NameTransformer$OpCodes;;
NameAndType	next:()Lscala/util/NameTransformer$OpCodes;
Method	scala/util/NameTransformer$OpCodes.next:()Lscala/util/NameTransformer$OpCodes;
Method	scala/collection/mutable/StringBuilder."<init>":()V
Asciz	(Ljava/lang/String;)Lscala/collection/mutable/StringBuilder;;
NameAndType	append:(Ljava/lang/String;)Lscala/collection/mutable/StringBuilder;
Method	scala/collection/mutable/StringBuilder.append:(Ljava/lang/String;)Lscala/collection/mutable/StringBuilder;
Asciz	op;
Asciz	()C;
NameAndType	op:()C
Method	scala/util/NameTransformer$OpCodes.op:()C
int	6;
int	117;
Asciz	java/lang/Character;
class	java/lang/Character
Asciz	isDigit;
Asciz	(C)Z;
NameAndType	isDigit:(C)Z
Method	java/lang/Character.isDigit:(C)Z
int	65;
int	70;
int	16;
Asciz	java/lang/Integer;
class	java/lang/Integer
Asciz	parseInt;
Asciz	(Ljava/lang/String;I)I;
NameAndType	parseInt:(Ljava/lang/String;I)I
Method	java/lang/Integer.parseInt:(Ljava/lang/String;I)I
Method	scala/collection/mutable/StringBuilder.toString:()Ljava/lang/String;
Asciz	java/lang/NumberFormatException;
class	java/lang/NumberFormatException
Asciz	name0;
Asciz	Ljava/lang/String;;
Asciz	name;
Asciz	buf;
Asciz	Lscala/collection/mutable/StringBuilder;;
Asciz	len;
Asciz	i;
Asciz	ops;
Asciz	Lscala/util/NameTransformer$OpCodes;;
Asciz	unicode;
Asciz	Z;
Asciz	c;
Asciz	C;
Asciz	ch1;
Asciz	ch2;
Asciz	hex;
Asciz	str;
Asciz	LocalVariableTable;
Asciz	encode;
Asciz	()[Ljava/lang/String;;
NameAndType	op2code:()[Ljava/lang/String;
Method	scala/util/NameTransformer$.op2code:()[Ljava/lang/String;
Asciz	isJavaIdentifierPart;
NameAndType	isJavaIdentifierPart:(C)Z
Method	java/lang/Character.isJavaIdentifierPart:(C)Z
Asciz	$u%04X;
String	$u%04X
Asciz	scala/collection/immutable/StringOps;
class	scala/collection/immutable/StringOps
Asciz	(Ljava/lang/String;)V;
NameAndType	"<init>":(Ljava/lang/String;)V
Method	scala/collection/immutable/StringOps."<init>":(Ljava/lang/String;)V
Asciz	scala/Predef$;
class	scala/Predef$
Asciz	Lscala/Predef$;;
NameAndType	MODULE$:Lscala/Predef$;
Field	scala/Predef$.MODULE$:Lscala/Predef$;
Asciz	scala/runtime/BoxesRunTime;
class	scala/runtime/BoxesRunTime
Asciz	boxToInteger;
Asciz	(I)Ljava/lang/Integer;;
NameAndType	boxToInteger:(I)Ljava/lang/Integer;
Method	scala/runtime/BoxesRunTime.boxToInteger:(I)Ljava/lang/Integer;
Asciz	genericWrapArray;
Asciz	(Ljava/lang/Object;)Lscala/collection/mutable/WrappedArray;;
NameAndType	genericWrapArray:(Ljava/lang/Object;)Lscala/collection/mutable/WrappedArray;
Method	scala/Predef$.genericWrapArray:(Ljava/lang/Object;)Lscala/collection/mutable/WrappedArray;
Asciz	scala/collection/immutable/StringLike;
class	scala/collection/immutable/StringLike
Asciz	format;
Asciz	(Lscala/collection/Seq;)Ljava/lang/String;;
NameAndType	format:(Lscala/collection/Seq;)Ljava/lang/String;
InterfaceMethod	scala/collection/immutable/StringLike.format:(Lscala/collection/Seq;)Ljava/lang/String;
Asciz	(CLjava/lang/String;Lscala/util/NameTransformer$OpCodes;)V;
NameAndType	"<init>":(CLjava/lang/String;Lscala/util/NameTransformer$OpCodes;)V
Method	scala/util/NameTransformer$OpCodes."<init>":(CLjava/lang/String;Lscala/util/NameTransformer$OpCodes;)V
Asciz	InnerClasses;
Asciz	scala/util/NameTransformer;
class	scala/util/NameTransformer
Asciz	OpCodes;
Asciz	scala/ScalaObject;
class	scala/ScalaObject

{
public static final scala.util.NameTransformer$ MODULE$;
  Signature: Lscala/util/NameTransformer$;

private final scala.util.NameTransformer$OpCodes[] code2op;
  Signature: [Lscala/util/NameTransformer$OpCodes;

private final java.lang.String[] op2code;
  Signature: [Ljava/lang/String;

private final int ncodes;
  Signature: I

private final int nops;
  Signature: I

public static {};
  Signature: ()V
  Code:
   Stack=1, Locals=0, Args_size=0
	new	class scala/util/NameTransformer$
	invokespecial	Method "<init>":()V
	return
  Labels:

private scala.util.NameTransformer$();
  Signature: ()V
  Code:
   Stack=3, Locals=1, Args_size=1
	aload_0
	invokespecial	Method java/lang/Object."<init>":()V
	aload_0
	putstatic	Field MODULE$:Lscala/util/NameTransformer$;
	aload_0
	ldc	int 128
	putfield	Field nops:I
	aload_0
	ldc	int 676
	putfield	Field ncodes:I
	aload_0
	aload_0
	invokespecial	Method nops:()I
	anewarray	class java/lang/String
	putfield	Field op2code:[Ljava/lang/String;
	aload_0
	aload_0
	invokespecial	Method ncodes:()I
	anewarray	class scala/util/NameTransformer$OpCodes
	putfield	Field code2op:[Lscala/util/NameTransformer$OpCodes;
	aload_0
	ldc	int 126
	ldc	String $tilde
	invokespecial	Method enterOp:(CLjava/lang/String;)V
	aload_0
	ldc	int 61
	ldc	String $eq
	invokespecial	Method enterOp:(CLjava/lang/String;)V
	aload_0
	ldc	int 60
	ldc	String $less
	invokespecial	Method enterOp:(CLjava/lang/String;)V
	aload_0
	ldc	int 62
	ldc	String $greater
	invokespecial	Method enterOp:(CLjava/lang/String;)V
	aload_0
	ldc	int 33
	ldc	String $bang
	invokespecial	Method enterOp:(CLjava/lang/String;)V
	aload_0
	ldc	int 35
	ldc	String $hash
	invokespecial	Method enterOp:(CLjava/lang/String;)V
	aload_0
	ldc	int 37
	ldc	String $percent
	invokespecial	Method enterOp:(CLjava/lang/String;)V
	aload_0
	ldc	int 94
	ldc	String $up
	invokespecial	Method enterOp:(CLjava/lang/String;)V
	aload_0
	ldc	int 38
	ldc	String $amp
	invokespecial	Method enterOp:(CLjava/lang/String;)V
	aload_0
	ldc	int 124
	ldc	String $bar
	invokespecial	Method enterOp:(CLjava/lang/String;)V
	aload_0
	ldc	int 42
	ldc	String $times
	invokespecial	Method enterOp:(CLjava/lang/String;)V
	aload_0
	ldc	int 47
	ldc	String $div
	invokespecial	Method enterOp:(CLjava/lang/String;)V
	aload_0
	ldc	int 43
	ldc	String $plus
	invokespecial	Method enterOp:(CLjava/lang/String;)V
	aload_0
	ldc	int 45
	ldc	String $minus
	invokespecial	Method enterOp:(CLjava/lang/String;)V
	aload_0
	ldc	int 58
	ldc	String $colon
	invokespecial	Method enterOp:(CLjava/lang/String;)V
	aload_0
	ldc	int 92
	ldc	String $bslash
	invokespecial	Method enterOp:(CLjava/lang/String;)V
	aload_0
	ldc	int 63
	ldc	String $qmark
	invokespecial	Method enterOp:(CLjava/lang/String;)V
	aload_0
	ldc	int 64
	ldc	String $at
	invokespecial	Method enterOp:(CLjava/lang/String;)V
	return
  Labels:

public java.lang.String decode(java.lang.String);
  Signature: (Ljava/lang/String;)Ljava/lang/String;
  Code:
   Stack=5, Locals=13, Args_size=2
	aload_1
	ldc	String <init>
	invokevirtual	Method java/lang/String.endsWith:(Ljava/lang/String;)Z
	ifeq	l1 // aload_1
	new	class scala/collection/mutable/StringBuilder
	dup
	invokespecial	Method scala/collection/mutable/StringBuilder."<init>":()V
	aload_1
	iconst_0
	aload_1
	invokevirtual	Method java/lang/String.length:()I
	ldc	String <init>
	invokevirtual	Method java/lang/String.length:()I
	isub
	invokevirtual	Method java/lang/String.substring:(II)Ljava/lang/String;
	invokevirtual	Method scala/collection/mutable/StringBuilder.append:(Ljava/lang/Object;)Lscala/collection/mutable/StringBuilder;
	ldc	String this
	invokevirtual	Method scala/collection/mutable/StringBuilder.append:(Ljava/lang/Object;)Lscala/collection/mutable/StringBuilder;
	invokevirtual	Method scala/collection/mutable/StringBuilder.toString:()Ljava/lang/String;
	goto	l2 // astore_2
l1	aload_1
l2	astore_2
	aconst_null
	astore_3
	aload_2
	invokevirtual	Method java/lang/String.length:()I
	istore	4
	iconst_0
	istore	5
	goto	l3 // iload
	pop
l7	aload	6
	ifnonnull	l3 // iload
	iload	7
	ifne	l3 // iload
	aload_3
	ifnull	l4 // getstatic
	aload_3
	iload	8
	invokevirtual	Method scala/collection/mutable/StringBuilder.append:(C)Lscala/collection/mutable/StringBuilder;
	goto	l5 // pop
l4	getstatic	Field scala/runtime/BoxedUnit.UNIT:Lscala/runtime/BoxedUnit;
l5	pop
	iload	5
	iconst_1
	iadd
	istore	5
l3	iload	5
	iload	4
	if_icmpge	l6 // aload_3
	aconst_null
	astore	6
	iconst_0
	istore	7
	aload_2
	iload	5
	invokevirtual	Method java/lang/String.charAt:(I)C
	istore	8
	iload	8
	ldc	int 36
	if_icmpne	l7 // aload
	iload	5
	iconst_2
	iadd
	iload	4
	if_icmpge	l7 // aload
	aload_2
	iload	5
	iconst_1
	iadd
	invokevirtual	Method java/lang/String.charAt:(I)C
	istore	9
	ldc	int 97
	iload	9
	if_icmpgt	l7 // aload
	iload	9
	ldc	int 122
	if_icmpgt	l7 // aload
	aload_2
	iload	5
	iconst_2
	iadd
	invokevirtual	Method java/lang/String.charAt:(I)C
	istore	10
	ldc	int 97
	iload	10
	if_icmpgt	l8 // iload
	iload	10
	ldc	int 122
	if_icmpgt	l8 // iload
	aload_0
	invokespecial	Method code2op:()[Lscala/util/NameTransformer$OpCodes;
	iload	9
	ldc	int 97
	isub
	ldc	int 26
	imul
	iload	10
	iadd
	ldc	int 97
	isub
	aaload
	astore	6
l10	aload	6
	ifnull	l9 // aload
	aload_2
	aload	6
	invokevirtual	Method scala/util/NameTransformer$OpCodes.code:()Ljava/lang/String;
	iload	5
	invokevirtual	Method java/lang/String.startsWith:(Ljava/lang/String;I)Z
	ifne	l9 // aload
	aload	6
	invokevirtual	Method scala/util/NameTransformer$OpCodes.next:()Lscala/util/NameTransformer$OpCodes;
	astore	6
	goto	l10 // aload
l9	aload	6
	ifnull	l7 // aload
	aload_3
	ifnonnull	l11 // getstatic
	new	class scala/collection/mutable/StringBuilder
	dup
	invokespecial	Method scala/collection/mutable/StringBuilder."<init>":()V
	astore_3
	aload_3
	aload_2
	iconst_0
	iload	5
	invokevirtual	Method java/lang/String.substring:(II)Ljava/lang/String;
	invokevirtual	Method scala/collection/mutable/StringBuilder.append:(Ljava/lang/String;)Lscala/collection/mutable/StringBuilder;
	goto	l12 // pop
l11	getstatic	Field scala/runtime/BoxedUnit.UNIT:Lscala/runtime/BoxedUnit;
l12	pop
	aload_3
	aload	6
	invokevirtual	Method scala/util/NameTransformer$OpCodes.op:()C
	invokevirtual	Method scala/collection/mutable/StringBuilder.append:(C)Lscala/collection/mutable/StringBuilder;
	pop
	iload	5
	aload	6
	invokevirtual	Method scala/util/NameTransformer$OpCodes.code:()Ljava/lang/String;
	invokevirtual	Method java/lang/String.length:()I
	iadd
	istore	5
	goto	l7 // aload
l8	iload	4
	iload	5
	isub
	ldc	int 6
	if_icmplt	l7 // aload
	iload	9
	ldc	int 117
	if_icmpne	l7 // aload
	iload	10
	invokestatic	Method java/lang/Character.isDigit:(C)Z
	ifne	l13 // aload_2
	ldc	int 65
	iload	10
	if_icmpgt	l7 // aload
	iload	10
	ldc	int 70
	if_icmpgt	l7 // aload
l13	aload_2
	iload	5
	iconst_2
	iadd
	iload	5
	ldc	int 6
	iadd
	invokevirtual	Method java/lang/String.substring:(II)Ljava/lang/String;
	astore	11
	aload	11
	ldc	int 16
	invokestatic	Method java/lang/Integer.parseInt:(Ljava/lang/String;I)I
	i2c
	istore	12
	aload_3
	ifnonnull	l14 // getstatic
	new	class scala/collection/mutable/StringBuilder
	dup
	invokespecial	Method scala/collection/mutable/StringBuilder."<init>":()V
	astore_3
	aload_3
	aload_2
	iconst_0
	iload	5
	invokevirtual	Method java/lang/String.substring:(II)Ljava/lang/String;
	invokevirtual	Method scala/collection/mutable/StringBuilder.append:(Ljava/lang/String;)Lscala/collection/mutable/StringBuilder;
	goto	l15 // pop
l14	getstatic	Field scala/runtime/BoxedUnit.UNIT:Lscala/runtime/BoxedUnit;
l15	pop
	aload_3
	iload	12
	invokevirtual	Method scala/collection/mutable/StringBuilder.append:(C)Lscala/collection/mutable/StringBuilder;
	pop
	iload	5
	ldc	int 6
	iadd
	istore	5
	iconst_1
	istore	7
	goto	l7 // aload
l6	aload_3
	ifnonnull	l16 // aload_3
	aload_2
	goto	l17 // areturn
l16	aload_3
	invokevirtual	Method scala/collection/mutable/StringBuilder.toString:()Ljava/lang/String;
l17	areturn
  Labels:
   	l1 = 45 // aload_1
   	l2 = 46 // astore_2
   	l7 = 62 // aload
   	l4 = 85 // getstatic
   	l5 = 88 // pop
   	l3 = 95 // iload
   	l10 = 201 // aload
   	l9 = 230 // aload
   	l11 = 261 // getstatic
   	l12 = 264 // pop
   	l8 = 291 // iload
   	l13 = 330 // aload_2
   	l14 = 381 // getstatic
   	l15 = 384 // pop
   	l6 = 405 // aload_3
   	l16 = 413 // aload_3
   	l17 = 417 // areturn
  Exception table:
   from   to  target type
   345   405    61   Class java/lang/NumberFormatException

  LocalVariableTable: 
   Start  Length  Slot  Name   Signature
   0      418      0    this       Lscala/util/NameTransformer$;
   0      418      1    name0       Ljava/lang/String;
   47      371      2    name       Ljava/lang/String;
   49      369      3    buf       Lscala/collection/mutable/StringBuilder;
   55      363      4    len       I
   58      360      5    i       I
   61      34      6    ops       Lscala/util/NameTransformer$OpCodes;
   105      300      6    ops       Lscala/util/NameTransformer$OpCodes;
   61      34      7    unicode       Z
   108      297      7    unicode       Z
   61      34      8    c       C
   116      289      8    c       C
   61      1      9    ch1       C
   142      263      9    ch1       C
   61      1      10    ch2       C
   166      239      10    ch2       C
   61      1      11    hex       Ljava/lang/String;
   345      60      11    hex       Ljava/lang/String;
   355      47      12    str       C


public java.lang.String encode(java.lang.String);
  Signature: (Ljava/lang/String;)Ljava/lang/String;
  Code:
   Stack=7, Locals=8, Args_size=2
	aconst_null
	astore	7
	aload_1
	invokevirtual	Method java/lang/String.length:()I
	istore_2
	iconst_0
	istore	6
l10	iload	6
	iload_2
	if_icmpge	l1 // aload
	aload_1
	iload	6
	invokevirtual	Method java/lang/String.charAt:(I)C
	istore	4
	iload	4
	aload_0
	invokespecial	Method nops:()I
	if_icmpge	l2 // iload
	aload_0
	invokespecial	Method op2code:()[Ljava/lang/String;
	iload	4
	aaload
	ifnull	l2 // iload
	aload	7
	ifnonnull	l3 // getstatic
	new	class scala/collection/mutable/StringBuilder
	dup
	invokespecial	Method scala/collection/mutable/StringBuilder."<init>":()V
	astore	7
	aload	7
	aload_1
	iconst_0
	iload	6
	invokevirtual	Method java/lang/String.substring:(II)Ljava/lang/String;
	invokevirtual	Method scala/collection/mutable/StringBuilder.append:(Ljava/lang/String;)Lscala/collection/mutable/StringBuilder;
	goto	l4 // pop
l3	getstatic	Field scala/runtime/BoxedUnit.UNIT:Lscala/runtime/BoxedUnit;
l4	pop
	aload	7
	aload_0
	invokespecial	Method op2code:()[Ljava/lang/String;
	iload	4
	aaload
	invokevirtual	Method scala/collection/mutable/StringBuilder.append:(Ljava/lang/String;)Lscala/collection/mutable/StringBuilder;
	goto	l5 // pop
l2	iload	4
	invokestatic	Method java/lang/Character.isJavaIdentifierPart:(C)Z
	ifeq	l6 // aload
	aload	7
	ifnull	l7 // getstatic
	aload	7
	iload	4
	invokevirtual	Method scala/collection/mutable/StringBuilder.append:(C)Lscala/collection/mutable/StringBuilder;
	goto	l5 // pop
l7	getstatic	Field scala/runtime/BoxedUnit.UNIT:Lscala/runtime/BoxedUnit;
	goto	l5 // pop
l6	aload	7
	ifnonnull	l8 // getstatic
	new	class scala/collection/mutable/StringBuilder
	dup
	invokespecial	Method scala/collection/mutable/StringBuilder."<init>":()V
	astore	7
	aload	7
	aload_1
	iconst_0
	iload	6
	invokevirtual	Method java/lang/String.substring:(II)Ljava/lang/String;
	invokevirtual	Method scala/collection/mutable/StringBuilder.append:(Ljava/lang/String;)Lscala/collection/mutable/StringBuilder;
	goto	l9 // pop
l8	getstatic	Field scala/runtime/BoxedUnit.UNIT:Lscala/runtime/BoxedUnit;
l9	pop
	aload	7
	ldc	String $u%04X
	astore_3
	new	class scala/collection/immutable/StringOps
	dup
	aload_3
	invokespecial	Method scala/collection/immutable/StringOps."<init>":(Ljava/lang/String;)V
	getstatic	Field scala/Predef$.MODULE$:Lscala/Predef$;
	iconst_1
	anewarray	class java/lang/Object
	dup
	iconst_0
	iload	4
	istore	5
	iload	5
	invokestatic	Method scala/runtime/BoxesRunTime.boxToInteger:(I)Ljava/lang/Integer;
	aastore
	invokevirtual	Method scala/Predef$.genericWrapArray:(Ljava/lang/Object;)Lscala/collection/mutable/WrappedArray;
	invokeinterface	InterfaceMethod scala/collection/immutable/StringLike.format:(Lscala/collection/Seq;)Ljava/lang/String;
	invokevirtual	Method scala/collection/mutable/StringBuilder.append:(Ljava/lang/String;)Lscala/collection/mutable/StringBuilder;
l5	pop
	iload	6
	iconst_1
	iadd
	istore	6
	goto	l10 // iload
l1	aload	7
	ifnonnull	l11 // aload
	aload_1
	goto	l12 // areturn
l11	aload	7
	invokevirtual	Method scala/collection/mutable/StringBuilder.toString:()Ljava/lang/String;
l12	areturn
  Labels:
   	l10 = 11 // iload
   	l3 = 73 // getstatic
   	l4 = 76 // pop
   	l2 = 92 // iload
   	l7 = 115 // getstatic
   	l6 = 121 // aload
   	l8 = 150 // getstatic
   	l9 = 153 // pop
   	l5 = 197 // pop
   	l1 = 207 // aload
   	l11 = 216 // aload
   	l12 = 221 // areturn
  LocalVariableTable: 
   Start  Length  Slot  Name   Signature
   0      222      0    this       Lscala/util/NameTransformer$;
   0      222      1    name       Ljava/lang/String;
   8      214      2    len       I
   25      179      4    c       C
   11      211      6    i       I
   3      219      7    buf       Lscala/collection/mutable/StringBuilder;


private void enterOp(char, java.lang.String);
  Signature: (CLjava/lang/String;)V
  Code:
   Stack=8, Locals=4, Args_size=3
	aload_0
	invokespecial	Method op2code:()[Ljava/lang/String;
	iload_1
	aload_2
	aastore
	aload_2
	iconst_1
	invokevirtual	Method java/lang/String.charAt:(I)C
	ldc	int 97
	isub
	ldc	int 26
	imul
	aload_2
	iconst_2
	invokevirtual	Method java/lang/String.charAt:(I)C
	iadd
	ldc	int 97
	isub
	istore_3
	aload_0
	invokespecial	Method code2op:()[Lscala/util/NameTransformer$OpCodes;
	iload_3
	new	class scala/util/NameTransformer$OpCodes
	dup
	iload_1
	aload_2
	aload_0
	invokespecial	Method code2op:()[Lscala/util/NameTransformer$OpCodes;
	iload_3
	aaload
	invokespecial	Method scala/util/NameTransformer$OpCodes."<init>":(CLjava/lang/String;Lscala/util/NameTransformer$OpCodes;)V
	aastore
	return
  Labels:
  LocalVariableTable: 
   Start  Length  Slot  Name   Signature
   0      50      0    this       Lscala/util/NameTransformer$;
   0      50      1    op       C
   0      50      2    code       Ljava/lang/String;
   28      21      3    c       I


private scala.util.NameTransformer$OpCodes[] code2op();
  Signature: ()[Lscala/util/NameTransformer$OpCodes;
  Code:
   Stack=1, Locals=1, Args_size=1
	aload_0
	getfield	Field code2op:[Lscala/util/NameTransformer$OpCodes;
	areturn
  Labels:

private java.lang.String[] op2code();
  Signature: ()[Ljava/lang/String;
  Code:
   Stack=1, Locals=1, Args_size=1
	aload_0
	getfield	Field op2code:[Ljava/lang/String;
	areturn
  Labels:

private int ncodes();
  Signature: ()I
  Code:
   Stack=1, Locals=1, Args_size=1
	aload_0
	getfield	Field ncodes:I
	ireturn
  Labels:

private int nops();
  Signature: ()I
  Code:
   Stack=1, Locals=1, Args_size=1
	aload_0
	getfield	Field nops:I
	ireturn
  Labels:

}

