Compiled from "Properties.scala"
public final class scala.util.PropertiesTrait$$anonfun$isJavaAtLeast$1 extends scala.runtime.AbstractFunction1 implements java.io.Serializable
  SourceFile: "Properties.scala"
  Scala: length = 0x
   
  InnerClass: 
   public final $anonfun$isJavaAtLeast$1=class scala/util/PropertiesTrait$$anonfun$isJavaAtLeast$1 of class scala/util/PropertiesTrait
  minor version: 0
  major version: 49
  Constant pool:
Asciz	SourceFile;
Asciz	Properties.scala;
Asciz	<clinit>;
Asciz	()V;
Asciz	Code;
Asciz	serialVersionUID;
Asciz	J;
Asciz	scala/util/PropertiesTrait$$anonfun$isJavaAtLeast$1;
class	scala/util/PropertiesTrait$$anonfun$isJavaAtLeast$1
NameAndType	serialVersionUID:J
Field	scala/util/PropertiesTrait$$anonfun$isJavaAtLeast$1.serialVersionUID:J
Asciz	$outer;
Asciz	Lscala/util/PropertiesTrait;;
Asciz	apply;
Asciz	(Ljava/lang/String;)Z;
Asciz	LineNumberTable;
NameAndType	$outer:Lscala/util/PropertiesTrait;
Field	scala/util/PropertiesTrait$$anonfun$isJavaAtLeast$1.$outer:Lscala/util/PropertiesTrait;
Asciz	scala/util/PropertiesTrait;
class	scala/util/PropertiesTrait
Asciz	javaVersion;
Asciz	()Ljava/lang/String;;
NameAndType	javaVersion:()Ljava/lang/String;
InterfaceMethod	scala/util/PropertiesTrait.javaVersion:()Ljava/lang/String;
Asciz	java/lang/String;
class	java/lang/String
Asciz	startsWith;
NameAndType	startsWith:(Ljava/lang/String;)Z
Method	java/lang/String.startsWith:(Ljava/lang/String;)Z
Asciz	(Ljava/lang/Object;)Ljava/lang/Object;;
NameAndType	apply:(Ljava/lang/String;)Z
Method	scala/util/PropertiesTrait$$anonfun$isJavaAtLeast$1.apply:(Ljava/lang/String;)Z
Asciz	scala/runtime/BoxesRunTime;
class	scala/runtime/BoxesRunTime
Asciz	boxToBoolean;
Asciz	(Z)Ljava/lang/Boolean;;
NameAndType	boxToBoolean:(Z)Ljava/lang/Boolean;
Method	scala/runtime/BoxesRunTime.boxToBoolean:(Z)Ljava/lang/Boolean;
Asciz	this;
Asciz	Lscala/util/PropertiesTrait$$anonfun$isJavaAtLeast$1;;
Asciz	v1;
Asciz	Ljava/lang/Object;;
Asciz	LocalVariableTable;
Asciz	<init>;
Asciz	(Lscala/util/PropertiesTrait;)V;
Asciz	java/lang/NullPointerException;
class	java/lang/NullPointerException
NameAndType	"<init>":()V
Method	java/lang/NullPointerException."<init>":()V
Asciz	scala/runtime/AbstractFunction1;
class	scala/runtime/AbstractFunction1
Method	scala/runtime/AbstractFunction1."<init>":()V
Asciz	Scala;
Asciz	InnerClasses;
Asciz	$anonfun$isJavaAtLeast$1;
Asciz	java/io/Serializable;
class	java/io/Serializable

{
public static final long serialVersionUID;
  Signature: J

private final scala.util.PropertiesTrait $outer;
  Signature: Lscala/util/PropertiesTrait;

public static {};
  Signature: ()V
  Code:
   Stack=2, Locals=0, Args_size=0
	lconst_0
	putstatic	Field serialVersionUID:J
	return
  Labels:

public final boolean apply(java.lang.String);
  Signature: (Ljava/lang/String;)Z
  Code:
   Stack=2, Locals=2, Args_size=2
	aload_0
	getfield	Field $outer:Lscala/util/PropertiesTrait;
	invokeinterface	InterfaceMethod scala/util/PropertiesTrait.javaVersion:()Ljava/lang/String;
	aload_1
	invokevirtual	Method java/lang/String.startsWith:(Ljava/lang/String;)Z
	ireturn
  Labels:

public final java.lang.Object apply(java.lang.Object);
  Signature: (Ljava/lang/Object;)Ljava/lang/Object;
  Code:
   Stack=2, Locals=2, Args_size=2
	aload_0
	aload_1
	checkcast	class java/lang/String
	invokevirtual	Method apply:(Ljava/lang/String;)Z
	invokestatic	Method scala/runtime/BoxesRunTime.boxToBoolean:(Z)Ljava/lang/Boolean;
	areturn
  Labels:
  LocalVariableTable: 
   Start  Length  Slot  Name   Signature
   0      12      0    this       Lscala/util/PropertiesTrait$$anonfun$isJavaAtLeast$1;
   0      12      1    v1       Ljava/lang/Object;


public scala.util.PropertiesTrait$$anonfun$isJavaAtLeast$1(scala.util.PropertiesTrait);
  Signature: (Lscala/util/PropertiesTrait;)V
  Code:
   Stack=2, Locals=2, Args_size=2
	aload_1
	ifnonnull	l1 // aload_0
	new	class java/lang/NullPointerException
	dup
	invokespecial	Method java/lang/NullPointerException."<init>":()V
	athrow
l1	aload_0
	aload_1
	putfield	Field $outer:Lscala/util/PropertiesTrait;
	aload_0
	invokespecial	Method scala/runtime/AbstractFunction1."<init>":()V
	return
  Labels:
   	l1 = 12 // aload_0
  LocalVariableTable: 
   Start  Length  Slot  Name   Signature
   0      22      0    this       Lscala/util/PropertiesTrait$$anonfun$isJavaAtLeast$1;
   0      22      1    $outer       Lscala/util/PropertiesTrait;


}

