Compiled from "Properties.scala"
public final class scala.util.PropertiesTrait$$anonfun$props$1 extends java.lang.Object implements scala.Function0,scala.ScalaObject,java.io.Serializable
  SourceFile: "Properties.scala"
  Scala: length = 0x
   
  InnerClass: 
   public final $anonfun$props$1=class scala/util/PropertiesTrait$$anonfun$props$1 of class scala/util/PropertiesTrait
  minor version: 0
  major version: 49
  Constant pool:
Asciz	SourceFile;
Asciz	Properties.scala;
Asciz	<clinit>;
Asciz	()V;
Asciz	Code;
Asciz	serialVersionUID;
Asciz	J;
Asciz	scala/util/PropertiesTrait$$anonfun$props$1;
class	scala/util/PropertiesTrait$$anonfun$props$1
NameAndType	serialVersionUID:J
Field	scala/util/PropertiesTrait$$anonfun$props$1.serialVersionUID:J
Asciz	stream$1;
Asciz	Ljava/io/InputStream;;
Asciz	props$1;
Asciz	Ljava/util/Properties;;
Asciz	<init>;
Asciz	(Lscala/util/PropertiesTrait;Ljava/util/Properties;Ljava/io/InputStream;)V;
Asciz	LineNumberTable;
NameAndType	props$1:Ljava/util/Properties;
Field	scala/util/PropertiesTrait$$anonfun$props$1.props$1:Ljava/util/Properties;
NameAndType	stream$1:Ljava/io/InputStream;
Field	scala/util/PropertiesTrait$$anonfun$props$1.stream$1:Ljava/io/InputStream;
Asciz	java/lang/Object;
class	java/lang/Object
NameAndType	"<init>":()V
Method	java/lang/Object."<init>":()V
Asciz	scala/Function0$class;
class	scala/Function0$class
Asciz	$init$;
Asciz	(Lscala/Function0;)V;
NameAndType	$init$:(Lscala/Function0;)V
Method	scala/Function0$class.$init$:(Lscala/Function0;)V
Asciz	this;
Asciz	Lscala/util/PropertiesTrait$$anonfun$props$1;;
Asciz	$outer;
Asciz	Lscala/util/PropertiesTrait;;
Asciz	LocalVariableTable;
Asciz	apply;
Asciz	()Ljava/lang/Object;;
NameAndType	apply:()V
Method	scala/util/PropertiesTrait$$anonfun$props$1.apply:()V
Asciz	scala/runtime/BoxedUnit;
class	scala/runtime/BoxedUnit
Asciz	UNIT;
Asciz	Lscala/runtime/BoxedUnit;;
NameAndType	UNIT:Lscala/runtime/BoxedUnit;
Field	scala/runtime/BoxedUnit.UNIT:Lscala/runtime/BoxedUnit;
Asciz	java/util/Properties;
class	java/util/Properties
Asciz	load;
Asciz	(Ljava/io/InputStream;)V;
NameAndType	load:(Ljava/io/InputStream;)V
Method	java/util/Properties.load:(Ljava/io/InputStream;)V
Asciz	toString;
Asciz	()Ljava/lang/String;;
Asciz	(Lscala/Function0;)Ljava/lang/String;;
NameAndType	toString:(Lscala/Function0;)Ljava/lang/String;
Method	scala/Function0$class.toString:(Lscala/Function0;)Ljava/lang/String;
Asciz	Scala;
Asciz	InnerClasses;
Asciz	scala/util/PropertiesTrait;
class	scala/util/PropertiesTrait
Asciz	$anonfun$props$1;
Asciz	scala/Function0;
class	scala/Function0
Asciz	scala/ScalaObject;
class	scala/ScalaObject
Asciz	java/io/Serializable;
class	java/io/Serializable

{
public static final long serialVersionUID;
  Signature: J

private final java.io.InputStream stream$1;
  Signature: Ljava/io/InputStream;

private final java.util.Properties props$1;
  Signature: Ljava/util/Properties;

public static {};
  Signature: ()V
  Code:
   Stack=2, Locals=0, Args_size=0
	lconst_0
	putstatic	Field serialVersionUID:J
	return
  Labels:

public scala.util.PropertiesTrait$$anonfun$props$1(scala.util.PropertiesTrait, java.util.Properties, java.io.InputStream);
  Signature: (Lscala/util/PropertiesTrait;Ljava/util/Properties;Ljava/io/InputStream;)V
  Code:
   Stack=2, Locals=4, Args_size=4
	aload_0
	aload_2
	putfield	Field props$1:Ljava/util/Properties;
	aload_0
	aload_3
	putfield	Field stream$1:Ljava/io/InputStream;
	aload_0
	invokespecial	Method java/lang/Object."<init>":()V
	aload_0
	invokestatic	Method scala/Function0$class.$init$:(Lscala/Function0;)V
	return
  Labels:
  LocalVariableTable: 
   Start  Length  Slot  Name   Signature
   0      19      0    this       Lscala/util/PropertiesTrait$$anonfun$props$1;
   0      19      1    $outer       Lscala/util/PropertiesTrait;


public final java.lang.Object apply();
  Signature: ()Ljava/lang/Object;
  Code:
   Stack=1, Locals=1, Args_size=1
	aload_0
	invokevirtual	Method apply:()V
	getstatic	Field scala/runtime/BoxedUnit.UNIT:Lscala/runtime/BoxedUnit;
	areturn
  Labels:

public final void apply();
  Signature: ()V
  Code:
   Stack=2, Locals=1, Args_size=1
	aload_0
	getfield	Field props$1:Ljava/util/Properties;
	aload_0
	getfield	Field stream$1:Ljava/io/InputStream;
	invokevirtual	Method java/util/Properties.load:(Ljava/io/InputStream;)V
	return
  Labels:

public java.lang.String toString();
  Signature: ()Ljava/lang/String;
  Code:
   Stack=1, Locals=1, Args_size=1
	aload_0
	invokestatic	Method scala/Function0$class.toString:(Lscala/Function0;)Ljava/lang/String;
	areturn
  Labels:

}

