Compiled from "Properties.scala"
public final class scala.util.PropertiesTrait$$anonfun$propOrFalse$1 extends scala.runtime.AbstractFunction1 implements java.io.Serializable
  SourceFile: "Properties.scala"
  Scala: length = 0x
   
  InnerClass: 
   public final $anonfun$propOrFalse$1=class scala/util/PropertiesTrait$$anonfun$propOrFalse$1 of class scala/util/PropertiesTrait
  minor version: 0
  major version: 49
  Constant pool:
Asciz	SourceFile;
Asciz	Properties.scala;
Asciz	<clinit>;
Asciz	()V;
Asciz	Code;
Asciz	serialVersionUID;
Asciz	J;
Asciz	scala/util/PropertiesTrait$$anonfun$propOrFalse$1;
class	scala/util/PropertiesTrait$$anonfun$propOrFalse$1
NameAndType	serialVersionUID:J
Field	scala/util/PropertiesTrait$$anonfun$propOrFalse$1.serialVersionUID:J
Asciz	apply;
Asciz	(Ljava/lang/String;)Z;
Asciz	scala/collection/immutable/List$;
class	scala/collection/immutable/List$
Asciz	MODULE$;
Asciz	Lscala/collection/immutable/List$;;
NameAndType	MODULE$:Lscala/collection/immutable/List$;
Field	scala/collection/immutable/List$.MODULE$:Lscala/collection/immutable/List$;
Asciz	LineNumberTable;
Asciz	scala/Predef$;
class	scala/Predef$
Asciz	Lscala/Predef$;;
NameAndType	MODULE$:Lscala/Predef$;
Field	scala/Predef$.MODULE$:Lscala/Predef$;
Asciz	java/lang/String;
class	java/lang/String
Asciz	yes;
String	yes
Asciz	on;
String	on
Asciz	true;
String	true
Asciz	[Ljava/lang/Object;;
class	"[Ljava/lang/Object;"
Asciz	wrapRefArray;
Asciz	([Ljava/lang/Object;)Lscala/collection/mutable/WrappedArray;;
NameAndType	wrapRefArray:([Ljava/lang/Object;)Lscala/collection/mutable/WrappedArray;
Method	scala/Predef$.wrapRefArray:([Ljava/lang/Object;)Lscala/collection/mutable/WrappedArray;
Asciz	(Lscala/collection/Seq;)Lscala/collection/immutable/List;;
NameAndType	apply:(Lscala/collection/Seq;)Lscala/collection/immutable/List;
Method	scala/collection/immutable/List$.apply:(Lscala/collection/Seq;)Lscala/collection/immutable/List;
Asciz	toLowerCase;
Asciz	()Ljava/lang/String;;
NameAndType	toLowerCase:()Ljava/lang/String;
Method	java/lang/String.toLowerCase:()Ljava/lang/String;
Asciz	scala/collection/SeqLike;
class	scala/collection/SeqLike
Asciz	contains;
Asciz	(Ljava/lang/Object;)Z;
NameAndType	contains:(Ljava/lang/Object;)Z
InterfaceMethod	scala/collection/SeqLike.contains:(Ljava/lang/Object;)Z
Asciz	this;
Asciz	Lscala/util/PropertiesTrait$$anonfun$propOrFalse$1;;
Asciz	x;
Asciz	Ljava/lang/String;;
Asciz	LocalVariableTable;
Asciz	(Ljava/lang/Object;)Ljava/lang/Object;;
NameAndType	apply:(Ljava/lang/String;)Z
Method	scala/util/PropertiesTrait$$anonfun$propOrFalse$1.apply:(Ljava/lang/String;)Z
Asciz	scala/runtime/BoxesRunTime;
class	scala/runtime/BoxesRunTime
Asciz	boxToBoolean;
Asciz	(Z)Ljava/lang/Boolean;;
NameAndType	boxToBoolean:(Z)Ljava/lang/Boolean;
Method	scala/runtime/BoxesRunTime.boxToBoolean:(Z)Ljava/lang/Boolean;
Asciz	v1;
Asciz	Ljava/lang/Object;;
Asciz	<init>;
Asciz	(Lscala/util/PropertiesTrait;)V;
Asciz	scala/runtime/AbstractFunction1;
class	scala/runtime/AbstractFunction1
NameAndType	"<init>":()V
Method	scala/runtime/AbstractFunction1."<init>":()V
Asciz	$outer;
Asciz	Lscala/util/PropertiesTrait;;
Asciz	Scala;
Asciz	InnerClasses;
Asciz	scala/util/PropertiesTrait;
class	scala/util/PropertiesTrait
Asciz	$anonfun$propOrFalse$1;
Asciz	java/io/Serializable;
class	java/io/Serializable

{
public static final long serialVersionUID;
  Signature: J

public static {};
  Signature: ()V
  Code:
   Stack=2, Locals=0, Args_size=0
	lconst_0
	putstatic	Field serialVersionUID:J
	return
  Labels:

public final boolean apply(java.lang.String);
  Signature: (Ljava/lang/String;)Z
  Code:
   Stack=6, Locals=2, Args_size=2
	getstatic	Field scala/collection/immutable/List$.MODULE$:Lscala/collection/immutable/List$;
	getstatic	Field scala/Predef$.MODULE$:Lscala/Predef$;
	iconst_3
	anewarray	class java/lang/String
	dup
	iconst_0
	ldc	String yes
	aastore
	dup
	iconst_1
	ldc	String on
	aastore
	dup
	iconst_2
	ldc	String true
	aastore
	checkcast	class "[Ljava/lang/Object;"
	invokevirtual	Method scala/Predef$.wrapRefArray:([Ljava/lang/Object;)Lscala/collection/mutable/WrappedArray;
	invokevirtual	Method scala/collection/immutable/List$.apply:(Lscala/collection/Seq;)Lscala/collection/immutable/List;
	aload_1
	invokevirtual	Method java/lang/String.toLowerCase:()Ljava/lang/String;
	invokeinterface	InterfaceMethod scala/collection/SeqLike.contains:(Ljava/lang/Object;)Z
	ireturn
  Labels:
  LocalVariableTable: 
   Start  Length  Slot  Name   Signature
   0      44      0    this       Lscala/util/PropertiesTrait$$anonfun$propOrFalse$1;
   0      44      1    x       Ljava/lang/String;


public final java.lang.Object apply(java.lang.Object);
  Signature: (Ljava/lang/Object;)Ljava/lang/Object;
  Code:
   Stack=2, Locals=3, Args_size=2
	aload_0
	aload_1
	checkcast	class java/lang/String
	invokevirtual	Method apply:(Ljava/lang/String;)Z
	istore_2
	iload_2
	invokestatic	Method scala/runtime/BoxesRunTime.boxToBoolean:(Z)Ljava/lang/Boolean;
	areturn
  Labels:
  LocalVariableTable: 
   Start  Length  Slot  Name   Signature
   0      14      0    this       Lscala/util/PropertiesTrait$$anonfun$propOrFalse$1;
   0      14      1    v1       Ljava/lang/Object;


public scala.util.PropertiesTrait$$anonfun$propOrFalse$1(scala.util.PropertiesTrait);
  Signature: (Lscala/util/PropertiesTrait;)V
  Code:
   Stack=1, Locals=2, Args_size=2
	aload_0
	invokespecial	Method scala/runtime/AbstractFunction1."<init>":()V
	return
  Labels:
  LocalVariableTable: 
   Start  Length  Slot  Name   Signature
   0      5      0    this       Lscala/util/PropertiesTrait$$anonfun$propOrFalse$1;
   0      5      1    $outer       Lscala/util/PropertiesTrait;


}

