Compiled from "Random.scala"
public final class scala.util.Random$$anonfun$nextASCIIString$1 extends scala.runtime.AbstractFunction0 implements java.io.Serializable
  SourceFile: "Random.scala"
  Scala: length = 0x
   
  InnerClass: 
   public final #55= #9 of #48; //$anonfun$nextASCIIString$1=class scala/util/Random$$anonfun$nextASCIIString$1 of class scala/util/Random
  minor version: 0
  major version: 49
  Constant pool:
const #1 = Asciz	SourceFile;
const #2 = Asciz	Random.scala;
const #3 = Asciz	<clinit>;
const #4 = Asciz	()V;
const #5 = Asciz	Code;
const #6 = Asciz	serialVersionUID;
const #7 = Asciz	J;
const #8 = Asciz	scala/util/Random$$anonfun$nextASCIIString$1;
const #9 = class	#8;	//  scala/util/Random$$anonfun$nextASCIIString$1
const #10 = NameAndType	#6:#7;//  serialVersionUID:J
const #11 = Field	#9.#10;	//  scala/util/Random$$anonfun$nextASCIIString$1.serialVersionUID:J
const #12 = Asciz	max$1;
const #13 = Asciz	I;
const #14 = Asciz	min$1;
const #15 = Asciz	$outer;
const #16 = Asciz	Lscala/util/Random;;
const #17 = Asciz	<init>;
const #18 = Asciz	(Lscala/util/Random;II)V;
const #19 = Asciz	LineNumberTable;
const #20 = Asciz	java/lang/NullPointerException;
const #21 = class	#20;	//  java/lang/NullPointerException
const #22 = NameAndType	#17:#4;//  "<init>":()V
const #23 = Method	#21.#22;	//  java/lang/NullPointerException."<init>":()V
const #24 = NameAndType	#15:#16;//  $outer:Lscala/util/Random;
const #25 = Field	#9.#24;	//  scala/util/Random$$anonfun$nextASCIIString$1.$outer:Lscala/util/Random;
const #26 = NameAndType	#14:#13;//  min$1:I
const #27 = Field	#9.#26;	//  scala/util/Random$$anonfun$nextASCIIString$1.min$1:I
const #28 = NameAndType	#12:#13;//  max$1:I
const #29 = Field	#9.#28;	//  scala/util/Random$$anonfun$nextASCIIString$1.max$1:I
const #30 = Asciz	scala/runtime/AbstractFunction0;
const #31 = class	#30;	//  scala/runtime/AbstractFunction0
const #32 = Method	#31.#22;	//  scala/runtime/AbstractFunction0."<init>":()V
const #33 = Asciz	this;
const #34 = Asciz	Lscala/util/Random$$anonfun$nextASCIIString$1;;
const #35 = Asciz	LocalVariableTable;
const #36 = Asciz	apply;
const #37 = Asciz	()Ljava/lang/Object;;
const #38 = Asciz	()B;
const #39 = NameAndType	#36:#38;//  apply:()B
const #40 = Method	#9.#39;	//  scala/util/Random$$anonfun$nextASCIIString$1.apply:()B
const #41 = Asciz	scala/runtime/BoxesRunTime;
const #42 = class	#41;	//  scala/runtime/BoxesRunTime
const #43 = Asciz	boxToByte;
const #44 = Asciz	(B)Ljava/lang/Byte;;
const #45 = NameAndType	#43:#44;//  boxToByte:(B)Ljava/lang/Byte;
const #46 = Method	#42.#45;	//  scala/runtime/BoxesRunTime.boxToByte:(B)Ljava/lang/Byte;
const #47 = Asciz	scala/util/Random;
const #48 = class	#47;	//  scala/util/Random
const #49 = Asciz	nextDigit$1;
const #50 = Asciz	(II)I;
const #51 = NameAndType	#49:#50;//  nextDigit$1:(II)I
const #52 = Method	#48.#51;	//  scala/util/Random.nextDigit$1:(II)I
const #53 = Asciz	Scala;
const #54 = Asciz	InnerClasses;
const #55 = Asciz	$anonfun$nextASCIIString$1;
const #56 = Asciz	java/io/Serializable;
const #57 = class	#56;	//  java/io/Serializable

{
public static final long serialVersionUID;

public final int max$1;

public final int min$1;

public final scala.util.Random $outer;

public static {};
  Code:
   Stack=2, Locals=0, Args_size=0
   0:	lconst_0
   1:	putstatic	#11; //Field serialVersionUID:J
   4:	return

public scala.util.Random$$anonfun$nextASCIIString$1(scala.util.Random, int, int);
  Code:
   Stack=2, Locals=4, Args_size=4
   0:	aload_1
   1:	ifnonnull	12
   4:	new	#21; //class java/lang/NullPointerException
   7:	dup
   8:	invokespecial	#23; //Method java/lang/NullPointerException."<init>":()V
   11:	athrow
   12:	aload_0
   13:	aload_1
   14:	putfield	#25; //Field $outer:Lscala/util/Random;
   17:	aload_0
   18:	iload_2
   19:	putfield	#27; //Field min$1:I
   22:	aload_0
   23:	iload_3
   24:	putfield	#29; //Field max$1:I
   27:	aload_0
   28:	invokespecial	#32; //Method scala/runtime/AbstractFunction0."<init>":()V
   31:	return
  LineNumberTable: 
   line 99: 0

  LocalVariableTable: 
   Start  Length  Slot  Name   Signature
   0      32      0    this       Lscala/util/Random$$anonfun$nextASCIIString$1;
   0      32      1    $outer       Lscala/util/Random;


public final java.lang.Object apply();
  Code:
   Stack=1, Locals=2, Args_size=1
   0:	aload_0
   1:	invokevirtual	#40; //Method apply:()B
   4:	istore_1
   5:	iload_1
   6:	invokestatic	#46; //Method scala/runtime/BoxesRunTime.boxToByte:(B)Ljava/lang/Byte;
   9:	areturn
  LineNumberTable: 
   line 99: 0


public final byte apply();
  Code:
   Stack=3, Locals=1, Args_size=1
   0:	aload_0
   1:	getfield	#25; //Field $outer:Lscala/util/Random;
   4:	aload_0
   5:	getfield	#27; //Field min$1:I
   8:	aload_0
   9:	getfield	#29; //Field max$1:I
   12:	invokevirtual	#52; //Method scala/util/Random.nextDigit$1:(II)I
   15:	i2b
   16:	ireturn
  LineNumberTable: 
   line 99: 0


}

