Compiled from "Random.scala"
public final class scala.util.Random$ extends scala.util.Random implements scala.ScalaObject
  SourceFile: "Random.scala"
  Scala: length = 0x
   
  InnerClass: 
   public final Cons=class scala/collection/immutable/Stream$Cons of class scala/collection/immutable/Stream
   public Inclusive=class scala/collection/immutable/Range$Inclusive of class scala/collection/immutable/Range
   public final $anonfun$shuffle$1=class scala/util/Random$$anonfun$shuffle$1 of class scala/util/Random
   public final $anonfun$nextString$1=class scala/util/Random$$anonfun$nextString$1 of class scala/util/Random
   public final $anonfun$continually$1=class scala/collection/immutable/Stream$$anonfun$continually$1 of class scala/collection/immutable/Stream
   public final $anonfun$alphanumeric$2=class scala/util/Random$$anonfun$alphanumeric$2 of class scala/util/Random
   public final $anonfun$alphanumeric$1=class scala/util/Random$$anonfun$alphanumeric$1 of class scala/util/Random
  minor version: 0
  major version: 49
  Constant pool:
Asciz	SourceFile;
Asciz	Random.scala;
Asciz	MODULE$;
Asciz	Lscala/util/Random$;;
Asciz	<clinit>;
Asciz	()V;
Asciz	Code;
Asciz	scala/util/Random$;
class	scala/util/Random$
Asciz	<init>;
NameAndType	"<init>":()V
Method	scala/util/Random$."<init>":()V
Asciz	alphanumeric;
Asciz	()Lscala/collection/immutable/Stream;;
Asciz	scala/util/Random$$anonfun$alphanumeric$1;
class	scala/util/Random$$anonfun$alphanumeric$1
Asciz	LineNumberTable;
Method	scala/util/Random$$anonfun$alphanumeric$1."<init>":()V
Asciz	scala/collection/immutable/Stream$Cons;
class	scala/collection/immutable/Stream$Cons
NameAndType	MODULE$:Lscala/util/Random$;
Field	scala/util/Random$.MODULE$:Lscala/util/Random$;
Asciz	nextPrintableChar;
Asciz	()C;
NameAndType	nextPrintableChar:()C
Method	scala/util/Random$.nextPrintableChar:()C
Asciz	scala/runtime/BoxesRunTime;
class	scala/runtime/BoxesRunTime
Asciz	boxToCharacter;
Asciz	(C)Ljava/lang/Character;;
NameAndType	boxToCharacter:(C)Ljava/lang/Character;
Method	scala/runtime/BoxesRunTime.boxToCharacter:(C)Ljava/lang/Character;
Asciz	scala/collection/immutable/Stream$$anonfun$continually$1;
class	scala/collection/immutable/Stream$$anonfun$continually$1
Asciz	(Lscala/Function0;)V;
NameAndType	"<init>":(Lscala/Function0;)V
Method	scala/collection/immutable/Stream$$anonfun$continually$1."<init>":(Lscala/Function0;)V
Asciz	(Ljava/lang/Object;Lscala/Function0;)V;
NameAndType	"<init>":(Ljava/lang/Object;Lscala/Function0;)V
Method	scala/collection/immutable/Stream$Cons."<init>":(Ljava/lang/Object;Lscala/Function0;)V
Asciz	scala/util/Random$$anonfun$alphanumeric$2;
class	scala/util/Random$$anonfun$alphanumeric$2
Method	scala/util/Random$$anonfun$alphanumeric$2."<init>":()V
Asciz	scala/collection/immutable/Stream;
class	scala/collection/immutable/Stream
Asciz	filter;
Asciz	(Lscala/Function1;)Lscala/collection/immutable/Stream;;
NameAndType	filter:(Lscala/Function1;)Lscala/collection/immutable/Stream;
Method	scala/collection/immutable/Stream.filter:(Lscala/Function1;)Lscala/collection/immutable/Stream;
Asciz	this;
Asciz	LocalVariableTable;
Asciz	()Lscala/collection/immutable/Stream<Ljava/lang/Character;>;;
Asciz	Signature;
Asciz	shuffle;
Asciz	(Lscala/collection/TraversableOnce;Lscala/collection/generic/CanBuildFrom;)Lscala/collection/TraversableOnce;;
Asciz	scala/collection/mutable/ArrayBuffer;
class	scala/collection/mutable/ArrayBuffer
Method	scala/collection/mutable/ArrayBuffer."<init>":()V
Asciz	$plus$plus$eq;
Asciz	(Lscala/collection/TraversableOnce;)Lscala/collection/mutable/ArrayBuffer;;
NameAndType	$plus$plus$eq:(Lscala/collection/TraversableOnce;)Lscala/collection/mutable/ArrayBuffer;
Method	scala/collection/mutable/ArrayBuffer.$plus$plus$eq:(Lscala/collection/TraversableOnce;)Lscala/collection/mutable/ArrayBuffer;
Asciz	scala/Predef$;
class	scala/Predef$
Asciz	Lscala/Predef$;;
NameAndType	MODULE$:Lscala/Predef$;
Field	scala/Predef$.MODULE$:Lscala/Predef$;
Asciz	scala/collection/mutable/ResizableArray;
class	scala/collection/mutable/ResizableArray
Asciz	length;
Asciz	()I;
NameAndType	length:()I
InterfaceMethod	scala/collection/mutable/ResizableArray.length:()I
Asciz	intWrapper;
Asciz	(I)Lscala/runtime/RichInt;;
NameAndType	intWrapper:(I)Lscala/runtime/RichInt;
Method	scala/Predef$.intWrapper:(I)Lscala/runtime/RichInt;
Asciz	scala/runtime/RichInt;
class	scala/runtime/RichInt
Asciz	to;
Asciz	(I)Lscala/collection/immutable/Range$Inclusive;;
NameAndType	to:(I)Lscala/collection/immutable/Range$Inclusive;
Method	scala/runtime/RichInt.to:(I)Lscala/collection/immutable/Range$Inclusive;
Asciz	scala/collection/immutable/Range$Inclusive;
class	scala/collection/immutable/Range$Inclusive
Asciz	by;
Asciz	(I)Lscala/collection/immutable/Range;;
NameAndType	by:(I)Lscala/collection/immutable/Range;
Method	scala/collection/immutable/Range$Inclusive.by:(I)Lscala/collection/immutable/Range;
Asciz	scala/util/Random$$anonfun$shuffle$1;
class	scala/util/Random$$anonfun$shuffle$1
Asciz	(Lscala/collection/mutable/ArrayBuffer;)V;
NameAndType	"<init>":(Lscala/collection/mutable/ArrayBuffer;)V
Method	scala/util/Random$$anonfun$shuffle$1."<init>":(Lscala/collection/mutable/ArrayBuffer;)V
Asciz	scala/collection/immutable/Range;
class	scala/collection/immutable/Range
Asciz	foreach$mVc$sp;
Asciz	(Lscala/Function1;)V;
NameAndType	foreach$mVc$sp:(Lscala/Function1;)V
Method	scala/collection/immutable/Range.foreach$mVc$sp:(Lscala/Function1;)V
Asciz	scala/collection/generic/CanBuildFrom;
class	scala/collection/generic/CanBuildFrom
Asciz	apply;
Asciz	(Ljava/lang/Object;)Lscala/collection/mutable/Builder;;
NameAndType	apply:(Ljava/lang/Object;)Lscala/collection/mutable/Builder;
InterfaceMethod	scala/collection/generic/CanBuildFrom.apply:(Ljava/lang/Object;)Lscala/collection/mutable/Builder;
Asciz	scala/collection/generic/Growable;
class	scala/collection/generic/Growable
Asciz	(Lscala/collection/TraversableOnce;)Lscala/collection/generic/Growable;;
NameAndType	$plus$plus$eq:(Lscala/collection/TraversableOnce;)Lscala/collection/generic/Growable;
InterfaceMethod	scala/collection/generic/Growable.$plus$plus$eq:(Lscala/collection/TraversableOnce;)Lscala/collection/generic/Growable;
Asciz	scala/collection/mutable/Builder;
class	scala/collection/mutable/Builder
Asciz	result;
Asciz	()Ljava/lang/Object;;
NameAndType	result:()Ljava/lang/Object;
InterfaceMethod	scala/collection/mutable/Builder.result:()Ljava/lang/Object;
Asciz	scala/collection/TraversableOnce;
class	scala/collection/TraversableOnce
Asciz	xs;
Asciz	Lscala/collection/TraversableOnce;;
Asciz	bf;
Asciz	Lscala/collection/generic/CanBuildFrom;;
Asciz	buf$1;
Asciz	Lscala/collection/mutable/ArrayBuffer;;
Asciz	<T:Ljava/lang/Object;CC::Lscala/collection/TraversableOnce<Ljava/lang/Object;>;>(TCC;Lscala/collection/generic/CanBuildFrom<TCC;TT;TCC;>;)TCC;;
Asciz	isAlphaNum$1;
Asciz	(C)Z;
int	65;
int	90;
int	97;
int	122;
int	48;
int	57;
Asciz	c;
Asciz	C;
Asciz	swap$1;
Asciz	(IILscala/collection/mutable/ArrayBuffer;)V;
Asciz	(I)Ljava/lang/Object;;
NameAndType	apply:(I)Ljava/lang/Object;
InterfaceMethod	scala/collection/mutable/ResizableArray.apply:(I)Ljava/lang/Object;
Asciz	update;
Asciz	(ILjava/lang/Object;)V;
NameAndType	update:(ILjava/lang/Object;)V
InterfaceMethod	scala/collection/mutable/ResizableArray.update:(ILjava/lang/Object;)V
Asciz	i1;
Asciz	I;
Asciz	i2;
Asciz	tmp;
Asciz	Ljava/lang/Object;;
Asciz	scala/util/Random;
class	scala/util/Random
Method	scala/util/Random."<init>":()V
Asciz	Scala;
Asciz	InnerClasses;
Asciz	Cons;
Asciz	Inclusive;
Asciz	$anonfun$shuffle$1;
Asciz	scala/util/Random$$anonfun$nextString$1;
class	scala/util/Random$$anonfun$nextString$1
Asciz	$anonfun$nextString$1;
Asciz	$anonfun$continually$1;
Asciz	$anonfun$alphanumeric$2;
Asciz	$anonfun$alphanumeric$1;
Asciz	scala/ScalaObject;
class	scala/ScalaObject

{
public static final scala.util.Random$ MODULE$;
  Signature: Lscala/util/Random$;

public static {};
  Signature: ()V
  Code:
   Stack=1, Locals=0, Args_size=0
	new	class scala/util/Random$
	invokespecial	Method "<init>":()V
	return
  Labels:

public scala.collection.immutable.Stream alphanumeric();
  Signature: ()Lscala/collection/immutable/Stream;
  Code:
   Stack=6, Locals=3, Args_size=1
	new	class scala/util/Random$$anonfun$alphanumeric$1
	dup
	invokespecial	Method scala/util/Random$$anonfun$alphanumeric$1."<init>":()V
	astore_2
	new	class scala/collection/immutable/Stream$Cons
	dup
	getstatic	Field MODULE$:Lscala/util/Random$;
	invokevirtual	Method nextPrintableChar:()C
	istore_1
	iload_1
	invokestatic	Method scala/runtime/BoxesRunTime.boxToCharacter:(C)Ljava/lang/Character;
	new	class scala/collection/immutable/Stream$$anonfun$continually$1
	dup
	aload_2
	invokespecial	Method scala/collection/immutable/Stream$$anonfun$continually$1."<init>":(Lscala/Function0;)V
	invokespecial	Method scala/collection/immutable/Stream$Cons."<init>":(Ljava/lang/Object;Lscala/Function0;)V
	new	class scala/util/Random$$anonfun$alphanumeric$2
	dup
	invokespecial	Method scala/util/Random$$anonfun$alphanumeric$2."<init>":()V
	invokevirtual	Method scala/collection/immutable/Stream.filter:(Lscala/Function1;)Lscala/collection/immutable/Stream;
	areturn
  Labels:
  LocalVariableTable: 
   Start  Length  Slot  Name   Signature
   0      45      0    this       Lscala/util/Random$;

  Signature: length = 0x2
   00 34 

public scala.collection.TraversableOnce shuffle(scala.collection.TraversableOnce, scala.collection.generic.CanBuildFrom);
  Signature: (Lscala/collection/TraversableOnce;Lscala/collection/generic/CanBuildFrom;)Lscala/collection/TraversableOnce;
  Code:
   Stack=4, Locals=4, Args_size=3
	new	class scala/collection/mutable/ArrayBuffer
	dup
	invokespecial	Method scala/collection/mutable/ArrayBuffer."<init>":()V
	aload_1
	invokevirtual	Method scala/collection/mutable/ArrayBuffer.$plus$plus$eq:(Lscala/collection/TraversableOnce;)Lscala/collection/mutable/ArrayBuffer;
	astore_3
	getstatic	Field scala/Predef$.MODULE$:Lscala/Predef$;
	aload_3
	invokeinterface	InterfaceMethod scala/collection/mutable/ResizableArray.length:()I
	invokevirtual	Method scala/Predef$.intWrapper:(I)Lscala/runtime/RichInt;
	iconst_2
	invokevirtual	Method scala/runtime/RichInt.to:(I)Lscala/collection/immutable/Range$Inclusive;
	iconst_m1
	invokevirtual	Method scala/collection/immutable/Range$Inclusive.by:(I)Lscala/collection/immutable/Range;
	new	class scala/util/Random$$anonfun$shuffle$1
	dup
	aload_3
	invokespecial	Method scala/util/Random$$anonfun$shuffle$1."<init>":(Lscala/collection/mutable/ArrayBuffer;)V
	invokevirtual	Method scala/collection/immutable/Range.foreach$mVc$sp:(Lscala/Function1;)V
	aload_2
	aload_1
	invokeinterface	InterfaceMethod scala/collection/generic/CanBuildFrom.apply:(Ljava/lang/Object;)Lscala/collection/mutable/Builder;
	aload_3
	invokeinterface	InterfaceMethod scala/collection/generic/Growable.$plus$plus$eq:(Lscala/collection/TraversableOnce;)Lscala/collection/generic/Growable;
	checkcast	class scala/collection/mutable/Builder
	invokeinterface	InterfaceMethod scala/collection/mutable/Builder.result:()Ljava/lang/Object;
	checkcast	class scala/collection/TraversableOnce
	areturn
  Labels:
  LocalVariableTable: 
   Start  Length  Slot  Name   Signature
   0      68      0    this       Lscala/util/Random$;
   0      68      1    xs       Lscala/collection/TraversableOnce;
   0      68      2    bf       Lscala/collection/generic/CanBuildFrom;
   12      55      3    buf$1       Lscala/collection/mutable/ArrayBuffer;

  Signature: length = 0x2
   00 7E 

public final boolean isAlphaNum$1(char);
  Signature: (C)Z
  Code:
   Stack=2, Locals=2, Args_size=2
	iload_1
	ldc	int 65
	if_icmplt	l1 // iload_1
	iload_1
	ldc	int 90
	if_icmple	l2 // iconst_1
l1	iload_1
	ldc	int 97
	if_icmplt	l3 // iload_1
	iload_1
	ldc	int 122
	if_icmple	l2 // iconst_1
l3	iload_1
	ldc	int 48
	if_icmplt	l4 // iconst_0
	iload_1
	ldc	int 57
	if_icmpgt	l4 // iconst_0
l2	iconst_1
	goto	l5 // ireturn
l4	iconst_0
l5	ireturn
  Labels:
   	l1 = 12 // iload_1
   	l3 = 24 // iload_1
   	l2 = 36 // iconst_1
   	l4 = 40 // iconst_0
   	l5 = 41 // ireturn
  LocalVariableTable: 
   Start  Length  Slot  Name   Signature
   0      42      0    this       Lscala/util/Random$;
   0      42      1    c       C


public final void swap$1(int, int, scala.collection.mutable.ArrayBuffer);
  Signature: (IILscala/collection/mutable/ArrayBuffer;)V
  Code:
   Stack=4, Locals=5, Args_size=4
	aload_3
	iload_1
	invokeinterface	InterfaceMethod scala/collection/mutable/ResizableArray.apply:(I)Ljava/lang/Object;
	astore	4
	aload_3
	iload_1
	aload_3
	iload_2
	invokeinterface	InterfaceMethod scala/collection/mutable/ResizableArray.apply:(I)Ljava/lang/Object;
	invokeinterface	InterfaceMethod scala/collection/mutable/ResizableArray.update:(ILjava/lang/Object;)V
	aload_3
	iload_2
	aload	4
	invokeinterface	InterfaceMethod scala/collection/mutable/ResizableArray.update:(ILjava/lang/Object;)V
	return
  Labels:
  LocalVariableTable: 
   Start  Length  Slot  Name   Signature
   0      33      0    this       Lscala/util/Random$;
   0      33      1    i1       I
   0      33      2    i2       I
   9      23      4    tmp       Ljava/lang/Object;


private scala.util.Random$();
  Signature: ()V
  Code:
   Stack=1, Locals=1, Args_size=1
	aload_0
	invokespecial	Method scala/util/Random."<init>":()V
	aload_0
	putstatic	Field MODULE$:Lscala/util/Random$;
	return
  Labels:

}

