Compiled from "Random.scala"
public final class scala.util.Random$$anonfun$nextASCIIString$1 extends scala.runtime.AbstractFunction0 implements java.io.Serializable
  SourceFile: "Random.scala"
  Scala: length = 0x
   
  InnerClass: 
   public final $anonfun$nextASCIIString$1=class scala/util/Random$$anonfun$nextASCIIString$1 of class scala/util/Random
  minor version: 0
  major version: 49
  Constant pool:
Asciz	SourceFile;
Asciz	Random.scala;
Asciz	<clinit>;
Asciz	()V;
Asciz	Code;
Asciz	serialVersionUID;
Asciz	J;
Asciz	scala/util/Random$$anonfun$nextASCIIString$1;
class	scala/util/Random$$anonfun$nextASCIIString$1
NameAndType	serialVersionUID:J
Field	scala/util/Random$$anonfun$nextASCIIString$1.serialVersionUID:J
Asciz	max$1;
Asciz	I;
Asciz	min$1;
Asciz	$outer;
Asciz	Lscala/util/Random;;
Asciz	apply;
Asciz	()B;
Asciz	LineNumberTable;
NameAndType	$outer:Lscala/util/Random;
Field	scala/util/Random$$anonfun$nextASCIIString$1.$outer:Lscala/util/Random;
NameAndType	min$1:I
Field	scala/util/Random$$anonfun$nextASCIIString$1.min$1:I
NameAndType	max$1:I
Field	scala/util/Random$$anonfun$nextASCIIString$1.max$1:I
Asciz	scala/util/Random;
class	scala/util/Random
Asciz	nextDigit$1;
Asciz	(II)I;
NameAndType	nextDigit$1:(II)I
Method	scala/util/Random.nextDigit$1:(II)I
Asciz	()Ljava/lang/Object;;
NameAndType	apply:()B
Method	scala/util/Random$$anonfun$nextASCIIString$1.apply:()B
Asciz	scala/runtime/BoxesRunTime;
class	scala/runtime/BoxesRunTime
Asciz	boxToByte;
Asciz	(B)Ljava/lang/Byte;;
NameAndType	boxToByte:(B)Ljava/lang/Byte;
Method	scala/runtime/BoxesRunTime.boxToByte:(B)Ljava/lang/Byte;
Asciz	<init>;
Asciz	(Lscala/util/Random;II)V;
Asciz	java/lang/NullPointerException;
class	java/lang/NullPointerException
NameAndType	"<init>":()V
Method	java/lang/NullPointerException."<init>":()V
Asciz	scala/runtime/AbstractFunction0;
class	scala/runtime/AbstractFunction0
Method	scala/runtime/AbstractFunction0."<init>":()V
Asciz	this;
Asciz	Lscala/util/Random$$anonfun$nextASCIIString$1;;
Asciz	LocalVariableTable;
Asciz	Scala;
Asciz	InnerClasses;
Asciz	$anonfun$nextASCIIString$1;
Asciz	java/io/Serializable;
class	java/io/Serializable

{
public static final long serialVersionUID;
  Signature: J

public final int max$1;
  Signature: I

public final int min$1;
  Signature: I

public final scala.util.Random $outer;
  Signature: Lscala/util/Random;

public static {};
  Signature: ()V
  Code:
   Stack=2, Locals=0, Args_size=0
	lconst_0
	putstatic	Field serialVersionUID:J
	return
  Labels:

public final byte apply();
  Signature: ()B
  Code:
   Stack=3, Locals=1, Args_size=1
	aload_0
	getfield	Field $outer:Lscala/util/Random;
	aload_0
	getfield	Field min$1:I
	aload_0
	getfield	Field max$1:I
	invokevirtual	Method scala/util/Random.nextDigit$1:(II)I
	i2b
	ireturn
  Labels:

public final java.lang.Object apply();
  Signature: ()Ljava/lang/Object;
  Code:
   Stack=1, Locals=2, Args_size=1
	aload_0
	invokevirtual	Method apply:()B
	istore_1
	iload_1
	invokestatic	Method scala/runtime/BoxesRunTime.boxToByte:(B)Ljava/lang/Byte;
	areturn
  Labels:

public scala.util.Random$$anonfun$nextASCIIString$1(scala.util.Random, int, int);
  Signature: (Lscala/util/Random;II)V
  Code:
   Stack=2, Locals=4, Args_size=4
	aload_1
	ifnonnull	l1 // aload_0
	new	class java/lang/NullPointerException
	dup
	invokespecial	Method java/lang/NullPointerException."<init>":()V
	athrow
l1	aload_0
	aload_1
	putfield	Field $outer:Lscala/util/Random;
	aload_0
	iload_2
	putfield	Field min$1:I
	aload_0
	iload_3
	putfield	Field max$1:I
	aload_0
	invokespecial	Method scala/runtime/AbstractFunction0."<init>":()V
	return
  Labels:
   	l1 = 12 // aload_0
  LocalVariableTable: 
   Start  Length  Slot  Name   Signature
   0      32      0    this       Lscala/util/Random$$anonfun$nextASCIIString$1;
   0      32      1    $outer       Lscala/util/Random;


}

