Compiled from "Random.scala"
public final class scala.util.Random$$anonfun$nextString$1 extends java.lang.Object implements scala.Function0,scala.ScalaObject,java.io.Serializable
  SourceFile: "Random.scala"
  Scala: length = 0x
   
  InnerClass: 
   public final #58= #9 of #47; //$anonfun$nextString$1=class scala/util/Random$$anonfun$nextString$1 of class scala/util/Random
  minor version: 0
  major version: 49
  Constant pool:
const #1 = Asciz	SourceFile;
const #2 = Asciz	Random.scala;
const #3 = Asciz	<clinit>;
const #4 = Asciz	()V;
const #5 = Asciz	Code;
const #6 = Asciz	serialVersionUID;
const #7 = Asciz	J;
const #8 = Asciz	scala/util/Random$$anonfun$nextString$1;
const #9 = class	#8;	//  scala/util/Random$$anonfun$nextString$1
const #10 = NameAndType	#6:#7;//  serialVersionUID:J
const #11 = Field	#9.#10;	//  scala/util/Random$$anonfun$nextString$1.serialVersionUID:J
const #12 = Asciz	$outer;
const #13 = Asciz	Lscala/util/Random;;
const #14 = Asciz	<init>;
const #15 = Asciz	(Lscala/util/Random;)V;
const #16 = Asciz	LineNumberTable;
const #17 = Asciz	java/lang/NullPointerException;
const #18 = class	#17;	//  java/lang/NullPointerException
const #19 = NameAndType	#14:#4;//  "<init>":()V
const #20 = Method	#18.#19;	//  java/lang/NullPointerException."<init>":()V
const #21 = NameAndType	#12:#13;//  $outer:Lscala/util/Random;
const #22 = Field	#9.#21;	//  scala/util/Random$$anonfun$nextString$1.$outer:Lscala/util/Random;
const #23 = Asciz	java/lang/Object;
const #24 = class	#23;	//  java/lang/Object
const #25 = Method	#24.#19;	//  java/lang/Object."<init>":()V
const #26 = Asciz	scala/Function0$class;
const #27 = class	#26;	//  scala/Function0$class
const #28 = Asciz	$init$;
const #29 = Asciz	(Lscala/Function0;)V;
const #30 = NameAndType	#28:#29;//  $init$:(Lscala/Function0;)V
const #31 = Method	#27.#30;	//  scala/Function0$class.$init$:(Lscala/Function0;)V
const #32 = Asciz	this;
const #33 = Asciz	Lscala/util/Random$$anonfun$nextString$1;;
const #34 = Asciz	LocalVariableTable;
const #35 = Asciz	apply;
const #36 = Asciz	()Ljava/lang/Object;;
const #37 = Asciz	()C;
const #38 = NameAndType	#35:#37;//  apply:()C
const #39 = Method	#9.#38;	//  scala/util/Random$$anonfun$nextString$1.apply:()C
const #40 = Asciz	scala/runtime/BoxesRunTime;
const #41 = class	#40;	//  scala/runtime/BoxesRunTime
const #42 = Asciz	boxToCharacter;
const #43 = Asciz	(C)Ljava/lang/Character;;
const #44 = NameAndType	#42:#43;//  boxToCharacter:(C)Ljava/lang/Character;
const #45 = Method	#41.#44;	//  scala/runtime/BoxesRunTime.boxToCharacter:(C)Ljava/lang/Character;
const #46 = Asciz	scala/util/Random;
const #47 = class	#46;	//  scala/util/Random
const #48 = Asciz	safeChar$1;
const #49 = NameAndType	#48:#37;//  safeChar$1:()C
const #50 = Method	#47.#49;	//  scala/util/Random.safeChar$1:()C
const #51 = Asciz	toString;
const #52 = Asciz	()Ljava/lang/String;;
const #53 = Asciz	(Lscala/Function0;)Ljava/lang/String;;
const #54 = NameAndType	#51:#53;//  toString:(Lscala/Function0;)Ljava/lang/String;
const #55 = Method	#27.#54;	//  scala/Function0$class.toString:(Lscala/Function0;)Ljava/lang/String;
const #56 = Asciz	Scala;
const #57 = Asciz	InnerClasses;
const #58 = Asciz	$anonfun$nextString$1;
const #59 = Asciz	scala/Function0;
const #60 = class	#59;	//  scala/Function0
const #61 = Asciz	scala/ScalaObject;
const #62 = class	#61;	//  scala/ScalaObject
const #63 = Asciz	java/io/Serializable;
const #64 = class	#63;	//  java/io/Serializable

{
public static final long serialVersionUID;

public static {};
  Code:
   Stack=2, Locals=0, Args_size=0
   0:	lconst_0
   1:	putstatic	#11; //Field serialVersionUID:J
   4:	return

public scala.util.Random$$anonfun$nextString$1(scala.util.Random);
  Code:
   Stack=2, Locals=2, Args_size=2
   0:	aload_1
   1:	ifnonnull	12
   4:	new	#18; //class java/lang/NullPointerException
   7:	dup
   8:	invokespecial	#20; //Method java/lang/NullPointerException."<init>":()V
   11:	athrow
   12:	aload_0
   13:	aload_1
   14:	putfield	#22; //Field $outer:Lscala/util/Random;
   17:	aload_0
   18:	invokespecial	#25; //Method java/lang/Object."<init>":()V
   21:	aload_0
   22:	invokestatic	#31; //Method scala/Function0$class.$init$:(Lscala/Function0;)V
   25:	return
  LineNumberTable: 
   line 89: 0

  LocalVariableTable: 
   Start  Length  Slot  Name   Signature
   0      26      0    this       Lscala/util/Random$$anonfun$nextString$1;
   0      26      1    $outer       Lscala/util/Random;


public final java.lang.Object apply();
  Code:
   Stack=1, Locals=3, Args_size=1
   0:	aload_0
   1:	getfield	#22; //Field $outer:Lscala/util/Random;
   4:	astore_2
   5:	aload_0
   6:	invokevirtual	#39; //Method apply:()C
   9:	istore_1
   10:	iload_1
   11:	invokestatic	#45; //Method scala/runtime/BoxesRunTime.boxToCharacter:(C)Ljava/lang/Character;
   14:	areturn
  LineNumberTable: 
   line 89: 0

  LocalVariableTable: 
   Start  Length  Slot  Name   Signature
   0      15      0    this       Lscala/util/Random$$anonfun$nextString$1;


public final char apply();
  Code:
   Stack=1, Locals=2, Args_size=1
   0:	aload_0
   1:	getfield	#22; //Field $outer:Lscala/util/Random;
   4:	astore_1
   5:	aload_0
   6:	getfield	#22; //Field $outer:Lscala/util/Random;
   9:	invokevirtual	#50; //Method scala/util/Random.safeChar$1:()C
   12:	ireturn
  LineNumberTable: 
   line 89: 0

  LocalVariableTable: 
   Start  Length  Slot  Name   Signature
   0      13      0    this       Lscala/util/Random$$anonfun$nextString$1;


public java.lang.String toString();
  Code:
   Stack=1, Locals=1, Args_size=1
   0:	aload_0
   1:	invokestatic	#55; //Method scala/Function0$class.toString:(Lscala/Function0;)Ljava/lang/String;
   4:	areturn
  LineNumberTable: 
   line 89: 0


}

