Compiled from "Random.scala"
public final class scala.util.Random$$anonfun$shuffle$1 extends scala.runtime.AbstractFunction1 implements java.io.Serializable
  SourceFile: "Random.scala"
  Scala: length = 0x
   
  InnerClass: 
   public final $anonfun$shuffle$1=class scala/util/Random$$anonfun$shuffle$1 of class scala/util/Random
  minor version: 0
  major version: 49
  Constant pool:
Asciz	SourceFile;
Asciz	Random.scala;
Asciz	<clinit>;
Asciz	()V;
Asciz	Code;
Asciz	serialVersionUID;
Asciz	J;
Asciz	scala/util/Random$$anonfun$shuffle$1;
class	scala/util/Random$$anonfun$shuffle$1
NameAndType	serialVersionUID:J
Field	scala/util/Random$$anonfun$shuffle$1.serialVersionUID:J
Asciz	buf$1;
Asciz	Lscala/collection/mutable/ArrayBuffer;;
Asciz	<init>;
Asciz	(Lscala/collection/mutable/ArrayBuffer;)V;
Asciz	LineNumberTable;
NameAndType	buf$1:Lscala/collection/mutable/ArrayBuffer;
Field	scala/util/Random$$anonfun$shuffle$1.buf$1:Lscala/collection/mutable/ArrayBuffer;
Asciz	scala/runtime/AbstractFunction1;
class	scala/runtime/AbstractFunction1
NameAndType	"<init>":()V
Method	scala/runtime/AbstractFunction1."<init>":()V
Asciz	apply;
Asciz	(Ljava/lang/Object;)Ljava/lang/Object;;
Asciz	scala/runtime/BoxesRunTime;
class	scala/runtime/BoxesRunTime
Asciz	unboxToInt;
Asciz	(Ljava/lang/Object;)I;
NameAndType	unboxToInt:(Ljava/lang/Object;)I
Method	scala/runtime/BoxesRunTime.unboxToInt:(Ljava/lang/Object;)I
Asciz	(I)V;
NameAndType	apply:(I)V
Method	scala/util/Random$$anonfun$shuffle$1.apply:(I)V
Asciz	scala/runtime/BoxedUnit;
class	scala/runtime/BoxedUnit
Asciz	UNIT;
Asciz	Lscala/runtime/BoxedUnit;;
NameAndType	UNIT:Lscala/runtime/BoxedUnit;
Field	scala/runtime/BoxedUnit.UNIT:Lscala/runtime/BoxedUnit;
Asciz	this;
Asciz	Lscala/util/Random$$anonfun$shuffle$1;;
Asciz	v1;
Asciz	Ljava/lang/Object;;
Asciz	LocalVariableTable;
Asciz	scala/util/Random$;
class	scala/util/Random$
Asciz	MODULE$;
Asciz	Lscala/util/Random$;;
NameAndType	MODULE$:Lscala/util/Random$;
Field	scala/util/Random$.MODULE$:Lscala/util/Random$;
Asciz	nextInt;
Asciz	(I)I;
NameAndType	nextInt:(I)I
Method	scala/util/Random$.nextInt:(I)I
Asciz	swap$1;
Asciz	(IILscala/collection/mutable/ArrayBuffer;)V;
NameAndType	swap$1:(IILscala/collection/mutable/ArrayBuffer;)V
Method	scala/util/Random$.swap$1:(IILscala/collection/mutable/ArrayBuffer;)V
Asciz	n;
Asciz	I;
Asciz	k;
Asciz	Scala;
Asciz	InnerClasses;
Asciz	scala/util/Random;
class	scala/util/Random
Asciz	$anonfun$shuffle$1;
Asciz	java/io/Serializable;
class	java/io/Serializable

{
public static final long serialVersionUID;
  Signature: J

public final scala.collection.mutable.ArrayBuffer buf$1;
  Signature: Lscala/collection/mutable/ArrayBuffer;

public static {};
  Signature: ()V
  Code:
   Stack=2, Locals=0, Args_size=0
	lconst_0
	putstatic	Field serialVersionUID:J
	return
  Labels:

public scala.util.Random$$anonfun$shuffle$1(scala.collection.mutable.ArrayBuffer);
  Signature: (Lscala/collection/mutable/ArrayBuffer;)V
  Code:
   Stack=2, Locals=2, Args_size=2
	aload_0
	aload_1
	putfield	Field buf$1:Lscala/collection/mutable/ArrayBuffer;
	aload_0
	invokespecial	Method scala/runtime/AbstractFunction1."<init>":()V
	return
  Labels:

public final java.lang.Object apply(java.lang.Object);
  Signature: (Ljava/lang/Object;)Ljava/lang/Object;
  Code:
   Stack=2, Locals=2, Args_size=2
	aload_0
	aload_1
	invokestatic	Method scala/runtime/BoxesRunTime.unboxToInt:(Ljava/lang/Object;)I
	invokevirtual	Method apply:(I)V
	getstatic	Field scala/runtime/BoxedUnit.UNIT:Lscala/runtime/BoxedUnit;
	areturn
  Labels:
  LocalVariableTable: 
   Start  Length  Slot  Name   Signature
   0      12      0    this       Lscala/util/Random$$anonfun$shuffle$1;
   0      12      1    v1       Ljava/lang/Object;


public final void apply(int);
  Signature: (I)V
  Code:
   Stack=4, Locals=3, Args_size=2
	getstatic	Field scala/util/Random$.MODULE$:Lscala/util/Random$;
	iload_1
	invokevirtual	Method scala/util/Random$.nextInt:(I)I
	istore_2
	getstatic	Field scala/util/Random$.MODULE$:Lscala/util/Random$;
	iload_1
	iconst_1
	isub
	iload_2
	aload_0
	getfield	Field buf$1:Lscala/collection/mutable/ArrayBuffer;
	invokevirtual	Method scala/util/Random$.swap$1:(IILscala/collection/mutable/ArrayBuffer;)V
	return
  Labels:
  LocalVariableTable: 
   Start  Length  Slot  Name   Signature
   0      23      0    this       Lscala/util/Random$$anonfun$shuffle$1;
   0      23      1    n       I
   8      14      2    k       I


}

