Compiled from "Sorting.scala"
public class scala.util.RichSorting extends java.lang.Object implements scala.ScalaObject
  SourceFile: "Sorting.scala"
  Signature: length = 0x2
   00 35 
  ScalaSig: length = 0x17F
   05 00 44 06 04 01 02 00 07 02 0B 52 69 63 68 53
   6F 72 74 69 6E 67 0A 02 03 04 01 04 75 74 69 6C
   0A 01 05 01 05 73 63 61 6C 61 03 00 15 02 08 25
   13 03 00 09 11 10 02 0A 0F 0D 01 0B 0A 02 0C 0D
   01 04 6C 61 6E 67 0A 01 0E 01 04 6A 61 76 61 09
   02 10 0B 02 06 4F 62 6A 65 63 74 10 02 12 13 0D
   01 04 09 02 14 04 02 0B 53 63 61 6C 61 4F 62 6A
   65 63 74 08 08 16 00 FFFFFF82 FFFFFF80 FFFFFFA0 FFFFFF80 04 17 01 01 73
   10 03 18 20 23 0E 02 19 1E 0E 02 1A 1D 0D 01 1B
   0A 02 1C 06 01 06 3C 72 6F 6F 74 3E 09 01 05 09
   02 1F 04 01 07 70 61 63 6B 61 67 65 09 02 21 22
   02 03 53 65 71 0A 02 1F 04 10 02 24 25 0C 00 04
   08 26 00 FFFFFF84 FFFFFF80 FFFFFF80 FFFFFFC2 00 27 02 01 4B 11 02 28 2B
   10 02 12 29 09 02 2A 04 02 07 4E 6F 74 68 69 6E
   67 10 03 18 2C 23 09 02 2D 22 02 07 4F 72 64 65
   72 65 64 08 08 2F 00 FFFFFF82 FFFFFF80 FFFFFFA0 FFFFFF80 05 30 01 0B 65
   76 69 64 65 6E 63 65 24 31 33 10 03 31 34 23 0D
   01 32 0A 02 33 04 01 07 72 65 66 6C 65 63 74 09
   02 35 32 02 0D 43 6C 61 73 73 4D 61 6E 69 66 65
   73 74 08 05 37 00 FFFFFF84 00 38 01 06 3C 69 6E 69 74
   3E 14 02 39 3D 16 02 3A 3C 10 03 3B 00 23 0D 01
   02 08 05 2F 36 FFFFFFC0 01 30 08 05 16 36 FFFFFFC0 00 17 08
   05 3F 00 FFFFFF84 00 40 01 04 73 6F 72 74 15 01 41 10
   03 12 42 23 09 02 43 04 02 05 41 72 72 61 79 
  InnerClass: 
   public abstract $less$colon$less=class scala/Predef$$less$colon$less of class scala/Predef
  minor version: 0
  major version: 49
  Constant pool:
Asciz	SourceFile;
Asciz	Sorting.scala;
Asciz	evidence$13;
Asciz	Lscala/reflect/ClassManifest;;
Asciz	Lscala/reflect/ClassManifest<TK;>;;
Asciz	Signature;
Asciz	s;
Asciz	Lscala/collection/Seq;;
Asciz	Lscala/collection/Seq<TK;>;;
Asciz	<init>;
Asciz	(Lscala/collection/Seq;Lscala/reflect/ClassManifest;)V;
Asciz	Code;
Asciz	LineNumberTable;
Asciz	scala/util/RichSorting;
class	scala/util/RichSorting
NameAndType	s:Lscala/collection/Seq;
Field	scala/util/RichSorting.s:Lscala/collection/Seq;
NameAndType	evidence$13:Lscala/reflect/ClassManifest;
Field	scala/util/RichSorting.evidence$13:Lscala/reflect/ClassManifest;
Asciz	java/lang/Object;
class	java/lang/Object
Asciz	()V;
NameAndType	"<init>":()V
Method	java/lang/Object."<init>":()V
Asciz	this;
Asciz	Lscala/util/RichSorting;;
Asciz	LocalVariableTable;
Asciz	(Lscala/collection/Seq<TK;>;Lscala/reflect/ClassManifest<TK;>;)V;
Asciz	sort;
Asciz	()[Lscala/math/Ordered;;
Asciz	scala/util/Sorting$;
class	scala/util/Sorting$
Asciz	MODULE$;
Asciz	Lscala/util/Sorting$;;
NameAndType	MODULE$:Lscala/util/Sorting$;
Field	scala/util/Sorting$.MODULE$:Lscala/util/Sorting$;
Asciz	scala/Predef$;
class	scala/Predef$
Asciz	Lscala/Predef$;;
NameAndType	MODULE$:Lscala/Predef$;
Field	scala/Predef$.MODULE$:Lscala/Predef$;
Asciz	conforms;
Asciz	()Lscala/Predef$$less$colon$less;;
NameAndType	conforms:()Lscala/Predef$$less$colon$less;
Method	scala/Predef$.conforms:()Lscala/Predef$$less$colon$less;
Asciz	stableSort;
Asciz	(Lscala/collection/Seq;Lscala/Function1;Lscala/reflect/ClassManifest;)Ljava/lang/Object;;
NameAndType	stableSort:(Lscala/collection/Seq;Lscala/Function1;Lscala/reflect/ClassManifest;)Ljava/lang/Object;
Method	scala/util/Sorting$.stableSort:(Lscala/collection/Seq;Lscala/Function1;Lscala/reflect/ClassManifest;)Ljava/lang/Object;
Asciz	[Lscala/math/Ordered;;
class	"[Lscala/math/Ordered;"
Asciz	()[TK;;
Asciz	<K::Lscala/math/Ordered<TK;>;>Ljava/lang/Object;Lscala/ScalaObject;;
Asciz	ScalaSig;
Asciz	InnerClasses;
Asciz	scala/Predef$$less$colon$less;
class	scala/Predef$$less$colon$less
Asciz	scala/Predef;
class	scala/Predef
Asciz	$less$colon$less;
Asciz	scala/ScalaObject;
class	scala/ScalaObject

{
private final scala.reflect.ClassManifest evidence$13;
  Signature: Lscala/reflect/ClassManifest;
  Signature: length = 0x2
   00 05 

private final scala.collection.Seq s;
  Signature: Lscala/collection/Seq;
  Signature: length = 0x2
   00 09 

public scala.util.RichSorting(scala.collection.Seq, scala.reflect.ClassManifest);
  Signature: (Lscala/collection/Seq;Lscala/reflect/ClassManifest;)V
  Code:
   Stack=2, Locals=3, Args_size=3
	aload_0
	aload_1
	putfield	Field s:Lscala/collection/Seq;
	aload_0
	aload_2
	putfield	Field evidence$13:Lscala/reflect/ClassManifest;
	aload_0
	invokespecial	Method java/lang/Object."<init>":()V
	return
  Labels:
  LocalVariableTable: 
   Start  Length  Slot  Name   Signature
   0      15      0    this       Lscala/util/RichSorting;
   0      15      1    s       Lscala/collection/Seq;
   0      15      2    evidence$13       Lscala/reflect/ClassManifest;

  Signature: length = 0x2
   00 1C 

public scala.math.Ordered[] sort();
  Signature: ()[Lscala/math/Ordered;
  Code:
   Stack=4, Locals=1, Args_size=1
	getstatic	Field scala/util/Sorting$.MODULE$:Lscala/util/Sorting$;
	aload_0
	getfield	Field s:Lscala/collection/Seq;
	getstatic	Field scala/Predef$.MODULE$:Lscala/Predef$;
	invokevirtual	Method scala/Predef$.conforms:()Lscala/Predef$$less$colon$less;
	aload_0
	getfield	Field evidence$13:Lscala/reflect/ClassManifest;
	invokevirtual	Method scala/util/Sorting$.stableSort:(Lscala/collection/Seq;Lscala/Function1;Lscala/reflect/ClassManifest;)Ljava/lang/Object;
	checkcast	class "[Lscala/math/Ordered;"
	areturn
  Labels:
  Signature: length = 0x2
   00 34 

}

