Compiled from "ClassLoader.scala"
public final class scala.util.ScalaClassLoader$$anonfun$tryClass$1 extends java.lang.Object implements scala.Function0,scala.ScalaObject,java.io.Serializable
  SourceFile: "ClassLoader.scala"
  Scala: length = 0x
   
  InnerClass: 
   public final #62= #19 of #61; //$anonfun$tryClass$1=class scala/util/ScalaClassLoader$$anonfun$tryClass$1 of class scala/util/ScalaClassLoader
  minor version: 0
  major version: 49
  Constant pool:
const #1 = Asciz	SourceFile;
const #2 = Asciz	ClassLoader.scala;
const #3 = Asciz	initialize$1;
const #4 = Asciz	Z;
const #5 = Asciz	path$1;
const #6 = Asciz	Ljava/lang/String;;
const #7 = Asciz	$outer;
const #8 = Asciz	Lscala/util/ScalaClassLoader;;
const #9 = Asciz	<init>;
const #10 = Asciz	(Lscala/util/ScalaClassLoader;Ljava/lang/String;Z)V;
const #11 = Asciz	Code;
const #12 = Asciz	LineNumberTable;
const #13 = Asciz	java/lang/NullPointerException;
const #14 = class	#13;	//  java/lang/NullPointerException
const #15 = Asciz	()V;
const #16 = NameAndType	#9:#15;//  "<init>":()V
const #17 = Method	#14.#16;	//  java/lang/NullPointerException."<init>":()V
const #18 = Asciz	scala/util/ScalaClassLoader$$anonfun$tryClass$1;
const #19 = class	#18;	//  scala/util/ScalaClassLoader$$anonfun$tryClass$1
const #20 = NameAndType	#7:#8;//  $outer:Lscala/util/ScalaClassLoader;
const #21 = Field	#19.#20;	//  scala/util/ScalaClassLoader$$anonfun$tryClass$1.$outer:Lscala/util/ScalaClassLoader;
const #22 = NameAndType	#5:#6;//  path$1:Ljava/lang/String;
const #23 = Field	#19.#22;	//  scala/util/ScalaClassLoader$$anonfun$tryClass$1.path$1:Ljava/lang/String;
const #24 = NameAndType	#3:#4;//  initialize$1:Z
const #25 = Field	#19.#24;	//  scala/util/ScalaClassLoader$$anonfun$tryClass$1.initialize$1:Z
const #26 = Asciz	java/lang/Object;
const #27 = class	#26;	//  java/lang/Object
const #28 = Method	#27.#16;	//  java/lang/Object."<init>":()V
const #29 = Asciz	scala/Function0$class;
const #30 = class	#29;	//  scala/Function0$class
const #31 = Asciz	$init$;
const #32 = Asciz	(Lscala/Function0;)V;
const #33 = NameAndType	#31:#32;//  $init$:(Lscala/Function0;)V
const #34 = Method	#30.#33;	//  scala/Function0$class.$init$:(Lscala/Function0;)V
const #35 = Asciz	this;
const #36 = Asciz	Lscala/util/ScalaClassLoader$$anonfun$tryClass$1;;
const #37 = Asciz	LocalVariableTable;
const #38 = Asciz	apply;
const #39 = Asciz	()Ljava/lang/Object;;
const #40 = Asciz	()Ljava/lang/Class;;
const #41 = NameAndType	#38:#40;//  apply:()Ljava/lang/Class;
const #42 = Method	#19.#41;	//  scala/util/ScalaClassLoader$$anonfun$tryClass$1.apply:()Ljava/lang/Class;
const #43 = Asciz	java/lang/ClassLoader;
const #44 = class	#43;	//  java/lang/ClassLoader
const #45 = Asciz	java/lang/Class;
const #46 = class	#45;	//  java/lang/Class
const #47 = Asciz	forName;
const #48 = Asciz	(Ljava/lang/String;ZLjava/lang/ClassLoader;)Ljava/lang/Class;;
const #49 = NameAndType	#47:#48;//  forName:(Ljava/lang/String;ZLjava/lang/ClassLoader;)Ljava/lang/Class;
const #50 = Method	#46.#49;	//  java/lang/Class.forName:(Ljava/lang/String;ZLjava/lang/ClassLoader;)Ljava/lang/Class;
const #51 = Asciz	()Ljava/lang/Class<TT;>;;
const #52 = Asciz	Signature;
const #53 = Asciz	toString;
const #54 = Asciz	()Ljava/lang/String;;
const #55 = Asciz	(Lscala/Function0;)Ljava/lang/String;;
const #56 = NameAndType	#53:#55;//  toString:(Lscala/Function0;)Ljava/lang/String;
const #57 = Method	#30.#56;	//  scala/Function0$class.toString:(Lscala/Function0;)Ljava/lang/String;
const #58 = Asciz	Scala;
const #59 = Asciz	InnerClasses;
const #60 = Asciz	scala/util/ScalaClassLoader;
const #61 = class	#60;	//  scala/util/ScalaClassLoader
const #62 = Asciz	$anonfun$tryClass$1;
const #63 = Asciz	scala/Function0;
const #64 = class	#63;	//  scala/Function0
const #65 = Asciz	scala/ScalaObject;
const #66 = class	#65;	//  scala/ScalaObject
const #67 = Asciz	java/io/Serializable;
const #68 = class	#67;	//  java/io/Serializable

{
public scala.util.ScalaClassLoader$$anonfun$tryClass$1(scala.util.ScalaClassLoader, java.lang.String, boolean);
  Code:
   Stack=2, Locals=4, Args_size=4
   0:	aload_1
   1:	ifnonnull	12
   4:	new	#14; //class java/lang/NullPointerException
   7:	dup
   8:	invokespecial	#17; //Method java/lang/NullPointerException."<init>":()V
   11:	athrow
   12:	aload_0
   13:	aload_1
   14:	putfield	#21; //Field $outer:Lscala/util/ScalaClassLoader;
   17:	aload_0
   18:	aload_2
   19:	putfield	#23; //Field path$1:Ljava/lang/String;
   22:	aload_0
   23:	iload_3
   24:	putfield	#25; //Field initialize$1:Z
   27:	aload_0
   28:	invokespecial	#28; //Method java/lang/Object."<init>":()V
   31:	aload_0
   32:	invokestatic	#34; //Method scala/Function0$class.$init$:(Lscala/Function0;)V
   35:	return
  LineNumberTable: 
   line 34: 0

  LocalVariableTable: 
   Start  Length  Slot  Name   Signature
   0      36      0    this       Lscala/util/ScalaClassLoader$$anonfun$tryClass$1;
   0      36      1    $outer       Lscala/util/ScalaClassLoader;


public final java.lang.Object apply();
  Code:
   Stack=1, Locals=2, Args_size=1
   0:	aload_0
   1:	getfield	#21; //Field $outer:Lscala/util/ScalaClassLoader;
   4:	astore_1
   5:	aload_0
   6:	invokevirtual	#42; //Method apply:()Ljava/lang/Class;
   9:	areturn
  LineNumberTable: 
   line 34: 0

  LocalVariableTable: 
   Start  Length  Slot  Name   Signature
   0      10      0    this       Lscala/util/ScalaClassLoader$$anonfun$tryClass$1;


public final java.lang.Class apply();
  Code:
   Stack=3, Locals=2, Args_size=1
   0:	aload_0
   1:	getfield	#21; //Field $outer:Lscala/util/ScalaClassLoader;
   4:	astore_1
   5:	aload_0
   6:	getfield	#23; //Field path$1:Ljava/lang/String;
   9:	aload_0
   10:	getfield	#25; //Field initialize$1:Z
   13:	aload_0
   14:	getfield	#21; //Field $outer:Lscala/util/ScalaClassLoader;
   17:	checkcast	#44; //class java/lang/ClassLoader
   20:	invokestatic	#50; //Method java/lang/Class.forName:(Ljava/lang/String;ZLjava/lang/ClassLoader;)Ljava/lang/Class;
   23:	areturn
  LineNumberTable: 
   line 34: 0

  LocalVariableTable: 
   Start  Length  Slot  Name   Signature
   0      24      0    this       Lscala/util/ScalaClassLoader$$anonfun$tryClass$1;

  Signature: length = 0x2
   00 33 

public java.lang.String toString();
  Code:
   Stack=1, Locals=1, Args_size=1
   0:	aload_0
   1:	invokestatic	#57; //Method scala/Function0$class.toString:(Lscala/Function0;)Ljava/lang/String;
   4:	areturn
  LineNumberTable: 
   line 34: 0


}

