Compiled from "ClassLoader.scala"
public abstract class scala.util.ScalaClassLoader$class extends java.lang.Object
  SourceFile: "ClassLoader.scala"
  Scala: length = 0x
   
  InnerClass: 
   public #199= #151 of #198; //Catch=class scala/util/control/Exception$Catch of class scala/util/control/Exception
   public final #200= #19 of #13; //$anonfun$1=class scala/util/ScalaClassLoader$$anonfun$1 of class scala/util/ScalaClassLoader
   public final #201= #53 of #13; //$anonfun$run$1=class scala/util/ScalaClassLoader$$anonfun$run$1 of class scala/util/ScalaClassLoader
   public final #202= #146 of #13; //$anonfun$tryClass$1=class scala/util/ScalaClassLoader$$anonfun$tryClass$1 of class scala/util/ScalaClassLoader
  minor version: 0
  major version: 49
  Constant pool:
const #1 = Asciz	SourceFile;
const #2 = Asciz	ClassLoader.scala;
const #3 = Asciz	$init$;
const #4 = Asciz	(Lscala/util/ScalaClassLoader;)V;
const #5 = Asciz	Code;
const #6 = Asciz	LineNumberTable;
const #7 = Asciz	$this;
const #8 = Asciz	Lscala/util/ScalaClassLoader;;
const #9 = Asciz	LocalVariableTable;
const #10 = Asciz	run;
const #11 = Asciz	(Lscala/util/ScalaClassLoader;Ljava/lang/String;Lscala/collection/Sequence;)V;
const #12 = Asciz	scala/util/ScalaClassLoader;
const #13 = class	#12;	//  scala/util/ScalaClassLoader
const #14 = Asciz	tryToInitializeClass;
const #15 = Asciz	(Ljava/lang/String;)Lscala/Option;;
const #16 = NameAndType	#14:#15;//  tryToInitializeClass:(Ljava/lang/String;)Lscala/Option;
const #17 = InterfaceMethod	#13.#16;	//  scala/util/ScalaClassLoader.tryToInitializeClass:(Ljava/lang/String;)Lscala/Option;
const #18 = Asciz	scala/util/ScalaClassLoader$$anonfun$1;
const #19 = class	#18;	//  scala/util/ScalaClassLoader$$anonfun$1
const #20 = Asciz	<init>;
const #21 = Asciz	(Lscala/util/ScalaClassLoader;Ljava/lang/String;)V;
const #22 = NameAndType	#20:#21;//  "<init>":(Lscala/util/ScalaClassLoader;Ljava/lang/String;)V
const #23 = Method	#19.#22;	//  scala/util/ScalaClassLoader$$anonfun$1."<init>":(Lscala/util/ScalaClassLoader;Ljava/lang/String;)V
const #24 = Asciz	scala/Option;
const #25 = class	#24;	//  scala/Option
const #26 = Asciz	getOrElse;
const #27 = Asciz	(Lscala/Function0;)Ljava/lang/Object;;
const #28 = NameAndType	#26:#27;//  getOrElse:(Lscala/Function0;)Ljava/lang/Object;
const #29 = Method	#25.#28;	//  scala/Option.getOrElse:(Lscala/Function0;)Ljava/lang/Object;
const #30 = Asciz	java/lang/Class;
const #31 = class	#30;	//  java/lang/Class
const #32 = Asciz	main;
const #33 = String	#32;	//  main
const #34 = Asciz	[Ljava/lang/String;;
const #35 = class	#34;	//  "[Ljava/lang/String;"
const #36 = Asciz	getMethod;
const #37 = Asciz	(Ljava/lang/String;[Ljava/lang/Class;)Ljava/lang/reflect/Method;;
const #38 = NameAndType	#36:#37;//  getMethod:(Ljava/lang/String;[Ljava/lang/Class;)Ljava/lang/reflect/Method;
const #39 = Method	#31.#38;	//  java/lang/Class.getMethod:(Ljava/lang/String;[Ljava/lang/Class;)Ljava/lang/reflect/Method;
const #40 = Asciz	java/lang/reflect/Method;
const #41 = class	#40;	//  java/lang/reflect/Method
const #42 = Asciz	getModifiers;
const #43 = Asciz	()I;
const #44 = NameAndType	#42:#43;//  getModifiers:()I
const #45 = Method	#41.#44;	//  java/lang/reflect/Method.getModifiers:()I
const #46 = Asciz	java/lang/reflect/Modifier;
const #47 = class	#46;	//  java/lang/reflect/Modifier
const #48 = Asciz	isStatic;
const #49 = Asciz	(I)Z;
const #50 = NameAndType	#48:#49;//  isStatic:(I)Z
const #51 = Method	#47.#50;	//  java/lang/reflect/Modifier.isStatic:(I)Z
const #52 = Asciz	scala/util/ScalaClassLoader$$anonfun$run$1;
const #53 = class	#52;	//  scala/util/ScalaClassLoader$$anonfun$run$1
const #54 = Asciz	(Lscala/util/ScalaClassLoader;Lscala/collection/Sequence;Ljava/lang/reflect/Method;)V;
const #55 = NameAndType	#20:#54;//  "<init>":(Lscala/util/ScalaClassLoader;Lscala/collection/Sequence;Ljava/lang/reflect/Method;)V
const #56 = Method	#53.#55;	//  scala/util/ScalaClassLoader$$anonfun$run$1."<init>":(Lscala/util/ScalaClassLoader;Lscala/collection/Sequence;Ljava/lang/reflect/Method;)V
const #57 = Asciz	asContext;
const #58 = NameAndType	#57:#27;//  asContext:(Lscala/Function0;)Ljava/lang/Object;
const #59 = InterfaceMethod	#13.#58;	//  scala/util/ScalaClassLoader.asContext:(Lscala/Function0;)Ljava/lang/Object;
const #60 = Asciz	java/lang/NoSuchMethodException;
const #61 = class	#60;	//  java/lang/NoSuchMethodException
const #62 = Asciz	scala/collection/mutable/StringBuilder;
const #63 = class	#62;	//  scala/collection/mutable/StringBuilder
const #64 = Asciz	()V;
const #65 = NameAndType	#20:#64;//  "<init>":()V
const #66 = Method	#63.#65;	//  scala/collection/mutable/StringBuilder."<init>":()V
const #67 = Asciz	append;
const #68 = Asciz	(Ljava/lang/Object;)Lscala/collection/mutable/StringBuilder;;
const #69 = NameAndType	#67:#68;//  append:(Ljava/lang/Object;)Lscala/collection/mutable/StringBuilder;
const #70 = Method	#63.#69;	//  scala/collection/mutable/StringBuilder.append:(Ljava/lang/Object;)Lscala/collection/mutable/StringBuilder;
const #71 = Asciz	.main is not static;
const #72 = String	#71;	//  .main is not static
const #73 = Asciz	toString;
const #74 = Asciz	()Ljava/lang/String;;
const #75 = NameAndType	#73:#74;//  toString:()Ljava/lang/String;
const #76 = Method	#63.#75;	//  scala/collection/mutable/StringBuilder.toString:()Ljava/lang/String;
const #77 = Asciz	(Ljava/lang/String;)V;
const #78 = NameAndType	#20:#77;//  "<init>":(Ljava/lang/String;)V
const #79 = Method	#61.#78;	//  java/lang/NoSuchMethodException."<init>":(Ljava/lang/String;)V
const #80 = Asciz	objectName$1;
const #81 = Asciz	Ljava/lang/String;;
const #82 = Asciz	arguments$1;
const #83 = Asciz	Lscala/collection/Sequence;;
const #84 = Asciz	clsToRun;
const #85 = Asciz	Ljava/lang/Class;;
const #86 = Asciz	method$1;
const #87 = Asciz	Ljava/lang/reflect/Method;;
const #88 = Asciz	create;
const #89 = Asciz	(Lscala/util/ScalaClassLoader;Ljava/lang/String;)Ljava/lang/Object;;
const #90 = Asciz	scala/Some;
const #91 = class	#90;	//  scala/Some
const #92 = Asciz	x;
const #93 = Asciz	()Ljava/lang/Object;;
const #94 = NameAndType	#92:#93;//  x:()Ljava/lang/Object;
const #95 = Method	#91.#94;	//  scala/Some.x:()Ljava/lang/Object;
const #96 = Asciz	newInstance;
const #97 = NameAndType	#96:#93;//  newInstance:()Ljava/lang/Object;
const #98 = Method	#31.#97;	//  java/lang/Class.newInstance:()Ljava/lang/Object;
const #99 = Asciz	scala/None$;
const #100 = class	#99;	//  scala/None$
const #101 = Asciz	MODULE$;
const #102 = Asciz	Lscala/None$;;
const #103 = NameAndType	#101:#102;//  MODULE$:Lscala/None$;
const #104 = Field	#100.#103;	//  scala/None$.MODULE$:Lscala/None$;
const #105 = Asciz	java/lang/Object;
const #106 = class	#105;	//  java/lang/Object
const #107 = Asciz	equals;
const #108 = Asciz	(Ljava/lang/Object;)Z;
const #109 = NameAndType	#107:#108;//  equals:(Ljava/lang/Object;)Z
const #110 = Method	#106.#109;	//  java/lang/Object.equals:(Ljava/lang/Object;)Z
const #111 = Asciz	scala/MatchError;
const #112 = class	#111;	//  scala/MatchError
const #113 = Method	#25.#75;	//  scala/Option.toString:()Ljava/lang/String;
const #114 = Method	#112.#78;	//  scala/MatchError."<init>":(Ljava/lang/String;)V
const #115 = Asciz	path;
const #116 = Asciz	temp1;
const #117 = Asciz	Lscala/Option;;
const #118 = Asciz	temp2;
const #119 = Asciz	Lscala/Some;;
const #120 = Asciz	temp3;
const #121 = Asciz	tryClass;
const #122 = Asciz	(Lscala/util/ScalaClassLoader;Ljava/lang/String;Z)Lscala/Option;;
const #123 = Asciz	scala/util/control/Exception$;
const #124 = class	#123;	//  scala/util/control/Exception$
const #125 = Asciz	Lscala/util/control/Exception$;;
const #126 = NameAndType	#101:#125;//  MODULE$:Lscala/util/control/Exception$;
const #127 = Field	#124.#126;	//  scala/util/control/Exception$.MODULE$:Lscala/util/control/Exception$;
const #128 = Asciz	scala/runtime/ScalaRunTime$;
const #129 = class	#128;	//  scala/runtime/ScalaRunTime$
const #130 = Asciz	Lscala/runtime/ScalaRunTime$;;
const #131 = NameAndType	#101:#130;//  MODULE$:Lscala/runtime/ScalaRunTime$;
const #132 = Field	#129.#131;	//  scala/runtime/ScalaRunTime$.MODULE$:Lscala/runtime/ScalaRunTime$;
const #133 = Asciz	java/lang/ClassNotFoundException;
const #134 = class	#133;	//  java/lang/ClassNotFoundException
const #135 = Asciz	java/lang/SecurityException;
const #136 = class	#135;	//  java/lang/SecurityException
const #137 = Asciz	boxArray;
const #138 = Asciz	(Ljava/lang/Object;)Lscala/runtime/BoxedArray;;
const #139 = NameAndType	#137:#138;//  boxArray:(Ljava/lang/Object;)Lscala/runtime/BoxedArray;
const #140 = Method	#129.#139;	//  scala/runtime/ScalaRunTime$.boxArray:(Ljava/lang/Object;)Lscala/runtime/BoxedArray;
const #141 = Asciz	catching;
const #142 = Asciz	(Lscala/collection/Sequence;)Lscala/util/control/Exception$Catch;;
const #143 = NameAndType	#141:#142;//  catching:(Lscala/collection/Sequence;)Lscala/util/control/Exception$Catch;
const #144 = Method	#124.#143;	//  scala/util/control/Exception$.catching:(Lscala/collection/Sequence;)Lscala/util/control/Exception$Catch;
const #145 = Asciz	scala/util/ScalaClassLoader$$anonfun$tryClass$1;
const #146 = class	#145;	//  scala/util/ScalaClassLoader$$anonfun$tryClass$1
const #147 = Asciz	(Lscala/util/ScalaClassLoader;Ljava/lang/String;Z)V;
const #148 = NameAndType	#20:#147;//  "<init>":(Lscala/util/ScalaClassLoader;Ljava/lang/String;Z)V
const #149 = Method	#146.#148;	//  scala/util/ScalaClassLoader$$anonfun$tryClass$1."<init>":(Lscala/util/ScalaClassLoader;Ljava/lang/String;Z)V
const #150 = Asciz	scala/util/control/Exception$Catch;
const #151 = class	#150;	//  scala/util/control/Exception$Catch
const #152 = Asciz	opt;
const #153 = Asciz	(Lscala/Function0;)Lscala/Option;;
const #154 = NameAndType	#152:#153;//  opt:(Lscala/Function0;)Lscala/Option;
const #155 = Method	#151.#154;	//  scala/util/control/Exception$Catch.opt:(Lscala/Function0;)Lscala/Option;
const #156 = Asciz	path$1;
const #157 = Asciz	initialize$1;
const #158 = Asciz	Z;
const #159 = Asciz	<T:Ljava/lang/Object;>(Ljava/lang/String;Z)Lscala/Option<Ljava/lang/Class<TT;>;>;;
const #160 = Asciz	Signature;
const #161 = Asciz	(Lscala/util/ScalaClassLoader;Ljava/lang/String;)Lscala/Option;;
const #162 = Asciz	scala/util/ScalaClassLoader$class;
const #163 = class	#162;	//  scala/util/ScalaClassLoader$class
const #164 = NameAndType	#121:#122;//  tryClass:(Lscala/util/ScalaClassLoader;Ljava/lang/String;Z)Lscala/Option;
const #165 = Method	#163.#164;	//  scala/util/ScalaClassLoader$class.tryClass:(Lscala/util/ScalaClassLoader;Ljava/lang/String;Z)Lscala/Option;
const #166 = Asciz	tryToLoadClass;
const #167 = Asciz	setAsContext;
const #168 = Asciz	scala/util/ScalaClassLoader$;
const #169 = class	#168;	//  scala/util/ScalaClassLoader$
const #170 = Asciz	Lscala/util/ScalaClassLoader$;;
const #171 = NameAndType	#101:#170;//  MODULE$:Lscala/util/ScalaClassLoader$;
const #172 = Field	#169.#171;	//  scala/util/ScalaClassLoader$.MODULE$:Lscala/util/ScalaClassLoader$;
const #173 = Asciz	java/lang/ClassLoader;
const #174 = class	#173;	//  java/lang/ClassLoader
const #175 = Asciz	setContextLoader;
const #176 = Asciz	(Ljava/lang/ClassLoader;)V;
const #177 = NameAndType	#175:#176;//  setContextLoader:(Ljava/lang/ClassLoader;)V
const #178 = Method	#169.#177;	//  scala/util/ScalaClassLoader$.setContextLoader:(Ljava/lang/ClassLoader;)V
const #179 = Asciz	(Lscala/util/ScalaClassLoader;Lscala/Function0;)Ljava/lang/Object;;
const #180 = Asciz	getContextLoader;
const #181 = Asciz	()Ljava/lang/ClassLoader;;
const #182 = NameAndType	#180:#181;//  getContextLoader:()Ljava/lang/ClassLoader;
const #183 = Method	#169.#182;	//  scala/util/ScalaClassLoader$.getContextLoader:()Ljava/lang/ClassLoader;
const #184 = Asciz	scala/Function0;
const #185 = class	#184;	//  scala/Function0
const #186 = Asciz	apply;
const #187 = NameAndType	#186:#93;//  apply:()Ljava/lang/Object;
const #188 = InterfaceMethod	#185.#187;	//  scala/Function0.apply:()Ljava/lang/Object;
const #189 = Asciz	action;
const #190 = Asciz	Lscala/Function0;;
const #191 = Asciz	oldLoader;
const #192 = Asciz	Ljava/lang/ClassLoader;;
const #193 = Asciz	exceptionResult1;
const #194 = Asciz	Ljava/lang/Object;;
const #195 = Asciz	Scala;
const #196 = Asciz	InnerClasses;
const #197 = Asciz	scala/util/control/Exception;
const #198 = class	#197;	//  scala/util/control/Exception
const #199 = Asciz	Catch;
const #200 = Asciz	$anonfun$1;
const #201 = Asciz	$anonfun$run$1;
const #202 = Asciz	$anonfun$tryClass$1;

{
public static void $init$(scala.util.ScalaClassLoader);
  Code:
   Stack=0, Locals=1, Args_size=1
   0:	return
  LineNumberTable: 
   line 14: 0

  LocalVariableTable: 
   Start  Length  Slot  Name   Signature
   0      1      0    $this       Lscala/util/ScalaClassLoader;


public static void run(scala.util.ScalaClassLoader, java.lang.String, scala.collection.Sequence);
  Code:
   Stack=6, Locals=5, Args_size=3
   0:	aload_0
   1:	aload_1
   2:	invokeinterface	#17,  2; //InterfaceMethod scala/util/ScalaClassLoader.tryToInitializeClass:(Ljava/lang/String;)Lscala/Option;
   7:	new	#19; //class scala/util/ScalaClassLoader$$anonfun$1
   10:	dup
   11:	aload_0
   12:	aload_1
   13:	invokespecial	#23; //Method scala/util/ScalaClassLoader$$anonfun$1."<init>":(Lscala/util/ScalaClassLoader;Ljava/lang/String;)V
   16:	invokevirtual	#29; //Method scala/Option.getOrElse:(Lscala/Function0;)Ljava/lang/Object;
   19:	checkcast	#31; //class java/lang/Class
   22:	astore_3
   23:	aload_3
   24:	ldc	#33; //String main
   26:	iconst_1
   27:	anewarray	#31; //class java/lang/Class
   30:	dup
   31:	iconst_0
   32:	ldc	#35; //class "[Ljava/lang/String;"
   34:	aastore
   35:	invokevirtual	#39; //Method java/lang/Class.getMethod:(Ljava/lang/String;[Ljava/lang/Class;)Ljava/lang/reflect/Method;
   38:	astore	4
   40:	aload	4
   42:	invokevirtual	#45; //Method java/lang/reflect/Method.getModifiers:()I
   45:	invokestatic	#51; //Method java/lang/reflect/Modifier.isStatic:(I)Z
   48:	ifeq	70
   51:	aload_0
   52:	new	#53; //class scala/util/ScalaClassLoader$$anonfun$run$1
   55:	dup
   56:	aload_0
   57:	aload_2
   58:	aload	4
   60:	invokespecial	#56; //Method scala/util/ScalaClassLoader$$anonfun$run$1."<init>":(Lscala/util/ScalaClassLoader;Lscala/collection/Sequence;Ljava/lang/reflect/Method;)V
   63:	invokeinterface	#59,  2; //InterfaceMethod scala/util/ScalaClassLoader.asContext:(Lscala/Function0;)Ljava/lang/Object;
   68:	pop
   69:	return
   70:	new	#61; //class java/lang/NoSuchMethodException
   73:	dup
   74:	new	#63; //class scala/collection/mutable/StringBuilder
   77:	dup
   78:	invokespecial	#66; //Method scala/collection/mutable/StringBuilder."<init>":()V
   81:	aload_1
   82:	invokevirtual	#70; //Method scala/collection/mutable/StringBuilder.append:(Ljava/lang/Object;)Lscala/collection/mutable/StringBuilder;
   85:	ldc	#72; //String .main is not static
   87:	invokevirtual	#70; //Method scala/collection/mutable/StringBuilder.append:(Ljava/lang/Object;)Lscala/collection/mutable/StringBuilder;
   90:	invokevirtual	#76; //Method scala/collection/mutable/StringBuilder.toString:()Ljava/lang/String;
   93:	invokespecial	#79; //Method java/lang/NoSuchMethodException."<init>":(Ljava/lang/String;)V
   96:	athrow
  LineNumberTable: 
   line 46: 0
   line 47: 7
   line 46: 16
   line 50: 23
   line 51: 40
   line 54: 51
   line 52: 70

  LocalVariableTable: 
   Start  Length  Slot  Name   Signature
   0      97      0    $this       Lscala/util/ScalaClassLoader;
   0      97      1    objectName$1       Ljava/lang/String;
   0      97      2    arguments$1       Lscala/collection/Sequence;
   23      46      3    clsToRun       Ljava/lang/Class;
   70      27      3    clsToRun       Ljava/lang/Class;
   40      29      4    method$1       Ljava/lang/reflect/Method;
   70      27      4    method$1       Ljava/lang/reflect/Method;


public static java.lang.Object create(scala.util.ScalaClassLoader, java.lang.String);
  Code:
   Stack=3, Locals=6, Args_size=2
   0:	aload_0
   1:	aload_1
   2:	invokeinterface	#17,  2; //InterfaceMethod scala/util/ScalaClassLoader.tryToInitializeClass:(Ljava/lang/String;)Lscala/Option;
   7:	astore_2
   8:	aload_2
   9:	instanceof	#91; //class scala/Some
   12:	ifeq	37
   15:	aload_2
   16:	checkcast	#91; //class scala/Some
   19:	astore_3
   20:	aload_3
   21:	invokevirtual	#95; //Method scala/Some.x:()Ljava/lang/Object;
   24:	checkcast	#31; //class java/lang/Class
   27:	astore	4
   29:	aload	4
   31:	invokevirtual	#98; //Method java/lang/Class.newInstance:()Ljava/lang/Object;
   34:	goto	74
   37:	getstatic	#104; //Field scala/None$.MODULE$:Lscala/None$;
   40:	aload_2
   41:	astore	5
   43:	dup
   44:	ifnonnull	56
   47:	pop
   48:	aload	5
   50:	ifnull	64
   53:	goto	75
   56:	aload	5
   58:	invokevirtual	#110; //Method java/lang/Object.equals:(Ljava/lang/Object;)Z
   61:	ifeq	75
   64:	aload_2
   65:	instanceof	#100; //class scala/None$
   68:	ifeq	75
   71:	aconst_null
   72:	pop
   73:	aconst_null
   74:	areturn
   75:	new	#112; //class scala/MatchError
   78:	dup
   79:	aload_2
   80:	invokevirtual	#113; //Method scala/Option.toString:()Ljava/lang/String;
   83:	invokespecial	#114; //Method scala/MatchError."<init>":(Ljava/lang/String;)V
   86:	athrow
  LineNumberTable: 
   line 38: 0
   line 39: 29
   line 38: 37
   line 40: 71
   line 38: 74

  LocalVariableTable: 
   Start  Length  Slot  Name   Signature
   0      87      0    $this       Lscala/util/ScalaClassLoader;
   0      87      1    path       Ljava/lang/String;
   8      79      2    temp1       Lscala/Option;
   20      14      3    temp2       Lscala/Some;
   29      5      4    temp3       Ljava/lang/Class;


public static scala.Option tryToInitializeClass(scala.util.ScalaClassLoader, java.lang.String);
  Code:
   Stack=3, Locals=2, Args_size=2
   0:	aload_0
   1:	aload_1
   2:	iconst_1
   3:	invokestatic	#165; //Method tryClass:(Lscala/util/ScalaClassLoader;Ljava/lang/String;Z)Lscala/Option;
   6:	areturn
  LineNumberTable: 
   line 30: 0

  LocalVariableTable: 
   Start  Length  Slot  Name   Signature
   0      7      0    $this       Lscala/util/ScalaClassLoader;
   0      7      1    path       Ljava/lang/String;


public static scala.Option tryToLoadClass(scala.util.ScalaClassLoader, java.lang.String);
  Code:
   Stack=3, Locals=2, Args_size=2
   0:	aload_0
   1:	aload_1
   2:	iconst_0
   3:	invokestatic	#165; //Method tryClass:(Lscala/util/ScalaClassLoader;Ljava/lang/String;Z)Lscala/Option;
   6:	areturn
  LineNumberTable: 
   line 28: 0

  LocalVariableTable: 
   Start  Length  Slot  Name   Signature
   0      7      0    $this       Lscala/util/ScalaClassLoader;
   0      7      1    path       Ljava/lang/String;


public static void setAsContext(scala.util.ScalaClassLoader);
  Code:
   Stack=2, Locals=1, Args_size=1
   0:	getstatic	#172; //Field scala/util/ScalaClassLoader$.MODULE$:Lscala/util/ScalaClassLoader$;
   3:	aload_0
   4:	checkcast	#174; //class java/lang/ClassLoader
   7:	invokevirtual	#178; //Method scala/util/ScalaClassLoader$.setContextLoader:(Ljava/lang/ClassLoader;)V
   10:	return
  LineNumberTable: 
   line 25: 0

  LocalVariableTable: 
   Start  Length  Slot  Name   Signature
   0      11      0    $this       Lscala/util/ScalaClassLoader;


public static java.lang.Object asContext(scala.util.ScalaClassLoader, scala.Function0);
  Code:
   Stack=2, Locals=5, Args_size=2
   0:	getstatic	#172; //Field scala/util/ScalaClassLoader$.MODULE$:Lscala/util/ScalaClassLoader$;
   3:	invokevirtual	#183; //Method scala/util/ScalaClassLoader$.getContextLoader:()Ljava/lang/ClassLoader;
   6:	astore_2
   7:	aconst_null
   8:	astore_3
   9:	getstatic	#172; //Field scala/util/ScalaClassLoader$.MODULE$:Lscala/util/ScalaClassLoader$;
   12:	aload_0
   13:	checkcast	#174; //class java/lang/ClassLoader
   16:	invokevirtual	#178; //Method scala/util/ScalaClassLoader$.setContextLoader:(Ljava/lang/ClassLoader;)V
   19:	aload_1
   20:	invokeinterface	#188,  1; //InterfaceMethod scala/Function0.apply:()Ljava/lang/Object;
   25:	astore_3
   26:	getstatic	#172; //Field scala/util/ScalaClassLoader$.MODULE$:Lscala/util/ScalaClassLoader$;
   29:	aload_2
   30:	invokevirtual	#178; //Method scala/util/ScalaClassLoader$.setContextLoader:(Ljava/lang/ClassLoader;)V
   33:	aload_3
   34:	areturn
   35:	astore	4
   37:	getstatic	#172; //Field scala/util/ScalaClassLoader$.MODULE$:Lscala/util/ScalaClassLoader$;
   40:	aload_2
   41:	invokevirtual	#178; //Method scala/util/ScalaClassLoader$.setContextLoader:(Ljava/lang/ClassLoader;)V
   44:	aload	4
   46:	athrow
  Exception table:
   from   to  target type
     9    33    35   any
  LineNumberTable: 
   line 18: 0
   line 19: 8
   line 20: 9
   line 21: 19
   line 23: 26

  LocalVariableTable: 
   Start  Length  Slot  Name   Signature
   0      47      0    $this       Lscala/util/ScalaClassLoader;
   0      47      1    action       Lscala/Function0;
   7      27      2    oldLoader       Ljava/lang/ClassLoader;
   35      12      2    oldLoader       Ljava/lang/ClassLoader;
   9      25      3    exceptionResult1       Ljava/lang/Object;
   35      12      3    exceptionResult1       Ljava/lang/Object;


}

