Compiled from "ClassLoader.scala"
public final class scala.util.ScalaClassLoader$$anonfun$run$1 extends java.lang.Object implements scala.Function0,scala.ScalaObject,java.io.Serializable
  SourceFile: "ClassLoader.scala"
  Scala: length = 0x
   
  InnerClass: 
   public final #86= #12 of #85; //$anonfun$run$1=class scala/util/ScalaClassLoader$$anonfun$run$1 of class scala/util/ScalaClassLoader
  minor version: 0
  major version: 49
  Constant pool:
const #1 = Asciz	SourceFile;
const #2 = Asciz	ClassLoader.scala;
const #3 = Asciz	method$1;
const #4 = Asciz	Ljava/lang/reflect/Method;;
const #5 = Asciz	arguments$1;
const #6 = Asciz	Lscala/collection/Sequence;;
const #7 = Asciz	<init>;
const #8 = Asciz	(Lscala/util/ScalaClassLoader;Lscala/collection/Sequence;Ljava/lang/reflect/Method;)V;
const #9 = Asciz	Code;
const #10 = Asciz	LineNumberTable;
const #11 = Asciz	scala/util/ScalaClassLoader$$anonfun$run$1;
const #12 = class	#11;	//  scala/util/ScalaClassLoader$$anonfun$run$1
const #13 = NameAndType	#5:#6;//  arguments$1:Lscala/collection/Sequence;
const #14 = Field	#12.#13;	//  scala/util/ScalaClassLoader$$anonfun$run$1.arguments$1:Lscala/collection/Sequence;
const #15 = NameAndType	#3:#4;//  method$1:Ljava/lang/reflect/Method;
const #16 = Field	#12.#15;	//  scala/util/ScalaClassLoader$$anonfun$run$1.method$1:Ljava/lang/reflect/Method;
const #17 = Asciz	java/lang/Object;
const #18 = class	#17;	//  java/lang/Object
const #19 = Asciz	()V;
const #20 = NameAndType	#7:#19;//  "<init>":()V
const #21 = Method	#18.#20;	//  java/lang/Object."<init>":()V
const #22 = Asciz	scala/Function0$class;
const #23 = class	#22;	//  scala/Function0$class
const #24 = Asciz	$init$;
const #25 = Asciz	(Lscala/Function0;)V;
const #26 = NameAndType	#24:#25;//  $init$:(Lscala/Function0;)V
const #27 = Method	#23.#26;	//  scala/Function0$class.$init$:(Lscala/Function0;)V
const #28 = Asciz	this;
const #29 = Asciz	Lscala/util/ScalaClassLoader$$anonfun$run$1;;
const #30 = Asciz	$outer;
const #31 = Asciz	Lscala/util/ScalaClassLoader;;
const #32 = Asciz	LocalVariableTable;
const #33 = Asciz	apply;
const #34 = Asciz	()Ljava/lang/Object;;
const #35 = Asciz	scala/runtime/ScalaRunTime$;
const #36 = class	#35;	//  scala/runtime/ScalaRunTime$
const #37 = Asciz	MODULE$;
const #38 = Asciz	Lscala/runtime/ScalaRunTime$;;
const #39 = NameAndType	#37:#38;//  MODULE$:Lscala/runtime/ScalaRunTime$;
const #40 = Field	#36.#39;	//  scala/runtime/ScalaRunTime$.MODULE$:Lscala/runtime/ScalaRunTime$;
const #41 = Asciz	scala/Array$;
const #42 = class	#41;	//  scala/Array$
const #43 = Asciz	Lscala/Array$;;
const #44 = NameAndType	#37:#43;//  MODULE$:Lscala/Array$;
const #45 = Field	#42.#44;	//  scala/Array$.MODULE$:Lscala/Array$;
const #46 = Asciz	[Ljava/lang/String;;
const #47 = class	#46;	//  "[Ljava/lang/String;"
const #48 = Asciz	scala/collection/generic/TraversableTemplate;
const #49 = class	#48;	//  scala/collection/generic/TraversableTemplate
const #50 = Asciz	toArray;
const #51 = Asciz	()Lscala/runtime/BoxedArray;;
const #52 = NameAndType	#50:#51;//  toArray:()Lscala/runtime/BoxedArray;
const #53 = InterfaceMethod	#49.#52;	//  scala/collection/generic/TraversableTemplate.toArray:()Lscala/runtime/BoxedArray;
const #54 = Asciz	java/lang/String;
const #55 = class	#54;	//  java/lang/String
const #56 = Asciz	arrayValue;
const #57 = Asciz	(Lscala/runtime/BoxedArray;Ljava/lang/Class;)Ljava/lang/Object;;
const #58 = NameAndType	#56:#57;//  arrayValue:(Lscala/runtime/BoxedArray;Ljava/lang/Class;)Ljava/lang/Object;
const #59 = Method	#36.#58;	//  scala/runtime/ScalaRunTime$.arrayValue:(Lscala/runtime/BoxedArray;Ljava/lang/Class;)Ljava/lang/Object;
const #60 = Asciz	scala/runtime/BoxedArray;
const #61 = class	#60;	//  scala/runtime/BoxedArray
const #62 = Asciz	boxArray;
const #63 = Asciz	(Ljava/lang/Object;)Lscala/runtime/BoxedArray;;
const #64 = NameAndType	#62:#63;//  boxArray:(Ljava/lang/Object;)Lscala/runtime/BoxedArray;
const #65 = Method	#36.#64;	//  scala/runtime/ScalaRunTime$.boxArray:(Ljava/lang/Object;)Lscala/runtime/BoxedArray;
const #66 = Asciz	(Lscala/collection/Sequence;)Lscala/runtime/BoxedArray;;
const #67 = NameAndType	#33:#66;//  apply:(Lscala/collection/Sequence;)Lscala/runtime/BoxedArray;
const #68 = Method	#42.#67;	//  scala/Array$.apply:(Lscala/collection/Sequence;)Lscala/runtime/BoxedArray;
const #69 = Asciz	[Ljava/lang/Object;;
const #70 = class	#69;	//  "[Ljava/lang/Object;"
const #71 = Asciz	java/lang/reflect/Method;
const #72 = class	#71;	//  java/lang/reflect/Method
const #73 = Asciz	invoke;
const #74 = Asciz	(Ljava/lang/Object;[Ljava/lang/Object;)Ljava/lang/Object;;
const #75 = NameAndType	#73:#74;//  invoke:(Ljava/lang/Object;[Ljava/lang/Object;)Ljava/lang/Object;
const #76 = Method	#72.#75;	//  java/lang/reflect/Method.invoke:(Ljava/lang/Object;[Ljava/lang/Object;)Ljava/lang/Object;
const #77 = Asciz	toString;
const #78 = Asciz	()Ljava/lang/String;;
const #79 = Asciz	(Lscala/Function0;)Ljava/lang/String;;
const #80 = NameAndType	#77:#79;//  toString:(Lscala/Function0;)Ljava/lang/String;
const #81 = Method	#23.#80;	//  scala/Function0$class.toString:(Lscala/Function0;)Ljava/lang/String;
const #82 = Asciz	Scala;
const #83 = Asciz	InnerClasses;
const #84 = Asciz	scala/util/ScalaClassLoader;
const #85 = class	#84;	//  scala/util/ScalaClassLoader
const #86 = Asciz	$anonfun$run$1;
const #87 = Asciz	scala/Function0;
const #88 = class	#87;	//  scala/Function0
const #89 = Asciz	scala/ScalaObject;
const #90 = class	#89;	//  scala/ScalaObject
const #91 = Asciz	java/io/Serializable;
const #92 = class	#91;	//  java/io/Serializable

{
public scala.util.ScalaClassLoader$$anonfun$run$1(scala.util.ScalaClassLoader, scala.collection.Sequence, java.lang.reflect.Method);
  Code:
   Stack=2, Locals=4, Args_size=4
   0:	aload_0
   1:	aload_2
   2:	putfield	#14; //Field arguments$1:Lscala/collection/Sequence;
   5:	aload_0
   6:	aload_3
   7:	putfield	#16; //Field method$1:Ljava/lang/reflect/Method;
   10:	aload_0
   11:	invokespecial	#21; //Method java/lang/Object."<init>":()V
   14:	aload_0
   15:	invokestatic	#27; //Method scala/Function0$class.$init$:(Lscala/Function0;)V
   18:	return
  LineNumberTable: 
   line 54: 0

  LocalVariableTable: 
   Start  Length  Slot  Name   Signature
   0      19      0    this       Lscala/util/ScalaClassLoader$$anonfun$run$1;
   0      19      1    $outer       Lscala/util/ScalaClassLoader;


public final java.lang.Object apply();
  Code:
   Stack=11, Locals=3, Args_size=1
   0:	aload_0
   1:	getfield	#16; //Field method$1:Ljava/lang/reflect/Method;
   4:	aconst_null
   5:	pop
   6:	aconst_null
   7:	getstatic	#40; //Field scala/runtime/ScalaRunTime$.MODULE$:Lscala/runtime/ScalaRunTime$;
   10:	getstatic	#45; //Field scala/Array$.MODULE$:Lscala/Array$;
   13:	getstatic	#40; //Field scala/runtime/ScalaRunTime$.MODULE$:Lscala/runtime/ScalaRunTime$;
   16:	iconst_1
   17:	anewarray	#47; //class "[Ljava/lang/String;"
   20:	dup
   21:	iconst_0
   22:	getstatic	#40; //Field scala/runtime/ScalaRunTime$.MODULE$:Lscala/runtime/ScalaRunTime$;
   25:	aload_0
   26:	getfield	#14; //Field arguments$1:Lscala/collection/Sequence;
   29:	invokeinterface	#53,  1; //InterfaceMethod scala/collection/generic/TraversableTemplate.toArray:()Lscala/runtime/BoxedArray;
   34:	ldc	#55; //class java/lang/String
   36:	invokevirtual	#59; //Method scala/runtime/ScalaRunTime$.arrayValue:(Lscala/runtime/BoxedArray;Ljava/lang/Class;)Ljava/lang/Object;
   39:	astore_2
   40:	aload_2
   41:	instanceof	#61; //class scala/runtime/BoxedArray
   44:	ifeq	62
   47:	getstatic	#40; //Field scala/runtime/ScalaRunTime$.MODULE$:Lscala/runtime/ScalaRunTime$;
   50:	aload_2
   51:	checkcast	#61; //class scala/runtime/BoxedArray
   54:	ldc	#55; //class java/lang/String
   56:	invokevirtual	#59; //Method scala/runtime/ScalaRunTime$.arrayValue:(Lscala/runtime/BoxedArray;Ljava/lang/Class;)Ljava/lang/Object;
   59:	goto	63
   62:	aload_2
   63:	checkcast	#47; //class "[Ljava/lang/String;"
   66:	aastore
   67:	invokevirtual	#65; //Method scala/runtime/ScalaRunTime$.boxArray:(Ljava/lang/Object;)Lscala/runtime/BoxedArray;
   70:	invokevirtual	#68; //Method scala/Array$.apply:(Lscala/collection/Sequence;)Lscala/runtime/BoxedArray;
   73:	invokeinterface	#53,  1; //InterfaceMethod scala/collection/generic/TraversableTemplate.toArray:()Lscala/runtime/BoxedArray;
   78:	ldc	#18; //class java/lang/Object
   80:	invokevirtual	#59; //Method scala/runtime/ScalaRunTime$.arrayValue:(Lscala/runtime/BoxedArray;Ljava/lang/Class;)Ljava/lang/Object;
   83:	astore_1
   84:	aload_1
   85:	instanceof	#61; //class scala/runtime/BoxedArray
   88:	ifeq	106
   91:	getstatic	#40; //Field scala/runtime/ScalaRunTime$.MODULE$:Lscala/runtime/ScalaRunTime$;
   94:	aload_1
   95:	checkcast	#61; //class scala/runtime/BoxedArray
   98:	ldc	#18; //class java/lang/Object
   100:	invokevirtual	#59; //Method scala/runtime/ScalaRunTime$.arrayValue:(Lscala/runtime/BoxedArray;Ljava/lang/Class;)Ljava/lang/Object;
   103:	goto	107
   106:	aload_1
   107:	checkcast	#70; //class "[Ljava/lang/Object;"
   110:	invokevirtual	#76; //Method java/lang/reflect/Method.invoke:(Ljava/lang/Object;[Ljava/lang/Object;)Ljava/lang/Object;
   113:	areturn
  LineNumberTable: 
   line 54: 0


public java.lang.String toString();
  Code:
   Stack=1, Locals=1, Args_size=1
   0:	aload_0
   1:	invokestatic	#81; //Method scala/Function0$class.toString:(Lscala/Function0;)Ljava/lang/String;
   4:	areturn
  LineNumberTable: 
   line 54: 0


}

