Compiled from "ClassLoader.scala"
public final class scala.util.ScalaClassLoader$ extends java.lang.Object implements scala.ScalaObject
  SourceFile: "ClassLoader.scala"
  Scala: length = 0x
   
  minor version: 0
  major version: 49
  Constant pool:
const #1 = Asciz	SourceFile;
const #2 = Asciz	ClassLoader.scala;
const #3 = Asciz	Scala;
const #4 = Asciz	MODULE$;
const #5 = Asciz	Lscala/util/ScalaClassLoader$;;
const #6 = Asciz	<clinit>;
const #7 = Asciz	()V;
const #8 = Asciz	Code;
const #9 = Asciz	scala/util/ScalaClassLoader$;
const #10 = class	#9;	//  scala/util/ScalaClassLoader$
const #11 = Asciz	<init>;
const #12 = NameAndType	#11:#7;//  "<init>":()V
const #13 = Method	#10.#12;	//  scala/util/ScalaClassLoader$."<init>":()V
const #14 = Asciz	LineNumberTable;
const #15 = Asciz	java/lang/Object;
const #16 = class	#15;	//  java/lang/Object
const #17 = Method	#16.#12;	//  java/lang/Object."<init>":()V
const #18 = NameAndType	#4:#5;//  MODULE$:Lscala/util/ScalaClassLoader$;
const #19 = Field	#10.#18;	//  scala/util/ScalaClassLoader$.MODULE$:Lscala/util/ScalaClassLoader$;
const #20 = Asciz	search$1;
const #21 = Asciz	(Ljava/lang/ClassLoader;)Ljava/lang/ClassLoader;;
const #22 = Asciz	equals;
const #23 = Asciz	(Ljava/lang/Object;)Z;
const #24 = NameAndType	#22:#23;//  equals:(Ljava/lang/Object;)Z
const #25 = Method	#16.#24;	//  java/lang/Object.equals:(Ljava/lang/Object;)Z
const #26 = Asciz	java/lang/ClassLoader;
const #27 = class	#26;	//  java/lang/ClassLoader
const #28 = Asciz	getParent;
const #29 = Asciz	()Ljava/lang/ClassLoader;;
const #30 = NameAndType	#28:#29;//  getParent:()Ljava/lang/ClassLoader;
const #31 = Method	#27.#30;	//  java/lang/ClassLoader.getParent:()Ljava/lang/ClassLoader;
const #32 = Asciz	this;
const #33 = Asciz	cl;
const #34 = Asciz	Ljava/lang/ClassLoader;;
const #35 = Asciz	LocalVariableTable;
const #36 = Asciz	findExtClassLoader;
const #37 = Asciz	getContextLoader;
const #38 = NameAndType	#37:#29;//  getContextLoader:()Ljava/lang/ClassLoader;
const #39 = Method	#10.#38;	//  scala/util/ScalaClassLoader$.getContextLoader:()Ljava/lang/ClassLoader;
const #40 = NameAndType	#20:#21;//  search$1:(Ljava/lang/ClassLoader;)Ljava/lang/ClassLoader;
const #41 = Method	#10.#40;	//  scala/util/ScalaClassLoader$.search$1:(Ljava/lang/ClassLoader;)Ljava/lang/ClassLoader;
const #42 = Asciz	classExists;
const #43 = Asciz	(Lscala/collection/Sequence;Ljava/lang/String;)Z;
const #44 = Asciz	fromURLs;
const #45 = Asciz	(Lscala/collection/Sequence;)Lscala/util/URLClassLoader;;
const #46 = NameAndType	#44:#45;//  fromURLs:(Lscala/collection/Sequence;)Lscala/util/URLClassLoader;
const #47 = Method	#10.#46;	//  scala/util/ScalaClassLoader$.fromURLs:(Lscala/collection/Sequence;)Lscala/util/URLClassLoader;
const #48 = Asciz	scala/util/ScalaClassLoader;
const #49 = class	#48;	//  scala/util/ScalaClassLoader
const #50 = Asciz	tryToLoadClass;
const #51 = Asciz	(Ljava/lang/String;)Lscala/Option;;
const #52 = NameAndType	#50:#51;//  tryToLoadClass:(Ljava/lang/String;)Lscala/Option;
const #53 = InterfaceMethod	#49.#52;	//  scala/util/ScalaClassLoader.tryToLoadClass:(Ljava/lang/String;)Lscala/Option;
const #54 = Asciz	scala/Option;
const #55 = class	#54;	//  scala/Option
const #56 = Asciz	isDefined;
const #57 = Asciz	()Z;
const #58 = NameAndType	#56:#57;//  isDefined:()Z
const #59 = Method	#55.#58;	//  scala/Option.isDefined:()Z
const #60 = Asciz	urls;
const #61 = Asciz	Lscala/collection/Sequence;;
const #62 = Asciz	name;
const #63 = Asciz	Ljava/lang/String;;
const #64 = Asciz	(Lscala/collection/Sequence<Ljava/net/URL;>;Ljava/lang/String;)Z;
const #65 = Asciz	Signature;
const #66 = Asciz	scala/util/URLClassLoader;
const #67 = class	#66;	//  scala/util/URLClassLoader
const #68 = Asciz	scala/collection/generic/TraversableTemplate;
const #69 = class	#68;	//  scala/collection/generic/TraversableTemplate
const #70 = Asciz	toList;
const #71 = Asciz	()Lscala/collection/immutable/List;;
const #72 = NameAndType	#70:#71;//  toList:()Lscala/collection/immutable/List;
const #73 = InterfaceMethod	#69.#72;	//  scala/collection/generic/TraversableTemplate.toList:()Lscala/collection/immutable/List;
const #74 = Asciz	defaultParentClassLoader;
const #75 = NameAndType	#74:#29;//  defaultParentClassLoader:()Ljava/lang/ClassLoader;
const #76 = Method	#10.#75;	//  scala/util/ScalaClassLoader$.defaultParentClassLoader:()Ljava/lang/ClassLoader;
const #77 = Asciz	(Lscala/collection/immutable/List;Ljava/lang/ClassLoader;)V;
const #78 = NameAndType	#11:#77;//  "<init>":(Lscala/collection/immutable/List;Ljava/lang/ClassLoader;)V
const #79 = Method	#67.#78;	//  scala/util/URLClassLoader."<init>":(Lscala/collection/immutable/List;Ljava/lang/ClassLoader;)V
const #80 = Asciz	(Lscala/collection/Sequence<Ljava/net/URL;>;)Lscala/util/URLClassLoader;;
const #81 = NameAndType	#36:#29;//  findExtClassLoader:()Ljava/lang/ClassLoader;
const #82 = Method	#10.#81;	//  scala/util/ScalaClassLoader$.findExtClassLoader:()Ljava/lang/ClassLoader;
const #83 = Asciz	getSystemLoader;
const #84 = Asciz	getSystemClassLoader;
const #85 = NameAndType	#84:#29;//  getSystemClassLoader:()Ljava/lang/ClassLoader;
const #86 = Method	#27.#85;	//  java/lang/ClassLoader.getSystemClassLoader:()Ljava/lang/ClassLoader;
const #87 = Asciz	java/lang/Thread;
const #88 = class	#87;	//  java/lang/Thread
const #89 = Asciz	currentThread;
const #90 = Asciz	()Ljava/lang/Thread;;
const #91 = NameAndType	#89:#90;//  currentThread:()Ljava/lang/Thread;
const #92 = Method	#88.#91;	//  java/lang/Thread.currentThread:()Ljava/lang/Thread;
const #93 = Asciz	getContextClassLoader;
const #94 = NameAndType	#93:#29;//  getContextClassLoader:()Ljava/lang/ClassLoader;
const #95 = Method	#88.#94;	//  java/lang/Thread.getContextClassLoader:()Ljava/lang/ClassLoader;
const #96 = Asciz	setContextLoader;
const #97 = Asciz	(Ljava/lang/ClassLoader;)V;
const #98 = Asciz	setContextClassLoader;
const #99 = NameAndType	#98:#97;//  setContextClassLoader:(Ljava/lang/ClassLoader;)V
const #100 = Method	#88.#99;	//  java/lang/Thread.setContextClassLoader:(Ljava/lang/ClassLoader;)V
const #101 = Asciz	scala/ScalaObject;
const #102 = class	#101;	//  scala/ScalaObject

{
public static final scala.util.ScalaClassLoader$ MODULE$;

public static {};
  Code:
   Stack=1, Locals=0, Args_size=0
   0:	new	#10; //class scala/util/ScalaClassLoader$
   3:	invokespecial	#13; //Method "<init>":()V
   6:	return

public java.lang.ClassLoader findExtClassLoader();
  Code:
   Stack=2, Locals=1, Args_size=1
   0:	aload_0
   1:	aload_0
   2:	invokevirtual	#39; //Method getContextLoader:()Ljava/lang/ClassLoader;
   5:	invokespecial	#41; //Method search$1:(Ljava/lang/ClassLoader;)Ljava/lang/ClassLoader;
   8:	areturn
  LineNumberTable: 
   line 90: 0


public boolean classExists(scala.collection.Sequence, java.lang.String);
  Code:
   Stack=2, Locals=3, Args_size=3
   0:	aload_0
   1:	aload_1
   2:	invokevirtual	#47; //Method fromURLs:(Lscala/collection/Sequence;)Lscala/util/URLClassLoader;
   5:	aload_2
   6:	invokeinterface	#53,  2; //InterfaceMethod scala/util/ScalaClassLoader.tryToLoadClass:(Ljava/lang/String;)Lscala/Option;
   11:	invokevirtual	#59; //Method scala/Option.isDefined:()Z
   14:	ireturn
  LineNumberTable: 
   line 77: 0

  LocalVariableTable: 
   Start  Length  Slot  Name   Signature
   0      15      0    this       Lscala/util/ScalaClassLoader$;
   0      15      1    urls       Lscala/collection/Sequence;
   0      15      2    name       Ljava/lang/String;

  Signature: length = 0x2
   00 40 

public scala.util.URLClassLoader fromURLs(scala.collection.Sequence);
  Code:
   Stack=4, Locals=2, Args_size=2
   0:	new	#67; //class scala/util/URLClassLoader
   3:	dup
   4:	aload_1
   5:	invokeinterface	#73,  1; //InterfaceMethod scala/collection/generic/TraversableTemplate.toList:()Lscala/collection/immutable/List;
   10:	aload_0
   11:	invokevirtual	#76; //Method defaultParentClassLoader:()Ljava/lang/ClassLoader;
   14:	invokespecial	#79; //Method scala/util/URLClassLoader."<init>":(Lscala/collection/immutable/List;Ljava/lang/ClassLoader;)V
   17:	areturn
  LineNumberTable: 
   line 73: 0

  LocalVariableTable: 
   Start  Length  Slot  Name   Signature
   0      18      0    this       Lscala/util/ScalaClassLoader$;
   0      18      1    urls       Lscala/collection/Sequence;

  Signature: length = 0x2
   00 50 

public java.lang.ClassLoader defaultParentClassLoader();
  Code:
   Stack=1, Locals=1, Args_size=1
   0:	aload_0
   1:	invokevirtual	#82; //Method findExtClassLoader:()Ljava/lang/ClassLoader;
   4:	areturn
  LineNumberTable: 
   line 70: 0


public java.lang.ClassLoader getSystemLoader();
  Code:
   Stack=1, Locals=1, Args_size=1
   0:	invokestatic	#86; //Method java/lang/ClassLoader.getSystemClassLoader:()Ljava/lang/ClassLoader;
   3:	areturn
  LineNumberTable: 
   line 69: 0


public java.lang.ClassLoader getContextLoader();
  Code:
   Stack=1, Locals=1, Args_size=1
   0:	invokestatic	#92; //Method java/lang/Thread.currentThread:()Ljava/lang/Thread;
   3:	invokevirtual	#95; //Method java/lang/Thread.getContextClassLoader:()Ljava/lang/ClassLoader;
   6:	areturn
  LineNumberTable: 
   line 68: 0


public void setContextLoader(java.lang.ClassLoader);
  Code:
   Stack=2, Locals=2, Args_size=2
   0:	invokestatic	#92; //Method java/lang/Thread.currentThread:()Ljava/lang/Thread;
   3:	aload_1
   4:	invokevirtual	#100; //Method java/lang/Thread.setContextClassLoader:(Ljava/lang/ClassLoader;)V
   7:	return
  LineNumberTable: 
   line 67: 0

  LocalVariableTable: 
   Start  Length  Slot  Name   Signature
   0      8      0    this       Lscala/util/ScalaClassLoader$;
   0      8      1    cl       Ljava/lang/ClassLoader;


}

