Compiled from "Sorting.scala"
public final class scala.util.Sorting$$anonfun$main$1 extends java.lang.Object implements scala.Function1,scala.ScalaObject,java.io.Serializable
  SourceFile: "Sorting.scala"
  Scala: length = 0x
   
  InnerClass: 
   public final #86= #9 of #85; //$anonfun$main$1=class scala/util/Sorting$$anonfun$main$1 of class scala/util/Sorting
  minor version: 0
  major version: 49
  Constant pool:
const #1 = Asciz	SourceFile;
const #2 = Asciz	Sorting.scala;
const #3 = Asciz	<clinit>;
const #4 = Asciz	()V;
const #5 = Asciz	Code;
const #6 = Asciz	serialVersionUID;
const #7 = Asciz	J;
const #8 = Asciz	scala/util/Sorting$$anonfun$main$1;
const #9 = class	#8;	//  scala/util/Sorting$$anonfun$main$1
const #10 = NameAndType	#6:#7;//  serialVersionUID:J
const #11 = Field	#9.#10;	//  scala/util/Sorting$$anonfun$main$1.serialVersionUID:J
const #12 = Asciz	<init>;
const #13 = Asciz	LineNumberTable;
const #14 = Asciz	java/lang/Object;
const #15 = class	#14;	//  java/lang/Object
const #16 = NameAndType	#12:#4;//  "<init>":()V
const #17 = Method	#15.#16;	//  java/lang/Object."<init>":()V
const #18 = Asciz	scala/Function1$class;
const #19 = class	#18;	//  scala/Function1$class
const #20 = Asciz	$init$;
const #21 = Asciz	(Lscala/Function1;)V;
const #22 = NameAndType	#20:#21;//  $init$:(Lscala/Function1;)V
const #23 = Method	#19.#22;	//  scala/Function1$class.$init$:(Lscala/Function1;)V
const #24 = Asciz	apply;
const #25 = Asciz	(Ljava/lang/Object;)Ljava/lang/Object;;
const #26 = Asciz	scala/Tuple2;
const #27 = class	#26;	//  scala/Tuple2
const #28 = Asciz	(Lscala/Tuple2;)Lscala/math/Ordered;;
const #29 = NameAndType	#24:#28;//  apply:(Lscala/Tuple2;)Lscala/math/Ordered;
const #30 = Method	#9.#29;	//  scala/util/Sorting$$anonfun$main$1.apply:(Lscala/Tuple2;)Lscala/math/Ordered;
const #31 = Asciz	this;
const #32 = Asciz	Lscala/util/Sorting$$anonfun$main$1;;
const #33 = Asciz	v1;
const #34 = Asciz	Ljava/lang/Object;;
const #35 = Asciz	LocalVariableTable;
const #36 = Asciz	scala/math/Ordered$;
const #37 = class	#36;	//  scala/math/Ordered$
const #38 = Asciz	MODULE$;
const #39 = Asciz	Lscala/math/Ordered$;;
const #40 = NameAndType	#38:#39;//  MODULE$:Lscala/math/Ordered$;
const #41 = Field	#37.#40;	//  scala/math/Ordered$.MODULE$:Lscala/math/Ordered$;
const #42 = Asciz	scala/math/Ordering$;
const #43 = class	#42;	//  scala/math/Ordering$
const #44 = Asciz	Lscala/math/Ordering$;;
const #45 = NameAndType	#38:#44;//  MODULE$:Lscala/math/Ordering$;
const #46 = Field	#43.#45;	//  scala/math/Ordering$.MODULE$:Lscala/math/Ordering$;
const #47 = Asciz	scala/math/Ordering$Int$;
const #48 = class	#47;	//  scala/math/Ordering$Int$
const #49 = Asciz	Lscala/math/Ordering$Int$;;
const #50 = NameAndType	#38:#49;//  MODULE$:Lscala/math/Ordering$Int$;
const #51 = Field	#48.#50;	//  scala/math/Ordering$Int$.MODULE$:Lscala/math/Ordering$Int$;
const #52 = Asciz	scala/math/Ordering$String$;
const #53 = class	#52;	//  scala/math/Ordering$String$
const #54 = Asciz	Lscala/math/Ordering$String$;;
const #55 = NameAndType	#38:#54;//  MODULE$:Lscala/math/Ordering$String$;
const #56 = Field	#53.#55;	//  scala/math/Ordering$String$.MODULE$:Lscala/math/Ordering$String$;
const #57 = Asciz	Tuple2;
const #58 = Asciz	(Lscala/math/Ordering;Lscala/math/Ordering;)Lscala/math/Ordering;;
const #59 = NameAndType	#57:#58;//  Tuple2:(Lscala/math/Ordering;Lscala/math/Ordering;)Lscala/math/Ordering;
const #60 = Method	#43.#59;	//  scala/math/Ordering$.Tuple2:(Lscala/math/Ordering;Lscala/math/Ordering;)Lscala/math/Ordering;
const #61 = Asciz	orderingToOrdered;
const #62 = Asciz	(Ljava/lang/Object;Lscala/math/Ordering;)Lscala/math/Ordered;;
const #63 = NameAndType	#61:#62;//  orderingToOrdered:(Ljava/lang/Object;Lscala/math/Ordering;)Lscala/math/Ordered;
const #64 = Method	#37.#63;	//  scala/math/Ordered$.orderingToOrdered:(Ljava/lang/Object;Lscala/math/Ordering;)Lscala/math/Ordered;
const #65 = Asciz	(Lscala/Tuple2<Ljava/lang/Integer;Ljava/lang/String;>;)Lscala/math/Ordered<Lscala/Tuple2<Ljava/lang/Integer;Ljava/lang/String;>;>;;
const #66 = Asciz	Signature;
const #67 = Asciz	andThen;
const #68 = Asciz	(Lscala/Function1;)Lscala/Function1;;
const #69 = Asciz	(Lscala/Function1;Lscala/Function1;)Lscala/Function1;;
const #70 = NameAndType	#67:#69;//  andThen:(Lscala/Function1;Lscala/Function1;)Lscala/Function1;
const #71 = Method	#19.#70;	//  scala/Function1$class.andThen:(Lscala/Function1;Lscala/Function1;)Lscala/Function1;
const #72 = Asciz	g;
const #73 = Asciz	Lscala/Function1;;
const #74 = Asciz	compose;
const #75 = NameAndType	#74:#69;//  compose:(Lscala/Function1;Lscala/Function1;)Lscala/Function1;
const #76 = Method	#19.#75;	//  scala/Function1$class.compose:(Lscala/Function1;Lscala/Function1;)Lscala/Function1;
const #77 = Asciz	toString;
const #78 = Asciz	()Ljava/lang/String;;
const #79 = Asciz	(Lscala/Function1;)Ljava/lang/String;;
const #80 = NameAndType	#77:#79;//  toString:(Lscala/Function1;)Ljava/lang/String;
const #81 = Method	#19.#80;	//  scala/Function1$class.toString:(Lscala/Function1;)Ljava/lang/String;
const #82 = Asciz	Scala;
const #83 = Asciz	InnerClasses;
const #84 = Asciz	scala/util/Sorting;
const #85 = class	#84;	//  scala/util/Sorting
const #86 = Asciz	$anonfun$main$1;
const #87 = Asciz	scala/Function1;
const #88 = class	#87;	//  scala/Function1
const #89 = Asciz	scala/ScalaObject;
const #90 = class	#89;	//  scala/ScalaObject
const #91 = Asciz	java/io/Serializable;
const #92 = class	#91;	//  java/io/Serializable

{
public static final long serialVersionUID;

public static {};
  Code:
   Stack=2, Locals=0, Args_size=0
   0:	lconst_0
   1:	putstatic	#11; //Field serialVersionUID:J
   4:	return

public scala.util.Sorting$$anonfun$main$1();
  Code:
   Stack=1, Locals=1, Args_size=1
   0:	aload_0
   1:	invokespecial	#17; //Method java/lang/Object."<init>":()V
   4:	aload_0
   5:	invokestatic	#23; //Method scala/Function1$class.$init$:(Lscala/Function1;)V
   8:	return
  LineNumberTable: 
   line 568: 0


public final java.lang.Object apply(java.lang.Object);
  Code:
   Stack=2, Locals=2, Args_size=2
   0:	aload_0
   1:	aload_1
   2:	checkcast	#27; //class scala/Tuple2
   5:	invokevirtual	#30; //Method apply:(Lscala/Tuple2;)Lscala/math/Ordered;
   8:	areturn
  LineNumberTable: 
   line 568: 0

  LocalVariableTable: 
   Start  Length  Slot  Name   Signature
   0      9      0    this       Lscala/util/Sorting$$anonfun$main$1;
   0      9      1    v1       Ljava/lang/Object;


public final scala.math.Ordered apply(scala.Tuple2);
  Code:
   Stack=5, Locals=2, Args_size=2
   0:	getstatic	#41; //Field scala/math/Ordered$.MODULE$:Lscala/math/Ordered$;
   3:	aload_1
   4:	getstatic	#46; //Field scala/math/Ordering$.MODULE$:Lscala/math/Ordering$;
   7:	getstatic	#51; //Field scala/math/Ordering$Int$.MODULE$:Lscala/math/Ordering$Int$;
   10:	getstatic	#56; //Field scala/math/Ordering$String$.MODULE$:Lscala/math/Ordering$String$;
   13:	invokevirtual	#60; //Method scala/math/Ordering$.Tuple2:(Lscala/math/Ordering;Lscala/math/Ordering;)Lscala/math/Ordering;
   16:	invokevirtual	#64; //Method scala/math/Ordered$.orderingToOrdered:(Ljava/lang/Object;Lscala/math/Ordering;)Lscala/math/Ordered;
   19:	areturn
  LineNumberTable: 
   line 568: 0

  Signature: length = 0x2
   00 41 

public scala.Function1 andThen(scala.Function1);
  Code:
   Stack=2, Locals=2, Args_size=2
   0:	aload_0
   1:	aload_1
   2:	invokestatic	#71; //Method scala/Function1$class.andThen:(Lscala/Function1;Lscala/Function1;)Lscala/Function1;
   5:	areturn
  LineNumberTable: 
   line 568: 0

  LocalVariableTable: 
   Start  Length  Slot  Name   Signature
   0      6      0    this       Lscala/util/Sorting$$anonfun$main$1;
   0      6      1    g       Lscala/Function1;


public scala.Function1 compose(scala.Function1);
  Code:
   Stack=2, Locals=2, Args_size=2
   0:	aload_0
   1:	aload_1
   2:	invokestatic	#76; //Method scala/Function1$class.compose:(Lscala/Function1;Lscala/Function1;)Lscala/Function1;
   5:	areturn
  LineNumberTable: 
   line 568: 0

  LocalVariableTable: 
   Start  Length  Slot  Name   Signature
   0      6      0    this       Lscala/util/Sorting$$anonfun$main$1;
   0      6      1    g       Lscala/Function1;


public java.lang.String toString();
  Code:
   Stack=1, Locals=1, Args_size=1
   0:	aload_0
   1:	invokestatic	#81; //Method scala/Function1$class.toString:(Lscala/Function1;)Ljava/lang/String;
   4:	areturn
  LineNumberTable: 
   line 568: 0


}

