Compiled from "Sorting.scala"
public final class scala.util.Sorting$$anonfun$main$1 extends java.lang.Object implements scala.Function1,scala.ScalaObject,java.io.Serializable
  SourceFile: "Sorting.scala"
  Scala: length = 0x
   
  InnerClass: 
   public final $anonfun$main$1=class scala/util/Sorting$$anonfun$main$1 of class scala/util/Sorting
  minor version: 0
  major version: 49
  Constant pool:
Asciz	SourceFile;
Asciz	Sorting.scala;
Asciz	<clinit>;
Asciz	()V;
Asciz	Code;
Asciz	serialVersionUID;
Asciz	J;
Asciz	scala/util/Sorting$$anonfun$main$1;
class	scala/util/Sorting$$anonfun$main$1
NameAndType	serialVersionUID:J
Field	scala/util/Sorting$$anonfun$main$1.serialVersionUID:J
Asciz	<init>;
Asciz	LineNumberTable;
Asciz	java/lang/Object;
class	java/lang/Object
NameAndType	"<init>":()V
Method	java/lang/Object."<init>":()V
Asciz	scala/Function1$class;
class	scala/Function1$class
Asciz	$init$;
Asciz	(Lscala/Function1;)V;
NameAndType	$init$:(Lscala/Function1;)V
Method	scala/Function1$class.$init$:(Lscala/Function1;)V
Asciz	apply;
Asciz	(Ljava/lang/Object;)Ljava/lang/Object;;
Asciz	scala/Tuple2;
class	scala/Tuple2
Asciz	(Lscala/Tuple2;)Lscala/math/Ordered;;
NameAndType	apply:(Lscala/Tuple2;)Lscala/math/Ordered;
Method	scala/util/Sorting$$anonfun$main$1.apply:(Lscala/Tuple2;)Lscala/math/Ordered;
Asciz	this;
Asciz	Lscala/util/Sorting$$anonfun$main$1;;
Asciz	v1;
Asciz	Ljava/lang/Object;;
Asciz	LocalVariableTable;
Asciz	scala/math/Ordered$;
class	scala/math/Ordered$
Asciz	MODULE$;
Asciz	Lscala/math/Ordered$;;
NameAndType	MODULE$:Lscala/math/Ordered$;
Field	scala/math/Ordered$.MODULE$:Lscala/math/Ordered$;
Asciz	scala/math/Ordering$;
class	scala/math/Ordering$
Asciz	Lscala/math/Ordering$;;
NameAndType	MODULE$:Lscala/math/Ordering$;
Field	scala/math/Ordering$.MODULE$:Lscala/math/Ordering$;
Asciz	scala/math/Ordering$Int$;
class	scala/math/Ordering$Int$
Asciz	Lscala/math/Ordering$Int$;;
NameAndType	MODULE$:Lscala/math/Ordering$Int$;
Field	scala/math/Ordering$Int$.MODULE$:Lscala/math/Ordering$Int$;
Asciz	scala/math/Ordering$String$;
class	scala/math/Ordering$String$
Asciz	Lscala/math/Ordering$String$;;
NameAndType	MODULE$:Lscala/math/Ordering$String$;
Field	scala/math/Ordering$String$.MODULE$:Lscala/math/Ordering$String$;
Asciz	Tuple2;
Asciz	(Lscala/math/Ordering;Lscala/math/Ordering;)Lscala/math/Ordering;;
NameAndType	Tuple2:(Lscala/math/Ordering;Lscala/math/Ordering;)Lscala/math/Ordering;
Method	scala/math/Ordering$.Tuple2:(Lscala/math/Ordering;Lscala/math/Ordering;)Lscala/math/Ordering;
Asciz	orderingToOrdered;
Asciz	(Ljava/lang/Object;Lscala/math/Ordering;)Lscala/math/Ordered;;
NameAndType	orderingToOrdered:(Ljava/lang/Object;Lscala/math/Ordering;)Lscala/math/Ordered;
Method	scala/math/Ordered$.orderingToOrdered:(Ljava/lang/Object;Lscala/math/Ordering;)Lscala/math/Ordered;
Asciz	(Lscala/Tuple2<Ljava/lang/Integer;Ljava/lang/String;>;)Lscala/math/Ordered<Lscala/Tuple2<Ljava/lang/Integer;Ljava/lang/String;>;>;;
Asciz	Signature;
Asciz	andThen;
Asciz	(Lscala/Function1;)Lscala/Function1;;
Asciz	(Lscala/Function1;Lscala/Function1;)Lscala/Function1;;
NameAndType	andThen:(Lscala/Function1;Lscala/Function1;)Lscala/Function1;
Method	scala/Function1$class.andThen:(Lscala/Function1;Lscala/Function1;)Lscala/Function1;
Asciz	g;
Asciz	Lscala/Function1;;
Asciz	compose;
NameAndType	compose:(Lscala/Function1;Lscala/Function1;)Lscala/Function1;
Method	scala/Function1$class.compose:(Lscala/Function1;Lscala/Function1;)Lscala/Function1;
Asciz	toString;
Asciz	()Ljava/lang/String;;
Asciz	(Lscala/Function1;)Ljava/lang/String;;
NameAndType	toString:(Lscala/Function1;)Ljava/lang/String;
Method	scala/Function1$class.toString:(Lscala/Function1;)Ljava/lang/String;
Asciz	Scala;
Asciz	InnerClasses;
Asciz	scala/util/Sorting;
class	scala/util/Sorting
Asciz	$anonfun$main$1;
Asciz	scala/Function1;
class	scala/Function1
Asciz	scala/ScalaObject;
class	scala/ScalaObject
Asciz	java/io/Serializable;
class	java/io/Serializable

{
public static final long serialVersionUID;
  Signature: J

public static {};
  Signature: ()V
  Code:
   Stack=2, Locals=0, Args_size=0
	lconst_0
	putstatic	Field serialVersionUID:J
	return
  Labels:

public scala.util.Sorting$$anonfun$main$1();
  Signature: ()V
  Code:
   Stack=1, Locals=1, Args_size=1
	aload_0
	invokespecial	Method java/lang/Object."<init>":()V
	aload_0
	invokestatic	Method scala/Function1$class.$init$:(Lscala/Function1;)V
	return
  Labels:

public final java.lang.Object apply(java.lang.Object);
  Signature: (Ljava/lang/Object;)Ljava/lang/Object;
  Code:
   Stack=2, Locals=2, Args_size=2
	aload_0
	aload_1
	checkcast	class scala/Tuple2
	invokevirtual	Method apply:(Lscala/Tuple2;)Lscala/math/Ordered;
	areturn
  Labels:
  LocalVariableTable: 
   Start  Length  Slot  Name   Signature
   0      9      0    this       Lscala/util/Sorting$$anonfun$main$1;
   0      9      1    v1       Ljava/lang/Object;


public final scala.math.Ordered apply(scala.Tuple2);
  Signature: (Lscala/Tuple2;)Lscala/math/Ordered;
  Code:
   Stack=5, Locals=2, Args_size=2
	getstatic	Field scala/math/Ordered$.MODULE$:Lscala/math/Ordered$;
	aload_1
	getstatic	Field scala/math/Ordering$.MODULE$:Lscala/math/Ordering$;
	getstatic	Field scala/math/Ordering$Int$.MODULE$:Lscala/math/Ordering$Int$;
	getstatic	Field scala/math/Ordering$String$.MODULE$:Lscala/math/Ordering$String$;
	invokevirtual	Method scala/math/Ordering$.Tuple2:(Lscala/math/Ordering;Lscala/math/Ordering;)Lscala/math/Ordering;
	invokevirtual	Method scala/math/Ordered$.orderingToOrdered:(Ljava/lang/Object;Lscala/math/Ordering;)Lscala/math/Ordered;
	areturn
  Labels:
  Signature: length = 0x2
   00 41 

public scala.Function1 andThen(scala.Function1);
  Signature: (Lscala/Function1;)Lscala/Function1;
  Code:
   Stack=2, Locals=2, Args_size=2
	aload_0
	aload_1
	invokestatic	Method scala/Function1$class.andThen:(Lscala/Function1;Lscala/Function1;)Lscala/Function1;
	areturn
  Labels:
  LocalVariableTable: 
   Start  Length  Slot  Name   Signature
   0      6      0    this       Lscala/util/Sorting$$anonfun$main$1;
   0      6      1    g       Lscala/Function1;


public scala.Function1 compose(scala.Function1);
  Signature: (Lscala/Function1;)Lscala/Function1;
  Code:
   Stack=2, Locals=2, Args_size=2
	aload_0
	aload_1
	invokestatic	Method scala/Function1$class.compose:(Lscala/Function1;Lscala/Function1;)Lscala/Function1;
	areturn
  Labels:
  LocalVariableTable: 
   Start  Length  Slot  Name   Signature
   0      6      0    this       Lscala/util/Sorting$$anonfun$main$1;
   0      6      1    g       Lscala/Function1;


public java.lang.String toString();
  Signature: ()Ljava/lang/String;
  Code:
   Stack=1, Locals=1, Args_size=1
	aload_0
	invokestatic	Method scala/Function1$class.toString:(Lscala/Function1;)Ljava/lang/String;
	areturn
  Labels:

}

