Compiled from "Sorting.scala"
public final class scala.util.Sorting$$anonfun$stableSort$3 extends scala.runtime.AbstractFunction2 implements java.io.Serializable
  SourceFile: "Sorting.scala"
  Scala: length = 0x
   
  InnerClass: 
   public final $anonfun$stableSort$3=class scala/util/Sorting$$anonfun$stableSort$3 of class scala/util/Sorting
  minor version: 0
  major version: 49
  Constant pool:
Asciz	SourceFile;
Asciz	Sorting.scala;
Asciz	<clinit>;
Asciz	()V;
Asciz	Code;
Asciz	serialVersionUID;
Asciz	J;
Asciz	scala/util/Sorting$$anonfun$stableSort$3;
class	scala/util/Sorting$$anonfun$stableSort$3
NameAndType	serialVersionUID:J
Field	scala/util/Sorting$$anonfun$stableSort$3.serialVersionUID:J
Asciz	evidence$10$1;
Asciz	Lscala/Function1;;
Asciz	f$1;
Asciz	<init>;
Asciz	(Lscala/Function1;Lscala/Function1;)V;
Asciz	LineNumberTable;
NameAndType	f$1:Lscala/Function1;
Field	scala/util/Sorting$$anonfun$stableSort$3.f$1:Lscala/Function1;
NameAndType	evidence$10$1:Lscala/Function1;
Field	scala/util/Sorting$$anonfun$stableSort$3.evidence$10$1:Lscala/Function1;
Asciz	scala/runtime/AbstractFunction2;
class	scala/runtime/AbstractFunction2
NameAndType	"<init>":()V
Method	scala/runtime/AbstractFunction2."<init>":()V
Asciz	apply;
Asciz	(Ljava/lang/Object;Ljava/lang/Object;)Ljava/lang/Object;;
Asciz	(Ljava/lang/Object;Ljava/lang/Object;)Z;
NameAndType	apply:(Ljava/lang/Object;Ljava/lang/Object;)Z
Method	scala/util/Sorting$$anonfun$stableSort$3.apply:(Ljava/lang/Object;Ljava/lang/Object;)Z
Asciz	scala/runtime/BoxesRunTime;
class	scala/runtime/BoxesRunTime
Asciz	boxToBoolean;
Asciz	(Z)Ljava/lang/Boolean;;
NameAndType	boxToBoolean:(Z)Ljava/lang/Boolean;
Method	scala/runtime/BoxesRunTime.boxToBoolean:(Z)Ljava/lang/Boolean;
Asciz	this;
Asciz	Lscala/util/Sorting$$anonfun$stableSort$3;;
Asciz	v1;
Asciz	Ljava/lang/Object;;
Asciz	v2;
Asciz	LocalVariableTable;
Asciz	scala/Function1;
class	scala/Function1
Asciz	(Ljava/lang/Object;)Ljava/lang/Object;;
NameAndType	apply:(Ljava/lang/Object;)Ljava/lang/Object;
InterfaceMethod	scala/Function1.apply:(Ljava/lang/Object;)Ljava/lang/Object;
Asciz	scala/math/Ordered;
class	scala/math/Ordered
Asciz	$less;
Asciz	(Ljava/lang/Object;)Z;
NameAndType	$less:(Ljava/lang/Object;)Z
InterfaceMethod	scala/math/Ordered.$less:(Ljava/lang/Object;)Z
Asciz	a;
Asciz	b;
Asciz	(TK;TK;)Z;
Asciz	Signature;
Asciz	Scala;
Asciz	InnerClasses;
Asciz	scala/util/Sorting;
class	scala/util/Sorting
Asciz	$anonfun$stableSort$3;
Asciz	java/io/Serializable;
class	java/io/Serializable

{
public static final long serialVersionUID;
  Signature: J

public final scala.Function1 evidence$10$1;
  Signature: Lscala/Function1;

public final scala.Function1 f$1;
  Signature: Lscala/Function1;

public static {};
  Signature: ()V
  Code:
   Stack=2, Locals=0, Args_size=0
	lconst_0
	putstatic	Field serialVersionUID:J
	return
  Labels:

public scala.util.Sorting$$anonfun$stableSort$3(scala.Function1, scala.Function1);
  Signature: (Lscala/Function1;Lscala/Function1;)V
  Code:
   Stack=2, Locals=3, Args_size=3
	aload_0
	aload_1
	putfield	Field f$1:Lscala/Function1;
	aload_0
	aload_2
	putfield	Field evidence$10$1:Lscala/Function1;
	aload_0
	invokespecial	Method scala/runtime/AbstractFunction2."<init>":()V
	return
  Labels:

public final java.lang.Object apply(java.lang.Object, java.lang.Object);
  Signature: (Ljava/lang/Object;Ljava/lang/Object;)Ljava/lang/Object;
  Code:
   Stack=3, Locals=4, Args_size=3
	aload_0
	aload_1
	aload_2
	invokevirtual	Method apply:(Ljava/lang/Object;Ljava/lang/Object;)Z
	istore_3
	iload_3
	invokestatic	Method scala/runtime/BoxesRunTime.boxToBoolean:(Z)Ljava/lang/Boolean;
	areturn
  Labels:
  LocalVariableTable: 
   Start  Length  Slot  Name   Signature
   0      12      0    this       Lscala/util/Sorting$$anonfun$stableSort$3;
   0      12      1    v1       Ljava/lang/Object;
   0      12      2    v2       Ljava/lang/Object;


public final boolean apply(java.lang.Object, java.lang.Object);
  Signature: (Ljava/lang/Object;Ljava/lang/Object;)Z
  Code:
   Stack=3, Locals=3, Args_size=3
	aload_0
	getfield	Field evidence$10$1:Lscala/Function1;
	aload_0
	getfield	Field f$1:Lscala/Function1;
	aload_1
	invokeinterface	InterfaceMethod scala/Function1.apply:(Ljava/lang/Object;)Ljava/lang/Object;
	invokeinterface	InterfaceMethod scala/Function1.apply:(Ljava/lang/Object;)Ljava/lang/Object;
	checkcast	class scala/math/Ordered
	aload_0
	getfield	Field f$1:Lscala/Function1;
	aload_2
	invokeinterface	InterfaceMethod scala/Function1.apply:(Ljava/lang/Object;)Ljava/lang/Object;
	invokeinterface	InterfaceMethod scala/math/Ordered.$less:(Ljava/lang/Object;)Z
	ireturn
  Labels:
  LocalVariableTable: 
   Start  Length  Slot  Name   Signature
   0      38      0    this       Lscala/util/Sorting$$anonfun$stableSort$3;
   0      38      1    a       Ljava/lang/Object;
   0      38      2    b       Ljava/lang/Object;

  Signature: length = 0x2
   00 38 

}

