Compiled from "Sorting.scala"
public final class scala.util.Sorting$$anonfun$stableSort$3 extends java.lang.Object implements scala.Function2,scala.ScalaObject,java.io.Serializable
  SourceFile: "Sorting.scala"
  Scala: length = 0x
   
  InnerClass: 
   public final #78= #9 of #77; //$anonfun$stableSort$3=class scala/util/Sorting$$anonfun$stableSort$3 of class scala/util/Sorting
  minor version: 0
  major version: 49
  Constant pool:
const #1 = Asciz	SourceFile;
const #2 = Asciz	Sorting.scala;
const #3 = Asciz	<clinit>;
const #4 = Asciz	()V;
const #5 = Asciz	Code;
const #6 = Asciz	serialVersionUID;
const #7 = Asciz	J;
const #8 = Asciz	scala/util/Sorting$$anonfun$stableSort$3;
const #9 = class	#8;	//  scala/util/Sorting$$anonfun$stableSort$3
const #10 = NameAndType	#6:#7;//  serialVersionUID:J
const #11 = Field	#9.#10;	//  scala/util/Sorting$$anonfun$stableSort$3.serialVersionUID:J
const #12 = Asciz	evidence$10$1;
const #13 = Asciz	Lscala/Function1;;
const #14 = Asciz	f$1;
const #15 = Asciz	<init>;
const #16 = Asciz	(Lscala/Function1;Lscala/Function1;)V;
const #17 = Asciz	LineNumberTable;
const #18 = NameAndType	#14:#13;//  f$1:Lscala/Function1;
const #19 = Field	#9.#18;	//  scala/util/Sorting$$anonfun$stableSort$3.f$1:Lscala/Function1;
const #20 = NameAndType	#12:#13;//  evidence$10$1:Lscala/Function1;
const #21 = Field	#9.#20;	//  scala/util/Sorting$$anonfun$stableSort$3.evidence$10$1:Lscala/Function1;
const #22 = Asciz	java/lang/Object;
const #23 = class	#22;	//  java/lang/Object
const #24 = NameAndType	#15:#4;//  "<init>":()V
const #25 = Method	#23.#24;	//  java/lang/Object."<init>":()V
const #26 = Asciz	scala/Function2$class;
const #27 = class	#26;	//  scala/Function2$class
const #28 = Asciz	$init$;
const #29 = Asciz	(Lscala/Function2;)V;
const #30 = NameAndType	#28:#29;//  $init$:(Lscala/Function2;)V
const #31 = Method	#27.#30;	//  scala/Function2$class.$init$:(Lscala/Function2;)V
const #32 = Asciz	apply;
const #33 = Asciz	(Ljava/lang/Object;Ljava/lang/Object;)Ljava/lang/Object;;
const #34 = Asciz	(Ljava/lang/Object;Ljava/lang/Object;)Z;
const #35 = NameAndType	#32:#34;//  apply:(Ljava/lang/Object;Ljava/lang/Object;)Z
const #36 = Method	#9.#35;	//  scala/util/Sorting$$anonfun$stableSort$3.apply:(Ljava/lang/Object;Ljava/lang/Object;)Z
const #37 = Asciz	scala/runtime/BoxesRunTime;
const #38 = class	#37;	//  scala/runtime/BoxesRunTime
const #39 = Asciz	boxToBoolean;
const #40 = Asciz	(Z)Ljava/lang/Boolean;;
const #41 = NameAndType	#39:#40;//  boxToBoolean:(Z)Ljava/lang/Boolean;
const #42 = Method	#38.#41;	//  scala/runtime/BoxesRunTime.boxToBoolean:(Z)Ljava/lang/Boolean;
const #43 = Asciz	this;
const #44 = Asciz	Lscala/util/Sorting$$anonfun$stableSort$3;;
const #45 = Asciz	v1;
const #46 = Asciz	Ljava/lang/Object;;
const #47 = Asciz	v2;
const #48 = Asciz	LocalVariableTable;
const #49 = Asciz	scala/Function1;
const #50 = class	#49;	//  scala/Function1
const #51 = Asciz	(Ljava/lang/Object;)Ljava/lang/Object;;
const #52 = NameAndType	#32:#51;//  apply:(Ljava/lang/Object;)Ljava/lang/Object;
const #53 = InterfaceMethod	#50.#52;	//  scala/Function1.apply:(Ljava/lang/Object;)Ljava/lang/Object;
const #54 = Asciz	scala/math/Ordered;
const #55 = class	#54;	//  scala/math/Ordered
const #56 = Asciz	$less;
const #57 = Asciz	(Ljava/lang/Object;)Z;
const #58 = NameAndType	#56:#57;//  $less:(Ljava/lang/Object;)Z
const #59 = InterfaceMethod	#55.#58;	//  scala/math/Ordered.$less:(Ljava/lang/Object;)Z
const #60 = Asciz	a;
const #61 = Asciz	b;
const #62 = Asciz	(TK;TK;)Z;
const #63 = Asciz	Signature;
const #64 = Asciz	curry;
const #65 = Asciz	()Lscala/Function1;;
const #66 = Asciz	(Lscala/Function2;)Lscala/Function1;;
const #67 = NameAndType	#64:#66;//  curry:(Lscala/Function2;)Lscala/Function1;
const #68 = Method	#27.#67;	//  scala/Function2$class.curry:(Lscala/Function2;)Lscala/Function1;
const #69 = Asciz	toString;
const #70 = Asciz	()Ljava/lang/String;;
const #71 = Asciz	(Lscala/Function2;)Ljava/lang/String;;
const #72 = NameAndType	#69:#71;//  toString:(Lscala/Function2;)Ljava/lang/String;
const #73 = Method	#27.#72;	//  scala/Function2$class.toString:(Lscala/Function2;)Ljava/lang/String;
const #74 = Asciz	Scala;
const #75 = Asciz	InnerClasses;
const #76 = Asciz	scala/util/Sorting;
const #77 = class	#76;	//  scala/util/Sorting
const #78 = Asciz	$anonfun$stableSort$3;
const #79 = Asciz	scala/Function2;
const #80 = class	#79;	//  scala/Function2
const #81 = Asciz	scala/ScalaObject;
const #82 = class	#81;	//  scala/ScalaObject
const #83 = Asciz	java/io/Serializable;
const #84 = class	#83;	//  java/io/Serializable

{
public static final long serialVersionUID;

public static {};
  Code:
   Stack=2, Locals=0, Args_size=0
   0:	lconst_0
   1:	putstatic	#11; //Field serialVersionUID:J
   4:	return

public scala.util.Sorting$$anonfun$stableSort$3(scala.Function1, scala.Function1);
  Code:
   Stack=2, Locals=3, Args_size=3
   0:	aload_0
   1:	aload_1
   2:	putfield	#19; //Field f$1:Lscala/Function1;
   5:	aload_0
   6:	aload_2
   7:	putfield	#21; //Field evidence$10$1:Lscala/Function1;
   10:	aload_0
   11:	invokespecial	#25; //Method java/lang/Object."<init>":()V
   14:	aload_0
   15:	invokestatic	#31; //Method scala/Function2$class.$init$:(Lscala/Function2;)V
   18:	return
  LineNumberTable: 
   line 91: 0


public final java.lang.Object apply(java.lang.Object, java.lang.Object);
  Code:
   Stack=3, Locals=4, Args_size=3
   0:	aload_0
   1:	aload_1
   2:	aload_2
   3:	invokevirtual	#36; //Method apply:(Ljava/lang/Object;Ljava/lang/Object;)Z
   6:	istore_3
   7:	iload_3
   8:	invokestatic	#42; //Method scala/runtime/BoxesRunTime.boxToBoolean:(Z)Ljava/lang/Boolean;
   11:	areturn
  LineNumberTable: 
   line 91: 0

  LocalVariableTable: 
   Start  Length  Slot  Name   Signature
   0      12      0    this       Lscala/util/Sorting$$anonfun$stableSort$3;
   0      12      1    v1       Ljava/lang/Object;
   0      12      2    v2       Ljava/lang/Object;


public final boolean apply(java.lang.Object, java.lang.Object);
  Code:
   Stack=3, Locals=3, Args_size=3
   0:	aload_0
   1:	getfield	#21; //Field evidence$10$1:Lscala/Function1;
   4:	aload_0
   5:	getfield	#19; //Field f$1:Lscala/Function1;
   8:	aload_1
   9:	invokeinterface	#53,  2; //InterfaceMethod scala/Function1.apply:(Ljava/lang/Object;)Ljava/lang/Object;
   14:	invokeinterface	#53,  2; //InterfaceMethod scala/Function1.apply:(Ljava/lang/Object;)Ljava/lang/Object;
   19:	checkcast	#55; //class scala/math/Ordered
   22:	aload_0
   23:	getfield	#19; //Field f$1:Lscala/Function1;
   26:	aload_2
   27:	invokeinterface	#53,  2; //InterfaceMethod scala/Function1.apply:(Ljava/lang/Object;)Ljava/lang/Object;
   32:	invokeinterface	#59,  2; //InterfaceMethod scala/math/Ordered.$less:(Ljava/lang/Object;)Z
   37:	ireturn
  LineNumberTable: 
   line 91: 0

  LocalVariableTable: 
   Start  Length  Slot  Name   Signature
   0      38      0    this       Lscala/util/Sorting$$anonfun$stableSort$3;
   0      38      1    a       Ljava/lang/Object;
   0      38      2    b       Ljava/lang/Object;

  Signature: length = 0x2
   00 3E 

public scala.Function1 curry();
  Code:
   Stack=1, Locals=1, Args_size=1
   0:	aload_0
   1:	invokestatic	#68; //Method scala/Function2$class.curry:(Lscala/Function2;)Lscala/Function1;
   4:	areturn
  LineNumberTable: 
   line 91: 0


public java.lang.String toString();
  Code:
   Stack=1, Locals=1, Args_size=1
   0:	aload_0
   1:	invokestatic	#73; //Method scala/Function2$class.toString:(Lscala/Function2;)Ljava/lang/String;
   4:	areturn
  LineNumberTable: 
   line 91: 0


}

