Compiled from "ClassLoader.scala"
public class scala.util.URLClassLoader extends java.net.URLClassLoader implements scala.util.ScalaClassLoader,scala.ScalaObject
  SourceFile: "ClassLoader.scala"
  ScalaSig: length = 0x169
   05 00 3E 06 08 01 02 FFFFFF84 FFFFFF80 FFFFFF80 FFFFFF80 00 07 02 0E 55
   52 4C 43 6C 61 73 73 4C 6F 61 64 65 72 0A 02 03
   04 01 04 75 74 69 6C 0A 01 05 01 05 73 63 61 6C
   61 03 00 13 04 00 08 0F 13 10 02 09 0E 0D 01 0A
   0A 02 0B 0C 01 03 6E 65 74 0A 01 0D 01 04 6A 61
   76 61 09 02 01 0A 10 02 10 11 0D 01 02 09 02 12
   02 02 10 53 63 61 6C 61 43 6C 61 73 73 4C 6F 61
   64 65 72 10 02 14 15 0D 01 04 09 02 16 04 02 0B
   53 63 61 6C 61 4F 62 6A 65 63 74 08 08 18 00 FFFFFF82
   FFFFFF80 FFFFFFA0 FFFFFF80 04 19 01 04 75 72 6C 73 10 03 1A 22 25
   0E 02 1B 20 0E 02 1C 1F 0D 01 1D 0A 02 1E 06 01
   06 3C 72 6F 6F 74 3E 09 01 05 09 02 21 04 01 07
   70 61 63 6B 61 67 65 09 02 23 24 02 04 4C 69 73
   74 0A 02 21 04 10 02 09 26 09 02 27 0A 02 03 55
   52 4C 08 08 29 00 FFFFFF82 FFFFFF80 FFFFFFA0 FFFFFF80 04 2A 01 06 70 61
   72 65 6E 74 10 02 2B 2E 0D 01 2C 0A 02 2D 0C 01
   04 6C 61 6E 67 09 02 2F 2C 02 0B 43 6C 61 73 73
   4C 6F 61 64 65 72 08 05 31 00 FFFFFF84 00 32 01 06 3C
   69 6E 69 74 3E 14 03 33 34 35 10 02 10 00 08 05
   18 30 FFFFFFC0 00 19 08 05 29 30 FFFFFFC0 00 2A 08 05 37 00
   FFFFFF84 20 38 01 06 61 64 64 55 52 4C 14 02 39 3C 10
   02 14 3A 09 02 3B 04 02 04 55 6E 69 74 08 05 3D
   36 FFFFFFC0 00 25 01 03 75 72 6C 
  minor version: 0
  major version: 49
  Constant pool:
const #1 = Asciz	SourceFile;
const #2 = Asciz	ClassLoader.scala;
const #3 = Asciz	<init>;
const #4 = Asciz	(Lscala/collection/immutable/List;Ljava/lang/ClassLoader;)V;
const #5 = Asciz	Code;
const #6 = Asciz	LineNumberTable;
const #7 = Asciz	scala/runtime/ScalaRunTime$;
const #8 = class	#7;	//  scala/runtime/ScalaRunTime$
const #9 = Asciz	MODULE$;
const #10 = Asciz	Lscala/runtime/ScalaRunTime$;;
const #11 = NameAndType	#9:#10;//  MODULE$:Lscala/runtime/ScalaRunTime$;
const #12 = Field	#8.#11;	//  scala/runtime/ScalaRunTime$.MODULE$:Lscala/runtime/ScalaRunTime$;
const #13 = Asciz	scala/collection/generic/TraversableTemplate;
const #14 = class	#13;	//  scala/collection/generic/TraversableTemplate
const #15 = Asciz	toArray;
const #16 = Asciz	()Lscala/runtime/BoxedArray;;
const #17 = NameAndType	#15:#16;//  toArray:()Lscala/runtime/BoxedArray;
const #18 = InterfaceMethod	#14.#17;	//  scala/collection/generic/TraversableTemplate.toArray:()Lscala/runtime/BoxedArray;
const #19 = Asciz	java/net/URL;
const #20 = class	#19;	//  java/net/URL
const #21 = Asciz	arrayValue;
const #22 = Asciz	(Lscala/runtime/BoxedArray;Ljava/lang/Class;)Ljava/lang/Object;;
const #23 = NameAndType	#21:#22;//  arrayValue:(Lscala/runtime/BoxedArray;Ljava/lang/Class;)Ljava/lang/Object;
const #24 = Method	#8.#23;	//  scala/runtime/ScalaRunTime$.arrayValue:(Lscala/runtime/BoxedArray;Ljava/lang/Class;)Ljava/lang/Object;
const #25 = Asciz	scala/runtime/BoxedArray;
const #26 = class	#25;	//  scala/runtime/BoxedArray
const #27 = Asciz	[Ljava/net/URL;;
const #28 = class	#27;	//  "[Ljava/net/URL;"
const #29 = Asciz	java/net/URLClassLoader;
const #30 = class	#29;	//  java/net/URLClassLoader
const #31 = Asciz	([Ljava/net/URL;Ljava/lang/ClassLoader;)V;
const #32 = NameAndType	#3:#31;//  "<init>":([Ljava/net/URL;Ljava/lang/ClassLoader;)V
const #33 = Method	#30.#32;	//  java/net/URLClassLoader."<init>":([Ljava/net/URL;Ljava/lang/ClassLoader;)V
const #34 = Asciz	scala/util/ScalaClassLoader$class;
const #35 = class	#34;	//  scala/util/ScalaClassLoader$class
const #36 = Asciz	$init$;
const #37 = Asciz	(Lscala/util/ScalaClassLoader;)V;
const #38 = NameAndType	#36:#37;//  $init$:(Lscala/util/ScalaClassLoader;)V
const #39 = Method	#35.#38;	//  scala/util/ScalaClassLoader$class.$init$:(Lscala/util/ScalaClassLoader;)V
const #40 = Asciz	this;
const #41 = Asciz	Lscala/util/URLClassLoader;;
const #42 = Asciz	urls;
const #43 = Asciz	Lscala/collection/immutable/List;;
const #44 = Asciz	parent;
const #45 = Asciz	Ljava/lang/ClassLoader;;
const #46 = Asciz	LocalVariableTable;
const #47 = Asciz	(Lscala/collection/immutable/List<Ljava/net/URL;>;Ljava/lang/ClassLoader;)V;
const #48 = Asciz	Signature;
const #49 = Asciz	addURL;
const #50 = Asciz	(Ljava/net/URL;)V;
const #51 = NameAndType	#49:#50;//  addURL:(Ljava/net/URL;)V
const #52 = Method	#30.#51;	//  java/net/URLClassLoader.addURL:(Ljava/net/URL;)V
const #53 = Asciz	url;
const #54 = Asciz	Ljava/net/URL;;
const #55 = Asciz	run;
const #56 = Asciz	(Ljava/lang/String;Lscala/collection/Sequence;)V;
const #57 = Asciz	(Lscala/util/ScalaClassLoader;Ljava/lang/String;Lscala/collection/Sequence;)V;
const #58 = NameAndType	#55:#57;//  run:(Lscala/util/ScalaClassLoader;Ljava/lang/String;Lscala/collection/Sequence;)V
const #59 = Method	#35.#58;	//  scala/util/ScalaClassLoader$class.run:(Lscala/util/ScalaClassLoader;Ljava/lang/String;Lscala/collection/Sequence;)V
const #60 = Asciz	objectName;
const #61 = Asciz	Ljava/lang/String;;
const #62 = Asciz	arguments;
const #63 = Asciz	Lscala/collection/Sequence;;
const #64 = Asciz	create;
const #65 = Asciz	(Ljava/lang/String;)Ljava/lang/Object;;
const #66 = Asciz	(Lscala/util/ScalaClassLoader;Ljava/lang/String;)Ljava/lang/Object;;
const #67 = NameAndType	#64:#66;//  create:(Lscala/util/ScalaClassLoader;Ljava/lang/String;)Ljava/lang/Object;
const #68 = Method	#35.#67;	//  scala/util/ScalaClassLoader$class.create:(Lscala/util/ScalaClassLoader;Ljava/lang/String;)Ljava/lang/Object;
const #69 = Asciz	path;
const #70 = Asciz	tryToInitializeClass;
const #71 = Asciz	(Ljava/lang/String;)Lscala/Option;;
const #72 = Asciz	(Lscala/util/ScalaClassLoader;Ljava/lang/String;)Lscala/Option;;
const #73 = NameAndType	#70:#72;//  tryToInitializeClass:(Lscala/util/ScalaClassLoader;Ljava/lang/String;)Lscala/Option;
const #74 = Method	#35.#73;	//  scala/util/ScalaClassLoader$class.tryToInitializeClass:(Lscala/util/ScalaClassLoader;Ljava/lang/String;)Lscala/Option;
const #75 = Asciz	tryToLoadClass;
const #76 = NameAndType	#75:#72;//  tryToLoadClass:(Lscala/util/ScalaClassLoader;Ljava/lang/String;)Lscala/Option;
const #77 = Method	#35.#76;	//  scala/util/ScalaClassLoader$class.tryToLoadClass:(Lscala/util/ScalaClassLoader;Ljava/lang/String;)Lscala/Option;
const #78 = Asciz	setAsContext;
const #79 = Asciz	()V;
const #80 = NameAndType	#78:#37;//  setAsContext:(Lscala/util/ScalaClassLoader;)V
const #81 = Method	#35.#80;	//  scala/util/ScalaClassLoader$class.setAsContext:(Lscala/util/ScalaClassLoader;)V
const #82 = Asciz	asContext;
const #83 = Asciz	(Lscala/Function0;)Ljava/lang/Object;;
const #84 = Asciz	(Lscala/util/ScalaClassLoader;Lscala/Function0;)Ljava/lang/Object;;
const #85 = NameAndType	#82:#84;//  asContext:(Lscala/util/ScalaClassLoader;Lscala/Function0;)Ljava/lang/Object;
const #86 = Method	#35.#85;	//  scala/util/ScalaClassLoader$class.asContext:(Lscala/util/ScalaClassLoader;Lscala/Function0;)Ljava/lang/Object;
const #87 = Asciz	action;
const #88 = Asciz	Lscala/Function0;;
const #89 = Asciz	ScalaSig;
const #90 = Asciz	scala/util/URLClassLoader;
const #91 = class	#90;	//  scala/util/URLClassLoader
const #92 = Asciz	scala/util/ScalaClassLoader;
const #93 = class	#92;	//  scala/util/ScalaClassLoader
const #94 = Asciz	scala/ScalaObject;
const #95 = class	#94;	//  scala/ScalaObject

{
public scala.util.URLClassLoader(scala.collection.immutable.List, java.lang.ClassLoader);
  Code:
   Stack=4, Locals=4, Args_size=3
   0:	aload_0
   1:	getstatic	#12; //Field scala/runtime/ScalaRunTime$.MODULE$:Lscala/runtime/ScalaRunTime$;
   4:	aload_1
   5:	invokeinterface	#18,  1; //InterfaceMethod scala/collection/generic/TraversableTemplate.toArray:()Lscala/runtime/BoxedArray;
   10:	ldc	#20; //class java/net/URL
   12:	invokevirtual	#24; //Method scala/runtime/ScalaRunTime$.arrayValue:(Lscala/runtime/BoxedArray;Ljava/lang/Class;)Ljava/lang/Object;
   15:	astore_3
   16:	aload_3
   17:	instanceof	#26; //class scala/runtime/BoxedArray
   20:	ifeq	38
   23:	getstatic	#12; //Field scala/runtime/ScalaRunTime$.MODULE$:Lscala/runtime/ScalaRunTime$;
   26:	aload_3
   27:	checkcast	#26; //class scala/runtime/BoxedArray
   30:	ldc	#20; //class java/net/URL
   32:	invokevirtual	#24; //Method scala/runtime/ScalaRunTime$.arrayValue:(Lscala/runtime/BoxedArray;Ljava/lang/Class;)Ljava/lang/Object;
   35:	goto	39
   38:	aload_3
   39:	checkcast	#28; //class "[Ljava/net/URL;"
   42:	aload_2
   43:	invokespecial	#33; //Method java/net/URLClassLoader."<init>":([Ljava/net/URL;Ljava/lang/ClassLoader;)V
   46:	aload_0
   47:	invokestatic	#39; //Method scala/util/ScalaClassLoader$class.$init$:(Lscala/util/ScalaClassLoader;)V
   50:	return
  LineNumberTable: 
   line 58: 0
   line 59: 1
   line 58: 43

  LocalVariableTable: 
   Start  Length  Slot  Name   Signature
   0      51      0    this       Lscala/util/URLClassLoader;
   0      51      1    urls       Lscala/collection/immutable/List;
   0      51      2    parent       Ljava/lang/ClassLoader;

  Signature: length = 0x2
   00 2F 

public void addURL(java.net.URL);
  Code:
   Stack=2, Locals=2, Args_size=2
   0:	aload_0
   1:	aload_1
   2:	invokespecial	#52; //Method java/net/URLClassLoader.addURL:(Ljava/net/URL;)V
   5:	return
  LineNumberTable: 
   line 63: 0

  LocalVariableTable: 
   Start  Length  Slot  Name   Signature
   0      6      0    this       Lscala/util/URLClassLoader;
   0      6      1    url       Ljava/net/URL;


public void run(java.lang.String, scala.collection.Sequence);
  Code:
   Stack=3, Locals=3, Args_size=3
   0:	aload_0
   1:	aload_1
   2:	aload_2
   3:	invokestatic	#59; //Method scala/util/ScalaClassLoader$class.run:(Lscala/util/ScalaClassLoader;Ljava/lang/String;Lscala/collection/Sequence;)V
   6:	return
  LineNumberTable: 
   line 58: 0

  LocalVariableTable: 
   Start  Length  Slot  Name   Signature
   0      7      0    this       Lscala/util/URLClassLoader;
   0      7      1    objectName       Ljava/lang/String;
   0      7      2    arguments       Lscala/collection/Sequence;


public java.lang.Object create(java.lang.String);
  Code:
   Stack=2, Locals=2, Args_size=2
   0:	aload_0
   1:	aload_1
   2:	invokestatic	#68; //Method scala/util/ScalaClassLoader$class.create:(Lscala/util/ScalaClassLoader;Ljava/lang/String;)Ljava/lang/Object;
   5:	areturn
  LineNumberTable: 
   line 58: 0

  LocalVariableTable: 
   Start  Length  Slot  Name   Signature
   0      6      0    this       Lscala/util/URLClassLoader;
   0      6      1    path       Ljava/lang/String;


public scala.Option tryToInitializeClass(java.lang.String);
  Code:
   Stack=2, Locals=2, Args_size=2
   0:	aload_0
   1:	aload_1
   2:	invokestatic	#74; //Method scala/util/ScalaClassLoader$class.tryToInitializeClass:(Lscala/util/ScalaClassLoader;Ljava/lang/String;)Lscala/Option;
   5:	areturn
  LineNumberTable: 
   line 58: 0

  LocalVariableTable: 
   Start  Length  Slot  Name   Signature
   0      6      0    this       Lscala/util/URLClassLoader;
   0      6      1    path       Ljava/lang/String;


public scala.Option tryToLoadClass(java.lang.String);
  Code:
   Stack=2, Locals=2, Args_size=2
   0:	aload_0
   1:	aload_1
   2:	invokestatic	#77; //Method scala/util/ScalaClassLoader$class.tryToLoadClass:(Lscala/util/ScalaClassLoader;Ljava/lang/String;)Lscala/Option;
   5:	areturn
  LineNumberTable: 
   line 58: 0

  LocalVariableTable: 
   Start  Length  Slot  Name   Signature
   0      6      0    this       Lscala/util/URLClassLoader;
   0      6      1    path       Ljava/lang/String;


public void setAsContext();
  Code:
   Stack=1, Locals=1, Args_size=1
   0:	aload_0
   1:	invokestatic	#81; //Method scala/util/ScalaClassLoader$class.setAsContext:(Lscala/util/ScalaClassLoader;)V
   4:	return
  LineNumberTable: 
   line 58: 0


public java.lang.Object asContext(scala.Function0);
  Code:
   Stack=2, Locals=2, Args_size=2
   0:	aload_0
   1:	aload_1
   2:	invokestatic	#86; //Method scala/util/ScalaClassLoader$class.asContext:(Lscala/util/ScalaClassLoader;Lscala/Function0;)Ljava/lang/Object;
   5:	areturn
  LineNumberTable: 
   line 58: 0

  LocalVariableTable: 
   Start  Length  Slot  Name   Signature
   0      6      0    this       Lscala/util/URLClassLoader;
   0      6      1    action       Lscala/Function0;


}

