public class scala.actors.threadpool.helpers.FIFOWaitQueue extends scala.actors.threadpool.helpers.WaitQueue implements java.io.Serializable
  InnerClass: 
   public #22= #21 of #13; //WaitNode=class scala/actors/threadpool/helpers/WaitQueue$WaitNode of class scala/actors/threadpool/helpers/WaitQueue
  minor version: 0
  major version: 49
  Constant pool:
const #1 = Method	#13.#42;	//  scala/actors/threadpool/helpers/WaitQueue."<init>":()V
const #2 = Field	#12.#43;	//  scala/actors/threadpool/helpers/FIFOWaitQueue.head_:Lscala/actors/threadpool/helpers/WaitQueue$WaitNode;
const #3 = Field	#12.#44;	//  scala/actors/threadpool/helpers/FIFOWaitQueue.tail_:Lscala/actors/threadpool/helpers/WaitQueue$WaitNode;
const #4 = Field	#21.#45;	//  scala/actors/threadpool/helpers/WaitQueue$WaitNode.next:Lscala/actors/threadpool/helpers/WaitQueue$WaitNode;
const #5 = Field	#21.#46;	//  scala/actors/threadpool/helpers/WaitQueue$WaitNode.waiting:Z
const #6 = class	#47;	//  java/util/ArrayList
const #7 = Method	#6.#42;	//  java/util/ArrayList."<init>":()V
const #8 = Field	#21.#48;	//  scala/actors/threadpool/helpers/WaitQueue$WaitNode.owner:Ljava/lang/Thread;
const #9 = InterfaceMethod	#49.#50;	//  java/util/List.add:(Ljava/lang/Object;)Z
const #10 = class	#51;	//  java/lang/NullPointerException
const #11 = Method	#10.#42;	//  java/lang/NullPointerException."<init>":()V
const #12 = class	#52;	//  scala/actors/threadpool/helpers/FIFOWaitQueue
const #13 = class	#53;	//  scala/actors/threadpool/helpers/WaitQueue
const #14 = class	#54;	//  java/io/Serializable
const #15 = Asciz	serialVersionUID;
const #16 = Asciz	J;
const #17 = Asciz	ConstantValue;
const #18 = long	2416444691925378811l;
const #20 = Asciz	head_;
const #21 = class	#55;	//  scala/actors/threadpool/helpers/WaitQueue$WaitNode
const #22 = Asciz	WaitNode;
const #23 = Asciz	InnerClasses;
const #24 = Asciz	Lscala/actors/threadpool/helpers/WaitQueue$WaitNode;;
const #25 = Asciz	tail_;
const #26 = Asciz	<init>;
const #27 = Asciz	()V;
const #28 = Asciz	Code;
const #29 = Asciz	insert;
const #30 = Asciz	(Lscala/actors/threadpool/helpers/WaitQueue$WaitNode;)V;
const #31 = Asciz	extract;
const #32 = Asciz	()Lscala/actors/threadpool/helpers/WaitQueue$WaitNode;;
const #33 = Asciz	putBack;
const #34 = Asciz	hasNodes;
const #35 = Asciz	()Z;
const #36 = Asciz	getLength;
const #37 = Asciz	()I;
const #38 = Asciz	getWaitingThreads;
const #39 = Asciz	()Ljava/util/Collection;;
const #40 = Asciz	isWaiting;
const #41 = Asciz	(Ljava/lang/Thread;)Z;
const #42 = NameAndType	#26:#27;//  "<init>":()V
const #43 = NameAndType	#20:#24;//  head_:Lscala/actors/threadpool/helpers/WaitQueue$WaitNode;
const #44 = NameAndType	#25:#24;//  tail_:Lscala/actors/threadpool/helpers/WaitQueue$WaitNode;
const #45 = NameAndType	#56:#24;//  next:Lscala/actors/threadpool/helpers/WaitQueue$WaitNode;
const #46 = NameAndType	#57:#58;//  waiting:Z
const #47 = Asciz	java/util/ArrayList;
const #48 = NameAndType	#59:#60;//  owner:Ljava/lang/Thread;
const #49 = class	#61;	//  java/util/List
const #50 = NameAndType	#62:#63;//  add:(Ljava/lang/Object;)Z
const #51 = Asciz	java/lang/NullPointerException;
const #52 = Asciz	scala/actors/threadpool/helpers/FIFOWaitQueue;
const #53 = Asciz	scala/actors/threadpool/helpers/WaitQueue;
const #54 = Asciz	java/io/Serializable;
const #55 = Asciz	scala/actors/threadpool/helpers/WaitQueue$WaitNode;
const #56 = Asciz	next;
const #57 = Asciz	waiting;
const #58 = Asciz	Z;
const #59 = Asciz	owner;
const #60 = Asciz	Ljava/lang/Thread;;
const #61 = Asciz	java/util/List;
const #62 = Asciz	add;
const #63 = Asciz	(Ljava/lang/Object;)Z;

{
protected transient scala.actors.threadpool.helpers.WaitQueue$WaitNode head_;

protected transient scala.actors.threadpool.helpers.WaitQueue$WaitNode tail_;

public scala.actors.threadpool.helpers.FIFOWaitQueue();
  Code:
   Stack=2, Locals=1, Args_size=1
   0:	aload_0
   1:	invokespecial	#1; //Method scala/actors/threadpool/helpers/WaitQueue."<init>":()V
   4:	aload_0
   5:	aconst_null
   6:	putfield	#2; //Field head_:Lscala/actors/threadpool/helpers/WaitQueue$WaitNode;
   9:	aload_0
   10:	aconst_null
   11:	putfield	#3; //Field tail_:Lscala/actors/threadpool/helpers/WaitQueue$WaitNode;
   14:	return

public void insert(scala.actors.threadpool.helpers.WaitQueue$WaitNode);
  Code:
   Stack=4, Locals=2, Args_size=2
   0:	aload_0
   1:	getfield	#3; //Field tail_:Lscala/actors/threadpool/helpers/WaitQueue$WaitNode;
   4:	ifnonnull	20
   7:	aload_0
   8:	aload_0
   9:	aload_1
   10:	dup_x1
   11:	putfield	#3; //Field tail_:Lscala/actors/threadpool/helpers/WaitQueue$WaitNode;
   14:	putfield	#2; //Field head_:Lscala/actors/threadpool/helpers/WaitQueue$WaitNode;
   17:	goto	33
   20:	aload_0
   21:	getfield	#3; //Field tail_:Lscala/actors/threadpool/helpers/WaitQueue$WaitNode;
   24:	aload_1
   25:	putfield	#4; //Field scala/actors/threadpool/helpers/WaitQueue$WaitNode.next:Lscala/actors/threadpool/helpers/WaitQueue$WaitNode;
   28:	aload_0
   29:	aload_1
   30:	putfield	#3; //Field tail_:Lscala/actors/threadpool/helpers/WaitQueue$WaitNode;
   33:	return

public scala.actors.threadpool.helpers.WaitQueue$WaitNode extract();
  Code:
   Stack=2, Locals=2, Args_size=1
   0:	aload_0
   1:	getfield	#2; //Field head_:Lscala/actors/threadpool/helpers/WaitQueue$WaitNode;
   4:	ifnonnull	9
   7:	aconst_null
   8:	areturn
   9:	aload_0
   10:	getfield	#2; //Field head_:Lscala/actors/threadpool/helpers/WaitQueue$WaitNode;
   13:	astore_1
   14:	aload_0
   15:	aload_1
   16:	getfield	#4; //Field scala/actors/threadpool/helpers/WaitQueue$WaitNode.next:Lscala/actors/threadpool/helpers/WaitQueue$WaitNode;
   19:	putfield	#2; //Field head_:Lscala/actors/threadpool/helpers/WaitQueue$WaitNode;
   22:	aload_0
   23:	getfield	#2; //Field head_:Lscala/actors/threadpool/helpers/WaitQueue$WaitNode;
   26:	ifnonnull	34
   29:	aload_0
   30:	aconst_null
   31:	putfield	#3; //Field tail_:Lscala/actors/threadpool/helpers/WaitQueue$WaitNode;
   34:	aload_1
   35:	aconst_null
   36:	putfield	#4; //Field scala/actors/threadpool/helpers/WaitQueue$WaitNode.next:Lscala/actors/threadpool/helpers/WaitQueue$WaitNode;
   39:	aload_1
   40:	areturn

public void putBack(scala.actors.threadpool.helpers.WaitQueue$WaitNode);
  Code:
   Stack=2, Locals=2, Args_size=2
   0:	aload_1
   1:	aload_0
   2:	getfield	#2; //Field head_:Lscala/actors/threadpool/helpers/WaitQueue$WaitNode;
   5:	putfield	#4; //Field scala/actors/threadpool/helpers/WaitQueue$WaitNode.next:Lscala/actors/threadpool/helpers/WaitQueue$WaitNode;
   8:	aload_0
   9:	aload_1
   10:	putfield	#2; //Field head_:Lscala/actors/threadpool/helpers/WaitQueue$WaitNode;
   13:	aload_0
   14:	getfield	#3; //Field tail_:Lscala/actors/threadpool/helpers/WaitQueue$WaitNode;
   17:	ifnonnull	25
   20:	aload_0
   21:	aload_1
   22:	putfield	#3; //Field tail_:Lscala/actors/threadpool/helpers/WaitQueue$WaitNode;
   25:	return

public boolean hasNodes();
  Code:
   Stack=1, Locals=1, Args_size=1
   0:	aload_0
   1:	getfield	#2; //Field head_:Lscala/actors/threadpool/helpers/WaitQueue$WaitNode;
   4:	ifnull	11
   7:	iconst_1
   8:	goto	12
   11:	iconst_0
   12:	ireturn

public int getLength();
  Code:
   Stack=1, Locals=3, Args_size=1
   0:	iconst_0
   1:	istore_1
   2:	aload_0
   3:	getfield	#2; //Field head_:Lscala/actors/threadpool/helpers/WaitQueue$WaitNode;
   6:	astore_2
   7:	aload_2
   8:	ifnull	29
   11:	aload_2
   12:	getfield	#5; //Field scala/actors/threadpool/helpers/WaitQueue$WaitNode.waiting:Z
   15:	ifeq	21
   18:	iinc	1, 1
   21:	aload_2
   22:	getfield	#4; //Field scala/actors/threadpool/helpers/WaitQueue$WaitNode.next:Lscala/actors/threadpool/helpers/WaitQueue$WaitNode;
   25:	astore_2
   26:	goto	7
   29:	iload_1
   30:	ireturn

public java.util.Collection getWaitingThreads();
  Code:
   Stack=2, Locals=4, Args_size=1
   0:	new	#6; //class java/util/ArrayList
   3:	dup
   4:	invokespecial	#7; //Method java/util/ArrayList."<init>":()V
   7:	astore_1
   8:	iconst_0
   9:	istore_2
   10:	aload_0
   11:	getfield	#2; //Field head_:Lscala/actors/threadpool/helpers/WaitQueue$WaitNode;
   14:	astore_3
   15:	aload_3
   16:	ifnull	45
   19:	aload_3
   20:	getfield	#5; //Field scala/actors/threadpool/helpers/WaitQueue$WaitNode.waiting:Z
   23:	ifeq	37
   26:	aload_1
   27:	aload_3
   28:	getfield	#8; //Field scala/actors/threadpool/helpers/WaitQueue$WaitNode.owner:Ljava/lang/Thread;
   31:	invokeinterface	#9,  2; //InterfaceMethod java/util/List.add:(Ljava/lang/Object;)Z
   36:	pop
   37:	aload_3
   38:	getfield	#4; //Field scala/actors/threadpool/helpers/WaitQueue$WaitNode.next:Lscala/actors/threadpool/helpers/WaitQueue$WaitNode;
   41:	astore_3
   42:	goto	15
   45:	aload_1
   46:	areturn

public boolean isWaiting(java.lang.Thread);
  Code:
   Stack=2, Locals=3, Args_size=2
   0:	aload_1
   1:	ifnonnull	12
   4:	new	#10; //class java/lang/NullPointerException
   7:	dup
   8:	invokespecial	#11; //Method java/lang/NullPointerException."<init>":()V
   11:	athrow
   12:	aload_0
   13:	getfield	#2; //Field head_:Lscala/actors/threadpool/helpers/WaitQueue$WaitNode;
   16:	astore_2
   17:	aload_2
   18:	ifnull	46
   21:	aload_2
   22:	getfield	#5; //Field scala/actors/threadpool/helpers/WaitQueue$WaitNode.waiting:Z
   25:	ifeq	38
   28:	aload_2
   29:	getfield	#8; //Field scala/actors/threadpool/helpers/WaitQueue$WaitNode.owner:Ljava/lang/Thread;
   32:	aload_1
   33:	if_acmpne	38
   36:	iconst_1
   37:	ireturn
   38:	aload_2
   39:	getfield	#4; //Field scala/actors/threadpool/helpers/WaitQueue$WaitNode.next:Lscala/actors/threadpool/helpers/WaitQueue$WaitNode;
   42:	astore_2
   43:	goto	17
   46:	iconst_0
   47:	ireturn

}

