public class scala.actors.threadpool.helpers.ThreadHelpers extends java.lang.Object
  InnerClass: 
   public abstract #9= #8 of #6; //UncaughtExceptionHandler=class scala/actors/threadpool/helpers/ThreadHelpers$UncaughtExceptionHandler of class scala/actors/threadpool/helpers/ThreadHelpers
   #4; //class scala/actors/threadpool/helpers/ThreadHelpers$1
  minor version: 0
  major version: 49
  Constant pool:
const #1 = Method	#7.#16;	//  java/lang/Object."<init>":()V
const #2 = class	#17;	//  java/lang/NullPointerException
const #3 = Method	#2.#16;	//  java/lang/NullPointerException."<init>":()V
const #4 = class	#18;	//  scala/actors/threadpool/helpers/ThreadHelpers$1
const #5 = Method	#4.#20;	//  scala/actors/threadpool/helpers/ThreadHelpers$1."<init>":(Ljava/lang/Runnable;Lscala/actors/threadpool/helpers/ThreadHelpers$UncaughtExceptionHandler;)V
const #6 = class	#21;	//  scala/actors/threadpool/helpers/ThreadHelpers
const #7 = class	#22;	//  java/lang/Object
const #8 = class	#23;	//  scala/actors/threadpool/helpers/ThreadHelpers$UncaughtExceptionHandler
const #9 = Asciz	UncaughtExceptionHandler;
const #10 = Asciz	InnerClasses;
const #11 = Asciz	<init>;
const #12 = Asciz	()V;
const #13 = Asciz	Code;
const #14 = Asciz	assignExceptionHandler;
const #15 = Asciz	(Ljava/lang/Runnable;Lscala/actors/threadpool/helpers/ThreadHelpers$UncaughtExceptionHandler;)Ljava/lang/Runnable;;
const #16 = NameAndType	#11:#12;//  "<init>":()V
const #17 = Asciz	java/lang/NullPointerException;
const #18 = Asciz	scala/actors/threadpool/helpers/ThreadHelpers$1;
const #19 = Asciz	;
const #20 = NameAndType	#11:#24;//  "<init>":(Ljava/lang/Runnable;Lscala/actors/threadpool/helpers/ThreadHelpers$UncaughtExceptionHandler;)V
const #21 = Asciz	scala/actors/threadpool/helpers/ThreadHelpers;
const #22 = Asciz	java/lang/Object;
const #23 = Asciz	scala/actors/threadpool/helpers/ThreadHelpers$UncaughtExceptionHandler;
const #24 = Asciz	(Ljava/lang/Runnable;Lscala/actors/threadpool/helpers/ThreadHelpers$UncaughtExceptionHandler;)V;

{
public static java.lang.Runnable assignExceptionHandler(java.lang.Runnable, scala.actors.threadpool.helpers.ThreadHelpers$UncaughtExceptionHandler);
  Code:
   Stack=4, Locals=2, Args_size=2
   0:	aload_0
   1:	ifnull	8
   4:	aload_1
   5:	ifnonnull	16
   8:	new	#2; //class java/lang/NullPointerException
   11:	dup
   12:	invokespecial	#3; //Method java/lang/NullPointerException."<init>":()V
   15:	athrow
   16:	new	#4; //class scala/actors/threadpool/helpers/ThreadHelpers$1
   19:	dup
   20:	aload_0
   21:	aload_1
   22:	invokespecial	#5; //Method scala/actors/threadpool/helpers/ThreadHelpers$1."<init>":(Ljava/lang/Runnable;Lscala/actors/threadpool/helpers/ThreadHelpers$UncaughtExceptionHandler;)V
   25:	areturn

}

