class scala.actors.threadpool.helpers.ThreadHelpers$1 extends java.lang.Object implements java.lang.Runnable
  EnclosingMethod: length = 0x4
   00 18 00 19 
  InnerClass: 
   public abstract #15= #14 of #24; //UncaughtExceptionHandler=class scala/actors/threadpool/helpers/ThreadHelpers$UncaughtExceptionHandler of class scala/actors/threadpool/helpers/ThreadHelpers
   #8; //class scala/actors/threadpool/helpers/ThreadHelpers$1
  minor version: 0
  major version: 49
  Constant pool:
const #1 = Field	#8.#26;	//  scala/actors/threadpool/helpers/ThreadHelpers$1.val$runnable:Ljava/lang/Runnable;
const #2 = Field	#8.#27;	//  scala/actors/threadpool/helpers/ThreadHelpers$1.val$handler:Lscala/actors/threadpool/helpers/ThreadHelpers$UncaughtExceptionHandler;
const #3 = Method	#9.#28;	//  java/lang/Object."<init>":()V
const #4 = InterfaceMethod	#10.#29;	//  java/lang/Runnable.run:()V
const #5 = class	#30;	//  java/lang/Throwable
const #6 = Method	#31.#32;	//  java/lang/Thread.currentThread:()Ljava/lang/Thread;
const #7 = InterfaceMethod	#14.#33;	//  scala/actors/threadpool/helpers/ThreadHelpers$UncaughtExceptionHandler.uncaughtException:(Ljava/lang/Thread;Ljava/lang/Throwable;)V
const #8 = class	#34;	//  scala/actors/threadpool/helpers/ThreadHelpers$1
const #9 = class	#36;	//  java/lang/Object
const #10 = class	#37;	//  java/lang/Runnable
const #11 = Asciz	val$runnable;
const #12 = Asciz	Ljava/lang/Runnable;;
const #13 = Asciz	val$handler;
const #14 = class	#38;	//  scala/actors/threadpool/helpers/ThreadHelpers$UncaughtExceptionHandler
const #15 = Asciz	UncaughtExceptionHandler;
const #16 = Asciz	InnerClasses;
const #17 = Asciz	Lscala/actors/threadpool/helpers/ThreadHelpers$UncaughtExceptionHandler;;
const #18 = Asciz	<init>;
const #19 = Asciz	(Ljava/lang/Runnable;Lscala/actors/threadpool/helpers/ThreadHelpers$UncaughtExceptionHandler;)V;
const #20 = Asciz	Code;
const #21 = Asciz	run;
const #22 = Asciz	()V;
const #23 = Asciz	EnclosingMethod;
const #24 = class	#39;	//  scala/actors/threadpool/helpers/ThreadHelpers
const #25 = NameAndType	#40:#41;//  assignExceptionHandler:(Ljava/lang/Runnable;Lscala/actors/threadpool/helpers/ThreadHelpers$UncaughtExceptionHandler;)Ljava/lang/Runnable;
const #26 = NameAndType	#11:#12;//  val$runnable:Ljava/lang/Runnable;
const #27 = NameAndType	#13:#17;//  val$handler:Lscala/actors/threadpool/helpers/ThreadHelpers$UncaughtExceptionHandler;
const #28 = NameAndType	#18:#22;//  "<init>":()V
const #29 = NameAndType	#21:#22;//  run:()V
const #30 = Asciz	java/lang/Throwable;
const #31 = class	#42;	//  java/lang/Thread
const #32 = NameAndType	#43:#44;//  currentThread:()Ljava/lang/Thread;
const #33 = NameAndType	#45:#46;//  uncaughtException:(Ljava/lang/Thread;Ljava/lang/Throwable;)V
const #34 = Asciz	scala/actors/threadpool/helpers/ThreadHelpers$1;
const #35 = Asciz	;
const #36 = Asciz	java/lang/Object;
const #37 = Asciz	java/lang/Runnable;
const #38 = Asciz	scala/actors/threadpool/helpers/ThreadHelpers$UncaughtExceptionHandler;
const #39 = Asciz	scala/actors/threadpool/helpers/ThreadHelpers;
const #40 = Asciz	assignExceptionHandler;
const #41 = Asciz	(Ljava/lang/Runnable;Lscala/actors/threadpool/helpers/ThreadHelpers$UncaughtExceptionHandler;)Ljava/lang/Runnable;;
const #42 = Asciz	java/lang/Thread;
const #43 = Asciz	currentThread;
const #44 = Asciz	()Ljava/lang/Thread;;
const #45 = Asciz	uncaughtException;
const #46 = Asciz	(Ljava/lang/Thread;Ljava/lang/Throwable;)V;

{
final java.lang.Runnable val$runnable;

final scala.actors.threadpool.helpers.ThreadHelpers$UncaughtExceptionHandler val$handler;

scala.actors.threadpool.helpers.ThreadHelpers$1(java.lang.Runnable, scala.actors.threadpool.helpers.ThreadHelpers$UncaughtExceptionHandler);
  Code:
   Stack=2, Locals=3, Args_size=3
   0:	aload_0
   1:	aload_1
   2:	putfield	#1; //Field val$runnable:Ljava/lang/Runnable;
   5:	aload_0
   6:	aload_2
   7:	putfield	#2; //Field val$handler:Lscala/actors/threadpool/helpers/ThreadHelpers$UncaughtExceptionHandler;
   10:	aload_0
   11:	invokespecial	#3; //Method java/lang/Object."<init>":()V
   14:	return

public void run();
  Code:
   Stack=3, Locals=3, Args_size=1
   0:	aload_0
   1:	getfield	#1; //Field val$runnable:Ljava/lang/Runnable;
   4:	invokeinterface	#4,  1; //InterfaceMethod java/lang/Runnable.run:()V
   9:	goto	30
   12:	astore_1
   13:	aload_0
   14:	getfield	#2; //Field val$handler:Lscala/actors/threadpool/helpers/ThreadHelpers$UncaughtExceptionHandler;
   17:	invokestatic	#6; //Method java/lang/Thread.currentThread:()Ljava/lang/Thread;
   20:	aload_1
   21:	invokeinterface	#7,  3; //InterfaceMethod scala/actors/threadpool/helpers/ThreadHelpers$UncaughtExceptionHandler.uncaughtException:(Ljava/lang/Thread;Ljava/lang/Throwable;)V
   26:	goto	30
   29:	astore_2
   30:	return
  Exception table:
   from   to  target type
     0     9    12   Class java/lang/Throwable

    13    26    29   Class java/lang/Throwable


}

