public final class scala.actors.threadpool.helpers.Utils extends java.lang.Object
  InnerClass: 
   final MillisProvider=class scala/actors/threadpool/helpers/Utils$MillisProvider of class scala/actors/threadpool/helpers/Utils
   final SunPerfProvider=class scala/actors/threadpool/helpers/Utils$SunPerfProvider of class scala/actors/threadpool/helpers/Utils
   class scala/actors/threadpool/helpers/Utils$1
  minor version: 0
  major version: 49
  Constant pool:
Method	scala/actors/threadpool/helpers/Utils.gcd:(JJ)J
Method	java/lang/Object."<init>":()V
Field	scala/actors/threadpool/helpers/Utils.nanoTimer:Lscala/actors/threadpool/helpers/NanoTimer;
InterfaceMethod	scala/actors/threadpool/helpers/NanoTimer.nanoTime:()J
Method	scala/actors/threadpool/helpers/Utils.nanoTime:()J
Field	scala/actors/threadpool/TimeUnit.NANOSECONDS:Lscala/actors/threadpool/TimeUnit;
InterfaceMethod	scala/actors/threadpool/locks/Condition.await:(JLscala/actors/threadpool/TimeUnit;)Z
InterfaceMethod	java/util/Collection.size:()I
class	java/lang/Object
InterfaceMethod	java/util/Collection.iterator:()Ljava/util/Iterator;
InterfaceMethod	java/util/Iterator.hasNext:()Z
InterfaceMethod	java/util/Iterator.next:()Ljava/lang/Object;
class	"[Ljava/lang/Object;"
Method	scala/actors/threadpool/Arrays.copyOf:([Ljava/lang/Object;ILjava/lang/Class;)[Ljava/lang/Object;
int	2147483647;
class	java/lang/OutOfMemoryError
String	required array size too large
Method	java/lang/OutOfMemoryError."<init>":(Ljava/lang/String;)V
Method	java/lang/Object.getClass:()Ljava/lang/Class;
Method	java/lang/Class.getComponentType:()Ljava/lang/Class;
Method	java/lang/reflect/Array.newInstance:(Ljava/lang/Class;I)Ljava/lang/Object;
class	scala/actors/threadpool/helpers/Utils$1
Method	scala/actors/threadpool/helpers/Utils$1."<init>":()V
Method	java/security/AccessController.doPrivileged:(Ljava/security/PrivilegedAction;)Ljava/lang/Object;
class	java/lang/String
Method	java/lang/Class.forName:(Ljava/lang/String;)Ljava/lang/Class;
Method	java/lang/Class.newInstance:()Ljava/lang/Object;
class	scala/actors/threadpool/helpers/NanoTimer
class	java/lang/Exception
Field	java/lang/System.err:Ljava/io/PrintStream;
String	WARNING: unable to load the system-property-defined nanotime provider; switching to the default
Method	java/io/PrintStream.println:(Ljava/lang/String;)V
Method	java/lang/Exception.printStackTrace:()V
class	scala/actors/threadpool/helpers/Utils$SunPerfProvider
Method	scala/actors/threadpool/helpers/Utils$SunPerfProvider."<init>":()V
class	java/lang/Throwable
class	scala/actors/threadpool/helpers/Utils$MillisProvider
Method	scala/actors/threadpool/helpers/Utils$MillisProvider."<init>":()V
class	scala/actors/threadpool/helpers/Utils
Asciz	MillisProvider;
Asciz	InnerClasses;
Asciz	SunPerfProvider;
Asciz	nanoTimer;
Asciz	Lscala/actors/threadpool/helpers/NanoTimer;;
Asciz	providerProp;
Asciz	Ljava/lang/String;;
Asciz	ConstantValue;
String	edu.emory.mathcs.backport.java.util.concurrent.NanoTimerProvider
Asciz	<init>;
Asciz	()V;
Asciz	Code;
Asciz	nanoTime;
Asciz	()J;
Asciz	awaitNanos;
Asciz	(Lscala/actors/threadpool/locks/Condition;J)J;
Asciz	Exceptions;
class	java/lang/InterruptedException
Asciz	gcd;
Asciz	(JJ)J;
Asciz	collectionToArray;
Asciz	(Ljava/util/Collection;)[Ljava/lang/Object;;
Asciz	(Ljava/util/Collection;[Ljava/lang/Object;)[Ljava/lang/Object;;
Asciz	access$000;
Asciz	<clinit>;
NameAndType	gcd:(JJ)J
NameAndType	"<init>":()V
NameAndType	nanoTimer:Lscala/actors/threadpool/helpers/NanoTimer;
NameAndType	nanoTime:()J
class	scala/actors/threadpool/TimeUnit
NameAndType	NANOSECONDS:Lscala/actors/threadpool/TimeUnit;
class	scala/actors/threadpool/locks/Condition
NameAndType	await:(JLscala/actors/threadpool/TimeUnit;)Z
class	java/util/Collection
NameAndType	size:()I
Asciz	java/lang/Object;
NameAndType	iterator:()Ljava/util/Iterator;
class	java/util/Iterator
NameAndType	hasNext:()Z
NameAndType	next:()Ljava/lang/Object;
Asciz	[Ljava/lang/Object;;
class	scala/actors/threadpool/Arrays
NameAndType	copyOf:([Ljava/lang/Object;ILjava/lang/Class;)[Ljava/lang/Object;
Asciz	java/lang/OutOfMemoryError;
Asciz	required array size too large;
NameAndType	"<init>":(Ljava/lang/String;)V
NameAndType	getClass:()Ljava/lang/Class;
class	java/lang/Class
NameAndType	getComponentType:()Ljava/lang/Class;
class	java/lang/reflect/Array
NameAndType	newInstance:(Ljava/lang/Class;I)Ljava/lang/Object;
Asciz	scala/actors/threadpool/helpers/Utils$1;
Asciz	;
class	java/security/AccessController
NameAndType	doPrivileged:(Ljava/security/PrivilegedAction;)Ljava/lang/Object;
Asciz	java/lang/String;
NameAndType	forName:(Ljava/lang/String;)Ljava/lang/Class;
NameAndType	newInstance:()Ljava/lang/Object;
Asciz	scala/actors/threadpool/helpers/NanoTimer;
Asciz	java/lang/Exception;
class	java/lang/System
NameAndType	err:Ljava/io/PrintStream;
Asciz	WARNING: unable to load the system-property-defined nanotime provider; switching to the default;
class	java/io/PrintStream
NameAndType	println:(Ljava/lang/String;)V
NameAndType	printStackTrace:()V
Asciz	scala/actors/threadpool/helpers/Utils$SunPerfProvider;
Asciz	java/lang/Throwable;
Asciz	scala/actors/threadpool/helpers/Utils$MillisProvider;
Asciz	scala/actors/threadpool/helpers/Utils;
Asciz	edu.emory.mathcs.backport.java.util.concurrent.NanoTimerProvider;
Asciz	java/lang/InterruptedException;
Asciz	scala/actors/threadpool/TimeUnit;
Asciz	NANOSECONDS;
Asciz	Lscala/actors/threadpool/TimeUnit;;
Asciz	scala/actors/threadpool/locks/Condition;
Asciz	await;
Asciz	(JLscala/actors/threadpool/TimeUnit;)Z;
Asciz	java/util/Collection;
Asciz	size;
Asciz	()I;
Asciz	iterator;
Asciz	()Ljava/util/Iterator;;
Asciz	java/util/Iterator;
Asciz	hasNext;
Asciz	()Z;
Asciz	next;
Asciz	()Ljava/lang/Object;;
Asciz	scala/actors/threadpool/Arrays;
Asciz	copyOf;
Asciz	([Ljava/lang/Object;ILjava/lang/Class;)[Ljava/lang/Object;;
Asciz	(Ljava/lang/String;)V;
Asciz	getClass;
Asciz	()Ljava/lang/Class;;
Asciz	java/lang/Class;
Asciz	getComponentType;
Asciz	java/lang/reflect/Array;
Asciz	newInstance;
Asciz	(Ljava/lang/Class;I)Ljava/lang/Object;;
Asciz	java/security/AccessController;
Asciz	doPrivileged;
Asciz	(Ljava/security/PrivilegedAction;)Ljava/lang/Object;;
Asciz	forName;
Asciz	(Ljava/lang/String;)Ljava/lang/Class;;
Asciz	java/lang/System;
Asciz	err;
Asciz	Ljava/io/PrintStream;;
Asciz	java/io/PrintStream;
Asciz	println;
Asciz	printStackTrace;

{
private static final scala.actors.threadpool.helpers.NanoTimer nanoTimer;
  Signature: Lscala/actors/threadpool/helpers/NanoTimer;

private static final java.lang.String providerProp;
  Signature: Ljava/lang/String;
  Constant value: String edu.emory.mathcs.backport.java.util.concurrent.NanoTimerProvider
private scala.actors.threadpool.helpers.Utils();
  Signature: ()V
  Code:
   Stack=1, Locals=1, Args_size=1
	aload_0
	invokespecial	Method java/lang/Object."<init>":()V
	return
  Labels:

public static long nanoTime();
  Signature: ()J
  Code:
   Stack=2, Locals=0, Args_size=0
	getstatic	Field nanoTimer:Lscala/actors/threadpool/helpers/NanoTimer;
	invokeinterface	InterfaceMethod scala/actors/threadpool/helpers/NanoTimer.nanoTime:()J
	lreturn
  Labels:

public static long awaitNanos(scala.actors.threadpool.locks.Condition, long)   throws java.lang.InterruptedException;
  Signature: (Lscala/actors/threadpool/locks/Condition;J)J
  Code:
   Stack=6, Locals=5, Args_size=2
	lload_1
	lconst_0
	lcmp
	ifgt	l1 // invokestatic
	lload_1
	lreturn
l1	invokestatic	Method nanoTime:()J
	lstore_3
	aload_0
	lload_1
	getstatic	Field scala/actors/threadpool/TimeUnit.NANOSECONDS:Lscala/actors/threadpool/TimeUnit;
	invokeinterface	InterfaceMethod scala/actors/threadpool/locks/Condition.await:(JLscala/actors/threadpool/TimeUnit;)Z
	pop
	lload_1
	invokestatic	Method nanoTime:()J
	lload_3
	lsub
	lsub
	lreturn
  Labels:
   	l1 = 8 // invokestatic
  Exceptions: 
   throws java.lang.InterruptedException
private static long gcd(long, long);
  Signature: (JJ)J
  Code:
   Stack=4, Locals=6, Args_size=2
l2	lload_2
	lconst_0
	lcmp
	ifle	l1 // lload_0
	lload_0
	lload_2
	lrem
	lstore	4
	lload_2
	lstore_0
	lload	4
	lstore_2
	goto	l2 // lload_2
l1	lload_0
	lreturn
  Labels:
   	l2 = 0 // lload_2
   	l1 = 19 // lload_0

public static java.lang.Object[] collectionToArray(java.util.Collection);
  Signature: (Ljava/util/Collection;)[Ljava/lang/Object;
  Code:
   Stack=3, Locals=6, Args_size=1
	aload_0
	invokeinterface	InterfaceMethod java/util/Collection.size:()I
	istore_1
	iload_1
	anewarray	class java/lang/Object
	astore_2
	aload_0
	invokeinterface	InterfaceMethod java/util/Collection.iterator:()Ljava/util/Iterator;
	astore_3
	iconst_0
	istore	4
l2	iload	4
	iload_1
	if_icmpge	l1 // aload_3
	aload_3
	invokeinterface	InterfaceMethod java/util/Iterator.hasNext:()Z
	ifeq	l1 // aload_3
	aload_2
	iload	4
	iinc	4, 1
	aload_3
	invokeinterface	InterfaceMethod java/util/Iterator.next:()Ljava/lang/Object;
	aastore
	goto	l2 // iload
l1	aload_3
	invokeinterface	InterfaceMethod java/util/Iterator.hasNext:()Z
	ifne	l3 // aload_2
	iload	4
	iload_1
	if_icmpne	l4 // aload_2
	aload_2
	areturn
l4	aload_2
	iload	4
	ldc_w	class "[Ljava/lang/Object;"
	invokestatic	Method scala/actors/threadpool/Arrays.copyOf:([Ljava/lang/Object;ILjava/lang/Class;)[Ljava/lang/Object;
	areturn
l3	aload_2
	arraylength
	iconst_2
	idiv
	iconst_1
	iadd
	iconst_3
	imul
	istore	5
	iload	5
	aload_2
	arraylength
	if_icmpge	l5 // aload_2
	aload_2
	arraylength
	ldc	int 2147483647
	if_icmpge	l6 // new
	ldc	int 2147483647
	istore	5
	goto	l5 // aload_2
l6	new	class java/lang/OutOfMemoryError
	dup
	ldc	String required array size too large
	invokespecial	Method java/lang/OutOfMemoryError."<init>":(Ljava/lang/String;)V
	athrow
l5	aload_2
	iload	5
	ldc_w	class "[Ljava/lang/Object;"
	invokestatic	Method scala/actors/threadpool/Arrays.copyOf:([Ljava/lang/Object;ILjava/lang/Class;)[Ljava/lang/Object;
	astore_2
	iload	5
	istore_1
	goto	l2 // iload
  Labels:
   	l2 = 22 // iload
   	l1 = 53 // aload_3
   	l4 = 70 // aload_2
   	l3 = 80 // aload_2
   	l6 = 111 // new
   	l5 = 121 // aload_2

public static java.lang.Object[] collectionToArray(java.util.Collection, java.lang.Object[]);
  Signature: (Ljava/util/Collection;[Ljava/lang/Object;)[Ljava/lang/Object;
  Code:
   Stack=3, Locals=8, Args_size=2
	aload_1
	invokevirtual	Method java/lang/Object.getClass:()Ljava/lang/Class;
	astore_2
	aload_0
	invokeinterface	InterfaceMethod java/util/Collection.size:()I
	istore_3
	aload_1
	arraylength
	iload_3
	if_icmplt	l1 // aload_2
	aload_1
	goto	l2 // astore
l1	aload_2
	invokevirtual	Method java/lang/Class.getComponentType:()Ljava/lang/Class;
	iload_3
	invokestatic	Method java/lang/reflect/Array.newInstance:(Ljava/lang/Class;I)Ljava/lang/Object;
	checkcast	class "[Ljava/lang/Object;"
	checkcast	class "[Ljava/lang/Object;"
l2	astore	4
	aload_0
	invokeinterface	InterfaceMethod java/util/Collection.iterator:()Ljava/util/Iterator;
	astore	5
	iconst_0
	istore	6
l4	iload	6
	iload_3
	if_icmpge	l3 // aload
	aload	5
	invokeinterface	InterfaceMethod java/util/Iterator.hasNext:()Z
	ifeq	l3 // aload
	aload	4
	iload	6
	iinc	6, 1
	aload	5
	invokeinterface	InterfaceMethod java/util/Iterator.next:()Ljava/lang/Object;
	aastore
	goto	l4 // iload
l3	aload	5
	invokeinterface	InterfaceMethod java/util/Iterator.hasNext:()Z
	ifne	l5 // aload
	iload	6
	iload_3
	if_icmpne	l6 // aload
	aload	4
	areturn
l6	aload	4
	aload_1
	if_acmpne	l7 // aload
	aload_1
	iload	6
	aconst_null
	aastore
	aload_1
	areturn
l7	aload	4
	iload	6
	aload_2
	invokestatic	Method scala/actors/threadpool/Arrays.copyOf:([Ljava/lang/Object;ILjava/lang/Class;)[Ljava/lang/Object;
	areturn
l5	aload	4
	arraylength
	iconst_2
	idiv
	iconst_1
	iadd
	iconst_3
	imul
	istore	7
	iload	7
	aload	4
	arraylength
	if_icmpge	l8 // aload
	aload	4
	arraylength
	ldc	int 2147483647
	if_icmpge	l9 // new
	ldc	int 2147483647
	istore	7
	goto	l8 // aload
l9	new	class java/lang/OutOfMemoryError
	dup
	ldc	String required array size too large
	invokespecial	Method java/lang/OutOfMemoryError."<init>":(Ljava/lang/String;)V
	athrow
l8	aload	4
	iload	7
	aload_2
	invokestatic	Method scala/actors/threadpool/Arrays.copyOf:([Ljava/lang/Object;ILjava/lang/Class;)[Ljava/lang/Object;
	astore	4
	iload	7
	istore_3
	goto	l4 // iload
  Labels:
   	l1 = 22 // aload_2
   	l2 = 36 // astore
   	l4 = 49 // iload
   	l3 = 83 // aload
   	l6 = 102 // aload
   	l7 = 115 // aload
   	l5 = 124 // aload
   	l9 = 158 // new
   	l8 = 168 // aload

static long access$000(long, long);
  Signature: (JJ)J
  Code:
   Stack=4, Locals=4, Args_size=2
	lload_0
	lload_2
	invokestatic	Method gcd:(JJ)J
	lreturn
  Labels:

static {};
  Signature: ()V
  Code:
   Stack=2, Locals=3, Args_size=0
	aconst_null
	astore_0
	new	class scala/actors/threadpool/helpers/Utils$1
	dup
	invokespecial	Method scala/actors/threadpool/helpers/Utils$1."<init>":()V
	invokestatic	Method java/security/AccessController.doPrivileged:(Ljava/security/PrivilegedAction;)Ljava/lang/Object;
	checkcast	class java/lang/String
	astore_1
	aload_1
	ifnull	l1 // goto
	aload_1
	invokestatic	Method java/lang/Class.forName:(Ljava/lang/String;)Ljava/lang/Class;
	astore_2
	aload_2
	invokevirtual	Method java/lang/Class.newInstance:()Ljava/lang/Object;
	checkcast	class scala/actors/threadpool/helpers/NanoTimer
	astore_0
l1	goto	l2 // aload_0
	astore_1
	getstatic	Field java/lang/System.err:Ljava/io/PrintStream;
	ldc	String WARNING: unable to load the system-property-defined nanotime provider; switching to the default
	invokevirtual	Method java/io/PrintStream.println:(Ljava/lang/String;)V
	aload_1
	invokevirtual	Method java/lang/Exception.printStackTrace:()V
l2	aload_0
	ifnonnull	l3 // aload_0
	new	class scala/actors/threadpool/helpers/Utils$SunPerfProvider
	dup
	invokespecial	Method scala/actors/threadpool/helpers/Utils$SunPerfProvider."<init>":()V
	astore_0
	goto	l3 // aload_0
	astore_1
l3	aload_0
	ifnonnull	l4 // aload_0
	new	class scala/actors/threadpool/helpers/Utils$MillisProvider
	dup
	invokespecial	Method scala/actors/threadpool/helpers/Utils$MillisProvider."<init>":()V
	astore_0
l4	aload_0
	putstatic	Field nanoTimer:Lscala/actors/threadpool/helpers/NanoTimer;
	return
  Labels:
   	l1 = 33 // goto
   	l2 = 49 // aload_0
   	l3 = 65 // aload_0
   	l4 = 77 // aload_0
  Exception table:
   from   to  target type
     2    33    36   Class java/lang/Exception

    53    61    64   Class java/lang/Throwable


}

