class scala.actors.threadpool.helpers.Utils$1 extends java.lang.Object implements java.security.PrivilegedAction
  EnclosingMethod: length = 0x4
   00 0D 00 00 
  InnerClass: 
   #4; //class scala/actors/threadpool/helpers/Utils$1
  minor version: 0
  major version: 49
  Constant pool:
const #1 = Method	#5.#14;	//  java/lang/Object."<init>":()V
const #2 = String	#15;	//  edu.emory.mathcs.backport.java.util.concurrent.NanoTimerProvider
const #3 = Method	#16.#17;	//  java/lang/System.getProperty:(Ljava/lang/String;)Ljava/lang/String;
const #4 = class	#18;	//  scala/actors/threadpool/helpers/Utils$1
const #5 = class	#21;	//  java/lang/Object
const #6 = class	#22;	//  java/security/PrivilegedAction
const #7 = Asciz	<init>;
const #8 = Asciz	()V;
const #9 = Asciz	Code;
const #10 = Asciz	run;
const #11 = Asciz	()Ljava/lang/Object;;
const #12 = Asciz	EnclosingMethod;
const #13 = class	#23;	//  scala/actors/threadpool/helpers/Utils
const #14 = NameAndType	#7:#8;//  "<init>":()V
const #15 = Asciz	edu.emory.mathcs.backport.java.util.concurrent.NanoTimerProvider;
const #16 = class	#24;	//  java/lang/System
const #17 = NameAndType	#25:#26;//  getProperty:(Ljava/lang/String;)Ljava/lang/String;
const #18 = Asciz	scala/actors/threadpool/helpers/Utils$1;
const #19 = Asciz	;
const #20 = Asciz	InnerClasses;
const #21 = Asciz	java/lang/Object;
const #22 = Asciz	java/security/PrivilegedAction;
const #23 = Asciz	scala/actors/threadpool/helpers/Utils;
const #24 = Asciz	java/lang/System;
const #25 = Asciz	getProperty;
const #26 = Asciz	(Ljava/lang/String;)Ljava/lang/String;;

{
scala.actors.threadpool.helpers.Utils$1();
  Code:
   Stack=1, Locals=1, Args_size=1
   0:	aload_0
   1:	invokespecial	#1; //Method java/lang/Object."<init>":()V
   4:	return

public java.lang.Object run();
  Code:
   Stack=1, Locals=1, Args_size=1
   0:	ldc	#2; //String edu.emory.mathcs.backport.java.util.concurrent.NanoTimerProvider
   2:	invokestatic	#3; //Method java/lang/System.getProperty:(Ljava/lang/String;)Ljava/lang/String;
   5:	areturn

}

