class scala.actors.threadpool.helpers.Utils$SunPerfProvider$1 extends java.lang.Object implements java.security.PrivilegedAction
  EnclosingMethod: length = 0x4
   00 08 00 12 
  InnerClass: 
   final #9= #8 of #26; //SunPerfProvider=class scala/actors/threadpool/helpers/Utils$SunPerfProvider of class scala/actors/threadpool/helpers/Utils
   #4; //class scala/actors/threadpool/helpers/Utils$SunPerfProvider$1
  minor version: 0
  major version: 49
  Constant pool:
const #1 = Field	#4.#19;	//  scala/actors/threadpool/helpers/Utils$SunPerfProvider$1.this$0:Lscala/actors/threadpool/helpers/Utils$SunPerfProvider;
const #2 = Method	#5.#18;	//  java/lang/Object."<init>":()V
const #3 = Method	#20.#21;	//  scala/actors/threadpool/Perf.getPerf:()Lscala/actors/threadpool/Perf;
const #4 = class	#22;	//  scala/actors/threadpool/helpers/Utils$SunPerfProvider$1
const #5 = class	#24;	//  java/lang/Object
const #6 = class	#25;	//  java/security/PrivilegedAction
const #7 = Asciz	this$0;
const #8 = class	#27;	//  scala/actors/threadpool/helpers/Utils$SunPerfProvider
const #9 = Asciz	SunPerfProvider;
const #10 = Asciz	InnerClasses;
const #11 = Asciz	Lscala/actors/threadpool/helpers/Utils$SunPerfProvider;;
const #12 = Asciz	<init>;
const #13 = Asciz	(Lscala/actors/threadpool/helpers/Utils$SunPerfProvider;)V;
const #14 = Asciz	Code;
const #15 = Asciz	run;
const #16 = Asciz	()Ljava/lang/Object;;
const #17 = Asciz	EnclosingMethod;
const #18 = NameAndType	#12:#28;//  "<init>":()V
const #19 = NameAndType	#7:#11;//  this$0:Lscala/actors/threadpool/helpers/Utils$SunPerfProvider;
const #20 = class	#29;	//  scala/actors/threadpool/Perf
const #21 = NameAndType	#30:#31;//  getPerf:()Lscala/actors/threadpool/Perf;
const #22 = Asciz	scala/actors/threadpool/helpers/Utils$SunPerfProvider$1;
const #23 = Asciz	;
const #24 = Asciz	java/lang/Object;
const #25 = Asciz	java/security/PrivilegedAction;
const #26 = class	#32;	//  scala/actors/threadpool/helpers/Utils
const #27 = Asciz	scala/actors/threadpool/helpers/Utils$SunPerfProvider;
const #28 = Asciz	()V;
const #29 = Asciz	scala/actors/threadpool/Perf;
const #30 = Asciz	getPerf;
const #31 = Asciz	()Lscala/actors/threadpool/Perf;;
const #32 = Asciz	scala/actors/threadpool/helpers/Utils;

{
final scala.actors.threadpool.helpers.Utils$SunPerfProvider this$0;

scala.actors.threadpool.helpers.Utils$SunPerfProvider$1(scala.actors.threadpool.helpers.Utils$SunPerfProvider);
  Code:
   Stack=2, Locals=2, Args_size=2
   0:	aload_0
   1:	aload_1
   2:	putfield	#1; //Field this$0:Lscala/actors/threadpool/helpers/Utils$SunPerfProvider;
   5:	aload_0
   6:	invokespecial	#2; //Method java/lang/Object."<init>":()V
   9:	return

public java.lang.Object run();
  Code:
   Stack=1, Locals=1, Args_size=1
   0:	invokestatic	#3; //Method scala/actors/threadpool/Perf.getPerf:()Lscala/actors/threadpool/Perf;
   3:	areturn

}

