final class scala.actors.threadpool.helpers.Utils$SunPerfProvider extends java.lang.Object implements scala.actors.threadpool.helpers.NanoTimer
  InnerClass: 
   #2; //class scala/actors/threadpool/helpers/Utils$SunPerfProvider$1
   final #43= #14 of #37; //SunPerfProvider=class scala/actors/threadpool/helpers/Utils$SunPerfProvider of class scala/actors/threadpool/helpers/Utils
  minor version: 0
  major version: 49
  Constant pool:
const #1 = Method	#15.#27;	//  java/lang/Object."<init>":()V
const #2 = class	#28;	//  scala/actors/threadpool/helpers/Utils$SunPerfProvider$1
const #3 = Method	#2.#31;	//  scala/actors/threadpool/helpers/Utils$SunPerfProvider$1."<init>":(Lscala/actors/threadpool/helpers/Utils$SunPerfProvider;)V
const #4 = Method	#32.#33;	//  java/security/AccessController.doPrivileged:(Ljava/security/PrivilegedAction;)Ljava/lang/Object;
const #5 = class	#34;	//  scala/actors/threadpool/Perf
const #6 = Field	#14.#35;	//  scala/actors/threadpool/helpers/Utils$SunPerfProvider.perf:Lscala/actors/threadpool/Perf;
const #7 = long	1000000000l;
const #9 = Method	#5.#36;	//  scala/actors/threadpool/Perf.highResFrequency:()J
const #10 = Method	#37.#38;	//  scala/actors/threadpool/helpers/Utils.access$000:(JJ)J
const #11 = Field	#14.#39;	//  scala/actors/threadpool/helpers/Utils$SunPerfProvider.multiplier:J
const #12 = Field	#14.#40;	//  scala/actors/threadpool/helpers/Utils$SunPerfProvider.divisor:J
const #13 = Method	#5.#41;	//  scala/actors/threadpool/Perf.highResCounter:()J
const #14 = class	#42;	//  scala/actors/threadpool/helpers/Utils$SunPerfProvider
const #15 = class	#44;	//  java/lang/Object
const #16 = class	#45;	//  scala/actors/threadpool/helpers/NanoTimer
const #17 = Asciz	perf;
const #18 = Asciz	Lscala/actors/threadpool/Perf;;
const #19 = Asciz	multiplier;
const #20 = Asciz	J;
const #21 = Asciz	divisor;
const #22 = Asciz	<init>;
const #23 = Asciz	()V;
const #24 = Asciz	Code;
const #25 = Asciz	nanoTime;
const #26 = Asciz	()J;
const #27 = NameAndType	#22:#23;//  "<init>":()V
const #28 = Asciz	scala/actors/threadpool/helpers/Utils$SunPerfProvider$1;
const #29 = Asciz	;
const #30 = Asciz	InnerClasses;
const #31 = NameAndType	#22:#46;//  "<init>":(Lscala/actors/threadpool/helpers/Utils$SunPerfProvider;)V
const #32 = class	#47;	//  java/security/AccessController
const #33 = NameAndType	#48:#49;//  doPrivileged:(Ljava/security/PrivilegedAction;)Ljava/lang/Object;
const #34 = Asciz	scala/actors/threadpool/Perf;
const #35 = NameAndType	#17:#18;//  perf:Lscala/actors/threadpool/Perf;
const #36 = NameAndType	#50:#26;//  highResFrequency:()J
const #37 = class	#51;	//  scala/actors/threadpool/helpers/Utils
const #38 = NameAndType	#52:#53;//  access$000:(JJ)J
const #39 = NameAndType	#19:#20;//  multiplier:J
const #40 = NameAndType	#21:#20;//  divisor:J
const #41 = NameAndType	#54:#26;//  highResCounter:()J
const #42 = Asciz	scala/actors/threadpool/helpers/Utils$SunPerfProvider;
const #43 = Asciz	SunPerfProvider;
const #44 = Asciz	java/lang/Object;
const #45 = Asciz	scala/actors/threadpool/helpers/NanoTimer;
const #46 = Asciz	(Lscala/actors/threadpool/helpers/Utils$SunPerfProvider;)V;
const #47 = Asciz	java/security/AccessController;
const #48 = Asciz	doPrivileged;
const #49 = Asciz	(Ljava/security/PrivilegedAction;)Ljava/lang/Object;;
const #50 = Asciz	highResFrequency;
const #51 = Asciz	scala/actors/threadpool/helpers/Utils;
const #52 = Asciz	access$000;
const #53 = Asciz	(JJ)J;
const #54 = Asciz	highResCounter;

{
final scala.actors.threadpool.Perf perf;

final long multiplier;

final long divisor;

scala.actors.threadpool.helpers.Utils$SunPerfProvider();
  Code:
   Stack=5, Locals=7, Args_size=1
   0:	aload_0
   1:	invokespecial	#1; //Method java/lang/Object."<init>":()V
   4:	aload_0
   5:	new	#2; //class scala/actors/threadpool/helpers/Utils$SunPerfProvider$1
   8:	dup
   9:	aload_0
   10:	invokespecial	#3; //Method scala/actors/threadpool/helpers/Utils$SunPerfProvider$1."<init>":(Lscala/actors/threadpool/helpers/Utils$SunPerfProvider;)V
   13:	invokestatic	#4; //Method java/security/AccessController.doPrivileged:(Ljava/security/PrivilegedAction;)Ljava/lang/Object;
   16:	checkcast	#5; //class scala/actors/threadpool/Perf
   19:	putfield	#6; //Field perf:Lscala/actors/threadpool/Perf;
   22:	ldc2_w	#7; //long 1000000000l
   25:	lstore_1
   26:	aload_0
   27:	getfield	#6; //Field perf:Lscala/actors/threadpool/Perf;
   30:	invokevirtual	#9; //Method scala/actors/threadpool/Perf.highResFrequency:()J
   33:	lstore_3
   34:	lload_1
   35:	lload_3
   36:	invokestatic	#10; //Method scala/actors/threadpool/helpers/Utils.access$000:(JJ)J
   39:	lstore	5
   41:	aload_0
   42:	lload_1
   43:	lload	5
   45:	ldiv
   46:	putfield	#11; //Field multiplier:J
   49:	aload_0
   50:	lload_3
   51:	lload	5
   53:	ldiv
   54:	putfield	#12; //Field divisor:J
   57:	return

public long nanoTime();
  Code:
   Stack=6, Locals=3, Args_size=1
   0:	aload_0
   1:	getfield	#6; //Field perf:Lscala/actors/threadpool/Perf;
   4:	invokevirtual	#13; //Method scala/actors/threadpool/Perf.highResCounter:()J
   7:	lstore_1
   8:	lload_1
   9:	aload_0
   10:	getfield	#12; //Field divisor:J
   13:	ldiv
   14:	aload_0
   15:	getfield	#11; //Field multiplier:J
   18:	lmul
   19:	lload_1
   20:	aload_0
   21:	getfield	#12; //Field divisor:J
   24:	lrem
   25:	aload_0
   26:	getfield	#11; //Field multiplier:J
   29:	lmul
   30:	aload_0
   31:	getfield	#12; //Field divisor:J
   34:	ldiv
   35:	ladd
   36:	lreturn

}

