final class scala.actors.threadpool.helpers.Utils$MillisProvider extends java.lang.Object implements scala.actors.threadpool.helpers.NanoTimer
  InnerClass: 
   final #18= #5 of #16; //MillisProvider=class scala/actors/threadpool/helpers/Utils$MillisProvider of class scala/actors/threadpool/helpers/Utils
  minor version: 0
  major version: 49
  Constant pool:
const #1 = Method	#6.#13;	//  java/lang/Object."<init>":()V
const #2 = Method	#14.#15;	//  java/lang/System.currentTimeMillis:()J
const #3 = long	1000000l;
const #5 = class	#17;	//  scala/actors/threadpool/helpers/Utils$MillisProvider
const #6 = class	#20;	//  java/lang/Object
const #7 = class	#21;	//  scala/actors/threadpool/helpers/NanoTimer
const #8 = Asciz	<init>;
const #9 = Asciz	()V;
const #10 = Asciz	Code;
const #11 = Asciz	nanoTime;
const #12 = Asciz	()J;
const #13 = NameAndType	#8:#9;//  "<init>":()V
const #14 = class	#22;	//  java/lang/System
const #15 = NameAndType	#23:#12;//  currentTimeMillis:()J
const #16 = class	#24;	//  scala/actors/threadpool/helpers/Utils
const #17 = Asciz	scala/actors/threadpool/helpers/Utils$MillisProvider;
const #18 = Asciz	MillisProvider;
const #19 = Asciz	InnerClasses;
const #20 = Asciz	java/lang/Object;
const #21 = Asciz	scala/actors/threadpool/helpers/NanoTimer;
const #22 = Asciz	java/lang/System;
const #23 = Asciz	currentTimeMillis;
const #24 = Asciz	scala/actors/threadpool/helpers/Utils;

{
scala.actors.threadpool.helpers.Utils$MillisProvider();
  Code:
   Stack=1, Locals=1, Args_size=1
   0:	aload_0
   1:	invokespecial	#1; //Method java/lang/Object."<init>":()V
   4:	return

public long nanoTime();
  Code:
   Stack=4, Locals=1, Args_size=1
   0:	invokestatic	#2; //Method java/lang/System.currentTimeMillis:()J
   3:	ldc2_w	#3; //long 1000000l
   6:	lmul
   7:	lreturn

}

