Compiled from "AbstractFunction0.scala"
public abstract class scala.runtime.AbstractFunction0$mcI$sp extends scala.runtime.AbstractFunction0 implements scala.Function0$mcI$sp
  SourceFile: "AbstractFunction0.scala"
  Scala: length = 0x
   
  Signature: length = 0x2
   00 22 
  minor version: 0
  major version: 49
  Constant pool:
Asciz	SourceFile;
Asciz	AbstractFunction0.scala;
Asciz	apply;
Asciz	()I;
Asciz	Code;
Asciz	LineNumberTable;
Asciz	scala/Function0$mcI$sp$class;
class	scala/Function0$mcI$sp$class
Asciz	(Lscala/Function0$mcI$sp;)I;
NameAndType	apply:(Lscala/Function0$mcI$sp;)I
Method	scala/Function0$mcI$sp$class.apply:(Lscala/Function0$mcI$sp;)I
Asciz	()Ljava/lang/Object;;
Asciz	scala/Function0$mcI$sp;
class	scala/Function0$mcI$sp
NameAndType	apply:()I
InterfaceMethod	scala/Function0$mcI$sp.apply:()I
Asciz	scala/runtime/BoxesRunTime;
class	scala/runtime/BoxesRunTime
Asciz	boxToInteger;
Asciz	(I)Ljava/lang/Integer;;
NameAndType	boxToInteger:(I)Ljava/lang/Integer;
Method	scala/runtime/BoxesRunTime.boxToInteger:(I)Ljava/lang/Integer;
Asciz	<init>;
Asciz	()V;
Asciz	scala/runtime/AbstractFunction0;
class	scala/runtime/AbstractFunction0
NameAndType	"<init>":()V
Method	scala/runtime/AbstractFunction0."<init>":()V
Asciz	$init$;
Asciz	(Lscala/Function0$mcI$sp;)V;
NameAndType	$init$:(Lscala/Function0$mcI$sp;)V
Method	scala/Function0$mcI$sp$class.$init$:(Lscala/Function0$mcI$sp;)V
Asciz	Scala;
Asciz	Lscala/runtime/AbstractFunction0<Ljava/lang/Integer;>;Lscala/Function0$mcI$sp;;
Asciz	Signature;
Asciz	scala/runtime/AbstractFunction0$mcI$sp;
class	scala/runtime/AbstractFunction0$mcI$sp

{
public int apply();
  Signature: ()I
  Code:
   Stack=1, Locals=1, Args_size=1
	aload_0
	invokestatic	Method scala/Function0$mcI$sp$class.apply:(Lscala/Function0$mcI$sp;)I
	ireturn
  Labels:

public java.lang.Object apply();
  Signature: ()Ljava/lang/Object;
  Code:
   Stack=1, Locals=2, Args_size=1
	aload_0
	invokeinterface	InterfaceMethod scala/Function0$mcI$sp.apply:()I
	istore_1
	iload_1
	invokestatic	Method scala/runtime/BoxesRunTime.boxToInteger:(I)Ljava/lang/Integer;
	areturn
  Labels:

public scala.runtime.AbstractFunction0$mcI$sp();
  Signature: ()V
  Code:
   Stack=1, Locals=1, Args_size=1
	aload_0
	invokespecial	Method scala/runtime/AbstractFunction0."<init>":()V
	aload_0
	invokestatic	Method scala/Function0$mcI$sp$class.$init$:(Lscala/Function0$mcI$sp;)V
	return
  Labels:

}

