Compiled from "AbstractFunction4.scala"
public abstract class scala.runtime.AbstractFunction4 extends java.lang.Object implements scala.Function4,scala.ScalaObject
  SourceFile: "AbstractFunction4.scala"
  ScalaSig: length = 0x3
   05 00 00 
  Signature: length = 0x2
   00 24 
  RuntimeVisibleAnnotations: length = 0xB
   00 01 00 25 00 01 00 26 73 00 27 
  minor version: 0
  major version: 49
  Constant pool:
Asciz	SourceFile;
Asciz	AbstractFunction4.scala;
Asciz	toString;
Asciz	()Ljava/lang/String;;
Asciz	Code;
Asciz	LineNumberTable;
Asciz	scala/Function4$class;
class	scala/Function4$class
Asciz	(Lscala/Function4;)Ljava/lang/String;;
NameAndType	toString:(Lscala/Function4;)Ljava/lang/String;
Method	scala/Function4$class.toString:(Lscala/Function4;)Ljava/lang/String;
Asciz	curried;
Asciz	()Lscala/Function1;;
Asciz	(Lscala/Function4;)Lscala/Function1;;
NameAndType	curried:(Lscala/Function4;)Lscala/Function1;
Method	scala/Function4$class.curried:(Lscala/Function4;)Lscala/Function1;
Asciz	curry;
NameAndType	curry:(Lscala/Function4;)Lscala/Function1;
Method	scala/Function4$class.curry:(Lscala/Function4;)Lscala/Function1;
Asciz	Deprecated;
Asciz	tupled;
NameAndType	tupled:(Lscala/Function4;)Lscala/Function1;
Method	scala/Function4$class.tupled:(Lscala/Function4;)Lscala/Function1;
Asciz	<init>;
Asciz	()V;
Asciz	java/lang/Object;
class	java/lang/Object
NameAndType	"<init>":()V
Method	java/lang/Object."<init>":()V
Asciz	$init$;
Asciz	(Lscala/Function4;)V;
NameAndType	$init$:(Lscala/Function4;)V
Method	scala/Function4$class.$init$:(Lscala/Function4;)V
Asciz	Signature;
Asciz	ScalaSig;
Asciz	<T1:Ljava/lang/Object;T2:Ljava/lang/Object;T3:Ljava/lang/Object;T4:Ljava/lang/Object;R:Ljava/lang/Object;>Ljava/lang/Object;Lscala/Function4<TT1;TT2;TT3;TT4;TR;>;Lscala/ScalaObject;;
Asciz	Lscala/reflect/ScalaSignature;;
Asciz	bytes;
Asciz	Q2Q!#2tiJ7\r$v]$n85\tA!Ask:$.\3\tQa]2bY!\t/\"sEK\n%\tB5\t1B\r!A.8hq6bmL!E\r='.Z2u!2#$M%jB)BR;oGRLwNY9B\t1!\t#b3\tA+M\t5u\"AE\nq!!a(pi\"Lgn\t%yI!asCA!CDUeAa\n\tK!\t#b3\tAk\r\t-\"#\r!)R\"A-A!CCeA\t%5J!AM\r\1PE*,7\ra!\t!My%t Ira\rA\r2&D;
Asciz	RuntimeVisibleAnnotations;
Asciz	scala/runtime/AbstractFunction4;
class	scala/runtime/AbstractFunction4
Asciz	scala/Function4;
class	scala/Function4
Asciz	scala/ScalaObject;
class	scala/ScalaObject

{
public java.lang.String toString();
  Signature: ()Ljava/lang/String;
  Code:
   Stack=1, Locals=1, Args_size=1
	aload_0
	invokestatic	Method scala/Function4$class.toString:(Lscala/Function4;)Ljava/lang/String;
	areturn
  Labels:

public scala.Function1 curried();
  Signature: ()Lscala/Function1;
  Code:
   Stack=1, Locals=1, Args_size=1
	aload_0
	invokestatic	Method scala/Function4$class.curried:(Lscala/Function4;)Lscala/Function1;
	areturn
  Labels:

public scala.Function1 curry();
  Signature: ()Lscala/Function1;
  Code:
   Stack=1, Locals=1, Args_size=1
	aload_0
	invokestatic	Method scala/Function4$class.curry:(Lscala/Function4;)Lscala/Function1;
	areturn
  Labels:
  Deprecated: true

public scala.Function1 tupled();
  Signature: ()Lscala/Function1;
  Code:
   Stack=1, Locals=1, Args_size=1
	aload_0
	invokestatic	Method scala/Function4$class.tupled:(Lscala/Function4;)Lscala/Function1;
	areturn
  Labels:

public scala.runtime.AbstractFunction4();
  Signature: ()V
  Code:
   Stack=1, Locals=1, Args_size=1
	aload_0
	invokespecial	Method java/lang/Object."<init>":()V
	aload_0
	invokestatic	Method scala/Function4$class.$init$:(Lscala/Function4;)V
	return
  Labels:
  Signature: length = 0x2
   00 19 

}

