Compiled from "AbstractFunction0.scala"
public abstract class scala.runtime.AbstractFunction0$mcL$sp extends scala.runtime.AbstractFunction0 implements scala.Function0$mcL$sp
  SourceFile: "AbstractFunction0.scala"
  Scala: length = 0x
   
  Signature: length = 0x2
   00 22 
  minor version: 0
  major version: 49
  Constant pool:
Asciz	SourceFile;
Asciz	AbstractFunction0.scala;
Asciz	apply;
Asciz	()J;
Asciz	Code;
Asciz	LineNumberTable;
Asciz	scala/Function0$mcL$sp$class;
class	scala/Function0$mcL$sp$class
Asciz	(Lscala/Function0$mcL$sp;)J;
NameAndType	apply:(Lscala/Function0$mcL$sp;)J
Method	scala/Function0$mcL$sp$class.apply:(Lscala/Function0$mcL$sp;)J
Asciz	()Ljava/lang/Object;;
Asciz	scala/Function0$mcL$sp;
class	scala/Function0$mcL$sp
NameAndType	apply:()J
InterfaceMethod	scala/Function0$mcL$sp.apply:()J
Asciz	scala/runtime/BoxesRunTime;
class	scala/runtime/BoxesRunTime
Asciz	boxToLong;
Asciz	(J)Ljava/lang/Long;;
NameAndType	boxToLong:(J)Ljava/lang/Long;
Method	scala/runtime/BoxesRunTime.boxToLong:(J)Ljava/lang/Long;
Asciz	<init>;
Asciz	()V;
Asciz	scala/runtime/AbstractFunction0;
class	scala/runtime/AbstractFunction0
NameAndType	"<init>":()V
Method	scala/runtime/AbstractFunction0."<init>":()V
Asciz	$init$;
Asciz	(Lscala/Function0$mcL$sp;)V;
NameAndType	$init$:(Lscala/Function0$mcL$sp;)V
Method	scala/Function0$mcL$sp$class.$init$:(Lscala/Function0$mcL$sp;)V
Asciz	Scala;
Asciz	Lscala/runtime/AbstractFunction0<Ljava/lang/Long;>;Lscala/Function0$mcL$sp;;
Asciz	Signature;
Asciz	scala/runtime/AbstractFunction0$mcL$sp;
class	scala/runtime/AbstractFunction0$mcL$sp

{
public long apply();
  Signature: ()J
  Code:
   Stack=2, Locals=1, Args_size=1
	aload_0
	invokestatic	Method scala/Function0$mcL$sp$class.apply:(Lscala/Function0$mcL$sp;)J
	lreturn
  Labels:

public java.lang.Object apply();
  Signature: ()Ljava/lang/Object;
  Code:
   Stack=2, Locals=3, Args_size=1
	aload_0
	invokeinterface	InterfaceMethod scala/Function0$mcL$sp.apply:()J
	lstore_1
	lload_1
	invokestatic	Method scala/runtime/BoxesRunTime.boxToLong:(J)Ljava/lang/Long;
	areturn
  Labels:

public scala.runtime.AbstractFunction0$mcL$sp();
  Signature: ()V
  Code:
   Stack=1, Locals=1, Args_size=1
	aload_0
	invokespecial	Method scala/runtime/AbstractFunction0."<init>":()V
	aload_0
	invokestatic	Method scala/Function0$mcL$sp$class.$init$:(Lscala/Function0$mcL$sp;)V
	return
  Labels:

}

