Compiled from "AbstractFunction10.scala"
public abstract class scala.runtime.AbstractFunction10 extends java.lang.Object implements scala.Function10,scala.ScalaObject
  SourceFile: "AbstractFunction10.scala"
  ScalaSig: length = 0x3
   05 00 00 
  Signature: length = 0x2
   00 24 
  RuntimeVisibleAnnotations: length = 0xB
   00 01 00 25 00 01 00 26 73 00 27 
  minor version: 0
  major version: 49
  Constant pool:
Asciz	SourceFile;
Asciz	AbstractFunction10.scala;
Asciz	toString;
Asciz	()Ljava/lang/String;;
Asciz	Code;
Asciz	LineNumberTable;
Asciz	scala/Function10$class;
class	scala/Function10$class
Asciz	(Lscala/Function10;)Ljava/lang/String;;
NameAndType	toString:(Lscala/Function10;)Ljava/lang/String;
Method	scala/Function10$class.toString:(Lscala/Function10;)Ljava/lang/String;
Asciz	curried;
Asciz	()Lscala/Function1;;
Asciz	(Lscala/Function10;)Lscala/Function1;;
NameAndType	curried:(Lscala/Function10;)Lscala/Function1;
Method	scala/Function10$class.curried:(Lscala/Function10;)Lscala/Function1;
Asciz	curry;
NameAndType	curry:(Lscala/Function10;)Lscala/Function1;
Method	scala/Function10$class.curry:(Lscala/Function10;)Lscala/Function1;
Asciz	Deprecated;
Asciz	tupled;
NameAndType	tupled:(Lscala/Function10;)Lscala/Function1;
Method	scala/Function10$class.tupled:(Lscala/Function10;)Lscala/Function1;
Asciz	<init>;
Asciz	()V;
Asciz	java/lang/Object;
class	java/lang/Object
NameAndType	"<init>":()V
Method	java/lang/Object."<init>":()V
Asciz	$init$;
Asciz	(Lscala/Function10;)V;
NameAndType	$init$:(Lscala/Function10;)V
Method	scala/Function10$class.$init$:(Lscala/Function10;)V
Asciz	Signature;
Asciz	ScalaSig;
Asciz	<T1:Ljava/lang/Object;T2:Ljava/lang/Object;T3:Ljava/lang/Object;T4:Ljava/lang/Object;T5:Ljava/lang/Object;T6:Ljava/lang/Object;T7:Ljava/lang/Object;T8:Ljava/lang/Object;T9:Ljava/lang/Object;T10:Ljava/lang/Object;R:Ljava/lang/Object;>Ljava/lang/Object;Lscala/Function10<TT1;TT2;TT3;TT4;TT5;TT6;TT7;TT8;TT9;TT10;TR;>;Lscala/ScalaObject;;
Asciz	Lscala/reflect/ScalaSignature;;
Asciz	bytes;
Asciz	3Q!!#2tiJ7\r$v]$n82a)1BeVtG/[7f)!B:dC27A\r]\tCe\n.aM2P\n%\tb5\t1B\r!A.8hq6bmL!E\r='.Z2u!52#$M%bsFM9w5\tA!\t\tQa)8di&|g.\rY9B\t1!\t#b3\tA+M\t5u\"AE\nq!!a(pi\"Lgn\t%yI!asCA!CDUeAa\n\tK!\t#b3\tAk\r\t-\"#\r!)R\"A-A!ECe!VYiC\tE)A\rQ3C1\t!\t\"A\tI\"A+8!\t125\tR1\t!mAqCDUsAa#\tu!\t#b3\tA+\rYaDC\t%)A\rI\"AE \n#!aC*dC2wJ6fGRDQA\raP5oSRtD##QI'S1z#'<;
Asciz	RuntimeVisibleAnnotations;
Asciz	scala/runtime/AbstractFunction10;
class	scala/runtime/AbstractFunction10
Asciz	scala/Function10;
class	scala/Function10
Asciz	scala/ScalaObject;
class	scala/ScalaObject

{
public java.lang.String toString();
  Signature: ()Ljava/lang/String;
  Code:
   Stack=1, Locals=1, Args_size=1
	aload_0
	invokestatic	Method scala/Function10$class.toString:(Lscala/Function10;)Ljava/lang/String;
	areturn
  Labels:

public scala.Function1 curried();
  Signature: ()Lscala/Function1;
  Code:
   Stack=1, Locals=1, Args_size=1
	aload_0
	invokestatic	Method scala/Function10$class.curried:(Lscala/Function10;)Lscala/Function1;
	areturn
  Labels:

public scala.Function1 curry();
  Signature: ()Lscala/Function1;
  Code:
   Stack=1, Locals=1, Args_size=1
	aload_0
	invokestatic	Method scala/Function10$class.curry:(Lscala/Function10;)Lscala/Function1;
	areturn
  Labels:
  Deprecated: true

public scala.Function1 tupled();
  Signature: ()Lscala/Function1;
  Code:
   Stack=1, Locals=1, Args_size=1
	aload_0
	invokestatic	Method scala/Function10$class.tupled:(Lscala/Function10;)Lscala/Function1;
	areturn
  Labels:

public scala.runtime.AbstractFunction10();
  Signature: ()V
  Code:
   Stack=1, Locals=1, Args_size=1
	aload_0
	invokespecial	Method java/lang/Object."<init>":()V
	aload_0
	invokestatic	Method scala/Function10$class.$init$:(Lscala/Function10;)V
	return
  Labels:
  Signature: length = 0x2
   00 19 

}

