Compiled from "AbstractFunction0.scala"
public abstract class scala.runtime.AbstractFunction0$mcZ$sp extends scala.runtime.AbstractFunction0 implements scala.Function0$mcZ$sp
  SourceFile: "AbstractFunction0.scala"
  Scala: length = 0x
   
  Signature: length = 0x2
   00 22 
  minor version: 0
  major version: 49
  Constant pool:
Asciz	SourceFile;
Asciz	AbstractFunction0.scala;
Asciz	apply;
Asciz	()Z;
Asciz	Code;
Asciz	LineNumberTable;
Asciz	scala/Function0$mcZ$sp$class;
class	scala/Function0$mcZ$sp$class
Asciz	(Lscala/Function0$mcZ$sp;)Z;
NameAndType	apply:(Lscala/Function0$mcZ$sp;)Z
Method	scala/Function0$mcZ$sp$class.apply:(Lscala/Function0$mcZ$sp;)Z
Asciz	()Ljava/lang/Object;;
Asciz	scala/Function0$mcZ$sp;
class	scala/Function0$mcZ$sp
NameAndType	apply:()Z
InterfaceMethod	scala/Function0$mcZ$sp.apply:()Z
Asciz	scala/runtime/BoxesRunTime;
class	scala/runtime/BoxesRunTime
Asciz	boxToBoolean;
Asciz	(Z)Ljava/lang/Boolean;;
NameAndType	boxToBoolean:(Z)Ljava/lang/Boolean;
Method	scala/runtime/BoxesRunTime.boxToBoolean:(Z)Ljava/lang/Boolean;
Asciz	<init>;
Asciz	()V;
Asciz	scala/runtime/AbstractFunction0;
class	scala/runtime/AbstractFunction0
NameAndType	"<init>":()V
Method	scala/runtime/AbstractFunction0."<init>":()V
Asciz	$init$;
Asciz	(Lscala/Function0$mcZ$sp;)V;
NameAndType	$init$:(Lscala/Function0$mcZ$sp;)V
Method	scala/Function0$mcZ$sp$class.$init$:(Lscala/Function0$mcZ$sp;)V
Asciz	Scala;
Asciz	Lscala/runtime/AbstractFunction0<Ljava/lang/Boolean;>;Lscala/Function0$mcZ$sp;;
Asciz	Signature;
Asciz	scala/runtime/AbstractFunction0$mcZ$sp;
class	scala/runtime/AbstractFunction0$mcZ$sp

{
public boolean apply();
  Signature: ()Z
  Code:
   Stack=1, Locals=1, Args_size=1
	aload_0
	invokestatic	Method scala/Function0$mcZ$sp$class.apply:(Lscala/Function0$mcZ$sp;)Z
	ireturn
  Labels:

public java.lang.Object apply();
  Signature: ()Ljava/lang/Object;
  Code:
   Stack=1, Locals=2, Args_size=1
	aload_0
	invokeinterface	InterfaceMethod scala/Function0$mcZ$sp.apply:()Z
	istore_1
	iload_1
	invokestatic	Method scala/runtime/BoxesRunTime.boxToBoolean:(Z)Ljava/lang/Boolean;
	areturn
  Labels:

public scala.runtime.AbstractFunction0$mcZ$sp();
  Signature: ()V
  Code:
   Stack=1, Locals=1, Args_size=1
	aload_0
	invokespecial	Method scala/runtime/AbstractFunction0."<init>":()V
	aload_0
	invokestatic	Method scala/Function0$mcZ$sp$class.$init$:(Lscala/Function0$mcZ$sp;)V
	return
  Labels:

}

