Compiled from "AbstractFunction0.scala"
public abstract class scala.runtime.AbstractFunction0$mcD$sp extends scala.runtime.AbstractFunction0 implements scala.Function0$mcD$sp
  SourceFile: "AbstractFunction0.scala"
  Scala: length = 0x
   
  Signature: length = 0x2
   00 22 
  minor version: 0
  major version: 49
  Constant pool:
Asciz	SourceFile;
Asciz	AbstractFunction0.scala;
Asciz	apply;
Asciz	()D;
Asciz	Code;
Asciz	LineNumberTable;
Asciz	scala/Function0$mcD$sp$class;
class	scala/Function0$mcD$sp$class
Asciz	(Lscala/Function0$mcD$sp;)D;
NameAndType	apply:(Lscala/Function0$mcD$sp;)D
Method	scala/Function0$mcD$sp$class.apply:(Lscala/Function0$mcD$sp;)D
Asciz	()Ljava/lang/Object;;
Asciz	scala/Function0$mcD$sp;
class	scala/Function0$mcD$sp
NameAndType	apply:()D
InterfaceMethod	scala/Function0$mcD$sp.apply:()D
Asciz	scala/runtime/BoxesRunTime;
class	scala/runtime/BoxesRunTime
Asciz	boxToDouble;
Asciz	(D)Ljava/lang/Double;;
NameAndType	boxToDouble:(D)Ljava/lang/Double;
Method	scala/runtime/BoxesRunTime.boxToDouble:(D)Ljava/lang/Double;
Asciz	<init>;
Asciz	()V;
Asciz	scala/runtime/AbstractFunction0;
class	scala/runtime/AbstractFunction0
NameAndType	"<init>":()V
Method	scala/runtime/AbstractFunction0."<init>":()V
Asciz	$init$;
Asciz	(Lscala/Function0$mcD$sp;)V;
NameAndType	$init$:(Lscala/Function0$mcD$sp;)V
Method	scala/Function0$mcD$sp$class.$init$:(Lscala/Function0$mcD$sp;)V
Asciz	Scala;
Asciz	Lscala/runtime/AbstractFunction0<Ljava/lang/Double;>;Lscala/Function0$mcD$sp;;
Asciz	Signature;
Asciz	scala/runtime/AbstractFunction0$mcD$sp;
class	scala/runtime/AbstractFunction0$mcD$sp

{
public double apply();
  Signature: ()D
  Code:
   Stack=2, Locals=1, Args_size=1
	aload_0
	invokestatic	Method scala/Function0$mcD$sp$class.apply:(Lscala/Function0$mcD$sp;)D
	dreturn
  Labels:

public java.lang.Object apply();
  Signature: ()Ljava/lang/Object;
  Code:
   Stack=2, Locals=3, Args_size=1
	aload_0
	invokeinterface	InterfaceMethod scala/Function0$mcD$sp.apply:()D
	dstore_1
	dload_1
	invokestatic	Method scala/runtime/BoxesRunTime.boxToDouble:(D)Ljava/lang/Double;
	areturn
  Labels:

public scala.runtime.AbstractFunction0$mcD$sp();
  Signature: ()V
  Code:
   Stack=1, Locals=1, Args_size=1
	aload_0
	invokespecial	Method scala/runtime/AbstractFunction0."<init>":()V
	aload_0
	invokestatic	Method scala/Function0$mcD$sp$class.$init$:(Lscala/Function0$mcD$sp;)V
	return
  Labels:

}

