Compiled from "AbstractFunction14.scala"
public abstract class scala.runtime.AbstractFunction14 extends java.lang.Object implements scala.Function14,scala.ScalaObject
  SourceFile: "AbstractFunction14.scala"
  ScalaSig: length = 0x3
   05 00 00 
  Signature: length = 0x2
   00 24 
  RuntimeVisibleAnnotations: length = 0xB
   00 01 00 25 00 01 00 26 73 00 27 
  minor version: 0
  major version: 49
  Constant pool:
Asciz	SourceFile;
Asciz	AbstractFunction14.scala;
Asciz	toString;
Asciz	()Ljava/lang/String;;
Asciz	Code;
Asciz	LineNumberTable;
Asciz	scala/Function14$class;
class	scala/Function14$class
Asciz	(Lscala/Function14;)Ljava/lang/String;;
NameAndType	toString:(Lscala/Function14;)Ljava/lang/String;
Method	scala/Function14$class.toString:(Lscala/Function14;)Ljava/lang/String;
Asciz	curried;
Asciz	()Lscala/Function1;;
Asciz	(Lscala/Function14;)Lscala/Function1;;
NameAndType	curried:(Lscala/Function14;)Lscala/Function1;
Method	scala/Function14$class.curried:(Lscala/Function14;)Lscala/Function1;
Asciz	curry;
NameAndType	curry:(Lscala/Function14;)Lscala/Function1;
Method	scala/Function14$class.curry:(Lscala/Function14;)Lscala/Function1;
Asciz	Deprecated;
Asciz	tupled;
NameAndType	tupled:(Lscala/Function14;)Lscala/Function1;
Method	scala/Function14$class.tupled:(Lscala/Function14;)Lscala/Function1;
Asciz	<init>;
Asciz	()V;
Asciz	java/lang/Object;
class	java/lang/Object
NameAndType	"<init>":()V
Method	java/lang/Object."<init>":()V
Asciz	$init$;
Asciz	(Lscala/Function14;)V;
NameAndType	$init$:(Lscala/Function14;)V
Method	scala/Function14$class.$init$:(Lscala/Function14;)V
Asciz	Signature;
Asciz	ScalaSig;
Asciz	<T1:Ljava/lang/Object;T2:Ljava/lang/Object;T3:Ljava/lang/Object;T4:Ljava/lang/Object;T5:Ljava/lang/Object;T6:Ljava/lang/Object;T7:Ljava/lang/Object;T8:Ljava/lang/Object;T9:Ljava/lang/Object;T10:Ljava/lang/Object;T11:Ljava/lang/Object;T12:Ljava/lang/Object;T13:Ljava/lang/Object;T14:Ljava/lang/Object;R:Ljava/lang/Object;>Ljava/lang/Object;Lscala/Function14<TT1;TT2;TT3;TT4;TT5;TT6;TT7;TT8;TT9;TT10;TT11;TT12;TT13;TT14;TR;>;Lscala/ScalaObject;;
Asciz	Lscala/reflect/ScalaSignature;;
Asciz	bytes;
Asciz	I3Q!!#2tiJ7\r$v]$n82i)1BeVtG/[7f)!B:dC27A]\tCe\n.aM2P C\"BAB!bD)A\"DYtwMCQM^1\nAY!AB(cUGE\t'U3EJ-_I*h B\tkB)!BR;oGRLwN\5!\t1raA!ECe!ViiC\n\taBAAO_RDN\4IqBA\r\te.\t-\"B\t#\r!)J\"AA!ECe!VY9C\tE)A\rQ#C+\t!Y\"A\tI\"A+6!\t1R/\tR1\t!faACDUoAac\r\ti!\t#b3\tA\t-Y\"b#\r!)f\"AFiA!ECe1V1!\t1B>\tR1\r!'\r\t-}\"#\r!)FCC\t!\"A\tI\"a+2gAa#\t\r!\t#b3\tA+\rYAEC%\t%)A\rI\"AE&\n1#!aC*dC2wJ6fGRDQA=aP5oSRtD#)#EQI'S1z#'<}#u)D;
Asciz	RuntimeVisibleAnnotations;
Asciz	scala/runtime/AbstractFunction14;
class	scala/runtime/AbstractFunction14
Asciz	scala/Function14;
class	scala/Function14
Asciz	scala/ScalaObject;
class	scala/ScalaObject

{
public java.lang.String toString();
  Signature: ()Ljava/lang/String;
  Code:
   Stack=1, Locals=1, Args_size=1
	aload_0
	invokestatic	Method scala/Function14$class.toString:(Lscala/Function14;)Ljava/lang/String;
	areturn
  Labels:

public scala.Function1 curried();
  Signature: ()Lscala/Function1;
  Code:
   Stack=1, Locals=1, Args_size=1
	aload_0
	invokestatic	Method scala/Function14$class.curried:(Lscala/Function14;)Lscala/Function1;
	areturn
  Labels:

public scala.Function1 curry();
  Signature: ()Lscala/Function1;
  Code:
   Stack=1, Locals=1, Args_size=1
	aload_0
	invokestatic	Method scala/Function14$class.curry:(Lscala/Function14;)Lscala/Function1;
	areturn
  Labels:
  Deprecated: true

public scala.Function1 tupled();
  Signature: ()Lscala/Function1;
  Code:
   Stack=1, Locals=1, Args_size=1
	aload_0
	invokestatic	Method scala/Function14$class.tupled:(Lscala/Function14;)Lscala/Function1;
	areturn
  Labels:

public scala.runtime.AbstractFunction14();
  Signature: ()V
  Code:
   Stack=1, Locals=1, Args_size=1
	aload_0
	invokespecial	Method java/lang/Object."<init>":()V
	aload_0
	invokestatic	Method scala/Function14$class.$init$:(Lscala/Function14;)V
	return
  Labels:
  Signature: length = 0x2
   00 19 

}

