Compiled from "AbstractFunction0.scala"
public abstract class scala.runtime.AbstractFunction0$mcB$sp extends scala.runtime.AbstractFunction0 implements scala.Function0$mcB$sp
  SourceFile: "AbstractFunction0.scala"
  Scala: length = 0x
   
  Signature: length = 0x2
   00 22 
  minor version: 0
  major version: 49
  Constant pool:
Asciz	SourceFile;
Asciz	AbstractFunction0.scala;
Asciz	apply;
Asciz	()B;
Asciz	Code;
Asciz	LineNumberTable;
Asciz	scala/Function0$mcB$sp$class;
class	scala/Function0$mcB$sp$class
Asciz	(Lscala/Function0$mcB$sp;)B;
NameAndType	apply:(Lscala/Function0$mcB$sp;)B
Method	scala/Function0$mcB$sp$class.apply:(Lscala/Function0$mcB$sp;)B
Asciz	()Ljava/lang/Object;;
Asciz	scala/Function0$mcB$sp;
class	scala/Function0$mcB$sp
NameAndType	apply:()B
InterfaceMethod	scala/Function0$mcB$sp.apply:()B
Asciz	scala/runtime/BoxesRunTime;
class	scala/runtime/BoxesRunTime
Asciz	boxToByte;
Asciz	(B)Ljava/lang/Byte;;
NameAndType	boxToByte:(B)Ljava/lang/Byte;
Method	scala/runtime/BoxesRunTime.boxToByte:(B)Ljava/lang/Byte;
Asciz	<init>;
Asciz	()V;
Asciz	scala/runtime/AbstractFunction0;
class	scala/runtime/AbstractFunction0
NameAndType	"<init>":()V
Method	scala/runtime/AbstractFunction0."<init>":()V
Asciz	$init$;
Asciz	(Lscala/Function0$mcB$sp;)V;
NameAndType	$init$:(Lscala/Function0$mcB$sp;)V
Method	scala/Function0$mcB$sp$class.$init$:(Lscala/Function0$mcB$sp;)V
Asciz	Scala;
Asciz	Lscala/runtime/AbstractFunction0<Ljava/lang/Byte;>;Lscala/Function0$mcB$sp;;
Asciz	Signature;
Asciz	scala/runtime/AbstractFunction0$mcB$sp;
class	scala/runtime/AbstractFunction0$mcB$sp

{
public byte apply();
  Signature: ()B
  Code:
   Stack=1, Locals=1, Args_size=1
	aload_0
	invokestatic	Method scala/Function0$mcB$sp$class.apply:(Lscala/Function0$mcB$sp;)B
	ireturn
  Labels:

public java.lang.Object apply();
  Signature: ()Ljava/lang/Object;
  Code:
   Stack=1, Locals=2, Args_size=1
	aload_0
	invokeinterface	InterfaceMethod scala/Function0$mcB$sp.apply:()B
	istore_1
	iload_1
	invokestatic	Method scala/runtime/BoxesRunTime.boxToByte:(B)Ljava/lang/Byte;
	areturn
  Labels:

public scala.runtime.AbstractFunction0$mcB$sp();
  Signature: ()V
  Code:
   Stack=1, Locals=1, Args_size=1
	aload_0
	invokespecial	Method scala/runtime/AbstractFunction0."<init>":()V
	aload_0
	invokestatic	Method scala/Function0$mcB$sp$class.$init$:(Lscala/Function0$mcB$sp;)V
	return
  Labels:

}

