Compiled from "AbstractFunction0.scala"
public abstract class scala.runtime.AbstractFunction8 extends java.lang.Object implements scala.Function8,scala.ScalaObject
  SourceFile: "AbstractFunction0.scala"
  Signature: length = 0x2
   00 23 
  ScalaSig: length = 0x189
   05 00 40 06 05 01 02 FFFFFF81 00 07 02 11 41 62 73 74
   72 61 63 74 46 75 6E 63 74 69 6F 6E 38 0A 02 03
   04 01 07 72 75 6E 74 69 6D 65 0A 01 05 01 05 73
   63 61 6C 61 03 00 15 0A 08 17 21 24 27 2A 2D 30
   33 36 13 04 00 09 11 38 10 02 0A 0F 0D 01 0B 0A
   02 0C 0D 01 04 6C 61 6E 67 0A 01 0E 01 04 6A 61
   76 61 09 02 10 0B 02 06 4F 62 6A 65 63 74 10 0B
   12 13 15 20 23 26 29 2C 2F 32 35 0D 01 04 09 02
   14 04 02 09 46 75 6E 63 74 69 6F 6E 38 10 02 16
   17 0C 00 04 08 18 00 FFFFFF84 FFFFFF80 FFFFFF88 FFFFFFC2 00 19 02 02 54
   31 11 02 1A 1D 10 02 12 1B 09 02 1C 04 02 07 4E
   6F 74 68 69 6E 67 10 02 12 1E 09 02 1F 04 02 03
   41 6E 79 10 02 16 21 04 08 22 00 FFFFFF84 FFFFFF80 FFFFFF88 FFFFFFC2 00
   19 02 02 54 32 10 02 16 24 04 08 25 00 FFFFFF84 FFFFFF80 FFFFFF88
   FFFFFFC2 00 19 02 02 54 33 10 02 16 27 04 08 28 00 FFFFFF84
   FFFFFF80 FFFFFF88 FFFFFFC2 00 19 02 02 54 34 10 02 16 2A 04 08 2B
   00 FFFFFF84 FFFFFF80 FFFFFF88 FFFFFFC2 00 19 02 02 54 35 10 02 16 2D 04
   08 2E 00 FFFFFF84 FFFFFF80 FFFFFF88 FFFFFFC2 00 19 02 02 54 36 10 02 16
   30 04 08 31 00 FFFFFF84 FFFFFF80 FFFFFF88 FFFFFFC2 00 19 02 02 54 37 10
   02 16 33 04 08 34 00 FFFFFF84 FFFFFF80 FFFFFF88 FFFFFFC2 00 19 02 02 54
   38 10 02 16 36 04 08 37 00 FFFFFF84 FFFFFF80 FFFFFF84 FFFFFFC2 00 19 02
   01 52 10 02 12 39 09 02 3A 04 02 0B 53 63 61 6C
   61 4F 62 6A 65 63 74 08 05 3C 00 FFFFFF84 00 3D 01 06
   3C 69 6E 69 74 3E 14 01 3E 10 0B 3F 00 15 20 23
   26 29 2C 2F 32 35 0D 01 02 
  minor version: 0
  major version: 49
  Constant pool:
Asciz	SourceFile;
Asciz	AbstractFunction0.scala;
Asciz	<init>;
Asciz	()V;
Asciz	Code;
Asciz	LineNumberTable;
Asciz	java/lang/Object;
class	java/lang/Object
NameAndType	"<init>":()V
Method	java/lang/Object."<init>":()V
Asciz	scala/Function8$class;
class	scala/Function8$class
Asciz	$init$;
Asciz	(Lscala/Function8;)V;
NameAndType	$init$:(Lscala/Function8;)V
Method	scala/Function8$class.$init$:(Lscala/Function8;)V
Asciz	Signature;
Asciz	tupled;
Asciz	()Lscala/Function1;;
Asciz	(Lscala/Function8;)Lscala/Function1;;
NameAndType	tupled:(Lscala/Function8;)Lscala/Function1;
Method	scala/Function8$class.tupled:(Lscala/Function8;)Lscala/Function1;
Asciz	curry;
NameAndType	curry:(Lscala/Function8;)Lscala/Function1;
Method	scala/Function8$class.curry:(Lscala/Function8;)Lscala/Function1;
Asciz	Deprecated;
Asciz	curried;
NameAndType	curried:(Lscala/Function8;)Lscala/Function1;
Method	scala/Function8$class.curried:(Lscala/Function8;)Lscala/Function1;
Asciz	toString;
Asciz	()Ljava/lang/String;;
Asciz	(Lscala/Function8;)Ljava/lang/String;;
NameAndType	toString:(Lscala/Function8;)Ljava/lang/String;
Method	scala/Function8$class.toString:(Lscala/Function8;)Ljava/lang/String;
Asciz	<T1:Ljava/lang/Object;T2:Ljava/lang/Object;T3:Ljava/lang/Object;T4:Ljava/lang/Object;T5:Ljava/lang/Object;T6:Ljava/lang/Object;T7:Ljava/lang/Object;T8:Ljava/lang/Object;R:Ljava/lang/Object;>Ljava/lang/Object;Lscala/Function8<TT1;TT2;TT3;TT4;TT5;TT6;TT7;TT8;TR;>;Lscala/ScalaObject;;
Asciz	ScalaSig;
Asciz	scala/runtime/AbstractFunction8;
class	scala/runtime/AbstractFunction8
Asciz	scala/Function8;
class	scala/Function8
Asciz	scala/ScalaObject;
class	scala/ScalaObject

{
public scala.runtime.AbstractFunction8();
  Signature: ()V
  Code:
   Stack=1, Locals=1, Args_size=1
	aload_0
	invokespecial	Method java/lang/Object."<init>":()V
	aload_0
	invokestatic	Method scala/Function8$class.$init$:(Lscala/Function8;)V
	return
  Labels:
  Signature: length = 0x2
   00 04 

public scala.Function1 tupled();
  Signature: ()Lscala/Function1;
  Code:
   Stack=1, Locals=1, Args_size=1
	aload_0
	invokestatic	Method scala/Function8$class.tupled:(Lscala/Function8;)Lscala/Function1;
	areturn
  Labels:

public scala.Function1 curry();
  Signature: ()Lscala/Function1;
  Code:
   Stack=1, Locals=1, Args_size=1
	aload_0
	invokestatic	Method scala/Function8$class.curry:(Lscala/Function8;)Lscala/Function1;
	areturn
  Labels:
  Deprecated: true

public scala.Function1 curried();
  Signature: ()Lscala/Function1;
  Code:
   Stack=1, Locals=1, Args_size=1
	aload_0
	invokestatic	Method scala/Function8$class.curried:(Lscala/Function8;)Lscala/Function1;
	areturn
  Labels:

public java.lang.String toString();
  Signature: ()Ljava/lang/String;
  Code:
   Stack=1, Locals=1, Args_size=1
	aload_0
	invokestatic	Method scala/Function8$class.toString:(Lscala/Function8;)Ljava/lang/String;
	areturn
  Labels:

}

