Compiled from "AbstractFunction0.scala"
public abstract class scala.runtime.AbstractFunction6 extends java.lang.Object implements scala.Function6,scala.ScalaObject
  SourceFile: "AbstractFunction0.scala"
  Signature: length = 0x2
   00 1F 
  ScalaSig: length = 0x15F
   05 00 3A 06 05 01 02 FFFFFF81 00 07 02 11 41 62 73 74
   72 61 63 74 46 75 6E 63 74 69 6F 6E 36 0A 02 03
   04 01 07 72 75 6E 74 69 6D 65 0A 01 05 01 05 73
   63 61 6C 61 03 00 15 08 08 17 21 24 27 2A 2D 30
   13 04 00 09 11 32 10 02 0A 0F 0D 01 0B 0A 02 0C
   0D 01 04 6C 61 6E 67 0A 01 0E 01 04 6A 61 76 61
   09 02 10 0B 02 06 4F 62 6A 65 63 74 10 09 12 13
   15 20 23 26 29 2C 2F 0D 01 04 09 02 14 04 02 09
   46 75 6E 63 74 69 6F 6E 36 10 02 16 17 0C 00 04
   08 18 00 FFFFFF84 FFFFFF80 FFFFFF88 FFFFFFC2 00 19 02 02 54 31 11 02 1A
   1D 10 02 12 1B 09 02 1C 04 02 07 4E 6F 74 68 69
   6E 67 10 02 12 1E 09 02 1F 04 02 03 41 6E 79 10
   02 16 21 04 08 22 00 FFFFFF84 FFFFFF80 FFFFFF88 FFFFFFC2 00 19 02 02 54
   32 10 02 16 24 04 08 25 00 FFFFFF84 FFFFFF80 FFFFFF88 FFFFFFC2 00 19 02
   02 54 33 10 02 16 27 04 08 28 00 FFFFFF84 FFFFFF80 FFFFFF88 FFFFFFC2 00
   19 02 02 54 34 10 02 16 2A 04 08 2B 00 FFFFFF84 FFFFFF80 FFFFFF88
   FFFFFFC2 00 19 02 02 54 35 10 02 16 2D 04 08 2E 00 FFFFFF84
   FFFFFF80 FFFFFF88 FFFFFFC2 00 19 02 02 54 36 10 02 16 30 04 08 31
   00 FFFFFF84 FFFFFF80 FFFFFF84 FFFFFFC2 00 19 02 01 52 10 02 12 33 09 02
   34 04 02 0B 53 63 61 6C 61 4F 62 6A 65 63 74 08
   05 36 00 FFFFFF84 00 37 01 06 3C 69 6E 69 74 3E 14 01
   38 10 09 39 00 15 20 23 26 29 2C 2F 0D 01 02 
  minor version: 0
  major version: 49
  Constant pool:
Asciz	SourceFile;
Asciz	AbstractFunction0.scala;
Asciz	<init>;
Asciz	()V;
Asciz	Code;
Asciz	LineNumberTable;
Asciz	java/lang/Object;
class	java/lang/Object
NameAndType	"<init>":()V
Method	java/lang/Object."<init>":()V
Asciz	scala/Function6$class;
class	scala/Function6$class
Asciz	$init$;
Asciz	(Lscala/Function6;)V;
NameAndType	$init$:(Lscala/Function6;)V
Method	scala/Function6$class.$init$:(Lscala/Function6;)V
Asciz	Signature;
Asciz	tuple;
Asciz	()Lscala/Function1;;
Asciz	(Lscala/Function6;)Lscala/Function1;;
NameAndType	tuple:(Lscala/Function6;)Lscala/Function1;
Method	scala/Function6$class.tuple:(Lscala/Function6;)Lscala/Function1;
Asciz	curry;
NameAndType	curry:(Lscala/Function6;)Lscala/Function1;
Method	scala/Function6$class.curry:(Lscala/Function6;)Lscala/Function1;
Asciz	toString;
Asciz	()Ljava/lang/String;;
Asciz	(Lscala/Function6;)Ljava/lang/String;;
NameAndType	toString:(Lscala/Function6;)Ljava/lang/String;
Method	scala/Function6$class.toString:(Lscala/Function6;)Ljava/lang/String;
Asciz	<T1:Ljava/lang/Object;T2:Ljava/lang/Object;T3:Ljava/lang/Object;T4:Ljava/lang/Object;T5:Ljava/lang/Object;T6:Ljava/lang/Object;R:Ljava/lang/Object;>Ljava/lang/Object;Lscala/Function6<TT1;TT2;TT3;TT4;TT5;TT6;TR;>;Lscala/ScalaObject;;
Asciz	ScalaSig;
Asciz	scala/runtime/AbstractFunction6;
class	scala/runtime/AbstractFunction6
Asciz	scala/Function6;
class	scala/Function6
Asciz	scala/ScalaObject;
class	scala/ScalaObject

{
public scala.runtime.AbstractFunction6();
  Signature: ()V
  Code:
   Stack=1, Locals=1, Args_size=1
	aload_0
	invokespecial	Method java/lang/Object."<init>":()V
	aload_0
	invokestatic	Method scala/Function6$class.$init$:(Lscala/Function6;)V
	return
  Labels:
  Signature: length = 0x2
   00 04 

public scala.Function1 tuple();
  Signature: ()Lscala/Function1;
  Code:
   Stack=1, Locals=1, Args_size=1
	aload_0
	invokestatic	Method scala/Function6$class.tuple:(Lscala/Function6;)Lscala/Function1;
	areturn
  Labels:

public scala.Function1 curry();
  Signature: ()Lscala/Function1;
  Code:
   Stack=1, Locals=1, Args_size=1
	aload_0
	invokestatic	Method scala/Function6$class.curry:(Lscala/Function6;)Lscala/Function1;
	areturn
  Labels:

public java.lang.String toString();
  Signature: ()Ljava/lang/String;
  Code:
   Stack=1, Locals=1, Args_size=1
	aload_0
	invokestatic	Method scala/Function6$class.toString:(Lscala/Function6;)Ljava/lang/String;
	areturn
  Labels:

}

