Compiled from "AbstractFunction21.scala"
public abstract class scala.runtime.AbstractFunction21 extends java.lang.Object implements scala.Function21,scala.ScalaObject
  SourceFile: "AbstractFunction21.scala"
  ScalaSig: length = 0x3
   05 00 00 
  Signature: length = 0x2
   00 24 
  RuntimeVisibleAnnotations: length = 0xB
   00 01 00 25 00 01 00 26 73 00 27 
  minor version: 0
  major version: 49
  Constant pool:
Asciz	SourceFile;
Asciz	AbstractFunction21.scala;
Asciz	toString;
Asciz	()Ljava/lang/String;;
Asciz	Code;
Asciz	LineNumberTable;
Asciz	scala/Function21$class;
class	scala/Function21$class
Asciz	(Lscala/Function21;)Ljava/lang/String;;
NameAndType	toString:(Lscala/Function21;)Ljava/lang/String;
Method	scala/Function21$class.toString:(Lscala/Function21;)Ljava/lang/String;
Asciz	curried;
Asciz	()Lscala/Function1;;
Asciz	(Lscala/Function21;)Lscala/Function1;;
NameAndType	curried:(Lscala/Function21;)Lscala/Function1;
Method	scala/Function21$class.curried:(Lscala/Function21;)Lscala/Function1;
Asciz	curry;
NameAndType	curry:(Lscala/Function21;)Lscala/Function1;
Method	scala/Function21$class.curry:(Lscala/Function21;)Lscala/Function1;
Asciz	Deprecated;
Asciz	tupled;
NameAndType	tupled:(Lscala/Function21;)Lscala/Function1;
Method	scala/Function21$class.tupled:(Lscala/Function21;)Lscala/Function1;
Asciz	<init>;
Asciz	()V;
Asciz	java/lang/Object;
class	java/lang/Object
NameAndType	"<init>":()V
Method	java/lang/Object."<init>":()V
Asciz	$init$;
Asciz	(Lscala/Function21;)V;
NameAndType	$init$:(Lscala/Function21;)V
Method	scala/Function21$class.$init$:(Lscala/Function21;)V
Asciz	Signature;
Asciz	ScalaSig;
Asciz	<T1:Ljava/lang/Object;T2:Ljava/lang/Object;T3:Ljava/lang/Object;T4:Ljava/lang/Object;T5:Ljava/lang/Object;T6:Ljava/lang/Object;T7:Ljava/lang/Object;T8:Ljava/lang/Object;T9:Ljava/lang/Object;T10:Ljava/lang/Object;T11:Ljava/lang/Object;T12:Ljava/lang/Object;T13:Ljava/lang/Object;T14:Ljava/lang/Object;T15:Ljava/lang/Object;T16:Ljava/lang/Object;T17:Ljava/lang/Object;T18:Ljava/lang/Object;T19:Ljava/lang/Object;T20:Ljava/lang/Object;T21:Ljava/lang/Object;R:Ljava/lang/Object;>Ljava/lang/Object;Lscala/Function21<TT1;TT2;TT3;TT4;TT5;TT6;TT7;TT8;TT9;TT10;TT11;TT12;TT13;TT14;TT15;TT16;TT17;TT18;TT19;TT20;TT21;TR;>;Lscala/ScalaObject;;
Asciz	Lscala/reflect/ScalaSignature;;
Asciz	bytes;
Asciz	4Q!!#2tiJ7\r$v]$n83c)1BeVtG/[7f)!B:dC27A]\tCe\n.aM2P C\"[e*+X5vBA?B!bD)A\"DYtwMCQM^1\nAY!AB(cUG\r'U3EJ-_I*h B\tSU\nU*W3rkB)!BR;oGRLwN2!\t1raA!ECe!ViiC\n\taBAAO_RDN\4IqBA\r\te.\t-\"B\t#\r!)J\"AA!ECe!VY9C\tE)A\rQ#C+\t!Y\"A\tI\"A+6!\t1R/\tR1\t!faACDUoAac\r\ti!\t#b3\tA\t-Y\"b#\r!)f\"AFiA!ECe1V1!\t1B>\tR1\r!'\r\t-}\"#\r!)FCC\t!\"A\tI\"a+2gAa#\t\r!\t#b3\tA+\rYAEC%\tE)A\rQTAA\nCDAUcY\"A(=A!ECe1V8!\t1S\tR1\r!\t-Q#\"#\r!)FJCX\t!A\"A\tI\"a+3aAaC\t7!\t#b3\tAKMYiF0\t%)A\rI\"A1\n$!aC*dC2wJ6fGRDQaaP5oSRtD#A31QI'S1z#'<}#uIS'Q'ZKF,D;
Asciz	RuntimeVisibleAnnotations;
Asciz	scala/runtime/AbstractFunction21;
class	scala/runtime/AbstractFunction21
Asciz	scala/Function21;
class	scala/Function21
Asciz	scala/ScalaObject;
class	scala/ScalaObject

{
public java.lang.String toString();
  Signature: ()Ljava/lang/String;
  Code:
   Stack=1, Locals=1, Args_size=1
	aload_0
	invokestatic	Method scala/Function21$class.toString:(Lscala/Function21;)Ljava/lang/String;
	areturn
  Labels:

public scala.Function1 curried();
  Signature: ()Lscala/Function1;
  Code:
   Stack=1, Locals=1, Args_size=1
	aload_0
	invokestatic	Method scala/Function21$class.curried:(Lscala/Function21;)Lscala/Function1;
	areturn
  Labels:

public scala.Function1 curry();
  Signature: ()Lscala/Function1;
  Code:
   Stack=1, Locals=1, Args_size=1
	aload_0
	invokestatic	Method scala/Function21$class.curry:(Lscala/Function21;)Lscala/Function1;
	areturn
  Labels:
  Deprecated: true

public scala.Function1 tupled();
  Signature: ()Lscala/Function1;
  Code:
   Stack=1, Locals=1, Args_size=1
	aload_0
	invokestatic	Method scala/Function21$class.tupled:(Lscala/Function21;)Lscala/Function1;
	areturn
  Labels:

public scala.runtime.AbstractFunction21();
  Signature: ()V
  Code:
   Stack=1, Locals=1, Args_size=1
	aload_0
	invokespecial	Method java/lang/Object."<init>":()V
	aload_0
	invokestatic	Method scala/Function21$class.$init$:(Lscala/Function21;)V
	return
  Labels:
  Signature: length = 0x2
   00 19 

}

