Compiled from "AbstractFunction20.scala"
public abstract class scala.runtime.AbstractFunction20 extends java.lang.Object implements scala.Function20,scala.ScalaObject
  SourceFile: "AbstractFunction20.scala"
  ScalaSig: length = 0x3
   05 00 00 
  Signature: length = 0x2
   00 24 
  RuntimeVisibleAnnotations: length = 0xB
   00 01 00 25 00 01 00 26 73 00 27 
  minor version: 0
  major version: 49
  Constant pool:
Asciz	SourceFile;
Asciz	AbstractFunction20.scala;
Asciz	toString;
Asciz	()Ljava/lang/String;;
Asciz	Code;
Asciz	LineNumberTable;
Asciz	scala/Function20$class;
class	scala/Function20$class
Asciz	(Lscala/Function20;)Ljava/lang/String;;
NameAndType	toString:(Lscala/Function20;)Ljava/lang/String;
Method	scala/Function20$class.toString:(Lscala/Function20;)Ljava/lang/String;
Asciz	curried;
Asciz	()Lscala/Function1;;
Asciz	(Lscala/Function20;)Lscala/Function1;;
NameAndType	curried:(Lscala/Function20;)Lscala/Function1;
Method	scala/Function20$class.curried:(Lscala/Function20;)Lscala/Function1;
Asciz	curry;
NameAndType	curry:(Lscala/Function20;)Lscala/Function1;
Method	scala/Function20$class.curry:(Lscala/Function20;)Lscala/Function1;
Asciz	Deprecated;
Asciz	tupled;
NameAndType	tupled:(Lscala/Function20;)Lscala/Function1;
Method	scala/Function20$class.tupled:(Lscala/Function20;)Lscala/Function1;
Asciz	<init>;
Asciz	()V;
Asciz	java/lang/Object;
class	java/lang/Object
NameAndType	"<init>":()V
Method	java/lang/Object."<init>":()V
Asciz	$init$;
Asciz	(Lscala/Function20;)V;
NameAndType	$init$:(Lscala/Function20;)V
Method	scala/Function20$class.$init$:(Lscala/Function20;)V
Asciz	Signature;
Asciz	ScalaSig;
Asciz	<T1:Ljava/lang/Object;T2:Ljava/lang/Object;T3:Ljava/lang/Object;T4:Ljava/lang/Object;T5:Ljava/lang/Object;T6:Ljava/lang/Object;T7:Ljava/lang/Object;T8:Ljava/lang/Object;T9:Ljava/lang/Object;T10:Ljava/lang/Object;T11:Ljava/lang/Object;T12:Ljava/lang/Object;T13:Ljava/lang/Object;T14:Ljava/lang/Object;T15:Ljava/lang/Object;T16:Ljava/lang/Object;T17:Ljava/lang/Object;T18:Ljava/lang/Object;T19:Ljava/lang/Object;T20:Ljava/lang/Object;R:Ljava/lang/Object;>Ljava/lang/Object;Lscala/Function20<TT1;TT2;TT3;TT4;TT5;TT6;TT7;TT8;TT9;TT10;TT11;TT12;TT13;TT14;TT15;TT16;TT17;TT18;TT19;TT20;TR;>;Lscala/ScalaObject;;
Asciz	Lscala/reflect/ScalaSignature;;
Asciz	bytes;
Asciz	4Q!!#2tiJ7\r$v]$n83a)1BeVtG/[7f)!B:dC27A]\tCe\n.aM2P C\"[e*+X5N!!C\t]!\tQq\"D\taQ\"mC:<'\"\t)g/Y!-aa2kK$c\n+c%0eUB4HP!E*kk,Z!B)1UO\2uS>t'\r\t-]a\tR1\t!';A!cG9qAT8uQ&tw\r=%q:LC\"\t!\"A\tI\"A+3!\t1B&\tR1\t!6OACDUiAaC\tW!\t#b3\tA+\t-5\"B#\r!)Z\"AEA!ECe!VYD\tE)A\rQCC7\t!9\"A\tI\"A+:!\t1;\tR1\r!\r\t-q\"\"#\r!)F\nC@\t!\"A\tI\"a+2eAaC\t!\t#b3\tA+MY)E$\tE)A\rQDA\nCDAUcU\"AF&1A!ECe1V7!\t1b\nP\tR1\r!g\t-E#B#\r!)FBCU\t!)\"A\tI\"a+2sAac\t1!\t#b3\tAK\rYQFC.\t%)A\rI\"AE/\ny#!aC*dC2wJ6fGRDQaP5oSRtD#2/\rQI'S1z#'<}#uIS'Q'ZKV\";
Asciz	RuntimeVisibleAnnotations;
Asciz	scala/runtime/AbstractFunction20;
class	scala/runtime/AbstractFunction20
Asciz	scala/Function20;
class	scala/Function20
Asciz	scala/ScalaObject;
class	scala/ScalaObject

{
public java.lang.String toString();
  Signature: ()Ljava/lang/String;
  Code:
   Stack=1, Locals=1, Args_size=1
	aload_0
	invokestatic	Method scala/Function20$class.toString:(Lscala/Function20;)Ljava/lang/String;
	areturn
  Labels:

public scala.Function1 curried();
  Signature: ()Lscala/Function1;
  Code:
   Stack=1, Locals=1, Args_size=1
	aload_0
	invokestatic	Method scala/Function20$class.curried:(Lscala/Function20;)Lscala/Function1;
	areturn
  Labels:

public scala.Function1 curry();
  Signature: ()Lscala/Function1;
  Code:
   Stack=1, Locals=1, Args_size=1
	aload_0
	invokestatic	Method scala/Function20$class.curry:(Lscala/Function20;)Lscala/Function1;
	areturn
  Labels:
  Deprecated: true

public scala.Function1 tupled();
  Signature: ()Lscala/Function1;
  Code:
   Stack=1, Locals=1, Args_size=1
	aload_0
	invokestatic	Method scala/Function20$class.tupled:(Lscala/Function20;)Lscala/Function1;
	areturn
  Labels:

public scala.runtime.AbstractFunction20();
  Signature: ()V
  Code:
   Stack=1, Locals=1, Args_size=1
	aload_0
	invokespecial	Method java/lang/Object."<init>":()V
	aload_0
	invokestatic	Method scala/Function20$class.$init$:(Lscala/Function20;)V
	return
  Labels:
  Signature: length = 0x2
   00 19 

}

