Compiled from "AbstractFunction0.scala"
public abstract class scala.runtime.AbstractFunction13 extends java.lang.Object implements scala.Function13,scala.ScalaObject
  SourceFile: "AbstractFunction0.scala"
  ScalaSig: length = 0x3
   05 00 00 
  Signature: length = 0x2
   00 24 
  RuntimeVisibleAnnotations: length = 0xB
   00 01 00 25 00 01 00 26 73 00 27 
  minor version: 0
  major version: 49
  Constant pool:
Asciz	SourceFile;
Asciz	AbstractFunction0.scala;
Asciz	toString;
Asciz	()Ljava/lang/String;;
Asciz	Code;
Asciz	LineNumberTable;
Asciz	scala/Function13$class;
class	scala/Function13$class
Asciz	(Lscala/Function13;)Ljava/lang/String;;
NameAndType	toString:(Lscala/Function13;)Ljava/lang/String;
Method	scala/Function13$class.toString:(Lscala/Function13;)Ljava/lang/String;
Asciz	curried;
Asciz	()Lscala/Function1;;
Asciz	(Lscala/Function13;)Lscala/Function1;;
NameAndType	curried:(Lscala/Function13;)Lscala/Function1;
Method	scala/Function13$class.curried:(Lscala/Function13;)Lscala/Function1;
Asciz	curry;
NameAndType	curry:(Lscala/Function13;)Lscala/Function1;
Method	scala/Function13$class.curry:(Lscala/Function13;)Lscala/Function1;
Asciz	Deprecated;
Asciz	tupled;
NameAndType	tupled:(Lscala/Function13;)Lscala/Function1;
Method	scala/Function13$class.tupled:(Lscala/Function13;)Lscala/Function1;
Asciz	<init>;
Asciz	()V;
Asciz	java/lang/Object;
class	java/lang/Object
NameAndType	"<init>":()V
Method	java/lang/Object."<init>":()V
Asciz	$init$;
Asciz	(Lscala/Function13;)V;
NameAndType	$init$:(Lscala/Function13;)V
Method	scala/Function13$class.$init$:(Lscala/Function13;)V
Asciz	Signature;
Asciz	ScalaSig;
Asciz	<T1:Ljava/lang/Object;T2:Ljava/lang/Object;T3:Ljava/lang/Object;T4:Ljava/lang/Object;T5:Ljava/lang/Object;T6:Ljava/lang/Object;T7:Ljava/lang/Object;T8:Ljava/lang/Object;T9:Ljava/lang/Object;T10:Ljava/lang/Object;T11:Ljava/lang/Object;T12:Ljava/lang/Object;T13:Ljava/lang/Object;R:Ljava/lang/Object;>Ljava/lang/Object;Lscala/Function13<TT1;TT2;TT3;TT4;TT5;TT6;TT7;TT8;TT9;TT10;TT11;TT12;TT13;TR;>;Lscala/ScalaObject;;
Asciz	Lscala/reflect/ScalaSignature;;
Asciz	bytes;
Asciz	=3Q!!#2tiJ7\r$v]$n82g)1BeVtG/[7f)!B:dC27A]\tCe\n.aM2P CN!!C\tH!\tQq\"D\taQ\"mC:<'\"\t)g/Y!-aa2kK$\n+c%0eUB4HP!E!B)1UO\2uS>tg\r\t-]a\tR1\t!';A!cG9qAT8uQ&tw\r=%q:LC\"\t!\"A\tI\"A+3!\t1B&\tR1\t!6OACDUiAaC\tW!\t#b3\tA+\t-5\"B#\r!)Z\"AEA!ECe!VYD\tE)A\rQCC7\t!9\"A\tI\"A+:!\t1;\tR1\r!\r\t-q\"\"#\r!)F\nC@\t!\"A\tI\"a+2eAaC\t!\t#b3\tA+MY)E$\t%)A\rI\"A%\n%#!aC*dC2wJ6fGRDQa1aP5oSRtD#A'!9QI'S1z#'<}#U\";
Asciz	RuntimeVisibleAnnotations;
Asciz	scala/runtime/AbstractFunction13;
class	scala/runtime/AbstractFunction13
Asciz	scala/Function13;
class	scala/Function13
Asciz	scala/ScalaObject;
class	scala/ScalaObject

{
public java.lang.String toString();
  Signature: ()Ljava/lang/String;
  Code:
   Stack=1, Locals=1, Args_size=1
	aload_0
	invokestatic	Method scala/Function13$class.toString:(Lscala/Function13;)Ljava/lang/String;
	areturn
  Labels:

public scala.Function1 curried();
  Signature: ()Lscala/Function1;
  Code:
   Stack=1, Locals=1, Args_size=1
	aload_0
	invokestatic	Method scala/Function13$class.curried:(Lscala/Function13;)Lscala/Function1;
	areturn
  Labels:

public scala.Function1 curry();
  Signature: ()Lscala/Function1;
  Code:
   Stack=1, Locals=1, Args_size=1
	aload_0
	invokestatic	Method scala/Function13$class.curry:(Lscala/Function13;)Lscala/Function1;
	areturn
  Labels:
  Deprecated: true

public scala.Function1 tupled();
  Signature: ()Lscala/Function1;
  Code:
   Stack=1, Locals=1, Args_size=1
	aload_0
	invokestatic	Method scala/Function13$class.tupled:(Lscala/Function13;)Lscala/Function1;
	areturn
  Labels:

public scala.runtime.AbstractFunction13();
  Signature: ()V
  Code:
   Stack=1, Locals=1, Args_size=1
	aload_0
	invokespecial	Method java/lang/Object."<init>":()V
	aload_0
	invokestatic	Method scala/Function13$class.$init$:(Lscala/Function13;)V
	return
  Labels:
  Signature: length = 0x2
   00 19 

}

