Compiled from "AbstractFunction0.scala"
public abstract class scala.runtime.AbstractFunction16 extends java.lang.Object implements scala.Function16,scala.ScalaObject
  SourceFile: "AbstractFunction0.scala"
  ScalaSig: length = 0x3
   05 00 00 
  Signature: length = 0x2
   00 24 
  RuntimeVisibleAnnotations: length = 0xB
   00 01 00 25 00 01 00 26 73 00 27 
  minor version: 0
  major version: 49
  Constant pool:
Asciz	SourceFile;
Asciz	AbstractFunction0.scala;
Asciz	toString;
Asciz	()Ljava/lang/String;;
Asciz	Code;
Asciz	LineNumberTable;
Asciz	scala/Function16$class;
class	scala/Function16$class
Asciz	(Lscala/Function16;)Ljava/lang/String;;
NameAndType	toString:(Lscala/Function16;)Ljava/lang/String;
Method	scala/Function16$class.toString:(Lscala/Function16;)Ljava/lang/String;
Asciz	curried;
Asciz	()Lscala/Function1;;
Asciz	(Lscala/Function16;)Lscala/Function1;;
NameAndType	curried:(Lscala/Function16;)Lscala/Function1;
Method	scala/Function16$class.curried:(Lscala/Function16;)Lscala/Function1;
Asciz	curry;
NameAndType	curry:(Lscala/Function16;)Lscala/Function1;
Method	scala/Function16$class.curry:(Lscala/Function16;)Lscala/Function1;
Asciz	Deprecated;
Asciz	tupled;
NameAndType	tupled:(Lscala/Function16;)Lscala/Function1;
Method	scala/Function16$class.tupled:(Lscala/Function16;)Lscala/Function1;
Asciz	<init>;
Asciz	()V;
Asciz	java/lang/Object;
class	java/lang/Object
NameAndType	"<init>":()V
Method	java/lang/Object."<init>":()V
Asciz	$init$;
Asciz	(Lscala/Function16;)V;
NameAndType	$init$:(Lscala/Function16;)V
Method	scala/Function16$class.$init$:(Lscala/Function16;)V
Asciz	Signature;
Asciz	ScalaSig;
Asciz	<T1:Ljava/lang/Object;T2:Ljava/lang/Object;T3:Ljava/lang/Object;T4:Ljava/lang/Object;T5:Ljava/lang/Object;T6:Ljava/lang/Object;T7:Ljava/lang/Object;T8:Ljava/lang/Object;T9:Ljava/lang/Object;T10:Ljava/lang/Object;T11:Ljava/lang/Object;T12:Ljava/lang/Object;T13:Ljava/lang/Object;T14:Ljava/lang/Object;T15:Ljava/lang/Object;T16:Ljava/lang/Object;R:Ljava/lang/Object;>Ljava/lang/Object;Lscala/Function16<TT1;TT2;TT3;TT4;TT5;TT6;TT7;TT8;TT9;TT10;TT11;TT12;TT13;TT14;TT15;TT16;TR;>;Lscala/ScalaObject;;
Asciz	Lscala/reflect/ScalaSignature;;
Asciz	bytes;
Asciz	a3Q!!#2tiJ7\r$v]$n82m)1BeVtG/[7f)!B:dC27A]\tCe\n.aM2P C\"[ejECY!BaM\49\tAA[1wC&c\nTWm;'IRI'S1z#'<}#uIS'I!+hn;j_:d/1A\r\tE)A\rQC!\t2$\t\t9aj;iS:<C\n\tyBAAB]f\"AF\tA!ECe!Y!CC\tE)A\rQC(\t!A\"A\tI\"A+5!\t1\",\tR1\t!V[AaCDUmAa\r\tc!\t#b3\tAk\t-M\"#\r!)b\"A]A!ECe!VYID\tE)A\rQyAQCDAUcE\"AF A!ECe1V3!\t1\"\tD\tR1\r!g\r\t-#B#\r!)F\"CI\t!I\"A\tI\"a+2kAac\t!\t#b3\tA+\rYqEC(\t%)A\rI\"AE)\nI#!aC*dC2wJ6fGRDQUaP5oSRtD#,']QI'S1z#'<}#uIS'\t;
Asciz	RuntimeVisibleAnnotations;
Asciz	scala/runtime/AbstractFunction16;
class	scala/runtime/AbstractFunction16
Asciz	scala/Function16;
class	scala/Function16
Asciz	scala/ScalaObject;
class	scala/ScalaObject

{
public java.lang.String toString();
  Signature: ()Ljava/lang/String;
  Code:
   Stack=1, Locals=1, Args_size=1
	aload_0
	invokestatic	Method scala/Function16$class.toString:(Lscala/Function16;)Ljava/lang/String;
	areturn
  Labels:

public scala.Function1 curried();
  Signature: ()Lscala/Function1;
  Code:
   Stack=1, Locals=1, Args_size=1
	aload_0
	invokestatic	Method scala/Function16$class.curried:(Lscala/Function16;)Lscala/Function1;
	areturn
  Labels:

public scala.Function1 curry();
  Signature: ()Lscala/Function1;
  Code:
   Stack=1, Locals=1, Args_size=1
	aload_0
	invokestatic	Method scala/Function16$class.curry:(Lscala/Function16;)Lscala/Function1;
	areturn
  Labels:
  Deprecated: true

public scala.Function1 tupled();
  Signature: ()Lscala/Function1;
  Code:
   Stack=1, Locals=1, Args_size=1
	aload_0
	invokestatic	Method scala/Function16$class.tupled:(Lscala/Function16;)Lscala/Function1;
	areturn
  Labels:

public scala.runtime.AbstractFunction16();
  Signature: ()V
  Code:
   Stack=1, Locals=1, Args_size=1
	aload_0
	invokespecial	Method java/lang/Object."<init>":()V
	aload_0
	invokestatic	Method scala/Function16$class.$init$:(Lscala/Function16;)V
	return
  Labels:
  Signature: length = 0x2
   00 19 

}

