Compiled from "AbstractFunction18.scala"
public abstract class scala.runtime.AbstractFunction18 extends java.lang.Object implements scala.Function18,scala.ScalaObject
  SourceFile: "AbstractFunction18.scala"
  ScalaSig: length = 0x3
   05 00 00 
  Signature: length = 0x2
   00 24 
  RuntimeVisibleAnnotations: length = 0xB
   00 01 00 25 00 01 00 26 73 00 27 
  minor version: 0
  major version: 49
  Constant pool:
Asciz	SourceFile;
Asciz	AbstractFunction18.scala;
Asciz	toString;
Asciz	()Ljava/lang/String;;
Asciz	Code;
Asciz	LineNumberTable;
Asciz	scala/Function18$class;
class	scala/Function18$class
Asciz	(Lscala/Function18;)Ljava/lang/String;;
NameAndType	toString:(Lscala/Function18;)Ljava/lang/String;
Method	scala/Function18$class.toString:(Lscala/Function18;)Ljava/lang/String;
Asciz	curried;
Asciz	()Lscala/Function1;;
Asciz	(Lscala/Function18;)Lscala/Function1;;
NameAndType	curried:(Lscala/Function18;)Lscala/Function1;
Method	scala/Function18$class.curried:(Lscala/Function18;)Lscala/Function1;
Asciz	curry;
NameAndType	curry:(Lscala/Function18;)Lscala/Function1;
Method	scala/Function18$class.curry:(Lscala/Function18;)Lscala/Function1;
Asciz	Deprecated;
Asciz	tupled;
NameAndType	tupled:(Lscala/Function18;)Lscala/Function1;
Method	scala/Function18$class.tupled:(Lscala/Function18;)Lscala/Function1;
Asciz	<init>;
Asciz	()V;
Asciz	java/lang/Object;
class	java/lang/Object
NameAndType	"<init>":()V
Method	java/lang/Object."<init>":()V
Asciz	$init$;
Asciz	(Lscala/Function18;)V;
NameAndType	$init$:(Lscala/Function18;)V
Method	scala/Function18$class.$init$:(Lscala/Function18;)V
Asciz	Signature;
Asciz	ScalaSig;
Asciz	<T1:Ljava/lang/Object;T2:Ljava/lang/Object;T3:Ljava/lang/Object;T4:Ljava/lang/Object;T5:Ljava/lang/Object;T6:Ljava/lang/Object;T7:Ljava/lang/Object;T8:Ljava/lang/Object;T9:Ljava/lang/Object;T10:Ljava/lang/Object;T11:Ljava/lang/Object;T12:Ljava/lang/Object;T13:Ljava/lang/Object;T14:Ljava/lang/Object;T15:Ljava/lang/Object;T16:Ljava/lang/Object;T17:Ljava/lang/Object;T18:Ljava/lang/Object;R:Ljava/lang/Object;>Ljava/lang/Object;Lscala/Function18<TT1;TT2;TT3;TT4;TT5;TT6;TT7;TT8;TT9;TT10;TT11;TT12;TT13;TT14;TT15;TT16;TT17;TT18;TR;>;Lscala/ScalaObject;;
Asciz	Lscala/reflect/ScalaSignature;;
Asciz	bytes;
Asciz	y3Q!!#2tiJ7\r$v]$n82q)1BeVtG/[7f)!B:dC27A]\tCe\n.aM2P C\"[e*+\tIC\t=ia5\tA\1oO*\ta\"kCZB\ty%M[3diB)\"cE!GJCf6qmr\tR$KBV\"\nQ!!A$v]$n82qAac\t!A\"A\tI\"A+2#\tQR7%A>$.8h!\tb$ \t\tI\=Y\tC\tE)A\rQC%\t!)\"A\tI\"A+4!\t1r)\tR1\t!FUA1CDUkAa#\t]!\t#b3\tAK\t-A\"\"\r#\r!)^\"AFQA!ECe!Y1DC\tE)A\rQKC:\t!Q\"A\tI\"a+2aAa\t{!\t#b3\tA+MYyD!\tE)A\rQ$A1\tCDAUcM\"AF#A!ECe1V5!\t1\nJ\tR1\r!'\t--##\r!)F2CO\t!y\"A\tI\"a+2oAa#\t%!\t#b3\tA+\rY!FC+\t%)A\rI\"AE,\na#!aC*dC2wJ6fGRDQAmaP5oSRtD#/+uQI'S1z#'<}#uIS'Q'6\t!;
Asciz	RuntimeVisibleAnnotations;
Asciz	scala/runtime/AbstractFunction18;
class	scala/runtime/AbstractFunction18
Asciz	scala/Function18;
class	scala/Function18
Asciz	scala/ScalaObject;
class	scala/ScalaObject

{
public java.lang.String toString();
  Signature: ()Ljava/lang/String;
  Code:
   Stack=1, Locals=1, Args_size=1
	aload_0
	invokestatic	Method scala/Function18$class.toString:(Lscala/Function18;)Ljava/lang/String;
	areturn
  Labels:

public scala.Function1 curried();
  Signature: ()Lscala/Function1;
  Code:
   Stack=1, Locals=1, Args_size=1
	aload_0
	invokestatic	Method scala/Function18$class.curried:(Lscala/Function18;)Lscala/Function1;
	areturn
  Labels:

public scala.Function1 curry();
  Signature: ()Lscala/Function1;
  Code:
   Stack=1, Locals=1, Args_size=1
	aload_0
	invokestatic	Method scala/Function18$class.curry:(Lscala/Function18;)Lscala/Function1;
	areturn
  Labels:
  Deprecated: true

public scala.Function1 tupled();
  Signature: ()Lscala/Function1;
  Code:
   Stack=1, Locals=1, Args_size=1
	aload_0
	invokestatic	Method scala/Function18$class.tupled:(Lscala/Function18;)Lscala/Function1;
	areturn
  Labels:

public scala.runtime.AbstractFunction18();
  Signature: ()V
  Code:
   Stack=1, Locals=1, Args_size=1
	aload_0
	invokespecial	Method java/lang/Object."<init>":()V
	aload_0
	invokestatic	Method scala/Function18$class.$init$:(Lscala/Function18;)V
	return
  Labels:
  Signature: length = 0x2
   00 19 

}

