Compiled from "AbstractFunction0.scala"
public abstract class scala.runtime.AbstractFunction0$mcC$sp extends scala.runtime.AbstractFunction0 implements scala.Function0$mcC$sp
  SourceFile: "AbstractFunction0.scala"
  Scala: length = 0x
   
  Signature: length = 0x2
   00 22 
  minor version: 0
  major version: 49
  Constant pool:
Asciz	SourceFile;
Asciz	AbstractFunction0.scala;
Asciz	apply;
Asciz	()C;
Asciz	Code;
Asciz	LineNumberTable;
Asciz	scala/Function0$mcC$sp$class;
class	scala/Function0$mcC$sp$class
Asciz	(Lscala/Function0$mcC$sp;)C;
NameAndType	apply:(Lscala/Function0$mcC$sp;)C
Method	scala/Function0$mcC$sp$class.apply:(Lscala/Function0$mcC$sp;)C
Asciz	()Ljava/lang/Object;;
Asciz	scala/Function0$mcC$sp;
class	scala/Function0$mcC$sp
NameAndType	apply:()C
InterfaceMethod	scala/Function0$mcC$sp.apply:()C
Asciz	scala/runtime/BoxesRunTime;
class	scala/runtime/BoxesRunTime
Asciz	boxToCharacter;
Asciz	(C)Ljava/lang/Character;;
NameAndType	boxToCharacter:(C)Ljava/lang/Character;
Method	scala/runtime/BoxesRunTime.boxToCharacter:(C)Ljava/lang/Character;
Asciz	<init>;
Asciz	()V;
Asciz	scala/runtime/AbstractFunction0;
class	scala/runtime/AbstractFunction0
NameAndType	"<init>":()V
Method	scala/runtime/AbstractFunction0."<init>":()V
Asciz	$init$;
Asciz	(Lscala/Function0$mcC$sp;)V;
NameAndType	$init$:(Lscala/Function0$mcC$sp;)V
Method	scala/Function0$mcC$sp$class.$init$:(Lscala/Function0$mcC$sp;)V
Asciz	Scala;
Asciz	Lscala/runtime/AbstractFunction0<Ljava/lang/Character;>;Lscala/Function0$mcC$sp;;
Asciz	Signature;
Asciz	scala/runtime/AbstractFunction0$mcC$sp;
class	scala/runtime/AbstractFunction0$mcC$sp

{
public char apply();
  Signature: ()C
  Code:
   Stack=1, Locals=1, Args_size=1
	aload_0
	invokestatic	Method scala/Function0$mcC$sp$class.apply:(Lscala/Function0$mcC$sp;)C
	ireturn
  Labels:

public java.lang.Object apply();
  Signature: ()Ljava/lang/Object;
  Code:
   Stack=1, Locals=2, Args_size=1
	aload_0
	invokeinterface	InterfaceMethod scala/Function0$mcC$sp.apply:()C
	istore_1
	iload_1
	invokestatic	Method scala/runtime/BoxesRunTime.boxToCharacter:(C)Ljava/lang/Character;
	areturn
  Labels:

public scala.runtime.AbstractFunction0$mcC$sp();
  Signature: ()V
  Code:
   Stack=1, Locals=1, Args_size=1
	aload_0
	invokespecial	Method scala/runtime/AbstractFunction0."<init>":()V
	aload_0
	invokestatic	Method scala/Function0$mcC$sp$class.$init$:(Lscala/Function0$mcC$sp;)V
	return
  Labels:

}

