Compiled from "AbstractFunction0.scala"
public abstract class scala.runtime.AbstractFunction19 extends java.lang.Object implements scala.Function19,scala.ScalaObject
  SourceFile: "AbstractFunction0.scala"
  Signature: length = 0x2
   00 23 
  ScalaSig: length = 0x27C
   05 00 61 06 05 01 02 FFFFFF81 00 07 02 12 41 62 73 74
   72 61 63 74 46 75 6E 63 74 69 6F 6E 31 39 0A 02
   03 04 01 07 72 75 6E 74 69 6D 65 0A 01 05 01 05
   73 63 61 6C 61 03 00 15 15 08 17 21 24 27 2A 2D
   30 33 36 39 3C 3F 42 45 48 4B 4E 51 54 57 13 04
   00 09 11 59 10 02 0A 0F 0D 01 0B 0A 02 0C 0D 01
   04 6C 61 6E 67 0A 01 0E 01 04 6A 61 76 61 09 02
   10 0B 02 06 4F 62 6A 65 63 74 10 16 12 13 15 20
   23 26 29 2C 2F 32 35 38 3B 3E 41 44 47 4A 4D 50
   53 56 0D 01 04 09 02 14 04 02 0A 46 75 6E 63 74
   69 6F 6E 31 39 10 02 16 17 0C 00 04 08 18 00 FFFFFF84
   FFFFFF80 FFFFFF88 FFFFFFC2 00 19 02 02 54 31 11 02 1A 1D 10 02 12
   1B 09 02 1C 04 02 07 4E 6F 74 68 69 6E 67 10 02
   12 1E 09 02 1F 04 02 03 41 6E 79 10 02 16 21 04
   08 22 00 FFFFFF84 FFFFFF80 FFFFFF88 FFFFFFC2 00 19 02 02 54 32 10 02 16
   24 04 08 25 00 FFFFFF84 FFFFFF80 FFFFFF88 FFFFFFC2 00 19 02 02 54 33 10
   02 16 27 04 08 28 00 FFFFFF84 FFFFFF80 FFFFFF88 FFFFFFC2 00 19 02 02 54
   34 10 02 16 2A 04 08 2B 00 FFFFFF84 FFFFFF80 FFFFFF88 FFFFFFC2 00 19 02
   02 54 35 10 02 16 2D 04 08 2E 00 FFFFFF84 FFFFFF80 FFFFFF88 FFFFFFC2 00
   19 02 02 54 36 10 02 16 30 04 08 31 00 FFFFFF84 FFFFFF80 FFFFFF88
   FFFFFFC2 00 19 02 02 54 37 10 02 16 33 04 08 34 00 FFFFFF84
   FFFFFF80 FFFFFF88 FFFFFFC2 00 19 02 02 54 38 10 02 16 36 04 08 37
   00 FFFFFF84 FFFFFF80 FFFFFF88 FFFFFFC2 00 19 02 02 54 39 10 02 16 39 04
   08 3A 00 FFFFFF84 FFFFFF80 FFFFFF88 FFFFFFC2 00 19 02 03 54 31 30 10 02
   16 3C 04 08 3D 00 FFFFFF84 FFFFFF80 FFFFFF88 FFFFFFC2 00 19 02 03 54 31
   31 10 02 16 3F 04 08 40 00 FFFFFF84 FFFFFF80 FFFFFF88 FFFFFFC2 00 19 02
   03 54 31 32 10 02 16 42 04 08 43 00 FFFFFF84 FFFFFF80 FFFFFF88 FFFFFFC2
   00 19 02 03 54 31 33 10 02 16 45 04 08 46 00 FFFFFF84
   FFFFFF80 FFFFFF88 FFFFFFC2 00 19 02 03 54 31 34 10 02 16 48 04 08
   49 00 FFFFFF84 FFFFFF80 FFFFFF88 FFFFFFC2 00 19 02 03 54 31 35 10 02 16
   4B 04 08 4C 00 FFFFFF84 FFFFFF80 FFFFFF88 FFFFFFC2 00 19 02 03 54 31 36
   10 02 16 4E 04 08 4F 00 FFFFFF84 FFFFFF80 FFFFFF88 FFFFFFC2 00 19 02 03
   54 31 37 10 02 16 51 04 08 52 00 FFFFFF84 FFFFFF80 FFFFFF88 FFFFFFC2 00
   19 02 03 54 31 38 10 02 16 54 04 08 55 00 FFFFFF84 FFFFFF80
   FFFFFF88 FFFFFFC2 00 19 02 03 54 31 39 10 02 16 57 04 08 58
   00 FFFFFF84 FFFFFF80 FFFFFF84 FFFFFFC2 00 19 02 01 52 10 02 12 5A 09 02
   5B 04 02 0B 53 63 61 6C 61 4F 62 6A 65 63 74 08
   05 5D 00 FFFFFF84 00 5E 01 06 3C 69 6E 69 74 3E 14 01
   5F 10 16 60 00 15 20 23 26 29 2C 2F 32 35 38 3B
   3E 41 44 47 4A 4D 50 53 56 0D 01 02 
  minor version: 0
  major version: 49
  Constant pool:
Asciz	SourceFile;
Asciz	AbstractFunction0.scala;
Asciz	<init>;
Asciz	()V;
Asciz	Code;
Asciz	LineNumberTable;
Asciz	java/lang/Object;
class	java/lang/Object
NameAndType	"<init>":()V
Method	java/lang/Object."<init>":()V
Asciz	scala/Function19$class;
class	scala/Function19$class
Asciz	$init$;
Asciz	(Lscala/Function19;)V;
NameAndType	$init$:(Lscala/Function19;)V
Method	scala/Function19$class.$init$:(Lscala/Function19;)V
Asciz	Signature;
Asciz	tupled;
Asciz	()Lscala/Function1;;
Asciz	(Lscala/Function19;)Lscala/Function1;;
NameAndType	tupled:(Lscala/Function19;)Lscala/Function1;
Method	scala/Function19$class.tupled:(Lscala/Function19;)Lscala/Function1;
Asciz	curry;
NameAndType	curry:(Lscala/Function19;)Lscala/Function1;
Method	scala/Function19$class.curry:(Lscala/Function19;)Lscala/Function1;
Asciz	Deprecated;
Asciz	curried;
NameAndType	curried:(Lscala/Function19;)Lscala/Function1;
Method	scala/Function19$class.curried:(Lscala/Function19;)Lscala/Function1;
Asciz	toString;
Asciz	()Ljava/lang/String;;
Asciz	(Lscala/Function19;)Ljava/lang/String;;
NameAndType	toString:(Lscala/Function19;)Ljava/lang/String;
Method	scala/Function19$class.toString:(Lscala/Function19;)Ljava/lang/String;
Asciz	<T1:Ljava/lang/Object;T2:Ljava/lang/Object;T3:Ljava/lang/Object;T4:Ljava/lang/Object;T5:Ljava/lang/Object;T6:Ljava/lang/Object;T7:Ljava/lang/Object;T8:Ljava/lang/Object;T9:Ljava/lang/Object;T10:Ljava/lang/Object;T11:Ljava/lang/Object;T12:Ljava/lang/Object;T13:Ljava/lang/Object;T14:Ljava/lang/Object;T15:Ljava/lang/Object;T16:Ljava/lang/Object;T17:Ljava/lang/Object;T18:Ljava/lang/Object;T19:Ljava/lang/Object;R:Ljava/lang/Object;>Ljava/lang/Object;Lscala/Function19<TT1;TT2;TT3;TT4;TT5;TT6;TT7;TT8;TT9;TT10;TT11;TT12;TT13;TT14;TT15;TT16;TT17;TT18;TT19;TR;>;Lscala/ScalaObject;;
Asciz	ScalaSig;
Asciz	scala/runtime/AbstractFunction19;
class	scala/runtime/AbstractFunction19
Asciz	scala/Function19;
class	scala/Function19
Asciz	scala/ScalaObject;
class	scala/ScalaObject

{
public scala.runtime.AbstractFunction19();
  Signature: ()V
  Code:
   Stack=1, Locals=1, Args_size=1
	aload_0
	invokespecial	Method java/lang/Object."<init>":()V
	aload_0
	invokestatic	Method scala/Function19$class.$init$:(Lscala/Function19;)V
	return
  Labels:
  Signature: length = 0x2
   00 04 

public scala.Function1 tupled();
  Signature: ()Lscala/Function1;
  Code:
   Stack=1, Locals=1, Args_size=1
	aload_0
	invokestatic	Method scala/Function19$class.tupled:(Lscala/Function19;)Lscala/Function1;
	areturn
  Labels:

public scala.Function1 curry();
  Signature: ()Lscala/Function1;
  Code:
   Stack=1, Locals=1, Args_size=1
	aload_0
	invokestatic	Method scala/Function19$class.curry:(Lscala/Function19;)Lscala/Function1;
	areturn
  Labels:
  Deprecated: true

public scala.Function1 curried();
  Signature: ()Lscala/Function1;
  Code:
   Stack=1, Locals=1, Args_size=1
	aload_0
	invokestatic	Method scala/Function19$class.curried:(Lscala/Function19;)Lscala/Function1;
	areturn
  Labels:

public java.lang.String toString();
  Signature: ()Ljava/lang/String;
  Code:
   Stack=1, Locals=1, Args_size=1
	aload_0
	invokestatic	Method scala/Function19$class.toString:(Lscala/Function19;)Ljava/lang/String;
	areturn
  Labels:

}

