Compiled from "AbstractFunction0.scala"
public abstract class scala.runtime.AbstractFunction0$mcF$sp extends scala.runtime.AbstractFunction0 implements scala.Function0$mcF$sp
  SourceFile: "AbstractFunction0.scala"
  Scala: length = 0x
   
  Signature: length = 0x2
   00 22 
  minor version: 0
  major version: 49
  Constant pool:
Asciz	SourceFile;
Asciz	AbstractFunction0.scala;
Asciz	apply;
Asciz	()F;
Asciz	Code;
Asciz	LineNumberTable;
Asciz	scala/Function0$mcF$sp$class;
class	scala/Function0$mcF$sp$class
Asciz	(Lscala/Function0$mcF$sp;)F;
NameAndType	apply:(Lscala/Function0$mcF$sp;)F
Method	scala/Function0$mcF$sp$class.apply:(Lscala/Function0$mcF$sp;)F
Asciz	()Ljava/lang/Object;;
Asciz	scala/Function0$mcF$sp;
class	scala/Function0$mcF$sp
NameAndType	apply:()F
InterfaceMethod	scala/Function0$mcF$sp.apply:()F
Asciz	scala/runtime/BoxesRunTime;
class	scala/runtime/BoxesRunTime
Asciz	boxToFloat;
Asciz	(F)Ljava/lang/Float;;
NameAndType	boxToFloat:(F)Ljava/lang/Float;
Method	scala/runtime/BoxesRunTime.boxToFloat:(F)Ljava/lang/Float;
Asciz	<init>;
Asciz	()V;
Asciz	scala/runtime/AbstractFunction0;
class	scala/runtime/AbstractFunction0
NameAndType	"<init>":()V
Method	scala/runtime/AbstractFunction0."<init>":()V
Asciz	$init$;
Asciz	(Lscala/Function0$mcF$sp;)V;
NameAndType	$init$:(Lscala/Function0$mcF$sp;)V
Method	scala/Function0$mcF$sp$class.$init$:(Lscala/Function0$mcF$sp;)V
Asciz	Scala;
Asciz	Lscala/runtime/AbstractFunction0<Ljava/lang/Float;>;Lscala/Function0$mcF$sp;;
Asciz	Signature;
Asciz	scala/runtime/AbstractFunction0$mcF$sp;
class	scala/runtime/AbstractFunction0$mcF$sp

{
public float apply();
  Signature: ()F
  Code:
   Stack=1, Locals=1, Args_size=1
	aload_0
	invokestatic	Method scala/Function0$mcF$sp$class.apply:(Lscala/Function0$mcF$sp;)F
	freturn
  Labels:

public java.lang.Object apply();
  Signature: ()Ljava/lang/Object;
  Code:
   Stack=1, Locals=2, Args_size=1
	aload_0
	invokeinterface	InterfaceMethod scala/Function0$mcF$sp.apply:()F
	fstore_1
	fload_1
	invokestatic	Method scala/runtime/BoxesRunTime.boxToFloat:(F)Ljava/lang/Float;
	areturn
  Labels:

public scala.runtime.AbstractFunction0$mcF$sp();
  Signature: ()V
  Code:
   Stack=1, Locals=1, Args_size=1
	aload_0
	invokespecial	Method scala/runtime/AbstractFunction0."<init>":()V
	aload_0
	invokestatic	Method scala/Function0$mcF$sp$class.$init$:(Lscala/Function0$mcF$sp;)V
	return
  Labels:

}

