Compiled from "AbstractFunction0.scala"
public abstract class scala.runtime.AbstractFunction11 extends java.lang.Object implements scala.Function11,scala.ScalaObject
  SourceFile: "AbstractFunction0.scala"
  ScalaSig: length = 0x3
   05 00 00 
  Signature: length = 0x2
   00 24 
  RuntimeVisibleAnnotations: length = 0xB
   00 01 00 25 00 01 00 26 73 00 27 
  minor version: 0
  major version: 49
  Constant pool:
Asciz	SourceFile;
Asciz	AbstractFunction0.scala;
Asciz	toString;
Asciz	()Ljava/lang/String;;
Asciz	Code;
Asciz	LineNumberTable;
Asciz	scala/Function11$class;
class	scala/Function11$class
Asciz	(Lscala/Function11;)Ljava/lang/String;;
NameAndType	toString:(Lscala/Function11;)Ljava/lang/String;
Method	scala/Function11$class.toString:(Lscala/Function11;)Ljava/lang/String;
Asciz	curried;
Asciz	()Lscala/Function1;;
Asciz	(Lscala/Function11;)Lscala/Function1;;
NameAndType	curried:(Lscala/Function11;)Lscala/Function1;
Method	scala/Function11$class.curried:(Lscala/Function11;)Lscala/Function1;
Asciz	curry;
NameAndType	curry:(Lscala/Function11;)Lscala/Function1;
Method	scala/Function11$class.curry:(Lscala/Function11;)Lscala/Function1;
Asciz	Deprecated;
Asciz	tupled;
NameAndType	tupled:(Lscala/Function11;)Lscala/Function1;
Method	scala/Function11$class.tupled:(Lscala/Function11;)Lscala/Function1;
Asciz	<init>;
Asciz	()V;
Asciz	java/lang/Object;
class	java/lang/Object
NameAndType	"<init>":()V
Method	java/lang/Object."<init>":()V
Asciz	$init$;
Asciz	(Lscala/Function11;)V;
NameAndType	$init$:(Lscala/Function11;)V
Method	scala/Function11$class.$init$:(Lscala/Function11;)V
Asciz	Signature;
Asciz	ScalaSig;
Asciz	<T1:Ljava/lang/Object;T2:Ljava/lang/Object;T3:Ljava/lang/Object;T4:Ljava/lang/Object;T5:Ljava/lang/Object;T6:Ljava/lang/Object;T7:Ljava/lang/Object;T8:Ljava/lang/Object;T9:Ljava/lang/Object;T10:Ljava/lang/Object;T11:Ljava/lang/Object;R:Ljava/lang/Object;>Ljava/lang/Object;Lscala/Function11<TT1;TT2;TT3;TT4;TT5;TT6;TT7;TT8;TT9;TT10;TT11;TR;>;Lscala/ScalaObject;;
Asciz	Lscala/reflect/ScalaSignature;;
Asciz	bytes;
Asciz	%3Q!!#2tiJ7\r$v]$n82c)1BeVtG/[7f)!B:dC27A]\tCe\n.aM2P \tI#\t=ia5\tA\1oO*\ta\"kCZB\ty%M[3diBq!cE!GJCf6qmrT\"\nQ!!A$v]$n82cAac\t!A\"A\tI\"A+2#\tQR7%A>$.8h!\tb$ \t\tI\=Y\tC\tE)A\rQC%\t!)\"A\tI\"A+4!\t1r)\tR1\t!FUA1CDUkAa#\t]!\t#b3\tAK\t-A\"\"\r#\r!)^\"AFQA!ECe!Y1DC\tE)A\rQKC:\t!Q\"A\tI\"a+2aAa\t{!\t#b3\tA+MYyD!\t%)A\rI\"A\"\n\r#!aC*dC2wJ6fGRDQ!aP5oSRtD#A$!QI'S1z#'<}5\t!;
Asciz	RuntimeVisibleAnnotations;
Asciz	scala/runtime/AbstractFunction11;
class	scala/runtime/AbstractFunction11
Asciz	scala/Function11;
class	scala/Function11
Asciz	scala/ScalaObject;
class	scala/ScalaObject

{
public java.lang.String toString();
  Signature: ()Ljava/lang/String;
  Code:
   Stack=1, Locals=1, Args_size=1
	aload_0
	invokestatic	Method scala/Function11$class.toString:(Lscala/Function11;)Ljava/lang/String;
	areturn
  Labels:

public scala.Function1 curried();
  Signature: ()Lscala/Function1;
  Code:
   Stack=1, Locals=1, Args_size=1
	aload_0
	invokestatic	Method scala/Function11$class.curried:(Lscala/Function11;)Lscala/Function1;
	areturn
  Labels:

public scala.Function1 curry();
  Signature: ()Lscala/Function1;
  Code:
   Stack=1, Locals=1, Args_size=1
	aload_0
	invokestatic	Method scala/Function11$class.curry:(Lscala/Function11;)Lscala/Function1;
	areturn
  Labels:
  Deprecated: true

public scala.Function1 tupled();
  Signature: ()Lscala/Function1;
  Code:
   Stack=1, Locals=1, Args_size=1
	aload_0
	invokestatic	Method scala/Function11$class.tupled:(Lscala/Function11;)Lscala/Function1;
	areturn
  Labels:

public scala.runtime.AbstractFunction11();
  Signature: ()V
  Code:
   Stack=1, Locals=1, Args_size=1
	aload_0
	invokespecial	Method java/lang/Object."<init>":()V
	aload_0
	invokestatic	Method scala/Function11$class.$init$:(Lscala/Function11;)V
	return
  Labels:
  Signature: length = 0x2
   00 19 

}

