Compiled from "AbstractFunction0.scala"
public abstract class scala.runtime.AbstractFunction0$mcS$sp extends scala.runtime.AbstractFunction0 implements scala.Function0$mcS$sp
  SourceFile: "AbstractFunction0.scala"
  Scala: length = 0x
   
  Signature: length = 0x2
   00 22 
  minor version: 0
  major version: 49
  Constant pool:
Asciz	SourceFile;
Asciz	AbstractFunction0.scala;
Asciz	apply;
Asciz	()S;
Asciz	Code;
Asciz	LineNumberTable;
Asciz	scala/Function0$mcS$sp$class;
class	scala/Function0$mcS$sp$class
Asciz	(Lscala/Function0$mcS$sp;)S;
NameAndType	apply:(Lscala/Function0$mcS$sp;)S
Method	scala/Function0$mcS$sp$class.apply:(Lscala/Function0$mcS$sp;)S
Asciz	()Ljava/lang/Object;;
Asciz	scala/Function0$mcS$sp;
class	scala/Function0$mcS$sp
NameAndType	apply:()S
InterfaceMethod	scala/Function0$mcS$sp.apply:()S
Asciz	scala/runtime/BoxesRunTime;
class	scala/runtime/BoxesRunTime
Asciz	boxToShort;
Asciz	(S)Ljava/lang/Short;;
NameAndType	boxToShort:(S)Ljava/lang/Short;
Method	scala/runtime/BoxesRunTime.boxToShort:(S)Ljava/lang/Short;
Asciz	<init>;
Asciz	()V;
Asciz	scala/runtime/AbstractFunction0;
class	scala/runtime/AbstractFunction0
NameAndType	"<init>":()V
Method	scala/runtime/AbstractFunction0."<init>":()V
Asciz	$init$;
Asciz	(Lscala/Function0$mcS$sp;)V;
NameAndType	$init$:(Lscala/Function0$mcS$sp;)V
Method	scala/Function0$mcS$sp$class.$init$:(Lscala/Function0$mcS$sp;)V
Asciz	Scala;
Asciz	Lscala/runtime/AbstractFunction0<Ljava/lang/Short;>;Lscala/Function0$mcS$sp;;
Asciz	Signature;
Asciz	scala/runtime/AbstractFunction0$mcS$sp;
class	scala/runtime/AbstractFunction0$mcS$sp

{
public short apply();
  Signature: ()S
  Code:
   Stack=1, Locals=1, Args_size=1
	aload_0
	invokestatic	Method scala/Function0$mcS$sp$class.apply:(Lscala/Function0$mcS$sp;)S
	ireturn
  Labels:

public java.lang.Object apply();
  Signature: ()Ljava/lang/Object;
  Code:
   Stack=1, Locals=2, Args_size=1
	aload_0
	invokeinterface	InterfaceMethod scala/Function0$mcS$sp.apply:()S
	istore_1
	iload_1
	invokestatic	Method scala/runtime/BoxesRunTime.boxToShort:(S)Ljava/lang/Short;
	areturn
  Labels:

public scala.runtime.AbstractFunction0$mcS$sp();
  Signature: ()V
  Code:
   Stack=1, Locals=1, Args_size=1
	aload_0
	invokespecial	Method scala/runtime/AbstractFunction0."<init>":()V
	aload_0
	invokestatic	Method scala/Function0$mcS$sp$class.$init$:(Lscala/Function0$mcS$sp;)V
	return
  Labels:

}

