Compiled from "AbstractFunction0.scala"
public abstract class scala.runtime.AbstractFunction17 extends java.lang.Object implements scala.Function17,scala.ScalaObject
  SourceFile: "AbstractFunction0.scala"
  ScalaSig: length = 0x3
   05 00 00 
  Signature: length = 0x2
   00 24 
  RuntimeVisibleAnnotations: length = 0xB
   00 01 00 25 00 01 00 26 73 00 27 
  minor version: 0
  major version: 49
  Constant pool:
Asciz	SourceFile;
Asciz	AbstractFunction0.scala;
Asciz	toString;
Asciz	()Ljava/lang/String;;
Asciz	Code;
Asciz	LineNumberTable;
Asciz	scala/Function17$class;
class	scala/Function17$class
Asciz	(Lscala/Function17;)Ljava/lang/String;;
NameAndType	toString:(Lscala/Function17;)Ljava/lang/String;
Method	scala/Function17$class.toString:(Lscala/Function17;)Ljava/lang/String;
Asciz	curried;
Asciz	()Lscala/Function1;;
Asciz	(Lscala/Function17;)Lscala/Function1;;
NameAndType	curried:(Lscala/Function17;)Lscala/Function1;
Method	scala/Function17$class.curried:(Lscala/Function17;)Lscala/Function1;
Asciz	curry;
NameAndType	curry:(Lscala/Function17;)Lscala/Function1;
Method	scala/Function17$class.curry:(Lscala/Function17;)Lscala/Function1;
Asciz	Deprecated;
Asciz	tupled;
NameAndType	tupled:(Lscala/Function17;)Lscala/Function1;
Method	scala/Function17$class.tupled:(Lscala/Function17;)Lscala/Function1;
Asciz	<init>;
Asciz	()V;
Asciz	java/lang/Object;
class	java/lang/Object
NameAndType	"<init>":()V
Method	java/lang/Object."<init>":()V
Asciz	$init$;
Asciz	(Lscala/Function17;)V;
NameAndType	$init$:(Lscala/Function17;)V
Method	scala/Function17$class.$init$:(Lscala/Function17;)V
Asciz	Signature;
Asciz	ScalaSig;
Asciz	<T1:Ljava/lang/Object;T2:Ljava/lang/Object;T3:Ljava/lang/Object;T4:Ljava/lang/Object;T5:Ljava/lang/Object;T6:Ljava/lang/Object;T7:Ljava/lang/Object;T8:Ljava/lang/Object;T9:Ljava/lang/Object;T10:Ljava/lang/Object;T11:Ljava/lang/Object;T12:Ljava/lang/Object;T13:Ljava/lang/Object;T14:Ljava/lang/Object;T15:Ljava/lang/Object;T16:Ljava/lang/Object;T17:Ljava/lang/Object;R:Ljava/lang/Object;>Ljava/lang/Object;Lscala/Function17<TT1;TT2;TT3;TT4;TT5;TT6;TT7;TT8;TT9;TT10;TT11;TT12;TT13;TT14;TT15;TT16;TT17;TR;>;Lscala/ScalaObject;;
Asciz	Lscala/reflect/ScalaSignature;;
Asciz	bytes;
Asciz	m3Q!!#2tiJ7\r$v]$n82o)1BeVtG/[7f)!B:dC27A]\tCe\n.aM2P C\"[e*U\n%\t25\t1B\r!A.8hq6bmL!E\r='.Z2u!Q2#$M%bsFM9wy\nEi&N!6\tA!\t\tQa)8di&|g.MY9B\t1!\t#b3\tA+M\t5u\"AE\nq!!a(pi\"Lgn\t%yI!asCA!CDUeAa\n\tK!\t#b3\tAk\r\t-\"#\r!)R\"A-A!ECe!VYiC\tE)A\rQ3C1\t!\t\"A\tI\"A+8!\t125\tR1\t!mAqCDUsAa#\tu!\t#b3\tA+\rYaDC\tE)A\rQA\tCDAUcI\"A\"\rA!ECe1V4!\t1R\tG\tR1\r!\t-!#\"#\r!)F*CL\t!a\"A\tI\"a+2mAaC\t!\t#b3\tA+MY\tF*\t%)A\rI\"A+\nU#!aC*dC2wJ6fGRDQaaaP5oSRtD#A-)iQI'S1z#'<}#uIS'Q;
Asciz	RuntimeVisibleAnnotations;
Asciz	scala/runtime/AbstractFunction17;
class	scala/runtime/AbstractFunction17
Asciz	scala/Function17;
class	scala/Function17
Asciz	scala/ScalaObject;
class	scala/ScalaObject

{
public java.lang.String toString();
  Signature: ()Ljava/lang/String;
  Code:
   Stack=1, Locals=1, Args_size=1
	aload_0
	invokestatic	Method scala/Function17$class.toString:(Lscala/Function17;)Ljava/lang/String;
	areturn
  Labels:

public scala.Function1 curried();
  Signature: ()Lscala/Function1;
  Code:
   Stack=1, Locals=1, Args_size=1
	aload_0
	invokestatic	Method scala/Function17$class.curried:(Lscala/Function17;)Lscala/Function1;
	areturn
  Labels:

public scala.Function1 curry();
  Signature: ()Lscala/Function1;
  Code:
   Stack=1, Locals=1, Args_size=1
	aload_0
	invokestatic	Method scala/Function17$class.curry:(Lscala/Function17;)Lscala/Function1;
	areturn
  Labels:
  Deprecated: true

public scala.Function1 tupled();
  Signature: ()Lscala/Function1;
  Code:
   Stack=1, Locals=1, Args_size=1
	aload_0
	invokestatic	Method scala/Function17$class.tupled:(Lscala/Function17;)Lscala/Function1;
	areturn
  Labels:

public scala.runtime.AbstractFunction17();
  Signature: ()V
  Code:
   Stack=1, Locals=1, Args_size=1
	aload_0
	invokespecial	Method java/lang/Object."<init>":()V
	aload_0
	invokestatic	Method scala/Function17$class.$init$:(Lscala/Function17;)V
	return
  Labels:
  Signature: length = 0x2
   00 19 

}

