Compiled from "AbstractFunction.scala"
public abstract class scala.runtime.AbstractFunction4 extends java.lang.Object implements scala.Function4,scala.ScalaObject
  SourceFile: "AbstractFunction.scala"
  Signature: length = 0x2
   00 1F 
  ScalaSig: length = 0x135
   05 00 34 06 05 01 02 FFFFFF81 00 07 02 11 41 62 73 74
   72 61 63 74 46 75 6E 63 74 69 6F 6E 34 0A 02 03
   04 01 07 72 75 6E 74 69 6D 65 0A 01 05 01 05 73
   63 61 6C 61 03 00 15 06 08 17 21 24 27 2A 13 04
   00 09 11 2C 10 02 0A 0F 0D 01 0B 0A 02 0C 0D 01
   04 6C 61 6E 67 0A 01 0E 01 04 6A 61 76 61 09 02
   10 0B 02 06 4F 62 6A 65 63 74 10 07 12 13 15 20
   23 26 29 0D 01 04 09 02 14 04 02 09 46 75 6E 63
   74 69 6F 6E 34 10 02 16 17 0C 00 04 08 18 00 FFFFFF84
   FFFFFF80 FFFFFF88 FFFFFFC2 00 19 02 02 54 31 11 02 1A 1D 10 02 12
   1B 09 02 1C 04 02 07 4E 6F 74 68 69 6E 67 10 02
   12 1E 09 02 1F 04 02 03 41 6E 79 10 02 16 21 04
   08 22 00 FFFFFF84 FFFFFF80 FFFFFF88 FFFFFFC2 00 19 02 02 54 32 10 02 16
   24 04 08 25 00 FFFFFF84 FFFFFF80 FFFFFF88 FFFFFFC2 00 19 02 02 54 33 10
   02 16 27 04 08 28 00 FFFFFF84 FFFFFF80 FFFFFF88 FFFFFFC2 00 19 02 02 54
   34 10 02 16 2A 04 08 2B 00 FFFFFF84 FFFFFF80 FFFFFF84 FFFFFFC2 00 19 02
   01 52 10 02 12 2D 09 02 2E 04 02 0B 53 63 61 6C
   61 4F 62 6A 65 63 74 08 05 30 00 FFFFFF84 00 31 01 06
   3C 69 6E 69 74 3E 14 01 32 10 07 33 00 15 20 23
   26 29 0D 01 02 
  minor version: 0
  major version: 49
  Constant pool:
const #1 = Asciz	SourceFile;
const #2 = Asciz	AbstractFunction.scala;
const #3 = Asciz	<init>;
const #4 = Asciz	()V;
const #5 = Asciz	Code;
const #6 = Asciz	LineNumberTable;
const #7 = Asciz	java/lang/Object;
const #8 = class	#7;	//  java/lang/Object
const #9 = NameAndType	#3:#4;//  "<init>":()V
const #10 = Method	#8.#9;	//  java/lang/Object."<init>":()V
const #11 = Asciz	scala/Function4$class;
const #12 = class	#11;	//  scala/Function4$class
const #13 = Asciz	$init$;
const #14 = Asciz	(Lscala/Function4;)V;
const #15 = NameAndType	#13:#14;//  $init$:(Lscala/Function4;)V
const #16 = Method	#12.#15;	//  scala/Function4$class.$init$:(Lscala/Function4;)V
const #17 = Asciz	Signature;
const #18 = Asciz	tuple;
const #19 = Asciz	()Lscala/Function1;;
const #20 = Asciz	(Lscala/Function4;)Lscala/Function1;;
const #21 = NameAndType	#18:#20;//  tuple:(Lscala/Function4;)Lscala/Function1;
const #22 = Method	#12.#21;	//  scala/Function4$class.tuple:(Lscala/Function4;)Lscala/Function1;
const #23 = Asciz	curry;
const #24 = NameAndType	#23:#20;//  curry:(Lscala/Function4;)Lscala/Function1;
const #25 = Method	#12.#24;	//  scala/Function4$class.curry:(Lscala/Function4;)Lscala/Function1;
const #26 = Asciz	toString;
const #27 = Asciz	()Ljava/lang/String;;
const #28 = Asciz	(Lscala/Function4;)Ljava/lang/String;;
const #29 = NameAndType	#26:#28;//  toString:(Lscala/Function4;)Ljava/lang/String;
const #30 = Method	#12.#29;	//  scala/Function4$class.toString:(Lscala/Function4;)Ljava/lang/String;
const #31 = Asciz	<T1:Ljava/lang/Object;T2:Ljava/lang/Object;T3:Ljava/lang/Object;T4:Ljava/lang/Object;R:Ljava/lang/Object;>Ljava/lang/Object;Lscala/Function4<TT1;TT2;TT3;TT4;TR;>;Lscala/ScalaObject;;
const #32 = Asciz	ScalaSig;
const #33 = Asciz	scala/runtime/AbstractFunction4;
const #34 = class	#33;	//  scala/runtime/AbstractFunction4
const #35 = Asciz	scala/Function4;
const #36 = class	#35;	//  scala/Function4
const #37 = Asciz	scala/ScalaObject;
const #38 = class	#37;	//  scala/ScalaObject

{
public scala.runtime.AbstractFunction4();
  Code:
   Stack=1, Locals=1, Args_size=1
   0:	aload_0
   1:	invokespecial	#10; //Method java/lang/Object."<init>":()V
   4:	aload_0
   5:	invokestatic	#16; //Method scala/Function4$class.$init$:(Lscala/Function4;)V
   8:	return
  LineNumberTable: 
   line 15: 0

  Signature: length = 0x2
   00 04 

public scala.Function1 tuple();
  Code:
   Stack=1, Locals=1, Args_size=1
   0:	aload_0
   1:	invokestatic	#22; //Method scala/Function4$class.tuple:(Lscala/Function4;)Lscala/Function1;
   4:	areturn
  LineNumberTable: 
   line 15: 0


public scala.Function1 curry();
  Code:
   Stack=1, Locals=1, Args_size=1
   0:	aload_0
   1:	invokestatic	#25; //Method scala/Function4$class.curry:(Lscala/Function4;)Lscala/Function1;
   4:	areturn
  LineNumberTable: 
   line 15: 0


public java.lang.String toString();
  Code:
   Stack=1, Locals=1, Args_size=1
   0:	aload_0
   1:	invokestatic	#30; //Method scala/Function4$class.toString:(Lscala/Function4;)Ljava/lang/String;
   4:	areturn
  LineNumberTable: 
   line 15: 0


}

