Compiled from "AbstractFunction0.scala"
public abstract class scala.runtime.AbstractFunction0 extends java.lang.Object implements scala.Function0,scala.ScalaObject
  SourceFile: "AbstractFunction0.scala"
  ScalaSig: length = 0x3
   05 00 00 
  Signature: length = 0x2
   00 43 
  RuntimeVisibleAnnotations: length = 0xB
   00 01 00 44 00 01 00 45 73 00 46 
  minor version: 0
  major version: 49
  Constant pool:
Asciz	SourceFile;
Asciz	AbstractFunction0.scala;
Asciz	apply$mcV$sp;
Asciz	()V;
Asciz	Code;
Asciz	LineNumberTable;
Asciz	scala/Function0$class;
class	scala/Function0$class
Asciz	(Lscala/Function0;)V;
NameAndType	apply$mcV$sp:(Lscala/Function0;)V
Method	scala/Function0$class.apply$mcV$sp:(Lscala/Function0;)V
Asciz	apply$mcZ$sp;
Asciz	()Z;
Asciz	(Lscala/Function0;)Z;
NameAndType	apply$mcZ$sp:(Lscala/Function0;)Z
Method	scala/Function0$class.apply$mcZ$sp:(Lscala/Function0;)Z
Asciz	apply$mcB$sp;
Asciz	()B;
Asciz	(Lscala/Function0;)B;
NameAndType	apply$mcB$sp:(Lscala/Function0;)B
Method	scala/Function0$class.apply$mcB$sp:(Lscala/Function0;)B
Asciz	apply$mcS$sp;
Asciz	()S;
Asciz	(Lscala/Function0;)S;
NameAndType	apply$mcS$sp:(Lscala/Function0;)S
Method	scala/Function0$class.apply$mcS$sp:(Lscala/Function0;)S
Asciz	apply$mcC$sp;
Asciz	()C;
Asciz	(Lscala/Function0;)C;
NameAndType	apply$mcC$sp:(Lscala/Function0;)C
Method	scala/Function0$class.apply$mcC$sp:(Lscala/Function0;)C
Asciz	apply$mcI$sp;
Asciz	()I;
Asciz	(Lscala/Function0;)I;
NameAndType	apply$mcI$sp:(Lscala/Function0;)I
Method	scala/Function0$class.apply$mcI$sp:(Lscala/Function0;)I
Asciz	apply$mcL$sp;
Asciz	()J;
Asciz	(Lscala/Function0;)J;
NameAndType	apply$mcL$sp:(Lscala/Function0;)J
Method	scala/Function0$class.apply$mcL$sp:(Lscala/Function0;)J
Asciz	apply$mcF$sp;
Asciz	()F;
Asciz	(Lscala/Function0;)F;
NameAndType	apply$mcF$sp:(Lscala/Function0;)F
Method	scala/Function0$class.apply$mcF$sp:(Lscala/Function0;)F
Asciz	apply$mcD$sp;
Asciz	()D;
Asciz	(Lscala/Function0;)D;
NameAndType	apply$mcD$sp:(Lscala/Function0;)D
Method	scala/Function0$class.apply$mcD$sp:(Lscala/Function0;)D
Asciz	toString;
Asciz	()Ljava/lang/String;;
Asciz	(Lscala/Function0;)Ljava/lang/String;;
NameAndType	toString:(Lscala/Function0;)Ljava/lang/String;
Method	scala/Function0$class.toString:(Lscala/Function0;)Ljava/lang/String;
Asciz	<init>;
Asciz	java/lang/Object;
class	java/lang/Object
NameAndType	"<init>":()V
Method	java/lang/Object."<init>":()V
Asciz	$init$;
NameAndType	$init$:(Lscala/Function0;)V
Method	scala/Function0$class.$init$:(Lscala/Function0;)V
Asciz	Signature;
Asciz	ScalaSig;
Asciz	<R:Ljava/lang/Object;>Ljava/lang/Object;Lscala/Function0<TR;>;Lscala/ScalaObject;;
Asciz	Lscala/reflect/ScalaSignature;;
Asciz	bytes;
Asciz	12Q!#2tiJ7\r$v]$n81\tA!Ask:$.\3\tQa]2bY!\t/M!!C\t%!\tQq\"D\taQ\"mC:<'\"\t)g/Y!-aa2kK$c\n+5\tA!\t\tIa)8di&|g\r\t-]aIQ1C!\t2$\t\t9aj;iS:<C\n\tyBAAB]fD#aFIBA-/Z2jC2L'03I)B-6-7b\nTWm;\t!AA\rqJg.;?)QcA+5\t!;
Asciz	RuntimeVisibleAnnotations;
Asciz	scala/runtime/AbstractFunction0;
class	scala/runtime/AbstractFunction0
Asciz	scala/Function0;
class	scala/Function0
Asciz	scala/ScalaObject;
class	scala/ScalaObject

{
public void apply$mcV$sp();
  Signature: ()V
  Code:
   Stack=1, Locals=1, Args_size=1
	aload_0
	invokestatic	Method scala/Function0$class.apply$mcV$sp:(Lscala/Function0;)V
	return
  Labels:

public boolean apply$mcZ$sp();
  Signature: ()Z
  Code:
   Stack=1, Locals=1, Args_size=1
	aload_0
	invokestatic	Method scala/Function0$class.apply$mcZ$sp:(Lscala/Function0;)Z
	ireturn
  Labels:

public byte apply$mcB$sp();
  Signature: ()B
  Code:
   Stack=1, Locals=1, Args_size=1
	aload_0
	invokestatic	Method scala/Function0$class.apply$mcB$sp:(Lscala/Function0;)B
	ireturn
  Labels:

public short apply$mcS$sp();
  Signature: ()S
  Code:
   Stack=1, Locals=1, Args_size=1
	aload_0
	invokestatic	Method scala/Function0$class.apply$mcS$sp:(Lscala/Function0;)S
	ireturn
  Labels:

public char apply$mcC$sp();
  Signature: ()C
  Code:
   Stack=1, Locals=1, Args_size=1
	aload_0
	invokestatic	Method scala/Function0$class.apply$mcC$sp:(Lscala/Function0;)C
	ireturn
  Labels:

public int apply$mcI$sp();
  Signature: ()I
  Code:
   Stack=1, Locals=1, Args_size=1
	aload_0
	invokestatic	Method scala/Function0$class.apply$mcI$sp:(Lscala/Function0;)I
	ireturn
  Labels:

public long apply$mcL$sp();
  Signature: ()J
  Code:
   Stack=2, Locals=1, Args_size=1
	aload_0
	invokestatic	Method scala/Function0$class.apply$mcL$sp:(Lscala/Function0;)J
	lreturn
  Labels:

public float apply$mcF$sp();
  Signature: ()F
  Code:
   Stack=1, Locals=1, Args_size=1
	aload_0
	invokestatic	Method scala/Function0$class.apply$mcF$sp:(Lscala/Function0;)F
	freturn
  Labels:

public double apply$mcD$sp();
  Signature: ()D
  Code:
   Stack=2, Locals=1, Args_size=1
	aload_0
	invokestatic	Method scala/Function0$class.apply$mcD$sp:(Lscala/Function0;)D
	dreturn
  Labels:

public java.lang.String toString();
  Signature: ()Ljava/lang/String;
  Code:
   Stack=1, Locals=1, Args_size=1
	aload_0
	invokestatic	Method scala/Function0$class.toString:(Lscala/Function0;)Ljava/lang/String;
	areturn
  Labels:

public scala.runtime.AbstractFunction0();
  Signature: ()V
  Code:
   Stack=1, Locals=1, Args_size=1
	aload_0
	invokespecial	Method java/lang/Object."<init>":()V
	aload_0
	invokestatic	Method scala/Function0$class.$init$:(Lscala/Function0;)V
	return
  Labels:
  Signature: length = 0x2
   00 04 

}

