Compiled from "AbstractFunction0.scala"
public abstract class scala.runtime.AbstractFunction5 extends java.lang.Object implements scala.Function5,scala.ScalaObject
  SourceFile: "AbstractFunction0.scala"
  ScalaSig: length = 0x3
   05 00 00 
  Signature: length = 0x2
   00 24 
  RuntimeVisibleAnnotations: length = 0xB
   00 01 00 25 00 01 00 26 73 00 27 
  minor version: 0
  major version: 49
  Constant pool:
Asciz	SourceFile;
Asciz	AbstractFunction0.scala;
Asciz	toString;
Asciz	()Ljava/lang/String;;
Asciz	Code;
Asciz	LineNumberTable;
Asciz	scala/Function5$class;
class	scala/Function5$class
Asciz	(Lscala/Function5;)Ljava/lang/String;;
NameAndType	toString:(Lscala/Function5;)Ljava/lang/String;
Method	scala/Function5$class.toString:(Lscala/Function5;)Ljava/lang/String;
Asciz	curried;
Asciz	()Lscala/Function1;;
Asciz	(Lscala/Function5;)Lscala/Function1;;
NameAndType	curried:(Lscala/Function5;)Lscala/Function1;
Method	scala/Function5$class.curried:(Lscala/Function5;)Lscala/Function1;
Asciz	curry;
NameAndType	curry:(Lscala/Function5;)Lscala/Function1;
Method	scala/Function5$class.curry:(Lscala/Function5;)Lscala/Function1;
Asciz	Deprecated;
Asciz	tupled;
NameAndType	tupled:(Lscala/Function5;)Lscala/Function1;
Method	scala/Function5$class.tupled:(Lscala/Function5;)Lscala/Function1;
Asciz	<init>;
Asciz	()V;
Asciz	java/lang/Object;
class	java/lang/Object
NameAndType	"<init>":()V
Method	java/lang/Object."<init>":()V
Asciz	$init$;
Asciz	(Lscala/Function5;)V;
NameAndType	$init$:(Lscala/Function5;)V
Method	scala/Function5$class.$init$:(Lscala/Function5;)V
Asciz	Signature;
Asciz	ScalaSig;
Asciz	<T1:Ljava/lang/Object;T2:Ljava/lang/Object;T3:Ljava/lang/Object;T4:Ljava/lang/Object;T5:Ljava/lang/Object;R:Ljava/lang/Object;>Ljava/lang/Object;Lscala/Function5<TT1;TT2;TT3;TT4;TT5;TR;>;Lscala/ScalaObject;;
Asciz	Lscala/reflect/ScalaSignature;;
Asciz	bytes;
Asciz	]2Q!#2tiJ7\r$v]$n86\tA!Ask:$.\3\tQa]2bY!F\t/\"sEK\tIc\t=ia5\tA\1oO*\ta\"kCZB\ty%M[3diBA!cE!GJC&D\t!BAAGk:G/[8okAac\t!A\"A\tI\"A+2#\tQR7%A>$.8h!\tb$ \t\tI\=Y\tC\tE)A\rQC%\t!)\"A\tI\"A+4!\t1r)\tR1\t!FUA1CDUkAa#\t]!\t\"b3\t\t!a%'G.Y(cUGC4A'=S:LGOkAAaA!GJC&D;
Asciz	RuntimeVisibleAnnotations;
Asciz	scala/runtime/AbstractFunction5;
class	scala/runtime/AbstractFunction5
Asciz	scala/Function5;
class	scala/Function5
Asciz	scala/ScalaObject;
class	scala/ScalaObject

{
public java.lang.String toString();
  Signature: ()Ljava/lang/String;
  Code:
   Stack=1, Locals=1, Args_size=1
	aload_0
	invokestatic	Method scala/Function5$class.toString:(Lscala/Function5;)Ljava/lang/String;
	areturn
  Labels:

public scala.Function1 curried();
  Signature: ()Lscala/Function1;
  Code:
   Stack=1, Locals=1, Args_size=1
	aload_0
	invokestatic	Method scala/Function5$class.curried:(Lscala/Function5;)Lscala/Function1;
	areturn
  Labels:

public scala.Function1 curry();
  Signature: ()Lscala/Function1;
  Code:
   Stack=1, Locals=1, Args_size=1
	aload_0
	invokestatic	Method scala/Function5$class.curry:(Lscala/Function5;)Lscala/Function1;
	areturn
  Labels:
  Deprecated: true

public scala.Function1 tupled();
  Signature: ()Lscala/Function1;
  Code:
   Stack=1, Locals=1, Args_size=1
	aload_0
	invokestatic	Method scala/Function5$class.tupled:(Lscala/Function5;)Lscala/Function1;
	areturn
  Labels:

public scala.runtime.AbstractFunction5();
  Signature: ()V
  Code:
   Stack=1, Locals=1, Args_size=1
	aload_0
	invokespecial	Method java/lang/Object."<init>":()V
	aload_0
	invokestatic	Method scala/Function5$class.$init$:(Lscala/Function5;)V
	return
  Labels:
  Signature: length = 0x2
   00 19 

}

