Compiled from "AbstractFunction22.scala"
public abstract class scala.runtime.AbstractFunction22 extends java.lang.Object implements scala.Function22,scala.ScalaObject
  SourceFile: "AbstractFunction22.scala"
  ScalaSig: length = 0x3
   05 00 00 
  Signature: length = 0x2
   00 24 
  RuntimeVisibleAnnotations: length = 0xB
   00 01 00 25 00 01 00 26 73 00 27 
  minor version: 0
  major version: 49
  Constant pool:
Asciz	SourceFile;
Asciz	AbstractFunction22.scala;
Asciz	toString;
Asciz	()Ljava/lang/String;;
Asciz	Code;
Asciz	LineNumberTable;
Asciz	scala/Function22$class;
class	scala/Function22$class
Asciz	(Lscala/Function22;)Ljava/lang/String;;
NameAndType	toString:(Lscala/Function22;)Ljava/lang/String;
Method	scala/Function22$class.toString:(Lscala/Function22;)Ljava/lang/String;
Asciz	curried;
Asciz	()Lscala/Function1;;
Asciz	(Lscala/Function22;)Lscala/Function1;;
NameAndType	curried:(Lscala/Function22;)Lscala/Function1;
Method	scala/Function22$class.curried:(Lscala/Function22;)Lscala/Function1;
Asciz	curry;
NameAndType	curry:(Lscala/Function22;)Lscala/Function1;
Method	scala/Function22$class.curry:(Lscala/Function22;)Lscala/Function1;
Asciz	Deprecated;
Asciz	tupled;
NameAndType	tupled:(Lscala/Function22;)Lscala/Function1;
Method	scala/Function22$class.tupled:(Lscala/Function22;)Lscala/Function1;
Asciz	<init>;
Asciz	()V;
Asciz	java/lang/Object;
class	java/lang/Object
NameAndType	"<init>":()V
Method	java/lang/Object."<init>":()V
Asciz	$init$;
Asciz	(Lscala/Function22;)V;
NameAndType	$init$:(Lscala/Function22;)V
Method	scala/Function22$class.$init$:(Lscala/Function22;)V
Asciz	Signature;
Asciz	ScalaSig;
Asciz	<T1:Ljava/lang/Object;T2:Ljava/lang/Object;T3:Ljava/lang/Object;T4:Ljava/lang/Object;T5:Ljava/lang/Object;T6:Ljava/lang/Object;T7:Ljava/lang/Object;T8:Ljava/lang/Object;T9:Ljava/lang/Object;T10:Ljava/lang/Object;T11:Ljava/lang/Object;T12:Ljava/lang/Object;T13:Ljava/lang/Object;T14:Ljava/lang/Object;T15:Ljava/lang/Object;T16:Ljava/lang/Object;T17:Ljava/lang/Object;T18:Ljava/lang/Object;T19:Ljava/lang/Object;T20:Ljava/lang/Object;T21:Ljava/lang/Object;T22:Ljava/lang/Object;R:Ljava/lang/Object;>Ljava/lang/Object;Lscala/Function22<TT1;TT2;TT3;TT4;TT5;TT6;TT7;TT8;TT9;TT10;TT11;TT12;TT13;TT14;TT15;TT16;TT17;TT18;TT19;TT20;TT21;TT22;TR;>;Lscala/ScalaObject;;
Asciz	Lscala/reflect/ScalaSignature;;
Asciz	bytes;
Asciz	)4Q!!#2tiJ7\r$v]$n83e)1BeVtG/[7f)!B:dC27A]\tCe\n.aM2P C\"[e*+X5v7\n#\t\"AC-Q!D\t1gn!!.<b\t2BPE*,7\r\t%M)e\t*Y=TO?;%*)T-fcv,D\t!BAGk:G/[8oeI\"AF\rACDUcE!$\t%mI!9{G[5oOB!CH?1!8z!\t1#\tR1\t!&IAQCDUgAac\n\tQ!\t#b3\tA\t-)\"b#\r!)V\"AF9A!ECe!YDC\tE)A\rQ;C4\t!!\"A\tI\"A+9!\t1b8\tR1\t!sA!CDAUcA\"AuA!ECe1V2!\t1rA\tR1\r!G\r\t-\t#b#\r!)FCF\t!1\"A\tI\"a+2iAa\t!\t#b3\tA+MYYE'\tE)A\rQdAq\nCDAUc]\"AF)IA!ECe1V9!\t1BV\tR1\r!'\t-]##\r!)JC[\t!Y\"A\tI\"a+3cAa#\t=!\t#b3\tAK\rYGC1\t%)A\rI\"AE2\n$!aC*dC2wJ6fGRDQAaP5oSRtD#53%QI'S1z#'<}#uIS'Q'ZKFlX;
Asciz	RuntimeVisibleAnnotations;
Asciz	scala/runtime/AbstractFunction22;
class	scala/runtime/AbstractFunction22
Asciz	scala/Function22;
class	scala/Function22
Asciz	scala/ScalaObject;
class	scala/ScalaObject

{
public java.lang.String toString();
  Signature: ()Ljava/lang/String;
  Code:
   Stack=1, Locals=1, Args_size=1
	aload_0
	invokestatic	Method scala/Function22$class.toString:(Lscala/Function22;)Ljava/lang/String;
	areturn
  Labels:

public scala.Function1 curried();
  Signature: ()Lscala/Function1;
  Code:
   Stack=1, Locals=1, Args_size=1
	aload_0
	invokestatic	Method scala/Function22$class.curried:(Lscala/Function22;)Lscala/Function1;
	areturn
  Labels:

public scala.Function1 curry();
  Signature: ()Lscala/Function1;
  Code:
   Stack=1, Locals=1, Args_size=1
	aload_0
	invokestatic	Method scala/Function22$class.curry:(Lscala/Function22;)Lscala/Function1;
	areturn
  Labels:
  Deprecated: true

public scala.Function1 tupled();
  Signature: ()Lscala/Function1;
  Code:
   Stack=1, Locals=1, Args_size=1
	aload_0
	invokestatic	Method scala/Function22$class.tupled:(Lscala/Function22;)Lscala/Function1;
	areturn
  Labels:

public scala.runtime.AbstractFunction22();
  Signature: ()V
  Code:
   Stack=1, Locals=1, Args_size=1
	aload_0
	invokespecial	Method java/lang/Object."<init>":()V
	aload_0
	invokestatic	Method scala/Function22$class.$init$:(Lscala/Function22;)V
	return
  Labels:
  Signature: length = 0x2
   00 19 

}

