Compiled from "AbstractFunction.scala"
public abstract class scala.runtime.AbstractFunction17 extends java.lang.Object implements scala.Function17,scala.ScalaObject
  SourceFile: "AbstractFunction.scala"
  Signature: length = 0x2
   00 1F 
  ScalaSig: length = 0x250
   05 00 5B 06 05 01 02 FFFFFF81 00 07 02 12 41 62 73 74
   72 61 63 74 46 75 6E 63 74 69 6F 6E 31 37 0A 02
   03 04 01 07 72 75 6E 74 69 6D 65 0A 01 05 01 05
   73 63 61 6C 61 03 00 15 13 08 17 21 24 27 2A 2D
   30 33 36 39 3C 3F 42 45 48 4B 4E 51 13 04 00 09
   11 53 10 02 0A 0F 0D 01 0B 0A 02 0C 0D 01 04 6C
   61 6E 67 0A 01 0E 01 04 6A 61 76 61 09 02 10 0B
   02 06 4F 62 6A 65 63 74 10 14 12 13 15 20 23 26
   29 2C 2F 32 35 38 3B 3E 41 44 47 4A 4D 50 0D 01
   04 09 02 14 04 02 0A 46 75 6E 63 74 69 6F 6E 31
   37 10 02 16 17 0C 00 04 08 18 00 FFFFFF84 FFFFFF80 FFFFFF88 FFFFFFC2 00
   19 02 02 54 31 11 02 1A 1D 10 02 12 1B 09 02 1C
   04 02 07 4E 6F 74 68 69 6E 67 10 02 12 1E 09 02
   1F 04 02 03 41 6E 79 10 02 16 21 04 08 22 00 FFFFFF84
   FFFFFF80 FFFFFF88 FFFFFFC2 00 19 02 02 54 32 10 02 16 24 04 08 25
   00 FFFFFF84 FFFFFF80 FFFFFF88 FFFFFFC2 00 19 02 02 54 33 10 02 16 27 04
   08 28 00 FFFFFF84 FFFFFF80 FFFFFF88 FFFFFFC2 00 19 02 02 54 34 10 02 16
   2A 04 08 2B 00 FFFFFF84 FFFFFF80 FFFFFF88 FFFFFFC2 00 19 02 02 54 35 10
   02 16 2D 04 08 2E 00 FFFFFF84 FFFFFF80 FFFFFF88 FFFFFFC2 00 19 02 02 54
   36 10 02 16 30 04 08 31 00 FFFFFF84 FFFFFF80 FFFFFF88 FFFFFFC2 00 19 02
   02 54 37 10 02 16 33 04 08 34 00 FFFFFF84 FFFFFF80 FFFFFF88 FFFFFFC2 00
   19 02 02 54 38 10 02 16 36 04 08 37 00 FFFFFF84 FFFFFF80 FFFFFF88
   FFFFFFC2 00 19 02 02 54 39 10 02 16 39 04 08 3A 00 FFFFFF84
   FFFFFF80 FFFFFF88 FFFFFFC2 00 19 02 03 54 31 30 10 02 16 3C 04 08
   3D 00 FFFFFF84 FFFFFF80 FFFFFF88 FFFFFFC2 00 19 02 03 54 31 31 10 02 16
   3F 04 08 40 00 FFFFFF84 FFFFFF80 FFFFFF88 FFFFFFC2 00 19 02 03 54 31 32
   10 02 16 42 04 08 43 00 FFFFFF84 FFFFFF80 FFFFFF88 FFFFFFC2 00 19 02 03
   54 31 33 10 02 16 45 04 08 46 00 FFFFFF84 FFFFFF80 FFFFFF88 FFFFFFC2 00
   19 02 03 54 31 34 10 02 16 48 04 08 49 00 FFFFFF84 FFFFFF80
   FFFFFF88 FFFFFFC2 00 19 02 03 54 31 35 10 02 16 4B 04 08 4C
   00 FFFFFF84 FFFFFF80 FFFFFF88 FFFFFFC2 00 19 02 03 54 31 36 10 02 16 4E
   04 08 4F 00 FFFFFF84 FFFFFF80 FFFFFF88 FFFFFFC2 00 19 02 03 54 31 37 10
   02 16 51 04 08 52 00 FFFFFF84 FFFFFF80 FFFFFF84 FFFFFFC2 00 19 02 01 52
   10 02 12 54 09 02 55 04 02 0B 53 63 61 6C 61 4F
   62 6A 65 63 74 08 05 57 00 FFFFFF84 00 58 01 06 3C 69
   6E 69 74 3E 14 01 59 10 14 5A 00 15 20 23 26 29
   2C 2F 32 35 38 3B 3E 41 44 47 4A 4D 50 0D 01 02
   
  minor version: 0
  major version: 49
  Constant pool:
const #1 = Asciz	SourceFile;
const #2 = Asciz	AbstractFunction.scala;
const #3 = Asciz	<init>;
const #4 = Asciz	()V;
const #5 = Asciz	Code;
const #6 = Asciz	LineNumberTable;
const #7 = Asciz	java/lang/Object;
const #8 = class	#7;	//  java/lang/Object
const #9 = NameAndType	#3:#4;//  "<init>":()V
const #10 = Method	#8.#9;	//  java/lang/Object."<init>":()V
const #11 = Asciz	scala/Function17$class;
const #12 = class	#11;	//  scala/Function17$class
const #13 = Asciz	$init$;
const #14 = Asciz	(Lscala/Function17;)V;
const #15 = NameAndType	#13:#14;//  $init$:(Lscala/Function17;)V
const #16 = Method	#12.#15;	//  scala/Function17$class.$init$:(Lscala/Function17;)V
const #17 = Asciz	Signature;
const #18 = Asciz	tuple;
const #19 = Asciz	()Lscala/Function1;;
const #20 = Asciz	(Lscala/Function17;)Lscala/Function1;;
const #21 = NameAndType	#18:#20;//  tuple:(Lscala/Function17;)Lscala/Function1;
const #22 = Method	#12.#21;	//  scala/Function17$class.tuple:(Lscala/Function17;)Lscala/Function1;
const #23 = Asciz	curry;
const #24 = NameAndType	#23:#20;//  curry:(Lscala/Function17;)Lscala/Function1;
const #25 = Method	#12.#24;	//  scala/Function17$class.curry:(Lscala/Function17;)Lscala/Function1;
const #26 = Asciz	toString;
const #27 = Asciz	()Ljava/lang/String;;
const #28 = Asciz	(Lscala/Function17;)Ljava/lang/String;;
const #29 = NameAndType	#26:#28;//  toString:(Lscala/Function17;)Ljava/lang/String;
const #30 = Method	#12.#29;	//  scala/Function17$class.toString:(Lscala/Function17;)Ljava/lang/String;
const #31 = Asciz	<T1:Ljava/lang/Object;T2:Ljava/lang/Object;T3:Ljava/lang/Object;T4:Ljava/lang/Object;T5:Ljava/lang/Object;T6:Ljava/lang/Object;T7:Ljava/lang/Object;T8:Ljava/lang/Object;T9:Ljava/lang/Object;T10:Ljava/lang/Object;T11:Ljava/lang/Object;T12:Ljava/lang/Object;T13:Ljava/lang/Object;T14:Ljava/lang/Object;T15:Ljava/lang/Object;T16:Ljava/lang/Object;T17:Ljava/lang/Object;R:Ljava/lang/Object;>Ljava/lang/Object;Lscala/Function17<TT1;TT2;TT3;TT4;TT5;TT6;TT7;TT8;TT9;TT10;TT11;TT12;TT13;TT14;TT15;TT16;TT17;TR;>;Lscala/ScalaObject;;
const #32 = Asciz	ScalaSig;
const #33 = Asciz	scala/runtime/AbstractFunction17;
const #34 = class	#33;	//  scala/runtime/AbstractFunction17
const #35 = Asciz	scala/Function17;
const #36 = class	#35;	//  scala/Function17
const #37 = Asciz	scala/ScalaObject;
const #38 = class	#37;	//  scala/ScalaObject

{
public scala.runtime.AbstractFunction17();
  Code:
   Stack=1, Locals=1, Args_size=1
   0:	aload_0
   1:	invokespecial	#10; //Method java/lang/Object."<init>":()V
   4:	aload_0
   5:	invokestatic	#16; //Method scala/Function17$class.$init$:(Lscala/Function17;)V
   8:	return
  LineNumberTable: 
   line 28: 0

  Signature: length = 0x2
   00 04 

public scala.Function1 tuple();
  Code:
   Stack=1, Locals=1, Args_size=1
   0:	aload_0
   1:	invokestatic	#22; //Method scala/Function17$class.tuple:(Lscala/Function17;)Lscala/Function1;
   4:	areturn
  LineNumberTable: 
   line 28: 0


public scala.Function1 curry();
  Code:
   Stack=1, Locals=1, Args_size=1
   0:	aload_0
   1:	invokestatic	#25; //Method scala/Function17$class.curry:(Lscala/Function17;)Lscala/Function1;
   4:	areturn
  LineNumberTable: 
   line 28: 0


public java.lang.String toString();
  Code:
   Stack=1, Locals=1, Args_size=1
   0:	aload_0
   1:	invokestatic	#30; //Method scala/Function17$class.toString:(Lscala/Function17;)Ljava/lang/String;
   4:	areturn
  LineNumberTable: 
   line 28: 0


}

