Compiled from "BoxedShortArray.scala"
public final class scala.runtime.BoxedShortArray extends scala.runtime.BoxedArray implements java.io.Serializable
  ScalaSig: length = 0x26F
   04 01 68 06 08 01 02 FFFFFF84 FFFFFF80 FFFFFF80 FFFFFF80 02 07 02 0F 42
   6F 78 65 64 53 68 6F 72 74 41 72 72 61 79 0A 02
   03 04 01 07 72 75 6E 74 69 6D 65 0A 01 05 01 05
   73 63 61 6C 61 03 00 13 03 00 08 0C 10 02 09 0A
   0D 01 02 09 02 0B 02 02 0A 42 6F 78 65 64 41 72
   72 61 79 10 02 0D 0E 0D 01 04 09 02 0F 04 02 0B
   53 63 61 6C 61 4F 62 6A 65 63 74 08 08 11 00 FFFFFF82
   FFFFFFC2 FFFFFF80 FFFFFF84 00 12 01 05 76 61 6C 75 65 15 01 13 10
   03 0D 14 16 09 02 15 04 02 05 41 72 72 61 79 10
   02 0D 17 09 02 18 04 02 05 53 68 6F 72 74 08 08
   1A 00 FFFFFF82 FFFFFF80 FFFFFFA0 FFFFFF80 04 13 01 06 76 61 6C 75 65 20
   08 05 1C 00 FFFFFF84 00 1D 01 06 3C 69 6E 69 74 3E 14
   02 1E 13 10 02 09 00 08 05 20 00 FFFFFF84 00 21 01 06
   6C 65 6E 67 74 68 15 01 22 10 02 0D 23 09 02 24
   04 02 03 49 6E 74 08 05 26 00 FFFFFF84 00 27 01 05 61
   70 70 6C 79 14 02 28 22 10 02 0D 29 09 02 2A 04
   02 03 41 6E 79 08 05 2C 00 FFFFFF84 00 2D 01 06 75 70
   64 61 74 65 14 03 2E 22 28 10 02 0D 2F 09 02 30
   04 02 04 55 6E 69 74 08 05 32 00 FFFFFF84 00 33 01 05
   75 6E 62 6F 78 14 02 34 37 10 02 0D 35 09 02 36
   04 02 06 41 6E 79 52 65 66 10 02 38 3B 0E 02 0D
   39 09 02 3A 04 01 06 50 72 65 64 65 66 09 02 3C
   3D 02 06 53 74 72 69 6E 67 0A 02 3A 04 08 05 32
   00 FFFFFF84 00 3F 14 02 34 40 30 02 41 46 10 03 38 42
   44 09 02 43 3D 02 05 43 6C 61 73 73 10 02 45 46
   0C 00 04 08 47 3E FFFFFF84 FFFFFF80 FFFFFF80 FFFFFF82 00 48 02 03 5F 24
   31 11 02 49 28 10 02 0D 4A 09 02 4B 04 02 07 4E
   6F 74 68 69 6E 67 08 05 4D 00 FFFFFF84 20 4E 01 06 65
   71 75 61 6C 73 14 02 4F 28 10 02 0D 50 09 02 51
   04 02 07 42 6F 6F 6C 65 61 6E 08 05 53 00 FFFFFF84 20
   54 01 08 68 61 73 68 43 6F 64 65 14 01 22 08 05
   56 00 FFFFFF84 00 57 01 08 73 75 62 41 72 72 61 79 14
   03 13 22 22 08 05 59 00 FFFFFF84 22 5A 01 06 66 69 6C
   74 65 72 14 02 08 5B 10 04 0D 5C 28 4F 09 02 5D
   04 02 09 46 75 6E 63 74 69 6F 6E 31 08 05 5F 00
   FFFFFF84 28 60 01 08 6E 65 77 41 72 72 61 79 14 03 1E
   22 61 10 03 0D 62 28 09 02 63 04 02 08 49 74 65
   72 61 74 6F 72 28 02 00 65 10 02 0D 66 09 02 67
   04 02 0C 73 65 72 69 61 6C 69 7A 61 62 6C 65 
  SourceFile: "BoxedShortArray.scala"
  minor version: 0
  major version: 49
  Constant pool:
class	java/io/Serializable
class	java/lang/Object
class	scala/runtime/BoxedArray
class	scala/runtime/BoxedShortArray
class	scala/runtime/BoxesRunTime
Field	scala/runtime/BoxedShortArray.value:[S
Method	java/lang/Object.hashCode:()I
Method	scala/runtime/BoxedArray."<init>":()V
Method	scala/runtime/BoxedShortArray.apply:(I)Ljava/lang/Object;
Method	scala/runtime/BoxedShortArray.value:()[S
Method	scala/runtime/BoxesRunTime.boxToShort:(S)Ljava/lang/Short;
Method	scala/runtime/BoxesRunTime.unboxToInt:(Ljava/lang/Object;)I
NameAndType	"<init>":()V
NameAndType	apply:(I)Ljava/lang/Object;
NameAndType	boxToShort:(S)Ljava/lang/Short;
NameAndType	hashCode:()I
NameAndType	unboxToInt:(Ljava/lang/Object;)I
NameAndType	value:()[S
NameAndType	value:[S
Asciz	()I;
Asciz	()V;
Asciz	()[S;
Asciz	(I)Ljava/lang/Object;;
Asciz	(Ljava/lang/Class;)Ljava/lang/Object;;
Asciz	(Ljava/lang/Class<*>;)Ljava/lang/Object;;
Asciz	(Ljava/lang/Object;)I;
Asciz	(Ljava/lang/Object;)Ljava/lang/Object;;
Asciz	(Ljava/lang/Object;)Z;
Asciz	(S)Ljava/lang/Short;;
Asciz	([S)V;
Asciz	<init>;
Asciz	BoxedShortArray.scala;
Asciz	Code;
Asciz	I;
Asciz	LineNumberTable;
Asciz	Ljava/lang/Class;;
Asciz	Ljava/lang/Object;;
Asciz	LocalVariableTable;
Asciz	Lscala/runtime/BoxedShortArray;;
Asciz	ScalaSig;
Asciz	Signature;
Asciz	SourceFile;
Asciz	[S;
Asciz	apply;
Asciz	boxToShort;
Asciz	elemClass;
Asciz	equals;
Asciz	hashCode;
Asciz	index;
Asciz	java/io/Serializable;
Asciz	java/lang/Object;
Asciz	length;
Asciz	other;
Asciz	scala/runtime/BoxedArray;
Asciz	scala/runtime/BoxedShortArray;
Asciz	scala/runtime/BoxesRunTime;
Asciz	this;
Asciz	unbox;
Asciz	unboxToInt;
Asciz	value;
Asciz	x$1;

{
private final short[] value;
  Signature: [S

public scala.runtime.BoxedShortArray(short[]);
  Signature: ([S)V
  Code:
   Stack=2, Locals=2, Args_size=2
	aload_0
	aload_1
	putfield	Field value:[S
	aload_0
	invokespecial	Method scala/runtime/BoxedArray."<init>":()V
	return
  Labels:
  LocalVariableTable: 
   Start  Length  Slot  Name   Signature
   0      10      0    this       Lscala/runtime/BoxedShortArray;
   0      10      1    value       [S


public java.lang.Object apply(java.lang.Object);
  Signature: (Ljava/lang/Object;)Ljava/lang/Object;
  Code:
   Stack=2, Locals=2, Args_size=2
	aload_0
	aload_1
	invokestatic	Method scala/runtime/BoxesRunTime.unboxToInt:(Ljava/lang/Object;)I
	invokevirtual	Method apply:(I)Ljava/lang/Object;
	areturn
  Labels:
  LocalVariableTable: 
   Start  Length  Slot  Name   Signature
   0      9      0    this       Lscala/runtime/BoxedShortArray;
   0      9      1    x$1       Ljava/lang/Object;


public int hashCode();
  Signature: ()I
  Code:
   Stack=1, Locals=1, Args_size=1
	aload_0
	invokevirtual	Method value:()[S
	invokevirtual	Method java/lang/Object.hashCode:()I
	ireturn
  Labels:

public boolean equals(java.lang.Object);
  Signature: (Ljava/lang/Object;)Z
  Code:
   Stack=2, Locals=2, Args_size=2
	aload_0
	invokevirtual	Method value:()[S
	aload_1
	if_acmpeq	l1 // iconst_1
	aload_1
	instanceof	class scala/runtime/BoxedShortArray
	ifeq	l2 // iconst_0
	aload_0
	invokevirtual	Method value:()[S
	aload_1
	checkcast	class scala/runtime/BoxedShortArray
	invokevirtual	Method value:()[S
	if_acmpne	l2 // iconst_0
l1	iconst_1
	goto	l3 // ireturn
l2	iconst_0
l3	ireturn
  Labels:
   	l1 = 29 // iconst_1
   	l2 = 33 // iconst_0
   	l3 = 34 // ireturn
  LocalVariableTable: 
   Start  Length  Slot  Name   Signature
   0      35      0    this       Lscala/runtime/BoxedShortArray;
   0      35      1    other       Ljava/lang/Object;


public java.lang.Object unbox(java.lang.Class);
  Signature: (Ljava/lang/Class;)Ljava/lang/Object;
  Code:
   Stack=1, Locals=2, Args_size=2
	aload_0
	invokevirtual	Method value:()[S
	areturn
  Labels:
  LocalVariableTable: 
   Start  Length  Slot  Name   Signature
   0      5      0    this       Lscala/runtime/BoxedShortArray;
   0      5      1    elemClass       Ljava/lang/Class;

  Signature: length = 0x2
   00 19 

public java.lang.Object apply(int);
  Signature: (I)Ljava/lang/Object;
  Code:
   Stack=2, Locals=2, Args_size=2
	aload_0
	invokevirtual	Method value:()[S
	iload_1
	saload
	invokestatic	Method scala/runtime/BoxesRunTime.boxToShort:(S)Ljava/lang/Short;
	areturn
  Labels:
  LocalVariableTable: 
   Start  Length  Slot  Name   Signature
   0      10      0    this       Lscala/runtime/BoxedShortArray;
   0      10      1    index       I


public int length();
  Signature: ()I
  Code:
   Stack=1, Locals=1, Args_size=1
	aload_0
	invokevirtual	Method value:()[S
	arraylength
	ireturn
  Labels:

public short[] value();
  Signature: ()[S
  Code:
   Stack=1, Locals=1, Args_size=1
	aload_0
	getfield	Field value:[S
	areturn
  Labels:

}

