Compiled from "BoxedObjectArray.scala"
public final class scala.runtime.BoxedObjectArray extends scala.runtime.BoxedArray implements scala.ScalaObject,java.io.Serializable
  SourceFile: "BoxedObjectArray.scala"
  Signature: length = 0x2
   00 72 
  ScalaSig: length = 0x281
   05 00 6B 06 04 01 02 02 07 02 10 42 6F 78 65 64
   4F 62 6A 65 63 74 41 72 72 61 79 0A 02 03 04 01
   07 72 75 6E 74 69 6D 65 0A 01 05 01 05 73 63 61
   6C 61 03 00 15 02 08 0F 13 03 00 09 19 10 03 0A
   0B 0D 0D 01 02 09 02 0C 02 02 0A 42 6F 78 65 64
   41 72 72 61 79 10 02 0E 0F 0C 00 04 08 10 00 FFFFFF84
   FFFFFF80 FFFFFF80 FFFFFFC2 00 11 02 01 41 11 02 12 16 10 02 13 14
   0D 01 04 09 02 15 04 02 07 4E 6F 74 68 69 6E 67
   10 02 13 17 09 02 18 04 02 06 41 6E 79 52 65 66
   10 02 13 1A 09 02 1B 04 02 0B 53 63 61 6C 61 4F
   62 6A 65 63 74 08 08 1D 00 FFFFFF82 FFFFFFC2 FFFFFF80 FFFFFF84 00 1E 01
   05 76 61 6C 75 65 15 01 1F 10 03 13 20 16 09 02
   21 04 02 05 41 72 72 61 79 08 08 23 00 FFFFFF82 FFFFFF80 FFFFFFA0
   FFFFFF80 04 1F 01 06 76 61 6C 75 65 20 08 05 25 00 FFFFFF84
   00 26 01 06 3C 69 6E 69 74 3E 14 02 27 28 10 03
   0A 00 0D 08 05 1D 24 FFFFFFC0 00 1F 08 05 2A 00 FFFFFF84 00
   2B 01 06 6C 65 6E 67 74 68 15 01 2C 10 02 13 2D
   09 02 2E 04 02 03 49 6E 74 08 05 30 00 FFFFFF84 00 31
   01 05 61 70 70 6C 79 14 02 0D 32 08 05 33 2F FFFFFFC0
   00 2C 01 05 69 6E 64 65 78 08 05 35 00 FFFFFF84 00 36
   01 06 75 70 64 61 74 65 14 03 37 3A 3B 10 02 13
   38 09 02 39 04 02 04 55 6E 69 74 08 05 33 34 FFFFFFC0
   00 2C 08 05 3C 34 FFFFFFC0 00 0D 01 04 65 6C 65 6D 08
   05 3E 00 FFFFFF84 00 3F 01 05 75 6E 62 6F 78 14 02 16
   40 08 05 41 3D FFFFFFC0 00 42 01 07 65 6C 65 6D 54 61
   67 10 02 43 46 0E 02 13 44 09 02 45 04 01 06 50
   72 65 64 65 66 09 02 47 48 02 06 53 74 72 69 6E
   67 0A 02 45 04 08 05 3E 00 FFFFFF84 00 4A 14 02 16 4B
   08 05 4C 49 FFFFFFC0 00 4D 01 09 65 6C 65 6D 43 6C 61
   73 73 30 02 4E 52 10 03 43 4F 51 09 02 50 48 02
   05 43 6C 61 73 73 10 02 0E 52 04 08 53 00 FFFFFF84 FFFFFF80
   FFFFFF80 FFFFFF82 00 54 02 03 5F 24 31 11 02 12 55 10 02 13
   56 09 02 57 04 02 03 41 6E 79 08 05 59 00 FFFFFF84 04
   5A 01 06 63 72 65 61 74 65 14 02 1F 5B 08 05 2A
   58 FFFFFFC0 00 2C 08 05 5D 00 FFFFFF84 22 5E 01 06 66 69 6C
   74 65 72 14 02 09 5F 08 05 60 5C FFFFFFC0 00 61 01 01
   70 10 04 13 62 0D 64 09 02 63 04 02 09 46 75 6E
   63 74 69 6F 6E 31 10 02 13 65 09 02 66 04 02 07
   42 6F 6F 6C 65 61 6E 28 02 00 68 10 02 13 69 09
   02 6A 04 02 0C 73 65 72 69 61 6C 69 7A 61 62 6C
   65 
  minor version: 0
  major version: 49
  Constant pool:
const #1 = Asciz	SourceFile;
const #2 = Asciz	BoxedObjectArray.scala;
const #3 = Asciz	value;
const #4 = Asciz	[Ljava/lang/Object;;
const #5 = Asciz	<init>;
const #6 = Asciz	([Ljava/lang/Object;)V;
const #7 = Asciz	Code;
const #8 = Asciz	LineNumberTable;
const #9 = Asciz	scala/runtime/BoxedObjectArray;
const #10 = class	#9;	//  scala/runtime/BoxedObjectArray
const #11 = NameAndType	#3:#4;//  value:[Ljava/lang/Object;
const #12 = Field	#10.#11;	//  scala/runtime/BoxedObjectArray.value:[Ljava/lang/Object;
const #13 = Asciz	scala/runtime/BoxedArray;
const #14 = class	#13;	//  scala/runtime/BoxedArray
const #15 = Asciz	()V;
const #16 = NameAndType	#5:#15;//  "<init>":()V
const #17 = Method	#14.#16;	//  scala/runtime/BoxedArray."<init>":()V
const #18 = Asciz	this;
const #19 = Asciz	Lscala/runtime/BoxedObjectArray;;
const #20 = Asciz	LocalVariableTable;
const #21 = Asciz	Signature;
const #22 = Asciz	()Ljava/lang/Object;;
const #23 = Asciz	()[Ljava/lang/Object;;
const #24 = NameAndType	#3:#23;//  value:()[Ljava/lang/Object;
const #25 = Method	#10.#24;	//  scala/runtime/BoxedObjectArray.value:()[Ljava/lang/Object;
const #26 = Asciz	apply;
const #27 = Asciz	(Ljava/lang/Object;)Ljava/lang/Object;;
const #28 = Asciz	scala/runtime/BoxesRunTime;
const #29 = class	#28;	//  scala/runtime/BoxesRunTime
const #30 = Asciz	unboxToInt;
const #31 = Asciz	(Ljava/lang/Object;)I;
const #32 = NameAndType	#30:#31;//  unboxToInt:(Ljava/lang/Object;)I
const #33 = Method	#29.#32;	//  scala/runtime/BoxesRunTime.unboxToInt:(Ljava/lang/Object;)I
const #34 = Asciz	(I)Ljava/lang/Object;;
const #35 = NameAndType	#26:#34;//  apply:(I)Ljava/lang/Object;
const #36 = Method	#10.#35;	//  scala/runtime/BoxedObjectArray.apply:(I)Ljava/lang/Object;
const #37 = Asciz	v1;
const #38 = Asciz	Ljava/lang/Object;;
const #39 = Asciz	filter;
const #40 = Asciz	(Lscala/Function1;)Lscala/collection/generic/TraversableTemplate;;
const #41 = Asciz	(Lscala/Function1;)Lscala/runtime/BoxedArray;;
const #42 = NameAndType	#39:#41;//  filter:(Lscala/Function1;)Lscala/runtime/BoxedArray;
const #43 = Method	#10.#42;	//  scala/runtime/BoxedObjectArray.filter:(Lscala/Function1;)Lscala/runtime/BoxedArray;
const #44 = Asciz	p;
const #45 = Asciz	Lscala/Function1;;
const #46 = Asciz	scala/Function1;
const #47 = class	#46;	//  scala/Function1
const #48 = NameAndType	#26:#27;//  apply:(Ljava/lang/Object;)Ljava/lang/Object;
const #49 = InterfaceMethod	#47.#48;	//  scala/Function1.apply:(Ljava/lang/Object;)Ljava/lang/Object;
const #50 = Asciz	unboxToBoolean;
const #51 = Asciz	(Ljava/lang/Object;)Z;
const #52 = NameAndType	#50:#51;//  unboxToBoolean:(Ljava/lang/Object;)Z
const #53 = Method	#29.#52;	//  scala/runtime/BoxesRunTime.unboxToBoolean:(Ljava/lang/Object;)Z
const #54 = Asciz	create;
const #55 = Asciz	(I)[Ljava/lang/Object;;
const #56 = NameAndType	#54:#55;//  create:(I)[Ljava/lang/Object;
const #57 = Method	#10.#56;	//  scala/runtime/BoxedObjectArray.create:(I)[Ljava/lang/Object;
const #58 = NameAndType	#5:#6;//  "<init>":([Ljava/lang/Object;)V
const #59 = Method	#10.#58;	//  scala/runtime/BoxedObjectArray."<init>":([Ljava/lang/Object;)V
const #60 = Asciz	include;
const #61 = Asciz	[Z;
const #62 = Asciz	len;
const #63 = Asciz	I;
const #64 = Asciz	i;
const #65 = Asciz	result;
const #66 = Asciz	(Lscala/Function1<TA;Ljava/lang/Boolean;>;)Lscala/runtime/BoxedArray<TA;>;;
const #67 = Asciz	scala/compat/Platform$;
const #68 = class	#67;	//  scala/compat/Platform$
const #69 = Asciz	MODULE$;
const #70 = Asciz	Lscala/compat/Platform$;;
const #71 = NameAndType	#69:#70;//  MODULE$:Lscala/compat/Platform$;
const #72 = Field	#68.#71;	//  scala/compat/Platform$.MODULE$:Lscala/compat/Platform$;
const #73 = Asciz	java/lang/Object;
const #74 = class	#73;	//  java/lang/Object
const #75 = Asciz	getClass;
const #76 = Asciz	()Ljava/lang/Class;;
const #77 = NameAndType	#75:#76;//  getClass:()Ljava/lang/Class;
const #78 = Method	#74.#77;	//  java/lang/Object.getClass:()Ljava/lang/Class;
const #79 = Asciz	java/lang/Class;
const #80 = class	#79;	//  java/lang/Class
const #81 = Asciz	getComponentType;
const #82 = NameAndType	#81:#76;//  getComponentType:()Ljava/lang/Class;
const #83 = Method	#80.#82;	//  java/lang/Class.getComponentType:()Ljava/lang/Class;
const #84 = Asciz	createArray;
const #85 = Asciz	(Ljava/lang/Class;I)Ljava/lang/Object;;
const #86 = NameAndType	#84:#85;//  createArray:(Ljava/lang/Class;I)Ljava/lang/Object;
const #87 = Method	#68.#86;	//  scala/compat/Platform$.createArray:(Ljava/lang/Class;I)Ljava/lang/Object;
const #88 = Asciz	scala/runtime/ScalaRunTime$;
const #89 = class	#88;	//  scala/runtime/ScalaRunTime$
const #90 = Asciz	Lscala/runtime/ScalaRunTime$;;
const #91 = NameAndType	#69:#90;//  MODULE$:Lscala/runtime/ScalaRunTime$;
const #92 = Field	#89.#91;	//  scala/runtime/ScalaRunTime$.MODULE$:Lscala/runtime/ScalaRunTime$;
const #93 = Asciz	arrayValue;
const #94 = Asciz	(Lscala/runtime/BoxedArray;Ljava/lang/Class;)Ljava/lang/Object;;
const #95 = NameAndType	#93:#94;//  arrayValue:(Lscala/runtime/BoxedArray;Ljava/lang/Class;)Ljava/lang/Object;
const #96 = Method	#89.#95;	//  scala/runtime/ScalaRunTime$.arrayValue:(Lscala/runtime/BoxedArray;Ljava/lang/Class;)Ljava/lang/Object;
const #97 = class	#4;	//  "[Ljava/lang/Object;"
const #98 = Asciz	length;
const #99 = Asciz	unbox;
const #100 = Asciz	(Ljava/lang/Class;)Ljava/lang/Object;;
const #101 = Asciz	elemClass;
const #102 = Asciz	Ljava/lang/Class;;
const #103 = Asciz	(Ljava/lang/Class<*>;)Ljava/lang/Object;;
const #104 = Asciz	(Ljava/lang/String;)Ljava/lang/Object;;
const #105 = Asciz	elemTag;
const #106 = Asciz	Ljava/lang/String;;
const #107 = Asciz	update;
const #108 = Asciz	(ILjava/lang/Object;)V;
const #109 = Asciz	index;
const #110 = Asciz	elem;
const #111 = Asciz	(ITA;)V;
const #112 = Asciz	(I)TA;;
const #113 = Asciz	()I;
const #114 = Asciz	<A:Ljava/lang/Object;>Lscala/runtime/BoxedArray<TA;>;Lscala/ScalaObject;;
const #115 = Asciz	ScalaSig;
const #116 = Asciz	scala/ScalaObject;
const #117 = class	#116;	//  scala/ScalaObject
const #118 = Asciz	java/io/Serializable;
const #119 = class	#118;	//  java/io/Serializable

{
public scala.runtime.BoxedObjectArray(java.lang.Object[]);
  Code:
   Stack=2, Locals=2, Args_size=2
   0:	aload_0
   1:	aload_1
   2:	putfield	#12; //Field value:[Ljava/lang/Object;
   5:	aload_0
   6:	invokespecial	#17; //Method scala/runtime/BoxedArray."<init>":()V
   9:	return
  LineNumberTable: 
   line 19: 0

  LocalVariableTable: 
   Start  Length  Slot  Name   Signature
   0      10      0    this       Lscala/runtime/BoxedObjectArray;
   0      10      1    value       [Ljava/lang/Object;

  Signature: length = 0x2
   00 06 

public java.lang.Object value();
  Code:
   Stack=1, Locals=1, Args_size=1
   0:	aload_0
   1:	invokevirtual	#25; //Method value:()[Ljava/lang/Object;
   4:	areturn
  LineNumberTable: 
   line 19: 0


public java.lang.Object apply(java.lang.Object);
  Code:
   Stack=2, Locals=2, Args_size=2
   0:	aload_0
   1:	aload_1
   2:	invokestatic	#33; //Method scala/runtime/BoxesRunTime.unboxToInt:(Ljava/lang/Object;)I
   5:	invokevirtual	#36; //Method apply:(I)Ljava/lang/Object;
   8:	areturn
  LineNumberTable: 
   line 19: 0

  LocalVariableTable: 
   Start  Length  Slot  Name   Signature
   0      9      0    this       Lscala/runtime/BoxedObjectArray;
   0      9      1    v1       Ljava/lang/Object;


public final scala.collection.generic.TraversableTemplate filter(scala.Function1);
  Code:
   Stack=2, Locals=2, Args_size=2
   0:	aload_0
   1:	aload_1
   2:	invokevirtual	#43; //Method filter:(Lscala/Function1;)Lscala/runtime/BoxedArray;
   5:	areturn
  LineNumberTable: 
   line 19: 0

  LocalVariableTable: 
   Start  Length  Slot  Name   Signature
   0      6      0    this       Lscala/runtime/BoxedObjectArray;
   0      6      1    p       Lscala/Function1;


public final scala.runtime.BoxedArray filter(scala.Function1);
  Code:
   Stack=4, Locals=6, Args_size=2
   0:	aload_0
   1:	invokevirtual	#25; //Method value:()[Ljava/lang/Object;
   4:	arraylength
   5:	newarray boolean
   7:	astore_2
   8:	iconst_0
   9:	istore_3
   10:	iconst_0
   11:	istore	4
   13:	iload	4
   15:	aload_0
   16:	invokevirtual	#25; //Method value:()[Ljava/lang/Object;
   19:	arraylength
   20:	if_icmpge	60
   23:	aload_1
   24:	aload_0
   25:	invokevirtual	#25; //Method value:()[Ljava/lang/Object;
   28:	iload	4
   30:	aaload
   31:	invokeinterface	#49,  2; //InterfaceMethod scala/Function1.apply:(Ljava/lang/Object;)Ljava/lang/Object;
   36:	invokestatic	#53; //Method scala/runtime/BoxesRunTime.unboxToBoolean:(Ljava/lang/Object;)Z
   39:	ifeq	51
   42:	aload_2
   43:	iload	4
   45:	iconst_1
   46:	bastore
   47:	iload_3
   48:	iconst_1
   49:	iadd
   50:	istore_3
   51:	iload	4
   53:	iconst_1
   54:	iadd
   55:	istore	4
   57:	goto	13
   60:	aload_0
   61:	iload_3
   62:	invokespecial	#57; //Method create:(I)[Ljava/lang/Object;
   65:	astore	5
   67:	iconst_0
   68:	istore_3
   69:	iconst_0
   70:	istore	4
   72:	iload_3
   73:	aload	5
   75:	arraylength
   76:	if_icmpge	110
   79:	aload_2
   80:	iload	4
   82:	baload
   83:	ifeq	101
   86:	aload	5
   88:	iload_3
   89:	aload_0
   90:	invokevirtual	#25; //Method value:()[Ljava/lang/Object;
   93:	iload	4
   95:	aaload
   96:	aastore
   97:	iload_3
   98:	iconst_1
   99:	iadd
   100:	istore_3
   101:	iload	4
   103:	iconst_1
   104:	iadd
   105:	istore	4
   107:	goto	72
   110:	new	#10; //class scala/runtime/BoxedObjectArray
   113:	dup
   114:	aload	5
   116:	invokespecial	#59; //Method "<init>":([Ljava/lang/Object;)V
   119:	areturn
  LineNumberTable: 
   line 45: 0
   line 46: 8
   line 47: 10
   line 48: 13
   line 49: 23
   line 50: 51
   line 48: 57
   line 52: 60
   line 53: 67
   line 54: 69
   line 55: 72
   line 56: 79
   line 57: 101
   line 55: 107
   line 59: 110

  LocalVariableTable: 
   Start  Length  Slot  Name   Signature
   0      120      0    this       Lscala/runtime/BoxedObjectArray;
   0      120      1    p       Lscala/Function1;
   8      111      2    include       [Z
   10      109      3    len       I
   13      106      4    i       I
   67      52      5    result       [Ljava/lang/Object;

  Signature: length = 0x2
   00 42 

public java.lang.Object unbox(java.lang.Class);
  Code:
   Stack=1, Locals=2, Args_size=2
   0:	aload_0
   1:	invokevirtual	#25; //Method value:()[Ljava/lang/Object;
   4:	areturn
  LineNumberTable: 
   line 30: 0

  LocalVariableTable: 
   Start  Length  Slot  Name   Signature
   0      5      0    this       Lscala/runtime/BoxedObjectArray;
   0      5      1    elemClass       Ljava/lang/Class;

  Signature: length = 0x2
   00 67 

public java.lang.Object unbox(java.lang.String);
  Code:
   Stack=1, Locals=2, Args_size=2
   0:	aload_0
   1:	invokevirtual	#25; //Method value:()[Ljava/lang/Object;
   4:	areturn
  LineNumberTable: 
   line 29: 0

  LocalVariableTable: 
   Start  Length  Slot  Name   Signature
   0      5      0    this       Lscala/runtime/BoxedObjectArray;
   0      5      1    elemTag       Ljava/lang/String;


public void update(int, java.lang.Object);
  Code:
   Stack=3, Locals=3, Args_size=3
   0:	aload_0
   1:	invokevirtual	#25; //Method value:()[Ljava/lang/Object;
   4:	iload_1
   5:	aload_2
   6:	aastore
   7:	return
  LineNumberTable: 
   line 26: 0

  LocalVariableTable: 
   Start  Length  Slot  Name   Signature
   0      8      0    this       Lscala/runtime/BoxedObjectArray;
   0      8      1    index       I
   0      8      2    elem       Ljava/lang/Object;

  Signature: length = 0x2
   00 6F 

public java.lang.Object apply(int);
  Code:
   Stack=2, Locals=2, Args_size=2
   0:	aload_0
   1:	invokevirtual	#25; //Method value:()[Ljava/lang/Object;
   4:	iload_1
   5:	aaload
   6:	areturn
  LineNumberTable: 
   line 23: 0

  LocalVariableTable: 
   Start  Length  Slot  Name   Signature
   0      7      0    this       Lscala/runtime/BoxedObjectArray;
   0      7      1    index       I

  Signature: length = 0x2
   00 70 

public int length();
  Code:
   Stack=1, Locals=1, Args_size=1
   0:	aload_0
   1:	invokevirtual	#25; //Method value:()[Ljava/lang/Object;
   4:	arraylength
   5:	ireturn
  LineNumberTable: 
   line 21: 0


public java.lang.Object[] value();
  Code:
   Stack=1, Locals=1, Args_size=1
   0:	aload_0
   1:	getfield	#12; //Field value:[Ljava/lang/Object;
   4:	areturn
  LineNumberTable: 
   line 19: 0


}

