Compiled from "BoxedAnyArray.scala"
public final class scala.runtime.BoxedAnyArray extends scala.runtime.BoxedArray implements scala.ScalaObject,java.io.Serializable
  SourceFile: "BoxedAnyArray.scala"
  Signature: length = 0x2
   01 4A 
  ScalaSig: length = 0x41A
   05 00 FFFFFF81 1E 06 04 01 02 02 07 02 0D 42 6F 78 65
   64 41 6E 79 41 72 72 61 79 0A 02 03 04 01 07 72
   75 6E 74 69 6D 65 0A 01 05 01 05 73 63 61 6C 61
   03 00 15 02 08 0F 13 03 00 09 19 10 03 0A 0B 0D
   0D 01 02 09 02 0C 02 02 0A 42 6F 78 65 64 41 72
   72 61 79 10 02 0E 0F 0C 00 04 08 10 00 FFFFFF84 FFFFFF80 FFFFFF80
   FFFFFFC2 00 11 02 01 41 11 02 12 16 10 02 13 14 0D 01
   04 09 02 15 04 02 07 4E 6F 74 68 69 6E 67 10 02
   13 17 09 02 18 04 02 03 41 6E 79 10 02 13 1A 09
   02 1B 04 02 0B 53 63 61 6C 61 4F 62 6A 65 63 74
   08 08 1D 00 FFFFFF82 FFFFFFC2 FFFFFF80 FFFFFF84 00 1E 01 06 6C 65 6E 67
   74 68 15 01 1F 10 02 13 20 09 02 21 04 02 03 49
   6E 74 08 08 23 00 FFFFFF82 FFFFFF80 FFFFFFA0 FFFFFF80 04 1F 01 07 6C 65
   6E 67 74 68 20 08 05 25 00 FFFFFF84 00 26 01 06 3C 69
   6E 69 74 3E 14 02 27 28 10 03 0A 00 0D 08 05 1D
   24 FFFFFFC0 00 1F 08 07 2A 00 FFFFFFC0 FFFFFF80 FFFFFF84 04 2B 01 05 62
   6F 78 65 64 15 01 2C 10 03 13 2D 2F 09 02 2E 04
   02 05 41 72 72 61 79 10 02 13 30 09 02 31 04 02
   06 41 6E 79 52 65 66 08 07 33 00 FFFFFFC0 FFFFFF80 FFFFFF84 04 34
   01 09 62 6F 78 65 64 5F 24 65 71 14 02 35 38 10
   02 13 36 09 02 37 04 02 04 55 6E 69 74 08 07 39
   32 FFFFFF81 FFFFFF80 FFFFFFC0 00 2C 01 03 78 24 31 08 06 3B 00 FFFFFFA0
   FFFFFFA0 04 2C 01 06 62 6F 78 65 64 20 08 07 3D 00 FFFFFFC0
   FFFFFF80 FFFFFF84 04 3E 01 07 75 6E 62 6F 78 65 64 15 01 2F
   08 07 40 00 FFFFFFC0 FFFFFF80 FFFFFF84 04 41 01 0B 75 6E 62 6F 78
   65 64 5F 24 65 71 14 02 35 42 08 07 39 3F FFFFFF81 FFFFFF80
   FFFFFFC0 00 2F 08 06 44 00 FFFFFFA0 FFFFFFA0 04 2F 01 08 75 6E 62
   6F 78 65 64 20 08 07 46 00 FFFFFFC0 FFFFFF80 FFFFFF84 04 47 01 09
   65 6C 65 6D 43 6C 61 73 73 15 01 48 30 02 49 51
   10 03 4A 4D 50 0E 02 13 4B 09 02 4C 04 01 06 50
   72 65 64 65 66 09 02 4E 4F 02 05 43 6C 61 73 73
   0A 02 4C 04 10 02 0E 51 04 08 52 00 FFFFFF84 FFFFFF80 FFFFFF80 FFFFFF82
   00 11 02 03 5F 24 31 08 07 54 00 FFFFFFC0 FFFFFF80 FFFFFF84 04 55
   01 0D 65 6C 65 6D 43 6C 61 73 73 5F 24 65 71 14
   02 35 56 08 07 39 53 FFFFFF81 FFFFFF80 FFFFFFC0 00 57 30 02 58 5A
   10 03 4A 4D 59 10 02 0E 5A 04 08 52 00 FFFFFF84 FFFFFF80 FFFFFF80
   FFFFFF82 00 11 08 06 5C 00 FFFFFFA0 FFFFFFA0 04 5D 01 0A 65 6C 65
   6D 43 6C 61 73 73 20 30 02 5E 60 10 03 4A 4D 5F
   10 02 0E 60 04 08 52 00 FFFFFF84 FFFFFF80 FFFFFF80 FFFFFF82 00 11 08 05
   62 00 FFFFFF84 00 63 01 05 61 70 70 6C 79 14 02 0D 64
   08 05 65 61 FFFFFFC0 00 1F 01 05 69 6E 64 65 78 08 05
   67 00 FFFFFF84 00 68 01 06 75 70 64 61 74 65 14 03 35
   69 6A 08 05 65 66 FFFFFFC0 00 1F 08 05 6B 66 FFFFFFC0 00 0D
   01 05 5F 65 6C 65 6D 08 05 6D 00 FFFFFF84 00 6E 01 05
   75 6E 62 6F 78 14 02 2F 6F 08 05 46 6C FFFFFFC0 00 70
   30 02 71 73 10 03 4A 4D 72 10 02 0E 73 04 08 74
   00 FFFFFF84 FFFFFF80 FFFFFF80 FFFFFF82 00 11 02 03 5F 24 32 08 05 76 00
   FFFFFF84 00 3E 01 05 76 61 6C 75 65 08 05 78 00 FFFFFF84 04
   79 01 05 61 64 61 70 74 14 02 2F 7A 08 05 7B 77
   FFFFFFC0 00 2F 01 05 6F 74 68 65 72 08 05 7D 00 FFFFFF84 20
   7E 01 08 63 6F 70 79 46 72 6F 6D 14 08 35 7F FFFFFF81
   01 FFFFFF81 03 FFFFFF81 05 08 06 FFFFFF81 00 7C FFFFFFC0 00 2F 01 03 73
   72 63 08 06 FFFFFF81 02 7C FFFFFFC0 00 1F 01 04 66 72 6F 6D
   08 06 FFFFFF81 04 7C FFFFFFC0 00 1F 01 02 74 6F 08 06 FFFFFF81 06
   7C FFFFFFC0 00 1F 01 03 6C 65 6E 08 07 FFFFFF81 08 00 FFFFFF84 20
   FFFFFF81 09 01 06 63 6F 70 79 54 6F 14 09 35 FFFFFF81 0A FFFFFF81
   0B FFFFFF81 0D FFFFFF81 0E 08 07 FFFFFF81 02 FFFFFF81 07 FFFFFFC0 00 1F 08 07
   FFFFFF81 0C FFFFFF81 07 FFFFFFC0 00 2F 01 04 64 65 73 74 08 07 FFFFFF81
   04 FFFFFF81 07 FFFFFFC0 00 1F 08 07 FFFFFF81 06 FFFFFF81 07 FFFFFFC0 00 1F 08
   07 FFFFFF81 10 00 FFFFFF84 22 FFFFFF81 11 01 06 66 69 6C 74 65 72
   14 03 09 FFFFFF81 12 08 08 FFFFFF81 13 FFFFFF81 0F FFFFFFC0 00 FFFFFF81 14 01
   01 70 10 06 13 FFFFFF81 15 0D FFFFFF81 17 09 03 FFFFFF81 16 04 02
   09 46 75 6E 63 74 69 6F 6E 31 10 03 13 FFFFFF81 18 09
   03 FFFFFF81 19 04 02 07 42 6F 6F 6C 65 61 6E 28 03 00
   FFFFFF81 1B 10 03 13 FFFFFF81 1C 09 03 FFFFFF81 1D 04 02 0C 73 65
   72 69 61 6C 69 7A 61 62 6C 65 
  minor version: 0
  major version: 49
  Constant pool:
const #1 = Asciz	SourceFile;
const #2 = Asciz	BoxedAnyArray.scala;
const #3 = Asciz	elemClass;
const #4 = Asciz	Ljava/lang/Class;;
const #5 = Asciz	Ljava/lang/Class<*>;;
const #6 = Asciz	Signature;
const #7 = Asciz	unboxed;
const #8 = Asciz	Ljava/lang/Object;;
const #9 = Asciz	boxed;
const #10 = Asciz	[Ljava/lang/Object;;
const #11 = Asciz	length;
const #12 = Asciz	I;
const #13 = Asciz	<init>;
const #14 = Asciz	(I)V;
const #15 = Asciz	Code;
const #16 = Asciz	LineNumberTable;
const #17 = Asciz	scala/runtime/BoxedAnyArray;
const #18 = class	#17;	//  scala/runtime/BoxedAnyArray
const #19 = NameAndType	#11:#12;//  length:I
const #20 = Field	#18.#19;	//  scala/runtime/BoxedAnyArray.length:I
const #21 = Asciz	scala/runtime/BoxedArray;
const #22 = class	#21;	//  scala/runtime/BoxedArray
const #23 = Asciz	()V;
const #24 = NameAndType	#13:#23;//  "<init>":()V
const #25 = Method	#22.#24;	//  scala/runtime/BoxedArray."<init>":()V
const #26 = Asciz	java/lang/Object;
const #27 = class	#26;	//  java/lang/Object
const #28 = NameAndType	#9:#10;//  boxed:[Ljava/lang/Object;
const #29 = Field	#18.#28;	//  scala/runtime/BoxedAnyArray.boxed:[Ljava/lang/Object;
const #30 = NameAndType	#7:#8;//  unboxed:Ljava/lang/Object;
const #31 = Field	#18.#30;	//  scala/runtime/BoxedAnyArray.unboxed:Ljava/lang/Object;
const #32 = NameAndType	#3:#4;//  elemClass:Ljava/lang/Class;
const #33 = Field	#18.#32;	//  scala/runtime/BoxedAnyArray.elemClass:Ljava/lang/Class;
const #34 = Asciz	this;
const #35 = Asciz	Lscala/runtime/BoxedAnyArray;;
const #36 = Asciz	LocalVariableTable;
const #37 = Asciz	apply;
const #38 = Asciz	(Ljava/lang/Object;)Ljava/lang/Object;;
const #39 = Asciz	scala/runtime/BoxesRunTime;
const #40 = class	#39;	//  scala/runtime/BoxesRunTime
const #41 = Asciz	unboxToInt;
const #42 = Asciz	(Ljava/lang/Object;)I;
const #43 = NameAndType	#41:#42;//  unboxToInt:(Ljava/lang/Object;)I
const #44 = Method	#40.#43;	//  scala/runtime/BoxesRunTime.unboxToInt:(Ljava/lang/Object;)I
const #45 = Asciz	(I)Ljava/lang/Object;;
const #46 = NameAndType	#37:#45;//  apply:(I)Ljava/lang/Object;
const #47 = Method	#18.#46;	//  scala/runtime/BoxedAnyArray.apply:(I)Ljava/lang/Object;
const #48 = Asciz	v1;
const #49 = Asciz	filter;
const #50 = Asciz	(Lscala/Function1;)Lscala/collection/generic/TraversableTemplate;;
const #51 = Asciz	(Lscala/Function1;)Lscala/runtime/BoxedArray;;
const #52 = NameAndType	#49:#51;//  filter:(Lscala/Function1;)Lscala/runtime/BoxedArray;
const #53 = Method	#18.#52;	//  scala/runtime/BoxedAnyArray.filter:(Lscala/Function1;)Lscala/runtime/BoxedArray;
const #54 = Asciz	p;
const #55 = Asciz	Lscala/Function1;;
const #56 = Asciz	countAndMemo;
const #57 = Asciz	(Lscala/Function1;)Lscala/Tuple2;;
const #58 = NameAndType	#56:#57;//  countAndMemo:(Lscala/Function1;)Lscala/Tuple2;
const #59 = Method	#18.#58;	//  scala/runtime/BoxedAnyArray.countAndMemo:(Lscala/Function1;)Lscala/Tuple2;
const #60 = Asciz	scala/Tuple2;
const #61 = class	#60;	//  scala/Tuple2
const #62 = Asciz	_1;
const #63 = Asciz	()Ljava/lang/Object;;
const #64 = NameAndType	#62:#63;//  _1:()Ljava/lang/Object;
const #65 = Method	#61.#64;	//  scala/Tuple2._1:()Ljava/lang/Object;
const #66 = Asciz	_2;
const #67 = NameAndType	#66:#63;//  _2:()Ljava/lang/Object;
const #68 = Method	#61.#67;	//  scala/Tuple2._2:()Ljava/lang/Object;
const #69 = Asciz	scala/runtime/ScalaRunTime$;
const #70 = class	#69;	//  scala/runtime/ScalaRunTime$
const #71 = Asciz	MODULE$;
const #72 = Asciz	Lscala/runtime/ScalaRunTime$;;
const #73 = NameAndType	#71:#72;//  MODULE$:Lscala/runtime/ScalaRunTime$;
const #74 = Field	#70.#73;	//  scala/runtime/ScalaRunTime$.MODULE$:Lscala/runtime/ScalaRunTime$;
const #75 = Asciz	java/lang/Boolean;
const #76 = class	#75;	//  java/lang/Boolean
const #77 = Asciz	TYPE;
const #78 = NameAndType	#77:#4;//  TYPE:Ljava/lang/Class;
const #79 = Field	#76.#78;	//  java/lang/Boolean.TYPE:Ljava/lang/Class;
const #80 = Asciz	arrayValue;
const #81 = Asciz	(Lscala/runtime/BoxedArray;Ljava/lang/Class;)Ljava/lang/Object;;
const #82 = NameAndType	#80:#81;//  arrayValue:(Lscala/runtime/BoxedArray;Ljava/lang/Class;)Ljava/lang/Object;
const #83 = Method	#70.#82;	//  scala/runtime/ScalaRunTime$.arrayValue:(Lscala/runtime/BoxedArray;Ljava/lang/Class;)Ljava/lang/Object;
const #84 = Asciz	[Z;
const #85 = class	#84;	//  "[Z"
const #86 = Asciz	boxToInteger;
const #87 = Asciz	(I)Ljava/lang/Integer;;
const #88 = NameAndType	#86:#87;//  boxToInteger:(I)Ljava/lang/Integer;
const #89 = Method	#40.#88;	//  scala/runtime/BoxesRunTime.boxToInteger:(I)Ljava/lang/Integer;
const #90 = Asciz	(Ljava/lang/Object;Ljava/lang/Object;)V;
const #91 = NameAndType	#13:#90;//  "<init>":(Ljava/lang/Object;Ljava/lang/Object;)V
const #92 = Method	#61.#91;	//  scala/Tuple2."<init>":(Ljava/lang/Object;Ljava/lang/Object;)V
const #93 = NameAndType	#13:#14;//  "<init>":(I)V
const #94 = Method	#18.#93;	//  scala/runtime/BoxedAnyArray."<init>":(I)V
const #95 = Asciz	update;
const #96 = Asciz	(ILjava/lang/Object;)V;
const #97 = NameAndType	#95:#96;//  update:(ILjava/lang/Object;)V
const #98 = Method	#18.#97;	//  scala/runtime/BoxedAnyArray.update:(ILjava/lang/Object;)V
const #99 = Asciz	scala/MatchError;
const #100 = class	#99;	//  scala/MatchError
const #101 = Asciz	toString;
const #102 = Asciz	()Ljava/lang/String;;
const #103 = NameAndType	#101:#102;//  toString:()Ljava/lang/String;
const #104 = Method	#61.#103;	//  scala/Tuple2.toString:()Ljava/lang/String;
const #105 = Asciz	(Ljava/lang/String;)V;
const #106 = NameAndType	#13:#105;//  "<init>":(Ljava/lang/String;)V
const #107 = Method	#100.#106;	//  scala/MatchError."<init>":(Ljava/lang/String;)V
const #108 = Asciz	temp17;
const #109 = Asciz	Lscala/Tuple2;;
const #110 = Asciz	temp18;
const #111 = Asciz	temp19;
const #112 = Asciz	include;
const #113 = Asciz	len;
const #114 = Asciz	result;
const #115 = Asciz	i;
const #116 = Asciz	j;
const #117 = Asciz	(Lscala/Function1<TA;Ljava/lang/Boolean;>;)Lscala/runtime/BoxedArray<TA;>;;
const #118 = Asciz	copyTo;
const #119 = Asciz	(ILjava/lang/Object;II)V;
const #120 = Asciz	adapt;
const #121 = NameAndType	#120:#38;//  adapt:(Ljava/lang/Object;)Ljava/lang/Object;
const #122 = Method	#18.#121;	//  scala/runtime/BoxedAnyArray.adapt:(Ljava/lang/Object;)Ljava/lang/Object;
const #123 = Asciz	scala/Array$;
const #124 = class	#123;	//  scala/Array$
const #125 = Asciz	Lscala/Array$;;
const #126 = NameAndType	#71:#125;//  MODULE$:Lscala/Array$;
const #127 = Field	#124.#126;	//  scala/Array$.MODULE$:Lscala/Array$;
const #128 = NameAndType	#7:#63;//  unboxed:()Ljava/lang/Object;
const #129 = Method	#18.#128;	//  scala/runtime/BoxedAnyArray.unboxed:()Ljava/lang/Object;
const #130 = Asciz	()[Ljava/lang/Object;;
const #131 = NameAndType	#9:#130;//  boxed:()[Ljava/lang/Object;
const #132 = Method	#18.#131;	//  scala/runtime/BoxedAnyArray.boxed:()[Ljava/lang/Object;
const #133 = Asciz	copy;
const #134 = Asciz	(Ljava/lang/Object;ILjava/lang/Object;II)V;
const #135 = NameAndType	#133:#134;//  copy:(Ljava/lang/Object;ILjava/lang/Object;II)V
const #136 = Method	#124.#135;	//  scala/Array$.copy:(Ljava/lang/Object;ILjava/lang/Object;II)V
const #137 = Asciz	from;
const #138 = Asciz	dest;
const #139 = Asciz	to;
const #140 = Asciz	dest1;
const #141 = Asciz	copyFrom;
const #142 = Asciz	(Ljava/lang/Object;III)V;
const #143 = Asciz	src;
const #144 = Asciz	src1;
const #145 = Asciz	()Ljava/lang/Class;;
const #146 = NameAndType	#3:#145;//  elemClass:()Ljava/lang/Class;
const #147 = Method	#18.#146;	//  scala/runtime/BoxedAnyArray.elemClass:()Ljava/lang/Class;
const #148 = Asciz	isValueClass;
const #149 = Asciz	(Ljava/lang/Class;)Z;
const #150 = NameAndType	#148:#149;//  isValueClass:(Ljava/lang/Class;)Z
const #151 = Method	#70.#150;	//  scala/runtime/ScalaRunTime$.isValueClass:(Ljava/lang/Class;)Z
const #152 = Asciz	unbox;
const #153 = Asciz	(Ljava/lang/Class;)Ljava/lang/Object;;
const #154 = NameAndType	#152:#153;//  unbox:(Ljava/lang/Class;)Ljava/lang/Object;
const #155 = Method	#18.#154;	//  scala/runtime/BoxedAnyArray.unbox:(Ljava/lang/Class;)Ljava/lang/Object;
const #156 = Asciz	scala/runtime/BoxedUnit;
const #157 = class	#156;	//  scala/runtime/BoxedUnit
const #158 = Asciz	UNIT;
const #159 = Asciz	Lscala/runtime/BoxedUnit;;
const #160 = NameAndType	#158:#159;//  UNIT:Lscala/runtime/BoxedUnit;
const #161 = Field	#157.#160;	//  scala/runtime/BoxedUnit.UNIT:Lscala/runtime/BoxedUnit;
const #162 = Asciz	value;
const #163 = NameAndType	#162:#63;//  value:()Ljava/lang/Object;
const #164 = Method	#22.#163;	//  scala/runtime/BoxedArray.value:()Ljava/lang/Object;
const #165 = Asciz	[I;
const #166 = class	#165;	//  "[I"
const #167 = Asciz	java/lang/Integer;
const #168 = class	#167;	//  java/lang/Integer
const #169 = Field	#168.#78;	//  java/lang/Integer.TYPE:Ljava/lang/Class;
const #170 = Asciz	[D;
const #171 = class	#170;	//  "[D"
const #172 = Asciz	java/lang/Double;
const #173 = class	#172;	//  java/lang/Double
const #174 = Field	#173.#78;	//  java/lang/Double.TYPE:Ljava/lang/Class;
const #175 = Asciz	[F;
const #176 = class	#175;	//  "[F"
const #177 = Asciz	java/lang/Float;
const #178 = class	#177;	//  java/lang/Float
const #179 = Field	#178.#78;	//  java/lang/Float.TYPE:Ljava/lang/Class;
const #180 = Asciz	[J;
const #181 = class	#180;	//  "[J"
const #182 = Asciz	java/lang/Long;
const #183 = class	#182;	//  java/lang/Long
const #184 = Field	#183.#78;	//  java/lang/Long.TYPE:Ljava/lang/Class;
const #185 = Asciz	[C;
const #186 = class	#185;	//  "[C"
const #187 = Asciz	java/lang/Character;
const #188 = class	#187;	//  java/lang/Character
const #189 = Field	#188.#78;	//  java/lang/Character.TYPE:Ljava/lang/Class;
const #190 = Asciz	[S;
const #191 = class	#190;	//  "[S"
const #192 = Asciz	java/lang/Short;
const #193 = class	#192;	//  java/lang/Short
const #194 = Field	#193.#78;	//  java/lang/Short.TYPE:Ljava/lang/Class;
const #195 = Asciz	[B;
const #196 = class	#195;	//  "[B"
const #197 = Asciz	java/lang/Byte;
const #198 = class	#197;	//  java/lang/Byte
const #199 = Field	#198.#78;	//  java/lang/Byte.TYPE:Ljava/lang/Class;
const #200 = Asciz	other;
const #201 = Asciz	temp3;
const #202 = Asciz	temp4;
const #203 = Asciz	that;
const #204 = Asciz	temp5;
const #205 = Asciz	Lscala/runtime/BoxedArray;;
const #206 = Asciz	temp6;
const #207 = Asciz	temp7;
const #208 = Asciz	temp8;
const #209 = Asciz	temp9;
const #210 = Asciz	temp10;
const #211 = Asciz	temp11;
const #212 = Asciz	temp12;
const #213 = Asciz	temp13;
const #214 = Asciz	temp14;
const #215 = Asciz	temp15;
const #216 = Asciz	temp16;
const #217 = Asciz	scala/NotDefinedError;
const #218 = class	#217;	//  scala/NotDefinedError
const #219 = Asciz	BoxedAnyArray.value;
const #220 = String	#219;	//  BoxedAnyArray.value
const #221 = Method	#218.#106;	//  scala/NotDefinedError."<init>":(Ljava/lang/String;)V
const #222 = Asciz	elemClass_$eq;
const #223 = Asciz	(Ljava/lang/Class;)V;
const #224 = NameAndType	#222:#223;//  elemClass_$eq:(Ljava/lang/Class;)V
const #225 = Method	#18.#224;	//  scala/runtime/BoxedAnyArray.elemClass_$eq:(Ljava/lang/Class;)V
const #226 = Asciz	()I;
const #227 = NameAndType	#11:#226;//  length:()I
const #228 = Method	#18.#227;	//  scala/runtime/BoxedAnyArray.length:()I
const #229 = Asciz	unboxed_$eq;
const #230 = Asciz	(Ljava/lang/Object;)V;
const #231 = NameAndType	#229:#230;//  unboxed_$eq:(Ljava/lang/Object;)V
const #232 = Method	#18.#231;	//  scala/runtime/BoxedAnyArray.unboxed_$eq:(Ljava/lang/Object;)V
const #233 = Asciz	unboxToDouble;
const #234 = Asciz	(Ljava/lang/Object;)D;
const #235 = NameAndType	#233:#234;//  unboxToDouble:(Ljava/lang/Object;)D
const #236 = Method	#40.#235;	//  scala/runtime/BoxesRunTime.unboxToDouble:(Ljava/lang/Object;)D
const #237 = Asciz	unboxToFloat;
const #238 = Asciz	(Ljava/lang/Object;)F;
const #239 = NameAndType	#237:#238;//  unboxToFloat:(Ljava/lang/Object;)F
const #240 = Method	#40.#239;	//  scala/runtime/BoxesRunTime.unboxToFloat:(Ljava/lang/Object;)F
const #241 = Asciz	unboxToLong;
const #242 = Asciz	(Ljava/lang/Object;)J;
const #243 = NameAndType	#241:#242;//  unboxToLong:(Ljava/lang/Object;)J
const #244 = Method	#40.#243;	//  scala/runtime/BoxesRunTime.unboxToLong:(Ljava/lang/Object;)J
const #245 = Asciz	unboxToChar;
const #246 = Asciz	(Ljava/lang/Object;)C;
const #247 = NameAndType	#245:#246;//  unboxToChar:(Ljava/lang/Object;)C
const #248 = Method	#40.#247;	//  scala/runtime/BoxesRunTime.unboxToChar:(Ljava/lang/Object;)C
const #249 = Asciz	unboxToByte;
const #250 = Asciz	(Ljava/lang/Object;)B;
const #251 = NameAndType	#249:#250;//  unboxToByte:(Ljava/lang/Object;)B
const #252 = Method	#40.#251;	//  scala/runtime/BoxesRunTime.unboxToByte:(Ljava/lang/Object;)B
const #253 = Asciz	unboxToShort;
const #254 = Asciz	(Ljava/lang/Object;)S;
const #255 = NameAndType	#253:#254;//  unboxToShort:(Ljava/lang/Object;)S
const #256 = Method	#40.#255;	//  scala/runtime/BoxesRunTime.unboxToShort:(Ljava/lang/Object;)S
const #257 = Asciz	unboxToBoolean;
const #258 = Asciz	(Ljava/lang/Object;)Z;
const #259 = NameAndType	#257:#258;//  unboxToBoolean:(Ljava/lang/Object;)Z
const #260 = Method	#40.#259;	//  scala/runtime/BoxesRunTime.unboxToBoolean:(Ljava/lang/Object;)Z
const #261 = Asciz	equals;
const #262 = NameAndType	#261:#258;//  equals:(Ljava/lang/Object;)Z
const #263 = Method	#27.#262;	//  java/lang/Object.equals:(Ljava/lang/Object;)Z
const #264 = Asciz	scala/compat/Platform$;
const #265 = class	#264;	//  scala/compat/Platform$
const #266 = Asciz	Lscala/compat/Platform$;;
const #267 = NameAndType	#71:#266;//  MODULE$:Lscala/compat/Platform$;
const #268 = Field	#265.#267;	//  scala/compat/Platform$.MODULE$:Lscala/compat/Platform$;
const #269 = Asciz	createArray;
const #270 = Asciz	(Ljava/lang/Class;I)Ljava/lang/Object;;
const #271 = NameAndType	#269:#270;//  createArray:(Ljava/lang/Class;I)Ljava/lang/Object;
const #272 = Method	#265.#271;	//  scala/compat/Platform$.createArray:(Ljava/lang/Class;I)Ljava/lang/Object;
const #273 = Asciz	java/lang/Class;
const #274 = class	#273;	//  java/lang/Class
const #275 = Asciz	isArray;
const #276 = Asciz	()Z;
const #277 = NameAndType	#275:#276;//  isArray:()Z
const #278 = Method	#274.#277;	//  java/lang/Class.isArray:()Z
const #279 = Asciz	getComponentType;
const #280 = NameAndType	#279:#145;//  getComponentType:()Ljava/lang/Class;
const #281 = Method	#274.#280;	//  java/lang/Class.getComponentType:()Ljava/lang/Class;
const #282 = Method	#22.#154;	//  scala/runtime/BoxedArray.unbox:(Ljava/lang/Class;)Ljava/lang/Object;
const #283 = Asciz	arraycopy;
const #284 = NameAndType	#283:#134;//  arraycopy:(Ljava/lang/Object;ILjava/lang/Object;II)V
const #285 = Method	#265.#284;	//  scala/compat/Platform$.arraycopy:(Ljava/lang/Object;ILjava/lang/Object;II)V
const #286 = Asciz	boxed_$eq;
const #287 = Asciz	([Ljava/lang/Object;)V;
const #288 = NameAndType	#286:#287;//  boxed_$eq:([Ljava/lang/Object;)V
const #289 = Method	#18.#288;	//  scala/runtime/BoxedAnyArray.boxed_$eq:([Ljava/lang/Object;)V
const #290 = Asciz	newvalue;
const #291 = Asciz	temp1;
const #292 = Asciz	temp2;
const #293 = Asciz	(Ljava/lang/Class<*>;)Ljava/lang/Object;;
const #294 = class	#10;	//  "[Ljava/lang/Object;"
const #295 = Asciz	index;
const #296 = Asciz	_elem;
const #297 = Asciz	elem;
const #298 = Asciz	(ITA;)V;
const #299 = Asciz	boxToDouble;
const #300 = Asciz	(D)Ljava/lang/Double;;
const #301 = NameAndType	#299:#300;//  boxToDouble:(D)Ljava/lang/Double;
const #302 = Method	#40.#301;	//  scala/runtime/BoxesRunTime.boxToDouble:(D)Ljava/lang/Double;
const #303 = Asciz	boxToFloat;
const #304 = Asciz	(F)Ljava/lang/Float;;
const #305 = NameAndType	#303:#304;//  boxToFloat:(F)Ljava/lang/Float;
const #306 = Method	#40.#305;	//  scala/runtime/BoxesRunTime.boxToFloat:(F)Ljava/lang/Float;
const #307 = Asciz	boxToLong;
const #308 = Asciz	(J)Ljava/lang/Long;;
const #309 = NameAndType	#307:#308;//  boxToLong:(J)Ljava/lang/Long;
const #310 = Method	#40.#309;	//  scala/runtime/BoxesRunTime.boxToLong:(J)Ljava/lang/Long;
const #311 = Asciz	boxToCharacter;
const #312 = Asciz	(C)Ljava/lang/Character;;
const #313 = NameAndType	#311:#312;//  boxToCharacter:(C)Ljava/lang/Character;
const #314 = Method	#40.#313;	//  scala/runtime/BoxesRunTime.boxToCharacter:(C)Ljava/lang/Character;
const #315 = Asciz	boxToByte;
const #316 = Asciz	(B)Ljava/lang/Byte;;
const #317 = NameAndType	#315:#316;//  boxToByte:(B)Ljava/lang/Byte;
const #318 = Method	#40.#317;	//  scala/runtime/BoxesRunTime.boxToByte:(B)Ljava/lang/Byte;
const #319 = Asciz	boxToShort;
const #320 = Asciz	(S)Ljava/lang/Short;;
const #321 = NameAndType	#319:#320;//  boxToShort:(S)Ljava/lang/Short;
const #322 = Method	#40.#321;	//  scala/runtime/BoxesRunTime.boxToShort:(S)Ljava/lang/Short;
const #323 = Asciz	boxToBoolean;
const #324 = Asciz	(Z)Ljava/lang/Boolean;;
const #325 = NameAndType	#323:#324;//  boxToBoolean:(Z)Ljava/lang/Boolean;
const #326 = Method	#40.#325;	//  scala/runtime/BoxesRunTime.boxToBoolean:(Z)Ljava/lang/Boolean;
const #327 = Asciz	(I)TA;;
const #328 = Asciz	(Ljava/lang/Class<*>;)V;
const #329 = Asciz	()Ljava/lang/Class<*>;;
const #330 = Asciz	<A:Ljava/lang/Object;>Lscala/runtime/BoxedArray<TA;>;Lscala/ScalaObject;;
const #331 = Asciz	ScalaSig;
const #332 = Asciz	scala/ScalaObject;
const #333 = class	#332;	//  scala/ScalaObject
const #334 = Asciz	java/io/Serializable;
const #335 = class	#334;	//  java/io/Serializable

{
public scala.runtime.BoxedAnyArray(int);
  Code:
   Stack=2, Locals=2, Args_size=2
   0:	aload_0
   1:	iload_1
   2:	putfield	#20; //Field length:I
   5:	aload_0
   6:	invokespecial	#25; //Method scala/runtime/BoxedArray."<init>":()V
   9:	aload_0
   10:	iload_1
   11:	anewarray	#27; //class java/lang/Object
   14:	putfield	#29; //Field boxed:[Ljava/lang/Object;
   17:	aload_0
   18:	aconst_null
   19:	pop
   20:	aconst_null
   21:	putfield	#31; //Field unboxed:Ljava/lang/Object;
   24:	aload_0
   25:	aconst_null
   26:	pop
   27:	aconst_null
   28:	putfield	#33; //Field elemClass:Ljava/lang/Class;
   31:	return
  LineNumberTable: 
   line 23: 0
   line 25: 9
   line 27: 17
   line 28: 24

  LocalVariableTable: 
   Start  Length  Slot  Name   Signature
   0      32      0    this       Lscala/runtime/BoxedAnyArray;
   0      32      1    length       I

  Signature: length = 0x2
   00 0E 

public java.lang.Object apply(java.lang.Object);
  Code:
   Stack=2, Locals=2, Args_size=2
   0:	aload_0
   1:	aload_1
   2:	invokestatic	#44; //Method scala/runtime/BoxesRunTime.unboxToInt:(Ljava/lang/Object;)I
   5:	invokevirtual	#47; //Method apply:(I)Ljava/lang/Object;
   8:	areturn
  LineNumberTable: 
   line 23: 0

  LocalVariableTable: 
   Start  Length  Slot  Name   Signature
   0      9      0    this       Lscala/runtime/BoxedAnyArray;
   0      9      1    v1       Ljava/lang/Object;


public final scala.collection.generic.TraversableTemplate filter(scala.Function1);
  Code:
   Stack=2, Locals=2, Args_size=2
   0:	aload_0
   1:	aload_1
   2:	invokevirtual	#53; //Method filter:(Lscala/Function1;)Lscala/runtime/BoxedArray;
   5:	areturn
  LineNumberTable: 
   line 23: 0

  LocalVariableTable: 
   Start  Length  Slot  Name   Signature
   0      6      0    this       Lscala/runtime/BoxedAnyArray;
   0      6      1    p       Lscala/Function1;


public final scala.runtime.BoxedArray filter(scala.Function1);
  Code:
   Stack=4, Locals=13, Args_size=2
   0:	aload_0
   1:	aload_1
   2:	invokevirtual	#59; //Method countAndMemo:(Lscala/Function1;)Lscala/Tuple2;
   5:	astore_3
   6:	aload_3
   7:	ifnull	186
   10:	aload_3
   11:	invokevirtual	#65; //Method scala/Tuple2._1:()Ljava/lang/Object;
   14:	invokestatic	#44; //Method scala/runtime/BoxesRunTime.unboxToInt:(Ljava/lang/Object;)I
   17:	istore	4
   19:	aload_3
   20:	invokevirtual	#68; //Method scala/Tuple2._2:()Ljava/lang/Object;
   23:	astore	6
   25:	aload	6
   27:	instanceof	#22; //class scala/runtime/BoxedArray
   30:	ifeq	50
   33:	getstatic	#74; //Field scala/runtime/ScalaRunTime$.MODULE$:Lscala/runtime/ScalaRunTime$;
   36:	aload	6
   38:	checkcast	#22; //class scala/runtime/BoxedArray
   41:	getstatic	#79; //Field java/lang/Boolean.TYPE:Ljava/lang/Class;
   44:	invokevirtual	#83; //Method scala/runtime/ScalaRunTime$.arrayValue:(Lscala/runtime/BoxedArray;Ljava/lang/Class;)Ljava/lang/Object;
   47:	goto	52
   50:	aload	6
   52:	checkcast	#85; //class "[Z"
   55:	astore	5
   57:	aload	5
   59:	astore	7
   61:	new	#61; //class scala/Tuple2
   64:	dup
   65:	iload	4
   67:	invokestatic	#89; //Method scala/runtime/BoxesRunTime.boxToInteger:(I)Ljava/lang/Integer;
   70:	aload	7
   72:	invokespecial	#92; //Method scala/Tuple2."<init>":(Ljava/lang/Object;Ljava/lang/Object;)V
   75:	astore_2
   76:	aload_2
   77:	invokevirtual	#65; //Method scala/Tuple2._1:()Ljava/lang/Object;
   80:	invokestatic	#44; //Method scala/runtime/BoxesRunTime.unboxToInt:(Ljava/lang/Object;)I
   83:	istore	8
   85:	aload_2
   86:	invokevirtual	#68; //Method scala/Tuple2._2:()Ljava/lang/Object;
   89:	instanceof	#22; //class scala/runtime/BoxedArray
   92:	ifeq	114
   95:	getstatic	#74; //Field scala/runtime/ScalaRunTime$.MODULE$:Lscala/runtime/ScalaRunTime$;
   98:	aload_2
   99:	invokevirtual	#68; //Method scala/Tuple2._2:()Ljava/lang/Object;
   102:	checkcast	#22; //class scala/runtime/BoxedArray
   105:	getstatic	#79; //Field java/lang/Boolean.TYPE:Ljava/lang/Class;
   108:	invokevirtual	#83; //Method scala/runtime/ScalaRunTime$.arrayValue:(Lscala/runtime/BoxedArray;Ljava/lang/Class;)Ljava/lang/Object;
   111:	goto	118
   114:	aload_2
   115:	invokevirtual	#68; //Method scala/Tuple2._2:()Ljava/lang/Object;
   118:	checkcast	#85; //class "[Z"
   121:	astore	9
   123:	new	#18; //class scala/runtime/BoxedAnyArray
   126:	dup
   127:	iload	8
   129:	invokespecial	#94; //Method "<init>":(I)V
   132:	astore	10
   134:	iconst_0
   135:	istore	11
   137:	iconst_0
   138:	istore	12
   140:	iload	12
   142:	iload	8
   144:	if_icmpge	183
   147:	aload	9
   149:	iload	11
   151:	baload
   152:	ifeq	174
   155:	aload	10
   157:	iload	12
   159:	aload_0
   160:	iload	11
   162:	invokevirtual	#47; //Method apply:(I)Ljava/lang/Object;
   165:	invokevirtual	#98; //Method update:(ILjava/lang/Object;)V
   168:	iload	12
   170:	iconst_1
   171:	iadd
   172:	istore	12
   174:	iload	11
   176:	iconst_1
   177:	iadd
   178:	istore	11
   180:	goto	140
   183:	aload	10
   185:	areturn
   186:	new	#100; //class scala/MatchError
   189:	dup
   190:	aload_3
   191:	invokevirtual	#104; //Method scala/Tuple2.toString:()Ljava/lang/String;
   194:	invokespecial	#107; //Method scala/MatchError."<init>":(Ljava/lang/String;)V
   197:	athrow
  LineNumberTable: 
   line 232: 0
   line 235: 118
   line 232: 121
   line 233: 123
   line 234: 134
   line 235: 140
   line 236: 147
   line 237: 174
   line 235: 180
   line 239: 183
   line 232: 186

  LocalVariableTable: 
   Start  Length  Slot  Name   Signature
   0      198      0    this       Lscala/runtime/BoxedAnyArray;
   0      198      1    p       Lscala/Function1;
   6      89      3    temp17       Lscala/Tuple2;
   186      12      3    temp17       Lscala/Tuple2;
   19      56      4    temp18       I
   57      18      5    temp19       [Z
   61      14      7    include       [Z
   85      100      8    len       I
   123      62      9    include       [Z
   134      51      10    result       Lscala/runtime/BoxedAnyArray;
   137      48      11    i       I
   140      45      12    j       I

  Signature: length = 0x2
   00 75 

public void copyTo(int, java.lang.Object, int, int);
  Code:
   Stack=6, Locals=6, Args_size=5
   0:	aload_0
   1:	aload_2
   2:	invokespecial	#122; //Method adapt:(Ljava/lang/Object;)Ljava/lang/Object;
   5:	astore	5
   7:	getstatic	#127; //Field scala/Array$.MODULE$:Lscala/Array$;
   10:	aload_0
   11:	invokespecial	#129; //Method unboxed:()Ljava/lang/Object;
   14:	ifnull	24
   17:	aload_0
   18:	invokespecial	#129; //Method unboxed:()Ljava/lang/Object;
   21:	goto	28
   24:	aload_0
   25:	invokespecial	#132; //Method boxed:()[Ljava/lang/Object;
   28:	iload_1
   29:	aload	5
   31:	iload_3
   32:	iload	4
   34:	invokevirtual	#136; //Method scala/Array$.copy:(Ljava/lang/Object;ILjava/lang/Object;II)V
   37:	return
  LineNumberTable: 
   line 227: 0
   line 228: 7

  LocalVariableTable: 
   Start  Length  Slot  Name   Signature
   0      38      0    this       Lscala/runtime/BoxedAnyArray;
   0      38      1    from       I
   0      38      2    dest       Ljava/lang/Object;
   0      38      3    to       I
   0      38      4    len       I
   7      30      5    dest1       Ljava/lang/Object;


public void copyFrom(java.lang.Object, int, int, int);
  Code:
   Stack=6, Locals=6, Args_size=5
   0:	aload_0
   1:	aload_1
   2:	invokespecial	#122; //Method adapt:(Ljava/lang/Object;)Ljava/lang/Object;
   5:	astore	5
   7:	getstatic	#127; //Field scala/Array$.MODULE$:Lscala/Array$;
   10:	aload	5
   12:	iload_2
   13:	aload_0
   14:	invokespecial	#129; //Method unboxed:()Ljava/lang/Object;
   17:	ifnull	27
   20:	aload_0
   21:	invokespecial	#129; //Method unboxed:()Ljava/lang/Object;
   24:	goto	31
   27:	aload_0
   28:	invokespecial	#132; //Method boxed:()[Ljava/lang/Object;
   31:	iload_3
   32:	iload	4
   34:	invokevirtual	#136; //Method scala/Array$.copy:(Ljava/lang/Object;ILjava/lang/Object;II)V
   37:	return
  LineNumberTable: 
   line 222: 0
   line 223: 7

  LocalVariableTable: 
   Start  Length  Slot  Name   Signature
   0      38      0    this       Lscala/runtime/BoxedAnyArray;
   0      38      1    src       Ljava/lang/Object;
   0      38      2    from       I
   0      38      3    to       I
   0      38      4    len       I
   7      30      5    src1       Ljava/lang/Object;


public java.lang.Object value();
  Code:
   Stack=3, Locals=1, Args_size=1
   0:	aload_0
   1:	invokespecial	#129; //Method unboxed:()Ljava/lang/Object;
   4:	ifnonnull	17
   7:	new	#218; //class scala/NotDefinedError
   10:	dup
   11:	ldc	#220; //String BoxedAnyArray.value
   13:	invokespecial	#221; //Method scala/NotDefinedError."<init>":(Ljava/lang/String;)V
   16:	athrow
   17:	aload_0
   18:	invokespecial	#129; //Method unboxed:()Ljava/lang/Object;
   21:	areturn
  LineNumberTable: 
   line 174: 0
   line 175: 17


public java.lang.Object unbox(java.lang.Class);
  Code:
   Stack=6, Locals=23, Args_size=2
   0:	aload_0
   1:	dup
   2:	astore_2
   3:	monitorenter
   4:	aload_0
   5:	invokespecial	#129; //Method unboxed:()Ljava/lang/Object;
   8:	ifnonnull	640
   11:	aload_0
   12:	aload_1
   13:	invokespecial	#225; //Method elemClass_$eq:(Ljava/lang/Class;)V
   16:	aload_1
   17:	getstatic	#169; //Field java/lang/Integer.TYPE:Ljava/lang/Class;
   20:	if_acmpne	73
   23:	aload_0
   24:	invokevirtual	#228; //Method length:()I
   27:	newarray int
   29:	astore_3
   30:	iconst_0
   31:	istore	4
   33:	iload	4
   35:	aload_0
   36:	invokevirtual	#228; //Method length:()I
   39:	if_icmpge	65
   42:	aload_3
   43:	iload	4
   45:	aload_0
   46:	invokespecial	#132; //Method boxed:()[Ljava/lang/Object;
   49:	iload	4
   51:	aaload
   52:	invokestatic	#44; //Method scala/runtime/BoxesRunTime.unboxToInt:(Ljava/lang/Object;)I
   55:	iastore
   56:	iload	4
   58:	iconst_1
   59:	iadd
   60:	istore	4
   62:	goto	33
   65:	aload_0
   66:	aload_3
   67:	invokespecial	#232; //Method unboxed_$eq:(Ljava/lang/Object;)V
   70:	goto	633
   73:	aload_1
   74:	getstatic	#174; //Field java/lang/Double.TYPE:Ljava/lang/Class;
   77:	if_acmpne	133
   80:	aload_0
   81:	invokevirtual	#228; //Method length:()I
   84:	newarray double
   86:	astore	5
   88:	iconst_0
   89:	istore	6
   91:	iload	6
   93:	aload_0
   94:	invokevirtual	#228; //Method length:()I
   97:	if_icmpge	124
   100:	aload	5
   102:	iload	6
   104:	aload_0
   105:	invokespecial	#132; //Method boxed:()[Ljava/lang/Object;
   108:	iload	6
   110:	aaload
   111:	invokestatic	#236; //Method scala/runtime/BoxesRunTime.unboxToDouble:(Ljava/lang/Object;)D
   114:	dastore
   115:	iload	6
   117:	iconst_1
   118:	iadd
   119:	istore	6
   121:	goto	91
   124:	aload_0
   125:	aload	5
   127:	invokespecial	#232; //Method unboxed_$eq:(Ljava/lang/Object;)V
   130:	goto	633
   133:	aload_1
   134:	getstatic	#179; //Field java/lang/Float.TYPE:Ljava/lang/Class;
   137:	if_acmpne	193
   140:	aload_0
   141:	invokevirtual	#228; //Method length:()I
   144:	newarray float
   146:	astore	7
   148:	iconst_0
   149:	istore	8
   151:	iload	8
   153:	aload_0
   154:	invokevirtual	#228; //Method length:()I
   157:	if_icmpge	184
   160:	aload	7
   162:	iload	8
   164:	aload_0
   165:	invokespecial	#132; //Method boxed:()[Ljava/lang/Object;
   168:	iload	8
   170:	aaload
   171:	invokestatic	#240; //Method scala/runtime/BoxesRunTime.unboxToFloat:(Ljava/lang/Object;)F
   174:	fastore
   175:	iload	8
   177:	iconst_1
   178:	iadd
   179:	istore	8
   181:	goto	151
   184:	aload_0
   185:	aload	7
   187:	invokespecial	#232; //Method unboxed_$eq:(Ljava/lang/Object;)V
   190:	goto	633
   193:	aload_1
   194:	getstatic	#184; //Field java/lang/Long.TYPE:Ljava/lang/Class;
   197:	if_acmpne	253
   200:	aload_0
   201:	invokevirtual	#228; //Method length:()I
   204:	newarray long
   206:	astore	9
   208:	iconst_0
   209:	istore	10
   211:	iload	10
   213:	aload_0
   214:	invokevirtual	#228; //Method length:()I
   217:	if_icmpge	244
   220:	aload	9
   222:	iload	10
   224:	aload_0
   225:	invokespecial	#132; //Method boxed:()[Ljava/lang/Object;
   228:	iload	10
   230:	aaload
   231:	invokestatic	#244; //Method scala/runtime/BoxesRunTime.unboxToLong:(Ljava/lang/Object;)J
   234:	lastore
   235:	iload	10
   237:	iconst_1
   238:	iadd
   239:	istore	10
   241:	goto	211
   244:	aload_0
   245:	aload	9
   247:	invokespecial	#232; //Method unboxed_$eq:(Ljava/lang/Object;)V
   250:	goto	633
   253:	aload_1
   254:	getstatic	#189; //Field java/lang/Character.TYPE:Ljava/lang/Class;
   257:	if_acmpne	313
   260:	aload_0
   261:	invokevirtual	#228; //Method length:()I
   264:	newarray char
   266:	astore	11
   268:	iconst_0
   269:	istore	12
   271:	iload	12
   273:	aload_0
   274:	invokevirtual	#228; //Method length:()I
   277:	if_icmpge	304
   280:	aload	11
   282:	iload	12
   284:	aload_0
   285:	invokespecial	#132; //Method boxed:()[Ljava/lang/Object;
   288:	iload	12
   290:	aaload
   291:	invokestatic	#248; //Method scala/runtime/BoxesRunTime.unboxToChar:(Ljava/lang/Object;)C
   294:	castore
   295:	iload	12
   297:	iconst_1
   298:	iadd
   299:	istore	12
   301:	goto	271
   304:	aload_0
   305:	aload	11
   307:	invokespecial	#232; //Method unboxed_$eq:(Ljava/lang/Object;)V
   310:	goto	633
   313:	aload_1
   314:	getstatic	#199; //Field java/lang/Byte.TYPE:Ljava/lang/Class;
   317:	if_acmpne	373
   320:	aload_0
   321:	invokevirtual	#228; //Method length:()I
   324:	newarray byte
   326:	astore	13
   328:	iconst_0
   329:	istore	14
   331:	iload	14
   333:	aload_0
   334:	invokevirtual	#228; //Method length:()I
   337:	if_icmpge	364
   340:	aload	13
   342:	iload	14
   344:	aload_0
   345:	invokespecial	#132; //Method boxed:()[Ljava/lang/Object;
   348:	iload	14
   350:	aaload
   351:	invokestatic	#252; //Method scala/runtime/BoxesRunTime.unboxToByte:(Ljava/lang/Object;)B
   354:	bastore
   355:	iload	14
   357:	iconst_1
   358:	iadd
   359:	istore	14
   361:	goto	331
   364:	aload_0
   365:	aload	13
   367:	invokespecial	#232; //Method unboxed_$eq:(Ljava/lang/Object;)V
   370:	goto	633
   373:	aload_1
   374:	getstatic	#194; //Field java/lang/Short.TYPE:Ljava/lang/Class;
   377:	if_acmpne	433
   380:	aload_0
   381:	invokevirtual	#228; //Method length:()I
   384:	newarray short
   386:	astore	15
   388:	iconst_0
   389:	istore	16
   391:	iload	16
   393:	aload_0
   394:	invokevirtual	#228; //Method length:()I
   397:	if_icmpge	424
   400:	aload	15
   402:	iload	16
   404:	aload_0
   405:	invokespecial	#132; //Method boxed:()[Ljava/lang/Object;
   408:	iload	16
   410:	aaload
   411:	invokestatic	#256; //Method scala/runtime/BoxesRunTime.unboxToShort:(Ljava/lang/Object;)S
   414:	sastore
   415:	iload	16
   417:	iconst_1
   418:	iadd
   419:	istore	16
   421:	goto	391
   424:	aload_0
   425:	aload	15
   427:	invokespecial	#232; //Method unboxed_$eq:(Ljava/lang/Object;)V
   430:	goto	633
   433:	aload_1
   434:	getstatic	#79; //Field java/lang/Boolean.TYPE:Ljava/lang/Class;
   437:	if_acmpne	493
   440:	aload_0
   441:	invokevirtual	#228; //Method length:()I
   444:	newarray boolean
   446:	astore	17
   448:	iconst_0
   449:	istore	18
   451:	iload	18
   453:	aload_0
   454:	invokevirtual	#228; //Method length:()I
   457:	if_icmpge	484
   460:	aload	17
   462:	iload	18
   464:	aload_0
   465:	invokespecial	#132; //Method boxed:()[Ljava/lang/Object;
   468:	iload	18
   470:	aaload
   471:	invokestatic	#260; //Method scala/runtime/BoxesRunTime.unboxToBoolean:(Ljava/lang/Object;)Z
   474:	bastore
   475:	iload	18
   477:	iconst_1
   478:	iadd
   479:	istore	18
   481:	goto	451
   484:	aload_0
   485:	aload	17
   487:	invokespecial	#232; //Method unboxed_$eq:(Ljava/lang/Object;)V
   490:	goto	633
   493:	aload_1
   494:	ldc	#27; //class java/lang/Object
   496:	astore	19
   498:	dup
   499:	ifnonnull	511
   502:	pop
   503:	aload	19
   505:	ifnull	519
   508:	goto	530
   511:	aload	19
   513:	invokevirtual	#263; //Method java/lang/Object.equals:(Ljava/lang/Object;)Z
   516:	ifeq	530
   519:	aload_0
   520:	aload_0
   521:	invokespecial	#132; //Method boxed:()[Ljava/lang/Object;
   524:	invokespecial	#232; //Method unboxed_$eq:(Ljava/lang/Object;)V
   527:	goto	633
   530:	aload_0
   531:	getstatic	#268; //Field scala/compat/Platform$.MODULE$:Lscala/compat/Platform$;
   534:	aload_1
   535:	aload_0
   536:	invokevirtual	#228; //Method length:()I
   539:	invokevirtual	#272; //Method scala/compat/Platform$.createArray:(Ljava/lang/Class;I)Ljava/lang/Object;
   542:	invokespecial	#232; //Method unboxed_$eq:(Ljava/lang/Object;)V
   545:	aload_1
   546:	invokevirtual	#278; //Method java/lang/Class.isArray:()Z
   549:	ifeq	613
   552:	iconst_0
   553:	istore	20
   555:	iload	20
   557:	aload_0
   558:	invokevirtual	#228; //Method length:()I
   561:	if_icmpge	613
   564:	aload_0
   565:	invokespecial	#132; //Method boxed:()[Ljava/lang/Object;
   568:	iload	20
   570:	aaload
   571:	astore	21
   573:	aload	21
   575:	instanceof	#22; //class scala/runtime/BoxedArray
   578:	ifeq	604
   581:	aload	21
   583:	checkcast	#22; //class scala/runtime/BoxedArray
   586:	astore	22
   588:	aload_0
   589:	invokespecial	#132; //Method boxed:()[Ljava/lang/Object;
   592:	iload	20
   594:	aload	22
   596:	aload_1
   597:	invokevirtual	#281; //Method java/lang/Class.getComponentType:()Ljava/lang/Class;
   600:	invokevirtual	#282; //Method scala/runtime/BoxedArray.unbox:(Ljava/lang/Class;)Ljava/lang/Object;
   603:	aastore
   604:	iload	20
   606:	iconst_1
   607:	iadd
   608:	istore	20
   610:	goto	555
   613:	getstatic	#268; //Field scala/compat/Platform$.MODULE$:Lscala/compat/Platform$;
   616:	aload_0
   617:	invokespecial	#132; //Method boxed:()[Ljava/lang/Object;
   620:	iconst_0
   621:	aload_0
   622:	invokespecial	#129; //Method unboxed:()Ljava/lang/Object;
   625:	iconst_0
   626:	aload_0
   627:	invokevirtual	#228; //Method length:()I
   630:	invokevirtual	#285; //Method scala/compat/Platform$.arraycopy:(Ljava/lang/Object;ILjava/lang/Object;II)V
   633:	aload_0
   634:	aconst_null
   635:	pop
   636:	aconst_null
   637:	invokespecial	#289; //Method boxed_$eq:([Ljava/lang/Object;)V
   640:	aload_0
   641:	invokespecial	#129; //Method unboxed:()Ljava/lang/Object;
   644:	aload_2
   645:	monitorexit
   646:	areturn
   647:	aload_2
   648:	monitorexit
   649:	athrow
  Exception table:
   from   to  target type
     4   646   647   any
  LineNumberTable: 
   line 77: 0
   line 78: 4
   line 79: 11
   line 80: 16
   line 81: 23
   line 82: 30
   line 83: 33
   line 84: 42
   line 85: 56
   line 83: 62
   line 87: 65
   line 88: 73
   line 89: 80
   line 90: 88
   line 91: 91
   line 92: 100
   line 93: 115
   line 91: 121
   line 95: 124
   line 96: 133
   line 97: 140
   line 98: 148
   line 99: 151
   line 100: 160
   line 101: 175
   line 99: 181
   line 103: 184
   line 104: 193
   line 105: 200
   line 106: 208
   line 107: 211
   line 108: 220
   line 109: 235
   line 107: 241
   line 111: 244
   line 112: 253
   line 113: 260
   line 114: 268
   line 115: 271
   line 116: 280
   line 117: 295
   line 115: 301
   line 119: 304
   line 120: 313
   line 121: 320
   line 122: 328
   line 123: 331
   line 124: 340
   line 125: 355
   line 123: 361
   line 127: 364
   line 128: 373
   line 129: 380
   line 130: 388
   line 131: 391
   line 132: 400
   line 133: 415
   line 131: 421
   line 135: 424
   line 136: 433
   line 137: 440
   line 138: 448
   line 139: 451
   line 140: 460
   line 141: 475
   line 139: 481
   line 143: 484
   line 144: 493
   line 145: 519
   line 147: 530
   line 148: 545
   line 149: 552
   line 150: 555
   line 151: 564
   line 152: 588
   line 155: 604
   line 150: 610
   line 158: 613
   line 160: 633
   line 162: 640
   line 77: 645

  LocalVariableTable: 
   Start  Length  Slot  Name   Signature
   0      650      0    this       Lscala/runtime/BoxedAnyArray;
   0      650      1    elemClass       Ljava/lang/Class;
   30      40      3    newvalue       [I
   33      37      4    i       I
   88      42      5    newvalue       [D
   91      39      6    i       I
   148      42      7    newvalue       [F
   151      39      8    i       I
   208      42      9    newvalue       [J
   211      39      10    i       I
   268      42      11    newvalue       [C
   271      39      12    i       I
   328      42      13    newvalue       [B
   331      39      14    i       I
   388      42      15    newvalue       [S
   391      39      16    i       I
   448      42      17    newvalue       [Z
   451      39      18    i       I
   555      58      20    i       I
   573      40      21    temp1       Ljava/lang/Object;
   588      16      22    temp2       Lscala/runtime/BoxedArray;

  Signature: length = 0x2
   01 25 

public void update(int, java.lang.Object);
  Code:
   Stack=4, Locals=14, Args_size=3
   0:	aload_0
   1:	dup
   2:	astore_3
   3:	monitorenter
   4:	aload_2
   5:	astore	4
   7:	aload_0
   8:	invokespecial	#129; //Method unboxed:()Ljava/lang/Object;
   11:	ifnonnull	28
   14:	aload_0
   15:	invokespecial	#132; //Method boxed:()[Ljava/lang/Object;
   18:	iload_1
   19:	aload	4
   21:	aastore
   22:	getstatic	#161; //Field scala/runtime/BoxedUnit.UNIT:Lscala/runtime/BoxedUnit;
   25:	goto	542
   28:	aload_0
   29:	invokespecial	#147; //Method elemClass:()Ljava/lang/Class;
   32:	getstatic	#169; //Field java/lang/Integer.TYPE:Ljava/lang/Class;
   35:	if_acmpne	87
   38:	aload_0
   39:	invokespecial	#129; //Method unboxed:()Ljava/lang/Object;
   42:	astore	5
   44:	aload	5
   46:	instanceof	#22; //class scala/runtime/BoxedArray
   49:	ifeq	69
   52:	getstatic	#74; //Field scala/runtime/ScalaRunTime$.MODULE$:Lscala/runtime/ScalaRunTime$;
   55:	aload	5
   57:	checkcast	#22; //class scala/runtime/BoxedArray
   60:	getstatic	#169; //Field java/lang/Integer.TYPE:Ljava/lang/Class;
   63:	invokevirtual	#83; //Method scala/runtime/ScalaRunTime$.arrayValue:(Lscala/runtime/BoxedArray;Ljava/lang/Class;)Ljava/lang/Object;
   66:	goto	71
   69:	aload	5
   71:	checkcast	#166; //class "[I"
   74:	iload_1
   75:	aload	4
   77:	invokestatic	#44; //Method scala/runtime/BoxesRunTime.unboxToInt:(Ljava/lang/Object;)I
   80:	iastore
   81:	getstatic	#161; //Field scala/runtime/BoxedUnit.UNIT:Lscala/runtime/BoxedUnit;
   84:	goto	542
   87:	aload_0
   88:	invokespecial	#147; //Method elemClass:()Ljava/lang/Class;
   91:	getstatic	#174; //Field java/lang/Double.TYPE:Ljava/lang/Class;
   94:	if_acmpne	146
   97:	aload_0
   98:	invokespecial	#129; //Method unboxed:()Ljava/lang/Object;
   101:	astore	6
   103:	aload	6
   105:	instanceof	#22; //class scala/runtime/BoxedArray
   108:	ifeq	128
   111:	getstatic	#74; //Field scala/runtime/ScalaRunTime$.MODULE$:Lscala/runtime/ScalaRunTime$;
   114:	aload	6
   116:	checkcast	#22; //class scala/runtime/BoxedArray
   119:	getstatic	#174; //Field java/lang/Double.TYPE:Ljava/lang/Class;
   122:	invokevirtual	#83; //Method scala/runtime/ScalaRunTime$.arrayValue:(Lscala/runtime/BoxedArray;Ljava/lang/Class;)Ljava/lang/Object;
   125:	goto	130
   128:	aload	6
   130:	checkcast	#171; //class "[D"
   133:	iload_1
   134:	aload	4
   136:	invokestatic	#236; //Method scala/runtime/BoxesRunTime.unboxToDouble:(Ljava/lang/Object;)D
   139:	dastore
   140:	getstatic	#161; //Field scala/runtime/BoxedUnit.UNIT:Lscala/runtime/BoxedUnit;
   143:	goto	542
   146:	aload_0
   147:	invokespecial	#147; //Method elemClass:()Ljava/lang/Class;
   150:	getstatic	#179; //Field java/lang/Float.TYPE:Ljava/lang/Class;
   153:	if_acmpne	205
   156:	aload_0
   157:	invokespecial	#129; //Method unboxed:()Ljava/lang/Object;
   160:	astore	7
   162:	aload	7
   164:	instanceof	#22; //class scala/runtime/BoxedArray
   167:	ifeq	187
   170:	getstatic	#74; //Field scala/runtime/ScalaRunTime$.MODULE$:Lscala/runtime/ScalaRunTime$;
   173:	aload	7
   175:	checkcast	#22; //class scala/runtime/BoxedArray
   178:	getstatic	#179; //Field java/lang/Float.TYPE:Ljava/lang/Class;
   181:	invokevirtual	#83; //Method scala/runtime/ScalaRunTime$.arrayValue:(Lscala/runtime/BoxedArray;Ljava/lang/Class;)Ljava/lang/Object;
   184:	goto	189
   187:	aload	7
   189:	checkcast	#176; //class "[F"
   192:	iload_1
   193:	aload	4
   195:	invokestatic	#240; //Method scala/runtime/BoxesRunTime.unboxToFloat:(Ljava/lang/Object;)F
   198:	fastore
   199:	getstatic	#161; //Field scala/runtime/BoxedUnit.UNIT:Lscala/runtime/BoxedUnit;
   202:	goto	542
   205:	aload_0
   206:	invokespecial	#147; //Method elemClass:()Ljava/lang/Class;
   209:	getstatic	#184; //Field java/lang/Long.TYPE:Ljava/lang/Class;
   212:	if_acmpne	264
   215:	aload_0
   216:	invokespecial	#129; //Method unboxed:()Ljava/lang/Object;
   219:	astore	8
   221:	aload	8
   223:	instanceof	#22; //class scala/runtime/BoxedArray
   226:	ifeq	246
   229:	getstatic	#74; //Field scala/runtime/ScalaRunTime$.MODULE$:Lscala/runtime/ScalaRunTime$;
   232:	aload	8
   234:	checkcast	#22; //class scala/runtime/BoxedArray
   237:	getstatic	#184; //Field java/lang/Long.TYPE:Ljava/lang/Class;
   240:	invokevirtual	#83; //Method scala/runtime/ScalaRunTime$.arrayValue:(Lscala/runtime/BoxedArray;Ljava/lang/Class;)Ljava/lang/Object;
   243:	goto	248
   246:	aload	8
   248:	checkcast	#181; //class "[J"
   251:	iload_1
   252:	aload	4
   254:	invokestatic	#244; //Method scala/runtime/BoxesRunTime.unboxToLong:(Ljava/lang/Object;)J
   257:	lastore
   258:	getstatic	#161; //Field scala/runtime/BoxedUnit.UNIT:Lscala/runtime/BoxedUnit;
   261:	goto	542
   264:	aload_0
   265:	invokespecial	#147; //Method elemClass:()Ljava/lang/Class;
   268:	getstatic	#189; //Field java/lang/Character.TYPE:Ljava/lang/Class;
   271:	if_acmpne	323
   274:	aload_0
   275:	invokespecial	#129; //Method unboxed:()Ljava/lang/Object;
   278:	astore	9
   280:	aload	9
   282:	instanceof	#22; //class scala/runtime/BoxedArray
   285:	ifeq	305
   288:	getstatic	#74; //Field scala/runtime/ScalaRunTime$.MODULE$:Lscala/runtime/ScalaRunTime$;
   291:	aload	9
   293:	checkcast	#22; //class scala/runtime/BoxedArray
   296:	getstatic	#189; //Field java/lang/Character.TYPE:Ljava/lang/Class;
   299:	invokevirtual	#83; //Method scala/runtime/ScalaRunTime$.arrayValue:(Lscala/runtime/BoxedArray;Ljava/lang/Class;)Ljava/lang/Object;
   302:	goto	307
   305:	aload	9
   307:	checkcast	#186; //class "[C"
   310:	iload_1
   311:	aload	4
   313:	invokestatic	#248; //Method scala/runtime/BoxesRunTime.unboxToChar:(Ljava/lang/Object;)C
   316:	castore
   317:	getstatic	#161; //Field scala/runtime/BoxedUnit.UNIT:Lscala/runtime/BoxedUnit;
   320:	goto	542
   323:	aload_0
   324:	invokespecial	#147; //Method elemClass:()Ljava/lang/Class;
   327:	getstatic	#199; //Field java/lang/Byte.TYPE:Ljava/lang/Class;
   330:	if_acmpne	382
   333:	aload_0
   334:	invokespecial	#129; //Method unboxed:()Ljava/lang/Object;
   337:	astore	10
   339:	aload	10
   341:	instanceof	#22; //class scala/runtime/BoxedArray
   344:	ifeq	364
   347:	getstatic	#74; //Field scala/runtime/ScalaRunTime$.MODULE$:Lscala/runtime/ScalaRunTime$;
   350:	aload	10
   352:	checkcast	#22; //class scala/runtime/BoxedArray
   355:	getstatic	#199; //Field java/lang/Byte.TYPE:Ljava/lang/Class;
   358:	invokevirtual	#83; //Method scala/runtime/ScalaRunTime$.arrayValue:(Lscala/runtime/BoxedArray;Ljava/lang/Class;)Ljava/lang/Object;
   361:	goto	366
   364:	aload	10
   366:	checkcast	#196; //class "[B"
   369:	iload_1
   370:	aload	4
   372:	invokestatic	#252; //Method scala/runtime/BoxesRunTime.unboxToByte:(Ljava/lang/Object;)B
   375:	bastore
   376:	getstatic	#161; //Field scala/runtime/BoxedUnit.UNIT:Lscala/runtime/BoxedUnit;
   379:	goto	542
   382:	aload_0
   383:	invokespecial	#147; //Method elemClass:()Ljava/lang/Class;
   386:	getstatic	#194; //Field java/lang/Short.TYPE:Ljava/lang/Class;
   389:	if_acmpne	441
   392:	aload_0
   393:	invokespecial	#129; //Method unboxed:()Ljava/lang/Object;
   396:	astore	11
   398:	aload	11
   400:	instanceof	#22; //class scala/runtime/BoxedArray
   403:	ifeq	423
   406:	getstatic	#74; //Field scala/runtime/ScalaRunTime$.MODULE$:Lscala/runtime/ScalaRunTime$;
   409:	aload	11
   411:	checkcast	#22; //class scala/runtime/BoxedArray
   414:	getstatic	#194; //Field java/lang/Short.TYPE:Ljava/lang/Class;
   417:	invokevirtual	#83; //Method scala/runtime/ScalaRunTime$.arrayValue:(Lscala/runtime/BoxedArray;Ljava/lang/Class;)Ljava/lang/Object;
   420:	goto	425
   423:	aload	11
   425:	checkcast	#191; //class "[S"
   428:	iload_1
   429:	aload	4
   431:	invokestatic	#256; //Method scala/runtime/BoxesRunTime.unboxToShort:(Ljava/lang/Object;)S
   434:	sastore
   435:	getstatic	#161; //Field scala/runtime/BoxedUnit.UNIT:Lscala/runtime/BoxedUnit;
   438:	goto	542
   441:	aload_0
   442:	invokespecial	#147; //Method elemClass:()Ljava/lang/Class;
   445:	getstatic	#79; //Field java/lang/Boolean.TYPE:Ljava/lang/Class;
   448:	if_acmpne	500
   451:	aload_0
   452:	invokespecial	#129; //Method unboxed:()Ljava/lang/Object;
   455:	astore	12
   457:	aload	12
   459:	instanceof	#22; //class scala/runtime/BoxedArray
   462:	ifeq	482
   465:	getstatic	#74; //Field scala/runtime/ScalaRunTime$.MODULE$:Lscala/runtime/ScalaRunTime$;
   468:	aload	12
   470:	checkcast	#22; //class scala/runtime/BoxedArray
   473:	getstatic	#79; //Field java/lang/Boolean.TYPE:Ljava/lang/Class;
   476:	invokevirtual	#83; //Method scala/runtime/ScalaRunTime$.arrayValue:(Lscala/runtime/BoxedArray;Ljava/lang/Class;)Ljava/lang/Object;
   479:	goto	484
   482:	aload	12
   484:	checkcast	#85; //class "[Z"
   487:	iload_1
   488:	aload	4
   490:	invokestatic	#260; //Method scala/runtime/BoxesRunTime.unboxToBoolean:(Ljava/lang/Object;)Z
   493:	bastore
   494:	getstatic	#161; //Field scala/runtime/BoxedUnit.UNIT:Lscala/runtime/BoxedUnit;
   497:	goto	542
   500:	aload_0
   501:	invokespecial	#129; //Method unboxed:()Ljava/lang/Object;
   504:	astore	13
   506:	aload	13
   508:	instanceof	#22; //class scala/runtime/BoxedArray
   511:	ifeq	530
   514:	getstatic	#74; //Field scala/runtime/ScalaRunTime$.MODULE$:Lscala/runtime/ScalaRunTime$;
   517:	aload	13
   519:	checkcast	#22; //class scala/runtime/BoxedArray
   522:	ldc	#27; //class java/lang/Object
   524:	invokevirtual	#83; //Method scala/runtime/ScalaRunTime$.arrayValue:(Lscala/runtime/BoxedArray;Ljava/lang/Class;)Ljava/lang/Object;
   527:	goto	532
   530:	aload	13
   532:	checkcast	#294; //class "[Ljava/lang/Object;"
   535:	iload_1
   536:	aload	4
   538:	aastore
   539:	getstatic	#161; //Field scala/runtime/BoxedUnit.UNIT:Lscala/runtime/BoxedUnit;
   542:	pop
   543:	aload_3
   544:	monitorexit
   545:	return
   546:	aload_3
   547:	monitorexit
   548:	athrow
  Exception table:
   from   to  target type
     4   545   546   any
  LineNumberTable: 
   line 53: 0
   line 54: 4
   line 55: 7
   line 56: 14
   line 57: 28
   line 58: 38
   line 59: 71
   line 58: 74
   line 59: 87
   line 60: 97
   line 61: 130
   line 60: 133
   line 61: 146
   line 62: 156
   line 63: 189
   line 62: 192
   line 63: 205
   line 64: 215
   line 65: 248
   line 64: 251
   line 65: 264
   line 66: 274
   line 67: 307
   line 66: 310
   line 67: 323
   line 68: 333
   line 69: 366
   line 68: 369
   line 69: 382
   line 70: 392
   line 71: 425
   line 70: 428
   line 71: 441
   line 72: 451
   line 74: 484
   line 72: 487
   line 74: 500
   line 55: 532
   line 74: 535
   line 55: 542
   line 53: 544

  LocalVariableTable: 
   Start  Length  Slot  Name   Signature
   0      549      0    this       Lscala/runtime/BoxedAnyArray;
   0      549      1    index       I
   0      549      2    _elem       Ljava/lang/Object;
   7      536      4    elem       Ljava/lang/Object;

  Signature: length = 0x2
   01 2A 

public java.lang.Object apply(int);
  Code:
   Stack=3, Locals=12, Args_size=2
   0:	aload_0
   1:	dup
   2:	astore_2
   3:	monitorenter
   4:	aload_0
   5:	invokespecial	#129; //Method unboxed:()Ljava/lang/Object;
   8:	ifnonnull	20
   11:	aload_0
   12:	invokespecial	#132; //Method boxed:()[Ljava/lang/Object;
   15:	iload_1
   16:	aaload
   17:	goto	485
   20:	aload_0
   21:	invokespecial	#147; //Method elemClass:()Ljava/lang/Class;
   24:	getstatic	#169; //Field java/lang/Integer.TYPE:Ljava/lang/Class;
   27:	if_acmpne	70
   30:	aload_0
   31:	invokespecial	#129; //Method unboxed:()Ljava/lang/Object;
   34:	astore_3
   35:	aload_3
   36:	instanceof	#22; //class scala/runtime/BoxedArray
   39:	ifeq	58
   42:	getstatic	#74; //Field scala/runtime/ScalaRunTime$.MODULE$:Lscala/runtime/ScalaRunTime$;
   45:	aload_3
   46:	checkcast	#22; //class scala/runtime/BoxedArray
   49:	getstatic	#169; //Field java/lang/Integer.TYPE:Ljava/lang/Class;
   52:	invokevirtual	#83; //Method scala/runtime/ScalaRunTime$.arrayValue:(Lscala/runtime/BoxedArray;Ljava/lang/Class;)Ljava/lang/Object;
   55:	goto	59
   58:	aload_3
   59:	checkcast	#166; //class "[I"
   62:	iload_1
   63:	iaload
   64:	invokestatic	#89; //Method scala/runtime/BoxesRunTime.boxToInteger:(I)Ljava/lang/Integer;
   67:	goto	485
   70:	aload_0
   71:	invokespecial	#147; //Method elemClass:()Ljava/lang/Class;
   74:	getstatic	#174; //Field java/lang/Double.TYPE:Ljava/lang/Class;
   77:	if_acmpne	124
   80:	aload_0
   81:	invokespecial	#129; //Method unboxed:()Ljava/lang/Object;
   84:	astore	4
   86:	aload	4
   88:	instanceof	#22; //class scala/runtime/BoxedArray
   91:	ifeq	111
   94:	getstatic	#74; //Field scala/runtime/ScalaRunTime$.MODULE$:Lscala/runtime/ScalaRunTime$;
   97:	aload	4
   99:	checkcast	#22; //class scala/runtime/BoxedArray
   102:	getstatic	#174; //Field java/lang/Double.TYPE:Ljava/lang/Class;
   105:	invokevirtual	#83; //Method scala/runtime/ScalaRunTime$.arrayValue:(Lscala/runtime/BoxedArray;Ljava/lang/Class;)Ljava/lang/Object;
   108:	goto	113
   111:	aload	4
   113:	checkcast	#171; //class "[D"
   116:	iload_1
   117:	daload
   118:	invokestatic	#302; //Method scala/runtime/BoxesRunTime.boxToDouble:(D)Ljava/lang/Double;
   121:	goto	485
   124:	aload_0
   125:	invokespecial	#147; //Method elemClass:()Ljava/lang/Class;
   128:	getstatic	#179; //Field java/lang/Float.TYPE:Ljava/lang/Class;
   131:	if_acmpne	178
   134:	aload_0
   135:	invokespecial	#129; //Method unboxed:()Ljava/lang/Object;
   138:	astore	5
   140:	aload	5
   142:	instanceof	#22; //class scala/runtime/BoxedArray
   145:	ifeq	165
   148:	getstatic	#74; //Field scala/runtime/ScalaRunTime$.MODULE$:Lscala/runtime/ScalaRunTime$;
   151:	aload	5
   153:	checkcast	#22; //class scala/runtime/BoxedArray
   156:	getstatic	#179; //Field java/lang/Float.TYPE:Ljava/lang/Class;
   159:	invokevirtual	#83; //Method scala/runtime/ScalaRunTime$.arrayValue:(Lscala/runtime/BoxedArray;Ljava/lang/Class;)Ljava/lang/Object;
   162:	goto	167
   165:	aload	5
   167:	checkcast	#176; //class "[F"
   170:	iload_1
   171:	faload
   172:	invokestatic	#306; //Method scala/runtime/BoxesRunTime.boxToFloat:(F)Ljava/lang/Float;
   175:	goto	485
   178:	aload_0
   179:	invokespecial	#147; //Method elemClass:()Ljava/lang/Class;
   182:	getstatic	#184; //Field java/lang/Long.TYPE:Ljava/lang/Class;
   185:	if_acmpne	232
   188:	aload_0
   189:	invokespecial	#129; //Method unboxed:()Ljava/lang/Object;
   192:	astore	6
   194:	aload	6
   196:	instanceof	#22; //class scala/runtime/BoxedArray
   199:	ifeq	219
   202:	getstatic	#74; //Field scala/runtime/ScalaRunTime$.MODULE$:Lscala/runtime/ScalaRunTime$;
   205:	aload	6
   207:	checkcast	#22; //class scala/runtime/BoxedArray
   210:	getstatic	#184; //Field java/lang/Long.TYPE:Ljava/lang/Class;
   213:	invokevirtual	#83; //Method scala/runtime/ScalaRunTime$.arrayValue:(Lscala/runtime/BoxedArray;Ljava/lang/Class;)Ljava/lang/Object;
   216:	goto	221
   219:	aload	6
   221:	checkcast	#181; //class "[J"
   224:	iload_1
   225:	laload
   226:	invokestatic	#310; //Method scala/runtime/BoxesRunTime.boxToLong:(J)Ljava/lang/Long;
   229:	goto	485
   232:	aload_0
   233:	invokespecial	#147; //Method elemClass:()Ljava/lang/Class;
   236:	getstatic	#189; //Field java/lang/Character.TYPE:Ljava/lang/Class;
   239:	if_acmpne	286
   242:	aload_0
   243:	invokespecial	#129; //Method unboxed:()Ljava/lang/Object;
   246:	astore	7
   248:	aload	7
   250:	instanceof	#22; //class scala/runtime/BoxedArray
   253:	ifeq	273
   256:	getstatic	#74; //Field scala/runtime/ScalaRunTime$.MODULE$:Lscala/runtime/ScalaRunTime$;
   259:	aload	7
   261:	checkcast	#22; //class scala/runtime/BoxedArray
   264:	getstatic	#189; //Field java/lang/Character.TYPE:Ljava/lang/Class;
   267:	invokevirtual	#83; //Method scala/runtime/ScalaRunTime$.arrayValue:(Lscala/runtime/BoxedArray;Ljava/lang/Class;)Ljava/lang/Object;
   270:	goto	275
   273:	aload	7
   275:	checkcast	#186; //class "[C"
   278:	iload_1
   279:	caload
   280:	invokestatic	#314; //Method scala/runtime/BoxesRunTime.boxToCharacter:(C)Ljava/lang/Character;
   283:	goto	485
   286:	aload_0
   287:	invokespecial	#147; //Method elemClass:()Ljava/lang/Class;
   290:	getstatic	#199; //Field java/lang/Byte.TYPE:Ljava/lang/Class;
   293:	if_acmpne	340
   296:	aload_0
   297:	invokespecial	#129; //Method unboxed:()Ljava/lang/Object;
   300:	astore	8
   302:	aload	8
   304:	instanceof	#22; //class scala/runtime/BoxedArray
   307:	ifeq	327
   310:	getstatic	#74; //Field scala/runtime/ScalaRunTime$.MODULE$:Lscala/runtime/ScalaRunTime$;
   313:	aload	8
   315:	checkcast	#22; //class scala/runtime/BoxedArray
   318:	getstatic	#199; //Field java/lang/Byte.TYPE:Ljava/lang/Class;
   321:	invokevirtual	#83; //Method scala/runtime/ScalaRunTime$.arrayValue:(Lscala/runtime/BoxedArray;Ljava/lang/Class;)Ljava/lang/Object;
   324:	goto	329
   327:	aload	8
   329:	checkcast	#196; //class "[B"
   332:	iload_1
   333:	baload
   334:	invokestatic	#318; //Method scala/runtime/BoxesRunTime.boxToByte:(B)Ljava/lang/Byte;
   337:	goto	485
   340:	aload_0
   341:	invokespecial	#147; //Method elemClass:()Ljava/lang/Class;
   344:	getstatic	#194; //Field java/lang/Short.TYPE:Ljava/lang/Class;
   347:	if_acmpne	394
   350:	aload_0
   351:	invokespecial	#129; //Method unboxed:()Ljava/lang/Object;
   354:	astore	9
   356:	aload	9
   358:	instanceof	#22; //class scala/runtime/BoxedArray
   361:	ifeq	381
   364:	getstatic	#74; //Field scala/runtime/ScalaRunTime$.MODULE$:Lscala/runtime/ScalaRunTime$;
   367:	aload	9
   369:	checkcast	#22; //class scala/runtime/BoxedArray
   372:	getstatic	#194; //Field java/lang/Short.TYPE:Ljava/lang/Class;
   375:	invokevirtual	#83; //Method scala/runtime/ScalaRunTime$.arrayValue:(Lscala/runtime/BoxedArray;Ljava/lang/Class;)Ljava/lang/Object;
   378:	goto	383
   381:	aload	9
   383:	checkcast	#191; //class "[S"
   386:	iload_1
   387:	saload
   388:	invokestatic	#322; //Method scala/runtime/BoxesRunTime.boxToShort:(S)Ljava/lang/Short;
   391:	goto	485
   394:	aload_0
   395:	invokespecial	#147; //Method elemClass:()Ljava/lang/Class;
   398:	getstatic	#79; //Field java/lang/Boolean.TYPE:Ljava/lang/Class;
   401:	if_acmpne	448
   404:	aload_0
   405:	invokespecial	#129; //Method unboxed:()Ljava/lang/Object;
   408:	astore	10
   410:	aload	10
   412:	instanceof	#22; //class scala/runtime/BoxedArray
   415:	ifeq	435
   418:	getstatic	#74; //Field scala/runtime/ScalaRunTime$.MODULE$:Lscala/runtime/ScalaRunTime$;
   421:	aload	10
   423:	checkcast	#22; //class scala/runtime/BoxedArray
   426:	getstatic	#79; //Field java/lang/Boolean.TYPE:Ljava/lang/Class;
   429:	invokevirtual	#83; //Method scala/runtime/ScalaRunTime$.arrayValue:(Lscala/runtime/BoxedArray;Ljava/lang/Class;)Ljava/lang/Object;
   432:	goto	437
   435:	aload	10
   437:	checkcast	#85; //class "[Z"
   440:	iload_1
   441:	baload
   442:	invokestatic	#326; //Method scala/runtime/BoxesRunTime.boxToBoolean:(Z)Ljava/lang/Boolean;
   445:	goto	485
   448:	aload_0
   449:	invokespecial	#129; //Method unboxed:()Ljava/lang/Object;
   452:	astore	11
   454:	aload	11
   456:	instanceof	#22; //class scala/runtime/BoxedArray
   459:	ifeq	478
   462:	getstatic	#74; //Field scala/runtime/ScalaRunTime$.MODULE$:Lscala/runtime/ScalaRunTime$;
   465:	aload	11
   467:	checkcast	#22; //class scala/runtime/BoxedArray
   470:	ldc	#27; //class java/lang/Object
   472:	invokevirtual	#83; //Method scala/runtime/ScalaRunTime$.arrayValue:(Lscala/runtime/BoxedArray;Ljava/lang/Class;)Ljava/lang/Object;
   475:	goto	480
   478:	aload	11
   480:	checkcast	#294; //class "[Ljava/lang/Object;"
   483:	iload_1
   484:	aaload
   485:	aload_2
   486:	monitorexit
   487:	areturn
   488:	aload_2
   489:	monitorexit
   490:	athrow
  Exception table:
   from   to  target type
     4   487   488   any
  LineNumberTable: 
   line 30: 0
   line 31: 4
   line 32: 11
   line 33: 20
   line 34: 30
   line 35: 59
   line 34: 62
   line 35: 70
   line 36: 80
   line 37: 113
   line 36: 116
   line 37: 124
   line 38: 134
   line 39: 167
   line 38: 170
   line 39: 178
   line 40: 188
   line 41: 221
   line 40: 224
   line 41: 232
   line 42: 242
   line 43: 275
   line 42: 278
   line 43: 286
   line 44: 296
   line 45: 329
   line 44: 332
   line 45: 340
   line 46: 350
   line 47: 383
   line 46: 386
   line 47: 394
   line 48: 404
   line 50: 437
   line 48: 440
   line 50: 448
   line 30: 480
   line 50: 483
   line 30: 485

  LocalVariableTable: 
   Start  Length  Slot  Name   Signature
   0      491      0    this       Lscala/runtime/BoxedAnyArray;
   0      491      1    index       I

  Signature: length = 0x2
   01 47 

public int length();
  Code:
   Stack=1, Locals=1, Args_size=1
   0:	aload_0
   1:	getfield	#20; //Field length:I
   4:	ireturn
  LineNumberTable: 
   line 23: 0


}

