Compiled from "BoxedArray.scala"
public class scala.runtime.BoxedArray$AnyIterator extends java.lang.Object implements java.io.Serializable,scala.Iterator
  InnerClass: 
   public AnyIterator=class scala/runtime/BoxedArray$AnyIterator of class scala/runtime/BoxedArray
  Scala: length = 0x
   
  Signature: length = 0x2
   00 3D 
  SourceFile: "BoxedArray.scala"
  minor version: 0
  major version: 49
  Constant pool:
class	java/io/Serializable
class	java/lang/NullPointerException
class	java/lang/Object
class	scala/Iterator
class	scala/Iterator$class
class	scala/runtime/BoxedArray
class	scala/runtime/BoxedArray$AnyIterator
Field	scala/runtime/BoxedArray$AnyIterator.$outer:Lscala/runtime/BoxedArray;
Field	scala/runtime/BoxedArray$AnyIterator.index:I
Method	java/lang/NullPointerException."<init>":()V
Method	java/lang/Object."<init>":()V
Method	scala/Iterator$class.$init$:(Lscala/Iterator;)V
Method	scala/Iterator$class.forall:(Lscala/Iterator;Lscala/Function1;)Z
Method	scala/Iterator$class.foreach:(Lscala/Iterator;Lscala/Function1;)V
Method	scala/Iterator$class.toString:(Lscala/Iterator;)Ljava/lang/String;
Method	scala/Iterator$class.zip:(Lscala/Iterator;Lscala/Iterator;)Ljava/lang/Object;
Method	scala/runtime/BoxedArray.apply:(I)Ljava/lang/Object;
Method	scala/runtime/BoxedArray.length:()I
Method	scala/runtime/BoxedArray$AnyIterator.index:()I
Method	scala/runtime/BoxedArray$AnyIterator.index_$eq:(I)V
Method	scala/runtime/BoxedArray$AnyIterator.scala$runtime$BoxedArray$AnyIterator$$$outer:()Lscala/runtime/BoxedArray;
NameAndType	$init$:(Lscala/Iterator;)V
NameAndType	$outer:Lscala/runtime/BoxedArray;
NameAndType	"<init>":()V
NameAndType	apply:(I)Ljava/lang/Object;
NameAndType	forall:(Lscala/Iterator;Lscala/Function1;)Z
NameAndType	foreach:(Lscala/Iterator;Lscala/Function1;)V
NameAndType	index:()I
NameAndType	index:I
NameAndType	index_$eq:(I)V
NameAndType	length:()I
NameAndType	scala$runtime$BoxedArray$AnyIterator$$$outer:()Lscala/runtime/BoxedArray;
NameAndType	toString:(Lscala/Iterator;)Ljava/lang/String;
NameAndType	zip:(Lscala/Iterator;Lscala/Iterator;)Ljava/lang/Object;
Asciz	$init$;
Asciz	$outer;
Asciz	()I;
Asciz	()Ljava/lang/Object;;
Asciz	()Ljava/lang/String;;
Asciz	()Lscala/runtime/BoxedArray;;
Asciz	()V;
Asciz	()Z;
Asciz	(I)Ljava/lang/Object;;
Asciz	(I)V;
Asciz	(Lscala/Function1;)V;
Asciz	(Lscala/Function1;)Z;
Asciz	(Lscala/Iterator;)Ljava/lang/Object;;
Asciz	(Lscala/Iterator;)Ljava/lang/String;;
Asciz	(Lscala/Iterator;)V;
Asciz	(Lscala/Iterator;Lscala/Function1;)V;
Asciz	(Lscala/Iterator;Lscala/Function1;)Z;
Asciz	(Lscala/Iterator;Lscala/Iterator;)Ljava/lang/Object;;
Asciz	(Lscala/runtime/BoxedArray;)V;
Asciz	<init>;
Asciz	AnyIterator;
Asciz	BoxedArray.scala;
Asciz	Code;
Asciz	I;
Asciz	InnerClasses;
Asciz	LineNumberTable;
Asciz	Ljava/lang/Object;Lscala/Iterator<Ljava/lang/Object;>;;
Asciz	LocalVariableTable;
Asciz	Lscala/Function1;;
Asciz	Lscala/Iterator;;
Asciz	Lscala/runtime/BoxedArray$AnyIterator;;
Asciz	Lscala/runtime/BoxedArray;;
Asciz	Scala;
Asciz	Signature;
Asciz	SourceFile;
Asciz	apply;
Asciz	forall;
Asciz	foreach;
Asciz	hasNext;
Asciz	i;
Asciz	index;
Asciz	index_$eq;
Asciz	java/io/Serializable;
Asciz	java/lang/NullPointerException;
Asciz	java/lang/Object;
Asciz	length;
Asciz	next;
Asciz	scala$runtime$BoxedArray$AnyIterator$$$outer;
Asciz	scala/Iterator;
Asciz	scala/Iterator$class;
Asciz	scala/runtime/BoxedArray;
Asciz	scala/runtime/BoxedArray$AnyIterator;
Asciz	this;
Asciz	toString;
Asciz	x$1;
Asciz	zip;

{
public final scala.runtime.BoxedArray $outer;
  Signature: Lscala/runtime/BoxedArray;

private int index;
  Signature: I

public scala.runtime.BoxedArray$AnyIterator(scala.runtime.BoxedArray);
  Signature: (Lscala/runtime/BoxedArray;)V
  Code:
   Stack=2, Locals=2, Args_size=2
	aload_1
	ifnonnull	l1 // aload_0
	new	class java/lang/NullPointerException
	dup
	invokespecial	Method java/lang/NullPointerException."<init>":()V
	athrow
l1	aload_0
	aload_1
	putfield	Field $outer:Lscala/runtime/BoxedArray;
	aload_0
	iconst_0
	putfield	Field index:I
	aload_0
	invokespecial	Method java/lang/Object."<init>":()V
	aload_0
	invokestatic	Method scala/Iterator$class.$init$:(Lscala/Iterator;)V
	return
  Labels:
   	l1 = 12 // aload_0
  LocalVariableTable: 
   Start  Length  Slot  Name   Signature
   0      31      0    this       Lscala/runtime/BoxedArray$AnyIterator;
   0      31      1    $outer       Lscala/runtime/BoxedArray;


public scala.runtime.BoxedArray scala$runtime$BoxedArray$AnyIterator$$$outer();
  Signature: ()Lscala/runtime/BoxedArray;
  Code:
   Stack=1, Locals=1, Args_size=1
	aload_0
	getfield	Field $outer:Lscala/runtime/BoxedArray;
	areturn
  Labels:

public java.lang.Object next();
  Signature: ()Ljava/lang/Object;
  Code:
   Stack=3, Locals=2, Args_size=1
	aload_0
	invokevirtual	Method index:()I
	istore_1
	aload_0
	iload_1
	iconst_1
	iadd
	invokevirtual	Method index_$eq:(I)V
	aload_0
	invokevirtual	Method scala$runtime$BoxedArray$AnyIterator$$$outer:()Lscala/runtime/BoxedArray;
	iload_1
	invokevirtual	Method scala/runtime/BoxedArray.apply:(I)Ljava/lang/Object;
	areturn
  Labels:
  LocalVariableTable: 
   Start  Length  Slot  Name   Signature
   0      21      0    this       Lscala/runtime/BoxedArray$AnyIterator;
   0      20      1    i       I


public boolean hasNext();
  Signature: ()Z
  Code:
   Stack=2, Locals=1, Args_size=1
	aload_0
	invokevirtual	Method index:()I
	aload_0
	invokevirtual	Method scala$runtime$BoxedArray$AnyIterator$$$outer:()Lscala/runtime/BoxedArray;
	invokevirtual	Method scala/runtime/BoxedArray.length:()I
	if_icmpge	l1 // iconst_0
	iconst_1
	goto	l2 // ireturn
l1	iconst_0
l2	ireturn
  Labels:
   	l1 = 18 // iconst_0
   	l2 = 19 // ireturn

public void index_$eq(int);
  Signature: (I)V
  Code:
   Stack=2, Locals=2, Args_size=2
	aload_0
	iload_1
	putfield	Field index:I
	return
  Labels:
  LocalVariableTable: 
   Start  Length  Slot  Name   Signature
   0      6      0    this       Lscala/runtime/BoxedArray$AnyIterator;
   0      6      1    x$1       I


public int index();
  Signature: ()I
  Code:
   Stack=1, Locals=1, Args_size=1
	aload_0
	getfield	Field index:I
	ireturn
  Labels:

public java.lang.String toString();
  Signature: ()Ljava/lang/String;
  Code:
   Stack=1, Locals=1, Args_size=1
	aload_0
	invokestatic	Method scala/Iterator$class.toString:(Lscala/Iterator;)Ljava/lang/String;
	areturn
  Labels:

public boolean forall(scala.Function1);
  Signature: (Lscala/Function1;)Z
  Code:
   Stack=2, Locals=2, Args_size=2
	aload_0
	aload_1
	invokestatic	Method scala/Iterator$class.forall:(Lscala/Iterator;Lscala/Function1;)Z
	ireturn
  Labels:
  LocalVariableTable: 
   Start  Length  Slot  Name   Signature
   0      6      0    this       Lscala/runtime/BoxedArray$AnyIterator;
   0      6      1    x$1       Lscala/Function1;


public void foreach(scala.Function1);
  Signature: (Lscala/Function1;)V
  Code:
   Stack=2, Locals=2, Args_size=2
	aload_0
	aload_1
	invokestatic	Method scala/Iterator$class.foreach:(Lscala/Iterator;Lscala/Function1;)V
	return
  Labels:
  LocalVariableTable: 
   Start  Length  Slot  Name   Signature
   0      6      0    this       Lscala/runtime/BoxedArray$AnyIterator;
   0      6      1    x$1       Lscala/Function1;


public java.lang.Object zip(scala.Iterator);
  Signature: (Lscala/Iterator;)Ljava/lang/Object;
  Code:
   Stack=2, Locals=2, Args_size=2
	aload_0
	aload_1
	invokestatic	Method scala/Iterator$class.zip:(Lscala/Iterator;Lscala/Iterator;)Ljava/lang/Object;
	areturn
  Labels:
  LocalVariableTable: 
   Start  Length  Slot  Name   Signature
   0      6      0    this       Lscala/runtime/BoxedArray$AnyIterator;
   0      6      1    x$1       Lscala/Iterator;


}

