Compiled from "BoxedArray.scala"
public abstract class scala.runtime.BoxedArray extends java.lang.Object implements scala.Array$Array0
  InnerClass: 
   public abstract Array0=class scala/Array$Array0 of class scala/Array
   public AnyIterator=class scala/runtime/BoxedArray$AnyIterator of class scala/runtime/BoxedArray
   public abstract Mutable=class scala/RandomAccessSeq$Mutable of class scala/RandomAccessSeq
  ScalaSig: length = 0x581
   04 01 FFFFFF81 57 06 08 01 02 FFFFFF84 FFFFFF80 FFFFFF80 FFFFFF81 00 07 02 0A
   42 6F 78 65 64 41 72 72 61 79 0A 02 03 04 01 07
   72 75 6E 74 69 6D 65 0A 01 05 01 05 73 63 61 6C
   61 03 00 13 04 00 08 10 1B 10 02 09 0E 0D 01 0A
   0A 02 0B 0C 01 04 6C 61 6E 67 0A 01 0D 01 04 6A
   61 76 61 09 02 0F 0A 02 06 4F 62 6A 65 63 74 10
   03 11 15 18 0E 02 12 13 0D 01 04 09 02 14 04 01
   05 41 72 72 61 79 09 02 16 17 02 06 41 72 72 61
   79 30 0A 02 14 04 10 02 12 19 09 02 1A 04 02 03
   41 6E 79 10 02 12 1C 09 02 1D 04 02 0B 53 63 61
   6C 61 4F 62 6A 65 63 74 08 05 1F 00 FFFFFF84 00 20 01
   06 3C 69 6E 69 74 3E 14 01 21 10 02 22 00 0D 01
   02 08 05 24 00 FFFFFF86 00 25 01 06 6C 65 6E 67 74 68
   15 01 26 10 02 12 27 09 02 28 04 02 03 49 6E 74
   08 05 2A 00 FFFFFF86 00 2B 01 05 61 70 70 6C 79 14 02
   18 26 08 05 2D 00 FFFFFF86 00 2E 01 06 75 70 64 61 74
   65 14 03 2F 26 18 10 02 12 30 09 02 31 04 02 04
   55 6E 69 74 08 05 33 00 FFFFFF86 00 34 01 05 75 6E 62
   6F 78 14 02 35 38 10 02 12 36 09 02 37 04 02 06
   41 6E 79 52 65 66 10 02 39 3C 0E 02 12 3A 09 02
   3B 04 01 06 50 72 65 64 65 66 09 02 3D 3E 02 06
   53 74 72 69 6E 67 0A 02 3B 04 08 05 33 00 FFFFFF86 00
   40 14 02 35 41 30 02 42 47 10 03 39 43 45 09 02
   44 3E 02 05 43 6C 61 73 73 10 02 46 47 0C 00 04
   08 48 3F FFFFFF84 FFFFFF80 FFFFFF80 FFFFFF82 00 49 02 03 5F 24 31 11 02
   4A 18 10 02 12 4B 09 02 4C 04 02 07 4E 6F 74 68
   69 6E 67 08 05 4E 00 FFFFFF84 20 4F 01 0B 69 73 44 65
   66 69 6E 65 64 41 74 14 02 50 26 10 02 12 51 09
   02 52 04 02 07 42 6F 6F 6C 65 61 6E 06 08 54 00
   FFFFFF84 FFFFFF80 FFFFFF80 FFFFFF80 08 55 02 0B 41 6E 79 49 74 65 72 61
   74 6F 72 13 04 53 08 56 1B 10 03 12 57 18 09 02
   58 04 02 08 49 74 65 72 61 74 6F 72 08 05 1F 53
   FFFFFF84 00 5A 14 01 5B 10 02 5C 53 0D 01 00 08 07 5E
   53 FFFFFFC0 FFFFFF80 FFFFFF84 00 25 01 05 69 6E 64 65 78 08 07 60
   53 FFFFFFC0 FFFFFF80 FFFFFF84 00 61 01 09 69 6E 64 65 78 5F 24 65
   71 14 02 2F 26 08 06 63 53 FFFFFFA0 FFFFFFA0 04 26 01 06 69
   6E 64 65 78 20 08 05 65 53 FFFFFF84 00 66 01 07 68 61
   73 4E 65 78 74 15 01 50 08 05 68 53 FFFFFF84 00 69 01
   04 6E 65 78 74 14 01 18 28 02 53 6B 10 02 12 6C
   09 02 6D 04 02 0C 73 65 72 69 61 6C 69 7A 61 62
   6C 65 08 05 6F 00 FFFFFF84 20 70 01 08 65 6C 65 6D 65
   6E 74 73 15 01 5B 08 05 72 00 FFFFFF86 00 73 01 05 76
   61 6C 75 65 15 01 35 08 05 75 00 FFFFFF84 00 76 01 08
   63 6F 70 79 46 72 6F 6D 14 05 2F 35 26 26 26 08
   05 78 00 FFFFFF84 00 79 01 06 63 6F 70 79 54 6F 14 05
   2F 26 35 26 26 08 05 7B 00 FFFFFF84 20 7C 01 0B 63 6F
   70 79 54 6F 41 72 72 61 79 15 03 7D FFFFFF81 02 14 03
   2F 7E 26 10 04 12 7F FFFFFF81 01 09 03 FFFFFF81 00 04 02 05
   41 72 72 61 79 10 03 46 FFFFFF81 02 04 09 FFFFFF81 03 7A FFFFFF84
   FFFFFF80 FFFFFF80 FFFFFFC2 00 49 02 01 42 08 07 FFFFFF81 05 00 FFFFFF86 00 FFFFFF81
   06 01 08 73 75 62 41 72 72 61 79 14 03 35 26 26
   08 07 FFFFFF81 08 00 FFFFFF84 22 FFFFFF81 09 01 03 6D 61 70 15 04
   FFFFFF81 0A FFFFFF81 0D 14 04 FFFFFF81 0B FFFFFF81 0F 10 04 12 7F FFFFFF81 0C
   10 03 46 FFFFFF81 0D 04 0A FFFFFF81 0E FFFFFF81 07 FFFFFF84 FFFFFF80 FFFFFF80 FFFFFFC2 00
   49 02 01 62 10 06 12 FFFFFF81 10 18 FFFFFF81 0C 09 03 FFFFFF81 11
   04 02 09 46 75 6E 63 74 69 6F 6E 31 08 07 FFFFFF81 13
   00 FFFFFF84 22 FFFFFF81 14 01 07 66 6C 61 74 4D 61 70 15 04
   FFFFFF81 15 FFFFFF81 18 14 04 FFFFFF81 16 FFFFFF81 19 10 04 12 7F FFFFFF81 17
   10 03 46 FFFFFF81 18 04 0A FFFFFF81 0E FFFFFF81 12 FFFFFF84 FFFFFF80 FFFFFF80 FFFFFFC2 00
   49 10 06 12 FFFFFF81 10 18 FFFFFF81 1A 10 05 12 FFFFFF81 1B FFFFFF81 17
   09 03 FFFFFF81 1C 04 02 08 49 74 65 72 61 62 6C 65 08
   07 FFFFFF81 1E 00 FFFFFF84 22 FFFFFF81 1F 01 0A 24 70 6C 75 73 24
   70 6C 75 73 15 04 FFFFFF81 20 FFFFFF81 23 14 04 FFFFFF81 21 FFFFFF81 25
   10 04 12 7F FFFFFF81 22 10 03 46 FFFFFF81 23 04 0B FFFFFF81 0E FFFFFF81
   1D FFFFFF84 FFFFFF80 FFFFFF80 FFFFFFC2 00 FFFFFF81 24 11 02 18 18 10 05 12 FFFFFF81
   1B FFFFFF81 22 08 07 FFFFFF81 27 00 FFFFFF84 02 FFFFFF81 28 01 03 7A 69
   70 15 04 FFFFFF81 29 FFFFFF81 2F 14 04 FFFFFF81 2A FFFFFF81 30 10 04 12
   7F FFFFFF81 2B 10 06 12 FFFFFF81 2C 18 FFFFFF81 2E 09 03 FFFFFF81 2D 04
   02 06 54 75 70 6C 65 32 10 03 46 FFFFFF81 2F 04 0A FFFFFF81
   0E FFFFFF81 26 FFFFFF84 FFFFFF80 FFFFFF80 FFFFFFC2 00 49 10 04 12 7F FFFFFF81 2E 08
   07 FFFFFF81 32 00 FFFFFF84 02 FFFFFF81 33 01 0C 7A 69 70 57 69 74
   68 49 6E 64 65 78 15 02 FFFFFF81 34 10 04 12 7F FFFFFF81 35
   10 05 12 FFFFFF81 2C 18 26 08 07 FFFFFF81 37 00 FFFFFF84 00 FFFFFF81 38
   01 07 69 6E 64 69 63 65 73 15 02 FFFFFF81 39 10 03 12
   7F 26 08 07 FFFFFF81 3B 00 FFFFFF84 02 FFFFFF81 3C 01 0C 64 65 65
   70 54 6F 53 74 72 69 6E 67 14 01 38 08 07 FFFFFF81 3E
   00 FFFFFF84 02 FFFFFF81 3F 01 0C 64 65 65 70 4D 6B 53 74 72
   69 6E 67 14 04 38 38 38 38 08 07 FFFFFF81 3E 00 FFFFFF84 02
   FFFFFF81 41 14 02 38 38 08 07 FFFFFF81 43 00 FFFFFF84 02 FFFFFF81 44 01
   0A 64 65 65 70 45 71 75 61 6C 73 14 02 50 18 08
   07 FFFFFF81 46 00 FFFFFF84 22 FFFFFF81 47 01 0C 73 74 72 69 6E 67
   50 72 65 66 69 78 15 01 38 08 07 FFFFFF81 49 00 FFFFFF86 08
   FFFFFF81 4A 01 08 6E 65 77 41 72 72 61 79 14 03 21 26
   56 08 07 FFFFFF81 4C 00 FFFFFF84 20 FFFFFF81 4D 01 0A 70 72 6F 6A
   65 63 74 69 6F 6E 15 02 FFFFFF81 4E 10 05 FFFFFF81 4F FFFFFF81 55
   18 0E 03 FFFFFF81 50 13 0E 04 FFFFFF81 51 FFFFFF81 54 0D 02 FFFFFF81 52
   0A 03 FFFFFF81 53 06 01 06 3C 72 6F 6F 74 3E 09 01 05
   09 03 FFFFFF81 56 17 02 0A 50 72 6F 6A 65 63 74 69 6F
   6E 
  Signature: length = 0x2
   00 52 
  SourceFile: "BoxedArray.scala"
  minor version: 0
  major version: 49
  Constant pool:
String	Array
class	java/lang/Object
class	scala/Array
class	scala/Array$Array0
class	scala/Array$Array0$class
class	scala/Collection$class
class	scala/Function1$class
class	scala/Iterable
class	scala/Iterable$class
class	scala/PartialFunction$class
class	scala/RandomAccessSeq
class	scala/RandomAccessSeq$Mutable
class	scala/RandomAccessSeq$Mutable$class
class	scala/RandomAccessSeq$class
class	scala/Seq
class	scala/Seq$class
class	scala/runtime/BoxedArray
class	scala/runtime/BoxedArray$AnyIterator
Method	java/lang/Object."<init>":()V
Method	scala/Array$Array0$class.$init$:(Lscala/Array$Array0;)V
Method	scala/Collection$class.$init$:(Lscala/Collection;)V
Method	scala/Collection$class.toString:(Lscala/Collection;)Ljava/lang/String;
Method	scala/Function1$class.$init$:(Lscala/Function1;)V
Method	scala/Iterable$class.$init$:(Lscala/Iterable;)V
Method	scala/Iterable$class.addString:(Lscala/Iterable;Lscala/StringBuilder;Ljava/lang/String;Ljava/lang/String;Ljava/lang/String;)Lscala/StringBuilder;
Method	scala/Iterable$class.mkString:(Lscala/Iterable;Ljava/lang/String;Ljava/lang/String;Ljava/lang/String;)Ljava/lang/String;
Method	scala/PartialFunction$class.$init$:(Lscala/PartialFunction;)V
Method	scala/RandomAccessSeq$Mutable$class.$init$:(Lscala/RandomAccessSeq$Mutable;)V
Method	scala/RandomAccessSeq$class.$init$:(Lscala/RandomAccessSeq;)V
Method	scala/Seq$class.$init$:(Lscala/Seq;)V
Method	scala/Seq$class.isEmpty:(Lscala/Seq;)Z
Method	scala/runtime/BoxedArray.elements:()Lscala/runtime/BoxedArray$AnyIterator;
Method	scala/runtime/BoxedArray$AnyIterator."<init>":(Lscala/runtime/BoxedArray;)V
NameAndType	$init$:(Lscala/Array$Array0;)V
NameAndType	$init$:(Lscala/Collection;)V
NameAndType	$init$:(Lscala/Function1;)V
NameAndType	$init$:(Lscala/Iterable;)V
NameAndType	$init$:(Lscala/PartialFunction;)V
NameAndType	$init$:(Lscala/RandomAccessSeq$Mutable;)V
NameAndType	$init$:(Lscala/RandomAccessSeq;)V
NameAndType	$init$:(Lscala/Seq;)V
NameAndType	"<init>":()V
NameAndType	"<init>":(Lscala/runtime/BoxedArray;)V
NameAndType	addString:(Lscala/Iterable;Lscala/StringBuilder;Ljava/lang/String;Ljava/lang/String;Ljava/lang/String;)Lscala/StringBuilder;
NameAndType	elements:()Lscala/runtime/BoxedArray$AnyIterator;
NameAndType	isEmpty:(Lscala/Seq;)Z
NameAndType	mkString:(Lscala/Iterable;Ljava/lang/String;Ljava/lang/String;Ljava/lang/String;)Ljava/lang/String;
NameAndType	toString:(Lscala/Collection;)Ljava/lang/String;
Asciz	$init$;
Asciz	()I;
Asciz	()Ljava/lang/String;;
Asciz	()Lscala/Iterator;;
Asciz	()Lscala/runtime/BoxedArray$AnyIterator;;
Asciz	()V;
Asciz	()Z;
Asciz	(I)Ljava/lang/Object;;
Asciz	(Ljava/lang/Class;)Ljava/lang/Object;;
Asciz	(Ljava/lang/Class<*>;)Ljava/lang/Object;;
Asciz	(Ljava/lang/String;Ljava/lang/String;Ljava/lang/String;)Ljava/lang/String;;
Asciz	(Lscala/Array$Array0;)V;
Asciz	(Lscala/Collection;)Ljava/lang/String;;
Asciz	(Lscala/Collection;)V;
Asciz	(Lscala/Function1;)V;
Asciz	(Lscala/Iterable;)V;
Asciz	(Lscala/Iterable;Ljava/lang/String;Ljava/lang/String;Ljava/lang/String;)Ljava/lang/String;;
Asciz	(Lscala/Iterable;Lscala/StringBuilder;Ljava/lang/String;Ljava/lang/String;Ljava/lang/String;)Lscala/StringBuilder;;
Asciz	(Lscala/PartialFunction;)V;
Asciz	(Lscala/RandomAccessSeq$Mutable;)V;
Asciz	(Lscala/RandomAccessSeq;)V;
Asciz	(Lscala/Seq;)V;
Asciz	(Lscala/Seq;)Z;
Asciz	(Lscala/StringBuilder;Ljava/lang/String;Ljava/lang/String;Ljava/lang/String;)Lscala/StringBuilder;;
Asciz	(Lscala/runtime/BoxedArray;)V;
Asciz	<init>;
Asciz	AnyIterator;
Asciz	Array;
Asciz	Array0;
Asciz	BoxedArray.scala;
Asciz	Code;
Asciz	InnerClasses;
Asciz	LineNumberTable;
Asciz	Ljava/lang/Object;Lscala/Array$Array0<Ljava/lang/Object;>;;
Asciz	Ljava/lang/String;;
Asciz	LocalVariableTable;
Asciz	Lscala/StringBuilder;;
Asciz	Lscala/runtime/BoxedArray;;
Asciz	Mutable;
Asciz	ScalaSig;
Asciz	Signature;
Asciz	SourceFile;
Asciz	addString;
Asciz	apply;
Asciz	elements;
Asciz	isEmpty;
Asciz	java/lang/Object;
Asciz	length;
Asciz	mkString;
Asciz	scala/Array;
Asciz	scala/Array$Array0;
Asciz	scala/Array$Array0$class;
Asciz	scala/Collection$class;
Asciz	scala/Function1$class;
Asciz	scala/Iterable;
Asciz	scala/Iterable$class;
Asciz	scala/PartialFunction$class;
Asciz	scala/RandomAccessSeq;
Asciz	scala/RandomAccessSeq$Mutable;
Asciz	scala/RandomAccessSeq$Mutable$class;
Asciz	scala/RandomAccessSeq$class;
Asciz	scala/Seq;
Asciz	scala/Seq$class;
Asciz	scala/runtime/BoxedArray;
Asciz	scala/runtime/BoxedArray$AnyIterator;
Asciz	stringPrefix;
Asciz	this;
Asciz	toString;
Asciz	unbox;
Asciz	x$1;
Asciz	x$2;
Asciz	x$3;
Asciz	x$4;

{
public scala.runtime.BoxedArray();
  Signature: ()V
  Code:
   Stack=1, Locals=1, Args_size=1
	aload_0
	invokespecial	Method java/lang/Object."<init>":()V
	aload_0
	invokestatic	Method scala/Function1$class.$init$:(Lscala/Function1;)V
	aload_0
	invokestatic	Method scala/PartialFunction$class.$init$:(Lscala/PartialFunction;)V
	aload_0
	invokestatic	Method scala/Iterable$class.$init$:(Lscala/Iterable;)V
	aload_0
	invokestatic	Method scala/Collection$class.$init$:(Lscala/Collection;)V
	aload_0
	invokestatic	Method scala/Seq$class.$init$:(Lscala/Seq;)V
	aload_0
	invokestatic	Method scala/RandomAccessSeq$class.$init$:(Lscala/RandomAccessSeq;)V
	aload_0
	invokestatic	Method scala/RandomAccessSeq$Mutable$class.$init$:(Lscala/RandomAccessSeq$Mutable;)V
	aload_0
	invokestatic	Method scala/Array$Array0$class.$init$:(Lscala/Array$Array0;)V
	return
  Labels:

public scala.Iterator elements();
  Signature: ()Lscala/Iterator;
  Code:
   Stack=1, Locals=1, Args_size=1
	aload_0
	invokevirtual	Method elements:()Lscala/runtime/BoxedArray$AnyIterator;
	areturn
  Labels:

public final java.lang.String stringPrefix();
  Signature: ()Ljava/lang/String;
  Code:
   Stack=1, Locals=1, Args_size=1
	ldc	String Array
	areturn
  Labels:

public scala.runtime.BoxedArray$AnyIterator elements();
  Signature: ()Lscala/runtime/BoxedArray$AnyIterator;
  Code:
   Stack=3, Locals=1, Args_size=1
	new	class scala/runtime/BoxedArray$AnyIterator
	dup
	aload_0
	invokespecial	Method scala/runtime/BoxedArray$AnyIterator."<init>":(Lscala/runtime/BoxedArray;)V
	areturn
  Labels:

public abstract java.lang.Object unbox(java.lang.Class);
  Signature: (Ljava/lang/Class;)Ljava/lang/Object;
  Signature: length = 0x2
   00 3A 

public abstract java.lang.Object apply(int);
  Signature: (I)Ljava/lang/Object;

public abstract int length();
  Signature: ()I

public scala.StringBuilder addString(scala.StringBuilder, java.lang.String, java.lang.String, java.lang.String);
  Signature: (Lscala/StringBuilder;Ljava/lang/String;Ljava/lang/String;Ljava/lang/String;)Lscala/StringBuilder;
  Code:
   Stack=5, Locals=5, Args_size=5
	aload_0
	aload_1
	aload_2
	aload_3
	aload	4
	invokestatic	Method scala/Iterable$class.addString:(Lscala/Iterable;Lscala/StringBuilder;Ljava/lang/String;Ljava/lang/String;Ljava/lang/String;)Lscala/StringBuilder;
	areturn
  Labels:
  LocalVariableTable: 
   Start  Length  Slot  Name   Signature
   0      10      0    this       Lscala/runtime/BoxedArray;
   0      10      1    x$1       Lscala/StringBuilder;
   0      10      2    x$2       Ljava/lang/String;
   0      10      3    x$3       Ljava/lang/String;
   0      10      4    x$4       Ljava/lang/String;


public java.lang.String mkString(java.lang.String, java.lang.String, java.lang.String);
  Signature: (Ljava/lang/String;Ljava/lang/String;Ljava/lang/String;)Ljava/lang/String;
  Code:
   Stack=4, Locals=4, Args_size=4
	aload_0
	aload_1
	aload_2
	aload_3
	invokestatic	Method scala/Iterable$class.mkString:(Lscala/Iterable;Ljava/lang/String;Ljava/lang/String;Ljava/lang/String;)Ljava/lang/String;
	areturn
  Labels:
  LocalVariableTable: 
   Start  Length  Slot  Name   Signature
   0      8      0    this       Lscala/runtime/BoxedArray;
   0      8      1    x$1       Ljava/lang/String;
   0      8      2    x$2       Ljava/lang/String;
   0      8      3    x$3       Ljava/lang/String;


public java.lang.String toString();
  Signature: ()Ljava/lang/String;
  Code:
   Stack=1, Locals=1, Args_size=1
	aload_0
	invokestatic	Method scala/Collection$class.toString:(Lscala/Collection;)Ljava/lang/String;
	areturn
  Labels:

public boolean isEmpty();
  Signature: ()Z
  Code:
   Stack=1, Locals=1, Args_size=1
	aload_0
	invokestatic	Method scala/Seq$class.isEmpty:(Lscala/Seq;)Z
	ireturn
  Labels:

}

