Compiled from "BoxedIntArray.scala"
public final class scala.runtime.BoxedIntArray extends scala.runtime.BoxedArray implements java.io.Serializable
  ScalaSig: length = 0x25E
   04 01 65 06 08 01 02 FFFFFF84 FFFFFF80 FFFFFF80 FFFFFF80 02 07 02 0D 42
   6F 78 65 64 49 6E 74 41 72 72 61 79 0A 02 03 04
   01 07 72 75 6E 74 69 6D 65 0A 01 05 01 05 73 63
   61 6C 61 03 00 13 03 00 08 0C 10 02 09 0A 0D 01
   02 09 02 0B 02 02 0A 42 6F 78 65 64 41 72 72 61
   79 10 02 0D 0E 0D 01 04 09 02 0F 04 02 0B 53 63
   61 6C 61 4F 62 6A 65 63 74 08 08 11 00 FFFFFF82 FFFFFFC2 FFFFFF80
   FFFFFF84 00 12 01 05 76 61 6C 75 65 15 01 13 10 03 0D
   14 16 09 02 15 04 02 05 41 72 72 61 79 10 02 0D
   17 09 02 18 04 02 03 49 6E 74 08 08 1A 00 FFFFFF82 FFFFFF80
   FFFFFFA0 FFFFFF80 04 13 01 06 76 61 6C 75 65 20 08 05 1C 00
   FFFFFF84 00 1D 01 06 3C 69 6E 69 74 3E 14 02 1E 13 10
   02 09 00 08 05 20 00 FFFFFF84 00 21 01 06 6C 65 6E 67
   74 68 15 01 16 08 05 23 00 FFFFFF84 00 24 01 05 61 70
   70 6C 79 14 02 25 16 10 02 0D 26 09 02 27 04 02
   03 41 6E 79 08 05 29 00 FFFFFF84 00 2A 01 06 75 70 64
   61 74 65 14 03 2B 16 25 10 02 0D 2C 09 02 2D 04
   02 04 55 6E 69 74 08 05 2F 00 FFFFFF84 00 30 01 05 75
   6E 62 6F 78 14 02 31 34 10 02 0D 32 09 02 33 04
   02 06 41 6E 79 52 65 66 10 02 35 38 0E 02 0D 36
   09 02 37 04 01 06 50 72 65 64 65 66 09 02 39 3A
   02 06 53 74 72 69 6E 67 0A 02 37 04 08 05 2F 00
   FFFFFF84 00 3C 14 02 31 3D 30 02 3E 43 10 03 35 3F 41
   09 02 40 3A 02 05 43 6C 61 73 73 10 02 42 43 0C
   00 04 08 44 3B FFFFFF84 FFFFFF80 FFFFFF80 FFFFFF82 00 45 02 03 5F 24 31
   11 02 46 25 10 02 0D 47 09 02 48 04 02 07 4E 6F
   74 68 69 6E 67 08 05 4A 00 FFFFFF84 20 4B 01 06 65 71
   75 61 6C 73 14 02 4C 25 10 02 0D 4D 09 02 4E 04
   02 07 42 6F 6F 6C 65 61 6E 08 05 50 00 FFFFFF84 20 51
   01 08 68 61 73 68 43 6F 64 65 14 01 16 08 05 53
   00 FFFFFF84 00 54 01 08 73 75 62 41 72 72 61 79 14 03
   13 16 16 08 05 56 00 FFFFFF84 22 57 01 06 66 69 6C 74
   65 72 14 02 08 58 10 04 0D 59 25 4C 09 02 5A 04
   02 09 46 75 6E 63 74 69 6F 6E 31 08 05 5C 00 FFFFFF84
   28 5D 01 08 6E 65 77 41 72 72 61 79 14 03 1E 16
   5E 10 03 0D 5F 25 09 02 60 04 02 08 49 74 65 72
   61 74 6F 72 28 02 00 62 10 02 0D 63 09 02 64 04
   02 0C 73 65 72 69 61 6C 69 7A 61 62 6C 65 
  SourceFile: "BoxedIntArray.scala"
  minor version: 0
  major version: 49
  Constant pool:
class	java/io/Serializable
class	java/lang/Object
class	scala/runtime/BoxedArray
class	scala/runtime/BoxedIntArray
class	scala/runtime/BoxesRunTime
Field	scala/runtime/BoxedIntArray.value:[I
Method	java/lang/Object.hashCode:()I
Method	scala/runtime/BoxedArray."<init>":()V
Method	scala/runtime/BoxedIntArray.apply:(I)Ljava/lang/Object;
Method	scala/runtime/BoxedIntArray.value:()[I
Method	scala/runtime/BoxesRunTime.boxToInteger:(I)Ljava/lang/Integer;
Method	scala/runtime/BoxesRunTime.unboxToInt:(Ljava/lang/Object;)I
NameAndType	"<init>":()V
NameAndType	apply:(I)Ljava/lang/Object;
NameAndType	boxToInteger:(I)Ljava/lang/Integer;
NameAndType	hashCode:()I
NameAndType	unboxToInt:(Ljava/lang/Object;)I
NameAndType	value:()[I
NameAndType	value:[I
Asciz	()I;
Asciz	()V;
Asciz	()[I;
Asciz	(I)Ljava/lang/Integer;;
Asciz	(I)Ljava/lang/Object;;
Asciz	(Ljava/lang/Class;)Ljava/lang/Object;;
Asciz	(Ljava/lang/Class<*>;)Ljava/lang/Object;;
Asciz	(Ljava/lang/Object;)I;
Asciz	(Ljava/lang/Object;)Ljava/lang/Object;;
Asciz	(Ljava/lang/Object;)Z;
Asciz	([I)V;
Asciz	<init>;
Asciz	BoxedIntArray.scala;
Asciz	Code;
Asciz	I;
Asciz	LineNumberTable;
Asciz	Ljava/lang/Class;;
Asciz	Ljava/lang/Object;;
Asciz	LocalVariableTable;
Asciz	Lscala/runtime/BoxedIntArray;;
Asciz	ScalaSig;
Asciz	Signature;
Asciz	SourceFile;
Asciz	[I;
Asciz	apply;
Asciz	boxToInteger;
Asciz	elemClass;
Asciz	equals;
Asciz	hashCode;
Asciz	index;
Asciz	java/io/Serializable;
Asciz	java/lang/Object;
Asciz	length;
Asciz	other;
Asciz	scala/runtime/BoxedArray;
Asciz	scala/runtime/BoxedIntArray;
Asciz	scala/runtime/BoxesRunTime;
Asciz	this;
Asciz	unbox;
Asciz	unboxToInt;
Asciz	value;
Asciz	x$1;

{
private final int[] value;
  Signature: [I

public scala.runtime.BoxedIntArray(int[]);
  Signature: ([I)V
  Code:
   Stack=2, Locals=2, Args_size=2
	aload_0
	aload_1
	putfield	Field value:[I
	aload_0
	invokespecial	Method scala/runtime/BoxedArray."<init>":()V
	return
  Labels:
  LocalVariableTable: 
   Start  Length  Slot  Name   Signature
   0      10      0    this       Lscala/runtime/BoxedIntArray;
   0      10      1    value       [I


public java.lang.Object apply(java.lang.Object);
  Signature: (Ljava/lang/Object;)Ljava/lang/Object;
  Code:
   Stack=2, Locals=2, Args_size=2
	aload_0
	aload_1
	invokestatic	Method scala/runtime/BoxesRunTime.unboxToInt:(Ljava/lang/Object;)I
	invokevirtual	Method apply:(I)Ljava/lang/Object;
	areturn
  Labels:
  LocalVariableTable: 
   Start  Length  Slot  Name   Signature
   0      9      0    this       Lscala/runtime/BoxedIntArray;
   0      9      1    x$1       Ljava/lang/Object;


public int hashCode();
  Signature: ()I
  Code:
   Stack=1, Locals=1, Args_size=1
	aload_0
	invokevirtual	Method value:()[I
	invokevirtual	Method java/lang/Object.hashCode:()I
	ireturn
  Labels:

public boolean equals(java.lang.Object);
  Signature: (Ljava/lang/Object;)Z
  Code:
   Stack=2, Locals=2, Args_size=2
	aload_0
	invokevirtual	Method value:()[I
	aload_1
	if_acmpeq	l1 // iconst_1
	aload_1
	instanceof	class scala/runtime/BoxedIntArray
	ifeq	l2 // iconst_0
	aload_0
	invokevirtual	Method value:()[I
	aload_1
	checkcast	class scala/runtime/BoxedIntArray
	invokevirtual	Method value:()[I
	if_acmpne	l2 // iconst_0
l1	iconst_1
	goto	l3 // ireturn
l2	iconst_0
l3	ireturn
  Labels:
   	l1 = 29 // iconst_1
   	l2 = 33 // iconst_0
   	l3 = 34 // ireturn
  LocalVariableTable: 
   Start  Length  Slot  Name   Signature
   0      35      0    this       Lscala/runtime/BoxedIntArray;
   0      35      1    other       Ljava/lang/Object;


public java.lang.Object unbox(java.lang.Class);
  Signature: (Ljava/lang/Class;)Ljava/lang/Object;
  Code:
   Stack=1, Locals=2, Args_size=2
	aload_0
	invokevirtual	Method value:()[I
	areturn
  Labels:
  LocalVariableTable: 
   Start  Length  Slot  Name   Signature
   0      5      0    this       Lscala/runtime/BoxedIntArray;
   0      5      1    elemClass       Ljava/lang/Class;

  Signature: length = 0x2
   00 1A 

public java.lang.Object apply(int);
  Signature: (I)Ljava/lang/Object;
  Code:
   Stack=2, Locals=2, Args_size=2
	aload_0
	invokevirtual	Method value:()[I
	iload_1
	iaload
	invokestatic	Method scala/runtime/BoxesRunTime.boxToInteger:(I)Ljava/lang/Integer;
	areturn
  Labels:
  LocalVariableTable: 
   Start  Length  Slot  Name   Signature
   0      10      0    this       Lscala/runtime/BoxedIntArray;
   0      10      1    index       I


public int length();
  Signature: ()I
  Code:
   Stack=1, Locals=1, Args_size=1
	aload_0
	invokevirtual	Method value:()[I
	arraylength
	ireturn
  Labels:

public int[] value();
  Signature: ()[I
  Code:
   Stack=1, Locals=1, Args_size=1
	aload_0
	getfield	Field value:[I
	areturn
  Labels:

}

