public class scala.runtime.IntRef extends java.lang.Object implements java.io.Serializable
  minor version: 0
  major version: 49
  Constant pool:
const #1 = Method	#5.#19;	//  java/lang/Object."<init>":()V
const #2 = Field	#4.#20;	//  scala/runtime/IntRef.elem:I
const #3 = Method	#21.#22;	//  java/lang/Integer.toString:(I)Ljava/lang/String;
const #4 = class	#23;	//  scala/runtime/IntRef
const #5 = class	#24;	//  java/lang/Object
const #6 = class	#25;	//  java/io/Serializable
const #7 = Asciz	serialVersionUID;
const #8 = Asciz	J;
const #9 = Asciz	ConstantValue;
const #10 = long	1488197132022872888l;
const #12 = Asciz	elem;
const #13 = Asciz	I;
const #14 = Asciz	<init>;
const #15 = Asciz	(I)V;
const #16 = Asciz	Code;
const #17 = Asciz	toString;
const #18 = Asciz	()Ljava/lang/String;;
const #19 = NameAndType	#14:#26;//  "<init>":()V
const #20 = NameAndType	#12:#13;//  elem:I
const #21 = class	#27;	//  java/lang/Integer
const #22 = NameAndType	#17:#28;//  toString:(I)Ljava/lang/String;
const #23 = Asciz	scala/runtime/IntRef;
const #24 = Asciz	java/lang/Object;
const #25 = Asciz	java/io/Serializable;
const #26 = Asciz	()V;
const #27 = Asciz	java/lang/Integer;
const #28 = Asciz	(I)Ljava/lang/String;;

{
public int elem;

public scala.runtime.IntRef(int);
  Code:
   Stack=2, Locals=2, Args_size=2
   0:	aload_0
   1:	invokespecial	#1; //Method java/lang/Object."<init>":()V
   4:	aload_0
   5:	iload_1
   6:	putfield	#2; //Field elem:I
   9:	return

public java.lang.String toString();
  Code:
   Stack=1, Locals=1, Args_size=1
   0:	aload_0
   1:	getfield	#2; //Field elem:I
   4:	invokestatic	#3; //Method java/lang/Integer.toString:(I)Ljava/lang/String;
   7:	areturn

}

