Compiled from "NonLocalReturnException.scala"
public class scala.runtime.NonLocalReturnException extends java.lang.RuntimeException implements scala.util.control.ControlException,scala.ScalaObject
  SourceFile: "NonLocalReturnException.scala"
  Signature: length = 0x2
   00 28 
  ScalaSig: length = 0x178
   05 00 3C 06 04 01 02 00 07 02 17 4E 6F 6E 4C 6F
   63 61 6C 52 65 74 75 72 6E 45 78 63 65 70 74 69
   6F 6E 0A 02 03 04 01 07 72 75 6E 74 69 6D 65 0A
   01 05 01 05 73 63 61 6C 61 03 00 15 02 08 2A 13
   04 00 09 11 19 10 02 0A 0F 0D 01 0B 0A 02 0C 0D
   01 04 6C 61 6E 67 0A 01 0E 01 04 6A 61 76 61 09
   02 10 0B 02 10 52 75 6E 74 69 6D 65 45 78 63 65
   70 74 69 6F 6E 10 02 12 17 0D 01 13 0A 02 14 15
   01 07 63 6F 6E 74 72 6F 6C 0A 02 16 04 01 04 75
   74 69 6C 09 02 18 13 02 10 43 6F 6E 74 72 6F 6C
   45 78 63 65 70 74 69 6F 6E 10 02 1A 1B 0D 01 04
   09 02 1C 04 02 0B 53 63 61 6C 61 4F 62 6A 65 63
   74 08 08 1E 00 FFFFFF82 FFFFFFC2 FFFFFF80 FFFFFF84 00 1F 01 03 6B 65 79
   15 01 20 10 02 1A 21 09 02 22 04 02 06 41 6E 79
   52 65 66 08 08 24 00 FFFFFF82 FFFFFF80 FFFFFFA0 FFFFFF80 04 20 01 04 6B
   65 79 20 08 08 26 00 FFFFFF82 FFFFFFC2 FFFFFF80 FFFFFF84 00 27 01 05 76
   61 6C 75 65 15 01 28 10 02 29 2A 0C 00 04 08 2B
   00 FFFFFF84 FFFFFF80 FFFFFF80 FFFFFFC2 00 2C 02 01 54 11 02 2D 30 10 02
   1A 2E 09 02 2F 04 02 07 4E 6F 74 68 69 6E 67 10
   02 1A 31 09 02 32 04 02 03 41 6E 79 08 08 34 00
   FFFFFF82 FFFFFF80 FFFFFFA0 FFFFFF80 04 28 01 06 76 61 6C 75 65 20 08 05
   36 00 FFFFFF84 00 37 01 06 3C 69 6E 69 74 3E 14 03 38
   3A 3B 10 03 39 00 28 0D 01 02 08 05 1E 35 FFFFFFC0 00
   20 08 05 26 35 FFFFFFC0 00 28 
  minor version: 0
  major version: 49
  Constant pool:
Asciz	SourceFile;
Asciz	NonLocalReturnException.scala;
Asciz	value;
Asciz	Ljava/lang/Object;;
Asciz	TT;;
Asciz	Signature;
Asciz	key;
Asciz	fillInStackTrace;
Asciz	()Ljava/lang/Throwable;;
Asciz	Code;
Asciz	LineNumberTable;
Asciz	scala/util/control/NoStackTrace$class;
class	scala/util/control/NoStackTrace$class
Asciz	(Lscala/util/control/NoStackTrace;)Ljava/lang/Throwable;;
NameAndType	fillInStackTrace:(Lscala/util/control/NoStackTrace;)Ljava/lang/Throwable;
Method	scala/util/control/NoStackTrace$class.fillInStackTrace:(Lscala/util/control/NoStackTrace;)Ljava/lang/Throwable;
Asciz	()Ljava/lang/Object;;
Asciz	scala/runtime/NonLocalReturnException;
class	scala/runtime/NonLocalReturnException
NameAndType	key:Ljava/lang/Object;
Field	scala/runtime/NonLocalReturnException.key:Ljava/lang/Object;
NameAndType	value:Ljava/lang/Object;
Field	scala/runtime/NonLocalReturnException.value:Ljava/lang/Object;
Asciz	()TT;;
Asciz	<init>;
Asciz	(Ljava/lang/Object;Ljava/lang/Object;)V;
Asciz	java/lang/RuntimeException;
class	java/lang/RuntimeException
Asciz	()V;
NameAndType	"<init>":()V
Method	java/lang/RuntimeException."<init>":()V
Asciz	$init$;
Asciz	(Lscala/util/control/NoStackTrace;)V;
NameAndType	$init$:(Lscala/util/control/NoStackTrace;)V
Method	scala/util/control/NoStackTrace$class.$init$:(Lscala/util/control/NoStackTrace;)V
Asciz	this;
Asciz	Lscala/runtime/NonLocalReturnException;;
Asciz	LocalVariableTable;
Asciz	(Ljava/lang/Object;TT;)V;
Asciz	<T:Ljava/lang/Object;>Ljava/lang/RuntimeException;Lscala/util/control/ControlException;Lscala/ScalaObject;;
Asciz	ScalaSig;
Asciz	scala/util/control/ControlException;
class	scala/util/control/ControlException
Asciz	scala/ScalaObject;
class	scala/ScalaObject

{
private final java.lang.Object value;
  Signature: Ljava/lang/Object;
  Signature: length = 0x2
   00 05 

private final java.lang.Object key;
  Signature: Ljava/lang/Object;

public java.lang.Throwable fillInStackTrace();
  Signature: ()Ljava/lang/Throwable;
  Code:
   Stack=1, Locals=1, Args_size=1
	aload_0
	invokestatic	Method scala/util/control/NoStackTrace$class.fillInStackTrace:(Lscala/util/control/NoStackTrace;)Ljava/lang/Throwable;
	areturn
  Labels:

public java.lang.Object key();
  Signature: ()Ljava/lang/Object;
  Code:
   Stack=1, Locals=1, Args_size=1
	aload_0
	getfield	Field key:Ljava/lang/Object;
	areturn
  Labels:

public java.lang.Object value();
  Signature: ()Ljava/lang/Object;
  Code:
   Stack=1, Locals=1, Args_size=1
	aload_0
	getfield	Field value:Ljava/lang/Object;
	areturn
  Labels:
  Signature: length = 0x2
   00 18 

public scala.runtime.NonLocalReturnException(java.lang.Object, java.lang.Object);
  Signature: (Ljava/lang/Object;Ljava/lang/Object;)V
  Code:
   Stack=2, Locals=3, Args_size=3
	aload_0
	aload_1
	putfield	Field key:Ljava/lang/Object;
	aload_0
	aload_2
	putfield	Field value:Ljava/lang/Object;
	aload_0
	invokespecial	Method java/lang/RuntimeException."<init>":()V
	aload_0
	invokestatic	Method scala/util/control/NoStackTrace$class.$init$:(Lscala/util/control/NoStackTrace;)V
	return
  Labels:
  LocalVariableTable: 
   Start  Length  Slot  Name   Signature
   0      19      0    this       Lscala/runtime/NonLocalReturnException;
   0      19      1    key       Ljava/lang/Object;
   0      19      2    value       Ljava/lang/Object;

  Signature: length = 0x2
   00 27 

}

