Compiled from "RichString.scala"
public class scala.runtime.RichString extends java.lang.Object implements scala.Proxy,scala.collection.immutable.Vector,scala.collection.generic.VectorTemplate,scala.PartialFunction,scala.Ordered,scala.ScalaObject
  SourceFile: "RichString.scala"
  Signature: length = 0x2
   04 00 
  ScalaSig: length = 0x753
   05 00 FFFFFF82 10 07 05 01 02 FFFFFF88 02 07 01 0A 52 69 63
   68 53 74 72 69 6E 67 0A 02 03 04 01 07 72 75 6E
   74 69 6D 65 0A 01 05 01 05 73 63 61 6C 61 03 00
   10 02 08 09 0D 01 02 06 08 0A 02 FFFFFF84 FFFFFF80 FFFFFF80 FFFFFF88 02
   0B 02 0A 52 69 63 68 53 74 72 69 6E 67 13 03 09
   0C 14 10 02 0D 12 0D 01 0E 0A 02 0F 10 01 04 6C
   61 6E 67 0A 01 11 01 04 6A 61 76 61 09 02 13 0E
   02 06 4F 62 6A 65 63 74 10 02 15 16 0D 01 04 09
   02 17 04 02 0B 53 63 61 6C 61 4F 62 6A 65 63 74
   08 05 19 09 FFFFFF84 00 1A 01 06 3C 69 6E 69 74 3E 14
   01 07 08 05 1C 09 FFFFFF84 00 1D 01 0A 6E 65 77 42 75
   69 6C 64 65 72 15 01 1E 10 04 1F 24 26 29 0D 01
   20 0A 02 21 22 01 07 67 65 6E 65 72 69 63 0A 02
   23 04 01 0A 63 6F 6C 6C 65 63 74 69 6F 6E 09 02
   25 20 02 07 42 75 69 6C 64 65 72 10 02 15 27 09
   02 28 04 02 04 43 68 61 72 10 02 08 2A 06 08 0A
   02 FFFFFF84 FFFFFF80 FFFFFF80 FFFFFF80 00 2B 13 08 2A 0C 2C 2F 35 38 3E
   14 10 02 15 2D 09 02 2E 04 02 05 50 72 6F 78 79
   10 03 30 33 26 0D 01 31 0A 02 32 22 01 09 69 6D
   6D 75 74 61 62 6C 65 09 02 34 31 02 06 56 65 63
   74 6F 72 10 04 1F 36 26 29 09 02 37 20 02 0E 56
   65 63 74 6F 72 54 65 6D 70 6C 61 74 65 10 04 15
   39 3B 26 09 02 3A 04 02 0F 50 61 72 74 69 61 6C
   46 75 6E 63 74 69 6F 6E 10 02 15 3C 09 02 3D 04
   02 03 49 6E 74 10 03 15 3F 41 09 02 40 04 02 07
   4F 72 64 65 72 65 64 10 02 42 45 0E 02 15 43 09
   02 44 04 01 06 50 72 65 64 65 66 09 02 46 47 02
   06 53 74 72 69 6E 67 0A 02 44 04 08 08 49 2A FFFFFF82
   FFFFFFC2 FFFFFF80 FFFFFF84 00 4A 01 04 73 65 6C 66 15 01 41 08 08
   4C 2A FFFFFF82 FFFFFF80 FFFFFFA0 FFFFFF80 04 41 01 05 73 65 6C 66 20 08
   05 19 2A FFFFFF84 00 4E 14 02 29 4F 08 05 49 4D FFFFFFC0 00
   41 08 06 1C 2A FFFFFFA0 FFFFFF84 28 1D 08 05 52 2A FFFFFF84 00 53
   01 05 61 70 70 6C 79 14 02 26 54 08 05 55 51 FFFFFFC0
   00 3B 01 01 6E 08 05 57 2A FFFFFF84 00 58 01 06 6C 65
   6E 67 74 68 15 01 3B 08 05 5A 2A FFFFFF84 20 4A 01 08
   6D 6B 53 74 72 69 6E 67 08 05 5C 2A FFFFFF84 20 5D 01
   08 74 6F 53 74 72 69 6E 67 14 01 41 08 05 5F 2A
   FFFFFF84 00 60 01 06 24 74 69 6D 65 73 14 02 41 61 08
   05 55 5E FFFFFFC0 00 3B 08 05 63 2A FFFFFF84 20 64 01 07 63
   6F 6D 70 61 72 65 14 02 3B 65 08 05 66 62 FFFFFFC0 00
   41 01 05 6F 74 68 65 72 08 05 68 2A FFFFFF84 04 69 01
   0B 69 73 4C 69 6E 65 42 72 65 61 6B 14 02 6A 6D
   10 02 15 6B 09 02 6C 04 02 07 42 6F 6F 6C 65 61
   6E 08 05 6E 67 FFFFFFC0 00 26 01 01 63 08 05 70 2A FFFFFF84
   00 4A 01 0C 73 74 72 69 70 4C 69 6E 65 45 6E 64
   08 05 72 2A FFFFFF84 00 73 01 13 6C 69 6E 65 73 57 69
   74 68 53 65 70 61 72 61 74 6F 72 73 15 01 74 10
   03 75 7D 41 0E 02 76 7B 0E 02 77 7A 0D 01 78 0A
   02 79 06 01 06 3C 72 6F 6F 74 3E 09 01 05 09 02
   7C 04 01 07 70 61 63 6B 61 67 65 09 02 7E 7F 02
   08 49 74 65 72 61 74 6F 72 0A 02 7C 04 08 06 FFFFFF81
   01 2A FFFFFF84 00 73 01 05 6C 69 6E 65 73 08 06 FFFFFF81 03
   2A FFFFFF84 00 73 01 0D 6C 69 6E 65 73 49 74 65 72 61
   74 6F 72 08 06 FFFFFF81 05 2A FFFFFF84 00 4A 01 0A 63 61 70
   69 74 61 6C 69 7A 65 08 07 FFFFFF81 07 2A FFFFFF84 00 FFFFFF81 08
   01 0B 73 74 72 69 70 4D 61 72 67 69 6E 14 03 41
   FFFFFF81 09 08 07 FFFFFF81 0A FFFFFF81 06 FFFFFFC0 00 26 01 0A 6D 61 72
   67 69 6E 43 68 61 72 08 06 FFFFFF81 07 2A FFFFFF84 00 4A 08
   07 FFFFFF81 0D 2A FFFFFF84 04 FFFFFF81 0E 01 06 65 73 63 61 70 65
   14 03 41 FFFFFF81 0F 08 07 FFFFFF81 10 FFFFFF81 0C FFFFFFC0 00 26 01 02
   63 68 08 07 FFFFFF81 12 2A FFFFFF84 00 FFFFFF81 13 01 05 73 70 6C
   69 74 14 04 FFFFFF81 14 FFFFFF81 17 10 04 15 FFFFFF81 15 41 09 03
   FFFFFF81 16 04 02 05 41 72 72 61 79 08 07 FFFFFF81 18 FFFFFF81 11
   FFFFFFC0 00 26 01 09 73 65 70 61 72 61 74 6F 72 28 06
   FFFFFF81 11 FFFFFF81 1A FFFFFF81 1D 10 03 15 FFFFFF81 1B 09 03 FFFFFF81 1C 04
   02 06 74 68 72 6F 77 73 23 02 FFFFFF81 1E 10 04 FFFFFF81 1F
   FFFFFF81 24 0D 02 FFFFFF81 20 0A 04 FFFFFF81 21 FFFFFF81 22 01 05 72 65
   67 65 78 0A 03 FFFFFF81 23 10 01 04 75 74 69 6C 09 04
   FFFFFF81 25 FFFFFF81 20 02 16 50 61 74 74 65 72 6E 53 79 6E
   74 61 78 45 78 63 65 70 74 69 6F 6E 08 07 FFFFFF81 12
   2A FFFFFF84 00 FFFFFF81 27 14 04 FFFFFF81 14 FFFFFF81 28 08 08 FFFFFF81 29 FFFFFF81
   26 FFFFFFC0 00 FFFFFF81 2A 01 0A 73 65 70 61 72 61 74 6F 72
   73 10 04 15 FFFFFF81 15 26 28 06 FFFFFF81 26 FFFFFF81 1A FFFFFF81 1D 08
   07 FFFFFF81 2D 2A FFFFFF84 00 FFFFFF81 2E 01 01 72 15 02 FFFFFF81 2F 10
   04 FFFFFF81 30 FFFFFF81 34 0D 02 FFFFFF81 31 0A 04 FFFFFF81 32 FFFFFF81 33 01
   08 6D 61 74 63 68 69 6E 67 0A 03 FFFFFF81 23 04 09 04
   FFFFFF81 35 FFFFFF81 31 02 05 52 65 67 65 78 08 07 FFFFFF81 37 2A
   FFFFFF84 00 FFFFFF81 38 01 09 74 6F 42 6F 6F 6C 65 61 6E 15
   01 6A 08 07 FFFFFF81 3A 2A FFFFFF84 00 FFFFFF81 3B 01 06 74 6F 42
   79 74 65 15 02 FFFFFF81 3C 10 03 15 FFFFFF81 3D 09 03 FFFFFF81 3E
   04 02 04 42 79 74 65 08 07 FFFFFF81 40 2A FFFFFF84 00 FFFFFF81 41
   01 07 74 6F 53 68 6F 72 74 15 02 FFFFFF81 42 10 03 15
   FFFFFF81 43 09 03 FFFFFF81 44 04 02 05 53 68 6F 72 74 08 06
   FFFFFF81 46 2A FFFFFF84 00 58 01 05 74 6F 49 6E 74 08 07 FFFFFF81
   48 2A FFFFFF84 00 FFFFFF81 49 01 06 74 6F 4C 6F 6E 67 15 02
   FFFFFF81 4A 10 03 15 FFFFFF81 4B 09 03 FFFFFF81 4C 04 02 04 4C 6F
   6E 67 08 07 FFFFFF81 4E 2A FFFFFF84 00 FFFFFF81 4F 01 07 74 6F 46
   6C 6F 61 74 15 02 FFFFFF81 50 10 03 15 FFFFFF81 51 09 03 FFFFFF81
   52 04 02 05 46 6C 6F 61 74 08 07 FFFFFF81 54 2A FFFFFF84 00
   FFFFFF81 55 01 08 74 6F 44 6F 75 62 6C 65 15 02 FFFFFF81 56
   10 03 15 FFFFFF81 57 09 03 FFFFFF81 58 04 02 06 44 6F 75 62
   6C 65 08 07 FFFFFF81 5A 2A FFFFFF84 04 FFFFFF81 5B 01 0C 70 61 72
   73 65 42 6F 6F 6C 65 61 6E 14 03 6A FFFFFF81 5C 08 07
   FFFFFF81 5D FFFFFF81 59 FFFFFFC0 00 41 01 01 73 08 07 FFFFFF81 5F 2A FFFFFF84
   00 FFFFFF81 60 01 07 74 6F 41 72 72 61 79 15 02 FFFFFF81 2A
   08 07 FFFFFF81 62 2A FFFFFF84 00 FFFFFF81 63 01 06 66 6F 72 6D 61
   74 14 03 41 FFFFFF81 64 08 08 FFFFFF81 65 FFFFFF81 61 FFFFFFC0 00 FFFFFF81 66
   01 04 61 72 67 73 10 05 15 FFFFFF81 67 FFFFFF81 69 09 03 FFFFFF81
   68 04 02 0A 3C 72 65 70 65 61 74 65 64 3E 10 03
   15 FFFFFF81 6A 09 03 FFFFFF81 6B 04 02 03 41 6E 79 08 07 FFFFFF81
   62 2A FFFFFF84 00 FFFFFF81 6D 14 05 41 FFFFFF81 6E FFFFFF81 74 08 08 FFFFFF81
   6F FFFFFF81 6C FFFFFFC0 00 FFFFFF81 70 01 01 6C 10 04 FFFFFF81 71 FFFFFF81 72
   0D 02 FFFFFF81 22 09 04 FFFFFF81 73 FFFFFF81 22 02 06 4C 6F 63 61
   6C 65 08 08 FFFFFF81 65 FFFFFF81 6C FFFFFFC0 00 FFFFFF81 66 08 07 FFFFFF81 76
   09 FFFFFF84 01 FFFFFF81 77 01 0E 62 75 69 6C 64 65 72 46 61
   63 74 6F 72 79 15 02 FFFFFF81 78 10 06 1F FFFFFF81 79 26 29
   29 09 03 FFFFFF81 7A 20 02 0E 42 75 69 6C 64 65 72 46
   61 63 74 6F 72 79 08 07 FFFFFF81 7C 09 FFFFFF84 01 FFFFFF81 7D 01
   0F 62 75 69 6C 64 65 72 46 61 63 74 6F 72 79 32
   15 02 FFFFFF81 7E 10 06 1F FFFFFF81 79 26 29 41 08 09 FFFFFF82 00
   09 FFFFFFC2 FFFFFF80 FFFFFF84 06 FFFFFF82 01 01 02 4C 46 15 01 26 08 07
   FFFFFF82 03 09 FFFFFFA0 FFFFFF80 06 26 01 03 4C 46 20 08 09 FFFFFF82 05
   09 FFFFFFC2 FFFFFF80 FFFFFF84 06 FFFFFF82 01 01 02 46 46 08 07 FFFFFF82 07 09
   FFFFFFA0 FFFFFF80 06 26 01 03 46 46 20 08 09 FFFFFF82 09 09 FFFFFFC2 FFFFFF80
   FFFFFF84 06 FFFFFF82 01 01 02 43 52 08 07 FFFFFF82 0B 09 FFFFFFA0 FFFFFF80 06
   26 01 03 43 52 20 08 09 FFFFFF82 0D 09 FFFFFFC2 FFFFFF80 FFFFFF84 06 FFFFFF82
   01 01 02 53 55 08 07 FFFFFF82 0F 09 FFFFFFA0 FFFFFF80 06 26 01 03
   53 55 20 
  InnerClass: 
   public final #1029= #1028 of #10; //$anon$2=class scala/runtime/RichString$$anon$2 of class scala/runtime/RichString
   public final #1030= #448 of #10; //$anon$1=class scala/runtime/RichString$$anon$1 of class scala/runtime/RichString
   public final #1033= #1032 of #10; //$anon$3=class scala/runtime/RichString$$anon$3 of class scala/runtime/RichString
   public final #1034= #355 of #10; //$anonfun$1=class scala/runtime/RichString$$anonfun$1 of class scala/runtime/RichString
   public final #1035= #445 of #10; //$anonfun$lines$1=class scala/runtime/RichString$$anonfun$lines$1 of class scala/runtime/RichString
   public final #1036= #492 of #10; //$anonfun$$times$1=class scala/runtime/RichString$$anonfun$$times$1 of class scala/runtime/RichString
   public final #1039= #1038 of #10; //$anonfun$newBuilder$1=class scala/runtime/RichString$$anonfun$newBuilder$1 of class scala/runtime/RichString
   public final #1040= #395 of #10; //$anonfun$stripMargin$1=class scala/runtime/RichString$$anonfun$stripMargin$1 of class scala/runtime/RichString
   public final #1041= #436 of #10; //$anonfun$linesIterator$1=class scala/runtime/RichString$$anonfun$linesIterator$1 of class scala/runtime/RichString
  minor version: 0
  major version: 49
  Constant pool:
const #1 = Asciz	SourceFile;
const #2 = Asciz	RichString.scala;
const #3 = Asciz	self;
const #4 = Asciz	Ljava/lang/String;;
const #5 = Asciz	<init>;
const #6 = Asciz	(Ljava/lang/String;)V;
const #7 = Asciz	Code;
const #8 = Asciz	LineNumberTable;
const #9 = Asciz	scala/runtime/RichString;
const #10 = class	#9;	//  scala/runtime/RichString
const #11 = NameAndType	#3:#4;//  self:Ljava/lang/String;
const #12 = Field	#10.#11;	//  scala/runtime/RichString.self:Ljava/lang/String;
const #13 = Asciz	java/lang/Object;
const #14 = class	#13;	//  java/lang/Object
const #15 = Asciz	()V;
const #16 = NameAndType	#5:#15;//  "<init>":()V
const #17 = Method	#14.#16;	//  java/lang/Object."<init>":()V
const #18 = Asciz	scala/Proxy$class;
const #19 = class	#18;	//  scala/Proxy$class
const #20 = Asciz	$init$;
const #21 = Asciz	(Lscala/Proxy;)V;
const #22 = NameAndType	#20:#21;//  $init$:(Lscala/Proxy;)V
const #23 = Method	#19.#22;	//  scala/Proxy$class.$init$:(Lscala/Proxy;)V
const #24 = Asciz	scala/collection/generic/TraversableTemplate$class;
const #25 = class	#24;	//  scala/collection/generic/TraversableTemplate$class
const #26 = Asciz	(Lscala/collection/generic/TraversableTemplate;)V;
const #27 = NameAndType	#20:#26;//  $init$:(Lscala/collection/generic/TraversableTemplate;)V
const #28 = Method	#25.#27;	//  scala/collection/generic/TraversableTemplate$class.$init$:(Lscala/collection/generic/TraversableTemplate;)V
const #29 = Asciz	scala/collection/generic/TraversableClass$class;
const #30 = class	#29;	//  scala/collection/generic/TraversableClass$class
const #31 = Asciz	(Lscala/collection/generic/TraversableClass;)V;
const #32 = NameAndType	#20:#31;//  $init$:(Lscala/collection/generic/TraversableClass;)V
const #33 = Method	#30.#32;	//  scala/collection/generic/TraversableClass$class.$init$:(Lscala/collection/generic/TraversableClass;)V
const #34 = Asciz	scala/collection/Traversable$class;
const #35 = class	#34;	//  scala/collection/Traversable$class
const #36 = Asciz	(Lscala/collection/Traversable;)V;
const #37 = NameAndType	#20:#36;//  $init$:(Lscala/collection/Traversable;)V
const #38 = Method	#35.#37;	//  scala/collection/Traversable$class.$init$:(Lscala/collection/Traversable;)V
const #39 = Asciz	scala/collection/immutable/Traversable$class;
const #40 = class	#39;	//  scala/collection/immutable/Traversable$class
const #41 = Asciz	(Lscala/collection/immutable/Traversable;)V;
const #42 = NameAndType	#20:#41;//  $init$:(Lscala/collection/immutable/Traversable;)V
const #43 = Method	#40.#42;	//  scala/collection/immutable/Traversable$class.$init$:(Lscala/collection/immutable/Traversable;)V
const #44 = Asciz	scala/collection/generic/IterableTemplate$class;
const #45 = class	#44;	//  scala/collection/generic/IterableTemplate$class
const #46 = Asciz	(Lscala/collection/generic/IterableTemplate;)V;
const #47 = NameAndType	#20:#46;//  $init$:(Lscala/collection/generic/IterableTemplate;)V
const #48 = Method	#45.#47;	//  scala/collection/generic/IterableTemplate$class.$init$:(Lscala/collection/generic/IterableTemplate;)V
const #49 = Asciz	scala/collection/Iterable$class;
const #50 = class	#49;	//  scala/collection/Iterable$class
const #51 = Asciz	(Lscala/collection/Iterable;)V;
const #52 = NameAndType	#20:#51;//  $init$:(Lscala/collection/Iterable;)V
const #53 = Method	#50.#52;	//  scala/collection/Iterable$class.$init$:(Lscala/collection/Iterable;)V
const #54 = Asciz	scala/collection/immutable/Iterable$class;
const #55 = class	#54;	//  scala/collection/immutable/Iterable$class
const #56 = Asciz	(Lscala/collection/immutable/Iterable;)V;
const #57 = NameAndType	#20:#56;//  $init$:(Lscala/collection/immutable/Iterable;)V
const #58 = Method	#55.#57;	//  scala/collection/immutable/Iterable$class.$init$:(Lscala/collection/immutable/Iterable;)V
const #59 = Asciz	scala/Function1$class;
const #60 = class	#59;	//  scala/Function1$class
const #61 = Asciz	(Lscala/Function1;)V;
const #62 = NameAndType	#20:#61;//  $init$:(Lscala/Function1;)V
const #63 = Method	#60.#62;	//  scala/Function1$class.$init$:(Lscala/Function1;)V
const #64 = Asciz	scala/PartialFunction$class;
const #65 = class	#64;	//  scala/PartialFunction$class
const #66 = Asciz	(Lscala/PartialFunction;)V;
const #67 = NameAndType	#20:#66;//  $init$:(Lscala/PartialFunction;)V
const #68 = Method	#65.#67;	//  scala/PartialFunction$class.$init$:(Lscala/PartialFunction;)V
const #69 = Asciz	scala/collection/generic/SequenceTemplate$class;
const #70 = class	#69;	//  scala/collection/generic/SequenceTemplate$class
const #71 = Asciz	(Lscala/collection/generic/SequenceTemplate;)V;
const #72 = NameAndType	#20:#71;//  $init$:(Lscala/collection/generic/SequenceTemplate;)V
const #73 = Method	#70.#72;	//  scala/collection/generic/SequenceTemplate$class.$init$:(Lscala/collection/generic/SequenceTemplate;)V
const #74 = Asciz	scala/collection/Sequence$class;
const #75 = class	#74;	//  scala/collection/Sequence$class
const #76 = Asciz	(Lscala/collection/Sequence;)V;
const #77 = NameAndType	#20:#76;//  $init$:(Lscala/collection/Sequence;)V
const #78 = Method	#75.#77;	//  scala/collection/Sequence$class.$init$:(Lscala/collection/Sequence;)V
const #79 = Asciz	scala/collection/immutable/Sequence$class;
const #80 = class	#79;	//  scala/collection/immutable/Sequence$class
const #81 = Asciz	(Lscala/collection/immutable/Sequence;)V;
const #82 = NameAndType	#20:#81;//  $init$:(Lscala/collection/immutable/Sequence;)V
const #83 = Method	#80.#82;	//  scala/collection/immutable/Sequence$class.$init$:(Lscala/collection/immutable/Sequence;)V
const #84 = Asciz	scala/collection/generic/VectorTemplate$class;
const #85 = class	#84;	//  scala/collection/generic/VectorTemplate$class
const #86 = Asciz	(Lscala/collection/generic/VectorTemplate;)V;
const #87 = NameAndType	#20:#86;//  $init$:(Lscala/collection/generic/VectorTemplate;)V
const #88 = Method	#85.#87;	//  scala/collection/generic/VectorTemplate$class.$init$:(Lscala/collection/generic/VectorTemplate;)V
const #89 = Asciz	scala/collection/Vector$class;
const #90 = class	#89;	//  scala/collection/Vector$class
const #91 = Asciz	(Lscala/collection/Vector;)V;
const #92 = NameAndType	#20:#91;//  $init$:(Lscala/collection/Vector;)V
const #93 = Method	#90.#92;	//  scala/collection/Vector$class.$init$:(Lscala/collection/Vector;)V
const #94 = Asciz	scala/collection/immutable/Vector$class;
const #95 = class	#94;	//  scala/collection/immutable/Vector$class
const #96 = Asciz	(Lscala/collection/immutable/Vector;)V;
const #97 = NameAndType	#20:#96;//  $init$:(Lscala/collection/immutable/Vector;)V
const #98 = Method	#95.#97;	//  scala/collection/immutable/Vector$class.$init$:(Lscala/collection/immutable/Vector;)V
const #99 = Asciz	scala/Ordered$class;
const #100 = class	#99;	//  scala/Ordered$class
const #101 = Asciz	(Lscala/Ordered;)V;
const #102 = NameAndType	#20:#101;//  $init$:(Lscala/Ordered;)V
const #103 = Method	#100.#102;	//  scala/Ordered$class.$init$:(Lscala/Ordered;)V
const #104 = Asciz	this;
const #105 = Asciz	Lscala/runtime/RichString;;
const #106 = Asciz	LocalVariableTable;
const #107 = Asciz	()Ljava/lang/Object;;
const #108 = Asciz	()Ljava/lang/String;;
const #109 = NameAndType	#3:#108;//  self:()Ljava/lang/String;
const #110 = Method	#10.#109;	//  scala/runtime/RichString.self:()Ljava/lang/String;
const #111 = Asciz	apply;
const #112 = Asciz	(I)Ljava/lang/Object;;
const #113 = Asciz	(I)C;
const #114 = NameAndType	#111:#113;//  apply:(I)C
const #115 = Method	#10.#114;	//  scala/runtime/RichString.apply:(I)C
const #116 = Asciz	scala/runtime/BoxesRunTime;
const #117 = class	#116;	//  scala/runtime/BoxesRunTime
const #118 = Asciz	boxToCharacter;
const #119 = Asciz	(C)Ljava/lang/Character;;
const #120 = NameAndType	#118:#119;//  boxToCharacter:(C)Ljava/lang/Character;
const #121 = Method	#117.#120;	//  scala/runtime/BoxesRunTime.boxToCharacter:(C)Ljava/lang/Character;
const #122 = Asciz	idx;
const #123 = Asciz	I;
const #124 = Asciz	(Ljava/lang/Object;)Ljava/lang/Object;;
const #125 = Asciz	unboxToInt;
const #126 = Asciz	(Ljava/lang/Object;)I;
const #127 = NameAndType	#125:#126;//  unboxToInt:(Ljava/lang/Object;)I
const #128 = Method	#117.#127;	//  scala/runtime/BoxesRunTime.unboxToInt:(Ljava/lang/Object;)I
const #129 = Asciz	v1;
const #130 = Asciz	Ljava/lang/Object;;
const #131 = Asciz	compare;
const #132 = Asciz	java/lang/String;
const #133 = class	#132;	//  java/lang/String
const #134 = Asciz	(Ljava/lang/String;)I;
const #135 = NameAndType	#131:#134;//  compare:(Ljava/lang/String;)I
const #136 = Method	#10.#135;	//  scala/runtime/RichString.compare:(Ljava/lang/String;)I
const #137 = Asciz	that;
const #138 = Asciz	slice;
const #139 = Asciz	(II)Lscala/collection/generic/TraversableTemplate;;
const #140 = Asciz	scala/collection/generic/VectorTemplate;
const #141 = class	#140;	//  scala/collection/generic/VectorTemplate
const #142 = Asciz	(II)Lscala/collection/generic/VectorTemplate;;
const #143 = NameAndType	#138:#142;//  slice:(II)Lscala/collection/generic/VectorTemplate;
const #144 = InterfaceMethod	#141.#143;	//  scala/collection/generic/VectorTemplate.slice:(II)Lscala/collection/generic/VectorTemplate;
const #145 = Asciz	from;
const #146 = Asciz	until;
const #147 = Asciz	tail;
const #148 = Asciz	()Lscala/collection/generic/TraversableTemplate;;
const #149 = Asciz	()Lscala/collection/generic/VectorTemplate;;
const #150 = NameAndType	#147:#149;//  tail:()Lscala/collection/generic/VectorTemplate;
const #151 = InterfaceMethod	#141.#150;	//  scala/collection/generic/VectorTemplate.tail:()Lscala/collection/generic/VectorTemplate;
const #152 = Asciz	init;
const #153 = NameAndType	#152:#149;//  init:()Lscala/collection/generic/VectorTemplate;
const #154 = InterfaceMethod	#141.#153;	//  scala/collection/generic/VectorTemplate.init:()Lscala/collection/generic/VectorTemplate;
const #155 = Asciz	take;
const #156 = Asciz	(I)Lscala/collection/generic/TraversableTemplate;;
const #157 = Asciz	(I)Lscala/collection/generic/VectorTemplate;;
const #158 = NameAndType	#155:#157;//  take:(I)Lscala/collection/generic/VectorTemplate;
const #159 = InterfaceMethod	#141.#158;	//  scala/collection/generic/VectorTemplate.take:(I)Lscala/collection/generic/VectorTemplate;
const #160 = Asciz	n;
const #161 = Asciz	drop;
const #162 = NameAndType	#161:#157;//  drop:(I)Lscala/collection/generic/VectorTemplate;
const #163 = InterfaceMethod	#141.#162;	//  scala/collection/generic/VectorTemplate.drop:(I)Lscala/collection/generic/VectorTemplate;
const #164 = Asciz	takeRight;
const #165 = Asciz	(I)Lscala/collection/generic/IterableTemplate;;
const #166 = NameAndType	#164:#157;//  takeRight:(I)Lscala/collection/generic/VectorTemplate;
const #167 = InterfaceMethod	#141.#166;	//  scala/collection/generic/VectorTemplate.takeRight:(I)Lscala/collection/generic/VectorTemplate;
const #168 = Asciz	dropRight;
const #169 = NameAndType	#168:#157;//  dropRight:(I)Lscala/collection/generic/VectorTemplate;
const #170 = InterfaceMethod	#141.#169;	//  scala/collection/generic/VectorTemplate.dropRight:(I)Lscala/collection/generic/VectorTemplate;
const #171 = Asciz	takeWhile;
const #172 = Asciz	(Lscala/Function1;)Lscala/collection/generic/TraversableTemplate;;
const #173 = Asciz	(Lscala/Function1;)Lscala/collection/generic/VectorTemplate;;
const #174 = NameAndType	#171:#173;//  takeWhile:(Lscala/Function1;)Lscala/collection/generic/VectorTemplate;
const #175 = InterfaceMethod	#141.#174;	//  scala/collection/generic/VectorTemplate.takeWhile:(Lscala/Function1;)Lscala/collection/generic/VectorTemplate;
const #176 = Asciz	p;
const #177 = Asciz	Lscala/Function1;;
const #178 = Asciz	dropWhile;
const #179 = NameAndType	#178:#173;//  dropWhile:(Lscala/Function1;)Lscala/collection/generic/VectorTemplate;
const #180 = InterfaceMethod	#141.#179;	//  scala/collection/generic/VectorTemplate.dropWhile:(Lscala/Function1;)Lscala/collection/generic/VectorTemplate;
const #181 = Asciz	reverse;
const #182 = Asciz	()Lscala/collection/generic/IterableTemplate;;
const #183 = NameAndType	#181:#149;//  reverse:()Lscala/collection/generic/VectorTemplate;
const #184 = InterfaceMethod	#141.#183;	//  scala/collection/generic/VectorTemplate.reverse:()Lscala/collection/generic/VectorTemplate;
const #185 = Asciz	view;
const #186 = Asciz	(II)Lscala/collection/generic/SequenceView;;
const #187 = Asciz	(II)Lscala/collection/generic/VectorView;;
const #188 = NameAndType	#185:#187;//  view:(II)Lscala/collection/generic/VectorView;
const #189 = InterfaceMethod	#141.#188;	//  scala/collection/generic/VectorTemplate.view:(II)Lscala/collection/generic/VectorView;
const #190 = Asciz	(II)Lscala/collection/generic/IterableView;;
const #191 = Asciz	(II)Lscala/collection/generic/TraversableView;;
const #192 = Asciz	isDefinedAt;
const #193 = Asciz	(Ljava/lang/Object;)Z;
const #194 = Asciz	scala/collection/generic/SequenceTemplate;
const #195 = class	#194;	//  scala/collection/generic/SequenceTemplate
const #196 = Asciz	(I)Z;
const #197 = NameAndType	#192:#196;//  isDefinedAt:(I)Z
const #198 = InterfaceMethod	#195.#197;	//  scala/collection/generic/SequenceTemplate.isDefinedAt:(I)Z
const #199 = Asciz	x;
const #200 = Asciz	andThen;
const #201 = Asciz	(Lscala/Function1;)Lscala/Function1;;
const #202 = Asciz	scala/PartialFunction;
const #203 = class	#202;	//  scala/PartialFunction
const #204 = Asciz	(Lscala/Function1;)Lscala/PartialFunction;;
const #205 = NameAndType	#200:#204;//  andThen:(Lscala/Function1;)Lscala/PartialFunction;
const #206 = InterfaceMethod	#203.#205;	//  scala/PartialFunction.andThen:(Lscala/Function1;)Lscala/PartialFunction;
const #207 = Asciz	g;
const #208 = Asciz	format;
const #209 = Asciz	(Ljava/util/Locale;Lscala/collection/Sequence;)Ljava/lang/String;;
const #210 = Asciz	scala/runtime/ScalaRunTime$;
const #211 = class	#210;	//  scala/runtime/ScalaRunTime$
const #212 = Asciz	MODULE$;
const #213 = Asciz	Lscala/runtime/ScalaRunTime$;;
const #214 = NameAndType	#212:#213;//  MODULE$:Lscala/runtime/ScalaRunTime$;
const #215 = Field	#211.#214;	//  scala/runtime/ScalaRunTime$.MODULE$:Lscala/runtime/ScalaRunTime$;
const #216 = Asciz	scala/collection/generic/TraversableTemplate;
const #217 = class	#216;	//  scala/collection/generic/TraversableTemplate
const #218 = Asciz	toArray;
const #219 = Asciz	()Lscala/runtime/BoxedArray;;
const #220 = NameAndType	#218:#219;//  toArray:()Lscala/runtime/BoxedArray;
const #221 = InterfaceMethod	#217.#220;	//  scala/collection/generic/TraversableTemplate.toArray:()Lscala/runtime/BoxedArray;
const #222 = Asciz	arrayValue;
const #223 = Asciz	(Lscala/runtime/BoxedArray;Ljava/lang/Class;)Ljava/lang/Object;;
const #224 = NameAndType	#222:#223;//  arrayValue:(Lscala/runtime/BoxedArray;Ljava/lang/Class;)Ljava/lang/Object;
const #225 = Method	#211.#224;	//  scala/runtime/ScalaRunTime$.arrayValue:(Lscala/runtime/BoxedArray;Ljava/lang/Class;)Ljava/lang/Object;
const #226 = Asciz	boxArray;
const #227 = Asciz	(Ljava/lang/Object;)Lscala/runtime/BoxedArray;;
const #228 = NameAndType	#226:#227;//  boxArray:(Ljava/lang/Object;)Lscala/runtime/BoxedArray;
const #229 = Method	#211.#228;	//  scala/runtime/ScalaRunTime$.boxArray:(Ljava/lang/Object;)Lscala/runtime/BoxedArray;
const #230 = Asciz	scala/runtime/BoxedArray;
const #231 = class	#230;	//  scala/runtime/BoxedArray
const #232 = Asciz	[Ljava/lang/Object;;
const #233 = class	#232;	//  "[Ljava/lang/Object;"
const #234 = Asciz	(Ljava/util/Locale;Ljava/lang/String;[Ljava/lang/Object;)Ljava/lang/String;;
const #235 = NameAndType	#208:#234;//  format:(Ljava/util/Locale;Ljava/lang/String;[Ljava/lang/Object;)Ljava/lang/String;
const #236 = Method	#133.#235;	//  java/lang/String.format:(Ljava/util/Locale;Ljava/lang/String;[Ljava/lang/Object;)Ljava/lang/String;
const #237 = Asciz	l;
const #238 = Asciz	Ljava/util/Locale;;
const #239 = Asciz	args;
const #240 = Asciz	Lscala/collection/Sequence;;
const #241 = Asciz	(Ljava/util/Locale;Lscala/collection/Sequence<Ljava/lang/Object;>;)Ljava/lang/String;;
const #242 = Asciz	Signature;
const #243 = Asciz	(Lscala/collection/Sequence;)Ljava/lang/String;;
const #244 = Asciz	(Ljava/lang/String;[Ljava/lang/Object;)Ljava/lang/String;;
const #245 = NameAndType	#208:#244;//  format:(Ljava/lang/String;[Ljava/lang/Object;)Ljava/lang/String;
const #246 = Method	#133.#245;	//  java/lang/String.format:(Ljava/lang/String;[Ljava/lang/Object;)Ljava/lang/String;
const #247 = Asciz	(Lscala/collection/Sequence<Ljava/lang/Object;>;)Ljava/lang/String;;
const #248 = Asciz	()[C;
const #249 = Asciz	length;
const #250 = Asciz	()I;
const #251 = NameAndType	#249:#250;//  length:()I
const #252 = Method	#10.#251;	//  scala/runtime/RichString.length:()I
const #253 = Asciz	getChars;
const #254 = Asciz	(II[CI)V;
const #255 = NameAndType	#253:#254;//  getChars:(II[CI)V
const #256 = Method	#133.#255;	//  java/lang/String.getChars:(II[CI)V
const #257 = Asciz	result;
const #258 = Asciz	[C;
const #259 = Asciz	parseBoolean;
const #260 = Asciz	(Ljava/lang/String;)Z;
const #261 = Asciz	equals;
const #262 = NameAndType	#261:#193;//  equals:(Ljava/lang/Object;)Z
const #263 = Method	#14.#262;	//  java/lang/Object.equals:(Ljava/lang/Object;)Z
const #264 = Asciz	java/lang/NumberFormatException;
const #265 = class	#264;	//  java/lang/NumberFormatException
const #266 = Asciz	For input string: \"null\";
const #267 = String	#266;	//  For input string: \"null\"
const #268 = NameAndType	#5:#6;//  "<init>":(Ljava/lang/String;)V
const #269 = Method	#265.#268;	//  java/lang/NumberFormatException."<init>":(Ljava/lang/String;)V
const #270 = Asciz	toLowerCase;
const #271 = NameAndType	#270:#108;//  toLowerCase:()Ljava/lang/String;
const #272 = Method	#133.#271;	//  java/lang/String.toLowerCase:()Ljava/lang/String;
const #273 = Asciz	true;
const #274 = String	#273;	//  true
const #275 = Asciz	false;
const #276 = String	#275;	//  false
const #277 = Asciz	scala/collection/mutable/StringBuilder;
const #278 = class	#277;	//  scala/collection/mutable/StringBuilder
const #279 = Method	#278.#16;	//  scala/collection/mutable/StringBuilder."<init>":()V
const #280 = Asciz	For input string: \";
const #281 = String	#280;	//  For input string: \"
const #282 = Asciz	append;
const #283 = Asciz	(Ljava/lang/Object;)Lscala/collection/mutable/StringBuilder;;
const #284 = NameAndType	#282:#283;//  append:(Ljava/lang/Object;)Lscala/collection/mutable/StringBuilder;
const #285 = Method	#278.#284;	//  scala/collection/mutable/StringBuilder.append:(Ljava/lang/Object;)Lscala/collection/mutable/StringBuilder;
const #286 = Asciz	\";
const #287 = String	#286;	//  \"
const #288 = Asciz	toString;
const #289 = NameAndType	#288:#108;//  toString:()Ljava/lang/String;
const #290 = Method	#278.#289;	//  scala/collection/mutable/StringBuilder.toString:()Ljava/lang/String;
const #291 = Asciz	s;
const #292 = Asciz	temp1;
const #293 = Asciz	toDouble;
const #294 = Asciz	()D;
const #295 = Asciz	java/lang/Double;
const #296 = class	#295;	//  java/lang/Double
const #297 = Asciz	parseDouble;
const #298 = Asciz	(Ljava/lang/String;)D;
const #299 = NameAndType	#297:#298;//  parseDouble:(Ljava/lang/String;)D
const #300 = Method	#296.#299;	//  java/lang/Double.parseDouble:(Ljava/lang/String;)D
const #301 = Asciz	toFloat;
const #302 = Asciz	()F;
const #303 = Asciz	java/lang/Float;
const #304 = class	#303;	//  java/lang/Float
const #305 = Asciz	parseFloat;
const #306 = Asciz	(Ljava/lang/String;)F;
const #307 = NameAndType	#305:#306;//  parseFloat:(Ljava/lang/String;)F
const #308 = Method	#304.#307;	//  java/lang/Float.parseFloat:(Ljava/lang/String;)F
const #309 = Asciz	toLong;
const #310 = Asciz	()J;
const #311 = Asciz	java/lang/Long;
const #312 = class	#311;	//  java/lang/Long
const #313 = Asciz	parseLong;
const #314 = Asciz	(Ljava/lang/String;)J;
const #315 = NameAndType	#313:#314;//  parseLong:(Ljava/lang/String;)J
const #316 = Method	#312.#315;	//  java/lang/Long.parseLong:(Ljava/lang/String;)J
const #317 = Asciz	toInt;
const #318 = Asciz	java/lang/Integer;
const #319 = class	#318;	//  java/lang/Integer
const #320 = Asciz	parseInt;
const #321 = NameAndType	#320:#134;//  parseInt:(Ljava/lang/String;)I
const #322 = Method	#319.#321;	//  java/lang/Integer.parseInt:(Ljava/lang/String;)I
const #323 = Asciz	toShort;
const #324 = Asciz	()S;
const #325 = Asciz	java/lang/Short;
const #326 = class	#325;	//  java/lang/Short
const #327 = Asciz	parseShort;
const #328 = Asciz	(Ljava/lang/String;)S;
const #329 = NameAndType	#327:#328;//  parseShort:(Ljava/lang/String;)S
const #330 = Method	#326.#329;	//  java/lang/Short.parseShort:(Ljava/lang/String;)S
const #331 = Asciz	toByte;
const #332 = Asciz	()B;
const #333 = Asciz	java/lang/Byte;
const #334 = class	#333;	//  java/lang/Byte
const #335 = Asciz	parseByte;
const #336 = Asciz	(Ljava/lang/String;)B;
const #337 = NameAndType	#335:#336;//  parseByte:(Ljava/lang/String;)B
const #338 = Method	#334.#337;	//  java/lang/Byte.parseByte:(Ljava/lang/String;)B
const #339 = Asciz	toBoolean;
const #340 = Asciz	()Z;
const #341 = NameAndType	#259:#260;//  parseBoolean:(Ljava/lang/String;)Z
const #342 = Method	#10.#341;	//  scala/runtime/RichString.parseBoolean:(Ljava/lang/String;)Z
const #343 = Asciz	r;
const #344 = Asciz	()Lscala/util/matching/Regex;;
const #345 = Asciz	scala/util/matching/Regex;
const #346 = class	#345;	//  scala/util/matching/Regex
const #347 = Asciz	(Ljava/lang/String;Lscala/collection/Sequence;)V;
const #348 = NameAndType	#5:#347;//  "<init>":(Ljava/lang/String;Lscala/collection/Sequence;)V
const #349 = Method	#346.#348;	//  scala/util/matching/Regex."<init>":(Ljava/lang/String;Lscala/collection/Sequence;)V
const #350 = Asciz	split;
const #351 = Asciz	([C)[Ljava/lang/String;;
const #352 = Asciz	[;
const #353 = String	#352;	//  [
const #354 = Asciz	scala/runtime/RichString$$anonfun$1;
const #355 = class	#354;	//  scala/runtime/RichString$$anonfun$1
const #356 = Asciz	(Lscala/runtime/RichString;)V;
const #357 = NameAndType	#5:#356;//  "<init>":(Lscala/runtime/RichString;)V
const #358 = Method	#355.#357;	//  scala/runtime/RichString$$anonfun$1."<init>":(Lscala/runtime/RichString;)V
const #359 = Asciz	foldLeft;
const #360 = Asciz	(Ljava/lang/Object;Lscala/Function2;)Ljava/lang/Object;;
const #361 = NameAndType	#359:#360;//  foldLeft:(Ljava/lang/Object;Lscala/Function2;)Ljava/lang/Object;
const #362 = InterfaceMethod	#141.#361;	//  scala/collection/generic/VectorTemplate.foldLeft:(Ljava/lang/Object;Lscala/Function2;)Ljava/lang/Object;
const #363 = Asciz	];
const #364 = String	#363;	//  ]
const #365 = Asciz	(Ljava/lang/String;)[Ljava/lang/String;;
const #366 = NameAndType	#350:#365;//  split:(Ljava/lang/String;)[Ljava/lang/String;
const #367 = Method	#133.#366;	//  java/lang/String.split:(Ljava/lang/String;)[Ljava/lang/String;
const #368 = Asciz	separators;
const #369 = Asciz	re;
const #370 = Asciz	java/util/regex/PatternSyntaxException;
const #371 = class	#370;	//  java/util/regex/PatternSyntaxException
const #372 = Asciz	Exceptions;
const #373 = Asciz	(C)[Ljava/lang/String;;
const #374 = Asciz	scala$runtime$RichString$$escape;
const #375 = Asciz	(C)Ljava/lang/String;;
const #376 = NameAndType	#374:#375;//  scala$runtime$RichString$$escape:(C)Ljava/lang/String;
const #377 = Method	#10.#376;	//  scala/runtime/RichString.scala$runtime$RichString$$escape:(C)Ljava/lang/String;
const #378 = Asciz	separator;
const #379 = Asciz	C;
const #380 = Asciz	\Q;
const #381 = String	#380;	//  \Q
const #382 = Asciz	\E;
const #383 = String	#382;	//  \E
const #384 = Asciz	ch;
const #385 = Asciz	stripMargin;
const #386 = int	124;
const #387 = NameAndType	#385:#375;//  stripMargin:(C)Ljava/lang/String;
const #388 = Method	#10.#387;	//  scala/runtime/RichString.stripMargin:(C)Ljava/lang/String;
const #389 = Method	#278.#16;	//  scala/collection/mutable/StringBuilder."<init>":()V
const #390 = Asciz	linesWithSeparators;
const #391 = Asciz	()Lscala/collection/Iterator;;
const #392 = NameAndType	#390:#391;//  linesWithSeparators:()Lscala/collection/Iterator;
const #393 = Method	#10.#392;	//  scala/runtime/RichString.linesWithSeparators:()Lscala/collection/Iterator;
const #394 = Asciz	scala/runtime/RichString$$anonfun$stripMargin$1;
const #395 = class	#394;	//  scala/runtime/RichString$$anonfun$stripMargin$1
const #396 = Asciz	(Lscala/runtime/RichString;CLscala/collection/mutable/StringBuilder;)V;
const #397 = NameAndType	#5:#396;//  "<init>":(Lscala/runtime/RichString;CLscala/collection/mutable/StringBuilder;)V
const #398 = Method	#395.#397;	//  scala/runtime/RichString$$anonfun$stripMargin$1."<init>":(Lscala/runtime/RichString;CLscala/collection/mutable/StringBuilder;)V
const #399 = Asciz	scala/collection/Iterator;
const #400 = class	#399;	//  scala/collection/Iterator
const #401 = Asciz	foreach;
const #402 = NameAndType	#401:#61;//  foreach:(Lscala/Function1;)V
const #403 = InterfaceMethod	#400.#402;	//  scala/collection/Iterator.foreach:(Lscala/Function1;)V
const #404 = Method	#278.#289;	//  scala/collection/mutable/StringBuilder.toString:()Ljava/lang/String;
const #405 = Asciz	marginChar$1;
const #406 = Asciz	buf$2;
const #407 = Asciz	Lscala/collection/mutable/StringBuilder;;
const #408 = Asciz	capitalize;
const #409 = Method	#133.#251;	//  java/lang/String.length:()I
const #410 = Asciz	;
const #411 = String	#410;	//  
const #412 = Asciz	toCharArray;
const #413 = NameAndType	#412:#248;//  toCharArray:()[C
const #414 = Method	#133.#413;	//  java/lang/String.toCharArray:()[C
const #415 = Asciz	scala/Predef$;
const #416 = class	#415;	//  scala/Predef$
const #417 = Asciz	Lscala/Predef$;;
const #418 = NameAndType	#212:#417;//  MODULE$:Lscala/Predef$;
const #419 = Field	#416.#418;	//  scala/Predef$.MODULE$:Lscala/Predef$;
const #420 = Asciz	charWrapper;
const #421 = Asciz	(C)Lscala/runtime/RichChar;;
const #422 = NameAndType	#420:#421;//  charWrapper:(C)Lscala/runtime/RichChar;
const #423 = Method	#416.#422;	//  scala/Predef$.charWrapper:(C)Lscala/runtime/RichChar;
const #424 = Asciz	scala/runtime/RichChar;
const #425 = class	#424;	//  scala/runtime/RichChar
const #426 = Asciz	toUpperCase;
const #427 = Asciz	()C;
const #428 = NameAndType	#426:#427;//  toUpperCase:()C
const #429 = Method	#425.#428;	//  scala/runtime/RichChar.toUpperCase:()C
const #430 = Asciz	([C)V;
const #431 = NameAndType	#5:#430;//  "<init>":([C)V
const #432 = Method	#133.#431;	//  java/lang/String."<init>":([C)V
const #433 = Asciz	chars;
const #434 = Asciz	linesIterator;
const #435 = Asciz	scala/runtime/RichString$$anonfun$linesIterator$1;
const #436 = class	#435;	//  scala/runtime/RichString$$anonfun$linesIterator$1
const #437 = Method	#436.#357;	//  scala/runtime/RichString$$anonfun$linesIterator$1."<init>":(Lscala/runtime/RichString;)V
const #438 = Asciz	map;
const #439 = Asciz	(Lscala/Function1;)Lscala/collection/Iterator;;
const #440 = NameAndType	#438:#439;//  map:(Lscala/Function1;)Lscala/collection/Iterator;
const #441 = InterfaceMethod	#400.#440;	//  scala/collection/Iterator.map:(Lscala/Function1;)Lscala/collection/Iterator;
const #442 = Asciz	()Lscala/collection/Iterator<Ljava/lang/String;>;;
const #443 = Asciz	lines;
const #444 = Asciz	scala/runtime/RichString$$anonfun$lines$1;
const #445 = class	#444;	//  scala/runtime/RichString$$anonfun$lines$1
const #446 = Method	#445.#357;	//  scala/runtime/RichString$$anonfun$lines$1."<init>":(Lscala/runtime/RichString;)V
const #447 = Asciz	scala/runtime/RichString$$anon$1;
const #448 = class	#447;	//  scala/runtime/RichString$$anon$1
const #449 = Method	#448.#357;	//  scala/runtime/RichString$$anon$1."<init>":(Lscala/runtime/RichString;)V
const #450 = Asciz	stripLineEnd;
const #451 = Asciz	scala$runtime$RichString$$isLineBreak;
const #452 = Asciz	(C)Z;
const #453 = NameAndType	#451:#452;//  scala$runtime$RichString$$isLineBreak:(C)Z
const #454 = Method	#10.#453;	//  scala/runtime/RichString.scala$runtime$RichString$$isLineBreak:(C)Z
const #455 = Asciz	scala/runtime/RichString$;
const #456 = class	#455;	//  scala/runtime/RichString$
const #457 = Asciz	Lscala/runtime/RichString$;;
const #458 = NameAndType	#212:#457;//  MODULE$:Lscala/runtime/RichString$;
const #459 = Field	#456.#458;	//  scala/runtime/RichString$.MODULE$:Lscala/runtime/RichString$;
const #460 = Asciz	scala$runtime$RichString$$LF;
const #461 = NameAndType	#460:#427;//  scala$runtime$RichString$$LF:()C
const #462 = Method	#456.#461;	//  scala/runtime/RichString$.scala$runtime$RichString$$LF:()C
const #463 = Asciz	scala$runtime$RichString$$CR;
const #464 = NameAndType	#463:#427;//  scala$runtime$RichString$$CR:()C
const #465 = Method	#456.#464;	//  scala/runtime/RichString$.scala$runtime$RichString$$CR:()C
const #466 = Asciz	substring;
const #467 = Asciz	(II)Ljava/lang/String;;
const #468 = NameAndType	#466:#467;//  substring:(II)Ljava/lang/String;
const #469 = Method	#133.#468;	//  java/lang/String.substring:(II)Ljava/lang/String;
const #470 = Asciz	len;
const #471 = Asciz	last;
const #472 = Asciz	scala$runtime$RichString$$FF;
const #473 = NameAndType	#472:#427;//  scala$runtime$RichString$$FF:()C
const #474 = Method	#456.#473;	//  scala/runtime/RichString$.scala$runtime$RichString$$FF:()C
const #475 = Asciz	c;
const #476 = Asciz	compareTo;
const #477 = NameAndType	#476:#134;//  compareTo:(Ljava/lang/String;)I
const #478 = Method	#133.#477;	//  java/lang/String.compareTo:(Ljava/lang/String;)I
const #479 = Asciz	other;
const #480 = Asciz	$times;
const #481 = Asciz	(I)Ljava/lang/String;;
const #482 = Asciz	intWrapper;
const #483 = Asciz	(I)Lscala/runtime/RichInt;;
const #484 = NameAndType	#482:#483;//  intWrapper:(I)Lscala/runtime/RichInt;
const #485 = Method	#416.#484;	//  scala/Predef$.intWrapper:(I)Lscala/runtime/RichInt;
const #486 = Asciz	scala/runtime/RichInt;
const #487 = class	#486;	//  scala/runtime/RichInt
const #488 = Asciz	(I)Lscala/Range;;
const #489 = NameAndType	#146:#488;//  until:(I)Lscala/Range;
const #490 = Method	#487.#489;	//  scala/runtime/RichInt.until:(I)Lscala/Range;
const #491 = Asciz	scala/runtime/RichString$$anonfun$$times$1;
const #492 = class	#491;	//  scala/runtime/RichString$$anonfun$$times$1
const #493 = Asciz	(Lscala/runtime/RichString;Lscala/collection/mutable/StringBuilder;)V;
const #494 = NameAndType	#5:#493;//  "<init>":(Lscala/runtime/RichString;Lscala/collection/mutable/StringBuilder;)V
const #495 = Method	#492.#494;	//  scala/runtime/RichString$$anonfun$$times$1."<init>":(Lscala/runtime/RichString;Lscala/collection/mutable/StringBuilder;)V
const #496 = Asciz	scala/Range;
const #497 = class	#496;	//  scala/Range
const #498 = Method	#497.#402;	//  scala/Range.foreach:(Lscala/Function1;)V
const #499 = Asciz	buf$1;
const #500 = Asciz	mkString;
const #501 = Asciz	charAt;
const #502 = NameAndType	#501:#113;//  charAt:(I)C
const #503 = Method	#133.#502;	//  java/lang/String.charAt:(I)C
const #504 = Asciz	newBuilder;
const #505 = Asciz	()Lscala/collection/generic/Builder;;
const #506 = NameAndType	#504:#505;//  newBuilder:()Lscala/collection/generic/Builder;
const #507 = Method	#456.#506;	//  scala/runtime/RichString$.newBuilder:()Lscala/collection/generic/Builder;
const #508 = Asciz	()Lscala/collection/generic/Builder<Ljava/lang/Character;Lscala/runtime/RichString;>;;
const #509 = Asciz	stringPrefix;
const #510 = Asciz	(Lscala/collection/generic/TraversableTemplate;)Ljava/lang/String;;
const #511 = NameAndType	#509:#510;//  stringPrefix:(Lscala/collection/generic/TraversableTemplate;)Ljava/lang/String;
const #512 = Method	#25.#511;	//  scala/collection/generic/TraversableTemplate$class.stringPrefix:(Lscala/collection/generic/TraversableTemplate;)Ljava/lang/String;
const #513 = Asciz	addString;
const #514 = Asciz	(Lscala/collection/mutable/StringBuilder;)Lscala/collection/mutable/StringBuilder;;
const #515 = Asciz	(Lscala/collection/generic/TraversableTemplate;Lscala/collection/mutable/StringBuilder;)Lscala/collection/mutable/StringBuilder;;
const #516 = NameAndType	#513:#515;//  addString:(Lscala/collection/generic/TraversableTemplate;Lscala/collection/mutable/StringBuilder;)Lscala/collection/mutable/StringBuilder;
const #517 = Method	#25.#516;	//  scala/collection/generic/TraversableTemplate$class.addString:(Lscala/collection/generic/TraversableTemplate;Lscala/collection/mutable/StringBuilder;)Lscala/collection/mutable/StringBuilder;
const #518 = Asciz	b;
const #519 = Asciz	(Lscala/collection/mutable/StringBuilder;Ljava/lang/String;)Lscala/collection/mutable/StringBuilder;;
const #520 = Asciz	(Lscala/collection/generic/TraversableTemplate;Lscala/collection/mutable/StringBuilder;Ljava/lang/String;)Lscala/collection/mutable/StringBuilder;;
const #521 = NameAndType	#513:#520;//  addString:(Lscala/collection/generic/TraversableTemplate;Lscala/collection/mutable/StringBuilder;Ljava/lang/String;)Lscala/collection/mutable/StringBuilder;
const #522 = Method	#25.#521;	//  scala/collection/generic/TraversableTemplate$class.addString:(Lscala/collection/generic/TraversableTemplate;Lscala/collection/mutable/StringBuilder;Ljava/lang/String;)Lscala/collection/mutable/StringBuilder;
const #523 = Asciz	sep;
const #524 = Asciz	(Lscala/collection/mutable/StringBuilder;Ljava/lang/String;Ljava/lang/String;Ljava/lang/String;)Lscala/collection/mutable/StringBuilder;;
const #525 = Asciz	(Lscala/collection/generic/TraversableTemplate;Lscala/collection/mutable/StringBuilder;Ljava/lang/String;Ljava/lang/String;Ljava/lang/String;)Lscala/collection/mutable/StringBuilder;;
const #526 = NameAndType	#513:#525;//  addString:(Lscala/collection/generic/TraversableTemplate;Lscala/collection/mutable/StringBuilder;Ljava/lang/String;Ljava/lang/String;Ljava/lang/String;)Lscala/collection/mutable/StringBuilder;
const #527 = Method	#25.#526;	//  scala/collection/generic/TraversableTemplate$class.addString:(Lscala/collection/generic/TraversableTemplate;Lscala/collection/mutable/StringBuilder;Ljava/lang/String;Ljava/lang/String;Ljava/lang/String;)Lscala/collection/mutable/StringBuilder;
const #528 = Asciz	start;
const #529 = Asciz	end;
const #530 = Asciz	(Ljava/lang/String;)Ljava/lang/String;;
const #531 = Asciz	(Lscala/collection/generic/TraversableTemplate;Ljava/lang/String;)Ljava/lang/String;;
const #532 = NameAndType	#500:#531;//  mkString:(Lscala/collection/generic/TraversableTemplate;Ljava/lang/String;)Ljava/lang/String;
const #533 = Method	#25.#532;	//  scala/collection/generic/TraversableTemplate$class.mkString:(Lscala/collection/generic/TraversableTemplate;Ljava/lang/String;)Ljava/lang/String;
const #534 = Asciz	(Ljava/lang/String;Ljava/lang/String;Ljava/lang/String;)Ljava/lang/String;;
const #535 = Asciz	(Lscala/collection/generic/TraversableTemplate;Ljava/lang/String;Ljava/lang/String;Ljava/lang/String;)Ljava/lang/String;;
const #536 = NameAndType	#500:#535;//  mkString:(Lscala/collection/generic/TraversableTemplate;Ljava/lang/String;Ljava/lang/String;Ljava/lang/String;)Ljava/lang/String;
const #537 = Method	#25.#536;	//  scala/collection/generic/TraversableTemplate$class.mkString:(Lscala/collection/generic/TraversableTemplate;Ljava/lang/String;Ljava/lang/String;Ljava/lang/String;)Ljava/lang/String;
const #538 = Asciz	toSet;
const #539 = Asciz	()Lscala/collection/immutable/Set;;
const #540 = Asciz	(Lscala/collection/generic/TraversableTemplate;)Lscala/collection/immutable/Set;;
const #541 = NameAndType	#538:#540;//  toSet:(Lscala/collection/generic/TraversableTemplate;)Lscala/collection/immutable/Set;
const #542 = Method	#25.#541;	//  scala/collection/generic/TraversableTemplate$class.toSet:(Lscala/collection/generic/TraversableTemplate;)Lscala/collection/immutable/Set;
const #543 = Asciz	toList;
const #544 = Asciz	()Lscala/collection/immutable/List;;
const #545 = Asciz	(Lscala/collection/generic/TraversableTemplate;)Lscala/collection/immutable/List;;
const #546 = NameAndType	#543:#545;//  toList:(Lscala/collection/generic/TraversableTemplate;)Lscala/collection/immutable/List;
const #547 = Method	#25.#546;	//  scala/collection/generic/TraversableTemplate$class.toList:(Lscala/collection/generic/TraversableTemplate;)Lscala/collection/immutable/List;
const #548 = Asciz	(Lscala/collection/generic/TraversableTemplate;)Lscala/runtime/BoxedArray;;
const #549 = NameAndType	#218:#548;//  toArray:(Lscala/collection/generic/TraversableTemplate;)Lscala/runtime/BoxedArray;
const #550 = Method	#25.#549;	//  scala/collection/generic/TraversableTemplate$class.toArray:(Lscala/collection/generic/TraversableTemplate;)Lscala/runtime/BoxedArray;
const #551 = Asciz	copyToArray;
const #552 = Asciz	(Lscala/runtime/BoxedArray;I)V;
const #553 = Asciz	(Lscala/collection/generic/TraversableTemplate;Lscala/runtime/BoxedArray;I)V;
const #554 = NameAndType	#551:#553;//  copyToArray:(Lscala/collection/generic/TraversableTemplate;Lscala/runtime/BoxedArray;I)V
const #555 = Method	#25.#554;	//  scala/collection/generic/TraversableTemplate$class.copyToArray:(Lscala/collection/generic/TraversableTemplate;Lscala/runtime/BoxedArray;I)V
const #556 = Asciz	xs;
const #557 = Asciz	Lscala/runtime/BoxedArray;;
const #558 = Asciz	copyToBuffer;
const #559 = Asciz	(Lscala/collection/mutable/Buffer;)V;
const #560 = Asciz	(Lscala/collection/generic/TraversableTemplate;Lscala/collection/mutable/Buffer;)V;
const #561 = NameAndType	#558:#560;//  copyToBuffer:(Lscala/collection/generic/TraversableTemplate;Lscala/collection/mutable/Buffer;)V
const #562 = Method	#25.#561;	//  scala/collection/generic/TraversableTemplate$class.copyToBuffer:(Lscala/collection/generic/TraversableTemplate;Lscala/collection/mutable/Buffer;)V
const #563 = Asciz	dest;
const #564 = Asciz	Lscala/collection/mutable/Buffer;;
const #565 = Asciz	lastOption;
const #566 = Asciz	()Lscala/Option;;
const #567 = Asciz	(Lscala/collection/generic/TraversableTemplate;)Lscala/Option;;
const #568 = NameAndType	#565:#567;//  lastOption:(Lscala/collection/generic/TraversableTemplate;)Lscala/Option;
const #569 = Method	#25.#568;	//  scala/collection/generic/TraversableTemplate$class.lastOption:(Lscala/collection/generic/TraversableTemplate;)Lscala/Option;
const #570 = Asciz	headOption;
const #571 = NameAndType	#570:#567;//  headOption:(Lscala/collection/generic/TraversableTemplate;)Lscala/Option;
const #572 = Method	#25.#571;	//  scala/collection/generic/TraversableTemplate$class.headOption:(Lscala/collection/generic/TraversableTemplate;)Lscala/Option;
const #573 = Asciz	reduceRightOption;
const #574 = Asciz	(Lscala/Function2;)Lscala/Option;;
const #575 = Asciz	(Lscala/collection/generic/TraversableTemplate;Lscala/Function2;)Lscala/Option;;
const #576 = NameAndType	#573:#575;//  reduceRightOption:(Lscala/collection/generic/TraversableTemplate;Lscala/Function2;)Lscala/Option;
const #577 = Method	#25.#576;	//  scala/collection/generic/TraversableTemplate$class.reduceRightOption:(Lscala/collection/generic/TraversableTemplate;Lscala/Function2;)Lscala/Option;
const #578 = Asciz	op;
const #579 = Asciz	Lscala/Function2;;
const #580 = Asciz	reduceLeftOption;
const #581 = NameAndType	#580:#575;//  reduceLeftOption:(Lscala/collection/generic/TraversableTemplate;Lscala/Function2;)Lscala/Option;
const #582 = Method	#25.#581;	//  scala/collection/generic/TraversableTemplate$class.reduceLeftOption:(Lscala/collection/generic/TraversableTemplate;Lscala/Function2;)Lscala/Option;
const #583 = Asciz	$colon$bslash;
const #584 = Asciz	(Lscala/collection/generic/TraversableTemplate;Ljava/lang/Object;Lscala/Function2;)Ljava/lang/Object;;
const #585 = NameAndType	#583:#584;//  $colon$bslash:(Lscala/collection/generic/TraversableTemplate;Ljava/lang/Object;Lscala/Function2;)Ljava/lang/Object;
const #586 = Method	#25.#585;	//  scala/collection/generic/TraversableTemplate$class.$colon$bslash:(Lscala/collection/generic/TraversableTemplate;Ljava/lang/Object;Lscala/Function2;)Ljava/lang/Object;
const #587 = Asciz	z;
const #588 = Asciz	$div$colon;
const #589 = NameAndType	#588:#584;//  $div$colon:(Lscala/collection/generic/TraversableTemplate;Ljava/lang/Object;Lscala/Function2;)Ljava/lang/Object;
const #590 = Method	#25.#589;	//  scala/collection/generic/TraversableTemplate$class.$div$colon:(Lscala/collection/generic/TraversableTemplate;Ljava/lang/Object;Lscala/Function2;)Ljava/lang/Object;
const #591 = Asciz	count;
const #592 = Asciz	(Lscala/Function1;)I;
const #593 = Asciz	(Lscala/collection/generic/TraversableTemplate;Lscala/Function1;)I;
const #594 = NameAndType	#591:#593;//  count:(Lscala/collection/generic/TraversableTemplate;Lscala/Function1;)I
const #595 = Method	#25.#594;	//  scala/collection/generic/TraversableTemplate$class.count:(Lscala/collection/generic/TraversableTemplate;Lscala/Function1;)I
const #596 = Asciz	groupBy;
const #597 = Asciz	(Lscala/Function1;)Lscala/collection/Map;;
const #598 = Asciz	(Lscala/collection/generic/TraversableTemplate;Lscala/Function1;)Lscala/collection/Map;;
const #599 = NameAndType	#596:#598;//  groupBy:(Lscala/collection/generic/TraversableTemplate;Lscala/Function1;)Lscala/collection/Map;
const #600 = Method	#25.#599;	//  scala/collection/generic/TraversableTemplate$class.groupBy:(Lscala/collection/generic/TraversableTemplate;Lscala/Function1;)Lscala/collection/Map;
const #601 = Asciz	f;
const #602 = Asciz	partition;
const #603 = Asciz	(Lscala/Function1;)Lscala/Tuple2;;
const #604 = Asciz	(Lscala/collection/generic/TraversableTemplate;Lscala/Function1;)Lscala/Tuple2;;
const #605 = NameAndType	#602:#604;//  partition:(Lscala/collection/generic/TraversableTemplate;Lscala/Function1;)Lscala/Tuple2;
const #606 = Method	#25.#605;	//  scala/collection/generic/TraversableTemplate$class.partition:(Lscala/collection/generic/TraversableTemplate;Lscala/Function1;)Lscala/Tuple2;
const #607 = Asciz	remove;
const #608 = Asciz	(Lscala/collection/generic/TraversableTemplate;Lscala/Function1;)Lscala/collection/generic/TraversableTemplate;;
const #609 = NameAndType	#607:#608;//  remove:(Lscala/collection/generic/TraversableTemplate;Lscala/Function1;)Lscala/collection/generic/TraversableTemplate;
const #610 = Method	#25.#609;	//  scala/collection/generic/TraversableTemplate$class.remove:(Lscala/collection/generic/TraversableTemplate;Lscala/Function1;)Lscala/collection/generic/TraversableTemplate;
const #611 = Asciz	filterNot;
const #612 = NameAndType	#611:#608;//  filterNot:(Lscala/collection/generic/TraversableTemplate;Lscala/Function1;)Lscala/collection/generic/TraversableTemplate;
const #613 = Method	#25.#612;	//  scala/collection/generic/TraversableTemplate$class.filterNot:(Lscala/collection/generic/TraversableTemplate;Lscala/Function1;)Lscala/collection/generic/TraversableTemplate;
const #614 = Asciz	filterMap;
const #615 = Asciz	(Lscala/PartialFunction;Lscala/collection/generic/BuilderFactory;)Ljava/lang/Object;;
const #616 = Asciz	(Lscala/collection/generic/TraversableTemplate;Lscala/PartialFunction;Lscala/collection/generic/BuilderFactory;)Ljava/lang/Object;;
const #617 = NameAndType	#614:#616;//  filterMap:(Lscala/collection/generic/TraversableTemplate;Lscala/PartialFunction;Lscala/collection/generic/BuilderFactory;)Ljava/lang/Object;
const #618 = Method	#25.#617;	//  scala/collection/generic/TraversableTemplate$class.filterMap:(Lscala/collection/generic/TraversableTemplate;Lscala/PartialFunction;Lscala/collection/generic/BuilderFactory;)Ljava/lang/Object;
const #619 = Asciz	pf;
const #620 = Asciz	Lscala/PartialFunction;;
const #621 = Asciz	bf;
const #622 = Asciz	Lscala/collection/generic/BuilderFactory;;
const #623 = Asciz	filter;
const #624 = NameAndType	#623:#608;//  filter:(Lscala/collection/generic/TraversableTemplate;Lscala/Function1;)Lscala/collection/generic/TraversableTemplate;
const #625 = Method	#25.#624;	//  scala/collection/generic/TraversableTemplate$class.filter:(Lscala/collection/generic/TraversableTemplate;Lscala/Function1;)Lscala/collection/generic/TraversableTemplate;
const #626 = Asciz	flatMap;
const #627 = Asciz	(Lscala/Function1;Lscala/collection/generic/BuilderFactory;)Ljava/lang/Object;;
const #628 = Asciz	(Lscala/collection/generic/TraversableTemplate;Lscala/Function1;Lscala/collection/generic/BuilderFactory;)Ljava/lang/Object;;
const #629 = NameAndType	#626:#628;//  flatMap:(Lscala/collection/generic/TraversableTemplate;Lscala/Function1;Lscala/collection/generic/BuilderFactory;)Ljava/lang/Object;
const #630 = Method	#25.#629;	//  scala/collection/generic/TraversableTemplate$class.flatMap:(Lscala/collection/generic/TraversableTemplate;Lscala/Function1;Lscala/collection/generic/BuilderFactory;)Ljava/lang/Object;
const #631 = NameAndType	#438:#628;//  map:(Lscala/collection/generic/TraversableTemplate;Lscala/Function1;Lscala/collection/generic/BuilderFactory;)Ljava/lang/Object;
const #632 = Method	#25.#631;	//  scala/collection/generic/TraversableTemplate$class.map:(Lscala/collection/generic/TraversableTemplate;Lscala/Function1;Lscala/collection/generic/BuilderFactory;)Ljava/lang/Object;
const #633 = Asciz	$plus$plus;
const #634 = Asciz	(Lscala/collection/Iterator;Lscala/collection/generic/BuilderFactory;)Ljava/lang/Object;;
const #635 = Asciz	(Lscala/collection/generic/TraversableTemplate;Lscala/collection/Iterator;Lscala/collection/generic/BuilderFactory;)Ljava/lang/Object;;
const #636 = NameAndType	#633:#635;//  $plus$plus:(Lscala/collection/generic/TraversableTemplate;Lscala/collection/Iterator;Lscala/collection/generic/BuilderFactory;)Ljava/lang/Object;
const #637 = Method	#25.#636;	//  scala/collection/generic/TraversableTemplate$class.$plus$plus:(Lscala/collection/generic/TraversableTemplate;Lscala/collection/Iterator;Lscala/collection/generic/BuilderFactory;)Ljava/lang/Object;
const #638 = Asciz	Lscala/collection/Iterator;;
const #639 = Asciz	(Lscala/collection/Traversable;Lscala/collection/generic/BuilderFactory;)Ljava/lang/Object;;
const #640 = Asciz	(Lscala/collection/generic/TraversableTemplate;Lscala/collection/Traversable;Lscala/collection/generic/BuilderFactory;)Ljava/lang/Object;;
const #641 = NameAndType	#633:#640;//  $plus$plus:(Lscala/collection/generic/TraversableTemplate;Lscala/collection/Traversable;Lscala/collection/generic/BuilderFactory;)Ljava/lang/Object;
const #642 = Method	#25.#641;	//  scala/collection/generic/TraversableTemplate$class.$plus$plus:(Lscala/collection/generic/TraversableTemplate;Lscala/collection/Traversable;Lscala/collection/generic/BuilderFactory;)Ljava/lang/Object;
const #643 = Asciz	Lscala/collection/Traversable;;
const #644 = Asciz	hasDefiniteSize;
const #645 = Asciz	(Lscala/collection/generic/TraversableTemplate;)Z;
const #646 = NameAndType	#644:#645;//  hasDefiniteSize:(Lscala/collection/generic/TraversableTemplate;)Z
const #647 = Method	#25.#646;	//  scala/collection/generic/TraversableTemplate$class.hasDefiniteSize:(Lscala/collection/generic/TraversableTemplate;)Z
const #648 = Asciz	nonEmpty;
const #649 = NameAndType	#648:#645;//  nonEmpty:(Lscala/collection/generic/TraversableTemplate;)Z
const #650 = Method	#25.#649;	//  scala/collection/generic/TraversableTemplate$class.nonEmpty:(Lscala/collection/generic/TraversableTemplate;)Z
const #651 = Asciz	thisCollection;
const #652 = Asciz	(Lscala/collection/generic/TraversableTemplate;)Lscala/collection/generic/TraversableTemplate;;
const #653 = NameAndType	#651:#652;//  thisCollection:(Lscala/collection/generic/TraversableTemplate;)Lscala/collection/generic/TraversableTemplate;
const #654 = Method	#25.#653;	//  scala/collection/generic/TraversableTemplate$class.thisCollection:(Lscala/collection/generic/TraversableTemplate;)Lscala/collection/generic/TraversableTemplate;
const #655 = Asciz	transpose;
const #656 = Asciz	(Lscala/Function1;)Lscala/collection/Traversable;;
const #657 = Asciz	(Lscala/collection/generic/TraversableClass;Lscala/Function1;)Lscala/collection/Traversable;;
const #658 = NameAndType	#655:#657;//  transpose:(Lscala/collection/generic/TraversableClass;Lscala/Function1;)Lscala/collection/Traversable;
const #659 = Method	#30.#658;	//  scala/collection/generic/TraversableClass$class.transpose:(Lscala/collection/generic/TraversableClass;Lscala/Function1;)Lscala/collection/Traversable;
const #660 = Asciz	toTraversable;
const #661 = Asciz	flatten;
const #662 = NameAndType	#661:#657;//  flatten:(Lscala/collection/generic/TraversableClass;Lscala/Function1;)Lscala/collection/Traversable;
const #663 = Method	#30.#662;	//  scala/collection/generic/TraversableClass$class.flatten:(Lscala/collection/generic/TraversableClass;Lscala/Function1;)Lscala/collection/Traversable;
const #664 = Asciz	unzip;
const #665 = Asciz	(Lscala/collection/generic/TraversableClass;Lscala/Function1;)Lscala/Tuple2;;
const #666 = NameAndType	#664:#665;//  unzip:(Lscala/collection/generic/TraversableClass;Lscala/Function1;)Lscala/Tuple2;
const #667 = Method	#30.#666;	//  scala/collection/generic/TraversableClass$class.unzip:(Lscala/collection/generic/TraversableClass;Lscala/Function1;)Lscala/Tuple2;
const #668 = Asciz	toPair;
const #669 = Asciz	genericBuilder;
const #670 = Asciz	(Lscala/collection/generic/TraversableClass;)Lscala/collection/generic/Builder;;
const #671 = NameAndType	#669:#670;//  genericBuilder:(Lscala/collection/generic/TraversableClass;)Lscala/collection/generic/Builder;
const #672 = Method	#30.#671;	//  scala/collection/generic/TraversableClass$class.genericBuilder:(Lscala/collection/generic/TraversableClass;)Lscala/collection/generic/Builder;
const #673 = Asciz	toSeq;
const #674 = Asciz	()Lscala/collection/Sequence;;
const #675 = Asciz	(Lscala/collection/generic/IterableTemplate;)Lscala/collection/Sequence;;
const #676 = NameAndType	#673:#675;//  toSeq:(Lscala/collection/generic/IterableTemplate;)Lscala/collection/Sequence;
const #677 = Method	#45.#676;	//  scala/collection/generic/IterableTemplate$class.toSeq:(Lscala/collection/generic/IterableTemplate;)Lscala/collection/Sequence;
const #678 = Asciz	firstOption;
const #679 = Asciz	(Lscala/collection/generic/IterableTemplate;)Lscala/Option;;
const #680 = NameAndType	#678:#679;//  firstOption:(Lscala/collection/generic/IterableTemplate;)Lscala/Option;
const #681 = Method	#45.#680;	//  scala/collection/generic/IterableTemplate$class.firstOption:(Lscala/collection/generic/IterableTemplate;)Lscala/Option;
const #682 = Asciz	first;
const #683 = Asciz	(Lscala/collection/generic/IterableTemplate;)Ljava/lang/Object;;
const #684 = NameAndType	#682:#683;//  first:(Lscala/collection/generic/IterableTemplate;)Ljava/lang/Object;
const #685 = Method	#45.#684;	//  scala/collection/generic/IterableTemplate$class.first:(Lscala/collection/generic/IterableTemplate;)Ljava/lang/Object;
const #686 = Asciz	toStream;
const #687 = Asciz	()Lscala/collection/immutable/Stream;;
const #688 = Asciz	(Lscala/collection/generic/IterableTemplate;)Lscala/collection/immutable/Stream;;
const #689 = NameAndType	#686:#688;//  toStream:(Lscala/collection/generic/IterableTemplate;)Lscala/collection/immutable/Stream;
const #690 = Method	#45.#689;	//  scala/collection/generic/IterableTemplate$class.toStream:(Lscala/collection/generic/IterableTemplate;)Lscala/collection/immutable/Stream;
const #691 = Asciz	toIterable;
const #692 = Asciz	()Lscala/collection/Iterable;;
const #693 = Asciz	(Lscala/collection/generic/IterableTemplate;)Lscala/collection/Iterable;;
const #694 = NameAndType	#691:#693;//  toIterable:(Lscala/collection/generic/IterableTemplate;)Lscala/collection/Iterable;
const #695 = Method	#45.#694;	//  scala/collection/generic/IterableTemplate$class.toIterable:(Lscala/collection/generic/IterableTemplate;)Lscala/collection/Iterable;
const #696 = Asciz	elements;
const #697 = Asciz	(Lscala/collection/generic/IterableTemplate;)Lscala/collection/Iterator;;
const #698 = NameAndType	#696:#697;//  elements:(Lscala/collection/generic/IterableTemplate;)Lscala/collection/Iterator;
const #699 = Method	#45.#698;	//  scala/collection/generic/IterableTemplate$class.elements:(Lscala/collection/generic/IterableTemplate;)Lscala/collection/Iterator;
const #700 = Asciz	compose;
const #701 = Asciz	(Lscala/Function1;Lscala/Function1;)Lscala/Function1;;
const #702 = NameAndType	#700:#701;//  compose:(Lscala/Function1;Lscala/Function1;)Lscala/Function1;
const #703 = Method	#60.#702;	//  scala/Function1$class.compose:(Lscala/Function1;Lscala/Function1;)Lscala/Function1;
const #704 = Asciz	(Lscala/PartialFunction;Lscala/Function1;)Lscala/PartialFunction;;
const #705 = NameAndType	#200:#704;//  andThen:(Lscala/PartialFunction;Lscala/Function1;)Lscala/PartialFunction;
const #706 = Method	#65.#705;	//  scala/PartialFunction$class.andThen:(Lscala/PartialFunction;Lscala/Function1;)Lscala/PartialFunction;
const #707 = Asciz	k;
const #708 = Asciz	orElse;
const #709 = Asciz	(Lscala/PartialFunction;)Lscala/PartialFunction;;
const #710 = Asciz	(Lscala/PartialFunction;Lscala/PartialFunction;)Lscala/PartialFunction;;
const #711 = NameAndType	#708:#710;//  orElse:(Lscala/PartialFunction;Lscala/PartialFunction;)Lscala/PartialFunction;
const #712 = Method	#65.#711;	//  scala/PartialFunction$class.orElse:(Lscala/PartialFunction;Lscala/PartialFunction;)Lscala/PartialFunction;
const #713 = Asciz	projection;
const #714 = Asciz	(Lscala/collection/generic/SequenceTemplate;)Ljava/lang/Object;;
const #715 = NameAndType	#713:#714;//  projection:(Lscala/collection/generic/SequenceTemplate;)Ljava/lang/Object;
const #716 = Method	#70.#715;	//  scala/collection/generic/SequenceTemplate$class.projection:(Lscala/collection/generic/SequenceTemplate;)Ljava/lang/Object;
const #717 = Asciz	containsSlice;
const #718 = Asciz	(Lscala/collection/Sequence;)Z;
const #719 = Asciz	(Lscala/collection/generic/SequenceTemplate;Lscala/collection/Sequence;)Z;
const #720 = NameAndType	#717:#719;//  containsSlice:(Lscala/collection/generic/SequenceTemplate;Lscala/collection/Sequence;)Z
const #721 = Method	#70.#720;	//  scala/collection/generic/SequenceTemplate$class.containsSlice:(Lscala/collection/generic/SequenceTemplate;Lscala/collection/Sequence;)Z
const #722 = Asciz	equalsWith;
const #723 = Asciz	(Lscala/collection/Sequence;Lscala/Function2;)Z;
const #724 = Asciz	(Lscala/collection/generic/SequenceTemplate;Lscala/collection/Sequence;Lscala/Function2;)Z;
const #725 = NameAndType	#722:#724;//  equalsWith:(Lscala/collection/generic/SequenceTemplate;Lscala/collection/Sequence;Lscala/Function2;)Z
const #726 = Method	#70.#725;	//  scala/collection/generic/SequenceTemplate$class.equalsWith:(Lscala/collection/generic/SequenceTemplate;Lscala/collection/Sequence;Lscala/Function2;)Z
const #727 = Asciz	(I)Lscala/collection/Sequence;;
const #728 = Asciz	(Lscala/collection/generic/SequenceTemplate;I)Lscala/collection/Sequence;;
const #729 = NameAndType	#138:#728;//  slice:(Lscala/collection/generic/SequenceTemplate;I)Lscala/collection/Sequence;
const #730 = Method	#70.#729;	//  scala/collection/generic/SequenceTemplate$class.slice:(Lscala/collection/generic/SequenceTemplate;I)Lscala/collection/Sequence;
const #731 = Asciz	findLastIndexOf;
const #732 = Asciz	(Lscala/collection/generic/SequenceTemplate;Lscala/Function1;)I;
const #733 = NameAndType	#731:#732;//  findLastIndexOf:(Lscala/collection/generic/SequenceTemplate;Lscala/Function1;)I
const #734 = Method	#70.#733;	//  scala/collection/generic/SequenceTemplate$class.findLastIndexOf:(Lscala/collection/generic/SequenceTemplate;Lscala/Function1;)I
const #735 = Asciz	indices;
const #736 = Asciz	()Lscala/Range;;
const #737 = Asciz	(Lscala/collection/generic/SequenceTemplate;)Lscala/Range;;
const #738 = NameAndType	#735:#737;//  indices:(Lscala/collection/generic/SequenceTemplate;)Lscala/Range;
const #739 = Method	#70.#738;	//  scala/collection/generic/SequenceTemplate$class.indices:(Lscala/collection/generic/SequenceTemplate;)Lscala/Range;
const #740 = Asciz	toSequence;
const #741 = Asciz	(Lscala/collection/generic/SequenceTemplate;)Lscala/collection/Sequence;;
const #742 = NameAndType	#740:#741;//  toSequence:(Lscala/collection/generic/SequenceTemplate;)Lscala/collection/Sequence;
const #743 = Method	#70.#742;	//  scala/collection/generic/SequenceTemplate$class.toSequence:(Lscala/collection/generic/SequenceTemplate;)Lscala/collection/Sequence;
const #744 = Asciz	padTo;
const #745 = Asciz	(ILjava/lang/Object;Lscala/collection/generic/BuilderFactory;)Ljava/lang/Object;;
const #746 = Asciz	(Lscala/collection/generic/SequenceTemplate;ILjava/lang/Object;Lscala/collection/generic/BuilderFactory;)Ljava/lang/Object;;
const #747 = NameAndType	#744:#746;//  padTo:(Lscala/collection/generic/SequenceTemplate;ILjava/lang/Object;Lscala/collection/generic/BuilderFactory;)Ljava/lang/Object;
const #748 = Method	#70.#747;	//  scala/collection/generic/SequenceTemplate$class.padTo:(Lscala/collection/generic/SequenceTemplate;ILjava/lang/Object;Lscala/collection/generic/BuilderFactory;)Ljava/lang/Object;
const #749 = Asciz	elem;
const #750 = Asciz	patch;
const #751 = Asciz	(ILscala/collection/Sequence;ILscala/collection/generic/BuilderFactory;)Ljava/lang/Object;;
const #752 = Asciz	(Lscala/collection/generic/SequenceTemplate;ILscala/collection/Sequence;ILscala/collection/generic/BuilderFactory;)Ljava/lang/Object;;
const #753 = NameAndType	#750:#752;//  patch:(Lscala/collection/generic/SequenceTemplate;ILscala/collection/Sequence;ILscala/collection/generic/BuilderFactory;)Ljava/lang/Object;
const #754 = Method	#70.#753;	//  scala/collection/generic/SequenceTemplate$class.patch:(Lscala/collection/generic/SequenceTemplate;ILscala/collection/Sequence;ILscala/collection/generic/BuilderFactory;)Ljava/lang/Object;
const #755 = Asciz	replaced;
const #756 = Asciz	removeDuplicates;
const #757 = Asciz	(Lscala/collection/generic/SequenceTemplate;)Lscala/collection/generic/IterableTemplate;;
const #758 = NameAndType	#756:#757;//  removeDuplicates:(Lscala/collection/generic/SequenceTemplate;)Lscala/collection/generic/IterableTemplate;
const #759 = Method	#70.#758;	//  scala/collection/generic/SequenceTemplate$class.removeDuplicates:(Lscala/collection/generic/SequenceTemplate;)Lscala/collection/generic/IterableTemplate;
const #760 = Asciz	intersect;
const #761 = Asciz	(Lscala/collection/Sequence;)Lscala/collection/generic/IterableTemplate;;
const #762 = Asciz	(Lscala/collection/generic/SequenceTemplate;Lscala/collection/Sequence;)Lscala/collection/generic/IterableTemplate;;
const #763 = NameAndType	#760:#762;//  intersect:(Lscala/collection/generic/SequenceTemplate;Lscala/collection/Sequence;)Lscala/collection/generic/IterableTemplate;
const #764 = Method	#70.#763;	//  scala/collection/generic/SequenceTemplate$class.intersect:(Lscala/collection/generic/SequenceTemplate;Lscala/collection/Sequence;)Lscala/collection/generic/IterableTemplate;
const #765 = Asciz	diff;
const #766 = NameAndType	#765:#762;//  diff:(Lscala/collection/generic/SequenceTemplate;Lscala/collection/Sequence;)Lscala/collection/generic/IterableTemplate;
const #767 = Method	#70.#766;	//  scala/collection/generic/SequenceTemplate$class.diff:(Lscala/collection/generic/SequenceTemplate;Lscala/collection/Sequence;)Lscala/collection/generic/IterableTemplate;
const #768 = Asciz	union;
const #769 = Asciz	(Lscala/collection/Sequence;Lscala/collection/generic/BuilderFactory;)Ljava/lang/Object;;
const #770 = Asciz	(Lscala/collection/generic/SequenceTemplate;Lscala/collection/Sequence;Lscala/collection/generic/BuilderFactory;)Ljava/lang/Object;;
const #771 = NameAndType	#768:#770;//  union:(Lscala/collection/generic/SequenceTemplate;Lscala/collection/Sequence;Lscala/collection/generic/BuilderFactory;)Ljava/lang/Object;
const #772 = Method	#70.#771;	//  scala/collection/generic/SequenceTemplate$class.union:(Lscala/collection/generic/SequenceTemplate;Lscala/collection/Sequence;Lscala/collection/generic/BuilderFactory;)Ljava/lang/Object;
const #773 = Asciz	contains;
const #774 = Asciz	(Lscala/collection/generic/SequenceTemplate;Ljava/lang/Object;)Z;
const #775 = NameAndType	#773:#774;//  contains:(Lscala/collection/generic/SequenceTemplate;Ljava/lang/Object;)Z
const #776 = Method	#70.#775;	//  scala/collection/generic/SequenceTemplate$class.contains:(Lscala/collection/generic/SequenceTemplate;Ljava/lang/Object;)Z
const #777 = Asciz	lastIndexOfSeq;
const #778 = Asciz	(Lscala/collection/Sequence;I)I;
const #779 = Asciz	(Lscala/collection/generic/SequenceTemplate;Lscala/collection/Sequence;I)I;
const #780 = NameAndType	#777:#779;//  lastIndexOfSeq:(Lscala/collection/generic/SequenceTemplate;Lscala/collection/Sequence;I)I
const #781 = Method	#70.#780;	//  scala/collection/generic/SequenceTemplate$class.lastIndexOfSeq:(Lscala/collection/generic/SequenceTemplate;Lscala/collection/Sequence;I)I
const #782 = Asciz	fromIndex;
const #783 = Asciz	(Lscala/collection/Sequence;)I;
const #784 = Asciz	(Lscala/collection/generic/SequenceTemplate;Lscala/collection/Sequence;)I;
const #785 = NameAndType	#777:#784;//  lastIndexOfSeq:(Lscala/collection/generic/SequenceTemplate;Lscala/collection/Sequence;)I
const #786 = Method	#70.#785;	//  scala/collection/generic/SequenceTemplate$class.lastIndexOfSeq:(Lscala/collection/generic/SequenceTemplate;Lscala/collection/Sequence;)I
const #787 = Asciz	indexOfSeq;
const #788 = NameAndType	#787:#779;//  indexOfSeq:(Lscala/collection/generic/SequenceTemplate;Lscala/collection/Sequence;I)I
const #789 = Method	#70.#788;	//  scala/collection/generic/SequenceTemplate$class.indexOfSeq:(Lscala/collection/generic/SequenceTemplate;Lscala/collection/Sequence;I)I
const #790 = NameAndType	#787:#784;//  indexOfSeq:(Lscala/collection/generic/SequenceTemplate;Lscala/collection/Sequence;)I
const #791 = Method	#70.#790;	//  scala/collection/generic/SequenceTemplate$class.indexOfSeq:(Lscala/collection/generic/SequenceTemplate;Lscala/collection/Sequence;)I
const #792 = Asciz	startsWith;
const #793 = NameAndType	#792:#719;//  startsWith:(Lscala/collection/generic/SequenceTemplate;Lscala/collection/Sequence;)Z
const #794 = Method	#70.#793;	//  scala/collection/generic/SequenceTemplate$class.startsWith:(Lscala/collection/generic/SequenceTemplate;Lscala/collection/Sequence;)Z
const #795 = Asciz	reversedElements;
const #796 = Asciz	(Lscala/collection/generic/SequenceTemplate;)Lscala/collection/Iterator;;
const #797 = NameAndType	#795:#796;//  reversedElements:(Lscala/collection/generic/SequenceTemplate;)Lscala/collection/Iterator;
const #798 = Method	#70.#797;	//  scala/collection/generic/SequenceTemplate$class.reversedElements:(Lscala/collection/generic/SequenceTemplate;)Lscala/collection/Iterator;
const #799 = Asciz	lastIndexWhere;
const #800 = NameAndType	#799:#732;//  lastIndexWhere:(Lscala/collection/generic/SequenceTemplate;Lscala/Function1;)I
const #801 = Method	#70.#800;	//  scala/collection/generic/SequenceTemplate$class.lastIndexWhere:(Lscala/collection/generic/SequenceTemplate;Lscala/Function1;)I
const #802 = Asciz	lastIndexOf;
const #803 = Asciz	(Ljava/lang/Object;I)I;
const #804 = Asciz	(Lscala/collection/generic/SequenceTemplate;Ljava/lang/Object;I)I;
const #805 = NameAndType	#802:#804;//  lastIndexOf:(Lscala/collection/generic/SequenceTemplate;Ljava/lang/Object;I)I
const #806 = Method	#70.#805;	//  scala/collection/generic/SequenceTemplate$class.lastIndexOf:(Lscala/collection/generic/SequenceTemplate;Ljava/lang/Object;I)I
const #807 = Asciz	(Lscala/collection/generic/SequenceTemplate;Ljava/lang/Object;)I;
const #808 = NameAndType	#802:#807;//  lastIndexOf:(Lscala/collection/generic/SequenceTemplate;Ljava/lang/Object;)I
const #809 = Method	#70.#808;	//  scala/collection/generic/SequenceTemplate$class.lastIndexOf:(Lscala/collection/generic/SequenceTemplate;Ljava/lang/Object;)I
const #810 = Asciz	indexOf;
const #811 = NameAndType	#810:#804;//  indexOf:(Lscala/collection/generic/SequenceTemplate;Ljava/lang/Object;I)I
const #812 = Method	#70.#811;	//  scala/collection/generic/SequenceTemplate$class.indexOf:(Lscala/collection/generic/SequenceTemplate;Ljava/lang/Object;I)I
const #813 = NameAndType	#810:#807;//  indexOf:(Lscala/collection/generic/SequenceTemplate;Ljava/lang/Object;)I
const #814 = Method	#70.#813;	//  scala/collection/generic/SequenceTemplate$class.indexOf:(Lscala/collection/generic/SequenceTemplate;Ljava/lang/Object;)I
const #815 = Asciz	findIndexOf;
const #816 = NameAndType	#815:#732;//  findIndexOf:(Lscala/collection/generic/SequenceTemplate;Lscala/Function1;)I
const #817 = Method	#70.#816;	//  scala/collection/generic/SequenceTemplate$class.findIndexOf:(Lscala/collection/generic/SequenceTemplate;Lscala/Function1;)I
const #818 = Asciz	indexWhere;
const #819 = NameAndType	#818:#732;//  indexWhere:(Lscala/collection/generic/SequenceTemplate;Lscala/Function1;)I
const #820 = Method	#70.#819;	//  scala/collection/generic/SequenceTemplate$class.indexWhere:(Lscala/collection/generic/SequenceTemplate;Lscala/Function1;)I
const #821 = Asciz	prefixLength;
const #822 = NameAndType	#821:#732;//  prefixLength:(Lscala/collection/generic/SequenceTemplate;Lscala/Function1;)I
const #823 = Method	#70.#822;	//  scala/collection/generic/SequenceTemplate$class.prefixLength:(Lscala/collection/generic/SequenceTemplate;Lscala/Function1;)I
const #824 = Asciz	zipAll;
const #825 = Asciz	(Lscala/collection/Sequence;Ljava/lang/Object;Ljava/lang/Object;Lscala/collection/generic/BuilderFactory;)Ljava/lang/Object;;
const #826 = Asciz	(Lscala/collection/generic/SequenceTemplate;Lscala/collection/Sequence;Ljava/lang/Object;Ljava/lang/Object;Lscala/collection/generic/BuilderFactory;)Ljava/lang/Object;;
const #827 = NameAndType	#824:#826;//  zipAll:(Lscala/collection/generic/SequenceTemplate;Lscala/collection/Sequence;Ljava/lang/Object;Ljava/lang/Object;Lscala/collection/generic/BuilderFactory;)Ljava/lang/Object;
const #828 = Method	#70.#827;	//  scala/collection/generic/SequenceTemplate$class.zipAll:(Lscala/collection/generic/SequenceTemplate;Lscala/collection/Sequence;Ljava/lang/Object;Ljava/lang/Object;Lscala/collection/generic/BuilderFactory;)Ljava/lang/Object;
const #829 = Asciz	thisElem;
const #830 = Asciz	thatElem;
const #831 = Asciz	(Lscala/collection/generic/SequenceTemplate;I)Z;
const #832 = NameAndType	#192:#831;//  isDefinedAt:(Lscala/collection/generic/SequenceTemplate;I)Z
const #833 = Method	#70.#832;	//  scala/collection/generic/SequenceTemplate$class.isDefinedAt:(Lscala/collection/generic/SequenceTemplate;I)Z
const #834 = Asciz	size;
const #835 = Asciz	(Lscala/collection/generic/SequenceTemplate;)I;
const #836 = NameAndType	#834:#835;//  size:(Lscala/collection/generic/SequenceTemplate;)I
const #837 = Method	#70.#836;	//  scala/collection/generic/SequenceTemplate$class.size:(Lscala/collection/generic/SequenceTemplate;)I
const #838 = Asciz	hashCode;
const #839 = Asciz	(Lscala/collection/immutable/Sequence;)I;
const #840 = NameAndType	#838:#839;//  hashCode:(Lscala/collection/immutable/Sequence;)I
const #841 = Method	#80.#840;	//  scala/collection/immutable/Sequence$class.hashCode:(Lscala/collection/immutable/Sequence;)I
const #842 = Asciz	(Lscala/collection/generic/VectorTemplate;II)Lscala/collection/generic/VectorView;;
const #843 = NameAndType	#185:#842;//  view:(Lscala/collection/generic/VectorTemplate;II)Lscala/collection/generic/VectorView;
const #844 = Method	#85.#843;	//  scala/collection/generic/VectorTemplate$class.view:(Lscala/collection/generic/VectorTemplate;II)Lscala/collection/generic/VectorView;
const #845 = Asciz	(Lscala/collection/generic/VectorTemplate;)Ljava/lang/Object;;
const #846 = NameAndType	#185:#845;//  view:(Lscala/collection/generic/VectorTemplate;)Ljava/lang/Object;
const #847 = Method	#85.#846;	//  scala/collection/generic/VectorTemplate$class.view:(Lscala/collection/generic/VectorTemplate;)Ljava/lang/Object;
const #848 = Asciz	(Lscala/collection/generic/VectorTemplate;Ljava/lang/Object;)Z;
const #849 = NameAndType	#261:#848;//  equals:(Lscala/collection/generic/VectorTemplate;Ljava/lang/Object;)Z
const #850 = Method	#85.#849;	//  scala/collection/generic/VectorTemplate$class.equals:(Lscala/collection/generic/VectorTemplate;Ljava/lang/Object;)Z
const #851 = Asciz	endsWith;
const #852 = Asciz	(Lscala/collection/generic/VectorTemplate;Lscala/collection/Sequence;)Z;
const #853 = NameAndType	#851:#852;//  endsWith:(Lscala/collection/generic/VectorTemplate;Lscala/collection/Sequence;)Z
const #854 = Method	#85.#853;	//  scala/collection/generic/VectorTemplate$class.endsWith:(Lscala/collection/generic/VectorTemplate;Lscala/collection/Sequence;)Z
const #855 = Asciz	(Lscala/collection/Sequence;I)Z;
const #856 = Asciz	(Lscala/collection/generic/VectorTemplate;Lscala/collection/Sequence;I)Z;
const #857 = NameAndType	#792:#856;//  startsWith:(Lscala/collection/generic/VectorTemplate;Lscala/collection/Sequence;I)Z
const #858 = Method	#85.#857;	//  scala/collection/generic/VectorTemplate$class.startsWith:(Lscala/collection/generic/VectorTemplate;Lscala/collection/Sequence;I)Z
const #859 = Asciz	offset;
const #860 = Asciz	reverseIterator;
const #861 = Asciz	(Lscala/collection/generic/VectorTemplate;)Lscala/collection/Iterator;;
const #862 = NameAndType	#860:#861;//  reverseIterator:(Lscala/collection/generic/VectorTemplate;)Lscala/collection/Iterator;
const #863 = Method	#85.#862;	//  scala/collection/generic/VectorTemplate$class.reverseIterator:(Lscala/collection/generic/VectorTemplate;)Lscala/collection/Iterator;
const #864 = Asciz	(Lscala/collection/generic/VectorTemplate;)Lscala/collection/generic/VectorTemplate;;
const #865 = NameAndType	#181:#864;//  reverse:(Lscala/collection/generic/VectorTemplate;)Lscala/collection/generic/VectorTemplate;
const #866 = Method	#85.#865;	//  scala/collection/generic/VectorTemplate$class.reverse:(Lscala/collection/generic/VectorTemplate;)Lscala/collection/generic/VectorTemplate;
const #867 = Asciz	(Lscala/Function1;I)I;
const #868 = Asciz	(Lscala/collection/generic/VectorTemplate;Lscala/Function1;I)I;
const #869 = NameAndType	#799:#868;//  lastIndexWhere:(Lscala/collection/generic/VectorTemplate;Lscala/Function1;I)I
const #870 = Method	#85.#869;	//  scala/collection/generic/VectorTemplate$class.lastIndexWhere:(Lscala/collection/generic/VectorTemplate;Lscala/Function1;I)I
const #871 = NameAndType	#818:#868;//  indexWhere:(Lscala/collection/generic/VectorTemplate;Lscala/Function1;I)I
const #872 = Method	#85.#871;	//  scala/collection/generic/VectorTemplate$class.indexWhere:(Lscala/collection/generic/VectorTemplate;Lscala/Function1;I)I
const #873 = Asciz	segmentLength;
const #874 = NameAndType	#873:#868;//  segmentLength:(Lscala/collection/generic/VectorTemplate;Lscala/Function1;I)I
const #875 = Method	#85.#874;	//  scala/collection/generic/VectorTemplate$class.segmentLength:(Lscala/collection/generic/VectorTemplate;Lscala/Function1;I)I
const #876 = Asciz	lengthCompare;
const #877 = Asciz	(I)I;
const #878 = Asciz	(Lscala/collection/generic/VectorTemplate;I)I;
const #879 = NameAndType	#876:#878;//  lengthCompare:(Lscala/collection/generic/VectorTemplate;I)I
const #880 = Method	#85.#879;	//  scala/collection/generic/VectorTemplate$class.lengthCompare:(Lscala/collection/generic/VectorTemplate;I)I
const #881 = Asciz	(Lscala/runtime/BoxedArray;II)V;
const #882 = Asciz	(Lscala/collection/generic/VectorTemplate;Lscala/runtime/BoxedArray;II)V;
const #883 = NameAndType	#551:#882;//  copyToArray:(Lscala/collection/generic/VectorTemplate;Lscala/runtime/BoxedArray;II)V
const #884 = Method	#85.#883;	//  scala/collection/generic/VectorTemplate$class.copyToArray:(Lscala/collection/generic/VectorTemplate;Lscala/runtime/BoxedArray;II)V
const #885 = Asciz	sameElements;
const #886 = Asciz	(Lscala/collection/Iterable;)Z;
const #887 = Asciz	(Lscala/collection/generic/VectorTemplate;Lscala/collection/Iterable;)Z;
const #888 = NameAndType	#885:#887;//  sameElements:(Lscala/collection/generic/VectorTemplate;Lscala/collection/Iterable;)Z
const #889 = Method	#85.#888;	//  scala/collection/generic/VectorTemplate$class.sameElements:(Lscala/collection/generic/VectorTemplate;Lscala/collection/Iterable;)Z
const #890 = Asciz	Lscala/collection/Iterable;;
const #891 = Asciz	span;
const #892 = Asciz	(Lscala/collection/generic/VectorTemplate;Lscala/Function1;)Lscala/Tuple2;;
const #893 = NameAndType	#891:#892;//  span:(Lscala/collection/generic/VectorTemplate;Lscala/Function1;)Lscala/Tuple2;
const #894 = Method	#85.#893;	//  scala/collection/generic/VectorTemplate$class.span:(Lscala/collection/generic/VectorTemplate;Lscala/Function1;)Lscala/Tuple2;
const #895 = Asciz	(Lscala/collection/generic/VectorTemplate;Lscala/Function1;)Lscala/collection/generic/VectorTemplate;;
const #896 = NameAndType	#178:#895;//  dropWhile:(Lscala/collection/generic/VectorTemplate;Lscala/Function1;)Lscala/collection/generic/VectorTemplate;
const #897 = Method	#85.#896;	//  scala/collection/generic/VectorTemplate$class.dropWhile:(Lscala/collection/generic/VectorTemplate;Lscala/Function1;)Lscala/collection/generic/VectorTemplate;
const #898 = NameAndType	#171:#895;//  takeWhile:(Lscala/collection/generic/VectorTemplate;Lscala/Function1;)Lscala/collection/generic/VectorTemplate;
const #899 = Method	#85.#898;	//  scala/collection/generic/VectorTemplate$class.takeWhile:(Lscala/collection/generic/VectorTemplate;Lscala/Function1;)Lscala/collection/generic/VectorTemplate;
const #900 = Asciz	splitAt;
const #901 = Asciz	(I)Lscala/Tuple2;;
const #902 = Asciz	(Lscala/collection/generic/VectorTemplate;I)Lscala/Tuple2;;
const #903 = NameAndType	#900:#902;//  splitAt:(Lscala/collection/generic/VectorTemplate;I)Lscala/Tuple2;
const #904 = Method	#85.#903;	//  scala/collection/generic/VectorTemplate$class.splitAt:(Lscala/collection/generic/VectorTemplate;I)Lscala/Tuple2;
const #905 = Asciz	(Lscala/collection/generic/VectorTemplate;I)Lscala/collection/generic/VectorTemplate;;
const #906 = NameAndType	#168:#905;//  dropRight:(Lscala/collection/generic/VectorTemplate;I)Lscala/collection/generic/VectorTemplate;
const #907 = Method	#85.#906;	//  scala/collection/generic/VectorTemplate$class.dropRight:(Lscala/collection/generic/VectorTemplate;I)Lscala/collection/generic/VectorTemplate;
const #908 = NameAndType	#164:#905;//  takeRight:(Lscala/collection/generic/VectorTemplate;I)Lscala/collection/generic/VectorTemplate;
const #909 = Method	#85.#908;	//  scala/collection/generic/VectorTemplate$class.takeRight:(Lscala/collection/generic/VectorTemplate;I)Lscala/collection/generic/VectorTemplate;
const #910 = NameAndType	#161:#905;//  drop:(Lscala/collection/generic/VectorTemplate;I)Lscala/collection/generic/VectorTemplate;
const #911 = Method	#85.#910;	//  scala/collection/generic/VectorTemplate$class.drop:(Lscala/collection/generic/VectorTemplate;I)Lscala/collection/generic/VectorTemplate;
const #912 = NameAndType	#155:#905;//  take:(Lscala/collection/generic/VectorTemplate;I)Lscala/collection/generic/VectorTemplate;
const #913 = Method	#85.#912;	//  scala/collection/generic/VectorTemplate$class.take:(Lscala/collection/generic/VectorTemplate;I)Lscala/collection/generic/VectorTemplate;
const #914 = NameAndType	#152:#864;//  init:(Lscala/collection/generic/VectorTemplate;)Lscala/collection/generic/VectorTemplate;
const #915 = Method	#85.#914;	//  scala/collection/generic/VectorTemplate$class.init:(Lscala/collection/generic/VectorTemplate;)Lscala/collection/generic/VectorTemplate;
const #916 = NameAndType	#471:#845;//  last:(Lscala/collection/generic/VectorTemplate;)Ljava/lang/Object;
const #917 = Method	#85.#916;	//  scala/collection/generic/VectorTemplate$class.last:(Lscala/collection/generic/VectorTemplate;)Ljava/lang/Object;
const #918 = NameAndType	#147:#864;//  tail:(Lscala/collection/generic/VectorTemplate;)Lscala/collection/generic/VectorTemplate;
const #919 = Method	#85.#918;	//  scala/collection/generic/VectorTemplate$class.tail:(Lscala/collection/generic/VectorTemplate;)Lscala/collection/generic/VectorTemplate;
const #920 = Asciz	head;
const #921 = NameAndType	#920:#845;//  head:(Lscala/collection/generic/VectorTemplate;)Ljava/lang/Object;
const #922 = Method	#85.#921;	//  scala/collection/generic/VectorTemplate$class.head:(Lscala/collection/generic/VectorTemplate;)Ljava/lang/Object;
const #923 = Asciz	(Lscala/collection/generic/VectorTemplate;II)Lscala/collection/generic/VectorTemplate;;
const #924 = NameAndType	#138:#923;//  slice:(Lscala/collection/generic/VectorTemplate;II)Lscala/collection/generic/VectorTemplate;
const #925 = Method	#85.#924;	//  scala/collection/generic/VectorTemplate$class.slice:(Lscala/collection/generic/VectorTemplate;II)Lscala/collection/generic/VectorTemplate;
const #926 = Asciz	zipWithIndex;
const #927 = Asciz	(Lscala/collection/generic/BuilderFactory;)Ljava/lang/Object;;
const #928 = Asciz	(Lscala/collection/generic/VectorTemplate;Lscala/collection/generic/BuilderFactory;)Ljava/lang/Object;;
const #929 = NameAndType	#926:#928;//  zipWithIndex:(Lscala/collection/generic/VectorTemplate;Lscala/collection/generic/BuilderFactory;)Ljava/lang/Object;
const #930 = Method	#85.#929;	//  scala/collection/generic/VectorTemplate$class.zipWithIndex:(Lscala/collection/generic/VectorTemplate;Lscala/collection/generic/BuilderFactory;)Ljava/lang/Object;
const #931 = Asciz	zip;
const #932 = Asciz	(Lscala/collection/generic/VectorTemplate;Lscala/collection/Sequence;Lscala/collection/generic/BuilderFactory;)Ljava/lang/Object;;
const #933 = NameAndType	#931:#932;//  zip:(Lscala/collection/generic/VectorTemplate;Lscala/collection/Sequence;Lscala/collection/generic/BuilderFactory;)Ljava/lang/Object;
const #934 = Method	#85.#933;	//  scala/collection/generic/VectorTemplate$class.zip:(Lscala/collection/generic/VectorTemplate;Lscala/collection/Sequence;Lscala/collection/generic/BuilderFactory;)Ljava/lang/Object;
const #935 = Asciz	reduceRight;
const #936 = Asciz	(Lscala/Function2;)Ljava/lang/Object;;
const #937 = Asciz	(Lscala/collection/generic/VectorTemplate;Lscala/Function2;)Ljava/lang/Object;;
const #938 = NameAndType	#935:#937;//  reduceRight:(Lscala/collection/generic/VectorTemplate;Lscala/Function2;)Ljava/lang/Object;
const #939 = Method	#85.#938;	//  scala/collection/generic/VectorTemplate$class.reduceRight:(Lscala/collection/generic/VectorTemplate;Lscala/Function2;)Ljava/lang/Object;
const #940 = Asciz	reduceLeft;
const #941 = NameAndType	#940:#937;//  reduceLeft:(Lscala/collection/generic/VectorTemplate;Lscala/Function2;)Ljava/lang/Object;
const #942 = Method	#85.#941;	//  scala/collection/generic/VectorTemplate$class.reduceLeft:(Lscala/collection/generic/VectorTemplate;Lscala/Function2;)Ljava/lang/Object;
const #943 = Asciz	foldRight;
const #944 = Asciz	(Lscala/collection/generic/VectorTemplate;Ljava/lang/Object;Lscala/Function2;)Ljava/lang/Object;;
const #945 = NameAndType	#943:#944;//  foldRight:(Lscala/collection/generic/VectorTemplate;Ljava/lang/Object;Lscala/Function2;)Ljava/lang/Object;
const #946 = Method	#85.#945;	//  scala/collection/generic/VectorTemplate$class.foldRight:(Lscala/collection/generic/VectorTemplate;Ljava/lang/Object;Lscala/Function2;)Ljava/lang/Object;
const #947 = NameAndType	#359:#944;//  foldLeft:(Lscala/collection/generic/VectorTemplate;Ljava/lang/Object;Lscala/Function2;)Ljava/lang/Object;
const #948 = Method	#85.#947;	//  scala/collection/generic/VectorTemplate$class.foldLeft:(Lscala/collection/generic/VectorTemplate;Ljava/lang/Object;Lscala/Function2;)Ljava/lang/Object;
const #949 = Asciz	find;
const #950 = Asciz	(Lscala/Function1;)Lscala/Option;;
const #951 = Asciz	(Lscala/collection/generic/VectorTemplate;Lscala/Function1;)Lscala/Option;;
const #952 = NameAndType	#949:#951;//  find:(Lscala/collection/generic/VectorTemplate;Lscala/Function1;)Lscala/Option;
const #953 = Method	#85.#952;	//  scala/collection/generic/VectorTemplate$class.find:(Lscala/collection/generic/VectorTemplate;Lscala/Function1;)Lscala/Option;
const #954 = Asciz	exists;
const #955 = Asciz	(Lscala/Function1;)Z;
const #956 = Asciz	(Lscala/collection/generic/VectorTemplate;Lscala/Function1;)Z;
const #957 = NameAndType	#954:#956;//  exists:(Lscala/collection/generic/VectorTemplate;Lscala/Function1;)Z
const #958 = Method	#85.#957;	//  scala/collection/generic/VectorTemplate$class.exists:(Lscala/collection/generic/VectorTemplate;Lscala/Function1;)Z
const #959 = Asciz	forall;
const #960 = NameAndType	#959:#956;//  forall:(Lscala/collection/generic/VectorTemplate;Lscala/Function1;)Z
const #961 = Method	#85.#960;	//  scala/collection/generic/VectorTemplate$class.forall:(Lscala/collection/generic/VectorTemplate;Lscala/Function1;)Z
const #962 = Asciz	(Lscala/collection/generic/VectorTemplate;Lscala/Function1;)V;
const #963 = NameAndType	#401:#962;//  foreach:(Lscala/collection/generic/VectorTemplate;Lscala/Function1;)V
const #964 = Method	#85.#963;	//  scala/collection/generic/VectorTemplate$class.foreach:(Lscala/collection/generic/VectorTemplate;Lscala/Function1;)V
const #965 = Asciz	isEmpty;
const #966 = Asciz	(Lscala/collection/generic/VectorTemplate;)Z;
const #967 = NameAndType	#965:#966;//  isEmpty:(Lscala/collection/generic/VectorTemplate;)Z
const #968 = Method	#85.#967;	//  scala/collection/generic/VectorTemplate$class.isEmpty:(Lscala/collection/generic/VectorTemplate;)Z
const #969 = Asciz	iterator;
const #970 = NameAndType	#969:#861;//  iterator:(Lscala/collection/generic/VectorTemplate;)Lscala/collection/Iterator;
const #971 = Method	#85.#970;	//  scala/collection/generic/VectorTemplate$class.iterator:(Lscala/collection/generic/VectorTemplate;)Lscala/collection/Iterator;
const #972 = Asciz	scala$collection$generic$VectorTemplate$$super$equals;
const #973 = NameAndType	#261:#774;//  equals:(Lscala/collection/generic/SequenceTemplate;Ljava/lang/Object;)Z
const #974 = Method	#70.#973;	//  scala/collection/generic/SequenceTemplate$class.equals:(Lscala/collection/generic/SequenceTemplate;Ljava/lang/Object;)Z
const #975 = Asciz	scala$collection$generic$VectorTemplate$$super$endsWith;
const #976 = NameAndType	#851:#719;//  endsWith:(Lscala/collection/generic/SequenceTemplate;Lscala/collection/Sequence;)Z
const #977 = Method	#70.#976;	//  scala/collection/generic/SequenceTemplate$class.endsWith:(Lscala/collection/generic/SequenceTemplate;Lscala/collection/Sequence;)Z
const #978 = Asciz	scala$collection$generic$VectorTemplate$$super$sameElements;
const #979 = Asciz	(Lscala/collection/generic/IterableTemplate;Lscala/collection/Iterable;)Z;
const #980 = NameAndType	#885:#979;//  sameElements:(Lscala/collection/generic/IterableTemplate;Lscala/collection/Iterable;)Z
const #981 = Method	#45.#980;	//  scala/collection/generic/IterableTemplate$class.sameElements:(Lscala/collection/generic/IterableTemplate;Lscala/collection/Iterable;)Z
const #982 = Asciz	scala$collection$generic$VectorTemplate$$super$init;
const #983 = NameAndType	#152:#652;//  init:(Lscala/collection/generic/TraversableTemplate;)Lscala/collection/generic/TraversableTemplate;
const #984 = Method	#25.#983;	//  scala/collection/generic/TraversableTemplate$class.init:(Lscala/collection/generic/TraversableTemplate;)Lscala/collection/generic/TraversableTemplate;
const #985 = Asciz	scala$collection$generic$VectorTemplate$$super$last;
const #986 = Asciz	(Lscala/collection/generic/TraversableTemplate;)Ljava/lang/Object;;
const #987 = NameAndType	#471:#986;//  last:(Lscala/collection/generic/TraversableTemplate;)Ljava/lang/Object;
const #988 = Method	#25.#987;	//  scala/collection/generic/TraversableTemplate$class.last:(Lscala/collection/generic/TraversableTemplate;)Ljava/lang/Object;
const #989 = Asciz	scala$collection$generic$VectorTemplate$$super$head;
const #990 = NameAndType	#920:#683;//  head:(Lscala/collection/generic/IterableTemplate;)Ljava/lang/Object;
const #991 = Method	#45.#990;	//  scala/collection/generic/IterableTemplate$class.head:(Lscala/collection/generic/IterableTemplate;)Ljava/lang/Object;
const #992 = Asciz	scala$collection$generic$VectorTemplate$$super$zip;
const #993 = NameAndType	#931:#770;//  zip:(Lscala/collection/generic/SequenceTemplate;Lscala/collection/Sequence;Lscala/collection/generic/BuilderFactory;)Ljava/lang/Object;
const #994 = Method	#70.#993;	//  scala/collection/generic/SequenceTemplate$class.zip:(Lscala/collection/generic/SequenceTemplate;Lscala/collection/Sequence;Lscala/collection/generic/BuilderFactory;)Ljava/lang/Object;
const #995 = Asciz	scala$collection$generic$VectorTemplate$$super$reduceRight;
const #996 = Asciz	(Lscala/collection/generic/IterableTemplate;Lscala/Function2;)Ljava/lang/Object;;
const #997 = NameAndType	#935:#996;//  reduceRight:(Lscala/collection/generic/IterableTemplate;Lscala/Function2;)Ljava/lang/Object;
const #998 = Method	#45.#997;	//  scala/collection/generic/IterableTemplate$class.reduceRight:(Lscala/collection/generic/IterableTemplate;Lscala/Function2;)Ljava/lang/Object;
const #999 = Asciz	scala$collection$generic$VectorTemplate$$super$reduceLeft;
const #1000 = Asciz	(Lscala/collection/generic/TraversableTemplate;Lscala/Function2;)Ljava/lang/Object;;
const #1001 = NameAndType	#940:#1000;//  reduceLeft:(Lscala/collection/generic/TraversableTemplate;Lscala/Function2;)Ljava/lang/Object;
const #1002 = Method	#25.#1001;	//  scala/collection/generic/TraversableTemplate$class.reduceLeft:(Lscala/collection/generic/TraversableTemplate;Lscala/Function2;)Ljava/lang/Object;
const #1003 = Asciz	companion;
const #1004 = Asciz	()Lscala/collection/generic/Companion;;
const #1005 = Asciz	(Lscala/collection/immutable/Vector;)Lscala/collection/generic/Companion;;
const #1006 = NameAndType	#1003:#1005;//  companion:(Lscala/collection/immutable/Vector;)Lscala/collection/generic/Companion;
const #1007 = Method	#95.#1006;	//  scala/collection/immutable/Vector$class.companion:(Lscala/collection/immutable/Vector;)Lscala/collection/generic/Companion;
const #1008 = Asciz	(Lscala/Ordered;Ljava/lang/Object;)I;
const #1009 = NameAndType	#476:#1008;//  compareTo:(Lscala/Ordered;Ljava/lang/Object;)I
const #1010 = Method	#100.#1009;	//  scala/Ordered$class.compareTo:(Lscala/Ordered;Ljava/lang/Object;)I
const #1011 = Asciz	$greater$eq;
const #1012 = Asciz	(Lscala/Ordered;Ljava/lang/Object;)Z;
const #1013 = NameAndType	#1011:#1012;//  $greater$eq:(Lscala/Ordered;Ljava/lang/Object;)Z
const #1014 = Method	#100.#1013;	//  scala/Ordered$class.$greater$eq:(Lscala/Ordered;Ljava/lang/Object;)Z
const #1015 = Asciz	$less$eq;
const #1016 = NameAndType	#1015:#1012;//  $less$eq:(Lscala/Ordered;Ljava/lang/Object;)Z
const #1017 = Method	#100.#1016;	//  scala/Ordered$class.$less$eq:(Lscala/Ordered;Ljava/lang/Object;)Z
const #1018 = Asciz	$greater;
const #1019 = NameAndType	#1018:#1012;//  $greater:(Lscala/Ordered;Ljava/lang/Object;)Z
const #1020 = Method	#100.#1019;	//  scala/Ordered$class.$greater:(Lscala/Ordered;Ljava/lang/Object;)Z
const #1021 = Asciz	$less;
const #1022 = NameAndType	#1021:#1012;//  $less:(Lscala/Ordered;Ljava/lang/Object;)Z
const #1023 = Method	#100.#1022;	//  scala/Ordered$class.$less:(Lscala/Ordered;Ljava/lang/Object;)Z
const #1024 = Asciz	Ljava/lang/Object;Lscala/Proxy;Lscala/collection/immutable/Vector<Ljava/lang/Character;>;Lscala/collection/generic/VectorTemplate<Ljava/lang/Character;Lscala/runtime/RichString;>;Lscala/PartialFunction<Ljava/lang/Integer;Ljava/lang/Character;>;Lscala/Ordered<Ljava/lang/String;>;Lscala/ScalaObject;;
const #1025 = Asciz	ScalaSig;
const #1026 = Asciz	InnerClasses;
const #1027 = Asciz	scala/runtime/RichString$$anon$2;
const #1028 = class	#1027;	//  scala/runtime/RichString$$anon$2
const #1029 = Asciz	$anon$2;
const #1030 = Asciz	$anon$1;
const #1031 = Asciz	scala/runtime/RichString$$anon$3;
const #1032 = class	#1031;	//  scala/runtime/RichString$$anon$3
const #1033 = Asciz	$anon$3;
const #1034 = Asciz	$anonfun$1;
const #1035 = Asciz	$anonfun$lines$1;
const #1036 = Asciz	$anonfun$$times$1;
const #1037 = Asciz	scala/runtime/RichString$$anonfun$newBuilder$1;
const #1038 = class	#1037;	//  scala/runtime/RichString$$anonfun$newBuilder$1
const #1039 = Asciz	$anonfun$newBuilder$1;
const #1040 = Asciz	$anonfun$stripMargin$1;
const #1041 = Asciz	$anonfun$linesIterator$1;
const #1042 = Asciz	scala/Proxy;
const #1043 = class	#1042;	//  scala/Proxy
const #1044 = Asciz	scala/collection/immutable/Vector;
const #1045 = class	#1044;	//  scala/collection/immutable/Vector
const #1046 = Asciz	scala/Ordered;
const #1047 = class	#1046;	//  scala/Ordered
const #1048 = Asciz	scala/ScalaObject;
const #1049 = class	#1048;	//  scala/ScalaObject

{
public scala.runtime.RichString(java.lang.String);
  Code:
   Stack=2, Locals=2, Args_size=2
   0:	aload_0
   1:	aload_1
   2:	putfield	#12; //Field self:Ljava/lang/String;
   5:	aload_0
   6:	invokespecial	#17; //Method java/lang/Object."<init>":()V
   9:	aload_0
   10:	invokestatic	#23; //Method scala/Proxy$class.$init$:(Lscala/Proxy;)V
   13:	aload_0
   14:	invokestatic	#28; //Method scala/collection/generic/TraversableTemplate$class.$init$:(Lscala/collection/generic/TraversableTemplate;)V
   17:	aload_0
   18:	invokestatic	#33; //Method scala/collection/generic/TraversableClass$class.$init$:(Lscala/collection/generic/TraversableClass;)V
   21:	aload_0
   22:	invokestatic	#38; //Method scala/collection/Traversable$class.$init$:(Lscala/collection/Traversable;)V
   25:	aload_0
   26:	invokestatic	#43; //Method scala/collection/immutable/Traversable$class.$init$:(Lscala/collection/immutable/Traversable;)V
   29:	aload_0
   30:	invokestatic	#48; //Method scala/collection/generic/IterableTemplate$class.$init$:(Lscala/collection/generic/IterableTemplate;)V
   33:	aload_0
   34:	invokestatic	#53; //Method scala/collection/Iterable$class.$init$:(Lscala/collection/Iterable;)V
   37:	aload_0
   38:	invokestatic	#58; //Method scala/collection/immutable/Iterable$class.$init$:(Lscala/collection/immutable/Iterable;)V
   41:	aload_0
   42:	invokestatic	#63; //Method scala/Function1$class.$init$:(Lscala/Function1;)V
   45:	aload_0
   46:	invokestatic	#68; //Method scala/PartialFunction$class.$init$:(Lscala/PartialFunction;)V
   49:	aload_0
   50:	invokestatic	#73; //Method scala/collection/generic/SequenceTemplate$class.$init$:(Lscala/collection/generic/SequenceTemplate;)V
   53:	aload_0
   54:	invokestatic	#78; //Method scala/collection/Sequence$class.$init$:(Lscala/collection/Sequence;)V
   57:	aload_0
   58:	invokestatic	#83; //Method scala/collection/immutable/Sequence$class.$init$:(Lscala/collection/immutable/Sequence;)V
   61:	aload_0
   62:	invokestatic	#88; //Method scala/collection/generic/VectorTemplate$class.$init$:(Lscala/collection/generic/VectorTemplate;)V
   65:	aload_0
   66:	invokestatic	#93; //Method scala/collection/Vector$class.$init$:(Lscala/collection/Vector;)V
   69:	aload_0
   70:	invokestatic	#98; //Method scala/collection/immutable/Vector$class.$init$:(Lscala/collection/immutable/Vector;)V
   73:	aload_0
   74:	invokestatic	#103; //Method scala/Ordered$class.$init$:(Lscala/Ordered;)V
   77:	return
  LineNumberTable: 
   line 34: 0

  LocalVariableTable: 
   Start  Length  Slot  Name   Signature
   0      78      0    this       Lscala/runtime/RichString;
   0      78      1    self       Ljava/lang/String;


public java.lang.Object self();
  Code:
   Stack=1, Locals=1, Args_size=1
   0:	aload_0
   1:	invokevirtual	#110; //Method self:()Ljava/lang/String;
   4:	areturn
  LineNumberTable: 
   line 34: 0


public java.lang.Object apply(int);
  Code:
   Stack=2, Locals=2, Args_size=2
   0:	aload_0
   1:	iload_1
   2:	invokevirtual	#115; //Method apply:(I)C
   5:	invokestatic	#121; //Method scala/runtime/BoxesRunTime.boxToCharacter:(C)Ljava/lang/Character;
   8:	areturn
  LineNumberTable: 
   line 34: 0

  LocalVariableTable: 
   Start  Length  Slot  Name   Signature
   0      9      0    this       Lscala/runtime/RichString;
   0      9      1    idx       I


public java.lang.Object apply(java.lang.Object);
  Code:
   Stack=2, Locals=2, Args_size=2
   0:	aload_0
   1:	aload_1
   2:	invokestatic	#128; //Method scala/runtime/BoxesRunTime.unboxToInt:(Ljava/lang/Object;)I
   5:	invokevirtual	#115; //Method apply:(I)C
   8:	invokestatic	#121; //Method scala/runtime/BoxesRunTime.boxToCharacter:(C)Ljava/lang/Character;
   11:	areturn
  LineNumberTable: 
   line 34: 0

  LocalVariableTable: 
   Start  Length  Slot  Name   Signature
   0      12      0    this       Lscala/runtime/RichString;
   0      12      1    v1       Ljava/lang/Object;


public int compare(java.lang.Object);
  Code:
   Stack=2, Locals=2, Args_size=2
   0:	aload_0
   1:	aload_1
   2:	checkcast	#133; //class java/lang/String
   5:	invokevirtual	#136; //Method compare:(Ljava/lang/String;)I
   8:	ireturn
  LineNumberTable: 
   line 34: 0

  LocalVariableTable: 
   Start  Length  Slot  Name   Signature
   0      9      0    this       Lscala/runtime/RichString;
   0      9      1    that       Ljava/lang/Object;


public scala.collection.generic.TraversableTemplate slice(int, int);
  Code:
   Stack=3, Locals=3, Args_size=3
   0:	aload_0
   1:	iload_1
   2:	iload_2
   3:	invokeinterface	#144,  3; //InterfaceMethod scala/collection/generic/VectorTemplate.slice:(II)Lscala/collection/generic/VectorTemplate;
   8:	areturn
  LineNumberTable: 
   line 34: 0

  LocalVariableTable: 
   Start  Length  Slot  Name   Signature
   0      9      0    this       Lscala/runtime/RichString;
   0      9      1    from       I
   0      9      2    until       I


public scala.collection.generic.TraversableTemplate tail();
  Code:
   Stack=1, Locals=1, Args_size=1
   0:	aload_0
   1:	invokeinterface	#151,  1; //InterfaceMethod scala/collection/generic/VectorTemplate.tail:()Lscala/collection/generic/VectorTemplate;
   6:	areturn
  LineNumberTable: 
   line 34: 0


public scala.collection.generic.TraversableTemplate init();
  Code:
   Stack=1, Locals=1, Args_size=1
   0:	aload_0
   1:	invokeinterface	#154,  1; //InterfaceMethod scala/collection/generic/VectorTemplate.init:()Lscala/collection/generic/VectorTemplate;
   6:	areturn
  LineNumberTable: 
   line 34: 0


public scala.collection.generic.TraversableTemplate take(int);
  Code:
   Stack=2, Locals=2, Args_size=2
   0:	aload_0
   1:	iload_1
   2:	invokeinterface	#159,  2; //InterfaceMethod scala/collection/generic/VectorTemplate.take:(I)Lscala/collection/generic/VectorTemplate;
   7:	areturn
  LineNumberTable: 
   line 34: 0

  LocalVariableTable: 
   Start  Length  Slot  Name   Signature
   0      8      0    this       Lscala/runtime/RichString;
   0      8      1    n       I


public scala.collection.generic.TraversableTemplate drop(int);
  Code:
   Stack=2, Locals=2, Args_size=2
   0:	aload_0
   1:	iload_1
   2:	invokeinterface	#163,  2; //InterfaceMethod scala/collection/generic/VectorTemplate.drop:(I)Lscala/collection/generic/VectorTemplate;
   7:	areturn
  LineNumberTable: 
   line 34: 0

  LocalVariableTable: 
   Start  Length  Slot  Name   Signature
   0      8      0    this       Lscala/runtime/RichString;
   0      8      1    n       I


public scala.collection.generic.IterableTemplate takeRight(int);
  Code:
   Stack=2, Locals=2, Args_size=2
   0:	aload_0
   1:	iload_1
   2:	invokeinterface	#167,  2; //InterfaceMethod scala/collection/generic/VectorTemplate.takeRight:(I)Lscala/collection/generic/VectorTemplate;
   7:	areturn
  LineNumberTable: 
   line 34: 0

  LocalVariableTable: 
   Start  Length  Slot  Name   Signature
   0      8      0    this       Lscala/runtime/RichString;
   0      8      1    n       I


public scala.collection.generic.IterableTemplate dropRight(int);
  Code:
   Stack=2, Locals=2, Args_size=2
   0:	aload_0
   1:	iload_1
   2:	invokeinterface	#170,  2; //InterfaceMethod scala/collection/generic/VectorTemplate.dropRight:(I)Lscala/collection/generic/VectorTemplate;
   7:	areturn
  LineNumberTable: 
   line 34: 0

  LocalVariableTable: 
   Start  Length  Slot  Name   Signature
   0      8      0    this       Lscala/runtime/RichString;
   0      8      1    n       I


public scala.collection.generic.TraversableTemplate takeWhile(scala.Function1);
  Code:
   Stack=2, Locals=2, Args_size=2
   0:	aload_0
   1:	aload_1
   2:	invokeinterface	#175,  2; //InterfaceMethod scala/collection/generic/VectorTemplate.takeWhile:(Lscala/Function1;)Lscala/collection/generic/VectorTemplate;
   7:	areturn
  LineNumberTable: 
   line 34: 0

  LocalVariableTable: 
   Start  Length  Slot  Name   Signature
   0      8      0    this       Lscala/runtime/RichString;
   0      8      1    p       Lscala/Function1;


public scala.collection.generic.TraversableTemplate dropWhile(scala.Function1);
  Code:
   Stack=2, Locals=2, Args_size=2
   0:	aload_0
   1:	aload_1
   2:	invokeinterface	#180,  2; //InterfaceMethod scala/collection/generic/VectorTemplate.dropWhile:(Lscala/Function1;)Lscala/collection/generic/VectorTemplate;
   7:	areturn
  LineNumberTable: 
   line 34: 0

  LocalVariableTable: 
   Start  Length  Slot  Name   Signature
   0      8      0    this       Lscala/runtime/RichString;
   0      8      1    p       Lscala/Function1;


public scala.collection.generic.IterableTemplate reverse();
  Code:
   Stack=1, Locals=1, Args_size=1
   0:	aload_0
   1:	invokeinterface	#184,  1; //InterfaceMethod scala/collection/generic/VectorTemplate.reverse:()Lscala/collection/generic/VectorTemplate;
   6:	areturn
  LineNumberTable: 
   line 34: 0


public scala.collection.generic.SequenceView view(int, int);
  Code:
   Stack=3, Locals=3, Args_size=3
   0:	aload_0
   1:	iload_1
   2:	iload_2
   3:	invokeinterface	#189,  3; //InterfaceMethod scala/collection/generic/VectorTemplate.view:(II)Lscala/collection/generic/VectorView;
   8:	areturn
  LineNumberTable: 
   line 34: 0

  LocalVariableTable: 
   Start  Length  Slot  Name   Signature
   0      9      0    this       Lscala/runtime/RichString;
   0      9      1    from       I
   0      9      2    until       I


public scala.collection.generic.IterableView view(int, int);
  Code:
   Stack=3, Locals=3, Args_size=3
   0:	aload_0
   1:	iload_1
   2:	iload_2
   3:	invokeinterface	#189,  3; //InterfaceMethod scala/collection/generic/VectorTemplate.view:(II)Lscala/collection/generic/VectorView;
   8:	areturn
  LineNumberTable: 
   line 34: 0

  LocalVariableTable: 
   Start  Length  Slot  Name   Signature
   0      9      0    this       Lscala/runtime/RichString;
   0      9      1    from       I
   0      9      2    until       I


public scala.collection.generic.TraversableView view(int, int);
  Code:
   Stack=3, Locals=3, Args_size=3
   0:	aload_0
   1:	iload_1
   2:	iload_2
   3:	invokeinterface	#189,  3; //InterfaceMethod scala/collection/generic/VectorTemplate.view:(II)Lscala/collection/generic/VectorView;
   8:	areturn
  LineNumberTable: 
   line 34: 0

  LocalVariableTable: 
   Start  Length  Slot  Name   Signature
   0      9      0    this       Lscala/runtime/RichString;
   0      9      1    from       I
   0      9      2    until       I


public boolean isDefinedAt(java.lang.Object);
  Code:
   Stack=2, Locals=2, Args_size=2
   0:	aload_0
   1:	aload_1
   2:	invokestatic	#128; //Method scala/runtime/BoxesRunTime.unboxToInt:(Ljava/lang/Object;)I
   5:	invokeinterface	#198,  2; //InterfaceMethod scala/collection/generic/SequenceTemplate.isDefinedAt:(I)Z
   10:	ireturn
  LineNumberTable: 
   line 34: 0

  LocalVariableTable: 
   Start  Length  Slot  Name   Signature
   0      11      0    this       Lscala/runtime/RichString;
   0      11      1    x       Ljava/lang/Object;


public scala.Function1 andThen(scala.Function1);
  Code:
   Stack=2, Locals=2, Args_size=2
   0:	aload_0
   1:	aload_1
   2:	invokeinterface	#206,  2; //InterfaceMethod scala/PartialFunction.andThen:(Lscala/Function1;)Lscala/PartialFunction;
   7:	areturn
  LineNumberTable: 
   line 34: 0

  LocalVariableTable: 
   Start  Length  Slot  Name   Signature
   0      8      0    this       Lscala/runtime/RichString;
   0      8      1    g       Lscala/Function1;


public java.lang.String format(java.util.Locale, scala.collection.Sequence);
  Code:
   Stack=6, Locals=5, Args_size=3
   0:	aload_1
   1:	aload_0
   2:	invokevirtual	#110; //Method self:()Ljava/lang/String;
   5:	getstatic	#215; //Field scala/runtime/ScalaRunTime$.MODULE$:Lscala/runtime/ScalaRunTime$;
   8:	getstatic	#215; //Field scala/runtime/ScalaRunTime$.MODULE$:Lscala/runtime/ScalaRunTime$;
   11:	aload_2
   12:	invokeinterface	#221,  1; //InterfaceMethod scala/collection/generic/TraversableTemplate.toArray:()Lscala/runtime/BoxedArray;
   17:	ldc	#14; //class java/lang/Object
   19:	invokevirtual	#225; //Method scala/runtime/ScalaRunTime$.arrayValue:(Lscala/runtime/BoxedArray;Ljava/lang/Class;)Ljava/lang/Object;
   22:	astore	4
   24:	aload	4
   26:	instanceof	#217; //class scala/collection/generic/TraversableTemplate
   29:	ifeq	37
   32:	aload	4
   34:	goto	45
   37:	getstatic	#215; //Field scala/runtime/ScalaRunTime$.MODULE$:Lscala/runtime/ScalaRunTime$;
   40:	aload	4
   42:	invokevirtual	#229; //Method scala/runtime/ScalaRunTime$.boxArray:(Ljava/lang/Object;)Lscala/runtime/BoxedArray;
   45:	checkcast	#217; //class scala/collection/generic/TraversableTemplate
   48:	invokeinterface	#221,  1; //InterfaceMethod scala/collection/generic/TraversableTemplate.toArray:()Lscala/runtime/BoxedArray;
   53:	ldc	#14; //class java/lang/Object
   55:	invokevirtual	#225; //Method scala/runtime/ScalaRunTime$.arrayValue:(Lscala/runtime/BoxedArray;Ljava/lang/Class;)Ljava/lang/Object;
   58:	astore_3
   59:	aload_3
   60:	instanceof	#231; //class scala/runtime/BoxedArray
   63:	ifeq	81
   66:	getstatic	#215; //Field scala/runtime/ScalaRunTime$.MODULE$:Lscala/runtime/ScalaRunTime$;
   69:	aload_3
   70:	checkcast	#231; //class scala/runtime/BoxedArray
   73:	ldc	#14; //class java/lang/Object
   75:	invokevirtual	#225; //Method scala/runtime/ScalaRunTime$.arrayValue:(Lscala/runtime/BoxedArray;Ljava/lang/Class;)Ljava/lang/Object;
   78:	goto	82
   81:	aload_3
   82:	checkcast	#233; //class "[Ljava/lang/Object;"
   85:	invokestatic	#236; //Method java/lang/String.format:(Ljava/util/Locale;Ljava/lang/String;[Ljava/lang/Object;)Ljava/lang/String;
   88:	areturn
  LineNumberTable: 
   line 240: 0

  LocalVariableTable: 
   Start  Length  Slot  Name   Signature
   0      89      0    this       Lscala/runtime/RichString;
   0      89      1    l       Ljava/util/Locale;
   0      89      2    args       Lscala/collection/Sequence;

  Signature: length = 0x2
   00 FFFFFFF1 

public java.lang.String format(scala.collection.Sequence);
  Code:
   Stack=5, Locals=4, Args_size=2
   0:	aload_0
   1:	invokevirtual	#110; //Method self:()Ljava/lang/String;
   4:	getstatic	#215; //Field scala/runtime/ScalaRunTime$.MODULE$:Lscala/runtime/ScalaRunTime$;
   7:	getstatic	#215; //Field scala/runtime/ScalaRunTime$.MODULE$:Lscala/runtime/ScalaRunTime$;
   10:	aload_1
   11:	invokeinterface	#221,  1; //InterfaceMethod scala/collection/generic/TraversableTemplate.toArray:()Lscala/runtime/BoxedArray;
   16:	ldc	#14; //class java/lang/Object
   18:	invokevirtual	#225; //Method scala/runtime/ScalaRunTime$.arrayValue:(Lscala/runtime/BoxedArray;Ljava/lang/Class;)Ljava/lang/Object;
   21:	astore_3
   22:	aload_3
   23:	instanceof	#217; //class scala/collection/generic/TraversableTemplate
   26:	ifeq	33
   29:	aload_3
   30:	goto	40
   33:	getstatic	#215; //Field scala/runtime/ScalaRunTime$.MODULE$:Lscala/runtime/ScalaRunTime$;
   36:	aload_3
   37:	invokevirtual	#229; //Method scala/runtime/ScalaRunTime$.boxArray:(Ljava/lang/Object;)Lscala/runtime/BoxedArray;
   40:	checkcast	#217; //class scala/collection/generic/TraversableTemplate
   43:	invokeinterface	#221,  1; //InterfaceMethod scala/collection/generic/TraversableTemplate.toArray:()Lscala/runtime/BoxedArray;
   48:	ldc	#14; //class java/lang/Object
   50:	invokevirtual	#225; //Method scala/runtime/ScalaRunTime$.arrayValue:(Lscala/runtime/BoxedArray;Ljava/lang/Class;)Ljava/lang/Object;
   53:	astore_2
   54:	aload_2
   55:	instanceof	#231; //class scala/runtime/BoxedArray
   58:	ifeq	76
   61:	getstatic	#215; //Field scala/runtime/ScalaRunTime$.MODULE$:Lscala/runtime/ScalaRunTime$;
   64:	aload_2
   65:	checkcast	#231; //class scala/runtime/BoxedArray
   68:	ldc	#14; //class java/lang/Object
   70:	invokevirtual	#225; //Method scala/runtime/ScalaRunTime$.arrayValue:(Lscala/runtime/BoxedArray;Ljava/lang/Class;)Ljava/lang/Object;
   73:	goto	77
   76:	aload_2
   77:	checkcast	#233; //class "[Ljava/lang/Object;"
   80:	invokestatic	#246; //Method java/lang/String.format:(Ljava/lang/String;[Ljava/lang/Object;)Ljava/lang/String;
   83:	areturn
  LineNumberTable: 
   line 223: 0

  LocalVariableTable: 
   Start  Length  Slot  Name   Signature
   0      84      0    this       Lscala/runtime/RichString;
   0      84      1    args       Lscala/collection/Sequence;

  Signature: length = 0x2
   00 FFFFFFF7 

public char[] toArray();
  Code:
   Stack=5, Locals=2, Args_size=1
   0:	aload_0
   1:	invokevirtual	#252; //Method length:()I
   4:	newarray char
   6:	astore_1
   7:	aload_0
   8:	invokevirtual	#110; //Method self:()Ljava/lang/String;
   11:	iconst_0
   12:	aload_0
   13:	invokevirtual	#252; //Method length:()I
   16:	aload_1
   17:	iconst_0
   18:	invokevirtual	#256; //Method java/lang/String.getChars:(II[CI)V
   21:	aload_1
   22:	areturn
  LineNumberTable: 
   line 203: 0
   line 204: 7
   line 205: 21

  LocalVariableTable: 
   Start  Length  Slot  Name   Signature
   0      23      0    this       Lscala/runtime/RichString;
   7      15      1    result       [C


public double toDouble();
  Code:
   Stack=2, Locals=1, Args_size=1
   0:	aload_0
   1:	invokevirtual	#110; //Method self:()Ljava/lang/String;
   4:	invokestatic	#300; //Method java/lang/Double.parseDouble:(Ljava/lang/String;)D
   7:	dreturn
  LineNumberTable: 
   line 191: 0


public float toFloat();
  Code:
   Stack=1, Locals=1, Args_size=1
   0:	aload_0
   1:	invokevirtual	#110; //Method self:()Ljava/lang/String;
   4:	invokestatic	#308; //Method java/lang/Float.parseFloat:(Ljava/lang/String;)F
   7:	freturn
  LineNumberTable: 
   line 190: 0


public long toLong();
  Code:
   Stack=2, Locals=1, Args_size=1
   0:	aload_0
   1:	invokevirtual	#110; //Method self:()Ljava/lang/String;
   4:	invokestatic	#316; //Method java/lang/Long.parseLong:(Ljava/lang/String;)J
   7:	lreturn
  LineNumberTable: 
   line 189: 0


public int toInt();
  Code:
   Stack=1, Locals=1, Args_size=1
   0:	aload_0
   1:	invokevirtual	#110; //Method self:()Ljava/lang/String;
   4:	invokestatic	#322; //Method java/lang/Integer.parseInt:(Ljava/lang/String;)I
   7:	ireturn
  LineNumberTable: 
   line 188: 0


public short toShort();
  Code:
   Stack=1, Locals=1, Args_size=1
   0:	aload_0
   1:	invokevirtual	#110; //Method self:()Ljava/lang/String;
   4:	invokestatic	#330; //Method java/lang/Short.parseShort:(Ljava/lang/String;)S
   7:	ireturn
  LineNumberTable: 
   line 187: 0


public byte toByte();
  Code:
   Stack=1, Locals=1, Args_size=1
   0:	aload_0
   1:	invokevirtual	#110; //Method self:()Ljava/lang/String;
   4:	invokestatic	#338; //Method java/lang/Byte.parseByte:(Ljava/lang/String;)B
   7:	ireturn
  LineNumberTable: 
   line 186: 0


public boolean toBoolean();
  Code:
   Stack=2, Locals=1, Args_size=1
   0:	aload_0
   1:	aload_0
   2:	invokevirtual	#110; //Method self:()Ljava/lang/String;
   5:	invokespecial	#342; //Method parseBoolean:(Ljava/lang/String;)Z
   8:	ireturn
  LineNumberTable: 
   line 185: 0


public scala.util.matching.Regex r();
  Code:
   Stack=5, Locals=1, Args_size=1
   0:	new	#346; //class scala/util/matching/Regex
   3:	dup
   4:	aload_0
   5:	invokevirtual	#110; //Method self:()Ljava/lang/String;
   8:	getstatic	#215; //Field scala/runtime/ScalaRunTime$.MODULE$:Lscala/runtime/ScalaRunTime$;
   11:	iconst_0
   12:	anewarray	#133; //class java/lang/String
   15:	invokevirtual	#229; //Method scala/runtime/ScalaRunTime$.boxArray:(Ljava/lang/Object;)Lscala/runtime/BoxedArray;
   18:	invokespecial	#349; //Method scala/util/matching/Regex."<init>":(Ljava/lang/String;Lscala/collection/Sequence;)V
   21:	areturn
  LineNumberTable: 
   line 183: 0


public java.lang.String[] split(char[])   throws java.util.regex.PatternSyntaxException;
  Code:
   Stack=6, Locals=3, Args_size=2
   0:	new	#278; //class scala/collection/mutable/StringBuilder
   3:	dup
   4:	invokespecial	#279; //Method scala/collection/mutable/StringBuilder."<init>":()V
   7:	getstatic	#215; //Field scala/runtime/ScalaRunTime$.MODULE$:Lscala/runtime/ScalaRunTime$;
   10:	aload_1
   11:	invokevirtual	#229; //Method scala/runtime/ScalaRunTime$.boxArray:(Ljava/lang/Object;)Lscala/runtime/BoxedArray;
   14:	ldc_w	#353; //String [
   17:	new	#355; //class scala/runtime/RichString$$anonfun$1
   20:	dup
   21:	aload_0
   22:	invokespecial	#358; //Method scala/runtime/RichString$$anonfun$1."<init>":(Lscala/runtime/RichString;)V
   25:	invokeinterface	#362,  3; //InterfaceMethod scala/collection/generic/VectorTemplate.foldLeft:(Ljava/lang/Object;Lscala/Function2;)Ljava/lang/Object;
   30:	checkcast	#133; //class java/lang/String
   33:	invokevirtual	#285; //Method scala/collection/mutable/StringBuilder.append:(Ljava/lang/Object;)Lscala/collection/mutable/StringBuilder;
   36:	ldc_w	#364; //String ]
   39:	invokevirtual	#285; //Method scala/collection/mutable/StringBuilder.append:(Ljava/lang/Object;)Lscala/collection/mutable/StringBuilder;
   42:	invokevirtual	#290; //Method scala/collection/mutable/StringBuilder.toString:()Ljava/lang/String;
   45:	astore_2
   46:	aload_0
   47:	invokevirtual	#110; //Method self:()Ljava/lang/String;
   50:	aload_2
   51:	invokevirtual	#367; //Method java/lang/String.split:(Ljava/lang/String;)[Ljava/lang/String;
   54:	areturn
  LineNumberTable: 
   line 174: 0
   line 175: 46

  LocalVariableTable: 
   Start  Length  Slot  Name   Signature
   0      55      0    this       Lscala/runtime/RichString;
   0      55      1    separators       [C
   46      8      2    re       Ljava/lang/String;

  Exceptions: 
   throws java.util.regex.PatternSyntaxException
public java.lang.String[] split(char)   throws java.util.regex.PatternSyntaxException;
  Code:
   Stack=3, Locals=2, Args_size=2
   0:	aload_0
   1:	invokevirtual	#110; //Method self:()Ljava/lang/String;
   4:	aload_0
   5:	iload_1
   6:	invokevirtual	#377; //Method scala$runtime$RichString$$escape:(C)Ljava/lang/String;
   9:	invokevirtual	#367; //Method java/lang/String.split:(Ljava/lang/String;)[Ljava/lang/String;
   12:	areturn
  LineNumberTable: 
   line 170: 0

  LocalVariableTable: 
   Start  Length  Slot  Name   Signature
   0      13      0    this       Lscala/runtime/RichString;
   0      13      1    separator       C

  Exceptions: 
   throws java.util.regex.PatternSyntaxException
public final java.lang.String scala$runtime$RichString$$escape(char);
  Code:
   Stack=2, Locals=2, Args_size=2
   0:	new	#278; //class scala/collection/mutable/StringBuilder
   3:	dup
   4:	invokespecial	#279; //Method scala/collection/mutable/StringBuilder."<init>":()V
   7:	ldc_w	#381; //String \Q
   10:	invokevirtual	#285; //Method scala/collection/mutable/StringBuilder.append:(Ljava/lang/Object;)Lscala/collection/mutable/StringBuilder;
   13:	iload_1
   14:	invokestatic	#121; //Method scala/runtime/BoxesRunTime.boxToCharacter:(C)Ljava/lang/Character;
   17:	invokevirtual	#285; //Method scala/collection/mutable/StringBuilder.append:(Ljava/lang/Object;)Lscala/collection/mutable/StringBuilder;
   20:	ldc_w	#383; //String \E
   23:	invokevirtual	#285; //Method scala/collection/mutable/StringBuilder.append:(Ljava/lang/Object;)Lscala/collection/mutable/StringBuilder;
   26:	invokevirtual	#290; //Method scala/collection/mutable/StringBuilder.toString:()Ljava/lang/String;
   29:	areturn
  LineNumberTable: 
   line 167: 0

  LocalVariableTable: 
   Start  Length  Slot  Name   Signature
   0      30      0    this       Lscala/runtime/RichString;
   0      30      1    ch       C


public java.lang.String stripMargin();
  Code:
   Stack=2, Locals=1, Args_size=1
   0:	aload_0
   1:	ldc_w	#386; //int 124
   4:	invokevirtual	#388; //Method stripMargin:(C)Ljava/lang/String;
   7:	areturn
  LineNumberTable: 
   line 165: 0


public java.lang.String stripMargin(char);
  Code:
   Stack=6, Locals=3, Args_size=2
   0:	new	#278; //class scala/collection/mutable/StringBuilder
   3:	dup
   4:	invokespecial	#389; //Method scala/collection/mutable/StringBuilder."<init>":()V
   7:	astore_2
   8:	aload_0
   9:	invokevirtual	#393; //Method linesWithSeparators:()Lscala/collection/Iterator;
   12:	new	#395; //class scala/runtime/RichString$$anonfun$stripMargin$1
   15:	dup
   16:	aload_0
   17:	iload_1
   18:	aload_2
   19:	invokespecial	#398; //Method scala/runtime/RichString$$anonfun$stripMargin$1."<init>":(Lscala/runtime/RichString;CLscala/collection/mutable/StringBuilder;)V
   22:	invokeinterface	#403,  2; //InterfaceMethod scala/collection/Iterator.foreach:(Lscala/Function1;)V
   27:	aload_2
   28:	invokevirtual	#404; //Method scala/collection/mutable/StringBuilder.toString:()Ljava/lang/String;
   31:	areturn
  LineNumberTable: 
   line 146: 0
   line 147: 8
   line 154: 27

  LocalVariableTable: 
   Start  Length  Slot  Name   Signature
   0      32      0    this       Lscala/runtime/RichString;
   0      32      1    marginChar$1       C
   8      23      2    buf$2       Lscala/collection/mutable/StringBuilder;


public java.lang.String capitalize();
  Code:
   Stack=5, Locals=3, Args_size=1
   0:	aload_0
   1:	invokevirtual	#110; //Method self:()Ljava/lang/String;
   4:	dup
   5:	astore_1
   6:	ifnull	17
   9:	aload_1
   10:	aconst_null
   11:	invokevirtual	#263; //Method java/lang/Object.equals:(Ljava/lang/Object;)Z
   14:	ifeq	23
   17:	aconst_null
   18:	pop
   19:	aconst_null
   20:	goto	71
   23:	aload_0
   24:	invokevirtual	#110; //Method self:()Ljava/lang/String;
   27:	invokevirtual	#409; //Method java/lang/String.length:()I
   30:	iconst_0
   31:	if_icmpne	40
   34:	ldc_w	#411; //String 
   37:	goto	71
   40:	aload_0
   41:	invokevirtual	#110; //Method self:()Ljava/lang/String;
   44:	invokevirtual	#414; //Method java/lang/String.toCharArray:()[C
   47:	astore_2
   48:	aload_2
   49:	iconst_0
   50:	getstatic	#419; //Field scala/Predef$.MODULE$:Lscala/Predef$;
   53:	aload_2
   54:	iconst_0
   55:	caload
   56:	invokevirtual	#423; //Method scala/Predef$.charWrapper:(C)Lscala/runtime/RichChar;
   59:	invokevirtual	#429; //Method scala/runtime/RichChar.toUpperCase:()C
   62:	castore
   63:	new	#133; //class java/lang/String
   66:	dup
   67:	aload_2
   68:	invokespecial	#432; //Method java/lang/String."<init>":([C)V
   71:	areturn
  LineNumberTable: 
   line 129: 0
   line 130: 23
   line 132: 40
   line 133: 48
   line 134: 63
   line 129: 71

  LocalVariableTable: 
   Start  Length  Slot  Name   Signature
   0      72      0    this       Lscala/runtime/RichString;
   48      23      2    chars       [C


public scala.collection.Iterator linesIterator();
  Code:
   Stack=4, Locals=1, Args_size=1
   0:	aload_0
   1:	invokevirtual	#393; //Method linesWithSeparators:()Lscala/collection/Iterator;
   4:	new	#436; //class scala/runtime/RichString$$anonfun$linesIterator$1
   7:	dup
   8:	aload_0
   9:	invokespecial	#437; //Method scala/runtime/RichString$$anonfun$linesIterator$1."<init>":(Lscala/runtime/RichString;)V
   12:	invokeinterface	#441,  2; //InterfaceMethod scala/collection/Iterator.map:(Lscala/Function1;)Lscala/collection/Iterator;
   17:	areturn
  LineNumberTable: 
   line 125: 0

  Signature: length = 0x2
   01 FFFFFFBA 

public scala.collection.Iterator lines();
  Code:
   Stack=4, Locals=1, Args_size=1
   0:	aload_0
   1:	invokevirtual	#393; //Method linesWithSeparators:()Lscala/collection/Iterator;
   4:	new	#445; //class scala/runtime/RichString$$anonfun$lines$1
   7:	dup
   8:	aload_0
   9:	invokespecial	#446; //Method scala/runtime/RichString$$anonfun$lines$1."<init>":(Lscala/runtime/RichString;)V
   12:	invokeinterface	#441,  2; //InterfaceMethod scala/collection/Iterator.map:(Lscala/Function1;)Lscala/collection/Iterator;
   17:	areturn
  LineNumberTable: 
   line 118: 0

  Signature: length = 0x2
   01 FFFFFFBA 

public scala.collection.Iterator linesWithSeparators();
  Code:
   Stack=3, Locals=1, Args_size=1
   0:	new	#448; //class scala/runtime/RichString$$anon$1
   3:	dup
   4:	aload_0
   5:	invokespecial	#449; //Method scala/runtime/RichString$$anon$1."<init>":(Lscala/runtime/RichString;)V
   8:	areturn
  LineNumberTable: 
   line 100: 0

  Signature: length = 0x2
   01 FFFFFFBA 

public java.lang.String stripLineEnd();
  Code:
   Stack=5, Locals=3, Args_size=1
   0:	aload_0
   1:	invokevirtual	#110; //Method self:()Ljava/lang/String;
   4:	invokevirtual	#409; //Method java/lang/String.length:()I
   7:	istore_1
   8:	iload_1
   9:	iconst_0
   10:	if_icmpne	20
   13:	aload_0
   14:	invokevirtual	#110; //Method self:()Ljava/lang/String;
   17:	goto	91
   20:	aload_0
   21:	iload_1
   22:	iconst_1
   23:	isub
   24:	invokevirtual	#115; //Method apply:(I)C
   27:	istore_2
   28:	aload_0
   29:	iload_2
   30:	invokevirtual	#454; //Method scala$runtime$RichString$$isLineBreak:(C)Z
   33:	ifeq	87
   36:	aload_0
   37:	invokevirtual	#110; //Method self:()Ljava/lang/String;
   40:	iconst_0
   41:	iload_2
   42:	getstatic	#459; //Field scala/runtime/RichString$.MODULE$:Lscala/runtime/RichString$;
   45:	invokevirtual	#462; //Method scala/runtime/RichString$.scala$runtime$RichString$$LF:()C
   48:	if_icmpne	78
   51:	iload_1
   52:	iconst_2
   53:	if_icmplt	78
   56:	aload_0
   57:	iload_1
   58:	iconst_2
   59:	isub
   60:	invokevirtual	#115; //Method apply:(I)C
   63:	getstatic	#459; //Field scala/runtime/RichString$.MODULE$:Lscala/runtime/RichString$;
   66:	invokevirtual	#465; //Method scala/runtime/RichString$.scala$runtime$RichString$$CR:()C
   69:	if_icmpne	78
   72:	iload_1
   73:	iconst_2
   74:	isub
   75:	goto	81
   78:	iload_1
   79:	iconst_1
   80:	isub
   81:	invokevirtual	#469; //Method java/lang/String.substring:(II)Ljava/lang/String;
   84:	goto	91
   87:	aload_0
   88:	invokevirtual	#110; //Method self:()Ljava/lang/String;
   91:	areturn
  LineNumberTable: 
   line 75: 0
   line 76: 8
   line 78: 20
   line 79: 28
   line 80: 36
   line 82: 87
   line 74: 91

  LocalVariableTable: 
   Start  Length  Slot  Name   Signature
   0      92      0    this       Lscala/runtime/RichString;
   8      84      1    len       I
   28      63      2    last       C


public final boolean scala$runtime$RichString$$isLineBreak(char);
  Code:
   Stack=2, Locals=2, Args_size=2
   0:	iload_1
   1:	getstatic	#459; //Field scala/runtime/RichString$.MODULE$:Lscala/runtime/RichString$;
   4:	invokevirtual	#462; //Method scala/runtime/RichString$.scala$runtime$RichString$$LF:()C
   7:	if_icmpeq	20
   10:	iload_1
   11:	getstatic	#459; //Field scala/runtime/RichString$.MODULE$:Lscala/runtime/RichString$;
   14:	invokevirtual	#474; //Method scala/runtime/RichString$.scala$runtime$RichString$$FF:()C
   17:	if_icmpne	24
   20:	iconst_1
   21:	goto	25
   24:	iconst_0
   25:	ireturn
  LineNumberTable: 
   line 59: 0

  LocalVariableTable: 
   Start  Length  Slot  Name   Signature
   0      26      0    this       Lscala/runtime/RichString;
   0      26      1    c       C


public int compare(java.lang.String);
  Code:
   Stack=2, Locals=2, Args_size=2
   0:	aload_0
   1:	invokevirtual	#110; //Method self:()Ljava/lang/String;
   4:	aload_1
   5:	invokevirtual	#478; //Method java/lang/String.compareTo:(Ljava/lang/String;)I
   8:	ireturn
  LineNumberTable: 
   line 57: 0

  LocalVariableTable: 
   Start  Length  Slot  Name   Signature
   0      9      0    this       Lscala/runtime/RichString;
   0      9      1    other       Ljava/lang/String;


public java.lang.String $times(int);
  Code:
   Stack=5, Locals=3, Args_size=2
   0:	new	#278; //class scala/collection/mutable/StringBuilder
   3:	dup
   4:	invokespecial	#389; //Method scala/collection/mutable/StringBuilder."<init>":()V
   7:	astore_2
   8:	getstatic	#419; //Field scala/Predef$.MODULE$:Lscala/Predef$;
   11:	iconst_0
   12:	invokevirtual	#485; //Method scala/Predef$.intWrapper:(I)Lscala/runtime/RichInt;
   15:	iload_1
   16:	invokevirtual	#490; //Method scala/runtime/RichInt.until:(I)Lscala/Range;
   19:	new	#492; //class scala/runtime/RichString$$anonfun$$times$1
   22:	dup
   23:	aload_0
   24:	aload_2
   25:	invokespecial	#495; //Method scala/runtime/RichString$$anonfun$$times$1."<init>":(Lscala/runtime/RichString;Lscala/collection/mutable/StringBuilder;)V
   28:	invokevirtual	#498; //Method scala/Range.foreach:(Lscala/Function1;)V
   31:	aload_2
   32:	invokevirtual	#404; //Method scala/collection/mutable/StringBuilder.toString:()Ljava/lang/String;
   35:	areturn
  LineNumberTable: 
   line 52: 0
   line 53: 8
   line 54: 31

  LocalVariableTable: 
   Start  Length  Slot  Name   Signature
   0      36      0    this       Lscala/runtime/RichString;
   0      36      1    n       I
   8      27      2    buf$1       Lscala/collection/mutable/StringBuilder;


public java.lang.String toString();
  Code:
   Stack=1, Locals=1, Args_size=1
   0:	aload_0
   1:	invokevirtual	#110; //Method self:()Ljava/lang/String;
   4:	areturn
  LineNumberTable: 
   line 47: 0


public java.lang.String mkString();
  Code:
   Stack=1, Locals=1, Args_size=1
   0:	aload_0
   1:	invokevirtual	#110; //Method self:()Ljava/lang/String;
   4:	areturn
  LineNumberTable: 
   line 46: 0


public int length();
  Code:
   Stack=1, Locals=1, Args_size=1
   0:	aload_0
   1:	invokevirtual	#110; //Method self:()Ljava/lang/String;
   4:	invokevirtual	#409; //Method java/lang/String.length:()I
   7:	ireturn
  LineNumberTable: 
   line 44: 0


public char apply(int);
  Code:
   Stack=2, Locals=2, Args_size=2
   0:	aload_0
   1:	invokevirtual	#110; //Method self:()Ljava/lang/String;
   4:	iload_1
   5:	invokevirtual	#503; //Method java/lang/String.charAt:(I)C
   8:	ireturn
  LineNumberTable: 
   line 42: 0

  LocalVariableTable: 
   Start  Length  Slot  Name   Signature
   0      9      0    this       Lscala/runtime/RichString;
   0      9      1    n       I


public scala.collection.generic.Builder newBuilder();
  Code:
   Stack=1, Locals=1, Args_size=1
   0:	getstatic	#459; //Field scala/runtime/RichString$.MODULE$:Lscala/runtime/RichString$;
   3:	invokevirtual	#507; //Method scala/runtime/RichString$.newBuilder:()Lscala/collection/generic/Builder;
   6:	areturn
  LineNumberTable: 
   line 37: 0

  Signature: length = 0x2
   01 FFFFFFFC 

public java.lang.String self();
  Code:
   Stack=1, Locals=1, Args_size=1
   0:	aload_0
   1:	getfield	#12; //Field self:Ljava/lang/String;
   4:	areturn
  LineNumberTable: 
   line 34: 0


public java.lang.String stringPrefix();
  Code:
   Stack=1, Locals=1, Args_size=1
   0:	aload_0
   1:	invokestatic	#512; //Method scala/collection/generic/TraversableTemplate$class.stringPrefix:(Lscala/collection/generic/TraversableTemplate;)Ljava/lang/String;
   4:	areturn
  LineNumberTable: 
   line 34: 0


public scala.collection.mutable.StringBuilder addString(scala.collection.mutable.StringBuilder);
  Code:
   Stack=2, Locals=2, Args_size=2
   0:	aload_0
   1:	aload_1
   2:	invokestatic	#517; //Method scala/collection/generic/TraversableTemplate$class.addString:(Lscala/collection/generic/TraversableTemplate;Lscala/collection/mutable/StringBuilder;)Lscala/collection/mutable/StringBuilder;
   5:	areturn
  LineNumberTable: 
   line 34: 0

  LocalVariableTable: 
   Start  Length  Slot  Name   Signature
   0      6      0    this       Lscala/runtime/RichString;
   0      6      1    b       Lscala/collection/mutable/StringBuilder;


public scala.collection.mutable.StringBuilder addString(scala.collection.mutable.StringBuilder, java.lang.String);
  Code:
   Stack=3, Locals=3, Args_size=3
   0:	aload_0
   1:	aload_1
   2:	aload_2
   3:	invokestatic	#522; //Method scala/collection/generic/TraversableTemplate$class.addString:(Lscala/collection/generic/TraversableTemplate;Lscala/collection/mutable/StringBuilder;Ljava/lang/String;)Lscala/collection/mutable/StringBuilder;
   6:	areturn
  LineNumberTable: 
   line 34: 0

  LocalVariableTable: 
   Start  Length  Slot  Name   Signature
   0      7      0    this       Lscala/runtime/RichString;
   0      7      1    b       Lscala/collection/mutable/StringBuilder;
   0      7      2    sep       Ljava/lang/String;


public scala.collection.mutable.StringBuilder addString(scala.collection.mutable.StringBuilder, java.lang.String, java.lang.String, java.lang.String);
  Code:
   Stack=5, Locals=5, Args_size=5
   0:	aload_0
   1:	aload_1
   2:	aload_2
   3:	aload_3
   4:	aload	4
   6:	invokestatic	#527; //Method scala/collection/generic/TraversableTemplate$class.addString:(Lscala/collection/generic/TraversableTemplate;Lscala/collection/mutable/StringBuilder;Ljava/lang/String;Ljava/lang/String;Ljava/lang/String;)Lscala/collection/mutable/StringBuilder;
   9:	areturn
  LineNumberTable: 
   line 34: 0

  LocalVariableTable: 
   Start  Length  Slot  Name   Signature
   0      10      0    this       Lscala/runtime/RichString;
   0      10      1    b       Lscala/collection/mutable/StringBuilder;
   0      10      2    start       Ljava/lang/String;
   0      10      3    sep       Ljava/lang/String;
   0      10      4    end       Ljava/lang/String;


public java.lang.String mkString(java.lang.String);
  Code:
   Stack=2, Locals=2, Args_size=2
   0:	aload_0
   1:	aload_1
   2:	invokestatic	#533; //Method scala/collection/generic/TraversableTemplate$class.mkString:(Lscala/collection/generic/TraversableTemplate;Ljava/lang/String;)Ljava/lang/String;
   5:	areturn
  LineNumberTable: 
   line 34: 0

  LocalVariableTable: 
   Start  Length  Slot  Name   Signature
   0      6      0    this       Lscala/runtime/RichString;
   0      6      1    sep       Ljava/lang/String;


public java.lang.String mkString(java.lang.String, java.lang.String, java.lang.String);
  Code:
   Stack=4, Locals=4, Args_size=4
   0:	aload_0
   1:	aload_1
   2:	aload_2
   3:	aload_3
   4:	invokestatic	#537; //Method scala/collection/generic/TraversableTemplate$class.mkString:(Lscala/collection/generic/TraversableTemplate;Ljava/lang/String;Ljava/lang/String;Ljava/lang/String;)Ljava/lang/String;
   7:	areturn
  LineNumberTable: 
   line 34: 0

  LocalVariableTable: 
   Start  Length  Slot  Name   Signature
   0      8      0    this       Lscala/runtime/RichString;
   0      8      1    start       Ljava/lang/String;
   0      8      2    sep       Ljava/lang/String;
   0      8      3    end       Ljava/lang/String;


public scala.collection.immutable.Set toSet();
  Code:
   Stack=1, Locals=1, Args_size=1
   0:	aload_0
   1:	invokestatic	#542; //Method scala/collection/generic/TraversableTemplate$class.toSet:(Lscala/collection/generic/TraversableTemplate;)Lscala/collection/immutable/Set;
   4:	areturn
  LineNumberTable: 
   line 34: 0


public scala.collection.immutable.List toList();
  Code:
   Stack=1, Locals=1, Args_size=1
   0:	aload_0
   1:	invokestatic	#547; //Method scala/collection/generic/TraversableTemplate$class.toList:(Lscala/collection/generic/TraversableTemplate;)Lscala/collection/immutable/List;
   4:	areturn
  LineNumberTable: 
   line 34: 0


public scala.runtime.BoxedArray toArray();
  Code:
   Stack=1, Locals=1, Args_size=1
   0:	aload_0
   1:	invokestatic	#550; //Method scala/collection/generic/TraversableTemplate$class.toArray:(Lscala/collection/generic/TraversableTemplate;)Lscala/runtime/BoxedArray;
   4:	areturn
  LineNumberTable: 
   line 34: 0


public void copyToArray(scala.runtime.BoxedArray, int);
  Code:
   Stack=3, Locals=3, Args_size=3
   0:	aload_0
   1:	aload_1
   2:	iload_2
   3:	invokestatic	#555; //Method scala/collection/generic/TraversableTemplate$class.copyToArray:(Lscala/collection/generic/TraversableTemplate;Lscala/runtime/BoxedArray;I)V
   6:	return
  LineNumberTable: 
   line 34: 0

  LocalVariableTable: 
   Start  Length  Slot  Name   Signature
   0      7      0    this       Lscala/runtime/RichString;
   0      7      1    xs       Lscala/runtime/BoxedArray;
   0      7      2    start       I


public void copyToBuffer(scala.collection.mutable.Buffer);
  Code:
   Stack=2, Locals=2, Args_size=2
   0:	aload_0
   1:	aload_1
   2:	invokestatic	#562; //Method scala/collection/generic/TraversableTemplate$class.copyToBuffer:(Lscala/collection/generic/TraversableTemplate;Lscala/collection/mutable/Buffer;)V
   5:	return
  LineNumberTable: 
   line 34: 0

  LocalVariableTable: 
   Start  Length  Slot  Name   Signature
   0      6      0    this       Lscala/runtime/RichString;
   0      6      1    dest       Lscala/collection/mutable/Buffer;


public scala.Option lastOption();
  Code:
   Stack=1, Locals=1, Args_size=1
   0:	aload_0
   1:	invokestatic	#569; //Method scala/collection/generic/TraversableTemplate$class.lastOption:(Lscala/collection/generic/TraversableTemplate;)Lscala/Option;
   4:	areturn
  LineNumberTable: 
   line 34: 0


public scala.Option headOption();
  Code:
   Stack=1, Locals=1, Args_size=1
   0:	aload_0
   1:	invokestatic	#572; //Method scala/collection/generic/TraversableTemplate$class.headOption:(Lscala/collection/generic/TraversableTemplate;)Lscala/Option;
   4:	areturn
  LineNumberTable: 
   line 34: 0


public scala.Option reduceRightOption(scala.Function2);
  Code:
   Stack=2, Locals=2, Args_size=2
   0:	aload_0
   1:	aload_1
   2:	invokestatic	#577; //Method scala/collection/generic/TraversableTemplate$class.reduceRightOption:(Lscala/collection/generic/TraversableTemplate;Lscala/Function2;)Lscala/Option;
   5:	areturn
  LineNumberTable: 
   line 34: 0

  LocalVariableTable: 
   Start  Length  Slot  Name   Signature
   0      6      0    this       Lscala/runtime/RichString;
   0      6      1    op       Lscala/Function2;


public scala.Option reduceLeftOption(scala.Function2);
  Code:
   Stack=2, Locals=2, Args_size=2
   0:	aload_0
   1:	aload_1
   2:	invokestatic	#582; //Method scala/collection/generic/TraversableTemplate$class.reduceLeftOption:(Lscala/collection/generic/TraversableTemplate;Lscala/Function2;)Lscala/Option;
   5:	areturn
  LineNumberTable: 
   line 34: 0

  LocalVariableTable: 
   Start  Length  Slot  Name   Signature
   0      6      0    this       Lscala/runtime/RichString;
   0      6      1    op       Lscala/Function2;


public java.lang.Object $colon$bslash(java.lang.Object, scala.Function2);
  Code:
   Stack=3, Locals=3, Args_size=3
   0:	aload_0
   1:	aload_1
   2:	aload_2
   3:	invokestatic	#586; //Method scala/collection/generic/TraversableTemplate$class.$colon$bslash:(Lscala/collection/generic/TraversableTemplate;Ljava/lang/Object;Lscala/Function2;)Ljava/lang/Object;
   6:	areturn
  LineNumberTable: 
   line 34: 0

  LocalVariableTable: 
   Start  Length  Slot  Name   Signature
   0      7      0    this       Lscala/runtime/RichString;
   0      7      1    z       Ljava/lang/Object;
   0      7      2    op       Lscala/Function2;


public java.lang.Object $div$colon(java.lang.Object, scala.Function2);
  Code:
   Stack=3, Locals=3, Args_size=3
   0:	aload_0
   1:	aload_1
   2:	aload_2
   3:	invokestatic	#590; //Method scala/collection/generic/TraversableTemplate$class.$div$colon:(Lscala/collection/generic/TraversableTemplate;Ljava/lang/Object;Lscala/Function2;)Ljava/lang/Object;
   6:	areturn
  LineNumberTable: 
   line 34: 0

  LocalVariableTable: 
   Start  Length  Slot  Name   Signature
   0      7      0    this       Lscala/runtime/RichString;
   0      7      1    z       Ljava/lang/Object;
   0      7      2    op       Lscala/Function2;


public int count(scala.Function1);
  Code:
   Stack=2, Locals=2, Args_size=2
   0:	aload_0
   1:	aload_1
   2:	invokestatic	#595; //Method scala/collection/generic/TraversableTemplate$class.count:(Lscala/collection/generic/TraversableTemplate;Lscala/Function1;)I
   5:	ireturn
  LineNumberTable: 
   line 34: 0

  LocalVariableTable: 
   Start  Length  Slot  Name   Signature
   0      6      0    this       Lscala/runtime/RichString;
   0      6      1    p       Lscala/Function1;


public scala.collection.Map groupBy(scala.Function1);
  Code:
   Stack=2, Locals=2, Args_size=2
   0:	aload_0
   1:	aload_1
   2:	invokestatic	#600; //Method scala/collection/generic/TraversableTemplate$class.groupBy:(Lscala/collection/generic/TraversableTemplate;Lscala/Function1;)Lscala/collection/Map;
   5:	areturn
  LineNumberTable: 
   line 34: 0

  LocalVariableTable: 
   Start  Length  Slot  Name   Signature
   0      6      0    this       Lscala/runtime/RichString;
   0      6      1    f       Lscala/Function1;


public scala.Tuple2 partition(scala.Function1);
  Code:
   Stack=2, Locals=2, Args_size=2
   0:	aload_0
   1:	aload_1
   2:	invokestatic	#606; //Method scala/collection/generic/TraversableTemplate$class.partition:(Lscala/collection/generic/TraversableTemplate;Lscala/Function1;)Lscala/Tuple2;
   5:	areturn
  LineNumberTable: 
   line 34: 0

  LocalVariableTable: 
   Start  Length  Slot  Name   Signature
   0      6      0    this       Lscala/runtime/RichString;
   0      6      1    p       Lscala/Function1;


public scala.collection.generic.TraversableTemplate remove(scala.Function1);
  Code:
   Stack=2, Locals=2, Args_size=2
   0:	aload_0
   1:	aload_1
   2:	invokestatic	#610; //Method scala/collection/generic/TraversableTemplate$class.remove:(Lscala/collection/generic/TraversableTemplate;Lscala/Function1;)Lscala/collection/generic/TraversableTemplate;
   5:	areturn
  LineNumberTable: 
   line 34: 0

  LocalVariableTable: 
   Start  Length  Slot  Name   Signature
   0      6      0    this       Lscala/runtime/RichString;
   0      6      1    p       Lscala/Function1;


public scala.collection.generic.TraversableTemplate filterNot(scala.Function1);
  Code:
   Stack=2, Locals=2, Args_size=2
   0:	aload_0
   1:	aload_1
   2:	invokestatic	#613; //Method scala/collection/generic/TraversableTemplate$class.filterNot:(Lscala/collection/generic/TraversableTemplate;Lscala/Function1;)Lscala/collection/generic/TraversableTemplate;
   5:	areturn
  LineNumberTable: 
   line 34: 0

  LocalVariableTable: 
   Start  Length  Slot  Name   Signature
   0      6      0    this       Lscala/runtime/RichString;
   0      6      1    p       Lscala/Function1;


public java.lang.Object filterMap(scala.PartialFunction, scala.collection.generic.BuilderFactory);
  Code:
   Stack=3, Locals=3, Args_size=3
   0:	aload_0
   1:	aload_1
   2:	aload_2
   3:	invokestatic	#618; //Method scala/collection/generic/TraversableTemplate$class.filterMap:(Lscala/collection/generic/TraversableTemplate;Lscala/PartialFunction;Lscala/collection/generic/BuilderFactory;)Ljava/lang/Object;
   6:	areturn
  LineNumberTable: 
   line 34: 0

  LocalVariableTable: 
   Start  Length  Slot  Name   Signature
   0      7      0    this       Lscala/runtime/RichString;
   0      7      1    pf       Lscala/PartialFunction;
   0      7      2    bf       Lscala/collection/generic/BuilderFactory;


public scala.collection.generic.TraversableTemplate filter(scala.Function1);
  Code:
   Stack=2, Locals=2, Args_size=2
   0:	aload_0
   1:	aload_1
   2:	invokestatic	#625; //Method scala/collection/generic/TraversableTemplate$class.filter:(Lscala/collection/generic/TraversableTemplate;Lscala/Function1;)Lscala/collection/generic/TraversableTemplate;
   5:	areturn
  LineNumberTable: 
   line 34: 0

  LocalVariableTable: 
   Start  Length  Slot  Name   Signature
   0      6      0    this       Lscala/runtime/RichString;
   0      6      1    p       Lscala/Function1;


public java.lang.Object flatMap(scala.Function1, scala.collection.generic.BuilderFactory);
  Code:
   Stack=3, Locals=3, Args_size=3
   0:	aload_0
   1:	aload_1
   2:	aload_2
   3:	invokestatic	#630; //Method scala/collection/generic/TraversableTemplate$class.flatMap:(Lscala/collection/generic/TraversableTemplate;Lscala/Function1;Lscala/collection/generic/BuilderFactory;)Ljava/lang/Object;
   6:	areturn
  LineNumberTable: 
   line 34: 0

  LocalVariableTable: 
   Start  Length  Slot  Name   Signature
   0      7      0    this       Lscala/runtime/RichString;
   0      7      1    f       Lscala/Function1;
   0      7      2    bf       Lscala/collection/generic/BuilderFactory;


public java.lang.Object map(scala.Function1, scala.collection.generic.BuilderFactory);
  Code:
   Stack=3, Locals=3, Args_size=3
   0:	aload_0
   1:	aload_1
   2:	aload_2
   3:	invokestatic	#632; //Method scala/collection/generic/TraversableTemplate$class.map:(Lscala/collection/generic/TraversableTemplate;Lscala/Function1;Lscala/collection/generic/BuilderFactory;)Ljava/lang/Object;
   6:	areturn
  LineNumberTable: 
   line 34: 0

  LocalVariableTable: 
   Start  Length  Slot  Name   Signature
   0      7      0    this       Lscala/runtime/RichString;
   0      7      1    f       Lscala/Function1;
   0      7      2    bf       Lscala/collection/generic/BuilderFactory;


public java.lang.Object $plus$plus(scala.collection.Iterator, scala.collection.generic.BuilderFactory);
  Code:
   Stack=3, Locals=3, Args_size=3
   0:	aload_0
   1:	aload_1
   2:	aload_2
   3:	invokestatic	#637; //Method scala/collection/generic/TraversableTemplate$class.$plus$plus:(Lscala/collection/generic/TraversableTemplate;Lscala/collection/Iterator;Lscala/collection/generic/BuilderFactory;)Ljava/lang/Object;
   6:	areturn
  LineNumberTable: 
   line 34: 0

  LocalVariableTable: 
   Start  Length  Slot  Name   Signature
   0      7      0    this       Lscala/runtime/RichString;
   0      7      1    that       Lscala/collection/Iterator;
   0      7      2    bf       Lscala/collection/generic/BuilderFactory;


public java.lang.Object $plus$plus(scala.collection.Traversable, scala.collection.generic.BuilderFactory);
  Code:
   Stack=3, Locals=3, Args_size=3
   0:	aload_0
   1:	aload_1
   2:	aload_2
   3:	invokestatic	#642; //Method scala/collection/generic/TraversableTemplate$class.$plus$plus:(Lscala/collection/generic/TraversableTemplate;Lscala/collection/Traversable;Lscala/collection/generic/BuilderFactory;)Ljava/lang/Object;
   6:	areturn
  LineNumberTable: 
   line 34: 0

  LocalVariableTable: 
   Start  Length  Slot  Name   Signature
   0      7      0    this       Lscala/runtime/RichString;
   0      7      1    that       Lscala/collection/Traversable;
   0      7      2    bf       Lscala/collection/generic/BuilderFactory;


public boolean hasDefiniteSize();
  Code:
   Stack=1, Locals=1, Args_size=1
   0:	aload_0
   1:	invokestatic	#647; //Method scala/collection/generic/TraversableTemplate$class.hasDefiniteSize:(Lscala/collection/generic/TraversableTemplate;)Z
   4:	ireturn
  LineNumberTable: 
   line 34: 0


public boolean nonEmpty();
  Code:
   Stack=1, Locals=1, Args_size=1
   0:	aload_0
   1:	invokestatic	#650; //Method scala/collection/generic/TraversableTemplate$class.nonEmpty:(Lscala/collection/generic/TraversableTemplate;)Z
   4:	ireturn
  LineNumberTable: 
   line 34: 0


public scala.collection.generic.TraversableTemplate thisCollection();
  Code:
   Stack=1, Locals=1, Args_size=1
   0:	aload_0
   1:	invokestatic	#654; //Method scala/collection/generic/TraversableTemplate$class.thisCollection:(Lscala/collection/generic/TraversableTemplate;)Lscala/collection/generic/TraversableTemplate;
   4:	areturn
  LineNumberTable: 
   line 34: 0


public scala.collection.Traversable transpose(scala.Function1);
  Code:
   Stack=2, Locals=2, Args_size=2
   0:	aload_0
   1:	aload_1
   2:	invokestatic	#659; //Method scala/collection/generic/TraversableClass$class.transpose:(Lscala/collection/generic/TraversableClass;Lscala/Function1;)Lscala/collection/Traversable;
   5:	areturn
  LineNumberTable: 
   line 34: 0

  LocalVariableTable: 
   Start  Length  Slot  Name   Signature
   0      6      0    this       Lscala/runtime/RichString;
   0      6      1    toTraversable       Lscala/Function1;


public scala.collection.Traversable flatten(scala.Function1);
  Code:
   Stack=2, Locals=2, Args_size=2
   0:	aload_0
   1:	aload_1
   2:	invokestatic	#663; //Method scala/collection/generic/TraversableClass$class.flatten:(Lscala/collection/generic/TraversableClass;Lscala/Function1;)Lscala/collection/Traversable;
   5:	areturn
  LineNumberTable: 
   line 34: 0

  LocalVariableTable: 
   Start  Length  Slot  Name   Signature
   0      6      0    this       Lscala/runtime/RichString;
   0      6      1    toTraversable       Lscala/Function1;


public scala.Tuple2 unzip(scala.Function1);
  Code:
   Stack=2, Locals=2, Args_size=2
   0:	aload_0
   1:	aload_1
   2:	invokestatic	#667; //Method scala/collection/generic/TraversableClass$class.unzip:(Lscala/collection/generic/TraversableClass;Lscala/Function1;)Lscala/Tuple2;
   5:	areturn
  LineNumberTable: 
   line 34: 0

  LocalVariableTable: 
   Start  Length  Slot  Name   Signature
   0      6      0    this       Lscala/runtime/RichString;
   0      6      1    toPair       Lscala/Function1;


public scala.collection.generic.Builder genericBuilder();
  Code:
   Stack=1, Locals=1, Args_size=1
   0:	aload_0
   1:	invokestatic	#672; //Method scala/collection/generic/TraversableClass$class.genericBuilder:(Lscala/collection/generic/TraversableClass;)Lscala/collection/generic/Builder;
   4:	areturn
  LineNumberTable: 
   line 34: 0


public scala.collection.Sequence toSeq();
  Code:
   Stack=1, Locals=1, Args_size=1
   0:	aload_0
   1:	invokestatic	#677; //Method scala/collection/generic/IterableTemplate$class.toSeq:(Lscala/collection/generic/IterableTemplate;)Lscala/collection/Sequence;
   4:	areturn
  LineNumberTable: 
   line 34: 0


public scala.Option firstOption();
  Code:
   Stack=1, Locals=1, Args_size=1
   0:	aload_0
   1:	invokestatic	#681; //Method scala/collection/generic/IterableTemplate$class.firstOption:(Lscala/collection/generic/IterableTemplate;)Lscala/Option;
   4:	areturn
  LineNumberTable: 
   line 34: 0


public java.lang.Object first();
  Code:
   Stack=1, Locals=1, Args_size=1
   0:	aload_0
   1:	invokestatic	#685; //Method scala/collection/generic/IterableTemplate$class.first:(Lscala/collection/generic/IterableTemplate;)Ljava/lang/Object;
   4:	areturn
  LineNumberTable: 
   line 34: 0


public scala.collection.immutable.Stream toStream();
  Code:
   Stack=1, Locals=1, Args_size=1
   0:	aload_0
   1:	invokestatic	#690; //Method scala/collection/generic/IterableTemplate$class.toStream:(Lscala/collection/generic/IterableTemplate;)Lscala/collection/immutable/Stream;
   4:	areturn
  LineNumberTable: 
   line 34: 0


public scala.collection.Iterable toIterable();
  Code:
   Stack=1, Locals=1, Args_size=1
   0:	aload_0
   1:	invokestatic	#695; //Method scala/collection/generic/IterableTemplate$class.toIterable:(Lscala/collection/generic/IterableTemplate;)Lscala/collection/Iterable;
   4:	areturn
  LineNumberTable: 
   line 34: 0


public scala.collection.Iterator elements();
  Code:
   Stack=1, Locals=1, Args_size=1
   0:	aload_0
   1:	invokestatic	#699; //Method scala/collection/generic/IterableTemplate$class.elements:(Lscala/collection/generic/IterableTemplate;)Lscala/collection/Iterator;
   4:	areturn
  LineNumberTable: 
   line 34: 0


public scala.Function1 compose(scala.Function1);
  Code:
   Stack=2, Locals=2, Args_size=2
   0:	aload_0
   1:	aload_1
   2:	invokestatic	#703; //Method scala/Function1$class.compose:(Lscala/Function1;Lscala/Function1;)Lscala/Function1;
   5:	areturn
  LineNumberTable: 
   line 34: 0

  LocalVariableTable: 
   Start  Length  Slot  Name   Signature
   0      6      0    this       Lscala/runtime/RichString;
   0      6      1    g       Lscala/Function1;


public scala.PartialFunction andThen(scala.Function1);
  Code:
   Stack=2, Locals=2, Args_size=2
   0:	aload_0
   1:	aload_1
   2:	invokestatic	#706; //Method scala/PartialFunction$class.andThen:(Lscala/PartialFunction;Lscala/Function1;)Lscala/PartialFunction;
   5:	areturn
  LineNumberTable: 
   line 34: 0

  LocalVariableTable: 
   Start  Length  Slot  Name   Signature
   0      6      0    this       Lscala/runtime/RichString;
   0      6      1    k       Lscala/Function1;


public scala.PartialFunction orElse(scala.PartialFunction);
  Code:
   Stack=2, Locals=2, Args_size=2
   0:	aload_0
   1:	aload_1
   2:	invokestatic	#712; //Method scala/PartialFunction$class.orElse:(Lscala/PartialFunction;Lscala/PartialFunction;)Lscala/PartialFunction;
   5:	areturn
  LineNumberTable: 
   line 34: 0

  LocalVariableTable: 
   Start  Length  Slot  Name   Signature
   0      6      0    this       Lscala/runtime/RichString;
   0      6      1    that       Lscala/PartialFunction;


public java.lang.Object projection();
  Code:
   Stack=1, Locals=1, Args_size=1
   0:	aload_0
   1:	invokestatic	#716; //Method scala/collection/generic/SequenceTemplate$class.projection:(Lscala/collection/generic/SequenceTemplate;)Ljava/lang/Object;
   4:	areturn
  LineNumberTable: 
   line 34: 0


public boolean containsSlice(scala.collection.Sequence);
  Code:
   Stack=2, Locals=2, Args_size=2
   0:	aload_0
   1:	aload_1
   2:	invokestatic	#721; //Method scala/collection/generic/SequenceTemplate$class.containsSlice:(Lscala/collection/generic/SequenceTemplate;Lscala/collection/Sequence;)Z
   5:	ireturn
  LineNumberTable: 
   line 34: 0

  LocalVariableTable: 
   Start  Length  Slot  Name   Signature
   0      6      0    this       Lscala/runtime/RichString;
   0      6      1    that       Lscala/collection/Sequence;


public boolean equalsWith(scala.collection.Sequence, scala.Function2);
  Code:
   Stack=3, Locals=3, Args_size=3
   0:	aload_0
   1:	aload_1
   2:	aload_2
   3:	invokestatic	#726; //Method scala/collection/generic/SequenceTemplate$class.equalsWith:(Lscala/collection/generic/SequenceTemplate;Lscala/collection/Sequence;Lscala/Function2;)Z
   6:	ireturn
  LineNumberTable: 
   line 34: 0

  LocalVariableTable: 
   Start  Length  Slot  Name   Signature
   0      7      0    this       Lscala/runtime/RichString;
   0      7      1    that       Lscala/collection/Sequence;
   0      7      2    f       Lscala/Function2;


public scala.collection.Sequence slice(int);
  Code:
   Stack=2, Locals=2, Args_size=2
   0:	aload_0
   1:	iload_1
   2:	invokestatic	#730; //Method scala/collection/generic/SequenceTemplate$class.slice:(Lscala/collection/generic/SequenceTemplate;I)Lscala/collection/Sequence;
   5:	areturn
  LineNumberTable: 
   line 34: 0

  LocalVariableTable: 
   Start  Length  Slot  Name   Signature
   0      6      0    this       Lscala/runtime/RichString;
   0      6      1    from       I


public int findLastIndexOf(scala.Function1);
  Code:
   Stack=2, Locals=2, Args_size=2
   0:	aload_0
   1:	aload_1
   2:	invokestatic	#734; //Method scala/collection/generic/SequenceTemplate$class.findLastIndexOf:(Lscala/collection/generic/SequenceTemplate;Lscala/Function1;)I
   5:	ireturn
  LineNumberTable: 
   line 34: 0

  LocalVariableTable: 
   Start  Length  Slot  Name   Signature
   0      6      0    this       Lscala/runtime/RichString;
   0      6      1    p       Lscala/Function1;


public scala.Range indices();
  Code:
   Stack=1, Locals=1, Args_size=1
   0:	aload_0
   1:	invokestatic	#739; //Method scala/collection/generic/SequenceTemplate$class.indices:(Lscala/collection/generic/SequenceTemplate;)Lscala/Range;
   4:	areturn
  LineNumberTable: 
   line 34: 0


public scala.collection.Sequence toSequence();
  Code:
   Stack=1, Locals=1, Args_size=1
   0:	aload_0
   1:	invokestatic	#743; //Method scala/collection/generic/SequenceTemplate$class.toSequence:(Lscala/collection/generic/SequenceTemplate;)Lscala/collection/Sequence;
   4:	areturn
  LineNumberTable: 
   line 34: 0


public java.lang.Object padTo(int, java.lang.Object, scala.collection.generic.BuilderFactory);
  Code:
   Stack=4, Locals=4, Args_size=4
   0:	aload_0
   1:	iload_1
   2:	aload_2
   3:	aload_3
   4:	invokestatic	#748; //Method scala/collection/generic/SequenceTemplate$class.padTo:(Lscala/collection/generic/SequenceTemplate;ILjava/lang/Object;Lscala/collection/generic/BuilderFactory;)Ljava/lang/Object;
   7:	areturn
  LineNumberTable: 
   line 34: 0

  LocalVariableTable: 
   Start  Length  Slot  Name   Signature
   0      8      0    this       Lscala/runtime/RichString;
   0      8      1    len       I
   0      8      2    elem       Ljava/lang/Object;
   0      8      3    bf       Lscala/collection/generic/BuilderFactory;


public java.lang.Object patch(int, scala.collection.Sequence, int, scala.collection.generic.BuilderFactory);
  Code:
   Stack=5, Locals=5, Args_size=5
   0:	aload_0
   1:	iload_1
   2:	aload_2
   3:	iload_3
   4:	aload	4
   6:	invokestatic	#754; //Method scala/collection/generic/SequenceTemplate$class.patch:(Lscala/collection/generic/SequenceTemplate;ILscala/collection/Sequence;ILscala/collection/generic/BuilderFactory;)Ljava/lang/Object;
   9:	areturn
  LineNumberTable: 
   line 34: 0

  LocalVariableTable: 
   Start  Length  Slot  Name   Signature
   0      10      0    this       Lscala/runtime/RichString;
   0      10      1    from       I
   0      10      2    patch       Lscala/collection/Sequence;
   0      10      3    replaced       I
   0      10      4    bf       Lscala/collection/generic/BuilderFactory;


public scala.collection.generic.IterableTemplate removeDuplicates();
  Code:
   Stack=1, Locals=1, Args_size=1
   0:	aload_0
   1:	invokestatic	#759; //Method scala/collection/generic/SequenceTemplate$class.removeDuplicates:(Lscala/collection/generic/SequenceTemplate;)Lscala/collection/generic/IterableTemplate;
   4:	areturn
  LineNumberTable: 
   line 34: 0


public scala.collection.generic.IterableTemplate intersect(scala.collection.Sequence);
  Code:
   Stack=2, Locals=2, Args_size=2
   0:	aload_0
   1:	aload_1
   2:	invokestatic	#764; //Method scala/collection/generic/SequenceTemplate$class.intersect:(Lscala/collection/generic/SequenceTemplate;Lscala/collection/Sequence;)Lscala/collection/generic/IterableTemplate;
   5:	areturn
  LineNumberTable: 
   line 34: 0

  LocalVariableTable: 
   Start  Length  Slot  Name   Signature
   0      6      0    this       Lscala/runtime/RichString;
   0      6      1    that       Lscala/collection/Sequence;


public scala.collection.generic.IterableTemplate diff(scala.collection.Sequence);
  Code:
   Stack=2, Locals=2, Args_size=2
   0:	aload_0
   1:	aload_1
   2:	invokestatic	#767; //Method scala/collection/generic/SequenceTemplate$class.diff:(Lscala/collection/generic/SequenceTemplate;Lscala/collection/Sequence;)Lscala/collection/generic/IterableTemplate;
   5:	areturn
  LineNumberTable: 
   line 34: 0

  LocalVariableTable: 
   Start  Length  Slot  Name   Signature
   0      6      0    this       Lscala/runtime/RichString;
   0      6      1    that       Lscala/collection/Sequence;


public java.lang.Object union(scala.collection.Sequence, scala.collection.generic.BuilderFactory);
  Code:
   Stack=3, Locals=3, Args_size=3
   0:	aload_0
   1:	aload_1
   2:	aload_2
   3:	invokestatic	#772; //Method scala/collection/generic/SequenceTemplate$class.union:(Lscala/collection/generic/SequenceTemplate;Lscala/collection/Sequence;Lscala/collection/generic/BuilderFactory;)Ljava/lang/Object;
   6:	areturn
  LineNumberTable: 
   line 34: 0

  LocalVariableTable: 
   Start  Length  Slot  Name   Signature
   0      7      0    this       Lscala/runtime/RichString;
   0      7      1    that       Lscala/collection/Sequence;
   0      7      2    bf       Lscala/collection/generic/BuilderFactory;


public boolean contains(java.lang.Object);
  Code:
   Stack=2, Locals=2, Args_size=2
   0:	aload_0
   1:	aload_1
   2:	invokestatic	#776; //Method scala/collection/generic/SequenceTemplate$class.contains:(Lscala/collection/generic/SequenceTemplate;Ljava/lang/Object;)Z
   5:	ireturn
  LineNumberTable: 
   line 34: 0

  LocalVariableTable: 
   Start  Length  Slot  Name   Signature
   0      6      0    this       Lscala/runtime/RichString;
   0      6      1    elem       Ljava/lang/Object;


public int lastIndexOfSeq(scala.collection.Sequence, int);
  Code:
   Stack=3, Locals=3, Args_size=3
   0:	aload_0
   1:	aload_1
   2:	iload_2
   3:	invokestatic	#781; //Method scala/collection/generic/SequenceTemplate$class.lastIndexOfSeq:(Lscala/collection/generic/SequenceTemplate;Lscala/collection/Sequence;I)I
   6:	ireturn
  LineNumberTable: 
   line 34: 0

  LocalVariableTable: 
   Start  Length  Slot  Name   Signature
   0      7      0    this       Lscala/runtime/RichString;
   0      7      1    that       Lscala/collection/Sequence;
   0      7      2    fromIndex       I


public int lastIndexOfSeq(scala.collection.Sequence);
  Code:
   Stack=2, Locals=2, Args_size=2
   0:	aload_0
   1:	aload_1
   2:	invokestatic	#786; //Method scala/collection/generic/SequenceTemplate$class.lastIndexOfSeq:(Lscala/collection/generic/SequenceTemplate;Lscala/collection/Sequence;)I
   5:	ireturn
  LineNumberTable: 
   line 34: 0

  LocalVariableTable: 
   Start  Length  Slot  Name   Signature
   0      6      0    this       Lscala/runtime/RichString;
   0      6      1    that       Lscala/collection/Sequence;


public int indexOfSeq(scala.collection.Sequence, int);
  Code:
   Stack=3, Locals=3, Args_size=3
   0:	aload_0
   1:	aload_1
   2:	iload_2
   3:	invokestatic	#789; //Method scala/collection/generic/SequenceTemplate$class.indexOfSeq:(Lscala/collection/generic/SequenceTemplate;Lscala/collection/Sequence;I)I
   6:	ireturn
  LineNumberTable: 
   line 34: 0

  LocalVariableTable: 
   Start  Length  Slot  Name   Signature
   0      7      0    this       Lscala/runtime/RichString;
   0      7      1    that       Lscala/collection/Sequence;
   0      7      2    fromIndex       I


public int indexOfSeq(scala.collection.Sequence);
  Code:
   Stack=2, Locals=2, Args_size=2
   0:	aload_0
   1:	aload_1
   2:	invokestatic	#791; //Method scala/collection/generic/SequenceTemplate$class.indexOfSeq:(Lscala/collection/generic/SequenceTemplate;Lscala/collection/Sequence;)I
   5:	ireturn
  LineNumberTable: 
   line 34: 0

  LocalVariableTable: 
   Start  Length  Slot  Name   Signature
   0      6      0    this       Lscala/runtime/RichString;
   0      6      1    that       Lscala/collection/Sequence;


public boolean startsWith(scala.collection.Sequence);
  Code:
   Stack=2, Locals=2, Args_size=2
   0:	aload_0
   1:	aload_1
   2:	invokestatic	#794; //Method scala/collection/generic/SequenceTemplate$class.startsWith:(Lscala/collection/generic/SequenceTemplate;Lscala/collection/Sequence;)Z
   5:	ireturn
  LineNumberTable: 
   line 34: 0

  LocalVariableTable: 
   Start  Length  Slot  Name   Signature
   0      6      0    this       Lscala/runtime/RichString;
   0      6      1    that       Lscala/collection/Sequence;


public scala.collection.Iterator reversedElements();
  Code:
   Stack=1, Locals=1, Args_size=1
   0:	aload_0
   1:	invokestatic	#798; //Method scala/collection/generic/SequenceTemplate$class.reversedElements:(Lscala/collection/generic/SequenceTemplate;)Lscala/collection/Iterator;
   4:	areturn
  LineNumberTable: 
   line 34: 0


public int lastIndexWhere(scala.Function1);
  Code:
   Stack=2, Locals=2, Args_size=2
   0:	aload_0
   1:	aload_1
   2:	invokestatic	#801; //Method scala/collection/generic/SequenceTemplate$class.lastIndexWhere:(Lscala/collection/generic/SequenceTemplate;Lscala/Function1;)I
   5:	ireturn
  LineNumberTable: 
   line 34: 0

  LocalVariableTable: 
   Start  Length  Slot  Name   Signature
   0      6      0    this       Lscala/runtime/RichString;
   0      6      1    p       Lscala/Function1;


public int lastIndexOf(java.lang.Object, int);
  Code:
   Stack=3, Locals=3, Args_size=3
   0:	aload_0
   1:	aload_1
   2:	iload_2
   3:	invokestatic	#806; //Method scala/collection/generic/SequenceTemplate$class.lastIndexOf:(Lscala/collection/generic/SequenceTemplate;Ljava/lang/Object;I)I
   6:	ireturn
  LineNumberTable: 
   line 34: 0

  LocalVariableTable: 
   Start  Length  Slot  Name   Signature
   0      7      0    this       Lscala/runtime/RichString;
   0      7      1    elem       Ljava/lang/Object;
   0      7      2    end       I


public int lastIndexOf(java.lang.Object);
  Code:
   Stack=2, Locals=2, Args_size=2
   0:	aload_0
   1:	aload_1
   2:	invokestatic	#809; //Method scala/collection/generic/SequenceTemplate$class.lastIndexOf:(Lscala/collection/generic/SequenceTemplate;Ljava/lang/Object;)I
   5:	ireturn
  LineNumberTable: 
   line 34: 0

  LocalVariableTable: 
   Start  Length  Slot  Name   Signature
   0      6      0    this       Lscala/runtime/RichString;
   0      6      1    elem       Ljava/lang/Object;


public int indexOf(java.lang.Object, int);
  Code:
   Stack=3, Locals=3, Args_size=3
   0:	aload_0
   1:	aload_1
   2:	iload_2
   3:	invokestatic	#812; //Method scala/collection/generic/SequenceTemplate$class.indexOf:(Lscala/collection/generic/SequenceTemplate;Ljava/lang/Object;I)I
   6:	ireturn
  LineNumberTable: 
   line 34: 0

  LocalVariableTable: 
   Start  Length  Slot  Name   Signature
   0      7      0    this       Lscala/runtime/RichString;
   0      7      1    elem       Ljava/lang/Object;
   0      7      2    from       I


public int indexOf(java.lang.Object);
  Code:
   Stack=2, Locals=2, Args_size=2
   0:	aload_0
   1:	aload_1
   2:	invokestatic	#814; //Method scala/collection/generic/SequenceTemplate$class.indexOf:(Lscala/collection/generic/SequenceTemplate;Ljava/lang/Object;)I
   5:	ireturn
  LineNumberTable: 
   line 34: 0

  LocalVariableTable: 
   Start  Length  Slot  Name   Signature
   0      6      0    this       Lscala/runtime/RichString;
   0      6      1    elem       Ljava/lang/Object;


public int findIndexOf(scala.Function1);
  Code:
   Stack=2, Locals=2, Args_size=2
   0:	aload_0
   1:	aload_1
   2:	invokestatic	#817; //Method scala/collection/generic/SequenceTemplate$class.findIndexOf:(Lscala/collection/generic/SequenceTemplate;Lscala/Function1;)I
   5:	ireturn
  LineNumberTable: 
   line 34: 0

  LocalVariableTable: 
   Start  Length  Slot  Name   Signature
   0      6      0    this       Lscala/runtime/RichString;
   0      6      1    p       Lscala/Function1;


public int indexWhere(scala.Function1);
  Code:
   Stack=2, Locals=2, Args_size=2
   0:	aload_0
   1:	aload_1
   2:	invokestatic	#820; //Method scala/collection/generic/SequenceTemplate$class.indexWhere:(Lscala/collection/generic/SequenceTemplate;Lscala/Function1;)I
   5:	ireturn
  LineNumberTable: 
   line 34: 0

  LocalVariableTable: 
   Start  Length  Slot  Name   Signature
   0      6      0    this       Lscala/runtime/RichString;
   0      6      1    p       Lscala/Function1;


public int prefixLength(scala.Function1);
  Code:
   Stack=2, Locals=2, Args_size=2
   0:	aload_0
   1:	aload_1
   2:	invokestatic	#823; //Method scala/collection/generic/SequenceTemplate$class.prefixLength:(Lscala/collection/generic/SequenceTemplate;Lscala/Function1;)I
   5:	ireturn
  LineNumberTable: 
   line 34: 0

  LocalVariableTable: 
   Start  Length  Slot  Name   Signature
   0      6      0    this       Lscala/runtime/RichString;
   0      6      1    p       Lscala/Function1;


public java.lang.Object zipAll(scala.collection.Sequence, java.lang.Object, java.lang.Object, scala.collection.generic.BuilderFactory);
  Code:
   Stack=5, Locals=5, Args_size=5
   0:	aload_0
   1:	aload_1
   2:	aload_2
   3:	aload_3
   4:	aload	4
   6:	invokestatic	#828; //Method scala/collection/generic/SequenceTemplate$class.zipAll:(Lscala/collection/generic/SequenceTemplate;Lscala/collection/Sequence;Ljava/lang/Object;Ljava/lang/Object;Lscala/collection/generic/BuilderFactory;)Ljava/lang/Object;
   9:	areturn
  LineNumberTable: 
   line 34: 0

  LocalVariableTable: 
   Start  Length  Slot  Name   Signature
   0      10      0    this       Lscala/runtime/RichString;
   0      10      1    that       Lscala/collection/Sequence;
   0      10      2    thisElem       Ljava/lang/Object;
   0      10      3    thatElem       Ljava/lang/Object;
   0      10      4    bf       Lscala/collection/generic/BuilderFactory;


public boolean isDefinedAt(int);
  Code:
   Stack=2, Locals=2, Args_size=2
   0:	aload_0
   1:	iload_1
   2:	invokestatic	#833; //Method scala/collection/generic/SequenceTemplate$class.isDefinedAt:(Lscala/collection/generic/SequenceTemplate;I)Z
   5:	ireturn
  LineNumberTable: 
   line 34: 0

  LocalVariableTable: 
   Start  Length  Slot  Name   Signature
   0      6      0    this       Lscala/runtime/RichString;
   0      6      1    x       I


public int size();
  Code:
   Stack=1, Locals=1, Args_size=1
   0:	aload_0
   1:	invokestatic	#837; //Method scala/collection/generic/SequenceTemplate$class.size:(Lscala/collection/generic/SequenceTemplate;)I
   4:	ireturn
  LineNumberTable: 
   line 34: 0


public int hashCode();
  Code:
   Stack=1, Locals=1, Args_size=1
   0:	aload_0
   1:	invokestatic	#841; //Method scala/collection/immutable/Sequence$class.hashCode:(Lscala/collection/immutable/Sequence;)I
   4:	ireturn
  LineNumberTable: 
   line 34: 0


public scala.collection.generic.VectorView view(int, int);
  Code:
   Stack=3, Locals=3, Args_size=3
   0:	aload_0
   1:	iload_1
   2:	iload_2
   3:	invokestatic	#844; //Method scala/collection/generic/VectorTemplate$class.view:(Lscala/collection/generic/VectorTemplate;II)Lscala/collection/generic/VectorView;
   6:	areturn
  LineNumberTable: 
   line 34: 0

  LocalVariableTable: 
   Start  Length  Slot  Name   Signature
   0      7      0    this       Lscala/runtime/RichString;
   0      7      1    from       I
   0      7      2    until       I


public java.lang.Object view();
  Code:
   Stack=1, Locals=1, Args_size=1
   0:	aload_0
   1:	invokestatic	#847; //Method scala/collection/generic/VectorTemplate$class.view:(Lscala/collection/generic/VectorTemplate;)Ljava/lang/Object;
   4:	areturn
  LineNumberTable: 
   line 34: 0


public boolean equals(java.lang.Object);
  Code:
   Stack=2, Locals=2, Args_size=2
   0:	aload_0
   1:	aload_1
   2:	invokestatic	#850; //Method scala/collection/generic/VectorTemplate$class.equals:(Lscala/collection/generic/VectorTemplate;Ljava/lang/Object;)Z
   5:	ireturn
  LineNumberTable: 
   line 34: 0

  LocalVariableTable: 
   Start  Length  Slot  Name   Signature
   0      6      0    this       Lscala/runtime/RichString;
   0      6      1    that       Ljava/lang/Object;


public boolean endsWith(scala.collection.Sequence);
  Code:
   Stack=2, Locals=2, Args_size=2
   0:	aload_0
   1:	aload_1
   2:	invokestatic	#854; //Method scala/collection/generic/VectorTemplate$class.endsWith:(Lscala/collection/generic/VectorTemplate;Lscala/collection/Sequence;)Z
   5:	ireturn
  LineNumberTable: 
   line 34: 0

  LocalVariableTable: 
   Start  Length  Slot  Name   Signature
   0      6      0    this       Lscala/runtime/RichString;
   0      6      1    that       Lscala/collection/Sequence;


public boolean startsWith(scala.collection.Sequence, int);
  Code:
   Stack=3, Locals=3, Args_size=3
   0:	aload_0
   1:	aload_1
   2:	iload_2
   3:	invokestatic	#858; //Method scala/collection/generic/VectorTemplate$class.startsWith:(Lscala/collection/generic/VectorTemplate;Lscala/collection/Sequence;I)Z
   6:	ireturn
  LineNumberTable: 
   line 34: 0

  LocalVariableTable: 
   Start  Length  Slot  Name   Signature
   0      7      0    this       Lscala/runtime/RichString;
   0      7      1    that       Lscala/collection/Sequence;
   0      7      2    offset       I


public scala.collection.Iterator reverseIterator();
  Code:
   Stack=1, Locals=1, Args_size=1
   0:	aload_0
   1:	invokestatic	#863; //Method scala/collection/generic/VectorTemplate$class.reverseIterator:(Lscala/collection/generic/VectorTemplate;)Lscala/collection/Iterator;
   4:	areturn
  LineNumberTable: 
   line 34: 0


public scala.collection.generic.VectorTemplate reverse();
  Code:
   Stack=1, Locals=1, Args_size=1
   0:	aload_0
   1:	invokestatic	#866; //Method scala/collection/generic/VectorTemplate$class.reverse:(Lscala/collection/generic/VectorTemplate;)Lscala/collection/generic/VectorTemplate;
   4:	areturn
  LineNumberTable: 
   line 34: 0


public int lastIndexWhere(scala.Function1, int);
  Code:
   Stack=3, Locals=3, Args_size=3
   0:	aload_0
   1:	aload_1
   2:	iload_2
   3:	invokestatic	#870; //Method scala/collection/generic/VectorTemplate$class.lastIndexWhere:(Lscala/collection/generic/VectorTemplate;Lscala/Function1;I)I
   6:	ireturn
  LineNumberTable: 
   line 34: 0

  LocalVariableTable: 
   Start  Length  Slot  Name   Signature
   0      7      0    this       Lscala/runtime/RichString;
   0      7      1    p       Lscala/Function1;
   0      7      2    end       I


public int indexWhere(scala.Function1, int);
  Code:
   Stack=3, Locals=3, Args_size=3
   0:	aload_0
   1:	aload_1
   2:	iload_2
   3:	invokestatic	#872; //Method scala/collection/generic/VectorTemplate$class.indexWhere:(Lscala/collection/generic/VectorTemplate;Lscala/Function1;I)I
   6:	ireturn
  LineNumberTable: 
   line 34: 0

  LocalVariableTable: 
   Start  Length  Slot  Name   Signature
   0      7      0    this       Lscala/runtime/RichString;
   0      7      1    p       Lscala/Function1;
   0      7      2    from       I


public int segmentLength(scala.Function1, int);
  Code:
   Stack=3, Locals=3, Args_size=3
   0:	aload_0
   1:	aload_1
   2:	iload_2
   3:	invokestatic	#875; //Method scala/collection/generic/VectorTemplate$class.segmentLength:(Lscala/collection/generic/VectorTemplate;Lscala/Function1;I)I
   6:	ireturn
  LineNumberTable: 
   line 34: 0

  LocalVariableTable: 
   Start  Length  Slot  Name   Signature
   0      7      0    this       Lscala/runtime/RichString;
   0      7      1    p       Lscala/Function1;
   0      7      2    from       I


public int lengthCompare(int);
  Code:
   Stack=2, Locals=2, Args_size=2
   0:	aload_0
   1:	iload_1
   2:	invokestatic	#880; //Method scala/collection/generic/VectorTemplate$class.lengthCompare:(Lscala/collection/generic/VectorTemplate;I)I
   5:	ireturn
  LineNumberTable: 
   line 34: 0

  LocalVariableTable: 
   Start  Length  Slot  Name   Signature
   0      6      0    this       Lscala/runtime/RichString;
   0      6      1    len       I


public void copyToArray(scala.runtime.BoxedArray, int, int);
  Code:
   Stack=4, Locals=4, Args_size=4
   0:	aload_0
   1:	aload_1
   2:	iload_2
   3:	iload_3
   4:	invokestatic	#884; //Method scala/collection/generic/VectorTemplate$class.copyToArray:(Lscala/collection/generic/VectorTemplate;Lscala/runtime/BoxedArray;II)V
   7:	return
  LineNumberTable: 
   line 34: 0

  LocalVariableTable: 
   Start  Length  Slot  Name   Signature
   0      8      0    this       Lscala/runtime/RichString;
   0      8      1    xs       Lscala/runtime/BoxedArray;
   0      8      2    start       I
   0      8      3    len       I


public boolean sameElements(scala.collection.Iterable);
  Code:
   Stack=2, Locals=2, Args_size=2
   0:	aload_0
   1:	aload_1
   2:	invokestatic	#889; //Method scala/collection/generic/VectorTemplate$class.sameElements:(Lscala/collection/generic/VectorTemplate;Lscala/collection/Iterable;)Z
   5:	ireturn
  LineNumberTable: 
   line 34: 0

  LocalVariableTable: 
   Start  Length  Slot  Name   Signature
   0      6      0    this       Lscala/runtime/RichString;
   0      6      1    that       Lscala/collection/Iterable;


public scala.Tuple2 span(scala.Function1);
  Code:
   Stack=2, Locals=2, Args_size=2
   0:	aload_0
   1:	aload_1
   2:	invokestatic	#894; //Method scala/collection/generic/VectorTemplate$class.span:(Lscala/collection/generic/VectorTemplate;Lscala/Function1;)Lscala/Tuple2;
   5:	areturn
  LineNumberTable: 
   line 34: 0

  LocalVariableTable: 
   Start  Length  Slot  Name   Signature
   0      6      0    this       Lscala/runtime/RichString;
   0      6      1    p       Lscala/Function1;


public scala.collection.generic.VectorTemplate dropWhile(scala.Function1);
  Code:
   Stack=2, Locals=2, Args_size=2
   0:	aload_0
   1:	aload_1
   2:	invokestatic	#897; //Method scala/collection/generic/VectorTemplate$class.dropWhile:(Lscala/collection/generic/VectorTemplate;Lscala/Function1;)Lscala/collection/generic/VectorTemplate;
   5:	areturn
  LineNumberTable: 
   line 34: 0

  LocalVariableTable: 
   Start  Length  Slot  Name   Signature
   0      6      0    this       Lscala/runtime/RichString;
   0      6      1    p       Lscala/Function1;


public scala.collection.generic.VectorTemplate takeWhile(scala.Function1);
  Code:
   Stack=2, Locals=2, Args_size=2
   0:	aload_0
   1:	aload_1
   2:	invokestatic	#899; //Method scala/collection/generic/VectorTemplate$class.takeWhile:(Lscala/collection/generic/VectorTemplate;Lscala/Function1;)Lscala/collection/generic/VectorTemplate;
   5:	areturn
  LineNumberTable: 
   line 34: 0

  LocalVariableTable: 
   Start  Length  Slot  Name   Signature
   0      6      0    this       Lscala/runtime/RichString;
   0      6      1    p       Lscala/Function1;


public scala.Tuple2 splitAt(int);
  Code:
   Stack=2, Locals=2, Args_size=2
   0:	aload_0
   1:	iload_1
   2:	invokestatic	#904; //Method scala/collection/generic/VectorTemplate$class.splitAt:(Lscala/collection/generic/VectorTemplate;I)Lscala/Tuple2;
   5:	areturn
  LineNumberTable: 
   line 34: 0

  LocalVariableTable: 
   Start  Length  Slot  Name   Signature
   0      6      0    this       Lscala/runtime/RichString;
   0      6      1    n       I


public scala.collection.generic.VectorTemplate dropRight(int);
  Code:
   Stack=2, Locals=2, Args_size=2
   0:	aload_0
   1:	iload_1
   2:	invokestatic	#907; //Method scala/collection/generic/VectorTemplate$class.dropRight:(Lscala/collection/generic/VectorTemplate;I)Lscala/collection/generic/VectorTemplate;
   5:	areturn
  LineNumberTable: 
   line 34: 0

  LocalVariableTable: 
   Start  Length  Slot  Name   Signature
   0      6      0    this       Lscala/runtime/RichString;
   0      6      1    n       I


public scala.collection.generic.VectorTemplate takeRight(int);
  Code:
   Stack=2, Locals=2, Args_size=2
   0:	aload_0
   1:	iload_1
   2:	invokestatic	#909; //Method scala/collection/generic/VectorTemplate$class.takeRight:(Lscala/collection/generic/VectorTemplate;I)Lscala/collection/generic/VectorTemplate;
   5:	areturn
  LineNumberTable: 
   line 34: 0

  LocalVariableTable: 
   Start  Length  Slot  Name   Signature
   0      6      0    this       Lscala/runtime/RichString;
   0      6      1    n       I


public scala.collection.generic.VectorTemplate drop(int);
  Code:
   Stack=2, Locals=2, Args_size=2
   0:	aload_0
   1:	iload_1
   2:	invokestatic	#911; //Method scala/collection/generic/VectorTemplate$class.drop:(Lscala/collection/generic/VectorTemplate;I)Lscala/collection/generic/VectorTemplate;
   5:	areturn
  LineNumberTable: 
   line 34: 0

  LocalVariableTable: 
   Start  Length  Slot  Name   Signature
   0      6      0    this       Lscala/runtime/RichString;
   0      6      1    n       I


public scala.collection.generic.VectorTemplate take(int);
  Code:
   Stack=2, Locals=2, Args_size=2
   0:	aload_0
   1:	iload_1
   2:	invokestatic	#913; //Method scala/collection/generic/VectorTemplate$class.take:(Lscala/collection/generic/VectorTemplate;I)Lscala/collection/generic/VectorTemplate;
   5:	areturn
  LineNumberTable: 
   line 34: 0

  LocalVariableTable: 
   Start  Length  Slot  Name   Signature
   0      6      0    this       Lscala/runtime/RichString;
   0      6      1    n       I


public scala.collection.generic.VectorTemplate init();
  Code:
   Stack=1, Locals=1, Args_size=1
   0:	aload_0
   1:	invokestatic	#915; //Method scala/collection/generic/VectorTemplate$class.init:(Lscala/collection/generic/VectorTemplate;)Lscala/collection/generic/VectorTemplate;
   4:	areturn
  LineNumberTable: 
   line 34: 0


public java.lang.Object last();
  Code:
   Stack=1, Locals=1, Args_size=1
   0:	aload_0
   1:	invokestatic	#917; //Method scala/collection/generic/VectorTemplate$class.last:(Lscala/collection/generic/VectorTemplate;)Ljava/lang/Object;
   4:	areturn
  LineNumberTable: 
   line 34: 0


public scala.collection.generic.VectorTemplate tail();
  Code:
   Stack=1, Locals=1, Args_size=1
   0:	aload_0
   1:	invokestatic	#919; //Method scala/collection/generic/VectorTemplate$class.tail:(Lscala/collection/generic/VectorTemplate;)Lscala/collection/generic/VectorTemplate;
   4:	areturn
  LineNumberTable: 
   line 34: 0


public java.lang.Object head();
  Code:
   Stack=1, Locals=1, Args_size=1
   0:	aload_0
   1:	invokestatic	#922; //Method scala/collection/generic/VectorTemplate$class.head:(Lscala/collection/generic/VectorTemplate;)Ljava/lang/Object;
   4:	areturn
  LineNumberTable: 
   line 34: 0


public scala.collection.generic.VectorTemplate slice(int, int);
  Code:
   Stack=3, Locals=3, Args_size=3
   0:	aload_0
   1:	iload_1
   2:	iload_2
   3:	invokestatic	#925; //Method scala/collection/generic/VectorTemplate$class.slice:(Lscala/collection/generic/VectorTemplate;II)Lscala/collection/generic/VectorTemplate;
   6:	areturn
  LineNumberTable: 
   line 34: 0

  LocalVariableTable: 
   Start  Length  Slot  Name   Signature
   0      7      0    this       Lscala/runtime/RichString;
   0      7      1    from       I
   0      7      2    until       I


public java.lang.Object zipWithIndex(scala.collection.generic.BuilderFactory);
  Code:
   Stack=2, Locals=2, Args_size=2
   0:	aload_0
   1:	aload_1
   2:	invokestatic	#930; //Method scala/collection/generic/VectorTemplate$class.zipWithIndex:(Lscala/collection/generic/VectorTemplate;Lscala/collection/generic/BuilderFactory;)Ljava/lang/Object;
   5:	areturn
  LineNumberTable: 
   line 34: 0

  LocalVariableTable: 
   Start  Length  Slot  Name   Signature
   0      6      0    this       Lscala/runtime/RichString;
   0      6      1    bf       Lscala/collection/generic/BuilderFactory;


public java.lang.Object zip(scala.collection.Sequence, scala.collection.generic.BuilderFactory);
  Code:
   Stack=3, Locals=3, Args_size=3
   0:	aload_0
   1:	aload_1
   2:	aload_2
   3:	invokestatic	#934; //Method scala/collection/generic/VectorTemplate$class.zip:(Lscala/collection/generic/VectorTemplate;Lscala/collection/Sequence;Lscala/collection/generic/BuilderFactory;)Ljava/lang/Object;
   6:	areturn
  LineNumberTable: 
   line 34: 0

  LocalVariableTable: 
   Start  Length  Slot  Name   Signature
   0      7      0    this       Lscala/runtime/RichString;
   0      7      1    that       Lscala/collection/Sequence;
   0      7      2    bf       Lscala/collection/generic/BuilderFactory;


public java.lang.Object reduceRight(scala.Function2);
  Code:
   Stack=2, Locals=2, Args_size=2
   0:	aload_0
   1:	aload_1
   2:	invokestatic	#939; //Method scala/collection/generic/VectorTemplate$class.reduceRight:(Lscala/collection/generic/VectorTemplate;Lscala/Function2;)Ljava/lang/Object;
   5:	areturn
  LineNumberTable: 
   line 34: 0

  LocalVariableTable: 
   Start  Length  Slot  Name   Signature
   0      6      0    this       Lscala/runtime/RichString;
   0      6      1    op       Lscala/Function2;


public java.lang.Object reduceLeft(scala.Function2);
  Code:
   Stack=2, Locals=2, Args_size=2
   0:	aload_0
   1:	aload_1
   2:	invokestatic	#942; //Method scala/collection/generic/VectorTemplate$class.reduceLeft:(Lscala/collection/generic/VectorTemplate;Lscala/Function2;)Ljava/lang/Object;
   5:	areturn
  LineNumberTable: 
   line 34: 0

  LocalVariableTable: 
   Start  Length  Slot  Name   Signature
   0      6      0    this       Lscala/runtime/RichString;
   0      6      1    op       Lscala/Function2;


public java.lang.Object foldRight(java.lang.Object, scala.Function2);
  Code:
   Stack=3, Locals=3, Args_size=3
   0:	aload_0
   1:	aload_1
   2:	aload_2
   3:	invokestatic	#946; //Method scala/collection/generic/VectorTemplate$class.foldRight:(Lscala/collection/generic/VectorTemplate;Ljava/lang/Object;Lscala/Function2;)Ljava/lang/Object;
   6:	areturn
  LineNumberTable: 
   line 34: 0

  LocalVariableTable: 
   Start  Length  Slot  Name   Signature
   0      7      0    this       Lscala/runtime/RichString;
   0      7      1    z       Ljava/lang/Object;
   0      7      2    op       Lscala/Function2;


public java.lang.Object foldLeft(java.lang.Object, scala.Function2);
  Code:
   Stack=3, Locals=3, Args_size=3
   0:	aload_0
   1:	aload_1
   2:	aload_2
   3:	invokestatic	#948; //Method scala/collection/generic/VectorTemplate$class.foldLeft:(Lscala/collection/generic/VectorTemplate;Ljava/lang/Object;Lscala/Function2;)Ljava/lang/Object;
   6:	areturn
  LineNumberTable: 
   line 34: 0

  LocalVariableTable: 
   Start  Length  Slot  Name   Signature
   0      7      0    this       Lscala/runtime/RichString;
   0      7      1    z       Ljava/lang/Object;
   0      7      2    op       Lscala/Function2;


public scala.Option find(scala.Function1);
  Code:
   Stack=2, Locals=2, Args_size=2
   0:	aload_0
   1:	aload_1
   2:	invokestatic	#953; //Method scala/collection/generic/VectorTemplate$class.find:(Lscala/collection/generic/VectorTemplate;Lscala/Function1;)Lscala/Option;
   5:	areturn
  LineNumberTable: 
   line 34: 0

  LocalVariableTable: 
   Start  Length  Slot  Name   Signature
   0      6      0    this       Lscala/runtime/RichString;
   0      6      1    p       Lscala/Function1;


public boolean exists(scala.Function1);
  Code:
   Stack=2, Locals=2, Args_size=2
   0:	aload_0
   1:	aload_1
   2:	invokestatic	#958; //Method scala/collection/generic/VectorTemplate$class.exists:(Lscala/collection/generic/VectorTemplate;Lscala/Function1;)Z
   5:	ireturn
  LineNumberTable: 
   line 34: 0

  LocalVariableTable: 
   Start  Length  Slot  Name   Signature
   0      6      0    this       Lscala/runtime/RichString;
   0      6      1    p       Lscala/Function1;


public boolean forall(scala.Function1);
  Code:
   Stack=2, Locals=2, Args_size=2
   0:	aload_0
   1:	aload_1
   2:	invokestatic	#961; //Method scala/collection/generic/VectorTemplate$class.forall:(Lscala/collection/generic/VectorTemplate;Lscala/Function1;)Z
   5:	ireturn
  LineNumberTable: 
   line 34: 0

  LocalVariableTable: 
   Start  Length  Slot  Name   Signature
   0      6      0    this       Lscala/runtime/RichString;
   0      6      1    p       Lscala/Function1;


public void foreach(scala.Function1);
  Code:
   Stack=2, Locals=2, Args_size=2
   0:	aload_0
   1:	aload_1
   2:	invokestatic	#964; //Method scala/collection/generic/VectorTemplate$class.foreach:(Lscala/collection/generic/VectorTemplate;Lscala/Function1;)V
   5:	return
  LineNumberTable: 
   line 34: 0

  LocalVariableTable: 
   Start  Length  Slot  Name   Signature
   0      6      0    this       Lscala/runtime/RichString;
   0      6      1    f       Lscala/Function1;


public boolean isEmpty();
  Code:
   Stack=1, Locals=1, Args_size=1
   0:	aload_0
   1:	invokestatic	#968; //Method scala/collection/generic/VectorTemplate$class.isEmpty:(Lscala/collection/generic/VectorTemplate;)Z
   4:	ireturn
  LineNumberTable: 
   line 34: 0


public scala.collection.Iterator iterator();
  Code:
   Stack=1, Locals=1, Args_size=1
   0:	aload_0
   1:	invokestatic	#971; //Method scala/collection/generic/VectorTemplate$class.iterator:(Lscala/collection/generic/VectorTemplate;)Lscala/collection/Iterator;
   4:	areturn
  LineNumberTable: 
   line 34: 0


public final boolean scala$collection$generic$VectorTemplate$$super$equals(java.lang.Object);
  Code:
   Stack=2, Locals=2, Args_size=2
   0:	aload_0
   1:	aload_1
   2:	invokestatic	#974; //Method scala/collection/generic/SequenceTemplate$class.equals:(Lscala/collection/generic/SequenceTemplate;Ljava/lang/Object;)Z
   5:	ireturn
  LineNumberTable: 
   line 34: 0

  LocalVariableTable: 
   Start  Length  Slot  Name   Signature
   0      6      0    this       Lscala/runtime/RichString;
   0      6      1    that       Ljava/lang/Object;


public final boolean scala$collection$generic$VectorTemplate$$super$endsWith(scala.collection.Sequence);
  Code:
   Stack=2, Locals=2, Args_size=2
   0:	aload_0
   1:	aload_1
   2:	invokestatic	#977; //Method scala/collection/generic/SequenceTemplate$class.endsWith:(Lscala/collection/generic/SequenceTemplate;Lscala/collection/Sequence;)Z
   5:	ireturn
  LineNumberTable: 
   line 34: 0

  LocalVariableTable: 
   Start  Length  Slot  Name   Signature
   0      6      0    this       Lscala/runtime/RichString;
   0      6      1    that       Lscala/collection/Sequence;


public final boolean scala$collection$generic$VectorTemplate$$super$sameElements(scala.collection.Iterable);
  Code:
   Stack=2, Locals=2, Args_size=2
   0:	aload_0
   1:	aload_1
   2:	invokestatic	#981; //Method scala/collection/generic/IterableTemplate$class.sameElements:(Lscala/collection/generic/IterableTemplate;Lscala/collection/Iterable;)Z
   5:	ireturn
  LineNumberTable: 
   line 34: 0

  LocalVariableTable: 
   Start  Length  Slot  Name   Signature
   0      6      0    this       Lscala/runtime/RichString;
   0      6      1    that       Lscala/collection/Iterable;


public final scala.collection.generic.VectorTemplate scala$collection$generic$VectorTemplate$$super$init();
  Code:
   Stack=1, Locals=1, Args_size=1
   0:	aload_0
   1:	invokestatic	#984; //Method scala/collection/generic/TraversableTemplate$class.init:(Lscala/collection/generic/TraversableTemplate;)Lscala/collection/generic/TraversableTemplate;
   4:	checkcast	#141; //class scala/collection/generic/VectorTemplate
   7:	areturn
  LineNumberTable: 
   line 34: 0


public final java.lang.Object scala$collection$generic$VectorTemplate$$super$last();
  Code:
   Stack=1, Locals=1, Args_size=1
   0:	aload_0
   1:	invokestatic	#988; //Method scala/collection/generic/TraversableTemplate$class.last:(Lscala/collection/generic/TraversableTemplate;)Ljava/lang/Object;
   4:	areturn
  LineNumberTable: 
   line 34: 0


public final java.lang.Object scala$collection$generic$VectorTemplate$$super$head();
  Code:
   Stack=1, Locals=1, Args_size=1
   0:	aload_0
   1:	invokestatic	#991; //Method scala/collection/generic/IterableTemplate$class.head:(Lscala/collection/generic/IterableTemplate;)Ljava/lang/Object;
   4:	areturn
  LineNumberTable: 
   line 34: 0


public final java.lang.Object scala$collection$generic$VectorTemplate$$super$zip(scala.collection.Sequence, scala.collection.generic.BuilderFactory);
  Code:
   Stack=3, Locals=3, Args_size=3
   0:	aload_0
   1:	aload_1
   2:	aload_2
   3:	invokestatic	#994; //Method scala/collection/generic/SequenceTemplate$class.zip:(Lscala/collection/generic/SequenceTemplate;Lscala/collection/Sequence;Lscala/collection/generic/BuilderFactory;)Ljava/lang/Object;
   6:	areturn
  LineNumberTable: 
   line 34: 0

  LocalVariableTable: 
   Start  Length  Slot  Name   Signature
   0      7      0    this       Lscala/runtime/RichString;
   0      7      1    that       Lscala/collection/Sequence;
   0      7      2    bf       Lscala/collection/generic/BuilderFactory;


public final java.lang.Object scala$collection$generic$VectorTemplate$$super$reduceRight(scala.Function2);
  Code:
   Stack=2, Locals=2, Args_size=2
   0:	aload_0
   1:	aload_1
   2:	invokestatic	#998; //Method scala/collection/generic/IterableTemplate$class.reduceRight:(Lscala/collection/generic/IterableTemplate;Lscala/Function2;)Ljava/lang/Object;
   5:	areturn
  LineNumberTable: 
   line 34: 0

  LocalVariableTable: 
   Start  Length  Slot  Name   Signature
   0      6      0    this       Lscala/runtime/RichString;
   0      6      1    op       Lscala/Function2;


public final java.lang.Object scala$collection$generic$VectorTemplate$$super$reduceLeft(scala.Function2);
  Code:
   Stack=2, Locals=2, Args_size=2
   0:	aload_0
   1:	aload_1
   2:	invokestatic	#1002; //Method scala/collection/generic/TraversableTemplate$class.reduceLeft:(Lscala/collection/generic/TraversableTemplate;Lscala/Function2;)Ljava/lang/Object;
   5:	areturn
  LineNumberTable: 
   line 34: 0

  LocalVariableTable: 
   Start  Length  Slot  Name   Signature
   0      6      0    this       Lscala/runtime/RichString;
   0      6      1    op       Lscala/Function2;


public scala.collection.generic.Companion companion();
  Code:
   Stack=1, Locals=1, Args_size=1
   0:	aload_0
   1:	invokestatic	#1007; //Method scala/collection/immutable/Vector$class.companion:(Lscala/collection/immutable/Vector;)Lscala/collection/generic/Companion;
   4:	areturn
  LineNumberTable: 
   line 34: 0


public int compareTo(java.lang.Object);
  Code:
   Stack=2, Locals=2, Args_size=2
   0:	aload_0
   1:	aload_1
   2:	invokestatic	#1010; //Method scala/Ordered$class.compareTo:(Lscala/Ordered;Ljava/lang/Object;)I
   5:	ireturn
  LineNumberTable: 
   line 34: 0

  LocalVariableTable: 
   Start  Length  Slot  Name   Signature
   0      6      0    this       Lscala/runtime/RichString;
   0      6      1    that       Ljava/lang/Object;


public boolean $greater$eq(java.lang.Object);
  Code:
   Stack=2, Locals=2, Args_size=2
   0:	aload_0
   1:	aload_1
   2:	invokestatic	#1014; //Method scala/Ordered$class.$greater$eq:(Lscala/Ordered;Ljava/lang/Object;)Z
   5:	ireturn
  LineNumberTable: 
   line 34: 0

  LocalVariableTable: 
   Start  Length  Slot  Name   Signature
   0      6      0    this       Lscala/runtime/RichString;
   0      6      1    that       Ljava/lang/Object;


public boolean $less$eq(java.lang.Object);
  Code:
   Stack=2, Locals=2, Args_size=2
   0:	aload_0
   1:	aload_1
   2:	invokestatic	#1017; //Method scala/Ordered$class.$less$eq:(Lscala/Ordered;Ljava/lang/Object;)Z
   5:	ireturn
  LineNumberTable: 
   line 34: 0

  LocalVariableTable: 
   Start  Length  Slot  Name   Signature
   0      6      0    this       Lscala/runtime/RichString;
   0      6      1    that       Ljava/lang/Object;


public boolean $greater(java.lang.Object);
  Code:
   Stack=2, Locals=2, Args_size=2
   0:	aload_0
   1:	aload_1
   2:	invokestatic	#1020; //Method scala/Ordered$class.$greater:(Lscala/Ordered;Ljava/lang/Object;)Z
   5:	ireturn
  LineNumberTable: 
   line 34: 0

  LocalVariableTable: 
   Start  Length  Slot  Name   Signature
   0      6      0    this       Lscala/runtime/RichString;
   0      6      1    that       Ljava/lang/Object;


public boolean $less(java.lang.Object);
  Code:
   Stack=2, Locals=2, Args_size=2
   0:	aload_0
   1:	aload_1
   2:	invokestatic	#1023; //Method scala/Ordered$class.$less:(Lscala/Ordered;Ljava/lang/Object;)Z
   5:	ireturn
  LineNumberTable: 
   line 34: 0

  LocalVariableTable: 
   Start  Length  Slot  Name   Signature
   0      6      0    this       Lscala/runtime/RichString;
   0      6      1    that       Ljava/lang/Object;


}

