Compiled from "RichException.scala"
public final class scala.runtime.RichException extends java.lang.Object implements scala.ScalaObject
  SourceFile: "RichException.scala"
  ScalaSig: length = 0xFE
   05 00 29 06 08 01 02 FFFFFF84 FFFFFF80 FFFFFF80 FFFFFF80 02 07 02 0D 52
   69 63 68 45 78 63 65 70 74 69 6F 6E 0A 02 03 04
   01 07 72 75 6E 74 69 6D 65 0A 01 05 01 05 73 63
   61 6C 61 03 00 13 03 00 08 10 10 02 09 0E 0D 01
   0A 0A 02 0B 0C 01 04 6C 61 6E 67 0A 01 0D 01 04
   6A 61 76 61 09 02 0F 0A 02 06 4F 62 6A 65 63 74
   10 02 11 12 0D 01 04 09 02 13 04 02 0B 53 63 61
   6C 61 4F 62 6A 65 63 74 08 08 15 00 FFFFFF82 FFFFFF80 FFFFFFA0 FFFFFF80
   04 16 01 03 65 78 63 10 02 17 1A 0E 02 11 18 09
   02 19 04 01 06 50 72 65 64 65 66 09 02 1B 1C 02
   09 54 68 72 6F 77 61 62 6C 65 0A 02 19 04 08 05
   1E 00 FFFFFF84 00 1F 01 06 3C 69 6E 69 74 3E 14 02 20
   22 10 02 21 00 0D 01 02 08 05 15 1D FFFFFFC0 00 16 08
   05 24 00 FFFFFF84 00 25 01 13 67 65 74 53 74 61 63 6B
   54 72 61 63 65 53 74 72 69 6E 67 15 01 26 10 02
   17 27 09 02 28 1C 02 06 53 74 72 69 6E 67 
  InnerClass: 
   public final #60= #43 of #10; //$anonfun$getStackTraceString$1=class scala/runtime/RichException$$anonfun$getStackTraceString$1 of class scala/runtime/RichException
  minor version: 0
  major version: 49
  Constant pool:
const #1 = Asciz	SourceFile;
const #2 = Asciz	RichException.scala;
const #3 = Asciz	exc;
const #4 = Asciz	Ljava/lang/Throwable;;
const #5 = Asciz	<init>;
const #6 = Asciz	(Ljava/lang/Throwable;)V;
const #7 = Asciz	Code;
const #8 = Asciz	LineNumberTable;
const #9 = Asciz	scala/runtime/RichException;
const #10 = class	#9;	//  scala/runtime/RichException
const #11 = NameAndType	#3:#4;//  exc:Ljava/lang/Throwable;
const #12 = Field	#10.#11;	//  scala/runtime/RichException.exc:Ljava/lang/Throwable;
const #13 = Asciz	java/lang/Object;
const #14 = class	#13;	//  java/lang/Object
const #15 = Asciz	()V;
const #16 = NameAndType	#5:#15;//  "<init>":()V
const #17 = Method	#14.#16;	//  java/lang/Object."<init>":()V
const #18 = Asciz	this;
const #19 = Asciz	Lscala/runtime/RichException;;
const #20 = Asciz	LocalVariableTable;
const #21 = Asciz	getStackTraceString;
const #22 = Asciz	()Ljava/lang/String;;
const #23 = Asciz	scala/collection/mutable/StringBuilder;
const #24 = class	#23;	//  scala/collection/mutable/StringBuilder
const #25 = Method	#24.#16;	//  scala/collection/mutable/StringBuilder."<init>":()V
const #26 = Asciz	scala/runtime/ScalaRunTime$;
const #27 = class	#26;	//  scala/runtime/ScalaRunTime$
const #28 = Asciz	MODULE$;
const #29 = Asciz	Lscala/runtime/ScalaRunTime$;;
const #30 = NameAndType	#28:#29;//  MODULE$:Lscala/runtime/ScalaRunTime$;
const #31 = Field	#27.#30;	//  scala/runtime/ScalaRunTime$.MODULE$:Lscala/runtime/ScalaRunTime$;
const #32 = Asciz	java/lang/Throwable;
const #33 = class	#32;	//  java/lang/Throwable
const #34 = Asciz	getStackTrace;
const #35 = Asciz	()[Ljava/lang/StackTraceElement;;
const #36 = NameAndType	#34:#35;//  getStackTrace:()[Ljava/lang/StackTraceElement;
const #37 = Method	#33.#36;	//  java/lang/Throwable.getStackTrace:()[Ljava/lang/StackTraceElement;
const #38 = Asciz	boxArray;
const #39 = Asciz	(Ljava/lang/Object;)Lscala/runtime/BoxedArray;;
const #40 = NameAndType	#38:#39;//  boxArray:(Ljava/lang/Object;)Lscala/runtime/BoxedArray;
const #41 = Method	#27.#40;	//  scala/runtime/ScalaRunTime$.boxArray:(Ljava/lang/Object;)Lscala/runtime/BoxedArray;
const #42 = Asciz	scala/runtime/RichException$$anonfun$getStackTraceString$1;
const #43 = class	#42;	//  scala/runtime/RichException$$anonfun$getStackTraceString$1
const #44 = Asciz	(Lscala/runtime/RichException;Lscala/collection/mutable/StringBuilder;)V;
const #45 = NameAndType	#5:#44;//  "<init>":(Lscala/runtime/RichException;Lscala/collection/mutable/StringBuilder;)V
const #46 = Method	#43.#45;	//  scala/runtime/RichException$$anonfun$getStackTraceString$1."<init>":(Lscala/runtime/RichException;Lscala/collection/mutable/StringBuilder;)V
const #47 = Asciz	scala/collection/generic/VectorTemplate;
const #48 = class	#47;	//  scala/collection/generic/VectorTemplate
const #49 = Asciz	foreach;
const #50 = Asciz	(Lscala/Function1;)V;
const #51 = NameAndType	#49:#50;//  foreach:(Lscala/Function1;)V
const #52 = InterfaceMethod	#48.#51;	//  scala/collection/generic/VectorTemplate.foreach:(Lscala/Function1;)V
const #53 = Asciz	toString;
const #54 = NameAndType	#53:#22;//  toString:()Ljava/lang/String;
const #55 = Method	#24.#54;	//  scala/collection/mutable/StringBuilder.toString:()Ljava/lang/String;
const #56 = Asciz	s$1;
const #57 = Asciz	Lscala/collection/mutable/StringBuilder;;
const #58 = Asciz	ScalaSig;
const #59 = Asciz	InnerClasses;
const #60 = Asciz	$anonfun$getStackTraceString$1;
const #61 = Asciz	scala/ScalaObject;
const #62 = class	#61;	//  scala/ScalaObject

{
public scala.runtime.RichException(java.lang.Throwable);
  Code:
   Stack=2, Locals=2, Args_size=2
   0:	aload_0
   1:	aload_1
   2:	putfield	#12; //Field exc:Ljava/lang/Throwable;
   5:	aload_0
   6:	invokespecial	#17; //Method java/lang/Object."<init>":()V
   9:	return
  LineNumberTable: 
   line 17: 0

  LocalVariableTable: 
   Start  Length  Slot  Name   Signature
   0      10      0    this       Lscala/runtime/RichException;
   0      10      1    exc       Ljava/lang/Throwable;


public java.lang.String getStackTraceString();
  Code:
   Stack=5, Locals=2, Args_size=1
   0:	new	#24; //class scala/collection/mutable/StringBuilder
   3:	dup
   4:	invokespecial	#25; //Method scala/collection/mutable/StringBuilder."<init>":()V
   7:	astore_1
   8:	getstatic	#31; //Field scala/runtime/ScalaRunTime$.MODULE$:Lscala/runtime/ScalaRunTime$;
   11:	aload_0
   12:	getfield	#12; //Field exc:Ljava/lang/Throwable;
   15:	invokevirtual	#37; //Method java/lang/Throwable.getStackTrace:()[Ljava/lang/StackTraceElement;
   18:	invokevirtual	#41; //Method scala/runtime/ScalaRunTime$.boxArray:(Ljava/lang/Object;)Lscala/runtime/BoxedArray;
   21:	new	#43; //class scala/runtime/RichException$$anonfun$getStackTraceString$1
   24:	dup
   25:	aload_0
   26:	aload_1
   27:	invokespecial	#46; //Method scala/runtime/RichException$$anonfun$getStackTraceString$1."<init>":(Lscala/runtime/RichException;Lscala/collection/mutable/StringBuilder;)V
   30:	invokeinterface	#52,  2; //InterfaceMethod scala/collection/generic/VectorTemplate.foreach:(Lscala/Function1;)V
   35:	aload_1
   36:	invokevirtual	#55; //Method scala/collection/mutable/StringBuilder.toString:()Ljava/lang/String;
   39:	areturn
  LineNumberTable: 
   line 20: 0
   line 21: 8
   line 25: 35

  LocalVariableTable: 
   Start  Length  Slot  Name   Signature
   0      40      0    this       Lscala/runtime/RichException;
   8      31      1    s$1       Lscala/collection/mutable/StringBuilder;


}

