Compiled from "RichDouble.scala"
public final class scala.runtime.RichDouble$$anonfun$until$1 extends java.lang.Object implements scala.Function1,scala.ScalaObject,java.io.Serializable
  SourceFile: "RichDouble.scala"
  Scala: length = 0x
   
  InnerClass: 
   public final $anonfun$until$1=class scala/runtime/RichDouble$$anonfun$until$1 of class scala/runtime/RichDouble
  minor version: 0
  major version: 49
  Constant pool:
Asciz	SourceFile;
Asciz	RichDouble.scala;
Asciz	<clinit>;
Asciz	()V;
Asciz	Code;
Asciz	serialVersionUID;
Asciz	J;
Asciz	scala/runtime/RichDouble$$anonfun$until$1;
class	scala/runtime/RichDouble$$anonfun$until$1
NameAndType	serialVersionUID:J
Field	scala/runtime/RichDouble$$anonfun$until$1.serialVersionUID:J
Asciz	end$1;
Asciz	D;
Asciz	$outer;
Asciz	Lscala/runtime/RichDouble;;
Asciz	<init>;
Asciz	(Lscala/runtime/RichDouble;D)V;
Asciz	LineNumberTable;
Asciz	java/lang/NullPointerException;
class	java/lang/NullPointerException
NameAndType	"<init>":()V
Method	java/lang/NullPointerException."<init>":()V
NameAndType	$outer:Lscala/runtime/RichDouble;
Field	scala/runtime/RichDouble$$anonfun$until$1.$outer:Lscala/runtime/RichDouble;
NameAndType	end$1:D
Field	scala/runtime/RichDouble$$anonfun$until$1.end$1:D
Asciz	java/lang/Object;
class	java/lang/Object
Method	java/lang/Object."<init>":()V
Asciz	scala/Function1$class;
class	scala/Function1$class
Asciz	$init$;
Asciz	(Lscala/Function1;)V;
NameAndType	$init$:(Lscala/Function1;)V
Method	scala/Function1$class.$init$:(Lscala/Function1;)V
Asciz	this;
Asciz	Lscala/runtime/RichDouble$$anonfun$until$1;;
Asciz	LocalVariableTable;
Asciz	apply;
Asciz	(Ljava/lang/Object;)Ljava/lang/Object;;
Asciz	scala/runtime/BoxesRunTime;
class	scala/runtime/BoxesRunTime
Asciz	unboxToDouble;
Asciz	(Ljava/lang/Object;)D;
NameAndType	unboxToDouble:(Ljava/lang/Object;)D
Method	scala/runtime/BoxesRunTime.unboxToDouble:(Ljava/lang/Object;)D
Asciz	(D)Lscala/collection/immutable/NumericRange;;
NameAndType	apply:(D)Lscala/collection/immutable/NumericRange;
Method	scala/runtime/RichDouble$$anonfun$until$1.apply:(D)Lscala/collection/immutable/NumericRange;
Asciz	v1;
Asciz	Ljava/lang/Object;;
Asciz	scala/runtime/RichDouble;
class	scala/runtime/RichDouble
Asciz	until;
Asciz	(DD)Lscala/collection/immutable/NumericRange;;
NameAndType	until:(DD)Lscala/collection/immutable/NumericRange;
Method	scala/runtime/RichDouble.until:(DD)Lscala/collection/immutable/NumericRange;
Asciz	(D)Lscala/collection/immutable/NumericRange<Ljava/lang/Double;>;;
Asciz	Signature;
Asciz	andThen;
Asciz	(Lscala/Function1;)Lscala/Function1;;
Asciz	(Lscala/Function1;Lscala/Function1;)Lscala/Function1;;
NameAndType	andThen:(Lscala/Function1;Lscala/Function1;)Lscala/Function1;
Method	scala/Function1$class.andThen:(Lscala/Function1;Lscala/Function1;)Lscala/Function1;
Asciz	g;
Asciz	Lscala/Function1;;
Asciz	compose;
NameAndType	compose:(Lscala/Function1;Lscala/Function1;)Lscala/Function1;
Method	scala/Function1$class.compose:(Lscala/Function1;Lscala/Function1;)Lscala/Function1;
Asciz	toString;
Asciz	()Ljava/lang/String;;
Asciz	(Lscala/Function1;)Ljava/lang/String;;
NameAndType	toString:(Lscala/Function1;)Ljava/lang/String;
Method	scala/Function1$class.toString:(Lscala/Function1;)Ljava/lang/String;
Asciz	Scala;
Asciz	InnerClasses;
Asciz	$anonfun$until$1;
Asciz	scala/Function1;
class	scala/Function1
Asciz	scala/ScalaObject;
class	scala/ScalaObject
Asciz	java/io/Serializable;
class	java/io/Serializable

{
public static final long serialVersionUID;
  Signature: J

private final double end$1;
  Signature: D

private final scala.runtime.RichDouble $outer;
  Signature: Lscala/runtime/RichDouble;

public static {};
  Signature: ()V
  Code:
   Stack=2, Locals=0, Args_size=0
	lconst_0
	putstatic	Field serialVersionUID:J
	return
  Labels:

public scala.runtime.RichDouble$$anonfun$until$1(scala.runtime.RichDouble, double);
  Signature: (Lscala/runtime/RichDouble;D)V
  Code:
   Stack=3, Locals=4, Args_size=3
	aload_1
	ifnonnull	l1 // aload_0
	new	class java/lang/NullPointerException
	dup
	invokespecial	Method java/lang/NullPointerException."<init>":()V
	athrow
l1	aload_0
	aload_1
	putfield	Field $outer:Lscala/runtime/RichDouble;
	aload_0
	dload_2
	putfield	Field end$1:D
	aload_0
	invokespecial	Method java/lang/Object."<init>":()V
	aload_0
	invokestatic	Method scala/Function1$class.$init$:(Lscala/Function1;)V
	return
  Labels:
   	l1 = 12 // aload_0
  LocalVariableTable: 
   Start  Length  Slot  Name   Signature
   0      31      0    this       Lscala/runtime/RichDouble$$anonfun$until$1;
   0      31      1    $outer       Lscala/runtime/RichDouble;


public final java.lang.Object apply(java.lang.Object);
  Signature: (Ljava/lang/Object;)Ljava/lang/Object;
  Code:
   Stack=3, Locals=3, Args_size=2
	aload_0
	getfield	Field $outer:Lscala/runtime/RichDouble;
	astore_2
	aload_0
	aload_1
	invokestatic	Method scala/runtime/BoxesRunTime.unboxToDouble:(Ljava/lang/Object;)D
	invokevirtual	Method apply:(D)Lscala/collection/immutable/NumericRange;
	areturn
  Labels:
  LocalVariableTable: 
   Start  Length  Slot  Name   Signature
   0      14      0    this       Lscala/runtime/RichDouble$$anonfun$until$1;
   5      9      1    v1       Ljava/lang/Object;


public final scala.collection.immutable.NumericRange apply(double);
  Signature: (D)Lscala/collection/immutable/NumericRange;
  Code:
   Stack=5, Locals=4, Args_size=2
	aload_0
	getfield	Field $outer:Lscala/runtime/RichDouble;
	astore_3
	aload_0
	getfield	Field $outer:Lscala/runtime/RichDouble;
	aload_0
	getfield	Field end$1:D
	dload_1
	invokevirtual	Method scala/runtime/RichDouble.until:(DD)Lscala/collection/immutable/NumericRange;
	areturn
  Labels:
  LocalVariableTable: 
   Start  Length  Slot  Name   Signature
   0      18      0    this       Lscala/runtime/RichDouble$$anonfun$until$1;

  Signature: length = 0x2
   00 3A 

public scala.Function1 andThen(scala.Function1);
  Signature: (Lscala/Function1;)Lscala/Function1;
  Code:
   Stack=2, Locals=2, Args_size=2
	aload_0
	aload_1
	invokestatic	Method scala/Function1$class.andThen:(Lscala/Function1;Lscala/Function1;)Lscala/Function1;
	areturn
  Labels:
  LocalVariableTable: 
   Start  Length  Slot  Name   Signature
   0      6      0    this       Lscala/runtime/RichDouble$$anonfun$until$1;
   0      6      1    g       Lscala/Function1;


public scala.Function1 compose(scala.Function1);
  Signature: (Lscala/Function1;)Lscala/Function1;
  Code:
   Stack=2, Locals=2, Args_size=2
	aload_0
	aload_1
	invokestatic	Method scala/Function1$class.compose:(Lscala/Function1;Lscala/Function1;)Lscala/Function1;
	areturn
  Labels:
  LocalVariableTable: 
   Start  Length  Slot  Name   Signature
   0      6      0    this       Lscala/runtime/RichDouble$$anonfun$until$1;
   0      6      1    g       Lscala/Function1;


public java.lang.String toString();
  Signature: ()Ljava/lang/String;
  Code:
   Stack=1, Locals=1, Args_size=1
	aload_0
	invokestatic	Method scala/Function1$class.toString:(Lscala/Function1;)Ljava/lang/String;
	areturn
  Labels:

}

