Compiled from "RichString.scala"
public final class scala.runtime.RichString extends java.lang.Object implements scala.Ordered,scala.Proxy,scala.RandomAccessSeq
  ScalaSig: length = 0x73A
   04 01 FFFFFF82 12 06 08 01 02 FFFFFF84 FFFFFF80 FFFFFF80 FFFFFF80 02 07 02 0A
   52 69 63 68 53 74 72 69 6E 67 0A 02 03 04 01 07
   72 75 6E 74 69 6D 65 0A 01 05 01 05 73 63 61 6C
   61 03 00 13 06 00 08 10 14 1A 24 10 02 09 0E 0D
   01 0A 0A 02 0B 0C 01 04 6C 61 6E 67 0A 01 0D 01
   04 6A 61 76 61 09 02 0F 0A 02 06 4F 62 6A 65 63
   74 10 02 11 12 0D 01 04 09 02 13 04 02 05 50 72
   6F 78 79 10 03 11 15 17 09 02 16 04 02 0F 52 61
   6E 64 6F 6D 41 63 63 65 73 73 53 65 71 10 02 11
   18 09 02 19 04 02 04 43 68 61 72 10 03 11 1B 1D
   09 02 1C 04 02 07 4F 72 64 65 72 65 64 10 02 1E
   21 0E 02 11 1F 09 02 20 04 01 06 50 72 65 64 65
   66 09 02 22 23 02 06 53 74 72 69 6E 67 0A 02 20
   04 10 02 11 25 09 02 26 04 02 0B 53 63 61 6C 61
   4F 62 6A 65 63 74 08 08 28 00 FFFFFF82 FFFFFFC2 FFFFFF80 FFFFFF84 00 29
   01 04 73 65 6C 66 15 01 1D 08 08 2B 00 FFFFFF82 FFFFFF80 FFFFFFA0
   FFFFFF80 04 1D 01 05 73 65 6C 66 20 08 05 2D 00 FFFFFF84 00
   2E 01 06 3C 69 6E 69 74 3E 14 02 2F 1D 10 02 30
   00 0D 01 02 08 05 32 00 FFFFFF84 20 33 01 05 61 70 70
   6C 79 14 02 17 34 10 02 11 35 09 02 36 04 02 03
   49 6E 74 08 05 38 00 FFFFFF84 20 39 01 06 6C 65 6E 67
   74 68 15 01 34 08 05 3B 00 FFFFFF84 20 3C 01 08 74 6F
   53 74 72 69 6E 67 14 01 1D 08 05 3E 00 FFFFFF84 20 29
   01 08 6D 6B 53 74 72 69 6E 67 08 05 40 00 FFFFFF84 20
   41 01 05 73 6C 69 63 65 14 03 2F 34 34 08 05 43
   00 FFFFFF84 20 44 01 0A 24 70 6C 75 73 24 70 6C 75 73
   15 02 45 49 14 02 46 4F 10 03 11 15 47 10 02 48
   49 0C 00 04 08 4A 42 FFFFFF84 FFFFFF80 FFFFFF80 FFFFFFC2 00 4B 02 01 42
   11 02 17 4C 10 02 11 4D 09 02 4E 04 02 03 41 6E
   79 10 03 11 50 47 09 02 51 04 02 08 49 74 65 72
   61 62 6C 65 08 05 53 00 FFFFFF84 20 54 01 04 74 61 6B
   65 14 02 2F 34 08 05 56 00 FFFFFF84 20 54 01 04 64 72
   6F 70 08 05 58 00 FFFFFF84 20 59 01 0A 73 74 61 72 74
   73 57 69 74 68 15 02 5A 62 14 02 5B 5E 10 02 11
   5C 09 02 5D 04 02 07 42 6F 6F 6C 65 61 6E 10 03
   11 5F 61 09 02 60 04 02 03 53 65 71 10 02 48 62
   04 08 4A 57 FFFFFF84 FFFFFF80 FFFFFF80 FFFFFFC2 00 63 11 02 64 4C 10 02
   11 65 09 02 66 04 02 07 4E 6F 74 68 69 6E 67 08
   05 68 00 FFFFFF84 20 69 01 08 65 6E 64 73 57 69 74 68
   15 02 6A 6D 14 02 5B 6B 10 03 11 5F 6C 10 02 48
   6D 04 08 4A 67 FFFFFF84 FFFFFF80 FFFFFF80 FFFFFFC2 00 63 08 05 6F 00 FFFFFF84
   20 70 01 07 69 6E 64 65 78 4F 66 15 02 71 74 14
   02 34 72 10 03 11 5F 73 10 02 48 74 04 08 4A 6E
   FFFFFF84 FFFFFF80 FFFFFF80 FFFFFFC2 00 63 08 05 76 00 FFFFFF84 20 77 01 0D 63
   6F 6E 74 61 69 6E 73 53 6C 69 63 65 15 02 78 7B
   14 02 5B 79 10 03 11 5F 7A 10 02 48 7B 04 08 4A
   75 FFFFFF84 FFFFFF80 FFFFFF80 FFFFFFC2 00 63 08 05 7D 00 FFFFFF84 20 7E 01 07
   72 65 76 65 72 73 65 15 01 2F 08 07 FFFFFF81 00 00 FFFFFF84
   00 FFFFFF81 01 01 06 24 74 69 6D 65 73 14 02 1D 34 08
   07 FFFFFF81 03 00 FFFFFF84 20 FFFFFF81 04 01 07 63 6F 6D 70 61 72
   65 14 02 34 1D 08 07 FFFFFF81 06 00 FFFFFF84 04 FFFFFF81 07 01 0B
   69 73 4C 69 6E 65 42 72 65 61 6B 14 02 5B 17 08
   06 FFFFFF81 09 00 FFFFFF84 00 29 01 0C 73 74 72 69 70 4C 69
   6E 65 45 6E 64 08 07 FFFFFF81 0B 00 FFFFFF84 00 FFFFFF81 0C 01 13
   6C 69 6E 65 73 57 69 74 68 53 65 70 61 72 61 74
   6F 72 73 15 02 FFFFFF81 0D 12 05 FFFFFF81 0E 08 FFFFFF81 10 06 0B
   FFFFFF81 0F FFFFFF81 0A FFFFFF84 FFFFFF80 FFFFFF80 FFFFFF80 00 FFFFFF81 0D 02 0C 3C 72 65
   66 69 6E 65 6D 65 6E 74 3E 10 04 11 FFFFFF81 11 1D 09
   03 FFFFFF81 12 04 02 08 49 74 65 72 61 74 6F 72 08 09
   FFFFFF81 14 FFFFFF81 0E FFFFFFC2 FFFFFF80 FFFFFF84 00 39 01 03 6C 65 6E 08 09
   FFFFFF81 16 FFFFFF81 0E FFFFFFC0 FFFFFF80 FFFFFF84 00 39 01 05 69 6E 64 65 78
   08 0A FFFFFF81 18 FFFFFF81 0E FFFFFFC0 FFFFFF80 FFFFFF84 00 FFFFFF81 19 01 09 69 6E
   64 65 78 5F 24 65 71 14 03 FFFFFF81 1A 34 10 03 11 FFFFFF81
   1B 09 03 FFFFFF81 1C 04 02 04 55 6E 69 74 08 07 FFFFFF81 1E
   00 FFFFFF84 00 FFFFFF81 1F 01 05 6C 69 6E 65 73 15 02 FFFFFF81 10
   08 06 FFFFFF81 21 00 FFFFFF84 00 29 01 0A 63 61 70 69 74 61
   6C 69 7A 65 08 07 FFFFFF81 23 00 FFFFFF84 00 FFFFFF81 24 01 0B 73
   74 72 69 70 4D 61 72 67 69 6E 14 02 1D 17 08 06
   FFFFFF81 23 00 FFFFFF84 00 29 08 07 FFFFFF81 27 00 FFFFFF84 04 FFFFFF81 24 01
   06 65 73 63 61 70 65 08 07 FFFFFF81 29 00 FFFFFF84 00 FFFFFF81 2A
   01 05 73 70 6C 69 74 14 03 FFFFFF81 2B 17 10 04 11 FFFFFF81
   2C 1D 09 03 FFFFFF81 2D 04 02 05 41 72 72 61 79 28 06
   FFFFFF81 28 FFFFFF81 2F FFFFFF81 32 10 03 11 FFFFFF81 30 09 03 FFFFFF81 31 04
   02 06 74 68 72 6F 77 73 23 02 FFFFFF81 34 23 02 FFFFFF81 34
   10 04 FFFFFF81 35 FFFFFF81 3A 0D 02 FFFFFF81 36 0A 04 FFFFFF81 37 FFFFFF81 38
   01 05 72 65 67 65 78 0A 03 FFFFFF81 39 0C 01 04 75 74
   69 6C 09 04 FFFFFF81 3B FFFFFF81 36 02 16 50 61 74 74 65 72
   6E 53 79 6E 74 61 78 45 78 63 65 70 74 69 6F 6E
   08 07 FFFFFF81 29 00 FFFFFF84 00 FFFFFF81 3D 14 04 FFFFFF81 2B FFFFFF81 3E 10
   04 11 FFFFFF81 2C 17 28 06 FFFFFF81 3C FFFFFF81 2F FFFFFF81 40 23 02 FFFFFF81
   34 08 07 FFFFFF81 42 00 FFFFFF84 00 FFFFFF81 43 01 01 72 15 02 FFFFFF81
   44 10 04 FFFFFF81 45 FFFFFF81 49 0D 02 FFFFFF81 46 0A 04 FFFFFF81 47 FFFFFF81
   48 01 08 6D 61 74 63 68 69 6E 67 0A 03 FFFFFF81 39 04
   09 04 FFFFFF81 4A FFFFFF81 46 02 05 52 65 67 65 78 08 07 FFFFFF81
   4C 00 FFFFFF84 00 FFFFFF81 4D 01 09 74 6F 42 6F 6F 6C 65 61
   6E 15 01 5B 08 07 FFFFFF81 4F 00 FFFFFF84 00 FFFFFF81 50 01 06 74
   6F 42 79 74 65 15 02 FFFFFF81 51 10 03 11 FFFFFF81 52 09 03
   FFFFFF81 53 04 02 04 42 79 74 65 08 07 FFFFFF81 55 00 FFFFFF84 00
   FFFFFF81 56 01 07 74 6F 53 68 6F 72 74 15 02 FFFFFF81 57 10
   03 11 FFFFFF81 58 09 03 FFFFFF81 59 04 02 05 53 68 6F 72 74
   08 06 FFFFFF81 5B 00 FFFFFF84 00 39 01 05 74 6F 49 6E 74 08
   07 FFFFFF81 5D 00 FFFFFF84 00 FFFFFF81 5E 01 06 74 6F 4C 6F 6E 67
   15 02 FFFFFF81 5F 10 03 11 FFFFFF81 60 09 03 FFFFFF81 61 04 02 04
   4C 6F 6E 67 08 07 FFFFFF81 63 00 FFFFFF84 00 FFFFFF81 64 01 07 74
   6F 46 6C 6F 61 74 15 02 FFFFFF81 65 10 03 11 FFFFFF81 66 09
   03 FFFFFF81 67 04 02 05 46 6C 6F 61 74 08 07 FFFFFF81 69 00
   FFFFFF84 00 FFFFFF81 6A 01 08 74 6F 44 6F 75 62 6C 65 15 02
   FFFFFF81 6B 10 03 11 FFFFFF81 6C 09 03 FFFFFF81 6D 04 02 06 44 6F
   75 62 6C 65 08 07 FFFFFF81 6F 00 FFFFFF84 00 FFFFFF81 70 01 07 74
   6F 41 72 72 61 79 15 02 FFFFFF81 3E 08 07 FFFFFF81 72 00 FFFFFF84
   00 FFFFFF81 73 01 06 66 6F 72 6D 61 74 14 03 1D FFFFFF81 74
   10 04 11 FFFFFF81 75 4C 09 03 FFFFFF81 76 04 02 0A 3C 72 65
   70 65 61 74 65 64 3E 07 07 FFFFFF81 78 02 FFFFFF88 02 FFFFFF81 79
   01 0A 52 69 63 68 53 74 72 69 6E 67 10 03 30 FFFFFF81
   7A 06 09 01 02 FFFFFF84 FFFFFF80 FFFFFF80 FFFFFF88 02 FFFFFF81 7B 13 04 FFFFFF81 7A
   08 24 08 07 2D FFFFFF81 7A FFFFFF84 00 FFFFFF81 7D 14 02 FFFFFF81 79 08
   0A FFFFFF81 7F FFFFFF81 7A FFFFFFC2 FFFFFF80 FFFFFF84 06 FFFFFF82 00 01 02 4C 46 15
   01 17 08 08 FFFFFF82 02 FFFFFF81 7A FFFFFFA0 FFFFFF80 06 17 01 03 4C 46
   20 08 0A FFFFFF82 04 FFFFFF81 7A FFFFFFC2 FFFFFF80 FFFFFF84 06 FFFFFF82 00 01 02 46
   46 08 08 FFFFFF82 06 FFFFFF81 7A FFFFFFA0 FFFFFF80 06 17 01 03 46 46 20
   08 0A FFFFFF82 08 FFFFFF81 7A FFFFFFC2 FFFFFF80 FFFFFF84 06 FFFFFF82 00 01 02 43 52
   08 08 FFFFFF82 0A FFFFFF81 7A FFFFFFA0 FFFFFF80 06 17 01 03 43 52 20 08
   0A FFFFFF82 0C FFFFFF81 7A FFFFFFC2 FFFFFF80 FFFFFF84 06 FFFFFF82 00 01 02 53 55 08
   08 FFFFFF82 0E FFFFFF81 7A FFFFFFA0 FFFFFF80 06 17 01 03 53 55 20 08 08
   FFFFFF82 10 FFFFFF81 7A FFFFFF84 04 FFFFFF82 11 01 0C 70 61 72 73 65 42
   6F 6F 6C 65 61 6E 14 02 5B 1D 
  Signature: length = 0x2
   00 67 
  SourceFile: "RichString.scala"
  minor version: 0
  major version: 49
  Constant pool:
class	java/lang/Integer
class	java/lang/Object
class	java/lang/String
class	scala/Collection$class
class	scala/Function1$class
class	scala/Iterable
class	scala/Iterable$class
class	scala/Ordered
class	scala/Ordered$class
class	scala/PartialFunction$class
class	scala/Proxy
class	scala/Proxy$class
class	scala/RandomAccessSeq
class	scala/RandomAccessSeq$class
class	scala/Seq
class	scala/Seq$class
class	scala/runtime/BoxesRunTime
class	scala/runtime/RichString
Field	scala/runtime/RichString.self:Ljava/lang/String;
Method	java/lang/Integer.parseInt:(Ljava/lang/String;)I
Method	java/lang/Object."<init>":()V
Method	java/lang/String.charAt:(I)C
Method	java/lang/String.length:()I
Method	scala/Collection$class.$init$:(Lscala/Collection;)V
Method	scala/Collection$class.stringPrefix:(Lscala/Collection;)Ljava/lang/String;
Method	scala/Function1$class.$init$:(Lscala/Function1;)V
Method	scala/Iterable$class.$init$:(Lscala/Iterable;)V
Method	scala/Iterable$class.addString:(Lscala/Iterable;Lscala/StringBuilder;Ljava/lang/String;Ljava/lang/String;Ljava/lang/String;)Lscala/StringBuilder;
Method	scala/Iterable$class.mkString:(Lscala/Iterable;Ljava/lang/String;Ljava/lang/String;Ljava/lang/String;)Ljava/lang/String;
Method	scala/Ordered$class.$init$:(Lscala/Ordered;)V
Method	scala/PartialFunction$class.$init$:(Lscala/PartialFunction;)V
Method	scala/Proxy$class.$init$:(Lscala/Proxy;)V
Method	scala/Proxy$class.equals:(Lscala/Proxy;Ljava/lang/Object;)Z
Method	scala/Proxy$class.hashCode:(Lscala/Proxy;)I
Method	scala/RandomAccessSeq$class.$init$:(Lscala/RandomAccessSeq;)V
Method	scala/RandomAccessSeq$class.elements:(Lscala/RandomAccessSeq;)Lscala/Iterator;
Method	scala/Seq$class.$init$:(Lscala/Seq;)V
Method	scala/Seq$class.isEmpty:(Lscala/Seq;)Z
Method	scala/runtime/BoxesRunTime.boxToCharacter:(C)Ljava/lang/Character;
Method	scala/runtime/BoxesRunTime.unboxToInt:(Ljava/lang/Object;)I
Method	scala/runtime/RichString.apply:(I)C
Method	scala/runtime/RichString.self:()Ljava/lang/String;
NameAndType	$init$:(Lscala/Collection;)V
NameAndType	$init$:(Lscala/Function1;)V
NameAndType	$init$:(Lscala/Iterable;)V
NameAndType	$init$:(Lscala/Ordered;)V
NameAndType	$init$:(Lscala/PartialFunction;)V
NameAndType	$init$:(Lscala/Proxy;)V
NameAndType	$init$:(Lscala/RandomAccessSeq;)V
NameAndType	$init$:(Lscala/Seq;)V
NameAndType	"<init>":()V
NameAndType	addString:(Lscala/Iterable;Lscala/StringBuilder;Ljava/lang/String;Ljava/lang/String;Ljava/lang/String;)Lscala/StringBuilder;
NameAndType	apply:(I)C
NameAndType	boxToCharacter:(C)Ljava/lang/Character;
NameAndType	charAt:(I)C
NameAndType	elements:(Lscala/RandomAccessSeq;)Lscala/Iterator;
NameAndType	equals:(Lscala/Proxy;Ljava/lang/Object;)Z
NameAndType	hashCode:(Lscala/Proxy;)I
NameAndType	isEmpty:(Lscala/Seq;)Z
NameAndType	length:()I
NameAndType	mkString:(Lscala/Iterable;Ljava/lang/String;Ljava/lang/String;Ljava/lang/String;)Ljava/lang/String;
NameAndType	parseInt:(Ljava/lang/String;)I
NameAndType	self:()Ljava/lang/String;
NameAndType	self:Ljava/lang/String;
NameAndType	stringPrefix:(Lscala/Collection;)Ljava/lang/String;
NameAndType	unboxToInt:(Ljava/lang/Object;)I
Asciz	$init$;
Asciz	()I;
Asciz	()Ljava/lang/Object;;
Asciz	()Ljava/lang/String;;
Asciz	()Lscala/Iterator;;
Asciz	()V;
Asciz	()Z;
Asciz	(C)Ljava/lang/Character;;
Asciz	(I)C;
Asciz	(Ljava/lang/Object;)I;
Asciz	(Ljava/lang/Object;)Ljava/lang/Object;;
Asciz	(Ljava/lang/Object;)Z;
Asciz	(Ljava/lang/String;)I;
Asciz	(Ljava/lang/String;)V;
Asciz	(Ljava/lang/String;Ljava/lang/String;Ljava/lang/String;)Ljava/lang/String;;
Asciz	(Lscala/Collection;)Ljava/lang/String;;
Asciz	(Lscala/Collection;)V;
Asciz	(Lscala/Function1;)V;
Asciz	(Lscala/Iterable;)V;
Asciz	(Lscala/Iterable;Ljava/lang/String;Ljava/lang/String;Ljava/lang/String;)Ljava/lang/String;;
Asciz	(Lscala/Iterable;Lscala/StringBuilder;Ljava/lang/String;Ljava/lang/String;Ljava/lang/String;)Lscala/StringBuilder;;
Asciz	(Lscala/Ordered;)V;
Asciz	(Lscala/PartialFunction;)V;
Asciz	(Lscala/Proxy;)I;
Asciz	(Lscala/Proxy;)V;
Asciz	(Lscala/Proxy;Ljava/lang/Object;)Z;
Asciz	(Lscala/RandomAccessSeq;)Lscala/Iterator;;
Asciz	(Lscala/RandomAccessSeq;)V;
Asciz	(Lscala/Seq;)V;
Asciz	(Lscala/Seq;)Z;
Asciz	(Lscala/StringBuilder;Ljava/lang/String;Ljava/lang/String;Ljava/lang/String;)Lscala/StringBuilder;;
Asciz	<init>;
Asciz	Code;
Asciz	I;
Asciz	LineNumberTable;
Asciz	Ljava/lang/Object;;
Asciz	Ljava/lang/Object;Lscala/Proxy;Lscala/RandomAccessSeq<Ljava/lang/Character;>;Lscala/Ordered<Ljava/lang/String;>;;
Asciz	Ljava/lang/String;;
Asciz	LocalVariableTable;
Asciz	Lscala/StringBuilder;;
Asciz	Lscala/runtime/RichString;;
Asciz	RichString.scala;
Asciz	ScalaSig;
Asciz	Signature;
Asciz	SourceFile;
Asciz	addString;
Asciz	apply;
Asciz	boxToCharacter;
Asciz	charAt;
Asciz	elements;
Asciz	equals;
Asciz	hashCode;
Asciz	isEmpty;
Asciz	java/lang/Integer;
Asciz	java/lang/Object;
Asciz	java/lang/String;
Asciz	length;
Asciz	mkString;
Asciz	n;
Asciz	parseInt;
Asciz	scala/Collection$class;
Asciz	scala/Function1$class;
Asciz	scala/Iterable;
Asciz	scala/Iterable$class;
Asciz	scala/Ordered;
Asciz	scala/Ordered$class;
Asciz	scala/PartialFunction$class;
Asciz	scala/Proxy;
Asciz	scala/Proxy$class;
Asciz	scala/RandomAccessSeq;
Asciz	scala/RandomAccessSeq$class;
Asciz	scala/Seq;
Asciz	scala/Seq$class;
Asciz	scala/runtime/BoxesRunTime;
Asciz	scala/runtime/RichString;
Asciz	self;
Asciz	stringPrefix;
Asciz	this;
Asciz	toInt;
Asciz	toString;
Asciz	unboxToInt;
Asciz	x$1;
Asciz	x$2;
Asciz	x$3;
Asciz	x$4;

{
private final java.lang.String self;
  Signature: Ljava/lang/String;

public scala.runtime.RichString(java.lang.String);
  Signature: (Ljava/lang/String;)V
  Code:
   Stack=2, Locals=2, Args_size=2
	aload_0
	aload_1
	putfield	Field self:Ljava/lang/String;
	aload_0
	invokespecial	Method java/lang/Object."<init>":()V
	aload_0
	invokestatic	Method scala/Proxy$class.$init$:(Lscala/Proxy;)V
	aload_0
	invokestatic	Method scala/Function1$class.$init$:(Lscala/Function1;)V
	aload_0
	invokestatic	Method scala/PartialFunction$class.$init$:(Lscala/PartialFunction;)V
	aload_0
	invokestatic	Method scala/Iterable$class.$init$:(Lscala/Iterable;)V
	aload_0
	invokestatic	Method scala/Collection$class.$init$:(Lscala/Collection;)V
	aload_0
	invokestatic	Method scala/Seq$class.$init$:(Lscala/Seq;)V
	aload_0
	invokestatic	Method scala/RandomAccessSeq$class.$init$:(Lscala/RandomAccessSeq;)V
	aload_0
	invokestatic	Method scala/Ordered$class.$init$:(Lscala/Ordered;)V
	return
  Labels:
  LocalVariableTable: 
   Start  Length  Slot  Name   Signature
   0      42      0    this       Lscala/runtime/RichString;
   0      42      1    self       Ljava/lang/String;


public java.lang.Object self();
  Signature: ()Ljava/lang/Object;
  Code:
   Stack=1, Locals=1, Args_size=1
	aload_0
	invokevirtual	Method self:()Ljava/lang/String;
	areturn
  Labels:

public java.lang.Object apply(java.lang.Object);
  Signature: (Ljava/lang/Object;)Ljava/lang/Object;
  Code:
   Stack=2, Locals=2, Args_size=2
	aload_0
	aload_1
	invokestatic	Method scala/runtime/BoxesRunTime.unboxToInt:(Ljava/lang/Object;)I
	invokevirtual	Method apply:(I)C
	invokestatic	Method scala/runtime/BoxesRunTime.boxToCharacter:(C)Ljava/lang/Character;
	areturn
  Labels:
  LocalVariableTable: 
   Start  Length  Slot  Name   Signature
   0      12      0    this       Lscala/runtime/RichString;
   0      12      1    x$1       Ljava/lang/Object;


public int toInt();
  Signature: ()I
  Code:
   Stack=1, Locals=1, Args_size=1
	aload_0
	invokevirtual	Method self:()Ljava/lang/String;
	invokestatic	Method java/lang/Integer.parseInt:(Ljava/lang/String;)I
	ireturn
  Labels:

public java.lang.String toString();
  Signature: ()Ljava/lang/String;
  Code:
   Stack=1, Locals=1, Args_size=1
	aload_0
	invokevirtual	Method self:()Ljava/lang/String;
	areturn
  Labels:

public int length();
  Signature: ()I
  Code:
   Stack=1, Locals=1, Args_size=1
	aload_0
	invokevirtual	Method self:()Ljava/lang/String;
	invokevirtual	Method java/lang/String.length:()I
	ireturn
  Labels:

public char apply(int);
  Signature: (I)C
  Code:
   Stack=2, Locals=2, Args_size=2
	aload_0
	invokevirtual	Method self:()Ljava/lang/String;
	iload_1
	invokevirtual	Method java/lang/String.charAt:(I)C
	ireturn
  Labels:
  LocalVariableTable: 
   Start  Length  Slot  Name   Signature
   0      9      0    this       Lscala/runtime/RichString;
   0      9      1    n       I


public java.lang.String self();
  Signature: ()Ljava/lang/String;
  Code:
   Stack=1, Locals=1, Args_size=1
	aload_0
	getfield	Field self:Ljava/lang/String;
	areturn
  Labels:

public boolean equals(java.lang.Object);
  Signature: (Ljava/lang/Object;)Z
  Code:
   Stack=2, Locals=2, Args_size=2
	aload_0
	aload_1
	invokestatic	Method scala/Proxy$class.equals:(Lscala/Proxy;Ljava/lang/Object;)Z
	ireturn
  Labels:
  LocalVariableTable: 
   Start  Length  Slot  Name   Signature
   0      6      0    this       Lscala/runtime/RichString;
   0      6      1    x$1       Ljava/lang/Object;


public int hashCode();
  Signature: ()I
  Code:
   Stack=1, Locals=1, Args_size=1
	aload_0
	invokestatic	Method scala/Proxy$class.hashCode:(Lscala/Proxy;)I
	ireturn
  Labels:

public scala.StringBuilder addString(scala.StringBuilder, java.lang.String, java.lang.String, java.lang.String);
  Signature: (Lscala/StringBuilder;Ljava/lang/String;Ljava/lang/String;Ljava/lang/String;)Lscala/StringBuilder;
  Code:
   Stack=5, Locals=5, Args_size=5
	aload_0
	aload_1
	aload_2
	aload_3
	aload	4
	invokestatic	Method scala/Iterable$class.addString:(Lscala/Iterable;Lscala/StringBuilder;Ljava/lang/String;Ljava/lang/String;Ljava/lang/String;)Lscala/StringBuilder;
	areturn
  Labels:
  LocalVariableTable: 
   Start  Length  Slot  Name   Signature
   0      10      0    this       Lscala/runtime/RichString;
   0      10      1    x$1       Lscala/StringBuilder;
   0      10      2    x$2       Ljava/lang/String;
   0      10      3    x$3       Ljava/lang/String;
   0      10      4    x$4       Ljava/lang/String;


public java.lang.String mkString(java.lang.String, java.lang.String, java.lang.String);
  Signature: (Ljava/lang/String;Ljava/lang/String;Ljava/lang/String;)Ljava/lang/String;
  Code:
   Stack=4, Locals=4, Args_size=4
	aload_0
	aload_1
	aload_2
	aload_3
	invokestatic	Method scala/Iterable$class.mkString:(Lscala/Iterable;Ljava/lang/String;Ljava/lang/String;Ljava/lang/String;)Ljava/lang/String;
	areturn
  Labels:
  LocalVariableTable: 
   Start  Length  Slot  Name   Signature
   0      8      0    this       Lscala/runtime/RichString;
   0      8      1    x$1       Ljava/lang/String;
   0      8      2    x$2       Ljava/lang/String;
   0      8      3    x$3       Ljava/lang/String;


public java.lang.String stringPrefix();
  Signature: ()Ljava/lang/String;
  Code:
   Stack=1, Locals=1, Args_size=1
	aload_0
	invokestatic	Method scala/Collection$class.stringPrefix:(Lscala/Collection;)Ljava/lang/String;
	areturn
  Labels:

public boolean isEmpty();
  Signature: ()Z
  Code:
   Stack=1, Locals=1, Args_size=1
	aload_0
	invokestatic	Method scala/Seq$class.isEmpty:(Lscala/Seq;)Z
	ireturn
  Labels:

public scala.Iterator elements();
  Signature: ()Lscala/Iterator;
  Code:
   Stack=1, Locals=1, Args_size=1
	aload_0
	invokestatic	Method scala/RandomAccessSeq$class.elements:(Lscala/RandomAccessSeq;)Lscala/Iterator;
	areturn
  Labels:

}

