Compiled from "RichString.scala"
public final class scala.runtime.RichString$ extends java.lang.Object implements scala.ScalaObject
  SourceFile: "RichString.scala"
  Scala: length = 0x
   
  InnerClass: 
   public final #68= #47 of #67; //$anon$2=class scala/runtime/RichString$$anon$2 of class scala/runtime/RichString
   public final #71= #70 of #67; //$anon$1=class scala/runtime/RichString$$anon$1 of class scala/runtime/RichString
   public final #72= #41 of #67; //$anon$3=class scala/runtime/RichString$$anon$3 of class scala/runtime/RichString
   public final #75= #74 of #67; //$anonfun$1=class scala/runtime/RichString$$anonfun$1 of class scala/runtime/RichString
   public final #78= #77 of #67; //$anonfun$lines$1=class scala/runtime/RichString$$anonfun$lines$1 of class scala/runtime/RichString
   public final #81= #80 of #67; //$anonfun$$times$1=class scala/runtime/RichString$$anonfun$$times$1 of class scala/runtime/RichString
   public final #82= #56 of #67; //$anonfun$newBuilder$1=class scala/runtime/RichString$$anonfun$newBuilder$1 of class scala/runtime/RichString
   public final #85= #84 of #67; //$anonfun$stripMargin$1=class scala/runtime/RichString$$anonfun$stripMargin$1 of class scala/runtime/RichString
   public final #88= #87 of #67; //$anonfun$linesIterator$1=class scala/runtime/RichString$$anonfun$linesIterator$1 of class scala/runtime/RichString
  minor version: 0
  major version: 49
  Constant pool:
const #1 = Asciz	SourceFile;
const #2 = Asciz	RichString.scala;
const #3 = Asciz	Scala;
const #4 = Asciz	MODULE$;
const #5 = Asciz	Lscala/runtime/RichString$;;
const #6 = Asciz	<clinit>;
const #7 = Asciz	()V;
const #8 = Asciz	Code;
const #9 = Asciz	scala/runtime/RichString$;
const #10 = class	#9;	//  scala/runtime/RichString$
const #11 = Asciz	<init>;
const #12 = NameAndType	#11:#7;//  "<init>":()V
const #13 = Method	#10.#12;	//  scala/runtime/RichString$."<init>":()V
const #14 = Asciz	SU;
const #15 = Asciz	C;
const #16 = Asciz	scala$runtime$RichString$$CR;
const #17 = Asciz	scala$runtime$RichString$$FF;
const #18 = Asciz	scala$runtime$RichString$$LF;
const #19 = Asciz	LineNumberTable;
const #20 = Asciz	java/lang/Object;
const #21 = class	#20;	//  java/lang/Object
const #22 = Method	#21.#12;	//  java/lang/Object."<init>":()V
const #23 = NameAndType	#4:#5;//  MODULE$:Lscala/runtime/RichString$;
const #24 = Field	#10.#23;	//  scala/runtime/RichString$.MODULE$:Lscala/runtime/RichString$;
const #25 = int	10;
const #26 = NameAndType	#18:#15;//  scala$runtime$RichString$$LF:C
const #27 = Field	#10.#26;	//  scala/runtime/RichString$.scala$runtime$RichString$$LF:C
const #28 = int	12;
const #29 = NameAndType	#17:#15;//  scala$runtime$RichString$$FF:C
const #30 = Field	#10.#29;	//  scala/runtime/RichString$.scala$runtime$RichString$$FF:C
const #31 = int	13;
const #32 = NameAndType	#16:#15;//  scala$runtime$RichString$$CR:C
const #33 = Field	#10.#32;	//  scala/runtime/RichString$.scala$runtime$RichString$$CR:C
const #34 = int	26;
const #35 = NameAndType	#14:#15;//  SU:C
const #36 = Field	#10.#35;	//  scala/runtime/RichString$.SU:C
const #37 = Asciz	()C;
const #38 = Asciz	builderFactory2;
const #39 = Asciz	()Lscala/collection/generic/BuilderFactory;;
const #40 = Asciz	scala/runtime/RichString$$anon$3;
const #41 = class	#40;	//  scala/runtime/RichString$$anon$3
const #42 = Method	#41.#12;	//  scala/runtime/RichString$$anon$3."<init>":()V
const #43 = Asciz	()Lscala/collection/generic/BuilderFactory<Ljava/lang/Character;Lscala/runtime/RichString;Ljava/lang/String;>;;
const #44 = Asciz	Signature;
const #45 = Asciz	builderFactory;
const #46 = Asciz	scala/runtime/RichString$$anon$2;
const #47 = class	#46;	//  scala/runtime/RichString$$anon$2
const #48 = Method	#47.#12;	//  scala/runtime/RichString$$anon$2."<init>":()V
const #49 = Asciz	()Lscala/collection/generic/BuilderFactory<Ljava/lang/Character;Lscala/runtime/RichString;Lscala/runtime/RichString;>;;
const #50 = Asciz	newBuilder;
const #51 = Asciz	()Lscala/collection/generic/Builder;;
const #52 = Asciz	scala/collection/mutable/StringBuilder;
const #53 = class	#52;	//  scala/collection/mutable/StringBuilder
const #54 = Method	#53.#12;	//  scala/collection/mutable/StringBuilder."<init>":()V
const #55 = Asciz	scala/runtime/RichString$$anonfun$newBuilder$1;
const #56 = class	#55;	//  scala/runtime/RichString$$anonfun$newBuilder$1
const #57 = Method	#56.#12;	//  scala/runtime/RichString$$anonfun$newBuilder$1."<init>":()V
const #58 = Asciz	scala/collection/generic/Builder;
const #59 = class	#58;	//  scala/collection/generic/Builder
const #60 = Asciz	mapResult;
const #61 = Asciz	(Lscala/Function1;)Lscala/collection/generic/Builder;;
const #62 = NameAndType	#60:#61;//  mapResult:(Lscala/Function1;)Lscala/collection/generic/Builder;
const #63 = InterfaceMethod	#59.#62;	//  scala/collection/generic/Builder.mapResult:(Lscala/Function1;)Lscala/collection/generic/Builder;
const #64 = Asciz	()Lscala/collection/generic/Builder<Ljava/lang/Character;Lscala/runtime/RichString;>;;
const #65 = Asciz	InnerClasses;
const #66 = Asciz	scala/runtime/RichString;
const #67 = class	#66;	//  scala/runtime/RichString
const #68 = Asciz	$anon$2;
const #69 = Asciz	scala/runtime/RichString$$anon$1;
const #70 = class	#69;	//  scala/runtime/RichString$$anon$1
const #71 = Asciz	$anon$1;
const #72 = Asciz	$anon$3;
const #73 = Asciz	scala/runtime/RichString$$anonfun$1;
const #74 = class	#73;	//  scala/runtime/RichString$$anonfun$1
const #75 = Asciz	$anonfun$1;
const #76 = Asciz	scala/runtime/RichString$$anonfun$lines$1;
const #77 = class	#76;	//  scala/runtime/RichString$$anonfun$lines$1
const #78 = Asciz	$anonfun$lines$1;
const #79 = Asciz	scala/runtime/RichString$$anonfun$$times$1;
const #80 = class	#79;	//  scala/runtime/RichString$$anonfun$$times$1
const #81 = Asciz	$anonfun$$times$1;
const #82 = Asciz	$anonfun$newBuilder$1;
const #83 = Asciz	scala/runtime/RichString$$anonfun$stripMargin$1;
const #84 = class	#83;	//  scala/runtime/RichString$$anonfun$stripMargin$1
const #85 = Asciz	$anonfun$stripMargin$1;
const #86 = Asciz	scala/runtime/RichString$$anonfun$linesIterator$1;
const #87 = class	#86;	//  scala/runtime/RichString$$anonfun$linesIterator$1
const #88 = Asciz	$anonfun$linesIterator$1;
const #89 = Asciz	scala/ScalaObject;
const #90 = class	#89;	//  scala/ScalaObject

{
public static final scala.runtime.RichString$ MODULE$;

public static {};
  Code:
   Stack=1, Locals=0, Args_size=0
   0:	new	#10; //class scala/runtime/RichString$
   3:	invokespecial	#13; //Method "<init>":()V
   6:	return

public final char scala$runtime$RichString$$CR();
  Code:
   Stack=1, Locals=1, Args_size=1
   0:	aload_0
   1:	getfield	#33; //Field scala$runtime$RichString$$CR:C
   4:	ireturn
  LineNumberTable: 
   line 28: 0


public final char scala$runtime$RichString$$FF();
  Code:
   Stack=1, Locals=1, Args_size=1
   0:	aload_0
   1:	getfield	#30; //Field scala$runtime$RichString$$FF:C
   4:	ireturn
  LineNumberTable: 
   line 27: 0


public final char scala$runtime$RichString$$LF();
  Code:
   Stack=1, Locals=1, Args_size=1
   0:	aload_0
   1:	getfield	#27; //Field scala$runtime$RichString$$LF:C
   4:	ireturn
  LineNumberTable: 
   line 26: 0


public scala.collection.generic.BuilderFactory builderFactory2();
  Code:
   Stack=2, Locals=1, Args_size=1
   0:	new	#41; //class scala/runtime/RichString$$anon$3
   3:	dup
   4:	invokespecial	#42; //Method scala/runtime/RichString$$anon$3."<init>":()V
   7:	areturn
  LineNumberTable: 
   line 23: 0

  Signature: length = 0x2
   00 2B 

public scala.collection.generic.BuilderFactory builderFactory();
  Code:
   Stack=2, Locals=1, Args_size=1
   0:	new	#47; //class scala/runtime/RichString$$anon$2
   3:	dup
   4:	invokespecial	#48; //Method scala/runtime/RichString$$anon$2."<init>":()V
   7:	areturn
  LineNumberTable: 
   line 22: 0

  Signature: length = 0x2
   00 31 

public scala.collection.generic.Builder newBuilder();
  Code:
   Stack=3, Locals=1, Args_size=1
   0:	new	#53; //class scala/collection/mutable/StringBuilder
   3:	dup
   4:	invokespecial	#54; //Method scala/collection/mutable/StringBuilder."<init>":()V
   7:	new	#56; //class scala/runtime/RichString$$anonfun$newBuilder$1
   10:	dup
   11:	invokespecial	#57; //Method scala/runtime/RichString$$anonfun$newBuilder$1."<init>":()V
   14:	invokeinterface	#63,  2; //InterfaceMethod scala/collection/generic/Builder.mapResult:(Lscala/Function1;)Lscala/collection/generic/Builder;
   19:	areturn
  LineNumberTable: 
   line 21: 0

  Signature: length = 0x2
   00 40 

}

