Compiled from "RichDouble.scala"
public final class scala.runtime.RichDouble$$anonfun$to$1 extends scala.runtime.AbstractFunction1 implements java.io.Serializable
  SourceFile: "RichDouble.scala"
  Scala: length = 0x
   
  InnerClass: 
   public final $anonfun$to$1=class scala/runtime/RichDouble$$anonfun$to$1 of class scala/runtime/RichDouble
  minor version: 0
  major version: 49
  Constant pool:
Asciz	SourceFile;
Asciz	RichDouble.scala;
Asciz	<clinit>;
Asciz	()V;
Asciz	Code;
Asciz	serialVersionUID;
Asciz	J;
Asciz	scala/runtime/RichDouble$$anonfun$to$1;
class	scala/runtime/RichDouble$$anonfun$to$1
NameAndType	serialVersionUID:J
Field	scala/runtime/RichDouble$$anonfun$to$1.serialVersionUID:J
Asciz	$outer;
Asciz	Lscala/runtime/RichDouble;;
Asciz	end$2;
Asciz	D;
Asciz	apply;
Asciz	(D)Lscala/collection/immutable/NumericRange;;
Asciz	LineNumberTable;
NameAndType	$outer:Lscala/runtime/RichDouble;
Field	scala/runtime/RichDouble$$anonfun$to$1.$outer:Lscala/runtime/RichDouble;
NameAndType	end$2:D
Field	scala/runtime/RichDouble$$anonfun$to$1.end$2:D
Asciz	scala/runtime/RichDouble;
class	scala/runtime/RichDouble
Asciz	to;
Asciz	(DD)Lscala/collection/immutable/NumericRange;;
NameAndType	to:(DD)Lscala/collection/immutable/NumericRange;
Method	scala/runtime/RichDouble.to:(DD)Lscala/collection/immutable/NumericRange;
Asciz	(D)Lscala/collection/immutable/NumericRange<Ljava/lang/Double;>;;
Asciz	Signature;
Asciz	(Ljava/lang/Object;)Ljava/lang/Object;;
Asciz	scala/runtime/BoxesRunTime;
class	scala/runtime/BoxesRunTime
Asciz	unboxToDouble;
Asciz	(Ljava/lang/Object;)D;
NameAndType	unboxToDouble:(Ljava/lang/Object;)D
Method	scala/runtime/BoxesRunTime.unboxToDouble:(Ljava/lang/Object;)D
NameAndType	apply:(D)Lscala/collection/immutable/NumericRange;
Method	scala/runtime/RichDouble$$anonfun$to$1.apply:(D)Lscala/collection/immutable/NumericRange;
Asciz	this;
Asciz	Lscala/runtime/RichDouble$$anonfun$to$1;;
Asciz	v1;
Asciz	Ljava/lang/Object;;
Asciz	LocalVariableTable;
Asciz	<init>;
Asciz	(Lscala/runtime/RichDouble;D)V;
Asciz	java/lang/NullPointerException;
class	java/lang/NullPointerException
NameAndType	"<init>":()V
Method	java/lang/NullPointerException."<init>":()V
Asciz	scala/runtime/AbstractFunction1;
class	scala/runtime/AbstractFunction1
Method	scala/runtime/AbstractFunction1."<init>":()V
Asciz	Scala;
Asciz	InnerClasses;
Asciz	$anonfun$to$1;
Asciz	java/io/Serializable;
class	java/io/Serializable

{
public static final long serialVersionUID;
  Signature: J

public final scala.runtime.RichDouble $outer;
  Signature: Lscala/runtime/RichDouble;

public final double end$2;
  Signature: D

public static {};
  Signature: ()V
  Code:
   Stack=2, Locals=0, Args_size=0
	lconst_0
	putstatic	Field serialVersionUID:J
	return
  Labels:

public final scala.collection.immutable.NumericRange apply(double);
  Signature: (D)Lscala/collection/immutable/NumericRange;
  Code:
   Stack=5, Locals=3, Args_size=2
	aload_0
	getfield	Field $outer:Lscala/runtime/RichDouble;
	aload_0
	getfield	Field end$2:D
	dload_1
	invokevirtual	Method scala/runtime/RichDouble.to:(DD)Lscala/collection/immutable/NumericRange;
	areturn
  Labels:
  Signature: length = 0x2
   00 1D 

public final java.lang.Object apply(java.lang.Object);
  Signature: (Ljava/lang/Object;)Ljava/lang/Object;
  Code:
   Stack=3, Locals=2, Args_size=2
	aload_0
	aload_1
	invokestatic	Method scala/runtime/BoxesRunTime.unboxToDouble:(Ljava/lang/Object;)D
	invokevirtual	Method apply:(D)Lscala/collection/immutable/NumericRange;
	areturn
  Labels:
  LocalVariableTable: 
   Start  Length  Slot  Name   Signature
   0      9      0    this       Lscala/runtime/RichDouble$$anonfun$to$1;
   0      9      1    v1       Ljava/lang/Object;


public scala.runtime.RichDouble$$anonfun$to$1(scala.runtime.RichDouble, double);
  Signature: (Lscala/runtime/RichDouble;D)V
  Code:
   Stack=3, Locals=4, Args_size=3
	aload_1
	ifnonnull	l1 // aload_0
	new	class java/lang/NullPointerException
	dup
	invokespecial	Method java/lang/NullPointerException."<init>":()V
	athrow
l1	aload_0
	aload_1
	putfield	Field $outer:Lscala/runtime/RichDouble;
	aload_0
	dload_2
	putfield	Field end$2:D
	aload_0
	invokespecial	Method scala/runtime/AbstractFunction1."<init>":()V
	return
  Labels:
   	l1 = 12 // aload_0
  LocalVariableTable: 
   Start  Length  Slot  Name   Signature
   0      27      0    this       Lscala/runtime/RichDouble$$anonfun$to$1;
   0      27      1    $outer       Lscala/runtime/RichDouble;


}

