Compiled from "RichString.scala"
public final class scala.runtime.RichString$$anonfun$1 extends java.lang.Object implements scala.Function2,scala.ScalaObject,java.io.Serializable
  SourceFile: "RichString.scala"
  Scala: length = 0x
   
  InnerClass: 
   public final #73= #15 of #54; //$anonfun$1=class scala/runtime/RichString$$anonfun$1 of class scala/runtime/RichString
  minor version: 0
  major version: 49
  Constant pool:
const #1 = Asciz	SourceFile;
const #2 = Asciz	RichString.scala;
const #3 = Asciz	$outer;
const #4 = Asciz	Lscala/runtime/RichString;;
const #5 = Asciz	<init>;
const #6 = Asciz	(Lscala/runtime/RichString;)V;
const #7 = Asciz	Code;
const #8 = Asciz	LineNumberTable;
const #9 = Asciz	java/lang/NullPointerException;
const #10 = class	#9;	//  java/lang/NullPointerException
const #11 = Asciz	()V;
const #12 = NameAndType	#5:#11;//  "<init>":()V
const #13 = Method	#10.#12;	//  java/lang/NullPointerException."<init>":()V
const #14 = Asciz	scala/runtime/RichString$$anonfun$1;
const #15 = class	#14;	//  scala/runtime/RichString$$anonfun$1
const #16 = NameAndType	#3:#4;//  $outer:Lscala/runtime/RichString;
const #17 = Field	#15.#16;	//  scala/runtime/RichString$$anonfun$1.$outer:Lscala/runtime/RichString;
const #18 = Asciz	java/lang/Object;
const #19 = class	#18;	//  java/lang/Object
const #20 = Method	#19.#12;	//  java/lang/Object."<init>":()V
const #21 = Asciz	scala/Function2$class;
const #22 = class	#21;	//  scala/Function2$class
const #23 = Asciz	$init$;
const #24 = Asciz	(Lscala/Function2;)V;
const #25 = NameAndType	#23:#24;//  $init$:(Lscala/Function2;)V
const #26 = Method	#22.#25;	//  scala/Function2$class.$init$:(Lscala/Function2;)V
const #27 = Asciz	this;
const #28 = Asciz	Lscala/runtime/RichString$$anonfun$1;;
const #29 = Asciz	LocalVariableTable;
const #30 = Asciz	apply;
const #31 = Asciz	(Ljava/lang/Object;Ljava/lang/Object;)Ljava/lang/Object;;
const #32 = Asciz	java/lang/String;
const #33 = class	#32;	//  java/lang/String
const #34 = Asciz	scala/runtime/BoxesRunTime;
const #35 = class	#34;	//  scala/runtime/BoxesRunTime
const #36 = Asciz	unboxToChar;
const #37 = Asciz	(Ljava/lang/Object;)C;
const #38 = NameAndType	#36:#37;//  unboxToChar:(Ljava/lang/Object;)C
const #39 = Method	#35.#38;	//  scala/runtime/BoxesRunTime.unboxToChar:(Ljava/lang/Object;)C
const #40 = Asciz	(Ljava/lang/String;C)Ljava/lang/String;;
const #41 = NameAndType	#30:#40;//  apply:(Ljava/lang/String;C)Ljava/lang/String;
const #42 = Method	#15.#41;	//  scala/runtime/RichString$$anonfun$1.apply:(Ljava/lang/String;C)Ljava/lang/String;
const #43 = Asciz	v1;
const #44 = Asciz	Ljava/lang/Object;;
const #45 = Asciz	v2;
const #46 = Asciz	scala/collection/mutable/StringBuilder;
const #47 = class	#46;	//  scala/collection/mutable/StringBuilder
const #48 = Method	#47.#12;	//  scala/collection/mutable/StringBuilder."<init>":()V
const #49 = Asciz	append;
const #50 = Asciz	(Ljava/lang/Object;)Lscala/collection/mutable/StringBuilder;;
const #51 = NameAndType	#49:#50;//  append:(Ljava/lang/Object;)Lscala/collection/mutable/StringBuilder;
const #52 = Method	#47.#51;	//  scala/collection/mutable/StringBuilder.append:(Ljava/lang/Object;)Lscala/collection/mutable/StringBuilder;
const #53 = Asciz	scala/runtime/RichString;
const #54 = class	#53;	//  scala/runtime/RichString
const #55 = Asciz	scala$runtime$RichString$$escape;
const #56 = Asciz	(C)Ljava/lang/String;;
const #57 = NameAndType	#55:#56;//  scala$runtime$RichString$$escape:(C)Ljava/lang/String;
const #58 = Method	#54.#57;	//  scala/runtime/RichString.scala$runtime$RichString$$escape:(C)Ljava/lang/String;
const #59 = Asciz	toString;
const #60 = Asciz	()Ljava/lang/String;;
const #61 = NameAndType	#59:#60;//  toString:()Ljava/lang/String;
const #62 = Method	#47.#61;	//  scala/collection/mutable/StringBuilder.toString:()Ljava/lang/String;
const #63 = Asciz	curry;
const #64 = Asciz	()Lscala/Function1;;
const #65 = Asciz	(Lscala/Function2;)Lscala/Function1;;
const #66 = NameAndType	#63:#65;//  curry:(Lscala/Function2;)Lscala/Function1;
const #67 = Method	#22.#66;	//  scala/Function2$class.curry:(Lscala/Function2;)Lscala/Function1;
const #68 = Asciz	(Lscala/Function2;)Ljava/lang/String;;
const #69 = NameAndType	#59:#68;//  toString:(Lscala/Function2;)Ljava/lang/String;
const #70 = Method	#22.#69;	//  scala/Function2$class.toString:(Lscala/Function2;)Ljava/lang/String;
const #71 = Asciz	Scala;
const #72 = Asciz	InnerClasses;
const #73 = Asciz	$anonfun$1;
const #74 = Asciz	scala/Function2;
const #75 = class	#74;	//  scala/Function2
const #76 = Asciz	scala/ScalaObject;
const #77 = class	#76;	//  scala/ScalaObject
const #78 = Asciz	java/io/Serializable;
const #79 = class	#78;	//  java/io/Serializable

{
public scala.runtime.RichString$$anonfun$1(scala.runtime.RichString);
  Code:
   Stack=2, Locals=2, Args_size=2
   0:	aload_1
   1:	ifnonnull	12
   4:	new	#10; //class java/lang/NullPointerException
   7:	dup
   8:	invokespecial	#13; //Method java/lang/NullPointerException."<init>":()V
   11:	athrow
   12:	aload_0
   13:	aload_1
   14:	putfield	#17; //Field $outer:Lscala/runtime/RichString;
   17:	aload_0
   18:	invokespecial	#20; //Method java/lang/Object."<init>":()V
   21:	aload_0
   22:	invokestatic	#26; //Method scala/Function2$class.$init$:(Lscala/Function2;)V
   25:	return
  LineNumberTable: 
   line 174: 0

  LocalVariableTable: 
   Start  Length  Slot  Name   Signature
   0      26      0    this       Lscala/runtime/RichString$$anonfun$1;
   0      26      1    $outer       Lscala/runtime/RichString;


public final java.lang.Object apply(java.lang.Object, java.lang.Object);
  Code:
   Stack=3, Locals=4, Args_size=3
   0:	aload_0
   1:	getfield	#17; //Field $outer:Lscala/runtime/RichString;
   4:	astore_3
   5:	aload_0
   6:	aload_1
   7:	checkcast	#33; //class java/lang/String
   10:	aload_2
   11:	invokestatic	#39; //Method scala/runtime/BoxesRunTime.unboxToChar:(Ljava/lang/Object;)C
   14:	invokevirtual	#42; //Method apply:(Ljava/lang/String;C)Ljava/lang/String;
   17:	areturn
  LineNumberTable: 
   line 174: 0

  LocalVariableTable: 
   Start  Length  Slot  Name   Signature
   0      18      0    this       Lscala/runtime/RichString$$anonfun$1;
   5      13      1    v1       Ljava/lang/Object;
   5      13      2    v2       Ljava/lang/Object;


public final java.lang.String apply(java.lang.String, char);
  Code:
   Stack=3, Locals=4, Args_size=3
   0:	aload_0
   1:	getfield	#17; //Field $outer:Lscala/runtime/RichString;
   4:	astore_3
   5:	new	#47; //class scala/collection/mutable/StringBuilder
   8:	dup
   9:	invokespecial	#48; //Method scala/collection/mutable/StringBuilder."<init>":()V
   12:	aload_1
   13:	invokevirtual	#52; //Method scala/collection/mutable/StringBuilder.append:(Ljava/lang/Object;)Lscala/collection/mutable/StringBuilder;
   16:	aload_0
   17:	getfield	#17; //Field $outer:Lscala/runtime/RichString;
   20:	iload_2
   21:	invokevirtual	#58; //Method scala/runtime/RichString.scala$runtime$RichString$$escape:(C)Ljava/lang/String;
   24:	invokevirtual	#52; //Method scala/collection/mutable/StringBuilder.append:(Ljava/lang/Object;)Lscala/collection/mutable/StringBuilder;
   27:	invokevirtual	#62; //Method scala/collection/mutable/StringBuilder.toString:()Ljava/lang/String;
   30:	areturn
  LineNumberTable: 
   line 174: 0

  LocalVariableTable: 
   Start  Length  Slot  Name   Signature
   0      31      0    this       Lscala/runtime/RichString$$anonfun$1;


public scala.Function1 curry();
  Code:
   Stack=1, Locals=1, Args_size=1
   0:	aload_0
   1:	invokestatic	#67; //Method scala/Function2$class.curry:(Lscala/Function2;)Lscala/Function1;
   4:	areturn
  LineNumberTable: 
   line 174: 0


public java.lang.String toString();
  Code:
   Stack=1, Locals=1, Args_size=1
   0:	aload_0
   1:	invokestatic	#70; //Method scala/Function2$class.toString:(Lscala/Function2;)Ljava/lang/String;
   4:	areturn
  LineNumberTable: 
   line 174: 0


}

