Compiled from "ScalaRunTime.scala"
public final class scala.runtime.ScalaRunTime$$anonfun$toObjectArray$1 extends java.lang.Object implements scala.Function1,scala.ScalaObject,java.io.Serializable
  SourceFile: "ScalaRunTime.scala"
  Scala: length = 0x
   
  InnerClass: 
   public final $anonfun$toObjectArray$1=class scala/runtime/ScalaRunTime$$anonfun$toObjectArray$1 of class scala/runtime/ScalaRunTime
  minor version: 0
  major version: 49
  Constant pool:
Asciz	SourceFile;
Asciz	ScalaRunTime.scala;
Asciz	<clinit>;
Asciz	()V;
Asciz	Code;
Asciz	serialVersionUID;
Asciz	J;
Asciz	scala/runtime/ScalaRunTime$$anonfun$toObjectArray$1;
class	scala/runtime/ScalaRunTime$$anonfun$toObjectArray$1
NameAndType	serialVersionUID:J
Field	scala/runtime/ScalaRunTime$$anonfun$toObjectArray$1.serialVersionUID:J
Asciz	dest$1;
Asciz	[Ljava/lang/Object;;
Asciz	src$1;
Asciz	Ljava/lang/Object;;
Asciz	<init>;
Asciz	(Ljava/lang/Object;[Ljava/lang/Object;)V;
Asciz	LineNumberTable;
NameAndType	src$1:Ljava/lang/Object;
Field	scala/runtime/ScalaRunTime$$anonfun$toObjectArray$1.src$1:Ljava/lang/Object;
NameAndType	dest$1:[Ljava/lang/Object;
Field	scala/runtime/ScalaRunTime$$anonfun$toObjectArray$1.dest$1:[Ljava/lang/Object;
Asciz	java/lang/Object;
class	java/lang/Object
NameAndType	"<init>":()V
Method	java/lang/Object."<init>":()V
Asciz	scala/Function1$class;
class	scala/Function1$class
Asciz	$init$;
Asciz	(Lscala/Function1;)V;
NameAndType	$init$:(Lscala/Function1;)V
Method	scala/Function1$class.$init$:(Lscala/Function1;)V
Asciz	apply;
Asciz	(Ljava/lang/Object;)Ljava/lang/Object;;
Asciz	scala/runtime/BoxesRunTime;
class	scala/runtime/BoxesRunTime
Asciz	unboxToInt;
Asciz	(Ljava/lang/Object;)I;
NameAndType	unboxToInt:(Ljava/lang/Object;)I
Method	scala/runtime/BoxesRunTime.unboxToInt:(Ljava/lang/Object;)I
Asciz	(I)V;
NameAndType	apply:(I)V
Method	scala/runtime/ScalaRunTime$$anonfun$toObjectArray$1.apply:(I)V
Asciz	scala/runtime/BoxedUnit;
class	scala/runtime/BoxedUnit
Asciz	UNIT;
Asciz	Lscala/runtime/BoxedUnit;;
NameAndType	UNIT:Lscala/runtime/BoxedUnit;
Field	scala/runtime/BoxedUnit.UNIT:Lscala/runtime/BoxedUnit;
Asciz	this;
Asciz	Lscala/runtime/ScalaRunTime$$anonfun$toObjectArray$1;;
Asciz	v1;
Asciz	LocalVariableTable;
Asciz	scala/runtime/ScalaRunTime$;
class	scala/runtime/ScalaRunTime$
Asciz	MODULE$;
Asciz	Lscala/runtime/ScalaRunTime$;;
NameAndType	MODULE$:Lscala/runtime/ScalaRunTime$;
Field	scala/runtime/ScalaRunTime$.MODULE$:Lscala/runtime/ScalaRunTime$;
Asciz	array_apply;
Asciz	(Ljava/lang/Object;I)Ljava/lang/Object;;
NameAndType	array_apply:(Ljava/lang/Object;I)Ljava/lang/Object;
Method	scala/runtime/ScalaRunTime$.array_apply:(Ljava/lang/Object;I)Ljava/lang/Object;
Asciz	array_update;
Asciz	(Ljava/lang/Object;ILjava/lang/Object;)V;
NameAndType	array_update:(Ljava/lang/Object;ILjava/lang/Object;)V
Method	scala/runtime/ScalaRunTime$.array_update:(Ljava/lang/Object;ILjava/lang/Object;)V
Asciz	i;
Asciz	I;
Asciz	andThen;
Asciz	(Lscala/Function1;)Lscala/Function1;;
Asciz	(Lscala/Function1;Lscala/Function1;)Lscala/Function1;;
NameAndType	andThen:(Lscala/Function1;Lscala/Function1;)Lscala/Function1;
Method	scala/Function1$class.andThen:(Lscala/Function1;Lscala/Function1;)Lscala/Function1;
Asciz	g;
Asciz	Lscala/Function1;;
Asciz	compose;
NameAndType	compose:(Lscala/Function1;Lscala/Function1;)Lscala/Function1;
Method	scala/Function1$class.compose:(Lscala/Function1;Lscala/Function1;)Lscala/Function1;
Asciz	toString;
Asciz	()Ljava/lang/String;;
Asciz	(Lscala/Function1;)Ljava/lang/String;;
NameAndType	toString:(Lscala/Function1;)Ljava/lang/String;
Method	scala/Function1$class.toString:(Lscala/Function1;)Ljava/lang/String;
Asciz	Scala;
Asciz	InnerClasses;
Asciz	scala/runtime/ScalaRunTime;
class	scala/runtime/ScalaRunTime
Asciz	$anonfun$toObjectArray$1;
Asciz	scala/Function1;
class	scala/Function1
Asciz	scala/ScalaObject;
class	scala/ScalaObject
Asciz	java/io/Serializable;
class	java/io/Serializable

{
public static final long serialVersionUID;
  Signature: J

private final java.lang.Object[] dest$1;
  Signature: [Ljava/lang/Object;

private final java.lang.Object src$1;
  Signature: Ljava/lang/Object;

public static {};
  Signature: ()V
  Code:
   Stack=2, Locals=0, Args_size=0
	lconst_0
	putstatic	Field serialVersionUID:J
	return
  Labels:

public scala.runtime.ScalaRunTime$$anonfun$toObjectArray$1(java.lang.Object, java.lang.Object[]);
  Signature: (Ljava/lang/Object;[Ljava/lang/Object;)V
  Code:
   Stack=2, Locals=3, Args_size=3
	aload_0
	aload_1
	putfield	Field src$1:Ljava/lang/Object;
	aload_0
	aload_2
	putfield	Field dest$1:[Ljava/lang/Object;
	aload_0
	invokespecial	Method java/lang/Object."<init>":()V
	aload_0
	invokestatic	Method scala/Function1$class.$init$:(Lscala/Function1;)V
	return
  Labels:

public final java.lang.Object apply(java.lang.Object);
  Signature: (Ljava/lang/Object;)Ljava/lang/Object;
  Code:
   Stack=2, Locals=2, Args_size=2
	aload_0
	aload_1
	invokestatic	Method scala/runtime/BoxesRunTime.unboxToInt:(Ljava/lang/Object;)I
	invokevirtual	Method apply:(I)V
	getstatic	Field scala/runtime/BoxedUnit.UNIT:Lscala/runtime/BoxedUnit;
	areturn
  Labels:
  LocalVariableTable: 
   Start  Length  Slot  Name   Signature
   0      12      0    this       Lscala/runtime/ScalaRunTime$$anonfun$toObjectArray$1;
   0      12      1    v1       Ljava/lang/Object;


public final void apply(int);
  Signature: (I)V
  Code:
   Stack=6, Locals=2, Args_size=2
	getstatic	Field scala/runtime/ScalaRunTime$.MODULE$:Lscala/runtime/ScalaRunTime$;
	aload_0
	getfield	Field dest$1:[Ljava/lang/Object;
	iload_1
	getstatic	Field scala/runtime/ScalaRunTime$.MODULE$:Lscala/runtime/ScalaRunTime$;
	aload_0
	getfield	Field src$1:Ljava/lang/Object;
	iload_1
	invokevirtual	Method scala/runtime/ScalaRunTime$.array_apply:(Ljava/lang/Object;I)Ljava/lang/Object;
	invokevirtual	Method scala/runtime/ScalaRunTime$.array_update:(Ljava/lang/Object;ILjava/lang/Object;)V
	return
  Labels:
  LocalVariableTable: 
   Start  Length  Slot  Name   Signature
   0      23      0    this       Lscala/runtime/ScalaRunTime$$anonfun$toObjectArray$1;
   0      23      1    i       I


public scala.Function1 andThen(scala.Function1);
  Signature: (Lscala/Function1;)Lscala/Function1;
  Code:
   Stack=2, Locals=2, Args_size=2
	aload_0
	aload_1
	invokestatic	Method scala/Function1$class.andThen:(Lscala/Function1;Lscala/Function1;)Lscala/Function1;
	areturn
  Labels:
  LocalVariableTable: 
   Start  Length  Slot  Name   Signature
   0      6      0    this       Lscala/runtime/ScalaRunTime$$anonfun$toObjectArray$1;
   0      6      1    g       Lscala/Function1;


public scala.Function1 compose(scala.Function1);
  Signature: (Lscala/Function1;)Lscala/Function1;
  Code:
   Stack=2, Locals=2, Args_size=2
	aload_0
	aload_1
	invokestatic	Method scala/Function1$class.compose:(Lscala/Function1;Lscala/Function1;)Lscala/Function1;
	areturn
  Labels:
  LocalVariableTable: 
   Start  Length  Slot  Name   Signature
   0      6      0    this       Lscala/runtime/ScalaRunTime$$anonfun$toObjectArray$1;
   0      6      1    g       Lscala/Function1;


public java.lang.String toString();
  Signature: ()Ljava/lang/String;
  Code:
   Stack=1, Locals=1, Args_size=1
	aload_0
	invokestatic	Method scala/Function1$class.toString:(Lscala/Function1;)Ljava/lang/String;
	areturn
  Labels:

}

