Compiled from "ScalaRunTime.scala"
public abstract class scala.runtime.ScalaRunTime$Try extends java.lang.Object implements scala.ScalaObject
  SourceFile: "ScalaRunTime.scala"
  Signature: length = 0x2
   00 12 
  Scala: length = 0x
   
  InnerClass: 
   public abstract #25= #22 of #24; //Try=class scala/runtime/ScalaRunTime$Try of class scala/runtime/ScalaRunTime
  minor version: 0
  major version: 49
  Constant pool:
const #1 = Asciz	SourceFile;
const #2 = Asciz	ScalaRunTime.scala;
const #3 = Asciz	<init>;
const #4 = Asciz	()V;
const #5 = Asciz	Code;
const #6 = Asciz	LineNumberTable;
const #7 = Asciz	java/lang/Object;
const #8 = class	#7;	//  java/lang/Object
const #9 = NameAndType	#3:#4;//  "<init>":()V
const #10 = Method	#8.#9;	//  java/lang/Object."<init>":()V
const #11 = Asciz	Signature;
const #12 = Asciz	Finally;
const #13 = Asciz	(Lscala/runtime/BoxedUnit;)Ljava/lang/Object;;
const #14 = Asciz	(Lscala/runtime/BoxedUnit;)Ta;;
const #15 = Asciz	Catch;
const #16 = Asciz	(Lscala/PartialFunction;)Ljava/lang/Object;;
const #17 = Asciz	<b:Ljava/lang/Object;>(Lscala/PartialFunction<Ljava/lang/Throwable;Tb;>;)Tb;;
const #18 = Asciz	<a:Ljava/lang/Object;>Ljava/lang/Object;Lscala/ScalaObject;;
const #19 = Asciz	Scala;
const #20 = Asciz	InnerClasses;
const #21 = Asciz	scala/runtime/ScalaRunTime$Try;
const #22 = class	#21;	//  scala/runtime/ScalaRunTime$Try
const #23 = Asciz	scala/runtime/ScalaRunTime;
const #24 = class	#23;	//  scala/runtime/ScalaRunTime
const #25 = Asciz	Try;
const #26 = Asciz	scala/ScalaObject;
const #27 = class	#26;	//  scala/ScalaObject

{
public scala.runtime.ScalaRunTime$Try();
  Code:
   Stack=1, Locals=1, Args_size=1
   0:	aload_0
   1:	invokespecial	#10; //Method java/lang/Object."<init>":()V
   4:	return
  LineNumberTable: 
   line 31: 0

  Signature: length = 0x2
   00 04 

public abstract java.lang.Object Finally(scala.runtime.BoxedUnit);
  Signature: length = 0x2
   00 0E 

public abstract java.lang.Object Catch(scala.PartialFunction);
  Signature: length = 0x2
   00 11 

}

