Compiled from "StreamCons.scala"
public final class scala.runtime.StreamCons extends java.lang.Object implements scala.ScalaObject
  SourceFile: "StreamCons.scala"
  Signature: length = 0x2
   00 32 
  ScalaSig: length = 0x180
   05 00 41 06 04 01 02 02 07 02 0A 53 74 72 65 61
   6D 43 6F 6E 73 0A 02 03 04 01 07 72 75 6E 74 69
   6D 65 0A 01 05 01 05 73 63 61 6C 61 03 00 15 02
   08 28 13 03 00 09 11 10 02 0A 0F 0D 01 0B 0A 02
   0C 0D 01 04 6C 61 6E 67 0A 01 0E 01 04 6A 61 76
   61 09 02 10 0B 02 06 4F 62 6A 65 63 74 10 02 12
   13 0D 01 04 09 02 14 04 02 0B 53 63 61 6C 61 4F
   62 6A 65 63 74 08 08 16 00 FFFFFF82 FFFFFF80 FFFFFFA4 FFFFFF80 04 17 01
   02 78 73 10 03 12 18 1A 09 02 19 04 02 08 3C 62
   79 6E 61 6D 65 3E 10 03 1B 23 26 0E 02 1C 21 0E
   02 1D 20 0D 01 1E 0A 02 1F 06 01 06 3C 72 6F 6F
   74 3E 09 01 05 09 02 22 04 01 07 70 61 63 6B 61
   67 65 09 02 24 25 02 06 53 74 72 65 61 6D 0A 02
   22 04 10 02 27 28 0C 00 04 08 29 00 FFFFFF84 FFFFFF80 FFFFFF80 FFFFFFC2
   00 2A 02 01 54 11 02 2B 2E 10 02 12 2C 09 02 2D
   04 02 07 4E 6F 74 68 69 6E 67 10 02 12 2F 09 02
   30 04 02 03 41 6E 79 08 05 32 00 FFFFFF84 00 33 01 06
   3C 69 6E 69 74 3E 14 02 34 36 10 03 35 00 26 0D
   01 02 08 05 16 31 FFFFFFC0 00 17 08 05 38 00 FFFFFF84 00 39
   01 11 6C 61 7A 79 5F 24 63 6F 6C 6F 6E 24 63 6F
   6C 6F 6E 14 02 1A 3A 08 05 3B 37 FFFFFFC0 00 26 01 01
   78 08 05 3D 00 FFFFFF84 00 3E 01 17 6C 61 7A 79 5F 24
   63 6F 6C 6F 6E 24 63 6F 6C 6F 6E 24 63 6F 6C 6F
   6E 14 02 1A 3F 08 05 40 3C FFFFFFC0 00 1A 01 02 79 73
   
  InnerClass: 
   public final #55= #54 of #27; //Cons=class scala/collection/immutable/Stream$Cons of class scala/collection/immutable/Stream
  minor version: 0
  major version: 49
  Constant pool:
const #1 = Asciz	SourceFile;
const #2 = Asciz	StreamCons.scala;
const #3 = Asciz	xs;
const #4 = Asciz	Lscala/Function0;;
const #5 = Asciz	Lscala/Function0<Lscala/collection/immutable/Stream<TT;>;>;;
const #6 = Asciz	Signature;
const #7 = Asciz	<init>;
const #8 = Asciz	(Lscala/Function0;)V;
const #9 = Asciz	Code;
const #10 = Asciz	LineNumberTable;
const #11 = Asciz	scala/runtime/StreamCons;
const #12 = class	#11;	//  scala/runtime/StreamCons
const #13 = NameAndType	#3:#4;//  xs:Lscala/Function0;
const #14 = Field	#12.#13;	//  scala/runtime/StreamCons.xs:Lscala/Function0;
const #15 = Asciz	java/lang/Object;
const #16 = class	#15;	//  java/lang/Object
const #17 = Asciz	()V;
const #18 = NameAndType	#7:#17;//  "<init>":()V
const #19 = Method	#16.#18;	//  java/lang/Object."<init>":()V
const #20 = Asciz	this;
const #21 = Asciz	Lscala/runtime/StreamCons;;
const #22 = Asciz	LocalVariableTable;
const #23 = Asciz	(Lscala/Function0<Lscala/collection/immutable/Stream<TT;>;>;)V;
const #24 = Asciz	lazy_$colon$colon$colon;
const #25 = Asciz	(Lscala/collection/immutable/Stream;)Lscala/collection/immutable/Stream;;
const #26 = Asciz	scala/collection/immutable/Stream;
const #27 = class	#26;	//  scala/collection/immutable/Stream
const #28 = Asciz	append;
const #29 = Asciz	(Lscala/Function0;)Lscala/collection/immutable/Stream;;
const #30 = NameAndType	#28:#29;//  append:(Lscala/Function0;)Lscala/collection/immutable/Stream;
const #31 = Method	#27.#30;	//  scala/collection/immutable/Stream.append:(Lscala/Function0;)Lscala/collection/immutable/Stream;
const #32 = Asciz	ys;
const #33 = Asciz	Lscala/collection/immutable/Stream;;
const #34 = Asciz	(Lscala/collection/immutable/Stream<TT;>;)Lscala/collection/immutable/Stream<TT;>;;
const #35 = Asciz	lazy_$colon$colon;
const #36 = Asciz	(Ljava/lang/Object;)Lscala/collection/immutable/Stream;;
const #37 = Asciz	scala/collection/immutable/Stream$cons$;
const #38 = class	#37;	//  scala/collection/immutable/Stream$cons$
const #39 = Asciz	MODULE$;
const #40 = Asciz	Lscala/collection/immutable/Stream$cons$;;
const #41 = NameAndType	#39:#40;//  MODULE$:Lscala/collection/immutable/Stream$cons$;
const #42 = Field	#38.#41;	//  scala/collection/immutable/Stream$cons$.MODULE$:Lscala/collection/immutable/Stream$cons$;
const #43 = Asciz	apply;
const #44 = Asciz	(Ljava/lang/Object;Lscala/Function0;)Lscala/collection/immutable/Stream$Cons;;
const #45 = NameAndType	#43:#44;//  apply:(Ljava/lang/Object;Lscala/Function0;)Lscala/collection/immutable/Stream$Cons;
const #46 = Method	#38.#45;	//  scala/collection/immutable/Stream$cons$.apply:(Ljava/lang/Object;Lscala/Function0;)Lscala/collection/immutable/Stream$Cons;
const #47 = Asciz	x;
const #48 = Asciz	Ljava/lang/Object;;
const #49 = Asciz	(TT;)Lscala/collection/immutable/Stream<TT;>;;
const #50 = Asciz	<T:Ljava/lang/Object;>Ljava/lang/Object;Lscala/ScalaObject;;
const #51 = Asciz	ScalaSig;
const #52 = Asciz	InnerClasses;
const #53 = Asciz	scala/collection/immutable/Stream$Cons;
const #54 = class	#53;	//  scala/collection/immutable/Stream$Cons
const #55 = Asciz	Cons;
const #56 = Asciz	scala/ScalaObject;
const #57 = class	#56;	//  scala/ScalaObject

{
public scala.runtime.StreamCons(scala.Function0);
  Code:
   Stack=2, Locals=2, Args_size=2
   0:	aload_0
   1:	aload_1
   2:	putfield	#14; //Field xs:Lscala/Function0;
   5:	aload_0
   6:	invokespecial	#19; //Method java/lang/Object."<init>":()V
   9:	return
  LineNumberTable: 
   line 14: 0

  LocalVariableTable: 
   Start  Length  Slot  Name   Signature
   0      10      0    this       Lscala/runtime/StreamCons;
   0      10      1    xs       Lscala/Function0;

  Signature: length = 0x2
   00 17 

public scala.collection.immutable.Stream lazy_$colon$colon$colon(scala.collection.immutable.Stream);
  Code:
   Stack=2, Locals=2, Args_size=2
   0:	aload_1
   1:	aload_0
   2:	getfield	#14; //Field xs:Lscala/Function0;
   5:	invokevirtual	#31; //Method scala/collection/immutable/Stream.append:(Lscala/Function0;)Lscala/collection/immutable/Stream;
   8:	areturn
  LineNumberTable: 
   line 16: 0

  LocalVariableTable: 
   Start  Length  Slot  Name   Signature
   0      9      0    this       Lscala/runtime/StreamCons;
   0      9      1    ys       Lscala/collection/immutable/Stream;

  Signature: length = 0x2
   00 22 

public scala.collection.immutable.Stream lazy_$colon$colon(java.lang.Object);
  Code:
   Stack=3, Locals=2, Args_size=2
   0:	getstatic	#42; //Field scala/collection/immutable/Stream$cons$.MODULE$:Lscala/collection/immutable/Stream$cons$;
   3:	aload_1
   4:	aload_0
   5:	getfield	#14; //Field xs:Lscala/Function0;
   8:	invokevirtual	#46; //Method scala/collection/immutable/Stream$cons$.apply:(Ljava/lang/Object;Lscala/Function0;)Lscala/collection/immutable/Stream$Cons;
   11:	areturn
  LineNumberTable: 
   line 15: 0

  LocalVariableTable: 
   Start  Length  Slot  Name   Signature
   0      12      0    this       Lscala/runtime/StreamCons;
   0      12      1    x       Ljava/lang/Object;

  Signature: length = 0x2
   00 31 

}

