Compiled from "Manifest.scala"
public abstract class scala.reflect.AnyValManifest$class extends java.lang.Object
  SourceFile: "Manifest.scala"
  Scala: length = 0x
   
  minor version: 0
  major version: 49
  Constant pool:
const #1 = Asciz	SourceFile;
const #2 = Asciz	Manifest.scala;
const #3 = Asciz	$init$;
const #4 = Asciz	(Lscala/reflect/AnyValManifest;)V;
const #5 = Asciz	Code;
const #6 = Asciz	LineNumberTable;
const #7 = Asciz	$this;
const #8 = Asciz	Lscala/reflect/AnyValManifest;;
const #9 = Asciz	LocalVariableTable;
const #10 = Asciz	equals;
const #11 = Asciz	(Lscala/reflect/AnyValManifest;Ljava/lang/Object;)Z;
const #12 = Asciz	that;
const #13 = Asciz	Ljava/lang/Object;;
const #14 = Asciz	$less$colon$less;
const #15 = Asciz	(Lscala/reflect/AnyValManifest;Lscala/reflect/ClassManifest;)Z;
const #16 = Asciz	scala/reflect/Manifest$;
const #17 = class	#16;	//  scala/reflect/Manifest$
const #18 = Asciz	MODULE$;
const #19 = Asciz	Lscala/reflect/Manifest$;;
const #20 = NameAndType	#18:#19;//  MODULE$:Lscala/reflect/Manifest$;
const #21 = Field	#17.#20;	//  scala/reflect/Manifest$.MODULE$:Lscala/reflect/Manifest$;
const #22 = Asciz	Any;
const #23 = Asciz	()Lscala/reflect/Manifest;;
const #24 = NameAndType	#22:#23;//  Any:()Lscala/reflect/Manifest;
const #25 = Method	#17.#24;	//  scala/reflect/Manifest$.Any:()Lscala/reflect/Manifest;
const #26 = Asciz	AnyVal;
const #27 = NameAndType	#26:#23;//  AnyVal:()Lscala/reflect/Manifest;
const #28 = Method	#17.#27;	//  scala/reflect/Manifest$.AnyVal:()Lscala/reflect/Manifest;
const #29 = Asciz	Lscala/reflect/ClassManifest;;
const #30 = Asciz	Scala;
const #31 = Asciz	scala/reflect/AnyValManifest$class;
const #32 = class	#31;	//  scala/reflect/AnyValManifest$class
const #33 = Asciz	java/lang/Object;
const #34 = class	#33;	//  java/lang/Object

{
public static void $init$(scala.reflect.AnyValManifest);
  Code:
   Stack=0, Locals=1, Args_size=1
   0:	return
  LineNumberTable: 
   line 38: 0

  LocalVariableTable: 
   Start  Length  Slot  Name   Signature
   0      1      0    $this       Lscala/reflect/AnyValManifest;


public static boolean equals(scala.reflect.AnyValManifest, java.lang.Object);
  Code:
   Stack=2, Locals=2, Args_size=2
   0:	aload_0
   1:	aload_1
   2:	if_acmpne	9
   5:	iconst_1
   6:	goto	10
   9:	iconst_0
   10:	ireturn
  LineNumberTable: 
   line 41: 0

  LocalVariableTable: 
   Start  Length  Slot  Name   Signature
   0      11      0    $this       Lscala/reflect/AnyValManifest;
   0      11      1    that       Ljava/lang/Object;


public static boolean $less$colon$less(scala.reflect.AnyValManifest, scala.reflect.ClassManifest);
  Code:
   Stack=2, Locals=2, Args_size=2
   0:	aload_1
   1:	aload_0
   2:	if_acmpeq	25
   5:	aload_1
   6:	getstatic	#21; //Field scala/reflect/Manifest$.MODULE$:Lscala/reflect/Manifest$;
   9:	invokevirtual	#25; //Method scala/reflect/Manifest$.Any:()Lscala/reflect/Manifest;
   12:	if_acmpeq	25
   15:	aload_1
   16:	getstatic	#21; //Field scala/reflect/Manifest$.MODULE$:Lscala/reflect/Manifest$;
   19:	invokevirtual	#28; //Method scala/reflect/Manifest$.AnyVal:()Lscala/reflect/Manifest;
   22:	if_acmpne	29
   25:	iconst_1
   26:	goto	30
   29:	iconst_0
   30:	ireturn
  LineNumberTable: 
   line 40: 0

  LocalVariableTable: 
   Start  Length  Slot  Name   Signature
   0      31      0    $this       Lscala/reflect/AnyValManifest;
   0      31      1    that       Lscala/reflect/ClassManifest;


}

