Compiled from "Manifest.scala"
public abstract class scala.reflect.AnyValManifest$class extends java.lang.Object
  Scala: length = 0x
   
  SourceFile: "Manifest.scala"
  minor version: 0
  major version: 49
  Constant pool:
class	java/lang/Object
class	java/lang/System
class	scala/reflect/AnyValManifest
class	scala/reflect/AnyValManifest$class
class	scala/reflect/Manifest$
Field	scala/reflect/Manifest$.MODULE$:Lscala/reflect/Manifest$;
Method	java/lang/System.identityHashCode:(Ljava/lang/Object;)I
Method	scala/reflect/Manifest$.Any:()Lscala/reflect/Manifest;
Method	scala/reflect/Manifest$.AnyVal:()Lscala/reflect/Manifest;
NameAndType	Any:()Lscala/reflect/Manifest;
NameAndType	AnyVal:()Lscala/reflect/Manifest;
NameAndType	MODULE$:Lscala/reflect/Manifest$;
NameAndType	identityHashCode:(Ljava/lang/Object;)I
Asciz	$init$;
Asciz	$less$colon$less;
Asciz	$this;
Asciz	()Lscala/reflect/Manifest;;
Asciz	(Ljava/lang/Object;)I;
Asciz	(Lscala/reflect/AnyValManifest;)I;
Asciz	(Lscala/reflect/AnyValManifest;)V;
Asciz	(Lscala/reflect/AnyValManifest;Ljava/lang/Object;)Z;
Asciz	(Lscala/reflect/AnyValManifest;Lscala/reflect/ClassManifest;)Z;
Asciz	Any;
Asciz	AnyVal;
Asciz	Code;
Asciz	LineNumberTable;
Asciz	Ljava/lang/Object;;
Asciz	LocalVariableTable;
Asciz	Lscala/reflect/AnyValManifest;;
Asciz	Lscala/reflect/ClassManifest;;
Asciz	Lscala/reflect/Manifest$;;
Asciz	MODULE$;
Asciz	Manifest.scala;
Asciz	Scala;
Asciz	SourceFile;
Asciz	canEqual;
Asciz	equals;
Asciz	hashCode;
Asciz	identityHashCode;
Asciz	java/lang/Object;
Asciz	java/lang/System;
Asciz	other;
Asciz	scala/reflect/AnyValManifest;
Asciz	scala/reflect/AnyValManifest$class;
Asciz	scala/reflect/Manifest$;
Asciz	that;

{
public static boolean $less$colon$less(scala.reflect.AnyValManifest, scala.reflect.ClassManifest);
  Signature: (Lscala/reflect/AnyValManifest;Lscala/reflect/ClassManifest;)Z
  Code:
   Stack=2, Locals=2, Args_size=2
	aload_1
	aload_0
	if_acmpeq	l1 // iconst_1
	aload_1
	getstatic	Field scala/reflect/Manifest$.MODULE$:Lscala/reflect/Manifest$;
	invokevirtual	Method scala/reflect/Manifest$.Any:()Lscala/reflect/Manifest;
	if_acmpeq	l1 // iconst_1
	aload_1
	getstatic	Field scala/reflect/Manifest$.MODULE$:Lscala/reflect/Manifest$;
	invokevirtual	Method scala/reflect/Manifest$.AnyVal:()Lscala/reflect/Manifest;
	if_acmpne	l2 // iconst_0
l1	iconst_1
	goto	l3 // ireturn
l2	iconst_0
l3	ireturn
  Labels:
   	l1 = 25 // iconst_1
   	l2 = 29 // iconst_0
   	l3 = 30 // ireturn
  LocalVariableTable: 
   Start  Length  Slot  Name   Signature
   0      31      0    $this       Lscala/reflect/AnyValManifest;
   0      31      1    that       Lscala/reflect/ClassManifest;


public static boolean canEqual(scala.reflect.AnyValManifest, java.lang.Object);
  Signature: (Lscala/reflect/AnyValManifest;Ljava/lang/Object;)Z
  Code:
   Stack=1, Locals=2, Args_size=2
	aload_1
	instanceof	class scala/reflect/AnyValManifest
	ireturn
  Labels:
  LocalVariableTable: 
   Start  Length  Slot  Name   Signature
   0      5      0    $this       Lscala/reflect/AnyValManifest;
   0      5      1    other       Ljava/lang/Object;


public static boolean equals(scala.reflect.AnyValManifest, java.lang.Object);
  Signature: (Lscala/reflect/AnyValManifest;Ljava/lang/Object;)Z
  Code:
   Stack=2, Locals=2, Args_size=2
	aload_0
	aload_1
	if_acmpne	l1 // iconst_0
	iconst_1
	goto	l2 // ireturn
l1	iconst_0
l2	ireturn
  Labels:
   	l1 = 9 // iconst_0
   	l2 = 10 // ireturn
  LocalVariableTable: 
   Start  Length  Slot  Name   Signature
   0      11      0    $this       Lscala/reflect/AnyValManifest;
   0      11      1    that       Ljava/lang/Object;


public static int hashCode(scala.reflect.AnyValManifest);
  Signature: (Lscala/reflect/AnyValManifest;)I
  Code:
   Stack=1, Locals=1, Args_size=1
	aload_0
	invokestatic	Method java/lang/System.identityHashCode:(Ljava/lang/Object;)I
	ireturn
  Labels:
  LocalVariableTable: 
   Start  Length  Slot  Name   Signature
   0      5      0    $this       Lscala/reflect/AnyValManifest;


public static void $init$(scala.reflect.AnyValManifest);
  Signature: (Lscala/reflect/AnyValManifest;)V
  Code:
   Stack=0, Locals=1, Args_size=1
	return
  Labels:
  LocalVariableTable: 
   Start  Length  Slot  Name   Signature
   0      1      0    $this       Lscala/reflect/AnyValManifest;


}

