Compiled from "Type.scala"
public final class scala.reflect.AppliedType$ extends java.lang.Object implements scala.Function2,scala.ScalaObject
  SourceFile: "Type.scala"
  Scala: length = 0x
   
  minor version: 0
  major version: 49
  Constant pool:
Asciz	SourceFile;
Asciz	Type.scala;
Asciz	Scala;
Asciz	MODULE$;
Asciz	Lscala/reflect/AppliedType$;;
Asciz	<clinit>;
Asciz	()V;
Asciz	Code;
Asciz	scala/reflect/AppliedType$;
class	scala/reflect/AppliedType$
Asciz	<init>;
NameAndType	"<init>":()V
Method	scala/reflect/AppliedType$."<init>":()V
Asciz	LineNumberTable;
Asciz	java/lang/Object;
class	java/lang/Object
Method	java/lang/Object."<init>":()V
NameAndType	MODULE$:Lscala/reflect/AppliedType$;
Field	scala/reflect/AppliedType$.MODULE$:Lscala/reflect/AppliedType$;
Asciz	scala/Function2$class;
class	scala/Function2$class
Asciz	$init$;
Asciz	(Lscala/Function2;)V;
NameAndType	$init$:(Lscala/Function2;)V
Method	scala/Function2$class.$init$:(Lscala/Function2;)V
Asciz	apply;
Asciz	(Ljava/lang/Object;Ljava/lang/Object;)Ljava/lang/Object;;
Asciz	scala/reflect/Type;
class	scala/reflect/Type
Asciz	scala/collection/immutable/List;
class	scala/collection/immutable/List
Asciz	(Lscala/reflect/Type;Lscala/collection/immutable/List;)Lscala/reflect/AppliedType;;
NameAndType	apply:(Lscala/reflect/Type;Lscala/collection/immutable/List;)Lscala/reflect/AppliedType;
Method	scala/reflect/AppliedType$.apply:(Lscala/reflect/Type;Lscala/collection/immutable/List;)Lscala/reflect/AppliedType;
Asciz	this;
Asciz	v1;
Asciz	Ljava/lang/Object;;
Asciz	v2;
Asciz	LocalVariableTable;
Asciz	scala/reflect/AppliedType;
class	scala/reflect/AppliedType
Asciz	(Lscala/reflect/Type;Lscala/collection/immutable/List;)V;
NameAndType	"<init>":(Lscala/reflect/Type;Lscala/collection/immutable/List;)V
Method	scala/reflect/AppliedType."<init>":(Lscala/reflect/Type;Lscala/collection/immutable/List;)V
Asciz	tpe;
Asciz	Lscala/reflect/Type;;
Asciz	args;
Asciz	Lscala/collection/immutable/List;;
Asciz	unapply;
Asciz	(Lscala/reflect/AppliedType;)Lscala/Some;;
Asciz	scala/Some;
class	scala/Some
Asciz	scala/Tuple2;
class	scala/Tuple2
Asciz	()Lscala/reflect/Type;;
NameAndType	tpe:()Lscala/reflect/Type;
Method	scala/reflect/AppliedType.tpe:()Lscala/reflect/Type;
Asciz	()Lscala/collection/immutable/List;;
NameAndType	args:()Lscala/collection/immutable/List;
Method	scala/reflect/AppliedType.args:()Lscala/collection/immutable/List;
Asciz	(Ljava/lang/Object;Ljava/lang/Object;)V;
NameAndType	"<init>":(Ljava/lang/Object;Ljava/lang/Object;)V
Method	scala/Tuple2."<init>":(Ljava/lang/Object;Ljava/lang/Object;)V
Asciz	(Ljava/lang/Object;)V;
NameAndType	"<init>":(Ljava/lang/Object;)V
Method	scala/Some."<init>":(Ljava/lang/Object;)V
Asciz	x$0;
Asciz	Lscala/reflect/AppliedType;;
Asciz	tupled;
Asciz	()Lscala/Function1;;
Asciz	(Lscala/Function2;)Lscala/Function1;;
NameAndType	tupled:(Lscala/Function2;)Lscala/Function1;
Method	scala/Function2$class.tupled:(Lscala/Function2;)Lscala/Function1;
Asciz	curry;
NameAndType	curry:(Lscala/Function2;)Lscala/Function1;
Method	scala/Function2$class.curry:(Lscala/Function2;)Lscala/Function1;
Asciz	Deprecated;
Asciz	curried;
NameAndType	curried:(Lscala/Function2;)Lscala/Function1;
Method	scala/Function2$class.curried:(Lscala/Function2;)Lscala/Function1;
Asciz	toString;
Asciz	()Ljava/lang/String;;
Asciz	(Lscala/Function2;)Ljava/lang/String;;
NameAndType	toString:(Lscala/Function2;)Ljava/lang/String;
Method	scala/Function2$class.toString:(Lscala/Function2;)Ljava/lang/String;
Asciz	scala/Function2;
class	scala/Function2
Asciz	scala/ScalaObject;
class	scala/ScalaObject

{
public static final scala.reflect.AppliedType$ MODULE$;
  Signature: Lscala/reflect/AppliedType$;

public static {};
  Signature: ()V
  Code:
   Stack=1, Locals=0, Args_size=0
	new	class scala/reflect/AppliedType$
	invokespecial	Method "<init>":()V
	return
  Labels:

private scala.reflect.AppliedType$();
  Signature: ()V
  Code:
   Stack=1, Locals=1, Args_size=1
	aload_0
	invokespecial	Method java/lang/Object."<init>":()V
	aload_0
	putstatic	Field MODULE$:Lscala/reflect/AppliedType$;
	aload_0
	invokestatic	Method scala/Function2$class.$init$:(Lscala/Function2;)V
	return
  Labels:

public java.lang.Object apply(java.lang.Object, java.lang.Object);
  Signature: (Ljava/lang/Object;Ljava/lang/Object;)Ljava/lang/Object;
  Code:
   Stack=3, Locals=3, Args_size=3
	aload_0
	aload_1
	checkcast	class scala/reflect/Type
	aload_2
	checkcast	class scala/collection/immutable/List
	invokevirtual	Method apply:(Lscala/reflect/Type;Lscala/collection/immutable/List;)Lscala/reflect/AppliedType;
	areturn
  Labels:
  LocalVariableTable: 
   Start  Length  Slot  Name   Signature
   0      13      0    this       Lscala/reflect/AppliedType$;
   0      13      1    v1       Ljava/lang/Object;
   0      13      2    v2       Ljava/lang/Object;


public scala.reflect.AppliedType apply(scala.reflect.Type, scala.collection.immutable.List);
  Signature: (Lscala/reflect/Type;Lscala/collection/immutable/List;)Lscala/reflect/AppliedType;
  Code:
   Stack=4, Locals=3, Args_size=3
	new	class scala/reflect/AppliedType
	dup
	aload_1
	aload_2
	invokespecial	Method scala/reflect/AppliedType."<init>":(Lscala/reflect/Type;Lscala/collection/immutable/List;)V
	areturn
  Labels:
  LocalVariableTable: 
   Start  Length  Slot  Name   Signature
   0      10      0    this       Lscala/reflect/AppliedType$;
   0      10      1    tpe       Lscala/reflect/Type;
   0      10      2    args       Lscala/collection/immutable/List;


public scala.Some unapply(scala.reflect.AppliedType);
  Signature: (Lscala/reflect/AppliedType;)Lscala/Some;
  Code:
   Stack=6, Locals=2, Args_size=2
	new	class scala/Some
	dup
	new	class scala/Tuple2
	dup
	aload_1
	invokevirtual	Method scala/reflect/AppliedType.tpe:()Lscala/reflect/Type;
	aload_1
	invokevirtual	Method scala/reflect/AppliedType.args:()Lscala/collection/immutable/List;
	invokespecial	Method scala/Tuple2."<init>":(Ljava/lang/Object;Ljava/lang/Object;)V
	invokespecial	Method scala/Some."<init>":(Ljava/lang/Object;)V
	areturn
  Labels:
  LocalVariableTable: 
   Start  Length  Slot  Name   Signature
   0      23      0    this       Lscala/reflect/AppliedType$;
   0      23      1    x$0       Lscala/reflect/AppliedType;


public scala.Function1 tupled();
  Signature: ()Lscala/Function1;
  Code:
   Stack=1, Locals=1, Args_size=1
	aload_0
	invokestatic	Method scala/Function2$class.tupled:(Lscala/Function2;)Lscala/Function1;
	areturn
  Labels:

public scala.Function1 curry();
  Signature: ()Lscala/Function1;
  Code:
   Stack=1, Locals=1, Args_size=1
	aload_0
	invokestatic	Method scala/Function2$class.curry:(Lscala/Function2;)Lscala/Function1;
	areturn
  Labels:
  Deprecated: true

public scala.Function1 curried();
  Signature: ()Lscala/Function1;
  Code:
   Stack=1, Locals=1, Args_size=1
	aload_0
	invokestatic	Method scala/Function2$class.curried:(Lscala/Function2;)Lscala/Function1;
	areturn
  Labels:

public java.lang.String toString();
  Signature: ()Ljava/lang/String;
  Code:
   Stack=1, Locals=1, Args_size=1
	aload_0
	invokestatic	Method scala/Function2$class.toString:(Lscala/Function2;)Ljava/lang/String;
	areturn
  Labels:

}

