Compiled from "Tree.scala"
public class scala.reflect.Apply extends scala.reflect.Tree implements scala.ScalaObject,scala.Product,java.io.Serializable
  SourceFile: "Tree.scala"
  ScalaSig: length = 0x3D7
   05 00 FFFFFF81 12 06 08 01 02 FFFFFF84 FFFFFF80 FFFFFF80 FFFFFF80 40 07 02 05
   41 70 70 6C 79 0A 02 03 04 01 07 72 65 66 6C 65
   63 74 0A 01 05 01 05 73 63 61 6C 61 03 00 13 04
   00 08 0C 10 10 02 09 0A 0D 01 02 09 02 0B 02 02
   04 54 72 65 65 10 02 0D 0E 0D 01 04 09 02 0F 04
   02 0B 53 63 61 6C 61 4F 62 6A 65 63 74 10 02 0D
   11 09 02 12 04 02 07 50 72 6F 64 75 63 74 08 08
   14 00 FFFFFF82 FFFFFFCA FFFFFF80 FFFFFF84 00 15 01 03 66 75 6E 15 01 08
   08 08 17 00 FFFFFF82 FFFFFF88 FFFFFFA0 FFFFFF80 04 08 01 04 66 75 6E 20
   08 08 19 00 FFFFFF82 FFFFFFCA FFFFFF80 FFFFFF84 00 1A 01 04 61 72 67 73
   15 01 1B 10 03 1C 21 08 0D 01 1D 0A 02 1E 1F 01
   09 69 6D 6D 75 74 61 62 6C 65 0A 02 20 04 01 0A
   63 6F 6C 6C 65 63 74 69 6F 6E 09 02 22 1D 02 04
   4C 69 73 74 08 08 24 00 FFFFFF82 FFFFFF88 FFFFFFA0 FFFFFF80 04 1B 01 05
   61 72 67 73 20 08 05 26 00 FFFFFF84 00 27 01 06 3C 69
   6E 69 74 3E 14 03 28 29 2A 10 02 09 00 08 05 14
   25 FFFFFFC0 00 08 08 05 19 25 FFFFFFC0 00 1B 08 07 2C 00 FFFFFF81
   FFFFFF80 FFFFFF84 00 2D 01 04 63 6F 70 79 14 03 28 2E 3C 08
   08 2F 14 2B FFFFFF90 FFFFFF80 FFFFFFC0 00 08 08 07 30 00 FFFFFF91 FFFFFF80 FFFFFF84
   00 31 01 0E 63 6F 70 79 24 64 65 66 61 75 6C 74
   24 31 15 01 32 2A 02 08 33 2B 01 34 10 02 35 3A
   0D 01 36 0A 02 37 38 01 09 75 6E 63 68 65 63 6B
   65 64 0A 02 39 04 01 0A 61 6E 6E 6F 74 61 74 69
   6F 6E 09 02 3B 36 02 11 75 6E 63 68 65 63 6B 65
   64 56 61 72 69 61 6E 63 65 08 08 3D 19 2B FFFFFF90 FFFFFF80
   FFFFFFC0 00 1B 08 07 3E 00 FFFFFF91 FFFFFF80 FFFFFF84 00 3F 01 0E 63 6F
   70 79 24 64 65 66 61 75 6C 74 24 32 15 01 40 2A
   02 1B 33 08 08 42 00 FFFFFF84 FFFFFF80 FFFFFF80 FFFFFF84 20 43 01 08 68
   61 73 68 43 6F 64 65 14 01 44 10 02 0D 45 09 02
   46 04 02 03 49 6E 74 08 08 48 00 FFFFFF84 FFFFFF80 FFFFFF80 FFFFFF84 20
   49 01 08 74 6F 53 74 72 69 6E 67 14 01 4A 10 02
   4B 4E 0E 02 0D 4C 09 02 4D 04 01 06 50 72 65 64
   65 66 09 02 4F 50 02 06 53 74 72 69 6E 67 0A 02
   4D 04 08 08 52 00 FFFFFF84 FFFFFF80 FFFFFF80 FFFFFF84 20 53 01 06 65 71
   75 61 6C 73 14 02 54 57 10 02 0D 55 09 02 56 04
   02 07 42 6F 6F 6C 65 61 6E 08 07 58 51 FFFFFF81 FFFFFF80 FFFFFFC0
   00 59 01 03 78 24 31 10 02 0D 5A 09 02 5B 04 02
   03 41 6E 79 08 08 5D 00 FFFFFF84 FFFFFF80 FFFFFF80 FFFFFF84 20 5E 01 0D
   70 72 6F 64 75 63 74 50 72 65 66 69 78 15 01 5F
   10 02 60 65 0D 01 61 0A 02 62 63 01 04 6C 61 6E
   67 0A 01 64 01 04 6A 61 76 61 09 02 4F 61 08 08
   67 00 FFFFFF84 FFFFFF80 FFFFFF80 FFFFFF84 20 68 01 0C 70 72 6F 64 75 63
   74 41 72 69 74 79 15 01 44 08 08 6A 00 FFFFFF84 FFFFFF80 FFFFFF80
   FFFFFF84 20 6B 01 0E 70 72 6F 64 75 63 74 45 6C 65 6D
   65 6E 74 14 02 59 6C 08 07 58 69 FFFFFF81 FFFFFF80 FFFFFFC0 00 44
   08 08 6E 00 FFFFFF84 FFFFFF80 FFFFFF80 FFFFFF84 20 6F 01 08 63 61 6E 45
   71 75 61 6C 14 02 54 70 08 07 58 6D FFFFFF81 FFFFFF80 FFFFFFC0 00
   59 28 02 00 72 10 02 0D 73 09 02 74 04 02 0C 73
   65 72 69 61 6C 69 7A 61 62 6C 65 07 07 76 02 FFFFFF81
   FFFFFF80 FFFFFF88 02 77 01 05 41 70 70 6C 79 10 02 09 78 06
   08 01 02 FFFFFF84 FFFFFF81 FFFFFF80 FFFFFF88 02 79 13 04 78 7A 7D 0C 10
   02 60 7B 09 02 7C 61 02 06 4F 62 6A 65 63 74 10
   05 0D 7E 08 1B 28 09 02 7F 04 02 09 46 75 6E 63
   74 69 6F 6E 32 08 06 26 78 FFFFFF84 00 FFFFFF81 01 14 01 77
   08 09 FFFFFF81 03 78 FFFFFF81 FFFFFF80 FFFFFF84 40 FFFFFF81 04 01 05 61 70 70
   6C 79 14 05 28 FFFFFF81 05 FFFFFF81 06 08 06 14 FFFFFF81 02 FFFFFFC0 00
   08 08 06 19 FFFFFF81 02 FFFFFFC0 00 1B 08 09 FFFFFF81 08 78 FFFFFF81 FFFFFF80
   FFFFFF84 40 FFFFFF81 09 01 07 75 6E 61 70 70 6C 79 14 04 FFFFFF81
   0A FFFFFF81 10 10 05 0D FFFFFF81 0B FFFFFF81 0D 09 03 FFFFFF81 0C 04 02
   04 53 6F 6D 65 10 05 0D FFFFFF81 0E 08 1B 09 03 FFFFFF81 0F
   04 02 06 54 75 70 6C 65 32 08 07 FFFFFF81 11 FFFFFF81 07 FFFFFFC0
   00 28 01 03 78 24 30 
  minor version: 0
  major version: 49
  Constant pool:
Asciz	SourceFile;
Asciz	Tree.scala;
Asciz	tuple;
Asciz	()Lscala/Function1;;
Asciz	Code;
Asciz	scala/reflect/Apply$;
class	scala/reflect/Apply$
Asciz	MODULE$;
Asciz	Lscala/reflect/Apply$;;
NameAndType	MODULE$:Lscala/reflect/Apply$;
Field	scala/reflect/Apply$.MODULE$:Lscala/reflect/Apply$;
NameAndType	tuple:()Lscala/Function1;
Method	scala/reflect/Apply$.tuple:()Lscala/Function1;
Asciz	curry;
NameAndType	curry:()Lscala/Function1;
Method	scala/reflect/Apply$.curry:()Lscala/Function1;
Asciz	args;
Asciz	Lscala/collection/immutable/List;;
Asciz	Lscala/collection/immutable/List<Lscala/reflect/Tree;>;;
Asciz	Signature;
Asciz	fun;
Asciz	Lscala/reflect/Tree;;
Asciz	<init>;
Asciz	(Lscala/reflect/Tree;Lscala/collection/immutable/List;)V;
Asciz	LineNumberTable;
Asciz	scala/reflect/Apply;
class	scala/reflect/Apply
NameAndType	fun:Lscala/reflect/Tree;
Field	scala/reflect/Apply.fun:Lscala/reflect/Tree;
NameAndType	args:Lscala/collection/immutable/List;
Field	scala/reflect/Apply.args:Lscala/collection/immutable/List;
Asciz	scala/reflect/Tree;
class	scala/reflect/Tree
Asciz	()V;
NameAndType	"<init>":()V
Method	scala/reflect/Tree."<init>":()V
Asciz	scala/Product$class;
class	scala/Product$class
Asciz	$init$;
Asciz	(Lscala/Product;)V;
NameAndType	$init$:(Lscala/Product;)V
Method	scala/Product$class.$init$:(Lscala/Product;)V
Asciz	this;
Asciz	Lscala/reflect/Apply;;
Asciz	LocalVariableTable;
Asciz	(Lscala/reflect/Tree;Lscala/collection/immutable/List<Lscala/reflect/Tree;>;)V;
Asciz	gd4$1;
Asciz	(Lscala/reflect/Tree;Lscala/collection/immutable/List;)Z;
Asciz	()Lscala/reflect/Tree;;
NameAndType	fun:()Lscala/reflect/Tree;
Method	scala/reflect/Apply.fun:()Lscala/reflect/Tree;
Asciz	java/lang/Object;
class	java/lang/Object
Asciz	equals;
Asciz	(Ljava/lang/Object;)Z;
NameAndType	equals:(Ljava/lang/Object;)Z
Method	java/lang/Object.equals:(Ljava/lang/Object;)Z
Asciz	()Lscala/collection/immutable/List;;
NameAndType	args:()Lscala/collection/immutable/List;
Method	scala/reflect/Apply.args:()Lscala/collection/immutable/List;
Asciz	canEqual;
Asciz	productElement;
Asciz	(I)Ljava/lang/Object;;
Asciz	java/lang/IndexOutOfBoundsException;
class	java/lang/IndexOutOfBoundsException
Asciz	scala/runtime/BoxesRunTime;
class	scala/runtime/BoxesRunTime
Asciz	boxToInteger;
Asciz	(I)Ljava/lang/Integer;;
NameAndType	boxToInteger:(I)Ljava/lang/Integer;
Method	scala/runtime/BoxesRunTime.boxToInteger:(I)Ljava/lang/Integer;
Asciz	toString;
Asciz	()Ljava/lang/String;;
NameAndType	toString:()Ljava/lang/String;
Method	java/lang/Object.toString:()Ljava/lang/String;
Asciz	(Ljava/lang/String;)V;
NameAndType	"<init>":(Ljava/lang/String;)V
Method	java/lang/IndexOutOfBoundsException."<init>":(Ljava/lang/String;)V
Asciz	productArity;
Asciz	()I;
Asciz	productPrefix;
Asciz	Apply;
String	Apply
NameAndType	gd4$1:(Lscala/reflect/Tree;Lscala/collection/immutable/List;)Z
Method	scala/reflect/Apply.gd4$1:(Lscala/reflect/Tree;Lscala/collection/immutable/List;)Z
Asciz	scala/Equals;
class	scala/Equals
NameAndType	canEqual:(Ljava/lang/Object;)Z
InterfaceMethod	scala/Equals.canEqual:(Ljava/lang/Object;)Z
Asciz	temp15;
Asciz	temp16;
Asciz	temp17;
Asciz	scala/runtime/ScalaRunTime$;
class	scala/runtime/ScalaRunTime$
Asciz	Lscala/runtime/ScalaRunTime$;;
NameAndType	MODULE$:Lscala/runtime/ScalaRunTime$;
Field	scala/runtime/ScalaRunTime$.MODULE$:Lscala/runtime/ScalaRunTime$;
Asciz	_toString;
Asciz	(Lscala/Product;)Ljava/lang/String;;
NameAndType	_toString:(Lscala/Product;)Ljava/lang/String;
Method	scala/runtime/ScalaRunTime$._toString:(Lscala/Product;)Ljava/lang/String;
Asciz	hashCode;
Asciz	_hashCode;
Asciz	(Lscala/Product;)I;
NameAndType	_hashCode:(Lscala/Product;)I
Method	scala/runtime/ScalaRunTime$._hashCode:(Lscala/Product;)I
Asciz	copy;
Asciz	(Lscala/reflect/Tree;Lscala/collection/immutable/List;)Lscala/reflect/Apply;;
NameAndType	"<init>":(Lscala/reflect/Tree;Lscala/collection/immutable/List;)V
Method	scala/reflect/Apply."<init>":(Lscala/reflect/Tree;Lscala/collection/immutable/List;)V
Asciz	()Lscala/collection/immutable/List<Lscala/reflect/Tree;>;;
Asciz	copy$default$1;
Asciz	copy$default$2;
Asciz	productElements;
Asciz	()Lscala/collection/Iterator;;
Asciz	(Lscala/Product;)Lscala/collection/Iterator;;
NameAndType	productElements:(Lscala/Product;)Lscala/collection/Iterator;
Method	scala/Product$class.productElements:(Lscala/Product;)Lscala/collection/Iterator;
Asciz	Deprecated;
Asciz	productIterator;
NameAndType	productIterator:(Lscala/Product;)Lscala/collection/Iterator;
Method	scala/Product$class.productIterator:(Lscala/Product;)Lscala/collection/Iterator;
Asciz	ScalaSig;
Asciz	scala/ScalaObject;
class	scala/ScalaObject
Asciz	scala/Product;
class	scala/Product
Asciz	java/io/Serializable;
class	java/io/Serializable

{
private final scala.collection.immutable.List args;
  Signature: Lscala/collection/immutable/List;
  Signature: length = 0x2
   00 13 

private final scala.reflect.Tree fun;
  Signature: Lscala/reflect/Tree;

public static final scala.Function1 tuple();
  Signature: ()Lscala/Function1;
  Code:
   Stack=1, Locals=0, Args_size=0
	getstatic	Field scala/reflect/Apply$.MODULE$:Lscala/reflect/Apply$;
	invokevirtual	Method scala/reflect/Apply$.tuple:()Lscala/Function1;
	areturn
  Labels:

public static final scala.Function1 curry();
  Signature: ()Lscala/Function1;
  Code:
   Stack=1, Locals=0, Args_size=0
	getstatic	Field scala/reflect/Apply$.MODULE$:Lscala/reflect/Apply$;
	invokevirtual	Method scala/reflect/Apply$.curry:()Lscala/Function1;
	areturn
  Labels:

public scala.reflect.Apply(scala.reflect.Tree, scala.collection.immutable.List);
  Signature: (Lscala/reflect/Tree;Lscala/collection/immutable/List;)V
  Code:
   Stack=2, Locals=3, Args_size=3
	aload_0
	aload_1
	putfield	Field fun:Lscala/reflect/Tree;
	aload_0
	aload_2
	putfield	Field args:Lscala/collection/immutable/List;
	aload_0
	invokespecial	Method scala/reflect/Tree."<init>":()V
	aload_0
	invokestatic	Method scala/Product$class.$init$:(Lscala/Product;)V
	return
  Labels:
  LocalVariableTable: 
   Start  Length  Slot  Name   Signature
   0      19      0    this       Lscala/reflect/Apply;
   0      19      1    fun       Lscala/reflect/Tree;
   0      19      2    args       Lscala/collection/immutable/List;

  Signature: length = 0x2
   00 2E 

private final boolean gd4$1(scala.reflect.Tree, scala.collection.immutable.List);
  Signature: (Lscala/reflect/Tree;Lscala/collection/immutable/List;)Z
  Code:
   Stack=2, Locals=5, Args_size=3
	aload_1
	aload_0
	invokevirtual	Method fun:()Lscala/reflect/Tree;
	astore_3
	dup
	ifnonnull	l1 // aload_3
	pop
	aload_3
	ifnull	l2 // aload_2
	goto	l3 // iconst_0
l1	aload_3
	invokevirtual	Method java/lang/Object.equals:(Ljava/lang/Object;)Z
	ifeq	l3 // iconst_0
l2	aload_2
	aload_0
	invokevirtual	Method args:()Lscala/collection/immutable/List;
	astore	4
	dup
	ifnonnull	l4 // aload
	pop
	aload	4
	ifnull	l5 // iconst_1
	goto	l3 // iconst_0
l4	aload	4
	invokevirtual	Method java/lang/Object.equals:(Ljava/lang/Object;)Z
	ifeq	l3 // iconst_0
l5	iconst_1
	goto	l6 // ireturn
l3	iconst_0
l6	ireturn
  Labels:
   	l1 = 18 // aload_3
   	l2 = 25 // aload_2
   	l4 = 45 // aload
   	l5 = 53 // iconst_1
   	l3 = 57 // iconst_0
   	l6 = 58 // ireturn

public boolean canEqual(java.lang.Object);
  Signature: (Ljava/lang/Object;)Z
  Code:
   Stack=1, Locals=2, Args_size=2
	aload_1
	instanceof	class scala/reflect/Apply
	ireturn
  Labels:

public java.lang.Object productElement(int);
  Signature: (I)Ljava/lang/Object;
  Code:
   Stack=3, Locals=2, Args_size=2
	iload_1
	tableswitch{ //0 to 1
		0: 46;
		1: 39;
		default: 24 }
	new	class java/lang/IndexOutOfBoundsException
	dup
	iload_1
	invokestatic	Method scala/runtime/BoxesRunTime.boxToInteger:(I)Ljava/lang/Integer;
	invokevirtual	Method java/lang/Object.toString:()Ljava/lang/String;
	invokespecial	Method java/lang/IndexOutOfBoundsException."<init>":(Ljava/lang/String;)V
	athrow
	aload_0
	invokevirtual	Method args:()Lscala/collection/immutable/List;
	goto	l1 // areturn
	aload_0
	invokevirtual	Method fun:()Lscala/reflect/Tree;
l1	areturn
  Labels:
   	l1 = 50 // areturn

public int productArity();
  Signature: ()I
  Code:
   Stack=1, Locals=1, Args_size=1
	iconst_2
	ireturn
  Labels:

public java.lang.String productPrefix();
  Signature: ()Ljava/lang/String;
  Code:
   Stack=1, Locals=1, Args_size=1
	ldc	String Apply
	areturn
  Labels:

public boolean equals(java.lang.Object);
  Signature: (Ljava/lang/Object;)Z
  Code:
   Stack=3, Locals=5, Args_size=2
	aload_0
	aload_1
	if_acmpeq	l1 // iconst_1
	aload_1
	instanceof	class scala/reflect/Apply
	ifeq	l2 // iconst_0
	aload_1
	checkcast	class scala/reflect/Apply
	astore_2
	aload_2
	invokevirtual	Method fun:()Lscala/reflect/Tree;
	astore_3
	aload_2
	invokevirtual	Method args:()Lscala/collection/immutable/List;
	astore	4
	aload_0
	aload_3
	aload	4
	invokespecial	Method gd4$1:(Lscala/reflect/Tree;Lscala/collection/immutable/List;)Z
	ifeq	l3 // iconst_0
	aload_1
	checkcast	class scala/reflect/Apply
	aload_0
	invokeinterface	InterfaceMethod scala/Equals.canEqual:(Ljava/lang/Object;)Z
	goto	l4 // ifeq
l3	iconst_0
	goto	l4 // ifeq
l2	iconst_0
l4	ifeq	l5 // iconst_0
l1	iconst_1
	goto	l6 // ireturn
l5	iconst_0
l6	ireturn
  Labels:
   	l3 = 51 // iconst_0
   	l2 = 55 // iconst_0
   	l4 = 56 // ifeq
   	l1 = 59 // iconst_1
   	l5 = 63 // iconst_0
   	l6 = 64 // ireturn
  LocalVariableTable: 
   Start  Length  Slot  Name   Signature
   0      65      0    this       Lscala/reflect/Apply;
   17      38      2    temp15       Lscala/reflect/Apply;
   22      33      3    temp16       Lscala/reflect/Tree;
   28      27      4    temp17       Lscala/collection/immutable/List;


public java.lang.String toString();
  Signature: ()Ljava/lang/String;
  Code:
   Stack=2, Locals=1, Args_size=1
	getstatic	Field scala/runtime/ScalaRunTime$.MODULE$:Lscala/runtime/ScalaRunTime$;
	aload_0
	invokevirtual	Method scala/runtime/ScalaRunTime$._toString:(Lscala/Product;)Ljava/lang/String;
	areturn
  Labels:

public int hashCode();
  Signature: ()I
  Code:
   Stack=2, Locals=1, Args_size=1
	getstatic	Field scala/runtime/ScalaRunTime$.MODULE$:Lscala/runtime/ScalaRunTime$;
	aload_0
	invokevirtual	Method scala/runtime/ScalaRunTime$._hashCode:(Lscala/Product;)I
	ireturn
  Labels:

public scala.reflect.Apply copy(scala.reflect.Tree, scala.collection.immutable.List);
  Signature: (Lscala/reflect/Tree;Lscala/collection/immutable/List;)Lscala/reflect/Apply;
  Code:
   Stack=4, Locals=3, Args_size=3
	new	class scala/reflect/Apply
	dup
	aload_1
	aload_2
	invokespecial	Method "<init>":(Lscala/reflect/Tree;Lscala/collection/immutable/List;)V
	areturn
  Labels:
  LocalVariableTable: 
   Start  Length  Slot  Name   Signature
   0      10      0    this       Lscala/reflect/Apply;
   0      10      1    fun       Lscala/reflect/Tree;
   0      10      2    args       Lscala/collection/immutable/List;


public scala.collection.immutable.List args();
  Signature: ()Lscala/collection/immutable/List;
  Code:
   Stack=1, Locals=1, Args_size=1
	aload_0
	getfield	Field args:Lscala/collection/immutable/List;
	areturn
  Labels:
  Signature: length = 0x2
   00 6F 

public scala.reflect.Tree fun();
  Signature: ()Lscala/reflect/Tree;
  Code:
   Stack=1, Locals=1, Args_size=1
	aload_0
	getfield	Field fun:Lscala/reflect/Tree;
	areturn
  Labels:

public scala.reflect.Tree copy$default$1();
  Signature: ()Lscala/reflect/Tree;
  Code:
   Stack=1, Locals=1, Args_size=1
	aload_0
	invokevirtual	Method fun:()Lscala/reflect/Tree;
	areturn
  Labels:

public scala.collection.immutable.List copy$default$2();
  Signature: ()Lscala/collection/immutable/List;
  Code:
   Stack=1, Locals=1, Args_size=1
	aload_0
	invokevirtual	Method args:()Lscala/collection/immutable/List;
	areturn
  Labels:

public scala.collection.Iterator productElements();
  Signature: ()Lscala/collection/Iterator;
  Code:
   Stack=1, Locals=1, Args_size=1
	aload_0
	invokestatic	Method scala/Product$class.productElements:(Lscala/Product;)Lscala/collection/Iterator;
	areturn
  Labels:
  Deprecated: true

public scala.collection.Iterator productIterator();
  Signature: ()Lscala/collection/Iterator;
  Code:
   Stack=1, Locals=1, Args_size=1
	aload_0
	invokestatic	Method scala/Product$class.productIterator:(Lscala/Product;)Lscala/collection/Iterator;
	areturn
  Labels:

}

