Compiled from "Type.scala"
public class scala.reflect.AppliedType extends scala.reflect.Type implements scala.ScalaObject,scala.Product,java.io.Serializable
  SourceFile: "Type.scala"
  ScalaSig: length = 0x3
   05 00 00 
  RuntimeVisibleAnnotations: length = 0xB
   00 01 00 FFFFFF86 00 01 00 FFFFFF87 73 00 FFFFFF88 
  minor version: 0
  major version: 49
  Constant pool:
Asciz	SourceFile;
Asciz	Type.scala;
Asciz	tupled;
Asciz	()Lscala/Function1;;
Asciz	Code;
Asciz	scala/reflect/AppliedType$;
class	scala/reflect/AppliedType$
Asciz	MODULE$;
Asciz	Lscala/reflect/AppliedType$;;
NameAndType	MODULE$:Lscala/reflect/AppliedType$;
Field	scala/reflect/AppliedType$.MODULE$:Lscala/reflect/AppliedType$;
NameAndType	tupled:()Lscala/Function1;
Method	scala/reflect/AppliedType$.tupled:()Lscala/Function1;
Asciz	curry;
NameAndType	curry:()Lscala/Function1;
Method	scala/reflect/AppliedType$.curry:()Lscala/Function1;
Asciz	Deprecated;
Asciz	curried;
NameAndType	curried:()Lscala/Function1;
Method	scala/reflect/AppliedType$.curried:()Lscala/Function1;
Asciz	tpe;
Asciz	Lscala/reflect/Type;;
Asciz	args;
Asciz	Lscala/collection/immutable/List;;
Asciz	Lscala/collection/immutable/List<Lscala/reflect/Type;>;;
Asciz	Signature;
Asciz	productElementName;
Asciz	(I)Ljava/lang/String;;
Asciz	LineNumberTable;
Asciz	scala/Product$class;
class	scala/Product$class
Asciz	(Lscala/Product;I)Ljava/lang/String;;
NameAndType	productElementName:(Lscala/Product;I)Ljava/lang/String;
Method	scala/Product$class.productElementName:(Lscala/Product;I)Ljava/lang/String;
Asciz	this;
Asciz	Lscala/reflect/AppliedType;;
Asciz	n;
Asciz	I;
Asciz	LocalVariableTable;
Asciz	productIterator;
Asciz	()Lscala/collection/Iterator;;
Asciz	(Lscala/Product;)Lscala/collection/Iterator;;
NameAndType	productIterator:(Lscala/Product;)Lscala/collection/Iterator;
Method	scala/Product$class.productIterator:(Lscala/Product;)Lscala/collection/Iterator;
Asciz	productElements;
NameAndType	productElements:(Lscala/Product;)Lscala/collection/Iterator;
Method	scala/Product$class.productElements:(Lscala/Product;)Lscala/collection/Iterator;
Asciz	copy$default$2;
Asciz	()Lscala/collection/immutable/List;;
Asciz	scala/reflect/AppliedType;
class	scala/reflect/AppliedType
NameAndType	args:()Lscala/collection/immutable/List;
Method	scala/reflect/AppliedType.args:()Lscala/collection/immutable/List;
Asciz	copy$default$1;
Asciz	()Lscala/reflect/Type;;
NameAndType	tpe:()Lscala/reflect/Type;
Method	scala/reflect/AppliedType.tpe:()Lscala/reflect/Type;
NameAndType	tpe:Lscala/reflect/Type;
Field	scala/reflect/AppliedType.tpe:Lscala/reflect/Type;
NameAndType	args:Lscala/collection/immutable/List;
Field	scala/reflect/AppliedType.args:Lscala/collection/immutable/List;
Asciz	()Lscala/collection/immutable/List<Lscala/reflect/Type;>;;
Asciz	copy;
Asciz	(Lscala/reflect/Type;Lscala/collection/immutable/List;)Lscala/reflect/AppliedType;;
Asciz	<init>;
Asciz	(Lscala/reflect/Type;Lscala/collection/immutable/List;)V;
NameAndType	"<init>":(Lscala/reflect/Type;Lscala/collection/immutable/List;)V
Method	scala/reflect/AppliedType."<init>":(Lscala/reflect/Type;Lscala/collection/immutable/List;)V
Asciz	hashCode;
Asciz	()I;
Asciz	scala/runtime/ScalaRunTime$;
class	scala/runtime/ScalaRunTime$
Asciz	Lscala/runtime/ScalaRunTime$;;
NameAndType	MODULE$:Lscala/runtime/ScalaRunTime$;
Field	scala/runtime/ScalaRunTime$.MODULE$:Lscala/runtime/ScalaRunTime$;
Asciz	_hashCode;
Asciz	(Lscala/Product;)I;
NameAndType	_hashCode:(Lscala/Product;)I
Method	scala/runtime/ScalaRunTime$._hashCode:(Lscala/Product;)I
Asciz	toString;
Asciz	()Ljava/lang/String;;
Asciz	_toString;
Asciz	(Lscala/Product;)Ljava/lang/String;;
NameAndType	_toString:(Lscala/Product;)Ljava/lang/String;
Method	scala/runtime/ScalaRunTime$._toString:(Lscala/Product;)Ljava/lang/String;
Asciz	equals;
Asciz	(Ljava/lang/Object;)Z;
Asciz	gd5$1;
Asciz	(Lscala/reflect/Type;Lscala/collection/immutable/List;)Z;
NameAndType	gd5$1:(Lscala/reflect/Type;Lscala/collection/immutable/List;)Z
Method	scala/reflect/AppliedType.gd5$1:(Lscala/reflect/Type;Lscala/collection/immutable/List;)Z
Asciz	scala/Equals;
class	scala/Equals
Asciz	canEqual;
NameAndType	canEqual:(Ljava/lang/Object;)Z
InterfaceMethod	scala/Equals.canEqual:(Ljava/lang/Object;)Z
Asciz	temp22;
Asciz	temp23;
Asciz	temp24;
Asciz	productPrefix;
Asciz	AppliedType;
String	AppliedType
Asciz	productArity;
Asciz	productElement;
Asciz	(I)Ljava/lang/Object;;
Asciz	java/lang/IndexOutOfBoundsException;
class	java/lang/IndexOutOfBoundsException
Asciz	scala/runtime/BoxesRunTime;
class	scala/runtime/BoxesRunTime
Asciz	boxToInteger;
Asciz	(I)Ljava/lang/Integer;;
NameAndType	boxToInteger:(I)Ljava/lang/Integer;
Method	scala/runtime/BoxesRunTime.boxToInteger:(I)Ljava/lang/Integer;
Asciz	java/lang/Object;
class	java/lang/Object
NameAndType	toString:()Ljava/lang/String;
Method	java/lang/Object.toString:()Ljava/lang/String;
Asciz	(Ljava/lang/String;)V;
NameAndType	"<init>":(Ljava/lang/String;)V
Method	java/lang/IndexOutOfBoundsException."<init>":(Ljava/lang/String;)V
NameAndType	equals:(Ljava/lang/Object;)Z
Method	java/lang/Object.equals:(Ljava/lang/Object;)Z
Asciz	scala/reflect/Type;
class	scala/reflect/Type
Asciz	()V;
NameAndType	"<init>":()V
Method	scala/reflect/Type."<init>":()V
Asciz	$init$;
Asciz	(Lscala/Product;)V;
NameAndType	$init$:(Lscala/Product;)V
Method	scala/Product$class.$init$:(Lscala/Product;)V
Asciz	(Lscala/reflect/Type;Lscala/collection/immutable/List<Lscala/reflect/Type;>;)V;
Asciz	ScalaSig;
Asciz	Lscala/reflect/ScalaSignature;;
Asciz	bytes;
Asciz	bC\t\tQ\5fIRK/\tqA]3gYGOC8-7bB\r!ABC%1B)fX\r5\tA!\t\tY1kY1mC>'.Z2u!\ti#\t\t9K]8ek$+IAQX-F\t!9A!E!A;qKB\"%\tAGCJ<7/F!\raC;)adH\nS6lW^1cYT!\t\r|G\3di&|g.#;\t!A*[:u!!A!E!Y!B1sON\"\t9Aj]&$hF)S)\"!\tQ)\te)A\t1!C[!1m9z)\rAcf)-\n1\tI2%AAmAq!\r!'d_BLHZ3gCVdGJMR#,U\"AN]R!OUt7\r[3dW$'B)\tgN\8uCRLwN\y]#8dQ7.3WCJLM\2fq!%A}\nabY8qs\"WMZ1vYR$#'FAU\tYBC\t\"D!Am5D_,G##5)B$\rIe\t!\t!C!AAo\*ue&tw\rFK!\tYeJ&Q\nB!J,G-4\n=&AB*ue&twMN\t!A!C3+fcVGn)^\"!D+\nY#!a\"p_2,M1F\t1Z\rAH%\r\tiK!as^\t\"_5(o3vGR&/4jqV\tqaK6\tMcG!A.8h!6bmL!aT1\tA!AB!A:pIVG/:jif,\tU!\t!C!WqO]8ek$X\t\3nK:$HCA-mA.!AACB%\te\\tGtW)];bYRA16\t1ZQ\t!g&A\rg.7juG.Zm\n\t\t#x-\t7jK$]3%AhC\t\tRA=aTHE|}\"Y&D}\tiH!Ask:$.\3\n}d(!E!cgRm;Gk:G/[8oe!1aC!a\nA!CA\tQ!9qYf$RKAAaFAABB\r1Ca\t\"!9QO\1qa2LHBACR!DA7I1!!y^5p]B)Q\"!\t7%q\rQ+\33\t#aA!\n11;
Asciz	RuntimeVisibleAnnotations;
Asciz	scala/ScalaObject;
class	scala/ScalaObject
Asciz	scala/Product;
class	scala/Product
Asciz	java/io/Serializable;
class	java/io/Serializable

{
private final scala.reflect.Type tpe;
  Signature: Lscala/reflect/Type;

private final scala.collection.immutable.List args;
  Signature: Lscala/collection/immutable/List;
  Signature: length = 0x2
   00 19 

public static final scala.Function1 tupled();
  Signature: ()Lscala/Function1;
  Code:
   Stack=1, Locals=0, Args_size=0
	getstatic	Field scala/reflect/AppliedType$.MODULE$:Lscala/reflect/AppliedType$;
	invokevirtual	Method scala/reflect/AppliedType$.tupled:()Lscala/Function1;
	areturn
  Labels:

public static final scala.Function1 curry();
  Signature: ()Lscala/Function1;
  Code:
   Stack=1, Locals=0, Args_size=0
	getstatic	Field scala/reflect/AppliedType$.MODULE$:Lscala/reflect/AppliedType$;
	invokevirtual	Method scala/reflect/AppliedType$.curry:()Lscala/Function1;
	areturn
  Labels:
  Deprecated: true

public static final scala.Function1 curried();
  Signature: ()Lscala/Function1;
  Code:
   Stack=1, Locals=0, Args_size=0
	getstatic	Field scala/reflect/AppliedType$.MODULE$:Lscala/reflect/AppliedType$;
	invokevirtual	Method scala/reflect/AppliedType$.curried:()Lscala/Function1;
	areturn
  Labels:

public java.lang.String productElementName(int);
  Signature: (I)Ljava/lang/String;
  Code:
   Stack=2, Locals=2, Args_size=2
	aload_0
	iload_1
	invokestatic	Method scala/Product$class.productElementName:(Lscala/Product;I)Ljava/lang/String;
	areturn
  Labels:
  LocalVariableTable: 
   Start  Length  Slot  Name   Signature
   0      6      0    this       Lscala/reflect/AppliedType;
   0      6      1    n       I


public scala.collection.Iterator productIterator();
  Signature: ()Lscala/collection/Iterator;
  Code:
   Stack=1, Locals=1, Args_size=1
	aload_0
	invokestatic	Method scala/Product$class.productIterator:(Lscala/Product;)Lscala/collection/Iterator;
	areturn
  Labels:

public scala.collection.Iterator productElements();
  Signature: ()Lscala/collection/Iterator;
  Code:
   Stack=1, Locals=1, Args_size=1
	aload_0
	invokestatic	Method scala/Product$class.productElements:(Lscala/Product;)Lscala/collection/Iterator;
	areturn
  Labels:
  Deprecated: true

public scala.collection.immutable.List copy$default$2();
  Signature: ()Lscala/collection/immutable/List;
  Code:
   Stack=1, Locals=1, Args_size=1
	aload_0
	invokevirtual	Method args:()Lscala/collection/immutable/List;
	areturn
  Labels:

public scala.reflect.Type copy$default$1();
  Signature: ()Lscala/reflect/Type;
  Code:
   Stack=1, Locals=1, Args_size=1
	aload_0
	invokevirtual	Method tpe:()Lscala/reflect/Type;
	areturn
  Labels:

public scala.reflect.Type tpe();
  Signature: ()Lscala/reflect/Type;
  Code:
   Stack=1, Locals=1, Args_size=1
	aload_0
	getfield	Field tpe:Lscala/reflect/Type;
	areturn
  Labels:

public scala.collection.immutable.List args();
  Signature: ()Lscala/collection/immutable/List;
  Code:
   Stack=1, Locals=1, Args_size=1
	aload_0
	getfield	Field args:Lscala/collection/immutable/List;
	areturn
  Labels:
  Signature: length = 0x2
   00 3E 

public scala.reflect.AppliedType copy(scala.reflect.Type, scala.collection.immutable.List);
  Signature: (Lscala/reflect/Type;Lscala/collection/immutable/List;)Lscala/reflect/AppliedType;
  Code:
   Stack=4, Locals=3, Args_size=3
	new	class scala/reflect/AppliedType
	dup
	aload_1
	aload_2
	invokespecial	Method "<init>":(Lscala/reflect/Type;Lscala/collection/immutable/List;)V
	areturn
  Labels:
  LocalVariableTable: 
   Start  Length  Slot  Name   Signature
   0      10      0    this       Lscala/reflect/AppliedType;
   0      10      1    tpe       Lscala/reflect/Type;
   0      10      2    args       Lscala/collection/immutable/List;


public int hashCode();
  Signature: ()I
  Code:
   Stack=2, Locals=1, Args_size=1
	getstatic	Field scala/runtime/ScalaRunTime$.MODULE$:Lscala/runtime/ScalaRunTime$;
	aload_0
	invokevirtual	Method scala/runtime/ScalaRunTime$._hashCode:(Lscala/Product;)I
	ireturn
  Labels:

public java.lang.String toString();
  Signature: ()Ljava/lang/String;
  Code:
   Stack=2, Locals=1, Args_size=1
	getstatic	Field scala/runtime/ScalaRunTime$.MODULE$:Lscala/runtime/ScalaRunTime$;
	aload_0
	invokevirtual	Method scala/runtime/ScalaRunTime$._toString:(Lscala/Product;)Ljava/lang/String;
	areturn
  Labels:

public boolean equals(java.lang.Object);
  Signature: (Ljava/lang/Object;)Z
  Code:
   Stack=3, Locals=5, Args_size=2
	aload_0
	aload_1
	if_acmpeq	l1 // iconst_1
	aload_1
	instanceof	class scala/reflect/AppliedType
	ifeq	l2 // iconst_0
	aload_1
	checkcast	class scala/reflect/AppliedType
	astore_2
	aload_2
	invokevirtual	Method tpe:()Lscala/reflect/Type;
	astore_3
	aload_2
	invokevirtual	Method args:()Lscala/collection/immutable/List;
	astore	4
	aload_0
	aload_3
	aload	4
	invokespecial	Method gd5$1:(Lscala/reflect/Type;Lscala/collection/immutable/List;)Z
	ifeq	l3 // iconst_0
	aload_1
	checkcast	class scala/reflect/AppliedType
	aload_0
	invokeinterface	InterfaceMethod scala/Equals.canEqual:(Ljava/lang/Object;)Z
	goto	l4 // ifeq
l3	iconst_0
	goto	l4 // ifeq
l2	iconst_0
l4	ifeq	l5 // iconst_0
l1	iconst_1
	goto	l6 // ireturn
l5	iconst_0
l6	ireturn
  Labels:
   	l3 = 51 // iconst_0
   	l2 = 55 // iconst_0
   	l4 = 56 // ifeq
   	l1 = 59 // iconst_1
   	l5 = 63 // iconst_0
   	l6 = 64 // ireturn
  LocalVariableTable: 
   Start  Length  Slot  Name   Signature
   0      65      0    this       Lscala/reflect/AppliedType;
   17      38      2    temp22       Lscala/reflect/AppliedType;
   22      33      3    temp23       Lscala/reflect/Type;
   28      27      4    temp24       Lscala/collection/immutable/List;


public java.lang.String productPrefix();
  Signature: ()Ljava/lang/String;
  Code:
   Stack=1, Locals=1, Args_size=1
	ldc	String AppliedType
	areturn
  Labels:

public int productArity();
  Signature: ()I
  Code:
   Stack=1, Locals=1, Args_size=1
	iconst_2
	ireturn
  Labels:

public java.lang.Object productElement(int);
  Signature: (I)Ljava/lang/Object;
  Code:
   Stack=3, Locals=2, Args_size=2
	iload_1
	tableswitch{ //0 to 1
		0: 46;
		1: 39;
		default: 24 }
	new	class java/lang/IndexOutOfBoundsException
	dup
	iload_1
	invokestatic	Method scala/runtime/BoxesRunTime.boxToInteger:(I)Ljava/lang/Integer;
	invokevirtual	Method java/lang/Object.toString:()Ljava/lang/String;
	invokespecial	Method java/lang/IndexOutOfBoundsException."<init>":(Ljava/lang/String;)V
	athrow
	aload_0
	invokevirtual	Method args:()Lscala/collection/immutable/List;
	goto	l1 // areturn
	aload_0
	invokevirtual	Method tpe:()Lscala/reflect/Type;
l1	areturn
  Labels:
   	l1 = 50 // areturn

public boolean canEqual(java.lang.Object);
  Signature: (Ljava/lang/Object;)Z
  Code:
   Stack=1, Locals=2, Args_size=2
	aload_1
	instanceof	class scala/reflect/AppliedType
	ireturn
  Labels:

private final boolean gd5$1(scala.reflect.Type, scala.collection.immutable.List);
  Signature: (Lscala/reflect/Type;Lscala/collection/immutable/List;)Z
  Code:
   Stack=2, Locals=5, Args_size=3
	aload_1
	aload_0
	invokevirtual	Method tpe:()Lscala/reflect/Type;
	astore_3
	dup
	ifnonnull	l1 // aload_3
	pop
	aload_3
	ifnull	l2 // aload_2
	goto	l3 // iconst_0
l1	aload_3
	invokevirtual	Method java/lang/Object.equals:(Ljava/lang/Object;)Z
	ifeq	l3 // iconst_0
l2	aload_2
	aload_0
	invokevirtual	Method args:()Lscala/collection/immutable/List;
	astore	4
	dup
	ifnonnull	l4 // aload
	pop
	aload	4
	ifnull	l5 // iconst_1
	goto	l3 // iconst_0
l4	aload	4
	invokevirtual	Method java/lang/Object.equals:(Ljava/lang/Object;)Z
	ifeq	l3 // iconst_0
l5	iconst_1
	goto	l6 // ireturn
l3	iconst_0
l6	ireturn
  Labels:
   	l1 = 18 // aload_3
   	l2 = 25 // aload_2
   	l4 = 45 // aload
   	l5 = 53 // iconst_1
   	l3 = 57 // iconst_0
   	l6 = 58 // ireturn

public scala.reflect.AppliedType(scala.reflect.Type, scala.collection.immutable.List);
  Signature: (Lscala/reflect/Type;Lscala/collection/immutable/List;)V
  Code:
   Stack=2, Locals=3, Args_size=3
	aload_0
	aload_1
	putfield	Field tpe:Lscala/reflect/Type;
	aload_0
	aload_2
	putfield	Field args:Lscala/collection/immutable/List;
	aload_0
	invokespecial	Method scala/reflect/Type."<init>":()V
	aload_0
	invokestatic	Method scala/Product$class.$init$:(Lscala/Product;)V
	return
  Labels:
  LocalVariableTable: 
   Start  Length  Slot  Name   Signature
   0      19      0    this       Lscala/reflect/AppliedType;
   0      19      1    tpe       Lscala/reflect/Type;
   0      19      2    args       Lscala/collection/immutable/List;

  Signature: length = 0x2
   00 FFFFFF84 

}

