Compiled from "Tree.scala"
public final class scala.reflect.Apply$ extends java.lang.Object implements scala.Function2,scala.ScalaObject
  SourceFile: "Tree.scala"
  Scala: length = 0x
   
  minor version: 0
  major version: 49
  Constant pool:
Asciz	SourceFile;
Asciz	Tree.scala;
Asciz	Scala;
Asciz	MODULE$;
Asciz	Lscala/reflect/Apply$;;
Asciz	<clinit>;
Asciz	()V;
Asciz	Code;
Asciz	scala/reflect/Apply$;
class	scala/reflect/Apply$
Asciz	<init>;
NameAndType	"<init>":()V
Method	scala/reflect/Apply$."<init>":()V
Asciz	toString;
Asciz	()Ljava/lang/String;;
Asciz	LineNumberTable;
Asciz	scala/Function2$class;
class	scala/Function2$class
Asciz	(Lscala/Function2;)Ljava/lang/String;;
NameAndType	toString:(Lscala/Function2;)Ljava/lang/String;
Method	scala/Function2$class.toString:(Lscala/Function2;)Ljava/lang/String;
Asciz	curried;
Asciz	()Lscala/Function1;;
Asciz	(Lscala/Function2;)Lscala/Function1;;
NameAndType	curried:(Lscala/Function2;)Lscala/Function1;
Method	scala/Function2$class.curried:(Lscala/Function2;)Lscala/Function1;
Asciz	curry;
NameAndType	curry:(Lscala/Function2;)Lscala/Function1;
Method	scala/Function2$class.curry:(Lscala/Function2;)Lscala/Function1;
Asciz	Deprecated;
Asciz	tupled;
NameAndType	tupled:(Lscala/Function2;)Lscala/Function1;
Method	scala/Function2$class.tupled:(Lscala/Function2;)Lscala/Function1;
Asciz	unapply;
Asciz	(Lscala/reflect/Apply;)Lscala/Some;;
Asciz	scala/Some;
class	scala/Some
Asciz	scala/Tuple2;
class	scala/Tuple2
Asciz	scala/reflect/Apply;
class	scala/reflect/Apply
Asciz	fun;
Asciz	()Lscala/reflect/Tree;;
NameAndType	fun:()Lscala/reflect/Tree;
Method	scala/reflect/Apply.fun:()Lscala/reflect/Tree;
Asciz	args;
Asciz	()Lscala/collection/immutable/List;;
NameAndType	args:()Lscala/collection/immutable/List;
Method	scala/reflect/Apply.args:()Lscala/collection/immutable/List;
Asciz	(Ljava/lang/Object;Ljava/lang/Object;)V;
NameAndType	"<init>":(Ljava/lang/Object;Ljava/lang/Object;)V
Method	scala/Tuple2."<init>":(Ljava/lang/Object;Ljava/lang/Object;)V
Asciz	(Ljava/lang/Object;)V;
NameAndType	"<init>":(Ljava/lang/Object;)V
Method	scala/Some."<init>":(Ljava/lang/Object;)V
Asciz	this;
Asciz	x$0;
Asciz	Lscala/reflect/Apply;;
Asciz	LocalVariableTable;
Asciz	apply;
Asciz	(Lscala/reflect/Tree;Lscala/collection/immutable/List;)Lscala/reflect/Apply;;
Asciz	(Lscala/reflect/Tree;Lscala/collection/immutable/List;)V;
NameAndType	"<init>":(Lscala/reflect/Tree;Lscala/collection/immutable/List;)V
Method	scala/reflect/Apply."<init>":(Lscala/reflect/Tree;Lscala/collection/immutable/List;)V
Asciz	Lscala/reflect/Tree;;
Asciz	Lscala/collection/immutable/List;;
Asciz	(Ljava/lang/Object;Ljava/lang/Object;)Ljava/lang/Object;;
Asciz	scala/reflect/Tree;
class	scala/reflect/Tree
Asciz	scala/collection/immutable/List;
class	scala/collection/immutable/List
NameAndType	apply:(Lscala/reflect/Tree;Lscala/collection/immutable/List;)Lscala/reflect/Apply;
Method	scala/reflect/Apply$.apply:(Lscala/reflect/Tree;Lscala/collection/immutable/List;)Lscala/reflect/Apply;
Asciz	v1;
Asciz	Ljava/lang/Object;;
Asciz	v2;
Asciz	java/lang/Object;
class	java/lang/Object
Method	java/lang/Object."<init>":()V
NameAndType	MODULE$:Lscala/reflect/Apply$;
Field	scala/reflect/Apply$.MODULE$:Lscala/reflect/Apply$;
Asciz	$init$;
Asciz	(Lscala/Function2;)V;
NameAndType	$init$:(Lscala/Function2;)V
Method	scala/Function2$class.$init$:(Lscala/Function2;)V
Asciz	scala/Function2;
class	scala/Function2
Asciz	scala/ScalaObject;
class	scala/ScalaObject

{
public static final scala.reflect.Apply$ MODULE$;
  Signature: Lscala/reflect/Apply$;

public static {};
  Signature: ()V
  Code:
   Stack=1, Locals=0, Args_size=0
	new	class scala/reflect/Apply$
	invokespecial	Method "<init>":()V
	return
  Labels:

public java.lang.String toString();
  Signature: ()Ljava/lang/String;
  Code:
   Stack=1, Locals=1, Args_size=1
	aload_0
	invokestatic	Method scala/Function2$class.toString:(Lscala/Function2;)Ljava/lang/String;
	areturn
  Labels:

public scala.Function1 curried();
  Signature: ()Lscala/Function1;
  Code:
   Stack=1, Locals=1, Args_size=1
	aload_0
	invokestatic	Method scala/Function2$class.curried:(Lscala/Function2;)Lscala/Function1;
	areturn
  Labels:

public scala.Function1 curry();
  Signature: ()Lscala/Function1;
  Code:
   Stack=1, Locals=1, Args_size=1
	aload_0
	invokestatic	Method scala/Function2$class.curry:(Lscala/Function2;)Lscala/Function1;
	areturn
  Labels:
  Deprecated: true

public scala.Function1 tupled();
  Signature: ()Lscala/Function1;
  Code:
   Stack=1, Locals=1, Args_size=1
	aload_0
	invokestatic	Method scala/Function2$class.tupled:(Lscala/Function2;)Lscala/Function1;
	areturn
  Labels:

public scala.Some unapply(scala.reflect.Apply);
  Signature: (Lscala/reflect/Apply;)Lscala/Some;
  Code:
   Stack=6, Locals=2, Args_size=2
	new	class scala/Some
	dup
	new	class scala/Tuple2
	dup
	aload_1
	invokevirtual	Method scala/reflect/Apply.fun:()Lscala/reflect/Tree;
	aload_1
	invokevirtual	Method scala/reflect/Apply.args:()Lscala/collection/immutable/List;
	invokespecial	Method scala/Tuple2."<init>":(Ljava/lang/Object;Ljava/lang/Object;)V
	invokespecial	Method scala/Some."<init>":(Ljava/lang/Object;)V
	areturn
  Labels:
  LocalVariableTable: 
   Start  Length  Slot  Name   Signature
   0      23      0    this       Lscala/reflect/Apply$;
   0      23      1    x$0       Lscala/reflect/Apply;


public scala.reflect.Apply apply(scala.reflect.Tree, scala.collection.immutable.List);
  Signature: (Lscala/reflect/Tree;Lscala/collection/immutable/List;)Lscala/reflect/Apply;
  Code:
   Stack=4, Locals=3, Args_size=3
	new	class scala/reflect/Apply
	dup
	aload_1
	aload_2
	invokespecial	Method scala/reflect/Apply."<init>":(Lscala/reflect/Tree;Lscala/collection/immutable/List;)V
	areturn
  Labels:
  LocalVariableTable: 
   Start  Length  Slot  Name   Signature
   0      10      0    this       Lscala/reflect/Apply$;
   0      10      1    fun       Lscala/reflect/Tree;
   0      10      2    args       Lscala/collection/immutable/List;


public java.lang.Object apply(java.lang.Object, java.lang.Object);
  Signature: (Ljava/lang/Object;Ljava/lang/Object;)Ljava/lang/Object;
  Code:
   Stack=3, Locals=3, Args_size=3
	aload_0
	aload_1
	checkcast	class scala/reflect/Tree
	aload_2
	checkcast	class scala/collection/immutable/List
	invokevirtual	Method apply:(Lscala/reflect/Tree;Lscala/collection/immutable/List;)Lscala/reflect/Apply;
	areturn
  Labels:
  LocalVariableTable: 
   Start  Length  Slot  Name   Signature
   0      13      0    this       Lscala/reflect/Apply$;
   0      13      1    v1       Ljava/lang/Object;
   0      13      2    v2       Ljava/lang/Object;


private scala.reflect.Apply$();
  Signature: ()V
  Code:
   Stack=1, Locals=1, Args_size=1
	aload_0
	invokespecial	Method java/lang/Object."<init>":()V
	aload_0
	putstatic	Field MODULE$:Lscala/reflect/Apply$;
	aload_0
	invokestatic	Method scala/Function2$class.$init$:(Lscala/Function2;)V
	return
  Labels:

}

