Compiled from "Tree.scala"
public class scala.reflect.Assign extends scala.reflect.Tree implements scala.ScalaObject,scala.Product,java.io.Serializable
  SourceFile: "Tree.scala"
  ScalaSig: length = 0x3
   05 00 00 
  RuntimeVisibleAnnotations: length = 0xB
   00 01 00 FFFFFF80 00 01 00 FFFFFF81 73 00 FFFFFF82 
  minor version: 0
  major version: 49
  Constant pool:
Asciz	SourceFile;
Asciz	Tree.scala;
Asciz	tupled;
Asciz	()Lscala/Function1;;
Asciz	Code;
Asciz	scala/reflect/Assign$;
class	scala/reflect/Assign$
Asciz	MODULE$;
Asciz	Lscala/reflect/Assign$;;
NameAndType	MODULE$:Lscala/reflect/Assign$;
Field	scala/reflect/Assign$.MODULE$:Lscala/reflect/Assign$;
NameAndType	tupled:()Lscala/Function1;
Method	scala/reflect/Assign$.tupled:()Lscala/Function1;
Asciz	curry;
NameAndType	curry:()Lscala/Function1;
Method	scala/reflect/Assign$.curry:()Lscala/Function1;
Asciz	Deprecated;
Asciz	curried;
NameAndType	curried:()Lscala/Function1;
Method	scala/reflect/Assign$.curried:()Lscala/Function1;
Asciz	destination;
Asciz	Lscala/reflect/Tree;;
Asciz	source;
Asciz	productElementName;
Asciz	(I)Ljava/lang/String;;
Asciz	LineNumberTable;
Asciz	scala/Product$class;
class	scala/Product$class
Asciz	(Lscala/Product;I)Ljava/lang/String;;
NameAndType	productElementName:(Lscala/Product;I)Ljava/lang/String;
Method	scala/Product$class.productElementName:(Lscala/Product;I)Ljava/lang/String;
Asciz	this;
Asciz	Lscala/reflect/Assign;;
Asciz	n;
Asciz	I;
Asciz	LocalVariableTable;
Asciz	productIterator;
Asciz	()Lscala/collection/Iterator;;
Asciz	(Lscala/Product;)Lscala/collection/Iterator;;
NameAndType	productIterator:(Lscala/Product;)Lscala/collection/Iterator;
Method	scala/Product$class.productIterator:(Lscala/Product;)Lscala/collection/Iterator;
Asciz	productElements;
NameAndType	productElements:(Lscala/Product;)Lscala/collection/Iterator;
Method	scala/Product$class.productElements:(Lscala/Product;)Lscala/collection/Iterator;
Asciz	copy$default$2;
Asciz	()Lscala/reflect/Tree;;
Asciz	scala/reflect/Assign;
class	scala/reflect/Assign
NameAndType	source:()Lscala/reflect/Tree;
Method	scala/reflect/Assign.source:()Lscala/reflect/Tree;
Asciz	copy$default$1;
NameAndType	destination:()Lscala/reflect/Tree;
Method	scala/reflect/Assign.destination:()Lscala/reflect/Tree;
NameAndType	destination:Lscala/reflect/Tree;
Field	scala/reflect/Assign.destination:Lscala/reflect/Tree;
NameAndType	source:Lscala/reflect/Tree;
Field	scala/reflect/Assign.source:Lscala/reflect/Tree;
Asciz	copy;
Asciz	(Lscala/reflect/Tree;Lscala/reflect/Tree;)Lscala/reflect/Assign;;
Asciz	<init>;
Asciz	(Lscala/reflect/Tree;Lscala/reflect/Tree;)V;
NameAndType	"<init>":(Lscala/reflect/Tree;Lscala/reflect/Tree;)V
Method	scala/reflect/Assign."<init>":(Lscala/reflect/Tree;Lscala/reflect/Tree;)V
Asciz	hashCode;
Asciz	()I;
Asciz	scala/runtime/ScalaRunTime$;
class	scala/runtime/ScalaRunTime$
Asciz	Lscala/runtime/ScalaRunTime$;;
NameAndType	MODULE$:Lscala/runtime/ScalaRunTime$;
Field	scala/runtime/ScalaRunTime$.MODULE$:Lscala/runtime/ScalaRunTime$;
Asciz	_hashCode;
Asciz	(Lscala/Product;)I;
NameAndType	_hashCode:(Lscala/Product;)I
Method	scala/runtime/ScalaRunTime$._hashCode:(Lscala/Product;)I
Asciz	toString;
Asciz	()Ljava/lang/String;;
Asciz	_toString;
Asciz	(Lscala/Product;)Ljava/lang/String;;
NameAndType	_toString:(Lscala/Product;)Ljava/lang/String;
Method	scala/runtime/ScalaRunTime$._toString:(Lscala/Product;)Ljava/lang/String;
Asciz	equals;
Asciz	(Ljava/lang/Object;)Z;
Asciz	gd11$1;
Asciz	(Lscala/reflect/Tree;Lscala/reflect/Tree;)Z;
NameAndType	gd11$1:(Lscala/reflect/Tree;Lscala/reflect/Tree;)Z
Method	scala/reflect/Assign.gd11$1:(Lscala/reflect/Tree;Lscala/reflect/Tree;)Z
Asciz	scala/Equals;
class	scala/Equals
Asciz	canEqual;
NameAndType	canEqual:(Ljava/lang/Object;)Z
InterfaceMethod	scala/Equals.canEqual:(Ljava/lang/Object;)Z
Asciz	temp49;
Asciz	temp50;
Asciz	temp51;
Asciz	productPrefix;
Asciz	Assign;
String	Assign
Asciz	productArity;
Asciz	productElement;
Asciz	(I)Ljava/lang/Object;;
Asciz	java/lang/IndexOutOfBoundsException;
class	java/lang/IndexOutOfBoundsException
Asciz	scala/runtime/BoxesRunTime;
class	scala/runtime/BoxesRunTime
Asciz	boxToInteger;
Asciz	(I)Ljava/lang/Integer;;
NameAndType	boxToInteger:(I)Ljava/lang/Integer;
Method	scala/runtime/BoxesRunTime.boxToInteger:(I)Ljava/lang/Integer;
Asciz	java/lang/Object;
class	java/lang/Object
NameAndType	toString:()Ljava/lang/String;
Method	java/lang/Object.toString:()Ljava/lang/String;
Asciz	(Ljava/lang/String;)V;
NameAndType	"<init>":(Ljava/lang/String;)V
Method	java/lang/IndexOutOfBoundsException."<init>":(Ljava/lang/String;)V
NameAndType	equals:(Ljava/lang/Object;)Z
Method	java/lang/Object.equals:(Ljava/lang/Object;)Z
Asciz	scala/reflect/Tree;
class	scala/reflect/Tree
Asciz	()V;
NameAndType	"<init>":()V
Method	scala/reflect/Tree."<init>":()V
Asciz	$init$;
Asciz	(Lscala/Product;)V;
NameAndType	$init$:(Lscala/Product;)V
Method	scala/Product$class.$init$:(Lscala/Product;)V
Asciz	ScalaSig;
Asciz	Lscala/reflect/ScalaSignature;;
Asciz	bytes;
Asciz	=aC\t\tQ\r8/[4o\tA!AsKdWm;\tQa]2bYa1CABA!&/Z35qQ\"\n=!!aC*dC2wJ6fGR\"!D\t\nI!!a)s_,8\r\t))!C+YA-Z:uS:G/[8o+AC#,7^5oCRLwN\te!Q3AU\taa]8ve,C#M|WO]2fA!)QC=1A(8jiz\"2a\"!\tIC9C9C$I\t\r|/?2b#!\r3\t\n1\tA!%A%\nabY8qs\"WMZ1vYR$'F+U\tA1fK-!\ti#'D/\ty'Av]DWmY6fI*BC:tw^1uS>tBA/E)hn5fG.,GMV1sSt7-k\t\n\"*9w]=%I4-7uIIBb%\tO\tQnQ8eKR\tu%1:$C\tI\t Q|7:j]$a\ts!!D!\n\t#A)sK,g-E\n11:j]T!A\tA!AB!a!Z9vC2HCA%M!\ti!*L\t\t9!i\8mKtbB'G\rATq\nCAP\tFAAB]fDB%\teUaJ|G-^2u!J,g-=Q\"!.YS!a-\t1gn3!!.<b\t!e]\t\"^1(o3vGR%/;z+IC0\tI\t1AxZ;dicW-\3oiRa*z\t1:!\"A\n\"C2b]X/7%+bB'c\rA\"!5\n%$!D:fe&G.>bE2,waB6E)\Nn8%igC\t\tR8\t5|'\t+BL!!,\r='.Z2u!i1 \t!HAAGk:G/[8oe!)Q$CmR\tACy[IQ=\=}Q8CoCoC~[I@Ut\r9msRq0a5\t\t!!\n\rAAPaRLwN\tC!!A+va2,'q\raHq;
Asciz	RuntimeVisibleAnnotations;
Asciz	scala/ScalaObject;
class	scala/ScalaObject
Asciz	scala/Product;
class	scala/Product
Asciz	java/io/Serializable;
class	java/io/Serializable

{
private final scala.reflect.Tree destination;
  Signature: Lscala/reflect/Tree;

private final scala.reflect.Tree source;
  Signature: Lscala/reflect/Tree;

public static final scala.Function1 tupled();
  Signature: ()Lscala/Function1;
  Code:
   Stack=1, Locals=0, Args_size=0
	getstatic	Field scala/reflect/Assign$.MODULE$:Lscala/reflect/Assign$;
	invokevirtual	Method scala/reflect/Assign$.tupled:()Lscala/Function1;
	areturn
  Labels:

public static final scala.Function1 curry();
  Signature: ()Lscala/Function1;
  Code:
   Stack=1, Locals=0, Args_size=0
	getstatic	Field scala/reflect/Assign$.MODULE$:Lscala/reflect/Assign$;
	invokevirtual	Method scala/reflect/Assign$.curry:()Lscala/Function1;
	areturn
  Labels:
  Deprecated: true

public static final scala.Function1 curried();
  Signature: ()Lscala/Function1;
  Code:
   Stack=1, Locals=0, Args_size=0
	getstatic	Field scala/reflect/Assign$.MODULE$:Lscala/reflect/Assign$;
	invokevirtual	Method scala/reflect/Assign$.curried:()Lscala/Function1;
	areturn
  Labels:

public java.lang.String productElementName(int);
  Signature: (I)Ljava/lang/String;
  Code:
   Stack=2, Locals=2, Args_size=2
	aload_0
	iload_1
	invokestatic	Method scala/Product$class.productElementName:(Lscala/Product;I)Ljava/lang/String;
	areturn
  Labels:
  LocalVariableTable: 
   Start  Length  Slot  Name   Signature
   0      6      0    this       Lscala/reflect/Assign;
   0      6      1    n       I


public scala.collection.Iterator productIterator();
  Signature: ()Lscala/collection/Iterator;
  Code:
   Stack=1, Locals=1, Args_size=1
	aload_0
	invokestatic	Method scala/Product$class.productIterator:(Lscala/Product;)Lscala/collection/Iterator;
	areturn
  Labels:

public scala.collection.Iterator productElements();
  Signature: ()Lscala/collection/Iterator;
  Code:
   Stack=1, Locals=1, Args_size=1
	aload_0
	invokestatic	Method scala/Product$class.productElements:(Lscala/Product;)Lscala/collection/Iterator;
	areturn
  Labels:
  Deprecated: true

public scala.reflect.Tree copy$default$2();
  Signature: ()Lscala/reflect/Tree;
  Code:
   Stack=1, Locals=1, Args_size=1
	aload_0
	invokevirtual	Method source:()Lscala/reflect/Tree;
	areturn
  Labels:

public scala.reflect.Tree copy$default$1();
  Signature: ()Lscala/reflect/Tree;
  Code:
   Stack=1, Locals=1, Args_size=1
	aload_0
	invokevirtual	Method destination:()Lscala/reflect/Tree;
	areturn
  Labels:

public scala.reflect.Tree destination();
  Signature: ()Lscala/reflect/Tree;
  Code:
   Stack=1, Locals=1, Args_size=1
	aload_0
	getfield	Field destination:Lscala/reflect/Tree;
	areturn
  Labels:

public scala.reflect.Tree source();
  Signature: ()Lscala/reflect/Tree;
  Code:
   Stack=1, Locals=1, Args_size=1
	aload_0
	getfield	Field source:Lscala/reflect/Tree;
	areturn
  Labels:

public scala.reflect.Assign copy(scala.reflect.Tree, scala.reflect.Tree);
  Signature: (Lscala/reflect/Tree;Lscala/reflect/Tree;)Lscala/reflect/Assign;
  Code:
   Stack=4, Locals=3, Args_size=3
	new	class scala/reflect/Assign
	dup
	aload_1
	aload_2
	invokespecial	Method "<init>":(Lscala/reflect/Tree;Lscala/reflect/Tree;)V
	areturn
  Labels:
  LocalVariableTable: 
   Start  Length  Slot  Name   Signature
   0      10      0    this       Lscala/reflect/Assign;
   0      10      1    destination       Lscala/reflect/Tree;
   0      10      2    source       Lscala/reflect/Tree;


public int hashCode();
  Signature: ()I
  Code:
   Stack=2, Locals=1, Args_size=1
	getstatic	Field scala/runtime/ScalaRunTime$.MODULE$:Lscala/runtime/ScalaRunTime$;
	aload_0
	invokevirtual	Method scala/runtime/ScalaRunTime$._hashCode:(Lscala/Product;)I
	ireturn
  Labels:

public java.lang.String toString();
  Signature: ()Ljava/lang/String;
  Code:
   Stack=2, Locals=1, Args_size=1
	getstatic	Field scala/runtime/ScalaRunTime$.MODULE$:Lscala/runtime/ScalaRunTime$;
	aload_0
	invokevirtual	Method scala/runtime/ScalaRunTime$._toString:(Lscala/Product;)Ljava/lang/String;
	areturn
  Labels:

public boolean equals(java.lang.Object);
  Signature: (Ljava/lang/Object;)Z
  Code:
   Stack=3, Locals=5, Args_size=2
	aload_0
	aload_1
	if_acmpeq	l1 // iconst_1
	aload_1
	instanceof	class scala/reflect/Assign
	ifeq	l2 // iconst_0
	aload_1
	checkcast	class scala/reflect/Assign
	astore_2
	aload_2
	invokevirtual	Method destination:()Lscala/reflect/Tree;
	astore_3
	aload_2
	invokevirtual	Method source:()Lscala/reflect/Tree;
	astore	4
	aload_0
	aload_3
	aload	4
	invokespecial	Method gd11$1:(Lscala/reflect/Tree;Lscala/reflect/Tree;)Z
	ifeq	l3 // iconst_0
	aload_1
	checkcast	class scala/reflect/Assign
	aload_0
	invokeinterface	InterfaceMethod scala/Equals.canEqual:(Ljava/lang/Object;)Z
	goto	l4 // ifeq
l3	iconst_0
	goto	l4 // ifeq
l2	iconst_0
l4	ifeq	l5 // iconst_0
l1	iconst_1
	goto	l6 // ireturn
l5	iconst_0
l6	ireturn
  Labels:
   	l3 = 51 // iconst_0
   	l2 = 55 // iconst_0
   	l4 = 56 // ifeq
   	l1 = 59 // iconst_1
   	l5 = 63 // iconst_0
   	l6 = 64 // ireturn
  LocalVariableTable: 
   Start  Length  Slot  Name   Signature
   0      65      0    this       Lscala/reflect/Assign;
   17      38      2    temp49       Lscala/reflect/Assign;
   22      33      3    temp50       Lscala/reflect/Tree;
   28      27      4    temp51       Lscala/reflect/Tree;


public java.lang.String productPrefix();
  Signature: ()Ljava/lang/String;
  Code:
   Stack=1, Locals=1, Args_size=1
	ldc	String Assign
	areturn
  Labels:

public int productArity();
  Signature: ()I
  Code:
   Stack=1, Locals=1, Args_size=1
	iconst_2
	ireturn
  Labels:

public java.lang.Object productElement(int);
  Signature: (I)Ljava/lang/Object;
  Code:
   Stack=3, Locals=2, Args_size=2
	iload_1
	tableswitch{ //0 to 1
		0: 46;
		1: 39;
		default: 24 }
	new	class java/lang/IndexOutOfBoundsException
	dup
	iload_1
	invokestatic	Method scala/runtime/BoxesRunTime.boxToInteger:(I)Ljava/lang/Integer;
	invokevirtual	Method java/lang/Object.toString:()Ljava/lang/String;
	invokespecial	Method java/lang/IndexOutOfBoundsException."<init>":(Ljava/lang/String;)V
	athrow
	aload_0
	invokevirtual	Method source:()Lscala/reflect/Tree;
	goto	l1 // areturn
	aload_0
	invokevirtual	Method destination:()Lscala/reflect/Tree;
l1	areturn
  Labels:
   	l1 = 50 // areturn

public boolean canEqual(java.lang.Object);
  Signature: (Ljava/lang/Object;)Z
  Code:
   Stack=1, Locals=2, Args_size=2
	aload_1
	instanceof	class scala/reflect/Assign
	ireturn
  Labels:

private final boolean gd11$1(scala.reflect.Tree, scala.reflect.Tree);
  Signature: (Lscala/reflect/Tree;Lscala/reflect/Tree;)Z
  Code:
   Stack=2, Locals=5, Args_size=3
	aload_1
	aload_0
	invokevirtual	Method destination:()Lscala/reflect/Tree;
	astore_3
	dup
	ifnonnull	l1 // aload_3
	pop
	aload_3
	ifnull	l2 // aload_2
	goto	l3 // iconst_0
l1	aload_3
	invokevirtual	Method java/lang/Object.equals:(Ljava/lang/Object;)Z
	ifeq	l3 // iconst_0
l2	aload_2
	aload_0
	invokevirtual	Method source:()Lscala/reflect/Tree;
	astore	4
	dup
	ifnonnull	l4 // aload
	pop
	aload	4
	ifnull	l5 // iconst_1
	goto	l3 // iconst_0
l4	aload	4
	invokevirtual	Method java/lang/Object.equals:(Ljava/lang/Object;)Z
	ifeq	l3 // iconst_0
l5	iconst_1
	goto	l6 // ireturn
l3	iconst_0
l6	ireturn
  Labels:
   	l1 = 18 // aload_3
   	l2 = 25 // aload_2
   	l4 = 45 // aload
   	l5 = 53 // iconst_1
   	l3 = 57 // iconst_0
   	l6 = 58 // ireturn

public scala.reflect.Assign(scala.reflect.Tree, scala.reflect.Tree);
  Signature: (Lscala/reflect/Tree;Lscala/reflect/Tree;)V
  Code:
   Stack=2, Locals=3, Args_size=3
	aload_0
	aload_1
	putfield	Field destination:Lscala/reflect/Tree;
	aload_0
	aload_2
	putfield	Field source:Lscala/reflect/Tree;
	aload_0
	invokespecial	Method scala/reflect/Tree."<init>":()V
	aload_0
	invokestatic	Method scala/Product$class.$init$:(Lscala/Product;)V
	return
  Labels:
  LocalVariableTable: 
   Start  Length  Slot  Name   Signature
   0      19      0    this       Lscala/reflect/Assign;
   0      19      1    destination       Lscala/reflect/Tree;
   0      19      2    source       Lscala/reflect/Tree;


}

