Compiled from "Tree.scala"
public class scala.reflect.Block extends scala.reflect.Tree implements scala.ScalaObject,scala.Product,java.io.Serializable
  SourceFile: "Tree.scala"
  ScalaSig: length = 0x3
   05 00 00 
  RuntimeVisibleAnnotations: length = 0xB
   00 01 00 FFFFFF86 00 01 00 FFFFFF87 73 00 FFFFFF88 
  minor version: 0
  major version: 49
  Constant pool:
Asciz	SourceFile;
Asciz	Tree.scala;
Asciz	tupled;
Asciz	()Lscala/Function1;;
Asciz	Code;
Asciz	scala/reflect/Block$;
class	scala/reflect/Block$
Asciz	MODULE$;
Asciz	Lscala/reflect/Block$;;
NameAndType	MODULE$:Lscala/reflect/Block$;
Field	scala/reflect/Block$.MODULE$:Lscala/reflect/Block$;
NameAndType	tupled:()Lscala/Function1;
Method	scala/reflect/Block$.tupled:()Lscala/Function1;
Asciz	curry;
NameAndType	curry:()Lscala/Function1;
Method	scala/reflect/Block$.curry:()Lscala/Function1;
Asciz	Deprecated;
Asciz	curried;
NameAndType	curried:()Lscala/Function1;
Method	scala/reflect/Block$.curried:()Lscala/Function1;
Asciz	stats;
Asciz	Lscala/collection/immutable/List;;
Asciz	Lscala/collection/immutable/List<Lscala/reflect/Tree;>;;
Asciz	Signature;
Asciz	expr;
Asciz	Lscala/reflect/Tree;;
Asciz	productElementName;
Asciz	(I)Ljava/lang/String;;
Asciz	LineNumberTable;
Asciz	scala/Product$class;
class	scala/Product$class
Asciz	(Lscala/Product;I)Ljava/lang/String;;
NameAndType	productElementName:(Lscala/Product;I)Ljava/lang/String;
Method	scala/Product$class.productElementName:(Lscala/Product;I)Ljava/lang/String;
Asciz	this;
Asciz	Lscala/reflect/Block;;
Asciz	n;
Asciz	I;
Asciz	LocalVariableTable;
Asciz	productIterator;
Asciz	()Lscala/collection/Iterator;;
Asciz	(Lscala/Product;)Lscala/collection/Iterator;;
NameAndType	productIterator:(Lscala/Product;)Lscala/collection/Iterator;
Method	scala/Product$class.productIterator:(Lscala/Product;)Lscala/collection/Iterator;
Asciz	productElements;
NameAndType	productElements:(Lscala/Product;)Lscala/collection/Iterator;
Method	scala/Product$class.productElements:(Lscala/Product;)Lscala/collection/Iterator;
Asciz	copy$default$2;
Asciz	()Lscala/reflect/Tree;;
Asciz	scala/reflect/Block;
class	scala/reflect/Block
NameAndType	expr:()Lscala/reflect/Tree;
Method	scala/reflect/Block.expr:()Lscala/reflect/Tree;
Asciz	copy$default$1;
Asciz	()Lscala/collection/immutable/List;;
NameAndType	stats:()Lscala/collection/immutable/List;
Method	scala/reflect/Block.stats:()Lscala/collection/immutable/List;
NameAndType	stats:Lscala/collection/immutable/List;
Field	scala/reflect/Block.stats:Lscala/collection/immutable/List;
Asciz	()Lscala/collection/immutable/List<Lscala/reflect/Tree;>;;
NameAndType	expr:Lscala/reflect/Tree;
Field	scala/reflect/Block.expr:Lscala/reflect/Tree;
Asciz	copy;
Asciz	(Lscala/collection/immutable/List;Lscala/reflect/Tree;)Lscala/reflect/Block;;
Asciz	<init>;
Asciz	(Lscala/collection/immutable/List;Lscala/reflect/Tree;)V;
NameAndType	"<init>":(Lscala/collection/immutable/List;Lscala/reflect/Tree;)V
Method	scala/reflect/Block."<init>":(Lscala/collection/immutable/List;Lscala/reflect/Tree;)V
Asciz	hashCode;
Asciz	()I;
Asciz	scala/runtime/ScalaRunTime$;
class	scala/runtime/ScalaRunTime$
Asciz	Lscala/runtime/ScalaRunTime$;;
NameAndType	MODULE$:Lscala/runtime/ScalaRunTime$;
Field	scala/runtime/ScalaRunTime$.MODULE$:Lscala/runtime/ScalaRunTime$;
Asciz	_hashCode;
Asciz	(Lscala/Product;)I;
NameAndType	_hashCode:(Lscala/Product;)I
Method	scala/runtime/ScalaRunTime$._hashCode:(Lscala/Product;)I
Asciz	toString;
Asciz	()Ljava/lang/String;;
Asciz	_toString;
Asciz	(Lscala/Product;)Ljava/lang/String;;
NameAndType	_toString:(Lscala/Product;)Ljava/lang/String;
Method	scala/runtime/ScalaRunTime$._toString:(Lscala/Product;)Ljava/lang/String;
Asciz	equals;
Asciz	(Ljava/lang/Object;)Z;
Asciz	gd8$1;
Asciz	(Lscala/collection/immutable/List;Lscala/reflect/Tree;)Z;
NameAndType	gd8$1:(Lscala/collection/immutable/List;Lscala/reflect/Tree;)Z
Method	scala/reflect/Block.gd8$1:(Lscala/collection/immutable/List;Lscala/reflect/Tree;)Z
Asciz	scala/Equals;
class	scala/Equals
Asciz	canEqual;
NameAndType	canEqual:(Ljava/lang/Object;)Z
InterfaceMethod	scala/Equals.canEqual:(Ljava/lang/Object;)Z
Asciz	temp34;
Asciz	temp35;
Asciz	temp36;
Asciz	productPrefix;
Asciz	Block;
String	Block
Asciz	productArity;
Asciz	productElement;
Asciz	(I)Ljava/lang/Object;;
Asciz	java/lang/IndexOutOfBoundsException;
class	java/lang/IndexOutOfBoundsException
Asciz	scala/runtime/BoxesRunTime;
class	scala/runtime/BoxesRunTime
Asciz	boxToInteger;
Asciz	(I)Ljava/lang/Integer;;
NameAndType	boxToInteger:(I)Ljava/lang/Integer;
Method	scala/runtime/BoxesRunTime.boxToInteger:(I)Ljava/lang/Integer;
Asciz	java/lang/Object;
class	java/lang/Object
NameAndType	toString:()Ljava/lang/String;
Method	java/lang/Object.toString:()Ljava/lang/String;
Asciz	(Ljava/lang/String;)V;
NameAndType	"<init>":(Ljava/lang/String;)V
Method	java/lang/IndexOutOfBoundsException."<init>":(Ljava/lang/String;)V
NameAndType	equals:(Ljava/lang/Object;)Z
Method	java/lang/Object.equals:(Ljava/lang/Object;)Z
Asciz	scala/reflect/Tree;
class	scala/reflect/Tree
Asciz	()V;
NameAndType	"<init>":()V
Method	scala/reflect/Tree."<init>":()V
Asciz	$init$;
Asciz	(Lscala/Product;)V;
NameAndType	$init$:(Lscala/Product;)V
Method	scala/Product$class.$init$:(Lscala/Product;)V
Asciz	(Lscala/collection/immutable/List<Lscala/reflect/Tree;>;Lscala/reflect/Tree;)V;
Asciz	ScalaSig;
Asciz	Lscala/reflect/ScalaSignature;;
Asciz	bytes;
Asciz	bC\t\tQ\tcwnY6\r!a:fM2,7\r)1oY1mC1\tA\"!\tI!a\tQX-\t9iB1bU2bY|%M[3diBQ\"E%q:pIVG\tU\r\"H/;t+1cA5\tD5I.\7viG.7\t!bY8mYG/[8o\tiDMSN$C#\rM$\r^:!!\tA!f\nB3yaJ,\tI\t)A)Q\r9sA!)aCO1A(8jiz\"2K+!\tICKaC\"KC-IA\t\r|/Q9zb,!\rAC-\n1\t\t!%AI\nabY8qs\"WMZ1vYR$'F4U\t1BgK6!\t14(D8\tA(Av]DWmY6fI*!BC:tw^1uS>tB8E)hn5fG.,GMV1sSt7-}\t\n\"@9w]=%I4-7uII*QBB%\teQ\tQnQ8eKR\tA\t&a\t:$%\tII%Q|7:j]$A\t:s!!'\n5#A)sK,g-P!\n11:j]T!!\tIA!ABMa!Z9vC2HC+X!\tiQ+W\t\t9!i\8mKtb-R\r!Wq\nCA[\tYFAAB]fD\"%\tEXaJ|G-^2u!J,g-=}\"Y3T!AY2\t1gnI!!.<b\ty\rh\t\"i1(o3vGR%/;z+!6\tII6AxZ;dicW-\3oiR1&\t1E!q\"A\nzC2b]X/7Qb-n\r!I\"!D:\nQ$!D:fe&G.>bE2,wa<E)a^2|7m\ta4\"E)!_\nqjlHaw&A0\nTWm;5qh\n}$!!$v]$n831\"Q\tqCa\t\"!\n)\r9msR)&a!1A#!AYAa!IAA\"CA\tqIQA\n)h.9qYf$B!!\"A)Q\"a%\r=H/[8o!iQ\t\r\ty)VH.\t\rqaQ\n;
Asciz	RuntimeVisibleAnnotations;
Asciz	scala/ScalaObject;
class	scala/ScalaObject
Asciz	scala/Product;
class	scala/Product
Asciz	java/io/Serializable;
class	java/io/Serializable

{
private final scala.collection.immutable.List stats;
  Signature: Lscala/collection/immutable/List;
  Signature: length = 0x2
   00 17 

private final scala.reflect.Tree expr;
  Signature: Lscala/reflect/Tree;

public static final scala.Function1 tupled();
  Signature: ()Lscala/Function1;
  Code:
   Stack=1, Locals=0, Args_size=0
	getstatic	Field scala/reflect/Block$.MODULE$:Lscala/reflect/Block$;
	invokevirtual	Method scala/reflect/Block$.tupled:()Lscala/Function1;
	areturn
  Labels:

public static final scala.Function1 curry();
  Signature: ()Lscala/Function1;
  Code:
   Stack=1, Locals=0, Args_size=0
	getstatic	Field scala/reflect/Block$.MODULE$:Lscala/reflect/Block$;
	invokevirtual	Method scala/reflect/Block$.curry:()Lscala/Function1;
	areturn
  Labels:
  Deprecated: true

public static final scala.Function1 curried();
  Signature: ()Lscala/Function1;
  Code:
   Stack=1, Locals=0, Args_size=0
	getstatic	Field scala/reflect/Block$.MODULE$:Lscala/reflect/Block$;
	invokevirtual	Method scala/reflect/Block$.curried:()Lscala/Function1;
	areturn
  Labels:

public java.lang.String productElementName(int);
  Signature: (I)Ljava/lang/String;
  Code:
   Stack=2, Locals=2, Args_size=2
	aload_0
	iload_1
	invokestatic	Method scala/Product$class.productElementName:(Lscala/Product;I)Ljava/lang/String;
	areturn
  Labels:
  LocalVariableTable: 
   Start  Length  Slot  Name   Signature
   0      6      0    this       Lscala/reflect/Block;
   0      6      1    n       I


public scala.collection.Iterator productIterator();
  Signature: ()Lscala/collection/Iterator;
  Code:
   Stack=1, Locals=1, Args_size=1
	aload_0
	invokestatic	Method scala/Product$class.productIterator:(Lscala/Product;)Lscala/collection/Iterator;
	areturn
  Labels:

public scala.collection.Iterator productElements();
  Signature: ()Lscala/collection/Iterator;
  Code:
   Stack=1, Locals=1, Args_size=1
	aload_0
	invokestatic	Method scala/Product$class.productElements:(Lscala/Product;)Lscala/collection/Iterator;
	areturn
  Labels:
  Deprecated: true

public scala.reflect.Tree copy$default$2();
  Signature: ()Lscala/reflect/Tree;
  Code:
   Stack=1, Locals=1, Args_size=1
	aload_0
	invokevirtual	Method expr:()Lscala/reflect/Tree;
	areturn
  Labels:

public scala.collection.immutable.List copy$default$1();
  Signature: ()Lscala/collection/immutable/List;
  Code:
   Stack=1, Locals=1, Args_size=1
	aload_0
	invokevirtual	Method stats:()Lscala/collection/immutable/List;
	areturn
  Labels:

public scala.collection.immutable.List stats();
  Signature: ()Lscala/collection/immutable/List;
  Code:
   Stack=1, Locals=1, Args_size=1
	aload_0
	getfield	Field stats:Lscala/collection/immutable/List;
	areturn
  Labels:
  Signature: length = 0x2
   00 3C 

public scala.reflect.Tree expr();
  Signature: ()Lscala/reflect/Tree;
  Code:
   Stack=1, Locals=1, Args_size=1
	aload_0
	getfield	Field expr:Lscala/reflect/Tree;
	areturn
  Labels:

public scala.reflect.Block copy(scala.collection.immutable.List, scala.reflect.Tree);
  Signature: (Lscala/collection/immutable/List;Lscala/reflect/Tree;)Lscala/reflect/Block;
  Code:
   Stack=4, Locals=3, Args_size=3
	new	class scala/reflect/Block
	dup
	aload_1
	aload_2
	invokespecial	Method "<init>":(Lscala/collection/immutable/List;Lscala/reflect/Tree;)V
	areturn
  Labels:
  LocalVariableTable: 
   Start  Length  Slot  Name   Signature
   0      10      0    this       Lscala/reflect/Block;
   0      10      1    stats       Lscala/collection/immutable/List;
   0      10      2    expr       Lscala/reflect/Tree;


public int hashCode();
  Signature: ()I
  Code:
   Stack=2, Locals=1, Args_size=1
	getstatic	Field scala/runtime/ScalaRunTime$.MODULE$:Lscala/runtime/ScalaRunTime$;
	aload_0
	invokevirtual	Method scala/runtime/ScalaRunTime$._hashCode:(Lscala/Product;)I
	ireturn
  Labels:

public java.lang.String toString();
  Signature: ()Ljava/lang/String;
  Code:
   Stack=2, Locals=1, Args_size=1
	getstatic	Field scala/runtime/ScalaRunTime$.MODULE$:Lscala/runtime/ScalaRunTime$;
	aload_0
	invokevirtual	Method scala/runtime/ScalaRunTime$._toString:(Lscala/Product;)Ljava/lang/String;
	areturn
  Labels:

public boolean equals(java.lang.Object);
  Signature: (Ljava/lang/Object;)Z
  Code:
   Stack=3, Locals=5, Args_size=2
	aload_0
	aload_1
	if_acmpeq	l1 // iconst_1
	aload_1
	instanceof	class scala/reflect/Block
	ifeq	l2 // iconst_0
	aload_1
	checkcast	class scala/reflect/Block
	astore_2
	aload_2
	invokevirtual	Method stats:()Lscala/collection/immutable/List;
	astore_3
	aload_2
	invokevirtual	Method expr:()Lscala/reflect/Tree;
	astore	4
	aload_0
	aload_3
	aload	4
	invokespecial	Method gd8$1:(Lscala/collection/immutable/List;Lscala/reflect/Tree;)Z
	ifeq	l3 // iconst_0
	aload_1
	checkcast	class scala/reflect/Block
	aload_0
	invokeinterface	InterfaceMethod scala/Equals.canEqual:(Ljava/lang/Object;)Z
	goto	l4 // ifeq
l3	iconst_0
	goto	l4 // ifeq
l2	iconst_0
l4	ifeq	l5 // iconst_0
l1	iconst_1
	goto	l6 // ireturn
l5	iconst_0
l6	ireturn
  Labels:
   	l3 = 51 // iconst_0
   	l2 = 55 // iconst_0
   	l4 = 56 // ifeq
   	l1 = 59 // iconst_1
   	l5 = 63 // iconst_0
   	l6 = 64 // ireturn
  LocalVariableTable: 
   Start  Length  Slot  Name   Signature
   0      65      0    this       Lscala/reflect/Block;
   17      38      2    temp34       Lscala/reflect/Block;
   22      33      3    temp35       Lscala/collection/immutable/List;
   28      27      4    temp36       Lscala/reflect/Tree;


public java.lang.String productPrefix();
  Signature: ()Ljava/lang/String;
  Code:
   Stack=1, Locals=1, Args_size=1
	ldc	String Block
	areturn
  Labels:

public int productArity();
  Signature: ()I
  Code:
   Stack=1, Locals=1, Args_size=1
	iconst_2
	ireturn
  Labels:

public java.lang.Object productElement(int);
  Signature: (I)Ljava/lang/Object;
  Code:
   Stack=3, Locals=2, Args_size=2
	iload_1
	tableswitch{ //0 to 1
		0: 46;
		1: 39;
		default: 24 }
	new	class java/lang/IndexOutOfBoundsException
	dup
	iload_1
	invokestatic	Method scala/runtime/BoxesRunTime.boxToInteger:(I)Ljava/lang/Integer;
	invokevirtual	Method java/lang/Object.toString:()Ljava/lang/String;
	invokespecial	Method java/lang/IndexOutOfBoundsException."<init>":(Ljava/lang/String;)V
	athrow
	aload_0
	invokevirtual	Method expr:()Lscala/reflect/Tree;
	goto	l1 // areturn
	aload_0
	invokevirtual	Method stats:()Lscala/collection/immutable/List;
l1	areturn
  Labels:
   	l1 = 50 // areturn

public boolean canEqual(java.lang.Object);
  Signature: (Ljava/lang/Object;)Z
  Code:
   Stack=1, Locals=2, Args_size=2
	aload_1
	instanceof	class scala/reflect/Block
	ireturn
  Labels:

private final boolean gd8$1(scala.collection.immutable.List, scala.reflect.Tree);
  Signature: (Lscala/collection/immutable/List;Lscala/reflect/Tree;)Z
  Code:
   Stack=2, Locals=5, Args_size=3
	aload_1
	aload_0
	invokevirtual	Method stats:()Lscala/collection/immutable/List;
	astore_3
	dup
	ifnonnull	l1 // aload_3
	pop
	aload_3
	ifnull	l2 // aload_2
	goto	l3 // iconst_0
l1	aload_3
	invokevirtual	Method java/lang/Object.equals:(Ljava/lang/Object;)Z
	ifeq	l3 // iconst_0
l2	aload_2
	aload_0
	invokevirtual	Method expr:()Lscala/reflect/Tree;
	astore	4
	dup
	ifnonnull	l4 // aload
	pop
	aload	4
	ifnull	l5 // iconst_1
	goto	l3 // iconst_0
l4	aload	4
	invokevirtual	Method java/lang/Object.equals:(Ljava/lang/Object;)Z
	ifeq	l3 // iconst_0
l5	iconst_1
	goto	l6 // ireturn
l3	iconst_0
l6	ireturn
  Labels:
   	l1 = 18 // aload_3
   	l2 = 25 // aload_2
   	l4 = 45 // aload
   	l5 = 53 // iconst_1
   	l3 = 57 // iconst_0
   	l6 = 58 // ireturn

public scala.reflect.Block(scala.collection.immutable.List, scala.reflect.Tree);
  Signature: (Lscala/collection/immutable/List;Lscala/reflect/Tree;)V
  Code:
   Stack=2, Locals=3, Args_size=3
	aload_0
	aload_1
	putfield	Field stats:Lscala/collection/immutable/List;
	aload_0
	aload_2
	putfield	Field expr:Lscala/reflect/Tree;
	aload_0
	invokespecial	Method scala/reflect/Tree."<init>":()V
	aload_0
	invokestatic	Method scala/Product$class.$init$:(Lscala/Product;)V
	return
  Labels:
  LocalVariableTable: 
   Start  Length  Slot  Name   Signature
   0      19      0    this       Lscala/reflect/Block;
   0      19      1    stats       Lscala/collection/immutable/List;
   0      19      2    expr       Lscala/reflect/Tree;

  Signature: length = 0x2
   00 FFFFFF84 

}

