Compiled from "ClassManifest.scala"
public final class scala.reflect.ClassManifest$ extends java.lang.Object implements scala.ScalaObject
  SourceFile: "ClassManifest.scala"
  Scala: length = 0x
   
  InnerClass: 
   public final #266= #127 of #160; //$anon$1=class scala/reflect/ClassManifest$$anon$1 of class scala/reflect/ClassManifest
   public final #267= #115 of #160; //$anon$2=class scala/reflect/ClassManifest$$anon$2 of class scala/reflect/ClassManifest
   public #268= #171 of #160; //ClassTypeManifest=class scala/reflect/ClassManifest$ClassTypeManifest of class scala/reflect/ClassManifest
   public final #271= #270 of #160; //$anonfun$subargs$1$1=class scala/reflect/ClassManifest$$anonfun$subargs$1$1 of class scala/reflect/ClassManifest
   public final #274= #273 of #160; //$anonfun$subtype$1$1=class scala/reflect/ClassManifest$$anonfun$subtype$1$1 of class scala/reflect/ClassManifest
  minor version: 0
  major version: 49
  Constant pool:
const #1 = Asciz	SourceFile;
const #2 = Asciz	ClassManifest.scala;
const #3 = Asciz	Scala;
const #4 = Asciz	MODULE$;
const #5 = Asciz	Lscala/reflect/ClassManifest$;;
const #6 = Asciz	<clinit>;
const #7 = Asciz	()V;
const #8 = Asciz	Code;
const #9 = Asciz	scala/reflect/ClassManifest$;
const #10 = class	#9;	//  scala/reflect/ClassManifest$
const #11 = Asciz	<init>;
const #12 = NameAndType	#11:#7;//  "<init>":()V
const #13 = Method	#10.#12;	//  scala/reflect/ClassManifest$."<init>":()V
const #14 = Asciz	Null;
const #15 = Asciz	Lscala/reflect/Manifest;;
const #16 = Asciz	Lscala/reflect/Manifest<Lscala/runtime/Null$;>;;
const #17 = Asciz	Signature;
const #18 = Asciz	Nothing;
const #19 = Asciz	Lscala/reflect/Manifest<Lscala/runtime/Nothing$;>;;
const #20 = Asciz	AnyVal;
const #21 = Asciz	Lscala/reflect/Manifest<Ljava/lang/Object;>;;
const #22 = Asciz	Object;
const #23 = Asciz	Any;
const #24 = Asciz	Unit;
const #25 = Asciz	Lscala/reflect/AnyValManifest;;
const #26 = Asciz	Lscala/reflect/AnyValManifest<Ljava/lang/Object;>;;
const #27 = Asciz	Boolean;
const #28 = Asciz	Lscala/reflect/AnyValManifest<Ljava/lang/Boolean;>;;
const #29 = Asciz	Double;
const #30 = Asciz	Lscala/reflect/AnyValManifest<Ljava/lang/Double;>;;
const #31 = Asciz	Float;
const #32 = Asciz	Lscala/reflect/AnyValManifest<Ljava/lang/Float;>;;
const #33 = Asciz	Long;
const #34 = Asciz	Lscala/reflect/AnyValManifest<Ljava/lang/Long;>;;
const #35 = Asciz	Int;
const #36 = Asciz	Lscala/reflect/AnyValManifest<Ljava/lang/Integer;>;;
const #37 = Asciz	Char;
const #38 = Asciz	Lscala/reflect/AnyValManifest<Ljava/lang/Character;>;;
const #39 = Asciz	Short;
const #40 = Asciz	Lscala/reflect/AnyValManifest<Ljava/lang/Short;>;;
const #41 = Asciz	Byte;
const #42 = Asciz	Lscala/reflect/AnyValManifest<Ljava/lang/Byte;>;;
const #43 = Asciz	LineNumberTable;
const #44 = Asciz	java/lang/Object;
const #45 = class	#44;	//  java/lang/Object
const #46 = Method	#45.#12;	//  java/lang/Object."<init>":()V
const #47 = NameAndType	#4:#5;//  MODULE$:Lscala/reflect/ClassManifest$;
const #48 = Field	#10.#47;	//  scala/reflect/ClassManifest$.MODULE$:Lscala/reflect/ClassManifest$;
const #49 = Asciz	scala/reflect/Manifest$;
const #50 = class	#49;	//  scala/reflect/Manifest$
const #51 = Asciz	Lscala/reflect/Manifest$;;
const #52 = NameAndType	#4:#51;//  MODULE$:Lscala/reflect/Manifest$;
const #53 = Field	#50.#52;	//  scala/reflect/Manifest$.MODULE$:Lscala/reflect/Manifest$;
const #54 = Asciz	()Lscala/reflect/AnyValManifest;;
const #55 = NameAndType	#41:#54;//  Byte:()Lscala/reflect/AnyValManifest;
const #56 = Method	#50.#55;	//  scala/reflect/Manifest$.Byte:()Lscala/reflect/AnyValManifest;
const #57 = NameAndType	#41:#25;//  Byte:Lscala/reflect/AnyValManifest;
const #58 = Field	#10.#57;	//  scala/reflect/ClassManifest$.Byte:Lscala/reflect/AnyValManifest;
const #59 = NameAndType	#39:#54;//  Short:()Lscala/reflect/AnyValManifest;
const #60 = Method	#50.#59;	//  scala/reflect/Manifest$.Short:()Lscala/reflect/AnyValManifest;
const #61 = NameAndType	#39:#25;//  Short:Lscala/reflect/AnyValManifest;
const #62 = Field	#10.#61;	//  scala/reflect/ClassManifest$.Short:Lscala/reflect/AnyValManifest;
const #63 = NameAndType	#37:#54;//  Char:()Lscala/reflect/AnyValManifest;
const #64 = Method	#50.#63;	//  scala/reflect/Manifest$.Char:()Lscala/reflect/AnyValManifest;
const #65 = NameAndType	#37:#25;//  Char:Lscala/reflect/AnyValManifest;
const #66 = Field	#10.#65;	//  scala/reflect/ClassManifest$.Char:Lscala/reflect/AnyValManifest;
const #67 = NameAndType	#35:#54;//  Int:()Lscala/reflect/AnyValManifest;
const #68 = Method	#50.#67;	//  scala/reflect/Manifest$.Int:()Lscala/reflect/AnyValManifest;
const #69 = NameAndType	#35:#25;//  Int:Lscala/reflect/AnyValManifest;
const #70 = Field	#10.#69;	//  scala/reflect/ClassManifest$.Int:Lscala/reflect/AnyValManifest;
const #71 = NameAndType	#33:#54;//  Long:()Lscala/reflect/AnyValManifest;
const #72 = Method	#50.#71;	//  scala/reflect/Manifest$.Long:()Lscala/reflect/AnyValManifest;
const #73 = NameAndType	#33:#25;//  Long:Lscala/reflect/AnyValManifest;
const #74 = Field	#10.#73;	//  scala/reflect/ClassManifest$.Long:Lscala/reflect/AnyValManifest;
const #75 = NameAndType	#31:#54;//  Float:()Lscala/reflect/AnyValManifest;
const #76 = Method	#50.#75;	//  scala/reflect/Manifest$.Float:()Lscala/reflect/AnyValManifest;
const #77 = NameAndType	#31:#25;//  Float:Lscala/reflect/AnyValManifest;
const #78 = Field	#10.#77;	//  scala/reflect/ClassManifest$.Float:Lscala/reflect/AnyValManifest;
const #79 = NameAndType	#29:#54;//  Double:()Lscala/reflect/AnyValManifest;
const #80 = Method	#50.#79;	//  scala/reflect/Manifest$.Double:()Lscala/reflect/AnyValManifest;
const #81 = NameAndType	#29:#25;//  Double:Lscala/reflect/AnyValManifest;
const #82 = Field	#10.#81;	//  scala/reflect/ClassManifest$.Double:Lscala/reflect/AnyValManifest;
const #83 = NameAndType	#27:#54;//  Boolean:()Lscala/reflect/AnyValManifest;
const #84 = Method	#50.#83;	//  scala/reflect/Manifest$.Boolean:()Lscala/reflect/AnyValManifest;
const #85 = NameAndType	#27:#25;//  Boolean:Lscala/reflect/AnyValManifest;
const #86 = Field	#10.#85;	//  scala/reflect/ClassManifest$.Boolean:Lscala/reflect/AnyValManifest;
const #87 = NameAndType	#24:#54;//  Unit:()Lscala/reflect/AnyValManifest;
const #88 = Method	#50.#87;	//  scala/reflect/Manifest$.Unit:()Lscala/reflect/AnyValManifest;
const #89 = NameAndType	#24:#25;//  Unit:Lscala/reflect/AnyValManifest;
const #90 = Field	#10.#89;	//  scala/reflect/ClassManifest$.Unit:Lscala/reflect/AnyValManifest;
const #91 = Asciz	()Lscala/reflect/Manifest;;
const #92 = NameAndType	#23:#91;//  Any:()Lscala/reflect/Manifest;
const #93 = Method	#50.#92;	//  scala/reflect/Manifest$.Any:()Lscala/reflect/Manifest;
const #94 = NameAndType	#23:#15;//  Any:Lscala/reflect/Manifest;
const #95 = Field	#10.#94;	//  scala/reflect/ClassManifest$.Any:Lscala/reflect/Manifest;
const #96 = NameAndType	#22:#91;//  Object:()Lscala/reflect/Manifest;
const #97 = Method	#50.#96;	//  scala/reflect/Manifest$.Object:()Lscala/reflect/Manifest;
const #98 = NameAndType	#22:#15;//  Object:Lscala/reflect/Manifest;
const #99 = Field	#10.#98;	//  scala/reflect/ClassManifest$.Object:Lscala/reflect/Manifest;
const #100 = NameAndType	#20:#91;//  AnyVal:()Lscala/reflect/Manifest;
const #101 = Method	#50.#100;	//  scala/reflect/Manifest$.AnyVal:()Lscala/reflect/Manifest;
const #102 = NameAndType	#20:#15;//  AnyVal:Lscala/reflect/Manifest;
const #103 = Field	#10.#102;	//  scala/reflect/ClassManifest$.AnyVal:Lscala/reflect/Manifest;
const #104 = NameAndType	#18:#91;//  Nothing:()Lscala/reflect/Manifest;
const #105 = Method	#50.#104;	//  scala/reflect/Manifest$.Nothing:()Lscala/reflect/Manifest;
const #106 = NameAndType	#18:#15;//  Nothing:Lscala/reflect/Manifest;
const #107 = Field	#10.#106;	//  scala/reflect/ClassManifest$.Nothing:Lscala/reflect/Manifest;
const #108 = NameAndType	#14:#91;//  Null:()Lscala/reflect/Manifest;
const #109 = Method	#50.#108;	//  scala/reflect/Manifest$.Null:()Lscala/reflect/Manifest;
const #110 = NameAndType	#14:#15;//  Null:Lscala/reflect/Manifest;
const #111 = Field	#10.#110;	//  scala/reflect/ClassManifest$.Null:Lscala/reflect/Manifest;
const #112 = Asciz	intersectionType;
const #113 = Asciz	(Lscala/collection/Seq;)Lscala/reflect/ClassManifest;;
const #114 = Asciz	scala/reflect/ClassManifest$$anon$2;
const #115 = class	#114;	//  scala/reflect/ClassManifest$$anon$2
const #116 = Asciz	(Lscala/collection/Seq;)V;
const #117 = NameAndType	#11:#116;//  "<init>":(Lscala/collection/Seq;)V
const #118 = Method	#115.#117;	//  scala/reflect/ClassManifest$$anon$2."<init>":(Lscala/collection/Seq;)V
const #119 = Asciz	this;
const #120 = Asciz	parents$1;
const #121 = Asciz	Lscala/collection/Seq;;
const #122 = Asciz	LocalVariableTable;
const #123 = Asciz	<T:Ljava/lang/Object;>(Lscala/collection/Seq<Lscala/reflect/ClassManifest<*>;>;)Lscala/reflect/ClassManifest<TT;>;;
const #124 = Asciz	abstractType;
const #125 = Asciz	(Lscala/reflect/OptManifest;Ljava/lang/String;Lscala/reflect/ClassManifest;Lscala/collection/Seq;)Lscala/reflect/ClassManifest;;
const #126 = Asciz	scala/reflect/ClassManifest$$anon$1;
const #127 = class	#126;	//  scala/reflect/ClassManifest$$anon$1
const #128 = Asciz	(Lscala/reflect/OptManifest;Ljava/lang/String;Lscala/reflect/ClassManifest;Lscala/collection/Seq;)V;
const #129 = NameAndType	#11:#128;//  "<init>":(Lscala/reflect/OptManifest;Ljava/lang/String;Lscala/reflect/ClassManifest;Lscala/collection/Seq;)V
const #130 = Method	#127.#129;	//  scala/reflect/ClassManifest$$anon$1."<init>":(Lscala/reflect/OptManifest;Ljava/lang/String;Lscala/reflect/ClassManifest;Lscala/collection/Seq;)V
const #131 = Asciz	prefix$1;
const #132 = Asciz	Lscala/reflect/OptManifest;;
const #133 = Asciz	name$1;
const #134 = Asciz	Ljava/lang/String;;
const #135 = Asciz	upperBound$1;
const #136 = Asciz	Lscala/reflect/ClassManifest;;
const #137 = Asciz	args$1;
const #138 = Asciz	<T:Ljava/lang/Object;>(Lscala/reflect/OptManifest<*>;Ljava/lang/String;Lscala/reflect/ClassManifest<*>;Lscala/collection/Seq<Lscala/reflect/OptManifest<*>;>;)Lscala/reflect/ClassManifest<TT;>;;
const #139 = Asciz	arrayType;
const #140 = Asciz	(Lscala/reflect/OptManifest;)Lscala/reflect/ClassManifest;;
const #141 = Asciz	scala/reflect/NoManifest$;
const #142 = class	#141;	//  scala/reflect/NoManifest$
const #143 = Asciz	Lscala/reflect/NoManifest$;;
const #144 = NameAndType	#4:#143;//  MODULE$:Lscala/reflect/NoManifest$;
const #145 = Field	#142.#144;	//  scala/reflect/NoManifest$.MODULE$:Lscala/reflect/NoManifest$;
const #146 = Asciz	equals;
const #147 = Asciz	(Ljava/lang/Object;)Z;
const #148 = NameAndType	#146:#147;//  equals:(Ljava/lang/Object;)Z
const #149 = Method	#45.#148;	//  java/lang/Object.equals:(Ljava/lang/Object;)Z
const #150 = Asciz	scala/MatchError;
const #151 = class	#150;	//  scala/MatchError
const #152 = Asciz	toString;
const #153 = Asciz	()Ljava/lang/String;;
const #154 = NameAndType	#152:#153;//  toString:()Ljava/lang/String;
const #155 = Method	#45.#154;	//  java/lang/Object.toString:()Ljava/lang/String;
const #156 = Asciz	(Ljava/lang/String;)V;
const #157 = NameAndType	#11:#156;//  "<init>":(Ljava/lang/String;)V
const #158 = Method	#151.#157;	//  scala/MatchError."<init>":(Ljava/lang/String;)V
const #159 = Asciz	scala/reflect/ClassManifest;
const #160 = class	#159;	//  scala/reflect/ClassManifest
const #161 = Asciz	arrayManifest;
const #162 = Asciz	()Lscala/reflect/ClassManifest;;
const #163 = NameAndType	#161:#162;//  arrayManifest:()Lscala/reflect/ClassManifest;
const #164 = InterfaceMethod	#160.#163;	//  scala/reflect/ClassManifest.arrayManifest:()Lscala/reflect/ClassManifest;
const #165 = Asciz	arg;
const #166 = Asciz	temp25;
const #167 = Asciz	<T:Ljava/lang/Object;>(Lscala/reflect/OptManifest<*>;)Lscala/reflect/ClassManifest<[TT;>;;
const #168 = Asciz	classType;
const #169 = Asciz	(Lscala/reflect/OptManifest;Ljava/lang/Class;Lscala/collection/Seq;)Lscala/reflect/ClassManifest;;
const #170 = Asciz	scala/reflect/ClassManifest$ClassTypeManifest;
const #171 = class	#170;	//  scala/reflect/ClassManifest$ClassTypeManifest
const #172 = Asciz	scala/Some;
const #173 = class	#172;	//  scala/Some
const #174 = Asciz	(Ljava/lang/Object;)V;
const #175 = NameAndType	#11:#174;//  "<init>":(Ljava/lang/Object;)V
const #176 = Method	#173.#175;	//  scala/Some."<init>":(Ljava/lang/Object;)V
const #177 = Asciz	scala/collection/TraversableLike;
const #178 = class	#177;	//  scala/collection/TraversableLike
const #179 = Asciz	toList;
const #180 = Asciz	()Lscala/collection/immutable/List;;
const #181 = NameAndType	#179:#180;//  toList:()Lscala/collection/immutable/List;
const #182 = InterfaceMethod	#178.#181;	//  scala/collection/TraversableLike.toList:()Lscala/collection/immutable/List;
const #183 = Asciz	(Lscala/Option;Ljava/lang/Class;Lscala/collection/immutable/List;)V;
const #184 = NameAndType	#11:#183;//  "<init>":(Lscala/Option;Ljava/lang/Class;Lscala/collection/immutable/List;)V
const #185 = Method	#171.#184;	//  scala/reflect/ClassManifest$ClassTypeManifest."<init>":(Lscala/Option;Ljava/lang/Class;Lscala/collection/immutable/List;)V
const #186 = Asciz	prefix;
const #187 = Asciz	clazz;
const #188 = Asciz	Ljava/lang/Class;;
const #189 = Asciz	args;
const #190 = Asciz	<T:Ljava/lang/Object;>(Lscala/reflect/OptManifest<*>;Ljava/lang/Class<*>;Lscala/collection/Seq<Lscala/reflect/OptManifest<*>;>;)Lscala/reflect/ClassManifest<TT;>;;
const #191 = Asciz	(Ljava/lang/Class;Lscala/reflect/OptManifest;Lscala/collection/Seq;)Lscala/reflect/ClassManifest;;
const #192 = Asciz	scala/None$;
const #193 = class	#192;	//  scala/None$
const #194 = Asciz	Lscala/None$;;
const #195 = NameAndType	#4:#194;//  MODULE$:Lscala/None$;
const #196 = Field	#193.#195;	//  scala/None$.MODULE$:Lscala/None$;
const #197 = Asciz	scala/collection/immutable/List;
const #198 = class	#197;	//  scala/collection/immutable/List
const #199 = Asciz	$colon$colon;
const #200 = Asciz	(Ljava/lang/Object;)Lscala/collection/immutable/List;;
const #201 = NameAndType	#199:#200;//  $colon$colon:(Ljava/lang/Object;)Lscala/collection/immutable/List;
const #202 = Method	#198.#201;	//  scala/collection/immutable/List.$colon$colon:(Ljava/lang/Object;)Lscala/collection/immutable/List;
const #203 = Asciz	arg1;
const #204 = Asciz	<T:Ljava/lang/Object;>(Ljava/lang/Class<*>;Lscala/reflect/OptManifest<*>;Lscala/collection/Seq<Lscala/reflect/OptManifest<*>;>;)Lscala/reflect/ClassManifest<TT;>;;
const #205 = Asciz	(Ljava/lang/Class;)Lscala/reflect/ClassManifest;;
const #206 = Asciz	scala/collection/immutable/Nil$;
const #207 = class	#206;	//  scala/collection/immutable/Nil$
const #208 = Asciz	Lscala/collection/immutable/Nil$;;
const #209 = NameAndType	#4:#208;//  MODULE$:Lscala/collection/immutable/Nil$;
const #210 = Field	#207.#209;	//  scala/collection/immutable/Nil$.MODULE$:Lscala/collection/immutable/Nil$;
const #211 = Asciz	<T:Ljava/lang/Object;>(Ljava/lang/Class<*>;)Lscala/reflect/ClassManifest<TT;>;;
const #212 = Asciz	singleType;
const #213 = Asciz	(Ljava/lang/Object;)Lscala/reflect/Manifest;;
const #214 = NameAndType	#212:#213;//  singleType:(Ljava/lang/Object;)Lscala/reflect/Manifest;
const #215 = Method	#50.#214;	//  scala/reflect/Manifest$.singleType:(Ljava/lang/Object;)Lscala/reflect/Manifest;
const #216 = Asciz	value;
const #217 = Asciz	Ljava/lang/Object;;
const #218 = Asciz	<T:Ljava/lang/Object;>(Ljava/lang/Object;)Lscala/reflect/Manifest<TT;>;;
const #219 = Asciz	fromClass;
const #220 = Asciz	java/lang/Byte;
const #221 = class	#220;	//  java/lang/Byte
const #222 = Asciz	TYPE;
const #223 = NameAndType	#222:#188;//  TYPE:Ljava/lang/Class;
const #224 = Field	#221.#223;	//  java/lang/Byte.TYPE:Ljava/lang/Class;
const #225 = Asciz	java/lang/Class;
const #226 = class	#225;	//  java/lang/Class
const #227 = Method	#226.#154;	//  java/lang/Class.toString:()Ljava/lang/String;
const #228 = Asciz	java/lang/Short;
const #229 = class	#228;	//  java/lang/Short
const #230 = Field	#229.#223;	//  java/lang/Short.TYPE:Ljava/lang/Class;
const #231 = Asciz	java/lang/Character;
const #232 = class	#231;	//  java/lang/Character
const #233 = Field	#232.#223;	//  java/lang/Character.TYPE:Ljava/lang/Class;
const #234 = Asciz	java/lang/Integer;
const #235 = class	#234;	//  java/lang/Integer
const #236 = Field	#235.#223;	//  java/lang/Integer.TYPE:Ljava/lang/Class;
const #237 = Asciz	java/lang/Long;
const #238 = class	#237;	//  java/lang/Long
const #239 = Field	#238.#223;	//  java/lang/Long.TYPE:Ljava/lang/Class;
const #240 = Asciz	java/lang/Float;
const #241 = class	#240;	//  java/lang/Float
const #242 = Field	#241.#223;	//  java/lang/Float.TYPE:Ljava/lang/Class;
const #243 = Asciz	java/lang/Double;
const #244 = class	#243;	//  java/lang/Double
const #245 = Field	#244.#223;	//  java/lang/Double.TYPE:Ljava/lang/Class;
const #246 = Asciz	java/lang/Boolean;
const #247 = class	#246;	//  java/lang/Boolean
const #248 = Field	#247.#223;	//  java/lang/Boolean.TYPE:Ljava/lang/Class;
const #249 = Asciz	java/lang/Void;
const #250 = class	#249;	//  java/lang/Void
const #251 = Field	#250.#223;	//  java/lang/Void.TYPE:Ljava/lang/Class;
const #252 = Asciz	<T:Ljava/lang/Object;>(Ljava/lang/Class<TT;>;)Lscala/reflect/ClassManifest<TT;>;;
const #253 = Asciz	()Lscala/reflect/Manifest<Lscala/runtime/Null$;>;;
const #254 = Asciz	()Lscala/reflect/Manifest<Lscala/runtime/Nothing$;>;;
const #255 = Asciz	()Lscala/reflect/Manifest<Ljava/lang/Object;>;;
const #256 = Asciz	()Lscala/reflect/AnyValManifest<Ljava/lang/Object;>;;
const #257 = Asciz	()Lscala/reflect/AnyValManifest<Ljava/lang/Boolean;>;;
const #258 = Asciz	()Lscala/reflect/AnyValManifest<Ljava/lang/Double;>;;
const #259 = Asciz	()Lscala/reflect/AnyValManifest<Ljava/lang/Float;>;;
const #260 = Asciz	()Lscala/reflect/AnyValManifest<Ljava/lang/Long;>;;
const #261 = Asciz	()Lscala/reflect/AnyValManifest<Ljava/lang/Integer;>;;
const #262 = Asciz	()Lscala/reflect/AnyValManifest<Ljava/lang/Character;>;;
const #263 = Asciz	()Lscala/reflect/AnyValManifest<Ljava/lang/Short;>;;
const #264 = Asciz	()Lscala/reflect/AnyValManifest<Ljava/lang/Byte;>;;
const #265 = Asciz	InnerClasses;
const #266 = Asciz	$anon$1;
const #267 = Asciz	$anon$2;
const #268 = Asciz	ClassTypeManifest;
const #269 = Asciz	scala/reflect/ClassManifest$$anonfun$subargs$1$1;
const #270 = class	#269;	//  scala/reflect/ClassManifest$$anonfun$subargs$1$1
const #271 = Asciz	$anonfun$subargs$1$1;
const #272 = Asciz	scala/reflect/ClassManifest$$anonfun$subtype$1$1;
const #273 = class	#272;	//  scala/reflect/ClassManifest$$anonfun$subtype$1$1
const #274 = Asciz	$anonfun$subtype$1$1;
const #275 = Asciz	scala/ScalaObject;
const #276 = class	#275;	//  scala/ScalaObject

{
public static final scala.reflect.ClassManifest$ MODULE$;

public static {};
  Code:
   Stack=1, Locals=0, Args_size=0
   0:	new	#10; //class scala/reflect/ClassManifest$
   3:	invokespecial	#13; //Method "<init>":()V
   6:	return

public scala.reflect.ClassManifest intersectionType(scala.collection.Seq);
  Code:
   Stack=3, Locals=2, Args_size=2
   0:	new	#115; //class scala/reflect/ClassManifest$$anon$2
   3:	dup
   4:	aload_1
   5:	invokespecial	#118; //Method scala/reflect/ClassManifest$$anon$2."<init>":(Lscala/collection/Seq;)V
   8:	areturn
  LineNumberTable: 
   line 219: 0

  LocalVariableTable: 
   Start  Length  Slot  Name   Signature
   0      9      0    this       Lscala/reflect/ClassManifest$;
   0      9      1    parents$1       Lscala/collection/Seq;

  Signature: length = 0x2
   00 7B 

public scala.reflect.ClassManifest abstractType(scala.reflect.OptManifest, java.lang.String, scala.reflect.ClassManifest, scala.collection.Seq);
  Code:
   Stack=6, Locals=5, Args_size=5
   0:	new	#127; //class scala/reflect/ClassManifest$$anon$1
   3:	dup
   4:	aload_1
   5:	aload_2
   6:	aload_3
   7:	aload	4
   9:	invokespecial	#130; //Method scala/reflect/ClassManifest$$anon$1."<init>":(Lscala/reflect/OptManifest;Ljava/lang/String;Lscala/reflect/ClassManifest;Lscala/collection/Seq;)V
   12:	areturn
  LineNumberTable: 
   line 211: 0

  LocalVariableTable: 
   Start  Length  Slot  Name   Signature
   0      13      0    this       Lscala/reflect/ClassManifest$;
   0      13      1    prefix$1       Lscala/reflect/OptManifest;
   0      13      2    name$1       Ljava/lang/String;
   0      13      3    upperBound$1       Lscala/reflect/ClassManifest;
   0      13      4    args$1       Lscala/collection/Seq;

  Signature: length = 0x2
   00 FFFFFF8A 

public scala.reflect.ClassManifest arrayType(scala.reflect.OptManifest);
  Code:
   Stack=3, Locals=3, Args_size=2
   0:	getstatic	#145; //Field scala/reflect/NoManifest$.MODULE$:Lscala/reflect/NoManifest$;
   3:	dup
   4:	ifnonnull	15
   7:	pop
   8:	aload_1
   9:	ifnull	22
   12:	goto	45
   15:	aload_1
   16:	invokevirtual	#149; //Method java/lang/Object.equals:(Ljava/lang/Object;)Z
   19:	ifeq	45
   22:	iconst_1
   23:	ifeq	33
   26:	aload_0
   27:	getfield	#99; //Field Object:Lscala/reflect/Manifest;
   30:	goto	67
   33:	new	#151; //class scala/MatchError
   36:	dup
   37:	aload_1
   38:	invokevirtual	#155; //Method java/lang/Object.toString:()Ljava/lang/String;
   41:	invokespecial	#158; //Method scala/MatchError."<init>":(Ljava/lang/String;)V
   44:	athrow
   45:	aload_1
   46:	instanceof	#160; //class scala/reflect/ClassManifest
   49:	ifeq	80
   52:	aload_1
   53:	checkcast	#160; //class scala/reflect/ClassManifest
   56:	astore_2
   57:	iconst_1
   58:	ifeq	68
   61:	aload_2
   62:	invokeinterface	#164,  1; //InterfaceMethod scala/reflect/ClassManifest.arrayManifest:()Lscala/reflect/ClassManifest;
   67:	areturn
   68:	new	#151; //class scala/MatchError
   71:	dup
   72:	aload_1
   73:	invokevirtual	#155; //Method java/lang/Object.toString:()Ljava/lang/String;
   76:	invokespecial	#158; //Method scala/MatchError."<init>":(Ljava/lang/String;)V
   79:	athrow
   80:	new	#151; //class scala/MatchError
   83:	dup
   84:	aload_1
   85:	invokevirtual	#155; //Method java/lang/Object.toString:()Ljava/lang/String;
   88:	invokespecial	#158; //Method scala/MatchError."<init>":(Ljava/lang/String;)V
   91:	athrow
  LineNumberTable: 
   line 202: 0
   line 21: 22
   line 203: 26
   line 202: 33
   line 21: 57
   line 204: 61
   line 202: 67

  LocalVariableTable: 
   Start  Length  Slot  Name   Signature
   0      92      0    this       Lscala/reflect/ClassManifest$;
   0      92      1    arg       Lscala/reflect/OptManifest;
   57      10      2    temp25       Lscala/reflect/ClassManifest;
   68      12      2    temp25       Lscala/reflect/ClassManifest;

  Signature: length = 0x2
   00 FFFFFFA7 

public scala.reflect.ClassManifest classType(scala.reflect.OptManifest, java.lang.Class, scala.collection.Seq);
  Code:
   Stack=5, Locals=4, Args_size=4
   0:	new	#171; //class scala/reflect/ClassManifest$ClassTypeManifest
   3:	dup
   4:	new	#173; //class scala/Some
   7:	dup
   8:	aload_1
   9:	invokespecial	#176; //Method scala/Some."<init>":(Ljava/lang/Object;)V
   12:	aload_2
   13:	aload_3
   14:	invokeinterface	#182,  1; //InterfaceMethod scala/collection/TraversableLike.toList:()Lscala/collection/immutable/List;
   19:	invokespecial	#185; //Method scala/reflect/ClassManifest$ClassTypeManifest."<init>":(Lscala/Option;Ljava/lang/Class;Lscala/collection/immutable/List;)V
   22:	areturn
  LineNumberTable: 
   line 188: 0

  LocalVariableTable: 
   Start  Length  Slot  Name   Signature
   0      23      0    this       Lscala/reflect/ClassManifest$;
   0      23      1    prefix       Lscala/reflect/OptManifest;
   0      23      2    clazz       Ljava/lang/Class;
   0      23      3    args       Lscala/collection/Seq;

  Signature: length = 0x2
   00 FFFFFFBE 

public scala.reflect.ClassManifest classType(java.lang.Class, scala.reflect.OptManifest, scala.collection.Seq);
  Code:
   Stack=6, Locals=4, Args_size=4
   0:	new	#171; //class scala/reflect/ClassManifest$ClassTypeManifest
   3:	dup
   4:	getstatic	#196; //Field scala/None$.MODULE$:Lscala/None$;
   7:	aload_1
   8:	aload_3
   9:	invokeinterface	#182,  1; //InterfaceMethod scala/collection/TraversableLike.toList:()Lscala/collection/immutable/List;
   14:	aload_2
   15:	invokevirtual	#202; //Method scala/collection/immutable/List.$colon$colon:(Ljava/lang/Object;)Lscala/collection/immutable/List;
   18:	invokespecial	#185; //Method scala/reflect/ClassManifest$ClassTypeManifest."<init>":(Lscala/Option;Ljava/lang/Class;Lscala/collection/immutable/List;)V
   21:	areturn
  LineNumberTable: 
   line 182: 0

  LocalVariableTable: 
   Start  Length  Slot  Name   Signature
   0      22      0    this       Lscala/reflect/ClassManifest$;
   0      22      1    clazz       Ljava/lang/Class;
   0      22      2    arg1       Lscala/reflect/OptManifest;
   0      22      3    args       Lscala/collection/Seq;

  Signature: length = 0x2
   00 FFFFFFCC 

public scala.reflect.ClassManifest classType(java.lang.Class);
  Code:
   Stack=5, Locals=2, Args_size=2
   0:	new	#171; //class scala/reflect/ClassManifest$ClassTypeManifest
   3:	dup
   4:	getstatic	#196; //Field scala/None$.MODULE$:Lscala/None$;
   7:	aload_1
   8:	getstatic	#210; //Field scala/collection/immutable/Nil$.MODULE$:Lscala/collection/immutable/Nil$;
   11:	invokespecial	#185; //Method scala/reflect/ClassManifest$ClassTypeManifest."<init>":(Lscala/Option;Ljava/lang/Class;Lscala/collection/immutable/List;)V
   14:	areturn
  LineNumberTable: 
   line 177: 0

  LocalVariableTable: 
   Start  Length  Slot  Name   Signature
   0      15      0    this       Lscala/reflect/ClassManifest$;
   0      15      1    clazz       Ljava/lang/Class;

  Signature: length = 0x2
   00 FFFFFFD3 

public scala.reflect.Manifest singleType(java.lang.Object);
  Code:
   Stack=2, Locals=2, Args_size=2
   0:	getstatic	#53; //Field scala/reflect/Manifest$.MODULE$:Lscala/reflect/Manifest$;
   3:	aload_1
   4:	invokevirtual	#215; //Method scala/reflect/Manifest$.singleType:(Ljava/lang/Object;)Lscala/reflect/Manifest;
   7:	areturn
  LineNumberTable: 
   line 167: 0

  LocalVariableTable: 
   Start  Length  Slot  Name   Signature
   0      8      0    this       Lscala/reflect/ClassManifest$;
   0      8      1    value       Ljava/lang/Object;

  Signature: length = 0x2
   00 FFFFFFDA 

public scala.reflect.ClassManifest fromClass(java.lang.Class);
  Code:
   Stack=5, Locals=2, Args_size=2
   0:	getstatic	#224; //Field java/lang/Byte.TYPE:Ljava/lang/Class;
   3:	dup
   4:	ifnonnull	15
   7:	pop
   8:	aload_1
   9:	ifnull	22
   12:	goto	45
   15:	aload_1
   16:	invokevirtual	#149; //Method java/lang/Object.equals:(Ljava/lang/Object;)Z
   19:	ifeq	45
   22:	iconst_1
   23:	ifeq	33
   26:	aload_0
   27:	getfield	#58; //Field Byte:Lscala/reflect/AnyValManifest;
   30:	goto	423
   33:	new	#151; //class scala/MatchError
   36:	dup
   37:	aload_1
   38:	invokevirtual	#227; //Method java/lang/Class.toString:()Ljava/lang/String;
   41:	invokespecial	#158; //Method scala/MatchError."<init>":(Ljava/lang/String;)V
   44:	athrow
   45:	getstatic	#230; //Field java/lang/Short.TYPE:Ljava/lang/Class;
   48:	dup
   49:	ifnonnull	60
   52:	pop
   53:	aload_1
   54:	ifnull	67
   57:	goto	90
   60:	aload_1
   61:	invokevirtual	#149; //Method java/lang/Object.equals:(Ljava/lang/Object;)Z
   64:	ifeq	90
   67:	iconst_1
   68:	ifeq	78
   71:	aload_0
   72:	getfield	#62; //Field Short:Lscala/reflect/AnyValManifest;
   75:	goto	423
   78:	new	#151; //class scala/MatchError
   81:	dup
   82:	aload_1
   83:	invokevirtual	#227; //Method java/lang/Class.toString:()Ljava/lang/String;
   86:	invokespecial	#158; //Method scala/MatchError."<init>":(Ljava/lang/String;)V
   89:	athrow
   90:	getstatic	#233; //Field java/lang/Character.TYPE:Ljava/lang/Class;
   93:	dup
   94:	ifnonnull	105
   97:	pop
   98:	aload_1
   99:	ifnull	112
   102:	goto	135
   105:	aload_1
   106:	invokevirtual	#149; //Method java/lang/Object.equals:(Ljava/lang/Object;)Z
   109:	ifeq	135
   112:	iconst_1
   113:	ifeq	123
   116:	aload_0
   117:	getfield	#66; //Field Char:Lscala/reflect/AnyValManifest;
   120:	goto	423
   123:	new	#151; //class scala/MatchError
   126:	dup
   127:	aload_1
   128:	invokevirtual	#227; //Method java/lang/Class.toString:()Ljava/lang/String;
   131:	invokespecial	#158; //Method scala/MatchError."<init>":(Ljava/lang/String;)V
   134:	athrow
   135:	getstatic	#236; //Field java/lang/Integer.TYPE:Ljava/lang/Class;
   138:	dup
   139:	ifnonnull	150
   142:	pop
   143:	aload_1
   144:	ifnull	157
   147:	goto	180
   150:	aload_1
   151:	invokevirtual	#149; //Method java/lang/Object.equals:(Ljava/lang/Object;)Z
   154:	ifeq	180
   157:	iconst_1
   158:	ifeq	168
   161:	aload_0
   162:	getfield	#70; //Field Int:Lscala/reflect/AnyValManifest;
   165:	goto	423
   168:	new	#151; //class scala/MatchError
   171:	dup
   172:	aload_1
   173:	invokevirtual	#227; //Method java/lang/Class.toString:()Ljava/lang/String;
   176:	invokespecial	#158; //Method scala/MatchError."<init>":(Ljava/lang/String;)V
   179:	athrow
   180:	getstatic	#239; //Field java/lang/Long.TYPE:Ljava/lang/Class;
   183:	dup
   184:	ifnonnull	195
   187:	pop
   188:	aload_1
   189:	ifnull	202
   192:	goto	225
   195:	aload_1
   196:	invokevirtual	#149; //Method java/lang/Object.equals:(Ljava/lang/Object;)Z
   199:	ifeq	225
   202:	iconst_1
   203:	ifeq	213
   206:	aload_0
   207:	getfield	#74; //Field Long:Lscala/reflect/AnyValManifest;
   210:	goto	423
   213:	new	#151; //class scala/MatchError
   216:	dup
   217:	aload_1
   218:	invokevirtual	#227; //Method java/lang/Class.toString:()Ljava/lang/String;
   221:	invokespecial	#158; //Method scala/MatchError."<init>":(Ljava/lang/String;)V
   224:	athrow
   225:	getstatic	#242; //Field java/lang/Float.TYPE:Ljava/lang/Class;
   228:	dup
   229:	ifnonnull	240
   232:	pop
   233:	aload_1
   234:	ifnull	247
   237:	goto	270
   240:	aload_1
   241:	invokevirtual	#149; //Method java/lang/Object.equals:(Ljava/lang/Object;)Z
   244:	ifeq	270
   247:	iconst_1
   248:	ifeq	258
   251:	aload_0
   252:	getfield	#78; //Field Float:Lscala/reflect/AnyValManifest;
   255:	goto	423
   258:	new	#151; //class scala/MatchError
   261:	dup
   262:	aload_1
   263:	invokevirtual	#227; //Method java/lang/Class.toString:()Ljava/lang/String;
   266:	invokespecial	#158; //Method scala/MatchError."<init>":(Ljava/lang/String;)V
   269:	athrow
   270:	getstatic	#245; //Field java/lang/Double.TYPE:Ljava/lang/Class;
   273:	dup
   274:	ifnonnull	285
   277:	pop
   278:	aload_1
   279:	ifnull	292
   282:	goto	315
   285:	aload_1
   286:	invokevirtual	#149; //Method java/lang/Object.equals:(Ljava/lang/Object;)Z
   289:	ifeq	315
   292:	iconst_1
   293:	ifeq	303
   296:	aload_0
   297:	getfield	#82; //Field Double:Lscala/reflect/AnyValManifest;
   300:	goto	423
   303:	new	#151; //class scala/MatchError
   306:	dup
   307:	aload_1
   308:	invokevirtual	#227; //Method java/lang/Class.toString:()Ljava/lang/String;
   311:	invokespecial	#158; //Method scala/MatchError."<init>":(Ljava/lang/String;)V
   314:	athrow
   315:	getstatic	#248; //Field java/lang/Boolean.TYPE:Ljava/lang/Class;
   318:	dup
   319:	ifnonnull	330
   322:	pop
   323:	aload_1
   324:	ifnull	337
   327:	goto	360
   330:	aload_1
   331:	invokevirtual	#149; //Method java/lang/Object.equals:(Ljava/lang/Object;)Z
   334:	ifeq	360
   337:	iconst_1
   338:	ifeq	348
   341:	aload_0
   342:	getfield	#86; //Field Boolean:Lscala/reflect/AnyValManifest;
   345:	goto	423
   348:	new	#151; //class scala/MatchError
   351:	dup
   352:	aload_1
   353:	invokevirtual	#227; //Method java/lang/Class.toString:()Ljava/lang/String;
   356:	invokespecial	#158; //Method scala/MatchError."<init>":(Ljava/lang/String;)V
   359:	athrow
   360:	getstatic	#251; //Field java/lang/Void.TYPE:Ljava/lang/Class;
   363:	dup
   364:	ifnonnull	375
   367:	pop
   368:	aload_1
   369:	ifnull	382
   372:	goto	405
   375:	aload_1
   376:	invokevirtual	#149; //Method java/lang/Object.equals:(Ljava/lang/Object;)Z
   379:	ifeq	405
   382:	iconst_1
   383:	ifeq	393
   386:	aload_0
   387:	getfield	#90; //Field Unit:Lscala/reflect/AnyValManifest;
   390:	goto	423
   393:	new	#151; //class scala/MatchError
   396:	dup
   397:	aload_1
   398:	invokevirtual	#227; //Method java/lang/Class.toString:()Ljava/lang/String;
   401:	invokespecial	#158; //Method scala/MatchError."<init>":(Ljava/lang/String;)V
   404:	athrow
   405:	iconst_1
   406:	ifeq	424
   409:	new	#171; //class scala/reflect/ClassManifest$ClassTypeManifest
   412:	dup
   413:	getstatic	#196; //Field scala/None$.MODULE$:Lscala/None$;
   416:	aload_1
   417:	getstatic	#210; //Field scala/collection/immutable/Nil$.MODULE$:Lscala/collection/immutable/Nil$;
   420:	invokespecial	#185; //Method scala/reflect/ClassManifest$ClassTypeManifest."<init>":(Lscala/Option;Ljava/lang/Class;Lscala/collection/immutable/List;)V
   423:	areturn
   424:	new	#151; //class scala/MatchError
   427:	dup
   428:	aload_1
   429:	invokevirtual	#227; //Method java/lang/Class.toString:()Ljava/lang/String;
   432:	invokespecial	#158; //Method scala/MatchError."<init>":(Ljava/lang/String;)V
   435:	athrow
  LineNumberTable: 
   line 154: 0
   line 21: 22
   line 155: 26
   line 154: 33
   line 21: 67
   line 156: 71
   line 154: 78
   line 21: 112
   line 157: 116
   line 154: 123
   line 21: 157
   line 158: 161
   line 154: 168
   line 21: 202
   line 159: 206
   line 154: 213
   line 21: 247
   line 160: 251
   line 154: 258
   line 21: 292
   line 161: 296
   line 154: 303
   line 21: 337
   line 162: 341
   line 154: 348
   line 21: 382
   line 163: 386
   line 154: 393
   line 21: 405
   line 164: 409
   line 154: 423

  LocalVariableTable: 
   Start  Length  Slot  Name   Signature
   0      436      0    this       Lscala/reflect/ClassManifest$;
   0      436      1    clazz       Ljava/lang/Class;

  Signature: length = 0x2
   00 FFFFFFFC 

public scala.reflect.Manifest Null();
  Code:
   Stack=1, Locals=1, Args_size=1
   0:	aload_0
   1:	getfield	#111; //Field Null:Lscala/reflect/Manifest;
   4:	areturn
  LineNumberTable: 
   line 152: 0

  Signature: length = 0x2
   00 FFFFFFFD 

public scala.reflect.Manifest Nothing();
  Code:
   Stack=1, Locals=1, Args_size=1
   0:	aload_0
   1:	getfield	#107; //Field Nothing:Lscala/reflect/Manifest;
   4:	areturn
  LineNumberTable: 
   line 151: 0

  Signature: length = 0x2
   00 FFFFFFFE 

public scala.reflect.Manifest AnyVal();
  Code:
   Stack=1, Locals=1, Args_size=1
   0:	aload_0
   1:	getfield	#103; //Field AnyVal:Lscala/reflect/Manifest;
   4:	areturn
  LineNumberTable: 
   line 150: 0

  Signature: length = 0x2
   00 FFFFFFFF 

public scala.reflect.Manifest Object();
  Code:
   Stack=1, Locals=1, Args_size=1
   0:	aload_0
   1:	getfield	#99; //Field Object:Lscala/reflect/Manifest;
   4:	areturn
  LineNumberTable: 
   line 149: 0

  Signature: length = 0x2
   00 FFFFFFFF 

public scala.reflect.Manifest Any();
  Code:
   Stack=1, Locals=1, Args_size=1
   0:	aload_0
   1:	getfield	#95; //Field Any:Lscala/reflect/Manifest;
   4:	areturn
  LineNumberTable: 
   line 148: 0

  Signature: length = 0x2
   00 FFFFFFFF 

public scala.reflect.AnyValManifest Unit();
  Code:
   Stack=1, Locals=1, Args_size=1
   0:	aload_0
   1:	getfield	#90; //Field Unit:Lscala/reflect/AnyValManifest;
   4:	areturn
  LineNumberTable: 
   line 147: 0

  Signature: length = 0x2
   01 00 

public scala.reflect.AnyValManifest Boolean();
  Code:
   Stack=1, Locals=1, Args_size=1
   0:	aload_0
   1:	getfield	#86; //Field Boolean:Lscala/reflect/AnyValManifest;
   4:	areturn
  LineNumberTable: 
   line 146: 0

  Signature: length = 0x2
   01 01 

public scala.reflect.AnyValManifest Double();
  Code:
   Stack=1, Locals=1, Args_size=1
   0:	aload_0
   1:	getfield	#82; //Field Double:Lscala/reflect/AnyValManifest;
   4:	areturn
  LineNumberTable: 
   line 145: 0

  Signature: length = 0x2
   01 02 

public scala.reflect.AnyValManifest Float();
  Code:
   Stack=1, Locals=1, Args_size=1
   0:	aload_0
   1:	getfield	#78; //Field Float:Lscala/reflect/AnyValManifest;
   4:	areturn
  LineNumberTable: 
   line 144: 0

  Signature: length = 0x2
   01 03 

public scala.reflect.AnyValManifest Long();
  Code:
   Stack=1, Locals=1, Args_size=1
   0:	aload_0
   1:	getfield	#74; //Field Long:Lscala/reflect/AnyValManifest;
   4:	areturn
  LineNumberTable: 
   line 143: 0

  Signature: length = 0x2
   01 04 

public scala.reflect.AnyValManifest Int();
  Code:
   Stack=1, Locals=1, Args_size=1
   0:	aload_0
   1:	getfield	#70; //Field Int:Lscala/reflect/AnyValManifest;
   4:	areturn
  LineNumberTable: 
   line 142: 0

  Signature: length = 0x2
   01 05 

public scala.reflect.AnyValManifest Char();
  Code:
   Stack=1, Locals=1, Args_size=1
   0:	aload_0
   1:	getfield	#66; //Field Char:Lscala/reflect/AnyValManifest;
   4:	areturn
  LineNumberTable: 
   line 141: 0

  Signature: length = 0x2
   01 06 

public scala.reflect.AnyValManifest Short();
  Code:
   Stack=1, Locals=1, Args_size=1
   0:	aload_0
   1:	getfield	#62; //Field Short:Lscala/reflect/AnyValManifest;
   4:	areturn
  LineNumberTable: 
   line 140: 0

  Signature: length = 0x2
   01 07 

public scala.reflect.AnyValManifest Byte();
  Code:
   Stack=1, Locals=1, Args_size=1
   0:	aload_0
   1:	getfield	#58; //Field Byte:Lscala/reflect/AnyValManifest;
   4:	areturn
  LineNumberTable: 
   line 139: 0

  Signature: length = 0x2
   01 08 

}

