Compiled from "ClassManifest.scala"
public class scala.reflect.ClassManifest$ClassTypeManifest extends java.lang.Object implements scala.reflect.ClassManifest,scala.ScalaObject,java.io.Serializable
  SourceFile: "ClassManifest.scala"
  Signature: length = 0x2
   00 FFFFFF9F 
  Scala: length = 0x
   
  InnerClass: 
   public ClassTypeManifest=class scala/reflect/ClassManifest$ClassTypeManifest of class scala/reflect/ClassManifest
  minor version: 0
  major version: 49
  Constant pool:
Asciz	SourceFile;
Asciz	ClassManifest.scala;
Asciz	typeArguments;
Asciz	Lscala/collection/immutable/List;;
Asciz	Lscala/collection/immutable/List<Lscala/reflect/OptManifest<*>;>;;
Asciz	Signature;
Asciz	erasure;
Asciz	Ljava/lang/Class;;
Asciz	Ljava/lang/Class<*>;;
Asciz	prefix;
Asciz	Lscala/Option;;
Asciz	Lscala/Option<Lscala/reflect/OptManifest<*>;>;;
Asciz	<init>;
Asciz	(Lscala/Option;Ljava/lang/Class;Lscala/collection/immutable/List;)V;
Asciz	Code;
Asciz	LineNumberTable;
Asciz	scala/reflect/ClassManifest$ClassTypeManifest;
class	scala/reflect/ClassManifest$ClassTypeManifest
NameAndType	prefix:Lscala/Option;
Field	scala/reflect/ClassManifest$ClassTypeManifest.prefix:Lscala/Option;
NameAndType	erasure:Ljava/lang/Class;
Field	scala/reflect/ClassManifest$ClassTypeManifest.erasure:Ljava/lang/Class;
NameAndType	typeArguments:Lscala/collection/immutable/List;
Field	scala/reflect/ClassManifest$ClassTypeManifest.typeArguments:Lscala/collection/immutable/List;
Asciz	java/lang/Object;
class	java/lang/Object
Asciz	()V;
NameAndType	"<init>":()V
Method	java/lang/Object."<init>":()V
Asciz	scala/reflect/ClassManifest$class;
class	scala/reflect/ClassManifest$class
Asciz	$init$;
Asciz	(Lscala/reflect/ClassManifest;)V;
NameAndType	$init$:(Lscala/reflect/ClassManifest;)V
Method	scala/reflect/ClassManifest$class.$init$:(Lscala/reflect/ClassManifest;)V
Asciz	this;
Asciz	Lscala/reflect/ClassManifest$ClassTypeManifest;;
Asciz	LocalVariableTable;
Asciz	(Lscala/Option<Lscala/reflect/OptManifest<*>;>;Ljava/lang/Class<*>;Lscala/collection/immutable/List<Lscala/reflect/OptManifest<*>;>;)V;
Asciz	toString;
Asciz	()Ljava/lang/String;;
Asciz	scala/collection/mutable/StringBuilder;
class	scala/collection/mutable/StringBuilder
Method	scala/collection/mutable/StringBuilder."<init>":()V
Asciz	scala/Option;
class	scala/Option
Asciz	isEmpty;
Asciz	()Z;
NameAndType	isEmpty:()Z
Method	scala/Option.isEmpty:()Z
Asciz	;
String	
Asciz	get;
Asciz	()Ljava/lang/Object;;
NameAndType	get:()Ljava/lang/Object;
Method	scala/Option.get:()Ljava/lang/Object;
NameAndType	toString:()Ljava/lang/String;
Method	java/lang/Object.toString:()Ljava/lang/String;
Asciz	append;
Asciz	(Ljava/lang/Object;)Lscala/collection/mutable/StringBuilder;;
NameAndType	append:(Ljava/lang/Object;)Lscala/collection/mutable/StringBuilder;
Method	scala/collection/mutable/StringBuilder.append:(Ljava/lang/Object;)Lscala/collection/mutable/StringBuilder;
Asciz	#;
String	#
Method	scala/collection/mutable/StringBuilder.toString:()Ljava/lang/String;
Asciz	()Ljava/lang/Class;;
NameAndType	erasure:()Ljava/lang/Class;
Method	scala/reflect/ClassManifest$ClassTypeManifest.erasure:()Ljava/lang/Class;
Asciz	java/lang/Class;
class	java/lang/Class
Asciz	isArray;
NameAndType	isArray:()Z
Method	java/lang/Class.isArray:()Z
Asciz	Array;
String	Array
Asciz	getName;
NameAndType	getName:()Ljava/lang/String;
Method	java/lang/Class.getName:()Ljava/lang/String;
Asciz	scala/reflect/ClassManifest;
class	scala/reflect/ClassManifest
Asciz	argString;
NameAndType	argString:()Ljava/lang/String;
InterfaceMethod	scala/reflect/ClassManifest.argString:()Ljava/lang/String;
Asciz	()Lscala/collection/immutable/List;;
Asciz	()Lscala/collection/immutable/List<Lscala/reflect/OptManifest<*>;>;;
Asciz	()Ljava/lang/Class<*>;;
Asciz	(Lscala/reflect/ClassManifest;)Ljava/lang/String;;
NameAndType	argString:(Lscala/reflect/ClassManifest;)Ljava/lang/String;
Method	scala/reflect/ClassManifest$class.argString:(Lscala/reflect/ClassManifest;)Ljava/lang/String;
Asciz	newArrayBuilder;
Asciz	()Lscala/collection/mutable/ArrayBuilder;;
Asciz	(Lscala/reflect/ClassManifest;)Lscala/collection/mutable/ArrayBuilder;;
NameAndType	newArrayBuilder:(Lscala/reflect/ClassManifest;)Lscala/collection/mutable/ArrayBuilder;
Method	scala/reflect/ClassManifest$class.newArrayBuilder:(Lscala/reflect/ClassManifest;)Lscala/collection/mutable/ArrayBuilder;
Asciz	newWrappedArray;
Asciz	(I)Lscala/collection/mutable/WrappedArray;;
Asciz	(Lscala/reflect/ClassManifest;I)Lscala/collection/mutable/WrappedArray;;
NameAndType	newWrappedArray:(Lscala/reflect/ClassManifest;I)Lscala/collection/mutable/WrappedArray;
Method	scala/reflect/ClassManifest$class.newWrappedArray:(Lscala/reflect/ClassManifest;I)Lscala/collection/mutable/WrappedArray;
Asciz	len;
Asciz	I;
Asciz	newArray5;
Asciz	(I)[[[[Ljava/lang/Object;;
Asciz	(Lscala/reflect/ClassManifest;I)[[[[Ljava/lang/Object;;
NameAndType	newArray5:(Lscala/reflect/ClassManifest;I)[[[[Ljava/lang/Object;
Method	scala/reflect/ClassManifest$class.newArray5:(Lscala/reflect/ClassManifest;I)[[[[Ljava/lang/Object;
Asciz	newArray4;
Asciz	(I)[[[Ljava/lang/Object;;
Asciz	(Lscala/reflect/ClassManifest;I)[[[Ljava/lang/Object;;
NameAndType	newArray4:(Lscala/reflect/ClassManifest;I)[[[Ljava/lang/Object;
Method	scala/reflect/ClassManifest$class.newArray4:(Lscala/reflect/ClassManifest;I)[[[Ljava/lang/Object;
Asciz	newArray3;
Asciz	(I)[[Ljava/lang/Object;;
Asciz	(Lscala/reflect/ClassManifest;I)[[Ljava/lang/Object;;
NameAndType	newArray3:(Lscala/reflect/ClassManifest;I)[[Ljava/lang/Object;
Method	scala/reflect/ClassManifest$class.newArray3:(Lscala/reflect/ClassManifest;I)[[Ljava/lang/Object;
Asciz	newArray2;
Asciz	(I)[Ljava/lang/Object;;
Asciz	(Lscala/reflect/ClassManifest;I)[Ljava/lang/Object;;
NameAndType	newArray2:(Lscala/reflect/ClassManifest;I)[Ljava/lang/Object;
Method	scala/reflect/ClassManifest$class.newArray2:(Lscala/reflect/ClassManifest;I)[Ljava/lang/Object;
Asciz	newArray;
Asciz	(I)Ljava/lang/Object;;
Asciz	(Lscala/reflect/ClassManifest;I)Ljava/lang/Object;;
NameAndType	newArray:(Lscala/reflect/ClassManifest;I)Ljava/lang/Object;
Method	scala/reflect/ClassManifest$class.newArray:(Lscala/reflect/ClassManifest;I)Ljava/lang/Object;
Asciz	arrayManifest;
Asciz	()Lscala/reflect/ClassManifest;;
Asciz	(Lscala/reflect/ClassManifest;)Lscala/reflect/ClassManifest;;
NameAndType	arrayManifest:(Lscala/reflect/ClassManifest;)Lscala/reflect/ClassManifest;
Method	scala/reflect/ClassManifest$class.arrayManifest:(Lscala/reflect/ClassManifest;)Lscala/reflect/ClassManifest;
Asciz	arrayClass;
Asciz	(Ljava/lang/Class;)Ljava/lang/Class;;
Asciz	(Lscala/reflect/ClassManifest;Ljava/lang/Class;)Ljava/lang/Class;;
NameAndType	arrayClass:(Lscala/reflect/ClassManifest;Ljava/lang/Class;)Ljava/lang/Class;
Method	scala/reflect/ClassManifest$class.arrayClass:(Lscala/reflect/ClassManifest;Ljava/lang/Class;)Ljava/lang/Class;
Asciz	tp;
Asciz	hashCode;
Asciz	()I;
Asciz	(Lscala/reflect/ClassManifest;)I;
NameAndType	hashCode:(Lscala/reflect/ClassManifest;)I
Method	scala/reflect/ClassManifest$class.hashCode:(Lscala/reflect/ClassManifest;)I
Asciz	equals;
Asciz	(Ljava/lang/Object;)Z;
Asciz	(Lscala/reflect/ClassManifest;Ljava/lang/Object;)Z;
NameAndType	equals:(Lscala/reflect/ClassManifest;Ljava/lang/Object;)Z
Method	scala/reflect/ClassManifest$class.equals:(Lscala/reflect/ClassManifest;Ljava/lang/Object;)Z
Asciz	that;
Asciz	Ljava/lang/Object;;
Asciz	$greater$colon$greater;
Asciz	(Lscala/reflect/ClassManifest;)Z;
Asciz	(Lscala/reflect/ClassManifest;Lscala/reflect/ClassManifest;)Z;
NameAndType	$greater$colon$greater:(Lscala/reflect/ClassManifest;Lscala/reflect/ClassManifest;)Z
Method	scala/reflect/ClassManifest$class.$greater$colon$greater:(Lscala/reflect/ClassManifest;Lscala/reflect/ClassManifest;)Z
Asciz	Lscala/reflect/ClassManifest;;
Asciz	$less$colon$less;
NameAndType	$less$colon$less:(Lscala/reflect/ClassManifest;Lscala/reflect/ClassManifest;)Z
Method	scala/reflect/ClassManifest$class.$less$colon$less:(Lscala/reflect/ClassManifest;Lscala/reflect/ClassManifest;)Z
Asciz	<T:Ljava/lang/Object;>Ljava/lang/Object;Lscala/reflect/ClassManifest<TT;>;Lscala/ScalaObject;;
Asciz	Scala;
Asciz	InnerClasses;
Asciz	ClassTypeManifest;
Asciz	scala/ScalaObject;
class	scala/ScalaObject
Asciz	java/io/Serializable;
class	java/io/Serializable

{
private final scala.collection.immutable.List typeArguments;
  Signature: Lscala/collection/immutable/List;
  Signature: length = 0x2
   00 05 

private final java.lang.Class erasure;
  Signature: Ljava/lang/Class;
  Signature: length = 0x2
   00 09 

private final scala.Option prefix;
  Signature: Lscala/Option;
  Signature: length = 0x2
   00 0C 

public scala.reflect.ClassManifest$ClassTypeManifest(scala.Option, java.lang.Class, scala.collection.immutable.List);
  Signature: (Lscala/Option;Ljava/lang/Class;Lscala/collection/immutable/List;)V
  Code:
   Stack=2, Locals=4, Args_size=4
	aload_0
	aload_1
	putfield	Field prefix:Lscala/Option;
	aload_0
	aload_2
	putfield	Field erasure:Ljava/lang/Class;
	aload_0
	aload_3
	putfield	Field typeArguments:Lscala/collection/immutable/List;
	aload_0
	invokespecial	Method java/lang/Object."<init>":()V
	aload_0
	invokestatic	Method scala/reflect/ClassManifest$class.$init$:(Lscala/reflect/ClassManifest;)V
	return
  Labels:
  LocalVariableTable: 
   Start  Length  Slot  Name   Signature
   0      24      0    this       Lscala/reflect/ClassManifest$ClassTypeManifest;
   0      24      1    prefix       Lscala/Option;
   0      24      2    erasure       Ljava/lang/Class;
   0      24      3    typeArguments       Lscala/collection/immutable/List;

  Signature: length = 0x2
   00 27 

public java.lang.String toString();
  Signature: ()Ljava/lang/String;
  Code:
   Stack=3, Locals=1, Args_size=1
	new	class scala/collection/mutable/StringBuilder
	dup
	invokespecial	Method scala/collection/mutable/StringBuilder."<init>":()V
	aload_0
	getfield	Field prefix:Lscala/Option;
	invokevirtual	Method scala/Option.isEmpty:()Z
	ifeq	l1 // new
	ldc	String 
	goto	l2 // invokevirtual
l1	new	class scala/collection/mutable/StringBuilder
	dup
	invokespecial	Method scala/collection/mutable/StringBuilder."<init>":()V
	aload_0
	getfield	Field prefix:Lscala/Option;
	invokevirtual	Method scala/Option.get:()Ljava/lang/Object;
	invokevirtual	Method java/lang/Object.toString:()Ljava/lang/String;
	invokevirtual	Method scala/collection/mutable/StringBuilder.append:(Ljava/lang/Object;)Lscala/collection/mutable/StringBuilder;
	ldc	String #
	invokevirtual	Method scala/collection/mutable/StringBuilder.append:(Ljava/lang/Object;)Lscala/collection/mutable/StringBuilder;
	invokevirtual	Method scala/collection/mutable/StringBuilder.toString:()Ljava/lang/String;
l2	invokevirtual	Method scala/collection/mutable/StringBuilder.append:(Ljava/lang/Object;)Lscala/collection/mutable/StringBuilder;
	aload_0
	invokevirtual	Method erasure:()Ljava/lang/Class;
	invokevirtual	Method java/lang/Class.isArray:()Z
	ifeq	l3 // aload_0
	ldc	String Array
	goto	l4 // invokevirtual
l3	aload_0
	invokevirtual	Method erasure:()Ljava/lang/Class;
	invokevirtual	Method java/lang/Class.getName:()Ljava/lang/String;
l4	invokevirtual	Method scala/collection/mutable/StringBuilder.append:(Ljava/lang/Object;)Lscala/collection/mutable/StringBuilder;
	aload_0
	invokeinterface	InterfaceMethod scala/reflect/ClassManifest.argString:()Ljava/lang/String;
	invokevirtual	Method scala/collection/mutable/StringBuilder.append:(Ljava/lang/Object;)Lscala/collection/mutable/StringBuilder;
	invokevirtual	Method scala/collection/mutable/StringBuilder.toString:()Ljava/lang/String;
	areturn
  Labels:
   	l1 = 22 // new
   	l2 = 50 // invokevirtual
   	l3 = 68 // aload_0
   	l4 = 75 // invokevirtual

public scala.collection.immutable.List typeArguments();
  Signature: ()Lscala/collection/immutable/List;
  Code:
   Stack=1, Locals=1, Args_size=1
	aload_0
	getfield	Field typeArguments:Lscala/collection/immutable/List;
	areturn
  Labels:
  Signature: length = 0x2
   00 55 

public java.lang.Class erasure();
  Signature: ()Ljava/lang/Class;
  Code:
   Stack=1, Locals=1, Args_size=1
	aload_0
	getfield	Field erasure:Ljava/lang/Class;
	areturn
  Labels:
  Signature: length = 0x2
   00 56 

public java.lang.String argString();
  Signature: ()Ljava/lang/String;
  Code:
   Stack=1, Locals=1, Args_size=1
	aload_0
	invokestatic	Method scala/reflect/ClassManifest$class.argString:(Lscala/reflect/ClassManifest;)Ljava/lang/String;
	areturn
  Labels:

public scala.collection.mutable.ArrayBuilder newArrayBuilder();
  Signature: ()Lscala/collection/mutable/ArrayBuilder;
  Code:
   Stack=1, Locals=1, Args_size=1
	aload_0
	invokestatic	Method scala/reflect/ClassManifest$class.newArrayBuilder:(Lscala/reflect/ClassManifest;)Lscala/collection/mutable/ArrayBuilder;
	areturn
  Labels:

public scala.collection.mutable.WrappedArray newWrappedArray(int);
  Signature: (I)Lscala/collection/mutable/WrappedArray;
  Code:
   Stack=2, Locals=2, Args_size=2
	aload_0
	iload_1
	invokestatic	Method scala/reflect/ClassManifest$class.newWrappedArray:(Lscala/reflect/ClassManifest;I)Lscala/collection/mutable/WrappedArray;
	areturn
  Labels:
  LocalVariableTable: 
   Start  Length  Slot  Name   Signature
   0      6      0    this       Lscala/reflect/ClassManifest$ClassTypeManifest;
   0      6      1    len       I


public java.lang.Object[][][][] newArray5(int);
  Signature: (I)[[[[Ljava/lang/Object;
  Code:
   Stack=2, Locals=2, Args_size=2
	aload_0
	iload_1
	invokestatic	Method scala/reflect/ClassManifest$class.newArray5:(Lscala/reflect/ClassManifest;I)[[[[Ljava/lang/Object;
	areturn
  Labels:
  LocalVariableTable: 
   Start  Length  Slot  Name   Signature
   0      6      0    this       Lscala/reflect/ClassManifest$ClassTypeManifest;
   0      6      1    len       I


public java.lang.Object[][][] newArray4(int);
  Signature: (I)[[[Ljava/lang/Object;
  Code:
   Stack=2, Locals=2, Args_size=2
	aload_0
	iload_1
	invokestatic	Method scala/reflect/ClassManifest$class.newArray4:(Lscala/reflect/ClassManifest;I)[[[Ljava/lang/Object;
	areturn
  Labels:
  LocalVariableTable: 
   Start  Length  Slot  Name   Signature
   0      6      0    this       Lscala/reflect/ClassManifest$ClassTypeManifest;
   0      6      1    len       I


public java.lang.Object[][] newArray3(int);
  Signature: (I)[[Ljava/lang/Object;
  Code:
   Stack=2, Locals=2, Args_size=2
	aload_0
	iload_1
	invokestatic	Method scala/reflect/ClassManifest$class.newArray3:(Lscala/reflect/ClassManifest;I)[[Ljava/lang/Object;
	areturn
  Labels:
  LocalVariableTable: 
   Start  Length  Slot  Name   Signature
   0      6      0    this       Lscala/reflect/ClassManifest$ClassTypeManifest;
   0      6      1    len       I


public java.lang.Object[] newArray2(int);
  Signature: (I)[Ljava/lang/Object;
  Code:
   Stack=2, Locals=2, Args_size=2
	aload_0
	iload_1
	invokestatic	Method scala/reflect/ClassManifest$class.newArray2:(Lscala/reflect/ClassManifest;I)[Ljava/lang/Object;
	areturn
  Labels:
  LocalVariableTable: 
   Start  Length  Slot  Name   Signature
   0      6      0    this       Lscala/reflect/ClassManifest$ClassTypeManifest;
   0      6      1    len       I


public java.lang.Object newArray(int);
  Signature: (I)Ljava/lang/Object;
  Code:
   Stack=2, Locals=2, Args_size=2
	aload_0
	iload_1
	invokestatic	Method scala/reflect/ClassManifest$class.newArray:(Lscala/reflect/ClassManifest;I)Ljava/lang/Object;
	areturn
  Labels:
  LocalVariableTable: 
   Start  Length  Slot  Name   Signature
   0      6      0    this       Lscala/reflect/ClassManifest$ClassTypeManifest;
   0      6      1    len       I


public scala.reflect.ClassManifest arrayManifest();
  Signature: ()Lscala/reflect/ClassManifest;
  Code:
   Stack=1, Locals=1, Args_size=1
	aload_0
	invokestatic	Method scala/reflect/ClassManifest$class.arrayManifest:(Lscala/reflect/ClassManifest;)Lscala/reflect/ClassManifest;
	areturn
  Labels:

public java.lang.Class arrayClass(java.lang.Class);
  Signature: (Ljava/lang/Class;)Ljava/lang/Class;
  Code:
   Stack=2, Locals=2, Args_size=2
	aload_0
	aload_1
	invokestatic	Method scala/reflect/ClassManifest$class.arrayClass:(Lscala/reflect/ClassManifest;Ljava/lang/Class;)Ljava/lang/Class;
	areturn
  Labels:
  LocalVariableTable: 
   Start  Length  Slot  Name   Signature
   0      6      0    this       Lscala/reflect/ClassManifest$ClassTypeManifest;
   0      6      1    tp       Ljava/lang/Class;


public int hashCode();
  Signature: ()I
  Code:
   Stack=1, Locals=1, Args_size=1
	aload_0
	invokestatic	Method scala/reflect/ClassManifest$class.hashCode:(Lscala/reflect/ClassManifest;)I
	ireturn
  Labels:

public boolean equals(java.lang.Object);
  Signature: (Ljava/lang/Object;)Z
  Code:
   Stack=2, Locals=2, Args_size=2
	aload_0
	aload_1
	invokestatic	Method scala/reflect/ClassManifest$class.equals:(Lscala/reflect/ClassManifest;Ljava/lang/Object;)Z
	ireturn
  Labels:
  LocalVariableTable: 
   Start  Length  Slot  Name   Signature
   0      6      0    this       Lscala/reflect/ClassManifest$ClassTypeManifest;
   0      6      1    that       Ljava/lang/Object;


public boolean $greater$colon$greater(scala.reflect.ClassManifest);
  Signature: (Lscala/reflect/ClassManifest;)Z
  Code:
   Stack=2, Locals=2, Args_size=2
	aload_0
	aload_1
	invokestatic	Method scala/reflect/ClassManifest$class.$greater$colon$greater:(Lscala/reflect/ClassManifest;Lscala/reflect/ClassManifest;)Z
	ireturn
  Labels:
  LocalVariableTable: 
   Start  Length  Slot  Name   Signature
   0      6      0    this       Lscala/reflect/ClassManifest$ClassTypeManifest;
   0      6      1    that       Lscala/reflect/ClassManifest;


public boolean $less$colon$less(scala.reflect.ClassManifest);
  Signature: (Lscala/reflect/ClassManifest;)Z
  Code:
   Stack=2, Locals=2, Args_size=2
	aload_0
	aload_1
	invokestatic	Method scala/reflect/ClassManifest$class.$less$colon$less:(Lscala/reflect/ClassManifest;Lscala/reflect/ClassManifest;)Z
	ireturn
  Labels:
  LocalVariableTable: 
   Start  Length  Slot  Name   Signature
   0      6      0    this       Lscala/reflect/ClassManifest$ClassTypeManifest;
   0      6      1    that       Lscala/reflect/ClassManifest;


}

