Compiled from "Tree.scala"
public class scala.reflect.ClassDef extends scala.reflect.Tree implements scala.ScalaObject,scala.Product,java.io.Serializable
  SourceFile: "Tree.scala"
  ScalaSig: length = 0x44A
   05 00 FFFFFF81 1F 06 08 01 02 FFFFFF84 FFFFFF80 FFFFFF80 FFFFFF80 40 07 02 08
   43 6C 61 73 73 44 65 66 0A 02 03 04 01 07 72 65
   66 6C 65 63 74 0A 01 05 01 05 73 63 61 6C 61 03
   00 13 04 00 08 0C 10 10 02 09 0A 0D 01 02 09 02
   0B 02 02 04 54 72 65 65 10 02 0D 0E 0D 01 04 09
   02 0F 04 02 0B 53 63 61 6C 61 4F 62 6A 65 63 74
   10 02 0D 11 09 02 12 04 02 07 50 72 6F 64 75 63
   74 08 08 14 00 FFFFFF82 FFFFFFCA FFFFFF80 FFFFFF84 00 15 01 03 73 79 6D
   15 01 16 10 02 09 17 09 02 18 02 02 06 53 79 6D
   62 6F 6C 08 08 1A 00 FFFFFF82 FFFFFF88 FFFFFFA0 FFFFFF80 04 16 01 04 73
   79 6D 20 08 08 1C 00 FFFFFF82 FFFFFFCA FFFFFF80 FFFFFF84 00 1D 01 03 74
   70 65 15 01 1E 10 02 09 1F 09 02 20 02 02 04 54
   79 70 65 08 08 22 00 FFFFFF82 FFFFFF88 FFFFFFA0 FFFFFF80 04 1E 01 04 74
   70 65 20 08 08 24 00 FFFFFF82 FFFFFFCA FFFFFF80 FFFFFF84 00 25 01 04 69
   6D 70 6C 15 01 26 10 02 09 27 09 02 28 02 02 08
   54 65 6D 70 6C 61 74 65 08 08 2A 00 FFFFFF82 FFFFFF88 FFFFFFA0 FFFFFF80
   04 26 01 05 69 6D 70 6C 20 08 05 2C 00 FFFFFF84 00 2D
   01 06 3C 69 6E 69 74 3E 14 04 2E 2F 30 31 10 02
   09 00 08 05 14 2B FFFFFFC0 00 16 08 05 1C 2B FFFFFFC0 00 1E
   08 05 24 2B FFFFFFC0 00 26 08 07 33 00 FFFFFF81 FFFFFF80 FFFFFF84 00 34
   01 04 63 6F 70 79 14 04 2E 35 36 37 08 07 14 32
   FFFFFF90 FFFFFF80 FFFFFFC0 00 16 08 07 1C 32 FFFFFF90 FFFFFF80 FFFFFFC0 00 1E 08 07
   24 32 FFFFFF90 FFFFFF80 FFFFFFC0 00 26 08 07 39 00 FFFFFF91 FFFFFF80 FFFFFF84 00 3A
   01 0E 63 6F 70 79 24 64 65 66 61 75 6C 74 24 31
   15 01 3B 2A 02 16 3C 2B 01 3D 10 02 3E 43 0D 01
   3F 0A 02 40 41 01 09 75 6E 63 68 65 63 6B 65 64
   0A 02 42 04 01 0A 61 6E 6E 6F 74 61 74 69 6F 6E
   09 02 44 3F 02 11 75 6E 63 68 65 63 6B 65 64 56
   61 72 69 61 6E 63 65 08 07 46 00 FFFFFF91 FFFFFF80 FFFFFF84 00 47
   01 0E 63 6F 70 79 24 64 65 66 61 75 6C 74 24 32
   15 01 48 2A 02 1E 3C 08 07 4A 00 FFFFFF91 FFFFFF80 FFFFFF84 00 4B
   01 0E 63 6F 70 79 24 64 65 66 61 75 6C 74 24 33
   15 01 4C 2A 02 26 3C 08 08 4E 00 FFFFFF84 FFFFFF80 FFFFFF80 FFFFFF84 20
   4F 01 08 68 61 73 68 43 6F 64 65 14 01 50 10 02
   0D 51 09 02 52 04 02 03 49 6E 74 08 08 54 00 FFFFFF84
   FFFFFF80 FFFFFF80 FFFFFF84 20 55 01 08 74 6F 53 74 72 69 6E 67 14
   01 56 10 02 57 5A 0E 02 0D 58 09 02 59 04 01 06
   50 72 65 64 65 66 09 02 5B 5C 02 06 53 74 72 69
   6E 67 0A 02 59 04 08 08 5E 00 FFFFFF84 FFFFFF80 FFFFFF80 FFFFFF84 20 5F
   01 06 65 71 75 61 6C 73 14 02 60 63 10 02 0D 61
   09 02 62 04 02 07 42 6F 6F 6C 65 61 6E 08 07 64
   5D FFFFFF81 FFFFFF80 FFFFFFC0 00 65 01 03 78 24 31 10 02 0D 66 09
   02 67 04 02 03 41 6E 79 08 08 69 00 FFFFFF84 FFFFFF80 FFFFFF80 FFFFFF84
   20 6A 01 0D 70 72 6F 64 75 63 74 50 72 65 66 69
   78 15 01 6B 10 02 6C 71 0D 01 6D 0A 02 6E 6F 01
   04 6C 61 6E 67 0A 01 70 01 04 6A 61 76 61 09 02
   5B 6D 08 08 73 00 FFFFFF84 FFFFFF80 FFFFFF80 FFFFFF84 20 74 01 0C 70 72
   6F 64 75 63 74 41 72 69 74 79 15 01 50 08 08 76
   00 FFFFFF84 FFFFFF80 FFFFFF80 FFFFFF84 20 77 01 0E 70 72 6F 64 75 63 74
   45 6C 65 6D 65 6E 74 14 02 65 78 08 07 64 75 FFFFFF81
   FFFFFF80 FFFFFFC0 00 50 08 08 7A 00 FFFFFF84 FFFFFF80 FFFFFF80 FFFFFF84 20 7B 01 08
   63 61 6E 45 71 75 61 6C 14 02 60 7C 08 07 64 79
   FFFFFF81 FFFFFF80 FFFFFFC0 00 65 28 02 00 7E 10 02 0D 7F 09 03 FFFFFF81
   00 04 02 0C 73 65 72 69 61 6C 69 7A 61 62 6C 65
   07 09 FFFFFF81 02 02 FFFFFF81 FFFFFF80 FFFFFF88 02 FFFFFF81 03 01 08 43 6C 61
   73 73 44 65 66 10 03 09 FFFFFF81 04 06 09 01 02 FFFFFF84 FFFFFF81
   FFFFFF80 FFFFFF88 02 FFFFFF81 05 13 07 FFFFFF81 04 FFFFFF81 06 FFFFFF81 09 0C 10 03
   6C FFFFFF81 07 09 03 FFFFFF81 08 6D 02 06 4F 62 6A 65 63 74
   10 07 0D FFFFFF81 0A 16 1E 26 2E 09 03 FFFFFF81 0B 04 02 09
   46 75 6E 63 74 69 6F 6E 33 08 07 2C FFFFFF81 04 FFFFFF84 00
   FFFFFF81 0D 14 02 FFFFFF81 03 08 0A FFFFFF81 0F FFFFFF81 04 FFFFFF81 FFFFFF80 FFFFFF84 40
   FFFFFF81 10 01 05 61 70 70 6C 79 14 07 2E FFFFFF81 11 FFFFFF81 12
   FFFFFF81 13 08 06 14 FFFFFF81 0E FFFFFFC0 00 16 08 06 1C FFFFFF81 0E FFFFFFC0
   00 1E 08 06 24 FFFFFF81 0E FFFFFFC0 00 26 08 0A FFFFFF81 15 FFFFFF81 04
   FFFFFF81 FFFFFF80 FFFFFF84 40 FFFFFF81 16 01 07 75 6E 61 70 70 6C 79 14
   04 FFFFFF81 17 FFFFFF81 1D 10 05 0D FFFFFF81 18 FFFFFF81 1A 09 03 FFFFFF81 19
   04 02 04 53 6F 6D 65 10 06 0D FFFFFF81 1B 16 1E 26 09
   03 FFFFFF81 1C 04 02 06 54 75 70 6C 65 33 08 07 FFFFFF81 1E
   FFFFFF81 14 FFFFFFC0 00 2E 01 03 78 24 30 
  minor version: 0
  major version: 49
  Constant pool:
Asciz	SourceFile;
Asciz	Tree.scala;
Asciz	tupled;
Asciz	()Lscala/Function1;;
Asciz	Code;
Asciz	scala/reflect/ClassDef$;
class	scala/reflect/ClassDef$
Asciz	MODULE$;
Asciz	Lscala/reflect/ClassDef$;;
NameAndType	MODULE$:Lscala/reflect/ClassDef$;
Field	scala/reflect/ClassDef$.MODULE$:Lscala/reflect/ClassDef$;
NameAndType	tupled:()Lscala/Function1;
Method	scala/reflect/ClassDef$.tupled:()Lscala/Function1;
Asciz	curry;
NameAndType	curry:()Lscala/Function1;
Method	scala/reflect/ClassDef$.curry:()Lscala/Function1;
Asciz	Deprecated;
Asciz	curried;
NameAndType	curried:()Lscala/Function1;
Method	scala/reflect/ClassDef$.curried:()Lscala/Function1;
Asciz	impl;
Asciz	Lscala/reflect/Template;;
Asciz	tpe;
Asciz	Lscala/reflect/Type;;
Asciz	sym;
Asciz	Lscala/reflect/Symbol;;
Asciz	<init>;
Asciz	(Lscala/reflect/Symbol;Lscala/reflect/Type;Lscala/reflect/Template;)V;
Asciz	LineNumberTable;
Asciz	scala/reflect/ClassDef;
class	scala/reflect/ClassDef
NameAndType	sym:Lscala/reflect/Symbol;
Field	scala/reflect/ClassDef.sym:Lscala/reflect/Symbol;
NameAndType	tpe:Lscala/reflect/Type;
Field	scala/reflect/ClassDef.tpe:Lscala/reflect/Type;
NameAndType	impl:Lscala/reflect/Template;
Field	scala/reflect/ClassDef.impl:Lscala/reflect/Template;
Asciz	scala/reflect/Tree;
class	scala/reflect/Tree
Asciz	()V;
NameAndType	"<init>":()V
Method	scala/reflect/Tree."<init>":()V
Asciz	scala/Product$class;
class	scala/Product$class
Asciz	$init$;
Asciz	(Lscala/Product;)V;
NameAndType	$init$:(Lscala/Product;)V
Method	scala/Product$class.$init$:(Lscala/Product;)V
Asciz	this;
Asciz	Lscala/reflect/ClassDef;;
Asciz	LocalVariableTable;
Asciz	gd15$1;
Asciz	(Lscala/reflect/Symbol;Lscala/reflect/Type;Lscala/reflect/Template;)Z;
Asciz	()Lscala/reflect/Symbol;;
NameAndType	sym:()Lscala/reflect/Symbol;
Method	scala/reflect/ClassDef.sym:()Lscala/reflect/Symbol;
Asciz	java/lang/Object;
class	java/lang/Object
Asciz	equals;
Asciz	(Ljava/lang/Object;)Z;
NameAndType	equals:(Ljava/lang/Object;)Z
Method	java/lang/Object.equals:(Ljava/lang/Object;)Z
Asciz	()Lscala/reflect/Type;;
NameAndType	tpe:()Lscala/reflect/Type;
Method	scala/reflect/ClassDef.tpe:()Lscala/reflect/Type;
Asciz	()Lscala/reflect/Template;;
NameAndType	impl:()Lscala/reflect/Template;
Method	scala/reflect/ClassDef.impl:()Lscala/reflect/Template;
Asciz	canEqual;
Asciz	productElement;
Asciz	(I)Ljava/lang/Object;;
Asciz	java/lang/IndexOutOfBoundsException;
class	java/lang/IndexOutOfBoundsException
Asciz	scala/runtime/BoxesRunTime;
class	scala/runtime/BoxesRunTime
Asciz	boxToInteger;
Asciz	(I)Ljava/lang/Integer;;
NameAndType	boxToInteger:(I)Ljava/lang/Integer;
Method	scala/runtime/BoxesRunTime.boxToInteger:(I)Ljava/lang/Integer;
Asciz	toString;
Asciz	()Ljava/lang/String;;
NameAndType	toString:()Ljava/lang/String;
Method	java/lang/Object.toString:()Ljava/lang/String;
Asciz	(Ljava/lang/String;)V;
NameAndType	"<init>":(Ljava/lang/String;)V
Method	java/lang/IndexOutOfBoundsException."<init>":(Ljava/lang/String;)V
Asciz	productArity;
Asciz	()I;
Asciz	productPrefix;
Asciz	ClassDef;
String	ClassDef
NameAndType	gd15$1:(Lscala/reflect/Symbol;Lscala/reflect/Type;Lscala/reflect/Template;)Z
Method	scala/reflect/ClassDef.gd15$1:(Lscala/reflect/Symbol;Lscala/reflect/Type;Lscala/reflect/Template;)Z
Asciz	scala/Equals;
class	scala/Equals
NameAndType	canEqual:(Ljava/lang/Object;)Z
InterfaceMethod	scala/Equals.canEqual:(Ljava/lang/Object;)Z
Asciz	temp68;
Asciz	temp69;
Asciz	temp70;
Asciz	temp71;
Asciz	scala/runtime/ScalaRunTime$;
class	scala/runtime/ScalaRunTime$
Asciz	Lscala/runtime/ScalaRunTime$;;
NameAndType	MODULE$:Lscala/runtime/ScalaRunTime$;
Field	scala/runtime/ScalaRunTime$.MODULE$:Lscala/runtime/ScalaRunTime$;
Asciz	_toString;
Asciz	(Lscala/Product;)Ljava/lang/String;;
NameAndType	_toString:(Lscala/Product;)Ljava/lang/String;
Method	scala/runtime/ScalaRunTime$._toString:(Lscala/Product;)Ljava/lang/String;
Asciz	hashCode;
Asciz	_hashCode;
Asciz	(Lscala/Product;)I;
NameAndType	_hashCode:(Lscala/Product;)I
Method	scala/runtime/ScalaRunTime$._hashCode:(Lscala/Product;)I
Asciz	copy;
Asciz	(Lscala/reflect/Symbol;Lscala/reflect/Type;Lscala/reflect/Template;)Lscala/reflect/ClassDef;;
NameAndType	"<init>":(Lscala/reflect/Symbol;Lscala/reflect/Type;Lscala/reflect/Template;)V
Method	scala/reflect/ClassDef."<init>":(Lscala/reflect/Symbol;Lscala/reflect/Type;Lscala/reflect/Template;)V
Asciz	copy$default$1;
Asciz	copy$default$2;
Asciz	copy$default$3;
Asciz	productElements;
Asciz	()Lscala/collection/Iterator;;
Asciz	(Lscala/Product;)Lscala/collection/Iterator;;
NameAndType	productElements:(Lscala/Product;)Lscala/collection/Iterator;
Method	scala/Product$class.productElements:(Lscala/Product;)Lscala/collection/Iterator;
Asciz	productIterator;
NameAndType	productIterator:(Lscala/Product;)Lscala/collection/Iterator;
Method	scala/Product$class.productIterator:(Lscala/Product;)Lscala/collection/Iterator;
Asciz	ScalaSig;
Asciz	scala/ScalaObject;
class	scala/ScalaObject
Asciz	scala/Product;
class	scala/Product
Asciz	java/io/Serializable;
class	java/io/Serializable

{
private final scala.reflect.Template impl;
  Signature: Lscala/reflect/Template;

private final scala.reflect.Type tpe;
  Signature: Lscala/reflect/Type;

private final scala.reflect.Symbol sym;
  Signature: Lscala/reflect/Symbol;

public static final scala.Function1 tupled();
  Signature: ()Lscala/Function1;
  Code:
   Stack=1, Locals=0, Args_size=0
	getstatic	Field scala/reflect/ClassDef$.MODULE$:Lscala/reflect/ClassDef$;
	invokevirtual	Method scala/reflect/ClassDef$.tupled:()Lscala/Function1;
	areturn
  Labels:

public static final scala.Function1 curry();
  Signature: ()Lscala/Function1;
  Code:
   Stack=1, Locals=0, Args_size=0
	getstatic	Field scala/reflect/ClassDef$.MODULE$:Lscala/reflect/ClassDef$;
	invokevirtual	Method scala/reflect/ClassDef$.curry:()Lscala/Function1;
	areturn
  Labels:
  Deprecated: true

public static final scala.Function1 curried();
  Signature: ()Lscala/Function1;
  Code:
   Stack=1, Locals=0, Args_size=0
	getstatic	Field scala/reflect/ClassDef$.MODULE$:Lscala/reflect/ClassDef$;
	invokevirtual	Method scala/reflect/ClassDef$.curried:()Lscala/Function1;
	areturn
  Labels:

public scala.reflect.ClassDef(scala.reflect.Symbol, scala.reflect.Type, scala.reflect.Template);
  Signature: (Lscala/reflect/Symbol;Lscala/reflect/Type;Lscala/reflect/Template;)V
  Code:
   Stack=2, Locals=4, Args_size=4
	aload_0
	aload_1
	putfield	Field sym:Lscala/reflect/Symbol;
	aload_0
	aload_2
	putfield	Field tpe:Lscala/reflect/Type;
	aload_0
	aload_3
	putfield	Field impl:Lscala/reflect/Template;
	aload_0
	invokespecial	Method scala/reflect/Tree."<init>":()V
	aload_0
	invokestatic	Method scala/Product$class.$init$:(Lscala/Product;)V
	return
  Labels:
  LocalVariableTable: 
   Start  Length  Slot  Name   Signature
   0      24      0    this       Lscala/reflect/ClassDef;
   0      24      1    sym       Lscala/reflect/Symbol;
   0      24      2    tpe       Lscala/reflect/Type;
   0      24      3    impl       Lscala/reflect/Template;


private final boolean gd15$1(scala.reflect.Symbol, scala.reflect.Type, scala.reflect.Template);
  Signature: (Lscala/reflect/Symbol;Lscala/reflect/Type;Lscala/reflect/Template;)Z
  Code:
   Stack=2, Locals=7, Args_size=4
	aload_1
	aload_0
	invokevirtual	Method sym:()Lscala/reflect/Symbol;
	astore	4
	dup
	ifnonnull	l1 // aload
	pop
	aload	4
	ifnull	l2 // aload_2
	goto	l3 // iconst_0
l1	aload	4
	invokevirtual	Method java/lang/Object.equals:(Ljava/lang/Object;)Z
	ifeq	l3 // iconst_0
l2	aload_2
	aload_0
	invokevirtual	Method tpe:()Lscala/reflect/Type;
	astore	5
	dup
	ifnonnull	l4 // aload
	pop
	aload	5
	ifnull	l5 // aload_3
	goto	l3 // iconst_0
l4	aload	5
	invokevirtual	Method java/lang/Object.equals:(Ljava/lang/Object;)Z
	ifeq	l3 // iconst_0
l5	aload_3
	aload_0
	invokevirtual	Method impl:()Lscala/reflect/Template;
	astore	6
	dup
	ifnonnull	l6 // aload
	pop
	aload	6
	ifnull	l7 // iconst_1
	goto	l3 // iconst_0
l6	aload	6
	invokevirtual	Method java/lang/Object.equals:(Ljava/lang/Object;)Z
	ifeq	l3 // iconst_0
l7	iconst_1
	goto	l8 // ireturn
l3	iconst_0
l8	ireturn
  Labels:
   	l1 = 20 // aload
   	l2 = 28 // aload_2
   	l4 = 48 // aload
   	l5 = 56 // aload_3
   	l6 = 76 // aload
   	l7 = 84 // iconst_1
   	l3 = 88 // iconst_0
   	l8 = 89 // ireturn

public boolean canEqual(java.lang.Object);
  Signature: (Ljava/lang/Object;)Z
  Code:
   Stack=1, Locals=2, Args_size=2
	aload_1
	instanceof	class scala/reflect/ClassDef
	ireturn
  Labels:

public java.lang.Object productElement(int);
  Signature: (I)Ljava/lang/Object;
  Code:
   Stack=3, Locals=2, Args_size=2
	iload_1
	tableswitch{ //0 to 2
		0: 57;
		1: 50;
		2: 43;
		default: 28 }
	new	class java/lang/IndexOutOfBoundsException
	dup
	iload_1
	invokestatic	Method scala/runtime/BoxesRunTime.boxToInteger:(I)Ljava/lang/Integer;
	invokevirtual	Method java/lang/Object.toString:()Ljava/lang/String;
	invokespecial	Method java/lang/IndexOutOfBoundsException."<init>":(Ljava/lang/String;)V
	athrow
	aload_0
	invokevirtual	Method impl:()Lscala/reflect/Template;
	goto	l1 // areturn
	aload_0
	invokevirtual	Method tpe:()Lscala/reflect/Type;
	goto	l1 // areturn
	aload_0
	invokevirtual	Method sym:()Lscala/reflect/Symbol;
l1	areturn
  Labels:
   	l1 = 61 // areturn

public int productArity();
  Signature: ()I
  Code:
   Stack=1, Locals=1, Args_size=1
	iconst_3
	ireturn
  Labels:

public java.lang.String productPrefix();
  Signature: ()Ljava/lang/String;
  Code:
   Stack=1, Locals=1, Args_size=1
	ldc	String ClassDef
	areturn
  Labels:

public boolean equals(java.lang.Object);
  Signature: (Ljava/lang/Object;)Z
  Code:
   Stack=4, Locals=6, Args_size=2
	aload_0
	aload_1
	if_acmpeq	l1 // iconst_1
	aload_1
	instanceof	class scala/reflect/ClassDef
	ifeq	l2 // iconst_0
	aload_1
	checkcast	class scala/reflect/ClassDef
	astore_2
	aload_2
	invokevirtual	Method sym:()Lscala/reflect/Symbol;
	astore_3
	aload_2
	invokevirtual	Method tpe:()Lscala/reflect/Type;
	astore	4
	aload_2
	invokevirtual	Method impl:()Lscala/reflect/Template;
	astore	5
	aload_0
	aload_3
	aload	4
	aload	5
	invokespecial	Method gd15$1:(Lscala/reflect/Symbol;Lscala/reflect/Type;Lscala/reflect/Template;)Z
	ifeq	l3 // iconst_0
	aload_1
	checkcast	class scala/reflect/ClassDef
	aload_0
	invokeinterface	InterfaceMethod scala/Equals.canEqual:(Ljava/lang/Object;)Z
	goto	l4 // ifeq
l3	iconst_0
	goto	l4 // ifeq
l2	iconst_0
l4	ifeq	l5 // iconst_0
l1	iconst_1
	goto	l6 // ireturn
l5	iconst_0
l6	ireturn
  Labels:
   	l3 = 59 // iconst_0
   	l2 = 63 // iconst_0
   	l4 = 64 // ifeq
   	l1 = 67 // iconst_1
   	l5 = 71 // iconst_0
   	l6 = 72 // ireturn
  LocalVariableTable: 
   Start  Length  Slot  Name   Signature
   0      73      0    this       Lscala/reflect/ClassDef;
   17      46      2    temp68       Lscala/reflect/ClassDef;
   22      41      3    temp69       Lscala/reflect/Symbol;
   28      35      4    temp70       Lscala/reflect/Type;
   34      29      5    temp71       Lscala/reflect/Template;


public java.lang.String toString();
  Signature: ()Ljava/lang/String;
  Code:
   Stack=2, Locals=1, Args_size=1
	getstatic	Field scala/runtime/ScalaRunTime$.MODULE$:Lscala/runtime/ScalaRunTime$;
	aload_0
	invokevirtual	Method scala/runtime/ScalaRunTime$._toString:(Lscala/Product;)Ljava/lang/String;
	areturn
  Labels:

public int hashCode();
  Signature: ()I
  Code:
   Stack=2, Locals=1, Args_size=1
	getstatic	Field scala/runtime/ScalaRunTime$.MODULE$:Lscala/runtime/ScalaRunTime$;
	aload_0
	invokevirtual	Method scala/runtime/ScalaRunTime$._hashCode:(Lscala/Product;)I
	ireturn
  Labels:

public scala.reflect.ClassDef copy(scala.reflect.Symbol, scala.reflect.Type, scala.reflect.Template);
  Signature: (Lscala/reflect/Symbol;Lscala/reflect/Type;Lscala/reflect/Template;)Lscala/reflect/ClassDef;
  Code:
   Stack=5, Locals=4, Args_size=4
	new	class scala/reflect/ClassDef
	dup
	aload_1
	aload_2
	aload_3
	invokespecial	Method "<init>":(Lscala/reflect/Symbol;Lscala/reflect/Type;Lscala/reflect/Template;)V
	areturn
  Labels:
  LocalVariableTable: 
   Start  Length  Slot  Name   Signature
   0      11      0    this       Lscala/reflect/ClassDef;
   0      11      1    sym       Lscala/reflect/Symbol;
   0      11      2    tpe       Lscala/reflect/Type;
   0      11      3    impl       Lscala/reflect/Template;


public scala.reflect.Template impl();
  Signature: ()Lscala/reflect/Template;
  Code:
   Stack=1, Locals=1, Args_size=1
	aload_0
	getfield	Field impl:Lscala/reflect/Template;
	areturn
  Labels:

public scala.reflect.Type tpe();
  Signature: ()Lscala/reflect/Type;
  Code:
   Stack=1, Locals=1, Args_size=1
	aload_0
	getfield	Field tpe:Lscala/reflect/Type;
	areturn
  Labels:

public scala.reflect.Symbol sym();
  Signature: ()Lscala/reflect/Symbol;
  Code:
   Stack=1, Locals=1, Args_size=1
	aload_0
	getfield	Field sym:Lscala/reflect/Symbol;
	areturn
  Labels:

public scala.reflect.Symbol copy$default$1();
  Signature: ()Lscala/reflect/Symbol;
  Code:
   Stack=1, Locals=1, Args_size=1
	aload_0
	invokevirtual	Method sym:()Lscala/reflect/Symbol;
	areturn
  Labels:

public scala.reflect.Type copy$default$2();
  Signature: ()Lscala/reflect/Type;
  Code:
   Stack=1, Locals=1, Args_size=1
	aload_0
	invokevirtual	Method tpe:()Lscala/reflect/Type;
	areturn
  Labels:

public scala.reflect.Template copy$default$3();
  Signature: ()Lscala/reflect/Template;
  Code:
   Stack=1, Locals=1, Args_size=1
	aload_0
	invokevirtual	Method impl:()Lscala/reflect/Template;
	areturn
  Labels:

public scala.collection.Iterator productElements();
  Signature: ()Lscala/collection/Iterator;
  Code:
   Stack=1, Locals=1, Args_size=1
	aload_0
	invokestatic	Method scala/Product$class.productElements:(Lscala/Product;)Lscala/collection/Iterator;
	areturn
  Labels:
  Deprecated: true

public scala.collection.Iterator productIterator();
  Signature: ()Lscala/collection/Iterator;
  Code:
   Stack=1, Locals=1, Args_size=1
	aload_0
	invokestatic	Method scala/Product$class.productIterator:(Lscala/Product;)Lscala/collection/Iterator;
	areturn
  Labels:

}

