Compiled from "ClassManifest.scala"
public final class scala.reflect.ClassManifest$ extends java.lang.Object implements scala.ScalaObject
  SourceFile: "ClassManifest.scala"
  Scala: length = 0x
   
  InnerClass: 
   public final $anon$1=class scala/reflect/ClassManifest$$anon$1 of class scala/reflect/ClassManifest
   public final $anon$2=class scala/reflect/ClassManifest$$anon$2 of class scala/reflect/ClassManifest
   public final $anon$3=class scala/reflect/ClassManifest$$anon$3 of class scala/reflect/ClassManifest
   public ClassTypeManifest=class scala/reflect/ClassManifest$ClassTypeManifest of class scala/reflect/ClassManifest
   public final $anonfun$subargs$1$1=class scala/reflect/ClassManifest$$anonfun$subargs$1$1 of class scala/reflect/ClassManifest
   public final $anonfun$subtype$1$1=class scala/reflect/ClassManifest$$anonfun$subtype$1$1 of class scala/reflect/ClassManifest
  minor version: 0
  major version: 49
  Constant pool:
Asciz	SourceFile;
Asciz	ClassManifest.scala;
Asciz	Scala;
Asciz	MODULE$;
Asciz	Lscala/reflect/ClassManifest$;;
Asciz	<clinit>;
Asciz	()V;
Asciz	Code;
Asciz	scala/reflect/ClassManifest$;
class	scala/reflect/ClassManifest$
Asciz	<init>;
NameAndType	"<init>":()V
Method	scala/reflect/ClassManifest$."<init>":()V
Asciz	Null;
Asciz	Lscala/reflect/Manifest;;
Asciz	Lscala/reflect/Manifest<Lscala/runtime/Null$;>;;
Asciz	Signature;
Asciz	Nothing;
Asciz	Lscala/reflect/Manifest<Lscala/runtime/Nothing$;>;;
Asciz	AnyVal;
Asciz	Lscala/reflect/Manifest<Ljava/lang/Object;>;;
Asciz	Object;
Asciz	Any;
Asciz	Unit;
Asciz	Lscala/reflect/AnyValManifest;;
Asciz	Lscala/reflect/AnyValManifest<Ljava/lang/Object;>;;
Asciz	Boolean;
Asciz	Lscala/reflect/AnyValManifest<Ljava/lang/Boolean;>;;
Asciz	Double;
Asciz	Lscala/reflect/AnyValManifest<Ljava/lang/Double;>;;
Asciz	Float;
Asciz	Lscala/reflect/AnyValManifest<Ljava/lang/Float;>;;
Asciz	Long;
Asciz	Lscala/reflect/AnyValManifest<Ljava/lang/Long;>;;
Asciz	Int;
Asciz	Lscala/reflect/AnyValManifest<Ljava/lang/Integer;>;;
Asciz	Char;
Asciz	Lscala/reflect/AnyValManifest<Ljava/lang/Character;>;;
Asciz	Short;
Asciz	Lscala/reflect/AnyValManifest<Ljava/lang/Short;>;;
Asciz	Byte;
Asciz	Lscala/reflect/AnyValManifest<Ljava/lang/Byte;>;;
Asciz	LineNumberTable;
Asciz	java/lang/Object;
class	java/lang/Object
Method	java/lang/Object."<init>":()V
NameAndType	MODULE$:Lscala/reflect/ClassManifest$;
Field	scala/reflect/ClassManifest$.MODULE$:Lscala/reflect/ClassManifest$;
Asciz	scala/reflect/Manifest$;
class	scala/reflect/Manifest$
Asciz	Lscala/reflect/Manifest$;;
NameAndType	MODULE$:Lscala/reflect/Manifest$;
Field	scala/reflect/Manifest$.MODULE$:Lscala/reflect/Manifest$;
Asciz	()Lscala/reflect/AnyValManifest;;
NameAndType	Byte:()Lscala/reflect/AnyValManifest;
Method	scala/reflect/Manifest$.Byte:()Lscala/reflect/AnyValManifest;
NameAndType	Byte:Lscala/reflect/AnyValManifest;
Field	scala/reflect/ClassManifest$.Byte:Lscala/reflect/AnyValManifest;
NameAndType	Short:()Lscala/reflect/AnyValManifest;
Method	scala/reflect/Manifest$.Short:()Lscala/reflect/AnyValManifest;
NameAndType	Short:Lscala/reflect/AnyValManifest;
Field	scala/reflect/ClassManifest$.Short:Lscala/reflect/AnyValManifest;
NameAndType	Char:()Lscala/reflect/AnyValManifest;
Method	scala/reflect/Manifest$.Char:()Lscala/reflect/AnyValManifest;
NameAndType	Char:Lscala/reflect/AnyValManifest;
Field	scala/reflect/ClassManifest$.Char:Lscala/reflect/AnyValManifest;
NameAndType	Int:()Lscala/reflect/AnyValManifest;
Method	scala/reflect/Manifest$.Int:()Lscala/reflect/AnyValManifest;
NameAndType	Int:Lscala/reflect/AnyValManifest;
Field	scala/reflect/ClassManifest$.Int:Lscala/reflect/AnyValManifest;
NameAndType	Long:()Lscala/reflect/AnyValManifest;
Method	scala/reflect/Manifest$.Long:()Lscala/reflect/AnyValManifest;
NameAndType	Long:Lscala/reflect/AnyValManifest;
Field	scala/reflect/ClassManifest$.Long:Lscala/reflect/AnyValManifest;
NameAndType	Float:()Lscala/reflect/AnyValManifest;
Method	scala/reflect/Manifest$.Float:()Lscala/reflect/AnyValManifest;
NameAndType	Float:Lscala/reflect/AnyValManifest;
Field	scala/reflect/ClassManifest$.Float:Lscala/reflect/AnyValManifest;
NameAndType	Double:()Lscala/reflect/AnyValManifest;
Method	scala/reflect/Manifest$.Double:()Lscala/reflect/AnyValManifest;
NameAndType	Double:Lscala/reflect/AnyValManifest;
Field	scala/reflect/ClassManifest$.Double:Lscala/reflect/AnyValManifest;
NameAndType	Boolean:()Lscala/reflect/AnyValManifest;
Method	scala/reflect/Manifest$.Boolean:()Lscala/reflect/AnyValManifest;
NameAndType	Boolean:Lscala/reflect/AnyValManifest;
Field	scala/reflect/ClassManifest$.Boolean:Lscala/reflect/AnyValManifest;
NameAndType	Unit:()Lscala/reflect/AnyValManifest;
Method	scala/reflect/Manifest$.Unit:()Lscala/reflect/AnyValManifest;
NameAndType	Unit:Lscala/reflect/AnyValManifest;
Field	scala/reflect/ClassManifest$.Unit:Lscala/reflect/AnyValManifest;
Asciz	()Lscala/reflect/Manifest;;
NameAndType	Any:()Lscala/reflect/Manifest;
Method	scala/reflect/Manifest$.Any:()Lscala/reflect/Manifest;
NameAndType	Any:Lscala/reflect/Manifest;
Field	scala/reflect/ClassManifest$.Any:Lscala/reflect/Manifest;
NameAndType	Object:()Lscala/reflect/Manifest;
Method	scala/reflect/Manifest$.Object:()Lscala/reflect/Manifest;
NameAndType	Object:Lscala/reflect/Manifest;
Field	scala/reflect/ClassManifest$.Object:Lscala/reflect/Manifest;
NameAndType	AnyVal:()Lscala/reflect/Manifest;
Method	scala/reflect/Manifest$.AnyVal:()Lscala/reflect/Manifest;
NameAndType	AnyVal:Lscala/reflect/Manifest;
Field	scala/reflect/ClassManifest$.AnyVal:Lscala/reflect/Manifest;
NameAndType	Nothing:()Lscala/reflect/Manifest;
Method	scala/reflect/Manifest$.Nothing:()Lscala/reflect/Manifest;
NameAndType	Nothing:Lscala/reflect/Manifest;
Field	scala/reflect/ClassManifest$.Nothing:Lscala/reflect/Manifest;
NameAndType	Null:()Lscala/reflect/Manifest;
Method	scala/reflect/Manifest$.Null:()Lscala/reflect/Manifest;
NameAndType	Null:Lscala/reflect/Manifest;
Field	scala/reflect/ClassManifest$.Null:Lscala/reflect/Manifest;
Asciz	intersectionType;
Asciz	(Lscala/collection/Seq;)Lscala/reflect/ClassManifest;;
Asciz	scala/reflect/ClassManifest$$anon$3;
class	scala/reflect/ClassManifest$$anon$3
Asciz	(Lscala/collection/Seq;)V;
NameAndType	"<init>":(Lscala/collection/Seq;)V
Method	scala/reflect/ClassManifest$$anon$3."<init>":(Lscala/collection/Seq;)V
Asciz	this;
Asciz	parents$1;
Asciz	Lscala/collection/Seq;;
Asciz	LocalVariableTable;
Asciz	<T:Ljava/lang/Object;>(Lscala/collection/Seq<Lscala/reflect/ClassManifest<*>;>;)Lscala/reflect/ClassManifest<TT;>;;
Asciz	abstractType;
Asciz	(Lscala/reflect/OptManifest;Ljava/lang/String;Lscala/reflect/ClassManifest;Lscala/collection/Seq;)Lscala/reflect/ClassManifest;;
Asciz	scala/reflect/ClassManifest$$anon$2;
class	scala/reflect/ClassManifest$$anon$2
Asciz	(Lscala/reflect/OptManifest;Ljava/lang/String;Lscala/reflect/ClassManifest;Lscala/collection/Seq;)V;
NameAndType	"<init>":(Lscala/reflect/OptManifest;Ljava/lang/String;Lscala/reflect/ClassManifest;Lscala/collection/Seq;)V
Method	scala/reflect/ClassManifest$$anon$2."<init>":(Lscala/reflect/OptManifest;Ljava/lang/String;Lscala/reflect/ClassManifest;Lscala/collection/Seq;)V
Asciz	prefix$2;
Asciz	Lscala/reflect/OptManifest;;
Asciz	name$2;
Asciz	Ljava/lang/String;;
Asciz	upperbound$1;
Asciz	Lscala/reflect/ClassManifest;;
Asciz	args$2;
Asciz	<T:Ljava/lang/Object;>(Lscala/reflect/OptManifest<*>;Ljava/lang/String;Lscala/reflect/ClassManifest<*>;Lscala/collection/Seq<Lscala/reflect/OptManifest<*>;>;)Lscala/reflect/ClassManifest<TT;>;;
Asciz	(Lscala/reflect/OptManifest;Ljava/lang/String;Ljava/lang/Class;Lscala/collection/Seq;)Lscala/reflect/ClassManifest;;
Asciz	scala/reflect/ClassManifest$$anon$1;
class	scala/reflect/ClassManifest$$anon$1
Asciz	(Lscala/reflect/OptManifest;Ljava/lang/String;Ljava/lang/Class;Lscala/collection/Seq;)V;
NameAndType	"<init>":(Lscala/reflect/OptManifest;Ljava/lang/String;Ljava/lang/Class;Lscala/collection/Seq;)V
Method	scala/reflect/ClassManifest$$anon$1."<init>":(Lscala/reflect/OptManifest;Ljava/lang/String;Ljava/lang/Class;Lscala/collection/Seq;)V
Asciz	prefix$1;
Asciz	name$1;
Asciz	clazz$1;
Asciz	Ljava/lang/Class;;
Asciz	args$1;
Asciz	<T:Ljava/lang/Object;>(Lscala/reflect/OptManifest<*>;Ljava/lang/String;Ljava/lang/Class<*>;Lscala/collection/Seq<Lscala/reflect/OptManifest<*>;>;)Lscala/reflect/ClassManifest<TT;>;;
Asciz	arrayType;
Asciz	(Lscala/reflect/OptManifest;)Lscala/reflect/ClassManifest;;
Asciz	scala/reflect/NoManifest$;
class	scala/reflect/NoManifest$
Asciz	Lscala/reflect/NoManifest$;;
NameAndType	MODULE$:Lscala/reflect/NoManifest$;
Field	scala/reflect/NoManifest$.MODULE$:Lscala/reflect/NoManifest$;
Asciz	equals;
Asciz	(Ljava/lang/Object;)Z;
NameAndType	equals:(Ljava/lang/Object;)Z
Method	java/lang/Object.equals:(Ljava/lang/Object;)Z
Asciz	scala/MatchError;
class	scala/MatchError
Asciz	toString;
Asciz	()Ljava/lang/String;;
NameAndType	toString:()Ljava/lang/String;
Method	java/lang/Object.toString:()Ljava/lang/String;
Asciz	(Ljava/lang/String;)V;
NameAndType	"<init>":(Ljava/lang/String;)V
Method	scala/MatchError."<init>":(Ljava/lang/String;)V
Asciz	scala/reflect/ClassManifest;
class	scala/reflect/ClassManifest
Asciz	arrayManifest;
Asciz	()Lscala/reflect/ClassManifest;;
NameAndType	arrayManifest:()Lscala/reflect/ClassManifest;
InterfaceMethod	scala/reflect/ClassManifest.arrayManifest:()Lscala/reflect/ClassManifest;
Asciz	arg;
Asciz	temp25;
Asciz	<T:Ljava/lang/Object;>(Lscala/reflect/OptManifest<*>;)Lscala/reflect/ClassManifest<[TT;>;;
Asciz	classType;
Asciz	(Lscala/reflect/OptManifest;Ljava/lang/Class;Lscala/collection/Seq;)Lscala/reflect/ClassManifest;;
Asciz	scala/reflect/ClassManifest$ClassTypeManifest;
class	scala/reflect/ClassManifest$ClassTypeManifest
Asciz	scala/Some;
class	scala/Some
Asciz	(Ljava/lang/Object;)V;
NameAndType	"<init>":(Ljava/lang/Object;)V
Method	scala/Some."<init>":(Ljava/lang/Object;)V
Asciz	scala/collection/TraversableLike;
class	scala/collection/TraversableLike
Asciz	toList;
Asciz	()Lscala/collection/immutable/List;;
NameAndType	toList:()Lscala/collection/immutable/List;
InterfaceMethod	scala/collection/TraversableLike.toList:()Lscala/collection/immutable/List;
Asciz	(Lscala/Option;Ljava/lang/Class;Lscala/collection/immutable/List;)V;
NameAndType	"<init>":(Lscala/Option;Ljava/lang/Class;Lscala/collection/immutable/List;)V
Method	scala/reflect/ClassManifest$ClassTypeManifest."<init>":(Lscala/Option;Ljava/lang/Class;Lscala/collection/immutable/List;)V
Asciz	prefix;
Asciz	clazz;
Asciz	args;
Asciz	<T:Ljava/lang/Object;>(Lscala/reflect/OptManifest<*>;Ljava/lang/Class<*>;Lscala/collection/Seq<Lscala/reflect/OptManifest<*>;>;)Lscala/reflect/ClassManifest<TT;>;;
Asciz	(Ljava/lang/Class;Lscala/reflect/OptManifest;Lscala/collection/Seq;)Lscala/reflect/ClassManifest;;
Asciz	scala/None$;
class	scala/None$
Asciz	Lscala/None$;;
NameAndType	MODULE$:Lscala/None$;
Field	scala/None$.MODULE$:Lscala/None$;
Asciz	scala/collection/immutable/List;
class	scala/collection/immutable/List
Asciz	$colon$colon;
Asciz	(Ljava/lang/Object;)Lscala/collection/immutable/List;;
NameAndType	$colon$colon:(Ljava/lang/Object;)Lscala/collection/immutable/List;
Method	scala/collection/immutable/List.$colon$colon:(Ljava/lang/Object;)Lscala/collection/immutable/List;
Asciz	arg1;
Asciz	<T:Ljava/lang/Object;>(Ljava/lang/Class<*>;Lscala/reflect/OptManifest<*>;Lscala/collection/Seq<Lscala/reflect/OptManifest<*>;>;)Lscala/reflect/ClassManifest<TT;>;;
Asciz	(Ljava/lang/Class;)Lscala/reflect/ClassManifest;;
Asciz	scala/collection/immutable/Nil$;
class	scala/collection/immutable/Nil$
Asciz	Lscala/collection/immutable/Nil$;;
NameAndType	MODULE$:Lscala/collection/immutable/Nil$;
Field	scala/collection/immutable/Nil$.MODULE$:Lscala/collection/immutable/Nil$;
Asciz	<T:Ljava/lang/Object;>(Ljava/lang/Class<*>;)Lscala/reflect/ClassManifest<TT;>;;
Asciz	singleType;
Asciz	(Ljava/lang/Object;)Lscala/reflect/Manifest;;
NameAndType	singleType:(Ljava/lang/Object;)Lscala/reflect/Manifest;
Method	scala/reflect/Manifest$.singleType:(Ljava/lang/Object;)Lscala/reflect/Manifest;
Asciz	value;
Asciz	Ljava/lang/Object;;
Asciz	<T:Ljava/lang/Object;>(Ljava/lang/Object;)Lscala/reflect/Manifest<TT;>;;
Asciz	fromClass;
Asciz	java/lang/Byte;
class	java/lang/Byte
Asciz	TYPE;
NameAndType	TYPE:Ljava/lang/Class;
Field	java/lang/Byte.TYPE:Ljava/lang/Class;
Asciz	java/lang/Class;
class	java/lang/Class
Method	java/lang/Class.toString:()Ljava/lang/String;
Asciz	java/lang/Short;
class	java/lang/Short
Field	java/lang/Short.TYPE:Ljava/lang/Class;
Asciz	java/lang/Character;
class	java/lang/Character
Field	java/lang/Character.TYPE:Ljava/lang/Class;
Asciz	java/lang/Integer;
class	java/lang/Integer
Field	java/lang/Integer.TYPE:Ljava/lang/Class;
Asciz	java/lang/Long;
class	java/lang/Long
Field	java/lang/Long.TYPE:Ljava/lang/Class;
Asciz	java/lang/Float;
class	java/lang/Float
Field	java/lang/Float.TYPE:Ljava/lang/Class;
Asciz	java/lang/Double;
class	java/lang/Double
Field	java/lang/Double.TYPE:Ljava/lang/Class;
Asciz	java/lang/Boolean;
class	java/lang/Boolean
Field	java/lang/Boolean.TYPE:Ljava/lang/Class;
Asciz	java/lang/Void;
class	java/lang/Void
Field	java/lang/Void.TYPE:Ljava/lang/Class;
Asciz	<T:Ljava/lang/Object;>(Ljava/lang/Class<TT;>;)Lscala/reflect/ClassManifest<TT;>;;
Asciz	()Lscala/reflect/Manifest<Lscala/runtime/Null$;>;;
Asciz	()Lscala/reflect/Manifest<Lscala/runtime/Nothing$;>;;
Asciz	()Lscala/reflect/Manifest<Ljava/lang/Object;>;;
Asciz	()Lscala/reflect/AnyValManifest<Ljava/lang/Object;>;;
Asciz	()Lscala/reflect/AnyValManifest<Ljava/lang/Boolean;>;;
Asciz	()Lscala/reflect/AnyValManifest<Ljava/lang/Double;>;;
Asciz	()Lscala/reflect/AnyValManifest<Ljava/lang/Float;>;;
Asciz	()Lscala/reflect/AnyValManifest<Ljava/lang/Long;>;;
Asciz	()Lscala/reflect/AnyValManifest<Ljava/lang/Integer;>;;
Asciz	()Lscala/reflect/AnyValManifest<Ljava/lang/Character;>;;
Asciz	()Lscala/reflect/AnyValManifest<Ljava/lang/Short;>;;
Asciz	()Lscala/reflect/AnyValManifest<Ljava/lang/Byte;>;;
Asciz	InnerClasses;
Asciz	$anon$1;
Asciz	$anon$2;
Asciz	$anon$3;
Asciz	ClassTypeManifest;
Asciz	scala/reflect/ClassManifest$$anonfun$subargs$1$1;
class	scala/reflect/ClassManifest$$anonfun$subargs$1$1
Asciz	$anonfun$subargs$1$1;
Asciz	scala/reflect/ClassManifest$$anonfun$subtype$1$1;
class	scala/reflect/ClassManifest$$anonfun$subtype$1$1
Asciz	$anonfun$subtype$1$1;
Asciz	scala/ScalaObject;
class	scala/ScalaObject

{
public static final scala.reflect.ClassManifest$ MODULE$;
  Signature: Lscala/reflect/ClassManifest$;

private final scala.reflect.Manifest Null;
  Signature: Lscala/reflect/Manifest;
  Signature: length = 0x2
   00 10 

private final scala.reflect.Manifest Nothing;
  Signature: Lscala/reflect/Manifest;
  Signature: length = 0x2
   00 13 

private final scala.reflect.Manifest AnyVal;
  Signature: Lscala/reflect/Manifest;
  Signature: length = 0x2
   00 15 

private final scala.reflect.Manifest Object;
  Signature: Lscala/reflect/Manifest;
  Signature: length = 0x2
   00 15 

private final scala.reflect.Manifest Any;
  Signature: Lscala/reflect/Manifest;
  Signature: length = 0x2
   00 15 

private final scala.reflect.AnyValManifest Unit;
  Signature: Lscala/reflect/AnyValManifest;
  Signature: length = 0x2
   00 1A 

private final scala.reflect.AnyValManifest Boolean;
  Signature: Lscala/reflect/AnyValManifest;
  Signature: length = 0x2
   00 1C 

private final scala.reflect.AnyValManifest Double;
  Signature: Lscala/reflect/AnyValManifest;
  Signature: length = 0x2
   00 1E 

private final scala.reflect.AnyValManifest Float;
  Signature: Lscala/reflect/AnyValManifest;
  Signature: length = 0x2
   00 20 

private final scala.reflect.AnyValManifest Long;
  Signature: Lscala/reflect/AnyValManifest;
  Signature: length = 0x2
   00 22 

private final scala.reflect.AnyValManifest Int;
  Signature: Lscala/reflect/AnyValManifest;
  Signature: length = 0x2
   00 24 

private final scala.reflect.AnyValManifest Char;
  Signature: Lscala/reflect/AnyValManifest;
  Signature: length = 0x2
   00 26 

private final scala.reflect.AnyValManifest Short;
  Signature: Lscala/reflect/AnyValManifest;
  Signature: length = 0x2
   00 28 

private final scala.reflect.AnyValManifest Byte;
  Signature: Lscala/reflect/AnyValManifest;
  Signature: length = 0x2
   00 2A 

public static {};
  Signature: ()V
  Code:
   Stack=1, Locals=0, Args_size=0
	new	class scala/reflect/ClassManifest$
	invokespecial	Method "<init>":()V
	return
  Labels:

private scala.reflect.ClassManifest$();
  Signature: ()V
  Code:
   Stack=2, Locals=1, Args_size=1
	aload_0
	invokespecial	Method java/lang/Object."<init>":()V
	aload_0
	putstatic	Field MODULE$:Lscala/reflect/ClassManifest$;
	aload_0
	getstatic	Field scala/reflect/Manifest$.MODULE$:Lscala/reflect/Manifest$;
	invokevirtual	Method scala/reflect/Manifest$.Byte:()Lscala/reflect/AnyValManifest;
	putfield	Field Byte:Lscala/reflect/AnyValManifest;
	aload_0
	getstatic	Field scala/reflect/Manifest$.MODULE$:Lscala/reflect/Manifest$;
	invokevirtual	Method scala/reflect/Manifest$.Short:()Lscala/reflect/AnyValManifest;
	putfield	Field Short:Lscala/reflect/AnyValManifest;
	aload_0
	getstatic	Field scala/reflect/Manifest$.MODULE$:Lscala/reflect/Manifest$;
	invokevirtual	Method scala/reflect/Manifest$.Char:()Lscala/reflect/AnyValManifest;
	putfield	Field Char:Lscala/reflect/AnyValManifest;
	aload_0
	getstatic	Field scala/reflect/Manifest$.MODULE$:Lscala/reflect/Manifest$;
	invokevirtual	Method scala/reflect/Manifest$.Int:()Lscala/reflect/AnyValManifest;
	putfield	Field Int:Lscala/reflect/AnyValManifest;
	aload_0
	getstatic	Field scala/reflect/Manifest$.MODULE$:Lscala/reflect/Manifest$;
	invokevirtual	Method scala/reflect/Manifest$.Long:()Lscala/reflect/AnyValManifest;
	putfield	Field Long:Lscala/reflect/AnyValManifest;
	aload_0
	getstatic	Field scala/reflect/Manifest$.MODULE$:Lscala/reflect/Manifest$;
	invokevirtual	Method scala/reflect/Manifest$.Float:()Lscala/reflect/AnyValManifest;
	putfield	Field Float:Lscala/reflect/AnyValManifest;
	aload_0
	getstatic	Field scala/reflect/Manifest$.MODULE$:Lscala/reflect/Manifest$;
	invokevirtual	Method scala/reflect/Manifest$.Double:()Lscala/reflect/AnyValManifest;
	putfield	Field Double:Lscala/reflect/AnyValManifest;
	aload_0
	getstatic	Field scala/reflect/Manifest$.MODULE$:Lscala/reflect/Manifest$;
	invokevirtual	Method scala/reflect/Manifest$.Boolean:()Lscala/reflect/AnyValManifest;
	putfield	Field Boolean:Lscala/reflect/AnyValManifest;
	aload_0
	getstatic	Field scala/reflect/Manifest$.MODULE$:Lscala/reflect/Manifest$;
	invokevirtual	Method scala/reflect/Manifest$.Unit:()Lscala/reflect/AnyValManifest;
	putfield	Field Unit:Lscala/reflect/AnyValManifest;
	aload_0
	getstatic	Field scala/reflect/Manifest$.MODULE$:Lscala/reflect/Manifest$;
	invokevirtual	Method scala/reflect/Manifest$.Any:()Lscala/reflect/Manifest;
	putfield	Field Any:Lscala/reflect/Manifest;
	aload_0
	getstatic	Field scala/reflect/Manifest$.MODULE$:Lscala/reflect/Manifest$;
	invokevirtual	Method scala/reflect/Manifest$.Object:()Lscala/reflect/Manifest;
	putfield	Field Object:Lscala/reflect/Manifest;
	aload_0
	getstatic	Field scala/reflect/Manifest$.MODULE$:Lscala/reflect/Manifest$;
	invokevirtual	Method scala/reflect/Manifest$.AnyVal:()Lscala/reflect/Manifest;
	putfield	Field AnyVal:Lscala/reflect/Manifest;
	aload_0
	getstatic	Field scala/reflect/Manifest$.MODULE$:Lscala/reflect/Manifest$;
	invokevirtual	Method scala/reflect/Manifest$.Nothing:()Lscala/reflect/Manifest;
	putfield	Field Nothing:Lscala/reflect/Manifest;
	aload_0
	getstatic	Field scala/reflect/Manifest$.MODULE$:Lscala/reflect/Manifest$;
	invokevirtual	Method scala/reflect/Manifest$.Null:()Lscala/reflect/Manifest;
	putfield	Field Null:Lscala/reflect/Manifest;
	return
  Labels:

public scala.reflect.ClassManifest intersectionType(scala.collection.Seq);
  Signature: (Lscala/collection/Seq;)Lscala/reflect/ClassManifest;
  Code:
   Stack=3, Locals=2, Args_size=2
	new	class scala/reflect/ClassManifest$$anon$3
	dup
	aload_1
	invokespecial	Method scala/reflect/ClassManifest$$anon$3."<init>":(Lscala/collection/Seq;)V
	areturn
  Labels:
  LocalVariableTable: 
   Start  Length  Slot  Name   Signature
   0      9      0    this       Lscala/reflect/ClassManifest$;
   0      9      1    parents$1       Lscala/collection/Seq;

  Signature: length = 0x2
   00 7B 

public scala.reflect.ClassManifest abstractType(scala.reflect.OptManifest, java.lang.String, scala.reflect.ClassManifest, scala.collection.Seq);
  Signature: (Lscala/reflect/OptManifest;Ljava/lang/String;Lscala/reflect/ClassManifest;Lscala/collection/Seq;)Lscala/reflect/ClassManifest;
  Code:
   Stack=6, Locals=5, Args_size=5
	new	class scala/reflect/ClassManifest$$anon$2
	dup
	aload_1
	aload_2
	aload_3
	aload	4
	invokespecial	Method scala/reflect/ClassManifest$$anon$2."<init>":(Lscala/reflect/OptManifest;Ljava/lang/String;Lscala/reflect/ClassManifest;Lscala/collection/Seq;)V
	areturn
  Labels:
  LocalVariableTable: 
   Start  Length  Slot  Name   Signature
   0      13      0    this       Lscala/reflect/ClassManifest$;
   0      13      1    prefix$2       Lscala/reflect/OptManifest;
   0      13      2    name$2       Ljava/lang/String;
   0      13      3    upperbound$1       Lscala/reflect/ClassManifest;
   0      13      4    args$2       Lscala/collection/Seq;

  Signature: length = 0x2
   00 FFFFFF8A 

public scala.reflect.ClassManifest abstractType(scala.reflect.OptManifest, java.lang.String, java.lang.Class, scala.collection.Seq);
  Signature: (Lscala/reflect/OptManifest;Ljava/lang/String;Ljava/lang/Class;Lscala/collection/Seq;)Lscala/reflect/ClassManifest;
  Code:
   Stack=6, Locals=5, Args_size=5
	new	class scala/reflect/ClassManifest$$anon$1
	dup
	aload_1
	aload_2
	aload_3
	aload	4
	invokespecial	Method scala/reflect/ClassManifest$$anon$1."<init>":(Lscala/reflect/OptManifest;Ljava/lang/String;Ljava/lang/Class;Lscala/collection/Seq;)V
	areturn
  Labels:
  LocalVariableTable: 
   Start  Length  Slot  Name   Signature
   0      13      0    this       Lscala/reflect/ClassManifest$;
   0      13      1    prefix$1       Lscala/reflect/OptManifest;
   0      13      2    name$1       Ljava/lang/String;
   0      13      3    clazz$1       Ljava/lang/Class;
   0      13      4    args$1       Lscala/collection/Seq;

  Signature: length = 0x2
   00 FFFFFF96 

public scala.reflect.ClassManifest arrayType(scala.reflect.OptManifest);
  Signature: (Lscala/reflect/OptManifest;)Lscala/reflect/ClassManifest;
  Code:
   Stack=3, Locals=3, Args_size=2
	getstatic	Field scala/reflect/NoManifest$.MODULE$:Lscala/reflect/NoManifest$;
	dup
	ifnonnull	l1 // aload_1
	pop
	aload_1
	ifnull	l2 // iconst_1
	goto	l3 // aload_1
l1	aload_1
	invokevirtual	Method java/lang/Object.equals:(Ljava/lang/Object;)Z
	ifeq	l3 // aload_1
l2	iconst_1
	ifeq	l4 // new
	aload_0
	getfield	Field Object:Lscala/reflect/Manifest;
	goto	l5 // areturn
l4	new	class scala/MatchError
	dup
	aload_1
	invokevirtual	Method java/lang/Object.toString:()Ljava/lang/String;
	invokespecial	Method scala/MatchError."<init>":(Ljava/lang/String;)V
	athrow
l3	aload_1
	instanceof	class scala/reflect/ClassManifest
	ifeq	l6 // new
	aload_1
	checkcast	class scala/reflect/ClassManifest
	astore_2
	iconst_1
	ifeq	l7 // new
	aload_2
	invokeinterface	InterfaceMethod scala/reflect/ClassManifest.arrayManifest:()Lscala/reflect/ClassManifest;
l5	areturn
l7	new	class scala/MatchError
	dup
	aload_1
	invokevirtual	Method java/lang/Object.toString:()Ljava/lang/String;
	invokespecial	Method scala/MatchError."<init>":(Ljava/lang/String;)V
	athrow
l6	new	class scala/MatchError
	dup
	aload_1
	invokevirtual	Method java/lang/Object.toString:()Ljava/lang/String;
	invokespecial	Method scala/MatchError."<init>":(Ljava/lang/String;)V
	athrow
  Labels:
   	l1 = 15 // aload_1
   	l2 = 22 // iconst_1
   	l4 = 33 // new
   	l3 = 45 // aload_1
   	l5 = 67 // areturn
   	l7 = 68 // new
   	l6 = 80 // new
  LocalVariableTable: 
   Start  Length  Slot  Name   Signature
   0      92      0    this       Lscala/reflect/ClassManifest$;
   0      92      1    arg       Lscala/reflect/OptManifest;
   57      10      2    temp25       Lscala/reflect/ClassManifest;
   68      12      2    temp25       Lscala/reflect/ClassManifest;

  Signature: length = 0x2
   00 FFFFFFB3 

public scala.reflect.ClassManifest classType(scala.reflect.OptManifest, java.lang.Class, scala.collection.Seq);
  Signature: (Lscala/reflect/OptManifest;Ljava/lang/Class;Lscala/collection/Seq;)Lscala/reflect/ClassManifest;
  Code:
   Stack=5, Locals=4, Args_size=4
	new	class scala/reflect/ClassManifest$ClassTypeManifest
	dup
	new	class scala/Some
	dup
	aload_1
	invokespecial	Method scala/Some."<init>":(Ljava/lang/Object;)V
	aload_2
	aload_3
	invokeinterface	InterfaceMethod scala/collection/TraversableLike.toList:()Lscala/collection/immutable/List;
	invokespecial	Method scala/reflect/ClassManifest$ClassTypeManifest."<init>":(Lscala/Option;Ljava/lang/Class;Lscala/collection/immutable/List;)V
	areturn
  Labels:
  LocalVariableTable: 
   Start  Length  Slot  Name   Signature
   0      23      0    this       Lscala/reflect/ClassManifest$;
   0      23      1    prefix       Lscala/reflect/OptManifest;
   0      23      2    clazz       Ljava/lang/Class;
   0      23      3    args       Lscala/collection/Seq;

  Signature: length = 0x2
   00 FFFFFFC9 

public scala.reflect.ClassManifest classType(java.lang.Class, scala.reflect.OptManifest, scala.collection.Seq);
  Signature: (Ljava/lang/Class;Lscala/reflect/OptManifest;Lscala/collection/Seq;)Lscala/reflect/ClassManifest;
  Code:
   Stack=6, Locals=4, Args_size=4
	new	class scala/reflect/ClassManifest$ClassTypeManifest
	dup
	getstatic	Field scala/None$.MODULE$:Lscala/None$;
	aload_1
	aload_3
	invokeinterface	InterfaceMethod scala/collection/TraversableLike.toList:()Lscala/collection/immutable/List;
	aload_2
	invokevirtual	Method scala/collection/immutable/List.$colon$colon:(Ljava/lang/Object;)Lscala/collection/immutable/List;
	invokespecial	Method scala/reflect/ClassManifest$ClassTypeManifest."<init>":(Lscala/Option;Ljava/lang/Class;Lscala/collection/immutable/List;)V
	areturn
  Labels:
  LocalVariableTable: 
   Start  Length  Slot  Name   Signature
   0      22      0    this       Lscala/reflect/ClassManifest$;
   0      22      1    clazz       Ljava/lang/Class;
   0      22      2    arg1       Lscala/reflect/OptManifest;
   0      22      3    args       Lscala/collection/Seq;

  Signature: length = 0x2
   00 FFFFFFD7 

public scala.reflect.ClassManifest classType(java.lang.Class);
  Signature: (Ljava/lang/Class;)Lscala/reflect/ClassManifest;
  Code:
   Stack=5, Locals=2, Args_size=2
	new	class scala/reflect/ClassManifest$ClassTypeManifest
	dup
	getstatic	Field scala/None$.MODULE$:Lscala/None$;
	aload_1
	getstatic	Field scala/collection/immutable/Nil$.MODULE$:Lscala/collection/immutable/Nil$;
	invokespecial	Method scala/reflect/ClassManifest$ClassTypeManifest."<init>":(Lscala/Option;Ljava/lang/Class;Lscala/collection/immutable/List;)V
	areturn
  Labels:
  LocalVariableTable: 
   Start  Length  Slot  Name   Signature
   0      15      0    this       Lscala/reflect/ClassManifest$;
   0      15      1    clazz       Ljava/lang/Class;

  Signature: length = 0x2
   00 FFFFFFDE 

public scala.reflect.Manifest singleType(java.lang.Object);
  Signature: (Ljava/lang/Object;)Lscala/reflect/Manifest;
  Code:
   Stack=2, Locals=2, Args_size=2
	getstatic	Field scala/reflect/Manifest$.MODULE$:Lscala/reflect/Manifest$;
	aload_1
	invokevirtual	Method scala/reflect/Manifest$.singleType:(Ljava/lang/Object;)Lscala/reflect/Manifest;
	areturn
  Labels:
  LocalVariableTable: 
   Start  Length  Slot  Name   Signature
   0      8      0    this       Lscala/reflect/ClassManifest$;
   0      8      1    value       Ljava/lang/Object;

  Signature: length = 0x2
   00 FFFFFFE5 

public scala.reflect.ClassManifest fromClass(java.lang.Class);
  Signature: (Ljava/lang/Class;)Lscala/reflect/ClassManifest;
  Code:
   Stack=5, Locals=2, Args_size=2
	getstatic	Field java/lang/Byte.TYPE:Ljava/lang/Class;
	dup
	ifnonnull	l1 // aload_1
	pop
	aload_1
	ifnull	l2 // iconst_1
	goto	l3 // getstatic
l1	aload_1
	invokevirtual	Method java/lang/Object.equals:(Ljava/lang/Object;)Z
	ifeq	l3 // getstatic
l2	iconst_1
	ifeq	l4 // new
	aload_0
	getfield	Field Byte:Lscala/reflect/AnyValManifest;
	goto	l5 // areturn
l4	new	class scala/MatchError
	dup
	aload_1
	invokevirtual	Method java/lang/Class.toString:()Ljava/lang/String;
	invokespecial	Method scala/MatchError."<init>":(Ljava/lang/String;)V
	athrow
l3	getstatic	Field java/lang/Short.TYPE:Ljava/lang/Class;
	dup
	ifnonnull	l6 // aload_1
	pop
	aload_1
	ifnull	l7 // iconst_1
	goto	l8 // getstatic
l6	aload_1
	invokevirtual	Method java/lang/Object.equals:(Ljava/lang/Object;)Z
	ifeq	l8 // getstatic
l7	iconst_1
	ifeq	l9 // new
	aload_0
	getfield	Field Short:Lscala/reflect/AnyValManifest;
	goto	l5 // areturn
l9	new	class scala/MatchError
	dup
	aload_1
	invokevirtual	Method java/lang/Class.toString:()Ljava/lang/String;
	invokespecial	Method scala/MatchError."<init>":(Ljava/lang/String;)V
	athrow
l8	getstatic	Field java/lang/Character.TYPE:Ljava/lang/Class;
	dup
	ifnonnull	l10 // aload_1
	pop
	aload_1
	ifnull	l11 // iconst_1
	goto	l12 // getstatic
l10	aload_1
	invokevirtual	Method java/lang/Object.equals:(Ljava/lang/Object;)Z
	ifeq	l12 // getstatic
l11	iconst_1
	ifeq	l13 // new
	aload_0
	getfield	Field Char:Lscala/reflect/AnyValManifest;
	goto	l5 // areturn
l13	new	class scala/MatchError
	dup
	aload_1
	invokevirtual	Method java/lang/Class.toString:()Ljava/lang/String;
	invokespecial	Method scala/MatchError."<init>":(Ljava/lang/String;)V
	athrow
l12	getstatic	Field java/lang/Integer.TYPE:Ljava/lang/Class;
	dup
	ifnonnull	l14 // aload_1
	pop
	aload_1
	ifnull	l15 // iconst_1
	goto	l16 // getstatic
l14	aload_1
	invokevirtual	Method java/lang/Object.equals:(Ljava/lang/Object;)Z
	ifeq	l16 // getstatic
l15	iconst_1
	ifeq	l17 // new
	aload_0
	getfield	Field Int:Lscala/reflect/AnyValManifest;
	goto	l5 // areturn
l17	new	class scala/MatchError
	dup
	aload_1
	invokevirtual	Method java/lang/Class.toString:()Ljava/lang/String;
	invokespecial	Method scala/MatchError."<init>":(Ljava/lang/String;)V
	athrow
l16	getstatic	Field java/lang/Long.TYPE:Ljava/lang/Class;
	dup
	ifnonnull	l18 // aload_1
	pop
	aload_1
	ifnull	l19 // iconst_1
	goto	l20 // getstatic
l18	aload_1
	invokevirtual	Method java/lang/Object.equals:(Ljava/lang/Object;)Z
	ifeq	l20 // getstatic
l19	iconst_1
	ifeq	l21 // new
	aload_0
	getfield	Field Long:Lscala/reflect/AnyValManifest;
	goto	l5 // areturn
l21	new	class scala/MatchError
	dup
	aload_1
	invokevirtual	Method java/lang/Class.toString:()Ljava/lang/String;
	invokespecial	Method scala/MatchError."<init>":(Ljava/lang/String;)V
	athrow
l20	getstatic	Field java/lang/Float.TYPE:Ljava/lang/Class;
	dup
	ifnonnull	l22 // aload_1
	pop
	aload_1
	ifnull	l23 // iconst_1
	goto	l24 // getstatic
l22	aload_1
	invokevirtual	Method java/lang/Object.equals:(Ljava/lang/Object;)Z
	ifeq	l24 // getstatic
l23	iconst_1
	ifeq	l25 // new
	aload_0
	getfield	Field Float:Lscala/reflect/AnyValManifest;
	goto	l5 // areturn
l25	new	class scala/MatchError
	dup
	aload_1
	invokevirtual	Method java/lang/Class.toString:()Ljava/lang/String;
	invokespecial	Method scala/MatchError."<init>":(Ljava/lang/String;)V
	athrow
l24	getstatic	Field java/lang/Double.TYPE:Ljava/lang/Class;
	dup
	ifnonnull	l26 // aload_1
	pop
	aload_1
	ifnull	l27 // iconst_1
	goto	l28 // getstatic
l26	aload_1
	invokevirtual	Method java/lang/Object.equals:(Ljava/lang/Object;)Z
	ifeq	l28 // getstatic
l27	iconst_1
	ifeq	l29 // new
	aload_0
	getfield	Field Double:Lscala/reflect/AnyValManifest;
	goto	l5 // areturn
l29	new	class scala/MatchError
	dup
	aload_1
	invokevirtual	Method java/lang/Class.toString:()Ljava/lang/String;
	invokespecial	Method scala/MatchError."<init>":(Ljava/lang/String;)V
	athrow
l28	getstatic	Field java/lang/Boolean.TYPE:Ljava/lang/Class;
	dup
	ifnonnull	l30 // aload_1
	pop
	aload_1
	ifnull	l31 // iconst_1
	goto	l32 // getstatic
l30	aload_1
	invokevirtual	Method java/lang/Object.equals:(Ljava/lang/Object;)Z
	ifeq	l32 // getstatic
l31	iconst_1
	ifeq	l33 // new
	aload_0
	getfield	Field Boolean:Lscala/reflect/AnyValManifest;
	goto	l5 // areturn
l33	new	class scala/MatchError
	dup
	aload_1
	invokevirtual	Method java/lang/Class.toString:()Ljava/lang/String;
	invokespecial	Method scala/MatchError."<init>":(Ljava/lang/String;)V
	athrow
l32	getstatic	Field java/lang/Void.TYPE:Ljava/lang/Class;
	dup
	ifnonnull	l34 // aload_1
	pop
	aload_1
	ifnull	l35 // iconst_1
	goto	l36 // iconst_1
l34	aload_1
	invokevirtual	Method java/lang/Object.equals:(Ljava/lang/Object;)Z
	ifeq	l36 // iconst_1
l35	iconst_1
	ifeq	l37 // new
	aload_0
	getfield	Field Unit:Lscala/reflect/AnyValManifest;
	goto	l5 // areturn
l37	new	class scala/MatchError
	dup
	aload_1
	invokevirtual	Method java/lang/Class.toString:()Ljava/lang/String;
	invokespecial	Method scala/MatchError."<init>":(Ljava/lang/String;)V
	athrow
l36	iconst_1
	ifeq	l38 // new
	new	class scala/reflect/ClassManifest$ClassTypeManifest
	dup
	getstatic	Field scala/None$.MODULE$:Lscala/None$;
	aload_1
	getstatic	Field scala/collection/immutable/Nil$.MODULE$:Lscala/collection/immutable/Nil$;
	invokespecial	Method scala/reflect/ClassManifest$ClassTypeManifest."<init>":(Lscala/Option;Ljava/lang/Class;Lscala/collection/immutable/List;)V
l5	areturn
l38	new	class scala/MatchError
	dup
	aload_1
	invokevirtual	Method java/lang/Class.toString:()Ljava/lang/String;
	invokespecial	Method scala/MatchError."<init>":(Ljava/lang/String;)V
	athrow
  Labels:
   	l1 = 15 // aload_1
   	l2 = 22 // iconst_1
   	l4 = 33 // new
   	l3 = 45 // getstatic
   	l6 = 60 // aload_1
   	l7 = 67 // iconst_1
   	l9 = 78 // new
   	l8 = 90 // getstatic
   	l10 = 105 // aload_1
   	l11 = 112 // iconst_1
   	l13 = 123 // new
   	l12 = 135 // getstatic
   	l14 = 150 // aload_1
   	l15 = 157 // iconst_1
   	l17 = 168 // new
   	l16 = 180 // getstatic
   	l18 = 195 // aload_1
   	l19 = 202 // iconst_1
   	l21 = 213 // new
   	l20 = 225 // getstatic
   	l22 = 240 // aload_1
   	l23 = 247 // iconst_1
   	l25 = 258 // new
   	l24 = 270 // getstatic
   	l26 = 285 // aload_1
   	l27 = 292 // iconst_1
   	l29 = 303 // new
   	l28 = 315 // getstatic
   	l30 = 330 // aload_1
   	l31 = 337 // iconst_1
   	l33 = 348 // new
   	l32 = 360 // getstatic
   	l34 = 375 // aload_1
   	l35 = 382 // iconst_1
   	l37 = 393 // new
   	l36 = 405 // iconst_1
   	l5 = 423 // areturn
   	l38 = 424 // new
  LocalVariableTable: 
   Start  Length  Slot  Name   Signature
   0      436      0    this       Lscala/reflect/ClassManifest$;
   0      436      1    clazz       Ljava/lang/Class;

  Signature: length = 0x2
   01 07 

public scala.reflect.Manifest Null();
  Signature: ()Lscala/reflect/Manifest;
  Code:
   Stack=1, Locals=1, Args_size=1
	aload_0
	getfield	Field Null:Lscala/reflect/Manifest;
	areturn
  Labels:
  Signature: length = 0x2
   01 08 

public scala.reflect.Manifest Nothing();
  Signature: ()Lscala/reflect/Manifest;
  Code:
   Stack=1, Locals=1, Args_size=1
	aload_0
	getfield	Field Nothing:Lscala/reflect/Manifest;
	areturn
  Labels:
  Signature: length = 0x2
   01 09 

public scala.reflect.Manifest AnyVal();
  Signature: ()Lscala/reflect/Manifest;
  Code:
   Stack=1, Locals=1, Args_size=1
	aload_0
	getfield	Field AnyVal:Lscala/reflect/Manifest;
	areturn
  Labels:
  Signature: length = 0x2
   01 0A 

public scala.reflect.Manifest Object();
  Signature: ()Lscala/reflect/Manifest;
  Code:
   Stack=1, Locals=1, Args_size=1
	aload_0
	getfield	Field Object:Lscala/reflect/Manifest;
	areturn
  Labels:
  Signature: length = 0x2
   01 0A 

public scala.reflect.Manifest Any();
  Signature: ()Lscala/reflect/Manifest;
  Code:
   Stack=1, Locals=1, Args_size=1
	aload_0
	getfield	Field Any:Lscala/reflect/Manifest;
	areturn
  Labels:
  Signature: length = 0x2
   01 0A 

public scala.reflect.AnyValManifest Unit();
  Signature: ()Lscala/reflect/AnyValManifest;
  Code:
   Stack=1, Locals=1, Args_size=1
	aload_0
	getfield	Field Unit:Lscala/reflect/AnyValManifest;
	areturn
  Labels:
  Signature: length = 0x2
   01 0B 

public scala.reflect.AnyValManifest Boolean();
  Signature: ()Lscala/reflect/AnyValManifest;
  Code:
   Stack=1, Locals=1, Args_size=1
	aload_0
	getfield	Field Boolean:Lscala/reflect/AnyValManifest;
	areturn
  Labels:
  Signature: length = 0x2
   01 0C 

public scala.reflect.AnyValManifest Double();
  Signature: ()Lscala/reflect/AnyValManifest;
  Code:
   Stack=1, Locals=1, Args_size=1
	aload_0
	getfield	Field Double:Lscala/reflect/AnyValManifest;
	areturn
  Labels:
  Signature: length = 0x2
   01 0D 

public scala.reflect.AnyValManifest Float();
  Signature: ()Lscala/reflect/AnyValManifest;
  Code:
   Stack=1, Locals=1, Args_size=1
	aload_0
	getfield	Field Float:Lscala/reflect/AnyValManifest;
	areturn
  Labels:
  Signature: length = 0x2
   01 0E 

public scala.reflect.AnyValManifest Long();
  Signature: ()Lscala/reflect/AnyValManifest;
  Code:
   Stack=1, Locals=1, Args_size=1
	aload_0
	getfield	Field Long:Lscala/reflect/AnyValManifest;
	areturn
  Labels:
  Signature: length = 0x2
   01 0F 

public scala.reflect.AnyValManifest Int();
  Signature: ()Lscala/reflect/AnyValManifest;
  Code:
   Stack=1, Locals=1, Args_size=1
	aload_0
	getfield	Field Int:Lscala/reflect/AnyValManifest;
	areturn
  Labels:
  Signature: length = 0x2
   01 10 

public scala.reflect.AnyValManifest Char();
  Signature: ()Lscala/reflect/AnyValManifest;
  Code:
   Stack=1, Locals=1, Args_size=1
	aload_0
	getfield	Field Char:Lscala/reflect/AnyValManifest;
	areturn
  Labels:
  Signature: length = 0x2
   01 11 

public scala.reflect.AnyValManifest Short();
  Signature: ()Lscala/reflect/AnyValManifest;
  Code:
   Stack=1, Locals=1, Args_size=1
	aload_0
	getfield	Field Short:Lscala/reflect/AnyValManifest;
	areturn
  Labels:
  Signature: length = 0x2
   01 12 

public scala.reflect.AnyValManifest Byte();
  Signature: ()Lscala/reflect/AnyValManifest;
  Code:
   Stack=1, Locals=1, Args_size=1
	aload_0
	getfield	Field Byte:Lscala/reflect/AnyValManifest;
	areturn
  Labels:
  Signature: length = 0x2
   01 13 

}

