Compiled from "ClassManifest.scala"
public final class scala.reflect.ClassManifest$$anon$2 extends java.lang.Object implements scala.reflect.ClassManifest
  SourceFile: "ClassManifest.scala"
  Scala: length = 0x
   
  Signature: length = 0x2
   00 FFFFFF95 
  InnerClass: 
   public final $anon$2=class scala/reflect/ClassManifest$$anon$2 of class scala/reflect/ClassManifest
  minor version: 0
  major version: 49
  Constant pool:
Asciz	SourceFile;
Asciz	ClassManifest.scala;
Asciz	typeArguments;
Asciz	Lscala/collection/immutable/List;;
Asciz	Lscala/collection/immutable/List<Lscala/reflect/OptManifest<*>;>;;
Asciz	Signature;
Asciz	prefix$2;
Asciz	Lscala/reflect/OptManifest;;
Asciz	name$2;
Asciz	Ljava/lang/String;;
Asciz	upperbound$1;
Asciz	Lscala/reflect/ClassManifest;;
Asciz	$less$colon$less;
Asciz	(Lscala/reflect/ClassManifest;)Z;
Asciz	Code;
Asciz	LineNumberTable;
Asciz	scala/reflect/ClassManifest$class;
class	scala/reflect/ClassManifest$class
Asciz	(Lscala/reflect/ClassManifest;Lscala/reflect/ClassManifest;)Z;
NameAndType	$less$colon$less:(Lscala/reflect/ClassManifest;Lscala/reflect/ClassManifest;)Z
Method	scala/reflect/ClassManifest$class.$less$colon$less:(Lscala/reflect/ClassManifest;Lscala/reflect/ClassManifest;)Z
Asciz	this;
Asciz	Lscala/reflect/ClassManifest$$anon$2;;
Asciz	that;
Asciz	LocalVariableTable;
Asciz	$greater$colon$greater;
NameAndType	$greater$colon$greater:(Lscala/reflect/ClassManifest;Lscala/reflect/ClassManifest;)Z
Method	scala/reflect/ClassManifest$class.$greater$colon$greater:(Lscala/reflect/ClassManifest;Lscala/reflect/ClassManifest;)Z
Asciz	canEqual;
Asciz	(Ljava/lang/Object;)Z;
Asciz	(Lscala/reflect/ClassManifest;Ljava/lang/Object;)Z;
NameAndType	canEqual:(Lscala/reflect/ClassManifest;Ljava/lang/Object;)Z
Method	scala/reflect/ClassManifest$class.canEqual:(Lscala/reflect/ClassManifest;Ljava/lang/Object;)Z
Asciz	other;
Asciz	Ljava/lang/Object;;
Asciz	equals;
NameAndType	equals:(Lscala/reflect/ClassManifest;Ljava/lang/Object;)Z
Method	scala/reflect/ClassManifest$class.equals:(Lscala/reflect/ClassManifest;Ljava/lang/Object;)Z
Asciz	hashCode;
Asciz	()I;
Asciz	(Lscala/reflect/ClassManifest;)I;
NameAndType	hashCode:(Lscala/reflect/ClassManifest;)I
Method	scala/reflect/ClassManifest$class.hashCode:(Lscala/reflect/ClassManifest;)I
Asciz	arrayClass;
Asciz	(Ljava/lang/Class;)Ljava/lang/Class;;
Asciz	(Lscala/reflect/ClassManifest;Ljava/lang/Class;)Ljava/lang/Class;;
NameAndType	arrayClass:(Lscala/reflect/ClassManifest;Ljava/lang/Class;)Ljava/lang/Class;
Method	scala/reflect/ClassManifest$class.arrayClass:(Lscala/reflect/ClassManifest;Ljava/lang/Class;)Ljava/lang/Class;
Asciz	tp;
Asciz	Ljava/lang/Class;;
Asciz	arrayManifest;
Asciz	()Lscala/reflect/ClassManifest;;
Asciz	(Lscala/reflect/ClassManifest;)Lscala/reflect/ClassManifest;;
NameAndType	arrayManifest:(Lscala/reflect/ClassManifest;)Lscala/reflect/ClassManifest;
Method	scala/reflect/ClassManifest$class.arrayManifest:(Lscala/reflect/ClassManifest;)Lscala/reflect/ClassManifest;
Asciz	newArray;
Asciz	(I)Ljava/lang/Object;;
Asciz	(Lscala/reflect/ClassManifest;I)Ljava/lang/Object;;
NameAndType	newArray:(Lscala/reflect/ClassManifest;I)Ljava/lang/Object;
Method	scala/reflect/ClassManifest$class.newArray:(Lscala/reflect/ClassManifest;I)Ljava/lang/Object;
Asciz	len;
Asciz	I;
Asciz	newArray2;
Asciz	(I)[Ljava/lang/Object;;
Asciz	(Lscala/reflect/ClassManifest;I)[Ljava/lang/Object;;
NameAndType	newArray2:(Lscala/reflect/ClassManifest;I)[Ljava/lang/Object;
Method	scala/reflect/ClassManifest$class.newArray2:(Lscala/reflect/ClassManifest;I)[Ljava/lang/Object;
Asciz	newArray3;
Asciz	(I)[[Ljava/lang/Object;;
Asciz	(Lscala/reflect/ClassManifest;I)[[Ljava/lang/Object;;
NameAndType	newArray3:(Lscala/reflect/ClassManifest;I)[[Ljava/lang/Object;
Method	scala/reflect/ClassManifest$class.newArray3:(Lscala/reflect/ClassManifest;I)[[Ljava/lang/Object;
Asciz	newArray4;
Asciz	(I)[[[Ljava/lang/Object;;
Asciz	(Lscala/reflect/ClassManifest;I)[[[Ljava/lang/Object;;
NameAndType	newArray4:(Lscala/reflect/ClassManifest;I)[[[Ljava/lang/Object;
Method	scala/reflect/ClassManifest$class.newArray4:(Lscala/reflect/ClassManifest;I)[[[Ljava/lang/Object;
Asciz	newArray5;
Asciz	(I)[[[[Ljava/lang/Object;;
Asciz	(Lscala/reflect/ClassManifest;I)[[[[Ljava/lang/Object;;
NameAndType	newArray5:(Lscala/reflect/ClassManifest;I)[[[[Ljava/lang/Object;
Method	scala/reflect/ClassManifest$class.newArray5:(Lscala/reflect/ClassManifest;I)[[[[Ljava/lang/Object;
Asciz	newWrappedArray;
Asciz	(I)Lscala/collection/mutable/WrappedArray;;
Asciz	(Lscala/reflect/ClassManifest;I)Lscala/collection/mutable/WrappedArray;;
NameAndType	newWrappedArray:(Lscala/reflect/ClassManifest;I)Lscala/collection/mutable/WrappedArray;
Method	scala/reflect/ClassManifest$class.newWrappedArray:(Lscala/reflect/ClassManifest;I)Lscala/collection/mutable/WrappedArray;
Asciz	newArrayBuilder;
Asciz	()Lscala/collection/mutable/ArrayBuilder;;
Asciz	(Lscala/reflect/ClassManifest;)Lscala/collection/mutable/ArrayBuilder;;
NameAndType	newArrayBuilder:(Lscala/reflect/ClassManifest;)Lscala/collection/mutable/ArrayBuilder;
Method	scala/reflect/ClassManifest$class.newArrayBuilder:(Lscala/reflect/ClassManifest;)Lscala/collection/mutable/ArrayBuilder;
Asciz	argString;
Asciz	()Ljava/lang/String;;
Asciz	(Lscala/reflect/ClassManifest;)Ljava/lang/String;;
NameAndType	argString:(Lscala/reflect/ClassManifest;)Ljava/lang/String;
Method	scala/reflect/ClassManifest$class.argString:(Lscala/reflect/ClassManifest;)Ljava/lang/String;
Asciz	erasure;
Asciz	()Ljava/lang/Class;;
Asciz	scala/reflect/ClassManifest$$anon$2;
class	scala/reflect/ClassManifest$$anon$2
NameAndType	upperbound$1:Lscala/reflect/ClassManifest;
Field	scala/reflect/ClassManifest$$anon$2.upperbound$1:Lscala/reflect/ClassManifest;
Asciz	scala/reflect/ClassManifest;
class	scala/reflect/ClassManifest
NameAndType	erasure:()Ljava/lang/Class;
InterfaceMethod	scala/reflect/ClassManifest.erasure:()Ljava/lang/Class;
Asciz	()Ljava/lang/Class<*>;;
Asciz	()Lscala/collection/immutable/List;;
NameAndType	typeArguments:Lscala/collection/immutable/List;
Field	scala/reflect/ClassManifest$$anon$2.typeArguments:Lscala/collection/immutable/List;
Asciz	()Lscala/collection/immutable/List<Lscala/reflect/OptManifest<*>;>;;
Asciz	toString;
Asciz	scala/collection/mutable/StringBuilder;
class	scala/collection/mutable/StringBuilder
Asciz	<init>;
Asciz	()V;
NameAndType	"<init>":()V
Method	scala/collection/mutable/StringBuilder."<init>":()V
NameAndType	prefix$2:Lscala/reflect/OptManifest;
Field	scala/reflect/ClassManifest$$anon$2.prefix$2:Lscala/reflect/OptManifest;
Asciz	java/lang/Object;
class	java/lang/Object
NameAndType	toString:()Ljava/lang/String;
Method	java/lang/Object.toString:()Ljava/lang/String;
Asciz	append;
Asciz	(Ljava/lang/Object;)Lscala/collection/mutable/StringBuilder;;
NameAndType	append:(Ljava/lang/Object;)Lscala/collection/mutable/StringBuilder;
Method	scala/collection/mutable/StringBuilder.append:(Ljava/lang/Object;)Lscala/collection/mutable/StringBuilder;
Asciz	#;
String	#
NameAndType	name$2:Ljava/lang/String;
Field	scala/reflect/ClassManifest$$anon$2.name$2:Ljava/lang/String;
NameAndType	argString:()Ljava/lang/String;
InterfaceMethod	scala/reflect/ClassManifest.argString:()Ljava/lang/String;
Method	scala/collection/mutable/StringBuilder.toString:()Ljava/lang/String;
Asciz	(Lscala/reflect/OptManifest;Ljava/lang/String;Lscala/reflect/ClassManifest;Lscala/collection/Seq;)V;
Method	java/lang/Object."<init>":()V
Asciz	$init$;
Asciz	(Lscala/reflect/ClassManifest;)V;
NameAndType	$init$:(Lscala/reflect/ClassManifest;)V
Method	scala/reflect/ClassManifest$class.$init$:(Lscala/reflect/ClassManifest;)V
Asciz	scala/collection/TraversableOnce;
class	scala/collection/TraversableOnce
Asciz	toList;
NameAndType	toList:()Lscala/collection/immutable/List;
InterfaceMethod	scala/collection/TraversableOnce.toList:()Lscala/collection/immutable/List;
Asciz	Scala;
Asciz	Ljava/lang/Object;Lscala/reflect/ClassManifest<TT;>;;
Asciz	InnerClasses;
Asciz	$anon$2;

{
private final scala.collection.immutable.List typeArguments;
  Signature: Lscala/collection/immutable/List;
  Signature: length = 0x2
   00 05 

private final scala.reflect.OptManifest prefix$2;
  Signature: Lscala/reflect/OptManifest;

private final java.lang.String name$2;
  Signature: Ljava/lang/String;

private final scala.reflect.ClassManifest upperbound$1;
  Signature: Lscala/reflect/ClassManifest;

public boolean $less$colon$less(scala.reflect.ClassManifest);
  Signature: (Lscala/reflect/ClassManifest;)Z
  Code:
   Stack=2, Locals=2, Args_size=2
	aload_0
	aload_1
	invokestatic	Method scala/reflect/ClassManifest$class.$less$colon$less:(Lscala/reflect/ClassManifest;Lscala/reflect/ClassManifest;)Z
	ireturn
  Labels:
  LocalVariableTable: 
   Start  Length  Slot  Name   Signature
   0      6      0    this       Lscala/reflect/ClassManifest$$anon$2;
   0      6      1    that       Lscala/reflect/ClassManifest;


public boolean $greater$colon$greater(scala.reflect.ClassManifest);
  Signature: (Lscala/reflect/ClassManifest;)Z
  Code:
   Stack=2, Locals=2, Args_size=2
	aload_0
	aload_1
	invokestatic	Method scala/reflect/ClassManifest$class.$greater$colon$greater:(Lscala/reflect/ClassManifest;Lscala/reflect/ClassManifest;)Z
	ireturn
  Labels:
  LocalVariableTable: 
   Start  Length  Slot  Name   Signature
   0      6      0    this       Lscala/reflect/ClassManifest$$anon$2;
   0      6      1    that       Lscala/reflect/ClassManifest;


public boolean canEqual(java.lang.Object);
  Signature: (Ljava/lang/Object;)Z
  Code:
   Stack=2, Locals=2, Args_size=2
	aload_0
	aload_1
	invokestatic	Method scala/reflect/ClassManifest$class.canEqual:(Lscala/reflect/ClassManifest;Ljava/lang/Object;)Z
	ireturn
  Labels:
  LocalVariableTable: 
   Start  Length  Slot  Name   Signature
   0      6      0    this       Lscala/reflect/ClassManifest$$anon$2;
   0      6      1    other       Ljava/lang/Object;


public boolean equals(java.lang.Object);
  Signature: (Ljava/lang/Object;)Z
  Code:
   Stack=2, Locals=2, Args_size=2
	aload_0
	aload_1
	invokestatic	Method scala/reflect/ClassManifest$class.equals:(Lscala/reflect/ClassManifest;Ljava/lang/Object;)Z
	ireturn
  Labels:
  LocalVariableTable: 
   Start  Length  Slot  Name   Signature
   0      6      0    this       Lscala/reflect/ClassManifest$$anon$2;
   0      6      1    that       Ljava/lang/Object;


public int hashCode();
  Signature: ()I
  Code:
   Stack=1, Locals=1, Args_size=1
	aload_0
	invokestatic	Method scala/reflect/ClassManifest$class.hashCode:(Lscala/reflect/ClassManifest;)I
	ireturn
  Labels:

public java.lang.Class arrayClass(java.lang.Class);
  Signature: (Ljava/lang/Class;)Ljava/lang/Class;
  Code:
   Stack=2, Locals=2, Args_size=2
	aload_0
	aload_1
	invokestatic	Method scala/reflect/ClassManifest$class.arrayClass:(Lscala/reflect/ClassManifest;Ljava/lang/Class;)Ljava/lang/Class;
	areturn
  Labels:
  LocalVariableTable: 
   Start  Length  Slot  Name   Signature
   0      6      0    this       Lscala/reflect/ClassManifest$$anon$2;
   0      6      1    tp       Ljava/lang/Class;


public scala.reflect.ClassManifest arrayManifest();
  Signature: ()Lscala/reflect/ClassManifest;
  Code:
   Stack=1, Locals=1, Args_size=1
	aload_0
	invokestatic	Method scala/reflect/ClassManifest$class.arrayManifest:(Lscala/reflect/ClassManifest;)Lscala/reflect/ClassManifest;
	areturn
  Labels:

public java.lang.Object newArray(int);
  Signature: (I)Ljava/lang/Object;
  Code:
   Stack=2, Locals=2, Args_size=2
	aload_0
	iload_1
	invokestatic	Method scala/reflect/ClassManifest$class.newArray:(Lscala/reflect/ClassManifest;I)Ljava/lang/Object;
	areturn
  Labels:
  LocalVariableTable: 
   Start  Length  Slot  Name   Signature
   0      6      0    this       Lscala/reflect/ClassManifest$$anon$2;
   0      6      1    len       I


public java.lang.Object[] newArray2(int);
  Signature: (I)[Ljava/lang/Object;
  Code:
   Stack=2, Locals=2, Args_size=2
	aload_0
	iload_1
	invokestatic	Method scala/reflect/ClassManifest$class.newArray2:(Lscala/reflect/ClassManifest;I)[Ljava/lang/Object;
	areturn
  Labels:
  LocalVariableTable: 
   Start  Length  Slot  Name   Signature
   0      6      0    this       Lscala/reflect/ClassManifest$$anon$2;
   0      6      1    len       I


public java.lang.Object[][] newArray3(int);
  Signature: (I)[[Ljava/lang/Object;
  Code:
   Stack=2, Locals=2, Args_size=2
	aload_0
	iload_1
	invokestatic	Method scala/reflect/ClassManifest$class.newArray3:(Lscala/reflect/ClassManifest;I)[[Ljava/lang/Object;
	areturn
  Labels:
  LocalVariableTable: 
   Start  Length  Slot  Name   Signature
   0      6      0    this       Lscala/reflect/ClassManifest$$anon$2;
   0      6      1    len       I


public java.lang.Object[][][] newArray4(int);
  Signature: (I)[[[Ljava/lang/Object;
  Code:
   Stack=2, Locals=2, Args_size=2
	aload_0
	iload_1
	invokestatic	Method scala/reflect/ClassManifest$class.newArray4:(Lscala/reflect/ClassManifest;I)[[[Ljava/lang/Object;
	areturn
  Labels:
  LocalVariableTable: 
   Start  Length  Slot  Name   Signature
   0      6      0    this       Lscala/reflect/ClassManifest$$anon$2;
   0      6      1    len       I


public java.lang.Object[][][][] newArray5(int);
  Signature: (I)[[[[Ljava/lang/Object;
  Code:
   Stack=2, Locals=2, Args_size=2
	aload_0
	iload_1
	invokestatic	Method scala/reflect/ClassManifest$class.newArray5:(Lscala/reflect/ClassManifest;I)[[[[Ljava/lang/Object;
	areturn
  Labels:
  LocalVariableTable: 
   Start  Length  Slot  Name   Signature
   0      6      0    this       Lscala/reflect/ClassManifest$$anon$2;
   0      6      1    len       I


public scala.collection.mutable.WrappedArray newWrappedArray(int);
  Signature: (I)Lscala/collection/mutable/WrappedArray;
  Code:
   Stack=2, Locals=2, Args_size=2
	aload_0
	iload_1
	invokestatic	Method scala/reflect/ClassManifest$class.newWrappedArray:(Lscala/reflect/ClassManifest;I)Lscala/collection/mutable/WrappedArray;
	areturn
  Labels:
  LocalVariableTable: 
   Start  Length  Slot  Name   Signature
   0      6      0    this       Lscala/reflect/ClassManifest$$anon$2;
   0      6      1    len       I


public scala.collection.mutable.ArrayBuilder newArrayBuilder();
  Signature: ()Lscala/collection/mutable/ArrayBuilder;
  Code:
   Stack=1, Locals=1, Args_size=1
	aload_0
	invokestatic	Method scala/reflect/ClassManifest$class.newArrayBuilder:(Lscala/reflect/ClassManifest;)Lscala/collection/mutable/ArrayBuilder;
	areturn
  Labels:

public java.lang.String argString();
  Signature: ()Ljava/lang/String;
  Code:
   Stack=1, Locals=1, Args_size=1
	aload_0
	invokestatic	Method scala/reflect/ClassManifest$class.argString:(Lscala/reflect/ClassManifest;)Ljava/lang/String;
	areturn
  Labels:

public java.lang.Class erasure();
  Signature: ()Ljava/lang/Class;
  Code:
   Stack=1, Locals=1, Args_size=1
	aload_0
	getfield	Field upperbound$1:Lscala/reflect/ClassManifest;
	invokeinterface	InterfaceMethod scala/reflect/ClassManifest.erasure:()Ljava/lang/Class;
	areturn
  Labels:
  Signature: length = 0x2
   00 6C 

public scala.collection.immutable.List typeArguments();
  Signature: ()Lscala/collection/immutable/List;
  Code:
   Stack=1, Locals=1, Args_size=1
	aload_0
	getfield	Field typeArguments:Lscala/collection/immutable/List;
	areturn
  Labels:
  Signature: length = 0x2
   00 70 

public java.lang.String toString();
  Signature: ()Ljava/lang/String;
  Code:
   Stack=2, Locals=1, Args_size=1
	new	class scala/collection/mutable/StringBuilder
	dup
	invokespecial	Method scala/collection/mutable/StringBuilder."<init>":()V
	aload_0
	getfield	Field prefix$2:Lscala/reflect/OptManifest;
	invokevirtual	Method java/lang/Object.toString:()Ljava/lang/String;
	invokevirtual	Method scala/collection/mutable/StringBuilder.append:(Ljava/lang/Object;)Lscala/collection/mutable/StringBuilder;
	ldc	String #
	invokevirtual	Method scala/collection/mutable/StringBuilder.append:(Ljava/lang/Object;)Lscala/collection/mutable/StringBuilder;
	aload_0
	getfield	Field name$2:Ljava/lang/String;
	invokevirtual	Method scala/collection/mutable/StringBuilder.append:(Ljava/lang/Object;)Lscala/collection/mutable/StringBuilder;
	aload_0
	invokeinterface	InterfaceMethod scala/reflect/ClassManifest.argString:()Ljava/lang/String;
	invokevirtual	Method scala/collection/mutable/StringBuilder.append:(Ljava/lang/Object;)Lscala/collection/mutable/StringBuilder;
	invokevirtual	Method scala/collection/mutable/StringBuilder.toString:()Ljava/lang/String;
	areturn
  Labels:

public scala.reflect.ClassManifest$$anon$2(scala.reflect.OptManifest, java.lang.String, scala.reflect.ClassManifest, scala.collection.Seq);
  Signature: (Lscala/reflect/OptManifest;Ljava/lang/String;Lscala/reflect/ClassManifest;Lscala/collection/Seq;)V
  Code:
   Stack=2, Locals=5, Args_size=5
	aload_0
	aload_1
	putfield	Field prefix$2:Lscala/reflect/OptManifest;
	aload_0
	aload_2
	putfield	Field name$2:Ljava/lang/String;
	aload_0
	aload_3
	putfield	Field upperbound$1:Lscala/reflect/ClassManifest;
	aload_0
	invokespecial	Method java/lang/Object."<init>":()V
	aload_0
	invokestatic	Method scala/reflect/ClassManifest$class.$init$:(Lscala/reflect/ClassManifest;)V
	aload_0
	aload	4
	invokeinterface	InterfaceMethod scala/collection/TraversableOnce.toList:()Lscala/collection/immutable/List;
	putfield	Field typeArguments:Lscala/collection/immutable/List;
	return
  Labels:

}

