Compiled from "Tree.scala"
public final class scala.reflect.ClassDef$ extends java.lang.Object implements scala.Function3,scala.ScalaObject
  SourceFile: "Tree.scala"
  Scala: length = 0x
   
  minor version: 0
  major version: 49
  Constant pool:
Asciz	SourceFile;
Asciz	Tree.scala;
Asciz	Scala;
Asciz	MODULE$;
Asciz	Lscala/reflect/ClassDef$;;
Asciz	<clinit>;
Asciz	()V;
Asciz	Code;
Asciz	scala/reflect/ClassDef$;
class	scala/reflect/ClassDef$
Asciz	<init>;
NameAndType	"<init>":()V
Method	scala/reflect/ClassDef$."<init>":()V
Asciz	toString;
Asciz	()Ljava/lang/String;;
Asciz	LineNumberTable;
Asciz	scala/Function3$class;
class	scala/Function3$class
Asciz	(Lscala/Function3;)Ljava/lang/String;;
NameAndType	toString:(Lscala/Function3;)Ljava/lang/String;
Method	scala/Function3$class.toString:(Lscala/Function3;)Ljava/lang/String;
Asciz	curried;
Asciz	()Lscala/Function1;;
Asciz	(Lscala/Function3;)Lscala/Function1;;
NameAndType	curried:(Lscala/Function3;)Lscala/Function1;
Method	scala/Function3$class.curried:(Lscala/Function3;)Lscala/Function1;
Asciz	curry;
NameAndType	curry:(Lscala/Function3;)Lscala/Function1;
Method	scala/Function3$class.curry:(Lscala/Function3;)Lscala/Function1;
Asciz	Deprecated;
Asciz	tupled;
NameAndType	tupled:(Lscala/Function3;)Lscala/Function1;
Method	scala/Function3$class.tupled:(Lscala/Function3;)Lscala/Function1;
Asciz	unapply;
Asciz	(Lscala/reflect/ClassDef;)Lscala/Some;;
Asciz	scala/Some;
class	scala/Some
Asciz	scala/Tuple3;
class	scala/Tuple3
Asciz	scala/reflect/ClassDef;
class	scala/reflect/ClassDef
Asciz	sym;
Asciz	()Lscala/reflect/Symbol;;
NameAndType	sym:()Lscala/reflect/Symbol;
Method	scala/reflect/ClassDef.sym:()Lscala/reflect/Symbol;
Asciz	tpe;
Asciz	()Lscala/reflect/Type;;
NameAndType	tpe:()Lscala/reflect/Type;
Method	scala/reflect/ClassDef.tpe:()Lscala/reflect/Type;
Asciz	impl;
Asciz	()Lscala/reflect/Template;;
NameAndType	impl:()Lscala/reflect/Template;
Method	scala/reflect/ClassDef.impl:()Lscala/reflect/Template;
Asciz	(Ljava/lang/Object;Ljava/lang/Object;Ljava/lang/Object;)V;
NameAndType	"<init>":(Ljava/lang/Object;Ljava/lang/Object;Ljava/lang/Object;)V
Method	scala/Tuple3."<init>":(Ljava/lang/Object;Ljava/lang/Object;Ljava/lang/Object;)V
Asciz	(Ljava/lang/Object;)V;
NameAndType	"<init>":(Ljava/lang/Object;)V
Method	scala/Some."<init>":(Ljava/lang/Object;)V
Asciz	this;
Asciz	x$0;
Asciz	Lscala/reflect/ClassDef;;
Asciz	LocalVariableTable;
Asciz	apply;
Asciz	(Lscala/reflect/Symbol;Lscala/reflect/Type;Lscala/reflect/Template;)Lscala/reflect/ClassDef;;
Asciz	(Lscala/reflect/Symbol;Lscala/reflect/Type;Lscala/reflect/Template;)V;
NameAndType	"<init>":(Lscala/reflect/Symbol;Lscala/reflect/Type;Lscala/reflect/Template;)V
Method	scala/reflect/ClassDef."<init>":(Lscala/reflect/Symbol;Lscala/reflect/Type;Lscala/reflect/Template;)V
Asciz	Lscala/reflect/Symbol;;
Asciz	Lscala/reflect/Type;;
Asciz	Lscala/reflect/Template;;
Asciz	(Ljava/lang/Object;Ljava/lang/Object;Ljava/lang/Object;)Ljava/lang/Object;;
Asciz	scala/reflect/Symbol;
class	scala/reflect/Symbol
Asciz	scala/reflect/Type;
class	scala/reflect/Type
Asciz	scala/reflect/Template;
class	scala/reflect/Template
NameAndType	apply:(Lscala/reflect/Symbol;Lscala/reflect/Type;Lscala/reflect/Template;)Lscala/reflect/ClassDef;
Method	scala/reflect/ClassDef$.apply:(Lscala/reflect/Symbol;Lscala/reflect/Type;Lscala/reflect/Template;)Lscala/reflect/ClassDef;
Asciz	v1;
Asciz	Ljava/lang/Object;;
Asciz	v2;
Asciz	v3;
Asciz	java/lang/Object;
class	java/lang/Object
Method	java/lang/Object."<init>":()V
NameAndType	MODULE$:Lscala/reflect/ClassDef$;
Field	scala/reflect/ClassDef$.MODULE$:Lscala/reflect/ClassDef$;
Asciz	$init$;
Asciz	(Lscala/Function3;)V;
NameAndType	$init$:(Lscala/Function3;)V
Method	scala/Function3$class.$init$:(Lscala/Function3;)V
Asciz	scala/Function3;
class	scala/Function3
Asciz	scala/ScalaObject;
class	scala/ScalaObject

{
public static final scala.reflect.ClassDef$ MODULE$;
  Signature: Lscala/reflect/ClassDef$;

public static {};
  Signature: ()V
  Code:
   Stack=1, Locals=0, Args_size=0
	new	class scala/reflect/ClassDef$
	invokespecial	Method "<init>":()V
	return
  Labels:

public java.lang.String toString();
  Signature: ()Ljava/lang/String;
  Code:
   Stack=1, Locals=1, Args_size=1
	aload_0
	invokestatic	Method scala/Function3$class.toString:(Lscala/Function3;)Ljava/lang/String;
	areturn
  Labels:

public scala.Function1 curried();
  Signature: ()Lscala/Function1;
  Code:
   Stack=1, Locals=1, Args_size=1
	aload_0
	invokestatic	Method scala/Function3$class.curried:(Lscala/Function3;)Lscala/Function1;
	areturn
  Labels:

public scala.Function1 curry();
  Signature: ()Lscala/Function1;
  Code:
   Stack=1, Locals=1, Args_size=1
	aload_0
	invokestatic	Method scala/Function3$class.curry:(Lscala/Function3;)Lscala/Function1;
	areturn
  Labels:
  Deprecated: true

public scala.Function1 tupled();
  Signature: ()Lscala/Function1;
  Code:
   Stack=1, Locals=1, Args_size=1
	aload_0
	invokestatic	Method scala/Function3$class.tupled:(Lscala/Function3;)Lscala/Function1;
	areturn
  Labels:

public scala.Some unapply(scala.reflect.ClassDef);
  Signature: (Lscala/reflect/ClassDef;)Lscala/Some;
  Code:
   Stack=7, Locals=2, Args_size=2
	new	class scala/Some
	dup
	new	class scala/Tuple3
	dup
	aload_1
	invokevirtual	Method scala/reflect/ClassDef.sym:()Lscala/reflect/Symbol;
	aload_1
	invokevirtual	Method scala/reflect/ClassDef.tpe:()Lscala/reflect/Type;
	aload_1
	invokevirtual	Method scala/reflect/ClassDef.impl:()Lscala/reflect/Template;
	invokespecial	Method scala/Tuple3."<init>":(Ljava/lang/Object;Ljava/lang/Object;Ljava/lang/Object;)V
	invokespecial	Method scala/Some."<init>":(Ljava/lang/Object;)V
	areturn
  Labels:
  LocalVariableTable: 
   Start  Length  Slot  Name   Signature
   0      27      0    this       Lscala/reflect/ClassDef$;
   0      27      1    x$0       Lscala/reflect/ClassDef;


public scala.reflect.ClassDef apply(scala.reflect.Symbol, scala.reflect.Type, scala.reflect.Template);
  Signature: (Lscala/reflect/Symbol;Lscala/reflect/Type;Lscala/reflect/Template;)Lscala/reflect/ClassDef;
  Code:
   Stack=5, Locals=4, Args_size=4
	new	class scala/reflect/ClassDef
	dup
	aload_1
	aload_2
	aload_3
	invokespecial	Method scala/reflect/ClassDef."<init>":(Lscala/reflect/Symbol;Lscala/reflect/Type;Lscala/reflect/Template;)V
	areturn
  Labels:
  LocalVariableTable: 
   Start  Length  Slot  Name   Signature
   0      11      0    this       Lscala/reflect/ClassDef$;
   0      11      1    sym       Lscala/reflect/Symbol;
   0      11      2    tpe       Lscala/reflect/Type;
   0      11      3    impl       Lscala/reflect/Template;


public java.lang.Object apply(java.lang.Object, java.lang.Object, java.lang.Object);
  Signature: (Ljava/lang/Object;Ljava/lang/Object;Ljava/lang/Object;)Ljava/lang/Object;
  Code:
   Stack=4, Locals=4, Args_size=4
	aload_0
	aload_1
	checkcast	class scala/reflect/Symbol
	aload_2
	checkcast	class scala/reflect/Type
	aload_3
	checkcast	class scala/reflect/Template
	invokevirtual	Method apply:(Lscala/reflect/Symbol;Lscala/reflect/Type;Lscala/reflect/Template;)Lscala/reflect/ClassDef;
	areturn
  Labels:
  LocalVariableTable: 
   Start  Length  Slot  Name   Signature
   0      17      0    this       Lscala/reflect/ClassDef$;
   0      17      1    v1       Ljava/lang/Object;
   0      17      2    v2       Ljava/lang/Object;
   0      17      3    v3       Ljava/lang/Object;


private scala.reflect.ClassDef$();
  Signature: ()V
  Code:
   Stack=1, Locals=1, Args_size=1
	aload_0
	invokespecial	Method java/lang/Object."<init>":()V
	aload_0
	putstatic	Field MODULE$:Lscala/reflect/ClassDef$;
	aload_0
	invokestatic	Method scala/Function3$class.$init$:(Lscala/Function3;)V
	return
  Labels:

}

