Compiled from "ClassManifest.scala"
public final class scala.reflect.ClassManifest$$anonfun$subtype$1$1 extends java.lang.Object implements scala.Function1,scala.ScalaObject,java.io.Serializable
  SourceFile: "ClassManifest.scala"
  Scala: length = 0x
   
  InnerClass: 
   public final $anonfun$subtype$1$1=class scala/reflect/ClassManifest$$anonfun$subtype$1$1 of class scala/reflect/ClassManifest
  minor version: 0
  major version: 49
  Constant pool:
Asciz	SourceFile;
Asciz	ClassManifest.scala;
Asciz	<clinit>;
Asciz	()V;
Asciz	Code;
Asciz	serialVersionUID;
Asciz	J;
Asciz	scala/reflect/ClassManifest$$anonfun$subtype$1$1;
class	scala/reflect/ClassManifest$$anonfun$subtype$1$1
NameAndType	serialVersionUID:J
Field	scala/reflect/ClassManifest$$anonfun$subtype$1$1.serialVersionUID:J
Asciz	sup$1;
Asciz	Ljava/lang/Class;;
Asciz	$outer;
Asciz	Lscala/reflect/ClassManifest;;
Asciz	<init>;
Asciz	(Lscala/reflect/ClassManifest;Ljava/lang/Class;)V;
Asciz	LineNumberTable;
Asciz	java/lang/NullPointerException;
class	java/lang/NullPointerException
NameAndType	"<init>":()V
Method	java/lang/NullPointerException."<init>":()V
NameAndType	$outer:Lscala/reflect/ClassManifest;
Field	scala/reflect/ClassManifest$$anonfun$subtype$1$1.$outer:Lscala/reflect/ClassManifest;
NameAndType	sup$1:Ljava/lang/Class;
Field	scala/reflect/ClassManifest$$anonfun$subtype$1$1.sup$1:Ljava/lang/Class;
Asciz	java/lang/Object;
class	java/lang/Object
Method	java/lang/Object."<init>":()V
Asciz	scala/Function1$class;
class	scala/Function1$class
Asciz	$init$;
Asciz	(Lscala/Function1;)V;
NameAndType	$init$:(Lscala/Function1;)V
Method	scala/Function1$class.$init$:(Lscala/Function1;)V
Asciz	this;
Asciz	Lscala/reflect/ClassManifest$$anonfun$subtype$1$1;;
Asciz	LocalVariableTable;
Asciz	(Lscala/reflect/ClassManifest<TT;>;)V;
Asciz	Signature;
Asciz	apply;
Asciz	(Ljava/lang/Object;)Ljava/lang/Object;;
Asciz	java/lang/Class;
class	java/lang/Class
Asciz	(Ljava/lang/Class;)Z;
NameAndType	apply:(Ljava/lang/Class;)Z
Method	scala/reflect/ClassManifest$$anonfun$subtype$1$1.apply:(Ljava/lang/Class;)Z
Asciz	scala/runtime/BoxesRunTime;
class	scala/runtime/BoxesRunTime
Asciz	boxToBoolean;
Asciz	(Z)Ljava/lang/Boolean;;
NameAndType	boxToBoolean:(Z)Ljava/lang/Boolean;
Method	scala/runtime/BoxesRunTime.boxToBoolean:(Z)Ljava/lang/Boolean;
Asciz	v1;
Asciz	Ljava/lang/Object;;
Asciz	scala/reflect/ClassManifest$class;
class	scala/reflect/ClassManifest$class
Asciz	subtype$1;
Asciz	(Lscala/reflect/ClassManifest;Ljava/lang/Class;Ljava/lang/Class;)Z;
NameAndType	subtype$1:(Lscala/reflect/ClassManifest;Ljava/lang/Class;Ljava/lang/Class;)Z
Method	scala/reflect/ClassManifest$class.subtype$1:(Lscala/reflect/ClassManifest;Ljava/lang/Class;Ljava/lang/Class;)Z
Asciz	(Ljava/lang/Class<*>;)Z;
Asciz	andThen;
Asciz	(Lscala/Function1;)Lscala/Function1;;
Asciz	(Lscala/Function1;Lscala/Function1;)Lscala/Function1;;
NameAndType	andThen:(Lscala/Function1;Lscala/Function1;)Lscala/Function1;
Method	scala/Function1$class.andThen:(Lscala/Function1;Lscala/Function1;)Lscala/Function1;
Asciz	g;
Asciz	Lscala/Function1;;
Asciz	compose;
NameAndType	compose:(Lscala/Function1;Lscala/Function1;)Lscala/Function1;
Method	scala/Function1$class.compose:(Lscala/Function1;Lscala/Function1;)Lscala/Function1;
Asciz	toString;
Asciz	()Ljava/lang/String;;
Asciz	(Lscala/Function1;)Ljava/lang/String;;
NameAndType	toString:(Lscala/Function1;)Ljava/lang/String;
Method	scala/Function1$class.toString:(Lscala/Function1;)Ljava/lang/String;
Asciz	Scala;
Asciz	InnerClasses;
Asciz	scala/reflect/ClassManifest;
class	scala/reflect/ClassManifest
Asciz	$anonfun$subtype$1$1;
Asciz	scala/Function1;
class	scala/Function1
Asciz	scala/ScalaObject;
class	scala/ScalaObject
Asciz	java/io/Serializable;
class	java/io/Serializable

{
public static final long serialVersionUID;
  Signature: J

private final java.lang.Class sup$1;
  Signature: Ljava/lang/Class;

private final scala.reflect.ClassManifest $outer;
  Signature: Lscala/reflect/ClassManifest;

public static {};
  Signature: ()V
  Code:
   Stack=2, Locals=0, Args_size=0
	lconst_0
	putstatic	Field serialVersionUID:J
	return
  Labels:

public scala.reflect.ClassManifest$$anonfun$subtype$1$1(scala.reflect.ClassManifest, java.lang.Class);
  Signature: (Lscala/reflect/ClassManifest;Ljava/lang/Class;)V
  Code:
   Stack=2, Locals=3, Args_size=3
	aload_1
	ifnonnull	l1 // aload_0
	new	class java/lang/NullPointerException
	dup
	invokespecial	Method java/lang/NullPointerException."<init>":()V
	athrow
l1	aload_0
	aload_1
	putfield	Field $outer:Lscala/reflect/ClassManifest;
	aload_0
	aload_2
	putfield	Field sup$1:Ljava/lang/Class;
	aload_0
	invokespecial	Method java/lang/Object."<init>":()V
	aload_0
	invokestatic	Method scala/Function1$class.$init$:(Lscala/Function1;)V
	return
  Labels:
   	l1 = 12 // aload_0
  LocalVariableTable: 
   Start  Length  Slot  Name   Signature
   0      31      0    this       Lscala/reflect/ClassManifest$$anonfun$subtype$1$1;
   0      31      1    $outer       Lscala/reflect/ClassManifest;

  Signature: length = 0x2
   00 27 

public final java.lang.Object apply(java.lang.Object);
  Signature: (Ljava/lang/Object;)Ljava/lang/Object;
  Code:
   Stack=2, Locals=4, Args_size=2
	aload_0
	getfield	Field $outer:Lscala/reflect/ClassManifest;
	astore_3
	aload_0
	aload_1
	checkcast	class java/lang/Class
	invokevirtual	Method apply:(Ljava/lang/Class;)Z
	istore_2
	iload_2
	invokestatic	Method scala/runtime/BoxesRunTime.boxToBoolean:(Z)Ljava/lang/Boolean;
	areturn
  Labels:
  LocalVariableTable: 
   Start  Length  Slot  Name   Signature
   0      19      0    this       Lscala/reflect/ClassManifest$$anonfun$subtype$1$1;
   5      14      1    v1       Ljava/lang/Object;


public final boolean apply(java.lang.Class);
  Signature: (Ljava/lang/Class;)Z
  Code:
   Stack=3, Locals=3, Args_size=2
	aload_0
	getfield	Field $outer:Lscala/reflect/ClassManifest;
	astore_2
	aload_0
	getfield	Field $outer:Lscala/reflect/ClassManifest;
	aload_1
	aload_0
	getfield	Field sup$1:Ljava/lang/Class;
	invokestatic	Method scala/reflect/ClassManifest$class.subtype$1:(Lscala/reflect/ClassManifest;Ljava/lang/Class;Ljava/lang/Class;)Z
	ireturn
  Labels:
  LocalVariableTable: 
   Start  Length  Slot  Name   Signature
   0      18      0    this       Lscala/reflect/ClassManifest$$anonfun$subtype$1$1;

  Signature: length = 0x2
   00 3E 

public scala.Function1 andThen(scala.Function1);
  Signature: (Lscala/Function1;)Lscala/Function1;
  Code:
   Stack=2, Locals=2, Args_size=2
	aload_0
	aload_1
	invokestatic	Method scala/Function1$class.andThen:(Lscala/Function1;Lscala/Function1;)Lscala/Function1;
	areturn
  Labels:
  LocalVariableTable: 
   Start  Length  Slot  Name   Signature
   0      6      0    this       Lscala/reflect/ClassManifest$$anonfun$subtype$1$1;
   0      6      1    g       Lscala/Function1;


public scala.Function1 compose(scala.Function1);
  Signature: (Lscala/Function1;)Lscala/Function1;
  Code:
   Stack=2, Locals=2, Args_size=2
	aload_0
	aload_1
	invokestatic	Method scala/Function1$class.compose:(Lscala/Function1;Lscala/Function1;)Lscala/Function1;
	areturn
  Labels:
  LocalVariableTable: 
   Start  Length  Slot  Name   Signature
   0      6      0    this       Lscala/reflect/ClassManifest$$anonfun$subtype$1$1;
   0      6      1    g       Lscala/Function1;


public java.lang.String toString();
  Signature: ()Ljava/lang/String;
  Code:
   Stack=1, Locals=1, Args_size=1
	aload_0
	invokestatic	Method scala/Function1$class.toString:(Lscala/Function1;)Ljava/lang/String;
	areturn
  Labels:

}

