Compiled from "ClassManifest.scala"
public abstract class scala.reflect.ClassManifest$class extends java.lang.Object
  SourceFile: "ClassManifest.scala"
  Scala: length = 0x
   
  InnerClass: 
   public #261= #57 of #260; //ofRef=class scala/collection/mutable/ArrayOps$ofRef of class scala/collection/mutable/ArrayOps
   public final #261= #175 of #263; //ofRef=class scala/collection/mutable/WrappedArray$ofRef of class scala/collection/mutable/WrappedArray
   public #261= #170 of #265; //ofRef=class scala/collection/mutable/ArrayBuilder$ofRef of class scala/collection/mutable/ArrayBuilder
   public final #266= #99 of #115; //$anonfun$subtype$1$1=class scala/reflect/ClassManifest$$anonfun$subtype$1$1 of class scala/reflect/ClassManifest
   public final #267= #31 of #115; //$anonfun$subargs$1$1=class scala/reflect/ClassManifest$$anonfun$subargs$1$1 of class scala/reflect/ClassManifest
  minor version: 0
  major version: 49
  Constant pool:
const #1 = Asciz	SourceFile;
const #2 = Asciz	ClassManifest.scala;
const #3 = Asciz	$init$;
const #4 = Asciz	(Lscala/reflect/ClassManifest;)V;
const #5 = Asciz	Code;
const #6 = Asciz	LineNumberTable;
const #7 = Asciz	$this;
const #8 = Asciz	Lscala/reflect/ClassManifest;;
const #9 = Asciz	LocalVariableTable;
const #10 = Asciz	subargs$1;
const #11 = Asciz	(Lscala/reflect/ClassManifest;Lscala/collection/immutable/List;Lscala/collection/immutable/List;)Z;
const #12 = Asciz	scala/collection/immutable/List$;
const #13 = class	#12;	//  scala/collection/immutable/List$
const #14 = Asciz	MODULE$;
const #15 = Asciz	Lscala/collection/immutable/List$;;
const #16 = NameAndType	#14:#15;//  MODULE$:Lscala/collection/immutable/List$;
const #17 = Field	#13.#16;	//  scala/collection/immutable/List$.MODULE$:Lscala/collection/immutable/List$;
const #18 = Asciz	canBuildFrom;
const #19 = Asciz	()Lscala/collection/generic/CanBuildFrom;;
const #20 = NameAndType	#18:#19;//  canBuildFrom:()Lscala/collection/generic/CanBuildFrom;
const #21 = Method	#13.#20;	//  scala/collection/immutable/List$.canBuildFrom:()Lscala/collection/generic/CanBuildFrom;
const #22 = Asciz	scala/collection/IterableLike;
const #23 = class	#22;	//  scala/collection/IterableLike
const #24 = Asciz	zip;
const #25 = Asciz	(Lscala/collection/Iterable;Lscala/collection/generic/CanBuildFrom;)Ljava/lang/Object;;
const #26 = NameAndType	#24:#25;//  zip:(Lscala/collection/Iterable;Lscala/collection/generic/CanBuildFrom;)Ljava/lang/Object;
const #27 = InterfaceMethod	#23.#26;	//  scala/collection/IterableLike.zip:(Lscala/collection/Iterable;Lscala/collection/generic/CanBuildFrom;)Ljava/lang/Object;
const #28 = Asciz	scala/collection/LinearSeqLike;
const #29 = class	#28;	//  scala/collection/LinearSeqLike
const #30 = Asciz	scala/reflect/ClassManifest$$anonfun$subargs$1$1;
const #31 = class	#30;	//  scala/reflect/ClassManifest$$anonfun$subargs$1$1
const #32 = Asciz	<init>;
const #33 = NameAndType	#32:#4;//  "<init>":(Lscala/reflect/ClassManifest;)V
const #34 = Method	#31.#33;	//  scala/reflect/ClassManifest$$anonfun$subargs$1$1."<init>":(Lscala/reflect/ClassManifest;)V
const #35 = Asciz	forall;
const #36 = Asciz	(Lscala/Function1;)Z;
const #37 = NameAndType	#35:#36;//  forall:(Lscala/Function1;)Z
const #38 = InterfaceMethod	#29.#37;	//  scala/collection/LinearSeqLike.forall:(Lscala/Function1;)Z
const #39 = Asciz	args1;
const #40 = Asciz	Lscala/collection/immutable/List;;
const #41 = Asciz	args2;
const #42 = Asciz	subtype$1;
const #43 = Asciz	(Lscala/reflect/ClassManifest;Ljava/lang/Class;Ljava/lang/Class;)Z;
const #44 = Asciz	java/lang/Class;
const #45 = class	#44;	//  java/lang/Class
const #46 = Asciz	getSuperclass;
const #47 = Asciz	()Ljava/lang/Class;;
const #48 = NameAndType	#46:#47;//  getSuperclass:()Ljava/lang/Class;
const #49 = Method	#45.#48;	//  java/lang/Class.getSuperclass:()Ljava/lang/Class;
const #50 = Asciz	getInterfaces;
const #51 = Asciz	()[Ljava/lang/Class;;
const #52 = NameAndType	#50:#51;//  getInterfaces:()[Ljava/lang/Class;
const #53 = Method	#45.#52;	//  java/lang/Class.getInterfaces:()[Ljava/lang/Class;
const #54 = Asciz	[Ljava/lang/Object;;
const #55 = class	#54;	//  "[Ljava/lang/Object;"
const #56 = Asciz	scala/collection/mutable/ArrayOps$ofRef;
const #57 = class	#56;	//  scala/collection/mutable/ArrayOps$ofRef
const #58 = Asciz	([Ljava/lang/Object;)V;
const #59 = NameAndType	#32:#58;//  "<init>":([Ljava/lang/Object;)V
const #60 = Method	#57.#59;	//  scala/collection/mutable/ArrayOps$ofRef."<init>":([Ljava/lang/Object;)V
const #61 = Asciz	scala/collection/TraversableLike;
const #62 = class	#61;	//  scala/collection/TraversableLike
const #63 = Asciz	toList;
const #64 = Asciz	()Lscala/collection/immutable/List;;
const #65 = NameAndType	#63:#64;//  toList:()Lscala/collection/immutable/List;
const #66 = InterfaceMethod	#62.#65;	//  scala/collection/TraversableLike.toList:()Lscala/collection/immutable/List;
const #67 = Asciz	java/lang/Object;
const #68 = class	#67;	//  java/lang/Object
const #69 = Asciz	equals;
const #70 = Asciz	(Ljava/lang/Object;)Z;
const #71 = NameAndType	#69:#70;//  equals:(Ljava/lang/Object;)Z
const #72 = Method	#68.#71;	//  java/lang/Object.equals:(Ljava/lang/Object;)Z
const #73 = Asciz	scala/collection/immutable/Nil$;
const #74 = class	#73;	//  scala/collection/immutable/Nil$
const #75 = Asciz	Lscala/collection/immutable/Nil$;;
const #76 = NameAndType	#14:#75;//  MODULE$:Lscala/collection/immutable/Nil$;
const #77 = Field	#74.#76;	//  scala/collection/immutable/Nil$.MODULE$:Lscala/collection/immutable/Nil$;
const #78 = Asciz	scala/Predef$;
const #79 = class	#78;	//  scala/Predef$
const #80 = Asciz	Lscala/Predef$;;
const #81 = NameAndType	#14:#80;//  MODULE$:Lscala/Predef$;
const #82 = Field	#79.#81;	//  scala/Predef$.MODULE$:Lscala/Predef$;
const #83 = Asciz	wrapRefArray;
const #84 = Asciz	([Ljava/lang/Object;)Lscala/collection/mutable/WrappedArray;;
const #85 = NameAndType	#83:#84;//  wrapRefArray:([Ljava/lang/Object;)Lscala/collection/mutable/WrappedArray;
const #86 = Method	#79.#85;	//  scala/Predef$.wrapRefArray:([Ljava/lang/Object;)Lscala/collection/mutable/WrappedArray;
const #87 = Asciz	scala/collection/immutable/List;
const #88 = class	#87;	//  scala/collection/immutable/List
const #89 = Asciz	$colon$colon$colon;
const #90 = Asciz	(Lscala/collection/immutable/List;)Lscala/collection/immutable/List;;
const #91 = NameAndType	#89:#90;//  $colon$colon$colon:(Lscala/collection/immutable/List;)Lscala/collection/immutable/List;
const #92 = Method	#88.#91;	//  scala/collection/immutable/List.$colon$colon$colon:(Lscala/collection/immutable/List;)Lscala/collection/immutable/List;
const #93 = Asciz	scala/collection/SeqLike;
const #94 = class	#93;	//  scala/collection/SeqLike
const #95 = Asciz	contains;
const #96 = NameAndType	#95:#70;//  contains:(Ljava/lang/Object;)Z
const #97 = InterfaceMethod	#94.#96;	//  scala/collection/SeqLike.contains:(Ljava/lang/Object;)Z
const #98 = Asciz	scala/reflect/ClassManifest$$anonfun$subtype$1$1;
const #99 = class	#98;	//  scala/reflect/ClassManifest$$anonfun$subtype$1$1
const #100 = Asciz	(Lscala/reflect/ClassManifest;Ljava/lang/Class;)V;
const #101 = NameAndType	#32:#100;//  "<init>":(Lscala/reflect/ClassManifest;Ljava/lang/Class;)V
const #102 = Method	#99.#101;	//  scala/reflect/ClassManifest$$anonfun$subtype$1$1."<init>":(Lscala/reflect/ClassManifest;Ljava/lang/Class;)V
const #103 = Asciz	exists;
const #104 = NameAndType	#103:#36;//  exists:(Lscala/Function1;)Z
const #105 = InterfaceMethod	#29.#104;	//  scala/collection/LinearSeqLike.exists:(Lscala/Function1;)Z
const #106 = Asciz	sub;
const #107 = Asciz	Ljava/lang/Class;;
const #108 = Asciz	sup$1;
const #109 = Asciz	subSuperClass;
const #110 = Asciz	subSuperInterfaces;
const #111 = Asciz	subSuper;
const #112 = Asciz	argString;
const #113 = Asciz	(Lscala/reflect/ClassManifest;)Ljava/lang/String;;
const #114 = Asciz	scala/reflect/ClassManifest;
const #115 = class	#114;	//  scala/reflect/ClassManifest
const #116 = Asciz	typeArguments;
const #117 = NameAndType	#116:#64;//  typeArguments:()Lscala/collection/immutable/List;
const #118 = InterfaceMethod	#115.#117;	//  scala/reflect/ClassManifest.typeArguments:()Lscala/collection/immutable/List;
const #119 = Asciz	nonEmpty;
const #120 = Asciz	()Z;
const #121 = NameAndType	#119:#120;//  nonEmpty:()Z
const #122 = InterfaceMethod	#62.#121;	//  scala/collection/TraversableLike.nonEmpty:()Z
const #123 = Asciz	[;
const #124 = String	#123;	//  [
const #125 = Asciz	, ;
const #126 = String	#125;	//  , 
const #127 = Asciz	];
const #128 = String	#127;	//  ]
const #129 = Asciz	mkString;
const #130 = Asciz	(Ljava/lang/String;Ljava/lang/String;Ljava/lang/String;)Ljava/lang/String;;
const #131 = NameAndType	#129:#130;//  mkString:(Ljava/lang/String;Ljava/lang/String;Ljava/lang/String;)Ljava/lang/String;
const #132 = InterfaceMethod	#62.#131;	//  scala/collection/TraversableLike.mkString:(Ljava/lang/String;Ljava/lang/String;Ljava/lang/String;)Ljava/lang/String;
const #133 = Asciz	erasure;
const #134 = NameAndType	#133:#47;//  erasure:()Ljava/lang/Class;
const #135 = InterfaceMethod	#115.#134;	//  scala/reflect/ClassManifest.erasure:()Ljava/lang/Class;
const #136 = Asciz	isArray;
const #137 = NameAndType	#136:#120;//  isArray:()Z
const #138 = Method	#45.#137;	//  java/lang/Class.isArray:()Z
const #139 = Asciz	scala/collection/mutable/StringBuilder;
const #140 = class	#139;	//  scala/collection/mutable/StringBuilder
const #141 = Asciz	()V;
const #142 = NameAndType	#32:#141;//  "<init>":()V
const #143 = Method	#140.#142;	//  scala/collection/mutable/StringBuilder."<init>":()V
const #144 = Asciz	append;
const #145 = Asciz	(Ljava/lang/Object;)Lscala/collection/mutable/StringBuilder;;
const #146 = NameAndType	#144:#145;//  append:(Ljava/lang/Object;)Lscala/collection/mutable/StringBuilder;
const #147 = Method	#140.#146;	//  scala/collection/mutable/StringBuilder.append:(Ljava/lang/Object;)Lscala/collection/mutable/StringBuilder;
const #148 = Asciz	scala/reflect/ClassManifest$;
const #149 = class	#148;	//  scala/reflect/ClassManifest$
const #150 = Asciz	Lscala/reflect/ClassManifest$;;
const #151 = NameAndType	#14:#150;//  MODULE$:Lscala/reflect/ClassManifest$;
const #152 = Field	#149.#151;	//  scala/reflect/ClassManifest$.MODULE$:Lscala/reflect/ClassManifest$;
const #153 = Asciz	getComponentType;
const #154 = NameAndType	#153:#47;//  getComponentType:()Ljava/lang/Class;
const #155 = Method	#45.#154;	//  java/lang/Class.getComponentType:()Ljava/lang/Class;
const #156 = Asciz	fromClass;
const #157 = Asciz	(Ljava/lang/Class;)Lscala/reflect/ClassManifest;;
const #158 = NameAndType	#156:#157;//  fromClass:(Ljava/lang/Class;)Lscala/reflect/ClassManifest;
const #159 = Method	#149.#158;	//  scala/reflect/ClassManifest$.fromClass:(Ljava/lang/Class;)Lscala/reflect/ClassManifest;
const #160 = Asciz	toString;
const #161 = Asciz	()Ljava/lang/String;;
const #162 = NameAndType	#160:#161;//  toString:()Ljava/lang/String;
const #163 = Method	#140.#162;	//  scala/collection/mutable/StringBuilder.toString:()Ljava/lang/String;
const #164 = Asciz	;
const #165 = String	#164;	//  
const #166 = Asciz	(Lscala/reflect/ClassManifest;)Lscala/collection/immutable/List;;
const #167 = Asciz	newArrayBuilder;
const #168 = Asciz	(Lscala/reflect/ClassManifest;)Lscala/collection/mutable/ArrayBuilder;;
const #169 = Asciz	scala/collection/mutable/ArrayBuilder$ofRef;
const #170 = class	#169;	//  scala/collection/mutable/ArrayBuilder$ofRef
const #171 = Method	#170.#33;	//  scala/collection/mutable/ArrayBuilder$ofRef."<init>":(Lscala/reflect/ClassManifest;)V
const #172 = Asciz	newWrappedArray;
const #173 = Asciz	(Lscala/reflect/ClassManifest;I)Lscala/collection/mutable/WrappedArray;;
const #174 = Asciz	scala/collection/mutable/WrappedArray$ofRef;
const #175 = class	#174;	//  scala/collection/mutable/WrappedArray$ofRef
const #176 = Asciz	newArray;
const #177 = Asciz	(I)Ljava/lang/Object;;
const #178 = NameAndType	#176:#177;//  newArray:(I)Ljava/lang/Object;
const #179 = InterfaceMethod	#115.#178;	//  scala/reflect/ClassManifest.newArray:(I)Ljava/lang/Object;
const #180 = Method	#175.#59;	//  scala/collection/mutable/WrappedArray$ofRef."<init>":([Ljava/lang/Object;)V
const #181 = Asciz	len;
const #182 = Asciz	I;
const #183 = Asciz	newArray5;
const #184 = Asciz	(Lscala/reflect/ClassManifest;I)[[[[Ljava/lang/Object;;
const #185 = Asciz	arrayClass;
const #186 = Asciz	(Ljava/lang/Class;)Ljava/lang/Class;;
const #187 = NameAndType	#185:#186;//  arrayClass:(Ljava/lang/Class;)Ljava/lang/Class;
const #188 = InterfaceMethod	#115.#187;	//  scala/reflect/ClassManifest.arrayClass:(Ljava/lang/Class;)Ljava/lang/Class;
const #189 = Asciz	java/lang/reflect/Array;
const #190 = class	#189;	//  java/lang/reflect/Array
const #191 = Asciz	newInstance;
const #192 = Asciz	(Ljava/lang/Class;I)Ljava/lang/Object;;
const #193 = NameAndType	#191:#192;//  newInstance:(Ljava/lang/Class;I)Ljava/lang/Object;
const #194 = Method	#190.#193;	//  java/lang/reflect/Array.newInstance:(Ljava/lang/Class;I)Ljava/lang/Object;
const #195 = Asciz	[[[[Ljava/lang/Object;;
const #196 = class	#195;	//  "[[[[Ljava/lang/Object;"
const #197 = Asciz	newArray4;
const #198 = Asciz	(Lscala/reflect/ClassManifest;I)[[[Ljava/lang/Object;;
const #199 = Asciz	[[[Ljava/lang/Object;;
const #200 = class	#199;	//  "[[[Ljava/lang/Object;"
const #201 = Asciz	newArray3;
const #202 = Asciz	(Lscala/reflect/ClassManifest;I)[[Ljava/lang/Object;;
const #203 = Asciz	[[Ljava/lang/Object;;
const #204 = class	#203;	//  "[[Ljava/lang/Object;"
const #205 = Asciz	newArray2;
const #206 = Asciz	(Lscala/reflect/ClassManifest;I)[Ljava/lang/Object;;
const #207 = Asciz	(Lscala/reflect/ClassManifest;I)Ljava/lang/Object;;
const #208 = Asciz	arrayManifest;
const #209 = Asciz	(Lscala/reflect/ClassManifest;)Lscala/reflect/ClassManifest;;
const #210 = Asciz	classType;
const #211 = NameAndType	#210:#157;//  classType:(Ljava/lang/Class;)Lscala/reflect/ClassManifest;
const #212 = Method	#149.#211;	//  scala/reflect/ClassManifest$.classType:(Ljava/lang/Class;)Lscala/reflect/ClassManifest;
const #213 = Asciz	(Lscala/reflect/ClassManifest;Ljava/lang/Class;)Ljava/lang/Class;;
const #214 = Asciz	getClass;
const #215 = NameAndType	#214:#47;//  getClass:()Ljava/lang/Class;
const #216 = Method	#68.#215;	//  java/lang/Object.getClass:()Ljava/lang/Class;
const #217 = Asciz	tp;
const #218 = Asciz	(Lscala/reflect/ClassManifest;Ljava/lang/Object;)Z;
const #219 = Asciz	scala/reflect/AnyValManifest;
const #220 = class	#219;	//  scala/reflect/AnyValManifest
const #221 = Asciz	scala/MatchError;
const #222 = class	#221;	//  scala/MatchError
const #223 = Method	#68.#162;	//  java/lang/Object.toString:()Ljava/lang/String;
const #224 = Asciz	(Ljava/lang/String;)V;
const #225 = NameAndType	#32:#224;//  "<init>":(Ljava/lang/String;)V
const #226 = Method	#222.#225;	//  scala/MatchError."<init>":(Ljava/lang/String;)V
const #227 = Asciz	that;
const #228 = Asciz	Ljava/lang/Object;;
const #229 = Asciz	temp12;
const #230 = Asciz	$greater$colon$greater;
const #231 = Asciz	(Lscala/reflect/ClassManifest;Lscala/reflect/ClassManifest;)Z;
const #232 = Asciz	$less$colon$less;
const #233 = Asciz	(Lscala/reflect/ClassManifest;)Z;
const #234 = NameAndType	#232:#233;//  $less$colon$less:(Lscala/reflect/ClassManifest;)Z
const #235 = InterfaceMethod	#115.#234;	//  scala/reflect/ClassManifest.$less$colon$less:(Lscala/reflect/ClassManifest;)Z
const #236 = Asciz	scala/reflect/Manifest$;
const #237 = class	#236;	//  scala/reflect/Manifest$
const #238 = Asciz	Lscala/reflect/Manifest$;;
const #239 = NameAndType	#14:#238;//  MODULE$:Lscala/reflect/Manifest$;
const #240 = Field	#237.#239;	//  scala/reflect/Manifest$.MODULE$:Lscala/reflect/Manifest$;
const #241 = Asciz	AnyVal;
const #242 = Asciz	()Lscala/reflect/Manifest;;
const #243 = NameAndType	#241:#242;//  AnyVal:()Lscala/reflect/Manifest;
const #244 = Method	#237.#243;	//  scala/reflect/Manifest$.AnyVal:()Lscala/reflect/Manifest;
const #245 = Asciz	Nothing;
const #246 = NameAndType	#245:#242;//  Nothing:()Lscala/reflect/Manifest;
const #247 = Method	#237.#246;	//  scala/reflect/Manifest$.Nothing:()Lscala/reflect/Manifest;
const #248 = Asciz	Null;
const #249 = NameAndType	#248:#242;//  Null:()Lscala/reflect/Manifest;
const #250 = Method	#237.#249;	//  scala/reflect/Manifest$.Null:()Lscala/reflect/Manifest;
const #251 = Asciz	scala/reflect/ClassManifest$class;
const #252 = class	#251;	//  scala/reflect/ClassManifest$class
const #253 = NameAndType	#42:#43;//  subtype$1:(Lscala/reflect/ClassManifest;Ljava/lang/Class;Ljava/lang/Class;)Z
const #254 = Method	#252.#253;	//  scala/reflect/ClassManifest$class.subtype$1:(Lscala/reflect/ClassManifest;Ljava/lang/Class;Ljava/lang/Class;)Z
const #255 = NameAndType	#10:#11;//  subargs$1:(Lscala/reflect/ClassManifest;Lscala/collection/immutable/List;Lscala/collection/immutable/List;)Z
const #256 = Method	#252.#255;	//  scala/reflect/ClassManifest$class.subargs$1:(Lscala/reflect/ClassManifest;Lscala/collection/immutable/List;Lscala/collection/immutable/List;)Z
const #257 = Asciz	Scala;
const #258 = Asciz	InnerClasses;
const #259 = Asciz	scala/collection/mutable/ArrayOps;
const #260 = class	#259;	//  scala/collection/mutable/ArrayOps
const #261 = Asciz	ofRef;
const #262 = Asciz	scala/collection/mutable/WrappedArray;
const #263 = class	#262;	//  scala/collection/mutable/WrappedArray
const #264 = Asciz	scala/collection/mutable/ArrayBuilder;
const #265 = class	#264;	//  scala/collection/mutable/ArrayBuilder
const #266 = Asciz	$anonfun$subtype$1$1;
const #267 = Asciz	$anonfun$subargs$1$1;

{
public static void $init$(scala.reflect.ClassManifest);
  Code:
   Stack=0, Locals=1, Args_size=1
   0:	return
  LineNumberTable: 
   line 30: 0

  LocalVariableTable: 
   Start  Length  Slot  Name   Signature
   0      1      0    $this       Lscala/reflect/ClassManifest;


public static final boolean subtype$1(scala.reflect.ClassManifest, java.lang.Class, java.lang.Class);
  Code:
   Stack=5, Locals=9, Args_size=3
   0:	aload_1
   1:	invokevirtual	#49; //Method java/lang/Class.getSuperclass:()Ljava/lang/Class;
   4:	astore	4
   6:	aload_1
   7:	invokevirtual	#53; //Method java/lang/Class.getInterfaces:()[Ljava/lang/Class;
   10:	checkcast	#55; //class "[Ljava/lang/Object;"
   13:	astore_3
   14:	new	#57; //class scala/collection/mutable/ArrayOps$ofRef
   17:	dup
   18:	aload_3
   19:	invokespecial	#60; //Method scala/collection/mutable/ArrayOps$ofRef."<init>":([Ljava/lang/Object;)V
   22:	invokeinterface	#66,  1; //InterfaceMethod scala/collection/TraversableLike.toList:()Lscala/collection/immutable/List;
   27:	astore	6
   29:	aload	4
   31:	dup
   32:	pop
   33:	ifnull	45
   36:	aload	4
   38:	aconst_null
   39:	invokevirtual	#72; //Method java/lang/Object.equals:(Ljava/lang/Object;)Z
   42:	ifeq	51
   45:	getstatic	#77; //Field scala/collection/immutable/Nil$.MODULE$:Lscala/collection/immutable/Nil$;
   48:	goto	78
   51:	getstatic	#82; //Field scala/Predef$.MODULE$:Lscala/Predef$;
   54:	iconst_1
   55:	anewarray	#45; //class java/lang/Class
   58:	dup
   59:	iconst_0
   60:	aload	4
   62:	aastore
   63:	checkcast	#55; //class "[Ljava/lang/Object;"
   66:	invokevirtual	#86; //Method scala/Predef$.wrapRefArray:([Ljava/lang/Object;)Lscala/collection/mutable/WrappedArray;
   69:	astore	5
   71:	aload	5
   73:	invokeinterface	#66,  1; //InterfaceMethod scala/collection/TraversableLike.toList:()Lscala/collection/immutable/List;
   78:	astore	7
   80:	aload	6
   82:	aload	7
   84:	invokevirtual	#92; //Method scala/collection/immutable/List.$colon$colon$colon:(Lscala/collection/immutable/List;)Lscala/collection/immutable/List;
   87:	astore	8
   89:	aload	8
   91:	aload_2
   92:	invokeinterface	#97,  2; //InterfaceMethod scala/collection/SeqLike.contains:(Ljava/lang/Object;)Z
   97:	ifne	119
   100:	aload	8
   102:	new	#99; //class scala/reflect/ClassManifest$$anonfun$subtype$1$1
   105:	dup
   106:	aload_0
   107:	aload_2
   108:	invokespecial	#102; //Method scala/reflect/ClassManifest$$anonfun$subtype$1$1."<init>":(Lscala/reflect/ClassManifest;Ljava/lang/Class;)V
   111:	invokeinterface	#105,  2; //InterfaceMethod scala/collection/LinearSeqLike.exists:(Lscala/Function1;)Z
   116:	ifeq	123
   119:	iconst_1
   120:	goto	124
   123:	iconst_0
   124:	ireturn
  LineNumberTable: 
   line 42: 0
   line 43: 6
   line 45: 29
   line 44: 87
   line 46: 89
   line 41: 124

  LocalVariableTable: 
   Start  Length  Slot  Name   Signature
   0      125      0    $this       Lscala/reflect/ClassManifest;
   0      125      1    sub       Ljava/lang/Class;
   0      125      2    sup$1       Ljava/lang/Class;
   6      119      4    subSuperClass       Ljava/lang/Class;
   29      96      6    subSuperInterfaces       Lscala/collection/immutable/List;
   89      36      8    subSuper       Lscala/collection/immutable/List;


public static java.lang.String argString(scala.reflect.ClassManifest);
  Code:
   Stack=4, Locals=1, Args_size=1
   0:	aload_0
   1:	invokeinterface	#118,  1; //InterfaceMethod scala/reflect/ClassManifest.typeArguments:()Lscala/collection/immutable/List;
   6:	invokeinterface	#122,  1; //InterfaceMethod scala/collection/TraversableLike.nonEmpty:()Z
   11:	ifeq	34
   14:	aload_0
   15:	invokeinterface	#118,  1; //InterfaceMethod scala/reflect/ClassManifest.typeArguments:()Lscala/collection/immutable/List;
   20:	ldc	#124; //String [
   22:	ldc	#126; //String , 
   24:	ldc	#128; //String ]
   26:	invokeinterface	#132,  4; //InterfaceMethod scala/collection/TraversableLike.mkString:(Ljava/lang/String;Ljava/lang/String;Ljava/lang/String;)Ljava/lang/String;
   31:	goto	89
   34:	aload_0
   35:	invokeinterface	#135,  1; //InterfaceMethod scala/reflect/ClassManifest.erasure:()Ljava/lang/Class;
   40:	invokevirtual	#138; //Method java/lang/Class.isArray:()Z
   43:	ifeq	87
   46:	new	#140; //class scala/collection/mutable/StringBuilder
   49:	dup
   50:	invokespecial	#143; //Method scala/collection/mutable/StringBuilder."<init>":()V
   53:	ldc	#124; //String [
   55:	invokevirtual	#147; //Method scala/collection/mutable/StringBuilder.append:(Ljava/lang/Object;)Lscala/collection/mutable/StringBuilder;
   58:	getstatic	#152; //Field scala/reflect/ClassManifest$.MODULE$:Lscala/reflect/ClassManifest$;
   61:	aload_0
   62:	invokeinterface	#135,  1; //InterfaceMethod scala/reflect/ClassManifest.erasure:()Ljava/lang/Class;
   67:	invokevirtual	#155; //Method java/lang/Class.getComponentType:()Ljava/lang/Class;
   70:	invokevirtual	#159; //Method scala/reflect/ClassManifest$.fromClass:(Ljava/lang/Class;)Lscala/reflect/ClassManifest;
   73:	invokevirtual	#147; //Method scala/collection/mutable/StringBuilder.append:(Ljava/lang/Object;)Lscala/collection/mutable/StringBuilder;
   76:	ldc	#128; //String ]
   78:	invokevirtual	#147; //Method scala/collection/mutable/StringBuilder.append:(Ljava/lang/Object;)Lscala/collection/mutable/StringBuilder;
   81:	invokevirtual	#163; //Method scala/collection/mutable/StringBuilder.toString:()Ljava/lang/String;
   84:	goto	89
   87:	ldc	#165; //String 
   89:	areturn
  LineNumberTable: 
   line 122: 0
   line 123: 34
   line 124: 87
   line 122: 89

  LocalVariableTable: 
   Start  Length  Slot  Name   Signature
   0      90      0    $this       Lscala/reflect/ClassManifest;


public static scala.collection.immutable.List typeArguments(scala.reflect.ClassManifest);
  Code:
   Stack=1, Locals=1, Args_size=1
   0:	getstatic	#77; //Field scala/collection/immutable/Nil$.MODULE$:Lscala/collection/immutable/Nil$;
   3:	areturn
  LineNumberTable: 
   line 119: 0

  LocalVariableTable: 
   Start  Length  Slot  Name   Signature
   0      4      0    $this       Lscala/reflect/ClassManifest;


public static scala.collection.mutable.ArrayBuilder newArrayBuilder(scala.reflect.ClassManifest);
  Code:
   Stack=3, Locals=1, Args_size=1
   0:	new	#170; //class scala/collection/mutable/ArrayBuilder$ofRef
   3:	dup
   4:	aload_0
   5:	invokespecial	#171; //Method scala/collection/mutable/ArrayBuilder$ofRef."<init>":(Lscala/reflect/ClassManifest;)V
   8:	areturn
  LineNumberTable: 
   line 117: 0

  LocalVariableTable: 
   Start  Length  Slot  Name   Signature
   0      9      0    $this       Lscala/reflect/ClassManifest;


public static scala.collection.mutable.WrappedArray newWrappedArray(scala.reflect.ClassManifest, int);
  Code:
   Stack=4, Locals=2, Args_size=2
   0:	new	#175; //class scala/collection/mutable/WrappedArray$ofRef
   3:	dup
   4:	aload_0
   5:	iload_1
   6:	invokeinterface	#179,  2; //InterfaceMethod scala/reflect/ClassManifest.newArray:(I)Ljava/lang/Object;
   11:	checkcast	#55; //class "[Ljava/lang/Object;"
   14:	invokespecial	#180; //Method scala/collection/mutable/WrappedArray$ofRef."<init>":([Ljava/lang/Object;)V
   17:	areturn
  LineNumberTable: 
   line 113: 0

  LocalVariableTable: 
   Start  Length  Slot  Name   Signature
   0      18      0    $this       Lscala/reflect/ClassManifest;
   0      18      1    len       I


public static java.lang.Object[][][][] newArray5(scala.reflect.ClassManifest, int);
  Code:
   Stack=5, Locals=2, Args_size=2
   0:	aload_0
   1:	aload_0
   2:	aload_0
   3:	aload_0
   4:	aload_0
   5:	invokeinterface	#135,  1; //InterfaceMethod scala/reflect/ClassManifest.erasure:()Ljava/lang/Class;
   10:	invokeinterface	#188,  2; //InterfaceMethod scala/reflect/ClassManifest.arrayClass:(Ljava/lang/Class;)Ljava/lang/Class;
   15:	invokeinterface	#188,  2; //InterfaceMethod scala/reflect/ClassManifest.arrayClass:(Ljava/lang/Class;)Ljava/lang/Class;
   20:	invokeinterface	#188,  2; //InterfaceMethod scala/reflect/ClassManifest.arrayClass:(Ljava/lang/Class;)Ljava/lang/Class;
   25:	invokeinterface	#188,  2; //InterfaceMethod scala/reflect/ClassManifest.arrayClass:(Ljava/lang/Class;)Ljava/lang/Class;
   30:	iload_1
   31:	invokestatic	#194; //Method java/lang/reflect/Array.newInstance:(Ljava/lang/Class;I)Ljava/lang/Object;
   34:	checkcast	#196; //class "[[[[Ljava/lang/Object;"
   37:	areturn
  LineNumberTable: 
   line 108: 0

  LocalVariableTable: 
   Start  Length  Slot  Name   Signature
   0      38      0    $this       Lscala/reflect/ClassManifest;
   0      38      1    len       I


public static java.lang.Object[][][] newArray4(scala.reflect.ClassManifest, int);
  Code:
   Stack=4, Locals=2, Args_size=2
   0:	aload_0
   1:	aload_0
   2:	aload_0
   3:	aload_0
   4:	invokeinterface	#135,  1; //InterfaceMethod scala/reflect/ClassManifest.erasure:()Ljava/lang/Class;
   9:	invokeinterface	#188,  2; //InterfaceMethod scala/reflect/ClassManifest.arrayClass:(Ljava/lang/Class;)Ljava/lang/Class;
   14:	invokeinterface	#188,  2; //InterfaceMethod scala/reflect/ClassManifest.arrayClass:(Ljava/lang/Class;)Ljava/lang/Class;
   19:	invokeinterface	#188,  2; //InterfaceMethod scala/reflect/ClassManifest.arrayClass:(Ljava/lang/Class;)Ljava/lang/Class;
   24:	iload_1
   25:	invokestatic	#194; //Method java/lang/reflect/Array.newInstance:(Ljava/lang/Class;I)Ljava/lang/Object;
   28:	checkcast	#200; //class "[[[Ljava/lang/Object;"
   31:	areturn
  LineNumberTable: 
   line 104: 0

  LocalVariableTable: 
   Start  Length  Slot  Name   Signature
   0      32      0    $this       Lscala/reflect/ClassManifest;
   0      32      1    len       I


public static java.lang.Object[][] newArray3(scala.reflect.ClassManifest, int);
  Code:
   Stack=3, Locals=2, Args_size=2
   0:	aload_0
   1:	aload_0
   2:	aload_0
   3:	invokeinterface	#135,  1; //InterfaceMethod scala/reflect/ClassManifest.erasure:()Ljava/lang/Class;
   8:	invokeinterface	#188,  2; //InterfaceMethod scala/reflect/ClassManifest.arrayClass:(Ljava/lang/Class;)Ljava/lang/Class;
   13:	invokeinterface	#188,  2; //InterfaceMethod scala/reflect/ClassManifest.arrayClass:(Ljava/lang/Class;)Ljava/lang/Class;
   18:	iload_1
   19:	invokestatic	#194; //Method java/lang/reflect/Array.newInstance:(Ljava/lang/Class;I)Ljava/lang/Object;
   22:	checkcast	#204; //class "[[Ljava/lang/Object;"
   25:	areturn
  LineNumberTable: 
   line 100: 0

  LocalVariableTable: 
   Start  Length  Slot  Name   Signature
   0      26      0    $this       Lscala/reflect/ClassManifest;
   0      26      1    len       I


public static java.lang.Object[] newArray2(scala.reflect.ClassManifest, int);
  Code:
   Stack=2, Locals=2, Args_size=2
   0:	aload_0
   1:	aload_0
   2:	invokeinterface	#135,  1; //InterfaceMethod scala/reflect/ClassManifest.erasure:()Ljava/lang/Class;
   7:	invokeinterface	#188,  2; //InterfaceMethod scala/reflect/ClassManifest.arrayClass:(Ljava/lang/Class;)Ljava/lang/Class;
   12:	iload_1
   13:	invokestatic	#194; //Method java/lang/reflect/Array.newInstance:(Ljava/lang/Class;I)Ljava/lang/Object;
   16:	checkcast	#55; //class "[Ljava/lang/Object;"
   19:	areturn
  LineNumberTable: 
   line 96: 0

  LocalVariableTable: 
   Start  Length  Slot  Name   Signature
   0      20      0    $this       Lscala/reflect/ClassManifest;
   0      20      1    len       I


public static java.lang.Object newArray(scala.reflect.ClassManifest, int);
  Code:
   Stack=2, Locals=2, Args_size=2
   0:	aload_0
   1:	invokeinterface	#135,  1; //InterfaceMethod scala/reflect/ClassManifest.erasure:()Ljava/lang/Class;
   6:	iload_1
   7:	invokestatic	#194; //Method java/lang/reflect/Array.newInstance:(Ljava/lang/Class;I)Ljava/lang/Object;
   10:	areturn
  LineNumberTable: 
   line 93: 0

  LocalVariableTable: 
   Start  Length  Slot  Name   Signature
   0      11      0    $this       Lscala/reflect/ClassManifest;
   0      11      1    len       I


public static scala.reflect.ClassManifest arrayManifest(scala.reflect.ClassManifest);
  Code:
   Stack=3, Locals=1, Args_size=1
   0:	getstatic	#152; //Field scala/reflect/ClassManifest$.MODULE$:Lscala/reflect/ClassManifest$;
   3:	aload_0
   4:	aload_0
   5:	invokeinterface	#135,  1; //InterfaceMethod scala/reflect/ClassManifest.erasure:()Ljava/lang/Class;
   10:	invokeinterface	#188,  2; //InterfaceMethod scala/reflect/ClassManifest.arrayClass:(Ljava/lang/Class;)Ljava/lang/Class;
   15:	invokevirtual	#212; //Method scala/reflect/ClassManifest$.classType:(Ljava/lang/Class;)Lscala/reflect/ClassManifest;
   18:	areturn
  LineNumberTable: 
   line 90: 0

  LocalVariableTable: 
   Start  Length  Slot  Name   Signature
   0      19      0    $this       Lscala/reflect/ClassManifest;


public static java.lang.Class arrayClass(scala.reflect.ClassManifest, java.lang.Class);
  Code:
   Stack=2, Locals=2, Args_size=2
   0:	aload_1
   1:	iconst_0
   2:	invokestatic	#194; //Method java/lang/reflect/Array.newInstance:(Ljava/lang/Class;I)Ljava/lang/Object;
   5:	invokevirtual	#216; //Method java/lang/Object.getClass:()Ljava/lang/Class;
   8:	areturn
  LineNumberTable: 
   line 87: 0

  LocalVariableTable: 
   Start  Length  Slot  Name   Signature
   0      9      0    $this       Lscala/reflect/ClassManifest;
   0      9      1    tp       Ljava/lang/Class;


public static boolean equals(scala.reflect.ClassManifest, java.lang.Object);
  Code:
   Stack=3, Locals=4, Args_size=2
   0:	aload_1
   1:	instanceof	#220; //class scala/reflect/AnyValManifest
   4:	ifeq	27
   7:	iconst_1
   8:	ifeq	15
   11:	iconst_0
   12:	goto	100
   15:	new	#222; //class scala/MatchError
   18:	dup
   19:	aload_1
   20:	invokevirtual	#223; //Method java/lang/Object.toString:()Ljava/lang/String;
   23:	invokespecial	#226; //Method scala/MatchError."<init>":(Ljava/lang/String;)V
   26:	athrow
   27:	aload_1
   28:	instanceof	#115; //class scala/reflect/ClassManifest
   31:	ifeq	95
   34:	aload_1
   35:	checkcast	#115; //class scala/reflect/ClassManifest
   38:	astore_2
   39:	iconst_1
   40:	ifeq	83
   43:	aload_0
   44:	invokeinterface	#135,  1; //InterfaceMethod scala/reflect/ClassManifest.erasure:()Ljava/lang/Class;
   49:	aload_2
   50:	invokeinterface	#135,  1; //InterfaceMethod scala/reflect/ClassManifest.erasure:()Ljava/lang/Class;
   55:	astore_3
   56:	dup
   57:	ifnonnull	68
   60:	pop
   61:	aload_3
   62:	ifnull	75
   65:	goto	79
   68:	aload_3
   69:	invokevirtual	#72; //Method java/lang/Object.equals:(Ljava/lang/Object;)Z
   72:	ifeq	79
   75:	iconst_1
   76:	goto	100
   79:	iconst_0
   80:	goto	100
   83:	new	#222; //class scala/MatchError
   86:	dup
   87:	aload_1
   88:	invokevirtual	#223; //Method java/lang/Object.toString:()Ljava/lang/String;
   91:	invokespecial	#226; //Method scala/MatchError."<init>":(Ljava/lang/String;)V
   94:	athrow
   95:	iconst_1
   96:	ifeq	101
   99:	iconst_0
   100:	ireturn
   101:	new	#222; //class scala/MatchError
   104:	dup
   105:	aload_1
   106:	invokevirtual	#223; //Method java/lang/Object.toString:()Ljava/lang/String;
   109:	invokespecial	#226; //Method scala/MatchError."<init>":(Ljava/lang/String;)V
   112:	athrow
  LineNumberTable: 
   line 80: 0
   line 21: 7
   line 81: 11
   line 80: 15
   line 21: 39
   line 82: 43
   line 80: 83
   line 21: 95
   line 83: 99
   line 80: 100

  LocalVariableTable: 
   Start  Length  Slot  Name   Signature
   0      113      0    $this       Lscala/reflect/ClassManifest;
   0      113      1    that       Ljava/lang/Object;
   39      56      2    temp12       Lscala/reflect/ClassManifest;


public static boolean $greater$colon$greater(scala.reflect.ClassManifest, scala.reflect.ClassManifest);
  Code:
   Stack=2, Locals=2, Args_size=2
   0:	aload_1
   1:	aload_0
   2:	invokeinterface	#235,  2; //InterfaceMethod scala/reflect/ClassManifest.$less$colon$less:(Lscala/reflect/ClassManifest;)Z
   7:	ireturn
  LineNumberTable: 
   line 74: 0

  LocalVariableTable: 
   Start  Length  Slot  Name   Signature
   0      8      0    $this       Lscala/reflect/ClassManifest;
   0      8      1    that       Lscala/reflect/ClassManifest;


public static boolean $less$colon$less(scala.reflect.ClassManifest, scala.reflect.ClassManifest);
  Code:
   Stack=3, Locals=6, Args_size=2
   0:	aload_1
   1:	instanceof	#220; //class scala/reflect/AnyValManifest
   4:	ifeq	27
   7:	iconst_1
   8:	ifeq	15
   11:	iconst_0
   12:	goto	253
   15:	new	#222; //class scala/MatchError
   18:	dup
   19:	aload_1
   20:	invokevirtual	#223; //Method java/lang/Object.toString:()Ljava/lang/String;
   23:	invokespecial	#226; //Method scala/MatchError."<init>":(Ljava/lang/String;)V
   26:	athrow
   27:	aload_1
   28:	getstatic	#240; //Field scala/reflect/Manifest$.MODULE$:Lscala/reflect/Manifest$;
   31:	invokevirtual	#244; //Method scala/reflect/Manifest$.AnyVal:()Lscala/reflect/Manifest;
   34:	astore_2
   35:	dup
   36:	ifnonnull	47
   39:	pop
   40:	aload_2
   41:	ifnull	54
   44:	goto	74
   47:	aload_2
   48:	invokevirtual	#72; //Method java/lang/Object.equals:(Ljava/lang/Object;)Z
   51:	ifeq	74
   54:	iconst_1
   55:	ifeq	62
   58:	iconst_0
   59:	goto	253
   62:	new	#222; //class scala/MatchError
   65:	dup
   66:	aload_1
   67:	invokevirtual	#223; //Method java/lang/Object.toString:()Ljava/lang/String;
   70:	invokespecial	#226; //Method scala/MatchError."<init>":(Ljava/lang/String;)V
   73:	athrow
   74:	aload_1
   75:	getstatic	#240; //Field scala/reflect/Manifest$.MODULE$:Lscala/reflect/Manifest$;
   78:	invokevirtual	#247; //Method scala/reflect/Manifest$.Nothing:()Lscala/reflect/Manifest;
   81:	astore_3
   82:	dup
   83:	ifnonnull	94
   86:	pop
   87:	aload_3
   88:	ifnull	101
   91:	goto	121
   94:	aload_3
   95:	invokevirtual	#72; //Method java/lang/Object.equals:(Ljava/lang/Object;)Z
   98:	ifeq	121
   101:	iconst_1
   102:	ifeq	109
   105:	iconst_0
   106:	goto	253
   109:	new	#222; //class scala/MatchError
   112:	dup
   113:	aload_1
   114:	invokevirtual	#223; //Method java/lang/Object.toString:()Ljava/lang/String;
   117:	invokespecial	#226; //Method scala/MatchError."<init>":(Ljava/lang/String;)V
   120:	athrow
   121:	aload_1
   122:	getstatic	#240; //Field scala/reflect/Manifest$.MODULE$:Lscala/reflect/Manifest$;
   125:	invokevirtual	#250; //Method scala/reflect/Manifest$.Null:()Lscala/reflect/Manifest;
   128:	astore	4
   130:	dup
   131:	ifnonnull	143
   134:	pop
   135:	aload	4
   137:	ifnull	151
   140:	goto	171
   143:	aload	4
   145:	invokevirtual	#72; //Method java/lang/Object.equals:(Ljava/lang/Object;)Z
   148:	ifeq	171
   151:	iconst_1
   152:	ifeq	159
   155:	iconst_0
   156:	goto	253
   159:	new	#222; //class scala/MatchError
   162:	dup
   163:	aload_1
   164:	invokevirtual	#223; //Method java/lang/Object.toString:()Ljava/lang/String;
   167:	invokespecial	#226; //Method scala/MatchError."<init>":(Ljava/lang/String;)V
   170:	athrow
   171:	iconst_1
   172:	ifeq	254
   175:	aload_0
   176:	invokeinterface	#135,  1; //InterfaceMethod scala/reflect/ClassManifest.erasure:()Ljava/lang/Class;
   181:	aload_1
   182:	invokeinterface	#135,  1; //InterfaceMethod scala/reflect/ClassManifest.erasure:()Ljava/lang/Class;
   187:	astore	5
   189:	dup
   190:	ifnonnull	202
   193:	pop
   194:	aload	5
   196:	ifnull	229
   199:	goto	210
   202:	aload	5
   204:	invokevirtual	#72; //Method java/lang/Object.equals:(Ljava/lang/Object;)Z
   207:	ifne	229
   210:	aload_0
   211:	aload_0
   212:	invokeinterface	#135,  1; //InterfaceMethod scala/reflect/ClassManifest.erasure:()Ljava/lang/Class;
   217:	aload_1
   218:	invokeinterface	#135,  1; //InterfaceMethod scala/reflect/ClassManifest.erasure:()Ljava/lang/Class;
   223:	invokestatic	#254; //Method subtype$1:(Lscala/reflect/ClassManifest;Ljava/lang/Class;Ljava/lang/Class;)Z
   226:	ifeq	252
   229:	aload_0
   230:	aload_0
   231:	invokeinterface	#118,  1; //InterfaceMethod scala/reflect/ClassManifest.typeArguments:()Lscala/collection/immutable/List;
   236:	aload_1
   237:	invokeinterface	#118,  1; //InterfaceMethod scala/reflect/ClassManifest.typeArguments:()Lscala/collection/immutable/List;
   242:	invokestatic	#256; //Method subargs$1:(Lscala/reflect/ClassManifest;Lscala/collection/immutable/List;Lscala/collection/immutable/List;)Z
   245:	ifeq	252
   248:	iconst_1
   249:	goto	253
   252:	iconst_0
   253:	ireturn
   254:	new	#222; //class scala/MatchError
   257:	dup
   258:	aload_1
   259:	invokevirtual	#223; //Method java/lang/Object.toString:()Ljava/lang/String;
   262:	invokespecial	#226; //Method scala/MatchError."<init>":(Ljava/lang/String;)V
   265:	athrow
  LineNumberTable: 
   line 58: 0
   line 21: 7
   line 60: 11
   line 58: 15
   line 21: 54
   line 62: 58
   line 58: 62
   line 21: 101
   line 62: 105
   line 58: 109
   line 21: 151
   line 62: 155
   line 58: 159
   line 21: 171
   line 64: 175
   line 65: 229
   line 64: 248
   line 58: 253

  LocalVariableTable: 
   Start  Length  Slot  Name   Signature
   0      266      0    $this       Lscala/reflect/ClassManifest;
   0      266      1    that       Lscala/reflect/ClassManifest;


}

