Compiled from "ClassManifest.scala"
public final class scala.reflect.ClassManifest$$anonfun$subargs$1$1 extends java.lang.Object implements scala.Function1,scala.ScalaObject,java.io.Serializable
  SourceFile: "ClassManifest.scala"
  Scala: length = 0x
   
  InnerClass: 
   public final #102= #9 of #57; //$anonfun$subargs$1$1=class scala/reflect/ClassManifest$$anonfun$subargs$1$1 of class scala/reflect/ClassManifest
  minor version: 0
  major version: 49
  Constant pool:
const #1 = Asciz	SourceFile;
const #2 = Asciz	ClassManifest.scala;
const #3 = Asciz	<clinit>;
const #4 = Asciz	()V;
const #5 = Asciz	Code;
const #6 = Asciz	serialVersionUID;
const #7 = Asciz	J;
const #8 = Asciz	scala/reflect/ClassManifest$$anonfun$subargs$1$1;
const #9 = class	#8;	//  scala/reflect/ClassManifest$$anonfun$subargs$1$1
const #10 = NameAndType	#6:#7;//  serialVersionUID:J
const #11 = Field	#9.#10;	//  scala/reflect/ClassManifest$$anonfun$subargs$1$1.serialVersionUID:J
const #12 = Asciz	<init>;
const #13 = Asciz	(Lscala/reflect/ClassManifest;)V;
const #14 = Asciz	LineNumberTable;
const #15 = Asciz	java/lang/Object;
const #16 = class	#15;	//  java/lang/Object
const #17 = NameAndType	#12:#4;//  "<init>":()V
const #18 = Method	#16.#17;	//  java/lang/Object."<init>":()V
const #19 = Asciz	scala/Function1$class;
const #20 = class	#19;	//  scala/Function1$class
const #21 = Asciz	$init$;
const #22 = Asciz	(Lscala/Function1;)V;
const #23 = NameAndType	#21:#22;//  $init$:(Lscala/Function1;)V
const #24 = Method	#20.#23;	//  scala/Function1$class.$init$:(Lscala/Function1;)V
const #25 = Asciz	this;
const #26 = Asciz	Lscala/reflect/ClassManifest$$anonfun$subargs$1$1;;
const #27 = Asciz	$outer;
const #28 = Asciz	Lscala/reflect/ClassManifest;;
const #29 = Asciz	LocalVariableTable;
const #30 = Asciz	(Lscala/reflect/ClassManifest<TT;>;)V;
const #31 = Asciz	Signature;
const #32 = Asciz	apply;
const #33 = Asciz	(Ljava/lang/Object;)Ljava/lang/Object;;
const #34 = Asciz	scala/Tuple2;
const #35 = class	#34;	//  scala/Tuple2
const #36 = Asciz	(Lscala/Tuple2;)Z;
const #37 = NameAndType	#32:#36;//  apply:(Lscala/Tuple2;)Z
const #38 = Method	#9.#37;	//  scala/reflect/ClassManifest$$anonfun$subargs$1$1.apply:(Lscala/Tuple2;)Z
const #39 = Asciz	scala/runtime/BoxesRunTime;
const #40 = class	#39;	//  scala/runtime/BoxesRunTime
const #41 = Asciz	boxToBoolean;
const #42 = Asciz	(Z)Ljava/lang/Boolean;;
const #43 = NameAndType	#41:#42;//  boxToBoolean:(Z)Ljava/lang/Boolean;
const #44 = Method	#40.#43;	//  scala/runtime/BoxesRunTime.boxToBoolean:(Z)Ljava/lang/Boolean;
const #45 = Asciz	v1;
const #46 = Asciz	Ljava/lang/Object;;
const #47 = Asciz	_1;
const #48 = Asciz	()Ljava/lang/Object;;
const #49 = NameAndType	#47:#48;//  _1:()Ljava/lang/Object;
const #50 = Method	#35.#49;	//  scala/Tuple2._1:()Ljava/lang/Object;
const #51 = Asciz	scala/reflect/OptManifest;
const #52 = class	#51;	//  scala/reflect/OptManifest
const #53 = Asciz	_2;
const #54 = NameAndType	#53:#48;//  _2:()Ljava/lang/Object;
const #55 = Method	#35.#54;	//  scala/Tuple2._2:()Ljava/lang/Object;
const #56 = Asciz	scala/reflect/ClassManifest;
const #57 = class	#56;	//  scala/reflect/ClassManifest
const #58 = Asciz	$less$colon$less;
const #59 = Asciz	(Lscala/reflect/ClassManifest;)Z;
const #60 = NameAndType	#58:#59;//  $less$colon$less:(Lscala/reflect/ClassManifest;)Z
const #61 = InterfaceMethod	#57.#60;	//  scala/reflect/ClassManifest.$less$colon$less:(Lscala/reflect/ClassManifest;)Z
const #62 = Asciz	scala/MatchError;
const #63 = class	#62;	//  scala/MatchError
const #64 = Asciz	toString;
const #65 = Asciz	()Ljava/lang/String;;
const #66 = NameAndType	#64:#65;//  toString:()Ljava/lang/String;
const #67 = Method	#35.#66;	//  scala/Tuple2.toString:()Ljava/lang/String;
const #68 = Asciz	(Ljava/lang/String;)V;
const #69 = NameAndType	#12:#68;//  "<init>":(Ljava/lang/String;)V
const #70 = Method	#63.#69;	//  scala/MatchError."<init>":(Ljava/lang/String;)V
const #71 = Asciz	scala/reflect/NoManifest$;
const #72 = class	#71;	//  scala/reflect/NoManifest$
const #73 = Asciz	MODULE$;
const #74 = Asciz	Lscala/reflect/NoManifest$;;
const #75 = NameAndType	#73:#74;//  MODULE$:Lscala/reflect/NoManifest$;
const #76 = Field	#72.#75;	//  scala/reflect/NoManifest$.MODULE$:Lscala/reflect/NoManifest$;
const #77 = Asciz	equals;
const #78 = Asciz	(Ljava/lang/Object;)Z;
const #79 = NameAndType	#77:#78;//  equals:(Ljava/lang/Object;)Z
const #80 = Method	#16.#79;	//  java/lang/Object.equals:(Ljava/lang/Object;)Z
const #81 = Asciz	temp4;
const #82 = Asciz	temp5;
const #83 = Asciz	temp2;
const #84 = Asciz	Lscala/reflect/OptManifest;;
const #85 = Asciz	temp3;
const #86 = Asciz	(Lscala/Tuple2<Lscala/reflect/OptManifest<*>;Lscala/reflect/OptManifest<*>;>;)Z;
const #87 = Asciz	andThen;
const #88 = Asciz	(Lscala/Function1;)Lscala/Function1;;
const #89 = Asciz	(Lscala/Function1;Lscala/Function1;)Lscala/Function1;;
const #90 = NameAndType	#87:#89;//  andThen:(Lscala/Function1;Lscala/Function1;)Lscala/Function1;
const #91 = Method	#20.#90;	//  scala/Function1$class.andThen:(Lscala/Function1;Lscala/Function1;)Lscala/Function1;
const #92 = Asciz	g;
const #93 = Asciz	Lscala/Function1;;
const #94 = Asciz	compose;
const #95 = NameAndType	#94:#89;//  compose:(Lscala/Function1;Lscala/Function1;)Lscala/Function1;
const #96 = Method	#20.#95;	//  scala/Function1$class.compose:(Lscala/Function1;Lscala/Function1;)Lscala/Function1;
const #97 = Asciz	(Lscala/Function1;)Ljava/lang/String;;
const #98 = NameAndType	#64:#97;//  toString:(Lscala/Function1;)Ljava/lang/String;
const #99 = Method	#20.#98;	//  scala/Function1$class.toString:(Lscala/Function1;)Ljava/lang/String;
const #100 = Asciz	Scala;
const #101 = Asciz	InnerClasses;
const #102 = Asciz	$anonfun$subargs$1$1;
const #103 = Asciz	scala/Function1;
const #104 = class	#103;	//  scala/Function1
const #105 = Asciz	scala/ScalaObject;
const #106 = class	#105;	//  scala/ScalaObject
const #107 = Asciz	java/io/Serializable;
const #108 = class	#107;	//  java/io/Serializable

{
public static final long serialVersionUID;

public static {};
  Code:
   Stack=2, Locals=0, Args_size=0
   0:	lconst_0
   1:	putstatic	#11; //Field serialVersionUID:J
   4:	return

public scala.reflect.ClassManifest$$anonfun$subargs$1$1(scala.reflect.ClassManifest);
  Code:
   Stack=1, Locals=2, Args_size=2
   0:	aload_0
   1:	invokespecial	#18; //Method java/lang/Object."<init>":()V
   4:	aload_0
   5:	invokestatic	#24; //Method scala/Function1$class.$init$:(Lscala/Function1;)V
   8:	return
  LineNumberTable: 
   line 49: 0

  LocalVariableTable: 
   Start  Length  Slot  Name   Signature
   0      9      0    this       Lscala/reflect/ClassManifest$$anonfun$subargs$1$1;
   0      9      1    $outer       Lscala/reflect/ClassManifest;

  Signature: length = 0x2
   00 1E 

public final java.lang.Object apply(java.lang.Object);
  Code:
   Stack=2, Locals=3, Args_size=2
   0:	aload_0
   1:	aload_1
   2:	checkcast	#35; //class scala/Tuple2
   5:	invokevirtual	#38; //Method apply:(Lscala/Tuple2;)Z
   8:	istore_2
   9:	iload_2
   10:	invokestatic	#44; //Method scala/runtime/BoxesRunTime.boxToBoolean:(Z)Ljava/lang/Boolean;
   13:	areturn
  LineNumberTable: 
   line 49: 0

  LocalVariableTable: 
   Start  Length  Slot  Name   Signature
   0      14      0    this       Lscala/reflect/ClassManifest$$anonfun$subargs$1$1;
   0      14      1    v1       Ljava/lang/Object;


public final boolean apply(scala.Tuple2);
  Code:
   Stack=3, Locals=6, Args_size=2
   0:	aload_1
   1:	ifnull	204
   4:	aload_1
   5:	invokevirtual	#50; //Method scala/Tuple2._1:()Ljava/lang/Object;
   8:	checkcast	#52; //class scala/reflect/OptManifest
   11:	astore	4
   13:	aload_1
   14:	invokevirtual	#55; //Method scala/Tuple2._2:()Ljava/lang/Object;
   17:	checkcast	#52; //class scala/reflect/OptManifest
   20:	astore	5
   22:	aload	4
   24:	instanceof	#57; //class scala/reflect/ClassManifest
   27:	ifeq	96
   30:	aload	4
   32:	checkcast	#57; //class scala/reflect/ClassManifest
   35:	astore_2
   36:	aload	5
   38:	instanceof	#57; //class scala/reflect/ClassManifest
   41:	ifeq	76
   44:	aload	5
   46:	checkcast	#57; //class scala/reflect/ClassManifest
   49:	astore_3
   50:	iconst_1
   51:	ifeq	64
   54:	aload_2
   55:	aload_3
   56:	invokeinterface	#61,  2; //InterfaceMethod scala/reflect/ClassManifest.$less$colon$less:(Lscala/reflect/ClassManifest;)Z
   61:	goto	209
   64:	new	#63; //class scala/MatchError
   67:	dup
   68:	aload_1
   69:	invokevirtual	#67; //Method scala/Tuple2.toString:()Ljava/lang/String;
   72:	invokespecial	#70; //Method scala/MatchError."<init>":(Ljava/lang/String;)V
   75:	athrow
   76:	iconst_1
   77:	ifeq	84
   80:	iconst_0
   81:	goto	209
   84:	new	#63; //class scala/MatchError
   87:	dup
   88:	aload_1
   89:	invokevirtual	#67; //Method scala/Tuple2.toString:()Ljava/lang/String;
   92:	invokespecial	#70; //Method scala/MatchError."<init>":(Ljava/lang/String;)V
   95:	athrow
   96:	getstatic	#76; //Field scala/reflect/NoManifest$.MODULE$:Lscala/reflect/NoManifest$;
   99:	dup
   100:	ifnonnull	112
   103:	pop
   104:	aload	4
   106:	ifnull	120
   109:	goto	184
   112:	aload	4
   114:	invokevirtual	#80; //Method java/lang/Object.equals:(Ljava/lang/Object;)Z
   117:	ifeq	184
   120:	getstatic	#76; //Field scala/reflect/NoManifest$.MODULE$:Lscala/reflect/NoManifest$;
   123:	dup
   124:	ifnonnull	136
   127:	pop
   128:	aload	5
   130:	ifnull	144
   133:	goto	164
   136:	aload	5
   138:	invokevirtual	#80; //Method java/lang/Object.equals:(Ljava/lang/Object;)Z
   141:	ifeq	164
   144:	iconst_1
   145:	ifeq	152
   148:	iconst_1
   149:	goto	209
   152:	new	#63; //class scala/MatchError
   155:	dup
   156:	aload_1
   157:	invokevirtual	#67; //Method scala/Tuple2.toString:()Ljava/lang/String;
   160:	invokespecial	#70; //Method scala/MatchError."<init>":(Ljava/lang/String;)V
   163:	athrow
   164:	iconst_1
   165:	ifeq	172
   168:	iconst_0
   169:	goto	209
   172:	new	#63; //class scala/MatchError
   175:	dup
   176:	aload_1
   177:	invokevirtual	#67; //Method scala/Tuple2.toString:()Ljava/lang/String;
   180:	invokespecial	#70; //Method scala/MatchError."<init>":(Ljava/lang/String;)V
   183:	athrow
   184:	iconst_1
   185:	ifeq	192
   188:	iconst_0
   189:	goto	209
   192:	new	#63; //class scala/MatchError
   195:	dup
   196:	aload_1
   197:	invokevirtual	#67; //Method scala/Tuple2.toString:()Ljava/lang/String;
   200:	invokespecial	#70; //Method scala/MatchError."<init>":(Ljava/lang/String;)V
   203:	athrow
   204:	iconst_1
   205:	ifeq	210
   208:	iconst_0
   209:	ireturn
   210:	new	#63; //class scala/MatchError
   213:	dup
   214:	aload_1
   215:	invokevirtual	#67; //Method scala/Tuple2.toString:()Ljava/lang/String;
   218:	invokespecial	#70; //Method scala/MatchError."<init>":(Ljava/lang/String;)V
   221:	athrow
  LineNumberTable: 
   line 49: 0
   line 21: 50
   line 50: 54
   line 49: 64
   line 21: 76
   line 52: 80
   line 49: 84
   line 21: 144
   line 51: 148
   line 49: 152
   line 21: 164
   line 52: 168
   line 49: 172
   line 21: 184
   line 52: 188
   line 49: 192
   line 21: 204
   line 52: 208
   line 49: 209

  LocalVariableTable: 
   Start  Length  Slot  Name   Signature
   0      222      0    this       Lscala/reflect/ClassManifest$$anonfun$subargs$1$1;
   36      60      2    temp4       Lscala/reflect/ClassManifest;
   50      26      3    temp5       Lscala/reflect/ClassManifest;
   13      191      4    temp2       Lscala/reflect/OptManifest;
   22      182      5    temp3       Lscala/reflect/OptManifest;

  Signature: length = 0x2
   00 56 

public scala.Function1 andThen(scala.Function1);
  Code:
   Stack=2, Locals=2, Args_size=2
   0:	aload_0
   1:	aload_1
   2:	invokestatic	#91; //Method scala/Function1$class.andThen:(Lscala/Function1;Lscala/Function1;)Lscala/Function1;
   5:	areturn
  LineNumberTable: 
   line 49: 0

  LocalVariableTable: 
   Start  Length  Slot  Name   Signature
   0      6      0    this       Lscala/reflect/ClassManifest$$anonfun$subargs$1$1;
   0      6      1    g       Lscala/Function1;


public scala.Function1 compose(scala.Function1);
  Code:
   Stack=2, Locals=2, Args_size=2
   0:	aload_0
   1:	aload_1
   2:	invokestatic	#96; //Method scala/Function1$class.compose:(Lscala/Function1;Lscala/Function1;)Lscala/Function1;
   5:	areturn
  LineNumberTable: 
   line 49: 0

  LocalVariableTable: 
   Start  Length  Slot  Name   Signature
   0      6      0    this       Lscala/reflect/ClassManifest$$anonfun$subargs$1$1;
   0      6      1    g       Lscala/Function1;


public java.lang.String toString();
  Code:
   Stack=1, Locals=1, Args_size=1
   0:	aload_0
   1:	invokestatic	#99; //Method scala/Function1$class.toString:(Lscala/Function1;)Ljava/lang/String;
   4:	areturn
  LineNumberTable: 
   line 49: 0


}

