Compiled from "Code.scala"
public final class scala.reflect.Code$ extends java.lang.Object implements scala.ScalaObject
  SourceFile: "Code.scala"
  Scala: length = 0x
   
  minor version: 0
  major version: 49
  Constant pool:
const #1 = Asciz	SourceFile;
const #2 = Asciz	Code.scala;
const #3 = Asciz	Scala;
const #4 = Asciz	MODULE$;
const #5 = Asciz	Lscala/reflect/Code$;;
const #6 = Asciz	<clinit>;
const #7 = Asciz	()V;
const #8 = Asciz	Code;
const #9 = Asciz	scala/reflect/Code$;
const #10 = class	#9;	//  scala/reflect/Code$
const #11 = Asciz	<init>;
const #12 = NameAndType	#11:#7;//  "<init>":()V
const #13 = Method	#10.#12;	//  scala/reflect/Code$."<init>":()V
const #14 = Asciz	LineNumberTable;
const #15 = Asciz	java/lang/Object;
const #16 = class	#15;	//  java/lang/Object
const #17 = Method	#16.#12;	//  java/lang/Object."<init>":()V
const #18 = NameAndType	#4:#5;//  MODULE$:Lscala/reflect/Code$;
const #19 = Field	#10.#18;	//  scala/reflect/Code$.MODULE$:Lscala/reflect/Code$;
const #20 = Asciz	lift;
const #21 = Asciz	(Ljava/lang/Object;)Lscala/reflect/Code;;
const #22 = Asciz	java/lang/Error;
const #23 = class	#22;	//  java/lang/Error
const #24 = Asciz	Code was not lifted by compiler;
const #25 = String	#24;	//  Code was not lifted by compiler
const #26 = Asciz	(Ljava/lang/String;)V;
const #27 = NameAndType	#11:#26;//  "<init>":(Ljava/lang/String;)V
const #28 = Method	#23.#27;	//  java/lang/Error."<init>":(Ljava/lang/String;)V
const #29 = Asciz	this;
const #30 = Asciz	tree;
const #31 = Asciz	Ljava/lang/Object;;
const #32 = Asciz	LocalVariableTable;
const #33 = Asciz	<A:Ljava/lang/Object;>(TA;)Lscala/reflect/Code<TA;>;;
const #34 = Asciz	Signature;
const #35 = Asciz	scala/ScalaObject;
const #36 = class	#35;	//  scala/ScalaObject

{
public static final scala.reflect.Code$ MODULE$;

public static {};
  Code:
   Stack=1, Locals=0, Args_size=0
   0:	new	#10; //class scala/reflect/Code$
   3:	invokespecial	#13; //Method "<init>":()V
   6:	return

public scala.reflect.Code lift(java.lang.Object);
  Code:
   Stack=3, Locals=2, Args_size=2
   0:	new	#23; //class java/lang/Error
   3:	dup
   4:	ldc	#25; //String Code was not lifted by compiler
   6:	invokespecial	#28; //Method java/lang/Error."<init>":(Ljava/lang/String;)V
   9:	athrow
  LineNumberTable: 
   line 22: 0

  LocalVariableTable: 
   Start  Length  Slot  Name   Signature
   0      10      0    this       Lscala/reflect/Code$;
   0      10      1    tree       Ljava/lang/Object;

  Signature: length = 0x2
   00 21 

}

