Compiled from "Tree.scala"
public final class scala.reflect.DefDef$ extends java.lang.Object implements scala.Function4,scala.ScalaObject
  SourceFile: "Tree.scala"
  Scala: length = 0x
   
  minor version: 0
  major version: 49
  Constant pool:
Asciz	SourceFile;
Asciz	Tree.scala;
Asciz	MODULE$;
Asciz	Lscala/reflect/DefDef$;;
Asciz	<clinit>;
Asciz	()V;
Asciz	Code;
Asciz	scala/reflect/DefDef$;
class	scala/reflect/DefDef$
Asciz	<init>;
NameAndType	"<init>":()V
Method	scala/reflect/DefDef$."<init>":()V
Asciz	toString;
Asciz	()Ljava/lang/String;;
Asciz	LineNumberTable;
Asciz	scala/Function4$class;
class	scala/Function4$class
Asciz	(Lscala/Function4;)Ljava/lang/String;;
NameAndType	toString:(Lscala/Function4;)Ljava/lang/String;
Method	scala/Function4$class.toString:(Lscala/Function4;)Ljava/lang/String;
Asciz	curried;
Asciz	()Lscala/Function1;;
Asciz	(Lscala/Function4;)Lscala/Function1;;
NameAndType	curried:(Lscala/Function4;)Lscala/Function1;
Method	scala/Function4$class.curried:(Lscala/Function4;)Lscala/Function1;
Asciz	curry;
NameAndType	curry:(Lscala/Function4;)Lscala/Function1;
Method	scala/Function4$class.curry:(Lscala/Function4;)Lscala/Function1;
Asciz	Deprecated;
Asciz	tupled;
NameAndType	tupled:(Lscala/Function4;)Lscala/Function1;
Method	scala/Function4$class.tupled:(Lscala/Function4;)Lscala/Function1;
Asciz	unapply;
Asciz	(Lscala/reflect/DefDef;)Lscala/Option;;
Asciz	scala/None$;
class	scala/None$
Asciz	Lscala/None$;;
NameAndType	MODULE$:Lscala/None$;
Field	scala/None$.MODULE$:Lscala/None$;
Asciz	scala/Some;
class	scala/Some
Asciz	scala/Tuple4;
class	scala/Tuple4
Asciz	scala/reflect/DefDef;
class	scala/reflect/DefDef
Asciz	sym;
Asciz	()Lscala/reflect/Symbol;;
NameAndType	sym:()Lscala/reflect/Symbol;
Method	scala/reflect/DefDef.sym:()Lscala/reflect/Symbol;
Asciz	vparamss;
Asciz	()Lscala/collection/immutable/List;;
NameAndType	vparamss:()Lscala/collection/immutable/List;
Method	scala/reflect/DefDef.vparamss:()Lscala/collection/immutable/List;
Asciz	ret;
Asciz	()Lscala/reflect/Type;;
NameAndType	ret:()Lscala/reflect/Type;
Method	scala/reflect/DefDef.ret:()Lscala/reflect/Type;
Asciz	rhs;
Asciz	()Lscala/reflect/Tree;;
NameAndType	rhs:()Lscala/reflect/Tree;
Method	scala/reflect/DefDef.rhs:()Lscala/reflect/Tree;
Asciz	(Ljava/lang/Object;Ljava/lang/Object;Ljava/lang/Object;Ljava/lang/Object;)V;
NameAndType	"<init>":(Ljava/lang/Object;Ljava/lang/Object;Ljava/lang/Object;Ljava/lang/Object;)V
Method	scala/Tuple4."<init>":(Ljava/lang/Object;Ljava/lang/Object;Ljava/lang/Object;Ljava/lang/Object;)V
Asciz	(Ljava/lang/Object;)V;
NameAndType	"<init>":(Ljava/lang/Object;)V
Method	scala/Some."<init>":(Ljava/lang/Object;)V
Asciz	this;
Asciz	x$0;
Asciz	Lscala/reflect/DefDef;;
Asciz	LocalVariableTable;
Asciz	apply;
Asciz	(Lscala/reflect/Symbol;Lscala/collection/immutable/List;Lscala/reflect/Type;Lscala/reflect/Tree;)Lscala/reflect/DefDef;;
Asciz	(Lscala/reflect/Symbol;Lscala/collection/immutable/List;Lscala/reflect/Type;Lscala/reflect/Tree;)V;
NameAndType	"<init>":(Lscala/reflect/Symbol;Lscala/collection/immutable/List;Lscala/reflect/Type;Lscala/reflect/Tree;)V
Method	scala/reflect/DefDef."<init>":(Lscala/reflect/Symbol;Lscala/collection/immutable/List;Lscala/reflect/Type;Lscala/reflect/Tree;)V
Asciz	Lscala/reflect/Symbol;;
Asciz	Lscala/collection/immutable/List;;
Asciz	Lscala/reflect/Type;;
Asciz	Lscala/reflect/Tree;;
Asciz	(Ljava/lang/Object;Ljava/lang/Object;Ljava/lang/Object;Ljava/lang/Object;)Ljava/lang/Object;;
Asciz	scala/reflect/Symbol;
class	scala/reflect/Symbol
Asciz	scala/collection/immutable/List;
class	scala/collection/immutable/List
Asciz	scala/reflect/Type;
class	scala/reflect/Type
Asciz	scala/reflect/Tree;
class	scala/reflect/Tree
NameAndType	apply:(Lscala/reflect/Symbol;Lscala/collection/immutable/List;Lscala/reflect/Type;Lscala/reflect/Tree;)Lscala/reflect/DefDef;
Method	scala/reflect/DefDef$.apply:(Lscala/reflect/Symbol;Lscala/collection/immutable/List;Lscala/reflect/Type;Lscala/reflect/Tree;)Lscala/reflect/DefDef;
Asciz	v1;
Asciz	Ljava/lang/Object;;
Asciz	v2;
Asciz	v3;
Asciz	v4;
Asciz	java/lang/Object;
class	java/lang/Object
Method	java/lang/Object."<init>":()V
NameAndType	MODULE$:Lscala/reflect/DefDef$;
Field	scala/reflect/DefDef$.MODULE$:Lscala/reflect/DefDef$;
Asciz	$init$;
Asciz	(Lscala/Function4;)V;
NameAndType	$init$:(Lscala/Function4;)V
Method	scala/Function4$class.$init$:(Lscala/Function4;)V
Asciz	Scala;
Asciz	scala/Function4;
class	scala/Function4
Asciz	scala/ScalaObject;
class	scala/ScalaObject

{
public static final scala.reflect.DefDef$ MODULE$;
  Signature: Lscala/reflect/DefDef$;

public static {};
  Signature: ()V
  Code:
   Stack=1, Locals=0, Args_size=0
	new	class scala/reflect/DefDef$
	invokespecial	Method "<init>":()V
	return
  Labels:

public java.lang.String toString();
  Signature: ()Ljava/lang/String;
  Code:
   Stack=1, Locals=1, Args_size=1
	aload_0
	invokestatic	Method scala/Function4$class.toString:(Lscala/Function4;)Ljava/lang/String;
	areturn
  Labels:

public scala.Function1 curried();
  Signature: ()Lscala/Function1;
  Code:
   Stack=1, Locals=1, Args_size=1
	aload_0
	invokestatic	Method scala/Function4$class.curried:(Lscala/Function4;)Lscala/Function1;
	areturn
  Labels:

public scala.Function1 curry();
  Signature: ()Lscala/Function1;
  Code:
   Stack=1, Locals=1, Args_size=1
	aload_0
	invokestatic	Method scala/Function4$class.curry:(Lscala/Function4;)Lscala/Function1;
	areturn
  Labels:
  Deprecated: true

public scala.Function1 tupled();
  Signature: ()Lscala/Function1;
  Code:
   Stack=1, Locals=1, Args_size=1
	aload_0
	invokestatic	Method scala/Function4$class.tupled:(Lscala/Function4;)Lscala/Function1;
	areturn
  Labels:

public scala.Option unapply(scala.reflect.DefDef);
  Signature: (Lscala/reflect/DefDef;)Lscala/Option;
  Code:
   Stack=8, Locals=2, Args_size=2
	aload_1
	ifnonnull	l1 // new
	getstatic	Field scala/None$.MODULE$:Lscala/None$;
	goto	l2 // areturn
l1	new	class scala/Some
	dup
	new	class scala/Tuple4
	dup
	aload_1
	invokevirtual	Method scala/reflect/DefDef.sym:()Lscala/reflect/Symbol;
	aload_1
	invokevirtual	Method scala/reflect/DefDef.vparamss:()Lscala/collection/immutable/List;
	aload_1
	invokevirtual	Method scala/reflect/DefDef.ret:()Lscala/reflect/Type;
	aload_1
	invokevirtual	Method scala/reflect/DefDef.rhs:()Lscala/reflect/Tree;
	invokespecial	Method scala/Tuple4."<init>":(Ljava/lang/Object;Ljava/lang/Object;Ljava/lang/Object;Ljava/lang/Object;)V
	invokespecial	Method scala/Some."<init>":(Ljava/lang/Object;)V
l2	areturn
  Labels:
   	l1 = 10 // new
   	l2 = 40 // areturn
  LocalVariableTable: 
   Start  Length  Slot  Name   Signature
   0      41      0    this       Lscala/reflect/DefDef$;
   0      41      1    x$0       Lscala/reflect/DefDef;


public scala.reflect.DefDef apply(scala.reflect.Symbol, scala.collection.immutable.List, scala.reflect.Type, scala.reflect.Tree);
  Signature: (Lscala/reflect/Symbol;Lscala/collection/immutable/List;Lscala/reflect/Type;Lscala/reflect/Tree;)Lscala/reflect/DefDef;
  Code:
   Stack=6, Locals=5, Args_size=5
	new	class scala/reflect/DefDef
	dup
	aload_1
	aload_2
	aload_3
	aload	4
	invokespecial	Method scala/reflect/DefDef."<init>":(Lscala/reflect/Symbol;Lscala/collection/immutable/List;Lscala/reflect/Type;Lscala/reflect/Tree;)V
	areturn
  Labels:
  LocalVariableTable: 
   Start  Length  Slot  Name   Signature
   0      13      0    this       Lscala/reflect/DefDef$;
   0      13      1    sym       Lscala/reflect/Symbol;
   0      13      2    vparamss       Lscala/collection/immutable/List;
   0      13      3    ret       Lscala/reflect/Type;
   0      13      4    rhs       Lscala/reflect/Tree;


public java.lang.Object apply(java.lang.Object, java.lang.Object, java.lang.Object, java.lang.Object);
  Signature: (Ljava/lang/Object;Ljava/lang/Object;Ljava/lang/Object;Ljava/lang/Object;)Ljava/lang/Object;
  Code:
   Stack=5, Locals=5, Args_size=5
	aload_0
	aload_1
	checkcast	class scala/reflect/Symbol
	aload_2
	checkcast	class scala/collection/immutable/List
	aload_3
	checkcast	class scala/reflect/Type
	aload	4
	checkcast	class scala/reflect/Tree
	invokevirtual	Method apply:(Lscala/reflect/Symbol;Lscala/collection/immutable/List;Lscala/reflect/Type;Lscala/reflect/Tree;)Lscala/reflect/DefDef;
	areturn
  Labels:
  LocalVariableTable: 
   Start  Length  Slot  Name   Signature
   0      22      0    this       Lscala/reflect/DefDef$;
   0      22      1    v1       Ljava/lang/Object;
   0      22      2    v2       Ljava/lang/Object;
   0      22      3    v3       Ljava/lang/Object;
   0      22      4    v4       Ljava/lang/Object;


private scala.reflect.DefDef$();
  Signature: ()V
  Code:
   Stack=1, Locals=1, Args_size=1
	aload_0
	invokespecial	Method java/lang/Object."<init>":()V
	aload_0
	putstatic	Field MODULE$:Lscala/reflect/DefDef$;
	aload_0
	invokestatic	Method scala/Function4$class.$init$:(Lscala/Function4;)V
	return
  Labels:

}

