Compiled from "Tree.scala"
public class scala.reflect.DefDef extends scala.reflect.Tree implements scala.ScalaObject,scala.Product,java.io.Serializable
  SourceFile: "Tree.scala"
  ScalaSig: length = 0x4E5
   05 00 FFFFFF81 31 06 08 01 02 FFFFFF84 FFFFFF80 FFFFFF80 FFFFFF80 40 07 02 06
   44 65 66 44 65 66 0A 02 03 04 01 07 72 65 66 6C
   65 63 74 0A 01 05 01 05 73 63 61 6C 61 03 00 13
   04 00 08 0C 10 10 02 09 0A 0D 01 02 09 02 0B 02
   02 04 54 72 65 65 10 02 0D 0E 0D 01 04 09 02 0F
   04 02 0B 53 63 61 6C 61 4F 62 6A 65 63 74 10 02
   0D 11 09 02 12 04 02 07 50 72 6F 64 75 63 74 08
   08 14 00 FFFFFF82 FFFFFFCA FFFFFF80 FFFFFF84 00 15 01 03 73 79 6D 15 01
   16 10 02 09 17 09 02 18 02 02 06 53 79 6D 62 6F
   6C 08 08 1A 00 FFFFFF82 FFFFFF88 FFFFFFA0 FFFFFF80 04 16 01 04 73 79 6D
   20 08 08 1C 00 FFFFFF82 FFFFFFCA FFFFFF80 FFFFFF84 00 1D 01 08 76 70 61
   72 61 6D 73 73 15 01 1E 10 03 1F 24 26 0D 01 20
   0A 02 21 22 01 09 69 6D 6D 75 74 61 62 6C 65 0A
   02 23 04 01 0A 63 6F 6C 6C 65 63 74 69 6F 6E 09
   02 25 20 02 04 4C 69 73 74 10 03 1F 24 08 08 08
   28 00 FFFFFF82 FFFFFF88 FFFFFFA0 FFFFFF80 04 1E 01 09 76 70 61 72 61 6D
   73 73 20 08 08 2A 00 FFFFFF82 FFFFFFCA FFFFFF80 FFFFFF84 00 2B 01 03 72
   65 74 15 01 2C 10 02 09 2D 09 02 2E 02 02 04 54
   79 70 65 08 08 30 00 FFFFFF82 FFFFFF88 FFFFFFA0 FFFFFF80 04 2C 01 04 72
   65 74 20 08 08 32 00 FFFFFF82 FFFFFFCA FFFFFF80 FFFFFF84 00 33 01 03 72
   68 73 15 01 08 08 08 35 00 FFFFFF82 FFFFFF88 FFFFFFA0 FFFFFF80 04 08 01
   04 72 68 73 20 08 05 37 00 FFFFFF84 00 38 01 06 3C 69
   6E 69 74 3E 14 05 39 3A 3B 3C 3D 10 02 09 00 08
   05 14 36 FFFFFFC0 00 16 08 05 1C 36 FFFFFFC0 00 1E 08 05 2A
   36 FFFFFFC0 00 2C 08 05 32 36 FFFFFFC0 00 08 08 07 3F 00 FFFFFF81
   FFFFFF80 FFFFFF84 00 40 01 04 63 6F 70 79 14 05 39 41 4F 54
   59 08 08 42 14 3E FFFFFF90 FFFFFF80 FFFFFFC0 00 16 08 07 43 00 FFFFFF91
   FFFFFF80 FFFFFF84 00 44 01 0E 63 6F 70 79 24 64 65 66 61 75
   6C 74 24 31 15 01 45 2A 02 16 46 2B 01 47 10 02
   48 4D 0D 01 49 0A 02 4A 4B 01 09 75 6E 63 68 65
   63 6B 65 64 0A 02 4C 04 01 0A 61 6E 6E 6F 74 61
   74 69 6F 6E 09 02 4E 49 02 11 75 6E 63 68 65 63
   6B 65 64 56 61 72 69 61 6E 63 65 08 08 50 1C 3E
   FFFFFF90 FFFFFF80 FFFFFFC0 00 1E 08 07 51 00 FFFFFF91 FFFFFF80 FFFFFF84 00 52 01 0E
   63 6F 70 79 24 64 65 66 61 75 6C 74 24 32 15 01
   53 2A 02 1E 46 08 08 55 2A 3E FFFFFF90 FFFFFF80 FFFFFFC0 00 2C 08
   07 56 00 FFFFFF91 FFFFFF80 FFFFFF84 00 57 01 0E 63 6F 70 79 24 64
   65 66 61 75 6C 74 24 33 15 01 58 2A 02 2C 46 08
   08 5A 32 3E FFFFFF90 FFFFFF80 FFFFFFC0 00 08 08 07 5B 00 FFFFFF91 FFFFFF80 FFFFFF84
   00 5C 01 0E 63 6F 70 79 24 64 65 66 61 75 6C 74
   24 34 15 01 5D 2A 02 08 46 08 08 5F 00 FFFFFF84 FFFFFF80 FFFFFF80
   FFFFFF84 20 60 01 08 68 61 73 68 43 6F 64 65 14 01 61
   10 02 0D 62 09 02 63 04 02 03 49 6E 74 08 08 65
   00 FFFFFF84 FFFFFF80 FFFFFF80 FFFFFF84 20 66 01 08 74 6F 53 74 72 69 6E
   67 14 01 67 10 02 68 6B 0E 02 0D 69 09 02 6A 04
   01 06 50 72 65 64 65 66 09 02 6C 6D 02 06 53 74
   72 69 6E 67 0A 02 6A 04 08 08 6F 00 FFFFFF84 FFFFFF80 FFFFFF80 FFFFFF84
   20 70 01 06 65 71 75 61 6C 73 14 02 71 74 10 02
   0D 72 09 02 73 04 02 07 42 6F 6F 6C 65 61 6E 08
   07 75 6E FFFFFF81 FFFFFF80 FFFFFFC0 00 76 01 03 78 24 31 10 02 0D
   77 09 02 78 04 02 03 41 6E 79 08 08 7A 00 FFFFFF84 FFFFFF80
   FFFFFF80 FFFFFF84 20 7B 01 0D 70 72 6F 64 75 63 74 50 72 65
   66 69 78 15 01 7C 10 03 7D FFFFFF81 02 0D 01 7E 0A 03
   7F FFFFFF81 00 01 04 6C 61 6E 67 0A 02 FFFFFF81 01 01 04 6A
   61 76 61 09 02 6C 7E 08 0A FFFFFF81 04 00 FFFFFF84 FFFFFF80 FFFFFF80 FFFFFF84
   20 FFFFFF81 05 01 0C 70 72 6F 64 75 63 74 41 72 69 74
   79 15 01 61 08 0A FFFFFF81 07 00 FFFFFF84 FFFFFF80 FFFFFF80 FFFFFF84 20 FFFFFF81 08
   01 0E 70 72 6F 64 75 63 74 45 6C 65 6D 65 6E 74
   14 03 76 FFFFFF81 09 08 08 75 FFFFFF81 06 FFFFFF81 FFFFFF80 FFFFFFC0 00 61 08
   0A FFFFFF81 0B 00 FFFFFF84 FFFFFF80 FFFFFF80 FFFFFF84 20 FFFFFF81 0C 01 08 63 61 6E
   45 71 75 61 6C 14 03 71 FFFFFF81 0D 08 08 75 FFFFFF81 0A FFFFFF81
   FFFFFF80 FFFFFFC0 00 76 28 03 00 FFFFFF81 0F 10 03 0D FFFFFF81 10 09 03
   FFFFFF81 11 04 02 0C 73 65 72 69 61 6C 69 7A 61 62 6C
   65 07 09 FFFFFF81 13 02 FFFFFF81 FFFFFF80 FFFFFF88 02 FFFFFF81 14 01 06 44 65
   66 44 65 66 10 03 09 FFFFFF81 15 06 09 01 02 FFFFFF84 FFFFFF81 FFFFFF80
   FFFFFF88 02 FFFFFF81 16 13 07 FFFFFF81 15 FFFFFF81 17 FFFFFF81 1A 0C 10 03 7D
   FFFFFF81 18 09 03 FFFFFF81 19 7E 02 06 4F 62 6A 65 63 74 10
   08 0D FFFFFF81 1B 16 1E 2C 08 39 09 03 FFFFFF81 1C 04 02 09
   46 75 6E 63 74 69 6F 6E 34 08 07 37 FFFFFF81 15 FFFFFF84 00
   FFFFFF81 1E 14 02 FFFFFF81 14 08 0A FFFFFF81 20 FFFFFF81 15 FFFFFF81 FFFFFF80 FFFFFF84 40
   FFFFFF81 21 01 05 61 70 70 6C 79 14 09 39 FFFFFF81 22 FFFFFF81 23
   FFFFFF81 24 FFFFFF81 25 08 06 14 FFFFFF81 1F FFFFFFC0 00 16 08 06 1C FFFFFF81
   1F FFFFFFC0 00 1E 08 06 2A FFFFFF81 1F FFFFFFC0 00 2C 08 06 32 FFFFFF81
   1F FFFFFFC0 00 08 08 0A FFFFFF81 27 FFFFFF81 15 FFFFFF81 FFFFFF80 FFFFFF84 40 FFFFFF81 28
   01 07 75 6E 61 70 70 6C 79 14 04 FFFFFF81 29 FFFFFF81 2F 10
   05 0D FFFFFF81 2A FFFFFF81 2C 09 03 FFFFFF81 2B 04 02 04 53 6F 6D
   65 10 07 0D FFFFFF81 2D 16 1E 2C 08 09 03 FFFFFF81 2E 04 02
   06 54 75 70 6C 65 34 08 07 FFFFFF81 30 FFFFFF81 26 FFFFFFC0 00 39
   01 03 78 24 30 
  minor version: 0
  major version: 49
  Constant pool:
Asciz	SourceFile;
Asciz	Tree.scala;
Asciz	curry;
Asciz	()Lscala/Function1;;
Asciz	Code;
Asciz	scala/reflect/DefDef$;
class	scala/reflect/DefDef$
Asciz	MODULE$;
Asciz	Lscala/reflect/DefDef$;;
NameAndType	MODULE$:Lscala/reflect/DefDef$;
Field	scala/reflect/DefDef$.MODULE$:Lscala/reflect/DefDef$;
NameAndType	curry:()Lscala/Function1;
Method	scala/reflect/DefDef$.curry:()Lscala/Function1;
Asciz	rhs;
Asciz	Lscala/reflect/Tree;;
Asciz	ret;
Asciz	Lscala/reflect/Type;;
Asciz	vparamss;
Asciz	Lscala/collection/immutable/List;;
Asciz	Lscala/collection/immutable/List<Lscala/collection/immutable/List<Lscala/reflect/Tree;>;>;;
Asciz	Signature;
Asciz	sym;
Asciz	Lscala/reflect/Symbol;;
Asciz	<init>;
Asciz	(Lscala/reflect/Symbol;Lscala/collection/immutable/List;Lscala/reflect/Type;Lscala/reflect/Tree;)V;
Asciz	LineNumberTable;
Asciz	scala/reflect/DefDef;
class	scala/reflect/DefDef
NameAndType	sym:Lscala/reflect/Symbol;
Field	scala/reflect/DefDef.sym:Lscala/reflect/Symbol;
NameAndType	vparamss:Lscala/collection/immutable/List;
Field	scala/reflect/DefDef.vparamss:Lscala/collection/immutable/List;
NameAndType	ret:Lscala/reflect/Type;
Field	scala/reflect/DefDef.ret:Lscala/reflect/Type;
NameAndType	rhs:Lscala/reflect/Tree;
Field	scala/reflect/DefDef.rhs:Lscala/reflect/Tree;
Asciz	scala/reflect/Tree;
class	scala/reflect/Tree
Asciz	()V;
NameAndType	"<init>":()V
Method	scala/reflect/Tree."<init>":()V
Asciz	scala/Product$class;
class	scala/Product$class
Asciz	$init$;
Asciz	(Lscala/Product;)V;
NameAndType	$init$:(Lscala/Product;)V
Method	scala/Product$class.$init$:(Lscala/Product;)V
Asciz	this;
Asciz	Lscala/reflect/DefDef;;
Asciz	LocalVariableTable;
Asciz	(Lscala/reflect/Symbol;Lscala/collection/immutable/List<Lscala/collection/immutable/List<Lscala/reflect/Tree;>;>;Lscala/reflect/Type;Lscala/reflect/Tree;)V;
Asciz	gd16$1;
Asciz	(Lscala/reflect/Symbol;Lscala/collection/immutable/List;Lscala/reflect/Type;Lscala/reflect/Tree;)Z;
Asciz	()Lscala/reflect/Symbol;;
NameAndType	sym:()Lscala/reflect/Symbol;
Method	scala/reflect/DefDef.sym:()Lscala/reflect/Symbol;
Asciz	java/lang/Object;
class	java/lang/Object
Asciz	equals;
Asciz	(Ljava/lang/Object;)Z;
NameAndType	equals:(Ljava/lang/Object;)Z
Method	java/lang/Object.equals:(Ljava/lang/Object;)Z
Asciz	()Lscala/collection/immutable/List;;
NameAndType	vparamss:()Lscala/collection/immutable/List;
Method	scala/reflect/DefDef.vparamss:()Lscala/collection/immutable/List;
Asciz	()Lscala/reflect/Type;;
NameAndType	ret:()Lscala/reflect/Type;
Method	scala/reflect/DefDef.ret:()Lscala/reflect/Type;
Asciz	()Lscala/reflect/Tree;;
NameAndType	rhs:()Lscala/reflect/Tree;
Method	scala/reflect/DefDef.rhs:()Lscala/reflect/Tree;
Asciz	canEqual;
Asciz	productElement;
Asciz	(I)Ljava/lang/Object;;
Asciz	java/lang/IndexOutOfBoundsException;
class	java/lang/IndexOutOfBoundsException
Asciz	scala/runtime/BoxesRunTime;
class	scala/runtime/BoxesRunTime
Asciz	boxToInteger;
Asciz	(I)Ljava/lang/Integer;;
NameAndType	boxToInteger:(I)Ljava/lang/Integer;
Method	scala/runtime/BoxesRunTime.boxToInteger:(I)Ljava/lang/Integer;
Asciz	toString;
Asciz	()Ljava/lang/String;;
NameAndType	toString:()Ljava/lang/String;
Method	java/lang/Object.toString:()Ljava/lang/String;
Asciz	(Ljava/lang/String;)V;
NameAndType	"<init>":(Ljava/lang/String;)V
Method	java/lang/IndexOutOfBoundsException."<init>":(Ljava/lang/String;)V
Asciz	scala/MatchError;
class	scala/MatchError
Method	scala/MatchError."<init>":(Ljava/lang/String;)V
Asciz	productArity;
Asciz	()I;
Asciz	productPrefix;
Asciz	DefDef;
String	DefDef
NameAndType	gd16$1:(Lscala/reflect/Symbol;Lscala/collection/immutable/List;Lscala/reflect/Type;Lscala/reflect/Tree;)Z
Method	scala/reflect/DefDef.gd16$1:(Lscala/reflect/Symbol;Lscala/collection/immutable/List;Lscala/reflect/Type;Lscala/reflect/Tree;)Z
Asciz	scala/Equals;
class	scala/Equals
NameAndType	canEqual:(Ljava/lang/Object;)Z
InterfaceMethod	scala/Equals.canEqual:(Ljava/lang/Object;)Z
Asciz	temp74;
Asciz	temp75;
Asciz	temp76;
Asciz	temp77;
Asciz	temp78;
Asciz	scala/runtime/ScalaRunTime$;
class	scala/runtime/ScalaRunTime$
Asciz	Lscala/runtime/ScalaRunTime$;;
NameAndType	MODULE$:Lscala/runtime/ScalaRunTime$;
Field	scala/runtime/ScalaRunTime$.MODULE$:Lscala/runtime/ScalaRunTime$;
Asciz	_toString;
Asciz	(Lscala/Product;)Ljava/lang/String;;
NameAndType	_toString:(Lscala/Product;)Ljava/lang/String;
Method	scala/runtime/ScalaRunTime$._toString:(Lscala/Product;)Ljava/lang/String;
Asciz	hashCode;
Asciz	_hashCode;
Asciz	(Lscala/Product;)I;
NameAndType	_hashCode:(Lscala/Product;)I
Method	scala/runtime/ScalaRunTime$._hashCode:(Lscala/Product;)I
Asciz	copy;
Asciz	(Lscala/reflect/Symbol;Lscala/collection/immutable/List;Lscala/reflect/Type;Lscala/reflect/Tree;)Lscala/reflect/DefDef;;
NameAndType	"<init>":(Lscala/reflect/Symbol;Lscala/collection/immutable/List;Lscala/reflect/Type;Lscala/reflect/Tree;)V
Method	scala/reflect/DefDef."<init>":(Lscala/reflect/Symbol;Lscala/collection/immutable/List;Lscala/reflect/Type;Lscala/reflect/Tree;)V
Asciz	()Lscala/collection/immutable/List<Lscala/collection/immutable/List<Lscala/reflect/Tree;>;>;;
Asciz	copy$default$1;
Asciz	copy$default$2;
Asciz	copy$default$3;
Asciz	copy$default$4;
Asciz	productElements;
Asciz	()Lscala/collection/Iterator;;
Asciz	(Lscala/Product;)Lscala/collection/Iterator;;
NameAndType	productElements:(Lscala/Product;)Lscala/collection/Iterator;
Method	scala/Product$class.productElements:(Lscala/Product;)Lscala/collection/Iterator;
Asciz	productIterator;
NameAndType	productIterator:(Lscala/Product;)Lscala/collection/Iterator;
Method	scala/Product$class.productIterator:(Lscala/Product;)Lscala/collection/Iterator;
Asciz	ScalaSig;
Asciz	scala/ScalaObject;
class	scala/ScalaObject
Asciz	scala/Product;
class	scala/Product
Asciz	java/io/Serializable;
class	java/io/Serializable

{
private final scala.reflect.Tree rhs;
  Signature: Lscala/reflect/Tree;

private final scala.reflect.Type ret;
  Signature: Lscala/reflect/Type;

private final scala.collection.immutable.List vparamss;
  Signature: Lscala/collection/immutable/List;
  Signature: length = 0x2
   00 14 

private final scala.reflect.Symbol sym;
  Signature: Lscala/reflect/Symbol;

public static final scala.Function1 curry();
  Signature: ()Lscala/Function1;
  Code:
   Stack=1, Locals=0, Args_size=0
	getstatic	Field scala/reflect/DefDef$.MODULE$:Lscala/reflect/DefDef$;
	invokevirtual	Method scala/reflect/DefDef$.curry:()Lscala/Function1;
	areturn
  Labels:

public scala.reflect.DefDef(scala.reflect.Symbol, scala.collection.immutable.List, scala.reflect.Type, scala.reflect.Tree);
  Signature: (Lscala/reflect/Symbol;Lscala/collection/immutable/List;Lscala/reflect/Type;Lscala/reflect/Tree;)V
  Code:
   Stack=2, Locals=5, Args_size=5
	aload_0
	aload_1
	putfield	Field sym:Lscala/reflect/Symbol;
	aload_0
	aload_2
	putfield	Field vparamss:Lscala/collection/immutable/List;
	aload_0
	aload_3
	putfield	Field ret:Lscala/reflect/Type;
	aload_0
	aload	4
	putfield	Field rhs:Lscala/reflect/Tree;
	aload_0
	invokespecial	Method scala/reflect/Tree."<init>":()V
	aload_0
	invokestatic	Method scala/Product$class.$init$:(Lscala/Product;)V
	return
  Labels:
  LocalVariableTable: 
   Start  Length  Slot  Name   Signature
   0      30      0    this       Lscala/reflect/DefDef;
   0      30      1    sym       Lscala/reflect/Symbol;
   0      30      2    vparamss       Lscala/collection/immutable/List;
   0      30      3    ret       Lscala/reflect/Type;
   0      30      4    rhs       Lscala/reflect/Tree;

  Signature: length = 0x2
   00 33 

private final boolean gd16$1(scala.reflect.Symbol, scala.collection.immutable.List, scala.reflect.Type, scala.reflect.Tree);
  Signature: (Lscala/reflect/Symbol;Lscala/collection/immutable/List;Lscala/reflect/Type;Lscala/reflect/Tree;)Z
  Code:
   Stack=2, Locals=9, Args_size=5
	aload_1
	aload_0
	invokevirtual	Method sym:()Lscala/reflect/Symbol;
	astore	5
	dup
	ifnonnull	l1 // aload
	pop
	aload	5
	ifnull	l2 // aload_2
	goto	l3 // iconst_0
l1	aload	5
	invokevirtual	Method java/lang/Object.equals:(Ljava/lang/Object;)Z
	ifeq	l3 // iconst_0
l2	aload_2
	aload_0
	invokevirtual	Method vparamss:()Lscala/collection/immutable/List;
	astore	6
	dup
	ifnonnull	l4 // aload
	pop
	aload	6
	ifnull	l5 // aload_3
	goto	l3 // iconst_0
l4	aload	6
	invokevirtual	Method java/lang/Object.equals:(Ljava/lang/Object;)Z
	ifeq	l3 // iconst_0
l5	aload_3
	aload_0
	invokevirtual	Method ret:()Lscala/reflect/Type;
	astore	7
	dup
	ifnonnull	l6 // aload
	pop
	aload	7
	ifnull	l7 // aload
	goto	l3 // iconst_0
l6	aload	7
	invokevirtual	Method java/lang/Object.equals:(Ljava/lang/Object;)Z
	ifeq	l3 // iconst_0
l7	aload	4
	aload_0
	invokevirtual	Method rhs:()Lscala/reflect/Tree;
	astore	8
	dup
	ifnonnull	l8 // aload
	pop
	aload	8
	ifnull	l9 // iconst_1
	goto	l3 // iconst_0
l8	aload	8
	invokevirtual	Method java/lang/Object.equals:(Ljava/lang/Object;)Z
	ifeq	l3 // iconst_0
l9	iconst_1
	goto	l10 // ireturn
l3	iconst_0
l10	ireturn
  Labels:
   	l1 = 20 // aload
   	l2 = 28 // aload_2
   	l4 = 48 // aload
   	l5 = 56 // aload_3
   	l6 = 76 // aload
   	l7 = 84 // aload
   	l8 = 105 // aload
   	l9 = 113 // iconst_1
   	l3 = 117 // iconst_0
   	l10 = 118 // ireturn

public boolean canEqual(java.lang.Object);
  Signature: (Ljava/lang/Object;)Z
  Code:
   Stack=1, Locals=2, Args_size=2
	aload_1
	instanceof	class scala/reflect/DefDef
	ireturn
  Labels:

public java.lang.Object productElement(int);
  Signature: (I)Ljava/lang/Object;
  Code:
   Stack=3, Locals=2, Args_size=2
	iload_1
	tableswitch{ //0 to 3
		0: 144;
		1: 118;
		2: 92;
		3: 66;
		default: 32 }
	iconst_1
	ifeq	l1 // new
	new	class java/lang/IndexOutOfBoundsException
	dup
	iload_1
	invokestatic	Method scala/runtime/BoxesRunTime.boxToInteger:(I)Ljava/lang/Integer;
	invokevirtual	Method java/lang/Object.toString:()Ljava/lang/String;
	invokespecial	Method java/lang/IndexOutOfBoundsException."<init>":(Ljava/lang/String;)V
	athrow
l1	new	class scala/MatchError
	dup
	iload_1
	invokestatic	Method scala/runtime/BoxesRunTime.boxToInteger:(I)Ljava/lang/Integer;
	invokevirtual	Method java/lang/Object.toString:()Ljava/lang/String;
	invokespecial	Method scala/MatchError."<init>":(Ljava/lang/String;)V
	athrow
	iconst_1
	ifeq	l2 // new
	aload_0
	invokevirtual	Method rhs:()Lscala/reflect/Tree;
	goto	l3 // areturn
l2	new	class scala/MatchError
	dup
	iload_1
	invokestatic	Method scala/runtime/BoxesRunTime.boxToInteger:(I)Ljava/lang/Integer;
	invokevirtual	Method java/lang/Object.toString:()Ljava/lang/String;
	invokespecial	Method scala/MatchError."<init>":(Ljava/lang/String;)V
	athrow
	iconst_1
	ifeq	l4 // new
	aload_0
	invokevirtual	Method ret:()Lscala/reflect/Type;
	goto	l3 // areturn
l4	new	class scala/MatchError
	dup
	iload_1
	invokestatic	Method scala/runtime/BoxesRunTime.boxToInteger:(I)Ljava/lang/Integer;
	invokevirtual	Method java/lang/Object.toString:()Ljava/lang/String;
	invokespecial	Method scala/MatchError."<init>":(Ljava/lang/String;)V
	athrow
	iconst_1
	ifeq	l5 // new
	aload_0
	invokevirtual	Method vparamss:()Lscala/collection/immutable/List;
	goto	l3 // areturn
l5	new	class scala/MatchError
	dup
	iload_1
	invokestatic	Method scala/runtime/BoxesRunTime.boxToInteger:(I)Ljava/lang/Integer;
	invokevirtual	Method java/lang/Object.toString:()Ljava/lang/String;
	invokespecial	Method scala/MatchError."<init>":(Ljava/lang/String;)V
	athrow
	iconst_1
	ifeq	l6 // new
	aload_0
	invokevirtual	Method sym:()Lscala/reflect/Symbol;
l3	areturn
l6	new	class scala/MatchError
	dup
	iload_1
	invokestatic	Method scala/runtime/BoxesRunTime.boxToInteger:(I)Ljava/lang/Integer;
	invokevirtual	Method java/lang/Object.toString:()Ljava/lang/String;
	invokespecial	Method scala/MatchError."<init>":(Ljava/lang/String;)V
	athrow
  Labels:
   	l1 = 51 // new
   	l2 = 77 // new
   	l4 = 103 // new
   	l5 = 129 // new
   	l3 = 152 // areturn
   	l6 = 153 // new

public int productArity();
  Signature: ()I
  Code:
   Stack=1, Locals=1, Args_size=1
	iconst_4
	ireturn
  Labels:

public java.lang.String productPrefix();
  Signature: ()Ljava/lang/String;
  Code:
   Stack=1, Locals=1, Args_size=1
	ldc	String DefDef
	areturn
  Labels:

public boolean equals(java.lang.Object);
  Signature: (Ljava/lang/Object;)Z
  Code:
   Stack=5, Locals=7, Args_size=2
	aload_0
	aload_1
	if_acmpeq	l1 // iconst_1
	aload_1
	instanceof	class scala/reflect/DefDef
	ifeq	l2 // iconst_1
	aload_1
	checkcast	class scala/reflect/DefDef
	astore_2
	aload_2
	invokevirtual	Method sym:()Lscala/reflect/Symbol;
	astore_3
	aload_2
	invokevirtual	Method vparamss:()Lscala/collection/immutable/List;
	astore	4
	aload_2
	invokevirtual	Method ret:()Lscala/reflect/Type;
	astore	5
	aload_2
	invokevirtual	Method rhs:()Lscala/reflect/Tree;
	astore	6
	aload_0
	aload_3
	aload	4
	aload	5
	aload	6
	invokespecial	Method gd16$1:(Lscala/reflect/Symbol;Lscala/collection/immutable/List;Lscala/reflect/Type;Lscala/reflect/Tree;)Z
	ifeq	l3 // iconst_1
	aload_1
	checkcast	class scala/reflect/DefDef
	aload_0
	invokeinterface	InterfaceMethod scala/Equals.canEqual:(Ljava/lang/Object;)Z
	goto	l4 // ifeq
l3	iconst_1
	ifeq	l5 // new
	iconst_0
	goto	l4 // ifeq
l5	new	class scala/MatchError
	dup
	aload_1
	invokevirtual	Method java/lang/Object.toString:()Ljava/lang/String;
	invokespecial	Method scala/MatchError."<init>":(Ljava/lang/String;)V
	athrow
l2	iconst_1
	ifeq	l6 // new
	iconst_0
l4	ifeq	l7 // iconst_0
l1	iconst_1
	goto	l8 // ireturn
l7	iconst_0
l8	ireturn
l6	new	class scala/MatchError
	dup
	aload_1
	invokevirtual	Method java/lang/Object.toString:()Ljava/lang/String;
	invokespecial	Method scala/MatchError."<init>":(Ljava/lang/String;)V
	athrow
  Labels:
   	l3 = 67 // iconst_1
   	l5 = 75 // new
   	l2 = 87 // iconst_1
   	l4 = 92 // ifeq
   	l1 = 95 // iconst_1
   	l7 = 99 // iconst_0
   	l8 = 100 // ireturn
   	l6 = 101 // new
  LocalVariableTable: 
   Start  Length  Slot  Name   Signature
   0      113      0    this       Lscala/reflect/DefDef;
   17      70      2    temp74       Lscala/reflect/DefDef;
   22      65      3    temp75       Lscala/reflect/Symbol;
   28      59      4    temp76       Lscala/collection/immutable/List;
   34      53      5    temp77       Lscala/reflect/Type;
   40      47      6    temp78       Lscala/reflect/Tree;


public java.lang.String toString();
  Signature: ()Ljava/lang/String;
  Code:
   Stack=2, Locals=1, Args_size=1
	getstatic	Field scala/runtime/ScalaRunTime$.MODULE$:Lscala/runtime/ScalaRunTime$;
	aload_0
	invokevirtual	Method scala/runtime/ScalaRunTime$._toString:(Lscala/Product;)Ljava/lang/String;
	areturn
  Labels:

public int hashCode();
  Signature: ()I
  Code:
   Stack=2, Locals=1, Args_size=1
	getstatic	Field scala/runtime/ScalaRunTime$.MODULE$:Lscala/runtime/ScalaRunTime$;
	aload_0
	invokevirtual	Method scala/runtime/ScalaRunTime$._hashCode:(Lscala/Product;)I
	ireturn
  Labels:

public scala.reflect.DefDef copy(scala.reflect.Symbol, scala.collection.immutable.List, scala.reflect.Type, scala.reflect.Tree);
  Signature: (Lscala/reflect/Symbol;Lscala/collection/immutable/List;Lscala/reflect/Type;Lscala/reflect/Tree;)Lscala/reflect/DefDef;
  Code:
   Stack=6, Locals=5, Args_size=5
	new	class scala/reflect/DefDef
	dup
	aload_1
	aload_2
	aload_3
	aload	4
	invokespecial	Method "<init>":(Lscala/reflect/Symbol;Lscala/collection/immutable/List;Lscala/reflect/Type;Lscala/reflect/Tree;)V
	areturn
  Labels:
  LocalVariableTable: 
   Start  Length  Slot  Name   Signature
   0      13      0    this       Lscala/reflect/DefDef;
   0      13      1    sym       Lscala/reflect/Symbol;
   0      13      2    vparamss       Lscala/collection/immutable/List;
   0      13      3    ret       Lscala/reflect/Type;
   0      13      4    rhs       Lscala/reflect/Tree;


public scala.reflect.Tree rhs();
  Signature: ()Lscala/reflect/Tree;
  Code:
   Stack=1, Locals=1, Args_size=1
	aload_0
	getfield	Field rhs:Lscala/reflect/Tree;
	areturn
  Labels:

public scala.reflect.Type ret();
  Signature: ()Lscala/reflect/Type;
  Code:
   Stack=1, Locals=1, Args_size=1
	aload_0
	getfield	Field ret:Lscala/reflect/Type;
	areturn
  Labels:

public scala.collection.immutable.List vparamss();
  Signature: ()Lscala/collection/immutable/List;
  Code:
   Stack=1, Locals=1, Args_size=1
	aload_0
	getfield	Field vparamss:Lscala/collection/immutable/List;
	areturn
  Labels:
  Signature: length = 0x2
   00 7F 

public scala.reflect.Symbol sym();
  Signature: ()Lscala/reflect/Symbol;
  Code:
   Stack=1, Locals=1, Args_size=1
	aload_0
	getfield	Field sym:Lscala/reflect/Symbol;
	areturn
  Labels:

public scala.reflect.Symbol copy$default$1();
  Signature: ()Lscala/reflect/Symbol;
  Code:
   Stack=1, Locals=1, Args_size=1
	aload_0
	invokevirtual	Method sym:()Lscala/reflect/Symbol;
	areturn
  Labels:

public scala.collection.immutable.List copy$default$2();
  Signature: ()Lscala/collection/immutable/List;
  Code:
   Stack=1, Locals=1, Args_size=1
	aload_0
	invokevirtual	Method vparamss:()Lscala/collection/immutable/List;
	areturn
  Labels:

public scala.reflect.Type copy$default$3();
  Signature: ()Lscala/reflect/Type;
  Code:
   Stack=1, Locals=1, Args_size=1
	aload_0
	invokevirtual	Method ret:()Lscala/reflect/Type;
	areturn
  Labels:

public scala.reflect.Tree copy$default$4();
  Signature: ()Lscala/reflect/Tree;
  Code:
   Stack=1, Locals=1, Args_size=1
	aload_0
	invokevirtual	Method rhs:()Lscala/reflect/Tree;
	areturn
  Labels:

public scala.collection.Iterator productElements();
  Signature: ()Lscala/collection/Iterator;
  Code:
   Stack=1, Locals=1, Args_size=1
	aload_0
	invokestatic	Method scala/Product$class.productElements:(Lscala/Product;)Lscala/collection/Iterator;
	areturn
  Labels:

public scala.collection.Iterator productIterator();
  Signature: ()Lscala/collection/Iterator;
  Code:
   Stack=1, Locals=1, Args_size=1
	aload_0
	invokestatic	Method scala/Product$class.productIterator:(Lscala/Product;)Lscala/collection/Iterator;
	areturn
  Labels:

}

