Compiled from "Tree.scala"
public final class scala.reflect.DefDef$ extends java.lang.Object implements scala.Function4,scala.ScalaObject
  SourceFile: "Tree.scala"
  Scala: length = 0x
   
  minor version: 0
  major version: 49
  Constant pool:
const #1 = Asciz	SourceFile;
const #2 = Asciz	Tree.scala;
const #3 = Asciz	Scala;
const #4 = Asciz	MODULE$;
const #5 = Asciz	Lscala/reflect/DefDef$;;
const #6 = Asciz	<clinit>;
const #7 = Asciz	()V;
const #8 = Asciz	Code;
const #9 = Asciz	scala/reflect/DefDef$;
const #10 = class	#9;	//  scala/reflect/DefDef$
const #11 = Asciz	<init>;
const #12 = NameAndType	#11:#7;//  "<init>":()V
const #13 = Method	#10.#12;	//  scala/reflect/DefDef$."<init>":()V
const #14 = Asciz	LineNumberTable;
const #15 = Asciz	java/lang/Object;
const #16 = class	#15;	//  java/lang/Object
const #17 = Method	#16.#12;	//  java/lang/Object."<init>":()V
const #18 = NameAndType	#4:#5;//  MODULE$:Lscala/reflect/DefDef$;
const #19 = Field	#10.#18;	//  scala/reflect/DefDef$.MODULE$:Lscala/reflect/DefDef$;
const #20 = Asciz	scala/Function4$class;
const #21 = class	#20;	//  scala/Function4$class
const #22 = Asciz	$init$;
const #23 = Asciz	(Lscala/Function4;)V;
const #24 = NameAndType	#22:#23;//  $init$:(Lscala/Function4;)V
const #25 = Method	#21.#24;	//  scala/Function4$class.$init$:(Lscala/Function4;)V
const #26 = Asciz	apply;
const #27 = Asciz	(Ljava/lang/Object;Ljava/lang/Object;Ljava/lang/Object;Ljava/lang/Object;)Ljava/lang/Object;;
const #28 = Asciz	scala/reflect/Symbol;
const #29 = class	#28;	//  scala/reflect/Symbol
const #30 = Asciz	scala/collection/immutable/List;
const #31 = class	#30;	//  scala/collection/immutable/List
const #32 = Asciz	scala/reflect/Type;
const #33 = class	#32;	//  scala/reflect/Type
const #34 = Asciz	scala/reflect/Tree;
const #35 = class	#34;	//  scala/reflect/Tree
const #36 = Asciz	(Lscala/reflect/Symbol;Lscala/collection/immutable/List;Lscala/reflect/Type;Lscala/reflect/Tree;)Lscala/reflect/DefDef;;
const #37 = NameAndType	#26:#36;//  apply:(Lscala/reflect/Symbol;Lscala/collection/immutable/List;Lscala/reflect/Type;Lscala/reflect/Tree;)Lscala/reflect/DefDef;
const #38 = Method	#10.#37;	//  scala/reflect/DefDef$.apply:(Lscala/reflect/Symbol;Lscala/collection/immutable/List;Lscala/reflect/Type;Lscala/reflect/Tree;)Lscala/reflect/DefDef;
const #39 = Asciz	this;
const #40 = Asciz	v1;
const #41 = Asciz	Ljava/lang/Object;;
const #42 = Asciz	v2;
const #43 = Asciz	v3;
const #44 = Asciz	v4;
const #45 = Asciz	LocalVariableTable;
const #46 = Asciz	scala/reflect/DefDef;
const #47 = class	#46;	//  scala/reflect/DefDef
const #48 = Asciz	(Lscala/reflect/Symbol;Lscala/collection/immutable/List;Lscala/reflect/Type;Lscala/reflect/Tree;)V;
const #49 = NameAndType	#11:#48;//  "<init>":(Lscala/reflect/Symbol;Lscala/collection/immutable/List;Lscala/reflect/Type;Lscala/reflect/Tree;)V
const #50 = Method	#47.#49;	//  scala/reflect/DefDef."<init>":(Lscala/reflect/Symbol;Lscala/collection/immutable/List;Lscala/reflect/Type;Lscala/reflect/Tree;)V
const #51 = Asciz	sym;
const #52 = Asciz	Lscala/reflect/Symbol;;
const #53 = Asciz	vparamss;
const #54 = Asciz	Lscala/collection/immutable/List;;
const #55 = Asciz	ret;
const #56 = Asciz	Lscala/reflect/Type;;
const #57 = Asciz	rhs;
const #58 = Asciz	Lscala/reflect/Tree;;
const #59 = Asciz	unapply;
const #60 = Asciz	(Lscala/reflect/DefDef;)Lscala/Some;;
const #61 = Asciz	scala/Some;
const #62 = class	#61;	//  scala/Some
const #63 = Asciz	scala/Tuple4;
const #64 = class	#63;	//  scala/Tuple4
const #65 = Asciz	()Lscala/reflect/Symbol;;
const #66 = NameAndType	#51:#65;//  sym:()Lscala/reflect/Symbol;
const #67 = Method	#47.#66;	//  scala/reflect/DefDef.sym:()Lscala/reflect/Symbol;
const #68 = Asciz	()Lscala/collection/immutable/List;;
const #69 = NameAndType	#53:#68;//  vparamss:()Lscala/collection/immutable/List;
const #70 = Method	#47.#69;	//  scala/reflect/DefDef.vparamss:()Lscala/collection/immutable/List;
const #71 = Asciz	()Lscala/reflect/Type;;
const #72 = NameAndType	#55:#71;//  ret:()Lscala/reflect/Type;
const #73 = Method	#47.#72;	//  scala/reflect/DefDef.ret:()Lscala/reflect/Type;
const #74 = Asciz	()Lscala/reflect/Tree;;
const #75 = NameAndType	#57:#74;//  rhs:()Lscala/reflect/Tree;
const #76 = Method	#47.#75;	//  scala/reflect/DefDef.rhs:()Lscala/reflect/Tree;
const #77 = Asciz	(Ljava/lang/Object;Ljava/lang/Object;Ljava/lang/Object;Ljava/lang/Object;)V;
const #78 = NameAndType	#11:#77;//  "<init>":(Ljava/lang/Object;Ljava/lang/Object;Ljava/lang/Object;Ljava/lang/Object;)V
const #79 = Method	#64.#78;	//  scala/Tuple4."<init>":(Ljava/lang/Object;Ljava/lang/Object;Ljava/lang/Object;Ljava/lang/Object;)V
const #80 = Asciz	(Ljava/lang/Object;)V;
const #81 = NameAndType	#11:#80;//  "<init>":(Ljava/lang/Object;)V
const #82 = Method	#62.#81;	//  scala/Some."<init>":(Ljava/lang/Object;)V
const #83 = Asciz	x$0;
const #84 = Asciz	Lscala/reflect/DefDef;;
const #85 = Asciz	tuple;
const #86 = Asciz	()Lscala/Function1;;
const #87 = Asciz	(Lscala/Function4;)Lscala/Function1;;
const #88 = NameAndType	#85:#87;//  tuple:(Lscala/Function4;)Lscala/Function1;
const #89 = Method	#21.#88;	//  scala/Function4$class.tuple:(Lscala/Function4;)Lscala/Function1;
const #90 = Asciz	curry;
const #91 = NameAndType	#90:#87;//  curry:(Lscala/Function4;)Lscala/Function1;
const #92 = Method	#21.#91;	//  scala/Function4$class.curry:(Lscala/Function4;)Lscala/Function1;
const #93 = Asciz	toString;
const #94 = Asciz	()Ljava/lang/String;;
const #95 = Asciz	(Lscala/Function4;)Ljava/lang/String;;
const #96 = NameAndType	#93:#95;//  toString:(Lscala/Function4;)Ljava/lang/String;
const #97 = Method	#21.#96;	//  scala/Function4$class.toString:(Lscala/Function4;)Ljava/lang/String;
const #98 = Asciz	scala/Function4;
const #99 = class	#98;	//  scala/Function4
const #100 = Asciz	scala/ScalaObject;
const #101 = class	#100;	//  scala/ScalaObject

{
public static final scala.reflect.DefDef$ MODULE$;

public static {};
  Code:
   Stack=1, Locals=0, Args_size=0
   0:	new	#10; //class scala/reflect/DefDef$
   3:	invokespecial	#13; //Method "<init>":()V
   6:	return

public java.lang.Object apply(java.lang.Object, java.lang.Object, java.lang.Object, java.lang.Object);
  Code:
   Stack=5, Locals=5, Args_size=5
   0:	aload_0
   1:	aload_1
   2:	checkcast	#29; //class scala/reflect/Symbol
   5:	aload_2
   6:	checkcast	#31; //class scala/collection/immutable/List
   9:	aload_3
   10:	checkcast	#33; //class scala/reflect/Type
   13:	aload	4
   15:	checkcast	#35; //class scala/reflect/Tree
   18:	invokevirtual	#38; //Method apply:(Lscala/reflect/Symbol;Lscala/collection/immutable/List;Lscala/reflect/Type;Lscala/reflect/Tree;)Lscala/reflect/DefDef;
   21:	areturn
  LineNumberTable: 
   line 52: 0

  LocalVariableTable: 
   Start  Length  Slot  Name   Signature
   0      22      0    this       Lscala/reflect/DefDef$;
   0      22      1    v1       Ljava/lang/Object;
   0      22      2    v2       Ljava/lang/Object;
   0      22      3    v3       Ljava/lang/Object;
   0      22      4    v4       Ljava/lang/Object;


public scala.reflect.DefDef apply(scala.reflect.Symbol, scala.collection.immutable.List, scala.reflect.Type, scala.reflect.Tree);
  Code:
   Stack=6, Locals=5, Args_size=5
   0:	new	#47; //class scala/reflect/DefDef
   3:	dup
   4:	aload_1
   5:	aload_2
   6:	aload_3
   7:	aload	4
   9:	invokespecial	#50; //Method scala/reflect/DefDef."<init>":(Lscala/reflect/Symbol;Lscala/collection/immutable/List;Lscala/reflect/Type;Lscala/reflect/Tree;)V
   12:	areturn
  LineNumberTable: 
   line 52: 0

  LocalVariableTable: 
   Start  Length  Slot  Name   Signature
   0      13      0    this       Lscala/reflect/DefDef$;
   0      13      1    sym       Lscala/reflect/Symbol;
   0      13      2    vparamss       Lscala/collection/immutable/List;
   0      13      3    ret       Lscala/reflect/Type;
   0      13      4    rhs       Lscala/reflect/Tree;


public scala.Some unapply(scala.reflect.DefDef);
  Code:
   Stack=8, Locals=2, Args_size=2
   0:	new	#62; //class scala/Some
   3:	dup
   4:	new	#64; //class scala/Tuple4
   7:	dup
   8:	aload_1
   9:	invokevirtual	#67; //Method scala/reflect/DefDef.sym:()Lscala/reflect/Symbol;
   12:	aload_1
   13:	invokevirtual	#70; //Method scala/reflect/DefDef.vparamss:()Lscala/collection/immutable/List;
   16:	aload_1
   17:	invokevirtual	#73; //Method scala/reflect/DefDef.ret:()Lscala/reflect/Type;
   20:	aload_1
   21:	invokevirtual	#76; //Method scala/reflect/DefDef.rhs:()Lscala/reflect/Tree;
   24:	invokespecial	#79; //Method scala/Tuple4."<init>":(Ljava/lang/Object;Ljava/lang/Object;Ljava/lang/Object;Ljava/lang/Object;)V
   27:	invokespecial	#82; //Method scala/Some."<init>":(Ljava/lang/Object;)V
   30:	areturn
  LineNumberTable: 
   line 52: 0

  LocalVariableTable: 
   Start  Length  Slot  Name   Signature
   0      31      0    this       Lscala/reflect/DefDef$;
   0      31      1    x$0       Lscala/reflect/DefDef;


public scala.Function1 tuple();
  Code:
   Stack=1, Locals=1, Args_size=1
   0:	aload_0
   1:	invokestatic	#89; //Method scala/Function4$class.tuple:(Lscala/Function4;)Lscala/Function1;
   4:	areturn
  LineNumberTable: 
   line 52: 0


public scala.Function1 curry();
  Code:
   Stack=1, Locals=1, Args_size=1
   0:	aload_0
   1:	invokestatic	#92; //Method scala/Function4$class.curry:(Lscala/Function4;)Lscala/Function1;
   4:	areturn
  LineNumberTable: 
   line 52: 0


public java.lang.String toString();
  Code:
   Stack=1, Locals=1, Args_size=1
   0:	aload_0
   1:	invokestatic	#97; //Method scala/Function4$class.toString:(Lscala/Function4;)Ljava/lang/String;
   4:	areturn
  LineNumberTable: 
   line 52: 0


}

