Compiled from "Symbol.scala"
public class scala.reflect.Field extends scala.reflect.GlobalSymbol implements scala.ScalaObject,scala.Product,java.io.Serializable
  SourceFile: "Symbol.scala"
  ScalaSig: length = 0x3
   05 00 00 
  RuntimeVisibleAnnotations: length = 0xB
   00 01 00 7E 00 01 00 7F 73 00 FFFFFF80 
  minor version: 0
  major version: 49
  Constant pool:
Asciz	SourceFile;
Asciz	Symbol.scala;
Asciz	tupled;
Asciz	()Lscala/Function1;;
Asciz	Code;
Asciz	scala/reflect/Field$;
class	scala/reflect/Field$
Asciz	MODULE$;
Asciz	Lscala/reflect/Field$;;
NameAndType	MODULE$:Lscala/reflect/Field$;
Field	scala/reflect/Field$.MODULE$:Lscala/reflect/Field$;
NameAndType	tupled:()Lscala/Function1;
Method	scala/reflect/Field$.tupled:()Lscala/Function1;
Asciz	curry;
NameAndType	curry:()Lscala/Function1;
Method	scala/reflect/Field$.curry:()Lscala/Function1;
Asciz	Deprecated;
Asciz	curried;
NameAndType	curried:()Lscala/Function1;
Method	scala/reflect/Field$.curried:()Lscala/Function1;
Asciz	tpe;
Asciz	Lscala/reflect/Type;;
Asciz	productElementName;
Asciz	(I)Ljava/lang/String;;
Asciz	LineNumberTable;
Asciz	scala/Product$class;
class	scala/Product$class
Asciz	(Lscala/Product;I)Ljava/lang/String;;
NameAndType	productElementName:(Lscala/Product;I)Ljava/lang/String;
Method	scala/Product$class.productElementName:(Lscala/Product;I)Ljava/lang/String;
Asciz	this;
Asciz	Lscala/reflect/Field;;
Asciz	n;
Asciz	I;
Asciz	LocalVariableTable;
Asciz	productIterator;
Asciz	()Lscala/collection/Iterator;;
Asciz	(Lscala/Product;)Lscala/collection/Iterator;;
NameAndType	productIterator:(Lscala/Product;)Lscala/collection/Iterator;
Method	scala/Product$class.productIterator:(Lscala/Product;)Lscala/collection/Iterator;
Asciz	productElements;
NameAndType	productElements:(Lscala/Product;)Lscala/collection/Iterator;
Method	scala/Product$class.productElements:(Lscala/Product;)Lscala/collection/Iterator;
Asciz	copy$default$2;
Asciz	()Lscala/reflect/Type;;
Asciz	scala/reflect/Field;
class	scala/reflect/Field
NameAndType	tpe:()Lscala/reflect/Type;
Method	scala/reflect/Field.tpe:()Lscala/reflect/Type;
Asciz	copy$default$1;
Asciz	()Ljava/lang/String;;
Asciz	fullname;
NameAndType	fullname:()Ljava/lang/String;
Method	scala/reflect/Field.fullname:()Ljava/lang/String;
Asciz	scala/reflect/GlobalSymbol;
class	scala/reflect/GlobalSymbol
Method	scala/reflect/GlobalSymbol.fullname:()Ljava/lang/String;
NameAndType	tpe:Lscala/reflect/Type;
Field	scala/reflect/Field.tpe:Lscala/reflect/Type;
Asciz	copy;
Asciz	(Ljava/lang/String;Lscala/reflect/Type;)Lscala/reflect/Field;;
Asciz	<init>;
Asciz	(Ljava/lang/String;Lscala/reflect/Type;)V;
NameAndType	"<init>":(Ljava/lang/String;Lscala/reflect/Type;)V
Method	scala/reflect/Field."<init>":(Ljava/lang/String;Lscala/reflect/Type;)V
Asciz	Ljava/lang/String;;
Asciz	hashCode;
Asciz	()I;
Asciz	scala/runtime/ScalaRunTime$;
class	scala/runtime/ScalaRunTime$
Asciz	Lscala/runtime/ScalaRunTime$;;
NameAndType	MODULE$:Lscala/runtime/ScalaRunTime$;
Field	scala/runtime/ScalaRunTime$.MODULE$:Lscala/runtime/ScalaRunTime$;
Asciz	_hashCode;
Asciz	(Lscala/Product;)I;
NameAndType	_hashCode:(Lscala/Product;)I
Method	scala/runtime/ScalaRunTime$._hashCode:(Lscala/Product;)I
Asciz	toString;
Asciz	_toString;
Asciz	(Lscala/Product;)Ljava/lang/String;;
NameAndType	_toString:(Lscala/Product;)Ljava/lang/String;
Method	scala/runtime/ScalaRunTime$._toString:(Lscala/Product;)Ljava/lang/String;
Asciz	equals;
Asciz	(Ljava/lang/Object;)Z;
Asciz	gd3$1;
Asciz	(Ljava/lang/String;Lscala/reflect/Type;)Z;
NameAndType	gd3$1:(Ljava/lang/String;Lscala/reflect/Type;)Z
Method	scala/reflect/Field.gd3$1:(Ljava/lang/String;Lscala/reflect/Type;)Z
Asciz	scala/Equals;
class	scala/Equals
Asciz	canEqual;
NameAndType	canEqual:(Ljava/lang/Object;)Z
InterfaceMethod	scala/Equals.canEqual:(Ljava/lang/Object;)Z
Asciz	temp11;
Asciz	temp12;
Asciz	temp13;
Asciz	productPrefix;
Asciz	Field;
String	Field
Asciz	productArity;
Asciz	productElement;
Asciz	(I)Ljava/lang/Object;;
Asciz	java/lang/IndexOutOfBoundsException;
class	java/lang/IndexOutOfBoundsException
Asciz	scala/runtime/BoxesRunTime;
class	scala/runtime/BoxesRunTime
Asciz	boxToInteger;
Asciz	(I)Ljava/lang/Integer;;
NameAndType	boxToInteger:(I)Ljava/lang/Integer;
Method	scala/runtime/BoxesRunTime.boxToInteger:(I)Ljava/lang/Integer;
Asciz	java/lang/Object;
class	java/lang/Object
NameAndType	toString:()Ljava/lang/String;
Method	java/lang/Object.toString:()Ljava/lang/String;
Asciz	(Ljava/lang/String;)V;
NameAndType	"<init>":(Ljava/lang/String;)V
Method	java/lang/IndexOutOfBoundsException."<init>":(Ljava/lang/String;)V
NameAndType	equals:(Ljava/lang/Object;)Z
Method	java/lang/Object.equals:(Ljava/lang/Object;)Z
Method	scala/reflect/GlobalSymbol."<init>":(Ljava/lang/String;)V
Asciz	$init$;
Asciz	(Lscala/Product;)V;
NameAndType	$init$:(Lscala/Product;)V
Method	scala/Product$class.$init$:(Lscala/Product;)V
Asciz	ScalaSig;
Asciz	Lscala/reflect/ScalaSignature;;
Asciz	bytes;
Asciz	uaC\t\tQKW\r3\r!a:fM2,7\r)1oY1mC1\tA\"!\tI!acwNY1m'fl'm75qQ\"\n=!!aC*dC2wJ6fGR\"!D\t\nI!!a)s_,8\r\t))!C!+Aa-7m]lW-F!\t9\"D1%B!J,G-4\nma\"AB*ue&twM\t!IaB\tB%acH\nMVdGN\1nKJ!\t!Q3A\t\n19f+CA%\t)#AUsB,C#B\tQX\r\tS!\tAKy%t -bS\n!)Aa-!)aG!9qAA\nB2paf$2aK3!b%AAYAq!\t1C5EIA\r|/eKW;%cU\taGo-\n:}5\t!H<yIQO\2iK\W\r{\t!\"8o_RG/[8o\ty$HA\tv]DWmY6fIZ'/[1oGDq!!)d_BLHZ3gCVdG\n\rS#aI\tA!AB[1tQ{G-BQS1!8u!Y\"A\nb;p'RN\4YAB%\teTKF,\r\:ACAR\tFAAC_>dW-8\tQk!a+J51BA,\r\te.\t3!\t!C!5iO]8ek$K]3gSb,a\t9l!=~A\1oO*\t-kCZBA^!\"A\n\"9s_,8\r^!sSRLX#A$\tA!ABa:pIVG/7f[tGVQ\"9A+ZA96\tII6\rg.R9vC2$\"7\tQK!a+\"A\t=L!M,'/[1mSj'\r\3I!Eg)a)[3mIB\t\t!!EkNAO]ThcIaT!!I,h^5nK&1\nHO]1di+hn;j_:\"Bu\tiH#A:\t}$!CA\tQ!9qYf$RaKAAQ@AYAQ!\t@A\rB\"!u%\t)aUt\r9msR!QBA\r!iqBA\n\r\t\tB$n85\t)BF\n]AAUkBdWM\r7\t91,\rAH\r;
Asciz	RuntimeVisibleAnnotations;
Asciz	scala/ScalaObject;
class	scala/ScalaObject
Asciz	scala/Product;
class	scala/Product
Asciz	java/io/Serializable;
class	java/io/Serializable

{
private final scala.reflect.Type tpe;
  Signature: Lscala/reflect/Type;

public static final scala.Function1 tupled();
  Signature: ()Lscala/Function1;
  Code:
   Stack=1, Locals=0, Args_size=0
	getstatic	Field scala/reflect/Field$.MODULE$:Lscala/reflect/Field$;
	invokevirtual	Method scala/reflect/Field$.tupled:()Lscala/Function1;
	areturn
  Labels:

public static final scala.Function1 curry();
  Signature: ()Lscala/Function1;
  Code:
   Stack=1, Locals=0, Args_size=0
	getstatic	Field scala/reflect/Field$.MODULE$:Lscala/reflect/Field$;
	invokevirtual	Method scala/reflect/Field$.curry:()Lscala/Function1;
	areturn
  Labels:
  Deprecated: true

public static final scala.Function1 curried();
  Signature: ()Lscala/Function1;
  Code:
   Stack=1, Locals=0, Args_size=0
	getstatic	Field scala/reflect/Field$.MODULE$:Lscala/reflect/Field$;
	invokevirtual	Method scala/reflect/Field$.curried:()Lscala/Function1;
	areturn
  Labels:

public java.lang.String productElementName(int);
  Signature: (I)Ljava/lang/String;
  Code:
   Stack=2, Locals=2, Args_size=2
	aload_0
	iload_1
	invokestatic	Method scala/Product$class.productElementName:(Lscala/Product;I)Ljava/lang/String;
	areturn
  Labels:
  LocalVariableTable: 
   Start  Length  Slot  Name   Signature
   0      6      0    this       Lscala/reflect/Field;
   0      6      1    n       I


public scala.collection.Iterator productIterator();
  Signature: ()Lscala/collection/Iterator;
  Code:
   Stack=1, Locals=1, Args_size=1
	aload_0
	invokestatic	Method scala/Product$class.productIterator:(Lscala/Product;)Lscala/collection/Iterator;
	areturn
  Labels:

public scala.collection.Iterator productElements();
  Signature: ()Lscala/collection/Iterator;
  Code:
   Stack=1, Locals=1, Args_size=1
	aload_0
	invokestatic	Method scala/Product$class.productElements:(Lscala/Product;)Lscala/collection/Iterator;
	areturn
  Labels:
  Deprecated: true

public scala.reflect.Type copy$default$2();
  Signature: ()Lscala/reflect/Type;
  Code:
   Stack=1, Locals=1, Args_size=1
	aload_0
	invokevirtual	Method tpe:()Lscala/reflect/Type;
	areturn
  Labels:

public java.lang.String copy$default$1();
  Signature: ()Ljava/lang/String;
  Code:
   Stack=1, Locals=1, Args_size=1
	aload_0
	invokevirtual	Method fullname:()Ljava/lang/String;
	areturn
  Labels:

public java.lang.String fullname();
  Signature: ()Ljava/lang/String;
  Code:
   Stack=1, Locals=1, Args_size=1
	aload_0
	invokespecial	Method scala/reflect/GlobalSymbol.fullname:()Ljava/lang/String;
	areturn
  Labels:

public scala.reflect.Type tpe();
  Signature: ()Lscala/reflect/Type;
  Code:
   Stack=1, Locals=1, Args_size=1
	aload_0
	getfield	Field tpe:Lscala/reflect/Type;
	areturn
  Labels:

public scala.reflect.Field copy(java.lang.String, scala.reflect.Type);
  Signature: (Ljava/lang/String;Lscala/reflect/Type;)Lscala/reflect/Field;
  Code:
   Stack=4, Locals=3, Args_size=3
	new	class scala/reflect/Field
	dup
	aload_1
	aload_2
	invokespecial	Method "<init>":(Ljava/lang/String;Lscala/reflect/Type;)V
	areturn
  Labels:
  LocalVariableTable: 
   Start  Length  Slot  Name   Signature
   0      10      0    this       Lscala/reflect/Field;
   0      10      1    fullname       Ljava/lang/String;
   0      10      2    tpe       Lscala/reflect/Type;


public int hashCode();
  Signature: ()I
  Code:
   Stack=2, Locals=1, Args_size=1
	getstatic	Field scala/runtime/ScalaRunTime$.MODULE$:Lscala/runtime/ScalaRunTime$;
	aload_0
	invokevirtual	Method scala/runtime/ScalaRunTime$._hashCode:(Lscala/Product;)I
	ireturn
  Labels:

public java.lang.String toString();
  Signature: ()Ljava/lang/String;
  Code:
   Stack=2, Locals=1, Args_size=1
	getstatic	Field scala/runtime/ScalaRunTime$.MODULE$:Lscala/runtime/ScalaRunTime$;
	aload_0
	invokevirtual	Method scala/runtime/ScalaRunTime$._toString:(Lscala/Product;)Ljava/lang/String;
	areturn
  Labels:

public boolean equals(java.lang.Object);
  Signature: (Ljava/lang/Object;)Z
  Code:
   Stack=3, Locals=5, Args_size=2
	aload_0
	aload_1
	if_acmpeq	l1 // iconst_1
	aload_1
	instanceof	class scala/reflect/Field
	ifeq	l2 // iconst_0
	aload_1
	checkcast	class scala/reflect/Field
	astore_2
	aload_2
	invokevirtual	Method fullname:()Ljava/lang/String;
	astore_3
	aload_2
	invokevirtual	Method tpe:()Lscala/reflect/Type;
	astore	4
	aload_0
	aload_3
	aload	4
	invokespecial	Method gd3$1:(Ljava/lang/String;Lscala/reflect/Type;)Z
	ifeq	l3 // iconst_0
	aload_1
	checkcast	class scala/reflect/Field
	aload_0
	invokeinterface	InterfaceMethod scala/Equals.canEqual:(Ljava/lang/Object;)Z
	goto	l4 // ifeq
l3	iconst_0
	goto	l4 // ifeq
l2	iconst_0
l4	ifeq	l5 // iconst_0
l1	iconst_1
	goto	l6 // ireturn
l5	iconst_0
l6	ireturn
  Labels:
   	l3 = 51 // iconst_0
   	l2 = 55 // iconst_0
   	l4 = 56 // ifeq
   	l1 = 59 // iconst_1
   	l5 = 63 // iconst_0
   	l6 = 64 // ireturn
  LocalVariableTable: 
   Start  Length  Slot  Name   Signature
   0      65      0    this       Lscala/reflect/Field;
   17      38      2    temp11       Lscala/reflect/Field;
   22      33      3    temp12       Ljava/lang/String;
   28      27      4    temp13       Lscala/reflect/Type;


public java.lang.String productPrefix();
  Signature: ()Ljava/lang/String;
  Code:
   Stack=1, Locals=1, Args_size=1
	ldc	String Field
	areturn
  Labels:

public int productArity();
  Signature: ()I
  Code:
   Stack=1, Locals=1, Args_size=1
	iconst_2
	ireturn
  Labels:

public java.lang.Object productElement(int);
  Signature: (I)Ljava/lang/Object;
  Code:
   Stack=3, Locals=2, Args_size=2
	iload_1
	tableswitch{ //0 to 1
		0: 46;
		1: 39;
		default: 24 }
	new	class java/lang/IndexOutOfBoundsException
	dup
	iload_1
	invokestatic	Method scala/runtime/BoxesRunTime.boxToInteger:(I)Ljava/lang/Integer;
	invokevirtual	Method java/lang/Object.toString:()Ljava/lang/String;
	invokespecial	Method java/lang/IndexOutOfBoundsException."<init>":(Ljava/lang/String;)V
	athrow
	aload_0
	invokevirtual	Method tpe:()Lscala/reflect/Type;
	goto	l1 // areturn
	aload_0
	invokevirtual	Method fullname:()Ljava/lang/String;
l1	areturn
  Labels:
   	l1 = 50 // areturn

public boolean canEqual(java.lang.Object);
  Signature: (Ljava/lang/Object;)Z
  Code:
   Stack=1, Locals=2, Args_size=2
	aload_1
	instanceof	class scala/reflect/Field
	ireturn
  Labels:

private final boolean gd3$1(java.lang.String, scala.reflect.Type);
  Signature: (Ljava/lang/String;Lscala/reflect/Type;)Z
  Code:
   Stack=2, Locals=5, Args_size=3
	aload_1
	aload_0
	invokevirtual	Method fullname:()Ljava/lang/String;
	astore_3
	dup
	ifnonnull	l1 // aload_3
	pop
	aload_3
	ifnull	l2 // aload_2
	goto	l3 // iconst_0
l1	aload_3
	invokevirtual	Method java/lang/Object.equals:(Ljava/lang/Object;)Z
	ifeq	l3 // iconst_0
l2	aload_2
	aload_0
	invokevirtual	Method tpe:()Lscala/reflect/Type;
	astore	4
	dup
	ifnonnull	l4 // aload
	pop
	aload	4
	ifnull	l5 // iconst_1
	goto	l3 // iconst_0
l4	aload	4
	invokevirtual	Method java/lang/Object.equals:(Ljava/lang/Object;)Z
	ifeq	l3 // iconst_0
l5	iconst_1
	goto	l6 // ireturn
l3	iconst_0
l6	ireturn
  Labels:
   	l1 = 18 // aload_3
   	l2 = 25 // aload_2
   	l4 = 45 // aload
   	l5 = 53 // iconst_1
   	l3 = 57 // iconst_0
   	l6 = 58 // ireturn

public scala.reflect.Field(java.lang.String, scala.reflect.Type);
  Signature: (Ljava/lang/String;Lscala/reflect/Type;)V
  Code:
   Stack=2, Locals=3, Args_size=3
	aload_0
	aload_2
	putfield	Field tpe:Lscala/reflect/Type;
	aload_0
	aload_1
	invokespecial	Method scala/reflect/GlobalSymbol."<init>":(Ljava/lang/String;)V
	aload_0
	invokestatic	Method scala/Product$class.$init$:(Lscala/Product;)V
	return
  Labels:
  LocalVariableTable: 
   Start  Length  Slot  Name   Signature
   0      15      0    this       Lscala/reflect/Field;
   0      15      1    fullname       Ljava/lang/String;
   0      15      2    tpe       Lscala/reflect/Type;


}

