Compiled from "Symbol.scala"
public abstract class scala.reflect.GlobalSymbol extends scala.reflect.Symbol implements scala.ScalaObject
  SourceFile: "Symbol.scala"
  ScalaSig: length = 0x14D
   05 00 32 06 08 01 02 FFFFFF84 FFFFFF80 FFFFFF80 FFFFFF81 00 07 02 0C 47
   6C 6F 62 61 6C 53 79 6D 62 6F 6C 0A 02 03 04 01
   07 72 65 66 6C 65 63 74 0A 01 05 01 05 73 63 61
   6C 61 03 00 13 03 00 08 0C 10 02 09 0A 0D 01 02
   09 02 0B 02 02 06 53 79 6D 62 6F 6C 10 02 0D 0E
   0D 01 04 09 02 0F 04 02 0B 53 63 61 6C 61 4F 62
   6A 65 63 74 08 08 11 00 FFFFFF82 FFFFFFC2 FFFFFF80 FFFFFF84 00 12 01 08
   66 75 6C 6C 6E 61 6D 65 15 01 13 10 02 14 17 0E
   02 0D 15 09 02 16 04 01 06 50 72 65 64 65 66 09
   02 18 19 02 06 53 74 72 69 6E 67 0A 02 16 04 08
   08 1B 00 FFFFFF82 FFFFFF80 FFFFFFA0 FFFFFF80 04 13 01 09 66 75 6C 6C 6E
   61 6D 65 20 08 05 1D 00 FFFFFF84 00 1E 01 06 3C 69 6E
   69 74 3E 14 02 1F 20 10 02 09 00 08 05 11 1C FFFFFFC0
   00 13 08 07 22 00 FFFFFFC2 FFFFFF80 FFFFFF84 04 23 01 0A 70 6F 69
   6E 74 49 6E 64 65 78 15 01 24 10 02 0D 25 09 02
   26 04 02 03 49 6E 74 08 06 28 00 FFFFFFA0 FFFFFF80 04 24 01
   0B 70 6F 69 6E 74 49 6E 64 65 78 20 08 07 2A 00
   FFFFFFC2 FFFFFF80 FFFFFF84 00 2B 01 05 6F 77 6E 65 72 15 01 08 08
   06 2D 00 FFFFFFA0 FFFFFF80 04 08 01 06 6F 77 6E 65 72 20 08
   07 2F 00 FFFFFFC2 FFFFFF80 FFFFFF84 00 12 01 04 6E 61 6D 65 08 06
   31 00 FFFFFFA0 FFFFFF80 04 13 01 05 6E 61 6D 65 20 
  minor version: 0
  major version: 49
  Constant pool:
const #1 = Asciz	SourceFile;
const #2 = Asciz	Symbol.scala;
const #3 = Asciz	name;
const #4 = Asciz	Ljava/lang/String;;
const #5 = Asciz	owner;
const #6 = Asciz	Lscala/reflect/Symbol;;
const #7 = Asciz	pointIndex;
const #8 = Asciz	I;
const #9 = Asciz	fullname;
const #10 = Asciz	<init>;
const #11 = Asciz	(Ljava/lang/String;)V;
const #12 = Asciz	Code;
const #13 = Asciz	LineNumberTable;
const #14 = Asciz	scala/reflect/GlobalSymbol;
const #15 = class	#14;	//  scala/reflect/GlobalSymbol
const #16 = NameAndType	#9:#4;//  fullname:Ljava/lang/String;
const #17 = Field	#15.#16;	//  scala/reflect/GlobalSymbol.fullname:Ljava/lang/String;
const #18 = Asciz	scala/reflect/Symbol;
const #19 = class	#18;	//  scala/reflect/Symbol
const #20 = Asciz	()V;
const #21 = NameAndType	#10:#20;//  "<init>":()V
const #22 = Method	#19.#21;	//  scala/reflect/Symbol."<init>":()V
const #23 = Asciz	.;
const #24 = String	#23;	//  .
const #25 = Asciz	java/lang/String;
const #26 = class	#25;	//  java/lang/String
const #27 = Asciz	lastIndexOf;
const #28 = Asciz	(Ljava/lang/String;)I;
const #29 = NameAndType	#27:#28;//  lastIndexOf:(Ljava/lang/String;)I
const #30 = Method	#26.#29;	//  java/lang/String.lastIndexOf:(Ljava/lang/String;)I
const #31 = NameAndType	#7:#8;//  pointIndex:I
const #32 = Field	#15.#31;	//  scala/reflect/GlobalSymbol.pointIndex:I
const #33 = Asciz	()I;
const #34 = NameAndType	#7:#33;//  pointIndex:()I
const #35 = Method	#15.#34;	//  scala/reflect/GlobalSymbol.pointIndex:()I
const #36 = Asciz	scala/reflect/RootSymbol$;
const #37 = class	#36;	//  scala/reflect/RootSymbol$
const #38 = Asciz	MODULE$;
const #39 = Asciz	Lscala/reflect/RootSymbol$;;
const #40 = NameAndType	#38:#39;//  MODULE$:Lscala/reflect/RootSymbol$;
const #41 = Field	#37.#40;	//  scala/reflect/RootSymbol$.MODULE$:Lscala/reflect/RootSymbol$;
const #42 = Asciz	scala/reflect/Class;
const #43 = class	#42;	//  scala/reflect/Class
const #44 = Asciz	substring;
const #45 = Asciz	(II)Ljava/lang/String;;
const #46 = NameAndType	#44:#45;//  substring:(II)Ljava/lang/String;
const #47 = Method	#26.#46;	//  java/lang/String.substring:(II)Ljava/lang/String;
const #48 = NameAndType	#10:#11;//  "<init>":(Ljava/lang/String;)V
const #49 = Method	#43.#48;	//  scala/reflect/Class."<init>":(Ljava/lang/String;)V
const #50 = NameAndType	#5:#6;//  owner:Lscala/reflect/Symbol;
const #51 = Field	#15.#50;	//  scala/reflect/GlobalSymbol.owner:Lscala/reflect/Symbol;
const #52 = Asciz	length;
const #53 = NameAndType	#52:#33;//  length:()I
const #54 = Method	#26.#53;	//  java/lang/String.length:()I
const #55 = NameAndType	#3:#4;//  name:Ljava/lang/String;
const #56 = Field	#15.#55;	//  scala/reflect/GlobalSymbol.name:Ljava/lang/String;
const #57 = Asciz	this;
const #58 = Asciz	Lscala/reflect/GlobalSymbol;;
const #59 = Asciz	LocalVariableTable;
const #60 = Asciz	()Ljava/lang/String;;
const #61 = Asciz	()Lscala/reflect/Symbol;;
const #62 = Asciz	ScalaSig;
const #63 = Asciz	scala/ScalaObject;
const #64 = class	#63;	//  scala/ScalaObject

{
public scala.reflect.GlobalSymbol(java.lang.String);
  Code:
   Stack=6, Locals=2, Args_size=2
   0:	aload_0
   1:	aload_1
   2:	putfield	#17; //Field fullname:Ljava/lang/String;
   5:	aload_0
   6:	invokespecial	#22; //Method scala/reflect/Symbol."<init>":()V
   9:	aload_0
   10:	aload_1
   11:	ldc	#24; //String .
   13:	invokevirtual	#30; //Method java/lang/String.lastIndexOf:(Ljava/lang/String;)I
   16:	putfield	#32; //Field pointIndex:I
   19:	aload_0
   20:	aload_0
   21:	invokespecial	#35; //Method pointIndex:()I
   24:	iconst_0
   25:	if_icmpge	34
   28:	getstatic	#41; //Field scala/reflect/RootSymbol$.MODULE$:Lscala/reflect/RootSymbol$;
   31:	goto	50
   34:	new	#43; //class scala/reflect/Class
   37:	dup
   38:	aload_1
   39:	iconst_0
   40:	aload_0
   41:	invokespecial	#35; //Method pointIndex:()I
   44:	invokevirtual	#47; //Method java/lang/String.substring:(II)Ljava/lang/String;
   47:	invokespecial	#49; //Method scala/reflect/Class."<init>":(Ljava/lang/String;)V
   50:	putfield	#51; //Field owner:Lscala/reflect/Symbol;
   53:	aload_0
   54:	aload_0
   55:	invokespecial	#35; //Method pointIndex:()I
   58:	iconst_0
   59:	if_icmpge	66
   62:	aload_1
   63:	goto	80
   66:	aload_1
   67:	aload_0
   68:	invokespecial	#35; //Method pointIndex:()I
   71:	iconst_1
   72:	iadd
   73:	aload_1
   74:	invokevirtual	#54; //Method java/lang/String.length:()I
   77:	invokevirtual	#47; //Method java/lang/String.substring:(II)Ljava/lang/String;
   80:	putfield	#56; //Field name:Ljava/lang/String;
   83:	return
  LineNumberTable: 
   line 22: 0
   line 23: 9
   line 24: 19
   line 25: 20
   line 26: 34
   line 24: 50
   line 27: 53
   line 28: 54
   line 29: 66
   line 27: 80

  LocalVariableTable: 
   Start  Length  Slot  Name   Signature
   0      84      0    this       Lscala/reflect/GlobalSymbol;
   0      84      1    fullname       Ljava/lang/String;


public java.lang.String name();
  Code:
   Stack=1, Locals=1, Args_size=1
   0:	aload_0
   1:	getfield	#56; //Field name:Ljava/lang/String;
   4:	areturn
  LineNumberTable: 
   line 27: 0


public scala.reflect.Symbol owner();
  Code:
   Stack=1, Locals=1, Args_size=1
   0:	aload_0
   1:	getfield	#51; //Field owner:Lscala/reflect/Symbol;
   4:	areturn
  LineNumberTable: 
   line 24: 0


public java.lang.String fullname();
  Code:
   Stack=1, Locals=1, Args_size=1
   0:	aload_0
   1:	getfield	#17; //Field fullname:Ljava/lang/String;
   4:	areturn
  LineNumberTable: 
   line 22: 0


}

