Compiled from "Symbol.scala"
public abstract class scala.reflect.GlobalSymbol extends scala.reflect.Symbol implements scala.ScalaObject
  SourceFile: "Symbol.scala"
  ScalaSig: length = 0x14D
   05 00 32 06 08 01 02 FFFFFF84 FFFFFF80 FFFFFF80 FFFFFF81 00 07 02 0C 47
   6C 6F 62 61 6C 53 79 6D 62 6F 6C 0A 02 03 04 01
   07 72 65 66 6C 65 63 74 0A 01 05 01 05 73 63 61
   6C 61 03 00 13 03 00 08 0C 10 02 09 0A 0D 01 02
   09 02 0B 02 02 06 53 79 6D 62 6F 6C 10 02 0D 0E
   0D 01 04 09 02 0F 04 02 0B 53 63 61 6C 61 4F 62
   6A 65 63 74 08 08 11 00 FFFFFF82 FFFFFFC2 FFFFFF80 FFFFFF84 00 12 01 08
   66 75 6C 6C 6E 61 6D 65 15 01 13 10 02 14 17 0E
   02 0D 15 09 02 16 04 01 06 50 72 65 64 65 66 09
   02 18 19 02 06 53 74 72 69 6E 67 0A 02 16 04 08
   08 1B 00 FFFFFF82 FFFFFF80 FFFFFFA0 FFFFFF80 04 13 01 09 66 75 6C 6C 6E
   61 6D 65 20 08 05 1D 00 FFFFFF84 00 1E 01 06 3C 69 6E
   69 74 3E 14 02 1F 20 10 02 09 00 08 05 11 1C FFFFFFC0
   00 13 08 07 22 00 FFFFFFC2 FFFFFF80 FFFFFF84 04 23 01 0A 70 6F 69
   6E 74 49 6E 64 65 78 15 01 24 10 02 0D 25 09 02
   26 04 02 03 49 6E 74 08 06 28 00 FFFFFFA0 FFFFFF80 04 24 01
   0B 70 6F 69 6E 74 49 6E 64 65 78 20 08 07 2A 00
   FFFFFFC2 FFFFFF80 FFFFFF84 00 2B 01 05 6F 77 6E 65 72 15 01 08 08
   06 2D 00 FFFFFFA0 FFFFFF80 04 08 01 06 6F 77 6E 65 72 20 08
   07 2F 00 FFFFFFC2 FFFFFF80 FFFFFF84 00 12 01 04 6E 61 6D 65 08 06
   31 00 FFFFFFA0 FFFFFF80 04 13 01 05 6E 61 6D 65 20 
  minor version: 0
  major version: 49
  Constant pool:
Asciz	SourceFile;
Asciz	Symbol.scala;
Asciz	name;
Asciz	Ljava/lang/String;;
Asciz	owner;
Asciz	Lscala/reflect/Symbol;;
Asciz	pointIndex;
Asciz	I;
Asciz	fullname;
Asciz	<init>;
Asciz	(Ljava/lang/String;)V;
Asciz	Code;
Asciz	LineNumberTable;
Asciz	scala/reflect/GlobalSymbol;
class	scala/reflect/GlobalSymbol
NameAndType	fullname:Ljava/lang/String;
Field	scala/reflect/GlobalSymbol.fullname:Ljava/lang/String;
Asciz	scala/reflect/Symbol;
class	scala/reflect/Symbol
Asciz	()V;
NameAndType	"<init>":()V
Method	scala/reflect/Symbol."<init>":()V
Asciz	.;
String	.
Asciz	java/lang/String;
class	java/lang/String
Asciz	lastIndexOf;
Asciz	(Ljava/lang/String;)I;
NameAndType	lastIndexOf:(Ljava/lang/String;)I
Method	java/lang/String.lastIndexOf:(Ljava/lang/String;)I
NameAndType	pointIndex:I
Field	scala/reflect/GlobalSymbol.pointIndex:I
Asciz	()I;
NameAndType	pointIndex:()I
Method	scala/reflect/GlobalSymbol.pointIndex:()I
Asciz	scala/reflect/RootSymbol$;
class	scala/reflect/RootSymbol$
Asciz	MODULE$;
Asciz	Lscala/reflect/RootSymbol$;;
NameAndType	MODULE$:Lscala/reflect/RootSymbol$;
Field	scala/reflect/RootSymbol$.MODULE$:Lscala/reflect/RootSymbol$;
Asciz	scala/reflect/Class;
class	scala/reflect/Class
Asciz	substring;
Asciz	(II)Ljava/lang/String;;
NameAndType	substring:(II)Ljava/lang/String;
Method	java/lang/String.substring:(II)Ljava/lang/String;
NameAndType	"<init>":(Ljava/lang/String;)V
Method	scala/reflect/Class."<init>":(Ljava/lang/String;)V
NameAndType	owner:Lscala/reflect/Symbol;
Field	scala/reflect/GlobalSymbol.owner:Lscala/reflect/Symbol;
Asciz	length;
NameAndType	length:()I
Method	java/lang/String.length:()I
NameAndType	name:Ljava/lang/String;
Field	scala/reflect/GlobalSymbol.name:Ljava/lang/String;
Asciz	this;
Asciz	Lscala/reflect/GlobalSymbol;;
Asciz	LocalVariableTable;
Asciz	()Ljava/lang/String;;
Asciz	()Lscala/reflect/Symbol;;
Asciz	ScalaSig;
Asciz	scala/ScalaObject;
class	scala/ScalaObject

{
private final java.lang.String name;
  Signature: Ljava/lang/String;

private final scala.reflect.Symbol owner;
  Signature: Lscala/reflect/Symbol;

private final int pointIndex;
  Signature: I

private final java.lang.String fullname;
  Signature: Ljava/lang/String;

public scala.reflect.GlobalSymbol(java.lang.String);
  Signature: (Ljava/lang/String;)V
  Code:
   Stack=6, Locals=2, Args_size=2
	aload_0
	aload_1
	putfield	Field fullname:Ljava/lang/String;
	aload_0
	invokespecial	Method scala/reflect/Symbol."<init>":()V
	aload_0
	aload_1
	ldc	String .
	invokevirtual	Method java/lang/String.lastIndexOf:(Ljava/lang/String;)I
	putfield	Field pointIndex:I
	aload_0
	aload_0
	invokespecial	Method pointIndex:()I
	iconst_0
	if_icmpge	l1 // new
	getstatic	Field scala/reflect/RootSymbol$.MODULE$:Lscala/reflect/RootSymbol$;
	goto	l2 // putfield
l1	new	class scala/reflect/Class
	dup
	aload_1
	iconst_0
	aload_0
	invokespecial	Method pointIndex:()I
	invokevirtual	Method java/lang/String.substring:(II)Ljava/lang/String;
	invokespecial	Method scala/reflect/Class."<init>":(Ljava/lang/String;)V
l2	putfield	Field owner:Lscala/reflect/Symbol;
	aload_0
	aload_0
	invokespecial	Method pointIndex:()I
	iconst_0
	if_icmpge	l3 // aload_1
	aload_1
	goto	l4 // putfield
l3	aload_1
	aload_0
	invokespecial	Method pointIndex:()I
	iconst_1
	iadd
	aload_1
	invokevirtual	Method java/lang/String.length:()I
	invokevirtual	Method java/lang/String.substring:(II)Ljava/lang/String;
l4	putfield	Field name:Ljava/lang/String;
	return
  Labels:
   	l1 = 34 // new
   	l2 = 50 // putfield
   	l3 = 66 // aload_1
   	l4 = 80 // putfield
  LocalVariableTable: 
   Start  Length  Slot  Name   Signature
   0      84      0    this       Lscala/reflect/GlobalSymbol;
   0      84      1    fullname       Ljava/lang/String;


public java.lang.String name();
  Signature: ()Ljava/lang/String;
  Code:
   Stack=1, Locals=1, Args_size=1
	aload_0
	getfield	Field name:Ljava/lang/String;
	areturn
  Labels:

public scala.reflect.Symbol owner();
  Signature: ()Lscala/reflect/Symbol;
  Code:
   Stack=1, Locals=1, Args_size=1
	aload_0
	getfield	Field owner:Lscala/reflect/Symbol;
	areturn
  Labels:

private int pointIndex();
  Signature: ()I
  Code:
   Stack=1, Locals=1, Args_size=1
	aload_0
	getfield	Field pointIndex:I
	ireturn
  Labels:

public java.lang.String fullname();
  Signature: ()Ljava/lang/String;
  Code:
   Stack=1, Locals=1, Args_size=1
	aload_0
	getfield	Field fullname:Ljava/lang/String;
	areturn
  Labels:

}

