Compiled from "Tree.scala"
public class scala.reflect.Goto extends scala.reflect.Tree implements scala.ScalaObject,scala.Product,java.io.Serializable
  SourceFile: "Tree.scala"
  ScalaSig: length = 0x369
   05 00 FFFFFF81 02 06 08 01 02 FFFFFF84 FFFFFF80 FFFFFF80 FFFFFF80 40 07 02 04
   47 6F 74 6F 0A 02 03 04 01 07 72 65 66 6C 65 63
   74 0A 01 05 01 05 73 63 61 6C 61 03 00 13 04 00
   08 0C 10 10 02 09 0A 0D 01 02 09 02 0B 02 02 04
   54 72 65 65 10 02 0D 0E 0D 01 04 09 02 0F 04 02
   0B 53 63 61 6C 61 4F 62 6A 65 63 74 10 02 0D 11
   09 02 12 04 02 07 50 72 6F 64 75 63 74 08 08 14
   00 FFFFFF82 FFFFFFCA FFFFFF80 FFFFFF84 00 15 01 06 74 61 72 67 65 74 15
   01 16 10 02 09 17 09 02 18 02 02 0B 4C 61 62 65
   6C 53 79 6D 62 6F 6C 08 08 1A 00 FFFFFF82 FFFFFF88 FFFFFFA0 FFFFFF80 04
   16 01 07 74 61 72 67 65 74 20 08 05 1C 00 FFFFFF84 00
   1D 01 06 3C 69 6E 69 74 3E 14 02 1E 1F 10 02 09
   00 08 05 14 1B FFFFFFC0 00 16 08 07 21 00 FFFFFF81 FFFFFF80 FFFFFF84 00
   22 01 04 63 6F 70 79 14 02 1E 23 08 07 14 20 FFFFFF90
   FFFFFF80 FFFFFFC0 00 16 08 07 25 00 FFFFFF91 FFFFFF80 FFFFFF84 00 26 01 0E 63
   6F 70 79 24 64 65 66 61 75 6C 74 24 31 15 01 27
   2A 02 16 28 2B 01 29 10 02 2A 2F 0D 01 2B 0A 02
   2C 2D 01 09 75 6E 63 68 65 63 6B 65 64 0A 02 2E
   04 01 0A 61 6E 6E 6F 74 61 74 69 6F 6E 09 02 30
   2B 02 11 75 6E 63 68 65 63 6B 65 64 56 61 72 69
   61 6E 63 65 08 08 32 00 FFFFFF84 FFFFFF80 FFFFFF80 FFFFFF84 20 33 01 08
   68 61 73 68 43 6F 64 65 14 01 34 10 02 0D 35 09
   02 36 04 02 03 49 6E 74 08 08 38 00 FFFFFF84 FFFFFF80 FFFFFF80 FFFFFF84
   20 39 01 08 74 6F 53 74 72 69 6E 67 14 01 3A 10
   02 3B 3E 0E 02 0D 3C 09 02 3D 04 01 06 50 72 65
   64 65 66 09 02 3F 40 02 06 53 74 72 69 6E 67 0A
   02 3D 04 08 08 42 00 FFFFFF84 FFFFFF80 FFFFFF80 FFFFFF84 20 43 01 06 65
   71 75 61 6C 73 14 02 44 47 10 02 0D 45 09 02 46
   04 02 07 42 6F 6F 6C 65 61 6E 08 07 48 41 FFFFFF81 FFFFFF80
   FFFFFFC0 00 49 01 03 78 24 31 10 02 0D 4A 09 02 4B 04
   02 03 41 6E 79 08 08 4D 00 FFFFFF84 FFFFFF80 FFFFFF80 FFFFFF84 20 4E 01
   0D 70 72 6F 64 75 63 74 50 72 65 66 69 78 15 01
   4F 10 02 50 55 0D 01 51 0A 02 52 53 01 04 6C 61
   6E 67 0A 01 54 01 04 6A 61 76 61 09 02 3F 51 08
   08 57 00 FFFFFF84 FFFFFF80 FFFFFF80 FFFFFF84 20 58 01 0C 70 72 6F 64 75
   63 74 41 72 69 74 79 15 01 34 08 08 5A 00 FFFFFF84 FFFFFF80
   FFFFFF80 FFFFFF84 20 5B 01 0E 70 72 6F 64 75 63 74 45 6C 65
   6D 65 6E 74 14 02 49 5C 08 07 48 59 FFFFFF81 FFFFFF80 FFFFFFC0 00
   34 08 08 5E 00 FFFFFF84 FFFFFF80 FFFFFF80 FFFFFF84 20 5F 01 12 70 72 6F
   64 75 63 74 45 6C 65 6D 65 6E 74 4E 61 6D 65 14
   02 4F 60 08 07 48 5D FFFFFF81 FFFFFF80 FFFFFFC0 00 34 08 08 62 00
   FFFFFF84 FFFFFF80 FFFFFF80 FFFFFF84 20 63 01 08 63 61 6E 45 71 75 61 6C
   14 02 44 64 08 07 48 61 FFFFFF81 FFFFFF80 FFFFFFC0 00 49 28 02 00
   66 10 02 0D 67 09 02 68 04 02 0C 73 65 72 69 61
   6C 69 7A 61 62 6C 65 07 07 6A 02 FFFFFF81 FFFFFF80 FFFFFF88 02 6B
   01 04 47 6F 74 6F 10 02 09 6C 06 08 01 02 FFFFFF84 FFFFFF81
   FFFFFF80 FFFFFF88 02 6D 13 04 6C 6E 71 0C 10 02 50 6F 09 02
   70 51 02 06 4F 62 6A 65 63 74 10 04 0D 72 16 1E
   09 02 73 04 02 09 46 75 6E 63 74 69 6F 6E 31 08
   05 1C 6C FFFFFF84 00 75 14 01 6B 08 07 77 6C FFFFFF81 FFFFFF80 FFFFFF84
   40 78 01 05 61 70 70 6C 79 14 02 1E 79 08 05 14
   76 FFFFFFC0 00 16 08 07 7B 6C FFFFFF81 FFFFFF80 FFFFFF84 40 7C 01 07 75
   6E 61 70 70 6C 79 14 03 7D FFFFFF81 00 10 03 0D 7E 16
   09 02 7F 04 02 06 4F 70 74 69 6F 6E 08 06 FFFFFF81 01
   7A FFFFFFC0 00 1E 01 03 78 24 30 
  minor version: 0
  major version: 49
  Constant pool:
Asciz	SourceFile;
Asciz	Tree.scala;
Asciz	andThen;
Asciz	(Lscala/Function1;)Lscala/Function1;;
Asciz	Code;
Asciz	scala/reflect/Goto$;
class	scala/reflect/Goto$
Asciz	MODULE$;
Asciz	Lscala/reflect/Goto$;;
NameAndType	MODULE$:Lscala/reflect/Goto$;
Field	scala/reflect/Goto$.MODULE$:Lscala/reflect/Goto$;
NameAndType	andThen:(Lscala/Function1;)Lscala/Function1;
Method	scala/reflect/Goto$.andThen:(Lscala/Function1;)Lscala/Function1;
Asciz	compose;
NameAndType	compose:(Lscala/Function1;)Lscala/Function1;
Method	scala/reflect/Goto$.compose:(Lscala/Function1;)Lscala/Function1;
Asciz	target;
Asciz	Lscala/reflect/LabelSymbol;;
Asciz	productIterator;
Asciz	()Lscala/collection/Iterator;;
Asciz	LineNumberTable;
Asciz	scala/Product$class;
class	scala/Product$class
Asciz	(Lscala/Product;)Lscala/collection/Iterator;;
NameAndType	productIterator:(Lscala/Product;)Lscala/collection/Iterator;
Method	scala/Product$class.productIterator:(Lscala/Product;)Lscala/collection/Iterator;
Asciz	productElements;
NameAndType	productElements:(Lscala/Product;)Lscala/collection/Iterator;
Method	scala/Product$class.productElements:(Lscala/Product;)Lscala/collection/Iterator;
Asciz	Deprecated;
Asciz	copy$default$1;
Asciz	()Lscala/reflect/LabelSymbol;;
Asciz	scala/reflect/Goto;
class	scala/reflect/Goto
NameAndType	target:()Lscala/reflect/LabelSymbol;
Method	scala/reflect/Goto.target:()Lscala/reflect/LabelSymbol;
NameAndType	target:Lscala/reflect/LabelSymbol;
Field	scala/reflect/Goto.target:Lscala/reflect/LabelSymbol;
Asciz	copy;
Asciz	(Lscala/reflect/LabelSymbol;)Lscala/reflect/Goto;;
Asciz	<init>;
Asciz	(Lscala/reflect/LabelSymbol;)V;
NameAndType	"<init>":(Lscala/reflect/LabelSymbol;)V
Method	scala/reflect/Goto."<init>":(Lscala/reflect/LabelSymbol;)V
Asciz	this;
Asciz	Lscala/reflect/Goto;;
Asciz	LocalVariableTable;
Asciz	hashCode;
Asciz	()I;
Asciz	scala/runtime/ScalaRunTime$;
class	scala/runtime/ScalaRunTime$
Asciz	Lscala/runtime/ScalaRunTime$;;
NameAndType	MODULE$:Lscala/runtime/ScalaRunTime$;
Field	scala/runtime/ScalaRunTime$.MODULE$:Lscala/runtime/ScalaRunTime$;
Asciz	_hashCode;
Asciz	(Lscala/Product;)I;
NameAndType	_hashCode:(Lscala/Product;)I
Method	scala/runtime/ScalaRunTime$._hashCode:(Lscala/Product;)I
Asciz	toString;
Asciz	()Ljava/lang/String;;
Asciz	_toString;
Asciz	(Lscala/Product;)Ljava/lang/String;;
NameAndType	_toString:(Lscala/Product;)Ljava/lang/String;
Method	scala/runtime/ScalaRunTime$._toString:(Lscala/Product;)Ljava/lang/String;
Asciz	equals;
Asciz	(Ljava/lang/Object;)Z;
Asciz	gd13$1;
Asciz	(Lscala/reflect/LabelSymbol;)Z;
NameAndType	gd13$1:(Lscala/reflect/LabelSymbol;)Z
Method	scala/reflect/Goto.gd13$1:(Lscala/reflect/LabelSymbol;)Z
Asciz	scala/Equals;
class	scala/Equals
Asciz	canEqual;
NameAndType	canEqual:(Ljava/lang/Object;)Z
InterfaceMethod	scala/Equals.canEqual:(Ljava/lang/Object;)Z
Asciz	temp70;
Asciz	Ljava/lang/Object;;
Asciz	temp71;
Asciz	temp72;
Asciz	target$1;
Asciz	productPrefix;
Asciz	Goto;
String	Goto
Asciz	productArity;
Asciz	productElement;
Asciz	(I)Ljava/lang/Object;;
Asciz	java/lang/IndexOutOfBoundsException;
class	java/lang/IndexOutOfBoundsException
Asciz	scala/runtime/BoxesRunTime;
class	scala/runtime/BoxesRunTime
Asciz	boxToInteger;
Asciz	(I)Ljava/lang/Integer;;
NameAndType	boxToInteger:(I)Ljava/lang/Integer;
Method	scala/runtime/BoxesRunTime.boxToInteger:(I)Ljava/lang/Integer;
Asciz	java/lang/Object;
class	java/lang/Object
NameAndType	toString:()Ljava/lang/String;
Method	java/lang/Object.toString:()Ljava/lang/String;
Asciz	(Ljava/lang/String;)V;
NameAndType	"<init>":(Ljava/lang/String;)V
Method	java/lang/IndexOutOfBoundsException."<init>":(Ljava/lang/String;)V
Asciz	temp73;
Asciz	I;
Asciz	productElementName;
Asciz	(I)Ljava/lang/String;;
String	target
Asciz	temp74;
NameAndType	equals:(Ljava/lang/Object;)Z
Method	java/lang/Object.equals:(Ljava/lang/Object;)Z
Asciz	scala/reflect/Tree;
class	scala/reflect/Tree
Asciz	()V;
NameAndType	"<init>":()V
Method	scala/reflect/Tree."<init>":()V
Asciz	$init$;
Asciz	(Lscala/Product;)V;
NameAndType	$init$:(Lscala/Product;)V
Method	scala/Product$class.$init$:(Lscala/Product;)V
Asciz	ScalaSig;
Asciz	scala/ScalaObject;
class	scala/ScalaObject
Asciz	scala/Product;
class	scala/Product
Asciz	java/io/Serializable;
class	java/io/Serializable

{
private final scala.reflect.LabelSymbol target;
  Signature: Lscala/reflect/LabelSymbol;

public static final scala.Function1 andThen(scala.Function1);
  Signature: (Lscala/Function1;)Lscala/Function1;
  Code:
   Stack=2, Locals=1, Args_size=1
	getstatic	Field scala/reflect/Goto$.MODULE$:Lscala/reflect/Goto$;
	aload_0
	invokevirtual	Method scala/reflect/Goto$.andThen:(Lscala/Function1;)Lscala/Function1;
	areturn
  Labels:

public static final scala.Function1 compose(scala.Function1);
  Signature: (Lscala/Function1;)Lscala/Function1;
  Code:
   Stack=2, Locals=1, Args_size=1
	getstatic	Field scala/reflect/Goto$.MODULE$:Lscala/reflect/Goto$;
	aload_0
	invokevirtual	Method scala/reflect/Goto$.compose:(Lscala/Function1;)Lscala/Function1;
	areturn
  Labels:

public scala.collection.Iterator productIterator();
  Signature: ()Lscala/collection/Iterator;
  Code:
   Stack=1, Locals=1, Args_size=1
	aload_0
	invokestatic	Method scala/Product$class.productIterator:(Lscala/Product;)Lscala/collection/Iterator;
	areturn
  Labels:

public scala.collection.Iterator productElements();
  Signature: ()Lscala/collection/Iterator;
  Code:
   Stack=1, Locals=1, Args_size=1
	aload_0
	invokestatic	Method scala/Product$class.productElements:(Lscala/Product;)Lscala/collection/Iterator;
	areturn
  Labels:
  Deprecated: true

public scala.reflect.LabelSymbol copy$default$1();
  Signature: ()Lscala/reflect/LabelSymbol;
  Code:
   Stack=1, Locals=1, Args_size=1
	aload_0
	invokevirtual	Method target:()Lscala/reflect/LabelSymbol;
	areturn
  Labels:

public scala.reflect.LabelSymbol target();
  Signature: ()Lscala/reflect/LabelSymbol;
  Code:
   Stack=1, Locals=1, Args_size=1
	aload_0
	getfield	Field target:Lscala/reflect/LabelSymbol;
	areturn
  Labels:

public scala.reflect.Goto copy(scala.reflect.LabelSymbol);
  Signature: (Lscala/reflect/LabelSymbol;)Lscala/reflect/Goto;
  Code:
   Stack=3, Locals=2, Args_size=2
	new	class scala/reflect/Goto
	dup
	aload_1
	invokespecial	Method "<init>":(Lscala/reflect/LabelSymbol;)V
	areturn
  Labels:
  LocalVariableTable: 
   Start  Length  Slot  Name   Signature
   0      9      0    this       Lscala/reflect/Goto;
   0      9      1    target       Lscala/reflect/LabelSymbol;


public int hashCode();
  Signature: ()I
  Code:
   Stack=2, Locals=1, Args_size=1
	getstatic	Field scala/runtime/ScalaRunTime$.MODULE$:Lscala/runtime/ScalaRunTime$;
	aload_0
	invokevirtual	Method scala/runtime/ScalaRunTime$._hashCode:(Lscala/Product;)I
	ireturn
  Labels:

public java.lang.String toString();
  Signature: ()Ljava/lang/String;
  Code:
   Stack=2, Locals=1, Args_size=1
	getstatic	Field scala/runtime/ScalaRunTime$.MODULE$:Lscala/runtime/ScalaRunTime$;
	aload_0
	invokevirtual	Method scala/runtime/ScalaRunTime$._toString:(Lscala/Product;)Ljava/lang/String;
	areturn
  Labels:

public boolean equals(java.lang.Object);
  Signature: (Ljava/lang/Object;)Z
  Code:
   Stack=2, Locals=6, Args_size=2
	aload_0
	aload_1
	if_acmpeq	l1 // iconst_1
	aload_1
	astore_2
	aload_2
	instanceof	class scala/reflect/Goto
	ifeq	l2 // iconst_0
	aload_2
	checkcast	class scala/reflect/Goto
	astore_3
	aload_3
	invokevirtual	Method target:()Lscala/reflect/LabelSymbol;
	astore	4
	aload	4
	astore	5
	aload_0
	aload	5
	invokespecial	Method gd13$1:(Lscala/reflect/LabelSymbol;)Z
	ifeq	l3 // iconst_0
	aload_1
	checkcast	class scala/reflect/Goto
	aload_0
	invokeinterface	InterfaceMethod scala/Equals.canEqual:(Ljava/lang/Object;)Z
	goto	l4 // ifeq
l3	iconst_0
	goto	l4 // ifeq
l2	iconst_0
l4	ifeq	l5 // iconst_0
l1	iconst_1
	goto	l6 // ireturn
l5	iconst_0
l6	ireturn
  Labels:
   	l3 = 51 // iconst_0
   	l2 = 55 // iconst_0
   	l4 = 56 // ifeq
   	l1 = 59 // iconst_1
   	l5 = 63 // iconst_0
   	l6 = 64 // ireturn
  LocalVariableTable: 
   Start  Length  Slot  Name   Signature
   0      65      0    this       Lscala/reflect/Goto;
   7      52      2    temp70       Ljava/lang/Object;
   19      36      3    temp71       Lscala/reflect/Goto;
   25      30      4    temp72       Lscala/reflect/LabelSymbol;
   29      26      5    target$1       Lscala/reflect/LabelSymbol;


public java.lang.String productPrefix();
  Signature: ()Ljava/lang/String;
  Code:
   Stack=1, Locals=1, Args_size=1
	ldc	String Goto
	areturn
  Labels:

public int productArity();
  Signature: ()I
  Code:
   Stack=1, Locals=1, Args_size=1
	iconst_1
	ireturn
  Labels:

public java.lang.Object productElement(int);
  Signature: (I)Ljava/lang/Object;
  Code:
   Stack=3, Locals=3, Args_size=2
	iload_1
	istore_2
	iload_2
	iconst_0
	if_icmpne	l1 // new
	aload_0
	invokevirtual	Method target:()Lscala/reflect/LabelSymbol;
	areturn
l1	new	class java/lang/IndexOutOfBoundsException
	dup
	iload_1
	invokestatic	Method scala/runtime/BoxesRunTime.boxToInteger:(I)Ljava/lang/Integer;
	invokevirtual	Method java/lang/Object.toString:()Ljava/lang/String;
	invokespecial	Method java/lang/IndexOutOfBoundsException."<init>":(Ljava/lang/String;)V
	athrow
  Labels:
   	l1 = 12 // new
  LocalVariableTable: 
   Start  Length  Slot  Name   Signature
   0      27      0    this       Lscala/reflect/Goto;
   2      25      2    temp73       I


public java.lang.String productElementName(int);
  Signature: (I)Ljava/lang/String;
  Code:
   Stack=3, Locals=3, Args_size=2
	iload_1
	istore_2
	iload_2
	iconst_0
	if_icmpne	l1 // new
	ldc	String target
	areturn
l1	new	class java/lang/IndexOutOfBoundsException
	dup
	iload_1
	invokestatic	Method scala/runtime/BoxesRunTime.boxToInteger:(I)Ljava/lang/Integer;
	invokevirtual	Method java/lang/Object.toString:()Ljava/lang/String;
	invokespecial	Method java/lang/IndexOutOfBoundsException."<init>":(Ljava/lang/String;)V
	athrow
  Labels:
   	l1 = 10 // new
  LocalVariableTable: 
   Start  Length  Slot  Name   Signature
   0      25      0    this       Lscala/reflect/Goto;
   2      23      2    temp74       I


public boolean canEqual(java.lang.Object);
  Signature: (Ljava/lang/Object;)Z
  Code:
   Stack=1, Locals=2, Args_size=2
	aload_1
	instanceof	class scala/reflect/Goto
	ireturn
  Labels:

private final boolean gd13$1(scala.reflect.LabelSymbol);
  Signature: (Lscala/reflect/LabelSymbol;)Z
  Code:
   Stack=2, Locals=3, Args_size=2
	aload_1
	aload_0
	invokevirtual	Method target:()Lscala/reflect/LabelSymbol;
	astore_2
	dup
	ifnonnull	l1 // aload_2
	pop
	aload_2
	ifnull	l2 // iconst_1
	goto	l3 // iconst_0
l1	aload_2
	invokevirtual	Method java/lang/Object.equals:(Ljava/lang/Object;)Z
	ifeq	l3 // iconst_0
l2	iconst_1
	goto	l4 // ireturn
l3	iconst_0
l4	ireturn
  Labels:
   	l1 = 18 // aload_2
   	l2 = 25 // iconst_1
   	l3 = 29 // iconst_0
   	l4 = 30 // ireturn

public scala.reflect.Goto(scala.reflect.LabelSymbol);
  Signature: (Lscala/reflect/LabelSymbol;)V
  Code:
   Stack=2, Locals=2, Args_size=2
	aload_0
	aload_1
	putfield	Field target:Lscala/reflect/LabelSymbol;
	aload_0
	invokespecial	Method scala/reflect/Tree."<init>":()V
	aload_0
	invokestatic	Method scala/Product$class.$init$:(Lscala/Product;)V
	return
  Labels:
  LocalVariableTable: 
   Start  Length  Slot  Name   Signature
   0      14      0    this       Lscala/reflect/Goto;
   0      14      1    target       Lscala/reflect/LabelSymbol;


}

