Compiled from "Tree.scala"
public final class scala.reflect.Goto$ extends java.lang.Object implements scala.Function1,scala.ScalaObject
  SourceFile: "Tree.scala"
  Scala: length = 0x
   
  minor version: 0
  major version: 49
  Constant pool:
Asciz	SourceFile;
Asciz	Tree.scala;
Asciz	Scala;
Asciz	MODULE$;
Asciz	Lscala/reflect/Goto$;;
Asciz	<clinit>;
Asciz	()V;
Asciz	Code;
Asciz	scala/reflect/Goto$;
class	scala/reflect/Goto$
Asciz	<init>;
NameAndType	"<init>":()V
Method	scala/reflect/Goto$."<init>":()V
Asciz	LineNumberTable;
Asciz	java/lang/Object;
class	java/lang/Object
Method	java/lang/Object."<init>":()V
NameAndType	MODULE$:Lscala/reflect/Goto$;
Field	scala/reflect/Goto$.MODULE$:Lscala/reflect/Goto$;
Asciz	scala/Function1$class;
class	scala/Function1$class
Asciz	$init$;
Asciz	(Lscala/Function1;)V;
NameAndType	$init$:(Lscala/Function1;)V
Method	scala/Function1$class.$init$:(Lscala/Function1;)V
Asciz	apply;
Asciz	(Ljava/lang/Object;)Ljava/lang/Object;;
Asciz	scala/reflect/LabelSymbol;
class	scala/reflect/LabelSymbol
Asciz	(Lscala/reflect/LabelSymbol;)Lscala/reflect/Goto;;
NameAndType	apply:(Lscala/reflect/LabelSymbol;)Lscala/reflect/Goto;
Method	scala/reflect/Goto$.apply:(Lscala/reflect/LabelSymbol;)Lscala/reflect/Goto;
Asciz	this;
Asciz	v1;
Asciz	Ljava/lang/Object;;
Asciz	LocalVariableTable;
Asciz	scala/reflect/Goto;
class	scala/reflect/Goto
Asciz	(Lscala/reflect/LabelSymbol;)V;
NameAndType	"<init>":(Lscala/reflect/LabelSymbol;)V
Method	scala/reflect/Goto."<init>":(Lscala/reflect/LabelSymbol;)V
Asciz	target;
Asciz	Lscala/reflect/LabelSymbol;;
Asciz	unapply;
Asciz	(Lscala/reflect/Goto;)Lscala/Some;;
Asciz	scala/Some;
class	scala/Some
Asciz	()Lscala/reflect/LabelSymbol;;
NameAndType	target:()Lscala/reflect/LabelSymbol;
Method	scala/reflect/Goto.target:()Lscala/reflect/LabelSymbol;
Asciz	(Ljava/lang/Object;)V;
NameAndType	"<init>":(Ljava/lang/Object;)V
Method	scala/Some."<init>":(Ljava/lang/Object;)V
Asciz	x$0;
Asciz	Lscala/reflect/Goto;;
Asciz	andThen;
Asciz	(Lscala/Function1;)Lscala/Function1;;
Asciz	(Lscala/Function1;Lscala/Function1;)Lscala/Function1;;
NameAndType	andThen:(Lscala/Function1;Lscala/Function1;)Lscala/Function1;
Method	scala/Function1$class.andThen:(Lscala/Function1;Lscala/Function1;)Lscala/Function1;
Asciz	g;
Asciz	Lscala/Function1;;
Asciz	compose;
NameAndType	compose:(Lscala/Function1;Lscala/Function1;)Lscala/Function1;
Method	scala/Function1$class.compose:(Lscala/Function1;Lscala/Function1;)Lscala/Function1;
Asciz	toString;
Asciz	()Ljava/lang/String;;
Asciz	(Lscala/Function1;)Ljava/lang/String;;
NameAndType	toString:(Lscala/Function1;)Ljava/lang/String;
Method	scala/Function1$class.toString:(Lscala/Function1;)Ljava/lang/String;
Asciz	scala/Function1;
class	scala/Function1
Asciz	scala/ScalaObject;
class	scala/ScalaObject

{
public static final scala.reflect.Goto$ MODULE$;
  Signature: Lscala/reflect/Goto$;

public static {};
  Signature: ()V
  Code:
   Stack=1, Locals=0, Args_size=0
	new	class scala/reflect/Goto$
	invokespecial	Method "<init>":()V
	return
  Labels:

private scala.reflect.Goto$();
  Signature: ()V
  Code:
   Stack=1, Locals=1, Args_size=1
	aload_0
	invokespecial	Method java/lang/Object."<init>":()V
	aload_0
	putstatic	Field MODULE$:Lscala/reflect/Goto$;
	aload_0
	invokestatic	Method scala/Function1$class.$init$:(Lscala/Function1;)V
	return
  Labels:

public java.lang.Object apply(java.lang.Object);
  Signature: (Ljava/lang/Object;)Ljava/lang/Object;
  Code:
   Stack=2, Locals=2, Args_size=2
	aload_0
	aload_1
	checkcast	class scala/reflect/LabelSymbol
	invokevirtual	Method apply:(Lscala/reflect/LabelSymbol;)Lscala/reflect/Goto;
	areturn
  Labels:
  LocalVariableTable: 
   Start  Length  Slot  Name   Signature
   0      9      0    this       Lscala/reflect/Goto$;
   0      9      1    v1       Ljava/lang/Object;


public scala.reflect.Goto apply(scala.reflect.LabelSymbol);
  Signature: (Lscala/reflect/LabelSymbol;)Lscala/reflect/Goto;
  Code:
   Stack=3, Locals=2, Args_size=2
	new	class scala/reflect/Goto
	dup
	aload_1
	invokespecial	Method scala/reflect/Goto."<init>":(Lscala/reflect/LabelSymbol;)V
	areturn
  Labels:
  LocalVariableTable: 
   Start  Length  Slot  Name   Signature
   0      9      0    this       Lscala/reflect/Goto$;
   0      9      1    target       Lscala/reflect/LabelSymbol;


public scala.Some unapply(scala.reflect.Goto);
  Signature: (Lscala/reflect/Goto;)Lscala/Some;
  Code:
   Stack=3, Locals=2, Args_size=2
	new	class scala/Some
	dup
	aload_1
	invokevirtual	Method scala/reflect/Goto.target:()Lscala/reflect/LabelSymbol;
	invokespecial	Method scala/Some."<init>":(Ljava/lang/Object;)V
	areturn
  Labels:
  LocalVariableTable: 
   Start  Length  Slot  Name   Signature
   0      12      0    this       Lscala/reflect/Goto$;
   0      12      1    x$0       Lscala/reflect/Goto;


public scala.Function1 andThen(scala.Function1);
  Signature: (Lscala/Function1;)Lscala/Function1;
  Code:
   Stack=2, Locals=2, Args_size=2
	aload_0
	aload_1
	invokestatic	Method scala/Function1$class.andThen:(Lscala/Function1;Lscala/Function1;)Lscala/Function1;
	areturn
  Labels:
  LocalVariableTable: 
   Start  Length  Slot  Name   Signature
   0      6      0    this       Lscala/reflect/Goto$;
   0      6      1    g       Lscala/Function1;


public scala.Function1 compose(scala.Function1);
  Signature: (Lscala/Function1;)Lscala/Function1;
  Code:
   Stack=2, Locals=2, Args_size=2
	aload_0
	aload_1
	invokestatic	Method scala/Function1$class.compose:(Lscala/Function1;Lscala/Function1;)Lscala/Function1;
	areturn
  Labels:
  LocalVariableTable: 
   Start  Length  Slot  Name   Signature
   0      6      0    this       Lscala/reflect/Goto$;
   0      6      1    g       Lscala/Function1;


public java.lang.String toString();
  Signature: ()Ljava/lang/String;
  Code:
   Stack=1, Locals=1, Args_size=1
	aload_0
	invokestatic	Method scala/Function1$class.toString:(Lscala/Function1;)Ljava/lang/String;
	areturn
  Labels:

}

