Compiled from "Tree.scala"
public final class scala.reflect.If$ extends java.lang.Object implements scala.Function3,scala.ScalaObject
  SourceFile: "Tree.scala"
  Scala: length = 0x
   
  minor version: 0
  major version: 49
  Constant pool:
const #1 = Asciz	SourceFile;
const #2 = Asciz	Tree.scala;
const #3 = Asciz	Scala;
const #4 = Asciz	MODULE$;
const #5 = Asciz	Lscala/reflect/If$;;
const #6 = Asciz	<clinit>;
const #7 = Asciz	()V;
const #8 = Asciz	Code;
const #9 = Asciz	scala/reflect/If$;
const #10 = class	#9;	//  scala/reflect/If$
const #11 = Asciz	<init>;
const #12 = NameAndType	#11:#7;//  "<init>":()V
const #13 = Method	#10.#12;	//  scala/reflect/If$."<init>":()V
const #14 = Asciz	LineNumberTable;
const #15 = Asciz	java/lang/Object;
const #16 = class	#15;	//  java/lang/Object
const #17 = Method	#16.#12;	//  java/lang/Object."<init>":()V
const #18 = NameAndType	#4:#5;//  MODULE$:Lscala/reflect/If$;
const #19 = Field	#10.#18;	//  scala/reflect/If$.MODULE$:Lscala/reflect/If$;
const #20 = Asciz	scala/Function3$class;
const #21 = class	#20;	//  scala/Function3$class
const #22 = Asciz	$init$;
const #23 = Asciz	(Lscala/Function3;)V;
const #24 = NameAndType	#22:#23;//  $init$:(Lscala/Function3;)V
const #25 = Method	#21.#24;	//  scala/Function3$class.$init$:(Lscala/Function3;)V
const #26 = Asciz	apply;
const #27 = Asciz	(Ljava/lang/Object;Ljava/lang/Object;Ljava/lang/Object;)Ljava/lang/Object;;
const #28 = Asciz	scala/reflect/Tree;
const #29 = class	#28;	//  scala/reflect/Tree
const #30 = Asciz	(Lscala/reflect/Tree;Lscala/reflect/Tree;Lscala/reflect/Tree;)Lscala/reflect/If;;
const #31 = NameAndType	#26:#30;//  apply:(Lscala/reflect/Tree;Lscala/reflect/Tree;Lscala/reflect/Tree;)Lscala/reflect/If;
const #32 = Method	#10.#31;	//  scala/reflect/If$.apply:(Lscala/reflect/Tree;Lscala/reflect/Tree;Lscala/reflect/Tree;)Lscala/reflect/If;
const #33 = Asciz	this;
const #34 = Asciz	v1;
const #35 = Asciz	Ljava/lang/Object;;
const #36 = Asciz	v2;
const #37 = Asciz	v3;
const #38 = Asciz	LocalVariableTable;
const #39 = Asciz	scala/reflect/If;
const #40 = class	#39;	//  scala/reflect/If
const #41 = Asciz	(Lscala/reflect/Tree;Lscala/reflect/Tree;Lscala/reflect/Tree;)V;
const #42 = NameAndType	#11:#41;//  "<init>":(Lscala/reflect/Tree;Lscala/reflect/Tree;Lscala/reflect/Tree;)V
const #43 = Method	#40.#42;	//  scala/reflect/If."<init>":(Lscala/reflect/Tree;Lscala/reflect/Tree;Lscala/reflect/Tree;)V
const #44 = Asciz	condition;
const #45 = Asciz	Lscala/reflect/Tree;;
const #46 = Asciz	trueCase;
const #47 = Asciz	falseCase;
const #48 = Asciz	unapply;
const #49 = Asciz	(Lscala/reflect/If;)Lscala/Some;;
const #50 = Asciz	scala/Some;
const #51 = class	#50;	//  scala/Some
const #52 = Asciz	scala/Tuple3;
const #53 = class	#52;	//  scala/Tuple3
const #54 = Asciz	()Lscala/reflect/Tree;;
const #55 = NameAndType	#44:#54;//  condition:()Lscala/reflect/Tree;
const #56 = Method	#40.#55;	//  scala/reflect/If.condition:()Lscala/reflect/Tree;
const #57 = NameAndType	#46:#54;//  trueCase:()Lscala/reflect/Tree;
const #58 = Method	#40.#57;	//  scala/reflect/If.trueCase:()Lscala/reflect/Tree;
const #59 = NameAndType	#47:#54;//  falseCase:()Lscala/reflect/Tree;
const #60 = Method	#40.#59;	//  scala/reflect/If.falseCase:()Lscala/reflect/Tree;
const #61 = Asciz	(Ljava/lang/Object;Ljava/lang/Object;Ljava/lang/Object;)V;
const #62 = NameAndType	#11:#61;//  "<init>":(Ljava/lang/Object;Ljava/lang/Object;Ljava/lang/Object;)V
const #63 = Method	#53.#62;	//  scala/Tuple3."<init>":(Ljava/lang/Object;Ljava/lang/Object;Ljava/lang/Object;)V
const #64 = Asciz	(Ljava/lang/Object;)V;
const #65 = NameAndType	#11:#64;//  "<init>":(Ljava/lang/Object;)V
const #66 = Method	#51.#65;	//  scala/Some."<init>":(Ljava/lang/Object;)V
const #67 = Asciz	x$0;
const #68 = Asciz	Lscala/reflect/If;;
const #69 = Asciz	curry;
const #70 = Asciz	()Lscala/Function1;;
const #71 = Asciz	(Lscala/Function3;)Lscala/Function1;;
const #72 = NameAndType	#69:#71;//  curry:(Lscala/Function3;)Lscala/Function1;
const #73 = Method	#21.#72;	//  scala/Function3$class.curry:(Lscala/Function3;)Lscala/Function1;
const #74 = Asciz	toString;
const #75 = Asciz	()Ljava/lang/String;;
const #76 = Asciz	(Lscala/Function3;)Ljava/lang/String;;
const #77 = NameAndType	#74:#76;//  toString:(Lscala/Function3;)Ljava/lang/String;
const #78 = Method	#21.#77;	//  scala/Function3$class.toString:(Lscala/Function3;)Ljava/lang/String;
const #79 = Asciz	scala/Function3;
const #80 = class	#79;	//  scala/Function3
const #81 = Asciz	scala/ScalaObject;
const #82 = class	#81;	//  scala/ScalaObject

{
public static final scala.reflect.If$ MODULE$;

public static {};
  Code:
   Stack=1, Locals=0, Args_size=0
   0:	new	#10; //class scala/reflect/If$
   3:	invokespecial	#13; //Method "<init>":()V
   6:	return

public java.lang.Object apply(java.lang.Object, java.lang.Object, java.lang.Object);
  Code:
   Stack=4, Locals=4, Args_size=4
   0:	aload_0
   1:	aload_1
   2:	checkcast	#29; //class scala/reflect/Tree
   5:	aload_2
   6:	checkcast	#29; //class scala/reflect/Tree
   9:	aload_3
   10:	checkcast	#29; //class scala/reflect/Tree
   13:	invokevirtual	#32; //Method apply:(Lscala/reflect/Tree;Lscala/reflect/Tree;Lscala/reflect/Tree;)Lscala/reflect/If;
   16:	areturn
  LineNumberTable: 
   line 36: 0

  LocalVariableTable: 
   Start  Length  Slot  Name   Signature
   0      17      0    this       Lscala/reflect/If$;
   0      17      1    v1       Ljava/lang/Object;
   0      17      2    v2       Ljava/lang/Object;
   0      17      3    v3       Ljava/lang/Object;


public scala.reflect.If apply(scala.reflect.Tree, scala.reflect.Tree, scala.reflect.Tree);
  Code:
   Stack=5, Locals=4, Args_size=4
   0:	new	#40; //class scala/reflect/If
   3:	dup
   4:	aload_1
   5:	aload_2
   6:	aload_3
   7:	invokespecial	#43; //Method scala/reflect/If."<init>":(Lscala/reflect/Tree;Lscala/reflect/Tree;Lscala/reflect/Tree;)V
   10:	areturn
  LineNumberTable: 
   line 36: 0

  LocalVariableTable: 
   Start  Length  Slot  Name   Signature
   0      11      0    this       Lscala/reflect/If$;
   0      11      1    condition       Lscala/reflect/Tree;
   0      11      2    trueCase       Lscala/reflect/Tree;
   0      11      3    falseCase       Lscala/reflect/Tree;


public scala.Some unapply(scala.reflect.If);
  Code:
   Stack=7, Locals=2, Args_size=2
   0:	new	#51; //class scala/Some
   3:	dup
   4:	new	#53; //class scala/Tuple3
   7:	dup
   8:	aload_1
   9:	invokevirtual	#56; //Method scala/reflect/If.condition:()Lscala/reflect/Tree;
   12:	aload_1
   13:	invokevirtual	#58; //Method scala/reflect/If.trueCase:()Lscala/reflect/Tree;
   16:	aload_1
   17:	invokevirtual	#60; //Method scala/reflect/If.falseCase:()Lscala/reflect/Tree;
   20:	invokespecial	#63; //Method scala/Tuple3."<init>":(Ljava/lang/Object;Ljava/lang/Object;Ljava/lang/Object;)V
   23:	invokespecial	#66; //Method scala/Some."<init>":(Ljava/lang/Object;)V
   26:	areturn
  LineNumberTable: 
   line 36: 0

  LocalVariableTable: 
   Start  Length  Slot  Name   Signature
   0      27      0    this       Lscala/reflect/If$;
   0      27      1    x$0       Lscala/reflect/If;


public scala.Function1 curry();
  Code:
   Stack=1, Locals=1, Args_size=1
   0:	aload_0
   1:	invokestatic	#73; //Method scala/Function3$class.curry:(Lscala/Function3;)Lscala/Function1;
   4:	areturn
  LineNumberTable: 
   line 36: 0


public java.lang.String toString();
  Code:
   Stack=1, Locals=1, Args_size=1
   0:	aload_0
   1:	invokestatic	#78; //Method scala/Function3$class.toString:(Lscala/Function3;)Ljava/lang/String;
   4:	areturn
  LineNumberTable: 
   line 36: 0


}

