Compiled from "Invocation.scala"
public final class scala.reflect.Invocation extends java.lang.Object
  SourceFile: "Invocation.scala"
  ScalaSig: length = 0xCC0
   05 00 FFFFFF83 28 07 05 01 02 FFFFFF88 02 07 01 0A 49 6E 76
   6F 63 61 74 69 6F 6E 0A 02 03 04 01 07 72 65 66
   6C 65 63 74 0A 01 05 01 05 73 63 61 6C 61 03 00
   10 02 08 09 0D 01 02 06 08 0A 02 FFFFFF84 FFFFFF80 FFFFFF80 FFFFFF88 02
   0B 02 0A 49 6E 76 6F 63 61 74 69 6F 6E 13 03 09
   0C 14 10 02 0D 12 0D 01 0E 0A 02 0F 10 01 04 6C
   61 6E 67 0A 01 11 01 04 6A 61 76 61 09 02 13 0E
   02 06 4F 62 6A 65 63 74 10 02 15 16 0D 01 04 09
   02 17 04 02 0B 53 63 61 6C 61 4F 62 6A 65 63 74
   08 05 19 09 FFFFFF84 00 1A 01 06 3C 69 6E 69 74 3E 14
   01 07 06 07 1C 09 FFFFFF90 FFFFFF80 FFFFFF91 00 1D 02 12 50 72 69
   6D 69 74 69 76 65 50 72 65 73 65 72 76 65 72 15
   02 1E 24 13 02 1B 0C 08 07 20 1B FFFFFFC2 FFFFFF80 FFFFFF86 00 21
   01 05 76 61 6C 75 65 15 01 22 10 02 23 24 0C 00
   04 08 25 1B FFFFFF84 FFFFFF80 FFFFFF80 FFFFFFC2 00 26 02 01 54 11 02 27
   2A 10 02 15 28 09 02 29 04 02 07 4E 6F 74 68 69
   6E 67 10 02 15 2B 09 02 2C 04 02 03 41 6E 79 08
   07 2E 1B FFFFFFC2 FFFFFF80 FFFFFF86 00 2F 01 05 63 6C 61 7A 7A 15
   01 30 30 02 31 35 10 03 0D 32 34 09 02 33 0E 02
   05 43 6C 61 73 73 10 02 23 35 04 08 36 00 FFFFFF84 FFFFFF80
   FFFFFF80 FFFFFF82 00 26 02 03 5F 24 31 06 04 38 09 40 39 02
   0F 50 72 65 73 65 72 76 65 64 41 6E 79 56 61 6C
   15 02 3A 3E 13 05 37 0C 3B 14 43 10 03 3C 1B 3D
   0D 01 09 10 02 23 3E 04 08 25 37 FFFFFF84 FFFFFF80 FFFFFF80 FFFFFFC2 00
   3F 11 02 27 40 10 02 15 41 09 02 42 04 02 06 41
   6E 79 56 61 6C 10 02 15 44 09 02 45 04 02 07 50
   72 6F 64 75 63 74 08 08 20 37 FFFFFF82 FFFFFFCA FFFFFF80 FFFFFF84 00 47
   15 01 3D 08 08 49 37 FFFFFF82 FFFFFF88 FFFFFFA0 FFFFFF80 04 3D 01 06 76
   61 6C 75 65 20 08 05 19 37 FFFFFF84 00 4B 14 02 4C 4D
   10 03 3C 37 3D 08 05 20 4A FFFFFFC0 00 3D 08 07 2E 37
   FFFFFFC2 FFFFFF80 FFFFFF84 00 4F 15 01 50 30 02 51 53 10 03 0D 32
   52 10 02 23 53 04 08 54 00 FFFFFF84 FFFFFF80 FFFFFF80 FFFFFF82 00 26 02
   03 5F 24 34 08 06 56 37 FFFFFFA0 FFFFFF80 04 50 01 06 63 6C
   61 7A 7A 20 08 07 58 37 FFFFFF81 FFFFFF80 FFFFFF84 00 59 01 04 63
   6F 70 79 15 02 5A 5D 14 02 5B 5E 10 03 3C 37 5C
   10 02 23 5D 04 08 25 57 FFFFFF84 FFFFFF80 FFFFFF80 FFFFFFC2 00 3F 08 08
   5F 20 57 FFFFFF90 FFFFFF80 FFFFFFC0 00 5C 08 07 60 37 FFFFFF91 FFFFFF80 FFFFFF84 00
   61 01 0E 63 6F 70 79 24 64 65 66 61 75 6C 74 24
   31 15 02 3D 62 04 08 25 5F FFFFFF84 FFFFFF80 FFFFFF80 FFFFFFC2 00 3F 08
   08 64 37 FFFFFF84 FFFFFF80 FFFFFF80 FFFFFF84 20 65 01 08 68 61 73 68 43
   6F 64 65 14 01 66 10 02 15 67 09 02 68 04 02 03
   49 6E 74 08 08 6A 37 FFFFFF84 FFFFFF80 FFFFFF80 FFFFFF84 20 6B 01 08 74
   6F 53 74 72 69 6E 67 14 01 6C 10 02 6D 70 0E 02
   15 6E 09 02 6F 04 01 06 50 72 65 64 65 66 09 02
   71 72 02 06 53 74 72 69 6E 67 0A 02 6F 04 08 08
   74 37 FFFFFF84 FFFFFF80 FFFFFF80 FFFFFF84 20 75 01 06 65 71 75 61 6C 73
   14 02 76 79 10 02 15 77 09 02 78 04 02 07 42 6F
   6F 6C 65 61 6E 08 07 7A 73 FFFFFF81 FFFFFF80 FFFFFFC0 00 2A 01 03
   78 24 31 08 08 7C 37 FFFFFF84 FFFFFF80 FFFFFF80 FFFFFF84 20 7D 01 0D 70
   72 6F 64 75 63 74 50 72 65 66 69 78 15 01 7E 10
   02 0D 7F 09 02 71 0E 08 0A FFFFFF81 01 37 FFFFFF84 FFFFFF80 FFFFFF80 FFFFFF84
   20 FFFFFF81 02 01 0C 70 72 6F 64 75 63 74 41 72 69 74
   79 15 01 66 08 0A FFFFFF81 04 37 FFFFFF84 FFFFFF80 FFFFFF80 FFFFFF84 20 FFFFFF81 05
   01 0E 70 72 6F 64 75 63 74 45 6C 65 6D 65 6E 74
   14 03 2A FFFFFF81 06 08 08 7A FFFFFF81 03 FFFFFF81 FFFFFF80 FFFFFFC0 00 66 08
   0A FFFFFF81 08 37 FFFFFF84 FFFFFF80 FFFFFF80 FFFFFF84 20 FFFFFF81 09 01 08 63 61 6E
   45 71 75 61 6C 14 03 76 FFFFFF81 0A 08 08 7A FFFFFF81 07 FFFFFF81
   FFFFFF80 FFFFFFC0 00 2A 28 03 37 FFFFFF81 0C 10 03 15 FFFFFF81 0D 09 03
   FFFFFF81 0E 04 02 0C 73 65 72 69 61 6C 69 7A 61 62 6C
   65 07 09 FFFFFF81 10 09 FFFFFF81 FFFFFF80 FFFFFF88 02 FFFFFF81 11 01 0F 50 72
   65 73 65 72 76 65 64 41 6E 79 56 61 6C 10 03 3C
   FFFFFF81 12 06 09 38 09 FFFFFF84 FFFFFF81 FFFFFF80 FFFFFF88 02 FFFFFF81 13 13 04 FFFFFF81
   12 0C 14 08 07 19 FFFFFF81 12 FFFFFF84 00 FFFFFF81 15 14 02 FFFFFF81 11
   08 0A FFFFFF81 17 FFFFFF81 12 FFFFFF81 FFFFFF80 FFFFFF84 40 FFFFFF81 18 01 05 61 70
   70 6C 79 15 04 FFFFFF81 19 FFFFFF81 1C 14 04 FFFFFF81 1A FFFFFF81 1D 10
   04 3C 37 FFFFFF81 1B 10 03 23 FFFFFF81 1C 04 09 25 FFFFFF81 16 FFFFFF84
   FFFFFF80 FFFFFF80 FFFFFFC2 00 3F 08 07 20 FFFFFF81 16 FFFFFFC0 00 FFFFFF81 1B 08 0A
   FFFFFF81 1F FFFFFF81 12 FFFFFF81 FFFFFF80 FFFFFF84 40 FFFFFF81 20 01 07 75 6E 61 70
   70 6C 79 15 04 FFFFFF81 21 FFFFFF81 26 14 04 FFFFFF81 22 FFFFFF81 27 10
   05 15 FFFFFF81 23 FFFFFF81 25 09 03 FFFFFF81 24 04 02 04 53 6F 6D
   65 10 03 23 FFFFFF81 26 04 09 25 FFFFFF81 1E FFFFFF84 FFFFFF80 FFFFFF80 FFFFFFC2 00
   3F 08 08 FFFFFF81 28 FFFFFF81 1E FFFFFFC0 00 FFFFFF81 29 01 03 78 24 30
   10 04 3C 37 FFFFFF81 25 06 06 FFFFFF81 2B 09 40 FFFFFF81 2C 02 0F
   50 72 65 73 65 72 76 65 64 41 6E 79 52 65 66 15
   04 FFFFFF81 2D FFFFFF81 30 13 07 FFFFFF81 2A 0C FFFFFF81 2E 14 43 10 04
   3C 1B FFFFFF81 2F 10 03 23 FFFFFF81 30 04 0A 25 FFFFFF81 2A FFFFFF84 FFFFFF80
   FFFFFF80 FFFFFFC2 00 FFFFFF81 31 11 03 27 FFFFFF81 32 10 03 15 FFFFFF81 33 09
   03 FFFFFF81 34 04 02 06 41 6E 79 52 65 66 08 0A 20 FFFFFF81
   2A FFFFFF82 FFFFFFCA FFFFFF80 FFFFFF84 00 FFFFFF81 36 15 02 FFFFFF81 2F 08 0A 49 FFFFFF81
   2A FFFFFF82 FFFFFF88 FFFFFFA0 FFFFFF80 04 FFFFFF81 2F 08 07 19 FFFFFF81 2A FFFFFF84 00 FFFFFF81
   39 14 04 FFFFFF81 3A FFFFFF81 3B 10 05 3C FFFFFF81 2A FFFFFF81 2F 08 07
   20 FFFFFF81 38 FFFFFFC0 00 FFFFFF81 2F 08 09 2E FFFFFF81 2A FFFFFFC2 FFFFFF80 FFFFFF84 00
   FFFFFF81 3D 15 02 FFFFFF81 3E 30 04 FFFFFF81 3F FFFFFF81 41 10 04 0D 32
   FFFFFF81 40 10 03 23 FFFFFF81 41 04 0A FFFFFF81 42 00 FFFFFF84 FFFFFF80 FFFFFF80 FFFFFF82
   00 FFFFFF81 44 02 02 3F 30 08 08 56 FFFFFF81 2A FFFFFFA0 FFFFFF80 04 FFFFFF81
   3E 11 02 27 0C 08 09 58 FFFFFF81 2A FFFFFF81 FFFFFF80 FFFFFF84 00 FFFFFF81 46
   15 04 FFFFFF81 47 FFFFFF81 4A 14 04 FFFFFF81 48 FFFFFF81 4B 10 05 3C FFFFFF81
   2A FFFFFF81 49 10 03 23 FFFFFF81 4A 04 0A 25 FFFFFF81 45 FFFFFF84 FFFFFF80 FFFFFF80
   FFFFFFC2 00 FFFFFF81 31 08 0B FFFFFF81 4C 20 FFFFFF81 45 FFFFFF90 FFFFFF80 FFFFFFC0 00 FFFFFF81
   49 08 09 60 FFFFFF81 2A FFFFFF91 FFFFFF80 FFFFFF84 00 FFFFFF81 4D 15 04 FFFFFF81 2F
   FFFFFF81 4E 04 0A 25 FFFFFF81 4C FFFFFF84 FFFFFF80 FFFFFF80 FFFFFFC2 00 FFFFFF81 31 08 09
   64 FFFFFF81 2A FFFFFF84 FFFFFF80 FFFFFF80 FFFFFF84 20 65 08 09 6A FFFFFF81 2A FFFFFF84 FFFFFF80
   FFFFFF80 FFFFFF84 20 6B 08 0A 74 FFFFFF81 2A FFFFFF84 FFFFFF80 FFFFFF80 FFFFFF84 20 FFFFFF81 52
   14 03 76 FFFFFF81 53 08 08 7A FFFFFF81 51 FFFFFF81 FFFFFF80 FFFFFFC0 00 2A 08
   09 7C FFFFFF81 2A FFFFFF84 FFFFFF80 FFFFFF80 FFFFFF84 20 7D 08 0B FFFFFF81 01 FFFFFF81 2A
   FFFFFF84 FFFFFF80 FFFFFF80 FFFFFF84 20 FFFFFF81 02 08 0B FFFFFF81 04 FFFFFF81 2A FFFFFF84 FFFFFF80 FFFFFF80
   FFFFFF84 20 FFFFFF81 57 14 03 2A FFFFFF81 58 08 08 7A FFFFFF81 56 FFFFFF81 FFFFFF80
   FFFFFFC0 00 66 08 0B FFFFFF81 08 FFFFFF81 2A FFFFFF84 FFFFFF80 FFFFFF80 FFFFFF84 20 FFFFFF81 5A
   14 03 76 FFFFFF81 5B 08 08 7A FFFFFF81 59 FFFFFF81 FFFFFF80 FFFFFFC0 00 2A 28
   04 FFFFFF81 2A FFFFFF81 0C 07 09 FFFFFF81 5E 09 FFFFFF81 FFFFFF80 FFFFFF88 02 FFFFFF81 5F
   01 0F 50 72 65 73 65 72 76 65 64 41 6E 79 52 65
   66 10 03 3C FFFFFF81 60 06 0A FFFFFF81 2B 09 FFFFFF84 FFFFFF81 FFFFFF80 FFFFFF88 02
   FFFFFF81 61 13 04 FFFFFF81 60 0C 14 08 07 19 FFFFFF81 60 FFFFFF84 00 FFFFFF81
   63 14 02 FFFFFF81 5F 08 0A FFFFFF81 17 FFFFFF81 60 FFFFFF81 FFFFFF80 FFFFFF84 40 FFFFFF81
   65 15 04 FFFFFF81 66 FFFFFF81 69 14 04 FFFFFF81 67 FFFFFF81 6A 10 05 3C
   FFFFFF81 2A FFFFFF81 68 10 03 23 FFFFFF81 69 04 0A 25 FFFFFF81 64 FFFFFF84 FFFFFF80
   FFFFFF80 FFFFFFC2 00 FFFFFF81 31 08 07 20 FFFFFF81 64 FFFFFFC0 00 FFFFFF81 68 08 0A
   FFFFFF81 1F FFFFFF81 60 FFFFFF81 FFFFFF80 FFFFFF84 40 FFFFFF81 6C 15 04 FFFFFF81 6D FFFFFF81 70
   14 04 FFFFFF81 6E FFFFFF81 71 10 05 15 FFFFFF81 23 FFFFFF81 6F 10 03 23
   FFFFFF81 70 04 0A 25 FFFFFF81 6B FFFFFF84 FFFFFF80 FFFFFF80 FFFFFFC2 00 FFFFFF81 31 08 08
   FFFFFF81 28 FFFFFF81 6B FFFFFFC0 00 FFFFFF81 72 10 05 3C FFFFFF81 2A FFFFFF81 6F 08
   07 FFFFFF81 74 09 FFFFFF84 01 FFFFFF81 75 01 13 6D 61 6B 65 50 72
   65 73 65 72 76 65 64 41 6E 79 52 65 66 15 04 FFFFFF81
   76 FFFFFF81 79 14 04 FFFFFF81 77 FFFFFF81 7A 10 05 3C FFFFFF81 2A FFFFFF81 78
   10 03 23 FFFFFF81 79 04 0A 25 FFFFFF81 73 FFFFFF84 FFFFFF80 FFFFFF80 FFFFFFC2 00 FFFFFF81
   31 08 08 FFFFFF81 7B FFFFFF81 73 FFFFFFC0 00 FFFFFF81 78 01 01 78 08 07
   FFFFFF81 7D 09 FFFFFF84 01 FFFFFF81 7E 01 13 6D 61 6B 65 50 72 65
   73 65 72 76 65 64 41 6E 79 56 61 6C 15 04 FFFFFF81 7F
   FFFFFF82 02 14 04 FFFFFF82 00 FFFFFF82 03 10 04 3C 37 FFFFFF82 01 10 03
   23 FFFFFF82 02 04 09 25 FFFFFF81 7C FFFFFF84 FFFFFF80 FFFFFF80 FFFFFFC2 00 3F 08 08
   FFFFFF81 7B FFFFFF81 7C FFFFFFC0 00 FFFFFF82 01 06 0A FFFFFF82 05 09 FFFFFF84 FFFFFF80 FFFFFF80
   FFFFFF80 00 FFFFFF82 06 02 13 53 79 6D 62 6F 6C 57 69 74 68
   41 72 67 75 6D 65 6E 74 73 13 04 FFFFFF82 04 0C 14 08
   0B FFFFFF82 08 FFFFFF82 04 FFFFFF82 FFFFFFC2 FFFFFF80 FFFFFF84 00 FFFFFF82 09 01 03 73 79
   6D 15 02 FFFFFF82 0A 10 03 15 FFFFFF82 0B 09 03 FFFFFF82 0C 04 02
   06 53 79 6D 62 6F 6C 08 0B FFFFFF82 0E FFFFFF82 04 FFFFFF82 FFFFFF80 FFFFFFA0
   FFFFFF80 04 FFFFFF82 0A 01 04 73 79 6D 20 08 0B FFFFFF82 10 FFFFFF82 04
   FFFFFF82 FFFFFFC2 FFFFFF80 FFFFFF84 00 FFFFFF82 11 01 04 61 72 67 73 15 02 FFFFFF82
   12 10 05 15 FFFFFF82 13 FFFFFF82 15 09 03 FFFFFF82 14 04 02 0A 3C
   72 65 70 65 61 74 65 64 3E 30 04 FFFFFF82 16 FFFFFF82 18 10
   04 3C 1B FFFFFF82 17 10 03 23 FFFFFF82 18 04 09 FFFFFF82 19 00 FFFFFF84
   FFFFFF80 FFFFFF80 FFFFFF82 00 26 02 03 5F 24 32 08 0B FFFFFF82 1B FFFFFF82 04
   FFFFFF82 FFFFFF80 FFFFFFA0 FFFFFF80 04 FFFFFF82 1C 01 05 61 72 67 73 20 10 05
   15 FFFFFF82 13 FFFFFF82 1D 30 04 FFFFFF82 1E FFFFFF82 20 10 04 3C 1B FFFFFF82
   1F 10 03 23 FFFFFF82 20 04 09 FFFFFF82 19 00 FFFFFF84 FFFFFF80 FFFFFF80 FFFFFF82 00
   26 08 07 19 FFFFFF82 04 FFFFFF84 00 FFFFFF82 22 14 06 FFFFFF82 23 FFFFFF82 24
   FFFFFF82 25 10 03 3C FFFFFF82 04 08 08 FFFFFF82 08 FFFFFF82 21 FFFFFFC0 00 FFFFFF82
   0A 08 08 FFFFFF82 10 FFFFFF82 21 FFFFFFC0 00 FFFFFF82 26 10 05 15 FFFFFF82 13
   FFFFFF82 27 30 04 FFFFFF82 28 FFFFFF82 2A 10 04 3C 1B FFFFFF82 29 10 03
   23 FFFFFF82 2A 04 09 FFFFFF82 19 00 FFFFFF84 FFFFFF80 FFFFFF80 FFFFFF82 00 26 08 08
   FFFFFF82 2C FFFFFF82 04 FFFFFF84 00 FFFFFF82 2D 01 07 67 65 74 41 72 67
   73 15 02 FFFFFF82 2E 10 06 FFFFFF82 2F FFFFFF82 32 FFFFFF81 32 0D 02 FFFFFF82
   30 0A 03 FFFFFF82 31 04 01 0A 63 6F 6C 6C 65 63 74 69
   6F 6E 09 04 FFFFFF82 33 FFFFFF82 30 02 08 53 65 71 75 65 6E
   63 65 08 08 FFFFFF82 35 FFFFFF82 04 FFFFFF84 00 FFFFFF82 36 01 0B 67 65
   74 41 72 67 54 79 70 65 73 15 02 FFFFFF82 37 10 06 FFFFFF82
   38 FFFFFF82 3B FFFFFF82 3D 0D 02 FFFFFF82 39 0A 04 FFFFFF82 3A FFFFFF82 30 01
   09 69 6D 6D 75 74 61 62 6C 65 09 04 FFFFFF82 3C FFFFFF82 39
   02 04 4C 69 73 74 30 04 FFFFFF82 3E FFFFFF82 40 10 04 0D 32
   FFFFFF82 3F 10 03 23 FFFFFF82 40 04 08 36 00 FFFFFF84 FFFFFF80 FFFFFF80 FFFFFF82 00
   26 08 0A FFFFFF82 42 FFFFFF82 34 FFFFFF81 FFFFFF80 FFFFFF80 00 FFFFFF82 43 01 08 24
   61 6E 6F 6E 66 75 6E 0B 00 08 08 FFFFFF82 45 FFFFFF82 04 FFFFFF84
   00 FFFFFF82 46 01 09 61 72 67 73 4D 61 74 63 68 14 03
   76 FFFFFF82 47 08 08 FFFFFF82 48 FFFFFF82 44 FFFFFFC0 00 FFFFFF82 49 01 01 6D
   10 04 FFFFFF82 4A FFFFFF82 4C 0D 02 FFFFFF82 4B 0A 02 03 0E 09 04
   FFFFFF82 4D FFFFFF82 4B 02 06 4D 65 74 68 6F 64 08 08 FFFFFF82 4F
   FFFFFF82 04 FFFFFF84 00 FFFFFF82 50 01 14 67 65 74 44 65 63 6C 61
   72 65 64 4D 65 74 68 6F 64 73 4F 6E 14 04 FFFFFF82 49
   FFFFFF82 51 08 08 FFFFFF81 7B FFFFFF82 4E FFFFFFC0 00 FFFFFF81 32 08 08 FFFFFF82 53
   FFFFFF82 04 FFFFFF84 00 FFFFFF82 54 01 0B 67 65 74 4D 65 74 68 6F
   64 4F 6E 14 04 FFFFFF82 49 FFFFFF82 55 08 08 FFFFFF81 7B FFFFFF82 52 FFFFFFC0
   00 FFFFFF81 32 06 0A FFFFFF82 57 09 FFFFFF84 FFFFFF80 FFFFFF80 FFFFFF80 00 FFFFFF82 58 02
   0A 52 69 63 68 53 79 6D 62 6F 6C 13 04 FFFFFF82 56 0C
   14 08 0B FFFFFF82 08 FFFFFF82 56 FFFFFF82 FFFFFF80 FFFFFFA0 FFFFFF80 04 FFFFFF82 0A 08 07
   19 FFFFFF82 56 FFFFFF84 00 FFFFFF82 5B 14 04 FFFFFF82 5C FFFFFF82 5D 10 03 3C
   FFFFFF82 56 08 08 FFFFFF82 08 FFFFFF82 5A FFFFFFC0 00 FFFFFF82 0A 08 08 FFFFFF81 17
   FFFFFF82 56 FFFFFF84 00 FFFFFF82 5F 14 04 FFFFFF82 23 FFFFFF82 60 08 08 FFFFFF82 10
   FFFFFF82 5E FFFFFFC0 00 FFFFFF82 61 10 05 15 FFFFFF82 13 FFFFFF82 62 30 04 FFFFFF82
   63 FFFFFF82 65 10 04 3C 1B FFFFFF82 64 10 03 23 FFFFFF82 65 04 09
   FFFFFF82 66 00 FFFFFF84 FFFFFF80 FFFFFF80 FFFFFF82 00 26 02 03 5F 24 33 08 07
   FFFFFF82 68 09 FFFFFF84 01 FFFFFF82 69 01 0E 6D 61 6B 65 52 69 63
   68 53 79 6D 62 6F 6C 14 04 FFFFFF82 5C FFFFFF82 6A 08 08 FFFFFF82
   08 FFFFFF82 67 FFFFFFC0 00 FFFFFF82 0A 06 06 FFFFFF82 6C 09 00 FFFFFF82 6D 02
   13 52 65 66 6C 65 63 74 69 6F 6E 4F 70 65 72 61
   74 6F 72 73 15 04 FFFFFF82 6E FFFFFF82 72 13 04 FFFFFF82 6B 0C 14
   08 0B FFFFFF82 70 FFFFFF82 6B FFFFFF82 FFFFFF80 FFFFFFA0 FFFFFF80 04 FFFFFF82 71 01 04 73
   65 6C 66 10 03 23 FFFFFF82 72 04 0A 25 FFFFFF82 6B FFFFFF84 FFFFFF80 FFFFFF80
   FFFFFFC2 00 FFFFFF81 31 08 07 19 FFFFFF82 6B FFFFFF84 00 FFFFFF82 74 14 04 FFFFFF82
   75 FFFFFF82 76 10 05 3C FFFFFF82 6B FFFFFF82 71 08 08 FFFFFF82 70 FFFFFF82 73
   FFFFFFC0 00 FFFFFF82 71 08 09 2E FFFFFF82 6B FFFFFFC2 FFFFFF80 FFFFFF84 00 FFFFFF82 78 15
   02 FFFFFF82 79 10 04 0D 32 FFFFFF82 71 08 08 56 FFFFFF82 6B FFFFFFA0 FFFFFF80
   04 FFFFFF82 79 08 08 FFFFFF82 7C FFFFFF82 6B FFFFFF84 00 FFFFFF82 7D 01 01 6F
   14 03 2A FFFFFF82 7E 08 08 FFFFFF82 08 FFFFFF82 7B FFFFFFC0 00 FFFFFF82 0A 08
   08 FFFFFF82 7C FFFFFF82 6B FFFFFF84 00 FFFFFF83 00 14 03 2A FFFFFF83 01 08 08
   FFFFFF83 02 FFFFFF82 7F FFFFFFC0 00 FFFFFF82 23 01 06 73 79 6D 41 70 70
   08 08 FFFFFF83 04 FFFFFF82 6B FFFFFF84 00 FFFFFF83 05 01 02 6F 6F 15 04
   FFFFFF83 06 FFFFFF83 08 14 04 FFFFFF83 07 FFFFFF83 0A 10 03 23 FFFFFF83 08 04
   0A FFFFFF83 09 FFFFFF83 03 FFFFFF84 FFFFFF80 FFFFFF80 FFFFFFC2 00 26 02 01 52 08 08
   FFFFFF82 08 FFFFFF83 03 FFFFFFC0 00 FFFFFF82 0A 08 08 FFFFFF83 04 FFFFFF82 6B FFFFFF84 00
   FFFFFF83 0C 15 04 FFFFFF83 0D FFFFFF83 0F 14 04 FFFFFF83 0E FFFFFF83 10 10 03
   23 FFFFFF83 0F 04 0A FFFFFF83 09 FFFFFF83 0B FFFFFF84 FFFFFF80 FFFFFF80 FFFFFFC2 00 26 08
   08 FFFFFF83 02 FFFFFF83 0B FFFFFFC0 00 FFFFFF82 23 08 07 FFFFFF83 12 09 FFFFFF84 01
   FFFFFF83 13 01 17 6D 61 6B 65 52 65 66 6C 65 63 74 69
   6F 6E 4F 70 65 72 61 74 6F 72 73 15 04 FFFFFF83 14 FFFFFF83
   17 14 04 FFFFFF83 15 FFFFFF83 18 10 05 3C FFFFFF82 6B FFFFFF83 16 10 03
   23 FFFFFF83 17 04 0A 25 FFFFFF83 11 FFFFFF84 FFFFFF80 FFFFFF80 FFFFFFC2 00 FFFFFF81 31 08
   08 FFFFFF81 7B FFFFFF83 11 FFFFFFC0 00 FFFFFF83 16 08 07 FFFFFF83 1A 09 FFFFFF84 00
   FFFFFF83 1B 01 0E 67 65 74 41 6E 79 56 61 6C 43 6C 61
   73 73 14 04 FFFFFF83 1C FFFFFF83 20 30 04 FFFFFF83 1D FFFFFF83 1F 10 04
   0D 32 FFFFFF83 1E 10 03 23 FFFFFF83 1F 04 08 54 00 FFFFFF84 FFFFFF80 FFFFFF80
   FFFFFF82 00 26 08 07 FFFFFF81 7B FFFFFF83 19 FFFFFFC0 00 40 28 03 09 FFFFFF83
   22 10 04 FFFFFF83 23 FFFFFF83 26 0D 02 FFFFFF83 24 0A 03 FFFFFF83 25 04
   01 0A 61 6E 6E 6F 74 61 74 69 6F 6E 09 04 FFFFFF83 27
   FFFFFF83 24 02 0C 65 78 70 65 72 69 6D 65 6E 74 61 6C
   
  InnerClass: 
   public #41= #38 of #40; //RichSymbol=class scala/reflect/Invocation$RichSymbol of class scala/reflect/Invocation
   public #44= #43 of #40; //PreservedAnyVal=class scala/reflect/Invocation$PreservedAnyVal of class scala/reflect/Invocation
   public #47= #46 of #40; //PreservedAnyRef=class scala/reflect/Invocation$PreservedAnyRef of class scala/reflect/Invocation
   public abstract #50= #49 of #40; //PrimitivePreserver=class scala/reflect/Invocation$PrimitivePreserver of class scala/reflect/Invocation
   public #53= #52 of #40; //ReflectionOperators=class scala/reflect/Invocation$ReflectionOperators of class scala/reflect/Invocation
   public #56= #55 of #40; //SymbolWithArguments=class scala/reflect/Invocation$SymbolWithArguments of class scala/reflect/Invocation
  minor version: 0
  major version: 49
  Constant pool:
const #1 = Asciz	SourceFile;
const #2 = Asciz	Invocation.scala;
const #3 = Asciz	getAnyValClass;
const #4 = Asciz	(Ljava/lang/Object;)Ljava/lang/Class;;
const #5 = Asciz	Code;
const #6 = Asciz	scala/reflect/Invocation$;
const #7 = class	#6;	//  scala/reflect/Invocation$
const #8 = Asciz	MODULE$;
const #9 = Asciz	Lscala/reflect/Invocation$;;
const #10 = NameAndType	#8:#9;//  MODULE$:Lscala/reflect/Invocation$;
const #11 = Field	#7.#10;	//  scala/reflect/Invocation$.MODULE$:Lscala/reflect/Invocation$;
const #12 = NameAndType	#3:#4;//  getAnyValClass:(Ljava/lang/Object;)Ljava/lang/Class;
const #13 = Method	#7.#12;	//  scala/reflect/Invocation$.getAnyValClass:(Ljava/lang/Object;)Ljava/lang/Class;
const #14 = Asciz	(Ljava/lang/Object;)Ljava/lang/Class<*>;;
const #15 = Asciz	Signature;
const #16 = Asciz	makeReflectionOperators;
const #17 = Asciz	(Ljava/lang/Object;)Lscala/reflect/Invocation$ReflectionOperators;;
const #18 = NameAndType	#16:#17;//  makeReflectionOperators:(Ljava/lang/Object;)Lscala/reflect/Invocation$ReflectionOperators;
const #19 = Method	#7.#18;	//  scala/reflect/Invocation$.makeReflectionOperators:(Ljava/lang/Object;)Lscala/reflect/Invocation$ReflectionOperators;
const #20 = Asciz	<T:Ljava/lang/Object;>(TT;)Lscala/reflect/Invocation$ReflectionOperators<TT;>;;
const #21 = Asciz	makeRichSymbol;
const #22 = Asciz	(Lscala/Symbol;)Lscala/reflect/Invocation$RichSymbol;;
const #23 = NameAndType	#21:#22;//  makeRichSymbol:(Lscala/Symbol;)Lscala/reflect/Invocation$RichSymbol;
const #24 = Method	#7.#23;	//  scala/reflect/Invocation$.makeRichSymbol:(Lscala/Symbol;)Lscala/reflect/Invocation$RichSymbol;
const #25 = Asciz	makePreservedAnyVal;
const #26 = Asciz	(Ljava/lang/Object;)Lscala/reflect/Invocation$PreservedAnyVal;;
const #27 = NameAndType	#25:#26;//  makePreservedAnyVal:(Ljava/lang/Object;)Lscala/reflect/Invocation$PreservedAnyVal;
const #28 = Method	#7.#27;	//  scala/reflect/Invocation$.makePreservedAnyVal:(Ljava/lang/Object;)Lscala/reflect/Invocation$PreservedAnyVal;
const #29 = Asciz	<T:Ljava/lang/Object;>(TT;)Lscala/reflect/Invocation$PreservedAnyVal<TT;>;;
const #30 = Asciz	makePreservedAnyRef;
const #31 = Asciz	(Ljava/lang/Object;)Lscala/reflect/Invocation$PreservedAnyRef;;
const #32 = NameAndType	#30:#31;//  makePreservedAnyRef:(Ljava/lang/Object;)Lscala/reflect/Invocation$PreservedAnyRef;
const #33 = Method	#7.#32;	//  scala/reflect/Invocation$.makePreservedAnyRef:(Ljava/lang/Object;)Lscala/reflect/Invocation$PreservedAnyRef;
const #34 = Asciz	<T:Ljava/lang/Object;>(TT;)Lscala/reflect/Invocation$PreservedAnyRef<TT;>;;
const #35 = Asciz	ScalaSig;
const #36 = Asciz	InnerClasses;
const #37 = Asciz	scala/reflect/Invocation$RichSymbol;
const #38 = class	#37;	//  scala/reflect/Invocation$RichSymbol
const #39 = Asciz	scala/reflect/Invocation;
const #40 = class	#39;	//  scala/reflect/Invocation
const #41 = Asciz	RichSymbol;
const #42 = Asciz	scala/reflect/Invocation$PreservedAnyVal;
const #43 = class	#42;	//  scala/reflect/Invocation$PreservedAnyVal
const #44 = Asciz	PreservedAnyVal;
const #45 = Asciz	scala/reflect/Invocation$PreservedAnyRef;
const #46 = class	#45;	//  scala/reflect/Invocation$PreservedAnyRef
const #47 = Asciz	PreservedAnyRef;
const #48 = Asciz	scala/reflect/Invocation$PrimitivePreserver;
const #49 = class	#48;	//  scala/reflect/Invocation$PrimitivePreserver
const #50 = Asciz	PrimitivePreserver;
const #51 = Asciz	scala/reflect/Invocation$ReflectionOperators;
const #52 = class	#51;	//  scala/reflect/Invocation$ReflectionOperators
const #53 = Asciz	ReflectionOperators;
const #54 = Asciz	scala/reflect/Invocation$SymbolWithArguments;
const #55 = class	#54;	//  scala/reflect/Invocation$SymbolWithArguments
const #56 = Asciz	SymbolWithArguments;
const #57 = Asciz	java/lang/Object;
const #58 = class	#57;	//  java/lang/Object

{
public static final java.lang.Class getAnyValClass(java.lang.Object);
  Code:
   Stack=2, Locals=1, Args_size=1
   0:	getstatic	#11; //Field scala/reflect/Invocation$.MODULE$:Lscala/reflect/Invocation$;
   3:	aload_0
   4:	invokevirtual	#13; //Method scala/reflect/Invocation$.getAnyValClass:(Ljava/lang/Object;)Ljava/lang/Class;
   7:	areturn
  Signature: length = 0x2
   00 0E 

public static final scala.reflect.Invocation$ReflectionOperators makeReflectionOperators(java.lang.Object);
  Code:
   Stack=2, Locals=1, Args_size=1
   0:	getstatic	#11; //Field scala/reflect/Invocation$.MODULE$:Lscala/reflect/Invocation$;
   3:	aload_0
   4:	invokevirtual	#19; //Method scala/reflect/Invocation$.makeReflectionOperators:(Ljava/lang/Object;)Lscala/reflect/Invocation$ReflectionOperators;
   7:	areturn
  Signature: length = 0x2
   00 14 

public static final scala.reflect.Invocation$RichSymbol makeRichSymbol(scala.Symbol);
  Code:
   Stack=2, Locals=1, Args_size=1
   0:	getstatic	#11; //Field scala/reflect/Invocation$.MODULE$:Lscala/reflect/Invocation$;
   3:	aload_0
   4:	invokevirtual	#24; //Method scala/reflect/Invocation$.makeRichSymbol:(Lscala/Symbol;)Lscala/reflect/Invocation$RichSymbol;
   7:	areturn

public static final scala.reflect.Invocation$PreservedAnyVal makePreservedAnyVal(java.lang.Object);
  Code:
   Stack=2, Locals=1, Args_size=1
   0:	getstatic	#11; //Field scala/reflect/Invocation$.MODULE$:Lscala/reflect/Invocation$;
   3:	aload_0
   4:	invokevirtual	#28; //Method scala/reflect/Invocation$.makePreservedAnyVal:(Ljava/lang/Object;)Lscala/reflect/Invocation$PreservedAnyVal;
   7:	areturn
  Signature: length = 0x2
   00 1D 

public static final scala.reflect.Invocation$PreservedAnyRef makePreservedAnyRef(java.lang.Object);
  Code:
   Stack=2, Locals=1, Args_size=1
   0:	getstatic	#11; //Field scala/reflect/Invocation$.MODULE$:Lscala/reflect/Invocation$;
   3:	aload_0
   4:	invokevirtual	#33; //Method scala/reflect/Invocation$.makePreservedAnyRef:(Ljava/lang/Object;)Lscala/reflect/Invocation$PreservedAnyRef;
   7:	areturn
  Signature: length = 0x2
   00 22 

}

