Compiled from "Symbol.scala"
public final class scala.reflect.LabelSymbol$ extends java.lang.Object implements scala.Function1,scala.ScalaObject
  SourceFile: "Symbol.scala"
  Scala: length = 0x
   
  minor version: 0
  major version: 49
  Constant pool:
const #1 = Asciz	SourceFile;
const #2 = Asciz	Symbol.scala;
const #3 = Asciz	Scala;
const #4 = Asciz	MODULE$;
const #5 = Asciz	Lscala/reflect/LabelSymbol$;;
const #6 = Asciz	<clinit>;
const #7 = Asciz	()V;
const #8 = Asciz	Code;
const #9 = Asciz	scala/reflect/LabelSymbol$;
const #10 = class	#9;	//  scala/reflect/LabelSymbol$
const #11 = Asciz	<init>;
const #12 = NameAndType	#11:#7;//  "<init>":()V
const #13 = Method	#10.#12;	//  scala/reflect/LabelSymbol$."<init>":()V
const #14 = Asciz	LineNumberTable;
const #15 = Asciz	java/lang/Object;
const #16 = class	#15;	//  java/lang/Object
const #17 = Method	#16.#12;	//  java/lang/Object."<init>":()V
const #18 = NameAndType	#4:#5;//  MODULE$:Lscala/reflect/LabelSymbol$;
const #19 = Field	#10.#18;	//  scala/reflect/LabelSymbol$.MODULE$:Lscala/reflect/LabelSymbol$;
const #20 = Asciz	scala/Function1$class;
const #21 = class	#20;	//  scala/Function1$class
const #22 = Asciz	$init$;
const #23 = Asciz	(Lscala/Function1;)V;
const #24 = NameAndType	#22:#23;//  $init$:(Lscala/Function1;)V
const #25 = Method	#21.#24;	//  scala/Function1$class.$init$:(Lscala/Function1;)V
const #26 = Asciz	apply;
const #27 = Asciz	(Ljava/lang/Object;)Ljava/lang/Object;;
const #28 = Asciz	java/lang/String;
const #29 = class	#28;	//  java/lang/String
const #30 = Asciz	(Ljava/lang/String;)Lscala/reflect/LabelSymbol;;
const #31 = NameAndType	#26:#30;//  apply:(Ljava/lang/String;)Lscala/reflect/LabelSymbol;
const #32 = Method	#10.#31;	//  scala/reflect/LabelSymbol$.apply:(Ljava/lang/String;)Lscala/reflect/LabelSymbol;
const #33 = Asciz	this;
const #34 = Asciz	v1;
const #35 = Asciz	Ljava/lang/Object;;
const #36 = Asciz	LocalVariableTable;
const #37 = Asciz	scala/reflect/LabelSymbol;
const #38 = class	#37;	//  scala/reflect/LabelSymbol
const #39 = Asciz	(Ljava/lang/String;)V;
const #40 = NameAndType	#11:#39;//  "<init>":(Ljava/lang/String;)V
const #41 = Method	#38.#40;	//  scala/reflect/LabelSymbol."<init>":(Ljava/lang/String;)V
const #42 = Asciz	name;
const #43 = Asciz	Ljava/lang/String;;
const #44 = Asciz	unapply;
const #45 = Asciz	(Lscala/reflect/LabelSymbol;)Lscala/Some;;
const #46 = Asciz	scala/Some;
const #47 = class	#46;	//  scala/Some
const #48 = Asciz	()Ljava/lang/String;;
const #49 = NameAndType	#42:#48;//  name:()Ljava/lang/String;
const #50 = Method	#38.#49;	//  scala/reflect/LabelSymbol.name:()Ljava/lang/String;
const #51 = Asciz	(Ljava/lang/Object;)V;
const #52 = NameAndType	#11:#51;//  "<init>":(Ljava/lang/Object;)V
const #53 = Method	#47.#52;	//  scala/Some."<init>":(Ljava/lang/Object;)V
const #54 = Asciz	x$0;
const #55 = Asciz	Lscala/reflect/LabelSymbol;;
const #56 = Asciz	andThen;
const #57 = Asciz	(Lscala/Function1;)Lscala/Function1;;
const #58 = Asciz	(Lscala/Function1;Lscala/Function1;)Lscala/Function1;;
const #59 = NameAndType	#56:#58;//  andThen:(Lscala/Function1;Lscala/Function1;)Lscala/Function1;
const #60 = Method	#21.#59;	//  scala/Function1$class.andThen:(Lscala/Function1;Lscala/Function1;)Lscala/Function1;
const #61 = Asciz	g;
const #62 = Asciz	Lscala/Function1;;
const #63 = Asciz	compose;
const #64 = NameAndType	#63:#58;//  compose:(Lscala/Function1;Lscala/Function1;)Lscala/Function1;
const #65 = Method	#21.#64;	//  scala/Function1$class.compose:(Lscala/Function1;Lscala/Function1;)Lscala/Function1;
const #66 = Asciz	toString;
const #67 = Asciz	(Lscala/Function1;)Ljava/lang/String;;
const #68 = NameAndType	#66:#67;//  toString:(Lscala/Function1;)Ljava/lang/String;
const #69 = Method	#21.#68;	//  scala/Function1$class.toString:(Lscala/Function1;)Ljava/lang/String;
const #70 = Asciz	scala/Function1;
const #71 = class	#70;	//  scala/Function1
const #72 = Asciz	scala/ScalaObject;
const #73 = class	#72;	//  scala/ScalaObject

{
public static final scala.reflect.LabelSymbol$ MODULE$;

public static {};
  Code:
   Stack=1, Locals=0, Args_size=0
   0:	new	#10; //class scala/reflect/LabelSymbol$
   3:	invokespecial	#13; //Method "<init>":()V
   6:	return

public java.lang.Object apply(java.lang.Object);
  Code:
   Stack=2, Locals=2, Args_size=2
   0:	aload_0
   1:	aload_1
   2:	checkcast	#29; //class java/lang/String
   5:	invokevirtual	#32; //Method apply:(Ljava/lang/String;)Lscala/reflect/LabelSymbol;
   8:	areturn
  LineNumberTable: 
   line 71: 0

  LocalVariableTable: 
   Start  Length  Slot  Name   Signature
   0      9      0    this       Lscala/reflect/LabelSymbol$;
   0      9      1    v1       Ljava/lang/Object;


public scala.reflect.LabelSymbol apply(java.lang.String);
  Code:
   Stack=3, Locals=2, Args_size=2
   0:	new	#38; //class scala/reflect/LabelSymbol
   3:	dup
   4:	aload_1
   5:	invokespecial	#41; //Method scala/reflect/LabelSymbol."<init>":(Ljava/lang/String;)V
   8:	areturn
  LineNumberTable: 
   line 71: 0

  LocalVariableTable: 
   Start  Length  Slot  Name   Signature
   0      9      0    this       Lscala/reflect/LabelSymbol$;
   0      9      1    name       Ljava/lang/String;


public scala.Some unapply(scala.reflect.LabelSymbol);
  Code:
   Stack=3, Locals=2, Args_size=2
   0:	new	#47; //class scala/Some
   3:	dup
   4:	aload_1
   5:	invokevirtual	#50; //Method scala/reflect/LabelSymbol.name:()Ljava/lang/String;
   8:	invokespecial	#53; //Method scala/Some."<init>":(Ljava/lang/Object;)V
   11:	areturn
  LineNumberTable: 
   line 71: 0

  LocalVariableTable: 
   Start  Length  Slot  Name   Signature
   0      12      0    this       Lscala/reflect/LabelSymbol$;
   0      12      1    x$0       Lscala/reflect/LabelSymbol;


public scala.Function1 andThen(scala.Function1);
  Code:
   Stack=2, Locals=2, Args_size=2
   0:	aload_0
   1:	aload_1
   2:	invokestatic	#60; //Method scala/Function1$class.andThen:(Lscala/Function1;Lscala/Function1;)Lscala/Function1;
   5:	areturn
  LineNumberTable: 
   line 71: 0

  LocalVariableTable: 
   Start  Length  Slot  Name   Signature
   0      6      0    this       Lscala/reflect/LabelSymbol$;
   0      6      1    g       Lscala/Function1;


public scala.Function1 compose(scala.Function1);
  Code:
   Stack=2, Locals=2, Args_size=2
   0:	aload_0
   1:	aload_1
   2:	invokestatic	#65; //Method scala/Function1$class.compose:(Lscala/Function1;Lscala/Function1;)Lscala/Function1;
   5:	areturn
  LineNumberTable: 
   line 71: 0

  LocalVariableTable: 
   Start  Length  Slot  Name   Signature
   0      6      0    this       Lscala/reflect/LabelSymbol$;
   0      6      1    g       Lscala/Function1;


public java.lang.String toString();
  Code:
   Stack=1, Locals=1, Args_size=1
   0:	aload_0
   1:	invokestatic	#69; //Method scala/Function1$class.toString:(Lscala/Function1;)Ljava/lang/String;
   4:	areturn
  LineNumberTable: 
   line 71: 0


}

