Compiled from "Tree.scala"
public class scala.reflect.Literal extends scala.reflect.Tree implements scala.ScalaObject,scala.Product,java.io.Serializable
  SourceFile: "Tree.scala"
  ScalaSig: length = 0x329
   05 00 7B 06 08 01 02 FFFFFF84 FFFFFF80 FFFFFF80 FFFFFF80 40 07 02 07 4C
   69 74 65 72 61 6C 0A 02 03 04 01 07 72 65 66 6C
   65 63 74 0A 01 05 01 05 73 63 61 6C 61 03 00 13
   04 00 08 0C 10 10 02 09 0A 0D 01 02 09 02 0B 02
   02 04 54 72 65 65 10 02 0D 0E 0D 01 04 09 02 0F
   04 02 0B 53 63 61 6C 61 4F 62 6A 65 63 74 10 02
   0D 11 09 02 12 04 02 07 50 72 6F 64 75 63 74 08
   08 14 00 FFFFFF82 FFFFFFCA FFFFFF80 FFFFFF84 00 15 01 05 76 61 6C 75 65
   15 01 16 10 02 0D 17 09 02 18 04 02 03 41 6E 79
   08 08 1A 00 FFFFFF82 FFFFFF88 FFFFFFA0 FFFFFF80 04 16 01 06 76 61 6C 75
   65 20 08 05 1C 00 FFFFFF84 00 1D 01 06 3C 69 6E 69 74
   3E 14 02 1E 1F 10 02 09 00 08 05 14 1B FFFFFFC0 00 16
   08 07 21 00 FFFFFF81 FFFFFF80 FFFFFF84 00 22 01 04 63 6F 70 79 14
   02 1E 23 08 08 24 14 20 FFFFFF90 FFFFFF80 FFFFFFC0 00 16 08 07 25
   00 FFFFFF91 FFFFFF80 FFFFFF84 00 26 01 0E 63 6F 70 79 24 64 65 66
   61 75 6C 74 24 31 15 01 27 2A 02 16 28 2B 01 29
   10 02 2A 2F 0D 01 2B 0A 02 2C 2D 01 09 75 6E 63
   68 65 63 6B 65 64 0A 02 2E 04 01 0A 61 6E 6E 6F
   74 61 74 69 6F 6E 09 02 30 2B 02 11 75 6E 63 68
   65 63 6B 65 64 56 61 72 69 61 6E 63 65 08 08 32
   00 FFFFFF84 FFFFFF80 FFFFFF80 FFFFFF84 20 33 01 08 68 61 73 68 43 6F 64
   65 14 01 34 10 02 0D 35 09 02 36 04 02 03 49 6E
   74 08 08 38 00 FFFFFF84 FFFFFF80 FFFFFF80 FFFFFF84 20 39 01 08 74 6F 53
   74 72 69 6E 67 14 01 3A 10 02 3B 3E 0E 02 0D 3C
   09 02 3D 04 01 06 50 72 65 64 65 66 09 02 3F 40
   02 06 53 74 72 69 6E 67 0A 02 3D 04 08 08 42 00
   FFFFFF84 FFFFFF80 FFFFFF80 FFFFFF84 20 43 01 06 65 71 75 61 6C 73 14 02
   44 47 10 02 0D 45 09 02 46 04 02 07 42 6F 6F 6C
   65 61 6E 08 07 48 41 FFFFFF81 FFFFFF80 FFFFFFC0 00 16 01 03 78 24
   31 08 08 4A 00 FFFFFF84 FFFFFF80 FFFFFF80 FFFFFF84 20 4B 01 0D 70 72 6F
   64 75 63 74 50 72 65 66 69 78 15 01 4C 10 02 4D
   52 0D 01 4E 0A 02 4F 50 01 04 6C 61 6E 67 0A 01
   51 01 04 6A 61 76 61 09 02 3F 4E 08 08 54 00 FFFFFF84
   FFFFFF80 FFFFFF80 FFFFFF84 20 55 01 0C 70 72 6F 64 75 63 74 41 72
   69 74 79 15 01 34 08 08 57 00 FFFFFF84 FFFFFF80 FFFFFF80 FFFFFF84 20 58
   01 0E 70 72 6F 64 75 63 74 45 6C 65 6D 65 6E 74
   14 02 16 59 08 07 48 56 FFFFFF81 FFFFFF80 FFFFFFC0 00 34 08 08 5B
   00 FFFFFF84 FFFFFF80 FFFFFF80 FFFFFF84 20 5C 01 08 63 61 6E 45 71 75 61
   6C 14 02 44 5D 08 07 48 5A FFFFFF81 FFFFFF80 FFFFFFC0 00 16 28 02
   00 5F 10 02 0D 60 09 02 61 04 02 0C 73 65 72 69
   61 6C 69 7A 61 62 6C 65 07 07 63 02 FFFFFF81 FFFFFF80 FFFFFF88 02
   64 01 07 4C 69 74 65 72 61 6C 10 02 09 65 06 08
   01 02 FFFFFF84 FFFFFF81 FFFFFF80 FFFFFF88 02 66 13 04 65 67 6A 0C 10 02
   4D 68 09 02 69 4E 02 06 4F 62 6A 65 63 74 10 04
   0D 6B 16 1E 09 02 6C 04 02 09 46 75 6E 63 74 69
   6F 6E 31 08 05 1C 65 FFFFFF84 00 6E 14 01 64 08 07 70
   65 FFFFFF81 FFFFFF80 FFFFFF84 40 71 01 05 61 70 70 6C 79 14 02 1E
   72 08 05 14 6F FFFFFFC0 00 16 08 07 74 65 FFFFFF81 FFFFFF80 FFFFFF84 40
   75 01 07 75 6E 61 70 70 6C 79 14 02 76 79 10 03
   0D 77 16 09 02 78 04 02 04 53 6F 6D 65 08 05 7A
   73 FFFFFFC0 00 1E 01 03 78 24 30 
  minor version: 0
  major version: 49
  Constant pool:
Asciz	SourceFile;
Asciz	Tree.scala;
Asciz	andThen;
Asciz	(Lscala/Function1;)Lscala/Function1;;
Asciz	Code;
Asciz	scala/reflect/Literal$;
class	scala/reflect/Literal$
Asciz	MODULE$;
Asciz	Lscala/reflect/Literal$;;
NameAndType	MODULE$:Lscala/reflect/Literal$;
Field	scala/reflect/Literal$.MODULE$:Lscala/reflect/Literal$;
NameAndType	andThen:(Lscala/Function1;)Lscala/Function1;
Method	scala/reflect/Literal$.andThen:(Lscala/Function1;)Lscala/Function1;
Asciz	compose;
NameAndType	compose:(Lscala/Function1;)Lscala/Function1;
Method	scala/reflect/Literal$.compose:(Lscala/Function1;)Lscala/Function1;
Asciz	value;
Asciz	Ljava/lang/Object;;
Asciz	<init>;
Asciz	(Ljava/lang/Object;)V;
Asciz	LineNumberTable;
Asciz	scala/reflect/Literal;
class	scala/reflect/Literal
NameAndType	value:Ljava/lang/Object;
Field	scala/reflect/Literal.value:Ljava/lang/Object;
Asciz	scala/reflect/Tree;
class	scala/reflect/Tree
Asciz	()V;
NameAndType	"<init>":()V
Method	scala/reflect/Tree."<init>":()V
Asciz	scala/Product$class;
class	scala/Product$class
Asciz	$init$;
Asciz	(Lscala/Product;)V;
NameAndType	$init$:(Lscala/Product;)V
Method	scala/Product$class.$init$:(Lscala/Product;)V
Asciz	this;
Asciz	Lscala/reflect/Literal;;
Asciz	LocalVariableTable;
Asciz	gd3$1;
Asciz	(Ljava/lang/Object;)Z;
Asciz	()Ljava/lang/Object;;
NameAndType	value:()Ljava/lang/Object;
Method	scala/reflect/Literal.value:()Ljava/lang/Object;
Asciz	java/lang/Number;
class	java/lang/Number
Asciz	java/lang/Character;
class	java/lang/Character
Asciz	scala/runtime/BoxesRunTime;
class	scala/runtime/BoxesRunTime
Asciz	equals2;
Asciz	(Ljava/lang/Object;Ljava/lang/Object;)Z;
NameAndType	equals2:(Ljava/lang/Object;Ljava/lang/Object;)Z
Method	scala/runtime/BoxesRunTime.equals2:(Ljava/lang/Object;Ljava/lang/Object;)Z
Asciz	java/lang/Object;
class	java/lang/Object
Asciz	equals;
NameAndType	equals:(Ljava/lang/Object;)Z
Method	java/lang/Object.equals:(Ljava/lang/Object;)Z
Asciz	y0;
Asciz	canEqual;
Asciz	productElement;
Asciz	(I)Ljava/lang/Object;;
Asciz	scala/MatchError;
class	scala/MatchError
Asciz	boxToInteger;
Asciz	(I)Ljava/lang/Integer;;
NameAndType	boxToInteger:(I)Ljava/lang/Integer;
Method	scala/runtime/BoxesRunTime.boxToInteger:(I)Ljava/lang/Integer;
Asciz	toString;
Asciz	()Ljava/lang/String;;
NameAndType	toString:()Ljava/lang/String;
Method	java/lang/Object.toString:()Ljava/lang/String;
Asciz	(Ljava/lang/String;)V;
NameAndType	"<init>":(Ljava/lang/String;)V
Method	scala/MatchError."<init>":(Ljava/lang/String;)V
Asciz	java/lang/IndexOutOfBoundsException;
class	java/lang/IndexOutOfBoundsException
Method	java/lang/IndexOutOfBoundsException."<init>":(Ljava/lang/String;)V
Asciz	productArity;
Asciz	()I;
Asciz	productPrefix;
Asciz	Literal;
String	Literal
NameAndType	gd3$1:(Ljava/lang/Object;)Z
Method	scala/reflect/Literal.gd3$1:(Ljava/lang/Object;)Z
Asciz	scala/Equals;
class	scala/Equals
NameAndType	canEqual:(Ljava/lang/Object;)Z
InterfaceMethod	scala/Equals.canEqual:(Ljava/lang/Object;)Z
Asciz	temp11;
Asciz	temp12;
Asciz	scala/runtime/ScalaRunTime$;
class	scala/runtime/ScalaRunTime$
Asciz	Lscala/runtime/ScalaRunTime$;;
NameAndType	MODULE$:Lscala/runtime/ScalaRunTime$;
Field	scala/runtime/ScalaRunTime$.MODULE$:Lscala/runtime/ScalaRunTime$;
Asciz	_toString;
Asciz	(Lscala/Product;)Ljava/lang/String;;
NameAndType	_toString:(Lscala/Product;)Ljava/lang/String;
Method	scala/runtime/ScalaRunTime$._toString:(Lscala/Product;)Ljava/lang/String;
Asciz	hashCode;
Asciz	_hashCode;
Asciz	(Lscala/Product;)I;
NameAndType	_hashCode:(Lscala/Product;)I
Method	scala/runtime/ScalaRunTime$._hashCode:(Lscala/Product;)I
Asciz	copy;
Asciz	(Ljava/lang/Object;)Lscala/reflect/Literal;;
NameAndType	"<init>":(Ljava/lang/Object;)V
Method	scala/reflect/Literal."<init>":(Ljava/lang/Object;)V
Asciz	copy$default$1;
Asciz	productElements;
Asciz	()Lscala/collection/Iterator;;
Asciz	(Lscala/Product;)Lscala/collection/Iterator;;
NameAndType	productElements:(Lscala/Product;)Lscala/collection/Iterator;
Method	scala/Product$class.productElements:(Lscala/Product;)Lscala/collection/Iterator;
Asciz	productIterator;
NameAndType	productIterator:(Lscala/Product;)Lscala/collection/Iterator;
Method	scala/Product$class.productIterator:(Lscala/Product;)Lscala/collection/Iterator;
Asciz	ScalaSig;
Asciz	scala/ScalaObject;
class	scala/ScalaObject
Asciz	scala/Product;
class	scala/Product
Asciz	java/io/Serializable;
class	java/io/Serializable

{
private final java.lang.Object value;
  Signature: Ljava/lang/Object;

public static final scala.Function1 andThen(scala.Function1);
  Signature: (Lscala/Function1;)Lscala/Function1;
  Code:
   Stack=2, Locals=1, Args_size=1
	getstatic	Field scala/reflect/Literal$.MODULE$:Lscala/reflect/Literal$;
	aload_0
	invokevirtual	Method scala/reflect/Literal$.andThen:(Lscala/Function1;)Lscala/Function1;
	areturn
  Labels:

public static final scala.Function1 compose(scala.Function1);
  Signature: (Lscala/Function1;)Lscala/Function1;
  Code:
   Stack=2, Locals=1, Args_size=1
	getstatic	Field scala/reflect/Literal$.MODULE$:Lscala/reflect/Literal$;
	aload_0
	invokevirtual	Method scala/reflect/Literal$.compose:(Lscala/Function1;)Lscala/Function1;
	areturn
  Labels:

public scala.reflect.Literal(java.lang.Object);
  Signature: (Ljava/lang/Object;)V
  Code:
   Stack=2, Locals=2, Args_size=2
	aload_0
	aload_1
	putfield	Field value:Ljava/lang/Object;
	aload_0
	invokespecial	Method scala/reflect/Tree."<init>":()V
	aload_0
	invokestatic	Method scala/Product$class.$init$:(Lscala/Product;)V
	return
  Labels:
  LocalVariableTable: 
   Start  Length  Slot  Name   Signature
   0      14      0    this       Lscala/reflect/Literal;
   0      14      1    value       Ljava/lang/Object;


private final boolean gd3$1(java.lang.Object);
  Signature: (Ljava/lang/Object;)Z
  Code:
   Stack=2, Locals=3, Args_size=2
	aload_0
	invokevirtual	Method value:()Ljava/lang/Object;
	astore_2
	aload_1
	aload_2
	if_acmpne	l1 // aload_1
	iconst_1
	goto	l2 // ifeq
l1	aload_1
	ifnonnull	l3 // aload_1
	iconst_0
	goto	l2 // ifeq
l3	aload_1
	instanceof	class java/lang/Number
	ifne	l4 // aload_1
	aload_1
	instanceof	class java/lang/Character
	ifeq	l5 // aload_1
l4	aload_1
	aload_2
	invokestatic	Method scala/runtime/BoxesRunTime.equals2:(Ljava/lang/Object;Ljava/lang/Object;)Z
	goto	l2 // ifeq
l5	aload_1
	aload_2
	invokevirtual	Method java/lang/Object.equals:(Ljava/lang/Object;)Z
l2	ifeq	l6 // iconst_0
	iconst_1
	goto	l7 // ireturn
l6	iconst_0
l7	ireturn
  Labels:
   	l1 = 14 // aload_1
   	l3 = 22 // aload_1
   	l4 = 36 // aload_1
   	l5 = 44 // aload_1
   	l2 = 49 // ifeq
   	l6 = 56 // iconst_0
   	l7 = 57 // ireturn
  LocalVariableTable: 
   Start  Length  Slot  Name   Signature
   0      58      0    this       Lscala/reflect/Literal;
   10      42      2    y0       Ljava/lang/Object;


public boolean canEqual(java.lang.Object);
  Signature: (Ljava/lang/Object;)Z
  Code:
   Stack=1, Locals=2, Args_size=2
	aload_1
	instanceof	class scala/reflect/Literal
	ireturn
  Labels:

public java.lang.Object productElement(int);
  Signature: (I)Ljava/lang/Object;
  Code:
   Stack=3, Locals=2, Args_size=2
	iload_1
	iconst_0
	if_icmpne	l1 // iconst_1
	iconst_1
	ifeq	l2 // new
	aload_0
	invokevirtual	Method value:()Ljava/lang/Object;
	areturn
l2	new	class scala/MatchError
	dup
	iload_1
	invokestatic	Method scala/runtime/BoxesRunTime.boxToInteger:(I)Ljava/lang/Integer;
	invokevirtual	Method java/lang/Object.toString:()Ljava/lang/String;
	invokespecial	Method scala/MatchError."<init>":(Ljava/lang/String;)V
	athrow
l1	iconst_1
	ifeq	l3 // new
	new	class java/lang/IndexOutOfBoundsException
	dup
	iload_1
	invokestatic	Method scala/runtime/BoxesRunTime.boxToInteger:(I)Ljava/lang/Integer;
	invokevirtual	Method java/lang/Object.toString:()Ljava/lang/String;
	invokespecial	Method java/lang/IndexOutOfBoundsException."<init>":(Ljava/lang/String;)V
	athrow
l3	new	class scala/MatchError
	dup
	iload_1
	invokestatic	Method scala/runtime/BoxesRunTime.boxToInteger:(I)Ljava/lang/Integer;
	invokevirtual	Method java/lang/Object.toString:()Ljava/lang/String;
	invokespecial	Method scala/MatchError."<init>":(Ljava/lang/String;)V
	athrow
  Labels:
   	l2 = 14 // new
   	l1 = 29 // iconst_1
   	l3 = 48 // new

public int productArity();
  Signature: ()I
  Code:
   Stack=1, Locals=1, Args_size=1
	iconst_1
	ireturn
  Labels:

public java.lang.String productPrefix();
  Signature: ()Ljava/lang/String;
  Code:
   Stack=1, Locals=1, Args_size=1
	ldc	String Literal
	areturn
  Labels:

public boolean equals(java.lang.Object);
  Signature: (Ljava/lang/Object;)Z
  Code:
   Stack=3, Locals=4, Args_size=2
	aload_0
	aload_1
	if_acmpeq	l1 // iconst_1
	aload_1
	instanceof	class scala/reflect/Literal
	ifeq	l2 // iconst_1
	aload_1
	checkcast	class scala/reflect/Literal
	astore_2
	aload_2
	invokevirtual	Method value:()Ljava/lang/Object;
	astore_3
	aload_0
	aload_3
	invokespecial	Method gd3$1:(Ljava/lang/Object;)Z
	ifeq	l3 // iconst_1
	aload_1
	checkcast	class scala/reflect/Literal
	aload_0
	invokeinterface	InterfaceMethod scala/Equals.canEqual:(Ljava/lang/Object;)Z
	goto	l4 // ifeq
l3	iconst_1
	ifeq	l5 // new
	iconst_0
	goto	l4 // ifeq
l5	new	class scala/MatchError
	dup
	aload_1
	invokevirtual	Method java/lang/Object.toString:()Ljava/lang/String;
	invokespecial	Method scala/MatchError."<init>":(Ljava/lang/String;)V
	athrow
l2	iconst_1
	ifeq	l6 // new
	iconst_0
l4	ifeq	l7 // iconst_0
l1	iconst_1
	goto	l8 // ireturn
l7	iconst_0
l8	ireturn
l6	new	class scala/MatchError
	dup
	aload_1
	invokevirtual	Method java/lang/Object.toString:()Ljava/lang/String;
	invokespecial	Method scala/MatchError."<init>":(Ljava/lang/String;)V
	athrow
  Labels:
   	l3 = 43 // iconst_1
   	l5 = 51 // new
   	l2 = 63 // iconst_1
   	l4 = 68 // ifeq
   	l1 = 71 // iconst_1
   	l7 = 75 // iconst_0
   	l8 = 76 // ireturn
   	l6 = 77 // new
  LocalVariableTable: 
   Start  Length  Slot  Name   Signature
   0      89      0    this       Lscala/reflect/Literal;
   17      46      2    temp11       Lscala/reflect/Literal;
   22      41      3    temp12       Ljava/lang/Object;


public java.lang.String toString();
  Signature: ()Ljava/lang/String;
  Code:
   Stack=2, Locals=1, Args_size=1
	getstatic	Field scala/runtime/ScalaRunTime$.MODULE$:Lscala/runtime/ScalaRunTime$;
	aload_0
	invokevirtual	Method scala/runtime/ScalaRunTime$._toString:(Lscala/Product;)Ljava/lang/String;
	areturn
  Labels:

public int hashCode();
  Signature: ()I
  Code:
   Stack=2, Locals=1, Args_size=1
	getstatic	Field scala/runtime/ScalaRunTime$.MODULE$:Lscala/runtime/ScalaRunTime$;
	aload_0
	invokevirtual	Method scala/runtime/ScalaRunTime$._hashCode:(Lscala/Product;)I
	ireturn
  Labels:

public scala.reflect.Literal copy(java.lang.Object);
  Signature: (Ljava/lang/Object;)Lscala/reflect/Literal;
  Code:
   Stack=3, Locals=2, Args_size=2
	new	class scala/reflect/Literal
	dup
	aload_1
	invokespecial	Method "<init>":(Ljava/lang/Object;)V
	areturn
  Labels:
  LocalVariableTable: 
   Start  Length  Slot  Name   Signature
   0      9      0    this       Lscala/reflect/Literal;
   0      9      1    value       Ljava/lang/Object;


public java.lang.Object value();
  Signature: ()Ljava/lang/Object;
  Code:
   Stack=1, Locals=1, Args_size=1
	aload_0
	getfield	Field value:Ljava/lang/Object;
	areturn
  Labels:

public java.lang.Object copy$default$1();
  Signature: ()Ljava/lang/Object;
  Code:
   Stack=1, Locals=1, Args_size=1
	aload_0
	invokevirtual	Method value:()Ljava/lang/Object;
	areturn
  Labels:

public scala.collection.Iterator productElements();
  Signature: ()Lscala/collection/Iterator;
  Code:
   Stack=1, Locals=1, Args_size=1
	aload_0
	invokestatic	Method scala/Product$class.productElements:(Lscala/Product;)Lscala/collection/Iterator;
	areturn
  Labels:

public scala.collection.Iterator productIterator();
  Signature: ()Lscala/collection/Iterator;
  Code:
   Stack=1, Locals=1, Args_size=1
	aload_0
	invokestatic	Method scala/Product$class.productIterator:(Lscala/Product;)Lscala/collection/Iterator;
	areturn
  Labels:

}

