Compiled from "Symbol.scala"
public final class scala.reflect.LocalValue$ extends java.lang.Object implements scala.Function3,scala.ScalaObject
  SourceFile: "Symbol.scala"
  Scala: length = 0x
   
  minor version: 0
  major version: 49
  Constant pool:
Asciz	SourceFile;
Asciz	Symbol.scala;
Asciz	Scala;
Asciz	MODULE$;
Asciz	Lscala/reflect/LocalValue$;;
Asciz	<clinit>;
Asciz	()V;
Asciz	Code;
Asciz	scala/reflect/LocalValue$;
class	scala/reflect/LocalValue$
Asciz	<init>;
NameAndType	"<init>":()V
Method	scala/reflect/LocalValue$."<init>":()V
Asciz	toString;
Asciz	()Ljava/lang/String;;
Asciz	LineNumberTable;
Asciz	scala/Function3$class;
class	scala/Function3$class
Asciz	(Lscala/Function3;)Ljava/lang/String;;
NameAndType	toString:(Lscala/Function3;)Ljava/lang/String;
Method	scala/Function3$class.toString:(Lscala/Function3;)Ljava/lang/String;
Asciz	curried;
Asciz	()Lscala/Function1;;
Asciz	(Lscala/Function3;)Lscala/Function1;;
NameAndType	curried:(Lscala/Function3;)Lscala/Function1;
Method	scala/Function3$class.curried:(Lscala/Function3;)Lscala/Function1;
Asciz	curry;
NameAndType	curry:(Lscala/Function3;)Lscala/Function1;
Method	scala/Function3$class.curry:(Lscala/Function3;)Lscala/Function1;
Asciz	Deprecated;
Asciz	tupled;
NameAndType	tupled:(Lscala/Function3;)Lscala/Function1;
Method	scala/Function3$class.tupled:(Lscala/Function3;)Lscala/Function1;
Asciz	unapply;
Asciz	(Lscala/reflect/LocalValue;)Lscala/Option;;
Asciz	java/lang/Object;
class	java/lang/Object
Asciz	equals;
Asciz	(Ljava/lang/Object;)Z;
NameAndType	equals:(Ljava/lang/Object;)Z
Method	java/lang/Object.equals:(Ljava/lang/Object;)Z
Asciz	scala/None$;
class	scala/None$
Asciz	Lscala/None$;;
NameAndType	MODULE$:Lscala/None$;
Field	scala/None$.MODULE$:Lscala/None$;
Asciz	scala/Some;
class	scala/Some
Asciz	scala/Tuple3;
class	scala/Tuple3
Asciz	scala/reflect/LocalValue;
class	scala/reflect/LocalValue
Asciz	owner;
Asciz	()Lscala/reflect/Symbol;;
NameAndType	owner:()Lscala/reflect/Symbol;
Method	scala/reflect/LocalValue.owner:()Lscala/reflect/Symbol;
Asciz	name;
NameAndType	name:()Ljava/lang/String;
Method	scala/reflect/LocalValue.name:()Ljava/lang/String;
Asciz	tpe;
Asciz	()Lscala/reflect/Type;;
NameAndType	tpe:()Lscala/reflect/Type;
Method	scala/reflect/LocalValue.tpe:()Lscala/reflect/Type;
Asciz	(Ljava/lang/Object;Ljava/lang/Object;Ljava/lang/Object;)V;
NameAndType	"<init>":(Ljava/lang/Object;Ljava/lang/Object;Ljava/lang/Object;)V
Method	scala/Tuple3."<init>":(Ljava/lang/Object;Ljava/lang/Object;Ljava/lang/Object;)V
Asciz	(Ljava/lang/Object;)V;
NameAndType	"<init>":(Ljava/lang/Object;)V
Method	scala/Some."<init>":(Ljava/lang/Object;)V
Asciz	this;
Asciz	x$0;
Asciz	Lscala/reflect/LocalValue;;
Asciz	LocalVariableTable;
Asciz	apply;
Asciz	(Lscala/reflect/Symbol;Ljava/lang/String;Lscala/reflect/Type;)Lscala/reflect/LocalValue;;
Asciz	(Lscala/reflect/Symbol;Ljava/lang/String;Lscala/reflect/Type;)V;
NameAndType	"<init>":(Lscala/reflect/Symbol;Ljava/lang/String;Lscala/reflect/Type;)V
Method	scala/reflect/LocalValue."<init>":(Lscala/reflect/Symbol;Ljava/lang/String;Lscala/reflect/Type;)V
Asciz	Lscala/reflect/Symbol;;
Asciz	Ljava/lang/String;;
Asciz	Lscala/reflect/Type;;
Asciz	(Ljava/lang/Object;Ljava/lang/Object;Ljava/lang/Object;)Ljava/lang/Object;;
Asciz	scala/reflect/Symbol;
class	scala/reflect/Symbol
Asciz	java/lang/String;
class	java/lang/String
Asciz	scala/reflect/Type;
class	scala/reflect/Type
NameAndType	apply:(Lscala/reflect/Symbol;Ljava/lang/String;Lscala/reflect/Type;)Lscala/reflect/LocalValue;
Method	scala/reflect/LocalValue$.apply:(Lscala/reflect/Symbol;Ljava/lang/String;Lscala/reflect/Type;)Lscala/reflect/LocalValue;
Asciz	v1;
Asciz	Ljava/lang/Object;;
Asciz	v2;
Asciz	v3;
Method	java/lang/Object."<init>":()V
NameAndType	MODULE$:Lscala/reflect/LocalValue$;
Field	scala/reflect/LocalValue$.MODULE$:Lscala/reflect/LocalValue$;
Asciz	$init$;
Asciz	(Lscala/Function3;)V;
NameAndType	$init$:(Lscala/Function3;)V
Method	scala/Function3$class.$init$:(Lscala/Function3;)V
Asciz	scala/Function3;
class	scala/Function3
Asciz	scala/ScalaObject;
class	scala/ScalaObject

{
public static final scala.reflect.LocalValue$ MODULE$;
  Signature: Lscala/reflect/LocalValue$;

public static {};
  Signature: ()V
  Code:
   Stack=1, Locals=0, Args_size=0
	new	class scala/reflect/LocalValue$
	invokespecial	Method "<init>":()V
	return
  Labels:

public java.lang.String toString();
  Signature: ()Ljava/lang/String;
  Code:
   Stack=1, Locals=1, Args_size=1
	aload_0
	invokestatic	Method scala/Function3$class.toString:(Lscala/Function3;)Ljava/lang/String;
	areturn
  Labels:

public scala.Function1 curried();
  Signature: ()Lscala/Function1;
  Code:
   Stack=1, Locals=1, Args_size=1
	aload_0
	invokestatic	Method scala/Function3$class.curried:(Lscala/Function3;)Lscala/Function1;
	areturn
  Labels:

public scala.Function1 curry();
  Signature: ()Lscala/Function1;
  Code:
   Stack=1, Locals=1, Args_size=1
	aload_0
	invokestatic	Method scala/Function3$class.curry:(Lscala/Function3;)Lscala/Function1;
	areturn
  Labels:
  Deprecated: true

public scala.Function1 tupled();
  Signature: ()Lscala/Function1;
  Code:
   Stack=1, Locals=1, Args_size=1
	aload_0
	invokestatic	Method scala/Function3$class.tupled:(Lscala/Function3;)Lscala/Function1;
	areturn
  Labels:

public scala.Option unapply(scala.reflect.LocalValue);
  Signature: (Lscala/reflect/LocalValue;)Lscala/Option;
  Code:
   Stack=7, Locals=3, Args_size=2
	aload_1
	dup
	astore_2
	ifnull	l1 // getstatic
	aload_2
	aconst_null
	invokevirtual	Method java/lang/Object.equals:(Ljava/lang/Object;)Z
	ifeq	l2 // new
l1	getstatic	Field scala/None$.MODULE$:Lscala/None$;
	goto	l3 // areturn
l2	new	class scala/Some
	dup
	new	class scala/Tuple3
	dup
	aload_1
	invokevirtual	Method scala/reflect/LocalValue.owner:()Lscala/reflect/Symbol;
	aload_1
	invokevirtual	Method scala/reflect/LocalValue.name:()Ljava/lang/String;
	aload_1
	invokevirtual	Method scala/reflect/LocalValue.tpe:()Lscala/reflect/Type;
	invokespecial	Method scala/Tuple3."<init>":(Ljava/lang/Object;Ljava/lang/Object;Ljava/lang/Object;)V
	invokespecial	Method scala/Some."<init>":(Ljava/lang/Object;)V
l3	areturn
  Labels:
   	l1 = 14 // getstatic
   	l2 = 20 // new
   	l3 = 46 // areturn
  LocalVariableTable: 
   Start  Length  Slot  Name   Signature
   0      47      0    this       Lscala/reflect/LocalValue$;
   0      47      1    x$0       Lscala/reflect/LocalValue;


public scala.reflect.LocalValue apply(scala.reflect.Symbol, java.lang.String, scala.reflect.Type);
  Signature: (Lscala/reflect/Symbol;Ljava/lang/String;Lscala/reflect/Type;)Lscala/reflect/LocalValue;
  Code:
   Stack=5, Locals=4, Args_size=4
	new	class scala/reflect/LocalValue
	dup
	aload_1
	aload_2
	aload_3
	invokespecial	Method scala/reflect/LocalValue."<init>":(Lscala/reflect/Symbol;Ljava/lang/String;Lscala/reflect/Type;)V
	areturn
  Labels:
  LocalVariableTable: 
   Start  Length  Slot  Name   Signature
   0      11      0    this       Lscala/reflect/LocalValue$;
   0      11      1    owner       Lscala/reflect/Symbol;
   0      11      2    name       Ljava/lang/String;
   0      11      3    tpe       Lscala/reflect/Type;


public java.lang.Object apply(java.lang.Object, java.lang.Object, java.lang.Object);
  Signature: (Ljava/lang/Object;Ljava/lang/Object;Ljava/lang/Object;)Ljava/lang/Object;
  Code:
   Stack=4, Locals=4, Args_size=4
	aload_0
	aload_1
	checkcast	class scala/reflect/Symbol
	aload_2
	checkcast	class java/lang/String
	aload_3
	checkcast	class scala/reflect/Type
	invokevirtual	Method apply:(Lscala/reflect/Symbol;Ljava/lang/String;Lscala/reflect/Type;)Lscala/reflect/LocalValue;
	areturn
  Labels:
  LocalVariableTable: 
   Start  Length  Slot  Name   Signature
   0      17      0    this       Lscala/reflect/LocalValue$;
   0      17      1    v1       Ljava/lang/Object;
   0      17      2    v2       Ljava/lang/Object;
   0      17      3    v3       Ljava/lang/Object;


private scala.reflect.LocalValue$();
  Signature: ()V
  Code:
   Stack=1, Locals=1, Args_size=1
	aload_0
	invokespecial	Method java/lang/Object."<init>":()V
	aload_0
	putstatic	Field MODULE$:Lscala/reflect/LocalValue$;
	aload_0
	invokestatic	Method scala/Function3$class.$init$:(Lscala/Function3;)V
	return
  Labels:

}

