Compiled from "Symbol.scala"
public class scala.reflect.LocalValue extends scala.reflect.LocalSymbol implements scala.ScalaObject,scala.Product,java.io.Serializable
  SourceFile: "Symbol.scala"
  ScalaSig: length = 0x475
   05 00 FFFFFF81 20 06 08 01 02 FFFFFF84 FFFFFF80 FFFFFF80 FFFFFF80 40 07 02 0A
   4C 6F 63 61 6C 56 61 6C 75 65 0A 02 03 04 01 07
   72 65 66 6C 65 63 74 0A 01 05 01 05 73 63 61 6C
   61 03 00 13 04 00 08 0C 10 10 02 09 0A 0D 01 02
   09 02 0B 02 02 0B 4C 6F 63 61 6C 53 79 6D 62 6F
   6C 10 02 0D 0E 0D 01 04 09 02 0F 04 02 0B 53 63
   61 6C 61 4F 62 6A 65 63 74 10 02 0D 11 09 02 12
   04 02 07 50 72 6F 64 75 63 74 08 08 14 00 FFFFFF82 FFFFFFCA
   FFFFFF80 FFFFFF84 00 15 01 05 6F 77 6E 65 72 15 01 16 10 02
   09 17 09 02 18 02 02 06 53 79 6D 62 6F 6C 08 08
   1A 00 FFFFFF82 FFFFFF88 FFFFFFA0 FFFFFF80 04 16 01 06 6F 77 6E 65 72 20
   08 08 1C 00 FFFFFF82 FFFFFFCA FFFFFF80 FFFFFF84 00 1D 01 04 6E 61 6D 65
   15 01 1E 10 02 1F 22 0E 02 0D 20 09 02 21 04 01
   06 50 72 65 64 65 66 09 02 23 24 02 06 53 74 72
   69 6E 67 0A 02 21 04 08 08 26 00 FFFFFF82 FFFFFF88 FFFFFFA0 FFFFFF80 04
   1E 01 05 6E 61 6D 65 20 08 08 28 00 FFFFFF82 FFFFFFCA FFFFFF80 FFFFFF84
   00 29 01 03 74 70 65 15 01 2A 10 02 09 2B 09 02
   2C 02 02 04 54 79 70 65 08 08 2E 00 FFFFFF82 FFFFFF88 FFFFFFA0 FFFFFF80
   04 2A 01 04 74 70 65 20 08 05 30 00 FFFFFF84 00 31 01
   06 3C 69 6E 69 74 3E 14 04 32 33 34 35 10 02 09
   00 08 05 14 2F FFFFFFC0 00 16 08 05 1C 2F FFFFFFC0 00 1E 08
   05 28 2F FFFFFFC0 00 2A 08 07 37 00 FFFFFF81 FFFFFF80 FFFFFF84 00 38 01
   04 63 6F 70 79 14 04 32 39 3A 3B 08 07 14 36 FFFFFF90
   FFFFFF80 FFFFFFC0 00 16 08 07 1C 36 FFFFFF90 FFFFFF80 FFFFFFC0 00 1E 08 07 28
   36 FFFFFF90 FFFFFF80 FFFFFFC0 00 2A 08 07 3D 00 FFFFFF91 FFFFFF80 FFFFFF84 00 3E 01
   0E 63 6F 70 79 24 64 65 66 61 75 6C 74 24 31 15
   01 3F 2A 02 16 40 2B 01 41 10 02 42 47 0D 01 43
   0A 02 44 45 01 09 75 6E 63 68 65 63 6B 65 64 0A
   02 46 04 01 0A 61 6E 6E 6F 74 61 74 69 6F 6E 09
   02 48 43 02 11 75 6E 63 68 65 63 6B 65 64 56 61
   72 69 61 6E 63 65 08 07 4A 00 FFFFFF91 FFFFFF80 FFFFFF84 00 4B 01
   0E 63 6F 70 79 24 64 65 66 61 75 6C 74 24 32 15
   01 4C 2A 02 1E 40 08 07 4E 00 FFFFFF91 FFFFFF80 FFFFFF84 00 4F 01
   0E 63 6F 70 79 24 64 65 66 61 75 6C 74 24 33 15
   01 50 2A 02 2A 40 08 08 52 00 FFFFFF84 FFFFFF80 FFFFFF80 FFFFFF84 20 53
   01 08 68 61 73 68 43 6F 64 65 14 01 54 10 02 0D
   55 09 02 56 04 02 03 49 6E 74 08 08 58 00 FFFFFF84 FFFFFF80
   FFFFFF80 FFFFFF84 20 59 01 08 74 6F 53 74 72 69 6E 67 14 01
   1E 08 08 5B 00 FFFFFF84 FFFFFF80 FFFFFF80 FFFFFF84 20 5C 01 06 65 71 75
   61 6C 73 14 02 5D 60 10 02 0D 5E 09 02 5F 04 02
   07 42 6F 6F 6C 65 61 6E 08 07 61 5A FFFFFF81 FFFFFF80 FFFFFFC0 00
   62 01 03 78 24 31 10 02 0D 63 09 02 64 04 02 03
   41 6E 79 08 08 66 00 FFFFFF84 FFFFFF80 FFFFFF80 FFFFFF84 20 67 01 0D 70
   72 6F 64 75 63 74 50 72 65 66 69 78 15 01 68 10
   02 69 6E 0D 01 6A 0A 02 6B 6C 01 04 6C 61 6E 67
   0A 01 6D 01 04 6A 61 76 61 09 02 23 6A 08 08 70
   00 FFFFFF84 FFFFFF80 FFFFFF80 FFFFFF84 20 71 01 0C 70 72 6F 64 75 63 74
   41 72 69 74 79 15 01 54 08 08 73 00 FFFFFF84 FFFFFF80 FFFFFF80 FFFFFF84
   20 74 01 0E 70 72 6F 64 75 63 74 45 6C 65 6D 65
   6E 74 14 02 62 75 08 07 61 72 FFFFFF81 FFFFFF80 FFFFFFC0 00 54 08
   08 77 00 FFFFFF84 FFFFFF80 FFFFFF80 FFFFFF84 20 78 01 12 70 72 6F 64 75
   63 74 45 6C 65 6D 65 6E 74 4E 61 6D 65 14 02 68
   79 08 07 61 76 FFFFFF81 FFFFFF80 FFFFFFC0 00 54 08 08 7B 00 FFFFFF84 FFFFFF80
   FFFFFF80 FFFFFF84 20 7C 01 08 63 61 6E 45 71 75 61 6C 14 02
   5D 7D 08 07 61 7A FFFFFF81 FFFFFF80 FFFFFFC0 00 62 28 02 00 7F 10
   03 0D FFFFFF81 00 09 03 FFFFFF81 01 04 02 0C 73 65 72 69 61
   6C 69 7A 61 62 6C 65 07 09 FFFFFF81 03 02 FFFFFF81 FFFFFF80 FFFFFF88 02
   FFFFFF81 04 01 0A 4C 6F 63 61 6C 56 61 6C 75 65 10 03
   09 FFFFFF81 05 06 09 01 02 FFFFFF84 FFFFFF81 FFFFFF80 FFFFFF88 02 FFFFFF81 06 13 07
   FFFFFF81 05 FFFFFF81 07 FFFFFF81 0A 0C 10 03 69 FFFFFF81 08 09 03 FFFFFF81 09
   6A 02 06 4F 62 6A 65 63 74 10 07 0D FFFFFF81 0B 16 1E
   2A 32 09 03 FFFFFF81 0C 04 02 09 46 75 6E 63 74 69 6F
   6E 33 08 07 30 FFFFFF81 05 FFFFFF84 00 FFFFFF81 0E 14 02 FFFFFF81 04 08
   0A FFFFFF81 10 FFFFFF81 05 FFFFFF81 FFFFFF80 FFFFFF84 40 FFFFFF81 11 01 05 61 70 70
   6C 79 14 07 32 FFFFFF81 12 FFFFFF81 13 FFFFFF81 14 08 06 14 FFFFFF81 0F
   FFFFFFC0 00 16 08 06 1C FFFFFF81 0F FFFFFFC0 00 1E 08 06 28 FFFFFF81 0F
   FFFFFFC0 00 2A 08 0A FFFFFF81 16 FFFFFF81 05 FFFFFF81 FFFFFF80 FFFFFF84 40 FFFFFF81 17 01
   07 75 6E 61 70 70 6C 79 14 04 FFFFFF81 18 FFFFFF81 1E 10 05
   0D FFFFFF81 19 FFFFFF81 1B 09 03 FFFFFF81 1A 04 02 06 4F 70 74 69
   6F 6E 10 06 0D FFFFFF81 1C 16 1E 2A 09 03 FFFFFF81 1D 04 02
   06 54 75 70 6C 65 33 08 07 FFFFFF81 1F FFFFFF81 15 FFFFFFC0 00 32
   01 03 78 24 30 
  minor version: 0
  major version: 49
  Constant pool:
Asciz	SourceFile;
Asciz	Symbol.scala;
Asciz	tupled;
Asciz	()Lscala/Function1;;
Asciz	Code;
Asciz	scala/reflect/LocalValue$;
class	scala/reflect/LocalValue$
Asciz	MODULE$;
Asciz	Lscala/reflect/LocalValue$;;
NameAndType	MODULE$:Lscala/reflect/LocalValue$;
Field	scala/reflect/LocalValue$.MODULE$:Lscala/reflect/LocalValue$;
NameAndType	tupled:()Lscala/Function1;
Method	scala/reflect/LocalValue$.tupled:()Lscala/Function1;
Asciz	curry;
NameAndType	curry:()Lscala/Function1;
Method	scala/reflect/LocalValue$.curry:()Lscala/Function1;
Asciz	Deprecated;
Asciz	curried;
NameAndType	curried:()Lscala/Function1;
Method	scala/reflect/LocalValue$.curried:()Lscala/Function1;
Asciz	tpe;
Asciz	Lscala/reflect/Type;;
Asciz	name;
Asciz	Ljava/lang/String;;
Asciz	owner;
Asciz	Lscala/reflect/Symbol;;
Asciz	productIterator;
Asciz	()Lscala/collection/Iterator;;
Asciz	LineNumberTable;
Asciz	scala/Product$class;
class	scala/Product$class
Asciz	(Lscala/Product;)Lscala/collection/Iterator;;
NameAndType	productIterator:(Lscala/Product;)Lscala/collection/Iterator;
Method	scala/Product$class.productIterator:(Lscala/Product;)Lscala/collection/Iterator;
Asciz	productElements;
NameAndType	productElements:(Lscala/Product;)Lscala/collection/Iterator;
Method	scala/Product$class.productElements:(Lscala/Product;)Lscala/collection/Iterator;
Asciz	copy$default$3;
Asciz	()Lscala/reflect/Type;;
Asciz	scala/reflect/LocalValue;
class	scala/reflect/LocalValue
NameAndType	tpe:()Lscala/reflect/Type;
Method	scala/reflect/LocalValue.tpe:()Lscala/reflect/Type;
Asciz	copy$default$2;
Asciz	()Ljava/lang/String;;
NameAndType	name:()Ljava/lang/String;
Method	scala/reflect/LocalValue.name:()Ljava/lang/String;
Asciz	copy$default$1;
Asciz	()Lscala/reflect/Symbol;;
NameAndType	owner:()Lscala/reflect/Symbol;
Method	scala/reflect/LocalValue.owner:()Lscala/reflect/Symbol;
NameAndType	owner:Lscala/reflect/Symbol;
Field	scala/reflect/LocalValue.owner:Lscala/reflect/Symbol;
NameAndType	name:Ljava/lang/String;
Field	scala/reflect/LocalValue.name:Ljava/lang/String;
NameAndType	tpe:Lscala/reflect/Type;
Field	scala/reflect/LocalValue.tpe:Lscala/reflect/Type;
Asciz	copy;
Asciz	(Lscala/reflect/Symbol;Ljava/lang/String;Lscala/reflect/Type;)Lscala/reflect/LocalValue;;
Asciz	<init>;
Asciz	(Lscala/reflect/Symbol;Ljava/lang/String;Lscala/reflect/Type;)V;
NameAndType	"<init>":(Lscala/reflect/Symbol;Ljava/lang/String;Lscala/reflect/Type;)V
Method	scala/reflect/LocalValue."<init>":(Lscala/reflect/Symbol;Ljava/lang/String;Lscala/reflect/Type;)V
Asciz	this;
Asciz	Lscala/reflect/LocalValue;;
Asciz	LocalVariableTable;
Asciz	hashCode;
Asciz	()I;
Asciz	scala/runtime/ScalaRunTime$;
class	scala/runtime/ScalaRunTime$
Asciz	Lscala/runtime/ScalaRunTime$;;
NameAndType	MODULE$:Lscala/runtime/ScalaRunTime$;
Field	scala/runtime/ScalaRunTime$.MODULE$:Lscala/runtime/ScalaRunTime$;
Asciz	_hashCode;
Asciz	(Lscala/Product;)I;
NameAndType	_hashCode:(Lscala/Product;)I
Method	scala/runtime/ScalaRunTime$._hashCode:(Lscala/Product;)I
Asciz	toString;
Asciz	_toString;
Asciz	(Lscala/Product;)Ljava/lang/String;;
NameAndType	_toString:(Lscala/Product;)Ljava/lang/String;
Method	scala/runtime/ScalaRunTime$._toString:(Lscala/Product;)Ljava/lang/String;
Asciz	equals;
Asciz	(Ljava/lang/Object;)Z;
Asciz	gd5$1;
Asciz	(Lscala/reflect/Symbol;Ljava/lang/String;Lscala/reflect/Type;)Z;
NameAndType	gd5$1:(Lscala/reflect/Symbol;Ljava/lang/String;Lscala/reflect/Type;)Z
Method	scala/reflect/LocalValue.gd5$1:(Lscala/reflect/Symbol;Ljava/lang/String;Lscala/reflect/Type;)Z
Asciz	scala/Equals;
class	scala/Equals
Asciz	canEqual;
NameAndType	canEqual:(Ljava/lang/Object;)Z
InterfaceMethod	scala/Equals.canEqual:(Ljava/lang/Object;)Z
Asciz	temp24;
Asciz	Ljava/lang/Object;;
Asciz	temp25;
Asciz	temp26;
Asciz	temp27;
Asciz	temp28;
Asciz	tpe$4;
Asciz	name$1;
Asciz	owner$1;
Asciz	productPrefix;
Asciz	LocalValue;
String	LocalValue
Asciz	productArity;
Asciz	productElement;
Asciz	(I)Ljava/lang/Object;;
Asciz	java/lang/IndexOutOfBoundsException;
class	java/lang/IndexOutOfBoundsException
Asciz	scala/runtime/BoxesRunTime;
class	scala/runtime/BoxesRunTime
Asciz	boxToInteger;
Asciz	(I)Ljava/lang/Integer;;
NameAndType	boxToInteger:(I)Ljava/lang/Integer;
Method	scala/runtime/BoxesRunTime.boxToInteger:(I)Ljava/lang/Integer;
Asciz	java/lang/Object;
class	java/lang/Object
NameAndType	toString:()Ljava/lang/String;
Method	java/lang/Object.toString:()Ljava/lang/String;
Asciz	(Ljava/lang/String;)V;
NameAndType	"<init>":(Ljava/lang/String;)V
Method	java/lang/IndexOutOfBoundsException."<init>":(Ljava/lang/String;)V
Asciz	temp29;
Asciz	I;
Asciz	productElementName;
Asciz	(I)Ljava/lang/String;;
String	tpe
String	name
String	owner
Asciz	temp30;
NameAndType	equals:(Ljava/lang/Object;)Z
Method	java/lang/Object.equals:(Ljava/lang/Object;)Z
Asciz	scala/reflect/LocalSymbol;
class	scala/reflect/LocalSymbol
Asciz	()V;
NameAndType	"<init>":()V
Method	scala/reflect/LocalSymbol."<init>":()V
Asciz	$init$;
Asciz	(Lscala/Product;)V;
NameAndType	$init$:(Lscala/Product;)V
Method	scala/Product$class.$init$:(Lscala/Product;)V
Asciz	ScalaSig;
Asciz	scala/ScalaObject;
class	scala/ScalaObject
Asciz	scala/Product;
class	scala/Product
Asciz	java/io/Serializable;
class	java/io/Serializable

{
private final scala.reflect.Type tpe;
  Signature: Lscala/reflect/Type;

private final java.lang.String name;
  Signature: Ljava/lang/String;

private final scala.reflect.Symbol owner;
  Signature: Lscala/reflect/Symbol;

public static final scala.Function1 tupled();
  Signature: ()Lscala/Function1;
  Code:
   Stack=1, Locals=0, Args_size=0
	getstatic	Field scala/reflect/LocalValue$.MODULE$:Lscala/reflect/LocalValue$;
	invokevirtual	Method scala/reflect/LocalValue$.tupled:()Lscala/Function1;
	areturn
  Labels:

public static final scala.Function1 curry();
  Signature: ()Lscala/Function1;
  Code:
   Stack=1, Locals=0, Args_size=0
	getstatic	Field scala/reflect/LocalValue$.MODULE$:Lscala/reflect/LocalValue$;
	invokevirtual	Method scala/reflect/LocalValue$.curry:()Lscala/Function1;
	areturn
  Labels:
  Deprecated: true

public static final scala.Function1 curried();
  Signature: ()Lscala/Function1;
  Code:
   Stack=1, Locals=0, Args_size=0
	getstatic	Field scala/reflect/LocalValue$.MODULE$:Lscala/reflect/LocalValue$;
	invokevirtual	Method scala/reflect/LocalValue$.curried:()Lscala/Function1;
	areturn
  Labels:

public scala.collection.Iterator productIterator();
  Signature: ()Lscala/collection/Iterator;
  Code:
   Stack=1, Locals=1, Args_size=1
	aload_0
	invokestatic	Method scala/Product$class.productIterator:(Lscala/Product;)Lscala/collection/Iterator;
	areturn
  Labels:

public scala.collection.Iterator productElements();
  Signature: ()Lscala/collection/Iterator;
  Code:
   Stack=1, Locals=1, Args_size=1
	aload_0
	invokestatic	Method scala/Product$class.productElements:(Lscala/Product;)Lscala/collection/Iterator;
	areturn
  Labels:
  Deprecated: true

public scala.reflect.Type copy$default$3();
  Signature: ()Lscala/reflect/Type;
  Code:
   Stack=1, Locals=1, Args_size=1
	aload_0
	invokevirtual	Method tpe:()Lscala/reflect/Type;
	areturn
  Labels:

public java.lang.String copy$default$2();
  Signature: ()Ljava/lang/String;
  Code:
   Stack=1, Locals=1, Args_size=1
	aload_0
	invokevirtual	Method name:()Ljava/lang/String;
	areturn
  Labels:

public scala.reflect.Symbol copy$default$1();
  Signature: ()Lscala/reflect/Symbol;
  Code:
   Stack=1, Locals=1, Args_size=1
	aload_0
	invokevirtual	Method owner:()Lscala/reflect/Symbol;
	areturn
  Labels:

public scala.reflect.Symbol owner();
  Signature: ()Lscala/reflect/Symbol;
  Code:
   Stack=1, Locals=1, Args_size=1
	aload_0
	getfield	Field owner:Lscala/reflect/Symbol;
	areturn
  Labels:

public java.lang.String name();
  Signature: ()Ljava/lang/String;
  Code:
   Stack=1, Locals=1, Args_size=1
	aload_0
	getfield	Field name:Ljava/lang/String;
	areturn
  Labels:

public scala.reflect.Type tpe();
  Signature: ()Lscala/reflect/Type;
  Code:
   Stack=1, Locals=1, Args_size=1
	aload_0
	getfield	Field tpe:Lscala/reflect/Type;
	areturn
  Labels:

public scala.reflect.LocalValue copy(scala.reflect.Symbol, java.lang.String, scala.reflect.Type);
  Signature: (Lscala/reflect/Symbol;Ljava/lang/String;Lscala/reflect/Type;)Lscala/reflect/LocalValue;
  Code:
   Stack=5, Locals=4, Args_size=4
	new	class scala/reflect/LocalValue
	dup
	aload_1
	aload_2
	aload_3
	invokespecial	Method "<init>":(Lscala/reflect/Symbol;Ljava/lang/String;Lscala/reflect/Type;)V
	areturn
  Labels:
  LocalVariableTable: 
   Start  Length  Slot  Name   Signature
   0      11      0    this       Lscala/reflect/LocalValue;
   0      11      1    owner       Lscala/reflect/Symbol;
   0      11      2    name       Ljava/lang/String;
   0      11      3    tpe       Lscala/reflect/Type;


public int hashCode();
  Signature: ()I
  Code:
   Stack=2, Locals=1, Args_size=1
	getstatic	Field scala/runtime/ScalaRunTime$.MODULE$:Lscala/runtime/ScalaRunTime$;
	aload_0
	invokevirtual	Method scala/runtime/ScalaRunTime$._hashCode:(Lscala/Product;)I
	ireturn
  Labels:

public java.lang.String toString();
  Signature: ()Ljava/lang/String;
  Code:
   Stack=2, Locals=1, Args_size=1
	getstatic	Field scala/runtime/ScalaRunTime$.MODULE$:Lscala/runtime/ScalaRunTime$;
	aload_0
	invokevirtual	Method scala/runtime/ScalaRunTime$._toString:(Lscala/Product;)Ljava/lang/String;
	areturn
  Labels:

public boolean equals(java.lang.Object);
  Signature: (Ljava/lang/Object;)Z
  Code:
   Stack=4, Locals=10, Args_size=2
	aload_0
	aload_1
	if_acmpeq	l1 // iconst_1
	aload_1
	astore_2
	aload_2
	instanceof	class scala/reflect/LocalValue
	ifeq	l2 // iconst_0
	aload_2
	checkcast	class scala/reflect/LocalValue
	astore_3
	aload_3
	invokevirtual	Method owner:()Lscala/reflect/Symbol;
	astore	4
	aload_3
	invokevirtual	Method name:()Ljava/lang/String;
	astore	5
	aload_3
	invokevirtual	Method tpe:()Lscala/reflect/Type;
	astore	6
	aload	6
	astore	7
	aload	5
	astore	8
	aload	4
	astore	9
	aload_0
	aload	9
	aload	8
	aload	7
	invokespecial	Method gd5$1:(Lscala/reflect/Symbol;Ljava/lang/String;Lscala/reflect/Type;)Z
	ifeq	l3 // iconst_0
	aload_1
	checkcast	class scala/reflect/LocalValue
	aload_0
	invokeinterface	InterfaceMethod scala/Equals.canEqual:(Ljava/lang/Object;)Z
	goto	l4 // ifeq
l3	iconst_0
	goto	l4 // ifeq
l2	iconst_0
l4	ifeq	l5 // iconst_0
l1	iconst_1
	goto	l6 // ireturn
l5	iconst_0
l6	ireturn
  Labels:
   	l3 = 75 // iconst_0
   	l2 = 79 // iconst_0
   	l4 = 80 // ifeq
   	l1 = 83 // iconst_1
   	l5 = 87 // iconst_0
   	l6 = 88 // ireturn
  LocalVariableTable: 
   Start  Length  Slot  Name   Signature
   0      89      0    this       Lscala/reflect/LocalValue;
   7      76      2    temp24       Ljava/lang/Object;
   19      60      3    temp25       Lscala/reflect/LocalValue;
   25      54      4    temp26       Lscala/reflect/Symbol;
   31      48      5    temp27       Ljava/lang/String;
   37      42      6    temp28       Lscala/reflect/Type;
   41      38      7    tpe$4       Lscala/reflect/Type;
   45      34      8    name$1       Ljava/lang/String;
   49      30      9    owner$1       Lscala/reflect/Symbol;


public java.lang.String productPrefix();
  Signature: ()Ljava/lang/String;
  Code:
   Stack=1, Locals=1, Args_size=1
	ldc	String LocalValue
	areturn
  Labels:

public int productArity();
  Signature: ()I
  Code:
   Stack=1, Locals=1, Args_size=1
	iconst_3
	ireturn
  Labels:

public java.lang.Object productElement(int);
  Signature: (I)Ljava/lang/Object;
  Code:
   Stack=3, Locals=3, Args_size=2
	iload_1
	istore_2
	iload_2
	tableswitch{ //0 to 2
		0: 57;
		1: 50;
		2: 43;
		default: 28 }
	new	class java/lang/IndexOutOfBoundsException
	dup
	iload_1
	invokestatic	Method scala/runtime/BoxesRunTime.boxToInteger:(I)Ljava/lang/Integer;
	invokevirtual	Method java/lang/Object.toString:()Ljava/lang/String;
	invokespecial	Method java/lang/IndexOutOfBoundsException."<init>":(Ljava/lang/String;)V
	athrow
	aload_0
	invokevirtual	Method tpe:()Lscala/reflect/Type;
	goto	l1 // areturn
	aload_0
	invokevirtual	Method name:()Ljava/lang/String;
	goto	l1 // areturn
	aload_0
	invokevirtual	Method owner:()Lscala/reflect/Symbol;
l1	areturn
  Labels:
   	l1 = 61 // areturn
  LocalVariableTable: 
   Start  Length  Slot  Name   Signature
   0      62      0    this       Lscala/reflect/LocalValue;
   2      60      2    temp29       I


public java.lang.String productElementName(int);
  Signature: (I)Ljava/lang/String;
  Code:
   Stack=3, Locals=3, Args_size=2
	iload_1
	istore_2
	iload_2
	tableswitch{ //0 to 2
		0: 53;
		1: 48;
		2: 43;
		default: 28 }
	new	class java/lang/IndexOutOfBoundsException
	dup
	iload_1
	invokestatic	Method scala/runtime/BoxesRunTime.boxToInteger:(I)Ljava/lang/Integer;
	invokevirtual	Method java/lang/Object.toString:()Ljava/lang/String;
	invokespecial	Method java/lang/IndexOutOfBoundsException."<init>":(Ljava/lang/String;)V
	athrow
	ldc	String tpe
	goto	l1 // areturn
	ldc	String name
	goto	l1 // areturn
	ldc	String owner
l1	areturn
  Labels:
   	l1 = 55 // areturn
  LocalVariableTable: 
   Start  Length  Slot  Name   Signature
   0      56      0    this       Lscala/reflect/LocalValue;
   2      54      2    temp30       I


public boolean canEqual(java.lang.Object);
  Signature: (Ljava/lang/Object;)Z
  Code:
   Stack=1, Locals=2, Args_size=2
	aload_1
	instanceof	class scala/reflect/LocalValue
	ireturn
  Labels:

private final boolean gd5$1(scala.reflect.Symbol, java.lang.String, scala.reflect.Type);
  Signature: (Lscala/reflect/Symbol;Ljava/lang/String;Lscala/reflect/Type;)Z
  Code:
   Stack=2, Locals=7, Args_size=4
	aload_1
	aload_0
	invokevirtual	Method owner:()Lscala/reflect/Symbol;
	astore	4
	dup
	ifnonnull	l1 // aload
	pop
	aload	4
	ifnull	l2 // aload_2
	goto	l3 // iconst_0
l1	aload	4
	invokevirtual	Method java/lang/Object.equals:(Ljava/lang/Object;)Z
	ifeq	l3 // iconst_0
l2	aload_2
	aload_0
	invokevirtual	Method name:()Ljava/lang/String;
	astore	5
	dup
	ifnonnull	l4 // aload
	pop
	aload	5
	ifnull	l5 // aload_3
	goto	l3 // iconst_0
l4	aload	5
	invokevirtual	Method java/lang/Object.equals:(Ljava/lang/Object;)Z
	ifeq	l3 // iconst_0
l5	aload_3
	aload_0
	invokevirtual	Method tpe:()Lscala/reflect/Type;
	astore	6
	dup
	ifnonnull	l6 // aload
	pop
	aload	6
	ifnull	l7 // iconst_1
	goto	l3 // iconst_0
l6	aload	6
	invokevirtual	Method java/lang/Object.equals:(Ljava/lang/Object;)Z
	ifeq	l3 // iconst_0
l7	iconst_1
	goto	l8 // ireturn
l3	iconst_0
l8	ireturn
  Labels:
   	l1 = 20 // aload
   	l2 = 28 // aload_2
   	l4 = 48 // aload
   	l5 = 56 // aload_3
   	l6 = 76 // aload
   	l7 = 84 // iconst_1
   	l3 = 88 // iconst_0
   	l8 = 89 // ireturn

public scala.reflect.LocalValue(scala.reflect.Symbol, java.lang.String, scala.reflect.Type);
  Signature: (Lscala/reflect/Symbol;Ljava/lang/String;Lscala/reflect/Type;)V
  Code:
   Stack=2, Locals=4, Args_size=4
	aload_0
	aload_1
	putfield	Field owner:Lscala/reflect/Symbol;
	aload_0
	aload_2
	putfield	Field name:Ljava/lang/String;
	aload_0
	aload_3
	putfield	Field tpe:Lscala/reflect/Type;
	aload_0
	invokespecial	Method scala/reflect/LocalSymbol."<init>":()V
	aload_0
	invokestatic	Method scala/Product$class.$init$:(Lscala/Product;)V
	return
  Labels:
  LocalVariableTable: 
   Start  Length  Slot  Name   Signature
   0      24      0    this       Lscala/reflect/LocalValue;
   0      24      1    owner       Lscala/reflect/Symbol;
   0      24      2    name       Ljava/lang/String;
   0      24      3    tpe       Lscala/reflect/Type;


}

