Compiled from "Symbol.scala"
public final class scala.reflect.LocalMethod$ extends java.lang.Object implements scala.Function3,scala.ScalaObject
  SourceFile: "Symbol.scala"
  Scala: length = 0x
   
  minor version: 0
  major version: 49
  Constant pool:
Asciz	SourceFile;
Asciz	Symbol.scala;
Asciz	Scala;
Asciz	MODULE$;
Asciz	Lscala/reflect/LocalMethod$;;
Asciz	<clinit>;
Asciz	()V;
Asciz	Code;
Asciz	scala/reflect/LocalMethod$;
class	scala/reflect/LocalMethod$
Asciz	<init>;
NameAndType	"<init>":()V
Method	scala/reflect/LocalMethod$."<init>":()V
Asciz	LineNumberTable;
Asciz	java/lang/Object;
class	java/lang/Object
Method	java/lang/Object."<init>":()V
NameAndType	MODULE$:Lscala/reflect/LocalMethod$;
Field	scala/reflect/LocalMethod$.MODULE$:Lscala/reflect/LocalMethod$;
Asciz	scala/Function3$class;
class	scala/Function3$class
Asciz	$init$;
Asciz	(Lscala/Function3;)V;
NameAndType	$init$:(Lscala/Function3;)V
Method	scala/Function3$class.$init$:(Lscala/Function3;)V
Asciz	apply;
Asciz	(Ljava/lang/Object;Ljava/lang/Object;Ljava/lang/Object;)Ljava/lang/Object;;
Asciz	scala/reflect/Symbol;
class	scala/reflect/Symbol
Asciz	java/lang/String;
class	java/lang/String
Asciz	scala/reflect/Type;
class	scala/reflect/Type
Asciz	(Lscala/reflect/Symbol;Ljava/lang/String;Lscala/reflect/Type;)Lscala/reflect/LocalMethod;;
NameAndType	apply:(Lscala/reflect/Symbol;Ljava/lang/String;Lscala/reflect/Type;)Lscala/reflect/LocalMethod;
Method	scala/reflect/LocalMethod$.apply:(Lscala/reflect/Symbol;Ljava/lang/String;Lscala/reflect/Type;)Lscala/reflect/LocalMethod;
Asciz	this;
Asciz	v1;
Asciz	Ljava/lang/Object;;
Asciz	v2;
Asciz	v3;
Asciz	LocalVariableTable;
Asciz	scala/reflect/LocalMethod;
class	scala/reflect/LocalMethod
Asciz	(Lscala/reflect/Symbol;Ljava/lang/String;Lscala/reflect/Type;)V;
NameAndType	"<init>":(Lscala/reflect/Symbol;Ljava/lang/String;Lscala/reflect/Type;)V
Method	scala/reflect/LocalMethod."<init>":(Lscala/reflect/Symbol;Ljava/lang/String;Lscala/reflect/Type;)V
Asciz	owner;
Asciz	Lscala/reflect/Symbol;;
Asciz	name;
Asciz	Ljava/lang/String;;
Asciz	tpe;
Asciz	Lscala/reflect/Type;;
Asciz	unapply;
Asciz	(Lscala/reflect/LocalMethod;)Lscala/Some;;
Asciz	scala/Some;
class	scala/Some
Asciz	scala/Tuple3;
class	scala/Tuple3
Asciz	()Lscala/reflect/Symbol;;
NameAndType	owner:()Lscala/reflect/Symbol;
Method	scala/reflect/LocalMethod.owner:()Lscala/reflect/Symbol;
Asciz	()Ljava/lang/String;;
NameAndType	name:()Ljava/lang/String;
Method	scala/reflect/LocalMethod.name:()Ljava/lang/String;
Asciz	()Lscala/reflect/Type;;
NameAndType	tpe:()Lscala/reflect/Type;
Method	scala/reflect/LocalMethod.tpe:()Lscala/reflect/Type;
Asciz	(Ljava/lang/Object;Ljava/lang/Object;Ljava/lang/Object;)V;
NameAndType	"<init>":(Ljava/lang/Object;Ljava/lang/Object;Ljava/lang/Object;)V
Method	scala/Tuple3."<init>":(Ljava/lang/Object;Ljava/lang/Object;Ljava/lang/Object;)V
Asciz	(Ljava/lang/Object;)V;
NameAndType	"<init>":(Ljava/lang/Object;)V
Method	scala/Some."<init>":(Ljava/lang/Object;)V
Asciz	x$0;
Asciz	Lscala/reflect/LocalMethod;;
Asciz	tuple;
Asciz	()Lscala/Function1;;
Asciz	(Lscala/Function3;)Lscala/Function1;;
NameAndType	tuple:(Lscala/Function3;)Lscala/Function1;
Method	scala/Function3$class.tuple:(Lscala/Function3;)Lscala/Function1;
Asciz	curry;
NameAndType	curry:(Lscala/Function3;)Lscala/Function1;
Method	scala/Function3$class.curry:(Lscala/Function3;)Lscala/Function1;
Asciz	toString;
Asciz	(Lscala/Function3;)Ljava/lang/String;;
NameAndType	toString:(Lscala/Function3;)Ljava/lang/String;
Method	scala/Function3$class.toString:(Lscala/Function3;)Ljava/lang/String;
Asciz	scala/Function3;
class	scala/Function3
Asciz	scala/ScalaObject;
class	scala/ScalaObject

{
public static final scala.reflect.LocalMethod$ MODULE$;
  Signature: Lscala/reflect/LocalMethod$;

public static {};
  Signature: ()V
  Code:
   Stack=1, Locals=0, Args_size=0
	new	class scala/reflect/LocalMethod$
	invokespecial	Method "<init>":()V
	return
  Labels:

private scala.reflect.LocalMethod$();
  Signature: ()V
  Code:
   Stack=1, Locals=1, Args_size=1
	aload_0
	invokespecial	Method java/lang/Object."<init>":()V
	aload_0
	putstatic	Field MODULE$:Lscala/reflect/LocalMethod$;
	aload_0
	invokestatic	Method scala/Function3$class.$init$:(Lscala/Function3;)V
	return
  Labels:

public java.lang.Object apply(java.lang.Object, java.lang.Object, java.lang.Object);
  Signature: (Ljava/lang/Object;Ljava/lang/Object;Ljava/lang/Object;)Ljava/lang/Object;
  Code:
   Stack=4, Locals=4, Args_size=4
	aload_0
	aload_1
	checkcast	class scala/reflect/Symbol
	aload_2
	checkcast	class java/lang/String
	aload_3
	checkcast	class scala/reflect/Type
	invokevirtual	Method apply:(Lscala/reflect/Symbol;Ljava/lang/String;Lscala/reflect/Type;)Lscala/reflect/LocalMethod;
	areturn
  Labels:
  LocalVariableTable: 
   Start  Length  Slot  Name   Signature
   0      17      0    this       Lscala/reflect/LocalMethod$;
   0      17      1    v1       Ljava/lang/Object;
   0      17      2    v2       Ljava/lang/Object;
   0      17      3    v3       Ljava/lang/Object;


public scala.reflect.LocalMethod apply(scala.reflect.Symbol, java.lang.String, scala.reflect.Type);
  Signature: (Lscala/reflect/Symbol;Ljava/lang/String;Lscala/reflect/Type;)Lscala/reflect/LocalMethod;
  Code:
   Stack=5, Locals=4, Args_size=4
	new	class scala/reflect/LocalMethod
	dup
	aload_1
	aload_2
	aload_3
	invokespecial	Method scala/reflect/LocalMethod."<init>":(Lscala/reflect/Symbol;Ljava/lang/String;Lscala/reflect/Type;)V
	areturn
  Labels:
  LocalVariableTable: 
   Start  Length  Slot  Name   Signature
   0      11      0    this       Lscala/reflect/LocalMethod$;
   0      11      1    owner       Lscala/reflect/Symbol;
   0      11      2    name       Ljava/lang/String;
   0      11      3    tpe       Lscala/reflect/Type;


public scala.Some unapply(scala.reflect.LocalMethod);
  Signature: (Lscala/reflect/LocalMethod;)Lscala/Some;
  Code:
   Stack=7, Locals=2, Args_size=2
	new	class scala/Some
	dup
	new	class scala/Tuple3
	dup
	aload_1
	invokevirtual	Method scala/reflect/LocalMethod.owner:()Lscala/reflect/Symbol;
	aload_1
	invokevirtual	Method scala/reflect/LocalMethod.name:()Ljava/lang/String;
	aload_1
	invokevirtual	Method scala/reflect/LocalMethod.tpe:()Lscala/reflect/Type;
	invokespecial	Method scala/Tuple3."<init>":(Ljava/lang/Object;Ljava/lang/Object;Ljava/lang/Object;)V
	invokespecial	Method scala/Some."<init>":(Ljava/lang/Object;)V
	areturn
  Labels:
  LocalVariableTable: 
   Start  Length  Slot  Name   Signature
   0      27      0    this       Lscala/reflect/LocalMethod$;
   0      27      1    x$0       Lscala/reflect/LocalMethod;


public scala.Function1 tuple();
  Signature: ()Lscala/Function1;
  Code:
   Stack=1, Locals=1, Args_size=1
	aload_0
	invokestatic	Method scala/Function3$class.tuple:(Lscala/Function3;)Lscala/Function1;
	areturn
  Labels:

public scala.Function1 curry();
  Signature: ()Lscala/Function1;
  Code:
   Stack=1, Locals=1, Args_size=1
	aload_0
	invokestatic	Method scala/Function3$class.curry:(Lscala/Function3;)Lscala/Function1;
	areturn
  Labels:

public java.lang.String toString();
  Signature: ()Ljava/lang/String;
  Code:
   Stack=1, Locals=1, Args_size=1
	aload_0
	invokestatic	Method scala/Function3$class.toString:(Lscala/Function3;)Ljava/lang/String;
	areturn
  Labels:

}

