Compiled from "Manifest.scala"
public final class scala.reflect.Manifest$$anon$13 extends scala.reflect.Manifest$ClassTypeManifest
  SourceFile: "Manifest.scala"
  Scala: length = 0x
   
  Signature: length = 0x2
   00 46 
  InnerClass: 
   public final $anon$13=class scala/reflect/Manifest$$anon$13 of class scala/reflect/Manifest
   public ClassTypeManifest=class scala/reflect/Manifest$ClassTypeManifest of class scala/reflect/Manifest
  minor version: 0
  major version: 49
  Constant pool:
Asciz	SourceFile;
Asciz	Manifest.scala;
Asciz	toString;
Asciz	()Ljava/lang/String;;
Asciz	Code;
Asciz	Null;
String	Null
Asciz	LineNumberTable;
Asciz	$less$colon$less;
Asciz	(Lscala/reflect/ClassManifest;)Z;
Asciz	scala/reflect/Manifest$;
class	scala/reflect/Manifest$
Asciz	MODULE$;
Asciz	Lscala/reflect/Manifest$;;
NameAndType	MODULE$:Lscala/reflect/Manifest$;
Field	scala/reflect/Manifest$.MODULE$:Lscala/reflect/Manifest$;
Asciz	Nothing;
Asciz	()Lscala/reflect/Manifest;;
NameAndType	Nothing:()Lscala/reflect/Manifest;
Method	scala/reflect/Manifest$.Nothing:()Lscala/reflect/Manifest;
Asciz	AnyVal;
NameAndType	AnyVal:()Lscala/reflect/Manifest;
Method	scala/reflect/Manifest$.AnyVal:()Lscala/reflect/Manifest;
Asciz	scala/reflect/ClassManifest;
class	scala/reflect/ClassManifest
NameAndType	$less$colon$less:(Lscala/reflect/ClassManifest;)Z
InterfaceMethod	scala/reflect/ClassManifest.$less$colon$less:(Lscala/reflect/ClassManifest;)Z
Asciz	this;
Asciz	Lscala/reflect/Manifest$$anon$13;;
Asciz	that;
Asciz	Lscala/reflect/ClassManifest;;
Asciz	LocalVariableTable;
Asciz	(Lscala/reflect/ClassManifest<*>;)Z;
Asciz	Signature;
Asciz	equals;
Asciz	(Ljava/lang/Object;)Z;
Asciz	Ljava/lang/Object;;
Asciz	hashCode;
Asciz	()I;
Asciz	java/lang/System;
class	java/lang/System
Asciz	identityHashCode;
Asciz	(Ljava/lang/Object;)I;
NameAndType	identityHashCode:(Ljava/lang/Object;)I
Method	java/lang/System.identityHashCode:(Ljava/lang/Object;)I
Asciz	readResolve;
Asciz	()Ljava/lang/Object;;
NameAndType	Null:()Lscala/reflect/Manifest;
Method	scala/reflect/Manifest$.Null:()Lscala/reflect/Manifest;
Asciz	<init>;
Asciz	()V;
Asciz	scala/None$;
class	scala/None$
Asciz	Lscala/None$;;
NameAndType	MODULE$:Lscala/None$;
Field	scala/None$.MODULE$:Lscala/None$;
Asciz	java/lang/Object;
class	java/lang/Object
Asciz	scala/collection/immutable/Nil$;
class	scala/collection/immutable/Nil$
Asciz	Lscala/collection/immutable/Nil$;;
NameAndType	MODULE$:Lscala/collection/immutable/Nil$;
Field	scala/collection/immutable/Nil$.MODULE$:Lscala/collection/immutable/Nil$;
Asciz	scala/reflect/Manifest$ClassTypeManifest;
class	scala/reflect/Manifest$ClassTypeManifest
Asciz	(Lscala/Option;Ljava/lang/Class;Lscala/collection/immutable/List;)V;
NameAndType	"<init>":(Lscala/Option;Ljava/lang/Class;Lscala/collection/immutable/List;)V
Method	scala/reflect/Manifest$ClassTypeManifest."<init>":(Lscala/Option;Ljava/lang/Class;Lscala/collection/immutable/List;)V
Asciz	Scala;
Asciz	Lscala/reflect/Manifest$ClassTypeManifest<Lscala/runtime/Null$;>;;
Asciz	InnerClasses;
Asciz	scala/reflect/Manifest$$anon$13;
class	scala/reflect/Manifest$$anon$13
Asciz	scala/reflect/Manifest;
class	scala/reflect/Manifest
Asciz	$anon$13;
Asciz	ClassTypeManifest;

{
public java.lang.String toString();
  Signature: ()Ljava/lang/String;
  Code:
   Stack=1, Locals=1, Args_size=1
	ldc	String Null
	areturn
  Labels:

public boolean $less$colon$less(scala.reflect.ClassManifest);
  Signature: (Lscala/reflect/ClassManifest;)Z
  Code:
   Stack=2, Locals=2, Args_size=2
	aload_1
	ifnull	l1 // iconst_0
	aload_1
	getstatic	Field scala/reflect/Manifest$.MODULE$:Lscala/reflect/Manifest$;
	invokevirtual	Method scala/reflect/Manifest$.Nothing:()Lscala/reflect/Manifest;
	if_acmpeq	l1 // iconst_0
	aload_1
	getstatic	Field scala/reflect/Manifest$.MODULE$:Lscala/reflect/Manifest$;
	invokevirtual	Method scala/reflect/Manifest$.AnyVal:()Lscala/reflect/Manifest;
	invokeinterface	InterfaceMethod scala/reflect/ClassManifest.$less$colon$less:(Lscala/reflect/ClassManifest;)Z
	ifne	l1 // iconst_0
	iconst_1
	goto	l2 // ireturn
l1	iconst_0
l2	ireturn
  Labels:
   	l1 = 33 // iconst_0
   	l2 = 34 // ireturn
  LocalVariableTable: 
   Start  Length  Slot  Name   Signature
   0      35      0    this       Lscala/reflect/Manifest$$anon$13;
   0      35      1    that       Lscala/reflect/ClassManifest;

  Signature: length = 0x2
   00 21 

public boolean equals(java.lang.Object);
  Signature: (Ljava/lang/Object;)Z
  Code:
   Stack=2, Locals=2, Args_size=2
	aload_0
	aload_1
	if_acmpne	l1 // iconst_0
	iconst_1
	goto	l2 // ireturn
l1	iconst_0
l2	ireturn
  Labels:
   	l1 = 9 // iconst_0
   	l2 = 10 // ireturn
  LocalVariableTable: 
   Start  Length  Slot  Name   Signature
   0      11      0    this       Lscala/reflect/Manifest$$anon$13;
   0      11      1    that       Ljava/lang/Object;


public int hashCode();
  Signature: ()I
  Code:
   Stack=1, Locals=1, Args_size=1
	aload_0
	invokestatic	Method java/lang/System.identityHashCode:(Ljava/lang/Object;)I
	ireturn
  Labels:

private java.lang.Object readResolve();
  Signature: ()Ljava/lang/Object;
  Code:
   Stack=1, Locals=1, Args_size=1
	getstatic	Field scala/reflect/Manifest$.MODULE$:Lscala/reflect/Manifest$;
	invokevirtual	Method scala/reflect/Manifest$.Null:()Lscala/reflect/Manifest;
	areturn
  Labels:

public scala.reflect.Manifest$$anon$13();
  Signature: ()V
  Code:
   Stack=4, Locals=1, Args_size=1
	aload_0
	getstatic	Field scala/None$.MODULE$:Lscala/None$;
	ldc	class java/lang/Object
	getstatic	Field scala/collection/immutable/Nil$.MODULE$:Lscala/collection/immutable/Nil$;
	invokespecial	Method scala/reflect/Manifest$ClassTypeManifest."<init>":(Lscala/Option;Ljava/lang/Class;Lscala/collection/immutable/List;)V
	return
  Labels:

}

