Compiled from "Manifest.scala"
public final class scala.reflect.Manifest$$anon$5 extends java.lang.Object implements scala.reflect.AnyValManifest
  InnerClass: 
   public final $anon$5=class scala/reflect/Manifest$$anon$5 of class scala/reflect/Manifest
   public final ofLong=class scala/collection/mutable/WrappedArray$ofLong of class scala/collection/mutable/WrappedArray
  Scala: length = 0x
   
  Signature: length = 0x2
   00 46 
  SourceFile: "Manifest.scala"
  minor version: 0
  major version: 49
  Constant pool:
String	Long
class	java/lang/Long
class	java/lang/Object
class	scala/collection/mutable/ArrayBuilder
class	scala/collection/mutable/WrappedArray
class	scala/collection/mutable/WrappedArray$ofLong
class	scala/reflect/AnyValManifest
class	scala/reflect/AnyValManifest$class
class	scala/reflect/ClassManifest$class
class	scala/reflect/Manifest
class	scala/reflect/Manifest$$anon$5
class	scala/reflect/Manifest$class
Field	java/lang/Long.TYPE:Ljava/lang/Class;
Method	java/lang/Object."<init>":()V
Method	scala/collection/mutable/WrappedArray$ofLong."<init>":([J)V
Method	scala/reflect/AnyValManifest$class.$init$:(Lscala/reflect/AnyValManifest;)V
Method	scala/reflect/AnyValManifest$class.$less$colon$less:(Lscala/reflect/AnyValManifest;Lscala/reflect/ClassManifest;)Z
Method	scala/reflect/AnyValManifest$class.canEqual:(Lscala/reflect/AnyValManifest;Ljava/lang/Object;)Z
Method	scala/reflect/AnyValManifest$class.equals:(Lscala/reflect/AnyValManifest;Ljava/lang/Object;)Z
Method	scala/reflect/AnyValManifest$class.hashCode:(Lscala/reflect/AnyValManifest;)I
Method	scala/reflect/ClassManifest$class.$init$:(Lscala/reflect/ClassManifest;)V
Method	scala/reflect/ClassManifest$class.argString:(Lscala/reflect/ClassManifest;)Ljava/lang/String;
Method	scala/reflect/Manifest$$anon$5.newArray:(I)[J
Method	scala/reflect/Manifest$class.$init$:(Lscala/reflect/Manifest;)V
Method	scala/reflect/Manifest$class.typeArguments:(Lscala/reflect/Manifest;)Lscala/collection/immutable/List;
NameAndType	$init$:(Lscala/reflect/AnyValManifest;)V
NameAndType	$init$:(Lscala/reflect/ClassManifest;)V
NameAndType	$init$:(Lscala/reflect/Manifest;)V
NameAndType	$less$colon$less:(Lscala/reflect/AnyValManifest;Lscala/reflect/ClassManifest;)Z
NameAndType	"<init>":()V
NameAndType	"<init>":([J)V
NameAndType	TYPE:Ljava/lang/Class;
NameAndType	argString:(Lscala/reflect/ClassManifest;)Ljava/lang/String;
NameAndType	canEqual:(Lscala/reflect/AnyValManifest;Ljava/lang/Object;)Z
NameAndType	equals:(Lscala/reflect/AnyValManifest;Ljava/lang/Object;)Z
NameAndType	hashCode:(Lscala/reflect/AnyValManifest;)I
NameAndType	newArray:(I)[J
NameAndType	typeArguments:(Lscala/reflect/Manifest;)Lscala/collection/immutable/List;
Asciz	$anon$5;
Asciz	$init$;
Asciz	$less$colon$less;
Asciz	()I;
Asciz	()Ljava/lang/Class;;
Asciz	()Ljava/lang/Class<Ljava/lang/Long;>;;
Asciz	()Ljava/lang/String;;
Asciz	()Lscala/collection/immutable/List;;
Asciz	()V;
Asciz	(I)Ljava/lang/Object;;
Asciz	(I)Lscala/collection/mutable/WrappedArray;;
Asciz	(I)Lscala/collection/mutable/WrappedArray<Ljava/lang/Long;>;;
Asciz	(I)[J;
Asciz	(Ljava/lang/Object;)Z;
Asciz	(Lscala/reflect/AnyValManifest;)I;
Asciz	(Lscala/reflect/AnyValManifest;)V;
Asciz	(Lscala/reflect/AnyValManifest;Ljava/lang/Object;)Z;
Asciz	(Lscala/reflect/AnyValManifest;Lscala/reflect/ClassManifest;)Z;
Asciz	(Lscala/reflect/ClassManifest;)Ljava/lang/String;;
Asciz	(Lscala/reflect/ClassManifest;)V;
Asciz	(Lscala/reflect/ClassManifest;)Z;
Asciz	(Lscala/reflect/Manifest;)Lscala/collection/immutable/List;;
Asciz	(Lscala/reflect/Manifest;)V;
Asciz	([J)V;
Asciz	<init>;
Asciz	Code;
Asciz	I;
Asciz	InnerClasses;
Asciz	LineNumberTable;
Asciz	Ljava/lang/Class;;
Asciz	Ljava/lang/Object;;
Asciz	Ljava/lang/Object;Lscala/reflect/AnyValManifest<Ljava/lang/Long;>;;
Asciz	LocalVariableTable;
Asciz	Long;
Asciz	Lscala/reflect/ClassManifest;;
Asciz	Lscala/reflect/Manifest$$anon$5;;
Asciz	Manifest.scala;
Asciz	Scala;
Asciz	Signature;
Asciz	SourceFile;
Asciz	TYPE;
Asciz	argString;
Asciz	canEqual;
Asciz	equals;
Asciz	erasure;
Asciz	hashCode;
Asciz	java/lang/Long;
Asciz	java/lang/Object;
Asciz	len;
Asciz	newArray;
Asciz	newWrappedArray;
Asciz	ofLong;
Asciz	other;
Asciz	scala/collection/mutable/ArrayBuilder;
Asciz	scala/collection/mutable/WrappedArray;
Asciz	scala/collection/mutable/WrappedArray$ofLong;
Asciz	scala/reflect/AnyValManifest;
Asciz	scala/reflect/AnyValManifest$class;
Asciz	scala/reflect/ClassManifest$class;
Asciz	scala/reflect/Manifest;
Asciz	scala/reflect/Manifest$$anon$5;
Asciz	scala/reflect/Manifest$class;
Asciz	that;
Asciz	this;
Asciz	toString;
Asciz	typeArguments;

{
public boolean $less$colon$less(scala.reflect.ClassManifest);
  Signature: (Lscala/reflect/ClassManifest;)Z
  Code:
   Stack=2, Locals=2, Args_size=2
	aload_0
	aload_1
	invokestatic	Method scala/reflect/AnyValManifest$class.$less$colon$less:(Lscala/reflect/AnyValManifest;Lscala/reflect/ClassManifest;)Z
	ireturn
  Labels:
  LocalVariableTable: 
   Start  Length  Slot  Name   Signature
   0      6      0    this       Lscala/reflect/Manifest$$anon$5;
   0      6      1    that       Lscala/reflect/ClassManifest;


public boolean canEqual(java.lang.Object);
  Signature: (Ljava/lang/Object;)Z
  Code:
   Stack=2, Locals=2, Args_size=2
	aload_0
	aload_1
	invokestatic	Method scala/reflect/AnyValManifest$class.canEqual:(Lscala/reflect/AnyValManifest;Ljava/lang/Object;)Z
	ireturn
  Labels:
  LocalVariableTable: 
   Start  Length  Slot  Name   Signature
   0      6      0    this       Lscala/reflect/Manifest$$anon$5;
   0      6      1    other       Ljava/lang/Object;


public boolean equals(java.lang.Object);
  Signature: (Ljava/lang/Object;)Z
  Code:
   Stack=2, Locals=2, Args_size=2
	aload_0
	aload_1
	invokestatic	Method scala/reflect/AnyValManifest$class.equals:(Lscala/reflect/AnyValManifest;Ljava/lang/Object;)Z
	ireturn
  Labels:
  LocalVariableTable: 
   Start  Length  Slot  Name   Signature
   0      6      0    this       Lscala/reflect/Manifest$$anon$5;
   0      6      1    that       Ljava/lang/Object;


public int hashCode();
  Signature: ()I
  Code:
   Stack=1, Locals=1, Args_size=1
	aload_0
	invokestatic	Method scala/reflect/AnyValManifest$class.hashCode:(Lscala/reflect/AnyValManifest;)I
	ireturn
  Labels:

public scala.collection.immutable.List typeArguments();
  Signature: ()Lscala/collection/immutable/List;
  Code:
   Stack=1, Locals=1, Args_size=1
	aload_0
	invokestatic	Method scala/reflect/Manifest$class.typeArguments:(Lscala/reflect/Manifest;)Lscala/collection/immutable/List;
	areturn
  Labels:

public java.lang.String argString();
  Signature: ()Ljava/lang/String;
  Code:
   Stack=1, Locals=1, Args_size=1
	aload_0
	invokestatic	Method scala/reflect/ClassManifest$class.argString:(Lscala/reflect/ClassManifest;)Ljava/lang/String;
	areturn
  Labels:

public java.lang.Class erasure();
  Signature: ()Ljava/lang/Class;
  Code:
   Stack=1, Locals=1, Args_size=1
	getstatic	Field java/lang/Long.TYPE:Ljava/lang/Class;
	areturn
  Labels:
  Signature: length = 0x2
   00 2C 

public java.lang.String toString();
  Signature: ()Ljava/lang/String;
  Code:
   Stack=1, Locals=1, Args_size=1
	ldc	String Long
	areturn
  Labels:

public long[] newArray(int);
  Signature: (I)[J
  Code:
   Stack=1, Locals=2, Args_size=2
	iload_1
	newarray long
	areturn
  Labels:
  LocalVariableTable: 
   Start  Length  Slot  Name   Signature
   0      4      0    this       Lscala/reflect/Manifest$$anon$5;
   0      4      1    len       I


public scala.collection.mutable.WrappedArray newWrappedArray(int);
  Signature: (I)Lscala/collection/mutable/WrappedArray;
  Code:
   Stack=3, Locals=2, Args_size=2
	new	class scala/collection/mutable/WrappedArray$ofLong
	dup
	iload_1
	newarray long
	invokespecial	Method scala/collection/mutable/WrappedArray$ofLong."<init>":([J)V
	areturn
  Labels:
  LocalVariableTable: 
   Start  Length  Slot  Name   Signature
   0      11      0    this       Lscala/reflect/Manifest$$anon$5;
   0      11      1    len       I

  Signature: length = 0x2
   00 32 

public java.lang.Object newArray(int);
  Signature: (I)Ljava/lang/Object;
  Code:
   Stack=2, Locals=2, Args_size=2
	aload_0
	iload_1
	invokevirtual	Method newArray:(I)[J
	areturn
  Labels:
  LocalVariableTable: 
   Start  Length  Slot  Name   Signature
   0      6      0    this       Lscala/reflect/Manifest$$anon$5;
   0      6      1    len       I


public scala.reflect.Manifest$$anon$5();
  Signature: ()V
  Code:
   Stack=1, Locals=1, Args_size=1
	aload_0
	invokespecial	Method java/lang/Object."<init>":()V
	aload_0
	invokestatic	Method scala/reflect/ClassManifest$class.$init$:(Lscala/reflect/ClassManifest;)V
	aload_0
	invokestatic	Method scala/reflect/Manifest$class.$init$:(Lscala/reflect/Manifest;)V
	aload_0
	invokestatic	Method scala/reflect/AnyValManifest$class.$init$:(Lscala/reflect/AnyValManifest;)V
	return
  Labels:

}

