Compiled from "Manifest.scala"
public abstract class scala.reflect.Manifest$class extends java.lang.Object
  SourceFile: "Manifest.scala"
  Scala: length = 0x
   
  minor version: 0
  major version: 49
  Constant pool:
Asciz	SourceFile;
Asciz	Manifest.scala;
Asciz	typeArguments;
Asciz	(Lscala/reflect/Manifest;)Lscala/collection/immutable/List;;
Asciz	Code;
Asciz	scala/collection/immutable/Nil$;
class	scala/collection/immutable/Nil$
Asciz	MODULE$;
Asciz	Lscala/collection/immutable/Nil$;;
NameAndType	MODULE$:Lscala/collection/immutable/Nil$;
Field	scala/collection/immutable/Nil$.MODULE$:Lscala/collection/immutable/Nil$;
Asciz	LineNumberTable;
Asciz	$this;
Asciz	Lscala/reflect/Manifest;;
Asciz	LocalVariableTable;
Asciz	arrayManifest;
Asciz	(Lscala/reflect/Manifest;)Lscala/reflect/Manifest;;
Asciz	scala/reflect/Manifest$;
class	scala/reflect/Manifest$
Asciz	Lscala/reflect/Manifest$;;
NameAndType	MODULE$:Lscala/reflect/Manifest$;
Field	scala/reflect/Manifest$.MODULE$:Lscala/reflect/Manifest$;
Asciz	scala/reflect/ClassManifest;
class	scala/reflect/ClassManifest
Asciz	erasure;
Asciz	()Ljava/lang/Class;;
NameAndType	erasure:()Ljava/lang/Class;
InterfaceMethod	scala/reflect/ClassManifest.erasure:()Ljava/lang/Class;
Asciz	arrayClass;
Asciz	(Ljava/lang/Class;)Ljava/lang/Class;;
NameAndType	arrayClass:(Ljava/lang/Class;)Ljava/lang/Class;
InterfaceMethod	scala/reflect/ClassManifest.arrayClass:(Ljava/lang/Class;)Ljava/lang/Class;
Asciz	classType;
Asciz	(Ljava/lang/Class;)Lscala/reflect/Manifest;;
NameAndType	classType:(Ljava/lang/Class;)Lscala/reflect/Manifest;
Method	scala/reflect/Manifest$.classType:(Ljava/lang/Class;)Lscala/reflect/Manifest;
Asciz	canEqual;
Asciz	(Lscala/reflect/Manifest;Ljava/lang/Object;)Z;
Asciz	scala/reflect/Manifest;
class	scala/reflect/Manifest
Asciz	that;
Asciz	Ljava/lang/Object;;
Asciz	equals;
Asciz	scala/reflect/Manifest$class;
class	scala/reflect/Manifest$class
Asciz	gd1$1;
Asciz	(Lscala/reflect/Manifest;Lscala/reflect/Manifest;)Z;
NameAndType	gd1$1:(Lscala/reflect/Manifest;Lscala/reflect/Manifest;)Z
Method	scala/reflect/Manifest$class.gd1$1:(Lscala/reflect/Manifest;Lscala/reflect/Manifest;)Z
Asciz	$less$colon$less;
Asciz	(Lscala/reflect/ClassManifest;)Z;
NameAndType	$less$colon$less:(Lscala/reflect/ClassManifest;)Z
InterfaceMethod	scala/reflect/ClassManifest.$less$colon$less:(Lscala/reflect/ClassManifest;)Z
Asciz	temp4;
Asciz	hashCode;
Asciz	(Lscala/reflect/Manifest;)I;
Asciz	java/lang/Class;
class	java/lang/Class
Asciz	()I;
NameAndType	hashCode:()I
Method	java/lang/Class.hashCode:()I
Asciz	(Ljava/lang/Object;)Z;
NameAndType	canEqual:(Ljava/lang/Object;)Z
InterfaceMethod	scala/reflect/Manifest.canEqual:(Ljava/lang/Object;)Z
Asciz	$init$;
Asciz	(Lscala/reflect/Manifest;)V;
Asciz	Scala;
Asciz	java/lang/Object;
class	java/lang/Object

{
public static scala.collection.immutable.List typeArguments(scala.reflect.Manifest);
  Signature: (Lscala/reflect/Manifest;)Lscala/collection/immutable/List;
  Code:
   Stack=1, Locals=1, Args_size=1
	getstatic	Field scala/collection/immutable/Nil$.MODULE$:Lscala/collection/immutable/Nil$;
	areturn
  Labels:
  LocalVariableTable: 
   Start  Length  Slot  Name   Signature
   0      4      0    $this       Lscala/reflect/Manifest;


public static scala.reflect.Manifest arrayManifest(scala.reflect.Manifest);
  Signature: (Lscala/reflect/Manifest;)Lscala/reflect/Manifest;
  Code:
   Stack=3, Locals=1, Args_size=1
	getstatic	Field scala/reflect/Manifest$.MODULE$:Lscala/reflect/Manifest$;
	aload_0
	aload_0
	invokeinterface	InterfaceMethod scala/reflect/ClassManifest.erasure:()Ljava/lang/Class;
	invokeinterface	InterfaceMethod scala/reflect/ClassManifest.arrayClass:(Ljava/lang/Class;)Ljava/lang/Class;
	invokevirtual	Method scala/reflect/Manifest$.classType:(Ljava/lang/Class;)Lscala/reflect/Manifest;
	areturn
  Labels:
  LocalVariableTable: 
   Start  Length  Slot  Name   Signature
   0      19      0    $this       Lscala/reflect/Manifest;


public static boolean canEqual(scala.reflect.Manifest, java.lang.Object);
  Signature: (Lscala/reflect/Manifest;Ljava/lang/Object;)Z
  Code:
   Stack=1, Locals=2, Args_size=2
	aload_1
	instanceof	class scala/reflect/Manifest
	ireturn
  Labels:
  LocalVariableTable: 
   Start  Length  Slot  Name   Signature
   0      5      0    $this       Lscala/reflect/Manifest;
   0      5      1    that       Ljava/lang/Object;


public static boolean equals(scala.reflect.Manifest, java.lang.Object);
  Signature: (Lscala/reflect/Manifest;Ljava/lang/Object;)Z
  Code:
   Stack=2, Locals=3, Args_size=2
	aload_1
	instanceof	class scala/reflect/Manifest
	ifeq	l1 // iconst_0
	aload_1
	checkcast	class scala/reflect/Manifest
	astore_2
	aload_0
	aload_2
	invokestatic	Method gd1$1:(Lscala/reflect/Manifest;Lscala/reflect/Manifest;)Z
	ifeq	l2 // iconst_0
	aload_0
	aload_2
	invokeinterface	InterfaceMethod scala/reflect/ClassManifest.$less$colon$less:(Lscala/reflect/ClassManifest;)Z
	ifeq	l3 // iconst_0
	aload_2
	aload_0
	invokeinterface	InterfaceMethod scala/reflect/ClassManifest.$less$colon$less:(Lscala/reflect/ClassManifest;)Z
	ifeq	l3 // iconst_0
	iconst_1
	goto	l4 // ireturn
l3	iconst_0
	goto	l4 // ireturn
l2	iconst_0
	goto	l4 // ireturn
l1	iconst_0
l4	ireturn
  Labels:
   	l3 = 44 // iconst_0
   	l2 = 48 // iconst_0
   	l1 = 52 // iconst_0
   	l4 = 53 // ireturn
  LocalVariableTable: 
   Start  Length  Slot  Name   Signature
   0      54      0    $this       Lscala/reflect/Manifest;
   0      54      1    that       Ljava/lang/Object;
   12      40      2    temp4       Lscala/reflect/Manifest;


public static int hashCode(scala.reflect.Manifest);
  Signature: (Lscala/reflect/Manifest;)I
  Code:
   Stack=1, Locals=1, Args_size=1
	aload_0
	invokeinterface	InterfaceMethod scala/reflect/ClassManifest.erasure:()Ljava/lang/Class;
	invokevirtual	Method java/lang/Class.hashCode:()I
	ireturn
  Labels:
  LocalVariableTable: 
   Start  Length  Slot  Name   Signature
   0      10      0    $this       Lscala/reflect/Manifest;


private static final boolean gd1$1(scala.reflect.Manifest, scala.reflect.Manifest);
  Signature: (Lscala/reflect/Manifest;Lscala/reflect/Manifest;)Z
  Code:
   Stack=2, Locals=2, Args_size=2
	aload_1
	aload_0
	invokeinterface	InterfaceMethod scala/reflect/Manifest.canEqual:(Ljava/lang/Object;)Z
	ireturn
  Labels:
  LocalVariableTable: 
   Start  Length  Slot  Name   Signature
   0      8      0    $this       Lscala/reflect/Manifest;


public static void $init$(scala.reflect.Manifest);
  Signature: (Lscala/reflect/Manifest;)V
  Code:
   Stack=0, Locals=1, Args_size=1
	return
  Labels:
  LocalVariableTable: 
   Start  Length  Slot  Name   Signature
   0      1      0    $this       Lscala/reflect/Manifest;


}

