Compiled from "Manifest.scala"
public final class scala.reflect.Manifest$ extends java.lang.Object implements scala.ScalaObject
  SourceFile: "Manifest.scala"
  Scala: length = 0x
   
  InnerClass: 
   public final $anon$9=class scala/reflect/Manifest$$anon$9 of class scala/reflect/Manifest
   public final $anon$8=class scala/reflect/Manifest$$anon$8 of class scala/reflect/Manifest
   public final $anon$7=class scala/reflect/Manifest$$anon$7 of class scala/reflect/Manifest
   public final $anon$6=class scala/reflect/Manifest$$anon$6 of class scala/reflect/Manifest
   public final $anon$5=class scala/reflect/Manifest$$anon$5 of class scala/reflect/Manifest
   public final $anon$4=class scala/reflect/Manifest$$anon$4 of class scala/reflect/Manifest
   public final $anon$3=class scala/reflect/Manifest$$anon$3 of class scala/reflect/Manifest
   public final $anon$2=class scala/reflect/Manifest$$anon$2 of class scala/reflect/Manifest
   public final $anon$1=class scala/reflect/Manifest$$anon$1 of class scala/reflect/Manifest
   public final $anon$14=class scala/reflect/Manifest$$anon$14 of class scala/reflect/Manifest
   public final $anon$13=class scala/reflect/Manifest$$anon$13 of class scala/reflect/Manifest
   public final $anon$12=class scala/reflect/Manifest$$anon$12 of class scala/reflect/Manifest
   public final $anon$11=class scala/reflect/Manifest$$anon$11 of class scala/reflect/Manifest
   public final $anon$10=class scala/reflect/Manifest$$anon$10 of class scala/reflect/Manifest
   public final $anon$18=class scala/reflect/Manifest$$anon$18 of class scala/reflect/Manifest
   public final $anon$17=class scala/reflect/Manifest$$anon$17 of class scala/reflect/Manifest
   public final $anon$16=class scala/reflect/Manifest$$anon$16 of class scala/reflect/Manifest
   public final $anon$15=class scala/reflect/Manifest$$anon$15 of class scala/reflect/Manifest
   public ClassTypeManifest=class scala/reflect/Manifest$ClassTypeManifest of class scala/reflect/Manifest
  minor version: 0
  major version: 49
  Constant pool:
Asciz	SourceFile;
Asciz	Manifest.scala;
Asciz	Scala;
Asciz	MODULE$;
Asciz	Lscala/reflect/Manifest$;;
Asciz	<clinit>;
Asciz	()V;
Asciz	Code;
Asciz	scala/reflect/Manifest$;
class	scala/reflect/Manifest$
Asciz	<init>;
NameAndType	"<init>":()V
Method	scala/reflect/Manifest$."<init>":()V
Asciz	Nothing;
Asciz	Lscala/reflect/Manifest;;
Asciz	Lscala/reflect/Manifest<Lscala/runtime/Nothing$;>;;
Asciz	Signature;
Asciz	Null;
Asciz	Lscala/reflect/Manifest<Lscala/runtime/Null$;>;;
Asciz	AnyVal;
Asciz	Lscala/reflect/Manifest<Ljava/lang/Object;>;;
Asciz	Object;
Asciz	Any;
Asciz	Unit;
Asciz	Lscala/reflect/AnyValManifest;;
Asciz	Lscala/reflect/AnyValManifest<Ljava/lang/Object;>;;
Asciz	Boolean;
Asciz	Lscala/reflect/AnyValManifest<Ljava/lang/Boolean;>;;
Asciz	Double;
Asciz	Lscala/reflect/AnyValManifest<Ljava/lang/Double;>;;
Asciz	Float;
Asciz	Lscala/reflect/AnyValManifest<Ljava/lang/Float;>;;
Asciz	Long;
Asciz	Lscala/reflect/AnyValManifest<Ljava/lang/Long;>;;
Asciz	Int;
Asciz	Lscala/reflect/AnyValManifest<Ljava/lang/Integer;>;;
Asciz	Char;
Asciz	Lscala/reflect/AnyValManifest<Ljava/lang/Character;>;;
Asciz	Short;
Asciz	Lscala/reflect/AnyValManifest<Ljava/lang/Short;>;;
Asciz	Byte;
Asciz	Lscala/reflect/AnyValManifest<Ljava/lang/Byte;>;;
Asciz	()Lscala/reflect/AnyValManifest;;
Asciz	LineNumberTable;
NameAndType	Byte:Lscala/reflect/AnyValManifest;
Field	scala/reflect/Manifest$.Byte:Lscala/reflect/AnyValManifest;
Asciz	()Lscala/reflect/AnyValManifest<Ljava/lang/Byte;>;;
NameAndType	Short:Lscala/reflect/AnyValManifest;
Field	scala/reflect/Manifest$.Short:Lscala/reflect/AnyValManifest;
Asciz	()Lscala/reflect/AnyValManifest<Ljava/lang/Short;>;;
NameAndType	Char:Lscala/reflect/AnyValManifest;
Field	scala/reflect/Manifest$.Char:Lscala/reflect/AnyValManifest;
Asciz	()Lscala/reflect/AnyValManifest<Ljava/lang/Character;>;;
NameAndType	Int:Lscala/reflect/AnyValManifest;
Field	scala/reflect/Manifest$.Int:Lscala/reflect/AnyValManifest;
Asciz	()Lscala/reflect/AnyValManifest<Ljava/lang/Integer;>;;
NameAndType	Long:Lscala/reflect/AnyValManifest;
Field	scala/reflect/Manifest$.Long:Lscala/reflect/AnyValManifest;
Asciz	()Lscala/reflect/AnyValManifest<Ljava/lang/Long;>;;
NameAndType	Float:Lscala/reflect/AnyValManifest;
Field	scala/reflect/Manifest$.Float:Lscala/reflect/AnyValManifest;
Asciz	()Lscala/reflect/AnyValManifest<Ljava/lang/Float;>;;
NameAndType	Double:Lscala/reflect/AnyValManifest;
Field	scala/reflect/Manifest$.Double:Lscala/reflect/AnyValManifest;
Asciz	()Lscala/reflect/AnyValManifest<Ljava/lang/Double;>;;
NameAndType	Boolean:Lscala/reflect/AnyValManifest;
Field	scala/reflect/Manifest$.Boolean:Lscala/reflect/AnyValManifest;
Asciz	()Lscala/reflect/AnyValManifest<Ljava/lang/Boolean;>;;
NameAndType	Unit:Lscala/reflect/AnyValManifest;
Field	scala/reflect/Manifest$.Unit:Lscala/reflect/AnyValManifest;
Asciz	()Lscala/reflect/AnyValManifest<Ljava/lang/Object;>;;
Asciz	()Lscala/reflect/Manifest;;
NameAndType	Any:Lscala/reflect/Manifest;
Field	scala/reflect/Manifest$.Any:Lscala/reflect/Manifest;
Asciz	()Lscala/reflect/Manifest<Ljava/lang/Object;>;;
NameAndType	Object:Lscala/reflect/Manifest;
Field	scala/reflect/Manifest$.Object:Lscala/reflect/Manifest;
NameAndType	AnyVal:Lscala/reflect/Manifest;
Field	scala/reflect/Manifest$.AnyVal:Lscala/reflect/Manifest;
NameAndType	Null:Lscala/reflect/Manifest;
Field	scala/reflect/Manifest$.Null:Lscala/reflect/Manifest;
Asciz	()Lscala/reflect/Manifest<Lscala/runtime/Null$;>;;
NameAndType	Nothing:Lscala/reflect/Manifest;
Field	scala/reflect/Manifest$.Nothing:Lscala/reflect/Manifest;
Asciz	()Lscala/reflect/Manifest<Lscala/runtime/Nothing$;>;;
Asciz	singleType;
Asciz	(Ljava/lang/Object;)Lscala/reflect/Manifest;;
Asciz	scala/reflect/Manifest$$anon$15;
class	scala/reflect/Manifest$$anon$15
Asciz	(Ljava/lang/Object;)V;
NameAndType	"<init>":(Ljava/lang/Object;)V
Method	scala/reflect/Manifest$$anon$15."<init>":(Ljava/lang/Object;)V
Asciz	this;
Asciz	value$1;
Asciz	Ljava/lang/Object;;
Asciz	LocalVariableTable;
Asciz	<T:Ljava/lang/Object;>(Ljava/lang/Object;)Lscala/reflect/Manifest<TT;>;;
Asciz	classType;
Asciz	(Ljava/lang/Class;)Lscala/reflect/Manifest;;
Asciz	scala/reflect/Manifest$ClassTypeManifest;
class	scala/reflect/Manifest$ClassTypeManifest
Asciz	scala/None$;
class	scala/None$
Asciz	Lscala/None$;;
NameAndType	MODULE$:Lscala/None$;
Field	scala/None$.MODULE$:Lscala/None$;
Asciz	scala/collection/immutable/Nil$;
class	scala/collection/immutable/Nil$
Asciz	Lscala/collection/immutable/Nil$;;
NameAndType	MODULE$:Lscala/collection/immutable/Nil$;
Field	scala/collection/immutable/Nil$.MODULE$:Lscala/collection/immutable/Nil$;
Asciz	(Lscala/Option;Ljava/lang/Class;Lscala/collection/immutable/List;)V;
NameAndType	"<init>":(Lscala/Option;Ljava/lang/Class;Lscala/collection/immutable/List;)V
Method	scala/reflect/Manifest$ClassTypeManifest."<init>":(Lscala/Option;Ljava/lang/Class;Lscala/collection/immutable/List;)V
Asciz	clazz;
Asciz	Ljava/lang/Class;;
Asciz	<T:Ljava/lang/Object;>(Ljava/lang/Class<*>;)Lscala/reflect/Manifest<TT;>;;
Asciz	(Ljava/lang/Class;Lscala/reflect/Manifest;Lscala/collection/Seq;)Lscala/reflect/Manifest;;
Asciz	scala/collection/TraversableLike;
class	scala/collection/TraversableLike
Asciz	toList;
Asciz	()Lscala/collection/immutable/List;;
NameAndType	toList:()Lscala/collection/immutable/List;
InterfaceMethod	scala/collection/TraversableLike.toList:()Lscala/collection/immutable/List;
Asciz	scala/collection/immutable/List;
class	scala/collection/immutable/List
Asciz	$colon$colon;
Asciz	(Ljava/lang/Object;)Lscala/collection/immutable/List;;
NameAndType	$colon$colon:(Ljava/lang/Object;)Lscala/collection/immutable/List;
Method	scala/collection/immutable/List.$colon$colon:(Ljava/lang/Object;)Lscala/collection/immutable/List;
Asciz	arg1;
Asciz	args;
Asciz	Lscala/collection/Seq;;
Asciz	<T:Ljava/lang/Object;>(Ljava/lang/Class<TT;>;Lscala/reflect/Manifest<*>;Lscala/collection/Seq<Lscala/reflect/Manifest<*>;>;)Lscala/reflect/Manifest<TT;>;;
Asciz	(Lscala/reflect/Manifest;Ljava/lang/Class;Lscala/collection/Seq;)Lscala/reflect/Manifest;;
Asciz	scala/Some;
class	scala/Some
Method	scala/Some."<init>":(Ljava/lang/Object;)V
Asciz	prefix;
Asciz	<T:Ljava/lang/Object;>(Lscala/reflect/Manifest<*>;Ljava/lang/Class<*>;Lscala/collection/Seq<Lscala/reflect/Manifest<*>;>;)Lscala/reflect/Manifest<TT;>;;
Asciz	arrayType;
Asciz	(Lscala/reflect/Manifest;)Lscala/reflect/Manifest;;
Asciz	scala/reflect/Manifest;
class	scala/reflect/Manifest
Asciz	arrayManifest;
NameAndType	arrayManifest:()Lscala/reflect/Manifest;
InterfaceMethod	scala/reflect/Manifest.arrayManifest:()Lscala/reflect/Manifest;
Asciz	arg;
Asciz	<T:Ljava/lang/Object;>(Lscala/reflect/Manifest<*>;)Lscala/reflect/Manifest<[TT;>;;
Asciz	abstractType;
Asciz	(Lscala/reflect/Manifest;Ljava/lang/String;Ljava/lang/Class;Lscala/collection/Seq;)Lscala/reflect/Manifest;;
Asciz	scala/reflect/Manifest$$anon$16;
class	scala/reflect/Manifest$$anon$16
Asciz	(Lscala/reflect/Manifest;Ljava/lang/String;Ljava/lang/Class;Lscala/collection/Seq;)V;
NameAndType	"<init>":(Lscala/reflect/Manifest;Ljava/lang/String;Ljava/lang/Class;Lscala/collection/Seq;)V
Method	scala/reflect/Manifest$$anon$16."<init>":(Lscala/reflect/Manifest;Ljava/lang/String;Ljava/lang/Class;Lscala/collection/Seq;)V
Asciz	prefix$1;
Asciz	name$1;
Asciz	Ljava/lang/String;;
Asciz	clazz$1;
Asciz	args$1;
Asciz	<T:Ljava/lang/Object;>(Lscala/reflect/Manifest<*>;Ljava/lang/String;Ljava/lang/Class<*>;Lscala/collection/Seq<Lscala/reflect/Manifest<*>;>;)Lscala/reflect/Manifest<TT;>;;
Asciz	(Lscala/reflect/Manifest;Ljava/lang/String;Lscala/reflect/ClassManifest;Lscala/collection/Seq;)Lscala/reflect/Manifest;;
Asciz	scala/reflect/Manifest$$anon$17;
class	scala/reflect/Manifest$$anon$17
Asciz	(Lscala/reflect/Manifest;Ljava/lang/String;Lscala/reflect/ClassManifest;Lscala/collection/Seq;)V;
NameAndType	"<init>":(Lscala/reflect/Manifest;Ljava/lang/String;Lscala/reflect/ClassManifest;Lscala/collection/Seq;)V
Method	scala/reflect/Manifest$$anon$17."<init>":(Lscala/reflect/Manifest;Ljava/lang/String;Lscala/reflect/ClassManifest;Lscala/collection/Seq;)V
Asciz	prefix$2;
Asciz	name$2;
Asciz	upperbound$1;
Asciz	Lscala/reflect/ClassManifest;;
Asciz	args$2;
Asciz	<T:Ljava/lang/Object;>(Lscala/reflect/Manifest<*>;Ljava/lang/String;Lscala/reflect/ClassManifest<*>;Lscala/collection/Seq<Lscala/reflect/Manifest<*>;>;)Lscala/reflect/Manifest<TT;>;;
Asciz	intersectionType;
Asciz	(Lscala/collection/Seq;)Lscala/reflect/Manifest;;
Asciz	scala/reflect/Manifest$$anon$18;
class	scala/reflect/Manifest$$anon$18
Asciz	(Lscala/collection/Seq;)V;
NameAndType	"<init>":(Lscala/collection/Seq;)V
Method	scala/reflect/Manifest$$anon$18."<init>":(Lscala/collection/Seq;)V
Asciz	parents$1;
Asciz	<T:Ljava/lang/Object;>(Lscala/collection/Seq<Lscala/reflect/Manifest<*>;>;)Lscala/reflect/Manifest<TT;>;;
Asciz	java/lang/Object;
class	java/lang/Object
Method	java/lang/Object."<init>":()V
NameAndType	MODULE$:Lscala/reflect/Manifest$;
Field	scala/reflect/Manifest$.MODULE$:Lscala/reflect/Manifest$;
Asciz	scala/reflect/Manifest$$anon$1;
class	scala/reflect/Manifest$$anon$1
Method	scala/reflect/Manifest$$anon$1."<init>":()V
Asciz	scala/reflect/Manifest$$anon$2;
class	scala/reflect/Manifest$$anon$2
Method	scala/reflect/Manifest$$anon$2."<init>":()V
Asciz	scala/reflect/Manifest$$anon$3;
class	scala/reflect/Manifest$$anon$3
Method	scala/reflect/Manifest$$anon$3."<init>":()V
Asciz	scala/reflect/Manifest$$anon$4;
class	scala/reflect/Manifest$$anon$4
Method	scala/reflect/Manifest$$anon$4."<init>":()V
Asciz	scala/reflect/Manifest$$anon$5;
class	scala/reflect/Manifest$$anon$5
Method	scala/reflect/Manifest$$anon$5."<init>":()V
Asciz	scala/reflect/Manifest$$anon$6;
class	scala/reflect/Manifest$$anon$6
Method	scala/reflect/Manifest$$anon$6."<init>":()V
Asciz	scala/reflect/Manifest$$anon$7;
class	scala/reflect/Manifest$$anon$7
Method	scala/reflect/Manifest$$anon$7."<init>":()V
Asciz	scala/reflect/Manifest$$anon$8;
class	scala/reflect/Manifest$$anon$8
Method	scala/reflect/Manifest$$anon$8."<init>":()V
Asciz	scala/reflect/Manifest$$anon$9;
class	scala/reflect/Manifest$$anon$9
Method	scala/reflect/Manifest$$anon$9."<init>":()V
Asciz	scala/reflect/Manifest$$anon$10;
class	scala/reflect/Manifest$$anon$10
Method	scala/reflect/Manifest$$anon$10."<init>":()V
Asciz	scala/reflect/Manifest$$anon$11;
class	scala/reflect/Manifest$$anon$11
Method	scala/reflect/Manifest$$anon$11."<init>":()V
Asciz	scala/reflect/Manifest$$anon$12;
class	scala/reflect/Manifest$$anon$12
Method	scala/reflect/Manifest$$anon$12."<init>":()V
Asciz	scala/reflect/Manifest$$anon$13;
class	scala/reflect/Manifest$$anon$13
Method	scala/reflect/Manifest$$anon$13."<init>":()V
Asciz	scala/reflect/Manifest$$anon$14;
class	scala/reflect/Manifest$$anon$14
Method	scala/reflect/Manifest$$anon$14."<init>":()V
Asciz	InnerClasses;
Asciz	$anon$9;
Asciz	$anon$8;
Asciz	$anon$7;
Asciz	$anon$6;
Asciz	$anon$5;
Asciz	$anon$4;
Asciz	$anon$3;
Asciz	$anon$2;
Asciz	$anon$1;
Asciz	$anon$14;
Asciz	$anon$13;
Asciz	$anon$12;
Asciz	$anon$11;
Asciz	$anon$10;
Asciz	$anon$18;
Asciz	$anon$17;
Asciz	$anon$16;
Asciz	$anon$15;
Asciz	ClassTypeManifest;
Asciz	scala/ScalaObject;
class	scala/ScalaObject

{
public static final scala.reflect.Manifest$ MODULE$;
  Signature: Lscala/reflect/Manifest$;

private final scala.reflect.Manifest Nothing;
  Signature: Lscala/reflect/Manifest;
  Signature: length = 0x2
   00 10 

private final scala.reflect.Manifest Null;
  Signature: Lscala/reflect/Manifest;
  Signature: length = 0x2
   00 13 

private final scala.reflect.Manifest AnyVal;
  Signature: Lscala/reflect/Manifest;
  Signature: length = 0x2
   00 15 

private final scala.reflect.Manifest Object;
  Signature: Lscala/reflect/Manifest;
  Signature: length = 0x2
   00 15 

private final scala.reflect.Manifest Any;
  Signature: Lscala/reflect/Manifest;
  Signature: length = 0x2
   00 15 

private final scala.reflect.AnyValManifest Unit;
  Signature: Lscala/reflect/AnyValManifest;
  Signature: length = 0x2
   00 1A 

private final scala.reflect.AnyValManifest Boolean;
  Signature: Lscala/reflect/AnyValManifest;
  Signature: length = 0x2
   00 1C 

private final scala.reflect.AnyValManifest Double;
  Signature: Lscala/reflect/AnyValManifest;
  Signature: length = 0x2
   00 1E 

private final scala.reflect.AnyValManifest Float;
  Signature: Lscala/reflect/AnyValManifest;
  Signature: length = 0x2
   00 20 

private final scala.reflect.AnyValManifest Long;
  Signature: Lscala/reflect/AnyValManifest;
  Signature: length = 0x2
   00 22 

private final scala.reflect.AnyValManifest Int;
  Signature: Lscala/reflect/AnyValManifest;
  Signature: length = 0x2
   00 24 

private final scala.reflect.AnyValManifest Char;
  Signature: Lscala/reflect/AnyValManifest;
  Signature: length = 0x2
   00 26 

private final scala.reflect.AnyValManifest Short;
  Signature: Lscala/reflect/AnyValManifest;
  Signature: length = 0x2
   00 28 

private final scala.reflect.AnyValManifest Byte;
  Signature: Lscala/reflect/AnyValManifest;
  Signature: length = 0x2
   00 2A 

public static {};
  Signature: ()V
  Code:
   Stack=1, Locals=0, Args_size=0
	new	class scala/reflect/Manifest$
	invokespecial	Method "<init>":()V
	return
  Labels:

public scala.reflect.AnyValManifest Byte();
  Signature: ()Lscala/reflect/AnyValManifest;
  Code:
   Stack=1, Locals=1, Args_size=1
	aload_0
	getfield	Field Byte:Lscala/reflect/AnyValManifest;
	areturn
  Labels:
  Signature: length = 0x2
   00 2F 

public scala.reflect.AnyValManifest Short();
  Signature: ()Lscala/reflect/AnyValManifest;
  Code:
   Stack=1, Locals=1, Args_size=1
	aload_0
	getfield	Field Short:Lscala/reflect/AnyValManifest;
	areturn
  Labels:
  Signature: length = 0x2
   00 32 

public scala.reflect.AnyValManifest Char();
  Signature: ()Lscala/reflect/AnyValManifest;
  Code:
   Stack=1, Locals=1, Args_size=1
	aload_0
	getfield	Field Char:Lscala/reflect/AnyValManifest;
	areturn
  Labels:
  Signature: length = 0x2
   00 35 

public scala.reflect.AnyValManifest Int();
  Signature: ()Lscala/reflect/AnyValManifest;
  Code:
   Stack=1, Locals=1, Args_size=1
	aload_0
	getfield	Field Int:Lscala/reflect/AnyValManifest;
	areturn
  Labels:
  Signature: length = 0x2
   00 38 

public scala.reflect.AnyValManifest Long();
  Signature: ()Lscala/reflect/AnyValManifest;
  Code:
   Stack=1, Locals=1, Args_size=1
	aload_0
	getfield	Field Long:Lscala/reflect/AnyValManifest;
	areturn
  Labels:
  Signature: length = 0x2
   00 3B 

public scala.reflect.AnyValManifest Float();
  Signature: ()Lscala/reflect/AnyValManifest;
  Code:
   Stack=1, Locals=1, Args_size=1
	aload_0
	getfield	Field Float:Lscala/reflect/AnyValManifest;
	areturn
  Labels:
  Signature: length = 0x2
   00 3E 

public scala.reflect.AnyValManifest Double();
  Signature: ()Lscala/reflect/AnyValManifest;
  Code:
   Stack=1, Locals=1, Args_size=1
	aload_0
	getfield	Field Double:Lscala/reflect/AnyValManifest;
	areturn
  Labels:
  Signature: length = 0x2
   00 41 

public scala.reflect.AnyValManifest Boolean();
  Signature: ()Lscala/reflect/AnyValManifest;
  Code:
   Stack=1, Locals=1, Args_size=1
	aload_0
	getfield	Field Boolean:Lscala/reflect/AnyValManifest;
	areturn
  Labels:
  Signature: length = 0x2
   00 44 

public scala.reflect.AnyValManifest Unit();
  Signature: ()Lscala/reflect/AnyValManifest;
  Code:
   Stack=1, Locals=1, Args_size=1
	aload_0
	getfield	Field Unit:Lscala/reflect/AnyValManifest;
	areturn
  Labels:
  Signature: length = 0x2
   00 47 

public scala.reflect.Manifest Any();
  Signature: ()Lscala/reflect/Manifest;
  Code:
   Stack=1, Locals=1, Args_size=1
	aload_0
	getfield	Field Any:Lscala/reflect/Manifest;
	areturn
  Labels:
  Signature: length = 0x2
   00 4B 

public scala.reflect.Manifest Object();
  Signature: ()Lscala/reflect/Manifest;
  Code:
   Stack=1, Locals=1, Args_size=1
	aload_0
	getfield	Field Object:Lscala/reflect/Manifest;
	areturn
  Labels:
  Signature: length = 0x2
   00 4B 

public scala.reflect.Manifest AnyVal();
  Signature: ()Lscala/reflect/Manifest;
  Code:
   Stack=1, Locals=1, Args_size=1
	aload_0
	getfield	Field AnyVal:Lscala/reflect/Manifest;
	areturn
  Labels:
  Signature: length = 0x2
   00 4B 

public scala.reflect.Manifest Null();
  Signature: ()Lscala/reflect/Manifest;
  Code:
   Stack=1, Locals=1, Args_size=1
	aload_0
	getfield	Field Null:Lscala/reflect/Manifest;
	areturn
  Labels:
  Signature: length = 0x2
   00 52 

public scala.reflect.Manifest Nothing();
  Signature: ()Lscala/reflect/Manifest;
  Code:
   Stack=1, Locals=1, Args_size=1
	aload_0
	getfield	Field Nothing:Lscala/reflect/Manifest;
	areturn
  Labels:
  Signature: length = 0x2
   00 55 

public scala.reflect.Manifest singleType(java.lang.Object);
  Signature: (Ljava/lang/Object;)Lscala/reflect/Manifest;
  Code:
   Stack=3, Locals=2, Args_size=2
	new	class scala/reflect/Manifest$$anon$15
	dup
	aload_1
	invokespecial	Method scala/reflect/Manifest$$anon$15."<init>":(Ljava/lang/Object;)V
	areturn
  Labels:
  LocalVariableTable: 
   Start  Length  Slot  Name   Signature
   0      9      0    this       Lscala/reflect/Manifest$;
   0      9      1    value$1       Ljava/lang/Object;

  Signature: length = 0x2
   00 61 

public scala.reflect.Manifest classType(java.lang.Class);
  Signature: (Ljava/lang/Class;)Lscala/reflect/Manifest;
  Code:
   Stack=5, Locals=2, Args_size=2
	new	class scala/reflect/Manifest$ClassTypeManifest
	dup
	getstatic	Field scala/None$.MODULE$:Lscala/None$;
	aload_1
	getstatic	Field scala/collection/immutable/Nil$.MODULE$:Lscala/collection/immutable/Nil$;
	invokespecial	Method scala/reflect/Manifest$ClassTypeManifest."<init>":(Lscala/Option;Ljava/lang/Class;Lscala/collection/immutable/List;)V
	areturn
  Labels:
  LocalVariableTable: 
   Start  Length  Slot  Name   Signature
   0      15      0    this       Lscala/reflect/Manifest$;
   0      15      1    clazz       Ljava/lang/Class;

  Signature: length = 0x2
   00 75 

public scala.reflect.Manifest classType(java.lang.Class, scala.reflect.Manifest, scala.collection.Seq);
  Signature: (Ljava/lang/Class;Lscala/reflect/Manifest;Lscala/collection/Seq;)Lscala/reflect/Manifest;
  Code:
   Stack=6, Locals=4, Args_size=4
	new	class scala/reflect/Manifest$ClassTypeManifest
	dup
	getstatic	Field scala/None$.MODULE$:Lscala/None$;
	aload_1
	aload_3
	invokeinterface	InterfaceMethod scala/collection/TraversableLike.toList:()Lscala/collection/immutable/List;
	aload_2
	invokevirtual	Method scala/collection/immutable/List.$colon$colon:(Ljava/lang/Object;)Lscala/collection/immutable/List;
	invokespecial	Method scala/reflect/Manifest$ClassTypeManifest."<init>":(Lscala/Option;Ljava/lang/Class;Lscala/collection/immutable/List;)V
	areturn
  Labels:
  LocalVariableTable: 
   Start  Length  Slot  Name   Signature
   0      22      0    this       Lscala/reflect/Manifest$;
   0      22      1    clazz       Ljava/lang/Class;
   0      22      2    arg1       Lscala/reflect/Manifest;
   0      22      3    args       Lscala/collection/Seq;

  Signature: length = 0x2
   00 FFFFFF86 

public scala.reflect.Manifest classType(scala.reflect.Manifest, java.lang.Class, scala.collection.Seq);
  Signature: (Lscala/reflect/Manifest;Ljava/lang/Class;Lscala/collection/Seq;)Lscala/reflect/Manifest;
  Code:
   Stack=5, Locals=4, Args_size=4
	new	class scala/reflect/Manifest$ClassTypeManifest
	dup
	new	class scala/Some
	dup
	aload_1
	invokespecial	Method scala/Some."<init>":(Ljava/lang/Object;)V
	aload_2
	aload_3
	invokeinterface	InterfaceMethod scala/collection/TraversableLike.toList:()Lscala/collection/immutable/List;
	invokespecial	Method scala/reflect/Manifest$ClassTypeManifest."<init>":(Lscala/Option;Ljava/lang/Class;Lscala/collection/immutable/List;)V
	areturn
  Labels:
  LocalVariableTable: 
   Start  Length  Slot  Name   Signature
   0      23      0    this       Lscala/reflect/Manifest$;
   0      23      1    prefix       Lscala/reflect/Manifest;
   0      23      2    clazz       Ljava/lang/Class;
   0      23      3    args       Lscala/collection/Seq;

  Signature: length = 0x2
   00 FFFFFF8C 

public scala.reflect.Manifest arrayType(scala.reflect.Manifest);
  Signature: (Lscala/reflect/Manifest;)Lscala/reflect/Manifest;
  Code:
   Stack=1, Locals=2, Args_size=2
	aload_1
	invokeinterface	InterfaceMethod scala/reflect/Manifest.arrayManifest:()Lscala/reflect/Manifest;
	areturn
  Labels:
  LocalVariableTable: 
   Start  Length  Slot  Name   Signature
   0      7      0    this       Lscala/reflect/Manifest$;
   0      7      1    arg       Lscala/reflect/Manifest;

  Signature: length = 0x2
   00 FFFFFF95 

public scala.reflect.Manifest abstractType(scala.reflect.Manifest, java.lang.String, java.lang.Class, scala.collection.Seq);
  Signature: (Lscala/reflect/Manifest;Ljava/lang/String;Ljava/lang/Class;Lscala/collection/Seq;)Lscala/reflect/Manifest;
  Code:
   Stack=6, Locals=5, Args_size=5
	new	class scala/reflect/Manifest$$anon$16
	dup
	aload_1
	aload_2
	aload_3
	aload	4
	invokespecial	Method scala/reflect/Manifest$$anon$16."<init>":(Lscala/reflect/Manifest;Ljava/lang/String;Ljava/lang/Class;Lscala/collection/Seq;)V
	areturn
  Labels:
  LocalVariableTable: 
   Start  Length  Slot  Name   Signature
   0      13      0    this       Lscala/reflect/Manifest$;
   0      13      1    prefix$1       Lscala/reflect/Manifest;
   0      13      2    name$1       Ljava/lang/String;
   0      13      3    clazz$1       Ljava/lang/Class;
   0      13      4    args$1       Lscala/collection/Seq;

  Signature: length = 0x2
   00 FFFFFFA2 

public scala.reflect.Manifest abstractType(scala.reflect.Manifest, java.lang.String, scala.reflect.ClassManifest, scala.collection.Seq);
  Signature: (Lscala/reflect/Manifest;Ljava/lang/String;Lscala/reflect/ClassManifest;Lscala/collection/Seq;)Lscala/reflect/Manifest;
  Code:
   Stack=6, Locals=5, Args_size=5
	new	class scala/reflect/Manifest$$anon$17
	dup
	aload_1
	aload_2
	aload_3
	aload	4
	invokespecial	Method scala/reflect/Manifest$$anon$17."<init>":(Lscala/reflect/Manifest;Ljava/lang/String;Lscala/reflect/ClassManifest;Lscala/collection/Seq;)V
	areturn
  Labels:
  LocalVariableTable: 
   Start  Length  Slot  Name   Signature
   0      13      0    this       Lscala/reflect/Manifest$;
   0      13      1    prefix$2       Lscala/reflect/Manifest;
   0      13      2    name$2       Ljava/lang/String;
   0      13      3    upperbound$1       Lscala/reflect/ClassManifest;
   0      13      4    args$2       Lscala/collection/Seq;

  Signature: length = 0x2
   00 FFFFFFAE 

public scala.reflect.Manifest intersectionType(scala.collection.Seq);
  Signature: (Lscala/collection/Seq;)Lscala/reflect/Manifest;
  Code:
   Stack=3, Locals=2, Args_size=2
	new	class scala/reflect/Manifest$$anon$18
	dup
	aload_1
	invokespecial	Method scala/reflect/Manifest$$anon$18."<init>":(Lscala/collection/Seq;)V
	areturn
  Labels:
  LocalVariableTable: 
   Start  Length  Slot  Name   Signature
   0      9      0    this       Lscala/reflect/Manifest$;
   0      9      1    parents$1       Lscala/collection/Seq;

  Signature: length = 0x2
   00 FFFFFFB7 

private scala.reflect.Manifest$();
  Signature: ()V
  Code:
   Stack=3, Locals=1, Args_size=1
	aload_0
	invokespecial	Method java/lang/Object."<init>":()V
	aload_0
	putstatic	Field MODULE$:Lscala/reflect/Manifest$;
	aload_0
	new	class scala/reflect/Manifest$$anon$1
	dup
	invokespecial	Method scala/reflect/Manifest$$anon$1."<init>":()V
	putfield	Field Byte:Lscala/reflect/AnyValManifest;
	aload_0
	new	class scala/reflect/Manifest$$anon$2
	dup
	invokespecial	Method scala/reflect/Manifest$$anon$2."<init>":()V
	putfield	Field Short:Lscala/reflect/AnyValManifest;
	aload_0
	new	class scala/reflect/Manifest$$anon$3
	dup
	invokespecial	Method scala/reflect/Manifest$$anon$3."<init>":()V
	putfield	Field Char:Lscala/reflect/AnyValManifest;
	aload_0
	new	class scala/reflect/Manifest$$anon$4
	dup
	invokespecial	Method scala/reflect/Manifest$$anon$4."<init>":()V
	putfield	Field Int:Lscala/reflect/AnyValManifest;
	aload_0
	new	class scala/reflect/Manifest$$anon$5
	dup
	invokespecial	Method scala/reflect/Manifest$$anon$5."<init>":()V
	putfield	Field Long:Lscala/reflect/AnyValManifest;
	aload_0
	new	class scala/reflect/Manifest$$anon$6
	dup
	invokespecial	Method scala/reflect/Manifest$$anon$6."<init>":()V
	putfield	Field Float:Lscala/reflect/AnyValManifest;
	aload_0
	new	class scala/reflect/Manifest$$anon$7
	dup
	invokespecial	Method scala/reflect/Manifest$$anon$7."<init>":()V
	putfield	Field Double:Lscala/reflect/AnyValManifest;
	aload_0
	new	class scala/reflect/Manifest$$anon$8
	dup
	invokespecial	Method scala/reflect/Manifest$$anon$8."<init>":()V
	putfield	Field Boolean:Lscala/reflect/AnyValManifest;
	aload_0
	new	class scala/reflect/Manifest$$anon$9
	dup
	invokespecial	Method scala/reflect/Manifest$$anon$9."<init>":()V
	putfield	Field Unit:Lscala/reflect/AnyValManifest;
	aload_0
	new	class scala/reflect/Manifest$$anon$10
	dup
	invokespecial	Method scala/reflect/Manifest$$anon$10."<init>":()V
	putfield	Field Any:Lscala/reflect/Manifest;
	aload_0
	new	class scala/reflect/Manifest$$anon$11
	dup
	invokespecial	Method scala/reflect/Manifest$$anon$11."<init>":()V
	putfield	Field Object:Lscala/reflect/Manifest;
	aload_0
	new	class scala/reflect/Manifest$$anon$12
	dup
	invokespecial	Method scala/reflect/Manifest$$anon$12."<init>":()V
	putfield	Field AnyVal:Lscala/reflect/Manifest;
	aload_0
	new	class scala/reflect/Manifest$$anon$13
	dup
	invokespecial	Method scala/reflect/Manifest$$anon$13."<init>":()V
	putfield	Field Null:Lscala/reflect/Manifest;
	aload_0
	new	class scala/reflect/Manifest$$anon$14
	dup
	invokespecial	Method scala/reflect/Manifest$$anon$14."<init>":()V
	putfield	Field Nothing:Lscala/reflect/Manifest;
	return
  Labels:

}

