Compiled from "Manifest.scala"
public final class scala.reflect.Manifest$$anon$9 extends java.lang.Object implements scala.reflect.AnyValManifest
  SourceFile: "Manifest.scala"
  Signature: length = 0x2
   00 FFFFFF8E 
  Scala: length = 0x
   
  InnerClass: 
   public final #145= #30 of #42; //$anon$9=class scala/reflect/Manifest$$anon$9 of class scala/reflect/Manifest
   public final #148= #68 of #147; //ofUnit=class scala/collection/mutable/WrappedArray$ofUnit of class scala/collection/mutable/WrappedArray
   public #148= #61 of #150; //ofUnit=class scala/collection/mutable/ArrayBuilder$ofUnit of class scala/collection/mutable/ArrayBuilder
  minor version: 0
  major version: 49
  Constant pool:
const #1 = Asciz	SourceFile;
const #2 = Asciz	Manifest.scala;
const #3 = Asciz	<init>;
const #4 = Asciz	()V;
const #5 = Asciz	Code;
const #6 = Asciz	LineNumberTable;
const #7 = Asciz	java/lang/Object;
const #8 = class	#7;	//  java/lang/Object
const #9 = NameAndType	#3:#4;//  "<init>":()V
const #10 = Method	#8.#9;	//  java/lang/Object."<init>":()V
const #11 = Asciz	scala/reflect/ClassManifest$class;
const #12 = class	#11;	//  scala/reflect/ClassManifest$class
const #13 = Asciz	$init$;
const #14 = Asciz	(Lscala/reflect/ClassManifest;)V;
const #15 = NameAndType	#13:#14;//  $init$:(Lscala/reflect/ClassManifest;)V
const #16 = Method	#12.#15;	//  scala/reflect/ClassManifest$class.$init$:(Lscala/reflect/ClassManifest;)V
const #17 = Asciz	scala/reflect/Manifest$class;
const #18 = class	#17;	//  scala/reflect/Manifest$class
const #19 = Asciz	(Lscala/reflect/Manifest;)V;
const #20 = NameAndType	#13:#19;//  $init$:(Lscala/reflect/Manifest;)V
const #21 = Method	#18.#20;	//  scala/reflect/Manifest$class.$init$:(Lscala/reflect/Manifest;)V
const #22 = Asciz	scala/reflect/AnyValManifest$class;
const #23 = class	#22;	//  scala/reflect/AnyValManifest$class
const #24 = Asciz	(Lscala/reflect/AnyValManifest;)V;
const #25 = NameAndType	#13:#24;//  $init$:(Lscala/reflect/AnyValManifest;)V
const #26 = Method	#23.#25;	//  scala/reflect/AnyValManifest$class.$init$:(Lscala/reflect/AnyValManifest;)V
const #27 = Asciz	newArray;
const #28 = Asciz	(I)Ljava/lang/Object;;
const #29 = Asciz	scala/reflect/Manifest$$anon$9;
const #30 = class	#29;	//  scala/reflect/Manifest$$anon$9
const #31 = Asciz	(I)[Lscala/runtime/BoxedUnit;;
const #32 = NameAndType	#27:#31;//  newArray:(I)[Lscala/runtime/BoxedUnit;
const #33 = Method	#30.#32;	//  scala/reflect/Manifest$$anon$9.newArray:(I)[Lscala/runtime/BoxedUnit;
const #34 = Asciz	this;
const #35 = Asciz	Lscala/reflect/Manifest$$anon$9;;
const #36 = Asciz	len;
const #37 = Asciz	I;
const #38 = Asciz	LocalVariableTable;
const #39 = Asciz	arrayManifest;
const #40 = Asciz	()Lscala/reflect/ClassManifest;;
const #41 = Asciz	scala/reflect/Manifest;
const #42 = class	#41;	//  scala/reflect/Manifest
const #43 = Asciz	()Lscala/reflect/Manifest;;
const #44 = NameAndType	#39:#43;//  arrayManifest:()Lscala/reflect/Manifest;
const #45 = InterfaceMethod	#42.#44;	//  scala/reflect/Manifest.arrayManifest:()Lscala/reflect/Manifest;
const #46 = Asciz	readResolve;
const #47 = Asciz	()Ljava/lang/Object;;
const #48 = Asciz	scala/reflect/Manifest$;
const #49 = class	#48;	//  scala/reflect/Manifest$
const #50 = Asciz	MODULE$;
const #51 = Asciz	Lscala/reflect/Manifest$;;
const #52 = NameAndType	#50:#51;//  MODULE$:Lscala/reflect/Manifest$;
const #53 = Field	#49.#52;	//  scala/reflect/Manifest$.MODULE$:Lscala/reflect/Manifest$;
const #54 = Asciz	Unit;
const #55 = Asciz	()Lscala/reflect/AnyValManifest;;
const #56 = NameAndType	#54:#55;//  Unit:()Lscala/reflect/AnyValManifest;
const #57 = Method	#49.#56;	//  scala/reflect/Manifest$.Unit:()Lscala/reflect/AnyValManifest;
const #58 = Asciz	newArrayBuilder;
const #59 = Asciz	()Lscala/collection/mutable/ArrayBuilder;;
const #60 = Asciz	scala/collection/mutable/ArrayBuilder$ofUnit;
const #61 = class	#60;	//  scala/collection/mutable/ArrayBuilder$ofUnit
const #62 = Method	#61.#9;	//  scala/collection/mutable/ArrayBuilder$ofUnit."<init>":()V
const #63 = Asciz	()Lscala/collection/mutable/ArrayBuilder<Ljava/lang/Object;>;;
const #64 = Asciz	Signature;
const #65 = Asciz	newWrappedArray;
const #66 = Asciz	(I)Lscala/collection/mutable/WrappedArray;;
const #67 = Asciz	scala/collection/mutable/WrappedArray$ofUnit;
const #68 = class	#67;	//  scala/collection/mutable/WrappedArray$ofUnit
const #69 = Asciz	scala/runtime/BoxedUnit;
const #70 = class	#69;	//  scala/runtime/BoxedUnit
const #71 = Asciz	([Lscala/runtime/BoxedUnit;)V;
const #72 = NameAndType	#3:#71;//  "<init>":([Lscala/runtime/BoxedUnit;)V
const #73 = Method	#68.#72;	//  scala/collection/mutable/WrappedArray$ofUnit."<init>":([Lscala/runtime/BoxedUnit;)V
const #74 = Asciz	(I)Lscala/collection/mutable/WrappedArray<Ljava/lang/Object;>;;
const #75 = Asciz	toString;
const #76 = Asciz	()Ljava/lang/String;;
const #77 = String	#54;	//  Unit
const #78 = Asciz	erasure;
const #79 = Asciz	()Ljava/lang/Class;;
const #80 = Asciz	java/lang/Void;
const #81 = class	#80;	//  java/lang/Void
const #82 = Asciz	TYPE;
const #83 = Asciz	Ljava/lang/Class;;
const #84 = NameAndType	#82:#83;//  TYPE:Ljava/lang/Class;
const #85 = Field	#81.#84;	//  java/lang/Void.TYPE:Ljava/lang/Class;
const #86 = Asciz	()Ljava/lang/Class<Ljava/lang/Void;>;;
const #87 = Asciz	argString;
const #88 = Asciz	(Lscala/reflect/ClassManifest;)Ljava/lang/String;;
const #89 = NameAndType	#87:#88;//  argString:(Lscala/reflect/ClassManifest;)Ljava/lang/String;
const #90 = Method	#12.#89;	//  scala/reflect/ClassManifest$class.argString:(Lscala/reflect/ClassManifest;)Ljava/lang/String;
const #91 = Asciz	newArray5;
const #92 = Asciz	(I)[[[[Ljava/lang/Object;;
const #93 = Asciz	(Lscala/reflect/ClassManifest;I)[[[[Ljava/lang/Object;;
const #94 = NameAndType	#91:#93;//  newArray5:(Lscala/reflect/ClassManifest;I)[[[[Ljava/lang/Object;
const #95 = Method	#12.#94;	//  scala/reflect/ClassManifest$class.newArray5:(Lscala/reflect/ClassManifest;I)[[[[Ljava/lang/Object;
const #96 = Asciz	newArray4;
const #97 = Asciz	(I)[[[Ljava/lang/Object;;
const #98 = Asciz	(Lscala/reflect/ClassManifest;I)[[[Ljava/lang/Object;;
const #99 = NameAndType	#96:#98;//  newArray4:(Lscala/reflect/ClassManifest;I)[[[Ljava/lang/Object;
const #100 = Method	#12.#99;	//  scala/reflect/ClassManifest$class.newArray4:(Lscala/reflect/ClassManifest;I)[[[Ljava/lang/Object;
const #101 = Asciz	newArray3;
const #102 = Asciz	(I)[[Ljava/lang/Object;;
const #103 = Asciz	(Lscala/reflect/ClassManifest;I)[[Ljava/lang/Object;;
const #104 = NameAndType	#101:#103;//  newArray3:(Lscala/reflect/ClassManifest;I)[[Ljava/lang/Object;
const #105 = Method	#12.#104;	//  scala/reflect/ClassManifest$class.newArray3:(Lscala/reflect/ClassManifest;I)[[Ljava/lang/Object;
const #106 = Asciz	newArray2;
const #107 = Asciz	(I)[Ljava/lang/Object;;
const #108 = Asciz	(Lscala/reflect/ClassManifest;I)[Ljava/lang/Object;;
const #109 = NameAndType	#106:#108;//  newArray2:(Lscala/reflect/ClassManifest;I)[Ljava/lang/Object;
const #110 = Method	#12.#109;	//  scala/reflect/ClassManifest$class.newArray2:(Lscala/reflect/ClassManifest;I)[Ljava/lang/Object;
const #111 = Asciz	arrayClass;
const #112 = Asciz	(Ljava/lang/Class;)Ljava/lang/Class;;
const #113 = Asciz	(Lscala/reflect/ClassManifest;Ljava/lang/Class;)Ljava/lang/Class;;
const #114 = NameAndType	#111:#113;//  arrayClass:(Lscala/reflect/ClassManifest;Ljava/lang/Class;)Ljava/lang/Class;
const #115 = Method	#12.#114;	//  scala/reflect/ClassManifest$class.arrayClass:(Lscala/reflect/ClassManifest;Ljava/lang/Class;)Ljava/lang/Class;
const #116 = Asciz	tp;
const #117 = Asciz	$greater$colon$greater;
const #118 = Asciz	(Lscala/reflect/ClassManifest;)Z;
const #119 = Asciz	(Lscala/reflect/ClassManifest;Lscala/reflect/ClassManifest;)Z;
const #120 = NameAndType	#117:#119;//  $greater$colon$greater:(Lscala/reflect/ClassManifest;Lscala/reflect/ClassManifest;)Z
const #121 = Method	#12.#120;	//  scala/reflect/ClassManifest$class.$greater$colon$greater:(Lscala/reflect/ClassManifest;Lscala/reflect/ClassManifest;)Z
const #122 = Asciz	that;
const #123 = Asciz	Lscala/reflect/ClassManifest;;
const #124 = Asciz	(Lscala/reflect/Manifest;)Lscala/reflect/Manifest;;
const #125 = NameAndType	#39:#124;//  arrayManifest:(Lscala/reflect/Manifest;)Lscala/reflect/Manifest;
const #126 = Method	#18.#125;	//  scala/reflect/Manifest$class.arrayManifest:(Lscala/reflect/Manifest;)Lscala/reflect/Manifest;
const #127 = Asciz	typeArguments;
const #128 = Asciz	()Lscala/collection/immutable/List;;
const #129 = Asciz	(Lscala/reflect/Manifest;)Lscala/collection/immutable/List;;
const #130 = NameAndType	#127:#129;//  typeArguments:(Lscala/reflect/Manifest;)Lscala/collection/immutable/List;
const #131 = Method	#18.#130;	//  scala/reflect/Manifest$class.typeArguments:(Lscala/reflect/Manifest;)Lscala/collection/immutable/List;
const #132 = Asciz	equals;
const #133 = Asciz	(Ljava/lang/Object;)Z;
const #134 = Asciz	(Lscala/reflect/AnyValManifest;Ljava/lang/Object;)Z;
const #135 = NameAndType	#132:#134;//  equals:(Lscala/reflect/AnyValManifest;Ljava/lang/Object;)Z
const #136 = Method	#23.#135;	//  scala/reflect/AnyValManifest$class.equals:(Lscala/reflect/AnyValManifest;Ljava/lang/Object;)Z
const #137 = Asciz	Ljava/lang/Object;;
const #138 = Asciz	$less$colon$less;
const #139 = Asciz	(Lscala/reflect/AnyValManifest;Lscala/reflect/ClassManifest;)Z;
const #140 = NameAndType	#138:#139;//  $less$colon$less:(Lscala/reflect/AnyValManifest;Lscala/reflect/ClassManifest;)Z
const #141 = Method	#23.#140;	//  scala/reflect/AnyValManifest$class.$less$colon$less:(Lscala/reflect/AnyValManifest;Lscala/reflect/ClassManifest;)Z
const #142 = Asciz	Ljava/lang/Object;Lscala/reflect/AnyValManifest<Ljava/lang/Object;>;;
const #143 = Asciz	Scala;
const #144 = Asciz	InnerClasses;
const #145 = Asciz	$anon$9;
const #146 = Asciz	scala/collection/mutable/WrappedArray;
const #147 = class	#146;	//  scala/collection/mutable/WrappedArray
const #148 = Asciz	ofUnit;
const #149 = Asciz	scala/collection/mutable/ArrayBuilder;
const #150 = class	#149;	//  scala/collection/mutable/ArrayBuilder
const #151 = Asciz	scala/reflect/AnyValManifest;
const #152 = class	#151;	//  scala/reflect/AnyValManifest

{
public scala.reflect.Manifest$$anon$9();
  Code:
   Stack=1, Locals=1, Args_size=1
   0:	aload_0
   1:	invokespecial	#10; //Method java/lang/Object."<init>":()V
   4:	aload_0
   5:	invokestatic	#16; //Method scala/reflect/ClassManifest$class.$init$:(Lscala/reflect/ClassManifest;)V
   8:	aload_0
   9:	invokestatic	#21; //Method scala/reflect/Manifest$class.$init$:(Lscala/reflect/Manifest;)V
   12:	aload_0
   13:	invokestatic	#26; //Method scala/reflect/AnyValManifest$class.$init$:(Lscala/reflect/AnyValManifest;)V
   16:	return
  LineNumberTable: 
   line 127: 0


public java.lang.Object newArray(int);
  Code:
   Stack=2, Locals=2, Args_size=2
   0:	aload_0
   1:	iload_1
   2:	invokevirtual	#33; //Method newArray:(I)[Lscala/runtime/BoxedUnit;
   5:	areturn
  LineNumberTable: 
   line 127: 0

  LocalVariableTable: 
   Start  Length  Slot  Name   Signature
   0      6      0    this       Lscala/reflect/Manifest$$anon$9;
   0      6      1    len       I


public scala.reflect.ClassManifest arrayManifest();
  Code:
   Stack=1, Locals=1, Args_size=1
   0:	aload_0
   1:	invokeinterface	#45,  1; //InterfaceMethod scala/reflect/Manifest.arrayManifest:()Lscala/reflect/Manifest;
   6:	areturn
  LineNumberTable: 
   line 127: 0


public scala.collection.mutable.ArrayBuilder newArrayBuilder();
  Code:
   Stack=2, Locals=1, Args_size=1
   0:	new	#61; //class scala/collection/mutable/ArrayBuilder$ofUnit
   3:	dup
   4:	invokespecial	#62; //Method scala/collection/mutable/ArrayBuilder$ofUnit."<init>":()V
   7:	areturn
  LineNumberTable: 
   line 132: 0

  Signature: length = 0x2
   00 3F 

public scala.collection.mutable.WrappedArray newWrappedArray(int);
  Code:
   Stack=3, Locals=2, Args_size=2
   0:	new	#68; //class scala/collection/mutable/WrappedArray$ofUnit
   3:	dup
   4:	iload_1
   5:	anewarray	#70; //class scala/runtime/BoxedUnit
   8:	invokespecial	#73; //Method scala/collection/mutable/WrappedArray$ofUnit."<init>":([Lscala/runtime/BoxedUnit;)V
   11:	areturn
  LineNumberTable: 
   line 131: 0

  LocalVariableTable: 
   Start  Length  Slot  Name   Signature
   0      12      0    this       Lscala/reflect/Manifest$$anon$9;
   0      12      1    len       I

  Signature: length = 0x2
   00 4A 

public scala.runtime.BoxedUnit[] newArray(int);
  Code:
   Stack=1, Locals=2, Args_size=2
   0:	iload_1
   1:	anewarray	#70; //class scala/runtime/BoxedUnit
   4:	areturn
  LineNumberTable: 
   line 130: 0

  LocalVariableTable: 
   Start  Length  Slot  Name   Signature
   0      5      0    this       Lscala/reflect/Manifest$$anon$9;
   0      5      1    len       I


public java.lang.String toString();
  Code:
   Stack=1, Locals=1, Args_size=1
   0:	ldc	#77; //String Unit
   2:	areturn
  LineNumberTable: 
   line 129: 0


public java.lang.Class erasure();
  Code:
   Stack=1, Locals=1, Args_size=1
   0:	getstatic	#85; //Field java/lang/Void.TYPE:Ljava/lang/Class;
   3:	areturn
  LineNumberTable: 
   line 128: 0

  Signature: length = 0x2
   00 56 

public java.lang.String argString();
  Code:
   Stack=1, Locals=1, Args_size=1
   0:	aload_0
   1:	invokestatic	#90; //Method scala/reflect/ClassManifest$class.argString:(Lscala/reflect/ClassManifest;)Ljava/lang/String;
   4:	areturn
  LineNumberTable: 
   line 127: 0


public java.lang.Object[][][][] newArray5(int);
  Code:
   Stack=2, Locals=2, Args_size=2
   0:	aload_0
   1:	iload_1
   2:	invokestatic	#95; //Method scala/reflect/ClassManifest$class.newArray5:(Lscala/reflect/ClassManifest;I)[[[[Ljava/lang/Object;
   5:	areturn
  LineNumberTable: 
   line 127: 0

  LocalVariableTable: 
   Start  Length  Slot  Name   Signature
   0      6      0    this       Lscala/reflect/Manifest$$anon$9;
   0      6      1    len       I


public java.lang.Object[][][] newArray4(int);
  Code:
   Stack=2, Locals=2, Args_size=2
   0:	aload_0
   1:	iload_1
   2:	invokestatic	#100; //Method scala/reflect/ClassManifest$class.newArray4:(Lscala/reflect/ClassManifest;I)[[[Ljava/lang/Object;
   5:	areturn
  LineNumberTable: 
   line 127: 0

  LocalVariableTable: 
   Start  Length  Slot  Name   Signature
   0      6      0    this       Lscala/reflect/Manifest$$anon$9;
   0      6      1    len       I


public java.lang.Object[][] newArray3(int);
  Code:
   Stack=2, Locals=2, Args_size=2
   0:	aload_0
   1:	iload_1
   2:	invokestatic	#105; //Method scala/reflect/ClassManifest$class.newArray3:(Lscala/reflect/ClassManifest;I)[[Ljava/lang/Object;
   5:	areturn
  LineNumberTable: 
   line 127: 0

  LocalVariableTable: 
   Start  Length  Slot  Name   Signature
   0      6      0    this       Lscala/reflect/Manifest$$anon$9;
   0      6      1    len       I


public java.lang.Object[] newArray2(int);
  Code:
   Stack=2, Locals=2, Args_size=2
   0:	aload_0
   1:	iload_1
   2:	invokestatic	#110; //Method scala/reflect/ClassManifest$class.newArray2:(Lscala/reflect/ClassManifest;I)[Ljava/lang/Object;
   5:	areturn
  LineNumberTable: 
   line 127: 0

  LocalVariableTable: 
   Start  Length  Slot  Name   Signature
   0      6      0    this       Lscala/reflect/Manifest$$anon$9;
   0      6      1    len       I


public java.lang.Class arrayClass(java.lang.Class);
  Code:
   Stack=2, Locals=2, Args_size=2
   0:	aload_0
   1:	aload_1
   2:	invokestatic	#115; //Method scala/reflect/ClassManifest$class.arrayClass:(Lscala/reflect/ClassManifest;Ljava/lang/Class;)Ljava/lang/Class;
   5:	areturn
  LineNumberTable: 
   line 127: 0

  LocalVariableTable: 
   Start  Length  Slot  Name   Signature
   0      6      0    this       Lscala/reflect/Manifest$$anon$9;
   0      6      1    tp       Ljava/lang/Class;


public boolean $greater$colon$greater(scala.reflect.ClassManifest);
  Code:
   Stack=2, Locals=2, Args_size=2
   0:	aload_0
   1:	aload_1
   2:	invokestatic	#121; //Method scala/reflect/ClassManifest$class.$greater$colon$greater:(Lscala/reflect/ClassManifest;Lscala/reflect/ClassManifest;)Z
   5:	ireturn
  LineNumberTable: 
   line 127: 0

  LocalVariableTable: 
   Start  Length  Slot  Name   Signature
   0      6      0    this       Lscala/reflect/Manifest$$anon$9;
   0      6      1    that       Lscala/reflect/ClassManifest;


public scala.reflect.Manifest arrayManifest();
  Code:
   Stack=1, Locals=1, Args_size=1
   0:	aload_0
   1:	invokestatic	#126; //Method scala/reflect/Manifest$class.arrayManifest:(Lscala/reflect/Manifest;)Lscala/reflect/Manifest;
   4:	areturn
  LineNumberTable: 
   line 127: 0


public scala.collection.immutable.List typeArguments();
  Code:
   Stack=1, Locals=1, Args_size=1
   0:	aload_0
   1:	invokestatic	#131; //Method scala/reflect/Manifest$class.typeArguments:(Lscala/reflect/Manifest;)Lscala/collection/immutable/List;
   4:	areturn
  LineNumberTable: 
   line 127: 0


public boolean equals(java.lang.Object);
  Code:
   Stack=2, Locals=2, Args_size=2
   0:	aload_0
   1:	aload_1
   2:	invokestatic	#136; //Method scala/reflect/AnyValManifest$class.equals:(Lscala/reflect/AnyValManifest;Ljava/lang/Object;)Z
   5:	ireturn
  LineNumberTable: 
   line 127: 0

  LocalVariableTable: 
   Start  Length  Slot  Name   Signature
   0      6      0    this       Lscala/reflect/Manifest$$anon$9;
   0      6      1    that       Ljava/lang/Object;


public boolean $less$colon$less(scala.reflect.ClassManifest);
  Code:
   Stack=2, Locals=2, Args_size=2
   0:	aload_0
   1:	aload_1
   2:	invokestatic	#141; //Method scala/reflect/AnyValManifest$class.$less$colon$less:(Lscala/reflect/AnyValManifest;Lscala/reflect/ClassManifest;)Z
   5:	ireturn
  LineNumberTable: 
   line 127: 0

  LocalVariableTable: 
   Start  Length  Slot  Name   Signature
   0      6      0    this       Lscala/reflect/Manifest$$anon$9;
   0      6      1    that       Lscala/reflect/ClassManifest;


}

