Compiled from "Manifest.scala"
public final class scala.reflect.Manifest$$anon$8 extends java.lang.Object implements scala.reflect.AnyValManifest
  SourceFile: "Manifest.scala"
  Signature: length = 0x2
   00 FFFFFF8C 
  Scala: length = 0x
   
  InnerClass: 
   public final $anon$8=class scala/reflect/Manifest$$anon$8 of class scala/reflect/Manifest
   public final ofBoolean=class scala/collection/mutable/WrappedArray$ofBoolean of class scala/collection/mutable/WrappedArray
   public ofBoolean=class scala/collection/mutable/ArrayBuilder$ofBoolean of class scala/collection/mutable/ArrayBuilder
  minor version: 0
  major version: 49
  Constant pool:
Asciz	SourceFile;
Asciz	Manifest.scala;
Asciz	<init>;
Asciz	()V;
Asciz	Code;
Asciz	LineNumberTable;
Asciz	java/lang/Object;
class	java/lang/Object
NameAndType	"<init>":()V
Method	java/lang/Object."<init>":()V
Asciz	scala/reflect/ClassManifest$class;
class	scala/reflect/ClassManifest$class
Asciz	$init$;
Asciz	(Lscala/reflect/ClassManifest;)V;
NameAndType	$init$:(Lscala/reflect/ClassManifest;)V
Method	scala/reflect/ClassManifest$class.$init$:(Lscala/reflect/ClassManifest;)V
Asciz	scala/reflect/Manifest$class;
class	scala/reflect/Manifest$class
Asciz	(Lscala/reflect/Manifest;)V;
NameAndType	$init$:(Lscala/reflect/Manifest;)V
Method	scala/reflect/Manifest$class.$init$:(Lscala/reflect/Manifest;)V
Asciz	scala/reflect/AnyValManifest$class;
class	scala/reflect/AnyValManifest$class
Asciz	(Lscala/reflect/AnyValManifest;)V;
NameAndType	$init$:(Lscala/reflect/AnyValManifest;)V
Method	scala/reflect/AnyValManifest$class.$init$:(Lscala/reflect/AnyValManifest;)V
Asciz	newArray;
Asciz	(I)Ljava/lang/Object;;
Asciz	scala/reflect/Manifest$$anon$8;
class	scala/reflect/Manifest$$anon$8
Asciz	(I)[Z;
NameAndType	newArray:(I)[Z
Method	scala/reflect/Manifest$$anon$8.newArray:(I)[Z
Asciz	this;
Asciz	Lscala/reflect/Manifest$$anon$8;;
Asciz	len;
Asciz	I;
Asciz	LocalVariableTable;
Asciz	arrayManifest;
Asciz	()Lscala/reflect/ClassManifest;;
Asciz	scala/reflect/Manifest;
class	scala/reflect/Manifest
Asciz	()Lscala/reflect/Manifest;;
NameAndType	arrayManifest:()Lscala/reflect/Manifest;
InterfaceMethod	scala/reflect/Manifest.arrayManifest:()Lscala/reflect/Manifest;
Asciz	readResolve;
Asciz	()Ljava/lang/Object;;
Asciz	scala/reflect/Manifest$;
class	scala/reflect/Manifest$
Asciz	MODULE$;
Asciz	Lscala/reflect/Manifest$;;
NameAndType	MODULE$:Lscala/reflect/Manifest$;
Field	scala/reflect/Manifest$.MODULE$:Lscala/reflect/Manifest$;
Asciz	Boolean;
Asciz	()Lscala/reflect/AnyValManifest;;
NameAndType	Boolean:()Lscala/reflect/AnyValManifest;
Method	scala/reflect/Manifest$.Boolean:()Lscala/reflect/AnyValManifest;
Asciz	newArrayBuilder;
Asciz	()Lscala/collection/mutable/ArrayBuilder;;
Asciz	scala/collection/mutable/ArrayBuilder$ofBoolean;
class	scala/collection/mutable/ArrayBuilder$ofBoolean
Method	scala/collection/mutable/ArrayBuilder$ofBoolean."<init>":()V
Asciz	()Lscala/collection/mutable/ArrayBuilder<Ljava/lang/Boolean;>;;
Asciz	Signature;
Asciz	newWrappedArray;
Asciz	(I)Lscala/collection/mutable/WrappedArray;;
Asciz	scala/collection/mutable/WrappedArray$ofBoolean;
class	scala/collection/mutable/WrappedArray$ofBoolean
Asciz	([Z)V;
NameAndType	"<init>":([Z)V
Method	scala/collection/mutable/WrappedArray$ofBoolean."<init>":([Z)V
Asciz	(I)Lscala/collection/mutable/WrappedArray<Ljava/lang/Boolean;>;;
Asciz	toString;
Asciz	()Ljava/lang/String;;
String	Boolean
Asciz	erasure;
Asciz	()Ljava/lang/Class;;
Asciz	java/lang/Boolean;
class	java/lang/Boolean
Asciz	TYPE;
Asciz	Ljava/lang/Class;;
NameAndType	TYPE:Ljava/lang/Class;
Field	java/lang/Boolean.TYPE:Ljava/lang/Class;
Asciz	()Ljava/lang/Class<Ljava/lang/Boolean;>;;
Asciz	argString;
Asciz	(Lscala/reflect/ClassManifest;)Ljava/lang/String;;
NameAndType	argString:(Lscala/reflect/ClassManifest;)Ljava/lang/String;
Method	scala/reflect/ClassManifest$class.argString:(Lscala/reflect/ClassManifest;)Ljava/lang/String;
Asciz	newArray5;
Asciz	(I)[[[[Ljava/lang/Object;;
Asciz	(Lscala/reflect/ClassManifest;I)[[[[Ljava/lang/Object;;
NameAndType	newArray5:(Lscala/reflect/ClassManifest;I)[[[[Ljava/lang/Object;
Method	scala/reflect/ClassManifest$class.newArray5:(Lscala/reflect/ClassManifest;I)[[[[Ljava/lang/Object;
Asciz	newArray4;
Asciz	(I)[[[Ljava/lang/Object;;
Asciz	(Lscala/reflect/ClassManifest;I)[[[Ljava/lang/Object;;
NameAndType	newArray4:(Lscala/reflect/ClassManifest;I)[[[Ljava/lang/Object;
Method	scala/reflect/ClassManifest$class.newArray4:(Lscala/reflect/ClassManifest;I)[[[Ljava/lang/Object;
Asciz	newArray3;
Asciz	(I)[[Ljava/lang/Object;;
Asciz	(Lscala/reflect/ClassManifest;I)[[Ljava/lang/Object;;
NameAndType	newArray3:(Lscala/reflect/ClassManifest;I)[[Ljava/lang/Object;
Method	scala/reflect/ClassManifest$class.newArray3:(Lscala/reflect/ClassManifest;I)[[Ljava/lang/Object;
Asciz	newArray2;
Asciz	(I)[Ljava/lang/Object;;
Asciz	(Lscala/reflect/ClassManifest;I)[Ljava/lang/Object;;
NameAndType	newArray2:(Lscala/reflect/ClassManifest;I)[Ljava/lang/Object;
Method	scala/reflect/ClassManifest$class.newArray2:(Lscala/reflect/ClassManifest;I)[Ljava/lang/Object;
Asciz	arrayClass;
Asciz	(Ljava/lang/Class;)Ljava/lang/Class;;
Asciz	(Lscala/reflect/ClassManifest;Ljava/lang/Class;)Ljava/lang/Class;;
NameAndType	arrayClass:(Lscala/reflect/ClassManifest;Ljava/lang/Class;)Ljava/lang/Class;
Method	scala/reflect/ClassManifest$class.arrayClass:(Lscala/reflect/ClassManifest;Ljava/lang/Class;)Ljava/lang/Class;
Asciz	tp;
Asciz	$greater$colon$greater;
Asciz	(Lscala/reflect/ClassManifest;)Z;
Asciz	(Lscala/reflect/ClassManifest;Lscala/reflect/ClassManifest;)Z;
NameAndType	$greater$colon$greater:(Lscala/reflect/ClassManifest;Lscala/reflect/ClassManifest;)Z
Method	scala/reflect/ClassManifest$class.$greater$colon$greater:(Lscala/reflect/ClassManifest;Lscala/reflect/ClassManifest;)Z
Asciz	that;
Asciz	Lscala/reflect/ClassManifest;;
Asciz	(Lscala/reflect/Manifest;)Lscala/reflect/Manifest;;
NameAndType	arrayManifest:(Lscala/reflect/Manifest;)Lscala/reflect/Manifest;
Method	scala/reflect/Manifest$class.arrayManifest:(Lscala/reflect/Manifest;)Lscala/reflect/Manifest;
Asciz	typeArguments;
Asciz	()Lscala/collection/immutable/List;;
Asciz	(Lscala/reflect/Manifest;)Lscala/collection/immutable/List;;
NameAndType	typeArguments:(Lscala/reflect/Manifest;)Lscala/collection/immutable/List;
Method	scala/reflect/Manifest$class.typeArguments:(Lscala/reflect/Manifest;)Lscala/collection/immutable/List;
Asciz	equals;
Asciz	(Ljava/lang/Object;)Z;
Asciz	(Lscala/reflect/AnyValManifest;Ljava/lang/Object;)Z;
NameAndType	equals:(Lscala/reflect/AnyValManifest;Ljava/lang/Object;)Z
Method	scala/reflect/AnyValManifest$class.equals:(Lscala/reflect/AnyValManifest;Ljava/lang/Object;)Z
Asciz	Ljava/lang/Object;;
Asciz	$less$colon$less;
Asciz	(Lscala/reflect/AnyValManifest;Lscala/reflect/ClassManifest;)Z;
NameAndType	$less$colon$less:(Lscala/reflect/AnyValManifest;Lscala/reflect/ClassManifest;)Z
Method	scala/reflect/AnyValManifest$class.$less$colon$less:(Lscala/reflect/AnyValManifest;Lscala/reflect/ClassManifest;)Z
Asciz	Ljava/lang/Object;Lscala/reflect/AnyValManifest<Ljava/lang/Boolean;>;;
Asciz	Scala;
Asciz	InnerClasses;
Asciz	$anon$8;
Asciz	scala/collection/mutable/WrappedArray;
class	scala/collection/mutable/WrappedArray
Asciz	ofBoolean;
Asciz	scala/collection/mutable/ArrayBuilder;
class	scala/collection/mutable/ArrayBuilder
Asciz	scala/reflect/AnyValManifest;
class	scala/reflect/AnyValManifest

{
public scala.reflect.Manifest$$anon$8();
  Signature: ()V
  Code:
   Stack=1, Locals=1, Args_size=1
	aload_0
	invokespecial	Method java/lang/Object."<init>":()V
	aload_0
	invokestatic	Method scala/reflect/ClassManifest$class.$init$:(Lscala/reflect/ClassManifest;)V
	aload_0
	invokestatic	Method scala/reflect/Manifest$class.$init$:(Lscala/reflect/Manifest;)V
	aload_0
	invokestatic	Method scala/reflect/AnyValManifest$class.$init$:(Lscala/reflect/AnyValManifest;)V
	return
  Labels:

public java.lang.Object newArray(int);
  Signature: (I)Ljava/lang/Object;
  Code:
   Stack=2, Locals=2, Args_size=2
	aload_0
	iload_1
	invokevirtual	Method newArray:(I)[Z
	areturn
  Labels:
  LocalVariableTable: 
   Start  Length  Slot  Name   Signature
   0      6      0    this       Lscala/reflect/Manifest$$anon$8;
   0      6      1    len       I


public scala.reflect.ClassManifest arrayManifest();
  Signature: ()Lscala/reflect/ClassManifest;
  Code:
   Stack=1, Locals=1, Args_size=1
	aload_0
	invokeinterface	InterfaceMethod scala/reflect/Manifest.arrayManifest:()Lscala/reflect/Manifest;
	areturn
  Labels:

private java.lang.Object readResolve();
  Signature: ()Ljava/lang/Object;
  Code:
   Stack=1, Locals=1, Args_size=1
	getstatic	Field scala/reflect/Manifest$.MODULE$:Lscala/reflect/Manifest$;
	invokevirtual	Method scala/reflect/Manifest$.Boolean:()Lscala/reflect/AnyValManifest;
	areturn
  Labels:

public scala.collection.mutable.ArrayBuilder newArrayBuilder();
  Signature: ()Lscala/collection/mutable/ArrayBuilder;
  Code:
   Stack=2, Locals=1, Args_size=1
	new	class scala/collection/mutable/ArrayBuilder$ofBoolean
	dup
	invokespecial	Method scala/collection/mutable/ArrayBuilder$ofBoolean."<init>":()V
	areturn
  Labels:
  Signature: length = 0x2
   00 3F 

public scala.collection.mutable.WrappedArray newWrappedArray(int);
  Signature: (I)Lscala/collection/mutable/WrappedArray;
  Code:
   Stack=3, Locals=2, Args_size=2
	new	class scala/collection/mutable/WrappedArray$ofBoolean
	dup
	iload_1
	newarray boolean
	invokespecial	Method scala/collection/mutable/WrappedArray$ofBoolean."<init>":([Z)V
	areturn
  Labels:
  LocalVariableTable: 
   Start  Length  Slot  Name   Signature
   0      11      0    this       Lscala/reflect/Manifest$$anon$8;
   0      11      1    len       I

  Signature: length = 0x2
   00 48 

public boolean[] newArray(int);
  Signature: (I)[Z
  Code:
   Stack=1, Locals=2, Args_size=2
	iload_1
	newarray boolean
	areturn
  Labels:
  LocalVariableTable: 
   Start  Length  Slot  Name   Signature
   0      4      0    this       Lscala/reflect/Manifest$$anon$8;
   0      4      1    len       I


public java.lang.String toString();
  Signature: ()Ljava/lang/String;
  Code:
   Stack=1, Locals=1, Args_size=1
	ldc	String Boolean
	areturn
  Labels:

public java.lang.Class erasure();
  Signature: ()Ljava/lang/Class;
  Code:
   Stack=1, Locals=1, Args_size=1
	getstatic	Field java/lang/Boolean.TYPE:Ljava/lang/Class;
	areturn
  Labels:
  Signature: length = 0x2
   00 54 

public java.lang.String argString();
  Signature: ()Ljava/lang/String;
  Code:
   Stack=1, Locals=1, Args_size=1
	aload_0
	invokestatic	Method scala/reflect/ClassManifest$class.argString:(Lscala/reflect/ClassManifest;)Ljava/lang/String;
	areturn
  Labels:

public java.lang.Object[][][][] newArray5(int);
  Signature: (I)[[[[Ljava/lang/Object;
  Code:
   Stack=2, Locals=2, Args_size=2
	aload_0
	iload_1
	invokestatic	Method scala/reflect/ClassManifest$class.newArray5:(Lscala/reflect/ClassManifest;I)[[[[Ljava/lang/Object;
	areturn
  Labels:
  LocalVariableTable: 
   Start  Length  Slot  Name   Signature
   0      6      0    this       Lscala/reflect/Manifest$$anon$8;
   0      6      1    len       I


public java.lang.Object[][][] newArray4(int);
  Signature: (I)[[[Ljava/lang/Object;
  Code:
   Stack=2, Locals=2, Args_size=2
	aload_0
	iload_1
	invokestatic	Method scala/reflect/ClassManifest$class.newArray4:(Lscala/reflect/ClassManifest;I)[[[Ljava/lang/Object;
	areturn
  Labels:
  LocalVariableTable: 
   Start  Length  Slot  Name   Signature
   0      6      0    this       Lscala/reflect/Manifest$$anon$8;
   0      6      1    len       I


public java.lang.Object[][] newArray3(int);
  Signature: (I)[[Ljava/lang/Object;
  Code:
   Stack=2, Locals=2, Args_size=2
	aload_0
	iload_1
	invokestatic	Method scala/reflect/ClassManifest$class.newArray3:(Lscala/reflect/ClassManifest;I)[[Ljava/lang/Object;
	areturn
  Labels:
  LocalVariableTable: 
   Start  Length  Slot  Name   Signature
   0      6      0    this       Lscala/reflect/Manifest$$anon$8;
   0      6      1    len       I


public java.lang.Object[] newArray2(int);
  Signature: (I)[Ljava/lang/Object;
  Code:
   Stack=2, Locals=2, Args_size=2
	aload_0
	iload_1
	invokestatic	Method scala/reflect/ClassManifest$class.newArray2:(Lscala/reflect/ClassManifest;I)[Ljava/lang/Object;
	areturn
  Labels:
  LocalVariableTable: 
   Start  Length  Slot  Name   Signature
   0      6      0    this       Lscala/reflect/Manifest$$anon$8;
   0      6      1    len       I


public java.lang.Class arrayClass(java.lang.Class);
  Signature: (Ljava/lang/Class;)Ljava/lang/Class;
  Code:
   Stack=2, Locals=2, Args_size=2
	aload_0
	aload_1
	invokestatic	Method scala/reflect/ClassManifest$class.arrayClass:(Lscala/reflect/ClassManifest;Ljava/lang/Class;)Ljava/lang/Class;
	areturn
  Labels:
  LocalVariableTable: 
   Start  Length  Slot  Name   Signature
   0      6      0    this       Lscala/reflect/Manifest$$anon$8;
   0      6      1    tp       Ljava/lang/Class;


public boolean $greater$colon$greater(scala.reflect.ClassManifest);
  Signature: (Lscala/reflect/ClassManifest;)Z
  Code:
   Stack=2, Locals=2, Args_size=2
	aload_0
	aload_1
	invokestatic	Method scala/reflect/ClassManifest$class.$greater$colon$greater:(Lscala/reflect/ClassManifest;Lscala/reflect/ClassManifest;)Z
	ireturn
  Labels:
  LocalVariableTable: 
   Start  Length  Slot  Name   Signature
   0      6      0    this       Lscala/reflect/Manifest$$anon$8;
   0      6      1    that       Lscala/reflect/ClassManifest;


public scala.reflect.Manifest arrayManifest();
  Signature: ()Lscala/reflect/Manifest;
  Code:
   Stack=1, Locals=1, Args_size=1
	aload_0
	invokestatic	Method scala/reflect/Manifest$class.arrayManifest:(Lscala/reflect/Manifest;)Lscala/reflect/Manifest;
	areturn
  Labels:

public scala.collection.immutable.List typeArguments();
  Signature: ()Lscala/collection/immutable/List;
  Code:
   Stack=1, Locals=1, Args_size=1
	aload_0
	invokestatic	Method scala/reflect/Manifest$class.typeArguments:(Lscala/reflect/Manifest;)Lscala/collection/immutable/List;
	areturn
  Labels:

public boolean equals(java.lang.Object);
  Signature: (Ljava/lang/Object;)Z
  Code:
   Stack=2, Locals=2, Args_size=2
	aload_0
	aload_1
	invokestatic	Method scala/reflect/AnyValManifest$class.equals:(Lscala/reflect/AnyValManifest;Ljava/lang/Object;)Z
	ireturn
  Labels:
  LocalVariableTable: 
   Start  Length  Slot  Name   Signature
   0      6      0    this       Lscala/reflect/Manifest$$anon$8;
   0      6      1    that       Ljava/lang/Object;


public boolean $less$colon$less(scala.reflect.ClassManifest);
  Signature: (Lscala/reflect/ClassManifest;)Z
  Code:
   Stack=2, Locals=2, Args_size=2
	aload_0
	aload_1
	invokestatic	Method scala/reflect/AnyValManifest$class.$less$colon$less:(Lscala/reflect/AnyValManifest;Lscala/reflect/ClassManifest;)Z
	ireturn
  Labels:
  LocalVariableTable: 
   Start  Length  Slot  Name   Signature
   0      6      0    this       Lscala/reflect/Manifest$$anon$8;
   0      6      1    that       Lscala/reflect/ClassManifest;


}

