Compiled from "Manifest.scala"
public final class scala.reflect.Manifest$$anon$18 extends java.lang.Object implements scala.reflect.Manifest
  SourceFile: "Manifest.scala"
  Signature: length = 0x2
   00 FFFFFF8C 
  Scala: length = 0x
   
  InnerClass: 
   public final $anon$18=class scala/reflect/Manifest$$anon$18 of class scala/reflect/Manifest
  minor version: 0
  major version: 49
  Constant pool:
Asciz	SourceFile;
Asciz	Manifest.scala;
Asciz	parents$1;
Asciz	Lscala/collection/Seq;;
Asciz	<init>;
Asciz	(Lscala/collection/Seq;)V;
Asciz	Code;
Asciz	LineNumberTable;
Asciz	scala/reflect/Manifest$$anon$18;
class	scala/reflect/Manifest$$anon$18
NameAndType	parents$1:Lscala/collection/Seq;
Field	scala/reflect/Manifest$$anon$18.parents$1:Lscala/collection/Seq;
Asciz	java/lang/Object;
class	java/lang/Object
Asciz	()V;
NameAndType	"<init>":()V
Method	java/lang/Object."<init>":()V
Asciz	scala/reflect/ClassManifest$class;
class	scala/reflect/ClassManifest$class
Asciz	$init$;
Asciz	(Lscala/reflect/ClassManifest;)V;
NameAndType	$init$:(Lscala/reflect/ClassManifest;)V
Method	scala/reflect/ClassManifest$class.$init$:(Lscala/reflect/ClassManifest;)V
Asciz	scala/reflect/Manifest$class;
class	scala/reflect/Manifest$class
Asciz	(Lscala/reflect/Manifest;)V;
NameAndType	$init$:(Lscala/reflect/Manifest;)V
Method	scala/reflect/Manifest$class.$init$:(Lscala/reflect/Manifest;)V
Asciz	arrayManifest;
Asciz	()Lscala/reflect/ClassManifest;;
Asciz	scala/reflect/Manifest;
class	scala/reflect/Manifest
Asciz	()Lscala/reflect/Manifest;;
NameAndType	arrayManifest:()Lscala/reflect/Manifest;
InterfaceMethod	scala/reflect/Manifest.arrayManifest:()Lscala/reflect/Manifest;
Asciz	toString;
Asciz	()Ljava/lang/String;;
Asciz	 with ;
String	 with 
Asciz	scala/collection/TraversableLike;
class	scala/collection/TraversableLike
Asciz	mkString;
Asciz	(Ljava/lang/String;)Ljava/lang/String;;
NameAndType	mkString:(Ljava/lang/String;)Ljava/lang/String;
InterfaceMethod	scala/collection/TraversableLike.mkString:(Ljava/lang/String;)Ljava/lang/String;
Asciz	erasure;
Asciz	()Ljava/lang/Class;;
Asciz	scala/collection/IterableLike;
class	scala/collection/IterableLike
Asciz	head;
Asciz	()Ljava/lang/Object;;
NameAndType	head:()Ljava/lang/Object;
InterfaceMethod	scala/collection/IterableLike.head:()Ljava/lang/Object;
Asciz	scala/reflect/ClassManifest;
class	scala/reflect/ClassManifest
NameAndType	erasure:()Ljava/lang/Class;
InterfaceMethod	scala/reflect/ClassManifest.erasure:()Ljava/lang/Class;
Asciz	()Ljava/lang/Class<*>;;
Asciz	Signature;
Asciz	argString;
Asciz	(Lscala/reflect/ClassManifest;)Ljava/lang/String;;
NameAndType	argString:(Lscala/reflect/ClassManifest;)Ljava/lang/String;
Method	scala/reflect/ClassManifest$class.argString:(Lscala/reflect/ClassManifest;)Ljava/lang/String;
Asciz	newArrayBuilder;
Asciz	()Lscala/collection/mutable/ArrayBuilder;;
Asciz	(Lscala/reflect/ClassManifest;)Lscala/collection/mutable/ArrayBuilder;;
NameAndType	newArrayBuilder:(Lscala/reflect/ClassManifest;)Lscala/collection/mutable/ArrayBuilder;
Method	scala/reflect/ClassManifest$class.newArrayBuilder:(Lscala/reflect/ClassManifest;)Lscala/collection/mutable/ArrayBuilder;
Asciz	newWrappedArray;
Asciz	(I)Lscala/collection/mutable/WrappedArray;;
Asciz	(Lscala/reflect/ClassManifest;I)Lscala/collection/mutable/WrappedArray;;
NameAndType	newWrappedArray:(Lscala/reflect/ClassManifest;I)Lscala/collection/mutable/WrappedArray;
Method	scala/reflect/ClassManifest$class.newWrappedArray:(Lscala/reflect/ClassManifest;I)Lscala/collection/mutable/WrappedArray;
Asciz	this;
Asciz	Lscala/reflect/Manifest$$anon$18;;
Asciz	len;
Asciz	I;
Asciz	LocalVariableTable;
Asciz	newArray5;
Asciz	(I)[[[[Ljava/lang/Object;;
Asciz	(Lscala/reflect/ClassManifest;I)[[[[Ljava/lang/Object;;
NameAndType	newArray5:(Lscala/reflect/ClassManifest;I)[[[[Ljava/lang/Object;
Method	scala/reflect/ClassManifest$class.newArray5:(Lscala/reflect/ClassManifest;I)[[[[Ljava/lang/Object;
Asciz	newArray4;
Asciz	(I)[[[Ljava/lang/Object;;
Asciz	(Lscala/reflect/ClassManifest;I)[[[Ljava/lang/Object;;
NameAndType	newArray4:(Lscala/reflect/ClassManifest;I)[[[Ljava/lang/Object;
Method	scala/reflect/ClassManifest$class.newArray4:(Lscala/reflect/ClassManifest;I)[[[Ljava/lang/Object;
Asciz	newArray3;
Asciz	(I)[[Ljava/lang/Object;;
Asciz	(Lscala/reflect/ClassManifest;I)[[Ljava/lang/Object;;
NameAndType	newArray3:(Lscala/reflect/ClassManifest;I)[[Ljava/lang/Object;
Method	scala/reflect/ClassManifest$class.newArray3:(Lscala/reflect/ClassManifest;I)[[Ljava/lang/Object;
Asciz	newArray2;
Asciz	(I)[Ljava/lang/Object;;
Asciz	(Lscala/reflect/ClassManifest;I)[Ljava/lang/Object;;
NameAndType	newArray2:(Lscala/reflect/ClassManifest;I)[Ljava/lang/Object;
Method	scala/reflect/ClassManifest$class.newArray2:(Lscala/reflect/ClassManifest;I)[Ljava/lang/Object;
Asciz	newArray;
Asciz	(I)Ljava/lang/Object;;
Asciz	(Lscala/reflect/ClassManifest;I)Ljava/lang/Object;;
NameAndType	newArray:(Lscala/reflect/ClassManifest;I)Ljava/lang/Object;
Method	scala/reflect/ClassManifest$class.newArray:(Lscala/reflect/ClassManifest;I)Ljava/lang/Object;
Asciz	arrayClass;
Asciz	(Ljava/lang/Class;)Ljava/lang/Class;;
Asciz	(Lscala/reflect/ClassManifest;Ljava/lang/Class;)Ljava/lang/Class;;
NameAndType	arrayClass:(Lscala/reflect/ClassManifest;Ljava/lang/Class;)Ljava/lang/Class;
Method	scala/reflect/ClassManifest$class.arrayClass:(Lscala/reflect/ClassManifest;Ljava/lang/Class;)Ljava/lang/Class;
Asciz	tp;
Asciz	Ljava/lang/Class;;
Asciz	hashCode;
Asciz	()I;
Asciz	(Lscala/reflect/ClassManifest;)I;
NameAndType	hashCode:(Lscala/reflect/ClassManifest;)I
Method	scala/reflect/ClassManifest$class.hashCode:(Lscala/reflect/ClassManifest;)I
Asciz	equals;
Asciz	(Ljava/lang/Object;)Z;
Asciz	(Lscala/reflect/ClassManifest;Ljava/lang/Object;)Z;
NameAndType	equals:(Lscala/reflect/ClassManifest;Ljava/lang/Object;)Z
Method	scala/reflect/ClassManifest$class.equals:(Lscala/reflect/ClassManifest;Ljava/lang/Object;)Z
Asciz	that;
Asciz	Ljava/lang/Object;;
Asciz	$greater$colon$greater;
Asciz	(Lscala/reflect/ClassManifest;)Z;
Asciz	(Lscala/reflect/ClassManifest;Lscala/reflect/ClassManifest;)Z;
NameAndType	$greater$colon$greater:(Lscala/reflect/ClassManifest;Lscala/reflect/ClassManifest;)Z
Method	scala/reflect/ClassManifest$class.$greater$colon$greater:(Lscala/reflect/ClassManifest;Lscala/reflect/ClassManifest;)Z
Asciz	Lscala/reflect/ClassManifest;;
Asciz	$less$colon$less;
NameAndType	$less$colon$less:(Lscala/reflect/ClassManifest;Lscala/reflect/ClassManifest;)Z
Method	scala/reflect/ClassManifest$class.$less$colon$less:(Lscala/reflect/ClassManifest;Lscala/reflect/ClassManifest;)Z
Asciz	(Lscala/reflect/Manifest;)Lscala/reflect/Manifest;;
NameAndType	arrayManifest:(Lscala/reflect/Manifest;)Lscala/reflect/Manifest;
Method	scala/reflect/Manifest$class.arrayManifest:(Lscala/reflect/Manifest;)Lscala/reflect/Manifest;
Asciz	typeArguments;
Asciz	()Lscala/collection/immutable/List;;
Asciz	(Lscala/reflect/Manifest;)Lscala/collection/immutable/List;;
NameAndType	typeArguments:(Lscala/reflect/Manifest;)Lscala/collection/immutable/List;
Method	scala/reflect/Manifest$class.typeArguments:(Lscala/reflect/Manifest;)Lscala/collection/immutable/List;
Asciz	Ljava/lang/Object;Lscala/reflect/Manifest<TT;>;;
Asciz	Scala;
Asciz	InnerClasses;
Asciz	$anon$18;

{
private final scala.collection.Seq parents$1;
  Signature: Lscala/collection/Seq;

public scala.reflect.Manifest$$anon$18(scala.collection.Seq);
  Signature: (Lscala/collection/Seq;)V
  Code:
   Stack=2, Locals=2, Args_size=2
	aload_0
	aload_1
	putfield	Field parents$1:Lscala/collection/Seq;
	aload_0
	invokespecial	Method java/lang/Object."<init>":()V
	aload_0
	invokestatic	Method scala/reflect/ClassManifest$class.$init$:(Lscala/reflect/ClassManifest;)V
	aload_0
	invokestatic	Method scala/reflect/Manifest$class.$init$:(Lscala/reflect/Manifest;)V
	return
  Labels:

public scala.reflect.ClassManifest arrayManifest();
  Signature: ()Lscala/reflect/ClassManifest;
  Code:
   Stack=1, Locals=1, Args_size=1
	aload_0
	invokeinterface	InterfaceMethod scala/reflect/Manifest.arrayManifest:()Lscala/reflect/Manifest;
	areturn
  Labels:

public java.lang.String toString();
  Signature: ()Ljava/lang/String;
  Code:
   Stack=2, Locals=1, Args_size=1
	aload_0
	getfield	Field parents$1:Lscala/collection/Seq;
	ldc	String  with 
	invokeinterface	InterfaceMethod scala/collection/TraversableLike.mkString:(Ljava/lang/String;)Ljava/lang/String;
	areturn
  Labels:

public java.lang.Class erasure();
  Signature: ()Ljava/lang/Class;
  Code:
   Stack=1, Locals=1, Args_size=1
	aload_0
	getfield	Field parents$1:Lscala/collection/Seq;
	invokeinterface	InterfaceMethod scala/collection/IterableLike.head:()Ljava/lang/Object;
	checkcast	class scala/reflect/ClassManifest
	invokeinterface	InterfaceMethod scala/reflect/ClassManifest.erasure:()Ljava/lang/Class;
	areturn
  Labels:
  Signature: length = 0x2
   00 3A 

public java.lang.String argString();
  Signature: ()Ljava/lang/String;
  Code:
   Stack=1, Locals=1, Args_size=1
	aload_0
	invokestatic	Method scala/reflect/ClassManifest$class.argString:(Lscala/reflect/ClassManifest;)Ljava/lang/String;
	areturn
  Labels:

public scala.collection.mutable.ArrayBuilder newArrayBuilder();
  Signature: ()Lscala/collection/mutable/ArrayBuilder;
  Code:
   Stack=1, Locals=1, Args_size=1
	aload_0
	invokestatic	Method scala/reflect/ClassManifest$class.newArrayBuilder:(Lscala/reflect/ClassManifest;)Lscala/collection/mutable/ArrayBuilder;
	areturn
  Labels:

public scala.collection.mutable.WrappedArray newWrappedArray(int);
  Signature: (I)Lscala/collection/mutable/WrappedArray;
  Code:
   Stack=2, Locals=2, Args_size=2
	aload_0
	iload_1
	invokestatic	Method scala/reflect/ClassManifest$class.newWrappedArray:(Lscala/reflect/ClassManifest;I)Lscala/collection/mutable/WrappedArray;
	areturn
  Labels:
  LocalVariableTable: 
   Start  Length  Slot  Name   Signature
   0      6      0    this       Lscala/reflect/Manifest$$anon$18;
   0      6      1    len       I


public java.lang.Object[][][][] newArray5(int);
  Signature: (I)[[[[Ljava/lang/Object;
  Code:
   Stack=2, Locals=2, Args_size=2
	aload_0
	iload_1
	invokestatic	Method scala/reflect/ClassManifest$class.newArray5:(Lscala/reflect/ClassManifest;I)[[[[Ljava/lang/Object;
	areturn
  Labels:
  LocalVariableTable: 
   Start  Length  Slot  Name   Signature
   0      6      0    this       Lscala/reflect/Manifest$$anon$18;
   0      6      1    len       I


public java.lang.Object[][][] newArray4(int);
  Signature: (I)[[[Ljava/lang/Object;
  Code:
   Stack=2, Locals=2, Args_size=2
	aload_0
	iload_1
	invokestatic	Method scala/reflect/ClassManifest$class.newArray4:(Lscala/reflect/ClassManifest;I)[[[Ljava/lang/Object;
	areturn
  Labels:
  LocalVariableTable: 
   Start  Length  Slot  Name   Signature
   0      6      0    this       Lscala/reflect/Manifest$$anon$18;
   0      6      1    len       I


public java.lang.Object[][] newArray3(int);
  Signature: (I)[[Ljava/lang/Object;
  Code:
   Stack=2, Locals=2, Args_size=2
	aload_0
	iload_1
	invokestatic	Method scala/reflect/ClassManifest$class.newArray3:(Lscala/reflect/ClassManifest;I)[[Ljava/lang/Object;
	areturn
  Labels:
  LocalVariableTable: 
   Start  Length  Slot  Name   Signature
   0      6      0    this       Lscala/reflect/Manifest$$anon$18;
   0      6      1    len       I


public java.lang.Object[] newArray2(int);
  Signature: (I)[Ljava/lang/Object;
  Code:
   Stack=2, Locals=2, Args_size=2
	aload_0
	iload_1
	invokestatic	Method scala/reflect/ClassManifest$class.newArray2:(Lscala/reflect/ClassManifest;I)[Ljava/lang/Object;
	areturn
  Labels:
  LocalVariableTable: 
   Start  Length  Slot  Name   Signature
   0      6      0    this       Lscala/reflect/Manifest$$anon$18;
   0      6      1    len       I


public java.lang.Object newArray(int);
  Signature: (I)Ljava/lang/Object;
  Code:
   Stack=2, Locals=2, Args_size=2
	aload_0
	iload_1
	invokestatic	Method scala/reflect/ClassManifest$class.newArray:(Lscala/reflect/ClassManifest;I)Ljava/lang/Object;
	areturn
  Labels:
  LocalVariableTable: 
   Start  Length  Slot  Name   Signature
   0      6      0    this       Lscala/reflect/Manifest$$anon$18;
   0      6      1    len       I


public java.lang.Class arrayClass(java.lang.Class);
  Signature: (Ljava/lang/Class;)Ljava/lang/Class;
  Code:
   Stack=2, Locals=2, Args_size=2
	aload_0
	aload_1
	invokestatic	Method scala/reflect/ClassManifest$class.arrayClass:(Lscala/reflect/ClassManifest;Ljava/lang/Class;)Ljava/lang/Class;
	areturn
  Labels:
  LocalVariableTable: 
   Start  Length  Slot  Name   Signature
   0      6      0    this       Lscala/reflect/Manifest$$anon$18;
   0      6      1    tp       Ljava/lang/Class;


public int hashCode();
  Signature: ()I
  Code:
   Stack=1, Locals=1, Args_size=1
	aload_0
	invokestatic	Method scala/reflect/ClassManifest$class.hashCode:(Lscala/reflect/ClassManifest;)I
	ireturn
  Labels:

public boolean equals(java.lang.Object);
  Signature: (Ljava/lang/Object;)Z
  Code:
   Stack=2, Locals=2, Args_size=2
	aload_0
	aload_1
	invokestatic	Method scala/reflect/ClassManifest$class.equals:(Lscala/reflect/ClassManifest;Ljava/lang/Object;)Z
	ireturn
  Labels:
  LocalVariableTable: 
   Start  Length  Slot  Name   Signature
   0      6      0    this       Lscala/reflect/Manifest$$anon$18;
   0      6      1    that       Ljava/lang/Object;


public boolean $greater$colon$greater(scala.reflect.ClassManifest);
  Signature: (Lscala/reflect/ClassManifest;)Z
  Code:
   Stack=2, Locals=2, Args_size=2
	aload_0
	aload_1
	invokestatic	Method scala/reflect/ClassManifest$class.$greater$colon$greater:(Lscala/reflect/ClassManifest;Lscala/reflect/ClassManifest;)Z
	ireturn
  Labels:
  LocalVariableTable: 
   Start  Length  Slot  Name   Signature
   0      6      0    this       Lscala/reflect/Manifest$$anon$18;
   0      6      1    that       Lscala/reflect/ClassManifest;


public boolean $less$colon$less(scala.reflect.ClassManifest);
  Signature: (Lscala/reflect/ClassManifest;)Z
  Code:
   Stack=2, Locals=2, Args_size=2
	aload_0
	aload_1
	invokestatic	Method scala/reflect/ClassManifest$class.$less$colon$less:(Lscala/reflect/ClassManifest;Lscala/reflect/ClassManifest;)Z
	ireturn
  Labels:
  LocalVariableTable: 
   Start  Length  Slot  Name   Signature
   0      6      0    this       Lscala/reflect/Manifest$$anon$18;
   0      6      1    that       Lscala/reflect/ClassManifest;


public scala.reflect.Manifest arrayManifest();
  Signature: ()Lscala/reflect/Manifest;
  Code:
   Stack=1, Locals=1, Args_size=1
	aload_0
	invokestatic	Method scala/reflect/Manifest$class.arrayManifest:(Lscala/reflect/Manifest;)Lscala/reflect/Manifest;
	areturn
  Labels:

public scala.collection.immutable.List typeArguments();
  Signature: ()Lscala/collection/immutable/List;
  Code:
   Stack=1, Locals=1, Args_size=1
	aload_0
	invokestatic	Method scala/reflect/Manifest$class.typeArguments:(Lscala/reflect/Manifest;)Lscala/collection/immutable/List;
	areturn
  Labels:

}

