Compiled from "Manifest.scala"
public final class scala.reflect.Manifest$$anon$3 extends java.lang.Object implements scala.reflect.AnyValManifest
  InnerClass: 
   public final $anon$3=class scala/reflect/Manifest$$anon$3 of class scala/reflect/Manifest
   public final ofChar=class scala/collection/mutable/WrappedArray$ofChar of class scala/collection/mutable/WrappedArray
  Scala: length = 0x
   
  Signature: length = 0x2
   00 3B 
  SourceFile: "Manifest.scala"
  minor version: 0
  major version: 49
  Constant pool:
String	Char
class	java/lang/Character
class	java/lang/Object
class	scala/collection/mutable/WrappedArray
class	scala/collection/mutable/WrappedArray$ofChar
class	scala/reflect/AnyValManifest
class	scala/reflect/AnyValManifest$class
class	scala/reflect/ClassManifest$class
class	scala/reflect/Manifest
class	scala/reflect/Manifest$$anon$3
class	scala/reflect/Manifest$class
Field	java/lang/Character.TYPE:Ljava/lang/Class;
Method	java/lang/Object."<init>":()V
Method	scala/collection/mutable/WrappedArray$ofChar."<init>":([C)V
Method	scala/reflect/AnyValManifest$class.$init$:(Lscala/reflect/AnyValManifest;)V
Method	scala/reflect/AnyValManifest$class.equals:(Lscala/reflect/AnyValManifest;Ljava/lang/Object;)Z
Method	scala/reflect/ClassManifest$class.$init$:(Lscala/reflect/ClassManifest;)V
Method	scala/reflect/ClassManifest$class.argString:(Lscala/reflect/ClassManifest;)Ljava/lang/String;
Method	scala/reflect/Manifest$$anon$3.newArray:(I)[C
Method	scala/reflect/Manifest$class.$init$:(Lscala/reflect/Manifest;)V
Method	scala/reflect/Manifest$class.typeArguments:(Lscala/reflect/Manifest;)Lscala/collection/immutable/List;
NameAndType	$init$:(Lscala/reflect/AnyValManifest;)V
NameAndType	$init$:(Lscala/reflect/ClassManifest;)V
NameAndType	$init$:(Lscala/reflect/Manifest;)V
NameAndType	"<init>":()V
NameAndType	"<init>":([C)V
NameAndType	TYPE:Ljava/lang/Class;
NameAndType	argString:(Lscala/reflect/ClassManifest;)Ljava/lang/String;
NameAndType	equals:(Lscala/reflect/AnyValManifest;Ljava/lang/Object;)Z
NameAndType	newArray:(I)[C
NameAndType	typeArguments:(Lscala/reflect/Manifest;)Lscala/collection/immutable/List;
Asciz	$anon$3;
Asciz	$init$;
Asciz	()Ljava/lang/Class;;
Asciz	()Ljava/lang/Class<Ljava/lang/Character;>;;
Asciz	()Ljava/lang/String;;
Asciz	()Lscala/collection/immutable/List;;
Asciz	()V;
Asciz	(I)Ljava/lang/Object;;
Asciz	(I)Lscala/collection/mutable/WrappedArray;;
Asciz	(I)Lscala/collection/mutable/WrappedArray<Ljava/lang/Character;>;;
Asciz	(I)[C;
Asciz	(Ljava/lang/Object;)Z;
Asciz	(Lscala/reflect/AnyValManifest;)V;
Asciz	(Lscala/reflect/AnyValManifest;Ljava/lang/Object;)Z;
Asciz	(Lscala/reflect/ClassManifest;)Ljava/lang/String;;
Asciz	(Lscala/reflect/ClassManifest;)V;
Asciz	(Lscala/reflect/Manifest;)Lscala/collection/immutable/List;;
Asciz	(Lscala/reflect/Manifest;)V;
Asciz	([C)V;
Asciz	<init>;
Asciz	Char;
Asciz	Code;
Asciz	I;
Asciz	InnerClasses;
Asciz	LineNumberTable;
Asciz	Ljava/lang/Class;;
Asciz	Ljava/lang/Object;;
Asciz	Ljava/lang/Object;Lscala/reflect/AnyValManifest<Ljava/lang/Character;>;;
Asciz	LocalVariableTable;
Asciz	Lscala/reflect/Manifest$$anon$3;;
Asciz	Manifest.scala;
Asciz	Scala;
Asciz	Signature;
Asciz	SourceFile;
Asciz	TYPE;
Asciz	argString;
Asciz	equals;
Asciz	erasure;
Asciz	java/lang/Character;
Asciz	java/lang/Object;
Asciz	len;
Asciz	newArray;
Asciz	newWrappedArray;
Asciz	ofChar;
Asciz	scala/collection/mutable/WrappedArray;
Asciz	scala/collection/mutable/WrappedArray$ofChar;
Asciz	scala/reflect/AnyValManifest;
Asciz	scala/reflect/AnyValManifest$class;
Asciz	scala/reflect/ClassManifest$class;
Asciz	scala/reflect/Manifest;
Asciz	scala/reflect/Manifest$$anon$3;
Asciz	scala/reflect/Manifest$class;
Asciz	that;
Asciz	this;
Asciz	toString;
Asciz	typeArguments;

{
public scala.reflect.Manifest$$anon$3();
  Signature: ()V
  Code:
   Stack=1, Locals=1, Args_size=1
	aload_0
	invokespecial	Method java/lang/Object."<init>":()V
	aload_0
	invokestatic	Method scala/reflect/ClassManifest$class.$init$:(Lscala/reflect/ClassManifest;)V
	aload_0
	invokestatic	Method scala/reflect/Manifest$class.$init$:(Lscala/reflect/Manifest;)V
	aload_0
	invokestatic	Method scala/reflect/AnyValManifest$class.$init$:(Lscala/reflect/AnyValManifest;)V
	return
  Labels:

public java.lang.Object newArray(int);
  Signature: (I)Ljava/lang/Object;
  Code:
   Stack=2, Locals=2, Args_size=2
	aload_0
	iload_1
	invokevirtual	Method newArray:(I)[C
	areturn
  Labels:
  LocalVariableTable: 
   Start  Length  Slot  Name   Signature
   0      6      0    this       Lscala/reflect/Manifest$$anon$3;
   0      6      1    len       I


public scala.collection.mutable.WrappedArray newWrappedArray(int);
  Signature: (I)Lscala/collection/mutable/WrappedArray;
  Code:
   Stack=3, Locals=2, Args_size=2
	new	class scala/collection/mutable/WrappedArray$ofChar
	dup
	iload_1
	newarray char
	invokespecial	Method scala/collection/mutable/WrappedArray$ofChar."<init>":([C)V
	areturn
  Labels:
  LocalVariableTable: 
   Start  Length  Slot  Name   Signature
   0      11      0    this       Lscala/reflect/Manifest$$anon$3;
   0      11      1    len       I

  Signature: length = 0x2
   00 29 

public char[] newArray(int);
  Signature: (I)[C
  Code:
   Stack=1, Locals=2, Args_size=2
	iload_1
	newarray char
	areturn
  Labels:
  LocalVariableTable: 
   Start  Length  Slot  Name   Signature
   0      4      0    this       Lscala/reflect/Manifest$$anon$3;
   0      4      1    len       I


public java.lang.String toString();
  Signature: ()Ljava/lang/String;
  Code:
   Stack=1, Locals=1, Args_size=1
	ldc	String Char
	areturn
  Labels:

public java.lang.Class erasure();
  Signature: ()Ljava/lang/Class;
  Code:
   Stack=1, Locals=1, Args_size=1
	getstatic	Field java/lang/Character.TYPE:Ljava/lang/Class;
	areturn
  Labels:
  Signature: length = 0x2
   00 23 

public java.lang.String argString();
  Signature: ()Ljava/lang/String;
  Code:
   Stack=1, Locals=1, Args_size=1
	aload_0
	invokestatic	Method scala/reflect/ClassManifest$class.argString:(Lscala/reflect/ClassManifest;)Ljava/lang/String;
	areturn
  Labels:

public scala.collection.immutable.List typeArguments();
  Signature: ()Lscala/collection/immutable/List;
  Code:
   Stack=1, Locals=1, Args_size=1
	aload_0
	invokestatic	Method scala/reflect/Manifest$class.typeArguments:(Lscala/reflect/Manifest;)Lscala/collection/immutable/List;
	areturn
  Labels:

public boolean equals(java.lang.Object);
  Signature: (Ljava/lang/Object;)Z
  Code:
   Stack=2, Locals=2, Args_size=2
	aload_0
	aload_1
	invokestatic	Method scala/reflect/AnyValManifest$class.equals:(Lscala/reflect/AnyValManifest;Ljava/lang/Object;)Z
	ireturn
  Labels:
  LocalVariableTable: 
   Start  Length  Slot  Name   Signature
   0      6      0    this       Lscala/reflect/Manifest$$anon$3;
   0      6      1    that       Ljava/lang/Object;


}

