Compiled from "Manifest.scala"
public final class scala.reflect.Manifest$$anon$13 extends scala.reflect.Manifest$ClassTypeManifest
  SourceFile: "Manifest.scala"
  Signature: length = 0x2
   00 3D 
  Scala: length = 0x
   
  InnerClass: 
   public final #68= #65 of #67; //$anon$13=class scala/reflect/Manifest$$anon$13 of class scala/reflect/Manifest
   public #69= #21 of #67; //ClassTypeManifest=class scala/reflect/Manifest$ClassTypeManifest of class scala/reflect/Manifest
  minor version: 0
  major version: 49
  Constant pool:
const #1 = Asciz	SourceFile;
const #2 = Asciz	Manifest.scala;
const #3 = Asciz	<init>;
const #4 = Asciz	()V;
const #5 = Asciz	Code;
const #6 = Asciz	LineNumberTable;
const #7 = Asciz	scala/None$;
const #8 = class	#7;	//  scala/None$
const #9 = Asciz	MODULE$;
const #10 = Asciz	Lscala/None$;;
const #11 = NameAndType	#9:#10;//  MODULE$:Lscala/None$;
const #12 = Field	#8.#11;	//  scala/None$.MODULE$:Lscala/None$;
const #13 = Asciz	java/lang/Object;
const #14 = class	#13;	//  java/lang/Object
const #15 = Asciz	scala/collection/immutable/Nil$;
const #16 = class	#15;	//  scala/collection/immutable/Nil$
const #17 = Asciz	Lscala/collection/immutable/Nil$;;
const #18 = NameAndType	#9:#17;//  MODULE$:Lscala/collection/immutable/Nil$;
const #19 = Field	#16.#18;	//  scala/collection/immutable/Nil$.MODULE$:Lscala/collection/immutable/Nil$;
const #20 = Asciz	scala/reflect/Manifest$ClassTypeManifest;
const #21 = class	#20;	//  scala/reflect/Manifest$ClassTypeManifest
const #22 = Asciz	(Lscala/Option;Ljava/lang/Class;Lscala/collection/immutable/List;)V;
const #23 = NameAndType	#3:#22;//  "<init>":(Lscala/Option;Ljava/lang/Class;Lscala/collection/immutable/List;)V
const #24 = Method	#21.#23;	//  scala/reflect/Manifest$ClassTypeManifest."<init>":(Lscala/Option;Ljava/lang/Class;Lscala/collection/immutable/List;)V
const #25 = Asciz	readResolve;
const #26 = Asciz	()Ljava/lang/Object;;
const #27 = Asciz	scala/reflect/Manifest$;
const #28 = class	#27;	//  scala/reflect/Manifest$
const #29 = Asciz	Lscala/reflect/Manifest$;;
const #30 = NameAndType	#9:#29;//  MODULE$:Lscala/reflect/Manifest$;
const #31 = Field	#28.#30;	//  scala/reflect/Manifest$.MODULE$:Lscala/reflect/Manifest$;
const #32 = Asciz	Null;
const #33 = Asciz	()Lscala/reflect/Manifest;;
const #34 = NameAndType	#32:#33;//  Null:()Lscala/reflect/Manifest;
const #35 = Method	#28.#34;	//  scala/reflect/Manifest$.Null:()Lscala/reflect/Manifest;
const #36 = Asciz	equals;
const #37 = Asciz	(Ljava/lang/Object;)Z;
const #38 = Asciz	this;
const #39 = Asciz	Lscala/reflect/Manifest$$anon$13;;
const #40 = Asciz	that;
const #41 = Asciz	Ljava/lang/Object;;
const #42 = Asciz	LocalVariableTable;
const #43 = Asciz	$less$colon$less;
const #44 = Asciz	(Lscala/reflect/ClassManifest;)Z;
const #45 = Asciz	Nothing;
const #46 = NameAndType	#45:#33;//  Nothing:()Lscala/reflect/Manifest;
const #47 = Method	#28.#46;	//  scala/reflect/Manifest$.Nothing:()Lscala/reflect/Manifest;
const #48 = Asciz	AnyVal;
const #49 = NameAndType	#48:#33;//  AnyVal:()Lscala/reflect/Manifest;
const #50 = Method	#28.#49;	//  scala/reflect/Manifest$.AnyVal:()Lscala/reflect/Manifest;
const #51 = Asciz	scala/reflect/ClassManifest;
const #52 = class	#51;	//  scala/reflect/ClassManifest
const #53 = NameAndType	#43:#44;//  $less$colon$less:(Lscala/reflect/ClassManifest;)Z
const #54 = InterfaceMethod	#52.#53;	//  scala/reflect/ClassManifest.$less$colon$less:(Lscala/reflect/ClassManifest;)Z
const #55 = Asciz	Lscala/reflect/ClassManifest;;
const #56 = Asciz	(Lscala/reflect/ClassManifest<*>;)Z;
const #57 = Asciz	Signature;
const #58 = Asciz	toString;
const #59 = Asciz	()Ljava/lang/String;;
const #60 = String	#32;	//  Null
const #61 = Asciz	Lscala/reflect/Manifest$ClassTypeManifest<Lscala/runtime/Null$;>;;
const #62 = Asciz	Scala;
const #63 = Asciz	InnerClasses;
const #64 = Asciz	scala/reflect/Manifest$$anon$13;
const #65 = class	#64;	//  scala/reflect/Manifest$$anon$13
const #66 = Asciz	scala/reflect/Manifest;
const #67 = class	#66;	//  scala/reflect/Manifest
const #68 = Asciz	$anon$13;
const #69 = Asciz	ClassTypeManifest;

{
public scala.reflect.Manifest$$anon$13();
  Code:
   Stack=4, Locals=1, Args_size=1
   0:	aload_0
   1:	getstatic	#12; //Field scala/None$.MODULE$:Lscala/None$;
   4:	ldc	#14; //class java/lang/Object
   6:	getstatic	#19; //Field scala/collection/immutable/Nil$.MODULE$:Lscala/collection/immutable/Nil$;
   9:	invokespecial	#24; //Method scala/reflect/Manifest$ClassTypeManifest."<init>":(Lscala/Option;Ljava/lang/Class;Lscala/collection/immutable/List;)V
   12:	return
  LineNumberTable: 
   line 157: 0


public boolean equals(java.lang.Object);
  Code:
   Stack=2, Locals=2, Args_size=2
   0:	aload_0
   1:	aload_1
   2:	if_acmpne	9
   5:	iconst_1
   6:	goto	10
   9:	iconst_0
   10:	ireturn
  LineNumberTable: 
   line 161: 0

  LocalVariableTable: 
   Start  Length  Slot  Name   Signature
   0      11      0    this       Lscala/reflect/Manifest$$anon$13;
   0      11      1    that       Ljava/lang/Object;


public boolean $less$colon$less(scala.reflect.ClassManifest);
  Code:
   Stack=2, Locals=2, Args_size=2
   0:	aload_1
   1:	ifnull	33
   4:	aload_1
   5:	getstatic	#31; //Field scala/reflect/Manifest$.MODULE$:Lscala/reflect/Manifest$;
   8:	invokevirtual	#47; //Method scala/reflect/Manifest$.Nothing:()Lscala/reflect/Manifest;
   11:	if_acmpeq	33
   14:	aload_1
   15:	getstatic	#31; //Field scala/reflect/Manifest$.MODULE$:Lscala/reflect/Manifest$;
   18:	invokevirtual	#50; //Method scala/reflect/Manifest$.AnyVal:()Lscala/reflect/Manifest;
   21:	invokeinterface	#54,  2; //InterfaceMethod scala/reflect/ClassManifest.$less$colon$less:(Lscala/reflect/ClassManifest;)Z
   26:	ifne	33
   29:	iconst_1
   30:	goto	34
   33:	iconst_0
   34:	ireturn
  LineNumberTable: 
   line 160: 0

  LocalVariableTable: 
   Start  Length  Slot  Name   Signature
   0      35      0    this       Lscala/reflect/Manifest$$anon$13;
   0      35      1    that       Lscala/reflect/ClassManifest;

  Signature: length = 0x2
   00 38 

public java.lang.String toString();
  Code:
   Stack=1, Locals=1, Args_size=1
   0:	ldc	#60; //String Null
   2:	areturn
  LineNumberTable: 
   line 158: 0


}

