Compiled from "Manifest.scala"
public class scala.reflect.Manifest$ClassTypeManifest extends java.lang.Object implements java.io.Serializable,scala.reflect.Manifest
  InnerClass: 
   public ClassTypeManifest=class scala/reflect/Manifest$ClassTypeManifest of class scala/reflect/Manifest
  Scala: length = 0x
   
  Signature: length = 0x2
   00 56 
  SourceFile: "Manifest.scala"
  minor version: 0
  major version: 49
  Constant pool:
String	
String	#
String	Array
class	java/io/Serializable
class	java/lang/Class
class	java/lang/Object
class	scala/Option
class	scala/collection/mutable/StringBuilder
class	scala/reflect/ClassManifest
class	scala/reflect/ClassManifest$class
class	scala/reflect/Manifest
class	scala/reflect/Manifest$ClassTypeManifest
class	scala/reflect/Manifest$class
Field	scala/reflect/Manifest$ClassTypeManifest.erasure:Ljava/lang/Class;
Field	scala/reflect/Manifest$ClassTypeManifest.prefix:Lscala/Option;
Field	scala/reflect/Manifest$ClassTypeManifest.typeArguments:Lscala/collection/immutable/List;
Method	java/lang/Class.getName:()Ljava/lang/String;
Method	java/lang/Class.isArray:()Z
Method	java/lang/Object."<init>":()V
Method	java/lang/Object.toString:()Ljava/lang/String;
Method	scala/Option.get:()Ljava/lang/Object;
Method	scala/Option.isEmpty:()Z
Method	scala/collection/mutable/StringBuilder."<init>":()V
Method	scala/collection/mutable/StringBuilder.append:(Ljava/lang/Object;)Lscala/collection/mutable/StringBuilder;
Method	scala/collection/mutable/StringBuilder.toString:()Ljava/lang/String;
Method	scala/reflect/ClassManifest$class.$init$:(Lscala/reflect/ClassManifest;)V
Method	scala/reflect/ClassManifest$class.$less$colon$less:(Lscala/reflect/ClassManifest;Lscala/reflect/ClassManifest;)Z
Method	scala/reflect/ClassManifest$class.argString:(Lscala/reflect/ClassManifest;)Ljava/lang/String;
Method	scala/reflect/ClassManifest$class.newArray:(Lscala/reflect/ClassManifest;I)Ljava/lang/Object;
Method	scala/reflect/ClassManifest$class.newWrappedArray:(Lscala/reflect/ClassManifest;I)Lscala/collection/mutable/WrappedArray;
Method	scala/reflect/Manifest$ClassTypeManifest.erasure:()Ljava/lang/Class;
Method	scala/reflect/Manifest$class.$init$:(Lscala/reflect/Manifest;)V
Method	scala/reflect/Manifest$class.canEqual:(Lscala/reflect/Manifest;Ljava/lang/Object;)Z
Method	scala/reflect/Manifest$class.equals:(Lscala/reflect/Manifest;Ljava/lang/Object;)Z
Method	scala/reflect/Manifest$class.hashCode:(Lscala/reflect/Manifest;)I
InterfaceMethod	scala/reflect/ClassManifest.argString:()Ljava/lang/String;
NameAndType	$init$:(Lscala/reflect/ClassManifest;)V
NameAndType	$init$:(Lscala/reflect/Manifest;)V
NameAndType	$less$colon$less:(Lscala/reflect/ClassManifest;Lscala/reflect/ClassManifest;)Z
NameAndType	"<init>":()V
NameAndType	append:(Ljava/lang/Object;)Lscala/collection/mutable/StringBuilder;
NameAndType	argString:()Ljava/lang/String;
NameAndType	argString:(Lscala/reflect/ClassManifest;)Ljava/lang/String;
NameAndType	canEqual:(Lscala/reflect/Manifest;Ljava/lang/Object;)Z
NameAndType	equals:(Lscala/reflect/Manifest;Ljava/lang/Object;)Z
NameAndType	erasure:()Ljava/lang/Class;
NameAndType	erasure:Ljava/lang/Class;
NameAndType	get:()Ljava/lang/Object;
NameAndType	getName:()Ljava/lang/String;
NameAndType	hashCode:(Lscala/reflect/Manifest;)I
NameAndType	isArray:()Z
NameAndType	isEmpty:()Z
NameAndType	newArray:(Lscala/reflect/ClassManifest;I)Ljava/lang/Object;
NameAndType	newWrappedArray:(Lscala/reflect/ClassManifest;I)Lscala/collection/mutable/WrappedArray;
NameAndType	prefix:Lscala/Option;
NameAndType	toString:()Ljava/lang/String;
NameAndType	typeArguments:Lscala/collection/immutable/List;
Asciz	;
Asciz	#;
Asciz	$init$;
Asciz	$less$colon$less;
Asciz	()I;
Asciz	()Ljava/lang/Class;;
Asciz	()Ljava/lang/Class<*>;;
Asciz	()Ljava/lang/Object;;
Asciz	()Ljava/lang/String;;
Asciz	()Lscala/collection/immutable/List;;
Asciz	()Lscala/collection/immutable/List<Lscala/reflect/Manifest<*>;>;;
Asciz	()V;
Asciz	()Z;
Asciz	(I)Ljava/lang/Object;;
Asciz	(I)Lscala/collection/mutable/WrappedArray;;
Asciz	(Ljava/lang/Object;)Lscala/collection/mutable/StringBuilder;;
Asciz	(Ljava/lang/Object;)Z;
Asciz	(Lscala/Option;Ljava/lang/Class;Lscala/collection/immutable/List;)V;
Asciz	(Lscala/Option<Lscala/reflect/Manifest<*>;>;Ljava/lang/Class<*>;Lscala/collection/immutable/List<Lscala/reflect/Manifest<*>;>;)V;
Asciz	(Lscala/reflect/ClassManifest;)Ljava/lang/String;;
Asciz	(Lscala/reflect/ClassManifest;)V;
Asciz	(Lscala/reflect/ClassManifest;)Z;
Asciz	(Lscala/reflect/ClassManifest;I)Ljava/lang/Object;;
Asciz	(Lscala/reflect/ClassManifest;I)Lscala/collection/mutable/WrappedArray;;
Asciz	(Lscala/reflect/ClassManifest;Lscala/reflect/ClassManifest;)Z;
Asciz	(Lscala/reflect/Manifest;)I;
Asciz	(Lscala/reflect/Manifest;)V;
Asciz	(Lscala/reflect/Manifest;Ljava/lang/Object;)Z;
Asciz	<T:Ljava/lang/Object;>Ljava/lang/Object;Lscala/reflect/Manifest<TT;>;;
Asciz	<init>;
Asciz	Array;
Asciz	ClassTypeManifest;
Asciz	Code;
Asciz	I;
Asciz	InnerClasses;
Asciz	LineNumberTable;
Asciz	Ljava/lang/Class;;
Asciz	Ljava/lang/Class<*>;;
Asciz	Ljava/lang/Object;;
Asciz	LocalVariableTable;
Asciz	Lscala/Option;;
Asciz	Lscala/Option<Lscala/reflect/Manifest<*>;>;;
Asciz	Lscala/collection/immutable/List;;
Asciz	Lscala/collection/immutable/List<Lscala/reflect/Manifest<*>;>;;
Asciz	Lscala/reflect/ClassManifest;;
Asciz	Lscala/reflect/Manifest$ClassTypeManifest;;
Asciz	Manifest.scala;
Asciz	Scala;
Asciz	Signature;
Asciz	SourceFile;
Asciz	append;
Asciz	argString;
Asciz	canEqual;
Asciz	equals;
Asciz	erasure;
Asciz	get;
Asciz	getName;
Asciz	hashCode;
Asciz	isArray;
Asciz	isEmpty;
Asciz	java/io/Serializable;
Asciz	java/lang/Class;
Asciz	java/lang/Object;
Asciz	len;
Asciz	newArray;
Asciz	newWrappedArray;
Asciz	prefix;
Asciz	scala/Option;
Asciz	scala/collection/mutable/StringBuilder;
Asciz	scala/reflect/ClassManifest;
Asciz	scala/reflect/ClassManifest$class;
Asciz	scala/reflect/Manifest;
Asciz	scala/reflect/Manifest$ClassTypeManifest;
Asciz	scala/reflect/Manifest$class;
Asciz	that;
Asciz	this;
Asciz	toString;
Asciz	typeArguments;

{
private final scala.Option prefix;
  Signature: Lscala/Option;
  Signature: length = 0x2
   00 63 

private final java.lang.Class erasure;
  Signature: Ljava/lang/Class;
  Signature: length = 0x2
   00 5F 

private final scala.collection.immutable.List typeArguments;
  Signature: Lscala/collection/immutable/List;
  Signature: length = 0x2
   00 65 

public boolean canEqual(java.lang.Object);
  Signature: (Ljava/lang/Object;)Z
  Code:
   Stack=2, Locals=2, Args_size=2
	aload_0
	aload_1
	invokestatic	Method scala/reflect/Manifest$class.canEqual:(Lscala/reflect/Manifest;Ljava/lang/Object;)Z
	ireturn
  Labels:
  LocalVariableTable: 
   Start  Length  Slot  Name   Signature
   0      6      0    this       Lscala/reflect/Manifest$ClassTypeManifest;
   0      6      1    that       Ljava/lang/Object;


public boolean equals(java.lang.Object);
  Signature: (Ljava/lang/Object;)Z
  Code:
   Stack=2, Locals=2, Args_size=2
	aload_0
	aload_1
	invokestatic	Method scala/reflect/Manifest$class.equals:(Lscala/reflect/Manifest;Ljava/lang/Object;)Z
	ireturn
  Labels:
  LocalVariableTable: 
   Start  Length  Slot  Name   Signature
   0      6      0    this       Lscala/reflect/Manifest$ClassTypeManifest;
   0      6      1    that       Ljava/lang/Object;


public int hashCode();
  Signature: ()I
  Code:
   Stack=1, Locals=1, Args_size=1
	aload_0
	invokestatic	Method scala/reflect/Manifest$class.hashCode:(Lscala/reflect/Manifest;)I
	ireturn
  Labels:

public boolean $less$colon$less(scala.reflect.ClassManifest);
  Signature: (Lscala/reflect/ClassManifest;)Z
  Code:
   Stack=2, Locals=2, Args_size=2
	aload_0
	aload_1
	invokestatic	Method scala/reflect/ClassManifest$class.$less$colon$less:(Lscala/reflect/ClassManifest;Lscala/reflect/ClassManifest;)Z
	ireturn
  Labels:
  LocalVariableTable: 
   Start  Length  Slot  Name   Signature
   0      6      0    this       Lscala/reflect/Manifest$ClassTypeManifest;
   0      6      1    that       Lscala/reflect/ClassManifest;


public java.lang.Object newArray(int);
  Signature: (I)Ljava/lang/Object;
  Code:
   Stack=2, Locals=2, Args_size=2
	aload_0
	iload_1
	invokestatic	Method scala/reflect/ClassManifest$class.newArray:(Lscala/reflect/ClassManifest;I)Ljava/lang/Object;
	areturn
  Labels:
  LocalVariableTable: 
   Start  Length  Slot  Name   Signature
   0      6      0    this       Lscala/reflect/Manifest$ClassTypeManifest;
   0      6      1    len       I


public scala.collection.mutable.WrappedArray newWrappedArray(int);
  Signature: (I)Lscala/collection/mutable/WrappedArray;
  Code:
   Stack=2, Locals=2, Args_size=2
	aload_0
	iload_1
	invokestatic	Method scala/reflect/ClassManifest$class.newWrappedArray:(Lscala/reflect/ClassManifest;I)Lscala/collection/mutable/WrappedArray;
	areturn
  Labels:
  LocalVariableTable: 
   Start  Length  Slot  Name   Signature
   0      6      0    this       Lscala/reflect/Manifest$ClassTypeManifest;
   0      6      1    len       I


public java.lang.String argString();
  Signature: ()Ljava/lang/String;
  Code:
   Stack=1, Locals=1, Args_size=1
	aload_0
	invokestatic	Method scala/reflect/ClassManifest$class.argString:(Lscala/reflect/ClassManifest;)Ljava/lang/String;
	areturn
  Labels:

public java.lang.Class erasure();
  Signature: ()Ljava/lang/Class;
  Code:
   Stack=1, Locals=1, Args_size=1
	aload_0
	getfield	Field erasure:Ljava/lang/Class;
	areturn
  Labels:
  Signature: length = 0x2
   00 40 

public scala.collection.immutable.List typeArguments();
  Signature: ()Lscala/collection/immutable/List;
  Code:
   Stack=1, Locals=1, Args_size=1
	aload_0
	getfield	Field typeArguments:Lscala/collection/immutable/List;
	areturn
  Labels:
  Signature: length = 0x2
   00 44 

public java.lang.String toString();
  Signature: ()Ljava/lang/String;
  Code:
   Stack=3, Locals=1, Args_size=1
	new	class scala/collection/mutable/StringBuilder
	dup
	invokespecial	Method scala/collection/mutable/StringBuilder."<init>":()V
	aload_0
	getfield	Field prefix:Lscala/Option;
	invokevirtual	Method scala/Option.isEmpty:()Z
	ifeq	l1 // new
	ldc	String 
	goto	l2 // invokevirtual
l1	new	class scala/collection/mutable/StringBuilder
	dup
	invokespecial	Method scala/collection/mutable/StringBuilder."<init>":()V
	aload_0
	getfield	Field prefix:Lscala/Option;
	invokevirtual	Method scala/Option.get:()Ljava/lang/Object;
	invokevirtual	Method java/lang/Object.toString:()Ljava/lang/String;
	invokevirtual	Method scala/collection/mutable/StringBuilder.append:(Ljava/lang/Object;)Lscala/collection/mutable/StringBuilder;
	ldc	String #
	invokevirtual	Method scala/collection/mutable/StringBuilder.append:(Ljava/lang/Object;)Lscala/collection/mutable/StringBuilder;
	invokevirtual	Method scala/collection/mutable/StringBuilder.toString:()Ljava/lang/String;
l2	invokevirtual	Method scala/collection/mutable/StringBuilder.append:(Ljava/lang/Object;)Lscala/collection/mutable/StringBuilder;
	aload_0
	invokevirtual	Method erasure:()Ljava/lang/Class;
	invokevirtual	Method java/lang/Class.isArray:()Z
	ifeq	l3 // aload_0
	ldc	String Array
	goto	l4 // invokevirtual
l3	aload_0
	invokevirtual	Method erasure:()Ljava/lang/Class;
	invokevirtual	Method java/lang/Class.getName:()Ljava/lang/String;
l4	invokevirtual	Method scala/collection/mutable/StringBuilder.append:(Ljava/lang/Object;)Lscala/collection/mutable/StringBuilder;
	aload_0
	invokeinterface	InterfaceMethod scala/reflect/ClassManifest.argString:()Ljava/lang/String;
	invokevirtual	Method scala/collection/mutable/StringBuilder.append:(Ljava/lang/Object;)Lscala/collection/mutable/StringBuilder;
	invokevirtual	Method scala/collection/mutable/StringBuilder.toString:()Ljava/lang/String;
	areturn
  Labels:
   	l1 = 22 // new
   	l2 = 50 // invokevirtual
   	l3 = 68 // aload_0
   	l4 = 75 // invokevirtual

public scala.reflect.Manifest$ClassTypeManifest(scala.Option, java.lang.Class, scala.collection.immutable.List);
  Signature: (Lscala/Option;Ljava/lang/Class;Lscala/collection/immutable/List;)V
  Code:
   Stack=2, Locals=4, Args_size=4
	aload_0
	aload_1
	putfield	Field prefix:Lscala/Option;
	aload_0
	aload_2
	putfield	Field erasure:Ljava/lang/Class;
	aload_0
	aload_3
	putfield	Field typeArguments:Lscala/collection/immutable/List;
	aload_0
	invokespecial	Method java/lang/Object."<init>":()V
	aload_0
	invokestatic	Method scala/reflect/ClassManifest$class.$init$:(Lscala/reflect/ClassManifest;)V
	aload_0
	invokestatic	Method scala/reflect/Manifest$class.$init$:(Lscala/reflect/Manifest;)V
	return
  Labels:
  LocalVariableTable: 
   Start  Length  Slot  Name   Signature
   0      28      0    this       Lscala/reflect/Manifest$ClassTypeManifest;
   0      28      1    prefix       Lscala/Option;
   0      28      2    erasure       Ljava/lang/Class;
   0      28      3    typeArguments       Lscala/collection/immutable/List;

  Signature: length = 0x2
   00 4C 

}

