Compiled from "Type.scala"
public class scala.reflect.MethodType extends scala.reflect.Type implements scala.ScalaObject,scala.Product,java.io.Serializable
  SourceFile: "Type.scala"
  ScalaSig: length = 0x3FE
   05 00 FFFFFF81 15 06 08 01 02 FFFFFF84 FFFFFF80 FFFFFF80 FFFFFF80 40 07 02 0A
   4D 65 74 68 6F 64 54 79 70 65 0A 02 03 04 01 07
   72 65 66 6C 65 63 74 0A 01 05 01 05 73 63 61 6C
   61 03 00 13 04 00 08 0C 10 10 02 09 0A 0D 01 02
   09 02 0B 02 02 04 54 79 70 65 10 02 0D 0E 0D 01
   04 09 02 0F 04 02 0B 53 63 61 6C 61 4F 62 6A 65
   63 74 10 02 0D 11 09 02 12 04 02 07 50 72 6F 64
   75 63 74 08 08 14 00 FFFFFF82 FFFFFFCA FFFFFF80 FFFFFF84 00 15 01 07 66
   6F 72 6D 61 6C 73 15 01 16 10 03 17 1C 1E 0D 01
   18 0A 02 19 1A 01 09 69 6D 6D 75 74 61 62 6C 65
   0A 02 1B 04 01 0A 63 6F 6C 6C 65 63 74 69 6F 6E
   09 02 1D 18 02 04 4C 69 73 74 10 02 09 1F 09 02
   20 02 02 06 53 79 6D 62 6F 6C 08 08 22 00 FFFFFF82 FFFFFF88
   FFFFFFA0 FFFFFF80 04 16 01 08 66 6F 72 6D 61 6C 73 20 08 08
   24 00 FFFFFF82 FFFFFFCA FFFFFF80 FFFFFF84 00 25 01 06 72 65 73 74 70 65
   15 01 08 08 08 27 00 FFFFFF82 FFFFFF88 FFFFFFA0 FFFFFF80 04 08 01 07 72
   65 73 74 70 65 20 08 05 29 00 FFFFFF84 00 2A 01 06 3C
   69 6E 69 74 3E 14 03 2B 2C 2D 10 02 09 00 08 05
   14 28 FFFFFFC0 00 16 08 05 24 28 FFFFFFC0 00 08 08 07 2F 00
   FFFFFF81 FFFFFF80 FFFFFF84 00 30 01 04 63 6F 70 79 14 03 2B 31 32
   08 07 14 2E FFFFFF90 FFFFFF80 FFFFFFC0 00 16 08 07 24 2E FFFFFF90 FFFFFF80 FFFFFFC0
   00 08 08 07 34 00 FFFFFF91 FFFFFF80 FFFFFF84 00 35 01 0E 63 6F 70
   79 24 64 65 66 61 75 6C 74 24 31 15 01 36 2A 02
   16 37 2B 01 38 10 02 39 3E 0D 01 3A 0A 02 3B 3C
   01 09 75 6E 63 68 65 63 6B 65 64 0A 02 3D 04 01
   0A 61 6E 6E 6F 74 61 74 69 6F 6E 09 02 3F 3A 02
   11 75 6E 63 68 65 63 6B 65 64 56 61 72 69 61 6E
   63 65 08 07 41 00 FFFFFF91 FFFFFF80 FFFFFF84 00 42 01 0E 63 6F 70
   79 24 64 65 66 61 75 6C 74 24 32 15 01 43 2A 02
   08 37 08 08 45 00 FFFFFF84 FFFFFF80 FFFFFF80 FFFFFF84 20 46 01 08 68 61
   73 68 43 6F 64 65 14 01 47 10 02 0D 48 09 02 49
   04 02 03 49 6E 74 08 08 4B 00 FFFFFF84 FFFFFF80 FFFFFF80 FFFFFF84 20 4C
   01 08 74 6F 53 74 72 69 6E 67 14 01 4D 10 02 4E
   51 0E 02 0D 4F 09 02 50 04 01 06 50 72 65 64 65
   66 09 02 52 53 02 06 53 74 72 69 6E 67 0A 02 50
   04 08 08 55 00 FFFFFF84 FFFFFF80 FFFFFF80 FFFFFF84 20 56 01 06 65 71 75
   61 6C 73 14 02 57 5A 10 02 0D 58 09 02 59 04 02
   07 42 6F 6F 6C 65 61 6E 08 07 5B 54 FFFFFF81 FFFFFF80 FFFFFFC0 00
   5C 01 03 78 24 31 10 02 0D 5D 09 02 5E 04 02 03
   41 6E 79 08 08 60 00 FFFFFF84 FFFFFF80 FFFFFF80 FFFFFF84 20 61 01 0D 70
   72 6F 64 75 63 74 50 72 65 66 69 78 15 01 62 10
   02 63 68 0D 01 64 0A 02 65 66 01 04 6C 61 6E 67
   0A 01 67 01 04 6A 61 76 61 09 02 52 64 08 08 6A
   00 FFFFFF84 FFFFFF80 FFFFFF80 FFFFFF84 20 6B 01 0C 70 72 6F 64 75 63 74
   41 72 69 74 79 15 01 47 08 08 6D 00 FFFFFF84 FFFFFF80 FFFFFF80 FFFFFF84
   20 6E 01 0E 70 72 6F 64 75 63 74 45 6C 65 6D 65
   6E 74 14 02 5C 6F 08 07 5B 6C FFFFFF81 FFFFFF80 FFFFFFC0 00 47 08
   08 71 00 FFFFFF84 FFFFFF80 FFFFFF80 FFFFFF84 20 72 01 08 63 61 6E 45 71
   75 61 6C 14 02 57 73 08 07 5B 70 FFFFFF81 FFFFFF80 FFFFFFC0 00 5C
   28 02 00 75 10 02 0D 76 09 02 77 04 02 0C 73 65
   72 69 61 6C 69 7A 61 62 6C 65 07 07 79 02 FFFFFF81 FFFFFF80
   FFFFFF88 02 7A 01 0A 4D 65 74 68 6F 64 54 79 70 65 10
   02 09 7B 06 08 01 02 FFFFFF84 FFFFFF81 FFFFFF80 FFFFFF88 02 7C 13 05 7B
   7D FFFFFF81 00 0C 10 02 63 7E 09 02 7F 64 02 06 4F 62
   6A 65 63 74 10 06 0D FFFFFF81 01 16 08 2B 09 03 FFFFFF81 02
   04 02 09 46 75 6E 63 74 69 6F 6E 32 08 06 29 7B
   FFFFFF84 00 FFFFFF81 04 14 01 7A 08 09 FFFFFF81 06 7B FFFFFF81 FFFFFF80 FFFFFF84 40
   FFFFFF81 07 01 05 61 70 70 6C 79 14 05 2B FFFFFF81 08 FFFFFF81 09
   08 06 14 FFFFFF81 05 FFFFFFC0 00 16 08 06 24 FFFFFF81 05 FFFFFFC0 00 08
   08 09 FFFFFF81 0B 7B FFFFFF81 FFFFFF80 FFFFFF84 40 FFFFFF81 0C 01 07 75 6E 61
   70 70 6C 79 14 04 FFFFFF81 0D FFFFFF81 13 10 05 0D FFFFFF81 0E FFFFFF81
   10 09 03 FFFFFF81 0F 04 02 04 53 6F 6D 65 10 05 0D FFFFFF81
   11 16 08 09 03 FFFFFF81 12 04 02 06 54 75 70 6C 65 32
   08 07 FFFFFF81 14 FFFFFF81 0A FFFFFFC0 00 2B 01 03 78 24 30 
  minor version: 0
  major version: 49
  Constant pool:
Asciz	SourceFile;
Asciz	Type.scala;
Asciz	tupled;
Asciz	()Lscala/Function1;;
Asciz	Code;
Asciz	scala/reflect/MethodType$;
class	scala/reflect/MethodType$
Asciz	MODULE$;
Asciz	Lscala/reflect/MethodType$;;
NameAndType	MODULE$:Lscala/reflect/MethodType$;
Field	scala/reflect/MethodType$.MODULE$:Lscala/reflect/MethodType$;
NameAndType	tupled:()Lscala/Function1;
Method	scala/reflect/MethodType$.tupled:()Lscala/Function1;
Asciz	curry;
NameAndType	curry:()Lscala/Function1;
Method	scala/reflect/MethodType$.curry:()Lscala/Function1;
Asciz	Deprecated;
Asciz	curried;
NameAndType	curried:()Lscala/Function1;
Method	scala/reflect/MethodType$.curried:()Lscala/Function1;
Asciz	restpe;
Asciz	Lscala/reflect/Type;;
Asciz	formals;
Asciz	Lscala/collection/immutable/List;;
Asciz	Lscala/collection/immutable/List<Lscala/reflect/Symbol;>;;
Asciz	Signature;
Asciz	productIterator;
Asciz	()Lscala/collection/Iterator;;
Asciz	LineNumberTable;
Asciz	scala/Product$class;
class	scala/Product$class
Asciz	(Lscala/Product;)Lscala/collection/Iterator;;
NameAndType	productIterator:(Lscala/Product;)Lscala/collection/Iterator;
Method	scala/Product$class.productIterator:(Lscala/Product;)Lscala/collection/Iterator;
Asciz	productElements;
NameAndType	productElements:(Lscala/Product;)Lscala/collection/Iterator;
Method	scala/Product$class.productElements:(Lscala/Product;)Lscala/collection/Iterator;
Asciz	copy$default$2;
Asciz	()Lscala/reflect/Type;;
Asciz	scala/reflect/MethodType;
class	scala/reflect/MethodType
NameAndType	restpe:()Lscala/reflect/Type;
Method	scala/reflect/MethodType.restpe:()Lscala/reflect/Type;
Asciz	copy$default$1;
Asciz	()Lscala/collection/immutable/List;;
NameAndType	formals:()Lscala/collection/immutable/List;
Method	scala/reflect/MethodType.formals:()Lscala/collection/immutable/List;
NameAndType	formals:Lscala/collection/immutable/List;
Field	scala/reflect/MethodType.formals:Lscala/collection/immutable/List;
Asciz	()Lscala/collection/immutable/List<Lscala/reflect/Symbol;>;;
NameAndType	restpe:Lscala/reflect/Type;
Field	scala/reflect/MethodType.restpe:Lscala/reflect/Type;
Asciz	copy;
Asciz	(Lscala/collection/immutable/List;Lscala/reflect/Type;)Lscala/reflect/MethodType;;
Asciz	<init>;
Asciz	(Lscala/collection/immutable/List;Lscala/reflect/Type;)V;
NameAndType	"<init>":(Lscala/collection/immutable/List;Lscala/reflect/Type;)V
Method	scala/reflect/MethodType."<init>":(Lscala/collection/immutable/List;Lscala/reflect/Type;)V
Asciz	this;
Asciz	Lscala/reflect/MethodType;;
Asciz	LocalVariableTable;
Asciz	hashCode;
Asciz	()I;
Asciz	scala/runtime/ScalaRunTime$;
class	scala/runtime/ScalaRunTime$
Asciz	Lscala/runtime/ScalaRunTime$;;
NameAndType	MODULE$:Lscala/runtime/ScalaRunTime$;
Field	scala/runtime/ScalaRunTime$.MODULE$:Lscala/runtime/ScalaRunTime$;
Asciz	_hashCode;
Asciz	(Lscala/Product;)I;
NameAndType	_hashCode:(Lscala/Product;)I
Method	scala/runtime/ScalaRunTime$._hashCode:(Lscala/Product;)I
Asciz	toString;
Asciz	()Ljava/lang/String;;
Asciz	_toString;
Asciz	(Lscala/Product;)Ljava/lang/String;;
NameAndType	_toString:(Lscala/Product;)Ljava/lang/String;
Method	scala/runtime/ScalaRunTime$._toString:(Lscala/Product;)Ljava/lang/String;
Asciz	equals;
Asciz	(Ljava/lang/Object;)Z;
Asciz	gd7$1;
Asciz	(Lscala/collection/immutable/List;Lscala/reflect/Type;)Z;
NameAndType	gd7$1:(Lscala/collection/immutable/List;Lscala/reflect/Type;)Z
Method	scala/reflect/MethodType.gd7$1:(Lscala/collection/immutable/List;Lscala/reflect/Type;)Z
Asciz	scala/Equals;
class	scala/Equals
Asciz	canEqual;
NameAndType	canEqual:(Ljava/lang/Object;)Z
InterfaceMethod	scala/Equals.canEqual:(Ljava/lang/Object;)Z
Asciz	temp32;
Asciz	temp33;
Asciz	temp34;
Asciz	productPrefix;
Asciz	MethodType;
String	MethodType
Asciz	productArity;
Asciz	productElement;
Asciz	(I)Ljava/lang/Object;;
Asciz	java/lang/IndexOutOfBoundsException;
class	java/lang/IndexOutOfBoundsException
Asciz	scala/runtime/BoxesRunTime;
class	scala/runtime/BoxesRunTime
Asciz	boxToInteger;
Asciz	(I)Ljava/lang/Integer;;
NameAndType	boxToInteger:(I)Ljava/lang/Integer;
Method	scala/runtime/BoxesRunTime.boxToInteger:(I)Ljava/lang/Integer;
Asciz	java/lang/Object;
class	java/lang/Object
NameAndType	toString:()Ljava/lang/String;
Method	java/lang/Object.toString:()Ljava/lang/String;
Asciz	(Ljava/lang/String;)V;
NameAndType	"<init>":(Ljava/lang/String;)V
Method	java/lang/IndexOutOfBoundsException."<init>":(Ljava/lang/String;)V
NameAndType	equals:(Ljava/lang/Object;)Z
Method	java/lang/Object.equals:(Ljava/lang/Object;)Z
Asciz	scala/reflect/Type;
class	scala/reflect/Type
Asciz	()V;
NameAndType	"<init>":()V
Method	scala/reflect/Type."<init>":()V
Asciz	$init$;
Asciz	(Lscala/Product;)V;
NameAndType	$init$:(Lscala/Product;)V
Method	scala/Product$class.$init$:(Lscala/Product;)V
Asciz	(Lscala/collection/immutable/List<Lscala/reflect/Symbol;>;Lscala/reflect/Type;)V;
Asciz	ScalaSig;
Asciz	scala/ScalaObject;
class	scala/ScalaObject
Asciz	scala/Product;
class	scala/Product
Asciz	java/io/Serializable;
class	java/io/Serializable

{
private final scala.reflect.Type restpe;
  Signature: Lscala/reflect/Type;

private final scala.collection.immutable.List formals;
  Signature: Lscala/collection/immutable/List;
  Signature: length = 0x2
   00 19 

public static final scala.Function1 tupled();
  Signature: ()Lscala/Function1;
  Code:
   Stack=1, Locals=0, Args_size=0
	getstatic	Field scala/reflect/MethodType$.MODULE$:Lscala/reflect/MethodType$;
	invokevirtual	Method scala/reflect/MethodType$.tupled:()Lscala/Function1;
	areturn
  Labels:

public static final scala.Function1 curry();
  Signature: ()Lscala/Function1;
  Code:
   Stack=1, Locals=0, Args_size=0
	getstatic	Field scala/reflect/MethodType$.MODULE$:Lscala/reflect/MethodType$;
	invokevirtual	Method scala/reflect/MethodType$.curry:()Lscala/Function1;
	areturn
  Labels:
  Deprecated: true

public static final scala.Function1 curried();
  Signature: ()Lscala/Function1;
  Code:
   Stack=1, Locals=0, Args_size=0
	getstatic	Field scala/reflect/MethodType$.MODULE$:Lscala/reflect/MethodType$;
	invokevirtual	Method scala/reflect/MethodType$.curried:()Lscala/Function1;
	areturn
  Labels:

public scala.collection.Iterator productIterator();
  Signature: ()Lscala/collection/Iterator;
  Code:
   Stack=1, Locals=1, Args_size=1
	aload_0
	invokestatic	Method scala/Product$class.productIterator:(Lscala/Product;)Lscala/collection/Iterator;
	areturn
  Labels:

public scala.collection.Iterator productElements();
  Signature: ()Lscala/collection/Iterator;
  Code:
   Stack=1, Locals=1, Args_size=1
	aload_0
	invokestatic	Method scala/Product$class.productElements:(Lscala/Product;)Lscala/collection/Iterator;
	areturn
  Labels:
  Deprecated: true

public scala.reflect.Type copy$default$2();
  Signature: ()Lscala/reflect/Type;
  Code:
   Stack=1, Locals=1, Args_size=1
	aload_0
	invokevirtual	Method restpe:()Lscala/reflect/Type;
	areturn
  Labels:

public scala.collection.immutable.List copy$default$1();
  Signature: ()Lscala/collection/immutable/List;
  Code:
   Stack=1, Locals=1, Args_size=1
	aload_0
	invokevirtual	Method formals:()Lscala/collection/immutable/List;
	areturn
  Labels:

public scala.collection.immutable.List formals();
  Signature: ()Lscala/collection/immutable/List;
  Code:
   Stack=1, Locals=1, Args_size=1
	aload_0
	getfield	Field formals:Lscala/collection/immutable/List;
	areturn
  Labels:
  Signature: length = 0x2
   00 32 

public scala.reflect.Type restpe();
  Signature: ()Lscala/reflect/Type;
  Code:
   Stack=1, Locals=1, Args_size=1
	aload_0
	getfield	Field restpe:Lscala/reflect/Type;
	areturn
  Labels:

public scala.reflect.MethodType copy(scala.collection.immutable.List, scala.reflect.Type);
  Signature: (Lscala/collection/immutable/List;Lscala/reflect/Type;)Lscala/reflect/MethodType;
  Code:
   Stack=4, Locals=3, Args_size=3
	new	class scala/reflect/MethodType
	dup
	aload_1
	aload_2
	invokespecial	Method "<init>":(Lscala/collection/immutable/List;Lscala/reflect/Type;)V
	areturn
  Labels:
  LocalVariableTable: 
   Start  Length  Slot  Name   Signature
   0      10      0    this       Lscala/reflect/MethodType;
   0      10      1    formals       Lscala/collection/immutable/List;
   0      10      2    restpe       Lscala/reflect/Type;


public int hashCode();
  Signature: ()I
  Code:
   Stack=2, Locals=1, Args_size=1
	getstatic	Field scala/runtime/ScalaRunTime$.MODULE$:Lscala/runtime/ScalaRunTime$;
	aload_0
	invokevirtual	Method scala/runtime/ScalaRunTime$._hashCode:(Lscala/Product;)I
	ireturn
  Labels:

public java.lang.String toString();
  Signature: ()Ljava/lang/String;
  Code:
   Stack=2, Locals=1, Args_size=1
	getstatic	Field scala/runtime/ScalaRunTime$.MODULE$:Lscala/runtime/ScalaRunTime$;
	aload_0
	invokevirtual	Method scala/runtime/ScalaRunTime$._toString:(Lscala/Product;)Ljava/lang/String;
	areturn
  Labels:

public boolean equals(java.lang.Object);
  Signature: (Ljava/lang/Object;)Z
  Code:
   Stack=3, Locals=5, Args_size=2
	aload_0
	aload_1
	if_acmpeq	l1 // iconst_1
	aload_1
	instanceof	class scala/reflect/MethodType
	ifeq	l2 // iconst_0
	aload_1
	checkcast	class scala/reflect/MethodType
	astore_2
	aload_2
	invokevirtual	Method formals:()Lscala/collection/immutable/List;
	astore_3
	aload_2
	invokevirtual	Method restpe:()Lscala/reflect/Type;
	astore	4
	aload_0
	aload_3
	aload	4
	invokespecial	Method gd7$1:(Lscala/collection/immutable/List;Lscala/reflect/Type;)Z
	ifeq	l3 // iconst_0
	aload_1
	checkcast	class scala/reflect/MethodType
	aload_0
	invokeinterface	InterfaceMethod scala/Equals.canEqual:(Ljava/lang/Object;)Z
	goto	l4 // ifeq
l3	iconst_0
	goto	l4 // ifeq
l2	iconst_0
l4	ifeq	l5 // iconst_0
l1	iconst_1
	goto	l6 // ireturn
l5	iconst_0
l6	ireturn
  Labels:
   	l3 = 51 // iconst_0
   	l2 = 55 // iconst_0
   	l4 = 56 // ifeq
   	l1 = 59 // iconst_1
   	l5 = 63 // iconst_0
   	l6 = 64 // ireturn
  LocalVariableTable: 
   Start  Length  Slot  Name   Signature
   0      65      0    this       Lscala/reflect/MethodType;
   17      38      2    temp32       Lscala/reflect/MethodType;
   22      33      3    temp33       Lscala/collection/immutable/List;
   28      27      4    temp34       Lscala/reflect/Type;


public java.lang.String productPrefix();
  Signature: ()Ljava/lang/String;
  Code:
   Stack=1, Locals=1, Args_size=1
	ldc	String MethodType
	areturn
  Labels:

public int productArity();
  Signature: ()I
  Code:
   Stack=1, Locals=1, Args_size=1
	iconst_2
	ireturn
  Labels:

public java.lang.Object productElement(int);
  Signature: (I)Ljava/lang/Object;
  Code:
   Stack=3, Locals=2, Args_size=2
	iload_1
	tableswitch{ //0 to 1
		0: 46;
		1: 39;
		default: 24 }
	new	class java/lang/IndexOutOfBoundsException
	dup
	iload_1
	invokestatic	Method scala/runtime/BoxesRunTime.boxToInteger:(I)Ljava/lang/Integer;
	invokevirtual	Method java/lang/Object.toString:()Ljava/lang/String;
	invokespecial	Method java/lang/IndexOutOfBoundsException."<init>":(Ljava/lang/String;)V
	athrow
	aload_0
	invokevirtual	Method restpe:()Lscala/reflect/Type;
	goto	l1 // areturn
	aload_0
	invokevirtual	Method formals:()Lscala/collection/immutable/List;
l1	areturn
  Labels:
   	l1 = 50 // areturn

public boolean canEqual(java.lang.Object);
  Signature: (Ljava/lang/Object;)Z
  Code:
   Stack=1, Locals=2, Args_size=2
	aload_1
	instanceof	class scala/reflect/MethodType
	ireturn
  Labels:

private final boolean gd7$1(scala.collection.immutable.List, scala.reflect.Type);
  Signature: (Lscala/collection/immutable/List;Lscala/reflect/Type;)Z
  Code:
   Stack=2, Locals=5, Args_size=3
	aload_1
	aload_0
	invokevirtual	Method formals:()Lscala/collection/immutable/List;
	astore_3
	dup
	ifnonnull	l1 // aload_3
	pop
	aload_3
	ifnull	l2 // aload_2
	goto	l3 // iconst_0
l1	aload_3
	invokevirtual	Method java/lang/Object.equals:(Ljava/lang/Object;)Z
	ifeq	l3 // iconst_0
l2	aload_2
	aload_0
	invokevirtual	Method restpe:()Lscala/reflect/Type;
	astore	4
	dup
	ifnonnull	l4 // aload
	pop
	aload	4
	ifnull	l5 // iconst_1
	goto	l3 // iconst_0
l4	aload	4
	invokevirtual	Method java/lang/Object.equals:(Ljava/lang/Object;)Z
	ifeq	l3 // iconst_0
l5	iconst_1
	goto	l6 // ireturn
l3	iconst_0
l6	ireturn
  Labels:
   	l1 = 18 // aload_3
   	l2 = 25 // aload_2
   	l4 = 45 // aload
   	l5 = 53 // iconst_1
   	l3 = 57 // iconst_0
   	l6 = 58 // ireturn

public scala.reflect.MethodType(scala.collection.immutable.List, scala.reflect.Type);
  Signature: (Lscala/collection/immutable/List;Lscala/reflect/Type;)V
  Code:
   Stack=2, Locals=3, Args_size=3
	aload_0
	aload_1
	putfield	Field formals:Lscala/collection/immutable/List;
	aload_0
	aload_2
	putfield	Field restpe:Lscala/reflect/Type;
	aload_0
	invokespecial	Method scala/reflect/Type."<init>":()V
	aload_0
	invokestatic	Method scala/Product$class.$init$:(Lscala/Product;)V
	return
  Labels:
  LocalVariableTable: 
   Start  Length  Slot  Name   Signature
   0      19      0    this       Lscala/reflect/MethodType;
   0      19      1    formals       Lscala/collection/immutable/List;
   0      19      2    restpe       Lscala/reflect/Type;

  Signature: length = 0x2
   00 7D 

}

