Compiled from "Type.scala"
public final class scala.reflect.MethodType$ extends java.lang.Object implements scala.Function2,scala.ScalaObject
  SourceFile: "Type.scala"
  Scala: length = 0x
   
  minor version: 0
  major version: 49
  Constant pool:
Asciz	SourceFile;
Asciz	Type.scala;
Asciz	Scala;
Asciz	MODULE$;
Asciz	Lscala/reflect/MethodType$;;
Asciz	<clinit>;
Asciz	()V;
Asciz	Code;
Asciz	scala/reflect/MethodType$;
class	scala/reflect/MethodType$
Asciz	<init>;
NameAndType	"<init>":()V
Method	scala/reflect/MethodType$."<init>":()V
Asciz	toString;
Asciz	()Ljava/lang/String;;
Asciz	LineNumberTable;
Asciz	scala/Function2$class;
class	scala/Function2$class
Asciz	(Lscala/Function2;)Ljava/lang/String;;
NameAndType	toString:(Lscala/Function2;)Ljava/lang/String;
Method	scala/Function2$class.toString:(Lscala/Function2;)Ljava/lang/String;
Asciz	curried;
Asciz	()Lscala/Function1;;
Asciz	(Lscala/Function2;)Lscala/Function1;;
NameAndType	curried:(Lscala/Function2;)Lscala/Function1;
Method	scala/Function2$class.curried:(Lscala/Function2;)Lscala/Function1;
Asciz	curry;
NameAndType	curry:(Lscala/Function2;)Lscala/Function1;
Method	scala/Function2$class.curry:(Lscala/Function2;)Lscala/Function1;
Asciz	Deprecated;
Asciz	tupled;
NameAndType	tupled:(Lscala/Function2;)Lscala/Function1;
Method	scala/Function2$class.tupled:(Lscala/Function2;)Lscala/Function1;
Asciz	unapply;
Asciz	(Lscala/reflect/MethodType;)Lscala/Some;;
Asciz	scala/Some;
class	scala/Some
Asciz	scala/Tuple2;
class	scala/Tuple2
Asciz	scala/reflect/MethodType;
class	scala/reflect/MethodType
Asciz	formals;
Asciz	()Lscala/collection/immutable/List;;
NameAndType	formals:()Lscala/collection/immutable/List;
Method	scala/reflect/MethodType.formals:()Lscala/collection/immutable/List;
Asciz	restpe;
Asciz	()Lscala/reflect/Type;;
NameAndType	restpe:()Lscala/reflect/Type;
Method	scala/reflect/MethodType.restpe:()Lscala/reflect/Type;
Asciz	(Ljava/lang/Object;Ljava/lang/Object;)V;
NameAndType	"<init>":(Ljava/lang/Object;Ljava/lang/Object;)V
Method	scala/Tuple2."<init>":(Ljava/lang/Object;Ljava/lang/Object;)V
Asciz	(Ljava/lang/Object;)V;
NameAndType	"<init>":(Ljava/lang/Object;)V
Method	scala/Some."<init>":(Ljava/lang/Object;)V
Asciz	this;
Asciz	x$0;
Asciz	Lscala/reflect/MethodType;;
Asciz	LocalVariableTable;
Asciz	apply;
Asciz	(Lscala/collection/immutable/List;Lscala/reflect/Type;)Lscala/reflect/MethodType;;
Asciz	(Lscala/collection/immutable/List;Lscala/reflect/Type;)V;
NameAndType	"<init>":(Lscala/collection/immutable/List;Lscala/reflect/Type;)V
Method	scala/reflect/MethodType."<init>":(Lscala/collection/immutable/List;Lscala/reflect/Type;)V
Asciz	Lscala/collection/immutable/List;;
Asciz	Lscala/reflect/Type;;
Asciz	(Ljava/lang/Object;Ljava/lang/Object;)Ljava/lang/Object;;
Asciz	scala/collection/immutable/List;
class	scala/collection/immutable/List
Asciz	scala/reflect/Type;
class	scala/reflect/Type
NameAndType	apply:(Lscala/collection/immutable/List;Lscala/reflect/Type;)Lscala/reflect/MethodType;
Method	scala/reflect/MethodType$.apply:(Lscala/collection/immutable/List;Lscala/reflect/Type;)Lscala/reflect/MethodType;
Asciz	v1;
Asciz	Ljava/lang/Object;;
Asciz	v2;
Asciz	java/lang/Object;
class	java/lang/Object
Method	java/lang/Object."<init>":()V
NameAndType	MODULE$:Lscala/reflect/MethodType$;
Field	scala/reflect/MethodType$.MODULE$:Lscala/reflect/MethodType$;
Asciz	$init$;
Asciz	(Lscala/Function2;)V;
NameAndType	$init$:(Lscala/Function2;)V
Method	scala/Function2$class.$init$:(Lscala/Function2;)V
Asciz	scala/Function2;
class	scala/Function2
Asciz	scala/ScalaObject;
class	scala/ScalaObject

{
public static final scala.reflect.MethodType$ MODULE$;
  Signature: Lscala/reflect/MethodType$;

public static {};
  Signature: ()V
  Code:
   Stack=1, Locals=0, Args_size=0
	new	class scala/reflect/MethodType$
	invokespecial	Method "<init>":()V
	return
  Labels:

public java.lang.String toString();
  Signature: ()Ljava/lang/String;
  Code:
   Stack=1, Locals=1, Args_size=1
	aload_0
	invokestatic	Method scala/Function2$class.toString:(Lscala/Function2;)Ljava/lang/String;
	areturn
  Labels:

public scala.Function1 curried();
  Signature: ()Lscala/Function1;
  Code:
   Stack=1, Locals=1, Args_size=1
	aload_0
	invokestatic	Method scala/Function2$class.curried:(Lscala/Function2;)Lscala/Function1;
	areturn
  Labels:

public scala.Function1 curry();
  Signature: ()Lscala/Function1;
  Code:
   Stack=1, Locals=1, Args_size=1
	aload_0
	invokestatic	Method scala/Function2$class.curry:(Lscala/Function2;)Lscala/Function1;
	areturn
  Labels:
  Deprecated: true

public scala.Function1 tupled();
  Signature: ()Lscala/Function1;
  Code:
   Stack=1, Locals=1, Args_size=1
	aload_0
	invokestatic	Method scala/Function2$class.tupled:(Lscala/Function2;)Lscala/Function1;
	areturn
  Labels:

public scala.Some unapply(scala.reflect.MethodType);
  Signature: (Lscala/reflect/MethodType;)Lscala/Some;
  Code:
   Stack=6, Locals=2, Args_size=2
	new	class scala/Some
	dup
	new	class scala/Tuple2
	dup
	aload_1
	invokevirtual	Method scala/reflect/MethodType.formals:()Lscala/collection/immutable/List;
	aload_1
	invokevirtual	Method scala/reflect/MethodType.restpe:()Lscala/reflect/Type;
	invokespecial	Method scala/Tuple2."<init>":(Ljava/lang/Object;Ljava/lang/Object;)V
	invokespecial	Method scala/Some."<init>":(Ljava/lang/Object;)V
	areturn
  Labels:
  LocalVariableTable: 
   Start  Length  Slot  Name   Signature
   0      23      0    this       Lscala/reflect/MethodType$;
   0      23      1    x$0       Lscala/reflect/MethodType;


public scala.reflect.MethodType apply(scala.collection.immutable.List, scala.reflect.Type);
  Signature: (Lscala/collection/immutable/List;Lscala/reflect/Type;)Lscala/reflect/MethodType;
  Code:
   Stack=4, Locals=3, Args_size=3
	new	class scala/reflect/MethodType
	dup
	aload_1
	aload_2
	invokespecial	Method scala/reflect/MethodType."<init>":(Lscala/collection/immutable/List;Lscala/reflect/Type;)V
	areturn
  Labels:
  LocalVariableTable: 
   Start  Length  Slot  Name   Signature
   0      10      0    this       Lscala/reflect/MethodType$;
   0      10      1    formals       Lscala/collection/immutable/List;
   0      10      2    restpe       Lscala/reflect/Type;


public java.lang.Object apply(java.lang.Object, java.lang.Object);
  Signature: (Ljava/lang/Object;Ljava/lang/Object;)Ljava/lang/Object;
  Code:
   Stack=3, Locals=3, Args_size=3
	aload_0
	aload_1
	checkcast	class scala/collection/immutable/List
	aload_2
	checkcast	class scala/reflect/Type
	invokevirtual	Method apply:(Lscala/collection/immutable/List;Lscala/reflect/Type;)Lscala/reflect/MethodType;
	areturn
  Labels:
  LocalVariableTable: 
   Start  Length  Slot  Name   Signature
   0      13      0    this       Lscala/reflect/MethodType$;
   0      13      1    v1       Ljava/lang/Object;
   0      13      2    v2       Ljava/lang/Object;


private scala.reflect.MethodType$();
  Signature: ()V
  Code:
   Stack=1, Locals=1, Args_size=1
	aload_0
	invokespecial	Method java/lang/Object."<init>":()V
	aload_0
	putstatic	Field MODULE$:Lscala/reflect/MethodType$;
	aload_0
	invokestatic	Method scala/Function2$class.$init$:(Lscala/Function2;)V
	return
  Labels:

}

