Compiled from "Symbol.scala"
public class scala.reflect.Method extends scala.reflect.GlobalSymbol implements scala.ScalaObject,scala.Product,java.io.Serializable
  SourceFile: "Symbol.scala"
  ScalaSig: length = 0x3
   05 00 00 
  RuntimeVisibleAnnotations: length = 0xB
   00 01 00 7E 00 01 00 7F 73 00 FFFFFF80 
  minor version: 0
  major version: 49
  Constant pool:
Asciz	SourceFile;
Asciz	Symbol.scala;
Asciz	tupled;
Asciz	()Lscala/Function1;;
Asciz	Code;
Asciz	scala/reflect/Method$;
class	scala/reflect/Method$
Asciz	MODULE$;
Asciz	Lscala/reflect/Method$;;
NameAndType	MODULE$:Lscala/reflect/Method$;
Field	scala/reflect/Method$.MODULE$:Lscala/reflect/Method$;
NameAndType	tupled:()Lscala/Function1;
Method	scala/reflect/Method$.tupled:()Lscala/Function1;
Asciz	curry;
NameAndType	curry:()Lscala/Function1;
Method	scala/reflect/Method$.curry:()Lscala/Function1;
Asciz	Deprecated;
Asciz	curried;
NameAndType	curried:()Lscala/Function1;
Method	scala/reflect/Method$.curried:()Lscala/Function1;
Asciz	tpe;
Asciz	Lscala/reflect/Type;;
Asciz	productElementName;
Asciz	(I)Ljava/lang/String;;
Asciz	LineNumberTable;
Asciz	scala/Product$class;
class	scala/Product$class
Asciz	(Lscala/Product;I)Ljava/lang/String;;
NameAndType	productElementName:(Lscala/Product;I)Ljava/lang/String;
Method	scala/Product$class.productElementName:(Lscala/Product;I)Ljava/lang/String;
Asciz	this;
Asciz	Lscala/reflect/Method;;
Asciz	n;
Asciz	I;
Asciz	LocalVariableTable;
Asciz	productIterator;
Asciz	()Lscala/collection/Iterator;;
Asciz	(Lscala/Product;)Lscala/collection/Iterator;;
NameAndType	productIterator:(Lscala/Product;)Lscala/collection/Iterator;
Method	scala/Product$class.productIterator:(Lscala/Product;)Lscala/collection/Iterator;
Asciz	productElements;
NameAndType	productElements:(Lscala/Product;)Lscala/collection/Iterator;
Method	scala/Product$class.productElements:(Lscala/Product;)Lscala/collection/Iterator;
Asciz	copy$default$2;
Asciz	()Lscala/reflect/Type;;
Asciz	scala/reflect/Method;
class	scala/reflect/Method
NameAndType	tpe:()Lscala/reflect/Type;
Method	scala/reflect/Method.tpe:()Lscala/reflect/Type;
Asciz	copy$default$1;
Asciz	()Ljava/lang/String;;
Asciz	fullname;
NameAndType	fullname:()Ljava/lang/String;
Method	scala/reflect/Method.fullname:()Ljava/lang/String;
Asciz	scala/reflect/GlobalSymbol;
class	scala/reflect/GlobalSymbol
Method	scala/reflect/GlobalSymbol.fullname:()Ljava/lang/String;
NameAndType	tpe:Lscala/reflect/Type;
Field	scala/reflect/Method.tpe:Lscala/reflect/Type;
Asciz	copy;
Asciz	(Ljava/lang/String;Lscala/reflect/Type;)Lscala/reflect/Method;;
Asciz	<init>;
Asciz	(Ljava/lang/String;Lscala/reflect/Type;)V;
NameAndType	"<init>":(Ljava/lang/String;Lscala/reflect/Type;)V
Method	scala/reflect/Method."<init>":(Ljava/lang/String;Lscala/reflect/Type;)V
Asciz	Ljava/lang/String;;
Asciz	hashCode;
Asciz	()I;
Asciz	scala/runtime/ScalaRunTime$;
class	scala/runtime/ScalaRunTime$
Asciz	Lscala/runtime/ScalaRunTime$;;
NameAndType	MODULE$:Lscala/runtime/ScalaRunTime$;
Field	scala/runtime/ScalaRunTime$.MODULE$:Lscala/runtime/ScalaRunTime$;
Asciz	_hashCode;
Asciz	(Lscala/Product;)I;
NameAndType	_hashCode:(Lscala/Product;)I
Method	scala/runtime/ScalaRunTime$._hashCode:(Lscala/Product;)I
Asciz	toString;
Asciz	_toString;
Asciz	(Lscala/Product;)Ljava/lang/String;;
NameAndType	_toString:(Lscala/Product;)Ljava/lang/String;
Method	scala/runtime/ScalaRunTime$._toString:(Lscala/Product;)Ljava/lang/String;
Asciz	equals;
Asciz	(Ljava/lang/Object;)Z;
Asciz	gd2$1;
Asciz	(Ljava/lang/String;Lscala/reflect/Type;)Z;
NameAndType	gd2$1:(Ljava/lang/String;Lscala/reflect/Type;)Z
Method	scala/reflect/Method.gd2$1:(Ljava/lang/String;Lscala/reflect/Type;)Z
Asciz	scala/Equals;
class	scala/Equals
Asciz	canEqual;
NameAndType	canEqual:(Ljava/lang/Object;)Z
InterfaceMethod	scala/Equals.canEqual:(Ljava/lang/Object;)Z
Asciz	temp6;
Asciz	temp7;
Asciz	temp8;
Asciz	productPrefix;
Asciz	Method;
String	Method
Asciz	productArity;
Asciz	productElement;
Asciz	(I)Ljava/lang/Object;;
Asciz	java/lang/IndexOutOfBoundsException;
class	java/lang/IndexOutOfBoundsException
Asciz	scala/runtime/BoxesRunTime;
class	scala/runtime/BoxesRunTime
Asciz	boxToInteger;
Asciz	(I)Ljava/lang/Integer;;
NameAndType	boxToInteger:(I)Ljava/lang/Integer;
Method	scala/runtime/BoxesRunTime.boxToInteger:(I)Ljava/lang/Integer;
Asciz	java/lang/Object;
class	java/lang/Object
NameAndType	toString:()Ljava/lang/String;
Method	java/lang/Object.toString:()Ljava/lang/String;
Asciz	(Ljava/lang/String;)V;
NameAndType	"<init>":(Ljava/lang/String;)V
Method	java/lang/IndexOutOfBoundsException."<init>":(Ljava/lang/String;)V
NameAndType	equals:(Ljava/lang/Object;)Z
Method	java/lang/Object.equals:(Ljava/lang/Object;)Z
Method	scala/reflect/GlobalSymbol."<init>":(Ljava/lang/String;)V
Asciz	$init$;
Asciz	(Lscala/Product;)V;
NameAndType	$init$:(Lscala/Product;)V
Method	scala/Product$class.$init$:(Lscala/Product;)V
Asciz	ScalaSig;
Asciz	Lscala/reflect/ScalaSignature;;
Asciz	bytes;
Asciz	uaC\t\tQ\r5+G[8e\tA!AsKdWm;\tQa]2bYa1CABA19En2bYNKXNY8m!\tia\"D\tyAAATGdm2kK$CA\tBAAQe>$Wo;\tQ!Q3ABU\tBZ;mY:W.Z-AqCaI!!\rAX\rZ3g\tYBDTiJLgn3ABIAF,H8b[B!\tA!f\na;qKV\t1\nI%QE)fX\r(\tE\t!$!/\t%A\rqJg.;?)\rYC&\tAQAYAQ!\tA\rBqa'd_BLHcA2e!9ACI1bB/!\ra\ti\t\n\"69w]=%I4-7uIE*A-]Z\tsyjAwq\n\"8dQ7.3u\"AC1o]>$\r^5p]&qHk:.Z2lK4M]5b],bB!#%\tAQG>\n3fM,H3+%FA8!)\"A\n25bg\"uZ3\"!%\n%#!aA%oi\"A1\nCC*u_N#(/8h)1(\tII(\rX/7t)\t6#&!>|G.Z1o!V*!AAU12!\tia+X\t\tI\=\teA!ABiQ:pIVG:fM&DX#A.qW\"A/y{7b]TYU4-;\"A1\rCC-qe>$Wo;Be&$0FH!1\"A\n:A9s_,8\r^#mK6,g+\"DqV3q\tk\t\"l!M\#rkdGC)m!.!AAUC#85yB91XM]5bY&TM7f(!!A\tMa!T3uQ>$CAu\r!\t!bA)8;ws2\"X<\nal&AB(cUGEuZ3&|\t\tIa)8di&|gN\rSQ$\t! g\"Aq^A\n\t!AbaBdF,\t)C}aC\"}1C\nQ\t\"!9QO\1qa2LHBA3R!DA'I1!!y^5p]B)Q\"!G%q\rQ+\33\tY\"aA-\n11;
Asciz	RuntimeVisibleAnnotations;
Asciz	scala/ScalaObject;
class	scala/ScalaObject
Asciz	scala/Product;
class	scala/Product
Asciz	java/io/Serializable;
class	java/io/Serializable

{
private final scala.reflect.Type tpe;
  Signature: Lscala/reflect/Type;

public static final scala.Function1 tupled();
  Signature: ()Lscala/Function1;
  Code:
   Stack=1, Locals=0, Args_size=0
	getstatic	Field scala/reflect/Method$.MODULE$:Lscala/reflect/Method$;
	invokevirtual	Method scala/reflect/Method$.tupled:()Lscala/Function1;
	areturn
  Labels:

public static final scala.Function1 curry();
  Signature: ()Lscala/Function1;
  Code:
   Stack=1, Locals=0, Args_size=0
	getstatic	Field scala/reflect/Method$.MODULE$:Lscala/reflect/Method$;
	invokevirtual	Method scala/reflect/Method$.curry:()Lscala/Function1;
	areturn
  Labels:
  Deprecated: true

public static final scala.Function1 curried();
  Signature: ()Lscala/Function1;
  Code:
   Stack=1, Locals=0, Args_size=0
	getstatic	Field scala/reflect/Method$.MODULE$:Lscala/reflect/Method$;
	invokevirtual	Method scala/reflect/Method$.curried:()Lscala/Function1;
	areturn
  Labels:

public java.lang.String productElementName(int);
  Signature: (I)Ljava/lang/String;
  Code:
   Stack=2, Locals=2, Args_size=2
	aload_0
	iload_1
	invokestatic	Method scala/Product$class.productElementName:(Lscala/Product;I)Ljava/lang/String;
	areturn
  Labels:
  LocalVariableTable: 
   Start  Length  Slot  Name   Signature
   0      6      0    this       Lscala/reflect/Method;
   0      6      1    n       I


public scala.collection.Iterator productIterator();
  Signature: ()Lscala/collection/Iterator;
  Code:
   Stack=1, Locals=1, Args_size=1
	aload_0
	invokestatic	Method scala/Product$class.productIterator:(Lscala/Product;)Lscala/collection/Iterator;
	areturn
  Labels:

public scala.collection.Iterator productElements();
  Signature: ()Lscala/collection/Iterator;
  Code:
   Stack=1, Locals=1, Args_size=1
	aload_0
	invokestatic	Method scala/Product$class.productElements:(Lscala/Product;)Lscala/collection/Iterator;
	areturn
  Labels:
  Deprecated: true

public scala.reflect.Type copy$default$2();
  Signature: ()Lscala/reflect/Type;
  Code:
   Stack=1, Locals=1, Args_size=1
	aload_0
	invokevirtual	Method tpe:()Lscala/reflect/Type;
	areturn
  Labels:

public java.lang.String copy$default$1();
  Signature: ()Ljava/lang/String;
  Code:
   Stack=1, Locals=1, Args_size=1
	aload_0
	invokevirtual	Method fullname:()Ljava/lang/String;
	areturn
  Labels:

public java.lang.String fullname();
  Signature: ()Ljava/lang/String;
  Code:
   Stack=1, Locals=1, Args_size=1
	aload_0
	invokespecial	Method scala/reflect/GlobalSymbol.fullname:()Ljava/lang/String;
	areturn
  Labels:

public scala.reflect.Type tpe();
  Signature: ()Lscala/reflect/Type;
  Code:
   Stack=1, Locals=1, Args_size=1
	aload_0
	getfield	Field tpe:Lscala/reflect/Type;
	areturn
  Labels:

public scala.reflect.Method copy(java.lang.String, scala.reflect.Type);
  Signature: (Ljava/lang/String;Lscala/reflect/Type;)Lscala/reflect/Method;
  Code:
   Stack=4, Locals=3, Args_size=3
	new	class scala/reflect/Method
	dup
	aload_1
	aload_2
	invokespecial	Method "<init>":(Ljava/lang/String;Lscala/reflect/Type;)V
	areturn
  Labels:
  LocalVariableTable: 
   Start  Length  Slot  Name   Signature
   0      10      0    this       Lscala/reflect/Method;
   0      10      1    fullname       Ljava/lang/String;
   0      10      2    tpe       Lscala/reflect/Type;


public int hashCode();
  Signature: ()I
  Code:
   Stack=2, Locals=1, Args_size=1
	getstatic	Field scala/runtime/ScalaRunTime$.MODULE$:Lscala/runtime/ScalaRunTime$;
	aload_0
	invokevirtual	Method scala/runtime/ScalaRunTime$._hashCode:(Lscala/Product;)I
	ireturn
  Labels:

public java.lang.String toString();
  Signature: ()Ljava/lang/String;
  Code:
   Stack=2, Locals=1, Args_size=1
	getstatic	Field scala/runtime/ScalaRunTime$.MODULE$:Lscala/runtime/ScalaRunTime$;
	aload_0
	invokevirtual	Method scala/runtime/ScalaRunTime$._toString:(Lscala/Product;)Ljava/lang/String;
	areturn
  Labels:

public boolean equals(java.lang.Object);
  Signature: (Ljava/lang/Object;)Z
  Code:
   Stack=3, Locals=5, Args_size=2
	aload_0
	aload_1
	if_acmpeq	l1 // iconst_1
	aload_1
	instanceof	class scala/reflect/Method
	ifeq	l2 // iconst_0
	aload_1
	checkcast	class scala/reflect/Method
	astore_2
	aload_2
	invokevirtual	Method fullname:()Ljava/lang/String;
	astore_3
	aload_2
	invokevirtual	Method tpe:()Lscala/reflect/Type;
	astore	4
	aload_0
	aload_3
	aload	4
	invokespecial	Method gd2$1:(Ljava/lang/String;Lscala/reflect/Type;)Z
	ifeq	l3 // iconst_0
	aload_1
	checkcast	class scala/reflect/Method
	aload_0
	invokeinterface	InterfaceMethod scala/Equals.canEqual:(Ljava/lang/Object;)Z
	goto	l4 // ifeq
l3	iconst_0
	goto	l4 // ifeq
l2	iconst_0
l4	ifeq	l5 // iconst_0
l1	iconst_1
	goto	l6 // ireturn
l5	iconst_0
l6	ireturn
  Labels:
   	l3 = 51 // iconst_0
   	l2 = 55 // iconst_0
   	l4 = 56 // ifeq
   	l1 = 59 // iconst_1
   	l5 = 63 // iconst_0
   	l6 = 64 // ireturn
  LocalVariableTable: 
   Start  Length  Slot  Name   Signature
   0      65      0    this       Lscala/reflect/Method;
   17      38      2    temp6       Lscala/reflect/Method;
   22      33      3    temp7       Ljava/lang/String;
   28      27      4    temp8       Lscala/reflect/Type;


public java.lang.String productPrefix();
  Signature: ()Ljava/lang/String;
  Code:
   Stack=1, Locals=1, Args_size=1
	ldc	String Method
	areturn
  Labels:

public int productArity();
  Signature: ()I
  Code:
   Stack=1, Locals=1, Args_size=1
	iconst_2
	ireturn
  Labels:

public java.lang.Object productElement(int);
  Signature: (I)Ljava/lang/Object;
  Code:
   Stack=3, Locals=2, Args_size=2
	iload_1
	tableswitch{ //0 to 1
		0: 46;
		1: 39;
		default: 24 }
	new	class java/lang/IndexOutOfBoundsException
	dup
	iload_1
	invokestatic	Method scala/runtime/BoxesRunTime.boxToInteger:(I)Ljava/lang/Integer;
	invokevirtual	Method java/lang/Object.toString:()Ljava/lang/String;
	invokespecial	Method java/lang/IndexOutOfBoundsException."<init>":(Ljava/lang/String;)V
	athrow
	aload_0
	invokevirtual	Method tpe:()Lscala/reflect/Type;
	goto	l1 // areturn
	aload_0
	invokevirtual	Method fullname:()Ljava/lang/String;
l1	areturn
  Labels:
   	l1 = 50 // areturn

public boolean canEqual(java.lang.Object);
  Signature: (Ljava/lang/Object;)Z
  Code:
   Stack=1, Locals=2, Args_size=2
	aload_1
	instanceof	class scala/reflect/Method
	ireturn
  Labels:

private final boolean gd2$1(java.lang.String, scala.reflect.Type);
  Signature: (Ljava/lang/String;Lscala/reflect/Type;)Z
  Code:
   Stack=2, Locals=5, Args_size=3
	aload_1
	aload_0
	invokevirtual	Method fullname:()Ljava/lang/String;
	astore_3
	dup
	ifnonnull	l1 // aload_3
	pop
	aload_3
	ifnull	l2 // aload_2
	goto	l3 // iconst_0
l1	aload_3
	invokevirtual	Method java/lang/Object.equals:(Ljava/lang/Object;)Z
	ifeq	l3 // iconst_0
l2	aload_2
	aload_0
	invokevirtual	Method tpe:()Lscala/reflect/Type;
	astore	4
	dup
	ifnonnull	l4 // aload
	pop
	aload	4
	ifnull	l5 // iconst_1
	goto	l3 // iconst_0
l4	aload	4
	invokevirtual	Method java/lang/Object.equals:(Ljava/lang/Object;)Z
	ifeq	l3 // iconst_0
l5	iconst_1
	goto	l6 // ireturn
l3	iconst_0
l6	ireturn
  Labels:
   	l1 = 18 // aload_3
   	l2 = 25 // aload_2
   	l4 = 45 // aload
   	l5 = 53 // iconst_1
   	l3 = 57 // iconst_0
   	l6 = 58 // ireturn

public scala.reflect.Method(java.lang.String, scala.reflect.Type);
  Signature: (Ljava/lang/String;Lscala/reflect/Type;)V
  Code:
   Stack=2, Locals=3, Args_size=3
	aload_0
	aload_2
	putfield	Field tpe:Lscala/reflect/Type;
	aload_0
	aload_1
	invokespecial	Method scala/reflect/GlobalSymbol."<init>":(Ljava/lang/String;)V
	aload_0
	invokestatic	Method scala/Product$class.$init$:(Lscala/Product;)V
	return
  Labels:
  LocalVariableTable: 
   Start  Length  Slot  Name   Signature
   0      15      0    this       Lscala/reflect/Method;
   0      15      1    fullname       Ljava/lang/String;
   0      15      2    tpe       Lscala/reflect/Type;


}

