Compiled from "Tree.scala"
public class scala.reflect.New extends scala.reflect.Tree implements scala.ScalaObject,scala.Product,java.io.Serializable
  SourceFile: "Tree.scala"
  ScalaSig: length = 0x31D
   05 00 7B 06 08 01 02 FFFFFF84 FFFFFF80 FFFFFF80 FFFFFF80 40 07 02 03 4E
   65 77 0A 02 03 04 01 07 72 65 66 6C 65 63 74 0A
   01 05 01 05 73 63 61 6C 61 03 00 13 04 00 08 0C
   10 10 02 09 0A 0D 01 02 09 02 0B 02 02 04 54 72
   65 65 10 02 0D 0E 0D 01 04 09 02 0F 04 02 0B 53
   63 61 6C 61 4F 62 6A 65 63 74 10 02 0D 11 09 02
   12 04 02 07 50 72 6F 64 75 63 74 08 08 14 00 FFFFFF82
   FFFFFFCA FFFFFF80 FFFFFF84 00 15 01 03 73 79 6D 15 01 08 08 08 17
   00 FFFFFF82 FFFFFF88 FFFFFFA0 FFFFFF80 04 08 01 04 73 79 6D 20 08 05 19
   00 FFFFFF84 00 1A 01 06 3C 69 6E 69 74 3E 14 02 1B 1C
   10 02 09 00 08 05 14 18 FFFFFFC0 00 08 08 07 1E 00 FFFFFF81
   FFFFFF80 FFFFFF84 00 1F 01 04 63 6F 70 79 14 02 1B 20 08 08
   21 14 1D FFFFFF90 FFFFFF80 FFFFFFC0 00 08 08 07 22 00 FFFFFF91 FFFFFF80 FFFFFF84 00
   23 01 0E 63 6F 70 79 24 64 65 66 61 75 6C 74 24
   31 15 01 24 2A 02 08 25 2B 01 26 10 02 27 2C 0D
   01 28 0A 02 29 2A 01 09 75 6E 63 68 65 63 6B 65
   64 0A 02 2B 04 01 0A 61 6E 6E 6F 74 61 74 69 6F
   6E 09 02 2D 28 02 11 75 6E 63 68 65 63 6B 65 64
   56 61 72 69 61 6E 63 65 08 08 2F 00 FFFFFF84 FFFFFF80 FFFFFF80 FFFFFF84
   20 30 01 08 68 61 73 68 43 6F 64 65 14 01 31 10
   02 0D 32 09 02 33 04 02 03 49 6E 74 08 08 35 00
   FFFFFF84 FFFFFF80 FFFFFF80 FFFFFF84 20 36 01 08 74 6F 53 74 72 69 6E 67
   14 01 37 10 02 38 3B 0E 02 0D 39 09 02 3A 04 01
   06 50 72 65 64 65 66 09 02 3C 3D 02 06 53 74 72
   69 6E 67 0A 02 3A 04 08 08 3F 00 FFFFFF84 FFFFFF80 FFFFFF80 FFFFFF84 20
   40 01 06 65 71 75 61 6C 73 14 02 41 44 10 02 0D
   42 09 02 43 04 02 07 42 6F 6F 6C 65 61 6E 08 07
   45 3E FFFFFF81 FFFFFF80 FFFFFFC0 00 46 01 03 78 24 31 10 02 0D 47
   09 02 48 04 02 03 41 6E 79 08 08 4A 00 FFFFFF84 FFFFFF80 FFFFFF80
   FFFFFF84 20 4B 01 0D 70 72 6F 64 75 63 74 50 72 65 66
   69 78 15 01 4C 10 02 4D 52 0D 01 4E 0A 02 4F 50
   01 04 6C 61 6E 67 0A 01 51 01 04 6A 61 76 61 09
   02 3C 4E 08 08 54 00 FFFFFF84 FFFFFF80 FFFFFF80 FFFFFF84 20 55 01 0C 70
   72 6F 64 75 63 74 41 72 69 74 79 15 01 31 08 08
   57 00 FFFFFF84 FFFFFF80 FFFFFF80 FFFFFF84 20 58 01 0E 70 72 6F 64 75 63
   74 45 6C 65 6D 65 6E 74 14 02 46 59 08 07 45 56
   FFFFFF81 FFFFFF80 FFFFFFC0 00 31 08 08 5B 00 FFFFFF84 FFFFFF80 FFFFFF80 FFFFFF84 20 5C 01
   08 63 61 6E 45 71 75 61 6C 14 02 41 5D 08 07 45
   5A FFFFFF81 FFFFFF80 FFFFFFC0 00 46 28 02 00 5F 10 02 0D 60 09 02
   61 04 02 0C 73 65 72 69 61 6C 69 7A 61 62 6C 65
   07 07 63 02 FFFFFF81 FFFFFF80 FFFFFF88 02 64 01 03 4E 65 77 10 02
   09 65 06 08 01 02 FFFFFF84 FFFFFF81 FFFFFF80 FFFFFF88 02 66 13 04 65 67
   6A 0C 10 02 4D 68 09 02 69 4E 02 06 4F 62 6A 65
   63 74 10 04 0D 6B 08 1B 09 02 6C 04 02 09 46 75
   6E 63 74 69 6F 6E 31 08 05 19 65 FFFFFF84 00 6E 14 01
   64 08 07 70 65 FFFFFF81 FFFFFF80 FFFFFF84 40 71 01 05 61 70 70 6C
   79 14 02 1B 72 08 05 14 6F FFFFFFC0 00 08 08 07 74 65
   FFFFFF81 FFFFFF80 FFFFFF84 40 75 01 07 75 6E 61 70 70 6C 79 14 02
   76 79 10 03 0D 77 08 09 02 78 04 02 04 53 6F 6D
   65 08 05 7A 73 FFFFFFC0 00 1B 01 03 78 24 30 
  minor version: 0
  major version: 49
  Constant pool:
Asciz	SourceFile;
Asciz	Tree.scala;
Asciz	andThen;
Asciz	(Lscala/Function1;)Lscala/Function1;;
Asciz	Code;
Asciz	scala/reflect/New$;
class	scala/reflect/New$
Asciz	MODULE$;
Asciz	Lscala/reflect/New$;;
NameAndType	MODULE$:Lscala/reflect/New$;
Field	scala/reflect/New$.MODULE$:Lscala/reflect/New$;
NameAndType	andThen:(Lscala/Function1;)Lscala/Function1;
Method	scala/reflect/New$.andThen:(Lscala/Function1;)Lscala/Function1;
Asciz	compose;
NameAndType	compose:(Lscala/Function1;)Lscala/Function1;
Method	scala/reflect/New$.compose:(Lscala/Function1;)Lscala/Function1;
Asciz	sym;
Asciz	Lscala/reflect/Tree;;
Asciz	<init>;
Asciz	(Lscala/reflect/Tree;)V;
Asciz	LineNumberTable;
Asciz	scala/reflect/New;
class	scala/reflect/New
NameAndType	sym:Lscala/reflect/Tree;
Field	scala/reflect/New.sym:Lscala/reflect/Tree;
Asciz	scala/reflect/Tree;
class	scala/reflect/Tree
Asciz	()V;
NameAndType	"<init>":()V
Method	scala/reflect/Tree."<init>":()V
Asciz	scala/Product$class;
class	scala/Product$class
Asciz	$init$;
Asciz	(Lscala/Product;)V;
NameAndType	$init$:(Lscala/Product;)V
Method	scala/Product$class.$init$:(Lscala/Product;)V
Asciz	this;
Asciz	Lscala/reflect/New;;
Asciz	LocalVariableTable;
Asciz	gd9$1;
Asciz	(Lscala/reflect/Tree;)Z;
Asciz	()Lscala/reflect/Tree;;
NameAndType	sym:()Lscala/reflect/Tree;
Method	scala/reflect/New.sym:()Lscala/reflect/Tree;
Asciz	java/lang/Object;
class	java/lang/Object
Asciz	equals;
Asciz	(Ljava/lang/Object;)Z;
NameAndType	equals:(Ljava/lang/Object;)Z
Method	java/lang/Object.equals:(Ljava/lang/Object;)Z
Asciz	canEqual;
Asciz	productElement;
Asciz	(I)Ljava/lang/Object;;
Asciz	scala/MatchError;
class	scala/MatchError
Asciz	scala/runtime/BoxesRunTime;
class	scala/runtime/BoxesRunTime
Asciz	boxToInteger;
Asciz	(I)Ljava/lang/Integer;;
NameAndType	boxToInteger:(I)Ljava/lang/Integer;
Method	scala/runtime/BoxesRunTime.boxToInteger:(I)Ljava/lang/Integer;
Asciz	toString;
Asciz	()Ljava/lang/String;;
NameAndType	toString:()Ljava/lang/String;
Method	java/lang/Object.toString:()Ljava/lang/String;
Asciz	(Ljava/lang/String;)V;
NameAndType	"<init>":(Ljava/lang/String;)V
Method	scala/MatchError."<init>":(Ljava/lang/String;)V
Asciz	java/lang/IndexOutOfBoundsException;
class	java/lang/IndexOutOfBoundsException
Method	java/lang/IndexOutOfBoundsException."<init>":(Ljava/lang/String;)V
Asciz	productArity;
Asciz	()I;
Asciz	productPrefix;
Asciz	New;
String	New
NameAndType	gd9$1:(Lscala/reflect/Tree;)Z
Method	scala/reflect/New.gd9$1:(Lscala/reflect/Tree;)Z
Asciz	scala/Equals;
class	scala/Equals
NameAndType	canEqual:(Ljava/lang/Object;)Z
InterfaceMethod	scala/Equals.canEqual:(Ljava/lang/Object;)Z
Asciz	temp39;
Asciz	temp40;
Asciz	scala/runtime/ScalaRunTime$;
class	scala/runtime/ScalaRunTime$
Asciz	Lscala/runtime/ScalaRunTime$;;
NameAndType	MODULE$:Lscala/runtime/ScalaRunTime$;
Field	scala/runtime/ScalaRunTime$.MODULE$:Lscala/runtime/ScalaRunTime$;
Asciz	_toString;
Asciz	(Lscala/Product;)Ljava/lang/String;;
NameAndType	_toString:(Lscala/Product;)Ljava/lang/String;
Method	scala/runtime/ScalaRunTime$._toString:(Lscala/Product;)Ljava/lang/String;
Asciz	hashCode;
Asciz	_hashCode;
Asciz	(Lscala/Product;)I;
NameAndType	_hashCode:(Lscala/Product;)I
Method	scala/runtime/ScalaRunTime$._hashCode:(Lscala/Product;)I
Asciz	copy;
Asciz	(Lscala/reflect/Tree;)Lscala/reflect/New;;
NameAndType	"<init>":(Lscala/reflect/Tree;)V
Method	scala/reflect/New."<init>":(Lscala/reflect/Tree;)V
Asciz	copy$default$1;
Asciz	productElements;
Asciz	()Lscala/collection/Iterator;;
Asciz	(Lscala/Product;)Lscala/collection/Iterator;;
NameAndType	productElements:(Lscala/Product;)Lscala/collection/Iterator;
Method	scala/Product$class.productElements:(Lscala/Product;)Lscala/collection/Iterator;
Asciz	productIterator;
NameAndType	productIterator:(Lscala/Product;)Lscala/collection/Iterator;
Method	scala/Product$class.productIterator:(Lscala/Product;)Lscala/collection/Iterator;
Asciz	ScalaSig;
Asciz	scala/ScalaObject;
class	scala/ScalaObject
Asciz	scala/Product;
class	scala/Product
Asciz	java/io/Serializable;
class	java/io/Serializable

{
private final scala.reflect.Tree sym;
  Signature: Lscala/reflect/Tree;

public static final scala.Function1 andThen(scala.Function1);
  Signature: (Lscala/Function1;)Lscala/Function1;
  Code:
   Stack=2, Locals=1, Args_size=1
	getstatic	Field scala/reflect/New$.MODULE$:Lscala/reflect/New$;
	aload_0
	invokevirtual	Method scala/reflect/New$.andThen:(Lscala/Function1;)Lscala/Function1;
	areturn
  Labels:

public static final scala.Function1 compose(scala.Function1);
  Signature: (Lscala/Function1;)Lscala/Function1;
  Code:
   Stack=2, Locals=1, Args_size=1
	getstatic	Field scala/reflect/New$.MODULE$:Lscala/reflect/New$;
	aload_0
	invokevirtual	Method scala/reflect/New$.compose:(Lscala/Function1;)Lscala/Function1;
	areturn
  Labels:

public scala.reflect.New(scala.reflect.Tree);
  Signature: (Lscala/reflect/Tree;)V
  Code:
   Stack=2, Locals=2, Args_size=2
	aload_0
	aload_1
	putfield	Field sym:Lscala/reflect/Tree;
	aload_0
	invokespecial	Method scala/reflect/Tree."<init>":()V
	aload_0
	invokestatic	Method scala/Product$class.$init$:(Lscala/Product;)V
	return
  Labels:
  LocalVariableTable: 
   Start  Length  Slot  Name   Signature
   0      14      0    this       Lscala/reflect/New;
   0      14      1    sym       Lscala/reflect/Tree;


private final boolean gd9$1(scala.reflect.Tree);
  Signature: (Lscala/reflect/Tree;)Z
  Code:
   Stack=2, Locals=3, Args_size=2
	aload_1
	aload_0
	invokevirtual	Method sym:()Lscala/reflect/Tree;
	astore_2
	dup
	ifnonnull	l1 // aload_2
	pop
	aload_2
	ifnull	l2 // iconst_1
	goto	l3 // iconst_0
l1	aload_2
	invokevirtual	Method java/lang/Object.equals:(Ljava/lang/Object;)Z
	ifeq	l3 // iconst_0
l2	iconst_1
	goto	l4 // ireturn
l3	iconst_0
l4	ireturn
  Labels:
   	l1 = 18 // aload_2
   	l2 = 25 // iconst_1
   	l3 = 29 // iconst_0
   	l4 = 30 // ireturn

public boolean canEqual(java.lang.Object);
  Signature: (Ljava/lang/Object;)Z
  Code:
   Stack=1, Locals=2, Args_size=2
	aload_1
	instanceof	class scala/reflect/New
	ireturn
  Labels:

public java.lang.Object productElement(int);
  Signature: (I)Ljava/lang/Object;
  Code:
   Stack=3, Locals=2, Args_size=2
	iload_1
	iconst_0
	if_icmpne	l1 // iconst_1
	iconst_1
	ifeq	l2 // new
	aload_0
	invokevirtual	Method sym:()Lscala/reflect/Tree;
	areturn
l2	new	class scala/MatchError
	dup
	iload_1
	invokestatic	Method scala/runtime/BoxesRunTime.boxToInteger:(I)Ljava/lang/Integer;
	invokevirtual	Method java/lang/Object.toString:()Ljava/lang/String;
	invokespecial	Method scala/MatchError."<init>":(Ljava/lang/String;)V
	athrow
l1	iconst_1
	ifeq	l3 // new
	new	class java/lang/IndexOutOfBoundsException
	dup
	iload_1
	invokestatic	Method scala/runtime/BoxesRunTime.boxToInteger:(I)Ljava/lang/Integer;
	invokevirtual	Method java/lang/Object.toString:()Ljava/lang/String;
	invokespecial	Method java/lang/IndexOutOfBoundsException."<init>":(Ljava/lang/String;)V
	athrow
l3	new	class scala/MatchError
	dup
	iload_1
	invokestatic	Method scala/runtime/BoxesRunTime.boxToInteger:(I)Ljava/lang/Integer;
	invokevirtual	Method java/lang/Object.toString:()Ljava/lang/String;
	invokespecial	Method scala/MatchError."<init>":(Ljava/lang/String;)V
	athrow
  Labels:
   	l2 = 14 // new
   	l1 = 29 // iconst_1
   	l3 = 48 // new

public int productArity();
  Signature: ()I
  Code:
   Stack=1, Locals=1, Args_size=1
	iconst_1
	ireturn
  Labels:

public java.lang.String productPrefix();
  Signature: ()Ljava/lang/String;
  Code:
   Stack=1, Locals=1, Args_size=1
	ldc	String New
	areturn
  Labels:

public boolean equals(java.lang.Object);
  Signature: (Ljava/lang/Object;)Z
  Code:
   Stack=3, Locals=4, Args_size=2
	aload_0
	aload_1
	if_acmpeq	l1 // iconst_1
	aload_1
	instanceof	class scala/reflect/New
	ifeq	l2 // iconst_1
	aload_1
	checkcast	class scala/reflect/New
	astore_2
	aload_2
	invokevirtual	Method sym:()Lscala/reflect/Tree;
	astore_3
	aload_0
	aload_3
	invokespecial	Method gd9$1:(Lscala/reflect/Tree;)Z
	ifeq	l3 // iconst_1
	aload_1
	checkcast	class scala/reflect/New
	aload_0
	invokeinterface	InterfaceMethod scala/Equals.canEqual:(Ljava/lang/Object;)Z
	goto	l4 // ifeq
l3	iconst_1
	ifeq	l5 // new
	iconst_0
	goto	l4 // ifeq
l5	new	class scala/MatchError
	dup
	aload_1
	invokevirtual	Method java/lang/Object.toString:()Ljava/lang/String;
	invokespecial	Method scala/MatchError."<init>":(Ljava/lang/String;)V
	athrow
l2	iconst_1
	ifeq	l6 // new
	iconst_0
l4	ifeq	l7 // iconst_0
l1	iconst_1
	goto	l8 // ireturn
l7	iconst_0
l8	ireturn
l6	new	class scala/MatchError
	dup
	aload_1
	invokevirtual	Method java/lang/Object.toString:()Ljava/lang/String;
	invokespecial	Method scala/MatchError."<init>":(Ljava/lang/String;)V
	athrow
  Labels:
   	l3 = 43 // iconst_1
   	l5 = 51 // new
   	l2 = 63 // iconst_1
   	l4 = 68 // ifeq
   	l1 = 71 // iconst_1
   	l7 = 75 // iconst_0
   	l8 = 76 // ireturn
   	l6 = 77 // new
  LocalVariableTable: 
   Start  Length  Slot  Name   Signature
   0      89      0    this       Lscala/reflect/New;
   17      46      2    temp39       Lscala/reflect/New;
   22      41      3    temp40       Lscala/reflect/Tree;


public java.lang.String toString();
  Signature: ()Ljava/lang/String;
  Code:
   Stack=2, Locals=1, Args_size=1
	getstatic	Field scala/runtime/ScalaRunTime$.MODULE$:Lscala/runtime/ScalaRunTime$;
	aload_0
	invokevirtual	Method scala/runtime/ScalaRunTime$._toString:(Lscala/Product;)Ljava/lang/String;
	areturn
  Labels:

public int hashCode();
  Signature: ()I
  Code:
   Stack=2, Locals=1, Args_size=1
	getstatic	Field scala/runtime/ScalaRunTime$.MODULE$:Lscala/runtime/ScalaRunTime$;
	aload_0
	invokevirtual	Method scala/runtime/ScalaRunTime$._hashCode:(Lscala/Product;)I
	ireturn
  Labels:

public scala.reflect.New copy(scala.reflect.Tree);
  Signature: (Lscala/reflect/Tree;)Lscala/reflect/New;
  Code:
   Stack=3, Locals=2, Args_size=2
	new	class scala/reflect/New
	dup
	aload_1
	invokespecial	Method "<init>":(Lscala/reflect/Tree;)V
	areturn
  Labels:
  LocalVariableTable: 
   Start  Length  Slot  Name   Signature
   0      9      0    this       Lscala/reflect/New;
   0      9      1    sym       Lscala/reflect/Tree;


public scala.reflect.Tree sym();
  Signature: ()Lscala/reflect/Tree;
  Code:
   Stack=1, Locals=1, Args_size=1
	aload_0
	getfield	Field sym:Lscala/reflect/Tree;
	areturn
  Labels:

public scala.reflect.Tree copy$default$1();
  Signature: ()Lscala/reflect/Tree;
  Code:
   Stack=1, Locals=1, Args_size=1
	aload_0
	invokevirtual	Method sym:()Lscala/reflect/Tree;
	areturn
  Labels:

public scala.collection.Iterator productElements();
  Signature: ()Lscala/collection/Iterator;
  Code:
   Stack=1, Locals=1, Args_size=1
	aload_0
	invokestatic	Method scala/Product$class.productElements:(Lscala/Product;)Lscala/collection/Iterator;
	areturn
  Labels:

public scala.collection.Iterator productIterator();
  Signature: ()Lscala/collection/Iterator;
  Code:
   Stack=1, Locals=1, Args_size=1
	aload_0
	invokestatic	Method scala/Product$class.productIterator:(Lscala/Product;)Lscala/collection/Iterator;
	areturn
  Labels:

}

