Compiled from "Type.scala"
public final class scala.reflect.NoPrefix extends java.lang.Object
  SourceFile: "Type.scala"
  ScalaSig: length = 0x3
   05 00 00 
  RuntimeVisibleAnnotations: length = 0xB
   00 01 00 27 00 01 00 28 73 00 29 
  minor version: 0
  major version: 49
  Constant pool:
Asciz	SourceFile;
Asciz	Type.scala;
Asciz	productElements;
Asciz	()Lscala/collection/Iterator;;
Asciz	Code;
Asciz	scala/reflect/NoPrefix$;
class	scala/reflect/NoPrefix$
Asciz	MODULE$;
Asciz	Lscala/reflect/NoPrefix$;;
NameAndType	MODULE$:Lscala/reflect/NoPrefix$;
Field	scala/reflect/NoPrefix$.MODULE$:Lscala/reflect/NoPrefix$;
NameAndType	productElements:()Lscala/collection/Iterator;
Method	scala/reflect/NoPrefix$.productElements:()Lscala/collection/Iterator;
Asciz	Deprecated;
Asciz	productIterator;
NameAndType	productIterator:()Lscala/collection/Iterator;
Method	scala/reflect/NoPrefix$.productIterator:()Lscala/collection/Iterator;
Asciz	productElementName;
Asciz	(I)Ljava/lang/String;;
NameAndType	productElementName:(I)Ljava/lang/String;
Method	scala/reflect/NoPrefix$.productElementName:(I)Ljava/lang/String;
Asciz	canEqual;
Asciz	(Ljava/lang/Object;)Z;
NameAndType	canEqual:(Ljava/lang/Object;)Z
Method	scala/reflect/NoPrefix$.canEqual:(Ljava/lang/Object;)Z
Asciz	productElement;
Asciz	(I)Ljava/lang/Object;;
NameAndType	productElement:(I)Ljava/lang/Object;
Method	scala/reflect/NoPrefix$.productElement:(I)Ljava/lang/Object;
Asciz	productArity;
Asciz	()I;
NameAndType	productArity:()I
Method	scala/reflect/NoPrefix$.productArity:()I
Asciz	productPrefix;
Asciz	()Ljava/lang/String;;
NameAndType	productPrefix:()Ljava/lang/String;
Method	scala/reflect/NoPrefix$.productPrefix:()Ljava/lang/String;
Asciz	ScalaSig;
Asciz	Lscala/reflect/ScalaSignature;;
Asciz	bytes;
Asciz	;Q!\t\tBT8Qe4\tqA]3gYGOC8-7b\"C\t1BE)i\t>&/4jqN!D!\tAQ\"\t!A+9f!\t#D\tBAATGdm2kK$C\t\t)BAAQe>$Wo;\t]IA\r\rqJg.;?)9\n\tIQIQ|7:j]$\t;\tjA?\nA\1oO*\t%kCZBAFO]5oO\"AQ%Cc%Aqe>$Wo;Qe4_9!A&C&qe>$Wo;Be&$0F+!\t2&-\t\tJ;\t9JA!AB=\na:pIVG/7f[tG1gA#Me1!8z!T&!AA)\n12!1\"A\n:C2b]X/7aZC\t:\tQDAAC_>dW-8\tQ*!aa!AQ(CEa(AsK$'+Z:pYZ,G#A uBA!y%M[3di\"b\t!K!!M,'/[1mSj'\r\3;
Asciz	RuntimeVisibleAnnotations;
Asciz	scala/reflect/NoPrefix;
class	scala/reflect/NoPrefix
Asciz	java/lang/Object;
class	java/lang/Object

{
public static final scala.collection.Iterator productElements();
  Signature: ()Lscala/collection/Iterator;
  Code:
   Stack=1, Locals=0, Args_size=0
	getstatic	Field scala/reflect/NoPrefix$.MODULE$:Lscala/reflect/NoPrefix$;
	invokevirtual	Method scala/reflect/NoPrefix$.productElements:()Lscala/collection/Iterator;
	areturn
  Labels:
  Deprecated: true

public static final scala.collection.Iterator productIterator();
  Signature: ()Lscala/collection/Iterator;
  Code:
   Stack=1, Locals=0, Args_size=0
	getstatic	Field scala/reflect/NoPrefix$.MODULE$:Lscala/reflect/NoPrefix$;
	invokevirtual	Method scala/reflect/NoPrefix$.productIterator:()Lscala/collection/Iterator;
	areturn
  Labels:

public static final java.lang.String productElementName(int);
  Signature: (I)Ljava/lang/String;
  Code:
   Stack=2, Locals=1, Args_size=1
	getstatic	Field scala/reflect/NoPrefix$.MODULE$:Lscala/reflect/NoPrefix$;
	iload_0
	invokevirtual	Method scala/reflect/NoPrefix$.productElementName:(I)Ljava/lang/String;
	areturn
  Labels:

public static final boolean canEqual(java.lang.Object);
  Signature: (Ljava/lang/Object;)Z
  Code:
   Stack=2, Locals=1, Args_size=1
	getstatic	Field scala/reflect/NoPrefix$.MODULE$:Lscala/reflect/NoPrefix$;
	aload_0
	invokevirtual	Method scala/reflect/NoPrefix$.canEqual:(Ljava/lang/Object;)Z
	ireturn
  Labels:

public static final java.lang.Object productElement(int);
  Signature: (I)Ljava/lang/Object;
  Code:
   Stack=2, Locals=1, Args_size=1
	getstatic	Field scala/reflect/NoPrefix$.MODULE$:Lscala/reflect/NoPrefix$;
	iload_0
	invokevirtual	Method scala/reflect/NoPrefix$.productElement:(I)Ljava/lang/Object;
	areturn
  Labels:

public static final int productArity();
  Signature: ()I
  Code:
   Stack=1, Locals=0, Args_size=0
	getstatic	Field scala/reflect/NoPrefix$.MODULE$:Lscala/reflect/NoPrefix$;
	invokevirtual	Method scala/reflect/NoPrefix$.productArity:()I
	ireturn
  Labels:

public static final java.lang.String productPrefix();
  Signature: ()Ljava/lang/String;
  Code:
   Stack=1, Locals=0, Args_size=0
	getstatic	Field scala/reflect/NoPrefix$.MODULE$:Lscala/reflect/NoPrefix$;
	invokevirtual	Method scala/reflect/NoPrefix$.productPrefix:()Ljava/lang/String;
	areturn
  Labels:

}

