Compiled from "Type.scala"
public final class scala.reflect.NoType extends java.lang.Object
  SourceFile: "Type.scala"
  ScalaSig: length = 0x1EE
   05 00 4A 07 05 01 02 FFFFFF88 42 07 01 06 4E 6F 54 79
   70 65 0A 02 03 04 01 07 72 65 66 6C 65 63 74 0A
   01 05 01 05 73 63 61 6C 61 03 00 10 02 08 09 0D
   01 02 06 08 0A 02 FFFFFF84 FFFFFF80 FFFFFF80 FFFFFF88 42 0B 02 06 4E 6F
   54 79 70 65 13 04 09 0C 0F 13 10 02 08 0D 09 02
   0E 02 02 04 54 79 70 65 10 02 10 11 0D 01 04 09
   02 12 04 02 0B 53 63 61 6C 61 4F 62 6A 65 63 74
   10 02 10 14 09 02 15 04 02 07 50 72 6F 64 75 63
   74 08 05 17 09 FFFFFF84 00 18 01 06 3C 69 6E 69 74 3E
   14 01 07 08 08 1A 09 FFFFFF84 FFFFFF80 FFFFFF80 FFFFFF84 22 1B 01 08 74
   6F 53 74 72 69 6E 67 14 01 1C 10 02 1D 22 0D 01
   1E 0A 02 1F 20 01 04 6C 61 6E 67 0A 01 21 01 04
   6A 61 76 61 09 02 23 1E 02 06 53 74 72 69 6E 67
   08 08 25 09 FFFFFF84 FFFFFF80 FFFFFF80 FFFFFF84 20 26 01 0D 70 72 6F 64
   75 63 74 50 72 65 66 69 78 15 01 1C 08 08 28 09
   FFFFFF84 FFFFFF80 FFFFFF80 FFFFFF84 20 29 01 0C 70 72 6F 64 75 63 74 41
   72 69 74 79 15 01 2A 10 02 10 2B 09 02 2C 04 02
   03 49 6E 74 08 08 2E 09 FFFFFF84 FFFFFF80 FFFFFF80 FFFFFF84 20 2F 01 0E
   70 72 6F 64 75 63 74 45 6C 65 6D 65 6E 74 14 02
   30 33 10 02 10 31 09 02 32 04 02 03 41 6E 79 08
   07 34 2D FFFFFF81 FFFFFF80 FFFFFFC0 00 2A 01 03 78 24 31 08 08 36
   09 FFFFFF84 FFFFFF80 FFFFFF80 FFFFFF84 20 37 01 12 70 72 6F 64 75 63 74
   45 6C 65 6D 65 6E 74 4E 61 6D 65 14 02 1C 38 08
   07 34 35 FFFFFF81 FFFFFF80 FFFFFFC0 00 2A 08 08 3A 09 FFFFFF84 FFFFFF80 FFFFFF80 FFFFFF84
   20 3B 01 08 63 61 6E 45 71 75 61 6C 14 02 3C 3F
   10 02 10 3D 09 02 3E 04 02 07 42 6F 6F 6C 65 61
   6E 08 07 34 39 FFFFFF81 FFFFFF80 FFFFFFC0 00 30 08 08 41 09 FFFFFF84 FFFFFF80
   FFFFFF80 FFFFFF84 08 42 01 0B 72 65 61 64 52 65 73 6F 6C 76
   65 14 01 43 10 02 1D 44 09 02 45 1E 02 06 4F 62
   6A 65 63 74 28 02 09 47 10 02 10 48 09 02 49 04
   02 0C 73 65 72 69 61 6C 69 7A 61 62 6C 65 
  minor version: 0
  major version: 49
  Constant pool:
Asciz	SourceFile;
Asciz	Type.scala;
Asciz	productElements;
Asciz	()Lscala/collection/Iterator;;
Asciz	Code;
Asciz	scala/reflect/NoType$;
class	scala/reflect/NoType$
Asciz	MODULE$;
Asciz	Lscala/reflect/NoType$;;
NameAndType	MODULE$:Lscala/reflect/NoType$;
Field	scala/reflect/NoType$.MODULE$:Lscala/reflect/NoType$;
NameAndType	productElements:()Lscala/collection/Iterator;
Method	scala/reflect/NoType$.productElements:()Lscala/collection/Iterator;
Asciz	Deprecated;
Asciz	productIterator;
NameAndType	productIterator:()Lscala/collection/Iterator;
Method	scala/reflect/NoType$.productIterator:()Lscala/collection/Iterator;
Asciz	canEqual;
Asciz	(Ljava/lang/Object;)Z;
NameAndType	canEqual:(Ljava/lang/Object;)Z
Method	scala/reflect/NoType$.canEqual:(Ljava/lang/Object;)Z
Asciz	productElementName;
Asciz	(I)Ljava/lang/String;;
NameAndType	productElementName:(I)Ljava/lang/String;
Method	scala/reflect/NoType$.productElementName:(I)Ljava/lang/String;
Asciz	productElement;
Asciz	(I)Ljava/lang/Object;;
NameAndType	productElement:(I)Ljava/lang/Object;
Method	scala/reflect/NoType$.productElement:(I)Ljava/lang/Object;
Asciz	productArity;
Asciz	()I;
NameAndType	productArity:()I
Method	scala/reflect/NoType$.productArity:()I
Asciz	productPrefix;
Asciz	()Ljava/lang/String;;
NameAndType	productPrefix:()Ljava/lang/String;
Method	scala/reflect/NoType$.productPrefix:()Ljava/lang/String;
Asciz	ScalaSig;
Asciz	scala/reflect/NoType;
class	scala/reflect/NoType
Asciz	java/lang/Object;
class	java/lang/Object

{
public static final scala.collection.Iterator productElements();
  Signature: ()Lscala/collection/Iterator;
  Code:
   Stack=1, Locals=0, Args_size=0
	getstatic	Field scala/reflect/NoType$.MODULE$:Lscala/reflect/NoType$;
	invokevirtual	Method scala/reflect/NoType$.productElements:()Lscala/collection/Iterator;
	areturn
  Labels:
  Deprecated: true

public static final scala.collection.Iterator productIterator();
  Signature: ()Lscala/collection/Iterator;
  Code:
   Stack=1, Locals=0, Args_size=0
	getstatic	Field scala/reflect/NoType$.MODULE$:Lscala/reflect/NoType$;
	invokevirtual	Method scala/reflect/NoType$.productIterator:()Lscala/collection/Iterator;
	areturn
  Labels:

public static final boolean canEqual(java.lang.Object);
  Signature: (Ljava/lang/Object;)Z
  Code:
   Stack=2, Locals=1, Args_size=1
	getstatic	Field scala/reflect/NoType$.MODULE$:Lscala/reflect/NoType$;
	aload_0
	invokevirtual	Method scala/reflect/NoType$.canEqual:(Ljava/lang/Object;)Z
	ireturn
  Labels:

public static final java.lang.String productElementName(int);
  Signature: (I)Ljava/lang/String;
  Code:
   Stack=2, Locals=1, Args_size=1
	getstatic	Field scala/reflect/NoType$.MODULE$:Lscala/reflect/NoType$;
	iload_0
	invokevirtual	Method scala/reflect/NoType$.productElementName:(I)Ljava/lang/String;
	areturn
  Labels:

public static final java.lang.Object productElement(int);
  Signature: (I)Ljava/lang/Object;
  Code:
   Stack=2, Locals=1, Args_size=1
	getstatic	Field scala/reflect/NoType$.MODULE$:Lscala/reflect/NoType$;
	iload_0
	invokevirtual	Method scala/reflect/NoType$.productElement:(I)Ljava/lang/Object;
	areturn
  Labels:

public static final int productArity();
  Signature: ()I
  Code:
   Stack=1, Locals=0, Args_size=0
	getstatic	Field scala/reflect/NoType$.MODULE$:Lscala/reflect/NoType$;
	invokevirtual	Method scala/reflect/NoType$.productArity:()I
	ireturn
  Labels:

public static final java.lang.String productPrefix();
  Signature: ()Ljava/lang/String;
  Code:
   Stack=1, Locals=0, Args_size=0
	getstatic	Field scala/reflect/NoType$.MODULE$:Lscala/reflect/NoType$;
	invokevirtual	Method scala/reflect/NoType$.productPrefix:()Ljava/lang/String;
	areturn
  Labels:

}

