Compiled from "Type.scala"
public class scala.reflect.PolyType extends scala.reflect.Type implements scala.ScalaObject,scala.Product,java.io.Serializable
  SourceFile: "Type.scala"
  ScalaSig: length = 0x4D0
   05 00 FFFFFF81 29 06 08 01 02 FFFFFF84 FFFFFF80 FFFFFF80 FFFFFF80 40 07 02 08
   50 6F 6C 79 54 79 70 65 0A 02 03 04 01 07 72 65
   66 6C 65 63 74 0A 01 05 01 05 73 63 61 6C 61 03
   00 13 04 00 08 0C 10 10 02 09 0A 0D 01 02 09 02
   0B 02 02 04 54 79 70 65 10 02 0D 0E 0D 01 04 09
   02 0F 04 02 0B 53 63 61 6C 61 4F 62 6A 65 63 74
   10 02 0D 11 09 02 12 04 02 07 50 72 6F 64 75 63
   74 08 08 14 00 FFFFFF82 FFFFFFCA FFFFFF80 FFFFFF84 00 15 01 0A 74 79 70
   65 50 61 72 61 6D 73 15 01 16 10 03 17 1C 1E 0D
   01 18 0A 02 19 1A 01 09 69 6D 6D 75 74 61 62 6C
   65 0A 02 1B 04 01 0A 63 6F 6C 6C 65 63 74 69 6F
   6E 09 02 1D 18 02 04 4C 69 73 74 10 02 09 1F 09
   02 20 02 02 06 53 79 6D 62 6F 6C 08 08 22 00 FFFFFF82
   FFFFFF88 FFFFFFA0 FFFFFF80 04 16 01 0B 74 79 70 65 50 61 72 61 6D
   73 20 08 08 24 00 FFFFFF82 FFFFFFCA FFFFFF80 FFFFFF84 00 25 01 0A 74 79
   70 65 42 6F 75 6E 64 73 15 01 26 10 03 17 1C 27
   10 04 0D 28 08 08 09 02 29 04 02 06 54 75 70 6C
   65 32 08 08 2B 00 FFFFFF82 FFFFFF88 FFFFFFA0 FFFFFF80 04 26 01 0B 74 79
   70 65 42 6F 75 6E 64 73 20 08 08 2D 00 FFFFFF82 FFFFFFCA FFFFFF80
   FFFFFF84 00 2E 01 0A 72 65 73 75 6C 74 54 79 70 65 15
   01 08 08 08 30 00 FFFFFF82 FFFFFF88 FFFFFFA0 FFFFFF80 04 08 01 0B 72 65
   73 75 6C 74 54 79 70 65 20 08 05 32 00 FFFFFF84 00 33
   01 06 3C 69 6E 69 74 3E 14 04 34 35 36 37 10 02
   09 00 08 05 14 31 FFFFFFC0 00 16 08 05 24 31 FFFFFFC0 00 26
   08 05 2D 31 FFFFFFC0 00 08 08 07 39 00 FFFFFF81 FFFFFF80 FFFFFF84 00 3A
   01 04 63 6F 70 79 14 04 34 3B 3C 3D 08 07 14 38
   FFFFFF90 FFFFFF80 FFFFFFC0 00 16 08 07 24 38 FFFFFF90 FFFFFF80 FFFFFFC0 00 26 08 07
   2D 38 FFFFFF90 FFFFFF80 FFFFFFC0 00 08 08 07 3F 00 FFFFFF91 FFFFFF80 FFFFFF84 00 40
   01 0E 63 6F 70 79 24 64 65 66 61 75 6C 74 24 31
   15 01 41 2A 02 16 42 2B 01 43 10 02 44 49 0D 01
   45 0A 02 46 47 01 09 75 6E 63 68 65 63 6B 65 64
   0A 02 48 04 01 0A 61 6E 6E 6F 74 61 74 69 6F 6E
   09 02 4A 45 02 11 75 6E 63 68 65 63 6B 65 64 56
   61 72 69 61 6E 63 65 08 07 4C 00 FFFFFF91 FFFFFF80 FFFFFF84 00 4D
   01 0E 63 6F 70 79 24 64 65 66 61 75 6C 74 24 32
   15 01 4E 2A 02 26 42 08 07 50 00 FFFFFF91 FFFFFF80 FFFFFF84 00 51
   01 0E 63 6F 70 79 24 64 65 66 61 75 6C 74 24 33
   15 01 52 2A 02 08 42 08 08 54 00 FFFFFF84 FFFFFF80 FFFFFF80 FFFFFF84 20
   55 01 08 68 61 73 68 43 6F 64 65 14 01 56 10 02
   0D 57 09 02 58 04 02 03 49 6E 74 08 08 5A 00 FFFFFF84
   FFFFFF80 FFFFFF80 FFFFFF84 20 5B 01 08 74 6F 53 74 72 69 6E 67 14
   01 5C 10 02 5D 60 0E 02 0D 5E 09 02 5F 04 01 06
   50 72 65 64 65 66 09 02 61 62 02 06 53 74 72 69
   6E 67 0A 02 5F 04 08 08 64 00 FFFFFF84 FFFFFF80 FFFFFF80 FFFFFF84 20 65
   01 06 65 71 75 61 6C 73 14 02 66 69 10 02 0D 67
   09 02 68 04 02 07 42 6F 6F 6C 65 61 6E 08 07 6A
   63 FFFFFF81 FFFFFF80 FFFFFFC0 00 6B 01 03 78 24 31 10 02 0D 6C 09
   02 6D 04 02 03 41 6E 79 08 08 6F 00 FFFFFF84 FFFFFF80 FFFFFF80 FFFFFF84
   20 70 01 0D 70 72 6F 64 75 63 74 50 72 65 66 69
   78 15 01 71 10 02 72 77 0D 01 73 0A 02 74 75 01
   04 6C 61 6E 67 0A 01 76 01 04 6A 61 76 61 09 02
   61 73 08 08 79 00 FFFFFF84 FFFFFF80 FFFFFF80 FFFFFF84 20 7A 01 0C 70 72
   6F 64 75 63 74 41 72 69 74 79 15 01 56 08 08 7C
   00 FFFFFF84 FFFFFF80 FFFFFF80 FFFFFF84 20 7D 01 0E 70 72 6F 64 75 63 74
   45 6C 65 6D 65 6E 74 14 02 6B 7E 08 07 6A 7B FFFFFF81
   FFFFFF80 FFFFFFC0 00 56 08 0A FFFFFF81 00 00 FFFFFF84 FFFFFF80 FFFFFF80 FFFFFF84 20 FFFFFF81 01
   01 12 70 72 6F 64 75 63 74 45 6C 65 6D 65 6E 74
   4E 61 6D 65 14 03 71 FFFFFF81 02 08 07 6A 7F FFFFFF81 FFFFFF80 FFFFFFC0
   00 56 08 0A FFFFFF81 04 00 FFFFFF84 FFFFFF80 FFFFFF80 FFFFFF84 20 FFFFFF81 05 01 08
   63 61 6E 45 71 75 61 6C 14 03 66 FFFFFF81 06 08 08 6A
   FFFFFF81 03 FFFFFF81 FFFFFF80 FFFFFFC0 00 6B 28 03 00 FFFFFF81 08 10 03 0D FFFFFF81
   09 09 03 FFFFFF81 0A 04 02 0C 73 65 72 69 61 6C 69 7A
   61 62 6C 65 07 09 FFFFFF81 0C 02 FFFFFF81 FFFFFF80 FFFFFF88 02 FFFFFF81 0D 01
   08 50 6F 6C 79 54 79 70 65 10 03 09 FFFFFF81 0E 06 09
   01 02 FFFFFF84 FFFFFF81 FFFFFF80 FFFFFF88 02 FFFFFF81 0F 13 07 FFFFFF81 0E FFFFFF81 10 FFFFFF81
   13 0C 10 03 72 FFFFFF81 11 09 03 FFFFFF81 12 73 02 06 4F 62
   6A 65 63 74 10 07 0D FFFFFF81 14 16 26 08 34 09 03 FFFFFF81
   15 04 02 09 46 75 6E 63 74 69 6F 6E 33 08 07 32
   FFFFFF81 0E FFFFFF84 00 FFFFFF81 17 14 02 FFFFFF81 0D 08 0A FFFFFF81 19 FFFFFF81 0E
   FFFFFF81 FFFFFF80 FFFFFF84 40 FFFFFF81 1A 01 05 61 70 70 6C 79 14 07 34
   FFFFFF81 1B FFFFFF81 1C FFFFFF81 1D 08 06 14 FFFFFF81 18 FFFFFFC0 00 16 08 06
   24 FFFFFF81 18 FFFFFFC0 00 26 08 06 2D FFFFFF81 18 FFFFFFC0 00 08 08 0A
   FFFFFF81 1F FFFFFF81 0E FFFFFF81 FFFFFF80 FFFFFF84 40 FFFFFF81 20 01 07 75 6E 61 70
   70 6C 79 14 04 FFFFFF81 21 FFFFFF81 27 10 05 0D FFFFFF81 22 FFFFFF81 24
   09 03 FFFFFF81 23 04 02 06 4F 70 74 69 6F 6E 10 06 0D
   FFFFFF81 25 16 26 08 09 03 FFFFFF81 26 04 02 06 54 75 70 6C
   65 33 08 07 FFFFFF81 28 FFFFFF81 1E FFFFFFC0 00 34 01 03 78 24 30
   
  minor version: 0
  major version: 49
  Constant pool:
Asciz	SourceFile;
Asciz	Type.scala;
Asciz	tupled;
Asciz	()Lscala/Function1;;
Asciz	Code;
Asciz	scala/reflect/PolyType$;
class	scala/reflect/PolyType$
Asciz	MODULE$;
Asciz	Lscala/reflect/PolyType$;;
NameAndType	MODULE$:Lscala/reflect/PolyType$;
Field	scala/reflect/PolyType$.MODULE$:Lscala/reflect/PolyType$;
NameAndType	tupled:()Lscala/Function1;
Method	scala/reflect/PolyType$.tupled:()Lscala/Function1;
Asciz	curry;
NameAndType	curry:()Lscala/Function1;
Method	scala/reflect/PolyType$.curry:()Lscala/Function1;
Asciz	Deprecated;
Asciz	curried;
NameAndType	curried:()Lscala/Function1;
Method	scala/reflect/PolyType$.curried:()Lscala/Function1;
Asciz	resultType;
Asciz	Lscala/reflect/Type;;
Asciz	typeBounds;
Asciz	Lscala/collection/immutable/List;;
Asciz	Lscala/collection/immutable/List<Lscala/Tuple2<Lscala/reflect/Type;Lscala/reflect/Type;>;>;;
Asciz	Signature;
Asciz	typeParams;
Asciz	Lscala/collection/immutable/List<Lscala/reflect/Symbol;>;;
Asciz	productIterator;
Asciz	()Lscala/collection/Iterator;;
Asciz	LineNumberTable;
Asciz	scala/Product$class;
class	scala/Product$class
Asciz	(Lscala/Product;)Lscala/collection/Iterator;;
NameAndType	productIterator:(Lscala/Product;)Lscala/collection/Iterator;
Method	scala/Product$class.productIterator:(Lscala/Product;)Lscala/collection/Iterator;
Asciz	productElements;
NameAndType	productElements:(Lscala/Product;)Lscala/collection/Iterator;
Method	scala/Product$class.productElements:(Lscala/Product;)Lscala/collection/Iterator;
Asciz	copy$default$3;
Asciz	()Lscala/reflect/Type;;
Asciz	scala/reflect/PolyType;
class	scala/reflect/PolyType
NameAndType	resultType:()Lscala/reflect/Type;
Method	scala/reflect/PolyType.resultType:()Lscala/reflect/Type;
Asciz	copy$default$2;
Asciz	()Lscala/collection/immutable/List;;
NameAndType	typeBounds:()Lscala/collection/immutable/List;
Method	scala/reflect/PolyType.typeBounds:()Lscala/collection/immutable/List;
Asciz	copy$default$1;
NameAndType	typeParams:()Lscala/collection/immutable/List;
Method	scala/reflect/PolyType.typeParams:()Lscala/collection/immutable/List;
NameAndType	typeParams:Lscala/collection/immutable/List;
Field	scala/reflect/PolyType.typeParams:Lscala/collection/immutable/List;
Asciz	()Lscala/collection/immutable/List<Lscala/reflect/Symbol;>;;
NameAndType	typeBounds:Lscala/collection/immutable/List;
Field	scala/reflect/PolyType.typeBounds:Lscala/collection/immutable/List;
Asciz	()Lscala/collection/immutable/List<Lscala/Tuple2<Lscala/reflect/Type;Lscala/reflect/Type;>;>;;
NameAndType	resultType:Lscala/reflect/Type;
Field	scala/reflect/PolyType.resultType:Lscala/reflect/Type;
Asciz	copy;
Asciz	(Lscala/collection/immutable/List;Lscala/collection/immutable/List;Lscala/reflect/Type;)Lscala/reflect/PolyType;;
Asciz	<init>;
Asciz	(Lscala/collection/immutable/List;Lscala/collection/immutable/List;Lscala/reflect/Type;)V;
NameAndType	"<init>":(Lscala/collection/immutable/List;Lscala/collection/immutable/List;Lscala/reflect/Type;)V
Method	scala/reflect/PolyType."<init>":(Lscala/collection/immutable/List;Lscala/collection/immutable/List;Lscala/reflect/Type;)V
Asciz	this;
Asciz	Lscala/reflect/PolyType;;
Asciz	LocalVariableTable;
Asciz	hashCode;
Asciz	()I;
Asciz	scala/runtime/ScalaRunTime$;
class	scala/runtime/ScalaRunTime$
Asciz	Lscala/runtime/ScalaRunTime$;;
NameAndType	MODULE$:Lscala/runtime/ScalaRunTime$;
Field	scala/runtime/ScalaRunTime$.MODULE$:Lscala/runtime/ScalaRunTime$;
Asciz	_hashCode;
Asciz	(Lscala/Product;)I;
NameAndType	_hashCode:(Lscala/Product;)I
Method	scala/runtime/ScalaRunTime$._hashCode:(Lscala/Product;)I
Asciz	toString;
Asciz	()Ljava/lang/String;;
Asciz	_toString;
Asciz	(Lscala/Product;)Ljava/lang/String;;
NameAndType	_toString:(Lscala/Product;)Ljava/lang/String;
Method	scala/runtime/ScalaRunTime$._toString:(Lscala/Product;)Ljava/lang/String;
Asciz	equals;
Asciz	(Ljava/lang/Object;)Z;
Asciz	gd8$1;
Asciz	(Lscala/collection/immutable/List;Lscala/collection/immutable/List;Lscala/reflect/Type;)Z;
NameAndType	gd8$1:(Lscala/collection/immutable/List;Lscala/collection/immutable/List;Lscala/reflect/Type;)Z
Method	scala/reflect/PolyType.gd8$1:(Lscala/collection/immutable/List;Lscala/collection/immutable/List;Lscala/reflect/Type;)Z
Asciz	scala/Equals;
class	scala/Equals
Asciz	canEqual;
NameAndType	canEqual:(Ljava/lang/Object;)Z
InterfaceMethod	scala/Equals.canEqual:(Ljava/lang/Object;)Z
Asciz	temp46;
Asciz	temp47;
Asciz	temp48;
Asciz	temp49;
Asciz	productPrefix;
Asciz	PolyType;
String	PolyType
Asciz	productArity;
Asciz	productElement;
Asciz	(I)Ljava/lang/Object;;
Asciz	java/lang/IndexOutOfBoundsException;
class	java/lang/IndexOutOfBoundsException
Asciz	scala/runtime/BoxesRunTime;
class	scala/runtime/BoxesRunTime
Asciz	boxToInteger;
Asciz	(I)Ljava/lang/Integer;;
NameAndType	boxToInteger:(I)Ljava/lang/Integer;
Method	scala/runtime/BoxesRunTime.boxToInteger:(I)Ljava/lang/Integer;
Asciz	java/lang/Object;
class	java/lang/Object
NameAndType	toString:()Ljava/lang/String;
Method	java/lang/Object.toString:()Ljava/lang/String;
Asciz	(Ljava/lang/String;)V;
NameAndType	"<init>":(Ljava/lang/String;)V
Method	java/lang/IndexOutOfBoundsException."<init>":(Ljava/lang/String;)V
Asciz	productElementName;
Asciz	(I)Ljava/lang/String;;
String	resultType
String	typeBounds
String	typeParams
NameAndType	equals:(Ljava/lang/Object;)Z
Method	java/lang/Object.equals:(Ljava/lang/Object;)Z
Asciz	scala/reflect/Type;
class	scala/reflect/Type
Asciz	()V;
NameAndType	"<init>":()V
Method	scala/reflect/Type."<init>":()V
Asciz	$init$;
Asciz	(Lscala/Product;)V;
NameAndType	$init$:(Lscala/Product;)V
Method	scala/Product$class.$init$:(Lscala/Product;)V
Asciz	(Lscala/collection/immutable/List<Lscala/reflect/Symbol;>;Lscala/collection/immutable/List<Lscala/Tuple2<Lscala/reflect/Type;Lscala/reflect/Type;>;>;Lscala/reflect/Type;)V;
Asciz	ScalaSig;
Asciz	scala/ScalaObject;
class	scala/ScalaObject
Asciz	scala/Product;
class	scala/Product
Asciz	java/io/Serializable;
class	java/io/Serializable

{
private final scala.reflect.Type resultType;
  Signature: Lscala/reflect/Type;

private final scala.collection.immutable.List typeBounds;
  Signature: Lscala/collection/immutable/List;
  Signature: length = 0x2
   00 19 

private final scala.collection.immutable.List typeParams;
  Signature: Lscala/collection/immutable/List;
  Signature: length = 0x2
   00 1C 

public static final scala.Function1 tupled();
  Signature: ()Lscala/Function1;
  Code:
   Stack=1, Locals=0, Args_size=0
	getstatic	Field scala/reflect/PolyType$.MODULE$:Lscala/reflect/PolyType$;
	invokevirtual	Method scala/reflect/PolyType$.tupled:()Lscala/Function1;
	areturn
  Labels:

public static final scala.Function1 curry();
  Signature: ()Lscala/Function1;
  Code:
   Stack=1, Locals=0, Args_size=0
	getstatic	Field scala/reflect/PolyType$.MODULE$:Lscala/reflect/PolyType$;
	invokevirtual	Method scala/reflect/PolyType$.curry:()Lscala/Function1;
	areturn
  Labels:
  Deprecated: true

public static final scala.Function1 curried();
  Signature: ()Lscala/Function1;
  Code:
   Stack=1, Locals=0, Args_size=0
	getstatic	Field scala/reflect/PolyType$.MODULE$:Lscala/reflect/PolyType$;
	invokevirtual	Method scala/reflect/PolyType$.curried:()Lscala/Function1;
	areturn
  Labels:

public scala.collection.Iterator productIterator();
  Signature: ()Lscala/collection/Iterator;
  Code:
   Stack=1, Locals=1, Args_size=1
	aload_0
	invokestatic	Method scala/Product$class.productIterator:(Lscala/Product;)Lscala/collection/Iterator;
	areturn
  Labels:

public scala.collection.Iterator productElements();
  Signature: ()Lscala/collection/Iterator;
  Code:
   Stack=1, Locals=1, Args_size=1
	aload_0
	invokestatic	Method scala/Product$class.productElements:(Lscala/Product;)Lscala/collection/Iterator;
	areturn
  Labels:
  Deprecated: true

public scala.reflect.Type copy$default$3();
  Signature: ()Lscala/reflect/Type;
  Code:
   Stack=1, Locals=1, Args_size=1
	aload_0
	invokevirtual	Method resultType:()Lscala/reflect/Type;
	areturn
  Labels:

public scala.collection.immutable.List copy$default$2();
  Signature: ()Lscala/collection/immutable/List;
  Code:
   Stack=1, Locals=1, Args_size=1
	aload_0
	invokevirtual	Method typeBounds:()Lscala/collection/immutable/List;
	areturn
  Labels:

public scala.collection.immutable.List copy$default$1();
  Signature: ()Lscala/collection/immutable/List;
  Code:
   Stack=1, Locals=1, Args_size=1
	aload_0
	invokevirtual	Method typeParams:()Lscala/collection/immutable/List;
	areturn
  Labels:

public scala.collection.immutable.List typeParams();
  Signature: ()Lscala/collection/immutable/List;
  Code:
   Stack=1, Locals=1, Args_size=1
	aload_0
	getfield	Field typeParams:Lscala/collection/immutable/List;
	areturn
  Labels:
  Signature: length = 0x2
   00 37 

public scala.collection.immutable.List typeBounds();
  Signature: ()Lscala/collection/immutable/List;
  Code:
   Stack=1, Locals=1, Args_size=1
	aload_0
	getfield	Field typeBounds:Lscala/collection/immutable/List;
	areturn
  Labels:
  Signature: length = 0x2
   00 3A 

public scala.reflect.Type resultType();
  Signature: ()Lscala/reflect/Type;
  Code:
   Stack=1, Locals=1, Args_size=1
	aload_0
	getfield	Field resultType:Lscala/reflect/Type;
	areturn
  Labels:

public scala.reflect.PolyType copy(scala.collection.immutable.List, scala.collection.immutable.List, scala.reflect.Type);
  Signature: (Lscala/collection/immutable/List;Lscala/collection/immutable/List;Lscala/reflect/Type;)Lscala/reflect/PolyType;
  Code:
   Stack=5, Locals=4, Args_size=4
	new	class scala/reflect/PolyType
	dup
	aload_1
	aload_2
	aload_3
	invokespecial	Method "<init>":(Lscala/collection/immutable/List;Lscala/collection/immutable/List;Lscala/reflect/Type;)V
	areturn
  Labels:
  LocalVariableTable: 
   Start  Length  Slot  Name   Signature
   0      11      0    this       Lscala/reflect/PolyType;
   0      11      1    typeParams       Lscala/collection/immutable/List;
   0      11      2    typeBounds       Lscala/collection/immutable/List;
   0      11      3    resultType       Lscala/reflect/Type;


public int hashCode();
  Signature: ()I
  Code:
   Stack=2, Locals=1, Args_size=1
	getstatic	Field scala/runtime/ScalaRunTime$.MODULE$:Lscala/runtime/ScalaRunTime$;
	aload_0
	invokevirtual	Method scala/runtime/ScalaRunTime$._hashCode:(Lscala/Product;)I
	ireturn
  Labels:

public java.lang.String toString();
  Signature: ()Ljava/lang/String;
  Code:
   Stack=2, Locals=1, Args_size=1
	getstatic	Field scala/runtime/ScalaRunTime$.MODULE$:Lscala/runtime/ScalaRunTime$;
	aload_0
	invokevirtual	Method scala/runtime/ScalaRunTime$._toString:(Lscala/Product;)Ljava/lang/String;
	areturn
  Labels:

public boolean equals(java.lang.Object);
  Signature: (Ljava/lang/Object;)Z
  Code:
   Stack=4, Locals=6, Args_size=2
	aload_0
	aload_1
	if_acmpeq	l1 // iconst_1
	aload_1
	instanceof	class scala/reflect/PolyType
	ifeq	l2 // iconst_0
	aload_1
	checkcast	class scala/reflect/PolyType
	astore_2
	aload_2
	invokevirtual	Method typeParams:()Lscala/collection/immutable/List;
	astore_3
	aload_2
	invokevirtual	Method typeBounds:()Lscala/collection/immutable/List;
	astore	4
	aload_2
	invokevirtual	Method resultType:()Lscala/reflect/Type;
	astore	5
	aload_0
	aload_3
	aload	4
	aload	5
	invokespecial	Method gd8$1:(Lscala/collection/immutable/List;Lscala/collection/immutable/List;Lscala/reflect/Type;)Z
	ifeq	l3 // iconst_0
	aload_1
	checkcast	class scala/reflect/PolyType
	aload_0
	invokeinterface	InterfaceMethod scala/Equals.canEqual:(Ljava/lang/Object;)Z
	goto	l4 // ifeq
l3	iconst_0
	goto	l4 // ifeq
l2	iconst_0
l4	ifeq	l5 // iconst_0
l1	iconst_1
	goto	l6 // ireturn
l5	iconst_0
l6	ireturn
  Labels:
   	l3 = 59 // iconst_0
   	l2 = 63 // iconst_0
   	l4 = 64 // ifeq
   	l1 = 67 // iconst_1
   	l5 = 71 // iconst_0
   	l6 = 72 // ireturn
  LocalVariableTable: 
   Start  Length  Slot  Name   Signature
   0      73      0    this       Lscala/reflect/PolyType;
   17      46      2    temp46       Lscala/reflect/PolyType;
   22      41      3    temp47       Lscala/collection/immutable/List;
   28      35      4    temp48       Lscala/collection/immutable/List;
   34      29      5    temp49       Lscala/reflect/Type;


public java.lang.String productPrefix();
  Signature: ()Ljava/lang/String;
  Code:
   Stack=1, Locals=1, Args_size=1
	ldc	String PolyType
	areturn
  Labels:

public int productArity();
  Signature: ()I
  Code:
   Stack=1, Locals=1, Args_size=1
	iconst_3
	ireturn
  Labels:

public java.lang.Object productElement(int);
  Signature: (I)Ljava/lang/Object;
  Code:
   Stack=3, Locals=2, Args_size=2
	iload_1
	tableswitch{ //0 to 2
		0: 57;
		1: 50;
		2: 43;
		default: 28 }
	new	class java/lang/IndexOutOfBoundsException
	dup
	iload_1
	invokestatic	Method scala/runtime/BoxesRunTime.boxToInteger:(I)Ljava/lang/Integer;
	invokevirtual	Method java/lang/Object.toString:()Ljava/lang/String;
	invokespecial	Method java/lang/IndexOutOfBoundsException."<init>":(Ljava/lang/String;)V
	athrow
	aload_0
	invokevirtual	Method resultType:()Lscala/reflect/Type;
	goto	l1 // areturn
	aload_0
	invokevirtual	Method typeBounds:()Lscala/collection/immutable/List;
	goto	l1 // areturn
	aload_0
	invokevirtual	Method typeParams:()Lscala/collection/immutable/List;
l1	areturn
  Labels:
   	l1 = 61 // areturn

public java.lang.String productElementName(int);
  Signature: (I)Ljava/lang/String;
  Code:
   Stack=3, Locals=2, Args_size=2
	iload_1
	tableswitch{ //0 to 2
		0: 53;
		1: 48;
		2: 43;
		default: 28 }
	new	class java/lang/IndexOutOfBoundsException
	dup
	iload_1
	invokestatic	Method scala/runtime/BoxesRunTime.boxToInteger:(I)Ljava/lang/Integer;
	invokevirtual	Method java/lang/Object.toString:()Ljava/lang/String;
	invokespecial	Method java/lang/IndexOutOfBoundsException."<init>":(Ljava/lang/String;)V
	athrow
	ldc	String resultType
	goto	l1 // areturn
	ldc	String typeBounds
	goto	l1 // areturn
	ldc	String typeParams
l1	areturn
  Labels:
   	l1 = 55 // areturn

public boolean canEqual(java.lang.Object);
  Signature: (Ljava/lang/Object;)Z
  Code:
   Stack=1, Locals=2, Args_size=2
	aload_1
	instanceof	class scala/reflect/PolyType
	ireturn
  Labels:

private final boolean gd8$1(scala.collection.immutable.List, scala.collection.immutable.List, scala.reflect.Type);
  Signature: (Lscala/collection/immutable/List;Lscala/collection/immutable/List;Lscala/reflect/Type;)Z
  Code:
   Stack=2, Locals=7, Args_size=4
	aload_1
	aload_0
	invokevirtual	Method typeParams:()Lscala/collection/immutable/List;
	astore	4
	dup
	ifnonnull	l1 // aload
	pop
	aload	4
	ifnull	l2 // aload_2
	goto	l3 // iconst_0
l1	aload	4
	invokevirtual	Method java/lang/Object.equals:(Ljava/lang/Object;)Z
	ifeq	l3 // iconst_0
l2	aload_2
	aload_0
	invokevirtual	Method typeBounds:()Lscala/collection/immutable/List;
	astore	5
	dup
	ifnonnull	l4 // aload
	pop
	aload	5
	ifnull	l5 // aload_3
	goto	l3 // iconst_0
l4	aload	5
	invokevirtual	Method java/lang/Object.equals:(Ljava/lang/Object;)Z
	ifeq	l3 // iconst_0
l5	aload_3
	aload_0
	invokevirtual	Method resultType:()Lscala/reflect/Type;
	astore	6
	dup
	ifnonnull	l6 // aload
	pop
	aload	6
	ifnull	l7 // iconst_1
	goto	l3 // iconst_0
l6	aload	6
	invokevirtual	Method java/lang/Object.equals:(Ljava/lang/Object;)Z
	ifeq	l3 // iconst_0
l7	iconst_1
	goto	l8 // ireturn
l3	iconst_0
l8	ireturn
  Labels:
   	l1 = 20 // aload
   	l2 = 28 // aload_2
   	l4 = 48 // aload
   	l5 = 56 // aload_3
   	l6 = 76 // aload
   	l7 = 84 // iconst_1
   	l3 = 88 // iconst_0
   	l8 = 89 // ireturn

public scala.reflect.PolyType(scala.collection.immutable.List, scala.collection.immutable.List, scala.reflect.Type);
  Signature: (Lscala/collection/immutable/List;Lscala/collection/immutable/List;Lscala/reflect/Type;)V
  Code:
   Stack=2, Locals=4, Args_size=4
	aload_0
	aload_1
	putfield	Field typeParams:Lscala/collection/immutable/List;
	aload_0
	aload_2
	putfield	Field typeBounds:Lscala/collection/immutable/List;
	aload_0
	aload_3
	putfield	Field resultType:Lscala/reflect/Type;
	aload_0
	invokespecial	Method scala/reflect/Type."<init>":()V
	aload_0
	invokestatic	Method scala/Product$class.$init$:(Lscala/Product;)V
	return
  Labels:
  LocalVariableTable: 
   Start  Length  Slot  Name   Signature
   0      24      0    this       Lscala/reflect/PolyType;
   0      24      1    typeParams       Lscala/collection/immutable/List;
   0      24      2    typeBounds       Lscala/collection/immutable/List;
   0      24      3    resultType       Lscala/reflect/Type;

  Signature: length = 0x2
   00 FFFFFF8B 

}

