Compiled from "Type.scala"
public final class scala.reflect.PolyType$ extends java.lang.Object implements scala.Function3,scala.ScalaObject
  SourceFile: "Type.scala"
  Scala: length = 0x
   
  minor version: 0
  major version: 49
  Constant pool:
Asciz	SourceFile;
Asciz	Type.scala;
Asciz	MODULE$;
Asciz	Lscala/reflect/PolyType$;;
Asciz	<clinit>;
Asciz	()V;
Asciz	Code;
Asciz	scala/reflect/PolyType$;
class	scala/reflect/PolyType$
Asciz	<init>;
NameAndType	"<init>":()V
Method	scala/reflect/PolyType$."<init>":()V
Asciz	toString;
Asciz	()Ljava/lang/String;;
Asciz	LineNumberTable;
Asciz	scala/Function3$class;
class	scala/Function3$class
Asciz	(Lscala/Function3;)Ljava/lang/String;;
NameAndType	toString:(Lscala/Function3;)Ljava/lang/String;
Method	scala/Function3$class.toString:(Lscala/Function3;)Ljava/lang/String;
Asciz	curried;
Asciz	()Lscala/Function1;;
Asciz	(Lscala/Function3;)Lscala/Function1;;
NameAndType	curried:(Lscala/Function3;)Lscala/Function1;
Method	scala/Function3$class.curried:(Lscala/Function3;)Lscala/Function1;
Asciz	curry;
NameAndType	curry:(Lscala/Function3;)Lscala/Function1;
Method	scala/Function3$class.curry:(Lscala/Function3;)Lscala/Function1;
Asciz	Deprecated;
Asciz	tupled;
NameAndType	tupled:(Lscala/Function3;)Lscala/Function1;
Method	scala/Function3$class.tupled:(Lscala/Function3;)Lscala/Function1;
Asciz	unapply;
Asciz	(Lscala/reflect/PolyType;)Lscala/Option;;
Asciz	scala/None$;
class	scala/None$
Asciz	Lscala/None$;;
NameAndType	MODULE$:Lscala/None$;
Field	scala/None$.MODULE$:Lscala/None$;
Asciz	scala/Some;
class	scala/Some
Asciz	scala/Tuple3;
class	scala/Tuple3
Asciz	scala/reflect/PolyType;
class	scala/reflect/PolyType
Asciz	typeParams;
Asciz	()Lscala/collection/immutable/List;;
NameAndType	typeParams:()Lscala/collection/immutable/List;
Method	scala/reflect/PolyType.typeParams:()Lscala/collection/immutable/List;
Asciz	typeBounds;
NameAndType	typeBounds:()Lscala/collection/immutable/List;
Method	scala/reflect/PolyType.typeBounds:()Lscala/collection/immutable/List;
Asciz	resultType;
Asciz	()Lscala/reflect/Type;;
NameAndType	resultType:()Lscala/reflect/Type;
Method	scala/reflect/PolyType.resultType:()Lscala/reflect/Type;
Asciz	(Ljava/lang/Object;Ljava/lang/Object;Ljava/lang/Object;)V;
NameAndType	"<init>":(Ljava/lang/Object;Ljava/lang/Object;Ljava/lang/Object;)V
Method	scala/Tuple3."<init>":(Ljava/lang/Object;Ljava/lang/Object;Ljava/lang/Object;)V
Asciz	(Ljava/lang/Object;)V;
NameAndType	"<init>":(Ljava/lang/Object;)V
Method	scala/Some."<init>":(Ljava/lang/Object;)V
Asciz	this;
Asciz	x$0;
Asciz	Lscala/reflect/PolyType;;
Asciz	LocalVariableTable;
Asciz	apply;
Asciz	(Lscala/collection/immutable/List;Lscala/collection/immutable/List;Lscala/reflect/Type;)Lscala/reflect/PolyType;;
Asciz	(Lscala/collection/immutable/List;Lscala/collection/immutable/List;Lscala/reflect/Type;)V;
NameAndType	"<init>":(Lscala/collection/immutable/List;Lscala/collection/immutable/List;Lscala/reflect/Type;)V
Method	scala/reflect/PolyType."<init>":(Lscala/collection/immutable/List;Lscala/collection/immutable/List;Lscala/reflect/Type;)V
Asciz	Lscala/collection/immutable/List;;
Asciz	Lscala/reflect/Type;;
Asciz	(Ljava/lang/Object;Ljava/lang/Object;Ljava/lang/Object;)Ljava/lang/Object;;
Asciz	scala/collection/immutable/List;
class	scala/collection/immutable/List
Asciz	scala/reflect/Type;
class	scala/reflect/Type
NameAndType	apply:(Lscala/collection/immutable/List;Lscala/collection/immutable/List;Lscala/reflect/Type;)Lscala/reflect/PolyType;
Method	scala/reflect/PolyType$.apply:(Lscala/collection/immutable/List;Lscala/collection/immutable/List;Lscala/reflect/Type;)Lscala/reflect/PolyType;
Asciz	v1;
Asciz	Ljava/lang/Object;;
Asciz	v2;
Asciz	v3;
Asciz	java/lang/Object;
class	java/lang/Object
Method	java/lang/Object."<init>":()V
NameAndType	MODULE$:Lscala/reflect/PolyType$;
Field	scala/reflect/PolyType$.MODULE$:Lscala/reflect/PolyType$;
Asciz	$init$;
Asciz	(Lscala/Function3;)V;
NameAndType	$init$:(Lscala/Function3;)V
Method	scala/Function3$class.$init$:(Lscala/Function3;)V
Asciz	Scala;
Asciz	scala/Function3;
class	scala/Function3
Asciz	scala/ScalaObject;
class	scala/ScalaObject

{
public static final scala.reflect.PolyType$ MODULE$;
  Signature: Lscala/reflect/PolyType$;

public static {};
  Signature: ()V
  Code:
   Stack=1, Locals=0, Args_size=0
	new	class scala/reflect/PolyType$
	invokespecial	Method "<init>":()V
	return
  Labels:

public java.lang.String toString();
  Signature: ()Ljava/lang/String;
  Code:
   Stack=1, Locals=1, Args_size=1
	aload_0
	invokestatic	Method scala/Function3$class.toString:(Lscala/Function3;)Ljava/lang/String;
	areturn
  Labels:

public scala.Function1 curried();
  Signature: ()Lscala/Function1;
  Code:
   Stack=1, Locals=1, Args_size=1
	aload_0
	invokestatic	Method scala/Function3$class.curried:(Lscala/Function3;)Lscala/Function1;
	areturn
  Labels:

public scala.Function1 curry();
  Signature: ()Lscala/Function1;
  Code:
   Stack=1, Locals=1, Args_size=1
	aload_0
	invokestatic	Method scala/Function3$class.curry:(Lscala/Function3;)Lscala/Function1;
	areturn
  Labels:
  Deprecated: true

public scala.Function1 tupled();
  Signature: ()Lscala/Function1;
  Code:
   Stack=1, Locals=1, Args_size=1
	aload_0
	invokestatic	Method scala/Function3$class.tupled:(Lscala/Function3;)Lscala/Function1;
	areturn
  Labels:

public scala.Option unapply(scala.reflect.PolyType);
  Signature: (Lscala/reflect/PolyType;)Lscala/Option;
  Code:
   Stack=7, Locals=2, Args_size=2
	aload_1
	ifnonnull	l1 // new
	getstatic	Field scala/None$.MODULE$:Lscala/None$;
	goto	l2 // areturn
l1	new	class scala/Some
	dup
	new	class scala/Tuple3
	dup
	aload_1
	invokevirtual	Method scala/reflect/PolyType.typeParams:()Lscala/collection/immutable/List;
	aload_1
	invokevirtual	Method scala/reflect/PolyType.typeBounds:()Lscala/collection/immutable/List;
	aload_1
	invokevirtual	Method scala/reflect/PolyType.resultType:()Lscala/reflect/Type;
	invokespecial	Method scala/Tuple3."<init>":(Ljava/lang/Object;Ljava/lang/Object;Ljava/lang/Object;)V
	invokespecial	Method scala/Some."<init>":(Ljava/lang/Object;)V
l2	areturn
  Labels:
   	l1 = 10 // new
   	l2 = 36 // areturn
  LocalVariableTable: 
   Start  Length  Slot  Name   Signature
   0      37      0    this       Lscala/reflect/PolyType$;
   0      37      1    x$0       Lscala/reflect/PolyType;


public scala.reflect.PolyType apply(scala.collection.immutable.List, scala.collection.immutable.List, scala.reflect.Type);
  Signature: (Lscala/collection/immutable/List;Lscala/collection/immutable/List;Lscala/reflect/Type;)Lscala/reflect/PolyType;
  Code:
   Stack=5, Locals=4, Args_size=4
	new	class scala/reflect/PolyType
	dup
	aload_1
	aload_2
	aload_3
	invokespecial	Method scala/reflect/PolyType."<init>":(Lscala/collection/immutable/List;Lscala/collection/immutable/List;Lscala/reflect/Type;)V
	areturn
  Labels:
  LocalVariableTable: 
   Start  Length  Slot  Name   Signature
   0      11      0    this       Lscala/reflect/PolyType$;
   0      11      1    typeParams       Lscala/collection/immutable/List;
   0      11      2    typeBounds       Lscala/collection/immutable/List;
   0      11      3    resultType       Lscala/reflect/Type;


public java.lang.Object apply(java.lang.Object, java.lang.Object, java.lang.Object);
  Signature: (Ljava/lang/Object;Ljava/lang/Object;Ljava/lang/Object;)Ljava/lang/Object;
  Code:
   Stack=4, Locals=4, Args_size=4
	aload_0
	aload_1
	checkcast	class scala/collection/immutable/List
	aload_2
	checkcast	class scala/collection/immutable/List
	aload_3
	checkcast	class scala/reflect/Type
	invokevirtual	Method apply:(Lscala/collection/immutable/List;Lscala/collection/immutable/List;Lscala/reflect/Type;)Lscala/reflect/PolyType;
	areturn
  Labels:
  LocalVariableTable: 
   Start  Length  Slot  Name   Signature
   0      17      0    this       Lscala/reflect/PolyType$;
   0      17      1    v1       Ljava/lang/Object;
   0      17      2    v2       Ljava/lang/Object;
   0      17      3    v3       Ljava/lang/Object;


private scala.reflect.PolyType$();
  Signature: ()V
  Code:
   Stack=1, Locals=1, Args_size=1
	aload_0
	invokespecial	Method java/lang/Object."<init>":()V
	aload_0
	putstatic	Field MODULE$:Lscala/reflect/PolyType$;
	aload_0
	invokestatic	Method scala/Function3$class.$init$:(Lscala/Function3;)V
	return
  Labels:

}

