Compiled from "Type.scala"
public final class scala.reflect.PrefixedType$ extends scala.runtime.AbstractFunction2 implements scala.ScalaObject
  SourceFile: "Type.scala"
  Scala: length = 0x
   
  minor version: 0
  major version: 49
  Constant pool:
Asciz	SourceFile;
Asciz	Type.scala;
Asciz	MODULE$;
Asciz	Lscala/reflect/PrefixedType$;;
Asciz	<clinit>;
Asciz	()V;
Asciz	Code;
Asciz	scala/reflect/PrefixedType$;
class	scala/reflect/PrefixedType$
Asciz	<init>;
NameAndType	"<init>":()V
Method	scala/reflect/PrefixedType$."<init>":()V
Asciz	unapply;
Asciz	(Lscala/reflect/PrefixedType;)Lscala/Option;;
Asciz	LineNumberTable;
Asciz	scala/None$;
class	scala/None$
Asciz	Lscala/None$;;
NameAndType	MODULE$:Lscala/None$;
Field	scala/None$.MODULE$:Lscala/None$;
Asciz	scala/Some;
class	scala/Some
Asciz	scala/Tuple2;
class	scala/Tuple2
Asciz	scala/reflect/PrefixedType;
class	scala/reflect/PrefixedType
Asciz	pre;
Asciz	()Lscala/reflect/Type;;
NameAndType	pre:()Lscala/reflect/Type;
Method	scala/reflect/PrefixedType.pre:()Lscala/reflect/Type;
Asciz	sym;
Asciz	()Lscala/reflect/Symbol;;
NameAndType	sym:()Lscala/reflect/Symbol;
Method	scala/reflect/PrefixedType.sym:()Lscala/reflect/Symbol;
Asciz	(Ljava/lang/Object;Ljava/lang/Object;)V;
NameAndType	"<init>":(Ljava/lang/Object;Ljava/lang/Object;)V
Method	scala/Tuple2."<init>":(Ljava/lang/Object;Ljava/lang/Object;)V
Asciz	(Ljava/lang/Object;)V;
NameAndType	"<init>":(Ljava/lang/Object;)V
Method	scala/Some."<init>":(Ljava/lang/Object;)V
Asciz	this;
Asciz	x$0;
Asciz	Lscala/reflect/PrefixedType;;
Asciz	LocalVariableTable;
Asciz	apply;
Asciz	(Lscala/reflect/Type;Lscala/reflect/Symbol;)Lscala/reflect/PrefixedType;;
Asciz	(Lscala/reflect/Type;Lscala/reflect/Symbol;)V;
NameAndType	"<init>":(Lscala/reflect/Type;Lscala/reflect/Symbol;)V
Method	scala/reflect/PrefixedType."<init>":(Lscala/reflect/Type;Lscala/reflect/Symbol;)V
Asciz	Lscala/reflect/Type;;
Asciz	Lscala/reflect/Symbol;;
Asciz	(Ljava/lang/Object;Ljava/lang/Object;)Ljava/lang/Object;;
Asciz	scala/reflect/Type;
class	scala/reflect/Type
Asciz	scala/reflect/Symbol;
class	scala/reflect/Symbol
NameAndType	apply:(Lscala/reflect/Type;Lscala/reflect/Symbol;)Lscala/reflect/PrefixedType;
Method	scala/reflect/PrefixedType$.apply:(Lscala/reflect/Type;Lscala/reflect/Symbol;)Lscala/reflect/PrefixedType;
Asciz	v1;
Asciz	Ljava/lang/Object;;
Asciz	v2;
Asciz	scala/runtime/AbstractFunction2;
class	scala/runtime/AbstractFunction2
Method	scala/runtime/AbstractFunction2."<init>":()V
NameAndType	MODULE$:Lscala/reflect/PrefixedType$;
Field	scala/reflect/PrefixedType$.MODULE$:Lscala/reflect/PrefixedType$;
Asciz	Scala;
Asciz	scala/ScalaObject;
class	scala/ScalaObject

{
public static final scala.reflect.PrefixedType$ MODULE$;
  Signature: Lscala/reflect/PrefixedType$;

public static {};
  Signature: ()V
  Code:
   Stack=1, Locals=0, Args_size=0
	new	class scala/reflect/PrefixedType$
	invokespecial	Method "<init>":()V
	return
  Labels:

public scala.Option unapply(scala.reflect.PrefixedType);
  Signature: (Lscala/reflect/PrefixedType;)Lscala/Option;
  Code:
   Stack=6, Locals=2, Args_size=2
	aload_1
	ifnonnull	l1 // new
	getstatic	Field scala/None$.MODULE$:Lscala/None$;
	goto	l2 // areturn
l1	new	class scala/Some
	dup
	new	class scala/Tuple2
	dup
	aload_1
	invokevirtual	Method scala/reflect/PrefixedType.pre:()Lscala/reflect/Type;
	aload_1
	invokevirtual	Method scala/reflect/PrefixedType.sym:()Lscala/reflect/Symbol;
	invokespecial	Method scala/Tuple2."<init>":(Ljava/lang/Object;Ljava/lang/Object;)V
	invokespecial	Method scala/Some."<init>":(Ljava/lang/Object;)V
l2	areturn
  Labels:
   	l1 = 10 // new
   	l2 = 32 // areturn
  LocalVariableTable: 
   Start  Length  Slot  Name   Signature
   0      33      0    this       Lscala/reflect/PrefixedType$;
   0      33      1    x$0       Lscala/reflect/PrefixedType;


public scala.reflect.PrefixedType apply(scala.reflect.Type, scala.reflect.Symbol);
  Signature: (Lscala/reflect/Type;Lscala/reflect/Symbol;)Lscala/reflect/PrefixedType;
  Code:
   Stack=4, Locals=3, Args_size=3
	new	class scala/reflect/PrefixedType
	dup
	aload_1
	aload_2
	invokespecial	Method scala/reflect/PrefixedType."<init>":(Lscala/reflect/Type;Lscala/reflect/Symbol;)V
	areturn
  Labels:
  LocalVariableTable: 
   Start  Length  Slot  Name   Signature
   0      10      0    this       Lscala/reflect/PrefixedType$;
   0      10      1    pre       Lscala/reflect/Type;
   0      10      2    sym       Lscala/reflect/Symbol;


public java.lang.Object apply(java.lang.Object, java.lang.Object);
  Signature: (Ljava/lang/Object;Ljava/lang/Object;)Ljava/lang/Object;
  Code:
   Stack=3, Locals=3, Args_size=3
	aload_0
	aload_1
	checkcast	class scala/reflect/Type
	aload_2
	checkcast	class scala/reflect/Symbol
	invokevirtual	Method apply:(Lscala/reflect/Type;Lscala/reflect/Symbol;)Lscala/reflect/PrefixedType;
	areturn
  Labels:
  LocalVariableTable: 
   Start  Length  Slot  Name   Signature
   0      13      0    this       Lscala/reflect/PrefixedType$;
   0      13      1    v1       Ljava/lang/Object;
   0      13      2    v2       Ljava/lang/Object;


private scala.reflect.PrefixedType$();
  Signature: ()V
  Code:
   Stack=1, Locals=1, Args_size=1
	aload_0
	invokespecial	Method scala/runtime/AbstractFunction2."<init>":()V
	aload_0
	putstatic	Field MODULE$:Lscala/reflect/PrefixedType$;
	return
  Labels:

}

