Compiled from "Print.scala"
public final class scala.reflect.Print$ extends java.lang.Object implements scala.Function1,scala.ScalaObject
  SourceFile: "Print.scala"
  Scala: length = 0x
   
  Signature: length = 0x2
   02 74 
  InnerClass: 
   public final $anon$1=class scala/Predef$$anon$1 of class scala/Predef
   public final $anonfun$1=class scala/reflect/Print$$anonfun$1 of class scala/reflect/Print
   public GenericCanBuildFrom=class scala/collection/generic/TraversableFactory$GenericCanBuildFrom of class scala/collection/generic/TraversableFactory
  minor version: 0
  major version: 49
  Constant pool:
Asciz	SourceFile;
Asciz	Print.scala;
Asciz	MODULE$;
Asciz	Lscala/reflect/Print$;;
Asciz	<clinit>;
Asciz	()V;
Asciz	Code;
Asciz	scala/reflect/Print$;
class	scala/reflect/Print$
Asciz	<init>;
NameAndType	"<init>":()V
Method	scala/reflect/Print$."<init>":()V
Asciz	apply$mcVI$sp;
Asciz	(I)V;
Asciz	LineNumberTable;
Asciz	scala/Function1$class;
class	scala/Function1$class
Asciz	(Lscala/Function1;I)V;
NameAndType	apply$mcVI$sp:(Lscala/Function1;I)V
Method	scala/Function1$class.apply$mcVI$sp:(Lscala/Function1;I)V
Asciz	this;
Asciz	v1;
Asciz	I;
Asciz	LocalVariableTable;
Asciz	apply$mcZI$sp;
Asciz	(I)Z;
Asciz	(Lscala/Function1;I)Z;
NameAndType	apply$mcZI$sp:(Lscala/Function1;I)Z
Method	scala/Function1$class.apply$mcZI$sp:(Lscala/Function1;I)Z
Asciz	apply$mcII$sp;
Asciz	(I)I;
Asciz	(Lscala/Function1;I)I;
NameAndType	apply$mcII$sp:(Lscala/Function1;I)I
Method	scala/Function1$class.apply$mcII$sp:(Lscala/Function1;I)I
Asciz	apply$mcLI$sp;
Asciz	(I)J;
Asciz	(Lscala/Function1;I)J;
NameAndType	apply$mcLI$sp:(Lscala/Function1;I)J
Method	scala/Function1$class.apply$mcLI$sp:(Lscala/Function1;I)J
Asciz	apply$mcDI$sp;
Asciz	(I)D;
Asciz	(Lscala/Function1;I)D;
NameAndType	apply$mcDI$sp:(Lscala/Function1;I)D
Method	scala/Function1$class.apply$mcDI$sp:(Lscala/Function1;I)D
Asciz	apply$mcVL$sp;
Asciz	(J)V;
Asciz	(Lscala/Function1;J)V;
NameAndType	apply$mcVL$sp:(Lscala/Function1;J)V
Method	scala/Function1$class.apply$mcVL$sp:(Lscala/Function1;J)V
Asciz	J;
Asciz	apply$mcZL$sp;
Asciz	(J)Z;
Asciz	(Lscala/Function1;J)Z;
NameAndType	apply$mcZL$sp:(Lscala/Function1;J)Z
Method	scala/Function1$class.apply$mcZL$sp:(Lscala/Function1;J)Z
Asciz	apply$mcIL$sp;
Asciz	(J)I;
Asciz	(Lscala/Function1;J)I;
NameAndType	apply$mcIL$sp:(Lscala/Function1;J)I
Method	scala/Function1$class.apply$mcIL$sp:(Lscala/Function1;J)I
Asciz	apply$mcLL$sp;
Asciz	(J)J;
Asciz	(Lscala/Function1;J)J;
NameAndType	apply$mcLL$sp:(Lscala/Function1;J)J
Method	scala/Function1$class.apply$mcLL$sp:(Lscala/Function1;J)J
Asciz	apply$mcDL$sp;
Asciz	(J)D;
Asciz	(Lscala/Function1;J)D;
NameAndType	apply$mcDL$sp:(Lscala/Function1;J)D
Method	scala/Function1$class.apply$mcDL$sp:(Lscala/Function1;J)D
Asciz	apply$mcVD$sp;
Asciz	(D)V;
Asciz	(Lscala/Function1;D)V;
NameAndType	apply$mcVD$sp:(Lscala/Function1;D)V
Method	scala/Function1$class.apply$mcVD$sp:(Lscala/Function1;D)V
Asciz	D;
Asciz	apply$mcZD$sp;
Asciz	(D)Z;
Asciz	(Lscala/Function1;D)Z;
NameAndType	apply$mcZD$sp:(Lscala/Function1;D)Z
Method	scala/Function1$class.apply$mcZD$sp:(Lscala/Function1;D)Z
Asciz	apply$mcID$sp;
Asciz	(D)I;
Asciz	(Lscala/Function1;D)I;
NameAndType	apply$mcID$sp:(Lscala/Function1;D)I
Method	scala/Function1$class.apply$mcID$sp:(Lscala/Function1;D)I
Asciz	apply$mcLD$sp;
Asciz	(D)J;
Asciz	(Lscala/Function1;D)J;
NameAndType	apply$mcLD$sp:(Lscala/Function1;D)J
Method	scala/Function1$class.apply$mcLD$sp:(Lscala/Function1;D)J
Asciz	apply$mcDD$sp;
Asciz	(D)D;
Asciz	(Lscala/Function1;D)D;
NameAndType	apply$mcDD$sp:(Lscala/Function1;D)D
Method	scala/Function1$class.apply$mcDD$sp:(Lscala/Function1;D)D
Asciz	toString;
Asciz	()Ljava/lang/String;;
Asciz	(Lscala/Function1;)Ljava/lang/String;;
NameAndType	toString:(Lscala/Function1;)Ljava/lang/String;
Method	scala/Function1$class.toString:(Lscala/Function1;)Ljava/lang/String;
Asciz	compose;
Asciz	(Lscala/Function1;)Lscala/Function1;;
Asciz	(Lscala/Function1;Lscala/Function1;)Lscala/Function1;;
NameAndType	compose:(Lscala/Function1;Lscala/Function1;)Lscala/Function1;
Method	scala/Function1$class.compose:(Lscala/Function1;Lscala/Function1;)Lscala/Function1;
Asciz	g;
Asciz	Lscala/Function1;;
Asciz	compose$mcVI$sp;
NameAndType	compose$mcVI$sp:(Lscala/Function1;Lscala/Function1;)Lscala/Function1;
Method	scala/Function1$class.compose$mcVI$sp:(Lscala/Function1;Lscala/Function1;)Lscala/Function1;
Asciz	compose$mcZI$sp;
NameAndType	compose$mcZI$sp:(Lscala/Function1;Lscala/Function1;)Lscala/Function1;
Method	scala/Function1$class.compose$mcZI$sp:(Lscala/Function1;Lscala/Function1;)Lscala/Function1;
Asciz	compose$mcII$sp;
NameAndType	compose$mcII$sp:(Lscala/Function1;Lscala/Function1;)Lscala/Function1;
Method	scala/Function1$class.compose$mcII$sp:(Lscala/Function1;Lscala/Function1;)Lscala/Function1;
Asciz	compose$mcLI$sp;
NameAndType	compose$mcLI$sp:(Lscala/Function1;Lscala/Function1;)Lscala/Function1;
Method	scala/Function1$class.compose$mcLI$sp:(Lscala/Function1;Lscala/Function1;)Lscala/Function1;
Asciz	compose$mcDI$sp;
NameAndType	compose$mcDI$sp:(Lscala/Function1;Lscala/Function1;)Lscala/Function1;
Method	scala/Function1$class.compose$mcDI$sp:(Lscala/Function1;Lscala/Function1;)Lscala/Function1;
Asciz	compose$mcVL$sp;
NameAndType	compose$mcVL$sp:(Lscala/Function1;Lscala/Function1;)Lscala/Function1;
Method	scala/Function1$class.compose$mcVL$sp:(Lscala/Function1;Lscala/Function1;)Lscala/Function1;
Asciz	compose$mcZL$sp;
NameAndType	compose$mcZL$sp:(Lscala/Function1;Lscala/Function1;)Lscala/Function1;
Method	scala/Function1$class.compose$mcZL$sp:(Lscala/Function1;Lscala/Function1;)Lscala/Function1;
Asciz	compose$mcIL$sp;
NameAndType	compose$mcIL$sp:(Lscala/Function1;Lscala/Function1;)Lscala/Function1;
Method	scala/Function1$class.compose$mcIL$sp:(Lscala/Function1;Lscala/Function1;)Lscala/Function1;
Asciz	compose$mcLL$sp;
NameAndType	compose$mcLL$sp:(Lscala/Function1;Lscala/Function1;)Lscala/Function1;
Method	scala/Function1$class.compose$mcLL$sp:(Lscala/Function1;Lscala/Function1;)Lscala/Function1;
Asciz	compose$mcDL$sp;
NameAndType	compose$mcDL$sp:(Lscala/Function1;Lscala/Function1;)Lscala/Function1;
Method	scala/Function1$class.compose$mcDL$sp:(Lscala/Function1;Lscala/Function1;)Lscala/Function1;
Asciz	compose$mcVD$sp;
NameAndType	compose$mcVD$sp:(Lscala/Function1;Lscala/Function1;)Lscala/Function1;
Method	scala/Function1$class.compose$mcVD$sp:(Lscala/Function1;Lscala/Function1;)Lscala/Function1;
Asciz	compose$mcZD$sp;
NameAndType	compose$mcZD$sp:(Lscala/Function1;Lscala/Function1;)Lscala/Function1;
Method	scala/Function1$class.compose$mcZD$sp:(Lscala/Function1;Lscala/Function1;)Lscala/Function1;
Asciz	compose$mcID$sp;
NameAndType	compose$mcID$sp:(Lscala/Function1;Lscala/Function1;)Lscala/Function1;
Method	scala/Function1$class.compose$mcID$sp:(Lscala/Function1;Lscala/Function1;)Lscala/Function1;
Asciz	compose$mcLD$sp;
NameAndType	compose$mcLD$sp:(Lscala/Function1;Lscala/Function1;)Lscala/Function1;
Method	scala/Function1$class.compose$mcLD$sp:(Lscala/Function1;Lscala/Function1;)Lscala/Function1;
Asciz	compose$mcDD$sp;
NameAndType	compose$mcDD$sp:(Lscala/Function1;Lscala/Function1;)Lscala/Function1;
Method	scala/Function1$class.compose$mcDD$sp:(Lscala/Function1;Lscala/Function1;)Lscala/Function1;
Asciz	andThen;
NameAndType	andThen:(Lscala/Function1;Lscala/Function1;)Lscala/Function1;
Method	scala/Function1$class.andThen:(Lscala/Function1;Lscala/Function1;)Lscala/Function1;
Asciz	andThen$mcVI$sp;
NameAndType	andThen$mcVI$sp:(Lscala/Function1;Lscala/Function1;)Lscala/Function1;
Method	scala/Function1$class.andThen$mcVI$sp:(Lscala/Function1;Lscala/Function1;)Lscala/Function1;
Asciz	andThen$mcZI$sp;
NameAndType	andThen$mcZI$sp:(Lscala/Function1;Lscala/Function1;)Lscala/Function1;
Method	scala/Function1$class.andThen$mcZI$sp:(Lscala/Function1;Lscala/Function1;)Lscala/Function1;
Asciz	andThen$mcII$sp;
NameAndType	andThen$mcII$sp:(Lscala/Function1;Lscala/Function1;)Lscala/Function1;
Method	scala/Function1$class.andThen$mcII$sp:(Lscala/Function1;Lscala/Function1;)Lscala/Function1;
Asciz	andThen$mcLI$sp;
NameAndType	andThen$mcLI$sp:(Lscala/Function1;Lscala/Function1;)Lscala/Function1;
Method	scala/Function1$class.andThen$mcLI$sp:(Lscala/Function1;Lscala/Function1;)Lscala/Function1;
Asciz	andThen$mcDI$sp;
NameAndType	andThen$mcDI$sp:(Lscala/Function1;Lscala/Function1;)Lscala/Function1;
Method	scala/Function1$class.andThen$mcDI$sp:(Lscala/Function1;Lscala/Function1;)Lscala/Function1;
Asciz	andThen$mcVL$sp;
NameAndType	andThen$mcVL$sp:(Lscala/Function1;Lscala/Function1;)Lscala/Function1;
Method	scala/Function1$class.andThen$mcVL$sp:(Lscala/Function1;Lscala/Function1;)Lscala/Function1;
Asciz	andThen$mcZL$sp;
NameAndType	andThen$mcZL$sp:(Lscala/Function1;Lscala/Function1;)Lscala/Function1;
Method	scala/Function1$class.andThen$mcZL$sp:(Lscala/Function1;Lscala/Function1;)Lscala/Function1;
Asciz	andThen$mcIL$sp;
NameAndType	andThen$mcIL$sp:(Lscala/Function1;Lscala/Function1;)Lscala/Function1;
Method	scala/Function1$class.andThen$mcIL$sp:(Lscala/Function1;Lscala/Function1;)Lscala/Function1;
Asciz	andThen$mcLL$sp;
NameAndType	andThen$mcLL$sp:(Lscala/Function1;Lscala/Function1;)Lscala/Function1;
Method	scala/Function1$class.andThen$mcLL$sp:(Lscala/Function1;Lscala/Function1;)Lscala/Function1;
Asciz	andThen$mcDL$sp;
NameAndType	andThen$mcDL$sp:(Lscala/Function1;Lscala/Function1;)Lscala/Function1;
Method	scala/Function1$class.andThen$mcDL$sp:(Lscala/Function1;Lscala/Function1;)Lscala/Function1;
Asciz	andThen$mcVD$sp;
NameAndType	andThen$mcVD$sp:(Lscala/Function1;Lscala/Function1;)Lscala/Function1;
Method	scala/Function1$class.andThen$mcVD$sp:(Lscala/Function1;Lscala/Function1;)Lscala/Function1;
Asciz	andThen$mcZD$sp;
NameAndType	andThen$mcZD$sp:(Lscala/Function1;Lscala/Function1;)Lscala/Function1;
Method	scala/Function1$class.andThen$mcZD$sp:(Lscala/Function1;Lscala/Function1;)Lscala/Function1;
Asciz	andThen$mcID$sp;
NameAndType	andThen$mcID$sp:(Lscala/Function1;Lscala/Function1;)Lscala/Function1;
Method	scala/Function1$class.andThen$mcID$sp:(Lscala/Function1;Lscala/Function1;)Lscala/Function1;
Asciz	andThen$mcLD$sp;
NameAndType	andThen$mcLD$sp:(Lscala/Function1;Lscala/Function1;)Lscala/Function1;
Method	scala/Function1$class.andThen$mcLD$sp:(Lscala/Function1;Lscala/Function1;)Lscala/Function1;
Asciz	andThen$mcDD$sp;
NameAndType	andThen$mcDD$sp:(Lscala/Function1;Lscala/Function1;)Lscala/Function1;
Method	scala/Function1$class.andThen$mcDD$sp:(Lscala/Function1;Lscala/Function1;)Lscala/Function1;
Asciz	apply;
Asciz	(Ljava/lang/Object;)Ljava/lang/String;;
Asciz	scala/reflect/Code;
class	scala/reflect/Code
Asciz	tree;
Asciz	()Lscala/reflect/Tree;;
NameAndType	tree:()Lscala/reflect/Tree;
Method	scala/reflect/Code.tree:()Lscala/reflect/Tree;
Asciz	(Lscala/reflect/Tree;)Ljava/lang/String;;
NameAndType	apply:(Lscala/reflect/Tree;)Ljava/lang/String;
Method	scala/reflect/Print$.apply:(Lscala/reflect/Tree;)Ljava/lang/String;
Asciz	scala/reflect/Tree;
class	scala/reflect/Tree
Asciz	scala/reflect/Symbol;
class	scala/reflect/Symbol
Asciz	(Lscala/reflect/Symbol;)Ljava/lang/String;;
NameAndType	apply:(Lscala/reflect/Symbol;)Ljava/lang/String;
Method	scala/reflect/Print$.apply:(Lscala/reflect/Symbol;)Ljava/lang/String;
Asciz	scala/reflect/Type;
class	scala/reflect/Type
Asciz	(Lscala/reflect/Type;)Ljava/lang/String;;
NameAndType	apply:(Lscala/reflect/Type;)Ljava/lang/String;
Method	scala/reflect/Print$.apply:(Lscala/reflect/Type;)Ljava/lang/String;
Asciz	UnknownAny;
String	UnknownAny
Asciz	any;
Asciz	Ljava/lang/Object;;
Asciz	scala/reflect/Ident;
class	scala/reflect/Ident
Asciz	sym;
Asciz	()Lscala/reflect/Symbol;;
NameAndType	sym:()Lscala/reflect/Symbol;
Method	scala/reflect/Ident.sym:()Lscala/reflect/Symbol;
Asciz	scala/reflect/Select;
class	scala/reflect/Select
Asciz	scala/collection/mutable/StringBuilder;
class	scala/collection/mutable/StringBuilder
Method	scala/collection/mutable/StringBuilder."<init>":()V
Asciz	qual;
NameAndType	qual:()Lscala/reflect/Tree;
Method	scala/reflect/Select.qual:()Lscala/reflect/Tree;
Asciz	append;
Asciz	(Ljava/lang/Object;)Lscala/collection/mutable/StringBuilder;;
NameAndType	append:(Ljava/lang/Object;)Lscala/collection/mutable/StringBuilder;
Method	scala/collection/mutable/StringBuilder.append:(Ljava/lang/Object;)Lscala/collection/mutable/StringBuilder;
Asciz	.;
String	.
Method	scala/reflect/Select.sym:()Lscala/reflect/Symbol;
NameAndType	toString:()Ljava/lang/String;
Method	scala/collection/mutable/StringBuilder.toString:()Ljava/lang/String;
Asciz	scala/reflect/Literal;
class	scala/reflect/Literal
Asciz	value;
Asciz	()Ljava/lang/Object;;
NameAndType	value:()Ljava/lang/Object;
Method	scala/reflect/Literal.value:()Ljava/lang/Object;
Asciz	java/lang/String;
class	java/lang/String
Asciz	\";
String	\"
Asciz	java/lang/Object;
class	java/lang/Object
Method	java/lang/Object.toString:()Ljava/lang/String;
Asciz	scala/reflect/Apply;
class	scala/reflect/Apply
Asciz	fun;
NameAndType	fun:()Lscala/reflect/Tree;
Method	scala/reflect/Apply.fun:()Lscala/reflect/Tree;
Asciz	args;
Asciz	()Lscala/collection/immutable/List;;
NameAndType	args:()Lscala/collection/immutable/List;
Method	scala/reflect/Apply.args:()Lscala/collection/immutable/List;
Asciz	scala/collection/immutable/List$;
class	scala/collection/immutable/List$
Asciz	Lscala/collection/immutable/List$;;
NameAndType	MODULE$:Lscala/collection/immutable/List$;
Field	scala/collection/immutable/List$.MODULE$:Lscala/collection/immutable/List$;
Asciz	scala/collection/generic/TraversableFactory$GenericCanBuildFrom;
class	scala/collection/generic/TraversableFactory$GenericCanBuildFrom
Asciz	(Lscala/collection/generic/TraversableFactory;)V;
NameAndType	"<init>":(Lscala/collection/generic/TraversableFactory;)V
Method	scala/collection/generic/TraversableFactory$GenericCanBuildFrom."<init>":(Lscala/collection/generic/TraversableFactory;)V
Asciz	scala/collection/TraversableLike;
class	scala/collection/TraversableLike
Asciz	map;
Asciz	(Lscala/Function1;Lscala/collection/generic/CanBuildFrom;)Ljava/lang/Object;;
NameAndType	map:(Lscala/Function1;Lscala/collection/generic/CanBuildFrom;)Ljava/lang/Object;
InterfaceMethod	scala/collection/TraversableLike.map:(Lscala/Function1;Lscala/collection/generic/CanBuildFrom;)Ljava/lang/Object;
Asciz	scala/collection/TraversableOnce;
class	scala/collection/TraversableOnce
Asciz	(;
String	(
Asciz	, ;
String	, 
Asciz	);
String	)
Asciz	mkString;
Asciz	(Ljava/lang/String;Ljava/lang/String;Ljava/lang/String;)Ljava/lang/String;;
NameAndType	mkString:(Ljava/lang/String;Ljava/lang/String;Ljava/lang/String;)Ljava/lang/String;
InterfaceMethod	scala/collection/TraversableOnce.mkString:(Ljava/lang/String;Ljava/lang/String;Ljava/lang/String;)Ljava/lang/String;
Asciz	scala/reflect/TypeApply;
class	scala/reflect/TypeApply
Method	scala/reflect/TypeApply.fun:()Lscala/reflect/Tree;
Method	scala/reflect/TypeApply.args:()Lscala/collection/immutable/List;
Asciz	[;
String	[
Asciz	];
String	]
Asciz	scala/reflect/Function;
class	scala/reflect/Function
Asciz	params;
NameAndType	params:()Lscala/collection/immutable/List;
Method	scala/reflect/Function.params:()Lscala/collection/immutable/List;
Asciz	 => ;
String	 => 
Asciz	body;
NameAndType	body:()Lscala/reflect/Tree;
Method	scala/reflect/Function.body:()Lscala/reflect/Tree;
Asciz	scala/reflect/This;
class	scala/reflect/This
Method	scala/reflect/This.sym:()Lscala/reflect/Symbol;
Asciz	.this;
String	.this
Asciz	scala/reflect/Block;
class	scala/reflect/Block
Asciz	stats;
NameAndType	stats:()Lscala/collection/immutable/List;
Method	scala/reflect/Block.stats:()Lscala/collection/immutable/List;
Asciz	scala/Predef$;
class	scala/Predef$
Asciz	Lscala/Predef$;;
NameAndType	MODULE$:Lscala/Predef$;
Field	scala/Predef$.MODULE$:Lscala/Predef$;
Asciz	expr;
NameAndType	expr:()Lscala/reflect/Tree;
Method	scala/reflect/Block.expr:()Lscala/reflect/Tree;
Asciz	[Ljava/lang/Object;;
class	"[Ljava/lang/Object;"
Asciz	wrapRefArray;
Asciz	([Ljava/lang/Object;)Lscala/collection/mutable/WrappedArray;;
NameAndType	wrapRefArray:([Ljava/lang/Object;)Lscala/collection/mutable/WrappedArray;
Method	scala/Predef$.wrapRefArray:([Ljava/lang/Object;)Lscala/collection/mutable/WrappedArray;
Asciz	toList;
NameAndType	toList:()Lscala/collection/immutable/List;
InterfaceMethod	scala/collection/TraversableOnce.toList:()Lscala/collection/immutable/List;
Asciz	scala/collection/immutable/List;
class	scala/collection/immutable/List
Asciz	$colon$colon$colon;
Asciz	(Lscala/collection/immutable/List;)Lscala/collection/immutable/List;;
NameAndType	$colon$colon$colon:(Lscala/collection/immutable/List;)Lscala/collection/immutable/List;
Method	scala/collection/immutable/List.$colon$colon$colon:(Lscala/collection/immutable/List;)Lscala/collection/immutable/List;
Asciz	canBuildFrom;
Asciz	()Lscala/collection/generic/CanBuildFrom;;
NameAndType	canBuildFrom:()Lscala/collection/generic/CanBuildFrom;
Method	scala/collection/immutable/List$.canBuildFrom:()Lscala/collection/generic/CanBuildFrom;
Asciz	{\n;
String	{\n
Asciz	;\n;
String	;\n
Asciz	\n};
String	\n}
Asciz	scala/reflect/New;
class	scala/reflect/New
Asciz	new ;
String	new 
NameAndType	sym:()Lscala/reflect/Tree;
Method	scala/reflect/New.sym:()Lscala/reflect/Tree;
Asciz	scala/reflect/If;
class	scala/reflect/If
Asciz	if (;
String	if (
Asciz	condition;
NameAndType	condition:()Lscala/reflect/Tree;
Method	scala/reflect/If.condition:()Lscala/reflect/Tree;
Asciz	) ;
String	) 
Asciz	trueCase;
NameAndType	trueCase:()Lscala/reflect/Tree;
Method	scala/reflect/If.trueCase:()Lscala/reflect/Tree;
Asciz	 else ;
String	 else 
Asciz	falseCase;
NameAndType	falseCase:()Lscala/reflect/Tree;
Method	scala/reflect/If.falseCase:()Lscala/reflect/Tree;
Asciz	scala/reflect/Assign;
class	scala/reflect/Assign
Asciz	destination;
NameAndType	destination:()Lscala/reflect/Tree;
Method	scala/reflect/Assign.destination:()Lscala/reflect/Tree;
Asciz	source;
NameAndType	source:()Lscala/reflect/Tree;
Method	scala/reflect/Assign.source:()Lscala/reflect/Tree;
Asciz	 = ;
String	 = 
Asciz	???;
String	???
Asciz	scala/reflect/Target;
class	scala/reflect/Target
Asciz	target ;
String	target 
Asciz	()Lscala/reflect/LabelSymbol;;
NameAndType	sym:()Lscala/reflect/LabelSymbol;
Method	scala/reflect/Target.sym:()Lscala/reflect/LabelSymbol;
Asciz	 {\n;
String	 {\n
Method	scala/reflect/Target.body:()Lscala/reflect/Tree;
Asciz	scala/reflect/Goto;
class	scala/reflect/Goto
Asciz	goto ;
String	goto 
Asciz	target;
NameAndType	target:()Lscala/reflect/LabelSymbol;
Method	scala/reflect/Goto.target:()Lscala/reflect/LabelSymbol;
Asciz	Lscala/reflect/Tree;;
Asciz	temp11;
Asciz	Lscala/reflect/Select;;
Asciz	temp14;
Asciz	Lscala/reflect/Literal;;
Asciz	temp15;
Asciz	temp16;
Asciz	Lscala/reflect/Apply;;
Asciz	temp19;
Asciz	Lscala/reflect/TypeApply;;
Asciz	temp22;
Asciz	Lscala/reflect/Function;;
Asciz	temp27;
Asciz	Lscala/reflect/Block;;
Asciz	temp28;
Asciz	Lscala/collection/immutable/List;;
Asciz	temp32;
Asciz	Lscala/reflect/If;;
Asciz	temp36;
Asciz	Lscala/reflect/Assign;;
Asciz	temp37;
Asciz	temp38;
Asciz	temp39;
Asciz	Lscala/reflect/Target;;
Asciz	scala/reflect/Class;
class	scala/reflect/Class
Asciz	fullname;
NameAndType	fullname:()Ljava/lang/String;
Method	scala/reflect/Class.fullname:()Ljava/lang/String;
int	46;
Asciz	lastIndexOf;
NameAndType	lastIndexOf:(I)I
Method	java/lang/String.lastIndexOf:(I)I
Asciz	substring;
Asciz	(I)Ljava/lang/String;;
NameAndType	substring:(I)Ljava/lang/String;
Method	java/lang/String.substring:(I)Ljava/lang/String;
Asciz	scala/reflect/Method;
class	scala/reflect/Method
Method	scala/reflect/Method.fullname:()Ljava/lang/String;
Asciz	scala/reflect/Field;
class	scala/reflect/Field
Method	scala/reflect/Field.fullname:()Ljava/lang/String;
Asciz	scala/reflect/TypeField;
class	scala/reflect/TypeField
Method	scala/reflect/TypeField.fullname:()Ljava/lang/String;
Asciz	scala/reflect/LocalValue;
class	scala/reflect/LocalValue
Asciz	name;
NameAndType	name:()Ljava/lang/String;
Method	scala/reflect/LocalValue.name:()Ljava/lang/String;
Asciz	scala/reflect/LocalMethod;
class	scala/reflect/LocalMethod
Method	scala/reflect/LocalMethod.name:()Ljava/lang/String;
Asciz	scala/reflect/NoSymbol$;
class	scala/reflect/NoSymbol$
Asciz	Lscala/reflect/NoSymbol$;;
NameAndType	MODULE$:Lscala/reflect/NoSymbol$;
Field	scala/reflect/NoSymbol$.MODULE$:Lscala/reflect/NoSymbol$;
Asciz	equals;
Asciz	(Ljava/lang/Object;)Z;
NameAndType	equals:(Ljava/lang/Object;)Z
Method	java/lang/Object.equals:(Ljava/lang/Object;)Z
Asciz	NoSymbol;
String	NoSymbol
Asciz	scala/reflect/RootSymbol$;
class	scala/reflect/RootSymbol$
Asciz	Lscala/reflect/RootSymbol$;;
NameAndType	MODULE$:Lscala/reflect/RootSymbol$;
Field	scala/reflect/RootSymbol$.MODULE$:Lscala/reflect/RootSymbol$;
Asciz	RootSymbol;
String	RootSymbol
Asciz	scala/reflect/LabelSymbol;
class	scala/reflect/LabelSymbol
Method	scala/reflect/LabelSymbol.name:()Ljava/lang/String;
Asciz	symbol;
Asciz	Lscala/reflect/Symbol;;
Asciz	temp45;
Asciz	Lscala/reflect/Class;;
Asciz	temp46;
Asciz	Ljava/lang/String;;
Asciz	temp47;
Asciz	Lscala/reflect/Method;;
Asciz	temp48;
Asciz	temp50;
Asciz	Lscala/reflect/Field;;
Asciz	temp51;
Asciz	temp53;
Asciz	Lscala/reflect/TypeField;;
Asciz	temp54;
Asciz	temp56;
Asciz	Lscala/reflect/LocalValue;;
Asciz	temp58;
Asciz	temp60;
Asciz	Lscala/reflect/LocalMethod;;
Asciz	temp62;
Asciz	scala/reflect/NoPrefix$;
class	scala/reflect/NoPrefix$
Asciz	Lscala/reflect/NoPrefix$;;
NameAndType	MODULE$:Lscala/reflect/NoPrefix$;
Field	scala/reflect/NoPrefix$.MODULE$:Lscala/reflect/NoPrefix$;
Asciz	NoPrefix;
String	NoPrefix
Asciz	scala/reflect/NoType$;
class	scala/reflect/NoType$
Asciz	Lscala/reflect/NoType$;;
NameAndType	MODULE$:Lscala/reflect/NoType$;
Field	scala/reflect/NoType$.MODULE$:Lscala/reflect/NoType$;
Asciz	NoType;
String	NoType
Asciz	scala/reflect/NamedType;
class	scala/reflect/NamedType
Asciz	(named: ;
String	(named: 
Method	scala/reflect/NamedType.fullname:()Ljava/lang/String;
Asciz	scala/reflect/PrefixedType;
class	scala/reflect/PrefixedType
Asciz	pre;
Asciz	()Lscala/reflect/Type;;
NameAndType	pre:()Lscala/reflect/Type;
Method	scala/reflect/PrefixedType.pre:()Lscala/reflect/Type;
Method	scala/reflect/PrefixedType.sym:()Lscala/reflect/Symbol;
Asciz	scala/reflect/SingleType;
class	scala/reflect/SingleType
Method	scala/reflect/SingleType.pre:()Lscala/reflect/Type;
Method	scala/reflect/SingleType.sym:()Lscala/reflect/Symbol;
Asciz	scala/reflect/ThisType;
class	scala/reflect/ThisType
Asciz	clazz;
NameAndType	clazz:()Lscala/reflect/Symbol;
Method	scala/reflect/ThisType.clazz:()Lscala/reflect/Symbol;
Asciz	.this.type);
String	.this.type)
Asciz	scala/reflect/AppliedType;
class	scala/reflect/AppliedType
Asciz	tpe;
NameAndType	tpe:()Lscala/reflect/Type;
Method	scala/reflect/AppliedType.tpe:()Lscala/reflect/Type;
Method	scala/reflect/AppliedType.args:()Lscala/collection/immutable/List;
Asciz	scala/reflect/TypeBounds;
class	scala/reflect/TypeBounds
Asciz	lo;
NameAndType	lo:()Lscala/reflect/Type;
Method	scala/reflect/TypeBounds.lo:()Lscala/reflect/Type;
Asciz	 ... ;
String	 ... 
Asciz	hi;
NameAndType	hi:()Lscala/reflect/Type;
Method	scala/reflect/TypeBounds.hi:()Lscala/reflect/Type;
Asciz	scala/reflect/MethodType;
class	scala/reflect/MethodType
Asciz	formals;
NameAndType	formals:()Lscala/collection/immutable/List;
Method	scala/reflect/MethodType.formals:()Lscala/collection/immutable/List;
Asciz	restpe;
NameAndType	restpe:()Lscala/reflect/Type;
Method	scala/reflect/MethodType.restpe:()Lscala/reflect/Type;
Asciz	scala/reflect/PolyType;
class	scala/reflect/PolyType
Asciz	typeParams;
NameAndType	typeParams:()Lscala/collection/immutable/List;
Method	scala/reflect/PolyType.typeParams:()Lscala/collection/immutable/List;
Asciz	typeBounds;
NameAndType	typeBounds:()Lscala/collection/immutable/List;
Method	scala/reflect/PolyType.typeBounds:()Lscala/collection/immutable/List;
Asciz	scala/Tuple2;
class	scala/Tuple2
Asciz	(Ljava/lang/Object;Ljava/lang/Object;)V;
NameAndType	"<init>":(Ljava/lang/Object;Ljava/lang/Object;)V
Method	scala/Tuple2."<init>":(Ljava/lang/Object;Ljava/lang/Object;)V
Asciz	scala/Predef$$anon$1;
class	scala/Predef$$anon$1
Method	scala/Predef$$anon$1."<init>":()V
Asciz	zip;
Asciz	(Lscala/Function1;Lscala/Function1;Lscala/collection/generic/CanBuildFrom;)Ljava/lang/Object;;
NameAndType	zip:(Lscala/Function1;Lscala/Function1;Lscala/collection/generic/CanBuildFrom;)Ljava/lang/Object;
Method	scala/Tuple2.zip:(Lscala/Function1;Lscala/Function1;Lscala/collection/generic/CanBuildFrom;)Ljava/lang/Object;
Asciz	scala/reflect/Print$$anonfun$1;
class	scala/reflect/Print$$anonfun$1
Method	scala/reflect/Print$$anonfun$1."<init>":()V
Asciz	 -> ;
String	 -> 
Asciz	resultType;
NameAndType	resultType:()Lscala/reflect/Type;
Method	scala/reflect/PolyType.resultType:()Lscala/reflect/Type;
Asciz	datatype;
Asciz	Lscala/reflect/Type;;
Asciz	temp76;
Asciz	Lscala/reflect/PrefixedType;;
Asciz	temp79;
Asciz	Lscala/reflect/SingleType;;
Asciz	temp84;
Asciz	Lscala/reflect/AppliedType;;
Asciz	temp87;
Asciz	Lscala/reflect/TypeBounds;;
Asciz	temp90;
Asciz	Lscala/reflect/MethodType;;
Asciz	temp94;
Asciz	temp95;
Asciz	z;
Asciz	temp93;
Asciz	Lscala/reflect/PolyType;;
Asciz	(Ljava/lang/Object;)Ljava/lang/Object;;
NameAndType	apply:(Ljava/lang/Object;)Ljava/lang/String;
Method	scala/reflect/Print$.apply:(Ljava/lang/Object;)Ljava/lang/String;
Method	java/lang/Object."<init>":()V
NameAndType	MODULE$:Lscala/reflect/Print$;
Field	scala/reflect/Print$.MODULE$:Lscala/reflect/Print$;
Asciz	$init$;
Asciz	(Lscala/Function1;)V;
NameAndType	$init$:(Lscala/Function1;)V
Method	scala/Function1$class.$init$:(Lscala/Function1;)V
Asciz	Scala;
Asciz	Ljava/lang/Object;Lscala/Function1<Ljava/lang/Object;Ljava/lang/String;>;Lscala/ScalaObject;;
Asciz	Signature;
Asciz	InnerClasses;
Asciz	scala/Predef;
class	scala/Predef
Asciz	$anon$1;
Asciz	scala/reflect/Print;
class	scala/reflect/Print
Asciz	$anonfun$1;
Asciz	scala/collection/generic/TraversableFactory;
class	scala/collection/generic/TraversableFactory
Asciz	GenericCanBuildFrom;
Asciz	scala/Function1;
class	scala/Function1
Asciz	scala/ScalaObject;
class	scala/ScalaObject

{
public static final scala.reflect.Print$ MODULE$;
  Signature: Lscala/reflect/Print$;

public static {};
  Signature: ()V
  Code:
   Stack=1, Locals=0, Args_size=0
	new	class scala/reflect/Print$
	invokespecial	Method "<init>":()V
	return
  Labels:

public void apply$mcVI$sp(int);
  Signature: (I)V
  Code:
   Stack=2, Locals=2, Args_size=2
	aload_0
	iload_1
	invokestatic	Method scala/Function1$class.apply$mcVI$sp:(Lscala/Function1;I)V
	return
  Labels:
  LocalVariableTable: 
   Start  Length  Slot  Name   Signature
   0      6      0    this       Lscala/reflect/Print$;
   0      6      1    v1       I


public boolean apply$mcZI$sp(int);
  Signature: (I)Z
  Code:
   Stack=2, Locals=2, Args_size=2
	aload_0
	iload_1
	invokestatic	Method scala/Function1$class.apply$mcZI$sp:(Lscala/Function1;I)Z
	ireturn
  Labels:
  LocalVariableTable: 
   Start  Length  Slot  Name   Signature
   0      6      0    this       Lscala/reflect/Print$;
   0      6      1    v1       I


public int apply$mcII$sp(int);
  Signature: (I)I
  Code:
   Stack=2, Locals=2, Args_size=2
	aload_0
	iload_1
	invokestatic	Method scala/Function1$class.apply$mcII$sp:(Lscala/Function1;I)I
	ireturn
  Labels:
  LocalVariableTable: 
   Start  Length  Slot  Name   Signature
   0      6      0    this       Lscala/reflect/Print$;
   0      6      1    v1       I


public long apply$mcLI$sp(int);
  Signature: (I)J
  Code:
   Stack=2, Locals=2, Args_size=2
	aload_0
	iload_1
	invokestatic	Method scala/Function1$class.apply$mcLI$sp:(Lscala/Function1;I)J
	lreturn
  Labels:
  LocalVariableTable: 
   Start  Length  Slot  Name   Signature
   0      6      0    this       Lscala/reflect/Print$;
   0      6      1    v1       I


public double apply$mcDI$sp(int);
  Signature: (I)D
  Code:
   Stack=2, Locals=2, Args_size=2
	aload_0
	iload_1
	invokestatic	Method scala/Function1$class.apply$mcDI$sp:(Lscala/Function1;I)D
	dreturn
  Labels:
  LocalVariableTable: 
   Start  Length  Slot  Name   Signature
   0      6      0    this       Lscala/reflect/Print$;
   0      6      1    v1       I


public void apply$mcVL$sp(long);
  Signature: (J)V
  Code:
   Stack=3, Locals=3, Args_size=2
	aload_0
	lload_1
	invokestatic	Method scala/Function1$class.apply$mcVL$sp:(Lscala/Function1;J)V
	return
  Labels:
  LocalVariableTable: 
   Start  Length  Slot  Name   Signature
   0      6      0    this       Lscala/reflect/Print$;
   0      6      1    v1       J


public boolean apply$mcZL$sp(long);
  Signature: (J)Z
  Code:
   Stack=3, Locals=3, Args_size=2
	aload_0
	lload_1
	invokestatic	Method scala/Function1$class.apply$mcZL$sp:(Lscala/Function1;J)Z
	ireturn
  Labels:
  LocalVariableTable: 
   Start  Length  Slot  Name   Signature
   0      6      0    this       Lscala/reflect/Print$;
   0      6      1    v1       J


public int apply$mcIL$sp(long);
  Signature: (J)I
  Code:
   Stack=3, Locals=3, Args_size=2
	aload_0
	lload_1
	invokestatic	Method scala/Function1$class.apply$mcIL$sp:(Lscala/Function1;J)I
	ireturn
  Labels:
  LocalVariableTable: 
   Start  Length  Slot  Name   Signature
   0      6      0    this       Lscala/reflect/Print$;
   0      6      1    v1       J


public long apply$mcLL$sp(long);
  Signature: (J)J
  Code:
   Stack=3, Locals=3, Args_size=2
	aload_0
	lload_1
	invokestatic	Method scala/Function1$class.apply$mcLL$sp:(Lscala/Function1;J)J
	lreturn
  Labels:
  LocalVariableTable: 
   Start  Length  Slot  Name   Signature
   0      6      0    this       Lscala/reflect/Print$;
   0      6      1    v1       J


public double apply$mcDL$sp(long);
  Signature: (J)D
  Code:
   Stack=3, Locals=3, Args_size=2
	aload_0
	lload_1
	invokestatic	Method scala/Function1$class.apply$mcDL$sp:(Lscala/Function1;J)D
	dreturn
  Labels:
  LocalVariableTable: 
   Start  Length  Slot  Name   Signature
   0      6      0    this       Lscala/reflect/Print$;
   0      6      1    v1       J


public void apply$mcVD$sp(double);
  Signature: (D)V
  Code:
   Stack=3, Locals=3, Args_size=2
	aload_0
	dload_1
	invokestatic	Method scala/Function1$class.apply$mcVD$sp:(Lscala/Function1;D)V
	return
  Labels:
  LocalVariableTable: 
   Start  Length  Slot  Name   Signature
   0      6      0    this       Lscala/reflect/Print$;
   0      6      1    v1       D


public boolean apply$mcZD$sp(double);
  Signature: (D)Z
  Code:
   Stack=3, Locals=3, Args_size=2
	aload_0
	dload_1
	invokestatic	Method scala/Function1$class.apply$mcZD$sp:(Lscala/Function1;D)Z
	ireturn
  Labels:
  LocalVariableTable: 
   Start  Length  Slot  Name   Signature
   0      6      0    this       Lscala/reflect/Print$;
   0      6      1    v1       D


public int apply$mcID$sp(double);
  Signature: (D)I
  Code:
   Stack=3, Locals=3, Args_size=2
	aload_0
	dload_1
	invokestatic	Method scala/Function1$class.apply$mcID$sp:(Lscala/Function1;D)I
	ireturn
  Labels:
  LocalVariableTable: 
   Start  Length  Slot  Name   Signature
   0      6      0    this       Lscala/reflect/Print$;
   0      6      1    v1       D


public long apply$mcLD$sp(double);
  Signature: (D)J
  Code:
   Stack=3, Locals=3, Args_size=2
	aload_0
	dload_1
	invokestatic	Method scala/Function1$class.apply$mcLD$sp:(Lscala/Function1;D)J
	lreturn
  Labels:
  LocalVariableTable: 
   Start  Length  Slot  Name   Signature
   0      6      0    this       Lscala/reflect/Print$;
   0      6      1    v1       D


public double apply$mcDD$sp(double);
  Signature: (D)D
  Code:
   Stack=3, Locals=3, Args_size=2
	aload_0
	dload_1
	invokestatic	Method scala/Function1$class.apply$mcDD$sp:(Lscala/Function1;D)D
	dreturn
  Labels:
  LocalVariableTable: 
   Start  Length  Slot  Name   Signature
   0      6      0    this       Lscala/reflect/Print$;
   0      6      1    v1       D


public java.lang.String toString();
  Signature: ()Ljava/lang/String;
  Code:
   Stack=1, Locals=1, Args_size=1
	aload_0
	invokestatic	Method scala/Function1$class.toString:(Lscala/Function1;)Ljava/lang/String;
	areturn
  Labels:

public scala.Function1 compose(scala.Function1);
  Signature: (Lscala/Function1;)Lscala/Function1;
  Code:
   Stack=2, Locals=2, Args_size=2
	aload_0
	aload_1
	invokestatic	Method scala/Function1$class.compose:(Lscala/Function1;Lscala/Function1;)Lscala/Function1;
	areturn
  Labels:
  LocalVariableTable: 
   Start  Length  Slot  Name   Signature
   0      6      0    this       Lscala/reflect/Print$;
   0      6      1    g       Lscala/Function1;


public scala.Function1 compose$mcVI$sp(scala.Function1);
  Signature: (Lscala/Function1;)Lscala/Function1;
  Code:
   Stack=2, Locals=2, Args_size=2
	aload_0
	aload_1
	invokestatic	Method scala/Function1$class.compose$mcVI$sp:(Lscala/Function1;Lscala/Function1;)Lscala/Function1;
	areturn
  Labels:
  LocalVariableTable: 
   Start  Length  Slot  Name   Signature
   0      6      0    this       Lscala/reflect/Print$;
   0      6      1    g       Lscala/Function1;


public scala.Function1 compose$mcZI$sp(scala.Function1);
  Signature: (Lscala/Function1;)Lscala/Function1;
  Code:
   Stack=2, Locals=2, Args_size=2
	aload_0
	aload_1
	invokestatic	Method scala/Function1$class.compose$mcZI$sp:(Lscala/Function1;Lscala/Function1;)Lscala/Function1;
	areturn
  Labels:
  LocalVariableTable: 
   Start  Length  Slot  Name   Signature
   0      6      0    this       Lscala/reflect/Print$;
   0      6      1    g       Lscala/Function1;


public scala.Function1 compose$mcII$sp(scala.Function1);
  Signature: (Lscala/Function1;)Lscala/Function1;
  Code:
   Stack=2, Locals=2, Args_size=2
	aload_0
	aload_1
	invokestatic	Method scala/Function1$class.compose$mcII$sp:(Lscala/Function1;Lscala/Function1;)Lscala/Function1;
	areturn
  Labels:
  LocalVariableTable: 
   Start  Length  Slot  Name   Signature
   0      6      0    this       Lscala/reflect/Print$;
   0      6      1    g       Lscala/Function1;


public scala.Function1 compose$mcLI$sp(scala.Function1);
  Signature: (Lscala/Function1;)Lscala/Function1;
  Code:
   Stack=2, Locals=2, Args_size=2
	aload_0
	aload_1
	invokestatic	Method scala/Function1$class.compose$mcLI$sp:(Lscala/Function1;Lscala/Function1;)Lscala/Function1;
	areturn
  Labels:
  LocalVariableTable: 
   Start  Length  Slot  Name   Signature
   0      6      0    this       Lscala/reflect/Print$;
   0      6      1    g       Lscala/Function1;


public scala.Function1 compose$mcDI$sp(scala.Function1);
  Signature: (Lscala/Function1;)Lscala/Function1;
  Code:
   Stack=2, Locals=2, Args_size=2
	aload_0
	aload_1
	invokestatic	Method scala/Function1$class.compose$mcDI$sp:(Lscala/Function1;Lscala/Function1;)Lscala/Function1;
	areturn
  Labels:
  LocalVariableTable: 
   Start  Length  Slot  Name   Signature
   0      6      0    this       Lscala/reflect/Print$;
   0      6      1    g       Lscala/Function1;


public scala.Function1 compose$mcVL$sp(scala.Function1);
  Signature: (Lscala/Function1;)Lscala/Function1;
  Code:
   Stack=2, Locals=2, Args_size=2
	aload_0
	aload_1
	invokestatic	Method scala/Function1$class.compose$mcVL$sp:(Lscala/Function1;Lscala/Function1;)Lscala/Function1;
	areturn
  Labels:
  LocalVariableTable: 
   Start  Length  Slot  Name   Signature
   0      6      0    this       Lscala/reflect/Print$;
   0      6      1    g       Lscala/Function1;


public scala.Function1 compose$mcZL$sp(scala.Function1);
  Signature: (Lscala/Function1;)Lscala/Function1;
  Code:
   Stack=2, Locals=2, Args_size=2
	aload_0
	aload_1
	invokestatic	Method scala/Function1$class.compose$mcZL$sp:(Lscala/Function1;Lscala/Function1;)Lscala/Function1;
	areturn
  Labels:
  LocalVariableTable: 
   Start  Length  Slot  Name   Signature
   0      6      0    this       Lscala/reflect/Print$;
   0      6      1    g       Lscala/Function1;


public scala.Function1 compose$mcIL$sp(scala.Function1);
  Signature: (Lscala/Function1;)Lscala/Function1;
  Code:
   Stack=2, Locals=2, Args_size=2
	aload_0
	aload_1
	invokestatic	Method scala/Function1$class.compose$mcIL$sp:(Lscala/Function1;Lscala/Function1;)Lscala/Function1;
	areturn
  Labels:
  LocalVariableTable: 
   Start  Length  Slot  Name   Signature
   0      6      0    this       Lscala/reflect/Print$;
   0      6      1    g       Lscala/Function1;


public scala.Function1 compose$mcLL$sp(scala.Function1);
  Signature: (Lscala/Function1;)Lscala/Function1;
  Code:
   Stack=2, Locals=2, Args_size=2
	aload_0
	aload_1
	invokestatic	Method scala/Function1$class.compose$mcLL$sp:(Lscala/Function1;Lscala/Function1;)Lscala/Function1;
	areturn
  Labels:
  LocalVariableTable: 
   Start  Length  Slot  Name   Signature
   0      6      0    this       Lscala/reflect/Print$;
   0      6      1    g       Lscala/Function1;


public scala.Function1 compose$mcDL$sp(scala.Function1);
  Signature: (Lscala/Function1;)Lscala/Function1;
  Code:
   Stack=2, Locals=2, Args_size=2
	aload_0
	aload_1
	invokestatic	Method scala/Function1$class.compose$mcDL$sp:(Lscala/Function1;Lscala/Function1;)Lscala/Function1;
	areturn
  Labels:
  LocalVariableTable: 
   Start  Length  Slot  Name   Signature
   0      6      0    this       Lscala/reflect/Print$;
   0      6      1    g       Lscala/Function1;


public scala.Function1 compose$mcVD$sp(scala.Function1);
  Signature: (Lscala/Function1;)Lscala/Function1;
  Code:
   Stack=2, Locals=2, Args_size=2
	aload_0
	aload_1
	invokestatic	Method scala/Function1$class.compose$mcVD$sp:(Lscala/Function1;Lscala/Function1;)Lscala/Function1;
	areturn
  Labels:
  LocalVariableTable: 
   Start  Length  Slot  Name   Signature
   0      6      0    this       Lscala/reflect/Print$;
   0      6      1    g       Lscala/Function1;


public scala.Function1 compose$mcZD$sp(scala.Function1);
  Signature: (Lscala/Function1;)Lscala/Function1;
  Code:
   Stack=2, Locals=2, Args_size=2
	aload_0
	aload_1
	invokestatic	Method scala/Function1$class.compose$mcZD$sp:(Lscala/Function1;Lscala/Function1;)Lscala/Function1;
	areturn
  Labels:
  LocalVariableTable: 
   Start  Length  Slot  Name   Signature
   0      6      0    this       Lscala/reflect/Print$;
   0      6      1    g       Lscala/Function1;


public scala.Function1 compose$mcID$sp(scala.Function1);
  Signature: (Lscala/Function1;)Lscala/Function1;
  Code:
   Stack=2, Locals=2, Args_size=2
	aload_0
	aload_1
	invokestatic	Method scala/Function1$class.compose$mcID$sp:(Lscala/Function1;Lscala/Function1;)Lscala/Function1;
	areturn
  Labels:
  LocalVariableTable: 
   Start  Length  Slot  Name   Signature
   0      6      0    this       Lscala/reflect/Print$;
   0      6      1    g       Lscala/Function1;


public scala.Function1 compose$mcLD$sp(scala.Function1);
  Signature: (Lscala/Function1;)Lscala/Function1;
  Code:
   Stack=2, Locals=2, Args_size=2
	aload_0
	aload_1
	invokestatic	Method scala/Function1$class.compose$mcLD$sp:(Lscala/Function1;Lscala/Function1;)Lscala/Function1;
	areturn
  Labels:
  LocalVariableTable: 
   Start  Length  Slot  Name   Signature
   0      6      0    this       Lscala/reflect/Print$;
   0      6      1    g       Lscala/Function1;


public scala.Function1 compose$mcDD$sp(scala.Function1);
  Signature: (Lscala/Function1;)Lscala/Function1;
  Code:
   Stack=2, Locals=2, Args_size=2
	aload_0
	aload_1
	invokestatic	Method scala/Function1$class.compose$mcDD$sp:(Lscala/Function1;Lscala/Function1;)Lscala/Function1;
	areturn
  Labels:
  LocalVariableTable: 
   Start  Length  Slot  Name   Signature
   0      6      0    this       Lscala/reflect/Print$;
   0      6      1    g       Lscala/Function1;


public scala.Function1 andThen(scala.Function1);
  Signature: (Lscala/Function1;)Lscala/Function1;
  Code:
   Stack=2, Locals=2, Args_size=2
	aload_0
	aload_1
	invokestatic	Method scala/Function1$class.andThen:(Lscala/Function1;Lscala/Function1;)Lscala/Function1;
	areturn
  Labels:
  LocalVariableTable: 
   Start  Length  Slot  Name   Signature
   0      6      0    this       Lscala/reflect/Print$;
   0      6      1    g       Lscala/Function1;


public scala.Function1 andThen$mcVI$sp(scala.Function1);
  Signature: (Lscala/Function1;)Lscala/Function1;
  Code:
   Stack=2, Locals=2, Args_size=2
	aload_0
	aload_1
	invokestatic	Method scala/Function1$class.andThen$mcVI$sp:(Lscala/Function1;Lscala/Function1;)Lscala/Function1;
	areturn
  Labels:
  LocalVariableTable: 
   Start  Length  Slot  Name   Signature
   0      6      0    this       Lscala/reflect/Print$;
   0      6      1    g       Lscala/Function1;


public scala.Function1 andThen$mcZI$sp(scala.Function1);
  Signature: (Lscala/Function1;)Lscala/Function1;
  Code:
   Stack=2, Locals=2, Args_size=2
	aload_0
	aload_1
	invokestatic	Method scala/Function1$class.andThen$mcZI$sp:(Lscala/Function1;Lscala/Function1;)Lscala/Function1;
	areturn
  Labels:
  LocalVariableTable: 
   Start  Length  Slot  Name   Signature
   0      6      0    this       Lscala/reflect/Print$;
   0      6      1    g       Lscala/Function1;


public scala.Function1 andThen$mcII$sp(scala.Function1);
  Signature: (Lscala/Function1;)Lscala/Function1;
  Code:
   Stack=2, Locals=2, Args_size=2
	aload_0
	aload_1
	invokestatic	Method scala/Function1$class.andThen$mcII$sp:(Lscala/Function1;Lscala/Function1;)Lscala/Function1;
	areturn
  Labels:
  LocalVariableTable: 
   Start  Length  Slot  Name   Signature
   0      6      0    this       Lscala/reflect/Print$;
   0      6      1    g       Lscala/Function1;


public scala.Function1 andThen$mcLI$sp(scala.Function1);
  Signature: (Lscala/Function1;)Lscala/Function1;
  Code:
   Stack=2, Locals=2, Args_size=2
	aload_0
	aload_1
	invokestatic	Method scala/Function1$class.andThen$mcLI$sp:(Lscala/Function1;Lscala/Function1;)Lscala/Function1;
	areturn
  Labels:
  LocalVariableTable: 
   Start  Length  Slot  Name   Signature
   0      6      0    this       Lscala/reflect/Print$;
   0      6      1    g       Lscala/Function1;


public scala.Function1 andThen$mcDI$sp(scala.Function1);
  Signature: (Lscala/Function1;)Lscala/Function1;
  Code:
   Stack=2, Locals=2, Args_size=2
	aload_0
	aload_1
	invokestatic	Method scala/Function1$class.andThen$mcDI$sp:(Lscala/Function1;Lscala/Function1;)Lscala/Function1;
	areturn
  Labels:
  LocalVariableTable: 
   Start  Length  Slot  Name   Signature
   0      6      0    this       Lscala/reflect/Print$;
   0      6      1    g       Lscala/Function1;


public scala.Function1 andThen$mcVL$sp(scala.Function1);
  Signature: (Lscala/Function1;)Lscala/Function1;
  Code:
   Stack=2, Locals=2, Args_size=2
	aload_0
	aload_1
	invokestatic	Method scala/Function1$class.andThen$mcVL$sp:(Lscala/Function1;Lscala/Function1;)Lscala/Function1;
	areturn
  Labels:
  LocalVariableTable: 
   Start  Length  Slot  Name   Signature
   0      6      0    this       Lscala/reflect/Print$;
   0      6      1    g       Lscala/Function1;


public scala.Function1 andThen$mcZL$sp(scala.Function1);
  Signature: (Lscala/Function1;)Lscala/Function1;
  Code:
   Stack=2, Locals=2, Args_size=2
	aload_0
	aload_1
	invokestatic	Method scala/Function1$class.andThen$mcZL$sp:(Lscala/Function1;Lscala/Function1;)Lscala/Function1;
	areturn
  Labels:
  LocalVariableTable: 
   Start  Length  Slot  Name   Signature
   0      6      0    this       Lscala/reflect/Print$;
   0      6      1    g       Lscala/Function1;


public scala.Function1 andThen$mcIL$sp(scala.Function1);
  Signature: (Lscala/Function1;)Lscala/Function1;
  Code:
   Stack=2, Locals=2, Args_size=2
	aload_0
	aload_1
	invokestatic	Method scala/Function1$class.andThen$mcIL$sp:(Lscala/Function1;Lscala/Function1;)Lscala/Function1;
	areturn
  Labels:
  LocalVariableTable: 
   Start  Length  Slot  Name   Signature
   0      6      0    this       Lscala/reflect/Print$;
   0      6      1    g       Lscala/Function1;


public scala.Function1 andThen$mcLL$sp(scala.Function1);
  Signature: (Lscala/Function1;)Lscala/Function1;
  Code:
   Stack=2, Locals=2, Args_size=2
	aload_0
	aload_1
	invokestatic	Method scala/Function1$class.andThen$mcLL$sp:(Lscala/Function1;Lscala/Function1;)Lscala/Function1;
	areturn
  Labels:
  LocalVariableTable: 
   Start  Length  Slot  Name   Signature
   0      6      0    this       Lscala/reflect/Print$;
   0      6      1    g       Lscala/Function1;


public scala.Function1 andThen$mcDL$sp(scala.Function1);
  Signature: (Lscala/Function1;)Lscala/Function1;
  Code:
   Stack=2, Locals=2, Args_size=2
	aload_0
	aload_1
	invokestatic	Method scala/Function1$class.andThen$mcDL$sp:(Lscala/Function1;Lscala/Function1;)Lscala/Function1;
	areturn
  Labels:
  LocalVariableTable: 
   Start  Length  Slot  Name   Signature
   0      6      0    this       Lscala/reflect/Print$;
   0      6      1    g       Lscala/Function1;


public scala.Function1 andThen$mcVD$sp(scala.Function1);
  Signature: (Lscala/Function1;)Lscala/Function1;
  Code:
   Stack=2, Locals=2, Args_size=2
	aload_0
	aload_1
	invokestatic	Method scala/Function1$class.andThen$mcVD$sp:(Lscala/Function1;Lscala/Function1;)Lscala/Function1;
	areturn
  Labels:
  LocalVariableTable: 
   Start  Length  Slot  Name   Signature
   0      6      0    this       Lscala/reflect/Print$;
   0      6      1    g       Lscala/Function1;


public scala.Function1 andThen$mcZD$sp(scala.Function1);
  Signature: (Lscala/Function1;)Lscala/Function1;
  Code:
   Stack=2, Locals=2, Args_size=2
	aload_0
	aload_1
	invokestatic	Method scala/Function1$class.andThen$mcZD$sp:(Lscala/Function1;Lscala/Function1;)Lscala/Function1;
	areturn
  Labels:
  LocalVariableTable: 
   Start  Length  Slot  Name   Signature
   0      6      0    this       Lscala/reflect/Print$;
   0      6      1    g       Lscala/Function1;


public scala.Function1 andThen$mcID$sp(scala.Function1);
  Signature: (Lscala/Function1;)Lscala/Function1;
  Code:
   Stack=2, Locals=2, Args_size=2
	aload_0
	aload_1
	invokestatic	Method scala/Function1$class.andThen$mcID$sp:(Lscala/Function1;Lscala/Function1;)Lscala/Function1;
	areturn
  Labels:
  LocalVariableTable: 
   Start  Length  Slot  Name   Signature
   0      6      0    this       Lscala/reflect/Print$;
   0      6      1    g       Lscala/Function1;


public scala.Function1 andThen$mcLD$sp(scala.Function1);
  Signature: (Lscala/Function1;)Lscala/Function1;
  Code:
   Stack=2, Locals=2, Args_size=2
	aload_0
	aload_1
	invokestatic	Method scala/Function1$class.andThen$mcLD$sp:(Lscala/Function1;Lscala/Function1;)Lscala/Function1;
	areturn
  Labels:
  LocalVariableTable: 
   Start  Length  Slot  Name   Signature
   0      6      0    this       Lscala/reflect/Print$;
   0      6      1    g       Lscala/Function1;


public scala.Function1 andThen$mcDD$sp(scala.Function1);
  Signature: (Lscala/Function1;)Lscala/Function1;
  Code:
   Stack=2, Locals=2, Args_size=2
	aload_0
	aload_1
	invokestatic	Method scala/Function1$class.andThen$mcDD$sp:(Lscala/Function1;Lscala/Function1;)Lscala/Function1;
	areturn
  Labels:
  LocalVariableTable: 
   Start  Length  Slot  Name   Signature
   0      6      0    this       Lscala/reflect/Print$;
   0      6      1    g       Lscala/Function1;


public java.lang.String apply(java.lang.Object);
  Signature: (Ljava/lang/Object;)Ljava/lang/String;
  Code:
   Stack=2, Locals=2, Args_size=2
	aload_1
	instanceof	class scala/reflect/Code
	ifeq	l1 // aload_1
	aload_0
	aload_1
	checkcast	class scala/reflect/Code
	invokevirtual	Method scala/reflect/Code.tree:()Lscala/reflect/Tree;
	invokevirtual	Method apply:(Lscala/reflect/Tree;)Ljava/lang/String;
	goto	l2 // areturn
l1	aload_1
	instanceof	class scala/reflect/Tree
	ifeq	l3 // aload_1
	aload_0
	aload_1
	checkcast	class scala/reflect/Tree
	invokevirtual	Method apply:(Lscala/reflect/Tree;)Ljava/lang/String;
	goto	l2 // areturn
l3	aload_1
	instanceof	class scala/reflect/Symbol
	ifeq	l4 // aload_1
	aload_0
	aload_1
	checkcast	class scala/reflect/Symbol
	invokevirtual	Method apply:(Lscala/reflect/Symbol;)Ljava/lang/String;
	goto	l2 // areturn
l4	aload_1
	instanceof	class scala/reflect/Type
	ifeq	l5 // ldc
	aload_0
	aload_1
	checkcast	class scala/reflect/Type
	invokevirtual	Method apply:(Lscala/reflect/Type;)Ljava/lang/String;
	goto	l2 // areturn
l5	ldc	String UnknownAny
l2	areturn
  Labels:
   	l1 = 21 // aload_1
   	l3 = 39 // aload_1
   	l4 = 57 // aload_1
   	l5 = 75 // ldc
   	l2 = 77 // areturn
  LocalVariableTable: 
   Start  Length  Slot  Name   Signature
   0      78      0    this       Lscala/reflect/Print$;
   0      78      1    any       Ljava/lang/Object;


public java.lang.String apply(scala.reflect.Tree);
  Signature: (Lscala/reflect/Tree;)Ljava/lang/String;
  Code:
   Stack=6, Locals=19, Args_size=2
	aload_1
	instanceof	class scala/reflect/Ident
	ifeq	l1 // aload_1
	aload_0
	aload_1
	checkcast	class scala/reflect/Ident
	invokevirtual	Method scala/reflect/Ident.sym:()Lscala/reflect/Symbol;
	invokevirtual	Method apply:(Lscala/reflect/Symbol;)Ljava/lang/String;
	goto	l2 // areturn
l1	aload_1
	instanceof	class scala/reflect/Select
	ifeq	l3 // aload_1
	aload_1
	checkcast	class scala/reflect/Select
	astore_2
	new	class scala/collection/mutable/StringBuilder
	dup
	invokespecial	Method scala/collection/mutable/StringBuilder."<init>":()V
	aload_0
	aload_2
	invokevirtual	Method scala/reflect/Select.qual:()Lscala/reflect/Tree;
	invokevirtual	Method apply:(Lscala/reflect/Tree;)Ljava/lang/String;
	invokevirtual	Method scala/collection/mutable/StringBuilder.append:(Ljava/lang/Object;)Lscala/collection/mutable/StringBuilder;
	ldc	String .
	invokevirtual	Method scala/collection/mutable/StringBuilder.append:(Ljava/lang/Object;)Lscala/collection/mutable/StringBuilder;
	aload_0
	aload_2
	invokevirtual	Method scala/reflect/Select.sym:()Lscala/reflect/Symbol;
	invokevirtual	Method apply:(Lscala/reflect/Symbol;)Ljava/lang/String;
	invokevirtual	Method scala/collection/mutable/StringBuilder.append:(Ljava/lang/Object;)Lscala/collection/mutable/StringBuilder;
	invokevirtual	Method scala/collection/mutable/StringBuilder.toString:()Ljava/lang/String;
	goto	l2 // areturn
l3	aload_1
	instanceof	class scala/reflect/Literal
	ifeq	l4 // aload_1
	aload_1
	checkcast	class scala/reflect/Literal
	astore_3
	aload_3
	invokevirtual	Method scala/reflect/Literal.value:()Ljava/lang/Object;
	astore	4
	aload	4
	instanceof	class java/lang/String
	ifeq	l5 // aload
	new	class scala/collection/mutable/StringBuilder
	dup
	invokespecial	Method scala/collection/mutable/StringBuilder."<init>":()V
	ldc_w	String \"
	invokevirtual	Method scala/collection/mutable/StringBuilder.append:(Ljava/lang/Object;)Lscala/collection/mutable/StringBuilder;
	aload	4
	checkcast	class java/lang/String
	invokevirtual	Method scala/collection/mutable/StringBuilder.append:(Ljava/lang/Object;)Lscala/collection/mutable/StringBuilder;
	ldc_w	String \"
	invokevirtual	Method scala/collection/mutable/StringBuilder.append:(Ljava/lang/Object;)Lscala/collection/mutable/StringBuilder;
	invokevirtual	Method scala/collection/mutable/StringBuilder.toString:()Ljava/lang/String;
	goto	l2 // areturn
l5	aload	4
	invokevirtual	Method java/lang/Object.toString:()Ljava/lang/String;
	goto	l2 // areturn
l4	aload_1
	instanceof	class scala/reflect/Apply
	ifeq	l6 // aload_1
	aload_1
	checkcast	class scala/reflect/Apply
	astore	5
	new	class scala/collection/mutable/StringBuilder
	dup
	invokespecial	Method scala/collection/mutable/StringBuilder."<init>":()V
	aload_0
	aload	5
	invokevirtual	Method scala/reflect/Apply.fun:()Lscala/reflect/Tree;
	invokevirtual	Method apply:(Lscala/reflect/Tree;)Ljava/lang/String;
	invokevirtual	Method scala/collection/mutable/StringBuilder.append:(Ljava/lang/Object;)Lscala/collection/mutable/StringBuilder;
	aload	5
	invokevirtual	Method scala/reflect/Apply.args:()Lscala/collection/immutable/List;
	aload_0
	getstatic	Field scala/collection/immutable/List$.MODULE$:Lscala/collection/immutable/List$;
	astore	6
	new	class scala/collection/generic/TraversableFactory$GenericCanBuildFrom
	dup
	aload	6
	invokespecial	Method scala/collection/generic/TraversableFactory$GenericCanBuildFrom."<init>":(Lscala/collection/generic/TraversableFactory;)V
	invokeinterface	InterfaceMethod scala/collection/TraversableLike.map:(Lscala/Function1;Lscala/collection/generic/CanBuildFrom;)Ljava/lang/Object;
	checkcast	class scala/collection/TraversableOnce
	ldc_w	String (
	ldc_w	String , 
	ldc_w	String )
	invokeinterface	InterfaceMethod scala/collection/TraversableOnce.mkString:(Ljava/lang/String;Ljava/lang/String;Ljava/lang/String;)Ljava/lang/String;
	invokevirtual	Method scala/collection/mutable/StringBuilder.append:(Ljava/lang/Object;)Lscala/collection/mutable/StringBuilder;
	invokevirtual	Method scala/collection/mutable/StringBuilder.toString:()Ljava/lang/String;
	goto	l2 // areturn
l6	aload_1
	instanceof	class scala/reflect/TypeApply
	ifeq	l7 // aload_1
	aload_1
	checkcast	class scala/reflect/TypeApply
	astore	7
	new	class scala/collection/mutable/StringBuilder
	dup
	invokespecial	Method scala/collection/mutable/StringBuilder."<init>":()V
	aload_0
	aload	7
	invokevirtual	Method scala/reflect/TypeApply.fun:()Lscala/reflect/Tree;
	invokevirtual	Method apply:(Lscala/reflect/Tree;)Ljava/lang/String;
	invokevirtual	Method scala/collection/mutable/StringBuilder.append:(Ljava/lang/Object;)Lscala/collection/mutable/StringBuilder;
	aload	7
	invokevirtual	Method scala/reflect/TypeApply.args:()Lscala/collection/immutable/List;
	aload_0
	getstatic	Field scala/collection/immutable/List$.MODULE$:Lscala/collection/immutable/List$;
	astore	8
	new	class scala/collection/generic/TraversableFactory$GenericCanBuildFrom
	dup
	aload	8
	invokespecial	Method scala/collection/generic/TraversableFactory$GenericCanBuildFrom."<init>":(Lscala/collection/generic/TraversableFactory;)V
	invokeinterface	InterfaceMethod scala/collection/TraversableLike.map:(Lscala/Function1;Lscala/collection/generic/CanBuildFrom;)Ljava/lang/Object;
	checkcast	class scala/collection/TraversableOnce
	ldc_w	String [
	ldc_w	String , 
	ldc_w	String ]
	invokeinterface	InterfaceMethod scala/collection/TraversableOnce.mkString:(Ljava/lang/String;Ljava/lang/String;Ljava/lang/String;)Ljava/lang/String;
	invokevirtual	Method scala/collection/mutable/StringBuilder.append:(Ljava/lang/Object;)Lscala/collection/mutable/StringBuilder;
	invokevirtual	Method scala/collection/mutable/StringBuilder.toString:()Ljava/lang/String;
	goto	l2 // areturn
l7	aload_1
	instanceof	class scala/reflect/Function
	ifeq	l8 // aload_1
	aload_1
	checkcast	class scala/reflect/Function
	astore	10
	new	class scala/collection/mutable/StringBuilder
	dup
	invokespecial	Method scala/collection/mutable/StringBuilder."<init>":()V
	aload	10
	invokevirtual	Method scala/reflect/Function.params:()Lscala/collection/immutable/List;
	aload_0
	getstatic	Field scala/collection/immutable/List$.MODULE$:Lscala/collection/immutable/List$;
	astore	9
	new	class scala/collection/generic/TraversableFactory$GenericCanBuildFrom
	dup
	aload	9
	invokespecial	Method scala/collection/generic/TraversableFactory$GenericCanBuildFrom."<init>":(Lscala/collection/generic/TraversableFactory;)V
	invokeinterface	InterfaceMethod scala/collection/TraversableLike.map:(Lscala/Function1;Lscala/collection/generic/CanBuildFrom;)Ljava/lang/Object;
	checkcast	class scala/collection/TraversableOnce
	ldc_w	String (
	ldc_w	String , 
	ldc_w	String )
	invokeinterface	InterfaceMethod scala/collection/TraversableOnce.mkString:(Ljava/lang/String;Ljava/lang/String;Ljava/lang/String;)Ljava/lang/String;
	invokevirtual	Method scala/collection/mutable/StringBuilder.append:(Ljava/lang/Object;)Lscala/collection/mutable/StringBuilder;
	ldc_w	String  => 
	invokevirtual	Method scala/collection/mutable/StringBuilder.append:(Ljava/lang/Object;)Lscala/collection/mutable/StringBuilder;
	aload_0
	aload	10
	invokevirtual	Method scala/reflect/Function.body:()Lscala/reflect/Tree;
	invokevirtual	Method apply:(Lscala/reflect/Tree;)Ljava/lang/String;
	invokevirtual	Method scala/collection/mutable/StringBuilder.append:(Ljava/lang/Object;)Lscala/collection/mutable/StringBuilder;
	invokevirtual	Method scala/collection/mutable/StringBuilder.toString:()Ljava/lang/String;
	goto	l2 // areturn
l8	aload_1
	instanceof	class scala/reflect/This
	ifeq	l9 // aload_1
	new	class scala/collection/mutable/StringBuilder
	dup
	invokespecial	Method scala/collection/mutable/StringBuilder."<init>":()V
	aload_0
	aload_1
	checkcast	class scala/reflect/This
	invokevirtual	Method scala/reflect/This.sym:()Lscala/reflect/Symbol;
	invokevirtual	Method apply:(Lscala/reflect/Symbol;)Ljava/lang/String;
	invokevirtual	Method scala/collection/mutable/StringBuilder.append:(Ljava/lang/Object;)Lscala/collection/mutable/StringBuilder;
	ldc_w	String .this
	invokevirtual	Method scala/collection/mutable/StringBuilder.append:(Ljava/lang/Object;)Lscala/collection/mutable/StringBuilder;
	invokevirtual	Method scala/collection/mutable/StringBuilder.toString:()Ljava/lang/String;
	goto	l2 // areturn
l9	aload_1
	instanceof	class scala/reflect/Block
	ifeq	l10 // aload_1
	aload_1
	checkcast	class scala/reflect/Block
	astore	11
	aload	11
	invokevirtual	Method scala/reflect/Block.stats:()Lscala/collection/immutable/List;
	astore	13
	getstatic	Field scala/Predef$.MODULE$:Lscala/Predef$;
	iconst_1
	anewarray	class scala/reflect/Tree
	dup
	iconst_0
	aload	11
	invokevirtual	Method scala/reflect/Block.expr:()Lscala/reflect/Tree;
	aastore
	checkcast	class "[Ljava/lang/Object;"
	invokevirtual	Method scala/Predef$.wrapRefArray:([Ljava/lang/Object;)Lscala/collection/mutable/WrappedArray;
	astore	12
	aload	12
	invokeinterface	InterfaceMethod scala/collection/TraversableOnce.toList:()Lscala/collection/immutable/List;
	aload	13
	invokevirtual	Method scala/collection/immutable/List.$colon$colon$colon:(Lscala/collection/immutable/List;)Lscala/collection/immutable/List;
	aload_0
	getstatic	Field scala/collection/immutable/List$.MODULE$:Lscala/collection/immutable/List$;
	invokevirtual	Method scala/collection/immutable/List$.canBuildFrom:()Lscala/collection/generic/CanBuildFrom;
	invokeinterface	InterfaceMethod scala/collection/TraversableLike.map:(Lscala/Function1;Lscala/collection/generic/CanBuildFrom;)Ljava/lang/Object;
	checkcast	class scala/collection/TraversableOnce
	ldc_w	String {\n
	ldc_w	String ;\n
	ldc_w	String \n}
	invokeinterface	InterfaceMethod scala/collection/TraversableOnce.mkString:(Ljava/lang/String;Ljava/lang/String;Ljava/lang/String;)Ljava/lang/String;
	goto	l2 // areturn
l10	aload_1
	instanceof	class scala/reflect/New
	ifeq	l11 // aload_1
	new	class scala/collection/mutable/StringBuilder
	dup
	invokespecial	Method scala/collection/mutable/StringBuilder."<init>":()V
	ldc_w	String new 
	invokevirtual	Method scala/collection/mutable/StringBuilder.append:(Ljava/lang/Object;)Lscala/collection/mutable/StringBuilder;
	aload_0
	aload_1
	checkcast	class scala/reflect/New
	invokevirtual	Method scala/reflect/New.sym:()Lscala/reflect/Tree;
	invokevirtual	Method apply:(Lscala/reflect/Tree;)Ljava/lang/String;
	invokevirtual	Method scala/collection/mutable/StringBuilder.append:(Ljava/lang/Object;)Lscala/collection/mutable/StringBuilder;
	invokevirtual	Method scala/collection/mutable/StringBuilder.toString:()Ljava/lang/String;
	goto	l2 // areturn
l11	aload_1
	instanceof	class scala/reflect/If
	ifeq	l12 // aload_1
	aload_1
	checkcast	class scala/reflect/If
	astore	14
	new	class scala/collection/mutable/StringBuilder
	dup
	invokespecial	Method scala/collection/mutable/StringBuilder."<init>":()V
	ldc_w	String if (
	invokevirtual	Method scala/collection/mutable/StringBuilder.append:(Ljava/lang/Object;)Lscala/collection/mutable/StringBuilder;
	aload_0
	aload	14
	invokevirtual	Method scala/reflect/If.condition:()Lscala/reflect/Tree;
	invokevirtual	Method apply:(Lscala/reflect/Tree;)Ljava/lang/String;
	invokevirtual	Method scala/collection/mutable/StringBuilder.append:(Ljava/lang/Object;)Lscala/collection/mutable/StringBuilder;
	ldc_w	String ) 
	invokevirtual	Method scala/collection/mutable/StringBuilder.append:(Ljava/lang/Object;)Lscala/collection/mutable/StringBuilder;
	aload_0
	aload	14
	invokevirtual	Method scala/reflect/If.trueCase:()Lscala/reflect/Tree;
	invokevirtual	Method apply:(Lscala/reflect/Tree;)Ljava/lang/String;
	invokevirtual	Method scala/collection/mutable/StringBuilder.append:(Ljava/lang/Object;)Lscala/collection/mutable/StringBuilder;
	ldc_w	String  else 
	invokevirtual	Method scala/collection/mutable/StringBuilder.append:(Ljava/lang/Object;)Lscala/collection/mutable/StringBuilder;
	aload_0
	aload	14
	invokevirtual	Method scala/reflect/If.falseCase:()Lscala/reflect/Tree;
	invokevirtual	Method apply:(Lscala/reflect/Tree;)Ljava/lang/String;
	invokevirtual	Method scala/collection/mutable/StringBuilder.append:(Ljava/lang/Object;)Lscala/collection/mutable/StringBuilder;
	invokevirtual	Method scala/collection/mutable/StringBuilder.toString:()Ljava/lang/String;
	goto	l2 // areturn
l12	aload_1
	instanceof	class scala/reflect/Assign
	ifeq	l13 // aload_1
	aload_1
	checkcast	class scala/reflect/Assign
	astore	15
	aload	15
	invokevirtual	Method scala/reflect/Assign.destination:()Lscala/reflect/Tree;
	astore	16
	aload	15
	invokevirtual	Method scala/reflect/Assign.source:()Lscala/reflect/Tree;
	astore	17
	aload	16
	ifnull	l14 // ldc_w
	aload	17
	ifnull	l15 // ldc_w
	new	class scala/collection/mutable/StringBuilder
	dup
	invokespecial	Method scala/collection/mutable/StringBuilder."<init>":()V
	aload_0
	aload	16
	invokevirtual	Method apply:(Lscala/reflect/Tree;)Ljava/lang/String;
	invokevirtual	Method scala/collection/mutable/StringBuilder.append:(Ljava/lang/Object;)Lscala/collection/mutable/StringBuilder;
	ldc_w	String  = 
	invokevirtual	Method scala/collection/mutable/StringBuilder.append:(Ljava/lang/Object;)Lscala/collection/mutable/StringBuilder;
	aload_0
	aload	17
	invokevirtual	Method apply:(Lscala/reflect/Tree;)Ljava/lang/String;
	invokevirtual	Method scala/collection/mutable/StringBuilder.append:(Ljava/lang/Object;)Lscala/collection/mutable/StringBuilder;
	invokevirtual	Method scala/collection/mutable/StringBuilder.toString:()Ljava/lang/String;
	goto	l2 // areturn
l15	ldc_w	String ???
	goto	l2 // areturn
l14	ldc_w	String ???
	goto	l2 // areturn
l13	aload_1
	instanceof	class scala/reflect/Target
	ifeq	l16 // aload_1
	aload_1
	checkcast	class scala/reflect/Target
	astore	18
	new	class scala/collection/mutable/StringBuilder
	dup
	invokespecial	Method scala/collection/mutable/StringBuilder."<init>":()V
	ldc_w	String target 
	invokevirtual	Method scala/collection/mutable/StringBuilder.append:(Ljava/lang/Object;)Lscala/collection/mutable/StringBuilder;
	aload_0
	aload	18
	invokevirtual	Method scala/reflect/Target.sym:()Lscala/reflect/LabelSymbol;
	invokevirtual	Method apply:(Lscala/reflect/Symbol;)Ljava/lang/String;
	invokevirtual	Method scala/collection/mutable/StringBuilder.append:(Ljava/lang/Object;)Lscala/collection/mutable/StringBuilder;
	ldc_w	String  {\n
	invokevirtual	Method scala/collection/mutable/StringBuilder.append:(Ljava/lang/Object;)Lscala/collection/mutable/StringBuilder;
	aload_0
	aload	18
	invokevirtual	Method scala/reflect/Target.body:()Lscala/reflect/Tree;
	invokevirtual	Method apply:(Lscala/reflect/Tree;)Ljava/lang/String;
	invokevirtual	Method scala/collection/mutable/StringBuilder.append:(Ljava/lang/Object;)Lscala/collection/mutable/StringBuilder;
	ldc_w	String \n}
	invokevirtual	Method scala/collection/mutable/StringBuilder.append:(Ljava/lang/Object;)Lscala/collection/mutable/StringBuilder;
	invokevirtual	Method scala/collection/mutable/StringBuilder.toString:()Ljava/lang/String;
	goto	l2 // areturn
l16	aload_1
	instanceof	class scala/reflect/Goto
	ifeq	l17 // ldc_w
	new	class scala/collection/mutable/StringBuilder
	dup
	invokespecial	Method scala/collection/mutable/StringBuilder."<init>":()V
	ldc_w	String goto 
	invokevirtual	Method scala/collection/mutable/StringBuilder.append:(Ljava/lang/Object;)Lscala/collection/mutable/StringBuilder;
	aload_0
	aload_1
	checkcast	class scala/reflect/Goto
	invokevirtual	Method scala/reflect/Goto.target:()Lscala/reflect/LabelSymbol;
	invokevirtual	Method apply:(Lscala/reflect/Symbol;)Ljava/lang/String;
	invokevirtual	Method scala/collection/mutable/StringBuilder.append:(Ljava/lang/Object;)Lscala/collection/mutable/StringBuilder;
	invokevirtual	Method scala/collection/mutable/StringBuilder.toString:()Ljava/lang/String;
	goto	l2 // areturn
l17	ldc_w	String ???
l2	areturn
  Labels:
   	l1 = 21 // aload_1
   	l3 = 73 // aload_1
   	l5 = 132 // aload
   	l4 = 140 // aload_1
   	l6 = 223 // aload_1
   	l7 = 306 // aload_1
   	l8 = 395 // aload_1
   	l9 = 435 // aload_1
   	l10 = 522 // aload_1
   	l11 = 562 // aload_1
   	l12 = 642 // aload_1
   	l15 = 716 // ldc_w
   	l14 = 722 // ldc_w
   	l13 = 728 // aload_1
   	l16 = 796 // aload_1
   	l17 = 836 // ldc_w
   	l2 = 839 // areturn
  LocalVariableTable: 
   Start  Length  Slot  Name   Signature
   0      840      0    this       Lscala/reflect/Print$;
   0      840      1    tree       Lscala/reflect/Tree;
   33      37      2    temp11       Lscala/reflect/Select;
   85      55      3    temp14       Lscala/reflect/Literal;
   91      49      4    temp15       Ljava/lang/Object;
   153      67      5    temp16       Lscala/reflect/Apply;
   236      67      7    temp19       Lscala/reflect/TypeApply;
   319      73      10    temp22       Lscala/reflect/Function;
   448      71      11    temp27       Lscala/reflect/Block;
   455      64      13    temp28       Lscala/collection/immutable/List;
   575      64      14    temp32       Lscala/reflect/If;
   655      73      15    temp36       Lscala/reflect/Assign;
   662      66      16    temp37       Lscala/reflect/Tree;
   669      59      17    temp38       Lscala/reflect/Tree;
   741      52      18    temp39       Lscala/reflect/Target;


public java.lang.String apply(scala.reflect.Symbol);
  Signature: (Lscala/reflect/Symbol;)Ljava/lang/String;
  Code:
   Stack=3, Locals=14, Args_size=2
	aload_1
	instanceof	class scala/reflect/Class
	ifeq	l1 // aload_1
	aload_1
	checkcast	class scala/reflect/Class
	astore_2
	aload_2
	invokevirtual	Method scala/reflect/Class.fullname:()Ljava/lang/String;
	astore_3
	aload_3
	aload_3
	ldc_w	int 46
	invokevirtual	Method java/lang/String.lastIndexOf:(I)I
	iconst_1
	iadd
	invokevirtual	Method java/lang/String.substring:(I)Ljava/lang/String;
	goto	l2 // areturn
l1	aload_1
	instanceof	class scala/reflect/Method
	ifeq	l3 // aload_1
	aload_1
	checkcast	class scala/reflect/Method
	astore	4
	aload	4
	invokevirtual	Method scala/reflect/Method.fullname:()Ljava/lang/String;
	astore	5
	aload	5
	aload	5
	ldc_w	int 46
	invokevirtual	Method java/lang/String.lastIndexOf:(I)I
	iconst_1
	iadd
	invokevirtual	Method java/lang/String.substring:(I)Ljava/lang/String;
	goto	l2 // areturn
l3	aload_1
	instanceof	class scala/reflect/Field
	ifeq	l4 // aload_1
	aload_1
	checkcast	class scala/reflect/Field
	astore	6
	aload	6
	invokevirtual	Method scala/reflect/Field.fullname:()Ljava/lang/String;
	astore	7
	aload	7
	aload	7
	ldc_w	int 46
	invokevirtual	Method java/lang/String.lastIndexOf:(I)I
	iconst_1
	iadd
	invokevirtual	Method java/lang/String.substring:(I)Ljava/lang/String;
	goto	l2 // areturn
l4	aload_1
	instanceof	class scala/reflect/TypeField
	ifeq	l5 // aload_1
	aload_1
	checkcast	class scala/reflect/TypeField
	astore	8
	aload	8
	invokevirtual	Method scala/reflect/TypeField.fullname:()Ljava/lang/String;
	astore	9
	aload	9
	aload	9
	ldc_w	int 46
	invokevirtual	Method java/lang/String.lastIndexOf:(I)I
	iconst_1
	iadd
	invokevirtual	Method java/lang/String.substring:(I)Ljava/lang/String;
	goto	l2 // areturn
l5	aload_1
	instanceof	class scala/reflect/LocalValue
	ifeq	l6 // aload_1
	aload_1
	checkcast	class scala/reflect/LocalValue
	astore	10
	aload	10
	invokevirtual	Method scala/reflect/LocalValue.name:()Ljava/lang/String;
	astore	11
	aload	11
	aload	11
	ldc_w	int 46
	invokevirtual	Method java/lang/String.lastIndexOf:(I)I
	iconst_1
	iadd
	invokevirtual	Method java/lang/String.substring:(I)Ljava/lang/String;
	goto	l2 // areturn
l6	aload_1
	instanceof	class scala/reflect/LocalMethod
	ifeq	l7 // getstatic
	aload_1
	checkcast	class scala/reflect/LocalMethod
	astore	12
	aload	12
	invokevirtual	Method scala/reflect/LocalMethod.name:()Ljava/lang/String;
	astore	13
	aload	13
	aload	13
	ldc_w	int 46
	invokevirtual	Method java/lang/String.lastIndexOf:(I)I
	iconst_1
	iadd
	invokevirtual	Method java/lang/String.substring:(I)Ljava/lang/String;
	goto	l2 // areturn
l7	getstatic	Field scala/reflect/NoSymbol$.MODULE$:Lscala/reflect/NoSymbol$;
	dup
	ifnonnull	l8 // aload_1
	pop
	aload_1
	ifnull	l9 // ldc_w
	goto	l10 // getstatic
l8	aload_1
	invokevirtual	Method java/lang/Object.equals:(Ljava/lang/Object;)Z
	ifeq	l10 // getstatic
l9	ldc_w	String NoSymbol
	goto	l2 // areturn
l10	getstatic	Field scala/reflect/RootSymbol$.MODULE$:Lscala/reflect/RootSymbol$;
	dup
	ifnonnull	l11 // aload_1
	pop
	aload_1
	ifnull	l12 // ldc_w
	goto	l13 // aload_1
l11	aload_1
	invokevirtual	Method java/lang/Object.equals:(Ljava/lang/Object;)Z
	ifeq	l13 // aload_1
l12	ldc_w	String RootSymbol
	goto	l2 // areturn
l13	aload_1
	instanceof	class scala/reflect/LabelSymbol
	ifeq	l14 // ldc_w
	aload_1
	checkcast	class scala/reflect/LabelSymbol
	invokevirtual	Method scala/reflect/LabelSymbol.name:()Ljava/lang/String;
	goto	l2 // areturn
l14	ldc_w	String ???
l2	areturn
  Labels:
   	l1 = 33 // aload_1
   	l3 = 71 // aload_1
   	l4 = 109 // aload_1
   	l5 = 147 // aload_1
   	l6 = 185 // aload_1
   	l7 = 223 // getstatic
   	l8 = 238 // aload_1
   	l9 = 245 // ldc_w
   	l10 = 251 // getstatic
   	l11 = 266 // aload_1
   	l12 = 273 // ldc_w
   	l13 = 279 // aload_1
   	l14 = 296 // ldc_w
   	l2 = 299 // areturn
  LocalVariableTable: 
   Start  Length  Slot  Name   Signature
   0      300      0    this       Lscala/reflect/Print$;
   0      300      1    symbol       Lscala/reflect/Symbol;
   12      18      2    temp45       Lscala/reflect/Class;
   17      13      3    temp46       Ljava/lang/String;
   46      22      4    temp47       Lscala/reflect/Method;
   53      15      5    temp48       Ljava/lang/String;
   84      22      6    temp50       Lscala/reflect/Field;
   91      15      7    temp51       Ljava/lang/String;
   122      22      8    temp53       Lscala/reflect/TypeField;
   129      15      9    temp54       Ljava/lang/String;
   160      22      10    temp56       Lscala/reflect/LocalValue;
   167      15      11    temp58       Ljava/lang/String;
   198      22      12    temp60       Lscala/reflect/LocalMethod;
   205      15      13    temp62       Ljava/lang/String;


public java.lang.String apply(scala.reflect.Type);
  Signature: (Lscala/reflect/Type;)Ljava/lang/String;
  Code:
   Stack=6, Locals=14, Args_size=2
	getstatic	Field scala/reflect/NoPrefix$.MODULE$:Lscala/reflect/NoPrefix$;
	dup
	ifnonnull	l1 // aload_1
	pop
	aload_1
	ifnull	l2 // ldc_w
	goto	l3 // getstatic
l1	aload_1
	invokevirtual	Method java/lang/Object.equals:(Ljava/lang/Object;)Z
	ifeq	l3 // getstatic
l2	ldc_w	String NoPrefix
	goto	l4 // areturn
l3	getstatic	Field scala/reflect/NoType$.MODULE$:Lscala/reflect/NoType$;
	dup
	ifnonnull	l5 // aload_1
	pop
	aload_1
	ifnull	l6 // ldc_w
	goto	l7 // aload_1
l5	aload_1
	invokevirtual	Method java/lang/Object.equals:(Ljava/lang/Object;)Z
	ifeq	l7 // aload_1
l6	ldc_w	String NoType
	goto	l4 // areturn
l7	aload_1
	instanceof	class scala/reflect/NamedType
	ifeq	l8 // aload_1
	new	class scala/collection/mutable/StringBuilder
	dup
	invokespecial	Method scala/collection/mutable/StringBuilder."<init>":()V
	ldc_w	String (named: 
	invokevirtual	Method scala/collection/mutable/StringBuilder.append:(Ljava/lang/Object;)Lscala/collection/mutable/StringBuilder;
	aload_1
	checkcast	class scala/reflect/NamedType
	invokevirtual	Method scala/reflect/NamedType.fullname:()Ljava/lang/String;
	invokevirtual	Method scala/collection/mutable/StringBuilder.append:(Ljava/lang/Object;)Lscala/collection/mutable/StringBuilder;
	ldc_w	String )
	invokevirtual	Method scala/collection/mutable/StringBuilder.append:(Ljava/lang/Object;)Lscala/collection/mutable/StringBuilder;
	invokevirtual	Method scala/collection/mutable/StringBuilder.toString:()Ljava/lang/String;
	goto	l4 // areturn
l8	aload_1
	instanceof	class scala/reflect/PrefixedType
	ifeq	l9 // aload_1
	aload_1
	checkcast	class scala/reflect/PrefixedType
	astore_2
	new	class scala/collection/mutable/StringBuilder
	dup
	invokespecial	Method scala/collection/mutable/StringBuilder."<init>":()V
	ldc_w	String (
	invokevirtual	Method scala/collection/mutable/StringBuilder.append:(Ljava/lang/Object;)Lscala/collection/mutable/StringBuilder;
	aload_0
	aload_2
	invokevirtual	Method scala/reflect/PrefixedType.pre:()Lscala/reflect/Type;
	invokevirtual	Method apply:(Lscala/reflect/Type;)Ljava/lang/String;
	invokevirtual	Method scala/collection/mutable/StringBuilder.append:(Ljava/lang/Object;)Lscala/collection/mutable/StringBuilder;
	ldc	String .
	invokevirtual	Method scala/collection/mutable/StringBuilder.append:(Ljava/lang/Object;)Lscala/collection/mutable/StringBuilder;
	aload_0
	aload_2
	invokevirtual	Method scala/reflect/PrefixedType.sym:()Lscala/reflect/Symbol;
	invokevirtual	Method apply:(Lscala/reflect/Symbol;)Ljava/lang/String;
	invokevirtual	Method scala/collection/mutable/StringBuilder.append:(Ljava/lang/Object;)Lscala/collection/mutable/StringBuilder;
	ldc_w	String )
	invokevirtual	Method scala/collection/mutable/StringBuilder.append:(Ljava/lang/Object;)Lscala/collection/mutable/StringBuilder;
	invokevirtual	Method scala/collection/mutable/StringBuilder.toString:()Ljava/lang/String;
	goto	l4 // areturn
l9	aload_1
	instanceof	class scala/reflect/SingleType
	ifeq	l10 // aload_1
	aload_1
	checkcast	class scala/reflect/SingleType
	astore_3
	new	class scala/collection/mutable/StringBuilder
	dup
	invokespecial	Method scala/collection/mutable/StringBuilder."<init>":()V
	ldc_w	String (
	invokevirtual	Method scala/collection/mutable/StringBuilder.append:(Ljava/lang/Object;)Lscala/collection/mutable/StringBuilder;
	aload_0
	aload_3
	invokevirtual	Method scala/reflect/SingleType.pre:()Lscala/reflect/Type;
	invokevirtual	Method apply:(Lscala/reflect/Type;)Ljava/lang/String;
	invokevirtual	Method scala/collection/mutable/StringBuilder.append:(Ljava/lang/Object;)Lscala/collection/mutable/StringBuilder;
	ldc	String .
	invokevirtual	Method scala/collection/mutable/StringBuilder.append:(Ljava/lang/Object;)Lscala/collection/mutable/StringBuilder;
	aload_0
	aload_3
	invokevirtual	Method scala/reflect/SingleType.sym:()Lscala/reflect/Symbol;
	invokevirtual	Method apply:(Lscala/reflect/Symbol;)Ljava/lang/String;
	invokevirtual	Method scala/collection/mutable/StringBuilder.append:(Ljava/lang/Object;)Lscala/collection/mutable/StringBuilder;
	ldc_w	String )
	invokevirtual	Method scala/collection/mutable/StringBuilder.append:(Ljava/lang/Object;)Lscala/collection/mutable/StringBuilder;
	invokevirtual	Method scala/collection/mutable/StringBuilder.toString:()Ljava/lang/String;
	goto	l4 // areturn
l10	aload_1
	instanceof	class scala/reflect/ThisType
	ifeq	l11 // aload_1
	new	class scala/collection/mutable/StringBuilder
	dup
	invokespecial	Method scala/collection/mutable/StringBuilder."<init>":()V
	ldc_w	String (
	invokevirtual	Method scala/collection/mutable/StringBuilder.append:(Ljava/lang/Object;)Lscala/collection/mutable/StringBuilder;
	aload_0
	aload_1
	checkcast	class scala/reflect/ThisType
	invokevirtual	Method scala/reflect/ThisType.clazz:()Lscala/reflect/Symbol;
	invokevirtual	Method apply:(Lscala/reflect/Symbol;)Ljava/lang/String;
	invokevirtual	Method scala/collection/mutable/StringBuilder.append:(Ljava/lang/Object;)Lscala/collection/mutable/StringBuilder;
	ldc_w	String .this.type)
	invokevirtual	Method scala/collection/mutable/StringBuilder.append:(Ljava/lang/Object;)Lscala/collection/mutable/StringBuilder;
	invokevirtual	Method scala/collection/mutable/StringBuilder.toString:()Ljava/lang/String;
	goto	l4 // areturn
l11	aload_1
	instanceof	class scala/reflect/AppliedType
	ifeq	l12 // aload_1
	aload_1
	checkcast	class scala/reflect/AppliedType
	astore	4
	new	class scala/collection/mutable/StringBuilder
	dup
	invokespecial	Method scala/collection/mutable/StringBuilder."<init>":()V
	aload_0
	aload	4
	invokevirtual	Method scala/reflect/AppliedType.tpe:()Lscala/reflect/Type;
	invokevirtual	Method apply:(Lscala/reflect/Type;)Ljava/lang/String;
	invokevirtual	Method scala/collection/mutable/StringBuilder.append:(Ljava/lang/Object;)Lscala/collection/mutable/StringBuilder;
	aload	4
	invokevirtual	Method scala/reflect/AppliedType.args:()Lscala/collection/immutable/List;
	aload_0
	getstatic	Field scala/collection/immutable/List$.MODULE$:Lscala/collection/immutable/List$;
	astore	5
	new	class scala/collection/generic/TraversableFactory$GenericCanBuildFrom
	dup
	aload	5
	invokespecial	Method scala/collection/generic/TraversableFactory$GenericCanBuildFrom."<init>":(Lscala/collection/generic/TraversableFactory;)V
	invokeinterface	InterfaceMethod scala/collection/TraversableLike.map:(Lscala/Function1;Lscala/collection/generic/CanBuildFrom;)Ljava/lang/Object;
	checkcast	class scala/collection/TraversableOnce
	ldc_w	String [
	ldc_w	String , 
	ldc_w	String ]
	invokeinterface	InterfaceMethod scala/collection/TraversableOnce.mkString:(Ljava/lang/String;Ljava/lang/String;Ljava/lang/String;)Ljava/lang/String;
	invokevirtual	Method scala/collection/mutable/StringBuilder.append:(Ljava/lang/Object;)Lscala/collection/mutable/StringBuilder;
	invokevirtual	Method scala/collection/mutable/StringBuilder.toString:()Ljava/lang/String;
	goto	l4 // areturn
l12	aload_1
	instanceof	class scala/reflect/TypeBounds
	ifeq	l13 // aload_1
	aload_1
	checkcast	class scala/reflect/TypeBounds
	astore	6
	new	class scala/collection/mutable/StringBuilder
	dup
	invokespecial	Method scala/collection/mutable/StringBuilder."<init>":()V
	ldc_w	String [
	invokevirtual	Method scala/collection/mutable/StringBuilder.append:(Ljava/lang/Object;)Lscala/collection/mutable/StringBuilder;
	aload_0
	aload	6
	invokevirtual	Method scala/reflect/TypeBounds.lo:()Lscala/reflect/Type;
	invokevirtual	Method apply:(Lscala/reflect/Type;)Ljava/lang/String;
	invokevirtual	Method scala/collection/mutable/StringBuilder.append:(Ljava/lang/Object;)Lscala/collection/mutable/StringBuilder;
	ldc_w	String  ... 
	invokevirtual	Method scala/collection/mutable/StringBuilder.append:(Ljava/lang/Object;)Lscala/collection/mutable/StringBuilder;
	aload_0
	aload	6
	invokevirtual	Method scala/reflect/TypeBounds.hi:()Lscala/reflect/Type;
	invokevirtual	Method apply:(Lscala/reflect/Type;)Ljava/lang/String;
	invokevirtual	Method scala/collection/mutable/StringBuilder.append:(Ljava/lang/Object;)Lscala/collection/mutable/StringBuilder;
	ldc_w	String ]
	invokevirtual	Method scala/collection/mutable/StringBuilder.append:(Ljava/lang/Object;)Lscala/collection/mutable/StringBuilder;
	invokevirtual	Method scala/collection/mutable/StringBuilder.toString:()Ljava/lang/String;
	goto	l4 // areturn
l13	aload_1
	instanceof	class scala/reflect/MethodType
	ifeq	l14 // aload_1
	aload_1
	checkcast	class scala/reflect/MethodType
	astore	8
	new	class scala/collection/mutable/StringBuilder
	dup
	invokespecial	Method scala/collection/mutable/StringBuilder."<init>":()V
	aload	8
	invokevirtual	Method scala/reflect/MethodType.formals:()Lscala/collection/immutable/List;
	aload_0
	getstatic	Field scala/collection/immutable/List$.MODULE$:Lscala/collection/immutable/List$;
	astore	7
	new	class scala/collection/generic/TraversableFactory$GenericCanBuildFrom
	dup
	aload	7
	invokespecial	Method scala/collection/generic/TraversableFactory$GenericCanBuildFrom."<init>":(Lscala/collection/generic/TraversableFactory;)V
	invokeinterface	InterfaceMethod scala/collection/TraversableLike.map:(Lscala/Function1;Lscala/collection/generic/CanBuildFrom;)Ljava/lang/Object;
	checkcast	class scala/collection/TraversableOnce
	ldc_w	String (
	ldc_w	String , 
	ldc_w	String )
	invokeinterface	InterfaceMethod scala/collection/TraversableOnce.mkString:(Ljava/lang/String;Ljava/lang/String;Ljava/lang/String;)Ljava/lang/String;
	invokevirtual	Method scala/collection/mutable/StringBuilder.append:(Ljava/lang/Object;)Lscala/collection/mutable/StringBuilder;
	ldc_w	String  => 
	invokevirtual	Method scala/collection/mutable/StringBuilder.append:(Ljava/lang/Object;)Lscala/collection/mutable/StringBuilder;
	aload_0
	aload	8
	invokevirtual	Method scala/reflect/MethodType.restpe:()Lscala/reflect/Type;
	invokevirtual	Method apply:(Lscala/reflect/Type;)Ljava/lang/String;
	invokevirtual	Method scala/collection/mutable/StringBuilder.append:(Ljava/lang/Object;)Lscala/collection/mutable/StringBuilder;
	invokevirtual	Method scala/collection/mutable/StringBuilder.toString:()Ljava/lang/String;
	goto	l4 // areturn
l14	aload_1
	instanceof	class scala/reflect/PolyType
	ifeq	l15 // ldc_w
	aload_1
	checkcast	class scala/reflect/PolyType
	astore	13
	aload	13
	invokevirtual	Method scala/reflect/PolyType.typeParams:()Lscala/collection/immutable/List;
	astore	9
	aload	13
	invokevirtual	Method scala/reflect/PolyType.typeBounds:()Lscala/collection/immutable/List;
	astore	10
	new	class scala/Tuple2
	dup
	aload	9
	aload	10
	invokespecial	Method scala/Tuple2."<init>":(Ljava/lang/Object;Ljava/lang/Object;)V
	new	class scala/Predef$$anon$1
	dup
	invokespecial	Method scala/Predef$$anon$1."<init>":()V
	new	class scala/Predef$$anon$1
	dup
	invokespecial	Method scala/Predef$$anon$1."<init>":()V
	getstatic	Field scala/collection/immutable/List$.MODULE$:Lscala/collection/immutable/List$;
	astore	11
	new	class scala/collection/generic/TraversableFactory$GenericCanBuildFrom
	dup
	aload	11
	invokespecial	Method scala/collection/generic/TraversableFactory$GenericCanBuildFrom."<init>":(Lscala/collection/generic/TraversableFactory;)V
	invokevirtual	Method scala/Tuple2.zip:(Lscala/Function1;Lscala/Function1;Lscala/collection/generic/CanBuildFrom;)Ljava/lang/Object;
	checkcast	class scala/collection/TraversableLike
	new	class scala/reflect/Print$$anonfun$1
	dup
	invokespecial	Method scala/reflect/Print$$anonfun$1."<init>":()V
	getstatic	Field scala/collection/immutable/List$.MODULE$:Lscala/collection/immutable/List$;
	invokevirtual	Method scala/collection/immutable/List$.canBuildFrom:()Lscala/collection/generic/CanBuildFrom;
	invokeinterface	InterfaceMethod scala/collection/TraversableLike.map:(Lscala/Function1;Lscala/collection/generic/CanBuildFrom;)Ljava/lang/Object;
	checkcast	class scala/collection/immutable/List
	astore	12
	new	class scala/collection/mutable/StringBuilder
	dup
	invokespecial	Method scala/collection/mutable/StringBuilder."<init>":()V
	aload	12
	ldc_w	String [
	ldc_w	String , 
	ldc_w	String ]
	invokeinterface	InterfaceMethod scala/collection/TraversableOnce.mkString:(Ljava/lang/String;Ljava/lang/String;Ljava/lang/String;)Ljava/lang/String;
	invokevirtual	Method scala/collection/mutable/StringBuilder.append:(Ljava/lang/Object;)Lscala/collection/mutable/StringBuilder;
	ldc_w	String  -> 
	invokevirtual	Method scala/collection/mutable/StringBuilder.append:(Ljava/lang/Object;)Lscala/collection/mutable/StringBuilder;
	aload_0
	aload	13
	invokevirtual	Method scala/reflect/PolyType.resultType:()Lscala/reflect/Type;
	invokevirtual	Method apply:(Lscala/reflect/Type;)Ljava/lang/String;
	invokevirtual	Method scala/collection/mutable/StringBuilder.append:(Ljava/lang/Object;)Lscala/collection/mutable/StringBuilder;
	invokevirtual	Method scala/collection/mutable/StringBuilder.toString:()Ljava/lang/String;
	goto	l4 // areturn
l15	ldc_w	String ???
l4	areturn
  Labels:
   	l1 = 15 // aload_1
   	l2 = 22 // ldc_w
   	l3 = 28 // getstatic
   	l5 = 43 // aload_1
   	l6 = 50 // ldc_w
   	l7 = 56 // aload_1
   	l8 = 98 // aload_1
   	l9 = 162 // aload_1
   	l10 = 226 // aload_1
   	l11 = 272 // aload_1
   	l12 = 355 // aload_1
   	l13 = 423 // aload_1
   	l14 = 512 // aload_1
   	l15 = 657 // ldc_w
   	l4 = 660 // areturn
  LocalVariableTable: 
   Start  Length  Slot  Name   Signature
   0      661      0    this       Lscala/reflect/Print$;
   0      661      1    datatype       Lscala/reflect/Type;
   110      49      2    temp76       Lscala/reflect/PrefixedType;
   174      49      3    temp79       Lscala/reflect/SingleType;
   285      67      4    temp84       Lscala/reflect/AppliedType;
   368      52      6    temp87       Lscala/reflect/TypeBounds;
   436      73      8    temp90       Lscala/reflect/MethodType;
   532      122      9    temp94       Lscala/collection/immutable/List;
   539      115      10    temp95       Lscala/collection/immutable/List;
   607      47      12    z       Lscala/collection/immutable/List;
   525      129      13    temp93       Lscala/reflect/PolyType;


public java.lang.Object apply(java.lang.Object);
  Signature: (Ljava/lang/Object;)Ljava/lang/Object;
  Code:
   Stack=2, Locals=2, Args_size=2
	aload_0
	aload_1
	invokevirtual	Method apply:(Ljava/lang/Object;)Ljava/lang/String;
	areturn
  Labels:
  LocalVariableTable: 
   Start  Length  Slot  Name   Signature
   0      6      0    this       Lscala/reflect/Print$;
   0      6      1    v1       Ljava/lang/Object;


private scala.reflect.Print$();
  Signature: ()V
  Code:
   Stack=1, Locals=1, Args_size=1
	aload_0
	invokespecial	Method java/lang/Object."<init>":()V
	aload_0
	putstatic	Field MODULE$:Lscala/reflect/Print$;
	aload_0
	invokestatic	Method scala/Function1$class.$init$:(Lscala/Function1;)V
	return
  Labels:

}

