Compiled from "Print.scala"
public final class scala.reflect.Print extends java.lang.Object
  SourceFile: "Print.scala"
  ScalaSig: length = 0x176
   05 00 42 07 05 01 02 FFFFFF88 02 07 01 05 50 72 69 6E
   74 0A 02 03 04 01 07 72 65 66 6C 65 63 74 0A 01
   05 01 05 73 63 61 6C 61 03 00 10 02 08 09 0D 01
   02 06 08 0A 02 FFFFFF84 FFFFFF80 FFFFFF80 FFFFFF88 02 0B 02 05 50 72 69
   6E 74 13 04 09 0C 14 22 10 02 0D 12 0D 01 0E 0A
   02 0F 10 01 04 6C 61 6E 67 0A 01 11 01 04 6A 61
   76 61 09 02 13 0E 02 06 4F 62 6A 65 63 74 10 04
   15 16 18 1B 0D 01 04 09 02 17 04 02 09 46 75 6E
   63 74 69 6F 6E 31 10 02 15 19 09 02 1A 04 02 03
   41 6E 79 10 02 1C 1F 0E 02 15 1D 09 02 1E 04 01
   06 50 72 65 64 65 66 09 02 20 21 02 06 53 74 72
   69 6E 67 0A 02 1E 04 10 02 15 23 09 02 24 04 02
   0B 53 63 61 6C 61 4F 62 6A 65 63 74 08 05 26 09
   FFFFFF84 00 27 01 06 3C 69 6E 69 74 3E 14 01 07 08 05
   29 09 FFFFFF84 00 2A 01 05 61 70 70 6C 79 14 02 1B 2B
   08 05 2C 28 FFFFFFC0 00 18 01 03 61 6E 79 08 05 29 09
   FFFFFF84 00 2E 14 02 1B 2F 08 05 30 2D FFFFFFC0 00 31 01 04
   74 72 65 65 10 02 08 32 09 02 33 02 02 04 54 72
   65 65 08 05 29 09 FFFFFF84 00 35 14 02 1B 36 08 05 37
   34 FFFFFFC0 00 38 01 06 73 79 6D 62 6F 6C 10 02 08 39
   09 02 3A 02 02 06 53 79 6D 62 6F 6C 08 05 29 09
   FFFFFF84 00 3C 14 02 1B 3D 08 05 3E 3B FFFFFFC0 00 3F 01 08
   64 61 74 61 74 79 70 65 10 02 08 40 09 02 41 02
   02 04 54 79 70 65 
  InnerClass: 
   public final $anonfun$1=class scala/reflect/Print$$anonfun$1 of class scala/reflect/Print
  minor version: 0
  major version: 49
  Constant pool:
Asciz	SourceFile;
Asciz	Print.scala;
Asciz	andThen;
Asciz	(Lscala/Function1;)Lscala/Function1;;
Asciz	Code;
Asciz	scala/reflect/Print$;
class	scala/reflect/Print$
Asciz	MODULE$;
Asciz	Lscala/reflect/Print$;;
NameAndType	MODULE$:Lscala/reflect/Print$;
Field	scala/reflect/Print$.MODULE$:Lscala/reflect/Print$;
NameAndType	andThen:(Lscala/Function1;)Lscala/Function1;
Method	scala/reflect/Print$.andThen:(Lscala/Function1;)Lscala/Function1;
Asciz	compose;
NameAndType	compose:(Lscala/Function1;)Lscala/Function1;
Method	scala/reflect/Print$.compose:(Lscala/Function1;)Lscala/Function1;
Asciz	apply;
Asciz	(Lscala/reflect/Type;)Ljava/lang/String;;
NameAndType	apply:(Lscala/reflect/Type;)Ljava/lang/String;
Method	scala/reflect/Print$.apply:(Lscala/reflect/Type;)Ljava/lang/String;
Asciz	(Lscala/reflect/Symbol;)Ljava/lang/String;;
NameAndType	apply:(Lscala/reflect/Symbol;)Ljava/lang/String;
Method	scala/reflect/Print$.apply:(Lscala/reflect/Symbol;)Ljava/lang/String;
Asciz	(Lscala/reflect/Tree;)Ljava/lang/String;;
NameAndType	apply:(Lscala/reflect/Tree;)Ljava/lang/String;
Method	scala/reflect/Print$.apply:(Lscala/reflect/Tree;)Ljava/lang/String;
Asciz	(Ljava/lang/Object;)Ljava/lang/String;;
NameAndType	apply:(Ljava/lang/Object;)Ljava/lang/String;
Method	scala/reflect/Print$.apply:(Ljava/lang/Object;)Ljava/lang/String;
Asciz	ScalaSig;
Asciz	InnerClasses;
Asciz	scala/reflect/Print$$anonfun$1;
class	scala/reflect/Print$$anonfun$1
Asciz	scala/reflect/Print;
class	scala/reflect/Print
Asciz	$anonfun$1;
Asciz	java/lang/Object;
class	java/lang/Object

{
public static final scala.Function1 andThen(scala.Function1);
  Signature: (Lscala/Function1;)Lscala/Function1;
  Code:
   Stack=2, Locals=1, Args_size=1
	getstatic	Field scala/reflect/Print$.MODULE$:Lscala/reflect/Print$;
	aload_0
	invokevirtual	Method scala/reflect/Print$.andThen:(Lscala/Function1;)Lscala/Function1;
	areturn
  Labels:

public static final scala.Function1 compose(scala.Function1);
  Signature: (Lscala/Function1;)Lscala/Function1;
  Code:
   Stack=2, Locals=1, Args_size=1
	getstatic	Field scala/reflect/Print$.MODULE$:Lscala/reflect/Print$;
	aload_0
	invokevirtual	Method scala/reflect/Print$.compose:(Lscala/Function1;)Lscala/Function1;
	areturn
  Labels:

public static final java.lang.String apply(scala.reflect.Type);
  Signature: (Lscala/reflect/Type;)Ljava/lang/String;
  Code:
   Stack=2, Locals=1, Args_size=1
	getstatic	Field scala/reflect/Print$.MODULE$:Lscala/reflect/Print$;
	aload_0
	invokevirtual	Method scala/reflect/Print$.apply:(Lscala/reflect/Type;)Ljava/lang/String;
	areturn
  Labels:

public static final java.lang.String apply(scala.reflect.Symbol);
  Signature: (Lscala/reflect/Symbol;)Ljava/lang/String;
  Code:
   Stack=2, Locals=1, Args_size=1
	getstatic	Field scala/reflect/Print$.MODULE$:Lscala/reflect/Print$;
	aload_0
	invokevirtual	Method scala/reflect/Print$.apply:(Lscala/reflect/Symbol;)Ljava/lang/String;
	areturn
  Labels:

public static final java.lang.String apply(scala.reflect.Tree);
  Signature: (Lscala/reflect/Tree;)Ljava/lang/String;
  Code:
   Stack=2, Locals=1, Args_size=1
	getstatic	Field scala/reflect/Print$.MODULE$:Lscala/reflect/Print$;
	aload_0
	invokevirtual	Method scala/reflect/Print$.apply:(Lscala/reflect/Tree;)Ljava/lang/String;
	areturn
  Labels:

public static final java.lang.String apply(java.lang.Object);
  Signature: (Ljava/lang/Object;)Ljava/lang/String;
  Code:
   Stack=2, Locals=1, Args_size=1
	getstatic	Field scala/reflect/Print$.MODULE$:Lscala/reflect/Print$;
	aload_0
	invokevirtual	Method scala/reflect/Print$.apply:(Ljava/lang/Object;)Ljava/lang/String;
	areturn
  Labels:

}

