Compiled from "Print.scala"
public final class scala.reflect.Print$ extends java.lang.Object implements scala.Function1,scala.ScalaObject
  SourceFile: "Print.scala"
  Scala: length = 0x
   
  Signature: length = 0x2
   02 07 
  InnerClass: 
   public final #524= #184 of #523; //$anon$1=class scala/Predef$$anon$1 of class scala/Predef
   public final #527= #191 of #526; //$anonfun$1=class scala/reflect/Print$$anonfun$1 of class scala/reflect/Print
   public #530= #127 of #529; //GenericCanBuildFrom=class scala/collection/generic/TraversableFactory$GenericCanBuildFrom of class scala/collection/generic/TraversableFactory
  minor version: 0
  major version: 49
  Constant pool:
const #1 = Asciz	SourceFile;
const #2 = Asciz	Print.scala;
const #3 = Asciz	Scala;
const #4 = Asciz	MODULE$;
const #5 = Asciz	Lscala/reflect/Print$;;
const #6 = Asciz	<clinit>;
const #7 = Asciz	()V;
const #8 = Asciz	Code;
const #9 = Asciz	scala/reflect/Print$;
const #10 = class	#9;	//  scala/reflect/Print$
const #11 = Asciz	<init>;
const #12 = NameAndType	#11:#7;//  "<init>":()V
const #13 = Method	#10.#12;	//  scala/reflect/Print$."<init>":()V
const #14 = Asciz	LineNumberTable;
const #15 = Asciz	java/lang/Object;
const #16 = class	#15;	//  java/lang/Object
const #17 = Method	#16.#12;	//  java/lang/Object."<init>":()V
const #18 = NameAndType	#4:#5;//  MODULE$:Lscala/reflect/Print$;
const #19 = Field	#10.#18;	//  scala/reflect/Print$.MODULE$:Lscala/reflect/Print$;
const #20 = Asciz	scala/Function1$class;
const #21 = class	#20;	//  scala/Function1$class
const #22 = Asciz	$init$;
const #23 = Asciz	(Lscala/Function1;)V;
const #24 = NameAndType	#22:#23;//  $init$:(Lscala/Function1;)V
const #25 = Method	#21.#24;	//  scala/Function1$class.$init$:(Lscala/Function1;)V
const #26 = Asciz	apply;
const #27 = Asciz	(Ljava/lang/Object;)Ljava/lang/Object;;
const #28 = Asciz	(Ljava/lang/Object;)Ljava/lang/String;;
const #29 = NameAndType	#26:#28;//  apply:(Ljava/lang/Object;)Ljava/lang/String;
const #30 = Method	#10.#29;	//  scala/reflect/Print$.apply:(Ljava/lang/Object;)Ljava/lang/String;
const #31 = Asciz	this;
const #32 = Asciz	v1;
const #33 = Asciz	Ljava/lang/Object;;
const #34 = Asciz	LocalVariableTable;
const #35 = Asciz	(Lscala/reflect/Type;)Ljava/lang/String;;
const #36 = Asciz	scala/reflect/NoPrefix$;
const #37 = class	#36;	//  scala/reflect/NoPrefix$
const #38 = Asciz	Lscala/reflect/NoPrefix$;;
const #39 = NameAndType	#4:#38;//  MODULE$:Lscala/reflect/NoPrefix$;
const #40 = Field	#37.#39;	//  scala/reflect/NoPrefix$.MODULE$:Lscala/reflect/NoPrefix$;
const #41 = Asciz	equals;
const #42 = Asciz	(Ljava/lang/Object;)Z;
const #43 = NameAndType	#41:#42;//  equals:(Ljava/lang/Object;)Z
const #44 = Method	#16.#43;	//  java/lang/Object.equals:(Ljava/lang/Object;)Z
const #45 = Asciz	NoPrefix;
const #46 = String	#45;	//  NoPrefix
const #47 = Asciz	scala/MatchError;
const #48 = class	#47;	//  scala/MatchError
const #49 = Asciz	scala/reflect/Type;
const #50 = class	#49;	//  scala/reflect/Type
const #51 = Asciz	toString;
const #52 = Asciz	()Ljava/lang/String;;
const #53 = NameAndType	#51:#52;//  toString:()Ljava/lang/String;
const #54 = Method	#50.#53;	//  scala/reflect/Type.toString:()Ljava/lang/String;
const #55 = Asciz	(Ljava/lang/String;)V;
const #56 = NameAndType	#11:#55;//  "<init>":(Ljava/lang/String;)V
const #57 = Method	#48.#56;	//  scala/MatchError."<init>":(Ljava/lang/String;)V
const #58 = Asciz	scala/reflect/NoType$;
const #59 = class	#58;	//  scala/reflect/NoType$
const #60 = Asciz	Lscala/reflect/NoType$;;
const #61 = NameAndType	#4:#60;//  MODULE$:Lscala/reflect/NoType$;
const #62 = Field	#59.#61;	//  scala/reflect/NoType$.MODULE$:Lscala/reflect/NoType$;
const #63 = Asciz	NoType;
const #64 = String	#63;	//  NoType
const #65 = Asciz	scala/reflect/NamedType;
const #66 = class	#65;	//  scala/reflect/NamedType
const #67 = Asciz	fullname;
const #68 = NameAndType	#67:#52;//  fullname:()Ljava/lang/String;
const #69 = Method	#66.#68;	//  scala/reflect/NamedType.fullname:()Ljava/lang/String;
const #70 = Asciz	scala/collection/mutable/StringBuilder;
const #71 = class	#70;	//  scala/collection/mutable/StringBuilder
const #72 = Method	#71.#12;	//  scala/collection/mutable/StringBuilder."<init>":()V
const #73 = Asciz	(named: ;
const #74 = String	#73;	//  (named: 
const #75 = Asciz	append;
const #76 = Asciz	(Ljava/lang/Object;)Lscala/collection/mutable/StringBuilder;;
const #77 = NameAndType	#75:#76;//  append:(Ljava/lang/Object;)Lscala/collection/mutable/StringBuilder;
const #78 = Method	#71.#77;	//  scala/collection/mutable/StringBuilder.append:(Ljava/lang/Object;)Lscala/collection/mutable/StringBuilder;
const #79 = Asciz	);
const #80 = String	#79;	//  )
const #81 = Method	#71.#53;	//  scala/collection/mutable/StringBuilder.toString:()Ljava/lang/String;
const #82 = Asciz	scala/reflect/PrefixedType;
const #83 = class	#82;	//  scala/reflect/PrefixedType
const #84 = Asciz	pre;
const #85 = Asciz	()Lscala/reflect/Type;;
const #86 = NameAndType	#84:#85;//  pre:()Lscala/reflect/Type;
const #87 = Method	#83.#86;	//  scala/reflect/PrefixedType.pre:()Lscala/reflect/Type;
const #88 = Asciz	sym;
const #89 = Asciz	()Lscala/reflect/Symbol;;
const #90 = NameAndType	#88:#89;//  sym:()Lscala/reflect/Symbol;
const #91 = Method	#83.#90;	//  scala/reflect/PrefixedType.sym:()Lscala/reflect/Symbol;
const #92 = Asciz	(;
const #93 = String	#92;	//  (
const #94 = NameAndType	#26:#35;//  apply:(Lscala/reflect/Type;)Ljava/lang/String;
const #95 = Method	#10.#94;	//  scala/reflect/Print$.apply:(Lscala/reflect/Type;)Ljava/lang/String;
const #96 = Asciz	.;
const #97 = String	#96;	//  .
const #98 = Asciz	(Lscala/reflect/Symbol;)Ljava/lang/String;;
const #99 = NameAndType	#26:#98;//  apply:(Lscala/reflect/Symbol;)Ljava/lang/String;
const #100 = Method	#10.#99;	//  scala/reflect/Print$.apply:(Lscala/reflect/Symbol;)Ljava/lang/String;
const #101 = Asciz	scala/reflect/SingleType;
const #102 = class	#101;	//  scala/reflect/SingleType
const #103 = Method	#102.#86;	//  scala/reflect/SingleType.pre:()Lscala/reflect/Type;
const #104 = Method	#102.#90;	//  scala/reflect/SingleType.sym:()Lscala/reflect/Symbol;
const #105 = Asciz	scala/reflect/ThisType;
const #106 = class	#105;	//  scala/reflect/ThisType
const #107 = Asciz	clazz;
const #108 = NameAndType	#107:#89;//  clazz:()Lscala/reflect/Symbol;
const #109 = Method	#106.#108;	//  scala/reflect/ThisType.clazz:()Lscala/reflect/Symbol;
const #110 = Asciz	.this.type);
const #111 = String	#110;	//  .this.type)
const #112 = Asciz	scala/reflect/AppliedType;
const #113 = class	#112;	//  scala/reflect/AppliedType
const #114 = Asciz	tpe;
const #115 = NameAndType	#114:#85;//  tpe:()Lscala/reflect/Type;
const #116 = Method	#113.#115;	//  scala/reflect/AppliedType.tpe:()Lscala/reflect/Type;
const #117 = Asciz	args;
const #118 = Asciz	()Lscala/collection/immutable/List;;
const #119 = NameAndType	#117:#118;//  args:()Lscala/collection/immutable/List;
const #120 = Method	#113.#119;	//  scala/reflect/AppliedType.args:()Lscala/collection/immutable/List;
const #121 = Asciz	scala/collection/immutable/List$;
const #122 = class	#121;	//  scala/collection/immutable/List$
const #123 = Asciz	Lscala/collection/immutable/List$;;
const #124 = NameAndType	#4:#123;//  MODULE$:Lscala/collection/immutable/List$;
const #125 = Field	#122.#124;	//  scala/collection/immutable/List$.MODULE$:Lscala/collection/immutable/List$;
const #126 = Asciz	scala/collection/generic/TraversableFactory$GenericCanBuildFrom;
const #127 = class	#126;	//  scala/collection/generic/TraversableFactory$GenericCanBuildFrom
const #128 = Asciz	(Lscala/collection/generic/TraversableFactory;)V;
const #129 = NameAndType	#11:#128;//  "<init>":(Lscala/collection/generic/TraversableFactory;)V
const #130 = Method	#127.#129;	//  scala/collection/generic/TraversableFactory$GenericCanBuildFrom."<init>":(Lscala/collection/generic/TraversableFactory;)V
const #131 = Asciz	scala/collection/TraversableLike;
const #132 = class	#131;	//  scala/collection/TraversableLike
const #133 = Asciz	map;
const #134 = Asciz	(Lscala/Function1;Lscala/collection/generic/CanBuildFrom;)Ljava/lang/Object;;
const #135 = NameAndType	#133:#134;//  map:(Lscala/Function1;Lscala/collection/generic/CanBuildFrom;)Ljava/lang/Object;
const #136 = InterfaceMethod	#132.#135;	//  scala/collection/TraversableLike.map:(Lscala/Function1;Lscala/collection/generic/CanBuildFrom;)Ljava/lang/Object;
const #137 = Asciz	[;
const #138 = String	#137;	//  [
const #139 = Asciz	, ;
const #140 = String	#139;	//  , 
const #141 = Asciz	];
const #142 = String	#141;	//  ]
const #143 = Asciz	mkString;
const #144 = Asciz	(Ljava/lang/String;Ljava/lang/String;Ljava/lang/String;)Ljava/lang/String;;
const #145 = NameAndType	#143:#144;//  mkString:(Ljava/lang/String;Ljava/lang/String;Ljava/lang/String;)Ljava/lang/String;
const #146 = InterfaceMethod	#132.#145;	//  scala/collection/TraversableLike.mkString:(Ljava/lang/String;Ljava/lang/String;Ljava/lang/String;)Ljava/lang/String;
const #147 = Asciz	scala/reflect/TypeBounds;
const #148 = class	#147;	//  scala/reflect/TypeBounds
const #149 = Asciz	lo;
const #150 = NameAndType	#149:#85;//  lo:()Lscala/reflect/Type;
const #151 = Method	#148.#150;	//  scala/reflect/TypeBounds.lo:()Lscala/reflect/Type;
const #152 = Asciz	hi;
const #153 = NameAndType	#152:#85;//  hi:()Lscala/reflect/Type;
const #154 = Method	#148.#153;	//  scala/reflect/TypeBounds.hi:()Lscala/reflect/Type;
const #155 = Asciz	 ... ;
const #156 = String	#155;	//   ... 
const #157 = Asciz	scala/reflect/MethodType;
const #158 = class	#157;	//  scala/reflect/MethodType
const #159 = Asciz	formals;
const #160 = NameAndType	#159:#118;//  formals:()Lscala/collection/immutable/List;
const #161 = Method	#158.#160;	//  scala/reflect/MethodType.formals:()Lscala/collection/immutable/List;
const #162 = Asciz	restpe;
const #163 = NameAndType	#162:#85;//  restpe:()Lscala/reflect/Type;
const #164 = Method	#158.#163;	//  scala/reflect/MethodType.restpe:()Lscala/reflect/Type;
const #165 = Asciz	 => ;
const #166 = String	#165;	//   => 
const #167 = Asciz	scala/reflect/PolyType;
const #168 = class	#167;	//  scala/reflect/PolyType
const #169 = Asciz	typeParams;
const #170 = NameAndType	#169:#118;//  typeParams:()Lscala/collection/immutable/List;
const #171 = Method	#168.#170;	//  scala/reflect/PolyType.typeParams:()Lscala/collection/immutable/List;
const #172 = Asciz	typeBounds;
const #173 = NameAndType	#172:#118;//  typeBounds:()Lscala/collection/immutable/List;
const #174 = Method	#168.#173;	//  scala/reflect/PolyType.typeBounds:()Lscala/collection/immutable/List;
const #175 = Asciz	resultType;
const #176 = NameAndType	#175:#85;//  resultType:()Lscala/reflect/Type;
const #177 = Method	#168.#176;	//  scala/reflect/PolyType.resultType:()Lscala/reflect/Type;
const #178 = Asciz	scala/Tuple2;
const #179 = class	#178;	//  scala/Tuple2
const #180 = Asciz	(Ljava/lang/Object;Ljava/lang/Object;)V;
const #181 = NameAndType	#11:#180;//  "<init>":(Ljava/lang/Object;Ljava/lang/Object;)V
const #182 = Method	#179.#181;	//  scala/Tuple2."<init>":(Ljava/lang/Object;Ljava/lang/Object;)V
const #183 = Asciz	scala/Predef$$anon$1;
const #184 = class	#183;	//  scala/Predef$$anon$1
const #185 = Method	#184.#12;	//  scala/Predef$$anon$1."<init>":()V
const #186 = Asciz	zip;
const #187 = Asciz	(Lscala/Function1;Lscala/Function1;Lscala/collection/generic/CanBuildFrom;)Ljava/lang/Object;;
const #188 = NameAndType	#186:#187;//  zip:(Lscala/Function1;Lscala/Function1;Lscala/collection/generic/CanBuildFrom;)Ljava/lang/Object;
const #189 = Method	#179.#188;	//  scala/Tuple2.zip:(Lscala/Function1;Lscala/Function1;Lscala/collection/generic/CanBuildFrom;)Ljava/lang/Object;
const #190 = Asciz	scala/reflect/Print$$anonfun$1;
const #191 = class	#190;	//  scala/reflect/Print$$anonfun$1
const #192 = Method	#191.#12;	//  scala/reflect/Print$$anonfun$1."<init>":()V
const #193 = Asciz	canBuildFrom;
const #194 = Asciz	()Lscala/collection/generic/CanBuildFrom;;
const #195 = NameAndType	#193:#194;//  canBuildFrom:()Lscala/collection/generic/CanBuildFrom;
const #196 = Method	#122.#195;	//  scala/collection/immutable/List$.canBuildFrom:()Lscala/collection/generic/CanBuildFrom;
const #197 = Asciz	scala/collection/immutable/List;
const #198 = class	#197;	//  scala/collection/immutable/List
const #199 = Asciz	 -> ;
const #200 = String	#199;	//   -> 
const #201 = Asciz	???;
const #202 = String	#201;	//  ???
const #203 = Asciz	datatype;
const #204 = Asciz	Lscala/reflect/Type;;
const #205 = Asciz	temp74;
const #206 = Asciz	Lscala/reflect/NamedType;;
const #207 = Asciz	temp75;
const #208 = Asciz	Ljava/lang/String;;
const #209 = Asciz	temp76;
const #210 = Asciz	Lscala/reflect/PrefixedType;;
const #211 = Asciz	temp77;
const #212 = Asciz	temp78;
const #213 = Asciz	Lscala/reflect/Symbol;;
const #214 = Asciz	temp79;
const #215 = Asciz	Lscala/reflect/SingleType;;
const #216 = Asciz	temp80;
const #217 = Asciz	temp81;
const #218 = Asciz	temp82;
const #219 = Asciz	Lscala/reflect/ThisType;;
const #220 = Asciz	temp83;
const #221 = Asciz	temp84;
const #222 = Asciz	Lscala/reflect/AppliedType;;
const #223 = Asciz	temp85;
const #224 = Asciz	temp86;
const #225 = Asciz	Lscala/collection/immutable/List;;
const #226 = Asciz	temp87;
const #227 = Asciz	Lscala/reflect/TypeBounds;;
const #228 = Asciz	temp88;
const #229 = Asciz	temp89;
const #230 = Asciz	temp90;
const #231 = Asciz	Lscala/reflect/MethodType;;
const #232 = Asciz	temp91;
const #233 = Asciz	temp92;
const #234 = Asciz	temp93;
const #235 = Asciz	Lscala/reflect/PolyType;;
const #236 = Asciz	temp94;
const #237 = Asciz	temp95;
const #238 = Asciz	z;
const #239 = Asciz	temp96;
const #240 = Asciz	scala/reflect/Class;
const #241 = class	#240;	//  scala/reflect/Class
const #242 = Method	#241.#68;	//  scala/reflect/Class.fullname:()Ljava/lang/String;
const #243 = int	46;
const #244 = Asciz	java/lang/String;
const #245 = class	#244;	//  java/lang/String
const #246 = Asciz	lastIndexOf;
const #247 = Asciz	(I)I;
const #248 = NameAndType	#246:#247;//  lastIndexOf:(I)I
const #249 = Method	#245.#248;	//  java/lang/String.lastIndexOf:(I)I
const #250 = Asciz	substring;
const #251 = Asciz	(I)Ljava/lang/String;;
const #252 = NameAndType	#250:#251;//  substring:(I)Ljava/lang/String;
const #253 = Method	#245.#252;	//  java/lang/String.substring:(I)Ljava/lang/String;
const #254 = Asciz	scala/reflect/Symbol;
const #255 = class	#254;	//  scala/reflect/Symbol
const #256 = Method	#255.#53;	//  scala/reflect/Symbol.toString:()Ljava/lang/String;
const #257 = Asciz	scala/reflect/Method;
const #258 = class	#257;	//  scala/reflect/Method
const #259 = Method	#258.#68;	//  scala/reflect/Method.fullname:()Ljava/lang/String;
const #260 = Asciz	scala/reflect/Field;
const #261 = class	#260;	//  scala/reflect/Field
const #262 = Method	#261.#68;	//  scala/reflect/Field.fullname:()Ljava/lang/String;
const #263 = Asciz	scala/reflect/TypeField;
const #264 = class	#263;	//  scala/reflect/TypeField
const #265 = Method	#264.#68;	//  scala/reflect/TypeField.fullname:()Ljava/lang/String;
const #266 = Asciz	scala/reflect/LocalValue;
const #267 = class	#266;	//  scala/reflect/LocalValue
const #268 = Asciz	name;
const #269 = NameAndType	#268:#52;//  name:()Ljava/lang/String;
const #270 = Method	#267.#269;	//  scala/reflect/LocalValue.name:()Ljava/lang/String;
const #271 = Asciz	scala/reflect/LocalMethod;
const #272 = class	#271;	//  scala/reflect/LocalMethod
const #273 = Method	#272.#269;	//  scala/reflect/LocalMethod.name:()Ljava/lang/String;
const #274 = Asciz	scala/reflect/NoSymbol$;
const #275 = class	#274;	//  scala/reflect/NoSymbol$
const #276 = Asciz	Lscala/reflect/NoSymbol$;;
const #277 = NameAndType	#4:#276;//  MODULE$:Lscala/reflect/NoSymbol$;
const #278 = Field	#275.#277;	//  scala/reflect/NoSymbol$.MODULE$:Lscala/reflect/NoSymbol$;
const #279 = Asciz	NoSymbol;
const #280 = String	#279;	//  NoSymbol
const #281 = Asciz	scala/reflect/RootSymbol$;
const #282 = class	#281;	//  scala/reflect/RootSymbol$
const #283 = Asciz	Lscala/reflect/RootSymbol$;;
const #284 = NameAndType	#4:#283;//  MODULE$:Lscala/reflect/RootSymbol$;
const #285 = Field	#282.#284;	//  scala/reflect/RootSymbol$.MODULE$:Lscala/reflect/RootSymbol$;
const #286 = Asciz	RootSymbol;
const #287 = String	#286;	//  RootSymbol
const #288 = Asciz	scala/reflect/LabelSymbol;
const #289 = class	#288;	//  scala/reflect/LabelSymbol
const #290 = Method	#289.#269;	//  scala/reflect/LabelSymbol.name:()Ljava/lang/String;
const #291 = Asciz	symbol;
const #292 = Asciz	temp45;
const #293 = Asciz	Lscala/reflect/Class;;
const #294 = Asciz	temp46;
const #295 = Asciz	temp47;
const #296 = Asciz	Lscala/reflect/Method;;
const #297 = Asciz	temp48;
const #298 = Asciz	temp50;
const #299 = Asciz	Lscala/reflect/Field;;
const #300 = Asciz	temp51;
const #301 = Asciz	temp53;
const #302 = Asciz	Lscala/reflect/TypeField;;
const #303 = Asciz	temp54;
const #304 = Asciz	temp56;
const #305 = Asciz	Lscala/reflect/LocalValue;;
const #306 = Asciz	temp58;
const #307 = Asciz	temp60;
const #308 = Asciz	Lscala/reflect/LocalMethod;;
const #309 = Asciz	temp62;
const #310 = Asciz	temp66;
const #311 = Asciz	Lscala/reflect/LabelSymbol;;
const #312 = Asciz	temp67;
const #313 = Asciz	(Lscala/reflect/Tree;)Ljava/lang/String;;
const #314 = Asciz	scala/reflect/Ident;
const #315 = class	#314;	//  scala/reflect/Ident
const #316 = Method	#315.#90;	//  scala/reflect/Ident.sym:()Lscala/reflect/Symbol;
const #317 = Asciz	scala/reflect/Tree;
const #318 = class	#317;	//  scala/reflect/Tree
const #319 = Method	#318.#53;	//  scala/reflect/Tree.toString:()Ljava/lang/String;
const #320 = Asciz	scala/reflect/Select;
const #321 = class	#320;	//  scala/reflect/Select
const #322 = Asciz	qual;
const #323 = Asciz	()Lscala/reflect/Tree;;
const #324 = NameAndType	#322:#323;//  qual:()Lscala/reflect/Tree;
const #325 = Method	#321.#324;	//  scala/reflect/Select.qual:()Lscala/reflect/Tree;
const #326 = Method	#321.#90;	//  scala/reflect/Select.sym:()Lscala/reflect/Symbol;
const #327 = NameAndType	#26:#313;//  apply:(Lscala/reflect/Tree;)Ljava/lang/String;
const #328 = Method	#10.#327;	//  scala/reflect/Print$.apply:(Lscala/reflect/Tree;)Ljava/lang/String;
const #329 = Asciz	scala/reflect/Literal;
const #330 = class	#329;	//  scala/reflect/Literal
const #331 = Asciz	value;
const #332 = Asciz	()Ljava/lang/Object;;
const #333 = NameAndType	#331:#332;//  value:()Ljava/lang/Object;
const #334 = Method	#330.#333;	//  scala/reflect/Literal.value:()Ljava/lang/Object;
const #335 = Asciz	\";
const #336 = String	#335;	//  \"
const #337 = Method	#16.#53;	//  java/lang/Object.toString:()Ljava/lang/String;
const #338 = Asciz	scala/reflect/Apply;
const #339 = class	#338;	//  scala/reflect/Apply
const #340 = Asciz	fun;
const #341 = NameAndType	#340:#323;//  fun:()Lscala/reflect/Tree;
const #342 = Method	#339.#341;	//  scala/reflect/Apply.fun:()Lscala/reflect/Tree;
const #343 = Method	#339.#119;	//  scala/reflect/Apply.args:()Lscala/collection/immutable/List;
const #344 = Asciz	scala/reflect/TypeApply;
const #345 = class	#344;	//  scala/reflect/TypeApply
const #346 = Method	#345.#341;	//  scala/reflect/TypeApply.fun:()Lscala/reflect/Tree;
const #347 = Method	#345.#119;	//  scala/reflect/TypeApply.args:()Lscala/collection/immutable/List;
const #348 = Asciz	scala/reflect/Function;
const #349 = class	#348;	//  scala/reflect/Function
const #350 = Asciz	params;
const #351 = NameAndType	#350:#118;//  params:()Lscala/collection/immutable/List;
const #352 = Method	#349.#351;	//  scala/reflect/Function.params:()Lscala/collection/immutable/List;
const #353 = Asciz	body;
const #354 = NameAndType	#353:#323;//  body:()Lscala/reflect/Tree;
const #355 = Method	#349.#354;	//  scala/reflect/Function.body:()Lscala/reflect/Tree;
const #356 = Asciz	scala/reflect/This;
const #357 = class	#356;	//  scala/reflect/This
const #358 = Method	#357.#90;	//  scala/reflect/This.sym:()Lscala/reflect/Symbol;
const #359 = Asciz	.this;
const #360 = String	#359;	//  .this
const #361 = Asciz	scala/reflect/Block;
const #362 = class	#361;	//  scala/reflect/Block
const #363 = Asciz	stats;
const #364 = NameAndType	#363:#118;//  stats:()Lscala/collection/immutable/List;
const #365 = Method	#362.#364;	//  scala/reflect/Block.stats:()Lscala/collection/immutable/List;
const #366 = Asciz	expr;
const #367 = NameAndType	#366:#323;//  expr:()Lscala/reflect/Tree;
const #368 = Method	#362.#367;	//  scala/reflect/Block.expr:()Lscala/reflect/Tree;
const #369 = Asciz	scala/Predef$;
const #370 = class	#369;	//  scala/Predef$
const #371 = Asciz	Lscala/Predef$;;
const #372 = NameAndType	#4:#371;//  MODULE$:Lscala/Predef$;
const #373 = Field	#370.#372;	//  scala/Predef$.MODULE$:Lscala/Predef$;
const #374 = Asciz	[Ljava/lang/Object;;
const #375 = class	#374;	//  "[Ljava/lang/Object;"
const #376 = Asciz	wrapRefArray;
const #377 = Asciz	([Ljava/lang/Object;)Lscala/collection/mutable/WrappedArray;;
const #378 = NameAndType	#376:#377;//  wrapRefArray:([Ljava/lang/Object;)Lscala/collection/mutable/WrappedArray;
const #379 = Method	#370.#378;	//  scala/Predef$.wrapRefArray:([Ljava/lang/Object;)Lscala/collection/mutable/WrappedArray;
const #380 = Asciz	toList;
const #381 = NameAndType	#380:#118;//  toList:()Lscala/collection/immutable/List;
const #382 = InterfaceMethod	#132.#381;	//  scala/collection/TraversableLike.toList:()Lscala/collection/immutable/List;
const #383 = Asciz	$colon$colon$colon;
const #384 = Asciz	(Lscala/collection/immutable/List;)Lscala/collection/immutable/List;;
const #385 = NameAndType	#383:#384;//  $colon$colon$colon:(Lscala/collection/immutable/List;)Lscala/collection/immutable/List;
const #386 = Method	#198.#385;	//  scala/collection/immutable/List.$colon$colon$colon:(Lscala/collection/immutable/List;)Lscala/collection/immutable/List;
const #387 = Asciz	{\n;
const #388 = String	#387;	//  {\n
const #389 = Asciz	;\n;
const #390 = String	#389;	//  ;\n
const #391 = Asciz	\n};
const #392 = String	#391;	//  \n}
const #393 = Asciz	scala/reflect/New;
const #394 = class	#393;	//  scala/reflect/New
const #395 = NameAndType	#88:#323;//  sym:()Lscala/reflect/Tree;
const #396 = Method	#394.#395;	//  scala/reflect/New.sym:()Lscala/reflect/Tree;
const #397 = Asciz	new ;
const #398 = String	#397;	//  new 
const #399 = Asciz	scala/reflect/If;
const #400 = class	#399;	//  scala/reflect/If
const #401 = Asciz	condition;
const #402 = NameAndType	#401:#323;//  condition:()Lscala/reflect/Tree;
const #403 = Method	#400.#402;	//  scala/reflect/If.condition:()Lscala/reflect/Tree;
const #404 = Asciz	trueCase;
const #405 = NameAndType	#404:#323;//  trueCase:()Lscala/reflect/Tree;
const #406 = Method	#400.#405;	//  scala/reflect/If.trueCase:()Lscala/reflect/Tree;
const #407 = Asciz	falseCase;
const #408 = NameAndType	#407:#323;//  falseCase:()Lscala/reflect/Tree;
const #409 = Method	#400.#408;	//  scala/reflect/If.falseCase:()Lscala/reflect/Tree;
const #410 = Asciz	if (;
const #411 = String	#410;	//  if (
const #412 = Asciz	) ;
const #413 = String	#412;	//  ) 
const #414 = Asciz	 else ;
const #415 = String	#414;	//   else 
const #416 = Asciz	scala/reflect/Assign;
const #417 = class	#416;	//  scala/reflect/Assign
const #418 = Asciz	destination;
const #419 = NameAndType	#418:#323;//  destination:()Lscala/reflect/Tree;
const #420 = Method	#417.#419;	//  scala/reflect/Assign.destination:()Lscala/reflect/Tree;
const #421 = Asciz	source;
const #422 = NameAndType	#421:#323;//  source:()Lscala/reflect/Tree;
const #423 = Method	#417.#422;	//  scala/reflect/Assign.source:()Lscala/reflect/Tree;
const #424 = Asciz	 = ;
const #425 = String	#424;	//   = 
const #426 = Asciz	scala/reflect/Target;
const #427 = class	#426;	//  scala/reflect/Target
const #428 = Asciz	()Lscala/reflect/LabelSymbol;;
const #429 = NameAndType	#88:#428;//  sym:()Lscala/reflect/LabelSymbol;
const #430 = Method	#427.#429;	//  scala/reflect/Target.sym:()Lscala/reflect/LabelSymbol;
const #431 = Method	#427.#354;	//  scala/reflect/Target.body:()Lscala/reflect/Tree;
const #432 = Asciz	target ;
const #433 = String	#432;	//  target 
const #434 = Asciz	 {\n;
const #435 = String	#434;	//   {\n
const #436 = Asciz	scala/reflect/Goto;
const #437 = class	#436;	//  scala/reflect/Goto
const #438 = Asciz	target;
const #439 = NameAndType	#438:#428;//  target:()Lscala/reflect/LabelSymbol;
const #440 = Method	#437.#439;	//  scala/reflect/Goto.target:()Lscala/reflect/LabelSymbol;
const #441 = Asciz	goto ;
const #442 = String	#441;	//  goto 
const #443 = Asciz	tree;
const #444 = Asciz	Lscala/reflect/Tree;;
const #445 = Asciz	temp9;
const #446 = Asciz	Lscala/reflect/Ident;;
const #447 = Asciz	temp10;
const #448 = Asciz	temp11;
const #449 = Asciz	Lscala/reflect/Select;;
const #450 = Asciz	temp12;
const #451 = Asciz	temp13;
const #452 = Asciz	temp14;
const #453 = Asciz	Lscala/reflect/Literal;;
const #454 = Asciz	temp7;
const #455 = Asciz	temp15;
const #456 = Asciz	temp16;
const #457 = Asciz	Lscala/reflect/Apply;;
const #458 = Asciz	temp17;
const #459 = Asciz	temp18;
const #460 = Asciz	temp19;
const #461 = Asciz	Lscala/reflect/TypeApply;;
const #462 = Asciz	temp20;
const #463 = Asciz	temp21;
const #464 = Asciz	temp22;
const #465 = Asciz	Lscala/reflect/Function;;
const #466 = Asciz	temp23;
const #467 = Asciz	temp24;
const #468 = Asciz	temp25;
const #469 = Asciz	Lscala/reflect/This;;
const #470 = Asciz	temp26;
const #471 = Asciz	temp27;
const #472 = Asciz	Lscala/reflect/Block;;
const #473 = Asciz	temp29;
const #474 = Asciz	temp28;
const #475 = Asciz	temp30;
const #476 = Asciz	Lscala/reflect/New;;
const #477 = Asciz	temp31;
const #478 = Asciz	temp32;
const #479 = Asciz	Lscala/reflect/If;;
const #480 = Asciz	temp33;
const #481 = Asciz	temp34;
const #482 = Asciz	temp35;
const #483 = Asciz	temp36;
const #484 = Asciz	Lscala/reflect/Assign;;
const #485 = Asciz	temp37;
const #486 = Asciz	temp38;
const #487 = Asciz	temp39;
const #488 = Asciz	Lscala/reflect/Target;;
const #489 = Asciz	temp40;
const #490 = Asciz	temp41;
const #491 = Asciz	temp42;
const #492 = Asciz	Lscala/reflect/Goto;;
const #493 = Asciz	temp43;
const #494 = Asciz	scala/reflect/Code;
const #495 = class	#494;	//  scala/reflect/Code
const #496 = NameAndType	#443:#323;//  tree:()Lscala/reflect/Tree;
const #497 = Method	#495.#496;	//  scala/reflect/Code.tree:()Lscala/reflect/Tree;
const #498 = Asciz	UnknownAny;
const #499 = String	#498;	//  UnknownAny
const #500 = Asciz	any;
const #501 = Asciz	temp2;
const #502 = Asciz	Lscala/reflect/Code;;
const #503 = Asciz	temp3;
const #504 = Asciz	temp4;
const #505 = Asciz	temp5;
const #506 = Asciz	andThen;
const #507 = Asciz	(Lscala/Function1;)Lscala/Function1;;
const #508 = Asciz	(Lscala/Function1;Lscala/Function1;)Lscala/Function1;;
const #509 = NameAndType	#506:#508;//  andThen:(Lscala/Function1;Lscala/Function1;)Lscala/Function1;
const #510 = Method	#21.#509;	//  scala/Function1$class.andThen:(Lscala/Function1;Lscala/Function1;)Lscala/Function1;
const #511 = Asciz	g;
const #512 = Asciz	Lscala/Function1;;
const #513 = Asciz	compose;
const #514 = NameAndType	#513:#508;//  compose:(Lscala/Function1;Lscala/Function1;)Lscala/Function1;
const #515 = Method	#21.#514;	//  scala/Function1$class.compose:(Lscala/Function1;Lscala/Function1;)Lscala/Function1;
const #516 = Asciz	(Lscala/Function1;)Ljava/lang/String;;
const #517 = NameAndType	#51:#516;//  toString:(Lscala/Function1;)Ljava/lang/String;
const #518 = Method	#21.#517;	//  scala/Function1$class.toString:(Lscala/Function1;)Ljava/lang/String;
const #519 = Asciz	Ljava/lang/Object;Lscala/Function1<Ljava/lang/Object;Ljava/lang/String;>;Lscala/ScalaObject;;
const #520 = Asciz	Signature;
const #521 = Asciz	InnerClasses;
const #522 = Asciz	scala/Predef;
const #523 = class	#522;	//  scala/Predef
const #524 = Asciz	$anon$1;
const #525 = Asciz	scala/reflect/Print;
const #526 = class	#525;	//  scala/reflect/Print
const #527 = Asciz	$anonfun$1;
const #528 = Asciz	scala/collection/generic/TraversableFactory;
const #529 = class	#528;	//  scala/collection/generic/TraversableFactory
const #530 = Asciz	GenericCanBuildFrom;
const #531 = Asciz	scala/Function1;
const #532 = class	#531;	//  scala/Function1
const #533 = Asciz	scala/ScalaObject;
const #534 = class	#533;	//  scala/ScalaObject

{
public static final scala.reflect.Print$ MODULE$;

public static {};
  Code:
   Stack=1, Locals=0, Args_size=0
   0:	new	#10; //class scala/reflect/Print$
   3:	invokespecial	#13; //Method "<init>":()V
   6:	return

public java.lang.Object apply(java.lang.Object);
  Code:
   Stack=2, Locals=2, Args_size=2
   0:	aload_0
   1:	aload_1
   2:	invokevirtual	#30; //Method apply:(Ljava/lang/Object;)Ljava/lang/String;
   5:	areturn
  LineNumberTable: 
   line 15: 0

  LocalVariableTable: 
   Start  Length  Slot  Name   Signature
   0      6      0    this       Lscala/reflect/Print$;
   0      6      1    v1       Ljava/lang/Object;


public java.lang.String apply(scala.reflect.Type);
  Code:
   Stack=6, Locals=29, Args_size=2
   0:	getstatic	#40; //Field scala/reflect/NoPrefix$.MODULE$:Lscala/reflect/NoPrefix$;
   3:	dup
   4:	ifnonnull	15
   7:	pop
   8:	aload_1
   9:	ifnull	22
   12:	goto	43
   15:	aload_1
   16:	invokevirtual	#44; //Method java/lang/Object.equals:(Ljava/lang/Object;)Z
   19:	ifeq	43
   22:	iconst_1
   23:	ifeq	31
   26:	ldc	#46; //String NoPrefix
   28:	goto	861
   31:	new	#48; //class scala/MatchError
   34:	dup
   35:	aload_1
   36:	invokevirtual	#54; //Method scala/reflect/Type.toString:()Ljava/lang/String;
   39:	invokespecial	#57; //Method scala/MatchError."<init>":(Ljava/lang/String;)V
   42:	athrow
   43:	getstatic	#62; //Field scala/reflect/NoType$.MODULE$:Lscala/reflect/NoType$;
   46:	dup
   47:	ifnonnull	58
   50:	pop
   51:	aload_1
   52:	ifnull	65
   55:	goto	86
   58:	aload_1
   59:	invokevirtual	#44; //Method java/lang/Object.equals:(Ljava/lang/Object;)Z
   62:	ifeq	86
   65:	iconst_1
   66:	ifeq	74
   69:	ldc	#64; //String NoType
   71:	goto	861
   74:	new	#48; //class scala/MatchError
   77:	dup
   78:	aload_1
   79:	invokevirtual	#54; //Method scala/reflect/Type.toString:()Ljava/lang/String;
   82:	invokespecial	#57; //Method scala/MatchError."<init>":(Ljava/lang/String;)V
   85:	athrow
   86:	aload_1
   87:	instanceof	#66; //class scala/reflect/NamedType
   90:	ifeq	146
   93:	aload_1
   94:	checkcast	#66; //class scala/reflect/NamedType
   97:	astore_2
   98:	aload_2
   99:	invokevirtual	#69; //Method scala/reflect/NamedType.fullname:()Ljava/lang/String;
   102:	astore_3
   103:	iconst_1
   104:	ifeq	134
   107:	new	#71; //class scala/collection/mutable/StringBuilder
   110:	dup
   111:	invokespecial	#72; //Method scala/collection/mutable/StringBuilder."<init>":()V
   114:	ldc	#74; //String (named: 
   116:	invokevirtual	#78; //Method scala/collection/mutable/StringBuilder.append:(Ljava/lang/Object;)Lscala/collection/mutable/StringBuilder;
   119:	aload_3
   120:	invokevirtual	#78; //Method scala/collection/mutable/StringBuilder.append:(Ljava/lang/Object;)Lscala/collection/mutable/StringBuilder;
   123:	ldc	#80; //String )
   125:	invokevirtual	#78; //Method scala/collection/mutable/StringBuilder.append:(Ljava/lang/Object;)Lscala/collection/mutable/StringBuilder;
   128:	invokevirtual	#81; //Method scala/collection/mutable/StringBuilder.toString:()Ljava/lang/String;
   131:	goto	861
   134:	new	#48; //class scala/MatchError
   137:	dup
   138:	aload_1
   139:	invokevirtual	#54; //Method scala/reflect/Type.toString:()Ljava/lang/String;
   142:	invokespecial	#57; //Method scala/MatchError."<init>":(Ljava/lang/String;)V
   145:	athrow
   146:	aload_1
   147:	instanceof	#83; //class scala/reflect/PrefixedType
   150:	ifeq	235
   153:	aload_1
   154:	checkcast	#83; //class scala/reflect/PrefixedType
   157:	astore	4
   159:	aload	4
   161:	invokevirtual	#87; //Method scala/reflect/PrefixedType.pre:()Lscala/reflect/Type;
   164:	astore	5
   166:	aload	4
   168:	invokevirtual	#91; //Method scala/reflect/PrefixedType.sym:()Lscala/reflect/Symbol;
   171:	astore	6
   173:	iconst_1
   174:	ifeq	223
   177:	new	#71; //class scala/collection/mutable/StringBuilder
   180:	dup
   181:	invokespecial	#72; //Method scala/collection/mutable/StringBuilder."<init>":()V
   184:	ldc	#93; //String (
   186:	invokevirtual	#78; //Method scala/collection/mutable/StringBuilder.append:(Ljava/lang/Object;)Lscala/collection/mutable/StringBuilder;
   189:	aload_0
   190:	aload	5
   192:	invokevirtual	#95; //Method apply:(Lscala/reflect/Type;)Ljava/lang/String;
   195:	invokevirtual	#78; //Method scala/collection/mutable/StringBuilder.append:(Ljava/lang/Object;)Lscala/collection/mutable/StringBuilder;
   198:	ldc	#97; //String .
   200:	invokevirtual	#78; //Method scala/collection/mutable/StringBuilder.append:(Ljava/lang/Object;)Lscala/collection/mutable/StringBuilder;
   203:	aload_0
   204:	aload	6
   206:	invokevirtual	#100; //Method apply:(Lscala/reflect/Symbol;)Ljava/lang/String;
   209:	invokevirtual	#78; //Method scala/collection/mutable/StringBuilder.append:(Ljava/lang/Object;)Lscala/collection/mutable/StringBuilder;
   212:	ldc	#80; //String )
   214:	invokevirtual	#78; //Method scala/collection/mutable/StringBuilder.append:(Ljava/lang/Object;)Lscala/collection/mutable/StringBuilder;
   217:	invokevirtual	#81; //Method scala/collection/mutable/StringBuilder.toString:()Ljava/lang/String;
   220:	goto	861
   223:	new	#48; //class scala/MatchError
   226:	dup
   227:	aload_1
   228:	invokevirtual	#54; //Method scala/reflect/Type.toString:()Ljava/lang/String;
   231:	invokespecial	#57; //Method scala/MatchError."<init>":(Ljava/lang/String;)V
   234:	athrow
   235:	aload_1
   236:	instanceof	#102; //class scala/reflect/SingleType
   239:	ifeq	324
   242:	aload_1
   243:	checkcast	#102; //class scala/reflect/SingleType
   246:	astore	7
   248:	aload	7
   250:	invokevirtual	#103; //Method scala/reflect/SingleType.pre:()Lscala/reflect/Type;
   253:	astore	8
   255:	aload	7
   257:	invokevirtual	#104; //Method scala/reflect/SingleType.sym:()Lscala/reflect/Symbol;
   260:	astore	9
   262:	iconst_1
   263:	ifeq	312
   266:	new	#71; //class scala/collection/mutable/StringBuilder
   269:	dup
   270:	invokespecial	#72; //Method scala/collection/mutable/StringBuilder."<init>":()V
   273:	ldc	#93; //String (
   275:	invokevirtual	#78; //Method scala/collection/mutable/StringBuilder.append:(Ljava/lang/Object;)Lscala/collection/mutable/StringBuilder;
   278:	aload_0
   279:	aload	8
   281:	invokevirtual	#95; //Method apply:(Lscala/reflect/Type;)Ljava/lang/String;
   284:	invokevirtual	#78; //Method scala/collection/mutable/StringBuilder.append:(Ljava/lang/Object;)Lscala/collection/mutable/StringBuilder;
   287:	ldc	#97; //String .
   289:	invokevirtual	#78; //Method scala/collection/mutable/StringBuilder.append:(Ljava/lang/Object;)Lscala/collection/mutable/StringBuilder;
   292:	aload_0
   293:	aload	9
   295:	invokevirtual	#100; //Method apply:(Lscala/reflect/Symbol;)Ljava/lang/String;
   298:	invokevirtual	#78; //Method scala/collection/mutable/StringBuilder.append:(Ljava/lang/Object;)Lscala/collection/mutable/StringBuilder;
   301:	ldc	#80; //String )
   303:	invokevirtual	#78; //Method scala/collection/mutable/StringBuilder.append:(Ljava/lang/Object;)Lscala/collection/mutable/StringBuilder;
   306:	invokevirtual	#81; //Method scala/collection/mutable/StringBuilder.toString:()Ljava/lang/String;
   309:	goto	861
   312:	new	#48; //class scala/MatchError
   315:	dup
   316:	aload_1
   317:	invokevirtual	#54; //Method scala/reflect/Type.toString:()Ljava/lang/String;
   320:	invokespecial	#57; //Method scala/MatchError."<init>":(Ljava/lang/String;)V
   323:	athrow
   324:	aload_1
   325:	instanceof	#106; //class scala/reflect/ThisType
   328:	ifeq	392
   331:	aload_1
   332:	checkcast	#106; //class scala/reflect/ThisType
   335:	astore	10
   337:	aload	10
   339:	invokevirtual	#109; //Method scala/reflect/ThisType.clazz:()Lscala/reflect/Symbol;
   342:	astore	11
   344:	iconst_1
   345:	ifeq	380
   348:	new	#71; //class scala/collection/mutable/StringBuilder
   351:	dup
   352:	invokespecial	#72; //Method scala/collection/mutable/StringBuilder."<init>":()V
   355:	ldc	#93; //String (
   357:	invokevirtual	#78; //Method scala/collection/mutable/StringBuilder.append:(Ljava/lang/Object;)Lscala/collection/mutable/StringBuilder;
   360:	aload_0
   361:	aload	11
   363:	invokevirtual	#100; //Method apply:(Lscala/reflect/Symbol;)Ljava/lang/String;
   366:	invokevirtual	#78; //Method scala/collection/mutable/StringBuilder.append:(Ljava/lang/Object;)Lscala/collection/mutable/StringBuilder;
   369:	ldc	#111; //String .this.type)
   371:	invokevirtual	#78; //Method scala/collection/mutable/StringBuilder.append:(Ljava/lang/Object;)Lscala/collection/mutable/StringBuilder;
   374:	invokevirtual	#81; //Method scala/collection/mutable/StringBuilder.toString:()Ljava/lang/String;
   377:	goto	861
   380:	new	#48; //class scala/MatchError
   383:	dup
   384:	aload_1
   385:	invokevirtual	#54; //Method scala/reflect/Type.toString:()Ljava/lang/String;
   388:	invokespecial	#57; //Method scala/MatchError."<init>":(Ljava/lang/String;)V
   391:	athrow
   392:	aload_1
   393:	instanceof	#113; //class scala/reflect/AppliedType
   396:	ifeq	496
   399:	aload_1
   400:	checkcast	#113; //class scala/reflect/AppliedType
   403:	astore	12
   405:	aload	12
   407:	invokevirtual	#116; //Method scala/reflect/AppliedType.tpe:()Lscala/reflect/Type;
   410:	astore	13
   412:	aload	12
   414:	invokevirtual	#120; //Method scala/reflect/AppliedType.args:()Lscala/collection/immutable/List;
   417:	astore	14
   419:	iconst_1
   420:	ifeq	484
   423:	new	#71; //class scala/collection/mutable/StringBuilder
   426:	dup
   427:	invokespecial	#72; //Method scala/collection/mutable/StringBuilder."<init>":()V
   430:	aload_0
   431:	aload	13
   433:	invokevirtual	#95; //Method apply:(Lscala/reflect/Type;)Ljava/lang/String;
   436:	invokevirtual	#78; //Method scala/collection/mutable/StringBuilder.append:(Ljava/lang/Object;)Lscala/collection/mutable/StringBuilder;
   439:	aload	14
   441:	aload_0
   442:	getstatic	#125; //Field scala/collection/immutable/List$.MODULE$:Lscala/collection/immutable/List$;
   445:	astore	15
   447:	new	#127; //class scala/collection/generic/TraversableFactory$GenericCanBuildFrom
   450:	dup
   451:	aload	15
   453:	invokespecial	#130; //Method scala/collection/generic/TraversableFactory$GenericCanBuildFrom."<init>":(Lscala/collection/generic/TraversableFactory;)V
   456:	invokeinterface	#136,  3; //InterfaceMethod scala/collection/TraversableLike.map:(Lscala/Function1;Lscala/collection/generic/CanBuildFrom;)Ljava/lang/Object;
   461:	checkcast	#132; //class scala/collection/TraversableLike
   464:	ldc	#138; //String [
   466:	ldc	#140; //String , 
   468:	ldc	#142; //String ]
   470:	invokeinterface	#146,  4; //InterfaceMethod scala/collection/TraversableLike.mkString:(Ljava/lang/String;Ljava/lang/String;Ljava/lang/String;)Ljava/lang/String;
   475:	invokevirtual	#78; //Method scala/collection/mutable/StringBuilder.append:(Ljava/lang/Object;)Lscala/collection/mutable/StringBuilder;
   478:	invokevirtual	#81; //Method scala/collection/mutable/StringBuilder.toString:()Ljava/lang/String;
   481:	goto	861
   484:	new	#48; //class scala/MatchError
   487:	dup
   488:	aload_1
   489:	invokevirtual	#54; //Method scala/reflect/Type.toString:()Ljava/lang/String;
   492:	invokespecial	#57; //Method scala/MatchError."<init>":(Ljava/lang/String;)V
   495:	athrow
   496:	aload_1
   497:	instanceof	#148; //class scala/reflect/TypeBounds
   500:	ifeq	585
   503:	aload_1
   504:	checkcast	#148; //class scala/reflect/TypeBounds
   507:	astore	16
   509:	aload	16
   511:	invokevirtual	#151; //Method scala/reflect/TypeBounds.lo:()Lscala/reflect/Type;
   514:	astore	17
   516:	aload	16
   518:	invokevirtual	#154; //Method scala/reflect/TypeBounds.hi:()Lscala/reflect/Type;
   521:	astore	18
   523:	iconst_1
   524:	ifeq	573
   527:	new	#71; //class scala/collection/mutable/StringBuilder
   530:	dup
   531:	invokespecial	#72; //Method scala/collection/mutable/StringBuilder."<init>":()V
   534:	ldc	#138; //String [
   536:	invokevirtual	#78; //Method scala/collection/mutable/StringBuilder.append:(Ljava/lang/Object;)Lscala/collection/mutable/StringBuilder;
   539:	aload_0
   540:	aload	17
   542:	invokevirtual	#95; //Method apply:(Lscala/reflect/Type;)Ljava/lang/String;
   545:	invokevirtual	#78; //Method scala/collection/mutable/StringBuilder.append:(Ljava/lang/Object;)Lscala/collection/mutable/StringBuilder;
   548:	ldc	#156; //String  ... 
   550:	invokevirtual	#78; //Method scala/collection/mutable/StringBuilder.append:(Ljava/lang/Object;)Lscala/collection/mutable/StringBuilder;
   553:	aload_0
   554:	aload	18
   556:	invokevirtual	#95; //Method apply:(Lscala/reflect/Type;)Ljava/lang/String;
   559:	invokevirtual	#78; //Method scala/collection/mutable/StringBuilder.append:(Ljava/lang/Object;)Lscala/collection/mutable/StringBuilder;
   562:	ldc	#142; //String ]
   564:	invokevirtual	#78; //Method scala/collection/mutable/StringBuilder.append:(Ljava/lang/Object;)Lscala/collection/mutable/StringBuilder;
   567:	invokevirtual	#81; //Method scala/collection/mutable/StringBuilder.toString:()Ljava/lang/String;
   570:	goto	861
   573:	new	#48; //class scala/MatchError
   576:	dup
   577:	aload_1
   578:	invokevirtual	#54; //Method scala/reflect/Type.toString:()Ljava/lang/String;
   581:	invokespecial	#57; //Method scala/MatchError."<init>":(Ljava/lang/String;)V
   584:	athrow
   585:	aload_1
   586:	instanceof	#158; //class scala/reflect/MethodType
   589:	ifeq	694
   592:	aload_1
   593:	checkcast	#158; //class scala/reflect/MethodType
   596:	astore	19
   598:	aload	19
   600:	invokevirtual	#161; //Method scala/reflect/MethodType.formals:()Lscala/collection/immutable/List;
   603:	astore	20
   605:	aload	19
   607:	invokevirtual	#164; //Method scala/reflect/MethodType.restpe:()Lscala/reflect/Type;
   610:	astore	22
   612:	iconst_1
   613:	ifeq	682
   616:	new	#71; //class scala/collection/mutable/StringBuilder
   619:	dup
   620:	invokespecial	#72; //Method scala/collection/mutable/StringBuilder."<init>":()V
   623:	aload	20
   625:	aload_0
   626:	getstatic	#125; //Field scala/collection/immutable/List$.MODULE$:Lscala/collection/immutable/List$;
   629:	astore	21
   631:	new	#127; //class scala/collection/generic/TraversableFactory$GenericCanBuildFrom
   634:	dup
   635:	aload	21
   637:	invokespecial	#130; //Method scala/collection/generic/TraversableFactory$GenericCanBuildFrom."<init>":(Lscala/collection/generic/TraversableFactory;)V
   640:	invokeinterface	#136,  3; //InterfaceMethod scala/collection/TraversableLike.map:(Lscala/Function1;Lscala/collection/generic/CanBuildFrom;)Ljava/lang/Object;
   645:	checkcast	#132; //class scala/collection/TraversableLike
   648:	ldc	#93; //String (
   650:	ldc	#140; //String , 
   652:	ldc	#80; //String )
   654:	invokeinterface	#146,  4; //InterfaceMethod scala/collection/TraversableLike.mkString:(Ljava/lang/String;Ljava/lang/String;Ljava/lang/String;)Ljava/lang/String;
   659:	invokevirtual	#78; //Method scala/collection/mutable/StringBuilder.append:(Ljava/lang/Object;)Lscala/collection/mutable/StringBuilder;
   662:	ldc	#166; //String  => 
   664:	invokevirtual	#78; //Method scala/collection/mutable/StringBuilder.append:(Ljava/lang/Object;)Lscala/collection/mutable/StringBuilder;
   667:	aload_0
   668:	aload	22
   670:	invokevirtual	#95; //Method apply:(Lscala/reflect/Type;)Ljava/lang/String;
   673:	invokevirtual	#78; //Method scala/collection/mutable/StringBuilder.append:(Ljava/lang/Object;)Lscala/collection/mutable/StringBuilder;
   676:	invokevirtual	#81; //Method scala/collection/mutable/StringBuilder.toString:()Ljava/lang/String;
   679:	goto	861
   682:	new	#48; //class scala/MatchError
   685:	dup
   686:	aload_1
   687:	invokevirtual	#54; //Method scala/reflect/Type.toString:()Ljava/lang/String;
   690:	invokespecial	#57; //Method scala/MatchError."<init>":(Ljava/lang/String;)V
   693:	athrow
   694:	aload_1
   695:	instanceof	#168; //class scala/reflect/PolyType
   698:	ifeq	855
   701:	aload_1
   702:	checkcast	#168; //class scala/reflect/PolyType
   705:	astore	23
   707:	aload	23
   709:	invokevirtual	#171; //Method scala/reflect/PolyType.typeParams:()Lscala/collection/immutable/List;
   712:	astore	24
   714:	aload	23
   716:	invokevirtual	#174; //Method scala/reflect/PolyType.typeBounds:()Lscala/collection/immutable/List;
   719:	astore	25
   721:	aload	23
   723:	invokevirtual	#177; //Method scala/reflect/PolyType.resultType:()Lscala/reflect/Type;
   726:	astore	28
   728:	iconst_1
   729:	ifeq	843
   732:	new	#179; //class scala/Tuple2
   735:	dup
   736:	aload	24
   738:	aload	25
   740:	invokespecial	#182; //Method scala/Tuple2."<init>":(Ljava/lang/Object;Ljava/lang/Object;)V
   743:	new	#184; //class scala/Predef$$anon$1
   746:	dup
   747:	invokespecial	#185; //Method scala/Predef$$anon$1."<init>":()V
   750:	new	#184; //class scala/Predef$$anon$1
   753:	dup
   754:	invokespecial	#185; //Method scala/Predef$$anon$1."<init>":()V
   757:	getstatic	#125; //Field scala/collection/immutable/List$.MODULE$:Lscala/collection/immutable/List$;
   760:	astore	26
   762:	new	#127; //class scala/collection/generic/TraversableFactory$GenericCanBuildFrom
   765:	dup
   766:	aload	26
   768:	invokespecial	#130; //Method scala/collection/generic/TraversableFactory$GenericCanBuildFrom."<init>":(Lscala/collection/generic/TraversableFactory;)V
   771:	invokevirtual	#189; //Method scala/Tuple2.zip:(Lscala/Function1;Lscala/Function1;Lscala/collection/generic/CanBuildFrom;)Ljava/lang/Object;
   774:	checkcast	#132; //class scala/collection/TraversableLike
   777:	new	#191; //class scala/reflect/Print$$anonfun$1
   780:	dup
   781:	invokespecial	#192; //Method scala/reflect/Print$$anonfun$1."<init>":()V
   784:	getstatic	#125; //Field scala/collection/immutable/List$.MODULE$:Lscala/collection/immutable/List$;
   787:	invokevirtual	#196; //Method scala/collection/immutable/List$.canBuildFrom:()Lscala/collection/generic/CanBuildFrom;
   790:	invokeinterface	#136,  3; //InterfaceMethod scala/collection/TraversableLike.map:(Lscala/Function1;Lscala/collection/generic/CanBuildFrom;)Ljava/lang/Object;
   795:	checkcast	#198; //class scala/collection/immutable/List
   798:	astore	27
   800:	new	#71; //class scala/collection/mutable/StringBuilder
   803:	dup
   804:	invokespecial	#72; //Method scala/collection/mutable/StringBuilder."<init>":()V
   807:	aload	27
   809:	ldc	#138; //String [
   811:	ldc	#140; //String , 
   813:	ldc	#142; //String ]
   815:	invokeinterface	#146,  4; //InterfaceMethod scala/collection/TraversableLike.mkString:(Ljava/lang/String;Ljava/lang/String;Ljava/lang/String;)Ljava/lang/String;
   820:	invokevirtual	#78; //Method scala/collection/mutable/StringBuilder.append:(Ljava/lang/Object;)Lscala/collection/mutable/StringBuilder;
   823:	ldc	#200; //String  -> 
   825:	invokevirtual	#78; //Method scala/collection/mutable/StringBuilder.append:(Ljava/lang/Object;)Lscala/collection/mutable/StringBuilder;
   828:	aload_0
   829:	aload	28
   831:	invokevirtual	#95; //Method apply:(Lscala/reflect/Type;)Ljava/lang/String;
   834:	invokevirtual	#78; //Method scala/collection/mutable/StringBuilder.append:(Ljava/lang/Object;)Lscala/collection/mutable/StringBuilder;
   837:	invokevirtual	#81; //Method scala/collection/mutable/StringBuilder.toString:()Ljava/lang/String;
   840:	goto	861
   843:	new	#48; //class scala/MatchError
   846:	dup
   847:	aload_1
   848:	invokevirtual	#54; //Method scala/reflect/Type.toString:()Ljava/lang/String;
   851:	invokespecial	#57; //Method scala/MatchError."<init>":(Ljava/lang/String;)V
   854:	athrow
   855:	iconst_1
   856:	ifeq	862
   859:	ldc	#202; //String ???
   861:	areturn
   862:	new	#48; //class scala/MatchError
   865:	dup
   866:	aload_1
   867:	invokevirtual	#54; //Method scala/reflect/Type.toString:()Ljava/lang/String;
   870:	invokespecial	#57; //Method scala/MatchError."<init>":(Ljava/lang/String;)V
   873:	athrow
  LineNumberTable: 
   line 86: 0
   line 21: 22
   line 88: 26
   line 86: 31
   line 21: 65
   line 90: 69
   line 86: 74
   line 21: 103
   line 92: 107
   line 86: 134
   line 21: 173
   line 94: 177
   line 86: 223
   line 21: 262
   line 96: 266
   line 86: 312
   line 21: 344
   line 98: 348
   line 86: 380
   line 21: 419
   line 100: 423
   line 86: 484
   line 21: 523
   line 102: 527
   line 86: 573
   line 21: 612
   line 104: 616
   line 86: 682
   line 21: 728
   line 106: 732
   line 107: 800
   line 86: 843
   line 21: 855
   line 109: 859
   line 86: 861

  LocalVariableTable: 
   Start  Length  Slot  Name   Signature
   0      874      0    this       Lscala/reflect/Print$;
   0      874      1    datatype       Lscala/reflect/Type;
   98      48      2    temp74       Lscala/reflect/NamedType;
   103      43      3    temp75       Ljava/lang/String;
   159      76      4    temp76       Lscala/reflect/PrefixedType;
   166      69      5    temp77       Lscala/reflect/Type;
   173      62      6    temp78       Lscala/reflect/Symbol;
   248      76      7    temp79       Lscala/reflect/SingleType;
   255      69      8    temp80       Lscala/reflect/Type;
   262      62      9    temp81       Lscala/reflect/Symbol;
   337      55      10    temp82       Lscala/reflect/ThisType;
   344      48      11    temp83       Lscala/reflect/Symbol;
   405      91      12    temp84       Lscala/reflect/AppliedType;
   412      84      13    temp85       Lscala/reflect/Type;
   419      77      14    temp86       Lscala/collection/immutable/List;
   509      76      16    temp87       Lscala/reflect/TypeBounds;
   516      69      17    temp88       Lscala/reflect/Type;
   523      62      18    temp89       Lscala/reflect/Type;
   598      96      19    temp90       Lscala/reflect/MethodType;
   605      89      20    temp91       Lscala/collection/immutable/List;
   612      82      22    temp92       Lscala/reflect/Type;
   707      148      23    temp93       Lscala/reflect/PolyType;
   714      141      24    temp94       Lscala/collection/immutable/List;
   721      134      25    temp95       Lscala/collection/immutable/List;
   800      40      27    z       Lscala/collection/immutable/List;
   728      127      28    temp96       Lscala/reflect/Type;


public java.lang.String apply(scala.reflect.Symbol);
  Code:
   Stack=3, Locals=16, Args_size=2
   0:	aload_1
   1:	instanceof	#241; //class scala/reflect/Class
   4:	ifeq	48
   7:	aload_1
   8:	checkcast	#241; //class scala/reflect/Class
   11:	astore_2
   12:	aload_2
   13:	invokevirtual	#242; //Method scala/reflect/Class.fullname:()Ljava/lang/String;
   16:	astore_3
   17:	iconst_1
   18:	ifeq	36
   21:	aload_3
   22:	aload_3
   23:	ldc	#243; //int 46
   25:	invokevirtual	#249; //Method java/lang/String.lastIndexOf:(I)I
   28:	iconst_1
   29:	iadd
   30:	invokevirtual	#253; //Method java/lang/String.substring:(I)Ljava/lang/String;
   33:	goto	448
   36:	new	#48; //class scala/MatchError
   39:	dup
   40:	aload_1
   41:	invokevirtual	#256; //Method scala/reflect/Symbol.toString:()Ljava/lang/String;
   44:	invokespecial	#57; //Method scala/MatchError."<init>":(Ljava/lang/String;)V
   47:	athrow
   48:	aload_1
   49:	instanceof	#258; //class scala/reflect/Method
   52:	ifeq	101
   55:	aload_1
   56:	checkcast	#258; //class scala/reflect/Method
   59:	astore	4
   61:	aload	4
   63:	invokevirtual	#259; //Method scala/reflect/Method.fullname:()Ljava/lang/String;
   66:	astore	5
   68:	iconst_1
   69:	ifeq	89
   72:	aload	5
   74:	aload	5
   76:	ldc	#243; //int 46
   78:	invokevirtual	#249; //Method java/lang/String.lastIndexOf:(I)I
   81:	iconst_1
   82:	iadd
   83:	invokevirtual	#253; //Method java/lang/String.substring:(I)Ljava/lang/String;
   86:	goto	448
   89:	new	#48; //class scala/MatchError
   92:	dup
   93:	aload_1
   94:	invokevirtual	#256; //Method scala/reflect/Symbol.toString:()Ljava/lang/String;
   97:	invokespecial	#57; //Method scala/MatchError."<init>":(Ljava/lang/String;)V
   100:	athrow
   101:	aload_1
   102:	instanceof	#261; //class scala/reflect/Field
   105:	ifeq	154
   108:	aload_1
   109:	checkcast	#261; //class scala/reflect/Field
   112:	astore	6
   114:	aload	6
   116:	invokevirtual	#262; //Method scala/reflect/Field.fullname:()Ljava/lang/String;
   119:	astore	7
   121:	iconst_1
   122:	ifeq	142
   125:	aload	7
   127:	aload	7
   129:	ldc	#243; //int 46
   131:	invokevirtual	#249; //Method java/lang/String.lastIndexOf:(I)I
   134:	iconst_1
   135:	iadd
   136:	invokevirtual	#253; //Method java/lang/String.substring:(I)Ljava/lang/String;
   139:	goto	448
   142:	new	#48; //class scala/MatchError
   145:	dup
   146:	aload_1
   147:	invokevirtual	#256; //Method scala/reflect/Symbol.toString:()Ljava/lang/String;
   150:	invokespecial	#57; //Method scala/MatchError."<init>":(Ljava/lang/String;)V
   153:	athrow
   154:	aload_1
   155:	instanceof	#264; //class scala/reflect/TypeField
   158:	ifeq	207
   161:	aload_1
   162:	checkcast	#264; //class scala/reflect/TypeField
   165:	astore	8
   167:	aload	8
   169:	invokevirtual	#265; //Method scala/reflect/TypeField.fullname:()Ljava/lang/String;
   172:	astore	9
   174:	iconst_1
   175:	ifeq	195
   178:	aload	9
   180:	aload	9
   182:	ldc	#243; //int 46
   184:	invokevirtual	#249; //Method java/lang/String.lastIndexOf:(I)I
   187:	iconst_1
   188:	iadd
   189:	invokevirtual	#253; //Method java/lang/String.substring:(I)Ljava/lang/String;
   192:	goto	448
   195:	new	#48; //class scala/MatchError
   198:	dup
   199:	aload_1
   200:	invokevirtual	#256; //Method scala/reflect/Symbol.toString:()Ljava/lang/String;
   203:	invokespecial	#57; //Method scala/MatchError."<init>":(Ljava/lang/String;)V
   206:	athrow
   207:	aload_1
   208:	instanceof	#267; //class scala/reflect/LocalValue
   211:	ifeq	260
   214:	aload_1
   215:	checkcast	#267; //class scala/reflect/LocalValue
   218:	astore	10
   220:	aload	10
   222:	invokevirtual	#270; //Method scala/reflect/LocalValue.name:()Ljava/lang/String;
   225:	astore	11
   227:	iconst_1
   228:	ifeq	248
   231:	aload	11
   233:	aload	11
   235:	ldc	#243; //int 46
   237:	invokevirtual	#249; //Method java/lang/String.lastIndexOf:(I)I
   240:	iconst_1
   241:	iadd
   242:	invokevirtual	#253; //Method java/lang/String.substring:(I)Ljava/lang/String;
   245:	goto	448
   248:	new	#48; //class scala/MatchError
   251:	dup
   252:	aload_1
   253:	invokevirtual	#256; //Method scala/reflect/Symbol.toString:()Ljava/lang/String;
   256:	invokespecial	#57; //Method scala/MatchError."<init>":(Ljava/lang/String;)V
   259:	athrow
   260:	aload_1
   261:	instanceof	#272; //class scala/reflect/LocalMethod
   264:	ifeq	313
   267:	aload_1
   268:	checkcast	#272; //class scala/reflect/LocalMethod
   271:	astore	12
   273:	aload	12
   275:	invokevirtual	#273; //Method scala/reflect/LocalMethod.name:()Ljava/lang/String;
   278:	astore	13
   280:	iconst_1
   281:	ifeq	301
   284:	aload	13
   286:	aload	13
   288:	ldc	#243; //int 46
   290:	invokevirtual	#249; //Method java/lang/String.lastIndexOf:(I)I
   293:	iconst_1
   294:	iadd
   295:	invokevirtual	#253; //Method java/lang/String.substring:(I)Ljava/lang/String;
   298:	goto	448
   301:	new	#48; //class scala/MatchError
   304:	dup
   305:	aload_1
   306:	invokevirtual	#256; //Method scala/reflect/Symbol.toString:()Ljava/lang/String;
   309:	invokespecial	#57; //Method scala/MatchError."<init>":(Ljava/lang/String;)V
   312:	athrow
   313:	getstatic	#278; //Field scala/reflect/NoSymbol$.MODULE$:Lscala/reflect/NoSymbol$;
   316:	dup
   317:	ifnonnull	328
   320:	pop
   321:	aload_1
   322:	ifnull	335
   325:	goto	357
   328:	aload_1
   329:	invokevirtual	#44; //Method java/lang/Object.equals:(Ljava/lang/Object;)Z
   332:	ifeq	357
   335:	iconst_1
   336:	ifeq	345
   339:	ldc_w	#280; //String NoSymbol
   342:	goto	448
   345:	new	#48; //class scala/MatchError
   348:	dup
   349:	aload_1
   350:	invokevirtual	#256; //Method scala/reflect/Symbol.toString:()Ljava/lang/String;
   353:	invokespecial	#57; //Method scala/MatchError."<init>":(Ljava/lang/String;)V
   356:	athrow
   357:	getstatic	#285; //Field scala/reflect/RootSymbol$.MODULE$:Lscala/reflect/RootSymbol$;
   360:	dup
   361:	ifnonnull	372
   364:	pop
   365:	aload_1
   366:	ifnull	379
   369:	goto	401
   372:	aload_1
   373:	invokevirtual	#44; //Method java/lang/Object.equals:(Ljava/lang/Object;)Z
   376:	ifeq	401
   379:	iconst_1
   380:	ifeq	389
   383:	ldc_w	#287; //String RootSymbol
   386:	goto	448
   389:	new	#48; //class scala/MatchError
   392:	dup
   393:	aload_1
   394:	invokevirtual	#256; //Method scala/reflect/Symbol.toString:()Ljava/lang/String;
   397:	invokespecial	#57; //Method scala/MatchError."<init>":(Ljava/lang/String;)V
   400:	athrow
   401:	aload_1
   402:	instanceof	#289; //class scala/reflect/LabelSymbol
   405:	ifeq	442
   408:	aload_1
   409:	checkcast	#289; //class scala/reflect/LabelSymbol
   412:	astore	14
   414:	aload	14
   416:	invokevirtual	#290; //Method scala/reflect/LabelSymbol.name:()Ljava/lang/String;
   419:	astore	15
   421:	iconst_1
   422:	ifeq	430
   425:	aload	15
   427:	goto	448
   430:	new	#48; //class scala/MatchError
   433:	dup
   434:	aload_1
   435:	invokevirtual	#256; //Method scala/reflect/Symbol.toString:()Ljava/lang/String;
   438:	invokespecial	#57; //Method scala/MatchError."<init>":(Ljava/lang/String;)V
   441:	athrow
   442:	iconst_1
   443:	ifeq	449
   446:	ldc	#202; //String ???
   448:	areturn
   449:	new	#48; //class scala/MatchError
   452:	dup
   453:	aload_1
   454:	invokevirtual	#256; //Method scala/reflect/Symbol.toString:()Ljava/lang/String;
   457:	invokespecial	#57; //Method scala/MatchError."<init>":(Ljava/lang/String;)V
   460:	athrow
  LineNumberTable: 
   line 63: 0
   line 21: 17
   line 65: 21
   line 63: 36
   line 21: 68
   line 67: 72
   line 63: 89
   line 21: 121
   line 69: 125
   line 63: 142
   line 21: 174
   line 71: 178
   line 63: 195
   line 21: 227
   line 73: 231
   line 63: 248
   line 21: 280
   line 75: 284
   line 63: 301
   line 21: 335
   line 77: 339
   line 63: 345
   line 21: 379
   line 79: 383
   line 63: 389
   line 21: 421
   line 81: 425
   line 63: 430
   line 21: 442
   line 83: 446
   line 63: 448

  LocalVariableTable: 
   Start  Length  Slot  Name   Signature
   0      461      0    this       Lscala/reflect/Print$;
   0      461      1    symbol       Lscala/reflect/Symbol;
   12      36      2    temp45       Lscala/reflect/Class;
   17      31      3    temp46       Ljava/lang/String;
   61      40      4    temp47       Lscala/reflect/Method;
   68      33      5    temp48       Ljava/lang/String;
   114      40      6    temp50       Lscala/reflect/Field;
   121      33      7    temp51       Ljava/lang/String;
   167      40      8    temp53       Lscala/reflect/TypeField;
   174      33      9    temp54       Ljava/lang/String;
   220      40      10    temp56       Lscala/reflect/LocalValue;
   227      33      11    temp58       Ljava/lang/String;
   273      40      12    temp60       Lscala/reflect/LocalMethod;
   280      33      13    temp62       Ljava/lang/String;
   414      28      14    temp66       Lscala/reflect/LabelSymbol;
   421      21      15    temp67       Ljava/lang/String;


public java.lang.String apply(scala.reflect.Tree);
  Code:
   Stack=6, Locals=42, Args_size=2
   0:	aload_1
   1:	instanceof	#315; //class scala/reflect/Ident
   4:	ifeq	41
   7:	aload_1
   8:	checkcast	#315; //class scala/reflect/Ident
   11:	astore_2
   12:	aload_2
   13:	invokevirtual	#316; //Method scala/reflect/Ident.sym:()Lscala/reflect/Symbol;
   16:	astore_3
   17:	iconst_1
   18:	ifeq	29
   21:	aload_0
   22:	aload_3
   23:	invokevirtual	#100; //Method apply:(Lscala/reflect/Symbol;)Ljava/lang/String;
   26:	goto	1197
   29:	new	#48; //class scala/MatchError
   32:	dup
   33:	aload_1
   34:	invokevirtual	#319; //Method scala/reflect/Tree.toString:()Ljava/lang/String;
   37:	invokespecial	#57; //Method scala/MatchError."<init>":(Ljava/lang/String;)V
   40:	athrow
   41:	aload_1
   42:	instanceof	#321; //class scala/reflect/Select
   45:	ifeq	120
   48:	aload_1
   49:	checkcast	#321; //class scala/reflect/Select
   52:	astore	4
   54:	aload	4
   56:	invokevirtual	#325; //Method scala/reflect/Select.qual:()Lscala/reflect/Tree;
   59:	astore	5
   61:	aload	4
   63:	invokevirtual	#326; //Method scala/reflect/Select.sym:()Lscala/reflect/Symbol;
   66:	astore	6
   68:	iconst_1
   69:	ifeq	108
   72:	new	#71; //class scala/collection/mutable/StringBuilder
   75:	dup
   76:	invokespecial	#72; //Method scala/collection/mutable/StringBuilder."<init>":()V
   79:	aload_0
   80:	aload	5
   82:	invokevirtual	#328; //Method apply:(Lscala/reflect/Tree;)Ljava/lang/String;
   85:	invokevirtual	#78; //Method scala/collection/mutable/StringBuilder.append:(Ljava/lang/Object;)Lscala/collection/mutable/StringBuilder;
   88:	ldc	#97; //String .
   90:	invokevirtual	#78; //Method scala/collection/mutable/StringBuilder.append:(Ljava/lang/Object;)Lscala/collection/mutable/StringBuilder;
   93:	aload_0
   94:	aload	6
   96:	invokevirtual	#100; //Method apply:(Lscala/reflect/Symbol;)Ljava/lang/String;
   99:	invokevirtual	#78; //Method scala/collection/mutable/StringBuilder.append:(Ljava/lang/Object;)Lscala/collection/mutable/StringBuilder;
   102:	invokevirtual	#81; //Method scala/collection/mutable/StringBuilder.toString:()Ljava/lang/String;
   105:	goto	1197
   108:	new	#48; //class scala/MatchError
   111:	dup
   112:	aload_1
   113:	invokevirtual	#319; //Method scala/reflect/Tree.toString:()Ljava/lang/String;
   116:	invokespecial	#57; //Method scala/MatchError."<init>":(Ljava/lang/String;)V
   119:	athrow
   120:	aload_1
   121:	instanceof	#330; //class scala/reflect/Literal
   124:	ifeq	243
   127:	aload_1
   128:	checkcast	#330; //class scala/reflect/Literal
   131:	astore	7
   133:	aload	7
   135:	invokevirtual	#334; //Method scala/reflect/Literal.value:()Ljava/lang/Object;
   138:	astore	9
   140:	iconst_1
   141:	ifeq	231
   144:	aload	9
   146:	instanceof	#245; //class java/lang/String
   149:	ifeq	206
   152:	aload	9
   154:	checkcast	#245; //class java/lang/String
   157:	astore	8
   159:	iconst_1
   160:	ifeq	193
   163:	new	#71; //class scala/collection/mutable/StringBuilder
   166:	dup
   167:	invokespecial	#72; //Method scala/collection/mutable/StringBuilder."<init>":()V
   170:	ldc_w	#336; //String \"
   173:	invokevirtual	#78; //Method scala/collection/mutable/StringBuilder.append:(Ljava/lang/Object;)Lscala/collection/mutable/StringBuilder;
   176:	aload	8
   178:	invokevirtual	#78; //Method scala/collection/mutable/StringBuilder.append:(Ljava/lang/Object;)Lscala/collection/mutable/StringBuilder;
   181:	ldc_w	#336; //String \"
   184:	invokevirtual	#78; //Method scala/collection/mutable/StringBuilder.append:(Ljava/lang/Object;)Lscala/collection/mutable/StringBuilder;
   187:	invokevirtual	#81; //Method scala/collection/mutable/StringBuilder.toString:()Ljava/lang/String;
   190:	goto	1197
   193:	new	#48; //class scala/MatchError
   196:	dup
   197:	aload	9
   199:	invokevirtual	#337; //Method java/lang/Object.toString:()Ljava/lang/String;
   202:	invokespecial	#57; //Method scala/MatchError."<init>":(Ljava/lang/String;)V
   205:	athrow
   206:	iconst_1
   207:	ifeq	218
   210:	aload	9
   212:	invokevirtual	#337; //Method java/lang/Object.toString:()Ljava/lang/String;
   215:	goto	1197
   218:	new	#48; //class scala/MatchError
   221:	dup
   222:	aload	9
   224:	invokevirtual	#337; //Method java/lang/Object.toString:()Ljava/lang/String;
   227:	invokespecial	#57; //Method scala/MatchError."<init>":(Ljava/lang/String;)V
   230:	athrow
   231:	new	#48; //class scala/MatchError
   234:	dup
   235:	aload_1
   236:	invokevirtual	#319; //Method scala/reflect/Tree.toString:()Ljava/lang/String;
   239:	invokespecial	#57; //Method scala/MatchError."<init>":(Ljava/lang/String;)V
   242:	athrow
   243:	aload_1
   244:	instanceof	#339; //class scala/reflect/Apply
   247:	ifeq	347
   250:	aload_1
   251:	checkcast	#339; //class scala/reflect/Apply
   254:	astore	10
   256:	aload	10
   258:	invokevirtual	#342; //Method scala/reflect/Apply.fun:()Lscala/reflect/Tree;
   261:	astore	11
   263:	aload	10
   265:	invokevirtual	#343; //Method scala/reflect/Apply.args:()Lscala/collection/immutable/List;
   268:	astore	12
   270:	iconst_1
   271:	ifeq	335
   274:	new	#71; //class scala/collection/mutable/StringBuilder
   277:	dup
   278:	invokespecial	#72; //Method scala/collection/mutable/StringBuilder."<init>":()V
   281:	aload_0
   282:	aload	11
   284:	invokevirtual	#328; //Method apply:(Lscala/reflect/Tree;)Ljava/lang/String;
   287:	invokevirtual	#78; //Method scala/collection/mutable/StringBuilder.append:(Ljava/lang/Object;)Lscala/collection/mutable/StringBuilder;
   290:	aload	12
   292:	aload_0
   293:	getstatic	#125; //Field scala/collection/immutable/List$.MODULE$:Lscala/collection/immutable/List$;
   296:	astore	13
   298:	new	#127; //class scala/collection/generic/TraversableFactory$GenericCanBuildFrom
   301:	dup
   302:	aload	13
   304:	invokespecial	#130; //Method scala/collection/generic/TraversableFactory$GenericCanBuildFrom."<init>":(Lscala/collection/generic/TraversableFactory;)V
   307:	invokeinterface	#136,  3; //InterfaceMethod scala/collection/TraversableLike.map:(Lscala/Function1;Lscala/collection/generic/CanBuildFrom;)Ljava/lang/Object;
   312:	checkcast	#132; //class scala/collection/TraversableLike
   315:	ldc	#93; //String (
   317:	ldc	#140; //String , 
   319:	ldc	#80; //String )
   321:	invokeinterface	#146,  4; //InterfaceMethod scala/collection/TraversableLike.mkString:(Ljava/lang/String;Ljava/lang/String;Ljava/lang/String;)Ljava/lang/String;
   326:	invokevirtual	#78; //Method scala/collection/mutable/StringBuilder.append:(Ljava/lang/Object;)Lscala/collection/mutable/StringBuilder;
   329:	invokevirtual	#81; //Method scala/collection/mutable/StringBuilder.toString:()Ljava/lang/String;
   332:	goto	1197
   335:	new	#48; //class scala/MatchError
   338:	dup
   339:	aload_1
   340:	invokevirtual	#319; //Method scala/reflect/Tree.toString:()Ljava/lang/String;
   343:	invokespecial	#57; //Method scala/MatchError."<init>":(Ljava/lang/String;)V
   346:	athrow
   347:	aload_1
   348:	instanceof	#345; //class scala/reflect/TypeApply
   351:	ifeq	451
   354:	aload_1
   355:	checkcast	#345; //class scala/reflect/TypeApply
   358:	astore	14
   360:	aload	14
   362:	invokevirtual	#346; //Method scala/reflect/TypeApply.fun:()Lscala/reflect/Tree;
   365:	astore	15
   367:	aload	14
   369:	invokevirtual	#347; //Method scala/reflect/TypeApply.args:()Lscala/collection/immutable/List;
   372:	astore	16
   374:	iconst_1
   375:	ifeq	439
   378:	new	#71; //class scala/collection/mutable/StringBuilder
   381:	dup
   382:	invokespecial	#72; //Method scala/collection/mutable/StringBuilder."<init>":()V
   385:	aload_0
   386:	aload	15
   388:	invokevirtual	#328; //Method apply:(Lscala/reflect/Tree;)Ljava/lang/String;
   391:	invokevirtual	#78; //Method scala/collection/mutable/StringBuilder.append:(Ljava/lang/Object;)Lscala/collection/mutable/StringBuilder;
   394:	aload	16
   396:	aload_0
   397:	getstatic	#125; //Field scala/collection/immutable/List$.MODULE$:Lscala/collection/immutable/List$;
   400:	astore	17
   402:	new	#127; //class scala/collection/generic/TraversableFactory$GenericCanBuildFrom
   405:	dup
   406:	aload	17
   408:	invokespecial	#130; //Method scala/collection/generic/TraversableFactory$GenericCanBuildFrom."<init>":(Lscala/collection/generic/TraversableFactory;)V
   411:	invokeinterface	#136,  3; //InterfaceMethod scala/collection/TraversableLike.map:(Lscala/Function1;Lscala/collection/generic/CanBuildFrom;)Ljava/lang/Object;
   416:	checkcast	#132; //class scala/collection/TraversableLike
   419:	ldc	#138; //String [
   421:	ldc	#140; //String , 
   423:	ldc	#142; //String ]
   425:	invokeinterface	#146,  4; //InterfaceMethod scala/collection/TraversableLike.mkString:(Ljava/lang/String;Ljava/lang/String;Ljava/lang/String;)Ljava/lang/String;
   430:	invokevirtual	#78; //Method scala/collection/mutable/StringBuilder.append:(Ljava/lang/Object;)Lscala/collection/mutable/StringBuilder;
   433:	invokevirtual	#81; //Method scala/collection/mutable/StringBuilder.toString:()Ljava/lang/String;
   436:	goto	1197
   439:	new	#48; //class scala/MatchError
   442:	dup
   443:	aload_1
   444:	invokevirtual	#319; //Method scala/reflect/Tree.toString:()Ljava/lang/String;
   447:	invokespecial	#57; //Method scala/MatchError."<init>":(Ljava/lang/String;)V
   450:	athrow
   451:	aload_1
   452:	instanceof	#349; //class scala/reflect/Function
   455:	ifeq	560
   458:	aload_1
   459:	checkcast	#349; //class scala/reflect/Function
   462:	astore	18
   464:	aload	18
   466:	invokevirtual	#352; //Method scala/reflect/Function.params:()Lscala/collection/immutable/List;
   469:	astore	19
   471:	aload	18
   473:	invokevirtual	#355; //Method scala/reflect/Function.body:()Lscala/reflect/Tree;
   476:	astore	21
   478:	iconst_1
   479:	ifeq	548
   482:	new	#71; //class scala/collection/mutable/StringBuilder
   485:	dup
   486:	invokespecial	#72; //Method scala/collection/mutable/StringBuilder."<init>":()V
   489:	aload	19
   491:	aload_0
   492:	getstatic	#125; //Field scala/collection/immutable/List$.MODULE$:Lscala/collection/immutable/List$;
   495:	astore	20
   497:	new	#127; //class scala/collection/generic/TraversableFactory$GenericCanBuildFrom
   500:	dup
   501:	aload	20
   503:	invokespecial	#130; //Method scala/collection/generic/TraversableFactory$GenericCanBuildFrom."<init>":(Lscala/collection/generic/TraversableFactory;)V
   506:	invokeinterface	#136,  3; //InterfaceMethod scala/collection/TraversableLike.map:(Lscala/Function1;Lscala/collection/generic/CanBuildFrom;)Ljava/lang/Object;
   511:	checkcast	#132; //class scala/collection/TraversableLike
   514:	ldc	#93; //String (
   516:	ldc	#140; //String , 
   518:	ldc	#80; //String )
   520:	invokeinterface	#146,  4; //InterfaceMethod scala/collection/TraversableLike.mkString:(Ljava/lang/String;Ljava/lang/String;Ljava/lang/String;)Ljava/lang/String;
   525:	invokevirtual	#78; //Method scala/collection/mutable/StringBuilder.append:(Ljava/lang/Object;)Lscala/collection/mutable/StringBuilder;
   528:	ldc	#166; //String  => 
   530:	invokevirtual	#78; //Method scala/collection/mutable/StringBuilder.append:(Ljava/lang/Object;)Lscala/collection/mutable/StringBuilder;
   533:	aload_0
   534:	aload	21
   536:	invokevirtual	#328; //Method apply:(Lscala/reflect/Tree;)Ljava/lang/String;
   539:	invokevirtual	#78; //Method scala/collection/mutable/StringBuilder.append:(Ljava/lang/Object;)Lscala/collection/mutable/StringBuilder;
   542:	invokevirtual	#81; //Method scala/collection/mutable/StringBuilder.toString:()Ljava/lang/String;
   545:	goto	1197
   548:	new	#48; //class scala/MatchError
   551:	dup
   552:	aload_1
   553:	invokevirtual	#319; //Method scala/reflect/Tree.toString:()Ljava/lang/String;
   556:	invokespecial	#57; //Method scala/MatchError."<init>":(Ljava/lang/String;)V
   559:	athrow
   560:	aload_1
   561:	instanceof	#357; //class scala/reflect/This
   564:	ifeq	624
   567:	aload_1
   568:	checkcast	#357; //class scala/reflect/This
   571:	astore	22
   573:	aload	22
   575:	invokevirtual	#358; //Method scala/reflect/This.sym:()Lscala/reflect/Symbol;
   578:	astore	23
   580:	iconst_1
   581:	ifeq	612
   584:	new	#71; //class scala/collection/mutable/StringBuilder
   587:	dup
   588:	invokespecial	#72; //Method scala/collection/mutable/StringBuilder."<init>":()V
   591:	aload_0
   592:	aload	23
   594:	invokevirtual	#100; //Method apply:(Lscala/reflect/Symbol;)Ljava/lang/String;
   597:	invokevirtual	#78; //Method scala/collection/mutable/StringBuilder.append:(Ljava/lang/Object;)Lscala/collection/mutable/StringBuilder;
   600:	ldc_w	#360; //String .this
   603:	invokevirtual	#78; //Method scala/collection/mutable/StringBuilder.append:(Ljava/lang/Object;)Lscala/collection/mutable/StringBuilder;
   606:	invokevirtual	#81; //Method scala/collection/mutable/StringBuilder.toString:()Ljava/lang/String;
   609:	goto	1197
   612:	new	#48; //class scala/MatchError
   615:	dup
   616:	aload_1
   617:	invokevirtual	#319; //Method scala/reflect/Tree.toString:()Ljava/lang/String;
   620:	invokespecial	#57; //Method scala/MatchError."<init>":(Ljava/lang/String;)V
   623:	athrow
   624:	aload_1
   625:	instanceof	#362; //class scala/reflect/Block
   628:	ifeq	731
   631:	aload_1
   632:	checkcast	#362; //class scala/reflect/Block
   635:	astore	24
   637:	aload	24
   639:	invokevirtual	#365; //Method scala/reflect/Block.stats:()Lscala/collection/immutable/List;
   642:	astore	27
   644:	aload	24
   646:	invokevirtual	#368; //Method scala/reflect/Block.expr:()Lscala/reflect/Tree;
   649:	astore	25
   651:	iconst_1
   652:	ifeq	719
   655:	getstatic	#373; //Field scala/Predef$.MODULE$:Lscala/Predef$;
   658:	iconst_1
   659:	anewarray	#318; //class scala/reflect/Tree
   662:	dup
   663:	iconst_0
   664:	aload	25
   666:	aastore
   667:	checkcast	#375; //class "[Ljava/lang/Object;"
   670:	invokevirtual	#379; //Method scala/Predef$.wrapRefArray:([Ljava/lang/Object;)Lscala/collection/mutable/WrappedArray;
   673:	astore	26
   675:	aload	26
   677:	invokeinterface	#382,  1; //InterfaceMethod scala/collection/TraversableLike.toList:()Lscala/collection/immutable/List;
   682:	aload	27
   684:	invokevirtual	#386; //Method scala/collection/immutable/List.$colon$colon$colon:(Lscala/collection/immutable/List;)Lscala/collection/immutable/List;
   687:	aload_0
   688:	getstatic	#125; //Field scala/collection/immutable/List$.MODULE$:Lscala/collection/immutable/List$;
   691:	invokevirtual	#196; //Method scala/collection/immutable/List$.canBuildFrom:()Lscala/collection/generic/CanBuildFrom;
   694:	invokeinterface	#136,  3; //InterfaceMethod scala/collection/TraversableLike.map:(Lscala/Function1;Lscala/collection/generic/CanBuildFrom;)Ljava/lang/Object;
   699:	checkcast	#132; //class scala/collection/TraversableLike
   702:	ldc_w	#388; //String {\n
   705:	ldc_w	#390; //String ;\n
   708:	ldc_w	#392; //String \n}
   711:	invokeinterface	#146,  4; //InterfaceMethod scala/collection/TraversableLike.mkString:(Ljava/lang/String;Ljava/lang/String;Ljava/lang/String;)Ljava/lang/String;
   716:	goto	1197
   719:	new	#48; //class scala/MatchError
   722:	dup
   723:	aload_1
   724:	invokevirtual	#319; //Method scala/reflect/Tree.toString:()Ljava/lang/String;
   727:	invokespecial	#57; //Method scala/MatchError."<init>":(Ljava/lang/String;)V
   730:	athrow
   731:	aload_1
   732:	instanceof	#394; //class scala/reflect/New
   735:	ifeq	795
   738:	aload_1
   739:	checkcast	#394; //class scala/reflect/New
   742:	astore	28
   744:	aload	28
   746:	invokevirtual	#396; //Method scala/reflect/New.sym:()Lscala/reflect/Tree;
   749:	astore	29
   751:	iconst_1
   752:	ifeq	783
   755:	new	#71; //class scala/collection/mutable/StringBuilder
   758:	dup
   759:	invokespecial	#72; //Method scala/collection/mutable/StringBuilder."<init>":()V
   762:	ldc_w	#398; //String new 
   765:	invokevirtual	#78; //Method scala/collection/mutable/StringBuilder.append:(Ljava/lang/Object;)Lscala/collection/mutable/StringBuilder;
   768:	aload_0
   769:	aload	29
   771:	invokevirtual	#328; //Method apply:(Lscala/reflect/Tree;)Ljava/lang/String;
   774:	invokevirtual	#78; //Method scala/collection/mutable/StringBuilder.append:(Ljava/lang/Object;)Lscala/collection/mutable/StringBuilder;
   777:	invokevirtual	#81; //Method scala/collection/mutable/StringBuilder.toString:()Ljava/lang/String;
   780:	goto	1197
   783:	new	#48; //class scala/MatchError
   786:	dup
   787:	aload_1
   788:	invokevirtual	#319; //Method scala/reflect/Tree.toString:()Ljava/lang/String;
   791:	invokespecial	#57; //Method scala/MatchError."<init>":(Ljava/lang/String;)V
   794:	athrow
   795:	aload_1
   796:	instanceof	#400; //class scala/reflect/If
   799:	ifeq	903
   802:	aload_1
   803:	checkcast	#400; //class scala/reflect/If
   806:	astore	30
   808:	aload	30
   810:	invokevirtual	#403; //Method scala/reflect/If.condition:()Lscala/reflect/Tree;
   813:	astore	31
   815:	aload	30
   817:	invokevirtual	#406; //Method scala/reflect/If.trueCase:()Lscala/reflect/Tree;
   820:	astore	32
   822:	aload	30
   824:	invokevirtual	#409; //Method scala/reflect/If.falseCase:()Lscala/reflect/Tree;
   827:	astore	33
   829:	iconst_1
   830:	ifeq	891
   833:	new	#71; //class scala/collection/mutable/StringBuilder
   836:	dup
   837:	invokespecial	#72; //Method scala/collection/mutable/StringBuilder."<init>":()V
   840:	ldc_w	#411; //String if (
   843:	invokevirtual	#78; //Method scala/collection/mutable/StringBuilder.append:(Ljava/lang/Object;)Lscala/collection/mutable/StringBuilder;
   846:	aload_0
   847:	aload	31
   849:	invokevirtual	#328; //Method apply:(Lscala/reflect/Tree;)Ljava/lang/String;
   852:	invokevirtual	#78; //Method scala/collection/mutable/StringBuilder.append:(Ljava/lang/Object;)Lscala/collection/mutable/StringBuilder;
   855:	ldc_w	#413; //String ) 
   858:	invokevirtual	#78; //Method scala/collection/mutable/StringBuilder.append:(Ljava/lang/Object;)Lscala/collection/mutable/StringBuilder;
   861:	aload_0
   862:	aload	32
   864:	invokevirtual	#328; //Method apply:(Lscala/reflect/Tree;)Ljava/lang/String;
   867:	invokevirtual	#78; //Method scala/collection/mutable/StringBuilder.append:(Ljava/lang/Object;)Lscala/collection/mutable/StringBuilder;
   870:	ldc_w	#415; //String  else 
   873:	invokevirtual	#78; //Method scala/collection/mutable/StringBuilder.append:(Ljava/lang/Object;)Lscala/collection/mutable/StringBuilder;
   876:	aload_0
   877:	aload	33
   879:	invokevirtual	#328; //Method apply:(Lscala/reflect/Tree;)Ljava/lang/String;
   882:	invokevirtual	#78; //Method scala/collection/mutable/StringBuilder.append:(Ljava/lang/Object;)Lscala/collection/mutable/StringBuilder;
   885:	invokevirtual	#81; //Method scala/collection/mutable/StringBuilder.toString:()Ljava/lang/String;
   888:	goto	1197
   891:	new	#48; //class scala/MatchError
   894:	dup
   895:	aload_1
   896:	invokevirtual	#319; //Method scala/reflect/Tree.toString:()Ljava/lang/String;
   899:	invokespecial	#57; //Method scala/MatchError."<init>":(Ljava/lang/String;)V
   902:	athrow
   903:	aload_1
   904:	instanceof	#417; //class scala/reflect/Assign
   907:	ifeq	1035
   910:	aload_1
   911:	checkcast	#417; //class scala/reflect/Assign
   914:	astore	34
   916:	aload	34
   918:	invokevirtual	#420; //Method scala/reflect/Assign.destination:()Lscala/reflect/Tree;
   921:	astore	35
   923:	aload	34
   925:	invokevirtual	#423; //Method scala/reflect/Assign.source:()Lscala/reflect/Tree;
   928:	astore	36
   930:	aload	35
   932:	ifnull	1014
   935:	aload	36
   937:	ifnull	993
   940:	iconst_1
   941:	ifeq	981
   944:	new	#71; //class scala/collection/mutable/StringBuilder
   947:	dup
   948:	invokespecial	#72; //Method scala/collection/mutable/StringBuilder."<init>":()V
   951:	aload_0
   952:	aload	35
   954:	invokevirtual	#328; //Method apply:(Lscala/reflect/Tree;)Ljava/lang/String;
   957:	invokevirtual	#78; //Method scala/collection/mutable/StringBuilder.append:(Ljava/lang/Object;)Lscala/collection/mutable/StringBuilder;
   960:	ldc_w	#425; //String  = 
   963:	invokevirtual	#78; //Method scala/collection/mutable/StringBuilder.append:(Ljava/lang/Object;)Lscala/collection/mutable/StringBuilder;
   966:	aload_0
   967:	aload	36
   969:	invokevirtual	#328; //Method apply:(Lscala/reflect/Tree;)Ljava/lang/String;
   972:	invokevirtual	#78; //Method scala/collection/mutable/StringBuilder.append:(Ljava/lang/Object;)Lscala/collection/mutable/StringBuilder;
   975:	invokevirtual	#81; //Method scala/collection/mutable/StringBuilder.toString:()Ljava/lang/String;
   978:	goto	1197
   981:	new	#48; //class scala/MatchError
   984:	dup
   985:	aload_1
   986:	invokevirtual	#319; //Method scala/reflect/Tree.toString:()Ljava/lang/String;
   989:	invokespecial	#57; //Method scala/MatchError."<init>":(Ljava/lang/String;)V
   992:	athrow
   993:	iconst_1
   994:	ifeq	1002
   997:	ldc	#202; //String ???
   999:	goto	1197
   1002:	new	#48; //class scala/MatchError
   1005:	dup
   1006:	aload_1
   1007:	invokevirtual	#319; //Method scala/reflect/Tree.toString:()Ljava/lang/String;
   1010:	invokespecial	#57; //Method scala/MatchError."<init>":(Ljava/lang/String;)V
   1013:	athrow
   1014:	iconst_1
   1015:	ifeq	1023
   1018:	ldc	#202; //String ???
   1020:	goto	1197
   1023:	new	#48; //class scala/MatchError
   1026:	dup
   1027:	aload_1
   1028:	invokevirtual	#319; //Method scala/reflect/Tree.toString:()Ljava/lang/String;
   1031:	invokespecial	#57; //Method scala/MatchError."<init>":(Ljava/lang/String;)V
   1034:	athrow
   1035:	aload_1
   1036:	instanceof	#427; //class scala/reflect/Target
   1039:	ifeq	1127
   1042:	aload_1
   1043:	checkcast	#427; //class scala/reflect/Target
   1046:	astore	37
   1048:	aload	37
   1050:	invokevirtual	#430; //Method scala/reflect/Target.sym:()Lscala/reflect/LabelSymbol;
   1053:	astore	38
   1055:	aload	37
   1057:	invokevirtual	#431; //Method scala/reflect/Target.body:()Lscala/reflect/Tree;
   1060:	astore	39
   1062:	iconst_1
   1063:	ifeq	1115
   1066:	new	#71; //class scala/collection/mutable/StringBuilder
   1069:	dup
   1070:	invokespecial	#72; //Method scala/collection/mutable/StringBuilder."<init>":()V
   1073:	ldc_w	#433; //String target 
   1076:	invokevirtual	#78; //Method scala/collection/mutable/StringBuilder.append:(Ljava/lang/Object;)Lscala/collection/mutable/StringBuilder;
   1079:	aload_0
   1080:	aload	38
   1082:	invokevirtual	#100; //Method apply:(Lscala/reflect/Symbol;)Ljava/lang/String;
   1085:	invokevirtual	#78; //Method scala/collection/mutable/StringBuilder.append:(Ljava/lang/Object;)Lscala/collection/mutable/StringBuilder;
   1088:	ldc_w	#435; //String  {\n
   1091:	invokevirtual	#78; //Method scala/collection/mutable/StringBuilder.append:(Ljava/lang/Object;)Lscala/collection/mutable/StringBuilder;
   1094:	aload_0
   1095:	aload	39
   1097:	invokevirtual	#328; //Method apply:(Lscala/reflect/Tree;)Ljava/lang/String;
   1100:	invokevirtual	#78; //Method scala/collection/mutable/StringBuilder.append:(Ljava/lang/Object;)Lscala/collection/mutable/StringBuilder;
   1103:	ldc_w	#392; //String \n}
   1106:	invokevirtual	#78; //Method scala/collection/mutable/StringBuilder.append:(Ljava/lang/Object;)Lscala/collection/mutable/StringBuilder;
   1109:	invokevirtual	#81; //Method scala/collection/mutable/StringBuilder.toString:()Ljava/lang/String;
   1112:	goto	1197
   1115:	new	#48; //class scala/MatchError
   1118:	dup
   1119:	aload_1
   1120:	invokevirtual	#319; //Method scala/reflect/Tree.toString:()Ljava/lang/String;
   1123:	invokespecial	#57; //Method scala/MatchError."<init>":(Ljava/lang/String;)V
   1126:	athrow
   1127:	aload_1
   1128:	instanceof	#437; //class scala/reflect/Goto
   1131:	ifeq	1191
   1134:	aload_1
   1135:	checkcast	#437; //class scala/reflect/Goto
   1138:	astore	40
   1140:	aload	40
   1142:	invokevirtual	#440; //Method scala/reflect/Goto.target:()Lscala/reflect/LabelSymbol;
   1145:	astore	41
   1147:	iconst_1
   1148:	ifeq	1179
   1151:	new	#71; //class scala/collection/mutable/StringBuilder
   1154:	dup
   1155:	invokespecial	#72; //Method scala/collection/mutable/StringBuilder."<init>":()V
   1158:	ldc_w	#442; //String goto 
   1161:	invokevirtual	#78; //Method scala/collection/mutable/StringBuilder.append:(Ljava/lang/Object;)Lscala/collection/mutable/StringBuilder;
   1164:	aload_0
   1165:	aload	41
   1167:	invokevirtual	#100; //Method apply:(Lscala/reflect/Symbol;)Ljava/lang/String;
   1170:	invokevirtual	#78; //Method scala/collection/mutable/StringBuilder.append:(Ljava/lang/Object;)Lscala/collection/mutable/StringBuilder;
   1173:	invokevirtual	#81; //Method scala/collection/mutable/StringBuilder.toString:()Ljava/lang/String;
   1176:	goto	1197
   1179:	new	#48; //class scala/MatchError
   1182:	dup
   1183:	aload_1
   1184:	invokevirtual	#319; //Method scala/reflect/Tree.toString:()Ljava/lang/String;
   1187:	invokespecial	#57; //Method scala/MatchError."<init>":(Ljava/lang/String;)V
   1190:	athrow
   1191:	iconst_1
   1192:	ifeq	1198
   1195:	ldc	#202; //String ???
   1197:	areturn
   1198:	new	#48; //class scala/MatchError
   1201:	dup
   1202:	aload_1
   1203:	invokevirtual	#319; //Method scala/reflect/Tree.toString:()Ljava/lang/String;
   1206:	invokespecial	#57; //Method scala/MatchError."<init>":(Ljava/lang/String;)V
   1209:	athrow
  LineNumberTable: 
   line 30: 0
   line 21: 17
   line 32: 21
   line 30: 29
   line 21: 68
   line 34: 72
   line 30: 108
   line 21: 140
   line 35: 144
   line 30: 152
   line 21: 159
   line 36: 163
   line 35: 193
   line 21: 206
   line 37: 210
   line 35: 218
   line 30: 231
   line 21: 270
   line 40: 274
   line 30: 335
   line 21: 374
   line 42: 378
   line 30: 439
   line 21: 478
   line 44: 482
   line 30: 548
   line 21: 580
   line 46: 584
   line 30: 612
   line 21: 651
   line 48: 655
   line 30: 719
   line 21: 751
   line 50: 755
   line 30: 783
   line 21: 829
   line 52: 833
   line 30: 891
   line 21: 940
   line 54: 944
   line 30: 981
   line 21: 993
   line 60: 997
   line 30: 1002
   line 21: 1014
   line 60: 1018
   line 30: 1023
   line 21: 1062
   line 56: 1066
   line 30: 1115
   line 21: 1147
   line 58: 1151
   line 30: 1179
   line 21: 1191
   line 60: 1195
   line 30: 1197

  LocalVariableTable: 
   Start  Length  Slot  Name   Signature
   0      1210      0    this       Lscala/reflect/Print$;
   0      1210      1    tree       Lscala/reflect/Tree;
   12      29      2    temp9       Lscala/reflect/Ident;
   17      24      3    temp10       Lscala/reflect/Symbol;
   54      66      4    temp11       Lscala/reflect/Select;
   61      59      5    temp12       Lscala/reflect/Tree;
   68      52      6    temp13       Lscala/reflect/Symbol;
   133      110      7    temp14       Lscala/reflect/Literal;
   159      47      8    temp7       Ljava/lang/String;
   140      103      9    temp15       Ljava/lang/Object;
   256      91      10    temp16       Lscala/reflect/Apply;
   263      84      11    temp17       Lscala/reflect/Tree;
   270      77      12    temp18       Lscala/collection/immutable/List;
   360      91      14    temp19       Lscala/reflect/TypeApply;
   367      84      15    temp20       Lscala/reflect/Tree;
   374      77      16    temp21       Lscala/collection/immutable/List;
   464      96      18    temp22       Lscala/reflect/Function;
   471      89      19    temp23       Lscala/collection/immutable/List;
   478      82      21    temp24       Lscala/reflect/Tree;
   573      51      22    temp25       Lscala/reflect/This;
   580      44      23    temp26       Lscala/reflect/Symbol;
   637      94      24    temp27       Lscala/reflect/Block;
   651      80      25    temp29       Lscala/reflect/Tree;
   644      87      27    temp28       Lscala/collection/immutable/List;
   744      51      28    temp30       Lscala/reflect/New;
   751      44      29    temp31       Lscala/reflect/Tree;
   808      95      30    temp32       Lscala/reflect/If;
   815      88      31    temp33       Lscala/reflect/Tree;
   822      81      32    temp34       Lscala/reflect/Tree;
   829      74      33    temp35       Lscala/reflect/Tree;
   916      119      34    temp36       Lscala/reflect/Assign;
   923      112      35    temp37       Lscala/reflect/Tree;
   930      105      36    temp38       Lscala/reflect/Tree;
   1048      79      37    temp39       Lscala/reflect/Target;
   1055      72      38    temp40       Lscala/reflect/LabelSymbol;
   1062      65      39    temp41       Lscala/reflect/Tree;
   1140      51      40    temp42       Lscala/reflect/Goto;
   1147      44      41    temp43       Lscala/reflect/LabelSymbol;


public java.lang.String apply(java.lang.Object);
  Code:
   Stack=3, Locals=6, Args_size=2
   0:	aload_1
   1:	instanceof	#495; //class scala/reflect/Code
   4:	ifeq	39
   7:	aload_1
   8:	checkcast	#495; //class scala/reflect/Code
   11:	astore_2
   12:	iconst_1
   13:	ifeq	27
   16:	aload_0
   17:	aload_2
   18:	invokevirtual	#497; //Method scala/reflect/Code.tree:()Lscala/reflect/Tree;
   21:	invokevirtual	#328; //Method apply:(Lscala/reflect/Tree;)Ljava/lang/String;
   24:	goto	158
   27:	new	#48; //class scala/MatchError
   30:	dup
   31:	aload_1
   32:	invokevirtual	#337; //Method java/lang/Object.toString:()Ljava/lang/String;
   35:	invokespecial	#57; //Method scala/MatchError."<init>":(Ljava/lang/String;)V
   38:	athrow
   39:	aload_1
   40:	instanceof	#318; //class scala/reflect/Tree
   43:	ifeq	75
   46:	aload_1
   47:	checkcast	#318; //class scala/reflect/Tree
   50:	astore_3
   51:	iconst_1
   52:	ifeq	63
   55:	aload_0
   56:	aload_3
   57:	invokevirtual	#328; //Method apply:(Lscala/reflect/Tree;)Ljava/lang/String;
   60:	goto	158
   63:	new	#48; //class scala/MatchError
   66:	dup
   67:	aload_1
   68:	invokevirtual	#337; //Method java/lang/Object.toString:()Ljava/lang/String;
   71:	invokespecial	#57; //Method scala/MatchError."<init>":(Ljava/lang/String;)V
   74:	athrow
   75:	aload_1
   76:	instanceof	#255; //class scala/reflect/Symbol
   79:	ifeq	113
   82:	aload_1
   83:	checkcast	#255; //class scala/reflect/Symbol
   86:	astore	4
   88:	iconst_1
   89:	ifeq	101
   92:	aload_0
   93:	aload	4
   95:	invokevirtual	#100; //Method apply:(Lscala/reflect/Symbol;)Ljava/lang/String;
   98:	goto	158
   101:	new	#48; //class scala/MatchError
   104:	dup
   105:	aload_1
   106:	invokevirtual	#337; //Method java/lang/Object.toString:()Ljava/lang/String;
   109:	invokespecial	#57; //Method scala/MatchError."<init>":(Ljava/lang/String;)V
   112:	athrow
   113:	aload_1
   114:	instanceof	#50; //class scala/reflect/Type
   117:	ifeq	151
   120:	aload_1
   121:	checkcast	#50; //class scala/reflect/Type
   124:	astore	5
   126:	iconst_1
   127:	ifeq	139
   130:	aload_0
   131:	aload	5
   133:	invokevirtual	#95; //Method apply:(Lscala/reflect/Type;)Ljava/lang/String;
   136:	goto	158
   139:	new	#48; //class scala/MatchError
   142:	dup
   143:	aload_1
   144:	invokevirtual	#337; //Method java/lang/Object.toString:()Ljava/lang/String;
   147:	invokespecial	#57; //Method scala/MatchError."<init>":(Ljava/lang/String;)V
   150:	athrow
   151:	iconst_1
   152:	ifeq	159
   155:	ldc_w	#499; //String UnknownAny
   158:	areturn
   159:	new	#48; //class scala/MatchError
   162:	dup
   163:	aload_1
   164:	invokevirtual	#337; //Method java/lang/Object.toString:()Ljava/lang/String;
   167:	invokespecial	#57; //Method scala/MatchError."<init>":(Ljava/lang/String;)V
   170:	athrow
  LineNumberTable: 
   line 17: 0
   line 21: 12
   line 19: 16
   line 17: 27
   line 21: 51
   line 17: 63
   line 21: 88
   line 23: 92
   line 17: 101
   line 21: 126
   line 25: 130
   line 17: 139
   line 21: 151
   line 27: 155
   line 17: 158

  LocalVariableTable: 
   Start  Length  Slot  Name   Signature
   0      171      0    this       Lscala/reflect/Print$;
   0      171      1    any       Ljava/lang/Object;
   12      27      2    temp2       Lscala/reflect/Code;
   51      24      3    temp3       Lscala/reflect/Tree;
   88      25      4    temp4       Lscala/reflect/Symbol;
   126      25      5    temp5       Lscala/reflect/Type;


public scala.Function1 andThen(scala.Function1);
  Code:
   Stack=2, Locals=2, Args_size=2
   0:	aload_0
   1:	aload_1
   2:	invokestatic	#510; //Method scala/Function1$class.andThen:(Lscala/Function1;Lscala/Function1;)Lscala/Function1;
   5:	areturn
  LineNumberTable: 
   line 15: 0

  LocalVariableTable: 
   Start  Length  Slot  Name   Signature
   0      6      0    this       Lscala/reflect/Print$;
   0      6      1    g       Lscala/Function1;


public scala.Function1 compose(scala.Function1);
  Code:
   Stack=2, Locals=2, Args_size=2
   0:	aload_0
   1:	aload_1
   2:	invokestatic	#515; //Method scala/Function1$class.compose:(Lscala/Function1;Lscala/Function1;)Lscala/Function1;
   5:	areturn
  LineNumberTable: 
   line 15: 0

  LocalVariableTable: 
   Start  Length  Slot  Name   Signature
   0      6      0    this       Lscala/reflect/Print$;
   0      6      1    g       Lscala/Function1;


public java.lang.String toString();
  Code:
   Stack=1, Locals=1, Args_size=1
   0:	aload_0
   1:	invokestatic	#518; //Method scala/Function1$class.toString:(Lscala/Function1;)Ljava/lang/String;
   4:	areturn
  LineNumberTable: 
   line 15: 0


}

