Compiled from "Print.scala"
public final class scala.reflect.Print extends java.lang.Object
  SourceFile: "Print.scala"
  ScalaSig: length = 0x1C9
   05 00 52 07 05 01 02 FFFFFF88 02 07 01 05 50 72 69 6E
   74 0A 02 03 04 01 07 72 65 66 6C 65 63 74 0A 01
   05 01 05 73 63 61 6C 61 03 00 10 02 08 09 0D 01
   02 06 08 0A 02 FFFFFF84 FFFFFF80 FFFFFF80 FFFFFF88 02 0B 02 05 50 72 69
   6E 74 13 04 09 0C 14 22 10 02 0D 12 0D 01 0E 0A
   02 0F 10 01 04 6C 61 6E 67 0A 01 11 01 04 6A 61
   76 61 09 02 13 0E 02 06 4F 62 6A 65 63 74 10 04
   15 16 18 1B 0D 01 04 09 02 17 04 02 09 46 75 6E
   63 74 69 6F 6E 31 10 02 15 19 09 02 1A 04 02 03
   41 6E 79 10 02 1C 1F 0E 02 15 1D 09 02 1E 04 01
   06 50 72 65 64 65 66 09 02 20 21 02 06 53 74 72
   69 6E 67 0A 02 1E 04 10 02 15 23 09 02 24 04 02
   0B 53 63 61 6C 61 4F 62 6A 65 63 74 08 05 26 09
   FFFFFF84 00 27 01 06 3C 69 6E 69 74 3E 14 01 07 08 05
   29 09 FFFFFF84 00 2A 01 05 61 70 70 6C 79 14 02 1B 2B
   08 05 2C 28 FFFFFFC0 00 18 01 03 61 6E 79 08 05 29 09
   FFFFFF84 00 2E 15 02 2F 37 14 02 1B 30 08 05 31 2D FFFFFFC0
   00 32 01 04 63 6F 64 65 10 03 08 33 35 09 02 34
   02 02 04 43 6F 64 65 10 02 36 37 0C 00 04 08 38
   2D FFFFFF84 FFFFFF80 FFFFFF80 FFFFFFC2 00 39 02 01 41 11 02 3A 18 10 02
   15 3B 09 02 3C 04 02 07 4E 6F 74 68 69 6E 67 08
   05 29 09 FFFFFF84 00 3E 14 02 1B 3F 08 05 40 3D FFFFFFC0 00
   41 01 04 74 72 65 65 10 02 08 42 09 02 43 02 02
   04 54 72 65 65 08 05 29 09 FFFFFF84 00 45 14 02 1B 46
   08 05 47 44 FFFFFFC0 00 48 01 06 73 79 6D 62 6F 6C 10
   02 08 49 09 02 4A 02 02 06 53 79 6D 62 6F 6C 08
   05 29 09 FFFFFF84 00 4C 14 02 1B 4D 08 05 4E 4B FFFFFFC0 00
   4F 01 08 64 61 74 61 74 79 70 65 10 02 08 50 09
   02 51 02 02 04 54 79 70 65 
  InnerClass: 
   public final #44= #41 of #43; //$anonfun$apply$1=class scala/reflect/Print$$anonfun$apply$1 of class scala/reflect/Print
  minor version: 0
  major version: 49
  Constant pool:
const #1 = Asciz	SourceFile;
const #2 = Asciz	Print.scala;
const #3 = Asciz	andThen;
const #4 = Asciz	(Lscala/Function1;)Lscala/Function1;;
const #5 = Asciz	Code;
const #6 = Asciz	scala/reflect/Print$;
const #7 = class	#6;	//  scala/reflect/Print$
const #8 = Asciz	MODULE$;
const #9 = Asciz	Lscala/reflect/Print$;;
const #10 = NameAndType	#8:#9;//  MODULE$:Lscala/reflect/Print$;
const #11 = Field	#7.#10;	//  scala/reflect/Print$.MODULE$:Lscala/reflect/Print$;
const #12 = NameAndType	#3:#4;//  andThen:(Lscala/Function1;)Lscala/Function1;
const #13 = Method	#7.#12;	//  scala/reflect/Print$.andThen:(Lscala/Function1;)Lscala/Function1;
const #14 = Asciz	compose;
const #15 = NameAndType	#14:#4;//  compose:(Lscala/Function1;)Lscala/Function1;
const #16 = Method	#7.#15;	//  scala/reflect/Print$.compose:(Lscala/Function1;)Lscala/Function1;
const #17 = Asciz	apply;
const #18 = Asciz	(Lscala/reflect/Type;)Ljava/lang/String;;
const #19 = NameAndType	#17:#18;//  apply:(Lscala/reflect/Type;)Ljava/lang/String;
const #20 = Method	#7.#19;	//  scala/reflect/Print$.apply:(Lscala/reflect/Type;)Ljava/lang/String;
const #21 = Asciz	(Lscala/reflect/Symbol;)Ljava/lang/String;;
const #22 = NameAndType	#17:#21;//  apply:(Lscala/reflect/Symbol;)Ljava/lang/String;
const #23 = Method	#7.#22;	//  scala/reflect/Print$.apply:(Lscala/reflect/Symbol;)Ljava/lang/String;
const #24 = Asciz	(Lscala/reflect/Tree;)Ljava/lang/String;;
const #25 = NameAndType	#17:#24;//  apply:(Lscala/reflect/Tree;)Ljava/lang/String;
const #26 = Method	#7.#25;	//  scala/reflect/Print$.apply:(Lscala/reflect/Tree;)Ljava/lang/String;
const #27 = Asciz	(Lscala/reflect/Code;)Ljava/lang/String;;
const #28 = NameAndType	#17:#27;//  apply:(Lscala/reflect/Code;)Ljava/lang/String;
const #29 = Method	#7.#28;	//  scala/reflect/Print$.apply:(Lscala/reflect/Code;)Ljava/lang/String;
const #30 = Asciz	<A:Ljava/lang/Object;>(Lscala/reflect/Code<TA;>;)Ljava/lang/String;;
const #31 = Asciz	Signature;
const #32 = Asciz	(Ljava/lang/Object;)Ljava/lang/String;;
const #33 = NameAndType	#17:#32;//  apply:(Ljava/lang/Object;)Ljava/lang/String;
const #34 = Method	#7.#33;	//  scala/reflect/Print$.apply:(Ljava/lang/Object;)Ljava/lang/String;
const #35 = Asciz	(Ljava/lang/Object;)Ljava/lang/Object;;
const #36 = NameAndType	#17:#35;//  apply:(Ljava/lang/Object;)Ljava/lang/Object;
const #37 = Method	#7.#36;	//  scala/reflect/Print$.apply:(Ljava/lang/Object;)Ljava/lang/Object;
const #38 = Asciz	ScalaSig;
const #39 = Asciz	InnerClasses;
const #40 = Asciz	scala/reflect/Print$$anonfun$apply$1;
const #41 = class	#40;	//  scala/reflect/Print$$anonfun$apply$1
const #42 = Asciz	scala/reflect/Print;
const #43 = class	#42;	//  scala/reflect/Print
const #44 = Asciz	$anonfun$apply$1;
const #45 = Asciz	java/lang/Object;
const #46 = class	#45;	//  java/lang/Object

{
public static final scala.Function1 andThen(scala.Function1);
  Code:
   Stack=2, Locals=1, Args_size=1
   0:	getstatic	#11; //Field scala/reflect/Print$.MODULE$:Lscala/reflect/Print$;
   3:	aload_0
   4:	invokevirtual	#13; //Method scala/reflect/Print$.andThen:(Lscala/Function1;)Lscala/Function1;
   7:	areturn

public static final scala.Function1 compose(scala.Function1);
  Code:
   Stack=2, Locals=1, Args_size=1
   0:	getstatic	#11; //Field scala/reflect/Print$.MODULE$:Lscala/reflect/Print$;
   3:	aload_0
   4:	invokevirtual	#16; //Method scala/reflect/Print$.compose:(Lscala/Function1;)Lscala/Function1;
   7:	areturn

public static final java.lang.String apply(scala.reflect.Type);
  Code:
   Stack=2, Locals=1, Args_size=1
   0:	getstatic	#11; //Field scala/reflect/Print$.MODULE$:Lscala/reflect/Print$;
   3:	aload_0
   4:	invokevirtual	#20; //Method scala/reflect/Print$.apply:(Lscala/reflect/Type;)Ljava/lang/String;
   7:	areturn

public static final java.lang.String apply(scala.reflect.Symbol);
  Code:
   Stack=2, Locals=1, Args_size=1
   0:	getstatic	#11; //Field scala/reflect/Print$.MODULE$:Lscala/reflect/Print$;
   3:	aload_0
   4:	invokevirtual	#23; //Method scala/reflect/Print$.apply:(Lscala/reflect/Symbol;)Ljava/lang/String;
   7:	areturn

public static final java.lang.String apply(scala.reflect.Tree);
  Code:
   Stack=2, Locals=1, Args_size=1
   0:	getstatic	#11; //Field scala/reflect/Print$.MODULE$:Lscala/reflect/Print$;
   3:	aload_0
   4:	invokevirtual	#26; //Method scala/reflect/Print$.apply:(Lscala/reflect/Tree;)Ljava/lang/String;
   7:	areturn

public static final java.lang.String apply(scala.reflect.Code);
  Code:
   Stack=2, Locals=1, Args_size=1
   0:	getstatic	#11; //Field scala/reflect/Print$.MODULE$:Lscala/reflect/Print$;
   3:	aload_0
   4:	invokevirtual	#29; //Method scala/reflect/Print$.apply:(Lscala/reflect/Code;)Ljava/lang/String;
   7:	areturn
  Signature: length = 0x2
   00 1E 

public static final java.lang.String apply(java.lang.Object);
  Code:
   Stack=2, Locals=1, Args_size=1
   0:	getstatic	#11; //Field scala/reflect/Print$.MODULE$:Lscala/reflect/Print$;
   3:	aload_0
   4:	invokevirtual	#34; //Method scala/reflect/Print$.apply:(Ljava/lang/Object;)Ljava/lang/String;
   7:	areturn

public static final java.lang.Object apply(java.lang.Object);
  Code:
   Stack=2, Locals=1, Args_size=1
   0:	getstatic	#11; //Field scala/reflect/Print$.MODULE$:Lscala/reflect/Print$;
   3:	aload_0
   4:	invokevirtual	#37; //Method scala/reflect/Print$.apply:(Ljava/lang/Object;)Ljava/lang/Object;
   7:	areturn

}

