Compiled from "Print.scala"
public final class scala.reflect.Print$$anonfun$1 extends scala.runtime.AbstractFunction1 implements java.io.Serializable
  SourceFile: "Print.scala"
  Scala: length = 0x
   
  InnerClass: 
   public final $anonfun$1=class scala/reflect/Print$$anonfun$1 of class scala/reflect/Print
  minor version: 0
  major version: 49
  Constant pool:
Asciz	SourceFile;
Asciz	Print.scala;
Asciz	<clinit>;
Asciz	()V;
Asciz	Code;
Asciz	serialVersionUID;
Asciz	J;
Asciz	scala/reflect/Print$$anonfun$1;
class	scala/reflect/Print$$anonfun$1
NameAndType	serialVersionUID:J
Field	scala/reflect/Print$$anonfun$1.serialVersionUID:J
Asciz	<init>;
Asciz	LineNumberTable;
Asciz	scala/runtime/AbstractFunction1;
class	scala/runtime/AbstractFunction1
NameAndType	"<init>":()V
Method	scala/runtime/AbstractFunction1."<init>":()V
Asciz	apply;
Asciz	(Ljava/lang/Object;)Ljava/lang/Object;;
Asciz	scala/Tuple2;
class	scala/Tuple2
Asciz	(Lscala/Tuple2;)Ljava/lang/String;;
NameAndType	apply:(Lscala/Tuple2;)Ljava/lang/String;
Method	scala/reflect/Print$$anonfun$1.apply:(Lscala/Tuple2;)Ljava/lang/String;
Asciz	this;
Asciz	Lscala/reflect/Print$$anonfun$1;;
Asciz	v1;
Asciz	Ljava/lang/Object;;
Asciz	LocalVariableTable;
Asciz	_1;
Asciz	()Ljava/lang/Object;;
NameAndType	_1:()Ljava/lang/Object;
Method	scala/Tuple2._1:()Ljava/lang/Object;
Asciz	scala/reflect/Symbol;
class	scala/reflect/Symbol
Asciz	_2;
NameAndType	_2:()Ljava/lang/Object;
Method	scala/Tuple2._2:()Ljava/lang/Object;
Asciz	scala/collection/mutable/StringBuilder;
class	scala/collection/mutable/StringBuilder
Method	scala/collection/mutable/StringBuilder."<init>":()V
Asciz	[;
String	[
Asciz	append;
Asciz	(Ljava/lang/Object;)Lscala/collection/mutable/StringBuilder;;
NameAndType	append:(Ljava/lang/Object;)Lscala/collection/mutable/StringBuilder;
Method	scala/collection/mutable/StringBuilder.append:(Ljava/lang/Object;)Lscala/collection/mutable/StringBuilder;
Asciz	scala/reflect/Print$;
class	scala/reflect/Print$
Asciz	MODULE$;
Asciz	Lscala/reflect/Print$;;
NameAndType	MODULE$:Lscala/reflect/Print$;
Field	scala/reflect/Print$.MODULE$:Lscala/reflect/Print$;
Asciz	scala/reflect/Type;
class	scala/reflect/Type
Asciz	(Lscala/reflect/Type;)Ljava/lang/String;;
NameAndType	apply:(Lscala/reflect/Type;)Ljava/lang/String;
Method	scala/reflect/Print$.apply:(Lscala/reflect/Type;)Ljava/lang/String;
Asciz	 :> ;
String	 :> 
Asciz	(Lscala/reflect/Symbol;)Ljava/lang/String;;
NameAndType	apply:(Lscala/reflect/Symbol;)Ljava/lang/String;
Method	scala/reflect/Print$.apply:(Lscala/reflect/Symbol;)Ljava/lang/String;
Asciz	];
String	]
Asciz	toString;
Asciz	()Ljava/lang/String;;
NameAndType	toString:()Ljava/lang/String;
Method	scala/collection/mutable/StringBuilder.toString:()Ljava/lang/String;
Asciz	scala/MatchError;
class	scala/MatchError
Method	scala/Tuple2.toString:()Ljava/lang/String;
Asciz	(Ljava/lang/String;)V;
NameAndType	"<init>":(Ljava/lang/String;)V
Method	scala/MatchError."<init>":(Ljava/lang/String;)V
Asciz	temp69;
Asciz	Lscala/reflect/Symbol;;
Asciz	temp70;
Asciz	Lscala/Tuple2;;
Asciz	(Lscala/Tuple2<Lscala/reflect/Symbol;Lscala/Tuple2<Lscala/reflect/Type;Lscala/reflect/Type;>;>;)Ljava/lang/String;;
Asciz	Signature;
Asciz	Scala;
Asciz	InnerClasses;
Asciz	scala/reflect/Print;
class	scala/reflect/Print
Asciz	$anonfun$1;
Asciz	java/io/Serializable;
class	java/io/Serializable

{
public static final long serialVersionUID;
  Signature: J

public static {};
  Signature: ()V
  Code:
   Stack=2, Locals=0, Args_size=0
	lconst_0
	putstatic	Field serialVersionUID:J
	return
  Labels:

public scala.reflect.Print$$anonfun$1();
  Signature: ()V
  Code:
   Stack=1, Locals=1, Args_size=1
	aload_0
	invokespecial	Method scala/runtime/AbstractFunction1."<init>":()V
	return
  Labels:

public final java.lang.Object apply(java.lang.Object);
  Signature: (Ljava/lang/Object;)Ljava/lang/Object;
  Code:
   Stack=2, Locals=2, Args_size=2
	aload_0
	aload_1
	checkcast	class scala/Tuple2
	invokevirtual	Method apply:(Lscala/Tuple2;)Ljava/lang/String;
	areturn
  Labels:
  LocalVariableTable: 
   Start  Length  Slot  Name   Signature
   0      9      0    this       Lscala/reflect/Print$$anonfun$1;
   0      9      1    v1       Ljava/lang/Object;


public final java.lang.String apply(scala.Tuple2);
  Signature: (Lscala/Tuple2;)Ljava/lang/String;
  Code:
   Stack=3, Locals=4, Args_size=2
	aload_1
	ifnull	l1 // new
	aload_1
	invokevirtual	Method scala/Tuple2._1:()Ljava/lang/Object;
	checkcast	class scala/reflect/Symbol
	astore_2
	aload_1
	invokevirtual	Method scala/Tuple2._2:()Ljava/lang/Object;
	checkcast	class scala/Tuple2
	astore_3
	iconst_1
	ifeq	l2 // new
	new	class scala/collection/mutable/StringBuilder
	dup
	invokespecial	Method scala/collection/mutable/StringBuilder."<init>":()V
	ldc	String [
	invokevirtual	Method scala/collection/mutable/StringBuilder.append:(Ljava/lang/Object;)Lscala/collection/mutable/StringBuilder;
	getstatic	Field scala/reflect/Print$.MODULE$:Lscala/reflect/Print$;
	aload_3
	invokevirtual	Method scala/Tuple2._1:()Ljava/lang/Object;
	checkcast	class scala/reflect/Type
	invokevirtual	Method scala/reflect/Print$.apply:(Lscala/reflect/Type;)Ljava/lang/String;
	invokevirtual	Method scala/collection/mutable/StringBuilder.append:(Ljava/lang/Object;)Lscala/collection/mutable/StringBuilder;
	ldc	String  :> 
	invokevirtual	Method scala/collection/mutable/StringBuilder.append:(Ljava/lang/Object;)Lscala/collection/mutable/StringBuilder;
	getstatic	Field scala/reflect/Print$.MODULE$:Lscala/reflect/Print$;
	aload_2
	invokevirtual	Method scala/reflect/Print$.apply:(Lscala/reflect/Symbol;)Ljava/lang/String;
	invokevirtual	Method scala/collection/mutable/StringBuilder.append:(Ljava/lang/Object;)Lscala/collection/mutable/StringBuilder;
	ldc	String  :> 
	invokevirtual	Method scala/collection/mutable/StringBuilder.append:(Ljava/lang/Object;)Lscala/collection/mutable/StringBuilder;
	getstatic	Field scala/reflect/Print$.MODULE$:Lscala/reflect/Print$;
	aload_3
	invokevirtual	Method scala/Tuple2._2:()Ljava/lang/Object;
	checkcast	class scala/reflect/Type
	invokevirtual	Method scala/reflect/Print$.apply:(Lscala/reflect/Type;)Ljava/lang/String;
	invokevirtual	Method scala/collection/mutable/StringBuilder.append:(Ljava/lang/Object;)Lscala/collection/mutable/StringBuilder;
	ldc	String ]
	invokevirtual	Method scala/collection/mutable/StringBuilder.append:(Ljava/lang/Object;)Lscala/collection/mutable/StringBuilder;
	invokevirtual	Method scala/collection/mutable/StringBuilder.toString:()Ljava/lang/String;
	areturn
l2	new	class scala/MatchError
	dup
	aload_1
	invokevirtual	Method scala/Tuple2.toString:()Ljava/lang/String;
	invokespecial	Method scala/MatchError."<init>":(Ljava/lang/String;)V
	athrow
l1	new	class scala/MatchError
	dup
	aload_1
	invokevirtual	Method scala/Tuple2.toString:()Ljava/lang/String;
	invokespecial	Method scala/MatchError."<init>":(Ljava/lang/String;)V
	athrow
  Labels:
   	l2 = 97 // new
   	l1 = 109 // new
  LocalVariableTable: 
   Start  Length  Slot  Name   Signature
   0      121      0    this       Lscala/reflect/Print$$anonfun$1;
   12      97      2    temp69       Lscala/reflect/Symbol;
   20      89      3    temp70       Lscala/Tuple2;

  Signature: length = 0x2
   00 50 

}

