Compiled from "RichClass.scala"
public final class scala.reflect.RichClass$ extends java.lang.Object implements scala.ScalaObject
  SourceFile: "RichClass.scala"
  Scala: length = 0x
   
  InnerClass: 
   public #36= #35 of #23; //ReflectiveCall=class scala/reflect/RichClass$ReflectiveCall of class scala/reflect/RichClass
   public #39= #38 of #23; //FailedReflectiveCall=class scala/reflect/RichClass$FailedReflectiveCall of class scala/reflect/RichClass
   public final #42= #41 of #23; //$anonfun$reflectiveCall$1=class scala/reflect/RichClass$$anonfun$reflectiveCall$1 of class scala/reflect/RichClass
   public final #45= #44 of #23; //$anonfun$getConstructorsTyped$1=class scala/reflect/RichClass$$anonfun$getConstructorsTyped$1 of class scala/reflect/RichClass
   public final #48= #47 of #23; //$anonfun$getDeclaredConstructorsTyped$1=class scala/reflect/RichClass$$anonfun$getDeclaredConstructorsTyped$1 of class scala/reflect/RichClass
  minor version: 0
  major version: 49
  Constant pool:
const #1 = Asciz	SourceFile;
const #2 = Asciz	RichClass.scala;
const #3 = Asciz	Scala;
const #4 = Asciz	MODULE$;
const #5 = Asciz	Lscala/reflect/RichClass$;;
const #6 = Asciz	<clinit>;
const #7 = Asciz	()V;
const #8 = Asciz	Code;
const #9 = Asciz	scala/reflect/RichClass$;
const #10 = class	#9;	//  scala/reflect/RichClass$
const #11 = Asciz	<init>;
const #12 = NameAndType	#11:#7;//  "<init>":()V
const #13 = Method	#10.#12;	//  scala/reflect/RichClass$."<init>":()V
const #14 = Asciz	LineNumberTable;
const #15 = Asciz	java/lang/Object;
const #16 = class	#15;	//  java/lang/Object
const #17 = Method	#16.#12;	//  java/lang/Object."<init>":()V
const #18 = NameAndType	#4:#5;//  MODULE$:Lscala/reflect/RichClass$;
const #19 = Field	#10.#18;	//  scala/reflect/RichClass$.MODULE$:Lscala/reflect/RichClass$;
const #20 = Asciz	classWrapper;
const #21 = Asciz	(Ljava/lang/Class;)Lscala/reflect/RichClass;;
const #22 = Asciz	scala/reflect/RichClass;
const #23 = class	#22;	//  scala/reflect/RichClass
const #24 = Asciz	(Ljava/lang/Class;)V;
const #25 = NameAndType	#11:#24;//  "<init>":(Ljava/lang/Class;)V
const #26 = Method	#23.#25;	//  scala/reflect/RichClass."<init>":(Ljava/lang/Class;)V
const #27 = Asciz	this;
const #28 = Asciz	x;
const #29 = Asciz	Ljava/lang/Class;;
const #30 = Asciz	LocalVariableTable;
const #31 = Asciz	<T:Ljava/lang/Object;>(Ljava/lang/Class<TT;>;)Lscala/reflect/RichClass<TT;>;;
const #32 = Asciz	Signature;
const #33 = Asciz	InnerClasses;
const #34 = Asciz	scala/reflect/RichClass$ReflectiveCall;
const #35 = class	#34;	//  scala/reflect/RichClass$ReflectiveCall
const #36 = Asciz	ReflectiveCall;
const #37 = Asciz	scala/reflect/RichClass$FailedReflectiveCall;
const #38 = class	#37;	//  scala/reflect/RichClass$FailedReflectiveCall
const #39 = Asciz	FailedReflectiveCall;
const #40 = Asciz	scala/reflect/RichClass$$anonfun$reflectiveCall$1;
const #41 = class	#40;	//  scala/reflect/RichClass$$anonfun$reflectiveCall$1
const #42 = Asciz	$anonfun$reflectiveCall$1;
const #43 = Asciz	scala/reflect/RichClass$$anonfun$getConstructorsTyped$1;
const #44 = class	#43;	//  scala/reflect/RichClass$$anonfun$getConstructorsTyped$1
const #45 = Asciz	$anonfun$getConstructorsTyped$1;
const #46 = Asciz	scala/reflect/RichClass$$anonfun$getDeclaredConstructorsTyped$1;
const #47 = class	#46;	//  scala/reflect/RichClass$$anonfun$getDeclaredConstructorsTyped$1
const #48 = Asciz	$anonfun$getDeclaredConstructorsTyped$1;
const #49 = Asciz	scala/ScalaObject;
const #50 = class	#49;	//  scala/ScalaObject

{
public static final scala.reflect.RichClass$ MODULE$;

public static {};
  Code:
   Stack=1, Locals=0, Args_size=0
   0:	new	#10; //class scala/reflect/RichClass$
   3:	invokespecial	#13; //Method "<init>":()V
   6:	return

public scala.reflect.RichClass classWrapper(java.lang.Class);
  Code:
   Stack=3, Locals=2, Args_size=2
   0:	new	#23; //class scala/reflect/RichClass
   3:	dup
   4:	aload_1
   5:	invokespecial	#26; //Method scala/reflect/RichClass."<init>":(Ljava/lang/Class;)V
   8:	areturn
  LineNumberTable: 
   line 22: 0

  LocalVariableTable: 
   Start  Length  Slot  Name   Signature
   0      9      0    this       Lscala/reflect/RichClass$;
   0      9      1    x       Ljava/lang/Class;

  Signature: length = 0x2
   00 1F 

}

