Compiled from "RichClass.scala"
public final class scala.reflect.RichClass extends java.lang.Object implements scala.Proxy,scala.ScalaObject
  SourceFile: "RichClass.scala"
  Signature: length = 0x2
   00 FFFFFFE2 
  ScalaSig: length = 0x5F2
   05 00 FFFFFF81 4E 07 05 01 02 FFFFFF88 02 07 01 09 52 69 63
   68 43 6C 61 73 73 0A 02 03 04 01 07 72 65 66 6C
   65 63 74 0A 01 05 01 05 73 63 61 6C 61 03 00 10
   02 08 09 0D 01 02 06 08 0A 02 FFFFFF84 FFFFFF80 FFFFFF80 FFFFFF88 02 0B
   02 09 52 69 63 68 43 6C 61 73 73 13 03 09 0C 14
   10 02 0D 12 0D 01 0E 0A 02 0F 10 01 04 6C 61 6E
   67 0A 01 11 01 04 6A 61 76 61 09 02 13 0E 02 06
   4F 62 6A 65 63 74 10 02 15 16 0D 01 04 09 02 17
   04 02 0B 53 63 61 6C 61 4F 62 6A 65 63 74 08 05
   19 09 FFFFFF84 00 1A 01 06 3C 69 6E 69 74 3E 14 01 07
   08 05 1C 09 FFFFFF84 01 1D 01 0C 63 6C 61 73 73 57 72
   61 70 70 65 72 15 03 1E FFFFFF81 4A 14 03 1F FFFFFF81 4B 10
   04 08 20 FFFFFF81 49 06 04 0A 02 02 21 15 02 22 2E 13
   04 20 0C 23 14 10 02 15 24 09 02 25 04 02 05 50
   72 6F 78 79 08 08 27 20 FFFFFF82 FFFFFFC2 FFFFFF80 FFFFFF84 00 28 01 04
   73 65 6C 66 15 01 29 10 03 0D 2A 2C 09 02 2B 0E
   02 05 43 6C 61 73 73 10 02 2D 2E 0C 00 04 08 2F
   20 FFFFFF84 FFFFFF80 FFFFFF80 FFFFFFC2 00 30 02 01 54 11 02 31 34 10 02
   15 32 09 02 33 04 02 07 4E 6F 74 68 69 6E 67 10
   02 15 35 09 02 36 04 02 03 41 6E 79 08 08 38 20
   FFFFFF82 FFFFFF80 FFFFFFA0 FFFFFF80 04 29 01 05 73 65 6C 66 20 08 05 19
   20 FFFFFF84 00 3A 14 02 3B 3C 10 03 08 20 2C 08 05 27
   39 FFFFFFC0 00 29 08 05 3E 20 FFFFFF84 00 3F 01 14 67 65 74
   43 6F 6E 73 74 72 75 63 74 6F 72 73 54 79 70 65
   64 14 01 40 10 03 15 41 43 09 02 42 04 02 05 41
   72 72 61 79 10 03 44 46 2C 0D 01 45 0A 02 03 0E
   09 02 47 45 02 0B 43 6F 6E 73 74 72 75 63 74 6F
   72 08 05 49 20 FFFFFF84 00 3F 01 1C 67 65 74 44 65 63
   6C 61 72 65 64 43 6F 6E 73 74 72 75 63 74 6F 72
   73 54 79 70 65 64 08 08 4B 20 FFFFFF88 FFFFFFC2 FFFFFF80 FFFFFF84 04 4C
   01 0B 63 6C 61 73 73 4C 6F 61 64 65 72 15 01 4D
   10 02 0D 4E 09 02 4F 0E 02 0B 43 6C 61 73 73 4C
   6F 61 64 65 72 08 08 51 20 FFFFFF88 FFFFFF80 FFFFFFA0 FFFFFFA0 04 4D 01
   0C 63 6C 61 73 73 4C 6F 61 64 65 72 20 08 07 53
   20 FFFFFFC2 FFFFFF80 FFFFFF84 04 54 01 0A 65 78 63 65 70 74 69 6F
   6E 73 15 01 55 10 03 56 5B 5D 0D 01 57 0A 02 58
   59 01 09 69 6D 6D 75 74 61 62 6C 65 0A 02 5A 04
   01 0A 63 6F 6C 6C 65 63 74 69 6F 6E 09 02 5C 57
   02 04 4C 69 73 74 30 02 5E 60 10 03 0D 2A 5F 10
   02 2D 60 04 08 61 00 FFFFFF84 FFFFFF80 FFFFFF80 FFFFFF82 00 62 02 04 5F
   31 30 35 11 02 63 79 12 06 64 66 6D 70 73 76 06
   08 65 06 FFFFFF84 FFFFFF80 FFFFFF80 FFFFFF80 00 63 02 0C 3C 72 65 66 69
   6E 65 6D 65 6E 74 3E 10 02 67 6A 0E 02 15 68 09
   02 69 04 01 06 50 72 65 64 65 66 09 02 6B 6C 02
   12 43 6C 61 73 73 43 61 73 74 45 78 63 65 70 74
   69 6F 6E 0A 02 69 04 10 02 67 6E 09 02 6F 6C 02
   14 4E 75 6C 6C 50 6F 69 6E 74 65 72 45 78 63 65
   70 74 69 6F 6E 10 02 0D 71 09 02 72 0E 02 11 53
   65 63 75 72 69 74 79 45 78 63 65 70 74 69 6F 6E
   10 02 0D 74 09 02 75 0E 02 15 4E 6F 53 75 63 68
   4D 65 74 68 6F 64 45 78 63 65 70 74 69 6F 6E 10
   02 0D 77 09 02 78 0E 02 16 43 6C 61 73 73 4E 6F
   74 46 6F 75 6E 64 45 78 63 65 70 74 69 6F 6E 10
   02 0D 7A 09 02 7B 0E 02 09 45 78 63 65 70 74 69
   6F 6E 08 06 7D 20 FFFFFFA0 FFFFFF80 04 55 01 0B 65 78 63 65
   70 74 69 6F 6E 73 20 06 05 7F 20 00 FFFFFF81 00 02 0E
   52 65 66 6C 65 63 74 69 76 65 43 61 6C 6C 15 04
   FFFFFF81 01 FFFFFF81 0E 13 03 7E 0C 14 08 09 FFFFFF81 03 7E FFFFFF82 FFFFFF80
   FFFFFFA0 FFFFFF80 04 2C 01 03 6F 62 6A 08 0A FFFFFF81 05 7E FFFFFF82 FFFFFF80
   FFFFFFA0 FFFFFF80 04 FFFFFF81 06 01 04 6E 61 6D 65 10 03 67 FFFFFF81 07
   09 03 FFFFFF81 08 6C 02 06 53 74 72 69 6E 67 08 06 19
   7E FFFFFF84 00 FFFFFF81 0A 14 06 FFFFFF81 0B FFFFFF81 10 FFFFFF81 11 10 05 FFFFFF81
   0C 7E FFFFFF81 0D 0D 01 20 10 03 2D FFFFFF81 0E 04 09 FFFFFF81 0F
   7E FFFFFF84 FFFFFF80 FFFFFF84 FFFFFFC2 00 30 02 01 55 08 07 FFFFFF81 03 FFFFFF81 09
   FFFFFFC0 00 2C 08 08 FFFFFF81 05 FFFFFF81 09 FFFFFFC0 00 FFFFFF81 06 08 07 FFFFFF81
   13 7E FFFFFF84 00 FFFFFF81 14 01 0D 6D 65 74 68 6F 64 46 6F
   72 41 72 67 73 14 04 FFFFFF81 15 FFFFFF81 18 10 03 44 FFFFFF81 16
   09 03 FFFFFF81 17 45 02 06 4D 65 74 68 6F 64 08 08 FFFFFF81
   19 FFFFFF81 12 FFFFFFC0 00 FFFFFF81 1A 01 04 61 72 67 73 10 05 15
   FFFFFF81 1B FFFFFF81 1D 09 03 FFFFFF81 1C 04 02 0A 3C 72 65 70 65
   61 74 65 64 3E 10 03 15 FFFFFF81 1E 09 03 FFFFFF81 1F 04 02
   06 41 6E 79 52 65 66 08 07 FFFFFF81 21 7E FFFFFF84 00 FFFFFF81 22
   01 0B 69 73 45 72 72 6F 6E 65 6F 75 73 15 02 FFFFFF81
   23 10 03 15 FFFFFF81 24 09 03 FFFFFF81 25 04 02 07 42 6F 6F
   6C 65 61 6E 08 07 FFFFFF81 27 7E FFFFFF84 00 FFFFFF81 28 01 05 61
   70 70 6C 79 14 04 FFFFFF81 0D FFFFFF81 29 08 08 FFFFFF81 19 FFFFFF81 26
   FFFFFFC0 00 FFFFFF81 2A 10 04 15 FFFFFF81 1B 34 06 06 FFFFFF81 2C 20 00
   FFFFFF81 2D 02 14 46 61 69 6C 65 64 52 65 66 6C 65 63
   74 69 76 65 43 61 6C 6C 15 04 FFFFFF81 2E FFFFFF81 31 13 05
   FFFFFF81 2B FFFFFF81 2F 14 10 05 FFFFFF81 0C 7E FFFFFF81 30 10 03 2D FFFFFF81
   31 04 0A FFFFFF81 0F FFFFFF81 2B FFFFFF84 FFFFFF80 FFFFFF84 FFFFFFC2 00 30 08 0B FFFFFF81
   33 FFFFFF81 2B FFFFFF82 FFFFFF80 FFFFFFA0 FFFFFF80 04 FFFFFF81 34 01 02 65 78 10 03
   67 FFFFFF81 35 09 03 FFFFFF81 36 6C 02 09 54 68 72 6F 77 61
   62 6C 65 08 07 19 FFFFFF81 2B FFFFFF84 00 FFFFFF81 38 14 04 FFFFFF81 39
   FFFFFF81 3A 10 06 FFFFFF81 0C FFFFFF81 2B FFFFFF81 30 08 08 FFFFFF81 33 FFFFFF81 37
   FFFFFFC0 00 FFFFFF81 34 08 08 FFFFFF81 21 FFFFFF81 2B FFFFFF84 20 FFFFFF81 22 08 08
   FFFFFF81 27 FFFFFF81 2B FFFFFF84 20 FFFFFF81 3D 14 03 31 FFFFFF81 3E 08 08 FFFFFF81
   19 FFFFFF81 3C FFFFFFC0 00 FFFFFF81 2A 08 07 FFFFFF81 40 20 FFFFFF84 00 FFFFFF81 41
   01 0E 72 65 66 6C 65 63 74 69 76 65 43 61 6C 6C
   15 04 FFFFFF81 42 FFFFFF81 45 14 06 FFFFFF81 43 FFFFFF81 46 FFFFFF81 47 10 05
   FFFFFF81 0C 7E FFFFFF81 44 10 03 2D FFFFFF81 45 04 0A FFFFFF81 0F FFFFFF81 3F
   FFFFFF84 FFFFFF80 FFFFFF80 FFFFFFC2 00 30 08 07 FFFFFF81 03 FFFFFF81 3F FFFFFFC0 00 2C 08
   08 FFFFFF81 48 FFFFFF81 3F FFFFFFC0 00 FFFFFF81 06 01 06 6D 65 74 68 6F
   64 10 03 2D FFFFFF81 4A 04 08 2F 1B FFFFFF84 FFFFFF80 FFFFFF80 FFFFFFC2 00 30
   08 07 FFFFFF81 4C 1B FFFFFFC0 00 FFFFFF81 4D 01 01 78 10 04 0D 2A
   FFFFFF81 49 
  InnerClass: 
   public #231= #94 of #230; //Catch=class scala/util/control/Exception$Catch of class scala/util/control/Exception
   public #232= #117 of #19; //ReflectiveCall=class scala/reflect/RichClass$ReflectiveCall of class scala/reflect/RichClass
   public #233= #107 of #19; //FailedReflectiveCall=class scala/reflect/RichClass$FailedReflectiveCall of class scala/reflect/RichClass
   public final #234= #89 of #19; //$anonfun$reflectiveCall$1=class scala/reflect/RichClass$$anonfun$reflectiveCall$1 of class scala/reflect/RichClass
   public final #235= #209 of #19; //$anonfun$getConstructorsTyped$1=class scala/reflect/RichClass$$anonfun$getConstructorsTyped$1 of class scala/reflect/RichClass
   public final #236= #174 of #19; //$anonfun$getDeclaredConstructorsTyped$1=class scala/reflect/RichClass$$anonfun$getDeclaredConstructorsTyped$1 of class scala/reflect/RichClass
  minor version: 0
  major version: 49
  Constant pool:
const #1 = Asciz	SourceFile;
const #2 = Asciz	RichClass.scala;
const #3 = Asciz	bitmap$0;
const #4 = Asciz	I;
const #5 = Asciz	exceptions;
const #6 = Asciz	Lscala/collection/immutable/List;;
const #7 = Asciz	Lscala/collection/immutable/List<Ljava/lang/Class<+Ljava/lang/Exception;>;>;;
const #8 = Asciz	Signature;
const #9 = Asciz	classLoader;
const #10 = Asciz	Ljava/lang/ClassLoader;;
const #11 = Asciz	self;
const #12 = Asciz	Ljava/lang/Class;;
const #13 = Asciz	Ljava/lang/Class<TT;>;;
const #14 = Asciz	<init>;
const #15 = Asciz	(Ljava/lang/Class;)V;
const #16 = Asciz	Code;
const #17 = Asciz	LineNumberTable;
const #18 = Asciz	scala/reflect/RichClass;
const #19 = class	#18;	//  scala/reflect/RichClass
const #20 = NameAndType	#11:#12;//  self:Ljava/lang/Class;
const #21 = Field	#19.#20;	//  scala/reflect/RichClass.self:Ljava/lang/Class;
const #22 = Asciz	java/lang/Object;
const #23 = class	#22;	//  java/lang/Object
const #24 = Asciz	()V;
const #25 = NameAndType	#14:#24;//  "<init>":()V
const #26 = Method	#23.#25;	//  java/lang/Object."<init>":()V
const #27 = Asciz	scala/Proxy$class;
const #28 = class	#27;	//  scala/Proxy$class
const #29 = Asciz	$init$;
const #30 = Asciz	(Lscala/Proxy;)V;
const #31 = NameAndType	#29:#30;//  $init$:(Lscala/Proxy;)V
const #32 = Method	#28.#31;	//  scala/Proxy$class.$init$:(Lscala/Proxy;)V
const #33 = Asciz	scala/collection/immutable/List$;
const #34 = class	#33;	//  scala/collection/immutable/List$
const #35 = Asciz	MODULE$;
const #36 = Asciz	Lscala/collection/immutable/List$;;
const #37 = NameAndType	#35:#36;//  MODULE$:Lscala/collection/immutable/List$;
const #38 = Field	#34.#37;	//  scala/collection/immutable/List$.MODULE$:Lscala/collection/immutable/List$;
const #39 = Asciz	scala/runtime/ScalaRunTime$;
const #40 = class	#39;	//  scala/runtime/ScalaRunTime$
const #41 = Asciz	Lscala/runtime/ScalaRunTime$;;
const #42 = NameAndType	#35:#41;//  MODULE$:Lscala/runtime/ScalaRunTime$;
const #43 = Field	#40.#42;	//  scala/runtime/ScalaRunTime$.MODULE$:Lscala/runtime/ScalaRunTime$;
const #44 = Asciz	java/lang/Class;
const #45 = class	#44;	//  java/lang/Class
const #46 = Asciz	java/lang/ClassNotFoundException;
const #47 = class	#46;	//  java/lang/ClassNotFoundException
const #48 = Asciz	java/lang/NoSuchMethodException;
const #49 = class	#48;	//  java/lang/NoSuchMethodException
const #50 = Asciz	java/lang/SecurityException;
const #51 = class	#50;	//  java/lang/SecurityException
const #52 = Asciz	java/lang/NullPointerException;
const #53 = class	#52;	//  java/lang/NullPointerException
const #54 = Asciz	java/lang/ClassCastException;
const #55 = class	#54;	//  java/lang/ClassCastException
const #56 = Asciz	boxArray;
const #57 = Asciz	(Ljava/lang/Object;)Lscala/runtime/BoxedArray;;
const #58 = NameAndType	#56:#57;//  boxArray:(Ljava/lang/Object;)Lscala/runtime/BoxedArray;
const #59 = Method	#40.#58;	//  scala/runtime/ScalaRunTime$.boxArray:(Ljava/lang/Object;)Lscala/runtime/BoxedArray;
const #60 = Asciz	apply;
const #61 = Asciz	(Lscala/collection/Sequence;)Lscala/collection/immutable/List;;
const #62 = NameAndType	#60:#61;//  apply:(Lscala/collection/Sequence;)Lscala/collection/immutable/List;
const #63 = Method	#34.#62;	//  scala/collection/immutable/List$.apply:(Lscala/collection/Sequence;)Lscala/collection/immutable/List;
const #64 = NameAndType	#5:#6;//  exceptions:Lscala/collection/immutable/List;
const #65 = Field	#19.#64;	//  scala/reflect/RichClass.exceptions:Lscala/collection/immutable/List;
const #66 = Asciz	this;
const #67 = Asciz	Lscala/reflect/RichClass;;
const #68 = Asciz	LocalVariableTable;
const #69 = Asciz	(Ljava/lang/Class<TT;>;)V;
const #70 = Asciz	()Ljava/lang/Object;;
const #71 = Asciz	()Ljava/lang/Class;;
const #72 = NameAndType	#11:#71;//  self:()Ljava/lang/Class;
const #73 = Method	#19.#72;	//  scala/reflect/RichClass.self:()Ljava/lang/Class;
const #74 = Asciz	reflectiveCall;
const #75 = Asciz	(Ljava/lang/Object;Ljava/lang/String;)Lscala/reflect/RichClass$ReflectiveCall;;
const #76 = Asciz	scala/util/control/Exception$;
const #77 = class	#76;	//  scala/util/control/Exception$
const #78 = Asciz	Lscala/util/control/Exception$;;
const #79 = NameAndType	#35:#78;//  MODULE$:Lscala/util/control/Exception$;
const #80 = Field	#77.#79;	//  scala/util/control/Exception$.MODULE$:Lscala/util/control/Exception$;
const #81 = Asciz	()Lscala/collection/immutable/List;;
const #82 = NameAndType	#5:#81;//  exceptions:()Lscala/collection/immutable/List;
const #83 = Method	#19.#82;	//  scala/reflect/RichClass.exceptions:()Lscala/collection/immutable/List;
const #84 = Asciz	catching;
const #85 = Asciz	(Lscala/collection/Sequence;)Lscala/util/control/Exception$Catch;;
const #86 = NameAndType	#84:#85;//  catching:(Lscala/collection/Sequence;)Lscala/util/control/Exception$Catch;
const #87 = Method	#77.#86;	//  scala/util/control/Exception$.catching:(Lscala/collection/Sequence;)Lscala/util/control/Exception$Catch;
const #88 = Asciz	scala/reflect/RichClass$$anonfun$reflectiveCall$1;
const #89 = class	#88;	//  scala/reflect/RichClass$$anonfun$reflectiveCall$1
const #90 = Asciz	(Lscala/reflect/RichClass;Ljava/lang/Object;Ljava/lang/String;)V;
const #91 = NameAndType	#14:#90;//  "<init>":(Lscala/reflect/RichClass;Ljava/lang/Object;Ljava/lang/String;)V
const #92 = Method	#89.#91;	//  scala/reflect/RichClass$$anonfun$reflectiveCall$1."<init>":(Lscala/reflect/RichClass;Ljava/lang/Object;Ljava/lang/String;)V
const #93 = Asciz	scala/util/control/Exception$Catch;
const #94 = class	#93;	//  scala/util/control/Exception$Catch
const #95 = Asciz	either;
const #96 = Asciz	(Lscala/Function0;)Lscala/Either;;
const #97 = NameAndType	#95:#96;//  either:(Lscala/Function0;)Lscala/Either;
const #98 = Method	#94.#97;	//  scala/util/control/Exception$Catch.either:(Lscala/Function0;)Lscala/Either;
const #99 = Asciz	scala/Left;
const #100 = class	#99;	//  scala/Left
const #101 = Asciz	a;
const #102 = NameAndType	#101:#70;//  a:()Ljava/lang/Object;
const #103 = Method	#100.#102;	//  scala/Left.a:()Ljava/lang/Object;
const #104 = Asciz	java/lang/Throwable;
const #105 = class	#104;	//  java/lang/Throwable
const #106 = Asciz	scala/reflect/RichClass$FailedReflectiveCall;
const #107 = class	#106;	//  scala/reflect/RichClass$FailedReflectiveCall
const #108 = Asciz	(Lscala/reflect/RichClass;Ljava/lang/Throwable;)V;
const #109 = NameAndType	#14:#108;//  "<init>":(Lscala/reflect/RichClass;Ljava/lang/Throwable;)V
const #110 = Method	#107.#109;	//  scala/reflect/RichClass$FailedReflectiveCall."<init>":(Lscala/reflect/RichClass;Ljava/lang/Throwable;)V
const #111 = Asciz	scala/Right;
const #112 = class	#111;	//  scala/Right
const #113 = Asciz	b;
const #114 = NameAndType	#113:#70;//  b:()Ljava/lang/Object;
const #115 = Method	#112.#114;	//  scala/Right.b:()Ljava/lang/Object;
const #116 = Asciz	scala/reflect/RichClass$ReflectiveCall;
const #117 = class	#116;	//  scala/reflect/RichClass$ReflectiveCall
const #118 = Asciz	scala/MatchError;
const #119 = class	#118;	//  scala/MatchError
const #120 = Asciz	scala/Either;
const #121 = class	#120;	//  scala/Either
const #122 = Asciz	toString;
const #123 = Asciz	()Ljava/lang/String;;
const #124 = NameAndType	#122:#123;//  toString:()Ljava/lang/String;
const #125 = Method	#121.#124;	//  scala/Either.toString:()Ljava/lang/String;
const #126 = Asciz	(Ljava/lang/String;)V;
const #127 = NameAndType	#14:#126;//  "<init>":(Ljava/lang/String;)V
const #128 = Method	#119.#127;	//  scala/MatchError."<init>":(Ljava/lang/String;)V
const #129 = Asciz	obj$1;
const #130 = Asciz	Ljava/lang/Object;;
const #131 = Asciz	method$1;
const #132 = Asciz	Ljava/lang/String;;
const #133 = Asciz	temp3;
const #134 = Asciz	Lscala/Either;;
const #135 = Asciz	temp4;
const #136 = Asciz	Lscala/Left;;
const #137 = Asciz	temp5;
const #138 = Asciz	Ljava/lang/Throwable;;
const #139 = Asciz	temp6;
const #140 = Asciz	Lscala/Right;;
const #141 = Asciz	temp7;
const #142 = Asciz	Lscala/reflect/RichClass$ReflectiveCall;;
const #143 = Asciz	<U:Ljava/lang/Object;>(TT;Ljava/lang/String;)Lscala/reflect/RichClass<TT;>.ReflectiveCall<TU;>;;
const #144 = Asciz	()Lscala/collection/immutable/List<Ljava/lang/Class<+Ljava/lang/Exception;>;>;;
const #145 = Asciz	()Ljava/lang/ClassLoader;;
const #146 = NameAndType	#3:#4;//  bitmap$0:I
const #147 = Field	#19.#146;	//  scala/reflect/RichClass.bitmap$0:I
const #148 = Asciz	getClassLoader;
const #149 = NameAndType	#148:#145;//  getClassLoader:()Ljava/lang/ClassLoader;
const #150 = Method	#45.#149;	//  java/lang/Class.getClassLoader:()Ljava/lang/ClassLoader;
const #151 = Asciz	scala/util/ScalaClassLoader$;
const #152 = class	#151;	//  scala/util/ScalaClassLoader$
const #153 = Asciz	Lscala/util/ScalaClassLoader$;;
const #154 = NameAndType	#35:#153;//  MODULE$:Lscala/util/ScalaClassLoader$;
const #155 = Field	#152.#154;	//  scala/util/ScalaClassLoader$.MODULE$:Lscala/util/ScalaClassLoader$;
const #156 = Asciz	getSystemLoader;
const #157 = NameAndType	#156:#145;//  getSystemLoader:()Ljava/lang/ClassLoader;
const #158 = Method	#152.#157;	//  scala/util/ScalaClassLoader$.getSystemLoader:()Ljava/lang/ClassLoader;
const #159 = NameAndType	#9:#10;//  classLoader:Ljava/lang/ClassLoader;
const #160 = Field	#19.#159;	//  scala/reflect/RichClass.classLoader:Ljava/lang/ClassLoader;
const #161 = Asciz	scala/runtime/BoxedUnit;
const #162 = class	#161;	//  scala/runtime/BoxedUnit
const #163 = Asciz	UNIT;
const #164 = Asciz	Lscala/runtime/BoxedUnit;;
const #165 = NameAndType	#163:#164;//  UNIT:Lscala/runtime/BoxedUnit;
const #166 = Field	#162.#165;	//  scala/runtime/BoxedUnit.UNIT:Lscala/runtime/BoxedUnit;
const #167 = Asciz	temp1;
const #168 = Asciz	getDeclaredConstructorsTyped;
const #169 = Asciz	()[Ljava/lang/reflect/Constructor;;
const #170 = Asciz	getDeclaredConstructors;
const #171 = NameAndType	#170:#169;//  getDeclaredConstructors:()[Ljava/lang/reflect/Constructor;
const #172 = Method	#45.#171;	//  java/lang/Class.getDeclaredConstructors:()[Ljava/lang/reflect/Constructor;
const #173 = Asciz	scala/reflect/RichClass$$anonfun$getDeclaredConstructorsTyped$1;
const #174 = class	#173;	//  scala/reflect/RichClass$$anonfun$getDeclaredConstructorsTyped$1
const #175 = Asciz	(Lscala/reflect/RichClass;)V;
const #176 = NameAndType	#14:#175;//  "<init>":(Lscala/reflect/RichClass;)V
const #177 = Method	#174.#176;	//  scala/reflect/RichClass$$anonfun$getDeclaredConstructorsTyped$1."<init>":(Lscala/reflect/RichClass;)V
const #178 = Asciz	scala/Array$;
const #179 = class	#178;	//  scala/Array$
const #180 = Asciz	Lscala/Array$;;
const #181 = NameAndType	#35:#180;//  MODULE$:Lscala/Array$;
const #182 = Field	#179.#181;	//  scala/Array$.MODULE$:Lscala/Array$;
const #183 = Asciz	builderFactory;
const #184 = Asciz	()Lscala/collection/generic/BuilderFactory;;
const #185 = NameAndType	#183:#184;//  builderFactory:()Lscala/collection/generic/BuilderFactory;
const #186 = Method	#179.#185;	//  scala/Array$.builderFactory:()Lscala/collection/generic/BuilderFactory;
const #187 = Asciz	scala/collection/generic/TraversableTemplate;
const #188 = class	#187;	//  scala/collection/generic/TraversableTemplate
const #189 = Asciz	map;
const #190 = Asciz	(Lscala/Function1;Lscala/collection/generic/BuilderFactory;)Ljava/lang/Object;;
const #191 = NameAndType	#189:#190;//  map:(Lscala/Function1;Lscala/collection/generic/BuilderFactory;)Ljava/lang/Object;
const #192 = InterfaceMethod	#188.#191;	//  scala/collection/generic/TraversableTemplate.map:(Lscala/Function1;Lscala/collection/generic/BuilderFactory;)Ljava/lang/Object;
const #193 = Asciz	scala/runtime/BoxedArray;
const #194 = class	#193;	//  scala/runtime/BoxedArray
const #195 = Asciz	java/lang/reflect/Constructor;
const #196 = class	#195;	//  java/lang/reflect/Constructor
const #197 = Asciz	arrayValue;
const #198 = Asciz	(Lscala/runtime/BoxedArray;Ljava/lang/Class;)Ljava/lang/Object;;
const #199 = NameAndType	#197:#198;//  arrayValue:(Lscala/runtime/BoxedArray;Ljava/lang/Class;)Ljava/lang/Object;
const #200 = Method	#40.#199;	//  scala/runtime/ScalaRunTime$.arrayValue:(Lscala/runtime/BoxedArray;Ljava/lang/Class;)Ljava/lang/Object;
const #201 = Asciz	[Ljava/lang/reflect/Constructor;;
const #202 = class	#201;	//  "[Ljava/lang/reflect/Constructor;"
const #203 = Asciz	()[Ljava/lang/reflect/Constructor<TT;>;;
const #204 = Asciz	getConstructorsTyped;
const #205 = Asciz	getConstructors;
const #206 = NameAndType	#205:#169;//  getConstructors:()[Ljava/lang/reflect/Constructor;
const #207 = Method	#45.#206;	//  java/lang/Class.getConstructors:()[Ljava/lang/reflect/Constructor;
const #208 = Asciz	scala/reflect/RichClass$$anonfun$getConstructorsTyped$1;
const #209 = class	#208;	//  scala/reflect/RichClass$$anonfun$getConstructorsTyped$1
const #210 = Method	#209.#176;	//  scala/reflect/RichClass$$anonfun$getConstructorsTyped$1."<init>":(Lscala/reflect/RichClass;)V
const #211 = Asciz	()Ljava/lang/Class<TT;>;;
const #212 = Asciz	(Lscala/Proxy;)Ljava/lang/String;;
const #213 = NameAndType	#122:#212;//  toString:(Lscala/Proxy;)Ljava/lang/String;
const #214 = Method	#28.#213;	//  scala/Proxy$class.toString:(Lscala/Proxy;)Ljava/lang/String;
const #215 = Asciz	equals;
const #216 = Asciz	(Ljava/lang/Object;)Z;
const #217 = Asciz	(Lscala/Proxy;Ljava/lang/Object;)Z;
const #218 = NameAndType	#215:#217;//  equals:(Lscala/Proxy;Ljava/lang/Object;)Z
const #219 = Method	#28.#218;	//  scala/Proxy$class.equals:(Lscala/Proxy;Ljava/lang/Object;)Z
const #220 = Asciz	that;
const #221 = Asciz	hashCode;
const #222 = Asciz	()I;
const #223 = Asciz	(Lscala/Proxy;)I;
const #224 = NameAndType	#221:#223;//  hashCode:(Lscala/Proxy;)I
const #225 = Method	#28.#224;	//  scala/Proxy$class.hashCode:(Lscala/Proxy;)I
const #226 = Asciz	<T:Ljava/lang/Object;>Ljava/lang/Object;Lscala/Proxy;Lscala/ScalaObject;;
const #227 = Asciz	ScalaSig;
const #228 = Asciz	InnerClasses;
const #229 = Asciz	scala/util/control/Exception;
const #230 = class	#229;	//  scala/util/control/Exception
const #231 = Asciz	Catch;
const #232 = Asciz	ReflectiveCall;
const #233 = Asciz	FailedReflectiveCall;
const #234 = Asciz	$anonfun$reflectiveCall$1;
const #235 = Asciz	$anonfun$getConstructorsTyped$1;
const #236 = Asciz	$anonfun$getDeclaredConstructorsTyped$1;
const #237 = Asciz	scala/Proxy;
const #238 = class	#237;	//  scala/Proxy
const #239 = Asciz	scala/ScalaObject;
const #240 = class	#239;	//  scala/ScalaObject

{
public volatile int bitmap$0;

public scala.reflect.RichClass(java.lang.Class);
  Code:
   Stack=7, Locals=2, Args_size=2
   0:	aload_0
   1:	aload_1
   2:	putfield	#21; //Field self:Ljava/lang/Class;
   5:	aload_0
   6:	invokespecial	#26; //Method java/lang/Object."<init>":()V
   9:	aload_0
   10:	invokestatic	#32; //Method scala/Proxy$class.$init$:(Lscala/Proxy;)V
   13:	aload_0
   14:	getstatic	#38; //Field scala/collection/immutable/List$.MODULE$:Lscala/collection/immutable/List$;
   17:	getstatic	#43; //Field scala/runtime/ScalaRunTime$.MODULE$:Lscala/runtime/ScalaRunTime$;
   20:	iconst_5
   21:	anewarray	#45; //class java/lang/Class
   24:	dup
   25:	iconst_0
   26:	ldc	#47; //class java/lang/ClassNotFoundException
   28:	aastore
   29:	dup
   30:	iconst_1
   31:	ldc	#49; //class java/lang/NoSuchMethodException
   33:	aastore
   34:	dup
   35:	iconst_2
   36:	ldc	#51; //class java/lang/SecurityException
   38:	aastore
   39:	dup
   40:	iconst_3
   41:	ldc	#53; //class java/lang/NullPointerException
   43:	aastore
   44:	dup
   45:	iconst_4
   46:	ldc	#55; //class java/lang/ClassCastException
   48:	aastore
   49:	invokevirtual	#59; //Method scala/runtime/ScalaRunTime$.boxArray:(Ljava/lang/Object;)Lscala/runtime/BoxedArray;
   52:	invokevirtual	#63; //Method scala/collection/immutable/List$.apply:(Lscala/collection/Sequence;)Lscala/collection/immutable/List;
   55:	putfield	#65; //Field exceptions:Lscala/collection/immutable/List;
   58:	return
  LineNumberTable: 
   line 25: 0
   line 53: 13
   line 54: 26
   line 53: 29
   line 55: 31
   line 53: 34
   line 56: 36
   line 53: 39
   line 57: 41
   line 53: 44
   line 58: 46
   line 53: 49

  LocalVariableTable: 
   Start  Length  Slot  Name   Signature
   0      59      0    this       Lscala/reflect/RichClass;
   0      59      1    self       Ljava/lang/Class;

  Signature: length = 0x2
   00 45 

public java.lang.Object self();
  Code:
   Stack=1, Locals=1, Args_size=1
   0:	aload_0
   1:	invokevirtual	#73; //Method self:()Ljava/lang/Class;
   4:	areturn
  LineNumberTable: 
   line 25: 0


public scala.reflect.RichClass$ReflectiveCall reflectiveCall(java.lang.Object, java.lang.String);
  Code:
   Stack=6, Locals=8, Args_size=3
   0:	getstatic	#80; //Field scala/util/control/Exception$.MODULE$:Lscala/util/control/Exception$;
   3:	aload_0
   4:	invokespecial	#83; //Method exceptions:()Lscala/collection/immutable/List;
   7:	invokevirtual	#87; //Method scala/util/control/Exception$.catching:(Lscala/collection/Sequence;)Lscala/util/control/Exception$Catch;
   10:	new	#89; //class scala/reflect/RichClass$$anonfun$reflectiveCall$1
   13:	dup
   14:	aload_0
   15:	aload_1
   16:	aload_2
   17:	invokespecial	#92; //Method scala/reflect/RichClass$$anonfun$reflectiveCall$1."<init>":(Lscala/reflect/RichClass;Ljava/lang/Object;Ljava/lang/String;)V
   20:	invokevirtual	#98; //Method scala/util/control/Exception$Catch.either:(Lscala/Function0;)Lscala/Either;
   23:	astore_3
   24:	aload_3
   25:	instanceof	#100; //class scala/Left
   28:	ifeq	60
   31:	aload_3
   32:	checkcast	#100; //class scala/Left
   35:	astore	4
   37:	aload	4
   39:	invokevirtual	#103; //Method scala/Left.a:()Ljava/lang/Object;
   42:	checkcast	#105; //class java/lang/Throwable
   45:	astore	5
   47:	new	#107; //class scala/reflect/RichClass$FailedReflectiveCall
   50:	dup
   51:	aload_0
   52:	aload	5
   54:	invokespecial	#110; //Method scala/reflect/RichClass$FailedReflectiveCall."<init>":(Lscala/reflect/RichClass;Ljava/lang/Throwable;)V
   57:	goto	85
   60:	aload_3
   61:	instanceof	#112; //class scala/Right
   64:	ifeq	86
   67:	aload_3
   68:	checkcast	#112; //class scala/Right
   71:	astore	6
   73:	aload	6
   75:	invokevirtual	#115; //Method scala/Right.b:()Ljava/lang/Object;
   78:	checkcast	#117; //class scala/reflect/RichClass$ReflectiveCall
   81:	astore	7
   83:	aload	7
   85:	areturn
   86:	new	#119; //class scala/MatchError
   89:	dup
   90:	aload_3
   91:	invokevirtual	#125; //Method scala/Either.toString:()Ljava/lang/String;
   94:	invokespecial	#128; //Method scala/MatchError."<init>":(Ljava/lang/String;)V
   97:	athrow
  LineNumberTable: 
   line 85: 0
   line 86: 47
   line 85: 60
   line 87: 83
   line 85: 85

  LocalVariableTable: 
   Start  Length  Slot  Name   Signature
   0      98      0    this       Lscala/reflect/RichClass;
   0      98      1    obj$1       Ljava/lang/Object;
   0      98      2    method$1       Ljava/lang/String;
   24      74      3    temp3       Lscala/Either;
   37      20      4    temp4       Lscala/Left;
   47      10      5    temp5       Ljava/lang/Throwable;
   73      12      6    temp6       Lscala/Right;
   83      2      7    temp7       Lscala/reflect/RichClass$ReflectiveCall;

  Signature: length = 0x2
   00 FFFFFF8F 

public java.lang.reflect.Constructor[] getDeclaredConstructorsTyped();
  Code:
   Stack=4, Locals=2, Args_size=1
   0:	getstatic	#43; //Field scala/runtime/ScalaRunTime$.MODULE$:Lscala/runtime/ScalaRunTime$;
   3:	aload_0
   4:	invokevirtual	#73; //Method self:()Ljava/lang/Class;
   7:	invokevirtual	#172; //Method java/lang/Class.getDeclaredConstructors:()[Ljava/lang/reflect/Constructor;
   10:	invokevirtual	#59; //Method scala/runtime/ScalaRunTime$.boxArray:(Ljava/lang/Object;)Lscala/runtime/BoxedArray;
   13:	new	#174; //class scala/reflect/RichClass$$anonfun$getDeclaredConstructorsTyped$1
   16:	dup
   17:	aload_0
   18:	invokespecial	#177; //Method scala/reflect/RichClass$$anonfun$getDeclaredConstructorsTyped$1."<init>":(Lscala/reflect/RichClass;)V
   21:	getstatic	#182; //Field scala/Array$.MODULE$:Lscala/Array$;
   24:	invokevirtual	#186; //Method scala/Array$.builderFactory:()Lscala/collection/generic/BuilderFactory;
   27:	invokeinterface	#192,  3; //InterfaceMethod scala/collection/generic/TraversableTemplate.map:(Lscala/Function1;Lscala/collection/generic/BuilderFactory;)Ljava/lang/Object;
   32:	astore_1
   33:	aload_1
   34:	instanceof	#194; //class scala/runtime/BoxedArray
   37:	ifeq	55
   40:	getstatic	#43; //Field scala/runtime/ScalaRunTime$.MODULE$:Lscala/runtime/ScalaRunTime$;
   43:	aload_1
   44:	checkcast	#194; //class scala/runtime/BoxedArray
   47:	ldc	#196; //class java/lang/reflect/Constructor
   49:	invokevirtual	#200; //Method scala/runtime/ScalaRunTime$.arrayValue:(Lscala/runtime/BoxedArray;Ljava/lang/Class;)Ljava/lang/Object;
   52:	goto	56
   55:	aload_1
   56:	checkcast	#202; //class "[Ljava/lang/reflect/Constructor;"
   59:	areturn
  LineNumberTable: 
   line 47: 0

  Signature: length = 0x2
   00 FFFFFFCB 

public java.lang.reflect.Constructor[] getConstructorsTyped();
  Code:
   Stack=4, Locals=2, Args_size=1
   0:	getstatic	#43; //Field scala/runtime/ScalaRunTime$.MODULE$:Lscala/runtime/ScalaRunTime$;
   3:	aload_0
   4:	invokevirtual	#73; //Method self:()Ljava/lang/Class;
   7:	invokevirtual	#207; //Method java/lang/Class.getConstructors:()[Ljava/lang/reflect/Constructor;
   10:	invokevirtual	#59; //Method scala/runtime/ScalaRunTime$.boxArray:(Ljava/lang/Object;)Lscala/runtime/BoxedArray;
   13:	new	#209; //class scala/reflect/RichClass$$anonfun$getConstructorsTyped$1
   16:	dup
   17:	aload_0
   18:	invokespecial	#210; //Method scala/reflect/RichClass$$anonfun$getConstructorsTyped$1."<init>":(Lscala/reflect/RichClass;)V
   21:	getstatic	#182; //Field scala/Array$.MODULE$:Lscala/Array$;
   24:	invokevirtual	#186; //Method scala/Array$.builderFactory:()Lscala/collection/generic/BuilderFactory;
   27:	invokeinterface	#192,  3; //InterfaceMethod scala/collection/generic/TraversableTemplate.map:(Lscala/Function1;Lscala/collection/generic/BuilderFactory;)Ljava/lang/Object;
   32:	astore_1
   33:	aload_1
   34:	instanceof	#194; //class scala/runtime/BoxedArray
   37:	ifeq	55
   40:	getstatic	#43; //Field scala/runtime/ScalaRunTime$.MODULE$:Lscala/runtime/ScalaRunTime$;
   43:	aload_1
   44:	checkcast	#194; //class scala/runtime/BoxedArray
   47:	ldc	#196; //class java/lang/reflect/Constructor
   49:	invokevirtual	#200; //Method scala/runtime/ScalaRunTime$.arrayValue:(Lscala/runtime/BoxedArray;Ljava/lang/Class;)Ljava/lang/Object;
   52:	goto	56
   55:	aload_1
   56:	checkcast	#202; //class "[Ljava/lang/reflect/Constructor;"
   59:	areturn
  LineNumberTable: 
   line 44: 0

  Signature: length = 0x2
   00 FFFFFFCB 

public java.lang.Class self();
  Code:
   Stack=1, Locals=1, Args_size=1
   0:	aload_0
   1:	getfield	#21; //Field self:Ljava/lang/Class;
   4:	areturn
  LineNumberTable: 
   line 25: 0

  Signature: length = 0x2
   00 FFFFFFD3 

public java.lang.String toString();
  Code:
   Stack=1, Locals=1, Args_size=1
   0:	aload_0
   1:	invokestatic	#214; //Method scala/Proxy$class.toString:(Lscala/Proxy;)Ljava/lang/String;
   4:	areturn
  LineNumberTable: 
   line 25: 0


public boolean equals(java.lang.Object);
  Code:
   Stack=2, Locals=2, Args_size=2
   0:	aload_0
   1:	aload_1
   2:	invokestatic	#219; //Method scala/Proxy$class.equals:(Lscala/Proxy;Ljava/lang/Object;)Z
   5:	ireturn
  LineNumberTable: 
   line 25: 0

  LocalVariableTable: 
   Start  Length  Slot  Name   Signature
   0      6      0    this       Lscala/reflect/RichClass;
   0      6      1    that       Ljava/lang/Object;


public int hashCode();
  Code:
   Stack=1, Locals=1, Args_size=1
   0:	aload_0
   1:	invokestatic	#225; //Method scala/Proxy$class.hashCode:(Lscala/Proxy;)I
   4:	ireturn
  LineNumberTable: 
   line 25: 0


}

