Compiled from "RichClass.scala"
public class scala.reflect.RichClass$FailedReflectiveCall extends scala.reflect.RichClass$ReflectiveCall implements scala.ScalaObject
  SourceFile: "RichClass.scala"
  Signature: length = 0x2
   00 27 
  Scala: length = 0x
   
  InnerClass: 
   public #44= #14 of #43; //ReflectiveCall=class scala/reflect/RichClass$ReflectiveCall of class scala/reflect/RichClass
   public #45= #10 of #43; //FailedReflectiveCall=class scala/reflect/RichClass$FailedReflectiveCall of class scala/reflect/RichClass
  minor version: 0
  major version: 49
  Constant pool:
const #1 = Asciz	SourceFile;
const #2 = Asciz	RichClass.scala;
const #3 = Asciz	ex;
const #4 = Asciz	Ljava/lang/Throwable;;
const #5 = Asciz	<init>;
const #6 = Asciz	(Lscala/reflect/RichClass;Ljava/lang/Throwable;)V;
const #7 = Asciz	Code;
const #8 = Asciz	LineNumberTable;
const #9 = Asciz	scala/reflect/RichClass$FailedReflectiveCall;
const #10 = class	#9;	//  scala/reflect/RichClass$FailedReflectiveCall
const #11 = NameAndType	#3:#4;//  ex:Ljava/lang/Throwable;
const #12 = Field	#10.#11;	//  scala/reflect/RichClass$FailedReflectiveCall.ex:Ljava/lang/Throwable;
const #13 = Asciz	scala/reflect/RichClass$ReflectiveCall;
const #14 = class	#13;	//  scala/reflect/RichClass$ReflectiveCall
const #15 = Asciz	(Lscala/reflect/RichClass;Ljava/lang/Object;Ljava/lang/String;)V;
const #16 = NameAndType	#5:#15;//  "<init>":(Lscala/reflect/RichClass;Ljava/lang/Object;Ljava/lang/String;)V
const #17 = Method	#14.#16;	//  scala/reflect/RichClass$ReflectiveCall."<init>":(Lscala/reflect/RichClass;Ljava/lang/Object;Ljava/lang/String;)V
const #18 = Asciz	this;
const #19 = Asciz	Lscala/reflect/RichClass$FailedReflectiveCall;;
const #20 = Asciz	$outer;
const #21 = Asciz	Lscala/reflect/RichClass;;
const #22 = Asciz	LocalVariableTable;
const #23 = Asciz	(Lscala/reflect/RichClass<TT;>;Ljava/lang/Throwable;)V;
const #24 = Asciz	Signature;
const #25 = Asciz	apply;
const #26 = Asciz	(Lscala/collection/Sequence;)Ljava/lang/Object;;
const #27 = Asciz	(Lscala/collection/Sequence;)Lscala/runtime/Nothing$;;
const #28 = NameAndType	#25:#27;//  apply:(Lscala/collection/Sequence;)Lscala/runtime/Nothing$;
const #29 = Method	#10.#28;	//  scala/reflect/RichClass$FailedReflectiveCall.apply:(Lscala/collection/Sequence;)Lscala/runtime/Nothing$;
const #30 = Asciz	args;
const #31 = Asciz	Lscala/collection/Sequence;;
const #32 = Asciz	scala$reflect$RichClass$FailedReflectiveCall$$$outer;
const #33 = Asciz	()Lscala/reflect/RichClass;;
const #34 = NameAndType	#20:#21;//  $outer:Lscala/reflect/RichClass;
const #35 = Field	#14.#34;	//  scala/reflect/RichClass$ReflectiveCall.$outer:Lscala/reflect/RichClass;
const #36 = Asciz	(Lscala/collection/Sequence<Ljava/lang/Object;>;)Lscala/runtime/Nothing$;;
const #37 = Asciz	isErroneous;
const #38 = Asciz	()Z;
const #39 = Asciz	<U:Ljava/lang/Object;>Lscala/reflect/RichClass<TT;>.ReflectiveCall<TU;>;Lscala/ScalaObject;;
const #40 = Asciz	Scala;
const #41 = Asciz	InnerClasses;
const #42 = Asciz	scala/reflect/RichClass;
const #43 = class	#42;	//  scala/reflect/RichClass
const #44 = Asciz	ReflectiveCall;
const #45 = Asciz	FailedReflectiveCall;
const #46 = Asciz	scala/ScalaObject;
const #47 = class	#46;	//  scala/ScalaObject

{
public scala.reflect.RichClass$FailedReflectiveCall(scala.reflect.RichClass, java.lang.Throwable);
  Code:
   Stack=4, Locals=3, Args_size=3
   0:	aload_0
   1:	aload_2
   2:	putfield	#12; //Field ex:Ljava/lang/Throwable;
   5:	aload_0
   6:	aload_1
   7:	aconst_null
   8:	pop
   9:	aconst_null
   10:	aconst_null
   11:	pop
   12:	aconst_null
   13:	invokespecial	#17; //Method scala/reflect/RichClass$ReflectiveCall."<init>":(Lscala/reflect/RichClass;Ljava/lang/Object;Ljava/lang/String;)V
   16:	return
  LineNumberTable: 
   line 79: 0

  LocalVariableTable: 
   Start  Length  Slot  Name   Signature
   0      17      0    this       Lscala/reflect/RichClass$FailedReflectiveCall;
   0      17      1    $outer       Lscala/reflect/RichClass;
   0      17      2    ex       Ljava/lang/Throwable;

  Signature: length = 0x2
   00 17 

public java.lang.Object apply(scala.collection.Sequence);
  Code:
   Stack=2, Locals=2, Args_size=2
   0:	aload_0
   1:	aload_1
   2:	invokevirtual	#29; //Method apply:(Lscala/collection/Sequence;)Lscala/runtime/Nothing$;
   5:	athrow
  LineNumberTable: 
   line 79: 0

  LocalVariableTable: 
   Start  Length  Slot  Name   Signature
   0      6      0    this       Lscala/reflect/RichClass$FailedReflectiveCall;
   0      6      1    args       Lscala/collection/Sequence;


public scala.reflect.RichClass scala$reflect$RichClass$FailedReflectiveCall$$$outer();
  Code:
   Stack=1, Locals=1, Args_size=1
   0:	aload_0
   1:	getfield	#35; //Field scala/reflect/RichClass$ReflectiveCall.$outer:Lscala/reflect/RichClass;
   4:	areturn
  LineNumberTable: 
   line 79: 0


public scala.runtime.Nothing$ apply(scala.collection.Sequence);
  Code:
   Stack=1, Locals=2, Args_size=2
   0:	aload_0
   1:	getfield	#12; //Field ex:Ljava/lang/Throwable;
   4:	athrow
  LineNumberTable: 
   line 81: 0

  LocalVariableTable: 
   Start  Length  Slot  Name   Signature
   0      5      0    this       Lscala/reflect/RichClass$FailedReflectiveCall;
   0      5      1    args       Lscala/collection/Sequence;

  Signature: length = 0x2
   00 24 

public boolean isErroneous();
  Code:
   Stack=1, Locals=1, Args_size=1
   0:	iconst_1
   1:	ireturn
  LineNumberTable: 
   line 80: 0


}

