Compiled from "RichClass.scala"
public final class scala.reflect.RichClass$$anonfun$reflectiveCall$1 extends java.lang.Object implements scala.Function0,scala.ScalaObject,java.io.Serializable
  SourceFile: "RichClass.scala"
  Scala: length = 0x
   
  InnerClass: 
   public #59= #46 of #58; //ReflectiveCall=class scala/reflect/RichClass$ReflectiveCall of class scala/reflect/RichClass
   public final #60= #19 of #58; //$anonfun$reflectiveCall$1=class scala/reflect/RichClass$$anonfun$reflectiveCall$1 of class scala/reflect/RichClass
  minor version: 0
  major version: 49
  Constant pool:
const #1 = Asciz	SourceFile;
const #2 = Asciz	RichClass.scala;
const #3 = Asciz	method$1;
const #4 = Asciz	Ljava/lang/String;;
const #5 = Asciz	obj$1;
const #6 = Asciz	Ljava/lang/Object;;
const #7 = Asciz	$outer;
const #8 = Asciz	Lscala/reflect/RichClass;;
const #9 = Asciz	<init>;
const #10 = Asciz	(Lscala/reflect/RichClass;Ljava/lang/Object;Ljava/lang/String;)V;
const #11 = Asciz	Code;
const #12 = Asciz	LineNumberTable;
const #13 = Asciz	java/lang/NullPointerException;
const #14 = class	#13;	//  java/lang/NullPointerException
const #15 = Asciz	()V;
const #16 = NameAndType	#9:#15;//  "<init>":()V
const #17 = Method	#14.#16;	//  java/lang/NullPointerException."<init>":()V
const #18 = Asciz	scala/reflect/RichClass$$anonfun$reflectiveCall$1;
const #19 = class	#18;	//  scala/reflect/RichClass$$anonfun$reflectiveCall$1
const #20 = NameAndType	#7:#8;//  $outer:Lscala/reflect/RichClass;
const #21 = Field	#19.#20;	//  scala/reflect/RichClass$$anonfun$reflectiveCall$1.$outer:Lscala/reflect/RichClass;
const #22 = NameAndType	#5:#6;//  obj$1:Ljava/lang/Object;
const #23 = Field	#19.#22;	//  scala/reflect/RichClass$$anonfun$reflectiveCall$1.obj$1:Ljava/lang/Object;
const #24 = NameAndType	#3:#4;//  method$1:Ljava/lang/String;
const #25 = Field	#19.#24;	//  scala/reflect/RichClass$$anonfun$reflectiveCall$1.method$1:Ljava/lang/String;
const #26 = Asciz	java/lang/Object;
const #27 = class	#26;	//  java/lang/Object
const #28 = Method	#27.#16;	//  java/lang/Object."<init>":()V
const #29 = Asciz	scala/Function0$class;
const #30 = class	#29;	//  scala/Function0$class
const #31 = Asciz	$init$;
const #32 = Asciz	(Lscala/Function0;)V;
const #33 = NameAndType	#31:#32;//  $init$:(Lscala/Function0;)V
const #34 = Method	#30.#33;	//  scala/Function0$class.$init$:(Lscala/Function0;)V
const #35 = Asciz	this;
const #36 = Asciz	Lscala/reflect/RichClass$$anonfun$reflectiveCall$1;;
const #37 = Asciz	LocalVariableTable;
const #38 = Asciz	(Lscala/reflect/RichClass<TT;>;)V;
const #39 = Asciz	Signature;
const #40 = Asciz	apply;
const #41 = Asciz	()Ljava/lang/Object;;
const #42 = Asciz	()Lscala/reflect/RichClass$ReflectiveCall;;
const #43 = NameAndType	#40:#42;//  apply:()Lscala/reflect/RichClass$ReflectiveCall;
const #44 = Method	#19.#43;	//  scala/reflect/RichClass$$anonfun$reflectiveCall$1.apply:()Lscala/reflect/RichClass$ReflectiveCall;
const #45 = Asciz	scala/reflect/RichClass$ReflectiveCall;
const #46 = class	#45;	//  scala/reflect/RichClass$ReflectiveCall
const #47 = NameAndType	#9:#10;//  "<init>":(Lscala/reflect/RichClass;Ljava/lang/Object;Ljava/lang/String;)V
const #48 = Method	#46.#47;	//  scala/reflect/RichClass$ReflectiveCall."<init>":(Lscala/reflect/RichClass;Ljava/lang/Object;Ljava/lang/String;)V
const #49 = Asciz	()Lscala/reflect/RichClass<TT;>.ReflectiveCall<TU;>;;
const #50 = Asciz	toString;
const #51 = Asciz	()Ljava/lang/String;;
const #52 = Asciz	(Lscala/Function0;)Ljava/lang/String;;
const #53 = NameAndType	#50:#52;//  toString:(Lscala/Function0;)Ljava/lang/String;
const #54 = Method	#30.#53;	//  scala/Function0$class.toString:(Lscala/Function0;)Ljava/lang/String;
const #55 = Asciz	Scala;
const #56 = Asciz	InnerClasses;
const #57 = Asciz	scala/reflect/RichClass;
const #58 = class	#57;	//  scala/reflect/RichClass
const #59 = Asciz	ReflectiveCall;
const #60 = Asciz	$anonfun$reflectiveCall$1;
const #61 = Asciz	scala/Function0;
const #62 = class	#61;	//  scala/Function0
const #63 = Asciz	scala/ScalaObject;
const #64 = class	#63;	//  scala/ScalaObject
const #65 = Asciz	java/io/Serializable;
const #66 = class	#65;	//  java/io/Serializable

{
public scala.reflect.RichClass$$anonfun$reflectiveCall$1(scala.reflect.RichClass, java.lang.Object, java.lang.String);
  Code:
   Stack=2, Locals=4, Args_size=4
   0:	aload_1
   1:	ifnonnull	12
   4:	new	#14; //class java/lang/NullPointerException
   7:	dup
   8:	invokespecial	#17; //Method java/lang/NullPointerException."<init>":()V
   11:	athrow
   12:	aload_0
   13:	aload_1
   14:	putfield	#21; //Field $outer:Lscala/reflect/RichClass;
   17:	aload_0
   18:	aload_2
   19:	putfield	#23; //Field obj$1:Ljava/lang/Object;
   22:	aload_0
   23:	aload_3
   24:	putfield	#25; //Field method$1:Ljava/lang/String;
   27:	aload_0
   28:	invokespecial	#28; //Method java/lang/Object."<init>":()V
   31:	aload_0
   32:	invokestatic	#34; //Method scala/Function0$class.$init$:(Lscala/Function0;)V
   35:	return
  LineNumberTable: 
   line 85: 0

  LocalVariableTable: 
   Start  Length  Slot  Name   Signature
   0      36      0    this       Lscala/reflect/RichClass$$anonfun$reflectiveCall$1;
   0      36      1    $outer       Lscala/reflect/RichClass;

  Signature: length = 0x2
   00 26 

public final java.lang.Object apply();
  Code:
   Stack=1, Locals=2, Args_size=1
   0:	aload_0
   1:	getfield	#21; //Field $outer:Lscala/reflect/RichClass;
   4:	astore_1
   5:	aload_0
   6:	invokevirtual	#44; //Method apply:()Lscala/reflect/RichClass$ReflectiveCall;
   9:	areturn
  LineNumberTable: 
   line 85: 0

  LocalVariableTable: 
   Start  Length  Slot  Name   Signature
   0      10      0    this       Lscala/reflect/RichClass$$anonfun$reflectiveCall$1;


public final scala.reflect.RichClass$ReflectiveCall apply();
  Code:
   Stack=5, Locals=2, Args_size=1
   0:	aload_0
   1:	getfield	#21; //Field $outer:Lscala/reflect/RichClass;
   4:	astore_1
   5:	new	#46; //class scala/reflect/RichClass$ReflectiveCall
   8:	dup
   9:	aload_0
   10:	getfield	#21; //Field $outer:Lscala/reflect/RichClass;
   13:	aload_0
   14:	getfield	#23; //Field obj$1:Ljava/lang/Object;
   17:	aload_0
   18:	getfield	#25; //Field method$1:Ljava/lang/String;
   21:	invokespecial	#48; //Method scala/reflect/RichClass$ReflectiveCall."<init>":(Lscala/reflect/RichClass;Ljava/lang/Object;Ljava/lang/String;)V
   24:	areturn
  LineNumberTable: 
   line 85: 0

  LocalVariableTable: 
   Start  Length  Slot  Name   Signature
   0      25      0    this       Lscala/reflect/RichClass$$anonfun$reflectiveCall$1;

  Signature: length = 0x2
   00 31 

public java.lang.String toString();
  Code:
   Stack=1, Locals=1, Args_size=1
   0:	aload_0
   1:	invokestatic	#54; //Method scala/Function0$class.toString:(Lscala/Function0;)Ljava/lang/String;
   4:	areturn
  LineNumberTable: 
   line 85: 0


}

