Compiled from "Symbol.scala"
public final class scala.reflect.RootSymbol$ extends scala.reflect.Symbol implements scala.ScalaObject,scala.Product,java.io.Serializable
  SourceFile: "Symbol.scala"
  Scala: length = 0x
   
  minor version: 0
  major version: 49
  Constant pool:
const #1 = Asciz	SourceFile;
const #2 = Asciz	Symbol.scala;
const #3 = Asciz	Scala;
const #4 = Asciz	MODULE$;
const #5 = Asciz	Lscala/reflect/RootSymbol$;;
const #6 = Asciz	<clinit>;
const #7 = Asciz	()V;
const #8 = Asciz	Code;
const #9 = Asciz	scala/reflect/RootSymbol$;
const #10 = class	#9;	//  scala/reflect/RootSymbol$
const #11 = Asciz	<init>;
const #12 = NameAndType	#11:#7;//  "<init>":()V
const #13 = Method	#10.#12;	//  scala/reflect/RootSymbol$."<init>":()V
const #14 = Asciz	tpe;
const #15 = Asciz	Lscala/reflect/NoPrefix$;;
const #16 = Asciz	name;
const #17 = Asciz	Ljava/lang/String;;
const #18 = Asciz	owner;
const #19 = Asciz	Lscala/reflect/NoSymbol$;;
const #20 = Asciz	LineNumberTable;
const #21 = Asciz	scala/reflect/Symbol;
const #22 = class	#21;	//  scala/reflect/Symbol
const #23 = Method	#22.#12;	//  scala/reflect/Symbol."<init>":()V
const #24 = NameAndType	#4:#5;//  MODULE$:Lscala/reflect/RootSymbol$;
const #25 = Field	#10.#24;	//  scala/reflect/RootSymbol$.MODULE$:Lscala/reflect/RootSymbol$;
const #26 = Asciz	scala/Product$class;
const #27 = class	#26;	//  scala/Product$class
const #28 = Asciz	$init$;
const #29 = Asciz	(Lscala/Product;)V;
const #30 = NameAndType	#28:#29;//  $init$:(Lscala/Product;)V
const #31 = Method	#27.#30;	//  scala/Product$class.$init$:(Lscala/Product;)V
const #32 = Asciz	scala/reflect/NoSymbol$;
const #33 = class	#32;	//  scala/reflect/NoSymbol$
const #34 = NameAndType	#4:#19;//  MODULE$:Lscala/reflect/NoSymbol$;
const #35 = Field	#33.#34;	//  scala/reflect/NoSymbol$.MODULE$:Lscala/reflect/NoSymbol$;
const #36 = NameAndType	#18:#19;//  owner:Lscala/reflect/NoSymbol$;
const #37 = Field	#10.#36;	//  scala/reflect/RootSymbol$.owner:Lscala/reflect/NoSymbol$;
const #38 = Asciz	<root>;
const #39 = String	#38;	//  <root>
const #40 = NameAndType	#16:#17;//  name:Ljava/lang/String;
const #41 = Field	#10.#40;	//  scala/reflect/RootSymbol$.name:Ljava/lang/String;
const #42 = Asciz	scala/reflect/NoPrefix$;
const #43 = class	#42;	//  scala/reflect/NoPrefix$
const #44 = NameAndType	#4:#15;//  MODULE$:Lscala/reflect/NoPrefix$;
const #45 = Field	#43.#44;	//  scala/reflect/NoPrefix$.MODULE$:Lscala/reflect/NoPrefix$;
const #46 = NameAndType	#14:#15;//  tpe:Lscala/reflect/NoPrefix$;
const #47 = Field	#10.#46;	//  scala/reflect/RootSymbol$.tpe:Lscala/reflect/NoPrefix$;
const #48 = Asciz	()Lscala/reflect/Symbol;;
const #49 = Asciz	()Lscala/reflect/NoSymbol$;;
const #50 = NameAndType	#18:#49;//  owner:()Lscala/reflect/NoSymbol$;
const #51 = Method	#10.#50;	//  scala/reflect/RootSymbol$.owner:()Lscala/reflect/NoSymbol$;
const #52 = Asciz	()Lscala/reflect/Type;;
const #53 = Asciz	()Lscala/reflect/NoPrefix$;;
const #54 = NameAndType	#14:#53;//  tpe:()Lscala/reflect/NoPrefix$;
const #55 = Method	#10.#54;	//  scala/reflect/RootSymbol$.tpe:()Lscala/reflect/NoPrefix$;
const #56 = Asciz	readResolve;
const #57 = Asciz	()Ljava/lang/Object;;
const #58 = Asciz	canEqual;
const #59 = Asciz	(Ljava/lang/Object;)Z;
const #60 = Asciz	productElement;
const #61 = Asciz	(I)Ljava/lang/Object;;
const #62 = Asciz	java/lang/IndexOutOfBoundsException;
const #63 = class	#62;	//  java/lang/IndexOutOfBoundsException
const #64 = Asciz	scala/runtime/BoxesRunTime;
const #65 = class	#64;	//  scala/runtime/BoxesRunTime
const #66 = Asciz	boxToInteger;
const #67 = Asciz	(I)Ljava/lang/Integer;;
const #68 = NameAndType	#66:#67;//  boxToInteger:(I)Ljava/lang/Integer;
const #69 = Method	#65.#68;	//  scala/runtime/BoxesRunTime.boxToInteger:(I)Ljava/lang/Integer;
const #70 = Asciz	java/lang/Object;
const #71 = class	#70;	//  java/lang/Object
const #72 = Asciz	toString;
const #73 = Asciz	()Ljava/lang/String;;
const #74 = NameAndType	#72:#73;//  toString:()Ljava/lang/String;
const #75 = Method	#71.#74;	//  java/lang/Object.toString:()Ljava/lang/String;
const #76 = Asciz	(Ljava/lang/String;)V;
const #77 = NameAndType	#11:#76;//  "<init>":(Ljava/lang/String;)V
const #78 = Method	#63.#77;	//  java/lang/IndexOutOfBoundsException."<init>":(Ljava/lang/String;)V
const #79 = Asciz	this;
const #80 = Asciz	temp33;
const #81 = Asciz	I;
const #82 = Asciz	LocalVariableTable;
const #83 = Asciz	productArity;
const #84 = Asciz	()I;
const #85 = Asciz	productPrefix;
const #86 = Asciz	RootSymbol;
const #87 = String	#86;	//  RootSymbol
const #88 = Asciz	productElements;
const #89 = Asciz	()Lscala/collection/Iterator;;
const #90 = Asciz	(Lscala/Product;)Lscala/collection/Iterator;;
const #91 = NameAndType	#88:#90;//  productElements:(Lscala/Product;)Lscala/collection/Iterator;
const #92 = Method	#27.#91;	//  scala/Product$class.productElements:(Lscala/Product;)Lscala/collection/Iterator;
const #93 = Asciz	productIterator;
const #94 = NameAndType	#93:#90;//  productIterator:(Lscala/Product;)Lscala/collection/Iterator;
const #95 = Method	#27.#94;	//  scala/Product$class.productIterator:(Lscala/Product;)Lscala/collection/Iterator;
const #96 = Asciz	scala/ScalaObject;
const #97 = class	#96;	//  scala/ScalaObject
const #98 = Asciz	scala/Product;
const #99 = class	#98;	//  scala/Product
const #100 = Asciz	java/io/Serializable;
const #101 = class	#100;	//  java/io/Serializable

{
public static final scala.reflect.RootSymbol$ MODULE$;

public static {};
  Code:
   Stack=1, Locals=0, Args_size=0
   0:	new	#10; //class scala/reflect/RootSymbol$
   3:	invokespecial	#13; //Method "<init>":()V
   6:	return

public scala.reflect.Symbol owner();
  Code:
   Stack=1, Locals=1, Args_size=1
   0:	aload_0
   1:	invokevirtual	#51; //Method owner:()Lscala/reflect/NoSymbol$;
   4:	areturn
  LineNumberTable: 
   line 64: 0


public scala.reflect.Type tpe();
  Code:
   Stack=1, Locals=1, Args_size=1
   0:	aload_0
   1:	invokevirtual	#55; //Method tpe:()Lscala/reflect/NoPrefix$;
   4:	areturn
  LineNumberTable: 
   line 64: 0


public java.lang.Object readResolve();
  Code:
   Stack=1, Locals=1, Args_size=1
   0:	getstatic	#25; //Field MODULE$:Lscala/reflect/RootSymbol$;
   3:	areturn
  LineNumberTable: 
   line 64: 0


public boolean canEqual(java.lang.Object);
  Code:
   Stack=1, Locals=2, Args_size=2
   0:	aload_1
   1:	instanceof	#10; //class scala/reflect/RootSymbol$
   4:	ireturn
  LineNumberTable: 
   line 64: 0


public java.lang.Object productElement(int);
  Code:
   Stack=3, Locals=3, Args_size=2
   0:	iload_1
   1:	istore_2
   2:	new	#63; //class java/lang/IndexOutOfBoundsException
   5:	dup
   6:	iload_1
   7:	invokestatic	#69; //Method scala/runtime/BoxesRunTime.boxToInteger:(I)Ljava/lang/Integer;
   10:	invokevirtual	#75; //Method java/lang/Object.toString:()Ljava/lang/String;
   13:	invokespecial	#78; //Method java/lang/IndexOutOfBoundsException."<init>":(Ljava/lang/String;)V
   16:	athrow
  LineNumberTable: 
   line 64: 0

  LocalVariableTable: 
   Start  Length  Slot  Name   Signature
   0      17      0    this       Lscala/reflect/RootSymbol$;
   2      15      2    temp33       I


public int productArity();
  Code:
   Stack=1, Locals=1, Args_size=1
   0:	iconst_0
   1:	ireturn
  LineNumberTable: 
   line 64: 0


public java.lang.String productPrefix();
  Code:
   Stack=1, Locals=1, Args_size=1
   0:	ldc	#87; //String RootSymbol
   2:	areturn
  LineNumberTable: 
   line 64: 0


public final java.lang.String toString();
  Code:
   Stack=1, Locals=1, Args_size=1
   0:	ldc	#87; //String RootSymbol
   2:	areturn
  LineNumberTable: 
   line 64: 0


public scala.reflect.NoPrefix$ tpe();
  Code:
   Stack=1, Locals=1, Args_size=1
   0:	aload_0
   1:	getfield	#47; //Field tpe:Lscala/reflect/NoPrefix$;
   4:	areturn
  LineNumberTable: 
   line 67: 0


public java.lang.String name();
  Code:
   Stack=1, Locals=1, Args_size=1
   0:	aload_0
   1:	getfield	#41; //Field name:Ljava/lang/String;
   4:	areturn
  LineNumberTable: 
   line 66: 0


public scala.reflect.NoSymbol$ owner();
  Code:
   Stack=1, Locals=1, Args_size=1
   0:	aload_0
   1:	getfield	#37; //Field owner:Lscala/reflect/NoSymbol$;
   4:	areturn
  LineNumberTable: 
   line 65: 0


public scala.collection.Iterator productElements();
  Code:
   Stack=1, Locals=1, Args_size=1
   0:	aload_0
   1:	invokestatic	#92; //Method scala/Product$class.productElements:(Lscala/Product;)Lscala/collection/Iterator;
   4:	areturn
  LineNumberTable: 
   line 64: 0


public scala.collection.Iterator productIterator();
  Code:
   Stack=1, Locals=1, Args_size=1
   0:	aload_0
   1:	invokestatic	#95; //Method scala/Product$class.productIterator:(Lscala/Product;)Lscala/collection/Iterator;
   4:	areturn
  LineNumberTable: 
   line 64: 0


}

