Compiled from "Symbol.scala"
public final class scala.reflect.RootSymbol extends java.lang.Object
  SourceFile: "Symbol.scala"
  ScalaSig: length = 0x251
   05 00 5A 07 05 01 02 FFFFFF88 42 07 01 0A 52 6F 6F 74
   53 79 6D 62 6F 6C 0A 02 03 04 01 07 72 65 66 6C
   65 63 74 0A 01 05 01 05 73 63 61 6C 61 03 00 10
   02 08 09 0D 01 02 06 08 0A 02 FFFFFF84 FFFFFF80 FFFFFF80 FFFFFF88 42 0B
   02 0A 52 6F 6F 74 53 79 6D 62 6F 6C 13 04 09 0C
   0F 13 10 02 08 0D 09 02 0E 02 02 06 53 79 6D 62
   6F 6C 10 02 10 11 0D 01 04 09 02 12 04 02 0B 53
   63 61 6C 61 4F 62 6A 65 63 74 10 02 10 14 09 02
   15 04 02 07 50 72 6F 64 75 63 74 08 05 17 09 FFFFFF84
   00 18 01 06 3C 69 6E 69 74 3E 14 01 07 08 07 1A
   09 FFFFFFC2 FFFFFF80 FFFFFF84 00 1B 01 05 6F 77 6E 65 72 15 01 1C
   0E 02 08 1D 09 02 1E 02 01 08 4E 6F 53 79 6D 62
   6F 6C 08 06 20 09 FFFFFFA0 FFFFFF80 04 1C 01 06 6F 77 6E 65
   72 20 08 07 22 09 FFFFFFC2 FFFFFF80 FFFFFF84 00 23 01 04 6E 61 6D
   65 15 01 24 10 02 25 2A 0D 01 26 0A 02 27 28 01
   04 6C 61 6E 67 0A 01 29 01 04 6A 61 76 61 09 02
   2B 26 02 06 53 74 72 69 6E 67 08 06 2D 09 FFFFFFA0 FFFFFF80
   04 24 01 05 6E 61 6D 65 20 08 07 2F 09 FFFFFFC2 FFFFFF80 FFFFFF84
   00 30 01 03 74 70 65 15 01 31 0E 02 08 32 09 02
   33 02 01 08 4E 6F 50 72 65 66 69 78 08 06 35 09
   FFFFFFA0 FFFFFF80 04 31 01 04 74 70 65 20 08 08 37 09 FFFFFF84 FFFFFF80
   FFFFFF80 FFFFFF84 22 38 01 08 74 6F 53 74 72 69 6E 67 14 01
   24 08 08 3A 09 FFFFFF84 FFFFFF80 FFFFFF80 FFFFFF84 20 23 01 0D 70 72 6F
   64 75 63 74 50 72 65 66 69 78 08 08 3C 09 FFFFFF84 FFFFFF80
   FFFFFF80 FFFFFF84 20 3D 01 0C 70 72 6F 64 75 63 74 41 72 69
   74 79 15 01 3E 10 02 10 3F 09 02 40 04 02 03 49
   6E 74 08 08 42 09 FFFFFF84 FFFFFF80 FFFFFF80 FFFFFF84 20 43 01 0E 70 72
   6F 64 75 63 74 45 6C 65 6D 65 6E 74 14 02 44 47
   10 02 10 45 09 02 46 04 02 03 41 6E 79 08 07 48
   41 FFFFFF81 FFFFFF80 FFFFFFC0 00 3E 01 03 78 24 31 08 08 4A 09 FFFFFF84
   FFFFFF80 FFFFFF80 FFFFFF84 20 4B 01 08 63 61 6E 45 71 75 61 6C 14
   02 4C 4F 10 02 10 4D 09 02 4E 04 02 07 42 6F 6F
   6C 65 61 6E 08 07 48 49 FFFFFF81 FFFFFF80 FFFFFFC0 00 44 08 08 51
   09 FFFFFF84 FFFFFF80 FFFFFF80 FFFFFF84 08 52 01 0B 72 65 61 64 52 65 73
   6F 6C 76 65 14 01 53 10 02 25 54 09 02 55 26 02
   06 4F 62 6A 65 63 74 28 02 09 57 10 02 10 58 09
   02 59 04 02 0C 73 65 72 69 61 6C 69 7A 61 62 6C
   65 
  minor version: 0
  major version: 49
  Constant pool:
const #1 = Asciz	SourceFile;
const #2 = Asciz	Symbol.scala;
const #3 = Asciz	productElements;
const #4 = Asciz	()Lscala/collection/Iterator;;
const #5 = Asciz	Code;
const #6 = Asciz	scala/reflect/RootSymbol$;
const #7 = class	#6;	//  scala/reflect/RootSymbol$
const #8 = Asciz	MODULE$;
const #9 = Asciz	Lscala/reflect/RootSymbol$;;
const #10 = NameAndType	#8:#9;//  MODULE$:Lscala/reflect/RootSymbol$;
const #11 = Field	#7.#10;	//  scala/reflect/RootSymbol$.MODULE$:Lscala/reflect/RootSymbol$;
const #12 = NameAndType	#3:#4;//  productElements:()Lscala/collection/Iterator;
const #13 = Method	#7.#12;	//  scala/reflect/RootSymbol$.productElements:()Lscala/collection/Iterator;
const #14 = Asciz	Deprecated;
const #15 = Asciz	productIterator;
const #16 = NameAndType	#15:#4;//  productIterator:()Lscala/collection/Iterator;
const #17 = Method	#7.#16;	//  scala/reflect/RootSymbol$.productIterator:()Lscala/collection/Iterator;
const #18 = Asciz	canEqual;
const #19 = Asciz	(Ljava/lang/Object;)Z;
const #20 = NameAndType	#18:#19;//  canEqual:(Ljava/lang/Object;)Z
const #21 = Method	#7.#20;	//  scala/reflect/RootSymbol$.canEqual:(Ljava/lang/Object;)Z
const #22 = Asciz	productElement;
const #23 = Asciz	(I)Ljava/lang/Object;;
const #24 = NameAndType	#22:#23;//  productElement:(I)Ljava/lang/Object;
const #25 = Method	#7.#24;	//  scala/reflect/RootSymbol$.productElement:(I)Ljava/lang/Object;
const #26 = Asciz	productArity;
const #27 = Asciz	()I;
const #28 = NameAndType	#26:#27;//  productArity:()I
const #29 = Method	#7.#28;	//  scala/reflect/RootSymbol$.productArity:()I
const #30 = Asciz	productPrefix;
const #31 = Asciz	()Ljava/lang/String;;
const #32 = NameAndType	#30:#31;//  productPrefix:()Ljava/lang/String;
const #33 = Method	#7.#32;	//  scala/reflect/RootSymbol$.productPrefix:()Ljava/lang/String;
const #34 = Asciz	tpe;
const #35 = Asciz	()Lscala/reflect/NoPrefix$;;
const #36 = NameAndType	#34:#35;//  tpe:()Lscala/reflect/NoPrefix$;
const #37 = Method	#7.#36;	//  scala/reflect/RootSymbol$.tpe:()Lscala/reflect/NoPrefix$;
const #38 = Asciz	name;
const #39 = NameAndType	#38:#31;//  name:()Ljava/lang/String;
const #40 = Method	#7.#39;	//  scala/reflect/RootSymbol$.name:()Ljava/lang/String;
const #41 = Asciz	owner;
const #42 = Asciz	()Lscala/reflect/NoSymbol$;;
const #43 = NameAndType	#41:#42;//  owner:()Lscala/reflect/NoSymbol$;
const #44 = Method	#7.#43;	//  scala/reflect/RootSymbol$.owner:()Lscala/reflect/NoSymbol$;
const #45 = Asciz	ScalaSig;
const #46 = Asciz	scala/reflect/RootSymbol;
const #47 = class	#46;	//  scala/reflect/RootSymbol
const #48 = Asciz	java/lang/Object;
const #49 = class	#48;	//  java/lang/Object

{
public static final scala.collection.Iterator productElements();
  Code:
   Stack=1, Locals=0, Args_size=0
   0:	getstatic	#11; //Field scala/reflect/RootSymbol$.MODULE$:Lscala/reflect/RootSymbol$;
   3:	invokevirtual	#13; //Method scala/reflect/RootSymbol$.productElements:()Lscala/collection/Iterator;
   6:	areturn
  Deprecated: true

public static final scala.collection.Iterator productIterator();
  Code:
   Stack=1, Locals=0, Args_size=0
   0:	getstatic	#11; //Field scala/reflect/RootSymbol$.MODULE$:Lscala/reflect/RootSymbol$;
   3:	invokevirtual	#17; //Method scala/reflect/RootSymbol$.productIterator:()Lscala/collection/Iterator;
   6:	areturn

public static final boolean canEqual(java.lang.Object);
  Code:
   Stack=2, Locals=1, Args_size=1
   0:	getstatic	#11; //Field scala/reflect/RootSymbol$.MODULE$:Lscala/reflect/RootSymbol$;
   3:	aload_0
   4:	invokevirtual	#21; //Method scala/reflect/RootSymbol$.canEqual:(Ljava/lang/Object;)Z
   7:	ireturn

public static final java.lang.Object productElement(int);
  Code:
   Stack=2, Locals=1, Args_size=1
   0:	getstatic	#11; //Field scala/reflect/RootSymbol$.MODULE$:Lscala/reflect/RootSymbol$;
   3:	iload_0
   4:	invokevirtual	#25; //Method scala/reflect/RootSymbol$.productElement:(I)Ljava/lang/Object;
   7:	areturn

public static final int productArity();
  Code:
   Stack=1, Locals=0, Args_size=0
   0:	getstatic	#11; //Field scala/reflect/RootSymbol$.MODULE$:Lscala/reflect/RootSymbol$;
   3:	invokevirtual	#29; //Method scala/reflect/RootSymbol$.productArity:()I
   6:	ireturn

public static final java.lang.String productPrefix();
  Code:
   Stack=1, Locals=0, Args_size=0
   0:	getstatic	#11; //Field scala/reflect/RootSymbol$.MODULE$:Lscala/reflect/RootSymbol$;
   3:	invokevirtual	#33; //Method scala/reflect/RootSymbol$.productPrefix:()Ljava/lang/String;
   6:	areturn

public static final scala.reflect.NoPrefix$ tpe();
  Code:
   Stack=1, Locals=0, Args_size=0
   0:	getstatic	#11; //Field scala/reflect/RootSymbol$.MODULE$:Lscala/reflect/RootSymbol$;
   3:	invokevirtual	#37; //Method scala/reflect/RootSymbol$.tpe:()Lscala/reflect/NoPrefix$;
   6:	areturn

public static final java.lang.String name();
  Code:
   Stack=1, Locals=0, Args_size=0
   0:	getstatic	#11; //Field scala/reflect/RootSymbol$.MODULE$:Lscala/reflect/RootSymbol$;
   3:	invokevirtual	#40; //Method scala/reflect/RootSymbol$.name:()Ljava/lang/String;
   6:	areturn

public static final scala.reflect.NoSymbol$ owner();
  Code:
   Stack=1, Locals=0, Args_size=0
   0:	getstatic	#11; //Field scala/reflect/RootSymbol$.MODULE$:Lscala/reflect/RootSymbol$;
   3:	invokevirtual	#44; //Method scala/reflect/RootSymbol$.owner:()Lscala/reflect/NoSymbol$;
   6:	areturn

}

