Compiled from "Symbol.scala"
public final class scala.reflect.RootSymbol$ extends scala.reflect.Symbol implements scala.ScalaObject,scala.Product,java.io.Serializable
  SourceFile: "Symbol.scala"
  Scala: length = 0x
   
  minor version: 0
  major version: 49
  Constant pool:
Asciz	SourceFile;
Asciz	Symbol.scala;
Asciz	Scala;
Asciz	MODULE$;
Asciz	Lscala/reflect/RootSymbol$;;
Asciz	<clinit>;
Asciz	()V;
Asciz	Code;
Asciz	scala/reflect/RootSymbol$;
class	scala/reflect/RootSymbol$
Asciz	<init>;
NameAndType	"<init>":()V
Method	scala/reflect/RootSymbol$."<init>":()V
Asciz	tpe;
Asciz	Lscala/reflect/NoPrefix$;;
Asciz	name;
Asciz	Ljava/lang/String;;
Asciz	owner;
Asciz	Lscala/reflect/NoSymbol$;;
Asciz	LineNumberTable;
Asciz	scala/reflect/Symbol;
class	scala/reflect/Symbol
Method	scala/reflect/Symbol."<init>":()V
NameAndType	MODULE$:Lscala/reflect/RootSymbol$;
Field	scala/reflect/RootSymbol$.MODULE$:Lscala/reflect/RootSymbol$;
Asciz	scala/Product$class;
class	scala/Product$class
Asciz	$init$;
Asciz	(Lscala/Product;)V;
NameAndType	$init$:(Lscala/Product;)V
Method	scala/Product$class.$init$:(Lscala/Product;)V
Asciz	scala/reflect/NoSymbol$;
class	scala/reflect/NoSymbol$
NameAndType	MODULE$:Lscala/reflect/NoSymbol$;
Field	scala/reflect/NoSymbol$.MODULE$:Lscala/reflect/NoSymbol$;
NameAndType	owner:Lscala/reflect/NoSymbol$;
Field	scala/reflect/RootSymbol$.owner:Lscala/reflect/NoSymbol$;
Asciz	<root>;
String	<root>
NameAndType	name:Ljava/lang/String;
Field	scala/reflect/RootSymbol$.name:Ljava/lang/String;
Asciz	scala/reflect/NoPrefix$;
class	scala/reflect/NoPrefix$
NameAndType	MODULE$:Lscala/reflect/NoPrefix$;
Field	scala/reflect/NoPrefix$.MODULE$:Lscala/reflect/NoPrefix$;
NameAndType	tpe:Lscala/reflect/NoPrefix$;
Field	scala/reflect/RootSymbol$.tpe:Lscala/reflect/NoPrefix$;
Asciz	()Lscala/reflect/Symbol;;
Asciz	()Lscala/reflect/NoSymbol$;;
NameAndType	owner:()Lscala/reflect/NoSymbol$;
Method	scala/reflect/RootSymbol$.owner:()Lscala/reflect/NoSymbol$;
Asciz	()Lscala/reflect/Type;;
Asciz	()Lscala/reflect/NoPrefix$;;
NameAndType	tpe:()Lscala/reflect/NoPrefix$;
Method	scala/reflect/RootSymbol$.tpe:()Lscala/reflect/NoPrefix$;
Asciz	readResolve;
Asciz	()Ljava/lang/Object;;
Asciz	canEqual;
Asciz	(Ljava/lang/Object;)Z;
Asciz	productElement;
Asciz	(I)Ljava/lang/Object;;
Asciz	java/lang/IndexOutOfBoundsException;
class	java/lang/IndexOutOfBoundsException
Asciz	scala/runtime/BoxesRunTime;
class	scala/runtime/BoxesRunTime
Asciz	boxToInteger;
Asciz	(I)Ljava/lang/Integer;;
NameAndType	boxToInteger:(I)Ljava/lang/Integer;
Method	scala/runtime/BoxesRunTime.boxToInteger:(I)Ljava/lang/Integer;
Asciz	java/lang/Object;
class	java/lang/Object
Asciz	toString;
Asciz	()Ljava/lang/String;;
NameAndType	toString:()Ljava/lang/String;
Method	java/lang/Object.toString:()Ljava/lang/String;
Asciz	(Ljava/lang/String;)V;
NameAndType	"<init>":(Ljava/lang/String;)V
Method	java/lang/IndexOutOfBoundsException."<init>":(Ljava/lang/String;)V
Asciz	scala/MatchError;
class	scala/MatchError
Method	scala/MatchError."<init>":(Ljava/lang/String;)V
Asciz	productArity;
Asciz	()I;
Asciz	productPrefix;
Asciz	RootSymbol;
String	RootSymbol
Asciz	productElements;
Asciz	()Lscala/collection/Iterator;;
Asciz	(Lscala/Product;)Lscala/collection/Iterator;;
NameAndType	productElements:(Lscala/Product;)Lscala/collection/Iterator;
Method	scala/Product$class.productElements:(Lscala/Product;)Lscala/collection/Iterator;
Asciz	Deprecated;
Asciz	productIterator;
NameAndType	productIterator:(Lscala/Product;)Lscala/collection/Iterator;
Method	scala/Product$class.productIterator:(Lscala/Product;)Lscala/collection/Iterator;
Asciz	scala/ScalaObject;
class	scala/ScalaObject
Asciz	scala/Product;
class	scala/Product
Asciz	java/io/Serializable;
class	java/io/Serializable

{
public static final scala.reflect.RootSymbol$ MODULE$;
  Signature: Lscala/reflect/RootSymbol$;

private final scala.reflect.NoPrefix$ tpe;
  Signature: Lscala/reflect/NoPrefix$;

private final java.lang.String name;
  Signature: Ljava/lang/String;

private final scala.reflect.NoSymbol$ owner;
  Signature: Lscala/reflect/NoSymbol$;

public static {};
  Signature: ()V
  Code:
   Stack=1, Locals=0, Args_size=0
	new	class scala/reflect/RootSymbol$
	invokespecial	Method "<init>":()V
	return
  Labels:

private scala.reflect.RootSymbol$();
  Signature: ()V
  Code:
   Stack=2, Locals=1, Args_size=1
	aload_0
	invokespecial	Method scala/reflect/Symbol."<init>":()V
	aload_0
	putstatic	Field MODULE$:Lscala/reflect/RootSymbol$;
	aload_0
	invokestatic	Method scala/Product$class.$init$:(Lscala/Product;)V
	aload_0
	getstatic	Field scala/reflect/NoSymbol$.MODULE$:Lscala/reflect/NoSymbol$;
	putfield	Field owner:Lscala/reflect/NoSymbol$;
	aload_0
	ldc	String <root>
	putfield	Field name:Ljava/lang/String;
	aload_0
	getstatic	Field scala/reflect/NoPrefix$.MODULE$:Lscala/reflect/NoPrefix$;
	putfield	Field tpe:Lscala/reflect/NoPrefix$;
	return
  Labels:

public scala.reflect.Symbol owner();
  Signature: ()Lscala/reflect/Symbol;
  Code:
   Stack=1, Locals=1, Args_size=1
	aload_0
	invokevirtual	Method owner:()Lscala/reflect/NoSymbol$;
	areturn
  Labels:

public scala.reflect.Type tpe();
  Signature: ()Lscala/reflect/Type;
  Code:
   Stack=1, Locals=1, Args_size=1
	aload_0
	invokevirtual	Method tpe:()Lscala/reflect/NoPrefix$;
	areturn
  Labels:

public java.lang.Object readResolve();
  Signature: ()Ljava/lang/Object;
  Code:
   Stack=1, Locals=1, Args_size=1
	getstatic	Field MODULE$:Lscala/reflect/RootSymbol$;
	areturn
  Labels:

public boolean canEqual(java.lang.Object);
  Signature: (Ljava/lang/Object;)Z
  Code:
   Stack=1, Locals=2, Args_size=2
	aload_1
	instanceof	class scala/reflect/RootSymbol$
	ireturn
  Labels:

public java.lang.Object productElement(int);
  Signature: (I)Ljava/lang/Object;
  Code:
   Stack=3, Locals=2, Args_size=2
	iconst_1
	ifeq	l1 // new
	new	class java/lang/IndexOutOfBoundsException
	dup
	iload_1
	invokestatic	Method scala/runtime/BoxesRunTime.boxToInteger:(I)Ljava/lang/Integer;
	invokevirtual	Method java/lang/Object.toString:()Ljava/lang/String;
	invokespecial	Method java/lang/IndexOutOfBoundsException."<init>":(Ljava/lang/String;)V
	athrow
l1	new	class scala/MatchError
	dup
	iload_1
	invokestatic	Method scala/runtime/BoxesRunTime.boxToInteger:(I)Ljava/lang/Integer;
	invokevirtual	Method java/lang/Object.toString:()Ljava/lang/String;
	invokespecial	Method scala/MatchError."<init>":(Ljava/lang/String;)V
	athrow
  Labels:
   	l1 = 19 // new

public int productArity();
  Signature: ()I
  Code:
   Stack=1, Locals=1, Args_size=1
	iconst_0
	ireturn
  Labels:

public java.lang.String productPrefix();
  Signature: ()Ljava/lang/String;
  Code:
   Stack=1, Locals=1, Args_size=1
	ldc	String RootSymbol
	areturn
  Labels:

public final java.lang.String toString();
  Signature: ()Ljava/lang/String;
  Code:
   Stack=1, Locals=1, Args_size=1
	ldc	String RootSymbol
	areturn
  Labels:

public scala.reflect.NoPrefix$ tpe();
  Signature: ()Lscala/reflect/NoPrefix$;
  Code:
   Stack=1, Locals=1, Args_size=1
	aload_0
	getfield	Field tpe:Lscala/reflect/NoPrefix$;
	areturn
  Labels:

public java.lang.String name();
  Signature: ()Ljava/lang/String;
  Code:
   Stack=1, Locals=1, Args_size=1
	aload_0
	getfield	Field name:Ljava/lang/String;
	areturn
  Labels:

public scala.reflect.NoSymbol$ owner();
  Signature: ()Lscala/reflect/NoSymbol$;
  Code:
   Stack=1, Locals=1, Args_size=1
	aload_0
	getfield	Field owner:Lscala/reflect/NoSymbol$;
	areturn
  Labels:

public scala.collection.Iterator productElements();
  Signature: ()Lscala/collection/Iterator;
  Code:
   Stack=1, Locals=1, Args_size=1
	aload_0
	invokestatic	Method scala/Product$class.productElements:(Lscala/Product;)Lscala/collection/Iterator;
	areturn
  Labels:
  Deprecated: true

public scala.collection.Iterator productIterator();
  Signature: ()Lscala/collection/Iterator;
  Code:
   Stack=1, Locals=1, Args_size=1
	aload_0
	invokestatic	Method scala/Product$class.productIterator:(Lscala/Product;)Lscala/collection/Iterator;
	areturn
  Labels:

}

