Compiled from "ScalaBeanInfo.scala"
public final class scala.reflect.ScalaBeanInfo$$anonfun$1 extends java.lang.Object implements scala.Function1,scala.ScalaObject,java.io.Serializable
  SourceFile: "ScalaBeanInfo.scala"
  Scala: length = 0x
   
  InnerClass: 
   public final #98= #9 of #57; //$anonfun$1=class scala/reflect/ScalaBeanInfo$$anonfun$1 of class scala/reflect/ScalaBeanInfo
   public final #99= #69 of #9; //$anonfun$apply$1=class scala/reflect/ScalaBeanInfo$$anonfun$1$$anonfun$apply$1 of class scala/reflect/ScalaBeanInfo$$anonfun$1
  minor version: 0
  major version: 49
  Constant pool:
const #1 = Asciz	SourceFile;
const #2 = Asciz	ScalaBeanInfo.scala;
const #3 = Asciz	<clinit>;
const #4 = Asciz	()V;
const #5 = Asciz	Code;
const #6 = Asciz	serialVersionUID;
const #7 = Asciz	J;
const #8 = Asciz	scala/reflect/ScalaBeanInfo$$anonfun$1;
const #9 = class	#8;	//  scala/reflect/ScalaBeanInfo$$anonfun$1
const #10 = NameAndType	#6:#7;//  serialVersionUID:J
const #11 = Field	#9.#10;	//  scala/reflect/ScalaBeanInfo$$anonfun$1.serialVersionUID:J
const #12 = Asciz	$outer;
const #13 = Asciz	Lscala/reflect/ScalaBeanInfo;;
const #14 = Asciz	<init>;
const #15 = Asciz	(Lscala/reflect/ScalaBeanInfo;)V;
const #16 = Asciz	LineNumberTable;
const #17 = Asciz	java/lang/NullPointerException;
const #18 = class	#17;	//  java/lang/NullPointerException
const #19 = NameAndType	#14:#4;//  "<init>":()V
const #20 = Method	#18.#19;	//  java/lang/NullPointerException."<init>":()V
const #21 = NameAndType	#12:#13;//  $outer:Lscala/reflect/ScalaBeanInfo;
const #22 = Field	#9.#21;	//  scala/reflect/ScalaBeanInfo$$anonfun$1.$outer:Lscala/reflect/ScalaBeanInfo;
const #23 = Asciz	java/lang/Object;
const #24 = class	#23;	//  java/lang/Object
const #25 = Method	#24.#19;	//  java/lang/Object."<init>":()V
const #26 = Asciz	scala/Function1$class;
const #27 = class	#26;	//  scala/Function1$class
const #28 = Asciz	$init$;
const #29 = Asciz	(Lscala/Function1;)V;
const #30 = NameAndType	#28:#29;//  $init$:(Lscala/Function1;)V
const #31 = Method	#27.#30;	//  scala/Function1$class.$init$:(Lscala/Function1;)V
const #32 = Asciz	this;
const #33 = Asciz	Lscala/reflect/ScalaBeanInfo$$anonfun$1;;
const #34 = Asciz	LocalVariableTable;
const #35 = Asciz	apply;
const #36 = Asciz	(Ljava/lang/Object;)Ljava/lang/Object;;
const #37 = Asciz	java/lang/reflect/Method;
const #38 = class	#37;	//  java/lang/reflect/Method
const #39 = Asciz	(Ljava/lang/reflect/Method;)Z;
const #40 = NameAndType	#35:#39;//  apply:(Ljava/lang/reflect/Method;)Z
const #41 = Method	#9.#40;	//  scala/reflect/ScalaBeanInfo$$anonfun$1.apply:(Ljava/lang/reflect/Method;)Z
const #42 = Asciz	scala/runtime/BoxesRunTime;
const #43 = class	#42;	//  scala/runtime/BoxesRunTime
const #44 = Asciz	boxToBoolean;
const #45 = Asciz	(Z)Ljava/lang/Boolean;;
const #46 = NameAndType	#44:#45;//  boxToBoolean:(Z)Ljava/lang/Boolean;
const #47 = Method	#43.#46;	//  scala/runtime/BoxesRunTime.boxToBoolean:(Z)Ljava/lang/Boolean;
const #48 = Asciz	v1;
const #49 = Asciz	Ljava/lang/Object;;
const #50 = Asciz	scala/Predef$;
const #51 = class	#50;	//  scala/Predef$
const #52 = Asciz	MODULE$;
const #53 = Asciz	Lscala/Predef$;;
const #54 = NameAndType	#52:#53;//  MODULE$:Lscala/Predef$;
const #55 = Field	#51.#54;	//  scala/Predef$.MODULE$:Lscala/Predef$;
const #56 = Asciz	scala/reflect/ScalaBeanInfo;
const #57 = class	#56;	//  scala/reflect/ScalaBeanInfo
const #58 = Asciz	scala$reflect$ScalaBeanInfo$$methods;
const #59 = Asciz	[Ljava/lang/String;;
const #60 = NameAndType	#58:#59;//  scala$reflect$ScalaBeanInfo$$methods:[Ljava/lang/String;
const #61 = Field	#57.#60;	//  scala/reflect/ScalaBeanInfo.scala$reflect$ScalaBeanInfo$$methods:[Ljava/lang/String;
const #62 = Asciz	[Ljava/lang/Object;;
const #63 = class	#62;	//  "[Ljava/lang/Object;"
const #64 = Asciz	refArrayOps;
const #65 = Asciz	([Ljava/lang/Object;)Lscala/collection/mutable/ArrayOps;;
const #66 = NameAndType	#64:#65;//  refArrayOps:([Ljava/lang/Object;)Lscala/collection/mutable/ArrayOps;
const #67 = Method	#51.#66;	//  scala/Predef$.refArrayOps:([Ljava/lang/Object;)Lscala/collection/mutable/ArrayOps;
const #68 = Asciz	scala/reflect/ScalaBeanInfo$$anonfun$1$$anonfun$apply$1;
const #69 = class	#68;	//  scala/reflect/ScalaBeanInfo$$anonfun$1$$anonfun$apply$1
const #70 = Asciz	(Lscala/reflect/ScalaBeanInfo$$anonfun$1;Ljava/lang/reflect/Method;)V;
const #71 = NameAndType	#14:#70;//  "<init>":(Lscala/reflect/ScalaBeanInfo$$anonfun$1;Ljava/lang/reflect/Method;)V
const #72 = Method	#69.#71;	//  scala/reflect/ScalaBeanInfo$$anonfun$1$$anonfun$apply$1."<init>":(Lscala/reflect/ScalaBeanInfo$$anonfun$1;Ljava/lang/reflect/Method;)V
const #73 = Asciz	scala/collection/IndexedSeqLike;
const #74 = class	#73;	//  scala/collection/IndexedSeqLike
const #75 = Asciz	exists;
const #76 = Asciz	(Lscala/Function1;)Z;
const #77 = NameAndType	#75:#76;//  exists:(Lscala/Function1;)Z
const #78 = InterfaceMethod	#74.#77;	//  scala/collection/IndexedSeqLike.exists:(Lscala/Function1;)Z
const #79 = Asciz	m$1;
const #80 = Asciz	Ljava/lang/reflect/Method;;
const #81 = Asciz	andThen;
const #82 = Asciz	(Lscala/Function1;)Lscala/Function1;;
const #83 = Asciz	(Lscala/Function1;Lscala/Function1;)Lscala/Function1;;
const #84 = NameAndType	#81:#83;//  andThen:(Lscala/Function1;Lscala/Function1;)Lscala/Function1;
const #85 = Method	#27.#84;	//  scala/Function1$class.andThen:(Lscala/Function1;Lscala/Function1;)Lscala/Function1;
const #86 = Asciz	g;
const #87 = Asciz	Lscala/Function1;;
const #88 = Asciz	compose;
const #89 = NameAndType	#88:#83;//  compose:(Lscala/Function1;Lscala/Function1;)Lscala/Function1;
const #90 = Method	#27.#89;	//  scala/Function1$class.compose:(Lscala/Function1;Lscala/Function1;)Lscala/Function1;
const #91 = Asciz	toString;
const #92 = Asciz	()Ljava/lang/String;;
const #93 = Asciz	(Lscala/Function1;)Ljava/lang/String;;
const #94 = NameAndType	#91:#93;//  toString:(Lscala/Function1;)Ljava/lang/String;
const #95 = Method	#27.#94;	//  scala/Function1$class.toString:(Lscala/Function1;)Ljava/lang/String;
const #96 = Asciz	Scala;
const #97 = Asciz	InnerClasses;
const #98 = Asciz	$anonfun$1;
const #99 = Asciz	$anonfun$apply$1;
const #100 = Asciz	scala/Function1;
const #101 = class	#100;	//  scala/Function1
const #102 = Asciz	scala/ScalaObject;
const #103 = class	#102;	//  scala/ScalaObject
const #104 = Asciz	java/io/Serializable;
const #105 = class	#104;	//  java/io/Serializable

{
public static final long serialVersionUID;

public static {};
  Code:
   Stack=2, Locals=0, Args_size=0
   0:	lconst_0
   1:	putstatic	#11; //Field serialVersionUID:J
   4:	return

public scala.reflect.ScalaBeanInfo$$anonfun$1(scala.reflect.ScalaBeanInfo);
  Code:
   Stack=2, Locals=2, Args_size=2
   0:	aload_1
   1:	ifnonnull	12
   4:	new	#18; //class java/lang/NullPointerException
   7:	dup
   8:	invokespecial	#20; //Method java/lang/NullPointerException."<init>":()V
   11:	athrow
   12:	aload_0
   13:	aload_1
   14:	putfield	#22; //Field $outer:Lscala/reflect/ScalaBeanInfo;
   17:	aload_0
   18:	invokespecial	#25; //Method java/lang/Object."<init>":()V
   21:	aload_0
   22:	invokestatic	#31; //Method scala/Function1$class.$init$:(Lscala/Function1;)V
   25:	return
  LineNumberTable: 
   line 28: 0

  LocalVariableTable: 
   Start  Length  Slot  Name   Signature
   0      26      0    this       Lscala/reflect/ScalaBeanInfo$$anonfun$1;
   0      26      1    $outer       Lscala/reflect/ScalaBeanInfo;


public final java.lang.Object apply(java.lang.Object);
  Code:
   Stack=2, Locals=4, Args_size=2
   0:	aload_0
   1:	getfield	#22; //Field $outer:Lscala/reflect/ScalaBeanInfo;
   4:	astore_3
   5:	aload_0
   6:	aload_1
   7:	checkcast	#38; //class java/lang/reflect/Method
   10:	invokevirtual	#41; //Method apply:(Ljava/lang/reflect/Method;)Z
   13:	istore_2
   14:	iload_2
   15:	invokestatic	#47; //Method scala/runtime/BoxesRunTime.boxToBoolean:(Z)Ljava/lang/Boolean;
   18:	areturn
  LineNumberTable: 
   line 28: 0

  LocalVariableTable: 
   Start  Length  Slot  Name   Signature
   0      19      0    this       Lscala/reflect/ScalaBeanInfo$$anonfun$1;
   5      14      1    v1       Ljava/lang/Object;


public final boolean apply(java.lang.reflect.Method);
  Code:
   Stack=5, Locals=3, Args_size=2
   0:	aload_0
   1:	getfield	#22; //Field $outer:Lscala/reflect/ScalaBeanInfo;
   4:	astore_2
   5:	getstatic	#55; //Field scala/Predef$.MODULE$:Lscala/Predef$;
   8:	aload_0
   9:	getfield	#22; //Field $outer:Lscala/reflect/ScalaBeanInfo;
   12:	getfield	#61; //Field scala/reflect/ScalaBeanInfo.scala$reflect$ScalaBeanInfo$$methods:[Ljava/lang/String;
   15:	checkcast	#63; //class "[Ljava/lang/Object;"
   18:	invokevirtual	#67; //Method scala/Predef$.refArrayOps:([Ljava/lang/Object;)Lscala/collection/mutable/ArrayOps;
   21:	new	#69; //class scala/reflect/ScalaBeanInfo$$anonfun$1$$anonfun$apply$1
   24:	dup
   25:	aload_0
   26:	aload_1
   27:	invokespecial	#72; //Method scala/reflect/ScalaBeanInfo$$anonfun$1$$anonfun$apply$1."<init>":(Lscala/reflect/ScalaBeanInfo$$anonfun$1;Ljava/lang/reflect/Method;)V
   30:	invokeinterface	#78,  2; //InterfaceMethod scala/collection/IndexedSeqLike.exists:(Lscala/Function1;)Z
   35:	ireturn
  LineNumberTable: 
   line 28: 0

  LocalVariableTable: 
   Start  Length  Slot  Name   Signature
   0      36      0    this       Lscala/reflect/ScalaBeanInfo$$anonfun$1;
   5      31      1    m$1       Ljava/lang/reflect/Method;


public scala.Function1 andThen(scala.Function1);
  Code:
   Stack=2, Locals=2, Args_size=2
   0:	aload_0
   1:	aload_1
   2:	invokestatic	#85; //Method scala/Function1$class.andThen:(Lscala/Function1;Lscala/Function1;)Lscala/Function1;
   5:	areturn
  LineNumberTable: 
   line 28: 0

  LocalVariableTable: 
   Start  Length  Slot  Name   Signature
   0      6      0    this       Lscala/reflect/ScalaBeanInfo$$anonfun$1;
   0      6      1    g       Lscala/Function1;


public scala.Function1 compose(scala.Function1);
  Code:
   Stack=2, Locals=2, Args_size=2
   0:	aload_0
   1:	aload_1
   2:	invokestatic	#90; //Method scala/Function1$class.compose:(Lscala/Function1;Lscala/Function1;)Lscala/Function1;
   5:	areturn
  LineNumberTable: 
   line 28: 0

  LocalVariableTable: 
   Start  Length  Slot  Name   Signature
   0      6      0    this       Lscala/reflect/ScalaBeanInfo$$anonfun$1;
   0      6      1    g       Lscala/Function1;


public java.lang.String toString();
  Code:
   Stack=1, Locals=1, Args_size=1
   0:	aload_0
   1:	invokestatic	#95; //Method scala/Function1$class.toString:(Lscala/Function1;)Ljava/lang/String;
   4:	areturn
  LineNumberTable: 
   line 28: 0


}

