Compiled from "ScalaBeanInfo.scala"
public final class scala.reflect.ScalaBeanInfo$$anonfun$1 extends scala.runtime.AbstractFunction1 implements java.io.Serializable
  SourceFile: "ScalaBeanInfo.scala"
  Scala: length = 0x
   
  InnerClass: 
   public final $anonfun$1=class scala/reflect/ScalaBeanInfo$$anonfun$1 of class scala/reflect/ScalaBeanInfo
   public final $anonfun$apply$1=class scala/reflect/ScalaBeanInfo$$anonfun$1$$anonfun$apply$1 of class scala/reflect/ScalaBeanInfo$$anonfun$1
  minor version: 0
  major version: 49
  Constant pool:
Asciz	SourceFile;
Asciz	ScalaBeanInfo.scala;
Asciz	<clinit>;
Asciz	()V;
Asciz	Code;
Asciz	serialVersionUID;
Asciz	J;
Asciz	scala/reflect/ScalaBeanInfo$$anonfun$1;
class	scala/reflect/ScalaBeanInfo$$anonfun$1
NameAndType	serialVersionUID:J
Field	scala/reflect/ScalaBeanInfo$$anonfun$1.serialVersionUID:J
Asciz	$outer;
Asciz	Lscala/reflect/ScalaBeanInfo;;
Asciz	<init>;
Asciz	(Lscala/reflect/ScalaBeanInfo;)V;
Asciz	LineNumberTable;
Asciz	java/lang/NullPointerException;
class	java/lang/NullPointerException
NameAndType	"<init>":()V
Method	java/lang/NullPointerException."<init>":()V
NameAndType	$outer:Lscala/reflect/ScalaBeanInfo;
Field	scala/reflect/ScalaBeanInfo$$anonfun$1.$outer:Lscala/reflect/ScalaBeanInfo;
Asciz	scala/runtime/AbstractFunction1;
class	scala/runtime/AbstractFunction1
Method	scala/runtime/AbstractFunction1."<init>":()V
Asciz	this;
Asciz	Lscala/reflect/ScalaBeanInfo$$anonfun$1;;
Asciz	LocalVariableTable;
Asciz	apply;
Asciz	(Ljava/lang/Object;)Ljava/lang/Object;;
Asciz	java/lang/reflect/Method;
class	java/lang/reflect/Method
Asciz	(Ljava/lang/reflect/Method;)Z;
NameAndType	apply:(Ljava/lang/reflect/Method;)Z
Method	scala/reflect/ScalaBeanInfo$$anonfun$1.apply:(Ljava/lang/reflect/Method;)Z
Asciz	scala/runtime/BoxesRunTime;
class	scala/runtime/BoxesRunTime
Asciz	boxToBoolean;
Asciz	(Z)Ljava/lang/Boolean;;
NameAndType	boxToBoolean:(Z)Ljava/lang/Boolean;
Method	scala/runtime/BoxesRunTime.boxToBoolean:(Z)Ljava/lang/Boolean;
Asciz	v1;
Asciz	Ljava/lang/Object;;
Asciz	scala/Predef$;
class	scala/Predef$
Asciz	MODULE$;
Asciz	Lscala/Predef$;;
NameAndType	MODULE$:Lscala/Predef$;
Field	scala/Predef$.MODULE$:Lscala/Predef$;
Asciz	scala/reflect/ScalaBeanInfo;
class	scala/reflect/ScalaBeanInfo
Asciz	scala$reflect$ScalaBeanInfo$$methods;
Asciz	[Ljava/lang/String;;
NameAndType	scala$reflect$ScalaBeanInfo$$methods:[Ljava/lang/String;
Field	scala/reflect/ScalaBeanInfo.scala$reflect$ScalaBeanInfo$$methods:[Ljava/lang/String;
Asciz	[Ljava/lang/Object;;
class	"[Ljava/lang/Object;"
Asciz	refArrayOps;
Asciz	([Ljava/lang/Object;)Lscala/collection/mutable/ArrayOps;;
NameAndType	refArrayOps:([Ljava/lang/Object;)Lscala/collection/mutable/ArrayOps;
Method	scala/Predef$.refArrayOps:([Ljava/lang/Object;)Lscala/collection/mutable/ArrayOps;
Asciz	scala/reflect/ScalaBeanInfo$$anonfun$1$$anonfun$apply$1;
class	scala/reflect/ScalaBeanInfo$$anonfun$1$$anonfun$apply$1
Asciz	(Lscala/reflect/ScalaBeanInfo$$anonfun$1;Ljava/lang/reflect/Method;)V;
NameAndType	"<init>":(Lscala/reflect/ScalaBeanInfo$$anonfun$1;Ljava/lang/reflect/Method;)V
Method	scala/reflect/ScalaBeanInfo$$anonfun$1$$anonfun$apply$1."<init>":(Lscala/reflect/ScalaBeanInfo$$anonfun$1;Ljava/lang/reflect/Method;)V
Asciz	scala/collection/IndexedSeqLike;
class	scala/collection/IndexedSeqLike
Asciz	exists;
Asciz	(Lscala/Function1;)Z;
NameAndType	exists:(Lscala/Function1;)Z
InterfaceMethod	scala/collection/IndexedSeqLike.exists:(Lscala/Function1;)Z
Asciz	m$1;
Asciz	Ljava/lang/reflect/Method;;
Asciz	Scala;
Asciz	InnerClasses;
Asciz	$anonfun$1;
Asciz	$anonfun$apply$1;
Asciz	java/io/Serializable;
class	java/io/Serializable

{
public static final long serialVersionUID;
  Signature: J

private final scala.reflect.ScalaBeanInfo $outer;
  Signature: Lscala/reflect/ScalaBeanInfo;

public static {};
  Signature: ()V
  Code:
   Stack=2, Locals=0, Args_size=0
	lconst_0
	putstatic	Field serialVersionUID:J
	return
  Labels:

public scala.reflect.ScalaBeanInfo$$anonfun$1(scala.reflect.ScalaBeanInfo);
  Signature: (Lscala/reflect/ScalaBeanInfo;)V
  Code:
   Stack=2, Locals=2, Args_size=2
	aload_1
	ifnonnull	l1 // aload_0
	new	class java/lang/NullPointerException
	dup
	invokespecial	Method java/lang/NullPointerException."<init>":()V
	athrow
l1	aload_0
	aload_1
	putfield	Field $outer:Lscala/reflect/ScalaBeanInfo;
	aload_0
	invokespecial	Method scala/runtime/AbstractFunction1."<init>":()V
	return
  Labels:
   	l1 = 12 // aload_0
  LocalVariableTable: 
   Start  Length  Slot  Name   Signature
   0      22      0    this       Lscala/reflect/ScalaBeanInfo$$anonfun$1;
   0      22      1    $outer       Lscala/reflect/ScalaBeanInfo;


public final java.lang.Object apply(java.lang.Object);
  Signature: (Ljava/lang/Object;)Ljava/lang/Object;
  Code:
   Stack=2, Locals=3, Args_size=2
	aload_0
	aload_1
	checkcast	class java/lang/reflect/Method
	invokevirtual	Method apply:(Ljava/lang/reflect/Method;)Z
	istore_2
	iload_2
	invokestatic	Method scala/runtime/BoxesRunTime.boxToBoolean:(Z)Ljava/lang/Boolean;
	areturn
  Labels:
  LocalVariableTable: 
   Start  Length  Slot  Name   Signature
   0      14      0    this       Lscala/reflect/ScalaBeanInfo$$anonfun$1;
   0      14      1    v1       Ljava/lang/Object;


public final boolean apply(java.lang.reflect.Method);
  Signature: (Ljava/lang/reflect/Method;)Z
  Code:
   Stack=5, Locals=2, Args_size=2
	getstatic	Field scala/Predef$.MODULE$:Lscala/Predef$;
	aload_0
	getfield	Field $outer:Lscala/reflect/ScalaBeanInfo;
	getfield	Field scala/reflect/ScalaBeanInfo.scala$reflect$ScalaBeanInfo$$methods:[Ljava/lang/String;
	checkcast	class "[Ljava/lang/Object;"
	invokevirtual	Method scala/Predef$.refArrayOps:([Ljava/lang/Object;)Lscala/collection/mutable/ArrayOps;
	new	class scala/reflect/ScalaBeanInfo$$anonfun$1$$anonfun$apply$1
	dup
	aload_0
	aload_1
	invokespecial	Method scala/reflect/ScalaBeanInfo$$anonfun$1$$anonfun$apply$1."<init>":(Lscala/reflect/ScalaBeanInfo$$anonfun$1;Ljava/lang/reflect/Method;)V
	invokeinterface	InterfaceMethod scala/collection/IndexedSeqLike.exists:(Lscala/Function1;)Z
	ireturn
  Labels:
  LocalVariableTable: 
   Start  Length  Slot  Name   Signature
   0      31      0    this       Lscala/reflect/ScalaBeanInfo$$anonfun$1;
   0      31      1    m$1       Ljava/lang/reflect/Method;


}

