Compiled from "ScalaBeanInfo.scala"
public abstract class scala.reflect.ScalaBeanInfo extends java.beans.SimpleBeanInfo implements scala.ScalaObject
  SourceFile: "ScalaBeanInfo.scala"
  ScalaSig: length = 0x264
   05 00 60 06 08 01 02 FFFFFF84 FFFFFF80 FFFFFF80 FFFFFF81 00 07 02 0D 53
   63 61 6C 61 42 65 61 6E 49 6E 66 6F 0A 02 03 04
   01 07 72 65 66 6C 65 63 74 0A 01 05 01 05 73 63
   61 6C 61 03 00 13 03 00 08 10 10 02 09 0E 0D 01
   0A 0A 02 0B 0C 01 05 62 65 61 6E 73 0A 01 0D 01
   04 6A 61 76 61 09 02 0F 0A 02 0E 53 69 6D 70 6C
   65 42 65 61 6E 49 6E 66 6F 10 02 11 12 0D 01 04
   09 02 13 04 02 0B 53 63 61 6C 61 4F 62 6A 65 63
   74 08 08 15 00 FFFFFF82 FFFFFF80 FFFFFFA0 FFFFFF80 04 16 01 05 63 6C 61
   7A 7A 30 02 17 1F 10 03 18 1B 1D 0D 01 19 0A 02
   1A 0C 01 04 6C 61 6E 67 09 02 1C 19 02 05 43 6C
   61 73 73 10 02 1E 1F 0C 00 04 08 20 00 FFFFFF84 FFFFFF80 FFFFFF80
   FFFFFF82 00 21 02 03 5F 24 31 11 02 22 25 10 02 11 23
   09 02 24 04 02 07 4E 6F 74 68 69 6E 67 10 02 11
   26 09 02 27 04 02 03 41 6E 79 08 08 29 00 FFFFFF82 FFFFFF80
   FFFFFFA0 FFFFFF80 04 2A 01 05 70 72 6F 70 73 10 03 11 2B 2D
   09 02 2C 04 02 05 41 72 72 61 79 10 02 2E 31 0E
   02 11 2F 09 02 30 04 01 06 50 72 65 64 65 66 09
   02 32 33 02 06 53 74 72 69 6E 67 0A 02 30 04 08
   08 35 00 FFFFFF82 FFFFFF80 FFFFFFA0 FFFFFF80 04 2A 01 07 6D 65 74 68 6F
   64 73 08 05 37 00 FFFFFF84 00 38 01 06 3C 69 6E 69 74
   3E 14 04 39 3B 40 41 10 02 3A 00 0D 01 02 08 05
   15 36 FFFFFFC0 00 3C 30 02 3D 3F 10 03 18 1B 3E 10 02
   1E 3F 04 08 20 36 FFFFFF84 FFFFFF80 FFFFFF80 FFFFFF82 00 21 08 05 29 36
   FFFFFFC0 00 2A 08 05 35 36 FFFFFFC0 00 2A 08 07 43 00 FFFFFFC2 FFFFFF80
   FFFFFF84 04 44 01 02 70 64 15 01 45 10 03 11 2B 46 10
   02 09 47 09 02 48 0A 02 12 50 72 6F 70 65 72 74
   79 44 65 73 63 72 69 70 74 6F 72 08 06 4A 00 FFFFFFA0
   FFFFFF80 04 45 01 03 70 64 20 08 07 4C 00 FFFFFFC2 FFFFFF80 FFFFFF84 04
   4D 01 02 6D 64 15 01 4E 10 03 11 2B 4F 10 02 09
   50 09 02 51 0A 02 10 4D 65 74 68 6F 64 44 65 73
   63 72 69 70 74 6F 72 08 06 53 00 FFFFFFA0 FFFFFF80 04 4E 01
   03 6D 64 20 08 05 55 00 FFFFFF84 20 56 01 16 67 65 74
   50 72 6F 70 65 72 74 79 44 65 73 63 72 69 70 74
   6F 72 73 14 01 45 08 05 58 00 FFFFFF84 20 59 01 14 67
   65 74 4D 65 74 68 6F 64 44 65 73 63 72 69 70 74
   6F 72 73 14 01 4E 08 05 5B 00 FFFFFF84 04 5C 01 04 69
   6E 69 74 15 01 5D 10 02 11 5E 09 02 5F 04 02 04
   55 6E 69 74 
  InnerClass: 
   public final #119= #65 of #19; //$anonfun$2=class scala/reflect/ScalaBeanInfo$$anonfun$2 of class scala/reflect/ScalaBeanInfo
   public final #120= #54 of #19; //$anonfun$1=class scala/reflect/ScalaBeanInfo$$anonfun$1 of class scala/reflect/ScalaBeanInfo
   public #121= #88 of #59; //WithFilter=class scala/collection/TraversableLike$WithFilter of class scala/collection/TraversableLike
  minor version: 0
  major version: 49
  Constant pool:
const #1 = Asciz	SourceFile;
const #2 = Asciz	ScalaBeanInfo.scala;
const #3 = Asciz	md;
const #4 = Asciz	[Ljava/beans/MethodDescriptor;;
const #5 = Asciz	pd;
const #6 = Asciz	[Ljava/beans/PropertyDescriptor;;
const #7 = Asciz	scala$reflect$ScalaBeanInfo$$methods;
const #8 = Asciz	[Ljava/lang/String;;
const #9 = Asciz	props;
const #10 = Asciz	clazz;
const #11 = Asciz	Ljava/lang/Class;;
const #12 = Asciz	Ljava/lang/Class<*>;;
const #13 = Asciz	Signature;
const #14 = Asciz	<init>;
const #15 = Asciz	(Ljava/lang/Class;[Ljava/lang/String;[Ljava/lang/String;)V;
const #16 = Asciz	Code;
const #17 = Asciz	LineNumberTable;
const #18 = Asciz	scala/reflect/ScalaBeanInfo;
const #19 = class	#18;	//  scala/reflect/ScalaBeanInfo
const #20 = NameAndType	#10:#11;//  clazz:Ljava/lang/Class;
const #21 = Field	#19.#20;	//  scala/reflect/ScalaBeanInfo.clazz:Ljava/lang/Class;
const #22 = NameAndType	#9:#8;//  props:[Ljava/lang/String;
const #23 = Field	#19.#22;	//  scala/reflect/ScalaBeanInfo.props:[Ljava/lang/String;
const #24 = NameAndType	#7:#8;//  scala$reflect$ScalaBeanInfo$$methods:[Ljava/lang/String;
const #25 = Field	#19.#24;	//  scala/reflect/ScalaBeanInfo.scala$reflect$ScalaBeanInfo$$methods:[Ljava/lang/String;
const #26 = Asciz	java/beans/SimpleBeanInfo;
const #27 = class	#26;	//  java/beans/SimpleBeanInfo
const #28 = Asciz	()V;
const #29 = NameAndType	#14:#28;//  "<init>":()V
const #30 = Method	#27.#29;	//  java/beans/SimpleBeanInfo."<init>":()V
const #31 = Asciz	java/beans/PropertyDescriptor;
const #32 = class	#31;	//  java/beans/PropertyDescriptor
const #33 = NameAndType	#5:#6;//  pd:[Ljava/beans/PropertyDescriptor;
const #34 = Field	#19.#33;	//  scala/reflect/ScalaBeanInfo.pd:[Ljava/beans/PropertyDescriptor;
const #35 = Asciz	scala/Predef$;
const #36 = class	#35;	//  scala/Predef$
const #37 = Asciz	MODULE$;
const #38 = Asciz	Lscala/Predef$;;
const #39 = NameAndType	#37:#38;//  MODULE$:Lscala/Predef$;
const #40 = Field	#36.#39;	//  scala/Predef$.MODULE$:Lscala/Predef$;
const #41 = Asciz	java/lang/Class;
const #42 = class	#41;	//  java/lang/Class
const #43 = Asciz	getMethods;
const #44 = Asciz	()[Ljava/lang/reflect/Method;;
const #45 = NameAndType	#43:#44;//  getMethods:()[Ljava/lang/reflect/Method;
const #46 = Method	#42.#45;	//  java/lang/Class.getMethods:()[Ljava/lang/reflect/Method;
const #47 = Asciz	[Ljava/lang/Object;;
const #48 = class	#47;	//  "[Ljava/lang/Object;"
const #49 = Asciz	refArrayOps;
const #50 = Asciz	([Ljava/lang/Object;)Lscala/collection/mutable/ArrayOps;;
const #51 = NameAndType	#49:#50;//  refArrayOps:([Ljava/lang/Object;)Lscala/collection/mutable/ArrayOps;
const #52 = Method	#36.#51;	//  scala/Predef$.refArrayOps:([Ljava/lang/Object;)Lscala/collection/mutable/ArrayOps;
const #53 = Asciz	scala/reflect/ScalaBeanInfo$$anonfun$1;
const #54 = class	#53;	//  scala/reflect/ScalaBeanInfo$$anonfun$1
const #55 = Asciz	(Lscala/reflect/ScalaBeanInfo;)V;
const #56 = NameAndType	#14:#55;//  "<init>":(Lscala/reflect/ScalaBeanInfo;)V
const #57 = Method	#54.#56;	//  scala/reflect/ScalaBeanInfo$$anonfun$1."<init>":(Lscala/reflect/ScalaBeanInfo;)V
const #58 = Asciz	scala/collection/TraversableLike;
const #59 = class	#58;	//  scala/collection/TraversableLike
const #60 = Asciz	withFilter;
const #61 = Asciz	(Lscala/Function1;)Lscala/collection/TraversableLike$WithFilter;;
const #62 = NameAndType	#60:#61;//  withFilter:(Lscala/Function1;)Lscala/collection/TraversableLike$WithFilter;
const #63 = InterfaceMethod	#59.#62;	//  scala/collection/TraversableLike.withFilter:(Lscala/Function1;)Lscala/collection/TraversableLike$WithFilter;
const #64 = Asciz	scala/reflect/ScalaBeanInfo$$anonfun$2;
const #65 = class	#64;	//  scala/reflect/ScalaBeanInfo$$anonfun$2
const #66 = Method	#65.#56;	//  scala/reflect/ScalaBeanInfo$$anonfun$2."<init>":(Lscala/reflect/ScalaBeanInfo;)V
const #67 = Asciz	scala/Array$;
const #68 = class	#67;	//  scala/Array$
const #69 = Asciz	Lscala/Array$;;
const #70 = NameAndType	#37:#69;//  MODULE$:Lscala/Array$;
const #71 = Field	#68.#70;	//  scala/Array$.MODULE$:Lscala/Array$;
const #72 = Asciz	scala/reflect/ClassManifest$;
const #73 = class	#72;	//  scala/reflect/ClassManifest$
const #74 = Asciz	Lscala/reflect/ClassManifest$;;
const #75 = NameAndType	#37:#74;//  MODULE$:Lscala/reflect/ClassManifest$;
const #76 = Field	#73.#75;	//  scala/reflect/ClassManifest$.MODULE$:Lscala/reflect/ClassManifest$;
const #77 = Asciz	java/beans/MethodDescriptor;
const #78 = class	#77;	//  java/beans/MethodDescriptor
const #79 = Asciz	classType;
const #80 = Asciz	(Ljava/lang/Class;)Lscala/reflect/ClassManifest;;
const #81 = NameAndType	#79:#80;//  classType:(Ljava/lang/Class;)Lscala/reflect/ClassManifest;
const #82 = Method	#73.#81;	//  scala/reflect/ClassManifest$.classType:(Ljava/lang/Class;)Lscala/reflect/ClassManifest;
const #83 = Asciz	canBuildFrom;
const #84 = Asciz	(Lscala/reflect/ClassManifest;)Lscala/collection/generic/CanBuildFrom;;
const #85 = NameAndType	#83:#84;//  canBuildFrom:(Lscala/reflect/ClassManifest;)Lscala/collection/generic/CanBuildFrom;
const #86 = Method	#68.#85;	//  scala/Array$.canBuildFrom:(Lscala/reflect/ClassManifest;)Lscala/collection/generic/CanBuildFrom;
const #87 = Asciz	scala/collection/TraversableLike$WithFilter;
const #88 = class	#87;	//  scala/collection/TraversableLike$WithFilter
const #89 = Asciz	map;
const #90 = Asciz	(Lscala/Function1;Lscala/collection/generic/CanBuildFrom;)Ljava/lang/Object;;
const #91 = NameAndType	#89:#90;//  map:(Lscala/Function1;Lscala/collection/generic/CanBuildFrom;)Ljava/lang/Object;
const #92 = Method	#88.#91;	//  scala/collection/TraversableLike$WithFilter.map:(Lscala/Function1;Lscala/collection/generic/CanBuildFrom;)Ljava/lang/Object;
const #93 = class	#4;	//  "[Ljava/beans/MethodDescriptor;"
const #94 = NameAndType	#3:#4;//  md:[Ljava/beans/MethodDescriptor;
const #95 = Field	#19.#94;	//  scala/reflect/ScalaBeanInfo.md:[Ljava/beans/MethodDescriptor;
const #96 = Asciz	init;
const #97 = NameAndType	#96:#28;//  init:()V
const #98 = Method	#19.#97;	//  scala/reflect/ScalaBeanInfo.init:()V
const #99 = Asciz	this;
const #100 = Asciz	Lscala/reflect/ScalaBeanInfo;;
const #101 = Asciz	methods;
const #102 = Asciz	LocalVariableTable;
const #103 = Asciz	(Ljava/lang/Class<*>;[Ljava/lang/String;[Ljava/lang/String;)V;
const #104 = Asciz	()[Ljava/beans/PropertyDescriptor;;
const #105 = NameAndType	#5:#104;//  pd:()[Ljava/beans/PropertyDescriptor;
const #106 = Method	#19.#105;	//  scala/reflect/ScalaBeanInfo.pd:()[Ljava/beans/PropertyDescriptor;
const #107 = Asciz	(Ljava/lang/String;Ljava/lang/Class;Ljava/lang/String;Ljava/lang/String;)V;
const #108 = NameAndType	#14:#107;//  "<init>":(Ljava/lang/String;Ljava/lang/Class;Ljava/lang/String;Ljava/lang/String;)V
const #109 = Method	#32.#108;	//  java/beans/PropertyDescriptor."<init>":(Ljava/lang/String;Ljava/lang/Class;Ljava/lang/String;Ljava/lang/String;)V
const #110 = Asciz	i;
const #111 = Asciz	I;
const #112 = Asciz	getMethodDescriptors;
const #113 = Asciz	()[Ljava/beans/MethodDescriptor;;
const #114 = NameAndType	#3:#113;//  md:()[Ljava/beans/MethodDescriptor;
const #115 = Method	#19.#114;	//  scala/reflect/ScalaBeanInfo.md:()[Ljava/beans/MethodDescriptor;
const #116 = Asciz	getPropertyDescriptors;
const #117 = Asciz	ScalaSig;
const #118 = Asciz	InnerClasses;
const #119 = Asciz	$anonfun$2;
const #120 = Asciz	$anonfun$1;
const #121 = Asciz	WithFilter;
const #122 = Asciz	scala/ScalaObject;
const #123 = class	#122;	//  scala/ScalaObject

{
public final java.lang.String[] scala$reflect$ScalaBeanInfo$$methods;

public scala.reflect.ScalaBeanInfo(java.lang.Class, java.lang.String[], java.lang.String[]);
  Code:
   Stack=6, Locals=4, Args_size=4
   0:	aload_0
   1:	aload_1
   2:	putfield	#21; //Field clazz:Ljava/lang/Class;
   5:	aload_0
   6:	aload_2
   7:	putfield	#23; //Field props:[Ljava/lang/String;
   10:	aload_0
   11:	aload_3
   12:	putfield	#25; //Field scala$reflect$ScalaBeanInfo$$methods:[Ljava/lang/String;
   15:	aload_0
   16:	invokespecial	#30; //Method java/beans/SimpleBeanInfo."<init>":()V
   19:	aload_0
   20:	aload_2
   21:	arraylength
   22:	iconst_3
   23:	idiv
   24:	anewarray	#32; //class java/beans/PropertyDescriptor
   27:	putfield	#34; //Field pd:[Ljava/beans/PropertyDescriptor;
   30:	aload_0
   31:	getstatic	#40; //Field scala/Predef$.MODULE$:Lscala/Predef$;
   34:	aload_1
   35:	invokevirtual	#46; //Method java/lang/Class.getMethods:()[Ljava/lang/reflect/Method;
   38:	checkcast	#48; //class "[Ljava/lang/Object;"
   41:	invokevirtual	#52; //Method scala/Predef$.refArrayOps:([Ljava/lang/Object;)Lscala/collection/mutable/ArrayOps;
   44:	new	#54; //class scala/reflect/ScalaBeanInfo$$anonfun$1
   47:	dup
   48:	aload_0
   49:	invokespecial	#57; //Method scala/reflect/ScalaBeanInfo$$anonfun$1."<init>":(Lscala/reflect/ScalaBeanInfo;)V
   52:	invokeinterface	#63,  2; //InterfaceMethod scala/collection/TraversableLike.withFilter:(Lscala/Function1;)Lscala/collection/TraversableLike$WithFilter;
   57:	new	#65; //class scala/reflect/ScalaBeanInfo$$anonfun$2
   60:	dup
   61:	aload_0
   62:	invokespecial	#66; //Method scala/reflect/ScalaBeanInfo$$anonfun$2."<init>":(Lscala/reflect/ScalaBeanInfo;)V
   65:	getstatic	#71; //Field scala/Array$.MODULE$:Lscala/Array$;
   68:	getstatic	#76; //Field scala/reflect/ClassManifest$.MODULE$:Lscala/reflect/ClassManifest$;
   71:	ldc	#78; //class java/beans/MethodDescriptor
   73:	invokevirtual	#82; //Method scala/reflect/ClassManifest$.classType:(Ljava/lang/Class;)Lscala/reflect/ClassManifest;
   76:	invokevirtual	#86; //Method scala/Array$.canBuildFrom:(Lscala/reflect/ClassManifest;)Lscala/collection/generic/CanBuildFrom;
   79:	invokevirtual	#92; //Method scala/collection/TraversableLike$WithFilter.map:(Lscala/Function1;Lscala/collection/generic/CanBuildFrom;)Ljava/lang/Object;
   82:	checkcast	#93; //class "[Ljava/beans/MethodDescriptor;"
   85:	putfield	#95; //Field md:[Ljava/beans/MethodDescriptor;
   88:	aload_0
   89:	invokespecial	#98; //Method init:()V
   92:	return
  LineNumberTable: 
   line 20: 0
   line 21: 5
   line 22: 10
   line 20: 15
   line 26: 19
   line 27: 30
   line 28: 31
   line 27: 85
   line 31: 88

  LocalVariableTable: 
   Start  Length  Slot  Name   Signature
   0      93      0    this       Lscala/reflect/ScalaBeanInfo;
   0      93      1    clazz       Ljava/lang/Class;
   0      93      2    props       [Ljava/lang/String;
   0      93      3    methods       [Ljava/lang/String;

  Signature: length = 0x2
   00 67 

public java.beans.MethodDescriptor[] getMethodDescriptors();
  Code:
   Stack=1, Locals=1, Args_size=1
   0:	aload_0
   1:	invokespecial	#115; //Method md:()[Ljava/beans/MethodDescriptor;
   4:	areturn
  LineNumberTable: 
   line 34: 0


public java.beans.PropertyDescriptor[] getPropertyDescriptors();
  Code:
   Stack=1, Locals=1, Args_size=1
   0:	aload_0
   1:	invokespecial	#106; //Method pd:()[Ljava/beans/PropertyDescriptor;
   4:	areturn
  LineNumberTable: 
   line 33: 0


}

