Compiled from "ScalaBeanInfo.scala"
public final class scala.reflect.ScalaBeanInfo$$anonfun$1$$anonfun$apply$1 extends java.lang.Object implements scala.Function1,scala.ScalaObject,java.io.Serializable
  SourceFile: "ScalaBeanInfo.scala"
  Scala: length = 0x
   
  InnerClass: 
   public final $anonfun$1=class scala/reflect/ScalaBeanInfo$$anonfun$1 of class scala/reflect/ScalaBeanInfo
   public final $anonfun$apply$1=class scala/reflect/ScalaBeanInfo$$anonfun$1$$anonfun$apply$1 of class scala/reflect/ScalaBeanInfo$$anonfun$1
  minor version: 0
  major version: 49
  Constant pool:
Asciz	SourceFile;
Asciz	ScalaBeanInfo.scala;
Asciz	<clinit>;
Asciz	()V;
Asciz	Code;
Asciz	serialVersionUID;
Asciz	J;
Asciz	scala/reflect/ScalaBeanInfo$$anonfun$1$$anonfun$apply$1;
class	scala/reflect/ScalaBeanInfo$$anonfun$1$$anonfun$apply$1
NameAndType	serialVersionUID:J
Field	scala/reflect/ScalaBeanInfo$$anonfun$1$$anonfun$apply$1.serialVersionUID:J
Asciz	m$1;
Asciz	Ljava/lang/reflect/Method;;
Asciz	<init>;
Asciz	(Lscala/reflect/ScalaBeanInfo$$anonfun$1;Ljava/lang/reflect/Method;)V;
Asciz	LineNumberTable;
NameAndType	m$1:Ljava/lang/reflect/Method;
Field	scala/reflect/ScalaBeanInfo$$anonfun$1$$anonfun$apply$1.m$1:Ljava/lang/reflect/Method;
Asciz	java/lang/Object;
class	java/lang/Object
NameAndType	"<init>":()V
Method	java/lang/Object."<init>":()V
Asciz	scala/Function1$class;
class	scala/Function1$class
Asciz	$init$;
Asciz	(Lscala/Function1;)V;
NameAndType	$init$:(Lscala/Function1;)V
Method	scala/Function1$class.$init$:(Lscala/Function1;)V
Asciz	this;
Asciz	Lscala/reflect/ScalaBeanInfo$$anonfun$1$$anonfun$apply$1;;
Asciz	$outer;
Asciz	Lscala/reflect/ScalaBeanInfo$$anonfun$1;;
Asciz	LocalVariableTable;
Asciz	apply;
Asciz	(Ljava/lang/Object;)Ljava/lang/Object;;
Asciz	java/lang/String;
class	java/lang/String
Asciz	(Ljava/lang/String;)Z;
NameAndType	apply:(Ljava/lang/String;)Z
Method	scala/reflect/ScalaBeanInfo$$anonfun$1$$anonfun$apply$1.apply:(Ljava/lang/String;)Z
Asciz	scala/runtime/BoxesRunTime;
class	scala/runtime/BoxesRunTime
Asciz	boxToBoolean;
Asciz	(Z)Ljava/lang/Boolean;;
NameAndType	boxToBoolean:(Z)Ljava/lang/Boolean;
Method	scala/runtime/BoxesRunTime.boxToBoolean:(Z)Ljava/lang/Boolean;
Asciz	v1;
Asciz	Ljava/lang/Object;;
Asciz	java/lang/reflect/Method;
class	java/lang/reflect/Method
Asciz	getName;
Asciz	()Ljava/lang/String;;
NameAndType	getName:()Ljava/lang/String;
Method	java/lang/reflect/Method.getName:()Ljava/lang/String;
Asciz	equals;
Asciz	(Ljava/lang/Object;)Z;
NameAndType	equals:(Ljava/lang/Object;)Z
Method	java/lang/Object.equals:(Ljava/lang/Object;)Z
Asciz	andThen;
Asciz	(Lscala/Function1;)Lscala/Function1;;
Asciz	(Lscala/Function1;Lscala/Function1;)Lscala/Function1;;
NameAndType	andThen:(Lscala/Function1;Lscala/Function1;)Lscala/Function1;
Method	scala/Function1$class.andThen:(Lscala/Function1;Lscala/Function1;)Lscala/Function1;
Asciz	g;
Asciz	Lscala/Function1;;
Asciz	compose;
NameAndType	compose:(Lscala/Function1;Lscala/Function1;)Lscala/Function1;
Method	scala/Function1$class.compose:(Lscala/Function1;Lscala/Function1;)Lscala/Function1;
Asciz	toString;
Asciz	(Lscala/Function1;)Ljava/lang/String;;
NameAndType	toString:(Lscala/Function1;)Ljava/lang/String;
Method	scala/Function1$class.toString:(Lscala/Function1;)Ljava/lang/String;
Asciz	Scala;
Asciz	InnerClasses;
Asciz	scala/reflect/ScalaBeanInfo$$anonfun$1;
class	scala/reflect/ScalaBeanInfo$$anonfun$1
Asciz	scala/reflect/ScalaBeanInfo;
class	scala/reflect/ScalaBeanInfo
Asciz	$anonfun$1;
Asciz	$anonfun$apply$1;
Asciz	scala/Function1;
class	scala/Function1
Asciz	scala/ScalaObject;
class	scala/ScalaObject
Asciz	java/io/Serializable;
class	java/io/Serializable

{
public static final long serialVersionUID;
  Signature: J

private final java.lang.reflect.Method m$1;
  Signature: Ljava/lang/reflect/Method;

public static {};
  Signature: ()V
  Code:
   Stack=2, Locals=0, Args_size=0
	lconst_0
	putstatic	Field serialVersionUID:J
	return
  Labels:

public scala.reflect.ScalaBeanInfo$$anonfun$1$$anonfun$apply$1(scala.reflect.ScalaBeanInfo$$anonfun$1, java.lang.reflect.Method);
  Signature: (Lscala/reflect/ScalaBeanInfo$$anonfun$1;Ljava/lang/reflect/Method;)V
  Code:
   Stack=2, Locals=3, Args_size=3
	aload_0
	aload_2
	putfield	Field m$1:Ljava/lang/reflect/Method;
	aload_0
	invokespecial	Method java/lang/Object."<init>":()V
	aload_0
	invokestatic	Method scala/Function1$class.$init$:(Lscala/Function1;)V
	return
  Labels:
  LocalVariableTable: 
   Start  Length  Slot  Name   Signature
   0      14      0    this       Lscala/reflect/ScalaBeanInfo$$anonfun$1$$anonfun$apply$1;
   0      14      1    $outer       Lscala/reflect/ScalaBeanInfo$$anonfun$1;


public final java.lang.Object apply(java.lang.Object);
  Signature: (Ljava/lang/Object;)Ljava/lang/Object;
  Code:
   Stack=2, Locals=3, Args_size=2
	aload_0
	aload_1
	checkcast	class java/lang/String
	invokevirtual	Method apply:(Ljava/lang/String;)Z
	istore_2
	iload_2
	invokestatic	Method scala/runtime/BoxesRunTime.boxToBoolean:(Z)Ljava/lang/Boolean;
	areturn
  Labels:
  LocalVariableTable: 
   Start  Length  Slot  Name   Signature
   0      14      0    this       Lscala/reflect/ScalaBeanInfo$$anonfun$1$$anonfun$apply$1;
   0      14      1    v1       Ljava/lang/Object;


public final boolean apply(java.lang.String);
  Signature: (Ljava/lang/String;)Z
  Code:
   Stack=2, Locals=3, Args_size=2
	aload_1
	aload_0
	getfield	Field m$1:Ljava/lang/reflect/Method;
	invokevirtual	Method java/lang/reflect/Method.getName:()Ljava/lang/String;
	astore_2
	dup
	ifnonnull	l1 // aload_2
	pop
	aload_2
	ifnull	l2 // iconst_1
	goto	l3 // iconst_0
l1	aload_2
	invokevirtual	Method java/lang/Object.equals:(Ljava/lang/Object;)Z
	ifeq	l3 // iconst_0
l2	iconst_1
	goto	l4 // ireturn
l3	iconst_0
l4	ireturn
  Labels:
   	l1 = 21 // aload_2
   	l2 = 28 // iconst_1
   	l3 = 32 // iconst_0
   	l4 = 33 // ireturn

public scala.Function1 andThen(scala.Function1);
  Signature: (Lscala/Function1;)Lscala/Function1;
  Code:
   Stack=2, Locals=2, Args_size=2
	aload_0
	aload_1
	invokestatic	Method scala/Function1$class.andThen:(Lscala/Function1;Lscala/Function1;)Lscala/Function1;
	areturn
  Labels:
  LocalVariableTable: 
   Start  Length  Slot  Name   Signature
   0      6      0    this       Lscala/reflect/ScalaBeanInfo$$anonfun$1$$anonfun$apply$1;
   0      6      1    g       Lscala/Function1;


public scala.Function1 compose(scala.Function1);
  Signature: (Lscala/Function1;)Lscala/Function1;
  Code:
   Stack=2, Locals=2, Args_size=2
	aload_0
	aload_1
	invokestatic	Method scala/Function1$class.compose:(Lscala/Function1;Lscala/Function1;)Lscala/Function1;
	areturn
  Labels:
  LocalVariableTable: 
   Start  Length  Slot  Name   Signature
   0      6      0    this       Lscala/reflect/ScalaBeanInfo$$anonfun$1$$anonfun$apply$1;
   0      6      1    g       Lscala/Function1;


public java.lang.String toString();
  Signature: ()Ljava/lang/String;
  Code:
   Stack=1, Locals=1, Args_size=1
	aload_0
	invokestatic	Method scala/Function1$class.toString:(Lscala/Function1;)Ljava/lang/String;
	areturn
  Labels:

}

