Compiled from "ScalaBeanInfo.scala"
public final class scala.reflect.ScalaBeanInfo$$anonfun$2 extends java.lang.Object implements scala.Function1,scala.ScalaObject,java.io.Serializable
  SourceFile: "ScalaBeanInfo.scala"
  Scala: length = 0x
   
  InnerClass: 
   public final $anonfun$2=class scala/reflect/ScalaBeanInfo$$anonfun$2 of class scala/reflect/ScalaBeanInfo
  minor version: 0
  major version: 49
  Constant pool:
Asciz	SourceFile;
Asciz	ScalaBeanInfo.scala;
Asciz	<clinit>;
Asciz	()V;
Asciz	Code;
Asciz	serialVersionUID;
Asciz	J;
Asciz	scala/reflect/ScalaBeanInfo$$anonfun$2;
class	scala/reflect/ScalaBeanInfo$$anonfun$2
NameAndType	serialVersionUID:J
Field	scala/reflect/ScalaBeanInfo$$anonfun$2.serialVersionUID:J
Asciz	<init>;
Asciz	(Lscala/reflect/ScalaBeanInfo;)V;
Asciz	LineNumberTable;
Asciz	java/lang/Object;
class	java/lang/Object
NameAndType	"<init>":()V
Method	java/lang/Object."<init>":()V
Asciz	scala/Function1$class;
class	scala/Function1$class
Asciz	$init$;
Asciz	(Lscala/Function1;)V;
NameAndType	$init$:(Lscala/Function1;)V
Method	scala/Function1$class.$init$:(Lscala/Function1;)V
Asciz	this;
Asciz	Lscala/reflect/ScalaBeanInfo$$anonfun$2;;
Asciz	$outer;
Asciz	Lscala/reflect/ScalaBeanInfo;;
Asciz	LocalVariableTable;
Asciz	apply;
Asciz	(Ljava/lang/Object;)Ljava/lang/Object;;
Asciz	java/lang/reflect/Method;
class	java/lang/reflect/Method
Asciz	(Ljava/lang/reflect/Method;)Ljava/beans/MethodDescriptor;;
NameAndType	apply:(Ljava/lang/reflect/Method;)Ljava/beans/MethodDescriptor;
Method	scala/reflect/ScalaBeanInfo$$anonfun$2.apply:(Ljava/lang/reflect/Method;)Ljava/beans/MethodDescriptor;
Asciz	v1;
Asciz	Ljava/lang/Object;;
Asciz	java/beans/MethodDescriptor;
class	java/beans/MethodDescriptor
Asciz	(Ljava/lang/reflect/Method;)V;
NameAndType	"<init>":(Ljava/lang/reflect/Method;)V
Method	java/beans/MethodDescriptor."<init>":(Ljava/lang/reflect/Method;)V
Asciz	m;
Asciz	Ljava/lang/reflect/Method;;
Asciz	andThen;
Asciz	(Lscala/Function1;)Lscala/Function1;;
Asciz	(Lscala/Function1;Lscala/Function1;)Lscala/Function1;;
NameAndType	andThen:(Lscala/Function1;Lscala/Function1;)Lscala/Function1;
Method	scala/Function1$class.andThen:(Lscala/Function1;Lscala/Function1;)Lscala/Function1;
Asciz	g;
Asciz	Lscala/Function1;;
Asciz	compose;
NameAndType	compose:(Lscala/Function1;Lscala/Function1;)Lscala/Function1;
Method	scala/Function1$class.compose:(Lscala/Function1;Lscala/Function1;)Lscala/Function1;
Asciz	toString;
Asciz	()Ljava/lang/String;;
Asciz	(Lscala/Function1;)Ljava/lang/String;;
NameAndType	toString:(Lscala/Function1;)Ljava/lang/String;
Method	scala/Function1$class.toString:(Lscala/Function1;)Ljava/lang/String;
Asciz	Scala;
Asciz	InnerClasses;
Asciz	scala/reflect/ScalaBeanInfo;
class	scala/reflect/ScalaBeanInfo
Asciz	$anonfun$2;
Asciz	scala/Function1;
class	scala/Function1
Asciz	scala/ScalaObject;
class	scala/ScalaObject
Asciz	java/io/Serializable;
class	java/io/Serializable

{
public static final long serialVersionUID;
  Signature: J

public static {};
  Signature: ()V
  Code:
   Stack=2, Locals=0, Args_size=0
	lconst_0
	putstatic	Field serialVersionUID:J
	return
  Labels:

public scala.reflect.ScalaBeanInfo$$anonfun$2(scala.reflect.ScalaBeanInfo);
  Signature: (Lscala/reflect/ScalaBeanInfo;)V
  Code:
   Stack=1, Locals=2, Args_size=2
	aload_0
	invokespecial	Method java/lang/Object."<init>":()V
	aload_0
	invokestatic	Method scala/Function1$class.$init$:(Lscala/Function1;)V
	return
  Labels:
  LocalVariableTable: 
   Start  Length  Slot  Name   Signature
   0      9      0    this       Lscala/reflect/ScalaBeanInfo$$anonfun$2;
   0      9      1    $outer       Lscala/reflect/ScalaBeanInfo;


public final java.lang.Object apply(java.lang.Object);
  Signature: (Ljava/lang/Object;)Ljava/lang/Object;
  Code:
   Stack=2, Locals=2, Args_size=2
	aload_0
	aload_1
	checkcast	class java/lang/reflect/Method
	invokevirtual	Method apply:(Ljava/lang/reflect/Method;)Ljava/beans/MethodDescriptor;
	areturn
  Labels:
  LocalVariableTable: 
   Start  Length  Slot  Name   Signature
   0      9      0    this       Lscala/reflect/ScalaBeanInfo$$anonfun$2;
   0      9      1    v1       Ljava/lang/Object;


public final java.beans.MethodDescriptor apply(java.lang.reflect.Method);
  Signature: (Ljava/lang/reflect/Method;)Ljava/beans/MethodDescriptor;
  Code:
   Stack=3, Locals=2, Args_size=2
	new	class java/beans/MethodDescriptor
	dup
	aload_1
	invokespecial	Method java/beans/MethodDescriptor."<init>":(Ljava/lang/reflect/Method;)V
	areturn
  Labels:
  LocalVariableTable: 
   Start  Length  Slot  Name   Signature
   0      9      0    this       Lscala/reflect/ScalaBeanInfo$$anonfun$2;
   0      9      1    m       Ljava/lang/reflect/Method;


public scala.Function1 andThen(scala.Function1);
  Signature: (Lscala/Function1;)Lscala/Function1;
  Code:
   Stack=2, Locals=2, Args_size=2
	aload_0
	aload_1
	invokestatic	Method scala/Function1$class.andThen:(Lscala/Function1;Lscala/Function1;)Lscala/Function1;
	areturn
  Labels:
  LocalVariableTable: 
   Start  Length  Slot  Name   Signature
   0      6      0    this       Lscala/reflect/ScalaBeanInfo$$anonfun$2;
   0      6      1    g       Lscala/Function1;


public scala.Function1 compose(scala.Function1);
  Signature: (Lscala/Function1;)Lscala/Function1;
  Code:
   Stack=2, Locals=2, Args_size=2
	aload_0
	aload_1
	invokestatic	Method scala/Function1$class.compose:(Lscala/Function1;Lscala/Function1;)Lscala/Function1;
	areturn
  Labels:
  LocalVariableTable: 
   Start  Length  Slot  Name   Signature
   0      6      0    this       Lscala/reflect/ScalaBeanInfo$$anonfun$2;
   0      6      1    g       Lscala/Function1;


public java.lang.String toString();
  Signature: ()Ljava/lang/String;
  Code:
   Stack=1, Locals=1, Args_size=1
	aload_0
	invokestatic	Method scala/Function1$class.toString:(Lscala/Function1;)Ljava/lang/String;
	areturn
  Labels:

}

