Compiled from "Tree.scala"
public class scala.reflect.Select extends scala.reflect.Tree implements scala.ScalaObject,scala.Product,java.io.Serializable
  SourceFile: "Tree.scala"
  ScalaSig: length = 0x3B1
   05 00 FFFFFF81 0D 06 08 01 02 FFFFFF84 FFFFFF80 FFFFFF80 FFFFFF80 40 07 02 06
   53 65 6C 65 63 74 0A 02 03 04 01 07 72 65 66 6C
   65 63 74 0A 01 05 01 05 73 63 61 6C 61 03 00 13
   04 00 08 0C 10 10 02 09 0A 0D 01 02 09 02 0B 02
   02 04 54 72 65 65 10 02 0D 0E 0D 01 04 09 02 0F
   04 02 0B 53 63 61 6C 61 4F 62 6A 65 63 74 10 02
   0D 11 09 02 12 04 02 07 50 72 6F 64 75 63 74 08
   08 14 00 FFFFFF82 FFFFFFCA FFFFFF80 FFFFFF84 00 15 01 04 71 75 61 6C 15
   01 08 08 08 17 00 FFFFFF82 FFFFFF88 FFFFFFA0 FFFFFF80 04 08 01 05 71 75
   61 6C 20 08 08 19 00 FFFFFF82 FFFFFFCA FFFFFF80 FFFFFF84 00 1A 01 03 73
   79 6D 15 01 1B 10 02 09 1C 09 02 1D 02 02 06 53
   79 6D 62 6F 6C 08 08 1F 00 FFFFFF82 FFFFFF88 FFFFFFA0 FFFFFF80 04 1B 01
   04 73 79 6D 20 08 05 21 00 FFFFFF84 00 22 01 06 3C 69
   6E 69 74 3E 14 03 23 24 25 10 02 09 00 08 05 14
   20 FFFFFFC0 00 08 08 05 19 20 FFFFFFC0 00 1B 08 07 27 00 FFFFFF81
   FFFFFF80 FFFFFF84 00 28 01 04 63 6F 70 79 14 03 23 29 2A 08
   07 14 26 FFFFFF90 FFFFFF80 FFFFFFC0 00 08 08 07 19 26 FFFFFF90 FFFFFF80 FFFFFFC0 00
   1B 08 07 2C 00 FFFFFF91 FFFFFF80 FFFFFF84 00 2D 01 0E 63 6F 70 79
   24 64 65 66 61 75 6C 74 24 31 15 01 2E 2A 02 08
   2F 2B 01 30 10 02 31 36 0D 01 32 0A 02 33 34 01
   09 75 6E 63 68 65 63 6B 65 64 0A 02 35 04 01 0A
   61 6E 6E 6F 74 61 74 69 6F 6E 09 02 37 32 02 11
   75 6E 63 68 65 63 6B 65 64 56 61 72 69 61 6E 63
   65 08 07 39 00 FFFFFF91 FFFFFF80 FFFFFF84 00 3A 01 0E 63 6F 70 79
   24 64 65 66 61 75 6C 74 24 32 15 01 3B 2A 02 1B
   2F 08 08 3D 00 FFFFFF84 FFFFFF80 FFFFFF80 FFFFFF84 20 3E 01 08 68 61 73
   68 43 6F 64 65 14 01 3F 10 02 0D 40 09 02 41 04
   02 03 49 6E 74 08 08 43 00 FFFFFF84 FFFFFF80 FFFFFF80 FFFFFF84 20 44 01
   08 74 6F 53 74 72 69 6E 67 14 01 45 10 02 46 49
   0E 02 0D 47 09 02 48 04 01 06 50 72 65 64 65 66
   09 02 4A 4B 02 06 53 74 72 69 6E 67 0A 02 48 04
   08 08 4D 00 FFFFFF84 FFFFFF80 FFFFFF80 FFFFFF84 20 4E 01 06 65 71 75 61
   6C 73 14 02 4F 52 10 02 0D 50 09 02 51 04 02 07
   42 6F 6F 6C 65 61 6E 08 07 53 4C FFFFFF81 FFFFFF80 FFFFFFC0 00 54
   01 03 78 24 31 10 02 0D 55 09 02 56 04 02 03 41
   6E 79 08 08 58 00 FFFFFF84 FFFFFF80 FFFFFF80 FFFFFF84 20 59 01 0D 70 72
   6F 64 75 63 74 50 72 65 66 69 78 15 01 5A 10 02
   5B 60 0D 01 5C 0A 02 5D 5E 01 04 6C 61 6E 67 0A
   01 5F 01 04 6A 61 76 61 09 02 4A 5C 08 08 62 00
   FFFFFF84 FFFFFF80 FFFFFF80 FFFFFF84 20 63 01 0C 70 72 6F 64 75 63 74 41
   72 69 74 79 15 01 3F 08 08 65 00 FFFFFF84 FFFFFF80 FFFFFF80 FFFFFF84 20
   66 01 0E 70 72 6F 64 75 63 74 45 6C 65 6D 65 6E
   74 14 02 54 67 08 07 53 64 FFFFFF81 FFFFFF80 FFFFFFC0 00 3F 08 08
   69 00 FFFFFF84 FFFFFF80 FFFFFF80 FFFFFF84 20 6A 01 08 63 61 6E 45 71 75
   61 6C 14 02 4F 6B 08 07 53 68 FFFFFF81 FFFFFF80 FFFFFFC0 00 54 28
   02 00 6D 10 02 0D 6E 09 02 6F 04 02 0C 73 65 72
   69 61 6C 69 7A 61 62 6C 65 07 07 71 02 FFFFFF81 FFFFFF80 FFFFFF88
   02 72 01 06 53 65 6C 65 63 74 10 02 09 73 06 08
   01 02 FFFFFF84 FFFFFF81 FFFFFF80 FFFFFF88 02 74 13 04 73 75 78 0C 10 02
   5B 76 09 02 77 5C 02 06 4F 62 6A 65 63 74 10 05
   0D 79 08 1B 23 09 02 7A 04 02 09 46 75 6E 63 74
   69 6F 6E 32 08 05 21 73 FFFFFF84 00 7C 14 01 72 08 07
   7E 73 FFFFFF81 FFFFFF80 FFFFFF84 40 7F 01 05 61 70 70 6C 79 14 05
   23 FFFFFF81 00 FFFFFF81 01 08 05 14 7D FFFFFFC0 00 08 08 05 19 7D
   FFFFFFC0 00 1B 08 09 FFFFFF81 03 73 FFFFFF81 FFFFFF80 FFFFFF84 40 FFFFFF81 04 01 07
   75 6E 61 70 70 6C 79 14 04 FFFFFF81 05 FFFFFF81 0B 10 05 0D
   FFFFFF81 06 FFFFFF81 08 09 03 FFFFFF81 07 04 02 04 53 6F 6D 65 10
   05 0D FFFFFF81 09 08 1B 09 03 FFFFFF81 0A 04 02 06 54 75 70
   6C 65 32 08 07 FFFFFF81 0C FFFFFF81 02 FFFFFFC0 00 23 01 03 78 24
   30 
  minor version: 0
  major version: 49
  Constant pool:
Asciz	SourceFile;
Asciz	Tree.scala;
Asciz	tupled;
Asciz	()Lscala/Function1;;
Asciz	Code;
Asciz	scala/reflect/Select$;
class	scala/reflect/Select$
Asciz	MODULE$;
Asciz	Lscala/reflect/Select$;;
NameAndType	MODULE$:Lscala/reflect/Select$;
Field	scala/reflect/Select$.MODULE$:Lscala/reflect/Select$;
NameAndType	tupled:()Lscala/Function1;
Method	scala/reflect/Select$.tupled:()Lscala/Function1;
Asciz	curry;
NameAndType	curry:()Lscala/Function1;
Method	scala/reflect/Select$.curry:()Lscala/Function1;
Asciz	Deprecated;
Asciz	curried;
NameAndType	curried:()Lscala/Function1;
Method	scala/reflect/Select$.curried:()Lscala/Function1;
Asciz	sym;
Asciz	Lscala/reflect/Symbol;;
Asciz	qual;
Asciz	Lscala/reflect/Tree;;
Asciz	productIterator;
Asciz	()Lscala/collection/Iterator;;
Asciz	LineNumberTable;
Asciz	scala/Product$class;
class	scala/Product$class
Asciz	(Lscala/Product;)Lscala/collection/Iterator;;
NameAndType	productIterator:(Lscala/Product;)Lscala/collection/Iterator;
Method	scala/Product$class.productIterator:(Lscala/Product;)Lscala/collection/Iterator;
Asciz	productElements;
NameAndType	productElements:(Lscala/Product;)Lscala/collection/Iterator;
Method	scala/Product$class.productElements:(Lscala/Product;)Lscala/collection/Iterator;
Asciz	copy$default$2;
Asciz	()Lscala/reflect/Symbol;;
Asciz	scala/reflect/Select;
class	scala/reflect/Select
NameAndType	sym:()Lscala/reflect/Symbol;
Method	scala/reflect/Select.sym:()Lscala/reflect/Symbol;
Asciz	copy$default$1;
Asciz	()Lscala/reflect/Tree;;
NameAndType	qual:()Lscala/reflect/Tree;
Method	scala/reflect/Select.qual:()Lscala/reflect/Tree;
NameAndType	qual:Lscala/reflect/Tree;
Field	scala/reflect/Select.qual:Lscala/reflect/Tree;
NameAndType	sym:Lscala/reflect/Symbol;
Field	scala/reflect/Select.sym:Lscala/reflect/Symbol;
Asciz	copy;
Asciz	(Lscala/reflect/Tree;Lscala/reflect/Symbol;)Lscala/reflect/Select;;
Asciz	<init>;
Asciz	(Lscala/reflect/Tree;Lscala/reflect/Symbol;)V;
NameAndType	"<init>":(Lscala/reflect/Tree;Lscala/reflect/Symbol;)V
Method	scala/reflect/Select."<init>":(Lscala/reflect/Tree;Lscala/reflect/Symbol;)V
Asciz	this;
Asciz	Lscala/reflect/Select;;
Asciz	LocalVariableTable;
Asciz	hashCode;
Asciz	()I;
Asciz	scala/runtime/ScalaRunTime$;
class	scala/runtime/ScalaRunTime$
Asciz	Lscala/runtime/ScalaRunTime$;;
NameAndType	MODULE$:Lscala/runtime/ScalaRunTime$;
Field	scala/runtime/ScalaRunTime$.MODULE$:Lscala/runtime/ScalaRunTime$;
Asciz	_hashCode;
Asciz	(Lscala/Product;)I;
NameAndType	_hashCode:(Lscala/Product;)I
Method	scala/runtime/ScalaRunTime$._hashCode:(Lscala/Product;)I
Asciz	toString;
Asciz	()Ljava/lang/String;;
Asciz	_toString;
Asciz	(Lscala/Product;)Ljava/lang/String;;
NameAndType	_toString:(Lscala/Product;)Ljava/lang/String;
Method	scala/runtime/ScalaRunTime$._toString:(Lscala/Product;)Ljava/lang/String;
Asciz	equals;
Asciz	(Ljava/lang/Object;)Z;
Asciz	gd2$1;
Asciz	(Lscala/reflect/Tree;Lscala/reflect/Symbol;)Z;
NameAndType	gd2$1:(Lscala/reflect/Tree;Lscala/reflect/Symbol;)Z
Method	scala/reflect/Select.gd2$1:(Lscala/reflect/Tree;Lscala/reflect/Symbol;)Z
Asciz	scala/Equals;
class	scala/Equals
Asciz	canEqual;
NameAndType	canEqual:(Ljava/lang/Object;)Z
InterfaceMethod	scala/Equals.canEqual:(Ljava/lang/Object;)Z
Asciz	temp6;
Asciz	temp7;
Asciz	temp8;
Asciz	productPrefix;
Asciz	Select;
String	Select
Asciz	productArity;
Asciz	productElement;
Asciz	(I)Ljava/lang/Object;;
Asciz	java/lang/IndexOutOfBoundsException;
class	java/lang/IndexOutOfBoundsException
Asciz	scala/runtime/BoxesRunTime;
class	scala/runtime/BoxesRunTime
Asciz	boxToInteger;
Asciz	(I)Ljava/lang/Integer;;
NameAndType	boxToInteger:(I)Ljava/lang/Integer;
Method	scala/runtime/BoxesRunTime.boxToInteger:(I)Ljava/lang/Integer;
Asciz	java/lang/Object;
class	java/lang/Object
NameAndType	toString:()Ljava/lang/String;
Method	java/lang/Object.toString:()Ljava/lang/String;
Asciz	(Ljava/lang/String;)V;
NameAndType	"<init>":(Ljava/lang/String;)V
Method	java/lang/IndexOutOfBoundsException."<init>":(Ljava/lang/String;)V
NameAndType	equals:(Ljava/lang/Object;)Z
Method	java/lang/Object.equals:(Ljava/lang/Object;)Z
Asciz	scala/reflect/Tree;
class	scala/reflect/Tree
Asciz	()V;
NameAndType	"<init>":()V
Method	scala/reflect/Tree."<init>":()V
Asciz	$init$;
Asciz	(Lscala/Product;)V;
NameAndType	$init$:(Lscala/Product;)V
Method	scala/Product$class.$init$:(Lscala/Product;)V
Asciz	ScalaSig;
Asciz	scala/ScalaObject;
class	scala/ScalaObject
Asciz	scala/Product;
class	scala/Product
Asciz	java/io/Serializable;
class	java/io/Serializable

{
private final scala.reflect.Symbol sym;
  Signature: Lscala/reflect/Symbol;

private final scala.reflect.Tree qual;
  Signature: Lscala/reflect/Tree;

public static final scala.Function1 tupled();
  Signature: ()Lscala/Function1;
  Code:
   Stack=1, Locals=0, Args_size=0
	getstatic	Field scala/reflect/Select$.MODULE$:Lscala/reflect/Select$;
	invokevirtual	Method scala/reflect/Select$.tupled:()Lscala/Function1;
	areturn
  Labels:

public static final scala.Function1 curry();
  Signature: ()Lscala/Function1;
  Code:
   Stack=1, Locals=0, Args_size=0
	getstatic	Field scala/reflect/Select$.MODULE$:Lscala/reflect/Select$;
	invokevirtual	Method scala/reflect/Select$.curry:()Lscala/Function1;
	areturn
  Labels:
  Deprecated: true

public static final scala.Function1 curried();
  Signature: ()Lscala/Function1;
  Code:
   Stack=1, Locals=0, Args_size=0
	getstatic	Field scala/reflect/Select$.MODULE$:Lscala/reflect/Select$;
	invokevirtual	Method scala/reflect/Select$.curried:()Lscala/Function1;
	areturn
  Labels:

public scala.collection.Iterator productIterator();
  Signature: ()Lscala/collection/Iterator;
  Code:
   Stack=1, Locals=1, Args_size=1
	aload_0
	invokestatic	Method scala/Product$class.productIterator:(Lscala/Product;)Lscala/collection/Iterator;
	areturn
  Labels:

public scala.collection.Iterator productElements();
  Signature: ()Lscala/collection/Iterator;
  Code:
   Stack=1, Locals=1, Args_size=1
	aload_0
	invokestatic	Method scala/Product$class.productElements:(Lscala/Product;)Lscala/collection/Iterator;
	areturn
  Labels:
  Deprecated: true

public scala.reflect.Symbol copy$default$2();
  Signature: ()Lscala/reflect/Symbol;
  Code:
   Stack=1, Locals=1, Args_size=1
	aload_0
	invokevirtual	Method sym:()Lscala/reflect/Symbol;
	areturn
  Labels:

public scala.reflect.Tree copy$default$1();
  Signature: ()Lscala/reflect/Tree;
  Code:
   Stack=1, Locals=1, Args_size=1
	aload_0
	invokevirtual	Method qual:()Lscala/reflect/Tree;
	areturn
  Labels:

public scala.reflect.Tree qual();
  Signature: ()Lscala/reflect/Tree;
  Code:
   Stack=1, Locals=1, Args_size=1
	aload_0
	getfield	Field qual:Lscala/reflect/Tree;
	areturn
  Labels:

public scala.reflect.Symbol sym();
  Signature: ()Lscala/reflect/Symbol;
  Code:
   Stack=1, Locals=1, Args_size=1
	aload_0
	getfield	Field sym:Lscala/reflect/Symbol;
	areturn
  Labels:

public scala.reflect.Select copy(scala.reflect.Tree, scala.reflect.Symbol);
  Signature: (Lscala/reflect/Tree;Lscala/reflect/Symbol;)Lscala/reflect/Select;
  Code:
   Stack=4, Locals=3, Args_size=3
	new	class scala/reflect/Select
	dup
	aload_1
	aload_2
	invokespecial	Method "<init>":(Lscala/reflect/Tree;Lscala/reflect/Symbol;)V
	areturn
  Labels:
  LocalVariableTable: 
   Start  Length  Slot  Name   Signature
   0      10      0    this       Lscala/reflect/Select;
   0      10      1    qual       Lscala/reflect/Tree;
   0      10      2    sym       Lscala/reflect/Symbol;


public int hashCode();
  Signature: ()I
  Code:
   Stack=2, Locals=1, Args_size=1
	getstatic	Field scala/runtime/ScalaRunTime$.MODULE$:Lscala/runtime/ScalaRunTime$;
	aload_0
	invokevirtual	Method scala/runtime/ScalaRunTime$._hashCode:(Lscala/Product;)I
	ireturn
  Labels:

public java.lang.String toString();
  Signature: ()Ljava/lang/String;
  Code:
   Stack=2, Locals=1, Args_size=1
	getstatic	Field scala/runtime/ScalaRunTime$.MODULE$:Lscala/runtime/ScalaRunTime$;
	aload_0
	invokevirtual	Method scala/runtime/ScalaRunTime$._toString:(Lscala/Product;)Ljava/lang/String;
	areturn
  Labels:

public boolean equals(java.lang.Object);
  Signature: (Ljava/lang/Object;)Z
  Code:
   Stack=3, Locals=5, Args_size=2
	aload_0
	aload_1
	if_acmpeq	l1 // iconst_1
	aload_1
	instanceof	class scala/reflect/Select
	ifeq	l2 // iconst_0
	aload_1
	checkcast	class scala/reflect/Select
	astore_2
	aload_2
	invokevirtual	Method qual:()Lscala/reflect/Tree;
	astore_3
	aload_2
	invokevirtual	Method sym:()Lscala/reflect/Symbol;
	astore	4
	aload_0
	aload_3
	aload	4
	invokespecial	Method gd2$1:(Lscala/reflect/Tree;Lscala/reflect/Symbol;)Z
	ifeq	l3 // iconst_0
	aload_1
	checkcast	class scala/reflect/Select
	aload_0
	invokeinterface	InterfaceMethod scala/Equals.canEqual:(Ljava/lang/Object;)Z
	goto	l4 // ifeq
l3	iconst_0
	goto	l4 // ifeq
l2	iconst_0
l4	ifeq	l5 // iconst_0
l1	iconst_1
	goto	l6 // ireturn
l5	iconst_0
l6	ireturn
  Labels:
   	l3 = 51 // iconst_0
   	l2 = 55 // iconst_0
   	l4 = 56 // ifeq
   	l1 = 59 // iconst_1
   	l5 = 63 // iconst_0
   	l6 = 64 // ireturn
  LocalVariableTable: 
   Start  Length  Slot  Name   Signature
   0      65      0    this       Lscala/reflect/Select;
   17      38      2    temp6       Lscala/reflect/Select;
   22      33      3    temp7       Lscala/reflect/Tree;
   28      27      4    temp8       Lscala/reflect/Symbol;


public java.lang.String productPrefix();
  Signature: ()Ljava/lang/String;
  Code:
   Stack=1, Locals=1, Args_size=1
	ldc	String Select
	areturn
  Labels:

public int productArity();
  Signature: ()I
  Code:
   Stack=1, Locals=1, Args_size=1
	iconst_2
	ireturn
  Labels:

public java.lang.Object productElement(int);
  Signature: (I)Ljava/lang/Object;
  Code:
   Stack=3, Locals=2, Args_size=2
	iload_1
	tableswitch{ //0 to 1
		0: 46;
		1: 39;
		default: 24 }
	new	class java/lang/IndexOutOfBoundsException
	dup
	iload_1
	invokestatic	Method scala/runtime/BoxesRunTime.boxToInteger:(I)Ljava/lang/Integer;
	invokevirtual	Method java/lang/Object.toString:()Ljava/lang/String;
	invokespecial	Method java/lang/IndexOutOfBoundsException."<init>":(Ljava/lang/String;)V
	athrow
	aload_0
	invokevirtual	Method sym:()Lscala/reflect/Symbol;
	goto	l1 // areturn
	aload_0
	invokevirtual	Method qual:()Lscala/reflect/Tree;
l1	areturn
  Labels:
   	l1 = 50 // areturn

public boolean canEqual(java.lang.Object);
  Signature: (Ljava/lang/Object;)Z
  Code:
   Stack=1, Locals=2, Args_size=2
	aload_1
	instanceof	class scala/reflect/Select
	ireturn
  Labels:

private final boolean gd2$1(scala.reflect.Tree, scala.reflect.Symbol);
  Signature: (Lscala/reflect/Tree;Lscala/reflect/Symbol;)Z
  Code:
   Stack=2, Locals=5, Args_size=3
	aload_1
	aload_0
	invokevirtual	Method qual:()Lscala/reflect/Tree;
	astore_3
	dup
	ifnonnull	l1 // aload_3
	pop
	aload_3
	ifnull	l2 // aload_2
	goto	l3 // iconst_0
l1	aload_3
	invokevirtual	Method java/lang/Object.equals:(Ljava/lang/Object;)Z
	ifeq	l3 // iconst_0
l2	aload_2
	aload_0
	invokevirtual	Method sym:()Lscala/reflect/Symbol;
	astore	4
	dup
	ifnonnull	l4 // aload
	pop
	aload	4
	ifnull	l5 // iconst_1
	goto	l3 // iconst_0
l4	aload	4
	invokevirtual	Method java/lang/Object.equals:(Ljava/lang/Object;)Z
	ifeq	l3 // iconst_0
l5	iconst_1
	goto	l6 // ireturn
l3	iconst_0
l6	ireturn
  Labels:
   	l1 = 18 // aload_3
   	l2 = 25 // aload_2
   	l4 = 45 // aload
   	l5 = 53 // iconst_1
   	l3 = 57 // iconst_0
   	l6 = 58 // ireturn

public scala.reflect.Select(scala.reflect.Tree, scala.reflect.Symbol);
  Signature: (Lscala/reflect/Tree;Lscala/reflect/Symbol;)V
  Code:
   Stack=2, Locals=3, Args_size=3
	aload_0
	aload_1
	putfield	Field qual:Lscala/reflect/Tree;
	aload_0
	aload_2
	putfield	Field sym:Lscala/reflect/Symbol;
	aload_0
	invokespecial	Method scala/reflect/Tree."<init>":()V
	aload_0
	invokestatic	Method scala/Product$class.$init$:(Lscala/Product;)V
	return
  Labels:
  LocalVariableTable: 
   Start  Length  Slot  Name   Signature
   0      19      0    this       Lscala/reflect/Select;
   0      19      1    qual       Lscala/reflect/Tree;
   0      19      2    sym       Lscala/reflect/Symbol;


}

