Compiled from "Type.scala"
public final class scala.reflect.SingleType$ extends java.lang.Object implements scala.Function2,scala.ScalaObject
  SourceFile: "Type.scala"
  Scala: length = 0x
   
  minor version: 0
  major version: 49
  Constant pool:
Asciz	SourceFile;
Asciz	Type.scala;
Asciz	MODULE$;
Asciz	Lscala/reflect/SingleType$;;
Asciz	<clinit>;
Asciz	()V;
Asciz	Code;
Asciz	scala/reflect/SingleType$;
class	scala/reflect/SingleType$
Asciz	<init>;
NameAndType	"<init>":()V
Method	scala/reflect/SingleType$."<init>":()V
Asciz	toString;
Asciz	()Ljava/lang/String;;
Asciz	LineNumberTable;
Asciz	scala/Function2$class;
class	scala/Function2$class
Asciz	(Lscala/Function2;)Ljava/lang/String;;
NameAndType	toString:(Lscala/Function2;)Ljava/lang/String;
Method	scala/Function2$class.toString:(Lscala/Function2;)Ljava/lang/String;
Asciz	curried;
Asciz	()Lscala/Function1;;
Asciz	(Lscala/Function2;)Lscala/Function1;;
NameAndType	curried:(Lscala/Function2;)Lscala/Function1;
Method	scala/Function2$class.curried:(Lscala/Function2;)Lscala/Function1;
Asciz	curry;
NameAndType	curry:(Lscala/Function2;)Lscala/Function1;
Method	scala/Function2$class.curry:(Lscala/Function2;)Lscala/Function1;
Asciz	Deprecated;
Asciz	tupled;
NameAndType	tupled:(Lscala/Function2;)Lscala/Function1;
Method	scala/Function2$class.tupled:(Lscala/Function2;)Lscala/Function1;
Asciz	unapply;
Asciz	(Lscala/reflect/SingleType;)Lscala/Option;;
Asciz	scala/None$;
class	scala/None$
Asciz	Lscala/None$;;
NameAndType	MODULE$:Lscala/None$;
Field	scala/None$.MODULE$:Lscala/None$;
Asciz	scala/Some;
class	scala/Some
Asciz	scala/Tuple2;
class	scala/Tuple2
Asciz	scala/reflect/SingleType;
class	scala/reflect/SingleType
Asciz	pre;
Asciz	()Lscala/reflect/Type;;
NameAndType	pre:()Lscala/reflect/Type;
Method	scala/reflect/SingleType.pre:()Lscala/reflect/Type;
Asciz	sym;
Asciz	()Lscala/reflect/Symbol;;
NameAndType	sym:()Lscala/reflect/Symbol;
Method	scala/reflect/SingleType.sym:()Lscala/reflect/Symbol;
Asciz	(Ljava/lang/Object;Ljava/lang/Object;)V;
NameAndType	"<init>":(Ljava/lang/Object;Ljava/lang/Object;)V
Method	scala/Tuple2."<init>":(Ljava/lang/Object;Ljava/lang/Object;)V
Asciz	(Ljava/lang/Object;)V;
NameAndType	"<init>":(Ljava/lang/Object;)V
Method	scala/Some."<init>":(Ljava/lang/Object;)V
Asciz	this;
Asciz	x$0;
Asciz	Lscala/reflect/SingleType;;
Asciz	LocalVariableTable;
Asciz	apply;
Asciz	(Lscala/reflect/Type;Lscala/reflect/Symbol;)Lscala/reflect/SingleType;;
Asciz	(Lscala/reflect/Type;Lscala/reflect/Symbol;)V;
NameAndType	"<init>":(Lscala/reflect/Type;Lscala/reflect/Symbol;)V
Method	scala/reflect/SingleType."<init>":(Lscala/reflect/Type;Lscala/reflect/Symbol;)V
Asciz	Lscala/reflect/Type;;
Asciz	Lscala/reflect/Symbol;;
Asciz	(Ljava/lang/Object;Ljava/lang/Object;)Ljava/lang/Object;;
Asciz	scala/reflect/Type;
class	scala/reflect/Type
Asciz	scala/reflect/Symbol;
class	scala/reflect/Symbol
NameAndType	apply:(Lscala/reflect/Type;Lscala/reflect/Symbol;)Lscala/reflect/SingleType;
Method	scala/reflect/SingleType$.apply:(Lscala/reflect/Type;Lscala/reflect/Symbol;)Lscala/reflect/SingleType;
Asciz	v1;
Asciz	Ljava/lang/Object;;
Asciz	v2;
Asciz	java/lang/Object;
class	java/lang/Object
Method	java/lang/Object."<init>":()V
NameAndType	MODULE$:Lscala/reflect/SingleType$;
Field	scala/reflect/SingleType$.MODULE$:Lscala/reflect/SingleType$;
Asciz	$init$;
Asciz	(Lscala/Function2;)V;
NameAndType	$init$:(Lscala/Function2;)V
Method	scala/Function2$class.$init$:(Lscala/Function2;)V
Asciz	Scala;
Asciz	scala/Function2;
class	scala/Function2
Asciz	scala/ScalaObject;
class	scala/ScalaObject

{
public static final scala.reflect.SingleType$ MODULE$;
  Signature: Lscala/reflect/SingleType$;

public static {};
  Signature: ()V
  Code:
   Stack=1, Locals=0, Args_size=0
	new	class scala/reflect/SingleType$
	invokespecial	Method "<init>":()V
	return
  Labels:

public java.lang.String toString();
  Signature: ()Ljava/lang/String;
  Code:
   Stack=1, Locals=1, Args_size=1
	aload_0
	invokestatic	Method scala/Function2$class.toString:(Lscala/Function2;)Ljava/lang/String;
	areturn
  Labels:

public scala.Function1 curried();
  Signature: ()Lscala/Function1;
  Code:
   Stack=1, Locals=1, Args_size=1
	aload_0
	invokestatic	Method scala/Function2$class.curried:(Lscala/Function2;)Lscala/Function1;
	areturn
  Labels:

public scala.Function1 curry();
  Signature: ()Lscala/Function1;
  Code:
   Stack=1, Locals=1, Args_size=1
	aload_0
	invokestatic	Method scala/Function2$class.curry:(Lscala/Function2;)Lscala/Function1;
	areturn
  Labels:
  Deprecated: true

public scala.Function1 tupled();
  Signature: ()Lscala/Function1;
  Code:
   Stack=1, Locals=1, Args_size=1
	aload_0
	invokestatic	Method scala/Function2$class.tupled:(Lscala/Function2;)Lscala/Function1;
	areturn
  Labels:

public scala.Option unapply(scala.reflect.SingleType);
  Signature: (Lscala/reflect/SingleType;)Lscala/Option;
  Code:
   Stack=6, Locals=2, Args_size=2
	aload_1
	ifnonnull	l1 // new
	getstatic	Field scala/None$.MODULE$:Lscala/None$;
	goto	l2 // areturn
l1	new	class scala/Some
	dup
	new	class scala/Tuple2
	dup
	aload_1
	invokevirtual	Method scala/reflect/SingleType.pre:()Lscala/reflect/Type;
	aload_1
	invokevirtual	Method scala/reflect/SingleType.sym:()Lscala/reflect/Symbol;
	invokespecial	Method scala/Tuple2."<init>":(Ljava/lang/Object;Ljava/lang/Object;)V
	invokespecial	Method scala/Some."<init>":(Ljava/lang/Object;)V
l2	areturn
  Labels:
   	l1 = 10 // new
   	l2 = 32 // areturn
  LocalVariableTable: 
   Start  Length  Slot  Name   Signature
   0      33      0    this       Lscala/reflect/SingleType$;
   0      33      1    x$0       Lscala/reflect/SingleType;


public scala.reflect.SingleType apply(scala.reflect.Type, scala.reflect.Symbol);
  Signature: (Lscala/reflect/Type;Lscala/reflect/Symbol;)Lscala/reflect/SingleType;
  Code:
   Stack=4, Locals=3, Args_size=3
	new	class scala/reflect/SingleType
	dup
	aload_1
	aload_2
	invokespecial	Method scala/reflect/SingleType."<init>":(Lscala/reflect/Type;Lscala/reflect/Symbol;)V
	areturn
  Labels:
  LocalVariableTable: 
   Start  Length  Slot  Name   Signature
   0      10      0    this       Lscala/reflect/SingleType$;
   0      10      1    pre       Lscala/reflect/Type;
   0      10      2    sym       Lscala/reflect/Symbol;


public java.lang.Object apply(java.lang.Object, java.lang.Object);
  Signature: (Ljava/lang/Object;Ljava/lang/Object;)Ljava/lang/Object;
  Code:
   Stack=3, Locals=3, Args_size=3
	aload_0
	aload_1
	checkcast	class scala/reflect/Type
	aload_2
	checkcast	class scala/reflect/Symbol
	invokevirtual	Method apply:(Lscala/reflect/Type;Lscala/reflect/Symbol;)Lscala/reflect/SingleType;
	areturn
  Labels:
  LocalVariableTable: 
   Start  Length  Slot  Name   Signature
   0      13      0    this       Lscala/reflect/SingleType$;
   0      13      1    v1       Ljava/lang/Object;
   0      13      2    v2       Ljava/lang/Object;


private scala.reflect.SingleType$();
  Signature: ()V
  Code:
   Stack=1, Locals=1, Args_size=1
	aload_0
	invokespecial	Method java/lang/Object."<init>":()V
	aload_0
	putstatic	Field MODULE$:Lscala/reflect/SingleType$;
	aload_0
	invokestatic	Method scala/Function2$class.$init$:(Lscala/Function2;)V
	return
  Labels:

}

