Compiled from "Symbol.scala"
public abstract class scala.reflect.Symbol extends java.lang.Object implements scala.ScalaObject
  SourceFile: "Symbol.scala"
  ScalaSig: length = 0xF2
   05 00 2C 06 08 01 02 FFFFFF84 FFFFFF80 FFFFFF80 FFFFFF81 00 07 02 06 53
   79 6D 62 6F 6C 0A 02 03 04 01 07 72 65 66 6C 65
   63 74 0A 01 05 01 05 73 63 61 6C 61 03 00 13 03
   00 08 10 10 02 09 0E 0D 01 0A 0A 02 0B 0C 01 04
   6C 61 6E 67 0A 01 0D 01 04 6A 61 76 61 09 02 0F
   0A 02 06 4F 62 6A 65 63 74 10 02 11 12 0D 01 04
   09 02 13 04 02 0B 53 63 61 6C 61 4F 62 6A 65 63
   74 08 05 15 00 FFFFFF84 00 16 01 06 3C 69 6E 69 74 3E
   14 01 17 10 02 18 00 0D 01 02 08 07 1A 00 FFFFFFC2 FFFFFF80
   FFFFFF86 00 1B 01 05 6F 77 6E 65 72 15 01 17 08 07 1D
   00 FFFFFFC2 FFFFFF80 FFFFFF86 00 1E 01 04 6E 61 6D 65 15 01 1F 10
   02 20 23 0E 02 11 21 09 02 22 04 01 06 50 72 65
   64 65 66 09 02 24 25 02 06 53 74 72 69 6E 67 0A
   02 22 04 08 07 27 00 FFFFFFC2 FFFFFF80 FFFFFF86 00 28 01 03 74 70
   65 15 01 29 10 02 18 2A 09 02 2B 02 02 04 54 79
   70 65 
  minor version: 0
  major version: 49
  Constant pool:
const #1 = Asciz	SourceFile;
const #2 = Asciz	Symbol.scala;
const #3 = Asciz	<init>;
const #4 = Asciz	()V;
const #5 = Asciz	Code;
const #6 = Asciz	LineNumberTable;
const #7 = Asciz	java/lang/Object;
const #8 = class	#7;	//  java/lang/Object
const #9 = NameAndType	#3:#4;//  "<init>":()V
const #10 = Method	#8.#9;	//  java/lang/Object."<init>":()V
const #11 = Asciz	tpe;
const #12 = Asciz	()Lscala/reflect/Type;;
const #13 = Asciz	name;
const #14 = Asciz	()Ljava/lang/String;;
const #15 = Asciz	owner;
const #16 = Asciz	()Lscala/reflect/Symbol;;
const #17 = Asciz	ScalaSig;
const #18 = Asciz	scala/reflect/Symbol;
const #19 = class	#18;	//  scala/reflect/Symbol
const #20 = Asciz	scala/ScalaObject;
const #21 = class	#20;	//  scala/ScalaObject

{
public scala.reflect.Symbol();
  Code:
   Stack=1, Locals=1, Args_size=1
   0:	aload_0
   1:	invokespecial	#10; //Method java/lang/Object."<init>":()V
   4:	return
  LineNumberTable: 
   line 15: 0


public abstract scala.reflect.Type tpe();

public abstract java.lang.String name();

public abstract scala.reflect.Symbol owner();

}

