Compiled from "Tree.scala"
public final class scala.reflect.Template$ extends java.lang.Object implements scala.Function2,scala.ScalaObject
  SourceFile: "Tree.scala"
  Scala: length = 0x
   
  minor version: 0
  major version: 49
  Constant pool:
Asciz	SourceFile;
Asciz	Tree.scala;
Asciz	Scala;
Asciz	MODULE$;
Asciz	Lscala/reflect/Template$;;
Asciz	<clinit>;
Asciz	()V;
Asciz	Code;
Asciz	scala/reflect/Template$;
class	scala/reflect/Template$
Asciz	<init>;
NameAndType	"<init>":()V
Method	scala/reflect/Template$."<init>":()V
Asciz	LineNumberTable;
Asciz	java/lang/Object;
class	java/lang/Object
Method	java/lang/Object."<init>":()V
NameAndType	MODULE$:Lscala/reflect/Template$;
Field	scala/reflect/Template$.MODULE$:Lscala/reflect/Template$;
Asciz	scala/Function2$class;
class	scala/Function2$class
Asciz	$init$;
Asciz	(Lscala/Function2;)V;
NameAndType	$init$:(Lscala/Function2;)V
Method	scala/Function2$class.$init$:(Lscala/Function2;)V
Asciz	apply;
Asciz	(Ljava/lang/Object;Ljava/lang/Object;)Ljava/lang/Object;;
Asciz	scala/collection/immutable/List;
class	scala/collection/immutable/List
Asciz	(Lscala/collection/immutable/List;Lscala/collection/immutable/List;)Lscala/reflect/Template;;
NameAndType	apply:(Lscala/collection/immutable/List;Lscala/collection/immutable/List;)Lscala/reflect/Template;
Method	scala/reflect/Template$.apply:(Lscala/collection/immutable/List;Lscala/collection/immutable/List;)Lscala/reflect/Template;
Asciz	this;
Asciz	v1;
Asciz	Ljava/lang/Object;;
Asciz	v2;
Asciz	LocalVariableTable;
Asciz	scala/reflect/Template;
class	scala/reflect/Template
Asciz	(Lscala/collection/immutable/List;Lscala/collection/immutable/List;)V;
NameAndType	"<init>":(Lscala/collection/immutable/List;Lscala/collection/immutable/List;)V
Method	scala/reflect/Template."<init>":(Lscala/collection/immutable/List;Lscala/collection/immutable/List;)V
Asciz	parents;
Asciz	Lscala/collection/immutable/List;;
Asciz	body;
Asciz	unapply;
Asciz	(Lscala/reflect/Template;)Lscala/Some;;
Asciz	scala/Some;
class	scala/Some
Asciz	scala/Tuple2;
class	scala/Tuple2
Asciz	()Lscala/collection/immutable/List;;
NameAndType	parents:()Lscala/collection/immutable/List;
Method	scala/reflect/Template.parents:()Lscala/collection/immutable/List;
NameAndType	body:()Lscala/collection/immutable/List;
Method	scala/reflect/Template.body:()Lscala/collection/immutable/List;
Asciz	(Ljava/lang/Object;Ljava/lang/Object;)V;
NameAndType	"<init>":(Ljava/lang/Object;Ljava/lang/Object;)V
Method	scala/Tuple2."<init>":(Ljava/lang/Object;Ljava/lang/Object;)V
Asciz	(Ljava/lang/Object;)V;
NameAndType	"<init>":(Ljava/lang/Object;)V
Method	scala/Some."<init>":(Ljava/lang/Object;)V
Asciz	x$0;
Asciz	Lscala/reflect/Template;;
Asciz	curry;
Asciz	()Lscala/Function1;;
Asciz	(Lscala/Function2;)Lscala/Function1;;
NameAndType	curry:(Lscala/Function2;)Lscala/Function1;
Method	scala/Function2$class.curry:(Lscala/Function2;)Lscala/Function1;
Asciz	toString;
Asciz	()Ljava/lang/String;;
Asciz	(Lscala/Function2;)Ljava/lang/String;;
NameAndType	toString:(Lscala/Function2;)Ljava/lang/String;
Method	scala/Function2$class.toString:(Lscala/Function2;)Ljava/lang/String;
Asciz	scala/Function2;
class	scala/Function2
Asciz	scala/ScalaObject;
class	scala/ScalaObject

{
public static final scala.reflect.Template$ MODULE$;
  Signature: Lscala/reflect/Template$;

public static {};
  Signature: ()V
  Code:
   Stack=1, Locals=0, Args_size=0
	new	class scala/reflect/Template$
	invokespecial	Method "<init>":()V
	return
  Labels:

private scala.reflect.Template$();
  Signature: ()V
  Code:
   Stack=1, Locals=1, Args_size=1
	aload_0
	invokespecial	Method java/lang/Object."<init>":()V
	aload_0
	putstatic	Field MODULE$:Lscala/reflect/Template$;
	aload_0
	invokestatic	Method scala/Function2$class.$init$:(Lscala/Function2;)V
	return
  Labels:

public java.lang.Object apply(java.lang.Object, java.lang.Object);
  Signature: (Ljava/lang/Object;Ljava/lang/Object;)Ljava/lang/Object;
  Code:
   Stack=3, Locals=3, Args_size=3
	aload_0
	aload_1
	checkcast	class scala/collection/immutable/List
	aload_2
	checkcast	class scala/collection/immutable/List
	invokevirtual	Method apply:(Lscala/collection/immutable/List;Lscala/collection/immutable/List;)Lscala/reflect/Template;
	areturn
  Labels:
  LocalVariableTable: 
   Start  Length  Slot  Name   Signature
   0      13      0    this       Lscala/reflect/Template$;
   0      13      1    v1       Ljava/lang/Object;
   0      13      2    v2       Ljava/lang/Object;


public scala.reflect.Template apply(scala.collection.immutable.List, scala.collection.immutable.List);
  Signature: (Lscala/collection/immutable/List;Lscala/collection/immutable/List;)Lscala/reflect/Template;
  Code:
   Stack=4, Locals=3, Args_size=3
	new	class scala/reflect/Template
	dup
	aload_1
	aload_2
	invokespecial	Method scala/reflect/Template."<init>":(Lscala/collection/immutable/List;Lscala/collection/immutable/List;)V
	areturn
  Labels:
  LocalVariableTable: 
   Start  Length  Slot  Name   Signature
   0      10      0    this       Lscala/reflect/Template$;
   0      10      1    parents       Lscala/collection/immutable/List;
   0      10      2    body       Lscala/collection/immutable/List;


public scala.Some unapply(scala.reflect.Template);
  Signature: (Lscala/reflect/Template;)Lscala/Some;
  Code:
   Stack=6, Locals=2, Args_size=2
	new	class scala/Some
	dup
	new	class scala/Tuple2
	dup
	aload_1
	invokevirtual	Method scala/reflect/Template.parents:()Lscala/collection/immutable/List;
	aload_1
	invokevirtual	Method scala/reflect/Template.body:()Lscala/collection/immutable/List;
	invokespecial	Method scala/Tuple2."<init>":(Ljava/lang/Object;Ljava/lang/Object;)V
	invokespecial	Method scala/Some."<init>":(Ljava/lang/Object;)V
	areturn
  Labels:
  LocalVariableTable: 
   Start  Length  Slot  Name   Signature
   0      23      0    this       Lscala/reflect/Template$;
   0      23      1    x$0       Lscala/reflect/Template;


public scala.Function1 curry();
  Signature: ()Lscala/Function1;
  Code:
   Stack=1, Locals=1, Args_size=1
	aload_0
	invokestatic	Method scala/Function2$class.curry:(Lscala/Function2;)Lscala/Function1;
	areturn
  Labels:

public java.lang.String toString();
  Signature: ()Ljava/lang/String;
  Code:
   Stack=1, Locals=1, Args_size=1
	aload_0
	invokestatic	Method scala/Function2$class.toString:(Lscala/Function2;)Ljava/lang/String;
	areturn
  Labels:

}

