Compiled from "Type.scala"
public class scala.reflect.ThisType extends scala.reflect.Type implements scala.ScalaObject,scala.Product,java.io.Serializable
  SourceFile: "Type.scala"
  ScalaSig: length = 0x3
   05 00 00 
  RuntimeVisibleAnnotations: length = 0xB
   00 01 00 76 00 01 00 77 73 00 78 
  minor version: 0
  major version: 49
  Constant pool:
Asciz	SourceFile;
Asciz	Type.scala;
Asciz	andThen;
Asciz	(Lscala/Function1;)Lscala/Function1;;
Asciz	Code;
Asciz	scala/reflect/ThisType$;
class	scala/reflect/ThisType$
Asciz	MODULE$;
Asciz	Lscala/reflect/ThisType$;;
NameAndType	MODULE$:Lscala/reflect/ThisType$;
Field	scala/reflect/ThisType$.MODULE$:Lscala/reflect/ThisType$;
NameAndType	andThen:(Lscala/Function1;)Lscala/Function1;
Method	scala/reflect/ThisType$.andThen:(Lscala/Function1;)Lscala/Function1;
Asciz	compose;
NameAndType	compose:(Lscala/Function1;)Lscala/Function1;
Method	scala/reflect/ThisType$.compose:(Lscala/Function1;)Lscala/Function1;
Asciz	clazz;
Asciz	Lscala/reflect/Symbol;;
Asciz	productElementName;
Asciz	(I)Ljava/lang/String;;
Asciz	LineNumberTable;
Asciz	scala/Product$class;
class	scala/Product$class
Asciz	(Lscala/Product;I)Ljava/lang/String;;
NameAndType	productElementName:(Lscala/Product;I)Ljava/lang/String;
Method	scala/Product$class.productElementName:(Lscala/Product;I)Ljava/lang/String;
Asciz	this;
Asciz	Lscala/reflect/ThisType;;
Asciz	n;
Asciz	I;
Asciz	LocalVariableTable;
Asciz	productIterator;
Asciz	()Lscala/collection/Iterator;;
Asciz	(Lscala/Product;)Lscala/collection/Iterator;;
NameAndType	productIterator:(Lscala/Product;)Lscala/collection/Iterator;
Method	scala/Product$class.productIterator:(Lscala/Product;)Lscala/collection/Iterator;
Asciz	productElements;
NameAndType	productElements:(Lscala/Product;)Lscala/collection/Iterator;
Method	scala/Product$class.productElements:(Lscala/Product;)Lscala/collection/Iterator;
Asciz	Deprecated;
Asciz	copy$default$1;
Asciz	()Lscala/reflect/Symbol;;
Asciz	scala/reflect/ThisType;
class	scala/reflect/ThisType
NameAndType	clazz:()Lscala/reflect/Symbol;
Method	scala/reflect/ThisType.clazz:()Lscala/reflect/Symbol;
NameAndType	clazz:Lscala/reflect/Symbol;
Field	scala/reflect/ThisType.clazz:Lscala/reflect/Symbol;
Asciz	copy;
Asciz	(Lscala/reflect/Symbol;)Lscala/reflect/ThisType;;
Asciz	<init>;
Asciz	(Lscala/reflect/Symbol;)V;
NameAndType	"<init>":(Lscala/reflect/Symbol;)V
Method	scala/reflect/ThisType."<init>":(Lscala/reflect/Symbol;)V
Asciz	hashCode;
Asciz	()I;
Asciz	scala/runtime/ScalaRunTime$;
class	scala/runtime/ScalaRunTime$
Asciz	Lscala/runtime/ScalaRunTime$;;
NameAndType	MODULE$:Lscala/runtime/ScalaRunTime$;
Field	scala/runtime/ScalaRunTime$.MODULE$:Lscala/runtime/ScalaRunTime$;
Asciz	_hashCode;
Asciz	(Lscala/Product;)I;
NameAndType	_hashCode:(Lscala/Product;)I
Method	scala/runtime/ScalaRunTime$._hashCode:(Lscala/Product;)I
Asciz	toString;
Asciz	()Ljava/lang/String;;
Asciz	_toString;
Asciz	(Lscala/Product;)Ljava/lang/String;;
NameAndType	_toString:(Lscala/Product;)Ljava/lang/String;
Method	scala/runtime/ScalaRunTime$._toString:(Lscala/Product;)Ljava/lang/String;
Asciz	equals;
Asciz	(Ljava/lang/Object;)Z;
Asciz	gd4$1;
Asciz	(Lscala/reflect/Symbol;)Z;
NameAndType	gd4$1:(Lscala/reflect/Symbol;)Z
Method	scala/reflect/ThisType.gd4$1:(Lscala/reflect/Symbol;)Z
Asciz	scala/Equals;
class	scala/Equals
Asciz	canEqual;
NameAndType	canEqual:(Ljava/lang/Object;)Z
InterfaceMethod	scala/Equals.canEqual:(Ljava/lang/Object;)Z
Asciz	temp18;
Asciz	temp19;
Asciz	productPrefix;
Asciz	ThisType;
String	ThisType
Asciz	productArity;
Asciz	productElement;
Asciz	(I)Ljava/lang/Object;;
Asciz	java/lang/IndexOutOfBoundsException;
class	java/lang/IndexOutOfBoundsException
Asciz	scala/runtime/BoxesRunTime;
class	scala/runtime/BoxesRunTime
Asciz	boxToInteger;
Asciz	(I)Ljava/lang/Integer;;
NameAndType	boxToInteger:(I)Ljava/lang/Integer;
Method	scala/runtime/BoxesRunTime.boxToInteger:(I)Ljava/lang/Integer;
Asciz	java/lang/Object;
class	java/lang/Object
NameAndType	toString:()Ljava/lang/String;
Method	java/lang/Object.toString:()Ljava/lang/String;
Asciz	(Ljava/lang/String;)V;
NameAndType	"<init>":(Ljava/lang/String;)V
Method	java/lang/IndexOutOfBoundsException."<init>":(Ljava/lang/String;)V
NameAndType	equals:(Ljava/lang/Object;)Z
Method	java/lang/Object.equals:(Ljava/lang/Object;)Z
Asciz	scala/reflect/Type;
class	scala/reflect/Type
Asciz	()V;
NameAndType	"<init>":()V
Method	scala/reflect/Type."<init>":()V
Asciz	$init$;
Asciz	(Lscala/Product;)V;
NameAndType	$init$:(Lscala/Product;)V
Method	scala/Product$class.$init$:(Lscala/Product;)V
Asciz	ScalaSig;
Asciz	Lscala/reflect/ScalaSignature;;
Asciz	bytes;
Asciz	y4\"\ti\t)\"L7V=qK*1Be4G.Z2u)!B:dC27A\n!a\n5\t!!\t!A+9f!\tia\"D\tyAAATGdm2kK$CA\tBAAQe>$Wo;\tQ!Q3AU\tQa7buj,A\t]I!\rMKXNY8m!QA!E!1AB2mCjTCQ$=S:LGO=}\"!\tQY\t!CE!1m9z)\tq2CAA\t\t!CMq1m9zI,g-Y;mi\nT#A+YA3&A)zS\"A1j!C;oG\",7m[3e\tqC!b]:|G/;j_:L!M#Ut7\r[3dW$g+:jC:W\r3\t\"4!Am5D_,G#5)B\rIe\tq!\t!C!sAAo\*ue&tw\rF;!\tYdHy%QB!J,G-4\n}%AB*ue&twM>\t!A!\tC3)fcVGn\t\"!D#\n#!a\"p_2,M\t1J\rAH%\r\t)K!asN\t\"O5(o3vGR&/4jqV\tq\nQ+6\tKS'!A.8h!6bmL!aP)\t]A!ABaA:pIVG/:jif,\t5!\t!C!7qO]8ek$X\t\3nK:$HCA%]A,!AAQBB%\teX\tGtW)];bYRA\tv\t1JQ\t!\rG&A\r\rg.7juG.ZM\n\t\t#h!!.[:UsB,CAi\r!\t!bAI7c5kA!1Na'BA7XO;j[L!a7#7:bGR4UO\2uS>tCQFh.!ARQ!9qYf$\"AH;\tQ\t]D!CAq9QO\1qa2LHCA=}!\ri!PFwaa9uS>t\"B?wqa=%a;
Asciz	RuntimeVisibleAnnotations;
Asciz	scala/ScalaObject;
class	scala/ScalaObject
Asciz	scala/Product;
class	scala/Product
Asciz	java/io/Serializable;
class	java/io/Serializable

{
private final scala.reflect.Symbol clazz;
  Signature: Lscala/reflect/Symbol;

public static final scala.Function1 andThen(scala.Function1);
  Signature: (Lscala/Function1;)Lscala/Function1;
  Code:
   Stack=2, Locals=1, Args_size=1
	getstatic	Field scala/reflect/ThisType$.MODULE$:Lscala/reflect/ThisType$;
	aload_0
	invokevirtual	Method scala/reflect/ThisType$.andThen:(Lscala/Function1;)Lscala/Function1;
	areturn
  Labels:

public static final scala.Function1 compose(scala.Function1);
  Signature: (Lscala/Function1;)Lscala/Function1;
  Code:
   Stack=2, Locals=1, Args_size=1
	getstatic	Field scala/reflect/ThisType$.MODULE$:Lscala/reflect/ThisType$;
	aload_0
	invokevirtual	Method scala/reflect/ThisType$.compose:(Lscala/Function1;)Lscala/Function1;
	areturn
  Labels:

public java.lang.String productElementName(int);
  Signature: (I)Ljava/lang/String;
  Code:
   Stack=2, Locals=2, Args_size=2
	aload_0
	iload_1
	invokestatic	Method scala/Product$class.productElementName:(Lscala/Product;I)Ljava/lang/String;
	areturn
  Labels:
  LocalVariableTable: 
   Start  Length  Slot  Name   Signature
   0      6      0    this       Lscala/reflect/ThisType;
   0      6      1    n       I


public scala.collection.Iterator productIterator();
  Signature: ()Lscala/collection/Iterator;
  Code:
   Stack=1, Locals=1, Args_size=1
	aload_0
	invokestatic	Method scala/Product$class.productIterator:(Lscala/Product;)Lscala/collection/Iterator;
	areturn
  Labels:

public scala.collection.Iterator productElements();
  Signature: ()Lscala/collection/Iterator;
  Code:
   Stack=1, Locals=1, Args_size=1
	aload_0
	invokestatic	Method scala/Product$class.productElements:(Lscala/Product;)Lscala/collection/Iterator;
	areturn
  Labels:
  Deprecated: true

public scala.reflect.Symbol copy$default$1();
  Signature: ()Lscala/reflect/Symbol;
  Code:
   Stack=1, Locals=1, Args_size=1
	aload_0
	invokevirtual	Method clazz:()Lscala/reflect/Symbol;
	areturn
  Labels:

public scala.reflect.Symbol clazz();
  Signature: ()Lscala/reflect/Symbol;
  Code:
   Stack=1, Locals=1, Args_size=1
	aload_0
	getfield	Field clazz:Lscala/reflect/Symbol;
	areturn
  Labels:

public scala.reflect.ThisType copy(scala.reflect.Symbol);
  Signature: (Lscala/reflect/Symbol;)Lscala/reflect/ThisType;
  Code:
   Stack=3, Locals=2, Args_size=2
	new	class scala/reflect/ThisType
	dup
	aload_1
	invokespecial	Method "<init>":(Lscala/reflect/Symbol;)V
	areturn
  Labels:
  LocalVariableTable: 
   Start  Length  Slot  Name   Signature
   0      9      0    this       Lscala/reflect/ThisType;
   0      9      1    clazz       Lscala/reflect/Symbol;


public int hashCode();
  Signature: ()I
  Code:
   Stack=2, Locals=1, Args_size=1
	getstatic	Field scala/runtime/ScalaRunTime$.MODULE$:Lscala/runtime/ScalaRunTime$;
	aload_0
	invokevirtual	Method scala/runtime/ScalaRunTime$._hashCode:(Lscala/Product;)I
	ireturn
  Labels:

public java.lang.String toString();
  Signature: ()Ljava/lang/String;
  Code:
   Stack=2, Locals=1, Args_size=1
	getstatic	Field scala/runtime/ScalaRunTime$.MODULE$:Lscala/runtime/ScalaRunTime$;
	aload_0
	invokevirtual	Method scala/runtime/ScalaRunTime$._toString:(Lscala/Product;)Ljava/lang/String;
	areturn
  Labels:

public boolean equals(java.lang.Object);
  Signature: (Ljava/lang/Object;)Z
  Code:
   Stack=2, Locals=4, Args_size=2
	aload_0
	aload_1
	if_acmpeq	l1 // iconst_1
	aload_1
	instanceof	class scala/reflect/ThisType
	ifeq	l2 // iconst_0
	aload_1
	checkcast	class scala/reflect/ThisType
	astore_2
	aload_2
	invokevirtual	Method clazz:()Lscala/reflect/Symbol;
	astore_3
	aload_0
	aload_3
	invokespecial	Method gd4$1:(Lscala/reflect/Symbol;)Z
	ifeq	l3 // iconst_0
	aload_1
	checkcast	class scala/reflect/ThisType
	aload_0
	invokeinterface	InterfaceMethod scala/Equals.canEqual:(Ljava/lang/Object;)Z
	goto	l4 // ifeq
l3	iconst_0
	goto	l4 // ifeq
l2	iconst_0
l4	ifeq	l5 // iconst_0
l1	iconst_1
	goto	l6 // ireturn
l5	iconst_0
l6	ireturn
  Labels:
   	l3 = 43 // iconst_0
   	l2 = 47 // iconst_0
   	l4 = 48 // ifeq
   	l1 = 51 // iconst_1
   	l5 = 55 // iconst_0
   	l6 = 56 // ireturn
  LocalVariableTable: 
   Start  Length  Slot  Name   Signature
   0      57      0    this       Lscala/reflect/ThisType;
   17      30      2    temp18       Lscala/reflect/ThisType;
   22      25      3    temp19       Lscala/reflect/Symbol;


public java.lang.String productPrefix();
  Signature: ()Ljava/lang/String;
  Code:
   Stack=1, Locals=1, Args_size=1
	ldc	String ThisType
	areturn
  Labels:

public int productArity();
  Signature: ()I
  Code:
   Stack=1, Locals=1, Args_size=1
	iconst_1
	ireturn
  Labels:

public java.lang.Object productElement(int);
  Signature: (I)Ljava/lang/Object;
  Code:
   Stack=3, Locals=2, Args_size=2
	iload_1
	iconst_0
	if_icmpne	l1 // new
	aload_0
	invokevirtual	Method clazz:()Lscala/reflect/Symbol;
	areturn
l1	new	class java/lang/IndexOutOfBoundsException
	dup
	iload_1
	invokestatic	Method scala/runtime/BoxesRunTime.boxToInteger:(I)Ljava/lang/Integer;
	invokevirtual	Method java/lang/Object.toString:()Ljava/lang/String;
	invokespecial	Method java/lang/IndexOutOfBoundsException."<init>":(Ljava/lang/String;)V
	athrow
  Labels:
   	l1 = 10 // new

public boolean canEqual(java.lang.Object);
  Signature: (Ljava/lang/Object;)Z
  Code:
   Stack=1, Locals=2, Args_size=2
	aload_1
	instanceof	class scala/reflect/ThisType
	ireturn
  Labels:

private final boolean gd4$1(scala.reflect.Symbol);
  Signature: (Lscala/reflect/Symbol;)Z
  Code:
   Stack=2, Locals=3, Args_size=2
	aload_1
	aload_0
	invokevirtual	Method clazz:()Lscala/reflect/Symbol;
	astore_2
	dup
	ifnonnull	l1 // aload_2
	pop
	aload_2
	ifnull	l2 // iconst_1
	goto	l3 // iconst_0
l1	aload_2
	invokevirtual	Method java/lang/Object.equals:(Ljava/lang/Object;)Z
	ifeq	l3 // iconst_0
l2	iconst_1
	goto	l4 // ireturn
l3	iconst_0
l4	ireturn
  Labels:
   	l1 = 18 // aload_2
   	l2 = 25 // iconst_1
   	l3 = 29 // iconst_0
   	l4 = 30 // ireturn

public scala.reflect.ThisType(scala.reflect.Symbol);
  Signature: (Lscala/reflect/Symbol;)V
  Code:
   Stack=2, Locals=2, Args_size=2
	aload_0
	aload_1
	putfield	Field clazz:Lscala/reflect/Symbol;
	aload_0
	invokespecial	Method scala/reflect/Type."<init>":()V
	aload_0
	invokestatic	Method scala/Product$class.$init$:(Lscala/Product;)V
	return
  Labels:
  LocalVariableTable: 
   Start  Length  Slot  Name   Signature
   0      14      0    this       Lscala/reflect/ThisType;
   0      14      1    clazz       Lscala/reflect/Symbol;


}

