Compiled from "Type.scala"
public final class scala.reflect.ThisType$ extends java.lang.Object implements scala.Function1,scala.ScalaObject
  SourceFile: "Type.scala"
  Scala: length = 0x
   
  minor version: 0
  major version: 49
  Constant pool:
Asciz	SourceFile;
Asciz	Type.scala;
Asciz	Scala;
Asciz	MODULE$;
Asciz	Lscala/reflect/ThisType$;;
Asciz	<clinit>;
Asciz	()V;
Asciz	Code;
Asciz	scala/reflect/ThisType$;
class	scala/reflect/ThisType$
Asciz	<init>;
NameAndType	"<init>":()V
Method	scala/reflect/ThisType$."<init>":()V
Asciz	toString;
Asciz	()Ljava/lang/String;;
Asciz	LineNumberTable;
Asciz	scala/Function1$class;
class	scala/Function1$class
Asciz	(Lscala/Function1;)Ljava/lang/String;;
NameAndType	toString:(Lscala/Function1;)Ljava/lang/String;
Method	scala/Function1$class.toString:(Lscala/Function1;)Ljava/lang/String;
Asciz	compose;
Asciz	(Lscala/Function1;)Lscala/Function1;;
Asciz	(Lscala/Function1;Lscala/Function1;)Lscala/Function1;;
NameAndType	compose:(Lscala/Function1;Lscala/Function1;)Lscala/Function1;
Method	scala/Function1$class.compose:(Lscala/Function1;Lscala/Function1;)Lscala/Function1;
Asciz	this;
Asciz	g;
Asciz	Lscala/Function1;;
Asciz	LocalVariableTable;
Asciz	andThen;
NameAndType	andThen:(Lscala/Function1;Lscala/Function1;)Lscala/Function1;
Method	scala/Function1$class.andThen:(Lscala/Function1;Lscala/Function1;)Lscala/Function1;
Asciz	unapply;
Asciz	(Lscala/reflect/ThisType;)Lscala/Some;;
Asciz	scala/Some;
class	scala/Some
Asciz	scala/reflect/ThisType;
class	scala/reflect/ThisType
Asciz	clazz;
Asciz	()Lscala/reflect/Symbol;;
NameAndType	clazz:()Lscala/reflect/Symbol;
Method	scala/reflect/ThisType.clazz:()Lscala/reflect/Symbol;
Asciz	(Ljava/lang/Object;)V;
NameAndType	"<init>":(Ljava/lang/Object;)V
Method	scala/Some."<init>":(Ljava/lang/Object;)V
Asciz	x$0;
Asciz	Lscala/reflect/ThisType;;
Asciz	apply;
Asciz	(Lscala/reflect/Symbol;)Lscala/reflect/ThisType;;
Asciz	(Lscala/reflect/Symbol;)V;
NameAndType	"<init>":(Lscala/reflect/Symbol;)V
Method	scala/reflect/ThisType."<init>":(Lscala/reflect/Symbol;)V
Asciz	Lscala/reflect/Symbol;;
Asciz	(Ljava/lang/Object;)Ljava/lang/Object;;
Asciz	scala/reflect/Symbol;
class	scala/reflect/Symbol
NameAndType	apply:(Lscala/reflect/Symbol;)Lscala/reflect/ThisType;
Method	scala/reflect/ThisType$.apply:(Lscala/reflect/Symbol;)Lscala/reflect/ThisType;
Asciz	v1;
Asciz	Ljava/lang/Object;;
Asciz	java/lang/Object;
class	java/lang/Object
Method	java/lang/Object."<init>":()V
NameAndType	MODULE$:Lscala/reflect/ThisType$;
Field	scala/reflect/ThisType$.MODULE$:Lscala/reflect/ThisType$;
Asciz	$init$;
Asciz	(Lscala/Function1;)V;
NameAndType	$init$:(Lscala/Function1;)V
Method	scala/Function1$class.$init$:(Lscala/Function1;)V
Asciz	scala/Function1;
class	scala/Function1
Asciz	scala/ScalaObject;
class	scala/ScalaObject

{
public static final scala.reflect.ThisType$ MODULE$;
  Signature: Lscala/reflect/ThisType$;

public static {};
  Signature: ()V
  Code:
   Stack=1, Locals=0, Args_size=0
	new	class scala/reflect/ThisType$
	invokespecial	Method "<init>":()V
	return
  Labels:

public java.lang.String toString();
  Signature: ()Ljava/lang/String;
  Code:
   Stack=1, Locals=1, Args_size=1
	aload_0
	invokestatic	Method scala/Function1$class.toString:(Lscala/Function1;)Ljava/lang/String;
	areturn
  Labels:

public scala.Function1 compose(scala.Function1);
  Signature: (Lscala/Function1;)Lscala/Function1;
  Code:
   Stack=2, Locals=2, Args_size=2
	aload_0
	aload_1
	invokestatic	Method scala/Function1$class.compose:(Lscala/Function1;Lscala/Function1;)Lscala/Function1;
	areturn
  Labels:
  LocalVariableTable: 
   Start  Length  Slot  Name   Signature
   0      6      0    this       Lscala/reflect/ThisType$;
   0      6      1    g       Lscala/Function1;


public scala.Function1 andThen(scala.Function1);
  Signature: (Lscala/Function1;)Lscala/Function1;
  Code:
   Stack=2, Locals=2, Args_size=2
	aload_0
	aload_1
	invokestatic	Method scala/Function1$class.andThen:(Lscala/Function1;Lscala/Function1;)Lscala/Function1;
	areturn
  Labels:
  LocalVariableTable: 
   Start  Length  Slot  Name   Signature
   0      6      0    this       Lscala/reflect/ThisType$;
   0      6      1    g       Lscala/Function1;


public scala.Some unapply(scala.reflect.ThisType);
  Signature: (Lscala/reflect/ThisType;)Lscala/Some;
  Code:
   Stack=3, Locals=2, Args_size=2
	new	class scala/Some
	dup
	aload_1
	invokevirtual	Method scala/reflect/ThisType.clazz:()Lscala/reflect/Symbol;
	invokespecial	Method scala/Some."<init>":(Ljava/lang/Object;)V
	areturn
  Labels:
  LocalVariableTable: 
   Start  Length  Slot  Name   Signature
   0      12      0    this       Lscala/reflect/ThisType$;
   0      12      1    x$0       Lscala/reflect/ThisType;


public scala.reflect.ThisType apply(scala.reflect.Symbol);
  Signature: (Lscala/reflect/Symbol;)Lscala/reflect/ThisType;
  Code:
   Stack=3, Locals=2, Args_size=2
	new	class scala/reflect/ThisType
	dup
	aload_1
	invokespecial	Method scala/reflect/ThisType."<init>":(Lscala/reflect/Symbol;)V
	areturn
  Labels:
  LocalVariableTable: 
   Start  Length  Slot  Name   Signature
   0      9      0    this       Lscala/reflect/ThisType$;
   0      9      1    clazz       Lscala/reflect/Symbol;


public java.lang.Object apply(java.lang.Object);
  Signature: (Ljava/lang/Object;)Ljava/lang/Object;
  Code:
   Stack=2, Locals=2, Args_size=2
	aload_0
	aload_1
	checkcast	class scala/reflect/Symbol
	invokevirtual	Method apply:(Lscala/reflect/Symbol;)Lscala/reflect/ThisType;
	areturn
  Labels:
  LocalVariableTable: 
   Start  Length  Slot  Name   Signature
   0      9      0    this       Lscala/reflect/ThisType$;
   0      9      1    v1       Ljava/lang/Object;


private scala.reflect.ThisType$();
  Signature: ()V
  Code:
   Stack=1, Locals=1, Args_size=1
	aload_0
	invokespecial	Method java/lang/Object."<init>":()V
	aload_0
	putstatic	Field MODULE$:Lscala/reflect/ThisType$;
	aload_0
	invokestatic	Method scala/Function1$class.$init$:(Lscala/Function1;)V
	return
  Labels:

}

