Compiled from "Symbol.scala"
public final class scala.reflect.TypeField$ extends java.lang.Object implements scala.Function2,scala.ScalaObject
  SourceFile: "Symbol.scala"
  Scala: length = 0x
   
  minor version: 0
  major version: 49
  Constant pool:
Asciz	SourceFile;
Asciz	Symbol.scala;
Asciz	Scala;
Asciz	MODULE$;
Asciz	Lscala/reflect/TypeField$;;
Asciz	<clinit>;
Asciz	()V;
Asciz	Code;
Asciz	scala/reflect/TypeField$;
class	scala/reflect/TypeField$
Asciz	<init>;
NameAndType	"<init>":()V
Method	scala/reflect/TypeField$."<init>":()V
Asciz	LineNumberTable;
Asciz	java/lang/Object;
class	java/lang/Object
Method	java/lang/Object."<init>":()V
NameAndType	MODULE$:Lscala/reflect/TypeField$;
Field	scala/reflect/TypeField$.MODULE$:Lscala/reflect/TypeField$;
Asciz	scala/Function2$class;
class	scala/Function2$class
Asciz	$init$;
Asciz	(Lscala/Function2;)V;
NameAndType	$init$:(Lscala/Function2;)V
Method	scala/Function2$class.$init$:(Lscala/Function2;)V
Asciz	apply;
Asciz	(Ljava/lang/Object;Ljava/lang/Object;)Ljava/lang/Object;;
Asciz	java/lang/String;
class	java/lang/String
Asciz	scala/reflect/Type;
class	scala/reflect/Type
Asciz	(Ljava/lang/String;Lscala/reflect/Type;)Lscala/reflect/TypeField;;
NameAndType	apply:(Ljava/lang/String;Lscala/reflect/Type;)Lscala/reflect/TypeField;
Method	scala/reflect/TypeField$.apply:(Ljava/lang/String;Lscala/reflect/Type;)Lscala/reflect/TypeField;
Asciz	this;
Asciz	v1;
Asciz	Ljava/lang/Object;;
Asciz	v2;
Asciz	LocalVariableTable;
Asciz	scala/reflect/TypeField;
class	scala/reflect/TypeField
Asciz	(Ljava/lang/String;Lscala/reflect/Type;)V;
NameAndType	"<init>":(Ljava/lang/String;Lscala/reflect/Type;)V
Method	scala/reflect/TypeField."<init>":(Ljava/lang/String;Lscala/reflect/Type;)V
Asciz	fullname;
Asciz	Ljava/lang/String;;
Asciz	tpe;
Asciz	Lscala/reflect/Type;;
Asciz	unapply;
Asciz	(Lscala/reflect/TypeField;)Lscala/Some;;
Asciz	scala/Some;
class	scala/Some
Asciz	scala/Tuple2;
class	scala/Tuple2
Asciz	()Ljava/lang/String;;
NameAndType	fullname:()Ljava/lang/String;
Method	scala/reflect/TypeField.fullname:()Ljava/lang/String;
Asciz	()Lscala/reflect/Type;;
NameAndType	tpe:()Lscala/reflect/Type;
Method	scala/reflect/TypeField.tpe:()Lscala/reflect/Type;
Asciz	(Ljava/lang/Object;Ljava/lang/Object;)V;
NameAndType	"<init>":(Ljava/lang/Object;Ljava/lang/Object;)V
Method	scala/Tuple2."<init>":(Ljava/lang/Object;Ljava/lang/Object;)V
Asciz	(Ljava/lang/Object;)V;
NameAndType	"<init>":(Ljava/lang/Object;)V
Method	scala/Some."<init>":(Ljava/lang/Object;)V
Asciz	x$0;
Asciz	Lscala/reflect/TypeField;;
Asciz	tupled;
Asciz	()Lscala/Function1;;
Asciz	(Lscala/Function2;)Lscala/Function1;;
NameAndType	tupled:(Lscala/Function2;)Lscala/Function1;
Method	scala/Function2$class.tupled:(Lscala/Function2;)Lscala/Function1;
Asciz	curry;
NameAndType	curry:(Lscala/Function2;)Lscala/Function1;
Method	scala/Function2$class.curry:(Lscala/Function2;)Lscala/Function1;
Asciz	Deprecated;
Asciz	curried;
NameAndType	curried:(Lscala/Function2;)Lscala/Function1;
Method	scala/Function2$class.curried:(Lscala/Function2;)Lscala/Function1;
Asciz	toString;
Asciz	(Lscala/Function2;)Ljava/lang/String;;
NameAndType	toString:(Lscala/Function2;)Ljava/lang/String;
Method	scala/Function2$class.toString:(Lscala/Function2;)Ljava/lang/String;
Asciz	scala/Function2;
class	scala/Function2
Asciz	scala/ScalaObject;
class	scala/ScalaObject

{
public static final scala.reflect.TypeField$ MODULE$;
  Signature: Lscala/reflect/TypeField$;

public static {};
  Signature: ()V
  Code:
   Stack=1, Locals=0, Args_size=0
	new	class scala/reflect/TypeField$
	invokespecial	Method "<init>":()V
	return
  Labels:

private scala.reflect.TypeField$();
  Signature: ()V
  Code:
   Stack=1, Locals=1, Args_size=1
	aload_0
	invokespecial	Method java/lang/Object."<init>":()V
	aload_0
	putstatic	Field MODULE$:Lscala/reflect/TypeField$;
	aload_0
	invokestatic	Method scala/Function2$class.$init$:(Lscala/Function2;)V
	return
  Labels:

public java.lang.Object apply(java.lang.Object, java.lang.Object);
  Signature: (Ljava/lang/Object;Ljava/lang/Object;)Ljava/lang/Object;
  Code:
   Stack=3, Locals=3, Args_size=3
	aload_0
	aload_1
	checkcast	class java/lang/String
	aload_2
	checkcast	class scala/reflect/Type
	invokevirtual	Method apply:(Ljava/lang/String;Lscala/reflect/Type;)Lscala/reflect/TypeField;
	areturn
  Labels:
  LocalVariableTable: 
   Start  Length  Slot  Name   Signature
   0      13      0    this       Lscala/reflect/TypeField$;
   0      13      1    v1       Ljava/lang/Object;
   0      13      2    v2       Ljava/lang/Object;


public scala.reflect.TypeField apply(java.lang.String, scala.reflect.Type);
  Signature: (Ljava/lang/String;Lscala/reflect/Type;)Lscala/reflect/TypeField;
  Code:
   Stack=4, Locals=3, Args_size=3
	new	class scala/reflect/TypeField
	dup
	aload_1
	aload_2
	invokespecial	Method scala/reflect/TypeField."<init>":(Ljava/lang/String;Lscala/reflect/Type;)V
	areturn
  Labels:
  LocalVariableTable: 
   Start  Length  Slot  Name   Signature
   0      10      0    this       Lscala/reflect/TypeField$;
   0      10      1    fullname       Ljava/lang/String;
   0      10      2    tpe       Lscala/reflect/Type;


public scala.Some unapply(scala.reflect.TypeField);
  Signature: (Lscala/reflect/TypeField;)Lscala/Some;
  Code:
   Stack=6, Locals=2, Args_size=2
	new	class scala/Some
	dup
	new	class scala/Tuple2
	dup
	aload_1
	invokevirtual	Method scala/reflect/TypeField.fullname:()Ljava/lang/String;
	aload_1
	invokevirtual	Method scala/reflect/TypeField.tpe:()Lscala/reflect/Type;
	invokespecial	Method scala/Tuple2."<init>":(Ljava/lang/Object;Ljava/lang/Object;)V
	invokespecial	Method scala/Some."<init>":(Ljava/lang/Object;)V
	areturn
  Labels:
  LocalVariableTable: 
   Start  Length  Slot  Name   Signature
   0      23      0    this       Lscala/reflect/TypeField$;
   0      23      1    x$0       Lscala/reflect/TypeField;


public scala.Function1 tupled();
  Signature: ()Lscala/Function1;
  Code:
   Stack=1, Locals=1, Args_size=1
	aload_0
	invokestatic	Method scala/Function2$class.tupled:(Lscala/Function2;)Lscala/Function1;
	areturn
  Labels:

public scala.Function1 curry();
  Signature: ()Lscala/Function1;
  Code:
   Stack=1, Locals=1, Args_size=1
	aload_0
	invokestatic	Method scala/Function2$class.curry:(Lscala/Function2;)Lscala/Function1;
	areturn
  Labels:
  Deprecated: true

public scala.Function1 curried();
  Signature: ()Lscala/Function1;
  Code:
   Stack=1, Locals=1, Args_size=1
	aload_0
	invokestatic	Method scala/Function2$class.curried:(Lscala/Function2;)Lscala/Function1;
	areturn
  Labels:

public java.lang.String toString();
  Signature: ()Ljava/lang/String;
  Code:
   Stack=1, Locals=1, Args_size=1
	aload_0
	invokestatic	Method scala/Function2$class.toString:(Lscala/Function2;)Ljava/lang/String;
	areturn
  Labels:

}

