Compiled from "Symbol.scala"
public class scala.reflect.TypeField extends scala.reflect.GlobalSymbol implements scala.ScalaObject,scala.Product,java.io.Serializable
  SourceFile: "Symbol.scala"
  ScalaSig: length = 0x3CB
   05 00 FFFFFF81 0E 06 08 01 02 FFFFFF84 FFFFFF80 FFFFFF80 FFFFFF80 40 07 02 09
   54 79 70 65 46 69 65 6C 64 0A 02 03 04 01 07 72
   65 66 6C 65 63 74 0A 01 05 01 05 73 63 61 6C 61
   03 00 13 04 00 08 0C 10 10 02 09 0A 0D 01 02 09
   02 0B 02 02 0C 47 6C 6F 62 61 6C 53 79 6D 62 6F
   6C 10 02 0D 0E 0D 01 04 09 02 0F 04 02 0B 53 63
   61 6C 61 4F 62 6A 65 63 74 10 02 0D 11 09 02 12
   04 02 07 50 72 6F 64 75 63 74 08 08 14 00 FFFFFF82 FFFFFFCA
   FFFFFF80 FFFFFF84 20 15 01 08 66 75 6C 6C 6E 61 6D 65 15 01
   16 10 02 17 1A 0E 02 0D 18 09 02 19 04 01 06 50
   72 65 64 65 66 09 02 1B 1C 02 06 53 74 72 69 6E
   67 0A 02 19 04 08 09 1E 00 FFFFFF82 FFFFFF88 FFFFFFA0 FFFFFF80 04 16 1F
   01 09 66 75 6C 6C 6E 61 6D 65 20 09 02 14 0A 08
   08 21 00 FFFFFF82 FFFFFFCA FFFFFF80 FFFFFF84 00 22 01 03 74 70 65 15 01
   23 10 02 09 24 09 02 25 02 02 04 54 79 70 65 08
   08 27 00 FFFFFF82 FFFFFF88 FFFFFFA0 FFFFFF80 04 23 01 04 74 70 65 20 08
   05 29 00 FFFFFF84 00 2A 01 06 3C 69 6E 69 74 3E 14 03
   2B 2C 2D 10 02 09 00 08 05 14 28 FFFFFFC0 00 16 08 05
   21 28 FFFFFFC0 00 23 08 07 2F 00 FFFFFF81 FFFFFF80 FFFFFF84 00 30 01 04
   63 6F 70 79 14 03 2B 31 32 08 07 14 2E FFFFFF90 FFFFFF80 FFFFFFC0
   00 16 08 07 21 2E FFFFFF90 FFFFFF80 FFFFFFC0 00 23 08 07 34 00 FFFFFF91
   FFFFFF80 FFFFFF84 00 35 01 0E 63 6F 70 79 24 64 65 66 61 75
   6C 74 24 31 15 01 36 2A 02 16 37 2B 01 38 10 02
   39 3E 0D 01 3A 0A 02 3B 3C 01 09 75 6E 63 68 65
   63 6B 65 64 0A 02 3D 04 01 0A 61 6E 6E 6F 74 61
   74 69 6F 6E 09 02 3F 3A 02 11 75 6E 63 68 65 63
   6B 65 64 56 61 72 69 61 6E 63 65 08 07 41 00 FFFFFF91
   FFFFFF80 FFFFFF84 00 42 01 0E 63 6F 70 79 24 64 65 66 61 75
   6C 74 24 32 15 01 43 2A 02 23 37 08 08 45 00 FFFFFF84
   FFFFFF80 FFFFFF80 FFFFFF84 20 46 01 08 68 61 73 68 43 6F 64 65 14
   01 47 10 02 0D 48 09 02 49 04 02 03 49 6E 74 08
   08 4B 00 FFFFFF84 FFFFFF80 FFFFFF80 FFFFFF84 20 4C 01 08 74 6F 53 74 72
   69 6E 67 14 01 16 08 08 4E 00 FFFFFF84 FFFFFF80 FFFFFF80 FFFFFF84 20 4F
   01 06 65 71 75 61 6C 73 14 02 50 53 10 02 0D 51
   09 02 52 04 02 07 42 6F 6F 6C 65 61 6E 08 07 54
   4D FFFFFF81 FFFFFF80 FFFFFFC0 00 55 01 03 78 24 31 10 02 0D 56 09
   02 57 04 02 03 41 6E 79 08 08 59 00 FFFFFF84 FFFFFF80 FFFFFF80 FFFFFF84
   20 5A 01 0D 70 72 6F 64 75 63 74 50 72 65 66 69
   78 15 01 5B 10 02 5C 61 0D 01 5D 0A 02 5E 5F 01
   04 6C 61 6E 67 0A 01 60 01 04 6A 61 76 61 09 02
   1B 5D 08 08 63 00 FFFFFF84 FFFFFF80 FFFFFF80 FFFFFF84 20 64 01 0C 70 72
   6F 64 75 63 74 41 72 69 74 79 15 01 47 08 08 66
   00 FFFFFF84 FFFFFF80 FFFFFF80 FFFFFF84 20 67 01 0E 70 72 6F 64 75 63 74
   45 6C 65 6D 65 6E 74 14 02 55 68 08 07 54 65 FFFFFF81
   FFFFFF80 FFFFFFC0 00 47 08 08 6A 00 FFFFFF84 FFFFFF80 FFFFFF80 FFFFFF84 20 6B 01 08
   63 61 6E 45 71 75 61 6C 14 02 50 6C 08 07 54 69
   FFFFFF81 FFFFFF80 FFFFFFC0 00 55 28 02 00 6E 10 02 0D 6F 09 02 70
   04 02 0C 73 65 72 69 61 6C 69 7A 61 62 6C 65 07
   07 72 02 FFFFFF81 FFFFFF80 FFFFFF88 02 73 01 09 54 79 70 65 46 69
   65 6C 64 10 02 09 74 06 08 01 02 FFFFFF84 FFFFFF81 FFFFFF80 FFFFFF88 02
   75 13 04 74 76 79 0C 10 02 5C 77 09 02 78 5D 02
   06 4F 62 6A 65 63 74 10 05 0D 7A 16 23 2B 09 02
   7B 04 02 09 46 75 6E 63 74 69 6F 6E 32 08 05 29
   74 FFFFFF84 00 7D 14 01 73 08 08 7F 74 FFFFFF81 FFFFFF80 FFFFFF84 40 FFFFFF81
   00 01 05 61 70 70 6C 79 14 05 2B FFFFFF81 01 FFFFFF81 02 08
   05 14 7E FFFFFFC0 00 16 08 05 21 7E FFFFFFC0 00 23 08 09 FFFFFF81
   04 74 FFFFFF81 FFFFFF80 FFFFFF84 40 FFFFFF81 05 01 07 75 6E 61 70 70 6C
   79 14 04 FFFFFF81 06 FFFFFF81 0C 10 05 0D FFFFFF81 07 FFFFFF81 09 09 03
   FFFFFF81 08 04 02 04 53 6F 6D 65 10 05 0D FFFFFF81 0A 16 23
   09 03 FFFFFF81 0B 04 02 06 54 75 70 6C 65 32 08 07 FFFFFF81
   0D FFFFFF81 03 FFFFFFC0 00 2B 01 03 78 24 30 
  minor version: 0
  major version: 49
  Constant pool:
Asciz	SourceFile;
Asciz	Symbol.scala;
Asciz	tupled;
Asciz	()Lscala/Function1;;
Asciz	Code;
Asciz	scala/reflect/TypeField$;
class	scala/reflect/TypeField$
Asciz	MODULE$;
Asciz	Lscala/reflect/TypeField$;;
NameAndType	MODULE$:Lscala/reflect/TypeField$;
Field	scala/reflect/TypeField$.MODULE$:Lscala/reflect/TypeField$;
NameAndType	tupled:()Lscala/Function1;
Method	scala/reflect/TypeField$.tupled:()Lscala/Function1;
Asciz	curry;
NameAndType	curry:()Lscala/Function1;
Method	scala/reflect/TypeField$.curry:()Lscala/Function1;
Asciz	Deprecated;
Asciz	curried;
NameAndType	curried:()Lscala/Function1;
Method	scala/reflect/TypeField$.curried:()Lscala/Function1;
Asciz	tpe;
Asciz	Lscala/reflect/Type;;
Asciz	<init>;
Asciz	(Ljava/lang/String;Lscala/reflect/Type;)V;
Asciz	LineNumberTable;
Asciz	scala/reflect/TypeField;
class	scala/reflect/TypeField
NameAndType	tpe:Lscala/reflect/Type;
Field	scala/reflect/TypeField.tpe:Lscala/reflect/Type;
Asciz	scala/reflect/GlobalSymbol;
class	scala/reflect/GlobalSymbol
Asciz	(Ljava/lang/String;)V;
NameAndType	"<init>":(Ljava/lang/String;)V
Method	scala/reflect/GlobalSymbol."<init>":(Ljava/lang/String;)V
Asciz	scala/Product$class;
class	scala/Product$class
Asciz	$init$;
Asciz	(Lscala/Product;)V;
NameAndType	$init$:(Lscala/Product;)V
Method	scala/Product$class.$init$:(Lscala/Product;)V
Asciz	this;
Asciz	Lscala/reflect/TypeField;;
Asciz	fullname;
Asciz	Ljava/lang/String;;
Asciz	LocalVariableTable;
Asciz	gd4$1;
Asciz	(Ljava/lang/String;Lscala/reflect/Type;)Z;
Asciz	()Ljava/lang/String;;
NameAndType	fullname:()Ljava/lang/String;
Method	scala/reflect/TypeField.fullname:()Ljava/lang/String;
Asciz	java/lang/Object;
class	java/lang/Object
Asciz	equals;
Asciz	(Ljava/lang/Object;)Z;
NameAndType	equals:(Ljava/lang/Object;)Z
Method	java/lang/Object.equals:(Ljava/lang/Object;)Z
Asciz	()Lscala/reflect/Type;;
NameAndType	tpe:()Lscala/reflect/Type;
Method	scala/reflect/TypeField.tpe:()Lscala/reflect/Type;
Asciz	canEqual;
Asciz	productElement;
Asciz	(I)Ljava/lang/Object;;
Asciz	java/lang/IndexOutOfBoundsException;
class	java/lang/IndexOutOfBoundsException
Asciz	scala/runtime/BoxesRunTime;
class	scala/runtime/BoxesRunTime
Asciz	boxToInteger;
Asciz	(I)Ljava/lang/Integer;;
NameAndType	boxToInteger:(I)Ljava/lang/Integer;
Method	scala/runtime/BoxesRunTime.boxToInteger:(I)Ljava/lang/Integer;
Asciz	toString;
NameAndType	toString:()Ljava/lang/String;
Method	java/lang/Object.toString:()Ljava/lang/String;
Method	java/lang/IndexOutOfBoundsException."<init>":(Ljava/lang/String;)V
Asciz	productArity;
Asciz	()I;
Asciz	productPrefix;
Asciz	TypeField;
String	TypeField
NameAndType	gd4$1:(Ljava/lang/String;Lscala/reflect/Type;)Z
Method	scala/reflect/TypeField.gd4$1:(Ljava/lang/String;Lscala/reflect/Type;)Z
Asciz	scala/Equals;
class	scala/Equals
NameAndType	canEqual:(Ljava/lang/Object;)Z
InterfaceMethod	scala/Equals.canEqual:(Ljava/lang/Object;)Z
Asciz	temp16;
Asciz	temp17;
Asciz	temp18;
Asciz	scala/runtime/ScalaRunTime$;
class	scala/runtime/ScalaRunTime$
Asciz	Lscala/runtime/ScalaRunTime$;;
NameAndType	MODULE$:Lscala/runtime/ScalaRunTime$;
Field	scala/runtime/ScalaRunTime$.MODULE$:Lscala/runtime/ScalaRunTime$;
Asciz	_toString;
Asciz	(Lscala/Product;)Ljava/lang/String;;
NameAndType	_toString:(Lscala/Product;)Ljava/lang/String;
Method	scala/runtime/ScalaRunTime$._toString:(Lscala/Product;)Ljava/lang/String;
Asciz	hashCode;
Asciz	_hashCode;
Asciz	(Lscala/Product;)I;
NameAndType	_hashCode:(Lscala/Product;)I
Method	scala/runtime/ScalaRunTime$._hashCode:(Lscala/Product;)I
Asciz	copy;
Asciz	(Ljava/lang/String;Lscala/reflect/Type;)Lscala/reflect/TypeField;;
NameAndType	"<init>":(Ljava/lang/String;Lscala/reflect/Type;)V
Method	scala/reflect/TypeField."<init>":(Ljava/lang/String;Lscala/reflect/Type;)V
Method	scala/reflect/GlobalSymbol.fullname:()Ljava/lang/String;
Asciz	copy$default$1;
Asciz	copy$default$2;
Asciz	productElements;
Asciz	()Lscala/collection/Iterator;;
Asciz	(Lscala/Product;)Lscala/collection/Iterator;;
NameAndType	productElements:(Lscala/Product;)Lscala/collection/Iterator;
Method	scala/Product$class.productElements:(Lscala/Product;)Lscala/collection/Iterator;
Asciz	productIterator;
NameAndType	productIterator:(Lscala/Product;)Lscala/collection/Iterator;
Method	scala/Product$class.productIterator:(Lscala/Product;)Lscala/collection/Iterator;
Asciz	ScalaSig;
Asciz	scala/ScalaObject;
class	scala/ScalaObject
Asciz	scala/Product;
class	scala/Product
Asciz	java/io/Serializable;
class	java/io/Serializable

{
private final scala.reflect.Type tpe;
  Signature: Lscala/reflect/Type;

public static final scala.Function1 tupled();
  Signature: ()Lscala/Function1;
  Code:
   Stack=1, Locals=0, Args_size=0
	getstatic	Field scala/reflect/TypeField$.MODULE$:Lscala/reflect/TypeField$;
	invokevirtual	Method scala/reflect/TypeField$.tupled:()Lscala/Function1;
	areturn
  Labels:

public static final scala.Function1 curry();
  Signature: ()Lscala/Function1;
  Code:
   Stack=1, Locals=0, Args_size=0
	getstatic	Field scala/reflect/TypeField$.MODULE$:Lscala/reflect/TypeField$;
	invokevirtual	Method scala/reflect/TypeField$.curry:()Lscala/Function1;
	areturn
  Labels:
  Deprecated: true

public static final scala.Function1 curried();
  Signature: ()Lscala/Function1;
  Code:
   Stack=1, Locals=0, Args_size=0
	getstatic	Field scala/reflect/TypeField$.MODULE$:Lscala/reflect/TypeField$;
	invokevirtual	Method scala/reflect/TypeField$.curried:()Lscala/Function1;
	areturn
  Labels:

public scala.reflect.TypeField(java.lang.String, scala.reflect.Type);
  Signature: (Ljava/lang/String;Lscala/reflect/Type;)V
  Code:
   Stack=2, Locals=3, Args_size=3
	aload_0
	aload_2
	putfield	Field tpe:Lscala/reflect/Type;
	aload_0
	aload_1
	invokespecial	Method scala/reflect/GlobalSymbol."<init>":(Ljava/lang/String;)V
	aload_0
	invokestatic	Method scala/Product$class.$init$:(Lscala/Product;)V
	return
  Labels:
  LocalVariableTable: 
   Start  Length  Slot  Name   Signature
   0      15      0    this       Lscala/reflect/TypeField;
   0      15      1    fullname       Ljava/lang/String;
   0      15      2    tpe       Lscala/reflect/Type;


private final boolean gd4$1(java.lang.String, scala.reflect.Type);
  Signature: (Ljava/lang/String;Lscala/reflect/Type;)Z
  Code:
   Stack=2, Locals=5, Args_size=3
	aload_1
	aload_0
	invokevirtual	Method fullname:()Ljava/lang/String;
	astore_3
	dup
	ifnonnull	l1 // aload_3
	pop
	aload_3
	ifnull	l2 // aload_2
	goto	l3 // iconst_0
l1	aload_3
	invokevirtual	Method java/lang/Object.equals:(Ljava/lang/Object;)Z
	ifeq	l3 // iconst_0
l2	aload_2
	aload_0
	invokevirtual	Method tpe:()Lscala/reflect/Type;
	astore	4
	dup
	ifnonnull	l4 // aload
	pop
	aload	4
	ifnull	l5 // iconst_1
	goto	l3 // iconst_0
l4	aload	4
	invokevirtual	Method java/lang/Object.equals:(Ljava/lang/Object;)Z
	ifeq	l3 // iconst_0
l5	iconst_1
	goto	l6 // ireturn
l3	iconst_0
l6	ireturn
  Labels:
   	l1 = 18 // aload_3
   	l2 = 25 // aload_2
   	l4 = 45 // aload
   	l5 = 53 // iconst_1
   	l3 = 57 // iconst_0
   	l6 = 58 // ireturn

public boolean canEqual(java.lang.Object);
  Signature: (Ljava/lang/Object;)Z
  Code:
   Stack=1, Locals=2, Args_size=2
	aload_1
	instanceof	class scala/reflect/TypeField
	ireturn
  Labels:

public java.lang.Object productElement(int);
  Signature: (I)Ljava/lang/Object;
  Code:
   Stack=3, Locals=2, Args_size=2
	iload_1
	tableswitch{ //0 to 1
		0: 46;
		1: 39;
		default: 24 }
	new	class java/lang/IndexOutOfBoundsException
	dup
	iload_1
	invokestatic	Method scala/runtime/BoxesRunTime.boxToInteger:(I)Ljava/lang/Integer;
	invokevirtual	Method java/lang/Object.toString:()Ljava/lang/String;
	invokespecial	Method java/lang/IndexOutOfBoundsException."<init>":(Ljava/lang/String;)V
	athrow
	aload_0
	invokevirtual	Method tpe:()Lscala/reflect/Type;
	goto	l1 // areturn
	aload_0
	invokevirtual	Method fullname:()Ljava/lang/String;
l1	areturn
  Labels:
   	l1 = 50 // areturn

public int productArity();
  Signature: ()I
  Code:
   Stack=1, Locals=1, Args_size=1
	iconst_2
	ireturn
  Labels:

public java.lang.String productPrefix();
  Signature: ()Ljava/lang/String;
  Code:
   Stack=1, Locals=1, Args_size=1
	ldc	String TypeField
	areturn
  Labels:

public boolean equals(java.lang.Object);
  Signature: (Ljava/lang/Object;)Z
  Code:
   Stack=3, Locals=5, Args_size=2
	aload_0
	aload_1
	if_acmpeq	l1 // iconst_1
	aload_1
	instanceof	class scala/reflect/TypeField
	ifeq	l2 // iconst_0
	aload_1
	checkcast	class scala/reflect/TypeField
	astore_2
	aload_2
	invokevirtual	Method fullname:()Ljava/lang/String;
	astore_3
	aload_2
	invokevirtual	Method tpe:()Lscala/reflect/Type;
	astore	4
	aload_0
	aload_3
	aload	4
	invokespecial	Method gd4$1:(Ljava/lang/String;Lscala/reflect/Type;)Z
	ifeq	l3 // iconst_0
	aload_1
	checkcast	class scala/reflect/TypeField
	aload_0
	invokeinterface	InterfaceMethod scala/Equals.canEqual:(Ljava/lang/Object;)Z
	goto	l4 // ifeq
l3	iconst_0
	goto	l4 // ifeq
l2	iconst_0
l4	ifeq	l5 // iconst_0
l1	iconst_1
	goto	l6 // ireturn
l5	iconst_0
l6	ireturn
  Labels:
   	l3 = 51 // iconst_0
   	l2 = 55 // iconst_0
   	l4 = 56 // ifeq
   	l1 = 59 // iconst_1
   	l5 = 63 // iconst_0
   	l6 = 64 // ireturn
  LocalVariableTable: 
   Start  Length  Slot  Name   Signature
   0      65      0    this       Lscala/reflect/TypeField;
   17      38      2    temp16       Lscala/reflect/TypeField;
   22      33      3    temp17       Ljava/lang/String;
   28      27      4    temp18       Lscala/reflect/Type;


public java.lang.String toString();
  Signature: ()Ljava/lang/String;
  Code:
   Stack=2, Locals=1, Args_size=1
	getstatic	Field scala/runtime/ScalaRunTime$.MODULE$:Lscala/runtime/ScalaRunTime$;
	aload_0
	invokevirtual	Method scala/runtime/ScalaRunTime$._toString:(Lscala/Product;)Ljava/lang/String;
	areturn
  Labels:

public int hashCode();
  Signature: ()I
  Code:
   Stack=2, Locals=1, Args_size=1
	getstatic	Field scala/runtime/ScalaRunTime$.MODULE$:Lscala/runtime/ScalaRunTime$;
	aload_0
	invokevirtual	Method scala/runtime/ScalaRunTime$._hashCode:(Lscala/Product;)I
	ireturn
  Labels:

public scala.reflect.TypeField copy(java.lang.String, scala.reflect.Type);
  Signature: (Ljava/lang/String;Lscala/reflect/Type;)Lscala/reflect/TypeField;
  Code:
   Stack=4, Locals=3, Args_size=3
	new	class scala/reflect/TypeField
	dup
	aload_1
	aload_2
	invokespecial	Method "<init>":(Ljava/lang/String;Lscala/reflect/Type;)V
	areturn
  Labels:
  LocalVariableTable: 
   Start  Length  Slot  Name   Signature
   0      10      0    this       Lscala/reflect/TypeField;
   0      10      1    fullname       Ljava/lang/String;
   0      10      2    tpe       Lscala/reflect/Type;


public scala.reflect.Type tpe();
  Signature: ()Lscala/reflect/Type;
  Code:
   Stack=1, Locals=1, Args_size=1
	aload_0
	getfield	Field tpe:Lscala/reflect/Type;
	areturn
  Labels:

public java.lang.String fullname();
  Signature: ()Ljava/lang/String;
  Code:
   Stack=1, Locals=1, Args_size=1
	aload_0
	invokespecial	Method scala/reflect/GlobalSymbol.fullname:()Ljava/lang/String;
	areturn
  Labels:

public java.lang.String copy$default$1();
  Signature: ()Ljava/lang/String;
  Code:
   Stack=1, Locals=1, Args_size=1
	aload_0
	invokevirtual	Method fullname:()Ljava/lang/String;
	areturn
  Labels:

public scala.reflect.Type copy$default$2();
  Signature: ()Lscala/reflect/Type;
  Code:
   Stack=1, Locals=1, Args_size=1
	aload_0
	invokevirtual	Method tpe:()Lscala/reflect/Type;
	areturn
  Labels:

public scala.collection.Iterator productElements();
  Signature: ()Lscala/collection/Iterator;
  Code:
   Stack=1, Locals=1, Args_size=1
	aload_0
	invokestatic	Method scala/Product$class.productElements:(Lscala/Product;)Lscala/collection/Iterator;
	areturn
  Labels:
  Deprecated: true

public scala.collection.Iterator productIterator();
  Signature: ()Lscala/collection/Iterator;
  Code:
   Stack=1, Locals=1, Args_size=1
	aload_0
	invokestatic	Method scala/Product$class.productIterator:(Lscala/Product;)Lscala/collection/Iterator;
	areturn
  Labels:

}

