Compiled from "Tree.scala"
public class scala.reflect.ValDef extends scala.reflect.Tree implements scala.ScalaObject,scala.Product,java.io.Serializable
  SourceFile: "Tree.scala"
  ScalaSig: length = 0x3
   05 00 00 
  RuntimeVisibleAnnotations: length = 0xB
   00 01 00 FFFFFF82 00 01 00 FFFFFF83 73 00 FFFFFF84 
  minor version: 0
  major version: 49
  Constant pool:
Asciz	SourceFile;
Asciz	Tree.scala;
Asciz	tupled;
Asciz	()Lscala/Function1;;
Asciz	Code;
Asciz	scala/reflect/ValDef$;
class	scala/reflect/ValDef$
Asciz	MODULE$;
Asciz	Lscala/reflect/ValDef$;;
NameAndType	MODULE$:Lscala/reflect/ValDef$;
Field	scala/reflect/ValDef$.MODULE$:Lscala/reflect/ValDef$;
NameAndType	tupled:()Lscala/Function1;
Method	scala/reflect/ValDef$.tupled:()Lscala/Function1;
Asciz	curry;
NameAndType	curry:()Lscala/Function1;
Method	scala/reflect/ValDef$.curry:()Lscala/Function1;
Asciz	Deprecated;
Asciz	curried;
NameAndType	curried:()Lscala/Function1;
Method	scala/reflect/ValDef$.curried:()Lscala/Function1;
Asciz	sym;
Asciz	Lscala/reflect/Symbol;;
Asciz	rhs;
Asciz	Lscala/reflect/Tree;;
Asciz	productElementName;
Asciz	(I)Ljava/lang/String;;
Asciz	LineNumberTable;
Asciz	scala/Product$class;
class	scala/Product$class
Asciz	(Lscala/Product;I)Ljava/lang/String;;
NameAndType	productElementName:(Lscala/Product;I)Ljava/lang/String;
Method	scala/Product$class.productElementName:(Lscala/Product;I)Ljava/lang/String;
Asciz	this;
Asciz	Lscala/reflect/ValDef;;
Asciz	n;
Asciz	I;
Asciz	LocalVariableTable;
Asciz	productIterator;
Asciz	()Lscala/collection/Iterator;;
Asciz	(Lscala/Product;)Lscala/collection/Iterator;;
NameAndType	productIterator:(Lscala/Product;)Lscala/collection/Iterator;
Method	scala/Product$class.productIterator:(Lscala/Product;)Lscala/collection/Iterator;
Asciz	productElements;
NameAndType	productElements:(Lscala/Product;)Lscala/collection/Iterator;
Method	scala/Product$class.productElements:(Lscala/Product;)Lscala/collection/Iterator;
Asciz	copy$default$2;
Asciz	()Lscala/reflect/Tree;;
Asciz	scala/reflect/ValDef;
class	scala/reflect/ValDef
NameAndType	rhs:()Lscala/reflect/Tree;
Method	scala/reflect/ValDef.rhs:()Lscala/reflect/Tree;
Asciz	copy$default$1;
Asciz	()Lscala/reflect/Symbol;;
NameAndType	sym:()Lscala/reflect/Symbol;
Method	scala/reflect/ValDef.sym:()Lscala/reflect/Symbol;
NameAndType	sym:Lscala/reflect/Symbol;
Field	scala/reflect/ValDef.sym:Lscala/reflect/Symbol;
NameAndType	rhs:Lscala/reflect/Tree;
Field	scala/reflect/ValDef.rhs:Lscala/reflect/Tree;
Asciz	copy;
Asciz	(Lscala/reflect/Symbol;Lscala/reflect/Tree;)Lscala/reflect/ValDef;;
Asciz	<init>;
Asciz	(Lscala/reflect/Symbol;Lscala/reflect/Tree;)V;
NameAndType	"<init>":(Lscala/reflect/Symbol;Lscala/reflect/Tree;)V
Method	scala/reflect/ValDef."<init>":(Lscala/reflect/Symbol;Lscala/reflect/Tree;)V
Asciz	hashCode;
Asciz	()I;
Asciz	scala/runtime/ScalaRunTime$;
class	scala/runtime/ScalaRunTime$
Asciz	Lscala/runtime/ScalaRunTime$;;
NameAndType	MODULE$:Lscala/runtime/ScalaRunTime$;
Field	scala/runtime/ScalaRunTime$.MODULE$:Lscala/runtime/ScalaRunTime$;
Asciz	_hashCode;
Asciz	(Lscala/Product;)I;
NameAndType	_hashCode:(Lscala/Product;)I
Method	scala/runtime/ScalaRunTime$._hashCode:(Lscala/Product;)I
Asciz	toString;
Asciz	()Ljava/lang/String;;
Asciz	_toString;
Asciz	(Lscala/Product;)Ljava/lang/String;;
NameAndType	_toString:(Lscala/Product;)Ljava/lang/String;
Method	scala/runtime/ScalaRunTime$._toString:(Lscala/Product;)Ljava/lang/String;
Asciz	equals;
Asciz	(Ljava/lang/Object;)Z;
Asciz	gd14$1;
Asciz	(Lscala/reflect/Symbol;Lscala/reflect/Tree;)Z;
NameAndType	gd14$1:(Lscala/reflect/Symbol;Lscala/reflect/Tree;)Z
Method	scala/reflect/ValDef.gd14$1:(Lscala/reflect/Symbol;Lscala/reflect/Tree;)Z
Asciz	scala/Equals;
class	scala/Equals
Asciz	canEqual;
NameAndType	canEqual:(Ljava/lang/Object;)Z
InterfaceMethod	scala/Equals.canEqual:(Ljava/lang/Object;)Z
Asciz	temp63;
Asciz	temp64;
Asciz	temp65;
Asciz	productPrefix;
Asciz	ValDef;
String	ValDef
Asciz	productArity;
Asciz	productElement;
Asciz	(I)Ljava/lang/Object;;
Asciz	java/lang/IndexOutOfBoundsException;
class	java/lang/IndexOutOfBoundsException
Asciz	scala/runtime/BoxesRunTime;
class	scala/runtime/BoxesRunTime
Asciz	boxToInteger;
Asciz	(I)Ljava/lang/Integer;;
NameAndType	boxToInteger:(I)Ljava/lang/Integer;
Method	scala/runtime/BoxesRunTime.boxToInteger:(I)Ljava/lang/Integer;
Asciz	java/lang/Object;
class	java/lang/Object
NameAndType	toString:()Ljava/lang/String;
Method	java/lang/Object.toString:()Ljava/lang/String;
Asciz	(Ljava/lang/String;)V;
NameAndType	"<init>":(Ljava/lang/String;)V
Method	java/lang/IndexOutOfBoundsException."<init>":(Ljava/lang/String;)V
NameAndType	equals:(Ljava/lang/Object;)Z
Method	java/lang/Object.equals:(Ljava/lang/Object;)Z
Asciz	scala/reflect/Tree;
class	scala/reflect/Tree
Asciz	()V;
NameAndType	"<init>":()V
Method	scala/reflect/Tree."<init>":()V
Asciz	$init$;
Asciz	(Lscala/Product;)V;
NameAndType	$init$:(Lscala/Product;)V
Method	scala/Product$class.$init$:(Lscala/Product;)V
Asciz	ScalaSig;
Asciz	Lscala/reflect/ScalaSignature;;
Asciz	bytes;
Asciz	maC\t\tQ\rYGR3g\tA!AsKdWm;\tQa]2bYa1CABA!&/Z35qQ\"\n=!!aC*dC2wJ6fGR\"!D\t\nI!!a)s_,8\r\t))!C+1/_7Y\"!C\na!AB*z[\n|G\tE\t!0\tq!Q3Au\t1A5t+AC#\tID7\tC!\tAIy%t \r\"S\n!)A\ta-!)A\ta!9qAA\nAB2paf$2aI+!b%AAYAqC-EIA\r|/eKW;%cU\taF_-\n2m5\t!G4iIQO\2iK\W\rk\t!\"8o_RG/[8o\t9$GA\tv]DWmY6fIZ'/[1oGDq!!(d_BLHZ3gCVdG\nmR#C\tuA!ABy\n[1tQ{G-AQQ1!8u!\"A\n\";p'RN\4\"AR%59B%&/3fM&!j'RN\4!#C'\tI\t(\rX/7t)\ty%!&>|G.Z1oF*!AAQ12!\tiQ+W\t\tI\=\taA!ABeQ:pIVG:fM&DX#.mW\"/us7b]TaXU4-K9\"A!\rC3-qe>$Wo;Be&$0F@!)\"A\n2A9s_,8\r^#mK6,g)Dqa3qj\t\"k!M\#rkdGCA(l.!AAQC#A75qBA81XM]5bY&TM7f\t(!!A\tIaAV1m\t4CAt\r!\t!bA!8cA:vA)a/\tG5\tqOy\t9!/8uS6,B>xE\t%m;sC$h)8di&|gN\rCM$\t e\"9ap]A\n{!B1qa2LH#B\r\"~1\"~A\"CAgIQA)h.9qYf$B!aA)Q\"!%q\r=H/[8o!i1\t\r\t))VH.\teQaG\n;
Asciz	RuntimeVisibleAnnotations;
Asciz	scala/ScalaObject;
class	scala/ScalaObject
Asciz	scala/Product;
class	scala/Product
Asciz	java/io/Serializable;
class	java/io/Serializable

{
private final scala.reflect.Symbol sym;
  Signature: Lscala/reflect/Symbol;

private final scala.reflect.Tree rhs;
  Signature: Lscala/reflect/Tree;

public static final scala.Function1 tupled();
  Signature: ()Lscala/Function1;
  Code:
   Stack=1, Locals=0, Args_size=0
	getstatic	Field scala/reflect/ValDef$.MODULE$:Lscala/reflect/ValDef$;
	invokevirtual	Method scala/reflect/ValDef$.tupled:()Lscala/Function1;
	areturn
  Labels:

public static final scala.Function1 curry();
  Signature: ()Lscala/Function1;
  Code:
   Stack=1, Locals=0, Args_size=0
	getstatic	Field scala/reflect/ValDef$.MODULE$:Lscala/reflect/ValDef$;
	invokevirtual	Method scala/reflect/ValDef$.curry:()Lscala/Function1;
	areturn
  Labels:
  Deprecated: true

public static final scala.Function1 curried();
  Signature: ()Lscala/Function1;
  Code:
   Stack=1, Locals=0, Args_size=0
	getstatic	Field scala/reflect/ValDef$.MODULE$:Lscala/reflect/ValDef$;
	invokevirtual	Method scala/reflect/ValDef$.curried:()Lscala/Function1;
	areturn
  Labels:

public java.lang.String productElementName(int);
  Signature: (I)Ljava/lang/String;
  Code:
   Stack=2, Locals=2, Args_size=2
	aload_0
	iload_1
	invokestatic	Method scala/Product$class.productElementName:(Lscala/Product;I)Ljava/lang/String;
	areturn
  Labels:
  LocalVariableTable: 
   Start  Length  Slot  Name   Signature
   0      6      0    this       Lscala/reflect/ValDef;
   0      6      1    n       I


public scala.collection.Iterator productIterator();
  Signature: ()Lscala/collection/Iterator;
  Code:
   Stack=1, Locals=1, Args_size=1
	aload_0
	invokestatic	Method scala/Product$class.productIterator:(Lscala/Product;)Lscala/collection/Iterator;
	areturn
  Labels:

public scala.collection.Iterator productElements();
  Signature: ()Lscala/collection/Iterator;
  Code:
   Stack=1, Locals=1, Args_size=1
	aload_0
	invokestatic	Method scala/Product$class.productElements:(Lscala/Product;)Lscala/collection/Iterator;
	areturn
  Labels:
  Deprecated: true

public scala.reflect.Tree copy$default$2();
  Signature: ()Lscala/reflect/Tree;
  Code:
   Stack=1, Locals=1, Args_size=1
	aload_0
	invokevirtual	Method rhs:()Lscala/reflect/Tree;
	areturn
  Labels:

public scala.reflect.Symbol copy$default$1();
  Signature: ()Lscala/reflect/Symbol;
  Code:
   Stack=1, Locals=1, Args_size=1
	aload_0
	invokevirtual	Method sym:()Lscala/reflect/Symbol;
	areturn
  Labels:

public scala.reflect.Symbol sym();
  Signature: ()Lscala/reflect/Symbol;
  Code:
   Stack=1, Locals=1, Args_size=1
	aload_0
	getfield	Field sym:Lscala/reflect/Symbol;
	areturn
  Labels:

public scala.reflect.Tree rhs();
  Signature: ()Lscala/reflect/Tree;
  Code:
   Stack=1, Locals=1, Args_size=1
	aload_0
	getfield	Field rhs:Lscala/reflect/Tree;
	areturn
  Labels:

public scala.reflect.ValDef copy(scala.reflect.Symbol, scala.reflect.Tree);
  Signature: (Lscala/reflect/Symbol;Lscala/reflect/Tree;)Lscala/reflect/ValDef;
  Code:
   Stack=4, Locals=3, Args_size=3
	new	class scala/reflect/ValDef
	dup
	aload_1
	aload_2
	invokespecial	Method "<init>":(Lscala/reflect/Symbol;Lscala/reflect/Tree;)V
	areturn
  Labels:
  LocalVariableTable: 
   Start  Length  Slot  Name   Signature
   0      10      0    this       Lscala/reflect/ValDef;
   0      10      1    sym       Lscala/reflect/Symbol;
   0      10      2    rhs       Lscala/reflect/Tree;


public int hashCode();
  Signature: ()I
  Code:
   Stack=2, Locals=1, Args_size=1
	getstatic	Field scala/runtime/ScalaRunTime$.MODULE$:Lscala/runtime/ScalaRunTime$;
	aload_0
	invokevirtual	Method scala/runtime/ScalaRunTime$._hashCode:(Lscala/Product;)I
	ireturn
  Labels:

public java.lang.String toString();
  Signature: ()Ljava/lang/String;
  Code:
   Stack=2, Locals=1, Args_size=1
	getstatic	Field scala/runtime/ScalaRunTime$.MODULE$:Lscala/runtime/ScalaRunTime$;
	aload_0
	invokevirtual	Method scala/runtime/ScalaRunTime$._toString:(Lscala/Product;)Ljava/lang/String;
	areturn
  Labels:

public boolean equals(java.lang.Object);
  Signature: (Ljava/lang/Object;)Z
  Code:
   Stack=3, Locals=5, Args_size=2
	aload_0
	aload_1
	if_acmpeq	l1 // iconst_1
	aload_1
	instanceof	class scala/reflect/ValDef
	ifeq	l2 // iconst_0
	aload_1
	checkcast	class scala/reflect/ValDef
	astore_2
	aload_2
	invokevirtual	Method sym:()Lscala/reflect/Symbol;
	astore_3
	aload_2
	invokevirtual	Method rhs:()Lscala/reflect/Tree;
	astore	4
	aload_0
	aload_3
	aload	4
	invokespecial	Method gd14$1:(Lscala/reflect/Symbol;Lscala/reflect/Tree;)Z
	ifeq	l3 // iconst_0
	aload_1
	checkcast	class scala/reflect/ValDef
	aload_0
	invokeinterface	InterfaceMethod scala/Equals.canEqual:(Ljava/lang/Object;)Z
	goto	l4 // ifeq
l3	iconst_0
	goto	l4 // ifeq
l2	iconst_0
l4	ifeq	l5 // iconst_0
l1	iconst_1
	goto	l6 // ireturn
l5	iconst_0
l6	ireturn
  Labels:
   	l3 = 51 // iconst_0
   	l2 = 55 // iconst_0
   	l4 = 56 // ifeq
   	l1 = 59 // iconst_1
   	l5 = 63 // iconst_0
   	l6 = 64 // ireturn
  LocalVariableTable: 
   Start  Length  Slot  Name   Signature
   0      65      0    this       Lscala/reflect/ValDef;
   17      38      2    temp63       Lscala/reflect/ValDef;
   22      33      3    temp64       Lscala/reflect/Symbol;
   28      27      4    temp65       Lscala/reflect/Tree;


public java.lang.String productPrefix();
  Signature: ()Ljava/lang/String;
  Code:
   Stack=1, Locals=1, Args_size=1
	ldc	String ValDef
	areturn
  Labels:

public int productArity();
  Signature: ()I
  Code:
   Stack=1, Locals=1, Args_size=1
	iconst_2
	ireturn
  Labels:

public java.lang.Object productElement(int);
  Signature: (I)Ljava/lang/Object;
  Code:
   Stack=3, Locals=2, Args_size=2
	iload_1
	tableswitch{ //0 to 1
		0: 46;
		1: 39;
		default: 24 }
	new	class java/lang/IndexOutOfBoundsException
	dup
	iload_1
	invokestatic	Method scala/runtime/BoxesRunTime.boxToInteger:(I)Ljava/lang/Integer;
	invokevirtual	Method java/lang/Object.toString:()Ljava/lang/String;
	invokespecial	Method java/lang/IndexOutOfBoundsException."<init>":(Ljava/lang/String;)V
	athrow
	aload_0
	invokevirtual	Method rhs:()Lscala/reflect/Tree;
	goto	l1 // areturn
	aload_0
	invokevirtual	Method sym:()Lscala/reflect/Symbol;
l1	areturn
  Labels:
   	l1 = 50 // areturn

public boolean canEqual(java.lang.Object);
  Signature: (Ljava/lang/Object;)Z
  Code:
   Stack=1, Locals=2, Args_size=2
	aload_1
	instanceof	class scala/reflect/ValDef
	ireturn
  Labels:

private final boolean gd14$1(scala.reflect.Symbol, scala.reflect.Tree);
  Signature: (Lscala/reflect/Symbol;Lscala/reflect/Tree;)Z
  Code:
   Stack=2, Locals=5, Args_size=3
	aload_1
	aload_0
	invokevirtual	Method sym:()Lscala/reflect/Symbol;
	astore_3
	dup
	ifnonnull	l1 // aload_3
	pop
	aload_3
	ifnull	l2 // aload_2
	goto	l3 // iconst_0
l1	aload_3
	invokevirtual	Method java/lang/Object.equals:(Ljava/lang/Object;)Z
	ifeq	l3 // iconst_0
l2	aload_2
	aload_0
	invokevirtual	Method rhs:()Lscala/reflect/Tree;
	astore	4
	dup
	ifnonnull	l4 // aload
	pop
	aload	4
	ifnull	l5 // iconst_1
	goto	l3 // iconst_0
l4	aload	4
	invokevirtual	Method java/lang/Object.equals:(Ljava/lang/Object;)Z
	ifeq	l3 // iconst_0
l5	iconst_1
	goto	l6 // ireturn
l3	iconst_0
l6	ireturn
  Labels:
   	l1 = 18 // aload_3
   	l2 = 25 // aload_2
   	l4 = 45 // aload
   	l5 = 53 // iconst_1
   	l3 = 57 // iconst_0
   	l6 = 58 // ireturn

public scala.reflect.ValDef(scala.reflect.Symbol, scala.reflect.Tree);
  Signature: (Lscala/reflect/Symbol;Lscala/reflect/Tree;)V
  Code:
   Stack=2, Locals=3, Args_size=3
	aload_0
	aload_1
	putfield	Field sym:Lscala/reflect/Symbol;
	aload_0
	aload_2
	putfield	Field rhs:Lscala/reflect/Tree;
	aload_0
	invokespecial	Method scala/reflect/Tree."<init>":()V
	aload_0
	invokestatic	Method scala/Product$class.$init$:(Lscala/Product;)V
	return
  Labels:
  LocalVariableTable: 
   Start  Length  Slot  Name   Signature
   0      19      0    this       Lscala/reflect/ValDef;
   0      19      1    sym       Lscala/reflect/Symbol;
   0      19      2    rhs       Lscala/reflect/Tree;


}

