Compiled from "ContentModel.scala"
public final class scala.xml.dtd.ANY extends java.lang.Object
  SourceFile: "ContentModel.scala"
  ScalaSig: length = 0x3
   05 00 00 
  RuntimeVisibleAnnotations: length = 0xB
   00 01 00 2B 00 01 00 2C 73 00 2D 
  minor version: 0
  major version: 49
  Constant pool:
Asciz	SourceFile;
Asciz	ContentModel.scala;
Asciz	productElements;
Asciz	()Lscala/collection/Iterator;;
Asciz	Code;
Asciz	scala/xml/dtd/ANY$;
class	scala/xml/dtd/ANY$
Asciz	MODULE$;
Asciz	Lscala/xml/dtd/ANY$;;
NameAndType	MODULE$:Lscala/xml/dtd/ANY$;
Field	scala/xml/dtd/ANY$.MODULE$:Lscala/xml/dtd/ANY$;
NameAndType	productElements:()Lscala/collection/Iterator;
Method	scala/xml/dtd/ANY$.productElements:()Lscala/collection/Iterator;
Asciz	Deprecated;
Asciz	productIterator;
NameAndType	productIterator:()Lscala/collection/Iterator;
Method	scala/xml/dtd/ANY$.productIterator:()Lscala/collection/Iterator;
Asciz	productElementName;
Asciz	(I)Ljava/lang/String;;
NameAndType	productElementName:(I)Ljava/lang/String;
Method	scala/xml/dtd/ANY$.productElementName:(I)Ljava/lang/String;
Asciz	canEqual;
Asciz	(Ljava/lang/Object;)Z;
NameAndType	canEqual:(Ljava/lang/Object;)Z
Method	scala/xml/dtd/ANY$.canEqual:(Ljava/lang/Object;)Z
Asciz	productElement;
Asciz	(I)Ljava/lang/Object;;
NameAndType	productElement:(I)Ljava/lang/Object;
Method	scala/xml/dtd/ANY$.productElement:(I)Ljava/lang/Object;
Asciz	productArity;
Asciz	()I;
NameAndType	productArity:()I
Method	scala/xml/dtd/ANY$.productArity:()I
Asciz	productPrefix;
Asciz	()Ljava/lang/String;;
NameAndType	productPrefix:()Ljava/lang/String;
Method	scala/xml/dtd/ANY$.productPrefix:()Ljava/lang/String;
Asciz	buildString;
Asciz	(Lscala/collection/mutable/StringBuilder;)Lscala/collection/mutable/StringBuilder;;
NameAndType	buildString:(Lscala/collection/mutable/StringBuilder;)Lscala/collection/mutable/StringBuilder;
Method	scala/xml/dtd/ANY$.buildString:(Lscala/collection/mutable/StringBuilder;)Lscala/collection/mutable/StringBuilder;
Asciz	ScalaSig;
Asciz	Lscala/reflect/ScalaSignature;;
Asciz	bytes;
Asciz	Y;Q!\t&\t1!(Z\tA!AeiT!!alGNC8-7b\"AC\t1E)):K6B#U\"AC\nA!D\"p]R,g^'pIdC\n1B-6-7b\nTWm;I1BA&o3vGRDQ!Gi\taP5oSRtD#A\tqYAI\t,3TiJLgn=)\"aH*cBA%#BA\ta$o\8u}%\tq!'\r9/Y2lC,B*5FO]5oO\n+3fe*aEWm\rAHg\nD\"L%\tELaJ|G-^2u!J,g-==\"MER!AM\t1gni!!.<b\t1GTiJLgn\tq-!\t!C!saO]8ek$I]5usV\t!w%AH:$ \tII AxZ;dicW-\3oiRi\t%K!AsCE{\ta$G\t\"H!M\#rkdGC%L!\t*K\r\t9!i\8mKtb#F\r\t.!\t!C\tY!/Z1e%x<f)yCQ\t\tGPE*,7\rM\"A+\nU3!D:fe&G.>bE2,;
Asciz	RuntimeVisibleAnnotations;
Asciz	scala/xml/dtd/ANY;
class	scala/xml/dtd/ANY
Asciz	java/lang/Object;
class	java/lang/Object

{
public static final scala.collection.Iterator productElements();
  Signature: ()Lscala/collection/Iterator;
  Code:
   Stack=1, Locals=0, Args_size=0
	getstatic	Field scala/xml/dtd/ANY$.MODULE$:Lscala/xml/dtd/ANY$;
	invokevirtual	Method scala/xml/dtd/ANY$.productElements:()Lscala/collection/Iterator;
	areturn
  Labels:
  Deprecated: true

public static final scala.collection.Iterator productIterator();
  Signature: ()Lscala/collection/Iterator;
  Code:
   Stack=1, Locals=0, Args_size=0
	getstatic	Field scala/xml/dtd/ANY$.MODULE$:Lscala/xml/dtd/ANY$;
	invokevirtual	Method scala/xml/dtd/ANY$.productIterator:()Lscala/collection/Iterator;
	areturn
  Labels:

public static final java.lang.String productElementName(int);
  Signature: (I)Ljava/lang/String;
  Code:
   Stack=2, Locals=1, Args_size=1
	getstatic	Field scala/xml/dtd/ANY$.MODULE$:Lscala/xml/dtd/ANY$;
	iload_0
	invokevirtual	Method scala/xml/dtd/ANY$.productElementName:(I)Ljava/lang/String;
	areturn
  Labels:

public static final boolean canEqual(java.lang.Object);
  Signature: (Ljava/lang/Object;)Z
  Code:
   Stack=2, Locals=1, Args_size=1
	getstatic	Field scala/xml/dtd/ANY$.MODULE$:Lscala/xml/dtd/ANY$;
	aload_0
	invokevirtual	Method scala/xml/dtd/ANY$.canEqual:(Ljava/lang/Object;)Z
	ireturn
  Labels:

public static final java.lang.Object productElement(int);
  Signature: (I)Ljava/lang/Object;
  Code:
   Stack=2, Locals=1, Args_size=1
	getstatic	Field scala/xml/dtd/ANY$.MODULE$:Lscala/xml/dtd/ANY$;
	iload_0
	invokevirtual	Method scala/xml/dtd/ANY$.productElement:(I)Ljava/lang/Object;
	areturn
  Labels:

public static final int productArity();
  Signature: ()I
  Code:
   Stack=1, Locals=0, Args_size=0
	getstatic	Field scala/xml/dtd/ANY$.MODULE$:Lscala/xml/dtd/ANY$;
	invokevirtual	Method scala/xml/dtd/ANY$.productArity:()I
	ireturn
  Labels:

public static final java.lang.String productPrefix();
  Signature: ()Ljava/lang/String;
  Code:
   Stack=1, Locals=0, Args_size=0
	getstatic	Field scala/xml/dtd/ANY$.MODULE$:Lscala/xml/dtd/ANY$;
	invokevirtual	Method scala/xml/dtd/ANY$.productPrefix:()Ljava/lang/String;
	areturn
  Labels:

public static final scala.collection.mutable.StringBuilder buildString(scala.collection.mutable.StringBuilder);
  Signature: (Lscala/collection/mutable/StringBuilder;)Lscala/collection/mutable/StringBuilder;
  Code:
   Stack=2, Locals=1, Args_size=1
	getstatic	Field scala/xml/dtd/ANY$.MODULE$:Lscala/xml/dtd/ANY$;
	aload_0
	invokevirtual	Method scala/xml/dtd/ANY$.buildString:(Lscala/collection/mutable/StringBuilder;)Lscala/collection/mutable/StringBuilder;
	areturn
  Labels:

}

