Compiled from "Decl.scala"
public class scala.xml.dtd.AttListDecl extends scala.xml.dtd.MarkupDecl implements scala.ScalaObject,scala.Product,java.io.Serializable
  SourceFile: "Decl.scala"
  ScalaSig: length = 0x48A
   05 00 FFFFFF81 27 06 08 01 02 FFFFFF84 FFFFFF80 FFFFFF80 FFFFFF80 40 09 02 0B
   41 74 74 4C 69 73 74 44 65 63 6C 0A 02 03 04 01
   03 64 74 64 0A 02 05 06 01 03 78 6D 6C 0A 01 07
   01 05 73 63 61 6C 61 03 00 13 04 00 0A 0E 12 10
   02 0B 0C 0D 01 02 09 02 0D 02 02 0A 4D 61 72 6B
   75 70 44 65 63 6C 10 02 0F 10 0D 01 06 09 02 11
   06 02 0B 53 63 61 6C 61 4F 62 6A 65 63 74 10 02
   0F 13 09 02 14 06 02 07 50 72 6F 64 75 63 74 08
   08 16 00 FFFFFF82 FFFFFFCA FFFFFF80 FFFFFF84 00 17 01 04 6E 61 6D 65 15
   01 18 10 02 19 1C 0E 02 0F 1A 09 02 1B 06 01 06
   50 72 65 64 65 66 09 02 1D 1E 02 06 53 74 72 69
   6E 67 0A 02 1B 06 08 08 20 00 FFFFFF82 FFFFFF88 FFFFFFA0 FFFFFF80 04 18
   01 05 6E 61 6D 65 20 08 08 22 00 FFFFFF82 FFFFFFCA FFFFFF80 FFFFFF84 00
   23 01 05 61 74 74 72 73 15 01 24 10 03 25 2D 30
   0E 02 26 2B 0E 02 27 2A 0D 01 28 0A 02 29 08 01
   06 3C 72 6F 6F 74 3E 09 01 07 09 02 2C 06 01 07
   70 61 63 6B 61 67 65 09 02 2E 2F 02 04 4C 69 73
   74 0A 02 2C 06 10 02 0B 31 09 02 32 02 02 08 41
   74 74 72 44 65 63 6C 08 08 34 00 FFFFFF82 FFFFFF88 FFFFFFA0 FFFFFF80 04
   24 01 06 61 74 74 72 73 20 08 05 36 00 FFFFFF84 00 37
   01 06 3C 69 6E 69 74 3E 14 03 38 39 3A 10 02 0B
   00 08 05 16 35 FFFFFFC0 00 18 08 05 22 35 FFFFFFC0 00 24 08
   05 3C 00 FFFFFF84 20 3D 01 0B 62 75 69 6C 64 53 74 72
   69 6E 67 14 02 3E 41 10 02 25 3F 09 02 40 2F 02
   0D 53 74 72 69 6E 67 42 75 69 6C 64 65 72 08 05
   42 3B FFFFFFC0 00 3E 01 02 73 62 08 07 44 00 FFFFFF81 FFFFFF80 FFFFFF84
   00 45 01 04 63 6F 70 79 14 03 38 46 47 08 07 16
   43 FFFFFF90 FFFFFF80 FFFFFFC0 00 18 08 07 22 43 FFFFFF90 FFFFFF80 FFFFFFC0 00 24 08
   07 49 00 FFFFFF91 FFFFFF80 FFFFFF84 00 4A 01 0E 63 6F 70 79 24 64
   65 66 61 75 6C 74 24 31 15 01 4B 2A 02 18 4C 2B
   01 4D 10 02 4E 53 0D 01 4F 0A 02 50 51 01 09 75
   6E 63 68 65 63 6B 65 64 0A 02 52 06 01 0A 61 6E
   6E 6F 74 61 74 69 6F 6E 09 02 54 4F 02 11 75 6E
   63 68 65 63 6B 65 64 56 61 72 69 61 6E 63 65 08
   07 56 00 FFFFFF91 FFFFFF80 FFFFFF84 00 57 01 0E 63 6F 70 79 24 64
   65 66 61 75 6C 74 24 32 15 01 58 2A 02 24 4C 08
   08 5A 00 FFFFFF84 FFFFFF80 FFFFFF80 FFFFFF84 20 5B 01 08 68 61 73 68 43
   6F 64 65 14 01 5C 10 02 0F 5D 09 02 5E 06 02 03
   49 6E 74 08 08 60 00 FFFFFF84 FFFFFF80 FFFFFF80 FFFFFF84 20 61 01 08 74
   6F 53 74 72 69 6E 67 14 01 18 08 08 63 00 FFFFFF84 FFFFFF80
   FFFFFF80 FFFFFF84 20 64 01 06 65 71 75 61 6C 73 14 02 65 68
   10 02 0F 66 09 02 67 06 02 07 42 6F 6F 6C 65 61
   6E 08 07 69 62 FFFFFF81 FFFFFF80 FFFFFFC0 00 6A 01 03 78 24 31 10
   02 0F 6B 09 02 6C 06 02 03 41 6E 79 08 08 6E 00
   FFFFFF84 FFFFFF80 FFFFFF80 FFFFFF84 20 6F 01 0D 70 72 6F 64 75 63 74 50
   72 65 66 69 78 15 01 70 10 02 71 76 0D 01 72 0A
   02 73 74 01 04 6C 61 6E 67 0A 01 75 01 04 6A 61
   76 61 09 02 1D 72 08 08 78 00 FFFFFF84 FFFFFF80 FFFFFF80 FFFFFF84 20 79
   01 0C 70 72 6F 64 75 63 74 41 72 69 74 79 15 01
   5C 08 08 7B 00 FFFFFF84 FFFFFF80 FFFFFF80 FFFFFF84 20 7C 01 0E 70 72 6F
   64 75 63 74 45 6C 65 6D 65 6E 74 14 02 6A 7D 08
   07 69 7A FFFFFF81 FFFFFF80 FFFFFFC0 00 5C 08 09 7F 00 FFFFFF84 FFFFFF80 FFFFFF80 FFFFFF84
   20 FFFFFF81 00 01 12 70 72 6F 64 75 63 74 45 6C 65 6D
   65 6E 74 4E 61 6D 65 14 03 70 FFFFFF81 01 08 07 69 7E
   FFFFFF81 FFFFFF80 FFFFFFC0 00 5C 08 0A FFFFFF81 03 00 FFFFFF84 FFFFFF80 FFFFFF80 FFFFFF84 20 FFFFFF81
   04 01 08 63 61 6E 45 71 75 61 6C 14 03 65 FFFFFF81 05
   08 08 69 FFFFFF81 02 FFFFFF81 FFFFFF80 FFFFFFC0 00 6A 28 03 00 FFFFFF81 07 10
   03 0F FFFFFF81 08 09 03 FFFFFF81 09 06 02 0C 73 65 72 69 61
   6C 69 7A 61 62 6C 65 07 09 FFFFFF81 0B 02 FFFFFF81 FFFFFF80 FFFFFF88 02
   FFFFFF81 0C 01 0B 41 74 74 4C 69 73 74 44 65 63 6C 10
   03 0B FFFFFF81 0D 06 09 01 02 FFFFFF84 FFFFFF81 FFFFFF80 FFFFFF88 02 FFFFFF81 0E 13
   07 FFFFFF81 0D FFFFFF81 0F FFFFFF81 12 0E 10 03 71 FFFFFF81 10 09 03 FFFFFF81
   11 72 02 06 4F 62 6A 65 63 74 10 06 0F FFFFFF81 13 18
   24 38 09 03 FFFFFF81 14 06 02 09 46 75 6E 63 74 69 6F
   6E 32 08 07 36 FFFFFF81 0D FFFFFF84 00 FFFFFF81 16 14 02 FFFFFF81 0C 08
   0A FFFFFF81 18 FFFFFF81 0D FFFFFF81 FFFFFF80 FFFFFF84 40 FFFFFF81 19 01 05 61 70 70
   6C 79 14 05 38 FFFFFF81 1A FFFFFF81 1B 08 06 16 FFFFFF81 17 FFFFFFC0 00
   18 08 06 22 FFFFFF81 17 FFFFFFC0 00 24 08 0A FFFFFF81 1D FFFFFF81 0D FFFFFF81
   FFFFFF80 FFFFFF84 40 FFFFFF81 1E 01 07 75 6E 61 70 70 6C 79 14 04
   FFFFFF81 1F FFFFFF81 25 10 05 0F FFFFFF81 20 FFFFFF81 22 09 03 FFFFFF81 21 06
   02 06 4F 70 74 69 6F 6E 10 05 0F FFFFFF81 23 18 24 09
   03 FFFFFF81 24 06 02 06 54 75 70 6C 65 32 08 07 FFFFFF81 26
   FFFFFF81 1C FFFFFFC0 00 38 01 03 78 24 30 
  minor version: 0
  major version: 49
  Constant pool:
Asciz	SourceFile;
Asciz	Decl.scala;
Asciz	tupled;
Asciz	()Lscala/Function1;;
Asciz	Code;
Asciz	scala/xml/dtd/AttListDecl$;
class	scala/xml/dtd/AttListDecl$
Asciz	MODULE$;
Asciz	Lscala/xml/dtd/AttListDecl$;;
NameAndType	MODULE$:Lscala/xml/dtd/AttListDecl$;
Field	scala/xml/dtd/AttListDecl$.MODULE$:Lscala/xml/dtd/AttListDecl$;
NameAndType	tupled:()Lscala/Function1;
Method	scala/xml/dtd/AttListDecl$.tupled:()Lscala/Function1;
Asciz	curry;
NameAndType	curry:()Lscala/Function1;
Method	scala/xml/dtd/AttListDecl$.curry:()Lscala/Function1;
Asciz	Deprecated;
Asciz	curried;
NameAndType	curried:()Lscala/Function1;
Method	scala/xml/dtd/AttListDecl$.curried:()Lscala/Function1;
Asciz	attrs;
Asciz	Lscala/collection/immutable/List;;
Asciz	Lscala/collection/immutable/List<Lscala/xml/dtd/AttrDecl;>;;
Asciz	Signature;
Asciz	name;
Asciz	Ljava/lang/String;;
Asciz	productIterator;
Asciz	()Lscala/collection/Iterator;;
Asciz	LineNumberTable;
Asciz	scala/Product$class;
class	scala/Product$class
Asciz	(Lscala/Product;)Lscala/collection/Iterator;;
NameAndType	productIterator:(Lscala/Product;)Lscala/collection/Iterator;
Method	scala/Product$class.productIterator:(Lscala/Product;)Lscala/collection/Iterator;
Asciz	productElements;
NameAndType	productElements:(Lscala/Product;)Lscala/collection/Iterator;
Method	scala/Product$class.productElements:(Lscala/Product;)Lscala/collection/Iterator;
Asciz	copy$default$2;
Asciz	()Lscala/collection/immutable/List;;
Asciz	scala/xml/dtd/AttListDecl;
class	scala/xml/dtd/AttListDecl
NameAndType	attrs:()Lscala/collection/immutable/List;
Method	scala/xml/dtd/AttListDecl.attrs:()Lscala/collection/immutable/List;
Asciz	copy$default$1;
Asciz	()Ljava/lang/String;;
NameAndType	name:()Ljava/lang/String;
Method	scala/xml/dtd/AttListDecl.name:()Ljava/lang/String;
NameAndType	name:Ljava/lang/String;
Field	scala/xml/dtd/AttListDecl.name:Ljava/lang/String;
NameAndType	attrs:Lscala/collection/immutable/List;
Field	scala/xml/dtd/AttListDecl.attrs:Lscala/collection/immutable/List;
Asciz	()Lscala/collection/immutable/List<Lscala/xml/dtd/AttrDecl;>;;
Asciz	buildString;
Asciz	(Lscala/collection/mutable/StringBuilder;)Lscala/collection/mutable/StringBuilder;;
Asciz	<!ATTLIST ;
String	<!ATTLIST 
Asciz	scala/collection/mutable/StringBuilder;
class	scala/collection/mutable/StringBuilder
Asciz	append;
Asciz	(Ljava/lang/String;)Lscala/collection/mutable/StringBuilder;;
NameAndType	append:(Ljava/lang/String;)Lscala/collection/mutable/StringBuilder;
Method	scala/collection/mutable/StringBuilder.append:(Ljava/lang/String;)Lscala/collection/mutable/StringBuilder;
int	10;
Asciz	(C)Lscala/collection/mutable/StringBuilder;;
NameAndType	append:(C)Lscala/collection/mutable/StringBuilder;
Method	scala/collection/mutable/StringBuilder.append:(C)Lscala/collection/mutable/StringBuilder;
Asciz	;
String	
Asciz	\n;
String	\n
Asciz	>;
String	>
Asciz	scala/collection/TraversableLike;
class	scala/collection/TraversableLike
Asciz	mkString;
Asciz	(Ljava/lang/String;Ljava/lang/String;Ljava/lang/String;)Ljava/lang/String;;
NameAndType	mkString:(Ljava/lang/String;Ljava/lang/String;Ljava/lang/String;)Ljava/lang/String;
InterfaceMethod	scala/collection/TraversableLike.mkString:(Ljava/lang/String;Ljava/lang/String;Ljava/lang/String;)Ljava/lang/String;
Asciz	this;
Asciz	Lscala/xml/dtd/AttListDecl;;
Asciz	sb;
Asciz	Lscala/collection/mutable/StringBuilder;;
Asciz	LocalVariableTable;
Asciz	copy;
Asciz	(Ljava/lang/String;Lscala/collection/immutable/List;)Lscala/xml/dtd/AttListDecl;;
Asciz	<init>;
Asciz	(Ljava/lang/String;Lscala/collection/immutable/List;)V;
NameAndType	"<init>":(Ljava/lang/String;Lscala/collection/immutable/List;)V
Method	scala/xml/dtd/AttListDecl."<init>":(Ljava/lang/String;Lscala/collection/immutable/List;)V
Asciz	hashCode;
Asciz	()I;
Asciz	scala/runtime/ScalaRunTime$;
class	scala/runtime/ScalaRunTime$
Asciz	Lscala/runtime/ScalaRunTime$;;
NameAndType	MODULE$:Lscala/runtime/ScalaRunTime$;
Field	scala/runtime/ScalaRunTime$.MODULE$:Lscala/runtime/ScalaRunTime$;
Asciz	_hashCode;
Asciz	(Lscala/Product;)I;
NameAndType	_hashCode:(Lscala/Product;)I
Method	scala/runtime/ScalaRunTime$._hashCode:(Lscala/Product;)I
Asciz	toString;
Asciz	_toString;
Asciz	(Lscala/Product;)Ljava/lang/String;;
NameAndType	_toString:(Lscala/Product;)Ljava/lang/String;
Method	scala/runtime/ScalaRunTime$._toString:(Lscala/Product;)Ljava/lang/String;
Asciz	equals;
Asciz	(Ljava/lang/Object;)Z;
Asciz	gd2$1;
Asciz	(Ljava/lang/String;Lscala/collection/immutable/List;)Z;
NameAndType	gd2$1:(Ljava/lang/String;Lscala/collection/immutable/List;)Z
Method	scala/xml/dtd/AttListDecl.gd2$1:(Ljava/lang/String;Lscala/collection/immutable/List;)Z
Asciz	scala/Equals;
class	scala/Equals
Asciz	canEqual;
NameAndType	canEqual:(Ljava/lang/Object;)Z
InterfaceMethod	scala/Equals.canEqual:(Ljava/lang/Object;)Z
Asciz	temp7;
Asciz	Ljava/lang/Object;;
Asciz	temp8;
Asciz	temp9;
Asciz	temp10;
Asciz	attrs$1;
Asciz	name$2;
Asciz	productPrefix;
Asciz	AttListDecl;
String	AttListDecl
Asciz	productArity;
Asciz	productElement;
Asciz	(I)Ljava/lang/Object;;
Asciz	java/lang/IndexOutOfBoundsException;
class	java/lang/IndexOutOfBoundsException
Asciz	scala/runtime/BoxesRunTime;
class	scala/runtime/BoxesRunTime
Asciz	boxToInteger;
Asciz	(I)Ljava/lang/Integer;;
NameAndType	boxToInteger:(I)Ljava/lang/Integer;
Method	scala/runtime/BoxesRunTime.boxToInteger:(I)Ljava/lang/Integer;
Asciz	java/lang/Object;
class	java/lang/Object
NameAndType	toString:()Ljava/lang/String;
Method	java/lang/Object.toString:()Ljava/lang/String;
Asciz	(Ljava/lang/String;)V;
NameAndType	"<init>":(Ljava/lang/String;)V
Method	java/lang/IndexOutOfBoundsException."<init>":(Ljava/lang/String;)V
Asciz	temp11;
Asciz	I;
Asciz	productElementName;
Asciz	(I)Ljava/lang/String;;
String	attrs
String	name
Asciz	temp12;
NameAndType	equals:(Ljava/lang/Object;)Z
Method	java/lang/Object.equals:(Ljava/lang/Object;)Z
Asciz	scala/xml/dtd/MarkupDecl;
class	scala/xml/dtd/MarkupDecl
Asciz	()V;
NameAndType	"<init>":()V
Method	scala/xml/dtd/MarkupDecl."<init>":()V
Asciz	$init$;
Asciz	(Lscala/Product;)V;
NameAndType	$init$:(Lscala/Product;)V
Method	scala/Product$class.$init$:(Lscala/Product;)V
Asciz	(Ljava/lang/String;Lscala/collection/immutable/List<Lscala/xml/dtd/AttrDecl;>;)V;
Asciz	ScalaSig;
Asciz	scala/ScalaObject;
class	scala/ScalaObject
Asciz	scala/Product;
class	scala/Product
Asciz	java/io/Serializable;
class	java/io/Serializable

{
private final scala.collection.immutable.List attrs;
  Signature: Lscala/collection/immutable/List;
  Signature: length = 0x2
   00 17 

private final java.lang.String name;
  Signature: Ljava/lang/String;

public static final scala.Function1 tupled();
  Signature: ()Lscala/Function1;
  Code:
   Stack=1, Locals=0, Args_size=0
	getstatic	Field scala/xml/dtd/AttListDecl$.MODULE$:Lscala/xml/dtd/AttListDecl$;
	invokevirtual	Method scala/xml/dtd/AttListDecl$.tupled:()Lscala/Function1;
	areturn
  Labels:

public static final scala.Function1 curry();
  Signature: ()Lscala/Function1;
  Code:
   Stack=1, Locals=0, Args_size=0
	getstatic	Field scala/xml/dtd/AttListDecl$.MODULE$:Lscala/xml/dtd/AttListDecl$;
	invokevirtual	Method scala/xml/dtd/AttListDecl$.curry:()Lscala/Function1;
	areturn
  Labels:
  Deprecated: true

public static final scala.Function1 curried();
  Signature: ()Lscala/Function1;
  Code:
   Stack=1, Locals=0, Args_size=0
	getstatic	Field scala/xml/dtd/AttListDecl$.MODULE$:Lscala/xml/dtd/AttListDecl$;
	invokevirtual	Method scala/xml/dtd/AttListDecl$.curried:()Lscala/Function1;
	areturn
  Labels:

public scala.collection.Iterator productIterator();
  Signature: ()Lscala/collection/Iterator;
  Code:
   Stack=1, Locals=1, Args_size=1
	aload_0
	invokestatic	Method scala/Product$class.productIterator:(Lscala/Product;)Lscala/collection/Iterator;
	areturn
  Labels:

public scala.collection.Iterator productElements();
  Signature: ()Lscala/collection/Iterator;
  Code:
   Stack=1, Locals=1, Args_size=1
	aload_0
	invokestatic	Method scala/Product$class.productElements:(Lscala/Product;)Lscala/collection/Iterator;
	areturn
  Labels:
  Deprecated: true

public scala.collection.immutable.List copy$default$2();
  Signature: ()Lscala/collection/immutable/List;
  Code:
   Stack=1, Locals=1, Args_size=1
	aload_0
	invokevirtual	Method attrs:()Lscala/collection/immutable/List;
	areturn
  Labels:

public java.lang.String copy$default$1();
  Signature: ()Ljava/lang/String;
  Code:
   Stack=1, Locals=1, Args_size=1
	aload_0
	invokevirtual	Method name:()Ljava/lang/String;
	areturn
  Labels:

public java.lang.String name();
  Signature: ()Ljava/lang/String;
  Code:
   Stack=1, Locals=1, Args_size=1
	aload_0
	getfield	Field name:Ljava/lang/String;
	areturn
  Labels:

public scala.collection.immutable.List attrs();
  Signature: ()Lscala/collection/immutable/List;
  Code:
   Stack=1, Locals=1, Args_size=1
	aload_0
	getfield	Field attrs:Lscala/collection/immutable/List;
	areturn
  Labels:
  Signature: length = 0x2
   00 34 

public scala.collection.mutable.StringBuilder buildString(scala.collection.mutable.StringBuilder);
  Signature: (Lscala/collection/mutable/StringBuilder;)Lscala/collection/mutable/StringBuilder;
  Code:
   Stack=5, Locals=2, Args_size=2
	aload_1
	ldc	String <!ATTLIST 
	invokevirtual	Method scala/collection/mutable/StringBuilder.append:(Ljava/lang/String;)Lscala/collection/mutable/StringBuilder;
	aload_0
	invokevirtual	Method name:()Ljava/lang/String;
	invokevirtual	Method scala/collection/mutable/StringBuilder.append:(Ljava/lang/String;)Lscala/collection/mutable/StringBuilder;
	ldc	int 10
	invokevirtual	Method scala/collection/mutable/StringBuilder.append:(C)Lscala/collection/mutable/StringBuilder;
	aload_0
	invokevirtual	Method attrs:()Lscala/collection/immutable/List;
	ldc	String 
	ldc	String \n
	ldc	String >
	invokeinterface	InterfaceMethod scala/collection/TraversableLike.mkString:(Ljava/lang/String;Ljava/lang/String;Ljava/lang/String;)Ljava/lang/String;
	invokevirtual	Method scala/collection/mutable/StringBuilder.append:(Ljava/lang/String;)Lscala/collection/mutable/StringBuilder;
	areturn
  Labels:
  LocalVariableTable: 
   Start  Length  Slot  Name   Signature
   0      37      0    this       Lscala/xml/dtd/AttListDecl;
   0      37      1    sb       Lscala/collection/mutable/StringBuilder;


public scala.xml.dtd.AttListDecl copy(java.lang.String, scala.collection.immutable.List);
  Signature: (Ljava/lang/String;Lscala/collection/immutable/List;)Lscala/xml/dtd/AttListDecl;
  Code:
   Stack=4, Locals=3, Args_size=3
	new	class scala/xml/dtd/AttListDecl
	dup
	aload_1
	aload_2
	invokespecial	Method "<init>":(Ljava/lang/String;Lscala/collection/immutable/List;)V
	areturn
  Labels:
  LocalVariableTable: 
   Start  Length  Slot  Name   Signature
   0      10      0    this       Lscala/xml/dtd/AttListDecl;
   0      10      1    name       Ljava/lang/String;
   0      10      2    attrs       Lscala/collection/immutable/List;


public int hashCode();
  Signature: ()I
  Code:
   Stack=2, Locals=1, Args_size=1
	getstatic	Field scala/runtime/ScalaRunTime$.MODULE$:Lscala/runtime/ScalaRunTime$;
	aload_0
	invokevirtual	Method scala/runtime/ScalaRunTime$._hashCode:(Lscala/Product;)I
	ireturn
  Labels:

public java.lang.String toString();
  Signature: ()Ljava/lang/String;
  Code:
   Stack=2, Locals=1, Args_size=1
	getstatic	Field scala/runtime/ScalaRunTime$.MODULE$:Lscala/runtime/ScalaRunTime$;
	aload_0
	invokevirtual	Method scala/runtime/ScalaRunTime$._toString:(Lscala/Product;)Ljava/lang/String;
	areturn
  Labels:

public boolean equals(java.lang.Object);
  Signature: (Ljava/lang/Object;)Z
  Code:
   Stack=3, Locals=8, Args_size=2
	aload_0
	aload_1
	if_acmpeq	l1 // iconst_1
	aload_1
	astore_2
	aload_2
	instanceof	class scala/xml/dtd/AttListDecl
	ifeq	l2 // iconst_0
	aload_2
	checkcast	class scala/xml/dtd/AttListDecl
	astore_3
	aload_3
	invokevirtual	Method name:()Ljava/lang/String;
	astore	4
	aload_3
	invokevirtual	Method attrs:()Lscala/collection/immutable/List;
	astore	5
	aload	5
	astore	6
	aload	4
	astore	7
	aload_0
	aload	7
	aload	6
	invokespecial	Method gd2$1:(Ljava/lang/String;Lscala/collection/immutable/List;)Z
	ifeq	l3 // iconst_0
	aload_1
	checkcast	class scala/xml/dtd/AttListDecl
	aload_0
	invokeinterface	InterfaceMethod scala/Equals.canEqual:(Ljava/lang/Object;)Z
	goto	l4 // ifeq
l3	iconst_0
	goto	l4 // ifeq
l2	iconst_0
l4	ifeq	l5 // iconst_0
l1	iconst_1
	goto	l6 // ireturn
l5	iconst_0
l6	ireturn
  Labels:
   	l3 = 63 // iconst_0
   	l2 = 67 // iconst_0
   	l4 = 68 // ifeq
   	l1 = 71 // iconst_1
   	l5 = 75 // iconst_0
   	l6 = 76 // ireturn
  LocalVariableTable: 
   Start  Length  Slot  Name   Signature
   0      77      0    this       Lscala/xml/dtd/AttListDecl;
   7      64      2    temp7       Ljava/lang/Object;
   19      48      3    temp8       Lscala/xml/dtd/AttListDecl;
   25      42      4    temp9       Ljava/lang/String;
   31      36      5    temp10       Lscala/collection/immutable/List;
   35      32      6    attrs$1       Lscala/collection/immutable/List;
   39      28      7    name$2       Ljava/lang/String;


public java.lang.String productPrefix();
  Signature: ()Ljava/lang/String;
  Code:
   Stack=1, Locals=1, Args_size=1
	ldc	String AttListDecl
	areturn
  Labels:

public int productArity();
  Signature: ()I
  Code:
   Stack=1, Locals=1, Args_size=1
	iconst_2
	ireturn
  Labels:

public java.lang.Object productElement(int);
  Signature: (I)Ljava/lang/Object;
  Code:
   Stack=3, Locals=3, Args_size=2
	iload_1
	istore_2
	iload_2
	tableswitch{ //0 to 1
		0: 46;
		1: 39;
		default: 24 }
	new	class java/lang/IndexOutOfBoundsException
	dup
	iload_1
	invokestatic	Method scala/runtime/BoxesRunTime.boxToInteger:(I)Ljava/lang/Integer;
	invokevirtual	Method java/lang/Object.toString:()Ljava/lang/String;
	invokespecial	Method java/lang/IndexOutOfBoundsException."<init>":(Ljava/lang/String;)V
	athrow
	aload_0
	invokevirtual	Method attrs:()Lscala/collection/immutable/List;
	goto	l1 // areturn
	aload_0
	invokevirtual	Method name:()Ljava/lang/String;
l1	areturn
  Labels:
   	l1 = 50 // areturn
  LocalVariableTable: 
   Start  Length  Slot  Name   Signature
   0      51      0    this       Lscala/xml/dtd/AttListDecl;
   2      49      2    temp11       I


public java.lang.String productElementName(int);
  Signature: (I)Ljava/lang/String;
  Code:
   Stack=3, Locals=3, Args_size=2
	iload_1
	istore_2
	iload_2
	tableswitch{ //0 to 1
		0: 44;
		1: 39;
		default: 24 }
	new	class java/lang/IndexOutOfBoundsException
	dup
	iload_1
	invokestatic	Method scala/runtime/BoxesRunTime.boxToInteger:(I)Ljava/lang/Integer;
	invokevirtual	Method java/lang/Object.toString:()Ljava/lang/String;
	invokespecial	Method java/lang/IndexOutOfBoundsException."<init>":(Ljava/lang/String;)V
	athrow
	ldc	String attrs
	goto	l1 // areturn
	ldc	String name
l1	areturn
  Labels:
   	l1 = 46 // areturn
  LocalVariableTable: 
   Start  Length  Slot  Name   Signature
   0      47      0    this       Lscala/xml/dtd/AttListDecl;
   2      45      2    temp12       I


public boolean canEqual(java.lang.Object);
  Signature: (Ljava/lang/Object;)Z
  Code:
   Stack=1, Locals=2, Args_size=2
	aload_1
	instanceof	class scala/xml/dtd/AttListDecl
	ireturn
  Labels:

private final boolean gd2$1(java.lang.String, scala.collection.immutable.List);
  Signature: (Ljava/lang/String;Lscala/collection/immutable/List;)Z
  Code:
   Stack=2, Locals=5, Args_size=3
	aload_1
	aload_0
	invokevirtual	Method name:()Ljava/lang/String;
	astore_3
	dup
	ifnonnull	l1 // aload_3
	pop
	aload_3
	ifnull	l2 // aload_2
	goto	l3 // iconst_0
l1	aload_3
	invokevirtual	Method java/lang/Object.equals:(Ljava/lang/Object;)Z
	ifeq	l3 // iconst_0
l2	aload_2
	aload_0
	invokevirtual	Method attrs:()Lscala/collection/immutable/List;
	astore	4
	dup
	ifnonnull	l4 // aload
	pop
	aload	4
	ifnull	l5 // iconst_1
	goto	l3 // iconst_0
l4	aload	4
	invokevirtual	Method java/lang/Object.equals:(Ljava/lang/Object;)Z
	ifeq	l3 // iconst_0
l5	iconst_1
	goto	l6 // ireturn
l3	iconst_0
l6	ireturn
  Labels:
   	l1 = 18 // aload_3
   	l2 = 25 // aload_2
   	l4 = 45 // aload
   	l5 = 53 // iconst_1
   	l3 = 57 // iconst_0
   	l6 = 58 // ireturn

public scala.xml.dtd.AttListDecl(java.lang.String, scala.collection.immutable.List);
  Signature: (Ljava/lang/String;Lscala/collection/immutable/List;)V
  Code:
   Stack=2, Locals=3, Args_size=3
	aload_0
	aload_1
	putfield	Field name:Ljava/lang/String;
	aload_0
	aload_2
	putfield	Field attrs:Lscala/collection/immutable/List;
	aload_0
	invokespecial	Method scala/xml/dtd/MarkupDecl."<init>":()V
	aload_0
	invokestatic	Method scala/Product$class.$init$:(Lscala/Product;)V
	return
  Labels:
  LocalVariableTable: 
   Start  Length  Slot  Name   Signature
   0      19      0    this       Lscala/xml/dtd/AttListDecl;
   0      19      1    name       Ljava/lang/String;
   0      19      2    attrs       Lscala/collection/immutable/List;

  Signature: length = 0x2
   00 FFFFFFA3 

}

