Compiled from "Decl.scala"
public final class scala.xml.dtd.AttrDecl$ extends java.lang.Object implements scala.Function3,scala.ScalaObject
  SourceFile: "Decl.scala"
  Scala: length = 0x
   
  InnerClass: 
   public final $anonfun$toString$1=class scala/xml/dtd/AttrDecl$$anonfun$toString$1 of class scala/xml/dtd/AttrDecl
  minor version: 0
  major version: 49
  Constant pool:
Asciz	SourceFile;
Asciz	Decl.scala;
Asciz	Scala;
Asciz	MODULE$;
Asciz	Lscala/xml/dtd/AttrDecl$;;
Asciz	<clinit>;
Asciz	()V;
Asciz	Code;
Asciz	scala/xml/dtd/AttrDecl$;
class	scala/xml/dtd/AttrDecl$
Asciz	<init>;
NameAndType	"<init>":()V
Method	scala/xml/dtd/AttrDecl$."<init>":()V
Asciz	LineNumberTable;
Asciz	java/lang/Object;
class	java/lang/Object
Method	java/lang/Object."<init>":()V
NameAndType	MODULE$:Lscala/xml/dtd/AttrDecl$;
Field	scala/xml/dtd/AttrDecl$.MODULE$:Lscala/xml/dtd/AttrDecl$;
Asciz	scala/Function3$class;
class	scala/Function3$class
Asciz	$init$;
Asciz	(Lscala/Function3;)V;
NameAndType	$init$:(Lscala/Function3;)V
Method	scala/Function3$class.$init$:(Lscala/Function3;)V
Asciz	apply;
Asciz	(Ljava/lang/Object;Ljava/lang/Object;Ljava/lang/Object;)Ljava/lang/Object;;
Asciz	java/lang/String;
class	java/lang/String
Asciz	scala/xml/dtd/DefaultDecl;
class	scala/xml/dtd/DefaultDecl
Asciz	(Ljava/lang/String;Ljava/lang/String;Lscala/xml/dtd/DefaultDecl;)Lscala/xml/dtd/AttrDecl;;
NameAndType	apply:(Ljava/lang/String;Ljava/lang/String;Lscala/xml/dtd/DefaultDecl;)Lscala/xml/dtd/AttrDecl;
Method	scala/xml/dtd/AttrDecl$.apply:(Ljava/lang/String;Ljava/lang/String;Lscala/xml/dtd/DefaultDecl;)Lscala/xml/dtd/AttrDecl;
Asciz	this;
Asciz	v1;
Asciz	Ljava/lang/Object;;
Asciz	v2;
Asciz	v3;
Asciz	LocalVariableTable;
Asciz	scala/xml/dtd/AttrDecl;
class	scala/xml/dtd/AttrDecl
Asciz	(Ljava/lang/String;Ljava/lang/String;Lscala/xml/dtd/DefaultDecl;)V;
NameAndType	"<init>":(Ljava/lang/String;Ljava/lang/String;Lscala/xml/dtd/DefaultDecl;)V
Method	scala/xml/dtd/AttrDecl."<init>":(Ljava/lang/String;Ljava/lang/String;Lscala/xml/dtd/DefaultDecl;)V
Asciz	name;
Asciz	Ljava/lang/String;;
Asciz	tpe;
Asciz	default;
Asciz	Lscala/xml/dtd/DefaultDecl;;
Asciz	unapply;
Asciz	(Lscala/xml/dtd/AttrDecl;)Lscala/Some;;
Asciz	scala/Some;
class	scala/Some
Asciz	scala/Tuple3;
class	scala/Tuple3
Asciz	()Ljava/lang/String;;
NameAndType	name:()Ljava/lang/String;
Method	scala/xml/dtd/AttrDecl.name:()Ljava/lang/String;
NameAndType	tpe:()Ljava/lang/String;
Method	scala/xml/dtd/AttrDecl.tpe:()Ljava/lang/String;
Asciz	()Lscala/xml/dtd/DefaultDecl;;
NameAndType	default:()Lscala/xml/dtd/DefaultDecl;
Method	scala/xml/dtd/AttrDecl.default:()Lscala/xml/dtd/DefaultDecl;
Asciz	(Ljava/lang/Object;Ljava/lang/Object;Ljava/lang/Object;)V;
NameAndType	"<init>":(Ljava/lang/Object;Ljava/lang/Object;Ljava/lang/Object;)V
Method	scala/Tuple3."<init>":(Ljava/lang/Object;Ljava/lang/Object;Ljava/lang/Object;)V
Asciz	(Ljava/lang/Object;)V;
NameAndType	"<init>":(Ljava/lang/Object;)V
Method	scala/Some."<init>":(Ljava/lang/Object;)V
Asciz	x$0;
Asciz	Lscala/xml/dtd/AttrDecl;;
Asciz	tupled;
Asciz	()Lscala/Function1;;
Asciz	(Lscala/Function3;)Lscala/Function1;;
NameAndType	tupled:(Lscala/Function3;)Lscala/Function1;
Method	scala/Function3$class.tupled:(Lscala/Function3;)Lscala/Function1;
Asciz	curry;
NameAndType	curry:(Lscala/Function3;)Lscala/Function1;
Method	scala/Function3$class.curry:(Lscala/Function3;)Lscala/Function1;
Asciz	Deprecated;
Asciz	curried;
NameAndType	curried:(Lscala/Function3;)Lscala/Function1;
Method	scala/Function3$class.curried:(Lscala/Function3;)Lscala/Function1;
Asciz	toString;
Asciz	(Lscala/Function3;)Ljava/lang/String;;
NameAndType	toString:(Lscala/Function3;)Ljava/lang/String;
Method	scala/Function3$class.toString:(Lscala/Function3;)Ljava/lang/String;
Asciz	InnerClasses;
Asciz	scala/xml/dtd/AttrDecl$$anonfun$toString$1;
class	scala/xml/dtd/AttrDecl$$anonfun$toString$1
Asciz	$anonfun$toString$1;
Asciz	scala/Function3;
class	scala/Function3
Asciz	scala/ScalaObject;
class	scala/ScalaObject

{
public static final scala.xml.dtd.AttrDecl$ MODULE$;
  Signature: Lscala/xml/dtd/AttrDecl$;

public static {};
  Signature: ()V
  Code:
   Stack=1, Locals=0, Args_size=0
	new	class scala/xml/dtd/AttrDecl$
	invokespecial	Method "<init>":()V
	return
  Labels:

private scala.xml.dtd.AttrDecl$();
  Signature: ()V
  Code:
   Stack=1, Locals=1, Args_size=1
	aload_0
	invokespecial	Method java/lang/Object."<init>":()V
	aload_0
	putstatic	Field MODULE$:Lscala/xml/dtd/AttrDecl$;
	aload_0
	invokestatic	Method scala/Function3$class.$init$:(Lscala/Function3;)V
	return
  Labels:

public java.lang.Object apply(java.lang.Object, java.lang.Object, java.lang.Object);
  Signature: (Ljava/lang/Object;Ljava/lang/Object;Ljava/lang/Object;)Ljava/lang/Object;
  Code:
   Stack=4, Locals=4, Args_size=4
	aload_0
	aload_1
	checkcast	class java/lang/String
	aload_2
	checkcast	class java/lang/String
	aload_3
	checkcast	class scala/xml/dtd/DefaultDecl
	invokevirtual	Method apply:(Ljava/lang/String;Ljava/lang/String;Lscala/xml/dtd/DefaultDecl;)Lscala/xml/dtd/AttrDecl;
	areturn
  Labels:
  LocalVariableTable: 
   Start  Length  Slot  Name   Signature
   0      17      0    this       Lscala/xml/dtd/AttrDecl$;
   0      17      1    v1       Ljava/lang/Object;
   0      17      2    v2       Ljava/lang/Object;
   0      17      3    v3       Ljava/lang/Object;


public scala.xml.dtd.AttrDecl apply(java.lang.String, java.lang.String, scala.xml.dtd.DefaultDecl);
  Signature: (Ljava/lang/String;Ljava/lang/String;Lscala/xml/dtd/DefaultDecl;)Lscala/xml/dtd/AttrDecl;
  Code:
   Stack=5, Locals=4, Args_size=4
	new	class scala/xml/dtd/AttrDecl
	dup
	aload_1
	aload_2
	aload_3
	invokespecial	Method scala/xml/dtd/AttrDecl."<init>":(Ljava/lang/String;Ljava/lang/String;Lscala/xml/dtd/DefaultDecl;)V
	areturn
  Labels:
  LocalVariableTable: 
   Start  Length  Slot  Name   Signature
   0      11      0    this       Lscala/xml/dtd/AttrDecl$;
   0      11      1    name       Ljava/lang/String;
   0      11      2    tpe       Ljava/lang/String;
   0      11      3    default       Lscala/xml/dtd/DefaultDecl;


public scala.Some unapply(scala.xml.dtd.AttrDecl);
  Signature: (Lscala/xml/dtd/AttrDecl;)Lscala/Some;
  Code:
   Stack=7, Locals=2, Args_size=2
	new	class scala/Some
	dup
	new	class scala/Tuple3
	dup
	aload_1
	invokevirtual	Method scala/xml/dtd/AttrDecl.name:()Ljava/lang/String;
	aload_1
	invokevirtual	Method scala/xml/dtd/AttrDecl.tpe:()Ljava/lang/String;
	aload_1
	invokevirtual	Method scala/xml/dtd/AttrDecl.default:()Lscala/xml/dtd/DefaultDecl;
	invokespecial	Method scala/Tuple3."<init>":(Ljava/lang/Object;Ljava/lang/Object;Ljava/lang/Object;)V
	invokespecial	Method scala/Some."<init>":(Ljava/lang/Object;)V
	areturn
  Labels:
  LocalVariableTable: 
   Start  Length  Slot  Name   Signature
   0      27      0    this       Lscala/xml/dtd/AttrDecl$;
   0      27      1    x$0       Lscala/xml/dtd/AttrDecl;


public scala.Function1 tupled();
  Signature: ()Lscala/Function1;
  Code:
   Stack=1, Locals=1, Args_size=1
	aload_0
	invokestatic	Method scala/Function3$class.tupled:(Lscala/Function3;)Lscala/Function1;
	areturn
  Labels:

public scala.Function1 curry();
  Signature: ()Lscala/Function1;
  Code:
   Stack=1, Locals=1, Args_size=1
	aload_0
	invokestatic	Method scala/Function3$class.curry:(Lscala/Function3;)Lscala/Function1;
	areturn
  Labels:
  Deprecated: true

public scala.Function1 curried();
  Signature: ()Lscala/Function1;
  Code:
   Stack=1, Locals=1, Args_size=1
	aload_0
	invokestatic	Method scala/Function3$class.curried:(Lscala/Function3;)Lscala/Function1;
	areturn
  Labels:

public java.lang.String toString();
  Signature: ()Ljava/lang/String;
  Code:
   Stack=1, Locals=1, Args_size=1
	aload_0
	invokestatic	Method scala/Function3$class.toString:(Lscala/Function3;)Ljava/lang/String;
	areturn
  Labels:

}

