Compiled from "Decl.scala"
public class scala.xml.dtd.AttrDecl extends java.lang.Object implements scala.ScalaObject,scala.Product,java.io.Serializable
  SourceFile: "Decl.scala"
  ScalaSig: length = 0x4BD
   05 00 FFFFFF81 2A 06 08 01 02 FFFFFF84 FFFFFF80 FFFFFF80 FFFFFF80 40 09 02 08
   41 74 74 72 44 65 63 6C 0A 02 03 04 01 03 64 74
   64 0A 02 05 06 01 03 78 6D 6C 0A 01 07 01 05 73
   63 61 6C 61 03 00 13 04 00 0A 12 16 10 02 0B 10
   0D 01 0C 0A 02 0D 0E 01 04 6C 61 6E 67 0A 01 0F
   01 04 6A 61 76 61 09 02 11 0C 02 06 4F 62 6A 65
   63 74 10 02 13 14 0D 01 06 09 02 15 06 02 0B 53
   63 61 6C 61 4F 62 6A 65 63 74 10 02 13 17 09 02
   18 06 02 07 50 72 6F 64 75 63 74 08 08 1A 00 FFFFFF82
   FFFFFFCA FFFFFF80 FFFFFF84 00 1B 01 04 6E 61 6D 65 15 01 1C 10 02
   1D 20 0E 02 13 1E 09 02 1F 06 01 06 50 72 65 64
   65 66 09 02 21 22 02 06 53 74 72 69 6E 67 0A 02
   1F 06 08 08 24 00 FFFFFF82 FFFFFF88 FFFFFFA0 FFFFFF80 04 1C 01 05 6E 61
   6D 65 20 08 08 26 00 FFFFFF82 FFFFFFCA FFFFFF80 FFFFFF84 00 1B 01 03 74
   70 65 08 08 28 00 FFFFFF82 FFFFFF88 FFFFFFA0 FFFFFF80 04 1C 01 04 74 70
   65 20 08 08 2A 00 FFFFFF82 FFFFFFCA FFFFFF80 FFFFFF84 00 2B 01 07 64 65
   66 61 75 6C 74 15 01 2C 10 02 2D 2E 0D 01 02 09
   02 2F 02 02 0B 44 65 66 61 75 6C 74 44 65 63 6C
   08 08 31 00 FFFFFF82 FFFFFF88 FFFFFFA0 FFFFFF80 04 2C 01 08 64 65 66 61
   75 6C 74 20 08 05 33 00 FFFFFF84 00 34 01 06 3C 69 6E
   69 74 3E 14 04 35 36 37 38 10 02 2D 00 08 05 1A
   32 FFFFFFC0 00 1C 08 05 26 32 FFFFFFC0 00 1C 08 05 2A 32 FFFFFFC0
   00 2C 08 05 3A 00 FFFFFF84 20 3B 01 08 74 6F 53 74 72
   69 6E 67 14 01 1C 08 05 3D 00 FFFFFF84 00 3E 01 0B 62
   75 69 6C 64 53 74 72 69 6E 67 14 02 3F 4B 10 02
   40 48 0E 02 41 46 0E 02 42 45 0D 01 43 0A 02 44
   08 01 06 3C 72 6F 6F 74 3E 09 01 07 09 02 47 06
   01 07 70 61 63 6B 61 67 65 09 02 49 4A 02 0D 53
   74 72 69 6E 67 42 75 69 6C 64 65 72 0A 02 47 06
   08 05 4C 3C FFFFFFC0 00 3F 01 02 73 62 08 07 4E 00 FFFFFF81
   FFFFFF80 FFFFFF84 00 4F 01 04 63 6F 70 79 14 04 35 50 51 52
   08 07 1A 4D FFFFFF90 FFFFFF80 FFFFFFC0 00 1C 08 07 26 4D FFFFFF90 FFFFFF80 FFFFFFC0
   00 1C 08 07 2A 4D FFFFFF90 FFFFFF80 FFFFFFC0 00 2C 08 07 54 00 FFFFFF91
   FFFFFF80 FFFFFF84 00 55 01 0E 63 6F 70 79 24 64 65 66 61 75
   6C 74 24 31 15 01 56 2A 02 1C 57 2B 01 58 10 02
   59 5E 0D 01 5A 0A 02 5B 5C 01 09 75 6E 63 68 65
   63 6B 65 64 0A 02 5D 06 01 0A 61 6E 6E 6F 74 61
   74 69 6F 6E 09 02 5F 5A 02 11 75 6E 63 68 65 63
   6B 65 64 56 61 72 69 61 6E 63 65 08 07 61 00 FFFFFF91
   FFFFFF80 FFFFFF84 00 55 01 0E 63 6F 70 79 24 64 65 66 61 75
   6C 74 24 32 08 07 63 00 FFFFFF91 FFFFFF80 FFFFFF84 00 64 01 0E 63
   6F 70 79 24 64 65 66 61 75 6C 74 24 33 15 01 65
   2A 02 2C 57 08 08 67 00 FFFFFF84 FFFFFF80 FFFFFF80 FFFFFF84 20 68 01 08
   68 61 73 68 43 6F 64 65 14 01 69 10 02 13 6A 09
   02 6B 06 02 03 49 6E 74 08 08 6D 00 FFFFFF84 FFFFFF80 FFFFFF80 FFFFFF84
   20 6E 01 06 65 71 75 61 6C 73 14 02 6F 72 10 02
   13 70 09 02 71 06 02 07 42 6F 6F 6C 65 61 6E 08
   07 73 6C FFFFFF81 FFFFFF80 FFFFFFC0 00 74 01 03 78 24 31 10 02 13
   75 09 02 76 06 02 03 41 6E 79 08 08 78 00 FFFFFF84 FFFFFF80
   FFFFFF80 FFFFFF84 20 79 01 0D 70 72 6F 64 75 63 74 50 72 65
   66 69 78 15 01 7A 10 02 0B 7B 09 02 21 0C 08 08
   7D 00 FFFFFF84 FFFFFF80 FFFFFF80 FFFFFF84 20 7E 01 0C 70 72 6F 64 75 63
   74 41 72 69 74 79 15 01 69 08 0A FFFFFF81 00 00 FFFFFF84 FFFFFF80
   FFFFFF80 FFFFFF84 20 FFFFFF81 01 01 0E 70 72 6F 64 75 63 74 45 6C
   65 6D 65 6E 74 14 03 74 FFFFFF81 02 08 07 73 7F FFFFFF81 FFFFFF80
   FFFFFFC0 00 69 08 0A FFFFFF81 04 00 FFFFFF84 FFFFFF80 FFFFFF80 FFFFFF84 20 FFFFFF81 05 01
   12 70 72 6F 64 75 63 74 45 6C 65 6D 65 6E 74 4E
   61 6D 65 14 03 7A FFFFFF81 06 08 08 73 FFFFFF81 03 FFFFFF81 FFFFFF80 FFFFFFC0
   00 69 08 0A FFFFFF81 08 00 FFFFFF84 FFFFFF80 FFFFFF80 FFFFFF84 20 FFFFFF81 09 01 08
   63 61 6E 45 71 75 61 6C 14 03 6F FFFFFF81 0A 08 08 73
   FFFFFF81 07 FFFFFF81 FFFFFF80 FFFFFFC0 00 74 28 03 00 FFFFFF81 0C 10 03 13 FFFFFF81
   0D 09 03 FFFFFF81 0E 06 02 0C 73 65 72 69 61 6C 69 7A
   61 62 6C 65 07 09 FFFFFF81 10 02 FFFFFF81 FFFFFF80 FFFFFF88 02 FFFFFF81 11 01
   08 41 74 74 72 44 65 63 6C 10 03 2D FFFFFF81 12 06 09
   01 02 FFFFFF84 FFFFFF81 FFFFFF80 FFFFFF88 02 FFFFFF81 13 13 06 FFFFFF81 12 0A FFFFFF81 14
   12 10 07 13 FFFFFF81 15 1C 1C 2C 35 09 03 FFFFFF81 16 06 02
   09 46 75 6E 63 74 69 6F 6E 33 08 07 33 FFFFFF81 12 FFFFFF84
   00 FFFFFF81 18 14 02 FFFFFF81 11 08 0A FFFFFF81 1A FFFFFF81 12 FFFFFF81 FFFFFF80 FFFFFF84
   40 FFFFFF81 1B 01 05 61 70 70 6C 79 14 07 35 FFFFFF81 1C FFFFFF81
   1D FFFFFF81 1E 08 06 1A FFFFFF81 19 FFFFFFC0 00 1C 08 06 26 FFFFFF81 19
   FFFFFFC0 00 1C 08 06 2A FFFFFF81 19 FFFFFFC0 00 2C 08 0A FFFFFF81 20 FFFFFF81
   12 FFFFFF81 FFFFFF80 FFFFFF84 40 FFFFFF81 21 01 07 75 6E 61 70 70 6C 79
   14 04 FFFFFF81 22 FFFFFF81 28 10 05 13 FFFFFF81 23 FFFFFF81 25 09 03 FFFFFF81
   24 06 02 06 4F 70 74 69 6F 6E 10 06 13 FFFFFF81 26 1C
   1C 2C 09 03 FFFFFF81 27 06 02 06 54 75 70 6C 65 33 08
   07 FFFFFF81 29 FFFFFF81 1F FFFFFFC0 00 35 01 03 78 24 30 
  InnerClass: 
   public final $anonfun$toString$1=class scala/xml/dtd/AttrDecl$$anonfun$toString$1 of class scala/xml/dtd/AttrDecl
  minor version: 0
  major version: 49
  Constant pool:
Asciz	SourceFile;
Asciz	Decl.scala;
Asciz	tupled;
Asciz	()Lscala/Function1;;
Asciz	Code;
Asciz	scala/xml/dtd/AttrDecl$;
class	scala/xml/dtd/AttrDecl$
Asciz	MODULE$;
Asciz	Lscala/xml/dtd/AttrDecl$;;
NameAndType	MODULE$:Lscala/xml/dtd/AttrDecl$;
Field	scala/xml/dtd/AttrDecl$.MODULE$:Lscala/xml/dtd/AttrDecl$;
NameAndType	tupled:()Lscala/Function1;
Method	scala/xml/dtd/AttrDecl$.tupled:()Lscala/Function1;
Asciz	curry;
NameAndType	curry:()Lscala/Function1;
Method	scala/xml/dtd/AttrDecl$.curry:()Lscala/Function1;
Asciz	Deprecated;
Asciz	curried;
NameAndType	curried:()Lscala/Function1;
Method	scala/xml/dtd/AttrDecl$.curried:()Lscala/Function1;
Asciz	default;
Asciz	Lscala/xml/dtd/DefaultDecl;;
Asciz	tpe;
Asciz	Ljava/lang/String;;
Asciz	name;
Asciz	productIterator;
Asciz	()Lscala/collection/Iterator;;
Asciz	LineNumberTable;
Asciz	scala/Product$class;
class	scala/Product$class
Asciz	(Lscala/Product;)Lscala/collection/Iterator;;
NameAndType	productIterator:(Lscala/Product;)Lscala/collection/Iterator;
Method	scala/Product$class.productIterator:(Lscala/Product;)Lscala/collection/Iterator;
Asciz	productElements;
NameAndType	productElements:(Lscala/Product;)Lscala/collection/Iterator;
Method	scala/Product$class.productElements:(Lscala/Product;)Lscala/collection/Iterator;
Asciz	copy$default$3;
Asciz	()Lscala/xml/dtd/DefaultDecl;;
Asciz	scala/xml/dtd/AttrDecl;
class	scala/xml/dtd/AttrDecl
NameAndType	default:()Lscala/xml/dtd/DefaultDecl;
Method	scala/xml/dtd/AttrDecl.default:()Lscala/xml/dtd/DefaultDecl;
Asciz	copy$default$2;
Asciz	()Ljava/lang/String;;
NameAndType	tpe:()Ljava/lang/String;
Method	scala/xml/dtd/AttrDecl.tpe:()Ljava/lang/String;
Asciz	copy$default$1;
NameAndType	name:()Ljava/lang/String;
Method	scala/xml/dtd/AttrDecl.name:()Ljava/lang/String;
NameAndType	name:Ljava/lang/String;
Field	scala/xml/dtd/AttrDecl.name:Ljava/lang/String;
NameAndType	tpe:Ljava/lang/String;
Field	scala/xml/dtd/AttrDecl.tpe:Ljava/lang/String;
NameAndType	default:Lscala/xml/dtd/DefaultDecl;
Field	scala/xml/dtd/AttrDecl.default:Lscala/xml/dtd/DefaultDecl;
Asciz	toString;
Asciz	scala/xml/Utility$;
class	scala/xml/Utility$
Asciz	Lscala/xml/Utility$;;
NameAndType	MODULE$:Lscala/xml/Utility$;
Field	scala/xml/Utility$.MODULE$:Lscala/xml/Utility$;
Asciz	scala/xml/dtd/AttrDecl$$anonfun$toString$1;
class	scala/xml/dtd/AttrDecl$$anonfun$toString$1
Asciz	<init>;
Asciz	(Lscala/xml/dtd/AttrDecl;)V;
NameAndType	"<init>":(Lscala/xml/dtd/AttrDecl;)V
Method	scala/xml/dtd/AttrDecl$$anonfun$toString$1."<init>":(Lscala/xml/dtd/AttrDecl;)V
Asciz	sbToString;
Asciz	(Lscala/Function1;)Ljava/lang/String;;
NameAndType	sbToString:(Lscala/Function1;)Ljava/lang/String;
Method	scala/xml/Utility$.sbToString:(Lscala/Function1;)Ljava/lang/String;
Asciz	buildString;
Asciz	(Lscala/collection/mutable/StringBuilder;)Lscala/collection/mutable/StringBuilder;;
Asciz	  ;
String	  
Asciz	scala/collection/mutable/StringBuilder;
class	scala/collection/mutable/StringBuilder
Asciz	append;
Asciz	(Ljava/lang/String;)Lscala/collection/mutable/StringBuilder;;
NameAndType	append:(Ljava/lang/String;)Lscala/collection/mutable/StringBuilder;
Method	scala/collection/mutable/StringBuilder.append:(Ljava/lang/String;)Lscala/collection/mutable/StringBuilder;
int	32;
Asciz	(C)Lscala/collection/mutable/StringBuilder;;
NameAndType	append:(C)Lscala/collection/mutable/StringBuilder;
Method	scala/collection/mutable/StringBuilder.append:(C)Lscala/collection/mutable/StringBuilder;
Asciz	scala/xml/dtd/DefaultDecl;
class	scala/xml/dtd/DefaultDecl
NameAndType	buildString:(Lscala/collection/mutable/StringBuilder;)Lscala/collection/mutable/StringBuilder;
Method	scala/xml/dtd/DefaultDecl.buildString:(Lscala/collection/mutable/StringBuilder;)Lscala/collection/mutable/StringBuilder;
Asciz	this;
Asciz	Lscala/xml/dtd/AttrDecl;;
Asciz	sb;
Asciz	Lscala/collection/mutable/StringBuilder;;
Asciz	LocalVariableTable;
Asciz	copy;
Asciz	(Ljava/lang/String;Ljava/lang/String;Lscala/xml/dtd/DefaultDecl;)Lscala/xml/dtd/AttrDecl;;
Asciz	(Ljava/lang/String;Ljava/lang/String;Lscala/xml/dtd/DefaultDecl;)V;
NameAndType	"<init>":(Ljava/lang/String;Ljava/lang/String;Lscala/xml/dtd/DefaultDecl;)V
Method	scala/xml/dtd/AttrDecl."<init>":(Ljava/lang/String;Ljava/lang/String;Lscala/xml/dtd/DefaultDecl;)V
Asciz	hashCode;
Asciz	()I;
Asciz	scala/runtime/ScalaRunTime$;
class	scala/runtime/ScalaRunTime$
Asciz	Lscala/runtime/ScalaRunTime$;;
NameAndType	MODULE$:Lscala/runtime/ScalaRunTime$;
Field	scala/runtime/ScalaRunTime$.MODULE$:Lscala/runtime/ScalaRunTime$;
Asciz	_hashCode;
Asciz	(Lscala/Product;)I;
NameAndType	_hashCode:(Lscala/Product;)I
Method	scala/runtime/ScalaRunTime$._hashCode:(Lscala/Product;)I
Asciz	equals;
Asciz	(Ljava/lang/Object;)Z;
Asciz	gd3$1;
Asciz	(Ljava/lang/String;Ljava/lang/String;Lscala/xml/dtd/DefaultDecl;)Z;
NameAndType	gd3$1:(Ljava/lang/String;Ljava/lang/String;Lscala/xml/dtd/DefaultDecl;)Z
Method	scala/xml/dtd/AttrDecl.gd3$1:(Ljava/lang/String;Ljava/lang/String;Lscala/xml/dtd/DefaultDecl;)Z
Asciz	scala/Equals;
class	scala/Equals
Asciz	canEqual;
NameAndType	canEqual:(Ljava/lang/Object;)Z
InterfaceMethod	scala/Equals.canEqual:(Ljava/lang/Object;)Z
Asciz	temp13;
Asciz	Ljava/lang/Object;;
Asciz	temp14;
Asciz	temp15;
Asciz	temp16;
Asciz	temp17;
Asciz	default$1;
Asciz	tpe$1;
Asciz	name$3;
Asciz	productPrefix;
Asciz	AttrDecl;
String	AttrDecl
Asciz	productArity;
Asciz	productElement;
Asciz	(I)Ljava/lang/Object;;
Asciz	java/lang/IndexOutOfBoundsException;
class	java/lang/IndexOutOfBoundsException
Asciz	scala/runtime/BoxesRunTime;
class	scala/runtime/BoxesRunTime
Asciz	boxToInteger;
Asciz	(I)Ljava/lang/Integer;;
NameAndType	boxToInteger:(I)Ljava/lang/Integer;
Method	scala/runtime/BoxesRunTime.boxToInteger:(I)Ljava/lang/Integer;
Asciz	java/lang/Object;
class	java/lang/Object
NameAndType	toString:()Ljava/lang/String;
Method	java/lang/Object.toString:()Ljava/lang/String;
Asciz	(Ljava/lang/String;)V;
NameAndType	"<init>":(Ljava/lang/String;)V
Method	java/lang/IndexOutOfBoundsException."<init>":(Ljava/lang/String;)V
Asciz	temp18;
Asciz	I;
Asciz	productElementName;
Asciz	(I)Ljava/lang/String;;
String	default
String	tpe
String	name
Asciz	temp19;
NameAndType	equals:(Ljava/lang/Object;)Z
Method	java/lang/Object.equals:(Ljava/lang/Object;)Z
Asciz	()V;
NameAndType	"<init>":()V
Method	java/lang/Object."<init>":()V
Asciz	$init$;
Asciz	(Lscala/Product;)V;
NameAndType	$init$:(Lscala/Product;)V
Method	scala/Product$class.$init$:(Lscala/Product;)V
Asciz	ScalaSig;
Asciz	InnerClasses;
Asciz	$anonfun$toString$1;
Asciz	scala/ScalaObject;
class	scala/ScalaObject
Asciz	scala/Product;
class	scala/Product
Asciz	java/io/Serializable;
class	java/io/Serializable

{
private final scala.xml.dtd.DefaultDecl default;
  Signature: Lscala/xml/dtd/DefaultDecl;

private final java.lang.String tpe;
  Signature: Ljava/lang/String;

private final java.lang.String name;
  Signature: Ljava/lang/String;

public static final scala.Function1 tupled();
  Signature: ()Lscala/Function1;
  Code:
   Stack=1, Locals=0, Args_size=0
	getstatic	Field scala/xml/dtd/AttrDecl$.MODULE$:Lscala/xml/dtd/AttrDecl$;
	invokevirtual	Method scala/xml/dtd/AttrDecl$.tupled:()Lscala/Function1;
	areturn
  Labels:

public static final scala.Function1 curry();
  Signature: ()Lscala/Function1;
  Code:
   Stack=1, Locals=0, Args_size=0
	getstatic	Field scala/xml/dtd/AttrDecl$.MODULE$:Lscala/xml/dtd/AttrDecl$;
	invokevirtual	Method scala/xml/dtd/AttrDecl$.curry:()Lscala/Function1;
	areturn
  Labels:
  Deprecated: true

public static final scala.Function1 curried();
  Signature: ()Lscala/Function1;
  Code:
   Stack=1, Locals=0, Args_size=0
	getstatic	Field scala/xml/dtd/AttrDecl$.MODULE$:Lscala/xml/dtd/AttrDecl$;
	invokevirtual	Method scala/xml/dtd/AttrDecl$.curried:()Lscala/Function1;
	areturn
  Labels:

public scala.collection.Iterator productIterator();
  Signature: ()Lscala/collection/Iterator;
  Code:
   Stack=1, Locals=1, Args_size=1
	aload_0
	invokestatic	Method scala/Product$class.productIterator:(Lscala/Product;)Lscala/collection/Iterator;
	areturn
  Labels:

public scala.collection.Iterator productElements();
  Signature: ()Lscala/collection/Iterator;
  Code:
   Stack=1, Locals=1, Args_size=1
	aload_0
	invokestatic	Method scala/Product$class.productElements:(Lscala/Product;)Lscala/collection/Iterator;
	areturn
  Labels:
  Deprecated: true

public scala.xml.dtd.DefaultDecl copy$default$3();
  Signature: ()Lscala/xml/dtd/DefaultDecl;
  Code:
   Stack=1, Locals=1, Args_size=1
	aload_0
	invokevirtual	Method default:()Lscala/xml/dtd/DefaultDecl;
	areturn
  Labels:

public java.lang.String copy$default$2();
  Signature: ()Ljava/lang/String;
  Code:
   Stack=1, Locals=1, Args_size=1
	aload_0
	invokevirtual	Method tpe:()Ljava/lang/String;
	areturn
  Labels:

public java.lang.String copy$default$1();
  Signature: ()Ljava/lang/String;
  Code:
   Stack=1, Locals=1, Args_size=1
	aload_0
	invokevirtual	Method name:()Ljava/lang/String;
	areturn
  Labels:

public java.lang.String name();
  Signature: ()Ljava/lang/String;
  Code:
   Stack=1, Locals=1, Args_size=1
	aload_0
	getfield	Field name:Ljava/lang/String;
	areturn
  Labels:

public java.lang.String tpe();
  Signature: ()Ljava/lang/String;
  Code:
   Stack=1, Locals=1, Args_size=1
	aload_0
	getfield	Field tpe:Ljava/lang/String;
	areturn
  Labels:

public scala.xml.dtd.DefaultDecl default();
  Signature: ()Lscala/xml/dtd/DefaultDecl;
  Code:
   Stack=1, Locals=1, Args_size=1
	aload_0
	getfield	Field default:Lscala/xml/dtd/DefaultDecl;
	areturn
  Labels:

public java.lang.String toString();
  Signature: ()Ljava/lang/String;
  Code:
   Stack=4, Locals=1, Args_size=1
	getstatic	Field scala/xml/Utility$.MODULE$:Lscala/xml/Utility$;
	new	class scala/xml/dtd/AttrDecl$$anonfun$toString$1
	dup
	aload_0
	invokespecial	Method scala/xml/dtd/AttrDecl$$anonfun$toString$1."<init>":(Lscala/xml/dtd/AttrDecl;)V
	invokevirtual	Method scala/xml/Utility$.sbToString:(Lscala/Function1;)Ljava/lang/String;
	areturn
  Labels:

public scala.collection.mutable.StringBuilder buildString(scala.collection.mutable.StringBuilder);
  Signature: (Lscala/collection/mutable/StringBuilder;)Lscala/collection/mutable/StringBuilder;
  Code:
   Stack=2, Locals=2, Args_size=2
	aload_1
	ldc	String   
	invokevirtual	Method scala/collection/mutable/StringBuilder.append:(Ljava/lang/String;)Lscala/collection/mutable/StringBuilder;
	aload_0
	invokevirtual	Method name:()Ljava/lang/String;
	invokevirtual	Method scala/collection/mutable/StringBuilder.append:(Ljava/lang/String;)Lscala/collection/mutable/StringBuilder;
	ldc	int 32
	invokevirtual	Method scala/collection/mutable/StringBuilder.append:(C)Lscala/collection/mutable/StringBuilder;
	aload_0
	invokevirtual	Method tpe:()Ljava/lang/String;
	invokevirtual	Method scala/collection/mutable/StringBuilder.append:(Ljava/lang/String;)Lscala/collection/mutable/StringBuilder;
	ldc	int 32
	invokevirtual	Method scala/collection/mutable/StringBuilder.append:(C)Lscala/collection/mutable/StringBuilder;
	pop
	aload_0
	invokevirtual	Method default:()Lscala/xml/dtd/DefaultDecl;
	aload_1
	invokevirtual	Method scala/xml/dtd/DefaultDecl.buildString:(Lscala/collection/mutable/StringBuilder;)Lscala/collection/mutable/StringBuilder;
	areturn
  Labels:
  LocalVariableTable: 
   Start  Length  Slot  Name   Signature
   0      40      0    this       Lscala/xml/dtd/AttrDecl;
   0      40      1    sb       Lscala/collection/mutable/StringBuilder;


public scala.xml.dtd.AttrDecl copy(java.lang.String, java.lang.String, scala.xml.dtd.DefaultDecl);
  Signature: (Ljava/lang/String;Ljava/lang/String;Lscala/xml/dtd/DefaultDecl;)Lscala/xml/dtd/AttrDecl;
  Code:
   Stack=5, Locals=4, Args_size=4
	new	class scala/xml/dtd/AttrDecl
	dup
	aload_1
	aload_2
	aload_3
	invokespecial	Method "<init>":(Ljava/lang/String;Ljava/lang/String;Lscala/xml/dtd/DefaultDecl;)V
	areturn
  Labels:
  LocalVariableTable: 
   Start  Length  Slot  Name   Signature
   0      11      0    this       Lscala/xml/dtd/AttrDecl;
   0      11      1    name       Ljava/lang/String;
   0      11      2    tpe       Ljava/lang/String;
   0      11      3    default       Lscala/xml/dtd/DefaultDecl;


public int hashCode();
  Signature: ()I
  Code:
   Stack=2, Locals=1, Args_size=1
	getstatic	Field scala/runtime/ScalaRunTime$.MODULE$:Lscala/runtime/ScalaRunTime$;
	aload_0
	invokevirtual	Method scala/runtime/ScalaRunTime$._hashCode:(Lscala/Product;)I
	ireturn
  Labels:

public boolean equals(java.lang.Object);
  Signature: (Ljava/lang/Object;)Z
  Code:
   Stack=4, Locals=10, Args_size=2
	aload_0
	aload_1
	if_acmpeq	l1 // iconst_1
	aload_1
	astore_2
	aload_2
	instanceof	class scala/xml/dtd/AttrDecl
	ifeq	l2 // iconst_0
	aload_2
	checkcast	class scala/xml/dtd/AttrDecl
	astore_3
	aload_3
	invokevirtual	Method name:()Ljava/lang/String;
	astore	4
	aload_3
	invokevirtual	Method tpe:()Ljava/lang/String;
	astore	5
	aload_3
	invokevirtual	Method default:()Lscala/xml/dtd/DefaultDecl;
	astore	6
	aload	6
	astore	7
	aload	5
	astore	8
	aload	4
	astore	9
	aload_0
	aload	9
	aload	8
	aload	7
	invokespecial	Method gd3$1:(Ljava/lang/String;Ljava/lang/String;Lscala/xml/dtd/DefaultDecl;)Z
	ifeq	l3 // iconst_0
	aload_1
	checkcast	class scala/xml/dtd/AttrDecl
	aload_0
	invokeinterface	InterfaceMethod scala/Equals.canEqual:(Ljava/lang/Object;)Z
	goto	l4 // ifeq
l3	iconst_0
	goto	l4 // ifeq
l2	iconst_0
l4	ifeq	l5 // iconst_0
l1	iconst_1
	goto	l6 // ireturn
l5	iconst_0
l6	ireturn
  Labels:
   	l3 = 75 // iconst_0
   	l2 = 79 // iconst_0
   	l4 = 80 // ifeq
   	l1 = 83 // iconst_1
   	l5 = 87 // iconst_0
   	l6 = 88 // ireturn
  LocalVariableTable: 
   Start  Length  Slot  Name   Signature
   0      89      0    this       Lscala/xml/dtd/AttrDecl;
   7      76      2    temp13       Ljava/lang/Object;
   19      60      3    temp14       Lscala/xml/dtd/AttrDecl;
   25      54      4    temp15       Ljava/lang/String;
   31      48      5    temp16       Ljava/lang/String;
   37      42      6    temp17       Lscala/xml/dtd/DefaultDecl;
   41      38      7    default$1       Lscala/xml/dtd/DefaultDecl;
   45      34      8    tpe$1       Ljava/lang/String;
   49      30      9    name$3       Ljava/lang/String;


public java.lang.String productPrefix();
  Signature: ()Ljava/lang/String;
  Code:
   Stack=1, Locals=1, Args_size=1
	ldc	String AttrDecl
	areturn
  Labels:

public int productArity();
  Signature: ()I
  Code:
   Stack=1, Locals=1, Args_size=1
	iconst_3
	ireturn
  Labels:

public java.lang.Object productElement(int);
  Signature: (I)Ljava/lang/Object;
  Code:
   Stack=3, Locals=3, Args_size=2
	iload_1
	istore_2
	iload_2
	tableswitch{ //0 to 2
		0: 57;
		1: 50;
		2: 43;
		default: 28 }
	new	class java/lang/IndexOutOfBoundsException
	dup
	iload_1
	invokestatic	Method scala/runtime/BoxesRunTime.boxToInteger:(I)Ljava/lang/Integer;
	invokevirtual	Method java/lang/Object.toString:()Ljava/lang/String;
	invokespecial	Method java/lang/IndexOutOfBoundsException."<init>":(Ljava/lang/String;)V
	athrow
	aload_0
	invokevirtual	Method default:()Lscala/xml/dtd/DefaultDecl;
	goto	l1 // areturn
	aload_0
	invokevirtual	Method tpe:()Ljava/lang/String;
	goto	l1 // areturn
	aload_0
	invokevirtual	Method name:()Ljava/lang/String;
l1	areturn
  Labels:
   	l1 = 61 // areturn
  LocalVariableTable: 
   Start  Length  Slot  Name   Signature
   0      62      0    this       Lscala/xml/dtd/AttrDecl;
   2      60      2    temp18       I


public java.lang.String productElementName(int);
  Signature: (I)Ljava/lang/String;
  Code:
   Stack=3, Locals=3, Args_size=2
	iload_1
	istore_2
	iload_2
	tableswitch{ //0 to 2
		0: 53;
		1: 48;
		2: 43;
		default: 28 }
	new	class java/lang/IndexOutOfBoundsException
	dup
	iload_1
	invokestatic	Method scala/runtime/BoxesRunTime.boxToInteger:(I)Ljava/lang/Integer;
	invokevirtual	Method java/lang/Object.toString:()Ljava/lang/String;
	invokespecial	Method java/lang/IndexOutOfBoundsException."<init>":(Ljava/lang/String;)V
	athrow
	ldc	String default
	goto	l1 // areturn
	ldc	String tpe
	goto	l1 // areturn
	ldc	String name
l1	areturn
  Labels:
   	l1 = 55 // areturn
  LocalVariableTable: 
   Start  Length  Slot  Name   Signature
   0      56      0    this       Lscala/xml/dtd/AttrDecl;
   2      54      2    temp19       I


public boolean canEqual(java.lang.Object);
  Signature: (Ljava/lang/Object;)Z
  Code:
   Stack=1, Locals=2, Args_size=2
	aload_1
	instanceof	class scala/xml/dtd/AttrDecl
	ireturn
  Labels:

private final boolean gd3$1(java.lang.String, java.lang.String, scala.xml.dtd.DefaultDecl);
  Signature: (Ljava/lang/String;Ljava/lang/String;Lscala/xml/dtd/DefaultDecl;)Z
  Code:
   Stack=2, Locals=7, Args_size=4
	aload_1
	aload_0
	invokevirtual	Method name:()Ljava/lang/String;
	astore	4
	dup
	ifnonnull	l1 // aload
	pop
	aload	4
	ifnull	l2 // aload_2
	goto	l3 // iconst_0
l1	aload	4
	invokevirtual	Method java/lang/Object.equals:(Ljava/lang/Object;)Z
	ifeq	l3 // iconst_0
l2	aload_2
	aload_0
	invokevirtual	Method tpe:()Ljava/lang/String;
	astore	5
	dup
	ifnonnull	l4 // aload
	pop
	aload	5
	ifnull	l5 // aload_3
	goto	l3 // iconst_0
l4	aload	5
	invokevirtual	Method java/lang/Object.equals:(Ljava/lang/Object;)Z
	ifeq	l3 // iconst_0
l5	aload_3
	aload_0
	invokevirtual	Method default:()Lscala/xml/dtd/DefaultDecl;
	astore	6
	dup
	ifnonnull	l6 // aload
	pop
	aload	6
	ifnull	l7 // iconst_1
	goto	l3 // iconst_0
l6	aload	6
	invokevirtual	Method java/lang/Object.equals:(Ljava/lang/Object;)Z
	ifeq	l3 // iconst_0
l7	iconst_1
	goto	l8 // ireturn
l3	iconst_0
l8	ireturn
  Labels:
   	l1 = 20 // aload
   	l2 = 28 // aload_2
   	l4 = 48 // aload
   	l5 = 56 // aload_3
   	l6 = 76 // aload
   	l7 = 84 // iconst_1
   	l3 = 88 // iconst_0
   	l8 = 89 // ireturn

public scala.xml.dtd.AttrDecl(java.lang.String, java.lang.String, scala.xml.dtd.DefaultDecl);
  Signature: (Ljava/lang/String;Ljava/lang/String;Lscala/xml/dtd/DefaultDecl;)V
  Code:
   Stack=2, Locals=4, Args_size=4
	aload_0
	aload_1
	putfield	Field name:Ljava/lang/String;
	aload_0
	aload_2
	putfield	Field tpe:Ljava/lang/String;
	aload_0
	aload_3
	putfield	Field default:Lscala/xml/dtd/DefaultDecl;
	aload_0
	invokespecial	Method java/lang/Object."<init>":()V
	aload_0
	invokestatic	Method scala/Product$class.$init$:(Lscala/Product;)V
	return
  Labels:
  LocalVariableTable: 
   Start  Length  Slot  Name   Signature
   0      24      0    this       Lscala/xml/dtd/AttrDecl;
   0      24      1    name       Ljava/lang/String;
   0      24      2    tpe       Ljava/lang/String;
   0      24      3    default       Lscala/xml/dtd/DefaultDecl;


}

