Compiled from "ContentModel.scala"
public abstract class scala.xml.dtd.ContentModel extends java.lang.Object implements scala.ScalaObject
  SourceFile: "ContentModel.scala"
  ScalaSig: length = 0x713
   05 00 FFFFFF81 7F 07 05 01 02 FFFFFF88 02 09 01 0C 43 6F 6E
   74 65 6E 74 4D 6F 64 65 6C 0A 02 03 04 01 03 64
   74 64 0A 02 05 06 01 03 78 6D 6C 0A 01 07 01 05
   73 63 61 6C 61 03 00 10 02 0A 0B 0D 01 02 06 08
   0C 02 FFFFFF84 FFFFFF80 FFFFFF80 FFFFFF88 02 0D 02 0C 43 6F 6E 74 65 6E
   74 4D 6F 64 65 6C 13 03 0B 0E 16 10 02 0F 14 0D
   01 10 0A 02 11 12 01 06 72 65 67 65 78 70 0A 02
   13 06 01 04 75 74 69 6C 09 02 15 10 02 07 57 6F
   72 64 45 78 70 10 02 17 18 0D 01 06 09 02 19 06
   02 0B 53 63 61 6C 61 4F 62 6A 65 63 74 08 05 1B
   0B FFFFFF84 00 1C 01 06 3C 69 6E 69 74 3E 14 01 09 05
   08 1E 0B FFFFFF84 FFFFFF80 FFFFFF80 FFFFFF80 00 1F 02 07 5F 6C 61 62 65
   6C 54 10 02 20 21 0D 01 0B 06 08 22 0B FFFFFF84 FFFFFF80 FFFFFF80
   FFFFFF80 40 23 02 08 45 6C 65 6D 4E 61 6D 65 13 04 21
   24 16 27 10 02 20 25 09 02 26 14 02 05 4C 61 62
   65 6C 10 02 17 28 09 02 29 06 02 07 50 72 6F 64
   75 63 74 08 08 2B 21 FFFFFF82 FFFFFFCA FFFFFF80 FFFFFF84 00 2C 01 04 6E
   61 6D 65 15 01 2D 10 02 2E 31 0E 02 17 2F 09 02
   30 06 01 06 50 72 65 64 65 66 09 02 32 33 02 06
   53 74 72 69 6E 67 0A 02 30 06 08 08 35 21 FFFFFF82 FFFFFF88
   FFFFFFA0 FFFFFF80 04 2D 01 05 6E 61 6D 65 20 08 05 1B 21 FFFFFF84
   00 37 14 02 1F 38 08 05 2B 36 FFFFFFC0 00 2D 08 05 3A
   21 FFFFFF84 20 3B 01 08 74 6F 53 74 72 69 6E 67 14 01
   2D 08 07 3D 21 FFFFFF81 FFFFFF80 FFFFFF84 00 3E 01 04 63 6F 70 79
   14 02 1F 3F 08 07 2B 3C FFFFFF90 FFFFFF80 FFFFFFC0 00 2D 08 07 41
   21 FFFFFF91 FFFFFF80 FFFFFF84 00 42 01 0E 63 6F 70 79 24 64 65 66
   61 75 6C 74 24 31 15 01 43 2A 02 2D 44 2B 01 45
   10 02 46 4B 0D 01 47 0A 02 48 49 01 09 75 6E 63
   68 65 63 6B 65 64 0A 02 4A 06 01 0A 61 6E 6E 6F
   74 61 74 69 6F 6E 09 02 4C 47 02 11 75 6E 63 68
   65 63 6B 65 64 56 61 72 69 61 6E 63 65 08 08 4E
   21 FFFFFF84 FFFFFF80 FFFFFF80 FFFFFF84 20 4F 01 08 68 61 73 68 43 6F 64
   65 14 01 50 10 02 17 51 09 02 52 06 02 03 49 6E
   74 08 08 54 21 FFFFFF84 FFFFFF80 FFFFFF80 FFFFFF84 20 55 01 06 65 71 75
   61 6C 73 14 02 56 59 10 02 17 57 09 02 58 06 02
   07 42 6F 6F 6C 65 61 6E 08 07 5A 53 FFFFFF81 FFFFFF80 FFFFFFC0 00
   5B 01 03 78 24 31 10 02 17 5C 09 02 5D 06 02 03
   41 6E 79 08 08 5F 21 FFFFFF84 FFFFFF80 FFFFFF80 FFFFFF84 20 60 01 0D 70
   72 6F 64 75 63 74 50 72 65 66 69 78 15 01 61 10
   02 62 67 0D 01 63 0A 02 64 65 01 04 6C 61 6E 67
   0A 01 66 01 04 6A 61 76 61 09 02 32 63 08 08 69
   21 FFFFFF84 FFFFFF80 FFFFFF80 FFFFFF84 20 6A 01 0C 70 72 6F 64 75 63 74
   41 72 69 74 79 15 01 50 08 08 6C 21 FFFFFF84 FFFFFF80 FFFFFF80 FFFFFF84
   20 6D 01 0E 70 72 6F 64 75 63 74 45 6C 65 6D 65
   6E 74 14 02 5B 6E 08 07 5A 6B FFFFFF81 FFFFFF80 FFFFFFC0 00 50 08
   08 70 21 FFFFFF84 FFFFFF80 FFFFFF80 FFFFFF84 20 71 01 12 70 72 6F 64 75
   63 74 45 6C 65 6D 65 6E 74 4E 61 6D 65 14 02 61
   72 08 07 5A 6F FFFFFF81 FFFFFF80 FFFFFFC0 00 50 08 08 74 21 FFFFFF84 FFFFFF80
   FFFFFF80 FFFFFF84 20 75 01 08 63 61 6E 45 71 75 61 6C 14 02
   56 76 08 07 5A 73 FFFFFF81 FFFFFF80 FFFFFFC0 00 5B 28 02 21 78 10
   02 17 79 09 02 7A 06 02 0C 73 65 72 69 61 6C 69
   7A 61 62 6C 65 05 08 7C 0B FFFFFF84 FFFFFF80 FFFFFF80 FFFFFF80 00 7D 02
   08 5F 72 65 67 65 78 70 54 10 02 20 7E 09 03 7F
   FFFFFF81 00 02 06 52 65 67 45 78 70 09 03 FFFFFF81 01 10 02
   04 42 61 73 65 07 07 FFFFFF81 03 0B FFFFFF88 02 FFFFFF81 04 01 0A
   54 72 61 6E 73 6C 61 74 6F 72 10 03 20 FFFFFF81 05 06
   0A FFFFFF81 06 0B FFFFFF84 FFFFFF80 FFFFFF80 FFFFFF88 02 FFFFFF81 07 02 0A 54 72 61
   6E 73 6C 61 74 6F 72 13 05 FFFFFF81 05 FFFFFF81 08 16 10 04
   FFFFFF81 09 FFFFFF81 0C 0D 02 FFFFFF81 0A 0A 03 FFFFFF81 0B 12 01 08 61
   75 74 6F 6D 61 74 61 09 04 FFFFFF81 0D FFFFFF81 0A 02 0E 57
   6F 72 64 42 65 72 72 79 53 65 74 68 69 08 07 1B
   FFFFFF81 05 FFFFFF84 00 FFFFFF81 0F 14 02 FFFFFF81 04 08 09 64 FFFFFF81 05 FFFFFFC2
   FFFFFF80 FFFFFF84 20 FFFFFF81 11 15 01 20 08 08 FFFFFF81 13 FFFFFF81 05 FFFFFFA0 FFFFFF80
   04 20 01 05 6C 61 6E 67 20 07 09 FFFFFF81 15 0B FFFFFF81 FFFFFF80
   FFFFFF88 02 FFFFFF81 16 01 08 45 6C 65 6D 4E 61 6D 65 10 03
   20 FFFFFF81 17 06 09 22 0B FFFFFF84 FFFFFF81 FFFFFF80 FFFFFF88 02 FFFFFF81 18 13 07
   FFFFFF81 17 FFFFFF81 19 FFFFFF81 1C 16 10 03 62 FFFFFF81 1A 09 03 FFFFFF81 1B
   63 02 06 4F 62 6A 65 63 74 10 05 17 FFFFFF81 1D 2D 1F
   09 03 FFFFFF81 1E 06 02 09 46 75 6E 63 74 69 6F 6E 31
   08 07 1B FFFFFF81 17 FFFFFF84 00 FFFFFF81 20 14 02 FFFFFF81 16 08 0A FFFFFF81
   22 FFFFFF81 17 FFFFFF81 FFFFFF80 FFFFFF84 40 FFFFFF81 23 01 05 61 70 70 6C 79
   14 03 1F FFFFFF81 24 08 06 2B FFFFFF81 21 FFFFFFC0 00 2D 08 0A FFFFFF81
   26 FFFFFF81 17 FFFFFF81 FFFFFF80 FFFFFF84 40 FFFFFF81 27 01 07 75 6E 61 70 70
   6C 79 14 04 FFFFFF81 28 FFFFFF81 2B 10 04 17 FFFFFF81 29 2D 09 03
   FFFFFF81 2A 06 02 04 53 6F 6D 65 08 07 FFFFFF81 2C FFFFFF81 25 FFFFFFC0
   00 1F 01 03 78 24 30 08 07 FFFFFF81 2E 0B FFFFFF84 00 FFFFFF81 2F
   01 07 69 73 4D 69 78 65 64 14 03 56 FFFFFF81 30 08 08
   FFFFFF81 31 FFFFFF81 2D FFFFFFC0 00 FFFFFF81 32 01 02 63 6D 10 03 0A FFFFFF81
   33 06 09 0C 02 FFFFFF84 FFFFFF80 FFFFFF80 FFFFFF81 10 FFFFFF81 34 13 05 FFFFFF81 33
   FFFFFF81 19 16 08 07 1B FFFFFF81 33 FFFFFF84 00 FFFFFF81 36 14 02 FFFFFF81 32
   08 06 3A FFFFFF81 33 FFFFFF84 20 3B 08 08 FFFFFF81 39 FFFFFF81 33 FFFFFF86 00
   FFFFFF81 3A 01 0B 62 75 69 6C 64 53 74 72 69 6E 67 14
   04 FFFFFF81 3B FFFFFF81 47 10 04 FFFFFF81 3C FFFFFF81 44 0E 04 FFFFFF81 3D FFFFFF81
   42 0E 04 FFFFFF81 3E FFFFFF81 41 0D 02 FFFFFF81 3F 0A 03 FFFFFF81 40 08
   01 06 3C 72 6F 6F 74 3E 09 01 07 09 03 FFFFFF81 43 06
   01 07 70 61 63 6B 61 67 65 09 04 FFFFFF81 45 FFFFFF81 46 02
   0D 53 74 72 69 6E 67 42 75 69 6C 64 65 72 0A 03
   FFFFFF81 43 06 08 08 FFFFFF81 48 FFFFFF81 38 FFFFFFC0 00 FFFFFF81 3B 01 02 73
   62 29 0A FFFFFF81 33 FFFFFF81 4A FFFFFF81 4C FFFFFF81 4E FFFFFF81 50 0A 03 FFFFFF81
   4B 02 01 03 41 4E 59 09 03 FFFFFF81 4D 02 02 0F 44 46
   41 43 6F 6E 74 65 6E 74 4D 6F 64 65 6C 0A 03 FFFFFF81
   4F 02 01 05 45 4D 50 54 59 0A 03 FFFFFF81 51 02 01 06
   50 43 44 41 54 41 08 07 FFFFFF81 53 0B FFFFFF84 00 FFFFFF81 54 01
   0C 63 6F 6E 74 61 69 6E 73 54 65 78 74 14 03 56
   FFFFFF81 55 08 08 FFFFFF81 31 FFFFFF81 52 FFFFFFC0 00 FFFFFF81 32 08 07 FFFFFF81 57
   0B FFFFFF84 00 FFFFFF81 58 01 05 70 61 72 73 65 14 04 FFFFFF81 32
   FFFFFF81 59 08 07 FFFFFF81 5A FFFFFF81 56 FFFFFFC0 00 2D 01 01 73 08 07
   FFFFFF81 5C 0B FFFFFF84 00 FFFFFF81 5D 01 09 67 65 74 4C 61 62 65
   6C 73 14 04 FFFFFF81 5E FFFFFF81 61 10 04 2E FFFFFF81 5F 2D 09 03
   FFFFFF81 60 33 02 03 53 65 74 08 07 FFFFFF81 62 FFFFFF81 5B FFFFFFC0 00
   7D 01 01 72 08 07 FFFFFF81 39 0B FFFFFF84 00 FFFFFF81 64 14 03 2D
   FFFFFF81 65 08 07 FFFFFF81 62 FFFFFF81 63 FFFFFFC0 00 7D 08 07 FFFFFF81 39 0B
   FFFFFF84 04 FFFFFF81 67 14 08 FFFFFF81 68 FFFFFF81 6B FFFFFF81 70 FFFFFF81 71 10 03
   17 FFFFFF81 69 09 03 FFFFFF81 6A 06 02 04 55 6E 69 74 08 08
   FFFFFF81 6C FFFFFF81 66 FFFFFFC0 00 FFFFFF81 6D 01 02 72 73 10 05 FFFFFF81 3C
   FFFFFF81 6E 7D 09 04 FFFFFF81 6F FFFFFF81 46 02 03 53 65 71 08 08
   FFFFFF81 48 FFFFFF81 66 FFFFFFC0 00 FFFFFF81 3B 08 08 FFFFFF81 72 FFFFFF81 66 FFFFFFC0 00
   FFFFFF81 73 01 03 73 65 70 10 03 17 FFFFFF81 74 09 03 FFFFFF81 75
   06 02 04 43 68 61 72 08 07 FFFFFF81 39 0B FFFFFF84 00 FFFFFF81 77
   14 06 FFFFFF81 3B FFFFFF81 78 FFFFFF81 7A 08 08 FFFFFF81 79 FFFFFF81 76 FFFFFFC0 00
   FFFFFF81 32 01 01 63 08 08 FFFFFF81 48 FFFFFF81 76 FFFFFFC0 00 FFFFFF81 3B 08
   07 FFFFFF81 39 0B FFFFFF84 00 FFFFFF81 7C 14 06 FFFFFF81 3B FFFFFF81 7D FFFFFF81 7E
   08 07 FFFFFF81 62 FFFFFF81 7B FFFFFFC0 00 7D 08 08 FFFFFF81 48 FFFFFF81 7B FFFFFFC0
   00 FFFFFF81 3B 
  InnerClass: 
   public abstract RegExp=class scala/util/regexp/Base$RegExp of class scala/util/regexp/Base
   public ElemName=class scala/xml/dtd/ContentModel$ElemName of class scala/xml/dtd/ContentModel
   public final $anonfun$isMixed$1=class scala/xml/dtd/ContentModel$$anonfun$isMixed$1 of class scala/xml/dtd/ContentModel
   public final $anonfun$toString$1=class scala/xml/dtd/ContentModel$$anonfun$toString$1 of class scala/xml/dtd/ContentModel
   public final $anonfun$traverse$1$2=class scala/xml/dtd/ContentModel$$anonfun$traverse$1$2 of class scala/xml/dtd/ContentModel
   public final $anonfun$traverse$1$1=class scala/xml/dtd/ContentModel$$anonfun$traverse$1$1 of class scala/xml/dtd/ContentModel
   public final $anonfun$buildString$2=class scala/xml/dtd/ContentModel$$anonfun$buildString$2 of class scala/xml/dtd/ContentModel
   public final $anonfun$buildString$1=class scala/xml/dtd/ContentModel$$anonfun$buildString$1 of class scala/xml/dtd/ContentModel
  minor version: 0
  major version: 49
  Constant pool:
Asciz	SourceFile;
Asciz	ContentModel.scala;
Asciz	traverse$1;
Asciz	(Lscala/util/regexp/Base$RegExp;)Lscala/collection/immutable/Set;;
Asciz	Code;
Asciz	scala/xml/dtd/ContentModel$;
class	scala/xml/dtd/ContentModel$
Asciz	MODULE$;
Asciz	Lscala/xml/dtd/ContentModel$;;
NameAndType	MODULE$:Lscala/xml/dtd/ContentModel$;
Field	scala/xml/dtd/ContentModel$.MODULE$:Lscala/xml/dtd/ContentModel$;
NameAndType	traverse$1:(Lscala/util/regexp/Base$RegExp;)Lscala/collection/immutable/Set;
Method	scala/xml/dtd/ContentModel$.traverse$1:(Lscala/util/regexp/Base$RegExp;)Lscala/collection/immutable/Set;
Asciz	getLabels;
NameAndType	getLabels:(Lscala/util/regexp/Base$RegExp;)Lscala/collection/immutable/Set;
Method	scala/xml/dtd/ContentModel$.getLabels:(Lscala/util/regexp/Base$RegExp;)Lscala/collection/immutable/Set;
Asciz	(Lscala/util/regexp/Base$RegExp;)Lscala/collection/immutable/Set<Ljava/lang/String;>;;
Asciz	Signature;
Asciz	parse;
Asciz	(Ljava/lang/String;)Lscala/xml/dtd/ContentModel;;
NameAndType	parse:(Ljava/lang/String;)Lscala/xml/dtd/ContentModel;
Method	scala/xml/dtd/ContentModel$.parse:(Ljava/lang/String;)Lscala/xml/dtd/ContentModel;
Asciz	containsText;
Asciz	(Lscala/xml/dtd/ContentModel;)Z;
NameAndType	containsText:(Lscala/xml/dtd/ContentModel;)Z
Method	scala/xml/dtd/ContentModel$.containsText:(Lscala/xml/dtd/ContentModel;)Z
Asciz	isMixed;
NameAndType	isMixed:(Lscala/xml/dtd/ContentModel;)Z
Method	scala/xml/dtd/ContentModel$.isMixed:(Lscala/xml/dtd/ContentModel;)Z
Asciz	toString;
Asciz	()Ljava/lang/String;;
Asciz	scala/collection/mutable/StringBuilder;
class	scala/collection/mutable/StringBuilder
Asciz	LineNumberTable;
Asciz	<init>;
Asciz	()V;
NameAndType	"<init>":()V
Method	scala/collection/mutable/StringBuilder."<init>":()V
Asciz	scala/xml/dtd/ContentModel;
class	scala/xml/dtd/ContentModel
Asciz	buildString;
Asciz	(Lscala/collection/mutable/StringBuilder;)Lscala/collection/mutable/StringBuilder;;
NameAndType	buildString:(Lscala/collection/mutable/StringBuilder;)Lscala/collection/mutable/StringBuilder;
Method	scala/xml/dtd/ContentModel.buildString:(Lscala/collection/mutable/StringBuilder;)Lscala/collection/mutable/StringBuilder;
NameAndType	toString:()Ljava/lang/String;
Method	scala/collection/mutable/StringBuilder.toString:()Ljava/lang/String;
Asciz	this;
Asciz	Lscala/xml/dtd/ContentModel;;
Asciz	sb0;
Asciz	Lscala/collection/mutable/StringBuilder;;
Asciz	LocalVariableTable;
Asciz	java/lang/Object;
class	java/lang/Object
Method	java/lang/Object."<init>":()V
Asciz	ScalaSig;
Asciz	InnerClasses;
Asciz	scala/util/regexp/Base$RegExp;
class	scala/util/regexp/Base$RegExp
Asciz	scala/util/regexp/Base;
class	scala/util/regexp/Base
Asciz	RegExp;
Asciz	scala/xml/dtd/ContentModel$ElemName;
class	scala/xml/dtd/ContentModel$ElemName
Asciz	ElemName;
Asciz	scala/xml/dtd/ContentModel$$anonfun$isMixed$1;
class	scala/xml/dtd/ContentModel$$anonfun$isMixed$1
Asciz	$anonfun$isMixed$1;
Asciz	scala/xml/dtd/ContentModel$$anonfun$toString$1;
class	scala/xml/dtd/ContentModel$$anonfun$toString$1
Asciz	$anonfun$toString$1;
Asciz	scala/xml/dtd/ContentModel$$anonfun$traverse$1$2;
class	scala/xml/dtd/ContentModel$$anonfun$traverse$1$2
Asciz	$anonfun$traverse$1$2;
Asciz	scala/xml/dtd/ContentModel$$anonfun$traverse$1$1;
class	scala/xml/dtd/ContentModel$$anonfun$traverse$1$1
Asciz	$anonfun$traverse$1$1;
Asciz	scala/xml/dtd/ContentModel$$anonfun$buildString$2;
class	scala/xml/dtd/ContentModel$$anonfun$buildString$2
Asciz	$anonfun$buildString$2;
Asciz	scala/xml/dtd/ContentModel$$anonfun$buildString$1;
class	scala/xml/dtd/ContentModel$$anonfun$buildString$1
Asciz	$anonfun$buildString$1;
Asciz	scala/ScalaObject;
class	scala/ScalaObject

{
public static final scala.collection.immutable.Set traverse$1(scala.util.regexp.Base$RegExp);
  Signature: (Lscala/util/regexp/Base$RegExp;)Lscala/collection/immutable/Set;
  Code:
   Stack=2, Locals=1, Args_size=1
	getstatic	Field scala/xml/dtd/ContentModel$.MODULE$:Lscala/xml/dtd/ContentModel$;
	aload_0
	invokevirtual	Method scala/xml/dtd/ContentModel$.traverse$1:(Lscala/util/regexp/Base$RegExp;)Lscala/collection/immutable/Set;
	areturn
  Labels:

public static final scala.collection.immutable.Set getLabels(scala.util.regexp.Base$RegExp);
  Signature: (Lscala/util/regexp/Base$RegExp;)Lscala/collection/immutable/Set;
  Code:
   Stack=2, Locals=1, Args_size=1
	getstatic	Field scala/xml/dtd/ContentModel$.MODULE$:Lscala/xml/dtd/ContentModel$;
	aload_0
	invokevirtual	Method scala/xml/dtd/ContentModel$.getLabels:(Lscala/util/regexp/Base$RegExp;)Lscala/collection/immutable/Set;
	areturn
  Labels:
  Signature: length = 0x2
   00 11 

public static final scala.xml.dtd.ContentModel parse(java.lang.String);
  Signature: (Ljava/lang/String;)Lscala/xml/dtd/ContentModel;
  Code:
   Stack=2, Locals=1, Args_size=1
	getstatic	Field scala/xml/dtd/ContentModel$.MODULE$:Lscala/xml/dtd/ContentModel$;
	aload_0
	invokevirtual	Method scala/xml/dtd/ContentModel$.parse:(Ljava/lang/String;)Lscala/xml/dtd/ContentModel;
	areturn
  Labels:

public static final boolean containsText(scala.xml.dtd.ContentModel);
  Signature: (Lscala/xml/dtd/ContentModel;)Z
  Code:
   Stack=2, Locals=1, Args_size=1
	getstatic	Field scala/xml/dtd/ContentModel$.MODULE$:Lscala/xml/dtd/ContentModel$;
	aload_0
	invokevirtual	Method scala/xml/dtd/ContentModel$.containsText:(Lscala/xml/dtd/ContentModel;)Z
	ireturn
  Labels:

public static final boolean isMixed(scala.xml.dtd.ContentModel);
  Signature: (Lscala/xml/dtd/ContentModel;)Z
  Code:
   Stack=2, Locals=1, Args_size=1
	getstatic	Field scala/xml/dtd/ContentModel$.MODULE$:Lscala/xml/dtd/ContentModel$;
	aload_0
	invokevirtual	Method scala/xml/dtd/ContentModel$.isMixed:(Lscala/xml/dtd/ContentModel;)Z
	ireturn
  Labels:

public java.lang.String toString();
  Signature: ()Ljava/lang/String;
  Code:
   Stack=2, Locals=3, Args_size=1
	new	class scala/collection/mutable/StringBuilder
	dup
	invokespecial	Method scala/collection/mutable/StringBuilder."<init>":()V
	astore_2
	aload_2
	checkcast	class scala/collection/mutable/StringBuilder
	astore_1
	aload_0
	aload_1
	invokevirtual	Method buildString:(Lscala/collection/mutable/StringBuilder;)Lscala/collection/mutable/StringBuilder;
	pop
	aload_2
	invokevirtual	Method scala/collection/mutable/StringBuilder.toString:()Ljava/lang/String;
	areturn
  Labels:
  LocalVariableTable: 
   Start  Length  Slot  Name   Signature
   0      24      0    this       Lscala/xml/dtd/ContentModel;
   8      15      2    sb0       Lscala/collection/mutable/StringBuilder;


public abstract scala.collection.mutable.StringBuilder buildString(scala.collection.mutable.StringBuilder);
  Signature: (Lscala/collection/mutable/StringBuilder;)Lscala/collection/mutable/StringBuilder;

public scala.xml.dtd.ContentModel();
  Signature: ()V
  Code:
   Stack=1, Locals=1, Args_size=1
	aload_0
	invokespecial	Method java/lang/Object."<init>":()V
	return
  Labels:

}

