Compiled from "ContentModel.scala"
public final class scala.xml.dtd.ContentModel$$anonfun$buildString$1 extends scala.runtime.AbstractFunction1 implements java.io.Serializable
  SourceFile: "ContentModel.scala"
  Scala: length = 0x
   
  InnerClass: 
   public abstract RegExp=class scala/util/regexp/Base$RegExp of class scala/util/regexp/Base
   public final $anonfun$buildString$1=class scala/xml/dtd/ContentModel$$anonfun$buildString$1 of class scala/xml/dtd/ContentModel
  minor version: 0
  major version: 49
  Constant pool:
Asciz	SourceFile;
Asciz	ContentModel.scala;
Asciz	<clinit>;
Asciz	()V;
Asciz	Code;
Asciz	serialVersionUID;
Asciz	J;
Asciz	scala/xml/dtd/ContentModel$$anonfun$buildString$1;
class	scala/xml/dtd/ContentModel$$anonfun$buildString$1
NameAndType	serialVersionUID:J
Field	scala/xml/dtd/ContentModel$$anonfun$buildString$1.serialVersionUID:J
Asciz	r$3;
Asciz	Lscala/util/regexp/Base$RegExp;;
Asciz	apply;
Asciz	(Lscala/collection/mutable/StringBuilder;)V;
Asciz	scala/xml/dtd/ContentModel$;
class	scala/xml/dtd/ContentModel$
Asciz	MODULE$;
Asciz	Lscala/xml/dtd/ContentModel$;;
NameAndType	MODULE$:Lscala/xml/dtd/ContentModel$;
Field	scala/xml/dtd/ContentModel$.MODULE$:Lscala/xml/dtd/ContentModel$;
Asciz	LineNumberTable;
NameAndType	r$3:Lscala/util/regexp/Base$RegExp;
Field	scala/xml/dtd/ContentModel$$anonfun$buildString$1.r$3:Lscala/util/regexp/Base$RegExp;
Asciz	buildString;
Asciz	(Lscala/util/regexp/Base$RegExp;Lscala/collection/mutable/StringBuilder;)Lscala/collection/mutable/StringBuilder;;
NameAndType	buildString:(Lscala/util/regexp/Base$RegExp;Lscala/collection/mutable/StringBuilder;)Lscala/collection/mutable/StringBuilder;
Method	scala/xml/dtd/ContentModel$.buildString:(Lscala/util/regexp/Base$RegExp;Lscala/collection/mutable/StringBuilder;)Lscala/collection/mutable/StringBuilder;
Asciz	(Ljava/lang/Object;)Ljava/lang/Object;;
Asciz	scala/collection/mutable/StringBuilder;
class	scala/collection/mutable/StringBuilder
NameAndType	apply:(Lscala/collection/mutable/StringBuilder;)V
Method	scala/xml/dtd/ContentModel$$anonfun$buildString$1.apply:(Lscala/collection/mutable/StringBuilder;)V
Asciz	scala/runtime/BoxedUnit;
class	scala/runtime/BoxedUnit
Asciz	UNIT;
Asciz	Lscala/runtime/BoxedUnit;;
NameAndType	UNIT:Lscala/runtime/BoxedUnit;
Field	scala/runtime/BoxedUnit.UNIT:Lscala/runtime/BoxedUnit;
Asciz	this;
Asciz	Lscala/xml/dtd/ContentModel$$anonfun$buildString$1;;
Asciz	v1;
Asciz	Ljava/lang/Object;;
Asciz	LocalVariableTable;
Asciz	<init>;
Asciz	(Lscala/util/regexp/Base$RegExp;)V;
Asciz	scala/runtime/AbstractFunction1;
class	scala/runtime/AbstractFunction1
NameAndType	"<init>":()V
Method	scala/runtime/AbstractFunction1."<init>":()V
Asciz	Scala;
Asciz	InnerClasses;
Asciz	scala/util/regexp/Base$RegExp;
class	scala/util/regexp/Base$RegExp
Asciz	scala/util/regexp/Base;
class	scala/util/regexp/Base
Asciz	RegExp;
Asciz	scala/xml/dtd/ContentModel;
class	scala/xml/dtd/ContentModel
Asciz	$anonfun$buildString$1;
Asciz	java/io/Serializable;
class	java/io/Serializable

{
public static final long serialVersionUID;
  Signature: J

private final scala.util.regexp.Base$RegExp r$3;
  Signature: Lscala/util/regexp/Base$RegExp;

public static {};
  Signature: ()V
  Code:
   Stack=2, Locals=0, Args_size=0
	lconst_0
	putstatic	Field serialVersionUID:J
	return
  Labels:

public final void apply(scala.collection.mutable.StringBuilder);
  Signature: (Lscala/collection/mutable/StringBuilder;)V
  Code:
   Stack=3, Locals=2, Args_size=2
	getstatic	Field scala/xml/dtd/ContentModel$.MODULE$:Lscala/xml/dtd/ContentModel$;
	aload_0
	getfield	Field r$3:Lscala/util/regexp/Base$RegExp;
	aload_1
	invokevirtual	Method scala/xml/dtd/ContentModel$.buildString:(Lscala/util/regexp/Base$RegExp;Lscala/collection/mutable/StringBuilder;)Lscala/collection/mutable/StringBuilder;
	pop
	return
  Labels:

public final java.lang.Object apply(java.lang.Object);
  Signature: (Ljava/lang/Object;)Ljava/lang/Object;
  Code:
   Stack=2, Locals=2, Args_size=2
	aload_0
	aload_1
	checkcast	class scala/collection/mutable/StringBuilder
	invokevirtual	Method apply:(Lscala/collection/mutable/StringBuilder;)V
	getstatic	Field scala/runtime/BoxedUnit.UNIT:Lscala/runtime/BoxedUnit;
	areturn
  Labels:
  LocalVariableTable: 
   Start  Length  Slot  Name   Signature
   0      12      0    this       Lscala/xml/dtd/ContentModel$$anonfun$buildString$1;
   0      12      1    v1       Ljava/lang/Object;


public scala.xml.dtd.ContentModel$$anonfun$buildString$1(scala.util.regexp.Base$RegExp);
  Signature: (Lscala/util/regexp/Base$RegExp;)V
  Code:
   Stack=2, Locals=2, Args_size=2
	aload_0
	aload_1
	putfield	Field r$3:Lscala/util/regexp/Base$RegExp;
	aload_0
	invokespecial	Method scala/runtime/AbstractFunction1."<init>":()V
	return
  Labels:

}

