Compiled from "ContentModel.scala"
public final class scala.xml.dtd.ContentModel$ extends scala.util.regexp.WordExp implements scala.ScalaObject
  SourceFile: "ContentModel.scala"
  Scala: length = 0x
   
  InnerClass: 
   public Alt=class scala/util/regexp/Base$Alt of class scala/util/regexp/Base
   public Sequ=class scala/util/regexp/Base$Sequ of class scala/util/regexp/Base
   public Star=class scala/util/regexp/Base$Star of class scala/util/regexp/Base
   public abstract RegExp=class scala/util/regexp/Base$RegExp of class scala/util/regexp/Base
   public abstract Label=class scala/util/regexp/WordExp$Label of class scala/util/regexp/WordExp
   public final $anon$1=class scala/Predef$$anon$1 of class scala/Predef
   public Letter=class scala/util/regexp/WordExp$Letter of class scala/util/regexp/WordExp
   public ElemName=class scala/xml/dtd/ContentModel$ElemName of class scala/xml/dtd/ContentModel
   public final $anonfun$isMixed$1=class scala/xml/dtd/ContentModel$$anonfun$isMixed$1 of class scala/xml/dtd/ContentModel
   public final $anonfun$toString$1=class scala/xml/dtd/ContentModel$$anonfun$toString$1 of class scala/xml/dtd/ContentModel
   public final $anonfun$traverse$1$2=class scala/xml/dtd/ContentModel$$anonfun$traverse$1$2 of class scala/xml/dtd/ContentModel
   public final $anonfun$traverse$1$1=class scala/xml/dtd/ContentModel$$anonfun$traverse$1$1 of class scala/xml/dtd/ContentModel
   public final $anonfun$buildString$1=class scala/xml/dtd/ContentModel$$anonfun$buildString$1 of class scala/xml/dtd/ContentModel
   public final $anonfun$buildString$2=class scala/xml/dtd/ContentModel$$anonfun$buildString$2 of class scala/xml/dtd/ContentModel
   public GenericCanBuildFrom=class scala/collection/generic/TraversableFactory$GenericCanBuildFrom of class scala/collection/generic/TraversableFactory
  minor version: 0
  major version: 49
  Constant pool:
Asciz	SourceFile;
Asciz	ContentModel.scala;
Asciz	Scala;
Asciz	MODULE$;
Asciz	Lscala/xml/dtd/ContentModel$;;
Asciz	<clinit>;
Asciz	()V;
Asciz	Code;
Asciz	scala/xml/dtd/ContentModel$;
class	scala/xml/dtd/ContentModel$
Asciz	<init>;
NameAndType	"<init>":()V
Method	scala/xml/dtd/ContentModel$."<init>":()V
Asciz	LineNumberTable;
Asciz	scala/util/regexp/WordExp;
class	scala/util/regexp/WordExp
Method	scala/util/regexp/WordExp."<init>":()V
NameAndType	MODULE$:Lscala/xml/dtd/ContentModel$;
Field	scala/xml/dtd/ContentModel$.MODULE$:Lscala/xml/dtd/ContentModel$;
Asciz	traverse$1;
Asciz	(Lscala/util/regexp/Base$RegExp;)Lscala/collection/immutable/Set;;
Asciz	scala/util/regexp/WordExp$Letter;
class	scala/util/regexp/WordExp$Letter
Asciz	a;
Asciz	()Lscala/util/regexp/WordExp$Label;;
NameAndType	a:()Lscala/util/regexp/WordExp$Label;
Method	scala/util/regexp/WordExp$Letter.a:()Lscala/util/regexp/WordExp$Label;
Asciz	scala/xml/dtd/ContentModel$ElemName;
class	scala/xml/dtd/ContentModel$ElemName
Asciz	name;
Asciz	()Ljava/lang/String;;
NameAndType	name:()Ljava/lang/String;
Method	scala/xml/dtd/ContentModel$ElemName.name:()Ljava/lang/String;
Asciz	scala/Predef$;
class	scala/Predef$
Asciz	Lscala/Predef$;;
NameAndType	MODULE$:Lscala/Predef$;
Field	scala/Predef$.MODULE$:Lscala/Predef$;
Asciz	Set;
Asciz	()Lscala/collection/immutable/Set$;;
NameAndType	Set:()Lscala/collection/immutable/Set$;
Method	scala/Predef$.Set:()Lscala/collection/immutable/Set$;
Asciz	java/lang/String;
class	java/lang/String
Asciz	[Ljava/lang/Object;;
class	"[Ljava/lang/Object;"
Asciz	wrapRefArray;
Asciz	([Ljava/lang/Object;)Lscala/collection/mutable/WrappedArray;;
NameAndType	wrapRefArray:([Ljava/lang/Object;)Lscala/collection/mutable/WrappedArray;
Method	scala/Predef$.wrapRefArray:([Ljava/lang/Object;)Lscala/collection/mutable/WrappedArray;
Asciz	scala/collection/immutable/Set$;
class	scala/collection/immutable/Set$
Asciz	apply;
Asciz	(Lscala/collection/Seq;)Lscala/collection/Traversable;;
NameAndType	apply:(Lscala/collection/Seq;)Lscala/collection/Traversable;
Method	scala/collection/immutable/Set$.apply:(Lscala/collection/Seq;)Lscala/collection/Traversable;
Asciz	scala/collection/immutable/Set;
class	scala/collection/immutable/Set
Asciz	scala/MatchError;
class	scala/MatchError
Asciz	scala/util/regexp/Base$RegExp;
class	scala/util/regexp/Base$RegExp
Asciz	toString;
NameAndType	toString:()Ljava/lang/String;
Method	scala/util/regexp/Base$RegExp.toString:()Ljava/lang/String;
Asciz	(Ljava/lang/String;)V;
NameAndType	"<init>":(Ljava/lang/String;)V
Method	scala/MatchError."<init>":(Ljava/lang/String;)V
Asciz	scala/util/regexp/Base$Star;
class	scala/util/regexp/Base$Star
Asciz	r;
Asciz	()Lscala/util/regexp/Base$RegExp;;
NameAndType	r:()Lscala/util/regexp/Base$RegExp;
Method	scala/util/regexp/Base$Star.r:()Lscala/util/regexp/Base$RegExp;
Asciz	scala/util/regexp/Base$Sequ;
class	scala/util/regexp/Base$Sequ
Asciz	Sequ;
Asciz	()Lscala/util/regexp/Base$Sequ$;;
NameAndType	Sequ:()Lscala/util/regexp/Base$Sequ$;
Method	scala/xml/dtd/ContentModel$.Sequ:()Lscala/util/regexp/Base$Sequ$;
Asciz	scala/Some;
class	scala/Some
Asciz	rs;
Asciz	()Lscala/collection/Seq;;
NameAndType	rs:()Lscala/collection/Seq;
Method	scala/util/regexp/Base$Sequ.rs:()Lscala/collection/Seq;
Asciz	(Ljava/lang/Object;)V;
NameAndType	"<init>":(Ljava/lang/Object;)V
Method	scala/Some."<init>":(Ljava/lang/Object;)V
Asciz	x;
Asciz	Ljava/lang/Object;;
NameAndType	x:Ljava/lang/Object;
Field	scala/Some.x:Ljava/lang/Object;
Asciz	scala/collection/Seq;
class	scala/collection/Seq
Asciz	java/lang/Object;
class	java/lang/Object
Asciz	equals;
Asciz	(Ljava/lang/Object;)Z;
NameAndType	equals:(Ljava/lang/Object;)Z
Method	java/lang/Object.equals:(Ljava/lang/Object;)Z
Asciz	scala/collection/SeqLike;
class	scala/collection/SeqLike
Asciz	lengthCompare;
Asciz	(I)I;
NameAndType	lengthCompare:(I)I
InterfaceMethod	scala/collection/SeqLike.lengthCompare:(I)I
Asciz	scala/xml/dtd/ContentModel$$anonfun$traverse$1$1;
class	scala/xml/dtd/ContentModel$$anonfun$traverse$1$1
Method	scala/xml/dtd/ContentModel$$anonfun$traverse$1$1."<init>":()V
Asciz	scala/collection/Seq$;
class	scala/collection/Seq$
Asciz	Lscala/collection/Seq$;;
NameAndType	MODULE$:Lscala/collection/Seq$;
Field	scala/collection/Seq$.MODULE$:Lscala/collection/Seq$;
Asciz	scala/collection/generic/TraversableFactory$GenericCanBuildFrom;
class	scala/collection/generic/TraversableFactory$GenericCanBuildFrom
Asciz	(Lscala/collection/generic/TraversableFactory;)V;
NameAndType	"<init>":(Lscala/collection/generic/TraversableFactory;)V
Method	scala/collection/generic/TraversableFactory$GenericCanBuildFrom."<init>":(Lscala/collection/generic/TraversableFactory;)V
Asciz	scala/collection/TraversableLike;
class	scala/collection/TraversableLike
Asciz	map;
Asciz	(Lscala/Function1;Lscala/collection/generic/CanBuildFrom;)Ljava/lang/Object;;
NameAndType	map:(Lscala/Function1;Lscala/collection/generic/CanBuildFrom;)Ljava/lang/Object;
InterfaceMethod	scala/collection/TraversableLike.map:(Lscala/Function1;Lscala/collection/generic/CanBuildFrom;)Ljava/lang/Object;
Asciz	scala/collection/generic/GenericTraversableTemplate;
class	scala/collection/generic/GenericTraversableTemplate
Asciz	scala/Predef$$anon$1;
class	scala/Predef$$anon$1
Method	scala/Predef$$anon$1."<init>":()V
Asciz	flatten;
Asciz	(Lscala/Function1;)Lscala/collection/Traversable;;
NameAndType	flatten:(Lscala/Function1;)Lscala/collection/Traversable;
InterfaceMethod	scala/collection/generic/GenericTraversableTemplate.flatten:(Lscala/Function1;)Lscala/collection/Traversable;
Asciz	scala/util/regexp/Base$Alt;
class	scala/util/regexp/Base$Alt
Asciz	Alt;
Asciz	()Lscala/util/regexp/Base$Alt$;;
NameAndType	Alt:()Lscala/util/regexp/Base$Alt$;
Method	scala/xml/dtd/ContentModel$.Alt:()Lscala/util/regexp/Base$Alt$;
Method	scala/util/regexp/Base$Alt.rs:()Lscala/collection/Seq;
Asciz	scala/xml/dtd/ContentModel$$anonfun$traverse$1$2;
class	scala/xml/dtd/ContentModel$$anonfun$traverse$1$2
Method	scala/xml/dtd/ContentModel$$anonfun$traverse$1$2."<init>":()V
Asciz	this;
Asciz	Lscala/util/regexp/Base$RegExp;;
Asciz	temp12;
Asciz	Lscala/util/regexp/WordExp$Letter;;
Asciz	temp13;
Asciz	Lscala/xml/dtd/ContentModel$ElemName;;
Asciz	temp14;
Asciz	Ljava/lang/String;;
Asciz	temp15;
Asciz	Lscala/util/regexp/Base$Star;;
Asciz	temp16;
Asciz	temp17;
Asciz	Lscala/util/regexp/Base$Sequ;;
Asciz	temp18;
Asciz	Lscala/Some;;
Asciz	temp19;
Asciz	Lscala/collection/Seq;;
Asciz	temp21;
Asciz	Lscala/util/regexp/Base$Alt;;
Asciz	temp22;
Asciz	temp23;
Asciz	LocalVariableTable;
Asciz	buildString;
Asciz	(Lscala/util/regexp/Base$RegExp;Lscala/collection/mutable/StringBuilder;)Lscala/collection/mutable/StringBuilder;;
Asciz	Eps;
Asciz	()Lscala/util/regexp/Base$Eps$;;
NameAndType	Eps:()Lscala/util/regexp/Base$Eps$;
Method	scala/xml/dtd/ContentModel$.Eps:()Lscala/util/regexp/Base$Eps$;
int	40;
Asciz	scala/collection/mutable/StringBuilder;
class	scala/collection/mutable/StringBuilder
Asciz	append;
Asciz	(C)Lscala/collection/mutable/StringBuilder;;
NameAndType	append:(C)Lscala/collection/mutable/StringBuilder;
Method	scala/collection/mutable/StringBuilder.append:(C)Lscala/collection/mutable/StringBuilder;
int	44;
Asciz	(Lscala/collection/Seq;Lscala/collection/mutable/StringBuilder;C)V;
NameAndType	buildString:(Lscala/collection/Seq;Lscala/collection/mutable/StringBuilder;C)V
Method	scala/xml/dtd/ContentModel$.buildString:(Lscala/collection/Seq;Lscala/collection/mutable/StringBuilder;C)V
int	41;
int	124;
NameAndType	buildString:(Lscala/util/regexp/Base$RegExp;Lscala/collection/mutable/StringBuilder;)Lscala/collection/mutable/StringBuilder;
Method	scala/xml/dtd/ContentModel$.buildString:(Lscala/util/regexp/Base$RegExp;Lscala/collection/mutable/StringBuilder;)Lscala/collection/mutable/StringBuilder;
Asciz	)*;
String	)*
Asciz	(Ljava/lang/String;)Lscala/collection/mutable/StringBuilder;;
NameAndType	append:(Ljava/lang/String;)Lscala/collection/mutable/StringBuilder;
Method	scala/collection/mutable/StringBuilder.append:(Ljava/lang/String;)Lscala/collection/mutable/StringBuilder;
Asciz	sb;
Asciz	Lscala/collection/mutable/StringBuilder;;
Asciz	temp34;
Asciz	temp35;
Asciz	temp36;
Asciz	temp38;
Asciz	temp39;
Asciz	temp40;
Asciz	temp42;
Asciz	temp43;
Asciz	temp44;
Asciz	temp45;
Asciz	temp46;
Asciz	(Lscala/xml/dtd/ContentModel;Lscala/collection/mutable/StringBuilder;)Lscala/collection/mutable/StringBuilder;;
Asciz	scala/xml/dtd/ANY$;
class	scala/xml/dtd/ANY$
Asciz	Lscala/xml/dtd/ANY$;;
NameAndType	MODULE$:Lscala/xml/dtd/ANY$;
Field	scala/xml/dtd/ANY$.MODULE$:Lscala/xml/dtd/ANY$;
Asciz	ANY;
String	ANY
Asciz	scala/xml/dtd/ContentModel;
class	scala/xml/dtd/ContentModel
Method	scala/xml/dtd/ContentModel.toString:()Ljava/lang/String;
Asciz	scala/xml/dtd/EMPTY$;
class	scala/xml/dtd/EMPTY$
Asciz	Lscala/xml/dtd/EMPTY$;;
NameAndType	MODULE$:Lscala/xml/dtd/EMPTY$;
Field	scala/xml/dtd/EMPTY$.MODULE$:Lscala/xml/dtd/EMPTY$;
Asciz	EMPTY;
String	EMPTY
Asciz	scala/xml/dtd/PCDATA$;
class	scala/xml/dtd/PCDATA$
Asciz	Lscala/xml/dtd/PCDATA$;;
NameAndType	MODULE$:Lscala/xml/dtd/PCDATA$;
Field	scala/xml/dtd/PCDATA$.MODULE$:Lscala/xml/dtd/PCDATA$;
Asciz	(#PCDATA);
String	(#PCDATA)
Asciz	scala/xml/dtd/ELEMENTS;
class	scala/xml/dtd/ELEMENTS
Asciz	scala/xml/dtd/MIXED;
class	scala/xml/dtd/MIXED
Asciz	(Lscala/collection/mutable/StringBuilder;)Lscala/collection/mutable/StringBuilder;;
NameAndType	buildString:(Lscala/collection/mutable/StringBuilder;)Lscala/collection/mutable/StringBuilder;
Method	scala/xml/dtd/ContentModel.buildString:(Lscala/collection/mutable/StringBuilder;)Lscala/collection/mutable/StringBuilder;
Asciz	c;
Asciz	Lscala/xml/dtd/ContentModel;;
Asciz	scala/collection/IterableLike;
class	scala/collection/IterableLike
Asciz	head;
Asciz	()Ljava/lang/Object;;
NameAndType	head:()Ljava/lang/Object;
InterfaceMethod	scala/collection/IterableLike.head:()Ljava/lang/Object;
Asciz	tail;
NameAndType	tail:()Ljava/lang/Object;
InterfaceMethod	scala/collection/TraversableLike.tail:()Ljava/lang/Object;
Asciz	scala/xml/dtd/ContentModel$$anonfun$buildString$2;
class	scala/xml/dtd/ContentModel$$anonfun$buildString$2
Asciz	(Lscala/collection/mutable/StringBuilder;C)V;
NameAndType	"<init>":(Lscala/collection/mutable/StringBuilder;C)V
Method	scala/xml/dtd/ContentModel$$anonfun$buildString$2."<init>":(Lscala/collection/mutable/StringBuilder;C)V
Asciz	foreach;
Asciz	(Lscala/Function1;)V;
NameAndType	foreach:(Lscala/Function1;)V
InterfaceMethod	scala/collection/IterableLike.foreach:(Lscala/Function1;)V
Asciz	sb$1;
Asciz	sep$1;
Asciz	C;
Asciz	(Lscala/collection/Seq<Lscala/util/regexp/Base$RegExp;>;Lscala/collection/mutable/StringBuilder;C)V;
Asciz	Signature;
Asciz	(Lscala/util/regexp/Base$RegExp;)Ljava/lang/String;;
Asciz	scala/xml/dtd/ContentModel$$anonfun$buildString$1;
class	scala/xml/dtd/ContentModel$$anonfun$buildString$1
Asciz	(Lscala/util/regexp/Base$RegExp;)V;
NameAndType	"<init>":(Lscala/util/regexp/Base$RegExp;)V
Method	scala/xml/dtd/ContentModel$$anonfun$buildString$1."<init>":(Lscala/util/regexp/Base$RegExp;)V
Method	scala/collection/mutable/StringBuilder."<init>":()V
Method	scala/collection/mutable/StringBuilder.toString:()Ljava/lang/String;
Asciz	r$3;
Asciz	sb0;
Asciz	getLabels;
NameAndType	traverse$1:(Lscala/util/regexp/Base$RegExp;)Lscala/collection/immutable/Set;
Method	scala/xml/dtd/ContentModel$.traverse$1:(Lscala/util/regexp/Base$RegExp;)Lscala/collection/immutable/Set;
Asciz	(Lscala/util/regexp/Base$RegExp;)Lscala/collection/immutable/Set<Ljava/lang/String;>;;
Asciz	parse;
Asciz	(Ljava/lang/String;)Lscala/xml/dtd/ContentModel;;
Asciz	scala/xml/dtd/ContentModelParser$;
class	scala/xml/dtd/ContentModelParser$
Asciz	Lscala/xml/dtd/ContentModelParser$;;
NameAndType	MODULE$:Lscala/xml/dtd/ContentModelParser$;
Field	scala/xml/dtd/ContentModelParser$.MODULE$:Lscala/xml/dtd/ContentModelParser$;
NameAndType	parse:(Ljava/lang/String;)Lscala/xml/dtd/ContentModel;
Method	scala/xml/dtd/ContentModelParser$.parse:(Ljava/lang/String;)Lscala/xml/dtd/ContentModel;
Asciz	s;
Asciz	containsText;
Asciz	(Lscala/xml/dtd/ContentModel;)Z;
Asciz	scala/PartialFunction$;
class	scala/PartialFunction$
Asciz	Lscala/PartialFunction$;;
NameAndType	MODULE$:Lscala/PartialFunction$;
Field	scala/PartialFunction$.MODULE$:Lscala/PartialFunction$;
Asciz	scala/xml/dtd/ContentModel$$anonfun$isMixed$1;
class	scala/xml/dtd/ContentModel$$anonfun$isMixed$1
Method	scala/xml/dtd/ContentModel$$anonfun$isMixed$1."<init>":()V
Asciz	cond;
Asciz	(Ljava/lang/Object;Lscala/PartialFunction;)Z;
NameAndType	cond:(Ljava/lang/Object;Lscala/PartialFunction;)Z
Method	scala/PartialFunction$.cond:(Ljava/lang/Object;Lscala/PartialFunction;)Z
Asciz	cm;
Asciz	isMixed;
Asciz	InnerClasses;
Asciz	scala/util/regexp/Base;
class	scala/util/regexp/Base
Asciz	Star;
Asciz	RegExp;
Asciz	scala/util/regexp/WordExp$Label;
class	scala/util/regexp/WordExp$Label
Asciz	Label;
Asciz	scala/Predef;
class	scala/Predef
Asciz	$anon$1;
Asciz	Letter;
Asciz	ElemName;
Asciz	$anonfun$isMixed$1;
Asciz	scala/xml/dtd/ContentModel$$anonfun$toString$1;
class	scala/xml/dtd/ContentModel$$anonfun$toString$1
Asciz	$anonfun$toString$1;
Asciz	$anonfun$traverse$1$2;
Asciz	$anonfun$traverse$1$1;
Asciz	$anonfun$buildString$1;
Asciz	$anonfun$buildString$2;
Asciz	scala/collection/generic/TraversableFactory;
class	scala/collection/generic/TraversableFactory
Asciz	GenericCanBuildFrom;
Asciz	scala/ScalaObject;
class	scala/ScalaObject

{
public static final scala.xml.dtd.ContentModel$ MODULE$;
  Signature: Lscala/xml/dtd/ContentModel$;

public static {};
  Signature: ()V
  Code:
   Stack=1, Locals=0, Args_size=0
	new	class scala/xml/dtd/ContentModel$
	invokespecial	Method "<init>":()V
	return
  Labels:

private scala.xml.dtd.ContentModel$();
  Signature: ()V
  Code:
   Stack=1, Locals=1, Args_size=1
	aload_0
	invokespecial	Method scala/util/regexp/WordExp."<init>":()V
	aload_0
	putstatic	Field MODULE$:Lscala/xml/dtd/ContentModel$;
	return
  Labels:

public final scala.collection.immutable.Set traverse$1(scala.util.regexp.Base$RegExp);
  Signature: (Lscala/util/regexp/Base$RegExp;)Lscala/collection/immutable/Set;
  Code:
   Stack=6, Locals=15, Args_size=2
l7	aload_1
	instanceof	class scala/util/regexp/WordExp$Letter
	ifeq	l1 // aload_1
	aload_1
	checkcast	class scala/util/regexp/WordExp$Letter
	astore_2
	aload_2
	invokevirtual	Method scala/util/regexp/WordExp$Letter.a:()Lscala/util/regexp/WordExp$Label;
	checkcast	class scala/xml/dtd/ContentModel$ElemName
	astore_3
	aload_3
	ifnull	l2 // new
	aload_3
	invokevirtual	Method scala/xml/dtd/ContentModel$ElemName.name:()Ljava/lang/String;
	astore	4
	iconst_1
	ifeq	l3 // new
	getstatic	Field scala/Predef$.MODULE$:Lscala/Predef$;
	invokevirtual	Method scala/Predef$.Set:()Lscala/collection/immutable/Set$;
	getstatic	Field scala/Predef$.MODULE$:Lscala/Predef$;
	iconst_1
	anewarray	class java/lang/String
	dup
	iconst_0
	aload	4
	aastore
	checkcast	class "[Ljava/lang/Object;"
	invokevirtual	Method scala/Predef$.wrapRefArray:([Ljava/lang/Object;)Lscala/collection/mutable/WrappedArray;
	invokevirtual	Method scala/collection/immutable/Set$.apply:(Lscala/collection/Seq;)Lscala/collection/Traversable;
	checkcast	class scala/collection/immutable/Set
	goto	l4 // areturn
l3	new	class scala/MatchError
	dup
	aload_1
	invokevirtual	Method scala/util/regexp/Base$RegExp.toString:()Ljava/lang/String;
	invokespecial	Method scala/MatchError."<init>":(Ljava/lang/String;)V
	athrow
l2	new	class scala/MatchError
	dup
	aload_1
	invokevirtual	Method scala/util/regexp/Base$RegExp.toString:()Ljava/lang/String;
	invokespecial	Method scala/MatchError."<init>":(Ljava/lang/String;)V
	athrow
l1	aload_1
	instanceof	class scala/util/regexp/Base$Star
	ifeq	l5 // aload_1
	aload_1
	checkcast	class scala/util/regexp/Base$Star
	astore	5
	aload	5
	invokevirtual	Method scala/util/regexp/Base$Star.r:()Lscala/util/regexp/Base$RegExp;
	astore	6
	iconst_1
	ifeq	l6 // new
	aload	6
	astore_1
	goto	l7 // aload_1
l6	new	class scala/MatchError
	dup
	aload_1
	invokevirtual	Method scala/util/regexp/Base$RegExp.toString:()Ljava/lang/String;
	invokespecial	Method scala/MatchError."<init>":(Ljava/lang/String;)V
	athrow
l5	aload_1
	instanceof	class scala/util/regexp/Base$Sequ
	ifeq	l8 // aload_1
	aload_1
	checkcast	class scala/util/regexp/Base$Sequ
	astore	7
	aload_0
	invokevirtual	Method Sequ:()Lscala/util/regexp/Base$Sequ$;
	pop
	new	class scala/Some
	dup
	aload	7
	invokevirtual	Method scala/util/regexp/Base$Sequ.rs:()Lscala/collection/Seq;
	invokespecial	Method scala/Some."<init>":(Ljava/lang/Object;)V
	astore	8
	iconst_1
	ifeq	l9 // new
	aload	8
	getfield	Field scala/Some.x:Ljava/lang/Object;
	checkcast	class scala/collection/Seq
	astore	9
	aload	9
	dup
	pop
	ifnull	l10 // iconst_0
	aload	9
	aconst_null
	invokevirtual	Method java/lang/Object.equals:(Ljava/lang/Object;)Z
	ifeq	l11 // aload
l10	iconst_0
	goto	l12 // ifeq
l11	aload	9
	iconst_0
	invokeinterface	InterfaceMethod scala/collection/SeqLike.lengthCompare:(I)I
	iconst_0
	if_icmplt	l13 // iconst_0
	iconst_1
	goto	l12 // ifeq
l13	iconst_0
l12	ifeq	l14 // new
	iconst_1
	ifeq	l15 // new
	getstatic	Field scala/Predef$.MODULE$:Lscala/Predef$;
	invokevirtual	Method scala/Predef$.Set:()Lscala/collection/immutable/Set$;
	aload	9
	new	class scala/xml/dtd/ContentModel$$anonfun$traverse$1$1
	dup
	invokespecial	Method scala/xml/dtd/ContentModel$$anonfun$traverse$1$1."<init>":()V
	getstatic	Field scala/collection/Seq$.MODULE$:Lscala/collection/Seq$;
	astore	10
	new	class scala/collection/generic/TraversableFactory$GenericCanBuildFrom
	dup
	aload	10
	invokespecial	Method scala/collection/generic/TraversableFactory$GenericCanBuildFrom."<init>":(Lscala/collection/generic/TraversableFactory;)V
	invokeinterface	InterfaceMethod scala/collection/TraversableLike.map:(Lscala/Function1;Lscala/collection/generic/CanBuildFrom;)Ljava/lang/Object;
	checkcast	class scala/collection/generic/GenericTraversableTemplate
	new	class scala/Predef$$anon$1
	dup
	invokespecial	Method scala/Predef$$anon$1."<init>":()V
	invokeinterface	InterfaceMethod scala/collection/generic/GenericTraversableTemplate.flatten:(Lscala/Function1;)Lscala/collection/Traversable;
	checkcast	class scala/collection/Seq
	invokevirtual	Method scala/collection/immutable/Set$.apply:(Lscala/collection/Seq;)Lscala/collection/Traversable;
	checkcast	class scala/collection/immutable/Set
	goto	l4 // areturn
l15	new	class scala/MatchError
	dup
	aload_1
	invokevirtual	Method scala/util/regexp/Base$RegExp.toString:()Ljava/lang/String;
	invokespecial	Method scala/MatchError."<init>":(Ljava/lang/String;)V
	athrow
l14	new	class scala/MatchError
	dup
	aload_1
	invokevirtual	Method scala/util/regexp/Base$RegExp.toString:()Ljava/lang/String;
	invokespecial	Method scala/MatchError."<init>":(Ljava/lang/String;)V
	athrow
l9	new	class scala/MatchError
	dup
	aload_1
	invokevirtual	Method scala/util/regexp/Base$RegExp.toString:()Ljava/lang/String;
	invokespecial	Method scala/MatchError."<init>":(Ljava/lang/String;)V
	athrow
l8	aload_1
	instanceof	class scala/util/regexp/Base$Alt
	ifeq	l16 // new
	aload_1
	checkcast	class scala/util/regexp/Base$Alt
	astore	11
	aload_0
	invokevirtual	Method Alt:()Lscala/util/regexp/Base$Alt$;
	pop
	new	class scala/Some
	dup
	aload	11
	invokevirtual	Method scala/util/regexp/Base$Alt.rs:()Lscala/collection/Seq;
	invokespecial	Method scala/Some."<init>":(Ljava/lang/Object;)V
	astore	12
	iconst_1
	ifeq	l17 // new
	aload	12
	getfield	Field scala/Some.x:Ljava/lang/Object;
	checkcast	class scala/collection/Seq
	astore	13
	aload	13
	dup
	pop
	ifnull	l18 // iconst_0
	aload	13
	aconst_null
	invokevirtual	Method java/lang/Object.equals:(Ljava/lang/Object;)Z
	ifeq	l19 // aload
l18	iconst_0
	goto	l20 // ifeq
l19	aload	13
	iconst_0
	invokeinterface	InterfaceMethod scala/collection/SeqLike.lengthCompare:(I)I
	iconst_0
	if_icmplt	l21 // iconst_0
	iconst_1
	goto	l20 // ifeq
l21	iconst_0
l20	ifeq	l22 // new
	iconst_1
	ifeq	l23 // new
	getstatic	Field scala/Predef$.MODULE$:Lscala/Predef$;
	invokevirtual	Method scala/Predef$.Set:()Lscala/collection/immutable/Set$;
	aload	13
	new	class scala/xml/dtd/ContentModel$$anonfun$traverse$1$2
	dup
	invokespecial	Method scala/xml/dtd/ContentModel$$anonfun$traverse$1$2."<init>":()V
	getstatic	Field scala/collection/Seq$.MODULE$:Lscala/collection/Seq$;
	astore	14
	new	class scala/collection/generic/TraversableFactory$GenericCanBuildFrom
	dup
	aload	14
	invokespecial	Method scala/collection/generic/TraversableFactory$GenericCanBuildFrom."<init>":(Lscala/collection/generic/TraversableFactory;)V
	invokeinterface	InterfaceMethod scala/collection/TraversableLike.map:(Lscala/Function1;Lscala/collection/generic/CanBuildFrom;)Ljava/lang/Object;
	checkcast	class scala/collection/generic/GenericTraversableTemplate
	new	class scala/Predef$$anon$1
	dup
	invokespecial	Method scala/Predef$$anon$1."<init>":()V
	invokeinterface	InterfaceMethod scala/collection/generic/GenericTraversableTemplate.flatten:(Lscala/Function1;)Lscala/collection/Traversable;
	checkcast	class scala/collection/Seq
	invokevirtual	Method scala/collection/immutable/Set$.apply:(Lscala/collection/Seq;)Lscala/collection/Traversable;
	checkcast	class scala/collection/immutable/Set
l4	areturn
l23	new	class scala/MatchError
	dup
	aload_1
	invokevirtual	Method scala/util/regexp/Base$RegExp.toString:()Ljava/lang/String;
	invokespecial	Method scala/MatchError."<init>":(Ljava/lang/String;)V
	athrow
l22	new	class scala/MatchError
	dup
	aload_1
	invokevirtual	Method scala/util/regexp/Base$RegExp.toString:()Ljava/lang/String;
	invokespecial	Method scala/MatchError."<init>":(Ljava/lang/String;)V
	athrow
l17	new	class scala/MatchError
	dup
	aload_1
	invokevirtual	Method scala/util/regexp/Base$RegExp.toString:()Ljava/lang/String;
	invokespecial	Method scala/MatchError."<init>":(Ljava/lang/String;)V
	athrow
l16	new	class scala/MatchError
	dup
	aload_1
	invokevirtual	Method scala/util/regexp/Base$RegExp.toString:()Ljava/lang/String;
	invokespecial	Method scala/MatchError."<init>":(Ljava/lang/String;)V
	athrow
  Labels:
   	l7 = 0 // aload_1
   	l3 = 67 // new
   	l2 = 79 // new
   	l1 = 91 // aload_1
   	l6 = 121 // new
   	l5 = 133 // aload_1
   	l10 = 195 // iconst_0
   	l11 = 199 // aload
   	l13 = 215 // iconst_0
   	l12 = 216 // ifeq
   	l15 = 284 // new
   	l14 = 296 // new
   	l9 = 308 // new
   	l8 = 320 // aload_1
   	l18 = 382 // iconst_0
   	l19 = 386 // aload
   	l21 = 402 // iconst_0
   	l20 = 403 // ifeq
   	l4 = 468 // areturn
   	l23 = 469 // new
   	l22 = 481 // new
   	l17 = 493 // new
   	l16 = 505 // new
  LocalVariableTable: 
   Start  Length  Slot  Name   Signature
   0      517      0    this       Lscala/xml/dtd/ContentModel$;
   0      517      1    r       Lscala/util/regexp/Base$RegExp;
   12      79      2    temp12       Lscala/util/regexp/WordExp$Letter;
   20      71      3    temp13       Lscala/xml/dtd/ContentModel$ElemName;
   30      49      4    temp14       Ljava/lang/String;
   104      29      5    temp15       Lscala/util/regexp/Base$Star;
   111      22      6    temp16       Lscala/util/regexp/Base$RegExp;
   146      174      7    temp17       Lscala/util/regexp/Base$Sequ;
   165      155      8    temp18       Lscala/Some;
   179      129      9    temp19       Lscala/collection/Seq;
   333      135      11    temp21       Lscala/util/regexp/Base$Alt;
   469      36      11    temp21       Lscala/util/regexp/Base$Alt;
   352      116      12    temp22       Lscala/Some;
   469      36      12    temp22       Lscala/Some;
   366      102      13    temp23       Lscala/collection/Seq;
   469      24      13    temp23       Lscala/collection/Seq;


public scala.collection.mutable.StringBuilder buildString(scala.util.regexp.Base$RegExp, scala.collection.mutable.StringBuilder);
  Signature: (Lscala/util/regexp/Base$RegExp;Lscala/collection/mutable/StringBuilder;)Lscala/collection/mutable/StringBuilder;
  Code:
   Stack=4, Locals=15, Args_size=3
	aload_1
	aload_0
	invokevirtual	Method Eps:()Lscala/util/regexp/Base$Eps$;
	astore_3
	dup
	ifnonnull	l1 // aload_3
	pop
	aload_3
	ifnull	l2 // iconst_1
	goto	l3 // aload_1
l1	aload_3
	invokevirtual	Method java/lang/Object.equals:(Ljava/lang/Object;)Z
	ifeq	l3 // aload_1
l2	iconst_1
	ifeq	l4 // new
	aload_2
	goto	l5 // areturn
l4	new	class scala/MatchError
	dup
	aload_1
	invokevirtual	Method scala/util/regexp/Base$RegExp.toString:()Ljava/lang/String;
	invokespecial	Method scala/MatchError."<init>":(Ljava/lang/String;)V
	athrow
l3	aload_1
	instanceof	class scala/util/regexp/Base$Sequ
	ifeq	l6 // aload_1
	aload_1
	checkcast	class scala/util/regexp/Base$Sequ
	astore	4
	aload_0
	invokevirtual	Method Sequ:()Lscala/util/regexp/Base$Sequ$;
	pop
	new	class scala/Some
	dup
	aload	4
	invokevirtual	Method scala/util/regexp/Base$Sequ.rs:()Lscala/collection/Seq;
	invokespecial	Method scala/Some."<init>":(Ljava/lang/Object;)V
	astore	5
	iconst_1
	ifeq	l7 // new
	aload	5
	getfield	Field scala/Some.x:Ljava/lang/Object;
	checkcast	class scala/collection/Seq
	astore	6
	aload	6
	dup
	pop
	ifnull	l8 // iconst_0
	aload	6
	aconst_null
	invokevirtual	Method java/lang/Object.equals:(Ljava/lang/Object;)Z
	ifeq	l9 // aload
l8	iconst_0
	goto	l10 // ifeq
l9	aload	6
	iconst_0
	invokeinterface	InterfaceMethod scala/collection/SeqLike.lengthCompare:(I)I
	iconst_0
	if_icmplt	l11 // iconst_0
	iconst_1
	goto	l10 // ifeq
l11	iconst_0
l10	ifeq	l12 // new
	iconst_1
	ifeq	l13 // new
	aload_2
	ldc	int 40
	invokevirtual	Method scala/collection/mutable/StringBuilder.append:(C)Lscala/collection/mutable/StringBuilder;
	pop
	aload_0
	aload	6
	aload_2
	ldc	int 44
	invokespecial	Method buildString:(Lscala/collection/Seq;Lscala/collection/mutable/StringBuilder;C)V
	aload_2
	ldc	int 41
	invokevirtual	Method scala/collection/mutable/StringBuilder.append:(C)Lscala/collection/mutable/StringBuilder;
	goto	l5 // areturn
l13	new	class scala/MatchError
	dup
	aload_1
	invokevirtual	Method scala/util/regexp/Base$RegExp.toString:()Ljava/lang/String;
	invokespecial	Method scala/MatchError."<init>":(Ljava/lang/String;)V
	athrow
l12	new	class scala/MatchError
	dup
	aload_1
	invokevirtual	Method scala/util/regexp/Base$RegExp.toString:()Ljava/lang/String;
	invokespecial	Method scala/MatchError."<init>":(Ljava/lang/String;)V
	athrow
l7	new	class scala/MatchError
	dup
	aload_1
	invokevirtual	Method scala/util/regexp/Base$RegExp.toString:()Ljava/lang/String;
	invokespecial	Method scala/MatchError."<init>":(Ljava/lang/String;)V
	athrow
l6	aload_1
	instanceof	class scala/util/regexp/Base$Alt
	ifeq	l14 // aload_1
	aload_1
	checkcast	class scala/util/regexp/Base$Alt
	astore	7
	aload_0
	invokevirtual	Method Alt:()Lscala/util/regexp/Base$Alt$;
	pop
	new	class scala/Some
	dup
	aload	7
	invokevirtual	Method scala/util/regexp/Base$Alt.rs:()Lscala/collection/Seq;
	invokespecial	Method scala/Some."<init>":(Ljava/lang/Object;)V
	astore	8
	iconst_1
	ifeq	l15 // new
	aload	8
	getfield	Field scala/Some.x:Ljava/lang/Object;
	checkcast	class scala/collection/Seq
	astore	9
	aload	9
	dup
	pop
	ifnull	l16 // iconst_0
	aload	9
	aconst_null
	invokevirtual	Method java/lang/Object.equals:(Ljava/lang/Object;)Z
	ifeq	l17 // aload
l16	iconst_0
	goto	l18 // ifeq
l17	aload	9
	iconst_0
	invokeinterface	InterfaceMethod scala/collection/SeqLike.lengthCompare:(I)I
	iconst_0
	if_icmplt	l19 // iconst_0
	iconst_1
	goto	l18 // ifeq
l19	iconst_0
l18	ifeq	l20 // new
	iconst_1
	ifeq	l21 // new
	aload_2
	ldc	int 40
	invokevirtual	Method scala/collection/mutable/StringBuilder.append:(C)Lscala/collection/mutable/StringBuilder;
	pop
	aload_0
	aload	9
	aload_2
	ldc	int 124
	invokespecial	Method buildString:(Lscala/collection/Seq;Lscala/collection/mutable/StringBuilder;C)V
	aload_2
	ldc	int 41
	invokevirtual	Method scala/collection/mutable/StringBuilder.append:(C)Lscala/collection/mutable/StringBuilder;
	goto	l5 // areturn
l21	new	class scala/MatchError
	dup
	aload_1
	invokevirtual	Method scala/util/regexp/Base$RegExp.toString:()Ljava/lang/String;
	invokespecial	Method scala/MatchError."<init>":(Ljava/lang/String;)V
	athrow
l20	new	class scala/MatchError
	dup
	aload_1
	invokevirtual	Method scala/util/regexp/Base$RegExp.toString:()Ljava/lang/String;
	invokespecial	Method scala/MatchError."<init>":(Ljava/lang/String;)V
	athrow
l15	new	class scala/MatchError
	dup
	aload_1
	invokevirtual	Method scala/util/regexp/Base$RegExp.toString:()Ljava/lang/String;
	invokespecial	Method scala/MatchError."<init>":(Ljava/lang/String;)V
	athrow
l14	aload_1
	instanceof	class scala/util/regexp/Base$Star
	ifeq	l22 // aload_1
	aload_1
	checkcast	class scala/util/regexp/Base$Star
	astore	10
	aload	10
	invokevirtual	Method scala/util/regexp/Base$Star.r:()Lscala/util/regexp/Base$RegExp;
	astore	11
	aload	11
	ifnull	l23 // new
	iconst_1
	ifeq	l24 // new
	aload_2
	ldc	int 40
	invokevirtual	Method scala/collection/mutable/StringBuilder.append:(C)Lscala/collection/mutable/StringBuilder;
	pop
	aload_0
	aload	11
	aload_2
	invokevirtual	Method buildString:(Lscala/util/regexp/Base$RegExp;Lscala/collection/mutable/StringBuilder;)Lscala/collection/mutable/StringBuilder;
	pop
	aload_2
	ldc	String )*
	invokevirtual	Method scala/collection/mutable/StringBuilder.append:(Ljava/lang/String;)Lscala/collection/mutable/StringBuilder;
	goto	l5 // areturn
l24	new	class scala/MatchError
	dup
	aload_1
	invokevirtual	Method scala/util/regexp/Base$RegExp.toString:()Ljava/lang/String;
	invokespecial	Method scala/MatchError."<init>":(Ljava/lang/String;)V
	athrow
l23	new	class scala/MatchError
	dup
	aload_1
	invokevirtual	Method scala/util/regexp/Base$RegExp.toString:()Ljava/lang/String;
	invokespecial	Method scala/MatchError."<init>":(Ljava/lang/String;)V
	athrow
l22	aload_1
	instanceof	class scala/util/regexp/WordExp$Letter
	ifeq	l25 // new
	aload_1
	checkcast	class scala/util/regexp/WordExp$Letter
	astore	12
	aload	12
	invokevirtual	Method scala/util/regexp/WordExp$Letter.a:()Lscala/util/regexp/WordExp$Label;
	checkcast	class scala/xml/dtd/ContentModel$ElemName
	astore	13
	aload	13
	ifnull	l26 // new
	aload	13
	invokevirtual	Method scala/xml/dtd/ContentModel$ElemName.name:()Ljava/lang/String;
	astore	14
	iconst_1
	ifeq	l27 // new
	aload_2
	aload	14
	invokevirtual	Method scala/collection/mutable/StringBuilder.append:(Ljava/lang/String;)Lscala/collection/mutable/StringBuilder;
l5	areturn
l27	new	class scala/MatchError
	dup
	aload_1
	invokevirtual	Method scala/util/regexp/Base$RegExp.toString:()Ljava/lang/String;
	invokespecial	Method scala/MatchError."<init>":(Ljava/lang/String;)V
	athrow
l26	new	class scala/MatchError
	dup
	aload_1
	invokevirtual	Method scala/util/regexp/Base$RegExp.toString:()Ljava/lang/String;
	invokespecial	Method scala/MatchError."<init>":(Ljava/lang/String;)V
	athrow
l25	new	class scala/MatchError
	dup
	aload_1
	invokevirtual	Method scala/util/regexp/Base$RegExp.toString:()Ljava/lang/String;
	invokespecial	Method scala/MatchError."<init>":(Ljava/lang/String;)V
	athrow
  Labels:
   	l1 = 18 // aload_3
   	l2 = 25 // iconst_1
   	l4 = 33 // new
   	l3 = 45 // aload_1
   	l8 = 107 // iconst_0
   	l9 = 111 // aload
   	l11 = 127 // iconst_0
   	l10 = 128 // ifeq
   	l13 = 160 // new
   	l12 = 172 // new
   	l7 = 184 // new
   	l6 = 196 // aload_1
   	l16 = 258 // iconst_0
   	l17 = 262 // aload
   	l19 = 278 // iconst_0
   	l18 = 279 // ifeq
   	l21 = 311 // new
   	l20 = 323 // new
   	l15 = 335 // new
   	l14 = 347 // aload_1
   	l24 = 400 // new
   	l23 = 412 // new
   	l22 = 424 // aload_1
   	l5 = 469 // areturn
   	l27 = 470 // new
   	l26 = 482 // new
   	l25 = 494 // new
  LocalVariableTable: 
   Start  Length  Slot  Name   Signature
   0      506      0    this       Lscala/xml/dtd/ContentModel$;
   0      506      1    r       Lscala/util/regexp/Base$RegExp;
   0      506      2    sb       Lscala/collection/mutable/StringBuilder;
   58      138      4    temp34       Lscala/util/regexp/Base$Sequ;
   77      119      5    temp35       Lscala/Some;
   91      93      6    temp36       Lscala/collection/Seq;
   209      138      7    temp38       Lscala/util/regexp/Base$Alt;
   228      119      8    temp39       Lscala/Some;
   242      93      9    temp40       Lscala/collection/Seq;
   360      64      10    temp42       Lscala/util/regexp/Base$Star;
   367      57      11    temp43       Lscala/util/regexp/Base$RegExp;
   437      32      12    temp44       Lscala/util/regexp/WordExp$Letter;
   470      24      12    temp44       Lscala/util/regexp/WordExp$Letter;
   447      22      13    temp45       Lscala/xml/dtd/ContentModel$ElemName;
   470      24      13    temp45       Lscala/xml/dtd/ContentModel$ElemName;
   459      10      14    temp46       Ljava/lang/String;
   470      12      14    temp46       Ljava/lang/String;


public scala.collection.mutable.StringBuilder buildString(scala.xml.dtd.ContentModel, scala.collection.mutable.StringBuilder);
  Signature: (Lscala/xml/dtd/ContentModel;Lscala/collection/mutable/StringBuilder;)Lscala/collection/mutable/StringBuilder;
  Code:
   Stack=3, Locals=3, Args_size=3
	getstatic	Field scala/xml/dtd/ANY$.MODULE$:Lscala/xml/dtd/ANY$;
	dup
	ifnonnull	l1 // aload_1
	pop
	aload_1
	ifnull	l2 // iconst_1
	goto	l3 // getstatic
l1	aload_1
	invokevirtual	Method java/lang/Object.equals:(Ljava/lang/Object;)Z
	ifeq	l3 // getstatic
l2	iconst_1
	ifeq	l4 // new
	aload_2
	ldc	String ANY
	invokevirtual	Method scala/collection/mutable/StringBuilder.append:(Ljava/lang/String;)Lscala/collection/mutable/StringBuilder;
	goto	l5 // areturn
l4	new	class scala/MatchError
	dup
	aload_1
	invokevirtual	Method scala/xml/dtd/ContentModel.toString:()Ljava/lang/String;
	invokespecial	Method scala/MatchError."<init>":(Ljava/lang/String;)V
	athrow
l3	getstatic	Field scala/xml/dtd/EMPTY$.MODULE$:Lscala/xml/dtd/EMPTY$;
	dup
	ifnonnull	l6 // aload_1
	pop
	aload_1
	ifnull	l7 // iconst_1
	goto	l8 // getstatic
l6	aload_1
	invokevirtual	Method java/lang/Object.equals:(Ljava/lang/Object;)Z
	ifeq	l8 // getstatic
l7	iconst_1
	ifeq	l9 // new
	aload_2
	ldc	String EMPTY
	invokevirtual	Method scala/collection/mutable/StringBuilder.append:(Ljava/lang/String;)Lscala/collection/mutable/StringBuilder;
	goto	l5 // areturn
l9	new	class scala/MatchError
	dup
	aload_1
	invokevirtual	Method scala/xml/dtd/ContentModel.toString:()Ljava/lang/String;
	invokespecial	Method scala/MatchError."<init>":(Ljava/lang/String;)V
	athrow
l8	getstatic	Field scala/xml/dtd/PCDATA$.MODULE$:Lscala/xml/dtd/PCDATA$;
	dup
	ifnonnull	l10 // aload_1
	pop
	aload_1
	ifnull	l11 // iconst_1
	goto	l12 // aload_1
l10	aload_1
	invokevirtual	Method java/lang/Object.equals:(Ljava/lang/Object;)Z
	ifeq	l12 // aload_1
l11	iconst_1
	ifeq	l13 // new
	aload_2
	ldc	String (#PCDATA)
	invokevirtual	Method scala/collection/mutable/StringBuilder.append:(Ljava/lang/String;)Lscala/collection/mutable/StringBuilder;
	goto	l5 // areturn
l13	new	class scala/MatchError
	dup
	aload_1
	invokevirtual	Method scala/xml/dtd/ContentModel.toString:()Ljava/lang/String;
	invokespecial	Method scala/MatchError."<init>":(Ljava/lang/String;)V
	athrow
l12	aload_1
	instanceof	class scala/xml/dtd/ELEMENTS
	ifeq	l14 // aload_1
	iconst_1
	ifne	l15 // aload_1
	new	class scala/MatchError
	dup
	aload_1
	invokevirtual	Method scala/xml/dtd/ContentModel.toString:()Ljava/lang/String;
	invokespecial	Method scala/MatchError."<init>":(Ljava/lang/String;)V
	athrow
l14	aload_1
	instanceof	class scala/xml/dtd/MIXED
	ifeq	l16 // new
	iconst_1
	ifeq	l17 // new
l15	aload_1
	aload_2
	invokevirtual	Method scala/xml/dtd/ContentModel.buildString:(Lscala/collection/mutable/StringBuilder;)Lscala/collection/mutable/StringBuilder;
l5	areturn
l17	new	class scala/MatchError
	dup
	aload_1
	invokevirtual	Method scala/xml/dtd/ContentModel.toString:()Ljava/lang/String;
	invokespecial	Method scala/MatchError."<init>":(Ljava/lang/String;)V
	athrow
l16	new	class scala/MatchError
	dup
	aload_1
	invokevirtual	Method scala/xml/dtd/ContentModel.toString:()Ljava/lang/String;
	invokespecial	Method scala/MatchError."<init>":(Ljava/lang/String;)V
	athrow
  Labels:
   	l1 = 15 // aload_1
   	l2 = 22 // iconst_1
   	l4 = 35 // new
   	l3 = 47 // getstatic
   	l6 = 62 // aload_1
   	l7 = 69 // iconst_1
   	l9 = 82 // new
   	l8 = 94 // getstatic
   	l10 = 109 // aload_1
   	l11 = 116 // iconst_1
   	l13 = 129 // new
   	l12 = 141 // aload_1
   	l14 = 164 // aload_1
   	l15 = 175 // aload_1
   	l5 = 180 // areturn
   	l17 = 181 // new
   	l16 = 193 // new
  LocalVariableTable: 
   Start  Length  Slot  Name   Signature
   0      205      0    this       Lscala/xml/dtd/ContentModel$;
   0      205      1    c       Lscala/xml/dtd/ContentModel;
   0      205      2    sb       Lscala/collection/mutable/StringBuilder;


private void buildString(scala.collection.Seq, scala.collection.mutable.StringBuilder, char);
  Signature: (Lscala/collection/Seq;Lscala/collection/mutable/StringBuilder;C)V
  Code:
   Stack=5, Locals=4, Args_size=4
	aload_0
	aload_1
	invokeinterface	InterfaceMethod scala/collection/IterableLike.head:()Ljava/lang/Object;
	checkcast	class scala/util/regexp/Base$RegExp
	aload_2
	invokevirtual	Method buildString:(Lscala/util/regexp/Base$RegExp;Lscala/collection/mutable/StringBuilder;)Lscala/collection/mutable/StringBuilder;
	pop
	aload_1
	invokeinterface	InterfaceMethod scala/collection/TraversableLike.tail:()Ljava/lang/Object;
	checkcast	class scala/collection/IterableLike
	new	class scala/xml/dtd/ContentModel$$anonfun$buildString$2
	dup
	aload_2
	iload_3
	invokespecial	Method scala/xml/dtd/ContentModel$$anonfun$buildString$2."<init>":(Lscala/collection/mutable/StringBuilder;C)V
	invokeinterface	InterfaceMethod scala/collection/IterableLike.foreach:(Lscala/Function1;)V
	return
  Labels:
  LocalVariableTable: 
   Start  Length  Slot  Name   Signature
   0      39      0    this       Lscala/xml/dtd/ContentModel$;
   0      39      1    rs       Lscala/collection/Seq;
   0      39      2    sb$1       Lscala/collection/mutable/StringBuilder;
   0      39      3    sep$1       C

  Signature: length = 0x2
   01 06 

public java.lang.String buildString(scala.util.regexp.Base$RegExp);
  Signature: (Lscala/util/regexp/Base$RegExp;)Ljava/lang/String;
  Code:
   Stack=3, Locals=4, Args_size=2
	new	class scala/xml/dtd/ContentModel$$anonfun$buildString$1
	dup
	pop
	aload_1
	invokespecial	Method scala/xml/dtd/ContentModel$$anonfun$buildString$1."<init>":(Lscala/util/regexp/Base$RegExp;)V
	new	class scala/collection/mutable/StringBuilder
	dup
	invokespecial	Method scala/collection/mutable/StringBuilder."<init>":()V
	astore_3
	aload_3
	checkcast	class scala/collection/mutable/StringBuilder
	astore_2
	getstatic	Field MODULE$:Lscala/xml/dtd/ContentModel$;
	aload_1
	aload_2
	invokevirtual	Method buildString:(Lscala/util/regexp/Base$RegExp;Lscala/collection/mutable/StringBuilder;)Lscala/collection/mutable/StringBuilder;
	pop
	aload_3
	invokevirtual	Method scala/collection/mutable/StringBuilder.toString:()Ljava/lang/String;
	areturn
  Labels:
  LocalVariableTable: 
   Start  Length  Slot  Name   Signature
   0      36      0    this       Lscala/xml/dtd/ContentModel$;
   0      36      1    r$3       Lscala/util/regexp/Base$RegExp;
   17      18      3    sb0       Lscala/collection/mutable/StringBuilder;


public scala.collection.immutable.Set getLabels(scala.util.regexp.Base$RegExp);
  Signature: (Lscala/util/regexp/Base$RegExp;)Lscala/collection/immutable/Set;
  Code:
   Stack=2, Locals=2, Args_size=2
	aload_0
	aload_1
	invokevirtual	Method traverse$1:(Lscala/util/regexp/Base$RegExp;)Lscala/collection/immutable/Set;
	areturn
  Labels:
  LocalVariableTable: 
   Start  Length  Slot  Name   Signature
   0      6      0    this       Lscala/xml/dtd/ContentModel$;
   0      6      1    r       Lscala/util/regexp/Base$RegExp;

  Signature: length = 0x2
   01 15 

public scala.xml.dtd.ContentModel parse(java.lang.String);
  Signature: (Ljava/lang/String;)Lscala/xml/dtd/ContentModel;
  Code:
   Stack=2, Locals=2, Args_size=2
	getstatic	Field scala/xml/dtd/ContentModelParser$.MODULE$:Lscala/xml/dtd/ContentModelParser$;
	aload_1
	invokevirtual	Method scala/xml/dtd/ContentModelParser$.parse:(Ljava/lang/String;)Lscala/xml/dtd/ContentModel;
	areturn
  Labels:
  LocalVariableTable: 
   Start  Length  Slot  Name   Signature
   0      8      0    this       Lscala/xml/dtd/ContentModel$;
   0      8      1    s       Ljava/lang/String;


public boolean containsText(scala.xml.dtd.ContentModel);
  Signature: (Lscala/xml/dtd/ContentModel;)Z
  Code:
   Stack=4, Locals=3, Args_size=2
	aload_1
	getstatic	Field scala/xml/dtd/PCDATA$.MODULE$:Lscala/xml/dtd/PCDATA$;
	astore_2
	dup
	ifnonnull	l1 // aload_2
	pop
	aload_2
	ifnull	l2 // iconst_1
	goto	l3 // getstatic
l1	aload_2
	invokevirtual	Method java/lang/Object.equals:(Ljava/lang/Object;)Z
	ifne	l2 // iconst_1
l3	getstatic	Field scala/PartialFunction$.MODULE$:Lscala/PartialFunction$;
	aload_1
	new	class scala/xml/dtd/ContentModel$$anonfun$isMixed$1
	dup
	invokespecial	Method scala/xml/dtd/ContentModel$$anonfun$isMixed$1."<init>":()V
	invokevirtual	Method scala/PartialFunction$.cond:(Ljava/lang/Object;Lscala/PartialFunction;)Z
	ifeq	l4 // iconst_0
l2	iconst_1
	goto	l5 // ireturn
l4	iconst_0
l5	ireturn
  Labels:
   	l1 = 17 // aload_2
   	l3 = 24 // getstatic
   	l2 = 41 // iconst_1
   	l4 = 45 // iconst_0
   	l5 = 46 // ireturn
  LocalVariableTable: 
   Start  Length  Slot  Name   Signature
   0      47      0    this       Lscala/xml/dtd/ContentModel$;
   0      47      1    cm       Lscala/xml/dtd/ContentModel;


public boolean isMixed(scala.xml.dtd.ContentModel);
  Signature: (Lscala/xml/dtd/ContentModel;)Z
  Code:
   Stack=4, Locals=2, Args_size=2
	getstatic	Field scala/PartialFunction$.MODULE$:Lscala/PartialFunction$;
	aload_1
	new	class scala/xml/dtd/ContentModel$$anonfun$isMixed$1
	dup
	invokespecial	Method scala/xml/dtd/ContentModel$$anonfun$isMixed$1."<init>":()V
	invokevirtual	Method scala/PartialFunction$.cond:(Ljava/lang/Object;Lscala/PartialFunction;)Z
	ireturn
  Labels:
  LocalVariableTable: 
   Start  Length  Slot  Name   Signature
   0      15      0    this       Lscala/xml/dtd/ContentModel$;
   0      15      1    cm       Lscala/xml/dtd/ContentModel;


}

