Compiled from "ContentModelParser.scala"
public final class scala.xml.dtd.ContentModelParser extends java.lang.Object
  SourceFile: "ContentModelParser.scala"
  ScalaSig: length = 0x24E
   05 00 60 07 05 01 02 FFFFFF88 02 09 01 12 43 6F 6E 74
   65 6E 74 4D 6F 64 65 6C 50 61 72 73 65 72 0A 02
   03 04 01 03 64 74 64 0A 02 05 06 01 03 78 6D 6C
   0A 01 07 01 05 73 63 61 6C 61 03 00 10 02 0A 0B
   0D 01 02 06 08 0C 02 FFFFFF84 FFFFFF80 FFFFFF80 FFFFFF88 02 0D 02 12 43
   6F 6E 74 65 6E 74 4D 6F 64 65 6C 50 61 72 73 65
   72 13 03 0B 0E 11 10 02 0A 0F 09 02 10 02 02 07
   53 63 61 6E 6E 65 72 10 02 12 13 0D 01 06 09 02
   14 06 02 0B 53 63 61 6C 61 4F 62 6A 65 63 74 08
   05 16 0B FFFFFF84 00 17 01 06 3C 69 6E 69 74 3E 14 01
   09 08 05 19 0B FFFFFF84 00 1A 01 05 70 61 72 73 65 14
   02 1B 1E 10 02 0A 1C 09 02 1D 02 02 0C 43 6F 6E
   74 65 6E 74 4D 6F 64 65 6C 08 05 1F 18 FFFFFFC0 00 20
   01 01 73 10 02 21 24 0E 02 12 22 09 02 23 06 01
   06 50 72 65 64 65 66 09 02 25 26 02 06 53 74 72
   69 6E 67 0A 02 23 06 08 05 28 0B FFFFFF84 00 29 01 06
   61 63 63 65 70 74 14 02 2A 2D 10 02 12 2B 09 02
   2C 06 02 04 55 6E 69 74 08 05 2E 27 FFFFFFC0 00 2F 01
   03 74 6F 6B 10 02 12 30 09 02 31 06 02 03 49 6E
   74 08 05 33 0B FFFFFF84 00 34 01 0B 6D 61 79 62 65 53
   75 66 66 69 78 14 02 35 41 10 02 36 39 0E 02 0A
   37 09 02 38 02 01 0C 43 6F 6E 74 65 6E 74 4D 6F
   64 65 6C 09 02 3A 3B 02 06 52 65 67 45 78 70 09
   02 3C 3D 02 04 42 61 73 65 0A 02 3E 3F 01 06 72
   65 67 65 78 70 0A 02 40 06 01 04 75 74 69 6C 08
   05 1F 32 FFFFFFC0 00 35 08 05 43 0B FFFFFF84 00 44 01 0B 63
   6F 6E 74 65 6E 74 73 70 65 63 15 01 1B 08 05 46
   0B FFFFFF84 00 47 01 04 73 4F 70 74 15 01 2A 08 05 3E
   0B FFFFFF84 00 49 15 01 35 08 05 4B 0B FFFFFF84 00 4C 01 07
   73 65 71 52 65 73 74 14 02 35 4D 08 05 4E 4A FFFFFFC0
   00 35 01 01 70 08 05 50 0B FFFFFF84 00 51 01 0A 63 68
   6F 69 63 65 52 65 73 74 14 02 52 55 10 02 36 53
   09 02 54 3B 02 03 41 6C 74 08 05 4E 4F FFFFFFC0 00 35
   08 05 57 0B FFFFFF84 00 49 01 08 70 61 72 74 69 63 6C
   65 08 05 59 0B FFFFFF84 00 5A 01 04 61 74 6F 6D 15 01
   5B 10 02 36 5C 09 02 5D 5E 02 06 4C 65 74 74 65
   72 09 02 5F 3D 02 07 57 6F 72 64 45 78 70 
  InnerClass: 
   public Alt=class scala/util/regexp/Base$Alt of class scala/util/regexp/Base
   public abstract RegExp=class scala/util/regexp/Base$RegExp of class scala/util/regexp/Base
   public Letter=class scala/util/regexp/WordExp$Letter of class scala/util/regexp/WordExp
  minor version: 0
  major version: 49
  Constant pool:
Asciz	SourceFile;
Asciz	ContentModelParser.scala;
Asciz	atom;
Asciz	()Lscala/util/regexp/WordExp$Letter;;
Asciz	Code;
Asciz	scala/xml/dtd/ContentModelParser$;
class	scala/xml/dtd/ContentModelParser$
Asciz	MODULE$;
Asciz	Lscala/xml/dtd/ContentModelParser$;;
NameAndType	MODULE$:Lscala/xml/dtd/ContentModelParser$;
Field	scala/xml/dtd/ContentModelParser$.MODULE$:Lscala/xml/dtd/ContentModelParser$;
NameAndType	atom:()Lscala/util/regexp/WordExp$Letter;
Method	scala/xml/dtd/ContentModelParser$.atom:()Lscala/util/regexp/WordExp$Letter;
Asciz	particle;
Asciz	()Lscala/util/regexp/Base$RegExp;;
NameAndType	particle:()Lscala/util/regexp/Base$RegExp;
Method	scala/xml/dtd/ContentModelParser$.particle:()Lscala/util/regexp/Base$RegExp;
Asciz	choiceRest;
Asciz	(Lscala/util/regexp/Base$RegExp;)Lscala/util/regexp/Base$Alt;;
NameAndType	choiceRest:(Lscala/util/regexp/Base$RegExp;)Lscala/util/regexp/Base$Alt;
Method	scala/xml/dtd/ContentModelParser$.choiceRest:(Lscala/util/regexp/Base$RegExp;)Lscala/util/regexp/Base$Alt;
Asciz	seqRest;
Asciz	(Lscala/util/regexp/Base$RegExp;)Lscala/util/regexp/Base$RegExp;;
NameAndType	seqRest:(Lscala/util/regexp/Base$RegExp;)Lscala/util/regexp/Base$RegExp;
Method	scala/xml/dtd/ContentModelParser$.seqRest:(Lscala/util/regexp/Base$RegExp;)Lscala/util/regexp/Base$RegExp;
Asciz	regexp;
NameAndType	regexp:()Lscala/util/regexp/Base$RegExp;
Method	scala/xml/dtd/ContentModelParser$.regexp:()Lscala/util/regexp/Base$RegExp;
Asciz	sOpt;
Asciz	()V;
NameAndType	sOpt:()V
Method	scala/xml/dtd/ContentModelParser$.sOpt:()V
Asciz	contentspec;
Asciz	()Lscala/xml/dtd/ContentModel;;
NameAndType	contentspec:()Lscala/xml/dtd/ContentModel;
Method	scala/xml/dtd/ContentModelParser$.contentspec:()Lscala/xml/dtd/ContentModel;
Asciz	maybeSuffix;
NameAndType	maybeSuffix:(Lscala/util/regexp/Base$RegExp;)Lscala/util/regexp/Base$RegExp;
Method	scala/xml/dtd/ContentModelParser$.maybeSuffix:(Lscala/util/regexp/Base$RegExp;)Lscala/util/regexp/Base$RegExp;
Asciz	accept;
Asciz	(I)V;
NameAndType	accept:(I)V
Method	scala/xml/dtd/ContentModelParser$.accept:(I)V
Asciz	parse;
Asciz	(Ljava/lang/String;)Lscala/xml/dtd/ContentModel;;
NameAndType	parse:(Ljava/lang/String;)Lscala/xml/dtd/ContentModel;
Method	scala/xml/dtd/ContentModelParser$.parse:(Ljava/lang/String;)Lscala/xml/dtd/ContentModel;
Asciz	checkPubID;
Asciz	(Ljava/lang/String;)Z;
NameAndType	checkPubID:(Ljava/lang/String;)Z
Method	scala/xml/dtd/ContentModelParser$.checkPubID:(Ljava/lang/String;)Z
Asciz	checkSysID;
NameAndType	checkSysID:(Ljava/lang/String;)Z
Method	scala/xml/dtd/ContentModelParser$.checkSysID:(Ljava/lang/String;)Z
Asciz	isValidIANAEncoding;
Asciz	(Lscala/collection/Seq;)Z;
NameAndType	isValidIANAEncoding:(Lscala/collection/Seq;)Z
Method	scala/xml/dtd/ContentModelParser$.isValidIANAEncoding:(Lscala/collection/Seq;)Z
Asciz	isPubIDChar;
Asciz	(C)Z;
NameAndType	isPubIDChar:(C)Z
Method	scala/xml/dtd/ContentModelParser$.isPubIDChar:(C)Z
Asciz	isName;
NameAndType	isName:(Ljava/lang/String;)Z
Method	scala/xml/dtd/ContentModelParser$.isName:(Ljava/lang/String;)Z
Asciz	isNameStart;
NameAndType	isNameStart:(C)Z
Method	scala/xml/dtd/ContentModelParser$.isNameStart:(C)Z
Asciz	isNameChar;
NameAndType	isNameChar:(C)Z
Method	scala/xml/dtd/ContentModelParser$.isNameChar:(C)Z
Asciz	isAlphaDigit;
NameAndType	isAlphaDigit:(C)Z
Method	scala/xml/dtd/ContentModelParser$.isAlphaDigit:(C)Z
Asciz	isAlpha;
NameAndType	isAlpha:(C)Z
Method	scala/xml/dtd/ContentModelParser$.isAlpha:(C)Z
Asciz	isSpace;
NameAndType	isSpace:(Lscala/collection/Seq;)Z
Method	scala/xml/dtd/ContentModelParser$.isSpace:(Lscala/collection/Seq;)Z
NameAndType	isSpace:(C)Z
Method	scala/xml/dtd/ContentModelParser$.isSpace:(C)Z
Asciz	name;
Asciz	()I;
NameAndType	name:()I
Method	scala/xml/dtd/ContentModelParser$.name:()I
Asciz	readToken;
NameAndType	readToken:()I
Method	scala/xml/dtd/ContentModelParser$.readToken:()I
Asciz	accS;
Asciz	(Lscala/collection/Seq;)V;
NameAndType	accS:(Lscala/collection/Seq;)V
Method	scala/xml/dtd/ContentModelParser$.accS:(Lscala/collection/Seq;)V
Asciz	(Lscala/collection/Seq<Ljava/lang/Character;>;)V;
Asciz	Signature;
Asciz	acc;
Asciz	(C)V;
NameAndType	acc:(C)V
Method	scala/xml/dtd/ContentModelParser$.acc:(C)V
Asciz	next;
NameAndType	next:()V
Method	scala/xml/dtd/ContentModelParser$.next:()V
Asciz	isIdentChar;
Asciz	()Z;
NameAndType	isIdentChar:()Z
Method	scala/xml/dtd/ContentModelParser$.isIdentChar:()Z
Asciz	nextToken;
NameAndType	nextToken:()V
Method	scala/xml/dtd/ContentModelParser$.nextToken:()V
Asciz	initScanner;
Asciz	(Ljava/lang/String;)V;
NameAndType	initScanner:(Ljava/lang/String;)V
Method	scala/xml/dtd/ContentModelParser$.initScanner:(Ljava/lang/String;)V
Asciz	value_$eq;
NameAndType	value_$eq:(Ljava/lang/String;)V
Method	scala/xml/dtd/ContentModelParser$.value_$eq:(Ljava/lang/String;)V
Asciz	value;
Asciz	()Ljava/lang/String;;
NameAndType	value:()Ljava/lang/String;
Method	scala/xml/dtd/ContentModelParser$.value:()Ljava/lang/String;
Asciz	token_$eq;
NameAndType	token_$eq:(I)V
Method	scala/xml/dtd/ContentModelParser$.token_$eq:(I)V
Asciz	token;
NameAndType	token:()I
Method	scala/xml/dtd/ContentModelParser$.token:()I
Asciz	ENDCH;
Asciz	()C;
NameAndType	ENDCH:()C
Method	scala/xml/dtd/ContentModelParser$.ENDCH:()C
Asciz	token2string;
Asciz	(I)Ljava/lang/String;;
NameAndType	token2string:(I)Ljava/lang/String;
Method	scala/xml/dtd/ContentModelParser$.token2string:(I)Ljava/lang/String;
Asciz	S;
NameAndType	S:()I
Method	scala/xml/dtd/ContentModelParser$.S:()I
Asciz	END;
NameAndType	END:()I
Method	scala/xml/dtd/ContentModelParser$.END:()I
Asciz	CHOICE;
NameAndType	CHOICE:()I
Method	scala/xml/dtd/ContentModelParser$.CHOICE:()I
Asciz	OPT;
NameAndType	OPT:()I
Method	scala/xml/dtd/ContentModelParser$.OPT:()I
Asciz	PLUS;
NameAndType	PLUS:()I
Method	scala/xml/dtd/ContentModelParser$.PLUS:()I
Asciz	STAR;
NameAndType	STAR:()I
Method	scala/xml/dtd/ContentModelParser$.STAR:()I
Asciz	COMMA;
NameAndType	COMMA:()I
Method	scala/xml/dtd/ContentModelParser$.COMMA:()I
Asciz	RPAREN;
NameAndType	RPAREN:()I
Method	scala/xml/dtd/ContentModelParser$.RPAREN:()I
Asciz	LPAREN;
NameAndType	LPAREN:()I
Method	scala/xml/dtd/ContentModelParser$.LPAREN:()I
Asciz	NAME;
NameAndType	NAME:()I
Method	scala/xml/dtd/ContentModelParser$.NAME:()I
Asciz	TOKEN_PCDATA;
NameAndType	TOKEN_PCDATA:()I
Method	scala/xml/dtd/ContentModelParser$.TOKEN_PCDATA:()I
Asciz	ScalaSig;
Asciz	InnerClasses;
Asciz	scala/util/regexp/Base$Alt;
class	scala/util/regexp/Base$Alt
Asciz	scala/util/regexp/Base;
class	scala/util/regexp/Base
Asciz	Alt;
Asciz	scala/util/regexp/Base$RegExp;
class	scala/util/regexp/Base$RegExp
Asciz	RegExp;
Asciz	scala/util/regexp/WordExp$Letter;
class	scala/util/regexp/WordExp$Letter
Asciz	scala/util/regexp/WordExp;
class	scala/util/regexp/WordExp
Asciz	Letter;
Asciz	scala/xml/dtd/ContentModelParser;
class	scala/xml/dtd/ContentModelParser
Asciz	java/lang/Object;
class	java/lang/Object

{
public static final scala.util.regexp.WordExp$Letter atom();
  Signature: ()Lscala/util/regexp/WordExp$Letter;
  Code:
   Stack=1, Locals=0, Args_size=0
	getstatic	Field scala/xml/dtd/ContentModelParser$.MODULE$:Lscala/xml/dtd/ContentModelParser$;
	invokevirtual	Method scala/xml/dtd/ContentModelParser$.atom:()Lscala/util/regexp/WordExp$Letter;
	areturn
  Labels:

public static final scala.util.regexp.Base$RegExp particle();
  Signature: ()Lscala/util/regexp/Base$RegExp;
  Code:
   Stack=1, Locals=0, Args_size=0
	getstatic	Field scala/xml/dtd/ContentModelParser$.MODULE$:Lscala/xml/dtd/ContentModelParser$;
	invokevirtual	Method scala/xml/dtd/ContentModelParser$.particle:()Lscala/util/regexp/Base$RegExp;
	areturn
  Labels:

public static final scala.util.regexp.Base$Alt choiceRest(scala.util.regexp.Base$RegExp);
  Signature: (Lscala/util/regexp/Base$RegExp;)Lscala/util/regexp/Base$Alt;
  Code:
   Stack=2, Locals=1, Args_size=1
	getstatic	Field scala/xml/dtd/ContentModelParser$.MODULE$:Lscala/xml/dtd/ContentModelParser$;
	aload_0
	invokevirtual	Method scala/xml/dtd/ContentModelParser$.choiceRest:(Lscala/util/regexp/Base$RegExp;)Lscala/util/regexp/Base$Alt;
	areturn
  Labels:

public static final scala.util.regexp.Base$RegExp seqRest(scala.util.regexp.Base$RegExp);
  Signature: (Lscala/util/regexp/Base$RegExp;)Lscala/util/regexp/Base$RegExp;
  Code:
   Stack=2, Locals=1, Args_size=1
	getstatic	Field scala/xml/dtd/ContentModelParser$.MODULE$:Lscala/xml/dtd/ContentModelParser$;
	aload_0
	invokevirtual	Method scala/xml/dtd/ContentModelParser$.seqRest:(Lscala/util/regexp/Base$RegExp;)Lscala/util/regexp/Base$RegExp;
	areturn
  Labels:

public static final scala.util.regexp.Base$RegExp regexp();
  Signature: ()Lscala/util/regexp/Base$RegExp;
  Code:
   Stack=1, Locals=0, Args_size=0
	getstatic	Field scala/xml/dtd/ContentModelParser$.MODULE$:Lscala/xml/dtd/ContentModelParser$;
	invokevirtual	Method scala/xml/dtd/ContentModelParser$.regexp:()Lscala/util/regexp/Base$RegExp;
	areturn
  Labels:

public static final void sOpt();
  Signature: ()V
  Code:
   Stack=1, Locals=0, Args_size=0
	getstatic	Field scala/xml/dtd/ContentModelParser$.MODULE$:Lscala/xml/dtd/ContentModelParser$;
	invokevirtual	Method scala/xml/dtd/ContentModelParser$.sOpt:()V
	return
  Labels:

public static final scala.xml.dtd.ContentModel contentspec();
  Signature: ()Lscala/xml/dtd/ContentModel;
  Code:
   Stack=1, Locals=0, Args_size=0
	getstatic	Field scala/xml/dtd/ContentModelParser$.MODULE$:Lscala/xml/dtd/ContentModelParser$;
	invokevirtual	Method scala/xml/dtd/ContentModelParser$.contentspec:()Lscala/xml/dtd/ContentModel;
	areturn
  Labels:

public static final scala.util.regexp.Base$RegExp maybeSuffix(scala.util.regexp.Base$RegExp);
  Signature: (Lscala/util/regexp/Base$RegExp;)Lscala/util/regexp/Base$RegExp;
  Code:
   Stack=2, Locals=1, Args_size=1
	getstatic	Field scala/xml/dtd/ContentModelParser$.MODULE$:Lscala/xml/dtd/ContentModelParser$;
	aload_0
	invokevirtual	Method scala/xml/dtd/ContentModelParser$.maybeSuffix:(Lscala/util/regexp/Base$RegExp;)Lscala/util/regexp/Base$RegExp;
	areturn
  Labels:

public static final void accept(int);
  Signature: (I)V
  Code:
   Stack=2, Locals=1, Args_size=1
	getstatic	Field scala/xml/dtd/ContentModelParser$.MODULE$:Lscala/xml/dtd/ContentModelParser$;
	iload_0
	invokevirtual	Method scala/xml/dtd/ContentModelParser$.accept:(I)V
	return
  Labels:

public static final scala.xml.dtd.ContentModel parse(java.lang.String);
  Signature: (Ljava/lang/String;)Lscala/xml/dtd/ContentModel;
  Code:
   Stack=2, Locals=1, Args_size=1
	getstatic	Field scala/xml/dtd/ContentModelParser$.MODULE$:Lscala/xml/dtd/ContentModelParser$;
	aload_0
	invokevirtual	Method scala/xml/dtd/ContentModelParser$.parse:(Ljava/lang/String;)Lscala/xml/dtd/ContentModel;
	areturn
  Labels:

public static final boolean checkPubID(java.lang.String);
  Signature: (Ljava/lang/String;)Z
  Code:
   Stack=2, Locals=1, Args_size=1
	getstatic	Field scala/xml/dtd/ContentModelParser$.MODULE$:Lscala/xml/dtd/ContentModelParser$;
	aload_0
	invokevirtual	Method scala/xml/dtd/ContentModelParser$.checkPubID:(Ljava/lang/String;)Z
	ireturn
  Labels:

public static final boolean checkSysID(java.lang.String);
  Signature: (Ljava/lang/String;)Z
  Code:
   Stack=2, Locals=1, Args_size=1
	getstatic	Field scala/xml/dtd/ContentModelParser$.MODULE$:Lscala/xml/dtd/ContentModelParser$;
	aload_0
	invokevirtual	Method scala/xml/dtd/ContentModelParser$.checkSysID:(Ljava/lang/String;)Z
	ireturn
  Labels:

public static final boolean isValidIANAEncoding(scala.collection.Seq);
  Signature: (Lscala/collection/Seq;)Z
  Code:
   Stack=2, Locals=1, Args_size=1
	getstatic	Field scala/xml/dtd/ContentModelParser$.MODULE$:Lscala/xml/dtd/ContentModelParser$;
	aload_0
	invokevirtual	Method scala/xml/dtd/ContentModelParser$.isValidIANAEncoding:(Lscala/collection/Seq;)Z
	ireturn
  Labels:

public static final boolean isPubIDChar(char);
  Signature: (C)Z
  Code:
   Stack=2, Locals=1, Args_size=1
	getstatic	Field scala/xml/dtd/ContentModelParser$.MODULE$:Lscala/xml/dtd/ContentModelParser$;
	iload_0
	invokevirtual	Method scala/xml/dtd/ContentModelParser$.isPubIDChar:(C)Z
	ireturn
  Labels:

public static final boolean isName(java.lang.String);
  Signature: (Ljava/lang/String;)Z
  Code:
   Stack=2, Locals=1, Args_size=1
	getstatic	Field scala/xml/dtd/ContentModelParser$.MODULE$:Lscala/xml/dtd/ContentModelParser$;
	aload_0
	invokevirtual	Method scala/xml/dtd/ContentModelParser$.isName:(Ljava/lang/String;)Z
	ireturn
  Labels:

public static final boolean isNameStart(char);
  Signature: (C)Z
  Code:
   Stack=2, Locals=1, Args_size=1
	getstatic	Field scala/xml/dtd/ContentModelParser$.MODULE$:Lscala/xml/dtd/ContentModelParser$;
	iload_0
	invokevirtual	Method scala/xml/dtd/ContentModelParser$.isNameStart:(C)Z
	ireturn
  Labels:

public static final boolean isNameChar(char);
  Signature: (C)Z
  Code:
   Stack=2, Locals=1, Args_size=1
	getstatic	Field scala/xml/dtd/ContentModelParser$.MODULE$:Lscala/xml/dtd/ContentModelParser$;
	iload_0
	invokevirtual	Method scala/xml/dtd/ContentModelParser$.isNameChar:(C)Z
	ireturn
  Labels:

public static final boolean isAlphaDigit(char);
  Signature: (C)Z
  Code:
   Stack=2, Locals=1, Args_size=1
	getstatic	Field scala/xml/dtd/ContentModelParser$.MODULE$:Lscala/xml/dtd/ContentModelParser$;
	iload_0
	invokevirtual	Method scala/xml/dtd/ContentModelParser$.isAlphaDigit:(C)Z
	ireturn
  Labels:

public static final boolean isAlpha(char);
  Signature: (C)Z
  Code:
   Stack=2, Locals=1, Args_size=1
	getstatic	Field scala/xml/dtd/ContentModelParser$.MODULE$:Lscala/xml/dtd/ContentModelParser$;
	iload_0
	invokevirtual	Method scala/xml/dtd/ContentModelParser$.isAlpha:(C)Z
	ireturn
  Labels:

public static final boolean isSpace(scala.collection.Seq);
  Signature: (Lscala/collection/Seq;)Z
  Code:
   Stack=2, Locals=1, Args_size=1
	getstatic	Field scala/xml/dtd/ContentModelParser$.MODULE$:Lscala/xml/dtd/ContentModelParser$;
	aload_0
	invokevirtual	Method scala/xml/dtd/ContentModelParser$.isSpace:(Lscala/collection/Seq;)Z
	ireturn
  Labels:

public static final boolean isSpace(char);
  Signature: (C)Z
  Code:
   Stack=2, Locals=1, Args_size=1
	getstatic	Field scala/xml/dtd/ContentModelParser$.MODULE$:Lscala/xml/dtd/ContentModelParser$;
	iload_0
	invokevirtual	Method scala/xml/dtd/ContentModelParser$.isSpace:(C)Z
	ireturn
  Labels:

public static final int name();
  Signature: ()I
  Code:
   Stack=1, Locals=0, Args_size=0
	getstatic	Field scala/xml/dtd/ContentModelParser$.MODULE$:Lscala/xml/dtd/ContentModelParser$;
	invokevirtual	Method scala/xml/dtd/ContentModelParser$.name:()I
	ireturn
  Labels:

public static final int readToken();
  Signature: ()I
  Code:
   Stack=1, Locals=0, Args_size=0
	getstatic	Field scala/xml/dtd/ContentModelParser$.MODULE$:Lscala/xml/dtd/ContentModelParser$;
	invokevirtual	Method scala/xml/dtd/ContentModelParser$.readToken:()I
	ireturn
  Labels:

public static final void accS(scala.collection.Seq);
  Signature: (Lscala/collection/Seq;)V
  Code:
   Stack=2, Locals=1, Args_size=1
	getstatic	Field scala/xml/dtd/ContentModelParser$.MODULE$:Lscala/xml/dtd/ContentModelParser$;
	aload_0
	invokevirtual	Method scala/xml/dtd/ContentModelParser$.accS:(Lscala/collection/Seq;)V
	return
  Labels:
  Signature: length = 0x2
   00 5E 

public static final void acc(char);
  Signature: (C)V
  Code:
   Stack=2, Locals=1, Args_size=1
	getstatic	Field scala/xml/dtd/ContentModelParser$.MODULE$:Lscala/xml/dtd/ContentModelParser$;
	iload_0
	invokevirtual	Method scala/xml/dtd/ContentModelParser$.acc:(C)V
	return
  Labels:

public static final void next();
  Signature: ()V
  Code:
   Stack=1, Locals=0, Args_size=0
	getstatic	Field scala/xml/dtd/ContentModelParser$.MODULE$:Lscala/xml/dtd/ContentModelParser$;
	invokevirtual	Method scala/xml/dtd/ContentModelParser$.next:()V
	return
  Labels:

public static final boolean isIdentChar();
  Signature: ()Z
  Code:
   Stack=1, Locals=0, Args_size=0
	getstatic	Field scala/xml/dtd/ContentModelParser$.MODULE$:Lscala/xml/dtd/ContentModelParser$;
	invokevirtual	Method scala/xml/dtd/ContentModelParser$.isIdentChar:()Z
	ireturn
  Labels:

public static final void nextToken();
  Signature: ()V
  Code:
   Stack=1, Locals=0, Args_size=0
	getstatic	Field scala/xml/dtd/ContentModelParser$.MODULE$:Lscala/xml/dtd/ContentModelParser$;
	invokevirtual	Method scala/xml/dtd/ContentModelParser$.nextToken:()V
	return
  Labels:

public static final void initScanner(java.lang.String);
  Signature: (Ljava/lang/String;)V
  Code:
   Stack=2, Locals=1, Args_size=1
	getstatic	Field scala/xml/dtd/ContentModelParser$.MODULE$:Lscala/xml/dtd/ContentModelParser$;
	aload_0
	invokevirtual	Method scala/xml/dtd/ContentModelParser$.initScanner:(Ljava/lang/String;)V
	return
  Labels:

public static final void value_$eq(java.lang.String);
  Signature: (Ljava/lang/String;)V
  Code:
   Stack=2, Locals=1, Args_size=1
	getstatic	Field scala/xml/dtd/ContentModelParser$.MODULE$:Lscala/xml/dtd/ContentModelParser$;
	aload_0
	invokevirtual	Method scala/xml/dtd/ContentModelParser$.value_$eq:(Ljava/lang/String;)V
	return
  Labels:

public static final java.lang.String value();
  Signature: ()Ljava/lang/String;
  Code:
   Stack=1, Locals=0, Args_size=0
	getstatic	Field scala/xml/dtd/ContentModelParser$.MODULE$:Lscala/xml/dtd/ContentModelParser$;
	invokevirtual	Method scala/xml/dtd/ContentModelParser$.value:()Ljava/lang/String;
	areturn
  Labels:

public static final void token_$eq(int);
  Signature: (I)V
  Code:
   Stack=2, Locals=1, Args_size=1
	getstatic	Field scala/xml/dtd/ContentModelParser$.MODULE$:Lscala/xml/dtd/ContentModelParser$;
	iload_0
	invokevirtual	Method scala/xml/dtd/ContentModelParser$.token_$eq:(I)V
	return
  Labels:

public static final int token();
  Signature: ()I
  Code:
   Stack=1, Locals=0, Args_size=0
	getstatic	Field scala/xml/dtd/ContentModelParser$.MODULE$:Lscala/xml/dtd/ContentModelParser$;
	invokevirtual	Method scala/xml/dtd/ContentModelParser$.token:()I
	ireturn
  Labels:

public static final char ENDCH();
  Signature: ()C
  Code:
   Stack=1, Locals=0, Args_size=0
	getstatic	Field scala/xml/dtd/ContentModelParser$.MODULE$:Lscala/xml/dtd/ContentModelParser$;
	invokevirtual	Method scala/xml/dtd/ContentModelParser$.ENDCH:()C
	ireturn
  Labels:

public static final java.lang.String token2string(int);
  Signature: (I)Ljava/lang/String;
  Code:
   Stack=2, Locals=1, Args_size=1
	getstatic	Field scala/xml/dtd/ContentModelParser$.MODULE$:Lscala/xml/dtd/ContentModelParser$;
	iload_0
	invokevirtual	Method scala/xml/dtd/ContentModelParser$.token2string:(I)Ljava/lang/String;
	areturn
  Labels:

public static final int S();
  Signature: ()I
  Code:
   Stack=1, Locals=0, Args_size=0
	getstatic	Field scala/xml/dtd/ContentModelParser$.MODULE$:Lscala/xml/dtd/ContentModelParser$;
	invokevirtual	Method scala/xml/dtd/ContentModelParser$.S:()I
	ireturn
  Labels:

public static final int END();
  Signature: ()I
  Code:
   Stack=1, Locals=0, Args_size=0
	getstatic	Field scala/xml/dtd/ContentModelParser$.MODULE$:Lscala/xml/dtd/ContentModelParser$;
	invokevirtual	Method scala/xml/dtd/ContentModelParser$.END:()I
	ireturn
  Labels:

public static final int CHOICE();
  Signature: ()I
  Code:
   Stack=1, Locals=0, Args_size=0
	getstatic	Field scala/xml/dtd/ContentModelParser$.MODULE$:Lscala/xml/dtd/ContentModelParser$;
	invokevirtual	Method scala/xml/dtd/ContentModelParser$.CHOICE:()I
	ireturn
  Labels:

public static final int OPT();
  Signature: ()I
  Code:
   Stack=1, Locals=0, Args_size=0
	getstatic	Field scala/xml/dtd/ContentModelParser$.MODULE$:Lscala/xml/dtd/ContentModelParser$;
	invokevirtual	Method scala/xml/dtd/ContentModelParser$.OPT:()I
	ireturn
  Labels:

public static final int PLUS();
  Signature: ()I
  Code:
   Stack=1, Locals=0, Args_size=0
	getstatic	Field scala/xml/dtd/ContentModelParser$.MODULE$:Lscala/xml/dtd/ContentModelParser$;
	invokevirtual	Method scala/xml/dtd/ContentModelParser$.PLUS:()I
	ireturn
  Labels:

public static final int STAR();
  Signature: ()I
  Code:
   Stack=1, Locals=0, Args_size=0
	getstatic	Field scala/xml/dtd/ContentModelParser$.MODULE$:Lscala/xml/dtd/ContentModelParser$;
	invokevirtual	Method scala/xml/dtd/ContentModelParser$.STAR:()I
	ireturn
  Labels:

public static final int COMMA();
  Signature: ()I
  Code:
   Stack=1, Locals=0, Args_size=0
	getstatic	Field scala/xml/dtd/ContentModelParser$.MODULE$:Lscala/xml/dtd/ContentModelParser$;
	invokevirtual	Method scala/xml/dtd/ContentModelParser$.COMMA:()I
	ireturn
  Labels:

public static final int RPAREN();
  Signature: ()I
  Code:
   Stack=1, Locals=0, Args_size=0
	getstatic	Field scala/xml/dtd/ContentModelParser$.MODULE$:Lscala/xml/dtd/ContentModelParser$;
	invokevirtual	Method scala/xml/dtd/ContentModelParser$.RPAREN:()I
	ireturn
  Labels:

public static final int LPAREN();
  Signature: ()I
  Code:
   Stack=1, Locals=0, Args_size=0
	getstatic	Field scala/xml/dtd/ContentModelParser$.MODULE$:Lscala/xml/dtd/ContentModelParser$;
	invokevirtual	Method scala/xml/dtd/ContentModelParser$.LPAREN:()I
	ireturn
  Labels:

public static final int NAME();
  Signature: ()I
  Code:
   Stack=1, Locals=0, Args_size=0
	getstatic	Field scala/xml/dtd/ContentModelParser$.MODULE$:Lscala/xml/dtd/ContentModelParser$;
	invokevirtual	Method scala/xml/dtd/ContentModelParser$.NAME:()I
	ireturn
  Labels:

public static final int TOKEN_PCDATA();
  Signature: ()I
  Code:
   Stack=1, Locals=0, Args_size=0
	getstatic	Field scala/xml/dtd/ContentModelParser$.MODULE$:Lscala/xml/dtd/ContentModelParser$;
	invokevirtual	Method scala/xml/dtd/ContentModelParser$.TOKEN_PCDATA:()I
	ireturn
  Labels:

}

