Compiled from "ContentModel.scala"
public final class scala.xml.dtd.ContentModel$Translator$ extends scala.util.automata.WordBerrySethi implements scala.ScalaObject
  SourceFile: "ContentModel.scala"
  Scala: length = 0x
   
  minor version: 0
  major version: 49
  Constant pool:
Asciz	SourceFile;
Asciz	ContentModel.scala;
Asciz	Scala;
Asciz	MODULE$;
Asciz	Lscala/xml/dtd/ContentModel$Translator$;;
Asciz	<clinit>;
Asciz	()V;
Asciz	Code;
Asciz	scala/xml/dtd/ContentModel$Translator$;
class	scala/xml/dtd/ContentModel$Translator$
Asciz	<init>;
NameAndType	"<init>":()V
Method	scala/xml/dtd/ContentModel$Translator$."<init>":()V
Asciz	lang;
Asciz	Lscala/xml/dtd/ContentModel$;;
Asciz	LineNumberTable;
Asciz	scala/util/automata/WordBerrySethi;
class	scala/util/automata/WordBerrySethi
Method	scala/util/automata/WordBerrySethi."<init>":()V
NameAndType	MODULE$:Lscala/xml/dtd/ContentModel$Translator$;
Field	scala/xml/dtd/ContentModel$Translator$.MODULE$:Lscala/xml/dtd/ContentModel$Translator$;
Asciz	scala/xml/dtd/ContentModel$;
class	scala/xml/dtd/ContentModel$
NameAndType	MODULE$:Lscala/xml/dtd/ContentModel$;
Field	scala/xml/dtd/ContentModel$.MODULE$:Lscala/xml/dtd/ContentModel$;
NameAndType	lang:Lscala/xml/dtd/ContentModel$;
Field	scala/xml/dtd/ContentModel$Translator$.lang:Lscala/xml/dtd/ContentModel$;
Asciz	()Lscala/util/regexp/WordExp;;
Asciz	()Lscala/xml/dtd/ContentModel$;;
NameAndType	lang:()Lscala/xml/dtd/ContentModel$;
Method	scala/xml/dtd/ContentModel$Translator$.lang:()Lscala/xml/dtd/ContentModel$;
Asciz	()Lscala/util/regexp/Base;;
Asciz	scala/ScalaObject;
class	scala/ScalaObject

{
public static final scala.xml.dtd.ContentModel$Translator$ MODULE$;
  Signature: Lscala/xml/dtd/ContentModel$Translator$;

private final scala.xml.dtd.ContentModel$ lang;
  Signature: Lscala/xml/dtd/ContentModel$;

public static {};
  Signature: ()V
  Code:
   Stack=1, Locals=0, Args_size=0
	new	class scala/xml/dtd/ContentModel$Translator$
	invokespecial	Method "<init>":()V
	return
  Labels:

public scala.xml.dtd.ContentModel$Translator$();
  Signature: ()V
  Code:
   Stack=2, Locals=1, Args_size=1
	aload_0
	invokespecial	Method scala/util/automata/WordBerrySethi."<init>":()V
	aload_0
	putstatic	Field MODULE$:Lscala/xml/dtd/ContentModel$Translator$;
	aload_0
	getstatic	Field scala/xml/dtd/ContentModel$.MODULE$:Lscala/xml/dtd/ContentModel$;
	putfield	Field lang:Lscala/xml/dtd/ContentModel$;
	return
  Labels:

public scala.util.regexp.WordExp lang();
  Signature: ()Lscala/util/regexp/WordExp;
  Code:
   Stack=1, Locals=1, Args_size=1
	aload_0
	invokevirtual	Method lang:()Lscala/xml/dtd/ContentModel$;
	areturn
  Labels:

public scala.util.regexp.Base lang();
  Signature: ()Lscala/util/regexp/Base;
  Code:
   Stack=1, Locals=1, Args_size=1
	aload_0
	invokevirtual	Method lang:()Lscala/xml/dtd/ContentModel$;
	areturn
  Labels:

public scala.xml.dtd.ContentModel$ lang();
  Signature: ()Lscala/xml/dtd/ContentModel$;
  Code:
   Stack=1, Locals=1, Args_size=1
	aload_0
	getfield	Field lang:Lscala/xml/dtd/ContentModel$;
	areturn
  Labels:

}

