Compiled from "ContentModel.scala"
public final class scala.xml.dtd.ContentModel$ extends scala.util.regexp.WordExp implements scala.ScalaObject
  SourceFile: "ContentModel.scala"
  Scala: length = 0x
   
  InnerClass: 
   public #138= #137 of #301; //Alt=class scala/util/regexp/Base$Alt of class scala/util/regexp/Base
   public #77= #76 of #301; //Sequ=class scala/util/regexp/Base$Sequ of class scala/util/regexp/Base
   public #302= #70 of #301; //Star=class scala/util/regexp/Base$Star of class scala/util/regexp/Base
   public abstract #303= #62 of #301; //RegExp=class scala/util/regexp/Base$RegExp of class scala/util/regexp/Base
   public abstract #306= #305 of #16; //Label=class scala/util/regexp/WordExp$Label of class scala/util/regexp/WordExp
   public final #309= #130 of #308; //$anon$1=class scala/Predef$$anon$1 of class scala/Predef
   public #310= #23 of #16; //Letter=class scala/util/regexp/WordExp$Letter of class scala/util/regexp/WordExp
   public #311= #29 of #216; //ElemName=class scala/xml/dtd/ContentModel$ElemName of class scala/xml/dtd/ContentModel
   public final #312= #291 of #216; //$anonfun$isMixed$1=class scala/xml/dtd/ContentModel$$anonfun$isMixed$1 of class scala/xml/dtd/ContentModel
   public final #315= #314 of #216; //$anonfun$toString$1=class scala/xml/dtd/ContentModel$$anonfun$toString$1 of class scala/xml/dtd/ContentModel
   public final #316= #144 of #216; //$anonfun$traverse$1$2=class scala/xml/dtd/ContentModel$$anonfun$traverse$1$2 of class scala/xml/dtd/ContentModel
   public final #317= #109 of #216; //$anonfun$traverse$1$1=class scala/xml/dtd/ContentModel$$anonfun$traverse$1$1 of class scala/xml/dtd/ContentModel
   public final #320= #319 of #216; //$anonfun$buildString$1=class scala/xml/dtd/ContentModel$$anonfun$buildString$1 of class scala/xml/dtd/ContentModel
   public final #321= #251 of #216; //$anonfun$buildString$2=class scala/xml/dtd/ContentModel$$anonfun$buildString$2 of class scala/xml/dtd/ContentModel
   public #324= #117 of #323; //GenericCanBuildFrom=class scala/collection/generic/TraversableFactory$GenericCanBuildFrom of class scala/collection/generic/TraversableFactory
  minor version: 0
  major version: 49
  Constant pool:
const #1 = Asciz	SourceFile;
const #2 = Asciz	ContentModel.scala;
const #3 = Asciz	Scala;
const #4 = Asciz	MODULE$;
const #5 = Asciz	Lscala/xml/dtd/ContentModel$;;
const #6 = Asciz	<clinit>;
const #7 = Asciz	()V;
const #8 = Asciz	Code;
const #9 = Asciz	scala/xml/dtd/ContentModel$;
const #10 = class	#9;	//  scala/xml/dtd/ContentModel$
const #11 = Asciz	<init>;
const #12 = NameAndType	#11:#7;//  "<init>":()V
const #13 = Method	#10.#12;	//  scala/xml/dtd/ContentModel$."<init>":()V
const #14 = Asciz	LineNumberTable;
const #15 = Asciz	scala/util/regexp/WordExp;
const #16 = class	#15;	//  scala/util/regexp/WordExp
const #17 = Method	#16.#12;	//  scala/util/regexp/WordExp."<init>":()V
const #18 = NameAndType	#4:#5;//  MODULE$:Lscala/xml/dtd/ContentModel$;
const #19 = Field	#10.#18;	//  scala/xml/dtd/ContentModel$.MODULE$:Lscala/xml/dtd/ContentModel$;
const #20 = Asciz	traverse$1;
const #21 = Asciz	(Lscala/util/regexp/Base$RegExp;)Lscala/collection/immutable/Set;;
const #22 = Asciz	scala/util/regexp/WordExp$Letter;
const #23 = class	#22;	//  scala/util/regexp/WordExp$Letter
const #24 = Asciz	a;
const #25 = Asciz	()Lscala/util/regexp/WordExp$Label;;
const #26 = NameAndType	#24:#25;//  a:()Lscala/util/regexp/WordExp$Label;
const #27 = Method	#23.#26;	//  scala/util/regexp/WordExp$Letter.a:()Lscala/util/regexp/WordExp$Label;
const #28 = Asciz	scala/xml/dtd/ContentModel$ElemName;
const #29 = class	#28;	//  scala/xml/dtd/ContentModel$ElemName
const #30 = Asciz	name;
const #31 = Asciz	()Ljava/lang/String;;
const #32 = NameAndType	#30:#31;//  name:()Ljava/lang/String;
const #33 = Method	#29.#32;	//  scala/xml/dtd/ContentModel$ElemName.name:()Ljava/lang/String;
const #34 = Asciz	scala/Predef$;
const #35 = class	#34;	//  scala/Predef$
const #36 = Asciz	Lscala/Predef$;;
const #37 = NameAndType	#4:#36;//  MODULE$:Lscala/Predef$;
const #38 = Field	#35.#37;	//  scala/Predef$.MODULE$:Lscala/Predef$;
const #39 = Asciz	Set;
const #40 = Asciz	()Lscala/collection/immutable/Set$;;
const #41 = NameAndType	#39:#40;//  Set:()Lscala/collection/immutable/Set$;
const #42 = Method	#35.#41;	//  scala/Predef$.Set:()Lscala/collection/immutable/Set$;
const #43 = Asciz	java/lang/String;
const #44 = class	#43;	//  java/lang/String
const #45 = Asciz	[Ljava/lang/Object;;
const #46 = class	#45;	//  "[Ljava/lang/Object;"
const #47 = Asciz	wrapRefArray;
const #48 = Asciz	([Ljava/lang/Object;)Lscala/collection/mutable/WrappedArray;;
const #49 = NameAndType	#47:#48;//  wrapRefArray:([Ljava/lang/Object;)Lscala/collection/mutable/WrappedArray;
const #50 = Method	#35.#49;	//  scala/Predef$.wrapRefArray:([Ljava/lang/Object;)Lscala/collection/mutable/WrappedArray;
const #51 = Asciz	scala/collection/immutable/Set$;
const #52 = class	#51;	//  scala/collection/immutable/Set$
const #53 = Asciz	apply;
const #54 = Asciz	(Lscala/collection/Seq;)Lscala/collection/Traversable;;
const #55 = NameAndType	#53:#54;//  apply:(Lscala/collection/Seq;)Lscala/collection/Traversable;
const #56 = Method	#52.#55;	//  scala/collection/immutable/Set$.apply:(Lscala/collection/Seq;)Lscala/collection/Traversable;
const #57 = Asciz	scala/collection/immutable/Set;
const #58 = class	#57;	//  scala/collection/immutable/Set
const #59 = Asciz	scala/MatchError;
const #60 = class	#59;	//  scala/MatchError
const #61 = Asciz	scala/util/regexp/Base$RegExp;
const #62 = class	#61;	//  scala/util/regexp/Base$RegExp
const #63 = Asciz	toString;
const #64 = NameAndType	#63:#31;//  toString:()Ljava/lang/String;
const #65 = Method	#62.#64;	//  scala/util/regexp/Base$RegExp.toString:()Ljava/lang/String;
const #66 = Asciz	(Ljava/lang/String;)V;
const #67 = NameAndType	#11:#66;//  "<init>":(Ljava/lang/String;)V
const #68 = Method	#60.#67;	//  scala/MatchError."<init>":(Ljava/lang/String;)V
const #69 = Asciz	scala/util/regexp/Base$Star;
const #70 = class	#69;	//  scala/util/regexp/Base$Star
const #71 = Asciz	r;
const #72 = Asciz	()Lscala/util/regexp/Base$RegExp;;
const #73 = NameAndType	#71:#72;//  r:()Lscala/util/regexp/Base$RegExp;
const #74 = Method	#70.#73;	//  scala/util/regexp/Base$Star.r:()Lscala/util/regexp/Base$RegExp;
const #75 = Asciz	scala/util/regexp/Base$Sequ;
const #76 = class	#75;	//  scala/util/regexp/Base$Sequ
const #77 = Asciz	Sequ;
const #78 = Asciz	()Lscala/util/regexp/Base$Sequ$;;
const #79 = NameAndType	#77:#78;//  Sequ:()Lscala/util/regexp/Base$Sequ$;
const #80 = Method	#10.#79;	//  scala/xml/dtd/ContentModel$.Sequ:()Lscala/util/regexp/Base$Sequ$;
const #81 = Asciz	scala/Some;
const #82 = class	#81;	//  scala/Some
const #83 = Asciz	rs;
const #84 = Asciz	()Lscala/collection/Seq;;
const #85 = NameAndType	#83:#84;//  rs:()Lscala/collection/Seq;
const #86 = Method	#76.#85;	//  scala/util/regexp/Base$Sequ.rs:()Lscala/collection/Seq;
const #87 = Asciz	(Ljava/lang/Object;)V;
const #88 = NameAndType	#11:#87;//  "<init>":(Ljava/lang/Object;)V
const #89 = Method	#82.#88;	//  scala/Some."<init>":(Ljava/lang/Object;)V
const #90 = Asciz	x;
const #91 = Asciz	Ljava/lang/Object;;
const #92 = NameAndType	#90:#91;//  x:Ljava/lang/Object;
const #93 = Field	#82.#92;	//  scala/Some.x:Ljava/lang/Object;
const #94 = Asciz	scala/collection/Seq;
const #95 = class	#94;	//  scala/collection/Seq
const #96 = Asciz	java/lang/Object;
const #97 = class	#96;	//  java/lang/Object
const #98 = Asciz	equals;
const #99 = Asciz	(Ljava/lang/Object;)Z;
const #100 = NameAndType	#98:#99;//  equals:(Ljava/lang/Object;)Z
const #101 = Method	#97.#100;	//  java/lang/Object.equals:(Ljava/lang/Object;)Z
const #102 = Asciz	scala/collection/SeqLike;
const #103 = class	#102;	//  scala/collection/SeqLike
const #104 = Asciz	lengthCompare;
const #105 = Asciz	(I)I;
const #106 = NameAndType	#104:#105;//  lengthCompare:(I)I
const #107 = InterfaceMethod	#103.#106;	//  scala/collection/SeqLike.lengthCompare:(I)I
const #108 = Asciz	scala/xml/dtd/ContentModel$$anonfun$traverse$1$1;
const #109 = class	#108;	//  scala/xml/dtd/ContentModel$$anonfun$traverse$1$1
const #110 = Method	#109.#12;	//  scala/xml/dtd/ContentModel$$anonfun$traverse$1$1."<init>":()V
const #111 = Asciz	scala/collection/Seq$;
const #112 = class	#111;	//  scala/collection/Seq$
const #113 = Asciz	Lscala/collection/Seq$;;
const #114 = NameAndType	#4:#113;//  MODULE$:Lscala/collection/Seq$;
const #115 = Field	#112.#114;	//  scala/collection/Seq$.MODULE$:Lscala/collection/Seq$;
const #116 = Asciz	scala/collection/generic/TraversableFactory$GenericCanBuildFrom;
const #117 = class	#116;	//  scala/collection/generic/TraversableFactory$GenericCanBuildFrom
const #118 = Asciz	(Lscala/collection/generic/TraversableFactory;)V;
const #119 = NameAndType	#11:#118;//  "<init>":(Lscala/collection/generic/TraversableFactory;)V
const #120 = Method	#117.#119;	//  scala/collection/generic/TraversableFactory$GenericCanBuildFrom."<init>":(Lscala/collection/generic/TraversableFactory;)V
const #121 = Asciz	scala/collection/TraversableLike;
const #122 = class	#121;	//  scala/collection/TraversableLike
const #123 = Asciz	map;
const #124 = Asciz	(Lscala/Function1;Lscala/collection/generic/CanBuildFrom;)Ljava/lang/Object;;
const #125 = NameAndType	#123:#124;//  map:(Lscala/Function1;Lscala/collection/generic/CanBuildFrom;)Ljava/lang/Object;
const #126 = InterfaceMethod	#122.#125;	//  scala/collection/TraversableLike.map:(Lscala/Function1;Lscala/collection/generic/CanBuildFrom;)Ljava/lang/Object;
const #127 = Asciz	scala/collection/generic/GenericTraversableTemplate;
const #128 = class	#127;	//  scala/collection/generic/GenericTraversableTemplate
const #129 = Asciz	scala/Predef$$anon$1;
const #130 = class	#129;	//  scala/Predef$$anon$1
const #131 = Method	#130.#12;	//  scala/Predef$$anon$1."<init>":()V
const #132 = Asciz	flatten;
const #133 = Asciz	(Lscala/Function1;)Lscala/collection/Traversable;;
const #134 = NameAndType	#132:#133;//  flatten:(Lscala/Function1;)Lscala/collection/Traversable;
const #135 = InterfaceMethod	#128.#134;	//  scala/collection/generic/GenericTraversableTemplate.flatten:(Lscala/Function1;)Lscala/collection/Traversable;
const #136 = Asciz	scala/util/regexp/Base$Alt;
const #137 = class	#136;	//  scala/util/regexp/Base$Alt
const #138 = Asciz	Alt;
const #139 = Asciz	()Lscala/util/regexp/Base$Alt$;;
const #140 = NameAndType	#138:#139;//  Alt:()Lscala/util/regexp/Base$Alt$;
const #141 = Method	#10.#140;	//  scala/xml/dtd/ContentModel$.Alt:()Lscala/util/regexp/Base$Alt$;
const #142 = Method	#137.#85;	//  scala/util/regexp/Base$Alt.rs:()Lscala/collection/Seq;
const #143 = Asciz	scala/xml/dtd/ContentModel$$anonfun$traverse$1$2;
const #144 = class	#143;	//  scala/xml/dtd/ContentModel$$anonfun$traverse$1$2
const #145 = Method	#144.#12;	//  scala/xml/dtd/ContentModel$$anonfun$traverse$1$2."<init>":()V
const #146 = Asciz	this;
const #147 = Asciz	Lscala/util/regexp/Base$RegExp;;
const #148 = Asciz	temp12;
const #149 = Asciz	Lscala/util/regexp/WordExp$Letter;;
const #150 = Asciz	temp13;
const #151 = Asciz	Lscala/xml/dtd/ContentModel$ElemName;;
const #152 = Asciz	temp14;
const #153 = Asciz	Ljava/lang/String;;
const #154 = Asciz	temp15;
const #155 = Asciz	Lscala/util/regexp/Base$Star;;
const #156 = Asciz	temp16;
const #157 = Asciz	temp17;
const #158 = Asciz	Lscala/util/regexp/Base$Sequ;;
const #159 = Asciz	temp18;
const #160 = Asciz	Lscala/Some;;
const #161 = Asciz	temp19;
const #162 = Asciz	Lscala/collection/Seq;;
const #163 = Asciz	temp21;
const #164 = Asciz	Lscala/util/regexp/Base$Alt;;
const #165 = Asciz	temp22;
const #166 = Asciz	temp23;
const #167 = Asciz	LocalVariableTable;
const #168 = Asciz	buildString;
const #169 = Asciz	(Lscala/util/regexp/Base$RegExp;Lscala/collection/mutable/StringBuilder;)Lscala/collection/mutable/StringBuilder;;
const #170 = Asciz	Eps;
const #171 = Asciz	()Lscala/util/regexp/Base$Eps$;;
const #172 = NameAndType	#170:#171;//  Eps:()Lscala/util/regexp/Base$Eps$;
const #173 = Method	#10.#172;	//  scala/xml/dtd/ContentModel$.Eps:()Lscala/util/regexp/Base$Eps$;
const #174 = int	40;
const #175 = Asciz	scala/collection/mutable/StringBuilder;
const #176 = class	#175;	//  scala/collection/mutable/StringBuilder
const #177 = Asciz	append;
const #178 = Asciz	(C)Lscala/collection/mutable/StringBuilder;;
const #179 = NameAndType	#177:#178;//  append:(C)Lscala/collection/mutable/StringBuilder;
const #180 = Method	#176.#179;	//  scala/collection/mutable/StringBuilder.append:(C)Lscala/collection/mutable/StringBuilder;
const #181 = int	44;
const #182 = Asciz	(Lscala/collection/Seq;Lscala/collection/mutable/StringBuilder;C)V;
const #183 = NameAndType	#168:#182;//  buildString:(Lscala/collection/Seq;Lscala/collection/mutable/StringBuilder;C)V
const #184 = Method	#10.#183;	//  scala/xml/dtd/ContentModel$.buildString:(Lscala/collection/Seq;Lscala/collection/mutable/StringBuilder;C)V
const #185 = int	41;
const #186 = int	124;
const #187 = NameAndType	#168:#169;//  buildString:(Lscala/util/regexp/Base$RegExp;Lscala/collection/mutable/StringBuilder;)Lscala/collection/mutable/StringBuilder;
const #188 = Method	#10.#187;	//  scala/xml/dtd/ContentModel$.buildString:(Lscala/util/regexp/Base$RegExp;Lscala/collection/mutable/StringBuilder;)Lscala/collection/mutable/StringBuilder;
const #189 = Asciz	)*;
const #190 = String	#189;	//  )*
const #191 = Asciz	(Ljava/lang/String;)Lscala/collection/mutable/StringBuilder;;
const #192 = NameAndType	#177:#191;//  append:(Ljava/lang/String;)Lscala/collection/mutable/StringBuilder;
const #193 = Method	#176.#192;	//  scala/collection/mutable/StringBuilder.append:(Ljava/lang/String;)Lscala/collection/mutable/StringBuilder;
const #194 = Asciz	sb;
const #195 = Asciz	Lscala/collection/mutable/StringBuilder;;
const #196 = Asciz	temp34;
const #197 = Asciz	temp35;
const #198 = Asciz	temp36;
const #199 = Asciz	temp38;
const #200 = Asciz	temp39;
const #201 = Asciz	temp40;
const #202 = Asciz	temp42;
const #203 = Asciz	temp43;
const #204 = Asciz	temp44;
const #205 = Asciz	temp45;
const #206 = Asciz	temp46;
const #207 = Asciz	(Lscala/xml/dtd/ContentModel;Lscala/collection/mutable/StringBuilder;)Lscala/collection/mutable/StringBuilder;;
const #208 = Asciz	scala/xml/dtd/ANY$;
const #209 = class	#208;	//  scala/xml/dtd/ANY$
const #210 = Asciz	Lscala/xml/dtd/ANY$;;
const #211 = NameAndType	#4:#210;//  MODULE$:Lscala/xml/dtd/ANY$;
const #212 = Field	#209.#211;	//  scala/xml/dtd/ANY$.MODULE$:Lscala/xml/dtd/ANY$;
const #213 = Asciz	ANY;
const #214 = String	#213;	//  ANY
const #215 = Asciz	scala/xml/dtd/ContentModel;
const #216 = class	#215;	//  scala/xml/dtd/ContentModel
const #217 = Method	#216.#64;	//  scala/xml/dtd/ContentModel.toString:()Ljava/lang/String;
const #218 = Asciz	scala/xml/dtd/EMPTY$;
const #219 = class	#218;	//  scala/xml/dtd/EMPTY$
const #220 = Asciz	Lscala/xml/dtd/EMPTY$;;
const #221 = NameAndType	#4:#220;//  MODULE$:Lscala/xml/dtd/EMPTY$;
const #222 = Field	#219.#221;	//  scala/xml/dtd/EMPTY$.MODULE$:Lscala/xml/dtd/EMPTY$;
const #223 = Asciz	EMPTY;
const #224 = String	#223;	//  EMPTY
const #225 = Asciz	scala/xml/dtd/PCDATA$;
const #226 = class	#225;	//  scala/xml/dtd/PCDATA$
const #227 = Asciz	Lscala/xml/dtd/PCDATA$;;
const #228 = NameAndType	#4:#227;//  MODULE$:Lscala/xml/dtd/PCDATA$;
const #229 = Field	#226.#228;	//  scala/xml/dtd/PCDATA$.MODULE$:Lscala/xml/dtd/PCDATA$;
const #230 = Asciz	(#PCDATA);
const #231 = String	#230;	//  (#PCDATA)
const #232 = Asciz	scala/xml/dtd/ELEMENTS;
const #233 = class	#232;	//  scala/xml/dtd/ELEMENTS
const #234 = Asciz	scala/xml/dtd/MIXED;
const #235 = class	#234;	//  scala/xml/dtd/MIXED
const #236 = Asciz	(Lscala/collection/mutable/StringBuilder;)Lscala/collection/mutable/StringBuilder;;
const #237 = NameAndType	#168:#236;//  buildString:(Lscala/collection/mutable/StringBuilder;)Lscala/collection/mutable/StringBuilder;
const #238 = Method	#216.#237;	//  scala/xml/dtd/ContentModel.buildString:(Lscala/collection/mutable/StringBuilder;)Lscala/collection/mutable/StringBuilder;
const #239 = Asciz	c;
const #240 = Asciz	Lscala/xml/dtd/ContentModel;;
const #241 = Asciz	scala/collection/IterableLike;
const #242 = class	#241;	//  scala/collection/IterableLike
const #243 = Asciz	head;
const #244 = Asciz	()Ljava/lang/Object;;
const #245 = NameAndType	#243:#244;//  head:()Ljava/lang/Object;
const #246 = InterfaceMethod	#242.#245;	//  scala/collection/IterableLike.head:()Ljava/lang/Object;
const #247 = Asciz	tail;
const #248 = NameAndType	#247:#244;//  tail:()Ljava/lang/Object;
const #249 = InterfaceMethod	#122.#248;	//  scala/collection/TraversableLike.tail:()Ljava/lang/Object;
const #250 = Asciz	scala/xml/dtd/ContentModel$$anonfun$buildString$2;
const #251 = class	#250;	//  scala/xml/dtd/ContentModel$$anonfun$buildString$2
const #252 = Asciz	(Lscala/collection/mutable/StringBuilder;C)V;
const #253 = NameAndType	#11:#252;//  "<init>":(Lscala/collection/mutable/StringBuilder;C)V
const #254 = Method	#251.#253;	//  scala/xml/dtd/ContentModel$$anonfun$buildString$2."<init>":(Lscala/collection/mutable/StringBuilder;C)V
const #255 = Asciz	foreach;
const #256 = Asciz	(Lscala/Function1;)V;
const #257 = NameAndType	#255:#256;//  foreach:(Lscala/Function1;)V
const #258 = InterfaceMethod	#242.#257;	//  scala/collection/IterableLike.foreach:(Lscala/Function1;)V
const #259 = Asciz	sb$1;
const #260 = Asciz	sep$1;
const #261 = Asciz	C;
const #262 = Asciz	(Lscala/collection/Seq<Lscala/util/regexp/Base$RegExp;>;Lscala/collection/mutable/StringBuilder;C)V;
const #263 = Asciz	Signature;
const #264 = Asciz	(Lscala/util/regexp/Base$RegExp;)Ljava/lang/String;;
const #265 = Method	#176.#12;	//  scala/collection/mutable/StringBuilder."<init>":()V
const #266 = Method	#176.#64;	//  scala/collection/mutable/StringBuilder.toString:()Ljava/lang/String;
const #267 = Asciz	r$3;
const #268 = Asciz	sb0;
const #269 = Asciz	getLabels;
const #270 = NameAndType	#20:#21;//  traverse$1:(Lscala/util/regexp/Base$RegExp;)Lscala/collection/immutable/Set;
const #271 = Method	#10.#270;	//  scala/xml/dtd/ContentModel$.traverse$1:(Lscala/util/regexp/Base$RegExp;)Lscala/collection/immutable/Set;
const #272 = Asciz	(Lscala/util/regexp/Base$RegExp;)Lscala/collection/immutable/Set<Ljava/lang/String;>;;
const #273 = Asciz	parse;
const #274 = Asciz	(Ljava/lang/String;)Lscala/xml/dtd/ContentModel;;
const #275 = Asciz	scala/xml/dtd/ContentModelParser$;
const #276 = class	#275;	//  scala/xml/dtd/ContentModelParser$
const #277 = Asciz	Lscala/xml/dtd/ContentModelParser$;;
const #278 = NameAndType	#4:#277;//  MODULE$:Lscala/xml/dtd/ContentModelParser$;
const #279 = Field	#276.#278;	//  scala/xml/dtd/ContentModelParser$.MODULE$:Lscala/xml/dtd/ContentModelParser$;
const #280 = NameAndType	#273:#274;//  parse:(Ljava/lang/String;)Lscala/xml/dtd/ContentModel;
const #281 = Method	#276.#280;	//  scala/xml/dtd/ContentModelParser$.parse:(Ljava/lang/String;)Lscala/xml/dtd/ContentModel;
const #282 = Asciz	s;
const #283 = Asciz	containsText;
const #284 = Asciz	(Lscala/xml/dtd/ContentModel;)Z;
const #285 = Asciz	scala/PartialFunction$;
const #286 = class	#285;	//  scala/PartialFunction$
const #287 = Asciz	Lscala/PartialFunction$;;
const #288 = NameAndType	#4:#287;//  MODULE$:Lscala/PartialFunction$;
const #289 = Field	#286.#288;	//  scala/PartialFunction$.MODULE$:Lscala/PartialFunction$;
const #290 = Asciz	scala/xml/dtd/ContentModel$$anonfun$isMixed$1;
const #291 = class	#290;	//  scala/xml/dtd/ContentModel$$anonfun$isMixed$1
const #292 = Method	#291.#12;	//  scala/xml/dtd/ContentModel$$anonfun$isMixed$1."<init>":()V
const #293 = Asciz	cond;
const #294 = Asciz	(Ljava/lang/Object;Lscala/PartialFunction;)Z;
const #295 = NameAndType	#293:#294;//  cond:(Ljava/lang/Object;Lscala/PartialFunction;)Z
const #296 = Method	#286.#295;	//  scala/PartialFunction$.cond:(Ljava/lang/Object;Lscala/PartialFunction;)Z
const #297 = Asciz	cm;
const #298 = Asciz	isMixed;
const #299 = Asciz	InnerClasses;
const #300 = Asciz	scala/util/regexp/Base;
const #301 = class	#300;	//  scala/util/regexp/Base
const #302 = Asciz	Star;
const #303 = Asciz	RegExp;
const #304 = Asciz	scala/util/regexp/WordExp$Label;
const #305 = class	#304;	//  scala/util/regexp/WordExp$Label
const #306 = Asciz	Label;
const #307 = Asciz	scala/Predef;
const #308 = class	#307;	//  scala/Predef
const #309 = Asciz	$anon$1;
const #310 = Asciz	Letter;
const #311 = Asciz	ElemName;
const #312 = Asciz	$anonfun$isMixed$1;
const #313 = Asciz	scala/xml/dtd/ContentModel$$anonfun$toString$1;
const #314 = class	#313;	//  scala/xml/dtd/ContentModel$$anonfun$toString$1
const #315 = Asciz	$anonfun$toString$1;
const #316 = Asciz	$anonfun$traverse$1$2;
const #317 = Asciz	$anonfun$traverse$1$1;
const #318 = Asciz	scala/xml/dtd/ContentModel$$anonfun$buildString$1;
const #319 = class	#318;	//  scala/xml/dtd/ContentModel$$anonfun$buildString$1
const #320 = Asciz	$anonfun$buildString$1;
const #321 = Asciz	$anonfun$buildString$2;
const #322 = Asciz	scala/collection/generic/TraversableFactory;
const #323 = class	#322;	//  scala/collection/generic/TraversableFactory
const #324 = Asciz	GenericCanBuildFrom;
const #325 = Asciz	scala/ScalaObject;
const #326 = class	#325;	//  scala/ScalaObject

{
public static final scala.xml.dtd.ContentModel$ MODULE$;

public static {};
  Code:
   Stack=1, Locals=0, Args_size=0
   0:	new	#10; //class scala/xml/dtd/ContentModel$
   3:	invokespecial	#13; //Method "<init>":()V
   6:	return

public final scala.collection.immutable.Set traverse$1(scala.util.regexp.Base$RegExp);
  Code:
   Stack=6, Locals=15, Args_size=2
   0:	aload_1
   1:	instanceof	#23; //class scala/util/regexp/WordExp$Letter
   4:	ifeq	91
   7:	aload_1
   8:	checkcast	#23; //class scala/util/regexp/WordExp$Letter
   11:	astore_2
   12:	aload_2
   13:	invokevirtual	#27; //Method scala/util/regexp/WordExp$Letter.a:()Lscala/util/regexp/WordExp$Label;
   16:	checkcast	#29; //class scala/xml/dtd/ContentModel$ElemName
   19:	astore_3
   20:	aload_3
   21:	ifnull	79
   24:	aload_3
   25:	invokevirtual	#33; //Method scala/xml/dtd/ContentModel$ElemName.name:()Ljava/lang/String;
   28:	astore	4
   30:	iconst_1
   31:	ifeq	67
   34:	getstatic	#38; //Field scala/Predef$.MODULE$:Lscala/Predef$;
   37:	invokevirtual	#42; //Method scala/Predef$.Set:()Lscala/collection/immutable/Set$;
   40:	getstatic	#38; //Field scala/Predef$.MODULE$:Lscala/Predef$;
   43:	iconst_1
   44:	anewarray	#44; //class java/lang/String
   47:	dup
   48:	iconst_0
   49:	aload	4
   51:	aastore
   52:	checkcast	#46; //class "[Ljava/lang/Object;"
   55:	invokevirtual	#50; //Method scala/Predef$.wrapRefArray:([Ljava/lang/Object;)Lscala/collection/mutable/WrappedArray;
   58:	invokevirtual	#56; //Method scala/collection/immutable/Set$.apply:(Lscala/collection/Seq;)Lscala/collection/Traversable;
   61:	checkcast	#58; //class scala/collection/immutable/Set
   64:	goto	468
   67:	new	#60; //class scala/MatchError
   70:	dup
   71:	aload_1
   72:	invokevirtual	#65; //Method scala/util/regexp/Base$RegExp.toString:()Ljava/lang/String;
   75:	invokespecial	#68; //Method scala/MatchError."<init>":(Ljava/lang/String;)V
   78:	athrow
   79:	new	#60; //class scala/MatchError
   82:	dup
   83:	aload_1
   84:	invokevirtual	#65; //Method scala/util/regexp/Base$RegExp.toString:()Ljava/lang/String;
   87:	invokespecial	#68; //Method scala/MatchError."<init>":(Ljava/lang/String;)V
   90:	athrow
   91:	aload_1
   92:	instanceof	#70; //class scala/util/regexp/Base$Star
   95:	ifeq	133
   98:	aload_1
   99:	checkcast	#70; //class scala/util/regexp/Base$Star
   102:	astore	5
   104:	aload	5
   106:	invokevirtual	#74; //Method scala/util/regexp/Base$Star.r:()Lscala/util/regexp/Base$RegExp;
   109:	astore	6
   111:	iconst_1
   112:	ifeq	121
   115:	aload	6
   117:	astore_1
   118:	goto	0
   121:	new	#60; //class scala/MatchError
   124:	dup
   125:	aload_1
   126:	invokevirtual	#65; //Method scala/util/regexp/Base$RegExp.toString:()Ljava/lang/String;
   129:	invokespecial	#68; //Method scala/MatchError."<init>":(Ljava/lang/String;)V
   132:	athrow
   133:	aload_1
   134:	instanceof	#76; //class scala/util/regexp/Base$Sequ
   137:	ifeq	320
   140:	aload_1
   141:	checkcast	#76; //class scala/util/regexp/Base$Sequ
   144:	astore	7
   146:	aload_0
   147:	invokevirtual	#80; //Method Sequ:()Lscala/util/regexp/Base$Sequ$;
   150:	pop
   151:	new	#82; //class scala/Some
   154:	dup
   155:	aload	7
   157:	invokevirtual	#86; //Method scala/util/regexp/Base$Sequ.rs:()Lscala/collection/Seq;
   160:	invokespecial	#89; //Method scala/Some."<init>":(Ljava/lang/Object;)V
   163:	astore	8
   165:	iconst_1
   166:	ifeq	308
   169:	aload	8
   171:	getfield	#93; //Field scala/Some.x:Ljava/lang/Object;
   174:	checkcast	#95; //class scala/collection/Seq
   177:	astore	9
   179:	aload	9
   181:	dup
   182:	pop
   183:	ifnull	195
   186:	aload	9
   188:	aconst_null
   189:	invokevirtual	#101; //Method java/lang/Object.equals:(Ljava/lang/Object;)Z
   192:	ifeq	199
   195:	iconst_0
   196:	goto	216
   199:	aload	9
   201:	iconst_0
   202:	invokeinterface	#107,  2; //InterfaceMethod scala/collection/SeqLike.lengthCompare:(I)I
   207:	iconst_0
   208:	if_icmplt	215
   211:	iconst_1
   212:	goto	216
   215:	iconst_0
   216:	ifeq	296
   219:	iconst_1
   220:	ifeq	284
   223:	getstatic	#38; //Field scala/Predef$.MODULE$:Lscala/Predef$;
   226:	invokevirtual	#42; //Method scala/Predef$.Set:()Lscala/collection/immutable/Set$;
   229:	aload	9
   231:	new	#109; //class scala/xml/dtd/ContentModel$$anonfun$traverse$1$1
   234:	dup
   235:	invokespecial	#110; //Method scala/xml/dtd/ContentModel$$anonfun$traverse$1$1."<init>":()V
   238:	getstatic	#115; //Field scala/collection/Seq$.MODULE$:Lscala/collection/Seq$;
   241:	astore	10
   243:	new	#117; //class scala/collection/generic/TraversableFactory$GenericCanBuildFrom
   246:	dup
   247:	aload	10
   249:	invokespecial	#120; //Method scala/collection/generic/TraversableFactory$GenericCanBuildFrom."<init>":(Lscala/collection/generic/TraversableFactory;)V
   252:	invokeinterface	#126,  3; //InterfaceMethod scala/collection/TraversableLike.map:(Lscala/Function1;Lscala/collection/generic/CanBuildFrom;)Ljava/lang/Object;
   257:	checkcast	#128; //class scala/collection/generic/GenericTraversableTemplate
   260:	new	#130; //class scala/Predef$$anon$1
   263:	dup
   264:	invokespecial	#131; //Method scala/Predef$$anon$1."<init>":()V
   267:	invokeinterface	#135,  2; //InterfaceMethod scala/collection/generic/GenericTraversableTemplate.flatten:(Lscala/Function1;)Lscala/collection/Traversable;
   272:	checkcast	#95; //class scala/collection/Seq
   275:	invokevirtual	#56; //Method scala/collection/immutable/Set$.apply:(Lscala/collection/Seq;)Lscala/collection/Traversable;
   278:	checkcast	#58; //class scala/collection/immutable/Set
   281:	goto	468
   284:	new	#60; //class scala/MatchError
   287:	dup
   288:	aload_1
   289:	invokevirtual	#65; //Method scala/util/regexp/Base$RegExp.toString:()Ljava/lang/String;
   292:	invokespecial	#68; //Method scala/MatchError."<init>":(Ljava/lang/String;)V
   295:	athrow
   296:	new	#60; //class scala/MatchError
   299:	dup
   300:	aload_1
   301:	invokevirtual	#65; //Method scala/util/regexp/Base$RegExp.toString:()Ljava/lang/String;
   304:	invokespecial	#68; //Method scala/MatchError."<init>":(Ljava/lang/String;)V
   307:	athrow
   308:	new	#60; //class scala/MatchError
   311:	dup
   312:	aload_1
   313:	invokevirtual	#65; //Method scala/util/regexp/Base$RegExp.toString:()Ljava/lang/String;
   316:	invokespecial	#68; //Method scala/MatchError."<init>":(Ljava/lang/String;)V
   319:	athrow
   320:	aload_1
   321:	instanceof	#137; //class scala/util/regexp/Base$Alt
   324:	ifeq	505
   327:	aload_1
   328:	checkcast	#137; //class scala/util/regexp/Base$Alt
   331:	astore	11
   333:	aload_0
   334:	invokevirtual	#141; //Method Alt:()Lscala/util/regexp/Base$Alt$;
   337:	pop
   338:	new	#82; //class scala/Some
   341:	dup
   342:	aload	11
   344:	invokevirtual	#142; //Method scala/util/regexp/Base$Alt.rs:()Lscala/collection/Seq;
   347:	invokespecial	#89; //Method scala/Some."<init>":(Ljava/lang/Object;)V
   350:	astore	12
   352:	iconst_1
   353:	ifeq	493
   356:	aload	12
   358:	getfield	#93; //Field scala/Some.x:Ljava/lang/Object;
   361:	checkcast	#95; //class scala/collection/Seq
   364:	astore	13
   366:	aload	13
   368:	dup
   369:	pop
   370:	ifnull	382
   373:	aload	13
   375:	aconst_null
   376:	invokevirtual	#101; //Method java/lang/Object.equals:(Ljava/lang/Object;)Z
   379:	ifeq	386
   382:	iconst_0
   383:	goto	403
   386:	aload	13
   388:	iconst_0
   389:	invokeinterface	#107,  2; //InterfaceMethod scala/collection/SeqLike.lengthCompare:(I)I
   394:	iconst_0
   395:	if_icmplt	402
   398:	iconst_1
   399:	goto	403
   402:	iconst_0
   403:	ifeq	481
   406:	iconst_1
   407:	ifeq	469
   410:	getstatic	#38; //Field scala/Predef$.MODULE$:Lscala/Predef$;
   413:	invokevirtual	#42; //Method scala/Predef$.Set:()Lscala/collection/immutable/Set$;
   416:	aload	13
   418:	new	#144; //class scala/xml/dtd/ContentModel$$anonfun$traverse$1$2
   421:	dup
   422:	invokespecial	#145; //Method scala/xml/dtd/ContentModel$$anonfun$traverse$1$2."<init>":()V
   425:	getstatic	#115; //Field scala/collection/Seq$.MODULE$:Lscala/collection/Seq$;
   428:	astore	14
   430:	new	#117; //class scala/collection/generic/TraversableFactory$GenericCanBuildFrom
   433:	dup
   434:	aload	14
   436:	invokespecial	#120; //Method scala/collection/generic/TraversableFactory$GenericCanBuildFrom."<init>":(Lscala/collection/generic/TraversableFactory;)V
   439:	invokeinterface	#126,  3; //InterfaceMethod scala/collection/TraversableLike.map:(Lscala/Function1;Lscala/collection/generic/CanBuildFrom;)Ljava/lang/Object;
   444:	checkcast	#128; //class scala/collection/generic/GenericTraversableTemplate
   447:	new	#130; //class scala/Predef$$anon$1
   450:	dup
   451:	invokespecial	#131; //Method scala/Predef$$anon$1."<init>":()V
   454:	invokeinterface	#135,  2; //InterfaceMethod scala/collection/generic/GenericTraversableTemplate.flatten:(Lscala/Function1;)Lscala/collection/Traversable;
   459:	checkcast	#95; //class scala/collection/Seq
   462:	invokevirtual	#56; //Method scala/collection/immutable/Set$.apply:(Lscala/collection/Seq;)Lscala/collection/Traversable;
   465:	checkcast	#58; //class scala/collection/immutable/Set
   468:	areturn
   469:	new	#60; //class scala/MatchError
   472:	dup
   473:	aload_1
   474:	invokevirtual	#65; //Method scala/util/regexp/Base$RegExp.toString:()Ljava/lang/String;
   477:	invokespecial	#68; //Method scala/MatchError."<init>":(Ljava/lang/String;)V
   480:	athrow
   481:	new	#60; //class scala/MatchError
   484:	dup
   485:	aload_1
   486:	invokevirtual	#65; //Method scala/util/regexp/Base$RegExp.toString:()Ljava/lang/String;
   489:	invokespecial	#68; //Method scala/MatchError."<init>":(Ljava/lang/String;)V
   492:	athrow
   493:	new	#60; //class scala/MatchError
   496:	dup
   497:	aload_1
   498:	invokevirtual	#65; //Method scala/util/regexp/Base$RegExp.toString:()Ljava/lang/String;
   501:	invokespecial	#68; //Method scala/MatchError."<init>":(Ljava/lang/String;)V
   504:	athrow
   505:	new	#60; //class scala/MatchError
   508:	dup
   509:	aload_1
   510:	invokevirtual	#65; //Method scala/util/regexp/Base$RegExp.toString:()Ljava/lang/String;
   513:	invokespecial	#68; //Method scala/MatchError."<init>":(Ljava/lang/String;)V
   516:	athrow
  LineNumberTable: 
   line 40: 0
   line 21: 30
   line 41: 34
   line 40: 67
   line 21: 111
   line 42: 115
   line 40: 121
   line 43: 146
   line 40: 151
   line 21: 165
   line 40: 169
   line 228: 195
   line 40: 199
   line 228: 207
   line 40: 211
   line 21: 219
   line 43: 223
   line 40: 284
   line 44: 333
   line 40: 338
   line 21: 352
   line 40: 356
   line 228: 382
   line 40: 386
   line 228: 394
   line 40: 398
   line 21: 406
   line 44: 410
   line 40: 468

  LocalVariableTable: 
   Start  Length  Slot  Name   Signature
   0      517      0    this       Lscala/xml/dtd/ContentModel$;
   0      517      1    r       Lscala/util/regexp/Base$RegExp;
   12      79      2    temp12       Lscala/util/regexp/WordExp$Letter;
   20      71      3    temp13       Lscala/xml/dtd/ContentModel$ElemName;
   30      49      4    temp14       Ljava/lang/String;
   104      29      5    temp15       Lscala/util/regexp/Base$Star;
   111      22      6    temp16       Lscala/util/regexp/Base$RegExp;
   146      174      7    temp17       Lscala/util/regexp/Base$Sequ;
   165      155      8    temp18       Lscala/Some;
   179      129      9    temp19       Lscala/collection/Seq;
   333      135      11    temp21       Lscala/util/regexp/Base$Alt;
   469      36      11    temp21       Lscala/util/regexp/Base$Alt;
   352      116      12    temp22       Lscala/Some;
   469      36      12    temp22       Lscala/Some;
   366      102      13    temp23       Lscala/collection/Seq;
   469      24      13    temp23       Lscala/collection/Seq;


public scala.collection.mutable.StringBuilder buildString(scala.util.regexp.Base$RegExp, scala.collection.mutable.StringBuilder);
  Code:
   Stack=4, Locals=15, Args_size=3
   0:	aload_1
   1:	aload_0
   2:	invokevirtual	#173; //Method Eps:()Lscala/util/regexp/Base$Eps$;
   5:	astore_3
   6:	dup
   7:	ifnonnull	18
   10:	pop
   11:	aload_3
   12:	ifnull	25
   15:	goto	45
   18:	aload_3
   19:	invokevirtual	#101; //Method java/lang/Object.equals:(Ljava/lang/Object;)Z
   22:	ifeq	45
   25:	iconst_1
   26:	ifeq	33
   29:	aload_2
   30:	goto	469
   33:	new	#60; //class scala/MatchError
   36:	dup
   37:	aload_1
   38:	invokevirtual	#65; //Method scala/util/regexp/Base$RegExp.toString:()Ljava/lang/String;
   41:	invokespecial	#68; //Method scala/MatchError."<init>":(Ljava/lang/String;)V
   44:	athrow
   45:	aload_1
   46:	instanceof	#76; //class scala/util/regexp/Base$Sequ
   49:	ifeq	196
   52:	aload_1
   53:	checkcast	#76; //class scala/util/regexp/Base$Sequ
   56:	astore	4
   58:	aload_0
   59:	invokevirtual	#80; //Method Sequ:()Lscala/util/regexp/Base$Sequ$;
   62:	pop
   63:	new	#82; //class scala/Some
   66:	dup
   67:	aload	4
   69:	invokevirtual	#86; //Method scala/util/regexp/Base$Sequ.rs:()Lscala/collection/Seq;
   72:	invokespecial	#89; //Method scala/Some."<init>":(Ljava/lang/Object;)V
   75:	astore	5
   77:	iconst_1
   78:	ifeq	184
   81:	aload	5
   83:	getfield	#93; //Field scala/Some.x:Ljava/lang/Object;
   86:	checkcast	#95; //class scala/collection/Seq
   89:	astore	6
   91:	aload	6
   93:	dup
   94:	pop
   95:	ifnull	107
   98:	aload	6
   100:	aconst_null
   101:	invokevirtual	#101; //Method java/lang/Object.equals:(Ljava/lang/Object;)Z
   104:	ifeq	111
   107:	iconst_0
   108:	goto	128
   111:	aload	6
   113:	iconst_0
   114:	invokeinterface	#107,  2; //InterfaceMethod scala/collection/SeqLike.lengthCompare:(I)I
   119:	iconst_0
   120:	if_icmplt	127
   123:	iconst_1
   124:	goto	128
   127:	iconst_0
   128:	ifeq	172
   131:	iconst_1
   132:	ifeq	160
   135:	aload_2
   136:	ldc	#174; //int 40
   138:	invokevirtual	#180; //Method scala/collection/mutable/StringBuilder.append:(C)Lscala/collection/mutable/StringBuilder;
   141:	pop
   142:	aload_0
   143:	aload	6
   145:	aload_2
   146:	ldc	#181; //int 44
   148:	invokespecial	#184; //Method buildString:(Lscala/collection/Seq;Lscala/collection/mutable/StringBuilder;C)V
   151:	aload_2
   152:	ldc	#185; //int 41
   154:	invokevirtual	#180; //Method scala/collection/mutable/StringBuilder.append:(C)Lscala/collection/mutable/StringBuilder;
   157:	goto	469
   160:	new	#60; //class scala/MatchError
   163:	dup
   164:	aload_1
   165:	invokevirtual	#65; //Method scala/util/regexp/Base$RegExp.toString:()Ljava/lang/String;
   168:	invokespecial	#68; //Method scala/MatchError."<init>":(Ljava/lang/String;)V
   171:	athrow
   172:	new	#60; //class scala/MatchError
   175:	dup
   176:	aload_1
   177:	invokevirtual	#65; //Method scala/util/regexp/Base$RegExp.toString:()Ljava/lang/String;
   180:	invokespecial	#68; //Method scala/MatchError."<init>":(Ljava/lang/String;)V
   183:	athrow
   184:	new	#60; //class scala/MatchError
   187:	dup
   188:	aload_1
   189:	invokevirtual	#65; //Method scala/util/regexp/Base$RegExp.toString:()Ljava/lang/String;
   192:	invokespecial	#68; //Method scala/MatchError."<init>":(Ljava/lang/String;)V
   195:	athrow
   196:	aload_1
   197:	instanceof	#137; //class scala/util/regexp/Base$Alt
   200:	ifeq	347
   203:	aload_1
   204:	checkcast	#137; //class scala/util/regexp/Base$Alt
   207:	astore	7
   209:	aload_0
   210:	invokevirtual	#141; //Method Alt:()Lscala/util/regexp/Base$Alt$;
   213:	pop
   214:	new	#82; //class scala/Some
   217:	dup
   218:	aload	7
   220:	invokevirtual	#142; //Method scala/util/regexp/Base$Alt.rs:()Lscala/collection/Seq;
   223:	invokespecial	#89; //Method scala/Some."<init>":(Ljava/lang/Object;)V
   226:	astore	8
   228:	iconst_1
   229:	ifeq	335
   232:	aload	8
   234:	getfield	#93; //Field scala/Some.x:Ljava/lang/Object;
   237:	checkcast	#95; //class scala/collection/Seq
   240:	astore	9
   242:	aload	9
   244:	dup
   245:	pop
   246:	ifnull	258
   249:	aload	9
   251:	aconst_null
   252:	invokevirtual	#101; //Method java/lang/Object.equals:(Ljava/lang/Object;)Z
   255:	ifeq	262
   258:	iconst_0
   259:	goto	279
   262:	aload	9
   264:	iconst_0
   265:	invokeinterface	#107,  2; //InterfaceMethod scala/collection/SeqLike.lengthCompare:(I)I
   270:	iconst_0
   271:	if_icmplt	278
   274:	iconst_1
   275:	goto	279
   278:	iconst_0
   279:	ifeq	323
   282:	iconst_1
   283:	ifeq	311
   286:	aload_2
   287:	ldc	#174; //int 40
   289:	invokevirtual	#180; //Method scala/collection/mutable/StringBuilder.append:(C)Lscala/collection/mutable/StringBuilder;
   292:	pop
   293:	aload_0
   294:	aload	9
   296:	aload_2
   297:	ldc	#186; //int 124
   299:	invokespecial	#184; //Method buildString:(Lscala/collection/Seq;Lscala/collection/mutable/StringBuilder;C)V
   302:	aload_2
   303:	ldc	#185; //int 41
   305:	invokevirtual	#180; //Method scala/collection/mutable/StringBuilder.append:(C)Lscala/collection/mutable/StringBuilder;
   308:	goto	469
   311:	new	#60; //class scala/MatchError
   314:	dup
   315:	aload_1
   316:	invokevirtual	#65; //Method scala/util/regexp/Base$RegExp.toString:()Ljava/lang/String;
   319:	invokespecial	#68; //Method scala/MatchError."<init>":(Ljava/lang/String;)V
   322:	athrow
   323:	new	#60; //class scala/MatchError
   326:	dup
   327:	aload_1
   328:	invokevirtual	#65; //Method scala/util/regexp/Base$RegExp.toString:()Ljava/lang/String;
   331:	invokespecial	#68; //Method scala/MatchError."<init>":(Ljava/lang/String;)V
   334:	athrow
   335:	new	#60; //class scala/MatchError
   338:	dup
   339:	aload_1
   340:	invokevirtual	#65; //Method scala/util/regexp/Base$RegExp.toString:()Ljava/lang/String;
   343:	invokespecial	#68; //Method scala/MatchError."<init>":(Ljava/lang/String;)V
   346:	athrow
   347:	aload_1
   348:	instanceof	#70; //class scala/util/regexp/Base$Star
   351:	ifeq	424
   354:	aload_1
   355:	checkcast	#70; //class scala/util/regexp/Base$Star
   358:	astore	10
   360:	aload	10
   362:	invokevirtual	#74; //Method scala/util/regexp/Base$Star.r:()Lscala/util/regexp/Base$RegExp;
   365:	astore	11
   367:	aload	11
   369:	ifnull	412
   372:	iconst_1
   373:	ifeq	400
   376:	aload_2
   377:	ldc	#174; //int 40
   379:	invokevirtual	#180; //Method scala/collection/mutable/StringBuilder.append:(C)Lscala/collection/mutable/StringBuilder;
   382:	pop
   383:	aload_0
   384:	aload	11
   386:	aload_2
   387:	invokevirtual	#188; //Method buildString:(Lscala/util/regexp/Base$RegExp;Lscala/collection/mutable/StringBuilder;)Lscala/collection/mutable/StringBuilder;
   390:	pop
   391:	aload_2
   392:	ldc	#190; //String )*
   394:	invokevirtual	#193; //Method scala/collection/mutable/StringBuilder.append:(Ljava/lang/String;)Lscala/collection/mutable/StringBuilder;
   397:	goto	469
   400:	new	#60; //class scala/MatchError
   403:	dup
   404:	aload_1
   405:	invokevirtual	#65; //Method scala/util/regexp/Base$RegExp.toString:()Ljava/lang/String;
   408:	invokespecial	#68; //Method scala/MatchError."<init>":(Ljava/lang/String;)V
   411:	athrow
   412:	new	#60; //class scala/MatchError
   415:	dup
   416:	aload_1
   417:	invokevirtual	#65; //Method scala/util/regexp/Base$RegExp.toString:()Ljava/lang/String;
   420:	invokespecial	#68; //Method scala/MatchError."<init>":(Ljava/lang/String;)V
   423:	athrow
   424:	aload_1
   425:	instanceof	#23; //class scala/util/regexp/WordExp$Letter
   428:	ifeq	494
   431:	aload_1
   432:	checkcast	#23; //class scala/util/regexp/WordExp$Letter
   435:	astore	12
   437:	aload	12
   439:	invokevirtual	#27; //Method scala/util/regexp/WordExp$Letter.a:()Lscala/util/regexp/WordExp$Label;
   442:	checkcast	#29; //class scala/xml/dtd/ContentModel$ElemName
   445:	astore	13
   447:	aload	13
   449:	ifnull	482
   452:	aload	13
   454:	invokevirtual	#33; //Method scala/xml/dtd/ContentModel$ElemName.name:()Ljava/lang/String;
   457:	astore	14
   459:	iconst_1
   460:	ifeq	470
   463:	aload_2
   464:	aload	14
   466:	invokevirtual	#193; //Method scala/collection/mutable/StringBuilder.append:(Ljava/lang/String;)Lscala/collection/mutable/StringBuilder;
   469:	areturn
   470:	new	#60; //class scala/MatchError
   473:	dup
   474:	aload_1
   475:	invokevirtual	#65; //Method scala/util/regexp/Base$RegExp.toString:()Ljava/lang/String;
   478:	invokespecial	#68; //Method scala/MatchError."<init>":(Ljava/lang/String;)V
   481:	athrow
   482:	new	#60; //class scala/MatchError
   485:	dup
   486:	aload_1
   487:	invokevirtual	#65; //Method scala/util/regexp/Base$RegExp.toString:()Ljava/lang/String;
   490:	invokespecial	#68; //Method scala/MatchError."<init>":(Ljava/lang/String;)V
   493:	athrow
   494:	new	#60; //class scala/MatchError
   497:	dup
   498:	aload_1
   499:	invokevirtual	#65; //Method scala/util/regexp/Base$RegExp.toString:()Ljava/lang/String;
   502:	invokespecial	#68; //Method scala/MatchError."<init>":(Ljava/lang/String;)V
   505:	athrow
  LineNumberTable: 
   line 70: 0
   line 21: 25
   line 72: 29
   line 70: 33
   line 69: 52
   line 73: 58
   line 69: 63
   line 21: 77
   line 69: 81
   line 70: 91
   line 228: 107
   line 70: 111
   line 228: 119
   line 70: 123
   line 21: 131
   line 74: 135
   line 70: 160
   line 69: 203
   line 75: 209
   line 69: 214
   line 21: 228
   line 69: 232
   line 70: 242
   line 228: 258
   line 70: 262
   line 228: 270
   line 70: 274
   line 21: 282
   line 76: 286
   line 70: 311
   line 69: 354
   line 70: 367
   line 21: 372
   line 78: 376
   line 70: 400
   line 69: 431
   line 70: 447
   line 69: 452
   line 21: 459
   line 80: 463
   line 70: 469

  LocalVariableTable: 
   Start  Length  Slot  Name   Signature
   0      506      0    this       Lscala/xml/dtd/ContentModel$;
   0      506      1    r       Lscala/util/regexp/Base$RegExp;
   0      506      2    sb       Lscala/collection/mutable/StringBuilder;
   58      138      4    temp34       Lscala/util/regexp/Base$Sequ;
   77      119      5    temp35       Lscala/Some;
   91      93      6    temp36       Lscala/collection/Seq;
   209      138      7    temp38       Lscala/util/regexp/Base$Alt;
   228      119      8    temp39       Lscala/Some;
   242      93      9    temp40       Lscala/collection/Seq;
   360      64      10    temp42       Lscala/util/regexp/Base$Star;
   367      57      11    temp43       Lscala/util/regexp/Base$RegExp;
   437      32      12    temp44       Lscala/util/regexp/WordExp$Letter;
   470      24      12    temp44       Lscala/util/regexp/WordExp$Letter;
   447      22      13    temp45       Lscala/xml/dtd/ContentModel$ElemName;
   470      24      13    temp45       Lscala/xml/dtd/ContentModel$ElemName;
   459      10      14    temp46       Ljava/lang/String;
   470      12      14    temp46       Ljava/lang/String;


public scala.collection.mutable.StringBuilder buildString(scala.xml.dtd.ContentModel, scala.collection.mutable.StringBuilder);
  Code:
   Stack=3, Locals=3, Args_size=3
   0:	getstatic	#212; //Field scala/xml/dtd/ANY$.MODULE$:Lscala/xml/dtd/ANY$;
   3:	dup
   4:	ifnonnull	15
   7:	pop
   8:	aload_1
   9:	ifnull	22
   12:	goto	47
   15:	aload_1
   16:	invokevirtual	#101; //Method java/lang/Object.equals:(Ljava/lang/Object;)Z
   19:	ifeq	47
   22:	iconst_1
   23:	ifeq	35
   26:	aload_2
   27:	ldc	#214; //String ANY
   29:	invokevirtual	#193; //Method scala/collection/mutable/StringBuilder.append:(Ljava/lang/String;)Lscala/collection/mutable/StringBuilder;
   32:	goto	180
   35:	new	#60; //class scala/MatchError
   38:	dup
   39:	aload_1
   40:	invokevirtual	#217; //Method scala/xml/dtd/ContentModel.toString:()Ljava/lang/String;
   43:	invokespecial	#68; //Method scala/MatchError."<init>":(Ljava/lang/String;)V
   46:	athrow
   47:	getstatic	#222; //Field scala/xml/dtd/EMPTY$.MODULE$:Lscala/xml/dtd/EMPTY$;
   50:	dup
   51:	ifnonnull	62
   54:	pop
   55:	aload_1
   56:	ifnull	69
   59:	goto	94
   62:	aload_1
   63:	invokevirtual	#101; //Method java/lang/Object.equals:(Ljava/lang/Object;)Z
   66:	ifeq	94
   69:	iconst_1
   70:	ifeq	82
   73:	aload_2
   74:	ldc	#224; //String EMPTY
   76:	invokevirtual	#193; //Method scala/collection/mutable/StringBuilder.append:(Ljava/lang/String;)Lscala/collection/mutable/StringBuilder;
   79:	goto	180
   82:	new	#60; //class scala/MatchError
   85:	dup
   86:	aload_1
   87:	invokevirtual	#217; //Method scala/xml/dtd/ContentModel.toString:()Ljava/lang/String;
   90:	invokespecial	#68; //Method scala/MatchError."<init>":(Ljava/lang/String;)V
   93:	athrow
   94:	getstatic	#229; //Field scala/xml/dtd/PCDATA$.MODULE$:Lscala/xml/dtd/PCDATA$;
   97:	dup
   98:	ifnonnull	109
   101:	pop
   102:	aload_1
   103:	ifnull	116
   106:	goto	141
   109:	aload_1
   110:	invokevirtual	#101; //Method java/lang/Object.equals:(Ljava/lang/Object;)Z
   113:	ifeq	141
   116:	iconst_1
   117:	ifeq	129
   120:	aload_2
   121:	ldc	#231; //String (#PCDATA)
   123:	invokevirtual	#193; //Method scala/collection/mutable/StringBuilder.append:(Ljava/lang/String;)Lscala/collection/mutable/StringBuilder;
   126:	goto	180
   129:	new	#60; //class scala/MatchError
   132:	dup
   133:	aload_1
   134:	invokevirtual	#217; //Method scala/xml/dtd/ContentModel.toString:()Ljava/lang/String;
   137:	invokespecial	#68; //Method scala/MatchError."<init>":(Ljava/lang/String;)V
   140:	athrow
   141:	aload_1
   142:	instanceof	#233; //class scala/xml/dtd/ELEMENTS
   145:	ifeq	164
   148:	iconst_1
   149:	ifne	175
   152:	new	#60; //class scala/MatchError
   155:	dup
   156:	aload_1
   157:	invokevirtual	#217; //Method scala/xml/dtd/ContentModel.toString:()Ljava/lang/String;
   160:	invokespecial	#68; //Method scala/MatchError."<init>":(Ljava/lang/String;)V
   163:	athrow
   164:	aload_1
   165:	instanceof	#235; //class scala/xml/dtd/MIXED
   168:	ifeq	193
   171:	iconst_1
   172:	ifeq	181
   175:	aload_1
   176:	aload_2
   177:	invokevirtual	#238; //Method scala/xml/dtd/ContentModel.buildString:(Lscala/collection/mutable/StringBuilder;)Lscala/collection/mutable/StringBuilder;
   180:	areturn
   181:	new	#60; //class scala/MatchError
   184:	dup
   185:	aload_1
   186:	invokevirtual	#217; //Method scala/xml/dtd/ContentModel.toString:()Ljava/lang/String;
   189:	invokespecial	#68; //Method scala/MatchError."<init>":(Ljava/lang/String;)V
   192:	athrow
   193:	new	#60; //class scala/MatchError
   196:	dup
   197:	aload_1
   198:	invokevirtual	#217; //Method scala/xml/dtd/ContentModel.toString:()Ljava/lang/String;
   201:	invokespecial	#68; //Method scala/MatchError."<init>":(Ljava/lang/String;)V
   204:	athrow
  LineNumberTable: 
   line 62: 0
   line 21: 22
   line 63: 26
   line 62: 35
   line 21: 69
   line 64: 73
   line 62: 82
   line 21: 116
   line 65: 120
   line 62: 129
   line 21: 148
   line 62: 152
   line 21: 171
   line 66: 175
   line 62: 180

  LocalVariableTable: 
   Start  Length  Slot  Name   Signature
   0      205      0    this       Lscala/xml/dtd/ContentModel$;
   0      205      1    c       Lscala/xml/dtd/ContentModel;
   0      205      2    sb       Lscala/collection/mutable/StringBuilder;


public java.lang.String buildString(scala.util.regexp.Base$RegExp);
  Code:
   Stack=3, Locals=4, Args_size=2
   0:	new	#176; //class scala/collection/mutable/StringBuilder
   3:	dup
   4:	invokespecial	#265; //Method scala/collection/mutable/StringBuilder."<init>":()V
   7:	astore_3
   8:	aload_3
   9:	checkcast	#176; //class scala/collection/mutable/StringBuilder
   12:	astore_2
   13:	getstatic	#19; //Field MODULE$:Lscala/xml/dtd/ContentModel$;
   16:	aload_1
   17:	aload_2
   18:	invokevirtual	#188; //Method buildString:(Lscala/util/regexp/Base$RegExp;Lscala/collection/mutable/StringBuilder;)Lscala/collection/mutable/StringBuilder;
   21:	pop
   22:	aload_3
   23:	invokevirtual	#266; //Method scala/collection/mutable/StringBuilder.toString:()Ljava/lang/String;
   26:	areturn
  LineNumberTable: 
   line 50: 0

  LocalVariableTable: 
   Start  Length  Slot  Name   Signature
   0      27      0    this       Lscala/xml/dtd/ContentModel$;
   0      27      1    r$3       Lscala/util/regexp/Base$RegExp;
   8      18      3    sb0       Lscala/collection/mutable/StringBuilder;


public scala.collection.immutable.Set getLabels(scala.util.regexp.Base$RegExp);
  Code:
   Stack=2, Locals=2, Args_size=2
   0:	aload_0
   1:	aload_1
   2:	invokevirtual	#271; //Method traverse$1:(Lscala/util/regexp/Base$RegExp;)Lscala/collection/immutable/Set;
   5:	areturn
  LineNumberTable: 
   line 47: 0

  LocalVariableTable: 
   Start  Length  Slot  Name   Signature
   0      6      0    this       Lscala/xml/dtd/ContentModel$;
   0      6      1    r       Lscala/util/regexp/Base$RegExp;

  Signature: length = 0x2
   01 10 

public scala.xml.dtd.ContentModel parse(java.lang.String);
  Code:
   Stack=2, Locals=2, Args_size=2
   0:	getstatic	#279; //Field scala/xml/dtd/ContentModelParser$.MODULE$:Lscala/xml/dtd/ContentModelParser$;
   3:	aload_1
   4:	invokevirtual	#281; //Method scala/xml/dtd/ContentModelParser$.parse:(Ljava/lang/String;)Lscala/xml/dtd/ContentModel;
   7:	areturn
  LineNumberTable: 
   line 37: 0

  LocalVariableTable: 
   Start  Length  Slot  Name   Signature
   0      8      0    this       Lscala/xml/dtd/ContentModel$;
   0      8      1    s       Ljava/lang/String;


public boolean containsText(scala.xml.dtd.ContentModel);
  Code:
   Stack=4, Locals=3, Args_size=2
   0:	aload_1
   1:	getstatic	#229; //Field scala/xml/dtd/PCDATA$.MODULE$:Lscala/xml/dtd/PCDATA$;
   4:	astore_2
   5:	dup
   6:	ifnonnull	17
   9:	pop
   10:	aload_2
   11:	ifnull	41
   14:	goto	24
   17:	aload_2
   18:	invokevirtual	#101; //Method java/lang/Object.equals:(Ljava/lang/Object;)Z
   21:	ifne	41
   24:	getstatic	#289; //Field scala/PartialFunction$.MODULE$:Lscala/PartialFunction$;
   27:	aload_1
   28:	new	#291; //class scala/xml/dtd/ContentModel$$anonfun$isMixed$1
   31:	dup
   32:	invokespecial	#292; //Method scala/xml/dtd/ContentModel$$anonfun$isMixed$1."<init>":()V
   35:	invokevirtual	#296; //Method scala/PartialFunction$.cond:(Ljava/lang/Object;Lscala/PartialFunction;)Z
   38:	ifeq	45
   41:	iconst_1
   42:	goto	46
   45:	iconst_0
   46:	ireturn
  LineNumberTable: 
   line 36: 0

  LocalVariableTable: 
   Start  Length  Slot  Name   Signature
   0      47      0    this       Lscala/xml/dtd/ContentModel$;
   0      47      1    cm       Lscala/xml/dtd/ContentModel;


public boolean isMixed(scala.xml.dtd.ContentModel);
  Code:
   Stack=4, Locals=2, Args_size=2
   0:	getstatic	#289; //Field scala/PartialFunction$.MODULE$:Lscala/PartialFunction$;
   3:	aload_1
   4:	new	#291; //class scala/xml/dtd/ContentModel$$anonfun$isMixed$1
   7:	dup
   8:	invokespecial	#292; //Method scala/xml/dtd/ContentModel$$anonfun$isMixed$1."<init>":()V
   11:	invokevirtual	#296; //Method scala/PartialFunction$.cond:(Ljava/lang/Object;Lscala/PartialFunction;)Z
   14:	ireturn
  LineNumberTable: 
   line 35: 0

  LocalVariableTable: 
   Start  Length  Slot  Name   Signature
   0      15      0    this       Lscala/xml/dtd/ContentModel$;
   0      15      1    cm       Lscala/xml/dtd/ContentModel;


}

