Compiled from "ContentModelParser.scala"
public final class scala.xml.dtd.ContentModelParser extends java.lang.Object
  SourceFile: "ContentModelParser.scala"
  ScalaSig: length = 0x24E
   05 00 60 07 05 01 02 FFFFFF88 02 09 01 12 43 6F 6E 74
   65 6E 74 4D 6F 64 65 6C 50 61 72 73 65 72 0A 02
   03 04 01 03 64 74 64 0A 02 05 06 01 03 78 6D 6C
   0A 01 07 01 05 73 63 61 6C 61 03 00 10 02 0A 0B
   0D 01 02 06 08 0C 02 FFFFFF84 FFFFFF80 FFFFFF80 FFFFFF88 02 0D 02 12 43
   6F 6E 74 65 6E 74 4D 6F 64 65 6C 50 61 72 73 65
   72 13 03 0B 0E 11 10 02 0A 0F 09 02 10 02 02 07
   53 63 61 6E 6E 65 72 10 02 12 13 0D 01 06 09 02
   14 06 02 0B 53 63 61 6C 61 4F 62 6A 65 63 74 08
   05 16 0B FFFFFF84 00 17 01 06 3C 69 6E 69 74 3E 14 01
   09 08 05 19 0B FFFFFF84 00 1A 01 05 70 61 72 73 65 14
   02 1B 1E 10 02 0A 1C 09 02 1D 02 02 0C 43 6F 6E
   74 65 6E 74 4D 6F 64 65 6C 08 05 1F 18 FFFFFFC0 00 20
   01 01 73 10 02 21 24 0E 02 12 22 09 02 23 06 01
   06 50 72 65 64 65 66 09 02 25 26 02 06 53 74 72
   69 6E 67 0A 02 23 06 08 05 28 0B FFFFFF84 00 29 01 06
   61 63 63 65 70 74 14 02 2A 2D 10 02 12 2B 09 02
   2C 06 02 04 55 6E 69 74 08 05 2E 27 FFFFFFC0 00 2F 01
   03 74 6F 6B 10 02 12 30 09 02 31 06 02 03 49 6E
   74 08 05 33 0B FFFFFF84 00 34 01 0B 6D 61 79 62 65 53
   75 66 66 69 78 14 02 35 41 10 02 36 39 0E 02 0A
   37 09 02 38 02 01 0C 43 6F 6E 74 65 6E 74 4D 6F
   64 65 6C 09 02 3A 3B 02 06 52 65 67 45 78 70 09
   02 3C 3D 02 04 42 61 73 65 0A 02 3E 3F 01 06 72
   65 67 65 78 70 0A 02 40 06 01 04 75 74 69 6C 08
   05 1F 32 FFFFFFC0 00 35 08 05 43 0B FFFFFF84 00 44 01 0B 63
   6F 6E 74 65 6E 74 73 70 65 63 15 01 1B 08 05 46
   0B FFFFFF84 00 47 01 04 73 4F 70 74 15 01 2A 08 05 3E
   0B FFFFFF84 00 49 15 01 35 08 05 4B 0B FFFFFF84 00 4C 01 07
   73 65 71 52 65 73 74 14 02 35 4D 08 05 4E 4A FFFFFFC0
   00 35 01 01 70 08 05 50 0B FFFFFF84 00 51 01 0A 63 68
   6F 69 63 65 52 65 73 74 14 02 52 55 10 02 36 53
   09 02 54 3B 02 03 41 6C 74 08 05 4E 4F FFFFFFC0 00 35
   08 05 57 0B FFFFFF84 00 49 01 08 70 61 72 74 69 63 6C
   65 08 05 59 0B FFFFFF84 00 5A 01 04 61 74 6F 6D 15 01
   5B 10 02 36 5C 09 02 5D 5E 02 06 4C 65 74 74 65
   72 09 02 5F 3D 02 07 57 6F 72 64 45 78 70 
  InnerClass: 
   public #174= #171 of #173; //Alt=class scala/util/regexp/Base$Alt of class scala/util/regexp/Base
   public abstract #177= #176 of #173; //RegExp=class scala/util/regexp/Base$RegExp of class scala/util/regexp/Base
   public #182= #179 of #181; //Letter=class scala/util/regexp/WordExp$Letter of class scala/util/regexp/WordExp
  minor version: 0
  major version: 49
  Constant pool:
const #1 = Asciz	SourceFile;
const #2 = Asciz	ContentModelParser.scala;
const #3 = Asciz	atom;
const #4 = Asciz	()Lscala/util/regexp/WordExp$Letter;;
const #5 = Asciz	Code;
const #6 = Asciz	scala/xml/dtd/ContentModelParser$;
const #7 = class	#6;	//  scala/xml/dtd/ContentModelParser$
const #8 = Asciz	MODULE$;
const #9 = Asciz	Lscala/xml/dtd/ContentModelParser$;;
const #10 = NameAndType	#8:#9;//  MODULE$:Lscala/xml/dtd/ContentModelParser$;
const #11 = Field	#7.#10;	//  scala/xml/dtd/ContentModelParser$.MODULE$:Lscala/xml/dtd/ContentModelParser$;
const #12 = NameAndType	#3:#4;//  atom:()Lscala/util/regexp/WordExp$Letter;
const #13 = Method	#7.#12;	//  scala/xml/dtd/ContentModelParser$.atom:()Lscala/util/regexp/WordExp$Letter;
const #14 = Asciz	particle;
const #15 = Asciz	()Lscala/util/regexp/Base$RegExp;;
const #16 = NameAndType	#14:#15;//  particle:()Lscala/util/regexp/Base$RegExp;
const #17 = Method	#7.#16;	//  scala/xml/dtd/ContentModelParser$.particle:()Lscala/util/regexp/Base$RegExp;
const #18 = Asciz	choiceRest;
const #19 = Asciz	(Lscala/util/regexp/Base$RegExp;)Lscala/util/regexp/Base$Alt;;
const #20 = NameAndType	#18:#19;//  choiceRest:(Lscala/util/regexp/Base$RegExp;)Lscala/util/regexp/Base$Alt;
const #21 = Method	#7.#20;	//  scala/xml/dtd/ContentModelParser$.choiceRest:(Lscala/util/regexp/Base$RegExp;)Lscala/util/regexp/Base$Alt;
const #22 = Asciz	seqRest;
const #23 = Asciz	(Lscala/util/regexp/Base$RegExp;)Lscala/util/regexp/Base$RegExp;;
const #24 = NameAndType	#22:#23;//  seqRest:(Lscala/util/regexp/Base$RegExp;)Lscala/util/regexp/Base$RegExp;
const #25 = Method	#7.#24;	//  scala/xml/dtd/ContentModelParser$.seqRest:(Lscala/util/regexp/Base$RegExp;)Lscala/util/regexp/Base$RegExp;
const #26 = Asciz	regexp;
const #27 = NameAndType	#26:#15;//  regexp:()Lscala/util/regexp/Base$RegExp;
const #28 = Method	#7.#27;	//  scala/xml/dtd/ContentModelParser$.regexp:()Lscala/util/regexp/Base$RegExp;
const #29 = Asciz	sOpt;
const #30 = Asciz	()V;
const #31 = NameAndType	#29:#30;//  sOpt:()V
const #32 = Method	#7.#31;	//  scala/xml/dtd/ContentModelParser$.sOpt:()V
const #33 = Asciz	contentspec;
const #34 = Asciz	()Lscala/xml/dtd/ContentModel;;
const #35 = NameAndType	#33:#34;//  contentspec:()Lscala/xml/dtd/ContentModel;
const #36 = Method	#7.#35;	//  scala/xml/dtd/ContentModelParser$.contentspec:()Lscala/xml/dtd/ContentModel;
const #37 = Asciz	maybeSuffix;
const #38 = NameAndType	#37:#23;//  maybeSuffix:(Lscala/util/regexp/Base$RegExp;)Lscala/util/regexp/Base$RegExp;
const #39 = Method	#7.#38;	//  scala/xml/dtd/ContentModelParser$.maybeSuffix:(Lscala/util/regexp/Base$RegExp;)Lscala/util/regexp/Base$RegExp;
const #40 = Asciz	accept;
const #41 = Asciz	(I)V;
const #42 = NameAndType	#40:#41;//  accept:(I)V
const #43 = Method	#7.#42;	//  scala/xml/dtd/ContentModelParser$.accept:(I)V
const #44 = Asciz	parse;
const #45 = Asciz	(Ljava/lang/String;)Lscala/xml/dtd/ContentModel;;
const #46 = NameAndType	#44:#45;//  parse:(Ljava/lang/String;)Lscala/xml/dtd/ContentModel;
const #47 = Method	#7.#46;	//  scala/xml/dtd/ContentModelParser$.parse:(Ljava/lang/String;)Lscala/xml/dtd/ContentModel;
const #48 = Asciz	checkPubID;
const #49 = Asciz	(Ljava/lang/String;)Z;
const #50 = NameAndType	#48:#49;//  checkPubID:(Ljava/lang/String;)Z
const #51 = Method	#7.#50;	//  scala/xml/dtd/ContentModelParser$.checkPubID:(Ljava/lang/String;)Z
const #52 = Asciz	checkSysID;
const #53 = NameAndType	#52:#49;//  checkSysID:(Ljava/lang/String;)Z
const #54 = Method	#7.#53;	//  scala/xml/dtd/ContentModelParser$.checkSysID:(Ljava/lang/String;)Z
const #55 = Asciz	isValidIANAEncoding;
const #56 = Asciz	(Lscala/collection/Seq;)Z;
const #57 = NameAndType	#55:#56;//  isValidIANAEncoding:(Lscala/collection/Seq;)Z
const #58 = Method	#7.#57;	//  scala/xml/dtd/ContentModelParser$.isValidIANAEncoding:(Lscala/collection/Seq;)Z
const #59 = Asciz	isPubIDChar;
const #60 = Asciz	(C)Z;
const #61 = NameAndType	#59:#60;//  isPubIDChar:(C)Z
const #62 = Method	#7.#61;	//  scala/xml/dtd/ContentModelParser$.isPubIDChar:(C)Z
const #63 = Asciz	isName;
const #64 = NameAndType	#63:#49;//  isName:(Ljava/lang/String;)Z
const #65 = Method	#7.#64;	//  scala/xml/dtd/ContentModelParser$.isName:(Ljava/lang/String;)Z
const #66 = Asciz	isNameStart;
const #67 = NameAndType	#66:#60;//  isNameStart:(C)Z
const #68 = Method	#7.#67;	//  scala/xml/dtd/ContentModelParser$.isNameStart:(C)Z
const #69 = Asciz	isNameChar;
const #70 = NameAndType	#69:#60;//  isNameChar:(C)Z
const #71 = Method	#7.#70;	//  scala/xml/dtd/ContentModelParser$.isNameChar:(C)Z
const #72 = Asciz	isAlphaDigit;
const #73 = NameAndType	#72:#60;//  isAlphaDigit:(C)Z
const #74 = Method	#7.#73;	//  scala/xml/dtd/ContentModelParser$.isAlphaDigit:(C)Z
const #75 = Asciz	isAlpha;
const #76 = NameAndType	#75:#60;//  isAlpha:(C)Z
const #77 = Method	#7.#76;	//  scala/xml/dtd/ContentModelParser$.isAlpha:(C)Z
const #78 = Asciz	isSpace;
const #79 = NameAndType	#78:#56;//  isSpace:(Lscala/collection/Seq;)Z
const #80 = Method	#7.#79;	//  scala/xml/dtd/ContentModelParser$.isSpace:(Lscala/collection/Seq;)Z
const #81 = NameAndType	#78:#60;//  isSpace:(C)Z
const #82 = Method	#7.#81;	//  scala/xml/dtd/ContentModelParser$.isSpace:(C)Z
const #83 = Asciz	name;
const #84 = Asciz	()I;
const #85 = NameAndType	#83:#84;//  name:()I
const #86 = Method	#7.#85;	//  scala/xml/dtd/ContentModelParser$.name:()I
const #87 = Asciz	readToken;
const #88 = NameAndType	#87:#84;//  readToken:()I
const #89 = Method	#7.#88;	//  scala/xml/dtd/ContentModelParser$.readToken:()I
const #90 = Asciz	accS;
const #91 = Asciz	(Lscala/collection/Seq;)V;
const #92 = NameAndType	#90:#91;//  accS:(Lscala/collection/Seq;)V
const #93 = Method	#7.#92;	//  scala/xml/dtd/ContentModelParser$.accS:(Lscala/collection/Seq;)V
const #94 = Asciz	(Lscala/collection/Seq<Ljava/lang/Character;>;)V;
const #95 = Asciz	Signature;
const #96 = Asciz	acc;
const #97 = Asciz	(C)V;
const #98 = NameAndType	#96:#97;//  acc:(C)V
const #99 = Method	#7.#98;	//  scala/xml/dtd/ContentModelParser$.acc:(C)V
const #100 = Asciz	next;
const #101 = NameAndType	#100:#30;//  next:()V
const #102 = Method	#7.#101;	//  scala/xml/dtd/ContentModelParser$.next:()V
const #103 = Asciz	isIdentChar;
const #104 = Asciz	()Z;
const #105 = NameAndType	#103:#104;//  isIdentChar:()Z
const #106 = Method	#7.#105;	//  scala/xml/dtd/ContentModelParser$.isIdentChar:()Z
const #107 = Asciz	nextToken;
const #108 = NameAndType	#107:#30;//  nextToken:()V
const #109 = Method	#7.#108;	//  scala/xml/dtd/ContentModelParser$.nextToken:()V
const #110 = Asciz	initScanner;
const #111 = Asciz	(Ljava/lang/String;)V;
const #112 = NameAndType	#110:#111;//  initScanner:(Ljava/lang/String;)V
const #113 = Method	#7.#112;	//  scala/xml/dtd/ContentModelParser$.initScanner:(Ljava/lang/String;)V
const #114 = Asciz	value_$eq;
const #115 = NameAndType	#114:#111;//  value_$eq:(Ljava/lang/String;)V
const #116 = Method	#7.#115;	//  scala/xml/dtd/ContentModelParser$.value_$eq:(Ljava/lang/String;)V
const #117 = Asciz	value;
const #118 = Asciz	()Ljava/lang/String;;
const #119 = NameAndType	#117:#118;//  value:()Ljava/lang/String;
const #120 = Method	#7.#119;	//  scala/xml/dtd/ContentModelParser$.value:()Ljava/lang/String;
const #121 = Asciz	token_$eq;
const #122 = NameAndType	#121:#41;//  token_$eq:(I)V
const #123 = Method	#7.#122;	//  scala/xml/dtd/ContentModelParser$.token_$eq:(I)V
const #124 = Asciz	token;
const #125 = NameAndType	#124:#84;//  token:()I
const #126 = Method	#7.#125;	//  scala/xml/dtd/ContentModelParser$.token:()I
const #127 = Asciz	ENDCH;
const #128 = Asciz	()C;
const #129 = NameAndType	#127:#128;//  ENDCH:()C
const #130 = Method	#7.#129;	//  scala/xml/dtd/ContentModelParser$.ENDCH:()C
const #131 = Asciz	token2string;
const #132 = Asciz	(I)Ljava/lang/String;;
const #133 = NameAndType	#131:#132;//  token2string:(I)Ljava/lang/String;
const #134 = Method	#7.#133;	//  scala/xml/dtd/ContentModelParser$.token2string:(I)Ljava/lang/String;
const #135 = Asciz	S;
const #136 = NameAndType	#135:#84;//  S:()I
const #137 = Method	#7.#136;	//  scala/xml/dtd/ContentModelParser$.S:()I
const #138 = Asciz	END;
const #139 = NameAndType	#138:#84;//  END:()I
const #140 = Method	#7.#139;	//  scala/xml/dtd/ContentModelParser$.END:()I
const #141 = Asciz	CHOICE;
const #142 = NameAndType	#141:#84;//  CHOICE:()I
const #143 = Method	#7.#142;	//  scala/xml/dtd/ContentModelParser$.CHOICE:()I
const #144 = Asciz	OPT;
const #145 = NameAndType	#144:#84;//  OPT:()I
const #146 = Method	#7.#145;	//  scala/xml/dtd/ContentModelParser$.OPT:()I
const #147 = Asciz	PLUS;
const #148 = NameAndType	#147:#84;//  PLUS:()I
const #149 = Method	#7.#148;	//  scala/xml/dtd/ContentModelParser$.PLUS:()I
const #150 = Asciz	STAR;
const #151 = NameAndType	#150:#84;//  STAR:()I
const #152 = Method	#7.#151;	//  scala/xml/dtd/ContentModelParser$.STAR:()I
const #153 = Asciz	COMMA;
const #154 = NameAndType	#153:#84;//  COMMA:()I
const #155 = Method	#7.#154;	//  scala/xml/dtd/ContentModelParser$.COMMA:()I
const #156 = Asciz	RPAREN;
const #157 = NameAndType	#156:#84;//  RPAREN:()I
const #158 = Method	#7.#157;	//  scala/xml/dtd/ContentModelParser$.RPAREN:()I
const #159 = Asciz	LPAREN;
const #160 = NameAndType	#159:#84;//  LPAREN:()I
const #161 = Method	#7.#160;	//  scala/xml/dtd/ContentModelParser$.LPAREN:()I
const #162 = Asciz	NAME;
const #163 = NameAndType	#162:#84;//  NAME:()I
const #164 = Method	#7.#163;	//  scala/xml/dtd/ContentModelParser$.NAME:()I
const #165 = Asciz	TOKEN_PCDATA;
const #166 = NameAndType	#165:#84;//  TOKEN_PCDATA:()I
const #167 = Method	#7.#166;	//  scala/xml/dtd/ContentModelParser$.TOKEN_PCDATA:()I
const #168 = Asciz	ScalaSig;
const #169 = Asciz	InnerClasses;
const #170 = Asciz	scala/util/regexp/Base$Alt;
const #171 = class	#170;	//  scala/util/regexp/Base$Alt
const #172 = Asciz	scala/util/regexp/Base;
const #173 = class	#172;	//  scala/util/regexp/Base
const #174 = Asciz	Alt;
const #175 = Asciz	scala/util/regexp/Base$RegExp;
const #176 = class	#175;	//  scala/util/regexp/Base$RegExp
const #177 = Asciz	RegExp;
const #178 = Asciz	scala/util/regexp/WordExp$Letter;
const #179 = class	#178;	//  scala/util/regexp/WordExp$Letter
const #180 = Asciz	scala/util/regexp/WordExp;
const #181 = class	#180;	//  scala/util/regexp/WordExp
const #182 = Asciz	Letter;
const #183 = Asciz	scala/xml/dtd/ContentModelParser;
const #184 = class	#183;	//  scala/xml/dtd/ContentModelParser
const #185 = Asciz	java/lang/Object;
const #186 = class	#185;	//  java/lang/Object

{
public static final scala.util.regexp.WordExp$Letter atom();
  Code:
   Stack=1, Locals=0, Args_size=0
   0:	getstatic	#11; //Field scala/xml/dtd/ContentModelParser$.MODULE$:Lscala/xml/dtd/ContentModelParser$;
   3:	invokevirtual	#13; //Method scala/xml/dtd/ContentModelParser$.atom:()Lscala/util/regexp/WordExp$Letter;
   6:	areturn

public static final scala.util.regexp.Base$RegExp particle();
  Code:
   Stack=1, Locals=0, Args_size=0
   0:	getstatic	#11; //Field scala/xml/dtd/ContentModelParser$.MODULE$:Lscala/xml/dtd/ContentModelParser$;
   3:	invokevirtual	#17; //Method scala/xml/dtd/ContentModelParser$.particle:()Lscala/util/regexp/Base$RegExp;
   6:	areturn

public static final scala.util.regexp.Base$Alt choiceRest(scala.util.regexp.Base$RegExp);
  Code:
   Stack=2, Locals=1, Args_size=1
   0:	getstatic	#11; //Field scala/xml/dtd/ContentModelParser$.MODULE$:Lscala/xml/dtd/ContentModelParser$;
   3:	aload_0
   4:	invokevirtual	#21; //Method scala/xml/dtd/ContentModelParser$.choiceRest:(Lscala/util/regexp/Base$RegExp;)Lscala/util/regexp/Base$Alt;
   7:	areturn

public static final scala.util.regexp.Base$RegExp seqRest(scala.util.regexp.Base$RegExp);
  Code:
   Stack=2, Locals=1, Args_size=1
   0:	getstatic	#11; //Field scala/xml/dtd/ContentModelParser$.MODULE$:Lscala/xml/dtd/ContentModelParser$;
   3:	aload_0
   4:	invokevirtual	#25; //Method scala/xml/dtd/ContentModelParser$.seqRest:(Lscala/util/regexp/Base$RegExp;)Lscala/util/regexp/Base$RegExp;
   7:	areturn

public static final scala.util.regexp.Base$RegExp regexp();
  Code:
   Stack=1, Locals=0, Args_size=0
   0:	getstatic	#11; //Field scala/xml/dtd/ContentModelParser$.MODULE$:Lscala/xml/dtd/ContentModelParser$;
   3:	invokevirtual	#28; //Method scala/xml/dtd/ContentModelParser$.regexp:()Lscala/util/regexp/Base$RegExp;
   6:	areturn

public static final void sOpt();
  Code:
   Stack=1, Locals=0, Args_size=0
   0:	getstatic	#11; //Field scala/xml/dtd/ContentModelParser$.MODULE$:Lscala/xml/dtd/ContentModelParser$;
   3:	invokevirtual	#32; //Method scala/xml/dtd/ContentModelParser$.sOpt:()V
   6:	return

public static final scala.xml.dtd.ContentModel contentspec();
  Code:
   Stack=1, Locals=0, Args_size=0
   0:	getstatic	#11; //Field scala/xml/dtd/ContentModelParser$.MODULE$:Lscala/xml/dtd/ContentModelParser$;
   3:	invokevirtual	#36; //Method scala/xml/dtd/ContentModelParser$.contentspec:()Lscala/xml/dtd/ContentModel;
   6:	areturn

public static final scala.util.regexp.Base$RegExp maybeSuffix(scala.util.regexp.Base$RegExp);
  Code:
   Stack=2, Locals=1, Args_size=1
   0:	getstatic	#11; //Field scala/xml/dtd/ContentModelParser$.MODULE$:Lscala/xml/dtd/ContentModelParser$;
   3:	aload_0
   4:	invokevirtual	#39; //Method scala/xml/dtd/ContentModelParser$.maybeSuffix:(Lscala/util/regexp/Base$RegExp;)Lscala/util/regexp/Base$RegExp;
   7:	areturn

public static final void accept(int);
  Code:
   Stack=2, Locals=1, Args_size=1
   0:	getstatic	#11; //Field scala/xml/dtd/ContentModelParser$.MODULE$:Lscala/xml/dtd/ContentModelParser$;
   3:	iload_0
   4:	invokevirtual	#43; //Method scala/xml/dtd/ContentModelParser$.accept:(I)V
   7:	return

public static final scala.xml.dtd.ContentModel parse(java.lang.String);
  Code:
   Stack=2, Locals=1, Args_size=1
   0:	getstatic	#11; //Field scala/xml/dtd/ContentModelParser$.MODULE$:Lscala/xml/dtd/ContentModelParser$;
   3:	aload_0
   4:	invokevirtual	#47; //Method scala/xml/dtd/ContentModelParser$.parse:(Ljava/lang/String;)Lscala/xml/dtd/ContentModel;
   7:	areturn

public static final boolean checkPubID(java.lang.String);
  Code:
   Stack=2, Locals=1, Args_size=1
   0:	getstatic	#11; //Field scala/xml/dtd/ContentModelParser$.MODULE$:Lscala/xml/dtd/ContentModelParser$;
   3:	aload_0
   4:	invokevirtual	#51; //Method scala/xml/dtd/ContentModelParser$.checkPubID:(Ljava/lang/String;)Z
   7:	ireturn

public static final boolean checkSysID(java.lang.String);
  Code:
   Stack=2, Locals=1, Args_size=1
   0:	getstatic	#11; //Field scala/xml/dtd/ContentModelParser$.MODULE$:Lscala/xml/dtd/ContentModelParser$;
   3:	aload_0
   4:	invokevirtual	#54; //Method scala/xml/dtd/ContentModelParser$.checkSysID:(Ljava/lang/String;)Z
   7:	ireturn

public static final boolean isValidIANAEncoding(scala.collection.Seq);
  Code:
   Stack=2, Locals=1, Args_size=1
   0:	getstatic	#11; //Field scala/xml/dtd/ContentModelParser$.MODULE$:Lscala/xml/dtd/ContentModelParser$;
   3:	aload_0
   4:	invokevirtual	#58; //Method scala/xml/dtd/ContentModelParser$.isValidIANAEncoding:(Lscala/collection/Seq;)Z
   7:	ireturn

public static final boolean isPubIDChar(char);
  Code:
   Stack=2, Locals=1, Args_size=1
   0:	getstatic	#11; //Field scala/xml/dtd/ContentModelParser$.MODULE$:Lscala/xml/dtd/ContentModelParser$;
   3:	iload_0
   4:	invokevirtual	#62; //Method scala/xml/dtd/ContentModelParser$.isPubIDChar:(C)Z
   7:	ireturn

public static final boolean isName(java.lang.String);
  Code:
   Stack=2, Locals=1, Args_size=1
   0:	getstatic	#11; //Field scala/xml/dtd/ContentModelParser$.MODULE$:Lscala/xml/dtd/ContentModelParser$;
   3:	aload_0
   4:	invokevirtual	#65; //Method scala/xml/dtd/ContentModelParser$.isName:(Ljava/lang/String;)Z
   7:	ireturn

public static final boolean isNameStart(char);
  Code:
   Stack=2, Locals=1, Args_size=1
   0:	getstatic	#11; //Field scala/xml/dtd/ContentModelParser$.MODULE$:Lscala/xml/dtd/ContentModelParser$;
   3:	iload_0
   4:	invokevirtual	#68; //Method scala/xml/dtd/ContentModelParser$.isNameStart:(C)Z
   7:	ireturn

public static final boolean isNameChar(char);
  Code:
   Stack=2, Locals=1, Args_size=1
   0:	getstatic	#11; //Field scala/xml/dtd/ContentModelParser$.MODULE$:Lscala/xml/dtd/ContentModelParser$;
   3:	iload_0
   4:	invokevirtual	#71; //Method scala/xml/dtd/ContentModelParser$.isNameChar:(C)Z
   7:	ireturn

public static final boolean isAlphaDigit(char);
  Code:
   Stack=2, Locals=1, Args_size=1
   0:	getstatic	#11; //Field scala/xml/dtd/ContentModelParser$.MODULE$:Lscala/xml/dtd/ContentModelParser$;
   3:	iload_0
   4:	invokevirtual	#74; //Method scala/xml/dtd/ContentModelParser$.isAlphaDigit:(C)Z
   7:	ireturn

public static final boolean isAlpha(char);
  Code:
   Stack=2, Locals=1, Args_size=1
   0:	getstatic	#11; //Field scala/xml/dtd/ContentModelParser$.MODULE$:Lscala/xml/dtd/ContentModelParser$;
   3:	iload_0
   4:	invokevirtual	#77; //Method scala/xml/dtd/ContentModelParser$.isAlpha:(C)Z
   7:	ireturn

public static final boolean isSpace(scala.collection.Seq);
  Code:
   Stack=2, Locals=1, Args_size=1
   0:	getstatic	#11; //Field scala/xml/dtd/ContentModelParser$.MODULE$:Lscala/xml/dtd/ContentModelParser$;
   3:	aload_0
   4:	invokevirtual	#80; //Method scala/xml/dtd/ContentModelParser$.isSpace:(Lscala/collection/Seq;)Z
   7:	ireturn

public static final boolean isSpace(char);
  Code:
   Stack=2, Locals=1, Args_size=1
   0:	getstatic	#11; //Field scala/xml/dtd/ContentModelParser$.MODULE$:Lscala/xml/dtd/ContentModelParser$;
   3:	iload_0
   4:	invokevirtual	#82; //Method scala/xml/dtd/ContentModelParser$.isSpace:(C)Z
   7:	ireturn

public static final int name();
  Code:
   Stack=1, Locals=0, Args_size=0
   0:	getstatic	#11; //Field scala/xml/dtd/ContentModelParser$.MODULE$:Lscala/xml/dtd/ContentModelParser$;
   3:	invokevirtual	#86; //Method scala/xml/dtd/ContentModelParser$.name:()I
   6:	ireturn

public static final int readToken();
  Code:
   Stack=1, Locals=0, Args_size=0
   0:	getstatic	#11; //Field scala/xml/dtd/ContentModelParser$.MODULE$:Lscala/xml/dtd/ContentModelParser$;
   3:	invokevirtual	#89; //Method scala/xml/dtd/ContentModelParser$.readToken:()I
   6:	ireturn

public static final void accS(scala.collection.Seq);
  Code:
   Stack=2, Locals=1, Args_size=1
   0:	getstatic	#11; //Field scala/xml/dtd/ContentModelParser$.MODULE$:Lscala/xml/dtd/ContentModelParser$;
   3:	aload_0
   4:	invokevirtual	#93; //Method scala/xml/dtd/ContentModelParser$.accS:(Lscala/collection/Seq;)V
   7:	return
  Signature: length = 0x2
   00 5E 

public static final void acc(char);
  Code:
   Stack=2, Locals=1, Args_size=1
   0:	getstatic	#11; //Field scala/xml/dtd/ContentModelParser$.MODULE$:Lscala/xml/dtd/ContentModelParser$;
   3:	iload_0
   4:	invokevirtual	#99; //Method scala/xml/dtd/ContentModelParser$.acc:(C)V
   7:	return

public static final void next();
  Code:
   Stack=1, Locals=0, Args_size=0
   0:	getstatic	#11; //Field scala/xml/dtd/ContentModelParser$.MODULE$:Lscala/xml/dtd/ContentModelParser$;
   3:	invokevirtual	#102; //Method scala/xml/dtd/ContentModelParser$.next:()V
   6:	return

public static final boolean isIdentChar();
  Code:
   Stack=1, Locals=0, Args_size=0
   0:	getstatic	#11; //Field scala/xml/dtd/ContentModelParser$.MODULE$:Lscala/xml/dtd/ContentModelParser$;
   3:	invokevirtual	#106; //Method scala/xml/dtd/ContentModelParser$.isIdentChar:()Z
   6:	ireturn

public static final void nextToken();
  Code:
   Stack=1, Locals=0, Args_size=0
   0:	getstatic	#11; //Field scala/xml/dtd/ContentModelParser$.MODULE$:Lscala/xml/dtd/ContentModelParser$;
   3:	invokevirtual	#109; //Method scala/xml/dtd/ContentModelParser$.nextToken:()V
   6:	return

public static final void initScanner(java.lang.String);
  Code:
   Stack=2, Locals=1, Args_size=1
   0:	getstatic	#11; //Field scala/xml/dtd/ContentModelParser$.MODULE$:Lscala/xml/dtd/ContentModelParser$;
   3:	aload_0
   4:	invokevirtual	#113; //Method scala/xml/dtd/ContentModelParser$.initScanner:(Ljava/lang/String;)V
   7:	return

public static final void value_$eq(java.lang.String);
  Code:
   Stack=2, Locals=1, Args_size=1
   0:	getstatic	#11; //Field scala/xml/dtd/ContentModelParser$.MODULE$:Lscala/xml/dtd/ContentModelParser$;
   3:	aload_0
   4:	invokevirtual	#116; //Method scala/xml/dtd/ContentModelParser$.value_$eq:(Ljava/lang/String;)V
   7:	return

public static final java.lang.String value();
  Code:
   Stack=1, Locals=0, Args_size=0
   0:	getstatic	#11; //Field scala/xml/dtd/ContentModelParser$.MODULE$:Lscala/xml/dtd/ContentModelParser$;
   3:	invokevirtual	#120; //Method scala/xml/dtd/ContentModelParser$.value:()Ljava/lang/String;
   6:	areturn

public static final void token_$eq(int);
  Code:
   Stack=2, Locals=1, Args_size=1
   0:	getstatic	#11; //Field scala/xml/dtd/ContentModelParser$.MODULE$:Lscala/xml/dtd/ContentModelParser$;
   3:	iload_0
   4:	invokevirtual	#123; //Method scala/xml/dtd/ContentModelParser$.token_$eq:(I)V
   7:	return

public static final int token();
  Code:
   Stack=1, Locals=0, Args_size=0
   0:	getstatic	#11; //Field scala/xml/dtd/ContentModelParser$.MODULE$:Lscala/xml/dtd/ContentModelParser$;
   3:	invokevirtual	#126; //Method scala/xml/dtd/ContentModelParser$.token:()I
   6:	ireturn

public static final char ENDCH();
  Code:
   Stack=1, Locals=0, Args_size=0
   0:	getstatic	#11; //Field scala/xml/dtd/ContentModelParser$.MODULE$:Lscala/xml/dtd/ContentModelParser$;
   3:	invokevirtual	#130; //Method scala/xml/dtd/ContentModelParser$.ENDCH:()C
   6:	ireturn

public static final java.lang.String token2string(int);
  Code:
   Stack=2, Locals=1, Args_size=1
   0:	getstatic	#11; //Field scala/xml/dtd/ContentModelParser$.MODULE$:Lscala/xml/dtd/ContentModelParser$;
   3:	iload_0
   4:	invokevirtual	#134; //Method scala/xml/dtd/ContentModelParser$.token2string:(I)Ljava/lang/String;
   7:	areturn

public static final int S();
  Code:
   Stack=1, Locals=0, Args_size=0
   0:	getstatic	#11; //Field scala/xml/dtd/ContentModelParser$.MODULE$:Lscala/xml/dtd/ContentModelParser$;
   3:	invokevirtual	#137; //Method scala/xml/dtd/ContentModelParser$.S:()I
   6:	ireturn

public static final int END();
  Code:
   Stack=1, Locals=0, Args_size=0
   0:	getstatic	#11; //Field scala/xml/dtd/ContentModelParser$.MODULE$:Lscala/xml/dtd/ContentModelParser$;
   3:	invokevirtual	#140; //Method scala/xml/dtd/ContentModelParser$.END:()I
   6:	ireturn

public static final int CHOICE();
  Code:
   Stack=1, Locals=0, Args_size=0
   0:	getstatic	#11; //Field scala/xml/dtd/ContentModelParser$.MODULE$:Lscala/xml/dtd/ContentModelParser$;
   3:	invokevirtual	#143; //Method scala/xml/dtd/ContentModelParser$.CHOICE:()I
   6:	ireturn

public static final int OPT();
  Code:
   Stack=1, Locals=0, Args_size=0
   0:	getstatic	#11; //Field scala/xml/dtd/ContentModelParser$.MODULE$:Lscala/xml/dtd/ContentModelParser$;
   3:	invokevirtual	#146; //Method scala/xml/dtd/ContentModelParser$.OPT:()I
   6:	ireturn

public static final int PLUS();
  Code:
   Stack=1, Locals=0, Args_size=0
   0:	getstatic	#11; //Field scala/xml/dtd/ContentModelParser$.MODULE$:Lscala/xml/dtd/ContentModelParser$;
   3:	invokevirtual	#149; //Method scala/xml/dtd/ContentModelParser$.PLUS:()I
   6:	ireturn

public static final int STAR();
  Code:
   Stack=1, Locals=0, Args_size=0
   0:	getstatic	#11; //Field scala/xml/dtd/ContentModelParser$.MODULE$:Lscala/xml/dtd/ContentModelParser$;
   3:	invokevirtual	#152; //Method scala/xml/dtd/ContentModelParser$.STAR:()I
   6:	ireturn

public static final int COMMA();
  Code:
   Stack=1, Locals=0, Args_size=0
   0:	getstatic	#11; //Field scala/xml/dtd/ContentModelParser$.MODULE$:Lscala/xml/dtd/ContentModelParser$;
   3:	invokevirtual	#155; //Method scala/xml/dtd/ContentModelParser$.COMMA:()I
   6:	ireturn

public static final int RPAREN();
  Code:
   Stack=1, Locals=0, Args_size=0
   0:	getstatic	#11; //Field scala/xml/dtd/ContentModelParser$.MODULE$:Lscala/xml/dtd/ContentModelParser$;
   3:	invokevirtual	#158; //Method scala/xml/dtd/ContentModelParser$.RPAREN:()I
   6:	ireturn

public static final int LPAREN();
  Code:
   Stack=1, Locals=0, Args_size=0
   0:	getstatic	#11; //Field scala/xml/dtd/ContentModelParser$.MODULE$:Lscala/xml/dtd/ContentModelParser$;
   3:	invokevirtual	#161; //Method scala/xml/dtd/ContentModelParser$.LPAREN:()I
   6:	ireturn

public static final int NAME();
  Code:
   Stack=1, Locals=0, Args_size=0
   0:	getstatic	#11; //Field scala/xml/dtd/ContentModelParser$.MODULE$:Lscala/xml/dtd/ContentModelParser$;
   3:	invokevirtual	#164; //Method scala/xml/dtd/ContentModelParser$.NAME:()I
   6:	ireturn

public static final int TOKEN_PCDATA();
  Code:
   Stack=1, Locals=0, Args_size=0
   0:	getstatic	#11; //Field scala/xml/dtd/ContentModelParser$.MODULE$:Lscala/xml/dtd/ContentModelParser$;
   3:	invokevirtual	#167; //Method scala/xml/dtd/ContentModelParser$.TOKEN_PCDATA:()I
   6:	ireturn

}

