Compiled from "ContentModelParser.scala"
public final class scala.xml.dtd.ContentModelParser$ extends scala.xml.dtd.Scanner implements scala.ScalaObject
  SourceFile: "ContentModelParser.scala"
  Scala: length = 0x
   
  InnerClass: 
   public #130= #244 of #246; //Alt=class scala/util/regexp/Base$Alt of class scala/util/regexp/Base
   public #247= #221 of #246; //Star=class scala/util/regexp/Base$Star of class scala/util/regexp/Base
   public abstract #248= #108 of #246; //RegExp=class scala/util/regexp/Base$RegExp of class scala/util/regexp/Base
   public abstract #253= #250 of #252; //Label=class scala/util/regexp/WordExp$Label of class scala/util/regexp/WordExp
   public #254= #27 of #252; //Letter=class scala/util/regexp/WordExp$Letter of class scala/util/regexp/WordExp
   public #257= #34 of #256; //ElemName=class scala/xml/dtd/ContentModel$ElemName of class scala/xml/dtd/ContentModel
  minor version: 0
  major version: 49
  Constant pool:
const #1 = Asciz	SourceFile;
const #2 = Asciz	ContentModelParser.scala;
const #3 = Asciz	Scala;
const #4 = Asciz	MODULE$;
const #5 = Asciz	Lscala/xml/dtd/ContentModelParser$;;
const #6 = Asciz	<clinit>;
const #7 = Asciz	()V;
const #8 = Asciz	Code;
const #9 = Asciz	scala/xml/dtd/ContentModelParser$;
const #10 = class	#9;	//  scala/xml/dtd/ContentModelParser$
const #11 = Asciz	<init>;
const #12 = NameAndType	#11:#7;//  "<init>":()V
const #13 = Method	#10.#12;	//  scala/xml/dtd/ContentModelParser$."<init>":()V
const #14 = Asciz	LineNumberTable;
const #15 = Asciz	scala/xml/dtd/Scanner;
const #16 = class	#15;	//  scala/xml/dtd/Scanner
const #17 = Method	#16.#12;	//  scala/xml/dtd/Scanner."<init>":()V
const #18 = NameAndType	#4:#5;//  MODULE$:Lscala/xml/dtd/ContentModelParser$;
const #19 = Field	#10.#18;	//  scala/xml/dtd/ContentModelParser$.MODULE$:Lscala/xml/dtd/ContentModelParser$;
const #20 = Asciz	atom;
const #21 = Asciz	()Lscala/util/regexp/WordExp$Letter;;
const #22 = Asciz	token;
const #23 = Asciz	()I;
const #24 = NameAndType	#22:#23;//  token:()I
const #25 = Method	#10.#24;	//  scala/xml/dtd/ContentModelParser$.token:()I
const #26 = Asciz	scala/util/regexp/WordExp$Letter;
const #27 = class	#26;	//  scala/util/regexp/WordExp$Letter
const #28 = Asciz	scala/xml/dtd/ContentModel$;
const #29 = class	#28;	//  scala/xml/dtd/ContentModel$
const #30 = Asciz	Lscala/xml/dtd/ContentModel$;;
const #31 = NameAndType	#4:#30;//  MODULE$:Lscala/xml/dtd/ContentModel$;
const #32 = Field	#29.#31;	//  scala/xml/dtd/ContentModel$.MODULE$:Lscala/xml/dtd/ContentModel$;
const #33 = Asciz	scala/xml/dtd/ContentModel$ElemName;
const #34 = class	#33;	//  scala/xml/dtd/ContentModel$ElemName
const #35 = Asciz	value;
const #36 = Asciz	()Ljava/lang/String;;
const #37 = NameAndType	#35:#36;//  value:()Ljava/lang/String;
const #38 = Method	#10.#37;	//  scala/xml/dtd/ContentModelParser$.value:()Ljava/lang/String;
const #39 = Asciz	(Ljava/lang/String;)V;
const #40 = NameAndType	#11:#39;//  "<init>":(Ljava/lang/String;)V
const #41 = Method	#34.#40;	//  scala/xml/dtd/ContentModel$ElemName."<init>":(Ljava/lang/String;)V
const #42 = Asciz	(Lscala/util/regexp/WordExp;Lscala/util/regexp/WordExp$Label;)V;
const #43 = NameAndType	#11:#42;//  "<init>":(Lscala/util/regexp/WordExp;Lscala/util/regexp/WordExp$Label;)V
const #44 = Method	#27.#43;	//  scala/util/regexp/WordExp$Letter."<init>":(Lscala/util/regexp/WordExp;Lscala/util/regexp/WordExp$Label;)V
const #45 = Asciz	nextToken;
const #46 = NameAndType	#45:#7;//  nextToken:()V
const #47 = Method	#10.#46;	//  scala/xml/dtd/ContentModelParser$.nextToken:()V
const #48 = Asciz	scala/MatchError;
const #49 = class	#48;	//  scala/MatchError
const #50 = Asciz	scala/runtime/BoxesRunTime;
const #51 = class	#50;	//  scala/runtime/BoxesRunTime
const #52 = Asciz	boxToInteger;
const #53 = Asciz	(I)Ljava/lang/Integer;;
const #54 = NameAndType	#52:#53;//  boxToInteger:(I)Ljava/lang/Integer;
const #55 = Method	#51.#54;	//  scala/runtime/BoxesRunTime.boxToInteger:(I)Ljava/lang/Integer;
const #56 = Asciz	java/lang/Object;
const #57 = class	#56;	//  java/lang/Object
const #58 = Asciz	toString;
const #59 = NameAndType	#58:#36;//  toString:()Ljava/lang/String;
const #60 = Method	#57.#59;	//  java/lang/Object.toString:()Ljava/lang/String;
const #61 = Method	#49.#40;	//  scala/MatchError."<init>":(Ljava/lang/String;)V
const #62 = Asciz	scala/collection/mutable/StringBuilder;
const #63 = class	#62;	//  scala/collection/mutable/StringBuilder
const #64 = Method	#63.#12;	//  scala/collection/mutable/StringBuilder."<init>":()V
const #65 = Asciz	expected Name, got:;
const #66 = String	#65;	//  expected Name, got:
const #67 = Asciz	append;
const #68 = Asciz	(Ljava/lang/Object;)Lscala/collection/mutable/StringBuilder;;
const #69 = NameAndType	#67:#68;//  append:(Ljava/lang/Object;)Lscala/collection/mutable/StringBuilder;
const #70 = Method	#63.#69;	//  scala/collection/mutable/StringBuilder.append:(Ljava/lang/Object;)Lscala/collection/mutable/StringBuilder;
const #71 = Asciz	token2string;
const #72 = Asciz	(I)Ljava/lang/String;;
const #73 = NameAndType	#71:#72;//  token2string:(I)Ljava/lang/String;
const #74 = Method	#10.#73;	//  scala/xml/dtd/ContentModelParser$.token2string:(I)Ljava/lang/String;
const #75 = Method	#63.#59;	//  scala/collection/mutable/StringBuilder.toString:()Ljava/lang/String;
const #76 = Asciz	java/lang/RuntimeException;
const #77 = class	#76;	//  java/lang/RuntimeException
const #78 = Method	#77.#40;	//  java/lang/RuntimeException."<init>":(Ljava/lang/String;)V
const #79 = Asciz	this;
const #80 = Asciz	a;
const #81 = Asciz	Lscala/util/regexp/WordExp$Letter;;
const #82 = Asciz	temp9;
const #83 = Asciz	I;
const #84 = Asciz	LocalVariableTable;
const #85 = Asciz	particle;
const #86 = Asciz	()Lscala/util/regexp/Base$RegExp;;
const #87 = Asciz	expected '(' or Name, got:;
const #88 = String	#87;	//  expected '(' or Name, got:
const #89 = Asciz	sOpt;
const #90 = NameAndType	#89:#7;//  sOpt:()V
const #91 = Method	#10.#90;	//  scala/xml/dtd/ContentModelParser$.sOpt:()V
const #92 = Asciz	regexp;
const #93 = NameAndType	#92:#86;//  regexp:()Lscala/util/regexp/Base$RegExp;
const #94 = Method	#10.#93;	//  scala/xml/dtd/ContentModelParser$.regexp:()Lscala/util/regexp/Base$RegExp;
const #95 = Asciz	maybeSuffix;
const #96 = Asciz	(Lscala/util/regexp/Base$RegExp;)Lscala/util/regexp/Base$RegExp;;
const #97 = NameAndType	#95:#96;//  maybeSuffix:(Lscala/util/regexp/Base$RegExp;)Lscala/util/regexp/Base$RegExp;
const #98 = Method	#10.#97;	//  scala/xml/dtd/ContentModelParser$.maybeSuffix:(Lscala/util/regexp/Base$RegExp;)Lscala/util/regexp/Base$RegExp;
const #99 = Asciz	temp8;
const #100 = Asciz	choiceRest;
const #101 = Asciz	(Lscala/util/regexp/Base$RegExp;)Lscala/util/regexp/Base$Alt;;
const #102 = Asciz	scala/Predef$;
const #103 = class	#102;	//  scala/Predef$
const #104 = Asciz	Lscala/Predef$;;
const #105 = NameAndType	#4:#104;//  MODULE$:Lscala/Predef$;
const #106 = Field	#103.#105;	//  scala/Predef$.MODULE$:Lscala/Predef$;
const #107 = Asciz	scala/util/regexp/Base$RegExp;
const #108 = class	#107;	//  scala/util/regexp/Base$RegExp
const #109 = Asciz	[Ljava/lang/Object;;
const #110 = class	#109;	//  "[Ljava/lang/Object;"
const #111 = Asciz	wrapRefArray;
const #112 = Asciz	([Ljava/lang/Object;)Lscala/collection/mutable/WrappedArray;;
const #113 = NameAndType	#111:#112;//  wrapRefArray:([Ljava/lang/Object;)Lscala/collection/mutable/WrappedArray;
const #114 = Method	#103.#113;	//  scala/Predef$.wrapRefArray:([Ljava/lang/Object;)Lscala/collection/mutable/WrappedArray;
const #115 = Asciz	scala/collection/TraversableLike;
const #116 = class	#115;	//  scala/collection/TraversableLike
const #117 = Asciz	toList;
const #118 = Asciz	()Lscala/collection/immutable/List;;
const #119 = NameAndType	#117:#118;//  toList:()Lscala/collection/immutable/List;
const #120 = InterfaceMethod	#116.#119;	//  scala/collection/TraversableLike.toList:()Lscala/collection/immutable/List;
const #121 = int	9;
const #122 = NameAndType	#85:#86;//  particle:()Lscala/util/regexp/Base$RegExp;
const #123 = Method	#10.#122;	//  scala/xml/dtd/ContentModelParser$.particle:()Lscala/util/regexp/Base$RegExp;
const #124 = Asciz	scala/collection/immutable/List;
const #125 = class	#124;	//  scala/collection/immutable/List
const #126 = Asciz	$colon$colon;
const #127 = Asciz	(Ljava/lang/Object;)Lscala/collection/immutable/List;;
const #128 = NameAndType	#126:#127;//  $colon$colon:(Ljava/lang/Object;)Lscala/collection/immutable/List;
const #129 = Method	#125.#128;	//  scala/collection/immutable/List.$colon$colon:(Ljava/lang/Object;)Lscala/collection/immutable/List;
const #130 = Asciz	Alt;
const #131 = Asciz	()Lscala/util/regexp/Base$Alt$;;
const #132 = NameAndType	#130:#131;//  Alt:()Lscala/util/regexp/Base$Alt$;
const #133 = Method	#29.#132;	//  scala/xml/dtd/ContentModel$.Alt:()Lscala/util/regexp/Base$Alt$;
const #134 = Asciz	reverse;
const #135 = NameAndType	#134:#118;//  reverse:()Lscala/collection/immutable/List;
const #136 = Method	#125.#135;	//  scala/collection/immutable/List.reverse:()Lscala/collection/immutable/List;
const #137 = Asciz	scala/util/regexp/Base$Alt$;
const #138 = class	#137;	//  scala/util/regexp/Base$Alt$
const #139 = Asciz	apply;
const #140 = Asciz	(Lscala/collection/Seq;)Lscala/util/regexp/Base$Alt;;
const #141 = NameAndType	#139:#140;//  apply:(Lscala/collection/Seq;)Lscala/util/regexp/Base$Alt;
const #142 = Method	#138.#141;	//  scala/util/regexp/Base$Alt$.apply:(Lscala/collection/Seq;)Lscala/util/regexp/Base$Alt;
const #143 = Asciz	p;
const #144 = Asciz	Lscala/util/regexp/Base$RegExp;;
const #145 = Asciz	k;
const #146 = Asciz	Lscala/collection/immutable/List;;
const #147 = Asciz	seqRest;
const #148 = Asciz	Sequ;
const #149 = Asciz	()Lscala/util/regexp/Base$Sequ$;;
const #150 = NameAndType	#148:#149;//  Sequ:()Lscala/util/regexp/Base$Sequ$;
const #151 = Method	#29.#150;	//  scala/xml/dtd/ContentModel$.Sequ:()Lscala/util/regexp/Base$Sequ$;
const #152 = Asciz	scala/util/regexp/Base$Sequ$;
const #153 = class	#152;	//  scala/util/regexp/Base$Sequ$
const #154 = Asciz	(Lscala/collection/Seq;)Lscala/util/regexp/Base$RegExp;;
const #155 = NameAndType	#139:#154;//  apply:(Lscala/collection/Seq;)Lscala/util/regexp/Base$RegExp;
const #156 = Method	#153.#155;	//  scala/util/regexp/Base$Sequ$.apply:(Lscala/collection/Seq;)Lscala/util/regexp/Base$RegExp;
const #157 = NameAndType	#100:#101;//  choiceRest:(Lscala/util/regexp/Base$RegExp;)Lscala/util/regexp/Base$Alt;
const #158 = Method	#10.#157;	//  scala/xml/dtd/ContentModelParser$.choiceRest:(Lscala/util/regexp/Base$RegExp;)Lscala/util/regexp/Base$Alt;
const #159 = Asciz	accept;
const #160 = Asciz	(I)V;
const #161 = NameAndType	#159:#160;//  accept:(I)V
const #162 = Method	#10.#161;	//  scala/xml/dtd/ContentModelParser$.accept:(I)V
const #163 = NameAndType	#147:#96;//  seqRest:(Lscala/util/regexp/Base$RegExp;)Lscala/util/regexp/Base$RegExp;
const #164 = Method	#10.#163;	//  scala/xml/dtd/ContentModelParser$.seqRest:(Lscala/util/regexp/Base$RegExp;)Lscala/util/regexp/Base$RegExp;
const #165 = Asciz	q;
const #166 = Asciz	Lscala/util/regexp/Base$Alt;;
const #167 = Asciz	temp7;
const #168 = int	13;
const #169 = Asciz	contentspec;
const #170 = Asciz	()Lscala/xml/dtd/ContentModel;;
const #171 = Asciz	unexpected token:;
const #172 = String	#171;	//  unexpected token:
const #173 = Asciz	scala/xml/dtd/ELEMENTS;
const #174 = class	#173;	//  scala/xml/dtd/ELEMENTS
const #175 = Asciz	(Lscala/util/regexp/Base$RegExp;)V;
const #176 = NameAndType	#11:#175;//  "<init>":(Lscala/util/regexp/Base$RegExp;)V
const #177 = Method	#174.#176;	//  scala/xml/dtd/ELEMENTS."<init>":(Lscala/util/regexp/Base$RegExp;)V
const #178 = Asciz	scala/xml/dtd/MIXED;
const #179 = class	#178;	//  scala/xml/dtd/MIXED
const #180 = Asciz	Eps;
const #181 = Asciz	()Lscala/util/regexp/Base$Eps$;;
const #182 = NameAndType	#180:#181;//  Eps:()Lscala/util/regexp/Base$Eps$;
const #183 = Method	#29.#182;	//  scala/xml/dtd/ContentModel$.Eps:()Lscala/util/regexp/Base$Eps$;
const #184 = Method	#179.#176;	//  scala/xml/dtd/MIXED."<init>":(Lscala/util/regexp/Base$RegExp;)V
const #185 = int	6;
const #186 = Asciz	scala/xml/dtd/PCDATA$;
const #187 = class	#186;	//  scala/xml/dtd/PCDATA$
const #188 = Asciz	Lscala/xml/dtd/PCDATA$;;
const #189 = NameAndType	#4:#188;//  MODULE$:Lscala/xml/dtd/PCDATA$;
const #190 = Field	#187.#189;	//  scala/xml/dtd/PCDATA$.MODULE$:Lscala/xml/dtd/PCDATA$;
const #191 = Asciz	ANY;
const #192 = String	#191;	//  ANY
const #193 = Asciz	equals;
const #194 = Asciz	(Ljava/lang/Object;)Z;
const #195 = NameAndType	#193:#194;//  equals:(Ljava/lang/Object;)Z
const #196 = Method	#57.#195;	//  java/lang/Object.equals:(Ljava/lang/Object;)Z
const #197 = Asciz	scala/xml/dtd/ANY$;
const #198 = class	#197;	//  scala/xml/dtd/ANY$
const #199 = Asciz	Lscala/xml/dtd/ANY$;;
const #200 = NameAndType	#4:#199;//  MODULE$:Lscala/xml/dtd/ANY$;
const #201 = Field	#198.#200;	//  scala/xml/dtd/ANY$.MODULE$:Lscala/xml/dtd/ANY$;
const #202 = Asciz	java/lang/String;
const #203 = class	#202;	//  java/lang/String
const #204 = Method	#203.#59;	//  java/lang/String.toString:()Ljava/lang/String;
const #205 = Asciz	EMPTY;
const #206 = String	#205;	//  EMPTY
const #207 = Asciz	scala/xml/dtd/EMPTY$;
const #208 = class	#207;	//  scala/xml/dtd/EMPTY$
const #209 = Asciz	Lscala/xml/dtd/EMPTY$;;
const #210 = NameAndType	#4:#209;//  MODULE$:Lscala/xml/dtd/EMPTY$;
const #211 = Field	#208.#210;	//  scala/xml/dtd/EMPTY$.MODULE$:Lscala/xml/dtd/EMPTY$;
const #212 = Asciz	expected ANY, EMPTY or '(' instead of ;
const #213 = String	#212;	//  expected ANY, EMPTY or '(' instead of 
const #214 = Asciz	res;
const #215 = Asciz	Lscala/xml/dtd/MIXED;;
const #216 = Asciz	temp5;
const #217 = Asciz	temp2;
const #218 = Asciz	Ljava/lang/String;;
const #219 = Asciz	temp6;
const #220 = Asciz	scala/util/regexp/Base$Star;
const #221 = class	#220;	//  scala/util/regexp/Base$Star
const #222 = Asciz	(Lscala/util/regexp/Base;Lscala/util/regexp/Base$RegExp;)V;
const #223 = NameAndType	#11:#222;//  "<init>":(Lscala/util/regexp/Base;Lscala/util/regexp/Base$RegExp;)V
const #224 = Method	#221.#223;	//  scala/util/regexp/Base$Star."<init>":(Lscala/util/regexp/Base;Lscala/util/regexp/Base$RegExp;)V
const #225 = Asciz	s;
const #226 = Asciz	temp1;
const #227 = int	10;
const #228 = Asciz	in DTDs, \nmixed content models must be like (#PCDATA|Name|Name|...)*;
const #229 = String	#228;	//  in DTDs, \nmixed content models must be like (#PCDATA|Name|Name|...)*
const #230 = Asciz	expected ;
const #231 = String	#230;	//  expected 
const #232 = Asciz	, got unexpected token:;
const #233 = String	#232;	//  , got unexpected token:
const #234 = Asciz	tok;
const #235 = Asciz	parse;
const #236 = Asciz	(Ljava/lang/String;)Lscala/xml/dtd/ContentModel;;
const #237 = Asciz	initScanner;
const #238 = NameAndType	#237:#39;//  initScanner:(Ljava/lang/String;)V
const #239 = Method	#10.#238;	//  scala/xml/dtd/ContentModelParser$.initScanner:(Ljava/lang/String;)V
const #240 = NameAndType	#169:#170;//  contentspec:()Lscala/xml/dtd/ContentModel;
const #241 = Method	#10.#240;	//  scala/xml/dtd/ContentModelParser$.contentspec:()Lscala/xml/dtd/ContentModel;
const #242 = Asciz	InnerClasses;
const #243 = Asciz	scala/util/regexp/Base$Alt;
const #244 = class	#243;	//  scala/util/regexp/Base$Alt
const #245 = Asciz	scala/util/regexp/Base;
const #246 = class	#245;	//  scala/util/regexp/Base
const #247 = Asciz	Star;
const #248 = Asciz	RegExp;
const #249 = Asciz	scala/util/regexp/WordExp$Label;
const #250 = class	#249;	//  scala/util/regexp/WordExp$Label
const #251 = Asciz	scala/util/regexp/WordExp;
const #252 = class	#251;	//  scala/util/regexp/WordExp
const #253 = Asciz	Label;
const #254 = Asciz	Letter;
const #255 = Asciz	scala/xml/dtd/ContentModel;
const #256 = class	#255;	//  scala/xml/dtd/ContentModel
const #257 = Asciz	ElemName;
const #258 = Asciz	scala/ScalaObject;
const #259 = class	#258;	//  scala/ScalaObject

{
public static final scala.xml.dtd.ContentModelParser$ MODULE$;

public static {};
  Code:
   Stack=1, Locals=0, Args_size=0
   0:	new	#10; //class scala/xml/dtd/ContentModelParser$
   3:	invokespecial	#13; //Method "<init>":()V
   6:	return

public scala.util.regexp.WordExp$Letter atom();
  Code:
   Stack=6, Locals=4, Args_size=1
   0:	aload_0
   1:	invokevirtual	#25; //Method token:()I
   4:	istore_3
   5:	iload_3
   6:	iconst_1
   7:	if_icmpne	57
   10:	iconst_1
   11:	ifeq	42
   14:	new	#27; //class scala/util/regexp/WordExp$Letter
   17:	dup
   18:	getstatic	#32; //Field scala/xml/dtd/ContentModel$.MODULE$:Lscala/xml/dtd/ContentModel$;
   21:	new	#34; //class scala/xml/dtd/ContentModel$ElemName
   24:	dup
   25:	aload_0
   26:	invokevirtual	#38; //Method value:()Ljava/lang/String;
   29:	invokespecial	#41; //Method scala/xml/dtd/ContentModel$ElemName."<init>":(Ljava/lang/String;)V
   32:	invokespecial	#44; //Method scala/util/regexp/WordExp$Letter."<init>":(Lscala/util/regexp/WordExp;Lscala/util/regexp/WordExp$Label;)V
   35:	astore_1
   36:	aload_0
   37:	invokevirtual	#47; //Method nextToken:()V
   40:	aload_1
   41:	areturn
   42:	new	#49; //class scala/MatchError
   45:	dup
   46:	iload_3
   47:	invokestatic	#55; //Method scala/runtime/BoxesRunTime.boxToInteger:(I)Ljava/lang/Integer;
   50:	invokevirtual	#60; //Method java/lang/Object.toString:()Ljava/lang/String;
   53:	invokespecial	#61; //Method scala/MatchError."<init>":(Ljava/lang/String;)V
   56:	athrow
   57:	iconst_1
   58:	ifeq	97
   61:	new	#63; //class scala/collection/mutable/StringBuilder
   64:	dup
   65:	invokespecial	#64; //Method scala/collection/mutable/StringBuilder."<init>":()V
   68:	ldc	#66; //String expected Name, got:
   70:	invokevirtual	#70; //Method scala/collection/mutable/StringBuilder.append:(Ljava/lang/Object;)Lscala/collection/mutable/StringBuilder;
   73:	aload_0
   74:	aload_0
   75:	invokevirtual	#25; //Method token:()I
   78:	invokevirtual	#74; //Method token2string:(I)Ljava/lang/String;
   81:	invokevirtual	#70; //Method scala/collection/mutable/StringBuilder.append:(Ljava/lang/Object;)Lscala/collection/mutable/StringBuilder;
   84:	invokevirtual	#75; //Method scala/collection/mutable/StringBuilder.toString:()Ljava/lang/String;
   87:	astore_2
   88:	new	#77; //class java/lang/RuntimeException
   91:	dup
   92:	aload_2
   93:	invokespecial	#78; //Method java/lang/RuntimeException."<init>":(Ljava/lang/String;)V
   96:	athrow
   97:	new	#49; //class scala/MatchError
   100:	dup
   101:	iload_3
   102:	invokestatic	#55; //Method scala/runtime/BoxesRunTime.boxToInteger:(I)Ljava/lang/Integer;
   105:	invokevirtual	#60; //Method java/lang/Object.toString:()Ljava/lang/String;
   108:	invokespecial	#61; //Method scala/MatchError."<init>":(Ljava/lang/String;)V
   111:	athrow
  LineNumberTable: 
   line 129: 0
   line 21: 10
   line 130: 14
   line 129: 41
   line 21: 57
   line 131: 61
   line 129: 97

  LocalVariableTable: 
   Start  Length  Slot  Name   Signature
   0      112      0    this       Lscala/xml/dtd/ContentModelParser$;
   36      5      1    a       Lscala/util/regexp/WordExp$Letter;
   5      107      3    temp9       I


public scala.util.regexp.Base$RegExp particle();
  Code:
   Stack=6, Locals=4, Args_size=1
   0:	aload_0
   1:	invokevirtual	#25; //Method token:()I
   4:	istore_3
   5:	iload_3
   6:	lookupswitch{ //2
		1: 121;
		3: 87;
		default: 32 }
   32:	iconst_1
   33:	ifeq	72
   36:	new	#63; //class scala/collection/mutable/StringBuilder
   39:	dup
   40:	invokespecial	#64; //Method scala/collection/mutable/StringBuilder."<init>":()V
   43:	ldc	#88; //String expected '(' or Name, got:
   45:	invokevirtual	#70; //Method scala/collection/mutable/StringBuilder.append:(Ljava/lang/Object;)Lscala/collection/mutable/StringBuilder;
   48:	aload_0
   49:	aload_0
   50:	invokevirtual	#25; //Method token:()I
   53:	invokevirtual	#74; //Method token2string:(I)Ljava/lang/String;
   56:	invokevirtual	#70; //Method scala/collection/mutable/StringBuilder.append:(Ljava/lang/Object;)Lscala/collection/mutable/StringBuilder;
   59:	invokevirtual	#75; //Method scala/collection/mutable/StringBuilder.toString:()Ljava/lang/String;
   62:	astore_1
   63:	new	#77; //class java/lang/RuntimeException
   66:	dup
   67:	aload_1
   68:	invokespecial	#78; //Method java/lang/RuntimeException."<init>":(Ljava/lang/String;)V
   71:	athrow
   72:	new	#49; //class scala/MatchError
   75:	dup
   76:	iload_3
   77:	invokestatic	#55; //Method scala/runtime/BoxesRunTime.boxToInteger:(I)Ljava/lang/Integer;
   80:	invokevirtual	#60; //Method java/lang/Object.toString:()Ljava/lang/String;
   83:	invokespecial	#61; //Method scala/MatchError."<init>":(Ljava/lang/String;)V
   86:	athrow
   87:	iconst_1
   88:	ifeq	106
   91:	aload_0
   92:	invokevirtual	#47; //Method nextToken:()V
   95:	aload_0
   96:	invokevirtual	#91; //Method sOpt:()V
   99:	aload_0
   100:	invokevirtual	#94; //Method regexp:()Lscala/util/regexp/Base$RegExp;
   103:	goto	156
   106:	new	#49; //class scala/MatchError
   109:	dup
   110:	iload_3
   111:	invokestatic	#55; //Method scala/runtime/BoxesRunTime.boxToInteger:(I)Ljava/lang/Integer;
   114:	invokevirtual	#60; //Method java/lang/Object.toString:()Ljava/lang/String;
   117:	invokespecial	#61; //Method scala/MatchError."<init>":(Ljava/lang/String;)V
   120:	athrow
   121:	iconst_1
   122:	ifeq	157
   125:	new	#27; //class scala/util/regexp/WordExp$Letter
   128:	dup
   129:	getstatic	#32; //Field scala/xml/dtd/ContentModel$.MODULE$:Lscala/xml/dtd/ContentModel$;
   132:	new	#34; //class scala/xml/dtd/ContentModel$ElemName
   135:	dup
   136:	aload_0
   137:	invokevirtual	#38; //Method value:()Ljava/lang/String;
   140:	invokespecial	#41; //Method scala/xml/dtd/ContentModel$ElemName."<init>":(Ljava/lang/String;)V
   143:	invokespecial	#44; //Method scala/util/regexp/WordExp$Letter."<init>":(Lscala/util/regexp/WordExp;Lscala/util/regexp/WordExp$Label;)V
   146:	astore_2
   147:	aload_0
   148:	invokevirtual	#47; //Method nextToken:()V
   151:	aload_0
   152:	aload_2
   153:	invokevirtual	#98; //Method maybeSuffix:(Lscala/util/regexp/Base$RegExp;)Lscala/util/regexp/Base$RegExp;
   156:	areturn
   157:	new	#49; //class scala/MatchError
   160:	dup
   161:	iload_3
   162:	invokestatic	#55; //Method scala/runtime/BoxesRunTime.boxToInteger:(I)Ljava/lang/Integer;
   165:	invokevirtual	#60; //Method java/lang/Object.toString:()Ljava/lang/String;
   168:	invokespecial	#61; //Method scala/MatchError."<init>":(Ljava/lang/String;)V
   171:	athrow
  LineNumberTable: 
   line 122: 0
   line 21: 32
   line 125: 36
   line 122: 72
   line 21: 87
   line 123: 91
   line 122: 106
   line 21: 121
   line 124: 125
   line 122: 156

  LocalVariableTable: 
   Start  Length  Slot  Name   Signature
   0      172      0    this       Lscala/xml/dtd/ContentModelParser$;
   147      9      2    a       Lscala/util/regexp/WordExp$Letter;
   5      167      3    temp8       I


public scala.util.regexp.Base$Alt choiceRest(scala.util.regexp.Base$RegExp);
  Code:
   Stack=5, Locals=5, Args_size=2
   0:	getstatic	#106; //Field scala/Predef$.MODULE$:Lscala/Predef$;
   3:	iconst_1
   4:	anewarray	#108; //class scala/util/regexp/Base$RegExp
   7:	dup
   8:	iconst_0
   9:	aload_1
   10:	aastore
   11:	checkcast	#110; //class "[Ljava/lang/Object;"
   14:	invokevirtual	#114; //Method scala/Predef$.wrapRefArray:([Ljava/lang/Object;)Lscala/collection/mutable/WrappedArray;
   17:	astore_2
   18:	aload_2
   19:	invokeinterface	#120,  1; //InterfaceMethod scala/collection/TraversableLike.toList:()Lscala/collection/immutable/List;
   24:	astore	4
   26:	aload_0
   27:	invokevirtual	#25; //Method token:()I
   30:	ldc	#121; //int 9
   32:	if_icmpne	63
   35:	aload_0
   36:	invokevirtual	#47; //Method nextToken:()V
   39:	aload_0
   40:	invokevirtual	#91; //Method sOpt:()V
   43:	aload_0
   44:	invokevirtual	#123; //Method particle:()Lscala/util/regexp/Base$RegExp;
   47:	astore_3
   48:	aload	4
   50:	aload_3
   51:	invokevirtual	#129; //Method scala/collection/immutable/List.$colon$colon:(Ljava/lang/Object;)Lscala/collection/immutable/List;
   54:	astore	4
   56:	aload_0
   57:	invokevirtual	#91; //Method sOpt:()V
   60:	goto	26
   63:	getstatic	#32; //Field scala/xml/dtd/ContentModel$.MODULE$:Lscala/xml/dtd/ContentModel$;
   66:	invokevirtual	#133; //Method scala/xml/dtd/ContentModel$.Alt:()Lscala/util/regexp/Base$Alt$;
   69:	aload	4
   71:	invokevirtual	#136; //Method scala/collection/immutable/List.reverse:()Lscala/collection/immutable/List;
   74:	invokevirtual	#142; //Method scala/util/regexp/Base$Alt$.apply:(Lscala/collection/Seq;)Lscala/util/regexp/Base$Alt;
   77:	areturn
  LineNumberTable: 
   line 110: 0
   line 111: 26
   line 112: 35
   line 113: 39
   line 114: 43
   line 115: 56
   line 117: 63

  LocalVariableTable: 
   Start  Length  Slot  Name   Signature
   0      78      0    this       Lscala/xml/dtd/ContentModelParser$;
   0      78      1    p       Lscala/util/regexp/Base$RegExp;
   26      51      4    k       Lscala/collection/immutable/List;


public scala.util.regexp.Base$RegExp seqRest(scala.util.regexp.Base$RegExp);
  Code:
   Stack=5, Locals=5, Args_size=2
   0:	getstatic	#106; //Field scala/Predef$.MODULE$:Lscala/Predef$;
   3:	iconst_1
   4:	anewarray	#108; //class scala/util/regexp/Base$RegExp
   7:	dup
   8:	iconst_0
   9:	aload_1
   10:	aastore
   11:	checkcast	#110; //class "[Ljava/lang/Object;"
   14:	invokevirtual	#114; //Method scala/Predef$.wrapRefArray:([Ljava/lang/Object;)Lscala/collection/mutable/WrappedArray;
   17:	astore_2
   18:	aload_2
   19:	invokeinterface	#120,  1; //InterfaceMethod scala/collection/TraversableLike.toList:()Lscala/collection/immutable/List;
   24:	astore	4
   26:	aload_0
   27:	invokevirtual	#25; //Method token:()I
   30:	iconst_5
   31:	if_icmpne	62
   34:	aload_0
   35:	invokevirtual	#47; //Method nextToken:()V
   38:	aload_0
   39:	invokevirtual	#91; //Method sOpt:()V
   42:	aload_0
   43:	invokevirtual	#123; //Method particle:()Lscala/util/regexp/Base$RegExp;
   46:	astore_3
   47:	aload	4
   49:	aload_3
   50:	invokevirtual	#129; //Method scala/collection/immutable/List.$colon$colon:(Ljava/lang/Object;)Lscala/collection/immutable/List;
   53:	astore	4
   55:	aload_0
   56:	invokevirtual	#91; //Method sOpt:()V
   59:	goto	26
   62:	getstatic	#32; //Field scala/xml/dtd/ContentModel$.MODULE$:Lscala/xml/dtd/ContentModel$;
   65:	invokevirtual	#151; //Method scala/xml/dtd/ContentModel$.Sequ:()Lscala/util/regexp/Base$Sequ$;
   68:	aload	4
   70:	invokevirtual	#136; //Method scala/collection/immutable/List.reverse:()Lscala/collection/immutable/List;
   73:	invokevirtual	#156; //Method scala/util/regexp/Base$Sequ$.apply:(Lscala/collection/Seq;)Lscala/util/regexp/Base$RegExp;
   76:	areturn
  LineNumberTable: 
   line 98: 0
   line 99: 26
   line 100: 34
   line 101: 38
   line 102: 42
   line 103: 55
   line 105: 62

  LocalVariableTable: 
   Start  Length  Slot  Name   Signature
   0      77      0    this       Lscala/xml/dtd/ContentModelParser$;
   0      77      1    p       Lscala/util/regexp/Base$RegExp;
   26      50      4    k       Lscala/collection/immutable/List;


public scala.util.regexp.Base$RegExp regexp();
  Code:
   Stack=4, Locals=5, Args_size=1
   0:	aload_0
   1:	invokevirtual	#123; //Method particle:()Lscala/util/regexp/Base$RegExp;
   4:	astore_3
   5:	aload_0
   6:	invokevirtual	#91; //Method sOpt:()V
   9:	aload_0
   10:	aload_0
   11:	invokevirtual	#25; //Method token:()I
   14:	istore	4
   16:	iload	4
   18:	lookupswitch{ //3
		4: 138;
		5: 103;
		9: 68;
		default: 52 }
   52:	new	#49; //class scala/MatchError
   55:	dup
   56:	iload	4
   58:	invokestatic	#55; //Method scala/runtime/BoxesRunTime.boxToInteger:(I)Ljava/lang/Integer;
   61:	invokevirtual	#60; //Method java/lang/Object.toString:()Ljava/lang/String;
   64:	invokespecial	#61; //Method scala/MatchError."<init>":(Ljava/lang/String;)V
   67:	athrow
   68:	iconst_1
   69:	ifeq	87
   72:	aload_0
   73:	aload_3
   74:	invokevirtual	#158; //Method choiceRest:(Lscala/util/regexp/Base$RegExp;)Lscala/util/regexp/Base$Alt;
   77:	astore_1
   78:	aload_0
   79:	iconst_4
   80:	invokevirtual	#162; //Method accept:(I)V
   83:	aload_1
   84:	goto	147
   87:	new	#49; //class scala/MatchError
   90:	dup
   91:	iload	4
   93:	invokestatic	#55; //Method scala/runtime/BoxesRunTime.boxToInteger:(I)Ljava/lang/Integer;
   96:	invokevirtual	#60; //Method java/lang/Object.toString:()Ljava/lang/String;
   99:	invokespecial	#61; //Method scala/MatchError."<init>":(Ljava/lang/String;)V
   102:	athrow
   103:	iconst_1
   104:	ifeq	122
   107:	aload_0
   108:	aload_3
   109:	invokevirtual	#164; //Method seqRest:(Lscala/util/regexp/Base$RegExp;)Lscala/util/regexp/Base$RegExp;
   112:	astore_2
   113:	aload_0
   114:	iconst_4
   115:	invokevirtual	#162; //Method accept:(I)V
   118:	aload_2
   119:	goto	147
   122:	new	#49; //class scala/MatchError
   125:	dup
   126:	iload	4
   128:	invokestatic	#55; //Method scala/runtime/BoxesRunTime.boxToInteger:(I)Ljava/lang/Integer;
   131:	invokevirtual	#60; //Method java/lang/Object.toString:()Ljava/lang/String;
   134:	invokespecial	#61; //Method scala/MatchError."<init>":(Ljava/lang/String;)V
   137:	athrow
   138:	iconst_1
   139:	ifeq	151
   142:	aload_0
   143:	invokevirtual	#47; //Method nextToken:()V
   146:	aload_3
   147:	invokevirtual	#98; //Method maybeSuffix:(Lscala/util/regexp/Base$RegExp;)Lscala/util/regexp/Base$RegExp;
   150:	areturn
   151:	new	#49; //class scala/MatchError
   154:	dup
   155:	iload	4
   157:	invokestatic	#55; //Method scala/runtime/BoxesRunTime.boxToInteger:(I)Ljava/lang/Integer;
   160:	invokevirtual	#60; //Method java/lang/Object.toString:()Ljava/lang/String;
   163:	invokespecial	#61; //Method scala/MatchError."<init>":(Ljava/lang/String;)V
   166:	athrow
  LineNumberTable: 
   line 87: 0
   line 88: 5
   line 89: 9
   line 21: 68
   line 91: 72
   line 89: 87
   line 21: 103
   line 92: 107
   line 89: 122
   line 21: 138
   line 90: 142
   line 89: 147

  LocalVariableTable: 
   Start  Length  Slot  Name   Signature
   0      167      0    this       Lscala/xml/dtd/ContentModelParser$;
   78      6      1    q       Lscala/util/regexp/Base$Alt;
   113      6      2    q       Lscala/util/regexp/Base$RegExp;
   5      145      3    p       Lscala/util/regexp/Base$RegExp;
   151      16      3    p       Lscala/util/regexp/Base$RegExp;
   16      151      4    temp7       I


public void sOpt();
  Code:
   Stack=2, Locals=1, Args_size=1
   0:	aload_0
   1:	invokevirtual	#25; //Method token:()I
   4:	ldc	#168; //int 13
   6:	if_icmpne	13
   9:	aload_0
   10:	invokevirtual	#47; //Method nextToken:()V
   13:	return
  LineNumberTable: 
   line 80: 0


public scala.xml.dtd.ContentModel contentspec();
  Code:
   Stack=4, Locals=10, Args_size=1
   0:	aload_0
   1:	invokevirtual	#25; //Method token:()I
   4:	istore	9
   6:	iload	9
   8:	lookupswitch{ //2
		1: 319;
		3: 92;
		default: 36 }
   36:	iconst_1
   37:	ifeq	76
   40:	new	#63; //class scala/collection/mutable/StringBuilder
   43:	dup
   44:	invokespecial	#64; //Method scala/collection/mutable/StringBuilder."<init>":()V
   47:	ldc	#172; //String unexpected token:
   49:	invokevirtual	#70; //Method scala/collection/mutable/StringBuilder.append:(Ljava/lang/Object;)Lscala/collection/mutable/StringBuilder;
   52:	aload_0
   53:	aload_0
   54:	invokevirtual	#25; //Method token:()I
   57:	invokevirtual	#74; //Method token2string:(I)Ljava/lang/String;
   60:	invokevirtual	#70; //Method scala/collection/mutable/StringBuilder.append:(Ljava/lang/Object;)Lscala/collection/mutable/StringBuilder;
   63:	invokevirtual	#75; //Method scala/collection/mutable/StringBuilder.toString:()Ljava/lang/String;
   66:	astore_1
   67:	new	#77; //class java/lang/RuntimeException
   70:	dup
   71:	aload_1
   72:	invokespecial	#78; //Method java/lang/RuntimeException."<init>":(Ljava/lang/String;)V
   75:	athrow
   76:	new	#49; //class scala/MatchError
   79:	dup
   80:	iload	9
   82:	invokestatic	#55; //Method scala/runtime/BoxesRunTime.boxToInteger:(I)Ljava/lang/Integer;
   85:	invokevirtual	#60; //Method java/lang/Object.toString:()Ljava/lang/String;
   88:	invokespecial	#61; //Method scala/MatchError."<init>":(Ljava/lang/String;)V
   91:	athrow
   92:	iconst_1
   93:	ifeq	303
   96:	aload_0
   97:	invokevirtual	#47; //Method nextToken:()V
   100:	aload_0
   101:	invokevirtual	#91; //Method sOpt:()V
   104:	aload_0
   105:	invokevirtual	#25; //Method token:()I
   108:	iconst_0
   109:	if_icmpeq	126
   112:	new	#174; //class scala/xml/dtd/ELEMENTS
   115:	dup
   116:	aload_0
   117:	invokevirtual	#94; //Method regexp:()Lscala/util/regexp/Base$RegExp;
   120:	invokespecial	#177; //Method scala/xml/dtd/ELEMENTS."<init>":(Lscala/util/regexp/Base$RegExp;)V
   123:	goto	413
   126:	aload_0
   127:	invokevirtual	#47; //Method nextToken:()V
   130:	aload_0
   131:	invokevirtual	#25; //Method token:()I
   134:	istore	4
   136:	iload	4
   138:	lookupswitch{ //2
		4: 277;
		9: 220;
		default: 164 }
   164:	iconst_1
   165:	ifeq	204
   168:	new	#63; //class scala/collection/mutable/StringBuilder
   171:	dup
   172:	invokespecial	#64; //Method scala/collection/mutable/StringBuilder."<init>":()V
   175:	ldc	#172; //String unexpected token:
   177:	invokevirtual	#70; //Method scala/collection/mutable/StringBuilder.append:(Ljava/lang/Object;)Lscala/collection/mutable/StringBuilder;
   180:	aload_0
   181:	aload_0
   182:	invokevirtual	#25; //Method token:()I
   185:	invokevirtual	#74; //Method token2string:(I)Ljava/lang/String;
   188:	invokevirtual	#70; //Method scala/collection/mutable/StringBuilder.append:(Ljava/lang/Object;)Lscala/collection/mutable/StringBuilder;
   191:	invokevirtual	#75; //Method scala/collection/mutable/StringBuilder.toString:()Ljava/lang/String;
   194:	astore_2
   195:	new	#77; //class java/lang/RuntimeException
   198:	dup
   199:	aload_2
   200:	invokespecial	#78; //Method java/lang/RuntimeException."<init>":(Ljava/lang/String;)V
   203:	athrow
   204:	new	#49; //class scala/MatchError
   207:	dup
   208:	iload	4
   210:	invokestatic	#55; //Method scala/runtime/BoxesRunTime.boxToInteger:(I)Ljava/lang/Integer;
   213:	invokevirtual	#60; //Method java/lang/Object.toString:()Ljava/lang/String;
   216:	invokespecial	#61; //Method scala/MatchError."<init>":(Ljava/lang/String;)V
   219:	athrow
   220:	iconst_1
   221:	ifeq	261
   224:	new	#179; //class scala/xml/dtd/MIXED
   227:	dup
   228:	aload_0
   229:	getstatic	#32; //Field scala/xml/dtd/ContentModel$.MODULE$:Lscala/xml/dtd/ContentModel$;
   232:	invokevirtual	#183; //Method scala/xml/dtd/ContentModel$.Eps:()Lscala/util/regexp/Base$Eps$;
   235:	invokevirtual	#158; //Method choiceRest:(Lscala/util/regexp/Base$RegExp;)Lscala/util/regexp/Base$Alt;
   238:	invokespecial	#184; //Method scala/xml/dtd/MIXED."<init>":(Lscala/util/regexp/Base$RegExp;)V
   241:	astore_3
   242:	aload_0
   243:	invokevirtual	#91; //Method sOpt:()V
   246:	aload_0
   247:	iconst_4
   248:	invokevirtual	#162; //Method accept:(I)V
   251:	aload_0
   252:	ldc	#185; //int 6
   254:	invokevirtual	#162; //Method accept:(I)V
   257:	aload_3
   258:	goto	413
   261:	new	#49; //class scala/MatchError
   264:	dup
   265:	iload	4
   267:	invokestatic	#55; //Method scala/runtime/BoxesRunTime.boxToInteger:(I)Ljava/lang/Integer;
   270:	invokevirtual	#60; //Method java/lang/Object.toString:()Ljava/lang/String;
   273:	invokespecial	#61; //Method scala/MatchError."<init>":(Ljava/lang/String;)V
   276:	athrow
   277:	iconst_1
   278:	ifeq	287
   281:	getstatic	#190; //Field scala/xml/dtd/PCDATA$.MODULE$:Lscala/xml/dtd/PCDATA$;
   284:	goto	413
   287:	new	#49; //class scala/MatchError
   290:	dup
   291:	iload	4
   293:	invokestatic	#55; //Method scala/runtime/BoxesRunTime.boxToInteger:(I)Ljava/lang/Integer;
   296:	invokevirtual	#60; //Method java/lang/Object.toString:()Ljava/lang/String;
   299:	invokespecial	#61; //Method scala/MatchError."<init>":(Ljava/lang/String;)V
   302:	athrow
   303:	new	#49; //class scala/MatchError
   306:	dup
   307:	iload	9
   309:	invokestatic	#55; //Method scala/runtime/BoxesRunTime.boxToInteger:(I)Ljava/lang/Integer;
   312:	invokevirtual	#60; //Method java/lang/Object.toString:()Ljava/lang/String;
   315:	invokespecial	#61; //Method scala/MatchError."<init>":(Ljava/lang/String;)V
   318:	athrow
   319:	iconst_1
   320:	ifeq	478
   323:	aload_0
   324:	invokevirtual	#38; //Method value:()Ljava/lang/String;
   327:	astore	8
   329:	aload	8
   331:	ldc	#192; //String ANY
   333:	astore	5
   335:	dup
   336:	ifnonnull	348
   339:	pop
   340:	aload	5
   342:	ifnull	356
   345:	goto	379
   348:	aload	5
   350:	invokevirtual	#196; //Method java/lang/Object.equals:(Ljava/lang/Object;)Z
   353:	ifeq	379
   356:	iconst_1
   357:	ifeq	366
   360:	getstatic	#201; //Field scala/xml/dtd/ANY$.MODULE$:Lscala/xml/dtd/ANY$;
   363:	goto	413
   366:	new	#49; //class scala/MatchError
   369:	dup
   370:	aload	8
   372:	invokevirtual	#204; //Method java/lang/String.toString:()Ljava/lang/String;
   375:	invokespecial	#61; //Method scala/MatchError."<init>":(Ljava/lang/String;)V
   378:	athrow
   379:	aload	8
   381:	ldc	#206; //String EMPTY
   383:	astore	6
   385:	dup
   386:	ifnonnull	398
   389:	pop
   390:	aload	6
   392:	ifnull	406
   395:	goto	427
   398:	aload	6
   400:	invokevirtual	#196; //Method java/lang/Object.equals:(Ljava/lang/Object;)Z
   403:	ifeq	427
   406:	iconst_1
   407:	ifeq	414
   410:	getstatic	#211; //Field scala/xml/dtd/EMPTY$.MODULE$:Lscala/xml/dtd/EMPTY$;
   413:	areturn
   414:	new	#49; //class scala/MatchError
   417:	dup
   418:	aload	8
   420:	invokevirtual	#204; //Method java/lang/String.toString:()Ljava/lang/String;
   423:	invokespecial	#61; //Method scala/MatchError."<init>":(Ljava/lang/String;)V
   426:	athrow
   427:	iconst_1
   428:	ifeq	465
   431:	new	#63; //class scala/collection/mutable/StringBuilder
   434:	dup
   435:	invokespecial	#64; //Method scala/collection/mutable/StringBuilder."<init>":()V
   438:	ldc	#213; //String expected ANY, EMPTY or '(' instead of 
   440:	invokevirtual	#70; //Method scala/collection/mutable/StringBuilder.append:(Ljava/lang/Object;)Lscala/collection/mutable/StringBuilder;
   443:	aload_0
   444:	invokevirtual	#38; //Method value:()Ljava/lang/String;
   447:	invokevirtual	#70; //Method scala/collection/mutable/StringBuilder.append:(Ljava/lang/Object;)Lscala/collection/mutable/StringBuilder;
   450:	invokevirtual	#75; //Method scala/collection/mutable/StringBuilder.toString:()Ljava/lang/String;
   453:	astore	7
   455:	new	#77; //class java/lang/RuntimeException
   458:	dup
   459:	aload	7
   461:	invokespecial	#78; //Method java/lang/RuntimeException."<init>":(Ljava/lang/String;)V
   464:	athrow
   465:	new	#49; //class scala/MatchError
   468:	dup
   469:	aload	8
   471:	invokevirtual	#204; //Method java/lang/String.toString:()Ljava/lang/String;
   474:	invokespecial	#61; //Method scala/MatchError."<init>":(Ljava/lang/String;)V
   477:	athrow
   478:	new	#49; //class scala/MatchError
   481:	dup
   482:	iload	9
   484:	invokestatic	#55; //Method scala/runtime/BoxesRunTime.boxToInteger:(I)Ljava/lang/Integer;
   487:	invokevirtual	#60; //Method java/lang/Object.toString:()Ljava/lang/String;
   490:	invokespecial	#61; //Method scala/MatchError."<init>":(Ljava/lang/String;)V
   493:	athrow
  LineNumberTable: 
   line 47: 0
   line 21: 36
   line 77: 40
   line 47: 76
   line 21: 92
   line 56: 96
   line 57: 100
   line 58: 104
   line 59: 112
   line 61: 126
   line 62: 130
   line 21: 164
   line 72: 168
   line 62: 204
   line 21: 220
   line 66: 224
   line 67: 242
   line 68: 246
   line 69: 251
   line 70: 257
   line 62: 261
   line 21: 277
   line 64: 281
   line 62: 287
   line 47: 303
   line 21: 319
   line 49: 323
   line 21: 356
   line 50: 360
   line 49: 366
   line 21: 406
   line 51: 410
   line 47: 413
   line 49: 414
   line 21: 427
   line 52: 431
   line 49: 465
   line 47: 478

  LocalVariableTable: 
   Start  Length  Slot  Name   Signature
   0      494      0    this       Lscala/xml/dtd/ContentModelParser$;
   242      16      3    res       Lscala/xml/dtd/MIXED;
   136      167      4    temp5       I
   329      84      8    temp2       Ljava/lang/String;
   414      64      8    temp2       Ljava/lang/String;
   6      488      9    temp6       I


public scala.util.regexp.Base$RegExp maybeSuffix(scala.util.regexp.Base$RegExp);
  Code:
   Stack=9, Locals=3, Args_size=2
   0:	aload_0
   1:	invokevirtual	#25; //Method token:()I
   4:	istore_2
   5:	iload_2
   6:	tableswitch{ //6 to 8
		6: 182;
		7: 116;
		8: 55;
		default: 32 }
   32:	iconst_1
   33:	ifeq	40
   36:	aload_1
   37:	goto	201
   40:	new	#49; //class scala/MatchError
   43:	dup
   44:	iload_2
   45:	invokestatic	#55; //Method scala/runtime/BoxesRunTime.boxToInteger:(I)Ljava/lang/Integer;
   48:	invokevirtual	#60; //Method java/lang/Object.toString:()Ljava/lang/String;
   51:	invokespecial	#61; //Method scala/MatchError."<init>":(Ljava/lang/String;)V
   54:	athrow
   55:	iconst_1
   56:	ifeq	101
   59:	aload_0
   60:	invokevirtual	#47; //Method nextToken:()V
   63:	getstatic	#32; //Field scala/xml/dtd/ContentModel$.MODULE$:Lscala/xml/dtd/ContentModel$;
   66:	invokevirtual	#133; //Method scala/xml/dtd/ContentModel$.Alt:()Lscala/util/regexp/Base$Alt$;
   69:	getstatic	#106; //Field scala/Predef$.MODULE$:Lscala/Predef$;
   72:	iconst_2
   73:	anewarray	#108; //class scala/util/regexp/Base$RegExp
   76:	dup
   77:	iconst_0
   78:	getstatic	#32; //Field scala/xml/dtd/ContentModel$.MODULE$:Lscala/xml/dtd/ContentModel$;
   81:	invokevirtual	#183; //Method scala/xml/dtd/ContentModel$.Eps:()Lscala/util/regexp/Base$Eps$;
   84:	aastore
   85:	dup
   86:	iconst_1
   87:	aload_1
   88:	aastore
   89:	checkcast	#110; //class "[Ljava/lang/Object;"
   92:	invokevirtual	#114; //Method scala/Predef$.wrapRefArray:([Ljava/lang/Object;)Lscala/collection/mutable/WrappedArray;
   95:	invokevirtual	#142; //Method scala/util/regexp/Base$Alt$.apply:(Lscala/collection/Seq;)Lscala/util/regexp/Base$Alt;
   98:	goto	201
   101:	new	#49; //class scala/MatchError
   104:	dup
   105:	iload_2
   106:	invokestatic	#55; //Method scala/runtime/BoxesRunTime.boxToInteger:(I)Ljava/lang/Integer;
   109:	invokevirtual	#60; //Method java/lang/Object.toString:()Ljava/lang/String;
   112:	invokespecial	#61; //Method scala/MatchError."<init>":(Ljava/lang/String;)V
   115:	athrow
   116:	iconst_1
   117:	ifeq	167
   120:	aload_0
   121:	invokevirtual	#47; //Method nextToken:()V
   124:	getstatic	#32; //Field scala/xml/dtd/ContentModel$.MODULE$:Lscala/xml/dtd/ContentModel$;
   127:	invokevirtual	#151; //Method scala/xml/dtd/ContentModel$.Sequ:()Lscala/util/regexp/Base$Sequ$;
   130:	getstatic	#106; //Field scala/Predef$.MODULE$:Lscala/Predef$;
   133:	iconst_2
   134:	anewarray	#108; //class scala/util/regexp/Base$RegExp
   137:	dup
   138:	iconst_0
   139:	aload_1
   140:	aastore
   141:	dup
   142:	iconst_1
   143:	new	#221; //class scala/util/regexp/Base$Star
   146:	dup
   147:	getstatic	#32; //Field scala/xml/dtd/ContentModel$.MODULE$:Lscala/xml/dtd/ContentModel$;
   150:	aload_1
   151:	invokespecial	#224; //Method scala/util/regexp/Base$Star."<init>":(Lscala/util/regexp/Base;Lscala/util/regexp/Base$RegExp;)V
   154:	aastore
   155:	checkcast	#110; //class "[Ljava/lang/Object;"
   158:	invokevirtual	#114; //Method scala/Predef$.wrapRefArray:([Ljava/lang/Object;)Lscala/collection/mutable/WrappedArray;
   161:	invokevirtual	#156; //Method scala/util/regexp/Base$Sequ$.apply:(Lscala/collection/Seq;)Lscala/util/regexp/Base$RegExp;
   164:	goto	201
   167:	new	#49; //class scala/MatchError
   170:	dup
   171:	iload_2
   172:	invokestatic	#55; //Method scala/runtime/BoxesRunTime.boxToInteger:(I)Ljava/lang/Integer;
   175:	invokevirtual	#60; //Method java/lang/Object.toString:()Ljava/lang/String;
   178:	invokespecial	#61; //Method scala/MatchError."<init>":(Ljava/lang/String;)V
   181:	athrow
   182:	iconst_1
   183:	ifeq	202
   186:	aload_0
   187:	invokevirtual	#47; //Method nextToken:()V
   190:	new	#221; //class scala/util/regexp/Base$Star
   193:	dup
   194:	getstatic	#32; //Field scala/xml/dtd/ContentModel$.MODULE$:Lscala/xml/dtd/ContentModel$;
   197:	aload_1
   198:	invokespecial	#224; //Method scala/util/regexp/Base$Star."<init>":(Lscala/util/regexp/Base;Lscala/util/regexp/Base$RegExp;)V
   201:	areturn
   202:	new	#49; //class scala/MatchError
   205:	dup
   206:	iload_2
   207:	invokestatic	#55; //Method scala/runtime/BoxesRunTime.boxToInteger:(I)Ljava/lang/Integer;
   210:	invokevirtual	#60; //Method java/lang/Object.toString:()Ljava/lang/String;
   213:	invokespecial	#61; //Method scala/MatchError."<init>":(Ljava/lang/String;)V
   216:	athrow
  LineNumberTable: 
   line 38: 0
   line 21: 32
   line 42: 36
   line 38: 40
   line 21: 55
   line 41: 59
   line 38: 101
   line 21: 116
   line 40: 120
   line 38: 167
   line 21: 182
   line 39: 186
   line 38: 201

  LocalVariableTable: 
   Start  Length  Slot  Name   Signature
   0      217      0    this       Lscala/xml/dtd/ContentModelParser$;
   0      217      1    s       Lscala/util/regexp/Base$RegExp;
   5      212      2    temp1       I


public void accept(int);
  Code:
   Stack=3, Locals=4, Args_size=2
   0:	aload_0
   1:	invokevirtual	#25; //Method token:()I
   4:	iload_1
   5:	if_icmpeq	84
   8:	iload_1
   9:	ldc	#185; //int 6
   11:	if_icmpne	35
   14:	aload_0
   15:	invokevirtual	#25; //Method token:()I
   18:	ldc	#227; //int 10
   20:	if_icmpne	35
   23:	ldc	#229; //String in DTDs, \nmixed content models must be like (#PCDATA|Name|Name|...)*
   25:	astore_2
   26:	new	#77; //class java/lang/RuntimeException
   29:	dup
   30:	aload_2
   31:	invokespecial	#78; //Method java/lang/RuntimeException."<init>":(Ljava/lang/String;)V
   34:	athrow
   35:	new	#63; //class scala/collection/mutable/StringBuilder
   38:	dup
   39:	invokespecial	#64; //Method scala/collection/mutable/StringBuilder."<init>":()V
   42:	ldc	#231; //String expected 
   44:	invokevirtual	#70; //Method scala/collection/mutable/StringBuilder.append:(Ljava/lang/Object;)Lscala/collection/mutable/StringBuilder;
   47:	aload_0
   48:	iload_1
   49:	invokevirtual	#74; //Method token2string:(I)Ljava/lang/String;
   52:	invokevirtual	#70; //Method scala/collection/mutable/StringBuilder.append:(Ljava/lang/Object;)Lscala/collection/mutable/StringBuilder;
   55:	ldc	#233; //String , got unexpected token:
   57:	invokevirtual	#70; //Method scala/collection/mutable/StringBuilder.append:(Ljava/lang/Object;)Lscala/collection/mutable/StringBuilder;
   60:	aload_0
   61:	aload_0
   62:	invokevirtual	#25; //Method token:()I
   65:	invokevirtual	#74; //Method token2string:(I)Ljava/lang/String;
   68:	invokevirtual	#70; //Method scala/collection/mutable/StringBuilder.append:(Ljava/lang/Object;)Lscala/collection/mutable/StringBuilder;
   71:	invokevirtual	#75; //Method scala/collection/mutable/StringBuilder.toString:()Ljava/lang/String;
   74:	astore_3
   75:	new	#77; //class java/lang/RuntimeException
   78:	dup
   79:	aload_3
   80:	invokespecial	#78; //Method java/lang/RuntimeException."<init>":(Ljava/lang/String;)V
   83:	athrow
   84:	aload_0
   85:	invokevirtual	#47; //Method nextToken:()V
   88:	return
  LineNumberTable: 
   line 26: 0
   line 27: 8
   line 28: 23
   line 32: 35
   line 31: 42
   line 32: 55
   line 31: 74
   line 34: 84

  LocalVariableTable: 
   Start  Length  Slot  Name   Signature
   0      89      0    this       Lscala/xml/dtd/ContentModelParser$;
   0      89      1    tok       I


public scala.xml.dtd.ContentModel parse(java.lang.String);
  Code:
   Stack=2, Locals=2, Args_size=2
   0:	aload_0
   1:	aload_1
   2:	invokevirtual	#239; //Method initScanner:(Ljava/lang/String;)V
   5:	aload_0
   6:	invokevirtual	#241; //Method contentspec:()Lscala/xml/dtd/ContentModel;
   9:	areturn
  LineNumberTable: 
   line 23: 0

  LocalVariableTable: 
   Start  Length  Slot  Name   Signature
   0      10      0    this       Lscala/xml/dtd/ContentModelParser$;
   0      10      1    s       Ljava/lang/String;


}

