Compiled from "ContentModel.scala"
public final class scala.xml.dtd.ContentModel$$anonfun$buildString$2 extends scala.runtime.AbstractFunction1 implements java.io.Serializable
  SourceFile: "ContentModel.scala"
  Scala: length = 0x
   
  InnerClass: 
   public abstract RegExp=class scala/util/regexp/Base$RegExp of class scala/util/regexp/Base
   public final $anonfun$buildString$2=class scala/xml/dtd/ContentModel$$anonfun$buildString$2 of class scala/xml/dtd/ContentModel
  minor version: 0
  major version: 49
  Constant pool:
Asciz	SourceFile;
Asciz	ContentModel.scala;
Asciz	<clinit>;
Asciz	()V;
Asciz	Code;
Asciz	serialVersionUID;
Asciz	J;
Asciz	scala/xml/dtd/ContentModel$$anonfun$buildString$2;
class	scala/xml/dtd/ContentModel$$anonfun$buildString$2
NameAndType	serialVersionUID:J
Field	scala/xml/dtd/ContentModel$$anonfun$buildString$2.serialVersionUID:J
Asciz	sep$1;
Asciz	C;
Asciz	sb$1;
Asciz	Lscala/collection/mutable/StringBuilder;;
Asciz	<init>;
Asciz	(Lscala/collection/mutable/StringBuilder;C)V;
Asciz	LineNumberTable;
NameAndType	sb$1:Lscala/collection/mutable/StringBuilder;
Field	scala/xml/dtd/ContentModel$$anonfun$buildString$2.sb$1:Lscala/collection/mutable/StringBuilder;
NameAndType	sep$1:C
Field	scala/xml/dtd/ContentModel$$anonfun$buildString$2.sep$1:C
Asciz	scala/runtime/AbstractFunction1;
class	scala/runtime/AbstractFunction1
NameAndType	"<init>":()V
Method	scala/runtime/AbstractFunction1."<init>":()V
Asciz	apply;
Asciz	(Ljava/lang/Object;)Ljava/lang/Object;;
Asciz	scala/util/regexp/Base$RegExp;
class	scala/util/regexp/Base$RegExp
Asciz	(Lscala/util/regexp/Base$RegExp;)Lscala/collection/mutable/StringBuilder;;
NameAndType	apply:(Lscala/util/regexp/Base$RegExp;)Lscala/collection/mutable/StringBuilder;
Method	scala/xml/dtd/ContentModel$$anonfun$buildString$2.apply:(Lscala/util/regexp/Base$RegExp;)Lscala/collection/mutable/StringBuilder;
Asciz	this;
Asciz	Lscala/xml/dtd/ContentModel$$anonfun$buildString$2;;
Asciz	v1;
Asciz	Ljava/lang/Object;;
Asciz	LocalVariableTable;
Asciz	scala/collection/mutable/StringBuilder;
class	scala/collection/mutable/StringBuilder
Asciz	append;
Asciz	(C)Lscala/collection/mutable/StringBuilder;;
NameAndType	append:(C)Lscala/collection/mutable/StringBuilder;
Method	scala/collection/mutable/StringBuilder.append:(C)Lscala/collection/mutable/StringBuilder;
Asciz	scala/xml/dtd/ContentModel$;
class	scala/xml/dtd/ContentModel$
Asciz	MODULE$;
Asciz	Lscala/xml/dtd/ContentModel$;;
NameAndType	MODULE$:Lscala/xml/dtd/ContentModel$;
Field	scala/xml/dtd/ContentModel$.MODULE$:Lscala/xml/dtd/ContentModel$;
Asciz	buildString;
Asciz	(Lscala/util/regexp/Base$RegExp;Lscala/collection/mutable/StringBuilder;)Lscala/collection/mutable/StringBuilder;;
NameAndType	buildString:(Lscala/util/regexp/Base$RegExp;Lscala/collection/mutable/StringBuilder;)Lscala/collection/mutable/StringBuilder;
Method	scala/xml/dtd/ContentModel$.buildString:(Lscala/util/regexp/Base$RegExp;Lscala/collection/mutable/StringBuilder;)Lscala/collection/mutable/StringBuilder;
Asciz	z;
Asciz	Lscala/util/regexp/Base$RegExp;;
Asciz	Scala;
Asciz	InnerClasses;
Asciz	scala/util/regexp/Base;
class	scala/util/regexp/Base
Asciz	RegExp;
Asciz	scala/xml/dtd/ContentModel;
class	scala/xml/dtd/ContentModel
Asciz	$anonfun$buildString$2;
Asciz	java/io/Serializable;
class	java/io/Serializable

{
public static final long serialVersionUID;
  Signature: J

public final char sep$1;
  Signature: C

public final scala.collection.mutable.StringBuilder sb$1;
  Signature: Lscala/collection/mutable/StringBuilder;

public static {};
  Signature: ()V
  Code:
   Stack=2, Locals=0, Args_size=0
	lconst_0
	putstatic	Field serialVersionUID:J
	return
  Labels:

public scala.xml.dtd.ContentModel$$anonfun$buildString$2(scala.collection.mutable.StringBuilder, char);
  Signature: (Lscala/collection/mutable/StringBuilder;C)V
  Code:
   Stack=2, Locals=3, Args_size=3
	aload_0
	aload_1
	putfield	Field sb$1:Lscala/collection/mutable/StringBuilder;
	aload_0
	iload_2
	putfield	Field sep$1:C
	aload_0
	invokespecial	Method scala/runtime/AbstractFunction1."<init>":()V
	return
  Labels:

public final java.lang.Object apply(java.lang.Object);
  Signature: (Ljava/lang/Object;)Ljava/lang/Object;
  Code:
   Stack=2, Locals=2, Args_size=2
	aload_0
	aload_1
	checkcast	class scala/util/regexp/Base$RegExp
	invokevirtual	Method apply:(Lscala/util/regexp/Base$RegExp;)Lscala/collection/mutable/StringBuilder;
	areturn
  Labels:
  LocalVariableTable: 
   Start  Length  Slot  Name   Signature
   0      9      0    this       Lscala/xml/dtd/ContentModel$$anonfun$buildString$2;
   0      9      1    v1       Ljava/lang/Object;


public final scala.collection.mutable.StringBuilder apply(scala.util.regexp.Base$RegExp);
  Signature: (Lscala/util/regexp/Base$RegExp;)Lscala/collection/mutable/StringBuilder;
  Code:
   Stack=3, Locals=2, Args_size=2
	aload_0
	getfield	Field sb$1:Lscala/collection/mutable/StringBuilder;
	aload_0
	getfield	Field sep$1:C
	invokevirtual	Method scala/collection/mutable/StringBuilder.append:(C)Lscala/collection/mutable/StringBuilder;
	pop
	getstatic	Field scala/xml/dtd/ContentModel$.MODULE$:Lscala/xml/dtd/ContentModel$;
	aload_1
	aload_0
	getfield	Field sb$1:Lscala/collection/mutable/StringBuilder;
	invokevirtual	Method scala/xml/dtd/ContentModel$.buildString:(Lscala/util/regexp/Base$RegExp;Lscala/collection/mutable/StringBuilder;)Lscala/collection/mutable/StringBuilder;
	areturn
  Labels:
  LocalVariableTable: 
   Start  Length  Slot  Name   Signature
   0      24      0    this       Lscala/xml/dtd/ContentModel$$anonfun$buildString$2;
   0      24      1    z       Lscala/util/regexp/Base$RegExp;


}

