Compiled from "ContentModel.scala"
public final class scala.xml.dtd.ContentModel$ElemName$ extends scala.runtime.AbstractFunction1 implements scala.ScalaObject
  SourceFile: "ContentModel.scala"
  Scala: length = 0x
   
  InnerClass: 
   public ElemName=class scala/xml/dtd/ContentModel$ElemName of class scala/xml/dtd/ContentModel
  minor version: 0
  major version: 49
  Constant pool:
Asciz	SourceFile;
Asciz	ContentModel.scala;
Asciz	MODULE$;
Asciz	Lscala/xml/dtd/ContentModel$ElemName$;;
Asciz	<clinit>;
Asciz	()V;
Asciz	Code;
Asciz	scala/xml/dtd/ContentModel$ElemName$;
class	scala/xml/dtd/ContentModel$ElemName$
Asciz	<init>;
NameAndType	"<init>":()V
Method	scala/xml/dtd/ContentModel$ElemName$."<init>":()V
Asciz	unapply;
Asciz	(Lscala/xml/dtd/ContentModel$ElemName;)Lscala/Option;;
Asciz	LineNumberTable;
Asciz	scala/None$;
class	scala/None$
Asciz	Lscala/None$;;
NameAndType	MODULE$:Lscala/None$;
Field	scala/None$.MODULE$:Lscala/None$;
Asciz	scala/Some;
class	scala/Some
Asciz	scala/xml/dtd/ContentModel$ElemName;
class	scala/xml/dtd/ContentModel$ElemName
Asciz	name;
Asciz	()Ljava/lang/String;;
NameAndType	name:()Ljava/lang/String;
Method	scala/xml/dtd/ContentModel$ElemName.name:()Ljava/lang/String;
Asciz	(Ljava/lang/Object;)V;
NameAndType	"<init>":(Ljava/lang/Object;)V
Method	scala/Some."<init>":(Ljava/lang/Object;)V
Asciz	this;
Asciz	x$0;
Asciz	Lscala/xml/dtd/ContentModel$ElemName;;
Asciz	LocalVariableTable;
Asciz	apply;
Asciz	(Ljava/lang/String;)Lscala/xml/dtd/ContentModel$ElemName;;
Asciz	(Ljava/lang/String;)V;
NameAndType	"<init>":(Ljava/lang/String;)V
Method	scala/xml/dtd/ContentModel$ElemName."<init>":(Ljava/lang/String;)V
Asciz	Ljava/lang/String;;
Asciz	(Ljava/lang/Object;)Ljava/lang/Object;;
Asciz	java/lang/String;
class	java/lang/String
NameAndType	apply:(Ljava/lang/String;)Lscala/xml/dtd/ContentModel$ElemName;
Method	scala/xml/dtd/ContentModel$ElemName$.apply:(Ljava/lang/String;)Lscala/xml/dtd/ContentModel$ElemName;
Asciz	v1;
Asciz	Ljava/lang/Object;;
Asciz	scala/runtime/AbstractFunction1;
class	scala/runtime/AbstractFunction1
Method	scala/runtime/AbstractFunction1."<init>":()V
NameAndType	MODULE$:Lscala/xml/dtd/ContentModel$ElemName$;
Field	scala/xml/dtd/ContentModel$ElemName$.MODULE$:Lscala/xml/dtd/ContentModel$ElemName$;
Asciz	Scala;
Asciz	InnerClasses;
Asciz	scala/xml/dtd/ContentModel;
class	scala/xml/dtd/ContentModel
Asciz	ElemName;
Asciz	scala/ScalaObject;
class	scala/ScalaObject

{
public static final scala.xml.dtd.ContentModel$ElemName$ MODULE$;
  Signature: Lscala/xml/dtd/ContentModel$ElemName$;

public static {};
  Signature: ()V
  Code:
   Stack=1, Locals=0, Args_size=0
	new	class scala/xml/dtd/ContentModel$ElemName$
	invokespecial	Method "<init>":()V
	return
  Labels:

public scala.Option unapply(scala.xml.dtd.ContentModel$ElemName);
  Signature: (Lscala/xml/dtd/ContentModel$ElemName;)Lscala/Option;
  Code:
   Stack=3, Locals=2, Args_size=2
	aload_1
	ifnonnull	l1 // new
	getstatic	Field scala/None$.MODULE$:Lscala/None$;
	goto	l2 // areturn
l1	new	class scala/Some
	dup
	aload_1
	invokevirtual	Method scala/xml/dtd/ContentModel$ElemName.name:()Ljava/lang/String;
	invokespecial	Method scala/Some."<init>":(Ljava/lang/Object;)V
l2	areturn
  Labels:
   	l1 = 10 // new
   	l2 = 21 // areturn
  LocalVariableTable: 
   Start  Length  Slot  Name   Signature
   0      22      0    this       Lscala/xml/dtd/ContentModel$ElemName$;
   0      22      1    x$0       Lscala/xml/dtd/ContentModel$ElemName;


public scala.xml.dtd.ContentModel$ElemName apply(java.lang.String);
  Signature: (Ljava/lang/String;)Lscala/xml/dtd/ContentModel$ElemName;
  Code:
   Stack=3, Locals=2, Args_size=2
	new	class scala/xml/dtd/ContentModel$ElemName
	dup
	aload_1
	invokespecial	Method scala/xml/dtd/ContentModel$ElemName."<init>":(Ljava/lang/String;)V
	areturn
  Labels:
  LocalVariableTable: 
   Start  Length  Slot  Name   Signature
   0      9      0    this       Lscala/xml/dtd/ContentModel$ElemName$;
   0      9      1    name       Ljava/lang/String;


public java.lang.Object apply(java.lang.Object);
  Signature: (Ljava/lang/Object;)Ljava/lang/Object;
  Code:
   Stack=2, Locals=2, Args_size=2
	aload_0
	aload_1
	checkcast	class java/lang/String
	invokevirtual	Method apply:(Ljava/lang/String;)Lscala/xml/dtd/ContentModel$ElemName;
	areturn
  Labels:
  LocalVariableTable: 
   Start  Length  Slot  Name   Signature
   0      9      0    this       Lscala/xml/dtd/ContentModel$ElemName$;
   0      9      1    v1       Ljava/lang/Object;


public scala.xml.dtd.ContentModel$ElemName$();
  Signature: ()V
  Code:
   Stack=1, Locals=1, Args_size=1
	aload_0
	invokespecial	Method scala/runtime/AbstractFunction1."<init>":()V
	aload_0
	putstatic	Field MODULE$:Lscala/xml/dtd/ContentModel$ElemName$;
	return
  Labels:

}

