Compiled from "ContentModelParser.scala"
public final class scala.xml.dtd.ContentModelParser$ extends scala.xml.dtd.Scanner implements scala.ScalaObject
  SourceFile: "ContentModelParser.scala"
  Scala: length = 0x
   
  InnerClass: 
   public Alt=class scala/util/regexp/Base$Alt of class scala/util/regexp/Base
   public Star=class scala/util/regexp/Base$Star of class scala/util/regexp/Base
   public abstract RegExp=class scala/util/regexp/Base$RegExp of class scala/util/regexp/Base
   public abstract Label=class scala/util/regexp/WordExp$Label of class scala/util/regexp/WordExp
   public Letter=class scala/util/regexp/WordExp$Letter of class scala/util/regexp/WordExp
   public ElemName=class scala/xml/dtd/ContentModel$ElemName of class scala/xml/dtd/ContentModel
  minor version: 0
  major version: 49
  Constant pool:
Asciz	SourceFile;
Asciz	ContentModelParser.scala;
Asciz	Scala;
Asciz	MODULE$;
Asciz	Lscala/xml/dtd/ContentModelParser$;;
Asciz	<clinit>;
Asciz	()V;
Asciz	Code;
Asciz	scala/xml/dtd/ContentModelParser$;
class	scala/xml/dtd/ContentModelParser$
Asciz	<init>;
NameAndType	"<init>":()V
Method	scala/xml/dtd/ContentModelParser$."<init>":()V
Asciz	LineNumberTable;
Asciz	scala/xml/dtd/Scanner;
class	scala/xml/dtd/Scanner
Method	scala/xml/dtd/Scanner."<init>":()V
NameAndType	MODULE$:Lscala/xml/dtd/ContentModelParser$;
Field	scala/xml/dtd/ContentModelParser$.MODULE$:Lscala/xml/dtd/ContentModelParser$;
Asciz	atom;
Asciz	()Lscala/util/regexp/WordExp$Letter;;
Asciz	token;
Asciz	()I;
NameAndType	token:()I
Method	scala/xml/dtd/ContentModelParser$.token:()I
Asciz	scala/util/regexp/WordExp$Letter;
class	scala/util/regexp/WordExp$Letter
Asciz	scala/xml/dtd/ContentModel$;
class	scala/xml/dtd/ContentModel$
Asciz	Lscala/xml/dtd/ContentModel$;;
NameAndType	MODULE$:Lscala/xml/dtd/ContentModel$;
Field	scala/xml/dtd/ContentModel$.MODULE$:Lscala/xml/dtd/ContentModel$;
Asciz	scala/xml/dtd/ContentModel$ElemName;
class	scala/xml/dtd/ContentModel$ElemName
Asciz	value;
Asciz	()Ljava/lang/String;;
NameAndType	value:()Ljava/lang/String;
Method	scala/xml/dtd/ContentModelParser$.value:()Ljava/lang/String;
Asciz	(Ljava/lang/String;)V;
NameAndType	"<init>":(Ljava/lang/String;)V
Method	scala/xml/dtd/ContentModel$ElemName."<init>":(Ljava/lang/String;)V
Asciz	(Lscala/util/regexp/WordExp;Lscala/util/regexp/WordExp$Label;)V;
NameAndType	"<init>":(Lscala/util/regexp/WordExp;Lscala/util/regexp/WordExp$Label;)V
Method	scala/util/regexp/WordExp$Letter."<init>":(Lscala/util/regexp/WordExp;Lscala/util/regexp/WordExp$Label;)V
Asciz	nextToken;
NameAndType	nextToken:()V
Method	scala/xml/dtd/ContentModelParser$.nextToken:()V
Asciz	scala/MatchError;
class	scala/MatchError
Asciz	scala/runtime/BoxesRunTime;
class	scala/runtime/BoxesRunTime
Asciz	boxToInteger;
Asciz	(I)Ljava/lang/Integer;;
NameAndType	boxToInteger:(I)Ljava/lang/Integer;
Method	scala/runtime/BoxesRunTime.boxToInteger:(I)Ljava/lang/Integer;
Asciz	java/lang/Object;
class	java/lang/Object
Asciz	toString;
NameAndType	toString:()Ljava/lang/String;
Method	java/lang/Object.toString:()Ljava/lang/String;
Method	scala/MatchError."<init>":(Ljava/lang/String;)V
Asciz	scala/collection/mutable/StringBuilder;
class	scala/collection/mutable/StringBuilder
Method	scala/collection/mutable/StringBuilder."<init>":()V
Asciz	expected Name, got:;
String	expected Name, got:
Asciz	append;
Asciz	(Ljava/lang/Object;)Lscala/collection/mutable/StringBuilder;;
NameAndType	append:(Ljava/lang/Object;)Lscala/collection/mutable/StringBuilder;
Method	scala/collection/mutable/StringBuilder.append:(Ljava/lang/Object;)Lscala/collection/mutable/StringBuilder;
Asciz	token2string;
Asciz	(I)Ljava/lang/String;;
NameAndType	token2string:(I)Ljava/lang/String;
Method	scala/xml/dtd/ContentModelParser$.token2string:(I)Ljava/lang/String;
Method	scala/collection/mutable/StringBuilder.toString:()Ljava/lang/String;
Asciz	java/lang/RuntimeException;
class	java/lang/RuntimeException
Method	java/lang/RuntimeException."<init>":(Ljava/lang/String;)V
Asciz	this;
Asciz	a;
Asciz	Lscala/util/regexp/WordExp$Letter;;
Asciz	temp9;
Asciz	I;
Asciz	LocalVariableTable;
Asciz	particle;
Asciz	()Lscala/util/regexp/Base$RegExp;;
Asciz	expected '(' or Name, got:;
String	expected '(' or Name, got:
Asciz	sOpt;
NameAndType	sOpt:()V
Method	scala/xml/dtd/ContentModelParser$.sOpt:()V
Asciz	regexp;
NameAndType	regexp:()Lscala/util/regexp/Base$RegExp;
Method	scala/xml/dtd/ContentModelParser$.regexp:()Lscala/util/regexp/Base$RegExp;
Asciz	maybeSuffix;
Asciz	(Lscala/util/regexp/Base$RegExp;)Lscala/util/regexp/Base$RegExp;;
NameAndType	maybeSuffix:(Lscala/util/regexp/Base$RegExp;)Lscala/util/regexp/Base$RegExp;
Method	scala/xml/dtd/ContentModelParser$.maybeSuffix:(Lscala/util/regexp/Base$RegExp;)Lscala/util/regexp/Base$RegExp;
Asciz	temp8;
Asciz	choiceRest;
Asciz	(Lscala/util/regexp/Base$RegExp;)Lscala/util/regexp/Base$Alt;;
Asciz	scala/Predef$;
class	scala/Predef$
Asciz	Lscala/Predef$;;
NameAndType	MODULE$:Lscala/Predef$;
Field	scala/Predef$.MODULE$:Lscala/Predef$;
Asciz	scala/util/regexp/Base$RegExp;
class	scala/util/regexp/Base$RegExp
Asciz	[Ljava/lang/Object;;
class	"[Ljava/lang/Object;"
Asciz	wrapRefArray;
Asciz	([Ljava/lang/Object;)Lscala/collection/mutable/WrappedArray;;
NameAndType	wrapRefArray:([Ljava/lang/Object;)Lscala/collection/mutable/WrappedArray;
Method	scala/Predef$.wrapRefArray:([Ljava/lang/Object;)Lscala/collection/mutable/WrappedArray;
Asciz	scala/collection/TraversableLike;
class	scala/collection/TraversableLike
Asciz	toList;
Asciz	()Lscala/collection/immutable/List;;
NameAndType	toList:()Lscala/collection/immutable/List;
InterfaceMethod	scala/collection/TraversableLike.toList:()Lscala/collection/immutable/List;
int	9;
NameAndType	particle:()Lscala/util/regexp/Base$RegExp;
Method	scala/xml/dtd/ContentModelParser$.particle:()Lscala/util/regexp/Base$RegExp;
Asciz	scala/collection/immutable/List;
class	scala/collection/immutable/List
Asciz	$colon$colon;
Asciz	(Ljava/lang/Object;)Lscala/collection/immutable/List;;
NameAndType	$colon$colon:(Ljava/lang/Object;)Lscala/collection/immutable/List;
Method	scala/collection/immutable/List.$colon$colon:(Ljava/lang/Object;)Lscala/collection/immutable/List;
Asciz	Alt;
Asciz	()Lscala/util/regexp/Base$Alt$;;
NameAndType	Alt:()Lscala/util/regexp/Base$Alt$;
Method	scala/xml/dtd/ContentModel$.Alt:()Lscala/util/regexp/Base$Alt$;
Asciz	reverse;
NameAndType	reverse:()Lscala/collection/immutable/List;
Method	scala/collection/immutable/List.reverse:()Lscala/collection/immutable/List;
Asciz	scala/util/regexp/Base$Alt$;
class	scala/util/regexp/Base$Alt$
Asciz	apply;
Asciz	(Lscala/collection/Seq;)Lscala/util/regexp/Base$Alt;;
NameAndType	apply:(Lscala/collection/Seq;)Lscala/util/regexp/Base$Alt;
Method	scala/util/regexp/Base$Alt$.apply:(Lscala/collection/Seq;)Lscala/util/regexp/Base$Alt;
Asciz	p;
Asciz	Lscala/util/regexp/Base$RegExp;;
Asciz	k;
Asciz	Lscala/collection/immutable/List;;
Asciz	seqRest;
Asciz	Sequ;
Asciz	()Lscala/util/regexp/Base$Sequ$;;
NameAndType	Sequ:()Lscala/util/regexp/Base$Sequ$;
Method	scala/xml/dtd/ContentModel$.Sequ:()Lscala/util/regexp/Base$Sequ$;
Asciz	scala/util/regexp/Base$Sequ$;
class	scala/util/regexp/Base$Sequ$
Asciz	(Lscala/collection/Seq;)Lscala/util/regexp/Base$RegExp;;
NameAndType	apply:(Lscala/collection/Seq;)Lscala/util/regexp/Base$RegExp;
Method	scala/util/regexp/Base$Sequ$.apply:(Lscala/collection/Seq;)Lscala/util/regexp/Base$RegExp;
NameAndType	choiceRest:(Lscala/util/regexp/Base$RegExp;)Lscala/util/regexp/Base$Alt;
Method	scala/xml/dtd/ContentModelParser$.choiceRest:(Lscala/util/regexp/Base$RegExp;)Lscala/util/regexp/Base$Alt;
Asciz	accept;
Asciz	(I)V;
NameAndType	accept:(I)V
Method	scala/xml/dtd/ContentModelParser$.accept:(I)V
NameAndType	seqRest:(Lscala/util/regexp/Base$RegExp;)Lscala/util/regexp/Base$RegExp;
Method	scala/xml/dtd/ContentModelParser$.seqRest:(Lscala/util/regexp/Base$RegExp;)Lscala/util/regexp/Base$RegExp;
Asciz	q;
Asciz	Lscala/util/regexp/Base$Alt;;
Asciz	temp7;
int	13;
Asciz	contentspec;
Asciz	()Lscala/xml/dtd/ContentModel;;
Asciz	unexpected token:;
String	unexpected token:
Asciz	scala/xml/dtd/ELEMENTS;
class	scala/xml/dtd/ELEMENTS
Asciz	(Lscala/util/regexp/Base$RegExp;)V;
NameAndType	"<init>":(Lscala/util/regexp/Base$RegExp;)V
Method	scala/xml/dtd/ELEMENTS."<init>":(Lscala/util/regexp/Base$RegExp;)V
Asciz	scala/xml/dtd/MIXED;
class	scala/xml/dtd/MIXED
Asciz	Eps;
Asciz	()Lscala/util/regexp/Base$Eps$;;
NameAndType	Eps:()Lscala/util/regexp/Base$Eps$;
Method	scala/xml/dtd/ContentModel$.Eps:()Lscala/util/regexp/Base$Eps$;
Method	scala/xml/dtd/MIXED."<init>":(Lscala/util/regexp/Base$RegExp;)V
int	6;
Asciz	scala/xml/dtd/PCDATA$;
class	scala/xml/dtd/PCDATA$
Asciz	Lscala/xml/dtd/PCDATA$;;
NameAndType	MODULE$:Lscala/xml/dtd/PCDATA$;
Field	scala/xml/dtd/PCDATA$.MODULE$:Lscala/xml/dtd/PCDATA$;
Asciz	ANY;
String	ANY
Asciz	equals;
Asciz	(Ljava/lang/Object;)Z;
NameAndType	equals:(Ljava/lang/Object;)Z
Method	java/lang/Object.equals:(Ljava/lang/Object;)Z
Asciz	scala/xml/dtd/ANY$;
class	scala/xml/dtd/ANY$
Asciz	Lscala/xml/dtd/ANY$;;
NameAndType	MODULE$:Lscala/xml/dtd/ANY$;
Field	scala/xml/dtd/ANY$.MODULE$:Lscala/xml/dtd/ANY$;
Asciz	java/lang/String;
class	java/lang/String
Method	java/lang/String.toString:()Ljava/lang/String;
Asciz	EMPTY;
String	EMPTY
Asciz	scala/xml/dtd/EMPTY$;
class	scala/xml/dtd/EMPTY$
Asciz	Lscala/xml/dtd/EMPTY$;;
NameAndType	MODULE$:Lscala/xml/dtd/EMPTY$;
Field	scala/xml/dtd/EMPTY$.MODULE$:Lscala/xml/dtd/EMPTY$;
Asciz	expected ANY, EMPTY or '(' instead of ;
String	expected ANY, EMPTY or '(' instead of 
Asciz	res;
Asciz	Lscala/xml/dtd/MIXED;;
Asciz	temp5;
Asciz	temp2;
Asciz	Ljava/lang/String;;
Asciz	temp6;
Asciz	scala/util/regexp/Base$Star;
class	scala/util/regexp/Base$Star
Asciz	(Lscala/util/regexp/Base;Lscala/util/regexp/Base$RegExp;)V;
NameAndType	"<init>":(Lscala/util/regexp/Base;Lscala/util/regexp/Base$RegExp;)V
Method	scala/util/regexp/Base$Star."<init>":(Lscala/util/regexp/Base;Lscala/util/regexp/Base$RegExp;)V
Asciz	s;
Asciz	temp1;
int	10;
Asciz	in DTDs, \nmixed content models must be like (#PCDATA|Name|Name|...)*;
String	in DTDs, \nmixed content models must be like (#PCDATA|Name|Name|...)*
Asciz	expected ;
String	expected 
Asciz	, got unexpected token:;
String	, got unexpected token:
Asciz	tok;
Asciz	parse;
Asciz	(Ljava/lang/String;)Lscala/xml/dtd/ContentModel;;
Asciz	initScanner;
NameAndType	initScanner:(Ljava/lang/String;)V
Method	scala/xml/dtd/ContentModelParser$.initScanner:(Ljava/lang/String;)V
NameAndType	contentspec:()Lscala/xml/dtd/ContentModel;
Method	scala/xml/dtd/ContentModelParser$.contentspec:()Lscala/xml/dtd/ContentModel;
Asciz	InnerClasses;
Asciz	scala/util/regexp/Base$Alt;
class	scala/util/regexp/Base$Alt
Asciz	scala/util/regexp/Base;
class	scala/util/regexp/Base
Asciz	Star;
Asciz	RegExp;
Asciz	scala/util/regexp/WordExp$Label;
class	scala/util/regexp/WordExp$Label
Asciz	scala/util/regexp/WordExp;
class	scala/util/regexp/WordExp
Asciz	Label;
Asciz	Letter;
Asciz	scala/xml/dtd/ContentModel;
class	scala/xml/dtd/ContentModel
Asciz	ElemName;
Asciz	scala/ScalaObject;
class	scala/ScalaObject

{
public static final scala.xml.dtd.ContentModelParser$ MODULE$;
  Signature: Lscala/xml/dtd/ContentModelParser$;

public static {};
  Signature: ()V
  Code:
   Stack=1, Locals=0, Args_size=0
	new	class scala/xml/dtd/ContentModelParser$
	invokespecial	Method "<init>":()V
	return
  Labels:

private scala.xml.dtd.ContentModelParser$();
  Signature: ()V
  Code:
   Stack=1, Locals=1, Args_size=1
	aload_0
	invokespecial	Method scala/xml/dtd/Scanner."<init>":()V
	aload_0
	putstatic	Field MODULE$:Lscala/xml/dtd/ContentModelParser$;
	return
  Labels:

public scala.util.regexp.WordExp$Letter atom();
  Signature: ()Lscala/util/regexp/WordExp$Letter;
  Code:
   Stack=6, Locals=4, Args_size=1
	aload_0
	invokevirtual	Method token:()I
	istore_3
	iload_3
	iconst_1
	if_icmpne	l1 // iconst_1
	iconst_1
	ifeq	l2 // new
	new	class scala/util/regexp/WordExp$Letter
	dup
	getstatic	Field scala/xml/dtd/ContentModel$.MODULE$:Lscala/xml/dtd/ContentModel$;
	new	class scala/xml/dtd/ContentModel$ElemName
	dup
	aload_0
	invokevirtual	Method value:()Ljava/lang/String;
	invokespecial	Method scala/xml/dtd/ContentModel$ElemName."<init>":(Ljava/lang/String;)V
	invokespecial	Method scala/util/regexp/WordExp$Letter."<init>":(Lscala/util/regexp/WordExp;Lscala/util/regexp/WordExp$Label;)V
	astore_1
	aload_0
	invokevirtual	Method nextToken:()V
	aload_1
	areturn
l2	new	class scala/MatchError
	dup
	iload_3
	invokestatic	Method scala/runtime/BoxesRunTime.boxToInteger:(I)Ljava/lang/Integer;
	invokevirtual	Method java/lang/Object.toString:()Ljava/lang/String;
	invokespecial	Method scala/MatchError."<init>":(Ljava/lang/String;)V
	athrow
l1	iconst_1
	ifeq	l3 // new
	new	class scala/collection/mutable/StringBuilder
	dup
	invokespecial	Method scala/collection/mutable/StringBuilder."<init>":()V
	ldc	String expected Name, got:
	invokevirtual	Method scala/collection/mutable/StringBuilder.append:(Ljava/lang/Object;)Lscala/collection/mutable/StringBuilder;
	aload_0
	aload_0
	invokevirtual	Method token:()I
	invokevirtual	Method token2string:(I)Ljava/lang/String;
	invokevirtual	Method scala/collection/mutable/StringBuilder.append:(Ljava/lang/Object;)Lscala/collection/mutable/StringBuilder;
	invokevirtual	Method scala/collection/mutable/StringBuilder.toString:()Ljava/lang/String;
	astore_2
	new	class java/lang/RuntimeException
	dup
	aload_2
	invokespecial	Method java/lang/RuntimeException."<init>":(Ljava/lang/String;)V
	athrow
l3	new	class scala/MatchError
	dup
	iload_3
	invokestatic	Method scala/runtime/BoxesRunTime.boxToInteger:(I)Ljava/lang/Integer;
	invokevirtual	Method java/lang/Object.toString:()Ljava/lang/String;
	invokespecial	Method scala/MatchError."<init>":(Ljava/lang/String;)V
	athrow
  Labels:
   	l2 = 42 // new
   	l1 = 57 // iconst_1
   	l3 = 97 // new
  LocalVariableTable: 
   Start  Length  Slot  Name   Signature
   0      112      0    this       Lscala/xml/dtd/ContentModelParser$;
   36      5      1    a       Lscala/util/regexp/WordExp$Letter;
   5      107      3    temp9       I


public scala.util.regexp.Base$RegExp particle();
  Signature: ()Lscala/util/regexp/Base$RegExp;
  Code:
   Stack=6, Locals=4, Args_size=1
	aload_0
	invokevirtual	Method token:()I
	istore_3
	iload_3
	lookupswitch{ //2
		1: 121;
		3: 87;
		default: 32 }
	iconst_1
	ifeq	l1 // new
	new	class scala/collection/mutable/StringBuilder
	dup
	invokespecial	Method scala/collection/mutable/StringBuilder."<init>":()V
	ldc	String expected '(' or Name, got:
	invokevirtual	Method scala/collection/mutable/StringBuilder.append:(Ljava/lang/Object;)Lscala/collection/mutable/StringBuilder;
	aload_0
	aload_0
	invokevirtual	Method token:()I
	invokevirtual	Method token2string:(I)Ljava/lang/String;
	invokevirtual	Method scala/collection/mutable/StringBuilder.append:(Ljava/lang/Object;)Lscala/collection/mutable/StringBuilder;
	invokevirtual	Method scala/collection/mutable/StringBuilder.toString:()Ljava/lang/String;
	astore_1
	new	class java/lang/RuntimeException
	dup
	aload_1
	invokespecial	Method java/lang/RuntimeException."<init>":(Ljava/lang/String;)V
	athrow
l1	new	class scala/MatchError
	dup
	iload_3
	invokestatic	Method scala/runtime/BoxesRunTime.boxToInteger:(I)Ljava/lang/Integer;
	invokevirtual	Method java/lang/Object.toString:()Ljava/lang/String;
	invokespecial	Method scala/MatchError."<init>":(Ljava/lang/String;)V
	athrow
	iconst_1
	ifeq	l2 // new
	aload_0
	invokevirtual	Method nextToken:()V
	aload_0
	invokevirtual	Method sOpt:()V
	aload_0
	invokevirtual	Method regexp:()Lscala/util/regexp/Base$RegExp;
	goto	l3 // areturn
l2	new	class scala/MatchError
	dup
	iload_3
	invokestatic	Method scala/runtime/BoxesRunTime.boxToInteger:(I)Ljava/lang/Integer;
	invokevirtual	Method java/lang/Object.toString:()Ljava/lang/String;
	invokespecial	Method scala/MatchError."<init>":(Ljava/lang/String;)V
	athrow
	iconst_1
	ifeq	l4 // new
	new	class scala/util/regexp/WordExp$Letter
	dup
	getstatic	Field scala/xml/dtd/ContentModel$.MODULE$:Lscala/xml/dtd/ContentModel$;
	new	class scala/xml/dtd/ContentModel$ElemName
	dup
	aload_0
	invokevirtual	Method value:()Ljava/lang/String;
	invokespecial	Method scala/xml/dtd/ContentModel$ElemName."<init>":(Ljava/lang/String;)V
	invokespecial	Method scala/util/regexp/WordExp$Letter."<init>":(Lscala/util/regexp/WordExp;Lscala/util/regexp/WordExp$Label;)V
	astore_2
	aload_0
	invokevirtual	Method nextToken:()V
	aload_0
	aload_2
	invokevirtual	Method maybeSuffix:(Lscala/util/regexp/Base$RegExp;)Lscala/util/regexp/Base$RegExp;
l3	areturn
l4	new	class scala/MatchError
	dup
	iload_3
	invokestatic	Method scala/runtime/BoxesRunTime.boxToInteger:(I)Ljava/lang/Integer;
	invokevirtual	Method java/lang/Object.toString:()Ljava/lang/String;
	invokespecial	Method scala/MatchError."<init>":(Ljava/lang/String;)V
	athrow
  Labels:
   	l1 = 72 // new
   	l2 = 106 // new
   	l3 = 156 // areturn
   	l4 = 157 // new
  LocalVariableTable: 
   Start  Length  Slot  Name   Signature
   0      172      0    this       Lscala/xml/dtd/ContentModelParser$;
   147      9      2    a       Lscala/util/regexp/WordExp$Letter;
   5      167      3    temp8       I


public scala.util.regexp.Base$Alt choiceRest(scala.util.regexp.Base$RegExp);
  Signature: (Lscala/util/regexp/Base$RegExp;)Lscala/util/regexp/Base$Alt;
  Code:
   Stack=5, Locals=5, Args_size=2
	getstatic	Field scala/Predef$.MODULE$:Lscala/Predef$;
	iconst_1
	anewarray	class scala/util/regexp/Base$RegExp
	dup
	iconst_0
	aload_1
	aastore
	checkcast	class "[Ljava/lang/Object;"
	invokevirtual	Method scala/Predef$.wrapRefArray:([Ljava/lang/Object;)Lscala/collection/mutable/WrappedArray;
	astore_2
	aload_2
	invokeinterface	InterfaceMethod scala/collection/TraversableLike.toList:()Lscala/collection/immutable/List;
	astore	4
l2	aload_0
	invokevirtual	Method token:()I
	ldc	int 9
	if_icmpne	l1 // getstatic
	aload_0
	invokevirtual	Method nextToken:()V
	aload_0
	invokevirtual	Method sOpt:()V
	aload_0
	invokevirtual	Method particle:()Lscala/util/regexp/Base$RegExp;
	astore_3
	aload	4
	aload_3
	invokevirtual	Method scala/collection/immutable/List.$colon$colon:(Ljava/lang/Object;)Lscala/collection/immutable/List;
	astore	4
	aload_0
	invokevirtual	Method sOpt:()V
	goto	l2 // aload_0
l1	getstatic	Field scala/xml/dtd/ContentModel$.MODULE$:Lscala/xml/dtd/ContentModel$;
	invokevirtual	Method scala/xml/dtd/ContentModel$.Alt:()Lscala/util/regexp/Base$Alt$;
	aload	4
	invokevirtual	Method scala/collection/immutable/List.reverse:()Lscala/collection/immutable/List;
	invokevirtual	Method scala/util/regexp/Base$Alt$.apply:(Lscala/collection/Seq;)Lscala/util/regexp/Base$Alt;
	areturn
  Labels:
   	l2 = 26 // aload_0
   	l1 = 63 // getstatic
  LocalVariableTable: 
   Start  Length  Slot  Name   Signature
   0      78      0    this       Lscala/xml/dtd/ContentModelParser$;
   0      78      1    p       Lscala/util/regexp/Base$RegExp;
   26      51      4    k       Lscala/collection/immutable/List;


public scala.util.regexp.Base$RegExp seqRest(scala.util.regexp.Base$RegExp);
  Signature: (Lscala/util/regexp/Base$RegExp;)Lscala/util/regexp/Base$RegExp;
  Code:
   Stack=5, Locals=5, Args_size=2
	getstatic	Field scala/Predef$.MODULE$:Lscala/Predef$;
	iconst_1
	anewarray	class scala/util/regexp/Base$RegExp
	dup
	iconst_0
	aload_1
	aastore
	checkcast	class "[Ljava/lang/Object;"
	invokevirtual	Method scala/Predef$.wrapRefArray:([Ljava/lang/Object;)Lscala/collection/mutable/WrappedArray;
	astore_2
	aload_2
	invokeinterface	InterfaceMethod scala/collection/TraversableLike.toList:()Lscala/collection/immutable/List;
	astore	4
l2	aload_0
	invokevirtual	Method token:()I
	iconst_5
	if_icmpne	l1 // getstatic
	aload_0
	invokevirtual	Method nextToken:()V
	aload_0
	invokevirtual	Method sOpt:()V
	aload_0
	invokevirtual	Method particle:()Lscala/util/regexp/Base$RegExp;
	astore_3
	aload	4
	aload_3
	invokevirtual	Method scala/collection/immutable/List.$colon$colon:(Ljava/lang/Object;)Lscala/collection/immutable/List;
	astore	4
	aload_0
	invokevirtual	Method sOpt:()V
	goto	l2 // aload_0
l1	getstatic	Field scala/xml/dtd/ContentModel$.MODULE$:Lscala/xml/dtd/ContentModel$;
	invokevirtual	Method scala/xml/dtd/ContentModel$.Sequ:()Lscala/util/regexp/Base$Sequ$;
	aload	4
	invokevirtual	Method scala/collection/immutable/List.reverse:()Lscala/collection/immutable/List;
	invokevirtual	Method scala/util/regexp/Base$Sequ$.apply:(Lscala/collection/Seq;)Lscala/util/regexp/Base$RegExp;
	areturn
  Labels:
   	l2 = 26 // aload_0
   	l1 = 62 // getstatic
  LocalVariableTable: 
   Start  Length  Slot  Name   Signature
   0      77      0    this       Lscala/xml/dtd/ContentModelParser$;
   0      77      1    p       Lscala/util/regexp/Base$RegExp;
   26      50      4    k       Lscala/collection/immutable/List;


public scala.util.regexp.Base$RegExp regexp();
  Signature: ()Lscala/util/regexp/Base$RegExp;
  Code:
   Stack=4, Locals=5, Args_size=1
	aload_0
	invokevirtual	Method particle:()Lscala/util/regexp/Base$RegExp;
	astore_3
	aload_0
	invokevirtual	Method sOpt:()V
	aload_0
	aload_0
	invokevirtual	Method token:()I
	istore	4
	iload	4
	lookupswitch{ //3
		4: 138;
		5: 103;
		9: 68;
		default: 52 }
	new	class scala/MatchError
	dup
	iload	4
	invokestatic	Method scala/runtime/BoxesRunTime.boxToInteger:(I)Ljava/lang/Integer;
	invokevirtual	Method java/lang/Object.toString:()Ljava/lang/String;
	invokespecial	Method scala/MatchError."<init>":(Ljava/lang/String;)V
	athrow
	iconst_1
	ifeq	l1 // new
	aload_0
	aload_3
	invokevirtual	Method choiceRest:(Lscala/util/regexp/Base$RegExp;)Lscala/util/regexp/Base$Alt;
	astore_1
	aload_0
	iconst_4
	invokevirtual	Method accept:(I)V
	aload_1
	goto	l2 // invokevirtual
l1	new	class scala/MatchError
	dup
	iload	4
	invokestatic	Method scala/runtime/BoxesRunTime.boxToInteger:(I)Ljava/lang/Integer;
	invokevirtual	Method java/lang/Object.toString:()Ljava/lang/String;
	invokespecial	Method scala/MatchError."<init>":(Ljava/lang/String;)V
	athrow
	iconst_1
	ifeq	l3 // new
	aload_0
	aload_3
	invokevirtual	Method seqRest:(Lscala/util/regexp/Base$RegExp;)Lscala/util/regexp/Base$RegExp;
	astore_2
	aload_0
	iconst_4
	invokevirtual	Method accept:(I)V
	aload_2
	goto	l2 // invokevirtual
l3	new	class scala/MatchError
	dup
	iload	4
	invokestatic	Method scala/runtime/BoxesRunTime.boxToInteger:(I)Ljava/lang/Integer;
	invokevirtual	Method java/lang/Object.toString:()Ljava/lang/String;
	invokespecial	Method scala/MatchError."<init>":(Ljava/lang/String;)V
	athrow
	iconst_1
	ifeq	l4 // new
	aload_0
	invokevirtual	Method nextToken:()V
	aload_3
l2	invokevirtual	Method maybeSuffix:(Lscala/util/regexp/Base$RegExp;)Lscala/util/regexp/Base$RegExp;
	areturn
l4	new	class scala/MatchError
	dup
	iload	4
	invokestatic	Method scala/runtime/BoxesRunTime.boxToInteger:(I)Ljava/lang/Integer;
	invokevirtual	Method java/lang/Object.toString:()Ljava/lang/String;
	invokespecial	Method scala/MatchError."<init>":(Ljava/lang/String;)V
	athrow
  Labels:
   	l1 = 87 // new
   	l3 = 122 // new
   	l2 = 147 // invokevirtual
   	l4 = 151 // new
  LocalVariableTable: 
   Start  Length  Slot  Name   Signature
   0      167      0    this       Lscala/xml/dtd/ContentModelParser$;
   78      6      1    q       Lscala/util/regexp/Base$Alt;
   113      6      2    q       Lscala/util/regexp/Base$RegExp;
   5      145      3    p       Lscala/util/regexp/Base$RegExp;
   151      16      3    p       Lscala/util/regexp/Base$RegExp;
   16      151      4    temp7       I


public void sOpt();
  Signature: ()V
  Code:
   Stack=2, Locals=1, Args_size=1
	aload_0
	invokevirtual	Method token:()I
	ldc	int 13
	if_icmpne	l1 // return
	aload_0
	invokevirtual	Method nextToken:()V
l1	return
  Labels:
   	l1 = 13 // return

public scala.xml.dtd.ContentModel contentspec();
  Signature: ()Lscala/xml/dtd/ContentModel;
  Code:
   Stack=4, Locals=10, Args_size=1
	aload_0
	invokevirtual	Method token:()I
	istore	9
	iload	9
	lookupswitch{ //2
		1: 319;
		3: 92;
		default: 36 }
	iconst_1
	ifeq	l1 // new
	new	class scala/collection/mutable/StringBuilder
	dup
	invokespecial	Method scala/collection/mutable/StringBuilder."<init>":()V
	ldc	String unexpected token:
	invokevirtual	Method scala/collection/mutable/StringBuilder.append:(Ljava/lang/Object;)Lscala/collection/mutable/StringBuilder;
	aload_0
	aload_0
	invokevirtual	Method token:()I
	invokevirtual	Method token2string:(I)Ljava/lang/String;
	invokevirtual	Method scala/collection/mutable/StringBuilder.append:(Ljava/lang/Object;)Lscala/collection/mutable/StringBuilder;
	invokevirtual	Method scala/collection/mutable/StringBuilder.toString:()Ljava/lang/String;
	astore_1
	new	class java/lang/RuntimeException
	dup
	aload_1
	invokespecial	Method java/lang/RuntimeException."<init>":(Ljava/lang/String;)V
	athrow
l1	new	class scala/MatchError
	dup
	iload	9
	invokestatic	Method scala/runtime/BoxesRunTime.boxToInteger:(I)Ljava/lang/Integer;
	invokevirtual	Method java/lang/Object.toString:()Ljava/lang/String;
	invokespecial	Method scala/MatchError."<init>":(Ljava/lang/String;)V
	athrow
	iconst_1
	ifeq	l2 // new
	aload_0
	invokevirtual	Method nextToken:()V
	aload_0
	invokevirtual	Method sOpt:()V
	aload_0
	invokevirtual	Method token:()I
	iconst_0
	if_icmpeq	l3 // aload_0
	new	class scala/xml/dtd/ELEMENTS
	dup
	aload_0
	invokevirtual	Method regexp:()Lscala/util/regexp/Base$RegExp;
	invokespecial	Method scala/xml/dtd/ELEMENTS."<init>":(Lscala/util/regexp/Base$RegExp;)V
	goto	l4 // areturn
l3	aload_0
	invokevirtual	Method nextToken:()V
	aload_0
	invokevirtual	Method token:()I
	istore	4
	iload	4
	lookupswitch{ //2
		4: 277;
		9: 220;
		default: 164 }
	iconst_1
	ifeq	l5 // new
	new	class scala/collection/mutable/StringBuilder
	dup
	invokespecial	Method scala/collection/mutable/StringBuilder."<init>":()V
	ldc	String unexpected token:
	invokevirtual	Method scala/collection/mutable/StringBuilder.append:(Ljava/lang/Object;)Lscala/collection/mutable/StringBuilder;
	aload_0
	aload_0
	invokevirtual	Method token:()I
	invokevirtual	Method token2string:(I)Ljava/lang/String;
	invokevirtual	Method scala/collection/mutable/StringBuilder.append:(Ljava/lang/Object;)Lscala/collection/mutable/StringBuilder;
	invokevirtual	Method scala/collection/mutable/StringBuilder.toString:()Ljava/lang/String;
	astore_2
	new	class java/lang/RuntimeException
	dup
	aload_2
	invokespecial	Method java/lang/RuntimeException."<init>":(Ljava/lang/String;)V
	athrow
l5	new	class scala/MatchError
	dup
	iload	4
	invokestatic	Method scala/runtime/BoxesRunTime.boxToInteger:(I)Ljava/lang/Integer;
	invokevirtual	Method java/lang/Object.toString:()Ljava/lang/String;
	invokespecial	Method scala/MatchError."<init>":(Ljava/lang/String;)V
	athrow
	iconst_1
	ifeq	l6 // new
	new	class scala/xml/dtd/MIXED
	dup
	aload_0
	getstatic	Field scala/xml/dtd/ContentModel$.MODULE$:Lscala/xml/dtd/ContentModel$;
	invokevirtual	Method scala/xml/dtd/ContentModel$.Eps:()Lscala/util/regexp/Base$Eps$;
	invokevirtual	Method choiceRest:(Lscala/util/regexp/Base$RegExp;)Lscala/util/regexp/Base$Alt;
	invokespecial	Method scala/xml/dtd/MIXED."<init>":(Lscala/util/regexp/Base$RegExp;)V
	astore_3
	aload_0
	invokevirtual	Method sOpt:()V
	aload_0
	iconst_4
	invokevirtual	Method accept:(I)V
	aload_0
	ldc	int 6
	invokevirtual	Method accept:(I)V
	aload_3
	goto	l4 // areturn
l6	new	class scala/MatchError
	dup
	iload	4
	invokestatic	Method scala/runtime/BoxesRunTime.boxToInteger:(I)Ljava/lang/Integer;
	invokevirtual	Method java/lang/Object.toString:()Ljava/lang/String;
	invokespecial	Method scala/MatchError."<init>":(Ljava/lang/String;)V
	athrow
	iconst_1
	ifeq	l7 // new
	getstatic	Field scala/xml/dtd/PCDATA$.MODULE$:Lscala/xml/dtd/PCDATA$;
	goto	l4 // areturn
l7	new	class scala/MatchError
	dup
	iload	4
	invokestatic	Method scala/runtime/BoxesRunTime.boxToInteger:(I)Ljava/lang/Integer;
	invokevirtual	Method java/lang/Object.toString:()Ljava/lang/String;
	invokespecial	Method scala/MatchError."<init>":(Ljava/lang/String;)V
	athrow
l2	new	class scala/MatchError
	dup
	iload	9
	invokestatic	Method scala/runtime/BoxesRunTime.boxToInteger:(I)Ljava/lang/Integer;
	invokevirtual	Method java/lang/Object.toString:()Ljava/lang/String;
	invokespecial	Method scala/MatchError."<init>":(Ljava/lang/String;)V
	athrow
	iconst_1
	ifeq	l8 // new
	aload_0
	invokevirtual	Method value:()Ljava/lang/String;
	astore	8
	aload	8
	ldc	String ANY
	astore	5
	dup
	ifnonnull	l9 // aload
	pop
	aload	5
	ifnull	l10 // iconst_1
	goto	l11 // aload
l9	aload	5
	invokevirtual	Method java/lang/Object.equals:(Ljava/lang/Object;)Z
	ifeq	l11 // aload
l10	iconst_1
	ifeq	l12 // new
	getstatic	Field scala/xml/dtd/ANY$.MODULE$:Lscala/xml/dtd/ANY$;
	goto	l4 // areturn
l12	new	class scala/MatchError
	dup
	aload	8
	invokevirtual	Method java/lang/String.toString:()Ljava/lang/String;
	invokespecial	Method scala/MatchError."<init>":(Ljava/lang/String;)V
	athrow
l11	aload	8
	ldc	String EMPTY
	astore	6
	dup
	ifnonnull	l13 // aload
	pop
	aload	6
	ifnull	l14 // iconst_1
	goto	l15 // iconst_1
l13	aload	6
	invokevirtual	Method java/lang/Object.equals:(Ljava/lang/Object;)Z
	ifeq	l15 // iconst_1
l14	iconst_1
	ifeq	l16 // new
	getstatic	Field scala/xml/dtd/EMPTY$.MODULE$:Lscala/xml/dtd/EMPTY$;
l4	areturn
l16	new	class scala/MatchError
	dup
	aload	8
	invokevirtual	Method java/lang/String.toString:()Ljava/lang/String;
	invokespecial	Method scala/MatchError."<init>":(Ljava/lang/String;)V
	athrow
l15	iconst_1
	ifeq	l17 // new
	new	class scala/collection/mutable/StringBuilder
	dup
	invokespecial	Method scala/collection/mutable/StringBuilder."<init>":()V
	ldc	String expected ANY, EMPTY or '(' instead of 
	invokevirtual	Method scala/collection/mutable/StringBuilder.append:(Ljava/lang/Object;)Lscala/collection/mutable/StringBuilder;
	aload_0
	invokevirtual	Method value:()Ljava/lang/String;
	invokevirtual	Method scala/collection/mutable/StringBuilder.append:(Ljava/lang/Object;)Lscala/collection/mutable/StringBuilder;
	invokevirtual	Method scala/collection/mutable/StringBuilder.toString:()Ljava/lang/String;
	astore	7
	new	class java/lang/RuntimeException
	dup
	aload	7
	invokespecial	Method java/lang/RuntimeException."<init>":(Ljava/lang/String;)V
	athrow
l17	new	class scala/MatchError
	dup
	aload	8
	invokevirtual	Method java/lang/String.toString:()Ljava/lang/String;
	invokespecial	Method scala/MatchError."<init>":(Ljava/lang/String;)V
	athrow
l8	new	class scala/MatchError
	dup
	iload	9
	invokestatic	Method scala/runtime/BoxesRunTime.boxToInteger:(I)Ljava/lang/Integer;
	invokevirtual	Method java/lang/Object.toString:()Ljava/lang/String;
	invokespecial	Method scala/MatchError."<init>":(Ljava/lang/String;)V
	athrow
  Labels:
   	l1 = 76 // new
   	l3 = 126 // aload_0
   	l5 = 204 // new
   	l6 = 261 // new
   	l7 = 287 // new
   	l2 = 303 // new
   	l9 = 348 // aload
   	l10 = 356 // iconst_1
   	l12 = 366 // new
   	l11 = 379 // aload
   	l13 = 398 // aload
   	l14 = 406 // iconst_1
   	l4 = 413 // areturn
   	l16 = 414 // new
   	l15 = 427 // iconst_1
   	l17 = 465 // new
   	l8 = 478 // new
  LocalVariableTable: 
   Start  Length  Slot  Name   Signature
   0      494      0    this       Lscala/xml/dtd/ContentModelParser$;
   242      16      3    res       Lscala/xml/dtd/MIXED;
   136      167      4    temp5       I
   329      84      8    temp2       Ljava/lang/String;
   414      64      8    temp2       Ljava/lang/String;
   6      488      9    temp6       I


public scala.util.regexp.Base$RegExp maybeSuffix(scala.util.regexp.Base$RegExp);
  Signature: (Lscala/util/regexp/Base$RegExp;)Lscala/util/regexp/Base$RegExp;
  Code:
   Stack=9, Locals=3, Args_size=2
	aload_0
	invokevirtual	Method token:()I
	istore_2
	iload_2
	tableswitch{ //6 to 8
		6: 182;
		7: 116;
		8: 55;
		default: 32 }
	iconst_1
	ifeq	l1 // new
	aload_1
	goto	l2 // areturn
l1	new	class scala/MatchError
	dup
	iload_2
	invokestatic	Method scala/runtime/BoxesRunTime.boxToInteger:(I)Ljava/lang/Integer;
	invokevirtual	Method java/lang/Object.toString:()Ljava/lang/String;
	invokespecial	Method scala/MatchError."<init>":(Ljava/lang/String;)V
	athrow
	iconst_1
	ifeq	l3 // new
	aload_0
	invokevirtual	Method nextToken:()V
	getstatic	Field scala/xml/dtd/ContentModel$.MODULE$:Lscala/xml/dtd/ContentModel$;
	invokevirtual	Method scala/xml/dtd/ContentModel$.Alt:()Lscala/util/regexp/Base$Alt$;
	getstatic	Field scala/Predef$.MODULE$:Lscala/Predef$;
	iconst_2
	anewarray	class scala/util/regexp/Base$RegExp
	dup
	iconst_0
	getstatic	Field scala/xml/dtd/ContentModel$.MODULE$:Lscala/xml/dtd/ContentModel$;
	invokevirtual	Method scala/xml/dtd/ContentModel$.Eps:()Lscala/util/regexp/Base$Eps$;
	aastore
	dup
	iconst_1
	aload_1
	aastore
	checkcast	class "[Ljava/lang/Object;"
	invokevirtual	Method scala/Predef$.wrapRefArray:([Ljava/lang/Object;)Lscala/collection/mutable/WrappedArray;
	invokevirtual	Method scala/util/regexp/Base$Alt$.apply:(Lscala/collection/Seq;)Lscala/util/regexp/Base$Alt;
	goto	l2 // areturn
l3	new	class scala/MatchError
	dup
	iload_2
	invokestatic	Method scala/runtime/BoxesRunTime.boxToInteger:(I)Ljava/lang/Integer;
	invokevirtual	Method java/lang/Object.toString:()Ljava/lang/String;
	invokespecial	Method scala/MatchError."<init>":(Ljava/lang/String;)V
	athrow
	iconst_1
	ifeq	l4 // new
	aload_0
	invokevirtual	Method nextToken:()V
	getstatic	Field scala/xml/dtd/ContentModel$.MODULE$:Lscala/xml/dtd/ContentModel$;
	invokevirtual	Method scala/xml/dtd/ContentModel$.Sequ:()Lscala/util/regexp/Base$Sequ$;
	getstatic	Field scala/Predef$.MODULE$:Lscala/Predef$;
	iconst_2
	anewarray	class scala/util/regexp/Base$RegExp
	dup
	iconst_0
	aload_1
	aastore
	dup
	iconst_1
	new	class scala/util/regexp/Base$Star
	dup
	getstatic	Field scala/xml/dtd/ContentModel$.MODULE$:Lscala/xml/dtd/ContentModel$;
	aload_1
	invokespecial	Method scala/util/regexp/Base$Star."<init>":(Lscala/util/regexp/Base;Lscala/util/regexp/Base$RegExp;)V
	aastore
	checkcast	class "[Ljava/lang/Object;"
	invokevirtual	Method scala/Predef$.wrapRefArray:([Ljava/lang/Object;)Lscala/collection/mutable/WrappedArray;
	invokevirtual	Method scala/util/regexp/Base$Sequ$.apply:(Lscala/collection/Seq;)Lscala/util/regexp/Base$RegExp;
	goto	l2 // areturn
l4	new	class scala/MatchError
	dup
	iload_2
	invokestatic	Method scala/runtime/BoxesRunTime.boxToInteger:(I)Ljava/lang/Integer;
	invokevirtual	Method java/lang/Object.toString:()Ljava/lang/String;
	invokespecial	Method scala/MatchError."<init>":(Ljava/lang/String;)V
	athrow
	iconst_1
	ifeq	l5 // new
	aload_0
	invokevirtual	Method nextToken:()V
	new	class scala/util/regexp/Base$Star
	dup
	getstatic	Field scala/xml/dtd/ContentModel$.MODULE$:Lscala/xml/dtd/ContentModel$;
	aload_1
	invokespecial	Method scala/util/regexp/Base$Star."<init>":(Lscala/util/regexp/Base;Lscala/util/regexp/Base$RegExp;)V
l2	areturn
l5	new	class scala/MatchError
	dup
	iload_2
	invokestatic	Method scala/runtime/BoxesRunTime.boxToInteger:(I)Ljava/lang/Integer;
	invokevirtual	Method java/lang/Object.toString:()Ljava/lang/String;
	invokespecial	Method scala/MatchError."<init>":(Ljava/lang/String;)V
	athrow
  Labels:
   	l1 = 40 // new
   	l3 = 101 // new
   	l4 = 167 // new
   	l2 = 201 // areturn
   	l5 = 202 // new
  LocalVariableTable: 
   Start  Length  Slot  Name   Signature
   0      217      0    this       Lscala/xml/dtd/ContentModelParser$;
   0      217      1    s       Lscala/util/regexp/Base$RegExp;
   5      212      2    temp1       I


public void accept(int);
  Signature: (I)V
  Code:
   Stack=3, Locals=4, Args_size=2
	aload_0
	invokevirtual	Method token:()I
	iload_1
	if_icmpeq	l1 // aload_0
	iload_1
	ldc	int 6
	if_icmpne	l2 // new
	aload_0
	invokevirtual	Method token:()I
	ldc	int 10
	if_icmpne	l2 // new
	ldc	String in DTDs, \nmixed content models must be like (#PCDATA|Name|Name|...)*
	astore_2
	new	class java/lang/RuntimeException
	dup
	aload_2
	invokespecial	Method java/lang/RuntimeException."<init>":(Ljava/lang/String;)V
	athrow
l2	new	class scala/collection/mutable/StringBuilder
	dup
	invokespecial	Method scala/collection/mutable/StringBuilder."<init>":()V
	ldc	String expected 
	invokevirtual	Method scala/collection/mutable/StringBuilder.append:(Ljava/lang/Object;)Lscala/collection/mutable/StringBuilder;
	aload_0
	iload_1
	invokevirtual	Method token2string:(I)Ljava/lang/String;
	invokevirtual	Method scala/collection/mutable/StringBuilder.append:(Ljava/lang/Object;)Lscala/collection/mutable/StringBuilder;
	ldc	String , got unexpected token:
	invokevirtual	Method scala/collection/mutable/StringBuilder.append:(Ljava/lang/Object;)Lscala/collection/mutable/StringBuilder;
	aload_0
	aload_0
	invokevirtual	Method token:()I
	invokevirtual	Method token2string:(I)Ljava/lang/String;
	invokevirtual	Method scala/collection/mutable/StringBuilder.append:(Ljava/lang/Object;)Lscala/collection/mutable/StringBuilder;
	invokevirtual	Method scala/collection/mutable/StringBuilder.toString:()Ljava/lang/String;
	astore_3
	new	class java/lang/RuntimeException
	dup
	aload_3
	invokespecial	Method java/lang/RuntimeException."<init>":(Ljava/lang/String;)V
	athrow
l1	aload_0
	invokevirtual	Method nextToken:()V
	return
  Labels:
   	l2 = 35 // new
   	l1 = 84 // aload_0
  LocalVariableTable: 
   Start  Length  Slot  Name   Signature
   0      89      0    this       Lscala/xml/dtd/ContentModelParser$;
   0      89      1    tok       I


public scala.xml.dtd.ContentModel parse(java.lang.String);
  Signature: (Ljava/lang/String;)Lscala/xml/dtd/ContentModel;
  Code:
   Stack=2, Locals=2, Args_size=2
	aload_0
	aload_1
	invokevirtual	Method initScanner:(Ljava/lang/String;)V
	aload_0
	invokevirtual	Method contentspec:()Lscala/xml/dtd/ContentModel;
	areturn
  Labels:
  LocalVariableTable: 
   Start  Length  Slot  Name   Signature
   0      10      0    this       Lscala/xml/dtd/ContentModelParser$;
   0      10      1    s       Ljava/lang/String;


}

