Compiled from "Decl.scala"
public final class scala.xml.dtd.DEFAULT$ extends java.lang.Object implements scala.Function2,scala.ScalaObject
  SourceFile: "Decl.scala"
  Scala: length = 0x
   
  InnerClass: 
   public final $anonfun$toString$2=class scala/xml/dtd/DEFAULT$$anonfun$toString$2 of class scala/xml/dtd/DEFAULT
  minor version: 0
  major version: 49
  Constant pool:
Asciz	SourceFile;
Asciz	Decl.scala;
Asciz	Scala;
Asciz	MODULE$;
Asciz	Lscala/xml/dtd/DEFAULT$;;
Asciz	<clinit>;
Asciz	()V;
Asciz	Code;
Asciz	scala/xml/dtd/DEFAULT$;
class	scala/xml/dtd/DEFAULT$
Asciz	<init>;
NameAndType	"<init>":()V
Method	scala/xml/dtd/DEFAULT$."<init>":()V
Asciz	toString;
Asciz	()Ljava/lang/String;;
Asciz	LineNumberTable;
Asciz	scala/Function2$class;
class	scala/Function2$class
Asciz	(Lscala/Function2;)Ljava/lang/String;;
NameAndType	toString:(Lscala/Function2;)Ljava/lang/String;
Method	scala/Function2$class.toString:(Lscala/Function2;)Ljava/lang/String;
Asciz	curried;
Asciz	()Lscala/Function1;;
Asciz	(Lscala/Function2;)Lscala/Function1;;
NameAndType	curried:(Lscala/Function2;)Lscala/Function1;
Method	scala/Function2$class.curried:(Lscala/Function2;)Lscala/Function1;
Asciz	curry;
NameAndType	curry:(Lscala/Function2;)Lscala/Function1;
Method	scala/Function2$class.curry:(Lscala/Function2;)Lscala/Function1;
Asciz	Deprecated;
Asciz	tupled;
NameAndType	tupled:(Lscala/Function2;)Lscala/Function1;
Method	scala/Function2$class.tupled:(Lscala/Function2;)Lscala/Function1;
Asciz	unapply;
Asciz	(Lscala/xml/dtd/DEFAULT;)Lscala/Some;;
Asciz	scala/Some;
class	scala/Some
Asciz	scala/Tuple2;
class	scala/Tuple2
Asciz	scala/xml/dtd/DEFAULT;
class	scala/xml/dtd/DEFAULT
Asciz	fixed;
Asciz	()Z;
NameAndType	fixed:()Z
Method	scala/xml/dtd/DEFAULT.fixed:()Z
Asciz	scala/runtime/BoxesRunTime;
class	scala/runtime/BoxesRunTime
Asciz	boxToBoolean;
Asciz	(Z)Ljava/lang/Boolean;;
NameAndType	boxToBoolean:(Z)Ljava/lang/Boolean;
Method	scala/runtime/BoxesRunTime.boxToBoolean:(Z)Ljava/lang/Boolean;
Asciz	attValue;
NameAndType	attValue:()Ljava/lang/String;
Method	scala/xml/dtd/DEFAULT.attValue:()Ljava/lang/String;
Asciz	(Ljava/lang/Object;Ljava/lang/Object;)V;
NameAndType	"<init>":(Ljava/lang/Object;Ljava/lang/Object;)V
Method	scala/Tuple2."<init>":(Ljava/lang/Object;Ljava/lang/Object;)V
Asciz	(Ljava/lang/Object;)V;
NameAndType	"<init>":(Ljava/lang/Object;)V
Method	scala/Some."<init>":(Ljava/lang/Object;)V
Asciz	this;
Asciz	x$0;
Asciz	Lscala/xml/dtd/DEFAULT;;
Asciz	LocalVariableTable;
Asciz	apply;
Asciz	(ZLjava/lang/String;)Lscala/xml/dtd/DEFAULT;;
Asciz	(ZLjava/lang/String;)V;
NameAndType	"<init>":(ZLjava/lang/String;)V
Method	scala/xml/dtd/DEFAULT."<init>":(ZLjava/lang/String;)V
Asciz	Z;
Asciz	Ljava/lang/String;;
Asciz	(Ljava/lang/Object;Ljava/lang/Object;)Ljava/lang/Object;;
Asciz	unboxToBoolean;
Asciz	(Ljava/lang/Object;)Z;
NameAndType	unboxToBoolean:(Ljava/lang/Object;)Z
Method	scala/runtime/BoxesRunTime.unboxToBoolean:(Ljava/lang/Object;)Z
Asciz	java/lang/String;
class	java/lang/String
NameAndType	apply:(ZLjava/lang/String;)Lscala/xml/dtd/DEFAULT;
Method	scala/xml/dtd/DEFAULT$.apply:(ZLjava/lang/String;)Lscala/xml/dtd/DEFAULT;
Asciz	v1;
Asciz	Ljava/lang/Object;;
Asciz	v2;
Asciz	java/lang/Object;
class	java/lang/Object
Method	java/lang/Object."<init>":()V
NameAndType	MODULE$:Lscala/xml/dtd/DEFAULT$;
Field	scala/xml/dtd/DEFAULT$.MODULE$:Lscala/xml/dtd/DEFAULT$;
Asciz	$init$;
Asciz	(Lscala/Function2;)V;
NameAndType	$init$:(Lscala/Function2;)V
Method	scala/Function2$class.$init$:(Lscala/Function2;)V
Asciz	InnerClasses;
Asciz	scala/xml/dtd/DEFAULT$$anonfun$toString$2;
class	scala/xml/dtd/DEFAULT$$anonfun$toString$2
Asciz	$anonfun$toString$2;
Asciz	scala/Function2;
class	scala/Function2
Asciz	scala/ScalaObject;
class	scala/ScalaObject

{
public static final scala.xml.dtd.DEFAULT$ MODULE$;
  Signature: Lscala/xml/dtd/DEFAULT$;

public static {};
  Signature: ()V
  Code:
   Stack=1, Locals=0, Args_size=0
	new	class scala/xml/dtd/DEFAULT$
	invokespecial	Method "<init>":()V
	return
  Labels:

public java.lang.String toString();
  Signature: ()Ljava/lang/String;
  Code:
   Stack=1, Locals=1, Args_size=1
	aload_0
	invokestatic	Method scala/Function2$class.toString:(Lscala/Function2;)Ljava/lang/String;
	areturn
  Labels:

public scala.Function1 curried();
  Signature: ()Lscala/Function1;
  Code:
   Stack=1, Locals=1, Args_size=1
	aload_0
	invokestatic	Method scala/Function2$class.curried:(Lscala/Function2;)Lscala/Function1;
	areturn
  Labels:

public scala.Function1 curry();
  Signature: ()Lscala/Function1;
  Code:
   Stack=1, Locals=1, Args_size=1
	aload_0
	invokestatic	Method scala/Function2$class.curry:(Lscala/Function2;)Lscala/Function1;
	areturn
  Labels:
  Deprecated: true

public scala.Function1 tupled();
  Signature: ()Lscala/Function1;
  Code:
   Stack=1, Locals=1, Args_size=1
	aload_0
	invokestatic	Method scala/Function2$class.tupled:(Lscala/Function2;)Lscala/Function1;
	areturn
  Labels:

public scala.Some unapply(scala.xml.dtd.DEFAULT);
  Signature: (Lscala/xml/dtd/DEFAULT;)Lscala/Some;
  Code:
   Stack=6, Locals=3, Args_size=2
	new	class scala/Some
	dup
	new	class scala/Tuple2
	dup
	aload_1
	invokevirtual	Method scala/xml/dtd/DEFAULT.fixed:()Z
	istore_2
	iload_2
	invokestatic	Method scala/runtime/BoxesRunTime.boxToBoolean:(Z)Ljava/lang/Boolean;
	aload_1
	invokevirtual	Method scala/xml/dtd/DEFAULT.attValue:()Ljava/lang/String;
	invokespecial	Method scala/Tuple2."<init>":(Ljava/lang/Object;Ljava/lang/Object;)V
	invokespecial	Method scala/Some."<init>":(Ljava/lang/Object;)V
	areturn
  Labels:
  LocalVariableTable: 
   Start  Length  Slot  Name   Signature
   0      28      0    this       Lscala/xml/dtd/DEFAULT$;
   0      28      1    x$0       Lscala/xml/dtd/DEFAULT;


public scala.xml.dtd.DEFAULT apply(boolean, java.lang.String);
  Signature: (ZLjava/lang/String;)Lscala/xml/dtd/DEFAULT;
  Code:
   Stack=4, Locals=3, Args_size=3
	new	class scala/xml/dtd/DEFAULT
	dup
	iload_1
	aload_2
	invokespecial	Method scala/xml/dtd/DEFAULT."<init>":(ZLjava/lang/String;)V
	areturn
  Labels:
  LocalVariableTable: 
   Start  Length  Slot  Name   Signature
   0      10      0    this       Lscala/xml/dtd/DEFAULT$;
   0      10      1    fixed       Z
   0      10      2    attValue       Ljava/lang/String;


public java.lang.Object apply(java.lang.Object, java.lang.Object);
  Signature: (Ljava/lang/Object;Ljava/lang/Object;)Ljava/lang/Object;
  Code:
   Stack=3, Locals=3, Args_size=3
	aload_0
	aload_1
	invokestatic	Method scala/runtime/BoxesRunTime.unboxToBoolean:(Ljava/lang/Object;)Z
	aload_2
	checkcast	class java/lang/String
	invokevirtual	Method apply:(ZLjava/lang/String;)Lscala/xml/dtd/DEFAULT;
	areturn
  Labels:
  LocalVariableTable: 
   Start  Length  Slot  Name   Signature
   0      13      0    this       Lscala/xml/dtd/DEFAULT$;
   0      13      1    v1       Ljava/lang/Object;
   0      13      2    v2       Ljava/lang/Object;


private scala.xml.dtd.DEFAULT$();
  Signature: ()V
  Code:
   Stack=1, Locals=1, Args_size=1
	aload_0
	invokespecial	Method java/lang/Object."<init>":()V
	aload_0
	putstatic	Field MODULE$:Lscala/xml/dtd/DEFAULT$;
	aload_0
	invokestatic	Method scala/Function2$class.$init$:(Lscala/Function2;)V
	return
  Labels:

}

