Compiled from "Decl.scala"
public class scala.xml.dtd.DEFAULT extends scala.xml.dtd.DefaultDecl implements scala.ScalaObject,scala.Product,java.io.Serializable
  SourceFile: "Decl.scala"
  ScalaSig: length = 0x420
   05 00 FFFFFF81 19 06 08 01 02 FFFFFF84 FFFFFF80 FFFFFF80 FFFFFF80 40 09 02 07
   44 45 46 41 55 4C 54 0A 02 03 04 01 03 64 74 64
   0A 02 05 06 01 03 78 6D 6C 0A 01 07 01 05 73 63
   61 6C 61 03 00 13 04 00 0A 0E 12 10 02 0B 0C 0D
   01 02 09 02 0D 02 02 0B 44 65 66 61 75 6C 74 44
   65 63 6C 10 02 0F 10 0D 01 06 09 02 11 06 02 0B
   53 63 61 6C 61 4F 62 6A 65 63 74 10 02 0F 13 09
   02 14 06 02 07 50 72 6F 64 75 63 74 08 08 16 00
   FFFFFF82 FFFFFFCA FFFFFF80 FFFFFF84 00 17 01 05 66 69 78 65 64 15 01 18
   10 02 0F 19 09 02 1A 06 02 07 42 6F 6F 6C 65 61
   6E 08 08 1C 00 FFFFFF82 FFFFFF88 FFFFFFA0 FFFFFF80 04 18 01 06 66 69 78
   65 64 20 08 08 1E 00 FFFFFF82 FFFFFFCA FFFFFF80 FFFFFF84 00 1F 01 08 61
   74 74 56 61 6C 75 65 15 01 20 10 02 21 24 0E 02
   0F 22 09 02 23 06 01 06 50 72 65 64 65 66 09 02
   25 26 02 06 53 74 72 69 6E 67 0A 02 23 06 08 08
   28 00 FFFFFF82 FFFFFF88 FFFFFFA0 FFFFFF80 04 20 01 09 61 74 74 56 61 6C
   75 65 20 08 05 2A 00 FFFFFF84 00 2B 01 06 3C 69 6E 69
   74 3E 14 03 2C 2D 2E 10 02 0B 00 08 05 16 29 FFFFFFC0
   00 18 08 05 1E 29 FFFFFFC0 00 20 08 05 30 00 FFFFFF84 20 31
   01 08 74 6F 53 74 72 69 6E 67 14 01 20 08 05 33
   00 FFFFFF84 20 34 01 0B 62 75 69 6C 64 53 74 72 69 6E
   67 14 02 35 3D 10 02 36 3B 0D 01 37 0A 02 38 39
   01 07 6D 75 74 61 62 6C 65 0A 02 3A 06 01 0A 63
   6F 6C 6C 65 63 74 69 6F 6E 09 02 3C 37 02 0D 53
   74 72 69 6E 67 42 75 69 6C 64 65 72 08 05 3E 32
   FFFFFFC0 00 35 01 02 73 62 08 07 40 00 FFFFFF81 FFFFFF80 FFFFFF84 00 41
   01 04 63 6F 70 79 14 03 2C 42 50 08 08 43 16 3F
   FFFFFF90 FFFFFF80 FFFFFFC0 00 18 08 07 44 00 FFFFFF91 FFFFFF80 FFFFFF84 00 45 01 0E
   63 6F 70 79 24 64 65 66 61 75 6C 74 24 31 15 01
   46 2A 02 18 47 2B 01 48 10 02 49 4E 0D 01 4A 0A
   02 4B 4C 01 09 75 6E 63 68 65 63 6B 65 64 0A 02
   4D 06 01 0A 61 6E 6E 6F 74 61 74 69 6F 6E 09 02
   4F 4A 02 11 75 6E 63 68 65 63 6B 65 64 56 61 72
   69 61 6E 63 65 08 08 51 1E 3F FFFFFF90 FFFFFF80 FFFFFFC0 00 20 08
   07 52 00 FFFFFF91 FFFFFF80 FFFFFF84 00 53 01 0E 63 6F 70 79 24 64
   65 66 61 75 6C 74 24 32 15 01 54 2A 02 20 47 08
   08 56 00 FFFFFF84 FFFFFF80 FFFFFF80 FFFFFF84 20 57 01 08 68 61 73 68 43
   6F 64 65 14 01 58 10 02 0F 59 09 02 5A 06 02 03
   49 6E 74 08 08 5C 00 FFFFFF84 FFFFFF80 FFFFFF80 FFFFFF84 20 5D 01 06 65
   71 75 61 6C 73 14 02 18 5E 08 07 5F 5B FFFFFF81 FFFFFF80 FFFFFFC0
   00 60 01 03 78 24 31 10 02 0F 61 09 02 62 06 02
   03 41 6E 79 08 08 64 00 FFFFFF84 FFFFFF80 FFFFFF80 FFFFFF84 20 65 01 0D
   70 72 6F 64 75 63 74 50 72 65 66 69 78 15 01 66
   10 02 67 6C 0D 01 68 0A 02 69 6A 01 04 6C 61 6E
   67 0A 01 6B 01 04 6A 61 76 61 09 02 25 68 08 08
   6E 00 FFFFFF84 FFFFFF80 FFFFFF80 FFFFFF84 20 6F 01 0C 70 72 6F 64 75 63
   74 41 72 69 74 79 15 01 58 08 08 71 00 FFFFFF84 FFFFFF80 FFFFFF80
   FFFFFF84 20 72 01 0E 70 72 6F 64 75 63 74 45 6C 65 6D
   65 6E 74 14 02 60 73 08 07 5F 70 FFFFFF81 FFFFFF80 FFFFFFC0 00 58
   08 08 75 00 FFFFFF84 FFFFFF80 FFFFFF80 FFFFFF84 20 76 01 08 63 61 6E 45
   71 75 61 6C 14 02 18 77 08 07 5F 74 FFFFFF81 FFFFFF80 FFFFFFC0 00
   60 28 02 00 79 10 02 0F 7A 09 02 7B 06 02 0C 73
   65 72 69 61 6C 69 7A 61 62 6C 65 07 07 7D 02 FFFFFF81
   FFFFFF80 FFFFFF88 02 7E 01 07 44 45 46 41 55 4C 54 10 02 0B
   7F 06 09 01 02 FFFFFF84 FFFFFF81 FFFFFF80 FFFFFF88 02 FFFFFF81 00 13 06 7F FFFFFF81
   01 FFFFFF81 04 0E 10 03 67 FFFFFF81 02 09 03 FFFFFF81 03 68 02 06
   4F 62 6A 65 63 74 10 06 0F FFFFFF81 05 18 20 2C 09 03
   FFFFFF81 06 06 02 09 46 75 6E 63 74 69 6F 6E 32 08 06
   2A 7F FFFFFF84 00 FFFFFF81 08 14 01 7E 08 09 FFFFFF81 0A 7F FFFFFF81 FFFFFF80
   FFFFFF84 40 FFFFFF81 0B 01 05 61 70 70 6C 79 14 05 2C FFFFFF81 0C
   FFFFFF81 0D 08 06 16 FFFFFF81 09 FFFFFFC0 00 18 08 06 1E FFFFFF81 09 FFFFFFC0
   00 20 08 09 FFFFFF81 0F 7F FFFFFF81 FFFFFF80 FFFFFF84 40 FFFFFF81 10 01 07 75
   6E 61 70 70 6C 79 14 04 FFFFFF81 11 FFFFFF81 17 10 05 0F FFFFFF81
   12 FFFFFF81 14 09 03 FFFFFF81 13 06 02 04 53 6F 6D 65 10 05
   0F FFFFFF81 15 18 20 09 03 FFFFFF81 16 06 02 06 54 75 70 6C
   65 32 08 07 FFFFFF81 18 FFFFFF81 0E FFFFFFC0 00 2C 01 03 78 24 30
   
  InnerClass: 
   public final $anonfun$toString$2=class scala/xml/dtd/DEFAULT$$anonfun$toString$2 of class scala/xml/dtd/DEFAULT
   public final $anonfun$appendEscapedQuoted$1=class scala/xml/Utility$$anonfun$appendEscapedQuoted$1 of class scala/xml/Utility
  minor version: 0
  major version: 49
  Constant pool:
Asciz	SourceFile;
Asciz	Decl.scala;
Asciz	tuple;
Asciz	()Lscala/Function1;;
Asciz	Code;
Asciz	scala/xml/dtd/DEFAULT$;
class	scala/xml/dtd/DEFAULT$
Asciz	MODULE$;
Asciz	Lscala/xml/dtd/DEFAULT$;;
NameAndType	MODULE$:Lscala/xml/dtd/DEFAULT$;
Field	scala/xml/dtd/DEFAULT$.MODULE$:Lscala/xml/dtd/DEFAULT$;
NameAndType	tuple:()Lscala/Function1;
Method	scala/xml/dtd/DEFAULT$.tuple:()Lscala/Function1;
Asciz	curry;
NameAndType	curry:()Lscala/Function1;
Method	scala/xml/dtd/DEFAULT$.curry:()Lscala/Function1;
Asciz	attValue;
Asciz	Ljava/lang/String;;
Asciz	fixed;
Asciz	Z;
Asciz	<init>;
Asciz	(ZLjava/lang/String;)V;
Asciz	LineNumberTable;
Asciz	scala/xml/dtd/DEFAULT;
class	scala/xml/dtd/DEFAULT
NameAndType	fixed:Z
Field	scala/xml/dtd/DEFAULT.fixed:Z
NameAndType	attValue:Ljava/lang/String;
Field	scala/xml/dtd/DEFAULT.attValue:Ljava/lang/String;
Asciz	scala/xml/dtd/DefaultDecl;
class	scala/xml/dtd/DefaultDecl
Asciz	()V;
NameAndType	"<init>":()V
Method	scala/xml/dtd/DefaultDecl."<init>":()V
Asciz	scala/Product$class;
class	scala/Product$class
Asciz	$init$;
Asciz	(Lscala/Product;)V;
NameAndType	$init$:(Lscala/Product;)V
Method	scala/Product$class.$init$:(Lscala/Product;)V
Asciz	this;
Asciz	Lscala/xml/dtd/DEFAULT;;
Asciz	LocalVariableTable;
Asciz	gd11$1;
Asciz	(ZLjava/lang/String;)Z;
Asciz	()Z;
NameAndType	fixed:()Z
Method	scala/xml/dtd/DEFAULT.fixed:()Z
Asciz	()Ljava/lang/String;;
NameAndType	attValue:()Ljava/lang/String;
Method	scala/xml/dtd/DEFAULT.attValue:()Ljava/lang/String;
Asciz	java/lang/Object;
class	java/lang/Object
Asciz	equals;
Asciz	(Ljava/lang/Object;)Z;
NameAndType	equals:(Ljava/lang/Object;)Z
Method	java/lang/Object.equals:(Ljava/lang/Object;)Z
Asciz	canEqual;
Asciz	productElement;
Asciz	(I)Ljava/lang/Object;;
Asciz	java/lang/IndexOutOfBoundsException;
class	java/lang/IndexOutOfBoundsException
Asciz	scala/runtime/BoxesRunTime;
class	scala/runtime/BoxesRunTime
Asciz	boxToInteger;
Asciz	(I)Ljava/lang/Integer;;
NameAndType	boxToInteger:(I)Ljava/lang/Integer;
Method	scala/runtime/BoxesRunTime.boxToInteger:(I)Ljava/lang/Integer;
Asciz	toString;
NameAndType	toString:()Ljava/lang/String;
Method	java/lang/Object.toString:()Ljava/lang/String;
Asciz	(Ljava/lang/String;)V;
NameAndType	"<init>":(Ljava/lang/String;)V
Method	java/lang/IndexOutOfBoundsException."<init>":(Ljava/lang/String;)V
Asciz	boxToBoolean;
Asciz	(Z)Ljava/lang/Boolean;;
NameAndType	boxToBoolean:(Z)Ljava/lang/Boolean;
Method	scala/runtime/BoxesRunTime.boxToBoolean:(Z)Ljava/lang/Boolean;
Asciz	productArity;
Asciz	()I;
Asciz	productPrefix;
Asciz	DEFAULT;
String	DEFAULT
NameAndType	gd11$1:(ZLjava/lang/String;)Z
Method	scala/xml/dtd/DEFAULT.gd11$1:(ZLjava/lang/String;)Z
Asciz	scala/Equals;
class	scala/Equals
NameAndType	canEqual:(Ljava/lang/Object;)Z
InterfaceMethod	scala/Equals.canEqual:(Ljava/lang/Object;)Z
Asciz	temp53;
Asciz	temp54;
Asciz	temp55;
Asciz	hashCode;
Asciz	scala/runtime/ScalaRunTime$;
class	scala/runtime/ScalaRunTime$
Asciz	Lscala/runtime/ScalaRunTime$;;
NameAndType	MODULE$:Lscala/runtime/ScalaRunTime$;
Field	scala/runtime/ScalaRunTime$.MODULE$:Lscala/runtime/ScalaRunTime$;
Asciz	_hashCode;
Asciz	(Lscala/Product;)I;
NameAndType	_hashCode:(Lscala/Product;)I
Method	scala/runtime/ScalaRunTime$._hashCode:(Lscala/Product;)I
Asciz	copy;
Asciz	(ZLjava/lang/String;)Lscala/xml/dtd/DEFAULT;;
NameAndType	"<init>":(ZLjava/lang/String;)V
Method	scala/xml/dtd/DEFAULT."<init>":(ZLjava/lang/String;)V
Asciz	buildString;
Asciz	(Lscala/collection/mutable/StringBuilder;)Lscala/collection/mutable/StringBuilder;;
Asciz	#FIXED ;
String	#FIXED 
Asciz	scala/collection/mutable/StringBuilder;
class	scala/collection/mutable/StringBuilder
Asciz	append;
Asciz	(Ljava/lang/String;)Lscala/collection/mutable/StringBuilder;;
NameAndType	append:(Ljava/lang/String;)Lscala/collection/mutable/StringBuilder;
Method	scala/collection/mutable/StringBuilder.append:(Ljava/lang/String;)Lscala/collection/mutable/StringBuilder;
Asciz	scala/runtime/BoxedUnit;
class	scala/runtime/BoxedUnit
Asciz	UNIT;
Asciz	Lscala/runtime/BoxedUnit;;
NameAndType	UNIT:Lscala/runtime/BoxedUnit;
Field	scala/runtime/BoxedUnit.UNIT:Lscala/runtime/BoxedUnit;
int	34;
Asciz	(C)Lscala/collection/mutable/StringBuilder;;
NameAndType	append:(C)Lscala/collection/mutable/StringBuilder;
Method	scala/collection/mutable/StringBuilder.append:(C)Lscala/collection/mutable/StringBuilder;
Asciz	scala/collection/immutable/StringOps;
class	scala/collection/immutable/StringOps
Method	scala/collection/immutable/StringOps."<init>":(Ljava/lang/String;)V
Asciz	scala/xml/Utility$$anonfun$appendEscapedQuoted$1;
class	scala/xml/Utility$$anonfun$appendEscapedQuoted$1
Asciz	(Lscala/collection/mutable/StringBuilder;)V;
NameAndType	"<init>":(Lscala/collection/mutable/StringBuilder;)V
Method	scala/xml/Utility$$anonfun$appendEscapedQuoted$1."<init>":(Lscala/collection/mutable/StringBuilder;)V
Asciz	scala/collection/IndexedSeqLike;
class	scala/collection/IndexedSeqLike
Asciz	foreach;
Asciz	(Lscala/Function1;)V;
NameAndType	foreach:(Lscala/Function1;)V
InterfaceMethod	scala/collection/IndexedSeqLike.foreach:(Lscala/Function1;)V
Asciz	sb;
Asciz	Lscala/collection/mutable/StringBuilder;;
Asciz	scala/xml/dtd/DEFAULT$$anonfun$toString$2;
class	scala/xml/dtd/DEFAULT$$anonfun$toString$2
Asciz	(Lscala/xml/dtd/DEFAULT;)V;
NameAndType	"<init>":(Lscala/xml/dtd/DEFAULT;)V
Method	scala/xml/dtd/DEFAULT$$anonfun$toString$2."<init>":(Lscala/xml/dtd/DEFAULT;)V
Method	scala/collection/mutable/StringBuilder."<init>":()V
NameAndType	buildString:(Lscala/collection/mutable/StringBuilder;)Lscala/collection/mutable/StringBuilder;
Method	scala/xml/dtd/DEFAULT.buildString:(Lscala/collection/mutable/StringBuilder;)Lscala/collection/mutable/StringBuilder;
Method	scala/collection/mutable/StringBuilder.toString:()Ljava/lang/String;
Asciz	sb0;
Asciz	copy$default$1;
Asciz	copy$default$2;
Asciz	productElements;
Asciz	()Lscala/collection/Iterator;;
Asciz	(Lscala/Product;)Lscala/collection/Iterator;;
NameAndType	productElements:(Lscala/Product;)Lscala/collection/Iterator;
Method	scala/Product$class.productElements:(Lscala/Product;)Lscala/collection/Iterator;
Asciz	Deprecated;
Asciz	productIterator;
NameAndType	productIterator:(Lscala/Product;)Lscala/collection/Iterator;
Method	scala/Product$class.productIterator:(Lscala/Product;)Lscala/collection/Iterator;
Asciz	ScalaSig;
Asciz	InnerClasses;
Asciz	$anonfun$toString$2;
Asciz	scala/xml/Utility;
class	scala/xml/Utility
Asciz	$anonfun$appendEscapedQuoted$1;
Asciz	scala/ScalaObject;
class	scala/ScalaObject
Asciz	scala/Product;
class	scala/Product
Asciz	java/io/Serializable;
class	java/io/Serializable

{
private final java.lang.String attValue;
  Signature: Ljava/lang/String;

private final boolean fixed;
  Signature: Z

public static final scala.Function1 tuple();
  Signature: ()Lscala/Function1;
  Code:
   Stack=1, Locals=0, Args_size=0
	getstatic	Field scala/xml/dtd/DEFAULT$.MODULE$:Lscala/xml/dtd/DEFAULT$;
	invokevirtual	Method scala/xml/dtd/DEFAULT$.tuple:()Lscala/Function1;
	areturn
  Labels:

public static final scala.Function1 curry();
  Signature: ()Lscala/Function1;
  Code:
   Stack=1, Locals=0, Args_size=0
	getstatic	Field scala/xml/dtd/DEFAULT$.MODULE$:Lscala/xml/dtd/DEFAULT$;
	invokevirtual	Method scala/xml/dtd/DEFAULT$.curry:()Lscala/Function1;
	areturn
  Labels:

public scala.xml.dtd.DEFAULT(boolean, java.lang.String);
  Signature: (ZLjava/lang/String;)V
  Code:
   Stack=2, Locals=3, Args_size=3
	aload_0
	iload_1
	putfield	Field fixed:Z
	aload_0
	aload_2
	putfield	Field attValue:Ljava/lang/String;
	aload_0
	invokespecial	Method scala/xml/dtd/DefaultDecl."<init>":()V
	aload_0
	invokestatic	Method scala/Product$class.$init$:(Lscala/Product;)V
	return
  Labels:
  LocalVariableTable: 
   Start  Length  Slot  Name   Signature
   0      19      0    this       Lscala/xml/dtd/DEFAULT;
   0      19      1    fixed       Z
   0      19      2    attValue       Ljava/lang/String;


private final boolean gd11$1(boolean, java.lang.String);
  Signature: (ZLjava/lang/String;)Z
  Code:
   Stack=2, Locals=4, Args_size=3
	iload_1
	aload_0
	invokevirtual	Method fixed:()Z
	if_icmpne	l1 // iconst_0
	aload_2
	aload_0
	invokevirtual	Method attValue:()Ljava/lang/String;
	astore_3
	dup
	ifnonnull	l2 // aload_3
	pop
	aload_3
	ifnull	l3 // iconst_1
	goto	l1 // iconst_0
l2	aload_3
	invokevirtual	Method java/lang/Object.equals:(Ljava/lang/Object;)Z
	ifeq	l1 // iconst_0
l3	iconst_1
	goto	l4 // ireturn
l1	iconst_0
l4	ireturn
  Labels:
   	l2 = 26 // aload_3
   	l3 = 33 // iconst_1
   	l1 = 37 // iconst_0
   	l4 = 38 // ireturn

public boolean canEqual(java.lang.Object);
  Signature: (Ljava/lang/Object;)Z
  Code:
   Stack=1, Locals=2, Args_size=2
	aload_1
	instanceof	class scala/xml/dtd/DEFAULT
	ireturn
  Labels:

public java.lang.Object productElement(int);
  Signature: (I)Ljava/lang/Object;
  Code:
   Stack=3, Locals=3, Args_size=2
	iload_1
	tableswitch{ //0 to 1
		0: 46;
		1: 39;
		default: 24 }
	new	class java/lang/IndexOutOfBoundsException
	dup
	iload_1
	invokestatic	Method scala/runtime/BoxesRunTime.boxToInteger:(I)Ljava/lang/Integer;
	invokevirtual	Method java/lang/Object.toString:()Ljava/lang/String;
	invokespecial	Method java/lang/IndexOutOfBoundsException."<init>":(Ljava/lang/String;)V
	athrow
	aload_0
	invokevirtual	Method attValue:()Ljava/lang/String;
	goto	l1 // areturn
	aload_0
	invokevirtual	Method fixed:()Z
	istore_2
	iload_2
	invokestatic	Method scala/runtime/BoxesRunTime.boxToBoolean:(Z)Ljava/lang/Boolean;
l1	areturn
  Labels:
   	l1 = 55 // areturn

public int productArity();
  Signature: ()I
  Code:
   Stack=1, Locals=1, Args_size=1
	iconst_2
	ireturn
  Labels:

public java.lang.String productPrefix();
  Signature: ()Ljava/lang/String;
  Code:
   Stack=1, Locals=1, Args_size=1
	ldc	String DEFAULT
	areturn
  Labels:

public boolean equals(java.lang.Object);
  Signature: (Ljava/lang/Object;)Z
  Code:
   Stack=3, Locals=5, Args_size=2
	aload_0
	aload_1
	if_acmpeq	l1 // iconst_1
	aload_1
	instanceof	class scala/xml/dtd/DEFAULT
	ifeq	l2 // iconst_0
	aload_1
	checkcast	class scala/xml/dtd/DEFAULT
	astore_2
	aload_2
	invokevirtual	Method fixed:()Z
	istore_3
	aload_2
	invokevirtual	Method attValue:()Ljava/lang/String;
	astore	4
	aload_0
	iload_3
	aload	4
	invokespecial	Method gd11$1:(ZLjava/lang/String;)Z
	ifeq	l3 // iconst_0
	aload_1
	checkcast	class scala/xml/dtd/DEFAULT
	aload_0
	invokeinterface	InterfaceMethod scala/Equals.canEqual:(Ljava/lang/Object;)Z
	goto	l4 // ifeq
l3	iconst_0
	goto	l4 // ifeq
l2	iconst_0
l4	ifeq	l5 // iconst_0
l1	iconst_1
	goto	l6 // ireturn
l5	iconst_0
l6	ireturn
  Labels:
   	l3 = 51 // iconst_0
   	l2 = 55 // iconst_0
   	l4 = 56 // ifeq
   	l1 = 59 // iconst_1
   	l5 = 63 // iconst_0
   	l6 = 64 // ireturn
  LocalVariableTable: 
   Start  Length  Slot  Name   Signature
   0      65      0    this       Lscala/xml/dtd/DEFAULT;
   17      38      2    temp53       Lscala/xml/dtd/DEFAULT;
   22      33      3    temp54       Z
   28      27      4    temp55       Ljava/lang/String;


public int hashCode();
  Signature: ()I
  Code:
   Stack=2, Locals=1, Args_size=1
	getstatic	Field scala/runtime/ScalaRunTime$.MODULE$:Lscala/runtime/ScalaRunTime$;
	aload_0
	invokevirtual	Method scala/runtime/ScalaRunTime$._hashCode:(Lscala/Product;)I
	ireturn
  Labels:

public scala.xml.dtd.DEFAULT copy(boolean, java.lang.String);
  Signature: (ZLjava/lang/String;)Lscala/xml/dtd/DEFAULT;
  Code:
   Stack=4, Locals=3, Args_size=3
	new	class scala/xml/dtd/DEFAULT
	dup
	iload_1
	aload_2
	invokespecial	Method "<init>":(ZLjava/lang/String;)V
	areturn
  Labels:
  LocalVariableTable: 
   Start  Length  Slot  Name   Signature
   0      10      0    this       Lscala/xml/dtd/DEFAULT;
   0      10      1    fixed       Z
   0      10      2    attValue       Ljava/lang/String;


public scala.collection.mutable.StringBuilder buildString(scala.collection.mutable.StringBuilder);
  Signature: (Lscala/collection/mutable/StringBuilder;)Lscala/collection/mutable/StringBuilder;
  Code:
   Stack=4, Locals=3, Args_size=2
	aload_0
	invokevirtual	Method fixed:()Z
	ifeq	l1 // getstatic
	aload_1
	ldc	String #FIXED 
	invokevirtual	Method scala/collection/mutable/StringBuilder.append:(Ljava/lang/String;)Lscala/collection/mutable/StringBuilder;
	goto	l2 // pop
l1	getstatic	Field scala/runtime/BoxedUnit.UNIT:Lscala/runtime/BoxedUnit;
l2	pop
	aload_0
	invokevirtual	Method attValue:()Ljava/lang/String;
	astore_2
	aload_1
	ldc	int 34
	invokevirtual	Method scala/collection/mutable/StringBuilder.append:(C)Lscala/collection/mutable/StringBuilder;
	pop
	new	class scala/collection/immutable/StringOps
	dup
	aload_2
	invokespecial	Method scala/collection/immutable/StringOps."<init>":(Ljava/lang/String;)V
	new	class scala/xml/Utility$$anonfun$appendEscapedQuoted$1
	dup
	aload_1
	invokespecial	Method scala/xml/Utility$$anonfun$appendEscapedQuoted$1."<init>":(Lscala/collection/mutable/StringBuilder;)V
	invokeinterface	InterfaceMethod scala/collection/IndexedSeqLike.foreach:(Lscala/Function1;)V
	aload_1
	ldc	int 34
	invokevirtual	Method scala/collection/mutable/StringBuilder.append:(C)Lscala/collection/mutable/StringBuilder;
	areturn
  Labels:
   	l1 = 16 // getstatic
   	l2 = 19 // pop
  LocalVariableTable: 
   Start  Length  Slot  Name   Signature
   0      60      0    this       Lscala/xml/dtd/DEFAULT;
   0      60      1    sb       Lscala/collection/mutable/StringBuilder;


public java.lang.String toString();
  Signature: ()Ljava/lang/String;
  Code:
   Stack=2, Locals=3, Args_size=1
	new	class scala/xml/dtd/DEFAULT$$anonfun$toString$2
	dup
	pop
	aload_0
	invokespecial	Method scala/xml/dtd/DEFAULT$$anonfun$toString$2."<init>":(Lscala/xml/dtd/DEFAULT;)V
	new	class scala/collection/mutable/StringBuilder
	dup
	invokespecial	Method scala/collection/mutable/StringBuilder."<init>":()V
	astore_2
	aload_2
	checkcast	class scala/collection/mutable/StringBuilder
	astore_1
	aload_0
	aload_1
	invokevirtual	Method buildString:(Lscala/collection/mutable/StringBuilder;)Lscala/collection/mutable/StringBuilder;
	pop
	aload_2
	invokevirtual	Method scala/collection/mutable/StringBuilder.toString:()Ljava/lang/String;
	areturn
  Labels:
  LocalVariableTable: 
   Start  Length  Slot  Name   Signature
   0      33      0    this       Lscala/xml/dtd/DEFAULT;
   17      15      2    sb0       Lscala/collection/mutable/StringBuilder;


public java.lang.String attValue();
  Signature: ()Ljava/lang/String;
  Code:
   Stack=1, Locals=1, Args_size=1
	aload_0
	getfield	Field attValue:Ljava/lang/String;
	areturn
  Labels:

public boolean fixed();
  Signature: ()Z
  Code:
   Stack=1, Locals=1, Args_size=1
	aload_0
	getfield	Field fixed:Z
	ireturn
  Labels:

public boolean copy$default$1();
  Signature: ()Z
  Code:
   Stack=1, Locals=1, Args_size=1
	aload_0
	invokevirtual	Method fixed:()Z
	ireturn
  Labels:

public java.lang.String copy$default$2();
  Signature: ()Ljava/lang/String;
  Code:
   Stack=1, Locals=1, Args_size=1
	aload_0
	invokevirtual	Method attValue:()Ljava/lang/String;
	areturn
  Labels:

public scala.collection.Iterator productElements();
  Signature: ()Lscala/collection/Iterator;
  Code:
   Stack=1, Locals=1, Args_size=1
	aload_0
	invokestatic	Method scala/Product$class.productElements:(Lscala/Product;)Lscala/collection/Iterator;
	areturn
  Labels:
  Deprecated: true

public scala.collection.Iterator productIterator();
  Signature: ()Lscala/collection/Iterator;
  Code:
   Stack=1, Locals=1, Args_size=1
	aload_0
	invokestatic	Method scala/Product$class.productIterator:(Lscala/Product;)Lscala/collection/Iterator;
	areturn
  Labels:

}

