Compiled from "ContentModel.scala"
public abstract class scala.xml.dtd.DFAContentModel extends scala.xml.dtd.ContentModel implements scala.ScalaObject
  SourceFile: "ContentModel.scala"
  ScalaSig: length = 0x197
   05 00 43 06 08 01 02 FFFFFF84 FFFFFF80 FFFFFF80 FFFFFF81 10 09 02 0F 44
   46 41 43 6F 6E 74 65 6E 74 4D 6F 64 65 6C 0A 02
   03 04 01 03 64 74 64 0A 02 05 06 01 03 78 6D 6C
   0A 01 07 01 05 73 63 61 6C 61 03 00 13 03 00 0A
   0E 10 02 0B 0C 0D 01 02 09 02 0D 02 02 0C 43 6F
   6E 74 65 6E 74 4D 6F 64 65 6C 10 02 0F 10 0D 01
   06 09 02 11 06 02 0B 53 63 61 6C 61 4F 62 6A 65
   63 74 08 05 13 00 FFFFFF84 00 14 01 06 3C 69 6E 69 74
   3E 14 01 15 10 02 0B 00 08 05 17 00 FFFFFF86 00 18 01
   01 72 15 01 19 10 02 1A 1D 0E 02 0B 1B 09 02 1C
   02 01 0C 43 6F 6E 74 65 6E 74 4D 6F 64 65 6C 09
   02 1E 1F 02 06 52 65 67 45 78 70 09 02 20 21 02
   04 42 61 73 65 0A 02 22 23 01 06 72 65 67 65 78
   70 0A 02 24 06 01 04 75 74 69 6C 08 07 26 00 FFFFFFC0
   FFFFFF80 FFFFFF84 04 27 01 04 5F 64 66 61 15 01 28 10 03 29
   2C 2E 0D 01 2A 0A 02 2B 23 01 08 61 75 74 6F 6D
   61 74 61 09 02 2D 2A 02 0C 44 65 74 57 6F 72 64
   41 75 74 6F 6D 10 02 1A 2F 09 02 30 31 02 08 45
   6C 65 6D 4E 61 6D 65 0A 02 1C 02 08 07 33 00 FFFFFFC0
   FFFFFF80 FFFFFF84 04 34 01 08 5F 64 66 61 5F 24 65 71 14 02
   35 38 10 02 0F 36 09 02 37 06 02 04 55 6E 69 74
   08 07 39 32 FFFFFF81 FFFFFF80 FFFFFFC0 00 28 01 03 78 24 31 08 06
   3B 00 FFFFFFA0 FFFFFFA0 04 28 01 05 5F 64 66 61 20 08 05 3D
   00 FFFFFF84 00 27 01 03 64 66 61 29 03 00 3F 41 09 02
   40 02 02 05 4D 49 58 45 44 09 02 42 02 02 08 45
   4C 45 4D 45 4E 54 53 
  InnerClass: 
   public abstract #62= #59 of #61; //RegExp=class scala/util/regexp/Base$RegExp of class scala/util/regexp/Base
  minor version: 0
  major version: 49
  Constant pool:
const #1 = Asciz	SourceFile;
const #2 = Asciz	ContentModel.scala;
const #3 = Asciz	_dfa;
const #4 = Asciz	Lscala/util/automata/DetWordAutom;;
const #5 = Asciz	Lscala/util/automata/DetWordAutom<Lscala/xml/dtd/ContentModel$ElemName;>;;
const #6 = Asciz	Signature;
const #7 = Asciz	<init>;
const #8 = Asciz	()V;
const #9 = Asciz	Code;
const #10 = Asciz	LineNumberTable;
const #11 = Asciz	scala/xml/dtd/ContentModel;
const #12 = class	#11;	//  scala/xml/dtd/ContentModel
const #13 = NameAndType	#7:#8;//  "<init>":()V
const #14 = Method	#12.#13;	//  scala/xml/dtd/ContentModel."<init>":()V
const #15 = Asciz	scala/xml/dtd/DFAContentModel;
const #16 = class	#15;	//  scala/xml/dtd/DFAContentModel
const #17 = NameAndType	#3:#4;//  _dfa:Lscala/util/automata/DetWordAutom;
const #18 = Field	#16.#17;	//  scala/xml/dtd/DFAContentModel._dfa:Lscala/util/automata/DetWordAutom;
const #19 = Asciz	dfa;
const #20 = Asciz	()Lscala/util/automata/DetWordAutom;;
const #21 = NameAndType	#3:#20;//  _dfa:()Lscala/util/automata/DetWordAutom;
const #22 = Method	#16.#21;	//  scala/xml/dtd/DFAContentModel._dfa:()Lscala/util/automata/DetWordAutom;
const #23 = Asciz	scala/xml/dtd/ContentModel$Translator$;
const #24 = class	#23;	//  scala/xml/dtd/ContentModel$Translator$
const #25 = Asciz	MODULE$;
const #26 = Asciz	Lscala/xml/dtd/ContentModel$Translator$;;
const #27 = NameAndType	#25:#26;//  MODULE$:Lscala/xml/dtd/ContentModel$Translator$;
const #28 = Field	#24.#27;	//  scala/xml/dtd/ContentModel$Translator$.MODULE$:Lscala/xml/dtd/ContentModel$Translator$;
const #29 = Asciz	r;
const #30 = Asciz	()Lscala/util/regexp/Base$RegExp;;
const #31 = NameAndType	#29:#30;//  r:()Lscala/util/regexp/Base$RegExp;
const #32 = Method	#16.#31;	//  scala/xml/dtd/DFAContentModel.r:()Lscala/util/regexp/Base$RegExp;
const #33 = Asciz	automatonFrom;
const #34 = Asciz	(Lscala/util/regexp/Base$RegExp;I)Lscala/util/automata/NondetWordAutom;;
const #35 = NameAndType	#33:#34;//  automatonFrom:(Lscala/util/regexp/Base$RegExp;I)Lscala/util/automata/NondetWordAutom;
const #36 = Method	#24.#35;	//  scala/xml/dtd/ContentModel$Translator$.automatonFrom:(Lscala/util/regexp/Base$RegExp;I)Lscala/util/automata/NondetWordAutom;
const #37 = Asciz	scala/util/automata/SubsetConstruction;
const #38 = class	#37;	//  scala/util/automata/SubsetConstruction
const #39 = Asciz	(Lscala/util/automata/NondetWordAutom;)V;
const #40 = NameAndType	#7:#39;//  "<init>":(Lscala/util/automata/NondetWordAutom;)V
const #41 = Method	#38.#40;	//  scala/util/automata/SubsetConstruction."<init>":(Lscala/util/automata/NondetWordAutom;)V
const #42 = Asciz	determinize;
const #43 = NameAndType	#42:#20;//  determinize:()Lscala/util/automata/DetWordAutom;
const #44 = Method	#38.#43;	//  scala/util/automata/SubsetConstruction.determinize:()Lscala/util/automata/DetWordAutom;
const #45 = Asciz	_dfa_$eq;
const #46 = Asciz	(Lscala/util/automata/DetWordAutom;)V;
const #47 = NameAndType	#45:#46;//  _dfa_$eq:(Lscala/util/automata/DetWordAutom;)V
const #48 = Method	#16.#47;	//  scala/xml/dtd/DFAContentModel._dfa_$eq:(Lscala/util/automata/DetWordAutom;)V
const #49 = Asciz	this;
const #50 = Asciz	Lscala/xml/dtd/DFAContentModel;;
const #51 = Asciz	nfa;
const #52 = Asciz	Lscala/util/automata/NondetWordAutom;;
const #53 = Asciz	LocalVariableTable;
const #54 = Asciz	()Lscala/util/automata/DetWordAutom<Lscala/xml/dtd/ContentModel$ElemName;>;;
const #55 = Asciz	(Lscala/util/automata/DetWordAutom<Lscala/xml/dtd/ContentModel$ElemName;>;)V;
const #56 = Asciz	ScalaSig;
const #57 = Asciz	InnerClasses;
const #58 = Asciz	scala/util/regexp/Base$RegExp;
const #59 = class	#58;	//  scala/util/regexp/Base$RegExp
const #60 = Asciz	scala/util/regexp/Base;
const #61 = class	#60;	//  scala/util/regexp/Base
const #62 = Asciz	RegExp;
const #63 = Asciz	scala/ScalaObject;
const #64 = class	#63;	//  scala/ScalaObject

{
public scala.xml.dtd.DFAContentModel();
  Code:
   Stack=2, Locals=1, Args_size=1
   0:	aload_0
   1:	invokespecial	#14; //Method scala/xml/dtd/ContentModel."<init>":()V
   4:	aload_0
   5:	aconst_null
   6:	pop
   7:	aconst_null
   8:	putfield	#18; //Field _dfa:Lscala/util/automata/DetWordAutom;
   11:	return
  LineNumberTable: 
   line 120: 0
   line 123: 4


public scala.util.automata.DetWordAutom dfa();
  Code:
   Stack=4, Locals=2, Args_size=1
   0:	aload_0
   1:	invokespecial	#22; //Method _dfa:()Lscala/util/automata/DetWordAutom;
   4:	ifnonnull	34
   7:	getstatic	#28; //Field scala/xml/dtd/ContentModel$Translator$.MODULE$:Lscala/xml/dtd/ContentModel$Translator$;
   10:	aload_0
   11:	invokevirtual	#32; //Method r:()Lscala/util/regexp/Base$RegExp;
   14:	iconst_1
   15:	invokevirtual	#36; //Method scala/xml/dtd/ContentModel$Translator$.automatonFrom:(Lscala/util/regexp/Base$RegExp;I)Lscala/util/automata/NondetWordAutom;
   18:	astore_1
   19:	aload_0
   20:	new	#38; //class scala/util/automata/SubsetConstruction
   23:	dup
   24:	aload_1
   25:	invokespecial	#41; //Method scala/util/automata/SubsetConstruction."<init>":(Lscala/util/automata/NondetWordAutom;)V
   28:	invokevirtual	#44; //Method scala/util/automata/SubsetConstruction.determinize:()Lscala/util/automata/DetWordAutom;
   31:	invokespecial	#48; //Method _dfa_$eq:(Lscala/util/automata/DetWordAutom;)V
   34:	aload_0
   35:	invokespecial	#22; //Method _dfa:()Lscala/util/automata/DetWordAutom;
   38:	areturn
  LineNumberTable: 
   line 126: 0
   line 127: 7
   line 128: 19
   line 130: 34

  LocalVariableTable: 
   Start  Length  Slot  Name   Signature
   0      39      0    this       Lscala/xml/dtd/DFAContentModel;
   19      15      1    nfa       Lscala/util/automata/NondetWordAutom;

  Signature: length = 0x2
   00 36 

public abstract scala.util.regexp.Base$RegExp r();

}

