Compiled from "DocType.scala"
public final class scala.xml.dtd.DocType$ extends java.lang.Object implements scala.Function3,scala.ScalaObject
  SourceFile: "DocType.scala"
  Scala: length = 0x
   
  minor version: 0
  major version: 49
  Constant pool:
Asciz	SourceFile;
Asciz	DocType.scala;
Asciz	Scala;
Asciz	MODULE$;
Asciz	Lscala/xml/dtd/DocType$;;
Asciz	<clinit>;
Asciz	()V;
Asciz	Code;
Asciz	scala/xml/dtd/DocType$;
class	scala/xml/dtd/DocType$
Asciz	<init>;
NameAndType	"<init>":()V
Method	scala/xml/dtd/DocType$."<init>":()V
Asciz	toString;
Asciz	()Ljava/lang/String;;
Asciz	LineNumberTable;
Asciz	scala/Function3$class;
class	scala/Function3$class
Asciz	(Lscala/Function3;)Ljava/lang/String;;
NameAndType	toString:(Lscala/Function3;)Ljava/lang/String;
Method	scala/Function3$class.toString:(Lscala/Function3;)Ljava/lang/String;
Asciz	curried;
Asciz	()Lscala/Function1;;
Asciz	(Lscala/Function3;)Lscala/Function1;;
NameAndType	curried:(Lscala/Function3;)Lscala/Function1;
Method	scala/Function3$class.curried:(Lscala/Function3;)Lscala/Function1;
Asciz	curry;
NameAndType	curry:(Lscala/Function3;)Lscala/Function1;
Method	scala/Function3$class.curry:(Lscala/Function3;)Lscala/Function1;
Asciz	Deprecated;
Asciz	tupled;
NameAndType	tupled:(Lscala/Function3;)Lscala/Function1;
Method	scala/Function3$class.tupled:(Lscala/Function3;)Lscala/Function1;
Asciz	unapply;
Asciz	(Lscala/xml/dtd/DocType;)Lscala/Some;;
Asciz	scala/Some;
class	scala/Some
Asciz	scala/Tuple3;
class	scala/Tuple3
Asciz	scala/xml/dtd/DocType;
class	scala/xml/dtd/DocType
Asciz	name;
NameAndType	name:()Ljava/lang/String;
Method	scala/xml/dtd/DocType.name:()Ljava/lang/String;
Asciz	extID;
Asciz	()Lscala/xml/dtd/ExternalID;;
NameAndType	extID:()Lscala/xml/dtd/ExternalID;
Method	scala/xml/dtd/DocType.extID:()Lscala/xml/dtd/ExternalID;
Asciz	intSubset;
Asciz	()Lscala/collection/Seq;;
NameAndType	intSubset:()Lscala/collection/Seq;
Method	scala/xml/dtd/DocType.intSubset:()Lscala/collection/Seq;
Asciz	(Ljava/lang/Object;Ljava/lang/Object;Ljava/lang/Object;)V;
NameAndType	"<init>":(Ljava/lang/Object;Ljava/lang/Object;Ljava/lang/Object;)V
Method	scala/Tuple3."<init>":(Ljava/lang/Object;Ljava/lang/Object;Ljava/lang/Object;)V
Asciz	(Ljava/lang/Object;)V;
NameAndType	"<init>":(Ljava/lang/Object;)V
Method	scala/Some."<init>":(Ljava/lang/Object;)V
Asciz	this;
Asciz	x$0;
Asciz	Lscala/xml/dtd/DocType;;
Asciz	LocalVariableTable;
Asciz	apply;
Asciz	(Ljava/lang/String;Lscala/xml/dtd/ExternalID;Lscala/collection/Seq;)Lscala/xml/dtd/DocType;;
Asciz	(Ljava/lang/String;Lscala/xml/dtd/ExternalID;Lscala/collection/Seq;)V;
NameAndType	"<init>":(Ljava/lang/String;Lscala/xml/dtd/ExternalID;Lscala/collection/Seq;)V
Method	scala/xml/dtd/DocType."<init>":(Ljava/lang/String;Lscala/xml/dtd/ExternalID;Lscala/collection/Seq;)V
Asciz	Ljava/lang/String;;
Asciz	Lscala/xml/dtd/ExternalID;;
Asciz	Lscala/collection/Seq;;
Asciz	(Ljava/lang/Object;Ljava/lang/Object;Ljava/lang/Object;)Ljava/lang/Object;;
Asciz	java/lang/String;
class	java/lang/String
Asciz	scala/xml/dtd/ExternalID;
class	scala/xml/dtd/ExternalID
Asciz	scala/collection/Seq;
class	scala/collection/Seq
NameAndType	apply:(Ljava/lang/String;Lscala/xml/dtd/ExternalID;Lscala/collection/Seq;)Lscala/xml/dtd/DocType;
Method	scala/xml/dtd/DocType$.apply:(Ljava/lang/String;Lscala/xml/dtd/ExternalID;Lscala/collection/Seq;)Lscala/xml/dtd/DocType;
Asciz	v1;
Asciz	Ljava/lang/Object;;
Asciz	v2;
Asciz	v3;
Asciz	java/lang/Object;
class	java/lang/Object
Method	java/lang/Object."<init>":()V
NameAndType	MODULE$:Lscala/xml/dtd/DocType$;
Field	scala/xml/dtd/DocType$.MODULE$:Lscala/xml/dtd/DocType$;
Asciz	$init$;
Asciz	(Lscala/Function3;)V;
NameAndType	$init$:(Lscala/Function3;)V
Method	scala/Function3$class.$init$:(Lscala/Function3;)V
Asciz	scala/Function3;
class	scala/Function3
Asciz	scala/ScalaObject;
class	scala/ScalaObject

{
public static final scala.xml.dtd.DocType$ MODULE$;
  Signature: Lscala/xml/dtd/DocType$;

public static {};
  Signature: ()V
  Code:
   Stack=1, Locals=0, Args_size=0
	new	class scala/xml/dtd/DocType$
	invokespecial	Method "<init>":()V
	return
  Labels:

public java.lang.String toString();
  Signature: ()Ljava/lang/String;
  Code:
   Stack=1, Locals=1, Args_size=1
	aload_0
	invokestatic	Method scala/Function3$class.toString:(Lscala/Function3;)Ljava/lang/String;
	areturn
  Labels:

public scala.Function1 curried();
  Signature: ()Lscala/Function1;
  Code:
   Stack=1, Locals=1, Args_size=1
	aload_0
	invokestatic	Method scala/Function3$class.curried:(Lscala/Function3;)Lscala/Function1;
	areturn
  Labels:

public scala.Function1 curry();
  Signature: ()Lscala/Function1;
  Code:
   Stack=1, Locals=1, Args_size=1
	aload_0
	invokestatic	Method scala/Function3$class.curry:(Lscala/Function3;)Lscala/Function1;
	areturn
  Labels:
  Deprecated: true

public scala.Function1 tupled();
  Signature: ()Lscala/Function1;
  Code:
   Stack=1, Locals=1, Args_size=1
	aload_0
	invokestatic	Method scala/Function3$class.tupled:(Lscala/Function3;)Lscala/Function1;
	areturn
  Labels:

public scala.Some unapply(scala.xml.dtd.DocType);
  Signature: (Lscala/xml/dtd/DocType;)Lscala/Some;
  Code:
   Stack=7, Locals=2, Args_size=2
	new	class scala/Some
	dup
	new	class scala/Tuple3
	dup
	aload_1
	invokevirtual	Method scala/xml/dtd/DocType.name:()Ljava/lang/String;
	aload_1
	invokevirtual	Method scala/xml/dtd/DocType.extID:()Lscala/xml/dtd/ExternalID;
	aload_1
	invokevirtual	Method scala/xml/dtd/DocType.intSubset:()Lscala/collection/Seq;
	invokespecial	Method scala/Tuple3."<init>":(Ljava/lang/Object;Ljava/lang/Object;Ljava/lang/Object;)V
	invokespecial	Method scala/Some."<init>":(Ljava/lang/Object;)V
	areturn
  Labels:
  LocalVariableTable: 
   Start  Length  Slot  Name   Signature
   0      27      0    this       Lscala/xml/dtd/DocType$;
   0      27      1    x$0       Lscala/xml/dtd/DocType;


public scala.xml.dtd.DocType apply(java.lang.String, scala.xml.dtd.ExternalID, scala.collection.Seq);
  Signature: (Ljava/lang/String;Lscala/xml/dtd/ExternalID;Lscala/collection/Seq;)Lscala/xml/dtd/DocType;
  Code:
   Stack=5, Locals=4, Args_size=4
	new	class scala/xml/dtd/DocType
	dup
	aload_1
	aload_2
	aload_3
	invokespecial	Method scala/xml/dtd/DocType."<init>":(Ljava/lang/String;Lscala/xml/dtd/ExternalID;Lscala/collection/Seq;)V
	areturn
  Labels:
  LocalVariableTable: 
   Start  Length  Slot  Name   Signature
   0      11      0    this       Lscala/xml/dtd/DocType$;
   0      11      1    name       Ljava/lang/String;
   0      11      2    extID       Lscala/xml/dtd/ExternalID;
   0      11      3    intSubset       Lscala/collection/Seq;


public java.lang.Object apply(java.lang.Object, java.lang.Object, java.lang.Object);
  Signature: (Ljava/lang/Object;Ljava/lang/Object;Ljava/lang/Object;)Ljava/lang/Object;
  Code:
   Stack=4, Locals=4, Args_size=4
	aload_0
	aload_1
	checkcast	class java/lang/String
	aload_2
	checkcast	class scala/xml/dtd/ExternalID
	aload_3
	checkcast	class scala/collection/Seq
	invokevirtual	Method apply:(Ljava/lang/String;Lscala/xml/dtd/ExternalID;Lscala/collection/Seq;)Lscala/xml/dtd/DocType;
	areturn
  Labels:
  LocalVariableTable: 
   Start  Length  Slot  Name   Signature
   0      17      0    this       Lscala/xml/dtd/DocType$;
   0      17      1    v1       Ljava/lang/Object;
   0      17      2    v2       Ljava/lang/Object;
   0      17      3    v3       Ljava/lang/Object;


private scala.xml.dtd.DocType$();
  Signature: ()V
  Code:
   Stack=1, Locals=1, Args_size=1
	aload_0
	invokespecial	Method java/lang/Object."<init>":()V
	aload_0
	putstatic	Field MODULE$:Lscala/xml/dtd/DocType$;
	aload_0
	invokestatic	Method scala/Function3$class.$init$:(Lscala/Function3;)V
	return
  Labels:

}

