Compiled from "DocType.scala"
public class scala.xml.dtd.DocType extends java.lang.Object implements scala.ScalaObject,scala.Product,java.io.Serializable
  SourceFile: "DocType.scala"
  ScalaSig: length = 0x4AF
   05 00 FFFFFF81 2B 06 08 01 02 FFFFFF84 FFFFFF80 FFFFFF80 FFFFFF80 40 09 02 07
   44 6F 63 54 79 70 65 0A 02 03 04 01 03 64 74 64
   0A 02 05 06 01 03 78 6D 6C 0A 01 07 01 05 73 63
   61 6C 61 03 00 13 04 00 0A 12 16 10 02 0B 10 0D
   01 0C 0A 02 0D 0E 01 04 6C 61 6E 67 0A 01 0F 01
   04 6A 61 76 61 09 02 11 0C 02 06 4F 62 6A 65 63
   74 10 02 13 14 0D 01 06 09 02 15 06 02 0B 53 63
   61 6C 61 4F 62 6A 65 63 74 10 02 13 17 09 02 18
   06 02 07 50 72 6F 64 75 63 74 08 08 1A 00 FFFFFF82 FFFFFFCA
   FFFFFF80 FFFFFF84 00 1B 01 04 6E 61 6D 65 15 01 1C 10 02 1D
   20 0E 02 13 1E 09 02 1F 06 01 06 50 72 65 64 65
   66 09 02 21 22 02 06 53 74 72 69 6E 67 0A 02 1F
   06 08 08 24 00 FFFFFF82 FFFFFF88 FFFFFFA0 FFFFFF80 04 1C 01 05 6E 61 6D
   65 20 08 08 26 00 FFFFFF82 FFFFFFCA FFFFFF80 FFFFFF84 00 27 01 05 65 78
   74 49 44 15 01 28 10 02 29 2A 0D 01 02 09 02 2B
   02 02 0A 45 78 74 65 72 6E 61 6C 49 44 08 08 2D
   00 FFFFFF82 FFFFFF88 FFFFFFA0 FFFFFF80 04 28 01 06 65 78 74 49 44 20 08
   08 2F 00 FFFFFF82 FFFFFFCA FFFFFF80 FFFFFF84 00 30 01 09 69 6E 74 53 75
   62 73 65 74 15 01 31 10 03 32 3A 3D 0E 02 33 38
   0E 02 34 37 0D 01 35 0A 02 36 08 01 06 3C 72 6F
   6F 74 3E 09 01 07 09 02 39 06 01 07 70 61 63 6B
   61 67 65 09 02 3B 3C 02 03 53 65 71 0A 02 39 06
   10 02 29 3E 09 02 3F 02 02 04 44 65 63 6C 08 08
   41 00 FFFFFF82 FFFFFF88 FFFFFFA0 FFFFFF80 04 31 01 0A 69 6E 74 53 75 62
   73 65 74 20 08 05 43 00 FFFFFF84 00 44 01 06 3C 69 6E
   69 74 3E 14 04 45 46 47 48 10 02 29 00 08 05 1A
   42 FFFFFFC0 00 1C 08 05 26 42 FFFFFFC0 00 28 08 05 2F 42 FFFFFFC0
   00 31 08 05 4A 00 FFFFFF84 22 4B 01 08 74 6F 53 74 72
   69 6E 67 14 01 1C 08 07 4D 00 FFFFFF81 FFFFFF80 FFFFFF84 00 4E 01
   04 63 6F 70 79 14 04 45 4F 50 51 08 07 1A 4C FFFFFF90
   FFFFFF80 FFFFFFC0 00 1C 08 07 26 4C FFFFFF90 FFFFFF80 FFFFFFC0 00 28 08 07 2F
   4C FFFFFF90 FFFFFF80 FFFFFFC0 00 31 08 07 53 00 FFFFFF91 FFFFFF80 FFFFFF84 00 54 01
   0E 63 6F 70 79 24 64 65 66 61 75 6C 74 24 31 15
   01 55 2A 02 1C 56 2B 01 57 10 02 58 5D 0D 01 59
   0A 02 5A 5B 01 09 75 6E 63 68 65 63 6B 65 64 0A
   02 5C 06 01 0A 61 6E 6E 6F 74 61 74 69 6F 6E 09
   02 5E 59 02 11 75 6E 63 68 65 63 6B 65 64 56 61
   72 69 61 6E 63 65 08 07 60 00 FFFFFF91 FFFFFF80 FFFFFF84 00 61 01
   0E 63 6F 70 79 24 64 65 66 61 75 6C 74 24 32 15
   01 62 2A 02 28 56 08 07 64 00 FFFFFF91 FFFFFF80 FFFFFF84 00 65 01
   0E 63 6F 70 79 24 64 65 66 61 75 6C 74 24 33 15
   01 66 2A 02 31 56 08 08 68 00 FFFFFF84 FFFFFF80 FFFFFF80 FFFFFF84 20 69
   01 08 68 61 73 68 43 6F 64 65 14 01 6A 10 02 13
   6B 09 02 6C 06 02 03 49 6E 74 08 08 6E 00 FFFFFF84 FFFFFF80
   FFFFFF80 FFFFFF84 20 6F 01 06 65 71 75 61 6C 73 14 02 70 73
   10 02 13 71 09 02 72 06 02 07 42 6F 6F 6C 65 61
   6E 08 07 74 6D FFFFFF81 FFFFFF80 FFFFFFC0 00 75 01 03 78 24 31 10
   02 13 76 09 02 77 06 02 03 41 6E 79 08 08 79 00
   FFFFFF84 FFFFFF80 FFFFFF80 FFFFFF84 20 7A 01 0D 70 72 6F 64 75 63 74 50
   72 65 66 69 78 15 01 7B 10 02 0B 7C 09 02 21 0C
   08 08 7E 00 FFFFFF84 FFFFFF80 FFFFFF80 FFFFFF84 20 7F 01 0C 70 72 6F 64
   75 63 74 41 72 69 74 79 15 01 6A 08 0A FFFFFF81 01 00
   FFFFFF84 FFFFFF80 FFFFFF80 FFFFFF84 20 FFFFFF81 02 01 0E 70 72 6F 64 75 63 74
   45 6C 65 6D 65 6E 74 14 03 75 FFFFFF81 03 08 08 74 FFFFFF81
   00 FFFFFF81 FFFFFF80 FFFFFFC0 00 6A 08 0A FFFFFF81 05 00 FFFFFF84 FFFFFF80 FFFFFF80 FFFFFF84 20
   FFFFFF81 06 01 12 70 72 6F 64 75 63 74 45 6C 65 6D 65
   6E 74 4E 61 6D 65 14 03 7B FFFFFF81 07 08 08 74 FFFFFF81 04
   FFFFFF81 FFFFFF80 FFFFFFC0 00 6A 08 0A FFFFFF81 09 00 FFFFFF84 FFFFFF80 FFFFFF80 FFFFFF84 20 FFFFFF81
   0A 01 08 63 61 6E 45 71 75 61 6C 14 03 70 FFFFFF81 0B
   08 08 74 FFFFFF81 08 FFFFFF81 FFFFFF80 FFFFFFC0 00 75 28 03 00 FFFFFF81 0D 10
   03 13 FFFFFF81 0E 09 03 FFFFFF81 0F 06 02 0C 73 65 72 69 61
   6C 69 7A 61 62 6C 65 07 09 FFFFFF81 11 02 FFFFFF81 FFFFFF80 FFFFFF88 02
   FFFFFF81 12 01 07 44 6F 63 54 79 70 65 10 03 29 FFFFFF81 13
   06 09 01 02 FFFFFF84 FFFFFF81 FFFFFF80 FFFFFF88 02 FFFFFF81 14 13 06 FFFFFF81 13 0A
   FFFFFF81 15 12 10 07 13 FFFFFF81 16 1C 28 31 45 09 03 FFFFFF81 17
   06 02 09 46 75 6E 63 74 69 6F 6E 33 08 07 43 FFFFFF81
   13 FFFFFF84 00 FFFFFF81 19 14 02 FFFFFF81 12 08 0A FFFFFF81 1B FFFFFF81 13 FFFFFF81
   FFFFFF80 FFFFFF84 40 FFFFFF81 1C 01 05 61 70 70 6C 79 14 07 45 FFFFFF81
   1D FFFFFF81 1E FFFFFF81 1F 08 06 1A FFFFFF81 1A FFFFFFC0 00 1C 08 06 26
   FFFFFF81 1A FFFFFFC0 00 28 08 06 2F FFFFFF81 1A FFFFFFC0 00 31 08 0A FFFFFF81
   21 FFFFFF81 13 FFFFFF81 FFFFFF80 FFFFFF84 40 FFFFFF81 22 01 07 75 6E 61 70 70
   6C 79 14 04 FFFFFF81 23 FFFFFF81 29 10 05 13 FFFFFF81 24 FFFFFF81 26 09
   03 FFFFFF81 25 06 02 06 4F 70 74 69 6F 6E 10 06 13 FFFFFF81
   27 1C 28 31 09 03 FFFFFF81 28 06 02 06 54 75 70 6C 65
   33 08 07 FFFFFF81 2A FFFFFF81 20 FFFFFFC0 00 45 01 03 78 24 30 
  minor version: 0
  major version: 49
  Constant pool:
Asciz	SourceFile;
Asciz	DocType.scala;
Asciz	tupled;
Asciz	()Lscala/Function1;;
Asciz	Code;
Asciz	scala/xml/dtd/DocType$;
class	scala/xml/dtd/DocType$
Asciz	MODULE$;
Asciz	Lscala/xml/dtd/DocType$;;
NameAndType	MODULE$:Lscala/xml/dtd/DocType$;
Field	scala/xml/dtd/DocType$.MODULE$:Lscala/xml/dtd/DocType$;
NameAndType	tupled:()Lscala/Function1;
Method	scala/xml/dtd/DocType$.tupled:()Lscala/Function1;
Asciz	curry;
NameAndType	curry:()Lscala/Function1;
Method	scala/xml/dtd/DocType$.curry:()Lscala/Function1;
Asciz	Deprecated;
Asciz	curried;
NameAndType	curried:()Lscala/Function1;
Method	scala/xml/dtd/DocType$.curried:()Lscala/Function1;
Asciz	intSubset;
Asciz	Lscala/collection/Seq;;
Asciz	Lscala/collection/Seq<Lscala/xml/dtd/Decl;>;;
Asciz	Signature;
Asciz	extID;
Asciz	Lscala/xml/dtd/ExternalID;;
Asciz	name;
Asciz	Ljava/lang/String;;
Asciz	productIterator;
Asciz	()Lscala/collection/Iterator;;
Asciz	LineNumberTable;
Asciz	scala/Product$class;
class	scala/Product$class
Asciz	(Lscala/Product;)Lscala/collection/Iterator;;
NameAndType	productIterator:(Lscala/Product;)Lscala/collection/Iterator;
Method	scala/Product$class.productIterator:(Lscala/Product;)Lscala/collection/Iterator;
Asciz	productElements;
NameAndType	productElements:(Lscala/Product;)Lscala/collection/Iterator;
Method	scala/Product$class.productElements:(Lscala/Product;)Lscala/collection/Iterator;
Asciz	copy$default$3;
Asciz	()Lscala/collection/Seq;;
Asciz	scala/xml/dtd/DocType;
class	scala/xml/dtd/DocType
NameAndType	intSubset:()Lscala/collection/Seq;
Method	scala/xml/dtd/DocType.intSubset:()Lscala/collection/Seq;
Asciz	copy$default$2;
Asciz	()Lscala/xml/dtd/ExternalID;;
NameAndType	extID:()Lscala/xml/dtd/ExternalID;
Method	scala/xml/dtd/DocType.extID:()Lscala/xml/dtd/ExternalID;
Asciz	copy$default$1;
Asciz	()Ljava/lang/String;;
NameAndType	name:()Ljava/lang/String;
Method	scala/xml/dtd/DocType.name:()Ljava/lang/String;
NameAndType	name:Ljava/lang/String;
Field	scala/xml/dtd/DocType.name:Ljava/lang/String;
NameAndType	extID:Lscala/xml/dtd/ExternalID;
Field	scala/xml/dtd/DocType.extID:Lscala/xml/dtd/ExternalID;
NameAndType	intSubset:Lscala/collection/Seq;
Field	scala/xml/dtd/DocType.intSubset:Lscala/collection/Seq;
Asciz	()Lscala/collection/Seq<Lscala/xml/dtd/Decl;>;;
Asciz	toString;
Asciz	scala/Predef$;
class	scala/Predef$
Asciz	Lscala/Predef$;;
NameAndType	MODULE$:Lscala/Predef$;
Field	scala/Predef$.MODULE$:Lscala/Predef$;
Asciz	<!DOCTYPE %s %s%s>;
String	<!DOCTYPE %s %s%s>
Asciz	augmentString;
Asciz	(Ljava/lang/String;)Lscala/collection/immutable/StringOps;;
NameAndType	augmentString:(Ljava/lang/String;)Lscala/collection/immutable/StringOps;
Method	scala/Predef$.augmentString:(Ljava/lang/String;)Lscala/collection/immutable/StringOps;
Asciz	java/lang/Object;
class	java/lang/Object
Asciz	scala/xml/dtd/ExternalID;
class	scala/xml/dtd/ExternalID
NameAndType	toString:()Ljava/lang/String;
Method	scala/xml/dtd/ExternalID.toString:()Ljava/lang/String;
Asciz	intString$1;
NameAndType	intString$1:()Ljava/lang/String;
Method	scala/xml/dtd/DocType.intString$1:()Ljava/lang/String;
Asciz	genericWrapArray;
Asciz	(Ljava/lang/Object;)Lscala/collection/mutable/WrappedArray;;
NameAndType	genericWrapArray:(Ljava/lang/Object;)Lscala/collection/mutable/WrappedArray;
Method	scala/Predef$.genericWrapArray:(Ljava/lang/Object;)Lscala/collection/mutable/WrappedArray;
Asciz	scala/collection/immutable/StringLike;
class	scala/collection/immutable/StringLike
Asciz	format;
Asciz	(Lscala/collection/Seq;)Ljava/lang/String;;
NameAndType	format:(Lscala/collection/Seq;)Ljava/lang/String;
InterfaceMethod	scala/collection/immutable/StringLike.format:(Lscala/collection/Seq;)Ljava/lang/String;
Asciz	copy;
Asciz	(Ljava/lang/String;Lscala/xml/dtd/ExternalID;Lscala/collection/Seq;)Lscala/xml/dtd/DocType;;
Asciz	<init>;
Asciz	(Ljava/lang/String;Lscala/xml/dtd/ExternalID;Lscala/collection/Seq;)V;
NameAndType	"<init>":(Ljava/lang/String;Lscala/xml/dtd/ExternalID;Lscala/collection/Seq;)V
Method	scala/xml/dtd/DocType."<init>":(Ljava/lang/String;Lscala/xml/dtd/ExternalID;Lscala/collection/Seq;)V
Asciz	this;
Asciz	Lscala/xml/dtd/DocType;;
Asciz	LocalVariableTable;
Asciz	hashCode;
Asciz	()I;
Asciz	scala/runtime/ScalaRunTime$;
class	scala/runtime/ScalaRunTime$
Asciz	Lscala/runtime/ScalaRunTime$;;
NameAndType	MODULE$:Lscala/runtime/ScalaRunTime$;
Field	scala/runtime/ScalaRunTime$.MODULE$:Lscala/runtime/ScalaRunTime$;
Asciz	_hashCode;
Asciz	(Lscala/Product;)I;
NameAndType	_hashCode:(Lscala/Product;)I
Method	scala/runtime/ScalaRunTime$._hashCode:(Lscala/Product;)I
Asciz	equals;
Asciz	(Ljava/lang/Object;)Z;
Asciz	gd1$1;
Asciz	(Ljava/lang/String;Lscala/xml/dtd/ExternalID;Lscala/collection/Seq;)Z;
NameAndType	gd1$1:(Ljava/lang/String;Lscala/xml/dtd/ExternalID;Lscala/collection/Seq;)Z
Method	scala/xml/dtd/DocType.gd1$1:(Ljava/lang/String;Lscala/xml/dtd/ExternalID;Lscala/collection/Seq;)Z
Asciz	scala/Equals;
class	scala/Equals
Asciz	canEqual;
NameAndType	canEqual:(Ljava/lang/Object;)Z
InterfaceMethod	scala/Equals.canEqual:(Ljava/lang/Object;)Z
Asciz	temp2;
Asciz	temp3;
Asciz	temp4;
Asciz	temp5;
Asciz	productPrefix;
Asciz	DocType;
String	DocType
Asciz	productArity;
Asciz	productElement;
Asciz	(I)Ljava/lang/Object;;
Asciz	java/lang/IndexOutOfBoundsException;
class	java/lang/IndexOutOfBoundsException
Asciz	scala/runtime/BoxesRunTime;
class	scala/runtime/BoxesRunTime
Asciz	boxToInteger;
Asciz	(I)Ljava/lang/Integer;;
NameAndType	boxToInteger:(I)Ljava/lang/Integer;
Method	scala/runtime/BoxesRunTime.boxToInteger:(I)Ljava/lang/Integer;
Method	java/lang/Object.toString:()Ljava/lang/String;
Asciz	(Ljava/lang/String;)V;
NameAndType	"<init>":(Ljava/lang/String;)V
Method	java/lang/IndexOutOfBoundsException."<init>":(Ljava/lang/String;)V
Asciz	productElementName;
Asciz	(I)Ljava/lang/String;;
String	intSubset
String	extID
String	name
Asciz	scala/collection/IterableLike;
class	scala/collection/IterableLike
Asciz	isEmpty;
Asciz	()Z;
NameAndType	isEmpty:()Z
InterfaceMethod	scala/collection/IterableLike.isEmpty:()Z
Asciz	;
String	
Asciz	[;
String	[
Asciz	];
String	]
Asciz	scala/collection/TraversableLike;
class	scala/collection/TraversableLike
Asciz	mkString;
Asciz	(Ljava/lang/String;Ljava/lang/String;Ljava/lang/String;)Ljava/lang/String;;
NameAndType	mkString:(Ljava/lang/String;Ljava/lang/String;Ljava/lang/String;)Ljava/lang/String;
InterfaceMethod	scala/collection/TraversableLike.mkString:(Ljava/lang/String;Ljava/lang/String;Ljava/lang/String;)Ljava/lang/String;
NameAndType	equals:(Ljava/lang/Object;)Z
Method	java/lang/Object.equals:(Ljava/lang/Object;)Z
Asciz	()V;
NameAndType	"<init>":()V
Method	java/lang/Object."<init>":()V
Asciz	$init$;
Asciz	(Lscala/Product;)V;
NameAndType	$init$:(Lscala/Product;)V
Method	scala/Product$class.$init$:(Lscala/Product;)V
Asciz	scala/xml/Utility$;
class	scala/xml/Utility$
Asciz	Lscala/xml/Utility$;;
NameAndType	MODULE$:Lscala/xml/Utility$;
Field	scala/xml/Utility$.MODULE$:Lscala/xml/Utility$;
Asciz	scala/xml/parsing/TokenTests;
class	scala/xml/parsing/TokenTests
Asciz	isName;
Asciz	(Ljava/lang/String;)Z;
NameAndType	isName:(Ljava/lang/String;)Z
InterfaceMethod	scala/xml/parsing/TokenTests.isName:(Ljava/lang/String;)Z
Asciz	java/lang/IllegalArgumentException;
class	java/lang/IllegalArgumentException
Asciz	scala/collection/mutable/StringBuilder;
class	scala/collection/mutable/StringBuilder
Method	scala/collection/mutable/StringBuilder."<init>":()V
Asciz	append;
Asciz	(Ljava/lang/Object;)Lscala/collection/mutable/StringBuilder;;
NameAndType	append:(Ljava/lang/Object;)Lscala/collection/mutable/StringBuilder;
Method	scala/collection/mutable/StringBuilder.append:(Ljava/lang/Object;)Lscala/collection/mutable/StringBuilder;
Asciz	 must be an XML Name;
String	 must be an XML Name
Method	scala/collection/mutable/StringBuilder.toString:()Ljava/lang/String;
Method	java/lang/IllegalArgumentException."<init>":(Ljava/lang/String;)V
Asciz	(Ljava/lang/String;Lscala/xml/dtd/ExternalID;Lscala/collection/Seq<Lscala/xml/dtd/Decl;>;)V;
Asciz	ScalaSig;
Asciz	scala/ScalaObject;
class	scala/ScalaObject
Asciz	scala/Product;
class	scala/Product
Asciz	java/io/Serializable;
class	java/io/Serializable

{
private final scala.collection.Seq intSubset;
  Signature: Lscala/collection/Seq;
  Signature: length = 0x2
   00 17 

private final scala.xml.dtd.ExternalID extID;
  Signature: Lscala/xml/dtd/ExternalID;

private final java.lang.String name;
  Signature: Ljava/lang/String;

public static final scala.Function1 tupled();
  Signature: ()Lscala/Function1;
  Code:
   Stack=1, Locals=0, Args_size=0
	getstatic	Field scala/xml/dtd/DocType$.MODULE$:Lscala/xml/dtd/DocType$;
	invokevirtual	Method scala/xml/dtd/DocType$.tupled:()Lscala/Function1;
	areturn
  Labels:

public static final scala.Function1 curry();
  Signature: ()Lscala/Function1;
  Code:
   Stack=1, Locals=0, Args_size=0
	getstatic	Field scala/xml/dtd/DocType$.MODULE$:Lscala/xml/dtd/DocType$;
	invokevirtual	Method scala/xml/dtd/DocType$.curry:()Lscala/Function1;
	areturn
  Labels:
  Deprecated: true

public static final scala.Function1 curried();
  Signature: ()Lscala/Function1;
  Code:
   Stack=1, Locals=0, Args_size=0
	getstatic	Field scala/xml/dtd/DocType$.MODULE$:Lscala/xml/dtd/DocType$;
	invokevirtual	Method scala/xml/dtd/DocType$.curried:()Lscala/Function1;
	areturn
  Labels:

public scala.collection.Iterator productIterator();
  Signature: ()Lscala/collection/Iterator;
  Code:
   Stack=1, Locals=1, Args_size=1
	aload_0
	invokestatic	Method scala/Product$class.productIterator:(Lscala/Product;)Lscala/collection/Iterator;
	areturn
  Labels:

public scala.collection.Iterator productElements();
  Signature: ()Lscala/collection/Iterator;
  Code:
   Stack=1, Locals=1, Args_size=1
	aload_0
	invokestatic	Method scala/Product$class.productElements:(Lscala/Product;)Lscala/collection/Iterator;
	areturn
  Labels:
  Deprecated: true

public scala.collection.Seq copy$default$3();
  Signature: ()Lscala/collection/Seq;
  Code:
   Stack=1, Locals=1, Args_size=1
	aload_0
	invokevirtual	Method intSubset:()Lscala/collection/Seq;
	areturn
  Labels:

public scala.xml.dtd.ExternalID copy$default$2();
  Signature: ()Lscala/xml/dtd/ExternalID;
  Code:
   Stack=1, Locals=1, Args_size=1
	aload_0
	invokevirtual	Method extID:()Lscala/xml/dtd/ExternalID;
	areturn
  Labels:

public java.lang.String copy$default$1();
  Signature: ()Ljava/lang/String;
  Code:
   Stack=1, Locals=1, Args_size=1
	aload_0
	invokevirtual	Method name:()Ljava/lang/String;
	areturn
  Labels:

public java.lang.String name();
  Signature: ()Ljava/lang/String;
  Code:
   Stack=1, Locals=1, Args_size=1
	aload_0
	getfield	Field name:Ljava/lang/String;
	areturn
  Labels:

public scala.xml.dtd.ExternalID extID();
  Signature: ()Lscala/xml/dtd/ExternalID;
  Code:
   Stack=1, Locals=1, Args_size=1
	aload_0
	getfield	Field extID:Lscala/xml/dtd/ExternalID;
	areturn
  Labels:

public scala.collection.Seq intSubset();
  Signature: ()Lscala/collection/Seq;
  Code:
   Stack=1, Locals=1, Args_size=1
	aload_0
	getfield	Field intSubset:Lscala/collection/Seq;
	areturn
  Labels:
  Signature: length = 0x2
   00 3C 

public final java.lang.String toString();
  Signature: ()Ljava/lang/String;
  Code:
   Stack=6, Locals=1, Args_size=1
	getstatic	Field scala/Predef$.MODULE$:Lscala/Predef$;
	ldc	String <!DOCTYPE %s %s%s>
	invokevirtual	Method scala/Predef$.augmentString:(Ljava/lang/String;)Lscala/collection/immutable/StringOps;
	getstatic	Field scala/Predef$.MODULE$:Lscala/Predef$;
	iconst_3
	anewarray	class java/lang/Object
	dup
	iconst_0
	aload_0
	invokevirtual	Method name:()Ljava/lang/String;
	aastore
	dup
	iconst_1
	aload_0
	invokevirtual	Method extID:()Lscala/xml/dtd/ExternalID;
	invokevirtual	Method scala/xml/dtd/ExternalID.toString:()Ljava/lang/String;
	aastore
	dup
	iconst_2
	aload_0
	invokespecial	Method intString$1:()Ljava/lang/String;
	aastore
	invokevirtual	Method scala/Predef$.genericWrapArray:(Ljava/lang/Object;)Lscala/collection/mutable/WrappedArray;
	invokeinterface	InterfaceMethod scala/collection/immutable/StringLike.format:(Lscala/collection/Seq;)Ljava/lang/String;
	areturn
  Labels:

public scala.xml.dtd.DocType copy(java.lang.String, scala.xml.dtd.ExternalID, scala.collection.Seq);
  Signature: (Ljava/lang/String;Lscala/xml/dtd/ExternalID;Lscala/collection/Seq;)Lscala/xml/dtd/DocType;
  Code:
   Stack=5, Locals=4, Args_size=4
	new	class scala/xml/dtd/DocType
	dup
	aload_1
	aload_2
	aload_3
	invokespecial	Method "<init>":(Ljava/lang/String;Lscala/xml/dtd/ExternalID;Lscala/collection/Seq;)V
	areturn
  Labels:
  LocalVariableTable: 
   Start  Length  Slot  Name   Signature
   0      11      0    this       Lscala/xml/dtd/DocType;
   0      11      1    name       Ljava/lang/String;
   0      11      2    extID       Lscala/xml/dtd/ExternalID;
   0      11      3    intSubset       Lscala/collection/Seq;


public int hashCode();
  Signature: ()I
  Code:
   Stack=2, Locals=1, Args_size=1
	getstatic	Field scala/runtime/ScalaRunTime$.MODULE$:Lscala/runtime/ScalaRunTime$;
	aload_0
	invokevirtual	Method scala/runtime/ScalaRunTime$._hashCode:(Lscala/Product;)I
	ireturn
  Labels:

public boolean equals(java.lang.Object);
  Signature: (Ljava/lang/Object;)Z
  Code:
   Stack=4, Locals=6, Args_size=2
	aload_0
	aload_1
	if_acmpeq	l1 // iconst_1
	aload_1
	instanceof	class scala/xml/dtd/DocType
	ifeq	l2 // iconst_0
	aload_1
	checkcast	class scala/xml/dtd/DocType
	astore_2
	aload_2
	invokevirtual	Method name:()Ljava/lang/String;
	astore_3
	aload_2
	invokevirtual	Method extID:()Lscala/xml/dtd/ExternalID;
	astore	4
	aload_2
	invokevirtual	Method intSubset:()Lscala/collection/Seq;
	astore	5
	aload_0
	aload_3
	aload	4
	aload	5
	invokespecial	Method gd1$1:(Ljava/lang/String;Lscala/xml/dtd/ExternalID;Lscala/collection/Seq;)Z
	ifeq	l3 // iconst_0
	aload_1
	checkcast	class scala/xml/dtd/DocType
	aload_0
	invokeinterface	InterfaceMethod scala/Equals.canEqual:(Ljava/lang/Object;)Z
	goto	l4 // ifeq
l3	iconst_0
	goto	l4 // ifeq
l2	iconst_0
l4	ifeq	l5 // iconst_0
l1	iconst_1
	goto	l6 // ireturn
l5	iconst_0
l6	ireturn
  Labels:
   	l3 = 59 // iconst_0
   	l2 = 63 // iconst_0
   	l4 = 64 // ifeq
   	l1 = 67 // iconst_1
   	l5 = 71 // iconst_0
   	l6 = 72 // ireturn
  LocalVariableTable: 
   Start  Length  Slot  Name   Signature
   0      73      0    this       Lscala/xml/dtd/DocType;
   17      46      2    temp2       Lscala/xml/dtd/DocType;
   22      41      3    temp3       Ljava/lang/String;
   28      35      4    temp4       Lscala/xml/dtd/ExternalID;
   34      29      5    temp5       Lscala/collection/Seq;


public java.lang.String productPrefix();
  Signature: ()Ljava/lang/String;
  Code:
   Stack=1, Locals=1, Args_size=1
	ldc	String DocType
	areturn
  Labels:

public int productArity();
  Signature: ()I
  Code:
   Stack=1, Locals=1, Args_size=1
	iconst_3
	ireturn
  Labels:

public java.lang.Object productElement(int);
  Signature: (I)Ljava/lang/Object;
  Code:
   Stack=3, Locals=2, Args_size=2
	iload_1
	tableswitch{ //0 to 2
		0: 57;
		1: 50;
		2: 43;
		default: 28 }
	new	class java/lang/IndexOutOfBoundsException
	dup
	iload_1
	invokestatic	Method scala/runtime/BoxesRunTime.boxToInteger:(I)Ljava/lang/Integer;
	invokevirtual	Method java/lang/Object.toString:()Ljava/lang/String;
	invokespecial	Method java/lang/IndexOutOfBoundsException."<init>":(Ljava/lang/String;)V
	athrow
	aload_0
	invokevirtual	Method intSubset:()Lscala/collection/Seq;
	goto	l1 // areturn
	aload_0
	invokevirtual	Method extID:()Lscala/xml/dtd/ExternalID;
	goto	l1 // areturn
	aload_0
	invokevirtual	Method name:()Ljava/lang/String;
l1	areturn
  Labels:
   	l1 = 61 // areturn

public java.lang.String productElementName(int);
  Signature: (I)Ljava/lang/String;
  Code:
   Stack=3, Locals=2, Args_size=2
	iload_1
	tableswitch{ //0 to 2
		0: 53;
		1: 48;
		2: 43;
		default: 28 }
	new	class java/lang/IndexOutOfBoundsException
	dup
	iload_1
	invokestatic	Method scala/runtime/BoxesRunTime.boxToInteger:(I)Ljava/lang/Integer;
	invokevirtual	Method java/lang/Object.toString:()Ljava/lang/String;
	invokespecial	Method java/lang/IndexOutOfBoundsException."<init>":(Ljava/lang/String;)V
	athrow
	ldc	String intSubset
	goto	l1 // areturn
	ldc	String extID
	goto	l1 // areturn
	ldc	String name
l1	areturn
  Labels:
   	l1 = 55 // areturn

public boolean canEqual(java.lang.Object);
  Signature: (Ljava/lang/Object;)Z
  Code:
   Stack=1, Locals=2, Args_size=2
	aload_1
	instanceof	class scala/xml/dtd/DocType
	ireturn
  Labels:

private final java.lang.String intString$1();
  Signature: ()Ljava/lang/String;
  Code:
   Stack=4, Locals=1, Args_size=1
	aload_0
	invokevirtual	Method intSubset:()Lscala/collection/Seq;
	invokeinterface	InterfaceMethod scala/collection/IterableLike.isEmpty:()Z
	ifeq	l1 // aload_0
	ldc	String 
	goto	l2 // areturn
l1	aload_0
	invokevirtual	Method intSubset:()Lscala/collection/Seq;
	ldc	String [
	ldc	String 
	ldc	String ]
	invokeinterface	InterfaceMethod scala/collection/TraversableLike.mkString:(Ljava/lang/String;Ljava/lang/String;Ljava/lang/String;)Ljava/lang/String;
l2	areturn
  Labels:
   	l1 = 17 // aload_0
   	l2 = 32 // areturn

private final boolean gd1$1(java.lang.String, scala.xml.dtd.ExternalID, scala.collection.Seq);
  Signature: (Ljava/lang/String;Lscala/xml/dtd/ExternalID;Lscala/collection/Seq;)Z
  Code:
   Stack=2, Locals=7, Args_size=4
	aload_1
	aload_0
	invokevirtual	Method name:()Ljava/lang/String;
	astore	4
	dup
	ifnonnull	l1 // aload
	pop
	aload	4
	ifnull	l2 // aload_2
	goto	l3 // iconst_0
l1	aload	4
	invokevirtual	Method java/lang/Object.equals:(Ljava/lang/Object;)Z
	ifeq	l3 // iconst_0
l2	aload_2
	aload_0
	invokevirtual	Method extID:()Lscala/xml/dtd/ExternalID;
	astore	5
	dup
	ifnonnull	l4 // aload
	pop
	aload	5
	ifnull	l5 // aload_3
	goto	l3 // iconst_0
l4	aload	5
	invokevirtual	Method java/lang/Object.equals:(Ljava/lang/Object;)Z
	ifeq	l3 // iconst_0
l5	aload_3
	aload_0
	invokevirtual	Method intSubset:()Lscala/collection/Seq;
	astore	6
	dup
	ifnonnull	l6 // aload
	pop
	aload	6
	ifnull	l7 // iconst_1
	goto	l3 // iconst_0
l6	aload	6
	invokevirtual	Method java/lang/Object.equals:(Ljava/lang/Object;)Z
	ifeq	l3 // iconst_0
l7	iconst_1
	goto	l8 // ireturn
l3	iconst_0
l8	ireturn
  Labels:
   	l1 = 20 // aload
   	l2 = 28 // aload_2
   	l4 = 48 // aload
   	l5 = 56 // aload_3
   	l6 = 76 // aload
   	l7 = 84 // iconst_1
   	l3 = 88 // iconst_0
   	l8 = 89 // ireturn

public scala.xml.dtd.DocType(java.lang.String, scala.xml.dtd.ExternalID, scala.collection.Seq);
  Signature: (Ljava/lang/String;Lscala/xml/dtd/ExternalID;Lscala/collection/Seq;)V
  Code:
   Stack=4, Locals=4, Args_size=4
	aload_0
	aload_1
	putfield	Field name:Ljava/lang/String;
	aload_0
	aload_2
	putfield	Field extID:Lscala/xml/dtd/ExternalID;
	aload_0
	aload_3
	putfield	Field intSubset:Lscala/collection/Seq;
	aload_0
	invokespecial	Method java/lang/Object."<init>":()V
	aload_0
	invokestatic	Method scala/Product$class.$init$:(Lscala/Product;)V
	getstatic	Field scala/xml/Utility$.MODULE$:Lscala/xml/Utility$;
	aload_1
	invokeinterface	InterfaceMethod scala/xml/parsing/TokenTests.isName:(Ljava/lang/String;)Z
	ifeq	l1 // new
	return
l1	new	class java/lang/IllegalArgumentException
	dup
	new	class scala/collection/mutable/StringBuilder
	dup
	invokespecial	Method scala/collection/mutable/StringBuilder."<init>":()V
	aload_1
	invokevirtual	Method scala/collection/mutable/StringBuilder.append:(Ljava/lang/Object;)Lscala/collection/mutable/StringBuilder;
	ldc	String  must be an XML Name
	invokevirtual	Method scala/collection/mutable/StringBuilder.append:(Ljava/lang/Object;)Lscala/collection/mutable/StringBuilder;
	invokevirtual	Method scala/collection/mutable/StringBuilder.toString:()Ljava/lang/String;
	invokespecial	Method java/lang/IllegalArgumentException."<init>":(Ljava/lang/String;)V
	athrow
  Labels:
   	l1 = 36 // new
  LocalVariableTable: 
   Start  Length  Slot  Name   Signature
   0      63      0    this       Lscala/xml/dtd/DocType;
   0      63      1    name       Ljava/lang/String;
   0      63      2    extID       Lscala/xml/dtd/ExternalID;
   0      63      3    intSubset       Lscala/collection/Seq;

  Signature: length = 0x2
   00 FFFFFFC9 

}

