Compiled from "ElementValidator.scala"
public final class scala.xml.dtd.ElementValidator$$anonfun$getIterable$2 extends java.lang.Object implements scala.Function1,scala.ScalaObject,java.io.Serializable
  SourceFile: "ElementValidator.scala"
  Scala: length = 0x
   
  InnerClass: 
   public ElemName=class scala/xml/dtd/ContentModel$ElemName of class scala/xml/dtd/ContentModel
   public final $anonfun$getIterable$2=class scala/xml/dtd/ElementValidator$$anonfun$getIterable$2 of class scala/xml/dtd/ElementValidator
  minor version: 0
  major version: 49
  Constant pool:
Asciz	SourceFile;
Asciz	ElementValidator.scala;
Asciz	<clinit>;
Asciz	()V;
Asciz	Code;
Asciz	serialVersionUID;
Asciz	J;
Asciz	scala/xml/dtd/ElementValidator$$anonfun$getIterable$2;
class	scala/xml/dtd/ElementValidator$$anonfun$getIterable$2
NameAndType	serialVersionUID:J
Field	scala/xml/dtd/ElementValidator$$anonfun$getIterable$2.serialVersionUID:J
Asciz	<init>;
Asciz	(Lscala/xml/dtd/ElementValidator;)V;
Asciz	LineNumberTable;
Asciz	java/lang/Object;
class	java/lang/Object
NameAndType	"<init>":()V
Method	java/lang/Object."<init>":()V
Asciz	scala/Function1$class;
class	scala/Function1$class
Asciz	$init$;
Asciz	(Lscala/Function1;)V;
NameAndType	$init$:(Lscala/Function1;)V
Method	scala/Function1$class.$init$:(Lscala/Function1;)V
Asciz	this;
Asciz	Lscala/xml/dtd/ElementValidator$$anonfun$getIterable$2;;
Asciz	$outer;
Asciz	Lscala/xml/dtd/ElementValidator;;
Asciz	LocalVariableTable;
Asciz	apply;
Asciz	(Ljava/lang/Object;)Ljava/lang/Object;;
Asciz	scala/xml/Node;
class	scala/xml/Node
Asciz	(Lscala/xml/Node;)Lscala/xml/dtd/ContentModel$ElemName;;
NameAndType	apply:(Lscala/xml/Node;)Lscala/xml/dtd/ContentModel$ElemName;
Method	scala/xml/dtd/ElementValidator$$anonfun$getIterable$2.apply:(Lscala/xml/Node;)Lscala/xml/dtd/ContentModel$ElemName;
Asciz	v1;
Asciz	Ljava/lang/Object;;
Asciz	scala/xml/dtd/ContentModel$ElemName;
class	scala/xml/dtd/ContentModel$ElemName
Asciz	label;
Asciz	()Ljava/lang/String;;
NameAndType	label:()Ljava/lang/String;
Method	scala/xml/Node.label:()Ljava/lang/String;
Asciz	(Ljava/lang/String;)V;
NameAndType	"<init>":(Ljava/lang/String;)V
Method	scala/xml/dtd/ContentModel$ElemName."<init>":(Ljava/lang/String;)V
Asciz	x;
Asciz	Lscala/xml/Node;;
Asciz	andThen;
Asciz	(Lscala/Function1;)Lscala/Function1;;
Asciz	(Lscala/Function1;Lscala/Function1;)Lscala/Function1;;
NameAndType	andThen:(Lscala/Function1;Lscala/Function1;)Lscala/Function1;
Method	scala/Function1$class.andThen:(Lscala/Function1;Lscala/Function1;)Lscala/Function1;
Asciz	g;
Asciz	Lscala/Function1;;
Asciz	compose;
NameAndType	compose:(Lscala/Function1;Lscala/Function1;)Lscala/Function1;
Method	scala/Function1$class.compose:(Lscala/Function1;Lscala/Function1;)Lscala/Function1;
Asciz	toString;
Asciz	(Lscala/Function1;)Ljava/lang/String;;
NameAndType	toString:(Lscala/Function1;)Ljava/lang/String;
Method	scala/Function1$class.toString:(Lscala/Function1;)Ljava/lang/String;
Asciz	Scala;
Asciz	InnerClasses;
Asciz	scala/xml/dtd/ContentModel;
class	scala/xml/dtd/ContentModel
Asciz	ElemName;
Asciz	scala/xml/dtd/ElementValidator;
class	scala/xml/dtd/ElementValidator
Asciz	$anonfun$getIterable$2;
Asciz	scala/Function1;
class	scala/Function1
Asciz	scala/ScalaObject;
class	scala/ScalaObject
Asciz	java/io/Serializable;
class	java/io/Serializable

{
public static final long serialVersionUID;
  Signature: J

public static {};
  Signature: ()V
  Code:
   Stack=2, Locals=0, Args_size=0
	lconst_0
	putstatic	Field serialVersionUID:J
	return
  Labels:

public scala.xml.dtd.ElementValidator$$anonfun$getIterable$2(scala.xml.dtd.ElementValidator);
  Signature: (Lscala/xml/dtd/ElementValidator;)V
  Code:
   Stack=1, Locals=2, Args_size=2
	aload_0
	invokespecial	Method java/lang/Object."<init>":()V
	aload_0
	invokestatic	Method scala/Function1$class.$init$:(Lscala/Function1;)V
	return
  Labels:
  LocalVariableTable: 
   Start  Length  Slot  Name   Signature
   0      9      0    this       Lscala/xml/dtd/ElementValidator$$anonfun$getIterable$2;
   0      9      1    $outer       Lscala/xml/dtd/ElementValidator;


public final java.lang.Object apply(java.lang.Object);
  Signature: (Ljava/lang/Object;)Ljava/lang/Object;
  Code:
   Stack=2, Locals=2, Args_size=2
	aload_0
	aload_1
	checkcast	class scala/xml/Node
	invokevirtual	Method apply:(Lscala/xml/Node;)Lscala/xml/dtd/ContentModel$ElemName;
	areturn
  Labels:
  LocalVariableTable: 
   Start  Length  Slot  Name   Signature
   0      9      0    this       Lscala/xml/dtd/ElementValidator$$anonfun$getIterable$2;
   0      9      1    v1       Ljava/lang/Object;


public final scala.xml.dtd.ContentModel$ElemName apply(scala.xml.Node);
  Signature: (Lscala/xml/Node;)Lscala/xml/dtd/ContentModel$ElemName;
  Code:
   Stack=3, Locals=2, Args_size=2
	new	class scala/xml/dtd/ContentModel$ElemName
	dup
	aload_1
	invokevirtual	Method scala/xml/Node.label:()Ljava/lang/String;
	invokespecial	Method scala/xml/dtd/ContentModel$ElemName."<init>":(Ljava/lang/String;)V
	areturn
  Labels:
  LocalVariableTable: 
   Start  Length  Slot  Name   Signature
   0      12      0    this       Lscala/xml/dtd/ElementValidator$$anonfun$getIterable$2;
   0      12      1    x       Lscala/xml/Node;


public scala.Function1 andThen(scala.Function1);
  Signature: (Lscala/Function1;)Lscala/Function1;
  Code:
   Stack=2, Locals=2, Args_size=2
	aload_0
	aload_1
	invokestatic	Method scala/Function1$class.andThen:(Lscala/Function1;Lscala/Function1;)Lscala/Function1;
	areturn
  Labels:
  LocalVariableTable: 
   Start  Length  Slot  Name   Signature
   0      6      0    this       Lscala/xml/dtd/ElementValidator$$anonfun$getIterable$2;
   0      6      1    g       Lscala/Function1;


public scala.Function1 compose(scala.Function1);
  Signature: (Lscala/Function1;)Lscala/Function1;
  Code:
   Stack=2, Locals=2, Args_size=2
	aload_0
	aload_1
	invokestatic	Method scala/Function1$class.compose:(Lscala/Function1;Lscala/Function1;)Lscala/Function1;
	areturn
  Labels:
  LocalVariableTable: 
   Start  Length  Slot  Name   Signature
   0      6      0    this       Lscala/xml/dtd/ElementValidator$$anonfun$getIterable$2;
   0      6      1    g       Lscala/Function1;


public java.lang.String toString();
  Signature: ()Ljava/lang/String;
  Code:
   Stack=1, Locals=1, Args_size=1
	aload_0
	invokestatic	Method scala/Function1$class.toString:(Lscala/Function1;)Ljava/lang/String;
	areturn
  Labels:

}

