Compiled from "ElementValidator.scala"
public final class scala.xml.dtd.ElementValidator$$anonfun$check$6 extends java.lang.Object implements scala.Function2,scala.ScalaObject,java.io.Serializable
  SourceFile: "ElementValidator.scala"
  Scala: length = 0x
   
  InnerClass: 
   public #96= #44 of #95; //ElemName=class scala/xml/dtd/ContentModel$ElemName of class scala/xml/dtd/ContentModel
   public final #97= #9 of #56; //$anonfun$check$6=class scala/xml/dtd/ElementValidator$$anonfun$check$6 of class scala/xml/dtd/ElementValidator
   public final #98= #68 of #9; //$anonfun$apply$1=class scala/xml/dtd/ElementValidator$$anonfun$check$6$$anonfun$apply$1 of class scala/xml/dtd/ElementValidator$$anonfun$check$6
  minor version: 0
  major version: 49
  Constant pool:
const #1 = Asciz	SourceFile;
const #2 = Asciz	ElementValidator.scala;
const #3 = Asciz	<clinit>;
const #4 = Asciz	()V;
const #5 = Asciz	Code;
const #6 = Asciz	serialVersionUID;
const #7 = Asciz	J;
const #8 = Asciz	scala/xml/dtd/ElementValidator$$anonfun$check$6;
const #9 = class	#8;	//  scala/xml/dtd/ElementValidator$$anonfun$check$6
const #10 = NameAndType	#6:#7;//  serialVersionUID:J
const #11 = Field	#9.#10;	//  scala/xml/dtd/ElementValidator$$anonfun$check$6.serialVersionUID:J
const #12 = Asciz	$outer;
const #13 = Asciz	Lscala/xml/dtd/ElementValidator;;
const #14 = Asciz	<init>;
const #15 = Asciz	(Lscala/xml/dtd/ElementValidator;)V;
const #16 = Asciz	LineNumberTable;
const #17 = Asciz	java/lang/NullPointerException;
const #18 = class	#17;	//  java/lang/NullPointerException
const #19 = NameAndType	#14:#4;//  "<init>":()V
const #20 = Method	#18.#19;	//  java/lang/NullPointerException."<init>":()V
const #21 = NameAndType	#12:#13;//  $outer:Lscala/xml/dtd/ElementValidator;
const #22 = Field	#9.#21;	//  scala/xml/dtd/ElementValidator$$anonfun$check$6.$outer:Lscala/xml/dtd/ElementValidator;
const #23 = Asciz	java/lang/Object;
const #24 = class	#23;	//  java/lang/Object
const #25 = Method	#24.#19;	//  java/lang/Object."<init>":()V
const #26 = Asciz	scala/Function2$class;
const #27 = class	#26;	//  scala/Function2$class
const #28 = Asciz	$init$;
const #29 = Asciz	(Lscala/Function2;)V;
const #30 = NameAndType	#28:#29;//  $init$:(Lscala/Function2;)V
const #31 = Method	#27.#30;	//  scala/Function2$class.$init$:(Lscala/Function2;)V
const #32 = Asciz	this;
const #33 = Asciz	Lscala/xml/dtd/ElementValidator$$anonfun$check$6;;
const #34 = Asciz	LocalVariableTable;
const #35 = Asciz	apply;
const #36 = Asciz	(Ljava/lang/Object;Ljava/lang/Object;)Ljava/lang/Object;;
const #37 = Asciz	scala/runtime/BoxesRunTime;
const #38 = class	#37;	//  scala/runtime/BoxesRunTime
const #39 = Asciz	unboxToInt;
const #40 = Asciz	(Ljava/lang/Object;)I;
const #41 = NameAndType	#39:#40;//  unboxToInt:(Ljava/lang/Object;)I
const #42 = Method	#38.#41;	//  scala/runtime/BoxesRunTime.unboxToInt:(Ljava/lang/Object;)I
const #43 = Asciz	scala/xml/dtd/ContentModel$ElemName;
const #44 = class	#43;	//  scala/xml/dtd/ContentModel$ElemName
const #45 = Asciz	(ILscala/xml/dtd/ContentModel$ElemName;)I;
const #46 = NameAndType	#35:#45;//  apply:(ILscala/xml/dtd/ContentModel$ElemName;)I
const #47 = Method	#9.#46;	//  scala/xml/dtd/ElementValidator$$anonfun$check$6.apply:(ILscala/xml/dtd/ContentModel$ElemName;)I
const #48 = Asciz	boxToInteger;
const #49 = Asciz	(I)Ljava/lang/Integer;;
const #50 = NameAndType	#48:#49;//  boxToInteger:(I)Ljava/lang/Integer;
const #51 = Method	#38.#50;	//  scala/runtime/BoxesRunTime.boxToInteger:(I)Ljava/lang/Integer;
const #52 = Asciz	v1;
const #53 = Asciz	Ljava/lang/Object;;
const #54 = Asciz	v2;
const #55 = Asciz	scala/xml/dtd/ElementValidator;
const #56 = class	#55;	//  scala/xml/dtd/ElementValidator
const #57 = Asciz	dfa;
const #58 = Asciz	()Lscala/util/automata/DetWordAutom;;
const #59 = NameAndType	#57:#58;//  dfa:()Lscala/util/automata/DetWordAutom;
const #60 = Method	#56.#59;	//  scala/xml/dtd/ElementValidator.dfa:()Lscala/util/automata/DetWordAutom;
const #61 = Asciz	scala/util/automata/DetWordAutom;
const #62 = class	#61;	//  scala/util/automata/DetWordAutom
const #63 = Asciz	delta;
const #64 = Asciz	()[Lscala/collection/Map;;
const #65 = NameAndType	#63:#64;//  delta:()[Lscala/collection/Map;
const #66 = Method	#62.#65;	//  scala/util/automata/DetWordAutom.delta:()[Lscala/collection/Map;
const #67 = Asciz	scala/xml/dtd/ElementValidator$$anonfun$check$6$$anonfun$apply$1;
const #68 = class	#67;	//  scala/xml/dtd/ElementValidator$$anonfun$check$6$$anonfun$apply$1
const #69 = Asciz	(Lscala/xml/dtd/ElementValidator$$anonfun$check$6;Lscala/xml/dtd/ContentModel$ElemName;)V;
const #70 = NameAndType	#14:#69;//  "<init>":(Lscala/xml/dtd/ElementValidator$$anonfun$check$6;Lscala/xml/dtd/ContentModel$ElemName;)V
const #71 = Method	#68.#70;	//  scala/xml/dtd/ElementValidator$$anonfun$check$6$$anonfun$apply$1."<init>":(Lscala/xml/dtd/ElementValidator$$anonfun$check$6;Lscala/xml/dtd/ContentModel$ElemName;)V
const #72 = Asciz	scala/collection/MapLike;
const #73 = class	#72;	//  scala/collection/MapLike
const #74 = Asciz	getOrElse;
const #75 = Asciz	(Ljava/lang/Object;Lscala/Function0;)Ljava/lang/Object;;
const #76 = NameAndType	#74:#75;//  getOrElse:(Ljava/lang/Object;Lscala/Function0;)Ljava/lang/Object;
const #77 = InterfaceMethod	#73.#76;	//  scala/collection/MapLike.getOrElse:(Ljava/lang/Object;Lscala/Function0;)Ljava/lang/Object;
const #78 = Asciz	q;
const #79 = Asciz	I;
const #80 = Asciz	e$1;
const #81 = Asciz	Lscala/xml/dtd/ContentModel$ElemName;;
const #82 = Asciz	curry;
const #83 = Asciz	()Lscala/Function1;;
const #84 = Asciz	(Lscala/Function2;)Lscala/Function1;;
const #85 = NameAndType	#82:#84;//  curry:(Lscala/Function2;)Lscala/Function1;
const #86 = Method	#27.#85;	//  scala/Function2$class.curry:(Lscala/Function2;)Lscala/Function1;
const #87 = Asciz	toString;
const #88 = Asciz	()Ljava/lang/String;;
const #89 = Asciz	(Lscala/Function2;)Ljava/lang/String;;
const #90 = NameAndType	#87:#89;//  toString:(Lscala/Function2;)Ljava/lang/String;
const #91 = Method	#27.#90;	//  scala/Function2$class.toString:(Lscala/Function2;)Ljava/lang/String;
const #92 = Asciz	Scala;
const #93 = Asciz	InnerClasses;
const #94 = Asciz	scala/xml/dtd/ContentModel;
const #95 = class	#94;	//  scala/xml/dtd/ContentModel
const #96 = Asciz	ElemName;
const #97 = Asciz	$anonfun$check$6;
const #98 = Asciz	$anonfun$apply$1;
const #99 = Asciz	scala/Function2;
const #100 = class	#99;	//  scala/Function2
const #101 = Asciz	scala/ScalaObject;
const #102 = class	#101;	//  scala/ScalaObject
const #103 = Asciz	java/io/Serializable;
const #104 = class	#103;	//  java/io/Serializable

{
public static final long serialVersionUID;

public static {};
  Code:
   Stack=2, Locals=0, Args_size=0
   0:	lconst_0
   1:	putstatic	#11; //Field serialVersionUID:J
   4:	return

public scala.xml.dtd.ElementValidator$$anonfun$check$6(scala.xml.dtd.ElementValidator);
  Code:
   Stack=2, Locals=2, Args_size=2
   0:	aload_1
   1:	ifnonnull	12
   4:	new	#18; //class java/lang/NullPointerException
   7:	dup
   8:	invokespecial	#20; //Method java/lang/NullPointerException."<init>":()V
   11:	athrow
   12:	aload_0
   13:	aload_1
   14:	putfield	#22; //Field $outer:Lscala/xml/dtd/ElementValidator;
   17:	aload_0
   18:	invokespecial	#25; //Method java/lang/Object."<init>":()V
   21:	aload_0
   22:	invokestatic	#31; //Method scala/Function2$class.$init$:(Lscala/Function2;)V
   25:	return
  LineNumberTable: 
   line 116: 0

  LocalVariableTable: 
   Start  Length  Slot  Name   Signature
   0      26      0    this       Lscala/xml/dtd/ElementValidator$$anonfun$check$6;
   0      26      1    $outer       Lscala/xml/dtd/ElementValidator;


public final java.lang.Object apply(java.lang.Object, java.lang.Object);
  Code:
   Stack=3, Locals=5, Args_size=3
   0:	aload_0
   1:	getfield	#22; //Field $outer:Lscala/xml/dtd/ElementValidator;
   4:	astore	4
   6:	aload_0
   7:	aload_1
   8:	invokestatic	#42; //Method scala/runtime/BoxesRunTime.unboxToInt:(Ljava/lang/Object;)I
   11:	aload_2
   12:	checkcast	#44; //class scala/xml/dtd/ContentModel$ElemName
   15:	invokevirtual	#47; //Method apply:(ILscala/xml/dtd/ContentModel$ElemName;)I
   18:	istore_3
   19:	iload_3
   20:	invokestatic	#51; //Method scala/runtime/BoxesRunTime.boxToInteger:(I)Ljava/lang/Integer;
   23:	areturn
  LineNumberTable: 
   line 116: 0

  LocalVariableTable: 
   Start  Length  Slot  Name   Signature
   0      24      0    this       Lscala/xml/dtd/ElementValidator$$anonfun$check$6;
   6      18      1    v1       Ljava/lang/Object;
   6      18      2    v2       Ljava/lang/Object;


public final int apply(int, scala.xml.dtd.ContentModel$ElemName);
  Code:
   Stack=6, Locals=4, Args_size=3
   0:	aload_0
   1:	getfield	#22; //Field $outer:Lscala/xml/dtd/ElementValidator;
   4:	astore_3
   5:	aload_0
   6:	getfield	#22; //Field $outer:Lscala/xml/dtd/ElementValidator;
   9:	invokevirtual	#60; //Method scala/xml/dtd/ElementValidator.dfa:()Lscala/util/automata/DetWordAutom;
   12:	invokevirtual	#66; //Method scala/util/automata/DetWordAutom.delta:()[Lscala/collection/Map;
   15:	iload_1
   16:	aaload
   17:	aload_2
   18:	new	#68; //class scala/xml/dtd/ElementValidator$$anonfun$check$6$$anonfun$apply$1
   21:	dup
   22:	aload_0
   23:	aload_2
   24:	invokespecial	#71; //Method scala/xml/dtd/ElementValidator$$anonfun$check$6$$anonfun$apply$1."<init>":(Lscala/xml/dtd/ElementValidator$$anonfun$check$6;Lscala/xml/dtd/ContentModel$ElemName;)V
   27:	invokeinterface	#77,  3; //InterfaceMethod scala/collection/MapLike.getOrElse:(Ljava/lang/Object;Lscala/Function0;)Ljava/lang/Object;
   32:	invokestatic	#42; //Method scala/runtime/BoxesRunTime.unboxToInt:(Ljava/lang/Object;)I
   35:	ireturn
  LineNumberTable: 
   line 117: 0

  LocalVariableTable: 
   Start  Length  Slot  Name   Signature
   0      36      0    this       Lscala/xml/dtd/ElementValidator$$anonfun$check$6;
   5      31      1    q       I
   5      31      2    e$1       Lscala/xml/dtd/ContentModel$ElemName;


public scala.Function1 curry();
  Code:
   Stack=1, Locals=1, Args_size=1
   0:	aload_0
   1:	invokestatic	#86; //Method scala/Function2$class.curry:(Lscala/Function2;)Lscala/Function1;
   4:	areturn
  LineNumberTable: 
   line 116: 0


public java.lang.String toString();
  Code:
   Stack=1, Locals=1, Args_size=1
   0:	aload_0
   1:	invokestatic	#91; //Method scala/Function2$class.toString:(Lscala/Function2;)Ljava/lang/String;
   4:	areturn
  LineNumberTable: 
   line 116: 0


}

