Compiled from "ElementValidator.scala"
public final class scala.xml.dtd.ElementValidator$$anonfun$check$2 extends java.lang.Object implements scala.Function1,scala.ScalaObject,java.io.Serializable
  SourceFile: "ElementValidator.scala"
  Scala: length = 0x
   
  InnerClass: 
   public final $anonfun$check$2=class scala/xml/dtd/ElementValidator$$anonfun$check$2 of class scala/xml/dtd/ElementValidator
  minor version: 0
  major version: 49
  Constant pool:
Asciz	SourceFile;
Asciz	ElementValidator.scala;
Asciz	<clinit>;
Asciz	()V;
Asciz	Code;
Asciz	serialVersionUID;
Asciz	J;
Asciz	scala/xml/dtd/ElementValidator$$anonfun$check$2;
class	scala/xml/dtd/ElementValidator$$anonfun$check$2
NameAndType	serialVersionUID:J
Field	scala/xml/dtd/ElementValidator$$anonfun$check$2.serialVersionUID:J
Asciz	ok$1;
Asciz	Lscala/runtime/ObjectRef;;
Asciz	$outer;
Asciz	Lscala/xml/dtd/ElementValidator;;
Asciz	<init>;
Asciz	(Lscala/xml/dtd/ElementValidator;Lscala/runtime/ObjectRef;)V;
Asciz	LineNumberTable;
Asciz	java/lang/NullPointerException;
class	java/lang/NullPointerException
NameAndType	"<init>":()V
Method	java/lang/NullPointerException."<init>":()V
NameAndType	$outer:Lscala/xml/dtd/ElementValidator;
Field	scala/xml/dtd/ElementValidator$$anonfun$check$2.$outer:Lscala/xml/dtd/ElementValidator;
NameAndType	ok$1:Lscala/runtime/ObjectRef;
Field	scala/xml/dtd/ElementValidator$$anonfun$check$2.ok$1:Lscala/runtime/ObjectRef;
Asciz	java/lang/Object;
class	java/lang/Object
Method	java/lang/Object."<init>":()V
Asciz	scala/Function1$class;
class	scala/Function1$class
Asciz	$init$;
Asciz	(Lscala/Function1;)V;
NameAndType	$init$:(Lscala/Function1;)V
Method	scala/Function1$class.$init$:(Lscala/Function1;)V
Asciz	this;
Asciz	Lscala/xml/dtd/ElementValidator$$anonfun$check$2;;
Asciz	LocalVariableTable;
Asciz	gd5$1;
Asciz	(Ljava/lang/String;Ljava/lang/String;I)Z;
Asciz	scala/runtime/ObjectRef;
class	scala/runtime/ObjectRef
Asciz	elem;
Asciz	Ljava/lang/Object;;
NameAndType	elem:Ljava/lang/Object;
Field	scala/runtime/ObjectRef.elem:Ljava/lang/Object;
Asciz	scala/collection/mutable/BitSet;
class	scala/collection/mutable/BitSet
Asciz	scala/runtime/BoxesRunTime;
class	scala/runtime/BoxesRunTime
Asciz	boxToInteger;
Asciz	(I)Ljava/lang/Integer;;
NameAndType	boxToInteger:(I)Ljava/lang/Integer;
Method	scala/runtime/BoxesRunTime.boxToInteger:(I)Ljava/lang/Integer;
Asciz	scala/collection/SetLike;
class	scala/collection/SetLike
Asciz	apply;
Asciz	(Ljava/lang/Object;)Z;
NameAndType	apply:(Ljava/lang/Object;)Z
InterfaceMethod	scala/collection/SetLike.apply:(Ljava/lang/Object;)Z
Asciz	(Ljava/lang/Object;)Ljava/lang/Object;;
Asciz	scala/Tuple2;
class	scala/Tuple2
Asciz	(Lscala/Tuple2;)V;
NameAndType	apply:(Lscala/Tuple2;)V
Method	scala/xml/dtd/ElementValidator$$anonfun$check$2.apply:(Lscala/Tuple2;)V
Asciz	scala/runtime/BoxedUnit;
class	scala/runtime/BoxedUnit
Asciz	UNIT;
Asciz	Lscala/runtime/BoxedUnit;;
NameAndType	UNIT:Lscala/runtime/BoxedUnit;
Field	scala/runtime/BoxedUnit.UNIT:Lscala/runtime/BoxedUnit;
Asciz	v1;
Asciz	_1;
Asciz	()Ljava/lang/Object;;
NameAndType	_1:()Ljava/lang/Object;
Method	scala/Tuple2._1:()Ljava/lang/Object;
Asciz	scala/xml/dtd/AttrDecl;
class	scala/xml/dtd/AttrDecl
Asciz	_2;
NameAndType	_2:()Ljava/lang/Object;
Method	scala/Tuple2._2:()Ljava/lang/Object;
Asciz	unboxToInt;
Asciz	(Ljava/lang/Object;)I;
NameAndType	unboxToInt:(Ljava/lang/Object;)I
Method	scala/runtime/BoxesRunTime.unboxToInt:(Ljava/lang/Object;)I
Asciz	name;
Asciz	()Ljava/lang/String;;
NameAndType	name:()Ljava/lang/String;
Method	scala/xml/dtd/AttrDecl.name:()Ljava/lang/String;
Asciz	tpe;
NameAndType	tpe:()Ljava/lang/String;
Method	scala/xml/dtd/AttrDecl.tpe:()Ljava/lang/String;
Asciz	scala/xml/dtd/REQUIRED$;
class	scala/xml/dtd/REQUIRED$
Asciz	MODULE$;
Asciz	Lscala/xml/dtd/REQUIRED$;;
NameAndType	MODULE$:Lscala/xml/dtd/REQUIRED$;
Field	scala/xml/dtd/REQUIRED$.MODULE$:Lscala/xml/dtd/REQUIRED$;
Asciz	default;
Asciz	()Lscala/xml/dtd/DefaultDecl;;
NameAndType	default:()Lscala/xml/dtd/DefaultDecl;
Method	scala/xml/dtd/AttrDecl.default:()Lscala/xml/dtd/DefaultDecl;
Asciz	equals;
NameAndType	equals:(Ljava/lang/Object;)Z
Method	java/lang/Object.equals:(Ljava/lang/Object;)Z
NameAndType	gd5$1:(Ljava/lang/String;Ljava/lang/String;I)Z
Method	scala/xml/dtd/ElementValidator$$anonfun$check$2.gd5$1:(Ljava/lang/String;Ljava/lang/String;I)Z
Asciz	scala/xml/dtd/ElementValidator;
class	scala/xml/dtd/ElementValidator
Asciz	scala$xml$dtd$ElementValidator$$exc;
Asciz	()Lscala/collection/immutable/List;;
NameAndType	scala$xml$dtd$ElementValidator$$exc:()Lscala/collection/immutable/List;
Method	scala/xml/dtd/ElementValidator.scala$xml$dtd$ElementValidator$$exc:()Lscala/collection/immutable/List;
Asciz	scala/xml/dtd/ValidationException;
class	scala/xml/dtd/ValidationException
Asciz	missing value for REQUIRED attribute %s of type %s;
String	missing value for REQUIRED attribute %s of type %s
Asciz	scala/collection/immutable/StringOps;
class	scala/collection/immutable/StringOps
Asciz	(Ljava/lang/String;)V;
NameAndType	"<init>":(Ljava/lang/String;)V
Method	scala/collection/immutable/StringOps."<init>":(Ljava/lang/String;)V
Asciz	scala/Predef$;
class	scala/Predef$
Asciz	Lscala/Predef$;;
NameAndType	MODULE$:Lscala/Predef$;
Field	scala/Predef$.MODULE$:Lscala/Predef$;
Asciz	genericWrapArray;
Asciz	(Ljava/lang/Object;)Lscala/collection/mutable/WrappedArray;;
NameAndType	genericWrapArray:(Ljava/lang/Object;)Lscala/collection/mutable/WrappedArray;
Method	scala/Predef$.genericWrapArray:(Ljava/lang/Object;)Lscala/collection/mutable/WrappedArray;
Asciz	scala/collection/immutable/StringLike;
class	scala/collection/immutable/StringLike
Asciz	format;
Asciz	(Lscala/collection/Seq;)Ljava/lang/String;;
NameAndType	format:(Lscala/collection/Seq;)Ljava/lang/String;
InterfaceMethod	scala/collection/immutable/StringLike.format:(Lscala/collection/Seq;)Ljava/lang/String;
Method	scala/xml/dtd/ValidationException."<init>":(Ljava/lang/String;)V
Asciz	scala/collection/immutable/List;
class	scala/collection/immutable/List
Asciz	$colon$colon;
Asciz	(Ljava/lang/Object;)Lscala/collection/immutable/List;;
NameAndType	$colon$colon:(Ljava/lang/Object;)Lscala/collection/immutable/List;
Method	scala/collection/immutable/List.$colon$colon:(Ljava/lang/Object;)Lscala/collection/immutable/List;
Asciz	scala$xml$dtd$ElementValidator$$exc_$eq;
Asciz	(Lscala/collection/immutable/List;)V;
NameAndType	scala$xml$dtd$ElementValidator$$exc_$eq:(Lscala/collection/immutable/List;)V
Method	scala/xml/dtd/ElementValidator.scala$xml$dtd$ElementValidator$$exc_$eq:(Lscala/collection/immutable/List;)V
Asciz	scala/MatchError;
class	scala/MatchError
Asciz	toString;
NameAndType	toString:()Ljava/lang/String;
Method	scala/Tuple2.toString:()Ljava/lang/String;
Method	scala/MatchError."<init>":(Ljava/lang/String;)V
Asciz	temp31;
Asciz	Lscala/xml/dtd/AttrDecl;;
Asciz	temp32;
Asciz	I;
Asciz	temp33;
Asciz	Ljava/lang/String;;
Asciz	temp34;
Asciz	(Lscala/Tuple2<Lscala/xml/dtd/AttrDecl;Ljava/lang/Integer;>;)V;
Asciz	Signature;
Asciz	andThen;
Asciz	(Lscala/Function1;)Lscala/Function1;;
Asciz	(Lscala/Function1;Lscala/Function1;)Lscala/Function1;;
NameAndType	andThen:(Lscala/Function1;Lscala/Function1;)Lscala/Function1;
Method	scala/Function1$class.andThen:(Lscala/Function1;Lscala/Function1;)Lscala/Function1;
Asciz	g;
Asciz	Lscala/Function1;;
Asciz	compose;
NameAndType	compose:(Lscala/Function1;Lscala/Function1;)Lscala/Function1;
Method	scala/Function1$class.compose:(Lscala/Function1;Lscala/Function1;)Lscala/Function1;
Asciz	(Lscala/Function1;)Ljava/lang/String;;
NameAndType	toString:(Lscala/Function1;)Ljava/lang/String;
Method	scala/Function1$class.toString:(Lscala/Function1;)Ljava/lang/String;
Asciz	Scala;
Asciz	InnerClasses;
Asciz	$anonfun$check$2;
Asciz	scala/Function1;
class	scala/Function1
Asciz	scala/ScalaObject;
class	scala/ScalaObject
Asciz	java/io/Serializable;
class	java/io/Serializable

{
public static final long serialVersionUID;
  Signature: J

private final scala.runtime.ObjectRef ok$1;
  Signature: Lscala/runtime/ObjectRef;

private final scala.xml.dtd.ElementValidator $outer;
  Signature: Lscala/xml/dtd/ElementValidator;

public static {};
  Signature: ()V
  Code:
   Stack=2, Locals=0, Args_size=0
	lconst_0
	putstatic	Field serialVersionUID:J
	return
  Labels:

public scala.xml.dtd.ElementValidator$$anonfun$check$2(scala.xml.dtd.ElementValidator, scala.runtime.ObjectRef);
  Signature: (Lscala/xml/dtd/ElementValidator;Lscala/runtime/ObjectRef;)V
  Code:
   Stack=2, Locals=3, Args_size=3
	aload_1
	ifnonnull	l1 // aload_0
	new	class java/lang/NullPointerException
	dup
	invokespecial	Method java/lang/NullPointerException."<init>":()V
	athrow
l1	aload_0
	aload_1
	putfield	Field $outer:Lscala/xml/dtd/ElementValidator;
	aload_0
	aload_2
	putfield	Field ok$1:Lscala/runtime/ObjectRef;
	aload_0
	invokespecial	Method java/lang/Object."<init>":()V
	aload_0
	invokestatic	Method scala/Function1$class.$init$:(Lscala/Function1;)V
	return
  Labels:
   	l1 = 12 // aload_0
  LocalVariableTable: 
   Start  Length  Slot  Name   Signature
   0      31      0    this       Lscala/xml/dtd/ElementValidator$$anonfun$check$2;
   0      31      1    $outer       Lscala/xml/dtd/ElementValidator;


private final boolean gd5$1(java.lang.String, java.lang.String, int);
  Signature: (Ljava/lang/String;Ljava/lang/String;I)Z
  Code:
   Stack=2, Locals=4, Args_size=4
	aload_0
	getfield	Field ok$1:Lscala/runtime/ObjectRef;
	getfield	Field scala/runtime/ObjectRef.elem:Ljava/lang/Object;
	checkcast	class scala/collection/mutable/BitSet
	iload_3
	invokestatic	Method scala/runtime/BoxesRunTime.boxToInteger:(I)Ljava/lang/Integer;
	invokeinterface	InterfaceMethod scala/collection/SetLike.apply:(Ljava/lang/Object;)Z
	ifeq	l1 // iconst_1
	iconst_0
	goto	l2 // ireturn
l1	iconst_1
l2	ireturn
  Labels:
   	l1 = 26 // iconst_1
   	l2 = 27 // ireturn

public final java.lang.Object apply(java.lang.Object);
  Signature: (Ljava/lang/Object;)Ljava/lang/Object;
  Code:
   Stack=2, Locals=3, Args_size=2
	aload_0
	getfield	Field $outer:Lscala/xml/dtd/ElementValidator;
	astore_2
	aload_0
	aload_1
	checkcast	class scala/Tuple2
	invokevirtual	Method apply:(Lscala/Tuple2;)V
	getstatic	Field scala/runtime/BoxedUnit.UNIT:Lscala/runtime/BoxedUnit;
	areturn
  Labels:
  LocalVariableTable: 
   Start  Length  Slot  Name   Signature
   0      17      0    this       Lscala/xml/dtd/ElementValidator$$anonfun$check$2;
   5      12      1    v1       Ljava/lang/Object;


public final void apply(scala.Tuple2);
  Signature: (Lscala/Tuple2;)V
  Code:
   Stack=10, Locals=9, Args_size=2
	aload_0
	getfield	Field $outer:Lscala/xml/dtd/ElementValidator;
	astore	8
	aload_1
	ifnull	l1 // iconst_1
	aload_1
	invokevirtual	Method scala/Tuple2._1:()Ljava/lang/Object;
	checkcast	class scala/xml/dtd/AttrDecl
	astore_2
	aload_1
	invokevirtual	Method scala/Tuple2._2:()Ljava/lang/Object;
	invokestatic	Method scala/runtime/BoxesRunTime.unboxToInt:(Ljava/lang/Object;)I
	istore	4
	aload_2
	ifnull	l2 // iconst_1
	aload_2
	invokevirtual	Method scala/xml/dtd/AttrDecl.name:()Ljava/lang/String;
	astore	6
	aload_2
	invokevirtual	Method scala/xml/dtd/AttrDecl.tpe:()Ljava/lang/String;
	astore	7
	getstatic	Field scala/xml/dtd/REQUIRED$.MODULE$:Lscala/xml/dtd/REQUIRED$;
	aload_2
	invokevirtual	Method scala/xml/dtd/AttrDecl.default:()Lscala/xml/dtd/DefaultDecl;
	astore_3
	dup
	ifnonnull	l3 // aload_3
	pop
	aload_3
	ifnull	l4 // aload_0
	goto	l5 // iconst_1
l3	aload_3
	invokevirtual	Method java/lang/Object.equals:(Ljava/lang/Object;)Z
	ifeq	l5 // iconst_1
l4	aload_0
	aload	6
	aload	7
	iload	4
	invokespecial	Method gd5$1:(Ljava/lang/String;Ljava/lang/String;I)Z
	ifeq	l6 // iconst_1
	aload_0
	getfield	Field $outer:Lscala/xml/dtd/ElementValidator;
	aload_0
	getfield	Field $outer:Lscala/xml/dtd/ElementValidator;
	invokevirtual	Method scala/xml/dtd/ElementValidator.scala$xml$dtd$ElementValidator$$exc:()Lscala/collection/immutable/List;
	new	class scala/xml/dtd/ValidationException
	dup
	ldc	String missing value for REQUIRED attribute %s of type %s
	astore	5
	new	class scala/collection/immutable/StringOps
	dup
	aload	5
	invokespecial	Method scala/collection/immutable/StringOps."<init>":(Ljava/lang/String;)V
	getstatic	Field scala/Predef$.MODULE$:Lscala/Predef$;
	iconst_2
	anewarray	class java/lang/Object
	dup
	iconst_0
	aload	6
	aastore
	dup
	iconst_1
	aload	7
	aastore
	invokevirtual	Method scala/Predef$.genericWrapArray:(Ljava/lang/Object;)Lscala/collection/mutable/WrappedArray;
	invokeinterface	InterfaceMethod scala/collection/immutable/StringLike.format:(Lscala/collection/Seq;)Ljava/lang/String;
	invokespecial	Method scala/xml/dtd/ValidationException."<init>":(Ljava/lang/String;)V
	invokevirtual	Method scala/collection/immutable/List.$colon$colon:(Ljava/lang/Object;)Lscala/collection/immutable/List;
	invokevirtual	Method scala/xml/dtd/ElementValidator.scala$xml$dtd$ElementValidator$$exc_$eq:(Lscala/collection/immutable/List;)V
	goto	l7 // return
l6	iconst_1
	ifne	l7 // return
	new	class scala/MatchError
	dup
	aload_1
	invokevirtual	Method scala/Tuple2.toString:()Ljava/lang/String;
	invokespecial	Method scala/MatchError."<init>":(Ljava/lang/String;)V
	athrow
l5	iconst_1
	ifne	l7 // return
	new	class scala/MatchError
	dup
	aload_1
	invokevirtual	Method scala/Tuple2.toString:()Ljava/lang/String;
	invokespecial	Method scala/MatchError."<init>":(Ljava/lang/String;)V
	athrow
l2	iconst_1
	ifne	l7 // return
	new	class scala/MatchError
	dup
	aload_1
	invokevirtual	Method scala/Tuple2.toString:()Ljava/lang/String;
	invokespecial	Method scala/MatchError."<init>":(Ljava/lang/String;)V
	athrow
l1	iconst_1
	ifeq	l8 // new
l7	return
l8	new	class scala/MatchError
	dup
	aload_1
	invokevirtual	Method scala/Tuple2.toString:()Ljava/lang/String;
	invokespecial	Method scala/MatchError."<init>":(Ljava/lang/String;)V
	athrow
  Labels:
   	l3 = 63 // aload_3
   	l4 = 70 // aload_0
   	l6 = 148 // iconst_1
   	l5 = 164 // iconst_1
   	l2 = 180 // iconst_1
   	l1 = 196 // iconst_1
   	l7 = 200 // return
   	l8 = 201 // new
  LocalVariableTable: 
   Start  Length  Slot  Name   Signature
   0      213      0    this       Lscala/xml/dtd/ElementValidator$$anonfun$check$2;
   18      178      2    temp31       Lscala/xml/dtd/AttrDecl;
   27      169      4    temp32       I
   37      143      6    temp33       Ljava/lang/String;
   43      137      7    temp34       Ljava/lang/String;

  Signature: length = 0x2
   00 FFFFFFA3 

public scala.Function1 andThen(scala.Function1);
  Signature: (Lscala/Function1;)Lscala/Function1;
  Code:
   Stack=2, Locals=2, Args_size=2
	aload_0
	aload_1
	invokestatic	Method scala/Function1$class.andThen:(Lscala/Function1;Lscala/Function1;)Lscala/Function1;
	areturn
  Labels:
  LocalVariableTable: 
   Start  Length  Slot  Name   Signature
   0      6      0    this       Lscala/xml/dtd/ElementValidator$$anonfun$check$2;
   0      6      1    g       Lscala/Function1;


public scala.Function1 compose(scala.Function1);
  Signature: (Lscala/Function1;)Lscala/Function1;
  Code:
   Stack=2, Locals=2, Args_size=2
	aload_0
	aload_1
	invokestatic	Method scala/Function1$class.compose:(Lscala/Function1;Lscala/Function1;)Lscala/Function1;
	areturn
  Labels:
  LocalVariableTable: 
   Start  Length  Slot  Name   Signature
   0      6      0    this       Lscala/xml/dtd/ElementValidator$$anonfun$check$2;
   0      6      1    g       Lscala/Function1;


public java.lang.String toString();
  Signature: ()Ljava/lang/String;
  Code:
   Stack=1, Locals=1, Args_size=1
	aload_0
	invokestatic	Method scala/Function1$class.toString:(Lscala/Function1;)Ljava/lang/String;
	areturn
  Labels:

}

