Compiled from "ElementValidator.scala"
public final class scala.xml.dtd.ElementValidator$$anonfun$check$6 extends scala.runtime.AbstractFunction2 implements java.io.Serializable
  SourceFile: "ElementValidator.scala"
  Scala: length = 0x
   
  InnerClass: 
   public ElemName=class scala/xml/dtd/ContentModel$ElemName of class scala/xml/dtd/ContentModel
   public final $anonfun$check$6=class scala/xml/dtd/ElementValidator$$anonfun$check$6 of class scala/xml/dtd/ElementValidator
   public final $anonfun$apply$1=class scala/xml/dtd/ElementValidator$$anonfun$check$6$$anonfun$apply$1 of class scala/xml/dtd/ElementValidator$$anonfun$check$6
  minor version: 0
  major version: 49
  Constant pool:
Asciz	SourceFile;
Asciz	ElementValidator.scala;
Asciz	<clinit>;
Asciz	()V;
Asciz	Code;
Asciz	serialVersionUID;
Asciz	J;
Asciz	scala/xml/dtd/ElementValidator$$anonfun$check$6;
class	scala/xml/dtd/ElementValidator$$anonfun$check$6
NameAndType	serialVersionUID:J
Field	scala/xml/dtd/ElementValidator$$anonfun$check$6.serialVersionUID:J
Asciz	$outer;
Asciz	Lscala/xml/dtd/ElementValidator;;
Asciz	<init>;
Asciz	(Lscala/xml/dtd/ElementValidator;)V;
Asciz	LineNumberTable;
Asciz	java/lang/NullPointerException;
class	java/lang/NullPointerException
NameAndType	"<init>":()V
Method	java/lang/NullPointerException."<init>":()V
NameAndType	$outer:Lscala/xml/dtd/ElementValidator;
Field	scala/xml/dtd/ElementValidator$$anonfun$check$6.$outer:Lscala/xml/dtd/ElementValidator;
Asciz	scala/runtime/AbstractFunction2;
class	scala/runtime/AbstractFunction2
Method	scala/runtime/AbstractFunction2."<init>":()V
Asciz	this;
Asciz	Lscala/xml/dtd/ElementValidator$$anonfun$check$6;;
Asciz	LocalVariableTable;
Asciz	apply;
Asciz	(Ljava/lang/Object;Ljava/lang/Object;)Ljava/lang/Object;;
Asciz	scala/runtime/BoxesRunTime;
class	scala/runtime/BoxesRunTime
Asciz	unboxToInt;
Asciz	(Ljava/lang/Object;)I;
NameAndType	unboxToInt:(Ljava/lang/Object;)I
Method	scala/runtime/BoxesRunTime.unboxToInt:(Ljava/lang/Object;)I
Asciz	scala/xml/dtd/ContentModel$ElemName;
class	scala/xml/dtd/ContentModel$ElemName
Asciz	(ILscala/xml/dtd/ContentModel$ElemName;)I;
NameAndType	apply:(ILscala/xml/dtd/ContentModel$ElemName;)I
Method	scala/xml/dtd/ElementValidator$$anonfun$check$6.apply:(ILscala/xml/dtd/ContentModel$ElemName;)I
Asciz	boxToInteger;
Asciz	(I)Ljava/lang/Integer;;
NameAndType	boxToInteger:(I)Ljava/lang/Integer;
Method	scala/runtime/BoxesRunTime.boxToInteger:(I)Ljava/lang/Integer;
Asciz	v1;
Asciz	Ljava/lang/Object;;
Asciz	v2;
Asciz	scala/xml/dtd/ElementValidator;
class	scala/xml/dtd/ElementValidator
Asciz	dfa;
Asciz	()Lscala/util/automata/DetWordAutom;;
NameAndType	dfa:()Lscala/util/automata/DetWordAutom;
Method	scala/xml/dtd/ElementValidator.dfa:()Lscala/util/automata/DetWordAutom;
Asciz	scala/util/automata/DetWordAutom;
class	scala/util/automata/DetWordAutom
Asciz	delta;
Asciz	()[Lscala/collection/Map;;
NameAndType	delta:()[Lscala/collection/Map;
Method	scala/util/automata/DetWordAutom.delta:()[Lscala/collection/Map;
Asciz	scala/xml/dtd/ElementValidator$$anonfun$check$6$$anonfun$apply$1;
class	scala/xml/dtd/ElementValidator$$anonfun$check$6$$anonfun$apply$1
Asciz	(Lscala/xml/dtd/ElementValidator$$anonfun$check$6;Lscala/xml/dtd/ContentModel$ElemName;)V;
NameAndType	"<init>":(Lscala/xml/dtd/ElementValidator$$anonfun$check$6;Lscala/xml/dtd/ContentModel$ElemName;)V
Method	scala/xml/dtd/ElementValidator$$anonfun$check$6$$anonfun$apply$1."<init>":(Lscala/xml/dtd/ElementValidator$$anonfun$check$6;Lscala/xml/dtd/ContentModel$ElemName;)V
Asciz	scala/collection/MapLike;
class	scala/collection/MapLike
Asciz	getOrElse;
Asciz	(Ljava/lang/Object;Lscala/Function0;)Ljava/lang/Object;;
NameAndType	getOrElse:(Ljava/lang/Object;Lscala/Function0;)Ljava/lang/Object;
InterfaceMethod	scala/collection/MapLike.getOrElse:(Ljava/lang/Object;Lscala/Function0;)Ljava/lang/Object;
Asciz	q;
Asciz	I;
Asciz	e$1;
Asciz	Lscala/xml/dtd/ContentModel$ElemName;;
Asciz	Scala;
Asciz	InnerClasses;
Asciz	scala/xml/dtd/ContentModel;
class	scala/xml/dtd/ContentModel
Asciz	ElemName;
Asciz	$anonfun$check$6;
Asciz	$anonfun$apply$1;
Asciz	java/io/Serializable;
class	java/io/Serializable

{
public static final long serialVersionUID;
  Signature: J

private final scala.xml.dtd.ElementValidator $outer;
  Signature: Lscala/xml/dtd/ElementValidator;

public static {};
  Signature: ()V
  Code:
   Stack=2, Locals=0, Args_size=0
	lconst_0
	putstatic	Field serialVersionUID:J
	return
  Labels:

public scala.xml.dtd.ElementValidator$$anonfun$check$6(scala.xml.dtd.ElementValidator);
  Signature: (Lscala/xml/dtd/ElementValidator;)V
  Code:
   Stack=2, Locals=2, Args_size=2
	aload_1
	ifnonnull	l1 // aload_0
	new	class java/lang/NullPointerException
	dup
	invokespecial	Method java/lang/NullPointerException."<init>":()V
	athrow
l1	aload_0
	aload_1
	putfield	Field $outer:Lscala/xml/dtd/ElementValidator;
	aload_0
	invokespecial	Method scala/runtime/AbstractFunction2."<init>":()V
	return
  Labels:
   	l1 = 12 // aload_0
  LocalVariableTable: 
   Start  Length  Slot  Name   Signature
   0      22      0    this       Lscala/xml/dtd/ElementValidator$$anonfun$check$6;
   0      22      1    $outer       Lscala/xml/dtd/ElementValidator;


public final java.lang.Object apply(java.lang.Object, java.lang.Object);
  Signature: (Ljava/lang/Object;Ljava/lang/Object;)Ljava/lang/Object;
  Code:
   Stack=3, Locals=4, Args_size=3
	aload_0
	aload_1
	invokestatic	Method scala/runtime/BoxesRunTime.unboxToInt:(Ljava/lang/Object;)I
	aload_2
	checkcast	class scala/xml/dtd/ContentModel$ElemName
	invokevirtual	Method apply:(ILscala/xml/dtd/ContentModel$ElemName;)I
	istore_3
	iload_3
	invokestatic	Method scala/runtime/BoxesRunTime.boxToInteger:(I)Ljava/lang/Integer;
	areturn
  Labels:
  LocalVariableTable: 
   Start  Length  Slot  Name   Signature
   0      18      0    this       Lscala/xml/dtd/ElementValidator$$anonfun$check$6;
   0      18      1    v1       Ljava/lang/Object;
   0      18      2    v2       Ljava/lang/Object;


public final int apply(int, scala.xml.dtd.ContentModel$ElemName);
  Signature: (ILscala/xml/dtd/ContentModel$ElemName;)I
  Code:
   Stack=6, Locals=3, Args_size=3
	aload_0
	getfield	Field $outer:Lscala/xml/dtd/ElementValidator;
	invokevirtual	Method scala/xml/dtd/ElementValidator.dfa:()Lscala/util/automata/DetWordAutom;
	invokevirtual	Method scala/util/automata/DetWordAutom.delta:()[Lscala/collection/Map;
	iload_1
	aaload
	aload_2
	new	class scala/xml/dtd/ElementValidator$$anonfun$check$6$$anonfun$apply$1
	dup
	aload_0
	aload_2
	invokespecial	Method scala/xml/dtd/ElementValidator$$anonfun$check$6$$anonfun$apply$1."<init>":(Lscala/xml/dtd/ElementValidator$$anonfun$check$6;Lscala/xml/dtd/ContentModel$ElemName;)V
	invokeinterface	InterfaceMethod scala/collection/MapLike.getOrElse:(Ljava/lang/Object;Lscala/Function0;)Ljava/lang/Object;
	invokestatic	Method scala/runtime/BoxesRunTime.unboxToInt:(Ljava/lang/Object;)I
	ireturn
  Labels:
  LocalVariableTable: 
   Start  Length  Slot  Name   Signature
   0      31      0    this       Lscala/xml/dtd/ElementValidator$$anonfun$check$6;
   0      31      1    q       I
   0      31      2    e$1       Lscala/xml/dtd/ContentModel$ElemName;


}

