Compiled from "ElementValidator.scala"
public final class scala.xml.dtd.ElementValidator$$anonfun$check$2 extends java.lang.Object implements scala.Function1,scala.ScalaObject,java.io.Serializable
  SourceFile: "ElementValidator.scala"
  Scala: length = 0x
   
  InnerClass: 
   public final #180= #9 of #110; //$anonfun$check$2=class scala/xml/dtd/ElementValidator$$anonfun$check$2 of class scala/xml/dtd/ElementValidator
  minor version: 0
  major version: 49
  Constant pool:
const #1 = Asciz	SourceFile;
const #2 = Asciz	ElementValidator.scala;
const #3 = Asciz	<clinit>;
const #4 = Asciz	()V;
const #5 = Asciz	Code;
const #6 = Asciz	serialVersionUID;
const #7 = Asciz	J;
const #8 = Asciz	scala/xml/dtd/ElementValidator$$anonfun$check$2;
const #9 = class	#8;	//  scala/xml/dtd/ElementValidator$$anonfun$check$2
const #10 = NameAndType	#6:#7;//  serialVersionUID:J
const #11 = Field	#9.#10;	//  scala/xml/dtd/ElementValidator$$anonfun$check$2.serialVersionUID:J
const #12 = Asciz	ok$1;
const #13 = Asciz	Lscala/runtime/ObjectRef;;
const #14 = Asciz	$outer;
const #15 = Asciz	Lscala/xml/dtd/ElementValidator;;
const #16 = Asciz	<init>;
const #17 = Asciz	(Lscala/xml/dtd/ElementValidator;Lscala/runtime/ObjectRef;)V;
const #18 = Asciz	LineNumberTable;
const #19 = Asciz	java/lang/NullPointerException;
const #20 = class	#19;	//  java/lang/NullPointerException
const #21 = NameAndType	#16:#4;//  "<init>":()V
const #22 = Method	#20.#21;	//  java/lang/NullPointerException."<init>":()V
const #23 = NameAndType	#14:#15;//  $outer:Lscala/xml/dtd/ElementValidator;
const #24 = Field	#9.#23;	//  scala/xml/dtd/ElementValidator$$anonfun$check$2.$outer:Lscala/xml/dtd/ElementValidator;
const #25 = NameAndType	#12:#13;//  ok$1:Lscala/runtime/ObjectRef;
const #26 = Field	#9.#25;	//  scala/xml/dtd/ElementValidator$$anonfun$check$2.ok$1:Lscala/runtime/ObjectRef;
const #27 = Asciz	java/lang/Object;
const #28 = class	#27;	//  java/lang/Object
const #29 = Method	#28.#21;	//  java/lang/Object."<init>":()V
const #30 = Asciz	scala/Function1$class;
const #31 = class	#30;	//  scala/Function1$class
const #32 = Asciz	$init$;
const #33 = Asciz	(Lscala/Function1;)V;
const #34 = NameAndType	#32:#33;//  $init$:(Lscala/Function1;)V
const #35 = Method	#31.#34;	//  scala/Function1$class.$init$:(Lscala/Function1;)V
const #36 = Asciz	this;
const #37 = Asciz	Lscala/xml/dtd/ElementValidator$$anonfun$check$2;;
const #38 = Asciz	LocalVariableTable;
const #39 = Asciz	gd5$1;
const #40 = Asciz	(Ljava/lang/String;Ljava/lang/String;I)Z;
const #41 = Asciz	scala/runtime/ObjectRef;
const #42 = class	#41;	//  scala/runtime/ObjectRef
const #43 = Asciz	elem;
const #44 = Asciz	Ljava/lang/Object;;
const #45 = NameAndType	#43:#44;//  elem:Ljava/lang/Object;
const #46 = Field	#42.#45;	//  scala/runtime/ObjectRef.elem:Ljava/lang/Object;
const #47 = Asciz	scala/collection/mutable/BitSet;
const #48 = class	#47;	//  scala/collection/mutable/BitSet
const #49 = Asciz	scala/runtime/BoxesRunTime;
const #50 = class	#49;	//  scala/runtime/BoxesRunTime
const #51 = Asciz	boxToInteger;
const #52 = Asciz	(I)Ljava/lang/Integer;;
const #53 = NameAndType	#51:#52;//  boxToInteger:(I)Ljava/lang/Integer;
const #54 = Method	#50.#53;	//  scala/runtime/BoxesRunTime.boxToInteger:(I)Ljava/lang/Integer;
const #55 = Asciz	scala/collection/SetLike;
const #56 = class	#55;	//  scala/collection/SetLike
const #57 = Asciz	apply;
const #58 = Asciz	(Ljava/lang/Object;)Z;
const #59 = NameAndType	#57:#58;//  apply:(Ljava/lang/Object;)Z
const #60 = InterfaceMethod	#56.#59;	//  scala/collection/SetLike.apply:(Ljava/lang/Object;)Z
const #61 = Asciz	(Ljava/lang/Object;)Ljava/lang/Object;;
const #62 = Asciz	scala/Tuple2;
const #63 = class	#62;	//  scala/Tuple2
const #64 = Asciz	(Lscala/Tuple2;)V;
const #65 = NameAndType	#57:#64;//  apply:(Lscala/Tuple2;)V
const #66 = Method	#9.#65;	//  scala/xml/dtd/ElementValidator$$anonfun$check$2.apply:(Lscala/Tuple2;)V
const #67 = Asciz	scala/runtime/BoxedUnit;
const #68 = class	#67;	//  scala/runtime/BoxedUnit
const #69 = Asciz	UNIT;
const #70 = Asciz	Lscala/runtime/BoxedUnit;;
const #71 = NameAndType	#69:#70;//  UNIT:Lscala/runtime/BoxedUnit;
const #72 = Field	#68.#71;	//  scala/runtime/BoxedUnit.UNIT:Lscala/runtime/BoxedUnit;
const #73 = Asciz	v1;
const #74 = Asciz	_1;
const #75 = Asciz	()Ljava/lang/Object;;
const #76 = NameAndType	#74:#75;//  _1:()Ljava/lang/Object;
const #77 = Method	#63.#76;	//  scala/Tuple2._1:()Ljava/lang/Object;
const #78 = Asciz	scala/xml/dtd/AttrDecl;
const #79 = class	#78;	//  scala/xml/dtd/AttrDecl
const #80 = Asciz	_2;
const #81 = NameAndType	#80:#75;//  _2:()Ljava/lang/Object;
const #82 = Method	#63.#81;	//  scala/Tuple2._2:()Ljava/lang/Object;
const #83 = Asciz	unboxToInt;
const #84 = Asciz	(Ljava/lang/Object;)I;
const #85 = NameAndType	#83:#84;//  unboxToInt:(Ljava/lang/Object;)I
const #86 = Method	#50.#85;	//  scala/runtime/BoxesRunTime.unboxToInt:(Ljava/lang/Object;)I
const #87 = Asciz	name;
const #88 = Asciz	()Ljava/lang/String;;
const #89 = NameAndType	#87:#88;//  name:()Ljava/lang/String;
const #90 = Method	#79.#89;	//  scala/xml/dtd/AttrDecl.name:()Ljava/lang/String;
const #91 = Asciz	tpe;
const #92 = NameAndType	#91:#88;//  tpe:()Ljava/lang/String;
const #93 = Method	#79.#92;	//  scala/xml/dtd/AttrDecl.tpe:()Ljava/lang/String;
const #94 = Asciz	scala/xml/dtd/REQUIRED$;
const #95 = class	#94;	//  scala/xml/dtd/REQUIRED$
const #96 = Asciz	MODULE$;
const #97 = Asciz	Lscala/xml/dtd/REQUIRED$;;
const #98 = NameAndType	#96:#97;//  MODULE$:Lscala/xml/dtd/REQUIRED$;
const #99 = Field	#95.#98;	//  scala/xml/dtd/REQUIRED$.MODULE$:Lscala/xml/dtd/REQUIRED$;
const #100 = Asciz	default;
const #101 = Asciz	()Lscala/xml/dtd/DefaultDecl;;
const #102 = NameAndType	#100:#101;//  default:()Lscala/xml/dtd/DefaultDecl;
const #103 = Method	#79.#102;	//  scala/xml/dtd/AttrDecl.default:()Lscala/xml/dtd/DefaultDecl;
const #104 = Asciz	equals;
const #105 = NameAndType	#104:#58;//  equals:(Ljava/lang/Object;)Z
const #106 = Method	#28.#105;	//  java/lang/Object.equals:(Ljava/lang/Object;)Z
const #107 = NameAndType	#39:#40;//  gd5$1:(Ljava/lang/String;Ljava/lang/String;I)Z
const #108 = Method	#9.#107;	//  scala/xml/dtd/ElementValidator$$anonfun$check$2.gd5$1:(Ljava/lang/String;Ljava/lang/String;I)Z
const #109 = Asciz	scala/xml/dtd/ElementValidator;
const #110 = class	#109;	//  scala/xml/dtd/ElementValidator
const #111 = Asciz	scala$xml$dtd$ElementValidator$$exc;
const #112 = Asciz	()Lscala/collection/immutable/List;;
const #113 = NameAndType	#111:#112;//  scala$xml$dtd$ElementValidator$$exc:()Lscala/collection/immutable/List;
const #114 = Method	#110.#113;	//  scala/xml/dtd/ElementValidator.scala$xml$dtd$ElementValidator$$exc:()Lscala/collection/immutable/List;
const #115 = Asciz	scala/xml/dtd/ValidationException;
const #116 = class	#115;	//  scala/xml/dtd/ValidationException
const #117 = Asciz	missing value for REQUIRED attribute %s of type %s;
const #118 = String	#117;	//  missing value for REQUIRED attribute %s of type %s
const #119 = Asciz	scala/collection/immutable/StringOps;
const #120 = class	#119;	//  scala/collection/immutable/StringOps
const #121 = Asciz	(Ljava/lang/String;)V;
const #122 = NameAndType	#16:#121;//  "<init>":(Ljava/lang/String;)V
const #123 = Method	#120.#122;	//  scala/collection/immutable/StringOps."<init>":(Ljava/lang/String;)V
const #124 = Asciz	scala/Predef$;
const #125 = class	#124;	//  scala/Predef$
const #126 = Asciz	Lscala/Predef$;;
const #127 = NameAndType	#96:#126;//  MODULE$:Lscala/Predef$;
const #128 = Field	#125.#127;	//  scala/Predef$.MODULE$:Lscala/Predef$;
const #129 = Asciz	genericWrapArray;
const #130 = Asciz	(Ljava/lang/Object;)Lscala/collection/mutable/WrappedArray;;
const #131 = NameAndType	#129:#130;//  genericWrapArray:(Ljava/lang/Object;)Lscala/collection/mutable/WrappedArray;
const #132 = Method	#125.#131;	//  scala/Predef$.genericWrapArray:(Ljava/lang/Object;)Lscala/collection/mutable/WrappedArray;
const #133 = Asciz	scala/collection/immutable/StringLike;
const #134 = class	#133;	//  scala/collection/immutable/StringLike
const #135 = Asciz	format;
const #136 = Asciz	(Lscala/collection/Seq;)Ljava/lang/String;;
const #137 = NameAndType	#135:#136;//  format:(Lscala/collection/Seq;)Ljava/lang/String;
const #138 = InterfaceMethod	#134.#137;	//  scala/collection/immutable/StringLike.format:(Lscala/collection/Seq;)Ljava/lang/String;
const #139 = Method	#116.#122;	//  scala/xml/dtd/ValidationException."<init>":(Ljava/lang/String;)V
const #140 = Asciz	scala/collection/immutable/List;
const #141 = class	#140;	//  scala/collection/immutable/List
const #142 = Asciz	$colon$colon;
const #143 = Asciz	(Ljava/lang/Object;)Lscala/collection/immutable/List;;
const #144 = NameAndType	#142:#143;//  $colon$colon:(Ljava/lang/Object;)Lscala/collection/immutable/List;
const #145 = Method	#141.#144;	//  scala/collection/immutable/List.$colon$colon:(Ljava/lang/Object;)Lscala/collection/immutable/List;
const #146 = Asciz	scala$xml$dtd$ElementValidator$$exc_$eq;
const #147 = Asciz	(Lscala/collection/immutable/List;)V;
const #148 = NameAndType	#146:#147;//  scala$xml$dtd$ElementValidator$$exc_$eq:(Lscala/collection/immutable/List;)V
const #149 = Method	#110.#148;	//  scala/xml/dtd/ElementValidator.scala$xml$dtd$ElementValidator$$exc_$eq:(Lscala/collection/immutable/List;)V
const #150 = Asciz	scala/MatchError;
const #151 = class	#150;	//  scala/MatchError
const #152 = Asciz	toString;
const #153 = NameAndType	#152:#88;//  toString:()Ljava/lang/String;
const #154 = Method	#63.#153;	//  scala/Tuple2.toString:()Ljava/lang/String;
const #155 = Method	#151.#122;	//  scala/MatchError."<init>":(Ljava/lang/String;)V
const #156 = Asciz	temp31;
const #157 = Asciz	Lscala/xml/dtd/AttrDecl;;
const #158 = Asciz	temp32;
const #159 = Asciz	I;
const #160 = Asciz	temp33;
const #161 = Asciz	Ljava/lang/String;;
const #162 = Asciz	temp34;
const #163 = Asciz	(Lscala/Tuple2<Lscala/xml/dtd/AttrDecl;Ljava/lang/Integer;>;)V;
const #164 = Asciz	Signature;
const #165 = Asciz	andThen;
const #166 = Asciz	(Lscala/Function1;)Lscala/Function1;;
const #167 = Asciz	(Lscala/Function1;Lscala/Function1;)Lscala/Function1;;
const #168 = NameAndType	#165:#167;//  andThen:(Lscala/Function1;Lscala/Function1;)Lscala/Function1;
const #169 = Method	#31.#168;	//  scala/Function1$class.andThen:(Lscala/Function1;Lscala/Function1;)Lscala/Function1;
const #170 = Asciz	g;
const #171 = Asciz	Lscala/Function1;;
const #172 = Asciz	compose;
const #173 = NameAndType	#172:#167;//  compose:(Lscala/Function1;Lscala/Function1;)Lscala/Function1;
const #174 = Method	#31.#173;	//  scala/Function1$class.compose:(Lscala/Function1;Lscala/Function1;)Lscala/Function1;
const #175 = Asciz	(Lscala/Function1;)Ljava/lang/String;;
const #176 = NameAndType	#152:#175;//  toString:(Lscala/Function1;)Ljava/lang/String;
const #177 = Method	#31.#176;	//  scala/Function1$class.toString:(Lscala/Function1;)Ljava/lang/String;
const #178 = Asciz	Scala;
const #179 = Asciz	InnerClasses;
const #180 = Asciz	$anonfun$check$2;
const #181 = Asciz	scala/Function1;
const #182 = class	#181;	//  scala/Function1
const #183 = Asciz	scala/ScalaObject;
const #184 = class	#183;	//  scala/ScalaObject
const #185 = Asciz	java/io/Serializable;
const #186 = class	#185;	//  java/io/Serializable

{
public static final long serialVersionUID;

public static {};
  Code:
   Stack=2, Locals=0, Args_size=0
   0:	lconst_0
   1:	putstatic	#11; //Field serialVersionUID:J
   4:	return

public scala.xml.dtd.ElementValidator$$anonfun$check$2(scala.xml.dtd.ElementValidator, scala.runtime.ObjectRef);
  Code:
   Stack=2, Locals=3, Args_size=3
   0:	aload_1
   1:	ifnonnull	12
   4:	new	#20; //class java/lang/NullPointerException
   7:	dup
   8:	invokespecial	#22; //Method java/lang/NullPointerException."<init>":()V
   11:	athrow
   12:	aload_0
   13:	aload_1
   14:	putfield	#24; //Field $outer:Lscala/xml/dtd/ElementValidator;
   17:	aload_0
   18:	aload_2
   19:	putfield	#26; //Field ok$1:Lscala/runtime/ObjectRef;
   22:	aload_0
   23:	invokespecial	#29; //Method java/lang/Object."<init>":()V
   26:	aload_0
   27:	invokestatic	#35; //Method scala/Function1$class.$init$:(Lscala/Function1;)V
   30:	return
  LineNumberTable: 
   line 89: 0

  LocalVariableTable: 
   Start  Length  Slot  Name   Signature
   0      31      0    this       Lscala/xml/dtd/ElementValidator$$anonfun$check$2;
   0      31      1    $outer       Lscala/xml/dtd/ElementValidator;


public final java.lang.Object apply(java.lang.Object);
  Code:
   Stack=2, Locals=3, Args_size=2
   0:	aload_0
   1:	getfield	#24; //Field $outer:Lscala/xml/dtd/ElementValidator;
   4:	astore_2
   5:	aload_0
   6:	aload_1
   7:	checkcast	#63; //class scala/Tuple2
   10:	invokevirtual	#66; //Method apply:(Lscala/Tuple2;)V
   13:	getstatic	#72; //Field scala/runtime/BoxedUnit.UNIT:Lscala/runtime/BoxedUnit;
   16:	areturn
  LineNumberTable: 
   line 89: 0

  LocalVariableTable: 
   Start  Length  Slot  Name   Signature
   0      17      0    this       Lscala/xml/dtd/ElementValidator$$anonfun$check$2;
   5      12      1    v1       Ljava/lang/Object;


public final void apply(scala.Tuple2);
  Code:
   Stack=10, Locals=9, Args_size=2
   0:	aload_0
   1:	getfield	#24; //Field $outer:Lscala/xml/dtd/ElementValidator;
   4:	astore	8
   6:	aload_1
   7:	ifnull	196
   10:	aload_1
   11:	invokevirtual	#77; //Method scala/Tuple2._1:()Ljava/lang/Object;
   14:	checkcast	#79; //class scala/xml/dtd/AttrDecl
   17:	astore_2
   18:	aload_1
   19:	invokevirtual	#82; //Method scala/Tuple2._2:()Ljava/lang/Object;
   22:	invokestatic	#86; //Method scala/runtime/BoxesRunTime.unboxToInt:(Ljava/lang/Object;)I
   25:	istore	4
   27:	aload_2
   28:	ifnull	180
   31:	aload_2
   32:	invokevirtual	#90; //Method scala/xml/dtd/AttrDecl.name:()Ljava/lang/String;
   35:	astore	6
   37:	aload_2
   38:	invokevirtual	#93; //Method scala/xml/dtd/AttrDecl.tpe:()Ljava/lang/String;
   41:	astore	7
   43:	getstatic	#99; //Field scala/xml/dtd/REQUIRED$.MODULE$:Lscala/xml/dtd/REQUIRED$;
   46:	aload_2
   47:	invokevirtual	#103; //Method scala/xml/dtd/AttrDecl.default:()Lscala/xml/dtd/DefaultDecl;
   50:	astore_3
   51:	dup
   52:	ifnonnull	63
   55:	pop
   56:	aload_3
   57:	ifnull	70
   60:	goto	164
   63:	aload_3
   64:	invokevirtual	#106; //Method java/lang/Object.equals:(Ljava/lang/Object;)Z
   67:	ifeq	164
   70:	aload_0
   71:	aload	6
   73:	aload	7
   75:	iload	4
   77:	invokespecial	#108; //Method gd5$1:(Ljava/lang/String;Ljava/lang/String;I)Z
   80:	ifeq	148
   83:	aload_0
   84:	getfield	#24; //Field $outer:Lscala/xml/dtd/ElementValidator;
   87:	aload_0
   88:	getfield	#24; //Field $outer:Lscala/xml/dtd/ElementValidator;
   91:	invokevirtual	#114; //Method scala/xml/dtd/ElementValidator.scala$xml$dtd$ElementValidator$$exc:()Lscala/collection/immutable/List;
   94:	new	#116; //class scala/xml/dtd/ValidationException
   97:	dup
   98:	ldc	#118; //String missing value for REQUIRED attribute %s of type %s
   100:	astore	5
   102:	new	#120; //class scala/collection/immutable/StringOps
   105:	dup
   106:	aload	5
   108:	invokespecial	#123; //Method scala/collection/immutable/StringOps."<init>":(Ljava/lang/String;)V
   111:	getstatic	#128; //Field scala/Predef$.MODULE$:Lscala/Predef$;
   114:	iconst_2
   115:	anewarray	#28; //class java/lang/Object
   118:	dup
   119:	iconst_0
   120:	aload	6
   122:	aastore
   123:	dup
   124:	iconst_1
   125:	aload	7
   127:	aastore
   128:	invokevirtual	#132; //Method scala/Predef$.genericWrapArray:(Ljava/lang/Object;)Lscala/collection/mutable/WrappedArray;
   131:	invokeinterface	#138,  2; //InterfaceMethod scala/collection/immutable/StringLike.format:(Lscala/collection/Seq;)Ljava/lang/String;
   136:	invokespecial	#139; //Method scala/xml/dtd/ValidationException."<init>":(Ljava/lang/String;)V
   139:	invokevirtual	#145; //Method scala/collection/immutable/List.$colon$colon:(Ljava/lang/Object;)Lscala/collection/immutable/List;
   142:	invokevirtual	#149; //Method scala/xml/dtd/ElementValidator.scala$xml$dtd$ElementValidator$$exc_$eq:(Lscala/collection/immutable/List;)V
   145:	goto	200
   148:	iconst_1
   149:	ifne	200
   152:	new	#151; //class scala/MatchError
   155:	dup
   156:	aload_1
   157:	invokevirtual	#154; //Method scala/Tuple2.toString:()Ljava/lang/String;
   160:	invokespecial	#155; //Method scala/MatchError."<init>":(Ljava/lang/String;)V
   163:	athrow
   164:	iconst_1
   165:	ifne	200
   168:	new	#151; //class scala/MatchError
   171:	dup
   172:	aload_1
   173:	invokevirtual	#154; //Method scala/Tuple2.toString:()Ljava/lang/String;
   176:	invokespecial	#155; //Method scala/MatchError."<init>":(Ljava/lang/String;)V
   179:	athrow
   180:	iconst_1
   181:	ifne	200
   184:	new	#151; //class scala/MatchError
   187:	dup
   188:	aload_1
   189:	invokevirtual	#154; //Method scala/Tuple2.toString:()Ljava/lang/String;
   192:	invokespecial	#155; //Method scala/MatchError."<init>":(Ljava/lang/String;)V
   195:	athrow
   196:	iconst_1
   197:	ifeq	201
   200:	return
   201:	new	#151; //class scala/MatchError
   204:	dup
   205:	aload_1
   206:	invokevirtual	#154; //Method scala/Tuple2.toString:()Ljava/lang/String;
   209:	invokespecial	#155; //Method scala/MatchError."<init>":(Ljava/lang/String;)V
   212:	athrow
  LineNumberTable: 
   line 89: 0
   line 90: 83
   line 21: 148
   line 89: 152
   line 21: 164
   line 89: 168
   line 21: 180
   line 89: 184
   line 21: 196
   line 89: 200

  LocalVariableTable: 
   Start  Length  Slot  Name   Signature
   0      213      0    this       Lscala/xml/dtd/ElementValidator$$anonfun$check$2;
   18      178      2    temp31       Lscala/xml/dtd/AttrDecl;
   27      169      4    temp32       I
   37      143      6    temp33       Ljava/lang/String;
   43      137      7    temp34       Ljava/lang/String;

  Signature: length = 0x2
   00 FFFFFFA3 

public scala.Function1 andThen(scala.Function1);
  Code:
   Stack=2, Locals=2, Args_size=2
   0:	aload_0
   1:	aload_1
   2:	invokestatic	#169; //Method scala/Function1$class.andThen:(Lscala/Function1;Lscala/Function1;)Lscala/Function1;
   5:	areturn
  LineNumberTable: 
   line 89: 0

  LocalVariableTable: 
   Start  Length  Slot  Name   Signature
   0      6      0    this       Lscala/xml/dtd/ElementValidator$$anonfun$check$2;
   0      6      1    g       Lscala/Function1;


public scala.Function1 compose(scala.Function1);
  Code:
   Stack=2, Locals=2, Args_size=2
   0:	aload_0
   1:	aload_1
   2:	invokestatic	#174; //Method scala/Function1$class.compose:(Lscala/Function1;Lscala/Function1;)Lscala/Function1;
   5:	areturn
  LineNumberTable: 
   line 89: 0

  LocalVariableTable: 
   Start  Length  Slot  Name   Signature
   0      6      0    this       Lscala/xml/dtd/ElementValidator$$anonfun$check$2;
   0      6      1    g       Lscala/Function1;


public java.lang.String toString();
  Code:
   Stack=1, Locals=1, Args_size=1
   0:	aload_0
   1:	invokestatic	#177; //Method scala/Function1$class.toString:(Lscala/Function1;)Ljava/lang/String;
   4:	areturn
  LineNumberTable: 
   line 89: 0


}

