Compiled from "ElementValidator.scala"
public final class scala.xml.dtd.ElementValidator$$anonfun$check$1 extends scala.runtime.AbstractFunction1 implements java.io.Serializable
  SourceFile: "ElementValidator.scala"
  Scala: length = 0x
   
  InnerClass: 
   public final $anonfun$check$1=class scala/xml/dtd/ElementValidator$$anonfun$check$1 of class scala/xml/dtd/ElementValidator
   public GenericCanBuildFrom=class scala/collection/generic/TraversableFactory$GenericCanBuildFrom of class scala/collection/generic/TraversableFactory
   public final $anonfun$find$1$1=class scala/xml/dtd/ElementValidator$$anonfun$check$1$$anonfun$find$1$1 of class scala/xml/dtd/ElementValidator$$anonfun$check$1
  minor version: 0
  major version: 49
  Constant pool:
Asciz	SourceFile;
Asciz	ElementValidator.scala;
Asciz	<clinit>;
Asciz	()V;
Asciz	Code;
Asciz	serialVersionUID;
Asciz	J;
Asciz	scala/xml/dtd/ElementValidator$$anonfun$check$1;
class	scala/xml/dtd/ElementValidator$$anonfun$check$1
NameAndType	serialVersionUID:J
Field	scala/xml/dtd/ElementValidator$$anonfun$check$1.serialVersionUID:J
Asciz	ok$1;
Asciz	Lscala/runtime/ObjectRef;;
Asciz	$outer;
Asciz	Lscala/xml/dtd/ElementValidator;;
Asciz	<init>;
Asciz	(Lscala/xml/dtd/ElementValidator;Lscala/runtime/ObjectRef;)V;
Asciz	LineNumberTable;
Asciz	java/lang/NullPointerException;
class	java/lang/NullPointerException
NameAndType	"<init>":()V
Method	java/lang/NullPointerException."<init>":()V
NameAndType	$outer:Lscala/xml/dtd/ElementValidator;
Field	scala/xml/dtd/ElementValidator$$anonfun$check$1.$outer:Lscala/xml/dtd/ElementValidator;
NameAndType	ok$1:Lscala/runtime/ObjectRef;
Field	scala/xml/dtd/ElementValidator$$anonfun$check$1.ok$1:Lscala/runtime/ObjectRef;
Asciz	scala/runtime/AbstractFunction1;
class	scala/runtime/AbstractFunction1
Method	scala/runtime/AbstractFunction1."<init>":()V
Asciz	this;
Asciz	Lscala/xml/dtd/ElementValidator$$anonfun$check$1;;
Asciz	LocalVariableTable;
Asciz	gd4$1;
Asciz	(Ljava/lang/String;Ljava/lang/String;Lscala/xml/MetaData;)Z;
Asciz	attrStr$1;
Asciz	(Lscala/xml/MetaData;)Ljava/lang/String;;
NameAndType	attrStr$1:(Lscala/xml/MetaData;)Ljava/lang/String;
Method	scala/xml/dtd/ElementValidator$$anonfun$check$1.attrStr$1:(Lscala/xml/MetaData;)Ljava/lang/String;
Asciz	java/lang/Object;
class	java/lang/Object
Asciz	equals;
Asciz	(Ljava/lang/Object;)Z;
NameAndType	equals:(Ljava/lang/Object;)Z
Method	java/lang/Object.equals:(Ljava/lang/Object;)Z
Asciz	find$1;
Asciz	(Ljava/lang/String;)Lscala/Option;;
Method	java/lang/Object."<init>":()V
Asciz	scala/xml/dtd/ElementValidator;
class	scala/xml/dtd/ElementValidator
Asciz	adecls;
Asciz	()Lscala/collection/immutable/List;;
NameAndType	adecls:()Lscala/collection/immutable/List;
Method	scala/xml/dtd/ElementValidator.adecls:()Lscala/collection/immutable/List;
Asciz	scala/collection/immutable/List$;
class	scala/collection/immutable/List$
Asciz	MODULE$;
Asciz	Lscala/collection/immutable/List$;;
NameAndType	MODULE$:Lscala/collection/immutable/List$;
Field	scala/collection/immutable/List$.MODULE$:Lscala/collection/immutable/List$;
Asciz	scala/collection/generic/TraversableFactory$GenericCanBuildFrom;
class	scala/collection/generic/TraversableFactory$GenericCanBuildFrom
Asciz	(Lscala/collection/generic/TraversableFactory;)V;
NameAndType	"<init>":(Lscala/collection/generic/TraversableFactory;)V
Method	scala/collection/generic/TraversableFactory$GenericCanBuildFrom."<init>":(Lscala/collection/generic/TraversableFactory;)V
Asciz	scala/collection/IterableLike;
class	scala/collection/IterableLike
Asciz	zipWithIndex;
Asciz	(Lscala/collection/generic/CanBuildFrom;)Ljava/lang/Object;;
NameAndType	zipWithIndex:(Lscala/collection/generic/CanBuildFrom;)Ljava/lang/Object;
InterfaceMethod	scala/collection/IterableLike.zipWithIndex:(Lscala/collection/generic/CanBuildFrom;)Ljava/lang/Object;
Asciz	scala/collection/LinearSeqLike;
class	scala/collection/LinearSeqLike
Asciz	scala/xml/dtd/ElementValidator$$anonfun$check$1$$anonfun$find$1$1;
class	scala/xml/dtd/ElementValidator$$anonfun$check$1$$anonfun$find$1$1
Asciz	(Lscala/xml/dtd/ElementValidator$$anonfun$check$1;Ljava/lang/String;Ljava/lang/Object;)V;
NameAndType	"<init>":(Lscala/xml/dtd/ElementValidator$$anonfun$check$1;Ljava/lang/String;Ljava/lang/Object;)V
Method	scala/xml/dtd/ElementValidator$$anonfun$check$1$$anonfun$find$1$1."<init>":(Lscala/xml/dtd/ElementValidator$$anonfun$check$1;Ljava/lang/String;Ljava/lang/Object;)V
Asciz	find;
Asciz	(Lscala/Function1;)Lscala/Option;;
NameAndType	find:(Lscala/Function1;)Lscala/Option;
InterfaceMethod	scala/collection/LinearSeqLike.find:(Lscala/Function1;)Lscala/Option;
Asciz	scala/None$;
class	scala/None$
Asciz	Lscala/None$;;
NameAndType	MODULE$:Lscala/None$;
Field	scala/None$.MODULE$:Lscala/None$;
Asciz	scala/runtime/NonLocalReturnException;
class	scala/runtime/NonLocalReturnException
Asciz	key;
Asciz	()Ljava/lang/Object;;
NameAndType	key:()Ljava/lang/Object;
Method	scala/runtime/NonLocalReturnException.key:()Ljava/lang/Object;
Asciz	value;
NameAndType	value:()Ljava/lang/Object;
Method	scala/runtime/NonLocalReturnException.value:()Ljava/lang/Object;
Asciz	scala/Option;
class	scala/Option
Asciz	Key$1;
Asciz	Ljava/lang/String;;
Asciz	$inlThis0;
Asciz	Ljava/lang/Object;;
Asciz	exceptionResult1;
Asciz	Lscala/Option;;
Asciz	scala/xml/MetaData;
class	scala/xml/MetaData
Asciz	()Lscala/collection/Seq;;
NameAndType	value:()Lscala/collection/Seq;
Method	scala/xml/MetaData.value:()Lscala/collection/Seq;
Asciz	scala/collection/SeqLike;
class	scala/collection/SeqLike
Asciz	toString;
Asciz	()Ljava/lang/String;;
NameAndType	toString:()Ljava/lang/String;
InterfaceMethod	scala/collection/SeqLike.toString:()Ljava/lang/String;
Asciz	apply;
Asciz	(Ljava/lang/Object;)Ljava/lang/Object;;
Asciz	(Lscala/xml/MetaData;)V;
NameAndType	apply:(Lscala/xml/MetaData;)V
Method	scala/xml/dtd/ElementValidator$$anonfun$check$1.apply:(Lscala/xml/MetaData;)V
Asciz	scala/runtime/BoxedUnit;
class	scala/runtime/BoxedUnit
Asciz	UNIT;
Asciz	Lscala/runtime/BoxedUnit;;
NameAndType	UNIT:Lscala/runtime/BoxedUnit;
Field	scala/runtime/BoxedUnit.UNIT:Lscala/runtime/BoxedUnit;
Asciz	v1;
NameAndType	key:()Ljava/lang/String;
Method	scala/xml/MetaData.key:()Ljava/lang/String;
NameAndType	find$1:(Ljava/lang/String;)Lscala/Option;
Method	scala/xml/dtd/ElementValidator$$anonfun$check$1.find$1:(Ljava/lang/String;)Lscala/Option;
Asciz	scala$xml$dtd$ElementValidator$$exc;
NameAndType	scala$xml$dtd$ElementValidator$$exc:()Lscala/collection/immutable/List;
Method	scala/xml/dtd/ElementValidator.scala$xml$dtd$ElementValidator$$exc:()Lscala/collection/immutable/List;
Asciz	scala/xml/dtd/ValidationException;
class	scala/xml/dtd/ValidationException
Asciz	scala/collection/mutable/StringBuilder;
class	scala/collection/mutable/StringBuilder
Method	scala/collection/mutable/StringBuilder."<init>":()V
Asciz	attribute ;
String	attribute 
Asciz	append;
Asciz	(Ljava/lang/Object;)Lscala/collection/mutable/StringBuilder;;
NameAndType	append:(Ljava/lang/Object;)Lscala/collection/mutable/StringBuilder;
Method	scala/collection/mutable/StringBuilder.append:(Ljava/lang/Object;)Lscala/collection/mutable/StringBuilder;
Asciz	 not allowed here;
String	 not allowed here
Method	scala/collection/mutable/StringBuilder.toString:()Ljava/lang/String;
Asciz	(Ljava/lang/String;)V;
NameAndType	"<init>":(Ljava/lang/String;)V
Method	scala/xml/dtd/ValidationException."<init>":(Ljava/lang/String;)V
Asciz	scala/collection/immutable/List;
class	scala/collection/immutable/List
Asciz	$colon$colon;
Asciz	(Ljava/lang/Object;)Lscala/collection/immutable/List;;
NameAndType	$colon$colon:(Ljava/lang/Object;)Lscala/collection/immutable/List;
Method	scala/collection/immutable/List.$colon$colon:(Ljava/lang/Object;)Lscala/collection/immutable/List;
Asciz	scala$xml$dtd$ElementValidator$$exc_$eq;
Asciz	(Lscala/collection/immutable/List;)V;
NameAndType	scala$xml$dtd$ElementValidator$$exc_$eq:(Lscala/collection/immutable/List;)V
Method	scala/xml/dtd/ElementValidator.scala$xml$dtd$ElementValidator$$exc_$eq:(Lscala/collection/immutable/List;)V
Asciz	scala/Some;
class	scala/Some
Asciz	x;
NameAndType	x:Ljava/lang/Object;
Field	scala/Some.x:Ljava/lang/Object;
Asciz	scala/xml/dtd/AttrDecl;
class	scala/xml/dtd/AttrDecl
Asciz	tpe;
NameAndType	tpe:()Ljava/lang/String;
Method	scala/xml/dtd/AttrDecl.tpe:()Ljava/lang/String;
Asciz	default;
Asciz	()Lscala/xml/dtd/DefaultDecl;;
NameAndType	default:()Lscala/xml/dtd/DefaultDecl;
Method	scala/xml/dtd/AttrDecl.default:()Lscala/xml/dtd/DefaultDecl;
Asciz	scala/xml/dtd/DEFAULT;
class	scala/xml/dtd/DEFAULT
Asciz	attValue;
NameAndType	attValue:()Ljava/lang/String;
Method	scala/xml/dtd/DEFAULT.attValue:()Ljava/lang/String;
Asciz	fixed;
Asciz	()Z;
NameAndType	fixed:()Z
Method	scala/xml/dtd/DEFAULT.fixed:()Z
NameAndType	gd4$1:(Ljava/lang/String;Ljava/lang/String;Lscala/xml/MetaData;)Z
Method	scala/xml/dtd/ElementValidator$$anonfun$check$1.gd4$1:(Ljava/lang/String;Ljava/lang/String;Lscala/xml/MetaData;)Z
Asciz	value of attribute ;
String	value of attribute 
Asciz	 FIXED to \";
String	 FIXED to \"
Asciz	\", but document tries \";
String	\", but document tries \"
Asciz	\";
String	\"
Asciz	attr$1;
Asciz	Lscala/xml/MetaData;;
Asciz	temp19;
Asciz	temp21;
Asciz	Lscala/Some;;
Asciz	temp22;
Asciz	Lscala/xml/dtd/AttrDecl;;
Asciz	temp25;
Asciz	Lscala/xml/dtd/DefaultDecl;;
Asciz	temp26;
Asciz	Lscala/xml/dtd/DEFAULT;;
Asciz	temp24;
Asciz	temp28;
Asciz	Scala;
Asciz	InnerClasses;
Asciz	$anonfun$check$1;
Asciz	scala/collection/generic/TraversableFactory;
class	scala/collection/generic/TraversableFactory
Asciz	GenericCanBuildFrom;
Asciz	$anonfun$find$1$1;
Asciz	java/io/Serializable;
class	java/io/Serializable

{
public static final long serialVersionUID;
  Signature: J

public final scala.runtime.ObjectRef ok$1;
  Signature: Lscala/runtime/ObjectRef;

private final scala.xml.dtd.ElementValidator $outer;
  Signature: Lscala/xml/dtd/ElementValidator;

public static {};
  Signature: ()V
  Code:
   Stack=2, Locals=0, Args_size=0
	lconst_0
	putstatic	Field serialVersionUID:J
	return
  Labels:

public scala.xml.dtd.ElementValidator$$anonfun$check$1(scala.xml.dtd.ElementValidator, scala.runtime.ObjectRef);
  Signature: (Lscala/xml/dtd/ElementValidator;Lscala/runtime/ObjectRef;)V
  Code:
   Stack=2, Locals=3, Args_size=3
	aload_1
	ifnonnull	l1 // aload_0
	new	class java/lang/NullPointerException
	dup
	invokespecial	Method java/lang/NullPointerException."<init>":()V
	athrow
l1	aload_0
	aload_1
	putfield	Field $outer:Lscala/xml/dtd/ElementValidator;
	aload_0
	aload_2
	putfield	Field ok$1:Lscala/runtime/ObjectRef;
	aload_0
	invokespecial	Method scala/runtime/AbstractFunction1."<init>":()V
	return
  Labels:
   	l1 = 12 // aload_0
  LocalVariableTable: 
   Start  Length  Slot  Name   Signature
   0      27      0    this       Lscala/xml/dtd/ElementValidator$$anonfun$check$1;
   0      27      1    $outer       Lscala/xml/dtd/ElementValidator;


private final boolean gd4$1(java.lang.String, java.lang.String, scala.xml.MetaData);
  Signature: (Ljava/lang/String;Ljava/lang/String;Lscala/xml/MetaData;)Z
  Code:
   Stack=2, Locals=4, Args_size=4
	aload_0
	aload_3
	invokespecial	Method attrStr$1:(Lscala/xml/MetaData;)Ljava/lang/String;
	dup
	ifnonnull	l1 // aload_2
	pop
	aload_2
	ifnull	l2 // iconst_0
	goto	l3 // iconst_1
l1	aload_2
	invokevirtual	Method java/lang/Object.equals:(Ljava/lang/Object;)Z
	ifeq	l3 // iconst_1
l2	iconst_0
	goto	l4 // ireturn
l3	iconst_1
l4	ireturn
  Labels:
   	l1 = 17 // aload_2
   	l2 = 24 // iconst_0
   	l3 = 28 // iconst_1
   	l4 = 29 // ireturn

private final scala.Option find$1(java.lang.String);
  Signature: (Ljava/lang/String;)Lscala/Option;
  Code:
   Stack=6, Locals=6, Args_size=2
	new	class java/lang/Object
	dup
	invokespecial	Method java/lang/Object."<init>":()V
	astore_3
	aload_0
	getfield	Field $outer:Lscala/xml/dtd/ElementValidator;
	invokevirtual	Method scala/xml/dtd/ElementValidator.adecls:()Lscala/collection/immutable/List;
	getstatic	Field scala/collection/immutable/List$.MODULE$:Lscala/collection/immutable/List$;
	astore_2
	new	class scala/collection/generic/TraversableFactory$GenericCanBuildFrom
	dup
	aload_2
	invokespecial	Method scala/collection/generic/TraversableFactory$GenericCanBuildFrom."<init>":(Lscala/collection/generic/TraversableFactory;)V
	invokeinterface	InterfaceMethod scala/collection/IterableLike.zipWithIndex:(Lscala/collection/generic/CanBuildFrom;)Ljava/lang/Object;
	checkcast	class scala/collection/LinearSeqLike
	new	class scala/xml/dtd/ElementValidator$$anonfun$check$1$$anonfun$find$1$1
	dup
	aload_0
	aload_1
	aload_3
	invokespecial	Method scala/xml/dtd/ElementValidator$$anonfun$check$1$$anonfun$find$1$1."<init>":(Lscala/xml/dtd/ElementValidator$$anonfun$check$1;Ljava/lang/String;Ljava/lang/Object;)V
	invokeinterface	InterfaceMethod scala/collection/LinearSeqLike.find:(Lscala/Function1;)Lscala/Option;
	pop
	getstatic	Field scala/None$.MODULE$:Lscala/None$;
	astore	4
	goto	l1 // aload
	astore	5
	aload	5
	invokevirtual	Method scala/runtime/NonLocalReturnException.key:()Ljava/lang/Object;
	aload_3
	if_acmpne	l2 // aload
	aload	5
	invokevirtual	Method scala/runtime/NonLocalReturnException.value:()Ljava/lang/Object;
	checkcast	class scala/Option
	astore	4
l1	aload	4
	areturn
l2	aload	5
	athrow
  Labels:
   	l1 = 80 // aload
   	l2 = 83 // aload
  Exception table:
   from   to  target type
     8    59    59   Class scala/runtime/NonLocalReturnException

  LocalVariableTable: 
   Start  Length  Slot  Name   Signature
   0      86      0    this       Lscala/xml/dtd/ElementValidator$$anonfun$check$1;
   0      86      1    Key$1       Ljava/lang/String;
   19      40      2    $inlThis0       Ljava/lang/Object;
   8      74      4    exceptionResult1       Lscala/Option;
   83      3      4    exceptionResult1       Lscala/Option;


private final java.lang.String attrStr$1(scala.xml.MetaData);
  Signature: (Lscala/xml/MetaData;)Ljava/lang/String;
  Code:
   Stack=1, Locals=2, Args_size=2
	aload_1
	invokevirtual	Method scala/xml/MetaData.value:()Lscala/collection/Seq;
	invokeinterface	InterfaceMethod scala/collection/SeqLike.toString:()Ljava/lang/String;
	areturn
  Labels:

public final java.lang.Object apply(java.lang.Object);
  Signature: (Ljava/lang/Object;)Ljava/lang/Object;
  Code:
   Stack=2, Locals=2, Args_size=2
	aload_0
	aload_1
	checkcast	class scala/xml/MetaData
	invokevirtual	Method apply:(Lscala/xml/MetaData;)V
	getstatic	Field scala/runtime/BoxedUnit.UNIT:Lscala/runtime/BoxedUnit;
	areturn
  Labels:
  LocalVariableTable: 
   Start  Length  Slot  Name   Signature
   0      12      0    this       Lscala/xml/dtd/ElementValidator$$anonfun$check$1;
   0      12      1    v1       Ljava/lang/Object;


public final void apply(scala.xml.MetaData);
  Signature: (Lscala/xml/MetaData;)V
  Code:
   Stack=6, Locals=12, Args_size=2
	aload_0
	aload_1
	invokevirtual	Method scala/xml/MetaData.key:()Ljava/lang/String;
	invokespecial	Method find$1:(Ljava/lang/String;)Lscala/Option;
	astore_3
	getstatic	Field scala/None$.MODULE$:Lscala/None$;
	dup
	ifnonnull	l1 // aload_3
	pop
	aload_3
	ifnull	l2 // aload_0
	goto	l3 // aload_3
l1	aload_3
	invokevirtual	Method java/lang/Object.equals:(Ljava/lang/Object;)Z
	ifeq	l3 // aload_3
l2	aload_0
	getfield	Field $outer:Lscala/xml/dtd/ElementValidator;
	aload_0
	getfield	Field $outer:Lscala/xml/dtd/ElementValidator;
	invokevirtual	Method scala/xml/dtd/ElementValidator.scala$xml$dtd$ElementValidator$$exc:()Lscala/collection/immutable/List;
	aload_1
	invokevirtual	Method scala/xml/MetaData.key:()Ljava/lang/String;
	astore_2
	new	class scala/xml/dtd/ValidationException
	dup
	new	class scala/collection/mutable/StringBuilder
	dup
	invokespecial	Method scala/collection/mutable/StringBuilder."<init>":()V
	ldc	String attribute 
	invokevirtual	Method scala/collection/mutable/StringBuilder.append:(Ljava/lang/Object;)Lscala/collection/mutable/StringBuilder;
	aload_2
	invokevirtual	Method scala/collection/mutable/StringBuilder.append:(Ljava/lang/Object;)Lscala/collection/mutable/StringBuilder;
	ldc	String  not allowed here
	invokevirtual	Method scala/collection/mutable/StringBuilder.append:(Ljava/lang/Object;)Lscala/collection/mutable/StringBuilder;
	invokevirtual	Method scala/collection/mutable/StringBuilder.toString:()Ljava/lang/String;
	invokespecial	Method scala/xml/dtd/ValidationException."<init>":(Ljava/lang/String;)V
	invokevirtual	Method scala/collection/immutable/List.$colon$colon:(Ljava/lang/Object;)Lscala/collection/immutable/List;
	invokevirtual	Method scala/xml/dtd/ElementValidator.scala$xml$dtd$ElementValidator$$exc_$eq:(Lscala/collection/immutable/List;)V
	goto	l4 // return
l3	aload_3
	instanceof	class scala/Some
	ifeq	l4 // return
	aload_3
	checkcast	class scala/Some
	astore	4
	aload	4
	getfield	Field scala/Some.x:Ljava/lang/Object;
	checkcast	class scala/xml/dtd/AttrDecl
	astore	5
	aload	5
	ifnull	l4 // return
	aload	5
	invokevirtual	Method scala/xml/dtd/AttrDecl.tpe:()Ljava/lang/String;
	astore	8
	aload	5
	invokevirtual	Method scala/xml/dtd/AttrDecl.default:()Lscala/xml/dtd/DefaultDecl;
	astore	6
	aload	6
	instanceof	class scala/xml/dtd/DEFAULT
	ifeq	l4 // return
	aload	6
	checkcast	class scala/xml/dtd/DEFAULT
	astore	7
	aload	7
	invokevirtual	Method scala/xml/dtd/DEFAULT.attValue:()Ljava/lang/String;
	astore	10
	aload	7
	invokevirtual	Method scala/xml/dtd/DEFAULT.fixed:()Z
	iconst_1
	if_icmpne	l4 // return
	aload_0
	aload	8
	aload	10
	aload_1
	invokespecial	Method gd4$1:(Ljava/lang/String;Ljava/lang/String;Lscala/xml/MetaData;)Z
	ifeq	l4 // return
	aload_0
	getfield	Field $outer:Lscala/xml/dtd/ElementValidator;
	aload_0
	getfield	Field $outer:Lscala/xml/dtd/ElementValidator;
	invokevirtual	Method scala/xml/dtd/ElementValidator.scala$xml$dtd$ElementValidator$$exc:()Lscala/collection/immutable/List;
	aload_1
	invokevirtual	Method scala/xml/MetaData.key:()Ljava/lang/String;
	aload_0
	aload_1
	invokespecial	Method attrStr$1:(Lscala/xml/MetaData;)Ljava/lang/String;
	astore	11
	astore	9
	new	class scala/xml/dtd/ValidationException
	dup
	new	class scala/collection/mutable/StringBuilder
	dup
	invokespecial	Method scala/collection/mutable/StringBuilder."<init>":()V
	ldc	String value of attribute 
	invokevirtual	Method scala/collection/mutable/StringBuilder.append:(Ljava/lang/Object;)Lscala/collection/mutable/StringBuilder;
	aload	9
	invokevirtual	Method scala/collection/mutable/StringBuilder.append:(Ljava/lang/Object;)Lscala/collection/mutable/StringBuilder;
	ldc	String  FIXED to \"
	invokevirtual	Method scala/collection/mutable/StringBuilder.append:(Ljava/lang/Object;)Lscala/collection/mutable/StringBuilder;
	aload	10
	invokevirtual	Method scala/collection/mutable/StringBuilder.append:(Ljava/lang/Object;)Lscala/collection/mutable/StringBuilder;
	ldc	String \", but document tries \"
	invokevirtual	Method scala/collection/mutable/StringBuilder.append:(Ljava/lang/Object;)Lscala/collection/mutable/StringBuilder;
	aload	11
	invokevirtual	Method scala/collection/mutable/StringBuilder.append:(Ljava/lang/Object;)Lscala/collection/mutable/StringBuilder;
	ldc	String \"
	invokevirtual	Method scala/collection/mutable/StringBuilder.append:(Ljava/lang/Object;)Lscala/collection/mutable/StringBuilder;
	invokevirtual	Method scala/collection/mutable/StringBuilder.toString:()Ljava/lang/String;
	invokespecial	Method scala/xml/dtd/ValidationException."<init>":(Ljava/lang/String;)V
	invokevirtual	Method scala/collection/immutable/List.$colon$colon:(Ljava/lang/Object;)Lscala/collection/immutable/List;
	invokevirtual	Method scala/xml/dtd/ElementValidator.scala$xml$dtd$ElementValidator$$exc_$eq:(Lscala/collection/immutable/List;)V
l4	return
  Labels:
   	l1 = 24 // aload_3
   	l2 = 31 // aload_0
   	l3 = 87 // aload_3
   	l4 = 254 // return
  LocalVariableTable: 
   Start  Length  Slot  Name   Signature
   0      255      0    this       Lscala/xml/dtd/ElementValidator$$anonfun$check$1;
   0      255      1    attr$1       Lscala/xml/MetaData;
   9      246      3    temp19       Lscala/Option;
   100      154      4    temp21       Lscala/Some;
   110      144      5    temp22       Lscala/xml/dtd/AttrDecl;
   129      125      6    temp25       Lscala/xml/dtd/DefaultDecl;
   144      110      7    temp26       Lscala/xml/dtd/DEFAULT;
   122      132      8    temp24       Ljava/lang/String;
   151      103      10    temp28       Ljava/lang/String;


}

