Compiled from "ElementValidator.scala"
public class scala.xml.dtd.ElementValidator extends java.lang.Object implements scala.Function1,scala.ScalaObject
  SourceFile: "ElementValidator.scala"
  ScalaSig: length = 0x3
   05 00 00 
  Signature: length = 0x2
   02 28 
  RuntimeVisibleAnnotations: length = 0xB
   00 01 02 29 00 01 02 2A 73 02 2B 
  InnerClass: 
   public Alt=class scala/util/regexp/Base$Alt of class scala/util/regexp/Base
   public abstract RegExp=class scala/util/regexp/Base$RegExp of class scala/util/regexp/Base
   public final $anonfun$check$6=class scala/xml/dtd/ElementValidator$$anonfun$check$6 of class scala/xml/dtd/ElementValidator
   public final $anonfun$check$5=class scala/xml/dtd/ElementValidator$$anonfun$check$5 of class scala/xml/dtd/ElementValidator
   public final $anonfun$check$4=class scala/xml/dtd/ElementValidator$$anonfun$check$4 of class scala/xml/dtd/ElementValidator
   public final $anonfun$check$3=class scala/xml/dtd/ElementValidator$$anonfun$check$3 of class scala/xml/dtd/ElementValidator
   public final $anonfun$check$2=class scala/xml/dtd/ElementValidator$$anonfun$check$2 of class scala/xml/dtd/ElementValidator
   public final $anonfun$check$1=class scala/xml/dtd/ElementValidator$$anonfun$check$1 of class scala/xml/dtd/ElementValidator
   public final $anonfun$find$2$1=class scala/xml/dtd/ElementValidator$$anonfun$find$2$1 of class scala/xml/dtd/ElementValidator
   public GenericCanBuildFrom=class scala/collection/generic/TraversableFactory$GenericCanBuildFrom of class scala/collection/generic/TraversableFactory
   public final $anonfun$getIterable$2=class scala/xml/dtd/ElementValidator$$anonfun$getIterable$2 of class scala/xml/dtd/ElementValidator
   public final $anonfun$getIterable$1=class scala/xml/dtd/ElementValidator$$anonfun$getIterable$1 of class scala/xml/dtd/ElementValidator
   public final $anonfun$isAllWhitespace$1$1=class scala/xml/dtd/ElementValidator$$anonfun$isAllWhitespace$1$1 of class scala/xml/dtd/ElementValidator
  minor version: 0
  major version: 49
  Constant pool:
Asciz	SourceFile;
Asciz	ElementValidator.scala;
Asciz	scala$xml$dtd$ElementValidator$$exc;
Asciz	Lscala/collection/immutable/List;;
Asciz	contentModel;
Asciz	Lscala/xml/dtd/ContentModel;;
Asciz	dfa;
Asciz	Lscala/util/automata/DetWordAutom;;
Asciz	Lscala/util/automata/DetWordAutom<Lscala/xml/dtd/ContentModel$ElemName;>;;
Asciz	Signature;
Asciz	adecls;
Asciz	Lscala/collection/immutable/List<Lscala/xml/dtd/AttrDecl;>;;
Asciz	apply$mcVI$sp;
Asciz	(I)V;
Asciz	Code;
Asciz	LineNumberTable;
Asciz	scala/Function1$class;
class	scala/Function1$class
Asciz	(Lscala/Function1;I)V;
NameAndType	apply$mcVI$sp:(Lscala/Function1;I)V
Method	scala/Function1$class.apply$mcVI$sp:(Lscala/Function1;I)V
Asciz	this;
Asciz	Lscala/xml/dtd/ElementValidator;;
Asciz	v1;
Asciz	I;
Asciz	LocalVariableTable;
Asciz	apply$mcZI$sp;
Asciz	(I)Z;
Asciz	(Lscala/Function1;I)Z;
NameAndType	apply$mcZI$sp:(Lscala/Function1;I)Z
Method	scala/Function1$class.apply$mcZI$sp:(Lscala/Function1;I)Z
Asciz	apply$mcII$sp;
Asciz	(I)I;
Asciz	(Lscala/Function1;I)I;
NameAndType	apply$mcII$sp:(Lscala/Function1;I)I
Method	scala/Function1$class.apply$mcII$sp:(Lscala/Function1;I)I
Asciz	apply$mcLI$sp;
Asciz	(I)J;
Asciz	(Lscala/Function1;I)J;
NameAndType	apply$mcLI$sp:(Lscala/Function1;I)J
Method	scala/Function1$class.apply$mcLI$sp:(Lscala/Function1;I)J
Asciz	apply$mcDI$sp;
Asciz	(I)D;
Asciz	(Lscala/Function1;I)D;
NameAndType	apply$mcDI$sp:(Lscala/Function1;I)D
Method	scala/Function1$class.apply$mcDI$sp:(Lscala/Function1;I)D
Asciz	apply$mcVL$sp;
Asciz	(J)V;
Asciz	(Lscala/Function1;J)V;
NameAndType	apply$mcVL$sp:(Lscala/Function1;J)V
Method	scala/Function1$class.apply$mcVL$sp:(Lscala/Function1;J)V
Asciz	J;
Asciz	apply$mcZL$sp;
Asciz	(J)Z;
Asciz	(Lscala/Function1;J)Z;
NameAndType	apply$mcZL$sp:(Lscala/Function1;J)Z
Method	scala/Function1$class.apply$mcZL$sp:(Lscala/Function1;J)Z
Asciz	apply$mcIL$sp;
Asciz	(J)I;
Asciz	(Lscala/Function1;J)I;
NameAndType	apply$mcIL$sp:(Lscala/Function1;J)I
Method	scala/Function1$class.apply$mcIL$sp:(Lscala/Function1;J)I
Asciz	apply$mcLL$sp;
Asciz	(J)J;
Asciz	(Lscala/Function1;J)J;
NameAndType	apply$mcLL$sp:(Lscala/Function1;J)J
Method	scala/Function1$class.apply$mcLL$sp:(Lscala/Function1;J)J
Asciz	apply$mcDL$sp;
Asciz	(J)D;
Asciz	(Lscala/Function1;J)D;
NameAndType	apply$mcDL$sp:(Lscala/Function1;J)D
Method	scala/Function1$class.apply$mcDL$sp:(Lscala/Function1;J)D
Asciz	apply$mcVD$sp;
Asciz	(D)V;
Asciz	(Lscala/Function1;D)V;
NameAndType	apply$mcVD$sp:(Lscala/Function1;D)V
Method	scala/Function1$class.apply$mcVD$sp:(Lscala/Function1;D)V
Asciz	D;
Asciz	apply$mcZD$sp;
Asciz	(D)Z;
Asciz	(Lscala/Function1;D)Z;
NameAndType	apply$mcZD$sp:(Lscala/Function1;D)Z
Method	scala/Function1$class.apply$mcZD$sp:(Lscala/Function1;D)Z
Asciz	apply$mcID$sp;
Asciz	(D)I;
Asciz	(Lscala/Function1;D)I;
NameAndType	apply$mcID$sp:(Lscala/Function1;D)I
Method	scala/Function1$class.apply$mcID$sp:(Lscala/Function1;D)I
Asciz	apply$mcLD$sp;
Asciz	(D)J;
Asciz	(Lscala/Function1;D)J;
NameAndType	apply$mcLD$sp:(Lscala/Function1;D)J
Method	scala/Function1$class.apply$mcLD$sp:(Lscala/Function1;D)J
Asciz	apply$mcDD$sp;
Asciz	(D)D;
Asciz	(Lscala/Function1;D)D;
NameAndType	apply$mcDD$sp:(Lscala/Function1;D)D
Method	scala/Function1$class.apply$mcDD$sp:(Lscala/Function1;D)D
Asciz	toString;
Asciz	()Ljava/lang/String;;
Asciz	(Lscala/Function1;)Ljava/lang/String;;
NameAndType	toString:(Lscala/Function1;)Ljava/lang/String;
Method	scala/Function1$class.toString:(Lscala/Function1;)Ljava/lang/String;
Asciz	compose;
Asciz	(Lscala/Function1;)Lscala/Function1;;
Asciz	(Lscala/Function1;Lscala/Function1;)Lscala/Function1;;
NameAndType	compose:(Lscala/Function1;Lscala/Function1;)Lscala/Function1;
Method	scala/Function1$class.compose:(Lscala/Function1;Lscala/Function1;)Lscala/Function1;
Asciz	g;
Asciz	Lscala/Function1;;
Asciz	compose$mcVI$sp;
NameAndType	compose$mcVI$sp:(Lscala/Function1;Lscala/Function1;)Lscala/Function1;
Method	scala/Function1$class.compose$mcVI$sp:(Lscala/Function1;Lscala/Function1;)Lscala/Function1;
Asciz	compose$mcZI$sp;
NameAndType	compose$mcZI$sp:(Lscala/Function1;Lscala/Function1;)Lscala/Function1;
Method	scala/Function1$class.compose$mcZI$sp:(Lscala/Function1;Lscala/Function1;)Lscala/Function1;
Asciz	compose$mcII$sp;
NameAndType	compose$mcII$sp:(Lscala/Function1;Lscala/Function1;)Lscala/Function1;
Method	scala/Function1$class.compose$mcII$sp:(Lscala/Function1;Lscala/Function1;)Lscala/Function1;
Asciz	compose$mcLI$sp;
NameAndType	compose$mcLI$sp:(Lscala/Function1;Lscala/Function1;)Lscala/Function1;
Method	scala/Function1$class.compose$mcLI$sp:(Lscala/Function1;Lscala/Function1;)Lscala/Function1;
Asciz	compose$mcDI$sp;
NameAndType	compose$mcDI$sp:(Lscala/Function1;Lscala/Function1;)Lscala/Function1;
Method	scala/Function1$class.compose$mcDI$sp:(Lscala/Function1;Lscala/Function1;)Lscala/Function1;
Asciz	compose$mcVL$sp;
NameAndType	compose$mcVL$sp:(Lscala/Function1;Lscala/Function1;)Lscala/Function1;
Method	scala/Function1$class.compose$mcVL$sp:(Lscala/Function1;Lscala/Function1;)Lscala/Function1;
Asciz	compose$mcZL$sp;
NameAndType	compose$mcZL$sp:(Lscala/Function1;Lscala/Function1;)Lscala/Function1;
Method	scala/Function1$class.compose$mcZL$sp:(Lscala/Function1;Lscala/Function1;)Lscala/Function1;
Asciz	compose$mcIL$sp;
NameAndType	compose$mcIL$sp:(Lscala/Function1;Lscala/Function1;)Lscala/Function1;
Method	scala/Function1$class.compose$mcIL$sp:(Lscala/Function1;Lscala/Function1;)Lscala/Function1;
Asciz	compose$mcLL$sp;
NameAndType	compose$mcLL$sp:(Lscala/Function1;Lscala/Function1;)Lscala/Function1;
Method	scala/Function1$class.compose$mcLL$sp:(Lscala/Function1;Lscala/Function1;)Lscala/Function1;
Asciz	compose$mcDL$sp;
NameAndType	compose$mcDL$sp:(Lscala/Function1;Lscala/Function1;)Lscala/Function1;
Method	scala/Function1$class.compose$mcDL$sp:(Lscala/Function1;Lscala/Function1;)Lscala/Function1;
Asciz	compose$mcVD$sp;
NameAndType	compose$mcVD$sp:(Lscala/Function1;Lscala/Function1;)Lscala/Function1;
Method	scala/Function1$class.compose$mcVD$sp:(Lscala/Function1;Lscala/Function1;)Lscala/Function1;
Asciz	compose$mcZD$sp;
NameAndType	compose$mcZD$sp:(Lscala/Function1;Lscala/Function1;)Lscala/Function1;
Method	scala/Function1$class.compose$mcZD$sp:(Lscala/Function1;Lscala/Function1;)Lscala/Function1;
Asciz	compose$mcID$sp;
NameAndType	compose$mcID$sp:(Lscala/Function1;Lscala/Function1;)Lscala/Function1;
Method	scala/Function1$class.compose$mcID$sp:(Lscala/Function1;Lscala/Function1;)Lscala/Function1;
Asciz	compose$mcLD$sp;
NameAndType	compose$mcLD$sp:(Lscala/Function1;Lscala/Function1;)Lscala/Function1;
Method	scala/Function1$class.compose$mcLD$sp:(Lscala/Function1;Lscala/Function1;)Lscala/Function1;
Asciz	compose$mcDD$sp;
NameAndType	compose$mcDD$sp:(Lscala/Function1;Lscala/Function1;)Lscala/Function1;
Method	scala/Function1$class.compose$mcDD$sp:(Lscala/Function1;Lscala/Function1;)Lscala/Function1;
Asciz	andThen;
NameAndType	andThen:(Lscala/Function1;Lscala/Function1;)Lscala/Function1;
Method	scala/Function1$class.andThen:(Lscala/Function1;Lscala/Function1;)Lscala/Function1;
Asciz	andThen$mcVI$sp;
NameAndType	andThen$mcVI$sp:(Lscala/Function1;Lscala/Function1;)Lscala/Function1;
Method	scala/Function1$class.andThen$mcVI$sp:(Lscala/Function1;Lscala/Function1;)Lscala/Function1;
Asciz	andThen$mcZI$sp;
NameAndType	andThen$mcZI$sp:(Lscala/Function1;Lscala/Function1;)Lscala/Function1;
Method	scala/Function1$class.andThen$mcZI$sp:(Lscala/Function1;Lscala/Function1;)Lscala/Function1;
Asciz	andThen$mcII$sp;
NameAndType	andThen$mcII$sp:(Lscala/Function1;Lscala/Function1;)Lscala/Function1;
Method	scala/Function1$class.andThen$mcII$sp:(Lscala/Function1;Lscala/Function1;)Lscala/Function1;
Asciz	andThen$mcLI$sp;
NameAndType	andThen$mcLI$sp:(Lscala/Function1;Lscala/Function1;)Lscala/Function1;
Method	scala/Function1$class.andThen$mcLI$sp:(Lscala/Function1;Lscala/Function1;)Lscala/Function1;
Asciz	andThen$mcDI$sp;
NameAndType	andThen$mcDI$sp:(Lscala/Function1;Lscala/Function1;)Lscala/Function1;
Method	scala/Function1$class.andThen$mcDI$sp:(Lscala/Function1;Lscala/Function1;)Lscala/Function1;
Asciz	andThen$mcVL$sp;
NameAndType	andThen$mcVL$sp:(Lscala/Function1;Lscala/Function1;)Lscala/Function1;
Method	scala/Function1$class.andThen$mcVL$sp:(Lscala/Function1;Lscala/Function1;)Lscala/Function1;
Asciz	andThen$mcZL$sp;
NameAndType	andThen$mcZL$sp:(Lscala/Function1;Lscala/Function1;)Lscala/Function1;
Method	scala/Function1$class.andThen$mcZL$sp:(Lscala/Function1;Lscala/Function1;)Lscala/Function1;
Asciz	andThen$mcIL$sp;
NameAndType	andThen$mcIL$sp:(Lscala/Function1;Lscala/Function1;)Lscala/Function1;
Method	scala/Function1$class.andThen$mcIL$sp:(Lscala/Function1;Lscala/Function1;)Lscala/Function1;
Asciz	andThen$mcLL$sp;
NameAndType	andThen$mcLL$sp:(Lscala/Function1;Lscala/Function1;)Lscala/Function1;
Method	scala/Function1$class.andThen$mcLL$sp:(Lscala/Function1;Lscala/Function1;)Lscala/Function1;
Asciz	andThen$mcDL$sp;
NameAndType	andThen$mcDL$sp:(Lscala/Function1;Lscala/Function1;)Lscala/Function1;
Method	scala/Function1$class.andThen$mcDL$sp:(Lscala/Function1;Lscala/Function1;)Lscala/Function1;
Asciz	andThen$mcVD$sp;
NameAndType	andThen$mcVD$sp:(Lscala/Function1;Lscala/Function1;)Lscala/Function1;
Method	scala/Function1$class.andThen$mcVD$sp:(Lscala/Function1;Lscala/Function1;)Lscala/Function1;
Asciz	andThen$mcZD$sp;
NameAndType	andThen$mcZD$sp:(Lscala/Function1;Lscala/Function1;)Lscala/Function1;
Method	scala/Function1$class.andThen$mcZD$sp:(Lscala/Function1;Lscala/Function1;)Lscala/Function1;
Asciz	andThen$mcID$sp;
NameAndType	andThen$mcID$sp:(Lscala/Function1;Lscala/Function1;)Lscala/Function1;
Method	scala/Function1$class.andThen$mcID$sp:(Lscala/Function1;Lscala/Function1;)Lscala/Function1;
Asciz	andThen$mcLD$sp;
NameAndType	andThen$mcLD$sp:(Lscala/Function1;Lscala/Function1;)Lscala/Function1;
Method	scala/Function1$class.andThen$mcLD$sp:(Lscala/Function1;Lscala/Function1;)Lscala/Function1;
Asciz	andThen$mcDD$sp;
NameAndType	andThen$mcDD$sp:(Lscala/Function1;Lscala/Function1;)Lscala/Function1;
Method	scala/Function1$class.andThen$mcDD$sp:(Lscala/Function1;Lscala/Function1;)Lscala/Function1;
Asciz	()Lscala/collection/immutable/List;;
Asciz	scala/xml/dtd/ElementValidator;
class	scala/xml/dtd/ElementValidator
NameAndType	scala$xml$dtd$ElementValidator$$exc:Lscala/collection/immutable/List;
Field	scala/xml/dtd/ElementValidator.scala$xml$dtd$ElementValidator$$exc:Lscala/collection/immutable/List;
Asciz	scala$xml$dtd$ElementValidator$$exc_$eq;
Asciz	(Lscala/collection/immutable/List;)V;
Asciz	()Lscala/xml/dtd/ContentModel;;
NameAndType	contentModel:Lscala/xml/dtd/ContentModel;
Field	scala/xml/dtd/ElementValidator.contentModel:Lscala/xml/dtd/ContentModel;
Asciz	contentModel_$eq;
Asciz	(Lscala/xml/dtd/ContentModel;)V;
Asciz	()Lscala/util/automata/DetWordAutom;;
NameAndType	dfa:Lscala/util/automata/DetWordAutom;
Field	scala/xml/dtd/ElementValidator.dfa:Lscala/util/automata/DetWordAutom;
Asciz	()Lscala/util/automata/DetWordAutom<Lscala/xml/dtd/ContentModel$ElemName;>;;
Asciz	dfa_$eq;
Asciz	(Lscala/util/automata/DetWordAutom;)V;
Asciz	(Lscala/util/automata/DetWordAutom<Lscala/xml/dtd/ContentModel$ElemName;>;)V;
NameAndType	adecls:Lscala/collection/immutable/List;
Field	scala/xml/dtd/ElementValidator.adecls:Lscala/collection/immutable/List;
Asciz	()Lscala/collection/immutable/List<Lscala/xml/dtd/AttrDecl;>;;
Asciz	adecls_$eq;
Asciz	(Lscala/collection/immutable/List<Lscala/xml/dtd/AttrDecl;>;)V;
Asciz	setContentModel;
NameAndType	contentModel_$eq:(Lscala/xml/dtd/ContentModel;)V
Method	scala/xml/dtd/ElementValidator.contentModel_$eq:(Lscala/xml/dtd/ContentModel;)V
Asciz	scala/xml/dtd/ELEMENTS;
class	scala/xml/dtd/ELEMENTS
Asciz	r;
Asciz	()Lscala/util/regexp/Base$RegExp;;
NameAndType	r:()Lscala/util/regexp/Base$RegExp;
Method	scala/xml/dtd/ELEMENTS.r:()Lscala/util/regexp/Base$RegExp;
Asciz	scala/xml/dtd/ContentModel$Translator$;
class	scala/xml/dtd/ContentModel$Translator$
Asciz	MODULE$;
Asciz	Lscala/xml/dtd/ContentModel$Translator$;;
NameAndType	MODULE$:Lscala/xml/dtd/ContentModel$Translator$;
Field	scala/xml/dtd/ContentModel$Translator$.MODULE$:Lscala/xml/dtd/ContentModel$Translator$;
Asciz	automatonFrom;
Asciz	(Lscala/util/regexp/Base$RegExp;I)Lscala/util/automata/NondetWordAutom;;
NameAndType	automatonFrom:(Lscala/util/regexp/Base$RegExp;I)Lscala/util/automata/NondetWordAutom;
Method	scala/xml/dtd/ContentModel$Translator$.automatonFrom:(Lscala/util/regexp/Base$RegExp;I)Lscala/util/automata/NondetWordAutom;
Asciz	scala/util/automata/SubsetConstruction;
class	scala/util/automata/SubsetConstruction
Asciz	<init>;
Asciz	(Lscala/util/automata/NondetWordAutom;)V;
NameAndType	"<init>":(Lscala/util/automata/NondetWordAutom;)V
Method	scala/util/automata/SubsetConstruction."<init>":(Lscala/util/automata/NondetWordAutom;)V
Asciz	determinize;
NameAndType	determinize:()Lscala/util/automata/DetWordAutom;
Method	scala/util/automata/SubsetConstruction.determinize:()Lscala/util/automata/DetWordAutom;
NameAndType	dfa_$eq:(Lscala/util/automata/DetWordAutom;)V
Method	scala/xml/dtd/ElementValidator.dfa_$eq:(Lscala/util/automata/DetWordAutom;)V
Asciz	cm;
Asciz	temp2;
Asciz	Lscala/xml/dtd/ELEMENTS;;
Asciz	temp3;
Asciz	Lscala/util/regexp/Base$RegExp;;
Asciz	nfa;
Asciz	Lscala/util/automata/NondetWordAutom;;
Asciz	getContentModel;
NameAndType	contentModel:()Lscala/xml/dtd/ContentModel;
Method	scala/xml/dtd/ElementValidator.contentModel:()Lscala/xml/dtd/ContentModel;
Asciz	setMetaData;
NameAndType	adecls_$eq:(Lscala/collection/immutable/List;)V
Method	scala/xml/dtd/ElementValidator.adecls_$eq:(Lscala/collection/immutable/List;)V
Asciz	getIterable;
Asciz	(Lscala/collection/Seq;Z)Lscala/collection/Iterable;;
Asciz	scala/xml/dtd/ElementValidator$$anonfun$getIterable$1;
class	scala/xml/dtd/ElementValidator$$anonfun$getIterable$1
Asciz	(Lscala/xml/dtd/ElementValidator;Z)V;
NameAndType	"<init>":(Lscala/xml/dtd/ElementValidator;Z)V
Method	scala/xml/dtd/ElementValidator$$anonfun$getIterable$1."<init>":(Lscala/xml/dtd/ElementValidator;Z)V
Asciz	scala/collection/TraversableLike;
class	scala/collection/TraversableLike
Asciz	filter;
Asciz	(Lscala/Function1;)Ljava/lang/Object;;
NameAndType	filter:(Lscala/Function1;)Ljava/lang/Object;
InterfaceMethod	scala/collection/TraversableLike.filter:(Lscala/Function1;)Ljava/lang/Object;
Asciz	scala/xml/dtd/ElementValidator$$anonfun$getIterable$2;
class	scala/xml/dtd/ElementValidator$$anonfun$getIterable$2
Asciz	(Lscala/xml/dtd/ElementValidator;)V;
NameAndType	"<init>":(Lscala/xml/dtd/ElementValidator;)V
Method	scala/xml/dtd/ElementValidator$$anonfun$getIterable$2."<init>":(Lscala/xml/dtd/ElementValidator;)V
Asciz	scala/collection/Seq$;
class	scala/collection/Seq$
Asciz	Lscala/collection/Seq$;;
NameAndType	MODULE$:Lscala/collection/Seq$;
Field	scala/collection/Seq$.MODULE$:Lscala/collection/Seq$;
Asciz	canBuildFrom;
Asciz	()Lscala/collection/generic/CanBuildFrom;;
NameAndType	canBuildFrom:()Lscala/collection/generic/CanBuildFrom;
Method	scala/collection/Seq$.canBuildFrom:()Lscala/collection/generic/CanBuildFrom;
Asciz	map;
Asciz	(Lscala/Function1;Lscala/collection/generic/CanBuildFrom;)Ljava/lang/Object;;
NameAndType	map:(Lscala/Function1;Lscala/collection/generic/CanBuildFrom;)Ljava/lang/Object;
InterfaceMethod	scala/collection/TraversableLike.map:(Lscala/Function1;Lscala/collection/generic/CanBuildFrom;)Ljava/lang/Object;
Asciz	scala/collection/Iterable;
class	scala/collection/Iterable
Asciz	nodes;
Asciz	Lscala/collection/Seq;;
Asciz	skipPCDATA$1;
Asciz	Z;
Asciz	(Lscala/collection/Seq<Lscala/xml/Node;>;Z)Lscala/collection/Iterable<Lscala/xml/dtd/ContentModel$ElemName;>;;
Asciz	check;
Asciz	(Lscala/xml/MetaData;)Z;
Asciz	scala/collection/LinearSeqOptimized;
class	scala/collection/LinearSeqOptimized
Asciz	length;
Asciz	()I;
NameAndType	length:()I
InterfaceMethod	scala/collection/LinearSeqOptimized.length:()I
Asciz	scala/runtime/ObjectRef;
class	scala/runtime/ObjectRef
Asciz	scala/collection/mutable/BitSet;
class	scala/collection/mutable/BitSet
NameAndType	adecls:()Lscala/collection/immutable/List;
Method	scala/xml/dtd/ElementValidator.adecls:()Lscala/collection/immutable/List;
NameAndType	"<init>":(I)V
Method	scala/collection/mutable/BitSet."<init>":(I)V
Asciz	(Ljava/lang/Object;)V;
NameAndType	"<init>":(Ljava/lang/Object;)V
Method	scala/runtime/ObjectRef."<init>":(Ljava/lang/Object;)V
Asciz	scala/xml/dtd/ElementValidator$$anonfun$check$1;
class	scala/xml/dtd/ElementValidator$$anonfun$check$1
Asciz	(Lscala/xml/dtd/ElementValidator;Lscala/runtime/ObjectRef;)V;
NameAndType	"<init>":(Lscala/xml/dtd/ElementValidator;Lscala/runtime/ObjectRef;)V
Method	scala/xml/dtd/ElementValidator$$anonfun$check$1."<init>":(Lscala/xml/dtd/ElementValidator;Lscala/runtime/ObjectRef;)V
Asciz	scala/collection/IterableLike;
class	scala/collection/IterableLike
Asciz	foreach;
Asciz	(Lscala/Function1;)V;
NameAndType	foreach:(Lscala/Function1;)V
InterfaceMethod	scala/collection/IterableLike.foreach:(Lscala/Function1;)V
Asciz	scala/collection/immutable/List$;
class	scala/collection/immutable/List$
Asciz	Lscala/collection/immutable/List$;;
NameAndType	MODULE$:Lscala/collection/immutable/List$;
Field	scala/collection/immutable/List$.MODULE$:Lscala/collection/immutable/List$;
Asciz	scala/collection/generic/TraversableFactory$GenericCanBuildFrom;
class	scala/collection/generic/TraversableFactory$GenericCanBuildFrom
Asciz	(Lscala/collection/generic/TraversableFactory;)V;
NameAndType	"<init>":(Lscala/collection/generic/TraversableFactory;)V
Method	scala/collection/generic/TraversableFactory$GenericCanBuildFrom."<init>":(Lscala/collection/generic/TraversableFactory;)V
Asciz	zipWithIndex;
Asciz	(Lscala/collection/generic/CanBuildFrom;)Ljava/lang/Object;;
NameAndType	zipWithIndex:(Lscala/collection/generic/CanBuildFrom;)Ljava/lang/Object;
InterfaceMethod	scala/collection/IterableLike.zipWithIndex:(Lscala/collection/generic/CanBuildFrom;)Ljava/lang/Object;
Asciz	scala/xml/dtd/ElementValidator$$anonfun$check$2;
class	scala/xml/dtd/ElementValidator$$anonfun$check$2
Method	scala/xml/dtd/ElementValidator$$anonfun$check$2."<init>":(Lscala/xml/dtd/ElementValidator;Lscala/runtime/ObjectRef;)V
InterfaceMethod	scala/collection/LinearSeqOptimized.foreach:(Lscala/Function1;)V
Asciz	md;
Asciz	Lscala/xml/MetaData;;
Asciz	ok$1;
Asciz	Lscala/runtime/ObjectRef;;
Asciz	len;
Asciz	(Lscala/collection/Seq;)Z;
Asciz	scala/xml/dtd/ANY$;
class	scala/xml/dtd/ANY$
Asciz	Lscala/xml/dtd/ANY$;;
NameAndType	MODULE$:Lscala/xml/dtd/ANY$;
Field	scala/xml/dtd/ANY$.MODULE$:Lscala/xml/dtd/ANY$;
Asciz	java/lang/Object;
class	java/lang/Object
Asciz	equals;
Asciz	(Ljava/lang/Object;)Z;
NameAndType	equals:(Ljava/lang/Object;)Z
Method	java/lang/Object.equals:(Ljava/lang/Object;)Z
Asciz	scala/xml/dtd/EMPTY$;
class	scala/xml/dtd/EMPTY$
Asciz	Lscala/xml/dtd/EMPTY$;;
NameAndType	MODULE$:Lscala/xml/dtd/EMPTY$;
Field	scala/xml/dtd/EMPTY$.MODULE$:Lscala/xml/dtd/EMPTY$;
NameAndType	getIterable:(Lscala/collection/Seq;Z)Lscala/collection/Iterable;
Method	scala/xml/dtd/ElementValidator.getIterable:(Lscala/collection/Seq;Z)Lscala/collection/Iterable;
Asciz	isEmpty;
Asciz	()Z;
NameAndType	isEmpty:()Z
InterfaceMethod	scala/collection/IterableLike.isEmpty:()Z
Asciz	scala/xml/dtd/PCDATA$;
class	scala/xml/dtd/PCDATA$
Asciz	Lscala/xml/dtd/PCDATA$;;
NameAndType	MODULE$:Lscala/xml/dtd/PCDATA$;
Field	scala/xml/dtd/PCDATA$.MODULE$:Lscala/xml/dtd/PCDATA$;
Asciz	scala/xml/dtd/MIXED;
class	scala/xml/dtd/MIXED
Method	scala/xml/dtd/MIXED.r:()Lscala/util/regexp/Base$RegExp;
Asciz	scala/util/regexp/Base$Alt;
class	scala/util/regexp/Base$Alt
Asciz	scala/xml/dtd/ContentModel$;
class	scala/xml/dtd/ContentModel$
Asciz	Lscala/xml/dtd/ContentModel$;;
NameAndType	MODULE$:Lscala/xml/dtd/ContentModel$;
Field	scala/xml/dtd/ContentModel$.MODULE$:Lscala/xml/dtd/ContentModel$;
Asciz	Alt;
Asciz	()Lscala/util/regexp/Base$Alt$;;
NameAndType	Alt:()Lscala/util/regexp/Base$Alt$;
Method	scala/xml/dtd/ContentModel$.Alt:()Lscala/util/regexp/Base$Alt$;
Asciz	scala/Some;
class	scala/Some
Asciz	rs;
Asciz	()Lscala/collection/Seq;;
NameAndType	rs:()Lscala/collection/Seq;
Method	scala/util/regexp/Base$Alt.rs:()Lscala/collection/Seq;
Method	scala/Some."<init>":(Ljava/lang/Object;)V
Asciz	x;
Asciz	Ljava/lang/Object;;
NameAndType	x:Ljava/lang/Object;
Field	scala/Some.x:Ljava/lang/Object;
Asciz	scala/collection/Seq;
class	scala/collection/Seq
Asciz	scala/collection/SeqLike;
class	scala/collection/SeqLike
Asciz	lengthCompare;
NameAndType	lengthCompare:(I)I
InterfaceMethod	scala/collection/SeqLike.lengthCompare:(I)I
Asciz	scala/xml/dtd/ElementValidator$$anonfun$check$3;
class	scala/xml/dtd/ElementValidator$$anonfun$check$3
Method	scala/xml/dtd/ElementValidator$$anonfun$check$3."<init>":(Lscala/xml/dtd/ElementValidator;)V
Asciz	scala/collection/Iterable$;
class	scala/collection/Iterable$
Asciz	Lscala/collection/Iterable$;;
NameAndType	MODULE$:Lscala/collection/Iterable$;
Field	scala/collection/Iterable$.MODULE$:Lscala/collection/Iterable$;
Asciz	scala/xml/dtd/ElementValidator$$anonfun$check$4;
class	scala/xml/dtd/ElementValidator$$anonfun$check$4
Asciz	(Lscala/xml/dtd/ElementValidator;Lscala/collection/Seq;)V;
NameAndType	"<init>":(Lscala/xml/dtd/ElementValidator;Lscala/collection/Seq;)V
Method	scala/xml/dtd/ElementValidator$$anonfun$check$4."<init>":(Lscala/xml/dtd/ElementValidator;Lscala/collection/Seq;)V
Asciz	filterNot;
NameAndType	filterNot:(Lscala/Function1;)Ljava/lang/Object;
InterfaceMethod	scala/collection/TraversableLike.filterNot:(Lscala/Function1;)Ljava/lang/Object;
Asciz	scala/xml/dtd/ElementValidator$$anonfun$check$5;
class	scala/xml/dtd/ElementValidator$$anonfun$check$5
Method	scala/xml/dtd/ElementValidator$$anonfun$check$5."<init>":(Lscala/xml/dtd/ElementValidator;)V
Asciz	scala/MatchError;
class	scala/MatchError
Method	scala/MatchError."<init>":(Ljava/lang/Object;)V
NameAndType	dfa:()Lscala/util/automata/DetWordAutom;
Method	scala/xml/dtd/ElementValidator.dfa:()Lscala/util/automata/DetWordAutom;
Asciz	scala/runtime/BoxesRunTime;
class	scala/runtime/BoxesRunTime
Asciz	boxToInteger;
Asciz	(I)Ljava/lang/Integer;;
NameAndType	boxToInteger:(I)Ljava/lang/Integer;
Method	scala/runtime/BoxesRunTime.boxToInteger:(I)Ljava/lang/Integer;
Asciz	scala/xml/dtd/ElementValidator$$anonfun$check$6;
class	scala/xml/dtd/ElementValidator$$anonfun$check$6
Method	scala/xml/dtd/ElementValidator$$anonfun$check$6."<init>":(Lscala/xml/dtd/ElementValidator;)V
Asciz	scala/collection/TraversableOnce;
class	scala/collection/TraversableOnce
Asciz	foldLeft;
Asciz	(Ljava/lang/Object;Lscala/Function2;)Ljava/lang/Object;;
NameAndType	foldLeft:(Ljava/lang/Object;Lscala/Function2;)Ljava/lang/Object;
InterfaceMethod	scala/collection/TraversableOnce.foldLeft:(Ljava/lang/Object;Lscala/Function2;)Ljava/lang/Object;
Asciz	unboxToInt;
Asciz	(Ljava/lang/Object;)I;
NameAndType	unboxToInt:(Ljava/lang/Object;)I
Method	scala/runtime/BoxesRunTime.unboxToInt:(Ljava/lang/Object;)I
Asciz	scala/util/automata/DetWordAutom;
class	scala/util/automata/DetWordAutom
Asciz	isFinal;
NameAndType	isFinal:(I)Z
Method	scala/util/automata/DetWordAutom.isFinal:(I)Z
Asciz	temp46;
Asciz	Lscala/xml/dtd/MIXED;;
Asciz	temp47;
Asciz	temp48;
Asciz	Lscala/util/regexp/Base$Alt;;
Asciz	temp49;
Asciz	Lscala/Some;;
Asciz	temp50;
Asciz	j;
Asciz	temp42;
Asciz	(Lscala/collection/Seq<Lscala/xml/Node;>;)Z;
Asciz	apply;
Asciz	(Lscala/xml/Node;)Z;
Asciz	scala/xml/Node;
class	scala/xml/Node
Asciz	child;
NameAndType	child:()Lscala/collection/Seq;
Method	scala/xml/Node.child:()Lscala/collection/Seq;
NameAndType	check:(Lscala/collection/Seq;)Z
Method	scala/xml/dtd/ElementValidator.check:(Lscala/collection/Seq;)Z
Asciz	attributes;
Asciz	()Lscala/xml/MetaData;;
NameAndType	attributes:()Lscala/xml/MetaData;
Method	scala/xml/Node.attributes:()Lscala/xml/MetaData;
NameAndType	check:(Lscala/xml/MetaData;)Z
Method	scala/xml/dtd/ElementValidator.check:(Lscala/xml/MetaData;)Z
Asciz	n;
Asciz	Lscala/xml/Node;;
Asciz	(Ljava/lang/Object;)Ljava/lang/Object;;
NameAndType	apply:(Lscala/xml/Node;)Z
Method	scala/xml/dtd/ElementValidator.apply:(Lscala/xml/Node;)Z
Asciz	boxToBoolean;
Asciz	(Z)Ljava/lang/Boolean;;
NameAndType	boxToBoolean:(Z)Ljava/lang/Boolean;
Method	scala/runtime/BoxesRunTime.boxToBoolean:(Z)Ljava/lang/Boolean;
Asciz	isAllWhitespace$1;
Asciz	(Lscala/xml/Atom;)Z;
Asciz	scala/PartialFunction$;
class	scala/PartialFunction$
Asciz	Lscala/PartialFunction$;;
NameAndType	MODULE$:Lscala/PartialFunction$;
Field	scala/PartialFunction$.MODULE$:Lscala/PartialFunction$;
Asciz	scala/xml/Atom;
class	scala/xml/Atom
Asciz	data;
Asciz	()Ljava/lang/Object;;
NameAndType	data:()Ljava/lang/Object;
Method	scala/xml/Atom.data:()Ljava/lang/Object;
Asciz	scala/xml/dtd/ElementValidator$$anonfun$isAllWhitespace$1$1;
class	scala/xml/dtd/ElementValidator$$anonfun$isAllWhitespace$1$1
Method	scala/xml/dtd/ElementValidator$$anonfun$isAllWhitespace$1$1."<init>":(Lscala/xml/dtd/ElementValidator;)V
Asciz	cond;
Asciz	(Ljava/lang/Object;Lscala/PartialFunction;)Z;
NameAndType	cond:(Ljava/lang/Object;Lscala/PartialFunction;)Z
Method	scala/PartialFunction$.cond:(Ljava/lang/Object;Lscala/PartialFunction;)Z
Asciz	a;
Asciz	Lscala/xml/Atom;;
Asciz	find$2;
Asciz	(Ljava/lang/String;Lscala/collection/Seq;)Z;
Asciz	scala/xml/dtd/ElementValidator$$anonfun$find$2$1;
class	scala/xml/dtd/ElementValidator$$anonfun$find$2$1
Asciz	(Lscala/xml/dtd/ElementValidator;Ljava/lang/String;)V;
NameAndType	"<init>":(Lscala/xml/dtd/ElementValidator;Ljava/lang/String;)V
Method	scala/xml/dtd/ElementValidator$$anonfun$find$2$1."<init>":(Lscala/xml/dtd/ElementValidator;Ljava/lang/String;)V
Asciz	exists;
Asciz	(Lscala/Function1;)Z;
NameAndType	exists:(Lscala/Function1;)Z
InterfaceMethod	scala/collection/IterableLike.exists:(Lscala/Function1;)Z
Asciz	Key$2;
Asciz	Ljava/lang/String;;
Asciz	()V;
NameAndType	"<init>":()V
Method	java/lang/Object."<init>":()V
Asciz	$init$;
NameAndType	$init$:(Lscala/Function1;)V
Method	scala/Function1$class.$init$:(Lscala/Function1;)V
Asciz	scala/collection/immutable/Nil$;
class	scala/collection/immutable/Nil$
Asciz	Lscala/collection/immutable/Nil$;;
NameAndType	MODULE$:Lscala/collection/immutable/Nil$;
Field	scala/collection/immutable/Nil$.MODULE$:Lscala/collection/immutable/Nil$;
Asciz	ScalaSig;
Asciz	Ljava/lang/Object;Lscala/Function1<Lscala/xml/Node;Ljava/lang/Boolean;>;Lscala/ScalaObject;;
Asciz	Lscala/reflect/ScalaSignature;;
Asciz	bytes;
Asciz	UbC\t\tA!cW-\3oiZG.3bi>(BA\r!G\t1_7m9!B:dC27A\n)R!5\tAB!A.8hy6bmL!!\r='.Z2u!BCI!!+hn;j_:CA!BA\rquZ3MYBun7fC:\"a\n}1!aC*dC2wJ6fGRDQ!\t\t\naP5oSRtD#AQ\"\t!COQ\r_2!2!K5\tQsF,]5\tAF.1AH]8pizJaBa\tq]1dW<W-3g\t!A*[:u\td%k%aG-dZ1uS>tW\t_2faRLwNq\r\":)pY0%KF$\"AOMYB)f.;\ty:!aQJ\t\r)))p\t\t!C\ta1m8uK:$Xj3fYV\tA\t%&aI\r>tG/8u>$W\r\r\"JAwN;f]RluZ3m?*;\"9ahRA!B'A&A)Ad_:$XM;N_,G\t\r\"P\r!g-Y!BK-IS!a+,Ho\7biT!!\tU$\/JAR3u/>H-Q;u_6\"!/RBA.1uN;f]RluZ3m\tifLFYlg*Y7f\tY&CaIC14mfcR!H}}\t1Q!)Q!!AMZ1!11Aa!3fG2X#5%\n%U&1N\tR$(R3dY\"9Qa\n#qAC1eKd7ofcR!h}1\t1i\t)QQ9\rZ3dYN\"B:\t!aD:fi{g^3oi6{G-7i*\"<s!AA2nA\"D=9W\r^\"p]R,g^'pId\">\tYaC:fi6+G/#bi$\"A?\tL5\tyAA@,G/;feG.\t9!!\t%\nW$C%uKJ'\r\3\t%Q1)an3fgB!&!\r\tya\r'BBA\n{!$tW&k#B)Cq!a\t\tI\"AdQ7F7A\"!qD[2aFA\r\t\t$\rR1uC\"9qBc*!ABA\tYC.!\t!a\=i\t\tC4-9;
Asciz	RuntimeVisibleAnnotations;
Asciz	InnerClasses;
Asciz	scala/util/regexp/Base;
class	scala/util/regexp/Base
Asciz	scala/util/regexp/Base$RegExp;
class	scala/util/regexp/Base$RegExp
Asciz	RegExp;
Asciz	$anonfun$check$6;
Asciz	$anonfun$check$5;
Asciz	$anonfun$check$4;
Asciz	$anonfun$check$3;
Asciz	$anonfun$check$2;
Asciz	$anonfun$check$1;
Asciz	$anonfun$find$2$1;
Asciz	scala/collection/generic/TraversableFactory;
class	scala/collection/generic/TraversableFactory
Asciz	GenericCanBuildFrom;
Asciz	$anonfun$getIterable$2;
Asciz	$anonfun$getIterable$1;
Asciz	$anonfun$isAllWhitespace$1$1;
Asciz	scala/Function1;
class	scala/Function1
Asciz	scala/ScalaObject;
class	scala/ScalaObject

{
private scala.collection.immutable.List scala$xml$dtd$ElementValidator$$exc;
  Signature: Lscala/collection/immutable/List;

private scala.xml.dtd.ContentModel contentModel;
  Signature: Lscala/xml/dtd/ContentModel;

private scala.util.automata.DetWordAutom dfa;
  Signature: Lscala/util/automata/DetWordAutom;
  Signature: length = 0x2
   00 09 

private scala.collection.immutable.List adecls;
  Signature: Lscala/collection/immutable/List;
  Signature: length = 0x2
   00 0C 

public void apply$mcVI$sp(int);
  Signature: (I)V
  Code:
   Stack=2, Locals=2, Args_size=2
	aload_0
	iload_1
	invokestatic	Method scala/Function1$class.apply$mcVI$sp:(Lscala/Function1;I)V
	return
  Labels:
  LocalVariableTable: 
   Start  Length  Slot  Name   Signature
   0      6      0    this       Lscala/xml/dtd/ElementValidator;
   0      6      1    v1       I


public boolean apply$mcZI$sp(int);
  Signature: (I)Z
  Code:
   Stack=2, Locals=2, Args_size=2
	aload_0
	iload_1
	invokestatic	Method scala/Function1$class.apply$mcZI$sp:(Lscala/Function1;I)Z
	ireturn
  Labels:
  LocalVariableTable: 
   Start  Length  Slot  Name   Signature
   0      6      0    this       Lscala/xml/dtd/ElementValidator;
   0      6      1    v1       I


public int apply$mcII$sp(int);
  Signature: (I)I
  Code:
   Stack=2, Locals=2, Args_size=2
	aload_0
	iload_1
	invokestatic	Method scala/Function1$class.apply$mcII$sp:(Lscala/Function1;I)I
	ireturn
  Labels:
  LocalVariableTable: 
   Start  Length  Slot  Name   Signature
   0      6      0    this       Lscala/xml/dtd/ElementValidator;
   0      6      1    v1       I


public long apply$mcLI$sp(int);
  Signature: (I)J
  Code:
   Stack=2, Locals=2, Args_size=2
	aload_0
	iload_1
	invokestatic	Method scala/Function1$class.apply$mcLI$sp:(Lscala/Function1;I)J
	lreturn
  Labels:
  LocalVariableTable: 
   Start  Length  Slot  Name   Signature
   0      6      0    this       Lscala/xml/dtd/ElementValidator;
   0      6      1    v1       I


public double apply$mcDI$sp(int);
  Signature: (I)D
  Code:
   Stack=2, Locals=2, Args_size=2
	aload_0
	iload_1
	invokestatic	Method scala/Function1$class.apply$mcDI$sp:(Lscala/Function1;I)D
	dreturn
  Labels:
  LocalVariableTable: 
   Start  Length  Slot  Name   Signature
   0      6      0    this       Lscala/xml/dtd/ElementValidator;
   0      6      1    v1       I


public void apply$mcVL$sp(long);
  Signature: (J)V
  Code:
   Stack=3, Locals=3, Args_size=2
	aload_0
	lload_1
	invokestatic	Method scala/Function1$class.apply$mcVL$sp:(Lscala/Function1;J)V
	return
  Labels:
  LocalVariableTable: 
   Start  Length  Slot  Name   Signature
   0      6      0    this       Lscala/xml/dtd/ElementValidator;
   0      6      1    v1       J


public boolean apply$mcZL$sp(long);
  Signature: (J)Z
  Code:
   Stack=3, Locals=3, Args_size=2
	aload_0
	lload_1
	invokestatic	Method scala/Function1$class.apply$mcZL$sp:(Lscala/Function1;J)Z
	ireturn
  Labels:
  LocalVariableTable: 
   Start  Length  Slot  Name   Signature
   0      6      0    this       Lscala/xml/dtd/ElementValidator;
   0      6      1    v1       J


public int apply$mcIL$sp(long);
  Signature: (J)I
  Code:
   Stack=3, Locals=3, Args_size=2
	aload_0
	lload_1
	invokestatic	Method scala/Function1$class.apply$mcIL$sp:(Lscala/Function1;J)I
	ireturn
  Labels:
  LocalVariableTable: 
   Start  Length  Slot  Name   Signature
   0      6      0    this       Lscala/xml/dtd/ElementValidator;
   0      6      1    v1       J


public long apply$mcLL$sp(long);
  Signature: (J)J
  Code:
   Stack=3, Locals=3, Args_size=2
	aload_0
	lload_1
	invokestatic	Method scala/Function1$class.apply$mcLL$sp:(Lscala/Function1;J)J
	lreturn
  Labels:
  LocalVariableTable: 
   Start  Length  Slot  Name   Signature
   0      6      0    this       Lscala/xml/dtd/ElementValidator;
   0      6      1    v1       J


public double apply$mcDL$sp(long);
  Signature: (J)D
  Code:
   Stack=3, Locals=3, Args_size=2
	aload_0
	lload_1
	invokestatic	Method scala/Function1$class.apply$mcDL$sp:(Lscala/Function1;J)D
	dreturn
  Labels:
  LocalVariableTable: 
   Start  Length  Slot  Name   Signature
   0      6      0    this       Lscala/xml/dtd/ElementValidator;
   0      6      1    v1       J


public void apply$mcVD$sp(double);
  Signature: (D)V
  Code:
   Stack=3, Locals=3, Args_size=2
	aload_0
	dload_1
	invokestatic	Method scala/Function1$class.apply$mcVD$sp:(Lscala/Function1;D)V
	return
  Labels:
  LocalVariableTable: 
   Start  Length  Slot  Name   Signature
   0      6      0    this       Lscala/xml/dtd/ElementValidator;
   0      6      1    v1       D


public boolean apply$mcZD$sp(double);
  Signature: (D)Z
  Code:
   Stack=3, Locals=3, Args_size=2
	aload_0
	dload_1
	invokestatic	Method scala/Function1$class.apply$mcZD$sp:(Lscala/Function1;D)Z
	ireturn
  Labels:
  LocalVariableTable: 
   Start  Length  Slot  Name   Signature
   0      6      0    this       Lscala/xml/dtd/ElementValidator;
   0      6      1    v1       D


public int apply$mcID$sp(double);
  Signature: (D)I
  Code:
   Stack=3, Locals=3, Args_size=2
	aload_0
	dload_1
	invokestatic	Method scala/Function1$class.apply$mcID$sp:(Lscala/Function1;D)I
	ireturn
  Labels:
  LocalVariableTable: 
   Start  Length  Slot  Name   Signature
   0      6      0    this       Lscala/xml/dtd/ElementValidator;
   0      6      1    v1       D


public long apply$mcLD$sp(double);
  Signature: (D)J
  Code:
   Stack=3, Locals=3, Args_size=2
	aload_0
	dload_1
	invokestatic	Method scala/Function1$class.apply$mcLD$sp:(Lscala/Function1;D)J
	lreturn
  Labels:
  LocalVariableTable: 
   Start  Length  Slot  Name   Signature
   0      6      0    this       Lscala/xml/dtd/ElementValidator;
   0      6      1    v1       D


public double apply$mcDD$sp(double);
  Signature: (D)D
  Code:
   Stack=3, Locals=3, Args_size=2
	aload_0
	dload_1
	invokestatic	Method scala/Function1$class.apply$mcDD$sp:(Lscala/Function1;D)D
	dreturn
  Labels:
  LocalVariableTable: 
   Start  Length  Slot  Name   Signature
   0      6      0    this       Lscala/xml/dtd/ElementValidator;
   0      6      1    v1       D


public java.lang.String toString();
  Signature: ()Ljava/lang/String;
  Code:
   Stack=1, Locals=1, Args_size=1
	aload_0
	invokestatic	Method scala/Function1$class.toString:(Lscala/Function1;)Ljava/lang/String;
	areturn
  Labels:

public scala.Function1 compose(scala.Function1);
  Signature: (Lscala/Function1;)Lscala/Function1;
  Code:
   Stack=2, Locals=2, Args_size=2
	aload_0
	aload_1
	invokestatic	Method scala/Function1$class.compose:(Lscala/Function1;Lscala/Function1;)Lscala/Function1;
	areturn
  Labels:
  LocalVariableTable: 
   Start  Length  Slot  Name   Signature
   0      6      0    this       Lscala/xml/dtd/ElementValidator;
   0      6      1    g       Lscala/Function1;


public scala.Function1 compose$mcVI$sp(scala.Function1);
  Signature: (Lscala/Function1;)Lscala/Function1;
  Code:
   Stack=2, Locals=2, Args_size=2
	aload_0
	aload_1
	invokestatic	Method scala/Function1$class.compose$mcVI$sp:(Lscala/Function1;Lscala/Function1;)Lscala/Function1;
	areturn
  Labels:
  LocalVariableTable: 
   Start  Length  Slot  Name   Signature
   0      6      0    this       Lscala/xml/dtd/ElementValidator;
   0      6      1    g       Lscala/Function1;


public scala.Function1 compose$mcZI$sp(scala.Function1);
  Signature: (Lscala/Function1;)Lscala/Function1;
  Code:
   Stack=2, Locals=2, Args_size=2
	aload_0
	aload_1
	invokestatic	Method scala/Function1$class.compose$mcZI$sp:(Lscala/Function1;Lscala/Function1;)Lscala/Function1;
	areturn
  Labels:
  LocalVariableTable: 
   Start  Length  Slot  Name   Signature
   0      6      0    this       Lscala/xml/dtd/ElementValidator;
   0      6      1    g       Lscala/Function1;


public scala.Function1 compose$mcII$sp(scala.Function1);
  Signature: (Lscala/Function1;)Lscala/Function1;
  Code:
   Stack=2, Locals=2, Args_size=2
	aload_0
	aload_1
	invokestatic	Method scala/Function1$class.compose$mcII$sp:(Lscala/Function1;Lscala/Function1;)Lscala/Function1;
	areturn
  Labels:
  LocalVariableTable: 
   Start  Length  Slot  Name   Signature
   0      6      0    this       Lscala/xml/dtd/ElementValidator;
   0      6      1    g       Lscala/Function1;


public scala.Function1 compose$mcLI$sp(scala.Function1);
  Signature: (Lscala/Function1;)Lscala/Function1;
  Code:
   Stack=2, Locals=2, Args_size=2
	aload_0
	aload_1
	invokestatic	Method scala/Function1$class.compose$mcLI$sp:(Lscala/Function1;Lscala/Function1;)Lscala/Function1;
	areturn
  Labels:
  LocalVariableTable: 
   Start  Length  Slot  Name   Signature
   0      6      0    this       Lscala/xml/dtd/ElementValidator;
   0      6      1    g       Lscala/Function1;


public scala.Function1 compose$mcDI$sp(scala.Function1);
  Signature: (Lscala/Function1;)Lscala/Function1;
  Code:
   Stack=2, Locals=2, Args_size=2
	aload_0
	aload_1
	invokestatic	Method scala/Function1$class.compose$mcDI$sp:(Lscala/Function1;Lscala/Function1;)Lscala/Function1;
	areturn
  Labels:
  LocalVariableTable: 
   Start  Length  Slot  Name   Signature
   0      6      0    this       Lscala/xml/dtd/ElementValidator;
   0      6      1    g       Lscala/Function1;


public scala.Function1 compose$mcVL$sp(scala.Function1);
  Signature: (Lscala/Function1;)Lscala/Function1;
  Code:
   Stack=2, Locals=2, Args_size=2
	aload_0
	aload_1
	invokestatic	Method scala/Function1$class.compose$mcVL$sp:(Lscala/Function1;Lscala/Function1;)Lscala/Function1;
	areturn
  Labels:
  LocalVariableTable: 
   Start  Length  Slot  Name   Signature
   0      6      0    this       Lscala/xml/dtd/ElementValidator;
   0      6      1    g       Lscala/Function1;


public scala.Function1 compose$mcZL$sp(scala.Function1);
  Signature: (Lscala/Function1;)Lscala/Function1;
  Code:
   Stack=2, Locals=2, Args_size=2
	aload_0
	aload_1
	invokestatic	Method scala/Function1$class.compose$mcZL$sp:(Lscala/Function1;Lscala/Function1;)Lscala/Function1;
	areturn
  Labels:
  LocalVariableTable: 
   Start  Length  Slot  Name   Signature
   0      6      0    this       Lscala/xml/dtd/ElementValidator;
   0      6      1    g       Lscala/Function1;


public scala.Function1 compose$mcIL$sp(scala.Function1);
  Signature: (Lscala/Function1;)Lscala/Function1;
  Code:
   Stack=2, Locals=2, Args_size=2
	aload_0
	aload_1
	invokestatic	Method scala/Function1$class.compose$mcIL$sp:(Lscala/Function1;Lscala/Function1;)Lscala/Function1;
	areturn
  Labels:
  LocalVariableTable: 
   Start  Length  Slot  Name   Signature
   0      6      0    this       Lscala/xml/dtd/ElementValidator;
   0      6      1    g       Lscala/Function1;


public scala.Function1 compose$mcLL$sp(scala.Function1);
  Signature: (Lscala/Function1;)Lscala/Function1;
  Code:
   Stack=2, Locals=2, Args_size=2
	aload_0
	aload_1
	invokestatic	Method scala/Function1$class.compose$mcLL$sp:(Lscala/Function1;Lscala/Function1;)Lscala/Function1;
	areturn
  Labels:
  LocalVariableTable: 
   Start  Length  Slot  Name   Signature
   0      6      0    this       Lscala/xml/dtd/ElementValidator;
   0      6      1    g       Lscala/Function1;


public scala.Function1 compose$mcDL$sp(scala.Function1);
  Signature: (Lscala/Function1;)Lscala/Function1;
  Code:
   Stack=2, Locals=2, Args_size=2
	aload_0
	aload_1
	invokestatic	Method scala/Function1$class.compose$mcDL$sp:(Lscala/Function1;Lscala/Function1;)Lscala/Function1;
	areturn
  Labels:
  LocalVariableTable: 
   Start  Length  Slot  Name   Signature
   0      6      0    this       Lscala/xml/dtd/ElementValidator;
   0      6      1    g       Lscala/Function1;


public scala.Function1 compose$mcVD$sp(scala.Function1);
  Signature: (Lscala/Function1;)Lscala/Function1;
  Code:
   Stack=2, Locals=2, Args_size=2
	aload_0
	aload_1
	invokestatic	Method scala/Function1$class.compose$mcVD$sp:(Lscala/Function1;Lscala/Function1;)Lscala/Function1;
	areturn
  Labels:
  LocalVariableTable: 
   Start  Length  Slot  Name   Signature
   0      6      0    this       Lscala/xml/dtd/ElementValidator;
   0      6      1    g       Lscala/Function1;


public scala.Function1 compose$mcZD$sp(scala.Function1);
  Signature: (Lscala/Function1;)Lscala/Function1;
  Code:
   Stack=2, Locals=2, Args_size=2
	aload_0
	aload_1
	invokestatic	Method scala/Function1$class.compose$mcZD$sp:(Lscala/Function1;Lscala/Function1;)Lscala/Function1;
	areturn
  Labels:
  LocalVariableTable: 
   Start  Length  Slot  Name   Signature
   0      6      0    this       Lscala/xml/dtd/ElementValidator;
   0      6      1    g       Lscala/Function1;


public scala.Function1 compose$mcID$sp(scala.Function1);
  Signature: (Lscala/Function1;)Lscala/Function1;
  Code:
   Stack=2, Locals=2, Args_size=2
	aload_0
	aload_1
	invokestatic	Method scala/Function1$class.compose$mcID$sp:(Lscala/Function1;Lscala/Function1;)Lscala/Function1;
	areturn
  Labels:
  LocalVariableTable: 
   Start  Length  Slot  Name   Signature
   0      6      0    this       Lscala/xml/dtd/ElementValidator;
   0      6      1    g       Lscala/Function1;


public scala.Function1 compose$mcLD$sp(scala.Function1);
  Signature: (Lscala/Function1;)Lscala/Function1;
  Code:
   Stack=2, Locals=2, Args_size=2
	aload_0
	aload_1
	invokestatic	Method scala/Function1$class.compose$mcLD$sp:(Lscala/Function1;Lscala/Function1;)Lscala/Function1;
	areturn
  Labels:
  LocalVariableTable: 
   Start  Length  Slot  Name   Signature
   0      6      0    this       Lscala/xml/dtd/ElementValidator;
   0      6      1    g       Lscala/Function1;


public scala.Function1 compose$mcDD$sp(scala.Function1);
  Signature: (Lscala/Function1;)Lscala/Function1;
  Code:
   Stack=2, Locals=2, Args_size=2
	aload_0
	aload_1
	invokestatic	Method scala/Function1$class.compose$mcDD$sp:(Lscala/Function1;Lscala/Function1;)Lscala/Function1;
	areturn
  Labels:
  LocalVariableTable: 
   Start  Length  Slot  Name   Signature
   0      6      0    this       Lscala/xml/dtd/ElementValidator;
   0      6      1    g       Lscala/Function1;


public scala.Function1 andThen(scala.Function1);
  Signature: (Lscala/Function1;)Lscala/Function1;
  Code:
   Stack=2, Locals=2, Args_size=2
	aload_0
	aload_1
	invokestatic	Method scala/Function1$class.andThen:(Lscala/Function1;Lscala/Function1;)Lscala/Function1;
	areturn
  Labels:
  LocalVariableTable: 
   Start  Length  Slot  Name   Signature
   0      6      0    this       Lscala/xml/dtd/ElementValidator;
   0      6      1    g       Lscala/Function1;


public scala.Function1 andThen$mcVI$sp(scala.Function1);
  Signature: (Lscala/Function1;)Lscala/Function1;
  Code:
   Stack=2, Locals=2, Args_size=2
	aload_0
	aload_1
	invokestatic	Method scala/Function1$class.andThen$mcVI$sp:(Lscala/Function1;Lscala/Function1;)Lscala/Function1;
	areturn
  Labels:
  LocalVariableTable: 
   Start  Length  Slot  Name   Signature
   0      6      0    this       Lscala/xml/dtd/ElementValidator;
   0      6      1    g       Lscala/Function1;


public scala.Function1 andThen$mcZI$sp(scala.Function1);
  Signature: (Lscala/Function1;)Lscala/Function1;
  Code:
   Stack=2, Locals=2, Args_size=2
	aload_0
	aload_1
	invokestatic	Method scala/Function1$class.andThen$mcZI$sp:(Lscala/Function1;Lscala/Function1;)Lscala/Function1;
	areturn
  Labels:
  LocalVariableTable: 
   Start  Length  Slot  Name   Signature
   0      6      0    this       Lscala/xml/dtd/ElementValidator;
   0      6      1    g       Lscala/Function1;


public scala.Function1 andThen$mcII$sp(scala.Function1);
  Signature: (Lscala/Function1;)Lscala/Function1;
  Code:
   Stack=2, Locals=2, Args_size=2
	aload_0
	aload_1
	invokestatic	Method scala/Function1$class.andThen$mcII$sp:(Lscala/Function1;Lscala/Function1;)Lscala/Function1;
	areturn
  Labels:
  LocalVariableTable: 
   Start  Length  Slot  Name   Signature
   0      6      0    this       Lscala/xml/dtd/ElementValidator;
   0      6      1    g       Lscala/Function1;


public scala.Function1 andThen$mcLI$sp(scala.Function1);
  Signature: (Lscala/Function1;)Lscala/Function1;
  Code:
   Stack=2, Locals=2, Args_size=2
	aload_0
	aload_1
	invokestatic	Method scala/Function1$class.andThen$mcLI$sp:(Lscala/Function1;Lscala/Function1;)Lscala/Function1;
	areturn
  Labels:
  LocalVariableTable: 
   Start  Length  Slot  Name   Signature
   0      6      0    this       Lscala/xml/dtd/ElementValidator;
   0      6      1    g       Lscala/Function1;


public scala.Function1 andThen$mcDI$sp(scala.Function1);
  Signature: (Lscala/Function1;)Lscala/Function1;
  Code:
   Stack=2, Locals=2, Args_size=2
	aload_0
	aload_1
	invokestatic	Method scala/Function1$class.andThen$mcDI$sp:(Lscala/Function1;Lscala/Function1;)Lscala/Function1;
	areturn
  Labels:
  LocalVariableTable: 
   Start  Length  Slot  Name   Signature
   0      6      0    this       Lscala/xml/dtd/ElementValidator;
   0      6      1    g       Lscala/Function1;


public scala.Function1 andThen$mcVL$sp(scala.Function1);
  Signature: (Lscala/Function1;)Lscala/Function1;
  Code:
   Stack=2, Locals=2, Args_size=2
	aload_0
	aload_1
	invokestatic	Method scala/Function1$class.andThen$mcVL$sp:(Lscala/Function1;Lscala/Function1;)Lscala/Function1;
	areturn
  Labels:
  LocalVariableTable: 
   Start  Length  Slot  Name   Signature
   0      6      0    this       Lscala/xml/dtd/ElementValidator;
   0      6      1    g       Lscala/Function1;


public scala.Function1 andThen$mcZL$sp(scala.Function1);
  Signature: (Lscala/Function1;)Lscala/Function1;
  Code:
   Stack=2, Locals=2, Args_size=2
	aload_0
	aload_1
	invokestatic	Method scala/Function1$class.andThen$mcZL$sp:(Lscala/Function1;Lscala/Function1;)Lscala/Function1;
	areturn
  Labels:
  LocalVariableTable: 
   Start  Length  Slot  Name   Signature
   0      6      0    this       Lscala/xml/dtd/ElementValidator;
   0      6      1    g       Lscala/Function1;


public scala.Function1 andThen$mcIL$sp(scala.Function1);
  Signature: (Lscala/Function1;)Lscala/Function1;
  Code:
   Stack=2, Locals=2, Args_size=2
	aload_0
	aload_1
	invokestatic	Method scala/Function1$class.andThen$mcIL$sp:(Lscala/Function1;Lscala/Function1;)Lscala/Function1;
	areturn
  Labels:
  LocalVariableTable: 
   Start  Length  Slot  Name   Signature
   0      6      0    this       Lscala/xml/dtd/ElementValidator;
   0      6      1    g       Lscala/Function1;


public scala.Function1 andThen$mcLL$sp(scala.Function1);
  Signature: (Lscala/Function1;)Lscala/Function1;
  Code:
   Stack=2, Locals=2, Args_size=2
	aload_0
	aload_1
	invokestatic	Method scala/Function1$class.andThen$mcLL$sp:(Lscala/Function1;Lscala/Function1;)Lscala/Function1;
	areturn
  Labels:
  LocalVariableTable: 
   Start  Length  Slot  Name   Signature
   0      6      0    this       Lscala/xml/dtd/ElementValidator;
   0      6      1    g       Lscala/Function1;


public scala.Function1 andThen$mcDL$sp(scala.Function1);
  Signature: (Lscala/Function1;)Lscala/Function1;
  Code:
   Stack=2, Locals=2, Args_size=2
	aload_0
	aload_1
	invokestatic	Method scala/Function1$class.andThen$mcDL$sp:(Lscala/Function1;Lscala/Function1;)Lscala/Function1;
	areturn
  Labels:
  LocalVariableTable: 
   Start  Length  Slot  Name   Signature
   0      6      0    this       Lscala/xml/dtd/ElementValidator;
   0      6      1    g       Lscala/Function1;


public scala.Function1 andThen$mcVD$sp(scala.Function1);
  Signature: (Lscala/Function1;)Lscala/Function1;
  Code:
   Stack=2, Locals=2, Args_size=2
	aload_0
	aload_1
	invokestatic	Method scala/Function1$class.andThen$mcVD$sp:(Lscala/Function1;Lscala/Function1;)Lscala/Function1;
	areturn
  Labels:
  LocalVariableTable: 
   Start  Length  Slot  Name   Signature
   0      6      0    this       Lscala/xml/dtd/ElementValidator;
   0      6      1    g       Lscala/Function1;


public scala.Function1 andThen$mcZD$sp(scala.Function1);
  Signature: (Lscala/Function1;)Lscala/Function1;
  Code:
   Stack=2, Locals=2, Args_size=2
	aload_0
	aload_1
	invokestatic	Method scala/Function1$class.andThen$mcZD$sp:(Lscala/Function1;Lscala/Function1;)Lscala/Function1;
	areturn
  Labels:
  LocalVariableTable: 
   Start  Length  Slot  Name   Signature
   0      6      0    this       Lscala/xml/dtd/ElementValidator;
   0      6      1    g       Lscala/Function1;


public scala.Function1 andThen$mcID$sp(scala.Function1);
  Signature: (Lscala/Function1;)Lscala/Function1;
  Code:
   Stack=2, Locals=2, Args_size=2
	aload_0
	aload_1
	invokestatic	Method scala/Function1$class.andThen$mcID$sp:(Lscala/Function1;Lscala/Function1;)Lscala/Function1;
	areturn
  Labels:
  LocalVariableTable: 
   Start  Length  Slot  Name   Signature
   0      6      0    this       Lscala/xml/dtd/ElementValidator;
   0      6      1    g       Lscala/Function1;


public scala.Function1 andThen$mcLD$sp(scala.Function1);
  Signature: (Lscala/Function1;)Lscala/Function1;
  Code:
   Stack=2, Locals=2, Args_size=2
	aload_0
	aload_1
	invokestatic	Method scala/Function1$class.andThen$mcLD$sp:(Lscala/Function1;Lscala/Function1;)Lscala/Function1;
	areturn
  Labels:
  LocalVariableTable: 
   Start  Length  Slot  Name   Signature
   0      6      0    this       Lscala/xml/dtd/ElementValidator;
   0      6      1    g       Lscala/Function1;


public scala.Function1 andThen$mcDD$sp(scala.Function1);
  Signature: (Lscala/Function1;)Lscala/Function1;
  Code:
   Stack=2, Locals=2, Args_size=2
	aload_0
	aload_1
	invokestatic	Method scala/Function1$class.andThen$mcDD$sp:(Lscala/Function1;Lscala/Function1;)Lscala/Function1;
	areturn
  Labels:
  LocalVariableTable: 
   Start  Length  Slot  Name   Signature
   0      6      0    this       Lscala/xml/dtd/ElementValidator;
   0      6      1    g       Lscala/Function1;


public final scala.collection.immutable.List scala$xml$dtd$ElementValidator$$exc();
  Signature: ()Lscala/collection/immutable/List;
  Code:
   Stack=1, Locals=1, Args_size=1
	aload_0
	getfield	Field scala$xml$dtd$ElementValidator$$exc:Lscala/collection/immutable/List;
	areturn
  Labels:

public final void scala$xml$dtd$ElementValidator$$exc_$eq(scala.collection.immutable.List);
  Signature: (Lscala/collection/immutable/List;)V
  Code:
   Stack=2, Locals=2, Args_size=2
	aload_0
	aload_1
	putfield	Field scala$xml$dtd$ElementValidator$$exc:Lscala/collection/immutable/List;
	return
  Labels:

public scala.xml.dtd.ContentModel contentModel();
  Signature: ()Lscala/xml/dtd/ContentModel;
  Code:
   Stack=1, Locals=1, Args_size=1
	aload_0
	getfield	Field contentModel:Lscala/xml/dtd/ContentModel;
	areturn
  Labels:

public void contentModel_$eq(scala.xml.dtd.ContentModel);
  Signature: (Lscala/xml/dtd/ContentModel;)V
  Code:
   Stack=2, Locals=2, Args_size=2
	aload_0
	aload_1
	putfield	Field contentModel:Lscala/xml/dtd/ContentModel;
	return
  Labels:

public scala.util.automata.DetWordAutom dfa();
  Signature: ()Lscala/util/automata/DetWordAutom;
  Code:
   Stack=1, Locals=1, Args_size=1
	aload_0
	getfield	Field dfa:Lscala/util/automata/DetWordAutom;
	areturn
  Labels:
  Signature: length = 0x2
   00 FFFFFFDB 

public void dfa_$eq(scala.util.automata.DetWordAutom);
  Signature: (Lscala/util/automata/DetWordAutom;)V
  Code:
   Stack=2, Locals=2, Args_size=2
	aload_0
	aload_1
	putfield	Field dfa:Lscala/util/automata/DetWordAutom;
	return
  Labels:
  Signature: length = 0x2
   00 FFFFFFDE 

public scala.collection.immutable.List adecls();
  Signature: ()Lscala/collection/immutable/List;
  Code:
   Stack=1, Locals=1, Args_size=1
	aload_0
	getfield	Field adecls:Lscala/collection/immutable/List;
	areturn
  Labels:
  Signature: length = 0x2
   00 FFFFFFE1 

public void adecls_$eq(scala.collection.immutable.List);
  Signature: (Lscala/collection/immutable/List;)V
  Code:
   Stack=2, Locals=2, Args_size=2
	aload_0
	aload_1
	putfield	Field adecls:Lscala/collection/immutable/List;
	return
  Labels:
  Signature: length = 0x2
   00 FFFFFFE3 

public void setContentModel(scala.xml.dtd.ContentModel);
  Signature: (Lscala/xml/dtd/ContentModel;)V
  Code:
   Stack=4, Locals=5, Args_size=2
	aload_0
	aload_1
	invokevirtual	Method contentModel_$eq:(Lscala/xml/dtd/ContentModel;)V
	aload_1
	instanceof	class scala/xml/dtd/ELEMENTS
	ifeq	l1 // aload_0
	aload_1
	checkcast	class scala/xml/dtd/ELEMENTS
	astore_2
	aload_2
	invokevirtual	Method scala/xml/dtd/ELEMENTS.r:()Lscala/util/regexp/Base$RegExp;
	astore_3
	getstatic	Field scala/xml/dtd/ContentModel$Translator$.MODULE$:Lscala/xml/dtd/ContentModel$Translator$;
	aload_3
	iconst_1
	invokevirtual	Method scala/xml/dtd/ContentModel$Translator$.automatonFrom:(Lscala/util/regexp/Base$RegExp;I)Lscala/util/automata/NondetWordAutom;
	astore	4
	aload_0
	new	class scala/util/automata/SubsetConstruction
	dup
	aload	4
	invokespecial	Method scala/util/automata/SubsetConstruction."<init>":(Lscala/util/automata/NondetWordAutom;)V
	invokevirtual	Method scala/util/automata/SubsetConstruction.determinize:()Lscala/util/automata/DetWordAutom;
	invokevirtual	Method dfa_$eq:(Lscala/util/automata/DetWordAutom;)V
	goto	l2 // return
l1	aload_0
	aconst_null
	invokevirtual	Method dfa_$eq:(Lscala/util/automata/DetWordAutom;)V
l2	return
  Labels:
   	l1 = 51 // aload_0
   	l2 = 56 // return
  LocalVariableTable: 
   Start  Length  Slot  Name   Signature
   0      57      0    this       Lscala/xml/dtd/ElementValidator;
   0      57      1    cm       Lscala/xml/dtd/ContentModel;
   17      31      2    temp2       Lscala/xml/dtd/ELEMENTS;
   22      26      3    temp3       Lscala/util/regexp/Base$RegExp;
   32      16      4    nfa       Lscala/util/automata/NondetWordAutom;


public scala.xml.dtd.ContentModel getContentModel();
  Signature: ()Lscala/xml/dtd/ContentModel;
  Code:
   Stack=1, Locals=1, Args_size=1
	aload_0
	invokevirtual	Method contentModel:()Lscala/xml/dtd/ContentModel;
	areturn
  Labels:

public void setMetaData(scala.collection.immutable.List);
  Signature: (Lscala/collection/immutable/List;)V
  Code:
   Stack=2, Locals=2, Args_size=2
	aload_0
	aload_1
	invokevirtual	Method adecls_$eq:(Lscala/collection/immutable/List;)V
	return
  Labels:
  LocalVariableTable: 
   Start  Length  Slot  Name   Signature
   0      6      0    this       Lscala/xml/dtd/ElementValidator;
   0      6      1    adecls       Lscala/collection/immutable/List;

  Signature: length = 0x2
   00 FFFFFFE3 

public scala.collection.Iterable getIterable(scala.collection.Seq, boolean);
  Signature: (Lscala/collection/Seq;Z)Lscala/collection/Iterable;
  Code:
   Stack=5, Locals=3, Args_size=3
	aload_1
	new	class scala/xml/dtd/ElementValidator$$anonfun$getIterable$1
	dup
	aload_0
	iload_2
	invokespecial	Method scala/xml/dtd/ElementValidator$$anonfun$getIterable$1."<init>":(Lscala/xml/dtd/ElementValidator;Z)V
	invokeinterface	InterfaceMethod scala/collection/TraversableLike.filter:(Lscala/Function1;)Ljava/lang/Object;
	checkcast	class scala/collection/TraversableLike
	new	class scala/xml/dtd/ElementValidator$$anonfun$getIterable$2
	dup
	aload_0
	invokespecial	Method scala/xml/dtd/ElementValidator$$anonfun$getIterable$2."<init>":(Lscala/xml/dtd/ElementValidator;)V
	getstatic	Field scala/collection/Seq$.MODULE$:Lscala/collection/Seq$;
	invokevirtual	Method scala/collection/Seq$.canBuildFrom:()Lscala/collection/generic/CanBuildFrom;
	invokeinterface	InterfaceMethod scala/collection/TraversableLike.map:(Lscala/Function1;Lscala/collection/generic/CanBuildFrom;)Ljava/lang/Object;
	checkcast	class scala/collection/Iterable
	areturn
  Labels:
  LocalVariableTable: 
   Start  Length  Slot  Name   Signature
   0      41      0    this       Lscala/xml/dtd/ElementValidator;
   0      41      1    nodes       Lscala/collection/Seq;
   0      41      2    skipPCDATA$1       Z

  Signature: length = 0x2
   01 34 

public boolean check(scala.xml.MetaData);
  Signature: (Lscala/xml/MetaData;)Z
  Code:
   Stack=5, Locals=5, Args_size=2
	aload_0
	getfield	Field scala$xml$dtd$ElementValidator$$exc:Lscala/collection/immutable/List;
	invokeinterface	InterfaceMethod scala/collection/LinearSeqOptimized.length:()I
	istore	4
	new	class scala/runtime/ObjectRef
	dup
	new	class scala/collection/mutable/BitSet
	dup
	aload_0
	invokevirtual	Method adecls:()Lscala/collection/immutable/List;
	invokeinterface	InterfaceMethod scala/collection/LinearSeqOptimized.length:()I
	invokespecial	Method scala/collection/mutable/BitSet."<init>":(I)V
	invokespecial	Method scala/runtime/ObjectRef."<init>":(Ljava/lang/Object;)V
	astore_3
	aload_1
	new	class scala/xml/dtd/ElementValidator$$anonfun$check$1
	dup
	aload_0
	aload_3
	invokespecial	Method scala/xml/dtd/ElementValidator$$anonfun$check$1."<init>":(Lscala/xml/dtd/ElementValidator;Lscala/runtime/ObjectRef;)V
	invokeinterface	InterfaceMethod scala/collection/IterableLike.foreach:(Lscala/Function1;)V
	aload_0
	invokevirtual	Method adecls:()Lscala/collection/immutable/List;
	getstatic	Field scala/collection/immutable/List$.MODULE$:Lscala/collection/immutable/List$;
	astore_2
	new	class scala/collection/generic/TraversableFactory$GenericCanBuildFrom
	dup
	aload_2
	invokespecial	Method scala/collection/generic/TraversableFactory$GenericCanBuildFrom."<init>":(Lscala/collection/generic/TraversableFactory;)V
	invokeinterface	InterfaceMethod scala/collection/IterableLike.zipWithIndex:(Lscala/collection/generic/CanBuildFrom;)Ljava/lang/Object;
	checkcast	class scala/collection/LinearSeqOptimized
	new	class scala/xml/dtd/ElementValidator$$anonfun$check$2
	dup
	aload_0
	aload_3
	invokespecial	Method scala/xml/dtd/ElementValidator$$anonfun$check$2."<init>":(Lscala/xml/dtd/ElementValidator;Lscala/runtime/ObjectRef;)V
	invokeinterface	InterfaceMethod scala/collection/LinearSeqOptimized.foreach:(Lscala/Function1;)V
	aload_0
	getfield	Field scala$xml$dtd$ElementValidator$$exc:Lscala/collection/immutable/List;
	invokeinterface	InterfaceMethod scala/collection/LinearSeqOptimized.length:()I
	iload	4
	if_icmpne	l1 // iconst_0
	iconst_1
	goto	l2 // ireturn
l1	iconst_0
l2	ireturn
  Labels:
   	l1 = 106 // iconst_0
   	l2 = 107 // ireturn
  LocalVariableTable: 
   Start  Length  Slot  Name   Signature
   0      108      0    this       Lscala/xml/dtd/ElementValidator;
   0      108      1    md       Lscala/xml/MetaData;
   35      73      3    ok$1       Lscala/runtime/ObjectRef;
   11      97      4    len       I


public boolean check(scala.collection.Seq);
  Signature: (Lscala/collection/Seq;)Z
  Code:
   Stack=6, Locals=11, Args_size=2
	aload_0
	invokevirtual	Method contentModel:()Lscala/xml/dtd/ContentModel;
	astore	10
	getstatic	Field scala/xml/dtd/ANY$.MODULE$:Lscala/xml/dtd/ANY$;
	dup
	ifnonnull	l1 // aload
	pop
	aload	10
	ifnull	l2 // iconst_1
	goto	l3 // getstatic
l1	aload	10
	invokevirtual	Method java/lang/Object.equals:(Ljava/lang/Object;)Z
	ifeq	l3 // getstatic
l2	iconst_1
	goto	l4 // ireturn
l3	getstatic	Field scala/xml/dtd/EMPTY$.MODULE$:Lscala/xml/dtd/EMPTY$;
	dup
	ifnonnull	l5 // aload
	pop
	aload	10
	ifnull	l6 // aload_0
	goto	l7 // getstatic
l5	aload	10
	invokevirtual	Method java/lang/Object.equals:(Ljava/lang/Object;)Z
	ifeq	l7 // getstatic
l6	aload_0
	aload_1
	iconst_0
	invokevirtual	Method getIterable:(Lscala/collection/Seq;Z)Lscala/collection/Iterable;
	invokeinterface	InterfaceMethod scala/collection/IterableLike.isEmpty:()Z
	goto	l4 // ireturn
l7	getstatic	Field scala/xml/dtd/PCDATA$.MODULE$:Lscala/xml/dtd/PCDATA$;
	dup
	ifnonnull	l8 // aload
	pop
	aload	10
	ifnull	l9 // aload_0
	goto	l10 // aload
l8	aload	10
	invokevirtual	Method java/lang/Object.equals:(Ljava/lang/Object;)Z
	ifeq	l10 // aload
l9	aload_0
	aload_1
	iconst_1
	invokevirtual	Method getIterable:(Lscala/collection/Seq;Z)Lscala/collection/Iterable;
	invokeinterface	InterfaceMethod scala/collection/IterableLike.isEmpty:()Z
	goto	l4 // ireturn
l10	aload	10
	instanceof	class scala/xml/dtd/MIXED
	ifeq	l11 // aload
	aload	10
	checkcast	class scala/xml/dtd/MIXED
	astore_2
	aload_2
	invokevirtual	Method scala/xml/dtd/MIXED.r:()Lscala/util/regexp/Base$RegExp;
	astore_3
	aload_3
	instanceof	class scala/util/regexp/Base$Alt
	ifeq	l12 // new
	aload_3
	checkcast	class scala/util/regexp/Base$Alt
	astore	4
	getstatic	Field scala/xml/dtd/ContentModel$.MODULE$:Lscala/xml/dtd/ContentModel$;
	invokevirtual	Method scala/xml/dtd/ContentModel$.Alt:()Lscala/util/regexp/Base$Alt$;
	pop
	new	class scala/Some
	dup
	aload	4
	invokevirtual	Method scala/util/regexp/Base$Alt.rs:()Lscala/collection/Seq;
	invokespecial	Method scala/Some."<init>":(Ljava/lang/Object;)V
	astore	5
	iconst_1
	ifeq	l13 // new
	aload	5
	getfield	Field scala/Some.x:Ljava/lang/Object;
	checkcast	class scala/collection/Seq
	astore	7
	aload	7
	ifnonnull	l14 // aload
	iconst_0
	goto	l15 // ifeq
l14	aload	7
	iconst_0
	invokeinterface	InterfaceMethod scala/collection/SeqLike.lengthCompare:(I)I
	iconst_0
	if_icmplt	l16 // iconst_0
	iconst_1
	goto	l15 // ifeq
l16	iconst_0
l15	ifeq	l17 // new
	aload_0
	getfield	Field scala$xml$dtd$ElementValidator$$exc:Lscala/collection/immutable/List;
	invokeinterface	InterfaceMethod scala/collection/LinearSeqOptimized.length:()I
	istore	8
	aload_0
	aload_1
	iconst_1
	invokevirtual	Method getIterable:(Lscala/collection/Seq;Z)Lscala/collection/Iterable;
	new	class scala/xml/dtd/ElementValidator$$anonfun$check$3
	dup
	aload_0
	invokespecial	Method scala/xml/dtd/ElementValidator$$anonfun$check$3."<init>":(Lscala/xml/dtd/ElementValidator;)V
	getstatic	Field scala/collection/Iterable$.MODULE$:Lscala/collection/Iterable$;
	astore	6
	new	class scala/collection/generic/TraversableFactory$GenericCanBuildFrom
	dup
	aload	6
	invokespecial	Method scala/collection/generic/TraversableFactory$GenericCanBuildFrom."<init>":(Lscala/collection/generic/TraversableFactory;)V
	invokeinterface	InterfaceMethod scala/collection/TraversableLike.map:(Lscala/Function1;Lscala/collection/generic/CanBuildFrom;)Ljava/lang/Object;
	checkcast	class scala/collection/TraversableLike
	new	class scala/xml/dtd/ElementValidator$$anonfun$check$4
	dup
	aload_0
	aload	7
	invokespecial	Method scala/xml/dtd/ElementValidator$$anonfun$check$4."<init>":(Lscala/xml/dtd/ElementValidator;Lscala/collection/Seq;)V
	invokeinterface	InterfaceMethod scala/collection/TraversableLike.filterNot:(Lscala/Function1;)Ljava/lang/Object;
	checkcast	class scala/collection/IterableLike
	new	class scala/xml/dtd/ElementValidator$$anonfun$check$5
	dup
	aload_0
	invokespecial	Method scala/xml/dtd/ElementValidator$$anonfun$check$5."<init>":(Lscala/xml/dtd/ElementValidator;)V
	invokeinterface	InterfaceMethod scala/collection/IterableLike.foreach:(Lscala/Function1;)V
	aload_0
	getfield	Field scala$xml$dtd$ElementValidator$$exc:Lscala/collection/immutable/List;
	invokeinterface	InterfaceMethod scala/collection/LinearSeqOptimized.length:()I
	iload	8
	if_icmpne	l18 // iconst_0
	iconst_1
	goto	l4 // ireturn
l18	iconst_0
	goto	l4 // ireturn
l17	new	class scala/MatchError
	dup
	aload	10
	invokespecial	Method scala/MatchError."<init>":(Ljava/lang/Object;)V
	athrow
l13	new	class scala/MatchError
	dup
	aload	10
	invokespecial	Method scala/MatchError."<init>":(Ljava/lang/Object;)V
	athrow
l12	new	class scala/MatchError
	dup
	aload	10
	invokespecial	Method scala/MatchError."<init>":(Ljava/lang/Object;)V
	athrow
l11	aload	10
	instanceof	class scala/xml/dtd/ELEMENTS
	ifeq	l19 // new
	aload_0
	invokevirtual	Method dfa:()Lscala/util/automata/DetWordAutom;
	aload_0
	aload_1
	iconst_0
	invokevirtual	Method getIterable:(Lscala/collection/Seq;Z)Lscala/collection/Iterable;
	iconst_0
	istore	9
	iload	9
	invokestatic	Method scala/runtime/BoxesRunTime.boxToInteger:(I)Ljava/lang/Integer;
	new	class scala/xml/dtd/ElementValidator$$anonfun$check$6
	dup
	aload_0
	invokespecial	Method scala/xml/dtd/ElementValidator$$anonfun$check$6."<init>":(Lscala/xml/dtd/ElementValidator;)V
	invokeinterface	InterfaceMethod scala/collection/TraversableOnce.foldLeft:(Ljava/lang/Object;Lscala/Function2;)Ljava/lang/Object;
	invokestatic	Method scala/runtime/BoxesRunTime.unboxToInt:(Ljava/lang/Object;)I
	invokevirtual	Method scala/util/automata/DetWordAutom.isFinal:(I)Z
l4	ireturn
l19	new	class scala/MatchError
	dup
	aload	10
	invokespecial	Method scala/MatchError."<init>":(Ljava/lang/Object;)V
	athrow
  Labels:
   	l1 = 22 // aload
   	l2 = 30 // iconst_1
   	l3 = 34 // getstatic
   	l5 = 50 // aload
   	l6 = 58 // aload_0
   	l7 = 72 // getstatic
   	l8 = 88 // aload
   	l9 = 96 // aload_0
   	l10 = 110 // aload
   	l14 = 186 // aload
   	l16 = 202 // iconst_0
   	l15 = 203 // ifeq
   	l18 = 302 // iconst_0
   	l17 = 306 // new
   	l13 = 316 // new
   	l12 = 326 // new
   	l11 = 336 // aload
   	l4 = 381 // ireturn
   	l19 = 382 // new
  LocalVariableTable: 
   Start  Length  Slot  Name   Signature
   0      392      0    this       Lscala/xml/dtd/ElementValidator;
   0      392      1    nodes       Lscala/collection/Seq;
   124      212      2    temp46       Lscala/xml/dtd/MIXED;
   129      207      3    temp47       Lscala/util/regexp/Base$RegExp;
   142      184      4    temp48       Lscala/util/regexp/Base$Alt;
   163      163      5    temp49       Lscala/Some;
   177      139      7    temp50       Lscala/collection/Seq;
   217      89      8    j       I
   6      386      10    temp42       Lscala/xml/dtd/ContentModel;

  Signature: length = 0x2
   01 FFFFFFE0 

public boolean apply(scala.xml.Node);
  Signature: (Lscala/xml/Node;)Z
  Code:
   Stack=2, Locals=2, Args_size=2
	aload_0
	invokevirtual	Method contentModel:()Lscala/xml/dtd/ContentModel;
	ifnull	l1 // aload_0
	aload_0
	aload_1
	invokevirtual	Method scala/xml/Node.child:()Lscala/collection/Seq;
	invokevirtual	Method check:(Lscala/collection/Seq;)Z
	ifeq	l2 // iconst_0
l1	aload_0
	invokevirtual	Method adecls:()Lscala/collection/immutable/List;
	ifnull	l3 // iconst_1
	aload_0
	aload_1
	invokevirtual	Method scala/xml/Node.attributes:()Lscala/xml/MetaData;
	invokevirtual	Method check:(Lscala/xml/MetaData;)Z
	ifeq	l2 // iconst_0
l3	iconst_1
	goto	l4 // ireturn
l2	iconst_0
l4	ireturn
  Labels:
   	l1 = 18 // aload_0
   	l3 = 36 // iconst_1
   	l2 = 40 // iconst_0
   	l4 = 41 // ireturn
  LocalVariableTable: 
   Start  Length  Slot  Name   Signature
   0      42      0    this       Lscala/xml/dtd/ElementValidator;
   0      42      1    n       Lscala/xml/Node;


public java.lang.Object apply(java.lang.Object);
  Signature: (Ljava/lang/Object;)Ljava/lang/Object;
  Code:
   Stack=2, Locals=3, Args_size=2
	aload_0
	aload_1
	checkcast	class scala/xml/Node
	invokevirtual	Method apply:(Lscala/xml/Node;)Z
	istore_2
	iload_2
	invokestatic	Method scala/runtime/BoxesRunTime.boxToBoolean:(Z)Ljava/lang/Boolean;
	areturn
  Labels:
  LocalVariableTable: 
   Start  Length  Slot  Name   Signature
   0      14      0    this       Lscala/xml/dtd/ElementValidator;
   0      14      1    v1       Ljava/lang/Object;


public final boolean isAllWhitespace$1(scala.xml.Atom);
  Signature: (Lscala/xml/Atom;)Z
  Code:
   Stack=5, Locals=2, Args_size=2
	getstatic	Field scala/PartialFunction$.MODULE$:Lscala/PartialFunction$;
	aload_1
	invokevirtual	Method scala/xml/Atom.data:()Ljava/lang/Object;
	new	class scala/xml/dtd/ElementValidator$$anonfun$isAllWhitespace$1$1
	dup
	aload_0
	invokespecial	Method scala/xml/dtd/ElementValidator$$anonfun$isAllWhitespace$1$1."<init>":(Lscala/xml/dtd/ElementValidator;)V
	invokevirtual	Method scala/PartialFunction$.cond:(Ljava/lang/Object;Lscala/PartialFunction;)Z
	ireturn
  Labels:
  LocalVariableTable: 
   Start  Length  Slot  Name   Signature
   0      19      0    this       Lscala/xml/dtd/ElementValidator;
   0      19      1    a       Lscala/xml/Atom;


public final boolean find$2(java.lang.String, scala.collection.Seq);
  Signature: (Ljava/lang/String;Lscala/collection/Seq;)Z
  Code:
   Stack=5, Locals=3, Args_size=3
	aload_2
	new	class scala/xml/dtd/ElementValidator$$anonfun$find$2$1
	dup
	aload_0
	aload_1
	invokespecial	Method scala/xml/dtd/ElementValidator$$anonfun$find$2$1."<init>":(Lscala/xml/dtd/ElementValidator;Ljava/lang/String;)V
	invokeinterface	InterfaceMethod scala/collection/IterableLike.exists:(Lscala/Function1;)Z
	ireturn
  Labels:
  LocalVariableTable: 
   Start  Length  Slot  Name   Signature
   0      16      0    this       Lscala/xml/dtd/ElementValidator;
   0      16      1    Key$2       Ljava/lang/String;


public scala.xml.dtd.ElementValidator();
  Signature: ()V
  Code:
   Stack=2, Locals=1, Args_size=1
	aload_0
	invokespecial	Method java/lang/Object."<init>":()V
	aload_0
	invokestatic	Method scala/Function1$class.$init$:(Lscala/Function1;)V
	aload_0
	getstatic	Field scala/collection/immutable/Nil$.MODULE$:Lscala/collection/immutable/Nil$;
	putfield	Field scala$xml$dtd$ElementValidator$$exc:Lscala/collection/immutable/List;
	return
  Labels:

}

