Compiled from "ElementValidator.scala"
public final class scala.xml.dtd.ElementValidator$$anonfun$find$2$1 extends scala.runtime.AbstractFunction1 implements java.io.Serializable
  SourceFile: "ElementValidator.scala"
  Scala: length = 0x
   
  InnerClass: 
   public abstract RegExp=class scala/util/regexp/Base$RegExp of class scala/util/regexp/Base
   public abstract Label=class scala/util/regexp/WordExp$Label of class scala/util/regexp/WordExp
   public Letter=class scala/util/regexp/WordExp$Letter of class scala/util/regexp/WordExp
   public ElemName=class scala/xml/dtd/ContentModel$ElemName of class scala/xml/dtd/ContentModel
   public final $anonfun$find$2$1=class scala/xml/dtd/ElementValidator$$anonfun$find$2$1 of class scala/xml/dtd/ElementValidator
  minor version: 0
  major version: 49
  Constant pool:
Asciz	SourceFile;
Asciz	ElementValidator.scala;
Asciz	<clinit>;
Asciz	()V;
Asciz	Code;
Asciz	serialVersionUID;
Asciz	J;
Asciz	scala/xml/dtd/ElementValidator$$anonfun$find$2$1;
class	scala/xml/dtd/ElementValidator$$anonfun$find$2$1
NameAndType	serialVersionUID:J
Field	scala/xml/dtd/ElementValidator$$anonfun$find$2$1.serialVersionUID:J
Asciz	Key$2;
Asciz	Ljava/lang/String;;
Asciz	<init>;
Asciz	(Lscala/xml/dtd/ElementValidator;Ljava/lang/String;)V;
Asciz	LineNumberTable;
NameAndType	Key$2:Ljava/lang/String;
Field	scala/xml/dtd/ElementValidator$$anonfun$find$2$1.Key$2:Ljava/lang/String;
Asciz	scala/runtime/AbstractFunction1;
class	scala/runtime/AbstractFunction1
NameAndType	"<init>":()V
Method	scala/runtime/AbstractFunction1."<init>":()V
Asciz	this;
Asciz	Lscala/xml/dtd/ElementValidator$$anonfun$find$2$1;;
Asciz	$outer;
Asciz	Lscala/xml/dtd/ElementValidator;;
Asciz	LocalVariableTable;
Asciz	apply;
Asciz	(Ljava/lang/Object;)Ljava/lang/Object;;
Asciz	scala/util/regexp/Base$RegExp;
class	scala/util/regexp/Base$RegExp
Asciz	(Lscala/util/regexp/Base$RegExp;)Z;
NameAndType	apply:(Lscala/util/regexp/Base$RegExp;)Z
Method	scala/xml/dtd/ElementValidator$$anonfun$find$2$1.apply:(Lscala/util/regexp/Base$RegExp;)Z
Asciz	scala/runtime/BoxesRunTime;
class	scala/runtime/BoxesRunTime
Asciz	boxToBoolean;
Asciz	(Z)Ljava/lang/Boolean;;
NameAndType	boxToBoolean:(Z)Ljava/lang/Boolean;
Method	scala/runtime/BoxesRunTime.boxToBoolean:(Z)Ljava/lang/Boolean;
Asciz	v1;
Asciz	Ljava/lang/Object;;
Asciz	scala/util/regexp/WordExp$Letter;
class	scala/util/regexp/WordExp$Letter
Asciz	a;
Asciz	()Lscala/util/regexp/WordExp$Label;;
NameAndType	a:()Lscala/util/regexp/WordExp$Label;
Method	scala/util/regexp/WordExp$Letter.a:()Lscala/util/regexp/WordExp$Label;
Asciz	scala/xml/dtd/ContentModel$ElemName;
class	scala/xml/dtd/ContentModel$ElemName
Asciz	name;
Asciz	()Ljava/lang/String;;
NameAndType	name:()Ljava/lang/String;
Method	scala/xml/dtd/ContentModel$ElemName.name:()Ljava/lang/String;
Asciz	java/lang/Object;
class	java/lang/Object
Asciz	equals;
Asciz	(Ljava/lang/Object;)Z;
NameAndType	equals:(Ljava/lang/Object;)Z
Method	java/lang/Object.equals:(Ljava/lang/Object;)Z
Asciz	scala/MatchError;
class	scala/MatchError
Asciz	toString;
NameAndType	toString:()Ljava/lang/String;
Method	scala/util/regexp/Base$RegExp.toString:()Ljava/lang/String;
Asciz	(Ljava/lang/String;)V;
NameAndType	"<init>":(Ljava/lang/String;)V
Method	scala/MatchError."<init>":(Ljava/lang/String;)V
Asciz	temp38;
Asciz	Lscala/util/regexp/WordExp$Letter;;
Asciz	temp39;
Asciz	Lscala/xml/dtd/ContentModel$ElemName;;
Asciz	Scala;
Asciz	InnerClasses;
Asciz	scala/util/regexp/Base;
class	scala/util/regexp/Base
Asciz	RegExp;
Asciz	scala/util/regexp/WordExp$Label;
class	scala/util/regexp/WordExp$Label
Asciz	scala/util/regexp/WordExp;
class	scala/util/regexp/WordExp
Asciz	Label;
Asciz	Letter;
Asciz	scala/xml/dtd/ContentModel;
class	scala/xml/dtd/ContentModel
Asciz	ElemName;
Asciz	scala/xml/dtd/ElementValidator;
class	scala/xml/dtd/ElementValidator
Asciz	$anonfun$find$2$1;
Asciz	java/io/Serializable;
class	java/io/Serializable

{
public static final long serialVersionUID;
  Signature: J

public final java.lang.String Key$2;
  Signature: Ljava/lang/String;

public static {};
  Signature: ()V
  Code:
   Stack=2, Locals=0, Args_size=0
	lconst_0
	putstatic	Field serialVersionUID:J
	return
  Labels:

public scala.xml.dtd.ElementValidator$$anonfun$find$2$1(scala.xml.dtd.ElementValidator, java.lang.String);
  Signature: (Lscala/xml/dtd/ElementValidator;Ljava/lang/String;)V
  Code:
   Stack=2, Locals=3, Args_size=3
	aload_0
	aload_2
	putfield	Field Key$2:Ljava/lang/String;
	aload_0
	invokespecial	Method scala/runtime/AbstractFunction1."<init>":()V
	return
  Labels:
  LocalVariableTable: 
   Start  Length  Slot  Name   Signature
   0      10      0    this       Lscala/xml/dtd/ElementValidator$$anonfun$find$2$1;
   0      10      1    $outer       Lscala/xml/dtd/ElementValidator;


public final java.lang.Object apply(java.lang.Object);
  Signature: (Ljava/lang/Object;)Ljava/lang/Object;
  Code:
   Stack=2, Locals=3, Args_size=2
	aload_0
	aload_1
	checkcast	class scala/util/regexp/Base$RegExp
	invokevirtual	Method apply:(Lscala/util/regexp/Base$RegExp;)Z
	istore_2
	iload_2
	invokestatic	Method scala/runtime/BoxesRunTime.boxToBoolean:(Z)Ljava/lang/Boolean;
	areturn
  Labels:
  LocalVariableTable: 
   Start  Length  Slot  Name   Signature
   0      14      0    this       Lscala/xml/dtd/ElementValidator$$anonfun$find$2$1;
   0      14      1    v1       Ljava/lang/Object;


public final boolean apply(scala.util.regexp.Base$RegExp);
  Signature: (Lscala/util/regexp/Base$RegExp;)Z
  Code:
   Stack=3, Locals=5, Args_size=2
	aload_1
	instanceof	class scala/util/regexp/WordExp$Letter
	ifeq	l1 // iconst_1
	aload_1
	checkcast	class scala/util/regexp/WordExp$Letter
	astore_2
	aload_2
	invokevirtual	Method scala/util/regexp/WordExp$Letter.a:()Lscala/util/regexp/WordExp$Label;
	checkcast	class scala/xml/dtd/ContentModel$ElemName
	astore_3
	aload_3
	ifnull	l2 // iconst_1
	aload_0
	getfield	Field Key$2:Ljava/lang/String;
	aload_3
	invokevirtual	Method scala/xml/dtd/ContentModel$ElemName.name:()Ljava/lang/String;
	astore	4
	dup
	ifnonnull	l3 // aload
	pop
	aload	4
	ifnull	l4 // iconst_1
	goto	l5 // iconst_1
l3	aload	4
	invokevirtual	Method java/lang/Object.equals:(Ljava/lang/Object;)Z
	ifeq	l5 // iconst_1
l4	iconst_1
	ifeq	l6 // new
	iconst_1
	goto	l7 // ireturn
l6	new	class scala/MatchError
	dup
	aload_1
	invokevirtual	Method scala/util/regexp/Base$RegExp.toString:()Ljava/lang/String;
	invokespecial	Method scala/MatchError."<init>":(Ljava/lang/String;)V
	athrow
l5	iconst_1
	ifeq	l8 // new
	iconst_0
	goto	l7 // ireturn
l8	new	class scala/MatchError
	dup
	aload_1
	invokevirtual	Method scala/util/regexp/Base$RegExp.toString:()Ljava/lang/String;
	invokespecial	Method scala/MatchError."<init>":(Ljava/lang/String;)V
	athrow
l2	iconst_1
	ifeq	l9 // new
	iconst_0
	goto	l7 // ireturn
l9	new	class scala/MatchError
	dup
	aload_1
	invokevirtual	Method scala/util/regexp/Base$RegExp.toString:()Ljava/lang/String;
	invokespecial	Method scala/MatchError."<init>":(Ljava/lang/String;)V
	athrow
l1	iconst_1
	ifeq	l10 // new
	iconst_0
l7	ireturn
l10	new	class scala/MatchError
	dup
	aload_1
	invokevirtual	Method scala/util/regexp/Base$RegExp.toString:()Ljava/lang/String;
	invokespecial	Method scala/MatchError."<init>":(Ljava/lang/String;)V
	athrow
  Labels:
   	l3 = 47 // aload
   	l4 = 55 // iconst_1
   	l6 = 63 // new
   	l5 = 75 // iconst_1
   	l8 = 83 // new
   	l2 = 95 // iconst_1
   	l9 = 103 // new
   	l1 = 115 // iconst_1
   	l7 = 120 // ireturn
   	l10 = 121 // new
  LocalVariableTable: 
   Start  Length  Slot  Name   Signature
   0      133      0    this       Lscala/xml/dtd/ElementValidator$$anonfun$find$2$1;
   12      103      2    temp38       Lscala/util/regexp/WordExp$Letter;
   20      95      3    temp39       Lscala/xml/dtd/ContentModel$ElemName;


}

