Compiled from "ElementValidator.scala"
public final class scala.xml.dtd.ElementValidator$$anonfun$check$1$$anonfun$find$1$1 extends java.lang.Object implements scala.Function1,scala.ScalaObject,java.io.Serializable
  SourceFile: "ElementValidator.scala"
  Scala: length = 0x
   
  InnerClass: 
   public final $anonfun$check$1=class scala/xml/dtd/ElementValidator$$anonfun$check$1 of class scala/xml/dtd/ElementValidator
   public final $anonfun$find$1$1=class scala/xml/dtd/ElementValidator$$anonfun$check$1$$anonfun$find$1$1 of class scala/xml/dtd/ElementValidator$$anonfun$check$1
  minor version: 0
  major version: 49
  Constant pool:
Asciz	SourceFile;
Asciz	ElementValidator.scala;
Asciz	<clinit>;
Asciz	()V;
Asciz	Code;
Asciz	serialVersionUID;
Asciz	J;
Asciz	scala/xml/dtd/ElementValidator$$anonfun$check$1$$anonfun$find$1$1;
class	scala/xml/dtd/ElementValidator$$anonfun$check$1$$anonfun$find$1$1
NameAndType	serialVersionUID:J
Field	scala/xml/dtd/ElementValidator$$anonfun$check$1$$anonfun$find$1$1.serialVersionUID:J
Asciz	nonLocalReturnKey1$1;
Asciz	Ljava/lang/Object;;
Asciz	Key$1;
Asciz	Ljava/lang/String;;
Asciz	$outer;
Asciz	Lscala/xml/dtd/ElementValidator$$anonfun$check$1;;
Asciz	<init>;
Asciz	(Lscala/xml/dtd/ElementValidator$$anonfun$check$1;Ljava/lang/String;Ljava/lang/Object;)V;
Asciz	LineNumberTable;
Asciz	java/lang/NullPointerException;
class	java/lang/NullPointerException
NameAndType	"<init>":()V
Method	java/lang/NullPointerException."<init>":()V
NameAndType	$outer:Lscala/xml/dtd/ElementValidator$$anonfun$check$1;
Field	scala/xml/dtd/ElementValidator$$anonfun$check$1$$anonfun$find$1$1.$outer:Lscala/xml/dtd/ElementValidator$$anonfun$check$1;
NameAndType	Key$1:Ljava/lang/String;
Field	scala/xml/dtd/ElementValidator$$anonfun$check$1$$anonfun$find$1$1.Key$1:Ljava/lang/String;
NameAndType	nonLocalReturnKey1$1:Ljava/lang/Object;
Field	scala/xml/dtd/ElementValidator$$anonfun$check$1$$anonfun$find$1$1.nonLocalReturnKey1$1:Ljava/lang/Object;
Asciz	java/lang/Object;
class	java/lang/Object
Method	java/lang/Object."<init>":()V
Asciz	scala/Function1$class;
class	scala/Function1$class
Asciz	$init$;
Asciz	(Lscala/Function1;)V;
NameAndType	$init$:(Lscala/Function1;)V
Method	scala/Function1$class.$init$:(Lscala/Function1;)V
Asciz	this;
Asciz	Lscala/xml/dtd/ElementValidator$$anonfun$check$1$$anonfun$find$1$1;;
Asciz	LocalVariableTable;
Asciz	apply;
Asciz	(Ljava/lang/Object;)Ljava/lang/Object;;
Asciz	scala/Tuple2;
class	scala/Tuple2
Asciz	(Lscala/Tuple2;)Z;
NameAndType	apply:(Lscala/Tuple2;)Z
Method	scala/xml/dtd/ElementValidator$$anonfun$check$1$$anonfun$find$1$1.apply:(Lscala/Tuple2;)Z
Asciz	scala/runtime/BoxesRunTime;
class	scala/runtime/BoxesRunTime
Asciz	boxToBoolean;
Asciz	(Z)Ljava/lang/Boolean;;
NameAndType	boxToBoolean:(Z)Ljava/lang/Boolean;
Method	scala/runtime/BoxesRunTime.boxToBoolean:(Z)Ljava/lang/Boolean;
Asciz	v1;
Asciz	_1;
Asciz	()Ljava/lang/Object;;
NameAndType	_1:()Ljava/lang/Object;
Method	scala/Tuple2._1:()Ljava/lang/Object;
Asciz	scala/xml/dtd/AttrDecl;
class	scala/xml/dtd/AttrDecl
Asciz	_2;
NameAndType	_2:()Ljava/lang/Object;
Method	scala/Tuple2._2:()Ljava/lang/Object;
Asciz	unboxToInt;
Asciz	(Ljava/lang/Object;)I;
NameAndType	unboxToInt:(Ljava/lang/Object;)I
Method	scala/runtime/BoxesRunTime.unboxToInt:(Ljava/lang/Object;)I
Asciz	name;
Asciz	()Ljava/lang/String;;
NameAndType	name:()Ljava/lang/String;
Method	scala/xml/dtd/AttrDecl.name:()Ljava/lang/String;
Asciz	equals;
Asciz	(Ljava/lang/Object;)Z;
NameAndType	equals:(Ljava/lang/Object;)Z
Method	java/lang/Object.equals:(Ljava/lang/Object;)Z
Asciz	scala/xml/dtd/ElementValidator$$anonfun$check$1;
class	scala/xml/dtd/ElementValidator$$anonfun$check$1
Asciz	ok$1;
Asciz	Lscala/runtime/ObjectRef;;
NameAndType	ok$1:Lscala/runtime/ObjectRef;
Field	scala/xml/dtd/ElementValidator$$anonfun$check$1.ok$1:Lscala/runtime/ObjectRef;
Asciz	scala/runtime/ObjectRef;
class	scala/runtime/ObjectRef
Asciz	elem;
NameAndType	elem:Ljava/lang/Object;
Field	scala/runtime/ObjectRef.elem:Ljava/lang/Object;
Asciz	scala/collection/mutable/BitSet;
class	scala/collection/mutable/BitSet
Asciz	$plus$eq;
Asciz	(I)Lscala/collection/mutable/BitSet;;
NameAndType	$plus$eq:(I)Lscala/collection/mutable/BitSet;
Method	scala/collection/mutable/BitSet.$plus$eq:(I)Lscala/collection/mutable/BitSet;
Asciz	scala/runtime/NonLocalReturnException;
class	scala/runtime/NonLocalReturnException
Asciz	scala/Some;
class	scala/Some
Asciz	(Ljava/lang/Object;)V;
NameAndType	"<init>":(Ljava/lang/Object;)V
Method	scala/Some."<init>":(Ljava/lang/Object;)V
Asciz	(Ljava/lang/Object;Ljava/lang/Object;)V;
NameAndType	"<init>":(Ljava/lang/Object;Ljava/lang/Object;)V
Method	scala/runtime/NonLocalReturnException."<init>":(Ljava/lang/Object;Ljava/lang/Object;)V
Asciz	scala/MatchError;
class	scala/MatchError
Asciz	toString;
NameAndType	toString:()Ljava/lang/String;
Method	scala/Tuple2.toString:()Ljava/lang/String;
Asciz	(Ljava/lang/String;)V;
NameAndType	"<init>":(Ljava/lang/String;)V
Method	scala/MatchError."<init>":(Ljava/lang/String;)V
Asciz	temp14;
Asciz	I;
Asciz	temp13;
Asciz	Lscala/xml/dtd/AttrDecl;;
Asciz	(Lscala/Tuple2<Lscala/xml/dtd/AttrDecl;Ljava/lang/Integer;>;)Z;
Asciz	Signature;
Asciz	andThen;
Asciz	(Lscala/Function1;)Lscala/Function1;;
Asciz	(Lscala/Function1;Lscala/Function1;)Lscala/Function1;;
NameAndType	andThen:(Lscala/Function1;Lscala/Function1;)Lscala/Function1;
Method	scala/Function1$class.andThen:(Lscala/Function1;Lscala/Function1;)Lscala/Function1;
Asciz	g;
Asciz	Lscala/Function1;;
Asciz	compose;
NameAndType	compose:(Lscala/Function1;Lscala/Function1;)Lscala/Function1;
Method	scala/Function1$class.compose:(Lscala/Function1;Lscala/Function1;)Lscala/Function1;
Asciz	(Lscala/Function1;)Ljava/lang/String;;
NameAndType	toString:(Lscala/Function1;)Ljava/lang/String;
Method	scala/Function1$class.toString:(Lscala/Function1;)Ljava/lang/String;
Asciz	Scala;
Asciz	InnerClasses;
Asciz	scala/xml/dtd/ElementValidator;
class	scala/xml/dtd/ElementValidator
Asciz	$anonfun$check$1;
Asciz	$anonfun$find$1$1;
Asciz	scala/Function1;
class	scala/Function1
Asciz	scala/ScalaObject;
class	scala/ScalaObject
Asciz	java/io/Serializable;
class	java/io/Serializable

{
public static final long serialVersionUID;
  Signature: J

private final java.lang.Object nonLocalReturnKey1$1;
  Signature: Ljava/lang/Object;

private final java.lang.String Key$1;
  Signature: Ljava/lang/String;

private final scala.xml.dtd.ElementValidator$$anonfun$check$1 $outer;
  Signature: Lscala/xml/dtd/ElementValidator$$anonfun$check$1;

public static {};
  Signature: ()V
  Code:
   Stack=2, Locals=0, Args_size=0
	lconst_0
	putstatic	Field serialVersionUID:J
	return
  Labels:

public scala.xml.dtd.ElementValidator$$anonfun$check$1$$anonfun$find$1$1(scala.xml.dtd.ElementValidator$$anonfun$check$1, java.lang.String, java.lang.Object);
  Signature: (Lscala/xml/dtd/ElementValidator$$anonfun$check$1;Ljava/lang/String;Ljava/lang/Object;)V
  Code:
   Stack=2, Locals=4, Args_size=4
	aload_1
	ifnonnull	l1 // aload_0
	new	class java/lang/NullPointerException
	dup
	invokespecial	Method java/lang/NullPointerException."<init>":()V
	athrow
l1	aload_0
	aload_1
	putfield	Field $outer:Lscala/xml/dtd/ElementValidator$$anonfun$check$1;
	aload_0
	aload_2
	putfield	Field Key$1:Ljava/lang/String;
	aload_0
	aload_3
	putfield	Field nonLocalReturnKey1$1:Ljava/lang/Object;
	aload_0
	invokespecial	Method java/lang/Object."<init>":()V
	aload_0
	invokestatic	Method scala/Function1$class.$init$:(Lscala/Function1;)V
	return
  Labels:
   	l1 = 12 // aload_0
  LocalVariableTable: 
   Start  Length  Slot  Name   Signature
   0      36      0    this       Lscala/xml/dtd/ElementValidator$$anonfun$check$1$$anonfun$find$1$1;
   0      36      1    $outer       Lscala/xml/dtd/ElementValidator$$anonfun$check$1;


public final java.lang.Object apply(java.lang.Object);
  Signature: (Ljava/lang/Object;)Ljava/lang/Object;
  Code:
   Stack=2, Locals=4, Args_size=2
	aload_0
	getfield	Field $outer:Lscala/xml/dtd/ElementValidator$$anonfun$check$1;
	astore_3
	aload_0
	aload_1
	checkcast	class scala/Tuple2
	invokevirtual	Method apply:(Lscala/Tuple2;)Z
	istore_2
	iload_2
	invokestatic	Method scala/runtime/BoxesRunTime.boxToBoolean:(Z)Ljava/lang/Boolean;
	areturn
  Labels:
  LocalVariableTable: 
   Start  Length  Slot  Name   Signature
   0      19      0    this       Lscala/xml/dtd/ElementValidator$$anonfun$check$1$$anonfun$find$1$1;
   5      14      1    v1       Ljava/lang/Object;


public final boolean apply(scala.Tuple2);
  Signature: (Lscala/Tuple2;)Z
  Code:
   Stack=6, Locals=6, Args_size=2
	aload_0
	getfield	Field $outer:Lscala/xml/dtd/ElementValidator$$anonfun$check$1;
	astore	5
	aload_1
	ifnull	l1 // iconst_1
	aload_1
	invokevirtual	Method scala/Tuple2._1:()Ljava/lang/Object;
	checkcast	class scala/xml/dtd/AttrDecl
	astore	4
	aload_1
	invokevirtual	Method scala/Tuple2._2:()Ljava/lang/Object;
	invokestatic	Method scala/runtime/BoxesRunTime.unboxToInt:(Ljava/lang/Object;)I
	istore_3
	aload	4
	ifnull	l2 // iconst_1
	aload_0
	getfield	Field Key$1:Ljava/lang/String;
	aload	4
	invokevirtual	Method scala/xml/dtd/AttrDecl.name:()Ljava/lang/String;
	astore_2
	dup
	ifnonnull	l3 // aload_2
	pop
	aload_2
	ifnull	l4 // iconst_1
	goto	l5 // iconst_1
l3	aload_2
	invokevirtual	Method java/lang/Object.equals:(Ljava/lang/Object;)Z
	ifeq	l5 // iconst_1
l4	iconst_1
	ifeq	l6 // new
	aload_0
	getfield	Field $outer:Lscala/xml/dtd/ElementValidator$$anonfun$check$1;
	getfield	Field scala/xml/dtd/ElementValidator$$anonfun$check$1.ok$1:Lscala/runtime/ObjectRef;
	getfield	Field scala/runtime/ObjectRef.elem:Ljava/lang/Object;
	checkcast	class scala/collection/mutable/BitSet
	iload_3
	invokevirtual	Method scala/collection/mutable/BitSet.$plus$eq:(I)Lscala/collection/mutable/BitSet;
	pop
	new	class scala/runtime/NonLocalReturnException
	dup
	aload_0
	getfield	Field nonLocalReturnKey1$1:Ljava/lang/Object;
	new	class scala/Some
	dup
	aload	4
	invokespecial	Method scala/Some."<init>":(Ljava/lang/Object;)V
	invokespecial	Method scala/runtime/NonLocalReturnException."<init>":(Ljava/lang/Object;Ljava/lang/Object;)V
	athrow
l6	new	class scala/MatchError
	dup
	aload_1
	invokevirtual	Method scala/Tuple2.toString:()Ljava/lang/String;
	invokespecial	Method scala/MatchError."<init>":(Ljava/lang/String;)V
	athrow
l5	iconst_1
	ifeq	l7 // new
	iconst_0
	goto	l8 // ireturn
l7	new	class scala/MatchError
	dup
	aload_1
	invokevirtual	Method scala/Tuple2.toString:()Ljava/lang/String;
	invokespecial	Method scala/MatchError."<init>":(Ljava/lang/String;)V
	athrow
l2	iconst_1
	ifeq	l9 // new
	iconst_0
	goto	l8 // ireturn
l9	new	class scala/MatchError
	dup
	aload_1
	invokevirtual	Method scala/Tuple2.toString:()Ljava/lang/String;
	invokespecial	Method scala/MatchError."<init>":(Ljava/lang/String;)V
	athrow
l1	iconst_1
	ifeq	l10 // new
	iconst_0
l8	ireturn
l10	new	class scala/MatchError
	dup
	aload_1
	invokevirtual	Method scala/Tuple2.toString:()Ljava/lang/String;
	invokespecial	Method scala/MatchError."<init>":(Ljava/lang/String;)V
	athrow
  Labels:
   	l3 = 54 // aload_2
   	l4 = 61 // iconst_1
   	l6 = 104 // new
   	l5 = 116 // iconst_1
   	l7 = 124 // new
   	l2 = 136 // iconst_1
   	l9 = 144 // new
   	l1 = 156 // iconst_1
   	l8 = 161 // ireturn
   	l10 = 162 // new
  LocalVariableTable: 
   Start  Length  Slot  Name   Signature
   0      174      0    this       Lscala/xml/dtd/ElementValidator$$anonfun$check$1$$anonfun$find$1$1;
   27      129      3    temp14       I
   19      137      4    temp13       Lscala/xml/dtd/AttrDecl;

  Signature: length = 0x2
   00 75 

public scala.Function1 andThen(scala.Function1);
  Signature: (Lscala/Function1;)Lscala/Function1;
  Code:
   Stack=2, Locals=2, Args_size=2
	aload_0
	aload_1
	invokestatic	Method scala/Function1$class.andThen:(Lscala/Function1;Lscala/Function1;)Lscala/Function1;
	areturn
  Labels:
  LocalVariableTable: 
   Start  Length  Slot  Name   Signature
   0      6      0    this       Lscala/xml/dtd/ElementValidator$$anonfun$check$1$$anonfun$find$1$1;
   0      6      1    g       Lscala/Function1;


public scala.Function1 compose(scala.Function1);
  Signature: (Lscala/Function1;)Lscala/Function1;
  Code:
   Stack=2, Locals=2, Args_size=2
	aload_0
	aload_1
	invokestatic	Method scala/Function1$class.compose:(Lscala/Function1;Lscala/Function1;)Lscala/Function1;
	areturn
  Labels:
  LocalVariableTable: 
   Start  Length  Slot  Name   Signature
   0      6      0    this       Lscala/xml/dtd/ElementValidator$$anonfun$check$1$$anonfun$find$1$1;
   0      6      1    g       Lscala/Function1;


public java.lang.String toString();
  Signature: ()Ljava/lang/String;
  Code:
   Stack=1, Locals=1, Args_size=1
	aload_0
	invokestatic	Method scala/Function1$class.toString:(Lscala/Function1;)Ljava/lang/String;
	areturn
  Labels:

}

