Compiled from "ElementValidator.scala"
public final class scala.xml.dtd.ElementValidator$$anonfun$check$6$$anonfun$apply$1 extends java.lang.Object implements scala.Function0,scala.ScalaObject,java.io.Serializable
  SourceFile: "ElementValidator.scala"
  Scala: length = 0x
   
  InnerClass: 
   public #77= #74 of #76; //ElemName=class scala/xml/dtd/ContentModel$ElemName of class scala/xml/dtd/ContentModel
   public final #82= #79 of #81; //$anonfun$check$6=class scala/xml/dtd/ElementValidator$$anonfun$check$6 of class scala/xml/dtd/ElementValidator
   public final #83= #9 of #79; //$anonfun$apply$1=class scala/xml/dtd/ElementValidator$$anonfun$check$6$$anonfun$apply$1 of class scala/xml/dtd/ElementValidator$$anonfun$check$6
  minor version: 0
  major version: 49
  Constant pool:
const #1 = Asciz	SourceFile;
const #2 = Asciz	ElementValidator.scala;
const #3 = Asciz	<clinit>;
const #4 = Asciz	()V;
const #5 = Asciz	Code;
const #6 = Asciz	serialVersionUID;
const #7 = Asciz	J;
const #8 = Asciz	scala/xml/dtd/ElementValidator$$anonfun$check$6$$anonfun$apply$1;
const #9 = class	#8;	//  scala/xml/dtd/ElementValidator$$anonfun$check$6$$anonfun$apply$1
const #10 = NameAndType	#6:#7;//  serialVersionUID:J
const #11 = Field	#9.#10;	//  scala/xml/dtd/ElementValidator$$anonfun$check$6$$anonfun$apply$1.serialVersionUID:J
const #12 = Asciz	e$1;
const #13 = Asciz	Lscala/xml/dtd/ContentModel$ElemName;;
const #14 = Asciz	<init>;
const #15 = Asciz	(Lscala/xml/dtd/ElementValidator$$anonfun$check$6;Lscala/xml/dtd/ContentModel$ElemName;)V;
const #16 = Asciz	LineNumberTable;
const #17 = NameAndType	#12:#13;//  e$1:Lscala/xml/dtd/ContentModel$ElemName;
const #18 = Field	#9.#17;	//  scala/xml/dtd/ElementValidator$$anonfun$check$6$$anonfun$apply$1.e$1:Lscala/xml/dtd/ContentModel$ElemName;
const #19 = Asciz	java/lang/Object;
const #20 = class	#19;	//  java/lang/Object
const #21 = NameAndType	#14:#4;//  "<init>":()V
const #22 = Method	#20.#21;	//  java/lang/Object."<init>":()V
const #23 = Asciz	scala/Function0$class;
const #24 = class	#23;	//  scala/Function0$class
const #25 = Asciz	$init$;
const #26 = Asciz	(Lscala/Function0;)V;
const #27 = NameAndType	#25:#26;//  $init$:(Lscala/Function0;)V
const #28 = Method	#24.#27;	//  scala/Function0$class.$init$:(Lscala/Function0;)V
const #29 = Asciz	this;
const #30 = Asciz	Lscala/xml/dtd/ElementValidator$$anonfun$check$6$$anonfun$apply$1;;
const #31 = Asciz	$outer;
const #32 = Asciz	Lscala/xml/dtd/ElementValidator$$anonfun$check$6;;
const #33 = Asciz	LocalVariableTable;
const #34 = Asciz	apply;
const #35 = Asciz	()Ljava/lang/Object;;
const #36 = Asciz	()Lscala/runtime/Nothing$;;
const #37 = NameAndType	#34:#36;//  apply:()Lscala/runtime/Nothing$;
const #38 = Method	#9.#37;	//  scala/xml/dtd/ElementValidator$$anonfun$check$6$$anonfun$apply$1.apply:()Lscala/runtime/Nothing$;
const #39 = Asciz	scala/xml/dtd/ValidationException;
const #40 = class	#39;	//  scala/xml/dtd/ValidationException
const #41 = Asciz	scala/Predef$;
const #42 = class	#41;	//  scala/Predef$
const #43 = Asciz	MODULE$;
const #44 = Asciz	Lscala/Predef$;;
const #45 = NameAndType	#43:#44;//  MODULE$:Lscala/Predef$;
const #46 = Field	#42.#45;	//  scala/Predef$.MODULE$:Lscala/Predef$;
const #47 = Asciz	element %s not allowed here;
const #48 = String	#47;	//  element %s not allowed here
const #49 = Asciz	augmentString;
const #50 = Asciz	(Ljava/lang/String;)Lscala/collection/immutable/StringOps;;
const #51 = NameAndType	#49:#50;//  augmentString:(Ljava/lang/String;)Lscala/collection/immutable/StringOps;
const #52 = Method	#42.#51;	//  scala/Predef$.augmentString:(Ljava/lang/String;)Lscala/collection/immutable/StringOps;
const #53 = Asciz	genericWrapArray;
const #54 = Asciz	(Ljava/lang/Object;)Lscala/collection/mutable/WrappedArray;;
const #55 = NameAndType	#53:#54;//  genericWrapArray:(Ljava/lang/Object;)Lscala/collection/mutable/WrappedArray;
const #56 = Method	#42.#55;	//  scala/Predef$.genericWrapArray:(Ljava/lang/Object;)Lscala/collection/mutable/WrappedArray;
const #57 = Asciz	scala/collection/immutable/StringLike;
const #58 = class	#57;	//  scala/collection/immutable/StringLike
const #59 = Asciz	format;
const #60 = Asciz	(Lscala/collection/Seq;)Ljava/lang/String;;
const #61 = NameAndType	#59:#60;//  format:(Lscala/collection/Seq;)Ljava/lang/String;
const #62 = InterfaceMethod	#58.#61;	//  scala/collection/immutable/StringLike.format:(Lscala/collection/Seq;)Ljava/lang/String;
const #63 = Asciz	(Ljava/lang/String;)V;
const #64 = NameAndType	#14:#63;//  "<init>":(Ljava/lang/String;)V
const #65 = Method	#40.#64;	//  scala/xml/dtd/ValidationException."<init>":(Ljava/lang/String;)V
const #66 = Asciz	toString;
const #67 = Asciz	()Ljava/lang/String;;
const #68 = Asciz	(Lscala/Function0;)Ljava/lang/String;;
const #69 = NameAndType	#66:#68;//  toString:(Lscala/Function0;)Ljava/lang/String;
const #70 = Method	#24.#69;	//  scala/Function0$class.toString:(Lscala/Function0;)Ljava/lang/String;
const #71 = Asciz	Scala;
const #72 = Asciz	InnerClasses;
const #73 = Asciz	scala/xml/dtd/ContentModel$ElemName;
const #74 = class	#73;	//  scala/xml/dtd/ContentModel$ElemName
const #75 = Asciz	scala/xml/dtd/ContentModel;
const #76 = class	#75;	//  scala/xml/dtd/ContentModel
const #77 = Asciz	ElemName;
const #78 = Asciz	scala/xml/dtd/ElementValidator$$anonfun$check$6;
const #79 = class	#78;	//  scala/xml/dtd/ElementValidator$$anonfun$check$6
const #80 = Asciz	scala/xml/dtd/ElementValidator;
const #81 = class	#80;	//  scala/xml/dtd/ElementValidator
const #82 = Asciz	$anonfun$check$6;
const #83 = Asciz	$anonfun$apply$1;
const #84 = Asciz	scala/Function0;
const #85 = class	#84;	//  scala/Function0
const #86 = Asciz	scala/ScalaObject;
const #87 = class	#86;	//  scala/ScalaObject
const #88 = Asciz	java/io/Serializable;
const #89 = class	#88;	//  java/io/Serializable

{
public static final long serialVersionUID;

public static {};
  Code:
   Stack=2, Locals=0, Args_size=0
   0:	lconst_0
   1:	putstatic	#11; //Field serialVersionUID:J
   4:	return

public scala.xml.dtd.ElementValidator$$anonfun$check$6$$anonfun$apply$1(scala.xml.dtd.ElementValidator$$anonfun$check$6, scala.xml.dtd.ContentModel$ElemName);
  Code:
   Stack=2, Locals=3, Args_size=3
   0:	aload_0
   1:	aload_2
   2:	putfield	#18; //Field e$1:Lscala/xml/dtd/ContentModel$ElemName;
   5:	aload_0
   6:	invokespecial	#22; //Method java/lang/Object."<init>":()V
   9:	aload_0
   10:	invokestatic	#28; //Method scala/Function0$class.$init$:(Lscala/Function0;)V
   13:	return
  LineNumberTable: 
   line 117: 0

  LocalVariableTable: 
   Start  Length  Slot  Name   Signature
   0      14      0    this       Lscala/xml/dtd/ElementValidator$$anonfun$check$6$$anonfun$apply$1;
   0      14      1    $outer       Lscala/xml/dtd/ElementValidator$$anonfun$check$6;


public final java.lang.Object apply();
  Code:
   Stack=1, Locals=1, Args_size=1
   0:	aload_0
   1:	invokevirtual	#38; //Method apply:()Lscala/runtime/Nothing$;
   4:	athrow
  LineNumberTable: 
   line 117: 0


public final scala.runtime.Nothing$ apply();
  Code:
   Stack=8, Locals=1, Args_size=1
   0:	new	#40; //class scala/xml/dtd/ValidationException
   3:	dup
   4:	getstatic	#46; //Field scala/Predef$.MODULE$:Lscala/Predef$;
   7:	ldc	#48; //String element %s not allowed here
   9:	invokevirtual	#52; //Method scala/Predef$.augmentString:(Ljava/lang/String;)Lscala/collection/immutable/StringOps;
   12:	getstatic	#46; //Field scala/Predef$.MODULE$:Lscala/Predef$;
   15:	iconst_1
   16:	anewarray	#20; //class java/lang/Object
   19:	dup
   20:	iconst_0
   21:	aload_0
   22:	getfield	#18; //Field e$1:Lscala/xml/dtd/ContentModel$ElemName;
   25:	aastore
   26:	invokevirtual	#56; //Method scala/Predef$.genericWrapArray:(Ljava/lang/Object;)Lscala/collection/mutable/WrappedArray;
   29:	invokeinterface	#62,  2; //InterfaceMethod scala/collection/immutable/StringLike.format:(Lscala/collection/Seq;)Ljava/lang/String;
   34:	invokespecial	#65; //Method scala/xml/dtd/ValidationException."<init>":(Ljava/lang/String;)V
   37:	athrow
  LineNumberTable: 
   line 117: 0


public java.lang.String toString();
  Code:
   Stack=1, Locals=1, Args_size=1
   0:	aload_0
   1:	invokestatic	#70; //Method scala/Function0$class.toString:(Lscala/Function0;)Ljava/lang/String;
   4:	areturn
  LineNumberTable: 
   line 117: 0


}

