Compiled from "ElementValidator.scala"
public final class scala.xml.dtd.ElementValidator$$anonfun$check$6$$anonfun$apply$1 extends java.lang.Object implements scala.Function0,scala.ScalaObject,java.io.Serializable
  SourceFile: "ElementValidator.scala"
  Scala: length = 0x
   
  InnerClass: 
   public ElemName=class scala/xml/dtd/ContentModel$ElemName of class scala/xml/dtd/ContentModel
   public final $anonfun$check$6=class scala/xml/dtd/ElementValidator$$anonfun$check$6 of class scala/xml/dtd/ElementValidator
   public final $anonfun$apply$1=class scala/xml/dtd/ElementValidator$$anonfun$check$6$$anonfun$apply$1 of class scala/xml/dtd/ElementValidator$$anonfun$check$6
  minor version: 0
  major version: 49
  Constant pool:
Asciz	SourceFile;
Asciz	ElementValidator.scala;
Asciz	<clinit>;
Asciz	()V;
Asciz	Code;
Asciz	serialVersionUID;
Asciz	J;
Asciz	scala/xml/dtd/ElementValidator$$anonfun$check$6$$anonfun$apply$1;
class	scala/xml/dtd/ElementValidator$$anonfun$check$6$$anonfun$apply$1
NameAndType	serialVersionUID:J
Field	scala/xml/dtd/ElementValidator$$anonfun$check$6$$anonfun$apply$1.serialVersionUID:J
Asciz	e$1;
Asciz	Lscala/xml/dtd/ContentModel$ElemName;;
Asciz	<init>;
Asciz	(Lscala/xml/dtd/ElementValidator$$anonfun$check$6;Lscala/xml/dtd/ContentModel$ElemName;)V;
Asciz	LineNumberTable;
NameAndType	e$1:Lscala/xml/dtd/ContentModel$ElemName;
Field	scala/xml/dtd/ElementValidator$$anonfun$check$6$$anonfun$apply$1.e$1:Lscala/xml/dtd/ContentModel$ElemName;
Asciz	java/lang/Object;
class	java/lang/Object
NameAndType	"<init>":()V
Method	java/lang/Object."<init>":()V
Asciz	scala/Function0$class;
class	scala/Function0$class
Asciz	$init$;
Asciz	(Lscala/Function0;)V;
NameAndType	$init$:(Lscala/Function0;)V
Method	scala/Function0$class.$init$:(Lscala/Function0;)V
Asciz	this;
Asciz	Lscala/xml/dtd/ElementValidator$$anonfun$check$6$$anonfun$apply$1;;
Asciz	$outer;
Asciz	Lscala/xml/dtd/ElementValidator$$anonfun$check$6;;
Asciz	LocalVariableTable;
Asciz	apply;
Asciz	()Ljava/lang/Object;;
Asciz	()Lscala/runtime/Nothing$;;
NameAndType	apply:()Lscala/runtime/Nothing$;
Method	scala/xml/dtd/ElementValidator$$anonfun$check$6$$anonfun$apply$1.apply:()Lscala/runtime/Nothing$;
Asciz	scala/xml/dtd/ValidationException;
class	scala/xml/dtd/ValidationException
Asciz	scala/Predef$;
class	scala/Predef$
Asciz	MODULE$;
Asciz	Lscala/Predef$;;
NameAndType	MODULE$:Lscala/Predef$;
Field	scala/Predef$.MODULE$:Lscala/Predef$;
Asciz	element %s not allowed here;
String	element %s not allowed here
Asciz	augmentString;
Asciz	(Ljava/lang/String;)Lscala/collection/immutable/StringOps;;
NameAndType	augmentString:(Ljava/lang/String;)Lscala/collection/immutable/StringOps;
Method	scala/Predef$.augmentString:(Ljava/lang/String;)Lscala/collection/immutable/StringOps;
Asciz	genericWrapArray;
Asciz	(Ljava/lang/Object;)Lscala/collection/mutable/WrappedArray;;
NameAndType	genericWrapArray:(Ljava/lang/Object;)Lscala/collection/mutable/WrappedArray;
Method	scala/Predef$.genericWrapArray:(Ljava/lang/Object;)Lscala/collection/mutable/WrappedArray;
Asciz	scala/collection/immutable/StringLike;
class	scala/collection/immutable/StringLike
Asciz	format;
Asciz	(Lscala/collection/Seq;)Ljava/lang/String;;
NameAndType	format:(Lscala/collection/Seq;)Ljava/lang/String;
InterfaceMethod	scala/collection/immutable/StringLike.format:(Lscala/collection/Seq;)Ljava/lang/String;
Asciz	(Ljava/lang/String;)V;
NameAndType	"<init>":(Ljava/lang/String;)V
Method	scala/xml/dtd/ValidationException."<init>":(Ljava/lang/String;)V
Asciz	toString;
Asciz	()Ljava/lang/String;;
Asciz	(Lscala/Function0;)Ljava/lang/String;;
NameAndType	toString:(Lscala/Function0;)Ljava/lang/String;
Method	scala/Function0$class.toString:(Lscala/Function0;)Ljava/lang/String;
Asciz	Scala;
Asciz	InnerClasses;
Asciz	scala/xml/dtd/ContentModel$ElemName;
class	scala/xml/dtd/ContentModel$ElemName
Asciz	scala/xml/dtd/ContentModel;
class	scala/xml/dtd/ContentModel
Asciz	ElemName;
Asciz	scala/xml/dtd/ElementValidator$$anonfun$check$6;
class	scala/xml/dtd/ElementValidator$$anonfun$check$6
Asciz	scala/xml/dtd/ElementValidator;
class	scala/xml/dtd/ElementValidator
Asciz	$anonfun$check$6;
Asciz	$anonfun$apply$1;
Asciz	scala/Function0;
class	scala/Function0
Asciz	scala/ScalaObject;
class	scala/ScalaObject
Asciz	java/io/Serializable;
class	java/io/Serializable

{
public static final long serialVersionUID;
  Signature: J

private final scala.xml.dtd.ContentModel$ElemName e$1;
  Signature: Lscala/xml/dtd/ContentModel$ElemName;

public static {};
  Signature: ()V
  Code:
   Stack=2, Locals=0, Args_size=0
	lconst_0
	putstatic	Field serialVersionUID:J
	return
  Labels:

public scala.xml.dtd.ElementValidator$$anonfun$check$6$$anonfun$apply$1(scala.xml.dtd.ElementValidator$$anonfun$check$6, scala.xml.dtd.ContentModel$ElemName);
  Signature: (Lscala/xml/dtd/ElementValidator$$anonfun$check$6;Lscala/xml/dtd/ContentModel$ElemName;)V
  Code:
   Stack=2, Locals=3, Args_size=3
	aload_0
	aload_2
	putfield	Field e$1:Lscala/xml/dtd/ContentModel$ElemName;
	aload_0
	invokespecial	Method java/lang/Object."<init>":()V
	aload_0
	invokestatic	Method scala/Function0$class.$init$:(Lscala/Function0;)V
	return
  Labels:
  LocalVariableTable: 
   Start  Length  Slot  Name   Signature
   0      14      0    this       Lscala/xml/dtd/ElementValidator$$anonfun$check$6$$anonfun$apply$1;
   0      14      1    $outer       Lscala/xml/dtd/ElementValidator$$anonfun$check$6;


public final java.lang.Object apply();
  Signature: ()Ljava/lang/Object;
  Code:
   Stack=1, Locals=1, Args_size=1
	aload_0
	invokevirtual	Method apply:()Lscala/runtime/Nothing$;
	athrow
  Labels:

public final scala.runtime.Nothing$ apply();
  Signature: ()Lscala/runtime/Nothing$;
  Code:
   Stack=8, Locals=1, Args_size=1
	new	class scala/xml/dtd/ValidationException
	dup
	getstatic	Field scala/Predef$.MODULE$:Lscala/Predef$;
	ldc	String element %s not allowed here
	invokevirtual	Method scala/Predef$.augmentString:(Ljava/lang/String;)Lscala/collection/immutable/StringOps;
	getstatic	Field scala/Predef$.MODULE$:Lscala/Predef$;
	iconst_1
	anewarray	class java/lang/Object
	dup
	iconst_0
	aload_0
	getfield	Field e$1:Lscala/xml/dtd/ContentModel$ElemName;
	aastore
	invokevirtual	Method scala/Predef$.genericWrapArray:(Ljava/lang/Object;)Lscala/collection/mutable/WrappedArray;
	invokeinterface	InterfaceMethod scala/collection/immutable/StringLike.format:(Lscala/collection/Seq;)Ljava/lang/String;
	invokespecial	Method scala/xml/dtd/ValidationException."<init>":(Ljava/lang/String;)V
	athrow
  Labels:

public java.lang.String toString();
  Signature: ()Ljava/lang/String;
  Code:
   Stack=1, Locals=1, Args_size=1
	aload_0
	invokestatic	Method scala/Function0$class.toString:(Lscala/Function0;)Ljava/lang/String;
	areturn
  Labels:

}

