Compiled from "ElementValidator.scala"
public final class scala.xml.dtd.ElementValidator$$anonfun$check$5 extends java.lang.Object implements scala.Function1,scala.ScalaObject,java.io.Serializable
  SourceFile: "ElementValidator.scala"
  Scala: length = 0x
   
  InnerClass: 
   public final $anonfun$check$5=class scala/xml/dtd/ElementValidator$$anonfun$check$5 of class scala/xml/dtd/ElementValidator
  minor version: 0
  major version: 49
  Constant pool:
Asciz	SourceFile;
Asciz	ElementValidator.scala;
Asciz	<clinit>;
Asciz	()V;
Asciz	Code;
Asciz	serialVersionUID;
Asciz	J;
Asciz	scala/xml/dtd/ElementValidator$$anonfun$check$5;
class	scala/xml/dtd/ElementValidator$$anonfun$check$5
NameAndType	serialVersionUID:J
Field	scala/xml/dtd/ElementValidator$$anonfun$check$5.serialVersionUID:J
Asciz	$outer;
Asciz	Lscala/xml/dtd/ElementValidator;;
Asciz	<init>;
Asciz	(Lscala/xml/dtd/ElementValidator;)V;
Asciz	LineNumberTable;
Asciz	java/lang/NullPointerException;
class	java/lang/NullPointerException
NameAndType	"<init>":()V
Method	java/lang/NullPointerException."<init>":()V
NameAndType	$outer:Lscala/xml/dtd/ElementValidator;
Field	scala/xml/dtd/ElementValidator$$anonfun$check$5.$outer:Lscala/xml/dtd/ElementValidator;
Asciz	java/lang/Object;
class	java/lang/Object
Method	java/lang/Object."<init>":()V
Asciz	scala/Function1$class;
class	scala/Function1$class
Asciz	$init$;
Asciz	(Lscala/Function1;)V;
NameAndType	$init$:(Lscala/Function1;)V
Method	scala/Function1$class.$init$:(Lscala/Function1;)V
Asciz	this;
Asciz	Lscala/xml/dtd/ElementValidator$$anonfun$check$5;;
Asciz	LocalVariableTable;
Asciz	apply;
Asciz	(Ljava/lang/Object;)Ljava/lang/Object;;
Asciz	java/lang/String;
class	java/lang/String
Asciz	(Ljava/lang/String;)V;
NameAndType	apply:(Ljava/lang/String;)V
Method	scala/xml/dtd/ElementValidator$$anonfun$check$5.apply:(Ljava/lang/String;)V
Asciz	scala/runtime/BoxedUnit;
class	scala/runtime/BoxedUnit
Asciz	UNIT;
Asciz	Lscala/runtime/BoxedUnit;;
NameAndType	UNIT:Lscala/runtime/BoxedUnit;
Field	scala/runtime/BoxedUnit.UNIT:Lscala/runtime/BoxedUnit;
Asciz	v1;
Asciz	Ljava/lang/Object;;
Asciz	scala/xml/dtd/ElementValidator;
class	scala/xml/dtd/ElementValidator
Asciz	scala$xml$dtd$ElementValidator$$exc;
Asciz	()Lscala/collection/immutable/List;;
NameAndType	scala$xml$dtd$ElementValidator$$exc:()Lscala/collection/immutable/List;
Method	scala/xml/dtd/ElementValidator.scala$xml$dtd$ElementValidator$$exc:()Lscala/collection/immutable/List;
Asciz	scala/xml/dtd/MakeValidationException$;
class	scala/xml/dtd/MakeValidationException$
Asciz	MODULE$;
Asciz	Lscala/xml/dtd/MakeValidationException$;;
NameAndType	MODULE$:Lscala/xml/dtd/MakeValidationException$;
Field	scala/xml/dtd/MakeValidationException$.MODULE$:Lscala/xml/dtd/MakeValidationException$;
Asciz	fromUndefinedElement;
Asciz	(Ljava/lang/String;)Lscala/xml/dtd/ValidationException;;
NameAndType	fromUndefinedElement:(Ljava/lang/String;)Lscala/xml/dtd/ValidationException;
Method	scala/xml/dtd/MakeValidationException$.fromUndefinedElement:(Ljava/lang/String;)Lscala/xml/dtd/ValidationException;
Asciz	scala/collection/immutable/List;
class	scala/collection/immutable/List
Asciz	$colon$colon;
Asciz	(Ljava/lang/Object;)Lscala/collection/immutable/List;;
NameAndType	$colon$colon:(Ljava/lang/Object;)Lscala/collection/immutable/List;
Method	scala/collection/immutable/List.$colon$colon:(Ljava/lang/Object;)Lscala/collection/immutable/List;
Asciz	scala$xml$dtd$ElementValidator$$exc_$eq;
Asciz	(Lscala/collection/immutable/List;)V;
NameAndType	scala$xml$dtd$ElementValidator$$exc_$eq:(Lscala/collection/immutable/List;)V
Method	scala/xml/dtd/ElementValidator.scala$xml$dtd$ElementValidator$$exc_$eq:(Lscala/collection/immutable/List;)V
Asciz	andThen;
Asciz	(Lscala/Function1;)Lscala/Function1;;
Asciz	(Lscala/Function1;Lscala/Function1;)Lscala/Function1;;
NameAndType	andThen:(Lscala/Function1;Lscala/Function1;)Lscala/Function1;
Method	scala/Function1$class.andThen:(Lscala/Function1;Lscala/Function1;)Lscala/Function1;
Asciz	g;
Asciz	Lscala/Function1;;
Asciz	compose;
NameAndType	compose:(Lscala/Function1;Lscala/Function1;)Lscala/Function1;
Method	scala/Function1$class.compose:(Lscala/Function1;Lscala/Function1;)Lscala/Function1;
Asciz	toString;
Asciz	()Ljava/lang/String;;
Asciz	(Lscala/Function1;)Ljava/lang/String;;
NameAndType	toString:(Lscala/Function1;)Ljava/lang/String;
Method	scala/Function1$class.toString:(Lscala/Function1;)Ljava/lang/String;
Asciz	Scala;
Asciz	InnerClasses;
Asciz	$anonfun$check$5;
Asciz	scala/Function1;
class	scala/Function1
Asciz	scala/ScalaObject;
class	scala/ScalaObject
Asciz	java/io/Serializable;
class	java/io/Serializable

{
public static final long serialVersionUID;
  Signature: J

private final scala.xml.dtd.ElementValidator $outer;
  Signature: Lscala/xml/dtd/ElementValidator;

public static {};
  Signature: ()V
  Code:
   Stack=2, Locals=0, Args_size=0
	lconst_0
	putstatic	Field serialVersionUID:J
	return
  Labels:

public scala.xml.dtd.ElementValidator$$anonfun$check$5(scala.xml.dtd.ElementValidator);
  Signature: (Lscala/xml/dtd/ElementValidator;)V
  Code:
   Stack=2, Locals=2, Args_size=2
	aload_1
	ifnonnull	l1 // aload_0
	new	class java/lang/NullPointerException
	dup
	invokespecial	Method java/lang/NullPointerException."<init>":()V
	athrow
l1	aload_0
	aload_1
	putfield	Field $outer:Lscala/xml/dtd/ElementValidator;
	aload_0
	invokespecial	Method java/lang/Object."<init>":()V
	aload_0
	invokestatic	Method scala/Function1$class.$init$:(Lscala/Function1;)V
	return
  Labels:
   	l1 = 12 // aload_0
  LocalVariableTable: 
   Start  Length  Slot  Name   Signature
   0      26      0    this       Lscala/xml/dtd/ElementValidator$$anonfun$check$5;
   0      26      1    $outer       Lscala/xml/dtd/ElementValidator;


public final java.lang.Object apply(java.lang.Object);
  Signature: (Ljava/lang/Object;)Ljava/lang/Object;
  Code:
   Stack=2, Locals=3, Args_size=2
	aload_0
	getfield	Field $outer:Lscala/xml/dtd/ElementValidator;
	astore_2
	aload_0
	aload_1
	checkcast	class java/lang/String
	invokevirtual	Method apply:(Ljava/lang/String;)V
	getstatic	Field scala/runtime/BoxedUnit.UNIT:Lscala/runtime/BoxedUnit;
	areturn
  Labels:
  LocalVariableTable: 
   Start  Length  Slot  Name   Signature
   0      17      0    this       Lscala/xml/dtd/ElementValidator$$anonfun$check$5;
   5      12      1    v1       Ljava/lang/Object;


public final void apply(java.lang.String);
  Signature: (Ljava/lang/String;)V
  Code:
   Stack=4, Locals=3, Args_size=2
	aload_0
	getfield	Field $outer:Lscala/xml/dtd/ElementValidator;
	astore_2
	aload_0
	getfield	Field $outer:Lscala/xml/dtd/ElementValidator;
	aload_0
	getfield	Field $outer:Lscala/xml/dtd/ElementValidator;
	invokevirtual	Method scala/xml/dtd/ElementValidator.scala$xml$dtd$ElementValidator$$exc:()Lscala/collection/immutable/List;
	getstatic	Field scala/xml/dtd/MakeValidationException$.MODULE$:Lscala/xml/dtd/MakeValidationException$;
	aload_1
	invokevirtual	Method scala/xml/dtd/MakeValidationException$.fromUndefinedElement:(Ljava/lang/String;)Lscala/xml/dtd/ValidationException;
	invokevirtual	Method scala/collection/immutable/List.$colon$colon:(Ljava/lang/Object;)Lscala/collection/immutable/List;
	invokevirtual	Method scala/xml/dtd/ElementValidator.scala$xml$dtd$ElementValidator$$exc_$eq:(Lscala/collection/immutable/List;)V
	return
  Labels:
  LocalVariableTable: 
   Start  Length  Slot  Name   Signature
   0      30      0    this       Lscala/xml/dtd/ElementValidator$$anonfun$check$5;


public scala.Function1 andThen(scala.Function1);
  Signature: (Lscala/Function1;)Lscala/Function1;
  Code:
   Stack=2, Locals=2, Args_size=2
	aload_0
	aload_1
	invokestatic	Method scala/Function1$class.andThen:(Lscala/Function1;Lscala/Function1;)Lscala/Function1;
	areturn
  Labels:
  LocalVariableTable: 
   Start  Length  Slot  Name   Signature
   0      6      0    this       Lscala/xml/dtd/ElementValidator$$anonfun$check$5;
   0      6      1    g       Lscala/Function1;


public scala.Function1 compose(scala.Function1);
  Signature: (Lscala/Function1;)Lscala/Function1;
  Code:
   Stack=2, Locals=2, Args_size=2
	aload_0
	aload_1
	invokestatic	Method scala/Function1$class.compose:(Lscala/Function1;Lscala/Function1;)Lscala/Function1;
	areturn
  Labels:
  LocalVariableTable: 
   Start  Length  Slot  Name   Signature
   0      6      0    this       Lscala/xml/dtd/ElementValidator$$anonfun$check$5;
   0      6      1    g       Lscala/Function1;


public java.lang.String toString();
  Signature: ()Ljava/lang/String;
  Code:
   Stack=1, Locals=1, Args_size=1
	aload_0
	invokestatic	Method scala/Function1$class.toString:(Lscala/Function1;)Ljava/lang/String;
	areturn
  Labels:

}

