Compiled from "ContentModel.scala"
public final class scala.xml.dtd.ELEMENTS$ extends java.lang.Object implements scala.Function1,scala.ScalaObject
  SourceFile: "ContentModel.scala"
  Scala: length = 0x
   
  InnerClass: 
   public abstract RegExp=class scala/util/regexp/Base$RegExp of class scala/util/regexp/Base
  minor version: 0
  major version: 49
  Constant pool:
Asciz	SourceFile;
Asciz	ContentModel.scala;
Asciz	Scala;
Asciz	MODULE$;
Asciz	Lscala/xml/dtd/ELEMENTS$;;
Asciz	<clinit>;
Asciz	()V;
Asciz	Code;
Asciz	scala/xml/dtd/ELEMENTS$;
class	scala/xml/dtd/ELEMENTS$
Asciz	<init>;
NameAndType	"<init>":()V
Method	scala/xml/dtd/ELEMENTS$."<init>":()V
Asciz	toString;
Asciz	()Ljava/lang/String;;
Asciz	LineNumberTable;
Asciz	scala/Function1$class;
class	scala/Function1$class
Asciz	(Lscala/Function1;)Ljava/lang/String;;
NameAndType	toString:(Lscala/Function1;)Ljava/lang/String;
Method	scala/Function1$class.toString:(Lscala/Function1;)Ljava/lang/String;
Asciz	compose;
Asciz	(Lscala/Function1;)Lscala/Function1;;
Asciz	(Lscala/Function1;Lscala/Function1;)Lscala/Function1;;
NameAndType	compose:(Lscala/Function1;Lscala/Function1;)Lscala/Function1;
Method	scala/Function1$class.compose:(Lscala/Function1;Lscala/Function1;)Lscala/Function1;
Asciz	this;
Asciz	g;
Asciz	Lscala/Function1;;
Asciz	LocalVariableTable;
Asciz	andThen;
NameAndType	andThen:(Lscala/Function1;Lscala/Function1;)Lscala/Function1;
Method	scala/Function1$class.andThen:(Lscala/Function1;Lscala/Function1;)Lscala/Function1;
Asciz	unapply;
Asciz	(Lscala/xml/dtd/ELEMENTS;)Lscala/Some;;
Asciz	scala/Some;
class	scala/Some
Asciz	scala/xml/dtd/ELEMENTS;
class	scala/xml/dtd/ELEMENTS
Asciz	r;
Asciz	()Lscala/util/regexp/Base$RegExp;;
NameAndType	r:()Lscala/util/regexp/Base$RegExp;
Method	scala/xml/dtd/ELEMENTS.r:()Lscala/util/regexp/Base$RegExp;
Asciz	(Ljava/lang/Object;)V;
NameAndType	"<init>":(Ljava/lang/Object;)V
Method	scala/Some."<init>":(Ljava/lang/Object;)V
Asciz	x$0;
Asciz	Lscala/xml/dtd/ELEMENTS;;
Asciz	apply;
Asciz	(Lscala/util/regexp/Base$RegExp;)Lscala/xml/dtd/ELEMENTS;;
Asciz	(Lscala/util/regexp/Base$RegExp;)V;
NameAndType	"<init>":(Lscala/util/regexp/Base$RegExp;)V
Method	scala/xml/dtd/ELEMENTS."<init>":(Lscala/util/regexp/Base$RegExp;)V
Asciz	Lscala/util/regexp/Base$RegExp;;
Asciz	(Ljava/lang/Object;)Ljava/lang/Object;;
Asciz	scala/util/regexp/Base$RegExp;
class	scala/util/regexp/Base$RegExp
NameAndType	apply:(Lscala/util/regexp/Base$RegExp;)Lscala/xml/dtd/ELEMENTS;
Method	scala/xml/dtd/ELEMENTS$.apply:(Lscala/util/regexp/Base$RegExp;)Lscala/xml/dtd/ELEMENTS;
Asciz	v1;
Asciz	Ljava/lang/Object;;
Asciz	java/lang/Object;
class	java/lang/Object
Method	java/lang/Object."<init>":()V
NameAndType	MODULE$:Lscala/xml/dtd/ELEMENTS$;
Field	scala/xml/dtd/ELEMENTS$.MODULE$:Lscala/xml/dtd/ELEMENTS$;
Asciz	$init$;
Asciz	(Lscala/Function1;)V;
NameAndType	$init$:(Lscala/Function1;)V
Method	scala/Function1$class.$init$:(Lscala/Function1;)V
Asciz	InnerClasses;
Asciz	scala/util/regexp/Base;
class	scala/util/regexp/Base
Asciz	RegExp;
Asciz	scala/Function1;
class	scala/Function1
Asciz	scala/ScalaObject;
class	scala/ScalaObject

{
public static final scala.xml.dtd.ELEMENTS$ MODULE$;
  Signature: Lscala/xml/dtd/ELEMENTS$;

public static {};
  Signature: ()V
  Code:
   Stack=1, Locals=0, Args_size=0
	new	class scala/xml/dtd/ELEMENTS$
	invokespecial	Method "<init>":()V
	return
  Labels:

public java.lang.String toString();
  Signature: ()Ljava/lang/String;
  Code:
   Stack=1, Locals=1, Args_size=1
	aload_0
	invokestatic	Method scala/Function1$class.toString:(Lscala/Function1;)Ljava/lang/String;
	areturn
  Labels:

public scala.Function1 compose(scala.Function1);
  Signature: (Lscala/Function1;)Lscala/Function1;
  Code:
   Stack=2, Locals=2, Args_size=2
	aload_0
	aload_1
	invokestatic	Method scala/Function1$class.compose:(Lscala/Function1;Lscala/Function1;)Lscala/Function1;
	areturn
  Labels:
  LocalVariableTable: 
   Start  Length  Slot  Name   Signature
   0      6      0    this       Lscala/xml/dtd/ELEMENTS$;
   0      6      1    g       Lscala/Function1;


public scala.Function1 andThen(scala.Function1);
  Signature: (Lscala/Function1;)Lscala/Function1;
  Code:
   Stack=2, Locals=2, Args_size=2
	aload_0
	aload_1
	invokestatic	Method scala/Function1$class.andThen:(Lscala/Function1;Lscala/Function1;)Lscala/Function1;
	areturn
  Labels:
  LocalVariableTable: 
   Start  Length  Slot  Name   Signature
   0      6      0    this       Lscala/xml/dtd/ELEMENTS$;
   0      6      1    g       Lscala/Function1;


public scala.Some unapply(scala.xml.dtd.ELEMENTS);
  Signature: (Lscala/xml/dtd/ELEMENTS;)Lscala/Some;
  Code:
   Stack=3, Locals=2, Args_size=2
	new	class scala/Some
	dup
	aload_1
	invokevirtual	Method scala/xml/dtd/ELEMENTS.r:()Lscala/util/regexp/Base$RegExp;
	invokespecial	Method scala/Some."<init>":(Ljava/lang/Object;)V
	areturn
  Labels:
  LocalVariableTable: 
   Start  Length  Slot  Name   Signature
   0      12      0    this       Lscala/xml/dtd/ELEMENTS$;
   0      12      1    x$0       Lscala/xml/dtd/ELEMENTS;


public scala.xml.dtd.ELEMENTS apply(scala.util.regexp.Base$RegExp);
  Signature: (Lscala/util/regexp/Base$RegExp;)Lscala/xml/dtd/ELEMENTS;
  Code:
   Stack=3, Locals=2, Args_size=2
	new	class scala/xml/dtd/ELEMENTS
	dup
	aload_1
	invokespecial	Method scala/xml/dtd/ELEMENTS."<init>":(Lscala/util/regexp/Base$RegExp;)V
	areturn
  Labels:
  LocalVariableTable: 
   Start  Length  Slot  Name   Signature
   0      9      0    this       Lscala/xml/dtd/ELEMENTS$;
   0      9      1    r       Lscala/util/regexp/Base$RegExp;


public java.lang.Object apply(java.lang.Object);
  Signature: (Ljava/lang/Object;)Ljava/lang/Object;
  Code:
   Stack=2, Locals=2, Args_size=2
	aload_0
	aload_1
	checkcast	class scala/util/regexp/Base$RegExp
	invokevirtual	Method apply:(Lscala/util/regexp/Base$RegExp;)Lscala/xml/dtd/ELEMENTS;
	areturn
  Labels:
  LocalVariableTable: 
   Start  Length  Slot  Name   Signature
   0      9      0    this       Lscala/xml/dtd/ELEMENTS$;
   0      9      1    v1       Ljava/lang/Object;


private scala.xml.dtd.ELEMENTS$();
  Signature: ()V
  Code:
   Stack=1, Locals=1, Args_size=1
	aload_0
	invokespecial	Method java/lang/Object."<init>":()V
	aload_0
	putstatic	Field MODULE$:Lscala/xml/dtd/ELEMENTS$;
	aload_0
	invokestatic	Method scala/Function1$class.$init$:(Lscala/Function1;)V
	return
  Labels:

}

