Compiled from "ElementValidator.scala"
public class scala.xml.dtd.ElementValidator extends java.lang.Object implements scala.Function1,scala.ScalaObject
  SourceFile: "ElementValidator.scala"
  Signature: length = 0x2
   01 FFFFFFE7 
  ScalaSig: length = 0x416
   05 00 FFFFFF81 1A 06 08 01 02 FFFFFF84 FFFFFF80 FFFFFF80 FFFFFF80 00 09 02 10
   45 6C 65 6D 65 6E 74 56 61 6C 69 64 61 74 6F 72
   0A 02 03 04 01 03 64 74 64 0A 02 05 06 01 03 78
   6D 6C 0A 01 07 01 05 73 63 61 6C 61 03 00 13 04
   00 0A 12 1D 10 02 0B 10 0D 01 0C 0A 02 0D 0E 01
   04 6C 61 6E 67 0A 01 0F 01 04 6A 61 76 61 09 02
   11 0C 02 06 4F 62 6A 65 63 74 10 04 13 14 16 1A
   0D 01 06 09 02 15 06 02 09 46 75 6E 63 74 69 6F
   6E 31 10 02 17 18 0D 01 04 09 02 19 04 02 04 4E
   6F 64 65 10 02 13 1B 09 02 1C 06 02 07 42 6F 6F
   6C 65 61 6E 10 02 13 1E 09 02 1F 06 02 0B 53 63
   61 6C 61 4F 62 6A 65 63 74 08 05 21 00 FFFFFF84 00 22
   01 06 3C 69 6E 69 74 3E 14 01 23 10 02 24 00 0D
   01 02 08 07 26 00 FFFFFFC0 FFFFFF80 FFFFFF84 00 27 01 03 65 78 63
   15 01 28 10 03 29 31 34 0E 02 2A 2F 0E 02 2B 2E
   0D 01 2C 0A 02 2D 08 01 06 3C 72 6F 6F 74 3E 09
   01 07 09 02 30 06 01 07 70 61 63 6B 61 67 65 09
   02 32 33 02 04 4C 69 73 74 0A 02 30 06 10 02 24
   35 09 02 36 02 02 13 56 61 6C 69 64 61 74 69 6F
   6E 45 78 63 65 70 74 69 6F 6E 08 07 38 00 FFFFFFC0 FFFFFF80
   FFFFFF84 00 39 01 07 65 78 63 5F 24 65 71 14 02 3A 3D
   10 02 13 3B 09 02 3C 06 02 04 55 6E 69 74 08 07
   3E 37 FFFFFF81 FFFFFF80 FFFFFFC0 00 28 01 03 78 24 31 08 06 40 00
   FFFFFFA0 FFFFFFA0 04 28 01 04 65 78 63 20 08 07 42 00 FFFFFFC0 FFFFFF80
   FFFFFF84 08 43 01 0C 63 6F 6E 74 65 6E 74 4D 6F 64 65
   6C 15 01 44 10 02 24 45 09 02 46 02 02 0C 43 6F
   6E 74 65 6E 74 4D 6F 64 65 6C 08 07 48 00 FFFFFFC0 FFFFFF80
   FFFFFF84 08 49 01 10 63 6F 6E 74 65 6E 74 4D 6F 64 65
   6C 5F 24 65 71 14 02 3A 4A 08 07 3E 47 FFFFFF81 FFFFFF80 FFFFFFC0
   00 44 08 06 4C 00 FFFFFFA0 FFFFFFA0 04 44 01 0D 63 6F 6E 74
   65 6E 74 4D 6F 64 65 6C 20 08 07 4E 00 FFFFFFC0 FFFFFF80 FFFFFF84
   08 4F 01 03 64 66 61 15 01 50 10 03 51 56 58 0D
   01 52 0A 02 53 54 01 08 61 75 74 6F 6D 61 74 61
   0A 02 55 06 01 04 75 74 69 6C 09 02 57 52 02 0C
   44 65 74 57 6F 72 64 41 75 74 6F 6D 10 02 59 5C
   0E 02 24 5A 09 02 5B 02 01 0C 43 6F 6E 74 65 6E
   74 4D 6F 64 65 6C 09 02 5D 5E 02 08 45 6C 65 6D
   4E 61 6D 65 0A 02 5B 02 08 07 60 00 FFFFFFC0 FFFFFF80 FFFFFF84 08
   61 01 07 64 66 61 5F 24 65 71 14 02 3A 62 08 07
   3E 5F FFFFFF81 FFFFFF80 FFFFFFC0 00 50 08 06 64 00 FFFFFFA0 FFFFFFA0 04 50 01
   04 64 66 61 20 08 07 66 00 FFFFFFC0 FFFFFF80 FFFFFF84 08 67 01 06
   61 64 65 63 6C 73 15 01 68 10 03 29 31 69 10 02
   24 6A 09 02 6B 02 02 08 41 74 74 72 44 65 63 6C
   08 07 6D 00 FFFFFFC0 FFFFFF80 FFFFFF84 08 6E 01 0A 61 64 65 63 6C
   73 5F 24 65 71 14 02 3A 6F 08 07 3E 6C FFFFFF81 FFFFFF80 FFFFFFC0
   00 68 08 06 71 00 FFFFFFA0 FFFFFFA0 04 68 01 07 61 64 65 63
   6C 73 20 08 05 73 00 FFFFFF84 00 74 01 0F 73 65 74 43
   6F 6E 74 65 6E 74 4D 6F 64 65 6C 14 02 3A 75 08
   05 76 72 FFFFFFC0 00 44 01 02 63 6D 08 05 78 00 FFFFFF84 00
   43 01 0F 67 65 74 43 6F 6E 74 65 6E 74 4D 6F 64
   65 6C 08 05 7A 00 FFFFFF84 00 7B 01 0B 73 65 74 4D 65
   74 61 44 61 74 61 14 02 3A 7C 08 05 66 79 FFFFFFC0 00
   68 08 05 7E 00 FFFFFF84 00 7F 01 0B 67 65 74 49 74 65
   72 61 74 6F 72 14 06 FFFFFF81 00 FFFFFF81 03 FFFFFF81 08 10 04 29
   FFFFFF81 01 58 09 03 FFFFFF81 02 33 02 08 49 74 65 72 61 74
   6F 72 08 07 FFFFFF81 04 7D FFFFFFC0 00 FFFFFF81 05 01 05 6E 6F 64
   65 73 10 04 29 FFFFFF81 06 16 09 03 FFFFFF81 07 33 02 03 53
   65 71 08 06 FFFFFF81 09 7D FFFFFFC0 00 1A 01 0A 73 6B 69 70
   50 43 44 41 54 41 08 07 FFFFFF81 0B 00 FFFFFF84 00 FFFFFF81 0C 01
   05 63 68 65 63 6B 14 03 1A FFFFFF81 0D 08 08 FFFFFF81 0E FFFFFF81
   0A FFFFFFC0 00 FFFFFF81 0F 01 02 6D 64 10 03 17 FFFFFF81 10 09 03
   FFFFFF81 11 04 02 08 4D 65 74 61 44 61 74 61 08 07 FFFFFF81
   0B 00 FFFFFF84 00 FFFFFF81 13 14 03 1A FFFFFF81 14 08 08 FFFFFF81 04 FFFFFF81
   12 FFFFFFC0 00 FFFFFF81 05 08 07 FFFFFF81 16 00 FFFFFF84 00 FFFFFF81 17 01 05
   61 70 70 6C 79 14 03 1A FFFFFF81 18 08 07 FFFFFF81 19 FFFFFF81 15
   FFFFFFC0 00 16 01 01 6E 
  InnerClass: 
   public #492= #216 of #491; //Alt=class scala/util/regexp/Base$Alt of class scala/util/regexp/Base
   public abstract #493= #57 of #491; //RegExp=class scala/util/regexp/Base$RegExp of class scala/util/regexp/Base
   public abstract #498= #495 of #497; //Label=class scala/util/regexp/WordExp$Label of class scala/util/regexp/WordExp
   public #499= #59 of #497; //Letter=class scala/util/regexp/WordExp$Letter of class scala/util/regexp/WordExp
   public #500= #65 of #248; //ElemName=class scala/xml/dtd/ContentModel$ElemName of class scala/xml/dtd/ContentModel
   public final #501= #395 of #35; //$anonfun$getIterator$1=class scala/xml/dtd/ElementValidator$$anonfun$getIterator$1 of class scala/xml/dtd/ElementValidator
   public final #502= #404 of #35; //$anonfun$getIterator$2=class scala/xml/dtd/ElementValidator$$anonfun$getIterator$2 of class scala/xml/dtd/ElementValidator
  minor version: 0
  major version: 49
  Constant pool:
const #1 = Asciz	SourceFile;
const #2 = Asciz	ElementValidator.scala;
const #3 = Asciz	adecls;
const #4 = Asciz	Lscala/collection/immutable/List;;
const #5 = Asciz	Lscala/collection/immutable/List<Lscala/xml/dtd/AttrDecl;>;;
const #6 = Asciz	Signature;
const #7 = Asciz	dfa;
const #8 = Asciz	Lscala/util/automata/DetWordAutom;;
const #9 = Asciz	Lscala/util/automata/DetWordAutom<Lscala/xml/dtd/ContentModel$ElemName;>;;
const #10 = Asciz	contentModel;
const #11 = Asciz	Lscala/xml/dtd/ContentModel;;
const #12 = Asciz	exc;
const #13 = Asciz	Lscala/collection/immutable/List<Lscala/xml/dtd/ValidationException;>;;
const #14 = Asciz	<init>;
const #15 = Asciz	()V;
const #16 = Asciz	Code;
const #17 = Asciz	LineNumberTable;
const #18 = Asciz	java/lang/Object;
const #19 = class	#18;	//  java/lang/Object
const #20 = NameAndType	#14:#15;//  "<init>":()V
const #21 = Method	#19.#20;	//  java/lang/Object."<init>":()V
const #22 = Asciz	scala/Function1$class;
const #23 = class	#22;	//  scala/Function1$class
const #24 = Asciz	$init$;
const #25 = Asciz	(Lscala/Function1;)V;
const #26 = NameAndType	#24:#25;//  $init$:(Lscala/Function1;)V
const #27 = Method	#23.#26;	//  scala/Function1$class.$init$:(Lscala/Function1;)V
const #28 = Asciz	scala/collection/immutable/Nil$;
const #29 = class	#28;	//  scala/collection/immutable/Nil$
const #30 = Asciz	MODULE$;
const #31 = Asciz	Lscala/collection/immutable/Nil$;;
const #32 = NameAndType	#30:#31;//  MODULE$:Lscala/collection/immutable/Nil$;
const #33 = Field	#29.#32;	//  scala/collection/immutable/Nil$.MODULE$:Lscala/collection/immutable/Nil$;
const #34 = Asciz	scala/xml/dtd/ElementValidator;
const #35 = class	#34;	//  scala/xml/dtd/ElementValidator
const #36 = NameAndType	#12:#4;//  exc:Lscala/collection/immutable/List;
const #37 = Field	#35.#36;	//  scala/xml/dtd/ElementValidator.exc:Lscala/collection/immutable/List;
const #38 = Asciz	find$2;
const #39 = Asciz	(Ljava/lang/String;Lscala/collection/Sequence;)Z;
const #40 = Asciz	scala/collection/generic/IterableTemplate;
const #41 = class	#40;	//  scala/collection/generic/IterableTemplate
const #42 = Asciz	iterator;
const #43 = Asciz	()Lscala/collection/Iterator;;
const #44 = NameAndType	#42:#43;//  iterator:()Lscala/collection/Iterator;
const #45 = InterfaceMethod	#41.#44;	//  scala/collection/generic/IterableTemplate.iterator:()Lscala/collection/Iterator;
const #46 = Asciz	scala/collection/Iterator;
const #47 = class	#46;	//  scala/collection/Iterator
const #48 = Asciz	hasNext;
const #49 = Asciz	()Z;
const #50 = NameAndType	#48:#49;//  hasNext:()Z
const #51 = InterfaceMethod	#47.#50;	//  scala/collection/Iterator.hasNext:()Z
const #52 = Asciz	next;
const #53 = Asciz	()Ljava/lang/Object;;
const #54 = NameAndType	#52:#53;//  next:()Ljava/lang/Object;
const #55 = InterfaceMethod	#47.#54;	//  scala/collection/Iterator.next:()Ljava/lang/Object;
const #56 = Asciz	scala/util/regexp/Base$RegExp;
const #57 = class	#56;	//  scala/util/regexp/Base$RegExp
const #58 = Asciz	scala/util/regexp/WordExp$Letter;
const #59 = class	#58;	//  scala/util/regexp/WordExp$Letter
const #60 = Asciz	a;
const #61 = Asciz	()Lscala/util/regexp/WordExp$Label;;
const #62 = NameAndType	#60:#61;//  a:()Lscala/util/regexp/WordExp$Label;
const #63 = Method	#59.#62;	//  scala/util/regexp/WordExp$Letter.a:()Lscala/util/regexp/WordExp$Label;
const #64 = Asciz	scala/xml/dtd/ContentModel$ElemName;
const #65 = class	#64;	//  scala/xml/dtd/ContentModel$ElemName
const #66 = Asciz	name;
const #67 = Asciz	()Ljava/lang/String;;
const #68 = NameAndType	#66:#67;//  name:()Ljava/lang/String;
const #69 = Method	#65.#68;	//  scala/xml/dtd/ContentModel$ElemName.name:()Ljava/lang/String;
const #70 = Asciz	equals;
const #71 = Asciz	(Ljava/lang/Object;)Z;
const #72 = NameAndType	#70:#71;//  equals:(Ljava/lang/Object;)Z
const #73 = Method	#19.#72;	//  java/lang/Object.equals:(Ljava/lang/Object;)Z
const #74 = Asciz	java/lang/String;
const #75 = class	#74;	//  java/lang/String
const #76 = Asciz	this;
const #77 = Asciz	Lscala/xml/dtd/ElementValidator;;
const #78 = Asciz	Key;
const #79 = Asciz	Ljava/lang/String;;
const #80 = Asciz	res;
const #81 = Asciz	Z;
const #82 = Asciz	jt;
const #83 = Asciz	Lscala/collection/Iterator;;
const #84 = Asciz	temp27;
const #85 = Asciz	Lscala/util/regexp/Base$RegExp;;
const #86 = Asciz	temp28;
const #87 = Asciz	Lscala/util/regexp/WordExp$Letter;;
const #88 = Asciz	temp29;
const #89 = Asciz	Lscala/xml/dtd/ContentModel$ElemName;;
const #90 = Asciz	temp30;
const #91 = Asciz	LocalVariableTable;
const #92 = Asciz	gd3$1;
const #93 = Asciz	(Ljava/lang/String;Ljava/lang/String;Lscala/runtime/IntRef;Lscala/runtime/ObjectRef;)Z;
const #94 = Asciz	scala/runtime/ObjectRef;
const #95 = class	#94;	//  scala/runtime/ObjectRef
const #96 = Asciz	elem;
const #97 = Asciz	Ljava/lang/Object;;
const #98 = NameAndType	#96:#97;//  elem:Ljava/lang/Object;
const #99 = Field	#95.#98;	//  scala/runtime/ObjectRef.elem:Ljava/lang/Object;
const #100 = Asciz	scala/collection/mutable/BitSet;
const #101 = class	#100;	//  scala/collection/mutable/BitSet
const #102 = Asciz	scala/runtime/IntRef;
const #103 = class	#102;	//  scala/runtime/IntRef
const #104 = Asciz	I;
const #105 = NameAndType	#96:#104;//  elem:I
const #106 = Field	#103.#105;	//  scala/runtime/IntRef.elem:I
const #107 = Asciz	scala/runtime/BoxesRunTime;
const #108 = class	#107;	//  scala/runtime/BoxesRunTime
const #109 = Asciz	boxToInteger;
const #110 = Asciz	(I)Ljava/lang/Integer;;
const #111 = NameAndType	#109:#110;//  boxToInteger:(I)Ljava/lang/Integer;
const #112 = Method	#108.#111;	//  scala/runtime/BoxesRunTime.boxToInteger:(I)Ljava/lang/Integer;
const #113 = Asciz	scala/collection/generic/SetTemplate;
const #114 = class	#113;	//  scala/collection/generic/SetTemplate
const #115 = Asciz	apply;
const #116 = NameAndType	#115:#71;//  apply:(Ljava/lang/Object;)Z
const #117 = InterfaceMethod	#114.#116;	//  scala/collection/generic/SetTemplate.apply:(Ljava/lang/Object;)Z
const #118 = Asciz	gd2$1;
const #119 = Asciz	(Ljava/lang/String;Ljava/lang/String;Lscala/xml/MetaData;)Z;
const #120 = Asciz	scala/xml/MetaData;
const #121 = class	#120;	//  scala/xml/MetaData
const #122 = Asciz	value;
const #123 = Asciz	()Lscala/collection/Sequence;;
const #124 = NameAndType	#122:#123;//  value:()Lscala/collection/Sequence;
const #125 = Method	#121.#124;	//  scala/xml/MetaData.value:()Lscala/collection/Sequence;
const #126 = Asciz	scala/collection/generic/SequenceTemplate;
const #127 = class	#126;	//  scala/collection/generic/SequenceTemplate
const #128 = Asciz	toString;
const #129 = NameAndType	#128:#67;//  toString:()Ljava/lang/String;
const #130 = InterfaceMethod	#127.#129;	//  scala/collection/generic/SequenceTemplate.toString:()Ljava/lang/String;
const #131 = Asciz	find$1;
const #132 = Asciz	(Ljava/lang/String;Lscala/runtime/IntRef;Lscala/runtime/ObjectRef;)Lscala/xml/dtd/AttrDecl;;
const #133 = Asciz	()Lscala/collection/immutable/List;;
const #134 = NameAndType	#3:#133;//  adecls:()Lscala/collection/immutable/List;
const #135 = Method	#35.#134;	//  scala/xml/dtd/ElementValidator.adecls:()Lscala/collection/immutable/List;
const #136 = Asciz	scala/collection/generic/LinearSequenceTemplate;
const #137 = class	#136;	//  scala/collection/generic/LinearSequenceTemplate
const #138 = InterfaceMethod	#137.#44;	//  scala/collection/generic/LinearSequenceTemplate.iterator:()Lscala/collection/Iterator;
const #139 = Asciz	length;
const #140 = Asciz	()I;
const #141 = NameAndType	#139:#140;//  length:()I
const #142 = InterfaceMethod	#137.#141;	//  scala/collection/generic/LinearSequenceTemplate.length:()I
const #143 = Asciz	scala/xml/dtd/AttrDecl;
const #144 = class	#143;	//  scala/xml/dtd/AttrDecl
const #145 = Method	#144.#68;	//  scala/xml/dtd/AttrDecl.name:()Ljava/lang/String;
const #146 = Asciz	$plus$eq;
const #147 = Asciz	(I)Lscala/collection/mutable/BitSet;;
const #148 = NameAndType	#146:#147;//  $plus$eq:(I)Lscala/collection/mutable/BitSet;
const #149 = Method	#101.#148;	//  scala/collection/mutable/BitSet.$plus$eq:(I)Lscala/collection/mutable/BitSet;
const #150 = Asciz	scala/MatchError;
const #151 = class	#150;	//  scala/MatchError
const #152 = Method	#144.#129;	//  scala/xml/dtd/AttrDecl.toString:()Ljava/lang/String;
const #153 = Asciz	(Ljava/lang/String;)V;
const #154 = NameAndType	#14:#153;//  "<init>":(Ljava/lang/String;)V
const #155 = Method	#151.#154;	//  scala/MatchError."<init>":(Ljava/lang/String;)V
const #156 = Asciz	attr;
const #157 = Asciz	Lscala/xml/dtd/AttrDecl;;
const #158 = Asciz	temp8;
const #159 = Asciz	temp9;
const #160 = Asciz	(Ljava/lang/Object;)Ljava/lang/Object;;
const #161 = Asciz	scala/xml/Node;
const #162 = class	#161;	//  scala/xml/Node
const #163 = Asciz	(Lscala/xml/Node;)Z;
const #164 = NameAndType	#115:#163;//  apply:(Lscala/xml/Node;)Z
const #165 = Method	#35.#164;	//  scala/xml/dtd/ElementValidator.apply:(Lscala/xml/Node;)Z
const #166 = Asciz	boxToBoolean;
const #167 = Asciz	(Z)Ljava/lang/Boolean;;
const #168 = NameAndType	#166:#167;//  boxToBoolean:(Z)Ljava/lang/Boolean;
const #169 = Method	#108.#168;	//  scala/runtime/BoxesRunTime.boxToBoolean:(Z)Ljava/lang/Boolean;
const #170 = Asciz	v1;
const #171 = Asciz	()Lscala/xml/dtd/ContentModel;;
const #172 = NameAndType	#10:#171;//  contentModel:()Lscala/xml/dtd/ContentModel;
const #173 = Method	#35.#172;	//  scala/xml/dtd/ElementValidator.contentModel:()Lscala/xml/dtd/ContentModel;
const #174 = Asciz	child;
const #175 = NameAndType	#174:#123;//  child:()Lscala/collection/Sequence;
const #176 = Method	#162.#175;	//  scala/xml/Node.child:()Lscala/collection/Sequence;
const #177 = Asciz	check;
const #178 = Asciz	(Lscala/collection/Sequence;)Z;
const #179 = NameAndType	#177:#178;//  check:(Lscala/collection/Sequence;)Z
const #180 = Method	#35.#179;	//  scala/xml/dtd/ElementValidator.check:(Lscala/collection/Sequence;)Z
const #181 = Asciz	attributes;
const #182 = Asciz	()Lscala/xml/MetaData;;
const #183 = NameAndType	#181:#182;//  attributes:()Lscala/xml/MetaData;
const #184 = Method	#162.#183;	//  scala/xml/Node.attributes:()Lscala/xml/MetaData;
const #185 = Asciz	(Lscala/xml/MetaData;)Z;
const #186 = NameAndType	#177:#185;//  check:(Lscala/xml/MetaData;)Z
const #187 = Method	#35.#186;	//  scala/xml/dtd/ElementValidator.check:(Lscala/xml/MetaData;)Z
const #188 = Asciz	n;
const #189 = Asciz	Lscala/xml/Node;;
const #190 = Asciz	scala/xml/dtd/ANY$;
const #191 = class	#190;	//  scala/xml/dtd/ANY$
const #192 = Asciz	Lscala/xml/dtd/ANY$;;
const #193 = NameAndType	#30:#192;//  MODULE$:Lscala/xml/dtd/ANY$;
const #194 = Field	#191.#193;	//  scala/xml/dtd/ANY$.MODULE$:Lscala/xml/dtd/ANY$;
const #195 = Asciz	scala/xml/dtd/EMPTY$;
const #196 = class	#195;	//  scala/xml/dtd/EMPTY$
const #197 = Asciz	Lscala/xml/dtd/EMPTY$;;
const #198 = NameAndType	#30:#197;//  MODULE$:Lscala/xml/dtd/EMPTY$;
const #199 = Field	#196.#198;	//  scala/xml/dtd/EMPTY$.MODULE$:Lscala/xml/dtd/EMPTY$;
const #200 = Asciz	getIterator;
const #201 = Asciz	(Lscala/collection/Sequence;Z)Lscala/collection/Iterator;;
const #202 = NameAndType	#200:#201;//  getIterator:(Lscala/collection/Sequence;Z)Lscala/collection/Iterator;
const #203 = Method	#35.#202;	//  scala/xml/dtd/ElementValidator.getIterator:(Lscala/collection/Sequence;Z)Lscala/collection/Iterator;
const #204 = Asciz	scala/xml/dtd/PCDATA$;
const #205 = class	#204;	//  scala/xml/dtd/PCDATA$
const #206 = Asciz	Lscala/xml/dtd/PCDATA$;;
const #207 = NameAndType	#30:#206;//  MODULE$:Lscala/xml/dtd/PCDATA$;
const #208 = Field	#205.#207;	//  scala/xml/dtd/PCDATA$.MODULE$:Lscala/xml/dtd/PCDATA$;
const #209 = Asciz	scala/xml/dtd/MIXED;
const #210 = class	#209;	//  scala/xml/dtd/MIXED
const #211 = Asciz	r;
const #212 = Asciz	()Lscala/util/regexp/Base$RegExp;;
const #213 = NameAndType	#211:#212;//  r:()Lscala/util/regexp/Base$RegExp;
const #214 = Method	#210.#213;	//  scala/xml/dtd/MIXED.r:()Lscala/util/regexp/Base$RegExp;
const #215 = Asciz	scala/util/regexp/Base$Alt;
const #216 = class	#215;	//  scala/util/regexp/Base$Alt
const #217 = Asciz	rs;
const #218 = NameAndType	#217:#123;//  rs:()Lscala/collection/Sequence;
const #219 = Method	#216.#218;	//  scala/util/regexp/Base$Alt.rs:()Lscala/collection/Sequence;
const #220 = Asciz	lengthCompare;
const #221 = Asciz	(I)I;
const #222 = NameAndType	#220:#221;//  lengthCompare:(I)I
const #223 = InterfaceMethod	#127.#222;	//  scala/collection/generic/SequenceTemplate.lengthCompare:(I)I
const #224 = NameAndType	#12:#133;//  exc:()Lscala/collection/immutable/List;
const #225 = Method	#35.#224;	//  scala/xml/dtd/ElementValidator.exc:()Lscala/collection/immutable/List;
const #226 = NameAndType	#38:#39;//  find$2:(Ljava/lang/String;Lscala/collection/Sequence;)Z
const #227 = Method	#35.#226;	//  scala/xml/dtd/ElementValidator.find$2:(Ljava/lang/String;Lscala/collection/Sequence;)Z
const #228 = Asciz	scala/xml/dtd/MakeValidationException$;
const #229 = class	#228;	//  scala/xml/dtd/MakeValidationException$
const #230 = Asciz	Lscala/xml/dtd/MakeValidationException$;;
const #231 = NameAndType	#30:#230;//  MODULE$:Lscala/xml/dtd/MakeValidationException$;
const #232 = Field	#229.#231;	//  scala/xml/dtd/MakeValidationException$.MODULE$:Lscala/xml/dtd/MakeValidationException$;
const #233 = Asciz	fromUndefinedElement;
const #234 = Asciz	(Ljava/lang/String;)Lscala/xml/dtd/ValidationException;;
const #235 = NameAndType	#233:#234;//  fromUndefinedElement:(Ljava/lang/String;)Lscala/xml/dtd/ValidationException;
const #236 = Method	#229.#235;	//  scala/xml/dtd/MakeValidationException$.fromUndefinedElement:(Ljava/lang/String;)Lscala/xml/dtd/ValidationException;
const #237 = Asciz	scala/collection/immutable/List;
const #238 = class	#237;	//  scala/collection/immutable/List
const #239 = Asciz	$colon$colon;
const #240 = Asciz	(Ljava/lang/Object;)Lscala/collection/immutable/List;;
const #241 = NameAndType	#239:#240;//  $colon$colon:(Ljava/lang/Object;)Lscala/collection/immutable/List;
const #242 = Method	#238.#241;	//  scala/collection/immutable/List.$colon$colon:(Ljava/lang/Object;)Lscala/collection/immutable/List;
const #243 = Asciz	exc_$eq;
const #244 = Asciz	(Lscala/collection/immutable/List;)V;
const #245 = NameAndType	#243:#244;//  exc_$eq:(Lscala/collection/immutable/List;)V
const #246 = Method	#35.#245;	//  scala/xml/dtd/ElementValidator.exc_$eq:(Lscala/collection/immutable/List;)V
const #247 = Asciz	scala/xml/dtd/ContentModel;
const #248 = class	#247;	//  scala/xml/dtd/ContentModel
const #249 = Method	#248.#129;	//  scala/xml/dtd/ContentModel.toString:()Ljava/lang/String;
const #250 = Asciz	scala/xml/dtd/ELEMENTS;
const #251 = class	#250;	//  scala/xml/dtd/ELEMENTS
const #252 = Asciz	()Lscala/util/automata/DetWordAutom;;
const #253 = NameAndType	#7:#252;//  dfa:()Lscala/util/automata/DetWordAutom;
const #254 = Method	#35.#253;	//  scala/xml/dtd/ElementValidator.dfa:()Lscala/util/automata/DetWordAutom;
const #255 = Asciz	scala/util/automata/DetWordAutom;
const #256 = class	#255;	//  scala/util/automata/DetWordAutom
const #257 = Asciz	delta;
const #258 = Asciz	()[Lscala/collection/Map;;
const #259 = NameAndType	#257:#258;//  delta:()[Lscala/collection/Map;
const #260 = Method	#256.#259;	//  scala/util/automata/DetWordAutom.delta:()[Lscala/collection/Map;
const #261 = Asciz	scala/collection/generic/MapTemplate;
const #262 = class	#261;	//  scala/collection/generic/MapTemplate
const #263 = Asciz	get;
const #264 = Asciz	(Ljava/lang/Object;)Lscala/Option;;
const #265 = NameAndType	#263:#264;//  get:(Ljava/lang/Object;)Lscala/Option;
const #266 = InterfaceMethod	#262.#265;	//  scala/collection/generic/MapTemplate.get:(Ljava/lang/Object;)Lscala/Option;
const #267 = Asciz	scala/Some;
const #268 = class	#267;	//  scala/Some
const #269 = Asciz	x;
const #270 = NameAndType	#269:#53;//  x:()Ljava/lang/Object;
const #271 = Method	#268.#270;	//  scala/Some.x:()Ljava/lang/Object;
const #272 = Asciz	unboxToInt;
const #273 = Asciz	(Ljava/lang/Object;)I;
const #274 = NameAndType	#272:#273;//  unboxToInt:(Ljava/lang/Object;)I
const #275 = Method	#108.#274;	//  scala/runtime/BoxesRunTime.unboxToInt:(Ljava/lang/Object;)I
const #276 = Asciz	scala/xml/dtd/ValidationException;
const #277 = class	#276;	//  scala/xml/dtd/ValidationException
const #278 = Asciz	scala/collection/mutable/StringBuilder;
const #279 = class	#278;	//  scala/collection/mutable/StringBuilder
const #280 = Method	#279.#20;	//  scala/collection/mutable/StringBuilder."<init>":()V
const #281 = Asciz	element ;
const #282 = String	#281;	//  element 
const #283 = Asciz	append;
const #284 = Asciz	(Ljava/lang/Object;)Lscala/collection/mutable/StringBuilder;;
const #285 = NameAndType	#283:#284;//  append:(Ljava/lang/Object;)Lscala/collection/mutable/StringBuilder;
const #286 = Method	#279.#285;	//  scala/collection/mutable/StringBuilder.append:(Ljava/lang/Object;)Lscala/collection/mutable/StringBuilder;
const #287 = Asciz	 not allowed here;
const #288 = String	#287;	//   not allowed here
const #289 = Method	#279.#129;	//  scala/collection/mutable/StringBuilder.toString:()Ljava/lang/String;
const #290 = Method	#277.#154;	//  scala/xml/dtd/ValidationException."<init>":(Ljava/lang/String;)V
const #291 = Asciz	isFinal;
const #292 = Asciz	(I)Z;
const #293 = NameAndType	#291:#292;//  isFinal:(I)Z
const #294 = Method	#256.#293;	//  scala/util/automata/DetWordAutom.isFinal:(I)Z
const #295 = Asciz	nodes;
const #296 = Asciz	Lscala/collection/Sequence;;
const #297 = Asciz	temp35;
const #298 = Asciz	temp39;
const #299 = Asciz	Lscala/xml/dtd/MIXED;;
const #300 = Asciz	temp40;
const #301 = Asciz	temp41;
const #302 = Asciz	Lscala/util/regexp/Base$Alt;;
const #303 = Asciz	temp42;
const #304 = Asciz	temp43;
const #305 = Asciz	branches$1;
const #306 = Asciz	j;
const #307 = Asciz	it;
const #308 = Asciz	label;
const #309 = Asciz	q;
const #310 = Asciz	e;
const #311 = Asciz	temp32;
const #312 = Asciz	Lscala/Option;;
const #313 = Asciz	temp33;
const #314 = Asciz	Lscala/Some;;
const #315 = Asciz	temp34;
const #316 = Asciz	(Lscala/collection/Sequence<Lscala/xml/Node;>;)Z;
const #317 = Asciz	(I)V;
const #318 = NameAndType	#14:#317;//  "<init>":(I)V
const #319 = Method	#103.#318;	//  scala/runtime/IntRef."<init>":(I)V
const #320 = Method	#101.#318;	//  scala/collection/mutable/BitSet."<init>":(I)V
const #321 = Asciz	(Ljava/lang/Object;)V;
const #322 = NameAndType	#14:#321;//  "<init>":(Ljava/lang/Object;)V
const #323 = Method	#95.#322;	//  scala/runtime/ObjectRef."<init>":(Ljava/lang/Object;)V
const #324 = Method	#121.#44;	//  scala/xml/MetaData.iterator:()Lscala/collection/Iterator;
const #325 = Asciz	key;
const #326 = NameAndType	#325:#67;//  key:()Ljava/lang/String;
const #327 = Method	#121.#326;	//  scala/xml/MetaData.key:()Ljava/lang/String;
const #328 = NameAndType	#131:#132;//  find$1:(Ljava/lang/String;Lscala/runtime/IntRef;Lscala/runtime/ObjectRef;)Lscala/xml/dtd/AttrDecl;
const #329 = Method	#35.#328;	//  scala/xml/dtd/ElementValidator.find$1:(Ljava/lang/String;Lscala/runtime/IntRef;Lscala/runtime/ObjectRef;)Lscala/xml/dtd/AttrDecl;
const #330 = Asciz	fromUndefinedAttribute;
const #331 = NameAndType	#330:#234;//  fromUndefinedAttribute:(Ljava/lang/String;)Lscala/xml/dtd/ValidationException;
const #332 = Method	#229.#331;	//  scala/xml/dtd/MakeValidationException$.fromUndefinedAttribute:(Ljava/lang/String;)Lscala/xml/dtd/ValidationException;
const #333 = Asciz	tpe;
const #334 = NameAndType	#333:#67;//  tpe:()Ljava/lang/String;
const #335 = Method	#144.#334;	//  scala/xml/dtd/AttrDecl.tpe:()Ljava/lang/String;
const #336 = Asciz	default;
const #337 = Asciz	()Lscala/xml/dtd/DefaultDecl;;
const #338 = NameAndType	#336:#337;//  default:()Lscala/xml/dtd/DefaultDecl;
const #339 = Method	#144.#338;	//  scala/xml/dtd/AttrDecl.default:()Lscala/xml/dtd/DefaultDecl;
const #340 = Asciz	scala/xml/dtd/DEFAULT;
const #341 = class	#340;	//  scala/xml/dtd/DEFAULT
const #342 = Asciz	attValue;
const #343 = NameAndType	#342:#67;//  attValue:()Ljava/lang/String;
const #344 = Method	#341.#343;	//  scala/xml/dtd/DEFAULT.attValue:()Ljava/lang/String;
const #345 = Asciz	fixed;
const #346 = NameAndType	#345:#49;//  fixed:()Z
const #347 = Method	#341.#346;	//  scala/xml/dtd/DEFAULT.fixed:()Z
const #348 = Asciz	(Ljava/lang/Object;Ljava/lang/Object;)Z;
const #349 = NameAndType	#70:#348;//  equals:(Ljava/lang/Object;Ljava/lang/Object;)Z
const #350 = Method	#108.#349;	//  scala/runtime/BoxesRunTime.equals:(Ljava/lang/Object;Ljava/lang/Object;)Z
const #351 = NameAndType	#118:#119;//  gd2$1:(Ljava/lang/String;Ljava/lang/String;Lscala/xml/MetaData;)Z
const #352 = Method	#35.#351;	//  scala/xml/dtd/ElementValidator.gd2$1:(Ljava/lang/String;Ljava/lang/String;Lscala/xml/MetaData;)Z
const #353 = Asciz	fromFixedAttribute;
const #354 = Asciz	(Ljava/lang/String;Ljava/lang/String;Ljava/lang/String;)Lscala/xml/dtd/ValidationException;;
const #355 = NameAndType	#353:#354;//  fromFixedAttribute:(Ljava/lang/String;Ljava/lang/String;Ljava/lang/String;)Lscala/xml/dtd/ValidationException;
const #356 = Method	#229.#355;	//  scala/xml/dtd/MakeValidationException$.fromFixedAttribute:(Ljava/lang/String;Ljava/lang/String;Ljava/lang/String;)Lscala/xml/dtd/ValidationException;
const #357 = Asciz	scala/xml/dtd/REQUIRED$;
const #358 = class	#357;	//  scala/xml/dtd/REQUIRED$
const #359 = Asciz	Lscala/xml/dtd/REQUIRED$;;
const #360 = NameAndType	#30:#359;//  MODULE$:Lscala/xml/dtd/REQUIRED$;
const #361 = Field	#358.#360;	//  scala/xml/dtd/REQUIRED$.MODULE$:Lscala/xml/dtd/REQUIRED$;
const #362 = NameAndType	#92:#93;//  gd3$1:(Ljava/lang/String;Ljava/lang/String;Lscala/runtime/IntRef;Lscala/runtime/ObjectRef;)Z
const #363 = Method	#35.#362;	//  scala/xml/dtd/ElementValidator.gd3$1:(Ljava/lang/String;Ljava/lang/String;Lscala/runtime/IntRef;Lscala/runtime/ObjectRef;)Z
const #364 = Asciz	fromMissingAttribute;
const #365 = Asciz	(Ljava/lang/String;Ljava/lang/String;)Lscala/xml/dtd/ValidationException;;
const #366 = NameAndType	#364:#365;//  fromMissingAttribute:(Ljava/lang/String;Ljava/lang/String;)Lscala/xml/dtd/ValidationException;
const #367 = Method	#229.#366;	//  scala/xml/dtd/MakeValidationException$.fromMissingAttribute:(Ljava/lang/String;Ljava/lang/String;)Lscala/xml/dtd/ValidationException;
const #368 = Asciz	md;
const #369 = Asciz	Lscala/xml/MetaData;;
const #370 = Asciz	len;
const #371 = Asciz	j$1;
const #372 = Asciz	Lscala/runtime/IntRef;;
const #373 = Asciz	ok$1;
const #374 = Asciz	Lscala/runtime/ObjectRef;;
const #375 = Asciz	attr$1;
const #376 = Asciz	temp13;
const #377 = Asciz	temp16;
const #378 = Asciz	temp17;
const #379 = Asciz	Lscala/xml/dtd/DefaultDecl;;
const #380 = Asciz	temp18;
const #381 = Asciz	Lscala/xml/dtd/DEFAULT;;
const #382 = Asciz	temp20;
const #383 = Asciz	fixedValue;
const #384 = Asciz	kt;
const #385 = Asciz	temp22;
const #386 = Asciz	temp23;
const #387 = Asciz	temp24;
const #388 = Asciz	temp25;
const #389 = Asciz	scala/collection/generic/TraversableTemplate;
const #390 = class	#389;	//  scala/collection/generic/TraversableTemplate
const #391 = Asciz	toList;
const #392 = NameAndType	#391:#133;//  toList:()Lscala/collection/immutable/List;
const #393 = InterfaceMethod	#390.#392;	//  scala/collection/generic/TraversableTemplate.toList:()Lscala/collection/immutable/List;
const #394 = Asciz	scala/xml/dtd/ElementValidator$$anonfun$getIterator$1;
const #395 = class	#394;	//  scala/xml/dtd/ElementValidator$$anonfun$getIterator$1
const #396 = Asciz	(Lscala/xml/dtd/ElementValidator;Z)V;
const #397 = NameAndType	#14:#396;//  "<init>":(Lscala/xml/dtd/ElementValidator;Z)V
const #398 = Method	#395.#397;	//  scala/xml/dtd/ElementValidator$$anonfun$getIterator$1."<init>":(Lscala/xml/dtd/ElementValidator;Z)V
const #399 = Asciz	filter;
const #400 = Asciz	(Lscala/Function1;)Lscala/collection/generic/TraversableTemplate;;
const #401 = NameAndType	#399:#400;//  filter:(Lscala/Function1;)Lscala/collection/generic/TraversableTemplate;
const #402 = InterfaceMethod	#390.#401;	//  scala/collection/generic/TraversableTemplate.filter:(Lscala/Function1;)Lscala/collection/generic/TraversableTemplate;
const #403 = Asciz	scala/xml/dtd/ElementValidator$$anonfun$getIterator$2;
const #404 = class	#403;	//  scala/xml/dtd/ElementValidator$$anonfun$getIterator$2
const #405 = Asciz	(Lscala/xml/dtd/ElementValidator;)V;
const #406 = NameAndType	#14:#405;//  "<init>":(Lscala/xml/dtd/ElementValidator;)V
const #407 = Method	#404.#406;	//  scala/xml/dtd/ElementValidator$$anonfun$getIterator$2."<init>":(Lscala/xml/dtd/ElementValidator;)V
const #408 = Asciz	scala/collection/immutable/List$;
const #409 = class	#408;	//  scala/collection/immutable/List$
const #410 = Asciz	Lscala/collection/immutable/List$;;
const #411 = NameAndType	#30:#410;//  MODULE$:Lscala/collection/immutable/List$;
const #412 = Field	#409.#411;	//  scala/collection/immutable/List$.MODULE$:Lscala/collection/immutable/List$;
const #413 = Asciz	builderFactory;
const #414 = Asciz	()Lscala/collection/generic/BuilderFactory;;
const #415 = NameAndType	#413:#414;//  builderFactory:()Lscala/collection/generic/BuilderFactory;
const #416 = Method	#409.#415;	//  scala/collection/immutable/List$.builderFactory:()Lscala/collection/generic/BuilderFactory;
const #417 = Asciz	map;
const #418 = Asciz	(Lscala/Function1;Lscala/collection/generic/BuilderFactory;)Ljava/lang/Object;;
const #419 = NameAndType	#417:#418;//  map:(Lscala/Function1;Lscala/collection/generic/BuilderFactory;)Ljava/lang/Object;
const #420 = InterfaceMethod	#390.#419;	//  scala/collection/generic/TraversableTemplate.map:(Lscala/Function1;Lscala/collection/generic/BuilderFactory;)Ljava/lang/Object;
const #421 = Asciz	skipPCDATA$1;
const #422 = Asciz	(Lscala/collection/Sequence<Lscala/xml/Node;>;Z)Lscala/collection/Iterator<Lscala/xml/dtd/ContentModel$ElemName;>;;
const #423 = Asciz	setMetaData;
const #424 = Asciz	adecls_$eq;
const #425 = NameAndType	#424:#244;//  adecls_$eq:(Lscala/collection/immutable/List;)V
const #426 = Method	#35.#425;	//  scala/xml/dtd/ElementValidator.adecls_$eq:(Lscala/collection/immutable/List;)V
const #427 = Asciz	(Lscala/collection/immutable/List<Lscala/xml/dtd/AttrDecl;>;)V;
const #428 = Asciz	getContentModel;
const #429 = Asciz	setContentModel;
const #430 = Asciz	(Lscala/xml/dtd/ContentModel;)V;
const #431 = Asciz	contentModel_$eq;
const #432 = NameAndType	#431:#430;//  contentModel_$eq:(Lscala/xml/dtd/ContentModel;)V
const #433 = Method	#35.#432;	//  scala/xml/dtd/ElementValidator.contentModel_$eq:(Lscala/xml/dtd/ContentModel;)V
const #434 = Method	#251.#213;	//  scala/xml/dtd/ELEMENTS.r:()Lscala/util/regexp/Base$RegExp;
const #435 = Asciz	scala/xml/dtd/ContentModel$Translator$;
const #436 = class	#435;	//  scala/xml/dtd/ContentModel$Translator$
const #437 = Asciz	Lscala/xml/dtd/ContentModel$Translator$;;
const #438 = NameAndType	#30:#437;//  MODULE$:Lscala/xml/dtd/ContentModel$Translator$;
const #439 = Field	#436.#438;	//  scala/xml/dtd/ContentModel$Translator$.MODULE$:Lscala/xml/dtd/ContentModel$Translator$;
const #440 = Asciz	automatonFrom;
const #441 = Asciz	(Lscala/util/regexp/Base$RegExp;I)Lscala/util/automata/NondetWordAutom;;
const #442 = NameAndType	#440:#441;//  automatonFrom:(Lscala/util/regexp/Base$RegExp;I)Lscala/util/automata/NondetWordAutom;
const #443 = Method	#436.#442;	//  scala/xml/dtd/ContentModel$Translator$.automatonFrom:(Lscala/util/regexp/Base$RegExp;I)Lscala/util/automata/NondetWordAutom;
const #444 = Asciz	scala/util/automata/SubsetConstruction;
const #445 = class	#444;	//  scala/util/automata/SubsetConstruction
const #446 = Asciz	(Lscala/util/automata/NondetWordAutom;)V;
const #447 = NameAndType	#14:#446;//  "<init>":(Lscala/util/automata/NondetWordAutom;)V
const #448 = Method	#445.#447;	//  scala/util/automata/SubsetConstruction."<init>":(Lscala/util/automata/NondetWordAutom;)V
const #449 = Asciz	determinize;
const #450 = NameAndType	#449:#252;//  determinize:()Lscala/util/automata/DetWordAutom;
const #451 = Method	#445.#450;	//  scala/util/automata/SubsetConstruction.determinize:()Lscala/util/automata/DetWordAutom;
const #452 = Asciz	dfa_$eq;
const #453 = Asciz	(Lscala/util/automata/DetWordAutom;)V;
const #454 = NameAndType	#452:#453;//  dfa_$eq:(Lscala/util/automata/DetWordAutom;)V
const #455 = Method	#35.#454;	//  scala/xml/dtd/ElementValidator.dfa_$eq:(Lscala/util/automata/DetWordAutom;)V
const #456 = Asciz	cm;
const #457 = Asciz	temp1;
const #458 = Asciz	temp2;
const #459 = Asciz	Lscala/xml/dtd/ELEMENTS;;
const #460 = Asciz	temp3;
const #461 = Asciz	nfa;
const #462 = Asciz	Lscala/util/automata/NondetWordAutom;;
const #463 = NameAndType	#3:#4;//  adecls:Lscala/collection/immutable/List;
const #464 = Field	#35.#463;	//  scala/xml/dtd/ElementValidator.adecls:Lscala/collection/immutable/List;
const #465 = Asciz	()Lscala/collection/immutable/List<Lscala/xml/dtd/AttrDecl;>;;
const #466 = NameAndType	#7:#8;//  dfa:Lscala/util/automata/DetWordAutom;
const #467 = Field	#35.#466;	//  scala/xml/dtd/ElementValidator.dfa:Lscala/util/automata/DetWordAutom;
const #468 = Asciz	(Lscala/util/automata/DetWordAutom<Lscala/xml/dtd/ContentModel$ElemName;>;)V;
const #469 = Asciz	()Lscala/util/automata/DetWordAutom<Lscala/xml/dtd/ContentModel$ElemName;>;;
const #470 = NameAndType	#10:#11;//  contentModel:Lscala/xml/dtd/ContentModel;
const #471 = Field	#35.#470;	//  scala/xml/dtd/ElementValidator.contentModel:Lscala/xml/dtd/ContentModel;
const #472 = Asciz	(Lscala/collection/immutable/List<Lscala/xml/dtd/ValidationException;>;)V;
const #473 = Asciz	()Lscala/collection/immutable/List<Lscala/xml/dtd/ValidationException;>;;
const #474 = Asciz	andThen;
const #475 = Asciz	(Lscala/Function1;)Lscala/Function1;;
const #476 = Asciz	(Lscala/Function1;Lscala/Function1;)Lscala/Function1;;
const #477 = NameAndType	#474:#476;//  andThen:(Lscala/Function1;Lscala/Function1;)Lscala/Function1;
const #478 = Method	#23.#477;	//  scala/Function1$class.andThen:(Lscala/Function1;Lscala/Function1;)Lscala/Function1;
const #479 = Asciz	g;
const #480 = Asciz	Lscala/Function1;;
const #481 = Asciz	compose;
const #482 = NameAndType	#481:#476;//  compose:(Lscala/Function1;Lscala/Function1;)Lscala/Function1;
const #483 = Method	#23.#482;	//  scala/Function1$class.compose:(Lscala/Function1;Lscala/Function1;)Lscala/Function1;
const #484 = Asciz	(Lscala/Function1;)Ljava/lang/String;;
const #485 = NameAndType	#128:#484;//  toString:(Lscala/Function1;)Ljava/lang/String;
const #486 = Method	#23.#485;	//  scala/Function1$class.toString:(Lscala/Function1;)Ljava/lang/String;
const #487 = Asciz	Ljava/lang/Object;Lscala/Function1<Lscala/xml/Node;Ljava/lang/Boolean;>;Lscala/ScalaObject;;
const #488 = Asciz	ScalaSig;
const #489 = Asciz	InnerClasses;
const #490 = Asciz	scala/util/regexp/Base;
const #491 = class	#490;	//  scala/util/regexp/Base
const #492 = Asciz	Alt;
const #493 = Asciz	RegExp;
const #494 = Asciz	scala/util/regexp/WordExp$Label;
const #495 = class	#494;	//  scala/util/regexp/WordExp$Label
const #496 = Asciz	scala/util/regexp/WordExp;
const #497 = class	#496;	//  scala/util/regexp/WordExp
const #498 = Asciz	Label;
const #499 = Asciz	Letter;
const #500 = Asciz	ElemName;
const #501 = Asciz	$anonfun$getIterator$1;
const #502 = Asciz	$anonfun$getIterator$2;
const #503 = Asciz	scala/Function1;
const #504 = class	#503;	//  scala/Function1
const #505 = Asciz	scala/ScalaObject;
const #506 = class	#505;	//  scala/ScalaObject

{
public scala.xml.dtd.ElementValidator();
  Code:
   Stack=2, Locals=1, Args_size=1
   0:	aload_0
   1:	invokespecial	#21; //Method java/lang/Object."<init>":()V
   4:	aload_0
   5:	invokestatic	#27; //Method scala/Function1$class.$init$:(Lscala/Function1;)V
   8:	aload_0
   9:	getstatic	#33; //Field scala/collection/immutable/Nil$.MODULE$:Lscala/collection/immutable/Nil$;
   12:	putfield	#37; //Field exc:Lscala/collection/immutable/List;
   15:	return
  LineNumberTable: 
   line 21: 0
   line 23: 8


public java.lang.Object apply(java.lang.Object);
  Code:
   Stack=2, Locals=2, Args_size=2
   0:	aload_0
   1:	aload_1
   2:	checkcast	#162; //class scala/xml/Node
   5:	invokevirtual	#165; //Method apply:(Lscala/xml/Node;)Z
   8:	invokestatic	#169; //Method scala/runtime/BoxesRunTime.boxToBoolean:(Z)Ljava/lang/Boolean;
   11:	areturn
  LineNumberTable: 
   line 21: 0

  LocalVariableTable: 
   Start  Length  Slot  Name   Signature
   0      12      0    this       Lscala/xml/dtd/ElementValidator;
   0      12      1    v1       Ljava/lang/Object;


public boolean apply(scala.xml.Node);
  Code:
   Stack=2, Locals=3, Args_size=2
   0:	aload_0
   1:	invokevirtual	#173; //Method contentModel:()Lscala/xml/dtd/ContentModel;
   4:	ifnull	18
   7:	aload_0
   8:	aload_1
   9:	invokevirtual	#176; //Method scala/xml/Node.child:()Lscala/collection/Sequence;
   12:	invokevirtual	#180; //Method check:(Lscala/collection/Sequence;)Z
   15:	ifeq	22
   18:	iconst_1
   19:	goto	23
   22:	iconst_0
   23:	istore_2
   24:	aload_0
   25:	invokevirtual	#135; //Method adecls:()Lscala/collection/immutable/List;
   28:	ifnull	42
   31:	aload_0
   32:	aload_1
   33:	invokevirtual	#184; //Method scala/xml/Node.attributes:()Lscala/xml/MetaData;
   36:	invokevirtual	#187; //Method check:(Lscala/xml/MetaData;)Z
   39:	ifeq	50
   42:	iload_2
   43:	ifeq	50
   46:	iconst_1
   47:	goto	51
   50:	iconst_0
   51:	istore_2
   52:	iload_2
   53:	ireturn
  LineNumberTable: 
   line 168: 0
   line 171: 24
   line 173: 52

  LocalVariableTable: 
   Start  Length  Slot  Name   Signature
   0      54      0    this       Lscala/xml/dtd/ElementValidator;
   0      54      1    n       Lscala/xml/Node;
   24      29      2    res       Z


public boolean check(scala.collection.Sequence);
  Code:
   Stack=4, Locals=22, Args_size=2
   0:	aload_0
   1:	invokevirtual	#173; //Method contentModel:()Lscala/xml/dtd/ContentModel;
   4:	astore_2
   5:	getstatic	#194; //Field scala/xml/dtd/ANY$.MODULE$:Lscala/xml/dtd/ANY$;
   8:	aload_2
   9:	astore_3
   10:	dup
   11:	ifnonnull	22
   14:	pop
   15:	aload_3
   16:	ifnull	29
   19:	goto	40
   22:	aload_3
   23:	invokevirtual	#73; //Method java/lang/Object.equals:(Ljava/lang/Object;)Z
   26:	ifeq	40
   29:	aload_2
   30:	instanceof	#191; //class scala/xml/dtd/ANY$
   33:	ifeq	40
   36:	iconst_1
   37:	goto	476
   40:	getstatic	#199; //Field scala/xml/dtd/EMPTY$.MODULE$:Lscala/xml/dtd/EMPTY$;
   43:	aload_2
   44:	astore	4
   46:	dup
   47:	ifnonnull	59
   50:	pop
   51:	aload	4
   53:	ifnull	67
   56:	goto	96
   59:	aload	4
   61:	invokevirtual	#73; //Method java/lang/Object.equals:(Ljava/lang/Object;)Z
   64:	ifeq	96
   67:	aload_2
   68:	instanceof	#196; //class scala/xml/dtd/EMPTY$
   71:	ifeq	96
   74:	aload_0
   75:	aload_1
   76:	iconst_0
   77:	invokevirtual	#203; //Method getIterator:(Lscala/collection/Sequence;Z)Lscala/collection/Iterator;
   80:	invokeinterface	#51,  1; //InterfaceMethod scala/collection/Iterator.hasNext:()Z
   85:	ifeq	92
   88:	iconst_0
   89:	goto	476
   92:	iconst_1
   93:	goto	476
   96:	getstatic	#208; //Field scala/xml/dtd/PCDATA$.MODULE$:Lscala/xml/dtd/PCDATA$;
   99:	aload_2
   100:	astore	5
   102:	dup
   103:	ifnonnull	115
   106:	pop
   107:	aload	5
   109:	ifnull	123
   112:	goto	152
   115:	aload	5
   117:	invokevirtual	#73; //Method java/lang/Object.equals:(Ljava/lang/Object;)Z
   120:	ifeq	152
   123:	aload_2
   124:	instanceof	#205; //class scala/xml/dtd/PCDATA$
   127:	ifeq	152
   130:	aload_0
   131:	aload_1
   132:	iconst_1
   133:	invokevirtual	#203; //Method getIterator:(Lscala/collection/Sequence;Z)Lscala/collection/Iterator;
   136:	invokeinterface	#51,  1; //InterfaceMethod scala/collection/Iterator.hasNext:()Z
   141:	ifeq	148
   144:	iconst_0
   145:	goto	476
   148:	iconst_1
   149:	goto	476
   152:	aload_2
   153:	instanceof	#210; //class scala/xml/dtd/MIXED
   156:	ifeq	341
   159:	aload_2
   160:	checkcast	#210; //class scala/xml/dtd/MIXED
   163:	astore	6
   165:	aload	6
   167:	invokevirtual	#214; //Method scala/xml/dtd/MIXED.r:()Lscala/util/regexp/Base$RegExp;
   170:	astore	7
   172:	aload	7
   174:	instanceof	#216; //class scala/util/regexp/Base$Alt
   177:	ifeq	329
   180:	aload	7
   182:	checkcast	#216; //class scala/util/regexp/Base$Alt
   185:	astore	8
   187:	aload	8
   189:	invokevirtual	#219; //Method scala/util/regexp/Base$Alt.rs:()Lscala/collection/Sequence;
   192:	astore	9
   194:	aload	9
   196:	iconst_0
   197:	invokeinterface	#223,  2; //InterfaceMethod scala/collection/generic/SequenceTemplate.lengthCompare:(I)I
   202:	iconst_0
   203:	if_icmplt	317
   206:	aload	9
   208:	astore	10
   210:	aload	10
   212:	astore	11
   214:	aload_0
   215:	invokevirtual	#225; //Method exc:()Lscala/collection/immutable/List;
   218:	invokeinterface	#142,  1; //InterfaceMethod scala/collection/generic/LinearSequenceTemplate.length:()I
   223:	istore	12
   225:	aload_0
   226:	aload_1
   227:	iconst_1
   228:	invokevirtual	#203; //Method getIterator:(Lscala/collection/Sequence;Z)Lscala/collection/Iterator;
   231:	astore	13
   233:	aload	13
   235:	invokeinterface	#51,  1; //InterfaceMethod scala/collection/Iterator.hasNext:()Z
   240:	ifeq	295
   243:	aload	13
   245:	invokeinterface	#55,  1; //InterfaceMethod scala/collection/Iterator.next:()Ljava/lang/Object;
   250:	checkcast	#65; //class scala/xml/dtd/ContentModel$ElemName
   253:	invokevirtual	#69; //Method scala/xml/dtd/ContentModel$ElemName.name:()Ljava/lang/String;
   256:	astore	14
   258:	aload_0
   259:	aload	14
   261:	aload	11
   263:	invokespecial	#227; //Method find$2:(Ljava/lang/String;Lscala/collection/Sequence;)Z
   266:	ifne	233
   269:	aload_0
   270:	getstatic	#232; //Field scala/xml/dtd/MakeValidationException$.MODULE$:Lscala/xml/dtd/MakeValidationException$;
   273:	aload	14
   275:	invokevirtual	#236; //Method scala/xml/dtd/MakeValidationException$.fromUndefinedElement:(Ljava/lang/String;)Lscala/xml/dtd/ValidationException;
   278:	astore	15
   280:	aload_0
   281:	invokevirtual	#225; //Method exc:()Lscala/collection/immutable/List;
   284:	aload	15
   286:	invokevirtual	#242; //Method scala/collection/immutable/List.$colon$colon:(Ljava/lang/Object;)Lscala/collection/immutable/List;
   289:	invokevirtual	#246; //Method exc_$eq:(Lscala/collection/immutable/List;)V
   292:	goto	233
   295:	aload_0
   296:	invokevirtual	#225; //Method exc:()Lscala/collection/immutable/List;
   299:	invokeinterface	#142,  1; //InterfaceMethod scala/collection/generic/LinearSequenceTemplate.length:()I
   304:	iload	12
   306:	if_icmpne	313
   309:	iconst_1
   310:	goto	476
   313:	iconst_0
   314:	goto	476
   317:	new	#151; //class scala/MatchError
   320:	dup
   321:	aload_2
   322:	invokevirtual	#249; //Method scala/xml/dtd/ContentModel.toString:()Ljava/lang/String;
   325:	invokespecial	#155; //Method scala/MatchError."<init>":(Ljava/lang/String;)V
   328:	athrow
   329:	new	#151; //class scala/MatchError
   332:	dup
   333:	aload_2
   334:	invokevirtual	#249; //Method scala/xml/dtd/ContentModel.toString:()Ljava/lang/String;
   337:	invokespecial	#155; //Method scala/MatchError."<init>":(Ljava/lang/String;)V
   340:	athrow
   341:	aload_2
   342:	instanceof	#251; //class scala/xml/dtd/ELEMENTS
   345:	ifeq	477
   348:	iconst_0
   349:	istore	16
   351:	aload_0
   352:	aload_1
   353:	iconst_0
   354:	invokevirtual	#203; //Method getIterator:(Lscala/collection/Sequence;Z)Lscala/collection/Iterator;
   357:	astore	17
   359:	aload	17
   361:	invokeinterface	#51,  1; //InterfaceMethod scala/collection/Iterator.hasNext:()Z
   366:	ifeq	467
   369:	aload	17
   371:	invokeinterface	#55,  1; //InterfaceMethod scala/collection/Iterator.next:()Ljava/lang/Object;
   376:	checkcast	#65; //class scala/xml/dtd/ContentModel$ElemName
   379:	astore	18
   381:	aload_0
   382:	invokevirtual	#254; //Method dfa:()Lscala/util/automata/DetWordAutom;
   385:	invokevirtual	#260; //Method scala/util/automata/DetWordAutom.delta:()[Lscala/collection/Map;
   388:	iload	16
   390:	aaload
   391:	aload	18
   393:	invokeinterface	#266,  2; //InterfaceMethod scala/collection/generic/MapTemplate.get:(Ljava/lang/Object;)Lscala/Option;
   398:	astore	19
   400:	aload	19
   402:	instanceof	#268; //class scala/Some
   405:	ifeq	432
   408:	aload	19
   410:	checkcast	#268; //class scala/Some
   413:	astore	20
   415:	aload	20
   417:	invokevirtual	#271; //Method scala/Some.x:()Ljava/lang/Object;
   420:	invokestatic	#275; //Method scala/runtime/BoxesRunTime.unboxToInt:(Ljava/lang/Object;)I
   423:	istore	21
   425:	iload	21
   427:	istore	16
   429:	goto	359
   432:	new	#277; //class scala/xml/dtd/ValidationException
   435:	dup
   436:	new	#279; //class scala/collection/mutable/StringBuilder
   439:	dup
   440:	invokespecial	#280; //Method scala/collection/mutable/StringBuilder."<init>":()V
   443:	ldc_w	#282; //String element 
   446:	invokevirtual	#286; //Method scala/collection/mutable/StringBuilder.append:(Ljava/lang/Object;)Lscala/collection/mutable/StringBuilder;
   449:	aload	18
   451:	invokevirtual	#286; //Method scala/collection/mutable/StringBuilder.append:(Ljava/lang/Object;)Lscala/collection/mutable/StringBuilder;
   454:	ldc_w	#288; //String  not allowed here
   457:	invokevirtual	#286; //Method scala/collection/mutable/StringBuilder.append:(Ljava/lang/Object;)Lscala/collection/mutable/StringBuilder;
   460:	invokevirtual	#289; //Method scala/collection/mutable/StringBuilder.toString:()Ljava/lang/String;
   463:	invokespecial	#290; //Method scala/xml/dtd/ValidationException."<init>":(Ljava/lang/String;)V
   466:	athrow
   467:	aload_0
   468:	invokevirtual	#254; //Method dfa:()Lscala/util/automata/DetWordAutom;
   471:	iload	16
   473:	invokevirtual	#294; //Method scala/util/automata/DetWordAutom.isFinal:(I)Z
   476:	ireturn
   477:	new	#151; //class scala/MatchError
   480:	dup
   481:	aload_2
   482:	invokevirtual	#249; //Method scala/xml/dtd/ContentModel.toString:()Ljava/lang/String;
   485:	invokespecial	#155; //Method scala/MatchError."<init>":(Ljava/lang/String;)V
   488:	athrow
  LineNumberTable: 
   line 118: 0
   line 120: 36
   line 118: 40
   line 123: 74
   line 118: 96
   line 126: 130
   line 118: 152
   line 59: 202
   line 118: 206
   line 128: 210
   line 129: 214
   line 141: 225
   line 142: 243
   line 143: 258
   line 144: 269
   line 148: 295
   line 118: 317
   line 151: 348
   line 152: 351
   line 153: 359
   line 154: 369
   line 155: 381
   line 156: 425
   line 157: 432
   line 160: 467
   line 118: 476

  LocalVariableTable: 
   Start  Length  Slot  Name   Signature
   0      489      0    this       Lscala/xml/dtd/ElementValidator;
   0      489      1    nodes       Lscala/collection/Sequence;
   5      484      2    temp35       Lscala/xml/dtd/ContentModel;
   165      176      6    temp39       Lscala/xml/dtd/MIXED;
   172      169      7    temp40       Lscala/util/regexp/Base$RegExp;
   187      142      8    temp41       Lscala/util/regexp/Base$Alt;
   194      135      9    temp42       Lscala/collection/Sequence;
   210      107      10    temp43       Lscala/collection/Sequence;
   214      103      11    branches$1       Lscala/collection/Sequence;
   225      92      12    j       I
   233      84      13    it       Lscala/collection/Iterator;
   258      37      14    label       Ljava/lang/String;
   351      125      16    q       I
   359      117      17    it       Lscala/collection/Iterator;
   381      86      18    e       Lscala/xml/dtd/ContentModel$ElemName;
   400      67      19    temp32       Lscala/Option;
   415      14      20    temp33       Lscala/Some;
   425      4      21    temp34       I

  Signature: length = 0x2
   01 3C 

public boolean check(scala.xml.MetaData);
  Code:
   Stack=5, Locals=25, Args_size=2
   0:	aload_0
   1:	invokevirtual	#225; //Method exc:()Lscala/collection/immutable/List;
   4:	invokeinterface	#142,  1; //InterfaceMethod scala/collection/generic/LinearSequenceTemplate.length:()I
   9:	istore_2
   10:	new	#103; //class scala/runtime/IntRef
   13:	dup
   14:	iconst_0
   15:	invokespecial	#319; //Method scala/runtime/IntRef."<init>":(I)V
   18:	astore_3
   19:	new	#95; //class scala/runtime/ObjectRef
   22:	dup
   23:	new	#101; //class scala/collection/mutable/BitSet
   26:	dup
   27:	aload_0
   28:	invokevirtual	#135; //Method adecls:()Lscala/collection/immutable/List;
   31:	invokeinterface	#142,  1; //InterfaceMethod scala/collection/generic/LinearSequenceTemplate.length:()I
   36:	invokespecial	#320; //Method scala/collection/mutable/BitSet."<init>":(I)V
   39:	invokespecial	#323; //Method scala/runtime/ObjectRef."<init>":(Ljava/lang/Object;)V
   42:	astore	4
   44:	aload_1
   45:	invokevirtual	#324; //Method scala/xml/MetaData.iterator:()Lscala/collection/Iterator;
   48:	astore	5
   50:	aload	5
   52:	invokeinterface	#51,  1; //InterfaceMethod scala/collection/Iterator.hasNext:()Z
   57:	ifeq	263
   60:	aload	5
   62:	invokeinterface	#55,  1; //InterfaceMethod scala/collection/Iterator.next:()Ljava/lang/Object;
   67:	checkcast	#121; //class scala/xml/MetaData
   70:	astore	6
   72:	aload_3
   73:	iconst_0
   74:	putfield	#106; //Field scala/runtime/IntRef.elem:I
   77:	aload_0
   78:	aload	6
   80:	invokevirtual	#327; //Method scala/xml/MetaData.key:()Ljava/lang/String;
   83:	aload_3
   84:	aload	4
   86:	invokespecial	#329; //Method find$1:(Ljava/lang/String;Lscala/runtime/IntRef;Lscala/runtime/ObjectRef;)Lscala/xml/dtd/AttrDecl;
   89:	astore	7
   91:	aload	7
   93:	ifnonnull	125
   96:	aload_0
   97:	getstatic	#232; //Field scala/xml/dtd/MakeValidationException$.MODULE$:Lscala/xml/dtd/MakeValidationException$;
   100:	aload	6
   102:	invokevirtual	#327; //Method scala/xml/MetaData.key:()Ljava/lang/String;
   105:	invokevirtual	#332; //Method scala/xml/dtd/MakeValidationException$.fromUndefinedAttribute:(Ljava/lang/String;)Lscala/xml/dtd/ValidationException;
   108:	astore	8
   110:	aload_0
   111:	invokevirtual	#225; //Method exc:()Lscala/collection/immutable/List;
   114:	aload	8
   116:	invokevirtual	#242; //Method scala/collection/immutable/List.$colon$colon:(Ljava/lang/Object;)Lscala/collection/immutable/List;
   119:	invokevirtual	#246; //Method exc_$eq:(Lscala/collection/immutable/List;)V
   122:	goto	50
   125:	aload	7
   127:	ifnull	250
   130:	aload	7
   132:	invokevirtual	#335; //Method scala/xml/dtd/AttrDecl.tpe:()Ljava/lang/String;
   135:	astore	9
   137:	aload	7
   139:	invokevirtual	#339; //Method scala/xml/dtd/AttrDecl.default:()Lscala/xml/dtd/DefaultDecl;
   142:	astore	10
   144:	aload	10
   146:	instanceof	#341; //class scala/xml/dtd/DEFAULT
   149:	ifeq	50
   152:	aload	10
   154:	checkcast	#341; //class scala/xml/dtd/DEFAULT
   157:	astore	11
   159:	aload	11
   161:	invokevirtual	#344; //Method scala/xml/dtd/DEFAULT.attValue:()Ljava/lang/String;
   164:	astore	12
   166:	aload	11
   168:	invokevirtual	#347; //Method scala/xml/dtd/DEFAULT.fixed:()Z
   171:	invokestatic	#169; //Method scala/runtime/BoxesRunTime.boxToBoolean:(Z)Ljava/lang/Boolean;
   174:	iconst_1
   175:	invokestatic	#169; //Method scala/runtime/BoxesRunTime.boxToBoolean:(Z)Ljava/lang/Boolean;
   178:	invokestatic	#350; //Method scala/runtime/BoxesRunTime.equals:(Ljava/lang/Object;Ljava/lang/Object;)Z
   181:	ifeq	50
   184:	aload	9
   186:	astore	13
   188:	aload	12
   190:	astore	14
   192:	aload_0
   193:	aload	14
   195:	aload	13
   197:	aload	6
   199:	invokespecial	#352; //Method gd2$1:(Ljava/lang/String;Ljava/lang/String;Lscala/xml/MetaData;)Z
   202:	ifeq	50
   205:	aload	12
   207:	astore	14
   209:	aload_0
   210:	getstatic	#232; //Field scala/xml/dtd/MakeValidationException$.MODULE$:Lscala/xml/dtd/MakeValidationException$;
   213:	aload	6
   215:	invokevirtual	#327; //Method scala/xml/MetaData.key:()Ljava/lang/String;
   218:	aload	14
   220:	aload	6
   222:	invokevirtual	#125; //Method scala/xml/MetaData.value:()Lscala/collection/Sequence;
   225:	invokeinterface	#130,  1; //InterfaceMethod scala/collection/generic/SequenceTemplate.toString:()Ljava/lang/String;
   230:	invokevirtual	#356; //Method scala/xml/dtd/MakeValidationException$.fromFixedAttribute:(Ljava/lang/String;Ljava/lang/String;Ljava/lang/String;)Lscala/xml/dtd/ValidationException;
   233:	astore	15
   235:	aload_0
   236:	invokevirtual	#225; //Method exc:()Lscala/collection/immutable/List;
   239:	aload	15
   241:	invokevirtual	#242; //Method scala/collection/immutable/List.$colon$colon:(Ljava/lang/Object;)Lscala/collection/immutable/List;
   244:	invokevirtual	#246; //Method exc_$eq:(Lscala/collection/immutable/List;)V
   247:	goto	50
   250:	new	#151; //class scala/MatchError
   253:	dup
   254:	aload	7
   256:	invokevirtual	#152; //Method scala/xml/dtd/AttrDecl.toString:()Ljava/lang/String;
   259:	invokespecial	#155; //Method scala/MatchError."<init>":(Ljava/lang/String;)V
   262:	athrow
   263:	aload_3
   264:	iconst_0
   265:	putfield	#106; //Field scala/runtime/IntRef.elem:I
   268:	aload_0
   269:	invokevirtual	#135; //Method adecls:()Lscala/collection/immutable/List;
   272:	invokeinterface	#138,  1; //InterfaceMethod scala/collection/generic/LinearSequenceTemplate.iterator:()Lscala/collection/Iterator;
   277:	astore	16
   279:	aload	16
   281:	invokeinterface	#51,  1; //InterfaceMethod scala/collection/Iterator.hasNext:()Z
   286:	ifeq	457
   289:	aload	16
   291:	invokeinterface	#55,  1; //InterfaceMethod scala/collection/Iterator.next:()Ljava/lang/Object;
   296:	checkcast	#144; //class scala/xml/dtd/AttrDecl
   299:	astore	17
   301:	aload	17
   303:	ifnull	444
   306:	aload	17
   308:	invokevirtual	#145; //Method scala/xml/dtd/AttrDecl.name:()Ljava/lang/String;
   311:	astore	18
   313:	aload	17
   315:	invokevirtual	#335; //Method scala/xml/dtd/AttrDecl.tpe:()Ljava/lang/String;
   318:	astore	19
   320:	aload	17
   322:	invokevirtual	#339; //Method scala/xml/dtd/AttrDecl.default:()Lscala/xml/dtd/DefaultDecl;
   325:	astore	20
   327:	getstatic	#361; //Field scala/xml/dtd/REQUIRED$.MODULE$:Lscala/xml/dtd/REQUIRED$;
   330:	aload	20
   332:	astore	21
   334:	dup
   335:	ifnonnull	347
   338:	pop
   339:	aload	21
   341:	ifnull	355
   344:	goto	431
   347:	aload	21
   349:	invokevirtual	#73; //Method java/lang/Object.equals:(Ljava/lang/Object;)Z
   352:	ifeq	431
   355:	aload	20
   357:	instanceof	#358; //class scala/xml/dtd/REQUIRED$
   360:	ifeq	431
   363:	aload	19
   365:	astore	22
   367:	aload	18
   369:	astore	23
   371:	aload_0
   372:	aload	22
   374:	aload	23
   376:	aload_3
   377:	aload	4
   379:	invokespecial	#363; //Method gd3$1:(Ljava/lang/String;Ljava/lang/String;Lscala/runtime/IntRef;Lscala/runtime/ObjectRef;)Z
   382:	ifeq	431
   385:	aload	19
   387:	astore	22
   389:	aload	18
   391:	astore	23
   393:	aload_0
   394:	getstatic	#232; //Field scala/xml/dtd/MakeValidationException$.MODULE$:Lscala/xml/dtd/MakeValidationException$;
   397:	aload	23
   399:	aload	22
   401:	invokevirtual	#367; //Method scala/xml/dtd/MakeValidationException$.fromMissingAttribute:(Ljava/lang/String;Ljava/lang/String;)Lscala/xml/dtd/ValidationException;
   404:	astore	24
   406:	aload_0
   407:	invokevirtual	#225; //Method exc:()Lscala/collection/immutable/List;
   410:	aload	24
   412:	invokevirtual	#242; //Method scala/collection/immutable/List.$colon$colon:(Ljava/lang/Object;)Lscala/collection/immutable/List;
   415:	invokevirtual	#246; //Method exc_$eq:(Lscala/collection/immutable/List;)V
   418:	aload_3
   419:	aload_3
   420:	getfield	#106; //Field scala/runtime/IntRef.elem:I
   423:	iconst_1
   424:	iadd
   425:	putfield	#106; //Field scala/runtime/IntRef.elem:I
   428:	goto	279
   431:	aload_3
   432:	aload_3
   433:	getfield	#106; //Field scala/runtime/IntRef.elem:I
   436:	iconst_1
   437:	iadd
   438:	putfield	#106; //Field scala/runtime/IntRef.elem:I
   441:	goto	279
   444:	new	#151; //class scala/MatchError
   447:	dup
   448:	aload	17
   450:	invokevirtual	#152; //Method scala/xml/dtd/AttrDecl.toString:()Ljava/lang/String;
   453:	invokespecial	#155; //Method scala/MatchError."<init>":(Ljava/lang/String;)V
   456:	athrow
   457:	aload_0
   458:	invokevirtual	#225; //Method exc:()Lscala/collection/immutable/List;
   461:	invokeinterface	#142,  1; //InterfaceMethod scala/collection/generic/LinearSequenceTemplate.length:()I
   466:	iload_2
   467:	if_icmpne	474
   470:	iconst_1
   471:	goto	475
   474:	iconst_0
   475:	ireturn
  LineNumberTable: 
   line 69: 0
   line 70: 10
   line 71: 19
   line 82: 44
   line 83: 60
   line 84: 72
   line 85: 77
   line 89: 96
   line 85: 125
   line 91: 184
   line 85: 192
   line 91: 205
   line 92: 209
   line 85: 250
   line 101: 263
   line 102: 268
   line 103: 279
   line 104: 289
   line 105: 363
   line 104: 371
   line 105: 385
   line 106: 393
   line 107: 418
   line 109: 431
   line 104: 444
   line 112: 457
   line 66: 475

  LocalVariableTable: 
   Start  Length  Slot  Name   Signature
   0      476      0    this       Lscala/xml/dtd/ElementValidator;
   0      476      1    md       Lscala/xml/MetaData;
   10      466      2    len       I
   19      457      3    j$1       Lscala/runtime/IntRef;
   44      432      4    ok$1       Lscala/runtime/ObjectRef;
   50      426      5    it       Lscala/collection/Iterator;
   72      191      6    attr$1       Lscala/xml/MetaData;
   91      172      7    temp13       Lscala/xml/dtd/AttrDecl;
   137      113      9    temp16       Ljava/lang/String;
   144      106      10    temp17       Lscala/xml/dtd/DefaultDecl;
   159      91      11    temp18       Lscala/xml/dtd/DEFAULT;
   166      84      12    temp20       Ljava/lang/String;
   188      62      13    tpe       Ljava/lang/String;
   192      13      14    fixedValue       Ljava/lang/String;
   209      38      14    fixedValue       Ljava/lang/String;
   205      45      14    fixedValue       Ljava/lang/String;
   279      197      16    kt       Lscala/collection/Iterator;
   301      156      17    temp22       Lscala/xml/dtd/AttrDecl;
   313      131      18    temp23       Ljava/lang/String;
   320      124      19    temp24       Ljava/lang/String;
   327      117      20    temp25       Lscala/xml/dtd/DefaultDecl;
   367      18      22    tpe       Ljava/lang/String;
   389      39      22    tpe       Ljava/lang/String;
   385      59      22    tpe       Ljava/lang/String;
   371      14      23    key       Ljava/lang/String;
   393      35      23    key       Ljava/lang/String;
   385      59      23    key       Ljava/lang/String;


public scala.collection.Iterator getIterator(scala.collection.Sequence, boolean);
  Code:
   Stack=5, Locals=3, Args_size=3
   0:	aload_1
   1:	invokeinterface	#393,  1; //InterfaceMethod scala/collection/generic/TraversableTemplate.toList:()Lscala/collection/immutable/List;
   6:	new	#395; //class scala/xml/dtd/ElementValidator$$anonfun$getIterator$1
   9:	dup
   10:	aload_0
   11:	iload_2
   12:	invokespecial	#398; //Method scala/xml/dtd/ElementValidator$$anonfun$getIterator$1."<init>":(Lscala/xml/dtd/ElementValidator;Z)V
   15:	invokeinterface	#402,  2; //InterfaceMethod scala/collection/generic/TraversableTemplate.filter:(Lscala/Function1;)Lscala/collection/generic/TraversableTemplate;
   20:	new	#404; //class scala/xml/dtd/ElementValidator$$anonfun$getIterator$2
   23:	dup
   24:	aload_0
   25:	invokespecial	#407; //Method scala/xml/dtd/ElementValidator$$anonfun$getIterator$2."<init>":(Lscala/xml/dtd/ElementValidator;)V
   28:	getstatic	#412; //Field scala/collection/immutable/List$.MODULE$:Lscala/collection/immutable/List$;
   31:	invokevirtual	#416; //Method scala/collection/immutable/List$.builderFactory:()Lscala/collection/generic/BuilderFactory;
   34:	invokeinterface	#420,  3; //InterfaceMethod scala/collection/generic/TraversableTemplate.map:(Lscala/Function1;Lscala/collection/generic/BuilderFactory;)Ljava/lang/Object;
   39:	checkcast	#137; //class scala/collection/generic/LinearSequenceTemplate
   42:	invokeinterface	#138,  1; //InterfaceMethod scala/collection/generic/LinearSequenceTemplate.iterator:()Lscala/collection/Iterator;
   47:	areturn
  LineNumberTable: 
   line 46: 0
   line 47: 6
   line 61: 20
   line 62: 42

  LocalVariableTable: 
   Start  Length  Slot  Name   Signature
   0      48      0    this       Lscala/xml/dtd/ElementValidator;
   0      48      1    nodes       Lscala/collection/Sequence;
   0      48      2    skipPCDATA$1       Z

  Signature: length = 0x2
   01 FFFFFFA6 

public void setMetaData(scala.collection.immutable.List);
  Code:
   Stack=2, Locals=2, Args_size=2
   0:	aload_0
   1:	aload_1
   2:	invokevirtual	#426; //Method adecls_$eq:(Lscala/collection/immutable/List;)V
   5:	return
  LineNumberTable: 
   line 43: 0

  LocalVariableTable: 
   Start  Length  Slot  Name   Signature
   0      6      0    this       Lscala/xml/dtd/ElementValidator;
   0      6      1    adecls       Lscala/collection/immutable/List;

  Signature: length = 0x2
   01 FFFFFFAB 

public scala.xml.dtd.ContentModel getContentModel();
  Code:
   Stack=1, Locals=1, Args_size=1
   0:	aload_0
   1:	invokevirtual	#173; //Method contentModel:()Lscala/xml/dtd/ContentModel;
   4:	areturn
  LineNumberTable: 
   line 40: 0


public void setContentModel(scala.xml.dtd.ContentModel);
  Code:
   Stack=4, Locals=7, Args_size=2
   0:	aload_0
   1:	aload_1
   2:	invokevirtual	#433; //Method contentModel_$eq:(Lscala/xml/dtd/ContentModel;)V
   5:	aload_1
   6:	astore_2
   7:	aload_2
   8:	instanceof	#251; //class scala/xml/dtd/ELEMENTS
   11:	ifeq	59
   14:	aload_2
   15:	checkcast	#251; //class scala/xml/dtd/ELEMENTS
   18:	astore_3
   19:	aload_3
   20:	invokevirtual	#434; //Method scala/xml/dtd/ELEMENTS.r:()Lscala/util/regexp/Base$RegExp;
   23:	astore	4
   25:	aload	4
   27:	astore	5
   29:	getstatic	#439; //Field scala/xml/dtd/ContentModel$Translator$.MODULE$:Lscala/xml/dtd/ContentModel$Translator$;
   32:	aload	5
   34:	iconst_1
   35:	invokevirtual	#443; //Method scala/xml/dtd/ContentModel$Translator$.automatonFrom:(Lscala/util/regexp/Base$RegExp;I)Lscala/util/automata/NondetWordAutom;
   38:	astore	6
   40:	aload_0
   41:	new	#445; //class scala/util/automata/SubsetConstruction
   44:	dup
   45:	aload	6
   47:	invokespecial	#448; //Method scala/util/automata/SubsetConstruction."<init>":(Lscala/util/automata/NondetWordAutom;)V
   50:	invokevirtual	#451; //Method scala/util/automata/SubsetConstruction.determinize:()Lscala/util/automata/DetWordAutom;
   53:	invokevirtual	#455; //Method dfa_$eq:(Lscala/util/automata/DetWordAutom;)V
   56:	goto	66
   59:	aload_0
   60:	aconst_null
   61:	pop
   62:	aconst_null
   63:	invokevirtual	#455; //Method dfa_$eq:(Lscala/util/automata/DetWordAutom;)V
   66:	return
  LineNumberTable: 
   line 31: 0
   line 32: 25
   line 33: 29
   line 34: 40
   line 36: 59
   line 30: 66

  LocalVariableTable: 
   Start  Length  Slot  Name   Signature
   0      67      0    this       Lscala/xml/dtd/ElementValidator;
   0      67      1    cm       Lscala/xml/dtd/ContentModel;
   7      60      2    temp1       Lscala/xml/dtd/ContentModel;
   19      37      3    temp2       Lscala/xml/dtd/ELEMENTS;
   25      31      4    temp3       Lscala/util/regexp/Base$RegExp;
   29      27      5    r       Lscala/util/regexp/Base$RegExp;
   40      16      6    nfa       Lscala/util/automata/NondetWordAutom;


public void adecls_$eq(scala.collection.immutable.List);
  Code:
   Stack=2, Locals=2, Args_size=2
   0:	aload_0
   1:	aload_1
   2:	putfield	#464; //Field adecls:Lscala/collection/immutable/List;
   5:	return
  LineNumberTable: 
   line 27: 0

  Signature: length = 0x2
   01 FFFFFFAB 

public scala.collection.immutable.List adecls();
  Code:
   Stack=1, Locals=1, Args_size=1
   0:	aload_0
   1:	getfield	#464; //Field adecls:Lscala/collection/immutable/List;
   4:	areturn
  LineNumberTable: 
   line 27: 0

  Signature: length = 0x2
   01 FFFFFFD1 

public void dfa_$eq(scala.util.automata.DetWordAutom);
  Code:
   Stack=2, Locals=2, Args_size=2
   0:	aload_0
   1:	aload_1
   2:	putfield	#467; //Field dfa:Lscala/util/automata/DetWordAutom;
   5:	return
  LineNumberTable: 
   line 26: 0

  Signature: length = 0x2
   01 FFFFFFD4 

public scala.util.automata.DetWordAutom dfa();
  Code:
   Stack=1, Locals=1, Args_size=1
   0:	aload_0
   1:	getfield	#467; //Field dfa:Lscala/util/automata/DetWordAutom;
   4:	areturn
  LineNumberTable: 
   line 26: 0

  Signature: length = 0x2
   01 FFFFFFD5 

public void contentModel_$eq(scala.xml.dtd.ContentModel);
  Code:
   Stack=2, Locals=2, Args_size=2
   0:	aload_0
   1:	aload_1
   2:	putfield	#471; //Field contentModel:Lscala/xml/dtd/ContentModel;
   5:	return
  LineNumberTable: 
   line 25: 0


public scala.xml.dtd.ContentModel contentModel();
  Code:
   Stack=1, Locals=1, Args_size=1
   0:	aload_0
   1:	getfield	#471; //Field contentModel:Lscala/xml/dtd/ContentModel;
   4:	areturn
  LineNumberTable: 
   line 25: 0


public void exc_$eq(scala.collection.immutable.List);
  Code:
   Stack=2, Locals=2, Args_size=2
   0:	aload_0
   1:	aload_1
   2:	putfield	#37; //Field exc:Lscala/collection/immutable/List;
   5:	return
  LineNumberTable: 
   line 23: 0

  Signature: length = 0x2
   01 FFFFFFD8 

public scala.collection.immutable.List exc();
  Code:
   Stack=1, Locals=1, Args_size=1
   0:	aload_0
   1:	getfield	#37; //Field exc:Lscala/collection/immutable/List;
   4:	areturn
  LineNumberTable: 
   line 23: 0

  Signature: length = 0x2
   01 FFFFFFD9 

public scala.Function1 andThen(scala.Function1);
  Code:
   Stack=2, Locals=2, Args_size=2
   0:	aload_0
   1:	aload_1
   2:	invokestatic	#478; //Method scala/Function1$class.andThen:(Lscala/Function1;Lscala/Function1;)Lscala/Function1;
   5:	areturn
  LineNumberTable: 
   line 21: 0

  LocalVariableTable: 
   Start  Length  Slot  Name   Signature
   0      6      0    this       Lscala/xml/dtd/ElementValidator;
   0      6      1    g       Lscala/Function1;


public scala.Function1 compose(scala.Function1);
  Code:
   Stack=2, Locals=2, Args_size=2
   0:	aload_0
   1:	aload_1
   2:	invokestatic	#483; //Method scala/Function1$class.compose:(Lscala/Function1;Lscala/Function1;)Lscala/Function1;
   5:	areturn
  LineNumberTable: 
   line 21: 0

  LocalVariableTable: 
   Start  Length  Slot  Name   Signature
   0      6      0    this       Lscala/xml/dtd/ElementValidator;
   0      6      1    g       Lscala/Function1;


public java.lang.String toString();
  Code:
   Stack=1, Locals=1, Args_size=1
   0:	aload_0
   1:	invokestatic	#486; //Method scala/Function1$class.toString:(Lscala/Function1;)Ljava/lang/String;
   4:	areturn
  LineNumberTable: 
   line 21: 0


}

