Compiled from "ElementValidator.scala"
public final class scala.xml.dtd.ElementValidator$$anonfun$check$1 extends java.lang.Object implements scala.Function1,scala.ScalaObject,java.io.Serializable
  SourceFile: "ElementValidator.scala"
  Scala: length = 0x
   
  InnerClass: 
   public final #229= #9 of #52; //$anonfun$check$1=class scala/xml/dtd/ElementValidator$$anonfun$check$1 of class scala/xml/dtd/ElementValidator
   public #232= #64 of #231; //GenericCanBuildFrom=class scala/collection/generic/TraversableFactory$GenericCanBuildFrom of class scala/collection/generic/TraversableFactory
   public final #233= #77 of #9; //$anonfun$find$1$1=class scala/xml/dtd/ElementValidator$$anonfun$check$1$$anonfun$find$1$1 of class scala/xml/dtd/ElementValidator$$anonfun$check$1
  minor version: 0
  major version: 49
  Constant pool:
const #1 = Asciz	SourceFile;
const #2 = Asciz	ElementValidator.scala;
const #3 = Asciz	<clinit>;
const #4 = Asciz	()V;
const #5 = Asciz	Code;
const #6 = Asciz	serialVersionUID;
const #7 = Asciz	J;
const #8 = Asciz	scala/xml/dtd/ElementValidator$$anonfun$check$1;
const #9 = class	#8;	//  scala/xml/dtd/ElementValidator$$anonfun$check$1
const #10 = NameAndType	#6:#7;//  serialVersionUID:J
const #11 = Field	#9.#10;	//  scala/xml/dtd/ElementValidator$$anonfun$check$1.serialVersionUID:J
const #12 = Asciz	ok$1;
const #13 = Asciz	Lscala/runtime/ObjectRef;;
const #14 = Asciz	$outer;
const #15 = Asciz	Lscala/xml/dtd/ElementValidator;;
const #16 = Asciz	<init>;
const #17 = Asciz	(Lscala/xml/dtd/ElementValidator;Lscala/runtime/ObjectRef;)V;
const #18 = Asciz	LineNumberTable;
const #19 = Asciz	java/lang/NullPointerException;
const #20 = class	#19;	//  java/lang/NullPointerException
const #21 = NameAndType	#16:#4;//  "<init>":()V
const #22 = Method	#20.#21;	//  java/lang/NullPointerException."<init>":()V
const #23 = NameAndType	#14:#15;//  $outer:Lscala/xml/dtd/ElementValidator;
const #24 = Field	#9.#23;	//  scala/xml/dtd/ElementValidator$$anonfun$check$1.$outer:Lscala/xml/dtd/ElementValidator;
const #25 = NameAndType	#12:#13;//  ok$1:Lscala/runtime/ObjectRef;
const #26 = Field	#9.#25;	//  scala/xml/dtd/ElementValidator$$anonfun$check$1.ok$1:Lscala/runtime/ObjectRef;
const #27 = Asciz	java/lang/Object;
const #28 = class	#27;	//  java/lang/Object
const #29 = Method	#28.#21;	//  java/lang/Object."<init>":()V
const #30 = Asciz	scala/Function1$class;
const #31 = class	#30;	//  scala/Function1$class
const #32 = Asciz	$init$;
const #33 = Asciz	(Lscala/Function1;)V;
const #34 = NameAndType	#32:#33;//  $init$:(Lscala/Function1;)V
const #35 = Method	#31.#34;	//  scala/Function1$class.$init$:(Lscala/Function1;)V
const #36 = Asciz	this;
const #37 = Asciz	Lscala/xml/dtd/ElementValidator$$anonfun$check$1;;
const #38 = Asciz	LocalVariableTable;
const #39 = Asciz	gd4$1;
const #40 = Asciz	(Ljava/lang/String;Ljava/lang/String;Lscala/xml/MetaData;)Z;
const #41 = Asciz	attrStr$1;
const #42 = Asciz	(Lscala/xml/MetaData;)Ljava/lang/String;;
const #43 = NameAndType	#41:#42;//  attrStr$1:(Lscala/xml/MetaData;)Ljava/lang/String;
const #44 = Method	#9.#43;	//  scala/xml/dtd/ElementValidator$$anonfun$check$1.attrStr$1:(Lscala/xml/MetaData;)Ljava/lang/String;
const #45 = Asciz	equals;
const #46 = Asciz	(Ljava/lang/Object;)Z;
const #47 = NameAndType	#45:#46;//  equals:(Ljava/lang/Object;)Z
const #48 = Method	#28.#47;	//  java/lang/Object.equals:(Ljava/lang/Object;)Z
const #49 = Asciz	find$1;
const #50 = Asciz	(Ljava/lang/String;)Lscala/Option;;
const #51 = Asciz	scala/xml/dtd/ElementValidator;
const #52 = class	#51;	//  scala/xml/dtd/ElementValidator
const #53 = Asciz	adecls;
const #54 = Asciz	()Lscala/collection/immutable/List;;
const #55 = NameAndType	#53:#54;//  adecls:()Lscala/collection/immutable/List;
const #56 = Method	#52.#55;	//  scala/xml/dtd/ElementValidator.adecls:()Lscala/collection/immutable/List;
const #57 = Asciz	scala/collection/immutable/List$;
const #58 = class	#57;	//  scala/collection/immutable/List$
const #59 = Asciz	MODULE$;
const #60 = Asciz	Lscala/collection/immutable/List$;;
const #61 = NameAndType	#59:#60;//  MODULE$:Lscala/collection/immutable/List$;
const #62 = Field	#58.#61;	//  scala/collection/immutable/List$.MODULE$:Lscala/collection/immutable/List$;
const #63 = Asciz	scala/collection/generic/TraversableFactory$GenericCanBuildFrom;
const #64 = class	#63;	//  scala/collection/generic/TraversableFactory$GenericCanBuildFrom
const #65 = Asciz	(Lscala/collection/generic/TraversableFactory;)V;
const #66 = NameAndType	#16:#65;//  "<init>":(Lscala/collection/generic/TraversableFactory;)V
const #67 = Method	#64.#66;	//  scala/collection/generic/TraversableFactory$GenericCanBuildFrom."<init>":(Lscala/collection/generic/TraversableFactory;)V
const #68 = Asciz	scala/collection/IterableLike;
const #69 = class	#68;	//  scala/collection/IterableLike
const #70 = Asciz	zipWithIndex;
const #71 = Asciz	(Lscala/collection/generic/CanBuildFrom;)Ljava/lang/Object;;
const #72 = NameAndType	#70:#71;//  zipWithIndex:(Lscala/collection/generic/CanBuildFrom;)Ljava/lang/Object;
const #73 = InterfaceMethod	#69.#72;	//  scala/collection/IterableLike.zipWithIndex:(Lscala/collection/generic/CanBuildFrom;)Ljava/lang/Object;
const #74 = Asciz	scala/collection/LinearSeqLike;
const #75 = class	#74;	//  scala/collection/LinearSeqLike
const #76 = Asciz	scala/xml/dtd/ElementValidator$$anonfun$check$1$$anonfun$find$1$1;
const #77 = class	#76;	//  scala/xml/dtd/ElementValidator$$anonfun$check$1$$anonfun$find$1$1
const #78 = Asciz	(Lscala/xml/dtd/ElementValidator$$anonfun$check$1;Ljava/lang/String;Ljava/lang/Object;)V;
const #79 = NameAndType	#16:#78;//  "<init>":(Lscala/xml/dtd/ElementValidator$$anonfun$check$1;Ljava/lang/String;Ljava/lang/Object;)V
const #80 = Method	#77.#79;	//  scala/xml/dtd/ElementValidator$$anonfun$check$1$$anonfun$find$1$1."<init>":(Lscala/xml/dtd/ElementValidator$$anonfun$check$1;Ljava/lang/String;Ljava/lang/Object;)V
const #81 = Asciz	find;
const #82 = Asciz	(Lscala/Function1;)Lscala/Option;;
const #83 = NameAndType	#81:#82;//  find:(Lscala/Function1;)Lscala/Option;
const #84 = InterfaceMethod	#75.#83;	//  scala/collection/LinearSeqLike.find:(Lscala/Function1;)Lscala/Option;
const #85 = Asciz	scala/None$;
const #86 = class	#85;	//  scala/None$
const #87 = Asciz	Lscala/None$;;
const #88 = NameAndType	#59:#87;//  MODULE$:Lscala/None$;
const #89 = Field	#86.#88;	//  scala/None$.MODULE$:Lscala/None$;
const #90 = Asciz	scala/runtime/NonLocalReturnException;
const #91 = class	#90;	//  scala/runtime/NonLocalReturnException
const #92 = Asciz	key;
const #93 = Asciz	()Ljava/lang/Object;;
const #94 = NameAndType	#92:#93;//  key:()Ljava/lang/Object;
const #95 = Method	#91.#94;	//  scala/runtime/NonLocalReturnException.key:()Ljava/lang/Object;
const #96 = Asciz	value;
const #97 = NameAndType	#96:#93;//  value:()Ljava/lang/Object;
const #98 = Method	#91.#97;	//  scala/runtime/NonLocalReturnException.value:()Ljava/lang/Object;
const #99 = Asciz	scala/Option;
const #100 = class	#99;	//  scala/Option
const #101 = Asciz	Key$1;
const #102 = Asciz	Ljava/lang/String;;
const #103 = Asciz	$inlThis0;
const #104 = Asciz	Ljava/lang/Object;;
const #105 = Asciz	exceptionResult1;
const #106 = Asciz	Lscala/Option;;
const #107 = Asciz	scala/xml/MetaData;
const #108 = class	#107;	//  scala/xml/MetaData
const #109 = Asciz	()Lscala/collection/Seq;;
const #110 = NameAndType	#96:#109;//  value:()Lscala/collection/Seq;
const #111 = Method	#108.#110;	//  scala/xml/MetaData.value:()Lscala/collection/Seq;
const #112 = Asciz	scala/collection/SeqLike;
const #113 = class	#112;	//  scala/collection/SeqLike
const #114 = Asciz	toString;
const #115 = Asciz	()Ljava/lang/String;;
const #116 = NameAndType	#114:#115;//  toString:()Ljava/lang/String;
const #117 = InterfaceMethod	#113.#116;	//  scala/collection/SeqLike.toString:()Ljava/lang/String;
const #118 = Asciz	apply;
const #119 = Asciz	(Ljava/lang/Object;)Ljava/lang/Object;;
const #120 = Asciz	(Lscala/xml/MetaData;)V;
const #121 = NameAndType	#118:#120;//  apply:(Lscala/xml/MetaData;)V
const #122 = Method	#9.#121;	//  scala/xml/dtd/ElementValidator$$anonfun$check$1.apply:(Lscala/xml/MetaData;)V
const #123 = Asciz	scala/runtime/BoxedUnit;
const #124 = class	#123;	//  scala/runtime/BoxedUnit
const #125 = Asciz	UNIT;
const #126 = Asciz	Lscala/runtime/BoxedUnit;;
const #127 = NameAndType	#125:#126;//  UNIT:Lscala/runtime/BoxedUnit;
const #128 = Field	#124.#127;	//  scala/runtime/BoxedUnit.UNIT:Lscala/runtime/BoxedUnit;
const #129 = Asciz	v1;
const #130 = NameAndType	#92:#115;//  key:()Ljava/lang/String;
const #131 = Method	#108.#130;	//  scala/xml/MetaData.key:()Ljava/lang/String;
const #132 = NameAndType	#49:#50;//  find$1:(Ljava/lang/String;)Lscala/Option;
const #133 = Method	#9.#132;	//  scala/xml/dtd/ElementValidator$$anonfun$check$1.find$1:(Ljava/lang/String;)Lscala/Option;
const #134 = Asciz	scala$xml$dtd$ElementValidator$$exc;
const #135 = NameAndType	#134:#54;//  scala$xml$dtd$ElementValidator$$exc:()Lscala/collection/immutable/List;
const #136 = Method	#52.#135;	//  scala/xml/dtd/ElementValidator.scala$xml$dtd$ElementValidator$$exc:()Lscala/collection/immutable/List;
const #137 = Asciz	scala/xml/dtd/ValidationException;
const #138 = class	#137;	//  scala/xml/dtd/ValidationException
const #139 = Asciz	scala/collection/mutable/StringBuilder;
const #140 = class	#139;	//  scala/collection/mutable/StringBuilder
const #141 = Method	#140.#21;	//  scala/collection/mutable/StringBuilder."<init>":()V
const #142 = Asciz	attribute ;
const #143 = String	#142;	//  attribute 
const #144 = Asciz	append;
const #145 = Asciz	(Ljava/lang/Object;)Lscala/collection/mutable/StringBuilder;;
const #146 = NameAndType	#144:#145;//  append:(Ljava/lang/Object;)Lscala/collection/mutable/StringBuilder;
const #147 = Method	#140.#146;	//  scala/collection/mutable/StringBuilder.append:(Ljava/lang/Object;)Lscala/collection/mutable/StringBuilder;
const #148 = Asciz	 not allowed here;
const #149 = String	#148;	//   not allowed here
const #150 = Method	#140.#116;	//  scala/collection/mutable/StringBuilder.toString:()Ljava/lang/String;
const #151 = Asciz	(Ljava/lang/String;)V;
const #152 = NameAndType	#16:#151;//  "<init>":(Ljava/lang/String;)V
const #153 = Method	#138.#152;	//  scala/xml/dtd/ValidationException."<init>":(Ljava/lang/String;)V
const #154 = Asciz	scala/collection/immutable/List;
const #155 = class	#154;	//  scala/collection/immutable/List
const #156 = Asciz	$colon$colon;
const #157 = Asciz	(Ljava/lang/Object;)Lscala/collection/immutable/List;;
const #158 = NameAndType	#156:#157;//  $colon$colon:(Ljava/lang/Object;)Lscala/collection/immutable/List;
const #159 = Method	#155.#158;	//  scala/collection/immutable/List.$colon$colon:(Ljava/lang/Object;)Lscala/collection/immutable/List;
const #160 = Asciz	scala$xml$dtd$ElementValidator$$exc_$eq;
const #161 = Asciz	(Lscala/collection/immutable/List;)V;
const #162 = NameAndType	#160:#161;//  scala$xml$dtd$ElementValidator$$exc_$eq:(Lscala/collection/immutable/List;)V
const #163 = Method	#52.#162;	//  scala/xml/dtd/ElementValidator.scala$xml$dtd$ElementValidator$$exc_$eq:(Lscala/collection/immutable/List;)V
const #164 = Asciz	scala/MatchError;
const #165 = class	#164;	//  scala/MatchError
const #166 = Method	#100.#116;	//  scala/Option.toString:()Ljava/lang/String;
const #167 = Method	#165.#152;	//  scala/MatchError."<init>":(Ljava/lang/String;)V
const #168 = Asciz	scala/Some;
const #169 = class	#168;	//  scala/Some
const #170 = Asciz	x;
const #171 = NameAndType	#170:#104;//  x:Ljava/lang/Object;
const #172 = Field	#169.#171;	//  scala/Some.x:Ljava/lang/Object;
const #173 = Asciz	scala/xml/dtd/AttrDecl;
const #174 = class	#173;	//  scala/xml/dtd/AttrDecl
const #175 = Asciz	tpe;
const #176 = NameAndType	#175:#115;//  tpe:()Ljava/lang/String;
const #177 = Method	#174.#176;	//  scala/xml/dtd/AttrDecl.tpe:()Ljava/lang/String;
const #178 = Asciz	default;
const #179 = Asciz	()Lscala/xml/dtd/DefaultDecl;;
const #180 = NameAndType	#178:#179;//  default:()Lscala/xml/dtd/DefaultDecl;
const #181 = Method	#174.#180;	//  scala/xml/dtd/AttrDecl.default:()Lscala/xml/dtd/DefaultDecl;
const #182 = Asciz	scala/xml/dtd/DEFAULT;
const #183 = class	#182;	//  scala/xml/dtd/DEFAULT
const #184 = Asciz	attValue;
const #185 = NameAndType	#184:#115;//  attValue:()Ljava/lang/String;
const #186 = Method	#183.#185;	//  scala/xml/dtd/DEFAULT.attValue:()Ljava/lang/String;
const #187 = Asciz	fixed;
const #188 = Asciz	()Z;
const #189 = NameAndType	#187:#188;//  fixed:()Z
const #190 = Method	#183.#189;	//  scala/xml/dtd/DEFAULT.fixed:()Z
const #191 = NameAndType	#39:#40;//  gd4$1:(Ljava/lang/String;Ljava/lang/String;Lscala/xml/MetaData;)Z
const #192 = Method	#9.#191;	//  scala/xml/dtd/ElementValidator$$anonfun$check$1.gd4$1:(Ljava/lang/String;Ljava/lang/String;Lscala/xml/MetaData;)Z
const #193 = Asciz	value of attribute ;
const #194 = String	#193;	//  value of attribute 
const #195 = Asciz	 FIXED to \";
const #196 = String	#195;	//   FIXED to \"
const #197 = Asciz	\", but document tries \";
const #198 = String	#197;	//  \", but document tries \"
const #199 = Asciz	\";
const #200 = String	#199;	//  \"
const #201 = Asciz	attr$1;
const #202 = Asciz	Lscala/xml/MetaData;;
const #203 = Asciz	temp21;
const #204 = Asciz	Lscala/Some;;
const #205 = Asciz	temp22;
const #206 = Asciz	Lscala/xml/dtd/AttrDecl;;
const #207 = Asciz	temp25;
const #208 = Asciz	Lscala/xml/dtd/DefaultDecl;;
const #209 = Asciz	temp26;
const #210 = Asciz	Lscala/xml/dtd/DEFAULT;;
const #211 = Asciz	temp24;
const #212 = Asciz	temp28;
const #213 = Asciz	temp19;
const #214 = Asciz	andThen;
const #215 = Asciz	(Lscala/Function1;)Lscala/Function1;;
const #216 = Asciz	(Lscala/Function1;Lscala/Function1;)Lscala/Function1;;
const #217 = NameAndType	#214:#216;//  andThen:(Lscala/Function1;Lscala/Function1;)Lscala/Function1;
const #218 = Method	#31.#217;	//  scala/Function1$class.andThen:(Lscala/Function1;Lscala/Function1;)Lscala/Function1;
const #219 = Asciz	g;
const #220 = Asciz	Lscala/Function1;;
const #221 = Asciz	compose;
const #222 = NameAndType	#221:#216;//  compose:(Lscala/Function1;Lscala/Function1;)Lscala/Function1;
const #223 = Method	#31.#222;	//  scala/Function1$class.compose:(Lscala/Function1;Lscala/Function1;)Lscala/Function1;
const #224 = Asciz	(Lscala/Function1;)Ljava/lang/String;;
const #225 = NameAndType	#114:#224;//  toString:(Lscala/Function1;)Ljava/lang/String;
const #226 = Method	#31.#225;	//  scala/Function1$class.toString:(Lscala/Function1;)Ljava/lang/String;
const #227 = Asciz	Scala;
const #228 = Asciz	InnerClasses;
const #229 = Asciz	$anonfun$check$1;
const #230 = Asciz	scala/collection/generic/TraversableFactory;
const #231 = class	#230;	//  scala/collection/generic/TraversableFactory
const #232 = Asciz	GenericCanBuildFrom;
const #233 = Asciz	$anonfun$find$1$1;
const #234 = Asciz	scala/Function1;
const #235 = class	#234;	//  scala/Function1
const #236 = Asciz	scala/ScalaObject;
const #237 = class	#236;	//  scala/ScalaObject
const #238 = Asciz	java/io/Serializable;
const #239 = class	#238;	//  java/io/Serializable

{
public static final long serialVersionUID;

public final scala.runtime.ObjectRef ok$1;

public static {};
  Code:
   Stack=2, Locals=0, Args_size=0
   0:	lconst_0
   1:	putstatic	#11; //Field serialVersionUID:J
   4:	return

public scala.xml.dtd.ElementValidator$$anonfun$check$1(scala.xml.dtd.ElementValidator, scala.runtime.ObjectRef);
  Code:
   Stack=2, Locals=3, Args_size=3
   0:	aload_1
   1:	ifnonnull	12
   4:	new	#20; //class java/lang/NullPointerException
   7:	dup
   8:	invokespecial	#22; //Method java/lang/NullPointerException."<init>":()V
   11:	athrow
   12:	aload_0
   13:	aload_1
   14:	putfield	#24; //Field $outer:Lscala/xml/dtd/ElementValidator;
   17:	aload_0
   18:	aload_2
   19:	putfield	#26; //Field ok$1:Lscala/runtime/ObjectRef;
   22:	aload_0
   23:	invokespecial	#29; //Method java/lang/Object."<init>":()V
   26:	aload_0
   27:	invokestatic	#35; //Method scala/Function1$class.$init$:(Lscala/Function1;)V
   30:	return
  LineNumberTable: 
   line 68: 0

  LocalVariableTable: 
   Start  Length  Slot  Name   Signature
   0      31      0    this       Lscala/xml/dtd/ElementValidator$$anonfun$check$1;
   0      31      1    $outer       Lscala/xml/dtd/ElementValidator;


public final java.lang.Object apply(java.lang.Object);
  Code:
   Stack=2, Locals=3, Args_size=2
   0:	aload_0
   1:	getfield	#24; //Field $outer:Lscala/xml/dtd/ElementValidator;
   4:	astore_2
   5:	aload_0
   6:	aload_1
   7:	checkcast	#108; //class scala/xml/MetaData
   10:	invokevirtual	#122; //Method apply:(Lscala/xml/MetaData;)V
   13:	getstatic	#128; //Field scala/runtime/BoxedUnit.UNIT:Lscala/runtime/BoxedUnit;
   16:	areturn
  LineNumberTable: 
   line 68: 0

  LocalVariableTable: 
   Start  Length  Slot  Name   Signature
   0      17      0    this       Lscala/xml/dtd/ElementValidator$$anonfun$check$1;
   5      12      1    v1       Ljava/lang/Object;


public final void apply(scala.xml.MetaData);
  Code:
   Stack=6, Locals=13, Args_size=2
   0:	aload_0
   1:	getfield	#24; //Field $outer:Lscala/xml/dtd/ElementValidator;
   4:	astore	12
   6:	aload_0
   7:	aload_1
   8:	invokevirtual	#131; //Method scala/xml/MetaData.key:()Ljava/lang/String;
   11:	invokespecial	#133; //Method find$1:(Ljava/lang/String;)Lscala/Option;
   14:	astore	11
   16:	getstatic	#89; //Field scala/None$.MODULE$:Lscala/None$;
   19:	dup
   20:	ifnonnull	32
   23:	pop
   24:	aload	11
   26:	ifnull	40
   29:	goto	113
   32:	aload	11
   34:	invokevirtual	#48; //Method java/lang/Object.equals:(Ljava/lang/Object;)Z
   37:	ifeq	113
   40:	iconst_1
   41:	ifeq	100
   44:	aload_0
   45:	getfield	#24; //Field $outer:Lscala/xml/dtd/ElementValidator;
   48:	aload_0
   49:	getfield	#24; //Field $outer:Lscala/xml/dtd/ElementValidator;
   52:	invokevirtual	#136; //Method scala/xml/dtd/ElementValidator.scala$xml$dtd$ElementValidator$$exc:()Lscala/collection/immutable/List;
   55:	aload_1
   56:	invokevirtual	#131; //Method scala/xml/MetaData.key:()Ljava/lang/String;
   59:	astore_2
   60:	new	#138; //class scala/xml/dtd/ValidationException
   63:	dup
   64:	new	#140; //class scala/collection/mutable/StringBuilder
   67:	dup
   68:	invokespecial	#141; //Method scala/collection/mutable/StringBuilder."<init>":()V
   71:	ldc	#143; //String attribute 
   73:	invokevirtual	#147; //Method scala/collection/mutable/StringBuilder.append:(Ljava/lang/Object;)Lscala/collection/mutable/StringBuilder;
   76:	aload_2
   77:	invokevirtual	#147; //Method scala/collection/mutable/StringBuilder.append:(Ljava/lang/Object;)Lscala/collection/mutable/StringBuilder;
   80:	ldc	#149; //String  not allowed here
   82:	invokevirtual	#147; //Method scala/collection/mutable/StringBuilder.append:(Ljava/lang/Object;)Lscala/collection/mutable/StringBuilder;
   85:	invokevirtual	#150; //Method scala/collection/mutable/StringBuilder.toString:()Ljava/lang/String;
   88:	invokespecial	#153; //Method scala/xml/dtd/ValidationException."<init>":(Ljava/lang/String;)V
   91:	invokevirtual	#159; //Method scala/collection/immutable/List.$colon$colon:(Ljava/lang/Object;)Lscala/collection/immutable/List;
   94:	invokevirtual	#163; //Method scala/xml/dtd/ElementValidator.scala$xml$dtd$ElementValidator$$exc_$eq:(Lscala/collection/immutable/List;)V
   97:	goto	355
   100:	new	#165; //class scala/MatchError
   103:	dup
   104:	aload	11
   106:	invokevirtual	#166; //Method scala/Option.toString:()Ljava/lang/String;
   109:	invokespecial	#167; //Method scala/MatchError."<init>":(Ljava/lang/String;)V
   112:	athrow
   113:	aload	11
   115:	instanceof	#169; //class scala/Some
   118:	ifeq	351
   121:	aload	11
   123:	checkcast	#169; //class scala/Some
   126:	astore_3
   127:	aload_3
   128:	getfield	#172; //Field scala/Some.x:Ljava/lang/Object;
   131:	checkcast	#174; //class scala/xml/dtd/AttrDecl
   134:	astore	4
   136:	aload	4
   138:	ifnull	334
   141:	aload	4
   143:	invokevirtual	#177; //Method scala/xml/dtd/AttrDecl.tpe:()Ljava/lang/String;
   146:	astore	7
   148:	aload	4
   150:	invokevirtual	#181; //Method scala/xml/dtd/AttrDecl.default:()Lscala/xml/dtd/DefaultDecl;
   153:	astore	5
   155:	aload	5
   157:	instanceof	#183; //class scala/xml/dtd/DEFAULT
   160:	ifeq	317
   163:	aload	5
   165:	checkcast	#183; //class scala/xml/dtd/DEFAULT
   168:	astore	6
   170:	aload	6
   172:	invokevirtual	#186; //Method scala/xml/dtd/DEFAULT.attValue:()Ljava/lang/String;
   175:	astore	9
   177:	aload	6
   179:	invokevirtual	#190; //Method scala/xml/dtd/DEFAULT.fixed:()Z
   182:	iconst_1
   183:	if_icmpne	300
   186:	aload_0
   187:	aload	7
   189:	aload	9
   191:	aload_1
   192:	invokespecial	#192; //Method gd4$1:(Ljava/lang/String;Ljava/lang/String;Lscala/xml/MetaData;)Z
   195:	ifeq	283
   198:	aload_0
   199:	getfield	#24; //Field $outer:Lscala/xml/dtd/ElementValidator;
   202:	aload_0
   203:	getfield	#24; //Field $outer:Lscala/xml/dtd/ElementValidator;
   206:	invokevirtual	#136; //Method scala/xml/dtd/ElementValidator.scala$xml$dtd$ElementValidator$$exc:()Lscala/collection/immutable/List;
   209:	aload_1
   210:	invokevirtual	#131; //Method scala/xml/MetaData.key:()Ljava/lang/String;
   213:	aload_0
   214:	aload_1
   215:	invokespecial	#44; //Method attrStr$1:(Lscala/xml/MetaData;)Ljava/lang/String;
   218:	astore	10
   220:	astore	8
   222:	new	#138; //class scala/xml/dtd/ValidationException
   225:	dup
   226:	new	#140; //class scala/collection/mutable/StringBuilder
   229:	dup
   230:	invokespecial	#141; //Method scala/collection/mutable/StringBuilder."<init>":()V
   233:	ldc	#194; //String value of attribute 
   235:	invokevirtual	#147; //Method scala/collection/mutable/StringBuilder.append:(Ljava/lang/Object;)Lscala/collection/mutable/StringBuilder;
   238:	aload	8
   240:	invokevirtual	#147; //Method scala/collection/mutable/StringBuilder.append:(Ljava/lang/Object;)Lscala/collection/mutable/StringBuilder;
   243:	ldc	#196; //String  FIXED to \"
   245:	invokevirtual	#147; //Method scala/collection/mutable/StringBuilder.append:(Ljava/lang/Object;)Lscala/collection/mutable/StringBuilder;
   248:	aload	9
   250:	invokevirtual	#147; //Method scala/collection/mutable/StringBuilder.append:(Ljava/lang/Object;)Lscala/collection/mutable/StringBuilder;
   253:	ldc	#198; //String \", but document tries \"
   255:	invokevirtual	#147; //Method scala/collection/mutable/StringBuilder.append:(Ljava/lang/Object;)Lscala/collection/mutable/StringBuilder;
   258:	aload	10
   260:	invokevirtual	#147; //Method scala/collection/mutable/StringBuilder.append:(Ljava/lang/Object;)Lscala/collection/mutable/StringBuilder;
   263:	ldc	#200; //String \"
   265:	invokevirtual	#147; //Method scala/collection/mutable/StringBuilder.append:(Ljava/lang/Object;)Lscala/collection/mutable/StringBuilder;
   268:	invokevirtual	#150; //Method scala/collection/mutable/StringBuilder.toString:()Ljava/lang/String;
   271:	invokespecial	#153; //Method scala/xml/dtd/ValidationException."<init>":(Ljava/lang/String;)V
   274:	invokevirtual	#159; //Method scala/collection/immutable/List.$colon$colon:(Ljava/lang/Object;)Lscala/collection/immutable/List;
   277:	invokevirtual	#163; //Method scala/xml/dtd/ElementValidator.scala$xml$dtd$ElementValidator$$exc_$eq:(Lscala/collection/immutable/List;)V
   280:	goto	355
   283:	iconst_1
   284:	ifne	355
   287:	new	#165; //class scala/MatchError
   290:	dup
   291:	aload	11
   293:	invokevirtual	#166; //Method scala/Option.toString:()Ljava/lang/String;
   296:	invokespecial	#167; //Method scala/MatchError."<init>":(Ljava/lang/String;)V
   299:	athrow
   300:	iconst_1
   301:	ifne	355
   304:	new	#165; //class scala/MatchError
   307:	dup
   308:	aload	11
   310:	invokevirtual	#166; //Method scala/Option.toString:()Ljava/lang/String;
   313:	invokespecial	#167; //Method scala/MatchError."<init>":(Ljava/lang/String;)V
   316:	athrow
   317:	iconst_1
   318:	ifne	355
   321:	new	#165; //class scala/MatchError
   324:	dup
   325:	aload	11
   327:	invokevirtual	#166; //Method scala/Option.toString:()Ljava/lang/String;
   330:	invokespecial	#167; //Method scala/MatchError."<init>":(Ljava/lang/String;)V
   333:	athrow
   334:	iconst_1
   335:	ifne	355
   338:	new	#165; //class scala/MatchError
   341:	dup
   342:	aload	11
   344:	invokevirtual	#166; //Method scala/Option.toString:()Ljava/lang/String;
   347:	invokespecial	#167; //Method scala/MatchError."<init>":(Ljava/lang/String;)V
   350:	athrow
   351:	iconst_1
   352:	ifeq	356
   355:	return
   356:	new	#165; //class scala/MatchError
   359:	dup
   360:	aload	11
   362:	invokevirtual	#166; //Method scala/Option.toString:()Ljava/lang/String;
   365:	invokespecial	#167; //Method scala/MatchError."<init>":(Ljava/lang/String;)V
   368:	athrow
  LineNumberTable: 
   line 78: 0
   line 21: 40
   line 80: 44
   line 78: 100
   line 68: 121
   line 78: 136
   line 68: 141
   line 78: 155
   line 68: 163
   line 78: 182
   line 83: 198
   line 21: 283
   line 78: 287
   line 21: 300
   line 78: 304
   line 21: 317
   line 78: 321
   line 21: 334
   line 78: 338
   line 21: 351
   line 78: 355

  LocalVariableTable: 
   Start  Length  Slot  Name   Signature
   0      369      0    this       Lscala/xml/dtd/ElementValidator$$anonfun$check$1;
   6      363      1    attr$1       Lscala/xml/MetaData;
   127      224      3    temp21       Lscala/Some;
   136      215      4    temp22       Lscala/xml/dtd/AttrDecl;
   155      179      5    temp25       Lscala/xml/dtd/DefaultDecl;
   170      147      6    temp26       Lscala/xml/dtd/DEFAULT;
   148      186      7    temp24       Ljava/lang/String;
   177      140      9    temp28       Ljava/lang/String;
   16      353      11    temp19       Lscala/Option;


public scala.Function1 andThen(scala.Function1);
  Code:
   Stack=2, Locals=2, Args_size=2
   0:	aload_0
   1:	aload_1
   2:	invokestatic	#218; //Method scala/Function1$class.andThen:(Lscala/Function1;Lscala/Function1;)Lscala/Function1;
   5:	areturn
  LineNumberTable: 
   line 68: 0

  LocalVariableTable: 
   Start  Length  Slot  Name   Signature
   0      6      0    this       Lscala/xml/dtd/ElementValidator$$anonfun$check$1;
   0      6      1    g       Lscala/Function1;


public scala.Function1 compose(scala.Function1);
  Code:
   Stack=2, Locals=2, Args_size=2
   0:	aload_0
   1:	aload_1
   2:	invokestatic	#223; //Method scala/Function1$class.compose:(Lscala/Function1;Lscala/Function1;)Lscala/Function1;
   5:	areturn
  LineNumberTable: 
   line 68: 0

  LocalVariableTable: 
   Start  Length  Slot  Name   Signature
   0      6      0    this       Lscala/xml/dtd/ElementValidator$$anonfun$check$1;
   0      6      1    g       Lscala/Function1;


public java.lang.String toString();
  Code:
   Stack=1, Locals=1, Args_size=1
   0:	aload_0
   1:	invokestatic	#226; //Method scala/Function1$class.toString:(Lscala/Function1;)Ljava/lang/String;
   4:	areturn
  LineNumberTable: 
   line 68: 0


}

