Compiled from "ElementValidator.scala"
public final class scala.xml.dtd.ElementValidator$$anonfun$find$2$1 extends java.lang.Object implements scala.Function1,scala.ScalaObject,java.io.Serializable
  SourceFile: "ElementValidator.scala"
  Scala: length = 0x
   
  InnerClass: 
   public abstract #94= #37 of #93; //RegExp=class scala/util/regexp/Base$RegExp of class scala/util/regexp/Base
   public abstract #99= #96 of #98; //Label=class scala/util/regexp/WordExp$Label of class scala/util/regexp/WordExp
   public #100= #50 of #98; //Letter=class scala/util/regexp/WordExp$Letter of class scala/util/regexp/WordExp
   public #103= #56 of #102; //ElemName=class scala/xml/dtd/ContentModel$ElemName of class scala/xml/dtd/ContentModel
   public final #106= #9 of #105; //$anonfun$find$2$1=class scala/xml/dtd/ElementValidator$$anonfun$find$2$1 of class scala/xml/dtd/ElementValidator
  minor version: 0
  major version: 49
  Constant pool:
const #1 = Asciz	SourceFile;
const #2 = Asciz	ElementValidator.scala;
const #3 = Asciz	<clinit>;
const #4 = Asciz	()V;
const #5 = Asciz	Code;
const #6 = Asciz	serialVersionUID;
const #7 = Asciz	J;
const #8 = Asciz	scala/xml/dtd/ElementValidator$$anonfun$find$2$1;
const #9 = class	#8;	//  scala/xml/dtd/ElementValidator$$anonfun$find$2$1
const #10 = NameAndType	#6:#7;//  serialVersionUID:J
const #11 = Field	#9.#10;	//  scala/xml/dtd/ElementValidator$$anonfun$find$2$1.serialVersionUID:J
const #12 = Asciz	Key$2;
const #13 = Asciz	Ljava/lang/String;;
const #14 = Asciz	<init>;
const #15 = Asciz	(Lscala/xml/dtd/ElementValidator;Ljava/lang/String;)V;
const #16 = Asciz	LineNumberTable;
const #17 = NameAndType	#12:#13;//  Key$2:Ljava/lang/String;
const #18 = Field	#9.#17;	//  scala/xml/dtd/ElementValidator$$anonfun$find$2$1.Key$2:Ljava/lang/String;
const #19 = Asciz	java/lang/Object;
const #20 = class	#19;	//  java/lang/Object
const #21 = NameAndType	#14:#4;//  "<init>":()V
const #22 = Method	#20.#21;	//  java/lang/Object."<init>":()V
const #23 = Asciz	scala/Function1$class;
const #24 = class	#23;	//  scala/Function1$class
const #25 = Asciz	$init$;
const #26 = Asciz	(Lscala/Function1;)V;
const #27 = NameAndType	#25:#26;//  $init$:(Lscala/Function1;)V
const #28 = Method	#24.#27;	//  scala/Function1$class.$init$:(Lscala/Function1;)V
const #29 = Asciz	this;
const #30 = Asciz	Lscala/xml/dtd/ElementValidator$$anonfun$find$2$1;;
const #31 = Asciz	$outer;
const #32 = Asciz	Lscala/xml/dtd/ElementValidator;;
const #33 = Asciz	LocalVariableTable;
const #34 = Asciz	apply;
const #35 = Asciz	(Ljava/lang/Object;)Ljava/lang/Object;;
const #36 = Asciz	scala/util/regexp/Base$RegExp;
const #37 = class	#36;	//  scala/util/regexp/Base$RegExp
const #38 = Asciz	(Lscala/util/regexp/Base$RegExp;)Z;
const #39 = NameAndType	#34:#38;//  apply:(Lscala/util/regexp/Base$RegExp;)Z
const #40 = Method	#9.#39;	//  scala/xml/dtd/ElementValidator$$anonfun$find$2$1.apply:(Lscala/util/regexp/Base$RegExp;)Z
const #41 = Asciz	scala/runtime/BoxesRunTime;
const #42 = class	#41;	//  scala/runtime/BoxesRunTime
const #43 = Asciz	boxToBoolean;
const #44 = Asciz	(Z)Ljava/lang/Boolean;;
const #45 = NameAndType	#43:#44;//  boxToBoolean:(Z)Ljava/lang/Boolean;
const #46 = Method	#42.#45;	//  scala/runtime/BoxesRunTime.boxToBoolean:(Z)Ljava/lang/Boolean;
const #47 = Asciz	v1;
const #48 = Asciz	Ljava/lang/Object;;
const #49 = Asciz	scala/util/regexp/WordExp$Letter;
const #50 = class	#49;	//  scala/util/regexp/WordExp$Letter
const #51 = Asciz	a;
const #52 = Asciz	()Lscala/util/regexp/WordExp$Label;;
const #53 = NameAndType	#51:#52;//  a:()Lscala/util/regexp/WordExp$Label;
const #54 = Method	#50.#53;	//  scala/util/regexp/WordExp$Letter.a:()Lscala/util/regexp/WordExp$Label;
const #55 = Asciz	scala/xml/dtd/ContentModel$ElemName;
const #56 = class	#55;	//  scala/xml/dtd/ContentModel$ElemName
const #57 = Asciz	name;
const #58 = Asciz	()Ljava/lang/String;;
const #59 = NameAndType	#57:#58;//  name:()Ljava/lang/String;
const #60 = Method	#56.#59;	//  scala/xml/dtd/ContentModel$ElemName.name:()Ljava/lang/String;
const #61 = Asciz	equals;
const #62 = Asciz	(Ljava/lang/Object;)Z;
const #63 = NameAndType	#61:#62;//  equals:(Ljava/lang/Object;)Z
const #64 = Method	#20.#63;	//  java/lang/Object.equals:(Ljava/lang/Object;)Z
const #65 = Asciz	scala/MatchError;
const #66 = class	#65;	//  scala/MatchError
const #67 = Asciz	toString;
const #68 = NameAndType	#67:#58;//  toString:()Ljava/lang/String;
const #69 = Method	#37.#68;	//  scala/util/regexp/Base$RegExp.toString:()Ljava/lang/String;
const #70 = Asciz	(Ljava/lang/String;)V;
const #71 = NameAndType	#14:#70;//  "<init>":(Ljava/lang/String;)V
const #72 = Method	#66.#71;	//  scala/MatchError."<init>":(Ljava/lang/String;)V
const #73 = Asciz	temp38;
const #74 = Asciz	Lscala/util/regexp/WordExp$Letter;;
const #75 = Asciz	temp39;
const #76 = Asciz	Lscala/xml/dtd/ContentModel$ElemName;;
const #77 = Asciz	andThen;
const #78 = Asciz	(Lscala/Function1;)Lscala/Function1;;
const #79 = Asciz	(Lscala/Function1;Lscala/Function1;)Lscala/Function1;;
const #80 = NameAndType	#77:#79;//  andThen:(Lscala/Function1;Lscala/Function1;)Lscala/Function1;
const #81 = Method	#24.#80;	//  scala/Function1$class.andThen:(Lscala/Function1;Lscala/Function1;)Lscala/Function1;
const #82 = Asciz	g;
const #83 = Asciz	Lscala/Function1;;
const #84 = Asciz	compose;
const #85 = NameAndType	#84:#79;//  compose:(Lscala/Function1;Lscala/Function1;)Lscala/Function1;
const #86 = Method	#24.#85;	//  scala/Function1$class.compose:(Lscala/Function1;Lscala/Function1;)Lscala/Function1;
const #87 = Asciz	(Lscala/Function1;)Ljava/lang/String;;
const #88 = NameAndType	#67:#87;//  toString:(Lscala/Function1;)Ljava/lang/String;
const #89 = Method	#24.#88;	//  scala/Function1$class.toString:(Lscala/Function1;)Ljava/lang/String;
const #90 = Asciz	Scala;
const #91 = Asciz	InnerClasses;
const #92 = Asciz	scala/util/regexp/Base;
const #93 = class	#92;	//  scala/util/regexp/Base
const #94 = Asciz	RegExp;
const #95 = Asciz	scala/util/regexp/WordExp$Label;
const #96 = class	#95;	//  scala/util/regexp/WordExp$Label
const #97 = Asciz	scala/util/regexp/WordExp;
const #98 = class	#97;	//  scala/util/regexp/WordExp
const #99 = Asciz	Label;
const #100 = Asciz	Letter;
const #101 = Asciz	scala/xml/dtd/ContentModel;
const #102 = class	#101;	//  scala/xml/dtd/ContentModel
const #103 = Asciz	ElemName;
const #104 = Asciz	scala/xml/dtd/ElementValidator;
const #105 = class	#104;	//  scala/xml/dtd/ElementValidator
const #106 = Asciz	$anonfun$find$2$1;
const #107 = Asciz	scala/Function1;
const #108 = class	#107;	//  scala/Function1
const #109 = Asciz	scala/ScalaObject;
const #110 = class	#109;	//  scala/ScalaObject
const #111 = Asciz	java/io/Serializable;
const #112 = class	#111;	//  java/io/Serializable

{
public static final long serialVersionUID;

public static {};
  Code:
   Stack=2, Locals=0, Args_size=0
   0:	lconst_0
   1:	putstatic	#11; //Field serialVersionUID:J
   4:	return

public scala.xml.dtd.ElementValidator$$anonfun$find$2$1(scala.xml.dtd.ElementValidator, java.lang.String);
  Code:
   Stack=2, Locals=3, Args_size=3
   0:	aload_0
   1:	aload_2
   2:	putfield	#18; //Field Key$2:Ljava/lang/String;
   5:	aload_0
   6:	invokespecial	#22; //Method java/lang/Object."<init>":()V
   9:	aload_0
   10:	invokestatic	#28; //Method scala/Function1$class.$init$:(Lscala/Function1;)V
   13:	return
  LineNumberTable: 
   line 107: 0

  LocalVariableTable: 
   Start  Length  Slot  Name   Signature
   0      14      0    this       Lscala/xml/dtd/ElementValidator$$anonfun$find$2$1;
   0      14      1    $outer       Lscala/xml/dtd/ElementValidator;


public final java.lang.Object apply(java.lang.Object);
  Code:
   Stack=2, Locals=3, Args_size=2
   0:	aload_0
   1:	aload_1
   2:	checkcast	#37; //class scala/util/regexp/Base$RegExp
   5:	invokevirtual	#40; //Method apply:(Lscala/util/regexp/Base$RegExp;)Z
   8:	istore_2
   9:	iload_2
   10:	invokestatic	#46; //Method scala/runtime/BoxesRunTime.boxToBoolean:(Z)Ljava/lang/Boolean;
   13:	areturn
  LineNumberTable: 
   line 107: 0

  LocalVariableTable: 
   Start  Length  Slot  Name   Signature
   0      14      0    this       Lscala/xml/dtd/ElementValidator$$anonfun$find$2$1;
   0      14      1    v1       Ljava/lang/Object;


public final boolean apply(scala.util.regexp.Base$RegExp);
  Code:
   Stack=3, Locals=5, Args_size=2
   0:	aload_1
   1:	instanceof	#50; //class scala/util/regexp/WordExp$Letter
   4:	ifeq	115
   7:	aload_1
   8:	checkcast	#50; //class scala/util/regexp/WordExp$Letter
   11:	astore_2
   12:	aload_2
   13:	invokevirtual	#54; //Method scala/util/regexp/WordExp$Letter.a:()Lscala/util/regexp/WordExp$Label;
   16:	checkcast	#56; //class scala/xml/dtd/ContentModel$ElemName
   19:	astore_3
   20:	aload_3
   21:	ifnull	95
   24:	aload_0
   25:	getfield	#18; //Field Key$2:Ljava/lang/String;
   28:	aload_3
   29:	invokevirtual	#60; //Method scala/xml/dtd/ContentModel$ElemName.name:()Ljava/lang/String;
   32:	astore	4
   34:	dup
   35:	ifnonnull	47
   38:	pop
   39:	aload	4
   41:	ifnull	55
   44:	goto	75
   47:	aload	4
   49:	invokevirtual	#64; //Method java/lang/Object.equals:(Ljava/lang/Object;)Z
   52:	ifeq	75
   55:	iconst_1
   56:	ifeq	63
   59:	iconst_1
   60:	goto	120
   63:	new	#66; //class scala/MatchError
   66:	dup
   67:	aload_1
   68:	invokevirtual	#69; //Method scala/util/regexp/Base$RegExp.toString:()Ljava/lang/String;
   71:	invokespecial	#72; //Method scala/MatchError."<init>":(Ljava/lang/String;)V
   74:	athrow
   75:	iconst_1
   76:	ifeq	83
   79:	iconst_0
   80:	goto	120
   83:	new	#66; //class scala/MatchError
   86:	dup
   87:	aload_1
   88:	invokevirtual	#69; //Method scala/util/regexp/Base$RegExp.toString:()Ljava/lang/String;
   91:	invokespecial	#72; //Method scala/MatchError."<init>":(Ljava/lang/String;)V
   94:	athrow
   95:	iconst_1
   96:	ifeq	103
   99:	iconst_0
   100:	goto	120
   103:	new	#66; //class scala/MatchError
   106:	dup
   107:	aload_1
   108:	invokevirtual	#69; //Method scala/util/regexp/Base$RegExp.toString:()Ljava/lang/String;
   111:	invokespecial	#72; //Method scala/MatchError."<init>":(Ljava/lang/String;)V
   114:	athrow
   115:	iconst_1
   116:	ifeq	121
   119:	iconst_0
   120:	ireturn
   121:	new	#66; //class scala/MatchError
   124:	dup
   125:	aload_1
   126:	invokevirtual	#69; //Method scala/util/regexp/Base$RegExp.toString:()Ljava/lang/String;
   129:	invokespecial	#72; //Method scala/MatchError."<init>":(Ljava/lang/String;)V
   132:	athrow
  LineNumberTable: 
   line 107: 0
   line 21: 55
   line 107: 59
   line 21: 75
   line 107: 79
   line 21: 95
   line 107: 99
   line 21: 115
   line 107: 119

  LocalVariableTable: 
   Start  Length  Slot  Name   Signature
   0      133      0    this       Lscala/xml/dtd/ElementValidator$$anonfun$find$2$1;
   12      103      2    temp38       Lscala/util/regexp/WordExp$Letter;
   20      95      3    temp39       Lscala/xml/dtd/ContentModel$ElemName;


public scala.Function1 andThen(scala.Function1);
  Code:
   Stack=2, Locals=2, Args_size=2
   0:	aload_0
   1:	aload_1
   2:	invokestatic	#81; //Method scala/Function1$class.andThen:(Lscala/Function1;Lscala/Function1;)Lscala/Function1;
   5:	areturn
  LineNumberTable: 
   line 107: 0

  LocalVariableTable: 
   Start  Length  Slot  Name   Signature
   0      6      0    this       Lscala/xml/dtd/ElementValidator$$anonfun$find$2$1;
   0      6      1    g       Lscala/Function1;


public scala.Function1 compose(scala.Function1);
  Code:
   Stack=2, Locals=2, Args_size=2
   0:	aload_0
   1:	aload_1
   2:	invokestatic	#86; //Method scala/Function1$class.compose:(Lscala/Function1;Lscala/Function1;)Lscala/Function1;
   5:	areturn
  LineNumberTable: 
   line 107: 0

  LocalVariableTable: 
   Start  Length  Slot  Name   Signature
   0      6      0    this       Lscala/xml/dtd/ElementValidator$$anonfun$find$2$1;
   0      6      1    g       Lscala/Function1;


public java.lang.String toString();
  Code:
   Stack=1, Locals=1, Args_size=1
   0:	aload_0
   1:	invokestatic	#89; //Method scala/Function1$class.toString:(Lscala/Function1;)Ljava/lang/String;
   4:	areturn
  LineNumberTable: 
   line 107: 0


}

