Compiled from "Decl.scala"
public final class scala.xml.dtd.ElemDecl$ extends java.lang.Object implements scala.Function2,scala.ScalaObject
  SourceFile: "Decl.scala"
  Scala: length = 0x
   
  minor version: 0
  major version: 49
  Constant pool:
Asciz	SourceFile;
Asciz	Decl.scala;
Asciz	Scala;
Asciz	MODULE$;
Asciz	Lscala/xml/dtd/ElemDecl$;;
Asciz	<clinit>;
Asciz	()V;
Asciz	Code;
Asciz	scala/xml/dtd/ElemDecl$;
class	scala/xml/dtd/ElemDecl$
Asciz	<init>;
NameAndType	"<init>":()V
Method	scala/xml/dtd/ElemDecl$."<init>":()V
Asciz	LineNumberTable;
Asciz	java/lang/Object;
class	java/lang/Object
Method	java/lang/Object."<init>":()V
NameAndType	MODULE$:Lscala/xml/dtd/ElemDecl$;
Field	scala/xml/dtd/ElemDecl$.MODULE$:Lscala/xml/dtd/ElemDecl$;
Asciz	scala/Function2$class;
class	scala/Function2$class
Asciz	$init$;
Asciz	(Lscala/Function2;)V;
NameAndType	$init$:(Lscala/Function2;)V
Method	scala/Function2$class.$init$:(Lscala/Function2;)V
Asciz	apply;
Asciz	(Ljava/lang/Object;Ljava/lang/Object;)Ljava/lang/Object;;
Asciz	java/lang/String;
class	java/lang/String
Asciz	scala/xml/dtd/ContentModel;
class	scala/xml/dtd/ContentModel
Asciz	(Ljava/lang/String;Lscala/xml/dtd/ContentModel;)Lscala/xml/dtd/ElemDecl;;
NameAndType	apply:(Ljava/lang/String;Lscala/xml/dtd/ContentModel;)Lscala/xml/dtd/ElemDecl;
Method	scala/xml/dtd/ElemDecl$.apply:(Ljava/lang/String;Lscala/xml/dtd/ContentModel;)Lscala/xml/dtd/ElemDecl;
Asciz	this;
Asciz	v1;
Asciz	Ljava/lang/Object;;
Asciz	v2;
Asciz	LocalVariableTable;
Asciz	scala/xml/dtd/ElemDecl;
class	scala/xml/dtd/ElemDecl
Asciz	(Ljava/lang/String;Lscala/xml/dtd/ContentModel;)V;
NameAndType	"<init>":(Ljava/lang/String;Lscala/xml/dtd/ContentModel;)V
Method	scala/xml/dtd/ElemDecl."<init>":(Ljava/lang/String;Lscala/xml/dtd/ContentModel;)V
Asciz	name;
Asciz	Ljava/lang/String;;
Asciz	contentModel;
Asciz	Lscala/xml/dtd/ContentModel;;
Asciz	unapply;
Asciz	(Lscala/xml/dtd/ElemDecl;)Lscala/Some;;
Asciz	scala/Some;
class	scala/Some
Asciz	scala/Tuple2;
class	scala/Tuple2
Asciz	()Ljava/lang/String;;
NameAndType	name:()Ljava/lang/String;
Method	scala/xml/dtd/ElemDecl.name:()Ljava/lang/String;
Asciz	()Lscala/xml/dtd/ContentModel;;
NameAndType	contentModel:()Lscala/xml/dtd/ContentModel;
Method	scala/xml/dtd/ElemDecl.contentModel:()Lscala/xml/dtd/ContentModel;
Asciz	(Ljava/lang/Object;Ljava/lang/Object;)V;
NameAndType	"<init>":(Ljava/lang/Object;Ljava/lang/Object;)V
Method	scala/Tuple2."<init>":(Ljava/lang/Object;Ljava/lang/Object;)V
Asciz	(Ljava/lang/Object;)V;
NameAndType	"<init>":(Ljava/lang/Object;)V
Method	scala/Some."<init>":(Ljava/lang/Object;)V
Asciz	x$0;
Asciz	Lscala/xml/dtd/ElemDecl;;
Asciz	curry;
Asciz	()Lscala/Function1;;
Asciz	(Lscala/Function2;)Lscala/Function1;;
NameAndType	curry:(Lscala/Function2;)Lscala/Function1;
Method	scala/Function2$class.curry:(Lscala/Function2;)Lscala/Function1;
Asciz	toString;
Asciz	(Lscala/Function2;)Ljava/lang/String;;
NameAndType	toString:(Lscala/Function2;)Ljava/lang/String;
Method	scala/Function2$class.toString:(Lscala/Function2;)Ljava/lang/String;
Asciz	scala/Function2;
class	scala/Function2
Asciz	scala/ScalaObject;
class	scala/ScalaObject

{
public static final scala.xml.dtd.ElemDecl$ MODULE$;
  Signature: Lscala/xml/dtd/ElemDecl$;

public static {};
  Signature: ()V
  Code:
   Stack=1, Locals=0, Args_size=0
	new	class scala/xml/dtd/ElemDecl$
	invokespecial	Method "<init>":()V
	return
  Labels:

private scala.xml.dtd.ElemDecl$();
  Signature: ()V
  Code:
   Stack=1, Locals=1, Args_size=1
	aload_0
	invokespecial	Method java/lang/Object."<init>":()V
	aload_0
	putstatic	Field MODULE$:Lscala/xml/dtd/ElemDecl$;
	aload_0
	invokestatic	Method scala/Function2$class.$init$:(Lscala/Function2;)V
	return
  Labels:

public java.lang.Object apply(java.lang.Object, java.lang.Object);
  Signature: (Ljava/lang/Object;Ljava/lang/Object;)Ljava/lang/Object;
  Code:
   Stack=3, Locals=3, Args_size=3
	aload_0
	aload_1
	checkcast	class java/lang/String
	aload_2
	checkcast	class scala/xml/dtd/ContentModel
	invokevirtual	Method apply:(Ljava/lang/String;Lscala/xml/dtd/ContentModel;)Lscala/xml/dtd/ElemDecl;
	areturn
  Labels:
  LocalVariableTable: 
   Start  Length  Slot  Name   Signature
   0      13      0    this       Lscala/xml/dtd/ElemDecl$;
   0      13      1    v1       Ljava/lang/Object;
   0      13      2    v2       Ljava/lang/Object;


public scala.xml.dtd.ElemDecl apply(java.lang.String, scala.xml.dtd.ContentModel);
  Signature: (Ljava/lang/String;Lscala/xml/dtd/ContentModel;)Lscala/xml/dtd/ElemDecl;
  Code:
   Stack=4, Locals=3, Args_size=3
	new	class scala/xml/dtd/ElemDecl
	dup
	aload_1
	aload_2
	invokespecial	Method scala/xml/dtd/ElemDecl."<init>":(Ljava/lang/String;Lscala/xml/dtd/ContentModel;)V
	areturn
  Labels:
  LocalVariableTable: 
   Start  Length  Slot  Name   Signature
   0      10      0    this       Lscala/xml/dtd/ElemDecl$;
   0      10      1    name       Ljava/lang/String;
   0      10      2    contentModel       Lscala/xml/dtd/ContentModel;


public scala.Some unapply(scala.xml.dtd.ElemDecl);
  Signature: (Lscala/xml/dtd/ElemDecl;)Lscala/Some;
  Code:
   Stack=6, Locals=2, Args_size=2
	new	class scala/Some
	dup
	new	class scala/Tuple2
	dup
	aload_1
	invokevirtual	Method scala/xml/dtd/ElemDecl.name:()Ljava/lang/String;
	aload_1
	invokevirtual	Method scala/xml/dtd/ElemDecl.contentModel:()Lscala/xml/dtd/ContentModel;
	invokespecial	Method scala/Tuple2."<init>":(Ljava/lang/Object;Ljava/lang/Object;)V
	invokespecial	Method scala/Some."<init>":(Ljava/lang/Object;)V
	areturn
  Labels:
  LocalVariableTable: 
   Start  Length  Slot  Name   Signature
   0      23      0    this       Lscala/xml/dtd/ElemDecl$;
   0      23      1    x$0       Lscala/xml/dtd/ElemDecl;


public scala.Function1 curry();
  Signature: ()Lscala/Function1;
  Code:
   Stack=1, Locals=1, Args_size=1
	aload_0
	invokestatic	Method scala/Function2$class.curry:(Lscala/Function2;)Lscala/Function1;
	areturn
  Labels:

public java.lang.String toString();
  Signature: ()Ljava/lang/String;
  Code:
   Stack=1, Locals=1, Args_size=1
	aload_0
	invokestatic	Method scala/Function2$class.toString:(Lscala/Function2;)Ljava/lang/String;
	areturn
  Labels:

}

