Compiled from "ElementValidator.scala"
public final class scala.xml.dtd.ElementValidator$$anonfun$getIterable$1 extends java.lang.Object implements scala.Function1,scala.ScalaObject,java.io.Serializable
  SourceFile: "ElementValidator.scala"
  Scala: length = 0x
   
  InnerClass: 
   public final $anonfun$getIterable$1=class scala/xml/dtd/ElementValidator$$anonfun$getIterable$1 of class scala/xml/dtd/ElementValidator
  minor version: 0
  major version: 49
  Constant pool:
Asciz	SourceFile;
Asciz	ElementValidator.scala;
Asciz	<clinit>;
Asciz	()V;
Asciz	Code;
Asciz	serialVersionUID;
Asciz	J;
Asciz	scala/xml/dtd/ElementValidator$$anonfun$getIterable$1;
class	scala/xml/dtd/ElementValidator$$anonfun$getIterable$1
NameAndType	serialVersionUID:J
Field	scala/xml/dtd/ElementValidator$$anonfun$getIterable$1.serialVersionUID:J
Asciz	skipPCDATA$1;
Asciz	Z;
Asciz	$outer;
Asciz	Lscala/xml/dtd/ElementValidator;;
Asciz	<init>;
Asciz	(Lscala/xml/dtd/ElementValidator;Z)V;
Asciz	LineNumberTable;
Asciz	java/lang/NullPointerException;
class	java/lang/NullPointerException
NameAndType	"<init>":()V
Method	java/lang/NullPointerException."<init>":()V
NameAndType	$outer:Lscala/xml/dtd/ElementValidator;
Field	scala/xml/dtd/ElementValidator$$anonfun$getIterable$1.$outer:Lscala/xml/dtd/ElementValidator;
NameAndType	skipPCDATA$1:Z
Field	scala/xml/dtd/ElementValidator$$anonfun$getIterable$1.skipPCDATA$1:Z
Asciz	java/lang/Object;
class	java/lang/Object
Method	java/lang/Object."<init>":()V
Asciz	scala/Function1$class;
class	scala/Function1$class
Asciz	$init$;
Asciz	(Lscala/Function1;)V;
NameAndType	$init$:(Lscala/Function1;)V
Method	scala/Function1$class.$init$:(Lscala/Function1;)V
Asciz	this;
Asciz	Lscala/xml/dtd/ElementValidator$$anonfun$getIterable$1;;
Asciz	LocalVariableTable;
Asciz	gd3$1;
Asciz	(Lscala/xml/Atom;)Z;
Asciz	scala/xml/dtd/ElementValidator;
class	scala/xml/dtd/ElementValidator
Asciz	isAllWhitespace$1;
NameAndType	isAllWhitespace$1:(Lscala/xml/Atom;)Z
Method	scala/xml/dtd/ElementValidator.isAllWhitespace$1:(Lscala/xml/Atom;)Z
Asciz	apply;
Asciz	(Ljava/lang/Object;)Ljava/lang/Object;;
Asciz	scala/xml/Node;
class	scala/xml/Node
Asciz	(Lscala/xml/Node;)Z;
NameAndType	apply:(Lscala/xml/Node;)Z
Method	scala/xml/dtd/ElementValidator$$anonfun$getIterable$1.apply:(Lscala/xml/Node;)Z
Asciz	scala/runtime/BoxesRunTime;
class	scala/runtime/BoxesRunTime
Asciz	boxToBoolean;
Asciz	(Z)Ljava/lang/Boolean;;
NameAndType	boxToBoolean:(Z)Ljava/lang/Boolean;
Method	scala/runtime/BoxesRunTime.boxToBoolean:(Z)Ljava/lang/Boolean;
Asciz	v1;
Asciz	Ljava/lang/Object;;
Asciz	scala/xml/SpecialNode;
class	scala/xml/SpecialNode
Asciz	scala/xml/Atom;
class	scala/xml/Atom
NameAndType	gd3$1:(Lscala/xml/Atom;)Z
Method	scala/xml/dtd/ElementValidator$$anonfun$getIterable$1.gd3$1:(Lscala/xml/Atom;)Z
Asciz	scala/MatchError;
class	scala/MatchError
Asciz	toString;
Asciz	()Ljava/lang/String;;
NameAndType	toString:()Ljava/lang/String;
Method	scala/xml/SpecialNode.toString:()Ljava/lang/String;
Asciz	(Ljava/lang/String;)V;
NameAndType	"<init>":(Ljava/lang/String;)V
Method	scala/MatchError."<init>":(Ljava/lang/String;)V
Method	scala/xml/Node.toString:()Ljava/lang/String;
Asciz	namespace;
NameAndType	namespace:()Ljava/lang/String;
Method	scala/xml/Node.namespace:()Ljava/lang/String;
Asciz	temp11;
Asciz	Lscala/xml/SpecialNode;;
Asciz	andThen;
Asciz	(Lscala/Function1;)Lscala/Function1;;
Asciz	(Lscala/Function1;Lscala/Function1;)Lscala/Function1;;
NameAndType	andThen:(Lscala/Function1;Lscala/Function1;)Lscala/Function1;
Method	scala/Function1$class.andThen:(Lscala/Function1;Lscala/Function1;)Lscala/Function1;
Asciz	g;
Asciz	Lscala/Function1;;
Asciz	compose;
NameAndType	compose:(Lscala/Function1;Lscala/Function1;)Lscala/Function1;
Method	scala/Function1$class.compose:(Lscala/Function1;Lscala/Function1;)Lscala/Function1;
Asciz	(Lscala/Function1;)Ljava/lang/String;;
NameAndType	toString:(Lscala/Function1;)Ljava/lang/String;
Method	scala/Function1$class.toString:(Lscala/Function1;)Ljava/lang/String;
Asciz	Scala;
Asciz	InnerClasses;
Asciz	$anonfun$getIterable$1;
Asciz	scala/Function1;
class	scala/Function1
Asciz	scala/ScalaObject;
class	scala/ScalaObject
Asciz	java/io/Serializable;
class	java/io/Serializable

{
public static final long serialVersionUID;
  Signature: J

private final boolean skipPCDATA$1;
  Signature: Z

private final scala.xml.dtd.ElementValidator $outer;
  Signature: Lscala/xml/dtd/ElementValidator;

public static {};
  Signature: ()V
  Code:
   Stack=2, Locals=0, Args_size=0
	lconst_0
	putstatic	Field serialVersionUID:J
	return
  Labels:

public scala.xml.dtd.ElementValidator$$anonfun$getIterable$1(scala.xml.dtd.ElementValidator, boolean);
  Signature: (Lscala/xml/dtd/ElementValidator;Z)V
  Code:
   Stack=2, Locals=3, Args_size=3
	aload_1
	ifnonnull	l1 // aload_0
	new	class java/lang/NullPointerException
	dup
	invokespecial	Method java/lang/NullPointerException."<init>":()V
	athrow
l1	aload_0
	aload_1
	putfield	Field $outer:Lscala/xml/dtd/ElementValidator;
	aload_0
	iload_2
	putfield	Field skipPCDATA$1:Z
	aload_0
	invokespecial	Method java/lang/Object."<init>":()V
	aload_0
	invokestatic	Method scala/Function1$class.$init$:(Lscala/Function1;)V
	return
  Labels:
   	l1 = 12 // aload_0
  LocalVariableTable: 
   Start  Length  Slot  Name   Signature
   0      31      0    this       Lscala/xml/dtd/ElementValidator$$anonfun$getIterable$1;
   0      31      1    $outer       Lscala/xml/dtd/ElementValidator;


private final boolean gd3$1(scala.xml.Atom);
  Signature: (Lscala/xml/Atom;)Z
  Code:
   Stack=2, Locals=2, Args_size=2
	aload_0
	getfield	Field $outer:Lscala/xml/dtd/ElementValidator;
	aload_1
	invokevirtual	Method scala/xml/dtd/ElementValidator.isAllWhitespace$1:(Lscala/xml/Atom;)Z
	ireturn
  Labels:

public final java.lang.Object apply(java.lang.Object);
  Signature: (Ljava/lang/Object;)Ljava/lang/Object;
  Code:
   Stack=2, Locals=4, Args_size=2
	aload_0
	getfield	Field $outer:Lscala/xml/dtd/ElementValidator;
	astore_3
	aload_0
	aload_1
	checkcast	class scala/xml/Node
	invokevirtual	Method apply:(Lscala/xml/Node;)Z
	istore_2
	iload_2
	invokestatic	Method scala/runtime/BoxesRunTime.boxToBoolean:(Z)Ljava/lang/Boolean;
	areturn
  Labels:
  LocalVariableTable: 
   Start  Length  Slot  Name   Signature
   0      19      0    this       Lscala/xml/dtd/ElementValidator$$anonfun$getIterable$1;
   5      14      1    v1       Ljava/lang/Object;


public final boolean apply(scala.xml.Node);
  Signature: (Lscala/xml/Node;)Z
  Code:
   Stack=3, Locals=4, Args_size=2
	aload_0
	getfield	Field $outer:Lscala/xml/dtd/ElementValidator;
	astore_3
	aload_1
	instanceof	class scala/xml/SpecialNode
	ifeq	l1 // iconst_1
	aload_1
	checkcast	class scala/xml/SpecialNode
	astore_2
	iconst_1
	ifeq	l2 // new
	aload_2
	instanceof	class scala/xml/Atom
	ifeq	l3 // iconst_1
	aload_0
	aload_2
	checkcast	class scala/xml/Atom
	invokespecial	Method gd3$1:(Lscala/xml/Atom;)Z
	ifeq	l4 // iconst_1
	iconst_0
	goto	l5 // ireturn
l4	iconst_1
	ifne	l6 // aload_0
	new	class scala/MatchError
	dup
	aload_2
	invokevirtual	Method scala/xml/SpecialNode.toString:()Ljava/lang/String;
	invokespecial	Method scala/MatchError."<init>":(Ljava/lang/String;)V
	athrow
l3	iconst_1
	ifeq	l7 // new
l6	aload_0
	getfield	Field skipPCDATA$1:Z
	ifeq	l8 // iconst_1
	iconst_0
	goto	l5 // ireturn
l8	iconst_1
	goto	l5 // ireturn
l7	new	class scala/MatchError
	dup
	aload_2
	invokevirtual	Method scala/xml/SpecialNode.toString:()Ljava/lang/String;
	invokespecial	Method scala/MatchError."<init>":(Ljava/lang/String;)V
	athrow
l2	new	class scala/MatchError
	dup
	aload_1
	invokevirtual	Method scala/xml/Node.toString:()Ljava/lang/String;
	invokespecial	Method scala/MatchError."<init>":(Ljava/lang/String;)V
	athrow
l1	iconst_1
	ifeq	l9 // new
	aload_1
	invokevirtual	Method scala/xml/Node.namespace:()Ljava/lang/String;
	ifnonnull	l10 // iconst_0
	iconst_1
	goto	l5 // ireturn
l10	iconst_0
l5	ireturn
l9	new	class scala/MatchError
	dup
	aload_1
	invokevirtual	Method scala/xml/Node.toString:()Ljava/lang/String;
	invokespecial	Method scala/MatchError."<init>":(Ljava/lang/String;)V
	athrow
  Labels:
   	l4 = 43 // iconst_1
   	l3 = 59 // iconst_1
   	l6 = 63 // aload_0
   	l8 = 74 // iconst_1
   	l7 = 78 // new
   	l2 = 90 // new
   	l1 = 102 // iconst_1
   	l10 = 117 // iconst_0
   	l5 = 118 // ireturn
   	l9 = 119 // new
  LocalVariableTable: 
   Start  Length  Slot  Name   Signature
   0      131      0    this       Lscala/xml/dtd/ElementValidator$$anonfun$getIterable$1;
   17      85      2    temp11       Lscala/xml/SpecialNode;


public scala.Function1 andThen(scala.Function1);
  Signature: (Lscala/Function1;)Lscala/Function1;
  Code:
   Stack=2, Locals=2, Args_size=2
	aload_0
	aload_1
	invokestatic	Method scala/Function1$class.andThen:(Lscala/Function1;Lscala/Function1;)Lscala/Function1;
	areturn
  Labels:
  LocalVariableTable: 
   Start  Length  Slot  Name   Signature
   0      6      0    this       Lscala/xml/dtd/ElementValidator$$anonfun$getIterable$1;
   0      6      1    g       Lscala/Function1;


public scala.Function1 compose(scala.Function1);
  Signature: (Lscala/Function1;)Lscala/Function1;
  Code:
   Stack=2, Locals=2, Args_size=2
	aload_0
	aload_1
	invokestatic	Method scala/Function1$class.compose:(Lscala/Function1;Lscala/Function1;)Lscala/Function1;
	areturn
  Labels:
  LocalVariableTable: 
   Start  Length  Slot  Name   Signature
   0      6      0    this       Lscala/xml/dtd/ElementValidator$$anonfun$getIterable$1;
   0      6      1    g       Lscala/Function1;


public java.lang.String toString();
  Signature: ()Ljava/lang/String;
  Code:
   Stack=1, Locals=1, Args_size=1
	aload_0
	invokestatic	Method scala/Function1$class.toString:(Lscala/Function1;)Ljava/lang/String;
	areturn
  Labels:

}

