Compiled from "ElementValidator.scala"
public final class scala.xml.dtd.ElementValidator$$anonfun$check$4 extends scala.runtime.AbstractFunction1 implements java.io.Serializable
  SourceFile: "ElementValidator.scala"
  Scala: length = 0x
   
  InnerClass: 
   public final #56= #9 of #49; //$anonfun$check$4=class scala/xml/dtd/ElementValidator$$anonfun$check$4 of class scala/xml/dtd/ElementValidator
  minor version: 0
  major version: 49
  Constant pool:
const #1 = Asciz	SourceFile;
const #2 = Asciz	ElementValidator.scala;
const #3 = Asciz	<clinit>;
const #4 = Asciz	()V;
const #5 = Asciz	Code;
const #6 = Asciz	serialVersionUID;
const #7 = Asciz	J;
const #8 = Asciz	scala/xml/dtd/ElementValidator$$anonfun$check$4;
const #9 = class	#8;	//  scala/xml/dtd/ElementValidator$$anonfun$check$4
const #10 = NameAndType	#6:#7;//  serialVersionUID:J
const #11 = Field	#9.#10;	//  scala/xml/dtd/ElementValidator$$anonfun$check$4.serialVersionUID:J
const #12 = Asciz	branches$1;
const #13 = Asciz	Lscala/collection/Seq;;
const #14 = Asciz	$outer;
const #15 = Asciz	Lscala/xml/dtd/ElementValidator;;
const #16 = Asciz	<init>;
const #17 = Asciz	(Lscala/xml/dtd/ElementValidator;Lscala/collection/Seq;)V;
const #18 = Asciz	LineNumberTable;
const #19 = Asciz	java/lang/NullPointerException;
const #20 = class	#19;	//  java/lang/NullPointerException
const #21 = NameAndType	#16:#4;//  "<init>":()V
const #22 = Method	#20.#21;	//  java/lang/NullPointerException."<init>":()V
const #23 = NameAndType	#14:#15;//  $outer:Lscala/xml/dtd/ElementValidator;
const #24 = Field	#9.#23;	//  scala/xml/dtd/ElementValidator$$anonfun$check$4.$outer:Lscala/xml/dtd/ElementValidator;
const #25 = NameAndType	#12:#13;//  branches$1:Lscala/collection/Seq;
const #26 = Field	#9.#25;	//  scala/xml/dtd/ElementValidator$$anonfun$check$4.branches$1:Lscala/collection/Seq;
const #27 = Asciz	scala/runtime/AbstractFunction1;
const #28 = class	#27;	//  scala/runtime/AbstractFunction1
const #29 = Method	#28.#21;	//  scala/runtime/AbstractFunction1."<init>":()V
const #30 = Asciz	this;
const #31 = Asciz	Lscala/xml/dtd/ElementValidator$$anonfun$check$4;;
const #32 = Asciz	LocalVariableTable;
const #33 = Asciz	apply;
const #34 = Asciz	(Ljava/lang/Object;)Ljava/lang/Object;;
const #35 = Asciz	java/lang/String;
const #36 = class	#35;	//  java/lang/String
const #37 = Asciz	(Ljava/lang/String;)Z;
const #38 = NameAndType	#33:#37;//  apply:(Ljava/lang/String;)Z
const #39 = Method	#9.#38;	//  scala/xml/dtd/ElementValidator$$anonfun$check$4.apply:(Ljava/lang/String;)Z
const #40 = Asciz	scala/runtime/BoxesRunTime;
const #41 = class	#40;	//  scala/runtime/BoxesRunTime
const #42 = Asciz	boxToBoolean;
const #43 = Asciz	(Z)Ljava/lang/Boolean;;
const #44 = NameAndType	#42:#43;//  boxToBoolean:(Z)Ljava/lang/Boolean;
const #45 = Method	#41.#44;	//  scala/runtime/BoxesRunTime.boxToBoolean:(Z)Ljava/lang/Boolean;
const #46 = Asciz	v1;
const #47 = Asciz	Ljava/lang/Object;;
const #48 = Asciz	scala/xml/dtd/ElementValidator;
const #49 = class	#48;	//  scala/xml/dtd/ElementValidator
const #50 = Asciz	find$2;
const #51 = Asciz	(Ljava/lang/String;Lscala/collection/Seq;)Z;
const #52 = NameAndType	#50:#51;//  find$2:(Ljava/lang/String;Lscala/collection/Seq;)Z
const #53 = Method	#49.#52;	//  scala/xml/dtd/ElementValidator.find$2:(Ljava/lang/String;Lscala/collection/Seq;)Z
const #54 = Asciz	Scala;
const #55 = Asciz	InnerClasses;
const #56 = Asciz	$anonfun$check$4;
const #57 = Asciz	java/io/Serializable;
const #58 = class	#57;	//  java/io/Serializable

{
public static final long serialVersionUID;

public static {};
  Code:
   Stack=2, Locals=0, Args_size=0
   0:	lconst_0
   1:	putstatic	#11; //Field serialVersionUID:J
   4:	return

public scala.xml.dtd.ElementValidator$$anonfun$check$4(scala.xml.dtd.ElementValidator, scala.collection.Seq);
  Code:
   Stack=2, Locals=3, Args_size=3
   0:	aload_1
   1:	ifnonnull	12
   4:	new	#20; //class java/lang/NullPointerException
   7:	dup
   8:	invokespecial	#22; //Method java/lang/NullPointerException."<init>":()V
   11:	athrow
   12:	aload_0
   13:	aload_1
   14:	putfield	#24; //Field $outer:Lscala/xml/dtd/ElementValidator;
   17:	aload_0
   18:	aload_2
   19:	putfield	#26; //Field branches$1:Lscala/collection/Seq;
   22:	aload_0
   23:	invokespecial	#29; //Method scala/runtime/AbstractFunction1."<init>":()V
   26:	return
  LineNumberTable: 
   line 109: 0

  LocalVariableTable: 
   Start  Length  Slot  Name   Signature
   0      27      0    this       Lscala/xml/dtd/ElementValidator$$anonfun$check$4;
   0      27      1    $outer       Lscala/xml/dtd/ElementValidator;


public final java.lang.Object apply(java.lang.Object);
  Code:
   Stack=2, Locals=3, Args_size=2
   0:	aload_0
   1:	aload_1
   2:	checkcast	#36; //class java/lang/String
   5:	invokevirtual	#39; //Method apply:(Ljava/lang/String;)Z
   8:	istore_2
   9:	iload_2
   10:	invokestatic	#45; //Method scala/runtime/BoxesRunTime.boxToBoolean:(Z)Ljava/lang/Boolean;
   13:	areturn
  LineNumberTable: 
   line 109: 0

  LocalVariableTable: 
   Start  Length  Slot  Name   Signature
   0      14      0    this       Lscala/xml/dtd/ElementValidator$$anonfun$check$4;
   0      14      1    v1       Ljava/lang/Object;


public final boolean apply(java.lang.String);
  Code:
   Stack=3, Locals=2, Args_size=2
   0:	aload_0
   1:	getfield	#24; //Field $outer:Lscala/xml/dtd/ElementValidator;
   4:	aload_1
   5:	aload_0
   6:	getfield	#26; //Field branches$1:Lscala/collection/Seq;
   9:	invokevirtual	#53; //Method scala/xml/dtd/ElementValidator.find$2:(Ljava/lang/String;Lscala/collection/Seq;)Z
   12:	ireturn
  LineNumberTable: 
   line 109: 0


}

