Compiled from "ContentModel.scala"
public final class scala.xml.dtd.EMPTY extends java.lang.Object
  SourceFile: "ContentModel.scala"
  ScalaSig: length = 0x3
   05 00 00 
  RuntimeVisibleAnnotations: length = 0xB
   00 01 00 2B 00 01 00 2C 73 00 2D 
  minor version: 0
  major version: 49
  Constant pool:
Asciz	SourceFile;
Asciz	ContentModel.scala;
Asciz	productElements;
Asciz	()Lscala/collection/Iterator;;
Asciz	Code;
Asciz	scala/xml/dtd/EMPTY$;
class	scala/xml/dtd/EMPTY$
Asciz	MODULE$;
Asciz	Lscala/xml/dtd/EMPTY$;;
NameAndType	MODULE$:Lscala/xml/dtd/EMPTY$;
Field	scala/xml/dtd/EMPTY$.MODULE$:Lscala/xml/dtd/EMPTY$;
NameAndType	productElements:()Lscala/collection/Iterator;
Method	scala/xml/dtd/EMPTY$.productElements:()Lscala/collection/Iterator;
Asciz	Deprecated;
Asciz	productIterator;
NameAndType	productIterator:()Lscala/collection/Iterator;
Method	scala/xml/dtd/EMPTY$.productIterator:()Lscala/collection/Iterator;
Asciz	productElementName;
Asciz	(I)Ljava/lang/String;;
NameAndType	productElementName:(I)Ljava/lang/String;
Method	scala/xml/dtd/EMPTY$.productElementName:(I)Ljava/lang/String;
Asciz	canEqual;
Asciz	(Ljava/lang/Object;)Z;
NameAndType	canEqual:(Ljava/lang/Object;)Z
Method	scala/xml/dtd/EMPTY$.canEqual:(Ljava/lang/Object;)Z
Asciz	productElement;
Asciz	(I)Ljava/lang/Object;;
NameAndType	productElement:(I)Ljava/lang/Object;
Method	scala/xml/dtd/EMPTY$.productElement:(I)Ljava/lang/Object;
Asciz	productArity;
Asciz	()I;
NameAndType	productArity:()I
Method	scala/xml/dtd/EMPTY$.productArity:()I
Asciz	productPrefix;
Asciz	()Ljava/lang/String;;
NameAndType	productPrefix:()Ljava/lang/String;
Method	scala/xml/dtd/EMPTY$.productPrefix:()Ljava/lang/String;
Asciz	buildString;
Asciz	(Lscala/collection/mutable/StringBuilder;)Lscala/collection/mutable/StringBuilder;;
NameAndType	buildString:(Lscala/collection/mutable/StringBuilder;)Lscala/collection/mutable/StringBuilder;
Method	scala/xml/dtd/EMPTY$.buildString:(Lscala/collection/mutable/StringBuilder;)Lscala/collection/mutable/StringBuilder;
Asciz	ScalaSig;
Asciz	Lscala/reflect/ScalaSignature;;
Asciz	bytes;
Asciz	Y;Q!\t&\tQ!R'Q)fS!a$HM\r07\tQa]2bY5\t!A\r\t#\")U\n+Z'Ya\"E)yB\t1uN;f]RluZ3m!\t2#D\t!bAATGdm2kK$C\n\t9bAAQe>$Wo;\teYA\rqJg.;?)I\"\tja2vS2$7:j]$\"A}9cB&\t\tC%D#\t\"=e>|GOP%aEBa7.Y4f\tAFATiJLgn\"vS2$WMMAQaKAy\t!a2\t5ZA!AB9\nQ:pIVG:fM&DX#AA*T\"AI7b]TNU4-7c\t11:j]DO%\t%O\raJ|G-^2uJLG/_uA!cOy1!8u!q4\"A\nzA9s_,8\r^#mK6,g\"AE!\n\t3!aA!os\"9A)PAQa=%c!AaiCs)dC:,/^1m)\tA5\n&!J>|G.Z1o!U)!AAC\"T%\tBTeGMU3t_24X\rFP!\t+Rc\t1qJ6fGRD#aC*I!BA+1XM]5bY&TM7f;
Asciz	RuntimeVisibleAnnotations;
Asciz	scala/xml/dtd/EMPTY;
class	scala/xml/dtd/EMPTY
Asciz	java/lang/Object;
class	java/lang/Object

{
public static final scala.collection.Iterator productElements();
  Signature: ()Lscala/collection/Iterator;
  Code:
   Stack=1, Locals=0, Args_size=0
	getstatic	Field scala/xml/dtd/EMPTY$.MODULE$:Lscala/xml/dtd/EMPTY$;
	invokevirtual	Method scala/xml/dtd/EMPTY$.productElements:()Lscala/collection/Iterator;
	areturn
  Labels:
  Deprecated: true

public static final scala.collection.Iterator productIterator();
  Signature: ()Lscala/collection/Iterator;
  Code:
   Stack=1, Locals=0, Args_size=0
	getstatic	Field scala/xml/dtd/EMPTY$.MODULE$:Lscala/xml/dtd/EMPTY$;
	invokevirtual	Method scala/xml/dtd/EMPTY$.productIterator:()Lscala/collection/Iterator;
	areturn
  Labels:

public static final java.lang.String productElementName(int);
  Signature: (I)Ljava/lang/String;
  Code:
   Stack=2, Locals=1, Args_size=1
	getstatic	Field scala/xml/dtd/EMPTY$.MODULE$:Lscala/xml/dtd/EMPTY$;
	iload_0
	invokevirtual	Method scala/xml/dtd/EMPTY$.productElementName:(I)Ljava/lang/String;
	areturn
  Labels:

public static final boolean canEqual(java.lang.Object);
  Signature: (Ljava/lang/Object;)Z
  Code:
   Stack=2, Locals=1, Args_size=1
	getstatic	Field scala/xml/dtd/EMPTY$.MODULE$:Lscala/xml/dtd/EMPTY$;
	aload_0
	invokevirtual	Method scala/xml/dtd/EMPTY$.canEqual:(Ljava/lang/Object;)Z
	ireturn
  Labels:

public static final java.lang.Object productElement(int);
  Signature: (I)Ljava/lang/Object;
  Code:
   Stack=2, Locals=1, Args_size=1
	getstatic	Field scala/xml/dtd/EMPTY$.MODULE$:Lscala/xml/dtd/EMPTY$;
	iload_0
	invokevirtual	Method scala/xml/dtd/EMPTY$.productElement:(I)Ljava/lang/Object;
	areturn
  Labels:

public static final int productArity();
  Signature: ()I
  Code:
   Stack=1, Locals=0, Args_size=0
	getstatic	Field scala/xml/dtd/EMPTY$.MODULE$:Lscala/xml/dtd/EMPTY$;
	invokevirtual	Method scala/xml/dtd/EMPTY$.productArity:()I
	ireturn
  Labels:

public static final java.lang.String productPrefix();
  Signature: ()Ljava/lang/String;
  Code:
   Stack=1, Locals=0, Args_size=0
	getstatic	Field scala/xml/dtd/EMPTY$.MODULE$:Lscala/xml/dtd/EMPTY$;
	invokevirtual	Method scala/xml/dtd/EMPTY$.productPrefix:()Ljava/lang/String;
	areturn
  Labels:

public static final scala.collection.mutable.StringBuilder buildString(scala.collection.mutable.StringBuilder);
  Signature: (Lscala/collection/mutable/StringBuilder;)Lscala/collection/mutable/StringBuilder;
  Code:
   Stack=2, Locals=1, Args_size=1
	getstatic	Field scala/xml/dtd/EMPTY$.MODULE$:Lscala/xml/dtd/EMPTY$;
	aload_0
	invokevirtual	Method scala/xml/dtd/EMPTY$.buildString:(Lscala/collection/mutable/StringBuilder;)Lscala/collection/mutable/StringBuilder;
	areturn
  Labels:

}

