Compiled from "Decl.scala"
public class scala.xml.dtd.ExtDef extends scala.xml.dtd.EntityDef implements scala.ScalaObject,scala.Product,java.io.Serializable
  SourceFile: "Decl.scala"
  ScalaSig: length = 0x3EB
   05 00 FFFFFF81 15 06 08 01 02 FFFFFF84 FFFFFF80 FFFFFF80 FFFFFF80 40 09 02 06
   45 78 74 44 65 66 0A 02 03 04 01 03 64 74 64 0A
   02 05 06 01 03 78 6D 6C 0A 01 07 01 05 73 63 61
   6C 61 03 00 13 04 00 0A 0E 12 10 02 0B 0C 0D 01
   02 09 02 0D 02 02 09 45 6E 74 69 74 79 44 65 66
   10 02 0F 10 0D 01 06 09 02 11 06 02 0B 53 63 61
   6C 61 4F 62 6A 65 63 74 10 02 0F 13 09 02 14 06
   02 07 50 72 6F 64 75 63 74 08 08 16 00 FFFFFF82 FFFFFFCA FFFFFF80
   FFFFFF84 00 17 01 05 65 78 74 49 44 15 01 18 10 02 0B
   19 09 02 1A 02 02 0A 45 78 74 65 72 6E 61 6C 49
   44 08 08 1C 00 FFFFFF82 FFFFFF88 FFFFFFA0 FFFFFF80 04 18 01 06 65 78 74
   49 44 20 08 05 1E 00 FFFFFF84 00 1F 01 06 3C 69 6E 69
   74 3E 14 02 20 21 10 02 0B 00 08 05 16 1D FFFFFFC0 00
   18 08 05 23 00 FFFFFF84 20 24 01 0B 62 75 69 6C 64 53
   74 72 69 6E 67 14 02 25 31 10 02 26 2E 0E 02 27
   2C 0E 02 28 2B 0D 01 29 0A 02 2A 08 01 06 3C 72
   6F 6F 74 3E 09 01 07 09 02 2D 06 01 07 70 61 63
   6B 61 67 65 09 02 2F 30 02 0D 53 74 72 69 6E 67
   42 75 69 6C 64 65 72 0A 02 2D 06 08 05 32 22 FFFFFFC0
   00 25 01 02 73 62 08 07 34 00 FFFFFF81 FFFFFF80 FFFFFF84 00 35 01
   04 63 6F 70 79 14 02 20 36 08 07 16 33 FFFFFF90 FFFFFF80 FFFFFFC0
   00 18 08 07 38 00 FFFFFF91 FFFFFF80 FFFFFF84 00 39 01 0E 63 6F 70
   79 24 64 65 66 61 75 6C 74 24 31 15 01 3A 2A 02
   18 3B 2B 01 3C 10 02 3D 42 0D 01 3E 0A 02 3F 40
   01 09 75 6E 63 68 65 63 6B 65 64 0A 02 41 06 01
   0A 61 6E 6E 6F 74 61 74 69 6F 6E 09 02 43 3E 02
   11 75 6E 63 68 65 63 6B 65 64 56 61 72 69 61 6E
   63 65 08 08 45 00 FFFFFF84 FFFFFF80 FFFFFF80 FFFFFF84 20 46 01 08 68 61
   73 68 43 6F 64 65 14 01 47 10 02 0F 48 09 02 49
   06 02 03 49 6E 74 08 08 4B 00 FFFFFF84 FFFFFF80 FFFFFF80 FFFFFF84 20 4C
   01 08 74 6F 53 74 72 69 6E 67 14 01 4D 10 02 4E
   51 0E 02 0F 4F 09 02 50 06 01 06 50 72 65 64 65
   66 09 02 52 53 02 06 53 74 72 69 6E 67 0A 02 50
   06 08 08 55 00 FFFFFF84 FFFFFF80 FFFFFF80 FFFFFF84 20 56 01 06 65 71 75
   61 6C 73 14 02 57 5A 10 02 0F 58 09 02 59 06 02
   07 42 6F 6F 6C 65 61 6E 08 07 5B 54 FFFFFF81 FFFFFF80 FFFFFFC0 00
   5C 01 03 78 24 31 10 02 0F 5D 09 02 5E 06 02 03
   41 6E 79 08 08 60 00 FFFFFF84 FFFFFF80 FFFFFF80 FFFFFF84 20 61 01 0D 70
   72 6F 64 75 63 74 50 72 65 66 69 78 15 01 62 10
   02 63 68 0D 01 64 0A 02 65 66 01 04 6C 61 6E 67
   0A 01 67 01 04 6A 61 76 61 09 02 52 64 08 08 6A
   00 FFFFFF84 FFFFFF80 FFFFFF80 FFFFFF84 20 6B 01 0C 70 72 6F 64 75 63 74
   41 72 69 74 79 15 01 47 08 08 6D 00 FFFFFF84 FFFFFF80 FFFFFF80 FFFFFF84
   20 6E 01 0E 70 72 6F 64 75 63 74 45 6C 65 6D 65
   6E 74 14 02 5C 6F 08 07 5B 6C FFFFFF81 FFFFFF80 FFFFFFC0 00 47 08
   08 71 00 FFFFFF84 FFFFFF80 FFFFFF80 FFFFFF84 20 72 01 12 70 72 6F 64 75
   63 74 45 6C 65 6D 65 6E 74 4E 61 6D 65 14 02 62
   73 08 07 5B 70 FFFFFF81 FFFFFF80 FFFFFFC0 00 47 08 08 75 00 FFFFFF84 FFFFFF80
   FFFFFF80 FFFFFF84 20 76 01 08 63 61 6E 45 71 75 61 6C 14 02
   57 77 08 07 5B 74 FFFFFF81 FFFFFF80 FFFFFFC0 00 5C 28 02 00 79 10
   02 0F 7A 09 02 7B 06 02 0C 73 65 72 69 61 6C 69
   7A 61 62 6C 65 07 07 7D 02 FFFFFF81 FFFFFF80 FFFFFF88 02 7E 01 06
   45 78 74 44 65 66 10 02 0B 7F 06 09 01 02 FFFFFF84 FFFFFF81
   FFFFFF80 FFFFFF88 02 FFFFFF81 00 13 06 7F FFFFFF81 01 FFFFFF81 04 0E 10 03 63
   FFFFFF81 02 09 03 FFFFFF81 03 64 02 06 4F 62 6A 65 63 74 10
   05 0F FFFFFF81 05 18 20 09 03 FFFFFF81 06 06 02 09 46 75 6E
   63 74 69 6F 6E 31 08 06 1E 7F FFFFFF84 00 FFFFFF81 08 14 01
   7E 08 09 FFFFFF81 0A 7F FFFFFF81 FFFFFF80 FFFFFF84 40 FFFFFF81 0B 01 05 61 70
   70 6C 79 14 03 20 FFFFFF81 0C 08 06 16 FFFFFF81 09 FFFFFFC0 00 18
   08 09 FFFFFF81 0E 7F FFFFFF81 FFFFFF80 FFFFFF84 40 FFFFFF81 0F 01 07 75 6E 61
   70 70 6C 79 14 04 FFFFFF81 10 FFFFFF81 13 10 04 0F FFFFFF81 11 18
   09 03 FFFFFF81 12 06 02 06 4F 70 74 69 6F 6E 08 07 FFFFFF81
   14 FFFFFF81 0D FFFFFFC0 00 20 01 03 78 24 30 
  minor version: 0
  major version: 49
  Constant pool:
Asciz	SourceFile;
Asciz	Decl.scala;
Asciz	andThen;
Asciz	(Lscala/Function1;)Lscala/Function1;;
Asciz	Code;
Asciz	scala/xml/dtd/ExtDef$;
class	scala/xml/dtd/ExtDef$
Asciz	MODULE$;
Asciz	Lscala/xml/dtd/ExtDef$;;
NameAndType	MODULE$:Lscala/xml/dtd/ExtDef$;
Field	scala/xml/dtd/ExtDef$.MODULE$:Lscala/xml/dtd/ExtDef$;
NameAndType	andThen:(Lscala/Function1;)Lscala/Function1;
Method	scala/xml/dtd/ExtDef$.andThen:(Lscala/Function1;)Lscala/Function1;
Asciz	compose;
NameAndType	compose:(Lscala/Function1;)Lscala/Function1;
Method	scala/xml/dtd/ExtDef$.compose:(Lscala/Function1;)Lscala/Function1;
Asciz	extID;
Asciz	Lscala/xml/dtd/ExternalID;;
Asciz	productIterator;
Asciz	()Lscala/collection/Iterator;;
Asciz	LineNumberTable;
Asciz	scala/Product$class;
class	scala/Product$class
Asciz	(Lscala/Product;)Lscala/collection/Iterator;;
NameAndType	productIterator:(Lscala/Product;)Lscala/collection/Iterator;
Method	scala/Product$class.productIterator:(Lscala/Product;)Lscala/collection/Iterator;
Asciz	productElements;
NameAndType	productElements:(Lscala/Product;)Lscala/collection/Iterator;
Method	scala/Product$class.productElements:(Lscala/Product;)Lscala/collection/Iterator;
Asciz	Deprecated;
Asciz	copy$default$1;
Asciz	()Lscala/xml/dtd/ExternalID;;
Asciz	scala/xml/dtd/ExtDef;
class	scala/xml/dtd/ExtDef
NameAndType	extID:()Lscala/xml/dtd/ExternalID;
Method	scala/xml/dtd/ExtDef.extID:()Lscala/xml/dtd/ExternalID;
NameAndType	extID:Lscala/xml/dtd/ExternalID;
Field	scala/xml/dtd/ExtDef.extID:Lscala/xml/dtd/ExternalID;
Asciz	buildString;
Asciz	(Lscala/collection/mutable/StringBuilder;)Lscala/collection/mutable/StringBuilder;;
Asciz	scala/xml/dtd/ExternalID;
class	scala/xml/dtd/ExternalID
NameAndType	buildString:(Lscala/collection/mutable/StringBuilder;)Lscala/collection/mutable/StringBuilder;
Method	scala/xml/dtd/ExternalID.buildString:(Lscala/collection/mutable/StringBuilder;)Lscala/collection/mutable/StringBuilder;
Asciz	this;
Asciz	Lscala/xml/dtd/ExtDef;;
Asciz	sb;
Asciz	Lscala/collection/mutable/StringBuilder;;
Asciz	LocalVariableTable;
Asciz	copy;
Asciz	(Lscala/xml/dtd/ExternalID;)Lscala/xml/dtd/ExtDef;;
Asciz	<init>;
Asciz	(Lscala/xml/dtd/ExternalID;)V;
NameAndType	"<init>":(Lscala/xml/dtd/ExternalID;)V
Method	scala/xml/dtd/ExtDef."<init>":(Lscala/xml/dtd/ExternalID;)V
Asciz	hashCode;
Asciz	()I;
Asciz	scala/runtime/ScalaRunTime$;
class	scala/runtime/ScalaRunTime$
Asciz	Lscala/runtime/ScalaRunTime$;;
NameAndType	MODULE$:Lscala/runtime/ScalaRunTime$;
Field	scala/runtime/ScalaRunTime$.MODULE$:Lscala/runtime/ScalaRunTime$;
Asciz	_hashCode;
Asciz	(Lscala/Product;)I;
NameAndType	_hashCode:(Lscala/Product;)I
Method	scala/runtime/ScalaRunTime$._hashCode:(Lscala/Product;)I
Asciz	toString;
Asciz	()Ljava/lang/String;;
Asciz	_toString;
Asciz	(Lscala/Product;)Ljava/lang/String;;
NameAndType	_toString:(Lscala/Product;)Ljava/lang/String;
Method	scala/runtime/ScalaRunTime$._toString:(Lscala/Product;)Ljava/lang/String;
Asciz	equals;
Asciz	(Ljava/lang/Object;)Z;
Asciz	gd9$1;
Asciz	(Lscala/xml/dtd/ExternalID;)Z;
NameAndType	gd9$1:(Lscala/xml/dtd/ExternalID;)Z
Method	scala/xml/dtd/ExtDef.gd9$1:(Lscala/xml/dtd/ExternalID;)Z
Asciz	scala/Equals;
class	scala/Equals
Asciz	canEqual;
NameAndType	canEqual:(Ljava/lang/Object;)Z
InterfaceMethod	scala/Equals.canEqual:(Ljava/lang/Object;)Z
Asciz	temp50;
Asciz	Ljava/lang/Object;;
Asciz	temp51;
Asciz	temp52;
Asciz	extID$3;
Asciz	productPrefix;
Asciz	ExtDef;
String	ExtDef
Asciz	productArity;
Asciz	productElement;
Asciz	(I)Ljava/lang/Object;;
Asciz	java/lang/IndexOutOfBoundsException;
class	java/lang/IndexOutOfBoundsException
Asciz	scala/runtime/BoxesRunTime;
class	scala/runtime/BoxesRunTime
Asciz	boxToInteger;
Asciz	(I)Ljava/lang/Integer;;
NameAndType	boxToInteger:(I)Ljava/lang/Integer;
Method	scala/runtime/BoxesRunTime.boxToInteger:(I)Ljava/lang/Integer;
Asciz	java/lang/Object;
class	java/lang/Object
NameAndType	toString:()Ljava/lang/String;
Method	java/lang/Object.toString:()Ljava/lang/String;
Asciz	(Ljava/lang/String;)V;
NameAndType	"<init>":(Ljava/lang/String;)V
Method	java/lang/IndexOutOfBoundsException."<init>":(Ljava/lang/String;)V
Asciz	temp53;
Asciz	I;
Asciz	productElementName;
Asciz	(I)Ljava/lang/String;;
String	extID
Asciz	temp54;
NameAndType	equals:(Ljava/lang/Object;)Z
Method	java/lang/Object.equals:(Ljava/lang/Object;)Z
Asciz	scala/xml/dtd/EntityDef;
class	scala/xml/dtd/EntityDef
Asciz	()V;
NameAndType	"<init>":()V
Method	scala/xml/dtd/EntityDef."<init>":()V
Asciz	$init$;
Asciz	(Lscala/Product;)V;
NameAndType	$init$:(Lscala/Product;)V
Method	scala/Product$class.$init$:(Lscala/Product;)V
Asciz	ScalaSig;
Asciz	scala/ScalaObject;
class	scala/ScalaObject
Asciz	scala/Product;
class	scala/Product
Asciz	java/io/Serializable;
class	java/io/Serializable

{
private final scala.xml.dtd.ExternalID extID;
  Signature: Lscala/xml/dtd/ExternalID;

public static final scala.Function1 andThen(scala.Function1);
  Signature: (Lscala/Function1;)Lscala/Function1;
  Code:
   Stack=2, Locals=1, Args_size=1
	getstatic	Field scala/xml/dtd/ExtDef$.MODULE$:Lscala/xml/dtd/ExtDef$;
	aload_0
	invokevirtual	Method scala/xml/dtd/ExtDef$.andThen:(Lscala/Function1;)Lscala/Function1;
	areturn
  Labels:

public static final scala.Function1 compose(scala.Function1);
  Signature: (Lscala/Function1;)Lscala/Function1;
  Code:
   Stack=2, Locals=1, Args_size=1
	getstatic	Field scala/xml/dtd/ExtDef$.MODULE$:Lscala/xml/dtd/ExtDef$;
	aload_0
	invokevirtual	Method scala/xml/dtd/ExtDef$.compose:(Lscala/Function1;)Lscala/Function1;
	areturn
  Labels:

public scala.collection.Iterator productIterator();
  Signature: ()Lscala/collection/Iterator;
  Code:
   Stack=1, Locals=1, Args_size=1
	aload_0
	invokestatic	Method scala/Product$class.productIterator:(Lscala/Product;)Lscala/collection/Iterator;
	areturn
  Labels:

public scala.collection.Iterator productElements();
  Signature: ()Lscala/collection/Iterator;
  Code:
   Stack=1, Locals=1, Args_size=1
	aload_0
	invokestatic	Method scala/Product$class.productElements:(Lscala/Product;)Lscala/collection/Iterator;
	areturn
  Labels:
  Deprecated: true

public scala.xml.dtd.ExternalID copy$default$1();
  Signature: ()Lscala/xml/dtd/ExternalID;
  Code:
   Stack=1, Locals=1, Args_size=1
	aload_0
	invokevirtual	Method extID:()Lscala/xml/dtd/ExternalID;
	areturn
  Labels:

public scala.xml.dtd.ExternalID extID();
  Signature: ()Lscala/xml/dtd/ExternalID;
  Code:
   Stack=1, Locals=1, Args_size=1
	aload_0
	getfield	Field extID:Lscala/xml/dtd/ExternalID;
	areturn
  Labels:

public scala.collection.mutable.StringBuilder buildString(scala.collection.mutable.StringBuilder);
  Signature: (Lscala/collection/mutable/StringBuilder;)Lscala/collection/mutable/StringBuilder;
  Code:
   Stack=2, Locals=2, Args_size=2
	aload_0
	invokevirtual	Method extID:()Lscala/xml/dtd/ExternalID;
	aload_1
	invokevirtual	Method scala/xml/dtd/ExternalID.buildString:(Lscala/collection/mutable/StringBuilder;)Lscala/collection/mutable/StringBuilder;
	areturn
  Labels:
  LocalVariableTable: 
   Start  Length  Slot  Name   Signature
   0      9      0    this       Lscala/xml/dtd/ExtDef;
   0      9      1    sb       Lscala/collection/mutable/StringBuilder;


public scala.xml.dtd.ExtDef copy(scala.xml.dtd.ExternalID);
  Signature: (Lscala/xml/dtd/ExternalID;)Lscala/xml/dtd/ExtDef;
  Code:
   Stack=3, Locals=2, Args_size=2
	new	class scala/xml/dtd/ExtDef
	dup
	aload_1
	invokespecial	Method "<init>":(Lscala/xml/dtd/ExternalID;)V
	areturn
  Labels:
  LocalVariableTable: 
   Start  Length  Slot  Name   Signature
   0      9      0    this       Lscala/xml/dtd/ExtDef;
   0      9      1    extID       Lscala/xml/dtd/ExternalID;


public int hashCode();
  Signature: ()I
  Code:
   Stack=2, Locals=1, Args_size=1
	getstatic	Field scala/runtime/ScalaRunTime$.MODULE$:Lscala/runtime/ScalaRunTime$;
	aload_0
	invokevirtual	Method scala/runtime/ScalaRunTime$._hashCode:(Lscala/Product;)I
	ireturn
  Labels:

public java.lang.String toString();
  Signature: ()Ljava/lang/String;
  Code:
   Stack=2, Locals=1, Args_size=1
	getstatic	Field scala/runtime/ScalaRunTime$.MODULE$:Lscala/runtime/ScalaRunTime$;
	aload_0
	invokevirtual	Method scala/runtime/ScalaRunTime$._toString:(Lscala/Product;)Ljava/lang/String;
	areturn
  Labels:

public boolean equals(java.lang.Object);
  Signature: (Ljava/lang/Object;)Z
  Code:
   Stack=2, Locals=6, Args_size=2
	aload_0
	aload_1
	if_acmpeq	l1 // iconst_1
	aload_1
	astore_2
	aload_2
	instanceof	class scala/xml/dtd/ExtDef
	ifeq	l2 // iconst_0
	aload_2
	checkcast	class scala/xml/dtd/ExtDef
	astore_3
	aload_3
	invokevirtual	Method extID:()Lscala/xml/dtd/ExternalID;
	astore	4
	aload	4
	astore	5
	aload_0
	aload	5
	invokespecial	Method gd9$1:(Lscala/xml/dtd/ExternalID;)Z
	ifeq	l3 // iconst_0
	aload_1
	checkcast	class scala/xml/dtd/ExtDef
	aload_0
	invokeinterface	InterfaceMethod scala/Equals.canEqual:(Ljava/lang/Object;)Z
	goto	l4 // ifeq
l3	iconst_0
	goto	l4 // ifeq
l2	iconst_0
l4	ifeq	l5 // iconst_0
l1	iconst_1
	goto	l6 // ireturn
l5	iconst_0
l6	ireturn
  Labels:
   	l3 = 51 // iconst_0
   	l2 = 55 // iconst_0
   	l4 = 56 // ifeq
   	l1 = 59 // iconst_1
   	l5 = 63 // iconst_0
   	l6 = 64 // ireturn
  LocalVariableTable: 
   Start  Length  Slot  Name   Signature
   0      65      0    this       Lscala/xml/dtd/ExtDef;
   7      52      2    temp50       Ljava/lang/Object;
   19      36      3    temp51       Lscala/xml/dtd/ExtDef;
   25      30      4    temp52       Lscala/xml/dtd/ExternalID;
   29      26      5    extID$3       Lscala/xml/dtd/ExternalID;


public java.lang.String productPrefix();
  Signature: ()Ljava/lang/String;
  Code:
   Stack=1, Locals=1, Args_size=1
	ldc	String ExtDef
	areturn
  Labels:

public int productArity();
  Signature: ()I
  Code:
   Stack=1, Locals=1, Args_size=1
	iconst_1
	ireturn
  Labels:

public java.lang.Object productElement(int);
  Signature: (I)Ljava/lang/Object;
  Code:
   Stack=3, Locals=3, Args_size=2
	iload_1
	istore_2
	iload_2
	iconst_0
	if_icmpne	l1 // new
	aload_0
	invokevirtual	Method extID:()Lscala/xml/dtd/ExternalID;
	areturn
l1	new	class java/lang/IndexOutOfBoundsException
	dup
	iload_1
	invokestatic	Method scala/runtime/BoxesRunTime.boxToInteger:(I)Ljava/lang/Integer;
	invokevirtual	Method java/lang/Object.toString:()Ljava/lang/String;
	invokespecial	Method java/lang/IndexOutOfBoundsException."<init>":(Ljava/lang/String;)V
	athrow
  Labels:
   	l1 = 12 // new
  LocalVariableTable: 
   Start  Length  Slot  Name   Signature
   0      27      0    this       Lscala/xml/dtd/ExtDef;
   2      25      2    temp53       I


public java.lang.String productElementName(int);
  Signature: (I)Ljava/lang/String;
  Code:
   Stack=3, Locals=3, Args_size=2
	iload_1
	istore_2
	iload_2
	iconst_0
	if_icmpne	l1 // new
	ldc	String extID
	areturn
l1	new	class java/lang/IndexOutOfBoundsException
	dup
	iload_1
	invokestatic	Method scala/runtime/BoxesRunTime.boxToInteger:(I)Ljava/lang/Integer;
	invokevirtual	Method java/lang/Object.toString:()Ljava/lang/String;
	invokespecial	Method java/lang/IndexOutOfBoundsException."<init>":(Ljava/lang/String;)V
	athrow
  Labels:
   	l1 = 10 // new
  LocalVariableTable: 
   Start  Length  Slot  Name   Signature
   0      25      0    this       Lscala/xml/dtd/ExtDef;
   2      23      2    temp54       I


public boolean canEqual(java.lang.Object);
  Signature: (Ljava/lang/Object;)Z
  Code:
   Stack=1, Locals=2, Args_size=2
	aload_1
	instanceof	class scala/xml/dtd/ExtDef
	ireturn
  Labels:

private final boolean gd9$1(scala.xml.dtd.ExternalID);
  Signature: (Lscala/xml/dtd/ExternalID;)Z
  Code:
   Stack=2, Locals=3, Args_size=2
	aload_1
	aload_0
	invokevirtual	Method extID:()Lscala/xml/dtd/ExternalID;
	astore_2
	dup
	ifnonnull	l1 // aload_2
	pop
	aload_2
	ifnull	l2 // iconst_1
	goto	l3 // iconst_0
l1	aload_2
	invokevirtual	Method java/lang/Object.equals:(Ljava/lang/Object;)Z
	ifeq	l3 // iconst_0
l2	iconst_1
	goto	l4 // ireturn
l3	iconst_0
l4	ireturn
  Labels:
   	l1 = 18 // aload_2
   	l2 = 25 // iconst_1
   	l3 = 29 // iconst_0
   	l4 = 30 // ireturn

public scala.xml.dtd.ExtDef(scala.xml.dtd.ExternalID);
  Signature: (Lscala/xml/dtd/ExternalID;)V
  Code:
   Stack=2, Locals=2, Args_size=2
	aload_0
	aload_1
	putfield	Field extID:Lscala/xml/dtd/ExternalID;
	aload_0
	invokespecial	Method scala/xml/dtd/EntityDef."<init>":()V
	aload_0
	invokestatic	Method scala/Product$class.$init$:(Lscala/Product;)V
	return
  Labels:
  LocalVariableTable: 
   Start  Length  Slot  Name   Signature
   0      14      0    this       Lscala/xml/dtd/ExtDef;
   0      14      1    extID       Lscala/xml/dtd/ExternalID;


}

