Compiled from "Decl.scala"
public final class scala.xml.dtd.ExtDef$ extends java.lang.Object implements scala.Function1,scala.ScalaObject
  SourceFile: "Decl.scala"
  Scala: length = 0x
   
  minor version: 0
  major version: 49
  Constant pool:
Asciz	SourceFile;
Asciz	Decl.scala;
Asciz	Scala;
Asciz	MODULE$;
Asciz	Lscala/xml/dtd/ExtDef$;;
Asciz	<clinit>;
Asciz	()V;
Asciz	Code;
Asciz	scala/xml/dtd/ExtDef$;
class	scala/xml/dtd/ExtDef$
Asciz	<init>;
NameAndType	"<init>":()V
Method	scala/xml/dtd/ExtDef$."<init>":()V
Asciz	toString;
Asciz	()Ljava/lang/String;;
Asciz	LineNumberTable;
Asciz	scala/Function1$class;
class	scala/Function1$class
Asciz	(Lscala/Function1;)Ljava/lang/String;;
NameAndType	toString:(Lscala/Function1;)Ljava/lang/String;
Method	scala/Function1$class.toString:(Lscala/Function1;)Ljava/lang/String;
Asciz	compose;
Asciz	(Lscala/Function1;)Lscala/Function1;;
Asciz	(Lscala/Function1;Lscala/Function1;)Lscala/Function1;;
NameAndType	compose:(Lscala/Function1;Lscala/Function1;)Lscala/Function1;
Method	scala/Function1$class.compose:(Lscala/Function1;Lscala/Function1;)Lscala/Function1;
Asciz	this;
Asciz	g;
Asciz	Lscala/Function1;;
Asciz	LocalVariableTable;
Asciz	andThen;
NameAndType	andThen:(Lscala/Function1;Lscala/Function1;)Lscala/Function1;
Method	scala/Function1$class.andThen:(Lscala/Function1;Lscala/Function1;)Lscala/Function1;
Asciz	unapply;
Asciz	(Lscala/xml/dtd/ExtDef;)Lscala/Some;;
Asciz	scala/Some;
class	scala/Some
Asciz	scala/xml/dtd/ExtDef;
class	scala/xml/dtd/ExtDef
Asciz	extID;
Asciz	()Lscala/xml/dtd/ExternalID;;
NameAndType	extID:()Lscala/xml/dtd/ExternalID;
Method	scala/xml/dtd/ExtDef.extID:()Lscala/xml/dtd/ExternalID;
Asciz	(Ljava/lang/Object;)V;
NameAndType	"<init>":(Ljava/lang/Object;)V
Method	scala/Some."<init>":(Ljava/lang/Object;)V
Asciz	x$0;
Asciz	Lscala/xml/dtd/ExtDef;;
Asciz	apply;
Asciz	(Lscala/xml/dtd/ExternalID;)Lscala/xml/dtd/ExtDef;;
Asciz	(Lscala/xml/dtd/ExternalID;)V;
NameAndType	"<init>":(Lscala/xml/dtd/ExternalID;)V
Method	scala/xml/dtd/ExtDef."<init>":(Lscala/xml/dtd/ExternalID;)V
Asciz	Lscala/xml/dtd/ExternalID;;
Asciz	(Ljava/lang/Object;)Ljava/lang/Object;;
Asciz	scala/xml/dtd/ExternalID;
class	scala/xml/dtd/ExternalID
NameAndType	apply:(Lscala/xml/dtd/ExternalID;)Lscala/xml/dtd/ExtDef;
Method	scala/xml/dtd/ExtDef$.apply:(Lscala/xml/dtd/ExternalID;)Lscala/xml/dtd/ExtDef;
Asciz	v1;
Asciz	Ljava/lang/Object;;
Asciz	java/lang/Object;
class	java/lang/Object
Method	java/lang/Object."<init>":()V
NameAndType	MODULE$:Lscala/xml/dtd/ExtDef$;
Field	scala/xml/dtd/ExtDef$.MODULE$:Lscala/xml/dtd/ExtDef$;
Asciz	$init$;
Asciz	(Lscala/Function1;)V;
NameAndType	$init$:(Lscala/Function1;)V
Method	scala/Function1$class.$init$:(Lscala/Function1;)V
Asciz	scala/Function1;
class	scala/Function1
Asciz	scala/ScalaObject;
class	scala/ScalaObject

{
public static final scala.xml.dtd.ExtDef$ MODULE$;
  Signature: Lscala/xml/dtd/ExtDef$;

public static {};
  Signature: ()V
  Code:
   Stack=1, Locals=0, Args_size=0
	new	class scala/xml/dtd/ExtDef$
	invokespecial	Method "<init>":()V
	return
  Labels:

public java.lang.String toString();
  Signature: ()Ljava/lang/String;
  Code:
   Stack=1, Locals=1, Args_size=1
	aload_0
	invokestatic	Method scala/Function1$class.toString:(Lscala/Function1;)Ljava/lang/String;
	areturn
  Labels:

public scala.Function1 compose(scala.Function1);
  Signature: (Lscala/Function1;)Lscala/Function1;
  Code:
   Stack=2, Locals=2, Args_size=2
	aload_0
	aload_1
	invokestatic	Method scala/Function1$class.compose:(Lscala/Function1;Lscala/Function1;)Lscala/Function1;
	areturn
  Labels:
  LocalVariableTable: 
   Start  Length  Slot  Name   Signature
   0      6      0    this       Lscala/xml/dtd/ExtDef$;
   0      6      1    g       Lscala/Function1;


public scala.Function1 andThen(scala.Function1);
  Signature: (Lscala/Function1;)Lscala/Function1;
  Code:
   Stack=2, Locals=2, Args_size=2
	aload_0
	aload_1
	invokestatic	Method scala/Function1$class.andThen:(Lscala/Function1;Lscala/Function1;)Lscala/Function1;
	areturn
  Labels:
  LocalVariableTable: 
   Start  Length  Slot  Name   Signature
   0      6      0    this       Lscala/xml/dtd/ExtDef$;
   0      6      1    g       Lscala/Function1;


public scala.Some unapply(scala.xml.dtd.ExtDef);
  Signature: (Lscala/xml/dtd/ExtDef;)Lscala/Some;
  Code:
   Stack=3, Locals=2, Args_size=2
	new	class scala/Some
	dup
	aload_1
	invokevirtual	Method scala/xml/dtd/ExtDef.extID:()Lscala/xml/dtd/ExternalID;
	invokespecial	Method scala/Some."<init>":(Ljava/lang/Object;)V
	areturn
  Labels:
  LocalVariableTable: 
   Start  Length  Slot  Name   Signature
   0      12      0    this       Lscala/xml/dtd/ExtDef$;
   0      12      1    x$0       Lscala/xml/dtd/ExtDef;


public scala.xml.dtd.ExtDef apply(scala.xml.dtd.ExternalID);
  Signature: (Lscala/xml/dtd/ExternalID;)Lscala/xml/dtd/ExtDef;
  Code:
   Stack=3, Locals=2, Args_size=2
	new	class scala/xml/dtd/ExtDef
	dup
	aload_1
	invokespecial	Method scala/xml/dtd/ExtDef."<init>":(Lscala/xml/dtd/ExternalID;)V
	areturn
  Labels:
  LocalVariableTable: 
   Start  Length  Slot  Name   Signature
   0      9      0    this       Lscala/xml/dtd/ExtDef$;
   0      9      1    extID       Lscala/xml/dtd/ExternalID;


public java.lang.Object apply(java.lang.Object);
  Signature: (Ljava/lang/Object;)Ljava/lang/Object;
  Code:
   Stack=2, Locals=2, Args_size=2
	aload_0
	aload_1
	checkcast	class scala/xml/dtd/ExternalID
	invokevirtual	Method apply:(Lscala/xml/dtd/ExternalID;)Lscala/xml/dtd/ExtDef;
	areturn
  Labels:
  LocalVariableTable: 
   Start  Length  Slot  Name   Signature
   0      9      0    this       Lscala/xml/dtd/ExtDef$;
   0      9      1    v1       Ljava/lang/Object;


private scala.xml.dtd.ExtDef$();
  Signature: ()V
  Code:
   Stack=1, Locals=1, Args_size=1
	aload_0
	invokespecial	Method java/lang/Object."<init>":()V
	aload_0
	putstatic	Field MODULE$:Lscala/xml/dtd/ExtDef$;
	aload_0
	invokestatic	Method scala/Function1$class.$init$:(Lscala/Function1;)V
	return
  Labels:

}

