Compiled from "ExternalID.scala"
public abstract class scala.xml.dtd.ExternalID extends java.lang.Object implements scala.xml.parsing.TokenTests,scala.ScalaObject
  SourceFile: "ExternalID.scala"
  ScalaSig: length = 0x19F
   05 00 48 06 08 01 02 FFFFFF84 FFFFFF80 FFFFFF80 FFFFFF81 00 09 02 0A 45
   78 74 65 72 6E 61 6C 49 44 0A 02 03 04 01 03 64
   74 64 0A 02 05 06 01 03 78 6D 6C 0A 01 07 01 05
   73 63 61 6C 61 03 00 13 04 00 0A 12 18 10 02 0B
   10 0D 01 0C 0A 02 0D 0E 01 04 6C 61 6E 67 0A 01
   0F 01 04 6A 61 76 61 09 02 11 0C 02 06 4F 62 6A
   65 63 74 10 02 13 16 0D 01 14 0A 02 15 04 01 07
   70 61 72 73 69 6E 67 09 02 17 14 02 0A 54 6F 6B
   65 6E 54 65 73 74 73 10 02 19 1A 0D 01 06 09 02
   1B 06 02 0B 53 63 61 6C 61 4F 62 6A 65 63 74 08
   05 1D 00 FFFFFF84 00 1E 01 06 3C 69 6E 69 74 3E 14 01
   1F 10 02 20 00 0D 01 02 08 05 22 00 FFFFFF84 00 23 01
   06 71 75 6F 74 65 64 14 02 24 27 10 02 0B 25 09
   02 26 0C 02 06 53 74 72 69 6E 67 08 05 28 21 FFFFFFC0
   00 29 01 01 73 10 02 2A 2D 0E 02 19 2B 09 02 2C
   06 01 06 50 72 65 64 65 66 09 02 26 2E 0A 02 2C
   06 08 05 30 00 FFFFFF84 20 31 01 08 74 6F 53 74 72 69
   6E 67 14 01 29 08 05 33 00 FFFFFF84 00 34 01 0B 62 75
   69 6C 64 53 74 72 69 6E 67 14 02 35 41 10 02 36
   3E 0E 02 37 3C 0E 02 38 3B 0D 01 39 0A 02 3A 08
   01 06 3C 72 6F 6F 74 3E 09 01 07 09 02 3D 06 01
   07 70 61 63 6B 61 67 65 09 02 3F 40 02 0D 53 74
   72 69 6E 67 42 75 69 6C 64 65 72 0A 02 3D 06 08
   05 42 32 FFFFFFC0 00 35 01 02 73 62 08 05 44 00 FFFFFF86 00
   45 01 08 73 79 73 74 65 6D 49 64 15 01 29 08 05
   47 00 FFFFFF86 00 45 01 08 70 75 62 6C 69 63 49 64 
  minor version: 0
  major version: 49
  Constant pool:
Asciz	SourceFile;
Asciz	ExternalID.scala;
Asciz	isSpace;
Asciz	(C)Z;
Asciz	Code;
Asciz	LineNumberTable;
Asciz	scala/xml/parsing/TokenTests$class;
class	scala/xml/parsing/TokenTests$class
Asciz	(Lscala/xml/parsing/TokenTests;C)Z;
NameAndType	isSpace:(Lscala/xml/parsing/TokenTests;C)Z
Method	scala/xml/parsing/TokenTests$class.isSpace:(Lscala/xml/parsing/TokenTests;C)Z
Asciz	this;
Asciz	Lscala/xml/dtd/ExternalID;;
Asciz	ch;
Asciz	C;
Asciz	LocalVariableTable;
Asciz	(Lscala/collection/Seq;)Z;
Asciz	(Lscala/xml/parsing/TokenTests;Lscala/collection/Seq;)Z;
NameAndType	isSpace:(Lscala/xml/parsing/TokenTests;Lscala/collection/Seq;)Z
Method	scala/xml/parsing/TokenTests$class.isSpace:(Lscala/xml/parsing/TokenTests;Lscala/collection/Seq;)Z
Asciz	cs;
Asciz	Lscala/collection/Seq;;
Asciz	isAlpha;
NameAndType	isAlpha:(Lscala/xml/parsing/TokenTests;C)Z
Method	scala/xml/parsing/TokenTests$class.isAlpha:(Lscala/xml/parsing/TokenTests;C)Z
Asciz	c;
Asciz	isAlphaDigit;
NameAndType	isAlphaDigit:(Lscala/xml/parsing/TokenTests;C)Z
Method	scala/xml/parsing/TokenTests$class.isAlphaDigit:(Lscala/xml/parsing/TokenTests;C)Z
Asciz	isNameChar;
NameAndType	isNameChar:(Lscala/xml/parsing/TokenTests;C)Z
Method	scala/xml/parsing/TokenTests$class.isNameChar:(Lscala/xml/parsing/TokenTests;C)Z
Asciz	isNameStart;
NameAndType	isNameStart:(Lscala/xml/parsing/TokenTests;C)Z
Method	scala/xml/parsing/TokenTests$class.isNameStart:(Lscala/xml/parsing/TokenTests;C)Z
Asciz	isName;
Asciz	(Ljava/lang/String;)Z;
Asciz	(Lscala/xml/parsing/TokenTests;Ljava/lang/String;)Z;
NameAndType	isName:(Lscala/xml/parsing/TokenTests;Ljava/lang/String;)Z
Method	scala/xml/parsing/TokenTests$class.isName:(Lscala/xml/parsing/TokenTests;Ljava/lang/String;)Z
Asciz	s;
Asciz	Ljava/lang/String;;
Asciz	isPubIDChar;
NameAndType	isPubIDChar:(Lscala/xml/parsing/TokenTests;C)Z
Method	scala/xml/parsing/TokenTests$class.isPubIDChar:(Lscala/xml/parsing/TokenTests;C)Z
Asciz	isValidIANAEncoding;
NameAndType	isValidIANAEncoding:(Lscala/xml/parsing/TokenTests;Lscala/collection/Seq;)Z
Method	scala/xml/parsing/TokenTests$class.isValidIANAEncoding:(Lscala/xml/parsing/TokenTests;Lscala/collection/Seq;)Z
Asciz	ianaEncoding;
Asciz	checkSysID;
NameAndType	checkSysID:(Lscala/xml/parsing/TokenTests;Ljava/lang/String;)Z
Method	scala/xml/parsing/TokenTests$class.checkSysID:(Lscala/xml/parsing/TokenTests;Ljava/lang/String;)Z
Asciz	checkPubID;
NameAndType	checkPubID:(Lscala/xml/parsing/TokenTests;Ljava/lang/String;)Z
Method	scala/xml/parsing/TokenTests$class.checkPubID:(Lscala/xml/parsing/TokenTests;Ljava/lang/String;)Z
Asciz	quoted;
Asciz	(Ljava/lang/String;)Ljava/lang/String;;
Asciz	scala/Predef$;
class	scala/Predef$
Asciz	MODULE$;
Asciz	Lscala/Predef$;;
NameAndType	MODULE$:Lscala/Predef$;
Field	scala/Predef$.MODULE$:Lscala/Predef$;
Asciz	augmentString;
Asciz	(Ljava/lang/String;)Lscala/collection/immutable/StringOps;;
NameAndType	augmentString:(Ljava/lang/String;)Lscala/collection/immutable/StringOps;
Method	scala/Predef$.augmentString:(Ljava/lang/String;)Lscala/collection/immutable/StringOps;
int	34;
Asciz	scala/runtime/BoxesRunTime;
class	scala/runtime/BoxesRunTime
Asciz	boxToCharacter;
Asciz	(C)Ljava/lang/Character;;
NameAndType	boxToCharacter:(C)Ljava/lang/Character;
Method	scala/runtime/BoxesRunTime.boxToCharacter:(C)Ljava/lang/Character;
Asciz	scala/collection/SeqLike;
class	scala/collection/SeqLike
Asciz	contains;
Asciz	(Ljava/lang/Object;)Z;
NameAndType	contains:(Ljava/lang/Object;)Z
InterfaceMethod	scala/collection/SeqLike.contains:(Ljava/lang/Object;)Z
int	39;
Asciz	scala/collection/mutable/StringBuilder;
class	scala/collection/mutable/StringBuilder
Asciz	<init>;
Asciz	()V;
NameAndType	"<init>":()V
Method	scala/collection/mutable/StringBuilder."<init>":()V
Asciz	append;
Asciz	(C)Lscala/collection/mutable/StringBuilder;;
NameAndType	append:(C)Lscala/collection/mutable/StringBuilder;
Method	scala/collection/mutable/StringBuilder.append:(C)Lscala/collection/mutable/StringBuilder;
Asciz	(Ljava/lang/Object;)Lscala/collection/mutable/StringBuilder;;
NameAndType	append:(Ljava/lang/Object;)Lscala/collection/mutable/StringBuilder;
Method	scala/collection/mutable/StringBuilder.append:(Ljava/lang/Object;)Lscala/collection/mutable/StringBuilder;
Asciz	toString;
Asciz	()Ljava/lang/String;;
NameAndType	toString:()Ljava/lang/String;
Method	scala/collection/mutable/StringBuilder.toString:()Ljava/lang/String;
Asciz	scala/runtime/IntRef;
class	scala/runtime/IntRef
Asciz	(I)V;
NameAndType	"<init>":(I)V
Method	scala/runtime/IntRef."<init>":(I)V
Asciz	scala/runtime/ObjectRef;
class	scala/runtime/ObjectRef
Asciz	(Ljava/lang/Object;)V;
NameAndType	"<init>":(Ljava/lang/Object;)V
Method	scala/runtime/ObjectRef."<init>":(Ljava/lang/Object;)V
Asciz	scala/xml/dtd/ExternalID;
class	scala/xml/dtd/ExternalID
Asciz	publicId;
NameAndType	publicId:()Ljava/lang/String;
Method	scala/xml/dtd/ExternalID.publicId:()Ljava/lang/String;
Asciz	java/lang/Object;
class	java/lang/Object
Asciz	equals;
NameAndType	equals:(Ljava/lang/Object;)Z
Method	java/lang/Object.equals:(Ljava/lang/Object;)Z
Asciz	SYSTEM ;
String	SYSTEM 
Asciz	quotedSystemLiteral$1;
Asciz	(Lscala/runtime/ObjectRef;Lscala/runtime/IntRef;)Ljava/lang/String;;
NameAndType	quotedSystemLiteral$1:(Lscala/runtime/ObjectRef;Lscala/runtime/IntRef;)Ljava/lang/String;
Method	scala/xml/dtd/ExternalID.quotedSystemLiteral$1:(Lscala/runtime/ObjectRef;Lscala/runtime/IntRef;)Ljava/lang/String;
Asciz	PUBLIC ;
String	PUBLIC 
Asciz	quotedPublicLiteral$1;
NameAndType	quotedPublicLiteral$1:(Lscala/runtime/ObjectRef;Lscala/runtime/IntRef;)Ljava/lang/String;
Method	scala/xml/dtd/ExternalID.quotedPublicLiteral$1:(Lscala/runtime/ObjectRef;Lscala/runtime/IntRef;)Ljava/lang/String;
Asciz	systemId;
NameAndType	systemId:()Ljava/lang/String;
Method	scala/xml/dtd/ExternalID.systemId:()Ljava/lang/String;
Asciz	;
String	
Asciz	 ;
String	 
Asciz	bitmap$0$1;
Asciz	Lscala/runtime/IntRef;;
Asciz	quotedSystemLiteral$lzy$1;
Asciz	Lscala/runtime/ObjectRef;;
Asciz	quotedPublicLiteral$lzy$1;
Asciz	buildString;
Asciz	(Lscala/collection/mutable/StringBuilder;)Lscala/collection/mutable/StringBuilder;;
Method	scala/xml/dtd/ExternalID.toString:()Ljava/lang/String;
Asciz	(Ljava/lang/String;)Lscala/collection/mutable/StringBuilder;;
NameAndType	append:(Ljava/lang/String;)Lscala/collection/mutable/StringBuilder;
Method	scala/collection/mutable/StringBuilder.append:(Ljava/lang/String;)Lscala/collection/mutable/StringBuilder;
Asciz	sb;
Asciz	Lscala/collection/mutable/StringBuilder;;
Asciz	elem;
Asciz	I;
NameAndType	elem:I
Field	scala/runtime/IntRef.elem:I
NameAndType	quoted:(Ljava/lang/String;)Ljava/lang/String;
Method	scala/xml/dtd/ExternalID.quoted:(Ljava/lang/String;)Ljava/lang/String;
Asciz	Ljava/lang/Object;;
NameAndType	elem:Ljava/lang/Object;
Field	scala/runtime/ObjectRef.elem:Ljava/lang/Object;
Asciz	java/lang/String;
class	java/lang/String
Method	java/lang/Object."<init>":()V
Asciz	$init$;
Asciz	(Lscala/xml/parsing/TokenTests;)V;
NameAndType	$init$:(Lscala/xml/parsing/TokenTests;)V
Method	scala/xml/parsing/TokenTests$class.$init$:(Lscala/xml/parsing/TokenTests;)V
Asciz	ScalaSig;
Asciz	scala/xml/parsing/TokenTests;
class	scala/xml/parsing/TokenTests
Asciz	scala/ScalaObject;
class	scala/ScalaObject

{
public final boolean isSpace(char);
  Signature: (C)Z
  Code:
   Stack=2, Locals=2, Args_size=2
	aload_0
	iload_1
	invokestatic	Method scala/xml/parsing/TokenTests$class.isSpace:(Lscala/xml/parsing/TokenTests;C)Z
	ireturn
  Labels:
  LocalVariableTable: 
   Start  Length  Slot  Name   Signature
   0      6      0    this       Lscala/xml/dtd/ExternalID;
   0      6      1    ch       C


public final boolean isSpace(scala.collection.Seq);
  Signature: (Lscala/collection/Seq;)Z
  Code:
   Stack=2, Locals=2, Args_size=2
	aload_0
	aload_1
	invokestatic	Method scala/xml/parsing/TokenTests$class.isSpace:(Lscala/xml/parsing/TokenTests;Lscala/collection/Seq;)Z
	ireturn
  Labels:
  LocalVariableTable: 
   Start  Length  Slot  Name   Signature
   0      6      0    this       Lscala/xml/dtd/ExternalID;
   0      6      1    cs       Lscala/collection/Seq;


public boolean isAlpha(char);
  Signature: (C)Z
  Code:
   Stack=2, Locals=2, Args_size=2
	aload_0
	iload_1
	invokestatic	Method scala/xml/parsing/TokenTests$class.isAlpha:(Lscala/xml/parsing/TokenTests;C)Z
	ireturn
  Labels:
  LocalVariableTable: 
   Start  Length  Slot  Name   Signature
   0      6      0    this       Lscala/xml/dtd/ExternalID;
   0      6      1    c       C


public boolean isAlphaDigit(char);
  Signature: (C)Z
  Code:
   Stack=2, Locals=2, Args_size=2
	aload_0
	iload_1
	invokestatic	Method scala/xml/parsing/TokenTests$class.isAlphaDigit:(Lscala/xml/parsing/TokenTests;C)Z
	ireturn
  Labels:
  LocalVariableTable: 
   Start  Length  Slot  Name   Signature
   0      6      0    this       Lscala/xml/dtd/ExternalID;
   0      6      1    c       C


public boolean isNameChar(char);
  Signature: (C)Z
  Code:
   Stack=2, Locals=2, Args_size=2
	aload_0
	iload_1
	invokestatic	Method scala/xml/parsing/TokenTests$class.isNameChar:(Lscala/xml/parsing/TokenTests;C)Z
	ireturn
  Labels:
  LocalVariableTable: 
   Start  Length  Slot  Name   Signature
   0      6      0    this       Lscala/xml/dtd/ExternalID;
   0      6      1    ch       C


public boolean isNameStart(char);
  Signature: (C)Z
  Code:
   Stack=2, Locals=2, Args_size=2
	aload_0
	iload_1
	invokestatic	Method scala/xml/parsing/TokenTests$class.isNameStart:(Lscala/xml/parsing/TokenTests;C)Z
	ireturn
  Labels:
  LocalVariableTable: 
   Start  Length  Slot  Name   Signature
   0      6      0    this       Lscala/xml/dtd/ExternalID;
   0      6      1    ch       C


public boolean isName(java.lang.String);
  Signature: (Ljava/lang/String;)Z
  Code:
   Stack=2, Locals=2, Args_size=2
	aload_0
	aload_1
	invokestatic	Method scala/xml/parsing/TokenTests$class.isName:(Lscala/xml/parsing/TokenTests;Ljava/lang/String;)Z
	ireturn
  Labels:
  LocalVariableTable: 
   Start  Length  Slot  Name   Signature
   0      6      0    this       Lscala/xml/dtd/ExternalID;
   0      6      1    s       Ljava/lang/String;


public boolean isPubIDChar(char);
  Signature: (C)Z
  Code:
   Stack=2, Locals=2, Args_size=2
	aload_0
	iload_1
	invokestatic	Method scala/xml/parsing/TokenTests$class.isPubIDChar:(Lscala/xml/parsing/TokenTests;C)Z
	ireturn
  Labels:
  LocalVariableTable: 
   Start  Length  Slot  Name   Signature
   0      6      0    this       Lscala/xml/dtd/ExternalID;
   0      6      1    ch       C


public boolean isValidIANAEncoding(scala.collection.Seq);
  Signature: (Lscala/collection/Seq;)Z
  Code:
   Stack=2, Locals=2, Args_size=2
	aload_0
	aload_1
	invokestatic	Method scala/xml/parsing/TokenTests$class.isValidIANAEncoding:(Lscala/xml/parsing/TokenTests;Lscala/collection/Seq;)Z
	ireturn
  Labels:
  LocalVariableTable: 
   Start  Length  Slot  Name   Signature
   0      6      0    this       Lscala/xml/dtd/ExternalID;
   0      6      1    ianaEncoding       Lscala/collection/Seq;


public boolean checkSysID(java.lang.String);
  Signature: (Ljava/lang/String;)Z
  Code:
   Stack=2, Locals=2, Args_size=2
	aload_0
	aload_1
	invokestatic	Method scala/xml/parsing/TokenTests$class.checkSysID:(Lscala/xml/parsing/TokenTests;Ljava/lang/String;)Z
	ireturn
  Labels:
  LocalVariableTable: 
   Start  Length  Slot  Name   Signature
   0      6      0    this       Lscala/xml/dtd/ExternalID;
   0      6      1    s       Ljava/lang/String;


public boolean checkPubID(java.lang.String);
  Signature: (Ljava/lang/String;)Z
  Code:
   Stack=2, Locals=2, Args_size=2
	aload_0
	aload_1
	invokestatic	Method scala/xml/parsing/TokenTests$class.checkPubID:(Lscala/xml/parsing/TokenTests;Ljava/lang/String;)Z
	ireturn
  Labels:
  LocalVariableTable: 
   Start  Length  Slot  Name   Signature
   0      6      0    this       Lscala/xml/dtd/ExternalID;
   0      6      1    s       Ljava/lang/String;


public java.lang.String quoted(java.lang.String);
  Signature: (Ljava/lang/String;)Ljava/lang/String;
  Code:
   Stack=2, Locals=3, Args_size=2
	getstatic	Field scala/Predef$.MODULE$:Lscala/Predef$;
	aload_1
	invokevirtual	Method scala/Predef$.augmentString:(Ljava/lang/String;)Lscala/collection/immutable/StringOps;
	ldc	int 34
	invokestatic	Method scala/runtime/BoxesRunTime.boxToCharacter:(C)Ljava/lang/Character;
	invokeinterface	InterfaceMethod scala/collection/SeqLike.contains:(Ljava/lang/Object;)Z
	ifeq	l1 // ldc
	ldc	int 39
	goto	l2 // istore_2
l1	ldc	int 34
l2	istore_2
	new	class scala/collection/mutable/StringBuilder
	dup
	invokespecial	Method scala/collection/mutable/StringBuilder."<init>":()V
	iload_2
	invokevirtual	Method scala/collection/mutable/StringBuilder.append:(C)Lscala/collection/mutable/StringBuilder;
	aload_1
	invokevirtual	Method scala/collection/mutable/StringBuilder.append:(Ljava/lang/Object;)Lscala/collection/mutable/StringBuilder;
	iload_2
	invokestatic	Method scala/runtime/BoxesRunTime.boxToCharacter:(C)Ljava/lang/Character;
	invokevirtual	Method scala/collection/mutable/StringBuilder.append:(Ljava/lang/Object;)Lscala/collection/mutable/StringBuilder;
	invokevirtual	Method scala/collection/mutable/StringBuilder.toString:()Ljava/lang/String;
	areturn
  Labels:
   	l1 = 25 // ldc
   	l2 = 27 // istore_2
  LocalVariableTable: 
   Start  Length  Slot  Name   Signature
   0      54      0    this       Lscala/xml/dtd/ExternalID;
   0      54      1    s       Ljava/lang/String;
   28      25      2    c       C


public java.lang.String toString();
  Signature: ()Ljava/lang/String;
  Code:
   Stack=5, Locals=6, Args_size=1
	new	class scala/runtime/IntRef
	dup
	iconst_0
	invokespecial	Method scala/runtime/IntRef."<init>":(I)V
	astore_1
	new	class scala/runtime/ObjectRef
	dup
	aconst_null
	invokespecial	Method scala/runtime/ObjectRef."<init>":(Ljava/lang/Object;)V
	astore_2
	new	class scala/runtime/ObjectRef
	dup
	aconst_null
	invokespecial	Method scala/runtime/ObjectRef."<init>":(Ljava/lang/Object;)V
	astore_3
	aload_0
	invokevirtual	Method publicId:()Ljava/lang/String;
	dup
	astore	4
	ifnull	l1 // new
	aload	4
	aconst_null
	invokevirtual	Method java/lang/Object.equals:(Ljava/lang/Object;)Z
	ifeq	l2 // new
l1	new	class scala/collection/mutable/StringBuilder
	dup
	invokespecial	Method scala/collection/mutable/StringBuilder."<init>":()V
	ldc	String SYSTEM 
	invokevirtual	Method scala/collection/mutable/StringBuilder.append:(Ljava/lang/Object;)Lscala/collection/mutable/StringBuilder;
	aload_0
	aload_2
	aload_1
	invokespecial	Method quotedSystemLiteral$1:(Lscala/runtime/ObjectRef;Lscala/runtime/IntRef;)Ljava/lang/String;
	invokevirtual	Method scala/collection/mutable/StringBuilder.append:(Ljava/lang/Object;)Lscala/collection/mutable/StringBuilder;
	invokevirtual	Method scala/collection/mutable/StringBuilder.toString:()Ljava/lang/String;
	goto	l3 // areturn
l2	new	class scala/collection/mutable/StringBuilder
	dup
	invokespecial	Method scala/collection/mutable/StringBuilder."<init>":()V
	ldc	String PUBLIC 
	invokevirtual	Method scala/collection/mutable/StringBuilder.append:(Ljava/lang/Object;)Lscala/collection/mutable/StringBuilder;
	aload_0
	aload_3
	aload_1
	invokespecial	Method quotedPublicLiteral$1:(Lscala/runtime/ObjectRef;Lscala/runtime/IntRef;)Ljava/lang/String;
	invokevirtual	Method scala/collection/mutable/StringBuilder.append:(Ljava/lang/Object;)Lscala/collection/mutable/StringBuilder;
	aload_0
	invokevirtual	Method systemId:()Ljava/lang/String;
	dup
	astore	5
	ifnull	l4 // ldc
	aload	5
	aconst_null
	invokevirtual	Method java/lang/Object.equals:(Ljava/lang/Object;)Z
	ifeq	l5 // new
l4	ldc	String 
	goto	l6 // invokevirtual
l5	new	class scala/collection/mutable/StringBuilder
	dup
	invokespecial	Method scala/collection/mutable/StringBuilder."<init>":()V
	ldc	String  
	invokevirtual	Method scala/collection/mutable/StringBuilder.append:(Ljava/lang/Object;)Lscala/collection/mutable/StringBuilder;
	aload_0
	aload_2
	aload_1
	invokespecial	Method quotedSystemLiteral$1:(Lscala/runtime/ObjectRef;Lscala/runtime/IntRef;)Ljava/lang/String;
	invokevirtual	Method scala/collection/mutable/StringBuilder.append:(Ljava/lang/Object;)Lscala/collection/mutable/StringBuilder;
	invokevirtual	Method scala/collection/mutable/StringBuilder.toString:()Ljava/lang/String;
l6	invokevirtual	Method scala/collection/mutable/StringBuilder.append:(Ljava/lang/Object;)Lscala/collection/mutable/StringBuilder;
	invokevirtual	Method scala/collection/mutable/StringBuilder.toString:()Ljava/lang/String;
l3	areturn
  Labels:
   	l1 = 46 // new
   	l2 = 73 // new
   	l4 = 113 // ldc
   	l5 = 118 // new
   	l6 = 142 // invokevirtual
   	l3 = 148 // areturn
  LocalVariableTable: 
   Start  Length  Slot  Name   Signature
   0      149      0    this       Lscala/xml/dtd/ExternalID;
   9      140      1    bitmap$0$1       Lscala/runtime/IntRef;
   18      131      2    quotedSystemLiteral$lzy$1       Lscala/runtime/ObjectRef;
   27      122      3    quotedPublicLiteral$lzy$1       Lscala/runtime/ObjectRef;


public scala.collection.mutable.StringBuilder buildString(scala.collection.mutable.StringBuilder);
  Signature: (Lscala/collection/mutable/StringBuilder;)Lscala/collection/mutable/StringBuilder;
  Code:
   Stack=2, Locals=2, Args_size=2
	aload_1
	aload_0
	invokevirtual	Method toString:()Ljava/lang/String;
	invokevirtual	Method scala/collection/mutable/StringBuilder.append:(Ljava/lang/String;)Lscala/collection/mutable/StringBuilder;
	areturn
  Labels:
  LocalVariableTable: 
   Start  Length  Slot  Name   Signature
   0      9      0    this       Lscala/xml/dtd/ExternalID;
   0      9      1    sb       Lscala/collection/mutable/StringBuilder;


public abstract java.lang.String systemId();
  Signature: ()Ljava/lang/String;

public abstract java.lang.String publicId();
  Signature: ()Ljava/lang/String;

private final java.lang.String quotedSystemLiteral$1(scala.runtime.ObjectRef, scala.runtime.IntRef);
  Signature: (Lscala/runtime/ObjectRef;Lscala/runtime/IntRef;)Ljava/lang/String;
  Code:
   Stack=3, Locals=3, Args_size=3
	aload_2
	getfield	Field scala/runtime/IntRef.elem:I
	iconst_1
	iand
	iconst_0
	if_icmpne	l1 // aload_1
	aload_1
	aload_0
	aload_0
	invokevirtual	Method systemId:()Ljava/lang/String;
	invokevirtual	Method quoted:(Ljava/lang/String;)Ljava/lang/String;
	putfield	Field scala/runtime/ObjectRef.elem:Ljava/lang/Object;
	aload_2
	aload_2
	getfield	Field scala/runtime/IntRef.elem:I
	iconst_1
	ior
	putfield	Field scala/runtime/IntRef.elem:I
l1	aload_1
	getfield	Field scala/runtime/ObjectRef.elem:Ljava/lang/Object;
	checkcast	class java/lang/String
	areturn
  Labels:
   	l1 = 32 // aload_1

private final java.lang.String quotedPublicLiteral$1(scala.runtime.ObjectRef, scala.runtime.IntRef);
  Signature: (Lscala/runtime/ObjectRef;Lscala/runtime/IntRef;)Ljava/lang/String;
  Code:
   Stack=3, Locals=3, Args_size=3
	aload_2
	getfield	Field scala/runtime/IntRef.elem:I
	iconst_2
	iand
	iconst_0
	if_icmpne	l1 // aload_1
	aload_1
	aload_0
	aload_0
	invokevirtual	Method publicId:()Ljava/lang/String;
	invokevirtual	Method quoted:(Ljava/lang/String;)Ljava/lang/String;
	putfield	Field scala/runtime/ObjectRef.elem:Ljava/lang/Object;
	aload_2
	aload_2
	getfield	Field scala/runtime/IntRef.elem:I
	iconst_2
	ior
	putfield	Field scala/runtime/IntRef.elem:I
l1	aload_1
	getfield	Field scala/runtime/ObjectRef.elem:Ljava/lang/Object;
	checkcast	class java/lang/String
	areturn
  Labels:
   	l1 = 32 // aload_1

public scala.xml.dtd.ExternalID();
  Signature: ()V
  Code:
   Stack=1, Locals=1, Args_size=1
	aload_0
	invokespecial	Method java/lang/Object."<init>":()V
	aload_0
	invokestatic	Method scala/xml/parsing/TokenTests$class.$init$:(Lscala/xml/parsing/TokenTests;)V
	return
  Labels:

}

