Compiled from "Decl.scala"
public final class scala.xml.dtd.IMPLIED extends java.lang.Object
  SourceFile: "Decl.scala"
  ScalaSig: length = 0x3
   05 00 00 
  RuntimeVisibleAnnotations: length = 0xB
   00 01 00 2B 00 01 00 2C 73 00 2D 
  minor version: 0
  major version: 49
  Constant pool:
Asciz	SourceFile;
Asciz	Decl.scala;
Asciz	productElements;
Asciz	()Lscala/collection/Iterator;;
Asciz	Code;
Asciz	scala/xml/dtd/IMPLIED$;
class	scala/xml/dtd/IMPLIED$
Asciz	MODULE$;
Asciz	Lscala/xml/dtd/IMPLIED$;;
NameAndType	MODULE$:Lscala/xml/dtd/IMPLIED$;
Field	scala/xml/dtd/IMPLIED$.MODULE$:Lscala/xml/dtd/IMPLIED$;
NameAndType	productElements:()Lscala/collection/Iterator;
Method	scala/xml/dtd/IMPLIED$.productElements:()Lscala/collection/Iterator;
Asciz	Deprecated;
Asciz	productIterator;
NameAndType	productIterator:()Lscala/collection/Iterator;
Method	scala/xml/dtd/IMPLIED$.productIterator:()Lscala/collection/Iterator;
Asciz	productElementName;
Asciz	(I)Ljava/lang/String;;
NameAndType	productElementName:(I)Ljava/lang/String;
Method	scala/xml/dtd/IMPLIED$.productElementName:(I)Ljava/lang/String;
Asciz	canEqual;
Asciz	(Ljava/lang/Object;)Z;
NameAndType	canEqual:(Ljava/lang/Object;)Z
Method	scala/xml/dtd/IMPLIED$.canEqual:(Ljava/lang/Object;)Z
Asciz	productElement;
Asciz	(I)Ljava/lang/Object;;
NameAndType	productElement:(I)Ljava/lang/Object;
Method	scala/xml/dtd/IMPLIED$.productElement:(I)Ljava/lang/Object;
Asciz	productArity;
Asciz	()I;
NameAndType	productArity:()I
Method	scala/xml/dtd/IMPLIED$.productArity:()I
Asciz	productPrefix;
Asciz	()Ljava/lang/String;;
NameAndType	productPrefix:()Ljava/lang/String;
Method	scala/xml/dtd/IMPLIED$.productPrefix:()Ljava/lang/String;
Asciz	buildString;
Asciz	(Lscala/collection/mutable/StringBuilder;)Lscala/collection/mutable/StringBuilder;;
NameAndType	buildString:(Lscala/collection/mutable/StringBuilder;)Lscala/collection/mutable/StringBuilder;
Method	scala/xml/dtd/IMPLIED$.buildString:(Lscala/collection/mutable/StringBuilder;)Lscala/collection/mutable/StringBuilder;
Asciz	ScalaSig;
Asciz	Lscala/reflect/ScalaSignature;;
Asciz	bytes;
Asciz	<Q!\t&\tq!S'Q&+EI\tA\r31a=nY*\tq!AtGdm)YQ\"1A!A\t6q!S'Q&+EiE)C\t\"AAEKW;EKdC\n1B-6-7b\nTWm;I1BA&o3vGRDQ!Gi\taP5oSRtD#A\tqYAIQ|7:j]$A\t?\tr!A\n2A)sK,g-$I\t11:j]T!!\t\tZAI\t,3TiJLgnQA\"!)R!a5,H/2mK*QFBG>dG.Z2uS>tBA+5FO]5oO\n+3fe\")'\nae1O\tgmr!NUBT\"]BAs_>$h(C\tQd!AqC\mZ3\n=b$B!q4\"A\nz!9s_,8\r)sKL0FA!\t\te)DC\tE)mC:<'\"A#\t)g/YG\tCS%\t%S\raJ|G-^2uJLG/_B!cS1!8u!q5\"A\nzA9s_,8\r^#mK6,g!N\"AE)\nI3!aA!os\"9A+TAQa=%c!AakCs+dC:,/^1m)\tA63&!L>|G.Z1o!V+!AAAC\"X%\tBXeGMU3t_24X\rF`!\t\t-b\n1qJ6fGRD#aC2I!BA31XM]5bY&TM7f;
Asciz	RuntimeVisibleAnnotations;
Asciz	scala/xml/dtd/IMPLIED;
class	scala/xml/dtd/IMPLIED
Asciz	java/lang/Object;
class	java/lang/Object

{
public static final scala.collection.Iterator productElements();
  Signature: ()Lscala/collection/Iterator;
  Code:
   Stack=1, Locals=0, Args_size=0
	getstatic	Field scala/xml/dtd/IMPLIED$.MODULE$:Lscala/xml/dtd/IMPLIED$;
	invokevirtual	Method scala/xml/dtd/IMPLIED$.productElements:()Lscala/collection/Iterator;
	areturn
  Labels:
  Deprecated: true

public static final scala.collection.Iterator productIterator();
  Signature: ()Lscala/collection/Iterator;
  Code:
   Stack=1, Locals=0, Args_size=0
	getstatic	Field scala/xml/dtd/IMPLIED$.MODULE$:Lscala/xml/dtd/IMPLIED$;
	invokevirtual	Method scala/xml/dtd/IMPLIED$.productIterator:()Lscala/collection/Iterator;
	areturn
  Labels:

public static final java.lang.String productElementName(int);
  Signature: (I)Ljava/lang/String;
  Code:
   Stack=2, Locals=1, Args_size=1
	getstatic	Field scala/xml/dtd/IMPLIED$.MODULE$:Lscala/xml/dtd/IMPLIED$;
	iload_0
	invokevirtual	Method scala/xml/dtd/IMPLIED$.productElementName:(I)Ljava/lang/String;
	areturn
  Labels:

public static final boolean canEqual(java.lang.Object);
  Signature: (Ljava/lang/Object;)Z
  Code:
   Stack=2, Locals=1, Args_size=1
	getstatic	Field scala/xml/dtd/IMPLIED$.MODULE$:Lscala/xml/dtd/IMPLIED$;
	aload_0
	invokevirtual	Method scala/xml/dtd/IMPLIED$.canEqual:(Ljava/lang/Object;)Z
	ireturn
  Labels:

public static final java.lang.Object productElement(int);
  Signature: (I)Ljava/lang/Object;
  Code:
   Stack=2, Locals=1, Args_size=1
	getstatic	Field scala/xml/dtd/IMPLIED$.MODULE$:Lscala/xml/dtd/IMPLIED$;
	iload_0
	invokevirtual	Method scala/xml/dtd/IMPLIED$.productElement:(I)Ljava/lang/Object;
	areturn
  Labels:

public static final int productArity();
  Signature: ()I
  Code:
   Stack=1, Locals=0, Args_size=0
	getstatic	Field scala/xml/dtd/IMPLIED$.MODULE$:Lscala/xml/dtd/IMPLIED$;
	invokevirtual	Method scala/xml/dtd/IMPLIED$.productArity:()I
	ireturn
  Labels:

public static final java.lang.String productPrefix();
  Signature: ()Ljava/lang/String;
  Code:
   Stack=1, Locals=0, Args_size=0
	getstatic	Field scala/xml/dtd/IMPLIED$.MODULE$:Lscala/xml/dtd/IMPLIED$;
	invokevirtual	Method scala/xml/dtd/IMPLIED$.productPrefix:()Ljava/lang/String;
	areturn
  Labels:

public static final scala.collection.mutable.StringBuilder buildString(scala.collection.mutable.StringBuilder);
  Signature: (Lscala/collection/mutable/StringBuilder;)Lscala/collection/mutable/StringBuilder;
  Code:
   Stack=2, Locals=1, Args_size=1
	getstatic	Field scala/xml/dtd/IMPLIED$.MODULE$:Lscala/xml/dtd/IMPLIED$;
	aload_0
	invokevirtual	Method scala/xml/dtd/IMPLIED$.buildString:(Lscala/collection/mutable/StringBuilder;)Lscala/collection/mutable/StringBuilder;
	areturn
  Labels:

}

