Compiled from "ValidationException.scala"
public final class scala.xml.dtd.MakeValidationException extends java.lang.Object
  SourceFile: "ValidationException.scala"
  ScalaSig: length = 0x224
   05 00 4A 07 05 01 02 FFFFFF88 02 09 01 17 4D 61 6B 65
   56 61 6C 69 64 61 74 69 6F 6E 45 78 63 65 70 74
   69 6F 6E 0A 02 03 04 01 03 64 74 64 0A 02 05 06
   01 03 78 6D 6C 0A 01 07 01 05 73 63 61 6C 61 03
   00 10 02 0A 0B 0D 01 02 06 08 0C 02 FFFFFF84 FFFFFF80 FFFFFF80 FFFFFF88
   02 0D 02 17 4D 61 6B 65 56 61 6C 69 64 61 74 69
   6F 6E 45 78 63 65 70 74 69 6F 6E 13 03 0B 0E 16
   10 02 0F 14 0D 01 10 0A 02 11 12 01 04 6C 61 6E
   67 0A 01 13 01 04 6A 61 76 61 09 02 15 10 02 06
   4F 62 6A 65 63 74 10 02 17 18 0D 01 06 09 02 19
   06 02 0B 53 63 61 6C 61 4F 62 6A 65 63 74 08 05
   1B 0B FFFFFF84 00 1C 01 06 3C 69 6E 69 74 3E 14 01 09
   08 05 1E 0B FFFFFF84 00 1F 01 12 66 72 6F 6D 46 69 78
   65 64 41 74 74 72 69 62 75 74 65 14 04 20 23 2C
   2E 10 02 0A 21 09 02 22 02 02 13 56 61 6C 69 64
   61 74 69 6F 6E 45 78 63 65 70 74 69 6F 6E 08 05
   24 1D FFFFFFC0 00 25 01 01 6B 10 02 26 29 0E 02 17 27
   09 02 28 06 01 06 50 72 65 64 65 66 09 02 2A 2B
   02 06 53 74 72 69 6E 67 0A 02 28 06 08 05 2D 1D
   FFFFFFC0 00 25 01 05 76 61 6C 75 65 08 05 2F 1D FFFFFFC0 00
   25 01 06 61 63 74 75 61 6C 08 05 31 0B FFFFFF84 00 32
   01 13 66 72 6F 6D 4E 6F 6E 45 6D 70 74 79 45 6C
   65 6D 65 6E 74 14 01 20 08 05 34 0B FFFFFF84 00 35 01
   14 66 72 6F 6D 55 6E 64 65 66 69 6E 65 64 45 6C
   65 6D 65 6E 74 14 02 20 36 08 05 37 33 FFFFFFC0 00 25
   01 05 6C 61 62 65 6C 08 05 39 0B FFFFFF84 00 3A 01 16
   66 72 6F 6D 55 6E 64 65 66 69 6E 65 64 41 74 74
   72 69 62 75 74 65 14 02 20 3B 08 05 3C 38 FFFFFFC0 00
   25 01 03 6B 65 79 08 05 3E 0B FFFFFF84 00 3F 01 14 66
   72 6F 6D 4D 69 73 73 69 6E 67 41 74 74 72 69 62
   75 74 65 14 02 20 40 08 05 41 3D FFFFFFC0 00 42 01 07
   61 6C 6C 4B 65 79 73 10 03 26 43 25 09 02 44 2B
   02 03 53 65 74 08 05 3E 0B FFFFFF84 00 46 14 03 20 47
   48 08 05 3C 45 FFFFFFC0 00 25 08 05 49 45 FFFFFFC0 00 25 01
   03 74 70 65 
  InnerClass: 
   public final $anonfun$fromMissingAttribute$1=class scala/xml/dtd/MakeValidationException$$anonfun$fromMissingAttribute$1 of class scala/xml/dtd/MakeValidationException
  minor version: 0
  major version: 49
  Constant pool:
Asciz	SourceFile;
Asciz	ValidationException.scala;
Asciz	fromMissingAttribute;
Asciz	(Ljava/lang/String;Ljava/lang/String;)Lscala/xml/dtd/ValidationException;;
Asciz	Code;
Asciz	scala/xml/dtd/MakeValidationException$;
class	scala/xml/dtd/MakeValidationException$
Asciz	MODULE$;
Asciz	Lscala/xml/dtd/MakeValidationException$;;
NameAndType	MODULE$:Lscala/xml/dtd/MakeValidationException$;
Field	scala/xml/dtd/MakeValidationException$.MODULE$:Lscala/xml/dtd/MakeValidationException$;
NameAndType	fromMissingAttribute:(Ljava/lang/String;Ljava/lang/String;)Lscala/xml/dtd/ValidationException;
Method	scala/xml/dtd/MakeValidationException$.fromMissingAttribute:(Ljava/lang/String;Ljava/lang/String;)Lscala/xml/dtd/ValidationException;
Asciz	(Lscala/collection/immutable/Set;)Lscala/xml/dtd/ValidationException;;
NameAndType	fromMissingAttribute:(Lscala/collection/immutable/Set;)Lscala/xml/dtd/ValidationException;
Method	scala/xml/dtd/MakeValidationException$.fromMissingAttribute:(Lscala/collection/immutable/Set;)Lscala/xml/dtd/ValidationException;
Asciz	(Lscala/collection/immutable/Set<Ljava/lang/String;>;)Lscala/xml/dtd/ValidationException;;
Asciz	Signature;
Asciz	fromUndefinedAttribute;
Asciz	(Ljava/lang/String;)Lscala/xml/dtd/ValidationException;;
NameAndType	fromUndefinedAttribute:(Ljava/lang/String;)Lscala/xml/dtd/ValidationException;
Method	scala/xml/dtd/MakeValidationException$.fromUndefinedAttribute:(Ljava/lang/String;)Lscala/xml/dtd/ValidationException;
Asciz	fromUndefinedElement;
NameAndType	fromUndefinedElement:(Ljava/lang/String;)Lscala/xml/dtd/ValidationException;
Method	scala/xml/dtd/MakeValidationException$.fromUndefinedElement:(Ljava/lang/String;)Lscala/xml/dtd/ValidationException;
Asciz	fromNonEmptyElement;
Asciz	()Lscala/xml/dtd/ValidationException;;
NameAndType	fromNonEmptyElement:()Lscala/xml/dtd/ValidationException;
Method	scala/xml/dtd/MakeValidationException$.fromNonEmptyElement:()Lscala/xml/dtd/ValidationException;
Asciz	fromFixedAttribute;
Asciz	(Ljava/lang/String;Ljava/lang/String;Ljava/lang/String;)Lscala/xml/dtd/ValidationException;;
NameAndType	fromFixedAttribute:(Ljava/lang/String;Ljava/lang/String;Ljava/lang/String;)Lscala/xml/dtd/ValidationException;
Method	scala/xml/dtd/MakeValidationException$.fromFixedAttribute:(Ljava/lang/String;Ljava/lang/String;Ljava/lang/String;)Lscala/xml/dtd/ValidationException;
Asciz	ScalaSig;
Asciz	InnerClasses;
Asciz	scala/xml/dtd/MakeValidationException$$anonfun$fromMissingAttribute$1;
class	scala/xml/dtd/MakeValidationException$$anonfun$fromMissingAttribute$1
Asciz	scala/xml/dtd/MakeValidationException;
class	scala/xml/dtd/MakeValidationException
Asciz	$anonfun$fromMissingAttribute$1;
Asciz	java/lang/Object;
class	java/lang/Object

{
public static final scala.xml.dtd.ValidationException fromMissingAttribute(java.lang.String, java.lang.String);
  Signature: (Ljava/lang/String;Ljava/lang/String;)Lscala/xml/dtd/ValidationException;
  Code:
   Stack=3, Locals=2, Args_size=2
	getstatic	Field scala/xml/dtd/MakeValidationException$.MODULE$:Lscala/xml/dtd/MakeValidationException$;
	aload_0
	aload_1
	invokevirtual	Method scala/xml/dtd/MakeValidationException$.fromMissingAttribute:(Ljava/lang/String;Ljava/lang/String;)Lscala/xml/dtd/ValidationException;
	areturn
  Labels:

public static final scala.xml.dtd.ValidationException fromMissingAttribute(scala.collection.immutable.Set);
  Signature: (Lscala/collection/immutable/Set;)Lscala/xml/dtd/ValidationException;
  Code:
   Stack=2, Locals=1, Args_size=1
	getstatic	Field scala/xml/dtd/MakeValidationException$.MODULE$:Lscala/xml/dtd/MakeValidationException$;
	aload_0
	invokevirtual	Method scala/xml/dtd/MakeValidationException$.fromMissingAttribute:(Lscala/collection/immutable/Set;)Lscala/xml/dtd/ValidationException;
	areturn
  Labels:
  Signature: length = 0x2
   00 11 

public static final scala.xml.dtd.ValidationException fromUndefinedAttribute(java.lang.String);
  Signature: (Ljava/lang/String;)Lscala/xml/dtd/ValidationException;
  Code:
   Stack=2, Locals=1, Args_size=1
	getstatic	Field scala/xml/dtd/MakeValidationException$.MODULE$:Lscala/xml/dtd/MakeValidationException$;
	aload_0
	invokevirtual	Method scala/xml/dtd/MakeValidationException$.fromUndefinedAttribute:(Ljava/lang/String;)Lscala/xml/dtd/ValidationException;
	areturn
  Labels:

public static final scala.xml.dtd.ValidationException fromUndefinedElement(java.lang.String);
  Signature: (Ljava/lang/String;)Lscala/xml/dtd/ValidationException;
  Code:
   Stack=2, Locals=1, Args_size=1
	getstatic	Field scala/xml/dtd/MakeValidationException$.MODULE$:Lscala/xml/dtd/MakeValidationException$;
	aload_0
	invokevirtual	Method scala/xml/dtd/MakeValidationException$.fromUndefinedElement:(Ljava/lang/String;)Lscala/xml/dtd/ValidationException;
	areturn
  Labels:

public static final scala.xml.dtd.ValidationException fromNonEmptyElement();
  Signature: ()Lscala/xml/dtd/ValidationException;
  Code:
   Stack=1, Locals=0, Args_size=0
	getstatic	Field scala/xml/dtd/MakeValidationException$.MODULE$:Lscala/xml/dtd/MakeValidationException$;
	invokevirtual	Method scala/xml/dtd/MakeValidationException$.fromNonEmptyElement:()Lscala/xml/dtd/ValidationException;
	areturn
  Labels:

public static final scala.xml.dtd.ValidationException fromFixedAttribute(java.lang.String, java.lang.String, java.lang.String);
  Signature: (Ljava/lang/String;Ljava/lang/String;Ljava/lang/String;)Lscala/xml/dtd/ValidationException;
  Code:
   Stack=4, Locals=3, Args_size=3
	getstatic	Field scala/xml/dtd/MakeValidationException$.MODULE$:Lscala/xml/dtd/MakeValidationException$;
	aload_0
	aload_1
	aload_2
	invokevirtual	Method scala/xml/dtd/MakeValidationException$.fromFixedAttribute:(Ljava/lang/String;Ljava/lang/String;Ljava/lang/String;)Lscala/xml/dtd/ValidationException;
	areturn
  Labels:

}

