Compiled from "ValidationException.scala"
public final class scala.xml.dtd.MakeValidationException$ extends java.lang.Object implements scala.ScalaObject
  SourceFile: "ValidationException.scala"
  Scala: length = 0x
   
  InnerClass: 
   public final $anonfun$fromMissingAttribute$1=class scala/xml/dtd/MakeValidationException$$anonfun$fromMissingAttribute$1 of class scala/xml/dtd/MakeValidationException
  minor version: 0
  major version: 49
  Constant pool:
Asciz	SourceFile;
Asciz	ValidationException.scala;
Asciz	Scala;
Asciz	MODULE$;
Asciz	Lscala/xml/dtd/MakeValidationException$;;
Asciz	<clinit>;
Asciz	()V;
Asciz	Code;
Asciz	scala/xml/dtd/MakeValidationException$;
class	scala/xml/dtd/MakeValidationException$
Asciz	<init>;
NameAndType	"<init>":()V
Method	scala/xml/dtd/MakeValidationException$."<init>":()V
Asciz	LineNumberTable;
Asciz	java/lang/Object;
class	java/lang/Object
Method	java/lang/Object."<init>":()V
NameAndType	MODULE$:Lscala/xml/dtd/MakeValidationException$;
Field	scala/xml/dtd/MakeValidationException$.MODULE$:Lscala/xml/dtd/MakeValidationException$;
Asciz	fromMissingAttribute;
Asciz	(Ljava/lang/String;Ljava/lang/String;)Lscala/xml/dtd/ValidationException;;
Asciz	scala/xml/dtd/ValidationException;
class	scala/xml/dtd/ValidationException
Asciz	scala/Predef$;
class	scala/Predef$
Asciz	Lscala/Predef$;;
NameAndType	MODULE$:Lscala/Predef$;
Field	scala/Predef$.MODULE$:Lscala/Predef$;
Asciz	missing value for REQUIRED attribute %s of type %s;
String	missing value for REQUIRED attribute %s of type %s
Asciz	augmentString;
Asciz	(Ljava/lang/String;)Lscala/collection/immutable/StringOps;;
NameAndType	augmentString:(Ljava/lang/String;)Lscala/collection/immutable/StringOps;
Method	scala/Predef$.augmentString:(Ljava/lang/String;)Lscala/collection/immutable/StringOps;
Asciz	genericWrapArray;
Asciz	(Ljava/lang/Object;)Lscala/collection/mutable/WrappedArray;;
NameAndType	genericWrapArray:(Ljava/lang/Object;)Lscala/collection/mutable/WrappedArray;
Method	scala/Predef$.genericWrapArray:(Ljava/lang/Object;)Lscala/collection/mutable/WrappedArray;
Asciz	scala/collection/immutable/StringLike;
class	scala/collection/immutable/StringLike
Asciz	format;
Asciz	(Lscala/collection/Seq;)Ljava/lang/String;;
NameAndType	format:(Lscala/collection/Seq;)Ljava/lang/String;
InterfaceMethod	scala/collection/immutable/StringLike.format:(Lscala/collection/Seq;)Ljava/lang/String;
Asciz	(Ljava/lang/String;)V;
NameAndType	"<init>":(Ljava/lang/String;)V
Method	scala/xml/dtd/ValidationException."<init>":(Ljava/lang/String;)V
Asciz	this;
Asciz	key;
Asciz	Ljava/lang/String;;
Asciz	tpe;
Asciz	LocalVariableTable;
Asciz	(Lscala/collection/immutable/Set;)Lscala/xml/dtd/ValidationException;;
Asciz	scala/collection/mutable/StringBuilder;
class	scala/collection/mutable/StringBuilder
Asciz	missing value for REQUIRED attribute;
String	missing value for REQUIRED attribute
Method	scala/collection/mutable/StringBuilder."<init>":(Ljava/lang/String;)V
Asciz	scala/collection/TraversableLike;
class	scala/collection/TraversableLike
Asciz	size;
Asciz	()I;
NameAndType	size:()I
InterfaceMethod	scala/collection/TraversableLike.size:()I
int	115;
Asciz	append;
Asciz	(C)Lscala/collection/mutable/StringBuilder;;
NameAndType	append:(C)Lscala/collection/mutable/StringBuilder;
Method	scala/collection/mutable/StringBuilder.append:(C)Lscala/collection/mutable/StringBuilder;
Asciz	scala/runtime/BoxedUnit;
class	scala/runtime/BoxedUnit
Asciz	UNIT;
Asciz	Lscala/runtime/BoxedUnit;;
NameAndType	UNIT:Lscala/runtime/BoxedUnit;
Field	scala/runtime/BoxedUnit.UNIT:Lscala/runtime/BoxedUnit;
Asciz	scala/xml/dtd/MakeValidationException$$anonfun$fromMissingAttribute$1;
class	scala/xml/dtd/MakeValidationException$$anonfun$fromMissingAttribute$1
Asciz	(Lscala/collection/mutable/StringBuilder;)V;
NameAndType	"<init>":(Lscala/collection/mutable/StringBuilder;)V
Method	scala/xml/dtd/MakeValidationException$$anonfun$fromMissingAttribute$1."<init>":(Lscala/collection/mutable/StringBuilder;)V
Asciz	scala/collection/IterableLike;
class	scala/collection/IterableLike
Asciz	foreach;
Asciz	(Lscala/Function1;)V;
NameAndType	foreach:(Lscala/Function1;)V
InterfaceMethod	scala/collection/IterableLike.foreach:(Lscala/Function1;)V
Asciz	toString;
Asciz	()Ljava/lang/String;;
NameAndType	toString:()Ljava/lang/String;
Method	scala/collection/mutable/StringBuilder.toString:()Ljava/lang/String;
Asciz	allKeys;
Asciz	Lscala/collection/immutable/Set;;
Asciz	sb$1;
Asciz	Lscala/collection/mutable/StringBuilder;;
Asciz	(Lscala/collection/immutable/Set<Ljava/lang/String;>;)Lscala/xml/dtd/ValidationException;;
Asciz	Signature;
Asciz	fromUndefinedAttribute;
Asciz	(Ljava/lang/String;)Lscala/xml/dtd/ValidationException;;
Method	scala/collection/mutable/StringBuilder."<init>":()V
Asciz	attribute ;
String	attribute 
Asciz	(Ljava/lang/Object;)Lscala/collection/mutable/StringBuilder;;
NameAndType	append:(Ljava/lang/Object;)Lscala/collection/mutable/StringBuilder;
Method	scala/collection/mutable/StringBuilder.append:(Ljava/lang/Object;)Lscala/collection/mutable/StringBuilder;
Asciz	 not allowed here;
String	 not allowed here
Method	scala/collection/mutable/StringBuilder.toString:()Ljava/lang/String;
Asciz	fromUndefinedElement;
Asciz	element \";
String	element \"
Asciz	\" not allowed here;
String	\" not allowed here
Asciz	label;
Asciz	fromNonEmptyElement;
Asciz	()Lscala/xml/dtd/ValidationException;;
Asciz	element should be *empty*;
String	element should be *empty*
Asciz	fromFixedAttribute;
Asciz	(Ljava/lang/String;Ljava/lang/String;Ljava/lang/String;)Lscala/xml/dtd/ValidationException;;
Asciz	value of attribute ;
String	value of attribute 
Asciz	 FIXED to \";
String	 FIXED to \"
Asciz	\", but document tries \";
String	\", but document tries \"
Asciz	\";
String	\"
Asciz	k;
Asciz	value;
Asciz	actual;
Asciz	InnerClasses;
Asciz	scala/xml/dtd/MakeValidationException;
class	scala/xml/dtd/MakeValidationException
Asciz	$anonfun$fromMissingAttribute$1;
Asciz	scala/ScalaObject;
class	scala/ScalaObject

{
public static final scala.xml.dtd.MakeValidationException$ MODULE$;
  Signature: Lscala/xml/dtd/MakeValidationException$;

public static {};
  Signature: ()V
  Code:
   Stack=1, Locals=0, Args_size=0
	new	class scala/xml/dtd/MakeValidationException$
	invokespecial	Method "<init>":()V
	return
  Labels:

private scala.xml.dtd.MakeValidationException$();
  Signature: ()V
  Code:
   Stack=1, Locals=1, Args_size=1
	aload_0
	invokespecial	Method java/lang/Object."<init>":()V
	aload_0
	putstatic	Field MODULE$:Lscala/xml/dtd/MakeValidationException$;
	return
  Labels:

public scala.xml.dtd.ValidationException fromMissingAttribute(java.lang.String, java.lang.String);
  Signature: (Ljava/lang/String;Ljava/lang/String;)Lscala/xml/dtd/ValidationException;
  Code:
   Stack=8, Locals=3, Args_size=3
	new	class scala/xml/dtd/ValidationException
	dup
	getstatic	Field scala/Predef$.MODULE$:Lscala/Predef$;
	ldc	String missing value for REQUIRED attribute %s of type %s
	invokevirtual	Method scala/Predef$.augmentString:(Ljava/lang/String;)Lscala/collection/immutable/StringOps;
	getstatic	Field scala/Predef$.MODULE$:Lscala/Predef$;
	iconst_2
	anewarray	class java/lang/Object
	dup
	iconst_0
	aload_1
	aastore
	dup
	iconst_1
	aload_2
	aastore
	invokevirtual	Method scala/Predef$.genericWrapArray:(Ljava/lang/Object;)Lscala/collection/mutable/WrappedArray;
	invokeinterface	InterfaceMethod scala/collection/immutable/StringLike.format:(Lscala/collection/Seq;)Ljava/lang/String;
	invokespecial	Method scala/xml/dtd/ValidationException."<init>":(Ljava/lang/String;)V
	areturn
  Labels:
  LocalVariableTable: 
   Start  Length  Slot  Name   Signature
   0      39      0    this       Lscala/xml/dtd/MakeValidationException$;
   0      39      1    key       Ljava/lang/String;
   0      39      2    tpe       Ljava/lang/String;


public scala.xml.dtd.ValidationException fromMissingAttribute(scala.collection.immutable.Set);
  Signature: (Lscala/collection/immutable/Set;)Lscala/xml/dtd/ValidationException;
  Code:
   Stack=4, Locals=3, Args_size=2
	new	class scala/collection/mutable/StringBuilder
	dup
	ldc	String missing value for REQUIRED attribute
	invokespecial	Method scala/collection/mutable/StringBuilder."<init>":(Ljava/lang/String;)V
	astore_2
	aload_1
	invokeinterface	InterfaceMethod scala/collection/TraversableLike.size:()I
	iconst_1
	if_icmple	l1 // getstatic
	aload_2
	ldc	int 115
	invokevirtual	Method scala/collection/mutable/StringBuilder.append:(C)Lscala/collection/mutable/StringBuilder;
	goto	l2 // pop
l1	getstatic	Field scala/runtime/BoxedUnit.UNIT:Lscala/runtime/BoxedUnit;
l2	pop
	aload_1
	new	class scala/xml/dtd/MakeValidationException$$anonfun$fromMissingAttribute$1
	dup
	aload_2
	invokespecial	Method scala/xml/dtd/MakeValidationException$$anonfun$fromMissingAttribute$1."<init>":(Lscala/collection/mutable/StringBuilder;)V
	invokeinterface	InterfaceMethod scala/collection/IterableLike.foreach:(Lscala/Function1;)V
	new	class scala/xml/dtd/ValidationException
	dup
	aload_2
	invokevirtual	Method scala/collection/mutable/StringBuilder.toString:()Ljava/lang/String;
	invokespecial	Method scala/xml/dtd/ValidationException."<init>":(Ljava/lang/String;)V
	areturn
  Labels:
   	l1 = 29 // getstatic
   	l2 = 32 // pop
  LocalVariableTable: 
   Start  Length  Slot  Name   Signature
   0      59      0    this       Lscala/xml/dtd/MakeValidationException$;
   0      59      1    allKeys       Lscala/collection/immutable/Set;
   10      48      2    sb$1       Lscala/collection/mutable/StringBuilder;

  Signature: length = 0x2
   00 5F 

public scala.xml.dtd.ValidationException fromUndefinedAttribute(java.lang.String);
  Signature: (Ljava/lang/String;)Lscala/xml/dtd/ValidationException;
  Code:
   Stack=4, Locals=2, Args_size=2
	new	class scala/xml/dtd/ValidationException
	dup
	new	class scala/collection/mutable/StringBuilder
	dup
	invokespecial	Method scala/collection/mutable/StringBuilder."<init>":()V
	ldc	String attribute 
	invokevirtual	Method scala/collection/mutable/StringBuilder.append:(Ljava/lang/Object;)Lscala/collection/mutable/StringBuilder;
	aload_1
	invokevirtual	Method scala/collection/mutable/StringBuilder.append:(Ljava/lang/Object;)Lscala/collection/mutable/StringBuilder;
	ldc	String  not allowed here
	invokevirtual	Method scala/collection/mutable/StringBuilder.append:(Ljava/lang/Object;)Lscala/collection/mutable/StringBuilder;
	invokevirtual	Method scala/collection/mutable/StringBuilder.toString:()Ljava/lang/String;
	invokespecial	Method scala/xml/dtd/ValidationException."<init>":(Ljava/lang/String;)V
	areturn
  Labels:
  LocalVariableTable: 
   Start  Length  Slot  Name   Signature
   0      32      0    this       Lscala/xml/dtd/MakeValidationException$;
   0      32      1    key       Ljava/lang/String;


public scala.xml.dtd.ValidationException fromUndefinedElement(java.lang.String);
  Signature: (Ljava/lang/String;)Lscala/xml/dtd/ValidationException;
  Code:
   Stack=4, Locals=2, Args_size=2
	new	class scala/xml/dtd/ValidationException
	dup
	new	class scala/collection/mutable/StringBuilder
	dup
	invokespecial	Method scala/collection/mutable/StringBuilder."<init>":()V
	ldc	String element \"
	invokevirtual	Method scala/collection/mutable/StringBuilder.append:(Ljava/lang/Object;)Lscala/collection/mutable/StringBuilder;
	aload_1
	invokevirtual	Method scala/collection/mutable/StringBuilder.append:(Ljava/lang/Object;)Lscala/collection/mutable/StringBuilder;
	ldc	String \" not allowed here
	invokevirtual	Method scala/collection/mutable/StringBuilder.append:(Ljava/lang/Object;)Lscala/collection/mutable/StringBuilder;
	invokevirtual	Method scala/collection/mutable/StringBuilder.toString:()Ljava/lang/String;
	invokespecial	Method scala/xml/dtd/ValidationException."<init>":(Ljava/lang/String;)V
	areturn
  Labels:
  LocalVariableTable: 
   Start  Length  Slot  Name   Signature
   0      32      0    this       Lscala/xml/dtd/MakeValidationException$;
   0      32      1    label       Ljava/lang/String;


public scala.xml.dtd.ValidationException fromNonEmptyElement();
  Signature: ()Lscala/xml/dtd/ValidationException;
  Code:
   Stack=3, Locals=1, Args_size=1
	new	class scala/xml/dtd/ValidationException
	dup
	ldc	String element should be *empty*
	invokespecial	Method scala/xml/dtd/ValidationException."<init>":(Ljava/lang/String;)V
	areturn
  Labels:

public scala.xml.dtd.ValidationException fromFixedAttribute(java.lang.String, java.lang.String, java.lang.String);
  Signature: (Ljava/lang/String;Ljava/lang/String;Ljava/lang/String;)Lscala/xml/dtd/ValidationException;
  Code:
   Stack=4, Locals=4, Args_size=4
	new	class scala/xml/dtd/ValidationException
	dup
	new	class scala/collection/mutable/StringBuilder
	dup
	invokespecial	Method scala/collection/mutable/StringBuilder."<init>":()V
	ldc	String value of attribute 
	invokevirtual	Method scala/collection/mutable/StringBuilder.append:(Ljava/lang/Object;)Lscala/collection/mutable/StringBuilder;
	aload_1
	invokevirtual	Method scala/collection/mutable/StringBuilder.append:(Ljava/lang/Object;)Lscala/collection/mutable/StringBuilder;
	ldc	String  FIXED to \"
	invokevirtual	Method scala/collection/mutable/StringBuilder.append:(Ljava/lang/Object;)Lscala/collection/mutable/StringBuilder;
	aload_2
	invokevirtual	Method scala/collection/mutable/StringBuilder.append:(Ljava/lang/Object;)Lscala/collection/mutable/StringBuilder;
	ldc	String \", but document tries \"
	invokevirtual	Method scala/collection/mutable/StringBuilder.append:(Ljava/lang/Object;)Lscala/collection/mutable/StringBuilder;
	aload_3
	invokevirtual	Method scala/collection/mutable/StringBuilder.append:(Ljava/lang/Object;)Lscala/collection/mutable/StringBuilder;
	ldc	String \"
	invokevirtual	Method scala/collection/mutable/StringBuilder.append:(Ljava/lang/Object;)Lscala/collection/mutable/StringBuilder;
	invokevirtual	Method scala/collection/mutable/StringBuilder.toString:()Ljava/lang/String;
	invokespecial	Method scala/xml/dtd/ValidationException."<init>":(Ljava/lang/String;)V
	areturn
  Labels:
  LocalVariableTable: 
   Start  Length  Slot  Name   Signature
   0      50      0    this       Lscala/xml/dtd/MakeValidationException$;
   0      50      1    k       Ljava/lang/String;
   0      50      2    value       Ljava/lang/String;
   0      50      3    actual       Ljava/lang/String;


}

