Compiled from "ContentModel.scala"
public class scala.xml.dtd.MIXED extends scala.xml.dtd.DFAContentModel implements scala.ScalaObject,scala.Product,java.io.Serializable
  SourceFile: "ContentModel.scala"
  ScalaSig: length = 0x3A8
   05 00 FFFFFF81 0D 06 08 01 02 FFFFFF84 FFFFFF80 FFFFFF80 FFFFFF80 40 09 02 05
   4D 49 58 45 44 0A 02 03 04 01 03 64 74 64 0A 02
   05 06 01 03 78 6D 6C 0A 01 07 01 05 73 63 61 6C
   61 03 00 13 04 00 0A 0E 12 10 02 0B 0C 0D 01 02
   09 02 0D 02 02 0F 44 46 41 43 6F 6E 74 65 6E 74
   4D 6F 64 65 6C 10 02 0F 10 0D 01 06 09 02 11 06
   02 0B 53 63 61 6C 61 4F 62 6A 65 63 74 10 02 0F
   13 09 02 14 06 02 07 50 72 6F 64 75 63 74 08 08
   16 00 FFFFFF82 FFFFFFCA FFFFFF80 FFFFFF84 00 17 01 01 72 15 01 18 10 02
   19 1C 0E 02 0B 1A 09 02 1B 02 01 0C 43 6F 6E 74
   65 6E 74 4D 6F 64 65 6C 09 02 1D 1E 02 06 52 65
   67 45 78 70 09 02 1F 20 02 04 42 61 73 65 0A 02
   21 22 01 06 72 65 67 65 78 70 0A 02 23 06 01 04
   75 74 69 6C 08 08 25 00 FFFFFF82 FFFFFF88 FFFFFFA0 FFFFFF80 04 18 01 02
   72 20 08 05 27 00 FFFFFF84 00 28 01 06 3C 69 6E 69 74
   3E 14 02 29 2A 10 02 0B 00 08 05 16 26 FFFFFFC0 00 18
   08 05 2C 00 FFFFFF84 20 2D 01 0B 62 75 69 6C 64 53 74
   72 69 6E 67 14 02 2E 36 10 02 2F 34 0D 01 30 0A
   02 31 32 01 07 6D 75 74 61 62 6C 65 0A 02 33 06
   01 0A 63 6F 6C 6C 65 63 74 69 6F 6E 09 02 35 30
   02 0D 53 74 72 69 6E 67 42 75 69 6C 64 65 72 08
   05 37 2B FFFFFFC0 00 2E 01 02 73 62 08 07 39 00 FFFFFF81 FFFFFF80
   FFFFFF84 00 3A 01 04 63 6F 70 79 14 02 29 3B 08 08 3C
   16 38 FFFFFF90 FFFFFF80 FFFFFFC0 00 18 08 07 3D 00 FFFFFF91 FFFFFF80 FFFFFF84 00 3E
   01 0E 63 6F 70 79 24 64 65 66 61 75 6C 74 24 31
   15 01 3F 2A 02 18 40 2B 01 41 10 02 42 47 0D 01
   43 0A 02 44 45 01 09 75 6E 63 68 65 63 6B 65 64
   0A 02 46 06 01 0A 61 6E 6E 6F 74 61 74 69 6F 6E
   09 02 48 43 02 11 75 6E 63 68 65 63 6B 65 64 56
   61 72 69 61 6E 63 65 08 08 4A 00 FFFFFF84 FFFFFF80 FFFFFF80 FFFFFF84 20
   4B 01 08 68 61 73 68 43 6F 64 65 14 01 4C 10 02
   0F 4D 09 02 4E 06 02 03 49 6E 74 08 08 50 00 FFFFFF84
   FFFFFF80 FFFFFF80 FFFFFF84 20 51 01 06 65 71 75 61 6C 73 14 02 52
   55 10 02 0F 53 09 02 54 06 02 07 42 6F 6F 6C 65
   61 6E 08 07 56 4F FFFFFF81 FFFFFF80 FFFFFFC0 00 57 01 03 78 24 31
   10 02 0F 58 09 02 59 06 02 03 41 6E 79 08 08 5B
   00 FFFFFF84 FFFFFF80 FFFFFF80 FFFFFF84 20 5C 01 0D 70 72 6F 64 75 63 74
   50 72 65 66 69 78 15 01 5D 10 02 5E 63 0D 01 5F
   0A 02 60 61 01 04 6C 61 6E 67 0A 01 62 01 04 6A
   61 76 61 09 02 64 5F 02 06 53 74 72 69 6E 67 08
   08 66 00 FFFFFF84 FFFFFF80 FFFFFF80 FFFFFF84 20 67 01 0C 70 72 6F 64 75
   63 74 41 72 69 74 79 15 01 4C 08 08 69 00 FFFFFF84 FFFFFF80
   FFFFFF80 FFFFFF84 20 6A 01 0E 70 72 6F 64 75 63 74 45 6C 65
   6D 65 6E 74 14 02 57 6B 08 07 56 68 FFFFFF81 FFFFFF80 FFFFFFC0 00
   4C 08 08 6D 00 FFFFFF84 FFFFFF80 FFFFFF80 FFFFFF84 20 6E 01 08 63 61 6E
   45 71 75 61 6C 14 02 52 6F 08 07 56 6C FFFFFF81 FFFFFF80 FFFFFFC0
   00 57 28 02 00 71 10 02 0F 72 09 02 73 06 02 0C
   73 65 72 69 61 6C 69 7A 61 62 6C 65 07 07 75 02
   FFFFFF81 FFFFFF80 FFFFFF88 02 76 01 05 4D 49 58 45 44 10 02 0B 77
   06 08 01 02 FFFFFF84 FFFFFF81 FFFFFF80 FFFFFF88 02 78 13 04 77 79 7C 0E
   10 02 5E 7A 09 02 7B 5F 02 06 4F 62 6A 65 63 74
   10 04 0F 7D 18 29 09 02 7E 06 02 09 46 75 6E 63
   74 69 6F 6E 31 08 06 27 77 FFFFFF84 00 FFFFFF81 00 14 01 76
   08 09 FFFFFF81 02 77 FFFFFF81 FFFFFF80 FFFFFF84 40 FFFFFF81 03 01 05 61 70 70
   6C 79 14 03 29 FFFFFF81 04 08 06 16 FFFFFF81 01 FFFFFFC0 00 18 08
   09 FFFFFF81 06 77 FFFFFF81 FFFFFF80 FFFFFF84 40 FFFFFF81 07 01 07 75 6E 61 70
   70 6C 79 14 04 FFFFFF81 08 FFFFFF81 0B 10 04 0F FFFFFF81 09 18 09
   03 FFFFFF81 0A 06 02 04 53 6F 6D 65 08 07 FFFFFF81 0C FFFFFF81 05
   FFFFFFC0 00 29 01 03 78 24 30 
  InnerClass: 
   public Alt=class scala/util/regexp/Base$Alt of class scala/util/regexp/Base
   public abstract RegExp=class scala/util/regexp/Base$RegExp of class scala/util/regexp/Base
  minor version: 0
  major version: 49
  Constant pool:
Asciz	SourceFile;
Asciz	ContentModel.scala;
Asciz	andThen;
Asciz	(Lscala/Function1;)Lscala/Function1;;
Asciz	Code;
Asciz	scala/xml/dtd/MIXED$;
class	scala/xml/dtd/MIXED$
Asciz	MODULE$;
Asciz	Lscala/xml/dtd/MIXED$;;
NameAndType	MODULE$:Lscala/xml/dtd/MIXED$;
Field	scala/xml/dtd/MIXED$.MODULE$:Lscala/xml/dtd/MIXED$;
NameAndType	andThen:(Lscala/Function1;)Lscala/Function1;
Method	scala/xml/dtd/MIXED$.andThen:(Lscala/Function1;)Lscala/Function1;
Asciz	compose;
NameAndType	compose:(Lscala/Function1;)Lscala/Function1;
Method	scala/xml/dtd/MIXED$.compose:(Lscala/Function1;)Lscala/Function1;
Asciz	r;
Asciz	Lscala/util/regexp/Base$RegExp;;
Asciz	<init>;
Asciz	(Lscala/util/regexp/Base$RegExp;)V;
Asciz	LineNumberTable;
Asciz	scala/xml/dtd/MIXED;
class	scala/xml/dtd/MIXED
NameAndType	r:Lscala/util/regexp/Base$RegExp;
Field	scala/xml/dtd/MIXED.r:Lscala/util/regexp/Base$RegExp;
Asciz	scala/xml/dtd/DFAContentModel;
class	scala/xml/dtd/DFAContentModel
Asciz	()V;
NameAndType	"<init>":()V
Method	scala/xml/dtd/DFAContentModel."<init>":()V
Asciz	scala/Product$class;
class	scala/Product$class
Asciz	$init$;
Asciz	(Lscala/Product;)V;
NameAndType	$init$:(Lscala/Product;)V
Method	scala/Product$class.$init$:(Lscala/Product;)V
Asciz	this;
Asciz	Lscala/xml/dtd/MIXED;;
Asciz	LocalVariableTable;
Asciz	gd2$1;
Asciz	(Lscala/util/regexp/Base$RegExp;)Z;
Asciz	()Lscala/util/regexp/Base$RegExp;;
NameAndType	r:()Lscala/util/regexp/Base$RegExp;
Method	scala/xml/dtd/MIXED.r:()Lscala/util/regexp/Base$RegExp;
Asciz	java/lang/Object;
class	java/lang/Object
Asciz	equals;
Asciz	(Ljava/lang/Object;)Z;
NameAndType	equals:(Ljava/lang/Object;)Z
Method	java/lang/Object.equals:(Ljava/lang/Object;)Z
Asciz	canEqual;
Asciz	productElement;
Asciz	(I)Ljava/lang/Object;;
Asciz	scala/MatchError;
class	scala/MatchError
Asciz	scala/runtime/BoxesRunTime;
class	scala/runtime/BoxesRunTime
Asciz	boxToInteger;
Asciz	(I)Ljava/lang/Integer;;
NameAndType	boxToInteger:(I)Ljava/lang/Integer;
Method	scala/runtime/BoxesRunTime.boxToInteger:(I)Ljava/lang/Integer;
Asciz	toString;
Asciz	()Ljava/lang/String;;
NameAndType	toString:()Ljava/lang/String;
Method	java/lang/Object.toString:()Ljava/lang/String;
Asciz	(Ljava/lang/String;)V;
NameAndType	"<init>":(Ljava/lang/String;)V
Method	scala/MatchError."<init>":(Ljava/lang/String;)V
Asciz	java/lang/IndexOutOfBoundsException;
class	java/lang/IndexOutOfBoundsException
Method	java/lang/IndexOutOfBoundsException."<init>":(Ljava/lang/String;)V
Asciz	productArity;
Asciz	()I;
Asciz	productPrefix;
Asciz	MIXED;
String	MIXED
NameAndType	gd2$1:(Lscala/util/regexp/Base$RegExp;)Z
Method	scala/xml/dtd/MIXED.gd2$1:(Lscala/util/regexp/Base$RegExp;)Z
Asciz	scala/Equals;
class	scala/Equals
NameAndType	canEqual:(Ljava/lang/Object;)Z
InterfaceMethod	scala/Equals.canEqual:(Ljava/lang/Object;)Z
Asciz	temp56;
Asciz	temp57;
Asciz	hashCode;
Asciz	scala/runtime/ScalaRunTime$;
class	scala/runtime/ScalaRunTime$
Asciz	Lscala/runtime/ScalaRunTime$;;
NameAndType	MODULE$:Lscala/runtime/ScalaRunTime$;
Field	scala/runtime/ScalaRunTime$.MODULE$:Lscala/runtime/ScalaRunTime$;
Asciz	_hashCode;
Asciz	(Lscala/Product;)I;
NameAndType	_hashCode:(Lscala/Product;)I
Method	scala/runtime/ScalaRunTime$._hashCode:(Lscala/Product;)I
Asciz	copy;
Asciz	(Lscala/util/regexp/Base$RegExp;)Lscala/xml/dtd/MIXED;;
NameAndType	"<init>":(Lscala/util/regexp/Base$RegExp;)V
Method	scala/xml/dtd/MIXED."<init>":(Lscala/util/regexp/Base$RegExp;)V
Asciz	buildString;
Asciz	(Lscala/collection/mutable/StringBuilder;)Lscala/collection/mutable/StringBuilder;;
Asciz	scala/util/regexp/Base$Alt;
class	scala/util/regexp/Base$Alt
Asciz	scala/xml/dtd/ContentModel$;
class	scala/xml/dtd/ContentModel$
Asciz	Lscala/xml/dtd/ContentModel$;;
NameAndType	MODULE$:Lscala/xml/dtd/ContentModel$;
Field	scala/xml/dtd/ContentModel$.MODULE$:Lscala/xml/dtd/ContentModel$;
Asciz	Alt;
Asciz	()Lscala/util/regexp/Base$Alt$;;
NameAndType	Alt:()Lscala/util/regexp/Base$Alt$;
Method	scala/xml/dtd/ContentModel$.Alt:()Lscala/util/regexp/Base$Alt$;
Asciz	scala/Some;
class	scala/Some
Asciz	rs;
Asciz	()Lscala/collection/Seq;;
NameAndType	rs:()Lscala/collection/Seq;
Method	scala/util/regexp/Base$Alt.rs:()Lscala/collection/Seq;
Asciz	(Ljava/lang/Object;)V;
NameAndType	"<init>":(Ljava/lang/Object;)V
Method	scala/Some."<init>":(Ljava/lang/Object;)V
Asciz	x;
Asciz	Ljava/lang/Object;;
NameAndType	x:Ljava/lang/Object;
Field	scala/Some.x:Ljava/lang/Object;
Asciz	scala/collection/Seq;
class	scala/collection/Seq
Asciz	scala/collection/SeqLike;
class	scala/collection/SeqLike
Asciz	lengthCompare;
Asciz	(I)I;
NameAndType	lengthCompare:(I)I
InterfaceMethod	scala/collection/SeqLike.lengthCompare:(I)I
Asciz	scala/collection/TraversableLike;
class	scala/collection/TraversableLike
Asciz	drop;
NameAndType	drop:(I)Ljava/lang/Object;
InterfaceMethod	scala/collection/TraversableLike.drop:(I)Ljava/lang/Object;
Asciz	scala/util/regexp/Base$Alt$;
class	scala/util/regexp/Base$Alt$
Asciz	apply;
Asciz	(Lscala/collection/Seq;)Lscala/util/regexp/Base$Alt;;
NameAndType	apply:(Lscala/collection/Seq;)Lscala/util/regexp/Base$Alt;
Method	scala/util/regexp/Base$Alt$.apply:(Lscala/collection/Seq;)Lscala/util/regexp/Base$Alt;
Asciz	(#PCDATA|;
String	(#PCDATA|
Asciz	scala/collection/mutable/StringBuilder;
class	scala/collection/mutable/StringBuilder
Asciz	append;
Asciz	(Ljava/lang/String;)Lscala/collection/mutable/StringBuilder;;
NameAndType	append:(Ljava/lang/String;)Lscala/collection/mutable/StringBuilder;
Method	scala/collection/mutable/StringBuilder.append:(Ljava/lang/String;)Lscala/collection/mutable/StringBuilder;
Asciz	(Lscala/util/regexp/Base$RegExp;Lscala/collection/mutable/StringBuilder;)Lscala/collection/mutable/StringBuilder;;
NameAndType	buildString:(Lscala/util/regexp/Base$RegExp;Lscala/collection/mutable/StringBuilder;)Lscala/collection/mutable/StringBuilder;
Method	scala/xml/dtd/ContentModel$.buildString:(Lscala/util/regexp/Base$RegExp;Lscala/collection/mutable/StringBuilder;)Lscala/collection/mutable/StringBuilder;
Asciz	)*;
String	)*
Asciz	scala/util/regexp/Base$RegExp;
class	scala/util/regexp/Base$RegExp
Method	scala/util/regexp/Base$RegExp.toString:()Ljava/lang/String;
Asciz	sb;
Asciz	Lscala/collection/mutable/StringBuilder;;
Asciz	temp51;
Asciz	Lscala/util/regexp/Base$Alt;;
Asciz	temp52;
Asciz	Lscala/Some;;
Asciz	temp53;
Asciz	Lscala/collection/Seq;;
Asciz	newAlt;
Asciz	temp50;
Asciz	copy$default$1;
Asciz	productElements;
Asciz	()Lscala/collection/Iterator;;
Asciz	(Lscala/Product;)Lscala/collection/Iterator;;
NameAndType	productElements:(Lscala/Product;)Lscala/collection/Iterator;
Method	scala/Product$class.productElements:(Lscala/Product;)Lscala/collection/Iterator;
Asciz	productIterator;
NameAndType	productIterator:(Lscala/Product;)Lscala/collection/Iterator;
Method	scala/Product$class.productIterator:(Lscala/Product;)Lscala/collection/Iterator;
Asciz	ScalaSig;
Asciz	InnerClasses;
Asciz	scala/util/regexp/Base;
class	scala/util/regexp/Base
Asciz	RegExp;
Asciz	scala/ScalaObject;
class	scala/ScalaObject
Asciz	scala/Product;
class	scala/Product
Asciz	java/io/Serializable;
class	java/io/Serializable

{
private final scala.util.regexp.Base$RegExp r;
  Signature: Lscala/util/regexp/Base$RegExp;

public static final scala.Function1 andThen(scala.Function1);
  Signature: (Lscala/Function1;)Lscala/Function1;
  Code:
   Stack=2, Locals=1, Args_size=1
	getstatic	Field scala/xml/dtd/MIXED$.MODULE$:Lscala/xml/dtd/MIXED$;
	aload_0
	invokevirtual	Method scala/xml/dtd/MIXED$.andThen:(Lscala/Function1;)Lscala/Function1;
	areturn
  Labels:

public static final scala.Function1 compose(scala.Function1);
  Signature: (Lscala/Function1;)Lscala/Function1;
  Code:
   Stack=2, Locals=1, Args_size=1
	getstatic	Field scala/xml/dtd/MIXED$.MODULE$:Lscala/xml/dtd/MIXED$;
	aload_0
	invokevirtual	Method scala/xml/dtd/MIXED$.compose:(Lscala/Function1;)Lscala/Function1;
	areturn
  Labels:

public scala.xml.dtd.MIXED(scala.util.regexp.Base$RegExp);
  Signature: (Lscala/util/regexp/Base$RegExp;)V
  Code:
   Stack=2, Locals=2, Args_size=2
	aload_0
	aload_1
	putfield	Field r:Lscala/util/regexp/Base$RegExp;
	aload_0
	invokespecial	Method scala/xml/dtd/DFAContentModel."<init>":()V
	aload_0
	invokestatic	Method scala/Product$class.$init$:(Lscala/Product;)V
	return
  Labels:
  LocalVariableTable: 
   Start  Length  Slot  Name   Signature
   0      14      0    this       Lscala/xml/dtd/MIXED;
   0      14      1    r       Lscala/util/regexp/Base$RegExp;


private final boolean gd2$1(scala.util.regexp.Base$RegExp);
  Signature: (Lscala/util/regexp/Base$RegExp;)Z
  Code:
   Stack=2, Locals=3, Args_size=2
	aload_1
	aload_0
	invokevirtual	Method r:()Lscala/util/regexp/Base$RegExp;
	astore_2
	dup
	ifnonnull	l1 // aload_2
	pop
	aload_2
	ifnull	l2 // iconst_1
	goto	l3 // iconst_0
l1	aload_2
	invokevirtual	Method java/lang/Object.equals:(Ljava/lang/Object;)Z
	ifeq	l3 // iconst_0
l2	iconst_1
	goto	l4 // ireturn
l3	iconst_0
l4	ireturn
  Labels:
   	l1 = 18 // aload_2
   	l2 = 25 // iconst_1
   	l3 = 29 // iconst_0
   	l4 = 30 // ireturn

public boolean canEqual(java.lang.Object);
  Signature: (Ljava/lang/Object;)Z
  Code:
   Stack=1, Locals=2, Args_size=2
	aload_1
	instanceof	class scala/xml/dtd/MIXED
	ireturn
  Labels:

public java.lang.Object productElement(int);
  Signature: (I)Ljava/lang/Object;
  Code:
   Stack=3, Locals=2, Args_size=2
	iload_1
	iconst_0
	if_icmpne	l1 // iconst_1
	iconst_1
	ifeq	l2 // new
	aload_0
	invokevirtual	Method r:()Lscala/util/regexp/Base$RegExp;
	areturn
l2	new	class scala/MatchError
	dup
	iload_1
	invokestatic	Method scala/runtime/BoxesRunTime.boxToInteger:(I)Ljava/lang/Integer;
	invokevirtual	Method java/lang/Object.toString:()Ljava/lang/String;
	invokespecial	Method scala/MatchError."<init>":(Ljava/lang/String;)V
	athrow
l1	iconst_1
	ifeq	l3 // new
	new	class java/lang/IndexOutOfBoundsException
	dup
	iload_1
	invokestatic	Method scala/runtime/BoxesRunTime.boxToInteger:(I)Ljava/lang/Integer;
	invokevirtual	Method java/lang/Object.toString:()Ljava/lang/String;
	invokespecial	Method java/lang/IndexOutOfBoundsException."<init>":(Ljava/lang/String;)V
	athrow
l3	new	class scala/MatchError
	dup
	iload_1
	invokestatic	Method scala/runtime/BoxesRunTime.boxToInteger:(I)Ljava/lang/Integer;
	invokevirtual	Method java/lang/Object.toString:()Ljava/lang/String;
	invokespecial	Method scala/MatchError."<init>":(Ljava/lang/String;)V
	athrow
  Labels:
   	l2 = 14 // new
   	l1 = 29 // iconst_1
   	l3 = 48 // new

public int productArity();
  Signature: ()I
  Code:
   Stack=1, Locals=1, Args_size=1
	iconst_1
	ireturn
  Labels:

public java.lang.String productPrefix();
  Signature: ()Ljava/lang/String;
  Code:
   Stack=1, Locals=1, Args_size=1
	ldc	String MIXED
	areturn
  Labels:

public boolean equals(java.lang.Object);
  Signature: (Ljava/lang/Object;)Z
  Code:
   Stack=3, Locals=4, Args_size=2
	aload_0
	aload_1
	if_acmpeq	l1 // iconst_1
	aload_1
	instanceof	class scala/xml/dtd/MIXED
	ifeq	l2 // iconst_1
	aload_1
	checkcast	class scala/xml/dtd/MIXED
	astore_2
	aload_2
	invokevirtual	Method r:()Lscala/util/regexp/Base$RegExp;
	astore_3
	aload_0
	aload_3
	invokespecial	Method gd2$1:(Lscala/util/regexp/Base$RegExp;)Z
	ifeq	l3 // iconst_1
	aload_1
	checkcast	class scala/xml/dtd/MIXED
	aload_0
	invokeinterface	InterfaceMethod scala/Equals.canEqual:(Ljava/lang/Object;)Z
	goto	l4 // ifeq
l3	iconst_1
	ifeq	l5 // new
	iconst_0
	goto	l4 // ifeq
l5	new	class scala/MatchError
	dup
	aload_1
	invokevirtual	Method java/lang/Object.toString:()Ljava/lang/String;
	invokespecial	Method scala/MatchError."<init>":(Ljava/lang/String;)V
	athrow
l2	iconst_1
	ifeq	l6 // new
	iconst_0
l4	ifeq	l7 // iconst_0
l1	iconst_1
	goto	l8 // ireturn
l7	iconst_0
l8	ireturn
l6	new	class scala/MatchError
	dup
	aload_1
	invokevirtual	Method java/lang/Object.toString:()Ljava/lang/String;
	invokespecial	Method scala/MatchError."<init>":(Ljava/lang/String;)V
	athrow
  Labels:
   	l3 = 43 // iconst_1
   	l5 = 51 // new
   	l2 = 63 // iconst_1
   	l4 = 68 // ifeq
   	l1 = 71 // iconst_1
   	l7 = 75 // iconst_0
   	l8 = 76 // ireturn
   	l6 = 77 // new
  LocalVariableTable: 
   Start  Length  Slot  Name   Signature
   0      89      0    this       Lscala/xml/dtd/MIXED;
   17      46      2    temp56       Lscala/xml/dtd/MIXED;
   22      41      3    temp57       Lscala/util/regexp/Base$RegExp;


public int hashCode();
  Signature: ()I
  Code:
   Stack=2, Locals=1, Args_size=1
	getstatic	Field scala/runtime/ScalaRunTime$.MODULE$:Lscala/runtime/ScalaRunTime$;
	aload_0
	invokevirtual	Method scala/runtime/ScalaRunTime$._hashCode:(Lscala/Product;)I
	ireturn
  Labels:

public scala.xml.dtd.MIXED copy(scala.util.regexp.Base$RegExp);
  Signature: (Lscala/util/regexp/Base$RegExp;)Lscala/xml/dtd/MIXED;
  Code:
   Stack=3, Locals=2, Args_size=2
	new	class scala/xml/dtd/MIXED
	dup
	aload_1
	invokespecial	Method "<init>":(Lscala/util/regexp/Base$RegExp;)V
	areturn
  Labels:
  LocalVariableTable: 
   Start  Length  Slot  Name   Signature
   0      9      0    this       Lscala/xml/dtd/MIXED;
   0      9      1    r       Lscala/util/regexp/Base$RegExp;


public scala.collection.mutable.StringBuilder buildString(scala.collection.mutable.StringBuilder);
  Signature: (Lscala/collection/mutable/StringBuilder;)Lscala/collection/mutable/StringBuilder;
  Code:
   Stack=3, Locals=7, Args_size=2
	aload_0
	invokevirtual	Method r:()Lscala/util/regexp/Base$RegExp;
	astore	6
	aload	6
	instanceof	class scala/util/regexp/Base$Alt
	ifeq	l1 // new
	aload	6
	checkcast	class scala/util/regexp/Base$Alt
	astore_2
	getstatic	Field scala/xml/dtd/ContentModel$.MODULE$:Lscala/xml/dtd/ContentModel$;
	invokevirtual	Method scala/xml/dtd/ContentModel$.Alt:()Lscala/util/regexp/Base$Alt$;
	pop
	new	class scala/Some
	dup
	aload_2
	invokevirtual	Method scala/util/regexp/Base$Alt.rs:()Lscala/collection/Seq;
	invokespecial	Method scala/Some."<init>":(Ljava/lang/Object;)V
	astore_3
	iconst_1
	ifeq	l2 // new
	aload_3
	getfield	Field scala/Some.x:Ljava/lang/Object;
	checkcast	class scala/collection/Seq
	astore	4
	aload	4
	dup
	pop
	ifnull	l3 // iconst_0
	aload	4
	aconst_null
	invokevirtual	Method java/lang/Object.equals:(Ljava/lang/Object;)Z
	ifeq	l4 // aload
l3	iconst_0
	goto	l5 // ifeq
l4	aload	4
	iconst_0
	invokeinterface	InterfaceMethod scala/collection/SeqLike.lengthCompare:(I)I
	iconst_0
	if_icmplt	l6 // iconst_0
	iconst_1
	goto	l5 // ifeq
l6	iconst_0
l5	ifeq	l7 // new
	iconst_1
	ifeq	l8 // new
	getstatic	Field scala/xml/dtd/ContentModel$.MODULE$:Lscala/xml/dtd/ContentModel$;
	invokevirtual	Method scala/xml/dtd/ContentModel$.Alt:()Lscala/util/regexp/Base$Alt$;
	aload	4
	iconst_1
	invokeinterface	InterfaceMethod scala/collection/TraversableLike.drop:(I)Ljava/lang/Object;
	checkcast	class scala/collection/Seq
	invokevirtual	Method scala/util/regexp/Base$Alt$.apply:(Lscala/collection/Seq;)Lscala/util/regexp/Base$Alt;
	astore	5
	aload_1
	ldc	String (#PCDATA|
	invokevirtual	Method scala/collection/mutable/StringBuilder.append:(Ljava/lang/String;)Lscala/collection/mutable/StringBuilder;
	pop
	getstatic	Field scala/xml/dtd/ContentModel$.MODULE$:Lscala/xml/dtd/ContentModel$;
	aload	5
	aload_1
	invokevirtual	Method scala/xml/dtd/ContentModel$.buildString:(Lscala/util/regexp/Base$RegExp;Lscala/collection/mutable/StringBuilder;)Lscala/collection/mutable/StringBuilder;
	pop
	aload_1
	ldc	String )*
	invokevirtual	Method scala/collection/mutable/StringBuilder.append:(Ljava/lang/String;)Lscala/collection/mutable/StringBuilder;
	areturn
l8	new	class scala/MatchError
	dup
	aload	6
	invokevirtual	Method scala/util/regexp/Base$RegExp.toString:()Ljava/lang/String;
	invokespecial	Method scala/MatchError."<init>":(Ljava/lang/String;)V
	athrow
l7	new	class scala/MatchError
	dup
	aload	6
	invokevirtual	Method scala/util/regexp/Base$RegExp.toString:()Ljava/lang/String;
	invokespecial	Method scala/MatchError."<init>":(Ljava/lang/String;)V
	athrow
l2	new	class scala/MatchError
	dup
	aload	6
	invokevirtual	Method scala/util/regexp/Base$RegExp.toString:()Ljava/lang/String;
	invokespecial	Method scala/MatchError."<init>":(Ljava/lang/String;)V
	athrow
l1	new	class scala/MatchError
	dup
	aload	6
	invokevirtual	Method scala/util/regexp/Base$RegExp.toString:()Ljava/lang/String;
	invokespecial	Method scala/MatchError."<init>":(Ljava/lang/String;)V
	athrow
  Labels:
   	l3 = 68 // iconst_0
   	l4 = 72 // aload
   	l6 = 88 // iconst_0
   	l5 = 89 // ifeq
   	l8 = 142 // new
   	l7 = 155 // new
   	l2 = 168 // new
   	l1 = 181 // new
  LocalVariableTable: 
   Start  Length  Slot  Name   Signature
   0      194      0    this       Lscala/xml/dtd/MIXED;
   0      194      1    sb       Lscala/collection/mutable/StringBuilder;
   20      161      2    temp51       Lscala/util/regexp/Base$Alt;
   39      142      3    temp52       Lscala/Some;
   52      116      4    temp53       Lscala/collection/Seq;
   118      23      5    newAlt       Lscala/util/regexp/Base$Alt;
   6      188      6    temp50       Lscala/util/regexp/Base$RegExp;


public scala.util.regexp.Base$RegExp r();
  Signature: ()Lscala/util/regexp/Base$RegExp;
  Code:
   Stack=1, Locals=1, Args_size=1
	aload_0
	getfield	Field r:Lscala/util/regexp/Base$RegExp;
	areturn
  Labels:

public scala.util.regexp.Base$RegExp copy$default$1();
  Signature: ()Lscala/util/regexp/Base$RegExp;
  Code:
   Stack=1, Locals=1, Args_size=1
	aload_0
	invokevirtual	Method r:()Lscala/util/regexp/Base$RegExp;
	areturn
  Labels:

public scala.collection.Iterator productElements();
  Signature: ()Lscala/collection/Iterator;
  Code:
   Stack=1, Locals=1, Args_size=1
	aload_0
	invokestatic	Method scala/Product$class.productElements:(Lscala/Product;)Lscala/collection/Iterator;
	areturn
  Labels:

public scala.collection.Iterator productIterator();
  Signature: ()Lscala/collection/Iterator;
  Code:
   Stack=1, Locals=1, Args_size=1
	aload_0
	invokestatic	Method scala/Product$class.productIterator:(Lscala/Product;)Lscala/collection/Iterator;
	areturn
  Labels:

}

