Compiled from "Decl.scala"
public class scala.xml.dtd.ParameterEntityDecl extends scala.xml.dtd.EntityDecl implements scala.ScalaObject,scala.Product,java.io.Serializable
  SourceFile: "Decl.scala"
  ScalaSig: length = 0x3
   05 00 00 
  RuntimeVisibleAnnotations: length = 0xB
   00 01 00 FFFFFF96 00 01 00 FFFFFF97 73 00 FFFFFF98 
  minor version: 0
  major version: 49
  Constant pool:
Asciz	SourceFile;
Asciz	Decl.scala;
Asciz	tupled;
Asciz	()Lscala/Function1;;
Asciz	Code;
Asciz	scala/xml/dtd/ParameterEntityDecl$;
class	scala/xml/dtd/ParameterEntityDecl$
Asciz	MODULE$;
Asciz	Lscala/xml/dtd/ParameterEntityDecl$;;
NameAndType	MODULE$:Lscala/xml/dtd/ParameterEntityDecl$;
Field	scala/xml/dtd/ParameterEntityDecl$.MODULE$:Lscala/xml/dtd/ParameterEntityDecl$;
NameAndType	tupled:()Lscala/Function1;
Method	scala/xml/dtd/ParameterEntityDecl$.tupled:()Lscala/Function1;
Asciz	curry;
NameAndType	curry:()Lscala/Function1;
Method	scala/xml/dtd/ParameterEntityDecl$.curry:()Lscala/Function1;
Asciz	Deprecated;
Asciz	curried;
NameAndType	curried:()Lscala/Function1;
Method	scala/xml/dtd/ParameterEntityDecl$.curried:()Lscala/Function1;
Asciz	name;
Asciz	Ljava/lang/String;;
Asciz	entdef;
Asciz	Lscala/xml/dtd/EntityDef;;
Asciz	productElementName;
Asciz	(I)Ljava/lang/String;;
Asciz	LineNumberTable;
Asciz	scala/Product$class;
class	scala/Product$class
Asciz	(Lscala/Product;I)Ljava/lang/String;;
NameAndType	productElementName:(Lscala/Product;I)Ljava/lang/String;
Method	scala/Product$class.productElementName:(Lscala/Product;I)Ljava/lang/String;
Asciz	this;
Asciz	Lscala/xml/dtd/ParameterEntityDecl;;
Asciz	n;
Asciz	I;
Asciz	LocalVariableTable;
Asciz	productIterator;
Asciz	()Lscala/collection/Iterator;;
Asciz	(Lscala/Product;)Lscala/collection/Iterator;;
NameAndType	productIterator:(Lscala/Product;)Lscala/collection/Iterator;
Method	scala/Product$class.productIterator:(Lscala/Product;)Lscala/collection/Iterator;
Asciz	productElements;
NameAndType	productElements:(Lscala/Product;)Lscala/collection/Iterator;
Method	scala/Product$class.productElements:(Lscala/Product;)Lscala/collection/Iterator;
Asciz	copy$default$2;
Asciz	()Lscala/xml/dtd/EntityDef;;
Asciz	scala/xml/dtd/ParameterEntityDecl;
class	scala/xml/dtd/ParameterEntityDecl
NameAndType	entdef:()Lscala/xml/dtd/EntityDef;
Method	scala/xml/dtd/ParameterEntityDecl.entdef:()Lscala/xml/dtd/EntityDef;
Asciz	copy$default$1;
Asciz	()Ljava/lang/String;;
NameAndType	name:()Ljava/lang/String;
Method	scala/xml/dtd/ParameterEntityDecl.name:()Ljava/lang/String;
NameAndType	name:Ljava/lang/String;
Field	scala/xml/dtd/ParameterEntityDecl.name:Ljava/lang/String;
NameAndType	entdef:Lscala/xml/dtd/EntityDef;
Field	scala/xml/dtd/ParameterEntityDecl.entdef:Lscala/xml/dtd/EntityDef;
Asciz	buildString;
Asciz	(Lscala/collection/mutable/StringBuilder;)Lscala/collection/mutable/StringBuilder;;
Asciz	<!ENTITY % ;
String	<!ENTITY % 
Asciz	scala/collection/mutable/StringBuilder;
class	scala/collection/mutable/StringBuilder
Asciz	append;
Asciz	(Ljava/lang/String;)Lscala/collection/mutable/StringBuilder;;
NameAndType	append:(Ljava/lang/String;)Lscala/collection/mutable/StringBuilder;
Method	scala/collection/mutable/StringBuilder.append:(Ljava/lang/String;)Lscala/collection/mutable/StringBuilder;
int	32;
Asciz	(C)Lscala/collection/mutable/StringBuilder;;
NameAndType	append:(C)Lscala/collection/mutable/StringBuilder;
Method	scala/collection/mutable/StringBuilder.append:(C)Lscala/collection/mutable/StringBuilder;
Asciz	scala/xml/dtd/EntityDef;
class	scala/xml/dtd/EntityDef
NameAndType	buildString:(Lscala/collection/mutable/StringBuilder;)Lscala/collection/mutable/StringBuilder;
Method	scala/xml/dtd/EntityDef.buildString:(Lscala/collection/mutable/StringBuilder;)Lscala/collection/mutable/StringBuilder;
int	62;
Asciz	sb;
Asciz	Lscala/collection/mutable/StringBuilder;;
Asciz	copy;
Asciz	(Ljava/lang/String;Lscala/xml/dtd/EntityDef;)Lscala/xml/dtd/ParameterEntityDecl;;
Asciz	<init>;
Asciz	(Ljava/lang/String;Lscala/xml/dtd/EntityDef;)V;
NameAndType	"<init>":(Ljava/lang/String;Lscala/xml/dtd/EntityDef;)V
Method	scala/xml/dtd/ParameterEntityDecl."<init>":(Ljava/lang/String;Lscala/xml/dtd/EntityDef;)V
Asciz	hashCode;
Asciz	()I;
Asciz	scala/runtime/ScalaRunTime$;
class	scala/runtime/ScalaRunTime$
Asciz	Lscala/runtime/ScalaRunTime$;;
NameAndType	MODULE$:Lscala/runtime/ScalaRunTime$;
Field	scala/runtime/ScalaRunTime$.MODULE$:Lscala/runtime/ScalaRunTime$;
Asciz	_hashCode;
Asciz	(Lscala/Product;)I;
NameAndType	_hashCode:(Lscala/Product;)I
Method	scala/runtime/ScalaRunTime$._hashCode:(Lscala/Product;)I
Asciz	toString;
Asciz	_toString;
Asciz	(Lscala/Product;)Ljava/lang/String;;
NameAndType	_toString:(Lscala/Product;)Ljava/lang/String;
Method	scala/runtime/ScalaRunTime$._toString:(Lscala/Product;)Ljava/lang/String;
Asciz	equals;
Asciz	(Ljava/lang/Object;)Z;
Asciz	gd5$1;
Asciz	(Ljava/lang/String;Lscala/xml/dtd/EntityDef;)Z;
NameAndType	gd5$1:(Ljava/lang/String;Lscala/xml/dtd/EntityDef;)Z
Method	scala/xml/dtd/ParameterEntityDecl.gd5$1:(Ljava/lang/String;Lscala/xml/dtd/EntityDef;)Z
Asciz	scala/Equals;
class	scala/Equals
Asciz	canEqual;
NameAndType	canEqual:(Ljava/lang/Object;)Z
InterfaceMethod	scala/Equals.canEqual:(Ljava/lang/Object;)Z
Asciz	temp23;
Asciz	temp24;
Asciz	temp25;
Asciz	productPrefix;
Asciz	ParameterEntityDecl;
String	ParameterEntityDecl
Asciz	productArity;
Asciz	productElement;
Asciz	(I)Ljava/lang/Object;;
Asciz	java/lang/IndexOutOfBoundsException;
class	java/lang/IndexOutOfBoundsException
Asciz	scala/runtime/BoxesRunTime;
class	scala/runtime/BoxesRunTime
Asciz	boxToInteger;
Asciz	(I)Ljava/lang/Integer;;
NameAndType	boxToInteger:(I)Ljava/lang/Integer;
Method	scala/runtime/BoxesRunTime.boxToInteger:(I)Ljava/lang/Integer;
Asciz	java/lang/Object;
class	java/lang/Object
NameAndType	toString:()Ljava/lang/String;
Method	java/lang/Object.toString:()Ljava/lang/String;
Asciz	(Ljava/lang/String;)V;
NameAndType	"<init>":(Ljava/lang/String;)V
Method	java/lang/IndexOutOfBoundsException."<init>":(Ljava/lang/String;)V
NameAndType	equals:(Ljava/lang/Object;)Z
Method	java/lang/Object.equals:(Ljava/lang/Object;)Z
Asciz	scala/xml/dtd/EntityDecl;
class	scala/xml/dtd/EntityDecl
Asciz	()V;
NameAndType	"<init>":()V
Method	scala/xml/dtd/EntityDecl."<init>":()V
Asciz	$init$;
Asciz	(Lscala/Product;)V;
NameAndType	$init$:(Lscala/Product;)V
Method	scala/Product$class.$init$:(Lscala/Product;)V
Asciz	ScalaSig;
Asciz	Lscala/reflect/ScalaSignature;;
Asciz	bytes;
Asciz	cC\t\tQ'A'/Y7fiXI;jif$Um7\r!a3uI*QABq6d'\"AM\r\1M!A!\tYA\"D\ti!AF]RLG/#fG2\"a\tI!!M\r\1PE*,7\r\tMI!AxZ;di\"AaBKq#oC6,W#\reabBA\tYb!Qe$WMZ;yaa;sS:<'BA!A!E!A!8b[+IA\rtGZ3g+!CA&\t1#AAF]RLG/#fM\"AB\tB%A%Af]R$WM\t)AA\rqJg.;?)\raSF\tAQAFAaAQAIABQ\rBE\n1BY;jYFO]5oOR!G\tgmr!NUBT\"]BAs_>$h(C\tQd!AqC\mZ3\nqj$!D*ue&twMQ;jY,'O;\r!)qhae1O\t\t\"Cw]=1E\tCB\t\r\t\t!aI!9a\tAI\n9AD2paf$C-4bk2$H%M*$SB1\nU*QJT\nk:.Z2lKT!atgn;bi&|g.R\n\tRO\2iK\W\r,be&gnY3\tM!C)q1m9zI,g-Y;miT#A++JC,\tI\t-!7[\"pI$!\tiK!a%sG^\t\"_!!xn;sS:<G#\r\tA!ABa!Z9vC2HC2f!\ty1-e\r\t9!i\8mKtb4`\raZq\nCAi\tIgAAB]fDb%\t\aJ|G-^2u!J,g-=5\"A\:=T!]9\t1gne!!.<b\tirv\t\"w1(o3vGR%/;z+I=\tII=AxZ;dicW-\3oiRqMM^\t1Z!a\"A\njC2b]X/7\ttb4|\racA%QM,'/[1mSj'\r\3%!!!A\t-a)belW\r^3s:$^=EKdcAIAC#qB\n\t\t\"a!\rq1C+y'AB(cUG3ABL71!!$v]$n83QQC?!\"!a\t\rQBA\n)#AbaBdF-O\tIC\rE\t5QBA\ny#Av]\=\tEQ\tMqGk1!AB(qi&|gEsAB%C<aV;qYbBA W\rLq;
Asciz	RuntimeVisibleAnnotations;
Asciz	scala/ScalaObject;
class	scala/ScalaObject
Asciz	scala/Product;
class	scala/Product
Asciz	java/io/Serializable;
class	java/io/Serializable

{
private final java.lang.String name;
  Signature: Ljava/lang/String;

private final scala.xml.dtd.EntityDef entdef;
  Signature: Lscala/xml/dtd/EntityDef;

public static final scala.Function1 tupled();
  Signature: ()Lscala/Function1;
  Code:
   Stack=1, Locals=0, Args_size=0
	getstatic	Field scala/xml/dtd/ParameterEntityDecl$.MODULE$:Lscala/xml/dtd/ParameterEntityDecl$;
	invokevirtual	Method scala/xml/dtd/ParameterEntityDecl$.tupled:()Lscala/Function1;
	areturn
  Labels:

public static final scala.Function1 curry();
  Signature: ()Lscala/Function1;
  Code:
   Stack=1, Locals=0, Args_size=0
	getstatic	Field scala/xml/dtd/ParameterEntityDecl$.MODULE$:Lscala/xml/dtd/ParameterEntityDecl$;
	invokevirtual	Method scala/xml/dtd/ParameterEntityDecl$.curry:()Lscala/Function1;
	areturn
  Labels:
  Deprecated: true

public static final scala.Function1 curried();
  Signature: ()Lscala/Function1;
  Code:
   Stack=1, Locals=0, Args_size=0
	getstatic	Field scala/xml/dtd/ParameterEntityDecl$.MODULE$:Lscala/xml/dtd/ParameterEntityDecl$;
	invokevirtual	Method scala/xml/dtd/ParameterEntityDecl$.curried:()Lscala/Function1;
	areturn
  Labels:

public java.lang.String productElementName(int);
  Signature: (I)Ljava/lang/String;
  Code:
   Stack=2, Locals=2, Args_size=2
	aload_0
	iload_1
	invokestatic	Method scala/Product$class.productElementName:(Lscala/Product;I)Ljava/lang/String;
	areturn
  Labels:
  LocalVariableTable: 
   Start  Length  Slot  Name   Signature
   0      6      0    this       Lscala/xml/dtd/ParameterEntityDecl;
   0      6      1    n       I


public scala.collection.Iterator productIterator();
  Signature: ()Lscala/collection/Iterator;
  Code:
   Stack=1, Locals=1, Args_size=1
	aload_0
	invokestatic	Method scala/Product$class.productIterator:(Lscala/Product;)Lscala/collection/Iterator;
	areturn
  Labels:

public scala.collection.Iterator productElements();
  Signature: ()Lscala/collection/Iterator;
  Code:
   Stack=1, Locals=1, Args_size=1
	aload_0
	invokestatic	Method scala/Product$class.productElements:(Lscala/Product;)Lscala/collection/Iterator;
	areturn
  Labels:
  Deprecated: true

public scala.xml.dtd.EntityDef copy$default$2();
  Signature: ()Lscala/xml/dtd/EntityDef;
  Code:
   Stack=1, Locals=1, Args_size=1
	aload_0
	invokevirtual	Method entdef:()Lscala/xml/dtd/EntityDef;
	areturn
  Labels:

public java.lang.String copy$default$1();
  Signature: ()Ljava/lang/String;
  Code:
   Stack=1, Locals=1, Args_size=1
	aload_0
	invokevirtual	Method name:()Ljava/lang/String;
	areturn
  Labels:

public java.lang.String name();
  Signature: ()Ljava/lang/String;
  Code:
   Stack=1, Locals=1, Args_size=1
	aload_0
	getfield	Field name:Ljava/lang/String;
	areturn
  Labels:

public scala.xml.dtd.EntityDef entdef();
  Signature: ()Lscala/xml/dtd/EntityDef;
  Code:
   Stack=1, Locals=1, Args_size=1
	aload_0
	getfield	Field entdef:Lscala/xml/dtd/EntityDef;
	areturn
  Labels:

public scala.collection.mutable.StringBuilder buildString(scala.collection.mutable.StringBuilder);
  Signature: (Lscala/collection/mutable/StringBuilder;)Lscala/collection/mutable/StringBuilder;
  Code:
   Stack=2, Locals=2, Args_size=2
	aload_1
	ldc	String <!ENTITY % 
	invokevirtual	Method scala/collection/mutable/StringBuilder.append:(Ljava/lang/String;)Lscala/collection/mutable/StringBuilder;
	aload_0
	invokevirtual	Method name:()Ljava/lang/String;
	invokevirtual	Method scala/collection/mutable/StringBuilder.append:(Ljava/lang/String;)Lscala/collection/mutable/StringBuilder;
	ldc	int 32
	invokevirtual	Method scala/collection/mutable/StringBuilder.append:(C)Lscala/collection/mutable/StringBuilder;
	pop
	aload_0
	invokevirtual	Method entdef:()Lscala/xml/dtd/EntityDef;
	aload_1
	invokevirtual	Method scala/xml/dtd/EntityDef.buildString:(Lscala/collection/mutable/StringBuilder;)Lscala/collection/mutable/StringBuilder;
	ldc	int 62
	invokevirtual	Method scala/collection/mutable/StringBuilder.append:(C)Lscala/collection/mutable/StringBuilder;
	areturn
  Labels:
  LocalVariableTable: 
   Start  Length  Slot  Name   Signature
   0      33      0    this       Lscala/xml/dtd/ParameterEntityDecl;
   0      33      1    sb       Lscala/collection/mutable/StringBuilder;


public scala.xml.dtd.ParameterEntityDecl copy(java.lang.String, scala.xml.dtd.EntityDef);
  Signature: (Ljava/lang/String;Lscala/xml/dtd/EntityDef;)Lscala/xml/dtd/ParameterEntityDecl;
  Code:
   Stack=4, Locals=3, Args_size=3
	new	class scala/xml/dtd/ParameterEntityDecl
	dup
	aload_1
	aload_2
	invokespecial	Method "<init>":(Ljava/lang/String;Lscala/xml/dtd/EntityDef;)V
	areturn
  Labels:
  LocalVariableTable: 
   Start  Length  Slot  Name   Signature
   0      10      0    this       Lscala/xml/dtd/ParameterEntityDecl;
   0      10      1    name       Ljava/lang/String;
   0      10      2    entdef       Lscala/xml/dtd/EntityDef;


public int hashCode();
  Signature: ()I
  Code:
   Stack=2, Locals=1, Args_size=1
	getstatic	Field scala/runtime/ScalaRunTime$.MODULE$:Lscala/runtime/ScalaRunTime$;
	aload_0
	invokevirtual	Method scala/runtime/ScalaRunTime$._hashCode:(Lscala/Product;)I
	ireturn
  Labels:

public java.lang.String toString();
  Signature: ()Ljava/lang/String;
  Code:
   Stack=2, Locals=1, Args_size=1
	getstatic	Field scala/runtime/ScalaRunTime$.MODULE$:Lscala/runtime/ScalaRunTime$;
	aload_0
	invokevirtual	Method scala/runtime/ScalaRunTime$._toString:(Lscala/Product;)Ljava/lang/String;
	areturn
  Labels:

public boolean equals(java.lang.Object);
  Signature: (Ljava/lang/Object;)Z
  Code:
   Stack=3, Locals=5, Args_size=2
	aload_0
	aload_1
	if_acmpeq	l1 // iconst_1
	aload_1
	instanceof	class scala/xml/dtd/ParameterEntityDecl
	ifeq	l2 // iconst_0
	aload_1
	checkcast	class scala/xml/dtd/ParameterEntityDecl
	astore_2
	aload_2
	invokevirtual	Method name:()Ljava/lang/String;
	astore_3
	aload_2
	invokevirtual	Method entdef:()Lscala/xml/dtd/EntityDef;
	astore	4
	aload_0
	aload_3
	aload	4
	invokespecial	Method gd5$1:(Ljava/lang/String;Lscala/xml/dtd/EntityDef;)Z
	ifeq	l3 // iconst_0
	aload_1
	checkcast	class scala/xml/dtd/ParameterEntityDecl
	aload_0
	invokeinterface	InterfaceMethod scala/Equals.canEqual:(Ljava/lang/Object;)Z
	goto	l4 // ifeq
l3	iconst_0
	goto	l4 // ifeq
l2	iconst_0
l4	ifeq	l5 // iconst_0
l1	iconst_1
	goto	l6 // ireturn
l5	iconst_0
l6	ireturn
  Labels:
   	l3 = 51 // iconst_0
   	l2 = 55 // iconst_0
   	l4 = 56 // ifeq
   	l1 = 59 // iconst_1
   	l5 = 63 // iconst_0
   	l6 = 64 // ireturn
  LocalVariableTable: 
   Start  Length  Slot  Name   Signature
   0      65      0    this       Lscala/xml/dtd/ParameterEntityDecl;
   17      38      2    temp23       Lscala/xml/dtd/ParameterEntityDecl;
   22      33      3    temp24       Ljava/lang/String;
   28      27      4    temp25       Lscala/xml/dtd/EntityDef;


public java.lang.String productPrefix();
  Signature: ()Ljava/lang/String;
  Code:
   Stack=1, Locals=1, Args_size=1
	ldc	String ParameterEntityDecl
	areturn
  Labels:

public int productArity();
  Signature: ()I
  Code:
   Stack=1, Locals=1, Args_size=1
	iconst_2
	ireturn
  Labels:

public java.lang.Object productElement(int);
  Signature: (I)Ljava/lang/Object;
  Code:
   Stack=3, Locals=2, Args_size=2
	iload_1
	tableswitch{ //0 to 1
		0: 46;
		1: 39;
		default: 24 }
	new	class java/lang/IndexOutOfBoundsException
	dup
	iload_1
	invokestatic	Method scala/runtime/BoxesRunTime.boxToInteger:(I)Ljava/lang/Integer;
	invokevirtual	Method java/lang/Object.toString:()Ljava/lang/String;
	invokespecial	Method java/lang/IndexOutOfBoundsException."<init>":(Ljava/lang/String;)V
	athrow
	aload_0
	invokevirtual	Method entdef:()Lscala/xml/dtd/EntityDef;
	goto	l1 // areturn
	aload_0
	invokevirtual	Method name:()Ljava/lang/String;
l1	areturn
  Labels:
   	l1 = 50 // areturn

public boolean canEqual(java.lang.Object);
  Signature: (Ljava/lang/Object;)Z
  Code:
   Stack=1, Locals=2, Args_size=2
	aload_1
	instanceof	class scala/xml/dtd/ParameterEntityDecl
	ireturn
  Labels:

private final boolean gd5$1(java.lang.String, scala.xml.dtd.EntityDef);
  Signature: (Ljava/lang/String;Lscala/xml/dtd/EntityDef;)Z
  Code:
   Stack=2, Locals=5, Args_size=3
	aload_1
	aload_0
	invokevirtual	Method name:()Ljava/lang/String;
	astore_3
	dup
	ifnonnull	l1 // aload_3
	pop
	aload_3
	ifnull	l2 // aload_2
	goto	l3 // iconst_0
l1	aload_3
	invokevirtual	Method java/lang/Object.equals:(Ljava/lang/Object;)Z
	ifeq	l3 // iconst_0
l2	aload_2
	aload_0
	invokevirtual	Method entdef:()Lscala/xml/dtd/EntityDef;
	astore	4
	dup
	ifnonnull	l4 // aload
	pop
	aload	4
	ifnull	l5 // iconst_1
	goto	l3 // iconst_0
l4	aload	4
	invokevirtual	Method java/lang/Object.equals:(Ljava/lang/Object;)Z
	ifeq	l3 // iconst_0
l5	iconst_1
	goto	l6 // ireturn
l3	iconst_0
l6	ireturn
  Labels:
   	l1 = 18 // aload_3
   	l2 = 25 // aload_2
   	l4 = 45 // aload
   	l5 = 53 // iconst_1
   	l3 = 57 // iconst_0
   	l6 = 58 // ireturn

public scala.xml.dtd.ParameterEntityDecl(java.lang.String, scala.xml.dtd.EntityDef);
  Signature: (Ljava/lang/String;Lscala/xml/dtd/EntityDef;)V
  Code:
   Stack=2, Locals=3, Args_size=3
	aload_0
	aload_1
	putfield	Field name:Ljava/lang/String;
	aload_0
	aload_2
	putfield	Field entdef:Lscala/xml/dtd/EntityDef;
	aload_0
	invokespecial	Method scala/xml/dtd/EntityDecl."<init>":()V
	aload_0
	invokestatic	Method scala/Product$class.$init$:(Lscala/Product;)V
	return
  Labels:
  LocalVariableTable: 
   Start  Length  Slot  Name   Signature
   0      19      0    this       Lscala/xml/dtd/ParameterEntityDecl;
   0      19      1    name       Ljava/lang/String;
   0      19      2    entdef       Lscala/xml/dtd/EntityDef;


}

