Compiled from "ContentModel.scala"
public final class scala.xml.dtd.PCDATA extends java.lang.Object
  SourceFile: "ContentModel.scala"
  ScalaSig: length = 0x21E
   05 00 56 07 05 01 02 FFFFFF88 42 09 01 06 50 43 44 41
   54 41 0A 02 03 04 01 03 64 74 64 0A 02 05 06 01
   03 78 6D 6C 0A 01 07 01 05 73 63 61 6C 61 03 00
   10 02 0A 0B 0D 01 02 06 08 0C 02 FFFFFF84 FFFFFF80 FFFFFF80 FFFFFF88 42
   0D 02 06 50 43 44 41 54 41 13 04 0B 0E 11 15 10
   02 0A 0F 09 02 10 02 02 0C 43 6F 6E 74 65 6E 74
   4D 6F 64 65 6C 10 02 12 13 0D 01 06 09 02 14 06
   02 0B 53 63 61 6C 61 4F 62 6A 65 63 74 10 02 12
   16 09 02 17 06 02 07 50 72 6F 64 75 63 74 08 05
   19 0B FFFFFF84 00 1A 01 06 3C 69 6E 69 74 3E 14 01 09
   08 05 1C 0B FFFFFF84 20 1D 01 0B 62 75 69 6C 64 53 74
   72 69 6E 67 14 02 1E 2A 10 02 1F 27 0E 02 20 25
   0E 02 21 24 0D 01 22 0A 02 23 08 01 06 3C 72 6F
   6F 74 3E 09 01 07 09 02 26 06 01 07 70 61 63 6B
   61 67 65 09 02 28 29 02 0D 53 74 72 69 6E 67 42
   75 69 6C 64 65 72 0A 02 26 06 08 05 2B 1B FFFFFFC0 00
   1E 01 02 73 62 08 08 2D 0B FFFFFF84 FFFFFF80 FFFFFF80 FFFFFF84 20 2E 01
   0D 70 72 6F 64 75 63 74 50 72 65 66 69 78 15 01
   2F 10 02 30 35 0D 01 31 0A 02 32 33 01 04 6C 61
   6E 67 0A 01 34 01 04 6A 61 76 61 09 02 36 31 02
   06 53 74 72 69 6E 67 08 08 38 0B FFFFFF84 FFFFFF80 FFFFFF80 FFFFFF84 20
   39 01 0C 70 72 6F 64 75 63 74 41 72 69 74 79 15
   01 3A 10 02 12 3B 09 02 3C 06 02 03 49 6E 74 08
   08 3E 0B FFFFFF84 FFFFFF80 FFFFFF80 FFFFFF84 20 3F 01 0E 70 72 6F 64 75
   63 74 45 6C 65 6D 65 6E 74 14 02 40 43 10 02 12
   41 09 02 42 06 02 03 41 6E 79 08 07 44 3D FFFFFF81 FFFFFF80
   FFFFFFC0 00 3A 01 03 78 24 31 08 08 46 0B FFFFFF84 FFFFFF80 FFFFFF80 FFFFFF84
   20 47 01 08 63 61 6E 45 71 75 61 6C 14 02 48 4B
   10 02 12 49 09 02 4A 06 02 07 42 6F 6F 6C 65 61
   6E 08 07 44 45 FFFFFF81 FFFFFF80 FFFFFFC0 00 40 08 08 4D 0B FFFFFF84 FFFFFF80
   FFFFFF80 FFFFFF84 08 4E 01 0B 72 65 61 64 52 65 73 6F 6C 76
   65 14 01 4F 10 02 30 50 09 02 51 31 02 06 4F 62
   6A 65 63 74 28 02 0B 53 10 02 12 54 09 02 55 06
   02 0C 73 65 72 69 61 6C 69 7A 61 62 6C 65 
  minor version: 0
  major version: 49
  Constant pool:
Asciz	SourceFile;
Asciz	ContentModel.scala;
Asciz	productElements;
Asciz	()Lscala/collection/Iterator;;
Asciz	Code;
Asciz	scala/xml/dtd/PCDATA$;
class	scala/xml/dtd/PCDATA$
Asciz	MODULE$;
Asciz	Lscala/xml/dtd/PCDATA$;;
NameAndType	MODULE$:Lscala/xml/dtd/PCDATA$;
Field	scala/xml/dtd/PCDATA$.MODULE$:Lscala/xml/dtd/PCDATA$;
NameAndType	productElements:()Lscala/collection/Iterator;
Method	scala/xml/dtd/PCDATA$.productElements:()Lscala/collection/Iterator;
Asciz	Deprecated;
Asciz	productIterator;
NameAndType	productIterator:()Lscala/collection/Iterator;
Method	scala/xml/dtd/PCDATA$.productIterator:()Lscala/collection/Iterator;
Asciz	productElementName;
Asciz	(I)Ljava/lang/String;;
NameAndType	productElementName:(I)Ljava/lang/String;
Method	scala/xml/dtd/PCDATA$.productElementName:(I)Ljava/lang/String;
Asciz	canEqual;
Asciz	(Ljava/lang/Object;)Z;
NameAndType	canEqual:(Ljava/lang/Object;)Z
Method	scala/xml/dtd/PCDATA$.canEqual:(Ljava/lang/Object;)Z
Asciz	productElement;
Asciz	(I)Ljava/lang/Object;;
NameAndType	productElement:(I)Ljava/lang/Object;
Method	scala/xml/dtd/PCDATA$.productElement:(I)Ljava/lang/Object;
Asciz	productArity;
Asciz	()I;
NameAndType	productArity:()I
Method	scala/xml/dtd/PCDATA$.productArity:()I
Asciz	productPrefix;
Asciz	()Ljava/lang/String;;
NameAndType	productPrefix:()Ljava/lang/String;
Method	scala/xml/dtd/PCDATA$.productPrefix:()Ljava/lang/String;
Asciz	buildString;
Asciz	(Lscala/collection/mutable/StringBuilder;)Lscala/collection/mutable/StringBuilder;;
NameAndType	buildString:(Lscala/collection/mutable/StringBuilder;)Lscala/collection/mutable/StringBuilder;
Method	scala/xml/dtd/PCDATA$.buildString:(Lscala/collection/mutable/StringBuilder;)Lscala/collection/mutable/StringBuilder;
Asciz	ScalaSig;
Asciz	scala/xml/dtd/PCDATA;
class	scala/xml/dtd/PCDATA
Asciz	java/lang/Object;
class	java/lang/Object

{
public static final scala.collection.Iterator productElements();
  Signature: ()Lscala/collection/Iterator;
  Code:
   Stack=1, Locals=0, Args_size=0
	getstatic	Field scala/xml/dtd/PCDATA$.MODULE$:Lscala/xml/dtd/PCDATA$;
	invokevirtual	Method scala/xml/dtd/PCDATA$.productElements:()Lscala/collection/Iterator;
	areturn
  Labels:
  Deprecated: true

public static final scala.collection.Iterator productIterator();
  Signature: ()Lscala/collection/Iterator;
  Code:
   Stack=1, Locals=0, Args_size=0
	getstatic	Field scala/xml/dtd/PCDATA$.MODULE$:Lscala/xml/dtd/PCDATA$;
	invokevirtual	Method scala/xml/dtd/PCDATA$.productIterator:()Lscala/collection/Iterator;
	areturn
  Labels:

public static final java.lang.String productElementName(int);
  Signature: (I)Ljava/lang/String;
  Code:
   Stack=2, Locals=1, Args_size=1
	getstatic	Field scala/xml/dtd/PCDATA$.MODULE$:Lscala/xml/dtd/PCDATA$;
	iload_0
	invokevirtual	Method scala/xml/dtd/PCDATA$.productElementName:(I)Ljava/lang/String;
	areturn
  Labels:

public static final boolean canEqual(java.lang.Object);
  Signature: (Ljava/lang/Object;)Z
  Code:
   Stack=2, Locals=1, Args_size=1
	getstatic	Field scala/xml/dtd/PCDATA$.MODULE$:Lscala/xml/dtd/PCDATA$;
	aload_0
	invokevirtual	Method scala/xml/dtd/PCDATA$.canEqual:(Ljava/lang/Object;)Z
	ireturn
  Labels:

public static final java.lang.Object productElement(int);
  Signature: (I)Ljava/lang/Object;
  Code:
   Stack=2, Locals=1, Args_size=1
	getstatic	Field scala/xml/dtd/PCDATA$.MODULE$:Lscala/xml/dtd/PCDATA$;
	iload_0
	invokevirtual	Method scala/xml/dtd/PCDATA$.productElement:(I)Ljava/lang/Object;
	areturn
  Labels:

public static final int productArity();
  Signature: ()I
  Code:
   Stack=1, Locals=0, Args_size=0
	getstatic	Field scala/xml/dtd/PCDATA$.MODULE$:Lscala/xml/dtd/PCDATA$;
	invokevirtual	Method scala/xml/dtd/PCDATA$.productArity:()I
	ireturn
  Labels:

public static final java.lang.String productPrefix();
  Signature: ()Ljava/lang/String;
  Code:
   Stack=1, Locals=0, Args_size=0
	getstatic	Field scala/xml/dtd/PCDATA$.MODULE$:Lscala/xml/dtd/PCDATA$;
	invokevirtual	Method scala/xml/dtd/PCDATA$.productPrefix:()Ljava/lang/String;
	areturn
  Labels:

public static final scala.collection.mutable.StringBuilder buildString(scala.collection.mutable.StringBuilder);
  Signature: (Lscala/collection/mutable/StringBuilder;)Lscala/collection/mutable/StringBuilder;
  Code:
   Stack=2, Locals=1, Args_size=1
	getstatic	Field scala/xml/dtd/PCDATA$.MODULE$:Lscala/xml/dtd/PCDATA$;
	aload_0
	invokevirtual	Method scala/xml/dtd/PCDATA$.buildString:(Lscala/collection/mutable/StringBuilder;)Lscala/collection/mutable/StringBuilder;
	areturn
  Labels:

}

