Compiled from "Decl.scala"
public class scala.xml.dtd.PEReference extends scala.xml.dtd.MarkupDecl implements scala.ScalaObject,scala.Product,java.io.Serializable
  SourceFile: "Decl.scala"
  ScalaSig: length = 0x3DB
   05 00 FFFFFF81 12 06 08 01 02 FFFFFF84 FFFFFF80 FFFFFF80 FFFFFF80 40 09 02 0B
   50 45 52 65 66 65 72 65 6E 63 65 0A 02 03 04 01
   03 64 74 64 0A 02 05 06 01 03 78 6D 6C 0A 01 07
   01 05 73 63 61 6C 61 03 00 13 04 00 0A 0E 12 10
   02 0B 0C 0D 01 02 09 02 0D 02 02 0A 4D 61 72 6B
   75 70 44 65 63 6C 10 02 0F 10 0D 01 06 09 02 11
   06 02 0B 53 63 61 6C 61 4F 62 6A 65 63 74 10 02
   0F 13 09 02 14 06 02 07 50 72 6F 64 75 63 74 08
   08 16 00 FFFFFF82 FFFFFFCA FFFFFF80 FFFFFF84 00 17 01 03 65 6E 74 15 01
   18 10 02 19 1C 0E 02 0F 1A 09 02 1B 06 01 06 50
   72 65 64 65 66 09 02 1D 1E 02 06 53 74 72 69 6E
   67 0A 02 1B 06 08 08 20 00 FFFFFF82 FFFFFF88 FFFFFFA0 FFFFFF80 04 18 01
   04 65 6E 74 20 08 05 22 00 FFFFFF84 00 23 01 06 3C 69
   6E 69 74 3E 14 02 24 25 10 02 0B 00 08 05 16 21
   FFFFFFC0 00 18 08 05 27 00 FFFFFF84 20 28 01 0B 62 75 69 6C
   64 53 74 72 69 6E 67 14 02 29 35 10 02 2A 32 0E
   02 2B 30 0E 02 2C 2F 0D 01 2D 0A 02 2E 08 01 06
   3C 72 6F 6F 74 3E 09 01 07 09 02 31 06 01 07 70
   61 63 6B 61 67 65 09 02 33 34 02 0D 53 74 72 69
   6E 67 42 75 69 6C 64 65 72 0A 02 31 06 08 05 36
   26 FFFFFFC0 00 29 01 02 73 62 08 07 38 00 FFFFFF81 FFFFFF80 FFFFFF84 00
   39 01 04 63 6F 70 79 14 02 24 3A 08 07 16 37 FFFFFF90
   FFFFFF80 FFFFFFC0 00 18 08 07 3C 00 FFFFFF91 FFFFFF80 FFFFFF84 00 3D 01 0E 63
   6F 70 79 24 64 65 66 61 75 6C 74 24 31 15 01 3E
   2A 02 18 3F 2B 01 40 10 02 41 46 0D 01 42 0A 02
   43 44 01 09 75 6E 63 68 65 63 6B 65 64 0A 02 45
   06 01 0A 61 6E 6E 6F 74 61 74 69 6F 6E 09 02 47
   42 02 11 75 6E 63 68 65 63 6B 65 64 56 61 72 69
   61 6E 63 65 08 08 49 00 FFFFFF84 FFFFFF80 FFFFFF80 FFFFFF84 20 4A 01 08
   68 61 73 68 43 6F 64 65 14 01 4B 10 02 0F 4C 09
   02 4D 06 02 03 49 6E 74 08 08 4F 00 FFFFFF84 FFFFFF80 FFFFFF80 FFFFFF84
   20 50 01 08 74 6F 53 74 72 69 6E 67 14 01 18 08
   08 52 00 FFFFFF84 FFFFFF80 FFFFFF80 FFFFFF84 20 53 01 06 65 71 75 61 6C
   73 14 02 54 57 10 02 0F 55 09 02 56 06 02 07 42
   6F 6F 6C 65 61 6E 08 07 58 51 FFFFFF81 FFFFFF80 FFFFFFC0 00 59 01
   03 78 24 31 10 02 0F 5A 09 02 5B 06 02 03 41 6E
   79 08 08 5D 00 FFFFFF84 FFFFFF80 FFFFFF80 FFFFFF84 20 5E 01 0D 70 72 6F
   64 75 63 74 50 72 65 66 69 78 15 01 5F 10 02 60
   65 0D 01 61 0A 02 62 63 01 04 6C 61 6E 67 0A 01
   64 01 04 6A 61 76 61 09 02 1D 61 08 08 67 00 FFFFFF84
   FFFFFF80 FFFFFF80 FFFFFF84 20 68 01 0C 70 72 6F 64 75 63 74 41 72
   69 74 79 15 01 4B 08 08 6A 00 FFFFFF84 FFFFFF80 FFFFFF80 FFFFFF84 20 6B
   01 0E 70 72 6F 64 75 63 74 45 6C 65 6D 65 6E 74
   14 02 59 6C 08 07 58 69 FFFFFF81 FFFFFF80 FFFFFFC0 00 4B 08 08 6E
   00 FFFFFF84 FFFFFF80 FFFFFF80 FFFFFF84 20 6F 01 12 70 72 6F 64 75 63 74
   45 6C 65 6D 65 6E 74 4E 61 6D 65 14 02 5F 70 08
   07 58 6D FFFFFF81 FFFFFF80 FFFFFFC0 00 4B 08 08 72 00 FFFFFF84 FFFFFF80 FFFFFF80 FFFFFF84
   20 73 01 08 63 61 6E 45 71 75 61 6C 14 02 54 74
   08 07 58 71 FFFFFF81 FFFFFF80 FFFFFFC0 00 59 28 02 00 76 10 02 0F
   77 09 02 78 06 02 0C 73 65 72 69 61 6C 69 7A 61
   62 6C 65 07 07 7A 02 FFFFFF81 FFFFFF80 FFFFFF88 02 7B 01 0B 50 45
   52 65 66 65 72 65 6E 63 65 10 02 0B 7C 06 08 01
   02 FFFFFF84 FFFFFF81 FFFFFF80 FFFFFF88 02 7D 13 05 7C 7E FFFFFF81 01 0E 10 02
   60 7F 09 03 FFFFFF81 00 61 02 06 4F 62 6A 65 63 74 10
   05 0F FFFFFF81 02 18 24 09 03 FFFFFF81 03 06 02 09 46 75 6E
   63 74 69 6F 6E 31 08 06 22 7C FFFFFF84 00 FFFFFF81 05 14 01
   7B 08 09 FFFFFF81 07 7C FFFFFF81 FFFFFF80 FFFFFF84 40 FFFFFF81 08 01 05 61 70
   70 6C 79 14 03 24 FFFFFF81 09 08 06 16 FFFFFF81 06 FFFFFFC0 00 18
   08 09 FFFFFF81 0B 7C FFFFFF81 FFFFFF80 FFFFFF84 40 FFFFFF81 0C 01 07 75 6E 61
   70 70 6C 79 14 04 FFFFFF81 0D FFFFFF81 10 10 04 0F FFFFFF81 0E 18
   09 03 FFFFFF81 0F 06 02 06 4F 70 74 69 6F 6E 08 07 FFFFFF81
   11 FFFFFF81 0A FFFFFFC0 00 24 01 03 78 24 30 
  minor version: 0
  major version: 49
  Constant pool:
Asciz	SourceFile;
Asciz	Decl.scala;
Asciz	andThen;
Asciz	(Lscala/Function1;)Lscala/Function1;;
Asciz	Code;
Asciz	scala/xml/dtd/PEReference$;
class	scala/xml/dtd/PEReference$
Asciz	MODULE$;
Asciz	Lscala/xml/dtd/PEReference$;;
NameAndType	MODULE$:Lscala/xml/dtd/PEReference$;
Field	scala/xml/dtd/PEReference$.MODULE$:Lscala/xml/dtd/PEReference$;
NameAndType	andThen:(Lscala/Function1;)Lscala/Function1;
Method	scala/xml/dtd/PEReference$.andThen:(Lscala/Function1;)Lscala/Function1;
Asciz	compose;
NameAndType	compose:(Lscala/Function1;)Lscala/Function1;
Method	scala/xml/dtd/PEReference$.compose:(Lscala/Function1;)Lscala/Function1;
Asciz	ent;
Asciz	Ljava/lang/String;;
Asciz	productIterator;
Asciz	()Lscala/collection/Iterator;;
Asciz	LineNumberTable;
Asciz	scala/Product$class;
class	scala/Product$class
Asciz	(Lscala/Product;)Lscala/collection/Iterator;;
NameAndType	productIterator:(Lscala/Product;)Lscala/collection/Iterator;
Method	scala/Product$class.productIterator:(Lscala/Product;)Lscala/collection/Iterator;
Asciz	productElements;
NameAndType	productElements:(Lscala/Product;)Lscala/collection/Iterator;
Method	scala/Product$class.productElements:(Lscala/Product;)Lscala/collection/Iterator;
Asciz	Deprecated;
Asciz	copy$default$1;
Asciz	()Ljava/lang/String;;
Asciz	scala/xml/dtd/PEReference;
class	scala/xml/dtd/PEReference
NameAndType	ent:()Ljava/lang/String;
Method	scala/xml/dtd/PEReference.ent:()Ljava/lang/String;
NameAndType	ent:Ljava/lang/String;
Field	scala/xml/dtd/PEReference.ent:Ljava/lang/String;
Asciz	buildString;
Asciz	(Lscala/collection/mutable/StringBuilder;)Lscala/collection/mutable/StringBuilder;;
int	37;
Asciz	scala/collection/mutable/StringBuilder;
class	scala/collection/mutable/StringBuilder
Asciz	append;
Asciz	(C)Lscala/collection/mutable/StringBuilder;;
NameAndType	append:(C)Lscala/collection/mutable/StringBuilder;
Method	scala/collection/mutable/StringBuilder.append:(C)Lscala/collection/mutable/StringBuilder;
Asciz	(Ljava/lang/String;)Lscala/collection/mutable/StringBuilder;;
NameAndType	append:(Ljava/lang/String;)Lscala/collection/mutable/StringBuilder;
Method	scala/collection/mutable/StringBuilder.append:(Ljava/lang/String;)Lscala/collection/mutable/StringBuilder;
int	59;
Asciz	this;
Asciz	Lscala/xml/dtd/PEReference;;
Asciz	sb;
Asciz	Lscala/collection/mutable/StringBuilder;;
Asciz	LocalVariableTable;
Asciz	copy;
Asciz	(Ljava/lang/String;)Lscala/xml/dtd/PEReference;;
Asciz	<init>;
Asciz	(Ljava/lang/String;)V;
NameAndType	"<init>":(Ljava/lang/String;)V
Method	scala/xml/dtd/PEReference."<init>":(Ljava/lang/String;)V
Asciz	hashCode;
Asciz	()I;
Asciz	scala/runtime/ScalaRunTime$;
class	scala/runtime/ScalaRunTime$
Asciz	Lscala/runtime/ScalaRunTime$;;
NameAndType	MODULE$:Lscala/runtime/ScalaRunTime$;
Field	scala/runtime/ScalaRunTime$.MODULE$:Lscala/runtime/ScalaRunTime$;
Asciz	_hashCode;
Asciz	(Lscala/Product;)I;
NameAndType	_hashCode:(Lscala/Product;)I
Method	scala/runtime/ScalaRunTime$._hashCode:(Lscala/Product;)I
Asciz	toString;
Asciz	_toString;
Asciz	(Lscala/Product;)Ljava/lang/String;;
NameAndType	_toString:(Lscala/Product;)Ljava/lang/String;
Method	scala/runtime/ScalaRunTime$._toString:(Lscala/Product;)Ljava/lang/String;
Asciz	equals;
Asciz	(Ljava/lang/Object;)Z;
Asciz	gd10$1;
Asciz	(Ljava/lang/String;)Z;
NameAndType	gd10$1:(Ljava/lang/String;)Z
Method	scala/xml/dtd/PEReference.gd10$1:(Ljava/lang/String;)Z
Asciz	scala/Equals;
class	scala/Equals
Asciz	canEqual;
NameAndType	canEqual:(Ljava/lang/Object;)Z
InterfaceMethod	scala/Equals.canEqual:(Ljava/lang/Object;)Z
Asciz	temp55;
Asciz	Ljava/lang/Object;;
Asciz	temp56;
Asciz	temp57;
Asciz	ent$1;
Asciz	productPrefix;
Asciz	PEReference;
String	PEReference
Asciz	productArity;
Asciz	productElement;
Asciz	(I)Ljava/lang/Object;;
Asciz	java/lang/IndexOutOfBoundsException;
class	java/lang/IndexOutOfBoundsException
Asciz	scala/runtime/BoxesRunTime;
class	scala/runtime/BoxesRunTime
Asciz	boxToInteger;
Asciz	(I)Ljava/lang/Integer;;
NameAndType	boxToInteger:(I)Ljava/lang/Integer;
Method	scala/runtime/BoxesRunTime.boxToInteger:(I)Ljava/lang/Integer;
Asciz	java/lang/Object;
class	java/lang/Object
NameAndType	toString:()Ljava/lang/String;
Method	java/lang/Object.toString:()Ljava/lang/String;
Method	java/lang/IndexOutOfBoundsException."<init>":(Ljava/lang/String;)V
Asciz	temp58;
Asciz	I;
Asciz	productElementName;
Asciz	(I)Ljava/lang/String;;
String	ent
Asciz	temp59;
NameAndType	equals:(Ljava/lang/Object;)Z
Method	java/lang/Object.equals:(Ljava/lang/Object;)Z
Asciz	scala/xml/dtd/MarkupDecl;
class	scala/xml/dtd/MarkupDecl
Asciz	()V;
NameAndType	"<init>":()V
Method	scala/xml/dtd/MarkupDecl."<init>":()V
Asciz	$init$;
Asciz	(Lscala/Product;)V;
NameAndType	$init$:(Lscala/Product;)V
Method	scala/Product$class.$init$:(Lscala/Product;)V
Asciz	scala/xml/Utility$;
class	scala/xml/Utility$
Asciz	Lscala/xml/Utility$;;
NameAndType	MODULE$:Lscala/xml/Utility$;
Field	scala/xml/Utility$.MODULE$:Lscala/xml/Utility$;
Asciz	scala/xml/parsing/TokenTests;
class	scala/xml/parsing/TokenTests
Asciz	isName;
NameAndType	isName:(Ljava/lang/String;)Z
InterfaceMethod	scala/xml/parsing/TokenTests.isName:(Ljava/lang/String;)Z
Asciz	java/lang/IllegalArgumentException;
class	java/lang/IllegalArgumentException
Asciz	ent must be an XML Name;
String	ent must be an XML Name
Method	java/lang/IllegalArgumentException."<init>":(Ljava/lang/String;)V
Asciz	ScalaSig;
Asciz	scala/ScalaObject;
class	scala/ScalaObject
Asciz	scala/Product;
class	scala/Product
Asciz	java/io/Serializable;
class	java/io/Serializable

{
private final java.lang.String ent;
  Signature: Ljava/lang/String;

public static final scala.Function1 andThen(scala.Function1);
  Signature: (Lscala/Function1;)Lscala/Function1;
  Code:
   Stack=2, Locals=1, Args_size=1
	getstatic	Field scala/xml/dtd/PEReference$.MODULE$:Lscala/xml/dtd/PEReference$;
	aload_0
	invokevirtual	Method scala/xml/dtd/PEReference$.andThen:(Lscala/Function1;)Lscala/Function1;
	areturn
  Labels:

public static final scala.Function1 compose(scala.Function1);
  Signature: (Lscala/Function1;)Lscala/Function1;
  Code:
   Stack=2, Locals=1, Args_size=1
	getstatic	Field scala/xml/dtd/PEReference$.MODULE$:Lscala/xml/dtd/PEReference$;
	aload_0
	invokevirtual	Method scala/xml/dtd/PEReference$.compose:(Lscala/Function1;)Lscala/Function1;
	areturn
  Labels:

public scala.collection.Iterator productIterator();
  Signature: ()Lscala/collection/Iterator;
  Code:
   Stack=1, Locals=1, Args_size=1
	aload_0
	invokestatic	Method scala/Product$class.productIterator:(Lscala/Product;)Lscala/collection/Iterator;
	areturn
  Labels:

public scala.collection.Iterator productElements();
  Signature: ()Lscala/collection/Iterator;
  Code:
   Stack=1, Locals=1, Args_size=1
	aload_0
	invokestatic	Method scala/Product$class.productElements:(Lscala/Product;)Lscala/collection/Iterator;
	areturn
  Labels:
  Deprecated: true

public java.lang.String copy$default$1();
  Signature: ()Ljava/lang/String;
  Code:
   Stack=1, Locals=1, Args_size=1
	aload_0
	invokevirtual	Method ent:()Ljava/lang/String;
	areturn
  Labels:

public java.lang.String ent();
  Signature: ()Ljava/lang/String;
  Code:
   Stack=1, Locals=1, Args_size=1
	aload_0
	getfield	Field ent:Ljava/lang/String;
	areturn
  Labels:

public scala.collection.mutable.StringBuilder buildString(scala.collection.mutable.StringBuilder);
  Signature: (Lscala/collection/mutable/StringBuilder;)Lscala/collection/mutable/StringBuilder;
  Code:
   Stack=2, Locals=2, Args_size=2
	aload_1
	ldc	int 37
	invokevirtual	Method scala/collection/mutable/StringBuilder.append:(C)Lscala/collection/mutable/StringBuilder;
	aload_0
	invokevirtual	Method ent:()Ljava/lang/String;
	invokevirtual	Method scala/collection/mutable/StringBuilder.append:(Ljava/lang/String;)Lscala/collection/mutable/StringBuilder;
	ldc	int 59
	invokevirtual	Method scala/collection/mutable/StringBuilder.append:(C)Lscala/collection/mutable/StringBuilder;
	areturn
  Labels:
  LocalVariableTable: 
   Start  Length  Slot  Name   Signature
   0      19      0    this       Lscala/xml/dtd/PEReference;
   0      19      1    sb       Lscala/collection/mutable/StringBuilder;


public scala.xml.dtd.PEReference copy(java.lang.String);
  Signature: (Ljava/lang/String;)Lscala/xml/dtd/PEReference;
  Code:
   Stack=3, Locals=2, Args_size=2
	new	class scala/xml/dtd/PEReference
	dup
	aload_1
	invokespecial	Method "<init>":(Ljava/lang/String;)V
	areturn
  Labels:
  LocalVariableTable: 
   Start  Length  Slot  Name   Signature
   0      9      0    this       Lscala/xml/dtd/PEReference;
   0      9      1    ent       Ljava/lang/String;


public int hashCode();
  Signature: ()I
  Code:
   Stack=2, Locals=1, Args_size=1
	getstatic	Field scala/runtime/ScalaRunTime$.MODULE$:Lscala/runtime/ScalaRunTime$;
	aload_0
	invokevirtual	Method scala/runtime/ScalaRunTime$._hashCode:(Lscala/Product;)I
	ireturn
  Labels:

public java.lang.String toString();
  Signature: ()Ljava/lang/String;
  Code:
   Stack=2, Locals=1, Args_size=1
	getstatic	Field scala/runtime/ScalaRunTime$.MODULE$:Lscala/runtime/ScalaRunTime$;
	aload_0
	invokevirtual	Method scala/runtime/ScalaRunTime$._toString:(Lscala/Product;)Ljava/lang/String;
	areturn
  Labels:

public boolean equals(java.lang.Object);
  Signature: (Ljava/lang/Object;)Z
  Code:
   Stack=2, Locals=6, Args_size=2
	aload_0
	aload_1
	if_acmpeq	l1 // iconst_1
	aload_1
	astore_2
	aload_2
	instanceof	class scala/xml/dtd/PEReference
	ifeq	l2 // iconst_0
	aload_2
	checkcast	class scala/xml/dtd/PEReference
	astore_3
	aload_3
	invokevirtual	Method ent:()Ljava/lang/String;
	astore	4
	aload	4
	astore	5
	aload_0
	aload	5
	invokespecial	Method gd10$1:(Ljava/lang/String;)Z
	ifeq	l3 // iconst_0
	aload_1
	checkcast	class scala/xml/dtd/PEReference
	aload_0
	invokeinterface	InterfaceMethod scala/Equals.canEqual:(Ljava/lang/Object;)Z
	goto	l4 // ifeq
l3	iconst_0
	goto	l4 // ifeq
l2	iconst_0
l4	ifeq	l5 // iconst_0
l1	iconst_1
	goto	l6 // ireturn
l5	iconst_0
l6	ireturn
  Labels:
   	l3 = 51 // iconst_0
   	l2 = 55 // iconst_0
   	l4 = 56 // ifeq
   	l1 = 59 // iconst_1
   	l5 = 63 // iconst_0
   	l6 = 64 // ireturn
  LocalVariableTable: 
   Start  Length  Slot  Name   Signature
   0      65      0    this       Lscala/xml/dtd/PEReference;
   7      52      2    temp55       Ljava/lang/Object;
   19      36      3    temp56       Lscala/xml/dtd/PEReference;
   25      30      4    temp57       Ljava/lang/String;
   29      26      5    ent$1       Ljava/lang/String;


public java.lang.String productPrefix();
  Signature: ()Ljava/lang/String;
  Code:
   Stack=1, Locals=1, Args_size=1
	ldc	String PEReference
	areturn
  Labels:

public int productArity();
  Signature: ()I
  Code:
   Stack=1, Locals=1, Args_size=1
	iconst_1
	ireturn
  Labels:

public java.lang.Object productElement(int);
  Signature: (I)Ljava/lang/Object;
  Code:
   Stack=3, Locals=3, Args_size=2
	iload_1
	istore_2
	iload_2
	iconst_0
	if_icmpne	l1 // new
	aload_0
	invokevirtual	Method ent:()Ljava/lang/String;
	areturn
l1	new	class java/lang/IndexOutOfBoundsException
	dup
	iload_1
	invokestatic	Method scala/runtime/BoxesRunTime.boxToInteger:(I)Ljava/lang/Integer;
	invokevirtual	Method java/lang/Object.toString:()Ljava/lang/String;
	invokespecial	Method java/lang/IndexOutOfBoundsException."<init>":(Ljava/lang/String;)V
	athrow
  Labels:
   	l1 = 12 // new
  LocalVariableTable: 
   Start  Length  Slot  Name   Signature
   0      27      0    this       Lscala/xml/dtd/PEReference;
   2      25      2    temp58       I


public java.lang.String productElementName(int);
  Signature: (I)Ljava/lang/String;
  Code:
   Stack=3, Locals=3, Args_size=2
	iload_1
	istore_2
	iload_2
	iconst_0
	if_icmpne	l1 // new
	ldc	String ent
	areturn
l1	new	class java/lang/IndexOutOfBoundsException
	dup
	iload_1
	invokestatic	Method scala/runtime/BoxesRunTime.boxToInteger:(I)Ljava/lang/Integer;
	invokevirtual	Method java/lang/Object.toString:()Ljava/lang/String;
	invokespecial	Method java/lang/IndexOutOfBoundsException."<init>":(Ljava/lang/String;)V
	athrow
  Labels:
   	l1 = 10 // new
  LocalVariableTable: 
   Start  Length  Slot  Name   Signature
   0      25      0    this       Lscala/xml/dtd/PEReference;
   2      23      2    temp59       I


public boolean canEqual(java.lang.Object);
  Signature: (Ljava/lang/Object;)Z
  Code:
   Stack=1, Locals=2, Args_size=2
	aload_1
	instanceof	class scala/xml/dtd/PEReference
	ireturn
  Labels:

private final boolean gd10$1(java.lang.String);
  Signature: (Ljava/lang/String;)Z
  Code:
   Stack=2, Locals=3, Args_size=2
	aload_1
	aload_0
	invokevirtual	Method ent:()Ljava/lang/String;
	astore_2
	dup
	ifnonnull	l1 // aload_2
	pop
	aload_2
	ifnull	l2 // iconst_1
	goto	l3 // iconst_0
l1	aload_2
	invokevirtual	Method java/lang/Object.equals:(Ljava/lang/Object;)Z
	ifeq	l3 // iconst_0
l2	iconst_1
	goto	l4 // ireturn
l3	iconst_0
l4	ireturn
  Labels:
   	l1 = 18 // aload_2
   	l2 = 25 // iconst_1
   	l3 = 29 // iconst_0
   	l4 = 30 // ireturn

public scala.xml.dtd.PEReference(java.lang.String);
  Signature: (Ljava/lang/String;)V
  Code:
   Stack=3, Locals=2, Args_size=2
	aload_0
	aload_1
	putfield	Field ent:Ljava/lang/String;
	aload_0
	invokespecial	Method scala/xml/dtd/MarkupDecl."<init>":()V
	aload_0
	invokestatic	Method scala/Product$class.$init$:(Lscala/Product;)V
	getstatic	Field scala/xml/Utility$.MODULE$:Lscala/xml/Utility$;
	aload_1
	invokeinterface	InterfaceMethod scala/xml/parsing/TokenTests.isName:(Ljava/lang/String;)Z
	ifeq	l1 // new
	return
l1	new	class java/lang/IllegalArgumentException
	dup
	ldc	String ent must be an XML Name
	invokespecial	Method java/lang/IllegalArgumentException."<init>":(Ljava/lang/String;)V
	athrow
  Labels:
   	l1 = 26 // new
  LocalVariableTable: 
   Start  Length  Slot  Name   Signature
   0      36      0    this       Lscala/xml/dtd/PEReference;
   0      36      1    ent       Ljava/lang/String;


}

