Compiled from "ExternalID.scala"
public class scala.xml.dtd.PublicID extends scala.xml.dtd.ExternalID implements scala.ScalaObject,scala.Product,java.io.Serializable
  SourceFile: "ExternalID.scala"
  ScalaSig: length = 0x42A
   05 00 FFFFFF81 1A 06 08 01 02 FFFFFF84 FFFFFF80 FFFFFF80 FFFFFF80 40 09 02 08
   50 75 62 6C 69 63 49 44 0A 02 03 04 01 03 64 74
   64 0A 02 05 06 01 03 78 6D 6C 0A 01 07 01 05 73
   63 61 6C 61 03 00 13 04 00 0A 0E 12 10 02 0B 0C
   0D 01 02 09 02 0D 02 02 0A 45 78 74 65 72 6E 61
   6C 49 44 10 02 0F 10 0D 01 06 09 02 11 06 02 0B
   53 63 61 6C 61 4F 62 6A 65 63 74 10 02 0F 13 09
   02 14 06 02 07 50 72 6F 64 75 63 74 08 08 16 00
   FFFFFF82 FFFFFFCA FFFFFF80 FFFFFF84 00 17 01 08 70 75 62 6C 69 63 49 64
   15 01 18 10 02 19 1C 0E 02 0F 1A 09 02 1B 06 01
   06 50 72 65 64 65 66 09 02 1D 1E 02 06 53 74 72
   69 6E 67 0A 02 1B 06 08 08 20 00 FFFFFF82 FFFFFF88 FFFFFFA0 FFFFFF80 04
   18 01 09 70 75 62 6C 69 63 49 64 20 08 08 22 00
   FFFFFF82 FFFFFFCA FFFFFF80 FFFFFF84 00 17 01 08 73 79 73 74 65 6D 49 64
   08 08 24 00 FFFFFF82 FFFFFF88 FFFFFFA0 FFFFFF80 04 18 01 09 73 79 73 74
   65 6D 49 64 20 08 05 26 00 FFFFFF84 00 27 01 06 3C 69
   6E 69 74 3E 14 03 28 29 2A 10 02 0B 00 08 05 16
   25 FFFFFFC0 00 18 08 05 22 25 FFFFFFC0 00 18 08 05 2C 00 FFFFFF84
   00 2D 01 05 6C 61 62 65 6C 15 01 2E 10 02 2F 34
   0D 01 30 0A 02 31 32 01 04 6C 61 6E 67 0A 01 33
   01 04 6A 61 76 61 09 02 1D 30 08 05 36 00 FFFFFF84 00
   37 01 09 61 74 74 72 69 62 75 74 65 15 01 38 10
   02 39 3A 0D 01 04 09 02 3B 04 02 08 4D 65 74 61
   44 61 74 61 08 05 3D 00 FFFFFF84 00 3E 01 05 63 68 69
   6C 64 15 01 3F 10 02 40 45 0D 01 41 0A 02 42 43
   01 09 69 6D 6D 75 74 61 62 6C 65 0A 02 44 06 01
   0A 63 6F 6C 6C 65 63 74 69 6F 6E 0A 02 46 41 01
   03 4E 69 6C 08 07 48 00 FFFFFF81 FFFFFF80 FFFFFF84 00 49 01 04 63
   6F 70 79 14 03 28 4A 4B 08 07 16 47 FFFFFF90 FFFFFF80 FFFFFFC0 00
   18 08 07 22 47 FFFFFF90 FFFFFF80 FFFFFFC0 00 18 08 07 4D 00 FFFFFF91 FFFFFF80
   FFFFFF84 00 4E 01 0E 63 6F 70 79 24 64 65 66 61 75 6C
   74 24 31 15 01 4F 2A 02 18 50 2B 01 51 10 02 52
   57 0D 01 53 0A 02 54 55 01 09 75 6E 63 68 65 63
   6B 65 64 0A 02 56 06 01 0A 61 6E 6E 6F 74 61 74
   69 6F 6E 09 02 58 53 02 11 75 6E 63 68 65 63 6B
   65 64 56 61 72 69 61 6E 63 65 08 07 5A 00 FFFFFF91 FFFFFF80
   FFFFFF84 00 4E 01 0E 63 6F 70 79 24 64 65 66 61 75 6C
   74 24 32 08 08 5C 00 FFFFFF84 FFFFFF80 FFFFFF80 FFFFFF84 20 5D 01 08 68
   61 73 68 43 6F 64 65 14 01 5E 10 02 0F 5F 09 02
   60 06 02 03 49 6E 74 08 08 62 00 FFFFFF84 FFFFFF80 FFFFFF80 FFFFFF84 20
   63 01 06 65 71 75 61 6C 73 14 02 64 67 10 02 0F
   65 09 02 66 06 02 07 42 6F 6F 6C 65 61 6E 08 07
   68 61 FFFFFF81 FFFFFF80 FFFFFFC0 00 69 01 03 78 24 31 10 02 0F 6A
   09 02 6B 06 02 03 41 6E 79 08 08 6D 00 FFFFFF84 FFFFFF80 FFFFFF80
   FFFFFF84 20 2D 01 0D 70 72 6F 64 75 63 74 50 72 65 66
   69 78 08 08 6F 00 FFFFFF84 FFFFFF80 FFFFFF80 FFFFFF84 20 70 01 0C 70 72
   6F 64 75 63 74 41 72 69 74 79 15 01 5E 08 08 72
   00 FFFFFF84 FFFFFF80 FFFFFF80 FFFFFF84 20 73 01 0E 70 72 6F 64 75 63 74
   45 6C 65 6D 65 6E 74 14 02 69 74 08 07 68 71 FFFFFF81
   FFFFFF80 FFFFFFC0 00 5E 08 08 76 00 FFFFFF84 FFFFFF80 FFFFFF80 FFFFFF84 20 77 01 08
   63 61 6E 45 71 75 61 6C 14 02 64 78 08 07 68 75
   FFFFFF81 FFFFFF80 FFFFFFC0 00 69 28 02 00 7A 10 02 0F 7B 09 02 7C
   06 02 0C 73 65 72 69 61 6C 69 7A 61 62 6C 65 07
   07 7E 02 FFFFFF81 FFFFFF80 FFFFFF88 02 7F 01 08 50 75 62 6C 69 63
   49 44 10 03 0B FFFFFF81 00 06 09 01 02 FFFFFF84 FFFFFF81 FFFFFF80 FFFFFF88 02
   FFFFFF81 01 13 07 FFFFFF81 00 FFFFFF81 02 FFFFFF81 05 0E 10 03 2F FFFFFF81 03
   09 03 FFFFFF81 04 30 02 06 4F 62 6A 65 63 74 10 06 0F
   FFFFFF81 06 18 18 28 09 03 FFFFFF81 07 06 02 09 46 75 6E 63
   74 69 6F 6E 32 08 07 26 FFFFFF81 00 FFFFFF84 00 FFFFFF81 09 14 01
   7F 08 0A FFFFFF81 0B FFFFFF81 00 FFFFFF81 FFFFFF80 FFFFFF84 40 FFFFFF81 0C 01 05 61
   70 70 6C 79 14 05 28 FFFFFF81 0D FFFFFF81 0E 08 06 16 FFFFFF81 0A
   FFFFFFC0 00 18 08 06 22 FFFFFF81 0A FFFFFFC0 00 18 08 0A FFFFFF81 10 FFFFFF81
   00 FFFFFF81 FFFFFF80 FFFFFF84 40 FFFFFF81 11 01 07 75 6E 61 70 70 6C 79
   14 04 FFFFFF81 12 FFFFFF81 18 10 05 0F FFFFFF81 13 FFFFFF81 15 09 03 FFFFFF81
   14 06 02 04 53 6F 6D 65 10 05 0F FFFFFF81 16 18 18 09
   03 FFFFFF81 17 06 02 06 54 75 70 6C 65 32 08 07 FFFFFF81 19
   FFFFFF81 0F FFFFFFC0 00 28 01 03 78 24 30 
  minor version: 0
  major version: 49
  Constant pool:
Asciz	SourceFile;
Asciz	ExternalID.scala;
Asciz	tupled;
Asciz	()Lscala/Function1;;
Asciz	Code;
Asciz	scala/xml/dtd/PublicID$;
class	scala/xml/dtd/PublicID$
Asciz	MODULE$;
Asciz	Lscala/xml/dtd/PublicID$;;
NameAndType	MODULE$:Lscala/xml/dtd/PublicID$;
Field	scala/xml/dtd/PublicID$.MODULE$:Lscala/xml/dtd/PublicID$;
NameAndType	tupled:()Lscala/Function1;
Method	scala/xml/dtd/PublicID$.tupled:()Lscala/Function1;
Asciz	curry;
NameAndType	curry:()Lscala/Function1;
Method	scala/xml/dtd/PublicID$.curry:()Lscala/Function1;
Asciz	Deprecated;
Asciz	curried;
NameAndType	curried:()Lscala/Function1;
Method	scala/xml/dtd/PublicID$.curried:()Lscala/Function1;
Asciz	systemId;
Asciz	Ljava/lang/String;;
Asciz	publicId;
Asciz	<init>;
Asciz	(Ljava/lang/String;Ljava/lang/String;)V;
Asciz	LineNumberTable;
Asciz	scala/xml/dtd/PublicID;
class	scala/xml/dtd/PublicID
NameAndType	publicId:Ljava/lang/String;
Field	scala/xml/dtd/PublicID.publicId:Ljava/lang/String;
NameAndType	systemId:Ljava/lang/String;
Field	scala/xml/dtd/PublicID.systemId:Ljava/lang/String;
Asciz	scala/xml/dtd/ExternalID;
class	scala/xml/dtd/ExternalID
Asciz	()V;
NameAndType	"<init>":()V
Method	scala/xml/dtd/ExternalID."<init>":()V
Asciz	scala/Product$class;
class	scala/Product$class
Asciz	$init$;
Asciz	(Lscala/Product;)V;
NameAndType	$init$:(Lscala/Product;)V
Method	scala/Product$class.$init$:(Lscala/Product;)V
Asciz	scala/xml/parsing/TokenTests;
class	scala/xml/parsing/TokenTests
Asciz	checkPubID;
Asciz	(Ljava/lang/String;)Z;
NameAndType	checkPubID:(Ljava/lang/String;)Z
InterfaceMethod	scala/xml/parsing/TokenTests.checkPubID:(Ljava/lang/String;)Z
Asciz	java/lang/Object;
class	java/lang/Object
Asciz	equals;
Asciz	(Ljava/lang/Object;)Z;
NameAndType	equals:(Ljava/lang/Object;)Z
Method	java/lang/Object.equals:(Ljava/lang/Object;)Z
Asciz	checkSysID;
NameAndType	checkSysID:(Ljava/lang/String;)Z
InterfaceMethod	scala/xml/parsing/TokenTests.checkSysID:(Ljava/lang/String;)Z
Asciz	java/lang/IllegalArgumentException;
class	java/lang/IllegalArgumentException
Asciz	can't use both \" and ' in systemId;
String	can't use both \" and ' in systemId
Asciz	(Ljava/lang/String;)V;
NameAndType	"<init>":(Ljava/lang/String;)V
Method	java/lang/IllegalArgumentException."<init>":(Ljava/lang/String;)V
Asciz	publicId must consist of PubidChars;
String	publicId must consist of PubidChars
Asciz	this;
Asciz	Lscala/xml/dtd/PublicID;;
Asciz	LocalVariableTable;
Asciz	gd2$1;
Asciz	(Ljava/lang/String;Ljava/lang/String;)Z;
Asciz	()Ljava/lang/String;;
NameAndType	publicId:()Ljava/lang/String;
Method	scala/xml/dtd/PublicID.publicId:()Ljava/lang/String;
NameAndType	systemId:()Ljava/lang/String;
Method	scala/xml/dtd/PublicID.systemId:()Ljava/lang/String;
Asciz	canEqual;
Asciz	productElement;
Asciz	(I)Ljava/lang/Object;;
Asciz	java/lang/IndexOutOfBoundsException;
class	java/lang/IndexOutOfBoundsException
Asciz	scala/runtime/BoxesRunTime;
class	scala/runtime/BoxesRunTime
Asciz	boxToInteger;
Asciz	(I)Ljava/lang/Integer;;
NameAndType	boxToInteger:(I)Ljava/lang/Integer;
Method	scala/runtime/BoxesRunTime.boxToInteger:(I)Ljava/lang/Integer;
Asciz	toString;
NameAndType	toString:()Ljava/lang/String;
Method	java/lang/Object.toString:()Ljava/lang/String;
Method	java/lang/IndexOutOfBoundsException."<init>":(Ljava/lang/String;)V
Asciz	productArity;
Asciz	()I;
Asciz	productPrefix;
Asciz	PublicID;
String	PublicID
NameAndType	gd2$1:(Ljava/lang/String;Ljava/lang/String;)Z
Method	scala/xml/dtd/PublicID.gd2$1:(Ljava/lang/String;Ljava/lang/String;)Z
Asciz	scala/Equals;
class	scala/Equals
NameAndType	canEqual:(Ljava/lang/Object;)Z
InterfaceMethod	scala/Equals.canEqual:(Ljava/lang/Object;)Z
Asciz	temp6;
Asciz	temp7;
Asciz	temp8;
Asciz	hashCode;
Asciz	scala/runtime/ScalaRunTime$;
class	scala/runtime/ScalaRunTime$
Asciz	Lscala/runtime/ScalaRunTime$;;
NameAndType	MODULE$:Lscala/runtime/ScalaRunTime$;
Field	scala/runtime/ScalaRunTime$.MODULE$:Lscala/runtime/ScalaRunTime$;
Asciz	_hashCode;
Asciz	(Lscala/Product;)I;
NameAndType	_hashCode:(Lscala/Product;)I
Method	scala/runtime/ScalaRunTime$._hashCode:(Lscala/Product;)I
Asciz	copy;
Asciz	(Ljava/lang/String;Ljava/lang/String;)Lscala/xml/dtd/PublicID;;
NameAndType	"<init>":(Ljava/lang/String;Ljava/lang/String;)V
Method	scala/xml/dtd/PublicID."<init>":(Ljava/lang/String;Ljava/lang/String;)V
Asciz	child;
Asciz	()Lscala/collection/immutable/Nil$;;
Asciz	scala/collection/immutable/Nil$;
class	scala/collection/immutable/Nil$
Asciz	Lscala/collection/immutable/Nil$;;
NameAndType	MODULE$:Lscala/collection/immutable/Nil$;
Field	scala/collection/immutable/Nil$.MODULE$:Lscala/collection/immutable/Nil$;
Asciz	attribute;
Asciz	()Lscala/xml/MetaData;;
Asciz	scala/xml/Node$;
class	scala/xml/Node$
Asciz	Lscala/xml/Node$;;
NameAndType	MODULE$:Lscala/xml/Node$;
Field	scala/xml/Node$.MODULE$:Lscala/xml/Node$;
Asciz	NoAttributes;
NameAndType	NoAttributes:()Lscala/xml/MetaData;
Method	scala/xml/Node$.NoAttributes:()Lscala/xml/MetaData;
Asciz	label;
Asciz	#PI;
String	#PI
Asciz	copy$default$1;
Asciz	copy$default$2;
Asciz	productElements;
Asciz	()Lscala/collection/Iterator;;
Asciz	(Lscala/Product;)Lscala/collection/Iterator;;
NameAndType	productElements:(Lscala/Product;)Lscala/collection/Iterator;
Method	scala/Product$class.productElements:(Lscala/Product;)Lscala/collection/Iterator;
Asciz	productIterator;
NameAndType	productIterator:(Lscala/Product;)Lscala/collection/Iterator;
Method	scala/Product$class.productIterator:(Lscala/Product;)Lscala/collection/Iterator;
Asciz	ScalaSig;
Asciz	scala/ScalaObject;
class	scala/ScalaObject
Asciz	scala/Product;
class	scala/Product
Asciz	java/io/Serializable;
class	java/io/Serializable

{
private final java.lang.String systemId;
  Signature: Ljava/lang/String;

private final java.lang.String publicId;
  Signature: Ljava/lang/String;

public static final scala.Function1 tupled();
  Signature: ()Lscala/Function1;
  Code:
   Stack=1, Locals=0, Args_size=0
	getstatic	Field scala/xml/dtd/PublicID$.MODULE$:Lscala/xml/dtd/PublicID$;
	invokevirtual	Method scala/xml/dtd/PublicID$.tupled:()Lscala/Function1;
	areturn
  Labels:

public static final scala.Function1 curry();
  Signature: ()Lscala/Function1;
  Code:
   Stack=1, Locals=0, Args_size=0
	getstatic	Field scala/xml/dtd/PublicID$.MODULE$:Lscala/xml/dtd/PublicID$;
	invokevirtual	Method scala/xml/dtd/PublicID$.curry:()Lscala/Function1;
	areturn
  Labels:
  Deprecated: true

public static final scala.Function1 curried();
  Signature: ()Lscala/Function1;
  Code:
   Stack=1, Locals=0, Args_size=0
	getstatic	Field scala/xml/dtd/PublicID$.MODULE$:Lscala/xml/dtd/PublicID$;
	invokevirtual	Method scala/xml/dtd/PublicID$.curried:()Lscala/Function1;
	areturn
  Labels:

public scala.xml.dtd.PublicID(java.lang.String, java.lang.String);
  Signature: (Ljava/lang/String;Ljava/lang/String;)V
  Code:
   Stack=3, Locals=3, Args_size=3
	aload_0
	aload_1
	putfield	Field publicId:Ljava/lang/String;
	aload_0
	aload_2
	putfield	Field systemId:Ljava/lang/String;
	aload_0
	invokespecial	Method scala/xml/dtd/ExternalID."<init>":()V
	aload_0
	invokestatic	Method scala/Product$class.$init$:(Lscala/Product;)V
	aload_0
	aload_1
	invokeinterface	InterfaceMethod scala/xml/parsing/TokenTests.checkPubID:(Ljava/lang/String;)Z
	ifeq	l1 // new
	aload_2
	dup
	pop
	ifnull	l2 // return
	aload_2
	aconst_null
	invokevirtual	Method java/lang/Object.equals:(Ljava/lang/Object;)Z
	ifne	l2 // return
	aload_0
	aload_2
	invokeinterface	InterfaceMethod scala/xml/parsing/TokenTests.checkSysID:(Ljava/lang/String;)Z
	ifeq	l3 // new
l2	return
l3	new	class java/lang/IllegalArgumentException
	dup
	ldc	String can't use both \" and ' in systemId
	invokespecial	Method java/lang/IllegalArgumentException."<init>":(Ljava/lang/String;)V
	athrow
l1	new	class java/lang/IllegalArgumentException
	dup
	ldc	String publicId must consist of PubidChars
	invokespecial	Method java/lang/IllegalArgumentException."<init>":(Ljava/lang/String;)V
	athrow
  Labels:
   	l2 = 52 // return
   	l3 = 53 // new
   	l1 = 63 // new
  LocalVariableTable: 
   Start  Length  Slot  Name   Signature
   0      73      0    this       Lscala/xml/dtd/PublicID;
   0      73      1    publicId       Ljava/lang/String;
   0      73      2    systemId       Ljava/lang/String;


private final boolean gd2$1(java.lang.String, java.lang.String);
  Signature: (Ljava/lang/String;Ljava/lang/String;)Z
  Code:
   Stack=2, Locals=5, Args_size=3
	aload_1
	aload_0
	invokevirtual	Method publicId:()Ljava/lang/String;
	astore_3
	dup
	ifnonnull	l1 // aload_3
	pop
	aload_3
	ifnull	l2 // aload_2
	goto	l3 // iconst_0
l1	aload_3
	invokevirtual	Method java/lang/Object.equals:(Ljava/lang/Object;)Z
	ifeq	l3 // iconst_0
l2	aload_2
	aload_0
	invokevirtual	Method systemId:()Ljava/lang/String;
	astore	4
	dup
	ifnonnull	l4 // aload
	pop
	aload	4
	ifnull	l5 // iconst_1
	goto	l3 // iconst_0
l4	aload	4
	invokevirtual	Method java/lang/Object.equals:(Ljava/lang/Object;)Z
	ifeq	l3 // iconst_0
l5	iconst_1
	goto	l6 // ireturn
l3	iconst_0
l6	ireturn
  Labels:
   	l1 = 18 // aload_3
   	l2 = 25 // aload_2
   	l4 = 45 // aload
   	l5 = 53 // iconst_1
   	l3 = 57 // iconst_0
   	l6 = 58 // ireturn

public boolean canEqual(java.lang.Object);
  Signature: (Ljava/lang/Object;)Z
  Code:
   Stack=1, Locals=2, Args_size=2
	aload_1
	instanceof	class scala/xml/dtd/PublicID
	ireturn
  Labels:

public java.lang.Object productElement(int);
  Signature: (I)Ljava/lang/Object;
  Code:
   Stack=3, Locals=2, Args_size=2
	iload_1
	tableswitch{ //0 to 1
		0: 46;
		1: 39;
		default: 24 }
	new	class java/lang/IndexOutOfBoundsException
	dup
	iload_1
	invokestatic	Method scala/runtime/BoxesRunTime.boxToInteger:(I)Ljava/lang/Integer;
	invokevirtual	Method java/lang/Object.toString:()Ljava/lang/String;
	invokespecial	Method java/lang/IndexOutOfBoundsException."<init>":(Ljava/lang/String;)V
	athrow
	aload_0
	invokevirtual	Method systemId:()Ljava/lang/String;
	goto	l1 // areturn
	aload_0
	invokevirtual	Method publicId:()Ljava/lang/String;
l1	areturn
  Labels:
   	l1 = 50 // areturn

public int productArity();
  Signature: ()I
  Code:
   Stack=1, Locals=1, Args_size=1
	iconst_2
	ireturn
  Labels:

public java.lang.String productPrefix();
  Signature: ()Ljava/lang/String;
  Code:
   Stack=1, Locals=1, Args_size=1
	ldc	String PublicID
	areturn
  Labels:

public boolean equals(java.lang.Object);
  Signature: (Ljava/lang/Object;)Z
  Code:
   Stack=3, Locals=5, Args_size=2
	aload_0
	aload_1
	if_acmpeq	l1 // iconst_1
	aload_1
	instanceof	class scala/xml/dtd/PublicID
	ifeq	l2 // iconst_0
	aload_1
	checkcast	class scala/xml/dtd/PublicID
	astore_2
	aload_2
	invokevirtual	Method publicId:()Ljava/lang/String;
	astore_3
	aload_2
	invokevirtual	Method systemId:()Ljava/lang/String;
	astore	4
	aload_0
	aload_3
	aload	4
	invokespecial	Method gd2$1:(Ljava/lang/String;Ljava/lang/String;)Z
	ifeq	l3 // iconst_0
	aload_1
	checkcast	class scala/xml/dtd/PublicID
	aload_0
	invokeinterface	InterfaceMethod scala/Equals.canEqual:(Ljava/lang/Object;)Z
	goto	l4 // ifeq
l3	iconst_0
	goto	l4 // ifeq
l2	iconst_0
l4	ifeq	l5 // iconst_0
l1	iconst_1
	goto	l6 // ireturn
l5	iconst_0
l6	ireturn
  Labels:
   	l3 = 51 // iconst_0
   	l2 = 55 // iconst_0
   	l4 = 56 // ifeq
   	l1 = 59 // iconst_1
   	l5 = 63 // iconst_0
   	l6 = 64 // ireturn
  LocalVariableTable: 
   Start  Length  Slot  Name   Signature
   0      65      0    this       Lscala/xml/dtd/PublicID;
   17      38      2    temp6       Lscala/xml/dtd/PublicID;
   22      33      3    temp7       Ljava/lang/String;
   28      27      4    temp8       Ljava/lang/String;


public int hashCode();
  Signature: ()I
  Code:
   Stack=2, Locals=1, Args_size=1
	getstatic	Field scala/runtime/ScalaRunTime$.MODULE$:Lscala/runtime/ScalaRunTime$;
	aload_0
	invokevirtual	Method scala/runtime/ScalaRunTime$._hashCode:(Lscala/Product;)I
	ireturn
  Labels:

public scala.xml.dtd.PublicID copy(java.lang.String, java.lang.String);
  Signature: (Ljava/lang/String;Ljava/lang/String;)Lscala/xml/dtd/PublicID;
  Code:
   Stack=4, Locals=3, Args_size=3
	new	class scala/xml/dtd/PublicID
	dup
	aload_1
	aload_2
	invokespecial	Method "<init>":(Ljava/lang/String;Ljava/lang/String;)V
	areturn
  Labels:
  LocalVariableTable: 
   Start  Length  Slot  Name   Signature
   0      10      0    this       Lscala/xml/dtd/PublicID;
   0      10      1    publicId       Ljava/lang/String;
   0      10      2    systemId       Ljava/lang/String;


public scala.collection.immutable.Nil$ child();
  Signature: ()Lscala/collection/immutable/Nil$;
  Code:
   Stack=1, Locals=1, Args_size=1
	getstatic	Field scala/collection/immutable/Nil$.MODULE$:Lscala/collection/immutable/Nil$;
	areturn
  Labels:

public scala.xml.MetaData attribute();
  Signature: ()Lscala/xml/MetaData;
  Code:
   Stack=1, Locals=1, Args_size=1
	getstatic	Field scala/xml/Node$.MODULE$:Lscala/xml/Node$;
	invokevirtual	Method scala/xml/Node$.NoAttributes:()Lscala/xml/MetaData;
	areturn
  Labels:

public java.lang.String label();
  Signature: ()Ljava/lang/String;
  Code:
   Stack=1, Locals=1, Args_size=1
	ldc	String #PI
	areturn
  Labels:

public java.lang.String systemId();
  Signature: ()Ljava/lang/String;
  Code:
   Stack=1, Locals=1, Args_size=1
	aload_0
	getfield	Field systemId:Ljava/lang/String;
	areturn
  Labels:

public java.lang.String publicId();
  Signature: ()Ljava/lang/String;
  Code:
   Stack=1, Locals=1, Args_size=1
	aload_0
	getfield	Field publicId:Ljava/lang/String;
	areturn
  Labels:

public java.lang.String copy$default$1();
  Signature: ()Ljava/lang/String;
  Code:
   Stack=1, Locals=1, Args_size=1
	aload_0
	invokevirtual	Method publicId:()Ljava/lang/String;
	areturn
  Labels:

public java.lang.String copy$default$2();
  Signature: ()Ljava/lang/String;
  Code:
   Stack=1, Locals=1, Args_size=1
	aload_0
	invokevirtual	Method systemId:()Ljava/lang/String;
	areturn
  Labels:

public scala.collection.Iterator productElements();
  Signature: ()Lscala/collection/Iterator;
  Code:
   Stack=1, Locals=1, Args_size=1
	aload_0
	invokestatic	Method scala/Product$class.productElements:(Lscala/Product;)Lscala/collection/Iterator;
	areturn
  Labels:
  Deprecated: true

public scala.collection.Iterator productIterator();
  Signature: ()Lscala/collection/Iterator;
  Code:
   Stack=1, Locals=1, Args_size=1
	aload_0
	invokestatic	Method scala/Product$class.productIterator:(Lscala/Product;)Lscala/collection/Iterator;
	areturn
  Labels:

}

