Compiled from "Decl.scala"
public final class scala.xml.dtd.REQUIRED extends java.lang.Object
  SourceFile: "Decl.scala"
  ScalaSig: length = 0x2A4
   05 00 6A 07 05 01 02 FFFFFF88 42 09 01 08 52 45 51 55
   49 52 45 44 0A 02 03 04 01 03 64 74 64 0A 02 05
   06 01 03 78 6D 6C 0A 01 07 01 05 73 63 61 6C 61
   03 00 10 02 0A 0B 0D 01 02 06 08 0C 02 FFFFFF84 FFFFFF80 FFFFFF80
   FFFFFF88 42 0D 02 08 52 45 51 55 49 52 45 44 13 04 0B
   0E 11 15 10 02 0A 0F 09 02 10 02 02 0B 44 65 66
   61 75 6C 74 44 65 63 6C 10 02 12 13 0D 01 06 09
   02 14 06 02 0B 53 63 61 6C 61 4F 62 6A 65 63 74
   10 02 12 16 09 02 17 06 02 07 50 72 6F 64 75 63
   74 08 05 19 0B FFFFFF84 00 1A 01 06 3C 69 6E 69 74 3E
   14 01 09 08 05 1C 0B FFFFFF84 20 1D 01 08 74 6F 53 74
   72 69 6E 67 14 01 1E 10 02 1F 22 0E 02 12 20 09
   02 21 06 01 06 50 72 65 64 65 66 09 02 23 24 02
   06 53 74 72 69 6E 67 0A 02 21 06 08 05 26 0B FFFFFF84
   20 27 01 0B 62 75 69 6C 64 53 74 72 69 6E 67 14
   02 28 30 10 02 29 2E 0D 01 2A 0A 02 2B 2C 01 07
   6D 75 74 61 62 6C 65 0A 02 2D 06 01 0A 63 6F 6C
   6C 65 63 74 69 6F 6E 09 02 2F 2A 02 0D 53 74 72
   69 6E 67 42 75 69 6C 64 65 72 08 05 31 25 FFFFFFC0 00
   32 01 02 73 62 10 02 33 3B 0E 02 34 39 0E 02 35
   38 0D 01 36 0A 02 37 08 01 06 3C 72 6F 6F 74 3E
   09 01 07 09 02 3A 06 01 07 70 61 63 6B 61 67 65
   09 02 2F 3C 0A 02 3A 06 08 08 3E 0B FFFFFF84 FFFFFF80 FFFFFF80 FFFFFF84
   20 3F 01 0D 70 72 6F 64 75 63 74 50 72 65 66 69
   78 15 01 40 10 02 41 46 0D 01 42 0A 02 43 44 01
   04 6C 61 6E 67 0A 01 45 01 04 6A 61 76 61 09 02
   23 42 08 08 48 0B FFFFFF84 FFFFFF80 FFFFFF80 FFFFFF84 20 49 01 0C 70 72
   6F 64 75 63 74 41 72 69 74 79 15 01 4A 10 02 12
   4B 09 02 4C 06 02 03 49 6E 74 08 08 4E 0B FFFFFF84 FFFFFF80
   FFFFFF80 FFFFFF84 20 4F 01 0E 70 72 6F 64 75 63 74 45 6C 65
   6D 65 6E 74 14 02 50 53 10 02 12 51 09 02 52 06
   02 03 41 6E 79 08 07 54 4D FFFFFF81 FFFFFF80 FFFFFFC0 00 4A 01 03
   78 24 31 08 08 56 0B FFFFFF84 FFFFFF80 FFFFFF80 FFFFFF84 20 57 01 12 70
   72 6F 64 75 63 74 45 6C 65 6D 65 6E 74 4E 61 6D
   65 14 02 40 58 08 07 54 55 FFFFFF81 FFFFFF80 FFFFFFC0 00 4A 08 08
   5A 0B FFFFFF84 FFFFFF80 FFFFFF80 FFFFFF84 20 5B 01 08 63 61 6E 45 71 75
   61 6C 14 02 5C 5F 10 02 12 5D 09 02 5E 06 02 07
   42 6F 6F 6C 65 61 6E 08 07 54 59 FFFFFF81 FFFFFF80 FFFFFFC0 00 50
   08 08 61 0B FFFFFF84 FFFFFF80 FFFFFF80 FFFFFF84 08 62 01 0B 72 65 61 64
   52 65 73 6F 6C 76 65 14 01 63 10 02 41 64 09 02
   65 42 02 06 4F 62 6A 65 63 74 28 02 0B 67 10 02
   12 68 09 02 69 06 02 0C 73 65 72 69 61 6C 69 7A
   61 62 6C 65 
  minor version: 0
  major version: 49
  Constant pool:
Asciz	SourceFile;
Asciz	Decl.scala;
Asciz	productElements;
Asciz	()Lscala/collection/Iterator;;
Asciz	Code;
Asciz	scala/xml/dtd/REQUIRED$;
class	scala/xml/dtd/REQUIRED$
Asciz	MODULE$;
Asciz	Lscala/xml/dtd/REQUIRED$;;
NameAndType	MODULE$:Lscala/xml/dtd/REQUIRED$;
Field	scala/xml/dtd/REQUIRED$.MODULE$:Lscala/xml/dtd/REQUIRED$;
NameAndType	productElements:()Lscala/collection/Iterator;
Method	scala/xml/dtd/REQUIRED$.productElements:()Lscala/collection/Iterator;
Asciz	Deprecated;
Asciz	productIterator;
NameAndType	productIterator:()Lscala/collection/Iterator;
Method	scala/xml/dtd/REQUIRED$.productIterator:()Lscala/collection/Iterator;
Asciz	canEqual;
Asciz	(Ljava/lang/Object;)Z;
NameAndType	canEqual:(Ljava/lang/Object;)Z
Method	scala/xml/dtd/REQUIRED$.canEqual:(Ljava/lang/Object;)Z
Asciz	productElementName;
Asciz	(I)Ljava/lang/String;;
NameAndType	productElementName:(I)Ljava/lang/String;
Method	scala/xml/dtd/REQUIRED$.productElementName:(I)Ljava/lang/String;
Asciz	productElement;
Asciz	(I)Ljava/lang/Object;;
NameAndType	productElement:(I)Ljava/lang/Object;
Method	scala/xml/dtd/REQUIRED$.productElement:(I)Ljava/lang/Object;
Asciz	productArity;
Asciz	()I;
NameAndType	productArity:()I
Method	scala/xml/dtd/REQUIRED$.productArity:()I
Asciz	productPrefix;
Asciz	()Ljava/lang/String;;
NameAndType	productPrefix:()Ljava/lang/String;
Method	scala/xml/dtd/REQUIRED$.productPrefix:()Ljava/lang/String;
Asciz	buildString;
Asciz	(Lscala/collection/mutable/StringBuilder;)Lscala/collection/mutable/StringBuilder;;
NameAndType	buildString:(Lscala/collection/mutable/StringBuilder;)Lscala/collection/mutable/StringBuilder;
Method	scala/xml/dtd/REQUIRED$.buildString:(Lscala/collection/mutable/StringBuilder;)Lscala/collection/mutable/StringBuilder;
Asciz	ScalaSig;
Asciz	scala/xml/dtd/REQUIRED;
class	scala/xml/dtd/REQUIRED
Asciz	java/lang/Object;
class	java/lang/Object

{
public static final scala.collection.Iterator productElements();
  Signature: ()Lscala/collection/Iterator;
  Code:
   Stack=1, Locals=0, Args_size=0
	getstatic	Field scala/xml/dtd/REQUIRED$.MODULE$:Lscala/xml/dtd/REQUIRED$;
	invokevirtual	Method scala/xml/dtd/REQUIRED$.productElements:()Lscala/collection/Iterator;
	areturn
  Labels:
  Deprecated: true

public static final scala.collection.Iterator productIterator();
  Signature: ()Lscala/collection/Iterator;
  Code:
   Stack=1, Locals=0, Args_size=0
	getstatic	Field scala/xml/dtd/REQUIRED$.MODULE$:Lscala/xml/dtd/REQUIRED$;
	invokevirtual	Method scala/xml/dtd/REQUIRED$.productIterator:()Lscala/collection/Iterator;
	areturn
  Labels:

public static final boolean canEqual(java.lang.Object);
  Signature: (Ljava/lang/Object;)Z
  Code:
   Stack=2, Locals=1, Args_size=1
	getstatic	Field scala/xml/dtd/REQUIRED$.MODULE$:Lscala/xml/dtd/REQUIRED$;
	aload_0
	invokevirtual	Method scala/xml/dtd/REQUIRED$.canEqual:(Ljava/lang/Object;)Z
	ireturn
  Labels:

public static final java.lang.String productElementName(int);
  Signature: (I)Ljava/lang/String;
  Code:
   Stack=2, Locals=1, Args_size=1
	getstatic	Field scala/xml/dtd/REQUIRED$.MODULE$:Lscala/xml/dtd/REQUIRED$;
	iload_0
	invokevirtual	Method scala/xml/dtd/REQUIRED$.productElementName:(I)Ljava/lang/String;
	areturn
  Labels:

public static final java.lang.Object productElement(int);
  Signature: (I)Ljava/lang/Object;
  Code:
   Stack=2, Locals=1, Args_size=1
	getstatic	Field scala/xml/dtd/REQUIRED$.MODULE$:Lscala/xml/dtd/REQUIRED$;
	iload_0
	invokevirtual	Method scala/xml/dtd/REQUIRED$.productElement:(I)Ljava/lang/Object;
	areturn
  Labels:

public static final int productArity();
  Signature: ()I
  Code:
   Stack=1, Locals=0, Args_size=0
	getstatic	Field scala/xml/dtd/REQUIRED$.MODULE$:Lscala/xml/dtd/REQUIRED$;
	invokevirtual	Method scala/xml/dtd/REQUIRED$.productArity:()I
	ireturn
  Labels:

public static final java.lang.String productPrefix();
  Signature: ()Ljava/lang/String;
  Code:
   Stack=1, Locals=0, Args_size=0
	getstatic	Field scala/xml/dtd/REQUIRED$.MODULE$:Lscala/xml/dtd/REQUIRED$;
	invokevirtual	Method scala/xml/dtd/REQUIRED$.productPrefix:()Ljava/lang/String;
	areturn
  Labels:

public static final scala.collection.mutable.StringBuilder buildString(scala.collection.mutable.StringBuilder);
  Signature: (Lscala/collection/mutable/StringBuilder;)Lscala/collection/mutable/StringBuilder;
  Code:
   Stack=2, Locals=1, Args_size=1
	getstatic	Field scala/xml/dtd/REQUIRED$.MODULE$:Lscala/xml/dtd/REQUIRED$;
	aload_0
	invokevirtual	Method scala/xml/dtd/REQUIRED$.buildString:(Lscala/collection/mutable/StringBuilder;)Lscala/collection/mutable/StringBuilder;
	areturn
  Labels:

}

