Compiled from "Scanner.scala"
public class scala.xml.dtd.Scanner extends scala.xml.dtd.Tokens implements scala.xml.parsing.TokenTests,scala.ScalaObject
  SourceFile: "Scanner.scala"
  ScalaSig: length = 0x30A
   05 00 7F 06 08 01 02 FFFFFF84 FFFFFF80 FFFFFF80 FFFFFF80 00 09 02 07 53
   63 61 6E 6E 65 72 0A 02 03 04 01 03 64 74 64 0A
   02 05 06 01 03 78 6D 6C 0A 01 07 01 05 73 63 61
   6C 61 03 00 13 04 00 0A 0E 14 10 02 0B 0C 0D 01
   02 09 02 0D 02 02 06 54 6F 6B 65 6E 73 10 02 0F
   12 0D 01 10 0A 02 11 04 01 07 70 61 72 73 69 6E
   67 09 02 13 10 02 0A 54 6F 6B 65 6E 54 65 73 74
   73 10 02 15 16 0D 01 06 09 02 17 06 02 0B 53 63
   61 6C 61 4F 62 6A 65 63 74 08 05 19 00 FFFFFF84 00 1A
   01 06 3C 69 6E 69 74 3E 14 01 1B 10 02 0B 00 08
   07 1D 00 FFFFFFC2 FFFFFF80 FFFFFF84 02 1E 01 05 45 4E 44 43 48 15
   01 1F 0F 01 20 1C 01 00 08 06 22 00 FFFFFFA0 FFFFFF80 06 1F
   01 06 45 4E 44 43 48 20 08 07 24 00 FFFFFFC0 FFFFFF80 FFFFFF84 00
   25 01 05 74 6F 6B 65 6E 15 01 26 10 02 15 27 09
   02 28 06 02 03 49 6E 74 08 07 2A 00 FFFFFFC0 FFFFFF80 FFFFFF84 00
   2B 01 09 74 6F 6B 65 6E 5F 24 65 71 14 02 2C 2F
   10 02 15 2D 09 02 2E 06 02 04 55 6E 69 74 08 07
   30 29 FFFFFF81 FFFFFF80 FFFFFFC0 00 26 01 03 78 24 31 08 06 32 00
   FFFFFFA0 FFFFFFA0 04 26 01 06 74 6F 6B 65 6E 20 08 07 34 00
   FFFFFFC0 FFFFFF80 FFFFFF84 00 35 01 05 76 61 6C 75 65 15 01 36 10
   02 37 3A 0E 02 15 38 09 02 39 06 01 06 50 72 65
   64 65 66 09 02 3B 3C 02 06 53 74 72 69 6E 67 0A
   02 39 06 08 07 3E 00 FFFFFFC0 FFFFFF80 FFFFFF84 00 3F 01 09 76 61
   6C 75 65 5F 24 65 71 14 02 2C 40 08 07 30 3D FFFFFF81
   FFFFFF80 FFFFFFC0 00 36 08 06 42 00 FFFFFFA0 FFFFFFA0 04 36 01 06 76 61
   6C 75 65 20 08 07 44 00 FFFFFFC0 FFFFFF80 FFFFFF84 04 45 01 02 69
   74 15 01 46 10 03 47 4A 4C 0D 01 48 0A 02 49 06
   01 0A 63 6F 6C 6C 65 63 74 69 6F 6E 09 02 4B 48
   02 08 49 74 65 72 61 74 6F 72 10 02 15 4D 09 02
   4E 06 02 04 43 68 61 72 08 07 50 00 FFFFFFC0 FFFFFF80 FFFFFF84 04
   51 01 06 69 74 5F 24 65 71 14 02 2C 52 08 07 30
   4F FFFFFF81 FFFFFF80 FFFFFFC0 00 46 08 06 54 00 FFFFFFA0 FFFFFFA0 04 46 01 03
   69 74 20 08 07 56 00 FFFFFFC0 FFFFFF80 FFFFFF84 04 57 01 01 63 15
   01 4C 08 07 59 00 FFFFFFC0 FFFFFF80 FFFFFF84 04 5A 01 05 63 5F 24
   65 71 14 02 2C 5B 08 07 30 58 FFFFFF81 FFFFFF80 FFFFFFC0 00 4C 08
   06 5D 00 FFFFFFA0 FFFFFFA0 04 4C 01 02 63 20 08 05 5F 00 FFFFFF84
   02 60 01 0B 69 6E 69 74 53 63 61 6E 6E 65 72 14
   02 2C 61 08 05 62 5E FFFFFFC0 00 36 01 01 73 08 05 64
   00 FFFFFF84 02 65 01 09 6E 65 78 74 54 6F 6B 65 6E 15
   01 2C 08 05 67 00 FFFFFF84 02 68 01 0B 69 73 49 64 65
   6E 74 43 68 61 72 15 01 69 10 02 15 6A 09 02 6B
   06 02 07 42 6F 6F 6C 65 61 6E 08 05 6D 00 FFFFFF84 02
   65 01 04 6E 65 78 74 08 05 6F 00 FFFFFF84 02 70 01 03
   61 63 63 14 02 2C 71 08 05 72 6E FFFFFFC0 00 4C 01 01
   64 08 05 74 00 FFFFFF84 02 75 01 04 61 63 63 53 14 02
   2C 76 08 05 77 73 FFFFFFC0 00 78 01 02 64 73 10 03 47
   79 4C 09 02 7A 48 02 03 53 65 71 08 05 7C 00 FFFFFF84
   02 25 01 09 72 65 61 64 54 6F 6B 65 6E 08 05 7E
   00 FFFFFF84 02 25 01 04 6E 61 6D 65 
  InnerClass: 
   public final #242= #138 of #30; //$anonfun$accS$1=class scala/xml/dtd/Scanner$$anonfun$accS$1 of class scala/xml/dtd/Scanner
  minor version: 0
  major version: 49
  Constant pool:
const #1 = Asciz	SourceFile;
const #2 = Asciz	Scanner.scala;
const #3 = Asciz	c;
const #4 = Asciz	C;
const #5 = Asciz	it;
const #6 = Asciz	Lscala/collection/Iterator;;
const #7 = Asciz	Lscala/collection/Iterator<Ljava/lang/Character;>;;
const #8 = Asciz	Signature;
const #9 = Asciz	value;
const #10 = Asciz	Ljava/lang/String;;
const #11 = Asciz	token;
const #12 = Asciz	I;
const #13 = Asciz	ENDCH;
const #14 = Asciz	<init>;
const #15 = Asciz	()V;
const #16 = Asciz	Code;
const #17 = Asciz	LineNumberTable;
const #18 = Asciz	scala/xml/dtd/Tokens;
const #19 = class	#18;	//  scala/xml/dtd/Tokens
const #20 = NameAndType	#14:#15;//  "<init>":()V
const #21 = Method	#19.#20;	//  scala/xml/dtd/Tokens."<init>":()V
const #22 = Asciz	scala/xml/parsing/TokenTests$class;
const #23 = class	#22;	//  scala/xml/parsing/TokenTests$class
const #24 = Asciz	$init$;
const #25 = Asciz	(Lscala/xml/parsing/TokenTests;)V;
const #26 = NameAndType	#24:#25;//  $init$:(Lscala/xml/parsing/TokenTests;)V
const #27 = Method	#23.#26;	//  scala/xml/parsing/TokenTests$class.$init$:(Lscala/xml/parsing/TokenTests;)V
const #28 = int	10;
const #29 = Asciz	scala/xml/dtd/Scanner;
const #30 = class	#29;	//  scala/xml/dtd/Scanner
const #31 = NameAndType	#11:#12;//  token:I
const #32 = Field	#30.#31;	//  scala/xml/dtd/Scanner.token:I
const #33 = NameAndType	#5:#6;//  it:Lscala/collection/Iterator;
const #34 = Field	#30.#33;	//  scala/xml/dtd/Scanner.it:Lscala/collection/Iterator;
const #35 = int	122;
const #36 = NameAndType	#3:#4;//  c:C
const #37 = Field	#30.#36;	//  scala/xml/dtd/Scanner.c:C
const #38 = Asciz	name;
const #39 = Asciz	()I;
const #40 = Asciz	scala/collection/mutable/StringBuilder;
const #41 = class	#40;	//  scala/collection/mutable/StringBuilder
const #42 = Method	#41.#20;	//  scala/collection/mutable/StringBuilder."<init>":()V
const #43 = Asciz	()C;
const #44 = NameAndType	#3:#43;//  c:()C
const #45 = Method	#30.#44;	//  scala/xml/dtd/Scanner.c:()C
const #46 = Asciz	append;
const #47 = Asciz	(C)Lscala/collection/mutable/StringBuilder;;
const #48 = NameAndType	#46:#47;//  append:(C)Lscala/collection/mutable/StringBuilder;
const #49 = Method	#41.#48;	//  scala/collection/mutable/StringBuilder.append:(C)Lscala/collection/mutable/StringBuilder;
const #50 = Asciz	next;
const #51 = NameAndType	#50:#15;//  next:()V
const #52 = Method	#30.#51;	//  scala/xml/dtd/Scanner.next:()V
const #53 = Asciz	scala/xml/parsing/TokenTests;
const #54 = class	#53;	//  scala/xml/parsing/TokenTests
const #55 = Asciz	isNameChar;
const #56 = Asciz	(C)Z;
const #57 = NameAndType	#55:#56;//  isNameChar:(C)Z
const #58 = InterfaceMethod	#54.#57;	//  scala/xml/parsing/TokenTests.isNameChar:(C)Z
const #59 = Asciz	toString;
const #60 = Asciz	()Ljava/lang/String;;
const #61 = NameAndType	#59:#60;//  toString:()Ljava/lang/String;
const #62 = Method	#41.#61;	//  scala/collection/mutable/StringBuilder.toString:()Ljava/lang/String;
const #63 = Asciz	value_$eq;
const #64 = Asciz	(Ljava/lang/String;)V;
const #65 = NameAndType	#63:#64;//  value_$eq:(Ljava/lang/String;)V
const #66 = Method	#30.#65;	//  scala/xml/dtd/Scanner.value_$eq:(Ljava/lang/String;)V
const #67 = Asciz	this;
const #68 = Asciz	Lscala/xml/dtd/Scanner;;
const #69 = Asciz	sb;
const #70 = Asciz	Lscala/collection/mutable/StringBuilder;;
const #71 = Asciz	LocalVariableTable;
const #72 = Asciz	readToken;
const #73 = Asciz	isSpace;
const #74 = NameAndType	#73:#56;//  isSpace:(C)Z
const #75 = InterfaceMethod	#54.#74;	//  scala/xml/parsing/TokenTests.isSpace:(C)Z
const #76 = Asciz	()Lscala/collection/Iterator;;
const #77 = NameAndType	#5:#76;//  it:()Lscala/collection/Iterator;
const #78 = Method	#30.#77;	//  scala/xml/dtd/Scanner.it:()Lscala/collection/Iterator;
const #79 = Asciz	scala/collection/Iterator;
const #80 = class	#79;	//  scala/collection/Iterator
const #81 = Asciz	()Ljava/lang/Object;;
const #82 = NameAndType	#50:#81;//  next:()Ljava/lang/Object;
const #83 = InterfaceMethod	#80.#82;	//  scala/collection/Iterator.next:()Ljava/lang/Object;
const #84 = Asciz	scala/runtime/BoxesRunTime;
const #85 = class	#84;	//  scala/runtime/BoxesRunTime
const #86 = Asciz	unboxToChar;
const #87 = Asciz	(Ljava/lang/Object;)C;
const #88 = NameAndType	#86:#87;//  unboxToChar:(Ljava/lang/Object;)C
const #89 = Method	#85.#88;	//  scala/runtime/BoxesRunTime.unboxToChar:(Ljava/lang/Object;)C
const #90 = Asciz	c_$eq;
const #91 = Asciz	(C)V;
const #92 = NameAndType	#90:#91;//  c_$eq:(C)V
const #93 = Method	#30.#92;	//  scala/xml/dtd/Scanner.c_$eq:(C)V
const #94 = int	13;
const #95 = Asciz	isNameStart;
const #96 = NameAndType	#95:#56;//  isNameStart:(C)Z
const #97 = InterfaceMethod	#54.#96;	//  scala/xml/parsing/TokenTests.isNameStart:(C)Z
const #98 = NameAndType	#38:#39;//  name:()I
const #99 = Method	#30.#98;	//  scala/xml/dtd/Scanner.name:()I
const #100 = Method	#41.#20;	//  scala/collection/mutable/StringBuilder."<init>":()V
const #101 = Asciz	unexpected character:;
const #102 = String	#101;	//  unexpected character:
const #103 = Asciz	(Ljava/lang/Object;)Lscala/collection/mutable/StringBuilder;;
const #104 = NameAndType	#46:#103;//  append:(Ljava/lang/Object;)Lscala/collection/mutable/StringBuilder;
const #105 = Method	#41.#104;	//  scala/collection/mutable/StringBuilder.append:(Ljava/lang/Object;)Lscala/collection/mutable/StringBuilder;
const #106 = Asciz	boxToCharacter;
const #107 = Asciz	(C)Ljava/lang/Character;;
const #108 = NameAndType	#106:#107;//  boxToCharacter:(C)Ljava/lang/Character;
const #109 = Method	#85.#108;	//  scala/runtime/BoxesRunTime.boxToCharacter:(C)Ljava/lang/Character;
const #110 = Method	#41.#61;	//  scala/collection/mutable/StringBuilder.toString:()Ljava/lang/String;
const #111 = Asciz	java/lang/RuntimeException;
const #112 = class	#111;	//  java/lang/RuntimeException
const #113 = NameAndType	#14:#64;//  "<init>":(Ljava/lang/String;)V
const #114 = Method	#112.#113;	//  java/lang/RuntimeException."<init>":(Ljava/lang/String;)V
const #115 = Asciz	scala/MatchError;
const #116 = class	#115;	//  scala/MatchError
const #117 = Asciz	java/lang/Object;
const #118 = class	#117;	//  java/lang/Object
const #119 = Method	#118.#61;	//  java/lang/Object.toString:()Ljava/lang/String;
const #120 = Method	#116.#113;	//  scala/MatchError."<init>":(Ljava/lang/String;)V
const #121 = int	9;
const #122 = int	8;
const #123 = int	7;
const #124 = int	6;
const #125 = Asciz	scala/Predef$;
const #126 = class	#125;	//  scala/Predef$
const #127 = Asciz	MODULE$;
const #128 = Asciz	Lscala/Predef$;;
const #129 = NameAndType	#127:#128;//  MODULE$:Lscala/Predef$;
const #130 = Field	#126.#129;	//  scala/Predef$.MODULE$:Lscala/Predef$;
const #131 = Asciz	PCDATA;
const #132 = String	#131;	//  PCDATA
const #133 = Asciz	wrapString;
const #134 = Asciz	(Ljava/lang/String;)Lscala/collection/immutable/WrappedString;;
const #135 = NameAndType	#133:#134;//  wrapString:(Ljava/lang/String;)Lscala/collection/immutable/WrappedString;
const #136 = Method	#126.#135;	//  scala/Predef$.wrapString:(Ljava/lang/String;)Lscala/collection/immutable/WrappedString;
const #137 = Asciz	scala/xml/dtd/Scanner$$anonfun$accS$1;
const #138 = class	#137;	//  scala/xml/dtd/Scanner$$anonfun$accS$1
const #139 = Asciz	(Lscala/xml/dtd/Scanner;)V;
const #140 = NameAndType	#14:#139;//  "<init>":(Lscala/xml/dtd/Scanner;)V
const #141 = Method	#138.#140;	//  scala/xml/dtd/Scanner$$anonfun$accS$1."<init>":(Lscala/xml/dtd/Scanner;)V
const #142 = Asciz	scala/collection/IterableLike;
const #143 = class	#142;	//  scala/collection/IterableLike
const #144 = Asciz	foreach;
const #145 = Asciz	(Lscala/Function1;)V;
const #146 = NameAndType	#144:#145;//  foreach:(Lscala/Function1;)V
const #147 = InterfaceMethod	#143.#146;	//  scala/collection/IterableLike.foreach:(Lscala/Function1;)V
const #148 = Asciz	temp1;
const #149 = Asciz	accS;
const #150 = Asciz	(Lscala/collection/Seq;)V;
const #151 = Asciz	ds;
const #152 = Asciz	Lscala/collection/Seq;;
const #153 = Asciz	(Lscala/collection/Seq<Ljava/lang/Character;>;)V;
const #154 = Asciz	acc;
const #155 = Asciz	expected ';
const #156 = String	#155;	//  expected '
const #157 = Asciz	' found ';
const #158 = String	#157;	//  ' found '
const #159 = Asciz	' !;
const #160 = String	#159;	//  ' !
const #161 = Asciz	d;
const #162 = Asciz	hasNext;
const #163 = Asciz	()Z;
const #164 = NameAndType	#162:#163;//  hasNext:()Z
const #165 = InterfaceMethod	#80.#164;	//  scala/collection/Iterator.hasNext:()Z
const #166 = Asciz	isIdentChar;
const #167 = int	97;
const #168 = int	65;
const #169 = int	90;
const #170 = Asciz	nextToken;
const #171 = NameAndType	#11:#39;//  token:()I
const #172 = Method	#30.#171;	//  scala/xml/dtd/Scanner.token:()I
const #173 = NameAndType	#72:#39;//  readToken:()I
const #174 = Method	#30.#173;	//  scala/xml/dtd/Scanner.readToken:()I
const #175 = Asciz	token_$eq;
const #176 = Asciz	(I)V;
const #177 = NameAndType	#175:#176;//  token_$eq:(I)V
const #178 = Method	#30.#177;	//  scala/xml/dtd/Scanner.token_$eq:(I)V
const #179 = Asciz	initScanner;
const #180 = Asciz	;
const #181 = String	#180;	//  
const #182 = Asciz	augmentString;
const #183 = Asciz	(Ljava/lang/String;)Lscala/collection/immutable/StringOps;;
const #184 = NameAndType	#182:#183;//  augmentString:(Ljava/lang/String;)Lscala/collection/immutable/StringOps;
const #185 = Method	#126.#184;	//  scala/Predef$.augmentString:(Ljava/lang/String;)Lscala/collection/immutable/StringOps;
const #186 = Asciz	scala/collection/IndexedSeqLike;
const #187 = class	#186;	//  scala/collection/IndexedSeqLike
const #188 = Asciz	iterator;
const #189 = NameAndType	#188:#76;//  iterator:()Lscala/collection/Iterator;
const #190 = InterfaceMethod	#187.#189;	//  scala/collection/IndexedSeqLike.iterator:()Lscala/collection/Iterator;
const #191 = Asciz	it_$eq;
const #192 = Asciz	(Lscala/collection/Iterator;)V;
const #193 = NameAndType	#191:#192;//  it_$eq:(Lscala/collection/Iterator;)V
const #194 = Method	#30.#193;	//  scala/xml/dtd/Scanner.it_$eq:(Lscala/collection/Iterator;)V
const #195 = int	11;
const #196 = NameAndType	#170:#15;//  nextToken:()V
const #197 = Method	#30.#196;	//  scala/xml/dtd/Scanner.nextToken:()V
const #198 = Asciz	s;
const #199 = Asciz	(Lscala/collection/Iterator<Ljava/lang/Character;>;)V;
const #200 = Asciz	()Lscala/collection/Iterator<Ljava/lang/Character;>;;
const #201 = NameAndType	#9:#10;//  value:Ljava/lang/String;
const #202 = Field	#30.#201;	//  scala/xml/dtd/Scanner.value:Ljava/lang/String;
const #203 = Asciz	checkPubID;
const #204 = Asciz	(Ljava/lang/String;)Z;
const #205 = Asciz	(Lscala/xml/parsing/TokenTests;Ljava/lang/String;)Z;
const #206 = NameAndType	#203:#205;//  checkPubID:(Lscala/xml/parsing/TokenTests;Ljava/lang/String;)Z
const #207 = Method	#23.#206;	//  scala/xml/parsing/TokenTests$class.checkPubID:(Lscala/xml/parsing/TokenTests;Ljava/lang/String;)Z
const #208 = Asciz	checkSysID;
const #209 = NameAndType	#208:#205;//  checkSysID:(Lscala/xml/parsing/TokenTests;Ljava/lang/String;)Z
const #210 = Method	#23.#209;	//  scala/xml/parsing/TokenTests$class.checkSysID:(Lscala/xml/parsing/TokenTests;Ljava/lang/String;)Z
const #211 = Asciz	isValidIANAEncoding;
const #212 = Asciz	(Lscala/collection/Seq;)Z;
const #213 = Asciz	(Lscala/xml/parsing/TokenTests;Lscala/collection/Seq;)Z;
const #214 = NameAndType	#211:#213;//  isValidIANAEncoding:(Lscala/xml/parsing/TokenTests;Lscala/collection/Seq;)Z
const #215 = Method	#23.#214;	//  scala/xml/parsing/TokenTests$class.isValidIANAEncoding:(Lscala/xml/parsing/TokenTests;Lscala/collection/Seq;)Z
const #216 = Asciz	ianaEncoding;
const #217 = Asciz	isPubIDChar;
const #218 = Asciz	(Lscala/xml/parsing/TokenTests;C)Z;
const #219 = NameAndType	#217:#218;//  isPubIDChar:(Lscala/xml/parsing/TokenTests;C)Z
const #220 = Method	#23.#219;	//  scala/xml/parsing/TokenTests$class.isPubIDChar:(Lscala/xml/parsing/TokenTests;C)Z
const #221 = Asciz	ch;
const #222 = Asciz	isName;
const #223 = NameAndType	#222:#205;//  isName:(Lscala/xml/parsing/TokenTests;Ljava/lang/String;)Z
const #224 = Method	#23.#223;	//  scala/xml/parsing/TokenTests$class.isName:(Lscala/xml/parsing/TokenTests;Ljava/lang/String;)Z
const #225 = NameAndType	#95:#218;//  isNameStart:(Lscala/xml/parsing/TokenTests;C)Z
const #226 = Method	#23.#225;	//  scala/xml/parsing/TokenTests$class.isNameStart:(Lscala/xml/parsing/TokenTests;C)Z
const #227 = NameAndType	#55:#218;//  isNameChar:(Lscala/xml/parsing/TokenTests;C)Z
const #228 = Method	#23.#227;	//  scala/xml/parsing/TokenTests$class.isNameChar:(Lscala/xml/parsing/TokenTests;C)Z
const #229 = Asciz	isAlphaDigit;
const #230 = NameAndType	#229:#218;//  isAlphaDigit:(Lscala/xml/parsing/TokenTests;C)Z
const #231 = Method	#23.#230;	//  scala/xml/parsing/TokenTests$class.isAlphaDigit:(Lscala/xml/parsing/TokenTests;C)Z
const #232 = Asciz	isAlpha;
const #233 = NameAndType	#232:#218;//  isAlpha:(Lscala/xml/parsing/TokenTests;C)Z
const #234 = Method	#23.#233;	//  scala/xml/parsing/TokenTests$class.isAlpha:(Lscala/xml/parsing/TokenTests;C)Z
const #235 = NameAndType	#73:#213;//  isSpace:(Lscala/xml/parsing/TokenTests;Lscala/collection/Seq;)Z
const #236 = Method	#23.#235;	//  scala/xml/parsing/TokenTests$class.isSpace:(Lscala/xml/parsing/TokenTests;Lscala/collection/Seq;)Z
const #237 = Asciz	cs;
const #238 = NameAndType	#73:#218;//  isSpace:(Lscala/xml/parsing/TokenTests;C)Z
const #239 = Method	#23.#238;	//  scala/xml/parsing/TokenTests$class.isSpace:(Lscala/xml/parsing/TokenTests;C)Z
const #240 = Asciz	ScalaSig;
const #241 = Asciz	InnerClasses;
const #242 = Asciz	$anonfun$accS$1;
const #243 = Asciz	scala/ScalaObject;
const #244 = class	#243;	//  scala/ScalaObject

{
public scala.xml.dtd.Scanner();
  Code:
   Stack=2, Locals=1, Args_size=1
   0:	aload_0
   1:	invokespecial	#21; //Method scala/xml/dtd/Tokens."<init>":()V
   4:	aload_0
   5:	invokestatic	#27; //Method scala/xml/parsing/TokenTests$class.$init$:(Lscala/xml/parsing/TokenTests;)V
   8:	aload_0
   9:	ldc	#28; //int 10
   11:	putfield	#32; //Field token:I
   14:	aload_0
   15:	aconst_null
   16:	putfield	#34; //Field it:Lscala/collection/Iterator;
   19:	aload_0
   20:	ldc	#35; //int 122
   22:	putfield	#37; //Field c:C
   25:	return
  LineNumberTable: 
   line 21: 0
   line 25: 8
   line 28: 14
   line 29: 19


public final int name();
  Code:
   Stack=2, Locals=2, Args_size=1
   0:	new	#41; //class scala/collection/mutable/StringBuilder
   3:	dup
   4:	invokespecial	#42; //Method scala/collection/mutable/StringBuilder."<init>":()V
   7:	astore_1
   8:	aload_1
   9:	aload_0
   10:	invokespecial	#45; //Method c:()C
   13:	invokevirtual	#49; //Method scala/collection/mutable/StringBuilder.append:(C)Lscala/collection/mutable/StringBuilder;
   16:	pop
   17:	aload_0
   18:	invokevirtual	#52; //Method next:()V
   21:	aload_0
   22:	aload_0
   23:	invokespecial	#45; //Method c:()C
   26:	invokeinterface	#58,  2; //InterfaceMethod scala/xml/parsing/TokenTests.isNameChar:(C)Z
   31:	ifne	8
   34:	aload_0
   35:	aload_1
   36:	invokevirtual	#62; //Method scala/collection/mutable/StringBuilder.toString:()Ljava/lang/String;
   39:	invokevirtual	#66; //Method value_$eq:(Ljava/lang/String;)V
   42:	iconst_1
   43:	ireturn
  LineNumberTable: 
   line 77: 0
   line 78: 8
   line 79: 34
   line 80: 42

  LocalVariableTable: 
   Start  Length  Slot  Name   Signature
   0      44      0    this       Lscala/xml/dtd/Scanner;
   8      35      1    sb       Lscala/collection/mutable/StringBuilder;


public final int readToken();
  Code:
   Stack=4, Locals=5, Args_size=1
   0:	aload_0
   1:	aload_0
   2:	invokespecial	#45; //Method c:()C
   5:	invokeinterface	#75,  2; //InterfaceMethod scala/xml/parsing/TokenTests.isSpace:(C)Z
   10:	ifeq	50
   13:	aload_0
   14:	aload_0
   15:	invokespecial	#45; //Method c:()C
   18:	invokeinterface	#75,  2; //InterfaceMethod scala/xml/parsing/TokenTests.isSpace:(C)Z
   23:	ifeq	45
   26:	aload_0
   27:	aload_0
   28:	invokespecial	#78; //Method it:()Lscala/collection/Iterator;
   31:	invokeinterface	#83,  1; //InterfaceMethod scala/collection/Iterator.next:()Ljava/lang/Object;
   36:	invokestatic	#89; //Method scala/runtime/BoxesRunTime.unboxToChar:(Ljava/lang/Object;)C
   39:	invokespecial	#93; //Method c_$eq:(C)V
   42:	goto	13
   45:	ldc	#94; //int 13
   47:	goto	474
   50:	aload_0
   51:	invokespecial	#45; //Method c:()C
   54:	istore	4
   56:	iload	4
   58:	lookupswitch{ //9
		0: 468;
		35: 417;
		40: 389;
		41: 361;
		42: 332;
		43: 303;
		44: 275;
		63: 246;
		124: 217;
		default: 140 }
   140:	iconst_1
   141:	ifeq	201
   144:	aload_0
   145:	aload_0
   146:	invokespecial	#45; //Method c:()C
   149:	invokeinterface	#97,  2; //InterfaceMethod scala/xml/parsing/TokenTests.isNameStart:(C)Z
   154:	ifeq	164
   157:	aload_0
   158:	invokevirtual	#99; //Method name:()I
   161:	goto	474
   164:	new	#41; //class scala/collection/mutable/StringBuilder
   167:	dup
   168:	invokespecial	#100; //Method scala/collection/mutable/StringBuilder."<init>":()V
   171:	ldc	#102; //String unexpected character:
   173:	invokevirtual	#105; //Method scala/collection/mutable/StringBuilder.append:(Ljava/lang/Object;)Lscala/collection/mutable/StringBuilder;
   176:	aload_0
   177:	invokespecial	#45; //Method c:()C
   180:	istore_1
   181:	iload_1
   182:	invokestatic	#109; //Method scala/runtime/BoxesRunTime.boxToCharacter:(C)Ljava/lang/Character;
   185:	invokevirtual	#105; //Method scala/collection/mutable/StringBuilder.append:(Ljava/lang/Object;)Lscala/collection/mutable/StringBuilder;
   188:	invokevirtual	#110; //Method scala/collection/mutable/StringBuilder.toString:()Ljava/lang/String;
   191:	astore_2
   192:	new	#112; //class java/lang/RuntimeException
   195:	dup
   196:	aload_2
   197:	invokespecial	#114; //Method java/lang/RuntimeException."<init>":(Ljava/lang/String;)V
   200:	athrow
   201:	new	#116; //class scala/MatchError
   204:	dup
   205:	iload	4
   207:	invokestatic	#109; //Method scala/runtime/BoxesRunTime.boxToCharacter:(C)Ljava/lang/Character;
   210:	invokevirtual	#119; //Method java/lang/Object.toString:()Ljava/lang/String;
   213:	invokespecial	#120; //Method scala/MatchError."<init>":(Ljava/lang/String;)V
   216:	athrow
   217:	iconst_1
   218:	ifeq	230
   221:	aload_0
   222:	invokevirtual	#52; //Method next:()V
   225:	ldc	#121; //int 9
   227:	goto	474
   230:	new	#116; //class scala/MatchError
   233:	dup
   234:	iload	4
   236:	invokestatic	#109; //Method scala/runtime/BoxesRunTime.boxToCharacter:(C)Ljava/lang/Character;
   239:	invokevirtual	#119; //Method java/lang/Object.toString:()Ljava/lang/String;
   242:	invokespecial	#120; //Method scala/MatchError."<init>":(Ljava/lang/String;)V
   245:	athrow
   246:	iconst_1
   247:	ifeq	259
   250:	aload_0
   251:	invokevirtual	#52; //Method next:()V
   254:	ldc	#122; //int 8
   256:	goto	474
   259:	new	#116; //class scala/MatchError
   262:	dup
   263:	iload	4
   265:	invokestatic	#109; //Method scala/runtime/BoxesRunTime.boxToCharacter:(C)Ljava/lang/Character;
   268:	invokevirtual	#119; //Method java/lang/Object.toString:()Ljava/lang/String;
   271:	invokespecial	#120; //Method scala/MatchError."<init>":(Ljava/lang/String;)V
   274:	athrow
   275:	iconst_1
   276:	ifeq	287
   279:	aload_0
   280:	invokevirtual	#52; //Method next:()V
   283:	iconst_5
   284:	goto	474
   287:	new	#116; //class scala/MatchError
   290:	dup
   291:	iload	4
   293:	invokestatic	#109; //Method scala/runtime/BoxesRunTime.boxToCharacter:(C)Ljava/lang/Character;
   296:	invokevirtual	#119; //Method java/lang/Object.toString:()Ljava/lang/String;
   299:	invokespecial	#120; //Method scala/MatchError."<init>":(Ljava/lang/String;)V
   302:	athrow
   303:	iconst_1
   304:	ifeq	316
   307:	aload_0
   308:	invokevirtual	#52; //Method next:()V
   311:	ldc	#123; //int 7
   313:	goto	474
   316:	new	#116; //class scala/MatchError
   319:	dup
   320:	iload	4
   322:	invokestatic	#109; //Method scala/runtime/BoxesRunTime.boxToCharacter:(C)Ljava/lang/Character;
   325:	invokevirtual	#119; //Method java/lang/Object.toString:()Ljava/lang/String;
   328:	invokespecial	#120; //Method scala/MatchError."<init>":(Ljava/lang/String;)V
   331:	athrow
   332:	iconst_1
   333:	ifeq	345
   336:	aload_0
   337:	invokevirtual	#52; //Method next:()V
   340:	ldc	#124; //int 6
   342:	goto	474
   345:	new	#116; //class scala/MatchError
   348:	dup
   349:	iload	4
   351:	invokestatic	#109; //Method scala/runtime/BoxesRunTime.boxToCharacter:(C)Ljava/lang/Character;
   354:	invokevirtual	#119; //Method java/lang/Object.toString:()Ljava/lang/String;
   357:	invokespecial	#120; //Method scala/MatchError."<init>":(Ljava/lang/String;)V
   360:	athrow
   361:	iconst_1
   362:	ifeq	373
   365:	aload_0
   366:	invokevirtual	#52; //Method next:()V
   369:	iconst_4
   370:	goto	474
   373:	new	#116; //class scala/MatchError
   376:	dup
   377:	iload	4
   379:	invokestatic	#109; //Method scala/runtime/BoxesRunTime.boxToCharacter:(C)Ljava/lang/Character;
   382:	invokevirtual	#119; //Method java/lang/Object.toString:()Ljava/lang/String;
   385:	invokespecial	#120; //Method scala/MatchError."<init>":(Ljava/lang/String;)V
   388:	athrow
   389:	iconst_1
   390:	ifeq	401
   393:	aload_0
   394:	invokevirtual	#52; //Method next:()V
   397:	iconst_3
   398:	goto	474
   401:	new	#116; //class scala/MatchError
   404:	dup
   405:	iload	4
   407:	invokestatic	#109; //Method scala/runtime/BoxesRunTime.boxToCharacter:(C)Ljava/lang/Character;
   410:	invokevirtual	#119; //Method java/lang/Object.toString:()Ljava/lang/String;
   413:	invokespecial	#120; //Method scala/MatchError."<init>":(Ljava/lang/String;)V
   416:	athrow
   417:	iconst_1
   418:	ifeq	452
   421:	aload_0
   422:	invokevirtual	#52; //Method next:()V
   425:	getstatic	#130; //Field scala/Predef$.MODULE$:Lscala/Predef$;
   428:	ldc	#132; //String PCDATA
   430:	invokevirtual	#136; //Method scala/Predef$.wrapString:(Ljava/lang/String;)Lscala/collection/immutable/WrappedString;
   433:	astore_3
   434:	aload_3
   435:	new	#138; //class scala/xml/dtd/Scanner$$anonfun$accS$1
   438:	dup
   439:	aload_0
   440:	invokespecial	#141; //Method scala/xml/dtd/Scanner$$anonfun$accS$1."<init>":(Lscala/xml/dtd/Scanner;)V
   443:	invokeinterface	#147,  2; //InterfaceMethod scala/collection/IterableLike.foreach:(Lscala/Function1;)V
   448:	iconst_0
   449:	goto	474
   452:	new	#116; //class scala/MatchError
   455:	dup
   456:	iload	4
   458:	invokestatic	#109; //Method scala/runtime/BoxesRunTime.boxToCharacter:(C)Ljava/lang/Character;
   461:	invokevirtual	#119; //Method java/lang/Object.toString:()Ljava/lang/String;
   464:	invokespecial	#120; //Method scala/MatchError."<init>":(Ljava/lang/String;)V
   467:	athrow
   468:	iconst_1
   469:	ifeq	475
   472:	ldc	#28; //int 10
   474:	ireturn
   475:	new	#116; //class scala/MatchError
   478:	dup
   479:	iload	4
   481:	invokestatic	#109; //Method scala/runtime/BoxesRunTime.boxToCharacter:(C)Ljava/lang/Character;
   484:	invokevirtual	#119; //Method java/lang/Object.toString:()Ljava/lang/String;
   487:	invokespecial	#120; //Method scala/MatchError."<init>":(Ljava/lang/String;)V
   490:	athrow
  LineNumberTable: 
   line 58: 0
   line 59: 13
   line 60: 45
   line 61: 50
   line 21: 140
   line 72: 144
   line 73: 164
   line 61: 201
   line 21: 217
   line 68: 221
   line 61: 230
   line 21: 246
   line 67: 250
   line 61: 259
   line 21: 275
   line 64: 279
   line 61: 287
   line 21: 303
   line 66: 307
   line 61: 316
   line 21: 332
   line 65: 336
   line 61: 345
   line 21: 361
   line 63: 365
   line 61: 373
   line 21: 389
   line 62: 393
   line 61: 401
   line 21: 417
   line 69: 421
   line 61: 452
   line 21: 468
   line 70: 472
   line 58: 474
   line 61: 475

  LocalVariableTable: 
   Start  Length  Slot  Name   Signature
   0      491      0    this       Lscala/xml/dtd/Scanner;
   56      418      4    temp1       C
   475      16      4    temp1       C


public final void accS(scala.collection.Seq);
  Code:
   Stack=4, Locals=2, Args_size=2
   0:	aload_1
   1:	new	#138; //class scala/xml/dtd/Scanner$$anonfun$accS$1
   4:	dup
   5:	aload_0
   6:	invokespecial	#141; //Method scala/xml/dtd/Scanner$$anonfun$accS$1."<init>":(Lscala/xml/dtd/Scanner;)V
   9:	invokeinterface	#147,  2; //InterfaceMethod scala/collection/IterableLike.foreach:(Lscala/Function1;)V
   14:	return
  LineNumberTable: 
   line 55: 0

  LocalVariableTable: 
   Start  Length  Slot  Name   Signature
   0      15      0    this       Lscala/xml/dtd/Scanner;
   0      15      1    ds       Lscala/collection/Seq;

  Signature: length = 0x2
   00 FFFFFF99 

public final void acc(char);
  Code:
   Stack=3, Locals=4, Args_size=2
   0:	aload_0
   1:	invokespecial	#45; //Method c:()C
   4:	iload_1
   5:	if_icmpne	13
   8:	aload_0
   9:	invokevirtual	#52; //Method next:()V
   12:	return
   13:	new	#41; //class scala/collection/mutable/StringBuilder
   16:	dup
   17:	invokespecial	#100; //Method scala/collection/mutable/StringBuilder."<init>":()V
   20:	ldc	#156; //String expected '
   22:	invokevirtual	#105; //Method scala/collection/mutable/StringBuilder.append:(Ljava/lang/Object;)Lscala/collection/mutable/StringBuilder;
   25:	iload_1
   26:	invokestatic	#109; //Method scala/runtime/BoxesRunTime.boxToCharacter:(C)Ljava/lang/Character;
   29:	invokevirtual	#105; //Method scala/collection/mutable/StringBuilder.append:(Ljava/lang/Object;)Lscala/collection/mutable/StringBuilder;
   32:	ldc	#158; //String ' found '
   34:	invokevirtual	#105; //Method scala/collection/mutable/StringBuilder.append:(Ljava/lang/Object;)Lscala/collection/mutable/StringBuilder;
   37:	aload_0
   38:	invokespecial	#45; //Method c:()C
   41:	istore_2
   42:	iload_2
   43:	invokestatic	#109; //Method scala/runtime/BoxesRunTime.boxToCharacter:(C)Ljava/lang/Character;
   46:	invokevirtual	#105; //Method scala/collection/mutable/StringBuilder.append:(Ljava/lang/Object;)Lscala/collection/mutable/StringBuilder;
   49:	ldc	#160; //String ' !
   51:	invokevirtual	#105; //Method scala/collection/mutable/StringBuilder.append:(Ljava/lang/Object;)Lscala/collection/mutable/StringBuilder;
   54:	invokevirtual	#110; //Method scala/collection/mutable/StringBuilder.toString:()Ljava/lang/String;
   57:	astore_3
   58:	new	#112; //class java/lang/RuntimeException
   61:	dup
   62:	aload_3
   63:	invokespecial	#114; //Method java/lang/RuntimeException."<init>":(Ljava/lang/String;)V
   66:	athrow
  LineNumberTable: 
   line 52: 0

  LocalVariableTable: 
   Start  Length  Slot  Name   Signature
   0      67      0    this       Lscala/xml/dtd/Scanner;
   0      67      1    d       C


public final void next();
  Code:
   Stack=2, Locals=1, Args_size=1
   0:	aload_0
   1:	invokespecial	#78; //Method it:()Lscala/collection/Iterator;
   4:	invokeinterface	#165,  1; //InterfaceMethod scala/collection/Iterator.hasNext:()Z
   9:	ifeq	31
   12:	aload_0
   13:	aload_0
   14:	invokespecial	#78; //Method it:()Lscala/collection/Iterator;
   17:	invokeinterface	#83,  1; //InterfaceMethod scala/collection/Iterator.next:()Ljava/lang/Object;
   22:	invokestatic	#89; //Method scala/runtime/BoxesRunTime.unboxToChar:(Ljava/lang/Object;)C
   25:	invokespecial	#93; //Method c_$eq:(C)V
   28:	goto	36
   31:	aload_0
   32:	iconst_0
   33:	invokespecial	#93; //Method c_$eq:(C)V
   36:	return
  LineNumberTable: 
   line 49: 0


public final boolean isIdentChar();
  Code:
   Stack=2, Locals=1, Args_size=1
   0:	ldc	#167; //int 97
   2:	aload_0
   3:	invokespecial	#45; //Method c:()C
   6:	if_icmpgt	18
   9:	aload_0
   10:	invokespecial	#45; //Method c:()C
   13:	ldc	#35; //int 122
   15:	if_icmple	36
   18:	ldc	#168; //int 65
   20:	aload_0
   21:	invokespecial	#45; //Method c:()C
   24:	if_icmpgt	40
   27:	aload_0
   28:	invokespecial	#45; //Method c:()C
   31:	ldc	#169; //int 90
   33:	if_icmpgt	40
   36:	iconst_1
   37:	goto	41
   40:	iconst_0
   41:	ireturn
  LineNumberTable: 
   line 46: 0
   line 47: 18


public final void nextToken();
  Code:
   Stack=2, Locals=1, Args_size=1
   0:	aload_0
   1:	invokevirtual	#172; //Method token:()I
   4:	ldc	#28; //int 10
   6:	if_icmpeq	17
   9:	aload_0
   10:	aload_0
   11:	invokevirtual	#174; //Method readToken:()I
   14:	invokevirtual	#178; //Method token_$eq:(I)V
   17:	return
  LineNumberTable: 
   line 42: 0


public final void initScanner(java.lang.String);
  Code:
   Stack=3, Locals=2, Args_size=2
   0:	aload_0
   1:	ldc	#181; //String 
   3:	invokevirtual	#66; //Method value_$eq:(Ljava/lang/String;)V
   6:	aload_0
   7:	getstatic	#130; //Field scala/Predef$.MODULE$:Lscala/Predef$;
   10:	aload_1
   11:	invokevirtual	#185; //Method scala/Predef$.augmentString:(Ljava/lang/String;)Lscala/collection/immutable/StringOps;
   14:	invokeinterface	#190,  1; //InterfaceMethod scala/collection/IndexedSeqLike.iterator:()Lscala/collection/Iterator;
   19:	invokespecial	#194; //Method it_$eq:(Lscala/collection/Iterator;)V
   22:	aload_0
   23:	ldc	#195; //int 11
   25:	invokevirtual	#178; //Method token_$eq:(I)V
   28:	aload_0
   29:	invokevirtual	#52; //Method next:()V
   32:	aload_0
   33:	invokevirtual	#197; //Method nextToken:()V
   36:	return
  LineNumberTable: 
   line 33: 0
   line 34: 6
   line 35: 22
   line 36: 28
   line 37: 32

  LocalVariableTable: 
   Start  Length  Slot  Name   Signature
   0      37      0    this       Lscala/xml/dtd/Scanner;
   0      37      1    s       Ljava/lang/String;


public void value_$eq(java.lang.String);
  Code:
   Stack=2, Locals=2, Args_size=2
   0:	aload_0
   1:	aload_1
   2:	putfield	#202; //Field value:Ljava/lang/String;
   5:	return
  LineNumberTable: 
   line 26: 0


public java.lang.String value();
  Code:
   Stack=1, Locals=1, Args_size=1
   0:	aload_0
   1:	getfield	#202; //Field value:Ljava/lang/String;
   4:	areturn
  LineNumberTable: 
   line 26: 0


public void token_$eq(int);
  Code:
   Stack=2, Locals=2, Args_size=2
   0:	aload_0
   1:	iload_1
   2:	putfield	#32; //Field token:I
   5:	return
  LineNumberTable: 
   line 25: 0


public int token();
  Code:
   Stack=1, Locals=1, Args_size=1
   0:	aload_0
   1:	getfield	#32; //Field token:I
   4:	ireturn
  LineNumberTable: 
   line 25: 0


public final char ENDCH();
  Code:
   Stack=1, Locals=1, Args_size=1
   0:	iconst_0
   1:	ireturn
  LineNumberTable: 
   line 23: 0


public boolean checkPubID(java.lang.String);
  Code:
   Stack=2, Locals=2, Args_size=2
   0:	aload_0
   1:	aload_1
   2:	invokestatic	#207; //Method scala/xml/parsing/TokenTests$class.checkPubID:(Lscala/xml/parsing/TokenTests;Ljava/lang/String;)Z
   5:	ireturn
  LineNumberTable: 
   line 21: 0

  LocalVariableTable: 
   Start  Length  Slot  Name   Signature
   0      6      0    this       Lscala/xml/dtd/Scanner;
   0      6      1    s       Ljava/lang/String;


public boolean checkSysID(java.lang.String);
  Code:
   Stack=2, Locals=2, Args_size=2
   0:	aload_0
   1:	aload_1
   2:	invokestatic	#210; //Method scala/xml/parsing/TokenTests$class.checkSysID:(Lscala/xml/parsing/TokenTests;Ljava/lang/String;)Z
   5:	ireturn
  LineNumberTable: 
   line 21: 0

  LocalVariableTable: 
   Start  Length  Slot  Name   Signature
   0      6      0    this       Lscala/xml/dtd/Scanner;
   0      6      1    s       Ljava/lang/String;


public boolean isValidIANAEncoding(scala.collection.Seq);
  Code:
   Stack=2, Locals=2, Args_size=2
   0:	aload_0
   1:	aload_1
   2:	invokestatic	#215; //Method scala/xml/parsing/TokenTests$class.isValidIANAEncoding:(Lscala/xml/parsing/TokenTests;Lscala/collection/Seq;)Z
   5:	ireturn
  LineNumberTable: 
   line 21: 0

  LocalVariableTable: 
   Start  Length  Slot  Name   Signature
   0      6      0    this       Lscala/xml/dtd/Scanner;
   0      6      1    ianaEncoding       Lscala/collection/Seq;


public boolean isPubIDChar(char);
  Code:
   Stack=2, Locals=2, Args_size=2
   0:	aload_0
   1:	iload_1
   2:	invokestatic	#220; //Method scala/xml/parsing/TokenTests$class.isPubIDChar:(Lscala/xml/parsing/TokenTests;C)Z
   5:	ireturn
  LineNumberTable: 
   line 21: 0

  LocalVariableTable: 
   Start  Length  Slot  Name   Signature
   0      6      0    this       Lscala/xml/dtd/Scanner;
   0      6      1    ch       C


public boolean isName(java.lang.String);
  Code:
   Stack=2, Locals=2, Args_size=2
   0:	aload_0
   1:	aload_1
   2:	invokestatic	#224; //Method scala/xml/parsing/TokenTests$class.isName:(Lscala/xml/parsing/TokenTests;Ljava/lang/String;)Z
   5:	ireturn
  LineNumberTable: 
   line 21: 0

  LocalVariableTable: 
   Start  Length  Slot  Name   Signature
   0      6      0    this       Lscala/xml/dtd/Scanner;
   0      6      1    s       Ljava/lang/String;


public boolean isNameStart(char);
  Code:
   Stack=2, Locals=2, Args_size=2
   0:	aload_0
   1:	iload_1
   2:	invokestatic	#226; //Method scala/xml/parsing/TokenTests$class.isNameStart:(Lscala/xml/parsing/TokenTests;C)Z
   5:	ireturn
  LineNumberTable: 
   line 21: 0

  LocalVariableTable: 
   Start  Length  Slot  Name   Signature
   0      6      0    this       Lscala/xml/dtd/Scanner;
   0      6      1    ch       C


public boolean isNameChar(char);
  Code:
   Stack=2, Locals=2, Args_size=2
   0:	aload_0
   1:	iload_1
   2:	invokestatic	#228; //Method scala/xml/parsing/TokenTests$class.isNameChar:(Lscala/xml/parsing/TokenTests;C)Z
   5:	ireturn
  LineNumberTable: 
   line 21: 0

  LocalVariableTable: 
   Start  Length  Slot  Name   Signature
   0      6      0    this       Lscala/xml/dtd/Scanner;
   0      6      1    ch       C


public boolean isAlphaDigit(char);
  Code:
   Stack=2, Locals=2, Args_size=2
   0:	aload_0
   1:	iload_1
   2:	invokestatic	#231; //Method scala/xml/parsing/TokenTests$class.isAlphaDigit:(Lscala/xml/parsing/TokenTests;C)Z
   5:	ireturn
  LineNumberTable: 
   line 21: 0

  LocalVariableTable: 
   Start  Length  Slot  Name   Signature
   0      6      0    this       Lscala/xml/dtd/Scanner;
   0      6      1    c       C


public boolean isAlpha(char);
  Code:
   Stack=2, Locals=2, Args_size=2
   0:	aload_0
   1:	iload_1
   2:	invokestatic	#234; //Method scala/xml/parsing/TokenTests$class.isAlpha:(Lscala/xml/parsing/TokenTests;C)Z
   5:	ireturn
  LineNumberTable: 
   line 21: 0

  LocalVariableTable: 
   Start  Length  Slot  Name   Signature
   0      6      0    this       Lscala/xml/dtd/Scanner;
   0      6      1    c       C


public final boolean isSpace(scala.collection.Seq);
  Code:
   Stack=2, Locals=2, Args_size=2
   0:	aload_0
   1:	aload_1
   2:	invokestatic	#236; //Method scala/xml/parsing/TokenTests$class.isSpace:(Lscala/xml/parsing/TokenTests;Lscala/collection/Seq;)Z
   5:	ireturn
  LineNumberTable: 
   line 21: 0

  LocalVariableTable: 
   Start  Length  Slot  Name   Signature
   0      6      0    this       Lscala/xml/dtd/Scanner;
   0      6      1    cs       Lscala/collection/Seq;


public final boolean isSpace(char);
  Code:
   Stack=2, Locals=2, Args_size=2
   0:	aload_0
   1:	iload_1
   2:	invokestatic	#239; //Method scala/xml/parsing/TokenTests$class.isSpace:(Lscala/xml/parsing/TokenTests;C)Z
   5:	ireturn
  LineNumberTable: 
   line 21: 0

  LocalVariableTable: 
   Start  Length  Slot  Name   Signature
   0      6      0    this       Lscala/xml/dtd/Scanner;
   0      6      1    ch       C


}

