Compiled from "ExternalID.scala"
public class scala.xml.dtd.SystemID extends scala.xml.dtd.ExternalID implements scala.ScalaObject,scala.Product,java.io.Serializable
  SourceFile: "ExternalID.scala"
  ScalaSig: length = 0x35F
   05 00 FFFFFF81 02 06 08 01 02 FFFFFF84 FFFFFF80 FFFFFF80 FFFFFF80 40 09 02 08
   53 79 73 74 65 6D 49 44 0A 02 03 04 01 03 64 74
   64 0A 02 05 06 01 03 78 6D 6C 0A 01 07 01 05 73
   63 61 6C 61 03 00 13 04 00 0A 0E 12 10 02 0B 0C
   0D 01 02 09 02 0D 02 02 0A 45 78 74 65 72 6E 61
   6C 49 44 10 02 0F 10 0D 01 06 09 02 11 06 02 0B
   53 63 61 6C 61 4F 62 6A 65 63 74 10 02 0F 13 09
   02 14 06 02 07 50 72 6F 64 75 63 74 08 08 16 00
   FFFFFF82 FFFFFFCA FFFFFF80 FFFFFF84 00 17 01 08 73 79 73 74 65 6D 49 64
   15 01 18 10 02 19 1C 0E 02 0F 1A 09 02 1B 06 01
   06 50 72 65 64 65 66 09 02 1D 1E 02 06 53 74 72
   69 6E 67 0A 02 1B 06 08 08 20 00 FFFFFF82 FFFFFF88 FFFFFFA0 FFFFFF80 04
   18 01 09 73 79 73 74 65 6D 49 64 20 08 05 22 00
   FFFFFF84 00 23 01 06 3C 69 6E 69 74 3E 14 02 24 25 10
   02 0B 00 08 05 16 21 FFFFFFC0 00 18 08 07 27 00 FFFFFFC2 FFFFFF80
   FFFFFF84 00 28 01 08 70 75 62 6C 69 63 49 64 15 01 29
   10 02 0F 2A 09 02 2B 06 02 04 4E 75 6C 6C 08 06
   2D 00 FFFFFFA0 FFFFFF80 04 29 01 09 70 75 62 6C 69 63 49 64
   20 08 07 2F 00 FFFFFF81 FFFFFF80 FFFFFF84 00 30 01 04 63 6F 70 79
   14 02 24 31 08 08 32 16 2E FFFFFF90 FFFFFF80 FFFFFFC0 00 18 08 07
   33 00 FFFFFF91 FFFFFF80 FFFFFF84 00 34 01 0E 63 6F 70 79 24 64 65
   66 61 75 6C 74 24 31 15 01 35 2A 02 18 36 2B 01
   37 10 02 38 3D 0D 01 39 0A 02 3A 3B 01 09 75 6E
   63 68 65 63 6B 65 64 0A 02 3C 06 01 0A 61 6E 6E
   6F 74 61 74 69 6F 6E 09 02 3E 39 02 11 75 6E 63
   68 65 63 6B 65 64 56 61 72 69 61 6E 63 65 08 08
   40 00 FFFFFF84 FFFFFF80 FFFFFF80 FFFFFF84 20 41 01 08 68 61 73 68 43 6F
   64 65 14 01 42 10 02 0F 43 09 02 44 06 02 03 49
   6E 74 08 08 46 00 FFFFFF84 FFFFFF80 FFFFFF80 FFFFFF84 20 47 01 06 65 71
   75 61 6C 73 14 02 48 4B 10 02 0F 49 09 02 4A 06
   02 07 42 6F 6F 6C 65 61 6E 08 07 4C 45 FFFFFF81 FFFFFF80 FFFFFFC0
   00 4D 01 03 78 24 31 10 02 0F 4E 09 02 4F 06 02
   03 41 6E 79 08 08 51 00 FFFFFF84 FFFFFF80 FFFFFF80 FFFFFF84 20 52 01 0D
   70 72 6F 64 75 63 74 50 72 65 66 69 78 15 01 53
   10 02 54 59 0D 01 55 0A 02 56 57 01 04 6C 61 6E
   67 0A 01 58 01 04 6A 61 76 61 09 02 1D 55 08 08
   5B 00 FFFFFF84 FFFFFF80 FFFFFF80 FFFFFF84 20 5C 01 0C 70 72 6F 64 75 63
   74 41 72 69 74 79 15 01 42 08 08 5E 00 FFFFFF84 FFFFFF80 FFFFFF80
   FFFFFF84 20 5F 01 0E 70 72 6F 64 75 63 74 45 6C 65 6D
   65 6E 74 14 02 4D 60 08 07 4C 5D FFFFFF81 FFFFFF80 FFFFFFC0 00 42
   08 08 62 00 FFFFFF84 FFFFFF80 FFFFFF80 FFFFFF84 20 63 01 08 63 61 6E 45
   71 75 61 6C 14 02 48 64 08 07 4C 61 FFFFFF81 FFFFFF80 FFFFFFC0 00
   4D 28 02 00 66 10 02 0F 67 09 02 68 06 02 0C 73
   65 72 69 61 6C 69 7A 61 62 6C 65 07 07 6A 02 FFFFFF81
   FFFFFF80 FFFFFF88 02 6B 01 08 53 79 73 74 65 6D 49 44 10 02
   0B 6C 06 08 01 02 FFFFFF84 FFFFFF81 FFFFFF80 FFFFFF88 02 6D 13 04 6C 6E
   71 0E 10 02 54 6F 09 02 70 55 02 06 4F 62 6A 65
   63 74 10 04 0F 72 18 24 09 02 73 06 02 09 46 75
   6E 63 74 69 6F 6E 31 08 05 22 6C FFFFFF84 00 75 14 01
   6B 08 07 77 6C FFFFFF81 FFFFFF80 FFFFFF84 40 78 01 05 61 70 70 6C
   79 14 02 24 79 08 05 16 76 FFFFFFC0 00 18 08 07 7B 6C
   FFFFFF81 FFFFFF80 FFFFFF84 40 7C 01 07 75 6E 61 70 70 6C 79 14 03
   7D FFFFFF81 00 10 03 0F 7E 18 09 02 7F 06 02 04 53 6F
   6D 65 08 06 FFFFFF81 01 7A FFFFFFC0 00 24 01 03 78 24 30 
  minor version: 0
  major version: 49
  Constant pool:
Asciz	SourceFile;
Asciz	ExternalID.scala;
Asciz	andThen;
Asciz	(Lscala/Function1;)Lscala/Function1;;
Asciz	Code;
Asciz	scala/xml/dtd/SystemID$;
class	scala/xml/dtd/SystemID$
Asciz	MODULE$;
Asciz	Lscala/xml/dtd/SystemID$;;
NameAndType	MODULE$:Lscala/xml/dtd/SystemID$;
Field	scala/xml/dtd/SystemID$.MODULE$:Lscala/xml/dtd/SystemID$;
NameAndType	andThen:(Lscala/Function1;)Lscala/Function1;
Method	scala/xml/dtd/SystemID$.andThen:(Lscala/Function1;)Lscala/Function1;
Asciz	compose;
NameAndType	compose:(Lscala/Function1;)Lscala/Function1;
Method	scala/xml/dtd/SystemID$.compose:(Lscala/Function1;)Lscala/Function1;
Asciz	publicId;
Asciz	Lscala/runtime/Null$;;
Asciz	systemId;
Asciz	Ljava/lang/String;;
Asciz	<init>;
Asciz	(Ljava/lang/String;)V;
Asciz	LineNumberTable;
Asciz	scala/xml/dtd/SystemID;
class	scala/xml/dtd/SystemID
NameAndType	systemId:Ljava/lang/String;
Field	scala/xml/dtd/SystemID.systemId:Ljava/lang/String;
Asciz	scala/xml/dtd/ExternalID;
class	scala/xml/dtd/ExternalID
Asciz	()V;
NameAndType	"<init>":()V
Method	scala/xml/dtd/ExternalID."<init>":()V
Asciz	scala/Product$class;
class	scala/Product$class
Asciz	$init$;
Asciz	(Lscala/Product;)V;
NameAndType	$init$:(Lscala/Product;)V
Method	scala/Product$class.$init$:(Lscala/Product;)V
NameAndType	publicId:Lscala/runtime/Null$;
Field	scala/xml/dtd/SystemID.publicId:Lscala/runtime/Null$;
Asciz	scala/xml/parsing/TokenTests;
class	scala/xml/parsing/TokenTests
Asciz	checkSysID;
Asciz	(Ljava/lang/String;)Z;
NameAndType	checkSysID:(Ljava/lang/String;)Z
InterfaceMethod	scala/xml/parsing/TokenTests.checkSysID:(Ljava/lang/String;)Z
Asciz	java/lang/IllegalArgumentException;
class	java/lang/IllegalArgumentException
Asciz	can't use both \" and ' in systemId;
String	can't use both \" and ' in systemId
NameAndType	"<init>":(Ljava/lang/String;)V
Method	java/lang/IllegalArgumentException."<init>":(Ljava/lang/String;)V
Asciz	this;
Asciz	Lscala/xml/dtd/SystemID;;
Asciz	LocalVariableTable;
Asciz	gd1$1;
Asciz	()Ljava/lang/String;;
NameAndType	systemId:()Ljava/lang/String;
Method	scala/xml/dtd/SystemID.systemId:()Ljava/lang/String;
Asciz	java/lang/Object;
class	java/lang/Object
Asciz	equals;
Asciz	(Ljava/lang/Object;)Z;
NameAndType	equals:(Ljava/lang/Object;)Z
Method	java/lang/Object.equals:(Ljava/lang/Object;)Z
Asciz	canEqual;
Asciz	productElement;
Asciz	(I)Ljava/lang/Object;;
Asciz	java/lang/IndexOutOfBoundsException;
class	java/lang/IndexOutOfBoundsException
Asciz	scala/runtime/BoxesRunTime;
class	scala/runtime/BoxesRunTime
Asciz	boxToInteger;
Asciz	(I)Ljava/lang/Integer;;
NameAndType	boxToInteger:(I)Ljava/lang/Integer;
Method	scala/runtime/BoxesRunTime.boxToInteger:(I)Ljava/lang/Integer;
Asciz	toString;
NameAndType	toString:()Ljava/lang/String;
Method	java/lang/Object.toString:()Ljava/lang/String;
Method	java/lang/IndexOutOfBoundsException."<init>":(Ljava/lang/String;)V
Asciz	productArity;
Asciz	()I;
Asciz	productPrefix;
Asciz	SystemID;
String	SystemID
NameAndType	gd1$1:(Ljava/lang/String;)Z
Method	scala/xml/dtd/SystemID.gd1$1:(Ljava/lang/String;)Z
Asciz	scala/Equals;
class	scala/Equals
NameAndType	canEqual:(Ljava/lang/Object;)Z
InterfaceMethod	scala/Equals.canEqual:(Ljava/lang/Object;)Z
Asciz	temp2;
Asciz	temp3;
Asciz	hashCode;
Asciz	scala/runtime/ScalaRunTime$;
class	scala/runtime/ScalaRunTime$
Asciz	Lscala/runtime/ScalaRunTime$;;
NameAndType	MODULE$:Lscala/runtime/ScalaRunTime$;
Field	scala/runtime/ScalaRunTime$.MODULE$:Lscala/runtime/ScalaRunTime$;
Asciz	_hashCode;
Asciz	(Lscala/Product;)I;
NameAndType	_hashCode:(Lscala/Product;)I
Method	scala/runtime/ScalaRunTime$._hashCode:(Lscala/Product;)I
Asciz	copy;
Asciz	(Ljava/lang/String;)Lscala/xml/dtd/SystemID;;
Method	scala/xml/dtd/SystemID."<init>":(Ljava/lang/String;)V
Asciz	()Lscala/runtime/Null$;;
Asciz	copy$default$1;
Asciz	productElements;
Asciz	()Lscala/collection/Iterator;;
Asciz	(Lscala/Product;)Lscala/collection/Iterator;;
NameAndType	productElements:(Lscala/Product;)Lscala/collection/Iterator;
Method	scala/Product$class.productElements:(Lscala/Product;)Lscala/collection/Iterator;
Asciz	Deprecated;
Asciz	productIterator;
NameAndType	productIterator:(Lscala/Product;)Lscala/collection/Iterator;
Method	scala/Product$class.productIterator:(Lscala/Product;)Lscala/collection/Iterator;
Asciz	ScalaSig;
Asciz	scala/ScalaObject;
class	scala/ScalaObject
Asciz	scala/Product;
class	scala/Product
Asciz	java/io/Serializable;
class	java/io/Serializable

{
private final scala.runtime.Null$ publicId;
  Signature: Lscala/runtime/Null$;

private final java.lang.String systemId;
  Signature: Ljava/lang/String;

public static final scala.Function1 andThen(scala.Function1);
  Signature: (Lscala/Function1;)Lscala/Function1;
  Code:
   Stack=2, Locals=1, Args_size=1
	getstatic	Field scala/xml/dtd/SystemID$.MODULE$:Lscala/xml/dtd/SystemID$;
	aload_0
	invokevirtual	Method scala/xml/dtd/SystemID$.andThen:(Lscala/Function1;)Lscala/Function1;
	areturn
  Labels:

public static final scala.Function1 compose(scala.Function1);
  Signature: (Lscala/Function1;)Lscala/Function1;
  Code:
   Stack=2, Locals=1, Args_size=1
	getstatic	Field scala/xml/dtd/SystemID$.MODULE$:Lscala/xml/dtd/SystemID$;
	aload_0
	invokevirtual	Method scala/xml/dtd/SystemID$.compose:(Lscala/Function1;)Lscala/Function1;
	areturn
  Labels:

public scala.xml.dtd.SystemID(java.lang.String);
  Signature: (Ljava/lang/String;)V
  Code:
   Stack=3, Locals=2, Args_size=2
	aload_0
	aload_1
	putfield	Field systemId:Ljava/lang/String;
	aload_0
	invokespecial	Method scala/xml/dtd/ExternalID."<init>":()V
	aload_0
	invokestatic	Method scala/Product$class.$init$:(Lscala/Product;)V
	aload_0
	aconst_null
	putfield	Field publicId:Lscala/runtime/Null$;
	aload_0
	aload_1
	invokeinterface	InterfaceMethod scala/xml/parsing/TokenTests.checkSysID:(Ljava/lang/String;)Z
	ifeq	l1 // new
	return
l1	new	class java/lang/IllegalArgumentException
	dup
	ldc	String can't use both \" and ' in systemId
	invokespecial	Method java/lang/IllegalArgumentException."<init>":(Ljava/lang/String;)V
	athrow
  Labels:
   	l1 = 29 // new
  LocalVariableTable: 
   Start  Length  Slot  Name   Signature
   0      39      0    this       Lscala/xml/dtd/SystemID;
   0      39      1    systemId       Ljava/lang/String;


private final boolean gd1$1(java.lang.String);
  Signature: (Ljava/lang/String;)Z
  Code:
   Stack=2, Locals=3, Args_size=2
	aload_1
	aload_0
	invokevirtual	Method systemId:()Ljava/lang/String;
	astore_2
	dup
	ifnonnull	l1 // aload_2
	pop
	aload_2
	ifnull	l2 // iconst_1
	goto	l3 // iconst_0
l1	aload_2
	invokevirtual	Method java/lang/Object.equals:(Ljava/lang/Object;)Z
	ifeq	l3 // iconst_0
l2	iconst_1
	goto	l4 // ireturn
l3	iconst_0
l4	ireturn
  Labels:
   	l1 = 18 // aload_2
   	l2 = 25 // iconst_1
   	l3 = 29 // iconst_0
   	l4 = 30 // ireturn

public java.lang.String publicId();
  Signature: ()Ljava/lang/String;
  Code:
   Stack=1, Locals=1, Args_size=1
	aconst_null
	areturn
  Labels:

public boolean canEqual(java.lang.Object);
  Signature: (Ljava/lang/Object;)Z
  Code:
   Stack=1, Locals=2, Args_size=2
	aload_1
	instanceof	class scala/xml/dtd/SystemID
	ireturn
  Labels:

public java.lang.Object productElement(int);
  Signature: (I)Ljava/lang/Object;
  Code:
   Stack=3, Locals=2, Args_size=2
	iload_1
	iconst_0
	if_icmpne	l1 // new
	aload_0
	invokevirtual	Method systemId:()Ljava/lang/String;
	areturn
l1	new	class java/lang/IndexOutOfBoundsException
	dup
	iload_1
	invokestatic	Method scala/runtime/BoxesRunTime.boxToInteger:(I)Ljava/lang/Integer;
	invokevirtual	Method java/lang/Object.toString:()Ljava/lang/String;
	invokespecial	Method java/lang/IndexOutOfBoundsException."<init>":(Ljava/lang/String;)V
	athrow
  Labels:
   	l1 = 10 // new

public int productArity();
  Signature: ()I
  Code:
   Stack=1, Locals=1, Args_size=1
	iconst_1
	ireturn
  Labels:

public java.lang.String productPrefix();
  Signature: ()Ljava/lang/String;
  Code:
   Stack=1, Locals=1, Args_size=1
	ldc	String SystemID
	areturn
  Labels:

public boolean equals(java.lang.Object);
  Signature: (Ljava/lang/Object;)Z
  Code:
   Stack=2, Locals=4, Args_size=2
	aload_0
	aload_1
	if_acmpeq	l1 // iconst_1
	aload_1
	instanceof	class scala/xml/dtd/SystemID
	ifeq	l2 // iconst_0
	aload_1
	checkcast	class scala/xml/dtd/SystemID
	astore_2
	aload_2
	invokevirtual	Method systemId:()Ljava/lang/String;
	astore_3
	aload_0
	aload_3
	invokespecial	Method gd1$1:(Ljava/lang/String;)Z
	ifeq	l3 // iconst_0
	aload_1
	checkcast	class scala/xml/dtd/SystemID
	aload_0
	invokeinterface	InterfaceMethod scala/Equals.canEqual:(Ljava/lang/Object;)Z
	goto	l4 // ifeq
l3	iconst_0
	goto	l4 // ifeq
l2	iconst_0
l4	ifeq	l5 // iconst_0
l1	iconst_1
	goto	l6 // ireturn
l5	iconst_0
l6	ireturn
  Labels:
   	l3 = 43 // iconst_0
   	l2 = 47 // iconst_0
   	l4 = 48 // ifeq
   	l1 = 51 // iconst_1
   	l5 = 55 // iconst_0
   	l6 = 56 // ireturn
  LocalVariableTable: 
   Start  Length  Slot  Name   Signature
   0      57      0    this       Lscala/xml/dtd/SystemID;
   17      30      2    temp2       Lscala/xml/dtd/SystemID;
   22      25      3    temp3       Ljava/lang/String;


public int hashCode();
  Signature: ()I
  Code:
   Stack=2, Locals=1, Args_size=1
	getstatic	Field scala/runtime/ScalaRunTime$.MODULE$:Lscala/runtime/ScalaRunTime$;
	aload_0
	invokevirtual	Method scala/runtime/ScalaRunTime$._hashCode:(Lscala/Product;)I
	ireturn
  Labels:

public scala.xml.dtd.SystemID copy(java.lang.String);
  Signature: (Ljava/lang/String;)Lscala/xml/dtd/SystemID;
  Code:
   Stack=3, Locals=2, Args_size=2
	new	class scala/xml/dtd/SystemID
	dup
	aload_1
	invokespecial	Method "<init>":(Ljava/lang/String;)V
	areturn
  Labels:
  LocalVariableTable: 
   Start  Length  Slot  Name   Signature
   0      9      0    this       Lscala/xml/dtd/SystemID;
   0      9      1    systemId       Ljava/lang/String;


public scala.runtime.Null$ publicId();
  Signature: ()Lscala/runtime/Null$;
  Code:
   Stack=1, Locals=1, Args_size=1
	aload_0
	getfield	Field publicId:Lscala/runtime/Null$;
	areturn
  Labels:

public java.lang.String systemId();
  Signature: ()Ljava/lang/String;
  Code:
   Stack=1, Locals=1, Args_size=1
	aload_0
	getfield	Field systemId:Ljava/lang/String;
	areturn
  Labels:

public java.lang.String copy$default$1();
  Signature: ()Ljava/lang/String;
  Code:
   Stack=1, Locals=1, Args_size=1
	aload_0
	invokevirtual	Method systemId:()Ljava/lang/String;
	areturn
  Labels:

public scala.collection.Iterator productElements();
  Signature: ()Lscala/collection/Iterator;
  Code:
   Stack=1, Locals=1, Args_size=1
	aload_0
	invokestatic	Method scala/Product$class.productElements:(Lscala/Product;)Lscala/collection/Iterator;
	areturn
  Labels:
  Deprecated: true

public scala.collection.Iterator productIterator();
  Signature: ()Lscala/collection/Iterator;
  Code:
   Stack=1, Locals=1, Args_size=1
	aload_0
	invokestatic	Method scala/Product$class.productIterator:(Lscala/Product;)Lscala/collection/Iterator;
	areturn
  Labels:

}

